{
  "type": "Feature",
  "properties": {
    "gn:admin1_code":"5",
    "gn:admin2_code":"77.0",
    "gn:asciiname":"Los Luceros 2da. Seccion",
    "gn:country_code":"MX",
    "gn:dem":422,
    "gn:feature_class":"P",
    "gn:feature_code":"PPL",
    "gn:name":"Los Luceros 2da. Secci\u00f3n",
    "gn:population":644,
    "gn:timezone":"America/Mexico_City",
    "iso:country":"MX",
    "name:und_x_variant":[
        "Los Luceros 2da. Secci\u00f3n"
    ],
    "wof:name":"Los Luceros 2da. Seccion",
    "wof:placetype":"locality",
    "wof:population":644
},
  "geometry": {"coordinates":[-92.42306000000001,17.52889],"type":"Point"}
}