{
  "type": "Feature",
  "properties": {
    "gn:admin1_code":"30.0",
    "gn:admin2_code":"141.0",
    "gn:asciiname":"Xoteapan",
    "gn:country_code":"MX",
    "gn:dem":643,
    "gn:feature_class":"P",
    "gn:feature_code":"PPL",
    "gn:name":"Xoteapan",
    "gn:population":5,
    "gn:timezone":"America/Mexico_City",
    "iso:country":"MX",
    "name:spa_x_preferred":[
        "Xoteapan"
    ],
    "wof:name":"Xoteapan",
    "wof:placetype":"locality",
    "wof:population":5
},
  "geometry": {"coordinates":[-95.23111,18.52333],"type":"Point"}
}