{
  "type": "Feature",
  "properties": {
    "gn:admin1_code":"25",
    "gn:admin2_code":"3",
    "gn:asciiname":"La Amapa",
    "gn:country_code":"MX",
    "gn:dem":262,
    "gn:feature_class":"P",
    "gn:feature_code":"PPL",
    "gn:name":"La Amapa",
    "gn:population":15,
    "gn:timezone":"America/Mazatlan",
    "iso:country":"MX",
    "wof:name":"La Amapa",
    "wof:placetype":"locality",
    "wof:population":15
},
  "geometry": {"coordinates":[-107.23195,25.29293],"type":"Point"}
}