{
  "type": "Feature",
  "properties": {
    "gn:admin1_code":"7",
    "gn:admin2_code":"10.0",
    "gn:asciiname":"Alberto Villa Arias",
    "gn:country_code":"MX",
    "gn:dem":535,
    "gn:feature_class":"P",
    "gn:feature_code":"PPL",
    "gn:name":"Alberto Villa Arias",
    "gn:population":4,
    "gn:timezone":"America/Monterrey",
    "iso:country":"MX",
    "wof:name":"Alberto Villa Arias",
    "wof:placetype":"locality",
    "wof:population":4
},
  "geometry": {"coordinates":[-101.49668,26.98932000000001],"type":"Point"}
}