{
  "type": "Feature",
  "properties": {
    "gn:admin1_code":"25.0",
    "gn:admin2_code":"6.0",
    "gn:asciiname":"Baila",
    "gn:cc2":"MX",
    "gn:country_code":"MX",
    "gn:dem":77,
    "gn:feature_class":"P",
    "gn:feature_code":"PPL",
    "gn:name":"Baila",
    "gn:population":499,
    "gn:timezone":"America/Mazatlan",
    "iso:country":"MX",
    "name:fra_x_preferred":[
        "Baila"
    ],
    "name:und_x_variant":[
        "Paila",
        "Bailna"
    ],
    "wof:name":"Baila",
    "wof:placetype":"locality",
    "wof:population":499
},
  "geometry": {"coordinates":[-106.97389,24.18306],"type":"Point"}
}