{
  "type": "Feature",
  "properties": {
    "gn:admin1_code":"32",
    "gn:admin2_code":"25",
    "gn:asciiname":"Colonia Lazaro Cardenas",
    "gn:country_code":"MX",
    "gn:dem":1975,
    "gn:feature_class":"P",
    "gn:feature_code":"PPL",
    "gn:name":"Colonia L\u00e1zaro C\u00e1rdenas",
    "gn:population":14,
    "gn:timezone":"America/Mexico_City",
    "iso:country":"MX",
    "name:und_x_variant":[
        "Colonia L\u00e1zaro C\u00e1rdenas"
    ],
    "wof:name":"Colonia Lazaro Cardenas",
    "wof:placetype":"locality",
    "wof:population":14
},
  "geometry": {"coordinates":[-102.24194,22.40944],"type":"Point"}
}