{
  "type": "Feature",
  "properties": {
    "gn:admin1_code":"30",
    "gn:admin2_code":"177.0",
    "gn:asciiname":"El Bordo",
    "gn:country_code":"MX",
    "gn:dem":2301,
    "gn:feature_class":"P",
    "gn:feature_code":"PPL",
    "gn:name":"El Bordo",
    "gn:population":232,
    "gn:timezone":"America/Mexico_City",
    "iso:country":"MX",
    "wof:name":"El Bordo",
    "wof:placetype":"locality",
    "wof:population":232
},
  "geometry": {"coordinates":[-97.02889,19.72833],"type":"Point"}
}