{
  "type": "Feature",
  "properties": {
    "gn:admin1_code":"30",
    "gn:admin2_code":"177.0",
    "gn:asciiname":"El Bordo",
    "gn:country_code":"MX",
    "gn:dem":2301,
    "gn:feature_class":"P",
    "gn:feature_code":"PPL",
    "gn:name":"El Bordo",
    "gn:population":232,
    "gn:timezone":"America/Mexico_City",
    "iso:country":"MX",
    "name:ceb_x_preferred":[
        "El Bordo"
    ],
    "name:spa_x_preferred":[
        "El Bordo"
    ],
    "name:srp_x_preferred":[
        "\u0415\u043b \u0411\u043e\u0440\u0434\u043e"
    ],
    "name:swe_x_preferred":[
        "El Bordo"
    ],
    "wof:name":"El Bordo",
    "wof:placetype":"locality",
    "wof:population":232
},
  "geometry": {"coordinates":[-97.02889,19.72833],"type":"Point"}
}