{
  "type": "Feature",
  "properties": {
    "gn:admin1_code":"3",
    "gn:admin2_code":"3.0",
    "gn:asciiname":"La Estrella del Norte",
    "gn:country_code":"MX",
    "gn:dem":458,
    "gn:feature_class":"P",
    "gn:feature_code":"PPL",
    "gn:name":"La Estrella del Norte",
    "gn:population":8,
    "gn:timezone":"America/Mazatlan",
    "iso:country":"MX",
    "wof:name":"La Estrella del Norte",
    "wof:placetype":"locality",
    "wof:population":8
},
  "geometry": {"coordinates":[-110.15401,23.8997],"type":"Point"}
}