{
  "type": "Feature",
  "properties": {
    "gn:admin1_code":"16",
    "gn:admin2_code":"10",
    "gn:asciiname":"La Escoba",
    "gn:country_code":"MX",
    "gn:dem":415,
    "gn:feature_class":"P",
    "gn:feature_code":"PPL",
    "gn:name":"La Escoba",
    "gn:population":11,
    "gn:timezone":"America/Mexico_City",
    "iso:country":"MX",
    "wof:name":"La Escoba",
    "wof:placetype":"locality",
    "wof:population":11
},
  "geometry": {"coordinates":[-102.16139,18.31361],"type":"Point"}
}