{
  "type": "Feature",
  "properties": {
    "gn:admin1_code":"16.0",
    "gn:admin2_code":"6.0",
    "gn:asciiname":"Las Tres Cruces",
    "gn:country_code":"MX",
    "gn:dem":241,
    "gn:feature_class":"P",
    "gn:feature_code":"PPL",
    "gn:name":"Las Tres Cruces",
    "gn:population":0,
    "gn:timezone":"America/Mexico_City",
    "iso:country":"MX",
    "name:spa_x_preferred":[
        "Las Tres Cruces"
    ],
    "wof:name":"Las Tres Cruces",
    "wof:placetype":"locality"
},
  "geometry": {"coordinates":[-102.50699,19.07736],"type":"Point"}
}