{
  "type": "Feature",
  "properties": {
    "gn:admin1_code":"7.0",
    "gn:admin2_code":"31.0",
    "gn:asciiname":"La Mota",
    "gn:country_code":"MX",
    "gn:dem":629,
    "gn:feature_class":"P",
    "gn:feature_code":"PPL",
    "gn:name":"La Mota",
    "gn:population":0,
    "gn:timezone":"America/Monterrey",
    "iso:country":"MX",
    "name:spa_x_preferred":[
        "La Mota"
    ],
    "wof:name":"La Mota",
    "wof:placetype":"locality"
},
  "geometry": {"coordinates":[-101.61839999999999,27.46837],"type":"Point"}
}