{
  "type": "Feature",
  "properties": {
    "gn:admin1_code":"25",
    "gn:admin2_code":"18.0",
    "gn:asciiname":"Plan de Ayala (El Zanjon)",
    "gn:country_code":"MX",
    "gn:dem":7,
    "gn:feature_class":"P",
    "gn:feature_code":"PPL",
    "gn:name":"Plan de Ayala (El Zanj\u00f3n)",
    "gn:population":305,
    "gn:timezone":"America/Mazatlan",
    "iso:country":"MX",
    "name:und_x_variant":[
        "Plan de Ayala (El Zanj\u00f3n)"
    ],
    "wof:name":"Plan de Ayala (El Zanjon)",
    "wof:placetype":"locality",
    "wof:population":305
},
  "geometry": {"coordinates":[-107.6575,24.64389],"type":"Point"}
}