{
  "type": "Feature",
  "properties": {
    "gn:admin1_code":"10",
    "gn:admin2_code":"31.0",
    "gn:asciiname":"Las Norias",
    "gn:country_code":"MX",
    "gn:dem":1825,
    "gn:feature_class":"P",
    "gn:feature_code":"PPL",
    "gn:name":"Las Norias",
    "gn:population":0,
    "gn:timezone":"America/Monterrey",
    "iso:country":"MX",
    "name:spa_x_preferred":[
        "Las Norias"
    ],
    "wof:name":"Las Norias",
    "wof:placetype":"locality"
},
  "geometry": {"coordinates":[-103.52358,24.53547],"type":"Point"}
}