{
  "type": "Feature",
  "properties": {
    "gn:admin1_code":"28.0",
    "gn:admin2_code":"8.0",
    "gn:asciiname":"Veintinueve de Enero",
    "gn:country_code":"MX",
    "gn:dem":366,
    "gn:feature_class":"P",
    "gn:feature_code":"PPL",
    "gn:name":"Veintinueve de Enero",
    "gn:population":1,
    "gn:timezone":"America/Monterrey",
    "iso:country":"MX",
    "name:spa_x_preferred":[
        "Veintinueve de Enero"
    ],
    "wof:name":"Veintinueve de Enero",
    "wof:placetype":"locality",
    "wof:population":1
},
  "geometry": {"coordinates":[-98.58,23.515],"type":"Point"}
}