{
  "type": "Feature",
  "properties": {
    "gn:admin1_code":"5",
    "gn:admin2_code":"32.0",
    "gn:asciiname":"Montagua",
    "gn:country_code":"MX",
    "gn:dem":976,
    "gn:feature_class":"P",
    "gn:feature_code":"PPL",
    "gn:name":"Montagua",
    "gn:population":89,
    "gn:timezone":"America/Mexico_City",
    "iso:country":"MX",
    "wof:name":"Montagua",
    "wof:placetype":"locality",
    "wof:population":89
},
  "geometry": {"coordinates":[-92.47111,15.26222],"type":"Point"}
}