{
  "type": "Feature",
  "properties": {
    "gn:admin1_code":"26.0",
    "gn:admin2_code":"18.0",
    "gn:asciiname":"Alvaro Obregon",
    "gn:country_code":"MX",
    "gn:dem":34,
    "gn:feature_class":"P",
    "gn:feature_code":"PPL",
    "gn:name":"\u00c1lvaro Obreg\u00f3n",
    "gn:population":0,
    "gn:timezone":"America/Hermosillo",
    "iso:country":"MX",
    "name:spa_x_preferred":[
        "\u00c1lvaro Obreg\u00f3n"
    ],
    "name:spa_x_variant":[
        "Alvaro Obreg\u00f3n"
    ],
    "wof:name":"Alvaro Obregon",
    "wof:placetype":"locality"
},
  "geometry": {"coordinates":[-109.9513,27.46291],"type":"Point"}
}