{
  "type": "Feature",
  "properties": {
    "gn:admin1_code":"6",
    "gn:admin2_code":"40.0",
    "gn:asciiname":"Campo el Dos (Dos de Arriba)",
    "gn:country_code":"MX",
    "gn:dem":2264,
    "gn:feature_class":"P",
    "gn:feature_code":"PPL",
    "gn:name":"Campo el Dos (Dos de Arriba)",
    "gn:population":85,
    "gn:timezone":"America/Chihuahua",
    "iso:country":"MX",
    "wof:name":"Campo el Dos (Dos de Arriba)",
    "wof:placetype":"locality",
    "wof:population":85
},
  "geometry": {"coordinates":[-108.19305,29.64709],"type":"Point"}
}