{
  "type": "Feature",
  "properties": {
    "gn:admin1_code":"26",
    "gn:admin2_code":"18.0",
    "gn:asciiname":"El Garambullo",
    "gn:country_code":"MX",
    "gn:dem":106,
    "gn:feature_class":"P",
    "gn:feature_code":"PPL",
    "gn:name":"El Garambullo",
    "gn:population":0,
    "gn:timezone":"America/Hermosillo",
    "iso:country":"MX",
    "name:spa_x_preferred":[
        "El Garambullo"
    ],
    "name:spa_x_variant":[
        "La Madera"
    ],
    "wof:name":"El Garambullo",
    "wof:placetype":"locality"
},
  "geometry": {"coordinates":[-109.83194,28.09028],"type":"Point"}
}