{
  "type": "Feature",
  "properties": {
    "gn:admin1_code":"5",
    "gn:admin2_code":"59",
    "gn:asciiname":"La Azuleta",
    "gn:country_code":"MX",
    "gn:dem":1064,
    "gn:feature_class":"P",
    "gn:feature_code":"PPL",
    "gn:name":"La Azuleta",
    "gn:population":12,
    "gn:timezone":"America/Mexico_City",
    "iso:country":"MX",
    "wof:name":"La Azuleta",
    "wof:placetype":"locality",
    "wof:population":12
},
  "geometry": {"coordinates":[-91.95361,16.94111],"type":"Point"}
}