{
  "type": "Feature",
  "properties": {
    "gn:admin1_code":"11",
    "gn:admin2_code":"11",
    "gn:asciiname":"El Baztan (El Milagro)",
    "gn:country_code":"MX",
    "gn:dem":1742,
    "gn:feature_class":"P",
    "gn:feature_code":"PPL",
    "gn:name":"El Bazt\u00e1n (El Milagro)",
    "gn:population":15,
    "gn:timezone":"America/Mexico_City",
    "iso:country":"MX",
    "name:und_x_variant":[
        "El Bazt\u00e1n (El Milagro)"
    ],
    "wof:name":"El Baztan (El Milagro)",
    "wof:placetype":"locality",
    "wof:population":15
},
  "geometry": {"coordinates":[-100.92055999999999,20.48806],"type":"Point"}
}