{
  "type": "Feature",
  "properties": {
    "gn:admin1_code":"14.0",
    "gn:admin2_code":"53.0",
    "gn:asciiname":"Chipinque de Abajo",
    "gn:country_code":"MX",
    "gn:dem":1889,
    "gn:feature_class":"P",
    "gn:feature_code":"PPL",
    "gn:name":"Chipinque de Abajo",
    "gn:population":0,
    "gn:timezone":"America/Mexico_City",
    "iso:country":"MX",
    "name:spa_x_preferred":[
        "Chipinque de Abajo"
    ],
    "wof:name":"Chipinque de Abajo",
    "wof:placetype":"locality"
},
  "geometry": {"coordinates":[-101.90348,21.42771],"type":"Point"}
}