{
  "type": "Feature",
  "properties": {
    "gn:admin1_code":"16",
    "gn:admin2_code":"54.0",
    "gn:asciiname":"El Desmonte",
    "gn:country_code":"MX",
    "gn:dem":2204,
    "gn:feature_class":"P",
    "gn:feature_code":"PPL",
    "gn:name":"El Desmonte",
    "gn:population":278,
    "gn:timezone":"America/Mexico_City",
    "iso:country":"MX",
    "name:ceb_x_preferred":[
        "El Desmonte"
    ],
    "name:spa_x_preferred":[
        "El Desmonte"
    ],
    "wof:name":"El Desmonte",
    "wof:placetype":"locality",
    "wof:population":278
},
  "geometry": {"coordinates":[-101.54361,19.96472],"type":"Point"}
}