{
  "type": "Feature",
  "properties": {
    "gn:admin1_code":"14.0",
    "gn:admin2_code":"100.0",
    "gn:asciiname":"Bramador",
    "gn:cc2":"MX",
    "gn:country_code":"MX",
    "gn:dem":166,
    "gn:feature_class":"P",
    "gn:feature_code":"PPL",
    "gn:name":"Bramador",
    "gn:population":0,
    "gn:timezone":"America/Mexico_City",
    "iso:country":"MX",
    "name:und_x_variant":[
        "Bramadero",
        "Bramador"
    ],
    "wof:name":"Bramador",
    "wof:placetype":"locality"
},
  "geometry": {"coordinates":[-105.09999999999999,20.06667],"type":"Point"}
}