{
  "type": "Feature",
  "properties": {
    "gn:admin1_code":"11.0",
    "gn:asciiname":"San Juan Viejo",
    "gn:country_code":"MX",
    "gn:dem":2298,
    "gn:feature_class":"P",
    "gn:feature_code":"PPL",
    "gn:name":"San Juan Viejo",
    "gn:population":0,
    "gn:timezone":"America/Mexico_City",
    "iso:country":"MX",
    "name:spa_x_preferred":[
        "San Juan Viejo"
    ],
    "wof:name":"San Juan Viejo",
    "wof:placetype":"locality"
},
  "geometry": {"coordinates":[-100.6122,20.25734],"type":"Point"}
}