{
  "type": "Feature",
  "properties": {
    "gn:admin1_code":"28.0",
    "gn:admin2_code":"27.0",
    "gn:asciiname":"El Tauro",
    "gn:country_code":"MX",
    "gn:dem":119,
    "gn:feature_class":"P",
    "gn:feature_code":"PPL",
    "gn:name":"El Tauro",
    "gn:population":3,
    "gn:timezone":"America/Matamoros",
    "iso:country":"MX",
    "name:spa_x_preferred":[
        "El Tauro"
    ],
    "wof:name":"El Tauro",
    "wof:placetype":"locality",
    "wof:population":3
},
  "geometry": {"coordinates":[-99.49361,27.40083],"type":"Point"}
}