{
  "type": "Feature",
  "properties": {
    "gn:admin1_code":"17",
    "gn:admin2_code":"30.0",
    "gn:asciiname":"Rancho Santa Teresa",
    "gn:country_code":"MX",
    "gn:dem":1580,
    "gn:feature_class":"P",
    "gn:feature_code":"PPL",
    "gn:name":"Rancho Santa Teresa",
    "gn:population":89,
    "gn:timezone":"America/Mexico_City",
    "iso:country":"MX",
    "wof:name":"Rancho Santa Teresa",
    "wof:placetype":"locality",
    "wof:population":89
},
  "geometry": {"coordinates":[-98.86861,18.87583],"type":"Point"}
}