{
  "type": "Feature",
  "properties": {
    "gn:admin1_code":"31",
    "gn:admin2_code":"52.0",
    "gn:asciiname":"Tanya",
    "gn:country_code":"MX",
    "gn:dem":12,
    "gn:feature_class":"P",
    "gn:feature_code":"PPL",
    "gn:name":"Tanya",
    "gn:population":0,
    "gn:timezone":"America/Merida",
    "iso:country":"MX",
    "name:spa_x_preferred":[
        "Tanya"
    ],
    "wof:name":"Tanya",
    "wof:placetype":"locality"
},
  "geometry": {"coordinates":[-89.24768,21.11111],"type":"Point"}
}