{
  "type": "Feature",
  "properties": {
    "gn:admin1_code":"31",
    "gn:admin2_code":"52.0",
    "gn:asciiname":"Tanya",
    "gn:country_code":"MX",
    "gn:dem":12,
    "gn:feature_class":"P",
    "gn:feature_code":"PPL",
    "gn:name":"Tanya",
    "gn:population":0,
    "gn:timezone":"America/Merida",
    "iso:country":"MX",
    "name:cat_x_preferred":[
        "Tania"
    ],
    "name:deu_x_preferred":[
        "Tanja"
    ],
    "name:fra_x_preferred":[
        "Tanya"
    ],
    "name:heb_x_preferred":[
        "\u05e1\u05e4\u05e8 \u05d4\u05ea\u05e0\u05d9\u05d0"
    ],
    "name:ita_x_preferred":[
        "Tanya"
    ],
    "name:ron_x_preferred":[
        "Tanya"
    ],
    "name:rus_x_preferred":[
        "\u0422\u0430\u043d\u0438\u044f"
    ],
    "name:spa_x_preferred":[
        "Tanya"
    ],
    "name:spa_x_variant":[
        "Tania"
    ],
    "name:tur_x_preferred":[
        "Tanya"
    ],
    "name:ukr_x_preferred":[
        "\u0422\u0430\u043d\u0456\u044f"
    ],
    "wof:name":"Tanya",
    "wof:placetype":"locality"
},
  "geometry": {"coordinates":[-89.24768,21.11111],"type":"Point"}
}