{
  "type": "Feature",
  "properties": {
    "gn:admin1_code":"5.0",
    "gn:admin2_code":"99.0",
    "gn:asciiname":"El Cedro",
    "gn:country_code":"MX",
    "gn:dem":767,
    "gn:feature_class":"P",
    "gn:feature_code":"PPL",
    "gn:name":"El Cedro",
    "gn:population":0,
    "gn:timezone":"America/Mexico_City",
    "iso:country":"MX",
    "name:ceb_x_preferred":[
        "El Cedro"
    ],
    "name:fra_x_preferred":[
        "El Cedro"
    ],
    "name:ita_x_preferred":[
        "El Cedro"
    ],
    "name:spa_x_preferred":[
        "El Cedro"
    ],
    "name:swe_x_preferred":[
        "El Cedro"
    ],
    "wof:name":"El Cedro",
    "wof:placetype":"locality"
},
  "geometry": {"coordinates":[-91.92028000000001,15.92415],"type":"Point"}
}