{
  "type": "Feature",
  "properties": {
    "gn:admin1_code":"16.0",
    "gn:admin2_code":"76.0",
    "gn:asciiname":"Barranca de la Gloria",
    "gn:country_code":"MX",
    "gn:dem":1732,
    "gn:feature_class":"P",
    "gn:feature_code":"PPL",
    "gn:name":"Barranca de la Gloria",
    "gn:population":0,
    "gn:timezone":"America/Mexico_City",
    "iso:country":"MX",
    "wof:name":"Barranca de la Gloria",
    "wof:placetype":"locality"
},
  "geometry": {"coordinates":[-102.80439,20.044],"type":"Point"}
}