{
  "type": "Feature",
  "properties": {
    "gn:admin1_code":"30",
    "gn:admin2_code":"104.0",
    "gn:asciiname":"La Guadalupe",
    "gn:country_code":"MX",
    "gn:dem":79,
    "gn:feature_class":"P",
    "gn:feature_code":"PPL",
    "gn:name":"La Guadalupe",
    "gn:population":7,
    "gn:timezone":"America/Mexico_City",
    "iso:country":"MX",
    "wof:name":"La Guadalupe",
    "wof:placetype":"locality",
    "wof:population":7
},
  "geometry": {"coordinates":[-94.81222,18.49028],"type":"Point"}
}