{
  "type": "Feature",
  "properties": {
    "gn:admin1_code":"6.0",
    "gn:admin2_code":"31.0",
    "gn:asciiname":"El Nogal",
    "gn:cc2":"MX",
    "gn:country_code":"MX",
    "gn:dem":2111,
    "gn:feature_class":"P",
    "gn:feature_code":"PPL",
    "gn:name":"El Nogal",
    "gn:population":0,
    "gn:timezone":"America/Chihuahua",
    "iso:country":"MX",
    "name:und_x_variant":[
        "Nogal",
        "El Nogal"
    ],
    "wof:name":"El Nogal",
    "wof:placetype":"locality"
},
  "geometry": {"coordinates":[-107.64746,28.58407],"type":"Point"}
}