{
  "type": "Feature",
  "properties": {
    "gn:admin1_code":"26",
    "gn:asciiname":"El Ramblas",
    "gn:country_code":"MX",
    "gn:dem":149,
    "gn:feature_class":"P",
    "gn:feature_code":"PPL",
    "gn:name":"El Ramblas",
    "gn:population":0,
    "gn:timezone":"America/Mazatlan",
    "iso:country":"MX",
    "name:spa_x_preferred":[
        "El Ramblas"
    ],
    "wof:name":"El Ramblas",
    "wof:placetype":"locality"
},
  "geometry": {"coordinates":[-108.81485000000001,26.44498],"type":"Point"}
}