{
  "type": "Feature",
  "properties": {
    "gn:admin1_code":"5.0",
    "gn:admin2_code":"107.0",
    "gn:asciiname":"La Bandera",
    "gn:country_code":"MX",
    "gn:dem":746,
    "gn:feature_class":"P",
    "gn:feature_code":"PPL",
    "gn:name":"La Bandera",
    "gn:population":0,
    "gn:timezone":"America/Mexico_City",
    "iso:country":"MX",
    "name:spa_x_preferred":[
        "La Bandera"
    ],
    "wof:name":"La Bandera",
    "wof:placetype":"locality"
},
  "geometry": {"coordinates":[-92.9605,16.10586],"type":"Point"}
}