{
  "type": "Feature",
  "properties": {
    "gn:admin1_code":"5",
    "gn:admin2_code":"61",
    "gn:asciiname":"El Corazon Meyapac",
    "gn:country_code":"MX",
    "gn:dem":1049,
    "gn:feature_class":"P",
    "gn:feature_code":"PPL",
    "gn:name":"El Coraz\u00f3n Meyapac",
    "gn:population":9,
    "gn:timezone":"America/Mexico_City",
    "iso:country":"MX",
    "name:und_x_variant":[
        "El Coraz\u00f3n Meyapac"
    ],
    "wof:name":"El Corazon Meyapac",
    "wof:placetype":"locality",
    "wof:population":9
},
  "geometry": {"coordinates":[-93.34222,16.77944],"type":"Point"}
}