{
  "type": "Feature",
  "properties": {
    "gn:admin1_code":"11.0",
    "gn:admin2_code":"37.0",
    "gn:asciiname":"Dolores de Gallegos",
    "gn:country_code":"MX",
    "gn:dem":1754,
    "gn:feature_class":"P",
    "gn:feature_code":"PPL",
    "gn:name":"Dolores de Gallegos",
    "gn:population":0,
    "gn:timezone":"America/Mexico_City",
    "iso:country":"MX",
    "name:und_x_variant":[
        "Dolores",
        "Dolores de Gallegos"
    ],
    "wof:name":"Dolores de Gallegos",
    "wof:placetype":"locality"
},
  "geometry": {"coordinates":[-101.38343999999999,20.86685],"type":"Point"}
}