{
  "type": "Feature",
  "properties": {
    "gn:admin1_code":"4.0",
    "gn:asciiname":"El Guacamayo",
    "gn:country_code":"MX",
    "gn:dem":50,
    "gn:feature_class":"P",
    "gn:feature_code":"PPL",
    "gn:name":"El Guacamayo",
    "gn:population":0,
    "gn:timezone":"America/Merida",
    "iso:country":"MX",
    "name:ceb_x_preferred":[
        "El Guacamayo"
    ],
    "name:fra_x_preferred":[
        "El Guacamayo"
    ],
    "name:ita_x_preferred":[
        "El Guacamayo"
    ],
    "name:kat_x_preferred":[
        "\u10d4\u10da-\u10d2\u10e3\u10d0\u10d9\u10d0\u10db\u10d0\u10d8\u10dd"
    ],
    "name:msa_x_preferred":[
        "El Guacamayo"
    ],
    "name:nld_x_preferred":[
        "El Guacamayo"
    ],
    "name:sco_x_preferred":[
        "El Guacamayo"
    ],
    "name:spa_x_preferred":[
        "El Guacamayo"
    ],
    "name:swe_x_preferred":[
        "El Guacamayo"
    ],
    "name:tgl_x_preferred":[
        "El Guacamayo"
    ],
    "name:vie_x_preferred":[
        "El Guacamayo"
    ],
    "name:war_x_preferred":[
        "El Guacamayo"
    ],
    "name:zho_x_preferred":[
        "\u57c3\u723e\u74dc\u5361\u99ac\u7d04"
    ],
    "wof:name":"El Guacamayo",
    "wof:placetype":"locality"
},
  "geometry": {"coordinates":[-90.66273,18.15012],"type":"Point"}
}