{
  "type": "Feature",
  "properties": {
    "gn:admin1_code":"4.0",
    "gn:asciiname":"El Guacamayo",
    "gn:country_code":"MX",
    "gn:dem":50,
    "gn:feature_class":"P",
    "gn:feature_code":"PPL",
    "gn:name":"El Guacamayo",
    "gn:population":0,
    "gn:timezone":"America/Merida",
    "iso:country":"MX",
    "name:spa_x_preferred":[
        "El Guacamayo"
    ],
    "wof:name":"El Guacamayo",
    "wof:placetype":"locality"
},
  "geometry": {"coordinates":[-90.66273,18.15012],"type":"Point"}
}