{
  "type": "Feature",
  "properties": {
    "gn:admin1_code":"6.0",
    "gn:admin2_code":"9.0",
    "gn:asciiname":"Bajio de Sasogueichic",
    "gn:country_code":"MX",
    "gn:dem":2310,
    "gn:feature_class":"P",
    "gn:feature_code":"PPL",
    "gn:name":"Baj\u00edo de Sasog\u00fc\u00edchic",
    "gn:population":0,
    "gn:timezone":"America/Chihuahua",
    "iso:country":"MX",
    "name:und_x_variant":[
        "Bajio de Sasaguiachic",
        "Baj\u00edo de Sasog\u00fc\u00edchic"
    ],
    "wof:name":"Bajio de Sasogueichic",
    "wof:placetype":"locality"
},
  "geometry": {"coordinates":[-107.45,27.86667000000001],"type":"Point"}
}