{
  "type": "Feature",
  "properties": {
    "gn:admin1_code":"11",
    "gn:admin2_code":"20",
    "gn:asciiname":"San Rafael Cerro Verde",
    "gn:country_code":"MX",
    "gn:dem":2365,
    "gn:feature_class":"P",
    "gn:feature_code":"PPL",
    "gn:name":"San Rafael Cerro Verde",
    "gn:population":47,
    "gn:timezone":"America/Mexico_City",
    "iso:country":"MX",
    "wof:name":"San Rafael Cerro Verde",
    "wof:placetype":"locality",
    "wof:population":47
},
  "geometry": {"coordinates":[-101.45806,21.17028],"type":"Point"}
}