{
  "type": "Feature",
  "properties": {
    "gn:admin1_code":"28.0",
    "gn:admin2_code":"18.0",
    "gn:asciiname":"Maria Mercedes",
    "gn:country_code":"MX",
    "gn:dem":192,
    "gn:feature_class":"P",
    "gn:feature_code":"PPL",
    "gn:name":"Mar\u00eda Mercedes",
    "gn:population":4,
    "gn:timezone":"America/Monterrey",
    "iso:country":"MX",
    "name:spa_x_preferred":[
        "Mar\u00eda Mercedes"
    ],
    "wof:name":"Maria Mercedes",
    "wof:placetype":"locality",
    "wof:population":4
},
  "geometry": {"coordinates":[-98.31471999999999,24.34361],"type":"Point"}
}