{
  "type": "Feature",
  "properties": {
    "gn:admin1_code":"16",
    "gn:admin2_code":"49.0",
    "gn:asciiname":"San Pedro Piedras Gordas",
    "gn:country_code":"MX",
    "gn:dem":2118,
    "gn:feature_class":"P",
    "gn:feature_code":"PPL",
    "gn:name":"San Pedro Piedras Gordas",
    "gn:population":114,
    "gn:timezone":"America/Mexico_City",
    "iso:country":"MX",
    "wof:name":"San Pedro Piedras Gordas",
    "wof:placetype":"locality",
    "wof:population":114
},
  "geometry": {"coordinates":[-101.26027999999999,19.43861],"type":"Point"}
}