{
  "type": "Feature",
  "properties": {
    "gn:admin1_code":"17",
    "gn:admin2_code":"8.0",
    "gn:asciiname":"Fraccionamiento Arboleda",
    "gn:country_code":"MX",
    "gn:dem":1267,
    "gn:feature_class":"P",
    "gn:feature_code":"PPL",
    "gn:name":"Fraccionamiento Arboleda",
    "gn:population":189,
    "gn:timezone":"America/Mexico_City",
    "iso:country":"MX",
    "wof:name":"Fraccionamiento Arboleda",
    "wof:placetype":"locality",
    "wof:population":189
},
  "geometry": {"coordinates":[-99.19902999999999,18.84866],"type":"Point"}
}