{
  "type": "Feature",
  "properties": {
    "gn:admin1_code":"30",
    "gn:admin2_code":"77",
    "gn:asciiname":"Rancho Nuevo",
    "gn:country_code":"MX",
    "gn:dem":62,
    "gn:feature_class":"P",
    "gn:feature_code":"PPL",
    "gn:name":"Rancho Nuevo",
    "gn:population":41,
    "gn:timezone":"America/Mexico_City",
    "iso:country":"MX",
    "wof:name":"Rancho Nuevo",
    "wof:placetype":"locality",
    "wof:population":41
},
  "geometry": {"coordinates":[-95.52943999999999,18.05833],"type":"Point"}
}