{
  "type": "Feature",
  "properties": {
    "gn:admin1_code":"2",
    "gn:admin2_code":"4.0",
    "gn:asciiname":"Agua Dulce",
    "gn:country_code":"MX",
    "gn:dem":147,
    "gn:feature_class":"P",
    "gn:feature_code":"PPL",
    "gn:name":"Agua Dulce",
    "gn:population":6,
    "gn:timezone":"America/Tijuana",
    "iso:country":"MX",
    "wof:name":"Agua Dulce",
    "wof:placetype":"locality",
    "wof:population":6
},
  "geometry": {"coordinates":[-117.06305999999999,32.42556],"type":"Point"}
}