{
  "type": "Feature",
  "properties": {
    "gn:admin1_code":"16",
    "gn:admin2_code":"92",
    "gn:asciiname":"El Guayabito",
    "gn:country_code":"MX",
    "gn:dem":548,
    "gn:feature_class":"P",
    "gn:feature_code":"PPL",
    "gn:name":"El Guayabito",
    "gn:population":30,
    "gn:timezone":"America/Mexico_City",
    "iso:country":"MX",
    "wof:name":"El Guayabito",
    "wof:placetype":"locality",
    "wof:population":30
},
  "geometry": {"coordinates":[-100.86444,18.87389],"type":"Point"}
}