{
  "type": "Feature",
  "properties": {
    "gn:admin1_code":"7",
    "gn:admin2_code":"35.0",
    "gn:asciiname":"Los Moralitos",
    "gn:country_code":"MX",
    "gn:dem":1124,
    "gn:feature_class":"P",
    "gn:feature_code":"PPL",
    "gn:name":"Los Moralitos",
    "gn:population":0,
    "gn:timezone":"America/Monterrey",
    "iso:country":"MX",
    "name:spa_x_preferred":[
        "Los Moralitos"
    ],
    "wof:name":"Los Moralitos",
    "wof:placetype":"locality"
},
  "geometry": {"coordinates":[-103.4144,25.57989],"type":"Point"}
}