{
  "type": "Feature",
  "properties": {
    "gn:admin1_code":"14",
    "gn:admin2_code":"71.0",
    "gn:asciiname":"Los Plueblitos",
    "gn:country_code":"MX",
    "gn:dem":1247,
    "gn:feature_class":"P",
    "gn:feature_code":"PPL",
    "gn:name":"Los Plueblitos",
    "gn:population":0,
    "gn:timezone":"America/Mexico_City",
    "iso:country":"MX",
    "wof:name":"Los Plueblitos",
    "wof:placetype":"locality"
},
  "geometry": {"coordinates":[-103.48251,21.01849],"type":"Point"}
}