{
  "type": "Feature",
  "properties": {
    "gn:admin1_code":"12.0",
    "gn:admin2_code":"38.0",
    "gn:asciiname":"Las Pipinas",
    "gn:country_code":"MX",
    "gn:dem":65,
    "gn:feature_class":"P",
    "gn:feature_code":"PPL",
    "gn:name":"Las Pipinas",
    "gn:population":136,
    "gn:timezone":"America/Mexico_City",
    "iso:country":"MX",
    "wof:name":"Las Pipinas",
    "wof:placetype":"locality",
    "wof:population":136
},
  "geometry": {"coordinates":[-101.57333,17.74527999999999],"type":"Point"}
}