{
  "type": "Feature",
  "properties": {
    "gn:admin1_code":"10",
    "gn:admin2_code":"5.0",
    "gn:asciiname":"Quince de Septiembre Viejo",
    "gn:country_code":"MX",
    "gn:dem":1877,
    "gn:feature_class":"P",
    "gn:feature_code":"PPL",
    "gn:name":"Quince de Septiembre Viejo",
    "gn:population":0,
    "gn:timezone":"America/Monterrey",
    "iso:country":"MX",
    "name:spa_x_preferred":[
        "Quince de Septiembre Viejo"
    ],
    "name:und_x_variant":[
        "Quince de Septiembre"
    ],
    "wof:name":"Quince de Septiembre Viejo",
    "wof:placetype":"locality"
},
  "geometry": {"coordinates":[-104.62103,23.97552],"type":"Point"}
}