{
  "type": "Feature",
  "properties": {
    "gn:admin1_code":"31",
    "gn:admin2_code":"102.0",
    "gn:asciiname":"Dzok",
    "gn:country_code":"MX",
    "gn:dem":26,
    "gn:feature_class":"P",
    "gn:feature_code":"PPL",
    "gn:name":"Dzok",
    "gn:population":0,
    "gn:timezone":"America/Cancun",
    "iso:country":"MX",
    "name:spa_x_preferred":[
        "Dzok"
    ],
    "wof:name":"Dzok",
    "wof:placetype":"locality"
},
  "geometry": {"coordinates":[-88.00601,20.48702],"type":"Point"}
}