{
  "type": "Feature",
  "properties": {
    "gn:admin1_code":"5.0",
    "gn:asciiname":"Flor de Mayo",
    "gn:country_code":"MX",
    "gn:dem":11,
    "gn:feature_class":"P",
    "gn:feature_code":"PPL",
    "gn:name":"Flor de Mayo",
    "gn:population":0,
    "gn:timezone":"America/Mexico_City",
    "iso:country":"MX",
    "name:spa_x_preferred":[
        "Flor de Mayo"
    ],
    "wof:name":"Flor de Mayo",
    "wof:placetype":"locality"
},
  "geometry": {"coordinates":[-92.56565999999999,15.03368],"type":"Point"}
}