{
  "type": "Feature",
  "properties": {
    "gn:admin1_code":"30.0",
    "gn:admin2_code":"123.0",
    "gn:asciiname":"El Atoron",
    "gn:country_code":"MX",
    "gn:dem":28,
    "gn:feature_class":"P",
    "gn:feature_code":"PPL",
    "gn:name":"El Ator\u00f3n",
    "gn:population":3,
    "gn:timezone":"America/Mexico_City",
    "iso:country":"MX",
    "name:spa_x_preferred":[
        "El Ator\u00f3n"
    ],
    "wof:name":"El Atoron",
    "wof:placetype":"locality",
    "wof:population":3
},
  "geometry": {"coordinates":[-98.38916999999999,22.335],"type":"Point"}
}