{
  "type": "Feature",
  "properties": {
    "gn:admin1_code":"11",
    "gn:admin2_code":"3.0",
    "gn:asciiname":"El Fraile",
    "gn:country_code":"MX",
    "gn:dem":2003,
    "gn:feature_class":"P",
    "gn:feature_code":"PPL",
    "gn:name":"El Fraile",
    "gn:population":510,
    "gn:timezone":"America/Mexico_City",
    "iso:country":"MX",
    "wof:name":"El Fraile",
    "wof:placetype":"locality",
    "wof:population":510
},
  "geometry": {"coordinates":[-100.59193999999999,21.09167],"type":"Point"}
}