{
  "type": "Feature",
  "properties": {
    "gn:admin1_code":"15",
    "gn:admin2_code":"118.0",
    "gn:asciiname":"Colonia Cuauhtemoc",
    "gn:country_code":"MX",
    "gn:dem":2891,
    "gn:feature_class":"P",
    "gn:feature_code":"PPL",
    "gn:name":"Colonia Cuauht\u00e9moc",
    "gn:population":0,
    "gn:timezone":"America/Mexico_City",
    "iso:country":"MX",
    "name:spa_x_preferred":[
        "Colonia Cuauht\u00e9moc"
    ],
    "name:und_x_variant":[
        "Cuauht\u00e9moc"
    ],
    "wof:name":"Colonia Cuauhtemoc",
    "wof:placetype":"locality"
},
  "geometry": {"coordinates":[-99.79161999999999,19.24903],"type":"Point"}
}