{
  "type": "Feature",
  "properties": {
    "gn:admin1_code":"14",
    "gn:admin2_code":"53",
    "gn:asciiname":"El Gato",
    "gn:country_code":"MX",
    "gn:dem":1999,
    "gn:feature_class":"P",
    "gn:feature_code":"PPL",
    "gn:name":"El Gato",
    "gn:population":42,
    "gn:timezone":"America/Mexico_City",
    "iso:country":"MX",
    "wof:name":"El Gato",
    "wof:placetype":"locality",
    "wof:population":42
},
  "geometry": {"coordinates":[-102.00194,21.7875],"type":"Point"}
}