{
  "type": "Feature",
  "properties": {
    "gn:admin1_code":"14",
    "gn:admin2_code":"81.0",
    "gn:asciiname":"Tenasco de Arriba",
    "gn:country_code":"MX",
    "gn:dem":1817,
    "gn:feature_class":"P",
    "gn:feature_code":"PPL",
    "gn:name":"Tenasco de Arriba",
    "gn:population":0,
    "gn:timezone":"America/Mexico_City",
    "iso:country":"MX",
    "name:spa_x_preferred":[
        "Tenasco de Arriba"
    ],
    "name:und_x_variant":[
        "Tenasco"
    ],
    "wof:name":"Tenasco de Arriba",
    "wof:placetype":"locality"
},
  "geometry": {"coordinates":[-103.16312000000001,22.18688],"type":"Point"}
}