{
  "type": "Feature",
  "properties": {
    "gn:admin1_code":"5.0",
    "gn:asciiname":"San Antonio Nancinapa",
    "gn:country_code":"MX",
    "gn:dem":709,
    "gn:feature_class":"P",
    "gn:feature_code":"PPL",
    "gn:name":"San Antonio Nancinapa",
    "gn:population":0,
    "gn:timezone":"America/Mexico_City",
    "iso:country":"MX",
    "name:spa_x_preferred":[
        "San Antonio Nancinapa"
    ],
    "wof:name":"San Antonio Nancinapa",
    "wof:placetype":"locality"
},
  "geometry": {"coordinates":[-92.69817,15.99092],"type":"Point"}
}