{
  "type": "Feature",
  "properties": {
    "gn:admin1_code":"2",
    "gn:admin2_code":"4.0",
    "gn:asciiname":"Xicotencatl Dos",
    "gn:country_code":"MX",
    "gn:dem":245,
    "gn:feature_class":"P",
    "gn:feature_code":"PPL",
    "gn:name":"Xicot\u00e9ncatl Dos",
    "gn:population":490,
    "gn:timezone":"America/Tijuana",
    "iso:country":"MX",
    "name:und_x_variant":[
        "Xicot\u00e9ncatl Dos"
    ],
    "wof:name":"Xicotencatl Dos",
    "wof:placetype":"locality",
    "wof:population":490
},
  "geometry": {"coordinates":[-117.06444,32.45917],"type":"Point"}
}