{
  "type": "Feature",
  "properties": {
    "gn:admin1_code":"6",
    "gn:admin2_code":"66.0",
    "gn:asciiname":"Rancho Colorado",
    "gn:country_code":"MX",
    "gn:dem":2437,
    "gn:feature_class":"P",
    "gn:feature_code":"PPL",
    "gn:name":"Rancho Colorado",
    "gn:population":6,
    "gn:timezone":"America/Chihuahua",
    "iso:country":"MX",
    "name:spa_x_preferred":[
        "Rancho Colorado"
    ],
    "wof:name":"Rancho Colorado",
    "wof:placetype":"locality",
    "wof:population":6
},
  "geometry": {"coordinates":[-108.19632,27.71769],"type":"Point"}
}