{
  "type": "Feature",
  "properties": {
    "gn:admin1_code":"30.0",
    "gn:admin2_code":"155.0",
    "gn:asciiname":"Paso de Piedras",
    "gn:country_code":"MX",
    "gn:dem":52,
    "gn:feature_class":"P",
    "gn:feature_code":"PPL",
    "gn:name":"Paso de Piedras",
    "gn:population":11,
    "gn:timezone":"America/Mexico_City",
    "iso:country":"MX",
    "name:spa_x_preferred":[
        "Paso de Piedras"
    ],
    "wof:name":"Paso de Piedras",
    "wof:placetype":"locality",
    "wof:population":11
},
  "geometry": {"coordinates":[-98.03036,21.57297],"type":"Point"}
}