{
  "type": "Feature",
  "properties": {
    "gn:admin1_code":"30.0",
    "gn:asciiname":"El Encinal",
    "gn:country_code":"MX",
    "gn:dem":100,
    "gn:feature_class":"P",
    "gn:feature_code":"PPL",
    "gn:name":"El Encinal",
    "gn:population":0,
    "gn:timezone":"America/Mexico_City",
    "iso:country":"MX",
    "name:spa_x_preferred":[
        "El Encinal"
    ],
    "wof:name":"El Encinal",
    "wof:placetype":"locality"
},
  "geometry": {"coordinates":[-95.06332999999999,17.98887999999999],"type":"Point"}
}