{
  "type": "Feature",
  "properties": {
    "gn:admin1_code":"28.0",
    "gn:admin2_code":"27.0",
    "gn:asciiname":"America",
    "gn:country_code":"MX",
    "gn:dem":133,
    "gn:feature_class":"P",
    "gn:feature_code":"PPL",
    "gn:name":"Am\u00e9rica",
    "gn:population":0,
    "gn:timezone":"America/Matamoros",
    "iso:country":"MX",
    "name:spa_x_preferred":[
        "Am\u00e9rica"
    ],
    "wof:name":"America",
    "wof:placetype":"locality"
},
  "geometry": {"coordinates":[-99.54868,27.43833],"type":"Point"}
}