{
  "type": "Feature",
  "properties": {
    "gn:admin1_code":"2.0",
    "gn:asciiname":"Cuatro Milpas",
    "gn:country_code":"MX",
    "gn:dem":39,
    "gn:feature_class":"P",
    "gn:feature_code":"PPL",
    "gn:name":"Cuatro Milpas",
    "gn:population":0,
    "gn:timezone":"America/Tijuana",
    "iso:country":"MX",
    "name:spa_x_preferred":[
        "Cuatro Milpas"
    ],
    "wof:name":"Cuatro Milpas",
    "wof:placetype":"locality"
},
  "geometry": {"coordinates":[-116.67494000000001,31.89548],"type":"Point"}
}