{
  "type": "Feature",
  "properties": {
    "gn:admin1_code":"6",
    "gn:admin2_code":"65.0",
    "gn:asciiname":"Sipurachi",
    "gn:country_code":"MX",
    "gn:dem":1986,
    "gn:feature_class":"P",
    "gn:feature_code":"PPL",
    "gn:name":"Sipurachi",
    "gn:population":0,
    "gn:timezone":"America/Chihuahua",
    "iso:country":"MX",
    "name:spa_x_preferred":[
        "Sipurachi"
    ],
    "wof:name":"Sipurachi",
    "wof:placetype":"locality"
},
  "geometry": {"coordinates":[-107.85569,27.56276],"type":"Point"}
}