{
  "type": "Feature",
  "properties": {
    "gn:admin1_code":"11",
    "gn:admin2_code":"20",
    "gn:asciiname":"Agua Zarca",
    "gn:country_code":"MX",
    "gn:dem":2253,
    "gn:feature_class":"P",
    "gn:feature_code":"PPL",
    "gn:name":"Agua Zarca",
    "gn:population":14,
    "gn:timezone":"America/Mexico_City",
    "iso:country":"MX",
    "wof:name":"Agua Zarca",
    "wof:placetype":"locality",
    "wof:population":14
},
  "geometry": {"coordinates":[-101.58139,21.24889],"type":"Point"}
}