{
  "type": "Feature",
  "properties": {
    "gn:admin1_code":"26.0",
    "gn:admin2_code":"33.0",
    "gn:asciiname":"Juliantabampo",
    "gn:cc2":"MX",
    "gn:country_code":"MX",
    "gn:dem":5,
    "gn:feature_class":"P",
    "gn:feature_code":"PPL",
    "gn:name":"Juliantabampo",
    "gn:population":94,
    "gn:timezone":"America/Hermosillo",
    "iso:country":"MX",
    "name:und_x_variant":[
        "Jaliantabampo",
        "Juliantabampo"
    ],
    "wof:name":"Juliantabampo",
    "wof:placetype":"locality",
    "wof:population":94
},
  "geometry": {"coordinates":[-109.70139,26.77389],"type":"Point"}
}