{
  "type": "Feature",
  "properties": {
    "gn:admin1_code":"28.0",
    "gn:admin2_code":"35.0",
    "gn:asciiname":"Catalina Numero Dos",
    "gn:country_code":"MX",
    "gn:dem":41,
    "gn:feature_class":"P",
    "gn:feature_code":"PPL",
    "gn:name":"Catalina N\u00famero Dos",
    "gn:population":0,
    "gn:timezone":"America/Monterrey",
    "iso:country":"MX",
    "name:spa_x_preferred":[
        "Catalina N\u00famero Dos"
    ],
    "wof:name":"Catalina Numero Dos",
    "wof:placetype":"locality"
},
  "geometry": {"coordinates":[-98.0856,24.79089],"type":"Point"}
}