{
  "type": "Feature",
  "properties": {
    "gn:admin1_code":"14",
    "gn:admin2_code":"31.0",
    "gn:asciiname":"Quiroz",
    "gn:country_code":"MX",
    "gn:dem":1869,
    "gn:feature_class":"P",
    "gn:feature_code":"PPL",
    "gn:name":"Quiroz",
    "gn:population":0,
    "gn:timezone":"America/Mexico_City",
    "iso:country":"MX",
    "name:spa_x_preferred":[
        "Quiroz"
    ],
    "wof:name":"Quiroz",
    "wof:placetype":"locality"
},
  "geometry": {"coordinates":[-103.68470000000001,21.90366],"type":"Point"}
}