{
  "type": "Feature",
  "properties": {
    "gn:admin1_code":"10",
    "gn:admin2_code":"6.0",
    "gn:asciiname":"El Rayo",
    "gn:country_code":"MX",
    "gn:dem":1527,
    "gn:feature_class":"P",
    "gn:feature_code":"PPL",
    "gn:name":"El Rayo",
    "gn:population":0,
    "gn:timezone":"America/Monterrey",
    "iso:country":"MX",
    "name:spa_x_preferred":[
        "El Rayo"
    ],
    "name:spa_x_variant":[
        "Pichahuilla"
    ],
    "wof:name":"El Rayo",
    "wof:placetype":"locality"
},
  "geometry": {"coordinates":[-102.98569000000001,24.70695],"type":"Point"}
}