{
  "type": "Feature",
  "properties": {
    "gn:admin1_code":"30",
    "gn:admin2_code":"168.0",
    "gn:asciiname":"Oxtotitla",
    "gn:country_code":"MX",
    "gn:dem":1267,
    "gn:feature_class":"P",
    "gn:feature_code":"PPL",
    "gn:name":"Oxtotitla",
    "gn:population":681,
    "gn:timezone":"America/Mexico_City",
    "iso:country":"MX",
    "wof:name":"Oxtotitla",
    "wof:placetype":"locality",
    "wof:population":681
},
  "geometry": {"coordinates":[-97.00806,18.72417],"type":"Point"}
}