{
  "type": "Feature",
  "properties": {
    "gn:admin1_code":"6",
    "gn:admin2_code":"20.0",
    "gn:asciiname":"Las Tunas",
    "gn:country_code":"MX",
    "gn:dem":1049,
    "gn:feature_class":"P",
    "gn:feature_code":"PPL",
    "gn:name":"Las Tunas",
    "gn:population":0,
    "gn:timezone":"America/Chihuahua",
    "iso:country":"MX",
    "name:spa_x_preferred":[
        "Las Tunas"
    ],
    "wof:name":"Las Tunas",
    "wof:placetype":"locality"
},
  "geometry": {"coordinates":[-108.61369999999999,27.54976],"type":"Point"}
}