{
  "type": "Feature",
  "properties": {
    "gn:admin1_code":"5",
    "gn:admin2_code":"19.0",
    "gn:asciiname":"Yaltache Buenavista",
    "gn:country_code":"MX",
    "gn:dem":2209,
    "gn:feature_class":"P",
    "gn:feature_code":"PPL",
    "gn:name":"Yaltach\u00e9 Buenavista",
    "gn:population":74,
    "gn:timezone":"America/Mexico_City",
    "iso:country":"MX",
    "name:und_x_variant":[
        "Yaltach\u00e9 Buenavista"
    ],
    "wof:name":"Yaltache Buenavista",
    "wof:placetype":"locality",
    "wof:population":74
},
  "geometry": {"coordinates":[-92.29555999999999,16.45944],"type":"Point"}
}