{
  "type": "Feature",
  "properties": {
    "gn:admin1_code":"10",
    "gn:admin2_code":"4.0",
    "gn:asciiname":"El Triunfo",
    "gn:country_code":"MX",
    "gn:dem":1984,
    "gn:feature_class":"P",
    "gn:feature_code":"PPL",
    "gn:name":"El Triunfo",
    "gn:population":0,
    "gn:timezone":"America/Monterrey",
    "iso:country":"MX",
    "name:spa_x_preferred":[
        "El Triunfo"
    ],
    "wof:name":"El Triunfo",
    "wof:placetype":"locality"
},
  "geometry": {"coordinates":[-103.80817,24.64862],"type":"Point"}
}