{
  "type": "Feature",
  "properties": {
    "gn:admin1_code":"12",
    "gn:admin2_code":"11",
    "gn:asciiname":"Barrio Nuevo",
    "gn:country_code":"MX",
    "gn:dem":29,
    "gn:feature_class":"P",
    "gn:feature_code":"PPL",
    "gn:name":"Barrio Nuevo",
    "gn:population":10,
    "gn:timezone":"America/Mexico_City",
    "iso:country":"MX",
    "wof:name":"Barrio Nuevo",
    "wof:placetype":"locality",
    "wof:population":10
},
  "geometry": {"coordinates":[-100.44659,17.16066],"type":"Point"}
}