{
  "type": "Feature",
  "properties": {
    "gn:admin1_code":"24",
    "gn:admin2_code":"32.0",
    "gn:asciiname":"Vallecito de la Cruz",
    "gn:country_code":"MX",
    "gn:dem":1997,
    "gn:feature_class":"P",
    "gn:feature_code":"PPL",
    "gn:name":"Vallecito de la Cruz",
    "gn:population":0,
    "gn:timezone":"America/Mexico_City",
    "iso:country":"MX",
    "name:spa_x_preferred":[
        "Vallecito de la Cruz"
    ],
    "name:und_x_variant":[
        "Vellecito",
        "Vallecitos"
    ],
    "wof:name":"Vallecito de la Cruz",
    "wof:placetype":"locality"
},
  "geometry": {"coordinates":[-100.41764999999999,21.88849],"type":"Point"}
}