{
  "type": "Feature",
  "properties": {
    "gn:admin1_code":"21",
    "gn:admin2_code":"10.0",
    "gn:asciiname":"Cuautotolapan (San Jose)",
    "gn:country_code":"MX",
    "gn:dem":2408,
    "gn:feature_class":"P",
    "gn:feature_code":"PPL",
    "gn:name":"Cuautotolapan (San Jos\u00e9)",
    "gn:population":1732,
    "gn:timezone":"America/Mexico_City",
    "iso:country":"MX",
    "name:und_x_variant":[
        "Cuautotolapan (San Jos\u00e9)"
    ],
    "wof:name":"Cuautotolapan (San Jose)",
    "wof:placetype":"locality",
    "wof:population":1732
},
  "geometry": {"coordinates":[-97.12090999999999,18.43299],"type":"Point"}
}