{
  "type": "Feature",
  "properties": {
    "gn:admin1_code":"6",
    "gn:admin2_code":"27",
    "gn:asciiname":"Cumbre de Tarahuitas (Cumbres del Rincon)",
    "gn:country_code":"MX",
    "gn:dem":2532,
    "gn:feature_class":"P",
    "gn:feature_code":"PPL",
    "gn:name":"Cumbre de Tarahuitas (Cumbres del Rinc\u00f3n)",
    "gn:population":28,
    "gn:timezone":"America/Chihuahua",
    "iso:country":"MX",
    "name:und_x_variant":[
        "Cumbre de Tarahuitas (Cumbres del Rinc\u00f3n)"
    ],
    "wof:name":"Cumbre de Tarahuitas (Cumbres del Rincon)",
    "wof:placetype":"locality",
    "wof:population":28
},
  "geometry": {"coordinates":[-107.25709999999999,26.67466],"type":"Point"}
}