{
  "type": "Feature",
  "properties": {
    "gn:admin1_code":"12",
    "gn:admin2_code":"76.0",
    "gn:asciiname":"Barranca Pobre",
    "gn:country_code":"MX",
    "gn:dem":1660,
    "gn:feature_class":"P",
    "gn:feature_code":"PPL",
    "gn:name":"Barranca Pobre",
    "gn:population":0,
    "gn:timezone":"America/Mexico_City",
    "iso:country":"MX",
    "name:spa_x_preferred":[
        "Barranca Pobre"
    ],
    "wof:name":"Barranca Pobre",
    "wof:placetype":"locality"
},
  "geometry": {"coordinates":[-98.88204,17.24966],"type":"Point"}
}