{
  "type": "Feature",
  "properties": {
    "gn:admin1_code":"18",
    "gn:admin2_code":"9",
    "gn:asciiname":"Teneracas",
    "gn:country_code":"MX",
    "gn:dem":894,
    "gn:feature_class":"P",
    "gn:feature_code":"PPL",
    "gn:name":"Teneracas",
    "gn:population":22,
    "gn:timezone":"America/Mazatlan",
    "iso:country":"MX",
    "wof:name":"Teneracas",
    "wof:placetype":"locality",
    "wof:population":22
},
  "geometry": {"coordinates":[-104.84889,21.91278],"type":"Point"}
}