{
  "type": "Feature",
  "properties": {
    "gn:admin1_code":"6.0",
    "gn:admin2_code":"37.0",
    "gn:asciiname":"La Lagunita",
    "gn:country_code":"MX",
    "gn:dem":1211,
    "gn:feature_class":"P",
    "gn:feature_code":"PPL",
    "gn:name":"La Lagunita",
    "gn:population":0,
    "gn:timezone":"America/Ojinaga",
    "iso:country":"MX",
    "name:spa_x_preferred":[
        "La Lagunita"
    ],
    "wof:name":"La Lagunita",
    "wof:placetype":"locality"
},
  "geometry": {"coordinates":[-106.6353,31.19579],"type":"Point"}
}