{
  "type": "Feature",
  "properties": {
    "gn:admin1_code":"14",
    "gn:admin2_code":"58",
    "gn:asciiname":"El Aguacate",
    "gn:country_code":"MX",
    "gn:dem":1251,
    "gn:feature_class":"P",
    "gn:feature_code":"PPL",
    "gn:name":"El Aguacate",
    "gn:population":30,
    "gn:timezone":"America/Mexico_City",
    "iso:country":"MX",
    "wof:name":"El Aguacate",
    "wof:placetype":"locality",
    "wof:population":30
},
  "geometry": {"coordinates":[-104.99833,20.51917000000001],"type":"Point"}
}