{
  "type": "Feature",
  "properties": {
    "gn:admin1_code":"30",
    "gn:admin2_code":"196",
    "gn:asciiname":"San Lazaro",
    "gn:country_code":"MX",
    "gn:dem":529,
    "gn:feature_class":"P",
    "gn:feature_code":"PPL",
    "gn:name":"San L\u00e1zaro",
    "gn:population":25,
    "gn:timezone":"America/Mexico_City",
    "iso:country":"MX",
    "name:und_x_variant":[
        "San L\u00e1zaro"
    ],
    "wof:name":"San Lazaro",
    "wof:placetype":"locality",
    "wof:population":25
},
  "geometry": {"coordinates":[-96.81444,18.82556],"type":"Point"}
}