{
  "type": "Feature",
  "properties": {
    "gn:admin1_code":"14.0",
    "gn:asciiname":"Acatique",
    "gn:country_code":"MX",
    "gn:dem":998,
    "gn:feature_class":"P",
    "gn:feature_code":"PPL",
    "gn:name":"Acatique",
    "gn:population":0,
    "gn:timezone":"America/Mexico_City",
    "iso:country":"MX",
    "name:spa_x_preferred":[
        "Acatique"
    ],
    "wof:name":"Acatique",
    "wof:placetype":"locality"
},
  "geometry": {"coordinates":[-103.91207,21.35796],"type":"Point"}
}