{
  "type": "Feature",
  "properties": {
    "gn:admin1_code":"8",
    "gn:admin2_code":"10",
    "gn:asciiname":"La Sidra",
    "gn:country_code":"MX",
    "gn:dem":678,
    "gn:feature_class":"P",
    "gn:feature_code":"PPL",
    "gn:name":"La Sidra",
    "gn:population":15,
    "gn:timezone":"America/Mexico_City",
    "iso:country":"MX",
    "name:ast_x_preferred":[
        "La Sidra"
    ],
    "name:glg_x_preferred":[
        "La Sidra"
    ],
    "wof:name":"La Sidra",
    "wof:placetype":"locality",
    "wof:population":15
},
  "geometry": {"coordinates":[-103.71666999999999,19.30361],"type":"Point"}
}