{
  "type": "Feature",
  "properties": {
    "gn:admin1_code":"5",
    "gn:admin2_code":"107.0",
    "gn:asciiname":"San Jose de los Altos",
    "gn:country_code":"MX",
    "gn:dem":1234,
    "gn:feature_class":"P",
    "gn:feature_code":"PPL",
    "gn:name":"San Jos\u00e9 de los Altos",
    "gn:population":6,
    "gn:timezone":"America/Mexico_City",
    "iso:country":"MX",
    "name:und_x_variant":[
        "San Jos\u00e9 de los Altos"
    ],
    "wof:name":"San Jose de los Altos",
    "wof:placetype":"locality",
    "wof:population":6
},
  "geometry": {"coordinates":[-93.37444000000001,15.98417],"type":"Point"}
}