{
  "type": "Feature",
  "properties": {
    "gn:admin1_code":"16",
    "gn:admin2_code":"19.0",
    "gn:asciiname":"Rincon de Magueyes",
    "gn:country_code":"MX",
    "gn:dem":1627,
    "gn:feature_class":"P",
    "gn:feature_code":"PPL",
    "gn:name":"Rinc\u00f3n de Magueyes",
    "gn:population":0,
    "gn:timezone":"America/Mexico_City",
    "iso:country":"MX",
    "wof:name":"Rincon de Magueyes",
    "wof:placetype":"locality"
},
  "geometry": {"coordinates":[-102.63333,19.76667],"type":"Point"}
}