{
  "type": "Feature",
  "properties": {
    "gn:admin1_code":"6",
    "gn:admin2_code":"9.0",
    "gn:asciiname":"Racochique",
    "gn:country_code":"MX",
    "gn:dem":2339,
    "gn:feature_class":"P",
    "gn:feature_code":"PPL",
    "gn:name":"Racochique",
    "gn:population":0,
    "gn:timezone":"America/Chihuahua",
    "iso:country":"MX",
    "name:spa_x_preferred":[
        "Racochique"
    ],
    "wof:name":"Racochique",
    "wof:placetype":"locality"
},
  "geometry": {"coordinates":[-107.66048000000001,27.81827],"type":"Point"}
}