{
  "type": "Feature",
  "properties": {
    "gn:admin1_code":"6.0",
    "gn:asciiname":"Las Canoas",
    "gn:country_code":"MX",
    "gn:dem":1867,
    "gn:feature_class":"P",
    "gn:feature_code":"PPL",
    "gn:name":"Las Canoas",
    "gn:population":0,
    "gn:timezone":"America/Chihuahua",
    "iso:country":"MX",
    "name:spa_x_preferred":[
        "Las Canoas"
    ],
    "wof:name":"Las Canoas",
    "wof:placetype":"locality"
},
  "geometry": {"coordinates":[-105.73735000000001,26.96969],"type":"Point"}
}