{
  "type": "Feature",
  "properties": {
    "gn:admin1_code":"4.0",
    "gn:asciiname":"El Pucte",
    "gn:country_code":"MX",
    "gn:dem":-1,
    "gn:feature_class":"P",
    "gn:feature_code":"PPL",
    "gn:name":"El Puct\u00e9",
    "gn:population":0,
    "gn:timezone":"America/Merida",
    "iso:country":"MX",
    "name:spa_x_preferred":[
        "El Puct\u00e9"
    ],
    "wof:name":"El Pucte",
    "wof:placetype":"locality"
},
  "geometry": {"coordinates":[-91.59918999999999,18.28282],"type":"Point"}
}