{
  "type": "Feature",
  "properties": {
    "gn:admin1_code":"26",
    "gn:admin2_code":"30.0",
    "gn:asciiname":"Santa Eduwiges",
    "gn:country_code":"MX",
    "gn:dem":69,
    "gn:feature_class":"P",
    "gn:feature_code":"PPL",
    "gn:name":"Santa Eduwiges",
    "gn:population":0,
    "gn:timezone":"America/Hermosillo",
    "iso:country":"MX",
    "name:und_x_variant":[
        "Rancho Santa Hedubijes",
        "Santa Eduwiges"
    ],
    "wof:name":"Santa Eduwiges",
    "wof:placetype":"locality"
},
  "geometry": {"coordinates":[-111.52907999999999,29.07079],"type":"Point"}
}