{
  "type": "Feature",
  "properties": {
    "gn:admin1_code":"13.0",
    "gn:admin2_code":"60.0",
    "gn:asciiname":"Los Planes de Santiago",
    "gn:country_code":"MX",
    "gn:dem":1056,
    "gn:feature_class":"P",
    "gn:feature_code":"PPL",
    "gn:name":"Los Planes de Santiago",
    "gn:population":0,
    "gn:timezone":"America/Mexico_City",
    "iso:country":"MX",
    "name:spa_x_preferred":[
        "Los Planes de Santiago"
    ],
    "wof:name":"Los Planes de Santiago",
    "wof:placetype":"locality"
},
  "geometry": {"coordinates":[-98.13337,20.3909],"type":"Point"}
}