{
  "type": "Feature",
  "properties": {
    "gn:admin1_code":"12",
    "gn:admin2_code":"22",
    "gn:asciiname":"Rio del Oro",
    "gn:country_code":"MX",
    "gn:dem":394,
    "gn:feature_class":"P",
    "gn:feature_code":"PPL",
    "gn:name":"R\u00edo del Oro",
    "gn:population":36,
    "gn:timezone":"America/Mexico_City",
    "iso:country":"MX",
    "name:und_x_variant":[
        "R\u00edo del Oro"
    ],
    "wof:name":"Rio del Oro",
    "wof:placetype":"locality",
    "wof:population":36
},
  "geometry": {"coordinates":[-100.8891,18.21608],"type":"Point"}
}