{
  "type": "Feature",
  "properties": {
    "gn:admin1_code":"11",
    "gn:admin2_code":"27.0",
    "gn:asciiname":"Uruetaro",
    "gn:country_code":"MX",
    "gn:dem":1719,
    "gn:feature_class":"P",
    "gn:feature_code":"PPL",
    "gn:name":"Uru\u00e9taro",
    "gn:population":831,
    "gn:timezone":"America/Mexico_City",
    "iso:country":"MX",
    "name:spa_x_preferred":[
        "Uru\u00e9taro"
    ],
    "wof:name":"Uruetaro",
    "wof:placetype":"locality",
    "wof:population":831
},
  "geometry": {"coordinates":[-101.18098999999999,20.51741],"type":"Point"}
}