{
  "type": "Feature",
  "properties": {
    "gn:admin1_code":"30.0",
    "gn:admin2_code":"48.0",
    "gn:asciiname":"Las Piedritas",
    "gn:country_code":"MX",
    "gn:dem":23,
    "gn:feature_class":"P",
    "gn:feature_code":"PPL",
    "gn:name":"Las Piedritas",
    "gn:population":0,
    "gn:timezone":"America/Mexico_City",
    "iso:country":"MX",
    "name:spa_x_preferred":[
        "Las Piedritas"
    ],
    "wof:name":"Las Piedritas",
    "wof:placetype":"locality"
},
  "geometry": {"coordinates":[-94.66775,17.88188],"type":"Point"}
}