{
  "type": "Feature",
  "properties": {
    "gn:admin1_code":"2",
    "gn:admin2_code":"2.0",
    "gn:asciiname":"Playa Grande",
    "gn:country_code":"MX",
    "gn:dem":4,
    "gn:feature_class":"P",
    "gn:feature_code":"PPL",
    "gn:name":"Playa Grande",
    "gn:population":0,
    "gn:timezone":"America/Tijuana",
    "iso:country":"MX",
    "name:ceb_x_preferred":[
        "Playa Grande"
    ],
    "name:fra_x_preferred":[
        "Playa Grande"
    ],
    "name:spa_x_preferred":[
        "Playa Grande"
    ],
    "name:swe_x_preferred":[
        "Playa Grande"
    ],
    "wof:name":"Playa Grande",
    "wof:placetype":"locality"
},
  "geometry": {"coordinates":[-114.89112,31.17021],"type":"Point"}
}