{
  "type": "Feature",
  "properties": {
    "gn:admin1_code":"12",
    "gn:admin2_code":"60.0",
    "gn:asciiname":"San Gregorio",
    "gn:country_code":"MX",
    "gn:dem":1550,
    "gn:feature_class":"P",
    "gn:feature_code":"PPL",
    "gn:name":"San Gregorio",
    "gn:population":0,
    "gn:timezone":"America/Mexico_City",
    "iso:country":"MX",
    "name:ceb_x_preferred":[
        "San Gregorio"
    ],
    "name:ces_x_preferred":[
        "San Gregorio"
    ],
    "name:deu_x_preferred":[
        "San Gregorio"
    ],
    "name:fra_x_preferred":[
        "San Gregorio"
    ],
    "name:glg_x_preferred":[
        "San Gregorio"
    ],
    "name:ita_x_preferred":[
        "San Gregorio"
    ],
    "name:nld_x_preferred":[
        "San Gregorio"
    ],
    "name:por_x_preferred":[
        "San Gregorio"
    ],
    "name:sco_x_preferred":[
        "San Gregorio"
    ],
    "name:spa_x_preferred":[
        "San Gregorio"
    ],
    "name:srp_x_preferred":[
        "San Gregorio"
    ],
    "name:swe_x_preferred":[
        "San Gregorio"
    ],
    "wof:name":"San Gregorio",
    "wof:placetype":"locality"
},
  "geometry": {"coordinates":[-99.59386000000001,18.62967],"type":"Point"}
}