{
  "type": "Feature",
  "properties": {
    "gn:admin1_code":"19",
    "gn:admin2_code":"5.0",
    "gn:asciiname":"Santa Teresa",
    "gn:country_code":"MX",
    "gn:dem":142,
    "gn:feature_class":"P",
    "gn:feature_code":"PPL",
    "gn:name":"Santa Teresa",
    "gn:population":6,
    "gn:timezone":"America/Matamoros",
    "iso:country":"MX",
    "wof:name":"Santa Teresa",
    "wof:placetype":"locality",
    "wof:population":6
},
  "geometry": {"coordinates":[-99.86949,26.89142],"type":"Point"}
}