{
  "type": "Feature",
  "properties": {
    "gn:admin1_code":"16.0",
    "gn:admin2_code":"15.0",
    "gn:asciiname":"Mata de Chayote",
    "gn:country_code":"MX",
    "gn:dem":1877,
    "gn:feature_class":"P",
    "gn:feature_code":"PPL",
    "gn:name":"Mata de Chayote",
    "gn:population":0,
    "gn:timezone":"America/Mexico_City",
    "iso:country":"MX",
    "name:spa_x_preferred":[
        "Mata de Chayote"
    ],
    "wof:name":"Mata de Chayote",
    "wof:placetype":"locality"
},
  "geometry": {"coordinates":[-103.28232,18.58511],"type":"Point"}
}