{
  "type": "Feature",
  "properties": {
    "gn:admin1_code":"16.0",
    "gn:admin2_code":"34.0",
    "gn:asciiname":"Huaniqueo",
    "gn:country_code":"MX",
    "gn:dem":1959,
    "gn:feature_class":"P",
    "gn:feature_code":"PPL",
    "gn:name":"Huaniqueo",
    "gn:population":476,
    "gn:timezone":"America/Mexico_City",
    "iso:country":"MX",
    "name:spa_x_preferred":[
        "Huaniqueo"
    ],
    "wof:name":"Huaniqueo",
    "wof:placetype":"locality",
    "wof:population":476
},
  "geometry": {"coordinates":[-100.52527000000001,19.64995],"type":"Point"}
}