{
  "type": "Feature",
  "properties": {
    "gn:admin1_code":"14",
    "gn:admin2_code":"19.0",
    "gn:asciiname":"La Capilla",
    "gn:country_code":"MX",
    "gn:dem":1239,
    "gn:feature_class":"P",
    "gn:feature_code":"PPL",
    "gn:name":"La Capilla",
    "gn:population":0,
    "gn:timezone":"America/Mexico_City",
    "iso:country":"MX",
    "name:spa_x_preferred":[
        "La Capilla"
    ],
    "name:und_x_variant":[
        "Los Hornitos"
    ],
    "wof:name":"La Capilla",
    "wof:placetype":"locality"
},
  "geometry": {"coordinates":[-103.70384,21.89299],"type":"Point"}
}