{
  "type": "Feature",
  "properties": {
    "gn:admin1_code":"5",
    "gn:admin2_code":"6.0",
    "gn:asciiname":"El Apazotal",
    "gn:country_code":"MX",
    "gn:dem":1307,
    "gn:feature_class":"P",
    "gn:feature_code":"PPL",
    "gn:name":"El Apazotal",
    "gn:population":7,
    "gn:timezone":"America/Mexico_City",
    "iso:country":"MX",
    "wof:name":"El Apazotal",
    "wof:placetype":"locality",
    "wof:population":7
},
  "geometry": {"coordinates":[-92.09806,15.55056],"type":"Point"}
}