{
  "type": "Feature",
  "properties": {
    "gn:admin1_code":"21",
    "gn:admin2_code":"1",
    "gn:asciiname":"San Antonio Conocido",
    "gn:country_code":"MX",
    "gn:dem":2520,
    "gn:feature_class":"P",
    "gn:feature_code":"PPL",
    "gn:name":"San Antonio Conocido",
    "gn:population":15,
    "gn:timezone":"America/Mexico_City",
    "iso:country":"MX",
    "wof:name":"San Antonio Conocido",
    "wof:placetype":"locality",
    "wof:population":15
},
  "geometry": {"coordinates":[-97.9419,19.13235],"type":"Point"}
}