{
  "type": "Feature",
  "properties": {
    "gn:admin1_code":"14.0",
    "gn:admin2_code":"38.0",
    "gn:asciiname":"Cerro Colorado",
    "gn:country_code":"MX",
    "gn:dem":1289,
    "gn:feature_class":"P",
    "gn:feature_code":"PPL",
    "gn:name":"Cerro Colorado",
    "gn:population":0,
    "gn:timezone":"America/Mexico_City",
    "iso:country":"MX",
    "name:spa_x_preferred":[
        "Cerro Colorado"
    ],
    "name:spa_x_variant":[
        "Cerro Alto"
    ],
    "wof:name":"Cerro Colorado",
    "wof:placetype":"locality"
},
  "geometry": {"coordinates":[-104.35133999999999,20.69703],"type":"Point"}
}