{
  "type": "Feature",
  "properties": {
    "gn:admin1_code":"19",
    "gn:admin2_code":"38.0",
    "gn:asciiname":"Leal [Avicola]",
    "gn:country_code":"MX",
    "gn:dem":416,
    "gn:feature_class":"P",
    "gn:feature_code":"PPL",
    "gn:name":"Leal [Av\u00edcola]",
    "gn:population":8,
    "gn:timezone":"America/Monterrey",
    "iso:country":"MX",
    "name:und_x_variant":[
        "Leal [Av\u00edcola]"
    ],
    "wof:name":"Leal [Avicola]",
    "wof:placetype":"locality",
    "wof:population":8
},
  "geometry": {"coordinates":[-99.96418,25.26784],"type":"Point"}
}