{
  "type": "Feature",
  "properties": {
    "gn:admin1_code":"26",
    "gn:admin2_code":"30.0",
    "gn:asciiname":"Santa Cecilia",
    "gn:country_code":"MX",
    "gn:dem":25,
    "gn:feature_class":"P",
    "gn:feature_code":"PPL",
    "gn:name":"Santa Cecilia",
    "gn:population":0,
    "gn:timezone":"America/Hermosillo",
    "iso:country":"MX",
    "name:spa_x_preferred":[
        "Santa Cecilia"
    ],
    "wof:name":"Santa Cecilia",
    "wof:placetype":"locality"
},
  "geometry": {"coordinates":[-111.68444,28.83694],"type":"Point"}
}