{
  "type": "Feature",
  "properties": {
    "gn:admin1_code":"28.0",
    "gn:admin2_code":"19.0",
    "gn:asciiname":"Los Manantiales",
    "gn:country_code":"MX",
    "gn:dem":315,
    "gn:feature_class":"P",
    "gn:feature_code":"PPL",
    "gn:name":"Los Manantiales",
    "gn:population":1,
    "gn:timezone":"America/Monterrey",
    "iso:country":"MX",
    "name:spa_x_preferred":[
        "Los Manantiales"
    ],
    "wof:name":"Los Manantiales",
    "wof:placetype":"locality",
    "wof:population":1
},
  "geometry": {"coordinates":[-98.97892,23.46845],"type":"Point"}
}