{
  "type": "Feature",
  "properties": {
    "gn:admin1_code":"16.0",
    "gn:admin2_code":"15.0",
    "gn:asciiname":"Puerto de las Cruces",
    "gn:country_code":"MX",
    "gn:dem":1356,
    "gn:feature_class":"P",
    "gn:feature_code":"PPL",
    "gn:name":"Puerto de las Cruces",
    "gn:population":0,
    "gn:timezone":"America/Mexico_City",
    "iso:country":"MX",
    "name:spa_x_preferred":[
        "Puerto de las Cruces"
    ],
    "wof:name":"Puerto de las Cruces",
    "wof:placetype":"locality"
},
  "geometry": {"coordinates":[-103.12399000000001,18.92401],"type":"Point"}
}