{
  "type": "Feature",
  "properties": {
    "gn:admin1_code":"7.0",
    "gn:admin2_code":"30.0",
    "gn:asciiname":"Ejido El Pino",
    "gn:country_code":"MX",
    "gn:dem":2051,
    "gn:feature_class":"P",
    "gn:feature_code":"PPL",
    "gn:name":"Ejido El Pino",
    "gn:population":0,
    "gn:timezone":"America/Monterrey",
    "iso:country":"MX",
    "wof:name":"Ejido El Pino",
    "wof:placetype":"locality"
},
  "geometry": {"coordinates":[-101.25,25.18333],"type":"Point"}
}