{
  "type": "Feature",
  "properties": {
    "gn:admin1_code":"31",
    "gn:admin2_code":"84.0",
    "gn:asciiname":"Pichichen",
    "gn:country_code":"MX",
    "gn:dem":8,
    "gn:feature_class":"P",
    "gn:feature_code":"PPL",
    "gn:name":"Pichich\u00e9n",
    "gn:population":6,
    "gn:timezone":"America/Merida",
    "iso:country":"MX",
    "name:und_x_variant":[
        "Pichich\u00e9n"
    ],
    "wof:name":"Pichichen",
    "wof:placetype":"locality",
    "wof:population":6
},
  "geometry": {"coordinates":[-88.91806,21.13528],"type":"Point"}
}