{
  "type": "Feature",
  "properties": {
    "gn:admin1_code":"24",
    "gn:admin2_code":"50",
    "gn:asciiname":"La Alcoholera",
    "gn:country_code":"MX",
    "gn:dem":1802,
    "gn:feature_class":"P",
    "gn:feature_code":"PPL",
    "gn:name":"La Alcoholera",
    "gn:population":25,
    "gn:timezone":"America/Mexico_City",
    "iso:country":"MX",
    "wof:name":"La Alcoholera",
    "wof:placetype":"locality",
    "wof:population":25
},
  "geometry": {"coordinates":[-100.87166999999999,21.89278],"type":"Point"}
}