{
  "type": "Feature",
  "properties": {
    "gn:admin1_code":"15.0",
    "gn:asciiname":"El Tecojote",
    "gn:country_code":"MX",
    "gn:dem":2258,
    "gn:feature_class":"P",
    "gn:feature_code":"PPL",
    "gn:name":"El Tecojote",
    "gn:population":0,
    "gn:timezone":"America/Mexico_City",
    "iso:country":"MX",
    "name:spa_x_preferred":[
        "El Tecojote"
    ],
    "wof:name":"El Tecojote",
    "wof:placetype":"locality"
},
  "geometry": {"coordinates":[-99.42269,19.8432],"type":"Point"}
}