{
  "type": "Feature",
  "properties": {
    "gn:admin1_code":"24",
    "gn:admin2_code":"28",
    "gn:asciiname":"Gonzalitos",
    "gn:country_code":"MX",
    "gn:dem":1750,
    "gn:feature_class":"P",
    "gn:feature_code":"PPL",
    "gn:name":"Gonzalitos",
    "gn:population":39,
    "gn:timezone":"America/Mexico_City",
    "iso:country":"MX",
    "wof:name":"Gonzalitos",
    "wof:placetype":"locality",
    "wof:population":39
},
  "geometry": {"coordinates":[-101.06361,22.465],"type":"Point"}
}