{
  "type": "Feature",
  "properties": {
    "gn:admin1_code":"28",
    "gn:admin2_code":"39.0",
    "gn:asciiname":"San Juanito",
    "gn:country_code":"MX",
    "gn:dem":2134,
    "gn:feature_class":"P",
    "gn:feature_code":"PPL",
    "gn:name":"San Juanito",
    "gn:population":0,
    "gn:timezone":"America/Monterrey",
    "iso:country":"MX",
    "wof:name":"San Juanito",
    "wof:placetype":"locality"
},
  "geometry": {"coordinates":[-99.59999999999999,23.05],"type":"Point"}
}