{
  "type": "Feature",
  "properties": {
    "gn:admin1_code":"19.0",
    "gn:admin2_code":"27.0",
    "gn:asciiname":"El Papalote",
    "gn:country_code":"MX",
    "gn:dem":191,
    "gn:feature_class":"P",
    "gn:feature_code":"PPL",
    "gn:name":"El Papalote",
    "gn:population":0,
    "gn:timezone":"America/Monterrey",
    "iso:country":"MX",
    "name:spa_x_preferred":[
        "El Papalote"
    ],
    "wof:name":"El Papalote",
    "wof:placetype":"locality"
},
  "geometry": {"coordinates":[-99.48638,25.9681],"type":"Point"}
}