{
  "type": "Feature",
  "properties": {
    "gn:admin1_code":"14",
    "gn:admin2_code":"97.0",
    "gn:asciiname":"Sendero Real",
    "gn:country_code":"MX",
    "gn:dem":1532,
    "gn:feature_class":"P",
    "gn:feature_code":"PPL",
    "gn:name":"Sendero Real",
    "gn:population":604,
    "gn:timezone":"America/Mexico_City",
    "iso:country":"MX",
    "wof:name":"Sendero Real",
    "wof:placetype":"locality",
    "wof:population":604
},
  "geometry": {"coordinates":[-103.35167,20.52806],"type":"Point"}
}