{
  "type": "Feature",
  "properties": {
    "gn:admin1_code":"5",
    "gn:admin2_code":"46",
    "gn:asciiname":"Monte Sinai",
    "gn:country_code":"MX",
    "gn:dem":836,
    "gn:feature_class":"P",
    "gn:feature_code":"PPL",
    "gn:name":"Monte Sina\u00ed",
    "gn:population":28,
    "gn:timezone":"America/Mexico_City",
    "iso:country":"MX",
    "name:und_x_variant":[
        "Monte Sina\u00ed"
    ],
    "wof:name":"Monte Sinai",
    "wof:placetype":"locality",
    "wof:population":28
},
  "geometry": {"coordinates":[-93.52639000000001,16.45361],"type":"Point"}
}