{
  "type": "Feature",
  "properties": {
    "gn:admin1_code":"6.0",
    "gn:admin2_code":"12.0",
    "gn:asciiname":"Huacharachic",
    "gn:country_code":"MX",
    "gn:dem":2360,
    "gn:feature_class":"P",
    "gn:feature_code":"PPL",
    "gn:name":"Huacharachic",
    "gn:population":0,
    "gn:timezone":"America/Chihuahua",
    "iso:country":"MX",
    "name:und_x_variant":[
        "San Carlos",
        "Guacharachic",
        "Huacharachic"
    ],
    "wof:name":"Huacharachic",
    "wof:placetype":"locality"
},
  "geometry": {"coordinates":[-106.92858,27.89719],"type":"Point"}
}