{
  "type": "Feature",
  "properties": {
    "gn:admin1_code":"25",
    "gn:admin2_code":"17.0",
    "gn:asciiname":"El Palotal",
    "gn:country_code":"MX",
    "gn:dem":41,
    "gn:feature_class":"P",
    "gn:feature_code":"PPL",
    "gn:name":"El Palotal",
    "gn:population":0,
    "gn:timezone":"America/Mazatlan",
    "iso:country":"MX",
    "name:spa_x_preferred":[
        "El Palotal"
    ],
    "name:und_x_variant":[
        "Palotal"
    ],
    "wof:name":"El Palotal",
    "wof:placetype":"locality"
},
  "geometry": {"coordinates":[-108.48086000000001,25.76933],"type":"Point"}
}