{
  "type": "Feature",
  "properties": {
    "gn:admin1_code":"30.0",
    "gn:asciiname":"El Escorial",
    "gn:country_code":"MX",
    "gn:dem":129,
    "gn:feature_class":"P",
    "gn:feature_code":"PPL",
    "gn:name":"El Escorial",
    "gn:population":0,
    "gn:timezone":"America/Mexico_City",
    "iso:country":"MX",
    "name:spa_x_preferred":[
        "El Escorial"
    ],
    "wof:name":"El Escorial",
    "wof:placetype":"locality"
},
  "geometry": {"coordinates":[-95.05065999999999,17.87735],"type":"Point"}
}