{
  "type": "Feature",
  "properties": {
    "gn:admin1_code":"30",
    "gn:admin2_code":"109.0",
    "gn:asciiname":"Villa Nueva",
    "gn:country_code":"MX",
    "gn:dem":964,
    "gn:feature_class":"P",
    "gn:feature_code":"PPL",
    "gn:name":"Villa Nueva",
    "gn:population":367,
    "gn:timezone":"America/Mexico_City",
    "iso:country":"MX",
    "wof:name":"Villa Nueva",
    "wof:placetype":"locality",
    "wof:population":367
},
  "geometry": {"coordinates":[-96.86709999999999,19.77268],"type":"Point"}
}