{
  "type": "Feature",
  "properties": {
    "gn:admin1_code":"5",
    "gn:admin2_code":"65.0",
    "gn:asciiname":"El Remolino",
    "gn:country_code":"MX",
    "gn:dem":74,
    "gn:feature_class":"P",
    "gn:feature_code":"PPL",
    "gn:name":"El Remolino",
    "gn:population":4,
    "gn:timezone":"America/Mexico_City",
    "iso:country":"MX",
    "name:fra_x_preferred":[
        "El Remolino"
    ],
    "name:spa_x_preferred":[
        "El Remolino"
    ],
    "wof:name":"El Remolino",
    "wof:placetype":"locality",
    "wof:population":4
},
  "geometry": {"coordinates":[-91.91028,17.55222],"type":"Point"}
}