{
  "type": "Feature",
  "properties": {
    "gn:admin1_code":"30",
    "gn:admin2_code":"178.0",
    "gn:asciiname":"Arroyo de la Barranca",
    "gn:country_code":"MX",
    "gn:dem":5,
    "gn:feature_class":"P",
    "gn:feature_code":"PPL",
    "gn:name":"Arroyo de la Barranca",
    "gn:population":0,
    "gn:timezone":"America/Mexico_City",
    "iso:country":"MX",
    "name:spa_x_preferred":[
        "Arroyo de la Barranca"
    ],
    "name:und_x_variant":[
        "Arroyo Barranca"
    ],
    "wof:name":"Arroyo de la Barranca",
    "wof:placetype":"locality"
},
  "geometry": {"coordinates":[-95.63701,18.66501],"type":"Point"}
}