{
  "type": "Feature",
  "properties": {
    "gn:admin1_code":"6.0",
    "gn:admin2_code":"15.0",
    "gn:asciiname":"Julimes",
    "gn:country_code":"MX",
    "gn:dem":922,
    "gn:feature_class":"P",
    "gn:feature_code":"PPL",
    "gn:name":"Julimes",
    "gn:population":0,
    "gn:timezone":"America/Chihuahua",
    "iso:country":"MX",
    "name:por_x_preferred":[
        "Julimes"
    ],
    "name:rus_x_preferred":[
        "\u0425\u0443\u043b\u0438\u043c\u0435\u0441"
    ],
    "name:sco_x_preferred":[
        "Julimes"
    ],
    "name:spa_x_preferred":[
        "Julimes"
    ],
    "name:srp_x_preferred":[
        "\u0425\u0443\u043b\u0438\u043c\u0435\u0441"
    ],
    "wof:name":"Julimes",
    "wof:placetype":"locality"
},
  "geometry": {"coordinates":[-104.92828,29.37584],"type":"Point"}
}