{
  "type": "Feature",
  "properties": {
    "gn:admin1_code":"6.0",
    "gn:admin2_code":"52.0",
    "gn:asciiname":"Cerros Colorados",
    "gn:country_code":"MX",
    "gn:dem":850,
    "gn:feature_class":"P",
    "gn:feature_code":"PPL",
    "gn:name":"Cerros Colorados",
    "gn:population":3,
    "gn:timezone":"America/Ojinaga",
    "iso:country":"MX",
    "name:spa_x_preferred":[
        "Cerros Colorados"
    ],
    "wof:name":"Cerros Colorados",
    "wof:placetype":"locality",
    "wof:population":3
},
  "geometry": {"coordinates":[-104.70052,30.19761],"type":"Point"}
}