{
  "type": "Feature",
  "properties": {
    "gn:admin1_code":"11",
    "gn:admin2_code":"20",
    "gn:asciiname":"Kilometro Ocho [Gasolinera]",
    "gn:country_code":"MX",
    "gn:dem":2042,
    "gn:feature_class":"P",
    "gn:feature_code":"PPL",
    "gn:name":"Kil\u00f3metro Ocho [Gasolinera]",
    "gn:population":19,
    "gn:timezone":"America/Mexico_City",
    "iso:country":"MX",
    "name:und_x_variant":[
        "Kil\u00f3metro Ocho [Gasolinera]"
    ],
    "wof:name":"Kilometro Ocho [Gasolinera]",
    "wof:placetype":"locality",
    "wof:population":19
},
  "geometry": {"coordinates":[-101.74417,21.18417],"type":"Point"}
}