{
  "type": "Feature",
  "properties": {
    "gn:admin1_code":"13",
    "gn:admin2_code":"7",
    "gn:asciiname":"San Antonio Alconedo",
    "gn:country_code":"MX",
    "gn:dem":2599,
    "gn:feature_class":"P",
    "gn:feature_code":"PPL",
    "gn:name":"San Antonio Alconedo",
    "gn:population":49,
    "gn:timezone":"America/Mexico_City",
    "iso:country":"MX",
    "wof:name":"San Antonio Alconedo",
    "wof:placetype":"locality",
    "wof:population":49
},
  "geometry": {"coordinates":[-98.38597,19.70955],"type":"Point"}
}