{
  "type": "Feature",
  "properties": {
    "gn:admin1_code":"19",
    "gn:admin2_code":"4",
    "gn:asciiname":"Villas de San Antonio",
    "gn:country_code":"MX",
    "gn:dem":427,
    "gn:feature_class":"P",
    "gn:feature_code":"PPL",
    "gn:name":"Villas de San Antonio",
    "gn:population":13,
    "gn:timezone":"America/Monterrey",
    "iso:country":"MX",
    "wof:name":"Villas de San Antonio",
    "wof:placetype":"locality",
    "wof:population":13
},
  "geometry": {"coordinates":[-100.03444,25.31528],"type":"Point"}
}