{
  "type": "Feature",
  "properties": {
    "gn:admin1_code":"7",
    "gn:admin2_code":"27.0",
    "gn:asciiname":"Los Ojitos",
    "gn:country_code":"MX",
    "gn:dem":1230,
    "gn:feature_class":"P",
    "gn:feature_code":"PPL",
    "gn:name":"Los Ojitos",
    "gn:population":0,
    "gn:timezone":"America/Monterrey",
    "iso:country":"MX",
    "name:spa_x_preferred":[
        "Los Ojitos"
    ],
    "wof:name":"Los Ojitos",
    "wof:placetype":"locality"
},
  "geometry": {"coordinates":[-100.94754,25.64309],"type":"Point"}
}