{
  "type": "Feature",
  "properties": {
    "gn:admin1_code":"17",
    "gn:admin2_code":"17.0",
    "gn:asciiname":"El Arco",
    "gn:country_code":"MX",
    "gn:dem":1049,
    "gn:feature_class":"P",
    "gn:feature_code":"PPL",
    "gn:name":"El Arco",
    "gn:population":132,
    "gn:timezone":"America/Mexico_City",
    "iso:country":"MX",
    "wof:name":"El Arco",
    "wof:placetype":"locality",
    "wof:population":132
},
  "geometry": {"coordinates":[-99.24861,18.70139],"type":"Point"}
}