{
  "type": "Feature",
  "properties": {
    "gn:admin1_code":"5.0",
    "gn:asciiname":"Santa Julia",
    "gn:country_code":"MX",
    "gn:dem":1325,
    "gn:feature_class":"P",
    "gn:feature_code":"PPL",
    "gn:name":"Santa Julia",
    "gn:population":0,
    "gn:timezone":"America/Mexico_City",
    "iso:country":"MX",
    "name:spa_x_preferred":[
        "Santa Julia"
    ],
    "wof:name":"Santa Julia",
    "wof:placetype":"locality"
},
  "geometry": {"coordinates":[-93.10803,15.86002],"type":"Point"}
}