{
  "type": "Feature",
  "properties": {
    "gn:admin1_code":"14",
    "gn:admin2_code":"78.0",
    "gn:asciiname":"Llano de los Conejos",
    "gn:country_code":"MX",
    "gn:dem":1892,
    "gn:feature_class":"P",
    "gn:feature_code":"PPL",
    "gn:name":"Llano de los Conejos",
    "gn:population":119,
    "gn:timezone":"America/Mexico_City",
    "iso:country":"MX",
    "wof:name":"Llano de los Conejos",
    "wof:placetype":"locality",
    "wof:population":119
},
  "geometry": {"coordinates":[-102.34889,21.02194],"type":"Point"}
}