{
  "type": "Feature",
  "properties": {
    "gn:admin1_code":"16.0",
    "gn:admin2_code":"102.0",
    "gn:asciiname":"La Mora",
    "gn:country_code":"MX",
    "gn:dem":1608,
    "gn:feature_class":"P",
    "gn:feature_code":"PPL",
    "gn:name":"La Mora",
    "gn:population":0,
    "gn:timezone":"America/Mexico_City",
    "iso:country":"MX",
    "name:spa_x_preferred":[
        "La Mora"
    ],
    "wof:name":"La Mora",
    "wof:placetype":"locality"
},
  "geometry": {"coordinates":[-102.03404999999999,19.40881],"type":"Point"}
}