{
  "type": "Feature",
  "properties": {
    "gn:admin1_code":"23.0",
    "gn:asciiname":"Los Tres Pozos",
    "gn:country_code":"MX",
    "gn:dem":130,
    "gn:feature_class":"P",
    "gn:feature_code":"PPL",
    "gn:name":"Los Tres Pozos",
    "gn:population":0,
    "gn:timezone":"America/Cancun",
    "iso:country":"MX",
    "name:spa_x_preferred":[
        "Los Tres Pozos"
    ],
    "wof:name":"Los Tres Pozos",
    "wof:placetype":"locality"
},
  "geometry": {"coordinates":[-88.93309000000001,18.44025],"type":"Point"}
}