{
  "type": "Feature",
  "properties": {
    "gn:admin1_code":"5",
    "gn:admin2_code":"107.0",
    "gn:asciiname":"El Tizate",
    "gn:country_code":"MX",
    "gn:dem":556,
    "gn:feature_class":"P",
    "gn:feature_code":"PPL",
    "gn:name":"El Tizate",
    "gn:population":4,
    "gn:timezone":"America/Mexico_City",
    "iso:country":"MX",
    "wof:name":"El Tizate",
    "wof:placetype":"locality",
    "wof:population":4
},
  "geometry": {"coordinates":[-93.12448999999999,16.13995],"type":"Point"}
}