{
  "type": "Feature",
  "properties": {
    "gn:admin1_code":"16",
    "gn:admin2_code":"8",
    "gn:asciiname":"El Murcielago",
    "gn:country_code":"MX",
    "gn:dem":538,
    "gn:feature_class":"P",
    "gn:feature_code":"PPL",
    "gn:name":"El Murci\u00e9lago",
    "gn:population":31,
    "gn:timezone":"America/Mexico_City",
    "iso:country":"MX",
    "name:und_x_variant":[
        "El Murci\u00e9lago"
    ],
    "wof:name":"El Murcielago",
    "wof:placetype":"locality",
    "wof:population":31
},
  "geometry": {"coordinates":[-103.52639000000001,18.50694],"type":"Point"}
}