{
  "type": "Feature",
  "properties": {
    "gn:admin1_code":"30",
    "gn:admin2_code":"127.0",
    "gn:asciiname":"La Cuchilla",
    "gn:country_code":"MX",
    "gn:dem":2239,
    "gn:feature_class":"P",
    "gn:feature_code":"PPL",
    "gn:name":"La Cuchilla",
    "gn:population":188,
    "gn:timezone":"America/Mexico_City",
    "iso:country":"MX",
    "wof:name":"La Cuchilla",
    "wof:placetype":"locality",
    "wof:population":188
},
  "geometry": {"coordinates":[-97.16333,18.985],"type":"Point"}
}