{
  "type": "Feature",
  "properties": {
    "gn:admin1_code":"25",
    "gn:admin2_code":"17",
    "gn:asciiname":"La Lagunita",
    "gn:country_code":"MX",
    "gn:dem":1211,
    "gn:feature_class":"P",
    "gn:feature_code":"PPL",
    "gn:name":"La Lagunita",
    "gn:population":11,
    "gn:timezone":"America/Mazatlan",
    "iso:country":"MX",
    "wof:name":"La Lagunita",
    "wof:placetype":"locality",
    "wof:population":11
},
  "geometry": {"coordinates":[-108.06525999999999,26.20823],"type":"Point"}
}