{
  "type": "Feature",
  "properties": {
    "gn:admin1_code":"32",
    "gn:admin2_code":"23.0",
    "gn:asciiname":"La Cantera (La Cantera de Arriba)",
    "gn:country_code":"MX",
    "gn:dem":1253,
    "gn:feature_class":"P",
    "gn:feature_code":"PPL",
    "gn:name":"La Cantera (La Cantera de Arriba)",
    "gn:population":166,
    "gn:timezone":"America/Mexico_City",
    "iso:country":"MX",
    "wof:name":"La Cantera (La Cantera de Arriba)",
    "wof:placetype":"locality",
    "wof:population":166
},
  "geometry": {"coordinates":[-103.12,21.42667],"type":"Point"}
}