{
  "type": "Feature",
  "properties": {
    "gn:admin1_code":"30.0",
    "gn:admin2_code":"174.0",
    "gn:asciiname":"Rancho Tepetaco",
    "gn:country_code":"MX",
    "gn:dem":23,
    "gn:feature_class":"P",
    "gn:feature_code":"PPL",
    "gn:name":"Rancho Tepetaco",
    "gn:population":0,
    "gn:timezone":"America/Mexico_City",
    "iso:country":"MX",
    "name:spa_x_preferred":[
        "Rancho Tepetaco"
    ],
    "name:spa_x_variant":[
        "Tepetaco"
    ],
    "wof:name":"Rancho Tepetaco",
    "wof:placetype":"locality"
},
  "geometry": {"coordinates":[-96.15289,18.62488],"type":"Point"}
}