{
  "type": "Feature",
  "properties": {
    "gn:admin1_code":"14",
    "gn:admin2_code":"124",
    "gn:asciiname":"El Ocote",
    "gn:country_code":"MX",
    "gn:dem":1638,
    "gn:feature_class":"P",
    "gn:feature_code":"PPL",
    "gn:name":"El Ocote",
    "gn:population":45,
    "gn:timezone":"America/Mexico_City",
    "iso:country":"MX",
    "wof:name":"El Ocote",
    "wof:placetype":"locality",
    "wof:population":45
},
  "geometry": {"coordinates":[-103.03778,20.71222],"type":"Point"}
}