{
  "type": "Feature",
  "properties": {
    "gn:admin1_code":"12",
    "gn:admin2_code":"76.0",
    "gn:asciiname":"Loma de la Silla",
    "gn:country_code":"MX",
    "gn:dem":1702,
    "gn:feature_class":"P",
    "gn:feature_code":"PPL",
    "gn:name":"Loma de la Silla",
    "gn:population":261,
    "gn:timezone":"America/Mexico_City",
    "iso:country":"MX",
    "wof:name":"Loma de la Silla",
    "wof:placetype":"locality",
    "wof:population":261
},
  "geometry": {"coordinates":[-98.88916999999999,17.27056],"type":"Point"}
}