{
  "type": "Feature",
  "properties": {
    "gn:admin1_code":"20",
    "gn:admin2_code":"12.0",
    "gn:asciiname":"Santa Maria Tepejipana",
    "gn:country_code":"MX",
    "gn:dem":676,
    "gn:feature_class":"P",
    "gn:feature_code":"PPL",
    "gn:name":"Santa Mar\u00eda Tepejipana",
    "gn:population":549,
    "gn:timezone":"America/Mexico_City",
    "iso:country":"MX",
    "name:und_x_variant":[
        "Santa Mar\u00eda Tepejipana"
    ],
    "wof:name":"Santa Maria Tepejipana",
    "wof:placetype":"locality",
    "wof:population":549
},
  "geometry": {"coordinates":[-96.52833,15.90972],"type":"Point"}
}