{
  "type": "Feature",
  "properties": {
    "gn:admin1_code":"21",
    "gn:admin2_code":"10.0",
    "gn:asciiname":"Cinco de Mayo",
    "gn:country_code":"MX",
    "gn:dem":1314,
    "gn:feature_class":"P",
    "gn:feature_code":"PPL",
    "gn:name":"Cinco de Mayo",
    "gn:population":578,
    "gn:timezone":"America/Mexico_City",
    "iso:country":"MX",
    "wof:name":"Cinco de Mayo",
    "wof:placetype":"locality",
    "wof:population":578
},
  "geometry": {"coordinates":[-97.26833000000001,18.41222],"type":"Point"}
}