{
  "type": "Feature",
  "properties": {
    "gn:admin1_code":"32",
    "gn:admin2_code":"51.0",
    "gn:asciiname":"La Becerra",
    "gn:country_code":"MX",
    "gn:dem":1991,
    "gn:feature_class":"P",
    "gn:feature_code":"PPL",
    "gn:name":"La Becerra",
    "gn:population":5,
    "gn:timezone":"America/Mexico_City",
    "iso:country":"MX",
    "wof:name":"La Becerra",
    "wof:placetype":"locality",
    "wof:population":5
},
  "geometry": {"coordinates":[-102.51639,23.56694],"type":"Point"}
}