{
  "type": "Feature",
  "properties": {
    "gn:admin1_code":"5.0",
    "gn:asciiname":"Los Angeles",
    "gn:country_code":"MX",
    "gn:dem":1685,
    "gn:feature_class":"P",
    "gn:feature_code":"PPL",
    "gn:name":"Los \u00c1ngeles",
    "gn:population":0,
    "gn:timezone":"America/Mexico_City",
    "iso:country":"MX",
    "name:spa_x_preferred":[
        "Los \u00c1ngeles"
    ],
    "wof:name":"Los Angeles",
    "wof:placetype":"locality"
},
  "geometry": {"coordinates":[-92.56297000000001,15.64496],"type":"Point"}
}