{
  "type": "Feature",
  "properties": {
    "gn:admin1_code":"30.0",
    "gn:admin2_code":"155.0",
    "gn:asciiname":"Izotal Cardonal",
    "gn:country_code":"MX",
    "gn:dem":143,
    "gn:feature_class":"P",
    "gn:feature_code":"PPL",
    "gn:name":"Izotal Cardonal",
    "gn:population":275,
    "gn:timezone":"America/Mexico_City",
    "iso:country":"MX",
    "name:spa_x_preferred":[
        "Izotal Cardonal"
    ],
    "wof:name":"Izotal Cardonal",
    "wof:placetype":"locality",
    "wof:population":275
},
  "geometry": {"coordinates":[-98.16806,21.37694],"type":"Point"}
}