{
  "type": "Feature",
  "properties": {
    "gn:admin1_code":"14.0",
    "gn:admin2_code":"116.0",
    "gn:asciiname":"Llano del Tordillo",
    "gn:country_code":"MX",
    "gn:dem":1914,
    "gn:feature_class":"P",
    "gn:feature_code":"PPL",
    "gn:name":"Llano del Tordillo",
    "gn:population":0,
    "gn:timezone":"America/Mexico_City",
    "iso:country":"MX",
    "name:spa_x_preferred":[
        "Llano del Tordillo"
    ],
    "wof:name":"Llano del Tordillo",
    "wof:placetype":"locality"
},
  "geometry": {"coordinates":[-102.57805,21.62504],"type":"Point"}
}