{
  "type": "Feature",
  "properties": {
    "iso:country":"MX",
    "name:cat_x_preferred":[
        "Reforma"
    ],
    "name:eus_x_preferred":[
        "Diario Reforma"
    ],
    "name:nld_x_preferred":[
        "Reforma"
    ],
    "name:nor_x_preferred":[
        "Reforma"
    ],
    "name:que_x_preferred":[
        "Reforma"
    ],
    "name:spa_x_preferred":[
        "Reforma"
    ],
    "qs_pg:aaroncc":"MX",
    "qs_pg:name":"Reforma",
    "qs_pg:name_adm0":"M\u00e9xico",
    "qs_pg:name_adm1":"Puebla",
    "qs_pg:photos":1,
    "qs_pg:photos_1k":1,
    "qs_pg:photos_9k":1,
    "qs_pg:photos_9r":1,
    "qs_pg:photos_all":1,
    "qs_pg:photos_sr":1,
    "qs_pg:pop_sr":0,
    "qs_pg:qs_pg_placetype":"neighbourhood",
    "qs_pg:qs_pg_placetype_gp":"Suburb",
    "qs_pg:woe_adm0":23424900,
    "woe:adm0_id":23424900,
    "woe:name_adm0":"M\u00e9xico",
    "woe:name_adm1":"Puebla",
    "woe:placetype":"Suburb",
    "wof:name":"Reforma",
    "wof:placetype":"neighbourhood"
},
  "geometry": {"coordinates":[-98.198123,19.051019],"type":"Point"}
}