{
  "type": "Feature",
  "properties": {
    "gn:admin1_code":"4.0",
    "gn:asciiname":"El Naranjal",
    "gn:country_code":"MX",
    "gn:dem":92,
    "gn:feature_class":"P",
    "gn:feature_code":"PPL",
    "gn:name":"El Naranjal",
    "gn:population":0,
    "gn:timezone":"America/Merida",
    "iso:country":"MX",
    "name:spa_x_preferred":[
        "El Naranjal"
    ],
    "name:spa_x_variant":[
        "Tres Hermanos"
    ],
    "wof:name":"El Naranjal",
    "wof:placetype":"locality"
},
  "geometry": {"coordinates":[-90.77596,18.48203],"type":"Point"}
}