{
  "type": "Feature",
  "properties": {
    "gn:admin1_code":"12",
    "gn:admin2_code":"47.0",
    "gn:asciiname":"Tepatulco",
    "gn:country_code":"MX",
    "gn:dem":1436,
    "gn:feature_class":"P",
    "gn:feature_code":"PPL",
    "gn:name":"Tepatulco",
    "gn:population":0,
    "gn:timezone":"America/Mexico_City",
    "iso:country":"MX",
    "name:spa_x_preferred":[
        "Tepatulco"
    ],
    "wof:name":"Tepatulco",
    "wof:placetype":"locality"
},
  "geometry": {"coordinates":[-99.90971,18.53678],"type":"Point"}
}