{
  "type": "Feature",
  "properties": {
    "gn:admin1_code":"20",
    "gn:admin2_code":"159.0",
    "gn:asciiname":"Bugambilias",
    "gn:country_code":"MX",
    "gn:dem":1293,
    "gn:feature_class":"P",
    "gn:feature_code":"PPL",
    "gn:name":"Bugambilias",
    "gn:population":99,
    "gn:timezone":"America/Mexico_City",
    "iso:country":"MX",
    "wof:name":"Bugambilias",
    "wof:placetype":"locality",
    "wof:population":99
},
  "geometry": {"coordinates":[-97.03139,16.18333],"type":"Point"}
}