{
  "type": "Feature",
  "properties": {
    "gn:admin1_code":"5",
    "gn:admin2_code":"31",
    "gn:asciiname":"Chumatelha",
    "gn:country_code":"MX",
    "gn:dem":885,
    "gn:feature_class":"P",
    "gn:feature_code":"PPL",
    "gn:name":"Chumatelh\u00e1",
    "gn:population":48,
    "gn:timezone":"America/Mexico_City",
    "iso:country":"MX",
    "name:und_x_variant":[
        "Chumatelh\u00e1"
    ],
    "wof:name":"Chumatelha",
    "wof:placetype":"locality",
    "wof:population":48
},
  "geometry": {"coordinates":[-92.26917,17.11583],"type":"Point"}
}