{
  "type": "Feature",
  "properties": {
    "gn:admin1_code":"19.0",
    "gn:admin2_code":"3.0",
    "gn:asciiname":"El Puerto",
    "gn:country_code":"MX",
    "gn:dem":146,
    "gn:feature_class":"P",
    "gn:feature_code":"PPL",
    "gn:name":"El Puerto",
    "gn:population":0,
    "gn:timezone":"America/Monterrey",
    "iso:country":"MX",
    "name:spa_x_preferred":[
        "El Puerto"
    ],
    "wof:name":"El Puerto",
    "wof:placetype":"locality"
},
  "geometry": {"coordinates":[-99.32644000000001,26.00874],"type":"Point"}
}