{
  "type": "Feature",
  "properties": {
    "gn:admin1_code":"1",
    "gn:admin2_code":"2.0",
    "gn:asciiname":"Rancho San Jose Rosas Azules (El Suspiro)",
    "gn:country_code":"MX",
    "gn:dem":2131,
    "gn:feature_class":"P",
    "gn:feature_code":"PPL",
    "gn:name":"Rancho San Jos\u00e9 Rosas Azules (El Suspiro)",
    "gn:population":8,
    "gn:timezone":"America/Mexico_City",
    "iso:country":"MX",
    "name:und_x_variant":[
        "Rancho San Jos\u00e9 Rosas Azules (El Suspiro)"
    ],
    "wof:name":"Rancho San Jose Rosas Azules (El Suspiro)",
    "wof:placetype":"locality",
    "wof:population":8
},
  "geometry": {"coordinates":[-102.08861,22.25222],"type":"Point"}
}