{
  "type": "Feature",
  "properties": {
    "gn:admin1_code":"26.0",
    "gn:admin2_code":"63.0",
    "gn:asciiname":"La Mina",
    "gn:country_code":"MX",
    "gn:dem":804,
    "gn:feature_class":"P",
    "gn:feature_code":"PPL",
    "gn:name":"La Mina",
    "gn:population":0,
    "gn:timezone":"America/Hermosillo",
    "iso:country":"MX",
    "name:ita_x_preferred":[
        "La Mina"
    ],
    "name:spa_x_preferred":[
        "La Mina"
    ],
    "wof:name":"La Mina",
    "wof:placetype":"locality"
},
  "geometry": {"coordinates":[-109.49703,29.37695],"type":"Point"}
}