{
  "type": "Feature",
  "properties": {
    "gn:admin1_code":"23",
    "gn:asciiname":"X-Kalakonot",
    "gn:country_code":"MX",
    "gn:dem":2,
    "gn:feature_class":"P",
    "gn:feature_code":"PPL",
    "gn:name":"X-Kalakonot",
    "gn:population":0,
    "gn:timezone":"America/Belize",
    "iso:country":"MX",
    "wof:name":"X-Kalakonot",
    "wof:placetype":"locality"
},
  "geometry": {"coordinates":[-88.23333000000002,18.26667],"type":"Point"}
}