{
  "type": "Feature",
  "properties": {
    "gn:admin1_code":"20",
    "gn:admin2_code":"382.0",
    "gn:asciiname":"Cerro Prieto",
    "gn:country_code":"MX",
    "gn:dem":1483,
    "gn:feature_class":"P",
    "gn:feature_code":"PPL",
    "gn:name":"Cerro Prieto",
    "gn:population":336,
    "gn:timezone":"America/Mexico_City",
    "iso:country":"MX",
    "name:hun_x_preferred":[
        "Cerro Prieto"
    ],
    "name:hye_x_preferred":[
        "\u054d\u0565\u057c\u0578 \u054a\u0580\u056b\u0565\u057f\u0578"
    ],
    "name:ita_x_preferred":[
        "Cerro Prieto"
    ],
    "name:slk_x_preferred":[
        "Cerro Prieto"
    ],
    "name:spa_x_preferred":[
        "Cerro Prieto"
    ],
    "wof:name":"Cerro Prieto",
    "wof:placetype":"locality",
    "wof:population":336
},
  "geometry": {"coordinates":[-97.43769,16.91324],"type":"Point"}
}