{
  "type": "Feature",
  "properties": {
    "gn:admin1_code":"7.0",
    "gn:admin2_code":"20.0",
    "gn:asciiname":"Zamora",
    "gn:country_code":"MX",
    "gn:dem":455,
    "gn:feature_class":"P",
    "gn:feature_code":"PPL",
    "gn:name":"Zamora",
    "gn:population":16,
    "gn:timezone":"America/Monterrey",
    "iso:country":"MX",
    "name:spa_x_preferred":[
        "Zamora"
    ],
    "wof:name":"Zamora",
    "wof:placetype":"locality",
    "wof:population":16
},
  "geometry": {"coordinates":[-101.47954,27.88193],"type":"Point"}
}