{
  "type": "Feature",
  "properties": {
    "gn:admin1_code":"25",
    "gn:admin2_code":"12.0",
    "gn:asciiname":"Tiro Nuevo",
    "gn:country_code":"MX",
    "gn:dem":33,
    "gn:feature_class":"P",
    "gn:feature_code":"PPL",
    "gn:name":"Tiro Nuevo",
    "gn:population":0,
    "gn:timezone":"America/Mazatlan",
    "iso:country":"MX",
    "name:spa_x_preferred":[
        "Tiro Nuevo"
    ],
    "wof:name":"Tiro Nuevo",
    "wof:placetype":"locality"
},
  "geometry": {"coordinates":[-106.44981,23.3585],"type":"Point"}
}