{
  "type": "Feature",
  "properties": {
    "gn:admin1_code":"5",
    "gn:admin2_code":"9",
    "gn:asciiname":"Las Margaritas",
    "gn:country_code":"MX",
    "gn:dem":134,
    "gn:feature_class":"P",
    "gn:feature_code":"PPL",
    "gn:name":"Las Margaritas",
    "gn:population":19,
    "gn:timezone":"America/Mexico_City",
    "iso:country":"MX",
    "wof:name":"Las Margaritas",
    "wof:placetype":"locality",
    "wof:population":19
},
  "geometry": {"coordinates":[-93.87528,16.26222000000001],"type":"Point"}
}