{
  "type": "Feature",
  "properties": {
    "gn:admin1_code":"20",
    "gn:admin2_code":"21.0",
    "gn:asciiname":"Cerro Alto",
    "gn:country_code":"MX",
    "gn:dem":353,
    "gn:feature_class":"P",
    "gn:feature_code":"PPL",
    "gn:name":"Cerro Alto",
    "gn:population":96,
    "gn:timezone":"America/Mexico_City",
    "iso:country":"MX",
    "name:ceb_x_preferred":[
        "Cerro Alto"
    ],
    "name:swe_x_preferred":[
        "Cerro Alto"
    ],
    "wof:name":"Cerro Alto",
    "wof:placetype":"locality",
    "wof:population":96
},
  "geometry": {"coordinates":[-96.70889,18.54583],"type":"Point"}
}