{
  "type": "Feature",
  "properties": {
    "gn:admin1_code":"7",
    "gn:admin2_code":"31.0",
    "gn:asciiname":"Las Corrientes",
    "gn:country_code":"MX",
    "gn:dem":1307,
    "gn:feature_class":"P",
    "gn:feature_code":"PPL",
    "gn:name":"Las Corrientes",
    "gn:population":0,
    "gn:timezone":"America/Monterrey",
    "iso:country":"MX",
    "name:spa_x_preferred":[
        "Las Corrientes"
    ],
    "name:und_x_variant":[
        "Rancho Los Correntes"
    ],
    "wof:name":"Las Corrientes",
    "wof:placetype":"locality"
},
  "geometry": {"coordinates":[-102.11621,27.86743],"type":"Point"}
}