{
  "type": "Feature",
  "properties": {
    "gn:admin1_code":"8",
    "gn:admin2_code":"9.0",
    "gn:asciiname":"La Perla",
    "gn:country_code":"MX",
    "gn:dem":29,
    "gn:feature_class":"P",
    "gn:feature_code":"PPL",
    "gn:name":"La Perla",
    "gn:population":6,
    "gn:timezone":"America/Mexico_City",
    "iso:country":"MX",
    "wof:name":"La Perla",
    "wof:placetype":"locality",
    "wof:population":6
},
  "geometry": {"coordinates":[-103.81167000000001,18.87028],"type":"Point"}
}