{
  "type": "Feature",
  "properties": {
    "gn:admin1_code":"12",
    "gn:admin2_code":"31",
    "gn:asciiname":"Hueyatenco",
    "gn:country_code":"MX",
    "gn:dem":1058,
    "gn:feature_class":"P",
    "gn:feature_code":"PPL",
    "gn:name":"Hueyatenco",
    "gn:population":32,
    "gn:timezone":"America/Mexico_City",
    "iso:country":"MX",
    "wof:name":"Hueyatenco",
    "wof:placetype":"locality",
    "wof:population":32
},
  "geometry": {"coordinates":[-100.10341,18.4327],"type":"Point"}
}