{
  "type": "Feature",
  "properties": {
    "gn:admin1_code":"16",
    "gn:admin2_code":"97.0",
    "gn:asciiname":"El Salitre",
    "gn:country_code":"MX",
    "gn:dem":651,
    "gn:feature_class":"P",
    "gn:feature_code":"PPL",
    "gn:name":"El Salitre",
    "gn:population":0,
    "gn:timezone":"America/Mexico_City",
    "iso:country":"MX",
    "name:spa_x_preferred":[
        "El Salitre"
    ],
    "wof:name":"El Salitre",
    "wof:placetype":"locality"
},
  "geometry": {"coordinates":[-101.40107999999999,19.00675],"type":"Point"}
}