{
  "type": "Feature",
  "properties": {
    "gn:admin1_code":"30",
    "gn:admin2_code":"32.0",
    "gn:asciiname":"Pesca",
    "gn:country_code":"MX",
    "gn:dem":10,
    "gn:feature_class":"P",
    "gn:feature_code":"PPL",
    "gn:name":"Pesca",
    "gn:population":5,
    "gn:timezone":"America/Mexico_City",
    "iso:country":"MX",
    "name:ceb_x_preferred":[
        "Pesca"
    ],
    "name:fra_x_preferred":[
        "Pesca"
    ],
    "name:ita_x_preferred":[
        "Pesca"
    ],
    "name:kat_x_preferred":[
        "\u10de\u10d4\u10e1\u10d9\u10d0"
    ],
    "name:msa_x_preferred":[
        "Pesca"
    ],
    "name:nld_x_preferred":[
        "Pesca"
    ],
    "name:por_x_preferred":[
        "Pesca"
    ],
    "name:rus_x_preferred":[
        "\u041f\u0435\u0441\u043a\u0430"
    ],
    "name:spa_x_preferred":[
        "Pesca"
    ],
    "name:swe_x_preferred":[
        "Pesca"
    ],
    "name:tgl_x_preferred":[
        "Pesca"
    ],
    "name:vie_x_preferred":[
        "Pesca"
    ],
    "name:war_x_preferred":[
        "Pesca"
    ],
    "name:zho_x_preferred":[
        "\u4f69\u65af\u5361"
    ],
    "wof:name":"Pesca",
    "wof:placetype":"locality",
    "wof:population":5
},
  "geometry": {"coordinates":[-95.00833,18.56111],"type":"Point"}
}