{
  "type": "Feature",
  "properties": {
    "gn:admin1_code":"30",
    "gn:admin2_code":"105.0",
    "gn:asciiname":"Finca Don Pablo",
    "gn:country_code":"MX",
    "gn:dem":39,
    "gn:feature_class":"P",
    "gn:feature_code":"PPL",
    "gn:name":"Finca Don Pablo",
    "gn:population":5,
    "gn:timezone":"America/Mexico_City",
    "iso:country":"MX",
    "wof:name":"Finca Don Pablo",
    "wof:placetype":"locality",
    "wof:population":5
},
  "geometry": {"coordinates":[-96.11583,18.98611],"type":"Point"}
}