{
  "type": "Feature",
  "properties": {
    "gn:admin1_code":"30",
    "gn:admin2_code":"61.0",
    "gn:asciiname":"Lindavista",
    "gn:country_code":"MX",
    "gn:dem":31,
    "gn:feature_class":"P",
    "gn:feature_code":"PPL",
    "gn:name":"Lindavista",
    "gn:population":110,
    "gn:timezone":"America/Mexico_City",
    "iso:country":"MX",
    "name:fra_x_preferred":[
        "Lindavista"
    ],
    "name:nor_x_preferred":[
        "Lindavista"
    ],
    "name:spa_x_preferred":[
        "Lindavista"
    ],
    "wof:name":"Lindavista",
    "wof:placetype":"locality",
    "wof:population":110
},
  "geometry": {"coordinates":[-93.88500000000001,17.52167],"type":"Point"}
}