{
  "type": "Feature",
  "properties": {
    "gn:admin1_code":"5",
    "gn:admin2_code":"46.0",
    "gn:asciiname":"Los Reyes (La Gloria)",
    "gn:country_code":"MX",
    "gn:dem":711,
    "gn:feature_class":"P",
    "gn:feature_code":"PPL",
    "gn:name":"Los Reyes (La Gloria)",
    "gn:population":7,
    "gn:timezone":"America/Mexico_City",
    "iso:country":"MX",
    "wof:name":"Los Reyes (La Gloria)",
    "wof:placetype":"locality",
    "wof:population":7
},
  "geometry": {"coordinates":[-93.58917,16.70389],"type":"Point"}
}