{
  "type": "Feature",
  "properties": {
    "gn:admin1_code":"31",
    "gn:admin2_code":"44.0",
    "gn:asciiname":"Cehchan",
    "gn:country_code":"MX",
    "gn:dem":11,
    "gn:feature_class":"P",
    "gn:feature_code":"PPL",
    "gn:name":"Cehchan",
    "gn:population":0,
    "gn:timezone":"America/Merida",
    "iso:country":"MX",
    "wof:name":"Cehchan",
    "wof:placetype":"locality"
},
  "geometry": {"coordinates":[-89.97083000000001,20.88639],"type":"Point"}
}