{
  "type": "Feature",
  "properties": {
    "gn:admin1_code":"7",
    "gn:admin2_code":"4",
    "gn:asciiname":"Silvano Padilla (El Mirador)",
    "gn:country_code":"MX",
    "gn:dem":2385,
    "gn:feature_class":"P",
    "gn:feature_code":"PPL",
    "gn:name":"Silvano Padilla (El Mirador)",
    "gn:population":12,
    "gn:timezone":"America/Monterrey",
    "iso:country":"MX",
    "wof:name":"Silvano Padilla (El Mirador)",
    "wof:placetype":"locality",
    "wof:population":12
},
  "geometry": {"coordinates":[-100.51558,25.25116],"type":"Point"}
}