{
  "type": "Feature",
  "properties": {
    "gn:admin1_code":"30",
    "gn:admin2_code":"129",
    "gn:asciiname":"Anacleto Ramos",
    "gn:country_code":"MX",
    "gn:dem":83,
    "gn:feature_class":"P",
    "gn:feature_code":"PPL",
    "gn:name":"Anacleto Ramos",
    "gn:population":36,
    "gn:timezone":"America/Mexico_City",
    "iso:country":"MX",
    "wof:name":"Anacleto Ramos",
    "wof:placetype":"locality",
    "wof:population":36
},
  "geometry": {"coordinates":[-98.42556,21.35889],"type":"Point"}
}