{
  "type": "Feature",
  "properties": {
    "gn:admin1_code":"6.0",
    "gn:admin2_code":"7.0",
    "gn:asciiname":"El Remate",
    "gn:country_code":"MX",
    "gn:dem":2677,
    "gn:feature_class":"P",
    "gn:feature_code":"PPL",
    "gn:name":"El Remate",
    "gn:population":0,
    "gn:timezone":"America/Chihuahua",
    "iso:country":"MX",
    "name:spa_x_preferred":[
        "El Remate"
    ],
    "wof:name":"El Remate",
    "wof:placetype":"locality"
},
  "geometry": {"coordinates":[-106.46299999999999,26.34199000000001],"type":"Point"}
}