{
  "type": "Feature",
  "properties": {
    "gn:admin1_code":"10",
    "gn:admin2_code":"6",
    "gn:asciiname":"El Jazminal",
    "gn:country_code":"MX",
    "gn:dem":1372,
    "gn:feature_class":"P",
    "gn:feature_code":"PPL",
    "gn:name":"El Jazminal",
    "gn:population":9,
    "gn:timezone":"America/Monterrey",
    "iso:country":"MX",
    "wof:name":"El Jazminal",
    "wof:placetype":"locality",
    "wof:population":9
},
  "geometry": {"coordinates":[-103.19864,24.87418],"type":"Point"}
}