{
  "type": "Feature",
  "properties": {
    "gn:admin1_code":"32.0",
    "gn:admin2_code":"49.0",
    "gn:asciiname":"Tatalucas",
    "gn:country_code":"MX",
    "gn:dem":2278,
    "gn:feature_class":"P",
    "gn:feature_code":"PPL",
    "gn:name":"Tatalucas",
    "gn:population":0,
    "gn:timezone":"America/Mexico_City",
    "iso:country":"MX",
    "name:spa_x_preferred":[
        "Tatalucas"
    ],
    "wof:name":"Tatalucas",
    "wof:placetype":"locality"
},
  "geometry": {"coordinates":[-103.70310000000001,22.71289],"type":"Point"}
}