{
  "type": "Feature",
  "properties": {
    "gn:admin1_code":"10.0",
    "gn:admin2_code":"9.0",
    "gn:asciiname":"El Arroyo de Cuevecillas",
    "gn:country_code":"MX",
    "gn:dem":2410,
    "gn:feature_class":"P",
    "gn:feature_code":"PPL",
    "gn:name":"El Arroyo de Cuevecillas",
    "gn:population":0,
    "gn:timezone":"America/Monterrey",
    "iso:country":"MX",
    "name:spa_x_preferred":[
        "El Arroyo de Cuevecillas"
    ],
    "wof:name":"El Arroyo de Cuevecillas",
    "wof:placetype":"locality"
},
  "geometry": {"coordinates":[-106.23895,25.77076],"type":"Point"}
}