{
  "type": "Feature",
  "properties": {
    "gn:admin1_code":"32.0",
    "gn:admin2_code":"28.0",
    "gn:asciiname":"Atravesano",
    "gn:country_code":"MX",
    "gn:dem":1879,
    "gn:feature_class":"P",
    "gn:feature_code":"PPL",
    "gn:name":"Atravesa\u00f1o",
    "gn:population":0,
    "gn:timezone":"America/Mexico_City",
    "iso:country":"MX",
    "wof:name":"Atravesano",
    "wof:placetype":"locality"
},
  "geometry": {"coordinates":[-103.33333,21.13333],"type":"Point"}
}