{
  "type": "Feature",
  "properties": {
    "gn:admin1_code":"26.0",
    "gn:admin2_code":"11.0",
    "gn:asciiname":"Pozo la Chupanita",
    "gn:country_code":"MX",
    "gn:dem":1438,
    "gn:feature_class":"P",
    "gn:feature_code":"PPL",
    "gn:name":"Pozo la Chupanita",
    "gn:population":0,
    "gn:timezone":"America/Hermosillo",
    "iso:country":"MX",
    "name:spa_x_preferred":[
        "Pozo la Chupanita"
    ],
    "wof:name":"Pozo la Chupanita",
    "wof:placetype":"locality"
},
  "geometry": {"coordinates":[-109.94732,30.83443],"type":"Point"}
}