{
  "type": "Feature",
  "properties": {
    "gn:admin1_code":"6",
    "gn:admin2_code":"16.0",
    "gn:asciiname":"El Vallecillo",
    "gn:country_code":"MX",
    "gn:dem":1469,
    "gn:feature_class":"P",
    "gn:feature_code":"PPL",
    "gn:name":"El Vallecillo",
    "gn:population":0,
    "gn:timezone":"America/Chihuahua",
    "iso:country":"MX",
    "name:arg_x_preferred":[
        "Val Longuiello"
    ],
    "name:ast_x_preferred":[
        "El Vallecillo"
    ],
    "name:cat_x_preferred":[
        "El Vallecillo"
    ],
    "name:eus_x_preferred":[
        "El Vallecillo"
    ],
    "name:fas_x_preferred":[
        "\u0627\u0644 \u0628\u0627\u06cc\u0633\u06cc\u06cc\u0648"
    ],
    "name:fra_x_preferred":[
        "El Vallecillo"
    ],
    "name:glg_x_preferred":[
        "El Vallecillo"
    ],
    "name:hun_x_preferred":[
        "El Vallecillo"
    ],
    "name:ita_x_preferred":[
        "El Vallecillo"
    ],
    "name:kaz_x_preferred":[
        "\u042d\u043b\u044c-\u0412\u0430\u043b\u044c\u0435\u0441\u0438\u043b\u044c\u043e"
    ],
    "name:msa_x_preferred":[
        "El Vallecillo"
    ],
    "name:nld_x_preferred":[
        "El Vallecillo"
    ],
    "name:oci_x_preferred":[
        "El Vallecillo"
    ],
    "name:pol_x_preferred":[
        "El Vallecillo"
    ],
    "name:por_x_preferred":[
        "El Vallecillo"
    ],
    "name:rus_x_preferred":[
        "\u042d\u043b\u044c-\u0412\u0430\u043b\u044c\u0435\u0441\u0438\u043b\u044c\u043e"
    ],
    "name:spa_x_preferred":[
        "El Vallecillo"
    ],
    "name:ukr_x_preferred":[
        "\u0415\u043b\u044c-\u0412\u0430\u043b\u044c\u0454\u0441\u0456\u043b\u044c\u0439\u043e"
    ],
    "name:und_x_variant":[
        "Rancho Vallecillo"
    ],
    "name:uzb_x_preferred":[
        "El Vallecillo"
    ],
    "name:vie_x_preferred":[
        "El Vallecillo"
    ],
    "name:war_x_preferred":[
        "El Vallecillo"
    ],
    "name:zho_x_preferred":[
        "\u57c3\u5c14\u74e6\u5217\u897f\u7565"
    ],
    "wof:name":"El Vallecillo",
    "wof:placetype":"locality"
},
  "geometry": {"coordinates":[-104.9605,27.91265],"type":"Point"}
}