{
  "type": "Feature",
  "properties": {
    "gn:admin1_code":"6",
    "gn:admin2_code":"16.0",
    "gn:asciiname":"El Vallecillo",
    "gn:country_code":"MX",
    "gn:dem":1469,
    "gn:feature_class":"P",
    "gn:feature_code":"PPL",
    "gn:name":"El Vallecillo",
    "gn:population":0,
    "gn:timezone":"America/Chihuahua",
    "iso:country":"MX",
    "name:spa_x_preferred":[
        "El Vallecillo"
    ],
    "name:und_x_variant":[
        "Rancho Vallecillo"
    ],
    "wof:name":"El Vallecillo",
    "wof:placetype":"locality"
},
  "geometry": {"coordinates":[-104.9605,27.91265],"type":"Point"}
}