{
  "type": "Feature",
  "properties": {
    "gn:admin1_code":"10",
    "gn:admin2_code":"17.0",
    "gn:asciiname":"Arroyo el Corral",
    "gn:country_code":"MX",
    "gn:dem":2035,
    "gn:feature_class":"P",
    "gn:feature_code":"PPL",
    "gn:name":"Arroyo el Corral",
    "gn:population":0,
    "gn:timezone":"America/Monterrey",
    "iso:country":"MX",
    "name:spa_x_preferred":[
        "La Mina"
    ],
    "name:spa_x_variant":[
        "Arroyo el Corral"
    ],
    "name:und_x_variant":[
        "Rancho La Mina"
    ],
    "wof:name":"Arroyo el Corral",
    "wof:placetype":"locality"
},
  "geometry": {"coordinates":[-105.89449999999999,26.54268],"type":"Point"}
}