{
  "type": "Feature",
  "properties": {
    "gn:admin1_code":"5.0",
    "gn:admin2_code":"107.0",
    "gn:asciiname":"Las Limas",
    "gn:country_code":"MX",
    "gn:dem":959,
    "gn:feature_class":"P",
    "gn:feature_code":"PPL",
    "gn:name":"Las Limas",
    "gn:population":0,
    "gn:timezone":"America/Mexico_City",
    "iso:country":"MX",
    "name:spa_x_preferred":[
        "Las Limas"
    ],
    "wof:name":"Las Limas",
    "wof:placetype":"locality"
},
  "geometry": {"coordinates":[-93.53492,16.14707000000001],"type":"Point"}
}