{
  "type": "Feature",
  "properties": {
    "gn:admin1_code":"13",
    "gn:admin2_code":"37.0",
    "gn:asciiname":"San Antonio Tlaxco",
    "gn:country_code":"MX",
    "gn:dem":1709,
    "gn:feature_class":"P",
    "gn:feature_code":"PPL",
    "gn:name":"San Antonio Tlaxco",
    "gn:population":0,
    "gn:timezone":"America/Mexico_City",
    "iso:country":"MX",
    "name:spa_x_preferred":[
        "San Antonio"
    ],
    "name:und_x_variant":[
        "Acalmanto"
    ],
    "wof:name":"San Antonio Tlaxco",
    "wof:placetype":"locality"
},
  "geometry": {"coordinates":[-98.82120999999999,20.71186],"type":"Point"}
}