{
  "type": "Feature",
  "properties": {
    "gn:admin1_code":"5.0",
    "gn:asciiname":"Tapachulita",
    "gn:country_code":"MX",
    "gn:dem":463,
    "gn:feature_class":"P",
    "gn:feature_code":"PPL",
    "gn:name":"Tapachulita",
    "gn:population":0,
    "gn:timezone":"America/Mexico_City",
    "iso:country":"MX",
    "name:spa_x_preferred":[
        "Tapachulita"
    ],
    "wof:name":"Tapachulita",
    "wof:placetype":"locality"
},
  "geometry": {"coordinates":[-92.26819999999999,15.03707],"type":"Point"}
}