{
  "type": "Feature",
  "properties": {
    "gn:admin1_code":"32.0",
    "gn:admin2_code":"29.0",
    "gn:asciiname":"Delicias Lopez Velarde",
    "gn:country_code":"MX",
    "gn:dem":2215,
    "gn:feature_class":"P",
    "gn:feature_code":"PPL",
    "gn:name":"Delicias L\u00f3pez Velarde",
    "gn:population":0,
    "gn:timezone":"America/Mexico_City",
    "iso:country":"MX",
    "name:spa_x_preferred":[
        "Delicias L\u00f3pez Velarde"
    ],
    "name:spa_x_variant":[
        "El Bueyero"
    ],
    "wof:name":"Delicias Lopez Velarde",
    "wof:placetype":"locality"
},
  "geometry": {"coordinates":[-103.60639999999999,24.06268],"type":"Point"}
}