{
  "type": "Feature",
  "properties": {
    "gn:admin1_code":"26.0",
    "gn:admin2_code":"66.0",
    "gn:asciiname":"El Alamo",
    "gn:country_code":"MX",
    "gn:dem":474,
    "gn:feature_class":"P",
    "gn:feature_code":"PPL",
    "gn:name":"El \u00c1lamo",
    "gn:population":0,
    "gn:timezone":"America/Hermosillo",
    "iso:country":"MX",
    "name:und_x_variant":[
        "Rancho Alamo",
        "Alamo",
        "El \u00c1lamo"
    ],
    "wof:name":"El Alamo",
    "wof:placetype":"locality"
},
  "geometry": {"coordinates":[-110.29436,29.33596],"type":"Point"}
}