{
  "type": "Feature",
  "properties": {
    "gn:country":"MX",
    "gn:fcode":"PPL",
    "gn:population":0,
    "iso:country":"MX",
    "name:eng_x_preferred":[
        "Valle Alto"
    ],
    "name:nld_x_preferred":[
        "Valle Alto"
    ],
    "name:rus_x_preferred":[
        "\u0412\u0430\u043b\u044c\u0435-\u0410\u043b\u044c\u0442\u043e"
    ],
    "name:spa_x_preferred":[
        "Valle Alto"
    ],
    "qs:gn_adm0_cc":"MX",
    "qs:gn_fcode":"PPL",
    "qs:gn_local":3995465,
    "qs:gn_nam_loc":"Monterrey, Monterrey, Nuevo Leon, MX",
    "qs:gn_namadm1":"19",
    "qs:gn_name":"Valle Alto",
    "qs:local_max":2766,
    "qs:local_sum":15661,
    "qs:localhoods":40,
    "qs:name":"Valle Alto",
    "qs:name_adm0":"M\u00e9xico",
    "qs:name_adm1":"Nuevo Leon",
    "qs:name_adm2":"Monterrey",
    "qs:name_local":"Monterrey",
    "qs:photo_max":47,
    "qs:photo_sum":161,
    "qs:placetype":"Suburb",
    "qs:quad_count":14,
    "qs:woe_adm0":23424900,
    "qs:woe_adm1":2346282,
    "qs:woe_adm2":12600645,
    "qs:woe_lau":0,
    "qs:woe_local":134047,
    "qs:woe_ver":"7.10.0",
    "qs_pg:aaroncc":"MX",
    "qs_pg:gn_country":"MX",
    "qs_pg:gn_fcode":"PPL",
    "qs_pg:gn_pop":0,
    "qs_pg:name":"Valle Alto",
    "qs_pg:name_adm0":"M\u00e9xico",
    "qs_pg:name_adm1":"Nuevo Leon",
    "qs_pg:photos":154,
    "qs_pg:photos_1k":31,
    "qs_pg:photos_9k":1,
    "qs_pg:photos_9r":4,
    "qs_pg:photos_all":154,
    "qs_pg:photos_sr":4,
    "qs_pg:pop_sr":0,
    "qs_pg:qs_pg_placetype":"neighbourhood",
    "qs_pg:qs_pg_placetype_gp":"Suburb",
    "qs_pg:woe_adm0":23424900,
    "wof:lang":[
        "spa"
    ],
    "wof:name":"Valle Alto",
    "wof:placetype":"neighbourhood"
},
  "geometry": {"coordinates":[-100.267865,25.555725],"type":"Point"}
}