{
  "type": "Feature",
  "properties": {
    "gn:admin1_code":"30",
    "gn:admin2_code":"33.0",
    "gn:asciiname":"Barrio Acosta Lagunes",
    "gn:country_code":"MX",
    "gn:dem":33,
    "gn:feature_class":"P",
    "gn:feature_code":"PPL",
    "gn:name":"Barrio Acosta Lagunes",
    "gn:population":580,
    "gn:timezone":"America/Mexico_City",
    "iso:country":"MX",
    "wof:name":"Barrio Acosta Lagunes",
    "wof:placetype":"locality",
    "wof:population":580
},
  "geometry": {"coordinates":[-97.31444,20.69472],"type":"Point"}
}