{
  "type": "Feature",
  "properties": {
    "gn:admin1_code":"15.0",
    "gn:admin2_code":"111.0",
    "gn:asciiname":"Mesa de Zacango",
    "gn:country_code":"MX",
    "gn:dem":2694,
    "gn:feature_class":"P",
    "gn:feature_code":"PPL",
    "gn:name":"Mesa de Zacango",
    "gn:population":0,
    "gn:timezone":"America/Mexico_City",
    "iso:country":"MX",
    "name:spa_x_preferred":[
        "Mesa de Zacango"
    ],
    "name:und_x_variant":[
        "Zacango"
    ],
    "wof:name":"Mesa de Zacango",
    "wof:placetype":"locality"
},
  "geometry": {"coordinates":[-100.10341,19.35631],"type":"Point"}
}