{
  "type": "Feature",
  "properties": {
    "iso:country":"MX",
    "name:bre_x_preferred":[
        "Palomar"
    ],
    "name:cat_x_preferred":[
        "Palomar"
    ],
    "name:ceb_x_preferred":[
        "Palomar"
    ],
    "name:deu_x_preferred":[
        "Palomar"
    ],
    "name:fas_x_preferred":[
        "\u067e\u0627\u0644\u0648\u0645\u0627\u0631"
    ],
    "name:fra_x_preferred":[
        "Palomar"
    ],
    "name:ita_x_preferred":[
        "Palomar"
    ],
    "name:por_x_preferred":[
        "Palomar"
    ],
    "name:spa_x_preferred":[
        "El Palomar",
        "Palomar"
    ],
    "qs:gn_adm0_cc":"MX",
    "qs:gn_fcode":"PPL",
    "qs:gn_local":4014338,
    "qs:gn_nam_loc":"Chihuahua, Chihuahua, Chihuahua, MX",
    "qs:gn_namadm1":"06",
    "qs:gn_name":"El Palomar",
    "qs:local_max":1142,
    "qs:local_sum":1903,
    "qs:localhoods":12,
    "qs:name":"El Palomar",
    "qs:name_adm0":"M\u00e9xico",
    "qs:name_adm1":"Chihuahua",
    "qs:name_adm2":"Chihuahua",
    "qs:name_local":"Chihuahua",
    "qs:photo_max":54,
    "qs:photo_sum":95,
    "qs:placetype":"Suburb",
    "qs:quad_count":9,
    "qs:woe_adm0":23424900,
    "qs:woe_adm1":2346269,
    "qs:woe_adm2":12599832,
    "qs:woe_lau":0,
    "qs:woe_local":115958,
    "qs:woe_ver":"7.10.0",
    "wof:lang":[
        "spa"
    ],
    "wof:name":"El Palomar",
    "wof:placetype":"neighbourhood"
},
  "geometry": {"coordinates":[-106.089271,28.640111],"type":"Point"}
}