{
  "type": "Feature",
  "properties": {
    "gn:admin1_code":"16",
    "gn:admin2_code":"8.0",
    "gn:asciiname":"Poza de Rita",
    "gn:country_code":"MX",
    "gn:dem":273,
    "gn:feature_class":"P",
    "gn:feature_code":"PPL",
    "gn:name":"Poza de Rita",
    "gn:population":8,
    "gn:timezone":"America/Mexico_City",
    "iso:country":"MX",
    "wof:name":"Poza de Rita",
    "wof:placetype":"locality",
    "wof:population":8
},
  "geometry": {"coordinates":[-102.82444,18.17028],"type":"Point"}
}