{
  "type": "Feature",
  "properties": {
    "gn:admin1_code":"31",
    "gn:admin2_code":"96.0",
    "gn:asciiname":"Candelaria",
    "gn:country_code":"MX",
    "gn:dem":10,
    "gn:feature_class":"P",
    "gn:feature_code":"PPL",
    "gn:name":"Candelaria",
    "gn:population":0,
    "gn:timezone":"America/Merida",
    "iso:country":"MX",
    "name:spa_x_preferred":[
        "Candelaria"
    ],
    "wof:name":"Candelaria",
    "wof:placetype":"locality"
},
  "geometry": {"coordinates":[-87.91022,21.38982],"type":"Point"}
}