{
  "type": "Feature",
  "properties": {
    "gn:admin1_code":"20",
    "gn:admin2_code":"384.0",
    "gn:asciiname":"San Bernardo",
    "gn:country_code":"MX",
    "gn:dem":1598,
    "gn:feature_class":"P",
    "gn:feature_code":"PPL",
    "gn:name":"San Bernardo",
    "gn:population":0,
    "gn:timezone":"America/Mexico_City",
    "iso:country":"MX",
    "name:sco_x_preferred":[
        "San Bernardo"
    ],
    "name:spa_x_preferred":[
        "San Bernardo"
    ],
    "name:srp_x_preferred":[
        "\u0421\u0430\u043d \u0411\u0435\u0440\u043d\u0430\u0440\u0434\u043e"
    ],
    "wof:name":"San Bernardo",
    "wof:placetype":"locality"
},
  "geometry": {"coordinates":[-96.7034,16.36793],"type":"Point"}
}