{
  "type": "Feature",
  "properties": {
    "gn:admin1_code":"7.0",
    "gn:admin2_code":"32.0",
    "gn:asciiname":"El Encino Solo",
    "gn:country_code":"MX",
    "gn:dem":443,
    "gn:feature_class":"P",
    "gn:feature_code":"PPL",
    "gn:name":"El Encino Solo",
    "gn:population":0,
    "gn:timezone":"America/Monterrey",
    "iso:country":"MX",
    "name:spa_x_preferred":[
        "El Encino Solo"
    ],
    "name:spa_x_variant":[
        "Encino Solo"
    ],
    "wof:name":"El Encino Solo",
    "wof:placetype":"locality"
},
  "geometry": {"coordinates":[-101.42871,28.12085],"type":"Point"}
}