{
  "type": "Feature",
  "properties": {
    "gn:admin1_code":"6",
    "gn:admin2_code":"29.0",
    "gn:asciiname":"Las Hormas",
    "gn:country_code":"MX",
    "gn:dem":2629,
    "gn:feature_class":"P",
    "gn:feature_code":"PPL",
    "gn:name":"Las Hormas",
    "gn:population":0,
    "gn:timezone":"America/Chihuahua",
    "iso:country":"MX",
    "name:spa_x_preferred":[
        "Las Hormas"
    ],
    "wof:name":"Las Hormas",
    "wof:placetype":"locality"
},
  "geometry": {"coordinates":[-106.89577,26.06497],"type":"Point"}
}