{
  "type": "Feature",
  "properties": {
    "gn:admin1_code":"13",
    "gn:admin2_code":"47.0",
    "gn:asciiname":"La Hoya",
    "gn:country_code":"MX",
    "gn:dem":1210,
    "gn:feature_class":"P",
    "gn:feature_code":"PPL",
    "gn:name":"La Hoya",
    "gn:population":0,
    "gn:timezone":"America/Mexico_City",
    "iso:country":"MX",
    "name:ceb_x_preferred":[
        "La Hoya"
    ],
    "name:fra_x_preferred":[
        "La Hoya"
    ],
    "name:glg_x_preferred":[
        "La Hoya"
    ],
    "name:spa_x_preferred":[
        "La Olla"
    ],
    "name:spa_x_variant":[
        "La Hoya"
    ],
    "name:swe_x_preferred":[
        "La Hoya"
    ],
    "wof:name":"La Hoya",
    "wof:placetype":"locality"
},
  "geometry": {"coordinates":[-99.28548000000001,20.99245],"type":"Point"}
}