{
  "type": "Feature",
  "properties": {
    "gn:admin1_code":"16.0",
    "gn:admin2_code":"38.0",
    "gn:asciiname":"Cutzio",
    "gn:cc2":"MX",
    "gn:country_code":"MX",
    "gn:dem":318,
    "gn:feature_class":"P",
    "gn:feature_code":"PPL",
    "gn:name":"Cutz\u00edo",
    "gn:population":0,
    "gn:timezone":"America/Mexico_City",
    "iso:country":"MX",
    "name:und_x_variant":[
        "Cuitzio",
        "Cutz\u00edo"
    ],
    "wof:name":"Cutzio",
    "wof:placetype":"locality"
},
  "geometry": {"coordinates":[-100.90000000000001,18.65],"type":"Point"}
}