{
  "type": "Feature",
  "properties": {
    "gn:admin1_code":"7.0",
    "gn:admin2_code":"35.0",
    "gn:asciiname":"Concepcion",
    "gn:country_code":"MX",
    "gn:dem":1124,
    "gn:feature_class":"P",
    "gn:feature_code":"PPL",
    "gn:name":"Concepci\u00f3n",
    "gn:population":0,
    "gn:timezone":"America/Monterrey",
    "iso:country":"MX",
    "wof:name":"Concepcion",
    "wof:placetype":"locality"
},
  "geometry": {"coordinates":[-103.41667,25.61667000000001],"type":"Point"}
}