{
  "type": "Feature",
  "properties": {
    "gn:admin1_code":"5",
    "gn:admin2_code":"80",
    "gn:asciiname":"Buenos Aires",
    "gn:country_code":"MX",
    "gn:dem":1835,
    "gn:feature_class":"P",
    "gn:feature_code":"PPL",
    "gn:name":"Buenos Aires",
    "gn:population":17,
    "gn:timezone":"America/Mexico_City",
    "iso:country":"MX",
    "wof:name":"Buenos Aires",
    "wof:placetype":"locality",
    "wof:population":17
},
  "geometry": {"coordinates":[-92.59389,15.52778],"type":"Point"}
}