{
  "type": "Feature",
  "properties": {
    "gn:admin1_code":"20",
    "gn:admin2_code":"263.0",
    "gn:asciiname":"Loma Larga (Cerro Largo)",
    "gn:country_code":"MX",
    "gn:dem":1254,
    "gn:feature_class":"P",
    "gn:feature_code":"PPL",
    "gn:name":"Loma Larga (Cerro Largo)",
    "gn:population":65,
    "gn:timezone":"America/Mexico_City",
    "iso:country":"MX",
    "wof:name":"Loma Larga (Cerro Largo)",
    "wof:placetype":"locality",
    "wof:population":65
},
  "geometry": {"coordinates":[-96.69583,16.14833],"type":"Point"}
}