{
  "type": "Feature",
  "properties": {
    "gn:admin1_code":"12",
    "gn:admin2_code":"21.0",
    "gn:asciiname":"La Bugambilia",
    "gn:country_code":"MX",
    "gn:dem":275,
    "gn:feature_class":"P",
    "gn:feature_code":"PPL",
    "gn:name":"La Bugambilia",
    "gn:population":5,
    "gn:timezone":"America/Mexico_City",
    "iso:country":"MX",
    "wof:name":"La Bugambilia",
    "wof:placetype":"locality",
    "wof:population":5
},
  "geometry": {"coordinates":[-100.10411000000001,17.13424],"type":"Point"}
}