{
  "type": "Feature",
  "properties": {
    "gn:admin1_code":"25",
    "gn:admin2_code":"4.0",
    "gn:asciiname":"El Brillante",
    "gn:country_code":"MX",
    "gn:dem":1499,
    "gn:feature_class":"P",
    "gn:feature_code":"PPL",
    "gn:name":"El Brillante",
    "gn:population":7,
    "gn:timezone":"America/Mazatlan",
    "iso:country":"MX",
    "wof:name":"El Brillante",
    "wof:placetype":"locality",
    "wof:population":7
},
  "geometry": {"coordinates":[-105.83653,23.45303],"type":"Point"}
}