{
  "type": "Feature",
  "properties": {
    "gn:admin1_code":"16.0",
    "gn:admin2_code":"96.0",
    "gn:asciiname":"El Cuatro",
    "gn:country_code":"MX",
    "gn:dem":323,
    "gn:feature_class":"P",
    "gn:feature_code":"PPL",
    "gn:name":"El Cuatro",
    "gn:population":0,
    "gn:timezone":"America/Mexico_City",
    "iso:country":"MX",
    "name:spa_x_preferred":[
        "El Cuatro"
    ],
    "wof:name":"El Cuatro",
    "wof:placetype":"locality"
},
  "geometry": {"coordinates":[-102.28447,18.70579],"type":"Point"}
}