{
  "type": "Feature",
  "properties": {
    "gn:admin1_code":"1.0",
    "gn:admin2_code":"5.0",
    "gn:asciiname":"Gracias a Dios",
    "gn:country_code":"MX",
    "gn:dem":1994,
    "gn:feature_class":"P",
    "gn:feature_code":"PPL",
    "gn:name":"Gracias a Dios",
    "gn:population":0,
    "gn:timezone":"America/Mexico_City",
    "iso:country":"MX",
    "name:ceb_x_preferred":[
        "Gracias a Dios"
    ],
    "name:nld_x_preferred":[
        "Gracias a Dios"
    ],
    "name:pol_x_preferred":[
        "Gracias a Dios"
    ],
    "name:rus_x_preferred":[
        "\u0413\u0440\u0430\u0441\u044c\u044f\u0441-\u0430-\u0414\u044c\u043e\u0441"
    ],
    "name:spa_x_preferred":[
        "Gracias a Dios"
    ],
    "name:swe_x_preferred":[
        "Gracias a Dios"
    ],
    "wof:name":"Gracias a Dios",
    "wof:placetype":"locality"
},
  "geometry": {"coordinates":[-102.49408,21.92913],"type":"Point"}
}