{
  "type": "Feature",
  "properties": {
    "gn:admin1_code":"23",
    "gn:asciiname":"Chichancha",
    "gn:country_code":"MX",
    "gn:dem":225,
    "gn:feature_class":"P",
    "gn:feature_code":"PPL",
    "gn:name":"Chichanch\u00e1",
    "gn:population":0,
    "gn:timezone":"America/Cancun",
    "iso:country":"MX",
    "wof:name":"Chichancha",
    "wof:placetype":"locality"
},
  "geometry": {"coordinates":[-89.21666999999999,18.18333],"type":"Point"}
}