{
  "type": "Feature",
  "properties": {
    "gn:admin1_code":"14",
    "gn:admin2_code":"49.0",
    "gn:asciiname":"El Rincon",
    "gn:country_code":"MX",
    "gn:dem":961,
    "gn:feature_class":"P",
    "gn:feature_code":"PPL",
    "gn:name":"El Rinc\u00f3n",
    "gn:population":125,
    "gn:timezone":"America/Mexico_City",
    "iso:country":"MX",
    "name:und_x_variant":[
        "El Rinc\u00f3n"
    ],
    "wof:name":"El Rincon",
    "wof:placetype":"locality",
    "wof:population":125
},
  "geometry": {"coordinates":[-103.08972,19.34083],"type":"Point"}
}