{
  "type": "Feature",
  "properties": {
    "gn:admin1_code":"5.0",
    "gn:admin2_code":"51.0",
    "gn:asciiname":"El Pescadero",
    "gn:country_code":"MX",
    "gn:dem":15,
    "gn:feature_class":"P",
    "gn:feature_code":"PPL",
    "gn:name":"El Pescadero",
    "gn:population":0,
    "gn:timezone":"America/Mexico_City",
    "iso:country":"MX",
    "name:spa_x_preferred":[
        "El Pescadero"
    ],
    "wof:name":"El Pescadero",
    "wof:placetype":"locality"
},
  "geometry": {"coordinates":[-93.00501,15.3995],"type":"Point"}
}