{
  "type": "Feature",
  "properties": {
    "gn:admin1_code":"28",
    "gn:admin2_code":"14.0",
    "gn:asciiname":"El Blanco",
    "gn:country_code":"MX",
    "gn:dem":142,
    "gn:feature_class":"P",
    "gn:feature_code":"PPL",
    "gn:name":"El Blanco",
    "gn:population":0,
    "gn:timezone":"America/Monterrey",
    "iso:country":"MX",
    "name:spa_x_preferred":[
        "El Blanco"
    ],
    "wof:name":"El Blanco",
    "wof:placetype":"locality"
},
  "geometry": {"coordinates":[-99.32771,26.57701],"type":"Point"}
}