{
  "type": "Feature",
  "properties": {
    "gn:admin1_code":"10",
    "gn:admin2_code":"9.0",
    "gn:asciiname":"La Osa",
    "gn:country_code":"MX",
    "gn:dem":2543,
    "gn:feature_class":"P",
    "gn:feature_code":"PPL",
    "gn:name":"La Osa",
    "gn:population":8,
    "gn:timezone":"America/Monterrey",
    "iso:country":"MX",
    "wof:name":"La Osa",
    "wof:placetype":"locality",
    "wof:population":8
},
  "geometry": {"coordinates":[-106.05816000000002,25.84441],"type":"Point"}
}