{
  "type": "Feature",
  "properties": {
    "gn:admin1_code":"2",
    "gn:admin2_code":"1.0",
    "gn:asciiname":"Las Joyitas",
    "gn:country_code":"MX",
    "gn:dem":688,
    "gn:feature_class":"P",
    "gn:feature_code":"PPL",
    "gn:name":"Las Joyitas",
    "gn:population":0,
    "gn:timezone":"America/Tijuana",
    "iso:country":"MX",
    "name:spa_x_preferred":[
        "Las Joyitas"
    ],
    "wof:name":"Las Joyitas",
    "wof:placetype":"locality"
},
  "geometry": {"coordinates":[-116.27392,31.93946],"type":"Point"}
}