{
  "type": "Feature",
  "properties": {
    "gn:admin1_code":"12.0",
    "gn:asciiname":"Acatlan del Rio",
    "gn:country_code":"MX",
    "gn:dem":1162,
    "gn:feature_class":"P",
    "gn:feature_code":"PPL",
    "gn:name":"Acatl\u00e1n del R\u00edo",
    "gn:population":0,
    "gn:timezone":"America/Mexico_City",
    "iso:country":"MX",
    "name:spa_x_preferred":[
        "Acatl\u00e1n del R\u00edo"
    ],
    "name:spa_x_variant":[
        "El Salado"
    ],
    "wof:name":"Acatlan del Rio",
    "wof:placetype":"locality"
},
  "geometry": {"coordinates":[-98.38373,17.55551],"type":"Point"}
}