{
  "type": "Feature",
  "properties": {
    "gn:admin1_code":"21",
    "gn:admin2_code":"63.0",
    "gn:asciiname":"Benito Juarez (Chicalote)",
    "gn:country_code":"MX",
    "gn:dem":2459,
    "gn:feature_class":"P",
    "gn:feature_code":"PPL",
    "gn:name":"Benito Ju\u00e1rez (Chicalote)",
    "gn:population":213,
    "gn:timezone":"America/Mexico_City",
    "iso:country":"MX",
    "name:und_x_variant":[
        "Benito Ju\u00e1rez (Chicalote)"
    ],
    "wof:name":"Benito Juarez (Chicalote)",
    "wof:placetype":"locality",
    "wof:population":213
},
  "geometry": {"coordinates":[-97.33889000000001,18.83306],"type":"Point"}
}