{
  "type": "Feature",
  "properties": {
    "gn:admin1_code":"10",
    "gn:admin2_code":"14",
    "gn:asciiname":"Las Aguilas",
    "gn:country_code":"MX",
    "gn:dem":1987,
    "gn:feature_class":"P",
    "gn:feature_code":"PPL",
    "gn:name":"Las \u00c1guilas",
    "gn:population":22,
    "gn:timezone":"America/Monterrey",
    "iso:country":"MX",
    "name:und_x_variant":[
        "Las \u00c1guilas"
    ],
    "wof:name":"Las Aguilas",
    "wof:placetype":"locality",
    "wof:population":22
},
  "geometry": {"coordinates":[-104.67914,23.10808],"type":"Point"}
}