{
  "type": "Feature",
  "properties": {
    "gn:admin1_code":"26",
    "gn:admin2_code":"43",
    "gn:asciiname":"Los Tres Garcia (Colina del Lago)",
    "gn:country_code":"MX",
    "gn:dem":1283,
    "gn:feature_class":"P",
    "gn:feature_code":"PPL",
    "gn:name":"Los Tres Garc\u00eda (Colina del Lago)",
    "gn:population":15,
    "gn:timezone":"America/Hermosillo",
    "iso:country":"MX",
    "name:und_x_variant":[
        "Los Tres Garc\u00eda (Colina del Lago)"
    ],
    "wof:name":"Los Tres Garcia (Colina del Lago)",
    "wof:placetype":"locality",
    "wof:population":15
},
  "geometry": {"coordinates":[-110.97083000000001,31.32722],"type":"Point"}
}