{
  "type": "Feature",
  "properties": {
    "gn:admin1_code":"25",
    "gn:admin2_code":"10.0",
    "gn:asciiname":"Zozoriqui",
    "gn:country_code":"MX",
    "gn:dem":64,
    "gn:feature_class":"P",
    "gn:feature_code":"PPL",
    "gn:name":"Zozoriqui",
    "gn:population":346,
    "gn:timezone":"America/Mazatlan",
    "iso:country":"MX",
    "name:spa_x_preferred":[
        "Zozoriqui"
    ],
    "name:und_x_variant":[
        "Zozorique"
    ],
    "wof:name":"Zozoriqui",
    "wof:placetype":"locality",
    "wof:population":346
},
  "geometry": {"coordinates":[-108.73950000000001,26.34647],"type":"Point"}
}