{
  "type": "Feature",
  "properties": {
    "gn:admin1_code":"3.0",
    "gn:admin2_code":"2.0",
    "gn:asciiname":"El Sauzalito",
    "gn:country_code":"MX",
    "gn:dem":731,
    "gn:feature_class":"P",
    "gn:feature_code":"PPL",
    "gn:name":"El Sauzalito",
    "gn:population":3,
    "gn:timezone":"America/Mazatlan",
    "iso:country":"MX",
    "name:ceb_x_preferred":[
        "El Sauzalito"
    ],
    "name:por_x_preferred":[
        "El Sauzalito"
    ],
    "name:spa_x_preferred":[
        "El Sauzalito"
    ],
    "name:swe_x_preferred":[
        "El Sauzalito"
    ],
    "wof:name":"El Sauzalito",
    "wof:placetype":"locality",
    "wof:population":3
},
  "geometry": {"coordinates":[-113.00627,27.5351],"type":"Point"}
}