{
  "type": "Feature",
  "properties": {
    "gn:admin1_code":"26.0",
    "gn:asciiname":"El Treinta y Ocho",
    "gn:country_code":"MX",
    "gn:dem":556,
    "gn:feature_class":"P",
    "gn:feature_code":"PPL",
    "gn:name":"El Treinta y Ocho",
    "gn:population":0,
    "gn:timezone":"America/Hermosillo",
    "iso:country":"MX",
    "name:spa_x_preferred":[
        "El Treinta y Ocho"
    ],
    "wof:name":"El Treinta y Ocho",
    "wof:placetype":"locality"
},
  "geometry": {"coordinates":[-111.14505,29.62392],"type":"Point"}
}