{
  "type": "Feature",
  "properties": {
    "gn:admin1_code":"5",
    "gn:admin2_code":"107.0",
    "gn:asciiname":"Nueva Cabana",
    "gn:country_code":"MX",
    "gn:dem":839,
    "gn:feature_class":"P",
    "gn:feature_code":"PPL",
    "gn:name":"Nueva Caba\u00f1a",
    "gn:population":6,
    "gn:timezone":"America/Mexico_City",
    "iso:country":"MX",
    "name:und_x_variant":[
        "Nueva Caba\u00f1a"
    ],
    "wof:name":"Nueva Cabana",
    "wof:placetype":"locality",
    "wof:population":6
},
  "geometry": {"coordinates":[-93.26167,16.08639],"type":"Point"}
}