{
  "type": "Feature",
  "properties": {
    "gn:admin1_code":"5",
    "gn:admin2_code":"23.0",
    "gn:asciiname":"Chilimjoveltic",
    "gn:country_code":"MX",
    "gn:dem":2586,
    "gn:feature_class":"P",
    "gn:feature_code":"PPL",
    "gn:name":"Chilimjoveltic",
    "gn:population":655,
    "gn:timezone":"America/Mexico_City",
    "iso:country":"MX",
    "wof:name":"Chilimjoveltic",
    "wof:placetype":"locality",
    "wof:population":655
},
  "geometry": {"coordinates":[-92.57944000000001,16.78778],"type":"Point"}
}