{
  "type": "Feature",
  "properties": {
    "gn:admin1_code":"26",
    "gn:admin2_code":"17.0",
    "gn:asciiname":"Rancho de Dolores",
    "gn:country_code":"MX",
    "gn:dem":241,
    "gn:feature_class":"P",
    "gn:feature_code":"PPL",
    "gn:name":"Rancho de Dolores",
    "gn:population":0,
    "gn:timezone":"America/Hermosillo",
    "iso:country":"MX",
    "wof:name":"Rancho de Dolores",
    "wof:placetype":"locality"
},
  "geometry": {"coordinates":[-112.23333,30.63333],"type":"Point"}
}