{
  "type": "Feature",
  "properties": {
    "gn:admin1_code":"20",
    "gn:admin2_code":"236.0",
    "gn:asciiname":"Frontera del Sol",
    "gn:country_code":"MX",
    "gn:dem":2574,
    "gn:feature_class":"P",
    "gn:feature_code":"PPL",
    "gn:name":"Frontera del Sol",
    "gn:population":9,
    "gn:timezone":"America/Mexico_City",
    "iso:country":"MX",
    "wof:name":"Frontera del Sol",
    "wof:placetype":"locality",
    "wof:population":9
},
  "geometry": {"coordinates":[-96.38444,16.07667],"type":"Point"}
}