{
  "type": "Feature",
  "properties": {
    "gn:admin1_code":"7",
    "gn:admin2_code":"27.0",
    "gn:asciiname":"Monte Redondo",
    "gn:country_code":"MX",
    "gn:dem":979,
    "gn:feature_class":"P",
    "gn:feature_code":"PPL",
    "gn:name":"Monte Redondo",
    "gn:population":1,
    "gn:timezone":"America/Monterrey",
    "iso:country":"MX",
    "name:spa_x_preferred":[
        "Monte Redondo"
    ],
    "wof:name":"Monte Redondo",
    "wof:placetype":"locality",
    "wof:population":1
},
  "geometry": {"coordinates":[-101.12144000000001,25.79391],"type":"Point"}
}