{
  "type": "Feature",
  "properties": {
    "gn:admin1_code":"1",
    "gn:admin2_code":"1.0",
    "gn:asciiname":"San Antonio de Penuelas",
    "gn:country_code":"MX",
    "gn:dem":1834,
    "gn:feature_class":"P",
    "gn:feature_code":"PPL",
    "gn:name":"San Antonio de Pe\u00f1uelas",
    "gn:population":0,
    "gn:timezone":"America/Mexico_City",
    "iso:country":"MX",
    "name:und_x_variant":[
        "Pe\u00f1uelas",
        "San Antonio de Pe\u00f1uelas"
    ],
    "wof:name":"San Antonio de Penuelas",
    "wof:placetype":"locality"
},
  "geometry": {"coordinates":[-102.3001,21.67471],"type":"Point"}
}