{
  "type": "Feature",
  "properties": {
    "gn:admin1_code":"27",
    "gn:admin2_code":"9.0",
    "gn:asciiname":"Chichonal 3ra. Seccion (La Capilla)",
    "gn:country_code":"MX",
    "gn:dem":31,
    "gn:feature_class":"P",
    "gn:feature_code":"PPL",
    "gn:name":"Chichonal 3ra. Secci\u00f3n (La Capilla)",
    "gn:population":565,
    "gn:timezone":"America/Mexico_City",
    "iso:country":"MX",
    "name:spa_x_preferred":[
        "Chichonal"
    ],
    "wof:name":"Chichonal 3ra. Seccion (La Capilla)",
    "wof:placetype":"locality",
    "wof:population":565
},
  "geometry": {"coordinates":[-92.67613,17.77133],"type":"Point"}
}