{
  "type": "Feature",
  "properties": {
    "gn:admin1_code":"13",
    "gn:admin2_code":"18.0",
    "gn:asciiname":"Iglesia Vieja",
    "gn:country_code":"MX",
    "gn:dem":1182,
    "gn:feature_class":"P",
    "gn:feature_code":"PPL",
    "gn:name":"Iglesia Vieja",
    "gn:population":0,
    "gn:timezone":"America/Mexico_City",
    "iso:country":"MX",
    "name:spa_x_preferred":[
        "Iglesia Vieja"
    ],
    "name:und_x_variant":[
        "Iglesia Nueva"
    ],
    "wof:name":"Iglesia Vieja",
    "wof:placetype":"locality"
},
  "geometry": {"coordinates":[-98.96724,21.10683],"type":"Point"}
}