{
  "type": "Feature",
  "properties": {
    "gn:admin1_code":"14.0",
    "gn:admin2_code":"90.0",
    "gn:asciiname":"La Tuna",
    "gn:country_code":"MX",
    "gn:dem":1337,
    "gn:feature_class":"P",
    "gn:feature_code":"PPL",
    "gn:name":"La Tuna",
    "gn:population":0,
    "gn:timezone":"America/Mexico_City",
    "iso:country":"MX",
    "name:spa_x_preferred":[
        "La Tuna"
    ],
    "wof:name":"La Tuna",
    "wof:placetype":"locality"
},
  "geometry": {"coordinates":[-104.08658,19.99514],"type":"Point"}
}