{
  "type": "Feature",
  "properties": {
    "gn:admin1_code":"14.0",
    "gn:admin2_code":"35.0",
    "gn:asciiname":"Coyotillos",
    "gn:country_code":"MX",
    "gn:dem":1873,
    "gn:feature_class":"P",
    "gn:feature_code":"PPL",
    "gn:name":"Coyotillos",
    "gn:population":0,
    "gn:timezone":"America/Mexico_City",
    "iso:country":"MX",
    "name:spa_x_preferred":[
        "Coyotillos"
    ],
    "wof:name":"Coyotillos",
    "wof:placetype":"locality"
},
  "geometry": {"coordinates":[-102.21802,21.50984],"type":"Point"}
}