{
  "type": "Feature",
  "properties": {
    "gn:admin1_code":"5",
    "gn:admin2_code":"76.0",
    "gn:asciiname":"Nuevo Poblado Sakija",
    "gn:country_code":"MX",
    "gn:dem":128,
    "gn:feature_class":"P",
    "gn:feature_code":"PPL",
    "gn:name":"Nuevo Poblado Sakija",
    "gn:population":99,
    "gn:timezone":"America/Mexico_City",
    "iso:country":"MX",
    "wof:name":"Nuevo Poblado Sakija",
    "wof:placetype":"locality",
    "wof:population":99
},
  "geometry": {"coordinates":[-92.63943999999999,17.38444],"type":"Point"}
}