{
  "type": "Feature",
  "properties": {
    "gn:admin1_code":"1",
    "gn:admin2_code":"6.0",
    "gn:asciiname":"Santa Isabel [Fraccionamiento]",
    "gn:country_code":"MX",
    "gn:dem":1891,
    "gn:feature_class":"P",
    "gn:feature_code":"PPL",
    "gn:name":"Santa Isabel [Fraccionamiento]",
    "gn:population":1065,
    "gn:timezone":"America/Mexico_City",
    "iso:country":"MX",
    "wof:name":"Santa Isabel [Fraccionamiento]",
    "wof:placetype":"locality",
    "wof:population":1065
},
  "geometry": {"coordinates":[-102.26778,22.08111],"type":"Point"}
}