{
  "type": "Feature",
  "properties": {
    "gn:admin1_code":"28.0",
    "gn:admin2_code":"35.0",
    "gn:asciiname":"El Guzmaneno",
    "gn:country_code":"MX",
    "gn:dem":35,
    "gn:feature_class":"P",
    "gn:feature_code":"PPL",
    "gn:name":"El Guzmane\u00f1o",
    "gn:population":0,
    "gn:timezone":"America/Monterrey",
    "iso:country":"MX",
    "name:spa_x_preferred":[
        "El Guzmane\u00f1o"
    ],
    "wof:name":"El Guzmaneno",
    "wof:placetype":"locality"
},
  "geometry": {"coordinates":[-98.10666999999999,24.68444],"type":"Point"}
}