{
  "type": "Feature",
  "properties": {
    "gn:admin1_code":"2",
    "gn:admin2_code":"1.0",
    "gn:asciiname":"Leon",
    "gn:country_code":"MX",
    "gn:dem":796,
    "gn:feature_class":"P",
    "gn:feature_code":"PPL",
    "gn:name":"Le\u00f3n",
    "gn:population":0,
    "gn:timezone":"America/Tijuana",
    "iso:country":"MX",
    "name:afr_x_preferred":[
        "Leon"
    ],
    "name:ara_x_preferred":[
        "\u0644\u064a\u0648\u0646"
    ],
    "name:aze_x_preferred":[
        "Leon"
    ],
    "name:bel_x_preferred":[
        "\u041b\u0435\u043e\u043d"
    ],
    "name:bre_x_preferred":[
        "Leon"
    ],
    "name:bul_x_preferred":[
        "\u041b\u0435\u043e\u043d"
    ],
    "name:ceb_x_preferred":[
        "Leon"
    ],
    "name:ces_x_preferred":[
        "Leon"
    ],
    "name:dan_x_preferred":[
        "Leon"
    ],
    "name:deu_x_preferred":[
        "Leon"
    ],
    "name:epo_x_preferred":[
        "Leon"
    ],
    "name:est_x_preferred":[
        "Leon"
    ],
    "name:eus_x_preferred":[
        "Leon"
    ],
    "name:fas_x_preferred":[
        "\u0644\u0626\u0648\u0646"
    ],
    "name:fin_x_preferred":[
        "Leon"
    ],
    "name:heb_x_preferred":[
        "\u05dc\u05d0\u05d5\u05df"
    ],
    "name:hye_x_preferred":[
        "\u053c\u0565\u0578\u0576"
    ],
    "name:ina_x_preferred":[
        "Leon"
    ],
    "name:ind_x_preferred":[
        "Leon"
    ],
    "name:ita_x_preferred":[
        "Leon"
    ],
    "name:jpn_x_preferred":[
        "\u30ec\u30aa\u30f3"
    ],
    "name:lav_x_preferred":[
        "Leon"
    ],
    "name:nld_x_preferred":[
        "Leon"
    ],
    "name:nor_x_preferred":[
        "Leon"
    ],
    "name:oci_x_preferred":[
        "Leon"
    ],
    "name:pam_x_preferred":[
        "Leon"
    ],
    "name:pol_x_preferred":[
        "Leon"
    ],
    "name:rus_x_preferred":[
        "\u041b\u0435\u043e\u043d"
    ],
    "name:sco_x_preferred":[
        "Leon"
    ],
    "name:slk_x_preferred":[
        "Leon"
    ],
    "name:slv_x_preferred":[
        "Leon"
    ],
    "name:srp_x_preferred":[
        "\u041b\u0438\u043e\u043d"
    ],
    "name:swe_x_preferred":[
        "Leon"
    ],
    "name:tur_x_preferred":[
        "Leon"
    ],
    "name:ukr_x_preferred":[
        "\u041b\u0435\u043e\u043d"
    ],
    "name:uzb_x_preferred":[
        "Leon"
    ],
    "name:vol_x_preferred":[
        "Leon"
    ],
    "name:war_x_preferred":[
        "Leon"
    ],
    "name:zho_x_preferred":[
        "Leon"
    ],
    "wof:name":"Leon",
    "wof:placetype":"locality"
},
  "geometry": {"coordinates":[-113.78333000000001,28.51667],"type":"Point"}
}