{
  "type": "Feature",
  "properties": {
    "gn:admin1_code":"2",
    "gn:admin2_code":"1.0",
    "gn:asciiname":"Leon",
    "gn:country_code":"MX",
    "gn:dem":796,
    "gn:feature_class":"P",
    "gn:feature_code":"PPL",
    "gn:name":"Le\u00f3n",
    "gn:population":0,
    "gn:timezone":"America/Tijuana",
    "iso:country":"MX",
    "wof:name":"Leon",
    "wof:placetype":"locality"
},
  "geometry": {"coordinates":[-113.78333000000001,28.51667],"type":"Point"}
}