{
  "type": "Feature",
  "properties": {
    "gn:admin1_code":"25",
    "gn:admin2_code":"11.0",
    "gn:asciiname":"El Soto de los Lopez",
    "gn:country_code":"MX",
    "gn:dem":8,
    "gn:feature_class":"P",
    "gn:feature_code":"PPL",
    "gn:name":"El Soto de los L\u00f3pez",
    "gn:population":5,
    "gn:timezone":"America/Mazatlan",
    "iso:country":"MX",
    "name:und_x_variant":[
        "El Soto de los L\u00f3pez"
    ],
    "wof:name":"El Soto de los Lopez",
    "wof:placetype":"locality",
    "wof:population":5
},
  "geometry": {"coordinates":[-108.49002,25.4376],"type":"Point"}
}