{
  "type": "Feature",
  "properties": {
    "gn:admin1_code":"28.0",
    "gn:admin2_code":"37.0",
    "gn:asciiname":"Las Galias",
    "gn:country_code":"MX",
    "gn:dem":129,
    "gn:feature_class":"P",
    "gn:feature_code":"PPL",
    "gn:name":"Las Galias",
    "gn:population":6,
    "gn:timezone":"America/Monterrey",
    "iso:country":"MX",
    "name:spa_x_preferred":[
        "Las Galias"
    ],
    "wof:name":"Las Galias",
    "wof:placetype":"locality",
    "wof:population":6
},
  "geometry": {"coordinates":[-97.90697,23.55684],"type":"Point"}
}