{
  "type": "Feature",
  "properties": {
    "gn:admin1_code":"11",
    "gn:admin2_code":"22",
    "gn:asciiname":"Presa de Dolores (El Clavelito)",
    "gn:country_code":"MX",
    "gn:dem":2146,
    "gn:feature_class":"P",
    "gn:feature_code":"PPL",
    "gn:name":"Presa de Dolores (El Clavelito)",
    "gn:population":24,
    "gn:timezone":"America/Mexico_City",
    "iso:country":"MX",
    "wof:name":"Presa de Dolores (El Clavelito)",
    "wof:placetype":"locality",
    "wof:population":24
},
  "geometry": {"coordinates":[-101.48917,21.48611],"type":"Point"}
}