{
  "type": "Feature",
  "properties": {
    "gn:admin1_code":"20",
    "gn:admin2_code":"135.0",
    "gn:asciiname":"La Nopalera",
    "gn:country_code":"MX",
    "gn:dem":1767,
    "gn:feature_class":"P",
    "gn:feature_code":"PPL",
    "gn:name":"La Nopalera",
    "gn:population":116,
    "gn:timezone":"America/Mexico_City",
    "iso:country":"MX",
    "wof:name":"La Nopalera",
    "wof:placetype":"locality",
    "wof:population":116
},
  "geometry": {"coordinates":[-96.88,17.05972],"type":"Point"}
}