{
  "type": "Feature",
  "properties": {
    "gn:admin1_code":"12",
    "gn:admin2_code":"28.0",
    "gn:asciiname":"San Jeronimo Palantla",
    "gn:country_code":"MX",
    "gn:dem":1852,
    "gn:feature_class":"P",
    "gn:feature_code":"PPL",
    "gn:name":"San Jer\u00f3nimo Palantla",
    "gn:population":566,
    "gn:timezone":"America/Mexico_City",
    "iso:country":"MX",
    "name:und_x_variant":[
        "San Jer\u00f3nimo Palantla"
    ],
    "wof:name":"San Jeronimo Palantla",
    "wof:placetype":"locality",
    "wof:population":566
},
  "geometry": {"coordinates":[-99.08833,17.52833],"type":"Point"}
}