{
  "type": "Feature",
  "properties": {
    "gn:admin1_code":"6.0",
    "gn:asciiname":"Aida",
    "gn:country_code":"MX",
    "gn:dem":1190,
    "gn:feature_class":"P",
    "gn:feature_code":"PPL",
    "gn:name":"Aida",
    "gn:population":0,
    "gn:timezone":"America/Chihuahua",
    "iso:country":"MX",
    "name:spa_x_preferred":[
        "Aida"
    ],
    "wof:name":"Aida",
    "wof:placetype":"locality"
},
  "geometry": {"coordinates":[-105.61148,28.37966],"type":"Point"}
}