{
  "type": "Feature",
  "properties": {
    "gn:admin1_code":"10",
    "gn:admin2_code":"26.0",
    "gn:asciiname":"Puentecillas",
    "gn:country_code":"MX",
    "gn:dem":2644,
    "gn:feature_class":"P",
    "gn:feature_code":"PPL",
    "gn:name":"Puentecillas",
    "gn:population":0,
    "gn:timezone":"America/Monterrey",
    "iso:country":"MX",
    "name:spa_x_preferred":[
        "Puentecillas"
    ],
    "wof:name":"Puentecillas",
    "wof:placetype":"locality"
},
  "geometry": {"coordinates":[-105.97108,24.31686],"type":"Point"}
}