{
  "type": "Feature",
  "properties": {
    "gn:admin1_code":"21.0",
    "gn:admin2_code":"197.0",
    "gn:asciiname":"Los Limones",
    "gn:country_code":"MX",
    "gn:dem":571,
    "gn:feature_class":"P",
    "gn:feature_code":"PPL",
    "gn:name":"Los Limones",
    "gn:population":460,
    "gn:timezone":"America/Mexico_City",
    "iso:country":"MX",
    "name:spa_x_preferred":[
        "Los Limones"
    ],
    "wof:name":"Los Limones",
    "wof:placetype":"locality",
    "wof:population":460
},
  "geometry": {"coordinates":[-97.91473000000001,20.33625],"type":"Point"}
}