{
  "type": "Feature",
  "properties": {
    "gn:admin1_code":"5",
    "gn:admin2_code":"59.0",
    "gn:asciiname":"Rancho Nuevo Uno",
    "gn:country_code":"MX",
    "gn:dem":831,
    "gn:feature_class":"P",
    "gn:feature_code":"PPL",
    "gn:name":"Rancho Nuevo Uno",
    "gn:population":8,
    "gn:timezone":"America/Mexico_City",
    "iso:country":"MX",
    "wof:name":"Rancho Nuevo Uno",
    "wof:placetype":"locality",
    "wof:population":8
},
  "geometry": {"coordinates":[-91.95166999999999,16.86667000000001],"type":"Point"}
}