{
  "type": "Feature",
  "properties": {
    "gn:admin1_code":"26",
    "gn:admin2_code":"68.0",
    "gn:asciiname":"Las Guasimas",
    "gn:country_code":"MX",
    "gn:dem":922,
    "gn:feature_class":"P",
    "gn:feature_code":"PPL",
    "gn:name":"Las Gu\u00e1simas",
    "gn:population":0,
    "gn:timezone":"America/Hermosillo",
    "iso:country":"MX",
    "wof:name":"Las Guasimas",
    "wof:placetype":"locality"
},
  "geometry": {"coordinates":[-109.90000000000001,28.91667],"type":"Point"}
}