{
  "type": "Feature",
  "properties": {
    "gn:admin1_code":"12",
    "gn:admin2_code":"59",
    "gn:asciiname":"Agua de Guamuchil",
    "gn:country_code":"MX",
    "gn:dem":881,
    "gn:feature_class":"P",
    "gn:feature_code":"PPL",
    "gn:name":"Agua de Guam\u00fachil",
    "gn:population":17,
    "gn:timezone":"America/Mexico_City",
    "iso:country":"MX",
    "name:und_x_variant":[
        "Agua de Guam\u00fachil"
    ],
    "wof:name":"Agua de Guamuchil",
    "wof:placetype":"locality",
    "wof:population":17
},
  "geometry": {"coordinates":[-99.43659,18.29882000000001],"type":"Point"}
}