{
  "type": "Feature",
  "properties": {
    "gn:admin1_code":"2.0",
    "gn:admin2_code":"1.0",
    "gn:asciiname":"La Mariposa",
    "gn:country_code":"MX",
    "gn:dem":1007,
    "gn:feature_class":"P",
    "gn:feature_code":"PPL",
    "gn:name":"La Mariposa",
    "gn:population":0,
    "gn:timezone":"America/Tijuana",
    "iso:country":"MX",
    "name:spa_x_preferred":[
        "La Mariposa"
    ],
    "wof:name":"La Mariposa",
    "wof:placetype":"locality"
},
  "geometry": {"coordinates":[-116.12472,31.92333],"type":"Point"}
}