{
  "type": "Feature",
  "properties": {
    "gn:admin1_code":"24.0",
    "gn:admin2_code":"16.0",
    "gn:asciiname":"Estacion Velazco",
    "gn:country_code":"MX",
    "gn:dem":52,
    "gn:feature_class":"P",
    "gn:feature_code":"PPL",
    "gn:name":"Estaci\u00f3n Velazco",
    "gn:population":594,
    "gn:timezone":"America/Mexico_City",
    "iso:country":"MX",
    "name:spa_x_preferred":[
        "Estaci\u00f3n Velazco"
    ],
    "wof:name":"Estacion Velazco",
    "wof:placetype":"locality",
    "wof:population":594
},
  "geometry": {"coordinates":[-98.56332999999999,22.19222],"type":"Point"}
}