{
  "type": "Feature",
  "properties": {
    "gn:admin1_code":"13",
    "gn:admin2_code":"60",
    "gn:asciiname":"Cerro Grande",
    "gn:country_code":"MX",
    "gn:dem":1125,
    "gn:feature_class":"P",
    "gn:feature_code":"PPL",
    "gn:name":"Cerro Grande",
    "gn:population":17,
    "gn:timezone":"America/Mexico_City",
    "iso:country":"MX",
    "name:ceb_x_preferred":[
        "Cerro Grande"
    ],
    "name:deu_x_preferred":[
        "Cerro Grande"
    ],
    "name:spa_x_preferred":[
        "Cerro Grande"
    ],
    "name:swe_x_preferred":[
        "Cerro Grande"
    ],
    "wof:name":"Cerro Grande",
    "wof:placetype":"locality",
    "wof:population":17
},
  "geometry": {"coordinates":[-98.16388000000001,20.38657000000001],"type":"Point"}
}