{
  "type": "Feature",
  "properties": {
    "gn:admin1_code":"17",
    "gn:admin2_code":"28.0",
    "gn:asciiname":"Colonia Acoculco (La Cruz)",
    "gn:country_code":"MX",
    "gn:dem":1166,
    "gn:feature_class":"P",
    "gn:feature_code":"PPL",
    "gn:name":"Colonia Acoculco (La Cruz)",
    "gn:population":96,
    "gn:timezone":"America/Mexico_City",
    "iso:country":"MX",
    "wof:name":"Colonia Acoculco (La Cruz)",
    "wof:placetype":"locality",
    "wof:population":96
},
  "geometry": {"coordinates":[-99.23166999999999,18.80611],"type":"Point"}
}