{
  "type": "Feature",
  "properties": {
    "gn:admin1_code":"10.0",
    "gn:admin2_code":"5.0",
    "gn:asciiname":"Casa Blanca",
    "gn:country_code":"MX",
    "gn:dem":1933,
    "gn:feature_class":"P",
    "gn:feature_code":"PPL",
    "gn:name":"Casa Blanca",
    "gn:population":0,
    "gn:timezone":"America/Monterrey",
    "iso:country":"MX",
    "wof:name":"Casa Blanca",
    "wof:placetype":"locality"
},
  "geometry": {"coordinates":[-104.71147999999999,24.14583],"type":"Point"}
}