{
  "type": "Feature",
  "properties": {
    "gn:admin1_code":"15",
    "gn:admin2_code":"80.0",
    "gn:asciiname":"Metlatepec",
    "gn:country_code":"MX",
    "gn:dem":1588,
    "gn:feature_class":"P",
    "gn:feature_code":"PPL",
    "gn:name":"Metlatepec",
    "gn:population":0,
    "gn:timezone":"America/Mexico_City",
    "iso:country":"MX",
    "name:und_x_variant":[
        "Metlaltepec",
        "Metlapetec",
        "Metlatepec"
    ],
    "wof:name":"Metlatepec",
    "wof:placetype":"locality"
},
  "geometry": {"coordinates":[-99.93716999999999,18.71984],"type":"Point"}
}