{
  "type": "Feature",
  "properties": {
    "gn:admin1_code":"26.0",
    "gn:admin2_code":"69.0",
    "gn:asciiname":"El Carrizal",
    "gn:cc2":"MX",
    "gn:country_code":"MX",
    "gn:dem":928,
    "gn:feature_class":"P",
    "gn:feature_code":"PPL",
    "gn:name":"El Carrizal",
    "gn:population":11,
    "gn:timezone":"America/Hermosillo",
    "iso:country":"MX",
    "name:und_x_variant":[
        "Carrizal"
    ],
    "wof:name":"El Carrizal",
    "wof:placetype":"locality",
    "wof:population":11
},
  "geometry": {"coordinates":[-109.16833,28.53944000000001],"type":"Point"}
}