{
  "type": "Feature",
  "properties": {
    "gn:admin1_code":"19",
    "gn:admin2_code":"7",
    "gn:asciiname":"La Vieja",
    "gn:country_code":"MX",
    "gn:dem":1075,
    "gn:feature_class":"P",
    "gn:feature_code":"PPL",
    "gn:name":"La Vieja",
    "gn:population":20,
    "gn:timezone":"America/Monterrey",
    "iso:country":"MX",
    "wof:name":"La Vieja",
    "wof:placetype":"locality",
    "wof:population":20
},
  "geometry": {"coordinates":[-99.6919,24.12369],"type":"Point"}
}