{
  "type": "Feature",
  "properties": {
    "gn:admin1_code":"30",
    "gn:admin2_code":"160.0",
    "gn:asciiname":"Zacatal",
    "gn:country_code":"MX",
    "gn:dem":12,
    "gn:feature_class":"P",
    "gn:feature_code":"PPL",
    "gn:name":"Zacatal",
    "gn:population":450,
    "gn:timezone":"America/Mexico_City",
    "iso:country":"MX",
    "wof:name":"Zacatal",
    "wof:placetype":"locality",
    "wof:population":450
},
  "geometry": {"coordinates":[-97.51806000000001,20.93139],"type":"Point"}
}