{
  "type": "Feature",
  "properties": {
    "gn:admin1_code":"6",
    "gn:admin2_code":"29.0",
    "gn:asciiname":"Sapopa",
    "gn:country_code":"MX",
    "gn:dem":1062,
    "gn:feature_class":"P",
    "gn:feature_code":"PPL",
    "gn:name":"Sapopa",
    "gn:population":0,
    "gn:timezone":"America/Chihuahua",
    "iso:country":"MX",
    "wof:name":"Sapopa",
    "wof:placetype":"locality"
},
  "geometry": {"coordinates":[-107.08333,25.86667000000001],"type":"Point"}
}