{
  "type": "Feature",
  "properties": {
    "gn:admin1_code":"20",
    "gn:admin2_code":"321.0",
    "gn:asciiname":"Zandaye",
    "gn:country_code":"MX",
    "gn:dem":2140,
    "gn:feature_class":"P",
    "gn:feature_code":"PPL",
    "gn:name":"Zandaye",
    "gn:population":8,
    "gn:timezone":"America/Mexico_City",
    "iso:country":"MX",
    "wof:name":"Zandaye",
    "wof:placetype":"locality",
    "wof:population":8
},
  "geometry": {"coordinates":[-97.53806,17.81833],"type":"Point"}
}