{
  "type": "Feature",
  "properties": {
    "gn:admin1_code":"2",
    "gn:admin2_code":"2.0",
    "gn:asciiname":"Mesa Arenosa de Andrade (Villa Zapata)",
    "gn:country_code":"MX",
    "gn:dem":21,
    "gn:feature_class":"P",
    "gn:feature_code":"PPL",
    "gn:name":"Mesa Arenosa de Andrade (Villa Zapata)",
    "gn:population":474,
    "gn:timezone":"America/Tijuana",
    "iso:country":"MX",
    "wof:name":"Mesa Arenosa de Andrade (Villa Zapata)",
    "wof:placetype":"locality",
    "wof:population":474
},
  "geometry": {"coordinates":[-115.20806,32.62667],"type":"Point"}
}