{
  "type": "Feature",
  "properties": {
    "gn:admin1_code":"6",
    "gn:admin2_code":"36.0",
    "gn:asciiname":"Sombreretillo",
    "gn:cc2":"MX",
    "gn:country_code":"MX",
    "gn:dem":1425,
    "gn:feature_class":"P",
    "gn:feature_code":"PPL",
    "gn:name":"Sombreretillo",
    "gn:population":0,
    "gn:timezone":"America/Chihuahua",
    "iso:country":"MX",
    "name:und_x_variant":[
        "Rancho Sombreretillo",
        "Sombreretillo"
    ],
    "wof:name":"Sombreretillo",
    "wof:placetype":"locality"
},
  "geometry": {"coordinates":[-104.43333,27.08333],"type":"Point"}
}