{
  "type": "Feature",
  "properties": {
    "gn:admin1_code":"14.0",
    "gn:admin2_code":"53.0",
    "gn:asciiname":"El Molino",
    "gn:country_code":"MX",
    "gn:dem":2061,
    "gn:feature_class":"P",
    "gn:feature_code":"PPL",
    "gn:name":"El Molino",
    "gn:population":0,
    "gn:timezone":"America/Mexico_City",
    "iso:country":"MX",
    "name:spa_x_preferred":[
        "El Molino"
    ],
    "wof:name":"El Molino",
    "wof:placetype":"locality"
},
  "geometry": {"coordinates":[-101.86750000000001,21.74118],"type":"Point"}
}