{
  "type": "Feature",
  "properties": {
    "gn:admin1_code":"30",
    "gn:admin2_code":"31.0",
    "gn:asciiname":"Loma de Piedra",
    "gn:country_code":"MX",
    "gn:dem":139,
    "gn:feature_class":"P",
    "gn:feature_code":"PPL",
    "gn:name":"Loma de Piedra",
    "gn:population":111,
    "gn:timezone":"America/Mexico_City",
    "iso:country":"MX",
    "wof:name":"Loma de Piedra",
    "wof:placetype":"locality",
    "wof:population":111
},
  "geometry": {"coordinates":[-96.49250000000001,18.79556],"type":"Point"}
}