{
  "type": "Feature",
  "properties": {
    "gn:admin1_code":"26",
    "gn:admin2_code":"18.0",
    "gn:asciiname":"Martin Cota (Bloque 802)",
    "gn:country_code":"MX",
    "gn:dem":27,
    "gn:feature_class":"P",
    "gn:feature_code":"PPL",
    "gn:name":"Mart\u00edn Cota (Bloque 802)",
    "gn:population":7,
    "gn:timezone":"America/Hermosillo",
    "iso:country":"MX",
    "name:und_x_variant":[
        "Mart\u00edn Cota (Bloque 802)"
    ],
    "wof:name":"Martin Cota (Bloque 802)",
    "wof:placetype":"locality",
    "wof:population":7
},
  "geometry": {"coordinates":[-109.99444,27.38194],"type":"Point"}
}