{
  "type": "Feature",
  "properties": {
    "gn:admin1_code":"6",
    "gn:admin2_code":"7",
    "gn:asciiname":"Los Fresnos",
    "gn:country_code":"MX",
    "gn:dem":1809,
    "gn:feature_class":"P",
    "gn:feature_code":"PPL",
    "gn:name":"Los Fresnos",
    "gn:population":19,
    "gn:timezone":"America/Chihuahua",
    "iso:country":"MX",
    "wof:name":"Los Fresnos",
    "wof:placetype":"locality",
    "wof:population":19
},
  "geometry": {"coordinates":[-106.24160999999999,26.59624],"type":"Point"}
}