{
  "type": "Feature",
  "properties": {
    "gn:admin1_code":"25.0",
    "gn:admin2_code":"1.0",
    "gn:asciiname":"Ejido Topolobampo",
    "gn:country_code":"MX",
    "gn:dem":3,
    "gn:feature_class":"P",
    "gn:feature_code":"PPL",
    "gn:name":"Ejido Topolobampo",
    "gn:population":0,
    "gn:timezone":"America/Mazatlan",
    "iso:country":"MX",
    "name:spa_x_preferred":[
        "Ejido Topolobampo"
    ],
    "name:spa_x_variant":[
        "Topolobampo"
    ],
    "wof:name":"Ejido Topolobampo",
    "wof:placetype":"locality"
},
  "geometry": {"coordinates":[-109.05681,25.62981],"type":"Point"}
}