{
  "type": "Feature",
  "properties": {
    "gn:admin1_code":"6",
    "gn:admin2_code":"3.0",
    "gn:asciiname":"El Preson de Esmeralda",
    "gn:country_code":"MX",
    "gn:dem":1492,
    "gn:feature_class":"P",
    "gn:feature_code":"PPL",
    "gn:name":"El Pres\u00f3n de Esmeralda",
    "gn:population":0,
    "gn:timezone":"America/Chihuahua",
    "iso:country":"MX",
    "name:spa_x_preferred":[
        "El Pres\u00f3n de Esmeralda"
    ],
    "wof:name":"El Preson de Esmeralda",
    "wof:placetype":"locality"
},
  "geometry": {"coordinates":[-105.31265,27.13412000000001],"type":"Point"}
}