{
  "type": "Feature",
  "properties": {
    "gn:admin1_code":"6",
    "gn:admin2_code":"3.0",
    "gn:asciiname":"San Manuel",
    "gn:country_code":"MX",
    "gn:dem":1467,
    "gn:feature_class":"P",
    "gn:feature_code":"PPL",
    "gn:name":"San Manuel",
    "gn:population":0,
    "gn:timezone":"America/Chihuahua",
    "iso:country":"MX",
    "name:ceb_x_preferred":[
        "San Manuel"
    ],
    "name:deu_x_preferred":[
        "San Manuel"
    ],
    "name:fra_x_preferred":[
        "San Manuel"
    ],
    "name:ilo_x_preferred":[
        "San Manuel"
    ],
    "name:ita_x_preferred":[
        "San Manuel"
    ],
    "name:nld_x_preferred":[
        "San Manuel"
    ],
    "name:por_x_preferred":[
        "San Manuel"
    ],
    "name:spa_x_preferred":[
        "San Manuel"
    ],
    "name:srp_x_preferred":[
        "\u0421\u0430\u043d \u041c\u0430\u043d\u0443\u0435\u043b"
    ],
    "name:swe_x_preferred":[
        "San Manuel"
    ],
    "name:war_x_preferred":[
        "San Manuel"
    ],
    "wof:name":"San Manuel",
    "wof:placetype":"locality"
},
  "geometry": {"coordinates":[-105.27046,27.17675],"type":"Point"}
}