{
  "type": "Feature",
  "properties": {
    "gn:admin1_code":"5",
    "gn:admin2_code":"64.0",
    "gn:asciiname":"Silailja",
    "gn:country_code":"MX",
    "gn:dem":1219,
    "gn:feature_class":"P",
    "gn:feature_code":"PPL",
    "gn:name":"Silailja",
    "gn:population":282,
    "gn:timezone":"America/Mexico_City",
    "iso:country":"MX",
    "wof:name":"Silailja",
    "wof:placetype":"locality",
    "wof:population":282
},
  "geometry": {"coordinates":[-92.14028,16.76194],"type":"Point"}
}