{
  "type": "Feature",
  "properties": {
    "gn:admin1_code":"4",
    "gn:admin2_code":"11.0",
    "gn:asciiname":"El Puma",
    "gn:country_code":"MX",
    "gn:dem":91,
    "gn:feature_class":"P",
    "gn:feature_code":"PPL",
    "gn:name":"El Puma",
    "gn:population":8,
    "gn:timezone":"America/Merida",
    "iso:country":"MX",
    "wof:name":"El Puma",
    "wof:placetype":"locality",
    "wof:population":8
},
  "geometry": {"coordinates":[-90.43000000000001,17.97332999999999],"type":"Point"}
}