{
  "type": "Feature",
  "properties": {
    "gn:admin1_code":"20",
    "gn:admin2_code":"417.0",
    "gn:asciiname":"Colonia Emiliano Zapata",
    "gn:country_code":"MX",
    "gn:dem":302,
    "gn:feature_class":"P",
    "gn:feature_code":"PPL",
    "gn:name":"Colonia Emiliano Zapata",
    "gn:population":356,
    "gn:timezone":"America/Mexico_City",
    "iso:country":"MX",
    "wof:name":"Colonia Emiliano Zapata",
    "wof:placetype":"locality",
    "wof:population":356
},
  "geometry": {"coordinates":[-96.18889,17.84],"type":"Point"}
}