{
  "type": "Feature",
  "properties": {
    "gn:admin1_code":"15",
    "gn:admin2_code":"7.0",
    "gn:asciiname":"San Miguel Tenextepec",
    "gn:country_code":"MX",
    "gn:dem":2332,
    "gn:feature_class":"P",
    "gn:feature_code":"PPL",
    "gn:name":"San Miguel Tenextepec",
    "gn:population":0,
    "gn:timezone":"America/Mexico_City",
    "iso:country":"MX",
    "name:und_x_variant":[
        "San Miguel"
    ],
    "wof:name":"San Miguel Tenextepec",
    "wof:placetype":"locality"
},
  "geometry": {"coordinates":[-100.02979999999999,19.26368],"type":"Point"}
}