{
  "type": "Feature",
  "properties": {
    "gn:admin1_code":"28",
    "gn:admin2_code":"21.0",
    "gn:asciiname":"Quintero",
    "gn:country_code":"MX",
    "gn:dem":118,
    "gn:feature_class":"P",
    "gn:feature_code":"PPL",
    "gn:name":"Quintero",
    "gn:population":0,
    "gn:timezone":"America/Monterrey",
    "iso:country":"MX",
    "name:spa_x_preferred":[
        "Quintero"
    ],
    "wof:name":"Quintero",
    "wof:placetype":"locality"
},
  "geometry": {"coordinates":[-99.03583999999999,22.66289],"type":"Point"}
}