{
  "type": "Feature",
  "properties": {
    "gn:admin1_code":"5.0",
    "gn:admin2_code":"20.0",
    "gn:asciiname":"Santa Martha",
    "gn:country_code":"MX",
    "gn:dem":595,
    "gn:feature_class":"P",
    "gn:feature_code":"PPL",
    "gn:name":"Santa Martha",
    "gn:population":0,
    "gn:timezone":"America/Mexico_City",
    "iso:country":"MX",
    "name:spa_x_preferred":[
        "Santa Martha"
    ],
    "wof:name":"Santa Martha",
    "wof:placetype":"locality"
},
  "geometry": {"coordinates":[-92.83627,16.23911],"type":"Point"}
}