{
  "type": "Feature",
  "properties": {
    "gn:admin1_code":"28",
    "gn:admin2_code":"39",
    "gn:asciiname":"Caudillos del Sur (Palos Altos)",
    "gn:country_code":"MX",
    "gn:dem":1116,
    "gn:feature_class":"P",
    "gn:feature_code":"PPL",
    "gn:name":"Caudillos del Sur (Palos Altos)",
    "gn:population":16,
    "gn:timezone":"America/Monterrey",
    "iso:country":"MX",
    "wof:name":"Caudillos del Sur (Palos Altos)",
    "wof:placetype":"locality",
    "wof:population":16
},
  "geometry": {"coordinates":[-99.70860999999999,22.94611],"type":"Point"}
}