{
  "type": "Feature",
  "properties": {
    "gn:admin1_code":"6.0",
    "gn:admin2_code":"61.0",
    "gn:asciiname":"Jose Maria Morelos",
    "gn:country_code":"MX",
    "gn:dem":1315,
    "gn:feature_class":"P",
    "gn:feature_code":"PPL",
    "gn:name":"Jos\u00e9 Mar\u00eda Morelos",
    "gn:population":0,
    "gn:timezone":"America/Chihuahua",
    "iso:country":"MX",
    "name:spa_x_preferred":[
        "Jos\u00e9 Mar\u00eda Morelos"
    ],
    "wof:name":"Jose Maria Morelos",
    "wof:placetype":"locality"
},
  "geometry": {"coordinates":[-105.90018999999999,27.92021],"type":"Point"}
}