{
  "type": "Feature",
  "properties": {
    "gn:admin1_code":"10",
    "gn:admin2_code":"4.0",
    "gn:asciiname":"San Jose de las Vegas",
    "gn:country_code":"MX",
    "gn:dem":1953,
    "gn:feature_class":"P",
    "gn:feature_code":"PPL",
    "gn:name":"San Jos\u00e9 de las Vegas",
    "gn:population":0,
    "gn:timezone":"America/Monterrey",
    "iso:country":"MX",
    "name:spa_x_preferred":[
        "San Jos\u00e9 de las Vegas"
    ],
    "wof:name":"San Jose de las Vegas",
    "wof:placetype":"locality"
},
  "geometry": {"coordinates":[-103.85107000000001,24.57737],"type":"Point"}
}