{
  "type": "Feature",
  "properties": {
    "gn:admin1_code":"6",
    "gn:admin2_code":"65.0",
    "gn:asciiname":"Trigo",
    "gn:country_code":"MX",
    "gn:dem":1762,
    "gn:feature_class":"P",
    "gn:feature_code":"PPL",
    "gn:name":"Trigo",
    "gn:population":0,
    "gn:timezone":"America/Chihuahua",
    "iso:country":"MX",
    "name:ceb_x_preferred":[
        "Trigo"
    ],
    "name:fra_x_preferred":[
        "Trigo"
    ],
    "name:glg_x_preferred":[
        "Trigo"
    ],
    "name:spa_x_preferred":[
        "Trigo"
    ],
    "name:srp_x_preferred":[
        "\u0422\u0440\u0438\u0433\u043e"
    ],
    "name:swe_x_preferred":[
        "Trigo"
    ],
    "wof:name":"Trigo",
    "wof:placetype":"locality"
},
  "geometry": {"coordinates":[-107.95704000000001,26.83817],"type":"Point"}
}