{
  "type": "Feature",
  "properties": {
    "gn:admin1_code":"12",
    "gn:admin2_code":"63.0",
    "gn:asciiname":"Laguna Seca",
    "gn:country_code":"MX",
    "gn:dem":2240,
    "gn:feature_class":"P",
    "gn:feature_code":"PPL",
    "gn:name":"Laguna Seca",
    "gn:population":438,
    "gn:timezone":"America/Mexico_City",
    "iso:country":"MX",
    "wof:name":"Laguna Seca",
    "wof:placetype":"locality",
    "wof:population":438
},
  "geometry": {"coordinates":[-98.78806,17.27528],"type":"Point"}
}