{
  "type": "Feature",
  "properties": {
    "gn:admin1_code":"20",
    "gn:admin2_code":"67",
    "gn:asciiname":"Gloria Antonio Cruz",
    "gn:country_code":"MX",
    "gn:dem":1639,
    "gn:feature_class":"P",
    "gn:feature_code":"PPL",
    "gn:name":"Gloria Antonio Cruz",
    "gn:population":42,
    "gn:timezone":"America/Mexico_City",
    "iso:country":"MX",
    "wof:name":"Gloria Antonio Cruz",
    "wof:placetype":"locality",
    "wof:population":42
},
  "geometry": {"coordinates":[-96.69194,17.0975],"type":"Point"}
}