{
  "type": "Feature",
  "properties": {
    "gn:admin1_code":"26",
    "gn:admin2_code":"39.0",
    "gn:asciiname":"Las Moritas",
    "gn:country_code":"MX",
    "gn:dem":1408,
    "gn:feature_class":"P",
    "gn:feature_code":"PPL",
    "gn:name":"Las Moritas",
    "gn:population":8,
    "gn:timezone":"America/Hermosillo",
    "iso:country":"MX",
    "name:spa_x_preferred":[
        "Las Moritas"
    ],
    "name:und_x_variant":[
        "Hacienda La Morita",
        "Aduana",
        "La Morita"
    ],
    "wof:name":"Las Moritas",
    "wof:placetype":"locality",
    "wof:population":8
},
  "geometry": {"coordinates":[-109.82118,31.26827],"type":"Point"}
}