{
  "type": "Feature",
  "properties": {
    "gn:admin1_code":"5",
    "gn:admin2_code":"30",
    "gn:asciiname":"San Martin",
    "gn:country_code":"MX",
    "gn:dem":677,
    "gn:feature_class":"P",
    "gn:feature_code":"PPL",
    "gn:name":"San Mart\u00edn",
    "gn:population":16,
    "gn:timezone":"America/Mexico_City",
    "iso:country":"MX",
    "name:und_x_variant":[
        "San Mart\u00edn"
    ],
    "wof:name":"San Martin",
    "wof:placetype":"locality",
    "wof:population":16
},
  "geometry": {"coordinates":[-92.38361,15.775],"type":"Point"}
}