{
  "type": "Feature",
  "properties": {
    "gn:admin1_code":"30",
    "gn:admin2_code":"139.0",
    "gn:asciiname":"La Perdida",
    "gn:country_code":"MX",
    "gn:dem":14,
    "gn:feature_class":"P",
    "gn:feature_code":"PPL",
    "gn:name":"La Perdida",
    "gn:population":0,
    "gn:timezone":"America/Mexico_City",
    "iso:country":"MX",
    "name:spa_x_preferred":[
        "La Perdida"
    ],
    "wof:name":"La Perdida",
    "wof:placetype":"locality"
},
  "geometry": {"coordinates":[-95.47211,18.55572],"type":"Point"}
}