{
  "type": "Feature",
  "properties": {
    "gn:admin1_code":"20",
    "gn:admin2_code":"526.0",
    "gn:asciiname":"Santa Maria Tiltepec",
    "gn:country_code":"MX",
    "gn:dem":477,
    "gn:feature_class":"P",
    "gn:feature_code":"PPL",
    "gn:name":"Santa Mar\u00eda Tiltepec",
    "gn:population":0,
    "gn:timezone":"America/Mexico_City",
    "iso:country":"MX",
    "name:spa_x_preferred":[
        "Santa Mar\u00eda Tiltepec"
    ],
    "name:und_x_variant":[
        "Tiltepec",
        "Santa Mar\u00eda Magdalena Tiltepec"
    ],
    "wof:name":"Santa Maria Tiltepec",
    "wof:placetype":"locality"
},
  "geometry": {"coordinates":[-97.17036,16.0627],"type":"Point"}
}