{
  "type": "Feature",
  "properties": {
    "gn:admin1_code":"2.0",
    "gn:asciiname":"El Canon",
    "gn:country_code":"MX",
    "gn:dem":697,
    "gn:feature_class":"P",
    "gn:feature_code":"PPL",
    "gn:name":"El Ca\u00f1\u00f3n",
    "gn:population":0,
    "gn:timezone":"America/Tijuana",
    "iso:country":"MX",
    "wof:name":"El Canon",
    "wof:placetype":"locality"
},
  "geometry": {"coordinates":[-116.56667,32.58333],"type":"Point"}
}