{
  "type": "Feature",
  "properties": {
    "gn:admin1_code":"16.0",
    "gn:admin2_code":"96.0",
    "gn:asciiname":"La Soyamichera",
    "gn:country_code":"MX",
    "gn:dem":679,
    "gn:feature_class":"P",
    "gn:feature_code":"PPL",
    "gn:name":"La Soyamichera",
    "gn:population":0,
    "gn:timezone":"America/Mexico_City",
    "iso:country":"MX",
    "name:spa_x_preferred":[
        "La Soyamichera"
    ],
    "wof:name":"La Soyamichera",
    "wof:placetype":"locality"
},
  "geometry": {"coordinates":[-102.75003,18.51939],"type":"Point"}
}