{
  "type": "Feature",
  "properties": {
    "gn:admin1_code":"14",
    "gn:admin2_code":"8.0",
    "gn:asciiname":"El Garbanzo",
    "gn:country_code":"MX",
    "gn:dem":2089,
    "gn:feature_class":"P",
    "gn:feature_code":"PPL",
    "gn:name":"El Garbanzo",
    "gn:population":6,
    "gn:timezone":"America/Mexico_City",
    "iso:country":"MX",
    "wof:name":"El Garbanzo",
    "wof:placetype":"locality",
    "wof:population":6
},
  "geometry": {"coordinates":[-102.26000000000001,20.86167],"type":"Point"}
}