{
  "type": "Feature",
  "properties": {
    "gn:admin1_code":"15",
    "gn:admin2_code":"8",
    "gn:asciiname":"Los Ciruelos (Rancho los Ciruelos)",
    "gn:country_code":"MX",
    "gn:dem":826,
    "gn:feature_class":"P",
    "gn:feature_code":"PPL",
    "gn:name":"Los Ciruelos (Rancho los Ciruelos)",
    "gn:population":16,
    "gn:timezone":"America/Mexico_City",
    "iso:country":"MX",
    "wof:name":"Los Ciruelos (Rancho los Ciruelos)",
    "wof:placetype":"locality",
    "wof:population":16
},
  "geometry": {"coordinates":[-100.43357,18.66904],"type":"Point"}
}