{
  "type": "Feature",
  "properties": {
    "gn:admin1_code":"23",
    "gn:admin2_code":"6.0",
    "gn:asciiname":"Los Tres Hermanos",
    "gn:country_code":"MX",
    "gn:dem":19,
    "gn:feature_class":"P",
    "gn:feature_code":"PPL",
    "gn:name":"Los Tres Hermanos",
    "gn:population":6,
    "gn:timezone":"America/Cancun",
    "iso:country":"MX",
    "wof:name":"Los Tres Hermanos",
    "wof:placetype":"locality",
    "wof:population":6
},
  "geometry": {"coordinates":[-88.69725,19.75494],"type":"Point"}
}