{
  "type": "Feature",
  "properties": {
    "gn:admin1_code":"7.0",
    "gn:admin2_code":"9.0",
    "gn:asciiname":"Alamito",
    "gn:country_code":"MX",
    "gn:dem":1118,
    "gn:feature_class":"P",
    "gn:feature_code":"PPL",
    "gn:name":"Alamito",
    "gn:population":802,
    "gn:timezone":"America/Monterrey",
    "iso:country":"MX",
    "wof:name":"Alamito",
    "wof:placetype":"locality",
    "wof:population":802
},
  "geometry": {"coordinates":[-103.30444,25.72306],"type":"Point"}
}