{
  "type": "Feature",
  "properties": {
    "gn:admin1_code":"5",
    "gn:admin2_code":"107",
    "gn:asciiname":"Ismael Cruz",
    "gn:country_code":"MX",
    "gn:dem":626,
    "gn:feature_class":"P",
    "gn:feature_code":"PPL",
    "gn:name":"Ismael Cruz",
    "gn:population":10,
    "gn:timezone":"America/Mexico_City",
    "iso:country":"MX",
    "wof:name":"Ismael Cruz",
    "wof:placetype":"locality",
    "wof:population":10
},
  "geometry": {"coordinates":[-93.10556,16.105],"type":"Point"}
}