{
  "type": "Feature",
  "properties": {
    "gn:admin1_code":"14",
    "gn:admin2_code":"25.0",
    "gn:asciiname":"Tulimic del Rosario",
    "gn:country_code":"MX",
    "gn:dem":1617,
    "gn:feature_class":"P",
    "gn:feature_code":"PPL",
    "gn:name":"Tulimic del Rosario",
    "gn:population":0,
    "gn:timezone":"America/Mexico_City",
    "iso:country":"MX",
    "name:und_x_variant":[
        "Tulimic",
        "Tulimic del Rosario"
    ],
    "wof:name":"Tulimic del Rosario",
    "wof:placetype":"locality"
},
  "geometry": {"coordinates":[-103.32274,21.99811],"type":"Point"}
}