{
  "type": "Feature",
  "properties": {
    "gn:admin1_code":"25.0",
    "gn:admin2_code":"1.0",
    "gn:asciiname":"Camayeca",
    "gn:country_code":"MX",
    "gn:dem":16,
    "gn:feature_class":"P",
    "gn:feature_code":"PPL",
    "gn:name":"Camayeca",
    "gn:population":217,
    "gn:timezone":"America/Mazatlan",
    "iso:country":"MX",
    "wof:name":"Camayeca",
    "wof:placetype":"locality",
    "wof:population":217
},
  "geometry": {"coordinates":[-109.06917,25.95583],"type":"Point"}
}