{
  "type": "Feature",
  "properties": {
    "gn:admin1_code":"6",
    "gn:admin2_code":"51.0",
    "gn:asciiname":"El Manzano",
    "gn:country_code":"MX",
    "gn:dem":1975,
    "gn:feature_class":"P",
    "gn:feature_code":"PPL",
    "gn:name":"El Manzano",
    "gn:population":41,
    "gn:timezone":"America/Chihuahua",
    "iso:country":"MX",
    "name:spa_x_preferred":[
        "El Manzano"
    ],
    "wof:name":"El Manzano",
    "wof:placetype":"locality",
    "wof:population":41
},
  "geometry": {"coordinates":[-108.25328,28.04852],"type":"Point"}
}