{
  "type": "Feature",
  "properties": {
    "gn:admin1_code":"12",
    "gn:admin2_code":"57.0",
    "gn:asciiname":"Boca Chica (El Bajadero)",
    "gn:country_code":"MX",
    "gn:dem":10,
    "gn:feature_class":"P",
    "gn:feature_code":"PPL",
    "gn:name":"Boca Chica (El Bajadero)",
    "gn:population":6,
    "gn:timezone":"America/Mexico_City",
    "iso:country":"MX",
    "wof:name":"Boca Chica (El Bajadero)",
    "wof:placetype":"locality",
    "wof:population":6
},
  "geometry": {"coordinates":[-100.64558,17.13913],"type":"Point"}
}