{
  "type": "Feature",
  "properties": {
    "gn:admin1_code":"24",
    "gn:admin2_code":"43.0",
    "gn:asciiname":"Salitre Rangel",
    "gn:country_code":"MX",
    "gn:dem":1804,
    "gn:feature_class":"P",
    "gn:feature_code":"PPL",
    "gn:name":"Salitre Rangel",
    "gn:population":0,
    "gn:timezone":"America/Mexico_City",
    "iso:country":"MX",
    "wof:name":"Salitre Rangel",
    "wof:placetype":"locality"
},
  "geometry": {"coordinates":[-100.56667,21.65],"type":"Point"}
}