{
  "type": "Feature",
  "properties": {
    "gn:admin1_code":"6",
    "gn:admin2_code":"46.0",
    "gn:asciiname":"Los Bajios",
    "gn:country_code":"MX",
    "gn:dem":1984,
    "gn:feature_class":"P",
    "gn:feature_code":"PPL",
    "gn:name":"Los Bajios",
    "gn:population":0,
    "gn:timezone":"America/Mazatlan",
    "iso:country":"MX",
    "name:spa_x_preferred":[
        "Aserradero San Vicente"
    ],
    "name:spa_x_variant":[
        "Los Bajios"
    ],
    "name:und_x_variant":[
        "San Vicente"
    ],
    "wof:name":"Los Bajios",
    "wof:placetype":"locality"
},
  "geometry": {"coordinates":[-107.97011000000001,26.71497],"type":"Point"}
}