{
  "type": "Feature",
  "properties": {
    "gn:admin1_code":"11",
    "gn:asciiname":"Turcal",
    "gn:cc2":"MX",
    "gn:country_code":"MX",
    "gn:dem":8,
    "gn:feature_class":"P",
    "gn:feature_code":"PPL",
    "gn:name":"Turcal",
    "gn:population":0,
    "gn:timezone":"America/Mexico_City",
    "iso:country":"MX",
    "name:und_x_variant":[
        "Turcol",
        "Turcal"
    ],
    "wof:name":"Turcal",
    "wof:placetype":"locality"
},
  "geometry": {"coordinates":[-94.41667,17.85],"type":"Point"}
}