{
  "type": "Feature",
  "properties": {
    "gn:admin1_code":"30.0",
    "gn:asciiname":"La Majagua",
    "gn:country_code":"MX",
    "gn:dem":7,
    "gn:feature_class":"P",
    "gn:feature_code":"PPL",
    "gn:name":"La Majagua",
    "gn:population":0,
    "gn:timezone":"America/Mexico_City",
    "iso:country":"MX",
    "name:spa_x_preferred":[
        "La Majagua"
    ],
    "wof:name":"La Majagua",
    "wof:placetype":"locality"
},
  "geometry": {"coordinates":[-95.53877,18.39227],"type":"Point"}
}