{
  "type": "Feature",
  "properties": {
    "gn:admin1_code":"21",
    "gn:asciiname":"Las Rosas",
    "gn:country_code":"MX",
    "gn:dem":2384,
    "gn:feature_class":"P",
    "gn:feature_code":"PPL",
    "gn:name":"Las Rosas",
    "gn:population":0,
    "gn:timezone":"America/Mexico_City",
    "iso:country":"MX",
    "name:spa_x_preferred":[
        "Las Rosas"
    ],
    "wof:name":"Las Rosas",
    "wof:placetype":"locality"
},
  "geometry": {"coordinates":[-98.44065999999999,19.38917],"type":"Point"}
}