{
  "type": "Feature",
  "properties": {
    "gn:admin1_code":"5",
    "gn:admin2_code":"22",
    "gn:asciiname":"Mashilo",
    "gn:country_code":"MX",
    "gn:dem":462,
    "gn:feature_class":"P",
    "gn:feature_code":"PPL",
    "gn:name":"Mashilo",
    "gn:population":34,
    "gn:timezone":"America/Mexico_City",
    "iso:country":"MX",
    "wof:name":"Mashilo",
    "wof:placetype":"locality",
    "wof:population":34
},
  "geometry": {"coordinates":[-92.55,17.07944],"type":"Point"}
}