{
  "type": "Feature",
  "properties": {
    "gn:admin1_code":"21",
    "gn:admin2_code":"200.0",
    "gn:asciiname":"Atzalan",
    "gn:country_code":"MX",
    "gn:dem":1583,
    "gn:feature_class":"P",
    "gn:feature_code":"PPL",
    "gn:name":"Atzal\u00e1n",
    "gn:population":346,
    "gn:timezone":"America/Mexico_City",
    "iso:country":"MX",
    "name:und_x_variant":[
        "Atzal\u00e1n"
    ],
    "wof:name":"Atzalan",
    "wof:placetype":"locality",
    "wof:population":346
},
  "geometry": {"coordinates":[-97.62139000000001,19.89722],"type":"Point"}
}