{
  "type": "Feature",
  "properties": {
    "gn:admin1_code":"13",
    "gn:admin2_code":"6.0",
    "gn:asciiname":"Cuarta Manzana Toxtha",
    "gn:country_code":"MX",
    "gn:dem":1886,
    "gn:feature_class":"P",
    "gn:feature_code":"PPL",
    "gn:name":"Cuarta Manzana Toxtha",
    "gn:population":192,
    "gn:timezone":"America/Mexico_City",
    "iso:country":"MX",
    "wof:name":"Cuarta Manzana Toxtha",
    "wof:placetype":"locality",
    "wof:population":192
},
  "geometry": {"coordinates":[-99.35527999999999,20.40889],"type":"Point"}
}