{
  "type": "Feature",
  "properties": {
    "gn:admin1_code":"20",
    "gn:admin2_code":"44.0",
    "gn:asciiname":"Chucho Zanatta",
    "gn:country_code":"MX",
    "gn:dem":47,
    "gn:feature_class":"P",
    "gn:feature_code":"PPL",
    "gn:name":"Chucho Zanatta",
    "gn:population":7,
    "gn:timezone":"America/Mexico_City",
    "iso:country":"MX",
    "wof:name":"Chucho Zanatta",
    "wof:placetype":"locality",
    "wof:population":7
},
  "geometry": {"coordinates":[-95.86722,18.07806],"type":"Point"}
}