{
  "type": "Feature",
  "properties": {
    "gn:admin1_code":"14.0",
    "gn:admin2_code":"61.0",
    "gn:asciiname":"Mesa de San Andres",
    "gn:country_code":"MX",
    "gn:dem":2001,
    "gn:feature_class":"P",
    "gn:feature_code":"PPL",
    "gn:name":"Mesa de San Andr\u00e9s",
    "gn:population":0,
    "gn:timezone":"America/Mexico_City",
    "iso:country":"MX",
    "name:spa_x_preferred":[
        "Mesa de San Andr\u00e9s"
    ],
    "wof:name":"Mesa de San Andres",
    "wof:placetype":"locality"
},
  "geometry": {"coordinates":[-104.22843,22.17722],"type":"Point"}
}