{
  "type": "Feature",
  "properties": {
    "gn:admin1_code":"24",
    "gn:admin2_code":"1.0",
    "gn:asciiname":"Casita Blanca",
    "gn:country_code":"MX",
    "gn:dem":2135,
    "gn:feature_class":"P",
    "gn:feature_code":"PPL",
    "gn:name":"Casita Blanca",
    "gn:population":28,
    "gn:timezone":"America/Mexico_City",
    "iso:country":"MX",
    "wof:name":"Casita Blanca",
    "wof:placetype":"locality",
    "wof:population":28
},
  "geometry": {"coordinates":[-101.21278,22.54417],"type":"Point"}
}