{
  "type": "Feature",
  "properties": {
    "gn:admin1_code":"7.0",
    "gn:admin2_code":"20.0",
    "gn:asciiname":"Babia",
    "gn:country_code":"MX",
    "gn:dem":710,
    "gn:feature_class":"P",
    "gn:feature_code":"PPL",
    "gn:name":"Babia",
    "gn:population":0,
    "gn:timezone":"America/Monterrey",
    "iso:country":"MX",
    "name:spa_x_preferred":[
        "Babia"
    ],
    "wof:name":"Babia",
    "wof:placetype":"locality"
},
  "geometry": {"coordinates":[-101.93055,28.48127],"type":"Point"}
}