{
  "type": "Feature",
  "properties": {
    "gn:admin1_code":"10",
    "gn:admin2_code":"7.0",
    "gn:asciiname":"Santa Lucina",
    "gn:country_code":"MX",
    "gn:dem":1120,
    "gn:feature_class":"P",
    "gn:feature_code":"PPL",
    "gn:name":"Santa Lucina",
    "gn:population":5,
    "gn:timezone":"America/Monterrey",
    "iso:country":"MX",
    "wof:name":"Santa Lucina",
    "wof:placetype":"locality",
    "wof:population":5
},
  "geometry": {"coordinates":[-103.44423,25.68612000000001],"type":"Point"}
}