{
  "type": "Feature",
  "properties": {
    "gn:admin1_code":"25",
    "gn:admin2_code":"16",
    "gn:asciiname":"El Verano",
    "gn:country_code":"MX",
    "gn:dem":57,
    "gn:feature_class":"P",
    "gn:feature_code":"PPL",
    "gn:name":"El Verano",
    "gn:population":21,
    "gn:timezone":"America/Mazatlan",
    "iso:country":"MX",
    "wof:name":"El Verano",
    "wof:placetype":"locality",
    "wof:population":21
},
  "geometry": {"coordinates":[-106.61587,23.77405],"type":"Point"}
}