{
  "type": "Feature",
  "properties": {
    "gn:admin1_code":"25",
    "gn:admin2_code":"6.0",
    "gn:asciiname":"Granja San Roberto (Las Higueras)",
    "gn:country_code":"MX",
    "gn:dem":6,
    "gn:feature_class":"P",
    "gn:feature_code":"PPL",
    "gn:name":"Granja San Roberto (Las Higueras)",
    "gn:population":5,
    "gn:timezone":"America/Mazatlan",
    "iso:country":"MX",
    "wof:name":"Granja San Roberto (Las Higueras)",
    "wof:placetype":"locality",
    "wof:population":5
},
  "geometry": {"coordinates":[-107.39248000000001,24.40921],"type":"Point"}
}