{
  "type": "Feature",
  "properties": {
    "gn:admin1_code":"11.0",
    "gn:admin2_code":"42.0",
    "gn:asciiname":"Gachupina",
    "gn:country_code":"MX",
    "gn:dem":1715,
    "gn:feature_class":"P",
    "gn:feature_code":"PPL",
    "gn:name":"Gachupina",
    "gn:population":0,
    "gn:timezone":"America/Mexico_City",
    "iso:country":"MX",
    "wof:name":"Gachupina",
    "wof:placetype":"locality"
},
  "geometry": {"coordinates":[-101.16667,20.43333],"type":"Point"}
}