{
  "type": "Feature",
  "properties": {
    "gn:admin1_code":"11.0",
    "gn:admin2_code":"1.0",
    "gn:asciiname":"Ojo de Agua el Zapote",
    "gn:country_code":"MX",
    "gn:dem":1728,
    "gn:feature_class":"P",
    "gn:feature_code":"PPL",
    "gn:name":"Ojo de Agua el Zapote",
    "gn:population":0,
    "gn:timezone":"America/Mexico_City",
    "iso:country":"MX",
    "name:spa_x_preferred":[
        "Ojo de Agua el Zapote"
    ],
    "wof:name":"Ojo de Agua el Zapote",
    "wof:placetype":"locality"
},
  "geometry": {"coordinates":[-101.62332000000001,20.71974],"type":"Point"}
}