{
  "type": "Feature",
  "properties": {
    "gn:admin1_code":"16",
    "gn:admin2_code":"26",
    "gn:asciiname":"Soliman",
    "gn:country_code":"MX",
    "gn:dem":960,
    "gn:feature_class":"P",
    "gn:feature_code":"PPL",
    "gn:name":"Solim\u00e1n",
    "gn:population":18,
    "gn:timezone":"America/Mexico_City",
    "iso:country":"MX",
    "name:ceb_x_preferred":[
        "Soliman"
    ],
    "name:deu_x_preferred":[
        "Soliman"
    ],
    "name:fra_x_preferred":[
        "Soliman"
    ],
    "name:ita_x_preferred":[
        "Soliman"
    ],
    "name:ron_x_preferred":[
        "Soliman"
    ],
    "name:rus_x_preferred":[
        "\u0421\u043e\u043b\u0438\u043c\u0430\u043d"
    ],
    "name:spa_x_preferred":[
        "Solim\u00e1n"
    ],
    "name:ukr_x_preferred":[
        "\u0421\u043e\u043b\u0456\u043c\u0430\u043d"
    ],
    "wof:name":"Soliman",
    "wof:placetype":"locality",
    "wof:population":18
},
  "geometry": {"coordinates":[-103.53139,18.69833],"type":"Point"}
}