{
  "type": "Feature",
  "properties": {
    "gn:admin1_code":"16",
    "gn:admin2_code":"26",
    "gn:asciiname":"Soliman",
    "gn:country_code":"MX",
    "gn:dem":960,
    "gn:feature_class":"P",
    "gn:feature_code":"PPL",
    "gn:name":"Solim\u00e1n",
    "gn:population":18,
    "gn:timezone":"America/Mexico_City",
    "iso:country":"MX",
    "name:und_x_variant":[
        "Solim\u00e1n"
    ],
    "wof:name":"Soliman",
    "wof:placetype":"locality",
    "wof:population":18
},
  "geometry": {"coordinates":[-103.53139,18.69833],"type":"Point"}
}