{
  "type": "Feature",
  "properties": {
    "gn:admin1_code":"26",
    "gn:asciiname":"Las Chinacas",
    "gn:country_code":"MX",
    "gn:dem":1609,
    "gn:feature_class":"P",
    "gn:feature_code":"PPL",
    "gn:name":"Las Chinacas",
    "gn:population":0,
    "gn:timezone":"America/Chihuahua",
    "iso:country":"MX",
    "wof:name":"Las Chinacas",
    "wof:placetype":"locality"
},
  "geometry": {"coordinates":[-108.65000000000001,27.25],"type":"Point"}
}