{
  "type": "Feature",
  "properties": {
    "gn:admin1_code":"5",
    "gn:admin2_code":"79.0",
    "gn:asciiname":"San Isidro Oyomotol",
    "gn:country_code":"MX",
    "gn:dem":916,
    "gn:feature_class":"P",
    "gn:feature_code":"PPL",
    "gn:name":"San Isidro Oyomotol",
    "gn:population":4,
    "gn:timezone":"America/Mexico_City",
    "iso:country":"MX",
    "wof:name":"San Isidro Oyomotol",
    "wof:placetype":"locality",
    "wof:population":4
},
  "geometry": {"coordinates":[-93.20166999999999,16.87917],"type":"Point"}
}