{
  "type": "Feature",
  "properties": {
    "gn:admin1_code":"30.0",
    "gn:admin2_code":"155.0",
    "gn:asciiname":"Huichinal Chila Perez",
    "gn:country_code":"MX",
    "gn:dem":134,
    "gn:feature_class":"P",
    "gn:feature_code":"PPL",
    "gn:name":"Huichinal Chila P\u00e9rez",
    "gn:population":373,
    "gn:timezone":"America/Mexico_City",
    "iso:country":"MX",
    "name:spa_x_preferred":[
        "Huichinal Chila P\u00e9rez"
    ],
    "wof:name":"Huichinal Chila Perez",
    "wof:placetype":"locality",
    "wof:population":373
},
  "geometry": {"coordinates":[-98.13833,21.41528],"type":"Point"}
}