{
  "type": "Feature",
  "properties": {
    "gn:admin1_code":"13",
    "gn:admin2_code":"30.0",
    "gn:asciiname":"Arenalito Remedios",
    "gn:country_code":"MX",
    "gn:dem":1757,
    "gn:feature_class":"P",
    "gn:feature_code":"PPL",
    "gn:name":"Arenalito Remedios",
    "gn:population":0,
    "gn:timezone":"America/Mexico_City",
    "iso:country":"MX",
    "name:spa_x_preferred":[
        "Arenalito"
    ],
    "name:spa_x_variant":[
        "Arenalito Remedios"
    ],
    "wof:name":"Arenalito Remedios",
    "wof:placetype":"locality"
},
  "geometry": {"coordinates":[-99.17916,20.50673],"type":"Point"}
}