{
  "type": "Feature",
  "properties": {
    "gn:admin1_code":"30",
    "gn:admin2_code":"104.0",
    "gn:asciiname":"El Diamante (Francisco Mendez Vazquez)",
    "gn:country_code":"MX",
    "gn:dem":37,
    "gn:feature_class":"P",
    "gn:feature_code":"PPL",
    "gn:name":"El Diamante (Francisco M\u00e9ndez V\u00e1zquez)",
    "gn:population":8,
    "gn:timezone":"America/Mexico_City",
    "iso:country":"MX",
    "name:und_x_variant":[
        "El Diamante (Francisco M\u00e9ndez V\u00e1zquez)"
    ],
    "wof:name":"El Diamante (Francisco Mendez Vazquez)",
    "wof:placetype":"locality",
    "wof:population":8
},
  "geometry": {"coordinates":[-94.80972,18.51611],"type":"Point"}
}