{
  "type": "Feature",
  "properties": {
    "gn:admin1_code":"21",
    "gn:admin2_code":"186.0",
    "gn:asciiname":"Ciudad de Tlatlauquitepec",
    "gn:country_code":"MX",
    "gn:dem":1904,
    "gn:feature_class":"P",
    "gn:feature_code":"PPL",
    "gn:name":"Ciudad de Tlatlauquitepec",
    "gn:population":9047,
    "gn:timezone":"America/Mexico_City",
    "iso:country":"MX",
    "wof:name":"Ciudad de Tlatlauquitepec",
    "wof:placetype":"locality",
    "wof:population":9047
},
  "geometry": {"coordinates":[-97.49527999999999,19.85278],"type":"Point"}
}