{
  "type": "Feature",
  "properties": {
    "gn:admin1_code":"32",
    "gn:admin2_code":"19",
    "gn:asciiname":"La Mesa de las Enramadas",
    "gn:country_code":"MX",
    "gn:dem":1823,
    "gn:feature_class":"P",
    "gn:feature_code":"PPL",
    "gn:name":"La Mesa de las Enramadas",
    "gn:population":20,
    "gn:timezone":"America/Mexico_City",
    "iso:country":"MX",
    "wof:name":"La Mesa de las Enramadas",
    "wof:placetype":"locality",
    "wof:population":20
},
  "geometry": {"coordinates":[-102.83972,21.66389],"type":"Point"}
}