{
  "type": "Feature",
  "properties": {
    "gn:admin1_code":"16",
    "gn:admin2_code":"97",
    "gn:asciiname":"Los Ates",
    "gn:country_code":"MX",
    "gn:dem":1577,
    "gn:feature_class":"P",
    "gn:feature_code":"PPL",
    "gn:name":"Los Ates",
    "gn:population":13,
    "gn:timezone":"America/Mexico_City",
    "iso:country":"MX",
    "wof:name":"Los Ates",
    "wof:placetype":"locality",
    "wof:population":13
},
  "geometry": {"coordinates":[-101.54722,19.12806],"type":"Point"}
}