{
  "type": "Feature",
  "properties": {
    "gn:admin1_code":"16",
    "gn:admin2_code":"26.0",
    "gn:asciiname":"El Mango Arrancado",
    "gn:country_code":"MX",
    "gn:dem":511,
    "gn:feature_class":"P",
    "gn:feature_code":"PPL",
    "gn:name":"El Mango Arrancado",
    "gn:population":9,
    "gn:timezone":"America/Mexico_City",
    "iso:country":"MX",
    "wof:name":"El Mango Arrancado",
    "wof:placetype":"locality",
    "wof:population":9
},
  "geometry": {"coordinates":[-103.49028,18.64083],"type":"Point"}
}