{
  "type": "Feature",
  "properties": {
    "gn:admin1_code":"6.0",
    "gn:admin2_code":"27.0",
    "gn:asciiname":"Perare",
    "gn:country_code":"MX",
    "gn:dem":2164,
    "gn:feature_class":"P",
    "gn:feature_code":"PPL",
    "gn:name":"Perare",
    "gn:population":0,
    "gn:timezone":"America/Chihuahua",
    "iso:country":"MX",
    "name:spa_x_preferred":[
        "Perare"
    ],
    "wof:name":"Perare",
    "wof:placetype":"locality"
},
  "geometry": {"coordinates":[-107.48126999999999,27.52852],"type":"Point"}
}