{
  "type": "Feature",
  "properties": {
    "gn:admin1_code":"11",
    "gn:admin2_code":"7",
    "gn:asciiname":"Los Joaquines (Pozo los Joaquines)",
    "gn:country_code":"MX",
    "gn:dem":1782,
    "gn:feature_class":"P",
    "gn:feature_code":"PPL",
    "gn:name":"Los Joaquines (Pozo los Joaquines)",
    "gn:population":15,
    "gn:timezone":"America/Mexico_City",
    "iso:country":"MX",
    "wof:name":"Los Joaquines (Pozo los Joaquines)",
    "wof:placetype":"locality",
    "wof:population":15
},
  "geometry": {"coordinates":[-100.78111,20.65111],"type":"Point"}
}