{
  "type": "Feature",
  "properties": {
    "gn:admin1_code":"11",
    "gn:admin2_code":"26.0",
    "gn:asciiname":"San Francisco de Ortega",
    "gn:country_code":"MX",
    "gn:dem":1745,
    "gn:feature_class":"P",
    "gn:feature_code":"PPL",
    "gn:name":"San Francisco de Ortega",
    "gn:population":0,
    "gn:timezone":"America/Mexico_City",
    "iso:country":"MX",
    "name:spa_x_preferred":[
        "San Francisco de Ortega"
    ],
    "name:und_x_variant":[
        "Ortega"
    ],
    "wof:name":"San Francisco de Ortega",
    "wof:placetype":"locality"
},
  "geometry": {"coordinates":[-101.56138,20.85115],"type":"Point"}
}