{
  "type": "Feature",
  "properties": {
    "gn:admin1_code":"5",
    "gn:admin2_code":"59.0",
    "gn:asciiname":"Nuevo Chetumal",
    "gn:country_code":"MX",
    "gn:dem":569,
    "gn:feature_class":"P",
    "gn:feature_code":"PPL",
    "gn:name":"Nuevo Chetumal",
    "gn:population":5,
    "gn:timezone":"America/Mexico_City",
    "iso:country":"MX",
    "wof:name":"Nuevo Chetumal",
    "wof:placetype":"locality",
    "wof:population":5
},
  "geometry": {"coordinates":[-91.30194,16.84694],"type":"Point"}
}