{
  "type": "Feature",
  "properties": {
    "gn:admin1_code":"7",
    "gn:admin2_code":"5.0",
    "gn:asciiname":"Vacas",
    "gn:country_code":"MX",
    "gn:dem":570,
    "gn:feature_class":"P",
    "gn:feature_code":"PPL",
    "gn:name":"Vacas",
    "gn:population":0,
    "gn:timezone":"America/Monterrey",
    "iso:country":"MX",
    "name:eus_x_preferred":[
        "Behiak"
    ],
    "name:fra_x_preferred":[
        "Vacas"
    ],
    "name:glg_x_preferred":[
        "Vacas"
    ],
    "name:rus_x_preferred":[
        "\u041a\u043e\u0440\u043e\u0432\u044b"
    ],
    "name:spa_x_preferred":[
        "Vacas"
    ],
    "name:ukr_x_preferred":[
        "\u041a\u043e\u0440\u043e\u0432\u0438"
    ],
    "name:und_x_variant":[
        "Varas",
        "Vacas",
        "Las Vacas"
    ],
    "wof:name":"Vacas",
    "wof:placetype":"locality"
},
  "geometry": {"coordinates":[-100.98718,27.00655],"type":"Point"}
}