{
  "type": "Feature",
  "properties": {
    "gn:admin1_code":"10",
    "gn:admin2_code":"10.0",
    "gn:asciiname":"Cuco",
    "gn:country_code":"MX",
    "gn:dem":1956,
    "gn:feature_class":"P",
    "gn:feature_code":"PPL",
    "gn:name":"Cuco",
    "gn:population":0,
    "gn:timezone":"America/Monterrey",
    "iso:country":"MX",
    "name:spa_x_preferred":[
        "Cuco"
    ],
    "wof:name":"Cuco",
    "wof:placetype":"locality"
},
  "geometry": {"coordinates":[-104.81564,25.76075],"type":"Point"}
}