{
  "type": "Feature",
  "properties": {
    "gn:admin1_code":"6.0",
    "gn:admin2_code":"34.0",
    "gn:asciiname":"Aldama",
    "gn:country_code":"MX",
    "gn:dem":2053,
    "gn:feature_class":"P",
    "gn:feature_code":"PPL",
    "gn:name":"Aldama",
    "gn:population":0,
    "gn:timezone":"America/Chihuahua",
    "iso:country":"MX",
    "name:ara_x_preferred":[
        "\u0627\u0644\u062f\u0627\u0645\u0627"
    ],
    "name:ben_x_preferred":[
        "\u0986\u09b2\u09a6\u09be\u09ae\u09be"
    ],
    "name:ceb_x_preferred":[
        "Aldama"
    ],
    "name:deu_x_preferred":[
        "Aldama"
    ],
    "name:ell_x_preferred":[
        "\u0391\u03bb\u03bd\u03c4\u03ac\u03bc\u03b1"
    ],
    "name:fas_x_preferred":[
        "\u0622\u0644\u062f\u0627\u0645\u0627"
    ],
    "name:fra_x_preferred":[
        "Juan Aldama"
    ],
    "name:fra_x_variant":[
        "Aldama"
    ],
    "name:glg_x_preferred":[
        "Aldama"
    ],
    "name:heb_x_preferred":[
        "\u05d0\u05dc\u05d3\u05de\u05d4"
    ],
    "name:hin_x_preferred":[
        "\u0905\u0932\u0926\u093e\u092e\u093e"
    ],
    "name:hun_x_preferred":[
        "Aldama"
    ],
    "name:ind_x_preferred":[
        "Aldama"
    ],
    "name:ita_x_preferred":[
        "Aldama"
    ],
    "name:jpn_x_preferred":[
        "\u30a2\u30eb\u30c0\u30de"
    ],
    "name:kor_x_preferred":[
        "\uc54c\ub2e4\ub9c8"
    ],
    "name:pol_x_preferred":[
        "Aldama"
    ],
    "name:por_x_preferred":[
        "Aldama"
    ],
    "name:rus_x_preferred":[
        "\u0410\u043b\u044c\u0434\u0430\u043c\u0430"
    ],
    "name:spa_x_preferred":[
        "Aldama"
    ],
    "name:srp_x_preferred":[
        "\u0410\u043b\u0434\u0430\u043c\u0430"
    ],
    "name:swe_x_preferred":[
        "Aldama"
    ],
    "name:tur_x_preferred":[
        "Aldama"
    ],
    "name:ukr_x_preferred":[
        "\u0410\u043b\u044c\u0434\u0430\u043c\u0430"
    ],
    "name:urd_x_preferred":[
        "\u0627\u06cc\u0644\u062f\u0627\u0645\u0627"
    ],
    "name:vie_x_preferred":[
        "Aldama"
    ],
    "name:zho_cn_x_preferred":[
        "\u963f\u5c14\u8fbe\u9a6c"
    ],
    "name:zho_tw_x_preferred":[
        "\u963f\u723e\u9054\u99ac"
    ],
    "wof:name":"Aldama",
    "wof:placetype":"locality"
},
  "geometry": {"coordinates":[-107.71666999999999,29.58333],"type":"Point"}
}