{
  "type": "Feature",
  "properties": {
    "gn:admin1_code":"26",
    "gn:admin2_code":"30.0",
    "gn:asciiname":"Rio Escondido",
    "gn:country_code":"MX",
    "gn:dem":52,
    "gn:feature_class":"P",
    "gn:feature_code":"PPL",
    "gn:name":"R\u00edo Escondido",
    "gn:population":0,
    "gn:timezone":"America/Hermosillo",
    "iso:country":"MX",
    "name:spa_x_preferred":[
        "R\u00edo Escondido"
    ],
    "wof:name":"Rio Escondido",
    "wof:placetype":"locality"
},
  "geometry": {"coordinates":[-111.59028000000001,28.93917],"type":"Point"}
}