{
  "type": "Feature",
  "properties": {
    "gn:admin1_code":"14.0",
    "gn:admin2_code":"85.0",
    "gn:asciiname":"Las Sierrillas",
    "gn:country_code":"MX",
    "gn:dem":1786,
    "gn:feature_class":"P",
    "gn:feature_code":"PPL",
    "gn:name":"Las Sierrillas",
    "gn:population":0,
    "gn:timezone":"America/Mexico_City",
    "iso:country":"MX",
    "name:spa_x_preferred":[
        "Las Sierrillas"
    ],
    "wof:name":"Las Sierrillas",
    "wof:placetype":"locality"
},
  "geometry": {"coordinates":[-103.11609,19.67337],"type":"Point"}
}