{
  "type": "Feature",
  "properties": {
    "gn:admin1_code":"30",
    "gn:admin2_code":"142.0",
    "gn:asciiname":"Bellaco",
    "gn:country_code":"MX",
    "gn:dem":39,
    "gn:feature_class":"P",
    "gn:feature_code":"PPL",
    "gn:name":"Bellaco",
    "gn:population":816,
    "gn:timezone":"America/Mexico_City",
    "iso:country":"MX",
    "wof:name":"Bellaco",
    "wof:placetype":"locality",
    "wof:population":816
},
  "geometry": {"coordinates":[-95.18083,17.78722],"type":"Point"}
}