{
  "type": "Feature",
  "properties": {
    "gn:admin1_code":"2",
    "gn:admin2_code":"2",
    "gn:asciiname":"Familia Castillo (Ejido Monterrey)",
    "gn:country_code":"MX",
    "gn:dem":17,
    "gn:feature_class":"P",
    "gn:feature_code":"PPL",
    "gn:name":"Familia Castillo (Ejido Monterrey)",
    "gn:population":16,
    "gn:timezone":"America/Tijuana",
    "iso:country":"MX",
    "wof:name":"Familia Castillo (Ejido Monterrey)",
    "wof:placetype":"locality",
    "wof:population":16
},
  "geometry": {"coordinates":[-115.08722,32.55056],"type":"Point"}
}