{
  "type": "Feature",
  "properties": {
    "gn:admin1_code":"2",
    "gn:admin2_code":"1.0",
    "gn:asciiname":"Bahia Falsa (La Ostionera)",
    "gn:country_code":"MX",
    "gn:dem":17,
    "gn:feature_class":"P",
    "gn:feature_code":"PPL",
    "gn:name":"Bah\u00eda Falsa (La Ostionera)",
    "gn:population":8,
    "gn:timezone":"America/Tijuana",
    "iso:country":"MX",
    "name:und_x_variant":[
        "Bah\u00eda Falsa (La Ostionera)"
    ],
    "wof:name":"Bahia Falsa (La Ostionera)",
    "wof:placetype":"locality",
    "wof:population":8
},
  "geometry": {"coordinates":[-116.0025,30.45583],"type":"Point"}
}