{
  "type": "Feature",
  "properties": {
    "gn:admin1_code":"24",
    "gn:admin2_code":"3.0",
    "gn:asciiname":"Moctezuma",
    "gn:country_code":"MX",
    "gn:dem":279,
    "gn:feature_class":"P",
    "gn:feature_code":"PPL",
    "gn:name":"Moctezuma",
    "gn:population":0,
    "gn:timezone":"America/Mexico_City",
    "iso:country":"MX",
    "name:spa_x_preferred":[
        "Moctezuma"
    ],
    "wof:name":"Moctezuma",
    "wof:placetype":"locality"
},
  "geometry": {"coordinates":[-99.23560000000001,21.84999],"type":"Point"}
}