{
  "type": "Feature",
  "properties": {
    "gn:admin1_code":"6",
    "gn:admin2_code":"7.0",
    "gn:asciiname":"La Viborilla",
    "gn:country_code":"MX",
    "gn:dem":2113,
    "gn:feature_class":"P",
    "gn:feature_code":"PPL",
    "gn:name":"La Viborilla",
    "gn:population":0,
    "gn:timezone":"America/Chihuahua",
    "iso:country":"MX",
    "name:und_x_variant":[
        "Viborillas",
        "La Viborilla"
    ],
    "wof:name":"La Viborilla",
    "wof:placetype":"locality"
},
  "geometry": {"coordinates":[-106.71680000000001,27.09716],"type":"Point"}
}