{
  "type": "Feature",
  "properties": {
    "gn:admin1_code":"10",
    "gn:admin2_code":"9.0",
    "gn:asciiname":"Paraje Bajio Iglesias",
    "gn:country_code":"MX",
    "gn:dem":2831,
    "gn:feature_class":"P",
    "gn:feature_code":"PPL",
    "gn:name":"Paraje Bajio Iglesias",
    "gn:population":0,
    "gn:timezone":"America/Monterrey",
    "iso:country":"MX",
    "name:spa_x_preferred":[
        "Paraje Bajio Iglesias"
    ],
    "wof:name":"Paraje Bajio Iglesias",
    "wof:placetype":"locality"
},
  "geometry": {"coordinates":[-106.29098999999999,26.11081],"type":"Point"}
}