{
  "type": "Feature",
  "properties": {
    "gn:admin1_code":"27",
    "gn:admin2_code":"3.0",
    "gn:asciiname":"Potrerillo",
    "gn:country_code":"MX",
    "gn:dem":8,
    "gn:feature_class":"P",
    "gn:feature_code":"PPL",
    "gn:name":"Potrerillo",
    "gn:population":0,
    "gn:timezone":"America/Mexico_City",
    "iso:country":"MX",
    "name:spa_x_preferred":[
        "Potrerillo"
    ],
    "wof:name":"Potrerillo",
    "wof:placetype":"locality"
},
  "geometry": {"coordinates":[-92.83677,18.34965],"type":"Point"}
}