{
  "type": "Feature",
  "properties": {
    "gn:admin1_code":"14.0",
    "gn:admin2_code":"16.0",
    "gn:asciiname":"El Guamuchil",
    "gn:country_code":"MX",
    "gn:dem":1561,
    "gn:feature_class":"P",
    "gn:feature_code":"PPL",
    "gn:name":"El Guam\u00fachil",
    "gn:population":0,
    "gn:timezone":"America/Mexico_City",
    "iso:country":"MX",
    "name:spa_x_preferred":[
        "El Guam\u00fachil"
    ],
    "name:spa_x_variant":[
        "El Guamochil"
    ],
    "wof:name":"El Guamuchil",
    "wof:placetype":"locality"
},
  "geometry": {"coordinates":[-102.33109,20.4184],"type":"Point"}
}