{
  "type": "Feature",
  "properties": {
    "gn:admin1_code":"17",
    "gn:asciiname":"Tlacaluca",
    "gn:country_code":"MX",
    "gn:dem":2395,
    "gn:feature_class":"P",
    "gn:feature_code":"PPL",
    "gn:name":"Tlacaluca",
    "gn:population":0,
    "gn:timezone":"America/Mexico_City",
    "iso:country":"MX",
    "name:spa_x_preferred":[
        "Tlacaluca"
    ],
    "wof:name":"Tlacaluca",
    "wof:placetype":"locality"
},
  "geometry": {"coordinates":[-98.80468999999999,19.57039],"type":"Point"}
}