{
  "type": "Feature",
  "properties": {
    "gn:admin1_code":"7",
    "gn:admin2_code":"38.0",
    "gn:asciiname":"Santa Cecilia",
    "gn:country_code":"MX",
    "gn:dem":595,
    "gn:feature_class":"P",
    "gn:feature_code":"PPL",
    "gn:name":"Santa Cecilia",
    "gn:population":0,
    "gn:timezone":"America/Monterrey",
    "iso:country":"MX",
    "name:spa_x_preferred":[
        "Santa Cecilia"
    ],
    "wof:name":"Santa Cecilia",
    "wof:placetype":"locality"
},
  "geometry": {"coordinates":[-101.27352,28.39567000000001],"type":"Point"}
}