{
  "type": "Feature",
  "properties": {
    "gn:admin1_code":"10",
    "gn:admin2_code":"36.0",
    "gn:asciiname":"San Miguel del Real",
    "gn:country_code":"MX",
    "gn:dem":1092,
    "gn:feature_class":"P",
    "gn:feature_code":"PPL",
    "gn:name":"San Miguel del Real",
    "gn:population":180,
    "gn:timezone":"America/Monterrey",
    "iso:country":"MX",
    "wof:name":"San Miguel del Real",
    "wof:placetype":"locality",
    "wof:population":180
},
  "geometry": {"coordinates":[-103.40333,26.02639],"type":"Point"}
}