{
  "type": "Feature",
  "properties": {
    "gn:admin1_code":"10",
    "gn:admin2_code":"21.0",
    "gn:asciiname":"Los Peces",
    "gn:country_code":"MX",
    "gn:dem":1812,
    "gn:feature_class":"P",
    "gn:feature_code":"PPL",
    "gn:name":"Los Peces",
    "gn:population":0,
    "gn:timezone":"America/Monterrey",
    "iso:country":"MX",
    "name:spa_x_preferred":[
        "Los Peces"
    ],
    "name:spa_x_variant":[
        "El Mezquite"
    ],
    "wof:name":"Los Peces",
    "wof:placetype":"locality"
},
  "geometry": {"coordinates":[-103.97535999999999,24.70853],"type":"Point"}
}