{
  "type": "Feature",
  "properties": {
    "gn:admin1_code":"24",
    "gn:admin2_code":"28.0",
    "gn:asciiname":"El Manzo",
    "gn:country_code":"MX",
    "gn:dem":1739,
    "gn:feature_class":"P",
    "gn:feature_code":"PPL",
    "gn:name":"El Manzo",
    "gn:population":77,
    "gn:timezone":"America/Mexico_City",
    "iso:country":"MX",
    "name:und_x_variant":[
        "Manso",
        "Manzo"
    ],
    "wof:name":"El Manzo",
    "wof:placetype":"locality",
    "wof:population":77
},
  "geometry": {"coordinates":[-100.91194,22.51382000000001],"type":"Point"}
}