{
  "type": "Feature",
  "properties": {
    "gn:admin1_code":"25.0",
    "gn:admin2_code":"13.0",
    "gn:asciiname":"Jurisdiccion de Arriba",
    "gn:country_code":"MX",
    "gn:dem":148,
    "gn:feature_class":"P",
    "gn:feature_code":"PPL",
    "gn:name":"Jurisdicci\u00f3n de Arriba",
    "gn:population":0,
    "gn:timezone":"America/Mazatlan",
    "iso:country":"MX",
    "name:und_x_variant":[
        "Jurisdicci\u00f3n de Arriba",
        "Jursan",
        "Jurisdicci\u00f3n"
    ],
    "wof:name":"Jurisdiccion de Arriba",
    "wof:placetype":"locality"
},
  "geometry": {"coordinates":[-107.71666999999999,25.26667],"type":"Point"}
}