{
  "type": "Feature",
  "properties": {
    "gn:admin1_code":"29",
    "gn:admin2_code":"3.0",
    "gn:asciiname":"Colonia Agricola San Luis",
    "gn:country_code":"MX",
    "gn:dem":2493,
    "gn:feature_class":"P",
    "gn:feature_code":"PPL",
    "gn:name":"Colonia Agr\u00edcola San Luis",
    "gn:population":142,
    "gn:timezone":"America/Mexico_City",
    "iso:country":"MX",
    "wof:name":"Colonia Agricola San Luis",
    "wof:placetype":"locality",
    "wof:population":142
},
  "geometry": {"coordinates":[-98.17139,19.56861],"type":"Point"}
}