{
  "type": "Feature",
  "properties": {
    "gn:admin1_code":"10",
    "gn:admin2_code":"34.0",
    "gn:asciiname":"La Punta",
    "gn:country_code":"MX",
    "gn:dem":516,
    "gn:feature_class":"P",
    "gn:feature_code":"PPL",
    "gn:name":"La Punta",
    "gn:population":0,
    "gn:timezone":"America/Monterrey",
    "iso:country":"MX",
    "name:cat_x_preferred":[
        "La Punta"
    ],
    "name:ceb_x_preferred":[
        "La Punta"
    ],
    "name:deu_x_preferred":[
        "La Punta"
    ],
    "name:jpn_x_preferred":[
        "\u30e9\u30fb\u30d7\u30f3\u30bf"
    ],
    "name:nld_x_preferred":[
        "La Punta"
    ],
    "name:srp_x_preferred":[
        "La Punta"
    ],
    "name:swe_x_preferred":[
        "La Punta"
    ],
    "wof:name":"La Punta",
    "wof:placetype":"locality"
},
  "geometry": {"coordinates":[-107.08333,25.23333],"type":"Point"}
}