{
  "type": "Feature",
  "properties": {
    "gn:admin1_code":"10.0",
    "gn:asciiname":"Los Horcones",
    "gn:country_code":"MX",
    "gn:dem":1338,
    "gn:feature_class":"P",
    "gn:feature_code":"PPL",
    "gn:name":"Los Horcones",
    "gn:population":0,
    "gn:timezone":"America/Monterrey",
    "iso:country":"MX",
    "name:fra_x_preferred":[
        "Los Horcones"
    ],
    "name:por_x_preferred":[
        "Los horcones"
    ],
    "name:spa_x_preferred":[
        "Los Horcones"
    ],
    "wof:name":"Los Horcones",
    "wof:placetype":"locality"
},
  "geometry": {"coordinates":[-106.33393,24.51725],"type":"Point"}
}