{
  "type": "Feature",
  "properties": {
    "gn:admin1_code":"22",
    "gn:admin2_code":"7",
    "gn:asciiname":"Embuja",
    "gn:country_code":"MX",
    "gn:dem":2055,
    "gn:feature_class":"P",
    "gn:feature_code":"PPL",
    "gn:name":"Embuja",
    "gn:population":18,
    "gn:timezone":"America/Mexico_City",
    "iso:country":"MX",
    "wof:name":"Embuja",
    "wof:placetype":"locality",
    "wof:population":18
},
  "geometry": {"coordinates":[-99.83750000000001,20.64806],"type":"Point"}
}