{
  "type": "Feature",
  "properties": {
    "gn:admin1_code":"30",
    "gn:admin2_code":"169.0",
    "gn:asciiname":"San Luis",
    "gn:country_code":"MX",
    "gn:dem":42,
    "gn:feature_class":"P",
    "gn:feature_code":"PPL",
    "gn:name":"San Luis",
    "gn:population":331,
    "gn:timezone":"America/Mexico_City",
    "iso:country":"MX",
    "name:spa_x_preferred":[
        "San Luis"
    ],
    "wof:name":"San Luis",
    "wof:placetype":"locality",
    "wof:population":331
},
  "geometry": {"coordinates":[-95.71406,18.01021],"type":"Point"}
}