{
  "type": "Feature",
  "properties": {
    "gn:admin1_code":"20",
    "gn:admin2_code":"365.0",
    "gn:asciiname":"Latuvi",
    "gn:country_code":"MX",
    "gn:dem":2434,
    "gn:feature_class":"P",
    "gn:feature_code":"PPL",
    "gn:name":"Latuvi",
    "gn:population":0,
    "gn:timezone":"America/Mexico_City",
    "iso:country":"MX",
    "name:spa_x_preferred":[
        "Latuvi"
    ],
    "wof:name":"Latuvi",
    "wof:placetype":"locality"
},
  "geometry": {"coordinates":[-96.51434,17.18851],"type":"Point"}
}