{
  "type": "Feature",
  "properties": {
    "gn:admin1_code":"14",
    "gn:admin2_code":"43.0",
    "gn:asciiname":"Boca de Iguanas",
    "gn:country_code":"MX",
    "gn:dem":5,
    "gn:feature_class":"P",
    "gn:feature_code":"PPL",
    "gn:name":"Boca de Iguanas",
    "gn:population":8,
    "gn:timezone":"America/Mexico_City",
    "iso:country":"MX",
    "wof:name":"Boca de Iguanas",
    "wof:placetype":"locality",
    "wof:population":8
},
  "geometry": {"coordinates":[-104.81917,19.30667],"type":"Point"}
}