{
  "type": "Feature",
  "properties": {
    "gn:admin1_code":"25",
    "gn:admin2_code":"3.0",
    "gn:asciiname":"Santa Rita de Abajo",
    "gn:country_code":"MX",
    "gn:dem":850,
    "gn:feature_class":"P",
    "gn:feature_code":"PPL",
    "gn:name":"Santa Rita de Abajo",
    "gn:population":0,
    "gn:timezone":"America/Mazatlan",
    "iso:country":"MX",
    "name:spa_x_preferred":[
        "Santa Rita"
    ],
    "name:spa_x_variant":[
        "Santa Rita de Abajo"
    ],
    "wof:name":"Santa Rita de Abajo",
    "wof:placetype":"locality"
},
  "geometry": {"coordinates":[-107.50223,25.92879],"type":"Point"}
}