{
  "type": "Feature",
  "properties": {
    "gn:admin1_code":"30",
    "gn:admin2_code":"91.0",
    "gn:asciiname":"Enrique Rodriguez Cano",
    "gn:country_code":"MX",
    "gn:dem":38,
    "gn:feature_class":"P",
    "gn:feature_code":"PPL",
    "gn:name":"Enrique Rodr\u00edguez Cano",
    "gn:population":138,
    "gn:timezone":"America/Mexico_City",
    "iso:country":"MX",
    "name:und_x_variant":[
        "Enrique Rodr\u00edguez Cano"
    ],
    "wof:name":"Enrique Rodriguez Cano",
    "wof:placetype":"locality",
    "wof:population":138
},
  "geometry": {"coordinates":[-94.71278,17.36722],"type":"Point"}
}