{
  "type": "Feature",
  "properties": {
    "gn:admin1_code":"8.0",
    "gn:admin2_code":"4.0",
    "gn:asciiname":"La Parota",
    "gn:country_code":"MX",
    "gn:dem":732,
    "gn:feature_class":"P",
    "gn:feature_code":"PPL",
    "gn:name":"La Parota",
    "gn:population":0,
    "gn:timezone":"America/Mexico_City",
    "iso:country":"MX",
    "name:spa_x_preferred":[
        "La Parota"
    ],
    "wof:name":"La Parota",
    "wof:placetype":"locality"
},
  "geometry": {"coordinates":[-104.02085,19.24228],"type":"Point"}
}