{
  "type": "Feature",
  "properties": {
    "gn:admin1_code":"22",
    "gn:admin2_code":"13",
    "gn:asciiname":"Las Camelinas",
    "gn:country_code":"MX",
    "gn:dem":1513,
    "gn:feature_class":"P",
    "gn:feature_code":"PPL",
    "gn:name":"Las Camelinas",
    "gn:population":32,
    "gn:timezone":"America/Mexico_City",
    "iso:country":"MX",
    "wof:name":"Las Camelinas",
    "wof:placetype":"locality",
    "wof:population":32
},
  "geometry": {"coordinates":[-99.98,21.10611],"type":"Point"}
}