{
  "type": "Feature",
  "properties": {
    "gn:admin1_code":"27",
    "gn:admin2_code":"9.0",
    "gn:asciiname":"El Cerro",
    "gn:country_code":"MX",
    "gn:dem":20,
    "gn:feature_class":"P",
    "gn:feature_code":"PPL",
    "gn:name":"El Cerro",
    "gn:population":0,
    "gn:timezone":"America/Mexico_City",
    "iso:country":"MX",
    "name:spa_x_preferred":[
        "El Cerro"
    ],
    "wof:name":"El Cerro",
    "wof:placetype":"locality"
},
  "geometry": {"coordinates":[-92.69905,17.75718999999999],"type":"Point"}
}