{
  "type": "Feature",
  "properties": {
    "gn:admin1_code":"29",
    "gn:admin2_code":"31",
    "gn:asciiname":"El Corazon",
    "gn:country_code":"MX",
    "gn:dem":2556,
    "gn:feature_class":"P",
    "gn:feature_code":"PPL",
    "gn:name":"El Coraz\u00f3n",
    "gn:population":14,
    "gn:timezone":"America/Mexico_City",
    "iso:country":"MX",
    "name:und_x_variant":[
        "El Coraz\u00f3n"
    ],
    "wof:name":"El Corazon",
    "wof:placetype":"locality",
    "wof:population":14
},
  "geometry": {"coordinates":[-98.14086,19.51022],"type":"Point"}
}