{
  "type": "Feature",
  "properties": {
    "gn:admin1_code":"5.0",
    "gn:asciiname":"Zaquiltum",
    "gn:country_code":"MX",
    "gn:dem":852,
    "gn:feature_class":"P",
    "gn:feature_code":"PPL",
    "gn:name":"Zaquiltum",
    "gn:population":0,
    "gn:timezone":"America/Mexico_City",
    "iso:country":"MX",
    "name:spa_x_preferred":[
        "Zaquiltum"
    ],
    "wof:name":"Zaquiltum",
    "wof:placetype":"locality"
},
  "geometry": {"coordinates":[-92.07264000000001,16.89757],"type":"Point"}
}