{
  "type": "Feature",
  "properties": {
    "gn:admin1_code":"26.0",
    "gn:admin2_code":"56.0",
    "gn:asciiname":"Las Bateas",
    "gn:country_code":"MX",
    "gn:dem":469,
    "gn:feature_class":"P",
    "gn:feature_code":"PPL",
    "gn:name":"Las Bateas",
    "gn:population":0,
    "gn:timezone":"America/Hermosillo",
    "iso:country":"MX",
    "name:und_x_variant":[
        "Rancho de las Bateas",
        "Las Bateas"
    ],
    "wof:name":"Las Bateas",
    "wof:placetype":"locality"
},
  "geometry": {"coordinates":[-110.98963999999999,29.3269],"type":"Point"}
}