{
  "type": "Feature",
  "properties": {
    "gn:admin1_code":"12.0",
    "gn:admin2_code":"53.0",
    "gn:asciiname":"Mata de Icaco",
    "gn:country_code":"MX",
    "gn:dem":13,
    "gn:feature_class":"P",
    "gn:feature_code":"PPL",
    "gn:name":"Mata de Icaco",
    "gn:population":0,
    "gn:timezone":"America/Mexico_City",
    "iso:country":"MX",
    "name:spa_x_preferred":[
        "Mata de Icaco"
    ],
    "wof:name":"Mata de Icaco",
    "wof:placetype":"locality"
},
  "geometry": {"coordinates":[-99.43657,16.69331],"type":"Point"}
}