{
  "type": "Feature",
  "properties": {
    "gn:admin1_code":"24",
    "gn:admin2_code":"40.0",
    "gn:asciiname":"Ricardo Flores Magon",
    "gn:country_code":"MX",
    "gn:dem":58,
    "gn:feature_class":"P",
    "gn:feature_code":"PPL",
    "gn:name":"Ricardo Flores Mag\u00f3n",
    "gn:population":5,
    "gn:timezone":"America/Mexico_City",
    "iso:country":"MX",
    "name:und_x_variant":[
        "Ricardo Flores Mag\u00f3n"
    ],
    "wof:name":"Ricardo Flores Magon",
    "wof:placetype":"locality",
    "wof:population":5
},
  "geometry": {"coordinates":[-98.71472,22.135],"type":"Point"}
}