{
  "type": "Feature",
  "properties": {
    "gn:admin1_code":"13",
    "gn:admin2_code":"57.0",
    "gn:asciiname":"La Pena",
    "gn:country_code":"MX",
    "gn:dem":2608,
    "gn:feature_class":"P",
    "gn:feature_code":"PPL",
    "gn:name":"La Pe\u00f1a",
    "gn:population":127,
    "gn:timezone":"America/Mexico_City",
    "iso:country":"MX",
    "name:und_x_variant":[
        "La Pe\u00f1a"
    ],
    "wof:name":"La Pena",
    "wof:placetype":"locality",
    "wof:population":127
},
  "geometry": {"coordinates":[-98.54085000000001,20.03913],"type":"Point"}
}