{
  "type": "Feature",
  "properties": {
    "gn:admin1_code":"21.0",
    "gn:admin2_code":"155.0",
    "gn:asciiname":"El Platanar",
    "gn:country_code":"MX",
    "gn:dem":1012,
    "gn:feature_class":"P",
    "gn:feature_code":"PPL",
    "gn:name":"El Platanar",
    "gn:population":0,
    "gn:timezone":"America/Mexico_City",
    "iso:country":"MX",
    "name:spa_x_preferred":[
        "El Platanar"
    ],
    "wof:name":"El Platanar",
    "wof:placetype":"locality"
},
  "geometry": {"coordinates":[-98.327,18.06917],"type":"Point"}
}