{
  "type": "Feature",
  "properties": {
    "gn:admin1_code":"3",
    "gn:admin2_code":"3",
    "gn:asciiname":"Las Dos Palmas",
    "gn:country_code":"MX",
    "gn:dem":206,
    "gn:feature_class":"P",
    "gn:feature_code":"PPL",
    "gn:name":"Las Dos Palmas",
    "gn:population":38,
    "gn:timezone":"America/Mazatlan",
    "iso:country":"MX",
    "wof:name":"Las Dos Palmas",
    "wof:placetype":"locality",
    "wof:population":38
},
  "geometry": {"coordinates":[-110.24639000000001,23.62986],"type":"Point"}
}