{
  "type": "Feature",
  "properties": {
    "gn:admin1_code":"5",
    "gn:admin2_code":"56.0",
    "gn:asciiname":"Cuchumton",
    "gn:country_code":"MX",
    "gn:dem":2176,
    "gn:feature_class":"P",
    "gn:feature_code":"PPL",
    "gn:name":"Cuchumt\u00f3n",
    "gn:population":713,
    "gn:timezone":"America/Mexico_City",
    "iso:country":"MX",
    "name:und_x_variant":[
        "Cuchumt\u00f3n"
    ],
    "wof:name":"Cuchumton",
    "wof:placetype":"locality",
    "wof:population":713
},
  "geometry": {"coordinates":[-92.58465,16.8721],"type":"Point"}
}