{
  "type": "Feature",
  "properties": {
    "gn:admin1_code":"10.0",
    "gn:admin2_code":"16.0",
    "gn:asciiname":"Amado Nervo",
    "gn:country_code":"MX",
    "gn:dem":1816,
    "gn:feature_class":"P",
    "gn:feature_code":"PPL",
    "gn:name":"Amado Nervo",
    "gn:population":0,
    "gn:timezone":"America/Monterrey",
    "iso:country":"MX",
    "name:und_x_variant":[
        "Juana Guerra",
        "Amado Nervo"
    ],
    "wof:name":"Amado Nervo",
    "wof:placetype":"locality"
},
  "geometry": {"coordinates":[-104.18583,23.84452000000001],"type":"Point"}
}