{
  "type": "Feature",
  "properties": {
    "gn:admin1_code":"10.0",
    "gn:admin2_code":"16.0",
    "gn:asciiname":"Amado Nervo",
    "gn:country_code":"MX",
    "gn:dem":1816,
    "gn:feature_class":"P",
    "gn:feature_code":"PPL",
    "gn:name":"Amado Nervo",
    "gn:population":0,
    "gn:timezone":"America/Monterrey",
    "iso:country":"MX",
    "name:afr_x_preferred":[
        "Amado Nervo"
    ],
    "name:ara_x_preferred":[
        "\u0623\u0645\u0627\u062f\u0648 \u0646\u064a\u0631\u0641\u0648"
    ],
    "name:cat_x_preferred":[
        "Amado Nervo"
    ],
    "name:deu_x_preferred":[
        "Amado Nervo"
    ],
    "name:epo_x_preferred":[
        "Amado Nervo"
    ],
    "name:eus_x_preferred":[
        "Amado Nervo"
    ],
    "name:fas_x_preferred":[
        "\u0622\u0645\u0627\u062f\u0648\u0648 \u0646\u0631\u0648\u0648"
    ],
    "name:fra_x_preferred":[
        "Amado Nervo"
    ],
    "name:ina_x_preferred":[
        "Amado Nervo"
    ],
    "name:ita_x_preferred":[
        "Amado Nervo"
    ],
    "name:nah_x_preferred":[
        "Amado Nervo"
    ],
    "name:nld_x_preferred":[
        "Amado Nervo"
    ],
    "name:pol_x_preferred":[
        "Amado Nervo"
    ],
    "name:por_x_preferred":[
        "Amado Nervo"
    ],
    "name:que_x_preferred":[
        "Amado Nervo"
    ],
    "name:ron_x_preferred":[
        "Amado Nervo"
    ],
    "name:rus_x_preferred":[
        "\u0410\u043c\u0430\u0434\u043e \u041d\u0435\u0440\u0432\u043e"
    ],
    "name:spa_x_preferred":[
        "Amado Nervo"
    ],
    "name:ukr_x_preferred":[
        "\u0410\u043c\u0430\u0434\u043e \u041d\u0435\u0440\u0432\u043e"
    ],
    "name:und_x_variant":[
        "Juana Guerra",
        "Amado Nervo"
    ],
    "wof:name":"Amado Nervo",
    "wof:placetype":"locality"
},
  "geometry": {"coordinates":[-104.18583,23.84452000000001],"type":"Point"}
}