{
  "type": "Feature",
  "properties": {
    "gn:admin1_code":"5.0",
    "gn:admin2_code":"65.0",
    "gn:asciiname":"La Giralda",
    "gn:country_code":"MX",
    "gn:dem":346,
    "gn:feature_class":"P",
    "gn:feature_code":"PPL",
    "gn:name":"La Giralda",
    "gn:population":0,
    "gn:timezone":"America/Mexico_City",
    "iso:country":"MX",
    "name:spa_x_preferred":[
        "La Giralda"
    ],
    "wof:name":"La Giralda",
    "wof:placetype":"locality"
},
  "geometry": {"coordinates":[-91.55636,17.13097999999999],"type":"Point"}
}