{
  "type": "Feature",
  "properties": {
    "gn:admin1_code":"24",
    "gn:admin2_code":"6.0",
    "gn:asciiname":"Loma Blanca",
    "gn:country_code":"MX",
    "gn:dem":1803,
    "gn:feature_class":"P",
    "gn:feature_code":"PPL",
    "gn:name":"Loma Blanca",
    "gn:population":5,
    "gn:timezone":"America/Mexico_City",
    "iso:country":"MX",
    "name:hye_x_preferred":[
        "\u053c\u0578\u0574\u0561 \u0532\u056c\u0561\u0576\u056f\u0561"
    ],
    "name:rus_x_preferred":[
        "\u041b\u043e\u043c\u0430-\u0411\u043b\u0430\u043d\u043a\u0430"
    ],
    "name:spa_x_preferred":[
        "Loma Blanca"
    ],
    "wof:name":"Loma Blanca",
    "wof:placetype":"locality",
    "wof:population":5
},
  "geometry": {"coordinates":[-101.06194000000001,23.62639],"type":"Point"}
}