{
  "type": "Feature",
  "properties": {
    "gn:admin1_code":"7.0",
    "gn:admin2_code":"38.0",
    "gn:asciiname":"El Mimbre",
    "gn:country_code":"MX",
    "gn:dem":434,
    "gn:feature_class":"P",
    "gn:feature_code":"PPL",
    "gn:name":"El Mimbre",
    "gn:population":0,
    "gn:timezone":"America/Monterrey",
    "iso:country":"MX",
    "name:und_x_variant":[
        "Rancho El Mimbre",
        "El Mimbre"
    ],
    "wof:name":"El Mimbre",
    "wof:placetype":"locality"
},
  "geometry": {"coordinates":[-101.06686000000001,28.43206],"type":"Point"}
}