{
  "type": "Feature",
  "properties": {
    "gn:admin1_code":"16.0",
    "gn:admin2_code":"96.0",
    "gn:asciiname":"Barranca de la Gloria",
    "gn:country_code":"MX",
    "gn:dem":722,
    "gn:feature_class":"P",
    "gn:feature_code":"PPL",
    "gn:name":"Barranca de la Gloria",
    "gn:population":0,
    "gn:timezone":"America/Mexico_City",
    "iso:country":"MX",
    "name:spa_x_preferred":[
        "Barranca de la Gloria"
    ],
    "wof:name":"Barranca de la Gloria",
    "wof:placetype":"locality"
},
  "geometry": {"coordinates":[-102.75363,18.40079],"type":"Point"}
}