{
  "type": "Feature",
  "properties": {
    "gn:admin1_code":"21",
    "gn:admin2_code":"185",
    "gn:asciiname":"Los Monjes",
    "gn:country_code":"MX",
    "gn:dem":1449,
    "gn:feature_class":"P",
    "gn:feature_code":"PPL",
    "gn:name":"Los Monjes",
    "gn:population":19,
    "gn:timezone":"America/Mexico_City",
    "iso:country":"MX",
    "wof:name":"Los Monjes",
    "wof:placetype":"locality",
    "wof:population":19
},
  "geometry": {"coordinates":[-98.49997999999999,18.70017],"type":"Point"}
}