{
  "type": "Feature",
  "properties": {
    "gn:admin1_code":"13",
    "gn:asciiname":"Acoculco",
    "gn:country_code":"MX",
    "gn:dem":2764,
    "gn:feature_class":"P",
    "gn:feature_code":"PPL",
    "gn:name":"Acoculco",
    "gn:population":0,
    "gn:timezone":"America/Mexico_City",
    "iso:country":"MX",
    "name:spa_x_preferred":[
        "Alamedita"
    ],
    "name:und_x_variant":[
        "Aculco",
        "Acoculco"
    ],
    "wof:name":"Acoculco",
    "wof:placetype":"locality"
},
  "geometry": {"coordinates":[-98.20985,19.93497],"type":"Point"}
}