{
  "type": "Feature",
  "properties": {
    "gn:admin1_code":"16",
    "gn:admin2_code":"10",
    "gn:asciiname":"Rincon Viejo (La Huerta)",
    "gn:country_code":"MX",
    "gn:dem":391,
    "gn:feature_class":"P",
    "gn:feature_code":"PPL",
    "gn:name":"Rinc\u00f3n Viejo (La Huerta)",
    "gn:population":19,
    "gn:timezone":"America/Mexico_City",
    "iso:country":"MX",
    "name:und_x_variant":[
        "Rinc\u00f3n Viejo (La Huerta)"
    ],
    "wof:name":"Rincon Viejo (La Huerta)",
    "wof:placetype":"locality",
    "wof:population":19
},
  "geometry": {"coordinates":[-102.02611,18.23944],"type":"Point"}
}