{
  "type": "Feature",
  "properties": {
    "gn:admin1_code":"30",
    "gn:admin2_code":"184.0",
    "gn:asciiname":"Zacatla",
    "gn:country_code":"MX",
    "gn:dem":2235,
    "gn:feature_class":"P",
    "gn:feature_code":"PPL",
    "gn:name":"Zacatla",
    "gn:population":190,
    "gn:timezone":"America/Mexico_City",
    "iso:country":"MX",
    "wof:name":"Zacatla",
    "wof:placetype":"locality",
    "wof:population":190
},
  "geometry": {"coordinates":[-97.11944,18.60667],"type":"Point"}
}