{
  "type": "Feature",
  "properties": {
    "gn:admin1_code":"7",
    "gn:admin2_code":"14.0",
    "gn:asciiname":"Ruben Perez",
    "gn:country_code":"MX",
    "gn:dem":345,
    "gn:feature_class":"P",
    "gn:feature_code":"PPL",
    "gn:name":"Rub\u00e9n P\u00e9rez",
    "gn:population":6,
    "gn:timezone":"America/Monterrey",
    "iso:country":"MX",
    "name:und_x_variant":[
        "Rub\u00e9n P\u00e9rez"
    ],
    "wof:name":"Ruben Perez",
    "wof:placetype":"locality",
    "wof:population":6
},
  "geometry": {"coordinates":[-100.96648999999999,29.16355],"type":"Point"}
}