{
  "type": "Feature",
  "properties": {
    "gn:admin1_code":"25.0",
    "gn:admin2_code":"7.0",
    "gn:asciiname":"Campo Buenavista",
    "gn:country_code":"MX",
    "gn:dem":290,
    "gn:feature_class":"P",
    "gn:feature_code":"PPL",
    "gn:name":"Campo Buenavista",
    "gn:population":0,
    "gn:timezone":"America/Mazatlan",
    "iso:country":"MX",
    "name:spa_x_preferred":[
        "Campo Buenavista"
    ],
    "wof:name":"Campo Buenavista",
    "wof:placetype":"locality"
},
  "geometry": {"coordinates":[-108.26013,26.88312],"type":"Point"}
}