{
  "type": "Feature",
  "properties": {
    "gn:admin1_code":"16",
    "gn:admin2_code":"9",
    "gn:asciiname":"El Mirador",
    "gn:country_code":"MX",
    "gn:dem":1743,
    "gn:feature_class":"P",
    "gn:feature_code":"PPL",
    "gn:name":"El Mirador",
    "gn:population":14,
    "gn:timezone":"America/Mexico_City",
    "iso:country":"MX",
    "wof:name":"El Mirador",
    "wof:placetype":"locality",
    "wof:population":14
},
  "geometry": {"coordinates":[-101.735,19.20889],"type":"Point"}
}