{
  "type": "Feature",
  "properties": {
    "gn:admin1_code":"30",
    "gn:admin2_code":"124.0",
    "gn:asciiname":"Insurgente Socialista",
    "gn:country_code":"MX",
    "gn:dem":116,
    "gn:feature_class":"P",
    "gn:feature_code":"PPL",
    "gn:name":"Insurgente Socialista",
    "gn:population":0,
    "gn:timezone":"America/Mexico_City",
    "iso:country":"MX",
    "name:spa_x_preferred":[
        "Insurgente Socialista"
    ],
    "name:und_x_variant":[
        "Insurgentes Socialistas"
    ],
    "wof:name":"Insurgente Socialista",
    "wof:placetype":"locality"
},
  "geometry": {"coordinates":[-97.26254,20.18776],"type":"Point"}
}