{
  "type": "Feature",
  "properties": {
    "gn:admin1_code":"32",
    "gn:admin2_code":"48.0",
    "gn:asciiname":"Salinas",
    "gn:country_code":"MX",
    "gn:dem":2089,
    "gn:feature_class":"P",
    "gn:feature_code":"PPL",
    "gn:name":"Salinas",
    "gn:population":0,
    "gn:timezone":"America/Mexico_City",
    "iso:country":"MX",
    "name:spa_x_preferred":[
        "Salinas"
    ],
    "wof:name":"Salinas",
    "wof:placetype":"locality"
},
  "geometry": {"coordinates":[-103.36382,21.8001],"type":"Point"}
}