{
  "type": "Feature",
  "properties": {
    "gn:admin1_code":"30",
    "gn:admin2_code":"3.0",
    "gn:asciiname":"Sabaneta",
    "gn:country_code":"MX",
    "gn:dem":81,
    "gn:feature_class":"P",
    "gn:feature_code":"PPL",
    "gn:name":"Sabaneta",
    "gn:population":0,
    "gn:timezone":"America/Mexico_City",
    "iso:country":"MX",
    "wof:name":"Sabaneta",
    "wof:placetype":"locality"
},
  "geometry": {"coordinates":[-94.99733999999999,17.94143],"type":"Point"}
}