{
  "type": "Feature",
  "properties": {
    "gn:admin1_code":"14",
    "gn:admin2_code":"94.0",
    "gn:asciiname":"La Culebra",
    "gn:country_code":"MX",
    "gn:dem":1080,
    "gn:feature_class":"P",
    "gn:feature_code":"PPL",
    "gn:name":"La Culebra",
    "gn:population":69,
    "gn:timezone":"America/Mexico_City",
    "iso:country":"MX",
    "wof:name":"La Culebra",
    "wof:placetype":"locality",
    "wof:population":69
},
  "geometry": {"coordinates":[-103.82832999999999,20.91028],"type":"Point"}
}