{
  "type": "Feature",
  "properties": {
    "gn:admin1_code":"15",
    "gn:admin2_code":"123.0",
    "gn:asciiname":"Puerto del Higo",
    "gn:country_code":"MX",
    "gn:dem":1211,
    "gn:feature_class":"P",
    "gn:feature_code":"PPL",
    "gn:name":"Puerto del Higo",
    "gn:population":128,
    "gn:timezone":"America/Mexico_City",
    "iso:country":"MX",
    "wof:name":"Puerto del Higo",
    "wof:placetype":"locality",
    "wof:population":128
},
  "geometry": {"coordinates":[-100.30037,19.01033],"type":"Point"}
}