{
  "type": "Feature",
  "properties": {
    "gn:admin1_code":"11.0",
    "gn:admin2_code":"9.0",
    "gn:asciiname":"Delgado de Abajo",
    "gn:country_code":"MX",
    "gn:dem":1902,
    "gn:feature_class":"P",
    "gn:feature_code":"PPL",
    "gn:name":"Delgado de Abajo",
    "gn:population":0,
    "gn:timezone":"America/Mexico_City",
    "iso:country":"MX",
    "name:spa_x_preferred":[
        "Delgado de Abajo"
    ],
    "wof:name":"Delgado de Abajo",
    "wof:placetype":"locality"
},
  "geometry": {"coordinates":[-100.89337999999999,20.71749],"type":"Point"}
}