{
  "type": "Feature",
  "properties": {
    "gn:admin1_code":"31",
    "gn:admin2_code":"48.0",
    "gn:asciiname":"San Sebastian",
    "gn:country_code":"MX",
    "gn:dem":30,
    "gn:feature_class":"P",
    "gn:feature_code":"PPL",
    "gn:name":"San Sebasti\u00e1n",
    "gn:population":5,
    "gn:timezone":"America/Merida",
    "iso:country":"MX",
    "name:und_x_variant":[
        "San Sebasti\u00e1n"
    ],
    "wof:name":"San Sebastian",
    "wof:placetype":"locality",
    "wof:population":5
},
  "geometry": {"coordinates":[-89.99639000000001,20.56861],"type":"Point"}
}