{
  "type": "Feature",
  "properties": {
    "gn:admin1_code":"13",
    "gn:admin2_code":"7.0",
    "gn:asciiname":"San Lorenzo Xicotencatl",
    "gn:country_code":"MX",
    "gn:dem":2558,
    "gn:feature_class":"P",
    "gn:feature_code":"PPL",
    "gn:name":"San Lorenzo Xicot\u00e9ncatl",
    "gn:population":193,
    "gn:timezone":"America/Mexico_City",
    "iso:country":"MX",
    "name:und_x_variant":[
        "San Lorenzo Xicot\u00e9ncatl"
    ],
    "wof:name":"San Lorenzo Xicotencatl",
    "wof:placetype":"locality",
    "wof:population":193
},
  "geometry": {"coordinates":[-98.375,19.69389],"type":"Point"}
}