{
  "type": "Feature",
  "properties": {
    "gn:admin1_code":"26",
    "gn:admin2_code":"51.0",
    "gn:asciiname":"Las Penas",
    "gn:country_code":"MX",
    "gn:dem":506,
    "gn:feature_class":"P",
    "gn:feature_code":"PPL",
    "gn:name":"Las Pe\u00f1as",
    "gn:population":6,
    "gn:timezone":"America/Hermosillo",
    "iso:country":"MX",
    "wof:name":"Las Penas",
    "wof:placetype":"locality",
    "wof:population":6
},
  "geometry": {"coordinates":[-109.05278,27.77444],"type":"Point"}
}