{
  "type": "Feature",
  "properties": {
    "gn:admin1_code":"12",
    "gn:admin2_code":"16.0",
    "gn:asciiname":"Los Limones",
    "gn:country_code":"MX",
    "gn:dem":826,
    "gn:feature_class":"P",
    "gn:feature_code":"PPL",
    "gn:name":"Los Limones",
    "gn:population":0,
    "gn:timezone":"America/Mexico_City",
    "iso:country":"MX",
    "name:spa_x_preferred":[
        "Los Limones"
    ],
    "name:und_x_variant":[
        "El Sauz"
    ],
    "wof:name":"Los Limones",
    "wof:placetype":"locality"
},
  "geometry": {"coordinates":[-101.62602,18.35923],"type":"Point"}
}