{
  "type": "Feature",
  "properties": {
    "gn:admin1_code":"32",
    "gn:admin2_code":"20.0",
    "gn:asciiname":"Tanque de San Juan",
    "gn:country_code":"MX",
    "gn:dem":2035,
    "gn:feature_class":"P",
    "gn:feature_code":"PPL",
    "gn:name":"Tanque de San Juan",
    "gn:population":255,
    "gn:timezone":"America/Mexico_City",
    "iso:country":"MX",
    "wof:name":"Tanque de San Juan",
    "wof:placetype":"locality",
    "wof:population":255
},
  "geometry": {"coordinates":[-102.94083000000001,22.67944],"type":"Point"}
}