{
  "type": "Feature",
  "properties": {
    "gn:admin1_code":"21",
    "gn:admin2_code":"157",
    "gn:asciiname":"Agua Zarca",
    "gn:country_code":"MX",
    "gn:dem":1250,
    "gn:feature_class":"P",
    "gn:feature_code":"PPL",
    "gn:name":"Agua Zarca",
    "gn:population":16,
    "gn:timezone":"America/Mexico_City",
    "iso:country":"MX",
    "wof:name":"Agua Zarca",
    "wof:placetype":"locality",
    "wof:population":16
},
  "geometry": {"coordinates":[-98.31413999999999,18.27603],"type":"Point"}
}