{
  "type": "Feature",
  "properties": {
    "gn:admin1_code":"6.0",
    "gn:admin2_code":"2.0",
    "gn:asciiname":"Carrera",
    "gn:country_code":"MX",
    "gn:dem":1009,
    "gn:feature_class":"P",
    "gn:feature_code":"PPL",
    "gn:name":"Carrera",
    "gn:population":0,
    "gn:timezone":"America/Chihuahua",
    "iso:country":"MX",
    "name:ast_x_preferred":[
        "Carrera"
    ],
    "name:cat_x_preferred":[
        "Carrera"
    ],
    "name:ceb_x_preferred":[
        "Carrera"
    ],
    "name:ces_x_preferred":[
        "Carrera"
    ],
    "name:deu_x_preferred":[
        "Carrera"
    ],
    "name:fra_x_preferred":[
        "Carrera"
    ],
    "name:ita_x_preferred":[
        "Carrera"
    ],
    "name:jpn_x_preferred":[
        "\u30ab\u30ec\u30e9"
    ],
    "name:kor_x_preferred":[
        "\uce74\ub808\ub77c"
    ],
    "name:nld_x_preferred":[
        "Carrera"
    ],
    "name:por_x_preferred":[
        "Carrera"
    ],
    "name:rus_x_preferred":[
        "\u041a\u0430\u0440\u0440\u0435\u0440\u0430"
    ],
    "name:spa_x_preferred":[
        "Carrera"
    ],
    "name:swe_x_preferred":[
        "Carrera"
    ],
    "wof:name":"Carrera",
    "wof:placetype":"locality"
},
  "geometry": {"coordinates":[-105.15000000000001,29.03333],"type":"Point"}
}