{
  "type": "Feature",
  "properties": {
    "gn:admin1_code":"25",
    "gn:admin2_code":"8.0",
    "gn:asciiname":"Las Granjas del Norote",
    "gn:country_code":"MX",
    "gn:dem":19,
    "gn:feature_class":"P",
    "gn:feature_code":"PPL",
    "gn:name":"Las Granjas del Norote",
    "gn:population":130,
    "gn:timezone":"America/Mazatlan",
    "iso:country":"MX",
    "wof:name":"Las Granjas del Norote",
    "wof:placetype":"locality",
    "wof:population":130
},
  "geometry": {"coordinates":[-106.96805999999999,24.02944],"type":"Point"}
}