{
  "type": "Feature",
  "properties": {
    "gn:admin1_code":"21",
    "gn:admin2_code":"64.0",
    "gn:asciiname":"Las Balsas",
    "gn:country_code":"MX",
    "gn:dem":226,
    "gn:feature_class":"P",
    "gn:feature_code":"PPL",
    "gn:name":"Las Balsas",
    "gn:population":0,
    "gn:timezone":"America/Mexico_City",
    "iso:country":"MX",
    "name:spa_x_preferred":[
        "Las Balsas"
    ],
    "wof:name":"Las Balsas",
    "wof:placetype":"locality"
},
  "geometry": {"coordinates":[-97.78438,20.70333],"type":"Point"}
}