{
  "type": "Feature",
  "properties": {
    "gn:admin1_code":"5",
    "gn:admin2_code":"97.0",
    "gn:asciiname":"Cristo Rey",
    "gn:country_code":"MX",
    "gn:dem":8,
    "gn:feature_class":"P",
    "gn:feature_code":"PPL",
    "gn:name":"Cristo Rey",
    "gn:population":4,
    "gn:timezone":"America/Mexico_City",
    "iso:country":"MX",
    "name:ceb_x_preferred":[
        "Cristo Rey"
    ],
    "name:fra_x_preferred":[
        "Statue du Christ-Roi"
    ],
    "name:hun_x_preferred":[
        "Krisztus kir\u00e1ly szobor"
    ],
    "name:nds_x_preferred":[
        "Cristo Rey"
    ],
    "name:spa_x_preferred":[
        "Cristo Rey"
    ],
    "name:swe_x_preferred":[
        "Cristo Rey"
    ],
    "wof:name":"Cristo Rey",
    "wof:placetype":"locality",
    "wof:population":4
},
  "geometry": {"coordinates":[-93.72833,15.90083],"type":"Point"}
}