{
  "type": "Feature",
  "properties": {
    "gn:admin1_code":"3",
    "gn:admin2_code":"3",
    "gn:asciiname":"Puerto Datil",
    "gn:country_code":"MX",
    "gn:dem":8,
    "gn:feature_class":"P",
    "gn:feature_code":"PPL",
    "gn:name":"Puerto D\u00e1til",
    "gn:population":42,
    "gn:timezone":"America/Mazatlan",
    "iso:country":"MX",
    "name:und_x_variant":[
        "Puerto D\u00e1til"
    ],
    "wof:name":"Puerto Datil",
    "wof:placetype":"locality",
    "wof:population":42
},
  "geometry": {"coordinates":[-111.52119,24.4072],"type":"Point"}
}