{
  "type": "Feature",
  "properties": {
    "gn:admin1_code":"20",
    "gn:admin2_code":"526.0",
    "gn:asciiname":"Cienega Grande",
    "gn:country_code":"MX",
    "gn:dem":989,
    "gn:feature_class":"P",
    "gn:feature_code":"PPL",
    "gn:name":"Ci\u00e9nega Grande",
    "gn:population":211,
    "gn:timezone":"America/Mexico_City",
    "iso:country":"MX",
    "name:und_x_variant":[
        "Ci\u00e9nega Grande"
    ],
    "wof:name":"Cienega Grande",
    "wof:placetype":"locality",
    "wof:population":211
},
  "geometry": {"coordinates":[-97.23806,16.09611],"type":"Point"}
}