{
  "type": "Feature",
  "properties": {
    "gn:admin1_code":"28",
    "gn:admin2_code":"35.0",
    "gn:asciiname":"San Juan (Francisco Ramirez)",
    "gn:country_code":"MX",
    "gn:dem":17,
    "gn:feature_class":"P",
    "gn:feature_code":"PPL",
    "gn:name":"San Juan (Francisco Ram\u00edrez)",
    "gn:population":5,
    "gn:timezone":"America/Monterrey",
    "iso:country":"MX",
    "wof:name":"San Juan (Francisco Ramirez)",
    "wof:placetype":"locality",
    "wof:population":5
},
  "geometry": {"coordinates":[-97.94861,25.37139],"type":"Point"}
}