{
  "type": "Feature",
  "properties": {
    "gn:admin1_code":"27",
    "gn:admin2_code":"3.0",
    "gn:asciiname":"Mixteca Tercera Seccion",
    "gn:country_code":"MX",
    "gn:dem":5,
    "gn:feature_class":"P",
    "gn:feature_code":"PPL",
    "gn:name":"Mixteca Tercera Secci\u00f3n",
    "gn:population":0,
    "gn:timezone":"America/Mexico_City",
    "iso:country":"MX",
    "name:spa_x_preferred":[
        "Mixteca Tecera Secci\u00f3n"
    ],
    "name:spa_x_variant":[
        "Mixteca Tercera Secci\u00f3n"
    ],
    "wof:name":"Mixteca Tercera Seccion",
    "wof:placetype":"locality"
},
  "geometry": {"coordinates":[-92.56389,18.09079],"type":"Point"}
}