{
  "type": "Feature",
  "properties": {
    "gn:admin1_code":"6.0",
    "gn:admin2_code":"29.0",
    "gn:asciiname":"El Chapulin",
    "gn:country_code":"MX",
    "gn:dem":2291,
    "gn:feature_class":"P",
    "gn:feature_code":"PPL",
    "gn:name":"El Chapul\u00edn",
    "gn:population":0,
    "gn:timezone":"America/Chihuahua",
    "iso:country":"MX",
    "name:spa_x_preferred":[
        "El Chapul\u00edn"
    ],
    "wof:name":"El Chapulin",
    "wof:placetype":"locality"
},
  "geometry": {"coordinates":[-106.88902,25.89985],"type":"Point"}
}