{
  "type": "Feature",
  "properties": {
    "gn:admin1_code":"30",
    "gn:admin2_code":"82.0",
    "gn:asciiname":"La Mendez",
    "gn:country_code":"MX",
    "gn:dem":22,
    "gn:feature_class":"P",
    "gn:feature_code":"PPL",
    "gn:name":"La M\u00e9ndez",
    "gn:population":58,
    "gn:timezone":"America/Mexico_City",
    "iso:country":"MX",
    "name:und_x_variant":[
        "La M\u00e9ndez"
    ],
    "wof:name":"La Mendez",
    "wof:placetype":"locality",
    "wof:population":58
},
  "geometry": {"coordinates":[-94.35972,18.04778],"type":"Point"}
}