{
  "type": "Feature",
  "properties": {
    "gn:admin1_code":"6",
    "gn:admin2_code":"48.0",
    "gn:asciiname":"El Entronque",
    "gn:country_code":"MX",
    "gn:dem":1886,
    "gn:feature_class":"P",
    "gn:feature_code":"PPL",
    "gn:name":"El Entronque",
    "gn:population":8,
    "gn:timezone":"America/Chihuahua",
    "iso:country":"MX",
    "wof:name":"El Entronque",
    "wof:placetype":"locality",
    "wof:population":8
},
  "geometry": {"coordinates":[-107.44944,29.02444],"type":"Point"}
}