{
  "type": "Feature",
  "properties": {
    "gn:admin1_code":"6",
    "gn:admin2_code":"28.0",
    "gn:asciiname":"Rancho Monte Bello",
    "gn:country_code":"MX",
    "gn:dem":1087,
    "gn:feature_class":"P",
    "gn:feature_code":"PPL",
    "gn:name":"Rancho Monte Bello",
    "gn:population":7,
    "gn:timezone":"America/Chihuahua",
    "iso:country":"MX",
    "wof:name":"Rancho Monte Bello",
    "wof:placetype":"locality",
    "wof:population":7
},
  "geometry": {"coordinates":[-106.10029,31.38381],"type":"Point"}
}