{
  "type": "Feature",
  "properties": {
    "gn:admin1_code":"14",
    "gn:admin2_code":"94",
    "gn:asciiname":"Los Sauces",
    "gn:country_code":"MX",
    "gn:dem":1502,
    "gn:feature_class":"P",
    "gn:feature_code":"PPL",
    "gn:name":"Los Sauces",
    "gn:population":19,
    "gn:timezone":"America/Mexico_City",
    "iso:country":"MX",
    "wof:name":"Los Sauces",
    "wof:placetype":"locality",
    "wof:population":19
},
  "geometry": {"coordinates":[-103.88333,21.10778],"type":"Point"}
}