{
  "type": "Feature",
  "properties": {
    "gn:admin1_code":"11",
    "gn:admin2_code":"32.0",
    "gn:asciiname":"El Mastranto",
    "gn:country_code":"MX",
    "gn:dem":2159,
    "gn:feature_class":"P",
    "gn:feature_code":"PPL",
    "gn:name":"El Mastranto",
    "gn:population":387,
    "gn:timezone":"America/Mexico_City",
    "iso:country":"MX",
    "wof:name":"El Mastranto",
    "wof:placetype":"locality",
    "wof:population":387
},
  "geometry": {"coordinates":[-100.45139,20.98],"type":"Point"}
}