{
  "type": "Feature",
  "properties": {
    "iso:country":"MX",
    "name:spa_x_preferred":[
        "Obrera"
    ],
    "qs:gn_adm0_cc":"MX",
    "qs:gn_local":3516355,
    "qs:gn_nam_loc":"Tampico, Tampico, Tamaulipas, MX",
    "qs:gn_namadm1":"28",
    "qs:local_max":228,
    "qs:local_sum":646,
    "qs:localhoods":7,
    "qs:name":"Obrera",
    "qs:name_adm0":"M\u00e9xico",
    "qs:name_adm1":"Tamaulipas",
    "qs:name_adm2":"Tampico",
    "qs:name_local":"Tampico",
    "qs:photo_max":133,
    "qs:photo_sum":217,
    "qs:placetype":"Suburb",
    "qs:quad_count":11,
    "qs:woe_adm0":23424900,
    "qs:woe_adm1":2346291,
    "qs:woe_adm2":12601669,
    "qs:woe_lau":0,
    "qs:woe_local":148123,
    "qs:woe_ver":"7.10.0",
    "wof:lang":[
        "spa"
    ],
    "wof:name":"Obrera",
    "wof:placetype":"neighbourhood"
},
  "geometry": {"coordinates":[-97.85230199999999,22.234159],"type":"Point"}
}