{
  "type": "Feature",
  "properties": {
    "gn:admin1_code":"28.0",
    "gn:admin2_code":"2.0",
    "gn:asciiname":"El Cabrito",
    "gn:country_code":"MX",
    "gn:dem":637,
    "gn:feature_class":"P",
    "gn:feature_code":"PPL",
    "gn:name":"El Cabrito",
    "gn:population":3,
    "gn:timezone":"America/Monterrey",
    "iso:country":"MX",
    "name:spa_x_preferred":[
        "El Cabrito"
    ],
    "wof:name":"El Cabrito",
    "wof:placetype":"locality",
    "wof:population":3
},
  "geometry": {"coordinates":[-98.34889,23.0575],"type":"Point"}
}