{
  "type": "Feature",
  "properties": {
    "gn:admin1_code":"14",
    "gn:admin2_code":"60",
    "gn:asciiname":"Ipalco de Enmedio",
    "gn:country_code":"MX",
    "gn:dem":1736,
    "gn:feature_class":"P",
    "gn:feature_code":"PPL",
    "gn:name":"Ipalco de Enmedio",
    "gn:population":37,
    "gn:timezone":"America/Mexico_City",
    "iso:country":"MX",
    "wof:name":"Ipalco de Enmedio",
    "wof:placetype":"locality",
    "wof:population":37
},
  "geometry": {"coordinates":[-102.73166999999999,21.29444],"type":"Point"}
}