{
  "type": "Feature",
  "properties": {
    "gn:admin1_code":"21",
    "gn:admin2_code":"145",
    "gn:asciiname":"Cotzapotitla",
    "gn:country_code":"MX",
    "gn:dem":115,
    "gn:feature_class":"P",
    "gn:feature_code":"PPL",
    "gn:name":"Cotzapotitla",
    "gn:population":20,
    "gn:timezone":"America/Mexico_City",
    "iso:country":"MX",
    "wof:name":"Cotzapotitla",
    "wof:placetype":"locality",
    "wof:population":20
},
  "geometry": {"coordinates":[-96.78354,18.42352],"type":"Point"}
}