{
  "type": "Feature",
  "properties": {
    "gn:admin1_code":"6",
    "gn:admin2_code":"9.0",
    "gn:asciiname":"Bellavista",
    "gn:country_code":"MX",
    "gn:dem":2341,
    "gn:feature_class":"P",
    "gn:feature_code":"PPL",
    "gn:name":"Bellavista",
    "gn:population":60,
    "gn:timezone":"America/Chihuahua",
    "iso:country":"MX",
    "name:cat_x_preferred":[
        "Bellavista"
    ],
    "name:ceb_x_preferred":[
        "Bellavista"
    ],
    "name:deu_x_preferred":[
        "Bellavista"
    ],
    "name:fra_x_preferred":[
        "Bellavista"
    ],
    "name:ita_x_preferred":[
        "Bellavista"
    ],
    "name:kor_x_preferred":[
        "\ubca8\ub77c\ube44\uc2a4\ud0c0"
    ],
    "name:nld_x_preferred":[
        "Bellavista"
    ],
    "name:pol_x_preferred":[
        "Bellavista"
    ],
    "name:por_x_preferred":[
        "Bellavista"
    ],
    "name:spa_x_preferred":[
        "Bellavista"
    ],
    "name:srp_x_preferred":[
        "Bellavista"
    ],
    "name:swe_x_preferred":[
        "Bellavista"
    ],
    "wof:name":"Bellavista",
    "wof:placetype":"locality",
    "wof:population":60
},
  "geometry": {"coordinates":[-107.77160000000001,27.73797],"type":"Point"}
}