{
  "type": "Feature",
  "properties": {
    "gn:admin1_code":"25",
    "gn:admin2_code":"17.0",
    "gn:asciiname":"El Chapote",
    "gn:country_code":"MX",
    "gn:dem":780,
    "gn:feature_class":"P",
    "gn:feature_code":"PPL",
    "gn:name":"El Chapote",
    "gn:population":8,
    "gn:timezone":"America/Mazatlan",
    "iso:country":"MX",
    "wof:name":"El Chapote",
    "wof:placetype":"locality",
    "wof:population":8
},
  "geometry": {"coordinates":[-107.94749,26.17256],"type":"Point"}
}