{
  "type": "Feature",
  "properties": {
    "gn:admin1_code":"5",
    "gn:admin2_code":"52",
    "gn:asciiname":"Tres Hermanos",
    "gn:country_code":"MX",
    "gn:dem":1101,
    "gn:feature_class":"P",
    "gn:feature_code":"PPL",
    "gn:name":"Tres Hermanos",
    "gn:population":14,
    "gn:timezone":"America/Mexico_City",
    "iso:country":"MX",
    "wof:name":"Tres Hermanos",
    "wof:placetype":"locality",
    "wof:population":14
},
  "geometry": {"coordinates":[-91.6675,16.26139],"type":"Point"}
}