{
  "type": "Feature",
  "properties": {
    "gn:admin1_code":"19.0",
    "gn:admin2_code":"17.0",
    "gn:asciiname":"Dolores",
    "gn:country_code":"MX",
    "gn:dem":1935,
    "gn:feature_class":"P",
    "gn:feature_code":"PPL",
    "gn:name":"Dolores",
    "gn:population":0,
    "gn:timezone":"America/Monterrey",
    "iso:country":"MX",
    "wof:name":"Dolores",
    "wof:placetype":"locality"
},
  "geometry": {"coordinates":[-100.16667,24.61667000000001],"type":"Point"}
}