{
  "type": "Feature",
  "properties": {
    "gn:admin1_code":"11.0",
    "gn:asciiname":"Loma de Palo Verde",
    "gn:country_code":"MX",
    "gn:dem":1711,
    "gn:feature_class":"P",
    "gn:feature_code":"PPL",
    "gn:name":"Loma de Palo Verde",
    "gn:population":0,
    "gn:timezone":"America/Mexico_City",
    "iso:country":"MX",
    "name:spa_x_preferred":[
        "Loma de Palo Verde"
    ],
    "name:spa_x_variant":[
        "Lomita de Palo Verde"
    ],
    "wof:name":"Loma de Palo Verde",
    "wof:placetype":"locality"
},
  "geometry": {"coordinates":[-101.83817000000001,20.32851],"type":"Point"}
}