{
  "type": "Feature",
  "properties": {
    "gn:admin1_code":"28",
    "gn:admin2_code":"32.0",
    "gn:asciiname":"Santa Librada",
    "gn:country_code":"MX",
    "gn:dem":189,
    "gn:feature_class":"P",
    "gn:feature_code":"PPL",
    "gn:name":"Santa Librada",
    "gn:population":0,
    "gn:timezone":"America/Matamoros",
    "iso:country":"MX",
    "name:spa_x_preferred":[
        "Santa Librada"
    ],
    "wof:name":"Santa Librada",
    "wof:placetype":"locality"
},
  "geometry": {"coordinates":[-98.45753000000001,25.53892],"type":"Point"}
}