{
  "type": "Feature",
  "properties": {
    "gn:admin1_code":"21",
    "gn:admin2_code":"27.0",
    "gn:asciiname":"San Simon Tlacuilotepec",
    "gn:country_code":"MX",
    "gn:dem":1952,
    "gn:feature_class":"P",
    "gn:feature_code":"PPL",
    "gn:name":"San Sim\u00f3n Tlacuilotepec",
    "gn:population":110,
    "gn:timezone":"America/Mexico_City",
    "iso:country":"MX",
    "name:und_x_variant":[
        "San Sim\u00f3n Tlacuilotepec"
    ],
    "wof:name":"San Simon Tlacuilotepec",
    "wof:placetype":"locality",
    "wof:population":110
},
  "geometry": {"coordinates":[-97.49401,18.04448],"type":"Point"}
}