{
  "type": "Feature",
  "properties": {
    "gn:admin1_code":"6",
    "gn:admin2_code":"27.0",
    "gn:asciiname":"Pesachi",
    "gn:country_code":"MX",
    "gn:dem":2377,
    "gn:feature_class":"P",
    "gn:feature_code":"PPL",
    "gn:name":"Pesachi",
    "gn:population":28,
    "gn:timezone":"America/Chihuahua",
    "iso:country":"MX",
    "name:spa_x_preferred":[
        "Pesachi"
    ],
    "wof:name":"Pesachi",
    "wof:placetype":"locality",
    "wof:population":28
},
  "geometry": {"coordinates":[-107.37231,27.21867],"type":"Point"}
}