{
  "type": "Feature",
  "properties": {
    "gn:admin1_code":"16",
    "gn:admin2_code":"12",
    "gn:asciiname":"La Nueva",
    "gn:country_code":"MX",
    "gn:dem":265,
    "gn:feature_class":"P",
    "gn:feature_code":"PPL",
    "gn:name":"La Nueva",
    "gn:population":15,
    "gn:timezone":"America/Mexico_City",
    "iso:country":"MX",
    "wof:name":"La Nueva",
    "wof:placetype":"locality",
    "wof:population":15
},
  "geometry": {"coordinates":[-102.52916999999999,19.12083],"type":"Point"}
}