{
  "type": "Feature",
  "properties": {
    "gn:admin1_code":"28",
    "gn:admin2_code":"6.0",
    "gn:asciiname":"El Caracol (Los Caracoles)",
    "gn:country_code":"MX",
    "gn:dem":1606,
    "gn:feature_class":"P",
    "gn:feature_code":"PPL",
    "gn:name":"El Caracol (Los Caracoles)",
    "gn:population":213,
    "gn:timezone":"America/Monterrey",
    "iso:country":"MX",
    "wof:name":"El Caracol (Los Caracoles)",
    "wof:placetype":"locality",
    "wof:population":213
},
  "geometry": {"coordinates":[-99.87166999999999,23.32944],"type":"Point"}
}