{
  "type": "Feature",
  "properties": {
    "gn:admin1_code":"4.0",
    "gn:admin2_code":"11.0",
    "gn:asciiname":"Arroyo San Juan",
    "gn:country_code":"MX",
    "gn:dem":49,
    "gn:feature_class":"P",
    "gn:feature_code":"PPL",
    "gn:name":"Arroyo San Juan",
    "gn:population":0,
    "gn:timezone":"America/Merida",
    "iso:country":"MX",
    "name:spa_x_preferred":[
        "San Juan"
    ],
    "name:spa_x_variant":[
        "Arroyo San Juan",
        "Las Golondrinas"
    ],
    "wof:name":"Arroyo San Juan",
    "wof:placetype":"locality"
},
  "geometry": {"coordinates":[-90.62945999999999,18.10773],"type":"Point"}
}