{
  "type": "Feature",
  "properties": {
    "gn:admin1_code":"5",
    "gn:admin2_code":"61.0",
    "gn:asciiname":"Union Zaragoza",
    "gn:country_code":"MX",
    "gn:dem":974,
    "gn:feature_class":"P",
    "gn:feature_code":"PPL",
    "gn:name":"Uni\u00f3n Zaragoza",
    "gn:population":252,
    "gn:timezone":"America/Mexico_City",
    "iso:country":"MX",
    "name:und_x_variant":[
        "Uni\u00f3n Zaragoza"
    ],
    "wof:name":"Union Zaragoza",
    "wof:placetype":"locality",
    "wof:population":252
},
  "geometry": {"coordinates":[-93.45186,16.88815],"type":"Point"}
}