{
  "type": "Feature",
  "properties": {
    "gn:admin1_code":"18",
    "gn:admin2_code":"17",
    "gn:asciiname":"Guayabitos",
    "gn:country_code":"MX",
    "gn:dem":1099,
    "gn:feature_class":"P",
    "gn:feature_code":"PPL",
    "gn:name":"Guayabitos",
    "gn:population":38,
    "gn:timezone":"America/Mazatlan",
    "iso:country":"MX",
    "wof:name":"Guayabitos",
    "wof:placetype":"locality",
    "wof:population":38
},
  "geometry": {"coordinates":[-105.00082999999999,21.52083],"type":"Point"}
}