{
  "type": "Feature",
  "properties": {
    "gn:admin1_code":"6.0",
    "gn:admin2_code":"51.0",
    "gn:asciiname":"El Perdedero",
    "gn:country_code":"MX",
    "gn:dem":948,
    "gn:feature_class":"P",
    "gn:feature_code":"PPL",
    "gn:name":"El Perdedero",
    "gn:population":0,
    "gn:timezone":"America/Chihuahua",
    "iso:country":"MX",
    "name:spa_x_preferred":[
        "El Perdedero"
    ],
    "wof:name":"El Perdedero",
    "wof:placetype":"locality"
},
  "geometry": {"coordinates":[-108.47322,28.26331],"type":"Point"}
}