{
  "type": "Feature",
  "properties": {
    "gn:admin1_code":"10.0",
    "gn:admin2_code":"19.0",
    "gn:asciiname":"Mesitas",
    "gn:country_code":"MX",
    "gn:dem":1515,
    "gn:feature_class":"P",
    "gn:feature_code":"PPL",
    "gn:name":"Mesitas",
    "gn:population":0,
    "gn:timezone":"America/Monterrey",
    "iso:country":"MX",
    "name:spa_x_preferred":[
        "Mesitas"
    ],
    "wof:name":"Mesitas",
    "wof:placetype":"locality"
},
  "geometry": {"coordinates":[-106.0154,24.76432],"type":"Point"}
}