{
  "type": "Feature",
  "properties": {
    "gn:admin1_code":"6",
    "gn:admin2_code":"45.0",
    "gn:asciiname":"Colonia Dieciocho de Marzo",
    "gn:country_code":"MX",
    "gn:dem":1170,
    "gn:feature_class":"P",
    "gn:feature_code":"PPL",
    "gn:name":"Colonia Dieciocho de Marzo",
    "gn:population":74,
    "gn:timezone":"America/Chihuahua",
    "iso:country":"MX",
    "wof:name":"Colonia Dieciocho de Marzo",
    "wof:placetype":"locality",
    "wof:population":74
},
  "geometry": {"coordinates":[-105.37712999999999,28.27104000000001],"type":"Point"}
}