{
  "type": "Feature",
  "properties": {
    "gn:admin1_code":"30.0",
    "gn:admin2_code":"211.0",
    "gn:asciiname":"Bella Esperanza",
    "gn:country_code":"MX",
    "gn:dem":62,
    "gn:feature_class":"P",
    "gn:feature_code":"PPL",
    "gn:name":"Bella Esperanza",
    "gn:population":36,
    "gn:timezone":"America/Mexico_City",
    "iso:country":"MX",
    "name:spa_x_preferred":[
        "Bella Esperanza"
    ],
    "wof:name":"Bella Esperanza",
    "wof:placetype":"locality",
    "wof:population":36
},
  "geometry": {"coordinates":[-96.97611000000001,20.14944],"type":"Point"}
}