{
  "type": "Feature",
  "properties": {
    "gn:admin1_code":"14",
    "gn:admin2_code":"46.0",
    "gn:asciiname":"El Mayoral de Abajo",
    "gn:country_code":"MX",
    "gn:dem":1805,
    "gn:feature_class":"P",
    "gn:feature_code":"PPL",
    "gn:name":"El Mayoral de Abajo",
    "gn:population":139,
    "gn:timezone":"America/Mexico_City",
    "iso:country":"MX",
    "wof:name":"El Mayoral de Abajo",
    "wof:placetype":"locality",
    "wof:population":139
},
  "geometry": {"coordinates":[-102.45222,21.21056],"type":"Point"}
}