{
  "type": "Feature",
  "properties": {
    "gn:admin1_code":"22.0",
    "gn:admin2_code":"11.0",
    "gn:asciiname":"El Meson",
    "gn:country_code":"MX",
    "gn:dem":1957,
    "gn:feature_class":"P",
    "gn:feature_code":"PPL",
    "gn:name":"El Mes\u00f3n",
    "gn:population":0,
    "gn:timezone":"America/Mexico_City",
    "iso:country":"MX",
    "name:spa_x_preferred":[
        "El Mes\u00f3n"
    ],
    "wof:name":"El Meson",
    "wof:placetype":"locality"
},
  "geometry": {"coordinates":[-100.34316,20.75694],"type":"Point"}
}