{
  "type": "Feature",
  "properties": {
    "gn:admin1_code":"4",
    "gn:admin2_code":"6",
    "gn:asciiname":"La Paz",
    "gn:country_code":"MX",
    "gn:dem":86,
    "gn:feature_class":"P",
    "gn:feature_code":"PPL",
    "gn:name":"La Paz",
    "gn:population":11,
    "gn:timezone":"America/Merida",
    "iso:country":"MX",
    "wof:name":"La Paz",
    "wof:placetype":"locality",
    "wof:population":11
},
  "geometry": {"coordinates":[-90.01778,19.70583],"type":"Point"}
}