{
  "type": "Feature",
  "properties": {
    "gn:admin1_code":"32.0",
    "gn:asciiname":"El Llano del Jocoyole",
    "gn:country_code":"MX",
    "gn:dem":2178,
    "gn:feature_class":"P",
    "gn:feature_code":"PPL",
    "gn:name":"El Llano del Jocoyole",
    "gn:population":0,
    "gn:timezone":"America/Mexico_City",
    "iso:country":"MX",
    "name:spa_x_preferred":[
        "El Llano del Jocoyole"
    ],
    "wof:name":"El Llano del Jocoyole",
    "wof:placetype":"locality"
},
  "geometry": {"coordinates":[-102.86315,21.63167],"type":"Point"}
}