{
  "type": "Feature",
  "properties": {
    "gn:admin1_code":"6",
    "gn:admin2_code":"8",
    "gn:asciiname":"El Pochote",
    "gn:country_code":"MX",
    "gn:dem":778,
    "gn:feature_class":"P",
    "gn:feature_code":"PPL",
    "gn:name":"El Pochote",
    "gn:population":14,
    "gn:timezone":"America/Chihuahua",
    "iso:country":"MX",
    "wof:name":"El Pochote",
    "wof:placetype":"locality",
    "wof:population":14
},
  "geometry": {"coordinates":[-107.74222,26.85139],"type":"Point"}
}