{
  "type": "Feature",
  "properties": {
    "gn:admin1_code":"10.0",
    "gn:admin2_code":"11.0",
    "gn:asciiname":"La Barranca",
    "gn:country_code":"MX",
    "gn:dem":1883,
    "gn:feature_class":"P",
    "gn:feature_code":"PPL",
    "gn:name":"La Barranca",
    "gn:population":0,
    "gn:timezone":"America/Monterrey",
    "iso:country":"MX",
    "name:fra_x_preferred":[
        "La Barranca"
    ],
    "name:spa_x_preferred":[
        "La Barranca"
    ],
    "name:und_x_variant":[
        "Barranco",
        "Barranca"
    ],
    "wof:name":"La Barranca",
    "wof:placetype":"locality"
},
  "geometry": {"coordinates":[-105.21528000000001,25.85831],"type":"Point"}
}