{
  "type": "Feature",
  "properties": {
    "gn:admin1_code":"12",
    "gn:admin2_code":"61.0",
    "gn:asciiname":"Colonia Tres de Mayo",
    "gn:country_code":"MX",
    "gn:dem":1376,
    "gn:feature_class":"P",
    "gn:feature_code":"PPL",
    "gn:name":"Colonia Tres de Mayo",
    "gn:population":6,
    "gn:timezone":"America/Mexico_City",
    "iso:country":"MX",
    "wof:name":"Colonia Tres de Mayo",
    "wof:placetype":"locality",
    "wof:population":6
},
  "geometry": {"coordinates":[-99.37721999999999,17.58861],"type":"Point"}
}