{
  "type": "Feature",
  "properties": {
    "gn:admin1_code":"11",
    "gn:admin2_code":"14",
    "gn:asciiname":"Lobitos de Abajo",
    "gn:country_code":"MX",
    "gn:dem":2005,
    "gn:feature_class":"P",
    "gn:feature_code":"PPL",
    "gn:name":"Lobitos de Abajo",
    "gn:population":13,
    "gn:timezone":"America/Mexico_City",
    "iso:country":"MX",
    "wof:name":"Lobitos de Abajo",
    "wof:placetype":"locality",
    "wof:population":13
},
  "geometry": {"coordinates":[-100.75082999999999,21.28556],"type":"Point"}
}