{
  "type": "Feature",
  "properties": {
    "gn:admin1_code":"6",
    "gn:admin2_code":"9.0",
    "gn:asciiname":"Recayna",
    "gn:country_code":"MX",
    "gn:dem":2275,
    "gn:feature_class":"P",
    "gn:feature_code":"PPL",
    "gn:name":"Recayna",
    "gn:population":0,
    "gn:timezone":"America/Chihuahua",
    "iso:country":"MX",
    "name:spa_x_preferred":[
        "Recayna"
    ],
    "name:und_x_variant":[
        "Rancho Recaina"
    ],
    "wof:name":"Recayna",
    "wof:placetype":"locality",
    "wof:population":8
},
  "geometry": {"coordinates":[-107.75017,27.83151],"type":"Point"}
}