{
  "type": "Feature",
  "properties": {
    "gn:admin1_code":"25",
    "gn:admin2_code":"6.0",
    "gn:asciiname":"El Tapon",
    "gn:country_code":"MX",
    "gn:dem":250,
    "gn:feature_class":"P",
    "gn:feature_code":"PPL",
    "gn:name":"El Tap\u00f3n",
    "gn:population":0,
    "gn:timezone":"America/Mazatlan",
    "iso:country":"MX",
    "name:spa_x_preferred":[
        "El Tap\u00f3n"
    ],
    "name:und_x_variant":[
        "Tap\u00f3n"
    ],
    "wof:name":"El Tapon",
    "wof:placetype":"locality"
},
  "geometry": {"coordinates":[-106.94504000000001,24.24503],"type":"Point"}
}