{
  "type": "Feature",
  "properties": {
    "gn:admin1_code":"5",
    "gn:admin2_code":"52",
    "gn:asciiname":"Nuevo Chacalaltic",
    "gn:country_code":"MX",
    "gn:dem":1520,
    "gn:feature_class":"P",
    "gn:feature_code":"PPL",
    "gn:name":"Nuevo Chacalaltic",
    "gn:population":45,
    "gn:timezone":"America/Mexico_City",
    "iso:country":"MX",
    "wof:name":"Nuevo Chacalaltic",
    "wof:placetype":"locality",
    "wof:population":45
},
  "geometry": {"coordinates":[-91.95944,16.37528],"type":"Point"}
}