{
  "type": "Feature",
  "properties": {
    "gn:admin1_code":"11",
    "gn:admin2_code":"3.0",
    "gn:asciiname":"Los Juarez",
    "gn:country_code":"MX",
    "gn:dem":1996,
    "gn:feature_class":"P",
    "gn:feature_code":"PPL",
    "gn:name":"Los Ju\u00e1rez",
    "gn:population":297,
    "gn:timezone":"America/Mexico_City",
    "iso:country":"MX",
    "name:und_x_variant":[
        "Los Ju\u00e1rez"
    ],
    "wof:name":"Los Juarez",
    "wof:placetype":"locality",
    "wof:population":297
},
  "geometry": {"coordinates":[-100.72638999999999,21.05167],"type":"Point"}
}