{
  "type": "Feature",
  "properties": {
    "gn:admin1_code":"11.0",
    "gn:admin2_code":"22.0",
    "gn:asciiname":"El Nopal Verde",
    "gn:country_code":"MX",
    "gn:dem":2272,
    "gn:feature_class":"P",
    "gn:feature_code":"PPL",
    "gn:name":"El Nopal Verde",
    "gn:population":2,
    "gn:timezone":"America/Mexico_City",
    "iso:country":"MX",
    "wof:name":"El Nopal Verde",
    "wof:placetype":"locality",
    "wof:population":2
},
  "geometry": {"coordinates":[-101.49444,21.70972],"type":"Point"}
}