{
  "type": "Feature",
  "properties": {
    "gn:admin1_code":"11.0",
    "gn:admin2_code":"1.0",
    "gn:asciiname":"Cerritos de Aceves",
    "gn:country_code":"MX",
    "gn:dem":1693,
    "gn:feature_class":"P",
    "gn:feature_code":"PPL",
    "gn:name":"Cerritos de Aceves",
    "gn:population":0,
    "gn:timezone":"America/Mexico_City",
    "iso:country":"MX",
    "name:spa_x_preferred":[
        "Cerritos de Aceves"
    ],
    "wof:name":"Cerritos de Aceves",
    "wof:placetype":"locality"
},
  "geometry": {"coordinates":[-101.61742,20.3274],"type":"Point"}
}