{
  "type": "Feature",
  "properties": {
    "gn:admin1_code":"7",
    "gn:admin2_code":"2.0",
    "gn:asciiname":"Santa Teresa",
    "gn:country_code":"MX",
    "gn:dem":757,
    "gn:feature_class":"P",
    "gn:feature_code":"PPL",
    "gn:name":"Santa Teresa",
    "gn:population":0,
    "gn:timezone":"America/Matamoros",
    "iso:country":"MX",
    "wof:name":"Santa Teresa",
    "wof:placetype":"locality"
},
  "geometry": {"coordinates":[-101.90679,29.36001],"type":"Point"}
}