{
  "type": "Feature",
  "properties": {
    "gn:admin1_code":"26",
    "gn:admin2_code":"26.0",
    "gn:asciiname":"Yemobari",
    "gn:country_code":"MX",
    "gn:dem":25,
    "gn:feature_class":"P",
    "gn:feature_code":"PPL",
    "gn:name":"Yemobari",
    "gn:population":4,
    "gn:timezone":"America/Hermosillo",
    "iso:country":"MX",
    "wof:name":"Yemobari",
    "wof:placetype":"locality",
    "wof:population":4
},
  "geometry": {"coordinates":[-109.58194,27.06],"type":"Point"}
}