{
  "type": "Feature",
  "properties": {
    "gn:admin1_code":"24",
    "gn:admin2_code":"12.0",
    "gn:asciiname":"Lay-Mom",
    "gn:country_code":"MX",
    "gn:dem":329,
    "gn:feature_class":"P",
    "gn:feature_code":"PPL",
    "gn:name":"Lay-Mom",
    "gn:population":0,
    "gn:timezone":"America/Mexico_City",
    "iso:country":"MX",
    "name:spa_x_preferred":[
        "Lay-Mom"
    ],
    "wof:name":"Lay-Mom",
    "wof:placetype":"locality"
},
  "geometry": {"coordinates":[-98.92076,21.60307],"type":"Point"}
}