{
  "type": "Feature",
  "properties": {
    "gn:admin1_code":"27",
    "gn:admin2_code":"17.0",
    "gn:asciiname":"Toquilpa",
    "gn:country_code":"MX",
    "gn:dem":18,
    "gn:feature_class":"P",
    "gn:feature_code":"PPL",
    "gn:name":"Toquilpa",
    "gn:population":0,
    "gn:timezone":"America/Mexico_City",
    "iso:country":"MX",
    "name:spa_x_preferred":[
        "Toquilpa"
    ],
    "wof:name":"Toquilpa",
    "wof:placetype":"locality"
},
  "geometry": {"coordinates":[-91.3192,17.54741],"type":"Point"}
}