{
  "type": "Feature",
  "properties": {
    "gn:admin1_code":"11",
    "gn:admin2_code":"44.0",
    "gn:asciiname":"San Antonio el Chico",
    "gn:country_code":"MX",
    "gn:dem":1731,
    "gn:feature_class":"P",
    "gn:feature_code":"PPL",
    "gn:name":"San Antonio el Chico",
    "gn:population":120,
    "gn:timezone":"America/Mexico_City",
    "iso:country":"MX",
    "wof:name":"San Antonio el Chico",
    "wof:placetype":"locality",
    "wof:population":120
},
  "geometry": {"coordinates":[-101.03333000000001,20.56472],"type":"Point"}
}