{
  "type": "Feature",
  "properties": {
    "gn:admin1_code":"12",
    "gn:admin2_code":"52.0",
    "gn:asciiname":"Llano Silleta",
    "gn:country_code":"MX",
    "gn:dem":786,
    "gn:feature_class":"P",
    "gn:feature_code":"PPL",
    "gn:name":"Llano Silleta",
    "gn:population":521,
    "gn:timezone":"America/Mexico_City",
    "iso:country":"MX",
    "wof:name":"Llano Silleta",
    "wof:placetype":"locality",
    "wof:population":521
},
  "geometry": {"coordinates":[-98.6125,16.93806],"type":"Point"}
}