{
  "type": "Feature",
  "properties": {
    "gn:admin1_code":"6.0",
    "gn:admin2_code":"1.0",
    "gn:asciiname":"Estrella del Norte",
    "gn:country_code":"MX",
    "gn:dem":1196,
    "gn:feature_class":"P",
    "gn:feature_code":"PPL",
    "gn:name":"Estrella del Norte",
    "gn:population":0,
    "gn:timezone":"America/Chihuahua",
    "iso:country":"MX",
    "name:spa_x_preferred":[
        "Estrella del Norte"
    ],
    "wof:name":"Estrella del Norte",
    "wof:placetype":"locality"
},
  "geometry": {"coordinates":[-106.50100999999999,30.71199],"type":"Point"}
}