{
  "type": "Feature",
  "properties": {
    "gn:admin1_code":"10",
    "gn:admin2_code":"28.0",
    "gn:asciiname":"Los Hoyos",
    "gn:country_code":"MX",
    "gn:dem":1777,
    "gn:feature_class":"P",
    "gn:feature_code":"PPL",
    "gn:name":"Los Hoyos",
    "gn:population":0,
    "gn:timezone":"America/Monterrey",
    "iso:country":"MX",
    "name:spa_x_preferred":[
        "Los Hoyos"
    ],
    "wof:name":"Los Hoyos",
    "wof:placetype":"locality"
},
  "geometry": {"coordinates":[-104.56365,24.77564],"type":"Point"}
}