{
  "type": "Feature",
  "properties": {
    "gn:admin1_code":"15.0",
    "gn:admin2_code":"7.0",
    "gn:asciiname":"El Capulin Tercera Seccion",
    "gn:country_code":"MX",
    "gn:dem":3036,
    "gn:feature_class":"P",
    "gn:feature_code":"PPL",
    "gn:name":"El Capul\u00edn Tercera Secci\u00f3n",
    "gn:population":0,
    "gn:timezone":"America/Mexico_City",
    "iso:country":"MX",
    "name:spa_x_preferred":[
        "El Capul\u00edn Tercera Secci\u00f3n"
    ],
    "wof:name":"El Capulin Tercera Seccion",
    "wof:placetype":"locality"
},
  "geometry": {"coordinates":[-99.91999,19.29337],"type":"Point"}
}