{
  "type": "Feature",
  "properties": {
    "gn:admin1_code":"31",
    "gn:admin2_code":"35.0",
    "gn:asciiname":"Tzamula",
    "gn:country_code":"MX",
    "gn:dem":23,
    "gn:feature_class":"P",
    "gn:feature_code":"PPL",
    "gn:name":"Tzamula",
    "gn:population":0,
    "gn:timezone":"America/Merida",
    "iso:country":"MX",
    "name:spa_x_preferred":[
        "Tzamula"
    ],
    "wof:name":"Tzamula",
    "wof:placetype":"locality"
},
  "geometry": {"coordinates":[-89.05889999999999,20.82697000000001],"type":"Point"}
}