{
  "type": "Feature",
  "properties": {
    "gn:admin1_code":"6",
    "gn:admin2_code":"12.0",
    "gn:asciiname":"Paraje Baniroachi",
    "gn:country_code":"MX",
    "gn:dem":2425,
    "gn:feature_class":"P",
    "gn:feature_code":"PPL",
    "gn:name":"Paraje Baniroachi",
    "gn:population":0,
    "gn:timezone":"America/Chihuahua",
    "iso:country":"MX",
    "name:spa_x_preferred":[
        "Paraje Baniroachi"
    ],
    "wof:name":"Paraje Baniroachi",
    "wof:placetype":"locality"
},
  "geometry": {"coordinates":[-107.24209999999999,27.86184],"type":"Point"}
}