{
  "type": "Feature",
  "properties": {
    "gn:admin1_code":"10",
    "gn:admin2_code":"39",
    "gn:asciiname":"San Jose de Vargas",
    "gn:country_code":"MX",
    "gn:dem":1982,
    "gn:feature_class":"P",
    "gn:feature_code":"PPL",
    "gn:name":"San Jos\u00e9 de Vargas",
    "gn:population":18,
    "gn:timezone":"America/Monterrey",
    "iso:country":"MX",
    "name:und_x_variant":[
        "San Jos\u00e9 de Vargas"
    ],
    "wof:name":"San Jose de Vargas",
    "wof:placetype":"locality",
    "wof:population":18
},
  "geometry": {"coordinates":[-105.11839000000001,25.00694],"type":"Point"}
}