{
  "type": "Feature",
  "properties": {
    "gn:admin1_code":"1",
    "gn:admin2_code":"6",
    "gn:asciiname":"Marquitos [Granja]",
    "gn:country_code":"MX",
    "gn:dem":1903,
    "gn:feature_class":"P",
    "gn:feature_code":"PPL",
    "gn:name":"Marquitos [Granja]",
    "gn:population":14,
    "gn:timezone":"America/Mexico_City",
    "iso:country":"MX",
    "wof:name":"Marquitos [Granja]",
    "wof:placetype":"locality",
    "wof:population":14
},
  "geometry": {"coordinates":[-102.26833000000001,22.1575],"type":"Point"}
}