{
  "type": "Feature",
  "properties": {
    "gn:admin1_code":"12",
    "gn:admin2_code":"57.0",
    "gn:asciiname":"Los Letrados",
    "gn:country_code":"MX",
    "gn:dem":445,
    "gn:feature_class":"P",
    "gn:feature_code":"PPL",
    "gn:name":"Los Letrados",
    "gn:population":53,
    "gn:timezone":"America/Mexico_City",
    "iso:country":"MX",
    "wof:name":"Los Letrados",
    "wof:placetype":"locality",
    "wof:population":53
},
  "geometry": {"coordinates":[-100.55056999999999,17.4094],"type":"Point"}
}