{
  "type": "Feature",
  "properties": {
    "gn:admin1_code":"26",
    "gn:admin2_code":"17.0",
    "gn:asciiname":"Mina la Herradura",
    "gn:country_code":"MX",
    "gn:dem":164,
    "gn:feature_class":"P",
    "gn:feature_code":"PPL",
    "gn:name":"Mina la Herradura",
    "gn:population":6,
    "gn:timezone":"America/Hermosillo",
    "iso:country":"MX",
    "wof:name":"Mina la Herradura",
    "wof:placetype":"locality",
    "wof:population":6
},
  "geometry": {"coordinates":[-112.84944,31.15083],"type":"Point"}
}