{
  "type": "Feature",
  "properties": {
    "gn:admin1_code":"28",
    "gn:admin2_code":"6.0",
    "gn:asciiname":"Felipe Angeles",
    "gn:country_code":"MX",
    "gn:dem":1555,
    "gn:feature_class":"P",
    "gn:feature_code":"PPL",
    "gn:name":"Felipe \u00c1ngeles",
    "gn:population":0,
    "gn:timezone":"America/Monterrey",
    "iso:country":"MX",
    "name:spa_x_preferred":[
        "Felipe \u00c1ngeles"
    ],
    "wof:name":"Felipe Angeles",
    "wof:placetype":"locality"
},
  "geometry": {"coordinates":[-99.75534,23.38876],"type":"Point"}
}