{
  "type": "Feature",
  "properties": {
    "gn:admin1_code":"10.0",
    "gn:admin2_code":"5.0",
    "gn:asciiname":"Golondrinas",
    "gn:country_code":"MX",
    "gn:dem":2226,
    "gn:feature_class":"P",
    "gn:feature_code":"PPL",
    "gn:name":"Golondrinas",
    "gn:population":0,
    "gn:timezone":"America/Monterrey",
    "iso:country":"MX",
    "name:ceb_x_preferred":[
        "Golondrinas"
    ],
    "name:srp_x_preferred":[
        "\u0413\u043e\u043b\u043e\u043d\u0434\u0440\u0438\u043d\u0430\u0441"
    ],
    "name:swe_x_preferred":[
        "Golondrinas"
    ],
    "wof:name":"Golondrinas",
    "wof:placetype":"locality"
},
  "geometry": {"coordinates":[-104.65000000000001,23.85],"type":"Point"}
}