{
  "type": "Feature",
  "properties": {
    "gn:admin1_code":"6.0",
    "gn:admin2_code":"52.0",
    "gn:asciiname":"El Trebol",
    "gn:country_code":"MX",
    "gn:dem":1229,
    "gn:feature_class":"P",
    "gn:feature_code":"PPL",
    "gn:name":"El Tr\u00e9bol",
    "gn:population":0,
    "gn:timezone":"America/Chihuahua",
    "iso:country":"MX",
    "name:spa_x_preferred":[
        "El Tr\u00e9bol"
    ],
    "name:und_x_variant":[
        "Rancho El Tr\u00e9bol"
    ],
    "wof:name":"El Trebol",
    "wof:placetype":"locality"
},
  "geometry": {"coordinates":[-104.58738,28.80657],"type":"Point"}
}