{
  "type": "Feature",
  "properties": {
    "gn:admin1_code":"21",
    "gn:admin2_code":"69.0",
    "gn:asciiname":"Champusco (Secundaria Tecnica Numero 4) [Escuela]",
    "gn:country_code":"MX",
    "gn:dem":1651,
    "gn:feature_class":"P",
    "gn:feature_code":"PPL",
    "gn:name":"Champusco (Secundaria T\u00e9cnica N\u00famero 4) [Escuela]",
    "gn:population":280,
    "gn:timezone":"America/Mexico_City",
    "iso:country":"MX",
    "wof:name":"Champusco (Secundaria Tecnica Numero 4) [Escuela]",
    "wof:placetype":"locality",
    "wof:population":280
},
  "geometry": {"coordinates":[-98.46444,18.79528],"type":"Point"}
}