{
  "type": "Feature",
  "properties": {
    "gn:admin1_code":"28",
    "gn:admin2_code":"39.0",
    "gn:asciiname":"Cieneguilla",
    "gn:country_code":"MX",
    "gn:dem":1068,
    "gn:feature_class":"P",
    "gn:feature_code":"PPL",
    "gn:name":"Cieneguilla",
    "gn:population":0,
    "gn:timezone":"America/Monterrey",
    "iso:country":"MX",
    "name:spa_x_preferred":[
        "Cieneguillas"
    ],
    "name:spa_x_variant":[
        "Francisco Ignacio Madero"
    ],
    "name:und_x_variant":[
        "Francisco I. Madero",
        "Cieneguilla"
    ],
    "wof:name":"Cieneguilla",
    "wof:placetype":"locality"
},
  "geometry": {"coordinates":[-99.70227,22.87123],"type":"Point"}
}