{
  "type": "Feature",
  "properties": {
    "gn:admin1_code":"6",
    "gn:admin2_code":"29.0",
    "gn:asciiname":"Puerto Blanco (Puerto Rio Verde)",
    "gn:country_code":"MX",
    "gn:dem":2462,
    "gn:feature_class":"P",
    "gn:feature_code":"PPL",
    "gn:name":"Puerto Blanco (Puerto R\u00edo Verde)",
    "gn:population":4,
    "gn:timezone":"America/Chihuahua",
    "iso:country":"MX",
    "name:und_x_variant":[
        "Puerto Blanco (Puerto R\u00edo Verde)"
    ],
    "wof:name":"Puerto Blanco (Puerto Rio Verde)",
    "wof:placetype":"locality",
    "wof:population":4
},
  "geometry": {"coordinates":[-106.49012999999999,26.28523],"type":"Point"}
}