{
  "type": "Feature",
  "properties": {
    "gn:admin1_code":"19",
    "gn:admin2_code":"8.0",
    "gn:asciiname":"Las Vacas",
    "gn:country_code":"MX",
    "gn:dem":552,
    "gn:feature_class":"P",
    "gn:feature_code":"PPL",
    "gn:name":"Las Vacas",
    "gn:population":0,
    "gn:timezone":"America/Monterrey",
    "iso:country":"MX",
    "name:spa_x_preferred":[
        "Las Vacas"
    ],
    "name:und_x_variant":[
        "Rancho Vacas",
        "Vacas"
    ],
    "wof:name":"Las Vacas",
    "wof:placetype":"locality"
},
  "geometry": {"coordinates":[-100.61068,26.47553],"type":"Point"}
}