{
  "type": "Feature",
  "properties": {
    "gn:admin1_code":"15",
    "gn:admin2_code":"86.0",
    "gn:asciiname":"San Martin Tequesquipan (Tequesquipan)",
    "gn:cc2":"MX",
    "gn:country_code":"MX",
    "gn:dem":2352,
    "gn:feature_class":"P",
    "gn:feature_code":"PPL",
    "gn:name":"San Mart\u00edn Tequesquipan (Tequesquipan)",
    "gn:population":1039,
    "gn:timezone":"America/Mexico_City",
    "iso:country":"MX",
    "name:und_x_variant":[
        "Tequisquiapan",
        "Tequexquipan",
        "Tequisquipan",
        "Tequesquipan"
    ],
    "wof:name":"San Martin Tequesquipan (Tequesquipan)",
    "wof:placetype":"locality",
    "wof:population":1039
},
  "geometry": {"coordinates":[-99.94667,19.05806],"type":"Point"}
}