{
  "type": "Feature",
  "properties": {
    "gn:gn_country":"MX",
    "gn:gn_fcode":"PPL",
    "gn:gn_pop":4512,
    "gn:population":4512,
    "iso:country":"MX",
    "name:unk_x_variant":[
        "Tetepa"
    ],
    "qs_pg:aaroncc":"MX",
    "qs_pg:gn_country":"MX",
    "qs_pg:gn_fcode":"PPL",
    "qs_pg:gn_pop":4512,
    "qs_pg:name":"Tepexapa",
    "qs_pg:name_adm0":"M\u00e9xico",
    "qs_pg:name_adm1":"Tlaxcala",
    "qs_pg:photos_9r":0,
    "qs_pg:photos_sr":0,
    "qs_pg:pop_sr":4,
    "qs_pg:qs_pg_placetype":"neighbourhood",
    "qs_pg:qs_pg_placetype_gp":"Suburb",
    "qs_pg:woe_adm0":23424900,
    "woe:adm0_id":23424900,
    "woe:name_adm0":"M\u00e9xico",
    "woe:name_adm1":"Tlaxcala",
    "woe:placetype":"Suburb",
    "wof:name":"Tepexapa",
    "wof:placetype":"neighbourhood",
    "wof:population":4512
},
  "geometry": {"coordinates":[-98.16968,20.1346],"type":"Point"}
}