{
  "type": "Feature",
  "properties": {
    "gn:admin1_code":"30",
    "gn:admin2_code":"62.0",
    "gn:asciiname":"Carrizal",
    "gn:country_code":"MX",
    "gn:dem":1449,
    "gn:feature_class":"P",
    "gn:feature_code":"PPL",
    "gn:name":"Carrizal",
    "gn:population":78,
    "gn:timezone":"America/Mexico_City",
    "iso:country":"MX",
    "name:ceb_x_preferred":[
        "Carrizal"
    ],
    "name:fra_x_preferred":[
        "Carrizal"
    ],
    "name:ita_x_preferred":[
        "Carrizal"
    ],
    "name:jpn_x_preferred":[
        "\u30ab\u30ea\u30b5\u30eb"
    ],
    "name:mlg_x_preferred":[
        "Carrizal"
    ],
    "name:por_x_preferred":[
        "Carrizal"
    ],
    "name:rus_x_preferred":[
        "\u041a\u0430\u0440\u0440\u0438\u0441\u0430\u043b\u044c"
    ],
    "name:spa_x_preferred":[
        "Carrizal"
    ],
    "name:swe_x_preferred":[
        "Carrizal"
    ],
    "wof:name":"Carrizal",
    "wof:placetype":"locality",
    "wof:population":78
},
  "geometry": {"coordinates":[-97.08389,18.97583],"type":"Point"}
}