{
  "type": "Feature",
  "properties": {
    "gn:admin1_code":"2",
    "gn:admin2_code":"2",
    "gn:asciiname":"Familia Lozano Rodriguez (Ejido Chiapas)",
    "gn:country_code":"MX",
    "gn:dem":21,
    "gn:feature_class":"P",
    "gn:feature_code":"PPL",
    "gn:name":"Familia Lozano Rodr\u00edguez (Ejido Chiapas)",
    "gn:population":27,
    "gn:timezone":"America/Tijuana",
    "iso:country":"MX",
    "name:und_x_variant":[
        "Familia Lozano Rodr\u00edguez (Ejido Chiapas)"
    ],
    "wof:name":"Familia Lozano Rodriguez (Ejido Chiapas)",
    "wof:placetype":"locality",
    "wof:population":27
},
  "geometry": {"coordinates":[-114.97889000000001,32.42972],"type":"Point"}
}