{
  "type": "Feature",
  "properties": {
    "gn:admin1_code":"20",
    "gn:admin2_code":"297.0",
    "gn:asciiname":"Candelaria",
    "gn:country_code":"MX",
    "gn:dem":2436,
    "gn:feature_class":"P",
    "gn:feature_code":"PPL",
    "gn:name":"Candelaria",
    "gn:population":0,
    "gn:timezone":"America/Mexico_City",
    "iso:country":"MX",
    "name:spa_x_preferred":[
        "Candelaria"
    ],
    "name:spa_x_variant":[
        "Candelaria de la Uni\u00f3n"
    ],
    "wof:name":"Candelaria",
    "wof:placetype":"locality"
},
  "geometry": {"coordinates":[-97.51152999999999,17.00211],"type":"Point"}
}