{
  "type": "Feature",
  "properties": {
    "gn:admin1_code":"15.0",
    "gn:admin2_code":"123.0",
    "gn:asciiname":"Las Garzas",
    "gn:country_code":"MX",
    "gn:dem":573,
    "gn:feature_class":"P",
    "gn:feature_code":"PPL",
    "gn:name":"Las Garzas",
    "gn:population":0,
    "gn:timezone":"America/Mexico_City",
    "iso:country":"MX",
    "name:spa_x_preferred":[
        "Las Garzas"
    ],
    "wof:name":"Las Garzas",
    "wof:placetype":"locality"
},
  "geometry": {"coordinates":[-100.51425,18.97744],"type":"Point"}
}