{
  "type": "Feature",
  "properties": {
    "gn:admin1_code":"26",
    "gn:admin2_code":"13.0",
    "gn:asciiname":"El Remudadero",
    "gn:country_code":"MX",
    "gn:dem":876,
    "gn:feature_class":"P",
    "gn:feature_code":"PPL",
    "gn:name":"El Remudadero",
    "gn:population":0,
    "gn:timezone":"America/Hermosillo",
    "iso:country":"MX",
    "name:spa_x_preferred":[
        "El Remudadero"
    ],
    "wof:name":"El Remudadero",
    "wof:placetype":"locality"
},
  "geometry": {"coordinates":[-110.16070999999999,30.05648],"type":"Point"}
}