{
  "type": "Feature",
  "properties": {
    "gn:admin1_code":"30",
    "gn:admin2_code":"116.0",
    "gn:asciiname":"La Malinche",
    "gn:country_code":"MX",
    "gn:dem":62,
    "gn:feature_class":"P",
    "gn:feature_code":"PPL",
    "gn:name":"La Malinche",
    "gn:population":6,
    "gn:timezone":"America/Mexico_City",
    "iso:country":"MX",
    "wof:name":"La Malinche",
    "wof:placetype":"locality",
    "wof:population":6
},
  "geometry": {"coordinates":[-94.87721999999999,17.90222],"type":"Point"}
}