{
  "type": "Feature",
  "properties": {
    "gn:admin1_code":"30",
    "gn:admin2_code":"116.0",
    "gn:asciiname":"La Malinche",
    "gn:country_code":"MX",
    "gn:dem":62,
    "gn:feature_class":"P",
    "gn:feature_code":"PPL",
    "gn:name":"La Malinche",
    "gn:population":6,
    "gn:timezone":"America/Mexico_City",
    "iso:country":"MX",
    "name:ara_x_preferred":[
        "\u062f\u0648\u0646\u0627 \u0645\u0627\u0631\u064a\u0646\u0627"
    ],
    "name:cat_x_preferred":[
        "Malintzin"
    ],
    "name:ces_x_preferred":[
        "Malinche"
    ],
    "name:deu_x_preferred":[
        "Malinche"
    ],
    "name:epo_x_preferred":[
        "La Malin\u0109e"
    ],
    "name:eus_x_preferred":[
        "Malintxe"
    ],
    "name:fin_x_preferred":[
        "La Malinche"
    ],
    "name:fra_x_preferred":[
        "La Malinche"
    ],
    "name:glg_x_preferred":[
        "Malinche"
    ],
    "name:heb_x_preferred":[
        "\u05de\u05dc\u05d9\u05e0\u05e6'\u05d4"
    ],
    "name:ind_x_preferred":[
        "La Malinche"
    ],
    "name:ita_x_preferred":[
        "La Malinche"
    ],
    "name:jpn_x_preferred":[
        "\u30de\u30ea\u30f3\u30c1\u30a7"
    ],
    "name:kor_x_preferred":[
        "\ub77c \ub9d0\ub9b0\uccb4"
    ],
    "name:lit_x_preferred":[
        "La Malinche"
    ],
    "name:mal_x_preferred":[
        "\u0d32\u0d3e \u0d2e\u0d32\u0d3f\u0d1e\u0d4d\u0d1a\u0d46"
    ],
    "name:mkd_x_preferred":[
        "\u041c\u0430\u043b\u0438\u043d\u0447\u0435"
    ],
    "name:msa_x_preferred":[
        "La Malinche"
    ],
    "name:nld_x_preferred":[
        "La Malinche"
    ],
    "name:nor_x_preferred":[
        "Malinche"
    ],
    "name:pol_x_preferred":[
        "Malintzin"
    ],
    "name:por_x_preferred":[
        "Malinche"
    ],
    "name:rus_x_preferred":[
        "\u041c\u0430\u043b\u0438\u043d\u0447\u0435"
    ],
    "name:slk_x_preferred":[
        "La Malinche"
    ],
    "name:slv_x_preferred":[
        "La Malinche"
    ],
    "name:spa_x_preferred":[
        "La Malinche"
    ],
    "name:srp_x_preferred":[
        "\u041c\u0430\u043b\u0438\u043d\u0447\u0435"
    ],
    "name:swe_x_preferred":[
        "La Malinche"
    ],
    "name:tha_x_preferred":[
        "\u0e25\u0e32\u0e21\u0e32\u0e25\u0e34\u0e19\u0e40\u0e0a"
    ],
    "name:tur_x_preferred":[
        "La Malinche"
    ],
    "name:ukr_x_preferred":[
        "\u041c\u0430\u043b\u0456\u043d\u0447\u0435"
    ],
    "name:zho_x_preferred":[
        "\u99ac\u6797\u5207"
    ],
    "wof:name":"La Malinche",
    "wof:placetype":"locality",
    "wof:population":6
},
  "geometry": {"coordinates":[-94.87721999999999,17.90222],"type":"Point"}
}