{
  "type": "Feature",
  "properties": {
    "gn:admin1_code":"13",
    "gn:admin2_code":"44.0",
    "gn:asciiname":"La Salita",
    "gn:country_code":"MX",
    "gn:dem":2363,
    "gn:feature_class":"P",
    "gn:feature_code":"PPL",
    "gn:name":"La Salita",
    "gn:population":165,
    "gn:timezone":"America/Mexico_City",
    "iso:country":"MX",
    "wof:name":"La Salita",
    "wof:placetype":"locality",
    "wof:population":165
},
  "geometry": {"coordinates":[-99.64749999999999,20.235],"type":"Point"}
}