{
  "type": "Feature",
  "properties": {
    "gn:admin1_code":"30.0",
    "gn:asciiname":"El Suchil Dos",
    "gn:country_code":"MX",
    "gn:dem":8,
    "gn:feature_class":"P",
    "gn:feature_code":"PPL",
    "gn:name":"El S\u00fachil Dos",
    "gn:population":0,
    "gn:timezone":"America/Mexico_City",
    "iso:country":"MX",
    "name:spa_x_preferred":[
        "El S\u00fachil Dos"
    ],
    "wof:name":"El Suchil Dos",
    "wof:placetype":"locality"
},
  "geometry": {"coordinates":[-95.65087,18.49829],"type":"Point"}
}