{
  "type": "Feature",
  "properties": {
    "gn:admin1_code":"19",
    "gn:admin2_code":"22.0",
    "gn:asciiname":"Guadalupe de las Estacas",
    "gn:country_code":"MX",
    "gn:dem":298,
    "gn:feature_class":"P",
    "gn:feature_code":"PPL",
    "gn:name":"Guadalupe de las Estacas",
    "gn:population":0,
    "gn:timezone":"America/Monterrey",
    "iso:country":"MX",
    "name:spa_x_preferred":[
        "Guadalupe de las Estacas"
    ],
    "name:und_x_variant":[
        "Guadalupe"
    ],
    "wof:name":"Guadalupe de las Estacas",
    "wof:placetype":"locality"
},
  "geometry": {"coordinates":[-99.556,25.17226],"type":"Point"}
}