{
  "type": "Feature",
  "properties": {
    "gn:admin1_code":"6",
    "gn:admin2_code":"38.0",
    "gn:asciiname":"Monte Seco",
    "gn:country_code":"MX",
    "gn:dem":1078,
    "gn:feature_class":"P",
    "gn:feature_code":"PPL",
    "gn:name":"Monte Seco",
    "gn:population":0,
    "gn:timezone":"America/Chihuahua",
    "iso:country":"MX",
    "name:und_x_variant":[
        "Rancho Monteseco",
        "Monteseco",
        "Monte Seco"
    ],
    "wof:name":"Monte Seco",
    "wof:placetype":"locality"
},
  "geometry": {"coordinates":[-105.39955,28.61579],"type":"Point"}
}