{
  "type": "Feature",
  "properties": {
    "gn:admin1_code":"11",
    "gn:admin2_code":"31.0",
    "gn:asciiname":"Fraccionamiento Villa Jardin",
    "gn:country_code":"MX",
    "gn:dem":1750,
    "gn:feature_class":"P",
    "gn:feature_code":"PPL",
    "gn:name":"Fraccionamiento Villa Jard\u00edn",
    "gn:population":1330,
    "gn:timezone":"America/Mexico_City",
    "iso:country":"MX",
    "name:und_x_variant":[
        "Fraccionamiento Villa Jard\u00edn"
    ],
    "wof:name":"Fraccionamiento Villa Jardin",
    "wof:placetype":"locality",
    "wof:population":1330
},
  "geometry": {"coordinates":[-101.85194,20.99167000000001],"type":"Point"}
}