{
  "type": "Feature",
  "properties": {
    "gn:admin1_code":"12",
    "gn:admin2_code":"81.0",
    "gn:asciiname":"Colonia Loma Encino (Iliatenco)",
    "gn:country_code":"MX",
    "gn:dem":1114,
    "gn:feature_class":"P",
    "gn:feature_code":"PPL",
    "gn:name":"Colonia Loma Encino (Iliatenco)",
    "gn:population":93,
    "gn:timezone":"America/Mexico_City",
    "iso:country":"MX",
    "wof:name":"Colonia Loma Encino (Iliatenco)",
    "wof:placetype":"locality",
    "wof:population":93
},
  "geometry": {"coordinates":[-98.66416,17.02917],"type":"Point"}
}