{
  "type": "Feature",
  "properties": {
    "gn:admin1_code":"15.0",
    "gn:asciiname":"Kilometro Dos Punto Cinco",
    "gn:country_code":"MX",
    "gn:dem":2266,
    "gn:feature_class":"P",
    "gn:feature_code":"PPL",
    "gn:name":"Kil\u00f3metro Dos Punto Cinco",
    "gn:population":0,
    "gn:timezone":"America/Mexico_City",
    "iso:country":"MX",
    "name:spa_x_preferred":[
        "Kil\u00f3metro Dos Punto Cinco"
    ],
    "wof:name":"Kilometro Dos Punto Cinco",
    "wof:placetype":"locality"
},
  "geometry": {"coordinates":[-98.86669999999999,19.22108],"type":"Point"}
}