{
  "type": "Feature",
  "properties": {
    "gn:admin1_code":"10",
    "gn:admin2_code":"35.0",
    "gn:asciiname":"Toro Quemado",
    "gn:country_code":"MX",
    "gn:dem":2577,
    "gn:feature_class":"P",
    "gn:feature_code":"PPL",
    "gn:name":"Toro Quemado",
    "gn:population":0,
    "gn:timezone":"America/Monterrey",
    "iso:country":"MX",
    "name:und_x_variant":[
        "Torquemado",
        "Toro Quemado"
    ],
    "wof:name":"Toro Quemado",
    "wof:placetype":"locality"
},
  "geometry": {"coordinates":[-106.17528,25.74407],"type":"Point"}
}