{
  "type": "Feature",
  "properties": {
    "gn:admin1_code":"5",
    "gn:admin2_code":"85.0",
    "gn:asciiname":"Nuevo Poblado Guadalupe",
    "gn:country_code":"MX",
    "gn:dem":1198,
    "gn:feature_class":"P",
    "gn:feature_code":"PPL",
    "gn:name":"Nuevo Poblado Guadalupe",
    "gn:population":56,
    "gn:timezone":"America/Mexico_City",
    "iso:country":"MX",
    "wof:name":"Nuevo Poblado Guadalupe",
    "wof:placetype":"locality",
    "wof:population":56
},
  "geometry": {"coordinates":[-92.92806,16.88278],"type":"Point"}
}