{
  "type": "Feature",
  "properties": {
    "gn:admin1_code":"15",
    "gn:admin2_code":"82.0",
    "gn:asciiname":"Limon de San Lucas del Maiz",
    "gn:country_code":"MX",
    "gn:dem":1205,
    "gn:feature_class":"P",
    "gn:feature_code":"PPL",
    "gn:name":"Lim\u00f3n de San Lucas del Ma\u00edz",
    "gn:population":492,
    "gn:timezone":"America/Mexico_City",
    "iso:country":"MX",
    "name:und_x_variant":[
        "Lim\u00f3n de San Lucas del Ma\u00edz"
    ],
    "wof:name":"Limon de San Lucas del Maiz",
    "wof:placetype":"locality",
    "wof:population":492
},
  "geometry": {"coordinates":[-100.24625,18.98355],"type":"Point"}
}