{
  "type": "Feature",
  "properties": {
    "gn:admin1_code":"15",
    "gn:admin2_code":"59.0",
    "gn:asciiname":"Tierra de Santa Ines",
    "gn:country_code":"MX",
    "gn:dem":2246,
    "gn:feature_class":"P",
    "gn:feature_code":"PPL",
    "gn:name":"Tierra de Santa In\u00e9s",
    "gn:population":70,
    "gn:timezone":"America/Mexico_City",
    "iso:country":"MX",
    "name:und_x_variant":[
        "Tierra de Santa In\u00e9s"
    ],
    "wof:name":"Tierra de Santa Ines",
    "wof:placetype":"locality",
    "wof:population":70
},
  "geometry": {"coordinates":[-99.07666,19.69592],"type":"Point"}
}