{
  "type": "Feature",
  "properties": {
    "gn:admin1_code":"10",
    "gn:admin2_code":"23.0",
    "gn:asciiname":"Guasima",
    "gn:country_code":"MX",
    "gn:dem":693,
    "gn:feature_class":"P",
    "gn:feature_code":"PPL",
    "gn:name":"Gu\u00e1sima",
    "gn:population":0,
    "gn:timezone":"America/Mazatlan",
    "iso:country":"MX",
    "name:spa_x_preferred":[
        "Gu\u00e1sima"
    ],
    "wof:name":"Guasima",
    "wof:placetype":"locality"
},
  "geometry": {"coordinates":[-105.34187,23.0205],"type":"Point"}
}