{
  "type": "Feature",
  "properties": {
    "gn:admin1_code":"30.0",
    "gn:admin2_code":"35.0",
    "gn:asciiname":"Mixcaltepec",
    "gn:country_code":"MX",
    "gn:dem":308,
    "gn:feature_class":"P",
    "gn:feature_code":"PPL",
    "gn:name":"Mixcaltepec",
    "gn:population":49,
    "gn:timezone":"America/Mexico_City",
    "iso:country":"MX",
    "name:spa_x_preferred":[
        "Mixcaltepec"
    ],
    "wof:name":"Mixcaltepec",
    "wof:placetype":"locality",
    "wof:population":49
},
  "geometry": {"coordinates":[-97.85972,21.32056],"type":"Point"}
}