{
  "type": "Feature",
  "properties": {
    "gn:admin1_code":"14.0",
    "gn:admin2_code":"49.0",
    "gn:asciiname":"Paso del Sombrero",
    "gn:country_code":"MX",
    "gn:dem":512,
    "gn:feature_class":"P",
    "gn:feature_code":"PPL",
    "gn:name":"Paso del Sombrero",
    "gn:population":0,
    "gn:timezone":"America/Mexico_City",
    "iso:country":"MX",
    "name:spa_x_preferred":[
        "Paso del Sombrero"
    ],
    "wof:name":"Paso del Sombrero",
    "wof:placetype":"locality"
},
  "geometry": {"coordinates":[-102.89270999999999,19.37638],"type":"Point"}
}