{
  "type": "Feature",
  "properties": {
    "gn:admin1_code":"25",
    "gn:admin2_code":"17",
    "gn:asciiname":"Bomba del Alacran",
    "gn:country_code":"MX",
    "gn:dem":30,
    "gn:feature_class":"P",
    "gn:feature_code":"PPL",
    "gn:name":"Bomba del Alacr\u00e1n",
    "gn:population":10,
    "gn:timezone":"America/Mazatlan",
    "iso:country":"MX",
    "name:und_x_variant":[
        "Bomba del Alacr\u00e1n"
    ],
    "wof:name":"Bomba del Alacran",
    "wof:placetype":"locality",
    "wof:population":10
},
  "geometry": {"coordinates":[-108.68210999999999,25.78665],"type":"Point"}
}