{
  "type": "Feature",
  "properties": {
    "gn:admin1_code":"27.0",
    "gn:admin2_code":"7.0",
    "gn:asciiname":"El Maranon",
    "gn:country_code":"MX",
    "gn:dem":65,
    "gn:feature_class":"P",
    "gn:feature_code":"PPL",
    "gn:name":"El Mara\u00f1\u00f3n",
    "gn:population":0,
    "gn:timezone":"America/Mexico_City",
    "iso:country":"MX",
    "name:spa_x_preferred":[
        "El Mara\u00f1\u00f3n"
    ],
    "wof:name":"El Maranon",
    "wof:placetype":"locality"
},
  "geometry": {"coordinates":[-91.61125,17.56897],"type":"Point"}
}