{
  "type": "Feature",
  "properties": {
    "gn:admin1_code":"15.0",
    "gn:asciiname":"La Silla",
    "gn:country_code":"MX",
    "gn:dem":2487,
    "gn:feature_class":"P",
    "gn:feature_code":"PPL",
    "gn:name":"La Silla",
    "gn:population":0,
    "gn:timezone":"America/Mexico_City",
    "iso:country":"MX",
    "name:spa_x_preferred":[
        "La Silla"
    ],
    "wof:name":"La Silla",
    "wof:placetype":"locality"
},
  "geometry": {"coordinates":[-100.32105,20.19057],"type":"Point"}
}