{
  "type": "Feature",
  "properties": {
    "gn:admin1_code":"14",
    "gn:admin2_code":"8.0",
    "gn:asciiname":"San Jeronimo (La Polvora)",
    "gn:country_code":"MX",
    "gn:dem":2176,
    "gn:feature_class":"P",
    "gn:feature_code":"PPL",
    "gn:name":"San Jer\u00f3nimo (La P\u00f3lvora)",
    "gn:population":6,
    "gn:timezone":"America/Mexico_City",
    "iso:country":"MX",
    "name:und_x_variant":[
        "San Jer\u00f3nimo (La P\u00f3lvora)"
    ],
    "wof:name":"San Jeronimo (La Polvora)",
    "wof:placetype":"locality",
    "wof:population":6
},
  "geometry": {"coordinates":[-102.26222,20.70389],"type":"Point"}
}