{
  "type": "Feature",
  "properties": {
    "gn:admin1_code":"10.0",
    "gn:admin2_code":"32.0",
    "gn:asciiname":"Boca del Arroyo del Huizache",
    "gn:country_code":"MX",
    "gn:dem":1826,
    "gn:feature_class":"P",
    "gn:feature_code":"PPL",
    "gn:name":"Boca del Arroyo del Huizache",
    "gn:population":0,
    "gn:timezone":"America/Monterrey",
    "iso:country":"MX",
    "name:spa_x_preferred":[
        "Boca del Arroyo del Huizache"
    ],
    "wof:name":"Boca del Arroyo del Huizache",
    "wof:placetype":"locality"
},
  "geometry": {"coordinates":[-105.35902,24.96179],"type":"Point"}
}