{
  "type": "Feature",
  "properties": {
    "gn:admin1_code":"20",
    "gn:admin2_code":"446",
    "gn:asciiname":"Llano San Miguel",
    "gn:country_code":"MX",
    "gn:dem":1815,
    "gn:feature_class":"P",
    "gn:feature_code":"PPL",
    "gn:name":"Llano San Miguel",
    "gn:population":52,
    "gn:timezone":"America/Mexico_City",
    "iso:country":"MX",
    "wof:name":"Llano San Miguel",
    "wof:placetype":"locality",
    "wof:population":52
},
  "geometry": {"coordinates":[-97.80194,17.02722],"type":"Point"}
}