{
  "type": "Feature",
  "properties": {
    "gn:admin1_code":"25",
    "gn:admin2_code":"10.0",
    "gn:asciiname":"Campo Virgen de Guadalupe",
    "gn:country_code":"MX",
    "gn:dem":23,
    "gn:feature_class":"P",
    "gn:feature_code":"PPL",
    "gn:name":"Campo Virgen de Guadalupe",
    "gn:population":0,
    "gn:timezone":"America/Mazatlan",
    "iso:country":"MX",
    "name:spa_x_preferred":[
        "Osuna"
    ],
    "name:spa_x_variant":[
        "Campo Virgen de Guadalupe"
    ],
    "wof:name":"Campo Virgen de Guadalupe",
    "wof:placetype":"locality"
},
  "geometry": {"coordinates":[-108.96635000000001,26.12986],"type":"Point"}
}