{
  "type": "Feature",
  "properties": {
    "gn:admin1_code":"10.0",
    "gn:admin2_code":"23.0",
    "gn:asciiname":"El Tapextle",
    "gn:country_code":"MX",
    "gn:dem":2487,
    "gn:feature_class":"P",
    "gn:feature_code":"PPL",
    "gn:name":"El Tapextle",
    "gn:population":201,
    "gn:timezone":"America/Monterrey",
    "iso:country":"MX",
    "name:und_x_variant":[
        "Tapextle",
        "El Tapextle"
    ],
    "wof:name":"El Tapextle",
    "wof:placetype":"locality",
    "wof:population":201
},
  "geometry": {"coordinates":[-105.5513,23.87097],"type":"Point"}
}