{
  "type": "Feature",
  "properties": {
    "gn:admin1_code":"10.0",
    "gn:admin2_code":"23.0",
    "gn:asciiname":"Las Pitacas",
    "gn:country_code":"MX",
    "gn:dem":2072,
    "gn:feature_class":"P",
    "gn:feature_code":"PPL",
    "gn:name":"Las Pitacas",
    "gn:population":0,
    "gn:timezone":"America/Monterrey",
    "iso:country":"MX",
    "name:spa_x_preferred":[
        "Las Pitacas"
    ],
    "wof:name":"Las Pitacas",
    "wof:placetype":"locality"
},
  "geometry": {"coordinates":[-104.82106,23.19236],"type":"Point"}
}