{
  "type": "Feature",
  "properties": {
    "gn:admin1_code":"21",
    "gn:admin2_code":"213.0",
    "gn:asciiname":"Tecpatlan",
    "gn:country_code":"MX",
    "gn:dem":536,
    "gn:feature_class":"P",
    "gn:feature_code":"PPL",
    "gn:name":"Tecpatl\u00e1n",
    "gn:population":591,
    "gn:timezone":"America/Mexico_City",
    "iso:country":"MX",
    "name:und_x_variant":[
        "Tecpatl\u00e1n"
    ],
    "wof:name":"Tecpatlan",
    "wof:placetype":"locality",
    "wof:population":591
},
  "geometry": {"coordinates":[-97.86750000000001,20.23944],"type":"Point"}
}