{
  "type": "Feature",
  "properties": {
    "gn:admin1_code":"30",
    "gn:admin2_code":"144.0",
    "gn:asciiname":"Correa",
    "gn:cc2":"MX",
    "gn:country_code":"MX",
    "gn:dem":77,
    "gn:feature_class":"P",
    "gn:feature_code":"PPL",
    "gn:name":"Correa",
    "gn:population":0,
    "gn:timezone":"America/Mexico_City",
    "iso:country":"MX",
    "name:und_x_variant":[
        "Correo",
        "Correa"
    ],
    "wof:name":"Correa",
    "wof:placetype":"locality"
},
  "geometry": {"coordinates":[-94.95,17.85],"type":"Point"}
}