{
  "type": "Feature",
  "properties": {
    "gn:admin1_code":"24.0",
    "gn:admin2_code":"40.0",
    "gn:asciiname":"Esparsa",
    "gn:country_code":"MX",
    "gn:dem":36,
    "gn:feature_class":"P",
    "gn:feature_code":"PPL",
    "gn:name":"Esparsa",
    "gn:population":0,
    "gn:timezone":"America/Mexico_City",
    "iso:country":"MX",
    "name:spa_x_preferred":[
        "Esparsa"
    ],
    "wof:name":"Esparsa",
    "wof:placetype":"locality"
},
  "geometry": {"coordinates":[-98.85404,22.03383],"type":"Point"}
}