{
  "type": "Feature",
  "properties": {
    "gn:admin1_code":"7",
    "gn:admin2_code":"20.0",
    "gn:asciiname":"Nacimiento de Kikapoo",
    "gn:cc2":"MX",
    "gn:country_code":"MX",
    "gn:dem":491,
    "gn:feature_class":"P",
    "gn:feature_code":"PPL",
    "gn:name":"Nacimiento de Kikapoo",
    "gn:population":0,
    "gn:timezone":"America/Monterrey",
    "iso:country":"MX",
    "name:und_x_variant":[
        "Nacimiento",
        "Nacimiento de Kikapoo"
    ],
    "wof:name":"Nacimiento de Kikapoo",
    "wof:placetype":"locality"
},
  "geometry": {"coordinates":[-101.65000000000001,28.06667],"type":"Point"}
}