{
  "type": "Feature",
  "properties": {
    "gn:admin1_code":"31",
    "gn:admin2_code":"53.0",
    "gn:asciiname":"Kankirixche",
    "gn:country_code":"MX",
    "gn:dem":14,
    "gn:feature_class":"P",
    "gn:feature_code":"PPL",
    "gn:name":"Kankirixche",
    "gn:population":0,
    "gn:timezone":"America/Merida",
    "iso:country":"MX",
    "name:spa_x_preferred":[
        "Kankirixche"
    ],
    "wof:name":"Kankirixche",
    "wof:placetype":"locality"
},
  "geometry": {"coordinates":[-89.74202,20.58217],"type":"Point"}
}