{
  "type": "Feature",
  "properties": {
    "iso:country":"MX",
    "name:spa_x_preferred":[
        "Colinas Serenidad"
    ],
    "qs:gn_adm0_cc":"MX",
    "qs:gn_local":4006702,
    "qs:local_max":1515,
    "qs:local_sum":2552,
    "qs:localhoods":10,
    "qs:name":"Colinas Serenidad",
    "qs:name_adm0":"M\u00e9xico",
    "qs:name_adm1":"Baja California",
    "qs:name_adm2":"Ensenada",
    "qs:name_local":"Ensenada",
    "qs:photo_max":1,
    "qs:photo_sum":1,
    "qs:placetype":"Suburb",
    "qs:quad_count":1,
    "qs:woe_adm0":23424900,
    "qs:woe_adm1":2346265,
    "qs:woe_adm2":12599691,
    "qs:woe_lau":0,
    "qs:woe_local":123253,
    "qs:woe_ver":"7.10.0",
    "wof:lang":[
        "spa"
    ],
    "wof:name":"Colinas Serenidad",
    "wof:placetype":"neighbourhood"
},
  "geometry": {"coordinates":[-116.67755099999999,31.87989],"type":"Point"}
}