{
  "type": "Feature",
  "properties": {
    "gn:admin1_code":"25",
    "gn:admin2_code":"15.0",
    "gn:asciiname":"Buenaventura",
    "gn:country_code":"MX",
    "gn:dem":23,
    "gn:feature_class":"P",
    "gn:feature_code":"PPL",
    "gn:name":"Buenaventura",
    "gn:population":0,
    "gn:timezone":"America/Mazatlan",
    "iso:country":"MX",
    "name:spa_x_preferred":[
        "Buenaventura"
    ],
    "name:und_x_variant":[
        "San Buenaventura"
    ],
    "wof:name":"Buenaventura",
    "wof:placetype":"locality"
},
  "geometry": {"coordinates":[-108.21639999999999,25.39177],"type":"Point"}
}