{
  "type": "Feature",
  "properties": {
    "gn:admin1_code":"19",
    "gn:admin2_code":"38.0",
    "gn:asciiname":"Mohinos",
    "gn:country_code":"MX",
    "gn:dem":383,
    "gn:feature_class":"P",
    "gn:feature_code":"PPL",
    "gn:name":"Mohinos",
    "gn:population":0,
    "gn:timezone":"America/Monterrey",
    "iso:country":"MX",
    "name:spa_x_preferred":[
        "Mohinos"
    ],
    "wof:name":"Mohinos",
    "wof:placetype":"locality"
},
  "geometry": {"coordinates":[-99.67167000000001,25.04444],"type":"Point"}
}