{
  "type": "Feature",
  "properties": {
    "gn:admin1_code":"20",
    "gn:admin2_code":"2.0",
    "gn:asciiname":"Los Mangos",
    "gn:country_code":"MX",
    "gn:dem":133,
    "gn:feature_class":"P",
    "gn:feature_code":"PPL",
    "gn:name":"Los Mangos",
    "gn:population":0,
    "gn:timezone":"America/Mexico_City",
    "iso:country":"MX",
    "name:spa_x_preferred":[
        "Los Mangos"
    ],
    "wof:name":"Los Mangos",
    "wof:placetype":"locality"
},
  "geometry": {"coordinates":[-96.51056,18.58061],"type":"Point"}
}