{
  "type": "Feature",
  "properties": {
    "gn:admin1_code":"28",
    "gn:admin2_code":"25.0",
    "gn:asciiname":"Los Altitos",
    "gn:country_code":"MX",
    "gn:dem":104,
    "gn:feature_class":"P",
    "gn:feature_code":"PPL",
    "gn:name":"Los Altitos",
    "gn:population":0,
    "gn:timezone":"America/Monterrey",
    "iso:country":"MX",
    "name:spa_x_preferred":[
        "Los Altitos"
    ],
    "name:und_x_variant":[
        "Rancho Los Altitos"
    ],
    "wof:name":"Los Altitos",
    "wof:placetype":"locality"
},
  "geometry": {"coordinates":[-99.15324,26.07587],"type":"Point"}
}