{
  "type": "Feature",
  "properties": {
    "gn:admin1_code":"28",
    "gn:admin2_code":"22.0",
    "gn:asciiname":"El Sabinito",
    "gn:country_code":"MX",
    "gn:dem":15,
    "gn:feature_class":"P",
    "gn:feature_code":"PPL",
    "gn:name":"El Sabinito",
    "gn:population":82,
    "gn:timezone":"America/Matamoros",
    "iso:country":"MX",
    "wof:name":"El Sabinito",
    "wof:placetype":"locality",
    "wof:population":82
},
  "geometry": {"coordinates":[-97.59611,25.94944],"type":"Point"}
}