{
  "type": "Feature",
  "properties": {
    "gn:admin1_code":"30.0",
    "gn:admin2_code":"160.0",
    "gn:asciiname":"Milcahuales",
    "gn:country_code":"MX",
    "gn:dem":88,
    "gn:feature_class":"P",
    "gn:feature_code":"PPL",
    "gn:name":"Milcahuales",
    "gn:population":307,
    "gn:timezone":"America/Mexico_City",
    "iso:country":"MX",
    "name:spa_x_preferred":[
        "Milcahuales"
    ],
    "name:spa_x_variant":[
        "La Flore\u00f1a"
    ],
    "wof:name":"Milcahuales",
    "wof:placetype":"locality",
    "wof:population":307
},
  "geometry": {"coordinates":[-97.69944,21.15444],"type":"Point"}
}