{
  "type": "Feature",
  "properties": {
    "gn:admin1_code":"16",
    "gn:admin2_code":"9.0",
    "gn:asciiname":"Plan del Chivo",
    "gn:country_code":"MX",
    "gn:dem":1835,
    "gn:feature_class":"P",
    "gn:feature_code":"PPL",
    "gn:name":"Plan del Chivo",
    "gn:population":0,
    "gn:timezone":"America/Mexico_City",
    "iso:country":"MX",
    "name:spa_x_preferred":[
        "Plan del Chivo"
    ],
    "wof:name":"Plan del Chivo",
    "wof:placetype":"locality"
},
  "geometry": {"coordinates":[-101.64851,18.98992],"type":"Point"}
}