{
  "type": "Feature",
  "properties": {
    "gn:admin1_code":"10",
    "gn:admin2_code":"14.0",
    "gn:asciiname":"Chalotes",
    "gn:country_code":"MX",
    "gn:dem":1534,
    "gn:feature_class":"P",
    "gn:feature_code":"PPL",
    "gn:name":"Chalotes",
    "gn:population":0,
    "gn:timezone":"America/Monterrey",
    "iso:country":"MX",
    "name:spa_x_preferred":[
        "Chalotes"
    ],
    "wof:name":"Chalotes",
    "wof:placetype":"locality"
},
  "geometry": {"coordinates":[-104.66937,22.78054],"type":"Point"}
}