{
  "type": "Feature",
  "properties": {
    "gn:admin1_code":"14",
    "gn:admin2_code":"9",
    "gn:asciiname":"La Mision (Los Pitufos)",
    "gn:country_code":"MX",
    "gn:dem":1487,
    "gn:feature_class":"P",
    "gn:feature_code":"PPL",
    "gn:name":"La Misi\u00f3n (Los Pitufos)",
    "gn:population":12,
    "gn:timezone":"America/Mexico_City",
    "iso:country":"MX",
    "name:und_x_variant":[
        "La Misi\u00f3n (Los Pitufos)"
    ],
    "wof:name":"La Mision (Los Pitufos)",
    "wof:placetype":"locality",
    "wof:population":12
},
  "geometry": {"coordinates":[-103.63333,20.70861],"type":"Point"}
}