{
  "type": "Feature",
  "properties": {
    "gn:admin1_code":"28.0",
    "gn:admin2_code":"35.0",
    "gn:asciiname":"La Enramada",
    "gn:country_code":"MX",
    "gn:dem":106,
    "gn:feature_class":"P",
    "gn:feature_code":"PPL",
    "gn:name":"La Enramada",
    "gn:population":0,
    "gn:timezone":"America/Monterrey",
    "iso:country":"MX",
    "name:spa_x_preferred":[
        "La Enramada"
    ],
    "wof:name":"La Enramada",
    "wof:placetype":"locality"
},
  "geometry": {"coordinates":[-98.1735,24.97889],"type":"Point"}
}