{
  "type": "Feature",
  "properties": {
    "gn:admin1_code":"28",
    "gn:admin2_code":"5.0",
    "gn:asciiname":"El Zurdo",
    "gn:country_code":"MX",
    "gn:dem":135,
    "gn:feature_class":"P",
    "gn:feature_code":"PPL",
    "gn:name":"El Zurdo",
    "gn:population":5,
    "gn:timezone":"America/Monterrey",
    "iso:country":"MX",
    "wof:name":"El Zurdo",
    "wof:placetype":"locality",
    "wof:population":5
},
  "geometry": {"coordinates":[-98.48417000000001,24.88139],"type":"Point"}
}