{
  "type": "Feature",
  "properties": {
    "gn:admin1_code":"12",
    "gn:admin2_code":"15",
    "gn:asciiname":"La Fundicion",
    "gn:country_code":"MX",
    "gn:dem":1334,
    "gn:feature_class":"P",
    "gn:feature_code":"PPL",
    "gn:name":"La Fundici\u00f3n",
    "gn:population":13,
    "gn:timezone":"America/Mexico_City",
    "iso:country":"MX",
    "name:und_x_variant":[
        "La Fundici\u00f3n"
    ],
    "wof:name":"La Fundicion",
    "wof:placetype":"locality",
    "wof:population":13
},
  "geometry": {"coordinates":[-99.41324,18.44858],"type":"Point"}
}