{
  "type": "Feature",
  "properties": {
    "gn:admin1_code":"16",
    "gn:admin2_code":"85.0",
    "gn:asciiname":"Colonia Junguaran",
    "gn:country_code":"MX",
    "gn:dem":1721,
    "gn:feature_class":"P",
    "gn:feature_code":"PPL",
    "gn:name":"Colonia Junguar\u00e1n",
    "gn:population":58,
    "gn:timezone":"America/Mexico_City",
    "iso:country":"MX",
    "name:und_x_variant":[
        "Colonia Junguar\u00e1n"
    ],
    "wof:name":"Colonia Junguaran",
    "wof:placetype":"locality",
    "wof:population":58
},
  "geometry": {"coordinates":[-102.22,19.87972],"type":"Point"}
}