{
  "type": "Feature",
  "properties": {
    "gn:admin1_code":"6",
    "gn:admin2_code":"20.0",
    "gn:asciiname":"Sahuipaco",
    "gn:country_code":"MX",
    "gn:dem":628,
    "gn:feature_class":"P",
    "gn:feature_code":"PPL",
    "gn:name":"Sahuipaco",
    "gn:population":0,
    "gn:timezone":"America/Chihuahua",
    "iso:country":"MX",
    "name:spa_x_preferred":[
        "Sahuipaco"
    ],
    "wof:name":"Sahuipaco",
    "wof:placetype":"locality"
},
  "geometry": {"coordinates":[-108.51846,27.05195],"type":"Point"}
}