{
  "type": "Feature",
  "properties": {
    "gn:admin1_code":"5",
    "gn:admin2_code":"82.0",
    "gn:asciiname":"Sibaca",
    "gn:country_code":"MX",
    "gn:dem":1078,
    "gn:feature_class":"P",
    "gn:feature_code":"PPL",
    "gn:name":"Sibaca",
    "gn:population":0,
    "gn:timezone":"America/Mexico_City",
    "iso:country":"MX",
    "wof:name":"Sibaca",
    "wof:placetype":"locality"
},
  "geometry": {"coordinates":[-92.31667,17.06667],"type":"Point"}
}