{
  "type": "Feature",
  "properties": {
    "gn:admin1_code":"21",
    "gn:admin2_code":"114.0",
    "gn:asciiname":"Tecolotzi",
    "gn:country_code":"MX",
    "gn:dem":2438,
    "gn:feature_class":"P",
    "gn:feature_code":"PPL",
    "gn:name":"Tecolotzi",
    "gn:population":98,
    "gn:timezone":"America/Mexico_City",
    "iso:country":"MX",
    "wof:name":"Tecolotzi",
    "wof:placetype":"locality",
    "wof:population":98
},
  "geometry": {"coordinates":[-98.12302,19.12902],"type":"Point"}
}