{
  "type": "Feature",
  "properties": {
    "gn:admin1_code":"5.0",
    "gn:admin2_code":"71.0",
    "gn:asciiname":"Canton el Escobo",
    "gn:country_code":"MX",
    "gn:dem":17,
    "gn:feature_class":"P",
    "gn:feature_code":"PPL",
    "gn:name":"Cant\u00f3n el Escobo",
    "gn:population":0,
    "gn:timezone":"America/Mexico_City",
    "iso:country":"MX",
    "name:spa_x_preferred":[
        "Cant\u00f3n el Escobo"
    ],
    "wof:name":"Canton el Escobo",
    "wof:placetype":"locality"
},
  "geometry": {"coordinates":[-92.65746,15.14633],"type":"Point"}
}