{
  "type": "Feature",
  "properties": {
    "gn:admin1_code":"26.0",
    "gn:admin2_code":"65.0",
    "gn:asciiname":"El Tepeyac",
    "gn:country_code":"MX",
    "gn:dem":732,
    "gn:feature_class":"P",
    "gn:feature_code":"PPL",
    "gn:name":"El Tepeyac",
    "gn:population":0,
    "gn:timezone":"America/Hermosillo",
    "iso:country":"MX",
    "wof:name":"El Tepeyac",
    "wof:placetype":"locality"
},
  "geometry": {"coordinates":[-111.31609,30.80107000000001],"type":"Point"}
}