{
  "type": "Feature",
  "properties": {
    "gn:admin1_code":"31",
    "gn:admin2_code":"87.0",
    "gn:asciiname":"Pixoy",
    "gn:country_code":"MX",
    "gn:dem":8,
    "gn:feature_class":"P",
    "gn:feature_code":"PPL",
    "gn:name":"Pixoy",
    "gn:population":0,
    "gn:timezone":"America/Merida",
    "iso:country":"MX",
    "name:spa_x_preferred":[
        "Pixoy"
    ],
    "wof:name":"Pixoy",
    "wof:placetype":"locality"
},
  "geometry": {"coordinates":[-90.05248,20.98029],"type":"Point"}
}