{
  "type": "Feature",
  "properties": {
    "gn:admin1_code":"10.0",
    "gn:admin2_code":"9.0",
    "gn:asciiname":"Cuatro Milpas",
    "gn:country_code":"MX",
    "gn:dem":1994,
    "gn:feature_class":"P",
    "gn:feature_code":"PPL",
    "gn:name":"Cuatro Milpas",
    "gn:population":0,
    "gn:timezone":"America/Monterrey",
    "iso:country":"MX",
    "name:und_x_variant":[
        "Rancho Cuatro Milpas",
        "Cuatro Milpas"
    ],
    "wof:name":"Cuatro Milpas",
    "wof:placetype":"locality"
},
  "geometry": {"coordinates":[-105.78983999999998,25.70742000000001],"type":"Point"}
}