{
  "type": "Feature",
  "properties": {
    "gn:admin1_code":"11",
    "gn:admin2_code":"23.0",
    "gn:asciiname":"El CERESO",
    "gn:country_code":"MX",
    "gn:dem":1775,
    "gn:feature_class":"P",
    "gn:feature_code":"PPL",
    "gn:name":"El CERESO",
    "gn:population":240,
    "gn:timezone":"America/Mexico_City",
    "iso:country":"MX",
    "wof:name":"El CERESO",
    "wof:placetype":"locality",
    "wof:population":240
},
  "geometry": {"coordinates":[-101.70111,20.44889],"type":"Point"}
}