{
  "type": "Feature",
  "properties": {
    "gn:admin1_code":"20",
    "gn:admin2_code":"515.0",
    "gn:asciiname":"Sin Pensar",
    "gn:cc2":"MX",
    "gn:country_code":"MX",
    "gn:dem":264,
    "gn:feature_class":"P",
    "gn:feature_code":"PPL",
    "gn:name":"Sin Pensar",
    "gn:population":0,
    "gn:timezone":"America/Mexico_City",
    "iso:country":"MX",
    "name:und_x_variant":[
        "Simpensar",
        "Sin Pensar"
    ],
    "wof:name":"Sin Pensar",
    "wof:placetype":"locality"
},
  "geometry": {"coordinates":[-95.46666999999999,16.06667],"type":"Point"}
}