{
  "type": "Feature",
  "properties": {
    "gn:admin1_code":"13",
    "gn:admin2_code":"17.0",
    "gn:asciiname":"La Comayhe",
    "gn:country_code":"MX",
    "gn:dem":2109,
    "gn:feature_class":"P",
    "gn:feature_code":"PPL",
    "gn:name":"La Comayhe",
    "gn:population":0,
    "gn:timezone":"America/Mexico_City",
    "iso:country":"MX",
    "name:spa_x_preferred":[
        "La Comayhe"
    ],
    "wof:name":"La Comayhe",
    "wof:placetype":"locality"
},
  "geometry": {"coordinates":[-99.40304999999999,20.29645],"type":"Point"}
}