{
  "type": "Feature",
  "properties": {
    "gn:admin1_code":"28.0",
    "gn:admin2_code":"37.0",
    "gn:asciiname":"El Coyote",
    "gn:country_code":"MX",
    "gn:dem":492,
    "gn:feature_class":"P",
    "gn:feature_code":"PPL",
    "gn:name":"El Coyote",
    "gn:population":0,
    "gn:timezone":"America/Monterrey",
    "iso:country":"MX",
    "name:spa_x_preferred":[
        "El Coyote"
    ],
    "wof:name":"El Coyote",
    "wof:placetype":"locality"
},
  "geometry": {"coordinates":[-98.24262,23.38678],"type":"Point"}
}