{
  "type": "Feature",
  "properties": {
    "gn:admin1_code":"21",
    "gn:admin2_code":"206",
    "gn:asciiname":"El Pitahayo",
    "gn:country_code":"MX",
    "gn:dem":1551,
    "gn:feature_class":"P",
    "gn:feature_code":"PPL",
    "gn:name":"El Pitahayo",
    "gn:population":37,
    "gn:timezone":"America/Mexico_City",
    "iso:country":"MX",
    "wof:name":"El Pitahayo",
    "wof:placetype":"locality",
    "wof:population":37
},
  "geometry": {"coordinates":[-98.05691,18.51684],"type":"Point"}
}