{
  "type": "Feature",
  "properties": {
    "gn:admin1_code":"26",
    "gn:admin2_code":"33",
    "gn:asciiname":"Lucio Blanco",
    "gn:country_code":"MX",
    "gn:dem":59,
    "gn:feature_class":"P",
    "gn:feature_code":"PPL",
    "gn:name":"Lucio Blanco",
    "gn:population":48,
    "gn:timezone":"America/Hermosillo",
    "iso:country":"MX",
    "name:ara_x_preferred":[
        "\u0644\u0648\u0633\u064a\u0648 \u0628\u0644\u0627\u0646\u0643\u0648"
    ],
    "name:nld_x_preferred":[
        "Lucio Blanco"
    ],
    "name:spa_x_preferred":[
        "Lucio Blanco"
    ],
    "wof:name":"Lucio Blanco",
    "wof:placetype":"locality",
    "wof:population":48
},
  "geometry": {"coordinates":[-109.13278,26.54722000000001],"type":"Point"}
}