{
  "type": "Feature",
  "properties": {
    "gn:admin1_code":"28",
    "gn:admin2_code":"35.0",
    "gn:asciiname":"Rancho El Huizachal",
    "gn:cc2":"MX",
    "gn:country_code":"MX",
    "gn:dem":11,
    "gn:feature_class":"P",
    "gn:feature_code":"PPL",
    "gn:name":"Rancho El Huizachal",
    "gn:population":0,
    "gn:timezone":"America/Monterrey",
    "iso:country":"MX",
    "name:und_x_variant":[
        "Rancho Huizachal",
        "Rancho El Huizachal"
    ],
    "wof:name":"Rancho El Huizachal",
    "wof:placetype":"locality"
},
  "geometry": {"coordinates":[-97.95,24.78333],"type":"Point"}
}