{
  "type": "Feature",
  "properties": {
    "gn:admin1_code":"21",
    "gn:admin2_code":"6.0",
    "gn:asciiname":"Camino de San Marcos (Palenque)",
    "gn:country_code":"MX",
    "gn:dem":1464,
    "gn:feature_class":"P",
    "gn:feature_code":"PPL",
    "gn:name":"Camino de San Marcos (Palenque)",
    "gn:population":286,
    "gn:timezone":"America/Mexico_City",
    "iso:country":"MX",
    "wof:name":"Camino de San Marcos (Palenque)",
    "wof:placetype":"locality",
    "wof:population":286
},
  "geometry": {"coordinates":[-97.86583,20.01056],"type":"Point"}
}