{
  "type": "Feature",
  "properties": {
    "gn:admin1_code":"5",
    "gn:admin2_code":"98.0",
    "gn:asciiname":"El Cangrejo",
    "gn:country_code":"MX",
    "gn:dem":425,
    "gn:feature_class":"P",
    "gn:feature_code":"PPL",
    "gn:name":"El Cangrejo",
    "gn:population":5,
    "gn:timezone":"America/Mexico_City",
    "iso:country":"MX",
    "wof:name":"El Cangrejo",
    "wof:placetype":"locality",
    "wof:population":5
},
  "geometry": {"coordinates":[-92.73889,16.52361],"type":"Point"}
}