{
  "type": "Feature",
  "properties": {
    "gn:admin1_code":"6.0",
    "gn:admin2_code":"63.0",
    "gn:asciiname":"La Mesa Verde",
    "gn:country_code":"MX",
    "gn:dem":1563,
    "gn:feature_class":"P",
    "gn:feature_code":"PPL",
    "gn:name":"La Mesa Verde",
    "gn:population":0,
    "gn:timezone":"America/Chihuahua",
    "iso:country":"MX",
    "name:spa_x_preferred":[
        "La Mesa Verde"
    ],
    "wof:name":"La Mesa Verde",
    "wof:placetype":"locality"
},
  "geometry": {"coordinates":[-108.45701,28.69544],"type":"Point"}
}