{
  "type": "Feature",
  "properties": {
    "gn:admin1_code":"30",
    "gn:admin2_code":"142",
    "gn:asciiname":"El Uveral",
    "gn:country_code":"MX",
    "gn:dem":45,
    "gn:feature_class":"P",
    "gn:feature_code":"PPL",
    "gn:name":"El Uveral",
    "gn:population":37,
    "gn:timezone":"America/Mexico_City",
    "iso:country":"MX",
    "wof:name":"El Uveral",
    "wof:placetype":"locality",
    "wof:population":37
},
  "geometry": {"coordinates":[-95.18306,17.87056],"type":"Point"}
}