{
  "type": "Feature",
  "properties": {
    "gn:admin1_code":"20",
    "gn:admin2_code":"258",
    "gn:asciiname":"Yunumano",
    "gn:country_code":"MX",
    "gn:dem":2022,
    "gn:feature_class":"P",
    "gn:feature_code":"PPL",
    "gn:name":"Yunuma\u00f1o",
    "gn:population":26,
    "gn:timezone":"America/Mexico_City",
    "iso:country":"MX",
    "name:und_x_variant":[
        "Yunuma\u00f1o"
    ],
    "wof:name":"Yunumano",
    "wof:placetype":"locality",
    "wof:population":26
},
  "geometry": {"coordinates":[-97.47917,17.30583],"type":"Point"}
}