{
  "type": "Feature",
  "properties": {
    "gn:admin1_code":"20.0",
    "gn:admin2_code":"334.0",
    "gn:asciiname":"Los Huesos",
    "gn:country_code":"MX",
    "gn:dem":65,
    "gn:feature_class":"P",
    "gn:feature_code":"PPL",
    "gn:name":"Los Huesos",
    "gn:population":0,
    "gn:timezone":"America/Mexico_City",
    "iso:country":"MX",
    "name:spa_x_preferred":[
        "Los Huesos"
    ],
    "wof:name":"Los Huesos",
    "wof:placetype":"locality"
},
  "geometry": {"coordinates":[-97.36953,15.96715],"type":"Point"}
}