{
  "type": "Feature",
  "properties": {
    "gn:admin1_code":"6",
    "gn:admin2_code":"65",
    "gn:asciiname":"El Pinal",
    "gn:country_code":"MX",
    "gn:dem":1766,
    "gn:feature_class":"P",
    "gn:feature_code":"PPL",
    "gn:name":"El Pinal",
    "gn:population":46,
    "gn:timezone":"America/Chihuahua",
    "iso:country":"MX",
    "wof:name":"El Pinal",
    "wof:placetype":"locality",
    "wof:population":46
},
  "geometry": {"coordinates":[-107.91713,27.13354],"type":"Point"}
}