{
  "type": "Feature",
  "properties": {
    "gn:admin1_code":"21",
    "gn:admin2_code":"76",
    "gn:asciiname":"Loma de las Flores (Predio la Citricola)",
    "gn:country_code":"MX",
    "gn:dem":398,
    "gn:feature_class":"P",
    "gn:feature_code":"PPL",
    "gn:name":"Loma de las Flores (Predio la Citr\u00edcola)",
    "gn:population":36,
    "gn:timezone":"America/Mexico_City",
    "iso:country":"MX",
    "name:und_x_variant":[
        "Loma de las Flores (Predio la Citr\u00edcola)"
    ],
    "wof:name":"Loma de las Flores (Predio la Citricola)",
    "wof:placetype":"locality",
    "wof:population":36
},
  "geometry": {"coordinates":[-97.32225,20.07156],"type":"Point"}
}