{
  "type": "Feature",
  "properties": {
    "gn:admin1_code":"21",
    "gn:admin2_code":"154.0",
    "gn:asciiname":"Invernadero Santa Ines",
    "gn:country_code":"MX",
    "gn:dem":1991,
    "gn:feature_class":"P",
    "gn:feature_code":"PPL",
    "gn:name":"Invernadero Santa In\u00e9s",
    "gn:population":8,
    "gn:timezone":"America/Mexico_City",
    "iso:country":"MX",
    "name:und_x_variant":[
        "Invernadero Santa In\u00e9s"
    ],
    "wof:name":"Invernadero Santa Ines",
    "wof:placetype":"locality",
    "wof:population":8
},
  "geometry": {"coordinates":[-97.73219,18.84069],"type":"Point"}
}