{
  "type": "Feature",
  "properties": {
    "gn:admin1_code":"16",
    "gn:admin2_code":"13.0",
    "gn:asciiname":"El Rinon",
    "gn:country_code":"MX",
    "gn:dem":512,
    "gn:feature_class":"P",
    "gn:feature_code":"PPL",
    "gn:name":"El Ri\u00f1\u00f3n",
    "gn:population":0,
    "gn:timezone":"America/Mexico_City",
    "iso:country":"MX",
    "name:spa_x_preferred":[
        "El Ri\u00f1\u00f3n"
    ],
    "wof:name":"El Rinon",
    "wof:placetype":"locality"
},
  "geometry": {"coordinates":[-101.13641,18.86129],"type":"Point"}
}