{
  "type": "Feature",
  "properties": {
    "gn:admin1_code":"29.0",
    "gn:admin2_code":"4.0",
    "gn:asciiname":"San Miguel Vista Hermosa",
    "gn:country_code":"MX",
    "gn:dem":2621,
    "gn:feature_class":"P",
    "gn:feature_code":"PPL",
    "gn:name":"San Miguel Vista Hermosa",
    "gn:population":0,
    "gn:timezone":"America/Mexico_City",
    "iso:country":"MX",
    "name:spa_x_preferred":[
        "San Miguel Vista Hermosa"
    ],
    "wof:name":"San Miguel Vista Hermosa",
    "wof:placetype":"locality"
},
  "geometry": {"coordinates":[-97.76278000000001,19.43093],"type":"Point"}
}