{
  "type": "Feature",
  "properties": {
    "gn:admin1_code":"14",
    "gn:admin2_code":"118.0",
    "gn:asciiname":"La Jarrilla",
    "gn:country_code":"MX",
    "gn:dem":1736,
    "gn:feature_class":"P",
    "gn:feature_code":"PPL",
    "gn:name":"La Jarrilla",
    "gn:population":109,
    "gn:timezone":"America/Mexico_City",
    "iso:country":"MX",
    "wof:name":"La Jarrilla",
    "wof:placetype":"locality",
    "wof:population":109
},
  "geometry": {"coordinates":[-102.95417,21.05444],"type":"Point"}
}