{
  "type": "Feature",
  "properties": {
    "gn:admin1_code":"6",
    "gn:admin2_code":"65.0",
    "gn:asciiname":"Piedra Cabeza",
    "gn:country_code":"MX",
    "gn:dem":2290,
    "gn:feature_class":"P",
    "gn:feature_code":"PPL",
    "gn:name":"Piedra Cabeza",
    "gn:population":4,
    "gn:timezone":"America/Chihuahua",
    "iso:country":"MX",
    "wof:name":"Piedra Cabeza",
    "wof:placetype":"locality",
    "wof:population":4
},
  "geometry": {"coordinates":[-107.96158,27.11548],"type":"Point"}
}