{
  "type": "Feature",
  "properties": {
    "gn:admin1_code":"20",
    "gn:admin2_code":"59.0",
    "gn:asciiname":"La Labor del Rosario",
    "gn:country_code":"MX",
    "gn:dem":1527,
    "gn:feature_class":"P",
    "gn:feature_code":"PPL",
    "gn:name":"La Labor del Rosario",
    "gn:population":92,
    "gn:timezone":"America/Mexico_City",
    "iso:country":"MX",
    "wof:name":"La Labor del Rosario",
    "wof:placetype":"locality",
    "wof:population":92
},
  "geometry": {"coordinates":[-96.61556,16.34639],"type":"Point"}
}