{
  "type": "Feature",
  "properties": {
    "gn:admin1_code":"18",
    "gn:admin2_code":"15.0",
    "gn:asciiname":"Playa el Sesteo",
    "gn:country_code":"MX",
    "gn:dem":7,
    "gn:feature_class":"P",
    "gn:feature_code":"PPL",
    "gn:name":"Playa el Sesteo",
    "gn:population":106,
    "gn:timezone":"America/Mazatlan",
    "iso:country":"MX",
    "wof:name":"Playa el Sesteo",
    "wof:placetype":"locality",
    "wof:population":106
},
  "geometry": {"coordinates":[-105.48583000000001,21.72583],"type":"Point"}
}