{
  "type": "Feature",
  "properties": {
    "gn:admin1_code":"30",
    "gn:admin2_code":"91.0",
    "gn:asciiname":"Nuevo Paraiso",
    "gn:country_code":"MX",
    "gn:dem":26,
    "gn:feature_class":"P",
    "gn:feature_code":"PPL",
    "gn:name":"Nuevo Para\u00edso",
    "gn:population":183,
    "gn:timezone":"America/Mexico_City",
    "iso:country":"MX",
    "name:und_x_variant":[
        "Nuevo Para\u00edso"
    ],
    "wof:name":"Nuevo Paraiso",
    "wof:placetype":"locality",
    "wof:population":183
},
  "geometry": {"coordinates":[-94.765,17.50056],"type":"Point"}
}