{
  "type": "Feature",
  "properties": {
    "gn:admin1_code":"30",
    "gn:admin2_code":"141.0",
    "gn:asciiname":"Kilometro Tres",
    "gn:country_code":"MX",
    "gn:dem":236,
    "gn:feature_class":"P",
    "gn:feature_code":"PPL",
    "gn:name":"Kil\u00f3metro Tres",
    "gn:population":57,
    "gn:timezone":"America/Mexico_City",
    "iso:country":"MX",
    "name:und_x_variant":[
        "Kil\u00f3metro Tres"
    ],
    "wof:name":"Kilometro Tres",
    "wof:placetype":"locality",
    "wof:population":57
},
  "geometry": {"coordinates":[-95.2375,18.44222],"type":"Point"}
}