{
  "type": "Feature",
  "properties": {
    "gn:admin1_code":"16.0",
    "gn:admin2_code":"2.0",
    "gn:asciiname":"El Faisan",
    "gn:country_code":"MX",
    "gn:dem":640,
    "gn:feature_class":"P",
    "gn:feature_code":"PPL",
    "gn:name":"El Fais\u00e1n",
    "gn:population":0,
    "gn:timezone":"America/Mexico_City",
    "iso:country":"MX",
    "name:spa_x_preferred":[
        "El Fais\u00e1n"
    ],
    "wof:name":"El Faisan",
    "wof:placetype":"locality"
},
  "geometry": {"coordinates":[-102.67616,18.80529],"type":"Point"}
}