{
  "type": "Feature",
  "properties": {
    "gn:admin1_code":"21",
    "gn:admin2_code":"85.0",
    "gn:asciiname":"Abelardo L. Rodriguez",
    "gn:country_code":"MX",
    "gn:dem":1318,
    "gn:feature_class":"P",
    "gn:feature_code":"PPL",
    "gn:name":"Abelardo L. Rodr\u00edguez",
    "gn:population":253,
    "gn:timezone":"America/Mexico_City",
    "iso:country":"MX",
    "wof:name":"Abelardo L. Rodriguez",
    "wof:placetype":"locality",
    "wof:population":253
},
  "geometry": {"coordinates":[-98.40416999999999,18.57278],"type":"Point"}
}