{
  "type": "Feature",
  "properties": {
    "gn:admin1_code":"4",
    "gn:admin2_code":"11.0",
    "gn:asciiname":"La Curva",
    "gn:country_code":"MX",
    "gn:dem":93,
    "gn:feature_class":"P",
    "gn:feature_code":"PPL",
    "gn:name":"La Curva",
    "gn:population":7,
    "gn:timezone":"America/Merida",
    "iso:country":"MX",
    "wof:name":"La Curva",
    "wof:placetype":"locality",
    "wof:population":7
},
  "geometry": {"coordinates":[-90.44583,17.88028],"type":"Point"}
}