{
  "type": "Feature",
  "properties": {
    "gn:admin1_code":"21.0",
    "gn:admin2_code":"96.0",
    "gn:asciiname":"El Paraiso",
    "gn:country_code":"MX",
    "gn:dem":2349,
    "gn:feature_class":"P",
    "gn:feature_code":"PPL",
    "gn:name":"El Paraiso",
    "gn:population":0,
    "gn:timezone":"America/Mexico_City",
    "iso:country":"MX",
    "name:spa_x_preferred":[
        "El Paraiso"
    ],
    "wof:name":"El Paraiso",
    "wof:placetype":"locality"
},
  "geometry": {"coordinates":[-97.68214999999999,19.14027],"type":"Point"}
}