{
  "type": "Feature",
  "properties": {
    "gn:admin1_code":"14",
    "gn:admin2_code":"118",
    "gn:asciiname":"El Humedo",
    "gn:country_code":"MX",
    "gn:dem":2080,
    "gn:feature_class":"P",
    "gn:feature_code":"PPL",
    "gn:name":"El H\u00famedo",
    "gn:population":18,
    "gn:timezone":"America/Mexico_City",
    "iso:country":"MX",
    "name:und_x_variant":[
        "El H\u00famedo"
    ],
    "wof:name":"El Humedo",
    "wof:placetype":"locality",
    "wof:population":18
},
  "geometry": {"coordinates":[-103.00221999999999,21.1275],"type":"Point"}
}