{
  "type": "Feature",
  "properties": {
    "gn:admin1_code":"14.0",
    "gn:asciiname":"El Estanco",
    "gn:country_code":"MX",
    "gn:dem":1965,
    "gn:feature_class":"P",
    "gn:feature_code":"PPL",
    "gn:name":"El Estanco",
    "gn:population":0,
    "gn:timezone":"America/Mexico_City",
    "iso:country":"MX",
    "name:spa_x_preferred":[
        "El Estanco"
    ],
    "wof:name":"El Estanco",
    "wof:placetype":"locality"
},
  "geometry": {"coordinates":[-102.27751000000001,21.01424],"type":"Point"}
}