{
  "type": "Feature",
  "properties": {
    "gn:admin1_code":"5",
    "gn:admin2_code":"70.0",
    "gn:asciiname":"Zoical",
    "gn:country_code":"MX",
    "gn:dem":2676,
    "gn:feature_class":"P",
    "gn:feature_code":"PPL",
    "gn:name":"Zoical",
    "gn:population":121,
    "gn:timezone":"America/Mexico_City",
    "iso:country":"MX",
    "wof:name":"Zoical",
    "wof:placetype":"locality",
    "wof:population":121
},
  "geometry": {"coordinates":[-92.32556,15.43833],"type":"Point"}
}