{
  "type": "Feature",
  "properties": {
    "gn:admin1_code":"20",
    "gn:admin2_code":"278.0",
    "gn:asciiname":"La Patria",
    "gn:country_code":"MX",
    "gn:dem":67,
    "gn:feature_class":"P",
    "gn:feature_code":"PPL",
    "gn:name":"La Patria",
    "gn:population":0,
    "gn:timezone":"America/Mexico_City",
    "iso:country":"MX",
    "name:spa_x_preferred":[
        "Nueva Patria"
    ],
    "name:spa_x_variant":[
        "La Patria"
    ],
    "wof:name":"La Patria",
    "wof:placetype":"locality"
},
  "geometry": {"coordinates":[-96.42838,18.31295],"type":"Point"}
}