{
  "type": "Feature",
  "properties": {
    "gn:admin1_code":"30.0",
    "gn:admin2_code":"141.0",
    "gn:asciiname":"Adolfo Ruiz Cortines",
    "gn:country_code":"MX",
    "gn:dem":371,
    "gn:feature_class":"P",
    "gn:feature_code":"PPL",
    "gn:name":"Adolfo Ruiz Cortines",
    "gn:population":0,
    "gn:timezone":"America/Mexico_City",
    "iso:country":"MX",
    "name:spa_x_preferred":[
        "Adolfo Ruiz Cortines"
    ],
    "wof:name":"Adolfo Ruiz Cortines",
    "wof:placetype":"locality"
},
  "geometry": {"coordinates":[-95.11655,18.60152],"type":"Point"}
}