{
  "type": "Feature",
  "properties": {
    "gn:admin1_code":"14",
    "gn:admin2_code":"118",
    "gn:asciiname":"El Rancho de Arriba",
    "gn:country_code":"MX",
    "gn:dem":1759,
    "gn:feature_class":"P",
    "gn:feature_code":"PPL",
    "gn:name":"El Rancho de Arriba",
    "gn:population":17,
    "gn:timezone":"America/Mexico_City",
    "iso:country":"MX",
    "wof:name":"El Rancho de Arriba",
    "wof:placetype":"locality",
    "wof:population":17
},
  "geometry": {"coordinates":[-102.85167,21.06333],"type":"Point"}
}