{
  "type": "Feature",
  "properties": {
    "gn:admin1_code":"13",
    "gn:admin2_code":"81.0",
    "gn:asciiname":"Colonia Benito Juarez",
    "gn:country_code":"MX",
    "gn:dem":2160,
    "gn:feature_class":"P",
    "gn:feature_code":"PPL",
    "gn:name":"Colonia Benito Ju\u00e1rez",
    "gn:population":99,
    "gn:timezone":"America/Mexico_City",
    "iso:country":"MX",
    "name:und_x_variant":[
        "Colonia Benito Ju\u00e1rez"
    ],
    "wof:name":"Colonia Benito Juarez",
    "wof:placetype":"locality",
    "wof:population":99
},
  "geometry": {"coordinates":[-98.68261,20.66531],"type":"Point"}
}