{
  "type": "Feature",
  "properties": {
    "gn:admin1_code":"15",
    "gn:admin2_code":"84.0",
    "gn:asciiname":"Ixtlahuaca de Cuauhtemoc",
    "gn:country_code":"MX",
    "gn:dem":2320,
    "gn:feature_class":"P",
    "gn:feature_code":"PPL",
    "gn:name":"Ixtlahuaca de Cuauht\u00e9moc",
    "gn:population":3468,
    "gn:timezone":"America/Mexico_City",
    "iso:country":"MX",
    "wof:name":"Ixtlahuaca de Cuauhtemoc",
    "wof:placetype":"locality",
    "wof:population":3468
},
  "geometry": {"coordinates":[-98.86028,19.88139],"type":"Point"}
}