{
  "type": "Feature",
  "properties": {
    "gn:admin1_code":"6.0",
    "gn:admin2_code":"57.0",
    "gn:asciiname":"Rancho de Damaso",
    "gn:country_code":"MX",
    "gn:dem":1713,
    "gn:feature_class":"P",
    "gn:feature_code":"PPL",
    "gn:name":"Rancho de Damaso",
    "gn:population":0,
    "gn:timezone":"America/Chihuahua",
    "iso:country":"MX",
    "name:spa_x_preferred":[
        "Rancho de Damaso"
    ],
    "wof:name":"Rancho de Damaso",
    "wof:placetype":"locality"
},
  "geometry": {"coordinates":[-106.61203999999999,27.7209],"type":"Point"}
}