{
  "type": "Feature",
  "properties": {
    "gn:admin1_code":"14",
    "gn:admin2_code":"84.0",
    "gn:asciiname":"El Verde",
    "gn:country_code":"MX",
    "gn:dem":367,
    "gn:feature_class":"P",
    "gn:feature_code":"PPL",
    "gn:name":"El Verde",
    "gn:population":5,
    "gn:timezone":"America/Mexico_City",
    "iso:country":"MX",
    "wof:name":"El Verde",
    "wof:placetype":"locality",
    "wof:population":5
},
  "geometry": {"coordinates":[-104.95719,20.19233],"type":"Point"}
}