{
  "type": "Feature",
  "properties": {
    "gn:admin1_code":"15",
    "gn:admin2_code":"99",
    "gn:asciiname":"Santa Cruz de la Constancia",
    "gn:country_code":"MX",
    "gn:dem":2315,
    "gn:feature_class":"P",
    "gn:feature_code":"PPL",
    "gn:name":"Santa Cruz de la Constancia",
    "gn:population":41,
    "gn:timezone":"America/Mexico_City",
    "iso:country":"MX",
    "wof:name":"Santa Cruz de la Constancia",
    "wof:placetype":"locality",
    "wof:population":41
},
  "geometry": {"coordinates":[-98.82724,19.55475],"type":"Point"}
}