{
  "type": "Feature",
  "properties": {
    "gn:admin1_code":"30",
    "gn:admin2_code":"163",
    "gn:asciiname":"El Saucal",
    "gn:country_code":"MX",
    "gn:dem":1765,
    "gn:feature_class":"P",
    "gn:feature_code":"PPL",
    "gn:name":"El Saucal",
    "gn:population":10,
    "gn:timezone":"America/Mexico_City",
    "iso:country":"MX",
    "wof:name":"El Saucal",
    "wof:placetype":"locality",
    "wof:population":10
},
  "geometry": {"coordinates":[-96.95278,19.76806],"type":"Point"}
}