{
  "type": "Feature",
  "properties": {
    "gn:admin1_code":"5.0",
    "gn:admin2_code":"31.0",
    "gn:asciiname":"Tacuba Vieja",
    "gn:country_code":"MX",
    "gn:dem":1217,
    "gn:feature_class":"P",
    "gn:feature_code":"PPL",
    "gn:name":"Tacuba Vieja",
    "gn:population":0,
    "gn:timezone":"America/Mexico_City",
    "iso:country":"MX",
    "name:spa_x_preferred":[
        "Tacuba Vieja"
    ],
    "wof:name":"Tacuba Vieja",
    "wof:placetype":"locality"
},
  "geometry": {"coordinates":[-92.35799,17.09154],"type":"Point"}
}