{
  "type": "Feature",
  "properties": {
    "gn:admin1_code":"30",
    "gn:admin2_code":"86.0",
    "gn:asciiname":"Cruz Alta",
    "gn:country_code":"MX",
    "gn:dem":750,
    "gn:feature_class":"P",
    "gn:feature_code":"PPL",
    "gn:name":"Cruz Alta",
    "gn:population":116,
    "gn:timezone":"America/Mexico_City",
    "iso:country":"MX",
    "wof:name":"Cruz Alta",
    "wof:placetype":"locality",
    "wof:population":116
},
  "geometry": {"coordinates":[-97.25,19.89],"type":"Point"}
}