{
  "type": "Feature",
  "properties": {
    "gn:admin1_code":"30",
    "gn:admin2_code":"86.0",
    "gn:asciiname":"Cruz Alta",
    "gn:country_code":"MX",
    "gn:dem":750,
    "gn:feature_class":"P",
    "gn:feature_code":"PPL",
    "gn:name":"Cruz Alta",
    "gn:population":116,
    "gn:timezone":"America/Mexico_City",
    "iso:country":"MX",
    "name:bpy_x_preferred":[
        "\u0995\u09cd\u09b0\u09c1\u099c \u0986\u09b2\u09cd\u099f\u09be"
    ],
    "name:ceb_x_preferred":[
        "Cruz Alta"
    ],
    "name:nld_x_preferred":[
        "Cruz Alta"
    ],
    "name:por_x_preferred":[
        "Cruz Alta"
    ],
    "name:rus_x_preferred":[
        "\u041a\u0440\u0443\u0441-\u0410\u043b\u0442\u0430"
    ],
    "name:spa_x_preferred":[
        "Cruz Alta"
    ],
    "name:swe_x_preferred":[
        "Cruz Alta"
    ],
    "wof:name":"Cruz Alta",
    "wof:placetype":"locality",
    "wof:population":116
},
  "geometry": {"coordinates":[-97.25,19.89],"type":"Point"}
}