{
  "type": "Feature",
  "properties": {
    "gn:admin1_code":"6",
    "gn:admin2_code":"65",
    "gn:asciiname":"Otonachi",
    "gn:country_code":"MX",
    "gn:dem":2307,
    "gn:feature_class":"P",
    "gn:feature_code":"PPL",
    "gn:name":"Otonachi",
    "gn:population":13,
    "gn:timezone":"America/Chihuahua",
    "iso:country":"MX",
    "wof:name":"Otonachi",
    "wof:placetype":"locality",
    "wof:population":13
},
  "geometry": {"coordinates":[-107.85714,27.49409],"type":"Point"}
}