{
  "type": "Feature",
  "properties": {
    "gn:admin1_code":"30",
    "gn:admin2_code":"144.0",
    "gn:asciiname":"Boca de Tizapan",
    "gn:country_code":"MX",
    "gn:dem":76,
    "gn:feature_class":"P",
    "gn:feature_code":"PPL",
    "gn:name":"Boca de Tizap\u00e1n",
    "gn:population":6,
    "gn:timezone":"America/Mexico_City",
    "iso:country":"MX",
    "wof:name":"Boca de Tizapan",
    "wof:placetype":"locality",
    "wof:population":6
},
  "geometry": {"coordinates":[-95.03139,17.84389],"type":"Point"}
}