{
  "type": "Feature",
  "properties": {
    "gn:admin1_code":"12",
    "gn:admin2_code":"47",
    "gn:asciiname":"La Aurora",
    "gn:country_code":"MX",
    "gn:dem":1732,
    "gn:feature_class":"P",
    "gn:feature_code":"PPL",
    "gn:name":"La Aurora",
    "gn:population":25,
    "gn:timezone":"America/Mexico_City",
    "iso:country":"MX",
    "name:ceb_x_preferred":[
        "La Aurora"
    ],
    "name:deu_x_preferred":[
        "La Aurora"
    ],
    "name:glg_x_preferred":[
        "La Aurora"
    ],
    "name:rus_x_preferred":[
        "\u041b\u0430-\u0410\u0443\u0440\u043e\u0440\u0430"
    ],
    "name:spa_x_preferred":[
        "La Aurora"
    ],
    "name:srp_x_preferred":[
        "\u041b\u0430 \u0410\u0443\u0440\u043e\u0440\u0430"
    ],
    "name:swe_x_preferred":[
        "La Aurora"
    ],
    "wof:name":"La Aurora",
    "wof:placetype":"locality",
    "wof:population":25
},
  "geometry": {"coordinates":[-99.84656,18.57143],"type":"Point"}
}