{
  "type": "Feature",
  "properties": {
    "gn:admin1_code":"24.0",
    "gn:asciiname":"Tampamal",
    "gn:country_code":"MX",
    "gn:dem":1094,
    "gn:feature_class":"P",
    "gn:feature_code":"PPL",
    "gn:name":"Tampam\u00e1l",
    "gn:population":0,
    "gn:timezone":"America/Mexico_City",
    "iso:country":"MX",
    "name:spa_x_preferred":[
        "Tampam\u00e1l"
    ],
    "wof:name":"Tampamal",
    "wof:placetype":"locality"
},
  "geometry": {"coordinates":[-99.51631999999999,21.79134],"type":"Point"}
}