{
  "type": "Feature",
  "properties": {
    "gn:admin1_code":"25",
    "gn:admin2_code":"15.0",
    "gn:asciiname":"Granja Edith",
    "gn:country_code":"MX",
    "gn:dem":37,
    "gn:feature_class":"P",
    "gn:feature_code":"PPL",
    "gn:name":"Granja Edith",
    "gn:population":0,
    "gn:timezone":"America/Mazatlan",
    "iso:country":"MX",
    "name:spa_x_preferred":[
        "Granja Edith"
    ],
    "wof:name":"Granja Edith",
    "wof:placetype":"locality"
},
  "geometry": {"coordinates":[-108.12972000000001,25.45976],"type":"Point"}
}