{
  "type": "Feature",
  "properties": {
    "gn:admin1_code":"15.0",
    "gn:asciiname":"Teacalco Chiquito",
    "gn:country_code":"MX",
    "gn:dem":2336,
    "gn:feature_class":"P",
    "gn:feature_code":"PPL",
    "gn:name":"Teacalco Chiquito",
    "gn:population":0,
    "gn:timezone":"America/Mexico_City",
    "iso:country":"MX",
    "name:spa_x_preferred":[
        "Teacalco Chiquito"
    ],
    "wof:name":"Teacalco Chiquito",
    "wof:placetype":"locality"
},
  "geometry": {"coordinates":[-98.78792,19.02295],"type":"Point"}
}