{
  "type": "Feature",
  "properties": {
    "gn:admin1_code":"24",
    "gn:admin2_code":"29.0",
    "gn:asciiname":"Sabinito",
    "gn:country_code":"MX",
    "gn:dem":140,
    "gn:feature_class":"P",
    "gn:feature_code":"PPL",
    "gn:name":"Sabinito",
    "gn:population":132,
    "gn:timezone":"America/Mexico_City",
    "iso:country":"MX",
    "wof:name":"Sabinito",
    "wof:placetype":"locality",
    "wof:population":132
},
  "geometry": {"coordinates":[-98.55222000000001,21.40917],"type":"Point"}
}