{
  "type": "Feature",
  "properties": {
    "gn:admin1_code":"5",
    "gn:admin2_code":"12",
    "gn:asciiname":"San Jose Porvenir",
    "gn:country_code":"MX",
    "gn:dem":998,
    "gn:feature_class":"P",
    "gn:feature_code":"PPL",
    "gn:name":"San Jos\u00e9 Porvenir",
    "gn:population":10,
    "gn:timezone":"America/Mexico_City",
    "iso:country":"MX",
    "name:und_x_variant":[
        "San Jos\u00e9 Porvenir"
    ],
    "wof:name":"San Jose Porvenir",
    "wof:placetype":"locality",
    "wof:population":10
},
  "geometry": {"coordinates":[-93.29277999999999,16.87861],"type":"Point"}
}