{
  "type": "Feature",
  "properties": {
    "gn:admin1_code":"30",
    "gn:admin2_code":"148.0",
    "gn:asciiname":"Mata Higuera",
    "gn:country_code":"MX",
    "gn:dem":109,
    "gn:feature_class":"P",
    "gn:feature_code":"PPL",
    "gn:name":"Mata Higuera",
    "gn:population":0,
    "gn:timezone":"America/Mexico_City",
    "iso:country":"MX",
    "name:spa_x_preferred":[
        "Mata Higuera"
    ],
    "wof:name":"Mata Higuera",
    "wof:placetype":"locality"
},
  "geometry": {"coordinates":[-96.42276,18.95086],"type":"Point"}
}