{
  "type": "Feature",
  "properties": {
    "gn:admin1_code":"13",
    "gn:admin2_code":"21.0",
    "gn:asciiname":"El Panteon",
    "gn:country_code":"MX",
    "gn:dem":2492,
    "gn:feature_class":"P",
    "gn:feature_code":"PPL",
    "gn:name":"El Pante\u00f3n",
    "gn:population":6,
    "gn:timezone":"America/Mexico_City",
    "iso:country":"MX",
    "name:und_x_variant":[
        "El Pante\u00f3n"
    ],
    "wof:name":"El Panteon",
    "wof:placetype":"locality",
    "wof:population":6
},
  "geometry": {"coordinates":[-98.53455,19.64569],"type":"Point"}
}