{
  "type": "Feature",
  "properties": {
    "gn:admin1_code":"5",
    "gn:admin2_code":"59.0",
    "gn:asciiname":"La Revancha",
    "gn:country_code":"MX",
    "gn:dem":653,
    "gn:feature_class":"P",
    "gn:feature_code":"PPL",
    "gn:name":"La Revancha",
    "gn:population":0,
    "gn:timezone":"America/Mexico_City",
    "iso:country":"MX",
    "wof:name":"La Revancha",
    "wof:placetype":"locality"
},
  "geometry": {"coordinates":[-91.56667,16.73611],"type":"Point"}
}