{
  "type": "Feature",
  "properties": {
    "gn:admin1_code":"5",
    "gn:admin2_code":"83.0",
    "gn:asciiname":"Nuevo Chejel",
    "gn:cc2":"MX",
    "gn:country_code":"MX",
    "gn:dem":549,
    "gn:feature_class":"P",
    "gn:feature_code":"PPL",
    "gn:name":"Nuevo Chejel",
    "gn:population":427,
    "gn:timezone":"America/Mexico_City",
    "iso:country":"MX",
    "name:und_x_variant":[
        "Chajel",
        "Chejel"
    ],
    "wof:name":"Nuevo Chejel",
    "wof:placetype":"locality",
    "wof:population":427
},
  "geometry": {"coordinates":[-92.28667,15.94361],"type":"Point"}
}