{
  "type": "Feature",
  "properties": {
    "gn:admin1_code":"32.0",
    "gn:admin2_code":"34.0",
    "gn:asciiname":"El Arabe",
    "gn:country_code":"MX",
    "gn:dem":2404,
    "gn:feature_class":"P",
    "gn:feature_code":"PPL",
    "gn:name":"El \u00c1rabe",
    "gn:population":0,
    "gn:timezone":"America/Mexico_City",
    "iso:country":"MX",
    "name:spa_x_preferred":[
        "El \u00c1rabe"
    ],
    "wof:name":"El Arabe",
    "wof:placetype":"locality"
},
  "geometry": {"coordinates":[-102.96169999999999,21.38271],"type":"Point"}
}