{
  "type": "Feature",
  "properties": {
    "gn:admin1_code":"10",
    "gn:admin2_code":"7.0",
    "gn:asciiname":"La Galleguita",
    "gn:country_code":"MX",
    "gn:dem":1113,
    "gn:feature_class":"P",
    "gn:feature_code":"PPL",
    "gn:name":"La Galleguita",
    "gn:population":0,
    "gn:timezone":"America/Monterrey",
    "iso:country":"MX",
    "name:spa_x_preferred":[
        "La Galleguita"
    ],
    "wof:name":"La Galleguita",
    "wof:placetype":"locality"
},
  "geometry": {"coordinates":[-103.58441999999999,25.79431],"type":"Point"}
}