{
  "type": "Feature",
  "properties": {
    "gn:admin1_code":"5",
    "gn:admin2_code":"17.0",
    "gn:asciiname":"El Jordan",
    "gn:country_code":"MX",
    "gn:dem":726,
    "gn:feature_class":"P",
    "gn:feature_code":"PPL",
    "gn:name":"El Jord\u00e1n",
    "gn:population":0,
    "gn:timezone":"America/Mexico_City",
    "iso:country":"MX",
    "name:spa_x_preferred":[
        "El Jord\u00e1n"
    ],
    "wof:name":"El Jordan",
    "wof:placetype":"locality"
},
  "geometry": {"coordinates":[-93.93236,16.73765],"type":"Point"}
}