{
  "type": "Feature",
  "properties": {
    "gn:admin1_code":"26.0",
    "gn:admin2_code":"14.0",
    "gn:asciiname":"El Temporal",
    "gn:country_code":"MX",
    "gn:dem":576,
    "gn:feature_class":"P",
    "gn:feature_code":"PPL",
    "gn:name":"El Temporal",
    "gn:population":0,
    "gn:timezone":"America/Hermosillo",
    "iso:country":"MX",
    "name:spa_x_preferred":[
        "El Temporal"
    ],
    "wof:name":"El Temporal",
    "wof:placetype":"locality"
},
  "geometry": {"coordinates":[-110.10101,29.64396],"type":"Point"}
}