{
  "type": "Feature",
  "properties": {
    "gn:admin1_code":"15.0",
    "gn:asciiname":"Terrenos Comunales Jaltocan",
    "gn:country_code":"MX",
    "gn:dem":2248,
    "gn:feature_class":"P",
    "gn:feature_code":"PPL",
    "gn:name":"Terrenos Comunales Jaltocan",
    "gn:population":0,
    "gn:timezone":"America/Mexico_City",
    "iso:country":"MX",
    "name:spa_x_preferred":[
        "Terrenos Comunales Jaltocan"
    ],
    "wof:name":"Terrenos Comunales Jaltocan",
    "wof:placetype":"locality"
},
  "geometry": {"coordinates":[-99.0492,19.71489],"type":"Point"}
}