{
  "type": "Feature",
  "properties": {
    "gn:admin1_code":"6",
    "gn:admin2_code":"8",
    "gn:asciiname":"El Barranco",
    "gn:country_code":"MX",
    "gn:dem":1319,
    "gn:feature_class":"P",
    "gn:feature_code":"PPL",
    "gn:name":"El Barranco",
    "gn:population":14,
    "gn:timezone":"America/Chihuahua",
    "iso:country":"MX",
    "wof:name":"El Barranco",
    "wof:placetype":"locality",
    "wof:population":14
},
  "geometry": {"coordinates":[-107.8224,27.02799000000001],"type":"Point"}
}