{
  "type": "Feature",
  "properties": {
    "gn:admin1_code":"10.0",
    "gn:asciiname":"Bahuiza",
    "gn:country_code":"MX",
    "gn:dem":374,
    "gn:feature_class":"P",
    "gn:feature_code":"PPL",
    "gn:name":"Bahuiza",
    "gn:population":0,
    "gn:timezone":"America/Monterrey",
    "iso:country":"MX",
    "name:spa_x_preferred":[
        "Bahuiza"
    ],
    "wof:name":"Bahuiza",
    "wof:placetype":"locality"
},
  "geometry": {"coordinates":[-106.78202,24.74997],"type":"Point"}
}