{
  "type": "Feature",
  "properties": {
    "gn:admin1_code":"25",
    "gn:admin2_code":"4.0",
    "gn:asciiname":"El Perico",
    "gn:country_code":"MX",
    "gn:dem":120,
    "gn:feature_class":"P",
    "gn:feature_code":"PPL",
    "gn:name":"El Perico",
    "gn:population":0,
    "gn:timezone":"America/Mazatlan",
    "iso:country":"MX",
    "name:spa_x_preferred":[
        "El Perico"
    ],
    "wof:name":"El Perico",
    "wof:placetype":"locality"
},
  "geometry": {"coordinates":[-106.08029999999999,23.33967],"type":"Point"}
}