{
  "type": "Feature",
  "properties": {
    "gn:admin1_code":"32",
    "gn:admin2_code":"35.0",
    "gn:asciiname":"Colonia Francisco I. Madero",
    "gn:country_code":"MX",
    "gn:dem":2131,
    "gn:feature_class":"P",
    "gn:feature_code":"PPL",
    "gn:name":"Colonia Francisco I. Madero",
    "gn:population":353,
    "gn:timezone":"America/Mexico_City",
    "iso:country":"MX",
    "wof:name":"Colonia Francisco I. Madero",
    "wof:placetype":"locality",
    "wof:population":353
},
  "geometry": {"coordinates":[-101.80833,22.44972000000001],"type":"Point"}
}