{
  "type": "Feature",
  "properties": {
    "gn:admin1_code":"18",
    "gn:admin2_code":"9",
    "gn:asciiname":"Bajio de la Cebolleta",
    "gn:country_code":"MX",
    "gn:dem":1890,
    "gn:feature_class":"P",
    "gn:feature_code":"PPL",
    "gn:name":"Baj\u00edo de la Cebolleta",
    "gn:population":13,
    "gn:timezone":"America/Mexico_City",
    "iso:country":"MX",
    "name:und_x_variant":[
        "Baj\u00edo de la Cebolleta"
    ],
    "wof:name":"Bajio de la Cebolleta",
    "wof:placetype":"locality",
    "wof:population":13
},
  "geometry": {"coordinates":[-104.30361000000001,22.31222],"type":"Point"}
}