{
  "type": "Feature",
  "properties": {
    "gn:admin1_code":"3",
    "gn:admin2_code":"3",
    "gn:asciiname":"San Luis",
    "gn:country_code":"MX",
    "gn:dem":184,
    "gn:feature_class":"P",
    "gn:feature_code":"PPL",
    "gn:name":"San Luis",
    "gn:population":16,
    "gn:timezone":"America/Mazatlan",
    "iso:country":"MX",
    "wof:name":"San Luis",
    "wof:placetype":"locality",
    "wof:population":16
},
  "geometry": {"coordinates":[-110.27067,23.65082],"type":"Point"}
}