{
  "type": "Feature",
  "properties": {
    "gn:admin1_code":"3",
    "gn:admin2_code":"3",
    "gn:asciiname":"San Luis",
    "gn:country_code":"MX",
    "gn:dem":184,
    "gn:feature_class":"P",
    "gn:feature_code":"PPL",
    "gn:name":"San Luis",
    "gn:population":16,
    "gn:timezone":"America/Mazatlan",
    "iso:country":"MX",
    "name:bre_x_preferred":[
        "San Luis"
    ],
    "name:cat_x_preferred":[
        "San Luis"
    ],
    "name:ceb_x_preferred":[
        "San Luis"
    ],
    "name:ces_x_preferred":[
        "San Luis"
    ],
    "name:deu_x_preferred":[
        "San Luis"
    ],
    "name:eus_x_preferred":[
        "San Luis"
    ],
    "name:fas_x_preferred":[
        "\u0633\u0627\u0646 \u0644\u0648\u0626\u06cc\u0633"
    ],
    "name:fin_x_preferred":[
        "San Luis"
    ],
    "name:fra_x_preferred":[
        "San Luis"
    ],
    "name:glg_x_preferred":[
        "San Luis"
    ],
    "name:heb_x_preferred":[
        "\u05e1\u05df \u05dc\u05d5\u05d0\u05d9\u05e1"
    ],
    "name:hin_x_preferred":[
        "\u0938\u0948\u0928 \u0932\u0941\u0908"
    ],
    "name:hye_x_preferred":[
        "\u054d\u0561\u0576 \u053c\u0578\u0582\u056b\u057d"
    ],
    "name:ilo_x_preferred":[
        "San Luis"
    ],
    "name:ita_x_preferred":[
        "San Luis"
    ],
    "name:jpn_x_preferred":[
        "\u30b5\u30f3\u30fb\u30eb\u30a4\u30b9"
    ],
    "name:kat_x_preferred":[
        "\u10e1\u10d0\u10dc-\u10da\u10e3\u10d8\u10e1\u10d8"
    ],
    "name:kor_x_preferred":[
        "\uc0b0\ub8e8\uc774\uc2a4"
    ],
    "name:lit_x_preferred":[
        "San Luisas"
    ],
    "name:mlg_x_preferred":[
        "San Luis"
    ],
    "name:nds_x_preferred":[
        "San Luis"
    ],
    "name:nld_x_preferred":[
        "San Luis"
    ],
    "name:pol_x_preferred":[
        "San Luis"
    ],
    "name:por_x_preferred":[
        "San Luis"
    ],
    "name:rus_x_preferred":[
        "\u0421\u0430\u043d-\u041b\u0443\u0438\u0441"
    ],
    "name:sco_x_preferred":[
        "San Luis"
    ],
    "name:slk_x_preferred":[
        "San Luis"
    ],
    "name:spa_x_preferred":[
        "San Luis"
    ],
    "name:srp_x_preferred":[
        "\u0421\u0430\u043d \u041b\u0443\u0438\u0441"
    ],
    "name:swe_x_preferred":[
        "San Luis"
    ],
    "name:tgl_x_preferred":[
        "San Luis"
    ],
    "name:ukr_x_preferred":[
        "\u0421\u0430\u043d-\u041b\u0443\u0457\u0441"
    ],
    "name:vol_x_preferred":[
        "San Luis"
    ],
    "name:war_x_preferred":[
        "San Luis"
    ],
    "wof:name":"San Luis",
    "wof:placetype":"locality",
    "wof:population":16
},
  "geometry": {"coordinates":[-110.27067,23.65082],"type":"Point"}
}