{
  "type": "Feature",
  "properties": {
    "gn:admin1_code":"12",
    "gn:admin2_code":"31.0",
    "gn:asciiname":"El Cascalote",
    "gn:country_code":"MX",
    "gn:dem":974,
    "gn:feature_class":"P",
    "gn:feature_code":"PPL",
    "gn:name":"El Cascalote",
    "gn:population":160,
    "gn:timezone":"America/Mexico_City",
    "iso:country":"MX",
    "wof:name":"El Cascalote",
    "wof:placetype":"locality",
    "wof:population":160
},
  "geometry": {"coordinates":[-100.15205,18.39034],"type":"Point"}
}