{
  "type": "Feature",
  "properties": {
    "gn:admin1_code":"26.0",
    "gn:admin2_code":"20.0",
    "gn:asciiname":"El Campo Santa Cruz",
    "gn:country_code":"MX",
    "gn:dem":476,
    "gn:feature_class":"P",
    "gn:feature_code":"PPL",
    "gn:name":"El Campo Santa Cruz",
    "gn:population":0,
    "gn:timezone":"America/Hermosillo",
    "iso:country":"MX",
    "name:spa_x_preferred":[
        "El Campo Santa Cruz"
    ],
    "wof:name":"El Campo Santa Cruz",
    "wof:placetype":"locality"
},
  "geometry": {"coordinates":[-110.952,29.71093],"type":"Point"}
}