{
  "type": "Feature",
  "properties": {
    "gn:admin1_code":"26.0",
    "gn:admin2_code":"30.0",
    "gn:asciiname":"El Nogal",
    "gn:country_code":"MX",
    "gn:dem":291,
    "gn:feature_class":"P",
    "gn:feature_code":"PPL",
    "gn:name":"El Nogal",
    "gn:population":0,
    "gn:timezone":"America/Hermosillo",
    "iso:country":"MX",
    "name:spa_x_preferred":[
        "El Nogal"
    ],
    "wof:name":"El Nogal",
    "wof:placetype":"locality"
},
  "geometry": {"coordinates":[-110.86485999999999,29.29404000000001],"type":"Point"}
}