{
  "type": "Feature",
  "properties": {
    "gn:admin1_code":"10",
    "gn:admin2_code":"14.0",
    "gn:asciiname":"Las Joyitas",
    "gn:country_code":"MX",
    "gn:dem":2037,
    "gn:feature_class":"P",
    "gn:feature_code":"PPL",
    "gn:name":"Las Joyitas",
    "gn:population":0,
    "gn:timezone":"America/Monterrey",
    "iso:country":"MX",
    "name:spa_x_preferred":[
        "Las Joyitas"
    ],
    "wof:name":"Las Joyitas",
    "wof:placetype":"locality"
},
  "geometry": {"coordinates":[-104.22808000000001,22.88931],"type":"Point"}
}