{
  "type": "Feature",
  "properties": {
    "gn:admin1_code":"32",
    "gn:admin2_code":"44.0",
    "gn:asciiname":"Huiscolco",
    "gn:country_code":"MX",
    "gn:dem":1561,
    "gn:feature_class":"P",
    "gn:feature_code":"PPL",
    "gn:name":"Huiscolco",
    "gn:population":0,
    "gn:timezone":"America/Mexico_City",
    "iso:country":"MX",
    "wof:name":"Huiscolco",
    "wof:placetype":"locality"
},
  "geometry": {"coordinates":[-102.94517,21.89403],"type":"Point"}
}