{
  "type": "Feature",
  "properties": {
    "gn:admin1_code":"10",
    "gn:admin2_code":"23.0",
    "gn:asciiname":"La Palma",
    "gn:country_code":"MX",
    "gn:dem":831,
    "gn:feature_class":"P",
    "gn:feature_code":"PPL",
    "gn:name":"La Palma",
    "gn:population":166,
    "gn:timezone":"America/Monterrey",
    "iso:country":"MX",
    "wof:name":"La Palma",
    "wof:placetype":"locality",
    "wof:population":166
},
  "geometry": {"coordinates":[-105.66228,23.43181],"type":"Point"}
}