{
  "type": "Feature",
  "properties": {
    "gn:admin1_code":"12",
    "gn:admin2_code":"16",
    "gn:asciiname":"Camino Real",
    "gn:country_code":"MX",
    "gn:dem":448,
    "gn:feature_class":"P",
    "gn:feature_code":"PPL",
    "gn:name":"Camino Real",
    "gn:population":30,
    "gn:timezone":"America/Mexico_City",
    "iso:country":"MX",
    "wof:name":"Camino Real",
    "wof:placetype":"locality",
    "wof:population":30
},
  "geometry": {"coordinates":[-101.59697,18.32185],"type":"Point"}
}