{
  "type": "Feature",
  "properties": {
    "gn:admin1_code":"30",
    "gn:admin2_code":"124.0",
    "gn:asciiname":"Manantial",
    "gn:country_code":"MX",
    "gn:dem":72,
    "gn:feature_class":"P",
    "gn:feature_code":"PPL",
    "gn:name":"Manantial",
    "gn:population":258,
    "gn:timezone":"America/Mexico_City",
    "iso:country":"MX",
    "wof:name":"Manantial",
    "wof:placetype":"locality",
    "wof:population":258
},
  "geometry": {"coordinates":[-97.30222000000001,20.24389],"type":"Point"}
}