{
  "type": "Feature",
  "properties": {
    "gn:admin1_code":"6",
    "gn:admin2_code":"9.0",
    "gn:asciiname":"Basacheachi",
    "gn:country_code":"MX",
    "gn:dem":2347,
    "gn:feature_class":"P",
    "gn:feature_code":"PPL",
    "gn:name":"Basacheachi",
    "gn:population":0,
    "gn:timezone":"America/Chihuahua",
    "iso:country":"MX",
    "name:spa_x_preferred":[
        "Basacheachi"
    ],
    "wof:name":"Basacheachi",
    "wof:placetype":"locality"
},
  "geometry": {"coordinates":[-107.56806,27.70249],"type":"Point"}
}