{
  "type": "Feature",
  "properties": {
    "gn:admin1_code":"28",
    "gn:admin2_code":"20",
    "gn:asciiname":"Emilio Vazquez Gomez (Agua Fria)",
    "gn:country_code":"MX",
    "gn:dem":543,
    "gn:feature_class":"P",
    "gn:feature_code":"PPL",
    "gn:name":"Emilio V\u00e1zquez G\u00f3mez (Agua Fr\u00eda)",
    "gn:population":51,
    "gn:timezone":"America/Monterrey",
    "iso:country":"MX",
    "name:und_x_variant":[
        "Emilio V\u00e1zquez G\u00f3mez (Agua Fr\u00eda)"
    ],
    "wof:name":"Emilio Vazquez Gomez (Agua Fria)",
    "wof:placetype":"locality",
    "wof:population":51
},
  "geometry": {"coordinates":[-99.6525,24.56028],"type":"Point"}
}