{
  "type": "Feature",
  "properties": {
    "gn:admin1_code":"26",
    "gn:admin2_code":"18.0",
    "gn:asciiname":"Sahuaro Sur",
    "gn:country_code":"MX",
    "gn:dem":24,
    "gn:feature_class":"P",
    "gn:feature_code":"PPL",
    "gn:name":"Sahuaro Sur",
    "gn:population":0,
    "gn:timezone":"America/Hermosillo",
    "iso:country":"MX",
    "name:spa_x_preferred":[
        "Sahuaro Sur"
    ],
    "wof:name":"Sahuaro Sur",
    "wof:placetype":"locality"
},
  "geometry": {"coordinates":[-110.01447,27.50414],"type":"Point"}
}