{
  "type": "Feature",
  "properties": {
    "gn:admin1_code":"26",
    "gn:admin2_code":"66.0",
    "gn:asciiname":"La Duana",
    "gn:country_code":"MX",
    "gn:dem":903,
    "gn:feature_class":"P",
    "gn:feature_code":"PPL",
    "gn:name":"La Duana",
    "gn:population":0,
    "gn:timezone":"America/Hermosillo",
    "iso:country":"MX",
    "name:spa_x_preferred":[
        "La Duana"
    ],
    "wof:name":"La Duana",
    "wof:placetype":"locality"
},
  "geometry": {"coordinates":[-110.16248,29.39856],"type":"Point"}
}