{
  "type": "Feature",
  "properties": {
    "gn:admin1_code":"11",
    "gn:admin2_code":"3.0",
    "gn:asciiname":"Hacienda Prieta",
    "gn:country_code":"MX",
    "gn:dem":2046,
    "gn:feature_class":"P",
    "gn:feature_code":"PPL",
    "gn:name":"Hacienda Prieta",
    "gn:population":4,
    "gn:timezone":"America/Mexico_City",
    "iso:country":"MX",
    "wof:name":"Hacienda Prieta",
    "wof:placetype":"locality",
    "wof:population":4
},
  "geometry": {"coordinates":[-100.67111,20.98111],"type":"Point"}
}