{
  "type": "Feature",
  "properties": {
    "gn:admin1_code":"27",
    "gn:admin2_code":"12.0",
    "gn:asciiname":"Arroyo Hondo",
    "gn:country_code":"MX",
    "gn:dem":7,
    "gn:feature_class":"P",
    "gn:feature_code":"PPL",
    "gn:name":"Arroyo Hondo",
    "gn:population":0,
    "gn:timezone":"America/Mexico_City",
    "iso:country":"MX",
    "name:ceb_x_preferred":[
        "Arroyo Hondo"
    ],
    "name:spa_x_preferred":[
        "Arroyo Hondo"
    ],
    "name:spa_x_variant":[
        "Vicente Guerrero Segunda Secci\u00f3n"
    ],
    "name:swe_x_preferred":[
        "Arroyo Hondo"
    ],
    "wof:name":"Arroyo Hondo",
    "wof:placetype":"locality"
},
  "geometry": {"coordinates":[-92.23191,17.80219],"type":"Point"}
}