{
  "type": "Feature",
  "properties": {
    "gn:admin1_code":"16",
    "gn:admin2_code":"22.0",
    "gn:asciiname":"San Antonio Corrales (Nuevo Coronillas)",
    "gn:country_code":"MX",
    "gn:dem":1879,
    "gn:feature_class":"P",
    "gn:feature_code":"PPL",
    "gn:name":"San Antonio Corrales (Nuevo Coronillas)",
    "gn:population":885,
    "gn:timezone":"America/Mexico_City",
    "iso:country":"MX",
    "wof:name":"San Antonio Corrales (Nuevo Coronillas)",
    "wof:placetype":"locality",
    "wof:population":885
},
  "geometry": {"coordinates":[-101.04472,19.77444],"type":"Point"}
}