{
  "type": "Feature",
  "properties": {
    "gn:admin1_code":"26",
    "gn:admin2_code":"18.0",
    "gn:asciiname":"Postura Dos (Rancho Grande)",
    "gn:country_code":"MX",
    "gn:dem":52,
    "gn:feature_class":"P",
    "gn:feature_code":"PPL",
    "gn:name":"Postura Dos (Rancho Grande)",
    "gn:population":9,
    "gn:timezone":"America/Hermosillo",
    "iso:country":"MX",
    "wof:name":"Postura Dos (Rancho Grande)",
    "wof:placetype":"locality",
    "wof:population":9
},
  "geometry": {"coordinates":[-109.84721999999999,27.43528],"type":"Point"}
}