{
  "type": "Feature",
  "properties": {
    "gn:admin1_code":"27",
    "gn:admin2_code":"5.0",
    "gn:asciiname":"Jose Maria Pino Suarez Primera Seccion",
    "gn:country_code":"MX",
    "gn:dem":9,
    "gn:feature_class":"P",
    "gn:feature_code":"PPL",
    "gn:name":"Jos\u00e9 Mar\u00eda Pino Su\u00e1rez Primera Secci\u00f3n",
    "gn:population":0,
    "gn:timezone":"America/Mexico_City",
    "iso:country":"MX",
    "name:spa_x_preferred":[
        "Jos\u00e9 Mar\u00eda Pino Su\u00e1rez Primera Secci\u00f3n"
    ],
    "wof:name":"Jose Maria Pino Suarez Primera Seccion",
    "wof:placetype":"locality"
},
  "geometry": {"coordinates":[-93.38374,18.35064],"type":"Point"}
}