{
  "type": "Feature",
  "properties": {
    "gn:admin1_code":"24",
    "gn:admin2_code":"50.0",
    "gn:asciiname":"Rodrigo",
    "gn:country_code":"MX",
    "gn:dem":1874,
    "gn:feature_class":"P",
    "gn:feature_code":"PPL",
    "gn:name":"Rodrigo",
    "gn:population":0,
    "gn:timezone":"America/Mexico_City",
    "iso:country":"MX",
    "name:spa_x_preferred":[
        "Rodrigo"
    ],
    "wof:name":"Rodrigo",
    "wof:placetype":"locality"
},
  "geometry": {"coordinates":[-100.95363,21.89158],"type":"Point"}
}