{
  "type": "Feature",
  "properties": {
    "gn:admin1_code":"24",
    "gn:admin2_code":"50.0",
    "gn:asciiname":"Rodrigo",
    "gn:country_code":"MX",
    "gn:dem":1874,
    "gn:feature_class":"P",
    "gn:feature_code":"PPL",
    "gn:name":"Rodrigo",
    "gn:population":0,
    "gn:timezone":"America/Mexico_City",
    "iso:country":"MX",
    "name:bre_x_preferred":[
        "Rodrigo"
    ],
    "name:ces_x_preferred":[
        "Rodrigo"
    ],
    "name:deu_x_preferred":[
        "Rodrigo"
    ],
    "name:fin_x_preferred":[
        "Rodrigo"
    ],
    "name:fra_x_preferred":[
        "Rodrigo"
    ],
    "name:ita_x_preferred":[
        "Rodrigo"
    ],
    "name:jpn_x_preferred":[
        "\u30ed\u30c9\u30ea\u30b4"
    ],
    "name:nld_x_preferred":[
        "Rodrigo"
    ],
    "name:nor_x_preferred":[
        "Rodrigo"
    ],
    "name:pol_x_preferred":[
        "Rodrigo"
    ],
    "name:por_x_preferred":[
        "Rodrigo"
    ],
    "name:rus_x_preferred":[
        "\u0420\u043e\u0434\u0440\u0438\u0433\u043e"
    ],
    "name:spa_x_preferred":[
        "Rodrigo"
    ],
    "name:swe_x_preferred":[
        "Rodrigo"
    ],
    "name:zho_x_preferred":[
        "\u7f57\u5fb7\u91cc\u6208"
    ],
    "wof:name":"Rodrigo",
    "wof:placetype":"locality"
},
  "geometry": {"coordinates":[-100.95363,21.89158],"type":"Point"}
}