{
  "type": "Feature",
  "properties": {
    "gn:admin1_code":"32.0",
    "gn:admin2_code":"10.0",
    "gn:asciiname":"Pozo Numero Dos",
    "gn:country_code":"MX",
    "gn:dem":2068,
    "gn:feature_class":"P",
    "gn:feature_code":"PPL",
    "gn:name":"Pozo N\u00famero Dos",
    "gn:population":0,
    "gn:timezone":"America/Mexico_City",
    "iso:country":"MX",
    "name:spa_x_preferred":[
        "Pozo N\u00famero Dos"
    ],
    "wof:name":"Pozo Numero Dos",
    "wof:placetype":"locality"
},
  "geometry": {"coordinates":[-103.02745,23.40639],"type":"Point"}
}