{
  "type": "Feature",
  "properties": {
    "gn:admin1_code":"16",
    "gn:admin2_code":"13.0",
    "gn:asciiname":"La Vinatita",
    "gn:country_code":"MX",
    "gn:dem":656,
    "gn:feature_class":"P",
    "gn:feature_code":"PPL",
    "gn:name":"La Vinatita",
    "gn:population":9,
    "gn:timezone":"America/Mexico_City",
    "iso:country":"MX",
    "wof:name":"La Vinatita",
    "wof:placetype":"locality",
    "wof:population":9
},
  "geometry": {"coordinates":[-101.05583,19.0275],"type":"Point"}
}