{
  "type": "Feature",
  "properties": {
    "gn:admin1_code":"25",
    "gn:admin2_code":"1.0",
    "gn:asciiname":"Rancho El Descanso",
    "gn:country_code":"MX",
    "gn:dem":6,
    "gn:feature_class":"P",
    "gn:feature_code":"PPL",
    "gn:name":"Rancho El Descanso",
    "gn:population":0,
    "gn:timezone":"America/Mazatlan",
    "iso:country":"MX",
    "wof:name":"Rancho El Descanso",
    "wof:placetype":"locality"
},
  "geometry": {"coordinates":[-109.06667,26.16667],"type":"Point"}
}