{
  "type": "Feature",
  "properties": {
    "gn:admin1_code":"2",
    "gn:admin2_code":"1.0",
    "gn:asciiname":"La Poza",
    "gn:country_code":"MX",
    "gn:dem":103,
    "gn:feature_class":"P",
    "gn:feature_code":"PPL",
    "gn:name":"La Poza",
    "gn:population":0,
    "gn:timezone":"America/Tijuana",
    "iso:country":"MX",
    "name:spa_x_preferred":[
        "La Poza"
    ],
    "name:und_x_variant":[
        "Rancho La Poza"
    ],
    "wof:name":"La Poza",
    "wof:placetype":"locality"
},
  "geometry": {"coordinates":[-116.50931,31.57619],"type":"Point"}
}