{
  "type": "Feature",
  "properties": {
    "gn:admin1_code":"20",
    "gn:admin2_code":"476.0",
    "gn:asciiname":"Santo Tomas",
    "gn:country_code":"MX",
    "gn:dem":1965,
    "gn:feature_class":"P",
    "gn:feature_code":"PPL",
    "gn:name":"Santo Tom\u00e1s",
    "gn:population":9,
    "gn:timezone":"America/Mexico_City",
    "iso:country":"MX",
    "name:und_x_variant":[
        "Santo Tom\u00e1s"
    ],
    "wof:name":"Santo Tomas",
    "wof:placetype":"locality",
    "wof:population":9
},
  "geometry": {"coordinates":[-97.69667,18.02167],"type":"Point"}
}