{
  "type": "Feature",
  "properties": {
    "gn:admin1_code":"14",
    "gn:admin2_code":"125",
    "gn:asciiname":"Coscusillo",
    "gn:country_code":"MX",
    "gn:dem":2067,
    "gn:feature_class":"P",
    "gn:feature_code":"PPL",
    "gn:name":"Coscusillo",
    "gn:population":33,
    "gn:timezone":"America/Mexico_City",
    "iso:country":"MX",
    "wof:name":"Coscusillo",
    "wof:placetype":"locality",
    "wof:population":33
},
  "geometry": {"coordinates":[-102.52778000000001,20.82028],"type":"Point"}
}