{
  "type": "Feature",
  "properties": {
    "gn:admin1_code":"22",
    "gn:admin2_code":"8.0",
    "gn:asciiname":"Lo de Casas",
    "gn:country_code":"MX",
    "gn:dem":1977,
    "gn:feature_class":"P",
    "gn:feature_code":"PPL",
    "gn:name":"Lo de Casas",
    "gn:population":0,
    "gn:timezone":"America/Mexico_City",
    "iso:country":"MX",
    "wof:name":"Lo de Casas",
    "wof:placetype":"locality"
},
  "geometry": {"coordinates":[-100.34999999999999,20.46667],"type":"Point"}
}