{
  "type": "Feature",
  "properties": {
    "gn:admin1_code":"30.0",
    "gn:admin2_code":"161.0",
    "gn:asciiname":"El Chijolar",
    "gn:country_code":"MX",
    "gn:dem":81,
    "gn:feature_class":"P",
    "gn:feature_code":"PPL",
    "gn:name":"El Chijolar",
    "gn:population":4,
    "gn:timezone":"America/Mexico_City",
    "iso:country":"MX",
    "name:spa_x_preferred":[
        "El Chijolar"
    ],
    "wof:name":"El Chijolar",
    "wof:placetype":"locality",
    "wof:population":4
},
  "geometry": {"coordinates":[-98.20031,21.61406],"type":"Point"}
}