{
  "type": "Feature",
  "properties": {
    "gn:admin1_code":"30",
    "gn:admin2_code":"142",
    "gn:asciiname":"San Rafael",
    "gn:country_code":"MX",
    "gn:dem":60,
    "gn:feature_class":"P",
    "gn:feature_code":"PPL",
    "gn:name":"San Rafael",
    "gn:population":20,
    "gn:timezone":"America/Mexico_City",
    "iso:country":"MX",
    "wof:name":"San Rafael",
    "wof:placetype":"locality",
    "wof:population":20
},
  "geometry": {"coordinates":[-95.05916999999999,17.75639],"type":"Point"}
}