{
  "type": "Feature",
  "properties": {
    "gn:admin1_code":"16",
    "gn:admin2_code":"10.0",
    "gn:asciiname":"El Encino",
    "gn:country_code":"MX",
    "gn:dem":932,
    "gn:feature_class":"P",
    "gn:feature_code":"PPL",
    "gn:name":"El Encino",
    "gn:population":5,
    "gn:timezone":"America/Mexico_City",
    "iso:country":"MX",
    "wof:name":"El Encino",
    "wof:placetype":"locality",
    "wof:population":5
},
  "geometry": {"coordinates":[-102.31389,18.33861],"type":"Point"}
}