{
  "type": "Feature",
  "properties": {
    "gn:admin1_code":"11",
    "gn:admin2_code":"46.0",
    "gn:asciiname":"Tinaja de Pastores",
    "gn:country_code":"MX",
    "gn:dem":1741,
    "gn:feature_class":"P",
    "gn:feature_code":"PPL",
    "gn:name":"Tinaja de Pastores",
    "gn:population":0,
    "gn:timezone":"America/Mexico_City",
    "iso:country":"MX",
    "name:und_x_variant":[
        "La Tinaja",
        "Tinaja",
        "Tinaja de Pastores"
    ],
    "wof:name":"Tinaja de Pastores",
    "wof:placetype":"locality"
},
  "geometry": {"coordinates":[-101.06202,20.19839],"type":"Point"}
}