{
  "type": "Feature",
  "properties": {
    "gn:admin1_code":"19.0",
    "gn:asciiname":"Valladolid",
    "gn:country_code":"MX",
    "gn:dem":466,
    "gn:feature_class":"P",
    "gn:feature_code":"PPL",
    "gn:name":"Valladolid",
    "gn:population":0,
    "gn:timezone":"America/Monterrey",
    "iso:country":"MX",
    "name:spa_x_preferred":[
        "Valladolid"
    ],
    "wof:name":"Valladolid",
    "wof:placetype":"locality"
},
  "geometry": {"coordinates":[-99.74601,24.99205],"type":"Point"}
}