{
  "type": "Feature",
  "properties": {
    "gn:admin1_code":"6",
    "gn:admin2_code":"19.0",
    "gn:asciiname":"Aigrias (El Puente)",
    "gn:country_code":"MX",
    "gn:dem":1489,
    "gn:feature_class":"P",
    "gn:feature_code":"PPL",
    "gn:name":"Aigrias (El Puente)",
    "gn:population":7,
    "gn:timezone":"America/Chihuahua",
    "iso:country":"MX",
    "wof:name":"Aigrias (El Puente)",
    "wof:placetype":"locality",
    "wof:population":7
},
  "geometry": {"coordinates":[-106.23103,28.18464],"type":"Point"}
}