{
  "type": "Feature",
  "properties": {
    "gn:admin1_code":"7",
    "gn:admin2_code":"24.0",
    "gn:asciiname":"Las Liebres",
    "gn:country_code":"MX",
    "gn:dem":1132,
    "gn:feature_class":"P",
    "gn:feature_code":"PPL",
    "gn:name":"Las Liebres",
    "gn:population":0,
    "gn:timezone":"America/Monterrey",
    "iso:country":"MX",
    "name:und_x_variant":[
        "Liebres",
        "Las Liebres"
    ],
    "wof:name":"Las Liebres",
    "wof:placetype":"locality"
},
  "geometry": {"coordinates":[-101.90239,25.79734],"type":"Point"}
}