{
  "type": "Feature",
  "properties": {
    "gn:admin1_code":"28.0",
    "gn:admin2_code":"13.0",
    "gn:asciiname":"El Yaqui",
    "gn:country_code":"MX",
    "gn:dem":177,
    "gn:feature_class":"P",
    "gn:feature_code":"PPL",
    "gn:name":"El Yaqui",
    "gn:population":0,
    "gn:timezone":"America/Monterrey",
    "iso:country":"MX",
    "name:spa_x_preferred":[
        "El Yaqui"
    ],
    "wof:name":"El Yaqui",
    "wof:placetype":"locality"
},
  "geometry": {"coordinates":[-99.00593000000001,23.87334],"type":"Point"}
}