{
  "type": "Feature",
  "properties": {
    "gn:admin1_code":"20",
    "gn:admin2_code":"494",
    "gn:asciiname":"Canada Hoja Mano de Leon",
    "gn:country_code":"MX",
    "gn:dem":2767,
    "gn:feature_class":"P",
    "gn:feature_code":"PPL",
    "gn:name":"Ca\u00f1ada Hoja Mano de Le\u00f3n",
    "gn:population":19,
    "gn:timezone":"America/Mexico_City",
    "iso:country":"MX",
    "name:und_x_variant":[
        "Ca\u00f1ada Hoja Mano de Le\u00f3n"
    ],
    "wof:name":"Canada Hoja Mano de Leon",
    "wof:placetype":"locality",
    "wof:population":19
},
  "geometry": {"coordinates":[-96.94389,17.02028],"type":"Point"}
}