{
  "type": "Feature",
  "properties": {
    "gn:admin1_code":"15.0",
    "gn:asciiname":"El Rancho Boca de la Barranca",
    "gn:country_code":"MX",
    "gn:dem":380,
    "gn:feature_class":"P",
    "gn:feature_code":"PPL",
    "gn:name":"El Rancho Boca de la Barranca",
    "gn:population":0,
    "gn:timezone":"America/Mexico_City",
    "iso:country":"MX",
    "name:spa_x_preferred":[
        "El Rancho Boca de la Barranca"
    ],
    "name:und_x_variant":[
        "Boca de la Barranca"
    ],
    "wof:name":"El Rancho Boca de la Barranca",
    "wof:placetype":"locality"
},
  "geometry": {"coordinates":[-100.48336999999999,18.53207],"type":"Point"}
}