{
  "type": "Feature",
  "properties": {
    "gn:admin1_code":"19.0",
    "gn:asciiname":"El Piquete",
    "gn:country_code":"MX",
    "gn:dem":1096,
    "gn:feature_class":"P",
    "gn:feature_code":"PPL",
    "gn:name":"El Piquete",
    "gn:population":0,
    "gn:timezone":"America/Monterrey",
    "iso:country":"MX",
    "name:spa_x_preferred":[
        "El Piquete"
    ],
    "wof:name":"El Piquete",
    "wof:placetype":"locality"
},
  "geometry": {"coordinates":[-99.82635000000001,24.11229],"type":"Point"}
}