{
  "type": "Feature",
  "properties": {
    "gn:admin1_code":"30",
    "gn:admin2_code":"76.0",
    "gn:asciiname":"Tlatlazoquico",
    "gn:country_code":"MX",
    "gn:dem":337,
    "gn:feature_class":"P",
    "gn:feature_code":"PPL",
    "gn:name":"Tlatlazoquico",
    "gn:population":509,
    "gn:timezone":"America/Mexico_City",
    "iso:country":"MX",
    "wof:name":"Tlatlazoquico",
    "wof:placetype":"locality",
    "wof:population":509
},
  "geometry": {"coordinates":[-98.35639,20.82083],"type":"Point"}
}