{
  "type": "Feature",
  "properties": {
    "gn:admin1_code":"26",
    "gn:admin2_code":"68.0",
    "gn:asciiname":"El Represito",
    "gn:country_code":"MX",
    "gn:dem":603,
    "gn:feature_class":"P",
    "gn:feature_code":"PPL",
    "gn:name":"El Represito",
    "gn:population":0,
    "gn:timezone":"America/Hermosillo",
    "iso:country":"MX",
    "name:spa_x_preferred":[
        "El Represito"
    ],
    "wof:name":"El Represito",
    "wof:placetype":"locality"
},
  "geometry": {"coordinates":[-110.02837,28.97119],"type":"Point"}
}