{
  "type": "Feature",
  "properties": {
    "gn:admin1_code":"24",
    "gn:admin2_code":"24.0",
    "gn:asciiname":"Cerrito Colorado",
    "gn:country_code":"MX",
    "gn:dem":968,
    "gn:feature_class":"P",
    "gn:feature_code":"PPL",
    "gn:name":"Cerrito Colorado",
    "gn:population":0,
    "gn:timezone":"America/Mexico_City",
    "iso:country":"MX",
    "name:spa_x_preferred":[
        "Cerrito Colorado"
    ],
    "wof:name":"Cerrito Colorado",
    "wof:placetype":"locality"
},
  "geometry": {"coordinates":[-99.88773,21.84544],"type":"Point"}
}