{
  "type": "Feature",
  "properties": {
    "gn:admin1_code":"25",
    "gn:admin2_code":"14.0",
    "gn:asciiname":"El Pato",
    "gn:country_code":"MX",
    "gn:dem":224,
    "gn:feature_class":"P",
    "gn:feature_code":"PPL",
    "gn:name":"El Pato",
    "gn:population":0,
    "gn:timezone":"America/Mazatlan",
    "iso:country":"MX",
    "name:spa_x_preferred":[
        "El Pato"
    ],
    "wof:name":"El Pato",
    "wof:placetype":"locality"
},
  "geometry": {"coordinates":[-105.54096,23.004],"type":"Point"}
}