{
  "type": "Feature",
  "properties": {
    "gn:admin1_code":"12",
    "gn:admin2_code":"46.0",
    "gn:asciiname":"San Vicente (San Vicente de Benitez)",
    "gn:country_code":"MX",
    "gn:dem":415,
    "gn:feature_class":"P",
    "gn:feature_code":"PPL",
    "gn:name":"San Vicente (San Vicente de Ben\u00edtez)",
    "gn:population":82,
    "gn:timezone":"America/Mexico_City",
    "iso:country":"MX",
    "name:und_x_variant":[
        "San Vicente (San Vicente de Ben\u00edtez)"
    ],
    "wof:name":"San Vicente (San Vicente de Benitez)",
    "wof:placetype":"locality",
    "wof:population":82
},
  "geometry": {"coordinates":[-98.41003000000001,16.71063],"type":"Point"}
}