{
  "type": "Feature",
  "properties": {
    "gn:admin1_code":"12",
    "gn:admin2_code":"41.0",
    "gn:asciiname":"Colonia Jardin de Cafetales",
    "gn:country_code":"MX",
    "gn:dem":1069,
    "gn:feature_class":"P",
    "gn:feature_code":"PPL",
    "gn:name":"Colonia Jard\u00edn de Cafetales",
    "gn:population":66,
    "gn:timezone":"America/Mexico_City",
    "iso:country":"MX",
    "name:und_x_variant":[
        "Colonia Jard\u00edn de Cafetales"
    ],
    "wof:name":"Colonia Jardin de Cafetales",
    "wof:placetype":"locality",
    "wof:population":66
},
  "geometry": {"coordinates":[-98.75221999999999,17.04528],"type":"Point"}
}