{
  "type": "Feature",
  "properties": {
    "gn:admin1_code":"25",
    "gn:admin2_code":"13.0",
    "gn:asciiname":"Los Mazates",
    "gn:country_code":"MX",
    "gn:dem":111,
    "gn:feature_class":"P",
    "gn:feature_code":"PPL",
    "gn:name":"Los Mazates",
    "gn:population":0,
    "gn:timezone":"America/Mazatlan",
    "iso:country":"MX",
    "wof:name":"Los Mazates",
    "wof:placetype":"locality"
},
  "geometry": {"coordinates":[-108.01667,25.63333],"type":"Point"}
}