{
  "type": "Feature",
  "properties": {
    "gn:admin1_code":"6.0",
    "gn:admin2_code":"40.0",
    "gn:asciiname":"La Lagunita de Tenunez",
    "gn:country_code":"MX",
    "gn:dem":1973,
    "gn:feature_class":"P",
    "gn:feature_code":"PPL",
    "gn:name":"La Lagunita de Ten\u00fa\u00f1ez",
    "gn:population":0,
    "gn:timezone":"America/Chihuahua",
    "iso:country":"MX",
    "name:spa_x_preferred":[
        "La Lagunita de Ten\u00fa\u00f1ez"
    ],
    "wof:name":"La Lagunita de Tenunez",
    "wof:placetype":"locality"
},
  "geometry": {"coordinates":[-108.29788000000001,29.20894],"type":"Point"}
}