{
  "type": "Feature",
  "properties": {
    "gn:admin1_code":"32",
    "gn:admin2_code":"10.0",
    "gn:asciiname":"Presa del Mezquite (Tapias del Mezquite)",
    "gn:country_code":"MX",
    "gn:dem":2068,
    "gn:feature_class":"P",
    "gn:feature_code":"PPL",
    "gn:name":"Presa del Mezquite (Tapias del Mezquite)",
    "gn:population":244,
    "gn:timezone":"America/Mexico_City",
    "iso:country":"MX",
    "wof:name":"Presa del Mezquite (Tapias del Mezquite)",
    "wof:placetype":"locality",
    "wof:population":244
},
  "geometry": {"coordinates":[-102.57277999999999,23.41611],"type":"Point"}
}