{
  "type": "Feature",
  "properties": {
    "gn:admin1_code":"5",
    "gn:admin2_code":"59",
    "gn:asciiname":"Primavera",
    "gn:country_code":"MX",
    "gn:dem":526,
    "gn:feature_class":"P",
    "gn:feature_code":"PPL",
    "gn:name":"Primavera",
    "gn:population":9,
    "gn:timezone":"America/Mexico_City",
    "iso:country":"MX",
    "name:bel_x_preferred":[
        "\u0412\u044f\u0441\u043d\u0430"
    ],
    "name:bre_x_preferred":[
        "Primavera"
    ],
    "name:cat_x_preferred":[
        "Primavera"
    ],
    "name:ceb_x_preferred":[
        "Primavera"
    ],
    "name:deu_x_preferred":[
        "Primavera"
    ],
    "name:fas_x_preferred":[
        "\u067e\u0631\u06cc\u0645\u0627\u0648\u0631\u0627"
    ],
    "name:fin_x_preferred":[
        "Primavera"
    ],
    "name:fra_x_preferred":[
        "Primavera"
    ],
    "name:ita_x_preferred":[
        "Primavera"
    ],
    "name:jpn_x_preferred":[
        "\u30d7\u30ea\u30de\u30f4\u30a7\u30fc\u30e9"
    ],
    "name:kor_x_preferred":[
        "\ud504\ub9ac\ub9c8\ubca0\ub77c"
    ],
    "name:nld_x_preferred":[
        "Primavera"
    ],
    "name:nor_x_preferred":[
        "Primavera"
    ],
    "name:por_x_preferred":[
        "Primavera"
    ],
    "name:rus_x_preferred":[
        "\u0412\u0435\u0441\u043d\u0430"
    ],
    "name:slk_x_preferred":[
        "Primavera"
    ],
    "name:spa_x_preferred":[
        "Primavera"
    ],
    "name:srp_x_preferred":[
        "\u041f\u0440\u0438\u043c\u0430\u0432\u0435\u0440\u0430"
    ],
    "name:swe_x_preferred":[
        "Primavera"
    ],
    "name:ukr_x_preferred":[
        "\u0412\u0435\u0441\u043d\u0430"
    ],
    "name:vol_x_preferred":[
        "Primavera"
    ],
    "wof:name":"Primavera",
    "wof:placetype":"locality",
    "wof:population":9
},
  "geometry": {"coordinates":[-91.65000000000001,16.77111],"type":"Point"}
}