{
  "type": "Feature",
  "properties": {
    "gn:admin1_code":"5",
    "gn:admin2_code":"59",
    "gn:asciiname":"Primavera",
    "gn:country_code":"MX",
    "gn:dem":526,
    "gn:feature_class":"P",
    "gn:feature_code":"PPL",
    "gn:name":"Primavera",
    "gn:population":9,
    "gn:timezone":"America/Mexico_City",
    "iso:country":"MX",
    "wof:name":"Primavera",
    "wof:placetype":"locality",
    "wof:population":9
},
  "geometry": {"coordinates":[-91.65000000000001,16.77111],"type":"Point"}
}