{
  "type": "Feature",
  "properties": {
    "gn:admin1_code":"30",
    "gn:admin2_code":"91.0",
    "gn:asciiname":"Rancho Petrolero (La Herradura)",
    "gn:country_code":"MX",
    "gn:dem":44,
    "gn:feature_class":"P",
    "gn:feature_code":"PPL",
    "gn:name":"Rancho Petrolero (La Herradura)",
    "gn:population":5,
    "gn:timezone":"America/Mexico_City",
    "iso:country":"MX",
    "wof:name":"Rancho Petrolero (La Herradura)",
    "wof:placetype":"locality",
    "wof:population":5
},
  "geometry": {"coordinates":[-95.05083,17.47833],"type":"Point"}
}