{
  "type": "Feature",
  "properties": {
    "gn:admin1_code":"13",
    "gn:admin2_code":"10",
    "gn:asciiname":"Ejido de San Luis",
    "gn:country_code":"MX",
    "gn:dem":2141,
    "gn:feature_class":"P",
    "gn:feature_code":"PPL",
    "gn:name":"Ejido de San Luis",
    "gn:population":28,
    "gn:timezone":"America/Mexico_City",
    "iso:country":"MX",
    "wof:name":"Ejido de San Luis",
    "wof:placetype":"locality",
    "wof:population":28
},
  "geometry": {"coordinates":[-99.21299,20.03613],"type":"Point"}
}