{
  "type": "Feature",
  "properties": {
    "gn:admin1_code":"30",
    "gn:admin2_code":"123",
    "gn:asciiname":"Los Huastecos",
    "gn:country_code":"MX",
    "gn:dem":13,
    "gn:feature_class":"P",
    "gn:feature_code":"PPL",
    "gn:name":"Los Huastecos",
    "gn:population":30,
    "gn:timezone":"America/Mexico_City",
    "iso:country":"MX",
    "wof:name":"Los Huastecos",
    "wof:placetype":"locality",
    "wof:population":30
},
  "geometry": {"coordinates":[-98.31972,21.99222],"type":"Point"}
}