{
  "type": "Feature",
  "properties": {
    "gn:admin1_code":"1",
    "gn:admin2_code":"5.0",
    "gn:asciiname":"Paseos de las Haciendas [Fraccionamiento]",
    "gn:country_code":"MX",
    "gn:dem":1901,
    "gn:feature_class":"P",
    "gn:feature_code":"PPL",
    "gn:name":"Paseos de las Haciendas [Fraccionamiento]",
    "gn:population":1596,
    "gn:timezone":"America/Mexico_City",
    "iso:country":"MX",
    "wof:name":"Paseos de las Haciendas [Fraccionamiento]",
    "wof:placetype":"locality",
    "wof:population":1596
},
  "geometry": {"coordinates":[-102.34361,21.99222],"type":"Point"}
}