{
  "type": "Feature",
  "properties": {
    "gn:admin1_code":"16.0",
    "gn:admin2_code":"88.0",
    "gn:asciiname":"Jamaica",
    "gn:country_code":"MX",
    "gn:dem":1895,
    "gn:feature_class":"P",
    "gn:feature_code":"PPL",
    "gn:name":"Jamaica",
    "gn:population":0,
    "gn:timezone":"America/Mexico_City",
    "iso:country":"MX",
    "name:spa_x_preferred":[
        "Jamaica"
    ],
    "wof:name":"Jamaica",
    "wof:placetype":"locality"
},
  "geometry": {"coordinates":[-101.13486,19.85577],"type":"Point"}
}