{
  "type": "Feature",
  "properties": {
    "gn:admin1_code":"14.0",
    "gn:admin2_code":"87.0",
    "gn:asciiname":"La Mesa de los Caballos",
    "gn:country_code":"MX",
    "gn:dem":2432,
    "gn:feature_class":"P",
    "gn:feature_code":"PPL",
    "gn:name":"La Mesa de los Caballos",
    "gn:population":0,
    "gn:timezone":"America/Mexico_City",
    "iso:country":"MX",
    "name:spa_x_preferred":[
        "La Mesa de los Caballos"
    ],
    "wof:name":"La Mesa de los Caballos",
    "wof:placetype":"locality"
},
  "geometry": {"coordinates":[-103.19584,19.21923],"type":"Point"}
}