{
  "type": "Feature",
  "properties": {
    "gn:admin1_code":"21.0",
    "gn:admin2_code":"164.0",
    "gn:asciiname":"Actipan",
    "gn:country_code":"MX",
    "gn:dem":2199,
    "gn:feature_class":"P",
    "gn:feature_code":"PPL",
    "gn:name":"Actipan",
    "gn:population":0,
    "gn:timezone":"America/Mexico_City",
    "iso:country":"MX",
    "name:spa_x_preferred":[
        "Actipan"
    ],
    "name:spa_x_variant":[
        "San Pablo Actipan"
    ],
    "wof:name":"Actipan",
    "wof:placetype":"locality"
},
  "geometry": {"coordinates":[-97.90252,18.93689],"type":"Point"}
}