{
  "type": "Feature",
  "properties": {
    "gn:admin1_code":"5",
    "gn:admin2_code":"108",
    "gn:asciiname":"Buenavista",
    "gn:country_code":"MX",
    "gn:dem":663,
    "gn:feature_class":"P",
    "gn:feature_code":"PPL",
    "gn:name":"Buenavista",
    "gn:population":11,
    "gn:timezone":"America/Mexico_City",
    "iso:country":"MX",
    "wof:name":"Buenavista",
    "wof:placetype":"locality",
    "wof:population":11
},
  "geometry": {"coordinates":[-93.42444,16.33222],"type":"Point"}
}