{
  "type": "Feature",
  "properties": {
    "gn:admin1_code":"20",
    "gn:admin2_code":"569.0",
    "gn:asciiname":"La Paz",
    "gn:country_code":"MX",
    "gn:dem":2094,
    "gn:feature_class":"P",
    "gn:feature_code":"PPL",
    "gn:name":"La Paz",
    "gn:population":179,
    "gn:timezone":"America/Mexico_City",
    "iso:country":"MX",
    "wof:name":"La Paz",
    "wof:placetype":"locality",
    "wof:population":179
},
  "geometry": {"coordinates":[-97.14654,17.28908],"type":"Point"}
}