{
  "type": "Feature",
  "properties": {
    "gn:admin1_code":"30",
    "gn:admin2_code":"212",
    "gn:asciiname":"Arturo Martinez Vazquez",
    "gn:country_code":"MX",
    "gn:dem":92,
    "gn:feature_class":"P",
    "gn:feature_code":"PPL",
    "gn:name":"Arturo Mart\u00ednez V\u00e1zquez",
    "gn:population":13,
    "gn:timezone":"America/Mexico_City",
    "iso:country":"MX",
    "name:und_x_variant":[
        "Arturo Mart\u00ednez V\u00e1zquez"
    ],
    "wof:name":"Arturo Martinez Vazquez",
    "wof:placetype":"locality",
    "wof:population":13
},
  "geometry": {"coordinates":[-95.52139,17.64389],"type":"Point"}
}