{
  "type": "Feature",
  "properties": {
    "gn:admin1_code":"16",
    "gn:admin2_code":"83.0",
    "gn:asciiname":"Huaricho",
    "gn:country_code":"MX",
    "gn:dem":1614,
    "gn:feature_class":"P",
    "gn:feature_code":"PPL",
    "gn:name":"Huaricho",
    "gn:population":66,
    "gn:timezone":"America/Mexico_City",
    "iso:country":"MX",
    "wof:name":"Huaricho",
    "wof:placetype":"locality",
    "wof:population":66
},
  "geometry": {"coordinates":[-102.45639,19.38],"type":"Point"}
}