{
  "type": "Feature",
  "properties": {
    "gn:admin1_code":"11.0",
    "gn:admin2_code":"25.0",
    "gn:asciiname":"El Raton",
    "gn:cc2":"MX",
    "gn:country_code":"MX",
    "gn:dem":1772,
    "gn:feature_class":"P",
    "gn:feature_code":"PPL",
    "gn:name":"El Rat\u00f3n",
    "gn:population":51,
    "gn:timezone":"America/Mexico_City",
    "iso:country":"MX",
    "name:und_x_variant":[
        "Puerta",
        "El Reto\u00f1o"
    ],
    "wof:name":"El Raton",
    "wof:placetype":"locality",
    "wof:population":51
},
  "geometry": {"coordinates":[-101.80083,21.04389],"type":"Point"}
}