{
  "type": "Feature",
  "properties": {
    "gn:admin1_code":"14.0",
    "gn:admin2_code":"60.0",
    "gn:asciiname":"El Ojo de Aqua",
    "gn:country_code":"MX",
    "gn:dem":1794,
    "gn:feature_class":"P",
    "gn:feature_code":"PPL",
    "gn:name":"El Ojo de Aqua",
    "gn:population":0,
    "gn:timezone":"America/Mexico_City",
    "iso:country":"MX",
    "name:spa_x_preferred":[
        "El Ojo de Aqua"
    ],
    "wof:name":"El Ojo de Aqua",
    "wof:placetype":"locality"
},
  "geometry": {"coordinates":[-102.72369,21.30965],"type":"Point"}
}