{
  "type": "Feature",
  "properties": {
    "gn:admin1_code":"25.0",
    "gn:admin2_code":"1.0",
    "gn:asciiname":"Las Glorias",
    "gn:country_code":"MX",
    "gn:dem":11,
    "gn:feature_class":"P",
    "gn:feature_code":"PPL",
    "gn:name":"Las Glorias",
    "gn:population":0,
    "gn:timezone":"America/Mazatlan",
    "iso:country":"MX",
    "name:spa_x_preferred":[
        "Las Glorias"
    ],
    "wof:name":"Las Glorias",
    "wof:placetype":"locality"
},
  "geometry": {"coordinates":[-109.04701,25.79405],"type":"Point"}
}