{
  "type": "Feature",
  "properties": {
    "gn:admin1_code":"20",
    "gn:admin2_code":"482.0",
    "gn:asciiname":"Yuyaquita",
    "gn:country_code":"MX",
    "gn:dem":24,
    "gn:feature_class":"P",
    "gn:feature_code":"PPL",
    "gn:name":"Yuyaquita",
    "gn:population":111,
    "gn:timezone":"America/Mexico_City",
    "iso:country":"MX",
    "wof:name":"Yuyaquita",
    "wof:placetype":"locality",
    "wof:population":111
},
  "geometry": {"coordinates":[-97.99805000000001,16.21651],"type":"Point"}
}