{
  "type": "Feature",
  "properties": {
    "gn:admin1_code":"15.0",
    "gn:admin2_code":"105.0",
    "gn:asciiname":"Rincon Grande",
    "gn:country_code":"MX",
    "gn:dem":455,
    "gn:feature_class":"P",
    "gn:feature_code":"PPL",
    "gn:name":"Rinc\u00f3n Grande",
    "gn:population":502,
    "gn:timezone":"America/Mexico_City",
    "iso:country":"MX",
    "name:spa_x_preferred":[
        "Rinc\u00f3n Grande"
    ],
    "wof:name":"Rincon Grande",
    "wof:placetype":"locality",
    "wof:population":502
},
  "geometry": {"coordinates":[-100.34815999999999,18.44739],"type":"Point"}
}