{
  "type": "Feature",
  "properties": {
    "gn:admin1_code":"10",
    "gn:admin2_code":"2",
    "gn:asciiname":"El Tablon",
    "gn:country_code":"MX",
    "gn:dem":1812,
    "gn:feature_class":"P",
    "gn:feature_code":"PPL",
    "gn:name":"El Tabl\u00f3n",
    "gn:population":31,
    "gn:timezone":"America/Monterrey",
    "iso:country":"MX",
    "name:und_x_variant":[
        "El Tabl\u00f3n"
    ],
    "wof:name":"El Tablon",
    "wof:placetype":"locality",
    "wof:population":31
},
  "geometry": {"coordinates":[-106.55981,25.10553],"type":"Point"}
}