{
  "type": "Feature",
  "properties": {
    "gn:admin1_code":"5",
    "gn:admin2_code":"59.0",
    "gn:asciiname":"Nuevo Mariscal",
    "gn:country_code":"MX",
    "gn:dem":138,
    "gn:feature_class":"P",
    "gn:feature_code":"PPL",
    "gn:name":"Nuevo Mariscal",
    "gn:population":616,
    "gn:timezone":"America/Mexico_City",
    "iso:country":"MX",
    "wof:name":"Nuevo Mariscal",
    "wof:placetype":"locality",
    "wof:population":616
},
  "geometry": {"coordinates":[-91.18444,16.97889],"type":"Point"}
}