{
  "type": "Feature",
  "properties": {
    "gn:admin1_code":"5",
    "gn:admin2_code":"93.0",
    "gn:asciiname":"Banavil",
    "gn:country_code":"MX",
    "gn:dem":2419,
    "gn:feature_class":"P",
    "gn:feature_code":"PPL",
    "gn:name":"Banavil",
    "gn:population":181,
    "gn:timezone":"America/Mexico_City",
    "iso:country":"MX",
    "wof:name":"Banavil",
    "wof:placetype":"locality",
    "wof:population":181
},
  "geometry": {"coordinates":[-92.51390000000001,16.78342],"type":"Point"}
}