{
  "type": "Feature",
  "properties": {
    "gn:admin1_code":"15.0",
    "gn:admin2_code":"124.0",
    "gn:asciiname":"Claudio Rojas",
    "gn:country_code":"MX",
    "gn:dem":2665,
    "gn:feature_class":"P",
    "gn:feature_code":"PPL",
    "gn:name":"Claudio Rojas",
    "gn:population":0,
    "gn:timezone":"America/Mexico_City",
    "iso:country":"MX",
    "name:ara_x_preferred":[
        "\u0643\u0644\u0627\u0648\u062f\u064a\u0648 \u0631\u0648\u062e\u0633"
    ],
    "name:ita_x_preferred":[
        "Claudio Rojas"
    ],
    "name:spa_x_preferred":[
        "Claudio Rojas"
    ],
    "name:spa_x_variant":[
        "Claudio Ariel Rojas"
    ],
    "name:tgk_x_preferred":[
        "\u041a\u043b\u0430\u0443\u0434\u0438\u043e \u0420\u043e\u0445\u0430\u0441"
    ],
    "wof:name":"Claudio Rojas",
    "wof:placetype":"locality"
},
  "geometry": {"coordinates":[-100.08093,19.60204],"type":"Point"}
}