{
  "type": "Feature",
  "properties": {
    "gn:admin1_code":"25",
    "gn:admin2_code":"10.0",
    "gn:asciiname":"La Aurora (Tierra Blanca)",
    "gn:country_code":"MX",
    "gn:dem":42,
    "gn:feature_class":"P",
    "gn:feature_code":"PPL",
    "gn:name":"La Aurora (Tierra Blanca)",
    "gn:population":89,
    "gn:timezone":"America/Mazatlan",
    "iso:country":"MX",
    "wof:name":"La Aurora (Tierra Blanca)",
    "wof:placetype":"locality",
    "wof:population":89
},
  "geometry": {"coordinates":[-108.76000000000001,26.17444],"type":"Point"}
}