{
  "type": "Feature",
  "properties": {
    "gn:admin1_code":"20",
    "gn:asciiname":"San Jose Chapultepec",
    "gn:country_code":"MX",
    "gn:dem":1632,
    "gn:feature_class":"P",
    "gn:feature_code":"PPL",
    "gn:name":"San Jos\u00e9 Chapultepec",
    "gn:population":0,
    "gn:timezone":"America/Mexico_City",
    "iso:country":"MX",
    "name:spa_x_preferred":[
        "San Jos\u00e9 Chapultepec"
    ],
    "wof:name":"San Jose Chapultepec",
    "wof:placetype":"locality"
},
  "geometry": {"coordinates":[-97.92165,17.91943],"type":"Point"}
}