{
  "type": "Feature",
  "properties": {
    "gn:admin1_code":"30",
    "gn:admin2_code":"174.0",
    "gn:asciiname":"El Zapotillo",
    "gn:country_code":"MX",
    "gn:dem":182,
    "gn:feature_class":"P",
    "gn:feature_code":"PPL",
    "gn:name":"El Zapotillo",
    "gn:population":128,
    "gn:timezone":"America/Mexico_City",
    "iso:country":"MX",
    "wof:name":"El Zapotillo",
    "wof:placetype":"locality",
    "wof:population":128
},
  "geometry": {"coordinates":[-96.56556,18.68917],"type":"Point"}
}