{
  "type": "Feature",
  "properties": {
    "gn:admin1_code":"24",
    "gn:admin2_code":"32.0",
    "gn:asciiname":"Las Nueces",
    "gn:country_code":"MX",
    "gn:dem":2192,
    "gn:feature_class":"P",
    "gn:feature_code":"PPL",
    "gn:name":"Las Nueces",
    "gn:population":0,
    "gn:timezone":"America/Mexico_City",
    "iso:country":"MX",
    "name:spa_x_preferred":[
        "Las Nueces"
    ],
    "wof:name":"Las Nueces",
    "wof:placetype":"locality"
},
  "geometry": {"coordinates":[-100.43226,21.76347],"type":"Point"}
}