{
  "type": "Feature",
  "properties": {
    "gn:admin1_code":"18",
    "gn:asciiname":"Gavilanes",
    "gn:country_code":"MX",
    "gn:dem":648,
    "gn:feature_class":"P",
    "gn:feature_code":"PPL",
    "gn:name":"Gavilanes",
    "gn:population":0,
    "gn:timezone":"America/Mazatlan",
    "iso:country":"MX",
    "name:spa_x_preferred":[
        "Gavilanes"
    ],
    "wof:name":"Gavilanes",
    "wof:placetype":"locality"
},
  "geometry": {"coordinates":[-104.98618,22.84011],"type":"Point"}
}