{
  "type": "Feature",
  "properties": {
    "gn:admin1_code":"32",
    "gn:admin2_code":"38.0",
    "gn:asciiname":"El Teniente",
    "gn:country_code":"MX",
    "gn:dem":2502,
    "gn:feature_class":"P",
    "gn:feature_code":"PPL",
    "gn:name":"El Teniente",
    "gn:population":6,
    "gn:timezone":"America/Mexico_City",
    "iso:country":"MX",
    "name:ara_x_preferred":[
        "\u0625\u0644 \u062a\u064a\u0646\u064a\u064a\u0646\u062a\u064a"
    ],
    "name:ceb_x_preferred":[
        "Mineral El Teniente"
    ],
    "name:deu_x_preferred":[
        "El Teniente"
    ],
    "name:fra_x_preferred":[
        "El Teniente"
    ],
    "name:jpn_x_preferred":[
        "\u30a8\u30eb\u30c6\u30cb\u30a8\u30f3\u30c6"
    ],
    "name:nld_x_preferred":[
        "El Teniente"
    ],
    "name:spa_x_preferred":[
        "Mina El Teniente"
    ],
    "name:swe_x_preferred":[
        "Mineral El Teniente"
    ],
    "wof:name":"El Teniente",
    "wof:placetype":"locality",
    "wof:population":6
},
  "geometry": {"coordinates":[-101.56694,22.35028],"type":"Point"}
}