{
  "type": "Feature",
  "properties": {
    "gn:admin1_code":"32",
    "gn:admin2_code":"38.0",
    "gn:asciiname":"El Teniente",
    "gn:country_code":"MX",
    "gn:dem":2502,
    "gn:feature_class":"P",
    "gn:feature_code":"PPL",
    "gn:name":"El Teniente",
    "gn:population":6,
    "gn:timezone":"America/Mexico_City",
    "iso:country":"MX",
    "wof:name":"El Teniente",
    "wof:placetype":"locality",
    "wof:population":6
},
  "geometry": {"coordinates":[-101.56694,22.35028],"type":"Point"}
}