{
  "type": "Feature",
  "properties": {
    "gn:admin1_code":"30",
    "gn:admin2_code":"57",
    "gn:asciiname":"Rio Resbaloso",
    "gn:country_code":"MX",
    "gn:dem":1965,
    "gn:feature_class":"P",
    "gn:feature_code":"PPL",
    "gn:name":"R\u00edo Resbaloso",
    "gn:population":18,
    "gn:timezone":"America/Mexico_City",
    "iso:country":"MX",
    "name:und_x_variant":[
        "R\u00edo Resbaloso"
    ],
    "wof:name":"Rio Resbaloso",
    "wof:placetype":"locality",
    "wof:population":18
},
  "geometry": {"coordinates":[-96.80472,19.75111],"type":"Point"}
}