{
  "type": "Feature",
  "properties": {
    "gn:admin1_code":"26.0",
    "gn:admin2_code":"25.0",
    "gn:asciiname":"El Pilar",
    "gn:country_code":"MX",
    "gn:dem":47,
    "gn:feature_class":"P",
    "gn:feature_code":"PPL",
    "gn:name":"El Pilar",
    "gn:population":0,
    "gn:timezone":"America/Hermosillo",
    "iso:country":"MX",
    "name:spa_x_preferred":[
        "El Pilar"
    ],
    "wof:name":"El Pilar",
    "wof:placetype":"locality"
},
  "geometry": {"coordinates":[-110.53288000000001,28.01286],"type":"Point"}
}