{
  "type": "Feature",
  "properties": {
    "gn:admin1_code":"30",
    "gn:admin2_code":"206.0",
    "gn:asciiname":"Piedra Iman",
    "gn:country_code":"MX",
    "gn:dem":11,
    "gn:feature_class":"P",
    "gn:feature_code":"PPL",
    "gn:name":"Piedra Im\u00e1n",
    "gn:population":9,
    "gn:timezone":"America/Mexico_City",
    "iso:country":"MX",
    "name:und_x_variant":[
        "Piedra Im\u00e1n"
    ],
    "wof:name":"Piedra Iman",
    "wof:placetype":"locality",
    "wof:population":9
},
  "geometry": {"coordinates":[-94.41417,18.04333],"type":"Point"}
}