{
  "type": "Feature",
  "properties": {
    "gn:admin1_code":"16.0",
    "gn:admin2_code":"92.0",
    "gn:asciiname":"Palula",
    "gn:country_code":"MX",
    "gn:dem":520,
    "gn:feature_class":"P",
    "gn:feature_code":"PPL",
    "gn:name":"Palula",
    "gn:population":0,
    "gn:timezone":"America/Mexico_City",
    "iso:country":"MX",
    "name:spa_x_preferred":[
        "Palula"
    ],
    "wof:name":"Palula",
    "wof:placetype":"locality"
},
  "geometry": {"coordinates":[-100.5371,18.98629],"type":"Point"}
}