{
  "type": "Feature",
  "properties": {
    "gn:admin1_code":"23",
    "gn:asciiname":"Rosa de Saaron",
    "gn:country_code":"MX",
    "gn:dem":84,
    "gn:feature_class":"P",
    "gn:feature_code":"PPL",
    "gn:name":"Rosa de Saar\u00f3n",
    "gn:population":0,
    "gn:timezone":"America/Cancun",
    "iso:country":"MX",
    "name:spa_x_preferred":[
        "Rosa de Saar\u00f3n"
    ],
    "wof:name":"Rosa de Saaron",
    "wof:placetype":"locality"
},
  "geometry": {"coordinates":[-89.08238,18.91639],"type":"Point"}
}