{
  "type": "Feature",
  "properties": {
    "gn:admin1_code":"20",
    "gn:admin2_code":"205",
    "gn:asciiname":"Arroyo Tortuga",
    "gn:country_code":"MX",
    "gn:dem":139,
    "gn:feature_class":"P",
    "gn:feature_code":"PPL",
    "gn:name":"Arroyo Tortuga",
    "gn:population":50,
    "gn:timezone":"America/Mexico_City",
    "iso:country":"MX",
    "wof:name":"Arroyo Tortuga",
    "wof:placetype":"locality",
    "wof:population":50
},
  "geometry": {"coordinates":[-95.815,17.55306],"type":"Point"}
}