{
  "type": "Feature",
  "properties": {
    "gn:admin1_code":"5.0",
    "gn:admin2_code":"56.0",
    "gn:asciiname":"Suyalho",
    "gn:country_code":"MX",
    "gn:dem":2047,
    "gn:feature_class":"P",
    "gn:feature_code":"PPL",
    "gn:name":"Suyalho",
    "gn:population":0,
    "gn:timezone":"America/Mexico_City",
    "iso:country":"MX",
    "name:spa_x_preferred":[
        "Zoyalo"
    ],
    "name:spa_x_variant":[
        "Suyalho"
    ],
    "wof:name":"Suyalho",
    "wof:placetype":"locality"
},
  "geometry": {"coordinates":[-92.57577999999999,16.88095],"type":"Point"}
}