{
  "type": "Feature",
  "properties": {
    "gn:admin1_code":"16",
    "gn:admin2_code":"15.0",
    "gn:asciiname":"Barranca de Villa",
    "gn:country_code":"MX",
    "gn:dem":957,
    "gn:feature_class":"P",
    "gn:feature_code":"PPL",
    "gn:name":"Barranca de Villa",
    "gn:population":7,
    "gn:timezone":"America/Mexico_City",
    "iso:country":"MX",
    "wof:name":"Barranca de Villa",
    "wof:placetype":"locality",
    "wof:population":7
},
  "geometry": {"coordinates":[-103.19389,18.59278],"type":"Point"}
}