{
  "type": "Feature",
  "properties": {
    "gn:admin1_code":"31.0",
    "gn:asciiname":"Don Antonio",
    "gn:country_code":"MX",
    "gn:dem":23,
    "gn:feature_class":"P",
    "gn:feature_code":"PPL",
    "gn:name":"Don Antonio",
    "gn:population":0,
    "gn:timezone":"America/Merida",
    "iso:country":"MX",
    "name:spa_x_preferred":[
        "Don Antonio"
    ],
    "name:spa_x_variant":[
        "San Antonio"
    ],
    "wof:name":"Don Antonio",
    "wof:placetype":"locality"
},
  "geometry": {"coordinates":[-88.15867,21.10284],"type":"Point"}
}