{
  "type": "Feature",
  "properties": {
    "gn:admin1_code":"14",
    "gn:admin2_code":"2",
    "gn:asciiname":"Loma del Panteon",
    "gn:country_code":"MX",
    "gn:dem":1369,
    "gn:feature_class":"P",
    "gn:feature_code":"PPL",
    "gn:name":"Loma del Pante\u00f3n",
    "gn:population":11,
    "gn:timezone":"America/Mexico_City",
    "iso:country":"MX",
    "name:und_x_variant":[
        "Loma del Pante\u00f3n"
    ],
    "wof:name":"Loma del Panteon",
    "wof:placetype":"locality",
    "wof:population":11
},
  "geometry": {"coordinates":[-103.59444000000001,20.40833],"type":"Point"}
}