{
  "type": "Feature",
  "properties": {
    "gn:admin1_code":"10",
    "gn:admin2_code":"7",
    "gn:asciiname":"El Alto del Chivo (Romero Rosas)",
    "gn:country_code":"MX",
    "gn:dem":1118,
    "gn:feature_class":"P",
    "gn:feature_code":"PPL",
    "gn:name":"El Alto del Chivo (Romero Rosas)",
    "gn:population":13,
    "gn:timezone":"America/Monterrey",
    "iso:country":"MX",
    "wof:name":"El Alto del Chivo (Romero Rosas)",
    "wof:placetype":"locality",
    "wof:population":13
},
  "geometry": {"coordinates":[-103.42479,25.69195],"type":"Point"}
}