{
  "type": "Feature",
  "properties": {
    "gn:admin1_code":"6",
    "gn:admin2_code":"7",
    "gn:asciiname":"El Alamo",
    "gn:country_code":"MX",
    "gn:dem":2311,
    "gn:feature_class":"P",
    "gn:feature_code":"PPL",
    "gn:name":"El \u00c1lamo",
    "gn:population":18,
    "gn:timezone":"America/Chihuahua",
    "iso:country":"MX",
    "name:und_x_variant":[
        "El \u00c1lamo"
    ],
    "wof:name":"El Alamo",
    "wof:placetype":"locality",
    "wof:population":18
},
  "geometry": {"coordinates":[-106.75303999999998,26.66931],"type":"Point"}
}