{
  "type": "Feature",
  "properties": {
    "gn:admin1_code":"21",
    "gn:admin2_code":"177.0",
    "gn:asciiname":"Palo Verde",
    "gn:country_code":"MX",
    "gn:dem":2204,
    "gn:feature_class":"P",
    "gn:feature_code":"PPL",
    "gn:name":"Palo Verde",
    "gn:population":83,
    "gn:timezone":"America/Mexico_City",
    "iso:country":"MX",
    "wof:name":"Palo Verde",
    "wof:placetype":"locality",
    "wof:population":83
},
  "geometry": {"coordinates":[-97.60056,18.75667],"type":"Point"}
}