{
  "type": "Feature",
  "properties": {
    "gn:admin1_code":"25",
    "gn:admin2_code":"12",
    "gn:asciiname":"Guasimilla",
    "gn:country_code":"MX",
    "gn:dem":148,
    "gn:feature_class":"P",
    "gn:feature_code":"PPL",
    "gn:name":"Guasimilla",
    "gn:population":15,
    "gn:timezone":"America/Mazatlan",
    "iso:country":"MX",
    "wof:name":"Guasimilla",
    "wof:placetype":"locality",
    "wof:population":15
},
  "geometry": {"coordinates":[-106.37888,23.47169],"type":"Point"}
}