{
  "type": "Feature",
  "properties": {
    "gn:admin1_code":"20",
    "gn:admin2_code":"334.0",
    "gn:asciiname":"Ampliacion Progreso",
    "gn:country_code":"MX",
    "gn:dem":49,
    "gn:feature_class":"P",
    "gn:feature_code":"PPL",
    "gn:name":"Ampliaci\u00f3n Progreso",
    "gn:population":72,
    "gn:timezone":"America/Mexico_City",
    "iso:country":"MX",
    "name:und_x_variant":[
        "Ampliaci\u00f3n Progreso"
    ],
    "wof:name":"Ampliacion Progreso",
    "wof:placetype":"locality",
    "wof:population":72
},
  "geometry": {"coordinates":[-97.69417,16.10083],"type":"Point"}
}