{
  "type": "Feature",
  "properties": {
    "gn:admin1_code":"13",
    "gn:admin2_code":"76.0",
    "gn:asciiname":"Julian Villagran",
    "gn:country_code":"MX",
    "gn:dem":2073,
    "gn:feature_class":"P",
    "gn:feature_code":"PPL",
    "gn:name":"Julian Villagran",
    "gn:population":0,
    "gn:timezone":"America/Mexico_City",
    "iso:country":"MX",
    "name:spa_x_preferred":[
        "Julian Villagran"
    ],
    "wof:name":"Julian Villagran",
    "wof:placetype":"locality"
},
  "geometry": {"coordinates":[-99.33977,20.10664],"type":"Point"}
}