{
  "type": "Feature",
  "properties": {
    "gn:admin1_code":"6.0",
    "gn:admin2_code":"40.0",
    "gn:asciiname":"El Naranjito",
    "gn:country_code":"MX",
    "gn:dem":1317,
    "gn:feature_class":"P",
    "gn:feature_code":"PPL",
    "gn:name":"El Naranjito",
    "gn:population":0,
    "gn:timezone":"America/Chihuahua",
    "iso:country":"MX",
    "name:spa_x_preferred":[
        "El Naranjito"
    ],
    "wof:name":"El Naranjito",
    "wof:placetype":"locality"
},
  "geometry": {"coordinates":[-108.54594,29.018],"type":"Point"}
}