{
  "type": "Feature",
  "properties": {
    "gn:admin1_code":"14.0",
    "gn:admin2_code":"62.0",
    "gn:asciiname":"El Fresnito",
    "gn:country_code":"MX",
    "gn:dem":1542,
    "gn:feature_class":"P",
    "gn:feature_code":"PPL",
    "gn:name":"El Fresnito",
    "gn:population":0,
    "gn:timezone":"America/Mexico_City",
    "iso:country":"MX",
    "name:spa_x_preferred":[
        "El Fresnito"
    ],
    "wof:name":"El Fresnito",
    "wof:placetype":"locality"
},
  "geometry": {"coordinates":[-104.41533,20.45935],"type":"Point"}
}