{
  "type": "Feature",
  "properties": {
    "gn:admin1_code":"24",
    "gn:admin2_code":"6.0",
    "gn:asciiname":"Las Amapolas",
    "gn:country_code":"MX",
    "gn:dem":1788,
    "gn:feature_class":"P",
    "gn:feature_code":"PPL",
    "gn:name":"Las Amapolas",
    "gn:population":0,
    "gn:timezone":"America/Mexico_City",
    "iso:country":"MX",
    "name:spa_x_preferred":[
        "Las Amapolas"
    ],
    "wof:name":"Las Amapolas",
    "wof:placetype":"locality"
},
  "geometry": {"coordinates":[-101.03342000000001,23.68494],"type":"Point"}
}