{
  "type": "Feature",
  "properties": {
    "gn:admin1_code":"21",
    "gn:admin2_code":"141.0",
    "gn:asciiname":"Santa Cruz Mirador",
    "gn:country_code":"MX",
    "gn:dem":1176,
    "gn:feature_class":"P",
    "gn:feature_code":"PPL",
    "gn:name":"Santa Cruz Mirador",
    "gn:population":111,
    "gn:timezone":"America/Mexico_City",
    "iso:country":"MX",
    "wof:name":"Santa Cruz Mirador",
    "wof:placetype":"locality",
    "wof:population":111
},
  "geometry": {"coordinates":[-98.09559,18.06429],"type":"Point"}
}