{
  "type": "Feature",
  "properties": {
    "gn:admin1_code":"14",
    "gn:admin2_code":"115.0",
    "gn:asciiname":"Agua Nueva",
    "gn:country_code":"MX",
    "gn:dem":1821,
    "gn:feature_class":"P",
    "gn:feature_code":"PPL",
    "gn:name":"Agua Nueva",
    "gn:population":0,
    "gn:timezone":"America/Mexico_City",
    "iso:country":"MX",
    "name:spa_x_preferred":[
        "Agua Nueva"
    ],
    "name:spa_x_variant":[
        "Agua nueva"
    ],
    "wof:name":"Agua Nueva",
    "wof:placetype":"locality"
},
  "geometry": {"coordinates":[-103.65662,21.94435],"type":"Point"}
}