{
  "type": "Feature",
  "properties": {
    "gn:admin1_code":"3",
    "gn:admin2_code":"8.0",
    "gn:asciiname":"Encino Gordo",
    "gn:country_code":"MX",
    "gn:dem":453,
    "gn:feature_class":"P",
    "gn:feature_code":"PPL",
    "gn:name":"Encino Gordo",
    "gn:population":0,
    "gn:timezone":"America/Mazatlan",
    "iso:country":"MX",
    "name:spa_x_preferred":[
        "Encino Gordo"
    ],
    "wof:name":"Encino Gordo",
    "wof:placetype":"locality"
},
  "geometry": {"coordinates":[-109.85296,23.55184],"type":"Point"}
}