{
  "type": "Feature",
  "properties": {
    "gn:admin1_code":"11",
    "gn:admin2_code":"1.0",
    "gn:asciiname":"La Galerita (Emilio Vargas)",
    "gn:country_code":"MX",
    "gn:dem":1692,
    "gn:feature_class":"P",
    "gn:feature_code":"PPL",
    "gn:name":"La Galerita (Emilio Vargas)",
    "gn:population":5,
    "gn:timezone":"America/Mexico_City",
    "iso:country":"MX",
    "wof:name":"La Galerita (Emilio Vargas)",
    "wof:placetype":"locality",
    "wof:population":5
},
  "geometry": {"coordinates":[-101.57083,20.43417],"type":"Point"}
}