{
  "type": "Feature",
  "properties": {
    "gn:admin1_code":"11",
    "gn:admin2_code":"15.0",
    "gn:asciiname":"San Jose de Transito",
    "gn:country_code":"MX",
    "gn:dem":1871,
    "gn:feature_class":"P",
    "gn:feature_code":"PPL",
    "gn:name":"San Jos\u00e9 de Tr\u00e1nsito",
    "gn:population":683,
    "gn:timezone":"America/Mexico_City",
    "iso:country":"MX",
    "name:und_x_variant":[
        "San Jos\u00e9 de Tr\u00e1nsito"
    ],
    "wof:name":"San Jose de Transito",
    "wof:placetype":"locality",
    "wof:population":683
},
  "geometry": {"coordinates":[-101.33154,20.93113],"type":"Point"}
}