{
  "type": "Feature",
  "properties": {
    "gn:admin1_code":"6",
    "gn:admin2_code":"34.0",
    "gn:asciiname":"Rancho El Arco",
    "gn:country_code":"MX",
    "gn:dem":1851,
    "gn:feature_class":"P",
    "gn:feature_code":"PPL",
    "gn:name":"Rancho El Arco",
    "gn:population":0,
    "gn:timezone":"America/Chihuahua",
    "iso:country":"MX",
    "wof:name":"Rancho El Arco",
    "wof:placetype":"locality"
},
  "geometry": {"coordinates":[-107.51667,29.66667],"type":"Point"}
}