{
  "type": "Feature",
  "properties": {
    "gn:admin1_code":"30.0",
    "gn:admin2_code":"155.0",
    "gn:asciiname":"Los Tocayos",
    "gn:country_code":"MX",
    "gn:dem":59,
    "gn:feature_class":"P",
    "gn:feature_code":"PPL",
    "gn:name":"Los Tocayos",
    "gn:population":1,
    "gn:timezone":"America/Mexico_City",
    "iso:country":"MX",
    "name:spa_x_preferred":[
        "Los Tocayos"
    ],
    "wof:name":"Los Tocayos",
    "wof:placetype":"locality",
    "wof:population":1
},
  "geometry": {"coordinates":[-98.29583,21.29278],"type":"Point"}
}