{
  "type": "Feature",
  "properties": {
    "gn:country":"MX",
    "gn:fcode":"PPL",
    "gn:population":0,
    "iso:country":"MX",
    "name:ara_x_preferred":[
        "\u0625\u0644 \u0641\u0631\u064a\u0633\u0646\u0648"
    ],
    "name:ast_x_preferred":[
        "El Fresno"
    ],
    "name:cat_x_preferred":[
        "El Fresno"
    ],
    "name:ceb_x_preferred":[
        "El Fresno"
    ],
    "name:deu_x_preferred":[
        "El Fresno"
    ],
    "name:eus_x_preferred":[
        "El Fresno"
    ],
    "name:fas_x_preferred":[
        "\u0627\u0644 \u0641\u0631\u0633\u0646\u0648"
    ],
    "name:fra_x_preferred":[
        "El Fresno"
    ],
    "name:hun_x_preferred":[
        "El Fresno"
    ],
    "name:ina_x_preferred":[
        "El Fresno"
    ],
    "name:ita_x_preferred":[
        "El Fresno"
    ],
    "name:kaz_x_preferred":[
        "\u042d\u043b\u044c-\u0424\u0440\u0435\u0441\u043d\u043e"
    ],
    "name:mkd_x_preferred":[
        "\u0415\u043b \u0424\u0440\u0435\u0441\u043d\u043e"
    ],
    "name:msa_x_preferred":[
        "El Fresno"
    ],
    "name:nld_x_preferred":[
        "El Fresno"
    ],
    "name:oci_x_preferred":[
        "El Fresno"
    ],
    "name:pol_x_preferred":[
        "El Fresno"
    ],
    "name:por_x_preferred":[
        "El Fresno"
    ],
    "name:rus_x_preferred":[
        "\u042d\u043b\u044c-\u0424\u0440\u0435\u0441\u043d\u043e"
    ],
    "name:spa_x_preferred":[
        "El Fresno"
    ],
    "name:ukr_x_preferred":[
        "\u0415\u043b\u044c-\u0424\u0440\u0435\u0441\u043d\u043e"
    ],
    "name:uzb_x_preferred":[
        "El Fresno"
    ],
    "name:vie_x_preferred":[
        "El Fresno"
    ],
    "name:war_x_preferred":[
        "El Fresno"
    ],
    "name:zho_x_preferred":[
        "\u57c3\u5c14\u592b\u96f7\u65af\u8bfa"
    ],
    "qs_pg:aaroncc":"MX",
    "qs_pg:gn_country":"MX",
    "qs_pg:gn_fcode":"PPL",
    "qs_pg:gn_pop":0,
    "qs_pg:name":"El Fresno",
    "qs_pg:name_adm0":"M\u00e9xico",
    "qs_pg:name_adm1":"Michoacan de Ocampo",
    "qs_pg:photos":136,
    "qs_pg:photos_1k":28,
    "qs_pg:photos_9k":1,
    "qs_pg:photos_9r":3,
    "qs_pg:photos_all":136,
    "qs_pg:photos_sr":3,
    "qs_pg:pop_sr":0,
    "qs_pg:qs_pg_placetype":"neighbourhood",
    "qs_pg:qs_pg_placetype_gp":"Suburb",
    "qs_pg:woe_adm0":23424900,
    "woe:adm0_id":23424900,
    "woe:name_adm0":"M\u00e9xico",
    "woe:name_adm1":"Michoacan de Ocampo",
    "woe:placetype":"Suburb",
    "wof:name":"El Fresno",
    "wof:placetype":"neighbourhood"
},
  "geometry": {"coordinates":[-102.66669,19.93931],"type":"Point"}
}