{
  "type": "Feature",
  "properties": {
    "gn:gn_country":"MX",
    "gn:gn_fcode":"PPL",
    "gn:gn_pop":0,
    "iso:country":"MX",
    "name:spa_x_preferred":[
        "El Fresno"
    ],
    "qs_pg:aaroncc":"MX",
    "qs_pg:gn_country":"MX",
    "qs_pg:gn_fcode":"PPL",
    "qs_pg:gn_pop":0,
    "qs_pg:name":"El Fresno",
    "qs_pg:name_adm0":"M\u00e9xico",
    "qs_pg:name_adm1":"Michoacan de Ocampo",
    "qs_pg:photos":136,
    "qs_pg:photos_1k":28,
    "qs_pg:photos_9k":1,
    "qs_pg:photos_9r":3,
    "qs_pg:photos_all":136,
    "qs_pg:photos_sr":3,
    "qs_pg:pop_sr":0,
    "qs_pg:qs_pg_placetype":"neighbourhood",
    "qs_pg:qs_pg_placetype_gp":"Suburb",
    "qs_pg:woe_adm0":23424900,
    "woe:adm0_id":23424900,
    "woe:name_adm0":"M\u00e9xico",
    "woe:name_adm1":"Michoacan de Ocampo",
    "woe:placetype":"Suburb",
    "wof:name":"El Fresno",
    "wof:placetype":"neighbourhood"
},
  "geometry": {"coordinates":[-102.66669,19.93931],"type":"Point"}
}