{
  "type": "Feature",
  "properties": {
    "gn:admin1_code":"10",
    "gn:admin2_code":"13",
    "gn:asciiname":"El Porvenir",
    "gn:country_code":"MX",
    "gn:dem":1182,
    "gn:feature_class":"P",
    "gn:feature_code":"PPL",
    "gn:name":"El Porvenir",
    "gn:population":50,
    "gn:timezone":"America/Monterrey",
    "iso:country":"MX",
    "wof:name":"El Porvenir",
    "wof:placetype":"locality",
    "wof:population":50
},
  "geometry": {"coordinates":[-104.15438,26.6053],"type":"Point"}
}