{
  "type": "Feature",
  "properties": {
    "gn:admin1_code":"5",
    "gn:admin2_code":"80.0",
    "gn:asciiname":"San Bartolo",
    "gn:country_code":"MX",
    "gn:dem":1097,
    "gn:feature_class":"P",
    "gn:feature_code":"PPL",
    "gn:name":"San Bartolo",
    "gn:population":157,
    "gn:timezone":"America/Mexico_City",
    "iso:country":"MX",
    "wof:name":"San Bartolo",
    "wof:placetype":"locality",
    "wof:population":157
},
  "geometry": {"coordinates":[-92.33806,15.55722],"type":"Point"}
}