{
  "type": "Feature",
  "properties": {
    "gn:admin1_code":"17.0",
    "gn:asciiname":"Don Pancho",
    "gn:country_code":"MX",
    "gn:dem":1321,
    "gn:feature_class":"P",
    "gn:feature_code":"PPL",
    "gn:name":"Don Pancho",
    "gn:population":0,
    "gn:timezone":"America/Mexico_City",
    "iso:country":"MX",
    "name:spa_x_preferred":[
        "Don Pancho"
    ],
    "wof:name":"Don Pancho",
    "wof:placetype":"locality"
},
  "geometry": {"coordinates":[-98.80498,18.67001],"type":"Point"}
}