{
  "type": "Feature",
  "properties": {
    "gn:admin1_code":"11.0",
    "gn:admin2_code":"20.0",
    "gn:asciiname":"El Raton",
    "gn:country_code":"MX",
    "gn:dem":1781,
    "gn:feature_class":"P",
    "gn:feature_code":"PPL",
    "gn:name":"El Rat\u00f3n",
    "gn:population":0,
    "gn:timezone":"America/Mexico_City",
    "iso:country":"MX",
    "name:spa_x_preferred":[
        "El Rat\u00f3n"
    ],
    "wof:name":"El Raton",
    "wof:placetype":"locality"
},
  "geometry": {"coordinates":[-101.68917999999999,21.01787],"type":"Point"}
}