{
  "type": "Feature",
  "properties": {
    "gn:admin1_code":"5",
    "gn:admin2_code":"69.0",
    "gn:asciiname":"La Esperanza (El Zapotal)",
    "gn:country_code":"MX",
    "gn:dem":12,
    "gn:feature_class":"P",
    "gn:feature_code":"PPL",
    "gn:name":"La Esperanza (El Zapotal)",
    "gn:population":1031,
    "gn:timezone":"America/Mexico_City",
    "iso:country":"MX",
    "wof:name":"La Esperanza (El Zapotal)",
    "wof:placetype":"locality",
    "wof:population":1031
},
  "geometry": {"coordinates":[-93.16417,15.44917],"type":"Point"}
}