{
  "type": "Feature",
  "properties": {
    "gn:admin1_code":"5",
    "gn:admin2_code":"83.0",
    "gn:asciiname":"Miramar",
    "gn:country_code":"MX",
    "gn:dem":652,
    "gn:feature_class":"P",
    "gn:feature_code":"PPL",
    "gn:name":"Miramar",
    "gn:population":158,
    "gn:timezone":"America/Mexico_City",
    "iso:country":"MX",
    "wof:name":"Miramar",
    "wof:placetype":"locality",
    "wof:population":158
},
  "geometry": {"coordinates":[-92.23778,15.98528],"type":"Point"}
}