{
  "type": "Feature",
  "properties": {
    "gn:admin1_code":"16",
    "gn:admin2_code":"92.0",
    "gn:asciiname":"El Asoleadero",
    "gn:country_code":"MX",
    "gn:dem":702,
    "gn:feature_class":"P",
    "gn:feature_code":"PPL",
    "gn:name":"El Asoleadero",
    "gn:population":0,
    "gn:timezone":"America/Mexico_City",
    "iso:country":"MX",
    "name:spa_x_preferred":[
        "El Asoleadero"
    ],
    "wof:name":"El Asoleadero",
    "wof:placetype":"locality"
},
  "geometry": {"coordinates":[-100.82834,19.22169],"type":"Point"}
}