{
  "type": "Feature",
  "properties": {
    "gn:admin1_code":"20",
    "gn:admin2_code":"59.0",
    "gn:asciiname":"Agua Blanca",
    "gn:country_code":"MX",
    "gn:dem":1623,
    "gn:feature_class":"P",
    "gn:feature_code":"PPL",
    "gn:name":"Agua Blanca",
    "gn:population":169,
    "gn:timezone":"America/Mexico_City",
    "iso:country":"MX",
    "wof:name":"Agua Blanca",
    "wof:placetype":"locality",
    "wof:population":169
},
  "geometry": {"coordinates":[-96.56028000000001,16.30194],"type":"Point"}
}