{
  "type": "Feature",
  "properties": {
    "gn:admin1_code":"11.0",
    "gn:admin2_code":"42.0",
    "gn:asciiname":"La Barquilla",
    "gn:country_code":"MX",
    "gn:dem":1707,
    "gn:feature_class":"P",
    "gn:feature_code":"PPL",
    "gn:name":"La Barquilla",
    "gn:population":0,
    "gn:timezone":"America/Mexico_City",
    "iso:country":"MX",
    "name:und_x_variant":[
        "La Banquilla",
        "La Barquilla",
        "Las Barquillas"
    ],
    "wof:name":"La Barquilla",
    "wof:placetype":"locality"
},
  "geometry": {"coordinates":[-101.44113,20.33568],"type":"Point"}
}