{
  "type": "Feature",
  "properties": {
    "gn:admin1_code":"18",
    "gn:admin2_code":"5.0",
    "gn:asciiname":"El Tronco de la Villa",
    "gn:country_code":"MX",
    "gn:dem":706,
    "gn:feature_class":"P",
    "gn:feature_code":"PPL",
    "gn:name":"El Tronco de la Villa",
    "gn:population":0,
    "gn:timezone":"America/Mazatlan",
    "iso:country":"MX",
    "name:spa_x_preferred":[
        "El Tronco de la Villa"
    ],
    "name:spa_x_variant":[
        "La Villita"
    ],
    "wof:name":"El Tronco de la Villa",
    "wof:placetype":"locality"
},
  "geometry": {"coordinates":[-105.20378999999998,22.89442],"type":"Point"}
}