{
  "type": "Feature",
  "properties": {
    "gn:admin1_code":"8",
    "gn:admin2_code":"3",
    "gn:asciiname":"Los Tomatillos",
    "gn:country_code":"MX",
    "gn:dem":1252,
    "gn:feature_class":"P",
    "gn:feature_code":"PPL",
    "gn:name":"Los Tomatillos",
    "gn:population":16,
    "gn:timezone":"America/Mexico_City",
    "iso:country":"MX",
    "wof:name":"Los Tomatillos",
    "wof:placetype":"locality",
    "wof:population":16
},
  "geometry": {"coordinates":[-103.71167,19.40778],"type":"Point"}
}