{
  "type": "Feature",
  "properties": {
    "gn:admin1_code":"30.0",
    "gn:asciiname":"El Pozon",
    "gn:country_code":"MX",
    "gn:dem":90,
    "gn:feature_class":"P",
    "gn:feature_code":"PPL",
    "gn:name":"El Poz\u00f3n",
    "gn:population":0,
    "gn:timezone":"America/Mexico_City",
    "iso:country":"MX",
    "name:spa_x_preferred":[
        "El Poz\u00f3n"
    ],
    "wof:name":"El Pozon",
    "wof:placetype":"locality"
},
  "geometry": {"coordinates":[-95.57906,17.95641],"type":"Point"}
}