{
  "type": "Feature",
  "properties": {
    "gn:admin1_code":"30",
    "gn:admin2_code":"45.0",
    "gn:asciiname":"Texas",
    "gn:country_code":"MX",
    "gn:dem":28,
    "gn:feature_class":"P",
    "gn:feature_code":"PPL",
    "gn:name":"Texas",
    "gn:population":0,
    "gn:timezone":"America/Mexico_City",
    "iso:country":"MX",
    "name:spa_x_preferred":[
        "Texas"
    ],
    "wof:name":"Texas",
    "wof:placetype":"locality"
},
  "geometry": {"coordinates":[-96.12975,18.17412],"type":"Point"}
}