{
  "type": "Feature",
  "properties": {
    "gn:admin1_code":"14",
    "gn:admin2_code":"100.0",
    "gn:asciiname":"Palmira",
    "gn:country_code":"MX",
    "gn:dem":57,
    "gn:feature_class":"P",
    "gn:feature_code":"PPL",
    "gn:name":"Palmira",
    "gn:population":5,
    "gn:timezone":"America/Mexico_City",
    "iso:country":"MX",
    "name:cat_x_preferred":[
        "Palmira"
    ],
    "name:ceb_x_preferred":[
        "Palmira"
    ],
    "name:deu_x_preferred":[
        "Palmira"
    ],
    "name:fra_x_preferred":[
        "Palmira"
    ],
    "name:hun_x_preferred":[
        "Palmira"
    ],
    "name:ita_x_preferred":[
        "Palmira"
    ],
    "name:mlg_x_preferred":[
        "Palmira"
    ],
    "name:nld_x_preferred":[
        "Palmira"
    ],
    "name:pol_x_preferred":[
        "Palmira"
    ],
    "name:por_x_preferred":[
        "Palmira"
    ],
    "name:sco_x_preferred":[
        "Palmira"
    ],
    "name:slv_x_preferred":[
        "Palmira"
    ],
    "name:spa_x_preferred":[
        "Palmira"
    ],
    "name:srp_x_preferred":[
        "\u041f\u0430\u043b\u043c\u0438\u0440\u0430"
    ],
    "name:swe_x_preferred":[
        "Palmira"
    ],
    "name:xmf_x_preferred":[
        "\u10de\u10d0\u10da\u10db\u10d8\u10e0\u10d0"
    ],
    "wof:name":"Palmira",
    "wof:placetype":"locality",
    "wof:population":5
},
  "geometry": {"coordinates":[-105.38667,20.07306],"type":"Point"}
}