{
  "type": "Feature",
  "properties": {
    "gn:admin1_code":"5.0",
    "gn:asciiname":"San Pablo Yalmutz",
    "gn:country_code":"MX",
    "gn:dem":1475,
    "gn:feature_class":"P",
    "gn:feature_code":"PPL",
    "gn:name":"San Pablo Yalmutz",
    "gn:population":0,
    "gn:timezone":"America/Mexico_City",
    "iso:country":"MX",
    "name:spa_x_preferred":[
        "San Pablo Yalmutz"
    ],
    "wof:name":"San Pablo Yalmutz",
    "wof:placetype":"locality"
},
  "geometry": {"coordinates":[-91.73429,16.13285],"type":"Point"}
}