{
  "type": "Feature",
  "properties": {
    "gn:admin1_code":"15",
    "gn:admin2_code":"52.0",
    "gn:asciiname":"Jalmolonga (La Hacienda)",
    "gn:country_code":"MX",
    "gn:dem":1573,
    "gn:feature_class":"P",
    "gn:feature_code":"PPL",
    "gn:name":"Jalmolonga (La Hacienda)",
    "gn:population":1019,
    "gn:timezone":"America/Mexico_City",
    "iso:country":"MX",
    "wof:name":"Jalmolonga (La Hacienda)",
    "wof:placetype":"locality",
    "wof:population":1019
},
  "geometry": {"coordinates":[-99.49406999999999,18.91835],"type":"Point"}
}