{
  "type": "Feature",
  "properties": {
    "gn:admin1_code":"2",
    "gn:admin2_code":"5",
    "gn:asciiname":"Los Chichos",
    "gn:country_code":"MX",
    "gn:dem":98,
    "gn:feature_class":"P",
    "gn:feature_code":"PPL",
    "gn:name":"Los Chichos",
    "gn:population":16,
    "gn:timezone":"America/Tijuana",
    "iso:country":"MX",
    "name:ast_x_preferred":[
        "Los Chichos"
    ],
    "name:eus_x_preferred":[
        "Los Chichos"
    ],
    "name:fra_x_preferred":[
        "Los Chichos"
    ],
    "name:glg_x_preferred":[
        "Los Chichos"
    ],
    "name:spa_x_preferred":[
        "Los Chichos"
    ],
    "wof:name":"Los Chichos",
    "wof:placetype":"locality",
    "wof:population":16
},
  "geometry": {"coordinates":[-116.94693999999998,32.26083],"type":"Point"}
}