{
  "type": "Feature",
  "properties": {
    "gn:admin1_code":"20.0",
    "gn:asciiname":"Putalzingo",
    "gn:country_code":"MX",
    "gn:dem":24,
    "gn:feature_class":"P",
    "gn:feature_code":"PPL",
    "gn:name":"Putalzingo",
    "gn:population":0,
    "gn:timezone":"America/Mexico_City",
    "iso:country":"MX",
    "name:spa_x_preferred":[
        "Putalzingo"
    ],
    "wof:name":"Putalzingo",
    "wof:placetype":"locality"
},
  "geometry": {"coordinates":[-96.27603999999999,18.28745],"type":"Point"}
}