{
  "type": "Feature",
  "properties": {
    "gn:admin1_code":"15",
    "gn:admin2_code":"123",
    "gn:asciiname":"Arrayan",
    "gn:country_code":"MX",
    "gn:dem":1003,
    "gn:feature_class":"P",
    "gn:feature_code":"PPL",
    "gn:name":"Array\u00e1n",
    "gn:population":12,
    "gn:timezone":"America/Mexico_City",
    "iso:country":"MX",
    "name:und_x_variant":[
        "Array\u00e1n"
    ],
    "wof:name":"Arrayan",
    "wof:placetype":"locality",
    "wof:population":12
},
  "geometry": {"coordinates":[-100.39060000000001,19.03655],"type":"Point"}
}