{
  "type": "Feature",
  "properties": {
    "gn:admin1_code":"30",
    "gn:admin2_code":"175.0",
    "gn:asciiname":"Santa Fe (Kilometro 8)",
    "gn:country_code":"MX",
    "gn:dem":63,
    "gn:feature_class":"P",
    "gn:feature_code":"PPL",
    "gn:name":"Santa Fe (Kil\u00f3metro 8)",
    "gn:population":284,
    "gn:timezone":"America/Mexico_City",
    "iso:country":"MX",
    "name:und_x_variant":[
        "Santa Fe (Kil\u00f3metro 8)"
    ],
    "wof:name":"Santa Fe (Kilometro 8)",
    "wof:placetype":"locality",
    "wof:population":284
},
  "geometry": {"coordinates":[-97.49388999999999,20.59028],"type":"Point"}
}