{
  "type": "Feature",
  "properties": {
    "gn:admin1_code":"12",
    "gn:admin2_code":"79.0",
    "gn:asciiname":"Quetzalapa",
    "gn:country_code":"MX",
    "gn:dem":1146,
    "gn:feature_class":"P",
    "gn:feature_code":"PPL",
    "gn:name":"Quetzalapa",
    "gn:population":410,
    "gn:timezone":"America/Mexico_City",
    "iso:country":"MX",
    "wof:name":"Quetzalapa",
    "wof:placetype":"locality",
    "wof:population":410
},
  "geometry": {"coordinates":[-99.01891000000001,17.41477],"type":"Point"}
}