{
  "type": "Feature",
  "properties": {
    "gn:admin1_code":"25",
    "gn:admin2_code":"2.0",
    "gn:asciiname":"Independencia",
    "gn:country_code":"MX",
    "gn:dem":23,
    "gn:feature_class":"P",
    "gn:feature_code":"PPL",
    "gn:name":"Independencia",
    "gn:population":0,
    "gn:timezone":"America/Mazatlan",
    "iso:country":"MX",
    "name:cat_x_preferred":[
        "Independ\u00e8ncia"
    ],
    "name:ceb_x_preferred":[
        "Independencia"
    ],
    "name:deu_x_preferred":[
        "Independencia"
    ],
    "name:epo_x_preferred":[
        "Independencia"
    ],
    "name:fra_x_preferred":[
        "Independencia"
    ],
    "name:ita_x_preferred":[
        "Independencia"
    ],
    "name:kor_x_preferred":[
        "\uc778\ub370\ud39c\ub374\uc2dc\uc544"
    ],
    "name:nld_x_preferred":[
        "Independencia"
    ],
    "name:nor_x_preferred":[
        "Independencia"
    ],
    "name:rus_x_preferred":[
        "\u0418\u043d\u0434\u0435\u043f\u0435\u043d\u0434\u0435\u043d\u0441\u0438\u044f"
    ],
    "name:sco_x_preferred":[
        "Independencia"
    ],
    "name:spa_x_preferred":[
        "Independencia"
    ],
    "name:swe_x_preferred":[
        "Independencia"
    ],
    "name:ukr_x_preferred":[
        "\u0406\u043d\u0434\u0435\u043f\u0435\u043d\u0434\u0435\u043d\u0441\u0456\u044f"
    ],
    "name:und_x_variant":[
        "Chinitos"
    ],
    "wof:name":"Independencia",
    "wof:placetype":"locality"
},
  "geometry": {"coordinates":[-107.91517,25.05698],"type":"Point"}
}