{
  "type": "Feature",
  "properties": {
    "gn:admin1_code":"5",
    "gn:admin2_code":"83",
    "gn:asciiname":"San Luis",
    "gn:country_code":"MX",
    "gn:dem":625,
    "gn:feature_class":"P",
    "gn:feature_code":"PPL",
    "gn:name":"San Luis",
    "gn:population":21,
    "gn:timezone":"America/Mexico_City",
    "iso:country":"MX",
    "wof:name":"San Luis",
    "wof:placetype":"locality",
    "wof:population":21
},
  "geometry": {"coordinates":[-92.44028,16.18528],"type":"Point"}
}