{
  "type": "Feature",
  "properties": {
    "gn:admin1_code":"20",
    "gn:admin2_code":"106.0",
    "gn:asciiname":"San Jose (Seccion Segunda)",
    "gn:country_code":"MX",
    "gn:dem":2188,
    "gn:feature_class":"P",
    "gn:feature_code":"PPL",
    "gn:name":"San Jos\u00e9 (Secci\u00f3n Segunda)",
    "gn:population":68,
    "gn:timezone":"America/Mexico_City",
    "iso:country":"MX",
    "name:und_x_variant":[
        "San Jos\u00e9 (Secci\u00f3n Segunda)"
    ],
    "wof:name":"San Jose (Seccion Segunda)",
    "wof:placetype":"locality",
    "wof:population":68
},
  "geometry": {"coordinates":[-97.48917,17.74361],"type":"Point"}
}