{
  "type": "Feature",
  "properties": {
    "gn:admin1_code":"19.0",
    "gn:admin2_code":"5.0",
    "gn:asciiname":"Los Tizones",
    "gn:country_code":"MX",
    "gn:dem":251,
    "gn:feature_class":"P",
    "gn:feature_code":"PPL",
    "gn:name":"Los Tizones",
    "gn:population":0,
    "gn:timezone":"America/Matamoros",
    "iso:country":"MX",
    "name:spa_x_preferred":[
        "Los Tizones"
    ],
    "wof:name":"Los Tizones",
    "wof:placetype":"locality"
},
  "geometry": {"coordinates":[-100.23329,27.61428],"type":"Point"}
}