{
  "type": "Feature",
  "properties": {
    "gn:admin1_code":"19",
    "gn:admin2_code":"49.0",
    "gn:asciiname":"El Tarillal",
    "gn:country_code":"MX",
    "gn:dem":2472,
    "gn:feature_class":"P",
    "gn:feature_code":"PPL",
    "gn:name":"El Tarillal",
    "gn:population":4,
    "gn:timezone":"America/Monterrey",
    "iso:country":"MX",
    "wof:name":"El Tarillal",
    "wof:placetype":"locality",
    "wof:population":4
},
  "geometry": {"coordinates":[-100.51631999999999,25.44804],"type":"Point"}
}