{
  "type": "Feature",
  "properties": {
    "gn:admin1_code":"14.0",
    "gn:admin2_code":"58.0",
    "gn:asciiname":"Lagunillas",
    "gn:country_code":"MX",
    "gn:dem":1768,
    "gn:feature_class":"P",
    "gn:feature_code":"PPL",
    "gn:name":"Lagunillas",
    "gn:population":0,
    "gn:timezone":"America/Mexico_City",
    "iso:country":"MX",
    "name:ceb_x_preferred":[
        "Lagunillas"
    ],
    "name:deu_x_preferred":[
        "Lagunillas"
    ],
    "name:fra_x_preferred":[
        "Lagunillas"
    ],
    "name:ita_x_preferred":[
        "Lagunillas"
    ],
    "name:lit_x_preferred":[
        "Laguniljasas"
    ],
    "name:nld_x_preferred":[
        "Lagunillas"
    ],
    "name:sco_x_preferred":[
        "Lagunillas"
    ],
    "name:spa_x_preferred":[
        "Lagunillas"
    ],
    "name:swe_x_preferred":[
        "Lagunillas"
    ],
    "name:und_x_variant":[
        "Laguna",
        "La Laguna"
    ],
    "wof:name":"Lagunillas",
    "wof:placetype":"locality"
},
  "geometry": {"coordinates":[-104.76564,20.64146],"type":"Point"}
}