{
  "type": "Feature",
  "properties": {
    "gn:admin1_code":"2",
    "gn:admin2_code":"2.0",
    "gn:asciiname":"Colonia Siete",
    "gn:country_code":"MX",
    "gn:dem":8,
    "gn:feature_class":"P",
    "gn:feature_code":"PPL",
    "gn:name":"Colonia Siete",
    "gn:population":0,
    "gn:timezone":"America/Tijuana",
    "iso:country":"MX",
    "name:und_x_variant":[
        "Colonia 7"
    ],
    "wof:name":"Colonia Siete",
    "wof:placetype":"locality"
},
  "geometry": {"coordinates":[-115.41651,32.51335],"type":"Point"}
}