{
  "type": "Feature",
  "properties": {
    "gn:admin1_code":"10",
    "gn:admin2_code":"26.0",
    "gn:asciiname":"Rio de Miravalles",
    "gn:country_code":"MX",
    "gn:dem":2364,
    "gn:feature_class":"P",
    "gn:feature_code":"PPL",
    "gn:name":"R\u00edo de Miravalles",
    "gn:population":0,
    "gn:timezone":"America/Monterrey",
    "iso:country":"MX",
    "name:und_x_variant":[
        "Miravalle",
        "Miravalles",
        "R\u00edo de Miravalles"
    ],
    "wof:name":"Rio de Miravalles",
    "wof:placetype":"locality"
},
  "geometry": {"coordinates":[-105.55203,24.29855],"type":"Point"}
}