{
  "type": "Feature",
  "properties": {
    "gn:admin1_code":"6.0",
    "gn:admin2_code":"42.0",
    "gn:asciiname":"La Agueita",
    "gn:country_code":"MX",
    "gn:dem":1107,
    "gn:feature_class":"P",
    "gn:feature_code":"PPL",
    "gn:name":"La Ag\u00fcita",
    "gn:population":0,
    "gn:timezone":"America/Chihuahua",
    "iso:country":"MX",
    "name:spa_x_preferred":[
        "La Ag\u00fcita"
    ],
    "wof:name":"La Agueita",
    "wof:placetype":"locality"
},
  "geometry": {"coordinates":[-104.24771,29.2022],"type":"Point"}
}