{
  "type": "Feature",
  "properties": {
    "gn:admin1_code":"5.0",
    "gn:admin2_code":"107.0",
    "gn:asciiname":"La Encanada",
    "gn:country_code":"MX",
    "gn:dem":1058,
    "gn:feature_class":"P",
    "gn:feature_code":"PPL",
    "gn:name":"La Enca\u00f1ada",
    "gn:population":0,
    "gn:timezone":"America/Mexico_City",
    "iso:country":"MX",
    "name:spa_x_preferred":[
        "La Enca\u00f1ada"
    ],
    "wof:name":"La Encanada",
    "wof:placetype":"locality"
},
  "geometry": {"coordinates":[-93.09305000000001,15.88815],"type":"Point"}
}