{
  "type": "Feature",
  "properties": {
    "gn:admin1_code":"17.0",
    "gn:asciiname":"Yecapixteca",
    "gn:country_code":"MX",
    "gn:dem":1501,
    "gn:feature_class":"P",
    "gn:feature_code":"PPL",
    "gn:name":"Yecapixteca",
    "gn:population":0,
    "gn:timezone":"America/Mexico_City",
    "iso:country":"MX",
    "name:spa_x_preferred":[
        "Yecapixteca"
    ],
    "wof:name":"Yecapixteca",
    "wof:placetype":"locality"
},
  "geometry": {"coordinates":[-98.90272,18.8823],"type":"Point"}
}