{
  "type": "Feature",
  "properties": {
    "gn:admin1_code":"12",
    "gn:admin2_code":"68",
    "gn:asciiname":"Paso de Godoy",
    "gn:country_code":"MX",
    "gn:dem":78,
    "gn:feature_class":"P",
    "gn:feature_code":"PPL",
    "gn:name":"Paso de Godoy",
    "gn:population":12,
    "gn:timezone":"America/Mexico_City",
    "iso:country":"MX",
    "wof:name":"Paso de Godoy",
    "wof:placetype":"locality",
    "wof:population":12
},
  "geometry": {"coordinates":[-102.06876,18.19273],"type":"Point"}
}