{
  "type": "Feature",
  "properties": {
    "gn:admin1_code":"32",
    "gn:admin2_code":"31.0",
    "gn:asciiname":"Fraccionamiento COPROVI",
    "gn:country_code":"MX",
    "gn:dem":2181,
    "gn:feature_class":"P",
    "gn:feature_code":"PPL",
    "gn:name":"Fraccionamiento COPROVI",
    "gn:population":177,
    "gn:timezone":"America/Mexico_City",
    "iso:country":"MX",
    "wof:name":"Fraccionamiento COPROVI",
    "wof:placetype":"locality",
    "wof:population":177
},
  "geometry": {"coordinates":[-103.54443999999999,22.30417000000001],"type":"Point"}
}