{
  "type": "Feature",
  "properties": {
    "gn:admin1_code":"9",
    "gn:admin2_code":"9.0",
    "gn:asciiname":"Tecoloxtitla",
    "gn:country_code":"MX",
    "gn:dem":2531,
    "gn:feature_class":"P",
    "gn:feature_code":"PPL",
    "gn:name":"Tecoloxtitla",
    "gn:population":159,
    "gn:timezone":"America/Mexico_City",
    "iso:country":"MX",
    "wof:name":"Tecoloxtitla",
    "wof:placetype":"locality",
    "wof:population":159
},
  "geometry": {"coordinates":[-99.01179,19.18186],"type":"Point"}
}