{
  "type": "Feature",
  "properties": {
    "gn:admin1_code":"20",
    "gn:admin2_code":"125.0",
    "gn:asciiname":"Verichiga",
    "gn:country_code":"MX",
    "gn:dem":554,
    "gn:feature_class":"P",
    "gn:feature_code":"PPL",
    "gn:name":"Verichiga",
    "gn:population":0,
    "gn:timezone":"America/Mexico_City",
    "iso:country":"MX",
    "name:spa_x_preferred":[
        "Verichiga"
    ],
    "wof:name":"Verichiga",
    "wof:placetype":"locality"
},
  "geometry": {"coordinates":[-95.90788999999999,16.7354],"type":"Point"}
}