{
  "type": "Feature",
  "properties": {
    "gn:admin1_code":"20",
    "gn:admin2_code":"434.0",
    "gn:asciiname":"Cinco Flores",
    "gn:country_code":"MX",
    "gn:dem":2211,
    "gn:feature_class":"P",
    "gn:feature_code":"PPL",
    "gn:name":"Cinco Flores",
    "gn:population":129,
    "gn:timezone":"America/Mexico_City",
    "iso:country":"MX",
    "wof:name":"Cinco Flores",
    "wof:placetype":"locality",
    "wof:population":129
},
  "geometry": {"coordinates":[-96.98472,18.15917],"type":"Point"}
}