{
  "type": "Feature",
  "properties": {
    "gn:admin1_code":"30",
    "gn:admin2_code":"54",
    "gn:asciiname":"El Espinal",
    "gn:country_code":"MX",
    "gn:dem":16,
    "gn:feature_class":"P",
    "gn:feature_code":"PPL",
    "gn:name":"El Espinal",
    "gn:population":43,
    "gn:timezone":"America/Mexico_City",
    "iso:country":"MX",
    "name:cat_x_preferred":[
        "L'Espinal"
    ],
    "name:ceb_x_preferred":[
        "El Espinal"
    ],
    "name:ita_x_preferred":[
        "El Espinal"
    ],
    "name:spa_x_preferred":[
        "El Espinal"
    ],
    "name:srp_x_preferred":[
        "\u0415\u043b \u0415\u0441\u043f\u0438\u043d\u0430\u043b"
    ],
    "name:swe_x_preferred":[
        "El Espinal"
    ],
    "wof:name":"El Espinal",
    "wof:placetype":"locality",
    "wof:population":43
},
  "geometry": {"coordinates":[-95.75221999999999,18.22639],"type":"Point"}
}