{
  "type": "Feature",
  "properties": {
    "gn:admin1_code":"16",
    "gn:admin2_code":"29.0",
    "gn:asciiname":"Las Cieneguitas",
    "gn:country_code":"MX",
    "gn:dem":1500,
    "gn:feature_class":"P",
    "gn:feature_code":"PPL",
    "gn:name":"Las Cieneguitas",
    "gn:population":0,
    "gn:timezone":"America/Mexico_City",
    "iso:country":"MX",
    "name:spa_x_preferred":[
        "Las Cieneguitas"
    ],
    "wof:name":"Las Cieneguitas",
    "wof:placetype":"locality"
},
  "geometry": {"coordinates":[-101.60505999999999,18.92936],"type":"Point"}
}