{
  "type": "Feature",
  "properties": {
    "gn:admin1_code":"7",
    "gn:admin2_code":"27.0",
    "gn:asciiname":"Los Girones",
    "gn:country_code":"MX",
    "gn:dem":1130,
    "gn:feature_class":"P",
    "gn:feature_code":"PPL",
    "gn:name":"Los Girones",
    "gn:population":4,
    "gn:timezone":"America/Monterrey",
    "iso:country":"MX",
    "wof:name":"Los Girones",
    "wof:placetype":"locality",
    "wof:population":4
},
  "geometry": {"coordinates":[-101.12338,25.68781],"type":"Point"}
}