{
  "type": "Feature",
  "properties": {
    "gn:admin1_code":"31",
    "gn:admin2_code":"98.0",
    "gn:asciiname":"X-cime",
    "gn:country_code":"MX",
    "gn:dem":105,
    "gn:feature_class":"P",
    "gn:feature_code":"PPL",
    "gn:name":"X-cime",
    "gn:population":0,
    "gn:timezone":"America/Merida",
    "iso:country":"MX",
    "name:spa_x_preferred":[
        "Xcimex"
    ],
    "name:spa_x_variant":[
        "X-Cime"
    ],
    "wof:name":"X-cime",
    "wof:placetype":"locality"
},
  "geometry": {"coordinates":[-89.06165,19.95842],"type":"Point"}
}