{
  "type": "Feature",
  "properties": {
    "gn:admin1_code":"4",
    "gn:admin2_code":"11.0",
    "gn:asciiname":"El Chechen",
    "gn:country_code":"MX",
    "gn:dem":23,
    "gn:feature_class":"P",
    "gn:feature_code":"PPL",
    "gn:name":"El Chech\u00e9n",
    "gn:population":6,
    "gn:timezone":"America/Merida",
    "iso:country":"MX",
    "name:und_x_variant":[
        "El Chech\u00e9n"
    ],
    "wof:name":"El Chechen",
    "wof:placetype":"locality",
    "wof:population":6
},
  "geometry": {"coordinates":[-91.18722,18.15],"type":"Point"}
}