{
  "type": "Feature",
  "properties": {
    "gn:admin1_code":"19",
    "gn:admin2_code":"17.0",
    "gn:asciiname":"Potrero Prieto de Abajo",
    "gn:country_code":"MX",
    "gn:dem":1186,
    "gn:feature_class":"P",
    "gn:feature_code":"PPL",
    "gn:name":"Potrero Prieto de Abajo",
    "gn:population":0,
    "gn:timezone":"America/Monterrey",
    "iso:country":"MX",
    "name:spa_x_preferred":[
        "Potrero Prieto de Abajo"
    ],
    "name:und_x_variant":[
        "Potrero Prieto",
        "Potrero del Prieto",
        "Potrero de Prieto"
    ],
    "wof:name":"Potrero Prieto de Abajo",
    "wof:placetype":"locality"
},
  "geometry": {"coordinates":[-99.98953,24.85449],"type":"Point"}
}