{
  "type": "Feature",
  "properties": {
    "gn:admin1_code":"5",
    "gn:admin2_code":"99",
    "gn:asciiname":"El Capulin",
    "gn:country_code":"MX",
    "gn:dem":603,
    "gn:feature_class":"P",
    "gn:feature_code":"PPL",
    "gn:name":"El Capul\u00edn",
    "gn:population":11,
    "gn:timezone":"America/Mexico_City",
    "iso:country":"MX",
    "name:und_x_variant":[
        "El Capul\u00edn"
    ],
    "wof:name":"El Capulin",
    "wof:placetype":"locality",
    "wof:population":11
},
  "geometry": {"coordinates":[-91.94,15.84889],"type":"Point"}
}