{
  "type": "Feature",
  "properties": {
    "gn:admin1_code":"18",
    "gn:admin2_code":"19",
    "gn:asciiname":"Cerro del Viejo",
    "gn:country_code":"MX",
    "gn:dem":1352,
    "gn:feature_class":"P",
    "gn:feature_code":"PPL",
    "gn:name":"Cerro del Viejo",
    "gn:population":26,
    "gn:timezone":"America/Mexico_City",
    "iso:country":"MX",
    "wof:name":"Cerro del Viejo",
    "wof:placetype":"locality",
    "wof:population":26
},
  "geometry": {"coordinates":[-103.86278,21.41833],"type":"Point"}
}