{
  "type": "Feature",
  "properties": {
    "gn:admin1_code":"24",
    "gn:admin2_code":"21.0",
    "gn:asciiname":"Salitrillo",
    "gn:country_code":"MX",
    "gn:dem":1906,
    "gn:feature_class":"P",
    "gn:feature_code":"PPL",
    "gn:name":"Salitrillo",
    "gn:population":341,
    "gn:timezone":"America/Mexico_City",
    "iso:country":"MX",
    "wof:name":"Salitrillo",
    "wof:placetype":"locality",
    "wof:population":341
},
  "geometry": {"coordinates":[-101.03722,22.28417],"type":"Point"}
}