{
  "type": "Feature",
  "properties": {
    "gn:admin1_code":"5",
    "gn:admin2_code":"106.0",
    "gn:asciiname":"Nueva Linda",
    "gn:country_code":"MX",
    "gn:dem":641,
    "gn:feature_class":"P",
    "gn:feature_code":"PPL",
    "gn:name":"Nueva Linda",
    "gn:population":0,
    "gn:timezone":"America/Mexico_City",
    "iso:country":"MX",
    "name:spa_x_preferred":[
        "Nueva Linda"
    ],
    "name:und_x_variant":[
        "Rancho Nuevo Linda"
    ],
    "wof:name":"Nueva Linda",
    "wof:placetype":"locality"
},
  "geometry": {"coordinates":[-92.53203000000001,16.30365],"type":"Point"}
}