{
  "type": "Feature",
  "properties": {
    "gn:admin1_code":"30.0",
    "gn:asciiname":"Santa Cipriana",
    "gn:country_code":"MX",
    "gn:dem":44,
    "gn:feature_class":"P",
    "gn:feature_code":"PPL",
    "gn:name":"Santa Cipriana",
    "gn:population":0,
    "gn:timezone":"America/Mexico_City",
    "iso:country":"MX",
    "name:spa_x_preferred":[
        "Santa Cipriana"
    ],
    "wof:name":"Santa Cipriana",
    "wof:placetype":"locality"
},
  "geometry": {"coordinates":[-97.41024,20.5986],"type":"Point"}
}