{
  "type": "Feature",
  "properties": {
    "gn:admin1_code":"32",
    "gn:admin2_code":"10.0",
    "gn:asciiname":"Rancho la Alegria",
    "gn:country_code":"MX",
    "gn:dem":2070,
    "gn:feature_class":"P",
    "gn:feature_code":"PPL",
    "gn:name":"Rancho la Alegr\u00eda",
    "gn:population":6,
    "gn:timezone":"America/Mexico_City",
    "iso:country":"MX",
    "name:und_x_variant":[
        "Rancho la Alegr\u00eda"
    ],
    "wof:name":"Rancho la Alegria",
    "wof:placetype":"locality",
    "wof:population":6
},
  "geometry": {"coordinates":[-102.93167,23.45111],"type":"Point"}
}