{
  "type": "Feature",
  "properties": {
    "gn:admin1_code":"23.0",
    "gn:asciiname":"Ixpaquina",
    "gn:country_code":"MX",
    "gn:dem":37,
    "gn:feature_class":"P",
    "gn:feature_code":"PPL",
    "gn:name":"Ixpaquin\u00e1",
    "gn:population":0,
    "gn:timezone":"America/Cancun",
    "iso:country":"MX",
    "name:spa_x_preferred":[
        "Ixpaquin\u00e1"
    ],
    "wof:name":"Ixpaquina",
    "wof:placetype":"locality"
},
  "geometry": {"coordinates":[-88.2392,20.13986],"type":"Point"}
}