{
  "type": "Feature",
  "properties": {
    "gn:admin1_code":"26.0",
    "gn:admin2_code":"66.0",
    "gn:asciiname":"La Junta",
    "gn:country_code":"MX",
    "gn:dem":347,
    "gn:feature_class":"P",
    "gn:feature_code":"PPL",
    "gn:name":"La Junta",
    "gn:population":0,
    "gn:timezone":"America/Hermosillo",
    "iso:country":"MX",
    "name:spa_x_preferred":[
        "La Junta"
    ],
    "name:und_x_variant":[
        "Junta"
    ],
    "wof:name":"La Junta",
    "wof:placetype":"locality"
},
  "geometry": {"coordinates":[-110.56316,29.11757],"type":"Point"}
}