{
  "type": "Feature",
  "properties": {
    "gn:admin1_code":"6",
    "gn:admin2_code":"27.0",
    "gn:asciiname":"Rojasarare",
    "gn:country_code":"MX",
    "gn:dem":2136,
    "gn:feature_class":"P",
    "gn:feature_code":"PPL",
    "gn:name":"Rojas\u00e1rare",
    "gn:population":0,
    "gn:timezone":"America/Chihuahua",
    "iso:country":"MX",
    "name:spa_x_preferred":[
        "Rojas\u00e1rare"
    ],
    "wof:name":"Rojasarare",
    "wof:placetype":"locality"
},
  "geometry": {"coordinates":[-107.19172,27.32301],"type":"Point"}
}