{
  "type": "Feature",
  "properties": {
    "gn:admin1_code":"15",
    "gn:admin2_code":"21.0",
    "gn:asciiname":"Piedras Anchas (Primera del Monte)",
    "gn:country_code":"MX",
    "gn:dem":2654,
    "gn:feature_class":"P",
    "gn:feature_code":"PPL",
    "gn:name":"Piedras Anchas (Primera del Monte)",
    "gn:population":989,
    "gn:timezone":"America/Mexico_City",
    "iso:country":"MX",
    "wof:name":"Piedras Anchas (Primera del Monte)",
    "wof:placetype":"locality",
    "wof:population":989
},
  "geometry": {"coordinates":[-99.78232,18.97982],"type":"Point"}
}