{
  "type": "Feature",
  "properties": {
    "gn:admin1_code":"6",
    "gn:admin2_code":"9.0",
    "gn:asciiname":"Huiyochi",
    "gn:country_code":"MX",
    "gn:dem":2266,
    "gn:feature_class":"P",
    "gn:feature_code":"PPL",
    "gn:name":"Huiyochi",
    "gn:population":65,
    "gn:timezone":"America/Chihuahua",
    "iso:country":"MX",
    "wof:name":"Huiyochi",
    "wof:placetype":"locality",
    "wof:population":65
},
  "geometry": {"coordinates":[-107.82771,27.69908],"type":"Point"}
}