{
  "type": "Feature",
  "properties": {
    "gn:admin1_code":"5.0",
    "gn:admin2_code":"61.0",
    "gn:asciiname":"El Cedro",
    "gn:country_code":"MX",
    "gn:dem":597,
    "gn:feature_class":"P",
    "gn:feature_code":"PPL",
    "gn:name":"El Cedro",
    "gn:population":0,
    "gn:timezone":"America/Mexico_City",
    "iso:country":"MX",
    "name:spa_x_preferred":[
        "El Cedro"
    ],
    "wof:name":"El Cedro",
    "wof:placetype":"locality"
},
  "geometry": {"coordinates":[-93.4593,16.95041],"type":"Point"}
}