{
  "type": "Feature",
  "properties": {
    "gn:admin1_code":"15.0",
    "gn:admin2_code":"110.0",
    "gn:asciiname":"Joya de Capulin",
    "gn:country_code":"MX",
    "gn:dem":2072,
    "gn:feature_class":"P",
    "gn:feature_code":"PPL",
    "gn:name":"Joya de Capul\u00edn",
    "gn:population":0,
    "gn:timezone":"America/Mexico_City",
    "iso:country":"MX",
    "name:spa_x_preferred":[
        "Joya de Capul\u00edn"
    ],
    "wof:name":"Joya de Capulin",
    "wof:placetype":"locality"
},
  "geometry": {"coordinates":[-100.13526,19.14535],"type":"Point"}
}