{
  "type": "Feature",
  "properties": {
    "gn:admin1_code":"16",
    "gn:admin2_code":"49.0",
    "gn:asciiname":"Parritas (El Aguacate)",
    "gn:country_code":"MX",
    "gn:dem":1399,
    "gn:feature_class":"P",
    "gn:feature_code":"PPL",
    "gn:name":"Parritas (El Aguacate)",
    "gn:population":138,
    "gn:timezone":"America/Mexico_City",
    "iso:country":"MX",
    "wof:name":"Parritas (El Aguacate)",
    "wof:placetype":"locality",
    "wof:population":138
},
  "geometry": {"coordinates":[-101.16110999999999,19.39111],"type":"Point"}
}