{
  "type": "Feature",
  "properties": {
    "gn:admin1_code":"12",
    "gn:admin2_code":"32.0",
    "gn:asciiname":"Los Hornos",
    "gn:country_code":"MX",
    "gn:dem":1927,
    "gn:feature_class":"P",
    "gn:feature_code":"PPL",
    "gn:name":"Los Hornos",
    "gn:population":8,
    "gn:timezone":"America/Mexico_City",
    "iso:country":"MX",
    "name:nld_x_preferred":[
        "Los Hornos"
    ],
    "name:rus_x_preferred":[
        "\u041b\u043e\u0441-\u041e\u0440\u043d\u043e\u0441"
    ],
    "name:spa_x_preferred":[
        "Los Hornos"
    ],
    "wof:name":"Los Hornos",
    "wof:placetype":"locality",
    "wof:population":8
},
  "geometry": {"coordinates":[-100.12142,17.56497],"type":"Point"}
}