{
  "type": "Feature",
  "properties": {
    "gn:admin1_code":"26",
    "gn:admin2_code":"12.0",
    "gn:asciiname":"El Eslabon",
    "gn:country_code":"MX",
    "gn:dem":138,
    "gn:feature_class":"P",
    "gn:feature_code":"PPL",
    "gn:name":"El Eslab\u00f3n",
    "gn:population":0,
    "gn:timezone":"America/Hermosillo",
    "iso:country":"MX",
    "name:spa_x_preferred":[
        "El Eslab\u00f3n"
    ],
    "wof:name":"El Eslabon",
    "wof:placetype":"locality"
},
  "geometry": {"coordinates":[-110.19167,27.80067],"type":"Point"}
}