{
  "type": "Feature",
  "properties": {
    "gn:admin1_code":"19",
    "gn:admin2_code":"41.0",
    "gn:asciiname":"Las Palmas",
    "gn:country_code":"MX",
    "gn:dem":362,
    "gn:feature_class":"P",
    "gn:feature_code":"PPL",
    "gn:name":"Las Palmas",
    "gn:population":189,
    "gn:timezone":"America/Monterrey",
    "iso:country":"MX",
    "wof:name":"Las Palmas",
    "wof:placetype":"locality",
    "wof:population":189
},
  "geometry": {"coordinates":[-100.07222,25.71389],"type":"Point"}
}