{
  "type": "Feature",
  "properties": {
    "gn:admin1_code":"32",
    "gn:admin2_code":"10.0",
    "gn:asciiname":"Mezquitillo Tercero",
    "gn:country_code":"MX",
    "gn:dem":2052,
    "gn:feature_class":"P",
    "gn:feature_code":"PPL",
    "gn:name":"Mezquitillo Tercero",
    "gn:population":5,
    "gn:timezone":"America/Mexico_City",
    "iso:country":"MX",
    "wof:name":"Mezquitillo Tercero",
    "wof:placetype":"locality",
    "wof:population":5
},
  "geometry": {"coordinates":[-103.0025,23.26889],"type":"Point"}
}