{
  "type": "Feature",
  "properties": {
    "gn:admin1_code":"6",
    "gn:admin2_code":"32.0",
    "gn:asciiname":"La Yerbabuena",
    "gn:country_code":"MX",
    "gn:dem":1778,
    "gn:feature_class":"P",
    "gn:feature_code":"PPL",
    "gn:name":"La Yerbabuena",
    "gn:population":0,
    "gn:timezone":"America/Chihuahua",
    "iso:country":"MX",
    "name:und_x_variant":[
        "Yerbabuena"
    ],
    "wof:name":"La Yerbabuena",
    "wof:placetype":"locality"
},
  "geometry": {"coordinates":[-105.78839000000001,27.0843],"type":"Point"}
}