{
  "type": "Feature",
  "properties": {
    "gn:admin1_code":"10",
    "gn:admin2_code":"34",
    "gn:asciiname":"San Antonio",
    "gn:country_code":"MX",
    "gn:dem":1246,
    "gn:feature_class":"P",
    "gn:feature_code":"PPL",
    "gn:name":"San Antonio",
    "gn:population":37,
    "gn:timezone":"America/Monterrey",
    "iso:country":"MX",
    "wof:name":"San Antonio",
    "wof:placetype":"locality",
    "wof:population":37
},
  "geometry": {"coordinates":[-107.069,25.52052],"type":"Point"}
}