{
  "type": "Feature",
  "properties": {
    "gn:admin1_code":"8.0",
    "gn:admin2_code":"2.0",
    "gn:asciiname":"Las Guasimas (Las Borregas)",
    "gn:country_code":"MX",
    "gn:dem":345,
    "gn:feature_class":"P",
    "gn:feature_code":"PPL",
    "gn:name":"Las Gu\u00e1simas (Las Borregas)",
    "gn:population":516,
    "gn:timezone":"America/Mexico_City",
    "iso:country":"MX",
    "wof:name":"Las Guasimas (Las Borregas)",
    "wof:placetype":"locality",
    "wof:population":516
},
  "geometry": {"coordinates":[-103.72499999999999,19.11639],"type":"Point"}
}