{
  "type": "Feature",
  "properties": {
    "gn:admin1_code":"19",
    "gn:admin2_code":"49.0",
    "gn:asciiname":"Las Haciendas (La Huerta de Manuel Rodriguez)",
    "gn:country_code":"MX",
    "gn:dem":435,
    "gn:feature_class":"P",
    "gn:feature_code":"PPL",
    "gn:name":"Las Haciendas (La Huerta de Manuel Rodr\u00edguez)",
    "gn:population":6,
    "gn:timezone":"America/Monterrey",
    "iso:country":"MX",
    "name:und_x_variant":[
        "Las Haciendas (La Huerta de Manuel Rodr\u00edguez)"
    ],
    "wof:name":"Las Haciendas (La Huerta de Manuel Rodriguez)",
    "wof:placetype":"locality",
    "wof:population":6
},
  "geometry": {"coordinates":[-100.10944000000001,25.48389],"type":"Point"}
}