{
  "type": "Feature",
  "properties": {
    "gn:admin1_code":"12",
    "gn:admin2_code":"22",
    "gn:asciiname":"La Palma (La Palma de los Ochoa)",
    "gn:country_code":"MX",
    "gn:dem":378,
    "gn:feature_class":"P",
    "gn:feature_code":"PPL",
    "gn:name":"La Palma (La Palma de los Ochoa)",
    "gn:population":38,
    "gn:timezone":"America/Mexico_City",
    "iso:country":"MX",
    "wof:name":"La Palma (La Palma de los Ochoa)",
    "wof:placetype":"locality",
    "wof:population":38
},
  "geometry": {"coordinates":[-100.8865,18.2889],"type":"Point"}
}