{
  "type": "Feature",
  "properties": {
    "gn:admin1_code":"6",
    "gn:admin2_code":"27.0",
    "gn:asciiname":"Bachirechi",
    "gn:country_code":"MX",
    "gn:dem":2169,
    "gn:feature_class":"P",
    "gn:feature_code":"PPL",
    "gn:name":"Bachirechi",
    "gn:population":0,
    "gn:timezone":"America/Chihuahua",
    "iso:country":"MX",
    "name:spa_x_preferred":[
        "Bachirechi"
    ],
    "wof:name":"Bachirechi",
    "wof:placetype":"locality"
},
  "geometry": {"coordinates":[-107.30471,27.38896],"type":"Point"}
}