{
  "type": "Feature",
  "properties": {
    "gn:admin1_code":"28.0",
    "gn:admin2_code":"12.0",
    "gn:asciiname":"Agua Marina",
    "gn:country_code":"MX",
    "gn:dem":55,
    "gn:feature_class":"P",
    "gn:feature_code":"PPL",
    "gn:name":"Agua Marina",
    "gn:population":0,
    "gn:timezone":"America/Monterrey",
    "iso:country":"MX",
    "name:spa_x_preferred":[
        "Agua Marina"
    ],
    "wof:name":"Agua Marina",
    "wof:placetype":"locality"
},
  "geometry": {"coordinates":[-98.70361,22.75083],"type":"Point"}
}