{
  "type": "Feature",
  "properties": {
    "gn:admin1_code":"10.0",
    "gn:admin2_code":"34.0",
    "gn:asciiname":"Mesa del Agua",
    "gn:country_code":"MX",
    "gn:dem":1242,
    "gn:feature_class":"P",
    "gn:feature_code":"PPL",
    "gn:name":"Mesa del Agua",
    "gn:population":0,
    "gn:timezone":"America/Monterrey",
    "iso:country":"MX",
    "name:spa_x_preferred":[
        "Mesa del Agua"
    ],
    "wof:name":"Mesa del Agua",
    "wof:placetype":"locality"
},
  "geometry": {"coordinates":[-106.73599,25.45907],"type":"Point"}
}