{
  "type": "Feature",
  "properties": {
    "gn:admin1_code":"11",
    "gn:admin2_code":"7",
    "gn:asciiname":"Chihuahuita",
    "gn:country_code":"MX",
    "gn:dem":1762,
    "gn:feature_class":"P",
    "gn:feature_code":"PPL",
    "gn:name":"Chihuahuita",
    "gn:population":23,
    "gn:timezone":"America/Mexico_City",
    "iso:country":"MX",
    "wof:name":"Chihuahuita",
    "wof:placetype":"locality",
    "wof:population":23
},
  "geometry": {"coordinates":[-100.86972,20.59639],"type":"Point"}
}