{
  "type": "Feature",
  "properties": {
    "gn:admin1_code":"22",
    "gn:admin2_code":"7",
    "gn:asciiname":"Rancho Alba",
    "gn:country_code":"MX",
    "gn:dem":1976,
    "gn:feature_class":"P",
    "gn:feature_code":"PPL",
    "gn:name":"Rancho Alba",
    "gn:population":13,
    "gn:timezone":"America/Mexico_City",
    "iso:country":"MX",
    "wof:name":"Rancho Alba",
    "wof:placetype":"locality",
    "wof:population":13
},
  "geometry": {"coordinates":[-99.91667,20.67306],"type":"Point"}
}