{
  "type": "Feature",
  "properties": {
    "gn:admin1_code":"6",
    "gn:admin2_code":"17",
    "gn:asciiname":"Huerta Salvador Corral",
    "gn:country_code":"MX",
    "gn:dem":2043,
    "gn:feature_class":"P",
    "gn:feature_code":"PPL",
    "gn:name":"Huerta Salvador Corral",
    "gn:population":19,
    "gn:timezone":"America/Chihuahua",
    "iso:country":"MX",
    "wof:name":"Huerta Salvador Corral",
    "wof:placetype":"locality",
    "wof:population":19
},
  "geometry": {"coordinates":[-106.82938,28.41269],"type":"Point"}
}