{
  "type": "Feature",
  "properties": {
    "gn:admin1_code":"11.0",
    "gn:admin2_code":"22.0",
    "gn:asciiname":"La Puerta del Callejon",
    "gn:country_code":"MX",
    "gn:dem":2294,
    "gn:feature_class":"P",
    "gn:feature_code":"PPL",
    "gn:name":"La Puerta del Callej\u00f3n",
    "gn:population":0,
    "gn:timezone":"America/Mexico_City",
    "iso:country":"MX",
    "name:spa_x_preferred":[
        "La Puerta del Callej\u00f3n"
    ],
    "wof:name":"La Puerta del Callejon",
    "wof:placetype":"locality"
},
  "geometry": {"coordinates":[-101.49522,21.67208],"type":"Point"}
}