{
  "type": "Feature",
  "properties": {
    "gn:admin1_code":"22",
    "gn:admin2_code":"9.0",
    "gn:asciiname":"Los Jassos",
    "gn:country_code":"MX",
    "gn:dem":995,
    "gn:feature_class":"P",
    "gn:feature_code":"PPL",
    "gn:name":"Los Jassos",
    "gn:population":0,
    "gn:timezone":"America/Mexico_City",
    "iso:country":"MX",
    "name:und_x_variant":[
        "Jaso",
        "El Jaso",
        "Los Jassos",
        "Los Jasso"
    ],
    "wof:name":"Los Jassos",
    "wof:placetype":"locality"
},
  "geometry": {"coordinates":[-99.4019,21.34992],"type":"Point"}
}