{
  "type": "Feature",
  "properties": {
    "gn:admin1_code":"17",
    "gn:admin2_code":"4.0",
    "gn:asciiname":"Fraccionamiento Villa Dorada",
    "gn:country_code":"MX",
    "gn:dem":1085,
    "gn:feature_class":"P",
    "gn:feature_code":"PPL",
    "gn:name":"Fraccionamiento Villa Dorada",
    "gn:population":7,
    "gn:timezone":"America/Mexico_City",
    "iso:country":"MX",
    "wof:name":"Fraccionamiento Villa Dorada",
    "wof:placetype":"locality",
    "wof:population":7
},
  "geometry": {"coordinates":[-99.00181000000001,18.66574],"type":"Point"}
}