{
  "type": "Feature",
  "properties": {
    "gn:admin1_code":"10",
    "gn:admin2_code":"7.0",
    "gn:asciiname":"El Olivo (Nombre de Dios)",
    "gn:country_code":"MX",
    "gn:dem":1115,
    "gn:feature_class":"P",
    "gn:feature_code":"PPL",
    "gn:name":"El Olivo (Nombre de Dios)",
    "gn:population":7,
    "gn:timezone":"America/Monterrey",
    "iso:country":"MX",
    "wof:name":"El Olivo (Nombre de Dios)",
    "wof:placetype":"locality",
    "wof:population":7
},
  "geometry": {"coordinates":[-103.39951000000001,25.72862000000001],"type":"Point"}
}