{
  "type": "Feature",
  "properties": {
    "gn:admin1_code":"13",
    "gn:admin2_code":"36.0",
    "gn:asciiname":"Zahuastipan",
    "gn:country_code":"MX",
    "gn:dem":1441,
    "gn:feature_class":"P",
    "gn:feature_code":"PPL",
    "gn:name":"Zahuastip\u00e1n",
    "gn:population":0,
    "gn:timezone":"America/Mexico_City",
    "iso:country":"MX",
    "name:spa_x_preferred":[
        "Zahuastip\u00e1n"
    ],
    "name:spa_x_variant":[
        "Zahuastipan"
    ],
    "wof:name":"Zahuastipan",
    "wof:placetype":"locality"
},
  "geometry": {"coordinates":[-98.56310999999999,20.60751],"type":"Point"}
}