{
  "type": "Feature",
  "properties": {
    "gn:admin1_code":"13",
    "gn:admin2_code":"18",
    "gn:asciiname":"La Golondrina",
    "gn:country_code":"MX",
    "gn:dem":960,
    "gn:feature_class":"P",
    "gn:feature_code":"PPL",
    "gn:name":"La Golondrina",
    "gn:population":36,
    "gn:timezone":"America/Mexico_City",
    "iso:country":"MX",
    "wof:name":"La Golondrina",
    "wof:placetype":"locality",
    "wof:population":36
},
  "geometry": {"coordinates":[-98.88603999999999,21.14905],"type":"Point"}
}