{
  "type": "Feature",
  "properties": {
    "gn:admin1_code":"7",
    "gn:admin2_code":"26.0",
    "gn:asciiname":"Ignacio Zaragoza (Casa Blanca)",
    "gn:country_code":"MX",
    "gn:dem":368,
    "gn:feature_class":"P",
    "gn:feature_code":"PPL",
    "gn:name":"Ignacio Zaragoza (Casa Blanca)",
    "gn:population":5,
    "gn:timezone":"America/Monterrey",
    "iso:country":"MX",
    "name:spa_x_preferred":[
        "Ignacio Zaragoza"
    ],
    "name:und_x_variant":[
        "Casa Blanca"
    ],
    "wof:name":"Ignacio Zaragoza (Casa Blanca)",
    "wof:placetype":"locality",
    "wof:population":5
},
  "geometry": {"coordinates":[-101.02356,27.32126],"type":"Point"}
}