{
  "type": "Feature",
  "properties": {
    "gn:admin1_code":"14",
    "gn:admin2_code":"8",
    "gn:asciiname":"Los Encinos",
    "gn:country_code":"MX",
    "gn:dem":2054,
    "gn:feature_class":"P",
    "gn:feature_code":"PPL",
    "gn:name":"Los Encinos",
    "gn:population":33,
    "gn:timezone":"America/Mexico_City",
    "iso:country":"MX",
    "wof:name":"Los Encinos",
    "wof:placetype":"locality",
    "wof:population":33
},
  "geometry": {"coordinates":[-102.30389,20.84694],"type":"Point"}
}