{
  "type": "Feature",
  "properties": {
    "gn:admin1_code":"27",
    "gn:admin2_code":"8.0",
    "gn:asciiname":"Tierra Colorada 1ra. Seccion",
    "gn:country_code":"MX",
    "gn:dem":18,
    "gn:feature_class":"P",
    "gn:feature_code":"PPL",
    "gn:name":"Tierra Colorada 1ra. Secci\u00f3n",
    "gn:population":563,
    "gn:timezone":"America/Mexico_City",
    "iso:country":"MX",
    "name:spa_x_preferred":[
        "Tierra Colorada Primera Secci\u00f3n"
    ],
    "wof:name":"Tierra Colorada 1ra. Seccion",
    "wof:placetype":"locality",
    "wof:population":563
},
  "geometry": {"coordinates":[-93.68556,17.89082999999999],"type":"Point"}
}