{
  "type": "Feature",
  "properties": {
    "gn:admin1_code":"30",
    "gn:admin2_code":"130.0",
    "gn:asciiname":"Arroyo Guadalupe la Palma",
    "gn:country_code":"MX",
    "gn:dem":68,
    "gn:feature_class":"P",
    "gn:feature_code":"PPL",
    "gn:name":"Arroyo Guadalupe la Palma",
    "gn:population":192,
    "gn:timezone":"America/Mexico_City",
    "iso:country":"MX",
    "wof:name":"Arroyo Guadalupe la Palma",
    "wof:placetype":"locality",
    "wof:population":192
},
  "geometry": {"coordinates":[-95.70471999999999,17.82082999999999],"type":"Point"}
}