{
  "type": "Feature",
  "properties": {
    "gn:admin1_code":"20",
    "gn:admin2_code":"330.0",
    "gn:asciiname":"Lazaro Cardenas (Colonia Lazaro Cardenas)",
    "gn:country_code":"MX",
    "gn:dem":1091,
    "gn:feature_class":"P",
    "gn:feature_code":"PPL",
    "gn:name":"L\u00e1zaro C\u00e1rdenas (Colonia L\u00e1zaro C\u00e1rdenas)",
    "gn:population":307,
    "gn:timezone":"America/Mexico_City",
    "iso:country":"MX",
    "name:und_x_variant":[
        "L\u00e1zaro C\u00e1rdenas (Colonia L\u00e1zaro C\u00e1rdenas)"
    ],
    "wof:name":"Lazaro Cardenas (Colonia Lazaro Cardenas)",
    "wof:placetype":"locality",
    "wof:population":307
},
  "geometry": {"coordinates":[-96.70917,17.96667],"type":"Point"}
}