{
  "type": "Feature",
  "properties": {
    "gn:admin1_code":"24",
    "gn:admin2_code":"32.0",
    "gn:asciiname":"Vallecito de la Cruz",
    "gn:country_code":"MX",
    "gn:dem":2005,
    "gn:feature_class":"P",
    "gn:feature_code":"PPL",
    "gn:name":"Vallecito de la Cruz",
    "gn:population":92,
    "gn:timezone":"America/Mexico_City",
    "iso:country":"MX",
    "wof:name":"Vallecito de la Cruz",
    "wof:placetype":"locality",
    "wof:population":92
},
  "geometry": {"coordinates":[-100.41972,21.89111],"type":"Point"}
}