{
  "type": "Feature",
  "properties": {
    "gn:admin1_code":"18.0",
    "gn:admin2_code":"17.0",
    "gn:asciiname":"El Izote",
    "gn:country_code":"MX",
    "gn:dem":1067,
    "gn:feature_class":"P",
    "gn:feature_code":"PPL",
    "gn:name":"El Izote",
    "gn:population":0,
    "gn:timezone":"America/Mazatlan",
    "iso:country":"MX",
    "name:spa_x_preferred":[
        "El Izote"
    ],
    "name:und_x_variant":[
        "Isote",
        "Izote"
    ],
    "wof:name":"El Izote",
    "wof:placetype":"locality"
},
  "geometry": {"coordinates":[-104.96343,21.52178],"type":"Point"}
}