{
  "type": "Feature",
  "properties": {
    "gn:admin1_code":"20",
    "gn:admin2_code":"469.0",
    "gn:asciiname":"Rancho Albino",
    "gn:country_code":"MX",
    "gn:dem":2733,
    "gn:feature_class":"P",
    "gn:feature_code":"PPL",
    "gn:name":"Rancho Albino",
    "gn:population":7,
    "gn:timezone":"America/Mexico_City",
    "iso:country":"MX",
    "wof:name":"Rancho Albino",
    "wof:placetype":"locality",
    "wof:population":7
},
  "geometry": {"coordinates":[-97.93944,17.32944],"type":"Point"}
}