{
  "type": "Feature",
  "properties": {
    "gn:admin1_code":"17.0",
    "gn:asciiname":"Kilometro Quince",
    "gn:country_code":"MX",
    "gn:dem":1661,
    "gn:feature_class":"P",
    "gn:feature_code":"PPL",
    "gn:name":"Kil\u00f3metro Quince",
    "gn:population":0,
    "gn:timezone":"America/Mexico_City",
    "iso:country":"MX",
    "name:spa_x_preferred":[
        "Kil\u00f3metro Quince"
    ],
    "wof:name":"Kilometro Quince",
    "wof:placetype":"locality"
},
  "geometry": {"coordinates":[-99.12121999999999,18.97009],"type":"Point"}
}