{
  "type": "Feature",
  "properties": {
    "gn:admin1_code":"12",
    "gn:admin2_code":"28.0",
    "gn:asciiname":"Chacaltla",
    "gn:country_code":"MX",
    "gn:dem":944,
    "gn:feature_class":"P",
    "gn:feature_code":"PPL",
    "gn:name":"Chacaltl\u00e1",
    "gn:population":173,
    "gn:timezone":"America/Mexico_City",
    "iso:country":"MX",
    "name:und_x_variant":[
        "Chacaltl\u00e1"
    ],
    "wof:name":"Chacaltla",
    "wof:placetype":"locality",
    "wof:population":173
},
  "geometry": {"coordinates":[-99.03367,17.37965],"type":"Point"}
}