{
  "type": "Feature",
  "properties": {
    "gn:admin1_code":"26",
    "gn:admin2_code":"23.0",
    "gn:asciiname":"El Socorro",
    "gn:country_code":"MX",
    "gn:dem":807,
    "gn:feature_class":"P",
    "gn:feature_code":"PPL",
    "gn:name":"El Socorro",
    "gn:population":0,
    "gn:timezone":"America/Hermosillo",
    "iso:country":"MX",
    "name:ceb_x_preferred":[
        "El Socorro"
    ],
    "name:fra_x_preferred":[
        "El Socorro"
    ],
    "name:spa_x_preferred":[
        "El Socorro"
    ],
    "name:swe_x_preferred":[
        "El Socorro"
    ],
    "wof:name":"El Socorro",
    "wof:placetype":"locality"
},
  "geometry": {"coordinates":[-109.79721000000001,30.10581],"type":"Point"}
}