{
  "type": "Feature",
  "properties": {
    "gn:admin1_code":"10",
    "gn:admin2_code":"4.0",
    "gn:asciiname":"San Pedro de Ocuila",
    "gn:country_code":"MX",
    "gn:dem":1655,
    "gn:feature_class":"P",
    "gn:feature_code":"PPL",
    "gn:name":"San Pedro de Ocuila",
    "gn:population":0,
    "gn:timezone":"America/Monterrey",
    "iso:country":"MX",
    "name:und_x_variant":[
        "Ocuila",
        "San Pedro Ocuila",
        "San Pedro de Ocuila"
    ],
    "wof:name":"San Pedro de Ocuila",
    "wof:placetype":"locality"
},
  "geometry": {"coordinates":[-103.68968,24.83108],"type":"Point"}
}