{
  "type": "Feature",
  "properties": {
    "gn:admin1_code":"5",
    "gn:admin2_code":"34",
    "gn:asciiname":"El Morrito",
    "gn:country_code":"MX",
    "gn:dem":669,
    "gn:feature_class":"P",
    "gn:feature_code":"PPL",
    "gn:name":"El Morrito",
    "gn:population":16,
    "gn:timezone":"America/Mexico_City",
    "iso:country":"MX",
    "wof:name":"El Morrito",
    "wof:placetype":"locality",
    "wof:population":16
},
  "geometry": {"coordinates":[-92.12166999999999,15.82722],"type":"Point"}
}