{
  "type": "Feature",
  "properties": {
    "gn:admin1_code":"30.0",
    "gn:admin2_code":"160.0",
    "gn:asciiname":"Chalavito",
    "gn:country_code":"MX",
    "gn:dem":184,
    "gn:feature_class":"P",
    "gn:feature_code":"PPL",
    "gn:name":"Chalavito",
    "gn:population":0,
    "gn:timezone":"America/Mexico_City",
    "iso:country":"MX",
    "name:spa_x_preferred":[
        "Chalavito"
    ],
    "wof:name":"Chalavito",
    "wof:placetype":"locality"
},
  "geometry": {"coordinates":[-97.70155,21.07858],"type":"Point"}
}