{
  "type": "Feature",
  "properties": {
    "gn:admin1_code":"11",
    "gn:admin2_code":"25.0",
    "gn:asciiname":"Fraccionamiento los Angeles",
    "gn:country_code":"MX",
    "gn:dem":1768,
    "gn:feature_class":"P",
    "gn:feature_code":"PPL",
    "gn:name":"Fraccionamiento los \u00c1ngeles",
    "gn:population":259,
    "gn:timezone":"America/Mexico_City",
    "iso:country":"MX",
    "name:und_x_variant":[
        "Fraccionamiento los \u00c1ngeles"
    ],
    "wof:name":"Fraccionamiento los Angeles",
    "wof:placetype":"locality",
    "wof:population":259
},
  "geometry": {"coordinates":[-101.94833,20.89528],"type":"Point"}
}