{
  "type": "Feature",
  "properties": {
    "gn:admin1_code":"30",
    "gn:admin2_code":"174.0",
    "gn:asciiname":"El Saltadero",
    "gn:cc2":"MX",
    "gn:country_code":"MX",
    "gn:dem":150,
    "gn:feature_class":"P",
    "gn:feature_code":"PPL",
    "gn:name":"El Saltadero",
    "gn:population":0,
    "gn:timezone":"America/Mexico_City",
    "iso:country":"MX",
    "name:und_x_variant":[
        "Saltadero",
        "El Saltadero"
    ],
    "wof:name":"El Saltadero",
    "wof:placetype":"locality"
},
  "geometry": {"coordinates":[-96.53333000000001,18.66667],"type":"Point"}
}