{
  "type": "Feature",
  "properties": {
    "gn:admin1_code":"28",
    "gn:admin2_code":"34",
    "gn:asciiname":"Heroes de la Revolucion (La Tamaulipeca)",
    "gn:country_code":"MX",
    "gn:dem":545,
    "gn:feature_class":"P",
    "gn:feature_code":"PPL",
    "gn:name":"H\u00e9roes de la Revoluci\u00f3n (La Tamaulipeca)",
    "gn:population":34,
    "gn:timezone":"America/Monterrey",
    "iso:country":"MX",
    "name:und_x_variant":[
        "H\u00e9roes de la Revoluci\u00f3n (La Tamaulipeca)"
    ],
    "wof:name":"Heroes de la Revolucion (La Tamaulipeca)",
    "wof:placetype":"locality",
    "wof:population":34
},
  "geometry": {"coordinates":[-99.08611000000001,24.73917],"type":"Point"}
}