{
  "type": "Feature",
  "properties": {
    "gn:admin1_code":"30.0",
    "gn:admin2_code":"152.0",
    "gn:asciiname":"Kilometro Cien",
    "gn:country_code":"MX",
    "gn:dem":10,
    "gn:feature_class":"P",
    "gn:feature_code":"PPL",
    "gn:name":"Kil\u00f3metro Cien",
    "gn:population":288,
    "gn:timezone":"America/Mexico_City",
    "iso:country":"MX",
    "name:spa_x_preferred":[
        "Kil\u00f3metro Cien"
    ],
    "wof:name":"Kilometro Cien",
    "wof:placetype":"locality",
    "wof:population":288
},
  "geometry": {"coordinates":[-97.77583,22.07528],"type":"Point"}
}