{
  "type": "Feature",
  "properties": {
    "gn:admin1_code":"16",
    "gn:admin2_code":"38",
    "gn:asciiname":"El Guayabo",
    "gn:country_code":"MX",
    "gn:dem":604,
    "gn:feature_class":"P",
    "gn:feature_code":"PPL",
    "gn:name":"El Guayabo",
    "gn:population":14,
    "gn:timezone":"America/Mexico_City",
    "iso:country":"MX",
    "wof:name":"El Guayabo",
    "wof:placetype":"locality",
    "wof:population":14
},
  "geometry": {"coordinates":[-101.23721999999999,18.67722],"type":"Point"}
}