{
  "type": "Feature",
  "properties": {
    "gn:admin1_code":"30",
    "gn:admin2_code":"91.0",
    "gn:asciiname":"El Tepache",
    "gn:country_code":"MX",
    "gn:dem":30,
    "gn:feature_class":"P",
    "gn:feature_code":"PPL",
    "gn:name":"El Tepache",
    "gn:population":0,
    "gn:timezone":"America/Mexico_City",
    "iso:country":"MX",
    "name:spa_x_preferred":[
        "El Tepache"
    ],
    "wof:name":"El Tepache",
    "wof:placetype":"locality"
},
  "geometry": {"coordinates":[-94.82025,17.50016],"type":"Point"}
}