{
  "type": "Feature",
  "properties": {
    "gn:admin1_code":"5",
    "gn:admin2_code":"46",
    "gn:asciiname":"Los Cocos",
    "gn:country_code":"MX",
    "gn:dem":539,
    "gn:feature_class":"P",
    "gn:feature_code":"PPL",
    "gn:name":"Los Cocos",
    "gn:population":9,
    "gn:timezone":"America/Mexico_City",
    "iso:country":"MX",
    "name:nld_x_preferred":[
        "Los Cocos"
    ],
    "name:por_x_preferred":[
        "Los Cocos"
    ],
    "name:spa_x_preferred":[
        "Los Cocos"
    ],
    "wof:name":"Los Cocos",
    "wof:placetype":"locality",
    "wof:population":9
},
  "geometry": {"coordinates":[-93.66056,16.63],"type":"Point"}
}