{
  "type": "Feature",
  "properties": {
    "gn:admin1_code":"30.0",
    "gn:admin2_code":"155.0",
    "gn:asciiname":"Veredas",
    "gn:country_code":"MX",
    "gn:dem":108,
    "gn:feature_class":"P",
    "gn:feature_code":"PPL",
    "gn:name":"Veredas",
    "gn:population":1,
    "gn:timezone":"America/Mexico_City",
    "iso:country":"MX",
    "name:fra_x_preferred":[
        "Veredas"
    ],
    "name:por_x_preferred":[
        "Veredas"
    ],
    "name:spa_x_preferred":[
        "Veredas"
    ],
    "wof:name":"Veredas",
    "wof:placetype":"locality",
    "wof:population":1
},
  "geometry": {"coordinates":[-98.14389,21.43639],"type":"Point"}
}