{
  "type": "Feature",
  "properties": {
    "gn:admin1_code":"11",
    "gn:admin2_code":"42",
    "gn:asciiname":"La Grulla",
    "gn:country_code":"MX",
    "gn:dem":1702,
    "gn:feature_class":"P",
    "gn:feature_code":"PPL",
    "gn:name":"La Grulla",
    "gn:population":10,
    "gn:timezone":"America/Mexico_City",
    "iso:country":"MX",
    "wof:name":"La Grulla",
    "wof:placetype":"locality",
    "wof:population":10
},
  "geometry": {"coordinates":[-101.37860999999999,20.48333],"type":"Point"}
}