{
  "type": "Feature",
  "properties": {
    "gn:admin1_code":"6",
    "gn:admin2_code":"52.0",
    "gn:asciiname":"San Jose Loma Blanca",
    "gn:country_code":"MX",
    "gn:dem":1245,
    "gn:feature_class":"P",
    "gn:feature_code":"PPL",
    "gn:name":"San Jos\u00e9 Loma Blanca",
    "gn:population":0,
    "gn:timezone":"America/Ojinaga",
    "iso:country":"MX",
    "wof:name":"San Jose Loma Blanca",
    "wof:placetype":"locality"
},
  "geometry": {"coordinates":[-104.50294,29.07851],"type":"Point"}
}