{
  "type": "Feature",
  "properties": {
    "gn:admin1_code":"5",
    "gn:admin2_code":"19.0",
    "gn:asciiname":"Rio Grande",
    "gn:country_code":"MX",
    "gn:dem":1562,
    "gn:feature_class":"P",
    "gn:feature_code":"PPL",
    "gn:name":"R\u00edo Grande",
    "gn:population":841,
    "gn:timezone":"America/Mexico_City",
    "iso:country":"MX",
    "name:und_x_variant":[
        "R\u00edo Grande"
    ],
    "wof:name":"Rio Grande",
    "wof:placetype":"locality",
    "wof:population":841
},
  "geometry": {"coordinates":[-92.12444000000001,16.27944],"type":"Point"}
}