{
  "type": "Feature",
  "properties": {
    "gn:admin1_code":"27",
    "gn:admin2_code":"12.0",
    "gn:asciiname":"Corralillo 2da. Seccion (La Princesa)",
    "gn:country_code":"MX",
    "gn:dem":19,
    "gn:feature_class":"P",
    "gn:feature_code":"PPL",
    "gn:name":"Corralillo 2da. Secci\u00f3n (La Princesa)",
    "gn:population":278,
    "gn:timezone":"America/Mexico_City",
    "iso:country":"MX",
    "name:und_x_variant":[
        "Corralillo 2da. Secci\u00f3n (La Princesa)"
    ],
    "wof:name":"Corralillo 2da. Seccion (La Princesa)",
    "wof:placetype":"locality",
    "wof:population":278
},
  "geometry": {"coordinates":[-92.13667,17.78111],"type":"Point"}
}