{
  "type": "Feature",
  "properties": {
    "gn:admin1_code":"19.0",
    "gn:asciiname":"Las Almas",
    "gn:country_code":"MX",
    "gn:dem":483,
    "gn:feature_class":"P",
    "gn:feature_code":"PPL",
    "gn:name":"Las Almas",
    "gn:population":0,
    "gn:timezone":"America/Monterrey",
    "iso:country":"MX",
    "name:spa_x_preferred":[
        "Las Almas"
    ],
    "wof:name":"Las Almas",
    "wof:placetype":"locality"
},
  "geometry": {"coordinates":[-100.30965,25.86457],"type":"Point"}
}