{
  "type": "Feature",
  "properties": {
    "gn:admin1_code":"14",
    "gn:admin2_code":"95.0",
    "gn:asciiname":"Puerta de la Noria",
    "gn:country_code":"MX",
    "gn:dem":1303,
    "gn:feature_class":"P",
    "gn:feature_code":"PPL",
    "gn:name":"Puerta de la Noria",
    "gn:population":7,
    "gn:timezone":"America/Mexico_City",
    "iso:country":"MX",
    "wof:name":"Puerta de la Noria",
    "wof:placetype":"locality",
    "wof:population":7
},
  "geometry": {"coordinates":[-103.90611,20.69333],"type":"Point"}
}