{
  "type": "Feature",
  "properties": {
    "gn:admin1_code":"6",
    "gn:admin2_code":"31.0",
    "gn:asciiname":"Tacuba",
    "gn:country_code":"MX",
    "gn:dem":2095,
    "gn:feature_class":"P",
    "gn:feature_code":"PPL",
    "gn:name":"Tacuba",
    "gn:population":0,
    "gn:timezone":"America/Chihuahua",
    "iso:country":"MX",
    "name:ceb_x_preferred":[
        "Tacuba"
    ],
    "name:deu_x_preferred":[
        "Tacuba"
    ],
    "name:fra_x_preferred":[
        "Tacuba"
    ],
    "name:ita_x_preferred":[
        "Tacuba"
    ],
    "name:nor_x_preferred":[
        "Tacuba"
    ],
    "name:por_x_preferred":[
        "Tacuba"
    ],
    "name:rus_x_preferred":[
        "\u0422\u0430\u043a\u0443\u0431\u0430"
    ],
    "name:spa_x_preferred":[
        "Tacuba"
    ],
    "name:urd_x_preferred":[
        "\u062a\u0627\u06a9\u0648\u0628\u0627"
    ],
    "name:zho_x_preferred":[
        "\u5854\u5eab\u74e6"
    ],
    "wof:name":"Tacuba",
    "wof:placetype":"locality"
},
  "geometry": {"coordinates":[-107.47320000000001,28.35134],"type":"Point"}
}