{
  "type": "Feature",
  "properties": {
    "gn:admin1_code":"12",
    "gn:admin2_code":"21",
    "gn:asciiname":"Rancho el Trueno (Palmas Blancas)",
    "gn:country_code":"MX",
    "gn:dem":23,
    "gn:feature_class":"P",
    "gn:feature_code":"PPL",
    "gn:name":"Rancho el Trueno (Palmas Blancas)",
    "gn:population":14,
    "gn:timezone":"America/Mexico_City",
    "iso:country":"MX",
    "wof:name":"Rancho el Trueno (Palmas Blancas)",
    "wof:placetype":"locality",
    "wof:population":14
},
  "geometry": {"coordinates":[-100.1249,17.0121],"type":"Point"}
}