{
  "type": "Feature",
  "properties": {
    "gn:admin1_code":"10",
    "gn:admin2_code":"32.0",
    "gn:asciiname":"Santa Rosalia",
    "gn:country_code":"MX",
    "gn:dem":724,
    "gn:feature_class":"P",
    "gn:feature_code":"PPL",
    "gn:name":"Santa Rosal\u00eda",
    "gn:population":0,
    "gn:timezone":"America/Monterrey",
    "iso:country":"MX",
    "wof:name":"Santa Rosalia",
    "wof:placetype":"locality"
},
  "geometry": {"coordinates":[-106.41528,24.95278],"type":"Point"}
}