{
  "type": "Feature",
  "properties": {
    "gn:admin1_code":"30",
    "gn:admin2_code":"8.0",
    "gn:asciiname":"Canontla",
    "gn:country_code":"MX",
    "gn:dem":1946,
    "gn:feature_class":"P",
    "gn:feature_code":"PPL",
    "gn:name":"Ca\u00f1ontla",
    "gn:population":0,
    "gn:timezone":"America/Mexico_City",
    "iso:country":"MX",
    "name:spa_x_preferred":[
        "Ca\u00f1ontla"
    ],
    "wof:name":"Canontla",
    "wof:placetype":"locality"
},
  "geometry": {"coordinates":[-97.10422,19.09731],"type":"Point"}
}