{
  "type": "Feature",
  "properties": {
    "gn:admin1_code":"6",
    "gn:admin2_code":"9",
    "gn:asciiname":"Las Lomas",
    "gn:country_code":"MX",
    "gn:dem":2462,
    "gn:feature_class":"P",
    "gn:feature_code":"PPL",
    "gn:name":"Las Lomas",
    "gn:population":10,
    "gn:timezone":"America/Chihuahua",
    "iso:country":"MX",
    "wof:name":"Las Lomas",
    "wof:placetype":"locality",
    "wof:population":10
},
  "geometry": {"coordinates":[-107.48938,28.00213],"type":"Point"}
}