{
  "type": "Feature",
  "properties": {
    "gn:admin1_code":"14",
    "gn:admin2_code":"15.0",
    "gn:asciiname":"Monte Verde",
    "gn:country_code":"MX",
    "gn:dem":928,
    "gn:feature_class":"P",
    "gn:feature_code":"PPL",
    "gn:name":"Monte Verde",
    "gn:population":5,
    "gn:timezone":"America/Mexico_City",
    "iso:country":"MX",
    "wof:name":"Monte Verde",
    "wof:placetype":"locality",
    "wof:population":5
},
  "geometry": {"coordinates":[-104.32666999999999,19.69083],"type":"Point"}
}