{
  "type": "Feature",
  "properties": {
    "gn:admin1_code":"6.0",
    "gn:admin2_code":"30.0",
    "gn:asciiname":"Los Lobos",
    "gn:country_code":"MX",
    "gn:dem":1560,
    "gn:feature_class":"P",
    "gn:feature_code":"PPL",
    "gn:name":"Los Lobos",
    "gn:population":0,
    "gn:timezone":"America/Chihuahua",
    "iso:country":"MX",
    "name:ces_x_preferred":[
        "Los Lobos"
    ],
    "name:dan_x_preferred":[
        "Los Lobos"
    ],
    "name:deu_x_preferred":[
        "Los Lobos"
    ],
    "name:epo_x_preferred":[
        "Los Lobos"
    ],
    "name:fin_x_preferred":[
        "Los Lobos"
    ],
    "name:fra_x_preferred":[
        "Los Lobos"
    ],
    "name:hrv_x_preferred":[
        "Los Lobos"
    ],
    "name:hun_x_preferred":[
        "Los Lobos"
    ],
    "name:ita_x_preferred":[
        "Los Lobos"
    ],
    "name:jpn_x_preferred":[
        "\u30ed\u30b9\u30fb\u30ed\u30dc\u30b9"
    ],
    "name:nld_x_preferred":[
        "Los Lobos"
    ],
    "name:pol_x_preferred":[
        "Los Lobos"
    ],
    "name:por_x_preferred":[
        "Los Lobos"
    ],
    "name:rus_x_preferred":[
        "Los Lobos"
    ],
    "name:spa_x_preferred":[
        "Los Lobos"
    ],
    "name:swe_x_preferred":[
        "Los Lobos"
    ],
    "name:ukr_x_preferred":[
        "Los Lobos"
    ],
    "wof:name":"Los Lobos",
    "wof:placetype":"locality"
},
  "geometry": {"coordinates":[-108.126,27.36897],"type":"Point"}
}