{
  "type": "Feature",
  "properties": {
    "gn:admin1_code":"11.0",
    "gn:asciiname":"El Jabonero",
    "gn:country_code":"MX",
    "gn:dem":1717,
    "gn:feature_class":"P",
    "gn:feature_code":"PPL",
    "gn:name":"El Jabonero",
    "gn:population":0,
    "gn:timezone":"America/Mexico_City",
    "iso:country":"MX",
    "name:spa_x_preferred":[
        "El Jabonero"
    ],
    "name:spa_x_variant":[
        "Jabonero"
    ],
    "wof:name":"El Jabonero",
    "wof:placetype":"locality"
},
  "geometry": {"coordinates":[-101.14709000000001,20.41548],"type":"Point"}
}