{
  "type": "Feature",
  "properties": {
    "gn:admin1_code":"5",
    "gn:admin2_code":"107.0",
    "gn:asciiname":"Ricardo Flores Magon",
    "gn:country_code":"MX",
    "gn:dem":1200,
    "gn:feature_class":"P",
    "gn:feature_code":"PPL",
    "gn:name":"Ricardo Flores Mag\u00f3n",
    "gn:population":68,
    "gn:timezone":"America/Mexico_City",
    "iso:country":"MX",
    "name:und_x_variant":[
        "Ricardo Flores Mag\u00f3n"
    ],
    "wof:name":"Ricardo Flores Magon",
    "wof:placetype":"locality",
    "wof:population":68
},
  "geometry": {"coordinates":[-93.26778,15.92],"type":"Point"}
}