{
  "type": "Feature",
  "properties": {
    "gn:admin1_code":"27",
    "gn:admin2_code":"2.0",
    "gn:asciiname":"Luis Donaldo Colosio Murrieta",
    "gn:country_code":"MX",
    "gn:dem":19,
    "gn:feature_class":"P",
    "gn:feature_code":"PPL",
    "gn:name":"Luis Donaldo Colosio Murrieta",
    "gn:population":605,
    "gn:timezone":"America/Mexico_City",
    "iso:country":"MX",
    "wof:name":"Luis Donaldo Colosio Murrieta",
    "wof:placetype":"locality",
    "wof:population":605
},
  "geometry": {"coordinates":[-93.34166999999999,18.07806],"type":"Point"}
}