{
  "type": "Feature",
  "properties": {
    "gn:admin1_code":"14",
    "gn:admin2_code":"100.0",
    "gn:asciiname":"El Portezuelo",
    "gn:country_code":"MX",
    "gn:dem":29,
    "gn:feature_class":"P",
    "gn:feature_code":"PPL",
    "gn:name":"El Portezuelo",
    "gn:population":273,
    "gn:timezone":"America/Mexico_City",
    "iso:country":"MX",
    "name:spa_x_preferred":[
        "El Portezuelo"
    ],
    "wof:name":"El Portezuelo",
    "wof:placetype":"locality",
    "wof:population":273
},
  "geometry": {"coordinates":[-105.47556000000002,20.02889],"type":"Point"}
}