{
  "type": "Feature",
  "properties": {
    "gn:admin1_code":"20",
    "gn:admin2_code":"171.0",
    "gn:asciiname":"Agua Jabali",
    "gn:country_code":"MX",
    "gn:dem":615,
    "gn:feature_class":"P",
    "gn:feature_code":"PPL",
    "gn:name":"Agua Jabal\u00ed",
    "gn:population":57,
    "gn:timezone":"America/Mexico_City",
    "iso:country":"MX",
    "name:und_x_variant":[
        "Agua Jabal\u00ed"
    ],
    "wof:name":"Agua Jabali",
    "wof:placetype":"locality",
    "wof:population":57
},
  "geometry": {"coordinates":[-96.64139,18.18306],"type":"Point"}
}