{
  "type": "Feature",
  "properties": {
    "gn:admin1_code":"5.0",
    "gn:asciiname":"La Bolsa",
    "gn:country_code":"MX",
    "gn:dem":11,
    "gn:feature_class":"P",
    "gn:feature_code":"PPL",
    "gn:name":"La Bolsa",
    "gn:population":0,
    "gn:timezone":"America/Mexico_City",
    "iso:country":"MX",
    "name:spa_x_preferred":[
        "La Bolsa"
    ],
    "wof:name":"La Bolsa",
    "wof:placetype":"locality"
},
  "geometry": {"coordinates":[-92.27448,14.62941],"type":"Point"}
}