{
  "type": "Feature",
  "properties": {
    "gn:admin1_code":"10.0",
    "gn:admin2_code":"34.0",
    "gn:asciiname":"La Candonga",
    "gn:country_code":"MX",
    "gn:dem":2435,
    "gn:feature_class":"P",
    "gn:feature_code":"PPL",
    "gn:name":"La Candonga",
    "gn:population":0,
    "gn:timezone":"America/Monterrey",
    "iso:country":"MX",
    "name:spa_x_preferred":[
        "La Candonga"
    ],
    "wof:name":"La Candonga",
    "wof:placetype":"locality"
},
  "geometry": {"coordinates":[-106.76678,25.45084],"type":"Point"}
}