{
  "type": "Feature",
  "properties": {
    "gn:admin1_code":"16.0",
    "gn:admin2_code":"102.0",
    "gn:asciiname":"San Juan Paricutin",
    "gn:country_code":"MX",
    "gn:dem":2277,
    "gn:feature_class":"P",
    "gn:feature_code":"PPL",
    "gn:name":"San Juan Paricutin",
    "gn:population":0,
    "gn:timezone":"America/Mexico_City",
    "iso:country":"MX",
    "name:spa_x_preferred":[
        "San Juan Paricutin"
    ],
    "wof:name":"San Juan Paricutin",
    "wof:placetype":"locality"
},
  "geometry": {"coordinates":[-102.24738000000001,19.53328],"type":"Point"}
}