{
  "type": "Feature",
  "properties": {
    "gn:admin1_code":"30",
    "gn:admin2_code":"100.0",
    "gn:asciiname":"La Firmeza",
    "gn:country_code":"MX",
    "gn:dem":51,
    "gn:feature_class":"P",
    "gn:feature_code":"PPL",
    "gn:name":"La Firmeza",
    "gn:population":269,
    "gn:timezone":"America/Mexico_City",
    "iso:country":"MX",
    "name:spa_x_preferred":[
        "La Firmeza"
    ],
    "wof:name":"La Firmeza",
    "wof:placetype":"locality",
    "wof:population":269
},
  "geometry": {"coordinates":[-96.38977,19.18159],"type":"Point"}
}