{
  "type": "Feature",
  "properties": {
    "gn:admin1_code":"5",
    "gn:admin2_code":"99.0",
    "gn:asciiname":"Coapa",
    "gn:country_code":"MX",
    "gn:dem":690,
    "gn:feature_class":"P",
    "gn:feature_code":"PPL",
    "gn:name":"Coapa",
    "gn:population":0,
    "gn:timezone":"America/Mexico_City",
    "iso:country":"MX",
    "wof:name":"Coapa",
    "wof:placetype":"locality"
},
  "geometry": {"coordinates":[-92.11667,16.03889],"type":"Point"}
}