{
  "type": "Feature",
  "properties": {
    "gn:admin1_code":"10",
    "gn:admin2_code":"18",
    "gn:asciiname":"La Cieneguita",
    "gn:country_code":"MX",
    "gn:dem":1399,
    "gn:feature_class":"P",
    "gn:feature_code":"PPL",
    "gn:name":"La Cieneguita",
    "gn:population":17,
    "gn:timezone":"America/Monterrey",
    "iso:country":"MX",
    "wof:name":"La Cieneguita",
    "wof:placetype":"locality",
    "wof:population":17
},
  "geometry": {"coordinates":[-104.76618000000001,25.37055],"type":"Point"}
}