{
  "type": "Feature",
  "properties": {
    "gn:admin1_code":"16",
    "gn:admin2_code":"69",
    "gn:asciiname":"Cuitzillo Dos [Granja]",
    "gn:country_code":"MX",
    "gn:dem":1685,
    "gn:feature_class":"P",
    "gn:feature_code":"PPL",
    "gn:name":"Cuitzillo Dos [Granja]",
    "gn:population":11,
    "gn:timezone":"America/Mexico_City",
    "iso:country":"MX",
    "wof:name":"Cuitzillo Dos [Granja]",
    "wof:placetype":"locality",
    "wof:population":11
},
  "geometry": {"coordinates":[-101.99639000000001,20.32139],"type":"Point"}
}