{
  "type": "Feature",
  "properties": {
    "gn:admin1_code":"4.0",
    "gn:admin2_code":"3.0",
    "gn:asciiname":"Barragan",
    "gn:country_code":"MX",
    "gn:dem":-1,
    "gn:feature_class":"P",
    "gn:feature_code":"PPL",
    "gn:name":"Barrag\u00e1n",
    "gn:population":0,
    "gn:timezone":"America/Merida",
    "iso:country":"MX",
    "name:deu_x_preferred":[
        "Barrag\u00e1n"
    ],
    "name:fra_x_preferred":[
        "Barragan"
    ],
    "name:nds_x_preferred":[
        "Barrag\u00e1n"
    ],
    "name:rus_x_preferred":[
        "\u0411\u0430\u0440\u0440\u0430\u0433\u0430\u043d"
    ],
    "name:spa_x_preferred":[
        "Barrag\u00e1n"
    ],
    "wof:name":"Barragan",
    "wof:placetype":"locality"
},
  "geometry": {"coordinates":[-91.7838,18.2675],"type":"Point"}
}