{
  "type": "Feature",
  "properties": {
    "gn:admin1_code":"20",
    "gn:admin2_code":"482.0",
    "gn:asciiname":"Pocitos",
    "gn:country_code":"MX",
    "gn:dem":16,
    "gn:feature_class":"P",
    "gn:feature_code":"PPL",
    "gn:name":"Pocitos",
    "gn:population":0,
    "gn:timezone":"America/Mexico_City",
    "iso:country":"MX",
    "name:cat_x_preferred":[
        "Pocitos"
    ],
    "name:deu_x_preferred":[
        "Pocitos"
    ],
    "name:glg_x_preferred":[
        "Pocitos"
    ],
    "name:pol_x_preferred":[
        "Pocitos"
    ],
    "name:por_x_preferred":[
        "Pocitos"
    ],
    "name:spa_x_preferred":[
        "Pocitos"
    ],
    "wof:name":"Pocitos",
    "wof:placetype":"locality"
},
  "geometry": {"coordinates":[-98.00599,16.20385],"type":"Point"}
}