{
  "type": "Feature",
  "properties": {
    "gn:admin1_code":"18",
    "gn:admin2_code":"7",
    "gn:asciiname":"Colonia San Sebastian",
    "gn:country_code":"MX",
    "gn:dem":1913,
    "gn:feature_class":"P",
    "gn:feature_code":"PPL",
    "gn:name":"Colonia San Sebasti\u00e1n",
    "gn:population":38,
    "gn:timezone":"America/Mazatlan",
    "iso:country":"MX",
    "name:und_x_variant":[
        "Colonia San Sebasti\u00e1n"
    ],
    "wof:name":"Colonia San Sebastian",
    "wof:placetype":"locality",
    "wof:population":38
},
  "geometry": {"coordinates":[-104.35944000000001,21.1125],"type":"Point"}
}