{
  "type": "Feature",
  "properties": {
    "gn:admin1_code":"13",
    "gn:admin2_code":"40.0",
    "gn:asciiname":"Macangui",
    "gn:country_code":"MX",
    "gn:dem":1715,
    "gn:feature_class":"P",
    "gn:feature_code":"PPL",
    "gn:name":"Macangui",
    "gn:population":0,
    "gn:timezone":"America/Mexico_City",
    "iso:country":"MX",
    "name:spa_x_preferred":[
        "Macangu\u00ed"
    ],
    "name:spa_x_variant":[
        "Macangui"
    ],
    "wof:name":"Macangui",
    "wof:placetype":"locality"
},
  "geometry": {"coordinates":[-99.1074,21.06724],"type":"Point"}
}