{
  "type": "Feature",
  "properties": {
    "gn:admin1_code":"16",
    "gn:admin2_code":"67",
    "gn:asciiname":"Cerrito de la Gloria",
    "gn:country_code":"MX",
    "gn:dem":1684,
    "gn:feature_class":"P",
    "gn:feature_code":"PPL",
    "gn:name":"Cerrito de la Gloria",
    "gn:population":32,
    "gn:timezone":"America/Mexico_City",
    "iso:country":"MX",
    "wof:name":"Cerrito de la Gloria",
    "wof:placetype":"locality",
    "wof:population":32
},
  "geometry": {"coordinates":[-101.87860999999999,20.19361],"type":"Point"}
}