{
  "type": "Feature",
  "properties": {
    "gn:admin1_code":"32",
    "gn:admin2_code":"38.0",
    "gn:asciiname":"Guadalupe de los Sauces",
    "gn:country_code":"MX",
    "gn:dem":2296,
    "gn:feature_class":"P",
    "gn:feature_code":"PPL",
    "gn:name":"Guadalupe de los Sauces",
    "gn:population":0,
    "gn:timezone":"America/Mexico_City",
    "iso:country":"MX",
    "name:und_x_variant":[
        "Guadalupe los Sauces"
    ],
    "wof:name":"Guadalupe de los Sauces",
    "wof:placetype":"locality"
},
  "geometry": {"coordinates":[-101.44486999999999,22.35876],"type":"Point"}
}