{
  "type": "Feature",
  "properties": {
    "gn:admin1_code":"16",
    "gn:admin2_code":"101",
    "gn:asciiname":"Los Aguacates",
    "gn:country_code":"MX",
    "gn:dem":1093,
    "gn:feature_class":"P",
    "gn:feature_code":"PPL",
    "gn:name":"Los Aguacates",
    "gn:population":15,
    "gn:timezone":"America/Mexico_City",
    "iso:country":"MX",
    "wof:name":"Los Aguacates",
    "wof:placetype":"locality",
    "wof:population":15
},
  "geometry": {"coordinates":[-100.89778,19.53694],"type":"Point"}
}