{
  "type": "Feature",
  "properties": {
    "gn:admin1_code":"15.0",
    "gn:admin2_code":"124.0",
    "gn:asciiname":"Minita del Cedro",
    "gn:country_code":"MX",
    "gn:dem":2771,
    "gn:feature_class":"P",
    "gn:feature_code":"PPL",
    "gn:name":"Minita del Cedro",
    "gn:population":0,
    "gn:timezone":"America/Mexico_City",
    "iso:country":"MX",
    "name:spa_x_preferred":[
        "Minita del Cedro"
    ],
    "name:und_x_variant":[
        "Minita Cedro"
    ],
    "wof:name":"Minita del Cedro",
    "wof:placetype":"locality"
},
  "geometry": {"coordinates":[-100.14039,19.57614],"type":"Point"}
}