{
  "type": "Feature",
  "properties": {
    "gn:admin1_code":"3",
    "gn:admin2_code":"3.0",
    "gn:asciiname":"El Chilerito [Agricola]",
    "gn:country_code":"MX",
    "gn:dem":26,
    "gn:feature_class":"P",
    "gn:feature_code":"PPL",
    "gn:name":"El Chilerito [Agr\u00edcola]",
    "gn:population":5,
    "gn:timezone":"America/Mazatlan",
    "iso:country":"MX",
    "name:und_x_variant":[
        "El Chilerito [Agr\u00edcola]"
    ],
    "wof:name":"El Chilerito [Agricola]",
    "wof:placetype":"locality",
    "wof:population":5
},
  "geometry": {"coordinates":[-110.37094999999999,24.04897],"type":"Point"}
}