{
  "type": "Feature",
  "properties": {
    "gn:admin1_code":"26.0",
    "gn:admin2_code":"58.0",
    "gn:asciiname":"El Rebaje",
    "gn:country_code":"MX",
    "gn:dem":635,
    "gn:feature_class":"P",
    "gn:feature_code":"PPL",
    "gn:name":"El Rebaje",
    "gn:population":0,
    "gn:timezone":"America/Hermosillo",
    "iso:country":"MX",
    "name:und_x_variant":[
        "Rebaje",
        "El Rebaje"
    ],
    "wof:name":"El Rebaje",
    "wof:placetype":"locality"
},
  "geometry": {"coordinates":[-111.24565,30.51298],"type":"Point"}
}