{
  "type": "Feature",
  "properties": {
    "gn:admin1_code":"31",
    "gn:admin2_code":"75",
    "gn:asciiname":"Santa Elena",
    "gn:country_code":"MX",
    "gn:dem":29,
    "gn:feature_class":"P",
    "gn:feature_code":"PPL",
    "gn:name":"Santa Elena",
    "gn:population":21,
    "gn:timezone":"America/Merida",
    "iso:country":"MX",
    "wof:name":"Santa Elena",
    "wof:placetype":"locality",
    "wof:population":21
},
  "geometry": {"coordinates":[-89.18111,20.3375],"type":"Point"}
}