{
  "type": "Feature",
  "properties": {
    "gn:admin1_code":"27",
    "gn:admin2_code":"15",
    "gn:asciiname":"La Esperanza",
    "gn:country_code":"MX",
    "gn:dem":89,
    "gn:feature_class":"P",
    "gn:feature_code":"PPL",
    "gn:name":"La Esperanza",
    "gn:population":16,
    "gn:timezone":"America/Mexico_City",
    "iso:country":"MX",
    "wof:name":"La Esperanza",
    "wof:placetype":"locality",
    "wof:population":16
},
  "geometry": {"coordinates":[-92.70778,17.44444],"type":"Point"}
}