{
  "type": "Feature",
  "properties": {
    "gn:admin1_code":"16.0",
    "gn:admin2_code":"37.0",
    "gn:asciiname":"Huaniqueo de Morales",
    "gn:country_code":"MX",
    "gn:dem":2049,
    "gn:feature_class":"P",
    "gn:feature_code":"PPLA2",
    "gn:name":"Huaniqueo de Morales",
    "gn:population":0,
    "gn:timezone":"America/Mexico_City",
    "iso:country":"MX",
    "name:und_x_variant":[
        "Huaniqueo",
        "Huaniqueo de Morales"
    ],
    "wof:name":"Huaniqueo de Morales",
    "wof:placetype":"locality"
},
  "geometry": {"coordinates":[-101.50449999999999,19.89682],"type":"Point"}
}