{
  "type": "Feature",
  "properties": {
    "gn:admin1_code":"21",
    "gn:admin2_code":"116.0",
    "gn:asciiname":"Alto Lucero",
    "gn:country_code":"MX",
    "gn:dem":2204,
    "gn:feature_class":"P",
    "gn:feature_code":"PPL",
    "gn:name":"Alto Lucero",
    "gn:population":416,
    "gn:timezone":"America/Mexico_City",
    "iso:country":"MX",
    "wof:name":"Alto Lucero",
    "wof:placetype":"locality",
    "wof:population":416
},
  "geometry": {"coordinates":[-97.10509,19.2699],"type":"Point"}
}