{
  "type": "Feature",
  "properties": {
    "gn:admin1_code":"6",
    "gn:admin2_code":"9.0",
    "gn:asciiname":"Huitochi",
    "gn:country_code":"MX",
    "gn:dem":2427,
    "gn:feature_class":"P",
    "gn:feature_code":"PPL",
    "gn:name":"Huitoch\u00ed",
    "gn:population":0,
    "gn:timezone":"America/Chihuahua",
    "iso:country":"MX",
    "name:spa_x_preferred":[
        "Huitoch\u00ed"
    ],
    "wof:name":"Huitochi",
    "wof:placetype":"locality"
},
  "geometry": {"coordinates":[-107.7355,27.7207],"type":"Point"}
}