{
  "type": "Feature",
  "properties": {
    "gn:admin1_code":"14",
    "gn:admin2_code":"93.0",
    "gn:asciiname":"La Loma",
    "gn:country_code":"MX",
    "gn:dem":2041,
    "gn:feature_class":"P",
    "gn:feature_code":"PPL",
    "gn:name":"La Loma",
    "gn:population":7,
    "gn:timezone":"America/Mexico_City",
    "iso:country":"MX",
    "wof:name":"La Loma",
    "wof:placetype":"locality",
    "wof:population":7
},
  "geometry": {"coordinates":[-102.61806,20.86389],"type":"Point"}
}