{
  "type": "Feature",
  "properties": {
    "gn:admin1_code":"7",
    "gn:admin2_code":"2.0",
    "gn:asciiname":"Manga el Colorado",
    "gn:country_code":"MX",
    "gn:dem":525,
    "gn:feature_class":"P",
    "gn:feature_code":"PPL",
    "gn:name":"Manga el Colorado",
    "gn:population":0,
    "gn:timezone":"America/Matamoros",
    "iso:country":"MX",
    "name:spa_x_preferred":[
        "Manga el Colorado"
    ],
    "name:und_x_variant":[
        "El Colorado"
    ],
    "wof:name":"Manga el Colorado",
    "wof:placetype":"locality"
},
  "geometry": {"coordinates":[-102.22101000000001,29.80942000000001],"type":"Point"}
}