{
  "type": "Feature",
  "properties": {
    "gn:admin1_code":"6",
    "gn:admin2_code":"52.0",
    "gn:asciiname":"El Almagre",
    "gn:country_code":"MX",
    "gn:dem":1316,
    "gn:feature_class":"P",
    "gn:feature_code":"PPL",
    "gn:name":"El Almagre",
    "gn:population":0,
    "gn:timezone":"America/Ojinaga",
    "iso:country":"MX",
    "name:und_x_variant":[
        "Rancho El Almagre",
        "El Almagre"
    ],
    "wof:name":"El Almagre",
    "wof:placetype":"locality"
},
  "geometry": {"coordinates":[-104.27059,29.10426],"type":"Point"}
}