{
  "type": "Feature",
  "properties": {
    "gn:admin1_code":"12",
    "gn:admin2_code":"12.0",
    "gn:asciiname":"Ocotitlan",
    "gn:country_code":"MX",
    "gn:dem":554,
    "gn:feature_class":"P",
    "gn:feature_code":"PPL",
    "gn:name":"Ocotitl\u00e1n",
    "gn:population":102,
    "gn:timezone":"America/Mexico_City",
    "iso:country":"MX",
    "name:und_x_variant":[
        "Ocotitl\u00e1n"
    ],
    "wof:name":"Ocotitlan",
    "wof:placetype":"locality",
    "wof:population":102
},
  "geometry": {"coordinates":[-99.03586,17.00527],"type":"Point"}
}