{
  "type": "Feature",
  "properties": {
    "gn:admin1_code":"11",
    "gn:admin2_code":"32",
    "gn:asciiname":"Viborillas",
    "gn:country_code":"MX",
    "gn:dem":2100,
    "gn:feature_class":"P",
    "gn:feature_code":"PPL",
    "gn:name":"Viborillas",
    "gn:population":28,
    "gn:timezone":"America/Mexico_City",
    "iso:country":"MX",
    "wof:name":"Viborillas",
    "wof:placetype":"locality",
    "wof:population":28
},
  "geometry": {"coordinates":[-100.41528,20.98472000000001],"type":"Point"}
}