{
  "type": "Feature",
  "properties": {
    "gn:admin1_code":"15",
    "gn:admin2_code":"82.0",
    "gn:asciiname":"Las Lomas (Los Depositos)",
    "gn:country_code":"MX",
    "gn:dem":558,
    "gn:feature_class":"P",
    "gn:feature_code":"PPL",
    "gn:name":"Las Lomas (Los Dep\u00f3sitos)",
    "gn:population":213,
    "gn:timezone":"America/Mexico_City",
    "iso:country":"MX",
    "name:und_x_variant":[
        "Las Lomas (Los Dep\u00f3sitos)"
    ],
    "wof:name":"Las Lomas (Los Depositos)",
    "wof:placetype":"locality",
    "wof:population":213
},
  "geometry": {"coordinates":[-100.42255,18.77823],"type":"Point"}
}