{
  "type": "Feature",
  "properties": {
    "gn:admin1_code":"18.0",
    "gn:admin2_code":"5.0",
    "gn:asciiname":"Viscuaxtla",
    "gn:country_code":"MX",
    "gn:dem":543,
    "gn:feature_class":"P",
    "gn:feature_code":"PPL",
    "gn:name":"Viscuaxtla",
    "gn:population":34,
    "gn:timezone":"America/Mazatlan",
    "iso:country":"MX",
    "wof:name":"Viscuaxtla",
    "wof:placetype":"locality",
    "wof:population":34
},
  "geometry": {"coordinates":[-105.25667,22.73722],"type":"Point"}
}