{
  "type": "Feature",
  "properties": {
    "gn:admin1_code":"16.0",
    "gn:admin2_code":"2.0",
    "gn:asciiname":"Paso de los Atutos",
    "gn:country_code":"MX",
    "gn:dem":639,
    "gn:feature_class":"P",
    "gn:feature_code":"PPL",
    "gn:name":"Paso de los Atutos",
    "gn:population":0,
    "gn:timezone":"America/Mexico_City",
    "iso:country":"MX",
    "name:spa_x_preferred":[
        "Paso de los Atutos"
    ],
    "wof:name":"Paso de los Atutos",
    "wof:placetype":"locality"
},
  "geometry": {"coordinates":[-102.79327000000001,18.53774],"type":"Point"}
}