{
  "type": "Feature",
  "properties": {
    "gn:admin1_code":"27.0",
    "gn:asciiname":"Miraflores Tercera Seccion",
    "gn:country_code":"MX",
    "gn:dem":57,
    "gn:feature_class":"P",
    "gn:feature_code":"PPL",
    "gn:name":"Miraflores Tercera Secci\u00f3n",
    "gn:population":0,
    "gn:timezone":"America/Mexico_City",
    "iso:country":"MX",
    "name:spa_x_preferred":[
        "Miraflores Tercera Secci\u00f3n"
    ],
    "name:spa_x_variant":[
        "Arroyo Grande Tercera Secci\u00f3n",
        "Miraflores"
    ],
    "wof:name":"Miraflores Tercera Seccion",
    "wof:placetype":"locality"
},
  "geometry": {"coordinates":[-92.73124,17.92637999999999],"type":"Point"}
}