{
  "type": "Feature",
  "properties": {
    "gn:admin1_code":"10",
    "gn:asciiname":"Las Mesitas",
    "gn:country_code":"MX",
    "gn:dem":2243,
    "gn:feature_class":"P",
    "gn:feature_code":"PPL",
    "gn:name":"Las Mesitas",
    "gn:population":0,
    "gn:timezone":"America/Chihuahua",
    "iso:country":"MX",
    "name:spa_x_preferred":[
        "Las Mesitas"
    ],
    "wof:name":"Las Mesitas",
    "wof:placetype":"locality"
},
  "geometry": {"coordinates":[-106.28144,26.60729000000001],"type":"Point"}
}