{
  "type": "Feature",
  "properties": {
    "gn:admin1_code":"30",
    "gn:admin2_code":"141.0",
    "gn:asciiname":"Los Nacimientos de Xogapan",
    "gn:country_code":"MX",
    "gn:dem":558,
    "gn:feature_class":"P",
    "gn:feature_code":"PPL",
    "gn:name":"Los Nacimientos de Xogapan",
    "gn:population":0,
    "gn:timezone":"America/Mexico_City",
    "iso:country":"MX",
    "name:spa_x_preferred":[
        "Los Nacimientos de Xogapan"
    ],
    "name:spa_x_variant":[
        "Francisco I. Madero"
    ],
    "name:und_x_variant":[
        "Nacimiento de Xogapan"
    ],
    "wof:name":"Los Nacimientos de Xogapan",
    "wof:placetype":"locality"
},
  "geometry": {"coordinates":[-95.251,18.52664],"type":"Point"}
}