{
  "type": "Feature",
  "properties": {
    "gn:admin1_code":"11",
    "gn:admin2_code":"7.0",
    "gn:asciiname":"Arreguin de Abajo",
    "gn:country_code":"MX",
    "gn:dem":1754,
    "gn:feature_class":"P",
    "gn:feature_code":"PPL",
    "gn:name":"Arregu\u00edn de Abajo",
    "gn:population":310,
    "gn:timezone":"America/Mexico_City",
    "iso:country":"MX",
    "name:und_x_variant":[
        "Arregu\u00edn de Abajo"
    ],
    "wof:name":"Arreguin de Abajo",
    "wof:placetype":"locality",
    "wof:population":310
},
  "geometry": {"coordinates":[-100.83306,20.47472],"type":"Point"}
}