{
  "type": "Feature",
  "properties": {
    "gn:admin1_code":"12",
    "gn:admin2_code":"45.0",
    "gn:asciiname":"Tecorrales",
    "gn:country_code":"MX",
    "gn:dem":1225,
    "gn:feature_class":"P",
    "gn:feature_code":"PPL",
    "gn:name":"Tecorrales",
    "gn:population":376,
    "gn:timezone":"America/Mexico_City",
    "iso:country":"MX",
    "wof:name":"Tecorrales",
    "wof:placetype":"locality",
    "wof:population":376
},
  "geometry": {"coordinates":[-98.65345000000001,17.89735],"type":"Point"}
}