{
  "type": "Feature",
  "properties": {
    "gn:admin1_code":"8",
    "gn:admin2_code":"2.0",
    "gn:asciiname":"Calhidra de Occidente",
    "gn:country_code":"MX",
    "gn:dem":356,
    "gn:feature_class":"P",
    "gn:feature_code":"PPL",
    "gn:name":"Calhidra de Occidente",
    "gn:population":4,
    "gn:timezone":"America/Mexico_City",
    "iso:country":"MX",
    "wof:name":"Calhidra de Occidente",
    "wof:placetype":"locality",
    "wof:population":4
},
  "geometry": {"coordinates":[-103.77167,19.10417],"type":"Point"}
}