{
  "type": "Feature",
  "properties": {
    "gn:admin1_code":"5",
    "gn:admin2_code":"9.0",
    "gn:asciiname":"El Amatillo",
    "gn:country_code":"MX",
    "gn:dem":6,
    "gn:feature_class":"P",
    "gn:feature_code":"PPL",
    "gn:name":"El Amatillo",
    "gn:population":6,
    "gn:timezone":"America/Mexico_City",
    "iso:country":"MX",
    "wof:name":"El Amatillo",
    "wof:placetype":"locality",
    "wof:population":6
},
  "geometry": {"coordinates":[-93.99611,16.13056],"type":"Point"}
}