{
  "type": "Feature",
  "properties": {
    "gn:admin1_code":"19.0",
    "gn:admin2_code":"35.0",
    "gn:asciiname":"Cinco de Diciembre",
    "gn:country_code":"MX",
    "gn:dem":203,
    "gn:feature_class":"P",
    "gn:feature_code":"PPL",
    "gn:name":"Cinco de Diciembre",
    "gn:population":0,
    "gn:timezone":"America/Monterrey",
    "iso:country":"MX",
    "name:spa_x_preferred":[
        "Cinco de Diciembre"
    ],
    "wof:name":"Cinco de Diciembre",
    "wof:placetype":"locality"
},
  "geometry": {"coordinates":[-99.51730000000001,26.00798],"type":"Point"}
}