{
  "type": "Feature",
  "properties": {
    "gn:admin1_code":"18",
    "gn:admin2_code":"9",
    "gn:asciiname":"La Ladrillera",
    "gn:country_code":"MX",
    "gn:dem":707,
    "gn:feature_class":"P",
    "gn:feature_code":"PPL",
    "gn:name":"La Ladrillera",
    "gn:population":33,
    "gn:timezone":"America/Mazatlan",
    "iso:country":"MX",
    "wof:name":"La Ladrillera",
    "wof:placetype":"locality",
    "wof:population":33
},
  "geometry": {"coordinates":[-104.77361000000001,21.99694],"type":"Point"}
}