{
  "type": "Feature",
  "properties": {
    "gn:admin1_code":"3",
    "gn:admin2_code":"8.0",
    "gn:asciiname":"La Puerta de Hierro",
    "gn:country_code":"MX",
    "gn:dem":81,
    "gn:feature_class":"P",
    "gn:feature_code":"PPL",
    "gn:name":"La Puerta de Hierro",
    "gn:population":84,
    "gn:timezone":"America/Mazatlan",
    "iso:country":"MX",
    "wof:name":"La Puerta de Hierro",
    "wof:placetype":"locality",
    "wof:population":84
},
  "geometry": {"coordinates":[-109.86221999999999,22.90944],"type":"Point"}
}