{
  "type": "Feature",
  "properties": {
    "gn:admin1_code":"5",
    "gn:admin2_code":"92",
    "gn:asciiname":"Rio Blanco",
    "gn:country_code":"MX",
    "gn:dem":343,
    "gn:feature_class":"P",
    "gn:feature_code":"PPL",
    "gn:name":"R\u00edo Blanco",
    "gn:population":48,
    "gn:timezone":"America/Mexico_City",
    "iso:country":"MX",
    "name:und_x_variant":[
        "R\u00edo Blanco"
    ],
    "wof:name":"Rio Blanco",
    "wof:placetype":"locality",
    "wof:population":48
},
  "geometry": {"coordinates":[-93.43832999999999,17.19778],"type":"Point"}
}