{
  "type": "Feature",
  "properties": {
    "gn:admin1_code":"25",
    "gn:admin2_code":"3.0",
    "gn:asciiname":"Otatita",
    "gn:country_code":"MX",
    "gn:dem":319,
    "gn:feature_class":"P",
    "gn:feature_code":"PPL",
    "gn:name":"Otatita",
    "gn:population":0,
    "gn:timezone":"America/Mazatlan",
    "iso:country":"MX",
    "name:spa_x_preferred":[
        "Otatita"
    ],
    "wof:name":"Otatita",
    "wof:placetype":"locality"
},
  "geometry": {"coordinates":[-107.40958999999999,25.37623],"type":"Point"}
}