{
  "type": "Feature",
  "properties": {
    "gn:admin1_code":"18",
    "gn:admin2_code":"9.0",
    "gn:asciiname":"Comal de Penita",
    "gn:country_code":"MX",
    "gn:dem":926,
    "gn:feature_class":"P",
    "gn:feature_code":"PPL",
    "gn:name":"Comal de Pe\u00f1ita",
    "gn:population":116,
    "gn:timezone":"America/Mazatlan",
    "iso:country":"MX",
    "name:und_x_variant":[
        "Comal de Pe\u00f1ita"
    ],
    "wof:name":"Comal de Penita",
    "wof:placetype":"locality",
    "wof:population":116
},
  "geometry": {"coordinates":[-104.64389,21.98611],"type":"Point"}
}