{
  "type": "Feature",
  "properties": {
    "gn:admin1_code":"5",
    "gn:admin2_code":"16",
    "gn:asciiname":"El Piedral",
    "gn:country_code":"MX",
    "gn:dem":25,
    "gn:feature_class":"P",
    "gn:feature_code":"PPL",
    "gn:name":"El Piedral",
    "gn:population":13,
    "gn:timezone":"America/Mexico_City",
    "iso:country":"MX",
    "wof:name":"El Piedral",
    "wof:placetype":"locality",
    "wof:population":13
},
  "geometry": {"coordinates":[-91.99194,17.75889],"type":"Point"}
}