{
  "type": "Feature",
  "properties": {
    "gn:admin1_code":"10",
    "gn:admin2_code":"14.0",
    "gn:asciiname":"Las Cabezas",
    "gn:country_code":"MX",
    "gn:dem":2635,
    "gn:feature_class":"P",
    "gn:feature_code":"PPL",
    "gn:name":"Las Cabezas",
    "gn:population":0,
    "gn:timezone":"America/Monterrey",
    "iso:country":"MX",
    "name:spa_x_preferred":[
        "Las Cabezas"
    ],
    "wof:name":"Las Cabezas",
    "wof:placetype":"locality"
},
  "geometry": {"coordinates":[-104.28706,22.7321],"type":"Point"}
}