{
  "type": "Feature",
  "properties": {
    "gn:admin1_code":"32",
    "gn:admin2_code":"10.0",
    "gn:asciiname":"Los Angeles",
    "gn:country_code":"MX",
    "gn:dem":2155,
    "gn:feature_class":"P",
    "gn:feature_code":"PPL",
    "gn:name":"Los \u00c1ngeles",
    "gn:population":8,
    "gn:timezone":"America/Mexico_City",
    "iso:country":"MX",
    "name:und_x_variant":[
        "Los \u00c1ngeles"
    ],
    "wof:name":"Los Angeles",
    "wof:placetype":"locality",
    "wof:population":8
},
  "geometry": {"coordinates":[-103.19083000000001,23.02944],"type":"Point"}
}