{
  "type": "Feature",
  "properties": {
    "gn:admin1_code":"32",
    "gn:admin2_code":"49",
    "gn:asciiname":"Agua Zarca",
    "gn:country_code":"MX",
    "gn:dem":2671,
    "gn:feature_class":"P",
    "gn:feature_code":"PPL",
    "gn:name":"Agua Zarca",
    "gn:population":11,
    "gn:timezone":"America/Mexico_City",
    "iso:country":"MX",
    "wof:name":"Agua Zarca",
    "wof:placetype":"locality",
    "wof:population":11
},
  "geometry": {"coordinates":[-104.22667,22.72833],"type":"Point"}
}