{
  "type": "Feature",
  "properties": {
    "gn:admin1_code":"27",
    "gn:admin2_code":"6.0",
    "gn:asciiname":"Colonia Santa Isabel",
    "gn:country_code":"MX",
    "gn:dem":12,
    "gn:feature_class":"P",
    "gn:feature_code":"PPL",
    "gn:name":"Colonia Santa Isabel",
    "gn:population":0,
    "gn:timezone":"America/Mexico_City",
    "iso:country":"MX",
    "name:spa_x_preferred":[
        "Santa Isabel"
    ],
    "name:spa_x_variant":[
        "Colonia Santa Isabel"
    ],
    "wof:name":"Colonia Santa Isabel",
    "wof:placetype":"locality"
},
  "geometry": {"coordinates":[-93.07353000000001,18.04847],"type":"Point"}
}