{
  "type": "Feature",
  "properties": {
    "gn:admin1_code":"23",
    "gn:admin2_code":"3.0",
    "gn:asciiname":"Paso Xulul",
    "gn:country_code":"MX",
    "gn:dem":3,
    "gn:feature_class":"P",
    "gn:feature_code":"PPL",
    "gn:name":"Paso Xulul",
    "gn:population":0,
    "gn:timezone":"America/Cancun",
    "iso:country":"MX",
    "name:spa_x_preferred":[
        "Paso Xulul"
    ],
    "name:spa_x_variant":[
        "Paso Xolul"
    ],
    "wof:name":"Paso Xulul",
    "wof:placetype":"locality"
},
  "geometry": {"coordinates":[-87.09958,21.5281],"type":"Point"}
}