{
  "type": "Feature",
  "properties": {
    "gn:country":"MX",
    "gn:fcode":"PPL",
    "gn:population":0,
    "iso:country":"MX",
    "name:ceb_x_preferred":[
        "Mirador"
    ],
    "name:deu_x_preferred":[
        "Mirador"
    ],
    "name:fra_x_preferred":[
        "Mirador"
    ],
    "name:ita_x_preferred":[
        "Mirador"
    ],
    "name:nld_x_preferred":[
        "Mirador"
    ],
    "name:nor_x_preferred":[
        "Mirador"
    ],
    "name:por_x_preferred":[
        "Mirador"
    ],
    "name:rus_x_preferred":[
        "\u041c\u0438\u0440\u0430\u0434\u043e\u0440"
    ],
    "name:spa_x_preferred":[
        "Mirador"
    ],
    "name:srp_x_preferred":[
        "\u041c\u0438\u0440\u0430\u0434\u043e\u0440"
    ],
    "name:swe_x_preferred":[
        "Mirador"
    ],
    "name:vie_x_preferred":[
        "Mirador"
    ],
    "name:vol_x_preferred":[
        "Mirador"
    ],
    "qs_pg:aaroncc":"MX",
    "qs_pg:gn_country":"MX",
    "qs_pg:gn_fcode":"PPL",
    "qs_pg:gn_pop":0,
    "qs_pg:name":"Mirador",
    "qs_pg:name_adm0":"M\u00e9xico",
    "qs_pg:name_adm1":"Chihuahua",
    "qs_pg:photos":32,
    "qs_pg:photos_1k":6,
    "qs_pg:photos_9k":1,
    "qs_pg:photos_9r":2,
    "qs_pg:photos_all":32,
    "qs_pg:photos_sr":2,
    "qs_pg:pop_sr":0,
    "qs_pg:qs_pg_placetype":"neighbourhood",
    "qs_pg:qs_pg_placetype_gp":"Suburb",
    "qs_pg:woe_adm0":23424900,
    "woe:adm0_id":23424900,
    "woe:name_adm0":"M\u00e9xico",
    "woe:name_adm1":"Chihuahua",
    "woe:placetype":"Suburb",
    "wof:name":"Mirador",
    "wof:placetype":"neighbourhood"
},
  "geometry": {"coordinates":[-106.26667,28.95],"type":"Point"}
}