{
  "type": "Feature",
  "properties": {
    "gn:admin1_code":"6",
    "gn:admin2_code":"27",
    "gn:asciiname":"Morizochi",
    "gn:country_code":"MX",
    "gn:dem":2253,
    "gn:feature_class":"P",
    "gn:feature_code":"PPL",
    "gn:name":"Morizochi",
    "gn:population":30,
    "gn:timezone":"America/Chihuahua",
    "iso:country":"MX",
    "wof:name":"Morizochi",
    "wof:placetype":"locality",
    "wof:population":30
},
  "geometry": {"coordinates":[-106.90627000000001,26.82939],"type":"Point"}
}