{
  "type": "Feature",
  "properties": {
    "gn:admin1_code":"24",
    "gn:admin2_code":"37.0",
    "gn:asciiname":"Texochitl",
    "gn:country_code":"MX",
    "gn:dem":315,
    "gn:feature_class":"P",
    "gn:feature_code":"PPL",
    "gn:name":"Texochitl",
    "gn:population":137,
    "gn:timezone":"America/Mexico_City",
    "iso:country":"MX",
    "wof:name":"Texochitl",
    "wof:placetype":"locality",
    "wof:population":137
},
  "geometry": {"coordinates":[-98.81722000000001,21.22583],"type":"Point"}
}