{
  "type": "Feature",
  "properties": {
    "gn:admin1_code":"28.0",
    "gn:admin2_code":"12.0",
    "gn:asciiname":"Felipe Carrillo Puerto",
    "gn:country_code":"MX",
    "gn:dem":56,
    "gn:feature_class":"P",
    "gn:feature_code":"PPL",
    "gn:name":"Felipe Carrillo Puerto",
    "gn:population":0,
    "gn:timezone":"America/Monterrey",
    "iso:country":"MX",
    "name:spa_x_preferred":[
        "Felipe Carrillo Puerto"
    ],
    "wof:name":"Felipe Carrillo Puerto",
    "wof:placetype":"locality"
},
  "geometry": {"coordinates":[-98.87215999999999,22.79708],"type":"Point"}
}