{
  "type": "Feature",
  "properties": {
    "gn:admin1_code":"6",
    "gn:admin2_code":"40.0",
    "gn:asciiname":"El Gavilan",
    "gn:country_code":"MX",
    "gn:dem":1822,
    "gn:feature_class":"P",
    "gn:feature_code":"PPL",
    "gn:name":"El Gavil\u00e1n",
    "gn:population":1,
    "gn:timezone":"America/Chihuahua",
    "iso:country":"MX",
    "name:spa_x_preferred":[
        "El Gavil\u00e1n"
    ],
    "wof:name":"El Gavilan",
    "wof:placetype":"locality",
    "wof:population":1
},
  "geometry": {"coordinates":[-108.65225,29.34589],"type":"Point"}
}