{
  "type": "Feature",
  "properties": {
    "gn:admin1_code":"16",
    "gn:admin2_code":"79",
    "gn:asciiname":"Comiembaro",
    "gn:country_code":"MX",
    "gn:dem":1877,
    "gn:feature_class":"P",
    "gn:feature_code":"PPL",
    "gn:name":"Comi\u00e9mbaro",
    "gn:population":49,
    "gn:timezone":"America/Mexico_City",
    "iso:country":"MX",
    "name:und_x_variant":[
        "Comi\u00e9mbaro"
    ],
    "wof:name":"Comiembaro",
    "wof:placetype":"locality",
    "wof:population":49
},
  "geometry": {"coordinates":[-101.79472,19.37833],"type":"Point"}
}