{
  "type": "Feature",
  "properties": {
    "gn:admin1_code":"26.0",
    "gn:admin2_code":"65.0",
    "gn:asciiname":"El Mulato",
    "gn:country_code":"MX",
    "gn:dem":754,
    "gn:feature_class":"P",
    "gn:feature_code":"PPL",
    "gn:name":"El Mulato",
    "gn:population":0,
    "gn:timezone":"America/Hermosillo",
    "iso:country":"MX",
    "name:spa_x_preferred":[
        "El Mulato"
    ],
    "wof:name":"El Mulato",
    "wof:placetype":"locality"
},
  "geometry": {"coordinates":[-111.30840000000001,30.66867],"type":"Point"}
}