{
  "type": "Feature",
  "properties": {
    "gn:admin1_code":"21",
    "gn:admin2_code":"120.0",
    "gn:asciiname":"Tlachichilco",
    "gn:country_code":"MX",
    "gn:dem":1966,
    "gn:feature_class":"P",
    "gn:feature_code":"PPL",
    "gn:name":"Tlachichilco",
    "gn:population":87,
    "gn:timezone":"America/Mexico_City",
    "iso:country":"MX",
    "name:ceb_x_preferred":[
        "Tlachichilco"
    ],
    "name:epo_x_preferred":[
        "Tlachichilco"
    ],
    "name:eus_x_preferred":[
        "Tlachichilco"
    ],
    "name:spa_x_preferred":[
        "Tlachichilco"
    ],
    "name:srp_x_preferred":[
        "\u041e\u043f\u0448\u0442\u0438\u043d\u0430 \u0422\u043b\u0430\u0447\u0438\u0447\u0438\u043b\u043a\u043e"
    ],
    "name:swe_x_preferred":[
        "Tlachichilco"
    ],
    "name:vie_x_preferred":[
        "Tlachichilco"
    ],
    "wof:name":"Tlachichilco",
    "wof:placetype":"locality",
    "wof:population":87
},
  "geometry": {"coordinates":[-97.28161,18.5074],"type":"Point"}
}