{
  "type": "Feature",
  "properties": {
    "gn:admin1_code":"14",
    "gn:admin2_code":"93.0",
    "gn:asciiname":"El Gueilote de Pegueros",
    "gn:country_code":"MX",
    "gn:dem":2023,
    "gn:feature_class":"P",
    "gn:feature_code":"PPL",
    "gn:name":"El G\u00fcilote de Pegueros",
    "gn:population":8,
    "gn:timezone":"America/Mexico_City",
    "iso:country":"MX",
    "name:und_x_variant":[
        "El G\u00fcilote de Pegueros"
    ],
    "wof:name":"El Gueilote de Pegueros",
    "wof:placetype":"locality",
    "wof:population":8
},
  "geometry": {"coordinates":[-102.63972,20.90583],"type":"Point"}
}