{
  "type": "Feature",
  "properties": {
    "gn:admin1_code":"24",
    "gn:admin2_code":"31",
    "gn:asciiname":"Tortugas",
    "gn:country_code":"MX",
    "gn:dem":901,
    "gn:feature_class":"P",
    "gn:feature_code":"PPL",
    "gn:name":"Tortugas",
    "gn:population":40,
    "gn:timezone":"America/Mexico_City",
    "iso:country":"MX",
    "wof:name":"Tortugas",
    "wof:placetype":"locality",
    "wof:population":40
},
  "geometry": {"coordinates":[-99.44361000000001,21.54306],"type":"Point"}
}