{
  "type": "Feature",
  "properties": {
    "gn:admin1_code":"17",
    "gn:admin2_code":"18.0",
    "gn:asciiname":"Ampliacion de los Amates",
    "gn:country_code":"MX",
    "gn:dem":1407,
    "gn:feature_class":"P",
    "gn:feature_code":"PPL",
    "gn:name":"Ampliaci\u00f3n de los Amates",
    "gn:population":130,
    "gn:timezone":"America/Mexico_City",
    "iso:country":"MX",
    "name:und_x_variant":[
        "Ampliaci\u00f3n de los Amates"
    ],
    "wof:name":"Ampliacion de los Amates",
    "wof:placetype":"locality",
    "wof:population":130
},
  "geometry": {"coordinates":[-99.24111000000001,18.88083],"type":"Point"}
}