{
  "type": "Feature",
  "properties": {
    "gn:admin1_code":"15",
    "gn:admin2_code":"118.0",
    "gn:asciiname":"Ciendabajo (Hacienda de Abajo)",
    "gn:country_code":"MX",
    "gn:dem":2812,
    "gn:feature_class":"P",
    "gn:feature_code":"PPL",
    "gn:name":"Ciendabajo (Hacienda de Abajo)",
    "gn:population":772,
    "gn:timezone":"America/Mexico_City",
    "iso:country":"MX",
    "wof:name":"Ciendabajo (Hacienda de Abajo)",
    "wof:placetype":"locality",
    "wof:population":772
},
  "geometry": {"coordinates":[-99.78222,19.275],"type":"Point"}
}