{
  "type": "Feature",
  "properties": {
    "gn:admin1_code":"31.0",
    "gn:asciiname":"San Martin",
    "gn:country_code":"MX",
    "gn:dem":17,
    "gn:feature_class":"P",
    "gn:feature_code":"PPL",
    "gn:name":"San Mart\u00edn",
    "gn:population":0,
    "gn:timezone":"America/Merida",
    "iso:country":"MX",
    "name:spa_x_preferred":[
        "San Mart\u00edn"
    ],
    "wof:name":"San Martin",
    "wof:placetype":"locality"
},
  "geometry": {"coordinates":[-88.25979,21.22726],"type":"Point"}
}