{
  "type": "Feature",
  "properties": {
    "gn:admin1_code":"12",
    "gn:admin2_code":"21.0",
    "gn:asciiname":"San Nicolas de las Playas",
    "gn:country_code":"MX",
    "gn:dem":9,
    "gn:feature_class":"P",
    "gn:feature_code":"PPL",
    "gn:name":"San Nicol\u00e1s de las Playas",
    "gn:population":253,
    "gn:timezone":"America/Mexico_City",
    "iso:country":"MX",
    "name:und_x_variant":[
        "San Nicol\u00e1s de las Playas"
    ],
    "wof:name":"San Nicolas de las Playas",
    "wof:placetype":"locality",
    "wof:population":253
},
  "geometry": {"coordinates":[-100.00888999999999,16.91778],"type":"Point"}
}