{
  "type": "Feature",
  "properties": {
    "gn:admin1_code":"6",
    "gn:admin2_code":"1.0",
    "gn:asciiname":"El Alamo de Villa",
    "gn:country_code":"MX",
    "gn:dem":1228,
    "gn:feature_class":"P",
    "gn:feature_code":"PPL",
    "gn:name":"El \u00c1lamo de Villa",
    "gn:population":0,
    "gn:timezone":"America/Chihuahua",
    "iso:country":"MX",
    "wof:name":"El Alamo de Villa",
    "wof:placetype":"locality"
},
  "geometry": {"coordinates":[-106.85329,30.5764],"type":"Point"}
}