{
  "type": "Feature",
  "properties": {
    "gn:admin1_code":"30",
    "gn:admin2_code":"91.0",
    "gn:asciiname":"Ruben Real",
    "gn:country_code":"MX",
    "gn:dem":70,
    "gn:feature_class":"P",
    "gn:feature_code":"PPL",
    "gn:name":"Rub\u00e9n Real",
    "gn:population":7,
    "gn:timezone":"America/Mexico_City",
    "iso:country":"MX",
    "name:und_x_variant":[
        "Rub\u00e9n Real"
    ],
    "wof:name":"Ruben Real",
    "wof:placetype":"locality",
    "wof:population":7
},
  "geometry": {"coordinates":[-95.11360999999999,17.47889],"type":"Point"}
}