{
  "type": "Feature",
  "properties": {
    "gn:admin1_code":"12",
    "gn:admin2_code":"24.0",
    "gn:asciiname":"El Guayabo",
    "gn:country_code":"MX",
    "gn:dem":1245,
    "gn:feature_class":"P",
    "gn:feature_code":"PPL",
    "gn:name":"El Guayabo",
    "gn:population":8,
    "gn:timezone":"America/Mexico_City",
    "iso:country":"MX",
    "wof:name":"El Guayabo",
    "wof:placetype":"locality",
    "wof:population":8
},
  "geometry": {"coordinates":[-98.62488,17.81007],"type":"Point"}
}