{
  "type": "Feature",
  "properties": {
    "gn:admin1_code":"30",
    "gn:admin2_code":"114.0",
    "gn:asciiname":"El Ciervo",
    "gn:country_code":"MX",
    "gn:dem":127,
    "gn:feature_class":"P",
    "gn:feature_code":"PPL",
    "gn:name":"El Ciervo",
    "gn:population":0,
    "gn:timezone":"America/Mexico_City",
    "iso:country":"MX",
    "name:cat_x_preferred":[
        "El Ciervo"
    ],
    "name:spa_x_preferred":[
        "El Ciervo"
    ],
    "name:und_x_variant":[
        "San Jos\u00e9 Buenavista"
    ],
    "wof:name":"El Ciervo",
    "wof:placetype":"locality"
},
  "geometry": {"coordinates":[-96.77500000000001,20.02694],"type":"Point"}
}