{
  "type": "Feature",
  "properties": {
    "gn:admin1_code":"12",
    "gn:admin2_code":"53",
    "gn:asciiname":"Sepudo",
    "gn:country_code":"MX",
    "gn:dem":28,
    "gn:feature_class":"P",
    "gn:feature_code":"PPL",
    "gn:name":"Sepudo",
    "gn:population":17,
    "gn:timezone":"America/Mexico_City",
    "iso:country":"MX",
    "wof:name":"Sepudo",
    "wof:placetype":"locality",
    "wof:population":17
},
  "geometry": {"coordinates":[-99.23823,16.74853],"type":"Point"}
}