{
  "type": "Feature",
  "properties": {
    "gn:admin1_code":"27",
    "gn:admin2_code":"17.0",
    "gn:asciiname":"Pomona Primera Seccion",
    "gn:country_code":"MX",
    "gn:dem":16,
    "gn:feature_class":"P",
    "gn:feature_code":"PPL",
    "gn:name":"Pomon\u00e1 Primera Secci\u00f3n",
    "gn:population":0,
    "gn:timezone":"America/Mexico_City",
    "iso:country":"MX",
    "name:spa_x_preferred":[
        "Pomon\u00e1 Primera Secci\u00f3n"
    ],
    "wof:name":"Pomona Primera Seccion",
    "wof:placetype":"locality"
},
  "geometry": {"coordinates":[-91.50042000000001,17.4812],"type":"Point"}
}