{
  "type": "Feature",
  "properties": {
    "gn:admin1_code":"19.0",
    "gn:admin2_code":"14.0",
    "gn:asciiname":"Lagunilla de Castillo",
    "gn:country_code":"MX",
    "gn:dem":1725,
    "gn:feature_class":"P",
    "gn:feature_code":"PPL",
    "gn:name":"Lagunilla de Castillo",
    "gn:population":0,
    "gn:timezone":"America/Monterrey",
    "iso:country":"MX",
    "name:spa_x_preferred":[
        "Lagunilla de Castillo"
    ],
    "wof:name":"Lagunilla de Castillo",
    "wof:placetype":"locality"
},
  "geometry": {"coordinates":[-100.36333,23.49667],"type":"Point"}
}