{
  "type": "Feature",
  "properties": {
    "gn:admin1_code":"5",
    "gn:admin2_code":"59.0",
    "gn:asciiname":"Suschila",
    "gn:country_code":"MX",
    "gn:dem":890,
    "gn:feature_class":"P",
    "gn:feature_code":"PPL",
    "gn:name":"Suschil\u00e1",
    "gn:population":0,
    "gn:timezone":"America/Mexico_City",
    "iso:country":"MX",
    "name:spa_x_preferred":[
        "Suschil\u00e1"
    ],
    "wof:name":"Suschila",
    "wof:placetype":"locality"
},
  "geometry": {"coordinates":[-92.01338,16.85706],"type":"Point"}
}