{
  "type": "Feature",
  "properties": {
    "gn:admin1_code":"6",
    "gn:admin2_code":"30.0",
    "gn:asciiname":"Pedro Jose",
    "gn:country_code":"MX",
    "gn:dem":975,
    "gn:feature_class":"P",
    "gn:feature_code":"PPL",
    "gn:name":"Pedro Jos\u00e9",
    "gn:population":0,
    "gn:timezone":"America/Chihuahua",
    "iso:country":"MX",
    "name:spa_x_preferred":[
        "Pedro Jos\u00e9"
    ],
    "wof:name":"Pedro Jose",
    "wof:placetype":"locality"
},
  "geometry": {"coordinates":[-108.44195000000001,27.49552000000001],"type":"Point"}
}