{
  "type": "Feature",
  "properties": {
    "gn:admin1_code":"25.0",
    "gn:admin2_code":"3.0",
    "gn:asciiname":"El Huejote",
    "gn:country_code":"MX",
    "gn:dem":340,
    "gn:feature_class":"P",
    "gn:feature_code":"PPL",
    "gn:name":"El Huejote",
    "gn:population":221,
    "gn:timezone":"America/Mazatlan",
    "iso:country":"MX",
    "wof:name":"El Huejote",
    "wof:placetype":"locality",
    "wof:population":221
},
  "geometry": {"coordinates":[-107.62296000000001,25.52899],"type":"Point"}
}