{
  "type": "Feature",
  "properties": {
    "gn:admin1_code":"25",
    "gn:admin2_code":"17.0",
    "gn:asciiname":"La Vinateria",
    "gn:country_code":"MX",
    "gn:dem":789,
    "gn:feature_class":"P",
    "gn:feature_code":"PPL",
    "gn:name":"La Vinater\u00eda",
    "gn:population":8,
    "gn:timezone":"America/Mazatlan",
    "iso:country":"MX",
    "name:und_x_variant":[
        "La Vinater\u00eda"
    ],
    "wof:name":"La Vinateria",
    "wof:placetype":"locality",
    "wof:population":8
},
  "geometry": {"coordinates":[-107.98548,26.13729],"type":"Point"}
}