{
  "type": "Feature",
  "properties": {
    "gn:admin1_code":"7.0",
    "gn:admin2_code":"38.0",
    "gn:asciiname":"Barrancos",
    "gn:country_code":"MX",
    "gn:dem":870,
    "gn:feature_class":"P",
    "gn:feature_code":"PPL",
    "gn:name":"Barrancos",
    "gn:population":3,
    "gn:timezone":"America/Monterrey",
    "iso:country":"MX",
    "name:cat_x_preferred":[
        "Barrancos"
    ],
    "name:ceb_x_preferred":[
        "Barrancos"
    ],
    "name:deu_x_preferred":[
        "Barrancos"
    ],
    "name:eus_x_preferred":[
        "Barrancos"
    ],
    "name:fin_x_preferred":[
        "Barrancos"
    ],
    "name:fra_x_preferred":[
        "Barrancos"
    ],
    "name:hun_x_preferred":[
        "Barrancos"
    ],
    "name:ita_x_preferred":[
        "Barrancos"
    ],
    "name:msa_x_preferred":[
        "Barrancos"
    ],
    "name:nld_x_preferred":[
        "Barrancos"
    ],
    "name:nor_x_preferred":[
        "Barrancos"
    ],
    "name:pol_x_preferred":[
        "Barrancos"
    ],
    "name:por_x_preferred":[
        "Barrancos"
    ],
    "name:rus_x_preferred":[
        "\u0411\u0430\u0440\u0440\u0430\u043d\u043a\u0443\u0448"
    ],
    "name:spa_x_preferred":[
        "Barrancos"
    ],
    "name:tur_x_preferred":[
        "Barrancos"
    ],
    "name:ukr_x_preferred":[
        "\u0411\u0430\u0440\u0440\u0430\u043d\u043a\u0443\u0448"
    ],
    "name:vie_x_preferred":[
        "Barrancos"
    ],
    "name:vol_x_preferred":[
        "Barrancos"
    ],
    "name:war_x_preferred":[
        "Barrancos"
    ],
    "name:zho_x_preferred":[
        "\u5df4\u862d\u79d1\u65af"
    ],
    "wof:name":"Barrancos",
    "wof:placetype":"locality",
    "wof:population":3
},
  "geometry": {"coordinates":[-101.53845,28.59053],"type":"Point"}
}