{
  "type": "Feature",
  "properties": {
    "gn:admin1_code":"11",
    "gn:admin2_code":"6.0",
    "gn:asciiname":"Platero",
    "gn:country_code":"MX",
    "gn:dem":1877,
    "gn:feature_class":"P",
    "gn:feature_code":"PPL",
    "gn:name":"Platero",
    "gn:population":0,
    "gn:timezone":"America/Mexico_City",
    "iso:country":"MX",
    "wof:name":"Platero",
    "wof:placetype":"locality"
},
  "geometry": {"coordinates":[-99.85138999999999,21.25778],"type":"Point"}
}