{
  "type": "Feature",
  "properties": {
    "gn:admin1_code":"11",
    "gn:admin2_code":"6.0",
    "gn:asciiname":"Platero",
    "gn:country_code":"MX",
    "gn:dem":1877,
    "gn:feature_class":"P",
    "gn:feature_code":"PPL",
    "gn:name":"Platero",
    "gn:population":0,
    "gn:timezone":"America/Mexico_City",
    "iso:country":"MX",
    "name:ara_x_preferred":[
        "\u0628\u0644\u0627\u062a\u064a\u0631\u0648 \u0648\u0623\u0646\u0627"
    ],
    "name:heb_x_preferred":[
        "\u05e4\u05dc\u05d8\u05e8\u05d5 \u05d5\u05d0\u05e0\u05d9"
    ],
    "name:zho_x_preferred":[
        "\u5c0f\u94f6\u548c\u6211"
    ],
    "wof:name":"Platero",
    "wof:placetype":"locality"
},
  "geometry": {"coordinates":[-99.85138999999999,21.25778],"type":"Point"}
}