{
  "type": "Feature",
  "properties": {
    "gn:admin1_code":"1",
    "gn:admin2_code":"1.0",
    "gn:asciiname":"Los Arbolitos [Rancho]",
    "gn:country_code":"MX",
    "gn:dem":1864,
    "gn:feature_class":"P",
    "gn:feature_code":"PPL",
    "gn:name":"Los Arbolitos [Rancho]",
    "gn:population":7,
    "gn:timezone":"America/Mexico_City",
    "iso:country":"MX",
    "wof:name":"Los Arbolitos [Rancho]",
    "wof:placetype":"locality",
    "wof:population":7
},
  "geometry": {"coordinates":[-102.35722,21.78028],"type":"Point"}
}