{
  "type": "Feature",
  "properties": {
    "gn:admin1_code":"28",
    "gn:admin2_code":"21.0",
    "gn:asciiname":"La Trinidad",
    "gn:country_code":"MX",
    "gn:dem":70,
    "gn:feature_class":"P",
    "gn:feature_code":"PPL",
    "gn:name":"La Trinidad",
    "gn:population":5,
    "gn:timezone":"America/Monterrey",
    "iso:country":"MX",
    "wof:name":"La Trinidad",
    "wof:placetype":"locality",
    "wof:population":5
},
  "geometry": {"coordinates":[-98.96583,22.76528],"type":"Point"}
}