{
  "type": "Feature",
  "properties": {
    "gn:admin1_code":"28",
    "gn:admin2_code":"21.0",
    "gn:asciiname":"La Trinidad",
    "gn:country_code":"MX",
    "gn:dem":70,
    "gn:feature_class":"P",
    "gn:feature_code":"PPL",
    "gn:name":"La Trinidad",
    "gn:population":5,
    "gn:timezone":"America/Monterrey",
    "iso:country":"MX",
    "name:ceb_x_preferred":[
        "La Trinidad"
    ],
    "name:deu_x_preferred":[
        "La Trinidad"
    ],
    "name:ita_x_preferred":[
        "La Trinidad"
    ],
    "name:nld_x_preferred":[
        "La Trinidad"
    ],
    "name:srp_x_preferred":[
        "\u041b\u0430 \u0422\u0440\u0438\u043d\u0438\u0434\u0430\u0434"
    ],
    "name:swe_x_preferred":[
        "La Trinidad"
    ],
    "name:vie_x_preferred":[
        "La Trinidad"
    ],
    "wof:name":"La Trinidad",
    "wof:placetype":"locality",
    "wof:population":5
},
  "geometry": {"coordinates":[-98.96583,22.76528],"type":"Point"}
}