{
  "type": "Feature",
  "properties": {
    "gn:admin1_code":"30",
    "gn:admin2_code":"171.0",
    "gn:asciiname":"Tepanzacualco",
    "gn:country_code":"MX",
    "gn:dem":1890,
    "gn:feature_class":"P",
    "gn:feature_code":"PPL",
    "gn:name":"Tepanzacualco",
    "gn:population":0,
    "gn:timezone":"America/Mexico_City",
    "iso:country":"MX",
    "name:spa_x_preferred":[
        "Tepanzacualco"
    ],
    "wof:name":"Tepanzacualco",
    "wof:placetype":"locality"
},
  "geometry": {"coordinates":[-97.04688,18.58912],"type":"Point"}
}