{
  "type": "Feature",
  "properties": {
    "gn:admin1_code":"5",
    "gn:admin2_code":"80.0",
    "gn:asciiname":"Santa Isabel Zijan (La Frailesca)",
    "gn:country_code":"MX",
    "gn:dem":1781,
    "gn:feature_class":"P",
    "gn:feature_code":"PPL",
    "gn:name":"Santa Isabel Zij\u00e1n (La Frailesca)",
    "gn:population":117,
    "gn:timezone":"America/Mexico_City",
    "iso:country":"MX",
    "name:und_x_variant":[
        "Santa Isabel Zij\u00e1n (La Frailesca)"
    ],
    "wof:name":"Santa Isabel Zijan (La Frailesca)",
    "wof:placetype":"locality",
    "wof:population":117
},
  "geometry": {"coordinates":[-92.57083,15.55083],"type":"Point"}
}