{
  "type": "Feature",
  "properties": {
    "gn:admin1_code":"16.0",
    "gn:admin2_code":"38.0",
    "gn:asciiname":"Vuelta Grande",
    "gn:country_code":"MX",
    "gn:dem":394,
    "gn:feature_class":"P",
    "gn:feature_code":"PPL",
    "gn:name":"Vuelta Grande",
    "gn:population":47,
    "gn:timezone":"America/Mexico_City",
    "iso:country":"MX",
    "name:spa_x_preferred":[
        "Vuelta Grande"
    ],
    "name:und_x_variant":[
        "La Vuelta Grande"
    ],
    "wof:name":"Vuelta Grande",
    "wof:placetype":"locality",
    "wof:population":47
},
  "geometry": {"coordinates":[-101.09375,18.78131],"type":"Point"}
}