{
  "type": "Feature",
  "properties": {
    "gn:admin1_code":"30",
    "gn:admin2_code":"65.0",
    "gn:asciiname":"Palmar de Perez",
    "gn:country_code":"MX",
    "gn:dem":703,
    "gn:feature_class":"P",
    "gn:feature_code":"PPL",
    "gn:name":"Palmar de P\u00e9rez",
    "gn:population":0,
    "gn:timezone":"America/Mexico_City",
    "iso:country":"MX",
    "name:spa_x_preferred":[
        "Palmar de P\u00e9rez"
    ],
    "name:und_x_variant":[
        "Palmas de P\u00e9rez"
    ],
    "wof:name":"Palmar de Perez",
    "wof:placetype":"locality"
},
  "geometry": {"coordinates":[-96.73182,19.38792],"type":"Point"}
}