{
  "type": "Feature",
  "properties": {
    "gn:admin1_code":"10.0",
    "gn:admin2_code":"2.0",
    "gn:asciiname":"Los Fresnos",
    "gn:country_code":"MX",
    "gn:dem":1862,
    "gn:feature_class":"P",
    "gn:feature_code":"PPL",
    "gn:name":"Los Fresnos",
    "gn:population":0,
    "gn:timezone":"America/Monterrey",
    "iso:country":"MX",
    "name:spa_x_preferred":[
        "Los Fresnos"
    ],
    "wof:name":"Los Fresnos",
    "wof:placetype":"locality"
},
  "geometry": {"coordinates":[-106.53364999999999,25.09085],"type":"Point"}
}