{
  "type": "Feature",
  "properties": {
    "gn:admin1_code":"24",
    "gn:admin2_code":"47.0",
    "gn:asciiname":"Ojo de Agua de Rodriguez",
    "gn:country_code":"MX",
    "gn:dem":2166,
    "gn:feature_class":"P",
    "gn:feature_code":"PPL",
    "gn:name":"Ojo de Agua de Rodr\u00edguez",
    "gn:population":86,
    "gn:timezone":"America/Mexico_City",
    "iso:country":"MX",
    "name:und_x_variant":[
        "Ojo de Agua de Rodr\u00edguez"
    ],
    "wof:name":"Ojo de Agua de Rodriguez",
    "wof:placetype":"locality",
    "wof:population":86
},
  "geometry": {"coordinates":[-100.84222,23.46833],"type":"Point"}
}