{
  "type": "Feature",
  "properties": {
    "gn:admin1_code":"13",
    "gn:admin2_code":"31.0",
    "gn:asciiname":"Agua Fria Chica",
    "gn:country_code":"MX",
    "gn:dem":1536,
    "gn:feature_class":"P",
    "gn:feature_code":"PPL",
    "gn:name":"Agua Fr\u00eda Chica",
    "gn:population":0,
    "gn:timezone":"America/Mexico_City",
    "iso:country":"MX",
    "name:spa_x_preferred":[
        "Agua Fr\u00eda Chica"
    ],
    "wof:name":"Agua Fria Chica",
    "wof:placetype":"locality"
},
  "geometry": {"coordinates":[-99.2011,20.9617],"type":"Point"}
}