{
  "type": "Feature",
  "properties": {
    "gn:admin1_code":"24.0",
    "gn:admin2_code":"42.0",
    "gn:asciiname":"San Miguel Tampacayal",
    "gn:country_code":"MX",
    "gn:dem":52,
    "gn:feature_class":"P",
    "gn:feature_code":"PPL",
    "gn:name":"San Miguel Tampacayal",
    "gn:population":7,
    "gn:timezone":"America/Mexico_City",
    "iso:country":"MX",
    "name:spa_x_preferred":[
        "San Miguel Tampacayal"
    ],
    "wof:name":"San Miguel Tampacayal",
    "wof:placetype":"locality",
    "wof:population":7
},
  "geometry": {"coordinates":[-98.65139000000001,21.58139],"type":"Point"}
}