{
  "type": "Feature",
  "properties": {
    "gn:admin1_code":"27",
    "gn:admin2_code":"4.0",
    "gn:asciiname":"Rancheria la Manga Segunda Seccion",
    "gn:country_code":"MX",
    "gn:dem":9,
    "gn:feature_class":"P",
    "gn:feature_code":"PPL",
    "gn:name":"Rancher\u00eda la Manga Segunda Secci\u00f3n",
    "gn:population":0,
    "gn:timezone":"America/Mexico_City",
    "iso:country":"MX",
    "name:spa_x_preferred":[
        "La Manga Segunda Secci\u00f3n"
    ],
    "name:spa_x_variant":[
        "Rancher\u00eda la Manga Segunda Secci\u00f3n"
    ],
    "wof:name":"Rancheria la Manga Segunda Seccion",
    "wof:placetype":"locality"
},
  "geometry": {"coordinates":[-92.87273999999999,18.00946],"type":"Point"}
}