{
  "type": "Feature",
  "properties": {
    "gn:admin1_code":"5",
    "gn:admin2_code":"21.0",
    "gn:asciiname":"Filadelfia",
    "gn:country_code":"MX",
    "gn:dem":1045,
    "gn:feature_class":"P",
    "gn:feature_code":"PPL",
    "gn:name":"Filadelfia",
    "gn:population":0,
    "gn:timezone":"America/Mexico_City",
    "iso:country":"MX",
    "name:ara_x_preferred":[
        "\u0641\u064a\u0644\u0627\u062f\u0644\u0641\u064a\u0627"
    ],
    "name:cat_x_preferred":[
        "Filad\u00e8lfia"
    ],
    "name:deu_x_preferred":[
        "Filadelfia"
    ],
    "name:epo_x_preferred":[
        "Filadelfio"
    ],
    "name:eus_x_preferred":[
        "Filadelfia"
    ],
    "name:fas_x_preferred":[
        "\u0641\u06cc\u0644\u0627\u062f\u0644\u0641\u06cc\u0627"
    ],
    "name:fin_x_preferred":[
        "Filadelfia"
    ],
    "name:fra_x_preferred":[
        "Filadelfia"
    ],
    "name:grn_x_preferred":[
        "Filadelfia"
    ],
    "name:ita_x_preferred":[
        "Filadelfia"
    ],
    "name:jpn_x_preferred":[
        "\u30d5\u30a3\u30e9\u30c7\u30eb\u30d5\u30a3\u30a2"
    ],
    "name:kat_x_preferred":[
        "\u10e4\u10d8\u10da\u10d0\u10d3\u10d4\u10da\u10e4\u10d8\u10d0"
    ],
    "name:kor_x_preferred":[
        "\ud544\ub77c\ub378\ud53c\uc544"
    ],
    "name:lit_x_preferred":[
        "Filadelfija"
    ],
    "name:nld_x_preferred":[
        "Filadelfia"
    ],
    "name:pdc_x_preferred":[
        "Filadelfia"
    ],
    "name:pol_x_preferred":[
        "Filadelfia"
    ],
    "name:por_x_preferred":[
        "Filadelfia"
    ],
    "name:ron_x_preferred":[
        "Filadelfia"
    ],
    "name:rus_x_preferred":[
        "\u0424\u0438\u043b\u0430\u0434\u0435\u043b\u044c\u0444\u0438\u044f"
    ],
    "name:sco_x_preferred":[
        "Filadelfia"
    ],
    "name:spa_x_preferred":[
        "Filadelfia"
    ],
    "name:ukr_x_preferred":[
        "\u0424\u0456\u043b\u0430\u0434\u0435\u043b\u044c\u0444\u0456\u044f"
    ],
    "name:urd_x_preferred":[
        "\u0641\u06cc\u0644\u0627\u062f\u06cc\u0644\u0641\u06cc\u0627"
    ],
    "name:war_x_preferred":[
        "Filadelfia"
    ],
    "wof:name":"Filadelfia",
    "wof:placetype":"locality"
},
  "geometry": {"coordinates":[-93.28333000000001,17.03333],"type":"Point"}
}