{
  "type": "Feature",
  "properties": {
    "gn:admin1_code":"20",
    "gn:admin2_code":"177.0",
    "gn:asciiname":"San Francisco Tutepetongo",
    "gn:cc2":"MX",
    "gn:country_code":"MX",
    "gn:dem":1566,
    "gn:feature_class":"P",
    "gn:feature_code":"PPL",
    "gn:name":"San Francisco Tutepetongo",
    "gn:population":694,
    "gn:timezone":"America/Mexico_City",
    "iso:country":"MX",
    "name:und_x_variant":[
        "Tuxtepetongo",
        "Tutepetongo",
        "San Francisco Tutepetongo"
    ],
    "wof:name":"San Francisco Tutepetongo",
    "wof:placetype":"locality",
    "wof:population":694
},
  "geometry": {"coordinates":[-96.88083,17.71611],"type":"Point"}
}