{
  "type": "Feature",
  "properties": {
    "gn:admin1_code":"24",
    "gn:admin2_code":"43.0",
    "gn:asciiname":"Salsipuedes",
    "gn:country_code":"MX",
    "gn:dem":1737,
    "gn:feature_class":"P",
    "gn:feature_code":"PPL",
    "gn:name":"Salsipuedes",
    "gn:population":0,
    "gn:timezone":"America/Mexico_City",
    "iso:country":"MX",
    "name:ceb_x_preferred":[
        "Salsipuedes"
    ],
    "name:spa_x_preferred":[
        "Salsipuedes"
    ],
    "name:swe_x_preferred":[
        "Salsipuedes"
    ],
    "wof:name":"Salsipuedes",
    "wof:placetype":"locality"
},
  "geometry": {"coordinates":[-100.61667,21.71667],"type":"Point"}
}