{
  "type": "Feature",
  "properties": {
    "gn:admin1_code":"1.0",
    "gn:admin2_code":"1.0",
    "gn:asciiname":"Piedras Chinas",
    "gn:country_code":"MX",
    "gn:dem":1891,
    "gn:feature_class":"P",
    "gn:feature_code":"PPL",
    "gn:name":"Piedras Chinas",
    "gn:population":0,
    "gn:timezone":"America/Mexico_City",
    "iso:country":"MX",
    "name:spa_x_preferred":[
        "Piedras Chinas"
    ],
    "wof:name":"Piedras Chinas",
    "wof:placetype":"locality"
},
  "geometry": {"coordinates":[-102.39946,21.67957],"type":"Point"}
}