{
  "type": "Feature",
  "properties": {
    "gn:admin1_code":"20.0",
    "gn:admin2_code":"370.0",
    "gn:asciiname":"La Laguna",
    "gn:country_code":"MX",
    "gn:dem":2211,
    "gn:feature_class":"P",
    "gn:feature_code":"PPL",
    "gn:name":"La Laguna",
    "gn:population":0,
    "gn:timezone":"America/Mexico_City",
    "iso:country":"MX",
    "name:spa_x_preferred":[
        "La Laguna"
    ],
    "wof:name":"La Laguna",
    "wof:placetype":"locality"
},
  "geometry": {"coordinates":[-97.53892999999999,17.35725],"type":"Point"}
}