{
  "type": "Feature",
  "properties": {
    "gn:admin1_code":"26.0",
    "gn:admin2_code":"57.0",
    "gn:asciiname":"El Limbo",
    "gn:cc2":"MX",
    "gn:country_code":"MX",
    "gn:dem":483,
    "gn:feature_class":"P",
    "gn:feature_code":"PPL",
    "gn:name":"El Limbo",
    "gn:population":13,
    "gn:timezone":"America/Hermosillo",
    "iso:country":"MX",
    "name:und_x_variant":[
        "Limbo",
        "El Limbo"
    ],
    "wof:name":"El Limbo",
    "wof:placetype":"locality",
    "wof:population":13
},
  "geometry": {"coordinates":[-109.60583,29.31833],"type":"Point"}
}