{
  "type": "Feature",
  "properties": {
    "gn:admin1_code":"30.0",
    "gn:admin2_code":"60.0",
    "gn:asciiname":"Don Alfredo",
    "gn:country_code":"MX",
    "gn:dem":19,
    "gn:feature_class":"P",
    "gn:feature_code":"PPL",
    "gn:name":"Don Alfredo",
    "gn:population":3,
    "gn:timezone":"America/Mexico_City",
    "iso:country":"MX",
    "name:spa_x_preferred":[
        "Don Alfredo"
    ],
    "wof:name":"Don Alfredo",
    "wof:placetype":"locality",
    "wof:population":3
},
  "geometry": {"coordinates":[-97.58336,21.36265],"type":"Point"}
}