{
  "type": "Feature",
  "properties": {
    "gn:admin1_code":"19.0",
    "gn:admin2_code":"15.0",
    "gn:asciiname":"Las Tres Palmas",
    "gn:country_code":"MX",
    "gn:dem":127,
    "gn:feature_class":"P",
    "gn:feature_code":"PPL",
    "gn:name":"Las Tres Palmas",
    "gn:population":0,
    "gn:timezone":"America/Monterrey",
    "iso:country":"MX",
    "name:spa_x_preferred":[
        "Las Tres Palmas"
    ],
    "wof:name":"Las Tres Palmas",
    "wof:placetype":"locality"
},
  "geometry": {"coordinates":[-99.01679,25.94226],"type":"Point"}
}