{
  "type": "Feature",
  "properties": {
    "gn:admin1_code":"5",
    "gn:asciiname":"San Bartolo",
    "gn:country_code":"MX",
    "gn:dem":5,
    "gn:feature_class":"P",
    "gn:feature_code":"PPL",
    "gn:name":"San Bartolo",
    "gn:population":0,
    "gn:timezone":"America/Mexico_City",
    "iso:country":"MX",
    "name:ceb_x_preferred":[
        "San Bartolo"
    ],
    "name:deu_x_preferred":[
        "San Bartolo"
    ],
    "name:epo_x_preferred":[
        "San Bartolo"
    ],
    "name:fra_x_preferred":[
        "San Bartolo"
    ],
    "name:por_x_preferred":[
        "San Bartolo"
    ],
    "name:sco_x_preferred":[
        "San Bartolo"
    ],
    "name:spa_x_preferred":[
        "San Bartolo"
    ],
    "name:srp_x_preferred":[
        "San Bartolo"
    ],
    "name:swe_x_preferred":[
        "San Bartolo"
    ],
    "wof:name":"San Bartolo",
    "wof:placetype":"locality"
},
  "geometry": {"coordinates":[-91.77764999999999,17.71355],"type":"Point"}
}