{
  "type": "Feature",
  "properties": {
    "gn:admin1_code":"6",
    "gn:admin2_code":"11.0",
    "gn:asciiname":"San Luis",
    "gn:country_code":"MX",
    "gn:dem":1301,
    "gn:feature_class":"P",
    "gn:feature_code":"PPL",
    "gn:name":"San Luis",
    "gn:population":0,
    "gn:timezone":"America/Chihuahua",
    "iso:country":"MX",
    "name:spa_x_preferred":[
        "San Luis"
    ],
    "name:und_x_variant":[
        "Rancho San Lu\u00eds"
    ],
    "wof:name":"San Luis",
    "wof:placetype":"locality"
},
  "geometry": {"coordinates":[-104.1268,28.01341],"type":"Point"}
}