{
  "type": "Feature",
  "properties": {
    "gn:admin1_code":"5",
    "gn:admin2_code":"20.0",
    "gn:asciiname":"Vistahermosa",
    "gn:country_code":"MX",
    "gn:dem":826,
    "gn:feature_class":"P",
    "gn:feature_code":"PPL",
    "gn:name":"Vistahermosa",
    "gn:population":5,
    "gn:timezone":"America/Mexico_City",
    "iso:country":"MX",
    "wof:name":"Vistahermosa",
    "wof:placetype":"locality",
    "wof:population":5
},
  "geometry": {"coordinates":[-92.97389,15.83444],"type":"Point"}
}