{
  "type": "Feature",
  "properties": {
    "gn:admin1_code":"30",
    "gn:admin2_code":"124.0",
    "gn:asciiname":"Leonides",
    "gn:country_code":"MX",
    "gn:dem":89,
    "gn:feature_class":"P",
    "gn:feature_code":"PPL",
    "gn:name":"Leonides",
    "gn:population":0,
    "gn:timezone":"America/Mexico_City",
    "iso:country":"MX",
    "name:srp_x_preferred":[
        "\u041b\u0435\u043e\u043d\u0438\u0434\u0435\u0441"
    ],
    "wof:name":"Leonides",
    "wof:placetype":"locality"
},
  "geometry": {"coordinates":[-97.36667,20.31667],"type":"Point"}
}