{
  "type": "Feature",
  "properties": {
    "gn:admin1_code":"14",
    "gn:admin2_code":"78.0",
    "gn:asciiname":"Mirandilla",
    "gn:country_code":"MX",
    "gn:dem":1961,
    "gn:feature_class":"P",
    "gn:feature_code":"PPL",
    "gn:name":"Mirandilla",
    "gn:population":0,
    "gn:timezone":"America/Mexico_City",
    "iso:country":"MX",
    "name:ara_x_preferred":[
        "\u0645\u064a\u0631\u0627\u0646\u062f\u0627\u064a\u0644\u0627"
    ],
    "name:ast_x_preferred":[
        "Mirandilla"
    ],
    "name:azb_x_preferred":[
        "\u0645\u06cc\u0631\u0627\u0646\u062f\u06cc\u06cc\u0627"
    ],
    "name:cat_x_preferred":[
        "Mirandilla"
    ],
    "name:ceb_x_preferred":[
        "Mirandilla"
    ],
    "name:ces_x_preferred":[
        "Mirandilla"
    ],
    "name:epo_x_preferred":[
        "Mirandilla"
    ],
    "name:eus_x_preferred":[
        "Mirandilla"
    ],
    "name:fas_x_preferred":[
        "\u0645\u06cc\u0631\u0627\u0646\u062f\u06cc\u06cc\u0627"
    ],
    "name:fra_x_preferred":[
        "Mirandilla"
    ],
    "name:hun_x_preferred":[
        "Mirandilla"
    ],
    "name:ido_x_preferred":[
        "Mirandilla"
    ],
    "name:ina_x_preferred":[
        "Mirandilla"
    ],
    "name:ita_x_preferred":[
        "Mirandilla"
    ],
    "name:mkd_x_preferred":[
        "\u041c\u0438\u0440\u0430\u043d\u0434\u0438\u043b\u0458\u0430"
    ],
    "name:msa_x_preferred":[
        "Mirandilla"
    ],
    "name:nld_x_preferred":[
        "Mirandilla"
    ],
    "name:oci_x_preferred":[
        "Mirandilla"
    ],
    "name:pol_x_preferred":[
        "Mirandilla"
    ],
    "name:por_x_preferred":[
        "Mirandilla"
    ],
    "name:ron_x_preferred":[
        "Mirandilla"
    ],
    "name:rus_x_preferred":[
        "\u041c\u0438\u0440\u0430\u043d\u0434\u0438\u043b\u044c\u044f"
    ],
    "name:spa_x_preferred":[
        "Mirandilla"
    ],
    "name:swe_x_preferred":[
        "Mirandilla"
    ],
    "name:ukr_x_preferred":[
        "\u041c\u0456\u0440\u0430\u043d\u0434\u0456\u043b\u044c\u044f"
    ],
    "name:und_x_variant":[
        "Mirandillas"
    ],
    "name:uzb_x_preferred":[
        "Mirandilla"
    ],
    "name:vie_x_preferred":[
        "Mirandilla"
    ],
    "name:war_x_preferred":[
        "Mirandilla"
    ],
    "name:zho_x_preferred":[
        "\u7c73\u5170\u8fea\u5229\u4e9a"
    ],
    "wof:name":"Mirandilla",
    "wof:placetype":"locality"
},
  "geometry": {"coordinates":[-102.54369,20.94363],"type":"Point"}
}