{
  "type": "Feature",
  "properties": {
    "gn:admin1_code":"14",
    "gn:admin2_code":"78.0",
    "gn:asciiname":"Mirandilla",
    "gn:country_code":"MX",
    "gn:dem":1961,
    "gn:feature_class":"P",
    "gn:feature_code":"PPL",
    "gn:name":"Mirandilla",
    "gn:population":0,
    "gn:timezone":"America/Mexico_City",
    "iso:country":"MX",
    "name:und_x_variant":[
        "Mirandillas",
        "Mirandilla"
    ],
    "wof:name":"Mirandilla",
    "wof:placetype":"locality"
},
  "geometry": {"coordinates":[-102.54369,20.94363],"type":"Point"}
}