{
  "type": "Feature",
  "properties": {
    "gn:admin1_code":"12",
    "gn:admin2_code":"29",
    "gn:asciiname":"Los Joveros",
    "gn:country_code":"MX",
    "gn:dem":942,
    "gn:feature_class":"P",
    "gn:feature_code":"PPL",
    "gn:name":"Los Joveros",
    "gn:population":17,
    "gn:timezone":"America/Mexico_City",
    "iso:country":"MX",
    "wof:name":"Los Joveros",
    "wof:placetype":"locality",
    "wof:population":17
},
  "geometry": {"coordinates":[-99.47631,17.34517],"type":"Point"}
}