{
  "type": "Feature",
  "properties": {
    "gn:admin1_code":"11.0",
    "gn:admin2_code":"14.0",
    "gn:asciiname":"Cuitzillo",
    "gn:country_code":"MX",
    "gn:dem":1961,
    "gn:feature_class":"P",
    "gn:feature_code":"PPL",
    "gn:name":"Cuitzillo",
    "gn:population":0,
    "gn:timezone":"America/Mexico_City",
    "iso:country":"MX",
    "name:spa_x_preferred":[
        "Cuitzillo"
    ],
    "wof:name":"Cuitzillo",
    "wof:placetype":"locality"
},
  "geometry": {"coordinates":[-100.9893,21.15142],"type":"Point"}
}