{
  "type": "Feature",
  "properties": {
    "gn:admin1_code":"6",
    "gn:admin2_code":"62.0",
    "gn:asciiname":"Granja la Providencia",
    "gn:country_code":"MX",
    "gn:dem":1184,
    "gn:feature_class":"P",
    "gn:feature_code":"PPL",
    "gn:name":"Granja la Providencia",
    "gn:population":6,
    "gn:timezone":"America/Chihuahua",
    "iso:country":"MX",
    "wof:name":"Granja la Providencia",
    "wof:placetype":"locality",
    "wof:population":6
},
  "geometry": {"coordinates":[-105.31185000000001,28.06354],"type":"Point"}
}