{
  "type": "Feature",
  "properties": {
    "gn:admin1_code":"12",
    "gn:admin2_code":"72.0",
    "gn:asciiname":"Cerro el Maguey",
    "gn:country_code":"MX",
    "gn:dem":1943,
    "gn:feature_class":"P",
    "gn:feature_code":"PPL",
    "gn:name":"Cerro el Maguey",
    "gn:population":278,
    "gn:timezone":"America/Mexico_City",
    "iso:country":"MX",
    "wof:name":"Cerro el Maguey",
    "wof:placetype":"locality",
    "wof:population":278
},
  "geometry": {"coordinates":[-98.86505,17.21096],"type":"Point"}
}