{
  "type": "Feature",
  "properties": {
    "gn:admin1_code":"13",
    "gn:admin2_code":"4.0",
    "gn:asciiname":"Rancheria Calabazas Primera Seccion",
    "gn:country_code":"MX",
    "gn:dem":2205,
    "gn:feature_class":"P",
    "gn:feature_code":"PPL",
    "gn:name":"Rancher\u00eda Calabazas Primera Secci\u00f3n",
    "gn:population":0,
    "gn:timezone":"America/Mexico_City",
    "iso:country":"MX",
    "name:spa_x_preferred":[
        "Rancher\u00eda Calabazas Primera Secci\u00f3n"
    ],
    "wof:name":"Rancheria Calabazas Primera Seccion",
    "wof:placetype":"locality"
},
  "geometry": {"coordinates":[-98.36977,20.34399],"type":"Point"}
}