{
  "type": "Feature",
  "properties": {
    "gn:admin1_code":"32",
    "gn:admin2_code":"31.0",
    "gn:asciiname":"El Portillito",
    "gn:country_code":"MX",
    "gn:dem":2193,
    "gn:feature_class":"P",
    "gn:feature_code":"PPL",
    "gn:name":"El Portillito",
    "gn:population":6,
    "gn:timezone":"America/Mexico_City",
    "iso:country":"MX",
    "wof:name":"El Portillito",
    "wof:placetype":"locality",
    "wof:population":6
},
  "geometry": {"coordinates":[-103.43694000000001,22.43306],"type":"Point"}
}