{
  "type": "Feature",
  "properties": {
    "gn:admin1_code":"23",
    "gn:admin2_code":"4.0",
    "gn:asciiname":"La Conchita",
    "gn:country_code":"MX",
    "gn:dem":7,
    "gn:feature_class":"P",
    "gn:feature_code":"PPL",
    "gn:name":"La Conchita",
    "gn:population":9,
    "gn:timezone":"America/Cancun",
    "iso:country":"MX",
    "wof:name":"La Conchita",
    "wof:placetype":"locality",
    "wof:population":9
},
  "geometry": {"coordinates":[-88.3809,18.50862],"type":"Point"}
}