{
  "type": "Feature",
  "properties": {
    "gn:admin1_code":"6",
    "gn:admin2_code":"31.0",
    "gn:asciiname":"Rancho San Gilberto",
    "gn:country_code":"MX",
    "gn:dem":2161,
    "gn:feature_class":"P",
    "gn:feature_code":"PPL",
    "gn:name":"Rancho San Gilberto",
    "gn:population":4,
    "gn:timezone":"America/Chihuahua",
    "iso:country":"MX",
    "wof:name":"Rancho San Gilberto",
    "wof:placetype":"locality",
    "wof:population":4
},
  "geometry": {"coordinates":[-107.39718000000001,28.41473],"type":"Point"}
}