{
  "type": "Feature",
  "properties": {
    "gn:admin1_code":"20",
    "gn:admin2_code":"81.0",
    "gn:asciiname":"San Francisco Paxtlahuaca",
    "gn:country_code":"MX",
    "gn:dem":1306,
    "gn:feature_class":"P",
    "gn:feature_code":"PPL",
    "gn:name":"San Francisco Paxtlahuaca",
    "gn:population":368,
    "gn:timezone":"America/Mexico_City",
    "iso:country":"MX",
    "name:spa_x_preferred":[
        "San Francisco Pantlahuaca"
    ],
    "wof:name":"San Francisco Paxtlahuaca",
    "wof:placetype":"locality",
    "wof:population":368
},
  "geometry": {"coordinates":[-98.01472,17.58333],"type":"Point"}
}