{
  "type": "Feature",
  "properties": {
    "gn:admin1_code":"4",
    "gn:admin2_code":"4.0",
    "gn:asciiname":"Yacamex",
    "gn:country_code":"MX",
    "gn:dem":66,
    "gn:feature_class":"P",
    "gn:feature_code":"PPL",
    "gn:name":"Yacamex",
    "gn:population":0,
    "gn:timezone":"America/Merida",
    "iso:country":"MX",
    "name:spa_x_preferred":[
        "Yacamex"
    ],
    "name:und_x_variant":[
        "Yacame"
    ],
    "wof:name":"Yacamex",
    "wof:placetype":"locality"
},
  "geometry": {"coordinates":[-90.47113,19.19191],"type":"Point"}
}