{
  "type": "Feature",
  "properties": {
    "gn:admin1_code":"21",
    "gn:admin2_code":"190",
    "gn:asciiname":"Barrio de San Juan",
    "gn:country_code":"MX",
    "gn:dem":1407,
    "gn:feature_class":"P",
    "gn:feature_code":"PPL",
    "gn:name":"Barrio de San Juan",
    "gn:population":26,
    "gn:timezone":"America/Mexico_City",
    "iso:country":"MX",
    "wof:name":"Barrio de San Juan",
    "wof:placetype":"locality",
    "wof:population":26
},
  "geometry": {"coordinates":[-97.8574,18.23145],"type":"Point"}
}