{
  "type": "Feature",
  "properties": {
    "gn:admin1_code":"31",
    "gn:admin2_code":"30.0",
    "gn:asciiname":"Santa Esperanza",
    "gn:country_code":"MX",
    "gn:dem":33,
    "gn:feature_class":"P",
    "gn:feature_code":"PPL",
    "gn:name":"Santa Esperanza",
    "gn:population":0,
    "gn:timezone":"America/Merida",
    "iso:country":"MX",
    "name:kat_x_preferred":[
        "\u10e1\u10d0\u10dc\u10e2\u10d0 \u10d4\u10e1\u10de\u10d4\u10e0\u10d0\u10dc\u10e1\u10d0"
    ],
    "name:spa_x_preferred":[
        "Santa Esperanza"
    ],
    "wof:name":"Santa Esperanza",
    "wof:placetype":"locality"
},
  "geometry": {"coordinates":[-88.52149,20.76237],"type":"Point"}
}