{
  "type": "Feature",
  "properties": {
    "gn:admin1_code":"14",
    "gn:admin2_code":"56",
    "gn:asciiname":"La Lagunita (Valle Alto)",
    "gn:country_code":"MX",
    "gn:dem":1022,
    "gn:feature_class":"P",
    "gn:feature_code":"PPL",
    "gn:name":"La Lagunita (Valle Alto)",
    "gn:population":15,
    "gn:timezone":"America/Mexico_City",
    "iso:country":"MX",
    "wof:name":"La Lagunita (Valle Alto)",
    "wof:placetype":"locality",
    "wof:population":15
},
  "geometry": {"coordinates":[-102.82944000000001,19.53056],"type":"Point"}
}