{
  "type": "Feature",
  "properties": {
    "gn:admin1_code":"6",
    "gn:admin2_code":"65",
    "gn:asciiname":"Sabanillas",
    "gn:country_code":"MX",
    "gn:dem":1498,
    "gn:feature_class":"P",
    "gn:feature_code":"PPL",
    "gn:name":"Sabanillas",
    "gn:population":10,
    "gn:timezone":"America/Chihuahua",
    "iso:country":"MX",
    "wof:name":"Sabanillas",
    "wof:placetype":"locality",
    "wof:population":10
},
  "geometry": {"coordinates":[-107.84575,27.27687],"type":"Point"}
}