{
  "type": "Feature",
  "properties": {
    "gn:admin1_code":"30",
    "gn:admin2_code":"172.0",
    "gn:asciiname":"Paso de los Ortices",
    "gn:country_code":"MX",
    "gn:dem":7,
    "gn:feature_class":"P",
    "gn:feature_code":"PPL",
    "gn:name":"Paso de los Ortices",
    "gn:population":0,
    "gn:timezone":"America/Mexico_City",
    "iso:country":"MX",
    "name:spa_x_preferred":[
        "Paso de los Ortices"
    ],
    "name:und_x_variant":[
        "Paso de Ortiz"
    ],
    "wof:name":"Paso de los Ortices",
    "wof:placetype":"locality"
},
  "geometry": {"coordinates":[-94.75508000000001,17.83313],"type":"Point"}
}