{
  "type": "Feature",
  "properties": {
    "gn:admin1_code":"14.0",
    "gn:admin2_code":"86.0",
    "gn:asciiname":"Rincon de los Pastores",
    "gn:country_code":"MX",
    "gn:dem":2136,
    "gn:feature_class":"P",
    "gn:feature_code":"PPL",
    "gn:name":"Rinc\u00f3n de los Pastores",
    "gn:population":0,
    "gn:timezone":"America/Mexico_City",
    "iso:country":"MX",
    "name:spa_x_preferred":[
        "Rinc\u00f3n de los Pastores"
    ],
    "wof:name":"Rincon de los Pastores",
    "wof:placetype":"locality"
},
  "geometry": {"coordinates":[-103.81238,19.92897],"type":"Point"}
}