{
  "type": "Feature",
  "properties": {
    "gn:admin1_code":"30",
    "gn:admin2_code":"157.0",
    "gn:asciiname":"Las Camelias",
    "gn:country_code":"MX",
    "gn:dem":145,
    "gn:feature_class":"P",
    "gn:feature_code":"PPL",
    "gn:name":"Las Camelias",
    "gn:population":6,
    "gn:timezone":"America/Mexico_City",
    "iso:country":"MX",
    "wof:name":"Las Camelias",
    "wof:placetype":"locality",
    "wof:population":6
},
  "geometry": {"coordinates":[-97.71944000000001,20.68028],"type":"Point"}
}