{
  "type": "Feature",
  "properties": {
    "gn:admin1_code":"20",
    "gn:admin2_code":"366",
    "gn:asciiname":"Nueva Luz",
    "gn:country_code":"MX",
    "gn:dem":430,
    "gn:feature_class":"P",
    "gn:feature_code":"PPL",
    "gn:name":"Nueva Luz",
    "gn:population":19,
    "gn:timezone":"America/Mexico_City",
    "iso:country":"MX",
    "wof:name":"Nueva Luz",
    "wof:placetype":"locality",
    "wof:population":19
},
  "geometry": {"coordinates":[-96.73583000000001,16.01806],"type":"Point"}
}