{
  "type": "Feature",
  "properties": {
    "gn:admin1_code":"26",
    "gn:admin2_code":"29.0",
    "gn:asciiname":"Guadalupe",
    "gn:country_code":"MX",
    "gn:dem":368,
    "gn:feature_class":"P",
    "gn:feature_code":"PPL",
    "gn:name":"Guadalupe",
    "gn:population":0,
    "gn:timezone":"America/Hermosillo",
    "iso:country":"MX",
    "name:spa_x_preferred":[
        "Guadalupe"
    ],
    "wof:name":"Guadalupe",
    "wof:placetype":"locality"
},
  "geometry": {"coordinates":[-110.18921,28.51725],"type":"Point"}
}