{
  "type": "Feature",
  "properties": {
    "gn:admin1_code":"5",
    "gn:admin2_code":"40.0",
    "gn:asciiname":"La Huerta",
    "gn:cc2":"MX",
    "gn:country_code":"MX",
    "gn:dem":40,
    "gn:feature_class":"P",
    "gn:feature_code":"PPL",
    "gn:name":"La Huerta",
    "gn:population":9,
    "gn:timezone":"America/Mexico_City",
    "iso:country":"MX",
    "name:und_x_variant":[
        "Huerta",
        "La Huerta"
    ],
    "wof:name":"La Huerta",
    "wof:placetype":"locality",
    "wof:population":9
},
  "geometry": {"coordinates":[-92.49583,15.13056],"type":"Point"}
}