{
  "type": "Feature",
  "properties": {
    "gn:admin1_code":"16.0",
    "gn:admin2_code":"95.0",
    "gn:asciiname":"Poca Sangre",
    "gn:country_code":"MX",
    "gn:dem":1160,
    "gn:feature_class":"P",
    "gn:feature_code":"PPL",
    "gn:name":"Poca Sangre",
    "gn:population":0,
    "gn:timezone":"America/Mexico_City",
    "iso:country":"MX",
    "name:spa_x_preferred":[
        "Poca Sangre"
    ],
    "wof:name":"Poca Sangre",
    "wof:placetype":"locality"
},
  "geometry": {"coordinates":[-102.59566,19.55575],"type":"Point"}
}