{
  "type": "Feature",
  "properties": {
    "gn:admin1_code":"11.0",
    "gn:admin2_code":"14.0",
    "gn:asciiname":"Capitanes",
    "gn:country_code":"MX",
    "gn:dem":2006,
    "gn:feature_class":"P",
    "gn:feature_code":"PPL",
    "gn:name":"Capitanes",
    "gn:population":0,
    "gn:timezone":"America/Mexico_City",
    "iso:country":"MX",
    "name:spa_x_preferred":[
        "Capitanes"
    ],
    "wof:name":"Capitanes",
    "wof:placetype":"locality"
},
  "geometry": {"coordinates":[-101.00733,21.19103],"type":"Point"}
}