{
  "type": "Feature",
  "properties": {
    "gn:admin1_code":"20",
    "gn:admin2_code":"57.0",
    "gn:asciiname":"Doce de Julio",
    "gn:country_code":"MX",
    "gn:dem":109,
    "gn:feature_class":"P",
    "gn:feature_code":"PPL",
    "gn:name":"Doce de Julio",
    "gn:population":100,
    "gn:timezone":"America/Mexico_City",
    "iso:country":"MX",
    "wof:name":"Doce de Julio",
    "wof:placetype":"locality",
    "wof:population":100
},
  "geometry": {"coordinates":[-95.11306,17.27667000000001],"type":"Point"}
}