{
  "type": "Feature",
  "properties": {
    "gn:admin1_code":"10.0",
    "gn:admin2_code":"3.0",
    "gn:asciiname":"Chignallo",
    "gn:cc2":"MX",
    "gn:country_code":"MX",
    "gn:dem":1713,
    "gn:feature_class":"P",
    "gn:feature_code":"PPL",
    "gn:name":"Chignallo",
    "gn:population":0,
    "gn:timezone":"America/Monterrey",
    "iso:country":"MX",
    "name:und_x_variant":[
        "Rancho Chicanayo",
        "Chiganyo",
        "Chiganayo",
        "Chiganallo",
        "Chignallo"
    ],
    "wof:name":"Chignallo",
    "wof:placetype":"locality"
},
  "geometry": {"coordinates":[-104.59999999999999,24.95],"type":"Point"}
}