{
  "type": "Feature",
  "properties": {
    "gn:admin1_code":"4",
    "gn:admin2_code":"7.0",
    "gn:asciiname":"San Marco",
    "gn:country_code":"MX",
    "gn:dem":8,
    "gn:feature_class":"P",
    "gn:feature_code":"PPL",
    "gn:name":"San Marco",
    "gn:population":0,
    "gn:timezone":"America/Mexico_City",
    "iso:country":"MX",
    "name:spa_x_preferred":[
        "San Marco"
    ],
    "wof:name":"San Marco",
    "wof:placetype":"locality"
},
  "geometry": {"coordinates":[-91.73696,17.94345],"type":"Point"}
}