{
  "type": "Feature",
  "properties": {
    "gn:admin1_code":"5.0",
    "gn:asciiname":"El Miradero",
    "gn:country_code":"MX",
    "gn:dem":900,
    "gn:feature_class":"P",
    "gn:feature_code":"PPL",
    "gn:name":"El Miradero",
    "gn:population":0,
    "gn:timezone":"America/Mexico_City",
    "iso:country":"MX",
    "name:spa_x_preferred":[
        "El Miradero"
    ],
    "wof:name":"El Miradero",
    "wof:placetype":"locality"
},
  "geometry": {"coordinates":[-92.01810999999999,16.90948],"type":"Point"}
}