{
  "type": "Feature",
  "properties": {
    "gn:admin1_code":"10.0",
    "gn:admin2_code":"34.0",
    "gn:asciiname":"Apomas",
    "gn:country_code":"MX",
    "gn:dem":715,
    "gn:feature_class":"P",
    "gn:feature_code":"PPL",
    "gn:name":"Apomas",
    "gn:population":0,
    "gn:timezone":"America/Monterrey",
    "iso:country":"MX",
    "name:und_x_variant":[
        "Apomal",
        "Apomas"
    ],
    "wof:name":"Apomas",
    "wof:placetype":"locality"
},
  "geometry": {"coordinates":[-106.52585999999999,24.68379],"type":"Point"}
}