{
  "type": "Feature",
  "properties": {
    "gn:admin1_code":"6",
    "gn:admin2_code":"43.0",
    "gn:asciiname":"El Sacrificio",
    "gn:country_code":"MX",
    "gn:dem":2096,
    "gn:feature_class":"P",
    "gn:feature_code":"PPL",
    "gn:name":"El Sacrificio",
    "gn:population":0,
    "gn:timezone":"America/Chihuahua",
    "iso:country":"MX",
    "name:spa_x_preferred":[
        "El Sacrificio"
    ],
    "wof:name":"El Sacrificio",
    "wof:placetype":"locality"
},
  "geometry": {"coordinates":[-107.61302000000001,28.79989],"type":"Point"}
}