{
  "type": "Feature",
  "properties": {
    "gn:admin1_code":"30",
    "gn:admin2_code":"208.0",
    "gn:asciiname":"Uluapeno",
    "gn:country_code":"MX",
    "gn:dem":11,
    "gn:feature_class":"P",
    "gn:feature_code":"PPL",
    "gn:name":"Uluape\u00f1o",
    "gn:population":178,
    "gn:timezone":"America/Mexico_City",
    "iso:country":"MX",
    "name:und_x_variant":[
        "Uluape\u00f1o"
    ],
    "wof:name":"Uluapeno",
    "wof:placetype":"locality",
    "wof:population":178
},
  "geometry": {"coordinates":[-95.68111,18.38639],"type":"Point"}
}