{
  "type": "Feature",
  "properties": {
    "gn:admin1_code":"23",
    "gn:admin2_code":"8.0",
    "gn:asciiname":"Iberostar",
    "gn:country_code":"MX",
    "gn:dem":6,
    "gn:feature_class":"P",
    "gn:feature_code":"PPL",
    "gn:name":"Iberostar",
    "gn:population":242,
    "gn:timezone":"America/Cancun",
    "iso:country":"MX",
    "wof:name":"Iberostar",
    "wof:placetype":"locality",
    "wof:population":242
},
  "geometry": {"coordinates":[-86.95806,20.75917],"type":"Point"}
}