{
  "type": "Feature",
  "properties": {
    "gn:admin1_code":"29",
    "gn:admin2_code":"34.0",
    "gn:asciiname":"El Dorado",
    "gn:country_code":"MX",
    "gn:dem":2682,
    "gn:feature_class":"P",
    "gn:feature_code":"PPL",
    "gn:name":"El Dorado",
    "gn:population":0,
    "gn:timezone":"America/Mexico_City",
    "iso:country":"MX",
    "name:spa_x_preferred":[
        "El Dorado"
    ],
    "wof:name":"El Dorado",
    "wof:placetype":"locality"
},
  "geometry": {"coordinates":[-98.09025,19.59741],"type":"Point"}
}