{
  "type": "Feature",
  "properties": {
    "gn:admin1_code":"5",
    "gn:admin2_code":"108.0",
    "gn:asciiname":"El Ranchito",
    "gn:country_code":"MX",
    "gn:dem":856,
    "gn:feature_class":"P",
    "gn:feature_code":"PPL",
    "gn:name":"El Ranchito",
    "gn:population":5,
    "gn:timezone":"America/Mexico_City",
    "iso:country":"MX",
    "wof:name":"El Ranchito",
    "wof:placetype":"locality",
    "wof:population":5
},
  "geometry": {"coordinates":[-93.47167,16.30417000000001],"type":"Point"}
}