{
  "type": "Feature",
  "properties": {
    "gn:admin1_code":"12",
    "gn:admin2_code":"18.0",
    "gn:asciiname":"Comunidad General Enrique Rodriguez [El Campamento]",
    "gn:country_code":"MX",
    "gn:dem":19,
    "gn:feature_class":"P",
    "gn:feature_code":"PPL",
    "gn:name":"Comunidad General Enrique Rodr\u00edguez [El Campamento]",
    "gn:population":254,
    "gn:timezone":"America/Mexico_City",
    "iso:country":"MX",
    "name:und_x_variant":[
        "Comunidad General Enrique Rodr\u00edguez [El Campamento]"
    ],
    "wof:name":"Comunidad General Enrique Rodriguez [El Campamento]",
    "wof:placetype":"locality",
    "wof:population":254
},
  "geometry": {"coordinates":[-98.82333,16.5998],"type":"Point"}
}