{
  "type": "Feature",
  "properties": {
    "gn:admin1_code":"30",
    "gn:admin2_code":"178.0",
    "gn:asciiname":"Palma Sola",
    "gn:country_code":"MX",
    "gn:dem":9,
    "gn:feature_class":"P",
    "gn:feature_code":"PPL",
    "gn:name":"Palma Sola",
    "gn:population":0,
    "gn:timezone":"America/Mexico_City",
    "iso:country":"MX",
    "name:ceb_x_preferred":[
        "Palma Sola"
    ],
    "name:deu_x_preferred":[
        "Palma Sola"
    ],
    "name:fra_x_preferred":[
        "Palma Sola"
    ],
    "name:spa_x_preferred":[
        "Palma Sola"
    ],
    "name:srp_x_preferred":[
        "\u041f\u0430\u043b\u043c\u0430 \u0421\u043e\u043b\u0430"
    ],
    "name:swe_x_preferred":[
        "Palma Sola"
    ],
    "wof:name":"Palma Sola",
    "wof:placetype":"locality"
},
  "geometry": {"coordinates":[-95.58418,18.53666],"type":"Point"}
}