{
  "type": "Feature",
  "properties": {
    "gn:admin1_code":"21",
    "gn:admin2_code":"115.0",
    "gn:asciiname":"Ejido Palmarito",
    "gn:country_code":"MX",
    "gn:dem":2193,
    "gn:feature_class":"P",
    "gn:feature_code":"PPL",
    "gn:name":"Ejido Palmarito",
    "gn:population":416,
    "gn:timezone":"America/Mexico_City",
    "iso:country":"MX",
    "wof:name":"Ejido Palmarito",
    "wof:placetype":"locality",
    "wof:population":416
},
  "geometry": {"coordinates":[-97.62528,18.91917],"type":"Point"}
}