{
  "type": "Feature",
  "properties": {
    "gn:admin1_code":"4",
    "gn:admin2_code":"3.0",
    "gn:asciiname":"Las Palomas",
    "gn:country_code":"MX",
    "gn:dem":2,
    "gn:feature_class":"P",
    "gn:feature_code":"PPL",
    "gn:name":"Las Palomas",
    "gn:population":7,
    "gn:timezone":"America/Merida",
    "iso:country":"MX",
    "wof:name":"Las Palomas",
    "wof:placetype":"locality",
    "wof:population":7
},
  "geometry": {"coordinates":[-91.9175,18.6275],"type":"Point"}
}