{
  "type": "Feature",
  "properties": {
    "gn:admin1_code":"14",
    "gn:admin2_code":"17",
    "gn:asciiname":"Los Callejones",
    "gn:country_code":"MX",
    "gn:dem":1517,
    "gn:feature_class":"P",
    "gn:feature_code":"PPL",
    "gn:name":"Los Callejones",
    "gn:population":21,
    "gn:timezone":"America/Mexico_City",
    "iso:country":"MX",
    "wof:name":"Los Callejones",
    "wof:placetype":"locality",
    "wof:population":21
},
  "geometry": {"coordinates":[-104.29861,20.2075],"type":"Point"}
}