{
  "type": "Feature",
  "properties": {
    "gn:admin1_code":"32",
    "gn:admin2_code":"36.0",
    "gn:asciiname":"Cerrito de la Cruz",
    "gn:country_code":"MX",
    "gn:dem":2088,
    "gn:feature_class":"P",
    "gn:feature_code":"PPL",
    "gn:name":"Cerrito de la Cruz",
    "gn:population":0,
    "gn:timezone":"America/Mexico_City",
    "iso:country":"MX",
    "name:spa_x_preferred":[
        "Cerrito de la Cruz"
    ],
    "wof:name":"Cerrito de la Cruz",
    "wof:placetype":"locality"
},
  "geometry": {"coordinates":[-102.27263000000001,22.65781],"type":"Point"}
}