{
  "type": "Feature",
  "properties": {
    "gn:admin1_code":"16",
    "gn:admin2_code":"99.0",
    "gn:asciiname":"Puerto del Aire",
    "gn:country_code":"MX",
    "gn:dem":1302,
    "gn:feature_class":"P",
    "gn:feature_code":"PPL",
    "gn:name":"Puerto del Aire",
    "gn:population":0,
    "gn:timezone":"America/Mexico_City",
    "iso:country":"MX",
    "name:spa_x_preferred":[
        "Puerto del Aire"
    ],
    "wof:name":"Puerto del Aire",
    "wof:placetype":"locality"
},
  "geometry": {"coordinates":[-100.73045999999999,19.31561],"type":"Point"}
}