{
  "type": "Feature",
  "properties": {
    "gn:admin1_code":"30.0",
    "gn:admin2_code":"123.0",
    "gn:asciiname":"Dos Huasteca",
    "gn:country_code":"MX",
    "gn:dem":8,
    "gn:feature_class":"P",
    "gn:feature_code":"PPL",
    "gn:name":"Dos Huasteca",
    "gn:population":10,
    "gn:timezone":"America/Mexico_City",
    "iso:country":"MX",
    "name:spa_x_preferred":[
        "Dos Huasteca"
    ],
    "wof:name":"Dos Huasteca",
    "wof:placetype":"locality",
    "wof:population":10
},
  "geometry": {"coordinates":[-98.15111,22.18389],"type":"Point"}
}