{
  "type": "Feature",
  "properties": {
    "gn:admin1_code":"12",
    "gn:admin2_code":"79.0",
    "gn:asciiname":"Ocotecomactitlan",
    "gn:country_code":"MX",
    "gn:dem":1339,
    "gn:feature_class":"P",
    "gn:feature_code":"PPL",
    "gn:name":"Ocotecomactitl\u00e1n",
    "gn:population":292,
    "gn:timezone":"America/Mexico_City",
    "iso:country":"MX",
    "name:und_x_variant":[
        "Ocotecomactitl\u00e1n"
    ],
    "wof:name":"Ocotecomactitlan",
    "wof:placetype":"locality",
    "wof:population":292
},
  "geometry": {"coordinates":[-98.98712999999999,17.38593],"type":"Point"}
}