{
  "type": "Feature",
  "properties": {
    "gn:admin1_code":"20",
    "gn:admin2_code":"449",
    "gn:asciiname":"El Rio Cabrito",
    "gn:country_code":"MX",
    "gn:dem":1272,
    "gn:feature_class":"P",
    "gn:feature_code":"PPL",
    "gn:name":"El R\u00edo Cabrito",
    "gn:population":23,
    "gn:timezone":"America/Mexico_City",
    "iso:country":"MX",
    "name:und_x_variant":[
        "El R\u00edo Cabrito"
    ],
    "wof:name":"El Rio Cabrito",
    "wof:placetype":"locality",
    "wof:population":23
},
  "geometry": {"coordinates":[-96.40639,16.48917],"type":"Point"}
}