{
  "type": "Feature",
  "properties": {
    "gn:admin1_code":"6",
    "gn:admin2_code":"65.0",
    "gn:asciiname":"Mechachi",
    "gn:country_code":"MX",
    "gn:dem":1462,
    "gn:feature_class":"P",
    "gn:feature_code":"PPL",
    "gn:name":"Mechachi",
    "gn:population":0,
    "gn:timezone":"America/Chihuahua",
    "iso:country":"MX",
    "name:spa_x_preferred":[
        "Mechachi"
    ],
    "wof:name":"Mechachi",
    "wof:placetype":"locality"
},
  "geometry": {"coordinates":[-107.79949999999999,27.38555],"type":"Point"}
}