{
  "type": "Feature",
  "properties": {
    "gn:admin1_code":"2.0",
    "gn:admin2_code":"4.0",
    "gn:asciiname":"El Manglecito",
    "gn:country_code":"MX",
    "gn:dem":308,
    "gn:feature_class":"P",
    "gn:feature_code":"PPL",
    "gn:name":"El Manglecito",
    "gn:population":0,
    "gn:timezone":"America/Tijuana",
    "iso:country":"MX",
    "name:spa_x_preferred":[
        "El Manglecito"
    ],
    "name:und_x_variant":[
        "Mangecito"
    ],
    "wof:name":"El Manglecito",
    "wof:placetype":"locality"
},
  "geometry": {"coordinates":[-116.95184,32.40636],"type":"Point"}
}