{
  "type": "Feature",
  "properties": {
    "gn:admin1_code":"30",
    "gn:admin2_code":"68.0",
    "gn:asciiname":"Fraccionamiento Villas de la Llave",
    "gn:country_code":"MX",
    "gn:dem":1048,
    "gn:feature_class":"P",
    "gn:feature_code":"PPL",
    "gn:name":"Fraccionamiento Villas de la Llave",
    "gn:population":1334,
    "gn:timezone":"America/Mexico_City",
    "iso:country":"MX",
    "wof:name":"Fraccionamiento Villas de la Llave",
    "wof:placetype":"locality",
    "wof:population":1334
},
  "geometry": {"coordinates":[-96.99111000000001,18.91583],"type":"Point"}
}