{
  "type": "Feature",
  "properties": {
    "gn:admin1_code":"6",
    "gn:admin2_code":"55.0",
    "gn:asciiname":"Nogalera del Ingeniero Soto",
    "gn:country_code":"MX",
    "gn:dem":1129,
    "gn:feature_class":"P",
    "gn:feature_code":"PPL",
    "gn:name":"Nogalera del Ingeniero Soto",
    "gn:population":4,
    "gn:timezone":"America/Chihuahua",
    "iso:country":"MX",
    "wof:name":"Nogalera del Ingeniero Soto",
    "wof:placetype":"locality",
    "wof:population":4
},
  "geometry": {"coordinates":[-105.54853,28.53547],"type":"Point"}
}