{
  "type": "Feature",
  "properties": {
    "gn:admin1_code":"7.0",
    "gn:admin2_code":"11.0",
    "gn:asciiname":"El Mesteno",
    "gn:cc2":"MX",
    "gn:country_code":"MX",
    "gn:dem":1264,
    "gn:feature_class":"P",
    "gn:feature_code":"PPL",
    "gn:name":"El Meste\u00f1o",
    "gn:population":0,
    "gn:timezone":"America/Monterrey",
    "iso:country":"MX",
    "name:und_x_variant":[
        "Meste\u00f1o",
        "El Meste\u00f1o"
    ],
    "wof:name":"El Mesteno",
    "wof:placetype":"locality"
},
  "geometry": {"coordinates":[-101.76667,25.58333],"type":"Point"}
}