{
  "type": "Feature",
  "properties": {
    "gn:admin1_code":"6",
    "gn:admin2_code":"9.0",
    "gn:asciiname":"Boriachi",
    "gn:country_code":"MX",
    "gn:dem":2332,
    "gn:feature_class":"P",
    "gn:feature_code":"PPL",
    "gn:name":"Boriachi",
    "gn:population":7,
    "gn:timezone":"America/Chihuahua",
    "iso:country":"MX",
    "wof:name":"Boriachi",
    "wof:placetype":"locality",
    "wof:population":7
},
  "geometry": {"coordinates":[-107.79353999999999,27.60686],"type":"Point"}
}