{
  "type": "Feature",
  "properties": {
    "gn:admin1_code":"31",
    "gn:admin2_code":"106.0",
    "gn:asciiname":"Kalat Dzonot",
    "gn:country_code":"MX",
    "gn:dem":9,
    "gn:feature_class":"P",
    "gn:feature_code":"PPL",
    "gn:name":"Kalat Dzonot",
    "gn:population":0,
    "gn:timezone":"America/Merida",
    "iso:country":"MX",
    "name:spa_x_preferred":[
        "Kalat Dzonot"
    ],
    "wof:name":"Kalat Dzonot",
    "wof:placetype":"locality"
},
  "geometry": {"coordinates":[-89.08301999999998,21.27893],"type":"Point"}
}