{
  "type": "Feature",
  "properties": {
    "gn:admin1_code":"22",
    "gn:admin2_code":"9.0",
    "gn:asciiname":"Orilla del Plan (La Laguna)",
    "gn:country_code":"MX",
    "gn:dem":668,
    "gn:feature_class":"P",
    "gn:feature_code":"PPL",
    "gn:name":"Orilla del Plan (La Laguna)",
    "gn:population":44,
    "gn:timezone":"America/Mexico_City",
    "iso:country":"MX",
    "wof:name":"Orilla del Plan (La Laguna)",
    "wof:placetype":"locality",
    "wof:population":44
},
  "geometry": {"coordinates":[-99.34866,21.38456],"type":"Point"}
}