{
  "type": "Feature",
  "properties": {
    "gn:admin1_code":"5",
    "gn:admin2_code":"51.0",
    "gn:asciiname":"Doctor Samuel Leon Brindis",
    "gn:country_code":"MX",
    "gn:dem":57,
    "gn:feature_class":"P",
    "gn:feature_code":"PPL",
    "gn:name":"Doctor Samuel Le\u00f3n Brindis",
    "gn:population":0,
    "gn:timezone":"America/Mexico_City",
    "iso:country":"MX",
    "name:spa_x_preferred":[
        "Samuel Le\u00f3n Brindis"
    ],
    "name:spa_x_variant":[
        "Doctor Samuel Le\u00f3n Brindis"
    ],
    "name:und_x_variant":[
        "Samuel Le\u00f3n"
    ],
    "wof:name":"Doctor Samuel Leon Brindis",
    "wof:placetype":"locality"
},
  "geometry": {"coordinates":[-92.97150000000001,15.50647],"type":"Point"}
}