{
  "type": "Feature",
  "properties": {
    "gn:admin1_code":"25",
    "gn:admin2_code":"17",
    "gn:asciiname":"Campo Montiel",
    "gn:country_code":"MX",
    "gn:dem":71,
    "gn:feature_class":"P",
    "gn:feature_code":"PPL",
    "gn:name":"Campo Montiel",
    "gn:population":39,
    "gn:timezone":"America/Mazatlan",
    "iso:country":"MX",
    "wof:name":"Campo Montiel",
    "wof:placetype":"locality",
    "wof:population":39
},
  "geometry": {"coordinates":[-108.43863,25.90849],"type":"Point"}
}