{
  "type": "Feature",
  "properties": {
    "gn:admin1_code":"11",
    "gn:admin2_code":"24.0",
    "gn:asciiname":"Colonia San Jose del Carmen",
    "gn:country_code":"MX",
    "gn:dem":1709,
    "gn:feature_class":"P",
    "gn:feature_code":"PPL",
    "gn:name":"Colonia San Jos\u00e9 del Carmen",
    "gn:population":73,
    "gn:timezone":"America/Mexico_City",
    "iso:country":"MX",
    "name:und_x_variant":[
        "Colonia San Jos\u00e9 del Carmen"
    ],
    "wof:name":"Colonia San Jose del Carmen",
    "wof:placetype":"locality",
    "wof:population":73
},
  "geometry": {"coordinates":[-101.35333,20.55167],"type":"Point"}
}