{
  "type": "Feature",
  "properties": {
    "gn:admin1_code":"30",
    "gn:admin2_code":"142",
    "gn:asciiname":"Zacatal (Plan de la Vieja)",
    "gn:country_code":"MX",
    "gn:dem":45,
    "gn:feature_class":"P",
    "gn:feature_code":"PPL",
    "gn:name":"Zacatal (Plan de la Vieja)",
    "gn:population":14,
    "gn:timezone":"America/Mexico_City",
    "iso:country":"MX",
    "wof:name":"Zacatal (Plan de la Vieja)",
    "wof:placetype":"locality",
    "wof:population":14
},
  "geometry": {"coordinates":[-95.02110999999999,17.70556000000001],"type":"Point"}
}