{
  "type": "Feature",
  "properties": {
    "gn:admin1_code":"14",
    "gn:admin2_code":"24",
    "gn:asciiname":"El Nahuache",
    "gn:country_code":"MX",
    "gn:dem":1335,
    "gn:feature_class":"P",
    "gn:feature_code":"PPL",
    "gn:name":"El Nahuache",
    "gn:population":24,
    "gn:timezone":"America/Mexico_City",
    "iso:country":"MX",
    "wof:name":"El Nahuache",
    "wof:placetype":"locality",
    "wof:population":24
},
  "geometry": {"coordinates":[-103.83722,20.36778],"type":"Point"}
}