{
  "type": "Feature",
  "properties": {
    "gn:admin1_code":"13",
    "gn:admin2_code":"37.0",
    "gn:asciiname":"Huixastla",
    "gn:country_code":"MX",
    "gn:dem":1871,
    "gn:feature_class":"P",
    "gn:feature_code":"PPL",
    "gn:name":"Huixastla",
    "gn:population":0,
    "gn:timezone":"America/Mexico_City",
    "iso:country":"MX",
    "name:spa_x_preferred":[
        "Huixastla"
    ],
    "name:spa_x_variant":[
        "Huijastla"
    ],
    "wof:name":"Huixastla",
    "wof:placetype":"locality"
},
  "geometry": {"coordinates":[-98.73105,20.46649],"type":"Point"}
}