{
  "type": "Feature",
  "properties": {
    "gn:admin1_code":"20",
    "gn:admin2_code":"205.0",
    "gn:asciiname":"San Jose Arroyo Copete",
    "gn:country_code":"MX",
    "gn:dem":245,
    "gn:feature_class":"P",
    "gn:feature_code":"PPL",
    "gn:name":"San Jos\u00e9 Arroyo Copete",
    "gn:population":99,
    "gn:timezone":"America/Mexico_City",
    "iso:country":"MX",
    "name:und_x_variant":[
        "San Jos\u00e9 Arroyo Copete"
    ],
    "wof:name":"San Jose Arroyo Copete",
    "wof:placetype":"locality",
    "wof:population":99
},
  "geometry": {"coordinates":[-95.78444,17.39139],"type":"Point"}
}