{
  "type": "Feature",
  "properties": {
    "gn:admin1_code":"6",
    "gn:admin2_code":"63.0",
    "gn:asciiname":"Yepomera",
    "gn:country_code":"MX",
    "gn:dem":1936,
    "gn:feature_class":"P",
    "gn:feature_code":"PPL",
    "gn:name":"Yepomera",
    "gn:population":0,
    "gn:timezone":"America/Chihuahua",
    "iso:country":"MX",
    "name:spa_x_preferred":[
        "Yepomera"
    ],
    "name:und_x_variant":[
        "Yepomara",
        "Yeponera",
        "Yep\u00f3mera"
    ],
    "wof:name":"Yepomera",
    "wof:placetype":"locality"
},
  "geometry": {"coordinates":[-107.85290000000001,29.05408],"type":"Point"}
}