{
  "type": "Feature",
  "properties": {
    "gn:admin1_code":"10",
    "gn:admin2_code":"2.0",
    "gn:asciiname":"La Tembladora de Camellones",
    "gn:country_code":"MX",
    "gn:dem":2411,
    "gn:feature_class":"P",
    "gn:feature_code":"PPL",
    "gn:name":"La Tembladora de Camellones",
    "gn:population":0,
    "gn:timezone":"America/Monterrey",
    "iso:country":"MX",
    "wof:name":"La Tembladora de Camellones",
    "wof:placetype":"locality"
},
  "geometry": {"coordinates":[-106.22083000000001,25.04182],"type":"Point"}
}