{
  "type": "Feature",
  "properties": {
    "gn:admin1_code":"26.0",
    "gn:admin2_code":"4.0",
    "gn:asciiname":"El Caliroy",
    "gn:country_code":"MX",
    "gn:dem":370,
    "gn:feature_class":"P",
    "gn:feature_code":"PPL",
    "gn:name":"El Caliroy",
    "gn:population":0,
    "gn:timezone":"America/Hermosillo",
    "iso:country":"MX",
    "name:spa_x_preferred":[
        "El Caliroy"
    ],
    "name:und_x_variant":[
        "San Jos\u00e9"
    ],
    "wof:name":"El Caliroy",
    "wof:placetype":"locality"
},
  "geometry": {"coordinates":[-111.86377,30.60786],"type":"Point"}
}