{
  "type": "Feature",
  "properties": {
    "gn:admin1_code":"6",
    "gn:admin2_code":"27.0",
    "gn:asciiname":"Samachic",
    "gn:cc2":"MX",
    "gn:country_code":"MX",
    "gn:dem":2385,
    "gn:feature_class":"P",
    "gn:feature_code":"PPL",
    "gn:name":"Samachic",
    "gn:population":0,
    "gn:timezone":"America/Chihuahua",
    "iso:country":"MX",
    "name:und_x_variant":[
        "Samachique",
        "Samachic"
    ],
    "wof:name":"Samachic",
    "wof:placetype":"locality"
},
  "geometry": {"coordinates":[-107.46666999999999,27.28333],"type":"Point"}
}