{
  "type": "Feature",
  "properties": {
    "gn:admin1_code":"19.0",
    "gn:asciiname":"El Callejon de la Cueva",
    "gn:country_code":"MX",
    "gn:dem":1117,
    "gn:feature_class":"P",
    "gn:feature_code":"PPL",
    "gn:name":"El Callej\u00f3n de la Cueva",
    "gn:population":0,
    "gn:timezone":"America/Monterrey",
    "iso:country":"MX",
    "name:spa_x_preferred":[
        "El Callej\u00f3n de la Cueva"
    ],
    "wof:name":"El Callejon de la Cueva",
    "wof:placetype":"locality"
},
  "geometry": {"coordinates":[-99.80759999999999,24.09312000000001],"type":"Point"}
}