{
  "type": "Feature",
  "properties": {
    "gn:admin1_code":"32",
    "gn:admin2_code":"56.0",
    "gn:asciiname":"Picones",
    "gn:country_code":"MX",
    "gn:dem":2313,
    "gn:feature_class":"P",
    "gn:feature_code":"PPL",
    "gn:name":"Picones",
    "gn:population":638,
    "gn:timezone":"America/Mexico_City",
    "iso:country":"MX",
    "wof:name":"Picones",
    "wof:placetype":"locality",
    "wof:population":638
},
  "geometry": {"coordinates":[-102.63417,22.75417],"type":"Point"}
}