{
  "type": "Feature",
  "properties": {
    "gn:admin1_code":"11",
    "gn:admin2_code":"37.0",
    "gn:asciiname":"El Colon",
    "gn:country_code":"MX",
    "gn:dem":1751,
    "gn:feature_class":"P",
    "gn:feature_code":"PPL",
    "gn:name":"El Col\u00f3n",
    "gn:population":150,
    "gn:timezone":"America/Mexico_City",
    "iso:country":"MX",
    "name:und_x_variant":[
        "El Col\u00f3n"
    ],
    "wof:name":"El Colon",
    "wof:placetype":"locality",
    "wof:population":150
},
  "geometry": {"coordinates":[-101.41667,20.85861],"type":"Point"}
}