{
  "type": "Feature",
  "properties": {
    "gn:admin1_code":"10",
    "gn:admin2_code":"23.0",
    "gn:asciiname":"Rincon de los Carrizos",
    "gn:country_code":"MX",
    "gn:dem":2300,
    "gn:feature_class":"P",
    "gn:feature_code":"PPL",
    "gn:name":"Rinc\u00f3n de los Carrizos",
    "gn:population":0,
    "gn:timezone":"America/Monterrey",
    "iso:country":"MX",
    "name:spa_x_preferred":[
        "Rinc\u00f3n de los Carrizos"
    ],
    "wof:name":"Rincon de los Carrizos",
    "wof:placetype":"locality"
},
  "geometry": {"coordinates":[-105.18432,23.20459],"type":"Point"}
}