{
  "type": "Feature",
  "properties": {
    "gn:admin1_code":"14.0",
    "gn:admin2_code":"85.0",
    "gn:asciiname":"El Guamuchilito",
    "gn:country_code":"MX",
    "gn:dem":1408,
    "gn:feature_class":"P",
    "gn:feature_code":"PPL",
    "gn:name":"El Guamuchilito",
    "gn:population":0,
    "gn:timezone":"America/Mexico_City",
    "iso:country":"MX",
    "name:spa_x_preferred":[
        "El Guamuchilito"
    ],
    "wof:name":"El Guamuchilito",
    "wof:placetype":"locality"
},
  "geometry": {"coordinates":[-103.05616999999999,19.52828],"type":"Point"}
}