{
  "type": "Feature",
  "properties": {
    "gn:admin1_code":"31",
    "gn:admin2_code":"57.0",
    "gn:asciiname":"San Jose Paz",
    "gn:country_code":"MX",
    "gn:dem":11,
    "gn:feature_class":"P",
    "gn:feature_code":"PPL",
    "gn:name":"San Jos\u00e9 Paz",
    "gn:population":0,
    "gn:timezone":"America/Merida",
    "iso:country":"MX",
    "name:und_x_variant":[
        "San Jos\u00e9 Paz",
        "San Jos\u00e9"
    ],
    "wof:name":"San Jose Paz",
    "wof:placetype":"locality"
},
  "geometry": {"coordinates":[-88.46705,21.28445],"type":"Point"}
}