{
  "type": "Feature",
  "properties": {
    "gn:admin1_code":"19.0",
    "gn:asciiname":"La Capilla",
    "gn:country_code":"MX",
    "gn:dem":388,
    "gn:feature_class":"P",
    "gn:feature_code":"PPL",
    "gn:name":"La Capilla",
    "gn:population":0,
    "gn:timezone":"America/Monterrey",
    "iso:country":"MX",
    "name:spa_x_preferred":[
        "La Capilla"
    ],
    "wof:name":"La Capilla",
    "wof:placetype":"locality"
},
  "geometry": {"coordinates":[-99.55683999999999,24.80543],"type":"Point"}
}