{
  "type": "Feature",
  "properties": {
    "gn:admin1_code":"24",
    "gn:admin2_code":"15.0",
    "gn:asciiname":"Noria Pinta",
    "gn:country_code":"MX",
    "gn:dem":2148,
    "gn:feature_class":"P",
    "gn:feature_code":"PPL",
    "gn:name":"Noria Pinta",
    "gn:population":0,
    "gn:timezone":"America/Mexico_City",
    "iso:country":"MX",
    "name:spa_x_preferred":[
        "Noria Pinta"
    ],
    "wof:name":"Noria Pinta",
    "wof:placetype":"locality"
},
  "geometry": {"coordinates":[-101.26635,23.19649],"type":"Point"}
}