{
  "type": "Feature",
  "properties": {
    "gn:admin1_code":"30",
    "gn:admin2_code":"58.0",
    "gn:asciiname":"El Pensamiento",
    "gn:country_code":"MX",
    "gn:dem":93,
    "gn:feature_class":"P",
    "gn:feature_code":"PPL",
    "gn:name":"El Pensamiento",
    "gn:population":0,
    "gn:timezone":"America/Mexico_City",
    "iso:country":"MX",
    "name:spa_x_preferred":[
        "El Pensamiento"
    ],
    "wof:name":"El Pensamiento",
    "wof:placetype":"locality"
},
  "geometry": {"coordinates":[-98.14139,21.075],"type":"Point"}
}