{
  "type": "Feature",
  "properties": {
    "gn:admin1_code":"27.0",
    "gn:asciiname":"La Gironda",
    "gn:country_code":"MX",
    "gn:dem":15,
    "gn:feature_class":"P",
    "gn:feature_code":"PPL",
    "gn:name":"La Gironda",
    "gn:population":0,
    "gn:timezone":"America/Mexico_City",
    "iso:country":"MX",
    "name:spa_x_preferred":[
        "La Gironda"
    ],
    "wof:name":"La Gironda",
    "wof:placetype":"locality"
},
  "geometry": {"coordinates":[-91.48737,17.97397999999999],"type":"Point"}
}