{
  "type": "Feature",
  "properties": {
    "gn:admin1_code":"30",
    "gn:admin2_code":"150.0",
    "gn:asciiname":"Carmona y Valle",
    "gn:country_code":"MX",
    "gn:dem":92,
    "gn:feature_class":"P",
    "gn:feature_code":"PPL",
    "gn:name":"Carmona y Valle",
    "gn:population":0,
    "gn:timezone":"America/Mexico_City",
    "iso:country":"MX",
    "name:und_x_variant":[
        "San Bartolo"
    ],
    "wof:name":"Carmona y Valle",
    "wof:placetype":"locality"
},
  "geometry": {"coordinates":[-97.79554,21.36056],"type":"Point"}
}