{
  "type": "Feature",
  "properties": {
    "gn:admin1_code":"20",
    "gn:admin2_code":"515.0",
    "gn:asciiname":"Majada de Maluco",
    "gn:country_code":"MX",
    "gn:dem":305,
    "gn:feature_class":"P",
    "gn:feature_code":"PPL",
    "gn:name":"Majada de Maluco",
    "gn:population":0,
    "gn:timezone":"America/Mexico_City",
    "iso:country":"MX",
    "wof:name":"Majada de Maluco",
    "wof:placetype":"locality"
},
  "geometry": {"coordinates":[-95.46666999999999,16.33333],"type":"Point"}
}