{
  "type": "Feature",
  "properties": {
    "gn:admin1_code":"5.0",
    "gn:asciiname":"Las Aguilillas",
    "gn:country_code":"MX",
    "gn:dem":5,
    "gn:feature_class":"P",
    "gn:feature_code":"PPL",
    "gn:name":"Las Aguilillas",
    "gn:population":0,
    "gn:timezone":"America/Mexico_City",
    "iso:country":"MX",
    "name:spa_x_preferred":[
        "Las Aguilillas"
    ],
    "wof:name":"Las Aguilillas",
    "wof:placetype":"locality"
},
  "geometry": {"coordinates":[-93.11,15.39798],"type":"Point"}
}