{
  "type": "Feature",
  "properties": {
    "gn:admin1_code":"18.0",
    "gn:admin2_code":"1.0",
    "gn:asciiname":"El Centenario",
    "gn:country_code":"MX",
    "gn:dem":34,
    "gn:feature_class":"P",
    "gn:feature_code":"PPL",
    "gn:name":"El Centenario",
    "gn:population":701,
    "gn:timezone":"America/Mazatlan",
    "iso:country":"MX",
    "name:srp_x_preferred":[
        "\u0415\u043b \u0421\u0435\u043d\u0442\u0435\u043d\u0430\u0440\u0438\u043e"
    ],
    "wof:name":"El Centenario",
    "wof:placetype":"locality",
    "wof:population":701
},
  "geometry": {"coordinates":[-105.36444,22.51139],"type":"Point"}
}