{
  "type": "Feature",
  "properties": {
    "gn:admin1_code":"18.0",
    "gn:admin2_code":"1.0",
    "gn:asciiname":"El Centenario",
    "gn:country_code":"MX",
    "gn:dem":34,
    "gn:feature_class":"P",
    "gn:feature_code":"PPL",
    "gn:name":"El Centenario",
    "gn:population":701,
    "gn:timezone":"America/Mazatlan",
    "iso:country":"MX",
    "wof:name":"El Centenario",
    "wof:placetype":"locality",
    "wof:population":701
},
  "geometry": {"coordinates":[-105.36444,22.51139],"type":"Point"}
}