{
  "type": "Feature",
  "properties": {
    "gn:admin1_code":"1",
    "gn:admin2_code":"1",
    "gn:asciiname":"San Carlos",
    "gn:country_code":"MX",
    "gn:dem":1849,
    "gn:feature_class":"P",
    "gn:feature_code":"PPL",
    "gn:name":"San Carlos",
    "gn:population":24,
    "gn:timezone":"America/Mexico_City",
    "iso:country":"MX",
    "wof:name":"San Carlos",
    "wof:placetype":"locality",
    "wof:population":24
},
  "geometry": {"coordinates":[-102.34944,21.67778],"type":"Point"}
}