{
  "type": "Feature",
  "properties": {
    "gn:admin1_code":"6",
    "gn:admin2_code":"19.0",
    "gn:asciiname":"El Establo",
    "gn:country_code":"MX",
    "gn:dem":1567,
    "gn:feature_class":"P",
    "gn:feature_code":"PPL",
    "gn:name":"El Establo",
    "gn:population":0,
    "gn:timezone":"America/Chihuahua",
    "iso:country":"MX",
    "name:spa_x_preferred":[
        "El Establo"
    ],
    "wof:name":"El Establo",
    "wof:placetype":"locality"
},
  "geometry": {"coordinates":[-106.2355,29.00901],"type":"Point"}
}