{
  "type": "Feature",
  "properties": {
    "gn:admin1_code":"27",
    "gn:admin2_code":"6.0",
    "gn:asciiname":"El Mote",
    "gn:country_code":"MX",
    "gn:dem":16,
    "gn:feature_class":"P",
    "gn:feature_code":"PPL",
    "gn:name":"El Mote",
    "gn:population":0,
    "gn:timezone":"America/Mexico_City",
    "iso:country":"MX",
    "name:spa_x_preferred":[
        "El Monte"
    ],
    "name:spa_x_variant":[
        "El Mote"
    ],
    "wof:name":"El Mote",
    "wof:placetype":"locality"
},
  "geometry": {"coordinates":[-93.21012,18.03711],"type":"Point"}
}