{
  "type": "Feature",
  "properties": {
    "gn:admin1_code":"13",
    "gn:admin2_code":"50",
    "gn:asciiname":"El Xamu",
    "gn:country_code":"MX",
    "gn:dem":1970,
    "gn:feature_class":"P",
    "gn:feature_code":"PPL",
    "gn:name":"El Xamu",
    "gn:population":40,
    "gn:timezone":"America/Mexico_City",
    "iso:country":"MX",
    "wof:name":"El Xamu",
    "wof:placetype":"locality",
    "wof:population":40
},
  "geometry": {"coordinates":[-99.17833,20.27056],"type":"Point"}
}