{
  "type": "Feature",
  "properties": {
    "gn:admin1_code":"7",
    "gn:admin2_code":"32.0",
    "gn:asciiname":"Paso del Coyote",
    "gn:country_code":"MX",
    "gn:dem":383,
    "gn:feature_class":"P",
    "gn:feature_code":"PPL",
    "gn:name":"Paso del Coyote",
    "gn:population":0,
    "gn:timezone":"America/Monterrey",
    "iso:country":"MX",
    "name:spa_x_preferred":[
        "Paso del Coyote"
    ],
    "name:und_x_variant":[
        "Ejido Pred\u00edo Pur\u00edsima",
        "Pur\u00edsima",
        "La Pur\u00edsima"
    ],
    "wof:name":"Paso del Coyote",
    "wof:placetype":"locality"
},
  "geometry": {"coordinates":[-101.28315000000001,27.96295],"type":"Point"}
}