{
  "type": "Feature",
  "properties": {
    "gn:admin1_code":"30",
    "gn:admin2_code":"48",
    "gn:asciiname":"Temoloapan",
    "gn:country_code":"MX",
    "gn:dem":16,
    "gn:feature_class":"P",
    "gn:feature_code":"PPL",
    "gn:name":"Temoloapan",
    "gn:population":35,
    "gn:timezone":"America/Mexico_City",
    "iso:country":"MX",
    "wof:name":"Temoloapan",
    "wof:placetype":"locality",
    "wof:population":35
},
  "geometry": {"coordinates":[-94.66139,17.88278],"type":"Point"}
}