{
  "type": "Feature",
  "properties": {
    "gn:admin1_code":"17",
    "gn:admin2_code":"16.0",
    "gn:asciiname":"Tecuautitlan",
    "gn:country_code":"MX",
    "gn:dem":2505,
    "gn:feature_class":"P",
    "gn:feature_code":"PPL",
    "gn:name":"Tecuautitl\u00e1n",
    "gn:population":4,
    "gn:timezone":"America/Mexico_City",
    "iso:country":"MX",
    "name:spa_x_preferred":[
        "Tecuautitl\u00e1n"
    ],
    "wof:name":"Tecuautitlan",
    "wof:placetype":"locality",
    "wof:population":4
},
  "geometry": {"coordinates":[-98.68953,19.72972],"type":"Point"}
}