{
  "type": "Feature",
  "properties": {
    "gn:admin1_code":"28",
    "gn:admin2_code":"15.0",
    "gn:asciiname":"El Blanquito",
    "gn:cc2":"MX",
    "gn:country_code":"MX",
    "gn:dem":84,
    "gn:feature_class":"P",
    "gn:feature_code":"PPL",
    "gn:name":"El Blanquito",
    "gn:population":0,
    "gn:timezone":"America/Monterrey",
    "iso:country":"MX",
    "name:und_x_variant":[
        "El Blanquillo",
        "El Blanquito"
    ],
    "wof:name":"El Blanquito",
    "wof:placetype":"locality"
},
  "geometry": {"coordinates":[-98.63333,26.06667],"type":"Point"}
}