{
  "type": "Feature",
  "properties": {
    "gn:admin1_code":"15",
    "gn:admin2_code":"92.0",
    "gn:asciiname":"Ejido de San Sebastian",
    "gn:country_code":"MX",
    "gn:dem":2288,
    "gn:feature_class":"P",
    "gn:feature_code":"PPL",
    "gn:name":"Ejido de San Sebasti\u00e1n",
    "gn:population":690,
    "gn:timezone":"America/Mexico_City",
    "iso:country":"MX",
    "name:und_x_variant":[
        "Ejido de San Sebasti\u00e1n"
    ],
    "wof:name":"Ejido de San Sebastian",
    "wof:placetype":"locality",
    "wof:population":690
},
  "geometry": {"coordinates":[-98.84111,19.66861],"type":"Point"}
}