{
  "type": "Feature",
  "properties": {
    "gn:admin1_code":"12.0",
    "gn:asciiname":"Ojo de Agua Palo Gordo",
    "gn:country_code":"MX",
    "gn:dem":545,
    "gn:feature_class":"P",
    "gn:feature_code":"PPL",
    "gn:name":"Ojo de Agua Palo Gordo",
    "gn:population":0,
    "gn:timezone":"America/Mexico_City",
    "iso:country":"MX",
    "name:spa_x_preferred":[
        "Ojo de Agua Palo Gordo"
    ],
    "name:und_x_variant":[
        "Ojo de Agua"
    ],
    "wof:name":"Ojo de Agua Palo Gordo",
    "wof:placetype":"locality"
},
  "geometry": {"coordinates":[-100.57583,18.87652000000001],"type":"Point"}
}