{
  "type": "Feature",
  "properties": {
    "gn:admin1_code":"11",
    "gn:admin2_code":"1.0",
    "gn:asciiname":"San Fernando de Cerda",
    "gn:country_code":"MX",
    "gn:dem":1695,
    "gn:feature_class":"P",
    "gn:feature_code":"PPL",
    "gn:name":"San Fernando de Cerda",
    "gn:population":56,
    "gn:timezone":"America/Mexico_City",
    "iso:country":"MX",
    "wof:name":"San Fernando de Cerda",
    "wof:placetype":"locality",
    "wof:population":56
},
  "geometry": {"coordinates":[-101.60805999999999,20.36333],"type":"Point"}
}