{
  "type": "Feature",
  "properties": {
    "gn:admin1_code":"15",
    "gn:admin2_code":"17.0",
    "gn:asciiname":"Ex-hacienda San Andres Teticpan",
    "gn:country_code":"MX",
    "gn:dem":2432,
    "gn:feature_class":"P",
    "gn:feature_code":"PPL",
    "gn:name":"Ex-hacienda San Andr\u00e9s Teticpan",
    "gn:population":0,
    "gn:timezone":"America/Mexico_City",
    "iso:country":"MX",
    "name:spa_x_preferred":[
        "Ex-hacienda San Andr\u00e9s Teticpan"
    ],
    "name:und_x_variant":[
        "Retana",
        "Retama"
    ],
    "wof:name":"Ex-hacienda San Andres Teticpan",
    "wof:placetype":"locality"
},
  "geometry": {"coordinates":[-98.83327,19.11882],"type":"Point"}
}