{
  "type": "Feature",
  "properties": {
    "iso:country":"MX",
    "qs_pg:aaroncc":"MX",
    "qs_pg:name":"Soledad de Graciano Sanchez",
    "qs_pg:name_adm0":"M\u00e9xico",
    "qs_pg:name_adm1":"San Luis Potosi",
    "qs_pg:photos":61,
    "qs_pg:photos_1k":12,
    "qs_pg:photos_9k":1,
    "qs_pg:photos_9r":3,
    "qs_pg:photos_all":125,
    "qs_pg:photos_sr":2,
    "qs_pg:pop_sr":0,
    "qs_pg:qs_pg_placetype":"locality",
    "qs_pg:qs_pg_placetype_gp":"Town",
    "qs_pg:woe_adm0":23424900,
    "woe:adm0_id":23424900,
    "woe:name_adm0":"M\u00e9xico",
    "woe:name_adm1":"San Luis Potosi",
    "woe:placetype":"Town",
    "wof:name":"Soledad de Graciano Sanchez",
    "wof:placetype":"locality"
},
  "geometry": {"coordinates":[-100.922212,22.156883],"type":"Point"}
}