{
  "type": "Feature",
  "properties": {
    "gn:admin1_code":"32",
    "gn:admin2_code":"42.0",
    "gn:asciiname":"Providencia del Carmen",
    "gn:country_code":"MX",
    "gn:dem":2254,
    "gn:feature_class":"P",
    "gn:feature_code":"PPL",
    "gn:name":"Providencia del Carmen",
    "gn:population":0,
    "gn:timezone":"America/Mexico_City",
    "iso:country":"MX",
    "name:spa_x_preferred":[
        "Providencia del Carmen"
    ],
    "name:spa_x_variant":[
        "Providencia"
    ],
    "wof:name":"Providencia del Carmen",
    "wof:placetype":"locality"
},
  "geometry": {"coordinates":[-103.72741000000001,23.47389],"type":"Point"}
}