{
  "type": "Feature",
  "properties": {
    "gn:admin1_code":"20",
    "gn:admin2_code":"134.0",
    "gn:asciiname":"Loma Cafetal",
    "gn:country_code":"MX",
    "gn:dem":384,
    "gn:feature_class":"P",
    "gn:feature_code":"PPL",
    "gn:name":"Loma Cafetal",
    "gn:population":183,
    "gn:timezone":"America/Mexico_City",
    "iso:country":"MX",
    "wof:name":"Loma Cafetal",
    "wof:placetype":"locality",
    "wof:population":183
},
  "geometry": {"coordinates":[-96.58333,18.04333],"type":"Point"}
}