{
  "type": "Feature",
  "properties": {
    "gn:admin1_code":"13",
    "gn:admin2_code":"46.0",
    "gn:asciiname":"Colonia el Pedregal",
    "gn:country_code":"MX",
    "gn:dem":177,
    "gn:feature_class":"P",
    "gn:feature_code":"PPL",
    "gn:name":"Colonia el Pedregal",
    "gn:population":393,
    "gn:timezone":"America/Mexico_City",
    "iso:country":"MX",
    "wof:name":"Colonia el Pedregal",
    "wof:placetype":"locality",
    "wof:population":393
},
  "geometry": {"coordinates":[-98.5925,21.17528],"type":"Point"}
}