{
  "type": "Feature",
  "properties": {
    "gn:admin1_code":"31",
    "gn:admin2_code":"53.0",
    "gn:asciiname":"Sancaba",
    "gn:country_code":"MX",
    "gn:dem":21,
    "gn:feature_class":"P",
    "gn:feature_code":"PPL",
    "gn:name":"Sancab\u00e1",
    "gn:population":0,
    "gn:timezone":"America/Merida",
    "iso:country":"MX",
    "name:spa_x_preferred":[
        "Sancab\u00e1"
    ],
    "name:und_x_variant":[
        "Sahcab\u00e1"
    ],
    "wof:name":"Sancaba",
    "wof:placetype":"locality"
},
  "geometry": {"coordinates":[-89.75173000000002,20.50461],"type":"Point"}
}