{
  "type": "Feature",
  "properties": {
    "gn:admin1_code":"24",
    "gn:admin2_code":"29.0",
    "gn:asciiname":"Ocuiltzapoyo",
    "gn:country_code":"MX",
    "gn:dem":140,
    "gn:feature_class":"P",
    "gn:feature_code":"PPL",
    "gn:name":"Ocuiltzapoyo",
    "gn:population":1060,
    "gn:timezone":"America/Mexico_City",
    "iso:country":"MX",
    "wof:name":"Ocuiltzapoyo",
    "wof:placetype":"locality",
    "wof:population":1060
},
  "geometry": {"coordinates":[-98.72861,21.32444],"type":"Point"}
}