{
  "type": "Feature",
  "properties": {
    "gn:admin1_code":"12",
    "gn:admin2_code":"73.0",
    "gn:asciiname":"El Caulote",
    "gn:country_code":"MX",
    "gn:dem":522,
    "gn:feature_class":"P",
    "gn:feature_code":"PPL",
    "gn:name":"El Caulote",
    "gn:population":0,
    "gn:timezone":"America/Mexico_City",
    "iso:country":"MX",
    "name:spa_x_preferred":[
        "El Caulote"
    ],
    "wof:name":"El Caulote",
    "wof:placetype":"locality"
},
  "geometry": {"coordinates":[-101.0813,18.27527000000001],"type":"Point"}
}