{
  "type": "Feature",
  "properties": {
    "gn:admin1_code":"30",
    "gn:admin2_code":"209.0",
    "gn:asciiname":"Mezcalapa",
    "gn:country_code":"MX",
    "gn:dem":31,
    "gn:feature_class":"P",
    "gn:feature_code":"PPL",
    "gn:name":"Mezcalapa",
    "gn:population":308,
    "gn:timezone":"America/Mexico_City",
    "iso:country":"MX",
    "wof:name":"Mezcalapa",
    "wof:placetype":"locality",
    "wof:population":308
},
  "geometry": {"coordinates":[-94.79028,18.46028],"type":"Point"}
}