{
  "type": "Feature",
  "properties": {
    "gn:admin1_code":"12",
    "gn:admin2_code":"48",
    "gn:asciiname":"El Rincon",
    "gn:country_code":"MX",
    "gn:dem":593,
    "gn:feature_class":"P",
    "gn:feature_code":"PPL",
    "gn:name":"El Rinc\u00f3n",
    "gn:population":15,
    "gn:timezone":"America/Mexico_City",
    "iso:country":"MX",
    "name:und_x_variant":[
        "El Rinc\u00f3n"
    ],
    "wof:name":"El Rincon",
    "wof:placetype":"locality",
    "wof:population":15
},
  "geometry": {"coordinates":[-101.24011,17.72581],"type":"Point"}
}