{
  "type": "Feature",
  "properties": {
    "gn:admin1_code":"2",
    "gn:admin2_code":"4",
    "gn:asciiname":"Los Venados (Los Elizalde)",
    "gn:country_code":"MX",
    "gn:dem":218,
    "gn:feature_class":"P",
    "gn:feature_code":"PPL",
    "gn:name":"Los Venados (Los Elizalde)",
    "gn:population":12,
    "gn:timezone":"America/Tijuana",
    "iso:country":"MX",
    "wof:name":"Los Venados (Los Elizalde)",
    "wof:placetype":"locality",
    "wof:population":12
},
  "geometry": {"coordinates":[-116.92278,32.41944],"type":"Point"}
}