{
  "type": "Feature",
  "properties": {
    "gn:admin1_code":"28",
    "gn:admin2_code":"16.0",
    "gn:asciiname":"Las Tinajas",
    "gn:country_code":"MX",
    "gn:dem":236,
    "gn:feature_class":"P",
    "gn:feature_code":"PPL",
    "gn:name":"Las Tinajas",
    "gn:population":0,
    "gn:timezone":"America/Monterrey",
    "iso:country":"MX",
    "name:spa_x_preferred":[
        "Las Tinajas"
    ],
    "name:und_x_variant":[
        "Rancho La Tinaja",
        "Tinajas"
    ],
    "wof:name":"Las Tinajas",
    "wof:placetype":"locality"
},
  "geometry": {"coordinates":[-99.27941,24.23381],"type":"Point"}
}