{
  "type": "Feature",
  "properties": {
    "gn:admin1_code":"2",
    "gn:admin2_code":"3.0",
    "gn:asciiname":"El Yaqui",
    "gn:country_code":"MX",
    "gn:dem":590,
    "gn:feature_class":"P",
    "gn:feature_code":"PPL",
    "gn:name":"El Yaqui",
    "gn:population":98,
    "gn:timezone":"America/Tijuana",
    "iso:country":"MX",
    "wof:name":"El Yaqui",
    "wof:placetype":"locality",
    "wof:population":98
},
  "geometry": {"coordinates":[-116.57277999999999,32.56],"type":"Point"}
}