{
  "type": "Feature",
  "properties": {
    "gn:admin1_code":"6.0",
    "gn:admin2_code":"2.0",
    "gn:asciiname":"Pueblito",
    "gn:country_code":"MX",
    "gn:dem":979,
    "gn:feature_class":"P",
    "gn:feature_code":"PPL",
    "gn:name":"Pueblito",
    "gn:population":0,
    "gn:timezone":"America/Chihuahua",
    "iso:country":"MX",
    "name:und_x_variant":[
        "El Pueblito"
    ],
    "wof:name":"Pueblito",
    "wof:placetype":"locality"
},
  "geometry": {"coordinates":[-105.11203999999999,29.10065],"type":"Point"}
}