{
  "type": "Feature",
  "properties": {
    "gn:admin1_code":"19",
    "gn:admin2_code":"17.0",
    "gn:asciiname":"El Saucito",
    "gn:country_code":"MX",
    "gn:dem":2137,
    "gn:feature_class":"P",
    "gn:feature_code":"PPL",
    "gn:name":"El Saucito",
    "gn:population":6,
    "gn:timezone":"America/Monterrey",
    "iso:country":"MX",
    "wof:name":"El Saucito",
    "wof:placetype":"locality",
    "wof:population":6
},
  "geometry": {"coordinates":[-100.63807,25.21311],"type":"Point"}
}