{
  "type": "Feature",
  "properties": {
    "gn:admin1_code":"5.0",
    "gn:admin2_code":"89.0",
    "gn:asciiname":"Santa Estefania",
    "gn:country_code":"MX",
    "gn:dem":20,
    "gn:feature_class":"P",
    "gn:feature_code":"PPL",
    "gn:name":"Santa Estefan\u00eda",
    "gn:population":0,
    "gn:timezone":"America/Mexico_City",
    "iso:country":"MX",
    "name:spa_x_preferred":[
        "Santa Estefan\u00eda"
    ],
    "wof:name":"Santa Estefania",
    "wof:placetype":"locality"
},
  "geometry": {"coordinates":[-92.38804,14.74604],"type":"Point"}
}