{
  "type": "Feature",
  "properties": {
    "gn:admin1_code":"11.0",
    "gn:admin2_code":"31.0",
    "gn:asciiname":"El Mogote",
    "gn:country_code":"MX",
    "gn:dem":1795,
    "gn:feature_class":"P",
    "gn:feature_code":"PPL",
    "gn:name":"El Mogote",
    "gn:population":0,
    "gn:timezone":"America/Mexico_City",
    "iso:country":"MX",
    "name:spa_x_preferred":[
        "El Mogote"
    ],
    "wof:name":"El Mogote",
    "wof:placetype":"locality"
},
  "geometry": {"coordinates":[-101.83377,20.93941],"type":"Point"}
}