{
  "type": "Feature",
  "properties": {
    "gn:admin1_code":"10",
    "gn:admin2_code":"26.0",
    "gn:asciiname":"Las Cuevas",
    "gn:country_code":"MX",
    "gn:dem":904,
    "gn:feature_class":"P",
    "gn:feature_code":"PPL",
    "gn:name":"Las Cuevas",
    "gn:population":0,
    "gn:timezone":"America/Mazatlan",
    "iso:country":"MX",
    "name:ceb_x_preferred":[
        "Las Cuevas"
    ],
    "name:deu_x_preferred":[
        "Las Cuevas"
    ],
    "name:nds_x_preferred":[
        "Las Cuevas"
    ],
    "name:spa_x_preferred":[
        "Las Cuevas"
    ],
    "name:swe_x_preferred":[
        "Las Cuevas"
    ],
    "wof:name":"Las Cuevas",
    "wof:placetype":"locality"
},
  "geometry": {"coordinates":[-105.86138,23.69836],"type":"Point"}
}