{
  "type": "Feature",
  "properties": {
    "gn:admin1_code":"26",
    "gn:admin2_code":"44.0",
    "gn:asciiname":"El Tulito",
    "gn:country_code":"MX",
    "gn:dem":620,
    "gn:feature_class":"P",
    "gn:feature_code":"PPL",
    "gn:name":"El Tulito",
    "gn:population":0,
    "gn:timezone":"America/Hermosillo",
    "iso:country":"MX",
    "name:spa_x_preferred":[
        "El Tulito"
    ],
    "wof:name":"El Tulito",
    "wof:placetype":"locality"
},
  "geometry": {"coordinates":[-109.38406999999999,28.47505],"type":"Point"}
}