{
  "type": "Feature",
  "properties": {
    "gn:admin1_code":"21.0",
    "gn:admin2_code":"3.0",
    "gn:asciiname":"Tierra Blanca",
    "gn:country_code":"MX",
    "gn:dem":1156,
    "gn:feature_class":"P",
    "gn:feature_code":"PPL",
    "gn:name":"Tierra Blanca",
    "gn:population":0,
    "gn:timezone":"America/Mexico_City",
    "iso:country":"MX",
    "name:ceb_x_preferred":[
        "Tierra Blanca"
    ],
    "name:deu_x_preferred":[
        "Tierra Blanca"
    ],
    "name:ita_x_preferred":[
        "Tierra Blanca"
    ],
    "name:pol_x_preferred":[
        "Tierra Blanca"
    ],
    "name:por_x_preferred":[
        "Tierra Blanca"
    ],
    "name:sco_x_preferred":[
        "Tierra Blanca"
    ],
    "name:spa_x_preferred":[
        "Tierra Blanca"
    ],
    "name:swe_x_preferred":[
        "Tierra Blanca"
    ],
    "wof:name":"Tierra Blanca",
    "wof:placetype":"locality"
},
  "geometry": {"coordinates":[-98.20645,18.01747],"type":"Point"}
}