{
  "type": "Feature",
  "properties": {
    "gn:admin1_code":"10.0",
    "gn:admin2_code":"5.0",
    "gn:asciiname":"El Chimal",
    "gn:country_code":"MX",
    "gn:dem":1892,
    "gn:feature_class":"P",
    "gn:feature_code":"PPL",
    "gn:name":"El Chimal",
    "gn:population":0,
    "gn:timezone":"America/Monterrey",
    "iso:country":"MX",
    "name:spa_x_preferred":[
        "El Chimal"
    ],
    "name:und_x_variant":[
        "Chimal"
    ],
    "wof:name":"El Chimal",
    "wof:placetype":"locality"
},
  "geometry": {"coordinates":[-104.54049999999999,23.90258],"type":"Point"}
}