{
  "type": "Feature",
  "properties": {
    "gn:admin1_code":"30",
    "gn:admin2_code":"56.0",
    "gn:asciiname":"Cuesta de Chorro",
    "gn:country_code":"MX",
    "gn:dem":297,
    "gn:feature_class":"P",
    "gn:feature_code":"PPL",
    "gn:name":"Cuesta de Chorro",
    "gn:population":6,
    "gn:timezone":"America/Mexico_City",
    "iso:country":"MX",
    "wof:name":"Cuesta de Chorro",
    "wof:placetype":"locality",
    "wof:population":6
},
  "geometry": {"coordinates":[-98.45,21.21],"type":"Point"}
}