{
  "type": "Feature",
  "properties": {
    "gn:admin1_code":"12.0",
    "gn:asciiname":"Temixco",
    "gn:country_code":"MX",
    "gn:dem":1428,
    "gn:feature_class":"P",
    "gn:feature_code":"PPL",
    "gn:name":"Temixco",
    "gn:population":0,
    "gn:timezone":"America/Mexico_City",
    "iso:country":"MX",
    "name:spa_x_preferred":[
        "Temixco"
    ],
    "name:spa_x_variant":[
        "Rancho Temixco"
    ],
    "wof:name":"Temixco",
    "wof:placetype":"locality"
},
  "geometry": {"coordinates":[-99.40244,17.58822],"type":"Point"}
}