{
  "type": "Feature",
  "properties": {
    "gn:admin1_code":"32",
    "gn:admin2_code":"10.0",
    "gn:asciiname":"Raul Alba",
    "gn:country_code":"MX",
    "gn:dem":2090,
    "gn:feature_class":"P",
    "gn:feature_code":"PPL",
    "gn:name":"Ra\u00fal Alba",
    "gn:population":9,
    "gn:timezone":"America/Mexico_City",
    "iso:country":"MX",
    "name:und_x_variant":[
        "Ra\u00fal Alba"
    ],
    "wof:name":"Raul Alba",
    "wof:placetype":"locality",
    "wof:population":9
},
  "geometry": {"coordinates":[-102.63056,23.10333],"type":"Point"}
}