{
  "type": "Feature",
  "properties": {
    "gn:admin1_code":"6",
    "gn:admin2_code":"27.0",
    "gn:asciiname":"Ranacherachi",
    "gn:country_code":"MX",
    "gn:dem":2351,
    "gn:feature_class":"P",
    "gn:feature_code":"PPL",
    "gn:name":"Ranacherachi",
    "gn:population":6,
    "gn:timezone":"America/Chihuahua",
    "iso:country":"MX",
    "wof:name":"Ranacherachi",
    "wof:placetype":"locality",
    "wof:population":6
},
  "geometry": {"coordinates":[-107.37269000000001,27.48854],"type":"Point"}
}