{
  "type": "Feature",
  "properties": {
    "gn:admin1_code":"16.0",
    "gn:admin2_code":"71.0",
    "gn:asciiname":"Las Sanguijuelas",
    "gn:country_code":"MX",
    "gn:dem":2020,
    "gn:feature_class":"P",
    "gn:feature_code":"PPL",
    "gn:name":"Las Sanguijuelas",
    "gn:population":773,
    "gn:timezone":"America/Mexico_City",
    "iso:country":"MX",
    "name:spa_x_preferred":[
        "Las Sanguijuelas"
    ],
    "name:spa_x_variant":[
        "Sanguijuelas"
    ],
    "wof:name":"Las Sanguijuelas",
    "wof:placetype":"locality",
    "wof:population":773
},
  "geometry": {"coordinates":[-101.42474,20.26389],"type":"Point"}
}