{
  "type": "Feature",
  "properties": {
    "gn:admin1_code":"16",
    "gn:admin2_code":"9",
    "gn:asciiname":"La Escondida",
    "gn:country_code":"MX",
    "gn:dem":2171,
    "gn:feature_class":"P",
    "gn:feature_code":"PPL",
    "gn:name":"La Escondida",
    "gn:population":15,
    "gn:timezone":"America/Mexico_City",
    "iso:country":"MX",
    "wof:name":"La Escondida",
    "wof:placetype":"locality",
    "wof:population":15
},
  "geometry": {"coordinates":[-101.6425,19.20889],"type":"Point"}
}