{
  "type": "Feature",
  "properties": {
    "gn:admin1_code":"23.0",
    "gn:admin2_code":"4.0",
    "gn:asciiname":"U-yumil-ceh",
    "gn:country_code":"MX",
    "gn:dem":7,
    "gn:feature_class":"P",
    "gn:feature_code":"PPL",
    "gn:name":"U-yumil-ceh",
    "gn:population":0,
    "gn:timezone":"America/Cancun",
    "iso:country":"MX",
    "name:spa_x_preferred":[
        "U-yumil-ceh"
    ],
    "wof:name":"U-yumil-ceh",
    "wof:placetype":"locality"
},
  "geometry": {"coordinates":[-87.67747,18.81595],"type":"Point"}
}