{
  "type": "Feature",
  "properties": {
    "gn:admin1_code":"26",
    "gn:admin2_code":"57.0",
    "gn:asciiname":"Tebonchi",
    "gn:country_code":"MX",
    "gn:dem":363,
    "gn:feature_class":"P",
    "gn:feature_code":"PPL",
    "gn:name":"Tebonchi",
    "gn:population":0,
    "gn:timezone":"America/Hermosillo",
    "iso:country":"MX",
    "name:spa_x_preferred":[
        "Tebonchi"
    ],
    "name:spa_x_variant":[
        "Agua de los Burros"
    ],
    "wof:name":"Tebonchi",
    "wof:placetype":"locality"
},
  "geometry": {"coordinates":[-109.73708000000001,29.19901],"type":"Point"}
}