{
  "type": "Feature",
  "properties": {
    "gn:admin1_code":"30.0",
    "gn:admin2_code":"69.0",
    "gn:asciiname":"El Cepillo",
    "gn:country_code":"MX",
    "gn:dem":23,
    "gn:feature_class":"P",
    "gn:feature_code":"PPL",
    "gn:name":"El Cepillo",
    "gn:population":306,
    "gn:timezone":"America/Mexico_City",
    "iso:country":"MX",
    "name:spa_x_preferred":[
        "El Cepillo"
    ],
    "wof:name":"El Cepillo",
    "wof:placetype":"locality",
    "wof:population":306
},
  "geometry": {"coordinates":[-97.12721999999999,20.41774],"type":"Point"}
}