{
  "type": "Feature",
  "properties": {
    "gn:admin1_code":"2",
    "gn:admin2_code":"1.0",
    "gn:asciiname":"Miramar",
    "gn:country_code":"MX",
    "gn:dem":45,
    "gn:feature_class":"P",
    "gn:feature_code":"PPL",
    "gn:name":"Miramar",
    "gn:population":0,
    "gn:timezone":"America/Tijuana",
    "iso:country":"MX",
    "name:spa_x_preferred":[
        "Miramar"
    ],
    "name:und_x_variant":[
        "Rancho Miramar"
    ],
    "wof:name":"Miramar",
    "wof:placetype":"locality"
},
  "geometry": {"coordinates":[-116.45225000000001,31.3552],"type":"Point"}
}