{
  "type": "Feature",
  "properties": {
    "gn:admin1_code":"30",
    "gn:admin2_code":"148.0",
    "gn:asciiname":"Colonia Jose Cardel",
    "gn:country_code":"MX",
    "gn:dem":133,
    "gn:feature_class":"P",
    "gn:feature_code":"PPL",
    "gn:name":"Colonia Jos\u00e9 Cardel",
    "gn:population":0,
    "gn:timezone":"America/Mexico_City",
    "iso:country":"MX",
    "name:spa_x_preferred":[
        "Colonia Jos\u00e9 Cardel"
    ],
    "name:und_x_variant":[
        "Jos\u00e9 C\u00e1rdel"
    ],
    "wof:name":"Colonia Jose Cardel",
    "wof:placetype":"locality"
},
  "geometry": {"coordinates":[-96.44519,19.06815],"type":"Point"}
}