{
  "type": "Feature",
  "properties": {
    "gn:admin1_code":"26",
    "gn:admin2_code":"17.0",
    "gn:asciiname":"Campo Norte",
    "gn:country_code":"MX",
    "gn:dem":198,
    "gn:feature_class":"P",
    "gn:feature_code":"PPL",
    "gn:name":"Campo Norte",
    "gn:population":5,
    "gn:timezone":"America/Hermosillo",
    "iso:country":"MX",
    "wof:name":"Campo Norte",
    "wof:placetype":"locality",
    "wof:population":5
},
  "geometry": {"coordinates":[-112.37833000000001,30.58222],"type":"Point"}
}