{
  "type": "Feature",
  "properties": {
    "gn:admin1_code":"7",
    "gn:admin2_code":"36.0",
    "gn:asciiname":"Tanque Aguilereno",
    "gn:country_code":"MX",
    "gn:dem":1467,
    "gn:feature_class":"P",
    "gn:feature_code":"PPL",
    "gn:name":"Tanque Aguilere\u00f1o",
    "gn:population":0,
    "gn:timezone":"America/Monterrey",
    "iso:country":"MX",
    "name:spa_x_preferred":[
        "Tanque Aguilere\u00f1o"
    ],
    "wof:name":"Tanque Aguilereno",
    "wof:placetype":"locality"
},
  "geometry": {"coordinates":[-102.94882,24.8128],"type":"Point"}
}