{
  "type": "Feature",
  "properties": {
    "gn:admin1_code":"19.0",
    "gn:admin2_code":"3.0",
    "gn:asciiname":"La Parcela",
    "gn:country_code":"MX",
    "gn:dem":132,
    "gn:feature_class":"P",
    "gn:feature_code":"PPL",
    "gn:name":"La Parcela",
    "gn:population":0,
    "gn:timezone":"America/Monterrey",
    "iso:country":"MX",
    "name:spa_x_preferred":[
        "La Parcela"
    ],
    "wof:name":"La Parcela",
    "wof:placetype":"locality"
},
  "geometry": {"coordinates":[-99.30148,25.91612000000001],"type":"Point"}
}