{
  "type": "Feature",
  "properties": {
    "gn:admin1_code":"6",
    "gn:admin2_code":"29.0",
    "gn:asciiname":"Las Piedras de Amolar",
    "gn:country_code":"MX",
    "gn:dem":2678,
    "gn:feature_class":"P",
    "gn:feature_code":"PPL",
    "gn:name":"Las Piedras de Amolar",
    "gn:population":0,
    "gn:timezone":"America/Chihuahua",
    "iso:country":"MX",
    "name:spa_x_preferred":[
        "Las Piedras de Amolar"
    ],
    "wof:name":"Las Piedras de Amolar",
    "wof:placetype":"locality"
},
  "geometry": {"coordinates":[-106.60097,26.22788],"type":"Point"}
}