{
  "type": "Feature",
  "properties": {
    "gn:admin1_code":"23.0",
    "gn:asciiname":"La Curva",
    "gn:country_code":"MX",
    "gn:dem":82,
    "gn:feature_class":"P",
    "gn:feature_code":"PPL",
    "gn:name":"La Curva",
    "gn:population":0,
    "gn:timezone":"America/Cancun",
    "iso:country":"MX",
    "name:spa_x_preferred":[
        "La Curva"
    ],
    "wof:name":"La Curva",
    "wof:placetype":"locality"
},
  "geometry": {"coordinates":[-88.85954,18.47729],"type":"Point"}
}