{
  "type": "Feature",
  "properties": {
    "gn:admin1_code":"25",
    "gn:admin2_code":"6.0",
    "gn:asciiname":"Los Compadres",
    "gn:country_code":"MX",
    "gn:dem":56,
    "gn:feature_class":"P",
    "gn:feature_code":"PPL",
    "gn:name":"Los Compadres",
    "gn:population":6,
    "gn:timezone":"America/Mazatlan",
    "iso:country":"MX",
    "name:bre_x_preferred":[
        "Los Compadres"
    ],
    "name:ell_x_preferred":[
        "Los Compadres"
    ],
    "name:epo_x_preferred":[
        "D\u00fao Los Compadres"
    ],
    "name:ita_x_preferred":[
        "Los Compadres"
    ],
    "name:spa_x_preferred":[
        "D\u00fao Los Compadres"
    ],
    "wof:name":"Los Compadres",
    "wof:placetype":"locality",
    "wof:population":6
},
  "geometry": {"coordinates":[-107.29039,24.56104],"type":"Point"}
}