{
  "type": "Feature",
  "properties": {
    "gn:admin1_code":"30.0",
    "gn:admin2_code":"121.0",
    "gn:asciiname":"El Humal",
    "gn:country_code":"MX",
    "gn:dem":74,
    "gn:feature_class":"P",
    "gn:feature_code":"PPL",
    "gn:name":"El Humal",
    "gn:population":14,
    "gn:timezone":"America/Mexico_City",
    "iso:country":"MX",
    "name:spa_x_preferred":[
        "El Humal"
    ],
    "wof:name":"El Humal",
    "wof:placetype":"locality",
    "wof:population":14
},
  "geometry": {"coordinates":[-97.91218000000001,21.55501],"type":"Point"}
}