{
  "type": "Feature",
  "properties": {
    "gn:admin1_code":"20",
    "gn:admin2_code":"226.0",
    "gn:asciiname":"Roaguia",
    "gn:country_code":"MX",
    "gn:dem":1824,
    "gn:feature_class":"P",
    "gn:feature_code":"PPL",
    "gn:name":"Roagu\u00eda",
    "gn:population":0,
    "gn:timezone":"America/Mexico_City",
    "iso:country":"MX",
    "name:spa_x_preferred":[
        "Hoagu\u00eda"
    ],
    "name:spa_x_variant":[
        "Roagu\u00eda"
    ],
    "wof:name":"Roaguia",
    "wof:placetype":"locality"
},
  "geometry": {"coordinates":[-96.27884,16.87265],"type":"Point"}
}