{
  "type": "Feature",
  "properties": {
    "gn:admin1_code":"25",
    "gn:admin2_code":"12",
    "gn:asciiname":"El Guayabo",
    "gn:country_code":"MX",
    "gn:dem":109,
    "gn:feature_class":"P",
    "gn:feature_code":"PPL",
    "gn:name":"El Guayabo",
    "gn:population":21,
    "gn:timezone":"America/Mazatlan",
    "iso:country":"MX",
    "wof:name":"El Guayabo",
    "wof:placetype":"locality",
    "wof:population":21
},
  "geometry": {"coordinates":[-106.33984,23.38946],"type":"Point"}
}