{
  "type": "Feature",
  "properties": {
    "gn:admin1_code":"5",
    "gn:admin2_code":"2.0",
    "gn:asciiname":"Camino Pintado",
    "gn:country_code":"MX",
    "gn:dem":426,
    "gn:feature_class":"P",
    "gn:feature_code":"PPL",
    "gn:name":"Camino Pintado",
    "gn:population":4,
    "gn:timezone":"America/Mexico_City",
    "iso:country":"MX",
    "wof:name":"Camino Pintado",
    "wof:placetype":"locality",
    "wof:population":4
},
  "geometry": {"coordinates":[-92.89225999999999,16.60982000000001],"type":"Point"}
}