{
  "type": "Feature",
  "properties": {
    "gn:admin1_code":"16.0",
    "gn:admin2_code":"95.0",
    "gn:asciiname":"Cuesta el Yeso",
    "gn:country_code":"MX",
    "gn:dem":1272,
    "gn:feature_class":"P",
    "gn:feature_code":"PPL",
    "gn:name":"Cuesta el Yeso",
    "gn:population":0,
    "gn:timezone":"America/Mexico_City",
    "iso:country":"MX",
    "name:spa_x_preferred":[
        "Cuesta el Yeso"
    ],
    "wof:name":"Cuesta el Yeso",
    "wof:placetype":"locality"
},
  "geometry": {"coordinates":[-102.60821,19.64362],"type":"Point"}
}