{
  "type": "Feature",
  "properties": {
    "gn:admin1_code":"12",
    "gn:admin2_code":"71.0",
    "gn:asciiname":"Cumbre de San Jose",
    "gn:country_code":"MX",
    "gn:dem":519,
    "gn:feature_class":"P",
    "gn:feature_code":"PPL",
    "gn:name":"Cumbre de San Jos\u00e9",
    "gn:population":356,
    "gn:timezone":"America/Mexico_City",
    "iso:country":"MX",
    "name:und_x_variant":[
        "Cumbre de San Jos\u00e9"
    ],
    "wof:name":"Cumbre de San Jose",
    "wof:placetype":"locality",
    "wof:population":356
},
  "geometry": {"coordinates":[-98.19414,16.79635],"type":"Point"}
}