{
  "type": "Feature",
  "properties": {
    "gn:admin1_code":"14",
    "gn:admin2_code":"99.0",
    "gn:asciiname":"Loma del Camichin",
    "gn:country_code":"MX",
    "gn:dem":680,
    "gn:feature_class":"P",
    "gn:feature_code":"PPL",
    "gn:name":"Loma del Camich\u00edn",
    "gn:population":8,
    "gn:timezone":"America/Mexico_City",
    "iso:country":"MX",
    "name:und_x_variant":[
        "Loma del Camich\u00edn"
    ],
    "wof:name":"Loma del Camichin",
    "wof:placetype":"locality",
    "wof:population":8
},
  "geometry": {"coordinates":[-103.87944,19.50306],"type":"Point"}
}