{
  "type": "Feature",
  "properties": {
    "gn:admin1_code":"26",
    "gn:admin2_code":"30.0",
    "gn:asciiname":"Miguel Aleman",
    "gn:country_code":"MX",
    "gn:dem":24,
    "gn:feature_class":"P",
    "gn:feature_code":"PPL",
    "gn:name":"Miguel Alem\u00e1n",
    "gn:population":0,
    "gn:timezone":"America/Hermosillo",
    "iso:country":"MX",
    "name:spa_x_preferred":[
        "Miguel Alem\u00e1n"
    ],
    "name:spa_x_variant":[
        "Santa Cruz"
    ],
    "wof:name":"Miguel Aleman",
    "wof:placetype":"locality"
},
  "geometry": {"coordinates":[-111.50363,28.56637000000001],"type":"Point"}
}