{
  "type": "Feature",
  "properties": {
    "gn:admin1_code":"6",
    "gn:admin2_code":"9",
    "gn:asciiname":"Estacion Sanchez",
    "gn:country_code":"MX",
    "gn:dem":2455,
    "gn:feature_class":"P",
    "gn:feature_code":"PPL",
    "gn:name":"Estaci\u00f3n S\u00e1nchez",
    "gn:population":11,
    "gn:timezone":"America/Chihuahua",
    "iso:country":"MX",
    "name:und_x_variant":[
        "Estaci\u00f3n S\u00e1nchez"
    ],
    "wof:name":"Estacion Sanchez",
    "wof:placetype":"locality",
    "wof:population":11
},
  "geometry": {"coordinates":[-107.67778,27.71972],"type":"Point"}
}