{
  "type": "Feature",
  "properties": {
    "gn:admin1_code":"27",
    "gn:admin2_code":"17.0",
    "gn:asciiname":"El Xotal Primera",
    "gn:country_code":"MX",
    "gn:dem":76,
    "gn:feature_class":"P",
    "gn:feature_code":"PPL",
    "gn:name":"El Xotal Primera",
    "gn:population":0,
    "gn:timezone":"America/Mexico_City",
    "iso:country":"MX",
    "name:spa_x_preferred":[
        "El Xotal Primera"
    ],
    "name:spa_x_variant":[
        "Xotal"
    ],
    "wof:name":"El Xotal Primera",
    "wof:placetype":"locality"
},
  "geometry": {"coordinates":[-91.22726,17.3564],"type":"Point"}
}