{
  "type": "Feature",
  "properties": {
    "gn:admin1_code":"20",
    "gn:admin2_code":"136.0",
    "gn:asciiname":"San Antonio del Barrio",
    "gn:country_code":"MX",
    "gn:dem":577,
    "gn:feature_class":"P",
    "gn:feature_code":"PPL",
    "gn:name":"San Antonio del Barrio",
    "gn:population":165,
    "gn:timezone":"America/Mexico_City",
    "iso:country":"MX",
    "wof:name":"San Antonio del Barrio",
    "wof:placetype":"locality",
    "wof:population":165
},
  "geometry": {"coordinates":[-96.55583,17.75889],"type":"Point"}
}