{
  "type": "Feature",
  "properties": {
    "gn:admin1_code":"20.0",
    "gn:admin2_code":"141.0",
    "gn:asciiname":"Los Patos",
    "gn:country_code":"MX",
    "gn:dem":45,
    "gn:feature_class":"P",
    "gn:feature_code":"PPL",
    "gn:name":"Los Patos",
    "gn:population":0,
    "gn:timezone":"America/Mexico_City",
    "iso:country":"MX",
    "name:deu_x_preferred":[
        "Los Patos"
    ],
    "name:fra_x_preferred":[
        "Los Patos"
    ],
    "name:ita_x_preferred":[
        "Tres Quebradas"
    ],
    "name:rus_x_preferred":[
        "\u0412\u043e\u043b\u043a\u0430\u043d-\u0434\u0435-\u043b\u043e\u0441-\u041f\u0430\u0442\u043e\u0441"
    ],
    "name:spa_x_preferred":[
        "Los Patos"
    ],
    "name:spa_x_variant":[
        "Volc\u00e1n Los Patos"
    ],
    "name:ukr_x_preferred":[
        "\u0412\u043e\u043b\u043a\u0430\u043d-\u0434\u0435-\u043b\u043e\u0441-\u041f\u0430\u0442\u043e\u0441"
    ],
    "name:zho_x_preferred":[
        "\u6d1b\u65af\u5e15\u6258\u65af\u5c71"
    ],
    "wof:name":"Los Patos",
    "wof:placetype":"locality"
},
  "geometry": {"coordinates":[-94.43875,16.29204],"type":"Point"}
}