{
  "type": "Feature",
  "properties": {
    "gn:admin1_code":"13",
    "gn:admin2_code":"28.0",
    "gn:asciiname":"Cacatetitla",
    "gn:country_code":"MX",
    "gn:dem":691,
    "gn:feature_class":"P",
    "gn:feature_code":"PPL",
    "gn:name":"Cacatetitla",
    "gn:population":90,
    "gn:timezone":"America/Mexico_City",
    "iso:country":"MX",
    "wof:name":"Cacatetitla",
    "wof:placetype":"locality",
    "wof:population":90
},
  "geometry": {"coordinates":[-98.52972,21.08806],"type":"Point"}
}