{
  "type": "Feature",
  "properties": {
    "gn:admin1_code":"15",
    "gn:admin2_code":"88.0",
    "gn:asciiname":"Rinconada de Atotonilco",
    "gn:country_code":"MX",
    "gn:dem":2094,
    "gn:feature_class":"P",
    "gn:feature_code":"PPL",
    "gn:name":"Rinconada de Atotonilco",
    "gn:population":869,
    "gn:timezone":"America/Mexico_City",
    "iso:country":"MX",
    "wof:name":"Rinconada de Atotonilco",
    "wof:placetype":"locality",
    "wof:population":869
},
  "geometry": {"coordinates":[-99.5936,18.97649],"type":"Point"}
}