{
  "type": "Feature",
  "properties": {
    "gn:admin1_code":"16",
    "gn:admin2_code":"88.0",
    "gn:asciiname":"El Vallado",
    "gn:country_code":"MX",
    "gn:dem":1844,
    "gn:feature_class":"P",
    "gn:feature_code":"PPL",
    "gn:name":"El Vallado",
    "gn:population":8,
    "gn:timezone":"America/Mexico_City",
    "iso:country":"MX",
    "wof:name":"El Vallado",
    "wof:placetype":"locality",
    "wof:population":8
},
  "geometry": {"coordinates":[-101.11111,19.83167000000001],"type":"Point"}
}