{
  "type": "Feature",
  "properties": {
    "gn:admin1_code":"25",
    "gn:admin2_code":"14.0",
    "gn:asciiname":"Agua Caliente de los Panales",
    "gn:country_code":"MX",
    "gn:dem":101,
    "gn:feature_class":"P",
    "gn:feature_code":"PPL",
    "gn:name":"Agua Caliente de los Panales",
    "gn:population":0,
    "gn:timezone":"America/Mazatlan",
    "iso:country":"MX",
    "name:spa_x_preferred":[
        "Agua Caliente de los Panales"
    ],
    "name:und_x_variant":[
        "Panales",
        "Los Panales"
    ],
    "wof:name":"Agua Caliente de los Panales",
    "wof:placetype":"locality"
},
  "geometry": {"coordinates":[-105.74576,22.99844],"type":"Point"}
}