{
  "type": "Feature",
  "properties": {
    "gn:admin1_code":"21",
    "gn:admin2_code":"19",
    "gn:asciiname":"Santa Elena",
    "gn:country_code":"MX",
    "gn:dem":1831,
    "gn:feature_class":"P",
    "gn:feature_code":"PPL",
    "gn:name":"Santa Elena",
    "gn:population":31,
    "gn:timezone":"America/Mexico_City",
    "iso:country":"MX",
    "wof:name":"Santa Elena",
    "wof:placetype":"locality",
    "wof:population":31
},
  "geometry": {"coordinates":[-98.47553000000001,18.86543],"type":"Point"}
}