{
  "type": "Feature",
  "properties": {
    "gn:admin1_code":"7",
    "gn:admin2_code":"36.0",
    "gn:asciiname":"Melchor Ocampo",
    "gn:country_code":"MX",
    "gn:dem":1157,
    "gn:feature_class":"P",
    "gn:feature_code":"PPL",
    "gn:name":"Melchor Ocampo",
    "gn:population":0,
    "gn:timezone":"America/Monterrey",
    "iso:country":"MX",
    "name:spa_x_preferred":[
        "Melchor Ocampo"
    ],
    "wof:name":"Melchor Ocampo",
    "wof:placetype":"locality"
},
  "geometry": {"coordinates":[-103.324,25.37113],"type":"Point"}
}