{
  "type": "Feature",
  "properties": {
    "gn:admin1_code":"2",
    "gn:admin2_code":"5.0",
    "gn:asciiname":"Don Tomas [Campo]",
    "gn:country_code":"MX",
    "gn:dem":11,
    "gn:feature_class":"P",
    "gn:feature_code":"PPL",
    "gn:name":"Don Tom\u00e1s [Campo]",
    "gn:population":7,
    "gn:timezone":"America/Tijuana",
    "iso:country":"MX",
    "name:und_x_variant":[
        "Don Tom\u00e1s [Campo]"
    ],
    "wof:name":"Don Tomas [Campo]",
    "wof:placetype":"locality",
    "wof:population":7
},
  "geometry": {"coordinates":[-116.98639,32.26028],"type":"Point"}
}