{
  "type": "Feature",
  "properties": {
    "gn:admin1_code":"20",
    "gn:admin2_code":"79.0",
    "gn:asciiname":"Reparo",
    "gn:country_code":"MX",
    "gn:dem":28,
    "gn:feature_class":"P",
    "gn:feature_code":"PPL",
    "gn:name":"Reparo",
    "gn:population":0,
    "gn:timezone":"America/Mexico_City",
    "iso:country":"MX",
    "wof:name":"Reparo",
    "wof:placetype":"locality"
},
  "geometry": {"coordinates":[-95.28333000000001,16.16667],"type":"Point"}
}