{
  "type": "Feature",
  "properties": {
    "gn:admin1_code":"17",
    "gn:admin2_code":"4.0",
    "gn:asciiname":"Rincon de los Sauces",
    "gn:country_code":"MX",
    "gn:dem":1206,
    "gn:feature_class":"P",
    "gn:feature_code":"PPL",
    "gn:name":"Rinc\u00f3n de los Sauces",
    "gn:population":101,
    "gn:timezone":"America/Mexico_City",
    "iso:country":"MX",
    "name:und_x_variant":[
        "Rinc\u00f3n de los Sauces"
    ],
    "wof:name":"Rincon de los Sauces",
    "wof:placetype":"locality",
    "wof:population":101
},
  "geometry": {"coordinates":[-98.95166999999999,18.75333],"type":"Point"}
}