{
  "type": "Feature",
  "properties": {
    "gn:admin1_code":"26.0",
    "gn:admin2_code":"30.0",
    "gn:asciiname":"San Jorge Elma",
    "gn:country_code":"MX",
    "gn:dem":281,
    "gn:feature_class":"P",
    "gn:feature_code":"PPL",
    "gn:name":"San Jorge Elma",
    "gn:population":0,
    "gn:timezone":"America/Hermosillo",
    "iso:country":"MX",
    "name:spa_x_preferred":[
        "San Jorge Elma"
    ],
    "name:und_x_variant":[
        "Granja Elma"
    ],
    "wof:name":"San Jorge Elma",
    "wof:placetype":"locality"
},
  "geometry": {"coordinates":[-110.96249,29.13416],"type":"Point"}
}