{
  "type": "Feature",
  "properties": {
    "gn:admin1_code":"6",
    "gn:admin2_code":"19.0",
    "gn:asciiname":"Palesina",
    "gn:country_code":"MX",
    "gn:dem":1373,
    "gn:feature_class":"P",
    "gn:feature_code":"PPL",
    "gn:name":"Palesina",
    "gn:population":0,
    "gn:timezone":"America/Chihuahua",
    "iso:country":"MX",
    "wof:name":"Palesina",
    "wof:placetype":"locality"
},
  "geometry": {"coordinates":[-106.01667,28.66667],"type":"Point"}
}