{
  "type": "Feature",
  "properties": {
    "gn:admin1_code":"30",
    "gn:admin2_code":"125.0",
    "gn:asciiname":"Los Limos",
    "gn:country_code":"MX",
    "gn:dem":443,
    "gn:feature_class":"P",
    "gn:feature_code":"PPL",
    "gn:name":"Los Limos",
    "gn:population":7,
    "gn:timezone":"America/Mexico_City",
    "iso:country":"MX",
    "wof:name":"Los Limos",
    "wof:placetype":"locality",
    "wof:population":7
},
  "geometry": {"coordinates":[-96.6925,18.96556],"type":"Point"}
}