{
  "type": "Feature",
  "properties": {
    "gn:admin1_code":"25.0",
    "gn:admin2_code":"11.0",
    "gn:asciiname":"Bebelama",
    "gn:country_code":"MX",
    "gn:dem":12,
    "gn:feature_class":"P",
    "gn:feature_code":"PPL",
    "gn:name":"Bebelama",
    "gn:population":0,
    "gn:timezone":"America/Mazatlan",
    "iso:country":"MX",
    "wof:name":"Bebelama",
    "wof:placetype":"locality"
},
  "geometry": {"coordinates":[-108.48333,25.46667],"type":"Point"}
}