{
  "type": "Feature",
  "properties": {
    "gn:admin1_code":"7",
    "gn:admin2_code":"24.0",
    "gn:asciiname":"Andres Guerrero",
    "gn:country_code":"MX",
    "gn:dem":1730,
    "gn:feature_class":"P",
    "gn:feature_code":"PPL",
    "gn:name":"Andres Guerrero",
    "gn:population":0,
    "gn:timezone":"America/Monterrey",
    "iso:country":"MX",
    "name:spa_x_preferred":[
        "Andres Guerrero"
    ],
    "wof:name":"Andres Guerrero",
    "wof:placetype":"locality"
},
  "geometry": {"coordinates":[-101.71684999999999,25.10147000000001],"type":"Point"}
}