{
  "type": "Feature",
  "properties": {
    "gn:admin1_code":"17.0",
    "gn:asciiname":"Llano las Brujas",
    "gn:country_code":"MX",
    "gn:dem":2507,
    "gn:feature_class":"P",
    "gn:feature_code":"PPL",
    "gn:name":"Llano las Brujas",
    "gn:population":0,
    "gn:timezone":"America/Mexico_City",
    "iso:country":"MX",
    "name:spa_x_preferred":[
        "Llano las Brujas"
    ],
    "wof:name":"Llano las Brujas",
    "wof:placetype":"locality"
},
  "geometry": {"coordinates":[-100.09269,19.95885],"type":"Point"}
}