{
  "type": "Feature",
  "properties": {
    "gn:admin1_code":"32",
    "gn:admin2_code":"31",
    "gn:asciiname":"San Pedro de Enmedio",
    "gn:country_code":"MX",
    "gn:dem":2054,
    "gn:feature_class":"P",
    "gn:feature_code":"PPL",
    "gn:name":"San Pedro de Enmedio",
    "gn:population":31,
    "gn:timezone":"America/Mexico_City",
    "iso:country":"MX",
    "wof:name":"San Pedro de Enmedio",
    "wof:placetype":"locality",
    "wof:population":31
},
  "geometry": {"coordinates":[-103.42806,22.55167],"type":"Point"}
}