{
  "type": "Feature",
  "properties": {
    "gn:admin1_code":"28",
    "gn:admin2_code":"21",
    "gn:asciiname":"Eugenio Hernandez",
    "gn:country_code":"MX",
    "gn:dem":103,
    "gn:feature_class":"P",
    "gn:feature_code":"PPL",
    "gn:name":"Eugenio Hern\u00e1ndez",
    "gn:population":22,
    "gn:timezone":"America/Monterrey",
    "iso:country":"MX",
    "name:und_x_variant":[
        "Eugenio Hern\u00e1ndez"
    ],
    "wof:name":"Eugenio Hernandez",
    "wof:placetype":"locality",
    "wof:population":22
},
  "geometry": {"coordinates":[-98.98889,22.67306],"type":"Point"}
}