{
  "type": "Feature",
  "properties": {
    "gn:admin1_code":"7",
    "gn:admin2_code":"18.0",
    "gn:asciiname":"Rancho El Rayo",
    "gn:country_code":"MX",
    "gn:dem":528,
    "gn:feature_class":"P",
    "gn:feature_code":"PPL",
    "gn:name":"Rancho El Rayo",
    "gn:population":0,
    "gn:timezone":"America/Monterrey",
    "iso:country":"MX",
    "wof:name":"Rancho El Rayo",
    "wof:placetype":"locality"
},
  "geometry": {"coordinates":[-101.08333,26.98333],"type":"Point"}
}