{
  "type": "Feature",
  "properties": {
    "gn:admin1_code":"15",
    "gn:admin2_code":"39.0",
    "gn:asciiname":"Ampliacion San Francisco",
    "gn:country_code":"MX",
    "gn:dem":2414,
    "gn:feature_class":"P",
    "gn:feature_code":"PPL",
    "gn:name":"Ampliaci\u00f3n San Francisco",
    "gn:population":102,
    "gn:timezone":"America/Mexico_City",
    "iso:country":"MX",
    "name:und_x_variant":[
        "Ampliaci\u00f3n San Francisco"
    ],
    "wof:name":"Ampliacion San Francisco",
    "wof:placetype":"locality",
    "wof:population":102
},
  "geometry": {"coordinates":[-98.83523,19.35578],"type":"Point"}
}