{
  "type": "Feature",
  "properties": {
    "gn:admin1_code":"14.0",
    "gn:admin2_code":"100.0",
    "gn:asciiname":"Pinuelos",
    "gn:country_code":"MX",
    "gn:dem":143,
    "gn:feature_class":"P",
    "gn:feature_code":"PPL",
    "gn:name":"Pi\u00f1uelos",
    "gn:population":0,
    "gn:timezone":"America/Mexico_City",
    "iso:country":"MX",
    "name:spa_x_preferred":[
        "Pi\u00f1uelos"
    ],
    "wof:name":"Pinuelos",
    "wof:placetype":"locality"
},
  "geometry": {"coordinates":[-105.05063,19.77067000000001],"type":"Point"}
}