{
  "type": "Feature",
  "properties": {
    "gn:admin1_code":"26.0",
    "gn:admin2_code":"41.0",
    "gn:asciiname":"La Viuda",
    "gn:country_code":"MX",
    "gn:dem":1165,
    "gn:feature_class":"P",
    "gn:feature_code":"PPL",
    "gn:name":"La Viuda",
    "gn:population":0,
    "gn:timezone":"America/Hermosillo",
    "iso:country":"MX",
    "name:spa_x_preferred":[
        "La Viuda"
    ],
    "wof:name":"La Viuda",
    "wof:placetype":"locality"
},
  "geometry": {"coordinates":[-109.79289,30.42236],"type":"Point"}
}