{
  "type": "Feature",
  "properties": {
    "gn:admin1_code":"3.0",
    "gn:admin2_code":"1.0",
    "gn:asciiname":"La Palmita",
    "gn:country_code":"MX",
    "gn:dem":153,
    "gn:feature_class":"P",
    "gn:feature_code":"PPL",
    "gn:name":"La Palmita",
    "gn:population":0,
    "gn:timezone":"America/Mazatlan",
    "iso:country":"MX",
    "name:spa_x_preferred":[
        "La Palmita"
    ],
    "name:und_x_variant":[
        "Palmita"
    ],
    "wof:name":"La Palmita",
    "wof:placetype":"locality"
},
  "geometry": {"coordinates":[-111.62094,25.6301],"type":"Point"}
}