{
  "type": "Feature",
  "properties": {
    "gn:admin1_code":"10",
    "gn:admin2_code":"10.0",
    "gn:asciiname":"Tramojos",
    "gn:country_code":"MX",
    "gn:dem":1969,
    "gn:feature_class":"P",
    "gn:feature_code":"PPL",
    "gn:name":"Tramojos",
    "gn:population":0,
    "gn:timezone":"America/Monterrey",
    "iso:country":"MX",
    "name:spa_x_preferred":[
        "Tramojos"
    ],
    "wof:name":"Tramojos",
    "wof:placetype":"locality"
},
  "geometry": {"coordinates":[-105.10706999999999,26.15486],"type":"Point"}
}