{
  "type": "Feature",
  "properties": {
    "gn:admin1_code":"6",
    "gn:admin2_code":"63.0",
    "gn:asciiname":"La Ardilla",
    "gn:country_code":"MX",
    "gn:dem":2020,
    "gn:feature_class":"P",
    "gn:feature_code":"PPL",
    "gn:name":"La Ardilla",
    "gn:population":0,
    "gn:timezone":"America/Chihuahua",
    "iso:country":"MX",
    "wof:name":"La Ardilla",
    "wof:placetype":"locality"
},
  "geometry": {"coordinates":[-108.33333,28.36667000000001],"type":"Point"}
}