{
  "type": "Feature",
  "properties": {
    "gn:admin1_code":"12",
    "gn:admin2_code":"39.0",
    "gn:asciiname":"El Potrero Oriental",
    "gn:country_code":"MX",
    "gn:dem":633,
    "gn:feature_class":"P",
    "gn:feature_code":"PPL",
    "gn:name":"El Potrero Oriental",
    "gn:population":621,
    "gn:timezone":"America/Mexico_City",
    "iso:country":"MX",
    "wof:name":"El Potrero Oriental",
    "wof:placetype":"locality",
    "wof:population":621
},
  "geometry": {"coordinates":[-99.49722,17.16167],"type":"Point"}
}