{
  "type": "Feature",
  "properties": {
    "gn:admin1_code":"28",
    "gn:admin2_code":"24.0",
    "gn:asciiname":"La Guadiana",
    "gn:country_code":"MX",
    "gn:dem":147,
    "gn:feature_class":"P",
    "gn:feature_code":"PPL",
    "gn:name":"La Guadiana",
    "gn:population":0,
    "gn:timezone":"America/Monterrey",
    "iso:country":"MX",
    "name:und_x_variant":[
        "Guadiana",
        "Rancho La Guadiana",
        "La Guadiana"
    ],
    "wof:name":"La Guadiana",
    "wof:placetype":"locality"
},
  "geometry": {"coordinates":[-99.25448,26.26721],"type":"Point"}
}