{
  "type": "Feature",
  "properties": {
    "gn:admin1_code":"21.0",
    "gn:admin2_code":"118.0",
    "gn:asciiname":"Benito Juarez",
    "gn:country_code":"MX",
    "gn:dem":2255,
    "gn:feature_class":"P",
    "gn:feature_code":"PPL",
    "gn:name":"Benito Ju\u00e1rez",
    "gn:population":0,
    "gn:timezone":"America/Mexico_City",
    "iso:country":"MX",
    "name:spa_x_preferred":[
        "Benito Ju\u00e1rez"
    ],
    "wof:name":"Benito Juarez",
    "wof:placetype":"locality"
},
  "geometry": {"coordinates":[-97.85718,19.0091],"type":"Point"}
}