{
  "type": "Feature",
  "properties": {
    "gn:admin1_code":"14",
    "gn:admin2_code":"94",
    "gn:asciiname":"Arroyo Hismoleque (Hismoleque)",
    "gn:country_code":"MX",
    "gn:dem":1628,
    "gn:feature_class":"P",
    "gn:feature_code":"PPL",
    "gn:name":"Arroyo Hismoleque (Hismoleque)",
    "gn:population":26,
    "gn:timezone":"America/Mexico_City",
    "iso:country":"MX",
    "wof:name":"Arroyo Hismoleque (Hismoleque)",
    "wof:placetype":"locality",
    "wof:population":26
},
  "geometry": {"coordinates":[-103.66194,21.17083],"type":"Point"}
}