{
  "type": "Feature",
  "properties": {
    "gn:admin1_code":"16.0",
    "gn:admin2_code":"55.0",
    "gn:asciiname":"Corondiro",
    "gn:country_code":"MX",
    "gn:dem":470,
    "gn:feature_class":"P",
    "gn:feature_code":"PPL",
    "gn:name":"Cor\u00f3ndiro",
    "gn:population":0,
    "gn:timezone":"America/Mexico_City",
    "iso:country":"MX",
    "name:spa_x_preferred":[
        "Cor\u00f3ndiro"
    ],
    "wof:name":"Corondiro",
    "wof:placetype":"locality"
},
  "geometry": {"coordinates":[-102.1247,19.05184],"type":"Point"}
}