{
  "type": "Feature",
  "properties": {
    "gn:admin1_code":"14",
    "gn:admin2_code":"93.0",
    "gn:asciiname":"Cocorrilla [Granja]",
    "gn:country_code":"MX",
    "gn:dem":2044,
    "gn:feature_class":"P",
    "gn:feature_code":"PPL",
    "gn:name":"Cocorrilla [Granja]",
    "gn:population":6,
    "gn:timezone":"America/Mexico_City",
    "iso:country":"MX",
    "wof:name":"Cocorrilla [Granja]",
    "wof:placetype":"locality",
    "wof:population":6
},
  "geometry": {"coordinates":[-102.58611000000001,20.83611],"type":"Point"}
}