{
  "type": "Feature",
  "properties": {
    "gn:admin1_code":"16",
    "gn:admin2_code":"8",
    "gn:asciiname":"La Parotita",
    "gn:country_code":"MX",
    "gn:dem":987,
    "gn:feature_class":"P",
    "gn:feature_code":"PPL",
    "gn:name":"La Parotita",
    "gn:population":49,
    "gn:timezone":"America/Mexico_City",
    "iso:country":"MX",
    "wof:name":"La Parotita",
    "wof:placetype":"locality",
    "wof:population":49
},
  "geometry": {"coordinates":[-103.22917,18.38056],"type":"Point"}
}