{
  "type": "Feature",
  "properties": {
    "gn:admin1_code":"11.0",
    "gn:admin2_code":"14.0",
    "gn:asciiname":"Los Carrizo",
    "gn:country_code":"MX",
    "gn:dem":1963,
    "gn:feature_class":"P",
    "gn:feature_code":"PPL",
    "gn:name":"Los Carrizo",
    "gn:population":0,
    "gn:timezone":"America/Mexico_City",
    "iso:country":"MX",
    "name:spa_x_preferred":[
        "Los Carrizo"
    ],
    "name:spa_x_variant":[
        "Los Carrizos"
    ],
    "wof:name":"Los Carrizo",
    "wof:placetype":"locality"
},
  "geometry": {"coordinates":[-100.98090000000001,21.15261],"type":"Point"}
}