{
  "type": "Feature",
  "properties": {
    "gn:admin1_code":"32",
    "gn:admin2_code":"40.0",
    "gn:asciiname":"El Olivan",
    "gn:country_code":"MX",
    "gn:dem":2064,
    "gn:feature_class":"P",
    "gn:feature_code":"PPL",
    "gn:name":"El Oliv\u00e1n",
    "gn:population":151,
    "gn:timezone":"America/Mexico_City",
    "iso:country":"MX",
    "name:und_x_variant":[
        "El Oliv\u00e1n"
    ],
    "wof:name":"El Olivan",
    "wof:placetype":"locality",
    "wof:population":151
},
  "geometry": {"coordinates":[-103.27943999999999,23.53833],"type":"Point"}
}