{
  "type": "Feature",
  "properties": {
    "gn:admin1_code":"5",
    "gn:admin2_code":"51.0",
    "gn:asciiname":"Barrita de Pajon",
    "gn:country_code":"MX",
    "gn:dem":9,
    "gn:feature_class":"P",
    "gn:feature_code":"PPL",
    "gn:name":"Barrita de Paj\u00f3n",
    "gn:population":375,
    "gn:timezone":"America/Mexico_City",
    "iso:country":"MX",
    "name:und_x_variant":[
        "Barrita de Paj\u00f3n"
    ],
    "wof:name":"Barrita de Pajon",
    "wof:placetype":"locality",
    "wof:population":375
},
  "geometry": {"coordinates":[-93.10278,15.3975],"type":"Point"}
}