{
  "type": "Feature",
  "properties": {
    "gn:admin1_code":"6",
    "gn:admin2_code":"65.0",
    "gn:asciiname":"Uruchutavo",
    "gn:country_code":"MX",
    "gn:dem":2156,
    "gn:feature_class":"P",
    "gn:feature_code":"PPL",
    "gn:name":"Uruch\u00fatavo",
    "gn:population":0,
    "gn:timezone":"America/Chihuahua",
    "iso:country":"MX",
    "name:spa_x_preferred":[
        "Uruch\u00fatavo"
    ],
    "wof:name":"Uruchutavo",
    "wof:placetype":"locality"
},
  "geometry": {"coordinates":[-107.82473,27.2524],"type":"Point"}
}