{
  "type": "Feature",
  "properties": {
    "gn:admin1_code":"11.0",
    "gn:admin2_code":"27.0",
    "gn:asciiname":"Granja San Nicolas",
    "gn:country_code":"MX",
    "gn:dem":1732,
    "gn:feature_class":"P",
    "gn:feature_code":"PPL",
    "gn:name":"Granja San Nicol\u00e1s",
    "gn:population":0,
    "gn:timezone":"America/Mexico_City",
    "iso:country":"MX",
    "name:spa_x_preferred":[
        "Granja San Nicol\u00e1s"
    ],
    "name:spa_x_variant":[
        "San Nicol\u00e1s"
    ],
    "wof:name":"Granja San Nicolas",
    "wof:placetype":"locality"
},
  "geometry": {"coordinates":[-101.21181,20.47399],"type":"Point"}
}