{
  "type": "Feature",
  "properties": {
    "gn:admin1_code":"12",
    "gn:admin2_code":"1",
    "gn:asciiname":"Colonia Nueva de San Rafael",
    "gn:country_code":"MX",
    "gn:dem":10,
    "gn:feature_class":"P",
    "gn:feature_code":"PPL",
    "gn:name":"Colonia Nueva de San Rafael",
    "gn:population":45,
    "gn:timezone":"America/Mexico_City",
    "iso:country":"MX",
    "wof:name":"Colonia Nueva de San Rafael",
    "wof:placetype":"locality",
    "wof:population":45
},
  "geometry": {"coordinates":[-99.61663,16.70833],"type":"Point"}
}