{
  "type": "Feature",
  "properties": {
    "iso:country":"MX",
    "name:spa_x_preferred":[
        "Barrio San Juan"
    ],
    "qs:gn_adm0_cc":"MX",
    "qs:gn_local":3532899,
    "qs:gn_nam_loc":"Amecameca, Amecameca de Ju\u00e1rez, Mexico, MX",
    "qs:gn_namadm1":"15",
    "qs:local_max":302,
    "qs:local_sum":357,
    "qs:localhoods":2,
    "qs:name":"Barrio San Juan",
    "qs:name_adm0":"M\u00e9xico",
    "qs:name_adm1":"Mexico",
    "qs:name_adm2":"Amecameca",
    "qs:name_local":"Amecameca de Ju\u00e1rez",
    "qs:photo_max":34,
    "qs:photo_sum":55,
    "qs:placetype":"Suburb",
    "qs:quad_count":8,
    "qs:woe_adm0":23424900,
    "qs:woe_adm1":2346278,
    "qs:woe_adm2":12600326,
    "qs:woe_lau":0,
    "qs:woe_local":112073,
    "qs:woe_ver":"7.10.0",
    "wof:lang":[
        "spa"
    ],
    "wof:name":"Barrio San Juan",
    "wof:placetype":"neighbourhood"
},
  "geometry": {"coordinates":[-98.774872,19.125798],"type":"Point"}
}