{
  "type": "Feature",
  "properties": {
    "gn:admin1_code":"30",
    "gn:admin2_code":"200.0",
    "gn:asciiname":"El Refugio",
    "gn:country_code":"MX",
    "gn:dem":854,
    "gn:feature_class":"P",
    "gn:feature_code":"PPL",
    "gn:name":"El Refugio",
    "gn:population":151,
    "gn:timezone":"America/Mexico_City",
    "iso:country":"MX",
    "wof:name":"El Refugio",
    "wof:placetype":"locality",
    "wof:population":151
},
  "geometry": {"coordinates":[-96.83556,19.09639],"type":"Point"}
}