{
  "type": "Feature",
  "properties": {
    "gn:admin1_code":"14",
    "gn:admin2_code":"41",
    "gn:asciiname":"El Alamo",
    "gn:country_code":"MX",
    "gn:dem":1785,
    "gn:feature_class":"P",
    "gn:feature_code":"PPL",
    "gn:name":"El \u00c1lamo",
    "gn:population":47,
    "gn:timezone":"America/Mexico_City",
    "iso:country":"MX",
    "name:und_x_variant":[
        "El \u00c1lamo"
    ],
    "wof:name":"El Alamo",
    "wof:placetype":"locality",
    "wof:population":47
},
  "geometry": {"coordinates":[-103.1875,22.2675],"type":"Point"}
}