{
  "type": "Feature",
  "properties": {
    "gn:admin1_code":"6",
    "gn:admin2_code":"62.0",
    "gn:asciiname":"San Jose de Colomo",
    "gn:country_code":"MX",
    "gn:dem":1316,
    "gn:feature_class":"P",
    "gn:feature_code":"PPL",
    "gn:name":"San Jos\u00e9 de Colomo",
    "gn:population":1,
    "gn:timezone":"America/Chihuahua",
    "iso:country":"MX",
    "name:spa_x_preferred":[
        "San Jos\u00e9 de Colomo"
    ],
    "name:und_x_variant":[
        "San Jos\u00e9 del Colomo"
    ],
    "wof:name":"San Jose de Colomo",
    "wof:placetype":"locality",
    "wof:population":1
},
  "geometry": {"coordinates":[-105.10290999999999,28.24685],"type":"Point"}
}