{
  "type": "Feature",
  "properties": {
    "gn:admin1_code":"30",
    "gn:admin2_code":"65.0",
    "gn:asciiname":"Xalapa [Club de Golf]",
    "gn:country_code":"MX",
    "gn:dem":931,
    "gn:feature_class":"P",
    "gn:feature_code":"PPL",
    "gn:name":"Xalapa [Club de Golf]",
    "gn:population":110,
    "gn:timezone":"America/Mexico_City",
    "iso:country":"MX",
    "wof:name":"Xalapa [Club de Golf]",
    "wof:placetype":"locality",
    "wof:population":110
},
  "geometry": {"coordinates":[-96.78389,19.47778],"type":"Point"}
}