{
  "type": "Feature",
  "properties": {
    "gn:admin1_code":"14.0",
    "gn:admin2_code":"62.0",
    "gn:asciiname":"La Laja",
    "gn:country_code":"MX",
    "gn:dem":1428,
    "gn:feature_class":"P",
    "gn:feature_code":"PPL",
    "gn:name":"La Laja",
    "gn:population":0,
    "gn:timezone":"America/Mexico_City",
    "iso:country":"MX",
    "name:spa_x_preferred":[
        "La Laja"
    ],
    "wof:name":"La Laja",
    "wof:placetype":"locality"
},
  "geometry": {"coordinates":[-104.52616999999999,20.58669],"type":"Point"}
}