{
  "type": "Feature",
  "properties": {
    "gn:admin1_code":"30",
    "gn:admin2_code":"101.0",
    "gn:asciiname":"Xiquila",
    "gn:country_code":"MX",
    "gn:dem":2166,
    "gn:feature_class":"P",
    "gn:feature_code":"PPL",
    "gn:name":"Xiquila",
    "gn:population":640,
    "gn:timezone":"America/Mexico_City",
    "iso:country":"MX",
    "wof:name":"Xiquila",
    "wof:placetype":"locality",
    "wof:population":640
},
  "geometry": {"coordinates":[-97.19472,18.95472],"type":"Point"}
}