{
  "type": "Feature",
  "properties": {
    "gn:admin1_code":"26",
    "gn:admin2_code":"29.0",
    "gn:asciiname":"Colonia la Peninsula",
    "gn:country_code":"MX",
    "gn:dem":6,
    "gn:feature_class":"P",
    "gn:feature_code":"PPL",
    "gn:name":"Colonia la Pen\u00ednsula",
    "gn:population":0,
    "gn:timezone":"America/Hermosillo",
    "iso:country":"MX",
    "name:spa_x_preferred":[
        "Colonia la Pen\u00ednsula"
    ],
    "wof:name":"Colonia la Peninsula",
    "wof:placetype":"locality"
},
  "geometry": {"coordinates":[-110.89946999999999,27.89572],"type":"Point"}
}