{
  "type": "Feature",
  "properties": {
    "gn:admin1_code":"32",
    "gn:admin2_code":"20.0",
    "gn:asciiname":"San Antonio Perienio",
    "gn:country_code":"MX",
    "gn:dem":2303,
    "gn:feature_class":"P",
    "gn:feature_code":"PPL",
    "gn:name":"San Antonio Perienio",
    "gn:population":0,
    "gn:timezone":"America/Mexico_City",
    "iso:country":"MX",
    "name:spa_x_preferred":[
        "San Antonio Perienio"
    ],
    "wof:name":"San Antonio Perienio",
    "wof:placetype":"locality"
},
  "geometry": {"coordinates":[-103.10136,22.82776],"type":"Point"}
}