{
  "type": "Feature",
  "properties": {
    "gn:admin1_code":"28",
    "gn:admin2_code":"5.0",
    "gn:asciiname":"Palos Blancos",
    "gn:country_code":"MX",
    "gn:dem":377,
    "gn:feature_class":"P",
    "gn:feature_code":"PPL",
    "gn:name":"Palos Blancos",
    "gn:population":0,
    "gn:timezone":"America/Monterrey",
    "iso:country":"MX",
    "name:und_x_variant":[
        "Palo Blanco"
    ],
    "wof:name":"Palos Blancos",
    "wof:placetype":"locality"
},
  "geometry": {"coordinates":[-98.94571000000001,24.83592],"type":"Point"}
}