{
  "type": "Feature",
  "properties": {
    "gn:admin1_code":"17",
    "gn:admin2_code":"29.0",
    "gn:asciiname":"El Nixcomil",
    "gn:country_code":"MX",
    "gn:dem":1235,
    "gn:feature_class":"P",
    "gn:feature_code":"PPL",
    "gn:name":"El Nixcomil",
    "gn:population":7,
    "gn:timezone":"America/Mexico_City",
    "iso:country":"MX",
    "wof:name":"El Nixcomil",
    "wof:placetype":"locality",
    "wof:population":7
},
  "geometry": {"coordinates":[-99.03917,18.91167],"type":"Point"}
}