{
  "type": "Feature",
  "properties": {
    "gn:admin1_code":"30",
    "gn:admin2_code":"15.0",
    "gn:asciiname":"La Soledad",
    "gn:country_code":"MX",
    "gn:dem":18,
    "gn:feature_class":"P",
    "gn:feature_code":"PPL",
    "gn:name":"La Soledad",
    "gn:population":8,
    "gn:timezone":"America/Mexico_City",
    "iso:country":"MX",
    "wof:name":"La Soledad",
    "wof:placetype":"locality",
    "wof:population":8
},
  "geometry": {"coordinates":[-95.37582999999999,18.66306],"type":"Point"}
}