{
  "type": "Feature",
  "properties": {
    "gn:admin1_code":"32",
    "gn:admin2_code":"10.0",
    "gn:asciiname":"Tepetatillo",
    "gn:country_code":"MX",
    "gn:dem":2121,
    "gn:feature_class":"P",
    "gn:feature_code":"PPL",
    "gn:name":"Tepetatillo",
    "gn:population":65,
    "gn:timezone":"America/Mexico_City",
    "iso:country":"MX",
    "wof:name":"Tepetatillo",
    "wof:placetype":"locality",
    "wof:population":65
},
  "geometry": {"coordinates":[-102.77556,23.09722],"type":"Point"}
}