{
  "type": "Feature",
  "properties": {
    "gn:admin1_code":"2",
    "gn:admin2_code":"1.0",
    "gn:asciiname":"El Marron",
    "gn:country_code":"MX",
    "gn:dem":10,
    "gn:feature_class":"P",
    "gn:feature_code":"PPL",
    "gn:name":"El Marr\u00f3n",
    "gn:population":0,
    "gn:timezone":"America/Tijuana",
    "iso:country":"MX",
    "name:spa_x_preferred":[
        "El Marr\u00f3n"
    ],
    "wof:name":"El Marron",
    "wof:placetype":"locality"
},
  "geometry": {"coordinates":[-114.3794,28.8142],"type":"Point"}
}