{
  "type": "Feature",
  "properties": {
    "gn:admin1_code":"18",
    "gn:admin2_code":"4",
    "gn:asciiname":"Palos Maria",
    "gn:country_code":"MX",
    "gn:dem":69,
    "gn:feature_class":"P",
    "gn:feature_code":"PPL",
    "gn:name":"Palos Mar\u00eda",
    "gn:population":14,
    "gn:timezone":"America/Mazatlan",
    "iso:country":"MX",
    "name:und_x_variant":[
        "Palos Mar\u00eda"
    ],
    "wof:name":"Palos Maria",
    "wof:placetype":"locality",
    "wof:population":14
},
  "geometry": {"coordinates":[-105.08667,21.25194],"type":"Point"}
}