{
  "type": "Feature",
  "properties": {
    "gn:admin1_code":"29",
    "gn:admin2_code":"34.0",
    "gn:asciiname":"El Convento",
    "gn:country_code":"MX",
    "gn:dem":2776,
    "gn:feature_class":"P",
    "gn:feature_code":"PPL",
    "gn:name":"El Convento",
    "gn:population":0,
    "gn:timezone":"America/Mexico_City",
    "iso:country":"MX",
    "name:spa_x_preferred":[
        "El Convento"
    ],
    "wof:name":"El Convento",
    "wof:placetype":"locality"
},
  "geometry": {"coordinates":[-98.06297000000001,19.61454],"type":"Point"}
}