{
  "type": "Feature",
  "properties": {
    "gn:admin1_code":"32",
    "gn:admin2_code":"39.0",
    "gn:asciiname":"Las Piedras",
    "gn:cc2":"MX",
    "gn:country_code":"MX",
    "gn:dem":2081,
    "gn:feature_class":"P",
    "gn:feature_code":"PPL",
    "gn:name":"Las Piedras",
    "gn:population":0,
    "gn:timezone":"America/Mexico_City",
    "iso:country":"MX",
    "name:und_x_variant":[
        "Piedras Negras",
        "Las Piedras"
    ],
    "wof:name":"Las Piedras",
    "wof:placetype":"locality"
},
  "geometry": {"coordinates":[-103.03333000000001,23.73333],"type":"Point"}
}