{
  "type": "Feature",
  "properties": {
    "gn:admin1_code":"28",
    "gn:admin2_code":"17.0",
    "gn:asciiname":"San Jose de Salamanca",
    "gn:country_code":"MX",
    "gn:dem":621,
    "gn:feature_class":"P",
    "gn:feature_code":"PPL",
    "gn:name":"San Jose de Salamanca",
    "gn:population":0,
    "gn:timezone":"America/Monterrey",
    "iso:country":"MX",
    "name:spa_x_preferred":[
        "San Jose de Salamanca"
    ],
    "name:und_x_variant":[
        "Salamanca",
        "San Jos\u00e9 de Salamanca"
    ],
    "wof:name":"San Jose de Salamanca",
    "wof:placetype":"locality"
},
  "geometry": {"coordinates":[-99.30233,23.46411],"type":"Point"}
}