{
  "type": "Feature",
  "properties": {
    "gn:admin1_code":"19",
    "gn:admin2_code":"42.0",
    "gn:asciiname":"Los Chaparros",
    "gn:country_code":"MX",
    "gn:dem":243,
    "gn:feature_class":"P",
    "gn:feature_code":"PPL",
    "gn:name":"Los Chaparros",
    "gn:population":9,
    "gn:timezone":"America/Monterrey",
    "iso:country":"MX",
    "wof:name":"Los Chaparros",
    "wof:placetype":"locality",
    "wof:population":9
},
  "geometry": {"coordinates":[-99.72221999999999,25.48352],"type":"Point"}
}