{
  "type": "Feature",
  "properties": {
    "gn:admin1_code":"5.0",
    "gn:asciiname":"San Juan Bautista",
    "gn:country_code":"MX",
    "gn:dem":19,
    "gn:feature_class":"P",
    "gn:feature_code":"PPL",
    "gn:name":"San Juan Bautista",
    "gn:population":0,
    "gn:timezone":"America/Mexico_City",
    "iso:country":"MX",
    "name:cat_x_preferred":[
        "San Juan Bautista"
    ],
    "name:ceb_x_preferred":[
        "San Juan Bautista"
    ],
    "name:deu_x_preferred":[
        "San Juan Bautista"
    ],
    "name:fas_x_preferred":[
        "\u0633\u0627\u0646 \u062e\u0648\u0622\u0646 \u0628\u0627\u062a\u06cc\u0633\u062a\u0627"
    ],
    "name:fra_x_preferred":[
        "San Juan Bautista"
    ],
    "name:ita_x_preferred":[
        "San Juan Bautista"
    ],
    "name:kat_x_preferred":[
        "\u10e1\u10d0\u10dc-\u10ee\u10e3\u10d0\u10dc-\u10d1\u10d0\u10e3\u10e2\u10d8\u10e1\u10e2\u10d0"
    ],
    "name:kor_x_preferred":[
        "\uc0b0\ud6c4\uc548\ubc14\uc6b0\ud2f0\uc2a4\ud0c0"
    ],
    "name:lit_x_preferred":[
        "San Chuan Bautista"
    ],
    "name:nld_x_preferred":[
        "San Juan Bautista"
    ],
    "name:pol_x_preferred":[
        "San Juan Bautista"
    ],
    "name:por_x_preferred":[
        "San Juan Bautista"
    ],
    "name:sco_x_preferred":[
        "San Juan Bautista"
    ],
    "name:spa_x_preferred":[
        "San Juan Bautista"
    ],
    "name:swe_x_preferred":[
        "San Juan Bautista"
    ],
    "name:war_x_preferred":[
        "San Juan Bautista"
    ],
    "wof:name":"San Juan Bautista",
    "wof:placetype":"locality"
},
  "geometry": {"coordinates":[-92.41076,14.79223],"type":"Point"}
}