{
  "type": "Feature",
  "properties": {
    "gn:admin1_code":"5.0",
    "gn:asciiname":"San Juan Bautista",
    "gn:country_code":"MX",
    "gn:dem":19,
    "gn:feature_class":"P",
    "gn:feature_code":"PPL",
    "gn:name":"San Juan Bautista",
    "gn:population":0,
    "gn:timezone":"America/Mexico_City",
    "iso:country":"MX",
    "name:spa_x_preferred":[
        "San Juan Bautista"
    ],
    "wof:name":"San Juan Bautista",
    "wof:placetype":"locality"
},
  "geometry": {"coordinates":[-92.41076,14.79223],"type":"Point"}
}