{
  "type": "Feature",
  "properties": {
    "gn:admin1_code":"28.0",
    "gn:admin2_code":"21.0",
    "gn:asciiname":"Los Rosales",
    "gn:country_code":"MX",
    "gn:dem":109,
    "gn:feature_class":"P",
    "gn:feature_code":"PPL",
    "gn:name":"Los Rosales",
    "gn:population":0,
    "gn:timezone":"America/Monterrey",
    "iso:country":"MX",
    "name:ceb_x_preferred":[
        "Los Rosales"
    ],
    "name:spa_x_preferred":[
        "Los Rosales"
    ],
    "name:srp_x_preferred":[
        "\u041b\u043e\u0441 \u0420\u043e\u0441\u0430\u043b\u0435\u0441"
    ],
    "name:swe_x_preferred":[
        "Los Rosales"
    ],
    "wof:name":"Los Rosales",
    "wof:placetype":"locality"
},
  "geometry": {"coordinates":[-98.99778000000001,22.62167],"type":"Point"}
}