{
  "type": "Feature",
  "properties": {
    "gn:admin1_code":"20",
    "gn:admin2_code":"309.0",
    "gn:asciiname":"Loma Coyol San Martin",
    "gn:country_code":"MX",
    "gn:dem":99,
    "gn:feature_class":"P",
    "gn:feature_code":"PPL",
    "gn:name":"Loma Coyol San Mart\u00edn",
    "gn:population":418,
    "gn:timezone":"America/Mexico_City",
    "iso:country":"MX",
    "name:und_x_variant":[
        "Loma Coyol San Mart\u00edn"
    ],
    "wof:name":"Loma Coyol San Martin",
    "wof:placetype":"locality",
    "wof:population":418
},
  "geometry": {"coordinates":[-96.48611,18.12722],"type":"Point"}
}