{
  "type": "Feature",
  "properties": {
    "gn:admin1_code":"30",
    "gn:admin2_code":"15.0",
    "gn:asciiname":"La Poza del Rifle",
    "gn:country_code":"MX",
    "gn:dem":17,
    "gn:feature_class":"P",
    "gn:feature_code":"PPL",
    "gn:name":"La Poza del Rifle",
    "gn:population":6,
    "gn:timezone":"America/Mexico_City",
    "iso:country":"MX",
    "wof:name":"La Poza del Rifle",
    "wof:placetype":"locality",
    "wof:population":6
},
  "geometry": {"coordinates":[-95.33499999999999,18.69917],"type":"Point"}
}