{
  "type": "Feature",
  "properties": {
    "gn:admin1_code":"26",
    "gn:admin2_code":"35.0",
    "gn:asciiname":"La Polinaria",
    "gn:country_code":"MX",
    "gn:dem":867,
    "gn:feature_class":"P",
    "gn:feature_code":"PPL",
    "gn:name":"La Polinaria",
    "gn:population":0,
    "gn:timezone":"America/Hermosillo",
    "iso:country":"MX",
    "name:spa_x_preferred":[
        "La Polinaria"
    ],
    "wof:name":"La Polinaria",
    "wof:placetype":"locality"
},
  "geometry": {"coordinates":[-110.88703999999998,30.81806],"type":"Point"}
}