{
  "type": "Feature",
  "properties": {
    "gn:admin1_code":"25",
    "gn:admin2_code":"6.0",
    "gn:asciiname":"El Comedero",
    "gn:country_code":"MX",
    "gn:dem":180,
    "gn:feature_class":"P",
    "gn:feature_code":"PPL",
    "gn:name":"El Comedero",
    "gn:population":0,
    "gn:timezone":"America/Mazatlan",
    "iso:country":"MX",
    "name:spa_x_preferred":[
        "El Comedero"
    ],
    "wof:name":"El Comedero",
    "wof:placetype":"locality"
},
  "geometry": {"coordinates":[-107.15161000000001,24.94754],"type":"Point"}
}