{
  "type": "Feature",
  "properties": {
    "gn:admin1_code":"24",
    "gn:admin2_code":"24.0",
    "gn:asciiname":"Cruz de Marin",
    "gn:country_code":"MX",
    "gn:dem":1182,
    "gn:feature_class":"P",
    "gn:feature_code":"PPL",
    "gn:name":"Cruz de Mar\u00edn",
    "gn:population":31,
    "gn:timezone":"America/Mexico_City",
    "iso:country":"MX",
    "wof:name":"Cruz de Marin",
    "wof:placetype":"locality",
    "wof:population":31
},
  "geometry": {"coordinates":[-99.98361,21.67556],"type":"Point"}
}