{
  "type": "Feature",
  "properties": {
    "gn:admin1_code":"10",
    "gn:admin2_code":"14",
    "gn:asciiname":"El Quitapeiste",
    "gn:country_code":"MX",
    "gn:dem":1288,
    "gn:feature_class":"P",
    "gn:feature_code":"PPL",
    "gn:name":"El Quitapeiste",
    "gn:population":17,
    "gn:timezone":"America/Mazatlan",
    "iso:country":"MX",
    "wof:name":"El Quitapeiste",
    "wof:placetype":"locality",
    "wof:population":17
},
  "geometry": {"coordinates":[-104.90457000000001,22.85645],"type":"Point"}
}