{
  "type": "Feature",
  "properties": {
    "gn:admin1_code":"19",
    "gn:admin2_code":"38.0",
    "gn:asciiname":"Santa Julia (El Refugio)",
    "gn:country_code":"MX",
    "gn:dem":449,
    "gn:feature_class":"P",
    "gn:feature_code":"PPL",
    "gn:name":"Santa Julia (El Refugio)",
    "gn:population":6,
    "gn:timezone":"America/Monterrey",
    "iso:country":"MX",
    "wof:name":"Santa Julia (El Refugio)",
    "wof:placetype":"locality",
    "wof:population":6
},
  "geometry": {"coordinates":[-99.745,25.07368],"type":"Point"}
}