{
  "type": "Feature",
  "properties": {
    "gn:admin1_code":"16",
    "gn:admin2_code":"92",
    "gn:asciiname":"El Algodon",
    "gn:country_code":"MX",
    "gn:dem":1217,
    "gn:feature_class":"P",
    "gn:feature_code":"PPL",
    "gn:name":"El Algod\u00f3n",
    "gn:population":34,
    "gn:timezone":"America/Mexico_City",
    "iso:country":"MX",
    "name:und_x_variant":[
        "El Algod\u00f3n"
    ],
    "wof:name":"El Algodon",
    "wof:placetype":"locality",
    "wof:population":34
},
  "geometry": {"coordinates":[-101.00833,19.20944],"type":"Point"}
}