{
  "type": "Feature",
  "properties": {
    "gn:admin1_code":"24",
    "gn:admin2_code":"37.0",
    "gn:asciiname":"Tlamaya Santiago",
    "gn:country_code":"MX",
    "gn:dem":613,
    "gn:feature_class":"P",
    "gn:feature_code":"PPL",
    "gn:name":"Tlamaya Santiago",
    "gn:population":0,
    "gn:timezone":"America/Mexico_City",
    "iso:country":"MX",
    "name:spa_x_preferred":[
        "Tlamaya Santiago"
    ],
    "name:spa_x_variant":[
        "Tlamaya"
    ],
    "wof:name":"Tlamaya Santiago",
    "wof:placetype":"locality"
},
  "geometry": {"coordinates":[-98.87466999999999,21.19449],"type":"Point"}
}