{
  "type": "Feature",
  "properties": {
    "gn:admin1_code":"20",
    "gn:admin2_code":"414.0",
    "gn:asciiname":"Yutanicani",
    "gn:country_code":"MX",
    "gn:dem":37,
    "gn:feature_class":"P",
    "gn:feature_code":"PPL",
    "gn:name":"Yutanicani",
    "gn:population":0,
    "gn:timezone":"America/Mexico_City",
    "iso:country":"MX",
    "name:spa_x_preferred":[
        "Yutanicani"
    ],
    "wof:name":"Yutanicani",
    "wof:placetype":"locality"
},
  "geometry": {"coordinates":[-97.98457000000001,16.27082],"type":"Point"}
}