{
  "type": "Feature",
  "properties": {
    "gn:admin1_code":"12",
    "gn:admin2_code":"41.0",
    "gn:asciiname":"El Potrerillo (Potrerillo del Rincon)",
    "gn:country_code":"MX",
    "gn:dem":691,
    "gn:feature_class":"P",
    "gn:feature_code":"PPL",
    "gn:name":"El Potrerillo (Potrerillo del Rinc\u00f3n)",
    "gn:population":1460,
    "gn:timezone":"America/Mexico_City",
    "iso:country":"MX",
    "name:und_x_variant":[
        "El Potrerillo (Potrerillo del Rinc\u00f3n)"
    ],
    "wof:name":"El Potrerillo (Potrerillo del Rincon)",
    "wof:placetype":"locality",
    "wof:population":1460
},
  "geometry": {"coordinates":[-98.73083,16.95806],"type":"Point"}
}