{
  "type": "Feature",
  "properties": {
    "gn:admin1_code":"7.0",
    "gn:admin2_code":"24.0",
    "gn:asciiname":"Jazminal",
    "gn:country_code":"MX",
    "gn:dem":1608,
    "gn:feature_class":"P",
    "gn:feature_code":"PPL",
    "gn:name":"Jazminal",
    "gn:population":0,
    "gn:timezone":"America/Monterrey",
    "iso:country":"MX",
    "wof:name":"Jazminal",
    "wof:placetype":"locality"
},
  "geometry": {"coordinates":[-101.82311,25.37172],"type":"Point"}
}