{
  "type": "Feature",
  "properties": {
    "gn:admin1_code":"10",
    "gn:admin2_code":"26.0",
    "gn:asciiname":"Chiqueritos",
    "gn:country_code":"MX",
    "gn:dem":2420,
    "gn:feature_class":"P",
    "gn:feature_code":"PPL",
    "gn:name":"Chiqueritos",
    "gn:population":0,
    "gn:timezone":"America/Monterrey",
    "iso:country":"MX",
    "name:spa_x_preferred":[
        "Chiqueritos"
    ],
    "wof:name":"Chiqueritos",
    "wof:placetype":"locality"
},
  "geometry": {"coordinates":[-105.76566,24.4509],"type":"Point"}
}