{
  "type": "Feature",
  "properties": {
    "gn:admin1_code":"15.0",
    "gn:asciiname":"El Cenicillo",
    "gn:country_code":"MX",
    "gn:dem":1564,
    "gn:feature_class":"P",
    "gn:feature_code":"PPL",
    "gn:name":"El Cenicillo",
    "gn:population":0,
    "gn:timezone":"America/Mexico_City",
    "iso:country":"MX",
    "name:spa_x_preferred":[
        "El Cenicillo"
    ],
    "wof:name":"El Cenicillo",
    "wof:placetype":"locality"
},
  "geometry": {"coordinates":[-102.32091,19.98565],"type":"Point"}
}