{
  "type": "Feature",
  "properties": {
    "gn:admin1_code":"16.0",
    "gn:asciiname":"Santa Maria del Rio",
    "gn:country_code":"MX",
    "gn:dem":1729,
    "gn:feature_class":"P",
    "gn:feature_code":"PPL",
    "gn:name":"Santa Mar\u00eda del R\u00edo",
    "gn:population":0,
    "gn:timezone":"America/Mexico_City",
    "iso:country":"MX",
    "name:spa_x_preferred":[
        "Santa Mar\u00eda del R\u00edo"
    ],
    "wof:name":"Santa Maria del Rio",
    "wof:placetype":"locality"
},
  "geometry": {"coordinates":[-101.81056,20.12751],"type":"Point"}
}