{
  "type": "Feature",
  "properties": {
    "gn:admin1_code":"24",
    "gn:admin2_code":"24.0",
    "gn:asciiname":"Tanque de San Juan",
    "gn:country_code":"MX",
    "gn:dem":1289,
    "gn:feature_class":"P",
    "gn:feature_code":"PPL",
    "gn:name":"Tanque de San Juan",
    "gn:population":0,
    "gn:timezone":"America/Mexico_City",
    "iso:country":"MX",
    "name:und_x_variant":[
        "Tanque"
    ],
    "wof:name":"Tanque de San Juan",
    "wof:placetype":"locality"
},
  "geometry": {"coordinates":[-100.35181,21.9906],"type":"Point"}
}