{
  "type": "Feature",
  "properties": {
    "gn:admin1_code":"14",
    "gn:admin2_code":"35.0",
    "gn:asciiname":"Las Piedras",
    "gn:country_code":"MX",
    "gn:dem":1872,
    "gn:feature_class":"P",
    "gn:feature_code":"PPL",
    "gn:name":"Las Piedras",
    "gn:population":7,
    "gn:timezone":"America/Mexico_City",
    "iso:country":"MX",
    "wof:name":"Las Piedras",
    "wof:placetype":"locality",
    "wof:population":7
},
  "geometry": {"coordinates":[-102.29667000000001,21.615],"type":"Point"}
}