{
  "type": "Feature",
  "properties": {
    "gn:admin1_code":"19",
    "gn:admin2_code":"9.0",
    "gn:asciiname":"La Prietita",
    "gn:country_code":"MX",
    "gn:dem":374,
    "gn:feature_class":"P",
    "gn:feature_code":"PPL",
    "gn:name":"La Prietita",
    "gn:population":9,
    "gn:timezone":"America/Monterrey",
    "iso:country":"MX",
    "wof:name":"La Prietita",
    "wof:placetype":"locality",
    "wof:population":9
},
  "geometry": {"coordinates":[-100.04806000000001,25.59806],"type":"Point"}
}