{
  "type": "Feature",
  "properties": {
    "gn:admin1_code":"7",
    "gn:admin2_code":"4.0",
    "gn:asciiname":"Tierras Prietas",
    "gn:country_code":"MX",
    "gn:dem":2048,
    "gn:feature_class":"P",
    "gn:feature_code":"PPL",
    "gn:name":"Tierras Prietas",
    "gn:population":72,
    "gn:timezone":"America/Monterrey",
    "iso:country":"MX",
    "name:spa_x_preferred":[
        "Tierras Prietas"
    ],
    "wof:name":"Tierras Prietas",
    "wof:placetype":"locality",
    "wof:population":72
},
  "geometry": {"coordinates":[-100.68447,25.30977],"type":"Point"}
}