{
  "type": "Feature",
  "properties": {
    "gn:admin1_code":"14.0",
    "gn:admin2_code":"120.0",
    "gn:asciiname":"Atemajac del valle",
    "gn:country_code":"MX",
    "gn:dem":1521,
    "gn:feature_class":"P",
    "gn:feature_code":"PPLL",
    "gn:name":"Atemajac del valle",
    "gn:population":0,
    "gn:timezone":"America/Mexico_City",
    "iso:country":"MX",
    "wof:name":"Atemajac del valle",
    "wof:placetype":"locality"
},
  "geometry": {"coordinates":[-103.35432,20.71965],"type":"Point"}
}