{
  "type": "Feature",
  "properties": {
    "gn:admin1_code":"16",
    "gn:admin2_code":"75.0",
    "gn:asciiname":"La Higuerita (Colonia San Rafael)",
    "gn:country_code":"MX",
    "gn:dem":1293,
    "gn:feature_class":"P",
    "gn:feature_code":"PPL",
    "gn:name":"La Higuerita (Colonia San Rafael)",
    "gn:population":1366,
    "gn:timezone":"America/Mexico_City",
    "iso:country":"MX",
    "wof:name":"La Higuerita (Colonia San Rafael)",
    "wof:placetype":"locality",
    "wof:population":1366
},
  "geometry": {"coordinates":[-102.48444000000001,19.61861],"type":"Point"}
}