{
  "type": "Feature",
  "properties": {
    "gn:admin1_code":"24.0",
    "gn:admin2_code":"22.0",
    "gn:asciiname":"Garabatillo",
    "gn:country_code":"MX",
    "gn:dem":1767,
    "gn:feature_class":"P",
    "gn:feature_code":"PPL",
    "gn:name":"Garabatillo",
    "gn:population":0,
    "gn:timezone":"America/Mexico_City",
    "iso:country":"MX",
    "wof:name":"Garabatillo",
    "wof:placetype":"locality"
},
  "geometry": {"coordinates":[-101.08759000000001,22.79112000000001],"type":"Point"}
}