{
  "type": "Feature",
  "properties": {
    "gn:admin1_code":"22",
    "gn:admin2_code":"6.0",
    "gn:asciiname":"Vista Real y Country Club",
    "gn:country_code":"MX",
    "gn:dem":2038,
    "gn:feature_class":"P",
    "gn:feature_code":"PPL",
    "gn:name":"Vista Real y Country Club",
    "gn:population":767,
    "gn:timezone":"America/Mexico_City",
    "iso:country":"MX",
    "wof:name":"Vista Real y Country Club",
    "wof:placetype":"locality",
    "wof:population":767
},
  "geometry": {"coordinates":[-100.4025,20.52222],"type":"Point"}
}