{
  "type": "Feature",
  "properties": {
    "gn:admin1_code":"20",
    "gn:admin2_code":"58.0",
    "gn:asciiname":"Loma Cozahuico",
    "gn:country_code":"MX",
    "gn:dem":1240,
    "gn:feature_class":"P",
    "gn:feature_code":"PPL",
    "gn:name":"Loma Cozahuico",
    "gn:population":139,
    "gn:timezone":"America/Mexico_City",
    "iso:country":"MX",
    "wof:name":"Loma Cozahuico",
    "wof:placetype":"locality",
    "wof:population":139
},
  "geometry": {"coordinates":[-96.87278000000001,18.02972],"type":"Point"}
}