{
  "type": "Feature",
  "properties": {
    "gn:admin1_code":"2.0",
    "gn:admin2_code":"5.0",
    "gn:asciiname":"La Ponderosa",
    "gn:country_code":"MX",
    "gn:dem":100,
    "gn:feature_class":"P",
    "gn:feature_code":"PPL",
    "gn:name":"La Ponderosa",
    "gn:population":7,
    "gn:timezone":"America/Tijuana",
    "iso:country":"MX",
    "name:spa_x_preferred":[
        "La Ponderosa"
    ],
    "wof:name":"La Ponderosa",
    "wof:placetype":"locality",
    "wof:population":7
},
  "geometry": {"coordinates":[-117.01194,32.36806],"type":"Point"}
}