{
  "type": "Feature",
  "properties": {
    "gn:admin1_code":"6",
    "gn:admin2_code":"67.0",
    "gn:asciiname":"Rinconada",
    "gn:country_code":"MX",
    "gn:dem":1323,
    "gn:feature_class":"P",
    "gn:feature_code":"PPL",
    "gn:name":"Rinconada",
    "gn:population":0,
    "gn:timezone":"America/Chihuahua",
    "iso:country":"MX",
    "wof:name":"Rinconada",
    "wof:placetype":"locality"
},
  "geometry": {"coordinates":[-105.78333000000001,27.53333],"type":"Point"}
}