{
  "type": "Feature",
  "properties": {
    "gn:admin1_code":"6",
    "gn:admin2_code":"67.0",
    "gn:asciiname":"Rinconada",
    "gn:country_code":"MX",
    "gn:dem":1323,
    "gn:feature_class":"P",
    "gn:feature_code":"PPL",
    "gn:name":"Rinconada",
    "gn:population":0,
    "gn:timezone":"America/Chihuahua",
    "iso:country":"MX",
    "name:eus_x_preferred":[
        "Rinconada"
    ],
    "name:fra_x_preferred":[
        "Rinconada"
    ],
    "name:ita_x_preferred":[
        "Rinconada"
    ],
    "name:kor_x_preferred":[
        "\ub9c1\ucf54\ub098\ub2e4"
    ],
    "name:nld_x_preferred":[
        "Rinconada"
    ],
    "name:por_x_preferred":[
        "Rinconada"
    ],
    "name:ron_x_preferred":[
        "Rinconada"
    ],
    "name:rus_x_preferred":[
        "\u0420\u0438\u043d\u043a\u043e\u043d\u0430\u0434\u0430"
    ],
    "name:spa_x_preferred":[
        "Rinconada"
    ],
    "name:zho_x_preferred":[
        "\u6797\u79d1\u7d0d\u9054"
    ],
    "wof:name":"Rinconada",
    "wof:placetype":"locality"
},
  "geometry": {"coordinates":[-105.78333000000001,27.53333],"type":"Point"}
}