{
  "type": "Feature",
  "properties": {
    "gn:admin1_code":"6",
    "gn:admin2_code":"11.0",
    "gn:asciiname":"San Juan",
    "gn:country_code":"MX",
    "gn:dem":1477,
    "gn:feature_class":"P",
    "gn:feature_code":"PPL",
    "gn:name":"San Juan",
    "gn:population":4,
    "gn:timezone":"America/Chihuahua",
    "iso:country":"MX",
    "wof:name":"San Juan",
    "wof:placetype":"locality",
    "wof:population":4
},
  "geometry": {"coordinates":[-104.31545,28.20300000000001],"type":"Point"}
}