{
  "type": "Feature",
  "properties": {
    "gn:admin1_code":"28",
    "gn:admin2_code":"3",
    "gn:asciiname":"El Consuelo (San Mateo)",
    "gn:country_code":"MX",
    "gn:dem":27,
    "gn:feature_class":"P",
    "gn:feature_code":"PPL",
    "gn:name":"El Consuelo (San Mateo)",
    "gn:population":17,
    "gn:timezone":"America/Monterrey",
    "iso:country":"MX",
    "wof:name":"El Consuelo (San Mateo)",
    "wof:placetype":"locality",
    "wof:population":17
},
  "geometry": {"coordinates":[-98.05972,22.46472],"type":"Point"}
}