{
  "type": "Feature",
  "properties": {
    "gn:admin1_code":"23",
    "gn:asciiname":"Celarain",
    "gn:country_code":"MX",
    "gn:dem":-9999,
    "gn:feature_class":"P",
    "gn:feature_code":"PPL",
    "gn:name":"Celarain",
    "gn:population":0,
    "gn:timezone":"America/Cancun",
    "iso:country":"MX",
    "wof:name":"Celarain",
    "wof:placetype":"locality"
},
  "geometry": {"coordinates":[-86.96666999999999,20.28333],"type":"Point"}
}