{
  "type": "Feature",
  "properties": {
    "gn:admin1_code":"30.0",
    "gn:admin2_code":"161.0",
    "gn:asciiname":"Paso de los Toros",
    "gn:country_code":"MX",
    "gn:dem":38,
    "gn:feature_class":"P",
    "gn:feature_code":"PPL",
    "gn:name":"Paso de los Toros",
    "gn:population":0,
    "gn:timezone":"America/Mexico_City",
    "iso:country":"MX",
    "name:fas_x_preferred":[
        "\u067e\u0627\u0633\u0648 \u062f \u0644\u0648\u0633\u200c\u062a\u0631\u0648\u0633"
    ],
    "name:heb_x_preferred":[
        "\u05e4\u05e1\u05d5 \u05d3\u05d4 \u05dc\u05d5\u05e1 \u05d8\u05d5\u05e8\u05d5\u05e1"
    ],
    "name:hun_x_preferred":[
        "Paso de los Toros"
    ],
    "name:hye_x_preferred":[
        "\u054a\u0561\u057d\u0578 \u0564\u0565 \u056c\u0578\u057d \u054f\u0578\u0580\u0578\u057d"
    ],
    "name:spa_x_preferred":[
        "Paso de los Toros"
    ],
    "name:urd_x_preferred":[
        "\u067e\u0627\u0633\u0648 \u062f\u06d2 \u0644\u0648\u0633 \u062a\u0648\u0631\u0648\u0633"
    ],
    "wof:name":"Paso de los Toros",
    "wof:placetype":"locality"
},
  "geometry": {"coordinates":[-98.40022999999999,21.51314],"type":"Point"}
}