{
  "type": "Feature",
  "properties": {
    "gn:admin1_code":"30.0",
    "gn:admin2_code":"161.0",
    "gn:asciiname":"Paso de los Toros",
    "gn:country_code":"MX",
    "gn:dem":38,
    "gn:feature_class":"P",
    "gn:feature_code":"PPL",
    "gn:name":"Paso de los Toros",
    "gn:population":0,
    "gn:timezone":"America/Mexico_City",
    "iso:country":"MX",
    "name:spa_x_preferred":[
        "Paso de los Toros"
    ],
    "wof:name":"Paso de los Toros",
    "wof:placetype":"locality"
},
  "geometry": {"coordinates":[-98.40022999999999,21.51314],"type":"Point"}
}