{
  "type": "Feature",
  "properties": {
    "gn:admin1_code":"32",
    "gn:admin2_code":"40.0",
    "gn:asciiname":"El Lindero",
    "gn:country_code":"MX",
    "gn:dem":2139,
    "gn:feature_class":"P",
    "gn:feature_code":"PPL",
    "gn:name":"El Lindero",
    "gn:population":51,
    "gn:timezone":"America/Mexico_City",
    "iso:country":"MX",
    "name:spa_x_preferred":[
        "El Lindero"
    ],
    "wof:name":"El Lindero",
    "wof:placetype":"locality",
    "wof:population":51
},
  "geometry": {"coordinates":[-103.37376,23.57641],"type":"Point"}
}