{
  "type": "Feature",
  "properties": {
    "gn:admin1_code":"7",
    "gn:admin2_code":"15.0",
    "gn:asciiname":"Cerro del Barril",
    "gn:country_code":"MX",
    "gn:dem":298,
    "gn:feature_class":"P",
    "gn:feature_code":"PPL",
    "gn:name":"Cerro del Barril",
    "gn:population":0,
    "gn:timezone":"America/Monterrey",
    "iso:country":"MX",
    "name:spa_x_preferred":[
        "Cerro del Barril"
    ],
    "name:und_x_variant":[
        "La Casita"
    ],
    "wof:name":"Cerro del Barril",
    "wof:placetype":"locality"
},
  "geometry": {"coordinates":[-100.8798,27.65506],"type":"Point"}
}