{
  "type": "Feature",
  "properties": {
    "gn:admin1_code":"6",
    "gn:admin2_code":"52.0",
    "gn:asciiname":"Tabaloapa",
    "gn:country_code":"MX",
    "gn:dem":798,
    "gn:feature_class":"P",
    "gn:feature_code":"PPL",
    "gn:name":"Tabaloapa",
    "gn:population":0,
    "gn:timezone":"America/Ojinaga",
    "iso:country":"MX",
    "wof:name":"Tabaloapa",
    "wof:placetype":"locality"
},
  "geometry": {"coordinates":[-104.35999,29.51818],"type":"Point"}
}