{
  "type": "Feature",
  "properties": {
    "gn:admin1_code":"26",
    "gn:admin2_code":"25.0",
    "gn:asciiname":"Ninguno [Diego Bojorquez Quezada]",
    "gn:country_code":"MX",
    "gn:dem":14,
    "gn:feature_class":"P",
    "gn:feature_code":"PPL",
    "gn:name":"Ninguno [Diego Boj\u00f3rquez Quezada]",
    "gn:population":6,
    "gn:timezone":"America/Hermosillo",
    "iso:country":"MX",
    "name:und_x_variant":[
        "Ninguno [Diego Boj\u00f3rquez Quezada]"
    ],
    "wof:name":"Ninguno [Diego Bojorquez Quezada]",
    "wof:placetype":"locality",
    "wof:population":6
},
  "geometry": {"coordinates":[-110.57319,27.921],"type":"Point"}
}