{
  "type": "Feature",
  "properties": {
    "gn:admin1_code":"32",
    "gn:admin2_code":"5.0",
    "gn:asciiname":"San Felipe (Hector Garcia)",
    "gn:country_code":"MX",
    "gn:dem":2187,
    "gn:feature_class":"P",
    "gn:feature_code":"PPL",
    "gn:name":"San Felipe (H\u00e9ctor Garc\u00eda)",
    "gn:population":5,
    "gn:timezone":"America/Mexico_City",
    "iso:country":"MX",
    "name:und_x_variant":[
        "San Felipe (H\u00e9ctor Garc\u00eda)"
    ],
    "wof:name":"San Felipe (Hector Garcia)",
    "wof:placetype":"locality",
    "wof:population":5
},
  "geometry": {"coordinates":[-102.6275,22.95],"type":"Point"}
}