{
  "type": "Feature",
  "properties": {
    "gn:admin1_code":"14",
    "gn:admin2_code":"91.0",
    "gn:asciiname":"El Barrio",
    "gn:country_code":"MX",
    "gn:dem":1704,
    "gn:feature_class":"P",
    "gn:feature_code":"PPL",
    "gn:name":"El Barrio",
    "gn:population":251,
    "gn:timezone":"America/Mexico_City",
    "iso:country":"MX",
    "name:ceb_x_preferred":[
        "El Barrio"
    ],
    "name:spa_x_preferred":[
        "El Barrio"
    ],
    "name:swe_x_preferred":[
        "El Barrio"
    ],
    "wof:name":"El Barrio",
    "wof:placetype":"locality",
    "wof:population":251
},
  "geometry": {"coordinates":[-102.55444,21.40056],"type":"Point"}
}