{
  "type": "Feature",
  "properties": {
    "gn:admin1_code":"24",
    "gn:admin2_code":"44.0",
    "gn:asciiname":"San Felipe I",
    "gn:country_code":"MX",
    "gn:dem":1730,
    "gn:feature_class":"P",
    "gn:feature_code":"PPL",
    "gn:name":"San Felipe I",
    "gn:population":6,
    "gn:timezone":"America/Mexico_City",
    "iso:country":"MX",
    "wof:name":"San Felipe I",
    "wof:placetype":"locality",
    "wof:population":6
},
  "geometry": {"coordinates":[-100.92361,23.94222],"type":"Point"}
}