{
  "type": "Feature",
  "properties": {
    "gn:admin1_code":"7",
    "gn:admin2_code":"30.0",
    "gn:asciiname":"El Chanate",
    "gn:country_code":"MX",
    "gn:dem":1993,
    "gn:feature_class":"P",
    "gn:feature_code":"PPL",
    "gn:name":"El Chanate",
    "gn:population":6,
    "gn:timezone":"America/Monterrey",
    "iso:country":"MX",
    "name:spa_x_preferred":[
        "El Chanate"
    ],
    "name:und_x_variant":[
        "Rancho Colonia Chanate"
    ],
    "wof:name":"El Chanate",
    "wof:placetype":"locality",
    "wof:population":6
},
  "geometry": {"coordinates":[-101.11185,25.02496],"type":"Point"}
}