{
  "type": "Feature",
  "properties": {
    "gn:admin1_code":"11.0",
    "gn:asciiname":"Las Carretas",
    "gn:country_code":"MX",
    "gn:dem":1757,
    "gn:feature_class":"P",
    "gn:feature_code":"PPL",
    "gn:name":"Las Carretas",
    "gn:population":0,
    "gn:timezone":"America/Mexico_City",
    "iso:country":"MX",
    "name:spa_x_preferred":[
        "Las Carretas"
    ],
    "name:spa_x_variant":[
        "La Carreta"
    ],
    "wof:name":"Las Carretas",
    "wof:placetype":"locality"
},
  "geometry": {"coordinates":[-101.92953,20.49245],"type":"Point"}
}