{
  "type": "Feature",
  "properties": {
    "gn:admin1_code":"27",
    "gn:admin2_code":"9.0",
    "gn:asciiname":"Chipilinar Segunda Seccion",
    "gn:country_code":"MX",
    "gn:dem":16,
    "gn:feature_class":"P",
    "gn:feature_code":"PPL",
    "gn:name":"Chipilinar Segunda Secci\u00f3n",
    "gn:population":0,
    "gn:timezone":"America/Mexico_City",
    "iso:country":"MX",
    "name:spa_x_preferred":[
        "Chipiljuar"
    ],
    "name:spa_x_variant":[
        "Chipilinar Segunda Secci\u00f3n",
        "Chipilinal Segunda Secci\u00f3n"
    ],
    "wof:name":"Chipilinar Segunda Seccion",
    "wof:placetype":"locality"
},
  "geometry": {"coordinates":[-92.7955,17.78847],"type":"Point"}
}