{
  "type": "Feature",
  "properties": {
    "gn:admin1_code":"19.0",
    "gn:admin2_code":"37.0",
    "gn:asciiname":"El Venado",
    "gn:country_code":"MX",
    "gn:dem":621,
    "gn:feature_class":"P",
    "gn:feature_code":"PPL",
    "gn:name":"El Venado",
    "gn:population":0,
    "gn:timezone":"America/Monterrey",
    "iso:country":"MX",
    "name:spa_x_preferred":[
        "El Venado"
    ],
    "name:und_x_variant":[
        "Rancho El Venado"
    ],
    "wof:name":"El Venado",
    "wof:placetype":"locality"
},
  "geometry": {"coordinates":[-100.53137,26.22311],"type":"Point"}
}