{
  "type": "Feature",
  "properties": {
    "gn:admin1_code":"6",
    "gn:admin2_code":"28.0",
    "gn:asciiname":"Rancho Beltran",
    "gn:country_code":"MX",
    "gn:dem":1068,
    "gn:feature_class":"P",
    "gn:feature_code":"PPL",
    "gn:name":"Rancho Beltr\u00e1n",
    "gn:population":4,
    "gn:timezone":"America/Chihuahua",
    "iso:country":"MX",
    "name:und_x_variant":[
        "Rancho Beltr\u00e1n"
    ],
    "wof:name":"Rancho Beltran",
    "wof:placetype":"locality",
    "wof:population":4
},
  "geometry": {"coordinates":[-105.77912999999999,31.16263],"type":"Point"}
}