{
  "type": "Feature",
  "properties": {
    "gn:admin1_code":"6",
    "gn:admin2_code":"19.0",
    "gn:asciiname":"Colonia Cuauhtemoc",
    "gn:country_code":"MX",
    "gn:dem":1682,
    "gn:feature_class":"P",
    "gn:feature_code":"PPL",
    "gn:name":"Colonia Cuauht\u00e9moc",
    "gn:population":0,
    "gn:timezone":"America/Chihuahua",
    "iso:country":"MX",
    "name:spa_x_preferred":[
        "Colonia Cuauht\u00e9moc"
    ],
    "name:spa_x_variant":[
        "Punta de Agua"
    ],
    "wof:name":"Colonia Cuauhtemoc",
    "wof:placetype":"locality"
},
  "geometry": {"coordinates":[-106.35232000000001,28.91538],"type":"Point"}
}