{
  "type": "Feature",
  "properties": {
    "gn:admin1_code":"21",
    "gn:admin2_code":"194.0",
    "gn:asciiname":"Gasolinera",
    "gn:country_code":"MX",
    "gn:dem":325,
    "gn:feature_class":"P",
    "gn:feature_code":"PPL",
    "gn:name":"Gasolinera",
    "gn:population":9,
    "gn:timezone":"America/Mexico_City",
    "iso:country":"MX",
    "wof:name":"Gasolinera",
    "wof:placetype":"locality",
    "wof:population":9
},
  "geometry": {"coordinates":[-97.68473,20.47306],"type":"Point"}
}