{
  "type": "Feature",
  "properties": {
    "gn:admin1_code":"19",
    "gn:admin2_code":"9.0",
    "gn:asciiname":"Hacienda de Vargas",
    "gn:country_code":"MX",
    "gn:dem":355,
    "gn:feature_class":"P",
    "gn:feature_code":"PPL",
    "gn:name":"Hacienda de Vargas",
    "gn:population":0,
    "gn:timezone":"America/Monterrey",
    "iso:country":"MX",
    "name:spa_x_preferred":[
        "Hacienda de Vargas"
    ],
    "wof:name":"Hacienda de Vargas",
    "wof:placetype":"locality"
},
  "geometry": {"coordinates":[-100.04724,25.49784],"type":"Point"}
}