{
  "type": "Feature",
  "properties": {
    "gn:admin1_code":"21",
    "gn:admin2_code":"45.0",
    "gn:asciiname":"El Huerto",
    "gn:country_code":"MX",
    "gn:dem":3345,
    "gn:feature_class":"P",
    "gn:feature_code":"PPL",
    "gn:name":"El Huerto",
    "gn:population":0,
    "gn:timezone":"America/Mexico_City",
    "iso:country":"MX",
    "name:spa_x_preferred":[
        "El Huerto"
    ],
    "wof:name":"El Huerto",
    "wof:placetype":"locality"
},
  "geometry": {"coordinates":[-97.3436,19.01254],"type":"Point"}
}