{
  "type": "Feature",
  "properties": {
    "gn:admin1_code":"30",
    "gn:admin2_code":"126",
    "gn:asciiname":"El Portugues",
    "gn:country_code":"MX",
    "gn:dem":14,
    "gn:feature_class":"P",
    "gn:feature_code":"PPL",
    "gn:name":"El Portugu\u00e9s",
    "gn:population":18,
    "gn:timezone":"America/Mexico_City",
    "iso:country":"MX",
    "name:und_x_variant":[
        "El Portugu\u00e9s"
    ],
    "wof:name":"El Portugues",
    "wof:placetype":"locality",
    "wof:population":18
},
  "geometry": {"coordinates":[-96.36,19.25583],"type":"Point"}
}