{
  "type": "Feature",
  "properties": {
    "gn:admin1_code":"19.0",
    "gn:admin2_code":"35.0",
    "gn:asciiname":"Mezquites Altos Dos",
    "gn:country_code":"MX",
    "gn:dem":171,
    "gn:feature_class":"P",
    "gn:feature_code":"PPL",
    "gn:name":"Mezquites Altos Dos",
    "gn:population":0,
    "gn:timezone":"America/Monterrey",
    "iso:country":"MX",
    "name:spa_x_preferred":[
        "Mezquites Altos Dos"
    ],
    "wof:name":"Mezquites Altos Dos",
    "wof:placetype":"locality"
},
  "geometry": {"coordinates":[-99.45746,26.03879],"type":"Point"}
}