{
  "type": "Feature",
  "properties": {
    "gn:admin1_code":"12",
    "gn:admin2_code":"57.0",
    "gn:asciiname":"Colonia Sorpresa",
    "gn:country_code":"MX",
    "gn:dem":23,
    "gn:feature_class":"P",
    "gn:feature_code":"PPL",
    "gn:name":"Colonia Sorpresa",
    "gn:population":59,
    "gn:timezone":"America/Mexico_City",
    "iso:country":"MX",
    "wof:name":"Colonia Sorpresa",
    "wof:placetype":"locality",
    "wof:population":59
},
  "geometry": {"coordinates":[-100.66638,17.20523],"type":"Point"}
}