{
  "type": "Feature",
  "properties": {
    "gn:admin1_code":"6",
    "gn:admin2_code":"9",
    "gn:asciiname":"Bacabochi",
    "gn:country_code":"MX",
    "gn:dem":2373,
    "gn:feature_class":"P",
    "gn:feature_code":"PPL",
    "gn:name":"Bacabochi",
    "gn:population":33,
    "gn:timezone":"America/Chihuahua",
    "iso:country":"MX",
    "wof:name":"Bacabochi",
    "wof:placetype":"locality",
    "wof:population":33
},
  "geometry": {"coordinates":[-107.65770000000001,27.69825],"type":"Point"}
}