{
  "type": "Feature",
  "properties": {
    "gn:admin1_code":"26.0",
    "gn:admin2_code":"4.0",
    "gn:asciiname":"El Dos",
    "gn:country_code":"MX",
    "gn:dem":715,
    "gn:feature_class":"P",
    "gn:feature_code":"PPL",
    "gn:name":"El Dos",
    "gn:population":0,
    "gn:timezone":"America/Hermosillo",
    "iso:country":"MX",
    "wof:name":"El Dos",
    "wof:placetype":"locality"
},
  "geometry": {"coordinates":[-111.97417,31.21472],"type":"Point"}
}