{
  "type": "Feature",
  "properties": {
    "gn:admin1_code":"10",
    "gn:admin2_code":"14.0",
    "gn:asciiname":"Bancos",
    "gn:country_code":"MX",
    "gn:dem":1494,
    "gn:feature_class":"P",
    "gn:feature_code":"PPL",
    "gn:name":"Bancos",
    "gn:population":4,
    "gn:timezone":"America/Monterrey",
    "iso:country":"MX",
    "wof:name":"Bancos",
    "wof:placetype":"locality",
    "wof:population":4
},
  "geometry": {"coordinates":[-104.38884,22.74893],"type":"Point"}
}