{
  "type": "Feature",
  "properties": {
    "gn:admin1_code":"14.0",
    "gn:admin2_code":"68.0",
    "gn:asciiname":"Los Cerrillos",
    "gn:country_code":"MX",
    "gn:dem":318,
    "gn:feature_class":"P",
    "gn:feature_code":"PPL",
    "gn:name":"Los Cerrillos",
    "gn:population":0,
    "gn:timezone":"America/Mexico_City",
    "iso:country":"MX",
    "name:ceb_x_preferred":[
        "Los Cerrillos"
    ],
    "name:spa_x_preferred":[
        "Los Cerrillos"
    ],
    "name:swe_x_preferred":[
        "Los Cerrillos"
    ],
    "wof:name":"Los Cerrillos",
    "wof:placetype":"locality"
},
  "geometry": {"coordinates":[-104.76148999999999,19.66689],"type":"Point"}
}