{
  "type": "Feature",
  "properties": {
    "gn:admin1_code":"15",
    "gn:admin2_code":"123",
    "gn:asciiname":"Los Tequereques",
    "gn:country_code":"MX",
    "gn:dem":937,
    "gn:feature_class":"P",
    "gn:feature_code":"PPL",
    "gn:name":"Los Tequereques",
    "gn:population":13,
    "gn:timezone":"America/Mexico_City",
    "iso:country":"MX",
    "wof:name":"Los Tequereques",
    "wof:placetype":"locality",
    "wof:population":13
},
  "geometry": {"coordinates":[-100.51309999999999,18.8735],"type":"Point"}
}