{
  "type": "Feature",
  "properties": {
    "gn:admin1_code":"19",
    "gn:admin2_code":"48.0",
    "gn:asciiname":"Horcones",
    "gn:country_code":"MX",
    "gn:dem":716,
    "gn:feature_class":"P",
    "gn:feature_code":"PPL",
    "gn:name":"Horcones",
    "gn:population":0,
    "gn:timezone":"America/Monterrey",
    "iso:country":"MX",
    "name:spa_x_preferred":[
        "Horcones"
    ],
    "name:und_x_variant":[
        "Hacienda de los Orcones"
    ],
    "wof:name":"Horcones",
    "wof:placetype":"locality"
},
  "geometry": {"coordinates":[-100.45987,25.63641],"type":"Point"}
}