{
  "type": "Feature",
  "properties": {
    "gn:admin1_code":"6",
    "gn:admin2_code":"27",
    "gn:asciiname":"Remochochi",
    "gn:country_code":"MX",
    "gn:dem":2347,
    "gn:feature_class":"P",
    "gn:feature_code":"PPL",
    "gn:name":"Remochochi",
    "gn:population":11,
    "gn:timezone":"America/Chihuahua",
    "iso:country":"MX",
    "wof:name":"Remochochi",
    "wof:placetype":"locality",
    "wof:population":11
},
  "geometry": {"coordinates":[-107.31158000000001,27.54187],"type":"Point"}
}