{
  "type": "Feature",
  "properties": {
    "gn:admin1_code":"15",
    "gn:admin2_code":"86.0",
    "gn:asciiname":"San Andres de los Gama",
    "gn:country_code":"MX",
    "gn:dem":2090,
    "gn:feature_class":"P",
    "gn:feature_code":"PPL",
    "gn:name":"San Andr\u00e9s de los Gama",
    "gn:population":0,
    "gn:timezone":"America/Mexico_City",
    "iso:country":"MX",
    "name:spa_x_preferred":[
        "San Andr\u00e9s de los Gama"
    ],
    "wof:name":"San Andres de los Gama",
    "wof:placetype":"locality"
},
  "geometry": {"coordinates":[-99.97403,19.03766],"type":"Point"}
}