{
  "type": "Feature",
  "properties": {
    "gn:admin1_code":"2.0",
    "gn:admin2_code":"1.0",
    "gn:asciiname":"Rancho Loza",
    "gn:country_code":"MX",
    "gn:dem":359,
    "gn:feature_class":"P",
    "gn:feature_code":"PPL",
    "gn:name":"Rancho Loza",
    "gn:population":7,
    "gn:timezone":"America/Tijuana",
    "iso:country":"MX",
    "name:spa_x_preferred":[
        "Loza"
    ],
    "wof:name":"Rancho Loza",
    "wof:placetype":"locality",
    "wof:population":7
},
  "geometry": {"coordinates":[-116.59694,32.05306],"type":"Point"}
}