{
  "type": "Feature",
  "properties": {
    "gn:admin1_code":"10.0",
    "gn:admin2_code":"17.0",
    "gn:asciiname":"Paraje El Chorro de Arriba",
    "gn:country_code":"MX",
    "gn:dem":2628,
    "gn:feature_class":"P",
    "gn:feature_code":"PPL",
    "gn:name":"Paraje El Chorro de Arriba",
    "gn:population":0,
    "gn:timezone":"America/Monterrey",
    "iso:country":"MX",
    "name:und_x_variant":[
        "Rancho El Chorro de Arriba",
        "Paraje El Chorro de Arriba"
    ],
    "wof:name":"Paraje El Chorro de Arriba",
    "wof:placetype":"locality"
},
  "geometry": {"coordinates":[-106.0261,26.43798],"type":"Point"}
}