{
  "type": "Feature",
  "properties": {
    "gn:admin1_code":"30.0",
    "gn:admin2_code":"121.0",
    "gn:asciiname":"Rancho Nuevo Veracruz",
    "gn:country_code":"MX",
    "gn:dem":52,
    "gn:feature_class":"P",
    "gn:feature_code":"PPL",
    "gn:name":"Rancho Nuevo Veracruz",
    "gn:population":6,
    "gn:timezone":"America/Mexico_City",
    "iso:country":"MX",
    "name:spa_x_preferred":[
        "Rancho Nuevo Veracruz"
    ],
    "wof:name":"Rancho Nuevo Veracruz",
    "wof:placetype":"locality",
    "wof:population":6
},
  "geometry": {"coordinates":[-98.01222,21.68167],"type":"Point"}
}