{
  "type": "Feature",
  "properties": {
    "gn:admin1_code":"31",
    "gn:admin2_code":"22.0",
    "gn:asciiname":"Chakan",
    "gn:country_code":"MX",
    "gn:dem":28,
    "gn:feature_class":"P",
    "gn:feature_code":"PPL",
    "gn:name":"Chak\u00e1n",
    "gn:population":0,
    "gn:timezone":"America/Merida",
    "iso:country":"MX",
    "name:ceb_x_preferred":[
        "Chakan"
    ],
    "name:hun_x_preferred":[
        "Chakan"
    ],
    "name:spa_x_preferred":[
        "Chak\u00e1n"
    ],
    "name:spa_x_variant":[
        "Chan Kan"
    ],
    "name:swe_x_preferred":[
        "Chakan"
    ],
    "wof:name":"Chakan",
    "wof:placetype":"locality"
},
  "geometry": {"coordinates":[-88.52294999999999,20.2455],"type":"Point"}
}