{
  "type": "Feature",
  "properties": {
    "gn:admin1_code":"23",
    "gn:admin2_code":"2.0",
    "gn:asciiname":"Chich-Muc",
    "gn:country_code":"MX",
    "gn:dem":21,
    "gn:feature_class":"P",
    "gn:feature_code":"PPL",
    "gn:name":"Chich-Muc",
    "gn:population":0,
    "gn:timezone":"America/Cancun",
    "iso:country":"MX",
    "name:spa_x_preferred":[
        "Chich-Muc"
    ],
    "name:und_x_variant":[
        "Chimuc"
    ],
    "wof:name":"Chich-Muc",
    "wof:placetype":"locality"
},
  "geometry": {"coordinates":[-88.43141,19.40148],"type":"Point"}
}