{
  "type": "Feature",
  "properties": {
    "gn:admin1_code":"24",
    "gn:admin2_code":"39.0",
    "gn:asciiname":"La Pimionta",
    "gn:country_code":"MX",
    "gn:dem":233,
    "gn:feature_class":"P",
    "gn:feature_code":"PPL",
    "gn:name":"La Pimionta",
    "gn:population":0,
    "gn:timezone":"America/Mexico_City",
    "iso:country":"MX",
    "name:spa_x_preferred":[
        "La Pimionta"
    ],
    "wof:name":"La Pimionta",
    "wof:placetype":"locality"
},
  "geometry": {"coordinates":[-98.81701,21.59363],"type":"Point"}
}