{
  "type": "Feature",
  "properties": {
    "gn:admin1_code":"19.0",
    "gn:admin2_code":"44.0",
    "gn:asciiname":"El Durazno",
    "gn:country_code":"MX",
    "gn:dem":317,
    "gn:feature_class":"P",
    "gn:feature_code":"PPL",
    "gn:name":"El Durazno",
    "gn:population":0,
    "gn:timezone":"America/Monterrey",
    "iso:country":"MX",
    "name:ceb_x_preferred":[
        "El Durazno"
    ],
    "name:spa_x_preferred":[
        "El Durazno"
    ],
    "name:swe_x_preferred":[
        "El Durazno"
    ],
    "wof:name":"El Durazno",
    "wof:placetype":"locality"
},
  "geometry": {"coordinates":[-100.15876,26.44821],"type":"Point"}
}