{
  "type": "Feature",
  "properties": {
    "gn:admin1_code":"32",
    "gn:admin2_code":"51.0",
    "gn:asciiname":"Mezquitillo",
    "gn:country_code":"MX",
    "gn:dem":1965,
    "gn:feature_class":"P",
    "gn:feature_code":"PPL",
    "gn:name":"Mezquitillo",
    "gn:population":0,
    "gn:timezone":"America/Mexico_City",
    "iso:country":"MX",
    "name:und_x_variant":[
        "Mexquitillo",
        "Mezquitillo"
    ],
    "wof:name":"Mezquitillo",
    "wof:placetype":"locality"
},
  "geometry": {"coordinates":[-102.50237,23.60467],"type":"Point"}
}