{
  "type": "Feature",
  "properties": {
    "gn:admin1_code":"21",
    "gn:admin2_code":"108.0",
    "gn:asciiname":"Rancho Martinez Parra",
    "gn:country_code":"MX",
    "gn:dem":2352,
    "gn:feature_class":"P",
    "gn:feature_code":"PPL",
    "gn:name":"Rancho Mart\u00ednez Parra",
    "gn:population":5,
    "gn:timezone":"America/Mexico_City",
    "iso:country":"MX",
    "name:und_x_variant":[
        "Rancho Mart\u00ednez Parra"
    ],
    "wof:name":"Rancho Martinez Parra",
    "wof:placetype":"locality",
    "wof:population":5
},
  "geometry": {"coordinates":[-97.61028,19.36472],"type":"Point"}
}