{
  "type": "Feature",
  "properties": {
    "gn:admin1_code":"6.0",
    "gn:admin2_code":"7.0",
    "gn:asciiname":"La Cuevita",
    "gn:country_code":"MX",
    "gn:dem":2247,
    "gn:feature_class":"P",
    "gn:feature_code":"PPL",
    "gn:name":"La Cuevita",
    "gn:population":0,
    "gn:timezone":"America/Chihuahua",
    "iso:country":"MX",
    "name:spa_x_preferred":[
        "La Cuevita"
    ],
    "wof:name":"La Cuevita",
    "wof:placetype":"locality"
},
  "geometry": {"coordinates":[-106.71501000000001,26.94896],"type":"Point"}
}