{
  "type": "Feature",
  "properties": {
    "gn:admin1_code":"26.0",
    "gn:admin2_code":"20.0",
    "gn:asciiname":"El Quemado",
    "gn:country_code":"MX",
    "gn:dem":596,
    "gn:feature_class":"P",
    "gn:feature_code":"PPL",
    "gn:name":"El Quemado",
    "gn:population":0,
    "gn:timezone":"America/Hermosillo",
    "iso:country":"MX",
    "name:spa_x_preferred":[
        "El Quemado"
    ],
    "wof:name":"El Quemado",
    "wof:placetype":"locality"
},
  "geometry": {"coordinates":[-110.78307,29.74101],"type":"Point"}
}