{
  "type": "Feature",
  "properties": {
    "gn:admin1_code":"11",
    "gn:admin2_code":"29",
    "gn:asciiname":"Rancho de Cuatro Palmas",
    "gn:country_code":"MX",
    "gn:dem":2046,
    "gn:feature_class":"P",
    "gn:feature_code":"PPL",
    "gn:name":"Rancho de Cuatro Palmas",
    "gn:population":21,
    "gn:timezone":"America/Mexico_City",
    "iso:country":"MX",
    "wof:name":"Rancho de Cuatro Palmas",
    "wof:placetype":"locality",
    "wof:population":21
},
  "geometry": {"coordinates":[-100.83278,21.44972000000001],"type":"Point"}
}