{
  "type": "Feature",
  "properties": {
    "gn:admin1_code":"24",
    "gn:admin2_code":"17",
    "gn:asciiname":"El Tulillo",
    "gn:country_code":"MX",
    "gn:dem":1510,
    "gn:feature_class":"P",
    "gn:feature_code":"PPL",
    "gn:name":"El Tulillo",
    "gn:population":13,
    "gn:timezone":"America/Monterrey",
    "iso:country":"MX",
    "wof:name":"El Tulillo",
    "wof:placetype":"locality",
    "wof:population":13
},
  "geometry": {"coordinates":[-100.26917,23.25389],"type":"Point"}
}