{
  "type": "Feature",
  "properties": {
    "gn:admin1_code":"30",
    "gn:admin2_code":"53.0",
    "gn:asciiname":"La Curva",
    "gn:country_code":"MX",
    "gn:dem":340,
    "gn:feature_class":"P",
    "gn:feature_code":"PPL",
    "gn:name":"La Curva",
    "gn:population":9,
    "gn:timezone":"America/Mexico_City",
    "iso:country":"MX",
    "wof:name":"La Curva",
    "wof:placetype":"locality",
    "wof:population":9
},
  "geometry": {"coordinates":[-96.70471999999999,18.79583],"type":"Point"}
}