{
  "type": "Feature",
  "properties": {
    "gn:admin1_code":"26.0",
    "gn:admin2_code":"52.0",
    "gn:asciiname":"Los Ciegos",
    "gn:country_code":"MX",
    "gn:dem":1533,
    "gn:feature_class":"P",
    "gn:feature_code":"PPL",
    "gn:name":"Los Ciegos",
    "gn:population":0,
    "gn:timezone":"America/Hermosillo",
    "iso:country":"MX",
    "name:spa_x_preferred":[
        "Los Ciegos"
    ],
    "wof:name":"Los Ciegos",
    "wof:placetype":"locality"
},
  "geometry": {"coordinates":[-108.80097000000001,28.64298],"type":"Point"}
}