{
  "type": "Feature",
  "properties": {
    "gn:admin1_code":"11",
    "gn:admin2_code":"15",
    "gn:asciiname":"Tajo de Adjuntas (Rancho de San Cayetano)",
    "gn:country_code":"MX",
    "gn:dem":2059,
    "gn:feature_class":"P",
    "gn:feature_code":"PPL",
    "gn:name":"Tajo de Adjuntas (Rancho de San Cayetano)",
    "gn:population":31,
    "gn:timezone":"America/Mexico_City",
    "iso:country":"MX",
    "wof:name":"Tajo de Adjuntas (Rancho de San Cayetano)",
    "wof:placetype":"locality",
    "wof:population":31
},
  "geometry": {"coordinates":[-101.29806000000001,21.02389],"type":"Point"}
}