{
  "type": "Feature",
  "properties": {
    "gn:admin1_code":"12",
    "gn:admin2_code":"49.0",
    "gn:asciiname":"Bordo Mora",
    "gn:country_code":"MX",
    "gn:dem":1626,
    "gn:feature_class":"P",
    "gn:feature_code":"PPL",
    "gn:name":"Bordo Mora",
    "gn:population":129,
    "gn:timezone":"America/Mexico_City",
    "iso:country":"MX",
    "wof:name":"Bordo Mora",
    "wof:placetype":"locality",
    "wof:population":129
},
  "geometry": {"coordinates":[-99.69698,18.70559],"type":"Point"}
}