{
  "type": "Feature",
  "properties": {
    "gn:admin1_code":"20",
    "gn:admin2_code":"437.0",
    "gn:asciiname":"Flores",
    "gn:country_code":"MX",
    "gn:dem":1666,
    "gn:feature_class":"P",
    "gn:feature_code":"PPL",
    "gn:name":"Flores",
    "gn:population":339,
    "gn:timezone":"America/Mexico_City",
    "iso:country":"MX",
    "wof:name":"Flores",
    "wof:placetype":"locality",
    "wof:population":339
},
  "geometry": {"coordinates":[-96.11083000000001,17.10361],"type":"Point"}
}