{
  "type": "Feature",
  "properties": {
    "gn:admin1_code":"15.0",
    "gn:admin2_code":"124.0",
    "gn:asciiname":"Rosa Concepcion",
    "gn:country_code":"MX",
    "gn:dem":2937,
    "gn:feature_class":"P",
    "gn:feature_code":"PPL",
    "gn:name":"Rosa Concepci\u00f3n",
    "gn:population":0,
    "gn:timezone":"America/Mexico_City",
    "iso:country":"MX",
    "name:spa_x_preferred":[
        "Rosa Concepci\u00f3n"
    ],
    "name:spa_x_variant":[
        "Rosa San Antonio"
    ],
    "wof:name":"Rosa Concepcion",
    "wof:placetype":"locality"
},
  "geometry": {"coordinates":[-100.18625,19.64274],"type":"Point"}
}