{
  "type": "Feature",
  "properties": {
    "gn:admin1_code":"17",
    "gn:admin2_code":"28.0",
    "gn:asciiname":"Campo la Tehuixtlera",
    "gn:country_code":"MX",
    "gn:dem":1102,
    "gn:feature_class":"P",
    "gn:feature_code":"PPL",
    "gn:name":"Campo la Tehuixtlera",
    "gn:population":112,
    "gn:timezone":"America/Mexico_City",
    "iso:country":"MX",
    "wof:name":"Campo la Tehuixtlera",
    "wof:placetype":"locality",
    "wof:population":112
},
  "geometry": {"coordinates":[-99.24028,18.76083],"type":"Point"}
}