{
  "type": "Feature",
  "properties": {
    "gn:admin1_code":"30",
    "gn:admin2_code":"72.0",
    "gn:asciiname":"El Plan",
    "gn:country_code":"MX",
    "gn:dem":1529,
    "gn:feature_class":"P",
    "gn:feature_code":"PPL",
    "gn:name":"El Plan",
    "gn:population":7,
    "gn:timezone":"America/Mexico_City",
    "iso:country":"MX",
    "wof:name":"El Plan",
    "wof:placetype":"locality",
    "wof:population":7
},
  "geometry": {"coordinates":[-98.42722000000001,20.66389],"type":"Point"}
}