{
  "type": "Feature",
  "properties": {
    "gn:admin1_code":"25",
    "gn:admin2_code":"12",
    "gn:asciiname":"El Magistral",
    "gn:country_code":"MX",
    "gn:dem":415,
    "gn:feature_class":"P",
    "gn:feature_code":"PPL",
    "gn:name":"El Magistral",
    "gn:population":12,
    "gn:timezone":"America/Mazatlan",
    "iso:country":"MX",
    "wof:name":"El Magistral",
    "wof:placetype":"locality",
    "wof:population":12
},
  "geometry": {"coordinates":[-105.98084,23.78005],"type":"Point"}
}