{
  "type": "Feature",
  "properties": {
    "gn:admin1_code":"6",
    "gn:admin2_code":"27.0",
    "gn:asciiname":"Aboreachi",
    "gn:country_code":"MX",
    "gn:dem":1951,
    "gn:feature_class":"P",
    "gn:feature_code":"PPL",
    "gn:name":"Aboreachi",
    "gn:population":0,
    "gn:timezone":"America/Chihuahua",
    "iso:country":"MX",
    "name:spa_x_preferred":[
        "Aboreachi"
    ],
    "wof:name":"Aboreachi",
    "wof:placetype":"locality"
},
  "geometry": {"coordinates":[-107.57131,27.47103],"type":"Point"}
}