{
  "type": "Feature",
  "properties": {
    "gn:admin1_code":"26",
    "gn:admin2_code":"61.0",
    "gn:asciiname":"Los Quiotes",
    "gn:country_code":"MX",
    "gn:dem":236,
    "gn:feature_class":"P",
    "gn:feature_code":"PPL",
    "gn:name":"Los Quiotes",
    "gn:population":0,
    "gn:timezone":"America/Hermosillo",
    "iso:country":"MX",
    "name:spa_x_preferred":[
        "Los Quiotes"
    ],
    "wof:name":"Los Quiotes",
    "wof:placetype":"locality"
},
  "geometry": {"coordinates":[-109.53278,28.62694],"type":"Point"}
}