{
  "type": "Feature",
  "properties": {
    "gn:admin1_code":"10",
    "gn:admin2_code":"1.0",
    "gn:asciiname":"Benjamin Aranda",
    "gn:country_code":"MX",
    "gn:dem":1935,
    "gn:feature_class":"P",
    "gn:feature_code":"PPL",
    "gn:name":"Benjam\u00edn Aranda",
    "gn:population":0,
    "gn:timezone":"America/Monterrey",
    "iso:country":"MX",
    "name:spa_x_preferred":[
        "Benjam\u00edn Aranda"
    ],
    "name:spa_x_variant":[
        "San Rafael"
    ],
    "wof:name":"Benjamin Aranda",
    "wof:placetype":"locality"
},
  "geometry": {"coordinates":[-104.7687,24.32162000000001],"type":"Point"}
}