{
  "type": "Feature",
  "properties": {
    "gn:admin1_code":"16.0",
    "gn:admin2_code":"97.0",
    "gn:asciiname":"La Tanicua",
    "gn:country_code":"MX",
    "gn:dem":1106,
    "gn:feature_class":"P",
    "gn:feature_code":"PPL",
    "gn:name":"La Tanicua",
    "gn:population":0,
    "gn:timezone":"America/Mexico_City",
    "iso:country":"MX",
    "name:spa_x_preferred":[
        "La Tanicua"
    ],
    "wof:name":"La Tanicua",
    "wof:placetype":"locality"
},
  "geometry": {"coordinates":[-101.49187000000001,19.02011],"type":"Point"}
}