{
  "type": "Feature",
  "properties": {
    "gn:admin1_code":"7.0",
    "gn:admin2_code":"29.0",
    "gn:asciiname":"El Chemiza",
    "gn:country_code":"MX",
    "gn:dem":563,
    "gn:feature_class":"P",
    "gn:feature_code":"PPL",
    "gn:name":"El Chemiza",
    "gn:population":0,
    "gn:timezone":"America/Monterrey",
    "iso:country":"MX",
    "name:spa_x_preferred":[
        "El Chemiza"
    ],
    "wof:name":"El Chemiza",
    "wof:placetype":"locality"
},
  "geometry": {"coordinates":[-101.72145,27.03254],"type":"Point"}
}