{
  "type": "Feature",
  "properties": {
    "gn:admin1_code":"25.0",
    "gn:admin2_code":"12.0",
    "gn:asciiname":"Chuchupira",
    "gn:country_code":"MX",
    "gn:dem":12,
    "gn:feature_class":"P",
    "gn:feature_code":"PPL",
    "gn:name":"Chuchupira",
    "gn:population":0,
    "gn:timezone":"America/Mazatlan",
    "iso:country":"MX",
    "name:spa_x_preferred":[
        "Chuchupira"
    ],
    "wof:name":"Chuchupira",
    "wof:placetype":"locality"
},
  "geometry": {"coordinates":[-106.50976,23.37965],"type":"Point"}
}