{
  "type": "Feature",
  "properties": {
    "gn:admin1_code":"11",
    "gn:admin2_code":"26",
    "gn:asciiname":"El Pato (Ejido Guadalupe de Amoles)",
    "gn:country_code":"MX",
    "gn:dem":1745,
    "gn:feature_class":"P",
    "gn:feature_code":"PPL",
    "gn:name":"El Pato (Ejido Guadalupe de Amoles)",
    "gn:population":10,
    "gn:timezone":"America/Mexico_City",
    "iso:country":"MX",
    "wof:name":"El Pato (Ejido Guadalupe de Amoles)",
    "wof:placetype":"locality",
    "wof:population":10
},
  "geometry": {"coordinates":[-101.60045,20.81718],"type":"Point"}
}