{
  "type": "Feature",
  "properties": {
    "gn:admin1_code":"16.0",
    "gn:admin2_code":"29.0",
    "gn:asciiname":"El Salitrillo",
    "gn:country_code":"MX",
    "gn:dem":527,
    "gn:feature_class":"P",
    "gn:feature_code":"PPL",
    "gn:name":"El Salitrillo",
    "gn:population":0,
    "gn:timezone":"America/Mexico_City",
    "iso:country":"MX",
    "name:spa_x_preferred":[
        "El Salitrillo"
    ],
    "wof:name":"El Salitrillo",
    "wof:placetype":"locality"
},
  "geometry": {"coordinates":[-101.4875,18.68861],"type":"Point"}
}