{
  "type": "Feature",
  "properties": {
    "gn:admin1_code":"21",
    "gn:admin2_code":"116.0",
    "gn:asciiname":"Tlamanca",
    "gn:country_code":"MX",
    "gn:dem":1643,
    "gn:feature_class":"P",
    "gn:feature_code":"PPL",
    "gn:name":"Tlamanca",
    "gn:population":551,
    "gn:timezone":"America/Mexico_City",
    "iso:country":"MX",
    "wof:name":"Tlamanca",
    "wof:placetype":"locality",
    "wof:population":551
},
  "geometry": {"coordinates":[-97.11346,19.29443],"type":"Point"}
}