{
  "type": "Feature",
  "properties": {
    "gn:admin1_code":"10",
    "gn:admin2_code":"32.0",
    "gn:asciiname":"San Maria de Huajupa",
    "gn:country_code":"MX",
    "gn:dem":1063,
    "gn:feature_class":"P",
    "gn:feature_code":"PPL",
    "gn:name":"San Mar\u00eda de Huajupa",
    "gn:population":0,
    "gn:timezone":"America/Monterrey",
    "iso:country":"MX",
    "wof:name":"San Maria de Huajupa",
    "wof:placetype":"locality"
},
  "geometry": {"coordinates":[-106.39943999999998,24.87333],"type":"Point"}
}