{
  "type": "Feature",
  "properties": {
    "gn:admin1_code":"19",
    "gn:admin2_code":"26.0",
    "gn:asciiname":"Bello Amanecer",
    "gn:country_code":"MX",
    "gn:dem":427,
    "gn:feature_class":"P",
    "gn:feature_code":"PPL",
    "gn:name":"Bello Amanecer",
    "gn:population":135,
    "gn:timezone":"America/Monterrey",
    "iso:country":"MX",
    "wof:name":"Bello Amanecer",
    "wof:placetype":"locality",
    "wof:population":135
},
  "geometry": {"coordinates":[-100.13527999999999,25.69806],"type":"Point"}
}