{
  "type": "Feature",
  "properties": {
    "gn:admin1_code":"28",
    "gn:admin2_code":"6.0",
    "gn:asciiname":"Presa San Antonio",
    "gn:cc2":"MX",
    "gn:country_code":"MX",
    "gn:dem":2098,
    "gn:feature_class":"P",
    "gn:feature_code":"PPL",
    "gn:name":"Presa San Antonio",
    "gn:population":0,
    "gn:timezone":"America/Monterrey",
    "iso:country":"MX",
    "name:und_x_variant":[
        "Presa de San Antonio",
        "Presa San Antonio"
    ],
    "wof:name":"Presa San Antonio",
    "wof:placetype":"locality"
},
  "geometry": {"coordinates":[-100.01667,23.35],"type":"Point"}
}