{
  "type": "Feature",
  "properties": {
    "gn:admin1_code":"16",
    "gn:admin2_code":"110.0",
    "gn:asciiname":"Los Trigos",
    "gn:country_code":"MX",
    "gn:dem":2400,
    "gn:feature_class":"P",
    "gn:feature_code":"PPL",
    "gn:name":"Los Trigos",
    "gn:population":143,
    "gn:timezone":"America/Mexico_City",
    "iso:country":"MX",
    "wof:name":"Los Trigos",
    "wof:placetype":"locality",
    "wof:population":143
},
  "geometry": {"coordinates":[-100.71444,19.86917],"type":"Point"}
}