{
  "type": "Feature",
  "properties": {
    "gn:admin1_code":"6.0",
    "gn:admin2_code":"46.0",
    "gn:asciiname":"Vinaterias",
    "gn:country_code":"MX",
    "gn:dem":1354,
    "gn:feature_class":"P",
    "gn:feature_code":"PPL",
    "gn:name":"Vinater\u00edas",
    "gn:population":0,
    "gn:timezone":"America/Chihuahua",
    "iso:country":"MX",
    "name:spa_x_preferred":[
        "Vinater\u00edas"
    ],
    "wof:name":"Vinaterias",
    "wof:placetype":"locality"
},
  "geometry": {"coordinates":[-107.73,26.72698],"type":"Point"}
}