{
  "type": "Feature",
  "properties": {
    "gn:admin1_code":"20",
    "gn:admin2_code":"407.0",
    "gn:asciiname":"Benito Juarez Uno",
    "gn:country_code":"MX",
    "gn:dem":887,
    "gn:feature_class":"P",
    "gn:feature_code":"PPL",
    "gn:name":"Benito Ju\u00e1rez Uno",
    "gn:population":0,
    "gn:timezone":"America/Mexico_City",
    "iso:country":"MX",
    "name:spa_x_preferred":[
        "Benito Ju\u00e1rez"
    ],
    "name:spa_x_variant":[
        "Benito Ju\u00e1rez Uno",
        "Chiapas Nuevo"
    ],
    "wof:name":"Benito Juarez Uno",
    "wof:placetype":"locality"
},
  "geometry": {"coordinates":[-93.94983999999999,17.0102],"type":"Point"}
}