{
  "type": "Feature",
  "properties": {
    "gn:admin1_code":"5.0",
    "gn:admin2_code":"89.0",
    "gn:asciiname":"San Jacinto",
    "gn:country_code":"MX",
    "gn:dem":467,
    "gn:feature_class":"P",
    "gn:feature_code":"PPL",
    "gn:name":"San Jacinto",
    "gn:population":0,
    "gn:timezone":"America/Mexico_City",
    "iso:country":"MX",
    "name:spa_x_preferred":[
        "San Jacinto"
    ],
    "wof:name":"San Jacinto",
    "wof:placetype":"locality"
},
  "geometry": {"coordinates":[-92.22302999999999,15.02811],"type":"Point"}
}