{
  "type": "Feature",
  "properties": {
    "gn:admin1_code":"6",
    "gn:admin2_code":"60.0",
    "gn:asciiname":"Las Adjuntas",
    "gn:country_code":"MX",
    "gn:dem":2031,
    "gn:feature_class":"P",
    "gn:feature_code":"PPL",
    "gn:name":"Las Adjuntas",
    "gn:population":7,
    "gn:timezone":"America/Chihuahua",
    "iso:country":"MX",
    "name:jpn_x_preferred":[
        "\u30e9\u30b9\u30fb\u30a2\u30c9\u30d5\u30f3\u30bf\u30b9\u99c5"
    ],
    "name:por_x_preferred":[
        "Esta\u00e7\u00e3o Las Adjuntas"
    ],
    "wof:name":"Las Adjuntas",
    "wof:placetype":"locality",
    "wof:population":7
},
  "geometry": {"coordinates":[-105.85972,26.79028],"type":"Point"}
}