{
  "type": "Feature",
  "properties": {
    "gn:admin1_code":"6",
    "gn:admin2_code":"27.0",
    "gn:asciiname":"La Cumbrecita",
    "gn:country_code":"MX",
    "gn:dem":2504,
    "gn:feature_class":"P",
    "gn:feature_code":"PPL",
    "gn:name":"La Cumbrecita",
    "gn:population":92,
    "gn:timezone":"America/Chihuahua",
    "iso:country":"MX",
    "wof:name":"La Cumbrecita",
    "wof:placetype":"locality",
    "wof:population":92
},
  "geometry": {"coordinates":[-107.13266000000002,26.71772],"type":"Point"}
}