{
  "type": "Feature",
  "properties": {
    "gn:admin1_code":"6",
    "gn:admin2_code":"27.0",
    "gn:asciiname":"La Cumbrecita",
    "gn:country_code":"MX",
    "gn:dem":2504,
    "gn:feature_class":"P",
    "gn:feature_code":"PPL",
    "gn:name":"La Cumbrecita",
    "gn:population":92,
    "gn:timezone":"America/Chihuahua",
    "iso:country":"MX",
    "name:ceb_x_preferred":[
        "La Cumbrecita"
    ],
    "name:deu_x_preferred":[
        "La Cumbrecita"
    ],
    "name:por_x_preferred":[
        "La Cumbrecita"
    ],
    "name:spa_x_preferred":[
        "La Cumbrecita"
    ],
    "name:swe_x_preferred":[
        "La Cumbrecita"
    ],
    "name:urd_x_preferred":[
        "\u0644\u0627 \u06a9\u0648\u0645\u0628\u0631\u06cc\u0633\u06cc\u062a\u0627"
    ],
    "wof:name":"La Cumbrecita",
    "wof:placetype":"locality",
    "wof:population":92
},
  "geometry": {"coordinates":[-107.13266000000002,26.71772],"type":"Point"}
}