{
  "type": "Feature",
  "properties": {
    "gn:admin1_code":"30",
    "gn:admin2_code":"17",
    "gn:asciiname":"Banos (El Bejuco)",
    "gn:country_code":"MX",
    "gn:dem":223,
    "gn:feature_class":"P",
    "gn:feature_code":"PPL",
    "gn:name":"Ba\u00f1os (El Bejuco)",
    "gn:population":25,
    "gn:timezone":"America/Mexico_City",
    "iso:country":"MX",
    "name:und_x_variant":[
        "Ba\u00f1os (El Bejuco)"
    ],
    "wof:name":"Banos (El Bejuco)",
    "wof:placetype":"locality",
    "wof:population":25
},
  "geometry": {"coordinates":[-96.63278,19.32167],"type":"Point"}
}