{
  "type": "Feature",
  "properties": {
    "gn:admin1_code":"22",
    "gn:admin2_code":"13.0",
    "gn:asciiname":"Cerro Colorado",
    "gn:country_code":"MX",
    "gn:dem":1755,
    "gn:feature_class":"P",
    "gn:feature_code":"PPL",
    "gn:name":"Cerro Colorado",
    "gn:population":65,
    "gn:timezone":"America/Mexico_City",
    "iso:country":"MX",
    "wof:name":"Cerro Colorado",
    "wof:placetype":"locality",
    "wof:population":65
},
  "geometry": {"coordinates":[-99.94,21.14611],"type":"Point"}
}