{
  "type": "Feature",
  "properties": {
    "gn:admin1_code":"6.0",
    "gn:admin2_code":"40.0",
    "gn:asciiname":"Cerro Colorado",
    "gn:country_code":"MX",
    "gn:dem":1304,
    "gn:feature_class":"P",
    "gn:feature_code":"PPL",
    "gn:name":"Cerro Colorado",
    "gn:population":0,
    "gn:timezone":"America/Chihuahua",
    "iso:country":"MX",
    "name:spa_x_preferred":[
        "Cerro Colorado"
    ],
    "wof:name":"Cerro Colorado",
    "wof:placetype":"locality"
},
  "geometry": {"coordinates":[-108.52701999999999,28.99201],"type":"Point"}
}