{
  "type": "Feature",
  "properties": {
    "gn:admin1_code":"5",
    "gn:admin2_code":"17.0",
    "gn:asciiname":"El Deseo (Mario Toledo C.)",
    "gn:country_code":"MX",
    "gn:dem":590,
    "gn:feature_class":"P",
    "gn:feature_code":"PPL",
    "gn:name":"El Deseo (Mario Toledo C.)",
    "gn:population":6,
    "gn:timezone":"America/Mexico_City",
    "iso:country":"MX",
    "wof:name":"El Deseo (Mario Toledo C.)",
    "wof:placetype":"locality",
    "wof:population":6
},
  "geometry": {"coordinates":[-93.74444,16.66972],"type":"Point"}
}