{
  "type": "Feature",
  "properties": {
    "gn:admin1_code":"5.0",
    "gn:asciiname":"Cafetal Miriam",
    "gn:country_code":"MX",
    "gn:dem":1409,
    "gn:feature_class":"P",
    "gn:feature_code":"PPL",
    "gn:name":"Cafetal Miriam",
    "gn:population":0,
    "gn:timezone":"America/Mexico_City",
    "iso:country":"MX",
    "name:spa_x_preferred":[
        "Cafetal Miriam"
    ],
    "wof:name":"Cafetal Miriam",
    "wof:placetype":"locality"
},
  "geometry": {"coordinates":[-92.08154999999999,15.06877],"type":"Point"}
}