{
  "type": "Feature",
  "properties": {
    "gn:admin1_code":"12.0",
    "gn:admin2_code":"21.0",
    "gn:asciiname":"Los Galeana",
    "gn:country_code":"MX",
    "gn:dem":65,
    "gn:feature_class":"P",
    "gn:feature_code":"PPL",
    "gn:name":"Los Galeana",
    "gn:population":0,
    "gn:timezone":"America/Mexico_City",
    "iso:country":"MX",
    "name:spa_x_preferred":[
        "Los Galeana"
    ],
    "wof:name":"Los Galeana",
    "wof:placetype":"locality"
},
  "geometry": {"coordinates":[-100.06479,17.0806],"type":"Point"}
}