{
  "type": "Feature",
  "properties": {
    "gn:admin1_code":"29.0",
    "gn:admin2_code":"4.0",
    "gn:asciiname":"Nazaret",
    "gn:country_code":"MX",
    "gn:dem":2576,
    "gn:feature_class":"P",
    "gn:feature_code":"PPL",
    "gn:name":"Nazaret",
    "gn:population":0,
    "gn:timezone":"America/Mexico_City",
    "iso:country":"MX",
    "name:spa_x_preferred":[
        "Nazaret"
    ],
    "name:spa_x_variant":[
        "Nazareth"
    ],
    "wof:name":"Nazaret",
    "wof:placetype":"locality"
},
  "geometry": {"coordinates":[-97.82653000000001,19.37586],"type":"Point"}
}