{
  "type": "Feature",
  "properties": {
    "gn:admin1_code":"1.0",
    "gn:admin2_code":"5.0",
    "gn:asciiname":"Valladolid",
    "gn:country_code":"MX",
    "gn:dem":1876,
    "gn:feature_class":"P",
    "gn:feature_code":"PPL",
    "gn:name":"Valladolid",
    "gn:population":1411,
    "gn:timezone":"America/Mexico_City",
    "iso:country":"MX",
    "wof:name":"Valladolid",
    "wof:placetype":"locality",
    "wof:population":1411
},
  "geometry": {"coordinates":[-102.315,22.02111],"type":"Point"}
}