{
  "type": "Feature",
  "properties": {
    "gn:admin1_code":"14",
    "gn:admin2_code":"101.0",
    "gn:asciiname":"Tololotlan",
    "gn:country_code":"MX",
    "gn:dem":1466,
    "gn:feature_class":"P",
    "gn:feature_code":"PPL",
    "gn:name":"Tololotl\u00e1n",
    "gn:population":0,
    "gn:timezone":"America/Mexico_City",
    "iso:country":"MX",
    "wof:name":"Tololotlan",
    "wof:placetype":"locality"
},
  "geometry": {"coordinates":[-103.16455999999999,20.55607],"type":"Point"}
}