{
  "type": "Feature",
  "properties": {
    "gn:admin1_code":"6.0",
    "gn:admin2_code":"48.0",
    "gn:asciiname":"Las Tunas",
    "gn:country_code":"MX",
    "gn:dem":1747,
    "gn:feature_class":"P",
    "gn:feature_code":"PPL",
    "gn:name":"Las Tunas",
    "gn:population":0,
    "gn:timezone":"America/Chihuahua",
    "iso:country":"MX",
    "name:ceb_x_preferred":[
        "Las Tunas"
    ],
    "name:deu_x_preferred":[
        "Las Tunas"
    ],
    "name:heb_x_preferred":[
        "\u05dc\u05d0\u05e1 \u05d8\u05d5\u05e0\u05d0\u05e1"
    ],
    "name:nld_x_preferred":[
        "Las Tunas"
    ],
    "name:pol_x_preferred":[
        "Las Tunas"
    ],
    "name:por_x_preferred":[
        "Las Tunas"
    ],
    "name:sco_x_preferred":[
        "Las Tunas"
    ],
    "name:spa_x_preferred":[
        "Las Tunas"
    ],
    "name:srp_x_preferred":[
        "\u041b\u0430\u0441 \u0422\u0443\u043d\u0430\u0441"
    ],
    "name:swe_x_preferred":[
        "Las Tunas"
    ],
    "name:tur_x_preferred":[
        "Las Tunas"
    ],
    "wof:name":"Las Tunas",
    "wof:placetype":"locality"
},
  "geometry": {"coordinates":[-107.08672,29.52761],"type":"Point"}
}