{
  "type": "Feature",
  "properties": {
    "gn:admin1_code":"7",
    "gn:admin2_code":"38.0",
    "gn:asciiname":"Tinaja de Hoyos",
    "gn:country_code":"MX",
    "gn:dem":439,
    "gn:feature_class":"P",
    "gn:feature_code":"PPL",
    "gn:name":"Tinaja de Hoyos",
    "gn:population":0,
    "gn:timezone":"America/Monterrey",
    "iso:country":"MX",
    "wof:name":"Tinaja de Hoyos",
    "wof:placetype":"locality"
},
  "geometry": {"coordinates":[-101.23333,28.76667],"type":"Point"}
}