{
  "type": "Feature",
  "properties": {
    "gn:admin1_code":"11",
    "gn:admin2_code":"43.0",
    "gn:asciiname":"Capilla Blanca",
    "gn:country_code":"MX",
    "gn:dem":1989,
    "gn:feature_class":"P",
    "gn:feature_code":"PPL",
    "gn:name":"Capilla Blanca",
    "gn:population":177,
    "gn:timezone":"America/Mexico_City",
    "iso:country":"MX",
    "wof:name":"Capilla Blanca",
    "wof:placetype":"locality",
    "wof:population":177
},
  "geometry": {"coordinates":[-100.33163999999999,21.2211],"type":"Point"}
}