{
  "type": "Feature",
  "properties": {
    "gn:admin1_code":"30",
    "gn:admin2_code":"76.0",
    "gn:asciiname":"Tenexco",
    "gn:country_code":"MX",
    "gn:dem":623,
    "gn:feature_class":"P",
    "gn:feature_code":"PPL",
    "gn:name":"Tenexco",
    "gn:population":160,
    "gn:timezone":"America/Mexico_City",
    "iso:country":"MX",
    "wof:name":"Tenexco",
    "wof:placetype":"locality",
    "wof:population":160
},
  "geometry": {"coordinates":[-98.43861,20.75028],"type":"Point"}
}