{
  "type": "Feature",
  "properties": {
    "gn:admin1_code":"19.0",
    "gn:asciiname":"Las Joyitas",
    "gn:country_code":"MX",
    "gn:dem":416,
    "gn:feature_class":"P",
    "gn:feature_code":"PPL",
    "gn:name":"Las Joyitas",
    "gn:population":0,
    "gn:timezone":"America/Monterrey",
    "iso:country":"MX",
    "name:spa_x_preferred":[
        "Las Joyitas"
    ],
    "wof:name":"Las Joyitas",
    "wof:placetype":"locality"
},
  "geometry": {"coordinates":[-100.18192000000001,25.79537],"type":"Point"}
}