{
  "type": "Feature",
  "properties": {
    "gn:admin1_code":"20",
    "gn:admin2_code":"494",
    "gn:asciiname":"Rio de Chicle",
    "gn:country_code":"MX",
    "gn:dem":2432,
    "gn:feature_class":"P",
    "gn:feature_code":"PPL",
    "gn:name":"R\u00edo de Chicle",
    "gn:population":16,
    "gn:timezone":"America/Mexico_City",
    "iso:country":"MX",
    "name:und_x_variant":[
        "R\u00edo de Chicle"
    ],
    "wof:name":"Rio de Chicle",
    "wof:placetype":"locality",
    "wof:population":16
},
  "geometry": {"coordinates":[-96.99472,17.04194],"type":"Point"}
}