{
  "type": "Feature",
  "properties": {
    "gn:admin1_code":"24",
    "gn:admin2_code":"10.0",
    "gn:asciiname":"Puerto de San Juan de Dios",
    "gn:country_code":"MX",
    "gn:dem":1025,
    "gn:feature_class":"P",
    "gn:feature_code":"PPL",
    "gn:name":"Puerto de San Juan de Dios",
    "gn:population":219,
    "gn:timezone":"America/Mexico_City",
    "iso:country":"MX",
    "wof:name":"Puerto de San Juan de Dios",
    "wof:placetype":"locality",
    "wof:population":219
},
  "geometry": {"coordinates":[-99.88968,22.68462],"type":"Point"}
}