{
  "type": "Feature",
  "properties": {
    "gn:admin1_code":"24",
    "gn:admin2_code":"12",
    "gn:asciiname":"Barrio la Laguna",
    "gn:country_code":"MX",
    "gn:dem":217,
    "gn:feature_class":"P",
    "gn:feature_code":"PPL",
    "gn:name":"Barrio la Laguna",
    "gn:population":52,
    "gn:timezone":"America/Mexico_City",
    "iso:country":"MX",
    "wof:name":"Barrio la Laguna",
    "wof:placetype":"locality",
    "wof:population":52
},
  "geometry": {"coordinates":[-98.93361,21.58361],"type":"Point"}
}