{
  "type": "Feature",
  "properties": {
    "gn:admin1_code":"6.0",
    "gn:admin2_code":"34.0",
    "gn:asciiname":"Tinajitas",
    "gn:country_code":"MX",
    "gn:dem":1881,
    "gn:feature_class":"P",
    "gn:feature_code":"PPL",
    "gn:name":"Tinajitas",
    "gn:population":0,
    "gn:timezone":"America/Chihuahua",
    "iso:country":"MX",
    "name:spa_x_preferred":[
        "Tinajitas"
    ],
    "wof:name":"Tinajitas",
    "wof:placetype":"locality"
},
  "geometry": {"coordinates":[-107.50085,29.63599],"type":"Point"}
}