{
  "type": "Feature",
  "properties": {
    "gn:admin1_code":"5.0",
    "gn:admin2_code":"108.0",
    "gn:asciiname":"El Pajuil",
    "gn:country_code":"MX",
    "gn:dem":940,
    "gn:feature_class":"P",
    "gn:feature_code":"PPL",
    "gn:name":"El Pajuil",
    "gn:population":0,
    "gn:timezone":"America/Mexico_City",
    "iso:country":"MX",
    "name:spa_x_preferred":[
        "El Pajuil"
    ],
    "wof:name":"El Pajuil",
    "wof:placetype":"locality"
},
  "geometry": {"coordinates":[-93.53655999999999,16.20605],"type":"Point"}
}