{
  "type": "Feature",
  "properties": {
    "gn:admin1_code":"16",
    "gn:admin2_code":"110.0",
    "gn:asciiname":"El Tico",
    "gn:country_code":"MX",
    "gn:dem":2522,
    "gn:feature_class":"P",
    "gn:feature_code":"PPL",
    "gn:name":"El Tico",
    "gn:population":169,
    "gn:timezone":"America/Mexico_City",
    "iso:country":"MX",
    "wof:name":"El Tico",
    "wof:placetype":"locality",
    "wof:population":169
},
  "geometry": {"coordinates":[-100.69389,19.89333],"type":"Point"}
}