{
  "type": "Feature",
  "properties": {
    "gn:admin1_code":"16",
    "gn:admin2_code":"61.0",
    "gn:asciiname":"El Llano (Cerro de la Cocina)",
    "gn:country_code":"MX",
    "gn:dem":2308,
    "gn:feature_class":"P",
    "gn:feature_code":"PPL",
    "gn:name":"El Llano (Cerro de la Cocina)",
    "gn:population":227,
    "gn:timezone":"America/Mexico_City",
    "iso:country":"MX",
    "wof:name":"El Llano (Cerro de la Cocina)",
    "wof:placetype":"locality",
    "wof:population":227
},
  "geometry": {"coordinates":[-100.36528,19.60472],"type":"Point"}
}