{
  "type": "Feature",
  "properties": {
    "gn:admin1_code":"32",
    "gn:admin2_code":"20.0",
    "gn:asciiname":"Rancho del Charro (Pozo Numero Uno)",
    "gn:country_code":"MX",
    "gn:dem":1972,
    "gn:feature_class":"P",
    "gn:feature_code":"PPL",
    "gn:name":"Rancho del Charro (Pozo N\u00famero Uno)",
    "gn:population":9,
    "gn:timezone":"America/Mexico_City",
    "iso:country":"MX",
    "name:und_x_variant":[
        "Rancho del Charro (Pozo N\u00famero Uno)"
    ],
    "wof:name":"Rancho del Charro (Pozo Numero Uno)",
    "wof:placetype":"locality",
    "wof:population":9
},
  "geometry": {"coordinates":[-103.02639000000001,22.60306],"type":"Point"}
}