{
  "type": "Feature",
  "properties": {
    "gn:admin1_code":"6.0",
    "gn:admin2_code":"35.0",
    "gn:asciiname":"El Uno",
    "gn:country_code":"MX",
    "gn:dem":1418,
    "gn:feature_class":"P",
    "gn:feature_code":"PPL",
    "gn:name":"El Uno",
    "gn:population":0,
    "gn:timezone":"America/Chihuahua",
    "iso:country":"MX",
    "name:spa_x_preferred":[
        "El Uno"
    ],
    "name:spa_x_variant":[
        "Rancho Uno"
    ],
    "wof:name":"El Uno",
    "wof:placetype":"locality"
},
  "geometry": {"coordinates":[-108.42934,30.8372],"type":"Point"}
}