{
  "type": "Feature",
  "properties": {
    "gn:admin1_code":"5",
    "gn:admin2_code":"80",
    "gn:asciiname":"Nueva Libertad",
    "gn:country_code":"MX",
    "gn:dem":2430,
    "gn:feature_class":"P",
    "gn:feature_code":"PPL",
    "gn:name":"Nueva Libertad",
    "gn:population":42,
    "gn:timezone":"America/Mexico_City",
    "iso:country":"MX",
    "wof:name":"Nueva Libertad",
    "wof:placetype":"locality",
    "wof:population":42
},
  "geometry": {"coordinates":[-92.36694,15.50417],"type":"Point"}
}