{
  "type": "Feature",
  "properties": {
    "gn:admin1_code":"10",
    "gn:admin2_code":"39.0",
    "gn:asciiname":"Bajio Verde",
    "gn:country_code":"MX",
    "gn:dem":1978,
    "gn:feature_class":"P",
    "gn:feature_code":"PPL",
    "gn:name":"Baj\u00edo Verde",
    "gn:population":139,
    "gn:timezone":"America/Monterrey",
    "iso:country":"MX",
    "name:und_x_variant":[
        "Baj\u00edo Verde"
    ],
    "wof:name":"Bajio Verde",
    "wof:placetype":"locality",
    "wof:population":139
},
  "geometry": {"coordinates":[-105.06471999999999,24.96667],"type":"Point"}
}