{
  "type": "Feature",
  "properties": {
    "gn:admin1_code":"32",
    "gn:admin2_code":"10.0",
    "gn:asciiname":"Las Ovejas",
    "gn:country_code":"MX",
    "gn:dem":2182,
    "gn:feature_class":"P",
    "gn:feature_code":"PPL",
    "gn:name":"Las Ovejas",
    "gn:population":0,
    "gn:timezone":"America/Mexico_City",
    "iso:country":"MX",
    "name:ceb_x_preferred":[
        "Las Ovejas"
    ],
    "name:spa_x_preferred":[
        "Las Ovejas"
    ],
    "name:swe_x_preferred":[
        "Las Ovejas"
    ],
    "name:urd_x_preferred":[
        "\u0644\u0627\u0633 \u0648\u0648\u06cc\u062c\u0627\u0633"
    ],
    "wof:name":"Las Ovejas",
    "wof:placetype":"locality"
},
  "geometry": {"coordinates":[-103.23882,23.05265],"type":"Point"}
}