{
  "type": "Feature",
  "properties": {
    "gn:admin1_code":"30",
    "gn:admin2_code":"4.0",
    "gn:asciiname":"Arroyo de Piedra",
    "gn:country_code":"MX",
    "gn:dem":68,
    "gn:feature_class":"P",
    "gn:feature_code":"PPL",
    "gn:name":"Arroyo de Piedra",
    "gn:population":419,
    "gn:timezone":"America/Mexico_City",
    "iso:country":"MX",
    "name:jpn_x_preferred":[
        "\u30a2\u30ed\u30e8\u30fb\u30c7\u30fb\u30d4\u30a8\u30c9\u30e9"
    ],
    "name:ukr_x_preferred":[
        "\u0410\u0440\u0440\u043e\u0439\u043e-\u0434\u0435-\u041f'\u0454\u0434\u0440\u0430"
    ],
    "wof:name":"Arroyo de Piedra",
    "wof:placetype":"locality",
    "wof:population":419
},
  "geometry": {"coordinates":[-96.47750000000001,19.44972000000001],"type":"Point"}
}