{
  "type": "Feature",
  "properties": {
    "gn:admin1_code":"32",
    "gn:admin2_code":"25",
    "gn:asciiname":"Rancho Santa Rita",
    "gn:country_code":"MX",
    "gn:dem":2071,
    "gn:feature_class":"P",
    "gn:feature_code":"PPL",
    "gn:name":"Rancho Santa Rita",
    "gn:population":14,
    "gn:timezone":"America/Mexico_City",
    "iso:country":"MX",
    "wof:name":"Rancho Santa Rita",
    "wof:placetype":"locality",
    "wof:population":14
},
  "geometry": {"coordinates":[-102.12472,22.38222],"type":"Point"}
}