{
  "type": "Feature",
  "properties": {
    "gn:admin1_code":"30",
    "gn:admin2_code":"201.0",
    "gn:asciiname":"Zacatal Grande",
    "gn:country_code":"MX",
    "gn:dem":736,
    "gn:feature_class":"P",
    "gn:feature_code":"PPL",
    "gn:name":"Zacatal Grande",
    "gn:population":409,
    "gn:timezone":"America/Mexico_City",
    "iso:country":"MX",
    "wof:name":"Zacatal Grande",
    "wof:placetype":"locality",
    "wof:population":409
},
  "geometry": {"coordinates":[-96.95860999999999,18.65417],"type":"Point"}
}