{
  "type": "Feature",
  "properties": {
    "gn:admin1_code":"18.0",
    "gn:admin2_code":"15.0",
    "gn:asciiname":"El Manguito",
    "gn:country_code":"MX",
    "gn:dem":833,
    "gn:feature_class":"P",
    "gn:feature_code":"PPL",
    "gn:name":"El Manguito",
    "gn:population":154,
    "gn:timezone":"America/Mazatlan",
    "iso:country":"MX",
    "name:spa_x_preferred":[
        "El Manguito"
    ],
    "wof:name":"El Manguito",
    "wof:placetype":"locality",
    "wof:population":154
},
  "geometry": {"coordinates":[-104.88930999999999,21.86463],"type":"Point"}
}