{
  "type": "Feature",
  "properties": {
    "gn:admin1_code":"25",
    "gn:admin2_code":"17.0",
    "gn:asciiname":"San Miguel de San Joaquin (San Miguel)",
    "gn:country_code":"MX",
    "gn:dem":118,
    "gn:feature_class":"P",
    "gn:feature_code":"PPL",
    "gn:name":"San Miguel de San Joaqu\u00edn (San Miguel)",
    "gn:population":108,
    "gn:timezone":"America/Mazatlan",
    "iso:country":"MX",
    "wof:name":"San Miguel de San Joaquin (San Miguel)",
    "wof:placetype":"locality",
    "wof:population":108
},
  "geometry": {"coordinates":[-108.05861000000002,25.66278],"type":"Point"}
}