{
  "type": "Feature",
  "properties": {
    "gn:admin1_code":"26",
    "gn:admin2_code":"42",
    "gn:asciiname":"Ninguno [Los Briseno]",
    "gn:country_code":"MX",
    "gn:dem":34,
    "gn:feature_class":"P",
    "gn:feature_code":"PPL",
    "gn:name":"Ninguno [Los Brise\u00f1o]",
    "gn:population":11,
    "gn:timezone":"America/Hermosillo",
    "iso:country":"MX",
    "name:und_x_variant":[
        "Ninguno [Los Brise\u00f1o]"
    ],
    "wof:name":"Ninguno [Los Briseno]",
    "wof:placetype":"locality",
    "wof:population":11
},
  "geometry": {"coordinates":[-109.48417000000001,27.08333],"type":"Point"}
}