{
  "type": "Feature",
  "properties": {
    "gn:admin1_code":"6",
    "gn:admin2_code":"65",
    "gn:asciiname":"Seyotavo",
    "gn:country_code":"MX",
    "gn:dem":2003,
    "gn:feature_class":"P",
    "gn:feature_code":"PPL",
    "gn:name":"Seyotavo",
    "gn:population":46,
    "gn:timezone":"America/Chihuahua",
    "iso:country":"MX",
    "wof:name":"Seyotavo",
    "wof:placetype":"locality",
    "wof:population":46
},
  "geometry": {"coordinates":[-107.74463,27.19215],"type":"Point"}
}