{
  "type": "Feature",
  "properties": {
    "gn:admin1_code":"11",
    "gn:admin2_code":"23.0",
    "gn:asciiname":"Tepetate de Negrete",
    "gn:country_code":"MX",
    "gn:dem":1704,
    "gn:feature_class":"P",
    "gn:feature_code":"PPL",
    "gn:name":"Tepetate de Negrete",
    "gn:population":300,
    "gn:timezone":"America/Mexico_City",
    "iso:country":"MX",
    "wof:name":"Tepetate de Negrete",
    "wof:placetype":"locality",
    "wof:population":300
},
  "geometry": {"coordinates":[-101.79889,20.31472],"type":"Point"}
}