{
  "type": "Feature",
  "properties": {
    "gn:admin1_code":"24",
    "gn:admin2_code":"20.0",
    "gn:asciiname":"Los Alamitos",
    "gn:country_code":"MX",
    "gn:dem":1334,
    "gn:feature_class":"P",
    "gn:feature_code":"PPL",
    "gn:name":"Los Alamitos",
    "gn:population":0,
    "gn:timezone":"America/Mexico_City",
    "iso:country":"MX",
    "name:ceb_x_preferred":[
        "Los Alamitos"
    ],
    "name:srp_x_preferred":[
        "\u041b\u043e\u0441 \u0410\u043b\u0430\u043c\u0438\u0442\u043e\u0441"
    ],
    "name:swe_x_preferred":[
        "Los Alamitos"
    ],
    "wof:name":"Los Alamitos",
    "wof:placetype":"locality"
},
  "geometry": {"coordinates":[-100.55782000000001,23.31043],"type":"Point"}
}