{
  "type": "Feature",
  "properties": {
    "gn:admin1_code":"14",
    "gn:admin2_code":"94.0",
    "gn:asciiname":"El Guaje",
    "gn:country_code":"MX",
    "gn:dem":1068,
    "gn:feature_class":"P",
    "gn:feature_code":"PPL",
    "gn:name":"El Guaje",
    "gn:population":8,
    "gn:timezone":"America/Mexico_City",
    "iso:country":"MX",
    "wof:name":"El Guaje",
    "wof:placetype":"locality",
    "wof:population":8
},
  "geometry": {"coordinates":[-103.82778,20.90917],"type":"Point"}
}