{
  "type": "Feature",
  "properties": {
    "gn:admin1_code":"31",
    "gn:admin2_code":"53.0",
    "gn:asciiname":"Yaxcopil",
    "gn:country_code":"MX",
    "gn:dem":21,
    "gn:feature_class":"P",
    "gn:feature_code":"PPL",
    "gn:name":"Yaxcopil",
    "gn:population":0,
    "gn:timezone":"America/Merida",
    "iso:country":"MX",
    "name:und_x_variant":[
        "Yaxcopoil",
        "Yaxcopil"
    ],
    "wof:name":"Yaxcopil",
    "wof:placetype":"locality"
},
  "geometry": {"coordinates":[-89.65657,20.51278],"type":"Point"}
}