{
  "type": "Feature",
  "properties": {
    "gn:admin1_code":"11",
    "gn:admin2_code":"17.0",
    "gn:asciiname":"Colonia la Villita de Guadalupe",
    "gn:country_code":"MX",
    "gn:dem":1744,
    "gn:feature_class":"P",
    "gn:feature_code":"PPL",
    "gn:name":"Colonia la Villita de Guadalupe",
    "gn:population":59,
    "gn:timezone":"America/Mexico_City",
    "iso:country":"MX",
    "wof:name":"Colonia la Villita de Guadalupe",
    "wof:placetype":"locality",
    "wof:population":59
},
  "geometry": {"coordinates":[-101.42749999999999,20.77806],"type":"Point"}
}