{
  "type": "Feature",
  "properties": {
    "gn:admin1_code":"29",
    "gn:admin2_code":"57",
    "gn:asciiname":"La Arena",
    "gn:country_code":"MX",
    "gn:dem":2204,
    "gn:feature_class":"P",
    "gn:feature_code":"PPL",
    "gn:name":"La Arena",
    "gn:population":21,
    "gn:timezone":"America/Mexico_City",
    "iso:country":"MX",
    "name:ceb_x_preferred":[
        "La Arena"
    ],
    "name:ita_x_preferred":[
        "La Arena"
    ],
    "name:srp_x_preferred":[
        "\u041b\u0430 \u0410\u0440\u0435\u043d\u0430"
    ],
    "name:swe_x_preferred":[
        "La Arena"
    ],
    "wof:name":"La Arena",
    "wof:placetype":"locality",
    "wof:population":21
},
  "geometry": {"coordinates":[-98.30611,19.23902],"type":"Point"}
}