{
  "type": "Feature",
  "properties": {
    "gn:admin1_code":"23",
    "gn:admin2_code":"4.0",
    "gn:asciiname":"Lazaro Cardenas Segundo",
    "gn:country_code":"MX",
    "gn:dem":146,
    "gn:feature_class":"P",
    "gn:feature_code":"PPL",
    "gn:name":"L\u00e1zaro C\u00e1rdenas Segundo",
    "gn:population":0,
    "gn:timezone":"America/Cancun",
    "iso:country":"MX",
    "name:spa_x_preferred":[
        "L\u00e1zaro C\u00e1rdenas Segundo"
    ],
    "name:und_x_variant":[
        "Nuevo L\u00e1zaro C\u00e1rdenas",
        "L\u00e1zaro C\u00e1rdenas"
    ],
    "wof:name":"Lazaro Cardenas Segundo",
    "wof:placetype":"locality"
},
  "geometry": {"coordinates":[-88.85821999999997,18.70123],"type":"Point"}
}