{
  "type": "Feature",
  "properties": {
    "gn:admin1_code":"26",
    "gn:admin2_code":"47.0",
    "gn:asciiname":"El Hay Nomas",
    "gn:country_code":"MX",
    "gn:dem":816,
    "gn:feature_class":"P",
    "gn:feature_code":"PPL",
    "gn:name":"El Hay Nom\u00e1s",
    "gn:population":5,
    "gn:timezone":"America/Hermosillo",
    "iso:country":"MX",
    "name:und_x_variant":[
        "El Hay Nom\u00e1s"
    ],
    "wof:name":"El Hay Nomas",
    "wof:placetype":"locality",
    "wof:population":5
},
  "geometry": {"coordinates":[-111.73444000000001,30.01917000000001],"type":"Point"}
}