{
  "type": "Feature",
  "properties": {
    "gn:admin1_code":"16",
    "gn:admin2_code":"53.0",
    "gn:asciiname":"Puerto de Celaya",
    "gn:country_code":"MX",
    "gn:dem":2381,
    "gn:feature_class":"P",
    "gn:feature_code":"PPL",
    "gn:name":"Puerto de Celaya",
    "gn:population":6,
    "gn:timezone":"America/Mexico_City",
    "iso:country":"MX",
    "wof:name":"Puerto de Celaya",
    "wof:placetype":"locality",
    "wof:population":6
},
  "geometry": {"coordinates":[-101.19278,19.56167],"type":"Point"}
}