{
  "type": "Feature",
  "properties": {
    "gn:admin1_code":"16",
    "gn:admin2_code":"89.0",
    "gn:asciiname":"Zoquitita",
    "gn:country_code":"MX",
    "gn:dem":507,
    "gn:feature_class":"P",
    "gn:feature_code":"PPL",
    "gn:name":"Zoquitita",
    "gn:population":0,
    "gn:timezone":"America/Mexico_City",
    "iso:country":"MX",
    "name:spa_x_preferred":[
        "Zoquitita"
    ],
    "wof:name":"Zoquitita",
    "wof:placetype":"locality",
    "wof:population":104
},
  "geometry": {"coordinates":[-102.96182,19.07267],"type":"Point"}
}