{
  "type": "Feature",
  "properties": {
    "gn:admin1_code":"16.0",
    "gn:admin2_code":"34.0",
    "gn:asciiname":"Cruz de Pinos",
    "gn:country_code":"MX",
    "gn:dem":2211,
    "gn:feature_class":"P",
    "gn:feature_code":"PPL",
    "gn:name":"Cruz de Pinos",
    "gn:population":0,
    "gn:timezone":"America/Mexico_City",
    "iso:country":"MX",
    "name:spa_x_preferred":[
        "Cruz de Pinos"
    ],
    "wof:name":"Cruz de Pinos",
    "wof:placetype":"locality"
},
  "geometry": {"coordinates":[-100.76989,19.54868],"type":"Point"}
}