{
  "type": "Feature",
  "properties": {
    "gn:admin1_code":"11",
    "gn:admin2_code":"13.0",
    "gn:asciiname":"Santa Cruz",
    "gn:country_code":"MX",
    "gn:dem":2094,
    "gn:feature_class":"P",
    "gn:feature_code":"PPL",
    "gn:name":"Santa Cruz",
    "gn:population":6,
    "gn:timezone":"America/Mexico_City",
    "iso:country":"MX",
    "wof:name":"Santa Cruz",
    "wof:placetype":"locality",
    "wof:population":6
},
  "geometry": {"coordinates":[-100.34444000000001,21.13889],"type":"Point"}
}