{
  "type": "Feature",
  "properties": {
    "gn:admin1_code":"20",
    "gn:admin2_code":"2.0",
    "gn:asciiname":"Selva Uno",
    "gn:country_code":"MX",
    "gn:dem":108,
    "gn:feature_class":"P",
    "gn:feature_code":"PPL",
    "gn:name":"Selva Uno",
    "gn:population":0,
    "gn:timezone":"America/Mexico_City",
    "iso:country":"MX",
    "name:spa_x_preferred":[
        "Selva Uno"
    ],
    "wof:name":"Selva Uno",
    "wof:placetype":"locality"
},
  "geometry": {"coordinates":[-96.51837999999999,18.44946],"type":"Point"}
}