{
  "type": "Feature",
  "properties": {
    "gn:admin1_code":"26.0",
    "gn:admin2_code":"6.0",
    "gn:asciiname":"Milpillas",
    "gn:country_code":"MX",
    "gn:dem":1092,
    "gn:feature_class":"P",
    "gn:feature_code":"PPL",
    "gn:name":"Milpillas",
    "gn:population":0,
    "gn:timezone":"America/Hermosillo",
    "iso:country":"MX",
    "name:spa_x_preferred":[
        "Milpillas"
    ],
    "wof:name":"Milpillas",
    "wof:placetype":"locality"
},
  "geometry": {"coordinates":[-110.27603999999999,30.61222],"type":"Point"}
}