{
  "type": "Feature",
  "properties": {
    "gn:admin1_code":"19",
    "gn:admin2_code":"16.0",
    "gn:asciiname":"Carlos Hernandez",
    "gn:country_code":"MX",
    "gn:dem":325,
    "gn:feature_class":"P",
    "gn:feature_code":"PPL",
    "gn:name":"Carlos Hern\u00e1ndez",
    "gn:population":5,
    "gn:timezone":"America/Monterrey",
    "iso:country":"MX",
    "name:und_x_variant":[
        "Carlos Hern\u00e1ndez"
    ],
    "wof:name":"Carlos Hernandez",
    "wof:placetype":"locality",
    "wof:population":5
},
  "geometry": {"coordinates":[-99.75725,25.86117],"type":"Point"}
}