{
  "type": "Feature",
  "properties": {
    "gn:admin1_code":"7",
    "gn:admin2_code":"18.0",
    "gn:asciiname":"El Vergel",
    "gn:country_code":"MX",
    "gn:dem":514,
    "gn:feature_class":"P",
    "gn:feature_code":"PPL",
    "gn:name":"El Vergel",
    "gn:population":7,
    "gn:timezone":"America/Monterrey",
    "iso:country":"MX",
    "wof:name":"El Vergel",
    "wof:placetype":"locality",
    "wof:population":7
},
  "geometry": {"coordinates":[-101.36731,26.99028],"type":"Point"}
}