{
  "type": "Feature",
  "properties": {
    "gn:admin1_code":"10",
    "gn:admin2_code":"19.0",
    "gn:asciiname":"Perdederos",
    "gn:country_code":"MX",
    "gn:dem":2710,
    "gn:feature_class":"P",
    "gn:feature_code":"PPL",
    "gn:name":"Perdederos",
    "gn:population":6,
    "gn:timezone":"America/Monterrey",
    "iso:country":"MX",
    "wof:name":"Perdederos",
    "wof:placetype":"locality",
    "wof:population":6
},
  "geometry": {"coordinates":[-105.89811,24.63416],"type":"Point"}
}