{
  "type": "Feature",
  "properties": {
    "gn:admin1_code":"12",
    "gn:admin2_code":"37.0",
    "gn:asciiname":"Huixquila",
    "gn:country_code":"MX",
    "gn:dem":1859,
    "gn:feature_class":"P",
    "gn:feature_code":"PPL",
    "gn:name":"Huixquila",
    "gn:population":109,
    "gn:timezone":"America/Mexico_City",
    "iso:country":"MX",
    "wof:name":"Huixquila",
    "wof:placetype":"locality",
    "wof:population":109
},
  "geometry": {"coordinates":[-99.79177,18.52283],"type":"Point"}
}