{
  "type": "Feature",
  "properties": {
    "gn:admin1_code":"10",
    "gn:admin2_code":"24.0",
    "gn:asciiname":"Los Corrales",
    "gn:country_code":"MX",
    "gn:dem":1655,
    "gn:feature_class":"P",
    "gn:feature_code":"PPL",
    "gn:name":"Los Corrales",
    "gn:population":0,
    "gn:timezone":"America/Monterrey",
    "iso:country":"MX",
    "name:spa_x_preferred":[
        "Los Corrales"
    ],
    "wof:name":"Los Corrales",
    "wof:placetype":"locality"
},
  "geometry": {"coordinates":[-104.70131000000001,25.1754],"type":"Point"}
}