{
  "type": "Feature",
  "properties": {
    "gn:admin1_code":"19.0",
    "gn:admin2_code":"11.0",
    "gn:asciiname":"El Guayacan",
    "gn:country_code":"MX",
    "gn:dem":332,
    "gn:feature_class":"P",
    "gn:feature_code":"PPL",
    "gn:name":"El Guayac\u00e1n",
    "gn:population":0,
    "gn:timezone":"America/Monterrey",
    "iso:country":"MX",
    "name:spa_x_preferred":[
        "El Guayac\u00e1n"
    ],
    "wof:name":"El Guayacan",
    "wof:placetype":"locality"
},
  "geometry": {"coordinates":[-99.67841,26.09229],"type":"Point"}
}