{
  "type": "Feature",
  "properties": {
    "gn:admin1_code":"26",
    "gn:admin2_code":"51.0",
    "gn:asciiname":"Los Valles",
    "gn:country_code":"MX",
    "gn:dem":472,
    "gn:feature_class":"P",
    "gn:feature_code":"PPL",
    "gn:name":"Los Valles",
    "gn:population":0,
    "gn:timezone":"America/Hermosillo",
    "iso:country":"MX",
    "name:spa_x_preferred":[
        "Los Valles"
    ],
    "name:spa_x_variant":[
        "Rancho Los Valles"
    ],
    "wof:name":"Los Valles",
    "wof:placetype":"locality"
},
  "geometry": {"coordinates":[-109.28937000000001,27.85501],"type":"Point"}
}