{
  "type": "Feature",
  "properties": {
    "gn:admin1_code":"23",
    "gn:admin2_code":"4.0",
    "gn:asciiname":"Xtomoc",
    "gn:country_code":"MX",
    "gn:dem":21,
    "gn:feature_class":"P",
    "gn:feature_code":"PPL",
    "gn:name":"Xtomoc",
    "gn:population":0,
    "gn:timezone":"America/Cancun",
    "iso:country":"MX",
    "name:spa_x_preferred":[
        "Xtomoc"
    ],
    "name:und_x_variant":[
        "Xtocmoc"
    ],
    "wof:name":"Xtomoc",
    "wof:placetype":"locality"
},
  "geometry": {"coordinates":[-88.3045,18.78189],"type":"Point"}
}