{
  "type": "Feature",
  "properties": {
    "gn:admin1_code":"5",
    "gn:admin2_code":"59.0",
    "gn:asciiname":"San Canuto",
    "gn:country_code":"MX",
    "gn:dem":605,
    "gn:feature_class":"P",
    "gn:feature_code":"PPL",
    "gn:name":"San Canuto",
    "gn:population":7,
    "gn:timezone":"America/Mexico_City",
    "iso:country":"MX",
    "wof:name":"San Canuto",
    "wof:placetype":"locality",
    "wof:population":7
},
  "geometry": {"coordinates":[-91.76528,16.90694],"type":"Point"}
}