{
  "type": "Feature",
  "properties": {
    "gn:admin1_code":"30.0",
    "gn:admin2_code":"27.0",
    "gn:asciiname":"Tlatlapango",
    "gn:country_code":"MX",
    "gn:dem":359,
    "gn:feature_class":"P",
    "gn:feature_code":"PPL",
    "gn:name":"Tlatlapango",
    "gn:population":0,
    "gn:timezone":"America/Mexico_City",
    "iso:country":"MX",
    "name:spa_x_preferred":[
        "Tlatlapango"
    ],
    "wof:name":"Tlatlapango",
    "wof:placetype":"locality"
},
  "geometry": {"coordinates":[-98.15501,20.82815],"type":"Point"}
}