{
  "type": "Feature",
  "properties": {
    "gn:admin1_code":"12",
    "gn:admin2_code":"2.0",
    "gn:asciiname":"Ajuatetla",
    "gn:country_code":"MX",
    "gn:dem":1363,
    "gn:feature_class":"P",
    "gn:feature_code":"PPL",
    "gn:name":"Ajuatetla",
    "gn:population":558,
    "gn:timezone":"America/Mexico_City",
    "iso:country":"MX",
    "wof:name":"Ajuatetla",
    "wof:placetype":"locality",
    "wof:population":558
},
  "geometry": {"coordinates":[-99.07444,17.78167000000001],"type":"Point"}
}