{
  "type": "Feature",
  "properties": {
    "gn:admin1_code":"20",
    "gn:admin2_code":"446.0",
    "gn:asciiname":"Carrizalillo",
    "gn:country_code":"MX",
    "gn:dem":1460,
    "gn:feature_class":"P",
    "gn:feature_code":"PPL",
    "gn:name":"Carrizalillo",
    "gn:population":97,
    "gn:timezone":"America/Mexico_City",
    "iso:country":"MX",
    "wof:name":"Carrizalillo",
    "wof:placetype":"locality",
    "wof:population":97
},
  "geometry": {"coordinates":[-97.82277999999999,17.04917],"type":"Point"}
}