{
  "type": "Feature",
  "properties": {
    "gn:admin1_code":"19",
    "gn:admin2_code":"21.0",
    "gn:asciiname":"San Miguel de los Garza",
    "gn:country_code":"MX",
    "gn:dem":586,
    "gn:feature_class":"P",
    "gn:feature_code":"PPL",
    "gn:name":"San Miguel de los Garza",
    "gn:population":0,
    "gn:timezone":"America/Monterrey",
    "iso:country":"MX",
    "name:spa_x_preferred":[
        "San Miguel de los Garza"
    ],
    "name:spa_x_variant":[
        "San Miguel de los Garzas"
    ],
    "name:und_x_variant":[
        "San Miguel De Los Garzo"
    ],
    "wof:name":"San Miguel de los Garza",
    "wof:placetype":"locality"
},
  "geometry": {"coordinates":[-100.41632,25.83023],"type":"Point"}
}