{
  "type": "Feature",
  "properties": {
    "gn:admin1_code":"10",
    "gn:admin2_code":"13.0",
    "gn:asciiname":"Venustiano Carranza (El Seis)",
    "gn:country_code":"MX",
    "gn:dem":1185,
    "gn:feature_class":"P",
    "gn:feature_code":"PPL",
    "gn:name":"Venustiano Carranza (El Seis)",
    "gn:population":74,
    "gn:timezone":"America/Monterrey",
    "iso:country":"MX",
    "wof:name":"Venustiano Carranza (El Seis)",
    "wof:placetype":"locality",
    "wof:population":74
},
  "geometry": {"coordinates":[-104.14646999999999,26.56607],"type":"Point"}
}