{
  "type": "Feature",
  "properties": {
    "gn:admin1_code":"11.0",
    "gn:admin2_code":"14.0",
    "gn:asciiname":"El Tenango",
    "gn:country_code":"MX",
    "gn:dem":1980,
    "gn:feature_class":"P",
    "gn:feature_code":"PPL",
    "gn:name":"El Tenango",
    "gn:population":0,
    "gn:timezone":"America/Mexico_City",
    "iso:country":"MX",
    "wof:name":"El Tenango",
    "wof:placetype":"locality"
},
  "geometry": {"coordinates":[-100.83333,21.21667],"type":"Point"}
}