{
  "type": "Feature",
  "properties": {
    "gn:admin1_code":"26",
    "gn:admin2_code":"42.0",
    "gn:asciiname":"Huirbis",
    "gn:country_code":"MX",
    "gn:dem":71,
    "gn:feature_class":"P",
    "gn:feature_code":"PPL",
    "gn:name":"Huirbis",
    "gn:population":0,
    "gn:timezone":"America/Hermosillo",
    "iso:country":"MX",
    "name:spa_x_preferred":[
        "Huirbis"
    ],
    "wof:name":"Huirbis",
    "wof:placetype":"locality"
},
  "geometry": {"coordinates":[-109.22816,26.75515],"type":"Point"}
}