{
  "type": "Feature",
  "properties": {
    "gn:admin1_code":"5",
    "gn:admin2_code":"27.0",
    "gn:asciiname":"El Vergel",
    "gn:country_code":"MX",
    "gn:dem":409,
    "gn:feature_class":"P",
    "gn:feature_code":"PPL",
    "gn:name":"El Vergel",
    "gn:population":396,
    "gn:timezone":"America/Mexico_City",
    "iso:country":"MX",
    "wof:name":"El Vergel",
    "wof:placetype":"locality",
    "wof:population":396
},
  "geometry": {"coordinates":[-93.01333,16.65056],"type":"Point"}
}