{
  "type": "Feature",
  "properties": {
    "gn:admin1_code":"12",
    "gn:admin2_code":"2",
    "gn:asciiname":"Quimixtepec",
    "gn:country_code":"MX",
    "gn:dem":1621,
    "gn:feature_class":"P",
    "gn:feature_code":"PPL",
    "gn:name":"Quimixtepec",
    "gn:population":10,
    "gn:timezone":"America/Mexico_City",
    "iso:country":"MX",
    "wof:name":"Quimixtepec",
    "wof:placetype":"locality",
    "wof:population":10
},
  "geometry": {"coordinates":[-98.88761,17.73936],"type":"Point"}
}