{
  "type": "Feature",
  "properties": {
    "gn:admin1_code":"28",
    "gn:admin2_code":"2.0",
    "gn:asciiname":"El Gavilan",
    "gn:country_code":"MX",
    "gn:dem":100,
    "gn:feature_class":"P",
    "gn:feature_code":"PPL",
    "gn:name":"El Gavil\u00e1n",
    "gn:population":9,
    "gn:timezone":"America/Monterrey",
    "iso:country":"MX",
    "name:und_x_variant":[
        "El Gavil\u00e1n"
    ],
    "wof:name":"El Gavilan",
    "wof:placetype":"locality",
    "wof:population":9
},
  "geometry": {"coordinates":[-97.8425,23.20389],"type":"Point"}
}