{
  "type": "Feature",
  "properties": {
    "gn:admin1_code":"14",
    "gn:admin2_code":"89.0",
    "gn:asciiname":"San Diego",
    "gn:country_code":"MX",
    "gn:dem":1423,
    "gn:feature_class":"P",
    "gn:feature_code":"PPL",
    "gn:name":"San Diego",
    "gn:population":0,
    "gn:timezone":"America/Mexico_City",
    "iso:country":"MX",
    "wof:name":"San Diego",
    "wof:placetype":"locality"
},
  "geometry": {"coordinates":[-103.55289999999999,20.0992],"type":"Point"}
}