{
  "type": "Feature",
  "properties": {
    "gn:gn_country":"MX",
    "gn:gn_fcode":"PPL",
    "gn:gn_pop":9581,
    "gn:population":9581,
    "iso:country":"MX",
    "name:ceb_x_preferred":[
        "Vista Hermosa"
    ],
    "name:deu_x_preferred":[
        "Vista Hermosa"
    ],
    "name:spa_x_preferred":[
        "Vista Hermosa de Negrete"
    ],
    "name:spa_x_variant":[
        "Vista Hermosa"
    ],
    "name:swe_x_preferred":[
        "Vista Hermosa"
    ],
    "name:unk_x_variant":[
        "Vistahermosa de Negrete"
    ],
    "name:vie_x_preferred":[
        "Vista Hermosa"
    ],
    "qs_pg:aaroncc":"MX",
    "qs_pg:gn_country":"MX",
    "qs_pg:gn_fcode":"PPL",
    "qs_pg:gn_pop":9581,
    "qs_pg:name":"Vista Hermosa",
    "qs_pg:name_adm0":"M\u00e9xico",
    "qs_pg:name_adm1":"Michoacan de Ocampo",
    "qs_pg:photos_9r":0,
    "qs_pg:photos_sr":0,
    "qs_pg:pop_sr":5,
    "qs_pg:qs_pg_placetype":"neighbourhood",
    "qs_pg:qs_pg_placetype_gp":"Suburb",
    "qs_pg:woe_adm0":23424900,
    "woe:adm0_id":23424900,
    "woe:name_adm0":"M\u00e9xico",
    "woe:name_adm1":"Michoacan de Ocampo",
    "woe:placetype":"Suburb",
    "wof:name":"Vista Hermosa",
    "wof:placetype":"neighbourhood",
    "wof:population":9581
},
  "geometry": {"coordinates":[-102.47499999999999,20.27286],"type":"Point"}
}