{
  "type": "Feature",
  "properties": {
    "gn:admin1_code":"26",
    "gn:admin2_code":"56.0",
    "gn:asciiname":"Los Seris",
    "gn:country_code":"MX",
    "gn:dem":424,
    "gn:feature_class":"P",
    "gn:feature_code":"PPL",
    "gn:name":"Los Seris",
    "gn:population":0,
    "gn:timezone":"America/Hermosillo",
    "iso:country":"MX",
    "name:spa_x_preferred":[
        "Los Seris"
    ],
    "wof:name":"Los Seris",
    "wof:placetype":"locality"
},
  "geometry": {"coordinates":[-110.65611,29.55139],"type":"Point"}
}