{
  "type": "Feature",
  "properties": {
    "gn:admin1_code":"18",
    "gn:admin2_code":"17.0",
    "gn:asciiname":"Los Fresnos (Corral de Rivas)",
    "gn:country_code":"MX",
    "gn:dem":921,
    "gn:feature_class":"P",
    "gn:feature_code":"PPL",
    "gn:name":"Los Fresnos (Corral de Rivas)",
    "gn:population":5,
    "gn:timezone":"America/Mazatlan",
    "iso:country":"MX",
    "wof:name":"Los Fresnos (Corral de Rivas)",
    "wof:placetype":"locality",
    "wof:population":5
},
  "geometry": {"coordinates":[-104.84556000000001,21.44528],"type":"Point"}
}