{
  "type": "Feature",
  "properties": {
    "gn:admin1_code":"24.0",
    "gn:admin2_code":"29.0",
    "gn:asciiname":"Ejido Nuevo Temamatla",
    "gn:country_code":"MX",
    "gn:dem":81,
    "gn:feature_class":"P",
    "gn:feature_code":"PPL",
    "gn:name":"Ejido Nuevo Temamatla",
    "gn:population":0,
    "gn:timezone":"America/Mexico_City",
    "iso:country":"MX",
    "name:spa_x_preferred":[
        "Ejido Nuevo Temamatla"
    ],
    "wof:name":"Ejido Nuevo Temamatla",
    "wof:placetype":"locality"
},
  "geometry": {"coordinates":[-98.58828,21.5022],"type":"Point"}
}