{
  "type": "Feature",
  "properties": {
    "gn:admin1_code":"6",
    "gn:admin2_code":"30.0",
    "gn:asciiname":"Rojarabo",
    "gn:country_code":"MX",
    "gn:dem":1616,
    "gn:feature_class":"P",
    "gn:feature_code":"PPL",
    "gn:name":"Rojarabo",
    "gn:population":0,
    "gn:timezone":"America/Chihuahua",
    "iso:country":"MX",
    "name:spa_x_preferred":[
        "Rojarabo"
    ],
    "wof:name":"Rojarabo",
    "wof:placetype":"locality"
},
  "geometry": {"coordinates":[-108.18443000000001,27.47082],"type":"Point"}
}