{
  "type": "Feature",
  "properties": {
    "gn:admin1_code":"6",
    "gn:admin2_code":"5.0",
    "gn:asciiname":"El Montecito",
    "gn:country_code":"MX",
    "gn:dem":1186,
    "gn:feature_class":"P",
    "gn:feature_code":"PPL",
    "gn:name":"El Montecito",
    "gn:population":0,
    "gn:timezone":"America/Chihuahua",
    "iso:country":"MX",
    "wof:name":"El Montecito",
    "wof:placetype":"locality"
},
  "geometry": {"coordinates":[-107.42010999999999,31.29658],"type":"Point"}
}