{
  "type": "Feature",
  "properties": {
    "gn:admin1_code":"30",
    "gn:admin2_code":"174.0",
    "gn:asciiname":"Loma del Caballo",
    "gn:country_code":"MX",
    "gn:dem":52,
    "gn:feature_class":"P",
    "gn:feature_code":"PPL",
    "gn:name":"Loma del Caballo",
    "gn:population":0,
    "gn:timezone":"America/Mexico_City",
    "iso:country":"MX",
    "name:spa_x_preferred":[
        "Loma del Caballo"
    ],
    "wof:name":"Loma del Caballo",
    "wof:placetype":"locality"
},
  "geometry": {"coordinates":[-96.2778,18.57133],"type":"Point"}
}