{
  "type": "Feature",
  "properties": {
    "gn:admin1_code":"25.0",
    "gn:admin2_code":"6.0",
    "gn:asciiname":"Valle del Sol",
    "gn:country_code":"MX",
    "gn:dem":76,
    "gn:feature_class":"P",
    "gn:feature_code":"PPL",
    "gn:name":"Valle del Sol",
    "gn:population":0,
    "gn:timezone":"America/Mazatlan",
    "iso:country":"MX",
    "name:spa_x_preferred":[
        "Valle del Sol"
    ],
    "wof:name":"Valle del Sol",
    "wof:placetype":"locality"
},
  "geometry": {"coordinates":[-107.47113,24.88543],"type":"Point"}
}