{
  "type": "Feature",
  "properties": {
    "gn:admin1_code":"30.0",
    "gn:admin2_code":"133.0",
    "gn:asciiname":"El Janito",
    "gn:country_code":"MX",
    "gn:dem":9,
    "gn:feature_class":"P",
    "gn:feature_code":"PPL",
    "gn:name":"El Janito",
    "gn:population":6,
    "gn:timezone":"America/Mexico_City",
    "iso:country":"MX",
    "name:spa_x_preferred":[
        "El Janito"
    ],
    "wof:name":"El Janito",
    "wof:placetype":"locality",
    "wof:population":6
},
  "geometry": {"coordinates":[-98.03833,22.115],"type":"Point"}
}