{
  "type": "Feature",
  "properties": {
    "gn:admin1_code":"32",
    "gn:admin2_code":"17.0",
    "gn:asciiname":"De la Riva",
    "gn:country_code":"MX",
    "gn:dem":2302,
    "gn:feature_class":"P",
    "gn:feature_code":"PPL",
    "gn:name":"De la Riva",
    "gn:population":6,
    "gn:timezone":"America/Mexico_City",
    "iso:country":"MX",
    "wof:name":"De la Riva",
    "wof:placetype":"locality",
    "wof:population":6
},
  "geometry": {"coordinates":[-102.48166999999999,22.63083],"type":"Point"}
}