{
  "type": "Feature",
  "properties": {
    "gn:admin1_code":"5",
    "gn:admin2_code":"6",
    "gn:asciiname":"El Relicario",
    "gn:country_code":"MX",
    "gn:dem":879,
    "gn:feature_class":"P",
    "gn:feature_code":"PPL",
    "gn:name":"El Relicario",
    "gn:population":23,
    "gn:timezone":"America/Mexico_City",
    "iso:country":"MX",
    "wof:name":"El Relicario",
    "wof:placetype":"locality",
    "wof:population":23
},
  "geometry": {"coordinates":[-92.09611,15.56278],"type":"Point"}
}