{
  "type": "Feature",
  "properties": {
    "gn:admin1_code":"5",
    "gn:admin2_code":"108",
    "gn:asciiname":"El Laurel",
    "gn:country_code":"MX",
    "gn:dem":671,
    "gn:feature_class":"P",
    "gn:feature_code":"PPL",
    "gn:name":"El Laurel",
    "gn:population":10,
    "gn:timezone":"America/Mexico_City",
    "iso:country":"MX",
    "wof:name":"El Laurel",
    "wof:placetype":"locality",
    "wof:population":10
},
  "geometry": {"coordinates":[-93.42972,16.32194],"type":"Point"}
}