{
  "type": "Feature",
  "properties": {
    "gn:admin1_code":"30.0",
    "gn:admin2_code":"175.0",
    "gn:asciiname":"San Francisco",
    "gn:country_code":"MX",
    "gn:dem":117,
    "gn:feature_class":"P",
    "gn:feature_code":"PPL",
    "gn:name":"San Francisco",
    "gn:population":13,
    "gn:timezone":"America/Mexico_City",
    "iso:country":"MX",
    "name:spa_x_preferred":[
        "San Francisco"
    ],
    "wof:name":"San Francisco",
    "wof:placetype":"locality",
    "wof:population":13
},
  "geometry": {"coordinates":[-97.55167,20.72111],"type":"Point"}
}