{
  "type": "Feature",
  "properties": {
    "gn:admin1_code":"28.0",
    "gn:admin2_code":"35.0",
    "gn:asciiname":"Palos Altos",
    "gn:country_code":"MX",
    "gn:dem":23,
    "gn:feature_class":"P",
    "gn:feature_code":"PPL",
    "gn:name":"Palos Altos",
    "gn:population":0,
    "gn:timezone":"America/Monterrey",
    "iso:country":"MX",
    "name:spa_x_preferred":[
        "Palos Altos"
    ],
    "wof:name":"Palos Altos",
    "wof:placetype":"locality"
},
  "geometry": {"coordinates":[-98.05556,24.73722],"type":"Point"}
}