{
  "type": "Feature",
  "properties": {
    "gn:admin1_code":"11",
    "gn:admin2_code":"15.0",
    "gn:asciiname":"Santa Catarina de Cuevas (El Tinaco)",
    "gn:cc2":"MX",
    "gn:country_code":"MX",
    "gn:dem":1866,
    "gn:feature_class":"P",
    "gn:feature_code":"PPL",
    "gn:name":"Santa Catarina de Cuevas (El Tinaco)",
    "gn:population":769,
    "gn:timezone":"America/Mexico_City",
    "iso:country":"MX",
    "name:und_x_variant":[
        "Santa Catarina",
        "Santa Catarina de Cuevas"
    ],
    "wof:name":"Santa Catarina de Cuevas (El Tinaco)",
    "wof:placetype":"locality",
    "wof:population":769
},
  "geometry": {"coordinates":[-101.29806000000001,20.93778],"type":"Point"}
}