{
  "type": "Feature",
  "properties": {
    "gn:admin1_code":"20",
    "gn:admin2_code":"504.0",
    "gn:asciiname":"Santiago Zooquiapam",
    "gn:country_code":"MX",
    "gn:dem":1873,
    "gn:feature_class":"P",
    "gn:feature_code":"PPL",
    "gn:name":"Santiago Zooquiapam",
    "gn:population":0,
    "gn:timezone":"America/Mexico_City",
    "iso:country":"MX",
    "name:spa_x_preferred":[
        "Santiago Zoqui\u00e1pam"
    ],
    "name:spa_x_variant":[
        "Santiago Zooquiapam"
    ],
    "name:und_x_variant":[
        "Zoquiapan",
        "Santiago Zoquiapan",
        "Zoquiapam",
        "Santiago"
    ],
    "wof:name":"Santiago Zooquiapam",
    "wof:placetype":"locality"
},
  "geometry": {"coordinates":[-96.61877,17.30121],"type":"Point"}
}