{
  "type": "Feature",
  "properties": {
    "gn:admin1_code":"12",
    "gn:admin2_code":"34.0",
    "gn:asciiname":"El Guayabal",
    "gn:country_code":"MX",
    "gn:dem":1489,
    "gn:feature_class":"P",
    "gn:feature_code":"PPL",
    "gn:name":"El Guayabal",
    "gn:population":1,
    "gn:timezone":"America/Mexico_City",
    "iso:country":"MX",
    "wof:name":"El Guayabal",
    "wof:placetype":"locality",
    "wof:population":1
},
  "geometry": {"coordinates":[-99.26752,18.32465],"type":"Point"}
}