{
  "type": "Feature",
  "properties": {
    "gn:admin1_code":"11",
    "gn:admin2_code":"1.0",
    "gn:asciiname":"Barrio Nuevo de Santa Barbara",
    "gn:country_code":"MX",
    "gn:dem":1689,
    "gn:feature_class":"P",
    "gn:feature_code":"PPL",
    "gn:name":"Barrio Nuevo de Santa B\u00e1rbara",
    "gn:population":6,
    "gn:timezone":"America/Mexico_City",
    "iso:country":"MX",
    "name:und_x_variant":[
        "Barrio Nuevo de Santa B\u00e1rbara"
    ],
    "wof:name":"Barrio Nuevo de Santa Barbara",
    "wof:placetype":"locality",
    "wof:population":6
},
  "geometry": {"coordinates":[-101.59611,20.51611],"type":"Point"}
}