{
  "type": "Feature",
  "properties": {
    "gn:admin1_code":"18.0",
    "gn:admin2_code":"11.0",
    "gn:asciiname":"El Taixte",
    "gn:cc2":"MX",
    "gn:country_code":"MX",
    "gn:dem":281,
    "gn:feature_class":"P",
    "gn:feature_code":"PPL",
    "gn:name":"El Taixte",
    "gn:population":31,
    "gn:timezone":"America/Mazatlan",
    "iso:country":"MX",
    "name:und_x_variant":[
        "El Taiste",
        "El Taixte"
    ],
    "wof:name":"El Taixte",
    "wof:placetype":"locality",
    "wof:population":31
},
  "geometry": {"coordinates":[-104.95833,21.94028],"type":"Point"}
}