{
  "type": "Feature",
  "properties": {
    "gn:admin1_code":"31.0",
    "gn:asciiname":"Yokdzonot Regadio",
    "gn:country_code":"MX",
    "gn:dem":23,
    "gn:feature_class":"P",
    "gn:feature_code":"PPL",
    "gn:name":"Yokdzonot Regad\u00edo",
    "gn:population":0,
    "gn:timezone":"America/Merida",
    "iso:country":"MX",
    "name:spa_x_preferred":[
        "Yokdzonot Regad\u00edo"
    ],
    "name:spa_x_variant":[
        "Yohdzonot Regad\u00edo"
    ],
    "wof:name":"Yokdzonot Regadio",
    "wof:placetype":"locality"
},
  "geometry": {"coordinates":[-88.05653000000002,21.08115],"type":"Point"}
}