{
  "type": "Feature",
  "properties": {
    "gn:admin1_code":"14",
    "gn:admin2_code":"90",
    "gn:asciiname":"Cofradia de los Coyotes",
    "gn:country_code":"MX",
    "gn:dem":1471,
    "gn:feature_class":"P",
    "gn:feature_code":"PPL",
    "gn:name":"Cofrad\u00eda de los Coyotes",
    "gn:population":23,
    "gn:timezone":"America/Mexico_City",
    "iso:country":"MX",
    "name:und_x_variant":[
        "Cofrad\u00eda de los Coyotes"
    ],
    "wof:name":"Cofradia de los Coyotes",
    "wof:placetype":"locality",
    "wof:population":23
},
  "geometry": {"coordinates":[-104.15944,20.18722],"type":"Point"}
}