{
  "type": "Feature",
  "properties": {
    "gn:admin1_code":"18",
    "gn:admin2_code":"20.0",
    "gn:asciiname":"Zuya",
    "gn:country_code":"MX",
    "gn:dem":78,
    "gn:feature_class":"P",
    "gn:feature_code":"PPL",
    "gn:name":"Zuya",
    "gn:population":7,
    "gn:timezone":"America/Bahia_Banderas",
    "iso:country":"MX",
    "wof:name":"Zuya",
    "wof:placetype":"locality",
    "wof:population":7
},
  "geometry": {"coordinates":[-105.37582999999999,20.91472000000001],"type":"Point"}
}