{
  "type": "Feature",
  "properties": {
    "gn:admin1_code":"12",
    "gn:admin2_code":"1.0",
    "gn:asciiname":"Pueblo Madero",
    "gn:country_code":"MX",
    "gn:dem":419,
    "gn:feature_class":"P",
    "gn:feature_code":"PPL",
    "gn:name":"Pueblo Madero",
    "gn:population":0,
    "gn:timezone":"America/Mexico_City",
    "iso:country":"MX",
    "name:spa_x_preferred":[
        "Pueblo Madero"
    ],
    "name:spa_x_variant":[
        "El Play\u00f3n"
    ],
    "wof:name":"Pueblo Madero",
    "wof:placetype":"locality"
},
  "geometry": {"coordinates":[-99.67225000000001,17.12688],"type":"Point"}
}