{
  "type": "Feature",
  "properties": {
    "gn:admin1_code":"30",
    "gn:admin2_code":"150.0",
    "gn:asciiname":"La Caridad",
    "gn:country_code":"MX",
    "gn:dem":36,
    "gn:feature_class":"P",
    "gn:feature_code":"PPL",
    "gn:name":"La Caridad",
    "gn:population":5,
    "gn:timezone":"America/Mexico_City",
    "iso:country":"MX",
    "name:ast_x_preferred":[
        "A Carid\u00e1"
    ],
    "name:deu_x_preferred":[
        "La Caridad"
    ],
    "name:spa_x_preferred":[
        "La Caridad"
    ],
    "name:urd_x_preferred":[
        "\u0644\u0627 \u06a9\u0627\u0631\u06cc\u0688\u0627\u0688"
    ],
    "wof:name":"La Caridad",
    "wof:placetype":"locality",
    "wof:population":5
},
  "geometry": {"coordinates":[-97.74194,21.47667],"type":"Point"}
}