{
  "type": "Feature",
  "properties": {
    "gn:admin1_code":"20",
    "gn:admin2_code":"110.0",
    "gn:asciiname":"Loma de Juarez",
    "gn:country_code":"MX",
    "gn:dem":2514,
    "gn:feature_class":"P",
    "gn:feature_code":"PPL",
    "gn:name":"Loma de Ju\u00e1rez",
    "gn:population":89,
    "gn:timezone":"America/Mexico_City",
    "iso:country":"MX",
    "name:und_x_variant":[
        "Loma de Ju\u00e1rez"
    ],
    "wof:name":"Loma de Juarez",
    "wof:placetype":"locality",
    "wof:population":89
},
  "geometry": {"coordinates":[-97.58,17.125],"type":"Point"}
}