{
  "type": "Feature",
  "properties": {
    "gn:admin1_code":"13",
    "gn:admin2_code":"68",
    "gn:asciiname":"Piedra Ancha",
    "gn:country_code":"MX",
    "gn:dem":1222,
    "gn:feature_class":"P",
    "gn:feature_code":"PPL",
    "gn:name":"Piedra Ancha",
    "gn:population":17,
    "gn:timezone":"America/Mexico_City",
    "iso:country":"MX",
    "wof:name":"Piedra Ancha",
    "wof:placetype":"locality",
    "wof:population":17
},
  "geometry": {"coordinates":[-98.53389,20.80389],"type":"Point"}
}