{
  "type": "Feature",
  "properties": {
    "gn:admin1_code":"6.0",
    "gn:admin2_code":"30.0",
    "gn:asciiname":"Guachajure",
    "gn:country_code":"MX",
    "gn:dem":682,
    "gn:feature_class":"P",
    "gn:feature_code":"PPL",
    "gn:name":"Guachajure",
    "gn:population":0,
    "gn:timezone":"America/Chihuahua",
    "iso:country":"MX",
    "name:spa_x_preferred":[
        "Guachajure"
    ],
    "name:und_x_variant":[
        "Huachajuri"
    ],
    "wof:name":"Guachajure",
    "wof:placetype":"locality"
},
  "geometry": {"coordinates":[-108.30186999999999,27.52461],"type":"Point"}
}