{
  "type": "Feature",
  "properties": {
    "gn:admin1_code":"5",
    "gn:admin2_code":"17.0",
    "gn:asciiname":"San Marcos",
    "gn:country_code":"MX",
    "gn:dem":667,
    "gn:feature_class":"P",
    "gn:feature_code":"PPL",
    "gn:name":"San Marcos",
    "gn:population":165,
    "gn:timezone":"America/Mexico_City",
    "iso:country":"MX",
    "wof:name":"San Marcos",
    "wof:placetype":"locality",
    "wof:population":165
},
  "geometry": {"coordinates":[-93.85472,16.50917],"type":"Point"}
}