{
  "type": "Feature",
  "properties": {
    "gn:admin1_code":"32.0",
    "gn:admin2_code":"14.0",
    "gn:asciiname":"Francisco I. Madero",
    "gn:country_code":"MX",
    "gn:dem":1838,
    "gn:feature_class":"P",
    "gn:feature_code":"PPL",
    "gn:name":"Francisco I. Madero",
    "gn:population":0,
    "gn:timezone":"America/Mexico_City",
    "iso:country":"MX",
    "name:spa_x_preferred":[
        "Francisco I. Madero"
    ],
    "name:und_x_variant":[
        "El Molino",
        "Colonia Madero"
    ],
    "wof:name":"Francisco I. Madero",
    "wof:placetype":"locality"
},
  "geometry": {"coordinates":[-102.95396,23.93109],"type":"Point"}
}