{
  "type": "Feature",
  "properties": {
    "gn:admin1_code":"20.0",
    "gn:admin2_code":"504.0",
    "gn:asciiname":"Nuevo Zooquiapam",
    "gn:country_code":"MX",
    "gn:dem":2089,
    "gn:feature_class":"P",
    "gn:feature_code":"PPL",
    "gn:name":"Nuevo Zooquiapam",
    "gn:population":0,
    "gn:timezone":"America/Mexico_City",
    "iso:country":"MX",
    "name:spa_x_preferred":[
        "Nuevo Zooquiapam"
    ],
    "wof:name":"Nuevo Zooquiapam",
    "wof:placetype":"locality"
},
  "geometry": {"coordinates":[-96.62066,17.28893],"type":"Point"}
}