{
  "type": "Feature",
  "properties": {
    "gn:admin1_code":"10",
    "gn:admin2_code":"35",
    "gn:asciiname":"El Cebollin",
    "gn:country_code":"MX",
    "gn:dem":2173,
    "gn:feature_class":"P",
    "gn:feature_code":"PPL",
    "gn:name":"El Ceboll\u00edn",
    "gn:population":12,
    "gn:timezone":"America/Monterrey",
    "iso:country":"MX",
    "name:und_x_variant":[
        "El Ceboll\u00edn"
    ],
    "wof:name":"El Cebollin",
    "wof:placetype":"locality",
    "wof:population":12
},
  "geometry": {"coordinates":[-106.13065,25.60901],"type":"Point"}
}