{
  "type": "Feature",
  "properties": {
    "gn:admin1_code":"29",
    "gn:admin2_code":"27.0",
    "gn:asciiname":"El Puente",
    "gn:country_code":"MX",
    "gn:dem":2274,
    "gn:feature_class":"P",
    "gn:feature_code":"PPL",
    "gn:name":"El Puente",
    "gn:population":70,
    "gn:timezone":"America/Mexico_City",
    "iso:country":"MX",
    "name:ceb_x_preferred":[
        "El Puente"
    ],
    "name:deu_x_preferred":[
        "El Puente"
    ],
    "name:ita_x_preferred":[
        "El Puente"
    ],
    "name:nld_x_preferred":[
        "El Puente"
    ],
    "name:pol_x_preferred":[
        "El Puente"
    ],
    "name:spa_x_preferred":[
        "El Puente"
    ],
    "name:srp_x_preferred":[
        "\u0415\u043b \u041f\u0443\u0435\u043d\u0442\u0435"
    ],
    "name:swe_x_preferred":[
        "El Puente"
    ],
    "wof:name":"El Puente",
    "wof:placetype":"locality",
    "wof:population":70
},
  "geometry": {"coordinates":[-98.19148,19.14064],"type":"Point"}
}