{
  "type": "Feature",
  "properties": {
    "gn:admin1_code":"6.0",
    "gn:admin2_code":"7.0",
    "gn:asciiname":"Los Lamentos",
    "gn:country_code":"MX",
    "gn:dem":2664,
    "gn:feature_class":"P",
    "gn:feature_code":"PPL",
    "gn:name":"Los Lamentos",
    "gn:population":0,
    "gn:timezone":"America/Chihuahua",
    "iso:country":"MX",
    "name:spa_x_preferred":[
        "Los Lamentos"
    ],
    "wof:name":"Los Lamentos",
    "wof:placetype":"locality"
},
  "geometry": {"coordinates":[-106.46102,26.33298],"type":"Point"}
}