{
  "type": "Feature",
  "properties": {
    "gn:admin1_code":"5",
    "gn:admin2_code":"92.0",
    "gn:asciiname":"Las Almendras (Las Laminas)",
    "gn:country_code":"MX",
    "gn:dem":231,
    "gn:feature_class":"P",
    "gn:feature_code":"PPL",
    "gn:name":"Las Almendras (Las L\u00e1minas)",
    "gn:population":60,
    "gn:timezone":"America/Mexico_City",
    "iso:country":"MX",
    "name:und_x_variant":[
        "Las Almendras (Las L\u00e1minas)"
    ],
    "wof:name":"Las Almendras (Las Laminas)",
    "wof:placetype":"locality",
    "wof:population":60
},
  "geometry": {"coordinates":[-93.52889,17.17611],"type":"Point"}
}