{
  "type": "Feature",
  "properties": {
    "gn:admin1_code":"21",
    "gn:admin2_code":"43.0",
    "gn:asciiname":"Zopilotepec",
    "gn:country_code":"MX",
    "gn:dem":233,
    "gn:feature_class":"P",
    "gn:feature_code":"PPL",
    "gn:name":"Zopilotepec",
    "gn:population":202,
    "gn:timezone":"America/Mexico_City",
    "iso:country":"MX",
    "wof:name":"Zopilotepec",
    "wof:placetype":"locality",
    "wof:population":202
},
  "geometry": {"coordinates":[-97.48690000000001,20.09646],"type":"Point"}
}