{
  "type": "Feature",
  "properties": {
    "gn:admin1_code":"28",
    "gn:admin2_code":"35.0",
    "gn:asciiname":"Los Alamos",
    "gn:country_code":"MX",
    "gn:dem":110,
    "gn:feature_class":"P",
    "gn:feature_code":"PPL",
    "gn:name":"Los \u00c1lamos",
    "gn:population":0,
    "gn:timezone":"America/Monterrey",
    "iso:country":"MX",
    "name:ceb_x_preferred":[
        "Los Alamos"
    ],
    "name:deu_x_preferred":[
        "Los Alamos"
    ],
    "name:nld_x_preferred":[
        "Los Alamos"
    ],
    "name:pol_x_preferred":[
        "Los Alamos"
    ],
    "name:por_x_preferred":[
        "Los Alamos"
    ],
    "name:rus_x_preferred":[
        "\u041b\u043e\u0441-\u0410\u043b\u0430\u043c\u043e\u0441"
    ],
    "name:spa_x_preferred":[
        "Los \u00c1lamos"
    ],
    "name:swe_x_preferred":[
        "Los Alamos"
    ],
    "name:tur_x_preferred":[
        "Los Alamos"
    ],
    "name:ukr_x_preferred":[
        "\u041b\u043e\u0441-\u0410\u043b\u0430\u043c\u043e\u0441"
    ],
    "name:vie_x_preferred":[
        "Los Alamos"
    ],
    "name:vol_x_preferred":[
        "Los Alamos"
    ],
    "wof:name":"Los Alamos",
    "wof:placetype":"locality"
},
  "geometry": {"coordinates":[-98.30531000000001,25.09396],"type":"Point"}
}