{
  "type": "Feature",
  "properties": {
    "gn:admin1_code":"30.0",
    "gn:admin2_code":"121.0",
    "gn:asciiname":"El Capricho",
    "gn:country_code":"MX",
    "gn:dem":34,
    "gn:feature_class":"P",
    "gn:feature_code":"PPL",
    "gn:name":"El Capricho",
    "gn:population":2,
    "gn:timezone":"America/Mexico_City",
    "iso:country":"MX",
    "name:spa_x_preferred":[
        "El Capricho"
    ],
    "wof:name":"El Capricho",
    "wof:placetype":"locality",
    "wof:population":2
},
  "geometry": {"coordinates":[-98.06417,21.68806],"type":"Point"}
}