{
  "type": "Feature",
  "properties": {
    "gn:admin1_code":"32",
    "gn:admin2_code":"31",
    "gn:asciiname":"El Bajio",
    "gn:country_code":"MX",
    "gn:dem":1785,
    "gn:feature_class":"P",
    "gn:feature_code":"PPL",
    "gn:name":"El Baj\u00edo",
    "gn:population":16,
    "gn:timezone":"America/Mexico_City",
    "iso:country":"MX",
    "name:und_x_variant":[
        "El Baj\u00edo"
    ],
    "wof:name":"El Bajio",
    "wof:placetype":"locality",
    "wof:population":16
},
  "geometry": {"coordinates":[-103.63083,22.14333],"type":"Point"}
}