{
  "type": "Feature",
  "properties": {
    "gn:admin1_code":"24.0",
    "gn:admin2_code":"16.0",
    "gn:asciiname":"Bonifacio Morato",
    "gn:country_code":"MX",
    "gn:dem":44,
    "gn:feature_class":"P",
    "gn:feature_code":"PPL",
    "gn:name":"Bonifacio Morato",
    "gn:population":0,
    "gn:timezone":"America/Mexico_City",
    "iso:country":"MX",
    "name:spa_x_preferred":[
        "Bonifacio Morato"
    ],
    "wof:name":"Bonifacio Morato",
    "wof:placetype":"locality"
},
  "geometry": {"coordinates":[-98.46302,22.26613],"type":"Point"}
}