{
  "type": "Feature",
  "properties": {
    "gn:admin1_code":"1",
    "gn:admin2_code":"1",
    "gn:asciiname":"El Ciervo [Rancho]",
    "gn:country_code":"MX",
    "gn:dem":1858,
    "gn:feature_class":"P",
    "gn:feature_code":"PPL",
    "gn:name":"El Ciervo [Rancho]",
    "gn:population":24,
    "gn:timezone":"America/Mexico_City",
    "iso:country":"MX",
    "wof:name":"El Ciervo [Rancho]",
    "wof:placetype":"locality",
    "wof:population":24
},
  "geometry": {"coordinates":[-102.32722,21.70222],"type":"Point"}
}