{
  "type": "Feature",
  "properties": {
    "gn:admin1_code":"2",
    "gn:admin2_code":"2",
    "gn:asciiname":"Columbina (Colonia Silva la Huaracha)",
    "gn:country_code":"MX",
    "gn:dem":21,
    "gn:feature_class":"P",
    "gn:feature_code":"PPL",
    "gn:name":"Columbina (Colonia Silva la Huaracha)",
    "gn:population":32,
    "gn:timezone":"America/Tijuana",
    "iso:country":"MX",
    "wof:name":"Columbina (Colonia Silva la Huaracha)",
    "wof:placetype":"locality",
    "wof:population":32
},
  "geometry": {"coordinates":[-114.9875,32.425],"type":"Point"}
}