{
  "type": "Feature",
  "properties": {
    "gn:admin1_code":"12.0",
    "gn:admin2_code":"14.0",
    "gn:asciiname":"El Tomatal",
    "gn:country_code":"MX",
    "gn:dem":22,
    "gn:feature_class":"P",
    "gn:feature_code":"PPL",
    "gn:name":"El Tomatal",
    "gn:population":0,
    "gn:timezone":"America/Mexico_City",
    "iso:country":"MX",
    "name:und_x_variant":[
        "Tomatal",
        "El Tomatal"
    ],
    "wof:name":"El Tomatal",
    "wof:placetype":"locality"
},
  "geometry": {"coordinates":[-100.42784,17.14062],"type":"Point"}
}