{
  "type": "Feature",
  "properties": {
    "gn:admin1_code":"5.0",
    "gn:admin2_code":"57.0",
    "gn:asciiname":"Piedra Redonda",
    "gn:country_code":"MX",
    "gn:dem":629,
    "gn:feature_class":"P",
    "gn:feature_code":"PPL",
    "gn:name":"Piedra Redonda",
    "gn:population":0,
    "gn:timezone":"America/Mexico_City",
    "iso:country":"MX",
    "name:spa_x_preferred":[
        "Piedra Redonda"
    ],
    "wof:name":"Piedra Redonda",
    "wof:placetype":"locality"
},
  "geometry": {"coordinates":[-92.38884,15.27765],"type":"Point"}
}