{
  "type": "Feature",
  "properties": {
    "gn:admin1_code":"18.0",
    "gn:admin2_code":"19.0",
    "gn:asciiname":"Puerto las Tapias",
    "gn:country_code":"MX",
    "gn:dem":1397,
    "gn:feature_class":"P",
    "gn:feature_code":"PPL",
    "gn:name":"Puerto las Tapias",
    "gn:population":0,
    "gn:timezone":"America/Mazatlan",
    "iso:country":"MX",
    "name:spa_x_preferred":[
        "Puerto las Tapias"
    ],
    "wof:name":"Puerto las Tapias",
    "wof:placetype":"locality"
},
  "geometry": {"coordinates":[-104.21677,21.25899],"type":"Point"}
}