{
  "type": "Feature",
  "properties": {
    "gn:admin1_code":"5.0",
    "gn:admin2_code":"57.0",
    "gn:asciiname":"El Potrerillo",
    "gn:country_code":"MX",
    "gn:dem":1586,
    "gn:feature_class":"P",
    "gn:feature_code":"PPL",
    "gn:name":"El Potrerillo",
    "gn:population":0,
    "gn:timezone":"America/Mexico_City",
    "iso:country":"MX",
    "name:spa_x_preferred":[
        "El Potrerillo"
    ],
    "wof:name":"El Potrerillo",
    "wof:placetype":"locality"
},
  "geometry": {"coordinates":[-92.2701,15.27393],"type":"Point"}
}