{
  "type": "Feature",
  "properties": {
    "gn:admin1_code":"30",
    "gn:admin2_code":"134.0",
    "gn:asciiname":"Rincon Panal",
    "gn:country_code":"MX",
    "gn:dem":358,
    "gn:feature_class":"P",
    "gn:feature_code":"PPL",
    "gn:name":"Rinc\u00f3n Panal",
    "gn:population":222,
    "gn:timezone":"America/Mexico_City",
    "iso:country":"MX",
    "wof:name":"Rincon Panal",
    "wof:placetype":"locality",
    "wof:population":222
},
  "geometry": {"coordinates":[-96.61583,19.25889],"type":"Point"}
}