{
  "type": "Feature",
  "properties": {
    "gn:admin1_code":"10",
    "gn:admin2_code":"7.0",
    "gn:asciiname":"Ana",
    "gn:country_code":"MX",
    "gn:dem":1121,
    "gn:feature_class":"P",
    "gn:feature_code":"PPL",
    "gn:name":"Ana",
    "gn:population":0,
    "gn:timezone":"America/Monterrey",
    "iso:country":"MX",
    "name:spa_x_preferred":[
        "Ana"
    ],
    "wof:name":"Ana",
    "wof:placetype":"locality"
},
  "geometry": {"coordinates":[-103.50082999999999,25.65134],"type":"Point"}
}