{
  "type": "Feature",
  "properties": {
    "gn:admin1_code":"21",
    "gn:admin2_code":"114.0",
    "gn:asciiname":"Huiloac",
    "gn:country_code":"MX",
    "gn:dem":2597,
    "gn:feature_class":"P",
    "gn:feature_code":"PPL",
    "gn:name":"Huiloac",
    "gn:population":6,
    "gn:timezone":"America/Mexico_City",
    "iso:country":"MX",
    "wof:name":"Huiloac",
    "wof:placetype":"locality",
    "wof:population":6
},
  "geometry": {"coordinates":[-98.07858,19.1343],"type":"Point"}
}