{
  "type": "Feature",
  "properties": {
    "gn:admin1_code":"5",
    "gn:admin2_code":"20.0",
    "gn:asciiname":"Calzada Redonda",
    "gn:country_code":"MX",
    "gn:dem":553,
    "gn:feature_class":"P",
    "gn:feature_code":"PPL",
    "gn:name":"Calzada Redonda",
    "gn:population":0,
    "gn:timezone":"America/Mexico_City",
    "iso:country":"MX",
    "name:spa_x_preferred":[
        "Calzada Redonda"
    ],
    "name:und_x_variant":[
        "Galzada Redonda"
    ],
    "wof:name":"Calzada Redonda",
    "wof:placetype":"locality"
},
  "geometry": {"coordinates":[-92.51011,15.98353],"type":"Point"}
}