{
  "type": "Feature",
  "properties": {
    "gn:admin1_code":"2",
    "gn:admin2_code":"1.0",
    "gn:asciiname":"El Mangle",
    "gn:country_code":"MX",
    "gn:dem":105,
    "gn:feature_class":"P",
    "gn:feature_code":"PPL",
    "gn:name":"El Mangle",
    "gn:population":5,
    "gn:timezone":"America/Tijuana",
    "iso:country":"MX",
    "wof:name":"El Mangle",
    "wof:placetype":"locality",
    "wof:population":5
},
  "geometry": {"coordinates":[-116.5325,31.68861],"type":"Point"}
}