{
  "type": "Feature",
  "properties": {
    "gn:admin1_code":"10",
    "gn:admin2_code":"26.0",
    "gn:asciiname":"Piedra Rajada",
    "gn:country_code":"MX",
    "gn:dem":2591,
    "gn:feature_class":"P",
    "gn:feature_code":"PPL",
    "gn:name":"Piedra Rajada",
    "gn:population":64,
    "gn:timezone":"America/Monterrey",
    "iso:country":"MX",
    "wof:name":"Piedra Rajada",
    "wof:placetype":"locality",
    "wof:population":64
},
  "geometry": {"coordinates":[-105.7042,24.08945],"type":"Point"}
}