{
  "type": "Feature",
  "properties": {
    "gn:admin1_code":"24",
    "gn:admin2_code":"37.0",
    "gn:asciiname":"Rio Claro (Las Adjuntas)",
    "gn:country_code":"MX",
    "gn:dem":154,
    "gn:feature_class":"P",
    "gn:feature_code":"PPL",
    "gn:name":"R\u00edo Claro (Las Adjuntas)",
    "gn:population":60,
    "gn:timezone":"America/Mexico_City",
    "iso:country":"MX",
    "name:und_x_variant":[
        "R\u00edo Claro (Las Adjuntas)"
    ],
    "wof:name":"Rio Claro (Las Adjuntas)",
    "wof:placetype":"locality",
    "wof:population":60
},
  "geometry": {"coordinates":[-98.75417,21.22139],"type":"Point"}
}