{
  "type": "Feature",
  "properties": {
    "gn:admin1_code":"6",
    "gn:admin2_code":"2.0",
    "gn:asciiname":"Placer de Guadalupe",
    "gn:cc2":"MX",
    "gn:country_code":"MX",
    "gn:dem":1424,
    "gn:feature_class":"P",
    "gn:feature_code":"PPL",
    "gn:name":"Placer de Guadalupe",
    "gn:population":168,
    "gn:timezone":"America/Chihuahua",
    "iso:country":"MX",
    "name:und_x_variant":[
        "Guadalupe",
        "Placer de Guadalupe"
    ],
    "wof:name":"Placer de Guadalupe",
    "wof:placetype":"locality",
    "wof:population":168
},
  "geometry": {"coordinates":[-105.38028,29.16194],"type":"Point"}
}