{
  "type": "Feature",
  "properties": {
    "gn:admin1_code":"5",
    "gn:admin2_code":"32.0",
    "gn:asciiname":"La Alianza",
    "gn:country_code":"MX",
    "gn:dem":293,
    "gn:feature_class":"P",
    "gn:feature_code":"PPL",
    "gn:name":"La Alianza",
    "gn:population":63,
    "gn:timezone":"America/Mexico_City",
    "iso:country":"MX",
    "wof:name":"La Alianza",
    "wof:placetype":"locality",
    "wof:population":63
},
  "geometry": {"coordinates":[-92.58526000000001,15.35598],"type":"Point"}
}