{
  "type": "Feature",
  "properties": {
    "gn:admin1_code":"20",
    "gn:admin2_code":"244.0",
    "gn:asciiname":"Capultitla",
    "gn:country_code":"MX",
    "gn:dem":2026,
    "gn:feature_class":"P",
    "gn:feature_code":"PPL",
    "gn:name":"Capultitla",
    "gn:population":0,
    "gn:timezone":"America/Mexico_City",
    "iso:country":"MX",
    "name:spa_x_preferred":[
        "Capultitla"
    ],
    "wof:name":"Capultitla",
    "wof:placetype":"locality"
},
  "geometry": {"coordinates":[-97.00744,18.13471],"type":"Point"}
}