{
  "type": "Feature",
  "properties": {
    "gn:admin1_code":"2",
    "gn:admin2_code":"4",
    "gn:asciiname":"Rancho Indi",
    "gn:country_code":"MX",
    "gn:dem":156,
    "gn:feature_class":"P",
    "gn:feature_code":"PPL",
    "gn:name":"Rancho Indi",
    "gn:population":17,
    "gn:timezone":"America/Tijuana",
    "iso:country":"MX",
    "wof:name":"Rancho Indi",
    "wof:placetype":"locality",
    "wof:population":17
},
  "geometry": {"coordinates":[-116.905,32.4425],"type":"Point"}
}