{
  "type": "Feature",
  "properties": {
    "gn:admin1_code":"24",
    "gn:admin2_code":"49.0",
    "gn:asciiname":"Villa de Ramos",
    "gn:country_code":"MX",
    "gn:dem":2206,
    "gn:feature_class":"P",
    "gn:feature_code":"PPLA2",
    "gn:name":"Villa de Ramos",
    "gn:population":0,
    "gn:timezone":"America/Mexico_City",
    "iso:country":"MX",
    "name:spa_x_preferred":[
        "Villa de Ramos"
    ],
    "name:srp_x_preferred":[
        "\u041e\u043f\u0448\u0442\u0438\u043d\u0430 \u0412\u0438\u0459\u0430 \u0434\u0435 \u0420\u0430\u043c\u043e\u0441"
    ],
    "name:und_x_variant":[
        "Ramos"
    ],
    "wof:name":"Villa de Ramos",
    "wof:placetype":"locality"
},
  "geometry": {"coordinates":[-101.91079000000001,22.83045],"type":"Point"}
}