{
  "type": "Feature",
  "properties": {
    "gn:admin1_code":"24",
    "gn:admin2_code":"49.0",
    "gn:asciiname":"Villa de Ramos",
    "gn:country_code":"MX",
    "gn:dem":2206,
    "gn:feature_class":"P",
    "gn:feature_code":"PPLA2",
    "gn:name":"Villa de Ramos",
    "gn:population":0,
    "gn:timezone":"America/Mexico_City",
    "iso:country":"MX",
    "name:spa_x_preferred":[
        "Villa de Ramos"
    ],
    "name:und_x_variant":[
        "Ramos"
    ],
    "wof:name":"Villa de Ramos",
    "wof:placetype":"locality"
},
  "geometry": {"coordinates":[-101.91079000000001,22.83045],"type":"Point"}
}