{
  "type": "Feature",
  "properties": {
    "gn:admin1_code":"2.0",
    "gn:admin2_code":"5.0",
    "gn:asciiname":"Puerto Nuevo",
    "gn:country_code":"MX",
    "gn:dem":23,
    "gn:feature_class":"P",
    "gn:feature_code":"PPL",
    "gn:name":"Puerto Nuevo",
    "gn:population":135,
    "gn:timezone":"America/Tijuana",
    "iso:country":"MX",
    "name:spa_x_preferred":[
        "Puerto Nuevo"
    ],
    "name:srp_x_preferred":[
        "\u041f\u0443\u0435\u0440\u0442\u043e \u041d\u0443\u0435\u0432\u043e"
    ],
    "wof:name":"Puerto Nuevo",
    "wof:placetype":"locality",
    "wof:population":135
},
  "geometry": {"coordinates":[-116.93465999999999,32.24299],"type":"Point"}
}