{
  "type": "Feature",
  "properties": {
    "gn:admin1_code":"2",
    "gn:admin2_code":"4",
    "gn:asciiname":"El Explorador",
    "gn:country_code":"MX",
    "gn:dem":202,
    "gn:feature_class":"P",
    "gn:feature_code":"PPL",
    "gn:name":"El Explorador",
    "gn:population":22,
    "gn:timezone":"America/Tijuana",
    "iso:country":"MX",
    "wof:name":"El Explorador",
    "wof:placetype":"locality",
    "wof:population":22
},
  "geometry": {"coordinates":[-116.87222,32.4375],"type":"Point"}
}