{
  "type": "Feature",
  "properties": {
    "gn:admin1_code":"16",
    "gn:asciiname":"Las Milpillas",
    "gn:country_code":"MX",
    "gn:dem":2063,
    "gn:feature_class":"P",
    "gn:feature_code":"PPL",
    "gn:name":"Las Milpillas",
    "gn:population":0,
    "gn:timezone":"America/Mexico_City",
    "iso:country":"MX",
    "name:spa_x_preferred":[
        "Las Milpillas"
    ],
    "wof:name":"Las Milpillas",
    "wof:placetype":"locality"
},
  "geometry": {"coordinates":[-103.00649,19.9642],"type":"Point"}
}