{
  "type": "Feature",
  "properties": {
    "gn:admin1_code":"24",
    "gn:admin2_code":"31.0",
    "gn:asciiname":"Carrizal Grande",
    "gn:country_code":"MX",
    "gn:dem":1061,
    "gn:feature_class":"P",
    "gn:feature_code":"PPL",
    "gn:name":"Carrizal Grande",
    "gn:population":0,
    "gn:timezone":"America/Mexico_City",
    "iso:country":"MX",
    "name:spa_x_preferred":[
        "Carrizal Grande"
    ],
    "wof:name":"Carrizal Grande",
    "wof:placetype":"locality"
},
  "geometry": {"coordinates":[-99.48396,21.54618],"type":"Point"}
}