{
  "type": "Feature",
  "properties": {
    "gn:admin1_code":"25",
    "gn:admin2_code":"3",
    "gn:asciiname":"Mesa de Bernal",
    "gn:country_code":"MX",
    "gn:dem":490,
    "gn:feature_class":"P",
    "gn:feature_code":"PPL",
    "gn:name":"Mesa de Bernal",
    "gn:population":14,
    "gn:timezone":"America/Mazatlan",
    "iso:country":"MX",
    "wof:name":"Mesa de Bernal",
    "wof:placetype":"locality",
    "wof:population":14
},
  "geometry": {"coordinates":[-107.45156,25.94828],"type":"Point"}
}