{
  "type": "Feature",
  "properties": {
    "gn:admin1_code":"16",
    "gn:admin2_code":"104.0",
    "gn:asciiname":"El Aguate (El Ajuate)",
    "gn:country_code":"MX",
    "gn:dem":1659,
    "gn:feature_class":"P",
    "gn:feature_code":"PPL",
    "gn:name":"El Aguate (El Ajuate)",
    "gn:population":65,
    "gn:timezone":"America/Mexico_City",
    "iso:country":"MX",
    "wof:name":"El Aguate (El Ajuate)",
    "wof:placetype":"locality",
    "wof:population":65
},
  "geometry": {"coordinates":[-102.62222,19.94222],"type":"Point"}
}