{
  "type": "Feature",
  "properties": {
    "gn:admin1_code":"15",
    "gn:admin2_code":"56.0",
    "gn:asciiname":"San Sebastian Buenos Aires",
    "gn:country_code":"MX",
    "gn:dem":2818,
    "gn:feature_class":"P",
    "gn:feature_code":"PPL",
    "gn:name":"San Sebasti\u00e1n Buenos Aires",
    "gn:population":0,
    "gn:timezone":"America/Mexico_City",
    "iso:country":"MX",
    "wof:name":"San Sebastian Buenos Aires",
    "wof:placetype":"locality"
},
  "geometry": {"coordinates":[-99.60361,19.72722000000001],"type":"Point"}
}