{
  "type": "Feature",
  "properties": {
    "gn:admin1_code":"6.0",
    "gn:admin2_code":"29.0",
    "gn:asciiname":"La Cebadilla",
    "gn:cc2":"MX",
    "gn:country_code":"MX",
    "gn:dem":2081,
    "gn:feature_class":"P",
    "gn:feature_code":"PPL",
    "gn:name":"La Cebadilla",
    "gn:population":0,
    "gn:timezone":"America/Chihuahua",
    "iso:country":"MX",
    "name:und_x_variant":[
        "Cebadillas",
        "La Cebadilla"
    ],
    "wof:name":"La Cebadilla",
    "wof:placetype":"locality"
},
  "geometry": {"coordinates":[-107.28333000000001,26.43333],"type":"Point"}
}