{
  "type": "Feature",
  "properties": {
    "gn:admin1_code":"17",
    "gn:admin2_code":"20",
    "gn:asciiname":"Achichipico",
    "gn:country_code":"MX",
    "gn:dem":1679,
    "gn:feature_class":"P",
    "gn:feature_code":"PPL",
    "gn:name":"Achichipico",
    "gn:population":21,
    "gn:timezone":"America/Mexico_City",
    "iso:country":"MX",
    "wof:name":"Achichipico",
    "wof:placetype":"locality",
    "wof:population":21
},
  "geometry": {"coordinates":[-99.07306,18.98389],"type":"Point"}
}