{
  "type": "Feature",
  "properties": {
    "gn:admin1_code":"23.0",
    "gn:admin2_code":"4.0",
    "gn:asciiname":"San Gabriel",
    "gn:country_code":"MX",
    "gn:dem":5,
    "gn:feature_class":"P",
    "gn:feature_code":"PPL",
    "gn:name":"San Gabriel",
    "gn:population":0,
    "gn:timezone":"America/Cancun",
    "iso:country":"MX",
    "name:spa_x_preferred":[
        "San Gabriel"
    ],
    "wof:name":"San Gabriel",
    "wof:placetype":"locality"
},
  "geometry": {"coordinates":[-88.06471999999999,18.97722000000001],"type":"Point"}
}