{
  "type": "Feature",
  "properties": {
    "gn:admin1_code":"6",
    "gn:admin2_code":"65.0",
    "gn:asciiname":"El Muerto",
    "gn:country_code":"MX",
    "gn:dem":2240,
    "gn:feature_class":"P",
    "gn:feature_code":"PPL",
    "gn:name":"El Muerto",
    "gn:population":0,
    "gn:timezone":"America/Chihuahua",
    "iso:country":"MX",
    "name:spa_x_preferred":[
        "El Muerto"
    ],
    "wof:name":"El Muerto",
    "wof:placetype":"locality"
},
  "geometry": {"coordinates":[-107.91054,27.44799],"type":"Point"}
}