{
  "type": "Feature",
  "properties": {
    "gn:admin1_code":"27",
    "gn:admin2_code":"8.0",
    "gn:asciiname":"Ostitan Primera Seccion",
    "gn:country_code":"MX",
    "gn:dem":40,
    "gn:feature_class":"P",
    "gn:feature_code":"PPL",
    "gn:name":"Ostit\u00e1n Primera Secci\u00f3n",
    "gn:population":0,
    "gn:timezone":"America/Mexico_City",
    "iso:country":"MX",
    "name:spa_x_preferred":[
        "Oxtitl\u00e1n"
    ],
    "name:spa_x_variant":[
        "Ostit\u00e1n Primera Secci\u00f3n",
        "Primera Secci\u00f3n",
        "Oxtit\u00e1n"
    ],
    "wof:name":"Ostitan Primera Seccion",
    "wof:placetype":"locality"
},
  "geometry": {"coordinates":[-93.41417,17.76006],"type":"Point"}
}