{
  "type": "Feature",
  "properties": {
    "gn:admin1_code":"28",
    "gn:admin2_code":"37.0",
    "gn:asciiname":"Sector Vista Hermosa",
    "gn:country_code":"MX",
    "gn:dem":6,
    "gn:feature_class":"P",
    "gn:feature_code":"PPL",
    "gn:name":"Sector Vista Hermosa",
    "gn:population":264,
    "gn:timezone":"America/Monterrey",
    "iso:country":"MX",
    "wof:name":"Sector Vista Hermosa",
    "wof:placetype":"locality",
    "wof:population":264
},
  "geometry": {"coordinates":[-97.83667,23.785],"type":"Point"}
}