{
  "type": "Feature",
  "properties": {
    "gn:admin1_code":"28.0",
    "gn:admin2_code":"43.0",
    "gn:asciiname":"Santa Fe de los Ebanos",
    "gn:country_code":"MX",
    "gn:dem":93,
    "gn:feature_class":"P",
    "gn:feature_code":"PPL",
    "gn:name":"Santa Fe de los \u00c9banos",
    "gn:population":27,
    "gn:timezone":"America/Monterrey",
    "iso:country":"MX",
    "name:spa_x_preferred":[
        "Santa Fe de los \u00c9banos"
    ],
    "wof:name":"Santa Fe de los Ebanos",
    "wof:placetype":"locality",
    "wof:population":27
},
  "geometry": {"coordinates":[-98.9675,22.98639],"type":"Point"}
}