{
  "type": "Feature",
  "properties": {
    "gn:admin1_code":"20",
    "gn:admin2_code":"277",
    "gn:asciiname":"La Cienega (La Cienega del Rancho)",
    "gn:country_code":"MX",
    "gn:dem":1740,
    "gn:feature_class":"P",
    "gn:feature_code":"PPL",
    "gn:name":"La Ci\u00e9nega (La Ci\u00e9nega del Rancho)",
    "gn:population":28,
    "gn:timezone":"America/Mexico_City",
    "iso:country":"MX",
    "name:und_x_variant":[
        "La Ci\u00e9nega (La Ci\u00e9nega del Rancho)"
    ],
    "wof:name":"La Cienega (La Cienega del Rancho)",
    "wof:placetype":"locality",
    "wof:population":28
},
  "geometry": {"coordinates":[-96.97056000000001,16.62944],"type":"Point"}
}