{
  "type": "Feature",
  "properties": {
    "gn:admin1_code":"6",
    "gn:admin2_code":"62.0",
    "gn:asciiname":"El Cozon",
    "gn:country_code":"MX",
    "gn:dem":1179,
    "gn:feature_class":"P",
    "gn:feature_code":"PPL",
    "gn:name":"El Coz\u00f3n",
    "gn:population":4,
    "gn:timezone":"America/Chihuahua",
    "iso:country":"MX",
    "name:und_x_variant":[
        "El Coz\u00f3n"
    ],
    "wof:name":"El Cozon",
    "wof:placetype":"locality",
    "wof:population":4
},
  "geometry": {"coordinates":[-105.28489999999999,28.04549],"type":"Point"}
}