{
  "type": "Feature",
  "properties": {
    "gn:admin1_code":"21",
    "gn:admin2_code":"71",
    "gn:asciiname":"Zacamila",
    "gn:country_code":"MX",
    "gn:dem":1564,
    "gn:feature_class":"P",
    "gn:feature_code":"PPL",
    "gn:name":"Zacamila",
    "gn:population":26,
    "gn:timezone":"America/Mexico_City",
    "iso:country":"MX",
    "wof:name":"Zacamila",
    "wof:placetype":"locality",
    "wof:population":26
},
  "geometry": {"coordinates":[-98.06394,20.18888],"type":"Point"}
}