{
  "type": "Feature",
  "properties": {
    "gn:admin1_code":"26",
    "gn:admin2_code":"18.0",
    "gn:asciiname":"Invernadero Santa Litta",
    "gn:country_code":"MX",
    "gn:dem":38,
    "gn:feature_class":"P",
    "gn:feature_code":"PPL",
    "gn:name":"Invernadero Santa Litta",
    "gn:population":7,
    "gn:timezone":"America/Hermosillo",
    "iso:country":"MX",
    "wof:name":"Invernadero Santa Litta",
    "wof:placetype":"locality",
    "wof:population":7
},
  "geometry": {"coordinates":[-109.93313000000001,27.39615],"type":"Point"}
}