{
  "type": "Feature",
  "properties": {
    "gn:admin1_code":"6.0",
    "gn:admin2_code":"51.0",
    "gn:asciiname":"Carpitas",
    "gn:country_code":"MX",
    "gn:dem":1718,
    "gn:feature_class":"P",
    "gn:feature_code":"PPL",
    "gn:name":"Carpitas",
    "gn:population":0,
    "gn:timezone":"America/Chihuahua",
    "iso:country":"MX",
    "wof:name":"Carpitas",
    "wof:placetype":"locality"
},
  "geometry": {"coordinates":[-108.43333,28.18333],"type":"Point"}
}