{
  "type": "Feature",
  "properties": {
    "gn:admin1_code":"16",
    "gn:admin2_code":"8",
    "gn:asciiname":"El Diezmo",
    "gn:country_code":"MX",
    "gn:dem":846,
    "gn:feature_class":"P",
    "gn:feature_code":"PPL",
    "gn:name":"El Diezmo",
    "gn:population":48,
    "gn:timezone":"America/Mexico_City",
    "iso:country":"MX",
    "wof:name":"El Diezmo",
    "wof:placetype":"locality",
    "wof:population":48
},
  "geometry": {"coordinates":[-103.30222000000001,18.44],"type":"Point"}
}