{
  "type": "Feature",
  "properties": {
    "gn:admin1_code":"26",
    "gn:admin2_code":"3.0",
    "gn:asciiname":"Aguaje de Domingo",
    "gn:country_code":"MX",
    "gn:dem":235,
    "gn:feature_class":"P",
    "gn:feature_code":"PPL",
    "gn:name":"Aguaje de Domingo",
    "gn:population":0,
    "gn:timezone":"America/Hermosillo",
    "iso:country":"MX",
    "name:spa_x_preferred":[
        "Aguaje de Domingo"
    ],
    "wof:name":"Aguaje de Domingo",
    "wof:placetype":"locality"
},
  "geometry": {"coordinates":[-108.70637000000001,26.67778],"type":"Point"}
}