{
  "type": "Feature",
  "properties": {
    "gn:admin1_code":"16",
    "gn:admin2_code":"38.0",
    "gn:asciiname":"Las Curucatas",
    "gn:country_code":"MX",
    "gn:dem":218,
    "gn:feature_class":"P",
    "gn:feature_code":"PPL",
    "gn:name":"Las Curucatas",
    "gn:population":8,
    "gn:timezone":"America/Mexico_City",
    "iso:country":"MX",
    "wof:name":"Las Curucatas",
    "wof:placetype":"locality",
    "wof:population":8
},
  "geometry": {"coordinates":[-101.12833000000001,18.55278],"type":"Point"}
}