{
  "type": "Feature",
  "properties": {
    "gn:admin1_code":"10",
    "gn:admin2_code":"23",
    "gn:asciiname":"La Laguna de Coyotes",
    "gn:country_code":"MX",
    "gn:dem":1634,
    "gn:feature_class":"P",
    "gn:feature_code":"PPL",
    "gn:name":"La Laguna de Coyotes",
    "gn:population":32,
    "gn:timezone":"America/Monterrey",
    "iso:country":"MX",
    "wof:name":"La Laguna de Coyotes",
    "wof:placetype":"locality",
    "wof:population":32
},
  "geometry": {"coordinates":[-105.30162,23.09537000000001],"type":"Point"}
}