{
  "type": "Feature",
  "properties": {
    "gn:admin1_code":"11",
    "gn:admin2_code":"20.0",
    "gn:asciiname":"Ninguno [Curtiduria]",
    "gn:country_code":"MX",
    "gn:dem":1782,
    "gn:feature_class":"P",
    "gn:feature_code":"PPL",
    "gn:name":"Ninguno [Curtidur\u00eda]",
    "gn:population":7,
    "gn:timezone":"America/Mexico_City",
    "iso:country":"MX",
    "name:und_x_variant":[
        "Ninguno [Curtidur\u00eda]"
    ],
    "wof:name":"Ninguno [Curtiduria]",
    "wof:placetype":"locality",
    "wof:population":7
},
  "geometry": {"coordinates":[-101.71222,21.05778],"type":"Point"}
}