{
  "type": "Feature",
  "properties": {
    "gn:admin1_code":"28",
    "gn:admin2_code":"40.0",
    "gn:asciiname":"Magueyes (Carretera Estatal 99 entre Sur 73 y Sur 78)",
    "gn:country_code":"MX",
    "gn:dem":18,
    "gn:feature_class":"P",
    "gn:feature_code":"PPL",
    "gn:name":"Magueyes (Carretera Estatal 99 entre Sur 73 y Sur 78)",
    "gn:population":358,
    "gn:timezone":"America/Monterrey",
    "iso:country":"MX",
    "wof:name":"Magueyes (Carretera Estatal 99 entre Sur 73 y Sur 78)",
    "wof:placetype":"locality",
    "wof:population":358
},
  "geometry": {"coordinates":[-97.81444,25.72139],"type":"Point"}
}