{
  "type": "Feature",
  "properties": {
    "gn:admin1_code":"32",
    "gn:admin2_code":"15.0",
    "gn:asciiname":"Los Bancos",
    "gn:country_code":"MX",
    "gn:dem":1935,
    "gn:feature_class":"P",
    "gn:feature_code":"PPL",
    "gn:name":"Los Bancos",
    "gn:population":4,
    "gn:timezone":"America/Mexico_City",
    "iso:country":"MX",
    "wof:name":"Los Bancos",
    "wof:placetype":"locality",
    "wof:population":4
},
  "geometry": {"coordinates":[-102.94722,22.10028],"type":"Point"}
}