{
  "type": "Feature",
  "properties": {
    "gn:admin1_code":"16",
    "gn:admin2_code":"15.0",
    "gn:asciiname":"Puentecillas",
    "gn:country_code":"MX",
    "gn:dem":2328,
    "gn:feature_class":"P",
    "gn:feature_code":"PPL",
    "gn:name":"Puentecillas",
    "gn:population":9,
    "gn:timezone":"America/Mexico_City",
    "iso:country":"MX",
    "wof:name":"Puentecillas",
    "wof:placetype":"locality",
    "wof:population":9
},
  "geometry": {"coordinates":[-102.94361000000001,18.80472],"type":"Point"}
}