{
  "type": "Feature",
  "properties": {
    "gn:admin1_code":"6",
    "gn:admin2_code":"29.0",
    "gn:asciiname":"Mesa de Satevo (Mesa de la Palma)",
    "gn:country_code":"MX",
    "gn:dem":2296,
    "gn:feature_class":"P",
    "gn:feature_code":"PPL",
    "gn:name":"Mesa de Satev\u00f3 (Mesa de la Palma)",
    "gn:population":72,
    "gn:timezone":"America/Chihuahua",
    "iso:country":"MX",
    "name:und_x_variant":[
        "Mesa de Satev\u00f3 (Mesa de la Palma)"
    ],
    "wof:name":"Mesa de Satevo (Mesa de la Palma)",
    "wof:placetype":"locality",
    "wof:population":72
},
  "geometry": {"coordinates":[-106.74459,26.40162],"type":"Point"}
}