{
  "type": "Feature",
  "properties": {
    "gn:admin1_code":"26.0",
    "gn:asciiname":"Las Guasimas",
    "gn:country_code":"MX",
    "gn:dem":395,
    "gn:feature_class":"P",
    "gn:feature_code":"PPL",
    "gn:name":"Las Gu\u00e1simas",
    "gn:population":0,
    "gn:timezone":"America/Hermosillo",
    "iso:country":"MX",
    "name:spa_x_preferred":[
        "Las Gu\u00e1simas"
    ],
    "wof:name":"Las Guasimas",
    "wof:placetype":"locality"
},
  "geometry": {"coordinates":[-109.56171999999999,27.77778],"type":"Point"}
}