{
  "type": "Feature",
  "properties": {
    "gn:admin1_code":"6",
    "gn:admin2_code":"27.0",
    "gn:asciiname":"Rosamachi",
    "gn:country_code":"MX",
    "gn:dem":2236,
    "gn:feature_class":"P",
    "gn:feature_code":"PPL",
    "gn:name":"Ros\u00e1machi",
    "gn:population":0,
    "gn:timezone":"America/Chihuahua",
    "iso:country":"MX",
    "name:spa_x_preferred":[
        "Ros\u00e1machi"
    ],
    "wof:name":"Rosamachi",
    "wof:placetype":"locality"
},
  "geometry": {"coordinates":[-107.70628000000001,27.42479],"type":"Point"}
}