{
  "type": "Feature",
  "properties": {
    "gn:admin1_code":"6",
    "gn:admin2_code":"29.0",
    "gn:asciiname":"Mesa de Tellez",
    "gn:country_code":"MX",
    "gn:dem":2381,
    "gn:feature_class":"P",
    "gn:feature_code":"PPL",
    "gn:name":"Mesa de T\u00e9llez",
    "gn:population":104,
    "gn:timezone":"America/Chihuahua",
    "iso:country":"MX",
    "name:und_x_variant":[
        "Mesa de T\u00e9llez"
    ],
    "wof:name":"Mesa de Tellez",
    "wof:placetype":"locality",
    "wof:population":104
},
  "geometry": {"coordinates":[-106.86667,26.02194],"type":"Point"}
}