{
  "type": "Feature",
  "properties": {
    "gn:admin1_code":"19",
    "gn:admin2_code":"48.0",
    "gn:asciiname":"Chupaderos",
    "gn:country_code":"MX",
    "gn:dem":1377,
    "gn:feature_class":"P",
    "gn:feature_code":"PPL",
    "gn:name":"Chupaderos",
    "gn:population":1,
    "gn:timezone":"America/Monterrey",
    "iso:country":"MX",
    "name:spa_x_preferred":[
        "Chupaderos"
    ],
    "wof:name":"Chupaderos",
    "wof:placetype":"locality",
    "wof:population":1
},
  "geometry": {"coordinates":[-100.71055,25.63174],"type":"Point"}
}