{
  "type": "Feature",
  "properties": {
    "gn:admin1_code":"27.0",
    "gn:admin2_code":"4.0",
    "gn:asciiname":"Mazaltepec",
    "gn:country_code":"MX",
    "gn:dem":13,
    "gn:feature_class":"P",
    "gn:feature_code":"PPL",
    "gn:name":"Mazaltepec",
    "gn:population":0,
    "gn:timezone":"America/Mexico_City",
    "iso:country":"MX",
    "name:spa_x_preferred":[
        "Mazaltepec"
    ],
    "wof:name":"Mazaltepec",
    "wof:placetype":"locality"
},
  "geometry": {"coordinates":[-92.99944000000001,18.01298],"type":"Point"}
}