{
  "type": "Feature",
  "properties": {
    "gn:admin1_code":"14",
    "gn:admin2_code":"22.0",
    "gn:asciiname":"Noble",
    "gn:country_code":"MX",
    "gn:dem":20,
    "gn:feature_class":"P",
    "gn:feature_code":"PPL",
    "gn:name":"Noble",
    "gn:population":6,
    "gn:timezone":"America/Mexico_City",
    "iso:country":"MX",
    "name:cat_x_preferred":[
        "Noble"
    ],
    "name:ceb_x_preferred":[
        "Noble"
    ],
    "name:deu_x_preferred":[
        "Noble"
    ],
    "name:fra_x_preferred":[
        "Noble"
    ],
    "name:ita_x_preferred":[
        "Noble"
    ],
    "name:jpn_x_preferred":[
        "\u30ce\u30fc\u30d6\u30eb"
    ],
    "name:nld_x_preferred":[
        "Noble"
    ],
    "name:pol_x_preferred":[
        "Noble"
    ],
    "name:por_x_preferred":[
        "Noble"
    ],
    "name:rus_x_preferred":[
        "\u041d\u043e\u0431\u043b"
    ],
    "name:spa_x_preferred":[
        "Noble"
    ],
    "name:srp_x_preferred":[
        "\u041d\u043e\u0431\u043b"
    ],
    "name:swe_x_preferred":[
        "Noble"
    ],
    "name:ukr_x_preferred":[
        "\u041d\u043e\u0431\u043b"
    ],
    "name:vol_x_preferred":[
        "Noble"
    ],
    "wof:name":"Noble",
    "wof:placetype":"locality",
    "wof:population":6
},
  "geometry": {"coordinates":[-104.69722,19.24028],"type":"Point"}
}