{
  "type": "Feature",
  "properties": {
    "gn:admin1_code":"2.0",
    "gn:admin2_code":"4.0",
    "gn:asciiname":"El Socorro",
    "gn:country_code":"MX",
    "gn:dem":191,
    "gn:feature_class":"P",
    "gn:feature_code":"PPL",
    "gn:name":"El Socorro",
    "gn:population":0,
    "gn:timezone":"America/Tijuana",
    "iso:country":"MX",
    "name:ceb_x_preferred":[
        "El Socorro"
    ],
    "name:fra_x_preferred":[
        "El Socorro"
    ],
    "name:spa_x_preferred":[
        "El Socorro"
    ],
    "name:swe_x_preferred":[
        "El Socorro"
    ],
    "wof:name":"El Socorro",
    "wof:placetype":"locality"
},
  "geometry": {"coordinates":[-116.76563,32.45971],"type":"Point"}
}