{
  "type": "Feature",
  "properties": {
    "gn:admin1_code":"21.0",
    "gn:admin2_code":"7.0",
    "gn:asciiname":"Anacahuite",
    "gn:country_code":"MX",
    "gn:dem":1260,
    "gn:feature_class":"P",
    "gn:feature_code":"PPL",
    "gn:name":"Anacahuite",
    "gn:population":0,
    "gn:timezone":"America/Mexico_City",
    "iso:country":"MX",
    "name:spa_x_preferred":[
        "Anacahuite"
    ],
    "wof:name":"Anacahuite",
    "wof:placetype":"locality"
},
  "geometry": {"coordinates":[-98.26667,18.53736],"type":"Point"}
}