{
  "type": "Feature",
  "properties": {
    "gn:admin1_code":"3.0",
    "gn:admin2_code":"1.0",
    "gn:asciiname":"Huatamote",
    "gn:country_code":"MX",
    "gn:dem":270,
    "gn:feature_class":"P",
    "gn:feature_code":"PPL",
    "gn:name":"Huatamote",
    "gn:population":0,
    "gn:timezone":"America/Mazatlan",
    "iso:country":"MX",
    "wof:name":"Huatamote",
    "wof:placetype":"locality"
},
  "geometry": {"coordinates":[-111.37083,25.40861],"type":"Point"}
}