{
  "type": "Feature",
  "properties": {
    "gn:admin1_code":"2.0",
    "gn:admin2_code":"3.0",
    "gn:asciiname":"Pie de la Cuesta",
    "gn:country_code":"MX",
    "gn:dem":259,
    "gn:feature_class":"P",
    "gn:feature_code":"PPL",
    "gn:name":"Pie de la Cuesta",
    "gn:population":0,
    "gn:timezone":"America/Tijuana",
    "iso:country":"MX",
    "name:spa_x_preferred":[
        "Pie de la Cuesta"
    ],
    "wof:name":"Pie de la Cuesta",
    "wof:placetype":"locality"
},
  "geometry": {"coordinates":[-115.94098,32.56664],"type":"Point"}
}