{
  "type": "Feature",
  "properties": {
    "gn:admin1_code":"14",
    "gn:admin2_code":"35",
    "gn:asciiname":"La Estanzuela",
    "gn:country_code":"MX",
    "gn:dem":2037,
    "gn:feature_class":"P",
    "gn:feature_code":"PPL",
    "gn:name":"La Estanzuela",
    "gn:population":11,
    "gn:timezone":"America/Mexico_City",
    "iso:country":"MX",
    "wof:name":"La Estanzuela",
    "wof:placetype":"locality",
    "wof:population":11
},
  "geometry": {"coordinates":[-102.02639000000001,21.50889],"type":"Point"}
}