{
  "type": "Feature",
  "properties": {
    "gn:admin1_code":"11.0",
    "gn:admin2_code":"2.0",
    "gn:asciiname":"La Ceba",
    "gn:country_code":"MX",
    "gn:dem":1853,
    "gn:feature_class":"P",
    "gn:feature_code":"PPL",
    "gn:name":"La Ceba",
    "gn:population":0,
    "gn:timezone":"America/Mexico_City",
    "iso:country":"MX",
    "name:spa_x_preferred":[
        "La Ceba"
    ],
    "wof:name":"La Ceba",
    "wof:placetype":"locality"
},
  "geometry": {"coordinates":[-100.72830999999999,20.07133],"type":"Point"}
}