{
  "type": "Feature",
  "properties": {
    "gn:admin1_code":"24",
    "gn:admin2_code":"11.0",
    "gn:asciiname":"La Tizar",
    "gn:country_code":"MX",
    "gn:dem":1437,
    "gn:feature_class":"P",
    "gn:feature_code":"PPL",
    "gn:name":"La T\u00edzar",
    "gn:population":6,
    "gn:timezone":"America/Mexico_City",
    "iso:country":"MX",
    "name:und_x_variant":[
        "La T\u00edzar"
    ],
    "wof:name":"La Tizar",
    "wof:placetype":"locality",
    "wof:population":6
},
  "geometry": {"coordinates":[-100.46028,21.98333],"type":"Point"}
}