{
  "type": "Feature",
  "properties": {
    "gn:admin1_code":"3",
    "gn:admin2_code":"2.0",
    "gn:asciiname":"Las Cuevitas",
    "gn:country_code":"MX",
    "gn:dem":639,
    "gn:feature_class":"P",
    "gn:feature_code":"PPL",
    "gn:name":"Las Cuevitas",
    "gn:population":0,
    "gn:timezone":"America/Mazatlan",
    "iso:country":"MX",
    "name:spa_x_preferred":[
        "Las Cuevitas"
    ],
    "wof:name":"Las Cuevitas",
    "wof:placetype":"locality"
},
  "geometry": {"coordinates":[-112.21635000000001,26.62932],"type":"Point"}
}