{
  "type": "Feature",
  "properties": {
    "gn:admin1_code":"7.0",
    "gn:admin2_code":"38.0",
    "gn:asciiname":"Pila Seca",
    "gn:country_code":"MX",
    "gn:dem":691,
    "gn:feature_class":"P",
    "gn:feature_code":"PPL",
    "gn:name":"Pila Seca",
    "gn:population":1,
    "gn:timezone":"America/Monterrey",
    "iso:country":"MX",
    "name:spa_x_preferred":[
        "Pila Seca"
    ],
    "wof:name":"Pila Seca",
    "wof:placetype":"locality",
    "wof:population":1
},
  "geometry": {"coordinates":[-101.58150000000001,29.01301],"type":"Point"}
}