{
  "type": "Feature",
  "properties": {
    "gn:admin1_code":"11",
    "gn:admin2_code":"1",
    "gn:asciiname":"Jose Eduardo Fuerte",
    "gn:country_code":"MX",
    "gn:dem":1695,
    "gn:feature_class":"P",
    "gn:feature_code":"PPL",
    "gn:name":"Jos\u00e9 Eduardo Fuerte",
    "gn:population":11,
    "gn:timezone":"America/Mexico_City",
    "iso:country":"MX",
    "name:und_x_variant":[
        "Jos\u00e9 Eduardo Fuerte"
    ],
    "wof:name":"Jose Eduardo Fuerte",
    "wof:placetype":"locality",
    "wof:population":11
},
  "geometry": {"coordinates":[-101.55583,20.59361],"type":"Point"}
}