{
  "type": "Feature",
  "properties": {
    "gn:admin1_code":"6",
    "gn:admin2_code":"39.0",
    "gn:asciiname":"Malpais",
    "gn:country_code":"MX",
    "gn:dem":1417,
    "gn:feature_class":"P",
    "gn:feature_code":"PPL",
    "gn:name":"Malpa\u00eds",
    "gn:population":0,
    "gn:timezone":"America/Chihuahua",
    "iso:country":"MX",
    "name:ceb_x_preferred":[
        "Malpais"
    ],
    "name:spa_x_preferred":[
        "Malpa\u00eds"
    ],
    "name:srp_x_preferred":[
        "\u041c\u0430\u043b\u043f\u0430\u0438\u0441"
    ],
    "name:swe_x_preferred":[
        "Malpais"
    ],
    "wof:name":"Malpais",
    "wof:placetype":"locality"
},
  "geometry": {"coordinates":[-105.00715,27.00192],"type":"Point"}
}