{
  "type": "Feature",
  "properties": {
    "gn:admin1_code":"28.0",
    "gn:admin2_code":"16.0",
    "gn:asciiname":"Jose Maria Morelos y Pavon",
    "gn:country_code":"MX",
    "gn:dem":254,
    "gn:feature_class":"P",
    "gn:feature_code":"PPL",
    "gn:name":"Jos\u00e9 Mar\u00eda Morelos y Pav\u00f3n",
    "gn:population":0,
    "gn:timezone":"America/Monterrey",
    "iso:country":"MX",
    "name:spa_x_preferred":[
        "Jos\u00e9 Mar\u00eda Morelos y Pav\u00f3n"
    ],
    "wof:name":"Jose Maria Morelos y Pavon",
    "wof:placetype":"locality"
},
  "geometry": {"coordinates":[-99.30779,24.15153],"type":"Point"}
}