{
  "type": "Feature",
  "properties": {
    "gn:admin1_code":"14",
    "gn:admin2_code":"67.0",
    "gn:asciiname":"Colonia Paso del Molino",
    "gn:country_code":"MX",
    "gn:dem":72,
    "gn:feature_class":"P",
    "gn:feature_code":"PPL",
    "gn:name":"Colonia Paso del Molino",
    "gn:population":113,
    "gn:timezone":"America/Mexico_City",
    "iso:country":"MX",
    "wof:name":"Colonia Paso del Molino",
    "wof:placetype":"locality",
    "wof:population":113
},
  "geometry": {"coordinates":[-105.21832999999999,20.59278],"type":"Point"}
}