{
  "type": "Feature",
  "properties": {
    "gn:admin1_code":"19",
    "gn:admin2_code":"17.0",
    "gn:asciiname":"Rancho Bernal",
    "gn:country_code":"MX",
    "gn:dem":2065,
    "gn:feature_class":"P",
    "gn:feature_code":"PPL",
    "gn:name":"Rancho Bernal",
    "gn:population":5,
    "gn:timezone":"America/Monterrey",
    "iso:country":"MX",
    "wof:name":"Rancho Bernal",
    "wof:placetype":"locality",
    "wof:population":5
},
  "geometry": {"coordinates":[-99.99666999999999,24.59944],"type":"Point"}
}