{
  "type": "Feature",
  "properties": {
    "gn:admin1_code":"32.0",
    "gn:asciiname":"La Manga",
    "gn:country_code":"MX",
    "gn:dem":1730,
    "gn:feature_class":"P",
    "gn:feature_code":"PPL",
    "gn:name":"La Manga",
    "gn:population":0,
    "gn:timezone":"America/Mexico_City",
    "iso:country":"MX",
    "name:spa_x_preferred":[
        "La Manga"
    ],
    "wof:name":"La Manga",
    "wof:placetype":"locality"
},
  "geometry": {"coordinates":[-102.79902,21.7355],"type":"Point"}
}