{
  "type": "Feature",
  "properties": {
    "gn:admin1_code":"14",
    "gn:admin2_code":"8",
    "gn:asciiname":"El Salto de Nogales",
    "gn:country_code":"MX",
    "gn:dem":2026,
    "gn:feature_class":"P",
    "gn:feature_code":"PPL",
    "gn:name":"El Salto de Nogales",
    "gn:population":33,
    "gn:timezone":"America/Mexico_City",
    "iso:country":"MX",
    "wof:name":"El Salto de Nogales",
    "wof:placetype":"locality",
    "wof:population":33
},
  "geometry": {"coordinates":[-102.19611,20.81278],"type":"Point"}
}