{
  "type": "Feature",
  "properties": {
    "gn:admin1_code":"19",
    "gn:admin2_code":"13.0",
    "gn:asciiname":"La Esperanza Dos",
    "gn:country_code":"MX",
    "gn:dem":121,
    "gn:feature_class":"P",
    "gn:feature_code":"PPL",
    "gn:name":"La Esperanza Dos",
    "gn:population":5,
    "gn:timezone":"America/Monterrey",
    "iso:country":"MX",
    "wof:name":"La Esperanza Dos",
    "wof:placetype":"locality",
    "wof:population":5
},
  "geometry": {"coordinates":[-98.86695,25.48064],"type":"Point"}
}