{
  "type": "Feature",
  "properties": {
    "gn:admin1_code":"14",
    "gn:admin2_code":"35.0",
    "gn:asciiname":"El Codo",
    "gn:country_code":"MX",
    "gn:dem":1984,
    "gn:feature_class":"P",
    "gn:feature_code":"PPL",
    "gn:name":"El Codo",
    "gn:population":8,
    "gn:timezone":"America/Mexico_City",
    "iso:country":"MX",
    "wof:name":"El Codo",
    "wof:placetype":"locality",
    "wof:population":8
},
  "geometry": {"coordinates":[-102.09972,21.74222],"type":"Point"}
}