{
  "type": "Feature",
  "properties": {
    "gn:admin1_code":"5",
    "gn:admin2_code":"23.0",
    "gn:asciiname":"Bahosil",
    "gn:country_code":"MX",
    "gn:dem":2280,
    "gn:feature_class":"P",
    "gn:feature_code":"PPL",
    "gn:name":"Bahosil",
    "gn:population":767,
    "gn:timezone":"America/Mexico_City",
    "iso:country":"MX",
    "wof:name":"Bahosil",
    "wof:placetype":"locality",
    "wof:population":767
},
  "geometry": {"coordinates":[-92.72815,16.78005],"type":"Point"}
}