{
  "type": "Feature",
  "properties": {
    "gn:admin1_code":"20",
    "gn:admin2_code":"253.0",
    "gn:asciiname":"El Perdiz",
    "gn:country_code":"MX",
    "gn:dem":1158,
    "gn:feature_class":"P",
    "gn:feature_code":"PPL",
    "gn:name":"El Perdiz",
    "gn:population":246,
    "gn:timezone":"America/Mexico_City",
    "iso:country":"MX",
    "wof:name":"El Perdiz",
    "wof:placetype":"locality",
    "wof:population":246
},
  "geometry": {"coordinates":[-96.34028000000001,15.93889],"type":"Point"}
}