{
  "type": "Feature",
  "properties": {
    "gn:admin1_code":"24.0",
    "gn:admin2_code":"10.0",
    "gn:asciiname":"Puerto de Lobos",
    "gn:country_code":"MX",
    "gn:dem":1326,
    "gn:feature_class":"P",
    "gn:feature_code":"PPL",
    "gn:name":"Puerto de Lobos",
    "gn:population":38,
    "gn:timezone":"America/Mexico_City",
    "iso:country":"MX",
    "name:spa_x_preferred":[
        "Puerto de Lobos"
    ],
    "wof:name":"Puerto de Lobos",
    "wof:placetype":"locality",
    "wof:population":38
},
  "geometry": {"coordinates":[-99.56222,22.48444],"type":"Point"}
}