{
  "type": "Feature",
  "properties": {
    "gn:admin1_code":"15.0",
    "gn:admin2_code":"82.0",
    "gn:asciiname":"El Paso",
    "gn:country_code":"MX",
    "gn:dem":736,
    "gn:feature_class":"P",
    "gn:feature_code":"PPL",
    "gn:name":"El Paso",
    "gn:population":0,
    "gn:timezone":"America/Mexico_City",
    "iso:country":"MX",
    "wof:name":"El Paso",
    "wof:placetype":"locality"
},
  "geometry": {"coordinates":[-100.375,18.78333],"type":"Point"}
}