{
  "type": "Feature",
  "properties": {
    "gn:admin1_code":"6",
    "gn:admin2_code":"61.0",
    "gn:asciiname":"Los Sosa",
    "gn:country_code":"MX",
    "gn:dem":1394,
    "gn:feature_class":"P",
    "gn:feature_code":"PPL",
    "gn:name":"Los Sosa",
    "gn:population":4,
    "gn:timezone":"America/Chihuahua",
    "iso:country":"MX",
    "wof:name":"Los Sosa",
    "wof:placetype":"locality",
    "wof:population":4
},
  "geometry": {"coordinates":[-106.13047,27.96826],"type":"Point"}
}