{
  "type": "Feature",
  "properties": {
    "gn:admin1_code":"30",
    "gn:admin2_code":"130.0",
    "gn:asciiname":"El Guadalupe",
    "gn:country_code":"MX",
    "gn:dem":60,
    "gn:feature_class":"P",
    "gn:feature_code":"PPL",
    "gn:name":"El Guadalupe",
    "gn:population":5,
    "gn:timezone":"America/Mexico_City",
    "iso:country":"MX",
    "wof:name":"El Guadalupe",
    "wof:placetype":"locality",
    "wof:population":5
},
  "geometry": {"coordinates":[-95.79194,17.79083],"type":"Point"}
}