{
  "type": "Feature",
  "properties": {
    "gn:admin1_code":"4",
    "gn:admin2_code":"5.0",
    "gn:asciiname":"Blanca Flor",
    "gn:country_code":"MX",
    "gn:dem":12,
    "gn:feature_class":"P",
    "gn:feature_code":"PPL",
    "gn:name":"Blanca Flor",
    "gn:population":0,
    "gn:timezone":"America/Merida",
    "iso:country":"MX",
    "name:spa_x_preferred":[
        "Blanca Flor"
    ],
    "wof:name":"Blanca Flor",
    "wof:placetype":"locality"
},
  "geometry": {"coordinates":[-90.11087999999999,20.21141],"type":"Point"}
}