{
  "type": "Feature",
  "properties": {
    "gn:admin1_code":"7",
    "gn:admin2_code":"11.0",
    "gn:asciiname":"Oratorio Chico",
    "gn:country_code":"MX",
    "gn:dem":1195,
    "gn:feature_class":"P",
    "gn:feature_code":"PPL",
    "gn:name":"Oratorio Chico",
    "gn:population":0,
    "gn:timezone":"America/Monterrey",
    "iso:country":"MX",
    "name:spa_x_preferred":[
        "Oratorio Chico"
    ],
    "wof:name":"Oratorio Chico",
    "wof:placetype":"locality"
},
  "geometry": {"coordinates":[-101.33052000000001,25.5844],"type":"Point"}
}