{
  "type": "Feature",
  "properties": {
    "gn:admin1_code":"6.0",
    "gn:admin2_code":"1.0",
    "gn:asciiname":"San Gerardo",
    "gn:country_code":"MX",
    "gn:dem":1200,
    "gn:feature_class":"P",
    "gn:feature_code":"PPL",
    "gn:name":"San Gerardo",
    "gn:population":0,
    "gn:timezone":"America/Chihuahua",
    "iso:country":"MX",
    "name:spa_x_preferred":[
        "San Gerardo"
    ],
    "wof:name":"San Gerardo",
    "wof:placetype":"locality"
},
  "geometry": {"coordinates":[-106.47329999999999,30.64881],"type":"Point"}
}