{
  "type": "Feature",
  "properties": {
    "gn:admin1_code":"5",
    "gn:admin2_code":"11.0",
    "gn:asciiname":"El Sabinalito",
    "gn:country_code":"MX",
    "gn:dem":1872,
    "gn:feature_class":"P",
    "gn:feature_code":"PPL",
    "gn:name":"El Sabinalito",
    "gn:population":73,
    "gn:timezone":"America/Mexico_City",
    "iso:country":"MX",
    "wof:name":"El Sabinalito",
    "wof:placetype":"locality",
    "wof:population":73
},
  "geometry": {"coordinates":[-92.23333,15.55944],"type":"Point"}
}