{
  "type": "Feature",
  "properties": {
    "gn:admin1_code":"6",
    "gn:admin2_code":"18.0",
    "gn:asciiname":"San Antonio de Loya",
    "gn:cc2":"MX",
    "gn:country_code":"MX",
    "gn:dem":1844,
    "gn:feature_class":"P",
    "gn:feature_code":"PPL",
    "gn:name":"San Antonio de Loya",
    "gn:population":5,
    "gn:timezone":"America/Chihuahua",
    "iso:country":"MX",
    "name:und_x_variant":[
        "Leija",
        "San Antonio"
    ],
    "wof:name":"San Antonio de Loya",
    "wof:placetype":"locality",
    "wof:population":5
},
  "geometry": {"coordinates":[-106.6724,28.32779],"type":"Point"}
}