{
  "type": "Feature",
  "properties": {
    "gn:admin1_code":"15",
    "gn:admin2_code":"74.0",
    "gn:asciiname":"Ejido San Agustin Mextepec",
    "gn:country_code":"MX",
    "gn:dem":2559,
    "gn:feature_class":"P",
    "gn:feature_code":"PPL",
    "gn:name":"Ejido San Agust\u00edn Mextepec",
    "gn:population":191,
    "gn:timezone":"America/Mexico_City",
    "iso:country":"MX",
    "wof:name":"Ejido San Agustin Mextepec",
    "wof:placetype":"locality",
    "wof:population":191
},
  "geometry": {"coordinates":[-99.91417,19.64333],"type":"Point"}
}