{
  "type": "Feature",
  "properties": {
    "gn:admin1_code":"15.0",
    "gn:asciiname":"La Canasta",
    "gn:country_code":"MX",
    "gn:dem":2396,
    "gn:feature_class":"P",
    "gn:feature_code":"PPL",
    "gn:name":"La Canasta",
    "gn:population":0,
    "gn:timezone":"America/Mexico_City",
    "iso:country":"MX",
    "name:spa_x_preferred":[
        "La Canasta"
    ],
    "wof:name":"La Canasta",
    "wof:placetype":"locality"
},
  "geometry": {"coordinates":[-99.48621,19.98939],"type":"Point"}
}