{
  "type": "Feature",
  "properties": {
    "gn:admin1_code":"30",
    "gn:admin2_code":"117.0",
    "gn:asciiname":"La Pochota",
    "gn:country_code":"MX",
    "gn:dem":301,
    "gn:feature_class":"P",
    "gn:feature_code":"PPL",
    "gn:name":"La Pochota",
    "gn:population":0,
    "gn:timezone":"America/Mexico_City",
    "iso:country":"MX",
    "name:spa_x_preferred":[
        "La Pochota"
    ],
    "wof:name":"La Pochota",
    "wof:placetype":"locality"
},
  "geometry": {"coordinates":[-96.69206,18.71535],"type":"Point"}
}