{
  "type": "Feature",
  "properties": {
    "gn:admin1_code":"28",
    "gn:admin2_code":"22.0",
    "gn:asciiname":"Rancho Nuevo (Esther Gaytan)",
    "gn:country_code":"MX",
    "gn:dem":6,
    "gn:feature_class":"P",
    "gn:feature_code":"PPL",
    "gn:name":"Rancho Nuevo (Esther Gayt\u00e1n)",
    "gn:population":9,
    "gn:timezone":"America/Matamoros",
    "iso:country":"MX",
    "wof:name":"Rancho Nuevo (Esther Gaytan)",
    "wof:placetype":"locality",
    "wof:population":9
},
  "geometry": {"coordinates":[-97.24695,25.87361],"type":"Point"}
}