{
  "type": "Feature",
  "properties": {
    "gn:admin1_code":"20",
    "gn:admin2_code":"336.0",
    "gn:asciiname":"San Martin Buenavista",
    "gn:country_code":"MX",
    "gn:dem":1752,
    "gn:feature_class":"P",
    "gn:feature_code":"PPL",
    "gn:name":"San Mart\u00edn Buenavista",
    "gn:population":0,
    "gn:timezone":"America/Mexico_City",
    "iso:country":"MX",
    "name:und_x_variant":[
        "San Mart\u00edn",
        "San Mart\u00edn Buenavista"
    ],
    "wof:name":"San Martin Buenavista",
    "wof:placetype":"locality"
},
  "geometry": {"coordinates":[-96.61394,17.635],"type":"Point"}
}