{
  "type": "Feature",
  "properties": {
    "gn:admin1_code":"31",
    "gn:admin2_code":"96.0",
    "gn:asciiname":"X-Iapak",
    "gn:country_code":"MX",
    "gn:dem":9,
    "gn:feature_class":"P",
    "gn:feature_code":"PPL",
    "gn:name":"X-Iapak",
    "gn:population":0,
    "gn:timezone":"America/Merida",
    "iso:country":"MX",
    "name:spa_x_preferred":[
        "X-Iapak"
    ],
    "wof:name":"X-Iapak",
    "wof:placetype":"locality"
},
  "geometry": {"coordinates":[-87.78950999999998,21.41077],"type":"Point"}
}