{
  "type": "Feature",
  "properties": {
    "gn:admin1_code":"13",
    "gn:admin2_code":"29",
    "gn:asciiname":"Las Sabilas",
    "gn:country_code":"MX",
    "gn:dem":2076,
    "gn:feature_class":"P",
    "gn:feature_code":"PPL",
    "gn:name":"Las S\u00e1bilas",
    "gn:population":27,
    "gn:timezone":"America/Mexico_City",
    "iso:country":"MX",
    "name:und_x_variant":[
        "Las S\u00e1bilas"
    ],
    "wof:name":"Las Sabilas",
    "wof:placetype":"locality",
    "wof:population":27
},
  "geometry": {"coordinates":[-99.58582,20.47154],"type":"Point"}
}