{
  "type": "Feature",
  "properties": {
    "gn:admin1_code":"21",
    "gn:admin2_code":"180.0",
    "gn:asciiname":"La Preciosita",
    "gn:country_code":"MX",
    "gn:dem":2509,
    "gn:feature_class":"P",
    "gn:feature_code":"PPL",
    "gn:name":"La Preciosita",
    "gn:population":714,
    "gn:timezone":"America/Mexico_City",
    "iso:country":"MX",
    "wof:name":"La Preciosita",
    "wof:placetype":"locality",
    "wof:population":714
},
  "geometry": {"coordinates":[-98.54416999999999,19.40833],"type":"Point"}
}