{
  "type": "Feature",
  "properties": {
    "gn:admin1_code":"5",
    "gn:admin2_code":"65.0",
    "gn:asciiname":"Santa Isabel",
    "gn:country_code":"MX",
    "gn:dem":132,
    "gn:feature_class":"P",
    "gn:feature_code":"PPL",
    "gn:name":"Santa Isabel",
    "gn:population":7,
    "gn:timezone":"America/Mexico_City",
    "iso:country":"MX",
    "wof:name":"Santa Isabel",
    "wof:placetype":"locality",
    "wof:population":7
},
  "geometry": {"coordinates":[-92.10527999999999,17.50444],"type":"Point"}
}