{
  "type": "Feature",
  "properties": {
    "gn:admin1_code":"30.0",
    "gn:admin2_code":"33.0",
    "gn:asciiname":"Don Ramon",
    "gn:country_code":"MX",
    "gn:dem":72,
    "gn:feature_class":"P",
    "gn:feature_code":"PPL",
    "gn:name":"Don Ram\u00f3n",
    "gn:population":2,
    "gn:timezone":"America/Mexico_City",
    "iso:country":"MX",
    "name:spa_x_preferred":[
        "Don Ram\u00f3n"
    ],
    "wof:name":"Don Ramon",
    "wof:placetype":"locality",
    "wof:population":2
},
  "geometry": {"coordinates":[-97.33722,20.6625],"type":"Point"}
}