{
  "type": "Feature",
  "properties": {
    "gn:admin1_code":"21",
    "gn:admin2_code":"113.0",
    "gn:asciiname":"Palos Blancos",
    "gn:country_code":"MX",
    "gn:dem":1146,
    "gn:feature_class":"P",
    "gn:feature_code":"PPL",
    "gn:name":"Palos Blancos",
    "gn:population":7,
    "gn:timezone":"America/Mexico_City",
    "iso:country":"MX",
    "name:deu_x_preferred":[
        "Palos Blancos"
    ],
    "name:zho_x_preferred":[
        "\u5e15\u6d1b\u65af\u5e03\u862d\u79d1\u65af"
    ],
    "wof:name":"Palos Blancos",
    "wof:placetype":"locality",
    "wof:population":7
},
  "geometry": {"coordinates":[-98.24665,18.21159],"type":"Point"}
}