{
  "type": "Feature",
  "properties": {
    "gn:admin1_code":"21",
    "gn:admin2_code":"150.0",
    "gn:asciiname":"San Nicolas Huajuapan",
    "gn:country_code":"MX",
    "gn:dem":1687,
    "gn:feature_class":"P",
    "gn:feature_code":"PPL",
    "gn:name":"San Nicol\u00e1s Huajuapan",
    "gn:population":0,
    "gn:timezone":"America/Mexico_City",
    "iso:country":"MX",
    "name:spa_x_preferred":[
        "San Nicol\u00e1s Huajuapan"
    ],
    "name:spa_x_variant":[
        "Huajuapan"
    ],
    "wof:name":"San Nicolas Huajuapan",
    "wof:placetype":"locality"
},
  "geometry": {"coordinates":[-98.12129,18.78497],"type":"Point"}
}