{
  "type": "Feature",
  "properties": {
    "gn:admin1_code":"3",
    "gn:admin2_code":"3.0",
    "gn:asciiname":"Kilometro 63",
    "gn:country_code":"MX",
    "gn:dem":43,
    "gn:feature_class":"P",
    "gn:feature_code":"PPL",
    "gn:name":"Kil\u00f3metro 63",
    "gn:population":5,
    "gn:timezone":"America/Mazatlan",
    "iso:country":"MX",
    "name:und_x_variant":[
        "Kil\u00f3metro 63"
    ],
    "wof:name":"Kilometro 63",
    "wof:placetype":"locality",
    "wof:population":5
},
  "geometry": {"coordinates":[-110.17147,23.35716],"type":"Point"}
}