{
  "type": "Feature",
  "properties": {
    "gn:admin1_code":"21",
    "gn:admin2_code":"198.0",
    "gn:asciiname":"Coacalco",
    "gn:country_code":"MX",
    "gn:dem":715,
    "gn:feature_class":"P",
    "gn:feature_code":"PPL",
    "gn:name":"Coacalco",
    "gn:population":519,
    "gn:timezone":"America/Mexico_City",
    "iso:country":"MX",
    "wof:name":"Coacalco",
    "wof:placetype":"locality",
    "wof:population":519
},
  "geometry": {"coordinates":[-98.66806,18.07167],"type":"Point"}
}