{
  "type": "Feature",
  "properties": {
    "gn:admin1_code":"26",
    "gn:admin2_code":"55.0",
    "gn:asciiname":"Nuevo Michoacan (Estacion Riito)",
    "gn:country_code":"MX",
    "gn:dem":14,
    "gn:feature_class":"P",
    "gn:feature_code":"PPL",
    "gn:name":"Nuevo Michoac\u00e1n (Estaci\u00f3n Ri\u00edto)",
    "gn:population":1425,
    "gn:timezone":"America/Hermosillo",
    "iso:country":"MX",
    "name:und_x_variant":[
        "Nuevo Michoac\u00e1n (Estaci\u00f3n Ri\u00edto)"
    ],
    "wof:name":"Nuevo Michoacan (Estacion Riito)",
    "wof:placetype":"locality",
    "wof:population":1425
},
  "geometry": {"coordinates":[-114.96167,32.16611],"type":"Point"}
}