{
  "type": "Feature",
  "properties": {
    "gn:admin1_code":"11",
    "gn:admin2_code":"42.0",
    "gn:asciiname":"San Isidro de Pitahayo",
    "gn:country_code":"MX",
    "gn:dem":1719,
    "gn:feature_class":"P",
    "gn:feature_code":"PPL",
    "gn:name":"San Isidro de Pitahayo",
    "gn:population":366,
    "gn:timezone":"America/Mexico_City",
    "iso:country":"MX",
    "wof:name":"San Isidro de Pitahayo",
    "wof:placetype":"locality",
    "wof:population":366
},
  "geometry": {"coordinates":[-101.13294999999999,20.47668],"type":"Point"}
}