{
  "type": "Feature",
  "properties": {
    "gn:admin1_code":"18.0",
    "gn:admin2_code":"1.0",
    "gn:asciiname":"Canones",
    "gn:country_code":"MX",
    "gn:dem":1866,
    "gn:feature_class":"P",
    "gn:feature_code":"PPL",
    "gn:name":"Ca\u00f1ones",
    "gn:population":41,
    "gn:timezone":"America/Mazatlan",
    "iso:country":"MX",
    "wof:name":"Canones",
    "wof:placetype":"locality",
    "wof:population":41
},
  "geometry": {"coordinates":[-105.05028,22.58333],"type":"Point"}
}