{
  "type": "Feature",
  "properties": {
    "gn:admin1_code":"10",
    "gn:admin2_code":"1.0",
    "gn:asciiname":"Los Calaveras",
    "gn:country_code":"MX",
    "gn:dem":1989,
    "gn:feature_class":"P",
    "gn:feature_code":"PPL",
    "gn:name":"Los Calaveras",
    "gn:population":0,
    "gn:timezone":"America/Monterrey",
    "iso:country":"MX",
    "wof:name":"Los Calaveras",
    "wof:placetype":"locality"
},
  "geometry": {"coordinates":[-104.76667,24.65],"type":"Point"}
}