{
  "type": "Feature",
  "properties": {
    "gn:admin1_code":"17.0",
    "gn:asciiname":"El Muerto",
    "gn:country_code":"MX",
    "gn:dem":1007,
    "gn:feature_class":"P",
    "gn:feature_code":"PPL",
    "gn:name":"El Muerto",
    "gn:population":0,
    "gn:timezone":"America/Mexico_City",
    "iso:country":"MX",
    "name:spa_x_preferred":[
        "El Muerto"
    ],
    "wof:name":"El Muerto",
    "wof:placetype":"locality"
},
  "geometry": {"coordinates":[-98.7111,18.47529],"type":"Point"}
}