{
  "type": "Feature",
  "properties": {
    "gn:admin1_code":"4.0",
    "gn:admin2_code":"9.0",
    "gn:asciiname":"Rodolfo Fierros",
    "gn:country_code":"MX",
    "gn:dem":123,
    "gn:feature_class":"P",
    "gn:feature_code":"PPL",
    "gn:name":"Rodolfo Fierros",
    "gn:population":0,
    "gn:timezone":"America/Merida",
    "iso:country":"MX",
    "name:spa_x_preferred":[
        "Rodolfo Fierros"
    ],
    "wof:name":"Rodolfo Fierros",
    "wof:placetype":"locality"
},
  "geometry": {"coordinates":[-90.62014000000001,18.57182],"type":"Point"}
}