{
  "type": "Feature",
  "properties": {
    "gn:admin1_code":"5",
    "gn:admin2_code":"89",
    "gn:asciiname":"San Gabriel",
    "gn:country_code":"MX",
    "gn:dem":35,
    "gn:feature_class":"P",
    "gn:feature_code":"PPL",
    "gn:name":"San Gabriel",
    "gn:population":21,
    "gn:timezone":"America/Mexico_City",
    "iso:country":"MX",
    "wof:name":"San Gabriel",
    "wof:placetype":"locality",
    "wof:population":21
},
  "geometry": {"coordinates":[-92.35472,14.83778],"type":"Point"}
}