{
  "type": "Feature",
  "properties": {
    "gn:admin1_code":"6",
    "gn:admin2_code":"27.0",
    "gn:asciiname":"Rancho Seco",
    "gn:country_code":"MX",
    "gn:dem":2464,
    "gn:feature_class":"P",
    "gn:feature_code":"PPL",
    "gn:name":"Rancho Seco",
    "gn:population":340,
    "gn:timezone":"America/Chihuahua",
    "iso:country":"MX",
    "name:spa_x_preferred":[
        "Rancho Seco"
    ],
    "wof:name":"Rancho Seco",
    "wof:placetype":"locality",
    "wof:population":340
},
  "geometry": {"coordinates":[-107.07138999999999,26.78917],"type":"Point"}
}