{
  "type": "Feature",
  "properties": {
    "gn:admin1_code":"31",
    "gn:admin2_code":"89.0",
    "gn:asciiname":"Pustunich",
    "gn:country_code":"MX",
    "gn:dem":29,
    "gn:feature_class":"P",
    "gn:feature_code":"PPL",
    "gn:name":"Pustunich",
    "gn:population":0,
    "gn:timezone":"America/Merida",
    "iso:country":"MX",
    "name:spa_x_preferred":[
        "Pustunich"
    ],
    "name:und_x_variant":[
        "Postunich"
    ],
    "wof:name":"Pustunich",
    "wof:placetype":"locality"
},
  "geometry": {"coordinates":[-89.51187,20.36914],"type":"Point"}
}