{
  "type": "Feature",
  "properties": {
    "gn:admin1_code":"14.0",
    "gn:admin2_code":"80.0",
    "gn:asciiname":"San Sebastian del Oeste",
    "gn:country_code":"MX",
    "gn:dem":1388,
    "gn:feature_class":"P",
    "gn:feature_code":"PPL",
    "gn:name":"San Sebasti\u00e1n del Oeste",
    "gn:population":0,
    "gn:timezone":"America/Mexico_City",
    "iso:country":"MX",
    "wof:name":"San Sebastian del Oeste",
    "wof:placetype":"locality"
},
  "geometry": {"coordinates":[-104.85145,20.76221],"type":"Point"}
}