{
  "type": "Feature",
  "properties": {
    "gn:admin1_code":"16.0",
    "gn:admin2_code":"34.0",
    "gn:asciiname":"Cerro la Mina",
    "gn:country_code":"MX",
    "gn:dem":2520,
    "gn:feature_class":"P",
    "gn:feature_code":"PPL",
    "gn:name":"Cerro la Mina",
    "gn:population":0,
    "gn:timezone":"America/Mexico_City",
    "iso:country":"MX",
    "name:spa_x_preferred":[
        "Cerro la Mina"
    ],
    "wof:name":"Cerro la Mina",
    "wof:placetype":"locality"
},
  "geometry": {"coordinates":[-100.67074,19.50512],"type":"Point"}
}