{
  "type": "Feature",
  "properties": {
    "gn:admin1_code":"26.0",
    "gn:admin2_code":"3.0",
    "gn:asciiname":"Chacari",
    "gn:country_code":"MX",
    "gn:dem":268,
    "gn:feature_class":"P",
    "gn:feature_code":"PPL",
    "gn:name":"Chacari",
    "gn:population":0,
    "gn:timezone":"America/Hermosillo",
    "iso:country":"MX",
    "name:spa_x_preferred":[
        "Chacari"
    ],
    "wof:name":"Chacari",
    "wof:placetype":"locality"
},
  "geometry": {"coordinates":[-108.82342,27.43903],"type":"Point"}
}