{
  "type": "Feature",
  "properties": {
    "gn:admin1_code":"26",
    "gn:admin2_code":"3.0",
    "gn:asciiname":"Vallecito",
    "gn:cc2":"MX",
    "gn:country_code":"MX",
    "gn:dem":191,
    "gn:feature_class":"P",
    "gn:feature_code":"PPL",
    "gn:name":"Vallecito",
    "gn:population":0,
    "gn:timezone":"America/Hermosillo",
    "iso:country":"MX",
    "name:ceb_x_preferred":[
        "Vallecito"
    ],
    "name:deu_x_preferred":[
        "Vallecito"
    ],
    "name:swe_x_preferred":[
        "Vallecito"
    ],
    "name:und_x_variant":[
        "Vallecitos",
        "Vallecito"
    ],
    "wof:name":"Vallecito",
    "wof:placetype":"locality"
},
  "geometry": {"coordinates":[-108.58333,26.85],"type":"Point"}
}