{
  "type": "Feature",
  "properties": {
    "gn:admin1_code":"7.0",
    "gn:admin2_code":"30.0",
    "gn:asciiname":"Estacion Fraile",
    "gn:country_code":"MX",
    "gn:dem":2031,
    "gn:feature_class":"P",
    "gn:feature_code":"PPL",
    "gn:name":"Estaci\u00f3n Fraile",
    "gn:population":0,
    "gn:timezone":"America/Monterrey",
    "iso:country":"MX",
    "wof:name":"Estacion Fraile",
    "wof:placetype":"locality"
},
  "geometry": {"coordinates":[-101.31667,25.03333],"type":"Point"}
}