{
  "type": "Feature",
  "properties": {
    "gn:admin1_code":"12.0",
    "gn:admin2_code":"48.0",
    "gn:asciiname":"Cayacal",
    "gn:country_code":"MX",
    "gn:dem":24,
    "gn:feature_class":"P",
    "gn:feature_code":"PPL",
    "gn:name":"Cayacal",
    "gn:population":0,
    "gn:timezone":"America/Mexico_City",
    "iso:country":"MX",
    "name:spa_x_preferred":[
        "Cayacal"
    ],
    "name:und_x_variant":[
        "El Cavacal",
        "Calvario"
    ],
    "wof:name":"Cayacal",
    "wof:placetype":"locality"
},
  "geometry": {"coordinates":[-101.16052000000001,17.38857],"type":"Point"}
}