{
  "type": "Feature",
  "properties": {
    "gn:admin1_code":"20",
    "gn:admin2_code":"366",
    "gn:asciiname":"El Comejen",
    "gn:country_code":"MX",
    "gn:dem":1117,
    "gn:feature_class":"P",
    "gn:feature_code":"PPL",
    "gn:name":"El Comej\u00e9n",
    "gn:population":34,
    "gn:timezone":"America/Mexico_City",
    "iso:country":"MX",
    "name:und_x_variant":[
        "El Comej\u00e9n"
    ],
    "wof:name":"El Comejen",
    "wof:placetype":"locality",
    "wof:population":34
},
  "geometry": {"coordinates":[-96.74917000000001,16.06167],"type":"Point"}
}