{
  "type": "Feature",
  "properties": {
    "gn:admin1_code":"13",
    "gn:admin2_code":"44.0",
    "gn:asciiname":"Batha",
    "gn:country_code":"MX",
    "gn:dem":2318,
    "gn:feature_class":"P",
    "gn:feature_code":"PPL",
    "gn:name":"Bath\u00e1",
    "gn:population":0,
    "gn:timezone":"America/Mexico_City",
    "iso:country":"MX",
    "name:ceb_x_preferred":[
        "Batha"
    ],
    "name:ces_x_preferred":[
        "Batha"
    ],
    "name:fra_x_preferred":[
        "Batha"
    ],
    "name:ita_x_preferred":[
        "Batha"
    ],
    "name:pol_x_preferred":[
        "Batha"
    ],
    "name:swe_x_preferred":[
        "Batha"
    ],
    "wof:name":"Batha",
    "wof:placetype":"locality"
},
  "geometry": {"coordinates":[-99.72469,20.2446],"type":"Point"}
}