{
  "type": "Feature",
  "properties": {
    "gn:admin1_code":"15",
    "gn:admin2_code":"52.0",
    "gn:asciiname":"La Joya Redonda",
    "gn:country_code":"MX",
    "gn:dem":1682,
    "gn:feature_class":"P",
    "gn:feature_code":"PPL",
    "gn:name":"La Joya Redonda",
    "gn:population":54,
    "gn:timezone":"America/Mexico_City",
    "iso:country":"MX",
    "wof:name":"La Joya Redonda",
    "wof:placetype":"locality",
    "wof:population":54
},
  "geometry": {"coordinates":[-99.52113,18.9021],"type":"Point"}
}