{
  "type": "Feature",
  "properties": {
    "gn:admin1_code":"30",
    "gn:admin2_code":"175",
    "gn:asciiname":"Gil Claudio",
    "gn:country_code":"MX",
    "gn:dem":86,
    "gn:feature_class":"P",
    "gn:feature_code":"PPL",
    "gn:name":"Gil Claudio",
    "gn:population":21,
    "gn:timezone":"America/Mexico_City",
    "iso:country":"MX",
    "wof:name":"Gil Claudio",
    "wof:placetype":"locality",
    "wof:population":21
},
  "geometry": {"coordinates":[-97.58194,20.68861],"type":"Point"}
}