{
  "type": "Feature",
  "properties": {
    "gn:admin1_code":"14",
    "gn:admin2_code":"124.0",
    "gn:asciiname":"La Sauceda",
    "gn:country_code":"MX",
    "gn:dem":1490,
    "gn:feature_class":"P",
    "gn:feature_code":"PPL",
    "gn:name":"La Sauceda",
    "gn:population":14,
    "gn:timezone":"America/Mexico_City",
    "iso:country":"MX",
    "wof:name":"La Sauceda",
    "wof:placetype":"locality",
    "wof:population":14
},
  "geometry": {"coordinates":[-103.0575,20.55],"type":"Point"}
}