{
  "type": "Feature",
  "properties": {
    "gn:admin1_code":"20",
    "gn:admin2_code":"217",
    "gn:asciiname":"Tidua",
    "gn:country_code":"MX",
    "gn:dem":2171,
    "gn:feature_class":"P",
    "gn:feature_code":"PPL",
    "gn:name":"Tidua",
    "gn:population":41,
    "gn:timezone":"America/Mexico_City",
    "iso:country":"MX",
    "wof:name":"Tidua",
    "wof:placetype":"locality",
    "wof:population":41
},
  "geometry": {"coordinates":[-97.20972,17.11083],"type":"Point"}
}