{
  "type": "Feature",
  "properties": {
    "gn:admin1_code":"10",
    "gn:admin2_code":"34",
    "gn:asciiname":"Los Coyotes",
    "gn:country_code":"MX",
    "gn:dem":391,
    "gn:feature_class":"P",
    "gn:feature_code":"PPL",
    "gn:name":"Los Coyotes",
    "gn:population":38,
    "gn:timezone":"America/Monterrey",
    "iso:country":"MX",
    "wof:name":"Los Coyotes",
    "wof:placetype":"locality",
    "wof:population":38
},
  "geometry": {"coordinates":[-106.97759000000001,25.09053],"type":"Point"}
}