{
  "type": "Feature",
  "properties": {
    "gn:admin1_code":"22",
    "gn:admin2_code":"4.0",
    "gn:asciiname":"San Jose del Catiteo",
    "gn:country_code":"MX",
    "gn:dem":2587,
    "gn:feature_class":"P",
    "gn:feature_code":"PPL",
    "gn:name":"San Jos\u00e9 del Catiteo",
    "gn:population":110,
    "gn:timezone":"America/Mexico_City",
    "iso:country":"MX",
    "name:und_x_variant":[
        "San Jos\u00e9 del Catiteo"
    ],
    "wof:name":"San Jose del Catiteo",
    "wof:placetype":"locality",
    "wof:population":110
},
  "geometry": {"coordinates":[-99.58556,20.89889],"type":"Point"}
}