{
  "type": "Feature",
  "properties": {
    "gn:admin1_code":"5",
    "gn:admin2_code":"7",
    "gn:asciiname":"San Jose la Florecilla",
    "gn:country_code":"MX",
    "gn:dem":2298,
    "gn:feature_class":"P",
    "gn:feature_code":"PPL",
    "gn:name":"San Jos\u00e9 la Florecilla",
    "gn:population":25,
    "gn:timezone":"America/Mexico_City",
    "iso:country":"MX",
    "name:und_x_variant":[
        "San Jos\u00e9 la Florecilla"
    ],
    "wof:name":"San Jose la Florecilla",
    "wof:placetype":"locality",
    "wof:population":25
},
  "geometry": {"coordinates":[-92.33360999999999,16.52778],"type":"Point"}
}