{
  "type": "Feature",
  "properties": {
    "gn:admin1_code":"4",
    "gn:admin2_code":"11.0",
    "gn:asciiname":"El Guamuchilito",
    "gn:country_code":"MX",
    "gn:dem":39,
    "gn:feature_class":"P",
    "gn:feature_code":"PPL",
    "gn:name":"El Guamuchilito",
    "gn:population":5,
    "gn:timezone":"America/Merida",
    "iso:country":"MX",
    "wof:name":"El Guamuchilito",
    "wof:placetype":"locality",
    "wof:population":5
},
  "geometry": {"coordinates":[-91.03528,18.18028],"type":"Point"}
}