{
  "type": "Feature",
  "properties": {
    "gn:admin1_code":"12",
    "gn:admin2_code":"29.0",
    "gn:asciiname":"Xoxomanatlan",
    "gn:country_code":"MX",
    "gn:dem":1887,
    "gn:feature_class":"P",
    "gn:feature_code":"PPL",
    "gn:name":"Xoxomanatl\u00e1n",
    "gn:population":0,
    "gn:timezone":"America/Mexico_City",
    "iso:country":"MX",
    "name:spa_x_preferred":[
        "Xoxomanatl\u00e1n"
    ],
    "name:spa_x_variant":[
        "Xocomanatl\u00e1n"
    ],
    "wof:name":"Xoxomanatlan",
    "wof:placetype":"locality"
},
  "geometry": {"coordinates":[-99.63485,17.55026],"type":"Point"}
}