{
  "type": "Feature",
  "properties": {
    "gn:admin1_code":"30",
    "gn:admin2_code":"45",
    "gn:asciiname":"Laguna Larga",
    "gn:country_code":"MX",
    "gn:dem":16,
    "gn:feature_class":"P",
    "gn:feature_code":"PPL",
    "gn:name":"Laguna Larga",
    "gn:population":13,
    "gn:timezone":"America/Mexico_City",
    "iso:country":"MX",
    "wof:name":"Laguna Larga",
    "wof:placetype":"locality",
    "wof:population":13
},
  "geometry": {"coordinates":[-95.93222,18.28444],"type":"Point"}
}