{
  "type": "Feature",
  "properties": {
    "gn:admin1_code":"15",
    "gn:admin2_code":"63.0",
    "gn:asciiname":"Ahuatenco",
    "gn:country_code":"MX",
    "gn:dem":1939,
    "gn:feature_class":"P",
    "gn:feature_code":"PPL",
    "gn:name":"Ahuatenco",
    "gn:population":960,
    "gn:timezone":"America/Mexico_City",
    "iso:country":"MX",
    "wof:name":"Ahuatenco",
    "wof:placetype":"locality",
    "wof:population":960
},
  "geometry": {"coordinates":[-99.33278,18.94778],"type":"Point"}
}