{
  "type": "Feature",
  "properties": {
    "gn:admin1_code":"30",
    "gn:admin2_code":"55.0",
    "gn:asciiname":"La Puente",
    "gn:country_code":"MX",
    "gn:dem":97,
    "gn:feature_class":"P",
    "gn:feature_code":"PPL",
    "gn:name":"La Puente",
    "gn:population":1,
    "gn:timezone":"America/Mexico_City",
    "iso:country":"MX",
    "name:spa_x_preferred":[
        "La Puente"
    ],
    "wof:name":"La Puente",
    "wof:placetype":"locality",
    "wof:population":1
},
  "geometry": {"coordinates":[-98.32250000000001,21.18278],"type":"Point"}
}