{
  "type": "Feature",
  "properties": {
    "gn:admin1_code":"30",
    "gn:admin2_code":"71.0",
    "gn:asciiname":"Cotecontla",
    "gn:country_code":"MX",
    "gn:dem":1070,
    "gn:feature_class":"P",
    "gn:feature_code":"PPL",
    "gn:name":"Cotecontla",
    "gn:population":408,
    "gn:timezone":"America/Mexico_City",
    "iso:country":"MX",
    "wof:name":"Cotecontla",
    "wof:placetype":"locality",
    "wof:population":408
},
  "geometry": {"coordinates":[-96.90917,19.11917],"type":"Point"}
}