{
  "type": "Feature",
  "properties": {
    "gn:admin1_code":"11.0",
    "gn:admin2_code":"4.0",
    "gn:asciiname":"San Isidro del Llanito",
    "gn:country_code":"MX",
    "gn:dem":1799,
    "gn:feature_class":"P",
    "gn:feature_code":"PPL",
    "gn:name":"San Isidro del Llanito",
    "gn:population":0,
    "gn:timezone":"America/Mexico_City",
    "iso:country":"MX",
    "name:spa_x_preferred":[
        "San Isidro del Llanito"
    ],
    "wof:name":"San Isidro del Llanito",
    "wof:placetype":"locality"
},
  "geometry": {"coordinates":[-100.53924000000001,20.52162],"type":"Point"}
}