{
  "type": "Feature",
  "properties": {
    "gn:admin1_code":"25",
    "gn:admin2_code":"17.0",
    "gn:asciiname":"Ahuama",
    "gn:country_code":"MX",
    "gn:dem":298,
    "gn:feature_class":"P",
    "gn:feature_code":"PPL",
    "gn:name":"Ahuama",
    "gn:population":0,
    "gn:timezone":"America/Mazatlan",
    "iso:country":"MX",
    "name:spa_x_preferred":[
        "Ahuama"
    ],
    "wof:name":"Ahuama",
    "wof:placetype":"locality"
},
  "geometry": {"coordinates":[-108.01699000000001,25.76288],"type":"Point"}
}