{
  "type": "Feature",
  "properties": {
    "gn:admin1_code":"4",
    "gn:admin2_code":"4.0",
    "gn:asciiname":"Monte Frio (El Molon)",
    "gn:country_code":"MX",
    "gn:dem":4,
    "gn:feature_class":"P",
    "gn:feature_code":"PPL",
    "gn:name":"Monte Frio (El Mol\u00f3n)",
    "gn:population":4,
    "gn:timezone":"America/Merida",
    "iso:country":"MX",
    "name:und_x_variant":[
        "Monte Frio (El Mol\u00f3n)"
    ],
    "wof:name":"Monte Frio (El Molon)",
    "wof:placetype":"locality",
    "wof:population":4
},
  "geometry": {"coordinates":[-90.67778,19.63056],"type":"Point"}
}