{
  "type": "Feature",
  "properties": {
    "gn:admin1_code":"30.0",
    "gn:asciiname":"Cerro Chino",
    "gn:country_code":"MX",
    "gn:dem":82,
    "gn:feature_class":"P",
    "gn:feature_code":"PPL",
    "gn:name":"Cerro Chino",
    "gn:population":0,
    "gn:timezone":"America/Mexico_City",
    "iso:country":"MX",
    "name:spa_x_preferred":[
        "Cerro Chino"
    ],
    "wof:name":"Cerro Chino",
    "wof:placetype":"locality"
},
  "geometry": {"coordinates":[-97.64999,20.82122],"type":"Point"}
}