{
  "type": "Feature",
  "properties": {
    "gn:admin1_code":"19",
    "gn:admin2_code":"33.0",
    "gn:asciiname":"Loma el Perico",
    "gn:country_code":"MX",
    "gn:dem":394,
    "gn:feature_class":"P",
    "gn:feature_code":"PPL",
    "gn:name":"Loma el Perico",
    "gn:population":139,
    "gn:timezone":"America/Monterrey",
    "iso:country":"MX",
    "wof:name":"Loma el Perico",
    "wof:placetype":"locality",
    "wof:population":139
},
  "geometry": {"coordinates":[-99.58944,24.81028],"type":"Point"}
}