{
  "type": "Feature",
  "properties": {
    "gn:admin1_code":"16",
    "gn:admin2_code":"52.0",
    "gn:asciiname":"El Colomo",
    "gn:country_code":"MX",
    "gn:dem":358,
    "gn:feature_class":"P",
    "gn:feature_code":"PPL",
    "gn:name":"El Colomo",
    "gn:population":0,
    "gn:timezone":"America/Mexico_City",
    "iso:country":"MX",
    "name:spa_x_preferred":[
        "El Colomo"
    ],
    "wof:name":"El Colomo",
    "wof:placetype":"locality"
},
  "geometry": {"coordinates":[-102.28361,18.18895],"type":"Point"}
}