{
  "type": "Feature",
  "properties": {
    "gn:admin1_code":"29",
    "gn:admin2_code":"12.0",
    "gn:asciiname":"San Miguel Tepalca",
    "gn:country_code":"MX",
    "gn:dem":2555,
    "gn:feature_class":"P",
    "gn:feature_code":"PPL",
    "gn:name":"San Miguel Tepalca",
    "gn:population":0,
    "gn:timezone":"America/Mexico_City",
    "iso:country":"MX",
    "name:spa_x_preferred":[
        "San Miguel Tepalca"
    ],
    "name:und_x_variant":[
        "San Miguel Tepalc"
    ],
    "wof:name":"San Miguel Tepalca",
    "wof:placetype":"locality"
},
  "geometry": {"coordinates":[-98.38733000000001,19.43169],"type":"Point"}
}