{
  "type": "Feature",
  "properties": {
    "gn:admin1_code":"15",
    "gn:admin2_code":"101.0",
    "gn:asciiname":"Tzitzicazapa",
    "gn:country_code":"MX",
    "gn:dem":2889,
    "gn:feature_class":"P",
    "gn:feature_code":"PPL",
    "gn:name":"Tzitzicazapa",
    "gn:population":137,
    "gn:timezone":"America/Mexico_City",
    "iso:country":"MX",
    "wof:name":"Tzitzicazapa",
    "wof:placetype":"locality",
    "wof:population":137
},
  "geometry": {"coordinates":[-99.39267,19.14077],"type":"Point"}
}