{
  "type": "Feature",
  "properties": {
    "gn:admin1_code":"30",
    "gn:admin2_code":"40.0",
    "gn:asciiname":"La Grandeza",
    "gn:country_code":"MX",
    "gn:dem":72,
    "gn:feature_class":"P",
    "gn:feature_code":"PPL",
    "gn:name":"La Grandeza",
    "gn:population":9,
    "gn:timezone":"America/Mexico_City",
    "iso:country":"MX",
    "name:ceb_x_preferred":[
        "La Grandeza"
    ],
    "name:deu_x_preferred":[
        "Municipio La Grandeza"
    ],
    "name:epo_x_preferred":[
        "La Grandeza"
    ],
    "name:eus_x_preferred":[
        "La Grandeza"
    ],
    "name:fra_x_preferred":[
        "La Grandeza"
    ],
    "name:por_x_preferred":[
        "La Grandeza"
    ],
    "name:rus_x_preferred":[
        "\u041b\u0430-\u0413\u0440\u0430\u043d\u0434\u0435\u0441\u0430"
    ],
    "name:sco_x_preferred":[
        "La Grandeza"
    ],
    "name:spa_x_preferred":[
        "La Grandeza"
    ],
    "name:srp_x_preferred":[
        "\u041e\u043f\u0448\u0442\u0438\u043d\u0430 \u041b\u0430 \u0413\u0440\u0430\u043d\u0434\u0435\u0437\u0430"
    ],
    "name:swe_x_preferred":[
        "La Grandeza"
    ],
    "name:urd_x_preferred":[
        "\u0644\u0627 \u06af\u0631\u0627\u0646\u062f\u06cc\u0632\u0627"
    ],
    "name:vie_x_preferred":[
        "La Grandeza"
    ],
    "wof:name":"La Grandeza",
    "wof:placetype":"locality",
    "wof:population":9
},
  "geometry": {"coordinates":[-97.49806,20.4875],"type":"Point"}
}