{
  "type": "Feature",
  "properties": {
    "gn:admin1_code":"30",
    "gn:admin2_code":"40.0",
    "gn:asciiname":"La Grandeza",
    "gn:country_code":"MX",
    "gn:dem":72,
    "gn:feature_class":"P",
    "gn:feature_code":"PPL",
    "gn:name":"La Grandeza",
    "gn:population":9,
    "gn:timezone":"America/Mexico_City",
    "iso:country":"MX",
    "wof:name":"La Grandeza",
    "wof:placetype":"locality",
    "wof:population":9
},
  "geometry": {"coordinates":[-97.49806,20.4875],"type":"Point"}
}