{
  "type": "Feature",
  "properties": {
    "gn:admin1_code":"12",
    "gn:admin2_code":"21.0",
    "gn:asciiname":"Ocotillo",
    "gn:country_code":"MX",
    "gn:dem":713,
    "gn:feature_class":"P",
    "gn:feature_code":"PPL",
    "gn:name":"Ocotillo",
    "gn:population":0,
    "gn:timezone":"America/Mexico_City",
    "iso:country":"MX",
    "name:spa_x_preferred":[
        "Ocotillo"
    ],
    "wof:name":"Ocotillo",
    "wof:placetype":"locality"
},
  "geometry": {"coordinates":[-99.87671,17.03551],"type":"Point"}
}