{
  "type": "Feature",
  "properties": {
    "gn:admin1_code":"15",
    "gn:admin2_code":"82",
    "gn:asciiname":"Lomas de Tejupilco",
    "gn:country_code":"MX",
    "gn:dem":1353,
    "gn:feature_class":"P",
    "gn:feature_code":"PPL",
    "gn:name":"Lomas de Tejupilco",
    "gn:population":50,
    "gn:timezone":"America/Mexico_City",
    "iso:country":"MX",
    "wof:name":"Lomas de Tejupilco",
    "wof:placetype":"locality",
    "wof:population":50
},
  "geometry": {"coordinates":[-100.14623,18.90733],"type":"Point"}
}