{
  "type": "Feature",
  "properties": {
    "gn:admin1_code":"24",
    "gn:admin2_code":"35",
    "gn:asciiname":"Familia Escobedo Partida",
    "gn:country_code":"MX",
    "gn:dem":1843,
    "gn:feature_class":"P",
    "gn:feature_code":"PPL",
    "gn:name":"Familia Escobedo Partida",
    "gn:population":11,
    "gn:timezone":"America/Mexico_City",
    "iso:country":"MX",
    "wof:name":"Familia Escobedo Partida",
    "wof:placetype":"locality",
    "wof:population":11
},
  "geometry": {"coordinates":[-100.90139000000001,22.20111],"type":"Point"}
}