{
  "type": "Feature",
  "properties": {
    "gn:admin1_code":"25.0",
    "gn:admin2_code":"11.0",
    "gn:asciiname":"Ranchito de Zavala",
    "gn:country_code":"MX",
    "gn:dem":41,
    "gn:feature_class":"P",
    "gn:feature_code":"PPL",
    "gn:name":"Ranchito de Zavala",
    "gn:population":668,
    "gn:timezone":"America/Mazatlan",
    "iso:country":"MX",
    "wof:name":"Ranchito de Zavala",
    "wof:placetype":"locality",
    "wof:population":668
},
  "geometry": {"coordinates":[-108.31968000000001,25.71878],"type":"Point"}
}