{
  "type": "Feature",
  "properties": {
    "gn:admin1_code":"5",
    "gn:admin2_code":"61.0",
    "gn:asciiname":"El Guapinolito",
    "gn:country_code":"MX",
    "gn:dem":794,
    "gn:feature_class":"P",
    "gn:feature_code":"PPL",
    "gn:name":"El Guapinolito",
    "gn:population":114,
    "gn:timezone":"America/Mexico_City",
    "iso:country":"MX",
    "wof:name":"El Guapinolito",
    "wof:placetype":"locality",
    "wof:population":114
},
  "geometry": {"coordinates":[-93.48111,16.48694],"type":"Point"}
}