{
  "type": "Feature",
  "properties": {
    "gn:admin1_code":"32.0",
    "gn:admin2_code":"10.0",
    "gn:asciiname":"Los Verdes",
    "gn:country_code":"MX",
    "gn:dem":2065,
    "gn:feature_class":"P",
    "gn:feature_code":"PPL",
    "gn:name":"Los Verdes",
    "gn:population":0,
    "gn:timezone":"America/Mexico_City",
    "iso:country":"MX",
    "name:spa_x_preferred":[
        "Los Verdes"
    ],
    "wof:name":"Los Verdes",
    "wof:placetype":"locality"
},
  "geometry": {"coordinates":[-103.07991,23.21512],"type":"Point"}
}