{
  "type": "Feature",
  "properties": {
    "gn:admin1_code":"17",
    "gn:admin2_code":"22.0",
    "gn:asciiname":"Tlalcomulco",
    "gn:country_code":"MX",
    "gn:dem":2138,
    "gn:feature_class":"P",
    "gn:feature_code":"PPL",
    "gn:name":"Tlalcomulco",
    "gn:population":71,
    "gn:timezone":"America/Mexico_City",
    "iso:country":"MX",
    "wof:name":"Tlalcomulco",
    "wof:placetype":"locality",
    "wof:population":71
},
  "geometry": {"coordinates":[-98.70611,18.85667],"type":"Point"}
}