{
  "type": "Feature",
  "properties": {
    "gn:admin1_code":"20",
    "gn:admin2_code":"278.0",
    "gn:asciiname":"Arroyo Caracol",
    "gn:country_code":"MX",
    "gn:dem":97,
    "gn:feature_class":"P",
    "gn:feature_code":"PPL",
    "gn:name":"Arroyo Caracol",
    "gn:population":247,
    "gn:timezone":"America/Mexico_City",
    "iso:country":"MX",
    "wof:name":"Arroyo Caracol",
    "wof:placetype":"locality",
    "wof:population":247
},
  "geometry": {"coordinates":[-96.47556,18.29972],"type":"Point"}
}