{
  "type": "Feature",
  "properties": {
    "gn:admin1_code":"28.0",
    "gn:admin2_code":"34.0",
    "gn:asciiname":"Lazaro Cardenas",
    "gn:country_code":"MX",
    "gn:dem":207,
    "gn:feature_class":"P",
    "gn:feature_code":"PPL",
    "gn:name":"L\u00e1zaro C\u00e1rdenas",
    "gn:population":9,
    "gn:timezone":"America/Monterrey",
    "iso:country":"MX",
    "name:spa_x_preferred":[
        "L\u00e1zaro C\u00e1rdenas"
    ],
    "wof:name":"Lazaro Cardenas",
    "wof:placetype":"locality",
    "wof:population":9
},
  "geometry": {"coordinates":[-99.12678,24.33007000000001],"type":"Point"}
}