{
  "type": "Feature",
  "properties": {
    "gn:admin1_code":"13",
    "gn:admin2_code":"35.0",
    "gn:asciiname":"El Ocote",
    "gn:country_code":"MX",
    "gn:dem":2172,
    "gn:feature_class":"P",
    "gn:feature_code":"PPL",
    "gn:name":"El Ocote",
    "gn:population":0,
    "gn:timezone":"America/Mexico_City",
    "iso:country":"MX",
    "wof:name":"El Ocote",
    "wof:placetype":"locality"
},
  "geometry": {"coordinates":[-98.38333,20.21667],"type":"Point"}
}