{
  "type": "Feature",
  "properties": {
    "gn:admin1_code":"26.0",
    "gn:admin2_code":"69.0",
    "gn:asciiname":"Los Alamillos",
    "gn:country_code":"MX",
    "gn:dem":1332,
    "gn:feature_class":"P",
    "gn:feature_code":"PPL",
    "gn:name":"Los Alamillos",
    "gn:population":0,
    "gn:timezone":"America/Hermosillo",
    "iso:country":"MX",
    "name:spa_x_preferred":[
        "Los Alamillos"
    ],
    "wof:name":"Los Alamillos",
    "wof:placetype":"locality"
},
  "geometry": {"coordinates":[-108.78576,28.33283],"type":"Point"}
}