{
  "type": "Feature",
  "properties": {
    "gn:admin1_code":"10",
    "gn:admin2_code":"13.0",
    "gn:asciiname":"El Chivo",
    "gn:country_code":"MX",
    "gn:dem":1182,
    "gn:feature_class":"P",
    "gn:feature_code":"PPL",
    "gn:name":"El Chivo",
    "gn:population":0,
    "gn:timezone":"America/Monterrey",
    "iso:country":"MX",
    "name:bul_x_preferred":[
        "\u041a\u043e\u0437\u0435\u043b\u044a\u0442"
    ],
    "name:fas_x_preferred":[
        "\u0627\u0644 \u0686\u06cc\u0648\u0648"
    ],
    "name:spa_x_preferred":[
        "El Chivo"
    ],
    "wof:name":"El Chivo",
    "wof:placetype":"locality"
},
  "geometry": {"coordinates":[-104.16078,26.59488],"type":"Point"}
}