{
  "type": "Feature",
  "properties": {
    "gn:admin1_code":"32",
    "gn:admin2_code":"10",
    "gn:asciiname":"San Pedro Cerro Gordo (Las Culecas)",
    "gn:country_code":"MX",
    "gn:dem":2191,
    "gn:feature_class":"P",
    "gn:feature_code":"PPL",
    "gn:name":"San Pedro Cerro Gordo (Las Culecas)",
    "gn:population":44,
    "gn:timezone":"America/Mexico_City",
    "iso:country":"MX",
    "wof:name":"San Pedro Cerro Gordo (Las Culecas)",
    "wof:placetype":"locality",
    "wof:population":44
},
  "geometry": {"coordinates":[-102.91611,23.25528],"type":"Point"}
}