{
  "type": "Feature",
  "properties": {
    "gn:admin1_code":"20.0",
    "gn:asciiname":"Cerro Plumaje",
    "gn:country_code":"MX",
    "gn:dem":734,
    "gn:feature_class":"P",
    "gn:feature_code":"PPL",
    "gn:name":"Cerro Plumaje",
    "gn:population":0,
    "gn:timezone":"America/Mexico_City",
    "iso:country":"MX",
    "name:spa_x_preferred":[
        "Cerro Plumaje"
    ],
    "wof:name":"Cerro Plumaje",
    "wof:placetype":"locality"
},
  "geometry": {"coordinates":[-96.68974,18.21883],"type":"Point"}
}