{
  "type": "Feature",
  "properties": {
    "gn:admin1_code":"28",
    "gn:admin2_code":"8.0",
    "gn:asciiname":"La Saga",
    "gn:country_code":"MX",
    "gn:dem":837,
    "gn:feature_class":"P",
    "gn:feature_code":"PPL",
    "gn:name":"La Saga",
    "gn:population":0,
    "gn:timezone":"America/Monterrey",
    "iso:country":"MX",
    "name:spa_x_preferred":[
        "La Saga"
    ],
    "wof:name":"La Saga",
    "wof:placetype":"locality"
},
  "geometry": {"coordinates":[-98.51802000000001,23.42366],"type":"Point"}
}