{
  "type": "Feature",
  "properties": {
    "gn:admin1_code":"4",
    "gn:admin2_code":"3.0",
    "gn:asciiname":"Bella Palizada",
    "gn:country_code":"MX",
    "gn:dem":2,
    "gn:feature_class":"P",
    "gn:feature_code":"PPL",
    "gn:name":"Bella Palizada",
    "gn:population":0,
    "gn:timezone":"America/Merida",
    "iso:country":"MX",
    "name:spa_x_preferred":[
        "Bella Palizada"
    ],
    "wof:name":"Bella Palizada",
    "wof:placetype":"locality"
},
  "geometry": {"coordinates":[-91.22033,18.5799],"type":"Point"}
}