{
  "type": "Feature",
  "properties": {
    "gn:admin1_code":"32.0",
    "gn:admin2_code":"31.0",
    "gn:asciiname":"Ojo de Agua de Alvarez",
    "gn:country_code":"MX",
    "gn:dem":2359,
    "gn:feature_class":"P",
    "gn:feature_code":"PPL",
    "gn:name":"Ojo de Agua de Alvarez",
    "gn:population":0,
    "gn:timezone":"America/Mexico_City",
    "iso:country":"MX",
    "name:spa_x_preferred":[
        "Ojo de Agua de Alvarez"
    ],
    "wof:name":"Ojo de Agua de Alvarez",
    "wof:placetype":"locality"
},
  "geometry": {"coordinates":[-103.58399,22.31297],"type":"Point"}
}