{
  "type": "Feature",
  "properties": {
    "gn:admin1_code":"30",
    "gn:admin2_code":"69.0",
    "gn:asciiname":"Ignacio Manuel Altamirano",
    "gn:country_code":"MX",
    "gn:dem":34,
    "gn:feature_class":"P",
    "gn:feature_code":"PPL",
    "gn:name":"Ignacio Manuel Altamirano",
    "gn:population":0,
    "gn:timezone":"America/Mexico_City",
    "iso:country":"MX",
    "name:afr_x_preferred":[
        "Ignacio Manuel Altamirano"
    ],
    "name:ara_x_preferred":[
        "\u0623\u062c\u0646\u0627\u0633\u064a\u0648 \u0645\u0627\u0646\u0648\u064a\u0644 \u0627\u0644\u062a\u0627\u0645\u064a\u0631\u0627\u0646\u0648"
    ],
    "name:cat_x_preferred":[
        "Ignacio Manuel Altamirano"
    ],
    "name:epo_x_preferred":[
        "Ignacio Manuel Altamirano"
    ],
    "name:fra_x_preferred":[
        "Ignacio Manuel Altamirano"
    ],
    "name:ina_x_preferred":[
        "Ignacio Manuel Altamirano"
    ],
    "name:ind_x_preferred":[
        "Ignacio Manuel Altamirano"
    ],
    "name:ita_x_preferred":[
        "Ignacio Manuel Altamirano"
    ],
    "name:nah_x_preferred":[
        "Ignacio Manuel Altamirano"
    ],
    "name:nld_x_preferred":[
        "Ignacio Manuel Altamirano"
    ],
    "name:pol_x_preferred":[
        "Ignacio Manuel Altamirano"
    ],
    "name:por_x_preferred":[
        "Ignacio Manuel Altamirano"
    ],
    "name:ron_x_preferred":[
        "Ignacio Manuel Altamirano"
    ],
    "name:rus_x_preferred":[
        "\u0410\u043b\u044c\u0442\u0430\u043c\u0438\u0440\u0430\u043d\u043e"
    ],
    "name:sco_x_preferred":[
        "Ignacio Manuel Altamirano"
    ],
    "name:spa_x_preferred":[
        "Ignacio Manuel Altamirano"
    ],
    "name:und_x_variant":[
        "El Plan"
    ],
    "wof:name":"Ignacio Manuel Altamirano",
    "wof:placetype":"locality"
},
  "geometry": {"coordinates":[-97.13217,20.38537],"type":"Point"}
}