{
  "type": "Feature",
  "properties": {
    "gn:admin1_code":"30",
    "gn:admin2_code":"69.0",
    "gn:asciiname":"Ignacio Manuel Altamirano",
    "gn:country_code":"MX",
    "gn:dem":34,
    "gn:feature_class":"P",
    "gn:feature_code":"PPL",
    "gn:name":"Ignacio Manuel Altamirano",
    "gn:population":0,
    "gn:timezone":"America/Mexico_City",
    "iso:country":"MX",
    "name:und_x_variant":[
        "El Plan"
    ],
    "wof:name":"Ignacio Manuel Altamirano",
    "wof:placetype":"locality"
},
  "geometry": {"coordinates":[-97.13217,20.38537],"type":"Point"}
}