{
  "type": "Feature",
  "properties": {
    "gn:admin1_code":"16.0",
    "gn:admin2_code":"70.0",
    "gn:asciiname":"Corral de la Mula",
    "gn:country_code":"MX",
    "gn:dem":2055,
    "gn:feature_class":"P",
    "gn:feature_code":"PPL",
    "gn:name":"Corral de la Mula",
    "gn:population":0,
    "gn:timezone":"America/Mexico_City",
    "iso:country":"MX",
    "wof:name":"Corral de la Mula",
    "wof:placetype":"locality"
},
  "geometry": {"coordinates":[-101.96666999999999,19.95],"type":"Point"}
}