{
  "type": "Feature",
  "properties": {
    "gn:admin1_code":"2.0",
    "gn:admin2_code":"4.0",
    "gn:asciiname":"El Juncalito",
    "gn:country_code":"MX",
    "gn:dem":291,
    "gn:feature_class":"P",
    "gn:feature_code":"PPL",
    "gn:name":"El Juncalito",
    "gn:population":8,
    "gn:timezone":"America/Tijuana",
    "iso:country":"MX",
    "name:spa_x_preferred":[
        "El Juncalito"
    ],
    "wof:name":"El Juncalito",
    "wof:placetype":"locality",
    "wof:population":8
},
  "geometry": {"coordinates":[-116.67083,32.43444],"type":"Point"}
}