{
  "type": "Feature",
  "properties": {
    "gn:admin1_code":"25",
    "gn:admin2_code":"3.0",
    "gn:asciiname":"Lo de Gabriel",
    "gn:country_code":"MX",
    "gn:dem":633,
    "gn:feature_class":"P",
    "gn:feature_code":"PPL",
    "gn:name":"Lo de Gabriel",
    "gn:population":114,
    "gn:timezone":"America/Mazatlan",
    "iso:country":"MX",
    "wof:name":"Lo de Gabriel",
    "wof:placetype":"locality",
    "wof:population":114
},
  "geometry": {"coordinates":[-107.35278,25.78472],"type":"Point"}
}