{
  "type": "Feature",
  "properties": {
    "gn:admin1_code":"13.0",
    "gn:admin2_code":"25.0",
    "gn:asciiname":"Huitzatlaco",
    "gn:country_code":"MX",
    "gn:dem":381,
    "gn:feature_class":"P",
    "gn:feature_code":"PPL",
    "gn:name":"Huitzatlaco",
    "gn:population":0,
    "gn:timezone":"America/Mexico_City",
    "iso:country":"MX",
    "name:spa_x_preferred":[
        "Huitzatlaco"
    ],
    "wof:name":"Huitzatlaco",
    "wof:placetype":"locality"
},
  "geometry": {"coordinates":[-98.21561,20.99367],"type":"Point"}
}