{
  "type": "Feature",
  "properties": {
    "gn:admin1_code":"30.0",
    "gn:asciiname":"El Esfuerzo",
    "gn:country_code":"MX",
    "gn:dem":61,
    "gn:feature_class":"P",
    "gn:feature_code":"PPL",
    "gn:name":"El Esfuerzo",
    "gn:population":0,
    "gn:timezone":"America/Mexico_City",
    "iso:country":"MX",
    "name:spa_x_preferred":[
        "El Esfuerzo"
    ],
    "wof:name":"El Esfuerzo",
    "wof:placetype":"locality"
},
  "geometry": {"coordinates":[-95.82428,17.80072999999999],"type":"Point"}
}