{
  "type": "Feature",
  "properties": {
    "gn:admin1_code":"6.0",
    "gn:asciiname":"El Gran Chaparral",
    "gn:country_code":"MX",
    "gn:dem":1665,
    "gn:feature_class":"P",
    "gn:feature_code":"PPL",
    "gn:name":"El Gran Chaparral",
    "gn:population":0,
    "gn:timezone":"America/Chihuahua",
    "iso:country":"MX",
    "name:spa_x_preferred":[
        "El Gran Chaparral"
    ],
    "wof:name":"El Gran Chaparral",
    "wof:placetype":"locality"
},
  "geometry": {"coordinates":[-105.64775,27.09915],"type":"Point"}
}