{
  "type": "Feature",
  "properties": {
    "gn:admin1_code":"14.0",
    "gn:admin2_code":"49.0",
    "gn:asciiname":"Cachalaquilla",
    "gn:country_code":"MX",
    "gn:dem":617,
    "gn:feature_class":"P",
    "gn:feature_code":"PPL",
    "gn:name":"Cachalaquilla",
    "gn:population":0,
    "gn:timezone":"America/Mexico_City",
    "iso:country":"MX",
    "name:spa_x_preferred":[
        "Cachalaquilla"
    ],
    "wof:name":"Cachalaquilla",
    "wof:placetype":"locality"
},
  "geometry": {"coordinates":[-102.91091,19.30763],"type":"Point"}
}