{
  "type": "Feature",
  "properties": {
    "gn:admin1_code":"6",
    "gn:admin2_code":"55.0",
    "gn:asciiname":"Rancho Cruz Marquez (Rancho la Esperanza)",
    "gn:country_code":"MX",
    "gn:dem":1167,
    "gn:feature_class":"P",
    "gn:feature_code":"PPL",
    "gn:name":"Rancho Cruz M\u00e1rquez (Rancho la Esperanza)",
    "gn:population":4,
    "gn:timezone":"America/Chihuahua",
    "iso:country":"MX",
    "name:und_x_variant":[
        "Rancho Cruz M\u00e1rquez (Rancho la Esperanza)"
    ],
    "wof:name":"Rancho Cruz Marquez (Rancho la Esperanza)",
    "wof:placetype":"locality",
    "wof:population":4
},
  "geometry": {"coordinates":[-105.54797000000001,28.23104],"type":"Point"}
}