{
  "type": "Feature",
  "properties": {
    "gn:admin1_code":"25",
    "gn:admin2_code":"16",
    "gn:asciiname":"La Vainilla",
    "gn:country_code":"MX",
    "gn:dem":848,
    "gn:feature_class":"P",
    "gn:feature_code":"PPL",
    "gn:name":"La Vainilla",
    "gn:population":20,
    "gn:timezone":"America/Mazatlan",
    "iso:country":"MX",
    "wof:name":"La Vainilla",
    "wof:placetype":"locality",
    "wof:population":20
},
  "geometry": {"coordinates":[-106.23445,24.06534],"type":"Point"}
}