{
  "type": "Feature",
  "properties": {
    "gn:admin1_code":"28.0",
    "gn:admin2_code":"21.0",
    "gn:asciiname":"La Mangana Dos",
    "gn:country_code":"MX",
    "gn:dem":28,
    "gn:feature_class":"P",
    "gn:feature_code":"PPL",
    "gn:name":"La Mangana Dos",
    "gn:population":0,
    "gn:timezone":"America/Monterrey",
    "iso:country":"MX",
    "name:spa_x_preferred":[
        "La Mangana Dos"
    ],
    "wof:name":"La Mangana Dos",
    "wof:placetype":"locality"
},
  "geometry": {"coordinates":[-98.62688,22.5886],"type":"Point"}
}