{
  "type": "Feature",
  "properties": {
    "gn:admin1_code":"10",
    "gn:admin2_code":"12.0",
    "gn:asciiname":"Dolores (La Borrega)",
    "gn:country_code":"MX",
    "gn:dem":1130,
    "gn:feature_class":"P",
    "gn:feature_code":"PPL",
    "gn:name":"Dolores (La Borrega)",
    "gn:population":601,
    "gn:timezone":"America/Monterrey",
    "iso:country":"MX",
    "wof:name":"Dolores (La Borrega)",
    "wof:placetype":"locality",
    "wof:population":601
},
  "geometry": {"coordinates":[-103.54944,25.5925],"type":"Point"}
}