{
  "type": "Feature",
  "properties": {
    "gn:admin1_code":"18",
    "gn:admin2_code":"4.0",
    "gn:asciiname":"El Bosque",
    "gn:country_code":"MX",
    "gn:dem":439,
    "gn:feature_class":"P",
    "gn:feature_code":"PPL",
    "gn:name":"El Bosque",
    "gn:population":0,
    "gn:timezone":"America/Mazatlan",
    "iso:country":"MX",
    "name:spa_x_preferred":[
        "El Bosque"
    ],
    "wof:name":"El Bosque",
    "wof:placetype":"locality"
},
  "geometry": {"coordinates":[-105.03533,21.12953],"type":"Point"}
}