{
  "type": "Feature",
  "properties": {
    "gn:admin1_code":"6",
    "gn:admin2_code":"47.0",
    "gn:asciiname":"La Vinata",
    "gn:country_code":"MX",
    "gn:dem":931,
    "gn:feature_class":"P",
    "gn:feature_code":"PPL",
    "gn:name":"La Vinata",
    "gn:population":2,
    "gn:timezone":"America/Chihuahua",
    "iso:country":"MX",
    "name:spa_x_preferred":[
        "La Vinata"
    ],
    "wof:name":"La Vinata",
    "wof:placetype":"locality",
    "wof:population":2
},
  "geometry": {"coordinates":[-108.81202999999999,28.14369000000001],"type":"Point"}
}