{
  "type": "Feature",
  "properties": {
    "gn:admin1_code":"20",
    "gn:admin2_code":"254.0",
    "gn:asciiname":"Tres Cruces",
    "gn:country_code":"MX",
    "gn:dem":2623,
    "gn:feature_class":"P",
    "gn:feature_code":"PPL",
    "gn:name":"Tres Cruces",
    "gn:population":9,
    "gn:timezone":"America/Mexico_City",
    "iso:country":"MX",
    "wof:name":"Tres Cruces",
    "wof:placetype":"locality",
    "wof:population":9
},
  "geometry": {"coordinates":[-96.49472,16.14056],"type":"Point"}
}