{
  "type": "Feature",
  "properties": {
    "gn:admin1_code":"28.0",
    "gn:admin2_code":"21.0",
    "gn:asciiname":"San Jose del Paraiso",
    "gn:country_code":"MX",
    "gn:dem":85,
    "gn:feature_class":"P",
    "gn:feature_code":"PPL",
    "gn:name":"San Jos\u00e9 del Para\u00edso",
    "gn:population":0,
    "gn:timezone":"America/Monterrey",
    "iso:country":"MX",
    "name:spa_x_preferred":[
        "San Jos\u00e9 del Para\u00edso"
    ],
    "wof:name":"San Jose del Paraiso",
    "wof:placetype":"locality"
},
  "geometry": {"coordinates":[-98.93416999999999,22.63639],"type":"Point"}
}