{
  "type": "Feature",
  "properties": {
    "gn:admin1_code":"10",
    "gn:admin2_code":"18.0",
    "gn:asciiname":"San Jose de Ramos",
    "gn:country_code":"MX",
    "gn:dem":1537,
    "gn:feature_class":"P",
    "gn:feature_code":"PPL",
    "gn:name":"San Jos\u00e9 de Ramos",
    "gn:population":0,
    "gn:timezone":"America/Monterrey",
    "iso:country":"MX",
    "name:spa_x_preferred":[
        "San Jos\u00e9 de Ramos"
    ],
    "wof:name":"San Jose de Ramos",
    "wof:placetype":"locality"
},
  "geometry": {"coordinates":[-105.17458000000001,25.48343],"type":"Point"}
}