{
  "type": "Feature",
  "properties": {
    "gn:admin1_code":"20.0",
    "gn:admin2_code":"525.0",
    "gn:asciiname":"El Morro",
    "gn:country_code":"MX",
    "gn:dem":342,
    "gn:feature_class":"P",
    "gn:feature_code":"PPL",
    "gn:name":"El Morro",
    "gn:population":0,
    "gn:timezone":"America/Mexico_City",
    "iso:country":"MX",
    "name:spa_x_preferred":[
        "El Morro"
    ],
    "wof:name":"El Morro",
    "wof:placetype":"locality"
},
  "geometry": {"coordinates":[-94.32174999999999,16.59169],"type":"Point"}
}