{
  "type": "Feature",
  "properties": {
    "gn:admin1_code":"10.0",
    "gn:admin2_code":"14.0",
    "gn:asciiname":"Candelaria del Alto",
    "gn:country_code":"MX",
    "gn:dem":1944,
    "gn:feature_class":"P",
    "gn:feature_code":"PPL",
    "gn:name":"Candelaria del Alto",
    "gn:population":284,
    "gn:timezone":"America/Monterrey",
    "iso:country":"MX",
    "name:spa_x_preferred":[
        "Candelaria del Alto"
    ],
    "name:und_x_variant":[
        "Candlelaria",
        "La Candelaria"
    ],
    "wof:name":"Candelaria del Alto",
    "wof:placetype":"locality",
    "wof:population":284
},
  "geometry": {"coordinates":[-104.54564000000001,23.07927],"type":"Point"}
}