{
  "type": "Feature",
  "properties": {
    "gn:admin1_code":"4",
    "gn:admin2_code":"10.0",
    "gn:asciiname":"El Hormiguero",
    "gn:country_code":"MX",
    "gn:dem":265,
    "gn:feature_class":"P",
    "gn:feature_code":"PPL",
    "gn:name":"El Hormiguero",
    "gn:population":0,
    "gn:timezone":"America/Cancun",
    "iso:country":"MX",
    "name:ara_x_preferred":[
        "\u0625\u0644 \u0647\u0648\u0631\u0645\u064a\u062c\u0648\u064a\u0631\u0648"
    ],
    "name:cat_x_preferred":[
        "El Hormiguero"
    ],
    "name:deu_x_preferred":[
        "El Hormiguero"
    ],
    "name:fra_x_preferred":[
        "El Hormiguero"
    ],
    "name:glg_x_preferred":[
        "El Hormiguero"
    ],
    "name:ita_x_preferred":[
        "El Hormiguero"
    ],
    "name:por_x_preferred":[
        "El Hormiguero"
    ],
    "name:spa_x_preferred":[
        "El Hormiguero"
    ],
    "name:spa_x_variant":[
        "El hormiguero"
    ],
    "name:swe_x_preferred":[
        "El Hormiguero"
    ],
    "name:ukr_x_preferred":[
        "El Hormiguero"
    ],
    "wof:name":"El Hormiguero",
    "wof:placetype":"locality"
},
  "geometry": {"coordinates":[-89.41967,18.81349],"type":"Point"}
}