{
  "type": "Feature",
  "properties": {
    "gn:admin1_code":"4",
    "gn:admin2_code":"10.0",
    "gn:asciiname":"El Hormiguero",
    "gn:country_code":"MX",
    "gn:dem":265,
    "gn:feature_class":"P",
    "gn:feature_code":"PPL",
    "gn:name":"El Hormiguero",
    "gn:population":0,
    "gn:timezone":"America/Cancun",
    "iso:country":"MX",
    "name:spa_x_preferred":[
        "El Hormiguero"
    ],
    "wof:name":"El Hormiguero",
    "wof:placetype":"locality"
},
  "geometry": {"coordinates":[-89.41967,18.81349],"type":"Point"}
}