{
  "type": "Feature",
  "properties": {
    "gn:admin1_code":"4.0",
    "gn:admin2_code":"11.0",
    "gn:asciiname":"San Antonio California II",
    "gn:country_code":"MX",
    "gn:dem":44,
    "gn:feature_class":"P",
    "gn:feature_code":"PPL",
    "gn:name":"San Antonio California II",
    "gn:population":0,
    "gn:timezone":"America/Merida",
    "iso:country":"MX",
    "name:spa_x_preferred":[
        "San Antonio California Dos"
    ],
    "name:spa_x_variant":[
        "San Antonio California II"
    ],
    "wof:name":"San Antonio California II",
    "wof:placetype":"locality"
},
  "geometry": {"coordinates":[-90.92394,17.89611],"type":"Point"}
}