{
  "type": "Feature",
  "properties": {
    "gn:admin1_code":"12.0",
    "gn:admin2_code":"54.0",
    "gn:asciiname":"Petlacala",
    "gn:country_code":"MX",
    "gn:dem":2039,
    "gn:feature_class":"P",
    "gn:feature_code":"PPL",
    "gn:name":"Petlacala",
    "gn:population":0,
    "gn:timezone":"America/Mexico_City",
    "iso:country":"MX",
    "name:spa_x_preferred":[
        "Petlacala"
    ],
    "wof:name":"Petlacala",
    "wof:placetype":"locality"
},
  "geometry": {"coordinates":[-100.28583999999999,17.75956],"type":"Point"}
}