{
  "type": "Feature",
  "properties": {
    "gn:admin1_code":"12",
    "gn:admin2_code":"16.0",
    "gn:asciiname":"Tuberia (La Tuberia)",
    "gn:country_code":"MX",
    "gn:dem":792,
    "gn:feature_class":"P",
    "gn:feature_code":"PPL",
    "gn:name":"Tuber\u00eda (La Tuber\u00eda)",
    "gn:population":44,
    "gn:timezone":"America/Mexico_City",
    "iso:country":"MX",
    "wof:name":"Tuberia (La Tuberia)",
    "wof:placetype":"locality",
    "wof:population":44
},
  "geometry": {"coordinates":[-101.39646999999999,18.03823],"type":"Point"}
}