{
  "type": "Feature",
  "properties": {
    "gn:admin1_code":"6",
    "gn:admin2_code":"8.0",
    "gn:asciiname":"Rancheria La Cana",
    "gn:country_code":"MX",
    "gn:dem":761,
    "gn:feature_class":"P",
    "gn:feature_code":"PPL",
    "gn:name":"Rancher\u00eda La Ca\u00f1a",
    "gn:population":0,
    "gn:timezone":"America/Chihuahua",
    "iso:country":"MX",
    "name:spa_x_preferred":[
        "Rancher\u00eda La Ca\u00f1a"
    ],
    "name:und_x_variant":[
        "La Ca\u00f1a"
    ],
    "wof:name":"Rancheria La Cana",
    "wof:placetype":"locality"
},
  "geometry": {"coordinates":[-107.8075,26.73767],"type":"Point"}
}