{
  "type": "Feature",
  "properties": {
    "gn:admin1_code":"6",
    "gn:admin2_code":"20.0",
    "gn:asciiname":"La Encantada",
    "gn:country_code":"MX",
    "gn:dem":499,
    "gn:feature_class":"P",
    "gn:feature_code":"PPL",
    "gn:name":"La Encantada",
    "gn:population":0,
    "gn:timezone":"America/Chihuahua",
    "iso:country":"MX",
    "name:ceb_x_preferred":[
        "La Encantada"
    ],
    "name:spa_x_preferred":[
        "La Encantada"
    ],
    "name:swe_x_preferred":[
        "La Encantada"
    ],
    "wof:name":"La Encantada",
    "wof:placetype":"locality"
},
  "geometry": {"coordinates":[-108.48206999999999,27.22328],"type":"Point"}
}