{
  "type": "Feature",
  "properties": {
    "gn:admin1_code":"25",
    "gn:admin2_code":"17",
    "gn:asciiname":"El Recodo",
    "gn:country_code":"MX",
    "gn:dem":206,
    "gn:feature_class":"P",
    "gn:feature_code":"PPL",
    "gn:name":"El Recodo",
    "gn:population":26,
    "gn:timezone":"America/Mazatlan",
    "iso:country":"MX",
    "wof:name":"El Recodo",
    "wof:placetype":"locality",
    "wof:population":26
},
  "geometry": {"coordinates":[-108.14901,26.0509],"type":"Point"}
}