{
  "type": "Feature",
  "properties": {
    "gn:admin1_code":"26",
    "gn:admin2_code":"6.0",
    "gn:asciiname":"El Rebaje",
    "gn:country_code":"MX",
    "gn:dem":755,
    "gn:feature_class":"P",
    "gn:feature_code":"PPL",
    "gn:name":"El Rebaje",
    "gn:population":0,
    "gn:timezone":"America/Hermosillo",
    "iso:country":"MX",
    "name:spa_x_preferred":[
        "El Rebaje"
    ],
    "wof:name":"El Rebaje",
    "wof:placetype":"locality"
},
  "geometry": {"coordinates":[-110.23469,30.22967],"type":"Point"}
}