{
  "type": "Feature",
  "properties": {
    "gn:admin1_code":"10",
    "gn:admin2_code":"5.0",
    "gn:asciiname":"Colonia las Palmas",
    "gn:country_code":"MX",
    "gn:dem":1931,
    "gn:feature_class":"P",
    "gn:feature_code":"PPL",
    "gn:name":"Colonia las Palmas",
    "gn:population":4,
    "gn:timezone":"America/Monterrey",
    "iso:country":"MX",
    "wof:name":"Colonia las Palmas",
    "wof:placetype":"locality",
    "wof:population":4
},
  "geometry": {"coordinates":[-104.45111,23.82696],"type":"Point"}
}