{
  "type": "Feature",
  "properties": {
    "gn:admin1_code":"4",
    "gn:admin2_code":"3.0",
    "gn:asciiname":"San Sebastian",
    "gn:country_code":"MX",
    "gn:dem":-3,
    "gn:feature_class":"P",
    "gn:feature_code":"PPL",
    "gn:name":"San Sebasti\u00e1n",
    "gn:population":6,
    "gn:timezone":"America/Merida",
    "iso:country":"MX",
    "name:und_x_variant":[
        "San Sebasti\u00e1n"
    ],
    "wof:name":"San Sebastian",
    "wof:placetype":"locality",
    "wof:population":6
},
  "geometry": {"coordinates":[-91.27528,18.85917],"type":"Point"}
}