{
  "type": "Feature",
  "properties": {
    "gn:admin1_code":"6",
    "gn:admin2_code":"27",
    "gn:asciiname":"Cutemachi",
    "gn:country_code":"MX",
    "gn:dem":1980,
    "gn:feature_class":"P",
    "gn:feature_code":"PPL",
    "gn:name":"Cutemachi",
    "gn:population":24,
    "gn:timezone":"America/Chihuahua",
    "iso:country":"MX",
    "wof:name":"Cutemachi",
    "wof:placetype":"locality",
    "wof:population":24
},
  "geometry": {"coordinates":[-107.49908000000001,27.4627],"type":"Point"}
}