{
  "type": "Feature",
  "properties": {
    "gn:admin1_code":"30",
    "gn:admin2_code":"178",
    "gn:asciiname":"Ejido el Saladito",
    "gn:country_code":"MX",
    "gn:dem":5,
    "gn:feature_class":"P",
    "gn:feature_code":"PPL",
    "gn:name":"Ejido el Saladito",
    "gn:population":11,
    "gn:timezone":"America/Mexico_City",
    "iso:country":"MX",
    "wof:name":"Ejido el Saladito",
    "wof:placetype":"locality",
    "wof:population":11
},
  "geometry": {"coordinates":[-95.68083,18.62194],"type":"Point"}
}