{
  "type": "Feature",
  "properties": {
    "gn:admin1_code":"13",
    "gn:admin2_code":"81",
    "gn:asciiname":"La Cumbre de Tlahuelompa",
    "gn:country_code":"MX",
    "gn:dem":1847,
    "gn:feature_class":"P",
    "gn:feature_code":"PPL",
    "gn:name":"La Cumbre de Tlahuelompa",
    "gn:population":43,
    "gn:timezone":"America/Mexico_City",
    "iso:country":"MX",
    "wof:name":"La Cumbre de Tlahuelompa",
    "wof:placetype":"locality",
    "wof:population":43
},
  "geometry": {"coordinates":[-98.57825,20.63743],"type":"Point"}
}