{
  "type": "Feature",
  "properties": {
    "gn:admin1_code":"12.0",
    "gn:admin2_code":"47.0",
    "gn:asciiname":"Molonial",
    "gn:country_code":"MX",
    "gn:dem":1639,
    "gn:feature_class":"P",
    "gn:feature_code":"PPL",
    "gn:name":"Molonial",
    "gn:population":0,
    "gn:timezone":"America/Mexico_City",
    "iso:country":"MX",
    "name:spa_x_preferred":[
        "Molonial"
    ],
    "wof:name":"Molonial",
    "wof:placetype":"locality"
},
  "geometry": {"coordinates":[-99.93517,18.46564],"type":"Point"}
}