{
  "type": "Feature",
  "properties": {
    "gn:admin1_code":"5",
    "gn:admin2_code":"77.0",
    "gn:asciiname":"Generacion Noventa y Cinco",
    "gn:country_code":"MX",
    "gn:dem":78,
    "gn:feature_class":"P",
    "gn:feature_code":"PPL",
    "gn:name":"Generaci\u00f3n Noventa y Cinco",
    "gn:population":208,
    "gn:timezone":"America/Mexico_City",
    "iso:country":"MX",
    "name:und_x_variant":[
        "Generaci\u00f3n Noventa y Cinco"
    ],
    "wof:name":"Generacion Noventa y Cinco",
    "wof:placetype":"locality",
    "wof:population":208
},
  "geometry": {"coordinates":[-92.03278,17.27917],"type":"Point"}
}