{
  "type": "Feature",
  "properties": {
    "gn:admin1_code":"14",
    "gn:admin2_code":"85.0",
    "gn:asciiname":"Morelos (Santa Rosa)",
    "gn:country_code":"MX",
    "gn:dem":1196,
    "gn:feature_class":"P",
    "gn:feature_code":"PPL",
    "gn:name":"Morelos (Santa Rosa)",
    "gn:population":281,
    "gn:timezone":"America/Mexico_City",
    "iso:country":"MX",
    "wof:name":"Morelos (Santa Rosa)",
    "wof:placetype":"locality",
    "wof:population":281
},
  "geometry": {"coordinates":[-103.20389,19.5925],"type":"Point"}
}