{
  "type": "Feature",
  "properties": {
    "gn:admin1_code":"15.0",
    "gn:asciiname":"El Higo",
    "gn:country_code":"MX",
    "gn:dem":806,
    "gn:feature_class":"P",
    "gn:feature_code":"PPL",
    "gn:name":"El Higo",
    "gn:population":0,
    "gn:timezone":"America/Mexico_City",
    "iso:country":"MX",
    "name:ceb_x_preferred":[
        "El Higo"
    ],
    "name:spa_x_preferred":[
        "El Higo"
    ],
    "name:swe_x_preferred":[
        "El Higo"
    ],
    "wof:name":"El Higo",
    "wof:placetype":"locality"
},
  "geometry": {"coordinates":[-100.43635,18.60867],"type":"Point"}
}