{
  "type": "Feature",
  "properties": {
    "gn:admin1_code":"30",
    "gn:admin2_code":"31.0",
    "gn:asciiname":"La Cruceta",
    "gn:country_code":"MX",
    "gn:dem":163,
    "gn:feature_class":"P",
    "gn:feature_code":"PPL",
    "gn:name":"La Cruceta",
    "gn:population":105,
    "gn:timezone":"America/Mexico_City",
    "iso:country":"MX",
    "wof:name":"La Cruceta",
    "wof:placetype":"locality",
    "wof:population":105
},
  "geometry": {"coordinates":[-96.53833,18.77472],"type":"Point"}
}