{
  "type": "Feature",
  "properties": {
    "gn:admin1_code":"5",
    "gn:admin2_code":"99",
    "gn:asciiname":"Los Arbolitos",
    "gn:country_code":"MX",
    "gn:dem":1554,
    "gn:feature_class":"P",
    "gn:feature_code":"PPL",
    "gn:name":"Los Arbolitos",
    "gn:population":9,
    "gn:timezone":"America/Mexico_City",
    "iso:country":"MX",
    "wof:name":"Los Arbolitos",
    "wof:placetype":"locality",
    "wof:population":9
},
  "geometry": {"coordinates":[-92.06666,16.13556],"type":"Point"}
}