{
  "type": "Feature",
  "properties": {
    "gn:admin1_code":"26.0",
    "gn:admin2_code":"35.0",
    "gn:asciiname":"Cumeral Viejo",
    "gn:country_code":"MX",
    "gn:dem":888,
    "gn:feature_class":"P",
    "gn:feature_code":"PPL",
    "gn:name":"Cumeral Viejo",
    "gn:population":0,
    "gn:timezone":"America/Hermosillo",
    "iso:country":"MX",
    "name:spa_x_preferred":[
        "Cumeral Viejo"
    ],
    "wof:name":"Cumeral Viejo",
    "wof:placetype":"locality"
},
  "geometry": {"coordinates":[-110.85120000000001,30.85547],"type":"Point"}
}