{
  "type": "Feature",
  "properties": {
    "gn:admin1_code":"24",
    "gn:admin2_code":"7.0",
    "gn:asciiname":"El Barrio",
    "gn:country_code":"MX",
    "gn:dem":1753,
    "gn:feature_class":"P",
    "gn:feature_code":"PPL",
    "gn:name":"El Barrio",
    "gn:population":0,
    "gn:timezone":"America/Mexico_City",
    "iso:country":"MX",
    "name:spa_x_preferred":[
        "El Barrio"
    ],
    "wof:name":"El Barrio",
    "wof:placetype":"locality"
},
  "geometry": {"coordinates":[-100.62353,23.9032],"type":"Point"}
}