{
  "type": "Feature",
  "properties": {
    "gn:admin1_code":"10",
    "gn:admin2_code":"14.0",
    "gn:asciiname":"El Penasco (Relices)",
    "gn:country_code":"MX",
    "gn:dem":1691,
    "gn:feature_class":"P",
    "gn:feature_code":"PPL",
    "gn:name":"El Pe\u00f1asco (Relices)",
    "gn:population":6,
    "gn:timezone":"America/Monterrey",
    "iso:country":"MX",
    "name:und_x_variant":[
        "El Pe\u00f1asco (Relices)"
    ],
    "wof:name":"El Penasco (Relices)",
    "wof:placetype":"locality",
    "wof:population":6
},
  "geometry": {"coordinates":[-104.82942,22.85371],"type":"Point"}
}