{
  "type": "Feature",
  "properties": {
    "gn:admin1_code":"26",
    "gn:admin2_code":"29.0",
    "gn:asciiname":"El Llano",
    "gn:country_code":"MX",
    "gn:dem":138,
    "gn:feature_class":"P",
    "gn:feature_code":"PPL",
    "gn:name":"El Llano",
    "gn:population":6,
    "gn:timezone":"America/Hermosillo",
    "iso:country":"MX",
    "wof:name":"El Llano",
    "wof:placetype":"locality",
    "wof:population":6
},
  "geometry": {"coordinates":[-110.62166999999999,28.34889],"type":"Point"}
}