{
  "type": "Feature",
  "properties": {
    "gn:admin1_code":"5",
    "gn:admin2_code":"92.0",
    "gn:asciiname":"El Carmen",
    "gn:country_code":"MX",
    "gn:dem":297,
    "gn:feature_class":"P",
    "gn:feature_code":"PPL",
    "gn:name":"El Carmen",
    "gn:population":7,
    "gn:timezone":"America/Mexico_City",
    "iso:country":"MX",
    "wof:name":"El Carmen",
    "wof:placetype":"locality",
    "wof:population":7
},
  "geometry": {"coordinates":[-93.55,17.18833],"type":"Point"}
}