{
  "type": "Feature",
  "properties": {
    "gn:admin1_code":"28.0",
    "gn:admin2_code":"21.0",
    "gn:asciiname":"Magdaleno Aguilar Castillo",
    "gn:country_code":"MX",
    "gn:dem":165,
    "gn:feature_class":"P",
    "gn:feature_code":"PPL",
    "gn:name":"Magdaleno Aguilar Castillo",
    "gn:population":0,
    "gn:timezone":"America/Monterrey",
    "iso:country":"MX",
    "name:spa_x_preferred":[
        "Magdaleno Aguilar Castillo"
    ],
    "wof:name":"Magdaleno Aguilar Castillo",
    "wof:placetype":"locality"
},
  "geometry": {"coordinates":[-99.11706,22.75742],"type":"Point"}
}