{
  "type": "Feature",
  "properties": {
    "gn:admin1_code":"6",
    "gn:admin2_code":"66.0",
    "gn:asciiname":"El Rebajito",
    "gn:country_code":"MX",
    "gn:dem":2262,
    "gn:feature_class":"P",
    "gn:feature_code":"PPL",
    "gn:name":"El Rebajito",
    "gn:population":5,
    "gn:timezone":"America/Chihuahua",
    "iso:country":"MX",
    "wof:name":"El Rebajito",
    "wof:placetype":"locality",
    "wof:population":5
},
  "geometry": {"coordinates":[-108.21944000000001,27.935],"type":"Point"}
}