{
  "type": "Feature",
  "properties": {
    "gn:admin1_code":"5.0",
    "gn:admin2_code":"107.0",
    "gn:asciiname":"El Vado del Higo",
    "gn:country_code":"MX",
    "gn:dem":618,
    "gn:feature_class":"P",
    "gn:feature_code":"PPL",
    "gn:name":"El Vado del Higo",
    "gn:population":0,
    "gn:timezone":"America/Mexico_City",
    "iso:country":"MX",
    "name:spa_x_preferred":[
        "El Vado del Higo"
    ],
    "wof:name":"El Vado del Higo",
    "wof:placetype":"locality"
},
  "geometry": {"coordinates":[-93.20027,16.08877],"type":"Point"}
}