{
  "type": "Feature",
  "properties": {
    "gn:admin1_code":"7",
    "gn:admin2_code":"17.0",
    "gn:asciiname":"Vizcaya",
    "gn:country_code":"MX",
    "gn:dem":1112,
    "gn:feature_class":"P",
    "gn:feature_code":"PPL",
    "gn:name":"Vizcaya",
    "gn:population":0,
    "gn:timezone":"America/Monterrey",
    "iso:country":"MX",
    "name:ceb_x_preferred":[
        "Vizcaya"
    ],
    "name:deu_x_preferred":[
        "Vizcaya"
    ],
    "name:nld_x_preferred":[
        "Vizcaya"
    ],
    "name:por_x_preferred":[
        "Vizcaya"
    ],
    "name:spa_x_preferred":[
        "Vizcaya"
    ],
    "name:swe_x_preferred":[
        "Vizcaya"
    ],
    "wof:name":"Vizcaya",
    "wof:placetype":"locality"
},
  "geometry": {"coordinates":[-103.2144,25.57952],"type":"Point"}
}