{
  "type": "Feature",
  "properties": {
    "gn:admin1_code":"20",
    "gn:admin2_code":"406.0",
    "gn:asciiname":"Llano de Insurgentes",
    "gn:country_code":"MX",
    "gn:dem":1076,
    "gn:feature_class":"P",
    "gn:feature_code":"PPL",
    "gn:name":"Llano de Insurgentes",
    "gn:population":60,
    "gn:timezone":"America/Mexico_City",
    "iso:country":"MX",
    "wof:name":"Llano de Insurgentes",
    "wof:placetype":"locality",
    "wof:population":60
},
  "geometry": {"coordinates":[-96.79222,18.31583],"type":"Point"}
}