{
  "type": "Feature",
  "properties": {
    "gn:admin1_code":"5",
    "gn:admin2_code":"20.0",
    "gn:asciiname":"La Escondida",
    "gn:country_code":"MX",
    "gn:dem":586,
    "gn:feature_class":"P",
    "gn:feature_code":"PPL",
    "gn:name":"La Escondida",
    "gn:population":6,
    "gn:timezone":"America/Mexico_City",
    "iso:country":"MX",
    "wof:name":"La Escondida",
    "wof:placetype":"locality",
    "wof:population":6
},
  "geometry": {"coordinates":[-92.84583000000001,16.02028],"type":"Point"}
}