{
  "type": "Feature",
  "properties": {
    "gn:admin1_code":"5",
    "gn:admin2_code":"65.0",
    "gn:asciiname":"Nueva Central",
    "gn:country_code":"MX",
    "gn:dem":148,
    "gn:feature_class":"P",
    "gn:feature_code":"PPL",
    "gn:name":"Nueva Central",
    "gn:population":130,
    "gn:timezone":"America/Mexico_City",
    "iso:country":"MX",
    "wof:name":"Nueva Central",
    "wof:placetype":"locality",
    "wof:population":130
},
  "geometry": {"coordinates":[-91.5675,17.34472],"type":"Point"}
}