{
  "type": "Feature",
  "properties": {
    "gn:admin1_code":"19",
    "gn:admin2_code":"7",
    "gn:asciiname":"El Nogalar (La Pita)",
    "gn:country_code":"MX",
    "gn:dem":800,
    "gn:feature_class":"P",
    "gn:feature_code":"PPL",
    "gn:name":"El Nogalar (La Pita)",
    "gn:population":19,
    "gn:timezone":"America/Monterrey",
    "iso:country":"MX",
    "wof:name":"El Nogalar (La Pita)",
    "wof:placetype":"locality",
    "wof:population":19
},
  "geometry": {"coordinates":[-99.68885,24.14425],"type":"Point"}
}