{
  "type": "Feature",
  "properties": {
    "gn:admin1_code":"22",
    "gn:admin2_code":"13.0",
    "gn:asciiname":"Milpillas",
    "gn:cc2":"MX",
    "gn:country_code":"MX",
    "gn:dem":1550,
    "gn:feature_class":"P",
    "gn:feature_code":"PPL",
    "gn:name":"Milpillas",
    "gn:population":110,
    "gn:timezone":"America/Mexico_City",
    "iso:country":"MX",
    "name:und_x_variant":[
        "Milpilla"
    ],
    "wof:name":"Milpillas",
    "wof:placetype":"locality",
    "wof:population":110
},
  "geometry": {"coordinates":[-99.76639,21.11167],"type":"Point"}
}