{
  "type": "Feature",
  "properties": {
    "gn:admin1_code":"5",
    "gn:admin2_code":"46.0",
    "gn:asciiname":"El Bosque",
    "gn:country_code":"MX",
    "gn:dem":640,
    "gn:feature_class":"P",
    "gn:feature_code":"PPL",
    "gn:name":"El Bosque",
    "gn:population":7,
    "gn:timezone":"America/Mexico_City",
    "iso:country":"MX",
    "wof:name":"El Bosque",
    "wof:placetype":"locality",
    "wof:population":7
},
  "geometry": {"coordinates":[-93.51000000000001,16.5425],"type":"Point"}
}