{
  "type": "Feature",
  "properties": {
    "gn:admin1_code":"23",
    "gn:admin2_code":"4.0",
    "gn:asciiname":"Xahuachol",
    "gn:country_code":"MX",
    "gn:dem":8,
    "gn:feature_class":"P",
    "gn:feature_code":"PPL",
    "gn:name":"Xahuachol",
    "gn:population":0,
    "gn:timezone":"America/Cancun",
    "iso:country":"MX",
    "name:spa_x_preferred":[
        "Xahuachol"
    ],
    "wof:name":"Xahuachol",
    "wof:placetype":"locality"
},
  "geometry": {"coordinates":[-87.75887,18.5111],"type":"Point"}
}