{
  "type": "Feature",
  "properties": {
    "gn:admin1_code":"5",
    "gn:admin2_code":"60.0",
    "gn:asciiname":"San Miguel de Allende",
    "gn:country_code":"MX",
    "gn:dem":1345,
    "gn:feature_class":"P",
    "gn:feature_code":"PPL",
    "gn:name":"San Miguel de Allende",
    "gn:population":106,
    "gn:timezone":"America/Mexico_City",
    "iso:country":"MX",
    "name:fas_x_preferred":[
        "\u0633\u0627\u0646 \u0645\u06cc\u06af\u0644 \u062f \u0622\u0644\u0646\u062f\u0647"
    ],
    "name:heb_x_preferred":[
        "\u05e1\u05df \u05de\u05d9\u05d2\u05dc \u05d3\u05d4 \u05d0\u05d9\u05d9\u05e0\u05d3\u05d4"
    ],
    "name:srp_x_preferred":[
        "\u0421\u0430\u043d \u041c\u0438\u0433\u0435\u043b \u0434\u0435 \u0410\u0459\u0435\u043d\u0434\u0435"
    ],
    "wof:name":"San Miguel de Allende",
    "wof:placetype":"locality",
    "wof:population":106
},
  "geometry": {"coordinates":[-93.18083,17.21056],"type":"Point"}
}