{
  "type": "Feature",
  "properties": {
    "gn:admin1_code":"5",
    "gn:admin2_code":"21.0",
    "gn:asciiname":"Monte Eliseo",
    "gn:country_code":"MX",
    "gn:dem":682,
    "gn:feature_class":"P",
    "gn:feature_code":"PPL",
    "gn:name":"Monte Eliseo",
    "gn:population":6,
    "gn:timezone":"America/Mexico_City",
    "iso:country":"MX",
    "wof:name":"Monte Eliseo",
    "wof:placetype":"locality",
    "wof:population":6
},
  "geometry": {"coordinates":[-93.24417,17.09778],"type":"Point"}
}