{
  "type": "Feature",
  "properties": {
    "gn:admin1_code":"14.0",
    "gn:admin2_code":"9.0",
    "gn:asciiname":"Polvorines",
    "gn:country_code":"MX",
    "gn:dem":1407,
    "gn:feature_class":"P",
    "gn:feature_code":"PPL",
    "gn:name":"Polvorines",
    "gn:population":0,
    "gn:timezone":"America/Mexico_City",
    "iso:country":"MX",
    "name:spa_x_preferred":[
        "Polvorines"
    ],
    "wof:name":"Polvorines",
    "wof:placetype":"locality"
},
  "geometry": {"coordinates":[-103.68755,20.79017],"type":"Point"}
}