{
  "type": "Feature",
  "properties": {
    "gn:admin1_code":"6",
    "gn:admin2_code":"65.0",
    "gn:asciiname":"Corral",
    "gn:country_code":"MX",
    "gn:dem":2324,
    "gn:feature_class":"P",
    "gn:feature_code":"PPL",
    "gn:name":"Corral",
    "gn:population":4,
    "gn:timezone":"America/Chihuahua",
    "iso:country":"MX",
    "wof:name":"Corral",
    "wof:placetype":"locality",
    "wof:population":4
},
  "geometry": {"coordinates":[-107.89964999999999,27.51964000000001],"type":"Point"}
}