{
  "type": "Feature",
  "properties": {
    "gn:admin1_code":"22",
    "gn:admin2_code":"2.0",
    "gn:asciiname":"Magueycitos",
    "gn:country_code":"MX",
    "gn:dem":2314,
    "gn:feature_class":"P",
    "gn:feature_code":"PPL",
    "gn:name":"Magueycitos",
    "gn:population":168,
    "gn:timezone":"America/Mexico_City",
    "iso:country":"MX",
    "wof:name":"Magueycitos",
    "wof:placetype":"locality",
    "wof:population":168
},
  "geometry": {"coordinates":[-99.61333,21.12278],"type":"Point"}
}