{
  "type": "Feature",
  "properties": {
    "gn:admin1_code":"5",
    "gn:admin2_code":"43.0",
    "gn:asciiname":"Lindavista",
    "gn:country_code":"MX",
    "gn:dem":671,
    "gn:feature_class":"P",
    "gn:feature_code":"PPL",
    "gn:name":"Lindavista",
    "gn:population":0,
    "gn:timezone":"America/Mexico_City",
    "iso:country":"MX",
    "name:fra_x_preferred":[
        "Lindavista"
    ],
    "name:nor_x_preferred":[
        "Lindavista"
    ],
    "name:spa_x_preferred":[
        "Lindavista"
    ],
    "name:und_x_variant":[
        "Viejo Lindavista"
    ],
    "wof:name":"Lindavista",
    "wof:placetype":"locality"
},
  "geometry": {"coordinates":[-93.15043,17.39965],"type":"Point"}
}