{
  "type": "Feature",
  "properties": {
    "gn:admin1_code":"32",
    "gn:admin2_code":"13.0",
    "gn:asciiname":"Felix U. Gomez",
    "gn:country_code":"MX",
    "gn:dem":2153,
    "gn:feature_class":"P",
    "gn:feature_code":"PPL",
    "gn:name":"F\u00e9lix U. G\u00f3mez",
    "gn:population":0,
    "gn:timezone":"America/Mexico_City",
    "iso:country":"MX",
    "name:spa_x_preferred":[
        "F\u00e9lix U. G\u00f3mez"
    ],
    "wof:name":"Felix U. Gomez",
    "wof:placetype":"locality"
},
  "geometry": {"coordinates":[-102.77238,23.04579],"type":"Point"}
}