{
  "type": "Feature",
  "properties": {
    "gn:admin1_code":"32",
    "gn:admin2_code":"38",
    "gn:asciiname":"Laguna del Duraznillo",
    "gn:country_code":"MX",
    "gn:dem":2110,
    "gn:feature_class":"P",
    "gn:feature_code":"PPL",
    "gn:name":"Laguna del Duraznillo",
    "gn:population":20,
    "gn:timezone":"America/Mexico_City",
    "iso:country":"MX",
    "wof:name":"Laguna del Duraznillo",
    "wof:placetype":"locality",
    "wof:population":20
},
  "geometry": {"coordinates":[-101.39028,22.09],"type":"Point"}
}