{
  "type": "Feature",
  "properties": {
    "gn:admin1_code":"30",
    "gn:admin2_code":"207",
    "gn:asciiname":"Rancho Chelesque",
    "gn:country_code":"MX",
    "gn:dem":47,
    "gn:feature_class":"P",
    "gn:feature_code":"PPL",
    "gn:name":"Rancho Chelesque",
    "gn:population":16,
    "gn:timezone":"America/Mexico_City",
    "iso:country":"MX",
    "wof:name":"Rancho Chelesque",
    "wof:placetype":"locality",
    "wof:population":16
},
  "geometry": {"coordinates":[-96.20083,18.29306],"type":"Point"}
}