{
  "type": "Feature",
  "properties": {
    "gn:admin1_code":"7.0",
    "gn:admin2_code":"38.0",
    "gn:asciiname":"Dixie",
    "gn:country_code":"MX",
    "gn:dem":371,
    "gn:feature_class":"P",
    "gn:feature_code":"PPL",
    "gn:name":"Dixie",
    "gn:population":0,
    "gn:timezone":"America/Monterrey",
    "iso:country":"MX",
    "name:spa_x_preferred":[
        "Dixie"
    ],
    "wof:name":"Dixie",
    "wof:placetype":"locality"
},
  "geometry": {"coordinates":[-101.08126,28.76241],"type":"Point"}
}