{
  "type": "Feature",
  "properties": {
    "gn:admin1_code":"30",
    "gn:admin2_code":"160.0",
    "gn:asciiname":"Articulo Veintisiete Constitucional",
    "gn:country_code":"MX",
    "gn:dem":116,
    "gn:feature_class":"P",
    "gn:feature_code":"PPL",
    "gn:name":"Art\u00edculo Veintisiete Constitucional",
    "gn:population":177,
    "gn:timezone":"America/Mexico_City",
    "iso:country":"MX",
    "name:und_x_variant":[
        "Art\u00edculo Veintisiete Constitucional"
    ],
    "wof:name":"Articulo Veintisiete Constitucional",
    "wof:placetype":"locality",
    "wof:population":177
},
  "geometry": {"coordinates":[-97.78972,21.01361],"type":"Point"}
}