{
  "type": "Feature",
  "properties": {
    "gn:admin1_code":"32",
    "gn:admin2_code":"55.0",
    "gn:asciiname":"San Alejo",
    "gn:country_code":"MX",
    "gn:dem":2170,
    "gn:feature_class":"P",
    "gn:feature_code":"PPL",
    "gn:name":"San Alejo",
    "gn:population":5,
    "gn:timezone":"America/Mexico_City",
    "iso:country":"MX",
    "wof:name":"San Alejo",
    "wof:placetype":"locality",
    "wof:population":5
},
  "geometry": {"coordinates":[-103.09389,22.065],"type":"Point"}
}