{
  "type": "Feature",
  "properties": {
    "gn:admin1_code":"11.0",
    "gn:admin2_code":"30.0",
    "gn:asciiname":"El Blanquillo",
    "gn:country_code":"MX",
    "gn:dem":2254,
    "gn:feature_class":"P",
    "gn:feature_code":"PPL",
    "gn:name":"El Blanquillo",
    "gn:population":0,
    "gn:timezone":"America/Mexico_City",
    "iso:country":"MX",
    "name:spa_x_preferred":[
        "El Blanquillo"
    ],
    "wof:name":"El Blanquillo",
    "wof:placetype":"locality"
},
  "geometry": {"coordinates":[-101.32644999999999,21.78268],"type":"Point"}
}