{
  "type": "Feature",
  "properties": {
    "gn:admin1_code":"30",
    "gn:admin2_code":"174.0",
    "gn:asciiname":"Congregacion Morelos",
    "gn:country_code":"MX",
    "gn:dem":50,
    "gn:feature_class":"P",
    "gn:feature_code":"PPL",
    "gn:name":"Congregaci\u00f3n Morelos",
    "gn:population":0,
    "gn:timezone":"America/Mexico_City",
    "iso:country":"MX",
    "wof:name":"Congregacion Morelos",
    "wof:placetype":"locality"
},
  "geometry": {"coordinates":[-96.25142,18.54431],"type":"Point"}
}