{
  "type": "Feature",
  "properties": {
    "gn:admin1_code":"14",
    "gn:admin2_code":"41",
    "gn:asciiname":"Charcos",
    "gn:country_code":"MX",
    "gn:dem":1855,
    "gn:feature_class":"P",
    "gn:feature_code":"PPL",
    "gn:name":"Charcos",
    "gn:population":14,
    "gn:timezone":"America/Mexico_City",
    "iso:country":"MX",
    "wof:name":"Charcos",
    "wof:placetype":"locality",
    "wof:population":14
},
  "geometry": {"coordinates":[-103.23611,22.34611],"type":"Point"}
}