{
  "type": "Feature",
  "properties": {
    "gn:admin1_code":"22",
    "gn:admin2_code":"7.0",
    "gn:asciiname":"Los Ramirez",
    "gn:country_code":"MX",
    "gn:dem":2179,
    "gn:feature_class":"P",
    "gn:feature_code":"PPL",
    "gn:name":"Los Ram\u00edrez",
    "gn:population":0,
    "gn:timezone":"America/Mexico_City",
    "iso:country":"MX",
    "name:spa_x_preferred":[
        "Los Ram\u00edrez"
    ],
    "wof:name":"Los Ramirez",
    "wof:placetype":"locality"
},
  "geometry": {"coordinates":[-99.81726999999999,20.62983],"type":"Point"}
}