{
  "type": "Feature",
  "properties": {
    "gn:admin1_code":"7",
    "gn:admin2_code":"37.0",
    "gn:asciiname":"Noria",
    "gn:country_code":"MX",
    "gn:dem":529,
    "gn:feature_class":"P",
    "gn:feature_code":"PPL",
    "gn:name":"Noria",
    "gn:population":0,
    "gn:timezone":"America/Monterrey",
    "iso:country":"MX",
    "wof:name":"Noria",
    "wof:placetype":"locality"
},
  "geometry": {"coordinates":[-100.90000000000001,27.95],"type":"Point"}
}