{
  "type": "Feature",
  "properties": {
    "gn:admin1_code":"17",
    "gn:admin2_code":"20",
    "gn:asciiname":"Tepepatlaxco",
    "gn:country_code":"MX",
    "gn:dem":1974,
    "gn:feature_class":"P",
    "gn:feature_code":"PPL",
    "gn:name":"Tepepatlaxco",
    "gn:population":24,
    "gn:timezone":"America/Mexico_City",
    "iso:country":"MX",
    "wof:name":"Tepepatlaxco",
    "wof:placetype":"locality",
    "wof:population":24
},
  "geometry": {"coordinates":[-99.06194000000001,18.9975],"type":"Point"}
}