{
  "type": "Feature",
  "properties": {
    "gn:admin1_code":"30",
    "gn:admin2_code":"4.0",
    "gn:asciiname":"San Jose Pastorias",
    "gn:country_code":"MX",
    "gn:dem":257,
    "gn:feature_class":"P",
    "gn:feature_code":"PPL",
    "gn:name":"San Jos\u00e9 Pastor\u00edas",
    "gn:population":620,
    "gn:timezone":"America/Mexico_City",
    "iso:country":"MX",
    "wof:name":"San Jose Pastorias",
    "wof:placetype":"locality",
    "wof:population":620
},
  "geometry": {"coordinates":[-96.57056,19.56417],"type":"Point"}
}