{
  "type": "Feature",
  "properties": {
    "gn:admin1_code":"10",
    "gn:admin2_code":"13.0",
    "gn:asciiname":"Las Amarillas",
    "gn:country_code":"MX",
    "gn:dem":1347,
    "gn:feature_class":"P",
    "gn:feature_code":"PPL",
    "gn:name":"Las Amarillas",
    "gn:population":0,
    "gn:timezone":"America/Monterrey",
    "iso:country":"MX",
    "name:spa_x_preferred":[
        "Las Amarillas"
    ],
    "name:und_x_variant":[
        "Rancho Las Amarillas"
    ],
    "wof:name":"Las Amarillas",
    "wof:placetype":"locality"
},
  "geometry": {"coordinates":[-103.98180000000001,25.89937],"type":"Point"}
}