{
  "type": "Feature",
  "properties": {
    "gn:admin1_code":"1",
    "gn:admin2_code":"1.0",
    "gn:asciiname":"Che Guevara [Colonia]",
    "gn:country_code":"MX",
    "gn:dem":1981,
    "gn:feature_class":"P",
    "gn:feature_code":"PPL",
    "gn:name":"Che Guevara [Colonia]",
    "gn:population":328,
    "gn:timezone":"America/Mexico_City",
    "iso:country":"MX",
    "wof:name":"Che Guevara [Colonia]",
    "wof:placetype":"locality",
    "wof:population":328
},
  "geometry": {"coordinates":[-102.20722000000001,21.8925],"type":"Point"}
}