{
  "type": "Feature",
  "properties": {
    "gn:admin1_code":"7",
    "gn:admin2_code":"4.0",
    "gn:asciiname":"Povarada el Tepeyac",
    "gn:country_code":"MX",
    "gn:dem":2359,
    "gn:feature_class":"P",
    "gn:feature_code":"PPL",
    "gn:name":"Povarada el Tepeyac",
    "gn:population":0,
    "gn:timezone":"America/Monterrey",
    "iso:country":"MX",
    "name:spa_x_preferred":[
        "Povarada el Tepeyac"
    ],
    "wof:name":"Povarada el Tepeyac",
    "wof:placetype":"locality"
},
  "geometry": {"coordinates":[-100.5916,25.42675],"type":"Point"}
}