{
  "type": "Feature",
  "properties": {
    "gn:admin1_code":"3",
    "gn:admin2_code":"9.0",
    "gn:asciiname":"Lote Cuarenta y Siete",
    "gn:country_code":"MX",
    "gn:dem":47,
    "gn:feature_class":"P",
    "gn:feature_code":"PPL",
    "gn:name":"Lote Cuarenta y Siete",
    "gn:population":0,
    "gn:timezone":"America/Mazatlan",
    "iso:country":"MX",
    "name:spa_x_preferred":[
        "Lote Cuarenta y Siete"
    ],
    "wof:name":"Lote Cuarenta y Siete",
    "wof:placetype":"locality"
},
  "geometry": {"coordinates":[-111.51478,26.25104],"type":"Point"}
}