{
  "type": "Feature",
  "properties": {
    "gn:admin1_code":"18.0",
    "gn:admin2_code":"9.0",
    "gn:asciiname":"Los Picachos",
    "gn:country_code":"MX",
    "gn:dem":597,
    "gn:feature_class":"P",
    "gn:feature_code":"PPL",
    "gn:name":"Los Picachos",
    "gn:population":0,
    "gn:timezone":"America/Mazatlan",
    "iso:country":"MX",
    "name:spa_x_preferred":[
        "Los Picachos"
    ],
    "wof:name":"Los Picachos",
    "wof:placetype":"locality"
},
  "geometry": {"coordinates":[-104.92332,22.49029],"type":"Point"}
}