{
  "type": "Feature",
  "properties": {
    "gn:admin1_code":"24",
    "gn:admin2_code":"13.0",
    "gn:asciiname":"San Antonio Huichimal",
    "gn:country_code":"MX",
    "gn:dem":155,
    "gn:feature_class":"P",
    "gn:feature_code":"PPL",
    "gn:name":"San Antonio Huichimal",
    "gn:population":0,
    "gn:timezone":"America/Mexico_City",
    "iso:country":"MX",
    "name:spa_x_preferred":[
        "San Antonio Huichimal"
    ],
    "name:und_x_variant":[
        "Huichinal",
        "Huichimal"
    ],
    "wof:name":"San Antonio Huichimal",
    "wof:placetype":"locality"
},
  "geometry": {"coordinates":[-99.10637,21.93904],"type":"Point"}
}