{
  "type": "Feature",
  "properties": {
    "gn:admin1_code":"24",
    "gn:admin2_code":"3.0",
    "gn:asciiname":"Tan Tzajib",
    "gn:country_code":"MX",
    "gn:dem":788,
    "gn:feature_class":"P",
    "gn:feature_code":"PPL",
    "gn:name":"Tan Tzajib",
    "gn:population":142,
    "gn:timezone":"America/Mexico_City",
    "iso:country":"MX",
    "wof:name":"Tan Tzajib",
    "wof:placetype":"locality",
    "wof:population":142
},
  "geometry": {"coordinates":[-99.03082999999999,21.56167],"type":"Point"}
}