{
  "type": "Feature",
  "properties": {
    "gn:admin1_code":"25",
    "gn:admin2_code":"9",
    "gn:asciiname":"El Camichin [Sitio de Pesca]",
    "gn:country_code":"MX",
    "gn:dem":7,
    "gn:feature_class":"P",
    "gn:feature_code":"PPL",
    "gn:name":"El Camich\u00edn [Sitio de Pesca]",
    "gn:population":10,
    "gn:timezone":"America/Mazatlan",
    "iso:country":"MX",
    "name:und_x_variant":[
        "El Camich\u00edn [Sitio de Pesca]"
    ],
    "wof:name":"El Camichin [Sitio de Pesca]",
    "wof:placetype":"locality",
    "wof:population":10
},
  "geometry": {"coordinates":[-105.70256000000001,22.57164],"type":"Point"}
}