{
  "type": "Feature",
  "properties": {
    "gn:admin1_code":"30",
    "gn:admin2_code":"121.0",
    "gn:asciiname":"La Orquidea",
    "gn:country_code":"MX",
    "gn:dem":64,
    "gn:feature_class":"P",
    "gn:feature_code":"PPL",
    "gn:name":"La Orqu\u00eddea",
    "gn:population":6,
    "gn:timezone":"America/Mexico_City",
    "iso:country":"MX",
    "name:und_x_variant":[
        "La Orqu\u00eddea"
    ],
    "wof:name":"La Orquidea",
    "wof:placetype":"locality",
    "wof:population":6
},
  "geometry": {"coordinates":[-97.97472,21.72083],"type":"Point"}
}