{
  "type": "Feature",
  "properties": {
    "gn:admin1_code":"20",
    "gn:admin2_code":"339.0",
    "gn:asciiname":"Guadalupe Vista Hermosa",
    "gn:country_code":"MX",
    "gn:dem":2248,
    "gn:feature_class":"P",
    "gn:feature_code":"PPL",
    "gn:name":"Guadalupe Vista Hermosa",
    "gn:population":0,
    "gn:timezone":"America/Mexico_City",
    "iso:country":"MX",
    "name:spa_x_preferred":[
        "Guadalupe Vista Hermosa"
    ],
    "wof:name":"Guadalupe Vista Hermosa",
    "wof:placetype":"locality"
},
  "geometry": {"coordinates":[-97.61378999999999,17.5214],"type":"Point"}
}