{
  "type": "Feature",
  "properties": {
    "gn:admin1_code":"20",
    "gn:admin2_code":"205.0",
    "gn:asciiname":"Santiago Yaveo",
    "gn:country_code":"MX",
    "gn:dem":351,
    "gn:feature_class":"P",
    "gn:feature_code":"PPL",
    "gn:name":"Santiago Yaveo",
    "gn:population":0,
    "gn:timezone":"America/Mexico_City",
    "iso:country":"MX",
    "name:und_x_variant":[
        "Yaveo",
        "Santiago",
        "Santiago Yaveo"
    ],
    "wof:name":"Santiago Yaveo",
    "wof:placetype":"locality"
},
  "geometry": {"coordinates":[-95.73439999999999,17.331],"type":"Point"}
}