{
  "type": "Feature",
  "properties": {
    "gn:admin1_code":"20",
    "gn:admin2_code":"205.0",
    "gn:asciiname":"Santiago Yaveo",
    "gn:country_code":"MX",
    "gn:dem":351,
    "gn:feature_class":"P",
    "gn:feature_code":"PPL",
    "gn:name":"Santiago Yaveo",
    "gn:population":0,
    "gn:timezone":"America/Mexico_City",
    "iso:country":"MX",
    "name:ceb_x_preferred":[
        "Santiago Yaveo"
    ],
    "name:epo_x_preferred":[
        "Santiago Yaveo"
    ],
    "name:eus_x_preferred":[
        "Santiago Yaveo"
    ],
    "name:sco_x_preferred":[
        "Santiago Yaveo"
    ],
    "name:srp_x_preferred":[
        "\u041e\u043f\u0448\u0442\u0438\u043d\u0430 \u0421\u0430\u043d\u0442\u0438\u0458\u0430\u0433\u043e \u0408\u0430\u0432\u0435\u043e"
    ],
    "name:swe_x_preferred":[
        "Santiago Yaveo"
    ],
    "name:und_x_variant":[
        "Yaveo",
        "Santiago"
    ],
    "name:vie_x_preferred":[
        "Santiago Yaveo"
    ],
    "wof:name":"Santiago Yaveo",
    "wof:placetype":"locality"
},
  "geometry": {"coordinates":[-95.73439999999999,17.331],"type":"Point"}
}