{
  "type": "Feature",
  "properties": {
    "gn:admin1_code":"26.0",
    "gn:admin2_code":"46.0",
    "gn:asciiname":"El Sahuarito",
    "gn:country_code":"MX",
    "gn:dem":461,
    "gn:feature_class":"P",
    "gn:feature_code":"PPL",
    "gn:name":"El Sahuarito",
    "gn:population":0,
    "gn:timezone":"America/Hermosillo",
    "iso:country":"MX",
    "name:spa_x_preferred":[
        "El Sahuarito"
    ],
    "wof:name":"El Sahuarito",
    "wof:placetype":"locality"
},
  "geometry": {"coordinates":[-111.76097,30.7362],"type":"Point"}
}