{
  "type": "Feature",
  "properties": {
    "gn:admin1_code":"12",
    "gn:admin2_code":"59.0",
    "gn:asciiname":"Colonia Valerio Trujano (Valerio Trujano)",
    "gn:country_code":"MX",
    "gn:dem":478,
    "gn:feature_class":"P",
    "gn:feature_code":"PPL",
    "gn:name":"Colonia Valerio Trujano (Valerio Trujano)",
    "gn:population":314,
    "gn:timezone":"America/Mexico_City",
    "iso:country":"MX",
    "wof:name":"Colonia Valerio Trujano (Valerio Trujano)",
    "wof:placetype":"locality",
    "wof:population":314
},
  "geometry": {"coordinates":[-99.58944,17.94027999999999],"type":"Point"}
}