{
  "type": "Feature",
  "properties": {
    "gn:admin1_code":"3",
    "gn:admin2_code":"8",
    "gn:asciiname":"Barrio Boca de la Canada",
    "gn:country_code":"MX",
    "gn:dem":117,
    "gn:feature_class":"P",
    "gn:feature_code":"PPL",
    "gn:name":"Barrio Boca de la Ca\u00f1ada",
    "gn:population":44,
    "gn:timezone":"America/Mazatlan",
    "iso:country":"MX",
    "name:und_x_variant":[
        "Barrio Boca de la Ca\u00f1ada"
    ],
    "wof:name":"Barrio Boca de la Canada",
    "wof:placetype":"locality",
    "wof:population":44
},
  "geometry": {"coordinates":[-109.7077,23.47849],"type":"Point"}
}