{
  "type": "Feature",
  "properties": {
    "gn:admin1_code":"12",
    "gn:admin2_code":"45",
    "gn:asciiname":"Teapan",
    "gn:country_code":"MX",
    "gn:dem":1113,
    "gn:feature_class":"P",
    "gn:feature_code":"PPL",
    "gn:name":"Teapan",
    "gn:population":12,
    "gn:timezone":"America/Mexico_City",
    "iso:country":"MX",
    "wof:name":"Teapan",
    "wof:placetype":"locality",
    "wof:population":12
},
  "geometry": {"coordinates":[-98.65589,17.90706],"type":"Point"}
}