{
  "type": "Feature",
  "properties": {
    "gn:admin1_code":"5",
    "gn:admin2_code":"30.0",
    "gn:asciiname":"20 de Noviembre",
    "gn:country_code":"MX",
    "gn:dem":634,
    "gn:feature_class":"P",
    "gn:feature_code":"PPL",
    "gn:name":"20 de Noviembre",
    "gn:population":524,
    "gn:timezone":"America/Mexico_City",
    "iso:country":"MX",
    "wof:name":"20 de Noviembre",
    "wof:placetype":"locality",
    "wof:population":524
},
  "geometry": {"coordinates":[-92.37860999999999,15.73806],"type":"Point"}
}