{
  "type": "Feature",
  "properties": {
    "gn:admin1_code":"14",
    "gn:admin2_code":"58.0",
    "gn:asciiname":"Amulco",
    "gn:country_code":"MX",
    "gn:dem":1797,
    "gn:feature_class":"P",
    "gn:feature_code":"PPL",
    "gn:name":"Amulco",
    "gn:population":8,
    "gn:timezone":"America/Mexico_City",
    "iso:country":"MX",
    "wof:name":"Amulco",
    "wof:placetype":"locality",
    "wof:population":8
},
  "geometry": {"coordinates":[-104.76472,20.64056],"type":"Point"}
}