{
  "type": "Feature",
  "properties": {
    "gn:admin1_code":"25",
    "gn:admin2_code":"17.0",
    "gn:asciiname":"La Aurora",
    "gn:country_code":"MX",
    "gn:dem":75,
    "gn:feature_class":"P",
    "gn:feature_code":"PPL",
    "gn:name":"La Aurora",
    "gn:population":0,
    "gn:timezone":"America/Mazatlan",
    "iso:country":"MX",
    "name:spa_x_preferred":[
        "La Aurora"
    ],
    "wof:name":"La Aurora",
    "wof:placetype":"locality"
},
  "geometry": {"coordinates":[-108.41200000000001,25.92375],"type":"Point"}
}