{
  "type": "Feature",
  "properties": {
    "iso:country":"MX",
    "name:ceb_x_preferred":[
        "Sierra Mojada"
    ],
    "name:eng_x_preferred":[
        "Sierra Mojada"
    ],
    "name:fra_x_preferred":[
        "Sierra Mojada"
    ],
    "name:nld_x_preferred":[
        "Sierra Mojada"
    ],
    "name:rus_x_preferred":[
        "\u0421\u044c\u0435\u0440\u0440\u0430-\u041c\u043e\u0445\u0430\u0434\u0430"
    ],
    "name:sco_x_preferred":[
        "Sierra Mojada"
    ],
    "name:spa_x_preferred":[
        "Sierra Mojada"
    ],
    "name:srp_x_preferred":[
        "\u0421\u0438\u0458\u0435\u0440\u0430 \u041c\u043e\u0445\u0430\u0434\u0430"
    ],
    "name:swe_x_preferred":[
        "Sierra Mojada"
    ],
    "name:vie_x_preferred":[
        "Sierra Mojada"
    ],
    "ne:ADM0CAP":0.0,
    "ne:ADM0NAME":"Mexico",
    "ne:ADM0_A3":"MEX",
    "ne:ADM1NAME":"Coahuila",
    "ne:ADMIN1_COD":0,
    "ne:CAPALT":0,
    "ne:CHANGED":0,
    "ne:CHECKME":0,
    "ne:COMPARE":0,
    "ne:DIFFASCII":0,
    "ne:ELEVATION":0.0,
    "ne:FEATURECLA":"Populated place",
    "ne:GEONAMEID":-1,
    "ne:GEONAMESNO":"No GeoNames match due to small population, not in GeoNames, or poor NEV placement.",
    "ne:GN_POP":0,
    "ne:GTOPO30":0.0,
    "ne:ISO_A2":"MX",
    "ne:LABELRANK":2,
    "ne:LATITUDE":27.287571,
    "ne:LONGITUDE":-103.287194,
    "ne:LS_MATCH":0,
    "ne:LS_NAME":"Sierra Mojada",
    "ne:MAX_AREAKM":0.0,
    "ne:MAX_AREAMI":0.0,
    "ne:MAX_BBXMAX":0.0,
    "ne:MAX_BBXMIN":0.0,
    "ne:MAX_BBYMAX":0.0,
    "ne:MAX_BBYMIN":0.0,
    "ne:MAX_NATSCA":0.0,
    "ne:MAX_PERKM":0.0,
    "ne:MAX_PERMI":0.0,
    "ne:MAX_POP10":0,
    "ne:MAX_POP20":0,
    "ne:MAX_POP300":0,
    "ne:MAX_POP310":0,
    "ne:MAX_POP50":0,
    "ne:MEAN_BBXC":0.0,
    "ne:MEAN_BBYC":0.0,
    "ne:MEGACITY":0,
    "ne:MIN_AREAKM":0.0,
    "ne:MIN_AREAMI":0.0,
    "ne:MIN_BBXMAX":0.0,
    "ne:MIN_BBXMIN":0.0,
    "ne:MIN_BBYMAX":0.0,
    "ne:MIN_BBYMIN":0.0,
    "ne:MIN_PERKM":0.0,
    "ne:MIN_PERMI":0.0,
    "ne:NAME":"Sierra Mojada",
    "ne:NAMEASCII":"Sierra Mojada",
    "ne:NAMEDIFF":0,
    "ne:NATSCALE":20,
    "ne:POP1950":0,
    "ne:POP1955":0,
    "ne:POP1960":0,
    "ne:POP1965":0,
    "ne:POP1970":0,
    "ne:POP1975":0,
    "ne:POP1980":0,
    "ne:POP1985":0,
    "ne:POP1990":0,
    "ne:POP1995":0,
    "ne:POP2000":0,
    "ne:POP2005":0,
    "ne:POP2010":0,
    "ne:POP2015":0,
    "ne:POP2020":0,
    "ne:POP2025":0,
    "ne:POP2050":0,
    "ne:POP_MAX":10,
    "ne:POP_MIN":10,
    "ne:POP_OTHER":0,
    "ne:RANK_MAX":1,
    "ne:RANK_MIN":1,
    "ne:SCALERANK":7,
    "ne:SOV0NAME":"Mexico",
    "ne:SOV_A3":"MEX",
    "ne:UN_FID":0,
    "ne:UN_LAT":0.0,
    "ne:UN_LONG":0.0,
    "ne:WORLDCITY":0,
    "ne:min_zoom":6.7,
    "wof:name":"Sierra Mojada",
    "wof:placetype":"locality"
},
  "geometry": {"coordinates":[-103.28719445983558,27.28757082011265],"type":"Point"}
}