{
  "type": "Feature",
  "properties": {
    "gn:admin1_code":"24",
    "gn:admin2_code":"3.0",
    "gn:asciiname":"Tanute",
    "gn:country_code":"MX",
    "gn:dem":67,
    "gn:feature_class":"P",
    "gn:feature_code":"PPL",
    "gn:name":"Tanute",
    "gn:population":1424,
    "gn:timezone":"America/Mexico_City",
    "iso:country":"MX",
    "name:und_x_variant":[
        "Tantate"
    ],
    "wof:name":"Tanute",
    "wof:placetype":"locality",
    "wof:population":1424
},
  "geometry": {"coordinates":[-99.03765,21.65243],"type":"Point"}
}