{
  "type": "Feature",
  "properties": {
    "gn:admin1_code":"31",
    "gn:admin2_code":"57.0",
    "gn:asciiname":"Santa Martha",
    "gn:country_code":"MX",
    "gn:dem":13,
    "gn:feature_class":"P",
    "gn:feature_code":"PPL",
    "gn:name":"Santa Martha",
    "gn:population":0,
    "gn:timezone":"America/Merida",
    "iso:country":"MX",
    "name:spa_x_preferred":[
        "Santa Martha"
    ],
    "wof:name":"Santa Martha",
    "wof:placetype":"locality"
},
  "geometry": {"coordinates":[-88.1348,21.35828],"type":"Point"}
}