{
  "type": "Feature",
  "properties": {
    "gn:admin1_code":"30.0",
    "gn:asciiname":"El Arenal",
    "gn:country_code":"MX",
    "gn:dem":13,
    "gn:feature_class":"P",
    "gn:feature_code":"PPL",
    "gn:name":"El Arenal",
    "gn:population":0,
    "gn:timezone":"America/Mexico_City",
    "iso:country":"MX",
    "name:spa_x_preferred":[
        "El Arenal"
    ],
    "wof:name":"El Arenal",
    "wof:placetype":"locality"
},
  "geometry": {"coordinates":[-94.48197999999999,17.97253],"type":"Point"}
}