{
  "type": "Feature",
  "properties": {
    "gn:admin1_code":"30",
    "gn:admin2_code":"32.0",
    "gn:asciiname":"Santa Lucia",
    "gn:country_code":"MX",
    "gn:dem":403,
    "gn:feature_class":"P",
    "gn:feature_code":"PPL",
    "gn:name":"Santa Luc\u00eda",
    "gn:population":8,
    "gn:timezone":"America/Mexico_City",
    "iso:country":"MX",
    "name:und_x_variant":[
        "Santa Luc\u00eda"
    ],
    "wof:name":"Santa Lucia",
    "wof:placetype":"locality",
    "wof:population":8
},
  "geometry": {"coordinates":[-95.04528000000001,18.44639],"type":"Point"}
}