{
  "type": "Feature",
  "properties": {
    "gn:admin1_code":"26",
    "gn:admin2_code":"18.0",
    "gn:asciiname":"Ruben Haros",
    "gn:country_code":"MX",
    "gn:dem":43,
    "gn:feature_class":"P",
    "gn:feature_code":"PPL",
    "gn:name":"Rub\u00e9n Haros",
    "gn:population":6,
    "gn:timezone":"America/Hermosillo",
    "iso:country":"MX",
    "name:und_x_variant":[
        "Rub\u00e9n Haros"
    ],
    "wof:name":"Ruben Haros",
    "wof:placetype":"locality",
    "wof:population":6
},
  "geometry": {"coordinates":[-109.91083,27.55611],"type":"Point"}
}