{
  "type": "Feature",
  "properties": {
    "gn:admin1_code":"26",
    "gn:admin2_code":"30.0",
    "gn:asciiname":"El Dorado",
    "gn:country_code":"MX",
    "gn:dem":40,
    "gn:feature_class":"P",
    "gn:feature_code":"PPL",
    "gn:name":"El Dorado",
    "gn:population":69,
    "gn:timezone":"America/Hermosillo",
    "iso:country":"MX",
    "name:spa_x_preferred":[
        "El Dorado"
    ],
    "wof:name":"El Dorado",
    "wof:placetype":"locality",
    "wof:population":69
},
  "geometry": {"coordinates":[-111.39084,28.59839],"type":"Point"}
}