{
  "type": "Feature",
  "properties": {
    "gn:admin1_code":"12",
    "gn:admin2_code":"32",
    "gn:asciiname":"Xochitepec",
    "gn:country_code":"MX",
    "gn:dem":1554,
    "gn:feature_class":"P",
    "gn:feature_code":"PPL",
    "gn:name":"Xochitepec",
    "gn:population":36,
    "gn:timezone":"America/Mexico_City",
    "iso:country":"MX",
    "name:ceb_x_preferred":[
        "Xochitepec"
    ],
    "name:deu_x_preferred":[
        "Xochitepec"
    ],
    "name:epo_x_preferred":[
        "Xochitepec"
    ],
    "name:eus_x_preferred":[
        "Xochitepec"
    ],
    "name:fra_x_preferred":[
        "Xochitepec"
    ],
    "name:ita_x_preferred":[
        "Xochitepec"
    ],
    "name:por_x_preferred":[
        "Xochitepec"
    ],
    "name:rus_x_preferred":[
        "\u0421\u043e\u0447\u0438\u0442\u0435\u043f\u0435\u043a"
    ],
    "name:sco_x_preferred":[
        "Xochitepec"
    ],
    "name:spa_x_preferred":[
        "Xochitepec"
    ],
    "name:srp_x_preferred":[
        "\u041e\u043f\u0448\u0442\u0438\u043d\u0430 \u0421\u043e\u0447\u0438\u0442\u0435\u043f\u0435\u043a"
    ],
    "name:swe_x_preferred":[
        "Xochitepec"
    ],
    "name:vie_x_preferred":[
        "Xochitepec"
    ],
    "wof:name":"Xochitepec",
    "wof:placetype":"locality",
    "wof:population":36
},
  "geometry": {"coordinates":[-100.0163,17.7881],"type":"Point"}
}