{
  "type": "Feature",
  "properties": {
    "gn:admin1_code":"26",
    "gn:admin2_code":"26.0",
    "gn:asciiname":"El Salitral",
    "gn:country_code":"MX",
    "gn:dem":14,
    "gn:feature_class":"P",
    "gn:feature_code":"PPL",
    "gn:name":"El Salitral",
    "gn:population":0,
    "gn:timezone":"America/Hermosillo",
    "iso:country":"MX",
    "name:spa_x_preferred":[
        "El Salitral"
    ],
    "name:und_x_variant":[
        "Rancho Salitral"
    ],
    "wof:name":"El Salitral",
    "wof:placetype":"locality"
},
  "geometry": {"coordinates":[-109.63979999999999,26.88441],"type":"Point"}
}