{
  "type": "Feature",
  "properties": {
    "gn:admin1_code":"6.0",
    "gn:asciiname":"La Hacienda",
    "gn:country_code":"MX",
    "gn:dem":1152,
    "gn:feature_class":"P",
    "gn:feature_code":"PPL",
    "gn:name":"La Hacienda",
    "gn:population":0,
    "gn:timezone":"America/Chihuahua",
    "iso:country":"MX",
    "name:spa_x_preferred":[
        "La Hacienda"
    ],
    "wof:name":"La Hacienda",
    "wof:placetype":"locality"
},
  "geometry": {"coordinates":[-105.50999,28.24429],"type":"Point"}
}