{
  "type": "Feature",
  "properties": {
    "gn:admin1_code":"12",
    "gn:admin2_code":"31.0",
    "gn:asciiname":"Sabino Alto",
    "gn:country_code":"MX",
    "gn:dem":1400,
    "gn:feature_class":"P",
    "gn:feature_code":"PPL",
    "gn:name":"Sabino Alto",
    "gn:population":61,
    "gn:timezone":"America/Mexico_City",
    "iso:country":"MX",
    "wof:name":"Sabino Alto",
    "wof:placetype":"locality",
    "wof:population":61
},
  "geometry": {"coordinates":[-100.11893999999999,18.40243],"type":"Point"}
}