{
  "type": "Feature",
  "properties": {
    "gn:admin1_code":"20",
    "gn:admin2_code":"171",
    "gn:asciiname":"Agua de Luna",
    "gn:country_code":"MX",
    "gn:dem":855,
    "gn:feature_class":"P",
    "gn:feature_code":"PPL",
    "gn:name":"Agua de Luna",
    "gn:population":14,
    "gn:timezone":"America/Mexico_City",
    "iso:country":"MX",
    "wof:name":"Agua de Luna",
    "wof:placetype":"locality",
    "wof:population":14
},
  "geometry": {"coordinates":[-96.71138999999999,18.22444],"type":"Point"}
}