{
  "type": "Feature",
  "properties": {
    "gn:admin1_code":"16",
    "gn:admin2_code":"77.0",
    "gn:asciiname":"Penas Prietas",
    "gn:country_code":"MX",
    "gn:dem":257,
    "gn:feature_class":"P",
    "gn:feature_code":"PPL",
    "gn:name":"Pe\u00f1as Prietas",
    "gn:population":8,
    "gn:timezone":"America/Mexico_City",
    "iso:country":"MX",
    "name:und_x_variant":[
        "Pe\u00f1as Prietas"
    ],
    "wof:name":"Penas Prietas",
    "wof:placetype":"locality",
    "wof:population":8
},
  "geometry": {"coordinates":[-100.64333000000001,18.37694],"type":"Point"}
}