{
  "type": "Feature",
  "properties": {
    "gn:admin1_code":"30",
    "gn:admin2_code":"89.0",
    "gn:asciiname":"La Cienega",
    "gn:cc2":"MX",
    "gn:country_code":"MX",
    "gn:dem":22,
    "gn:feature_class":"P",
    "gn:feature_code":"PPL",
    "gn:name":"La Ci\u00e9nega",
    "gn:population":280,
    "gn:timezone":"America/Mexico_City",
    "iso:country":"MX",
    "name:ceb_x_preferred":[
        "La Cienega"
    ],
    "name:swe_x_preferred":[
        "La Cienega"
    ],
    "name:und_x_variant":[
        "Cienega",
        "La Ci\u00e9naga"
    ],
    "wof:name":"La Cienega",
    "wof:placetype":"locality",
    "wof:population":280
},
  "geometry": {"coordinates":[-94.7075,17.90972],"type":"Point"}
}