{
  "type": "Feature",
  "properties": {
    "gn:admin1_code":"12",
    "gn:admin2_code":"45.0",
    "gn:asciiname":"San Felipe Amatitlan (Amatitlan)",
    "gn:country_code":"MX",
    "gn:dem":1386,
    "gn:feature_class":"P",
    "gn:feature_code":"PPL",
    "gn:name":"San Felipe Amatitl\u00e1n (Amatitl\u00e1n)",
    "gn:population":103,
    "gn:timezone":"America/Mexico_City",
    "iso:country":"MX",
    "name:und_x_variant":[
        "San Felipe Amatitl\u00e1n (Amatitl\u00e1n)"
    ],
    "wof:name":"San Felipe Amatitlan (Amatitlan)",
    "wof:placetype":"locality",
    "wof:population":103
},
  "geometry": {"coordinates":[-98.69450000000001,17.84321],"type":"Point"}
}