{
  "type": "Feature",
  "properties": {
    "gn:admin1_code":"32.0",
    "gn:admin2_code":"14.0",
    "gn:asciiname":"Atotonico",
    "gn:country_code":"MX",
    "gn:dem":1803,
    "gn:feature_class":"P",
    "gn:feature_code":"PPL",
    "gn:name":"Atotonico",
    "gn:population":0,
    "gn:timezone":"America/Mexico_City",
    "iso:country":"MX",
    "wof:name":"Atotonico",
    "wof:placetype":"locality"
},
  "geometry": {"coordinates":[-102.81667,24.21667],"type":"Point"}
}