{
  "type": "Feature",
  "properties": {
    "gn:admin1_code":"1",
    "gn:admin2_code":"7.0",
    "gn:asciiname":"El Halcon",
    "gn:country_code":"MX",
    "gn:dem":1918,
    "gn:feature_class":"P",
    "gn:feature_code":"PPL",
    "gn:name":"El Halc\u00f3n",
    "gn:population":7,
    "gn:timezone":"America/Mexico_City",
    "iso:country":"MX",
    "name:und_x_variant":[
        "El Halc\u00f3n"
    ],
    "wof:name":"El Halcon",
    "wof:placetype":"locality",
    "wof:population":7
},
  "geometry": {"coordinates":[-102.29194,22.175],"type":"Point"}
}