{
  "type": "Feature",
  "properties": {
    "gn:admin1_code":"28.0",
    "gn:admin2_code":"8.0",
    "gn:asciiname":"Las Lajas",
    "gn:country_code":"MX",
    "gn:dem":417,
    "gn:feature_class":"P",
    "gn:feature_code":"PPL",
    "gn:name":"Las Lajas",
    "gn:population":6,
    "gn:timezone":"America/Monterrey",
    "iso:country":"MX",
    "name:spa_x_preferred":[
        "Las Lajas"
    ],
    "wof:name":"Las Lajas",
    "wof:placetype":"locality",
    "wof:population":6
},
  "geometry": {"coordinates":[-98.53306000000001,23.52222],"type":"Point"}
}