{
  "type": "Feature",
  "properties": {
    "gn:admin1_code":"20",
    "gn:admin2_code":"491.0",
    "gn:asciiname":"Recibimiento de Cuauhtemoc",
    "gn:country_code":"MX",
    "gn:dem":2336,
    "gn:feature_class":"P",
    "gn:feature_code":"PPL",
    "gn:name":"Recibimiento de Cuauht\u00e9moc",
    "gn:population":0,
    "gn:timezone":"America/Mexico_City",
    "iso:country":"MX",
    "name:spa_x_preferred":[
        "Recibimiento de Cuauht\u00e9moc"
    ],
    "wof:name":"Recibimiento de Cuauhtemoc",
    "wof:placetype":"locality"
},
  "geometry": {"coordinates":[-97.26372000000001,16.74733],"type":"Point"}
}