{
  "type": "Feature",
  "properties": {
    "gn:admin1_code":"15",
    "gn:admin2_code":"112.0",
    "gn:asciiname":"San Luis Anahuac (Toriles)",
    "gn:country_code":"MX",
    "gn:dem":2361,
    "gn:feature_class":"P",
    "gn:feature_code":"PPL",
    "gn:name":"San Luis An\u00e1huac (Toriles)",
    "gn:population":1554,
    "gn:timezone":"America/Mexico_City",
    "iso:country":"MX",
    "wof:name":"San Luis Anahuac (Toriles)",
    "wof:placetype":"locality",
    "wof:population":1554
},
  "geometry": {"coordinates":[-99.40029,19.79679],"type":"Point"}
}