{
  "type": "Feature",
  "properties": {
    "gn:admin1_code":"12.0",
    "gn:admin2_code":"55.0",
    "gn:asciiname":"Coatlapanaloya",
    "gn:country_code":"MX",
    "gn:dem":1746,
    "gn:feature_class":"P",
    "gn:feature_code":"PPL",
    "gn:name":"Coatlapanaloya",
    "gn:population":0,
    "gn:timezone":"America/Mexico_City",
    "iso:country":"MX",
    "name:spa_x_preferred":[
        "Coatlapanaloya"
    ],
    "wof:name":"Coatlapanaloya",
    "wof:placetype":"locality"
},
  "geometry": {"coordinates":[-99.56453,18.52061],"type":"Point"}
}