{
  "type": "Feature",
  "properties": {
    "gn:admin1_code":"12.0",
    "gn:admin2_code":"22.0",
    "gn:asciiname":"La Bajada",
    "gn:country_code":"MX",
    "gn:dem":254,
    "gn:feature_class":"P",
    "gn:feature_code":"PPL",
    "gn:name":"La Bajada",
    "gn:population":0,
    "gn:timezone":"America/Mexico_City",
    "iso:country":"MX",
    "name:spa_x_preferred":[
        "La Bajada"
    ],
    "wof:name":"La Bajada",
    "wof:placetype":"locality"
},
  "geometry": {"coordinates":[-100.67195,18.31937000000001],"type":"Point"}
}