{
  "type": "Feature",
  "properties": {
    "gn:admin1_code":"19.0",
    "gn:admin2_code":"22.0",
    "gn:asciiname":"El Sitio",
    "gn:country_code":"MX",
    "gn:dem":260,
    "gn:feature_class":"P",
    "gn:feature_code":"PPL",
    "gn:name":"El Sitio",
    "gn:population":0,
    "gn:timezone":"America/Monterrey",
    "iso:country":"MX",
    "name:spa_x_preferred":[
        "El Sitio"
    ],
    "wof:name":"El Sitio",
    "wof:placetype":"locality"
},
  "geometry": {"coordinates":[-99.6494,25.39647],"type":"Point"}
}