{
  "type": "Feature",
  "properties": {
    "gn:admin1_code":"14.0",
    "gn:admin2_code":"110.0",
    "gn:asciiname":"Los Arquitos",
    "gn:country_code":"MX",
    "gn:dem":1377,
    "gn:feature_class":"P",
    "gn:feature_code":"PPL",
    "gn:name":"Los Arquitos",
    "gn:population":0,
    "gn:timezone":"America/Mexico_City",
    "iso:country":"MX",
    "name:spa_x_preferred":[
        "Los Arquitos"
    ],
    "wof:name":"Los Arquitos",
    "wof:placetype":"locality"
},
  "geometry": {"coordinates":[-104.22529,19.97887],"type":"Point"}
}