{
  "type": "Feature",
  "properties": {
    "gn:admin1_code":"25.0",
    "gn:admin2_code":"15.0",
    "gn:asciiname":"El Aguaje",
    "gn:country_code":"MX",
    "gn:dem":91,
    "gn:feature_class":"P",
    "gn:feature_code":"PPL",
    "gn:name":"El Aguaje",
    "gn:population":2,
    "gn:timezone":"America/Mazatlan",
    "iso:country":"MX",
    "wof:name":"El Aguaje",
    "wof:placetype":"locality",
    "wof:population":2
},
  "geometry": {"coordinates":[-108.02328,25.36748],"type":"Point"}
}