{
  "type": "Feature",
  "properties": {
    "gn:admin1_code":"13",
    "gn:admin2_code":"26.0",
    "gn:asciiname":"Acohuaco",
    "gn:country_code":"MX",
    "gn:dem":706,
    "gn:feature_class":"P",
    "gn:feature_code":"PPL",
    "gn:name":"Acohuaco",
    "gn:population":5,
    "gn:timezone":"America/Mexico_City",
    "iso:country":"MX",
    "wof:name":"Acohuaco",
    "wof:placetype":"locality",
    "wof:population":5
},
  "geometry": {"coordinates":[-98.50194,20.97333],"type":"Point"}
}