{
  "type": "Feature",
  "properties": {
    "gn:admin1_code":"30",
    "gn:admin2_code":"143",
    "gn:asciiname":"Tepozapan",
    "gn:country_code":"MX",
    "gn:dem":281,
    "gn:feature_class":"P",
    "gn:feature_code":"PPL",
    "gn:name":"Tepozapan",
    "gn:population":11,
    "gn:timezone":"America/Mexico_City",
    "iso:country":"MX",
    "wof:name":"Tepozapan",
    "wof:placetype":"locality",
    "wof:population":11
},
  "geometry": {"coordinates":[-95.29361,18.45472],"type":"Point"}
}