{
  "type": "Feature",
  "properties": {
    "gn:admin1_code":"30",
    "gn:admin2_code":"23",
    "gn:asciiname":"Las Trojas",
    "gn:country_code":"MX",
    "gn:dem":589,
    "gn:feature_class":"P",
    "gn:feature_code":"PPL",
    "gn:name":"Las Trojas",
    "gn:population":31,
    "gn:timezone":"America/Mexico_City",
    "iso:country":"MX",
    "wof:name":"Las Trojas",
    "wof:placetype":"locality",
    "wof:population":31
},
  "geometry": {"coordinates":[-96.97583,19.90222],"type":"Point"}
}