{
  "type": "Feature",
  "properties": {
    "gn:admin1_code":"14.0",
    "gn:asciiname":"Bajio de Charcos",
    "gn:country_code":"MX",
    "gn:dem":1676,
    "gn:feature_class":"P",
    "gn:feature_code":"PPL",
    "gn:name":"Baj\u00edo de Charcos",
    "gn:population":0,
    "gn:timezone":"America/Mexico_City",
    "iso:country":"MX",
    "name:spa_x_preferred":[
        "Baj\u00edo de Charcos"
    ],
    "wof:name":"Bajio de Charcos",
    "wof:placetype":"locality"
},
  "geometry": {"coordinates":[-103.88821,22.49271],"type":"Point"}
}