{
  "type": "Feature",
  "properties": {
    "gn:admin1_code":"30",
    "gn:admin2_code":"181",
    "gn:asciiname":"Mata Guitarra",
    "gn:country_code":"MX",
    "gn:dem":86,
    "gn:feature_class":"P",
    "gn:feature_code":"PPL",
    "gn:name":"Mata Guitarra",
    "gn:population":52,
    "gn:timezone":"America/Mexico_City",
    "iso:country":"MX",
    "wof:name":"Mata Guitarra",
    "wof:placetype":"locality",
    "wof:population":52
},
  "geometry": {"coordinates":[-96.36722,18.71639],"type":"Point"}
}