{
  "type": "Feature",
  "properties": {
    "gn:admin1_code":"18.0",
    "gn:admin2_code":"5.0",
    "gn:asciiname":"Contadero",
    "gn:country_code":"MX",
    "gn:dem":192,
    "gn:feature_class":"P",
    "gn:feature_code":"PPL",
    "gn:name":"Contadero",
    "gn:population":200,
    "gn:timezone":"America/Mazatlan",
    "iso:country":"MX",
    "wof:name":"Contadero",
    "wof:placetype":"locality",
    "wof:population":200
},
  "geometry": {"coordinates":[-105.35805999999999,22.85833],"type":"Point"}
}