{
  "type": "Feature",
  "properties": {
    "gn:admin1_code":"18.0",
    "gn:admin2_code":"5.0",
    "gn:asciiname":"Contadero",
    "gn:country_code":"MX",
    "gn:dem":192,
    "gn:feature_class":"P",
    "gn:feature_code":"PPL",
    "gn:name":"Contadero",
    "gn:population":200,
    "gn:timezone":"America/Mazatlan",
    "iso:country":"MX",
    "name:ceb_x_preferred":[
        "Contadero"
    ],
    "name:fra_x_preferred":[
        "Contadero"
    ],
    "name:ita_x_preferred":[
        "Contadero"
    ],
    "name:kat_x_preferred":[
        "\u10d9\u10dd\u10dc\u10e2\u10d0\u10dc\u10d3\u10d4\u10e0\u10dd"
    ],
    "name:msa_x_preferred":[
        "Contadero"
    ],
    "name:nld_x_preferred":[
        "Contadero"
    ],
    "name:por_x_preferred":[
        "Contadero"
    ],
    "name:spa_x_preferred":[
        "Contadero"
    ],
    "name:swe_x_preferred":[
        "Contadero"
    ],
    "name:tgl_x_preferred":[
        "Contadero"
    ],
    "name:vie_x_preferred":[
        "Contadero"
    ],
    "name:war_x_preferred":[
        "Contadero"
    ],
    "name:zho_x_preferred":[
        "\u5b54\u5854\u5fb7\u7f85"
    ],
    "wof:name":"Contadero",
    "wof:placetype":"locality",
    "wof:population":200
},
  "geometry": {"coordinates":[-105.35805999999999,22.85833],"type":"Point"}
}