{
  "type": "Feature",
  "properties": {
    "gn:admin1_code":"6.0",
    "gn:admin2_code":"66.0",
    "gn:asciiname":"Corregidora de Arriba",
    "gn:country_code":"MX",
    "gn:dem":788,
    "gn:feature_class":"P",
    "gn:feature_code":"PPL",
    "gn:name":"Corregidora de Arriba",
    "gn:population":0,
    "gn:timezone":"America/Chihuahua",
    "iso:country":"MX",
    "name:spa_x_preferred":[
        "Corregidora de Arriba"
    ],
    "name:und_x_variant":[
        "Rancho Concepci\u00f3n de Arriba",
        "Concepcion de Arriba",
        "Concepci\u00f3n"
    ],
    "wof:name":"Corregidora de Arriba",
    "wof:placetype":"locality"
},
  "geometry": {"coordinates":[-108.26117000000001,27.81048],"type":"Point"}
}