{
  "type": "Feature",
  "properties": {
    "gn:admin1_code":"24",
    "gn:admin2_code":"13.0",
    "gn:asciiname":"El Desengano",
    "gn:country_code":"MX",
    "gn:dem":38,
    "gn:feature_class":"P",
    "gn:feature_code":"PPL",
    "gn:name":"El Desenga\u00f1o",
    "gn:population":0,
    "gn:timezone":"America/Mexico_City",
    "iso:country":"MX",
    "name:spa_x_preferred":[
        "El Desenga\u00f1o"
    ],
    "wof:name":"El Desengano",
    "wof:placetype":"locality"
},
  "geometry": {"coordinates":[-98.85319,21.85328],"type":"Point"}
}