{
  "type": "Feature",
  "properties": {
    "gn:admin1_code":"28.0",
    "gn:admin2_code":"2.0",
    "gn:asciiname":"El Coral",
    "gn:country_code":"MX",
    "gn:dem":90,
    "gn:feature_class":"P",
    "gn:feature_code":"PPL",
    "gn:name":"El Coral",
    "gn:population":0,
    "gn:timezone":"America/Monterrey",
    "iso:country":"MX",
    "name:ell_x_preferred":[
        "\u0395\u03bb \u039a\u03bf\u03c1\u03ac\u03bb"
    ],
    "name:fra_x_preferred":[
        "El Coral"
    ],
    "name:ita_x_preferred":[
        "El Coral"
    ],
    "name:spa_x_preferred":[
        "El Coral"
    ],
    "name:swe_x_preferred":[
        "El Coral"
    ],
    "name:urd_x_preferred":[
        "\u0627\u06cc\u0644 \u06a9\u0648\u0631\u0627\u0644"
    ],
    "name:vie_x_preferred":[
        "El Coral"
    ],
    "name:zho_x_preferred":[
        "\u57c3\u723e\u79d1\u62c9\u723e"
    ],
    "wof:name":"El Coral",
    "wof:placetype":"locality"
},
  "geometry": {"coordinates":[-98.29861,22.80333],"type":"Point"}
}