{
  "type": "Feature",
  "properties": {
    "gn:admin1_code":"28.0",
    "gn:admin2_code":"2.0",
    "gn:asciiname":"El Coral",
    "gn:country_code":"MX",
    "gn:dem":90,
    "gn:feature_class":"P",
    "gn:feature_code":"PPL",
    "gn:name":"El Coral",
    "gn:population":0,
    "gn:timezone":"America/Monterrey",
    "iso:country":"MX",
    "name:spa_x_preferred":[
        "El Coral"
    ],
    "wof:name":"El Coral",
    "wof:placetype":"locality"
},
  "geometry": {"coordinates":[-98.29861,22.80333],"type":"Point"}
}