{
  "type": "Feature",
  "properties": {
    "gn:admin1_code":"24",
    "gn:admin2_code":"20.0",
    "gn:asciiname":"Troje de los Moreno",
    "gn:cc2":"MX",
    "gn:country_code":"MX",
    "gn:dem":1645,
    "gn:feature_class":"P",
    "gn:feature_code":"PPL",
    "gn:name":"Troje de los Moreno",
    "gn:population":0,
    "gn:timezone":"America/Mexico_City",
    "iso:country":"MX",
    "name:und_x_variant":[
        "Troje",
        "Troje de los Moreno"
    ],
    "wof:name":"Troje de los Moreno",
    "wof:placetype":"locality"
},
  "geometry": {"coordinates":[-100.66667,23.71667],"type":"Point"}
}