{
  "type": "Feature",
  "properties": {
    "gn:admin1_code":"5",
    "gn:admin2_code":"47.0",
    "gn:asciiname":"Senor de Tila",
    "gn:country_code":"MX",
    "gn:dem":1416,
    "gn:feature_class":"P",
    "gn:feature_code":"PPL",
    "gn:name":"Se\u00f1or de Tila",
    "gn:population":4,
    "gn:timezone":"America/Mexico_City",
    "iso:country":"MX",
    "name:und_x_variant":[
        "Se\u00f1or de Tila"
    ],
    "wof:name":"Senor de Tila",
    "wof:placetype":"locality",
    "wof:population":4
},
  "geometry": {"coordinates":[-92.80249999999999,17.10972000000001],"type":"Point"}
}