{
  "type": "Feature",
  "properties": {
    "gn:admin1_code":"31",
    "gn:admin2_code":"26.0",
    "gn:asciiname":"Chen Kim",
    "gn:country_code":"MX",
    "gn:dem":9,
    "gn:feature_class":"P",
    "gn:feature_code":"PPL",
    "gn:name":"Chen Kim",
    "gn:population":0,
    "gn:timezone":"America/Merida",
    "iso:country":"MX",
    "name:spa_x_preferred":[
        "Chen Kim"
    ],
    "wof:name":"Chen Kim",
    "wof:placetype":"locality"
},
  "geometry": {"coordinates":[-89.32659,21.28593],"type":"Point"}
}