{
  "type": "Feature",
  "properties": {
    "gn:admin1_code":"30",
    "gn:admin2_code":"61",
    "gn:asciiname":"La Preferida (Rio Nuevo)",
    "gn:country_code":"MX",
    "gn:dem":11,
    "gn:feature_class":"P",
    "gn:feature_code":"PPL",
    "gn:name":"La Preferida (R\u00edo Nuevo)",
    "gn:population":17,
    "gn:timezone":"America/Mexico_City",
    "iso:country":"MX",
    "name:und_x_variant":[
        "La Preferida (R\u00edo Nuevo)"
    ],
    "wof:name":"La Preferida (Rio Nuevo)",
    "wof:placetype":"locality",
    "wof:population":17
},
  "geometry": {"coordinates":[-93.96639,17.70611],"type":"Point"}
}