{
  "type": "Feature",
  "properties": {
    "gn:admin1_code":"28",
    "gn:admin2_code":"22.0",
    "gn:asciiname":"La Tijerita",
    "gn:country_code":"MX",
    "gn:dem":11,
    "gn:feature_class":"P",
    "gn:feature_code":"PPL",
    "gn:name":"La Tijerita",
    "gn:population":0,
    "gn:timezone":"America/Matamoros",
    "iso:country":"MX",
    "name:spa_x_preferred":[
        "La Tijerita"
    ],
    "name:und_x_variant":[
        "La Tijera"
    ],
    "wof:name":"La Tijerita",
    "wof:placetype":"locality"
},
  "geometry": {"coordinates":[-97.54222,25.75203],"type":"Point"}
}