{
  "type": "Feature",
  "properties": {
    "gn:admin1_code":"14.0",
    "gn:admin2_code":"100.0",
    "gn:asciiname":"Las Cotorras",
    "gn:country_code":"MX",
    "gn:dem":265,
    "gn:feature_class":"P",
    "gn:feature_code":"PPL",
    "gn:name":"Las Cotorras",
    "gn:population":0,
    "gn:timezone":"America/Mexico_City",
    "iso:country":"MX",
    "name:spa_x_preferred":[
        "Las Cotorras"
    ],
    "wof:name":"Las Cotorras",
    "wof:placetype":"locality"
},
  "geometry": {"coordinates":[-104.86208999999999,19.95287],"type":"Point"}
}