{
  "type": "Feature",
  "properties": {
    "gn:admin1_code":"20",
    "gn:admin2_code":"71.0",
    "gn:asciiname":"El Fenix",
    "gn:country_code":"MX",
    "gn:dem":1244,
    "gn:feature_class":"P",
    "gn:feature_code":"PPL",
    "gn:name":"El F\u00e9nix",
    "gn:population":0,
    "gn:timezone":"America/Mexico_City",
    "iso:country":"MX",
    "name:spa_x_preferred":[
        "El F\u00e9nix"
    ],
    "wof:name":"El Fenix",
    "wof:placetype":"locality"
},
  "geometry": {"coordinates":[-96.44443,15.9609],"type":"Point"}
}