{
  "type": "Feature",
  "properties": {
    "gn:admin1_code":"30",
    "gn:admin2_code":"89.0",
    "gn:asciiname":"El Negro",
    "gn:country_code":"MX",
    "gn:dem":44,
    "gn:feature_class":"P",
    "gn:feature_code":"PPL",
    "gn:name":"El Negro",
    "gn:population":7,
    "gn:timezone":"America/Mexico_City",
    "iso:country":"MX",
    "name:ceb_x_preferred":[
        "El Negro"
    ],
    "name:nld_x_preferred":[
        "El Negro"
    ],
    "name:srp_x_preferred":[
        "\u0415\u043b \u041d\u0435\u0433\u0440\u043e"
    ],
    "name:swe_x_preferred":[
        "El Negro"
    ],
    "wof:name":"El Negro",
    "wof:placetype":"locality",
    "wof:population":7
},
  "geometry": {"coordinates":[-94.78556,17.96417000000001],"type":"Point"}
}