{
  "type": "Feature",
  "properties": {
    "gn:admin1_code":"2",
    "gn:admin2_code":"1",
    "gn:asciiname":"La Mesa",
    "gn:country_code":"MX",
    "gn:dem":89,
    "gn:feature_class":"P",
    "gn:feature_code":"PPL",
    "gn:name":"La Mesa",
    "gn:population":23,
    "gn:timezone":"America/Tijuana",
    "iso:country":"MX",
    "wof:name":"La Mesa",
    "wof:placetype":"locality",
    "wof:population":23
},
  "geometry": {"coordinates":[-116.52222,31.67806],"type":"Point"}
}