{
  "type": "Feature",
  "properties": {
    "gn:admin1_code":"6",
    "gn:admin2_code":"29.0",
    "gn:asciiname":"Los Borreguitos",
    "gn:country_code":"MX",
    "gn:dem":1128,
    "gn:feature_class":"P",
    "gn:feature_code":"PPL",
    "gn:name":"Los Borreguitos",
    "gn:population":6,
    "gn:timezone":"America/Mazatlan",
    "iso:country":"MX",
    "wof:name":"Los Borreguitos",
    "wof:placetype":"locality",
    "wof:population":6
},
  "geometry": {"coordinates":[-107.82043,26.34800000000001],"type":"Point"}
}