{
  "type": "Feature",
  "properties": {
    "gn:admin1_code":"12",
    "gn:admin2_code":"24.0",
    "gn:asciiname":"Tlalixtlahuac",
    "gn:country_code":"MX",
    "gn:dem":1406,
    "gn:feature_class":"P",
    "gn:feature_code":"PPL",
    "gn:name":"Tlalixtl\u00e1huac",
    "gn:population":63,
    "gn:timezone":"America/Mexico_City",
    "iso:country":"MX",
    "name:und_x_variant":[
        "Tlalixtl\u00e1huac"
    ],
    "wof:name":"Tlalixtlahuac",
    "wof:placetype":"locality",
    "wof:population":63
},
  "geometry": {"coordinates":[-98.64541,17.71808],"type":"Point"}
}