{
  "type": "Feature",
  "properties": {
    "gn:admin1_code":"5",
    "gn:admin2_code":"80.0",
    "gn:asciiname":"Ain Karim",
    "gn:country_code":"MX",
    "gn:dem":2564,
    "gn:feature_class":"P",
    "gn:feature_code":"PPL",
    "gn:name":"A\u00edn Karim",
    "gn:population":62,
    "gn:timezone":"America/Mexico_City",
    "iso:country":"MX",
    "name:und_x_variant":[
        "A\u00edn Karim"
    ],
    "wof:name":"Ain Karim",
    "wof:placetype":"locality",
    "wof:population":62
},
  "geometry": {"coordinates":[-92.28,15.52833],"type":"Point"}
}