{
  "type": "Feature",
  "properties": {
    "gn:admin1_code":"14",
    "gn:admin2_code":"68.0",
    "gn:asciiname":"El Llano de los Pozos",
    "gn:country_code":"MX",
    "gn:dem":433,
    "gn:feature_class":"P",
    "gn:feature_code":"PPL",
    "gn:name":"El Llano de los Pozos",
    "gn:population":6,
    "gn:timezone":"America/Mexico_City",
    "iso:country":"MX",
    "wof:name":"El Llano de los Pozos",
    "wof:placetype":"locality",
    "wof:population":6
},
  "geometry": {"coordinates":[-104.68837000000001,19.75302000000001],"type":"Point"}
}