{
  "type": "Feature",
  "properties": {
    "gn:admin1_code":"5",
    "gn:admin2_code":"56.0",
    "gn:asciiname":"Jomtealho",
    "gn:country_code":"MX",
    "gn:dem":2105,
    "gn:feature_class":"P",
    "gn:feature_code":"PPL",
    "gn:name":"Jomtealh\u00f3",
    "gn:population":450,
    "gn:timezone":"America/Mexico_City",
    "iso:country":"MX",
    "name:und_x_variant":[
        "Jomtealh\u00f3"
    ],
    "wof:name":"Jomtealho",
    "wof:placetype":"locality",
    "wof:population":450
},
  "geometry": {"coordinates":[-92.59139,16.88222],"type":"Point"}
}