{
  "type": "Feature",
  "properties": {
    "gn:admin1_code":"6",
    "gn:admin2_code":"17.0",
    "gn:asciiname":"Granjas el Venado",
    "gn:country_code":"MX",
    "gn:dem":2053,
    "gn:feature_class":"P",
    "gn:feature_code":"PPL",
    "gn:name":"Granjas el Venado",
    "gn:population":585,
    "gn:timezone":"America/Chihuahua",
    "iso:country":"MX",
    "wof:name":"Granjas el Venado",
    "wof:placetype":"locality",
    "wof:population":585
},
  "geometry": {"coordinates":[-106.88056,28.75444],"type":"Point"}
}