{
  "type": "Feature",
  "properties": {
    "gn:admin1_code":"30",
    "gn:admin2_code":"191.0",
    "gn:asciiname":"Puente Roto",
    "gn:country_code":"MX",
    "gn:dem":24,
    "gn:feature_class":"P",
    "gn:feature_code":"PPL",
    "gn:name":"Puente Roto",
    "gn:population":9,
    "gn:timezone":"America/Mexico_City",
    "iso:country":"MX",
    "wof:name":"Puente Roto",
    "wof:placetype":"locality",
    "wof:population":9
},
  "geometry": {"coordinates":[-96.40139000000001,19.45944],"type":"Point"}
}