{
  "type": "Feature",
  "properties": {
    "gn:admin1_code":"20",
    "gn:admin2_code":"263",
    "gn:asciiname":"Cerro Chivo",
    "gn:country_code":"MX",
    "gn:dem":1947,
    "gn:feature_class":"P",
    "gn:feature_code":"PPL",
    "gn:name":"Cerro Chivo",
    "gn:population":13,
    "gn:timezone":"America/Mexico_City",
    "iso:country":"MX",
    "wof:name":"Cerro Chivo",
    "wof:placetype":"locality",
    "wof:population":13
},
  "geometry": {"coordinates":[-96.68832999999999,16.16639],"type":"Point"}
}