{
  "type": "Feature",
  "properties": {
    "gn:admin1_code":"24",
    "gn:admin2_code":"24.0",
    "gn:asciiname":"La Salitrera",
    "gn:country_code":"MX",
    "gn:dem":1264,
    "gn:feature_class":"P",
    "gn:feature_code":"PPL",
    "gn:name":"La Salitrera",
    "gn:population":13,
    "gn:timezone":"America/Mexico_City",
    "iso:country":"MX",
    "wof:name":"La Salitrera",
    "wof:placetype":"locality",
    "wof:population":13
},
  "geometry": {"coordinates":[-99.97722,21.65583],"type":"Point"}
}