{
  "type": "Feature",
  "properties": {
    "gn:admin1_code":"3",
    "gn:admin2_code":"9.0",
    "gn:asciiname":"El Duende",
    "gn:country_code":"MX",
    "gn:dem":436,
    "gn:feature_class":"P",
    "gn:feature_code":"PPL",
    "gn:name":"El Duende",
    "gn:population":0,
    "gn:timezone":"America/Mazatlan",
    "iso:country":"MX",
    "name:spa_x_preferred":[
        "El Duende"
    ],
    "wof:name":"El Duende",
    "wof:placetype":"locality"
},
  "geometry": {"coordinates":[-111.44853999999999,25.77944],"type":"Point"}
}