{
  "type": "Feature",
  "properties": {
    "gn:admin1_code":"26",
    "gn:admin2_code":"23.0",
    "gn:asciiname":"Las Piochas",
    "gn:country_code":"MX",
    "gn:dem":771,
    "gn:feature_class":"P",
    "gn:feature_code":"PPL",
    "gn:name":"Las Piochas",
    "gn:population":0,
    "gn:timezone":"America/Hermosillo",
    "iso:country":"MX",
    "name:spa_x_preferred":[
        "Las Piochas"
    ],
    "wof:name":"Las Piochas",
    "wof:placetype":"locality"
},
  "geometry": {"coordinates":[-109.79649999999999,30.05879],"type":"Point"}
}