{
  "type": "Feature",
  "properties": {
    "gn:admin1_code":"14.0",
    "gn:admin2_code":"20.0",
    "gn:asciiname":"Chacala",
    "gn:cc2":"MX",
    "gn:country_code":"MX",
    "gn:dem":682,
    "gn:feature_class":"P",
    "gn:feature_code":"PPL",
    "gn:name":"Chacala",
    "gn:population":0,
    "gn:timezone":"America/Mexico_City",
    "iso:country":"MX",
    "name:und_x_variant":[
        "Concepci\u00f3n",
        "Chacal",
        "Chacala"
    ],
    "wof:name":"Chacala",
    "wof:placetype":"locality"
},
  "geometry": {"coordinates":[-105.34999999999999,20.35],"type":"Point"}
}