{
  "type": "Feature",
  "properties": {
    "gn:admin1_code":"30",
    "gn:admin2_code":"143.0",
    "gn:asciiname":"Las Lajas",
    "gn:country_code":"MX",
    "gn:dem":16,
    "gn:feature_class":"P",
    "gn:feature_code":"PPL",
    "gn:name":"Las Lajas",
    "gn:population":6,
    "gn:timezone":"America/Mexico_City",
    "iso:country":"MX",
    "name:bre_x_preferred":[
        "Las Lajas"
    ],
    "name:ceb_x_preferred":[
        "Las Lajas"
    ],
    "name:deu_x_preferred":[
        "Las Lajas"
    ],
    "name:fra_x_preferred":[
        "Las Lajas"
    ],
    "name:ita_x_preferred":[
        "Las Lajas"
    ],
    "name:lit_x_preferred":[
        "Las Lachasas"
    ],
    "name:nld_x_preferred":[
        "Las Lajas"
    ],
    "name:pol_x_preferred":[
        "Las Lajas"
    ],
    "name:spa_x_preferred":[
        "Las Lajas"
    ],
    "name:swe_x_preferred":[
        "Las Lajas"
    ],
    "wof:name":"Las Lajas",
    "wof:placetype":"locality",
    "wof:population":6
},
  "geometry": {"coordinates":[-95.47139,18.3675],"type":"Point"}
}