{
  "type": "Feature",
  "properties": {
    "gn:admin1_code":"20",
    "gn:admin2_code":"548.0",
    "gn:asciiname":"El Mirador",
    "gn:country_code":"MX",
    "gn:dem":1873,
    "gn:feature_class":"P",
    "gn:feature_code":"PPL",
    "gn:name":"El Mirador",
    "gn:population":6,
    "gn:timezone":"America/Mexico_City",
    "iso:country":"MX",
    "name:bel_x_preferred":[
        "\u042d\u043b\u044c-\u041c\u0456\u0440\u0430\u0434\u043e\u0440"
    ],
    "name:dan_x_preferred":[
        "El Mirador"
    ],
    "name:deu_x_preferred":[
        "El Mirador"
    ],
    "name:epo_x_preferred":[
        "El Mirador"
    ],
    "name:fin_x_preferred":[
        "El Mirador"
    ],
    "name:fra_x_preferred":[
        "El Mirador"
    ],
    "name:hun_x_preferred":[
        "El Mirador"
    ],
    "name:ind_x_preferred":[
        "El Mirador"
    ],
    "name:ita_x_preferred":[
        "El Mirador"
    ],
    "name:jpn_x_preferred":[
        "\u30a8\u30eb\u30fb\u30df\u30e9\u30c9\u30fc\u30eb"
    ],
    "name:lit_x_preferred":[
        "El Miradoras"
    ],
    "name:mkd_x_preferred":[
        "\u0415\u043b \u041c\u0438\u0440\u0430\u0434\u043e\u0440"
    ],
    "name:nds_x_preferred":[
        "El Mirador"
    ],
    "name:nor_x_preferred":[
        "El Mirador"
    ],
    "name:pol_x_preferred":[
        "El Mirador"
    ],
    "name:por_x_preferred":[
        "El Mirador"
    ],
    "name:rus_x_preferred":[
        "\u042d\u043b\u044c-\u041c\u0438\u0440\u0430\u0434\u043e\u0440"
    ],
    "name:spa_x_preferred":[
        "El Mirador"
    ],
    "name:ukr_x_preferred":[
        "\u0415\u043b\u044c-\u041c\u0456\u0440\u0430\u0434\u043e\u0440"
    ],
    "wof:name":"El Mirador",
    "wof:placetype":"locality",
    "wof:population":6
},
  "geometry": {"coordinates":[-97.35389000000001,18.06528],"type":"Point"}
}