{
  "type": "Feature",
  "properties": {
    "gn:admin1_code":"12",
    "gn:admin2_code":"28",
    "gn:asciiname":"Minas",
    "gn:country_code":"MX",
    "gn:dem":2175,
    "gn:feature_class":"P",
    "gn:feature_code":"PPL",
    "gn:name":"Minas",
    "gn:population":16,
    "gn:timezone":"America/Mexico_City",
    "iso:country":"MX",
    "wof:name":"Minas",
    "wof:placetype":"locality",
    "wof:population":16
},
  "geometry": {"coordinates":[-98.91695,17.48887],"type":"Point"}
}