{
  "type": "Feature",
  "properties": {
    "gn:admin1_code":"28.0",
    "gn:admin2_code":"19.0",
    "gn:asciiname":"Las Galeras",
    "gn:country_code":"MX",
    "gn:dem":190,
    "gn:feature_class":"P",
    "gn:feature_code":"PPL",
    "gn:name":"Las Galeras",
    "gn:population":0,
    "gn:timezone":"America/Monterrey",
    "iso:country":"MX",
    "name:spa_x_preferred":[
        "Las Galeras"
    ],
    "wof:name":"Las Galeras",
    "wof:placetype":"locality"
},
  "geometry": {"coordinates":[-98.85402999999999,23.21773],"type":"Point"}
}