{
  "type": "Feature",
  "properties": {
    "gn:admin1_code":"14",
    "gn:admin2_code":"97.0",
    "gn:asciiname":"Rancho Luisiana",
    "gn:country_code":"MX",
    "gn:dem":1564,
    "gn:feature_class":"P",
    "gn:feature_code":"PPL",
    "gn:name":"Rancho Luisiana",
    "gn:population":7,
    "gn:timezone":"America/Mexico_City",
    "iso:country":"MX",
    "wof:name":"Rancho Luisiana",
    "wof:placetype":"locality",
    "wof:population":7
},
  "geometry": {"coordinates":[-103.56389,20.46361],"type":"Point"}
}