{
  "type": "Feature",
  "properties": {
    "gn:admin1_code":"26",
    "gn:admin2_code":"3.0",
    "gn:asciiname":"Puertas Cuatas",
    "gn:country_code":"MX",
    "gn:dem":217,
    "gn:feature_class":"P",
    "gn:feature_code":"PPL",
    "gn:name":"Puertas Cuatas",
    "gn:population":0,
    "gn:timezone":"America/Hermosillo",
    "iso:country":"MX",
    "name:spa_x_preferred":[
        "Puertas Cuatas"
    ],
    "wof:name":"Puertas Cuatas",
    "wof:placetype":"locality"
},
  "geometry": {"coordinates":[-108.76685000000001,26.72896],"type":"Point"}
}