{
  "type": "Feature",
  "properties": {
    "gn:admin1_code":"20",
    "gn:admin2_code":"71.0",
    "gn:asciiname":"Huatalguito",
    "gn:cc2":"MX",
    "gn:country_code":"MX",
    "gn:dem":442,
    "gn:feature_class":"P",
    "gn:feature_code":"PPL",
    "gn:name":"Huatalguito",
    "gn:population":0,
    "gn:timezone":"America/Mexico_City",
    "iso:country":"MX",
    "name:und_x_variant":[
        "Huotulquito",
        "Huatalguito"
    ],
    "wof:name":"Huatalguito",
    "wof:placetype":"locality"
},
  "geometry": {"coordinates":[-96.38333,15.88333],"type":"Point"}
}