{
  "type": "Feature",
  "properties": {
    "gn:admin1_code":"20",
    "gn:admin2_code":"105",
    "gn:asciiname":"Segunda Seccion",
    "gn:country_code":"MX",
    "gn:dem":2237,
    "gn:feature_class":"P",
    "gn:feature_code":"PPL",
    "gn:name":"Segunda Secci\u00f3n",
    "gn:population":38,
    "gn:timezone":"America/Mexico_City",
    "iso:country":"MX",
    "name:und_x_variant":[
        "Segunda Secci\u00f3n"
    ],
    "wof:name":"Segunda Seccion",
    "wof:placetype":"locality",
    "wof:population":38
},
  "geometry": {"coordinates":[-97.72417,17.53139],"type":"Point"}
}