{
  "type": "Feature",
  "properties": {
    "gn:admin1_code":"24",
    "gn:admin2_code":"36.0",
    "gn:asciiname":"La Raya del Cura",
    "gn:country_code":"MX",
    "gn:dem":337,
    "gn:feature_class":"P",
    "gn:feature_code":"PPL",
    "gn:name":"La Raya del Cura",
    "gn:population":5,
    "gn:timezone":"America/Mexico_City",
    "iso:country":"MX",
    "wof:name":"La Raya del Cura",
    "wof:placetype":"locality",
    "wof:population":5
},
  "geometry": {"coordinates":[-99.30944,21.96306],"type":"Point"}
}