{
  "type": "Feature",
  "properties": {
    "gn:admin1_code":"5",
    "gn:admin2_code":"2.0",
    "gn:asciiname":"Union Buena Vista",
    "gn:country_code":"MX",
    "gn:dem":533,
    "gn:feature_class":"P",
    "gn:feature_code":"PPL",
    "gn:name":"Uni\u00f3n Buena Vista",
    "gn:population":1847,
    "gn:timezone":"America/Mexico_City",
    "iso:country":"MX",
    "name:spa_x_preferred":[
        "Uni\u00f3n Buena Vista"
    ],
    "wof:name":"Union Buena Vista",
    "wof:placetype":"locality",
    "wof:population":1847
},
  "geometry": {"coordinates":[-92.81823,16.48582],"type":"Point"}
}