{
  "type": "Feature",
  "properties": {
    "gn:admin1_code":"6",
    "gn:admin2_code":"46.0",
    "gn:asciiname":"La Fabrica",
    "gn:country_code":"MX",
    "gn:dem":1926,
    "gn:feature_class":"P",
    "gn:feature_code":"PPL",
    "gn:name":"La F\u00e1brica",
    "gn:population":0,
    "gn:timezone":"America/Mazatlan",
    "iso:country":"MX",
    "name:spa_x_preferred":[
        "La F\u00e1brica"
    ],
    "wof:name":"La Fabrica",
    "wof:placetype":"locality"
},
  "geometry": {"coordinates":[-107.86964,26.44717],"type":"Point"}
}