{
  "type": "Feature",
  "properties": {
    "gn:admin1_code":"24",
    "gn:admin2_code":"32",
    "gn:asciiname":"Cueva del Suelo",
    "gn:country_code":"MX",
    "gn:dem":2016,
    "gn:feature_class":"P",
    "gn:feature_code":"PPL",
    "gn:name":"Cueva del Suelo",
    "gn:population":10,
    "gn:timezone":"America/Mexico_City",
    "iso:country":"MX",
    "wof:name":"Cueva del Suelo",
    "wof:placetype":"locality",
    "wof:population":10
},
  "geometry": {"coordinates":[-100.625,21.86583],"type":"Point"}
}