{
  "type": "Feature",
  "properties": {
    "gn:admin1_code":"25.0",
    "gn:admin2_code":"6.0",
    "gn:asciiname":"Higueras de Abuya",
    "gn:country_code":"MX",
    "gn:dem":64,
    "gn:feature_class":"P",
    "gn:feature_code":"PPL",
    "gn:name":"Higueras de Abuya",
    "gn:population":1648,
    "gn:timezone":"America/Mazatlan",
    "iso:country":"MX",
    "name:spa_x_preferred":[
        "Higueras de Abuya"
    ],
    "wof:name":"Higueras de Abuya",
    "wof:placetype":"locality",
    "wof:population":1648
},
  "geometry": {"coordinates":[-107.07089999999999,24.26058],"type":"Point"}
}