{
  "type": "Feature",
  "properties": {
    "gn:admin1_code":"30.0",
    "gn:admin2_code":"175.0",
    "gn:asciiname":"Santa Cruz",
    "gn:country_code":"MX",
    "gn:dem":225,
    "gn:feature_class":"P",
    "gn:feature_code":"PPL",
    "gn:name":"Santa Cruz",
    "gn:population":20,
    "gn:timezone":"America/Mexico_City",
    "iso:country":"MX",
    "name:spa_x_preferred":[
        "Santa Cruz"
    ],
    "wof:name":"Santa Cruz",
    "wof:placetype":"locality",
    "wof:population":20
},
  "geometry": {"coordinates":[-97.54944,20.51583],"type":"Point"}
}