{
  "type": "Feature",
  "properties": {
    "gn:admin1_code":"1.0",
    "gn:admin2_code":"3.0",
    "gn:asciiname":"Arroyo de Soto",
    "gn:country_code":"MX",
    "gn:dem":1559,
    "gn:feature_class":"P",
    "gn:feature_code":"PPL",
    "gn:name":"Arroyo de Soto",
    "gn:population":0,
    "gn:timezone":"America/Mexico_City",
    "iso:country":"MX",
    "wof:name":"Arroyo de Soto",
    "wof:placetype":"locality"
},
  "geometry": {"coordinates":[-102.81222,21.765],"type":"Point"}
}