{
  "type": "Feature",
  "properties": {
    "gn:admin1_code":"14",
    "gn:admin2_code":"124.0",
    "gn:asciiname":"Las Avispas",
    "gn:country_code":"MX",
    "gn:dem":1872,
    "gn:feature_class":"P",
    "gn:feature_code":"PPL",
    "gn:name":"Las Avispas",
    "gn:population":0,
    "gn:timezone":"America/Mexico_City",
    "iso:country":"MX",
    "name:und_x_variant":[
        "Avispas",
        "Las Avispas"
    ],
    "wof:name":"Las Avispas",
    "wof:placetype":"locality"
},
  "geometry": {"coordinates":[-102.89215,20.55901],"type":"Point"}
}