{
  "type": "Feature",
  "properties": {
    "gn:admin1_code":"16",
    "gn:admin2_code":"10",
    "gn:asciiname":"Rincon de Valdes",
    "gn:country_code":"MX",
    "gn:dem":659,
    "gn:feature_class":"P",
    "gn:feature_code":"PPL",
    "gn:name":"Rinc\u00f3n de Vald\u00e9s",
    "gn:population":46,
    "gn:timezone":"America/Mexico_City",
    "iso:country":"MX",
    "name:und_x_variant":[
        "Rinc\u00f3n de Vald\u00e9s"
    ],
    "wof:name":"Rincon de Valdes",
    "wof:placetype":"locality",
    "wof:population":46
},
  "geometry": {"coordinates":[-102.04361,18.26028],"type":"Point"}
}