{
  "type": "Feature",
  "properties": {
    "gn:admin1_code":"30",
    "gn:admin2_code":"8.0",
    "gn:asciiname":"Xicola",
    "gn:country_code":"MX",
    "gn:dem":1703,
    "gn:feature_class":"P",
    "gn:feature_code":"PPL",
    "gn:name":"Xicola",
    "gn:population":440,
    "gn:timezone":"America/Mexico_City",
    "iso:country":"MX",
    "wof:name":"Xicola",
    "wof:placetype":"locality",
    "wof:population":440
},
  "geometry": {"coordinates":[-97.07528000000001,19.1025],"type":"Point"}
}