{
  "type": "Feature",
  "properties": {
    "gn:admin1_code":"25",
    "gn:admin2_code":"18",
    "gn:asciiname":"Campo la 15",
    "gn:country_code":"MX",
    "gn:dem":13,
    "gn:feature_class":"P",
    "gn:feature_code":"PPL",
    "gn:name":"Campo la 15",
    "gn:population":13,
    "gn:timezone":"America/Mazatlan",
    "iso:country":"MX",
    "wof:name":"Campo la 15",
    "wof:placetype":"locality",
    "wof:population":13
},
  "geometry": {"coordinates":[-107.7175,24.74056],"type":"Point"}
}