{
  "type": "Feature",
  "properties": {
    "gn:admin1_code":"16",
    "gn:admin2_code":"29.0",
    "gn:asciiname":"Puerto de Ruedas (El Ancon)",
    "gn:country_code":"MX",
    "gn:dem":187,
    "gn:feature_class":"P",
    "gn:feature_code":"PPL",
    "gn:name":"Puerto de Ruedas (El Anc\u00f3n)",
    "gn:population":147,
    "gn:timezone":"America/Mexico_City",
    "iso:country":"MX",
    "name:und_x_variant":[
        "Puerto de Ruedas (El Anc\u00f3n)"
    ],
    "wof:name":"Puerto de Ruedas (El Ancon)",
    "wof:placetype":"locality",
    "wof:population":147
},
  "geometry": {"coordinates":[-101.86360999999999,18.62917],"type":"Point"}
}