{
  "type": "Feature",
  "properties": {
    "gn:admin1_code":"14",
    "gn:admin2_code":"93",
    "gn:asciiname":"El Cedazo",
    "gn:country_code":"MX",
    "gn:dem":1805,
    "gn:feature_class":"P",
    "gn:feature_code":"PPL",
    "gn:name":"El Cedazo",
    "gn:population":27,
    "gn:timezone":"America/Mexico_City",
    "iso:country":"MX",
    "wof:name":"El Cedazo",
    "wof:placetype":"locality",
    "wof:population":27
},
  "geometry": {"coordinates":[-102.77972,20.75639],"type":"Point"}
}