{
  "type": "Feature",
  "properties": {
    "gn:admin1_code":"12",
    "gn:admin2_code":"48.0",
    "gn:asciiname":"Paso de la Ceiba",
    "gn:country_code":"MX",
    "gn:dem":88,
    "gn:feature_class":"P",
    "gn:feature_code":"PPL",
    "gn:name":"Paso de la Ceiba",
    "gn:population":97,
    "gn:timezone":"America/Mexico_City",
    "iso:country":"MX",
    "wof:name":"Paso de la Ceiba",
    "wof:placetype":"locality",
    "wof:population":97
},
  "geometry": {"coordinates":[-101.1908,17.47559],"type":"Point"}
}