{
  "type": "Feature",
  "properties": {
    "gn:admin1_code":"2.0",
    "gn:admin2_code":"5.0",
    "gn:asciiname":"El Cuervo",
    "gn:country_code":"MX",
    "gn:dem":149,
    "gn:feature_class":"P",
    "gn:feature_code":"PPL",
    "gn:name":"El Cuervo",
    "gn:population":0,
    "gn:timezone":"America/Tijuana",
    "iso:country":"MX",
    "name:spa_x_preferred":[
        "El Cuervo"
    ],
    "wof:name":"El Cuervo",
    "wof:placetype":"locality"
},
  "geometry": {"coordinates":[-116.96333,32.35639],"type":"Point"}
}