{
  "type": "Feature",
  "properties": {
    "gn:admin1_code":"2.0",
    "gn:admin2_code":"1.0",
    "gn:asciiname":"Campo Aleman",
    "gn:country_code":"MX",
    "gn:dem":214,
    "gn:feature_class":"P",
    "gn:feature_code":"PPL",
    "gn:name":"Campo Alem\u00e1n",
    "gn:population":0,
    "gn:timezone":"America/Tijuana",
    "iso:country":"MX",
    "wof:name":"Campo Aleman",
    "wof:placetype":"locality"
},
  "geometry": {"coordinates":[-113.56667,28.06667],"type":"Point"}
}