{
  "type": "Feature",
  "properties": {
    "gn:admin1_code":"3",
    "gn:admin2_code":"3.0",
    "gn:asciiname":"Los Sauces",
    "gn:country_code":"MX",
    "gn:dem":314,
    "gn:feature_class":"P",
    "gn:feature_code":"PPL",
    "gn:name":"Los Sauces",
    "gn:population":0,
    "gn:timezone":"America/Mazatlan",
    "iso:country":"MX",
    "name:eus_x_preferred":[
        "Los Sauces"
    ],
    "name:fra_x_preferred":[
        "Los Sauces"
    ],
    "name:ita_x_preferred":[
        "Los Sauces"
    ],
    "name:kor_x_preferred":[
        "\ub85c\uc2a4\uc0ac\uc6b0\uc138\uc2a4"
    ],
    "name:nld_x_preferred":[
        "Los Sauces"
    ],
    "name:por_x_preferred":[
        "Los Sauces"
    ],
    "name:ron_x_preferred":[
        "Los Sauces"
    ],
    "name:rus_x_preferred":[
        "\u041b\u043e\u0441-\u0421\u0430\u0443\u0441\u0435\u0441"
    ],
    "name:spa_x_preferred":[
        "Los Sauces"
    ],
    "name:zho_x_preferred":[
        "\u6d1b\u65af\u7d39\u585e\u65af"
    ],
    "wof:name":"Los Sauces",
    "wof:placetype":"locality"
},
  "geometry": {"coordinates":[-110.06399,23.32018],"type":"Point"}
}