{
  "type": "Feature",
  "properties": {
    "gn:admin1_code":"17",
    "gn:admin2_code":"12.0",
    "gn:asciiname":"Los Amates",
    "gn:country_code":"MX",
    "gn:dem":894,
    "gn:feature_class":"P",
    "gn:feature_code":"PPL",
    "gn:name":"Los Amates",
    "gn:population":9,
    "gn:timezone":"America/Mexico_City",
    "iso:country":"MX",
    "wof:name":"Los Amates",
    "wof:placetype":"locality",
    "wof:population":9
},
  "geometry": {"coordinates":[-99.26582999999999,18.5675],"type":"Point"}
}