{
  "type": "Feature",
  "properties": {
    "gn:admin1_code":"6",
    "gn:admin2_code":"7.0",
    "gn:asciiname":"Los Pilares",
    "gn:country_code":"MX",
    "gn:dem":1799,
    "gn:feature_class":"P",
    "gn:feature_code":"PPL",
    "gn:name":"Los Pilares",
    "gn:population":0,
    "gn:timezone":"America/Chihuahua",
    "iso:country":"MX",
    "name:und_x_variant":[
        "Pilares",
        "Rancho Pilares",
        "Los Pilares"
    ],
    "wof:name":"Los Pilares",
    "wof:placetype":"locality"
},
  "geometry": {"coordinates":[-106.40797999999999,26.80597],"type":"Point"}
}