{
  "type": "Feature",
  "properties": {
    "gn:admin1_code":"16.0",
    "gn:admin2_code":"96.0",
    "gn:asciiname":"El Arenoso",
    "gn:country_code":"MX",
    "gn:dem":994,
    "gn:feature_class":"P",
    "gn:feature_code":"PPL",
    "gn:name":"El Arenoso",
    "gn:population":0,
    "gn:timezone":"America/Mexico_City",
    "iso:country":"MX",
    "name:spa_x_preferred":[
        "El Arenoso"
    ],
    "wof:name":"El Arenoso",
    "wof:placetype":"locality"
},
  "geometry": {"coordinates":[-102.41663,18.53299],"type":"Point"}
}