{
  "type": "Feature",
  "properties": {
    "gn:admin1_code":"24",
    "gn:admin2_code":"29.0",
    "gn:asciiname":"El Rinconcito",
    "gn:country_code":"MX",
    "gn:dem":123,
    "gn:feature_class":"P",
    "gn:feature_code":"PPL",
    "gn:name":"El Rinconcito",
    "gn:population":6,
    "gn:timezone":"America/Mexico_City",
    "iso:country":"MX",
    "wof:name":"El Rinconcito",
    "wof:placetype":"locality",
    "wof:population":6
},
  "geometry": {"coordinates":[-98.66916999999999,21.25778],"type":"Point"}
}