{
  "type": "Feature",
  "properties": {
    "gn:admin1_code":"5.0",
    "gn:asciiname":"Los Encinos",
    "gn:country_code":"MX",
    "gn:dem":831,
    "gn:feature_class":"P",
    "gn:feature_code":"PPL",
    "gn:name":"Los Encinos",
    "gn:population":0,
    "gn:timezone":"America/Mexico_City",
    "iso:country":"MX",
    "name:spa_x_preferred":[
        "Los Encinos"
    ],
    "wof:name":"Los Encinos",
    "wof:placetype":"locality"
},
  "geometry": {"coordinates":[-93.44372,16.52434],"type":"Point"}
}