{
  "type": "Feature",
  "properties": {
    "gn:admin1_code":"11",
    "gn:admin2_code":"9.0",
    "gn:asciiname":"Rosales",
    "gn:country_code":"MX",
    "gn:dem":1900,
    "gn:feature_class":"P",
    "gn:feature_code":"PPL",
    "gn:name":"Rosales",
    "gn:population":483,
    "gn:timezone":"America/Mexico_City",
    "iso:country":"MX",
    "wof:name":"Rosales",
    "wof:placetype":"locality",
    "wof:population":483
},
  "geometry": {"coordinates":[-100.66139,20.74944],"type":"Point"}
}