{
  "type": "Feature",
  "properties": {
    "gn:admin1_code":"7",
    "gn:admin2_code":"4.0",
    "gn:asciiname":"El Alambre",
    "gn:country_code":"MX",
    "gn:dem":2155,
    "gn:feature_class":"P",
    "gn:feature_code":"PPL",
    "gn:name":"El Alambre",
    "gn:population":0,
    "gn:timezone":"America/Monterrey",
    "iso:country":"MX",
    "name:spa_x_preferred":[
        "El Alambre"
    ],
    "wof:name":"El Alambre",
    "wof:placetype":"locality"
},
  "geometry": {"coordinates":[-100.71142,25.50115],"type":"Point"}
}