{
  "type": "Feature",
  "properties": {
    "gn:admin1_code":"31",
    "gn:admin2_code":"69.0",
    "gn:asciiname":"Usil Chen",
    "gn:country_code":"MX",
    "gn:dem":27,
    "gn:feature_class":"P",
    "gn:feature_code":"PPL",
    "gn:name":"Usil Chen",
    "gn:population":0,
    "gn:timezone":"America/Merida",
    "iso:country":"MX",
    "name:spa_x_preferred":[
        "Usil Chen"
    ],
    "wof:name":"Usil Chen",
    "wof:placetype":"locality"
},
  "geometry": {"coordinates":[-88.93257,20.681],"type":"Point"}
}