{
  "type": "Feature",
  "properties": {
    "gn:admin1_code":"25",
    "gn:admin2_code":"10.0",
    "gn:asciiname":"Bialacahui",
    "gn:country_code":"MX",
    "gn:dem":21,
    "gn:feature_class":"P",
    "gn:feature_code":"PPL",
    "gn:name":"Bialacahui",
    "gn:population":150,
    "gn:timezone":"America/Mazatlan",
    "iso:country":"MX",
    "wof:name":"Bialacahui",
    "wof:placetype":"locality",
    "wof:population":150
},
  "geometry": {"coordinates":[-108.91694,25.95778],"type":"Point"}
}