{
  "type": "Feature",
  "properties": {
    "gn:admin1_code":"16",
    "gn:admin2_code":"108.0",
    "gn:asciiname":"El Coyote Grande",
    "gn:country_code":"MX",
    "gn:dem":1563,
    "gn:feature_class":"P",
    "gn:feature_code":"PPL",
    "gn:name":"El Coyote Grande",
    "gn:population":7,
    "gn:timezone":"America/Mexico_City",
    "iso:country":"MX",
    "wof:name":"El Coyote Grande",
    "wof:placetype":"locality",
    "wof:population":7
},
  "geometry": {"coordinates":[-102.33,19.99444],"type":"Point"}
}