{
  "type": "Feature",
  "properties": {
    "gn:admin1_code":"21.0",
    "gn:admin2_code":"128.0",
    "gn:asciiname":"Rancho de la Rosa",
    "gn:country_code":"MX",
    "gn:dem":2401,
    "gn:feature_class":"P",
    "gn:feature_code":"PPL",
    "gn:name":"Rancho de la Rosa",
    "gn:population":0,
    "gn:timezone":"America/Mexico_City",
    "iso:country":"MX",
    "name:spa_x_preferred":[
        "Rancho de la Rosa"
    ],
    "name:spa_x_variant":[
        "Coyahualulco"
    ],
    "wof:name":"Rancho de la Rosa",
    "wof:placetype":"locality"
},
  "geometry": {"coordinates":[-97.74782,19.28786],"type":"Point"}
}