{
  "type": "Feature",
  "properties": {
    "gn:admin1_code":"26",
    "gn:admin2_code":"42.0",
    "gn:asciiname":"Los Bahuises",
    "gn:country_code":"MX",
    "gn:dem":41,
    "gn:feature_class":"P",
    "gn:feature_code":"PPL",
    "gn:name":"Los Bahuises",
    "gn:population":1303,
    "gn:timezone":"America/Hermosillo",
    "iso:country":"MX",
    "wof:name":"Los Bahuises",
    "wof:placetype":"locality",
    "wof:population":1303
},
  "geometry": {"coordinates":[-109.46722,27.11667000000001],"type":"Point"}
}