{
  "type": "Feature",
  "properties": {
    "gn:admin1_code":"21",
    "gn:asciiname":"Contla",
    "gn:country_code":"MX",
    "gn:dem":1033,
    "gn:feature_class":"P",
    "gn:feature_code":"PPL",
    "gn:name":"Contla",
    "gn:population":0,
    "gn:timezone":"America/Mexico_City",
    "iso:country":"MX",
    "name:spa_x_preferred":[
        "Contla"
    ],
    "name:spa_x_variant":[
        "Guadalupe"
    ],
    "wof:name":"Contla",
    "wof:placetype":"locality"
},
  "geometry": {"coordinates":[-98.8126,18.51758],"type":"Point"}
}