{
  "type": "Feature",
  "properties": {
    "gn:admin1_code":"15.0",
    "gn:asciiname":"Jacal del Gato",
    "gn:country_code":"MX",
    "gn:dem":1565,
    "gn:feature_class":"P",
    "gn:feature_code":"PPL",
    "gn:name":"Jacal del Gato",
    "gn:population":0,
    "gn:timezone":"America/Mexico_City",
    "iso:country":"MX",
    "name:spa_x_preferred":[
        "Jacal del Gato"
    ],
    "wof:name":"Jacal del Gato",
    "wof:placetype":"locality"
},
  "geometry": {"coordinates":[-102.32791,19.97099],"type":"Point"}
}