{
  "type": "Feature",
  "properties": {
    "gn:admin1_code":"14",
    "gn:asciiname":"Carrizo Colorado",
    "gn:country_code":"MX",
    "gn:dem":2373,
    "gn:feature_class":"P",
    "gn:feature_code":"PPL",
    "gn:name":"Carrizo Colorado",
    "gn:population":0,
    "gn:timezone":"America/Mexico_City",
    "iso:country":"MX",
    "wof:name":"Carrizo Colorado",
    "wof:placetype":"locality"
},
  "geometry": {"coordinates":[-103.83333,21.28333],"type":"Point"}
}