{
  "type": "Feature",
  "properties": {
    "iso:country":"MX",
    "name:bel_x_preferred":[
        "\u0413\u043e\u0440\u0430\u0434 \u0413\u0443\u0430\u043d\u0442\u0430\u043d\u0430\u043c\u0430"
    ],
    "name:bel_x_variant":[
        "\u0413\u0443\u0430\u043d\u0442\u0430\u043d\u0430\u043c\u0430"
    ],
    "name:bre_x_preferred":[
        "Guant\u00e1namo"
    ],
    "name:bul_x_preferred":[
        "\u0413\u0443\u0430\u043d\u0442\u0430\u043d\u0430\u043c\u043e"
    ],
    "name:cat_x_preferred":[
        "Guant\u00e1namo"
    ],
    "name:ceb_x_preferred":[
        "Guant\u00e1namo"
    ],
    "name:ces_x_preferred":[
        "Guant\u00e1namo"
    ],
    "name:dan_x_preferred":[
        "Guantanamo"
    ],
    "name:deu_x_preferred":[
        "Guant\u00e1namo"
    ],
    "name:ell_x_preferred":[
        "\u0393\u03ba\u03bf\u03c5\u03b1\u03bd\u03c4\u03ac\u03bd\u03b1\u03bc\u03bf"
    ],
    "name:spa_x_preferred":[
        "Isleta Perez"
    ],
    "name:und_x_variant":[
        "La Isleta"
    ],
    "wof:lang":[
        "spa"
    ],
    "wof:name":"Isleta Perez",
    "wof:placetype":"neighbourhood"
},
  "geometry": {"coordinates":[-97.840445,22.21223],"type":"Point"}
}