{
  "type": "Feature",
  "properties": {
    "gn:admin1_code":"31",
    "gn:asciiname":"Nohalal",
    "gn:country_code":"MX",
    "gn:dem":74,
    "gn:feature_class":"P",
    "gn:feature_code":"PPL",
    "gn:name":"Nohalal",
    "gn:population":0,
    "gn:timezone":"America/Merida",
    "iso:country":"MX",
    "name:spa_x_preferred":[
        "Nohalal"
    ],
    "wof:name":"Nohalal",
    "wof:placetype":"locality"
},
  "geometry": {"coordinates":[-89.33275999999999,19.7931],"type":"Point"}
}