{
  "type": "Feature",
  "properties": {
    "gn:admin1_code":"8",
    "gn:admin2_code":"10.0",
    "gn:asciiname":"Rodolfo Salazar Carrillo",
    "gn:country_code":"MX",
    "gn:dem":472,
    "gn:feature_class":"P",
    "gn:feature_code":"PPL",
    "gn:name":"Rodolfo Salazar Carrillo",
    "gn:population":6,
    "gn:timezone":"America/Mexico_City",
    "iso:country":"MX",
    "wof:name":"Rodolfo Salazar Carrillo",
    "wof:placetype":"locality",
    "wof:population":6
},
  "geometry": {"coordinates":[-103.79194,19.27],"type":"Point"}
}