{
  "type": "Feature",
  "properties": {
    "gn:admin1_code":"14",
    "gn:admin2_code":"107.0",
    "gn:asciiname":"Las Cebollas",
    "gn:country_code":"MX",
    "gn:dem":1979,
    "gn:feature_class":"P",
    "gn:feature_code":"PPL",
    "gn:name":"Las Cebollas",
    "gn:population":0,
    "gn:timezone":"America/Mexico_City",
    "iso:country":"MX",
    "wof:name":"Las Cebollas",
    "wof:placetype":"locality"
},
  "geometry": {"coordinates":[-103.17628999999999,20.09457],"type":"Point"}
}