{
  "type": "Feature",
  "properties": {
    "iso:country":"MX",
    "qs_pg:aaroncc":"MX",
    "qs_pg:name":"Priv Del Maestro",
    "qs_pg:name_adm0":"M\u00e9xico",
    "qs_pg:name_adm1":"Yucatan",
    "qs_pg:photos":76,
    "qs_pg:photos_1k":15,
    "qs_pg:photos_9k":1,
    "qs_pg:photos_9r":3,
    "qs_pg:photos_all":76,
    "qs_pg:photos_sr":3,
    "qs_pg:pop_sr":0,
    "qs_pg:qs_pg_placetype":"neighbourhood",
    "qs_pg:qs_pg_placetype_gp":"Suburb",
    "qs_pg:woe_adm0":23424900,
    "woe:adm0_id":23424900,
    "woe:name_adm0":"M\u00e9xico",
    "woe:name_adm1":"Yucatan",
    "woe:placetype":"Suburb",
    "wof:name":"Priv Del Maestro",
    "wof:placetype":"neighbourhood"
},
  "geometry": {"coordinates":[-89.6217115,20.976459],"type":"Point"}
}