{
  "type": "Feature",
  "properties": {
    "gn:admin1_code":"19",
    "gn:admin2_code":"20.0",
    "gn:asciiname":"Retamitas",
    "gn:country_code":"MX",
    "gn:dem":87,
    "gn:feature_class":"P",
    "gn:feature_code":"PPL",
    "gn:name":"Retamitas",
    "gn:population":0,
    "gn:timezone":"America/Monterrey",
    "iso:country":"MX",
    "name:spa_x_preferred":[
        "Retamitas"
    ],
    "wof:name":"Retamitas",
    "wof:placetype":"locality"
},
  "geometry": {"coordinates":[-98.72324999999999,26.03269],"type":"Point"}
}