{
  "type": "Feature",
  "properties": {
    "gn:admin1_code":"11",
    "gn:admin2_code":"40.0",
    "gn:asciiname":"La Cuchilla Blanca",
    "gn:country_code":"MX",
    "gn:dem":2472,
    "gn:feature_class":"P",
    "gn:feature_code":"PPL",
    "gn:name":"La Cuchilla Blanca",
    "gn:population":8,
    "gn:timezone":"America/Mexico_City",
    "iso:country":"MX",
    "wof:name":"La Cuchilla Blanca",
    "wof:placetype":"locality",
    "wof:population":8
},
  "geometry": {"coordinates":[-100.12083,20.95611],"type":"Point"}
}