{
  "type": "Feature",
  "properties": {
    "gn:admin1_code":"15",
    "gn:admin2_code":"93.0",
    "gn:asciiname":"La Venta (La Loma)",
    "gn:country_code":"MX",
    "gn:dem":2594,
    "gn:feature_class":"P",
    "gn:feature_code":"PPL",
    "gn:name":"La Venta (La Loma)",
    "gn:population":135,
    "gn:timezone":"America/Mexico_City",
    "iso:country":"MX",
    "wof:name":"La Venta (La Loma)",
    "wof:placetype":"locality",
    "wof:population":135
},
  "geometry": {"coordinates":[-98.76804,19.54927],"type":"Point"}
}