{
  "type": "Feature",
  "properties": {
    "gn:admin1_code":"16",
    "gn:admin2_code":"41.0",
    "gn:asciiname":"Balvaneda",
    "gn:country_code":"MX",
    "gn:dem":2149,
    "gn:feature_class":"P",
    "gn:feature_code":"PPL",
    "gn:name":"Balvaneda",
    "gn:population":148,
    "gn:timezone":"America/Mexico_City",
    "iso:country":"MX",
    "wof:name":"Balvaneda",
    "wof:placetype":"locality",
    "wof:population":148
},
  "geometry": {"coordinates":[-100.44833,19.745],"type":"Point"}
}