{
  "type": "Feature",
  "properties": {
    "gn:admin1_code":"15",
    "gn:admin2_code":"3.0",
    "gn:asciiname":"Fondo",
    "gn:country_code":"MX",
    "gn:dem":2623,
    "gn:feature_class":"P",
    "gn:feature_code":"PPL",
    "gn:name":"Fondo",
    "gn:population":0,
    "gn:timezone":"America/Mexico_City",
    "iso:country":"MX",
    "name:spa_x_preferred":[
        "Fondo"
    ],
    "wof:name":"Fondo",
    "wof:placetype":"locality"
},
  "geometry": {"coordinates":[-99.76578000000001,20.05953],"type":"Point"}
}