{
  "type": "Feature",
  "properties": {
    "gn:admin1_code":"26",
    "gn:admin2_code":"55",
    "gn:asciiname":"Familia Monroy",
    "gn:country_code":"MX",
    "gn:dem":21,
    "gn:feature_class":"P",
    "gn:feature_code":"PPL",
    "gn:name":"Familia Monroy",
    "gn:population":12,
    "gn:timezone":"America/Hermosillo",
    "iso:country":"MX",
    "wof:name":"Familia Monroy",
    "wof:placetype":"locality",
    "wof:population":12
},
  "geometry": {"coordinates":[-114.90555999999999,32.37306],"type":"Point"}
}