{
  "type": "Feature",
  "properties": {
    "gn:admin1_code":"20",
    "gn:admin2_code":"30.0",
    "gn:asciiname":"Ingenio Juchitan (Jose Lopez Portillo)",
    "gn:country_code":"MX",
    "gn:dem":30,
    "gn:feature_class":"P",
    "gn:feature_code":"PPL",
    "gn:name":"Ingenio Juchit\u00e1n (Jos\u00e9 L\u00f3pez Portillo)",
    "gn:population":236,
    "gn:timezone":"America/Mexico_City",
    "iso:country":"MX",
    "name:und_x_variant":[
        "Ingenio Juchit\u00e1n (Jos\u00e9 L\u00f3pez Portillo)"
    ],
    "wof:name":"Ingenio Juchitan (Jose Lopez Portillo)",
    "wof:placetype":"locality",
    "wof:population":236
},
  "geometry": {"coordinates":[-95.03,16.47556],"type":"Point"}
}