{
  "type": "Feature",
  "properties": {
    "gn:admin1_code":"18.0",
    "gn:admin2_code":"15.0",
    "gn:asciiname":"Palmar de Cuautla",
    "gn:cc2":"MX",
    "gn:country_code":"MX",
    "gn:dem":4,
    "gn:feature_class":"P",
    "gn:feature_code":"PPL",
    "gn:name":"Palmar de Cuautla",
    "gn:population":1359,
    "gn:timezone":"America/Mazatlan",
    "iso:country":"MX",
    "name:und_x_variant":[
        "Cuantla",
        "Cuautla"
    ],
    "wof:name":"Palmar de Cuautla",
    "wof:placetype":"locality",
    "wof:population":1359
},
  "geometry": {"coordinates":[-105.64749999999999,22.21972],"type":"Point"}
}