{
  "type": "Feature",
  "properties": {
    "gn:admin1_code":"32.0",
    "gn:admin2_code":"55.0",
    "gn:asciiname":"La Mesa de los Patos",
    "gn:country_code":"MX",
    "gn:dem":1813,
    "gn:feature_class":"P",
    "gn:feature_code":"PPL",
    "gn:name":"La Mesa de los Patos",
    "gn:population":0,
    "gn:timezone":"America/Mexico_City",
    "iso:country":"MX",
    "name:spa_x_preferred":[
        "La Mesa de los Patos"
    ],
    "wof:name":"La Mesa de los Patos",
    "wof:placetype":"locality"
},
  "geometry": {"coordinates":[-102.86529,22.15571],"type":"Point"}
}