{
  "type": "Feature",
  "properties": {
    "gn:admin1_code":"30",
    "gn:admin2_code":"84.0",
    "gn:asciiname":"Los Amates",
    "gn:country_code":"MX",
    "gn:dem":10,
    "gn:feature_class":"P",
    "gn:feature_code":"PPL",
    "gn:name":"Los Amates",
    "gn:population":0,
    "gn:timezone":"America/Mexico_City",
    "iso:country":"MX",
    "name:und_x_variant":[
        "Amates",
        "Los Amates"
    ],
    "wof:name":"Los Amates",
    "wof:placetype":"locality"
},
  "geometry": {"coordinates":[-95.88208,18.37923],"type":"Point"}
}