{
  "type": "Feature",
  "properties": {
    "gn:admin1_code":"30",
    "gn:admin2_code":"122.0",
    "gn:asciiname":"Jicacal",
    "gn:country_code":"MX",
    "gn:dem":12,
    "gn:feature_class":"P",
    "gn:feature_code":"PPL",
    "gn:name":"Jicacal",
    "gn:population":951,
    "gn:timezone":"America/Mexico_City",
    "iso:country":"MX",
    "name:spa_x_preferred":[
        "Jicacal"
    ],
    "wof:name":"Jicacal",
    "wof:placetype":"locality",
    "wof:population":951
},
  "geometry": {"coordinates":[-94.61251,18.21413],"type":"Point"}
}