{
  "type": "Feature",
  "properties": {
    "gn:admin1_code":"11",
    "gn:admin2_code":"44",
    "gn:asciiname":"Manuel Aguilar (Caja de Campos)",
    "gn:country_code":"MX",
    "gn:dem":1737,
    "gn:feature_class":"P",
    "gn:feature_code":"PPL",
    "gn:name":"Manuel Aguilar (Caja de Campos)",
    "gn:population":9,
    "gn:timezone":"America/Mexico_City",
    "iso:country":"MX",
    "wof:name":"Manuel Aguilar (Caja de Campos)",
    "wof:placetype":"locality",
    "wof:population":9
},
  "geometry": {"coordinates":[-100.98111,20.52778],"type":"Point"}
}