{
  "type": "Feature",
  "properties": {
    "gn:admin1_code":"18.0",
    "gn:admin2_code":"4.0",
    "gn:asciiname":"El Limbo",
    "gn:country_code":"MX",
    "gn:dem":901,
    "gn:feature_class":"P",
    "gn:feature_code":"PPL",
    "gn:name":"El Limbo",
    "gn:population":0,
    "gn:timezone":"America/Mazatlan",
    "iso:country":"MX",
    "wof:name":"El Limbo",
    "wof:placetype":"locality"
},
  "geometry": {"coordinates":[-104.87917,21.25833],"type":"Point"}
}