{
  "type": "Feature",
  "properties": {
    "gn:admin1_code":"30",
    "gn:admin2_code":"125.0",
    "gn:asciiname":"Paso Gavilan",
    "gn:country_code":"MX",
    "gn:dem":355,
    "gn:feature_class":"P",
    "gn:feature_code":"PPL",
    "gn:name":"Paso Gavil\u00e1n",
    "gn:population":0,
    "gn:timezone":"America/Mexico_City",
    "iso:country":"MX",
    "name:spa_x_preferred":[
        "Paso Gavil\u00e1n"
    ],
    "wof:name":"Paso Gavilan",
    "wof:placetype":"locality"
},
  "geometry": {"coordinates":[-96.62461,18.98218],"type":"Point"}
}