{
  "type": "Feature",
  "properties": {
    "gn:admin1_code":"24",
    "gn:admin2_code":"29.0",
    "gn:asciiname":"El Higuito",
    "gn:country_code":"MX",
    "gn:dem":139,
    "gn:feature_class":"P",
    "gn:feature_code":"PPL",
    "gn:name":"El Higuito",
    "gn:population":248,
    "gn:timezone":"America/Mexico_City",
    "iso:country":"MX",
    "wof:name":"El Higuito",
    "wof:placetype":"locality",
    "wof:population":248
},
  "geometry": {"coordinates":[-98.56806,21.45583],"type":"Point"}
}