{
  "type": "Feature",
  "properties": {
    "gn:admin1_code":"28",
    "gn:admin2_code":"28.0",
    "gn:asciiname":"San Vicente",
    "gn:country_code":"MX",
    "gn:dem":292,
    "gn:feature_class":"P",
    "gn:feature_code":"PPL",
    "gn:name":"San Vicente",
    "gn:population":0,
    "gn:timezone":"America/Monterrey",
    "iso:country":"MX",
    "name:bel_x_preferred":[
        "\u0421\u0430\u043d-\u0412\u0456\u0441\u0435\u043d\u0442\u044d"
    ],
    "name:bre_x_preferred":[
        "San Vicente"
    ],
    "name:cat_x_preferred":[
        "San Vicente"
    ],
    "name:ceb_x_preferred":[
        "San Vicente"
    ],
    "name:deu_x_preferred":[
        "San Vicente"
    ],
    "name:eus_x_preferred":[
        "San Vicente"
    ],
    "name:fas_x_preferred":[
        "\u0633\u0627\u0646 \u0648\u06cc\u0633\u0646\u062a\u0647"
    ],
    "name:fra_x_preferred":[
        "San Vicente"
    ],
    "name:glg_x_preferred":[
        "San Vicente"
    ],
    "name:heb_x_preferred":[
        "\u05e1\u05df \u05d5\u05d9\u05e1\u05e0\u05d8\u05d4"
    ],
    "name:hun_x_preferred":[
        "San Vicente"
    ],
    "name:ilo_x_preferred":[
        "San Vicente"
    ],
    "name:ita_x_preferred":[
        "San Vicente"
    ],
    "name:kor_x_preferred":[
        "\uc0b0\ube44\uc13c\ud14c"
    ],
    "name:lit_x_preferred":[
        "San Visent\u0117"
    ],
    "name:nah_x_preferred":[
        "San Vicente"
    ],
    "name:nds_x_preferred":[
        "San Vicente"
    ],
    "name:nld_x_preferred":[
        "San Vicente"
    ],
    "name:pol_x_preferred":[
        "San Vicente"
    ],
    "name:por_x_preferred":[
        "San Vicente"
    ],
    "name:ron_x_preferred":[
        "San Vicente"
    ],
    "name:rus_x_preferred":[
        "\u0421\u0430\u043d-\u0412\u0438\u0441\u0435\u043d\u0442\u0435"
    ],
    "name:sco_x_preferred":[
        "San Vicente"
    ],
    "name:slk_x_preferred":[
        "San Vicente"
    ],
    "name:spa_x_preferred":[
        "San Vicente"
    ],
    "name:swe_x_preferred":[
        "San Vicente"
    ],
    "name:ukr_x_preferred":[
        "\u0421\u0430\u043d-\u0412\u0456\u0441\u0435\u043d\u0442\u0435"
    ],
    "name:war_x_preferred":[
        "San Vicente"
    ],
    "wof:name":"San Vicente",
    "wof:placetype":"locality"
},
  "geometry": {"coordinates":[-99.25418000000001,22.574],"type":"Point"}
}