{
  "type": "Feature",
  "properties": {
    "gn:admin1_code":"19",
    "gn:admin2_code":"32.0",
    "gn:asciiname":"Rancho Palo Blanco",
    "gn:country_code":"MX",
    "gn:dem":284,
    "gn:feature_class":"P",
    "gn:feature_code":"PPL",
    "gn:name":"Rancho Palo Blanco",
    "gn:population":0,
    "gn:timezone":"America/Monterrey",
    "iso:country":"MX",
    "wof:name":"Rancho Palo Blanco",
    "wof:placetype":"locality"
},
  "geometry": {"coordinates":[-100.28333000000001,26.98333],"type":"Point"}
}