{
  "type": "Feature",
  "properties": {
    "gn:admin1_code":"16",
    "gn:admin2_code":"49",
    "gn:asciiname":"La Joya de los Nogales",
    "gn:country_code":"MX",
    "gn:dem":1272,
    "gn:feature_class":"P",
    "gn:feature_code":"PPL",
    "gn:name":"La Joya de los Nogales",
    "gn:population":13,
    "gn:timezone":"America/Mexico_City",
    "iso:country":"MX",
    "wof:name":"La Joya de los Nogales",
    "wof:placetype":"locality",
    "wof:population":13
},
  "geometry": {"coordinates":[-101.13722,19.37556],"type":"Point"}
}