{
  "type": "Feature",
  "properties": {
    "gn:admin1_code":"21.0",
    "gn:asciiname":"El Tetenco",
    "gn:country_code":"MX",
    "gn:dem":2226,
    "gn:feature_class":"P",
    "gn:feature_code":"PPL",
    "gn:name":"El Tetenco",
    "gn:population":0,
    "gn:timezone":"America/Mexico_City",
    "iso:country":"MX",
    "name:spa_x_preferred":[
        "El Tetenco"
    ],
    "wof:name":"El Tetenco",
    "wof:placetype":"locality"
},
  "geometry": {"coordinates":[-98.43326999999999,19.04294],"type":"Point"}
}