{
  "type": "Feature",
  "properties": {
    "gn:admin1_code":"11.0",
    "gn:asciiname":"Puerto del Gallo",
    "gn:country_code":"MX",
    "gn:dem":2252,
    "gn:feature_class":"P",
    "gn:feature_code":"PPL",
    "gn:name":"Puerto del Gallo",
    "gn:population":0,
    "gn:timezone":"America/Mexico_City",
    "iso:country":"MX",
    "name:spa_x_preferred":[
        "Puerto del Gallo"
    ],
    "wof:name":"Puerto del Gallo",
    "wof:placetype":"locality"
},
  "geometry": {"coordinates":[-101.78792,20.48885],"type":"Point"}
}