{
  "type": "Feature",
  "properties": {
    "gn:admin1_code":"30",
    "gn:admin2_code":"121.0",
    "gn:asciiname":"El Coyolar (Isla Juan A. Ramirez)",
    "gn:country_code":"MX",
    "gn:dem":5,
    "gn:feature_class":"P",
    "gn:feature_code":"PPL",
    "gn:name":"El Coyolar (Isla Juan A. Ram\u00edrez)",
    "gn:population":6,
    "gn:timezone":"America/Mexico_City",
    "iso:country":"MX",
    "name:und_x_variant":[
        "El Coyolar (Isla Juan A. Ram\u00edrez)"
    ],
    "wof:name":"El Coyolar (Isla Juan A. Ramirez)",
    "wof:placetype":"locality",
    "wof:population":6
},
  "geometry": {"coordinates":[-97.69417,21.86306],"type":"Point"}
}