{
  "type": "Feature",
  "properties": {
    "gn:admin1_code":"28.0",
    "gn:admin2_code":"29.0",
    "gn:asciiname":"El Parque",
    "gn:country_code":"MX",
    "gn:dem":1048,
    "gn:feature_class":"P",
    "gn:feature_code":"PPL",
    "gn:name":"El Parque",
    "gn:population":0,
    "gn:timezone":"America/Monterrey",
    "iso:country":"MX",
    "name:spa_x_preferred":[
        "El Parque"
    ],
    "wof:name":"El Parque",
    "wof:placetype":"locality"
},
  "geometry": {"coordinates":[-99.30942,22.96778],"type":"Point"}
}