{
  "type": "Feature",
  "properties": {
    "gn:admin1_code":"30",
    "gn:admin2_code":"21",
    "gn:asciiname":"El Aguaje",
    "gn:country_code":"MX",
    "gn:dem":1219,
    "gn:feature_class":"P",
    "gn:feature_code":"PPL",
    "gn:name":"El Aguaje",
    "gn:population":37,
    "gn:timezone":"America/Mexico_City",
    "iso:country":"MX",
    "wof:name":"El Aguaje",
    "wof:placetype":"locality",
    "wof:population":37
},
  "geometry": {"coordinates":[-96.84305999999999,18.98722],"type":"Point"}
}