{
  "type": "Feature",
  "properties": {
    "gn:admin1_code":"12",
    "gn:admin2_code":"59",
    "gn:asciiname":"Kari y Elenita",
    "gn:country_code":"MX",
    "gn:dem":710,
    "gn:feature_class":"P",
    "gn:feature_code":"PPL",
    "gn:name":"Kari y Elenita",
    "gn:population":12,
    "gn:timezone":"America/Mexico_City",
    "iso:country":"MX",
    "wof:name":"Kari y Elenita",
    "wof:placetype":"locality",
    "wof:population":12
},
  "geometry": {"coordinates":[-99.55726,18.123],"type":"Point"}
}