{
  "type": "Feature",
  "properties": {
    "gn:admin1_code":"19",
    "gn:admin2_code":"14",
    "gn:asciiname":"La Minita",
    "gn:country_code":"MX",
    "gn:dem":1848,
    "gn:feature_class":"P",
    "gn:feature_code":"PPL",
    "gn:name":"La Minita",
    "gn:population":12,
    "gn:timezone":"America/Monterrey",
    "iso:country":"MX",
    "wof:name":"La Minita",
    "wof:placetype":"locality",
    "wof:population":12
},
  "geometry": {"coordinates":[-100.25355,23.69952],"type":"Point"}
}