{
  "type": "Feature",
  "properties": {
    "gn:admin1_code":"16.0",
    "gn:admin2_code":"99.0",
    "gn:asciiname":"Las Juntas del Rodeo",
    "gn:country_code":"MX",
    "gn:dem":535,
    "gn:feature_class":"P",
    "gn:feature_code":"PPL",
    "gn:name":"Las Juntas del Rodeo",
    "gn:population":0,
    "gn:timezone":"America/Mexico_City",
    "iso:country":"MX",
    "name:spa_x_preferred":[
        "Las Juntas del Rodeo"
    ],
    "wof:name":"Las Juntas del Rodeo",
    "wof:placetype":"locality"
},
  "geometry": {"coordinates":[-100.65857,19.16506],"type":"Point"}
}