{
  "type": "Feature",
  "properties": {
    "gn:admin1_code":"24",
    "gn:admin2_code":"54.0",
    "gn:asciiname":"Puerto de Belen",
    "gn:country_code":"MX",
    "gn:dem":782,
    "gn:feature_class":"P",
    "gn:feature_code":"PPL",
    "gn:name":"Puerto de Bel\u00e9n",
    "gn:population":310,
    "gn:timezone":"America/Mexico_City",
    "iso:country":"MX",
    "name:und_x_variant":[
        "Puerto de Bel\u00e9n"
    ],
    "wof:name":"Puerto de Belen",
    "wof:placetype":"locality",
    "wof:population":310
},
  "geometry": {"coordinates":[-98.95806,21.38056],"type":"Point"}
}