{
  "type": "Feature",
  "properties": {
    "gn:admin1_code":"20",
    "gn:admin2_code":"123",
    "gn:asciiname":"La Loma Grande",
    "gn:country_code":"MX",
    "gn:dem":1778,
    "gn:feature_class":"P",
    "gn:feature_code":"PPL",
    "gn:name":"La Loma Grande",
    "gn:population":11,
    "gn:timezone":"America/Mexico_City",
    "iso:country":"MX",
    "wof:name":"La Loma Grande",
    "wof:placetype":"locality",
    "wof:population":11
},
  "geometry": {"coordinates":[-96.90472,16.83472],"type":"Point"}
}