{
  "type": "Feature",
  "properties": {
    "gn:admin1_code":"31",
    "gn:admin2_code":"102",
    "gn:asciiname":"San Pedro Sula",
    "gn:country_code":"MX",
    "gn:dem":24,
    "gn:feature_class":"P",
    "gn:feature_code":"PPL",
    "gn:name":"San Pedro Sula",
    "gn:population":31,
    "gn:timezone":"America/Merida",
    "iso:country":"MX",
    "wof:name":"San Pedro Sula",
    "wof:placetype":"locality",
    "wof:population":31
},
  "geometry": {"coordinates":[-88.08667,20.70889],"type":"Point"}
}