{
  "type": "Feature",
  "properties": {
    "gn:admin1_code":"12",
    "gn:asciiname":"Corvillo",
    "gn:country_code":"MX",
    "gn:dem":-9999,
    "gn:feature_class":"P",
    "gn:feature_code":"PPL",
    "gn:name":"Corvillo",
    "gn:population":0,
    "gn:timezone":"America/Mazatlan",
    "iso:country":"MX",
    "wof:name":"Corvillo",
    "wof:placetype":"locality"
},
  "geometry": {"coordinates":[-99.93333,16.73333],"type":"Point"}
}