{
  "type": "Feature",
  "properties": {
    "gn:admin1_code":"12",
    "gn:admin2_code":"52.0",
    "gn:asciiname":"Nejapa",
    "gn:country_code":"MX",
    "gn:dem":291,
    "gn:feature_class":"P",
    "gn:feature_code":"PPL",
    "gn:name":"Nejapa",
    "gn:population":115,
    "gn:timezone":"America/Mexico_City",
    "iso:country":"MX",
    "name:ceb_x_preferred":[
        "Nejapa"
    ],
    "name:deu_x_preferred":[
        "Nejapa"
    ],
    "name:fra_x_preferred":[
        "Nejapa"
    ],
    "name:ita_x_preferred":[
        "Nejapa"
    ],
    "name:pol_x_preferred":[
        "Nejapa"
    ],
    "name:por_x_preferred":[
        "Nejapa"
    ],
    "name:spa_x_preferred":[
        "Nejapa"
    ],
    "name:urd_x_preferred":[
        "\u0646\u06cc\u062e\u0627\u067e\u0627"
    ],
    "name:zho_x_preferred":[
        "\u5167\u54c8\u5e15"
    ],
    "wof:name":"Nejapa",
    "wof:placetype":"locality",
    "wof:population":115
},
  "geometry": {"coordinates":[-98.70665,16.84474],"type":"Point"}
}