{
  "type": "Feature",
  "properties": {
    "gn:admin1_code":"14.0",
    "gn:admin2_code":"119.0",
    "gn:asciiname":"Barranca de Santa Clara",
    "gn:country_code":"MX",
    "gn:dem":1486,
    "gn:feature_class":"P",
    "gn:feature_code":"PPL",
    "gn:name":"Barranca de Santa Clara",
    "gn:population":957,
    "gn:timezone":"America/Mexico_City",
    "iso:country":"MX",
    "name:und_x_variant":[
        "Santa Clara",
        "Barranca de Santa Clara"
    ],
    "wof:name":"Barranca de Santa Clara",
    "wof:placetype":"locality",
    "wof:population":957
},
  "geometry": {"coordinates":[-103.65560000000001,20.25566],"type":"Point"}
}