{
  "type": "Feature",
  "properties": {
    "gn:admin1_code":"14",
    "gn:admin2_code":"124",
    "gn:asciiname":"El Campamento (Loma del Campamento)",
    "gn:country_code":"MX",
    "gn:dem":1628,
    "gn:feature_class":"P",
    "gn:feature_code":"PPL",
    "gn:name":"El Campamento (Loma del Campamento)",
    "gn:population":31,
    "gn:timezone":"America/Mexico_City",
    "iso:country":"MX",
    "wof:name":"El Campamento (Loma del Campamento)",
    "wof:placetype":"locality",
    "wof:population":31
},
  "geometry": {"coordinates":[-103.03471999999999,20.6625],"type":"Point"}
}