{
  "type": "Feature",
  "properties": {
    "gn:admin1_code":"20.0",
    "gn:admin2_code":"208.0",
    "gn:asciiname":"San Miguel Lado",
    "gn:country_code":"MX",
    "gn:dem":1746,
    "gn:feature_class":"P",
    "gn:feature_code":"PPL",
    "gn:name":"San Miguel Lado",
    "gn:population":0,
    "gn:timezone":"America/Mexico_City",
    "iso:country":"MX",
    "name:spa_x_preferred":[
        "San Miguel Lado"
    ],
    "wof:name":"San Miguel Lado",
    "wof:placetype":"locality"
},
  "geometry": {"coordinates":[-97.82447000000001,17.30693],"type":"Point"}
}