{
  "type": "Feature",
  "properties": {
    "gn:admin1_code":"30",
    "gn:admin2_code":"11",
    "gn:asciiname":"San Alberto",
    "gn:country_code":"MX",
    "gn:dem":9,
    "gn:feature_class":"P",
    "gn:feature_code":"PPL",
    "gn:name":"San Alberto",
    "gn:population":15,
    "gn:timezone":"America/Mexico_City",
    "iso:country":"MX",
    "name:ceb_x_preferred":[
        "San Alberto"
    ],
    "name:deu_x_preferred":[
        "San Alberto"
    ],
    "name:nld_x_preferred":[
        "San Alberto"
    ],
    "name:por_x_preferred":[
        "San Alberto"
    ],
    "name:spa_x_preferred":[
        "San Alberto"
    ],
    "name:srp_x_preferred":[
        "\u0421\u0430\u043d \u0410\u043b\u0431\u0435\u0440\u0442\u043e"
    ],
    "name:swe_x_preferred":[
        "San Alberto"
    ],
    "name:vie_x_preferred":[
        "San Alberto"
    ],
    "wof:name":"San Alberto",
    "wof:placetype":"locality",
    "wof:population":15
},
  "geometry": {"coordinates":[-95.54611,18.67639],"type":"Point"}
}