{
  "type": "Feature",
  "properties": {
    "gn:admin1_code":"22",
    "gn:admin2_code":"6.0",
    "gn:asciiname":"Tejeda",
    "gn:country_code":"MX",
    "gn:dem":1818,
    "gn:feature_class":"P",
    "gn:feature_code":"PPL",
    "gn:name":"Tejeda",
    "gn:population":0,
    "gn:timezone":"America/Mexico_City",
    "iso:country":"MX",
    "name:spa_x_preferred":[
        "Tejeda"
    ],
    "wof:name":"Tejeda",
    "wof:placetype":"locality"
},
  "geometry": {"coordinates":[-100.42283999999999,20.54124],"type":"Point"}
}