{
  "type": "Feature",
  "properties": {
    "gn:admin1_code":"30",
    "gn:admin2_code":"201.0",
    "gn:asciiname":"Quetzaltototl",
    "gn:country_code":"MX",
    "gn:dem":1675,
    "gn:feature_class":"P",
    "gn:feature_code":"PPL",
    "gn:name":"Quetzalt\u00f3totl",
    "gn:population":231,
    "gn:timezone":"America/Mexico_City",
    "iso:country":"MX",
    "name:und_x_variant":[
        "Quetzalt\u00f3totl"
    ],
    "wof:name":"Quetzaltototl",
    "wof:placetype":"locality",
    "wof:population":231
},
  "geometry": {"coordinates":[-96.98361,18.53972000000001],"type":"Point"}
}