{
  "type": "Feature",
  "properties": {
    "gn:admin1_code":"29",
    "gn:admin2_code":"6.0",
    "gn:asciiname":"San Jose el Lindero",
    "gn:country_code":"MX",
    "gn:dem":2622,
    "gn:feature_class":"P",
    "gn:feature_code":"PPL",
    "gn:name":"San Jose el Lindero",
    "gn:population":0,
    "gn:timezone":"America/Mexico_City",
    "iso:country":"MX",
    "name:spa_x_preferred":[
        "San Jose el Lindero"
    ],
    "wof:name":"San Jose el Lindero",
    "wof:placetype":"locality"
},
  "geometry": {"coordinates":[-98.56668999999999,19.56836],"type":"Point"}
}