{
  "type": "Feature",
  "properties": {
    "gn:admin1_code":"11",
    "gn:admin2_code":"3.0",
    "gn:asciiname":"Cruz Caballero",
    "gn:country_code":"MX",
    "gn:dem":1873,
    "gn:feature_class":"P",
    "gn:feature_code":"PPL",
    "gn:name":"Cruz Caballero",
    "gn:population":5,
    "gn:timezone":"America/Mexico_City",
    "iso:country":"MX",
    "wof:name":"Cruz Caballero",
    "wof:placetype":"locality",
    "wof:population":5
},
  "geometry": {"coordinates":[-100.79416999999999,21.01361],"type":"Point"}
}