{
  "type": "Feature",
  "properties": {
    "gn:admin1_code":"21",
    "gn:admin2_code":"3.0",
    "gn:asciiname":"La Trinidad (Los Hobos)",
    "gn:country_code":"MX",
    "gn:dem":1200,
    "gn:feature_class":"P",
    "gn:feature_code":"PPL",
    "gn:name":"La Trinidad (Los Hobos)",
    "gn:population":218,
    "gn:timezone":"America/Mexico_City",
    "iso:country":"MX",
    "wof:name":"La Trinidad (Los Hobos)",
    "wof:placetype":"locality",
    "wof:population":218
},
  "geometry": {"coordinates":[-98.02472,18.22333],"type":"Point"}
}