{
  "type": "Feature",
  "properties": {
    "gn:admin1_code":"19.0",
    "gn:admin2_code":"14.0",
    "gn:asciiname":"Vallecillos",
    "gn:country_code":"MX",
    "gn:dem":1580,
    "gn:feature_class":"P",
    "gn:feature_code":"PPL",
    "gn:name":"Vallecillos",
    "gn:population":0,
    "gn:timezone":"America/Monterrey",
    "iso:country":"MX",
    "name:spa_x_preferred":[
        "Vallecitos"
    ],
    "name:spa_x_variant":[
        "Vallecillos"
    ],
    "wof:name":"Vallecillos",
    "wof:placetype":"locality"
},
  "geometry": {"coordinates":[-100.14149,24.04056],"type":"Point"}
}