{
  "type": "Feature",
  "properties": {
    "gn:admin1_code":"12",
    "gn:admin2_code":"45.0",
    "gn:asciiname":"Tepetitlan",
    "gn:country_code":"MX",
    "gn:dem":1331,
    "gn:feature_class":"P",
    "gn:feature_code":"PPL",
    "gn:name":"Tepetitl\u00e1n",
    "gn:population":177,
    "gn:timezone":"America/Mexico_City",
    "iso:country":"MX",
    "name:und_x_variant":[
        "Tepetitl\u00e1n"
    ],
    "wof:name":"Tepetitlan",
    "wof:placetype":"locality",
    "wof:population":177
},
  "geometry": {"coordinates":[-98.84556000000001,17.84],"type":"Point"}
}