{
  "type": "Feature",
  "properties": {
    "gn:admin1_code":"15",
    "gn:admin2_code":"52.0",
    "gn:asciiname":"La Maroma",
    "gn:country_code":"MX",
    "gn:dem":1240,
    "gn:feature_class":"P",
    "gn:feature_code":"PPL",
    "gn:name":"La Maroma",
    "gn:population":0,
    "gn:timezone":"America/Mexico_City",
    "iso:country":"MX",
    "name:deu_x_preferred":[
        "La Maroma"
    ],
    "name:nno_x_preferred":[
        "La Maroma"
    ],
    "name:nor_x_preferred":[
        "La Maroma"
    ],
    "name:spa_x_preferred":[
        "La Maroma"
    ],
    "name:und_x_variant":[
        "La Maromar"
    ],
    "name:zho_x_preferred":[
        "\u99ac\u7f85\u99ac\u5cf0"
    ],
    "wof:name":"La Maroma",
    "wof:placetype":"locality"
},
  "geometry": {"coordinates":[-99.44405999999999,18.80956],"type":"Point"}
}