{
  "type": "Feature",
  "properties": {
    "gn:admin1_code":"2.0",
    "gn:admin2_code":"2.0",
    "gn:asciiname":"Crucero Valle de la Trinidad (El Oasis)",
    "gn:country_code":"MX",
    "gn:dem":68,
    "gn:feature_class":"P",
    "gn:feature_code":"PPL",
    "gn:name":"Crucero Valle de la Trinidad (El Oasis)",
    "gn:population":1,
    "gn:timezone":"America/Tijuana",
    "iso:country":"MX",
    "name:spa_x_preferred":[
        "Crucero del Valle de la Trinidad"
    ],
    "wof:name":"Crucero Valle de la Trinidad (El Oasis)",
    "wof:placetype":"locality",
    "wof:population":1
},
  "geometry": {"coordinates":[-115.04694000000001,31.42417],"type":"Point"}
}