{
  "type": "Feature",
  "properties": {
    "gn:admin1_code":"10",
    "gn:admin2_code":"12.0",
    "gn:asciiname":"El Oasis",
    "gn:country_code":"MX",
    "gn:dem":1169,
    "gn:feature_class":"P",
    "gn:feature_code":"PPL",
    "gn:name":"El Oasis",
    "gn:population":0,
    "gn:timezone":"America/Monterrey",
    "iso:country":"MX",
    "name:sco_x_preferred":[
        "El Oasis"
    ],
    "name:spa_x_preferred":[
        "El Oasis"
    ],
    "name:srp_x_preferred":[
        "\u0415\u043b \u041e\u0430\u0441\u0438\u0441"
    ],
    "wof:name":"El Oasis",
    "wof:placetype":"locality"
},
  "geometry": {"coordinates":[-103.74281000000001,25.42866],"type":"Point"}
}