{
  "type": "Feature",
  "properties": {
    "gn:admin1_code":"30.0",
    "gn:admin2_code":"160.0",
    "gn:asciiname":"Espiritu Santo",
    "gn:country_code":"MX",
    "gn:dem":97,
    "gn:feature_class":"P",
    "gn:feature_code":"PPL",
    "gn:name":"Esp\u00edritu Santo",
    "gn:population":0,
    "gn:timezone":"America/Mexico_City",
    "iso:country":"MX",
    "name:spa_x_preferred":[
        "Esp\u00edritu Santo"
    ],
    "name:spa_x_variant":[
        "Zapote Hueco"
    ],
    "wof:name":"Espiritu Santo",
    "wof:placetype":"locality"
},
  "geometry": {"coordinates":[-97.61374000000001,21.06137],"type":"Point"}
}