{
  "type": "Feature",
  "properties": {
    "gn:admin1_code":"30.0",
    "gn:admin2_code":"144.0",
    "gn:asciiname":"Finca la Ilama",
    "gn:country_code":"MX",
    "gn:dem":20,
    "gn:feature_class":"P",
    "gn:feature_code":"PPL",
    "gn:name":"Finca la Ilama",
    "gn:population":0,
    "gn:timezone":"America/Mexico_City",
    "iso:country":"MX",
    "name:spa_x_preferred":[
        "Finca la Ilama"
    ],
    "name:spa_x_variant":[
        "La Ilama"
    ],
    "wof:name":"Finca la Ilama",
    "wof:placetype":"locality"
},
  "geometry": {"coordinates":[-94.88271,17.76062],"type":"Point"}
}