{
  "type": "Feature",
  "properties": {
    "gn:admin1_code":"14",
    "gn:admin2_code":"93.0",
    "gn:asciiname":"La Mota",
    "gn:country_code":"MX",
    "gn:dem":1926,
    "gn:feature_class":"P",
    "gn:feature_code":"PPL",
    "gn:name":"La Mota",
    "gn:population":141,
    "gn:timezone":"America/Mexico_City",
    "iso:country":"MX",
    "wof:name":"La Mota",
    "wof:placetype":"locality",
    "wof:population":141
},
  "geometry": {"coordinates":[-102.69028,20.70556],"type":"Point"}
}