{
  "type": "Feature",
  "properties": {
    "gn:admin1_code":"16",
    "gn:admin2_code":"78.0",
    "gn:asciiname":"Tayo",
    "gn:country_code":"MX",
    "gn:dem":1846,
    "gn:feature_class":"P",
    "gn:feature_code":"PPL",
    "gn:name":"Tayo",
    "gn:population":0,
    "gn:timezone":"America/Mexico_City",
    "iso:country":"MX",
    "wof:name":"Tayo",
    "wof:placetype":"locality"
},
  "geometry": {"coordinates":[-101.08333,20.06667],"type":"Point"}
}