{
  "type": "Feature",
  "properties": {
    "gn:admin1_code":"12.0",
    "gn:admin2_code":"22.0",
    "gn:asciiname":"El Limon Potrero",
    "gn:country_code":"MX",
    "gn:dem":558,
    "gn:feature_class":"P",
    "gn:feature_code":"PPL",
    "gn:name":"El Lim\u00f3n Potrero",
    "gn:population":0,
    "gn:timezone":"America/Mexico_City",
    "iso:country":"MX",
    "name:spa_x_preferred":[
        "El Lim\u00f3n Potrero"
    ],
    "name:und_x_variant":[
        "El Lim\u00f3n"
    ],
    "wof:name":"El Limon Potrero",
    "wof:placetype":"locality"
},
  "geometry": {"coordinates":[-100.78230000000001,18.04126],"type":"Point"}
}