{
  "type": "Feature",
  "properties": {
    "gn:admin1_code":"24.0",
    "gn:asciiname":"Los Pasitos",
    "gn:country_code":"MX",
    "gn:dem":30,
    "gn:feature_class":"P",
    "gn:feature_code":"PPL",
    "gn:name":"Los Pasitos",
    "gn:population":0,
    "gn:timezone":"America/Mexico_City",
    "iso:country":"MX",
    "name:spa_x_preferred":[
        "Los Pasitos"
    ],
    "wof:name":"Los Pasitos",
    "wof:placetype":"locality"
},
  "geometry": {"coordinates":[-98.49518,21.83957],"type":"Point"}
}