{
  "type": "Feature",
  "properties": {
    "gn:admin1_code":"21",
    "gn:admin2_code":"207",
    "gn:asciiname":"Tepetitlan",
    "gn:country_code":"MX",
    "gn:dem":1875,
    "gn:feature_class":"P",
    "gn:feature_code":"PPL",
    "gn:name":"Tepetitlan",
    "gn:population":26,
    "gn:timezone":"America/Mexico_City",
    "iso:country":"MX",
    "wof:name":"Tepetitlan",
    "wof:placetype":"locality",
    "wof:population":26
},
  "geometry": {"coordinates":[-97.57778,19.89111],"type":"Point"}
}