{
  "type": "Feature",
  "properties": {
    "gn:admin1_code":"5",
    "gn:admin2_code":"80.0",
    "gn:asciiname":"El Zapotillo",
    "gn:cc2":"MX",
    "gn:country_code":"MX",
    "gn:dem":2778,
    "gn:feature_class":"P",
    "gn:feature_code":"PPL",
    "gn:name":"El Zapotillo",
    "gn:population":0,
    "gn:timezone":"America/Mexico_City",
    "iso:country":"MX",
    "name:und_x_variant":[
        "Zapotillo",
        "El Zapotillo"
    ],
    "wof:name":"El Zapotillo",
    "wof:placetype":"locality"
},
  "geometry": {"coordinates":[-92.28333000000001,15.48333],"type":"Point"}
}