{
  "type": "Feature",
  "properties": {
    "gn:admin1_code":"16.0",
    "gn:admin2_code":"96.0",
    "gn:asciiname":"Guayabillas",
    "gn:country_code":"MX",
    "gn:dem":926,
    "gn:feature_class":"P",
    "gn:feature_code":"PPL",
    "gn:name":"Guayabillas",
    "gn:population":0,
    "gn:timezone":"America/Mexico_City",
    "iso:country":"MX",
    "name:spa_x_preferred":[
        "Guayabillas"
    ],
    "wof:name":"Guayabillas",
    "wof:placetype":"locality"
},
  "geometry": {"coordinates":[-102.64086,18.57359],"type":"Point"}
}