{
  "type": "Feature",
  "properties": {
    "gn:admin1_code":"25",
    "gn:admin2_code":"7",
    "gn:asciiname":"Los Mirasoles",
    "gn:country_code":"MX",
    "gn:dem":839,
    "gn:feature_class":"P",
    "gn:feature_code":"PPL",
    "gn:name":"Los Mirasoles",
    "gn:population":14,
    "gn:timezone":"America/Mazatlan",
    "iso:country":"MX",
    "wof:name":"Los Mirasoles",
    "wof:placetype":"locality",
    "wof:population":14
},
  "geometry": {"coordinates":[-108.02016999999999,26.68938],"type":"Point"}
}