{
  "type": "Feature",
  "properties": {
    "gn:admin1_code":"5",
    "gn:admin2_code":"77.0",
    "gn:asciiname":"Los Dos Hermanos",
    "gn:country_code":"MX",
    "gn:dem":55,
    "gn:feature_class":"P",
    "gn:feature_code":"PPL",
    "gn:name":"Los Dos Hermanos",
    "gn:population":5,
    "gn:timezone":"America/Mexico_City",
    "iso:country":"MX",
    "wof:name":"Los Dos Hermanos",
    "wof:placetype":"locality",
    "wof:population":5
},
  "geometry": {"coordinates":[-92.24917000000001,17.45639],"type":"Point"}
}