{
  "type": "Feature",
  "properties": {
    "gn:admin1_code":"20",
    "gn:admin2_code":"253",
    "gn:asciiname":"El Borrego",
    "gn:country_code":"MX",
    "gn:dem":1083,
    "gn:feature_class":"P",
    "gn:feature_code":"PPL",
    "gn:name":"El Borrego",
    "gn:population":30,
    "gn:timezone":"America/Mexico_City",
    "iso:country":"MX",
    "wof:name":"El Borrego",
    "wof:placetype":"locality",
    "wof:population":30
},
  "geometry": {"coordinates":[-96.40555999999999,15.96889],"type":"Point"}
}