{
  "type": "Feature",
  "properties": {
    "gn:admin1_code":"6",
    "gn:admin2_code":"62.0",
    "gn:asciiname":"La Cruz",
    "gn:country_code":"MX",
    "gn:dem":1189,
    "gn:feature_class":"P",
    "gn:feature_code":"PPL",
    "gn:name":"La Cruz",
    "gn:population":0,
    "gn:timezone":"America/Chihuahua",
    "iso:country":"MX",
    "name:spa_x_preferred":[
        "La Cruz"
    ],
    "wof:name":"La Cruz",
    "wof:placetype":"locality"
},
  "geometry": {"coordinates":[-105.28888999999999,28.023],"type":"Point"}
}