{
  "type": "Feature",
  "properties": {
    "gn:admin1_code":"5",
    "gn:admin2_code":"52.0",
    "gn:asciiname":"La Conquista",
    "gn:country_code":"MX",
    "gn:dem":1435,
    "gn:feature_class":"P",
    "gn:feature_code":"PPL",
    "gn:name":"La Conquista",
    "gn:population":269,
    "gn:timezone":"America/Mexico_City",
    "iso:country":"MX",
    "wof:name":"La Conquista",
    "wof:placetype":"locality",
    "wof:population":269
},
  "geometry": {"coordinates":[-91.71222,16.38111],"type":"Point"}
}