{
  "type": "Feature",
  "properties": {
    "gn:admin1_code":"21.0",
    "gn:asciiname":"Kilometro Dos",
    "gn:country_code":"MX",
    "gn:dem":2238,
    "gn:feature_class":"P",
    "gn:feature_code":"PPL",
    "gn:name":"Kil\u00f3metro Dos",
    "gn:population":0,
    "gn:timezone":"America/Mexico_City",
    "iso:country":"MX",
    "name:spa_x_preferred":[
        "Kil\u00f3metro Dos"
    ],
    "wof:name":"Kilometro Dos",
    "wof:placetype":"locality"
},
  "geometry": {"coordinates":[-98.39292,19.18901],"type":"Point"}
}