{
  "type": "Feature",
  "properties": {
    "gn:admin1_code":"18",
    "gn:admin2_code":"5",
    "gn:asciiname":"La Campana (El Mimbre)",
    "gn:country_code":"MX",
    "gn:dem":1065,
    "gn:feature_class":"P",
    "gn:feature_code":"PPL",
    "gn:name":"La Campana (El Mimbre)",
    "gn:population":40,
    "gn:timezone":"America/Mazatlan",
    "iso:country":"MX",
    "wof:name":"La Campana (El Mimbre)",
    "wof:placetype":"locality",
    "wof:population":40
},
  "geometry": {"coordinates":[-105.18861,22.88417],"type":"Point"}
}