{
  "type": "Feature",
  "properties": {
    "gn:admin1_code":"24",
    "gn:admin2_code":"40.0",
    "gn:asciiname":"El Conejo",
    "gn:country_code":"MX",
    "gn:dem":72,
    "gn:feature_class":"P",
    "gn:feature_code":"PPL",
    "gn:name":"El Conejo",
    "gn:population":0,
    "gn:timezone":"America/Mexico_City",
    "iso:country":"MX",
    "name:spa_x_preferred":[
        "El Conejo"
    ],
    "wof:name":"El Conejo",
    "wof:placetype":"locality"
},
  "geometry": {"coordinates":[-98.70547999999999,21.8133],"type":"Point"}
}