{
  "type": "Feature",
  "properties": {
    "gn:admin1_code":"14",
    "gn:admin2_code":"2",
    "gn:asciiname":"El Quelele",
    "gn:country_code":"MX",
    "gn:dem":1355,
    "gn:feature_class":"P",
    "gn:feature_code":"PPL",
    "gn:name":"El Quelele",
    "gn:population":22,
    "gn:timezone":"America/Mexico_City",
    "iso:country":"MX",
    "wof:name":"El Quelele",
    "wof:placetype":"locality",
    "wof:population":22
},
  "geometry": {"coordinates":[-103.58917,20.39806],"type":"Point"}
}