{
  "type": "Feature",
  "properties": {
    "gn:admin1_code":"14.0",
    "gn:admin2_code":"53.0",
    "gn:asciiname":"Los Hernandez",
    "gn:country_code":"MX",
    "gn:dem":1874,
    "gn:feature_class":"P",
    "gn:feature_code":"PPL",
    "gn:name":"Los Hern\u00e1ndez",
    "gn:population":0,
    "gn:timezone":"America/Mexico_City",
    "iso:country":"MX",
    "name:spa_x_preferred":[
        "Los Hern\u00e1ndez"
    ],
    "wof:name":"Los Hernandez",
    "wof:placetype":"locality"
},
  "geometry": {"coordinates":[-101.91851,21.34271],"type":"Point"}
}