{
  "type": "Feature",
  "properties": {
    "gn:admin1_code":"7",
    "gn:admin2_code":"36.0",
    "gn:asciiname":"El Palmito",
    "gn:country_code":"MX",
    "gn:dem":1189,
    "gn:feature_class":"P",
    "gn:feature_code":"PPL",
    "gn:name":"El Palmito",
    "gn:population":0,
    "gn:timezone":"America/Chihuahua",
    "iso:country":"MX",
    "name:spa_x_preferred":[
        "El Palmito"
    ],
    "wof:name":"El Palmito",
    "wof:placetype":"locality"
},
  "geometry": {"coordinates":[-103.848,27.18238],"type":"Point"}
}