{
  "type": "Feature",
  "properties": {
    "gn:admin1_code":"19.0",
    "gn:admin2_code":"44.0",
    "gn:asciiname":"Guterrenas",
    "gn:country_code":"MX",
    "gn:dem":301,
    "gn:feature_class":"P",
    "gn:feature_code":"PPL",
    "gn:name":"Guterre\u00f1as",
    "gn:population":0,
    "gn:timezone":"America/Monterrey",
    "iso:country":"MX",
    "name:spa_x_preferred":[
        "Guterre\u00f1as"
    ],
    "wof:name":"Guterrenas",
    "wof:placetype":"locality"
},
  "geometry": {"coordinates":[-100.12144000000001,26.6892],"type":"Point"}
}