{
  "type": "Feature",
  "properties": {
    "gn:admin1_code":"19",
    "gn:admin2_code":"22.0",
    "gn:asciiname":"Del Maestro",
    "gn:country_code":"MX",
    "gn:dem":321,
    "gn:feature_class":"P",
    "gn:feature_code":"PPL",
    "gn:name":"Del Maestro",
    "gn:population":53,
    "gn:timezone":"America/Monterrey",
    "iso:country":"MX",
    "wof:name":"Del Maestro",
    "wof:placetype":"locality",
    "wof:population":53
},
  "geometry": {"coordinates":[-99.69223,25.26979],"type":"Point"}
}