{
  "type": "Feature",
  "properties": {
    "gn:admin1_code":"11",
    "gn:admin2_code":"31",
    "gn:asciiname":"El Mosco",
    "gn:country_code":"MX",
    "gn:dem":1734,
    "gn:feature_class":"P",
    "gn:feature_code":"PPL",
    "gn:name":"El Mosco",
    "gn:population":12,
    "gn:timezone":"America/Mexico_City",
    "iso:country":"MX",
    "wof:name":"El Mosco",
    "wof:placetype":"locality",
    "wof:population":12
},
  "geometry": {"coordinates":[-101.86611000000001,20.84722],"type":"Point"}
}