{
  "type": "Feature",
  "properties": {
    "gn:admin1_code":"6.0",
    "gn:admin2_code":"8.0",
    "gn:asciiname":"Camino Viejo",
    "gn:country_code":"MX",
    "gn:dem":608,
    "gn:feature_class":"P",
    "gn:feature_code":"PPL",
    "gn:name":"Camino Viejo",
    "gn:population":0,
    "gn:timezone":"America/Chihuahua",
    "iso:country":"MX",
    "name:spa_x_preferred":[
        "Camino Viejo"
    ],
    "wof:name":"Camino Viejo",
    "wof:placetype":"locality"
},
  "geometry": {"coordinates":[-107.86997,26.72694000000001],"type":"Point"}
}