{
  "type": "Feature",
  "properties": {
    "gn:admin1_code":"25.0",
    "gn:asciiname":"Los Chinos",
    "gn:country_code":"MX",
    "gn:dem":24,
    "gn:feature_class":"P",
    "gn:feature_code":"PPL",
    "gn:name":"Los Chinos",
    "gn:population":0,
    "gn:timezone":"America/Mazatlan",
    "iso:country":"MX",
    "name:spa_x_preferred":[
        "Los Chinos"
    ],
    "wof:name":"Los Chinos",
    "wof:placetype":"locality"
},
  "geometry": {"coordinates":[-108.82791,25.87985],"type":"Point"}
}