{
  "type": "Feature",
  "properties": {
    "gn:admin1_code":"10",
    "gn:admin2_code":"28.0",
    "gn:asciiname":"Cieneguitas",
    "gn:country_code":"MX",
    "gn:dem":2018,
    "gn:feature_class":"P",
    "gn:feature_code":"PPL",
    "gn:name":"Cieneguitas",
    "gn:population":0,
    "gn:timezone":"America/Monterrey",
    "iso:country":"MX",
    "name:spa_x_preferred":[
        "Cieneguitas"
    ],
    "wof:name":"Cieneguitas",
    "wof:placetype":"locality"
},
  "geometry": {"coordinates":[-104.54815000000001,24.6228],"type":"Point"}
}