{
  "type": "Feature",
  "properties": {
    "gn:admin1_code":"11",
    "gn:admin2_code":"17.0",
    "gn:asciiname":"Colonia Plan Vivira",
    "gn:country_code":"MX",
    "gn:dem":1723,
    "gn:feature_class":"P",
    "gn:feature_code":"PPL",
    "gn:name":"Colonia Plan Vivir\u00e1",
    "gn:population":273,
    "gn:timezone":"America/Mexico_City",
    "iso:country":"MX",
    "name:und_x_variant":[
        "Colonia Plan Vivir\u00e1"
    ],
    "wof:name":"Colonia Plan Vivira",
    "wof:placetype":"locality",
    "wof:population":273
},
  "geometry": {"coordinates":[-101.39111,20.66278],"type":"Point"}
}