{
  "type": "Feature",
  "properties": {
    "gn:admin1_code":"28",
    "gn:admin2_code":"2.0",
    "gn:asciiname":"Leon Carrizales",
    "gn:country_code":"MX",
    "gn:dem":116,
    "gn:feature_class":"P",
    "gn:feature_code":"PPL",
    "gn:name":"Le\u00f3n Carrizales",
    "gn:population":6,
    "gn:timezone":"America/Monterrey",
    "iso:country":"MX",
    "name:und_x_variant":[
        "Le\u00f3n Carrizales"
    ],
    "wof:name":"Leon Carrizales",
    "wof:placetype":"locality",
    "wof:population":6
},
  "geometry": {"coordinates":[-98.16556,22.89639],"type":"Point"}
}