{
  "type": "Feature",
  "properties": {
    "gn:admin1_code":"30",
    "gn:admin2_code":"32.0",
    "gn:asciiname":"Ahuatepec",
    "gn:country_code":"MX",
    "gn:dem":551,
    "gn:feature_class":"P",
    "gn:feature_code":"PPL",
    "gn:name":"Ahuatepec",
    "gn:population":324,
    "gn:timezone":"America/Mexico_City",
    "iso:country":"MX",
    "wof:name":"Ahuatepec",
    "wof:placetype":"locality",
    "wof:population":324
},
  "geometry": {"coordinates":[-95.11499999999999,18.33972],"type":"Point"}
}