{
  "type": "Feature",
  "properties": {
    "gn:admin1_code":"12.0",
    "gn:admin2_code":"40.0",
    "gn:asciiname":"Las Tilias",
    "gn:country_code":"MX",
    "gn:dem":2252,
    "gn:feature_class":"P",
    "gn:feature_code":"PPL",
    "gn:name":"Las Tilias",
    "gn:population":0,
    "gn:timezone":"America/Mexico_City",
    "iso:country":"MX",
    "name:spa_x_preferred":[
        "Las Tilias"
    ],
    "wof:name":"Las Tilias",
    "wof:placetype":"locality"
},
  "geometry": {"coordinates":[-99.88753,17.72762999999999],"type":"Point"}
}