{
  "type": "Feature",
  "properties": {
    "gn:admin1_code":"6",
    "gn:admin2_code":"67.0",
    "gn:asciiname":"La Cieneguita",
    "gn:country_code":"MX",
    "gn:dem":1489,
    "gn:feature_class":"P",
    "gn:feature_code":"PPL",
    "gn:name":"La Cieneguita",
    "gn:population":0,
    "gn:timezone":"America/Chihuahua",
    "iso:country":"MX",
    "name:spa_x_preferred":[
        "La Cieneguita"
    ],
    "wof:name":"La Cieneguita",
    "wof:placetype":"locality"
},
  "geometry": {"coordinates":[-105.9213,27.40598],"type":"Point"}
}