{
  "type": "Feature",
  "properties": {
    "gn:admin1_code":"6",
    "gn:admin2_code":"60.0",
    "gn:asciiname":"La Tinajita",
    "gn:country_code":"MX",
    "gn:dem":1955,
    "gn:feature_class":"P",
    "gn:feature_code":"PPL",
    "gn:name":"La Tinajita",
    "gn:population":0,
    "gn:timezone":"America/Chihuahua",
    "iso:country":"MX",
    "name:spa_x_preferred":[
        "La Tinajita"
    ],
    "wof:name":"La Tinajita",
    "wof:placetype":"locality"
},
  "geometry": {"coordinates":[-105.79091,26.72418],"type":"Point"}
}