{
  "type": "Feature",
  "properties": {
    "gn:admin1_code":"28",
    "gn:admin2_code":"11",
    "gn:asciiname":"Lazaro Cardenas (El Malacate)",
    "gn:country_code":"MX",
    "gn:dem":1157,
    "gn:feature_class":"P",
    "gn:feature_code":"PPL",
    "gn:name":"L\u00e1zaro C\u00e1rdenas (El Malacate)",
    "gn:population":12,
    "gn:timezone":"America/Monterrey",
    "iso:country":"MX",
    "name:und_x_variant":[
        "L\u00e1zaro C\u00e1rdenas (El Malacate)"
    ],
    "wof:name":"Lazaro Cardenas (El Malacate)",
    "wof:placetype":"locality",
    "wof:population":12
},
  "geometry": {"coordinates":[-99.19499999999999,23.11972],"type":"Point"}
}