{
  "type": "Feature",
  "properties": {
    "gn:admin1_code":"7.0",
    "gn:admin2_code":"2.0",
    "gn:asciiname":"Los Gonzalez",
    "gn:country_code":"MX",
    "gn:dem":307,
    "gn:feature_class":"P",
    "gn:feature_code":"PPL",
    "gn:name":"Los Gonz\u00e1lez",
    "gn:population":0,
    "gn:timezone":"America/Matamoros",
    "iso:country":"MX",
    "name:spa_x_preferred":[
        "Los Gonz\u00e1lez"
    ],
    "wof:name":"Los Gonzalez",
    "wof:placetype":"locality"
},
  "geometry": {"coordinates":[-100.89937999999999,29.24882],"type":"Point"}
}