{
  "type": "Feature",
  "properties": {
    "gn:admin1_code":"11",
    "gn:admin2_code":"26",
    "gn:asciiname":"Ejido Colonia Juarez (Alejandro Mata)",
    "gn:country_code":"MX",
    "gn:dem":1745,
    "gn:feature_class":"P",
    "gn:feature_code":"PPL",
    "gn:name":"Ejido Colonia Ju\u00e1rez (Alejandro Mata)",
    "gn:population":9,
    "gn:timezone":"America/Mexico_City",
    "iso:country":"MX",
    "name:und_x_variant":[
        "Ejido Colonia Ju\u00e1rez (Alejandro Mata)"
    ],
    "wof:name":"Ejido Colonia Juarez (Alejandro Mata)",
    "wof:placetype":"locality",
    "wof:population":9
},
  "geometry": {"coordinates":[-101.49111000000001,20.85],"type":"Point"}
}