{
  "type": "Feature",
  "properties": {
    "gn:admin1_code":"26",
    "gn:admin2_code":"25.0",
    "gn:asciiname":"San Antonio",
    "gn:country_code":"MX",
    "gn:dem":11,
    "gn:feature_class":"P",
    "gn:feature_code":"PPL",
    "gn:name":"San Antonio",
    "gn:population":1,
    "gn:timezone":"America/Hermosillo",
    "iso:country":"MX",
    "name:spa_x_preferred":[
        "San Antonio"
    ],
    "wof:name":"San Antonio",
    "wof:placetype":"locality",
    "wof:population":1
},
  "geometry": {"coordinates":[-110.60944000000001,27.92972],"type":"Point"}
}