{
  "type": "Feature",
  "properties": {
    "gn:admin1_code":"12.0",
    "gn:admin2_code":"38.0",
    "gn:asciiname":"El Patacual",
    "gn:country_code":"MX",
    "gn:dem":931,
    "gn:feature_class":"P",
    "gn:feature_code":"PPL",
    "gn:name":"El Patacual",
    "gn:population":0,
    "gn:timezone":"America/Mexico_City",
    "iso:country":"MX",
    "wof:name":"El Patacual",
    "wof:placetype":"locality"
},
  "geometry": {"coordinates":[-101.31439,17.80283],"type":"Point"}
}