{
  "type": "Feature",
  "properties": {
    "gn:admin1_code":"14",
    "gn:admin2_code":"6.0",
    "gn:asciiname":"El Realito",
    "gn:country_code":"MX",
    "gn:dem":1329,
    "gn:feature_class":"P",
    "gn:feature_code":"PPL",
    "gn:name":"El Realito",
    "gn:population":66,
    "gn:timezone":"America/Mexico_City",
    "iso:country":"MX",
    "wof:name":"El Realito",
    "wof:placetype":"locality",
    "wof:population":66
},
  "geometry": {"coordinates":[-104.17559,20.53879],"type":"Point"}
}