{
  "type": "Feature",
  "properties": {
    "gn:admin1_code":"29",
    "gn:admin2_code":"31.0",
    "gn:asciiname":"Teotlalpan",
    "gn:country_code":"MX",
    "gn:dem":2459,
    "gn:feature_class":"P",
    "gn:feature_code":"PPL",
    "gn:name":"Teotlalpan",
    "gn:population":0,
    "gn:timezone":"America/Mexico_City",
    "iso:country":"MX",
    "name:ceb_x_preferred":[
        "Teotlalpan"
    ],
    "name:deu_x_preferred":[
        "Teotlalpan"
    ],
    "name:fra_x_preferred":[
        "Teotlalpan"
    ],
    "name:lad_x_preferred":[
        "Teotlalpan"
    ],
    "name:nld_x_preferred":[
        "Teotlalpan"
    ],
    "name:por_x_preferred":[
        "Teotlalpan"
    ],
    "name:spa_x_preferred":[
        "Teotlalpan"
    ],
    "name:swe_x_preferred":[
        "Teotlalpan"
    ],
    "name:und_x_variant":[
        "Tetla Segunda Secci\u00f3n"
    ],
    "wof:name":"Teotlalpan",
    "wof:placetype":"locality"
},
  "geometry": {"coordinates":[-98.10414,19.44291],"type":"Point"}
}