{
  "type": "Feature",
  "properties": {
    "gn:admin1_code":"20",
    "gn:admin2_code":"29",
    "gn:asciiname":"Agua de Cuchara (Agua de Cucharon)",
    "gn:country_code":"MX",
    "gn:dem":1357,
    "gn:feature_class":"P",
    "gn:feature_code":"PPL",
    "gn:name":"Agua de Cuchara (Agua de Cuchar\u00f3n)",
    "gn:population":28,
    "gn:timezone":"America/Mexico_City",
    "iso:country":"MX",
    "name:und_x_variant":[
        "Agua de Cuchara (Agua de Cuchar\u00f3n)"
    ],
    "wof:name":"Agua de Cuchara (Agua de Cucharon)",
    "wof:placetype":"locality",
    "wof:population":28
},
  "geometry": {"coordinates":[-96.85611,18.16361],"type":"Point"}
}