{
  "type": "Feature",
  "properties": {
    "gn:admin1_code":"6",
    "gn:admin2_code":"66.0",
    "gn:asciiname":"El Hoyo",
    "gn:country_code":"MX",
    "gn:dem":2326,
    "gn:feature_class":"P",
    "gn:feature_code":"PPL",
    "gn:name":"El Hoyo",
    "gn:population":6,
    "gn:timezone":"America/Chihuahua",
    "iso:country":"MX",
    "name:ita_x_preferred":[
        "El Hoyo"
    ],
    "name:spa_x_preferred":[
        "El Hoyo"
    ],
    "wof:name":"El Hoyo",
    "wof:placetype":"locality",
    "wof:population":6
},
  "geometry": {"coordinates":[-108.19389,27.70944],"type":"Point"}
}