{
  "type": "Feature",
  "properties": {
    "gn:admin1_code":"26",
    "gn:admin2_code":"30.0",
    "gn:asciiname":"Las Bombitas",
    "gn:country_code":"MX",
    "gn:dem":280,
    "gn:feature_class":"P",
    "gn:feature_code":"PPL",
    "gn:name":"Las Bombitas",
    "gn:population":0,
    "gn:timezone":"America/Hermosillo",
    "iso:country":"MX",
    "name:spa_x_preferred":[
        "Las Bombitas"
    ],
    "wof:name":"Las Bombitas",
    "wof:placetype":"locality"
},
  "geometry": {"coordinates":[-110.72750000000001,29.21348],"type":"Point"}
}