{
  "type": "Feature",
  "properties": {
    "gn:admin1_code":"14",
    "gn:admin2_code":"29",
    "gn:asciiname":"Agua Escondida",
    "gn:country_code":"MX",
    "gn:dem":1797,
    "gn:feature_class":"P",
    "gn:feature_code":"PPL",
    "gn:name":"Agua Escondida",
    "gn:population":28,
    "gn:timezone":"America/Mexico_City",
    "iso:country":"MX",
    "wof:name":"Agua Escondida",
    "wof:placetype":"locality",
    "wof:population":28
},
  "geometry": {"coordinates":[-103.03167000000001,20.88639],"type":"Point"}
}