{
  "type": "Feature",
  "properties": {
    "gn:admin1_code":"25",
    "gn:admin2_code":"5",
    "gn:asciiname":"Llano Grande",
    "gn:country_code":"MX",
    "gn:dem":262,
    "gn:feature_class":"P",
    "gn:feature_code":"PPL",
    "gn:name":"Llano Grande",
    "gn:population":50,
    "gn:timezone":"America/Mazatlan",
    "iso:country":"MX",
    "name:ceb_x_preferred":[
        "Llano Grande"
    ],
    "name:deu_x_preferred":[
        "Llano Grande"
    ],
    "name:fra_x_preferred":[
        "Llano Grande"
    ],
    "name:ita_x_preferred":[
        "Llano Grande"
    ],
    "name:spa_x_preferred":[
        "Llano Grande"
    ],
    "name:swe_x_preferred":[
        "Llano Grande"
    ],
    "wof:name":"Llano Grande",
    "wof:placetype":"locality",
    "wof:population":50
},
  "geometry": {"coordinates":[-106.62739999999999,24.31706],"type":"Point"}
}