{
  "type": "Feature",
  "properties": {
    "gn:admin1_code":"6",
    "gn:admin2_code":"10.0",
    "gn:asciiname":"Ojo Carvajaleno",
    "gn:country_code":"MX",
    "gn:dem":1474,
    "gn:feature_class":"P",
    "gn:feature_code":"PPL",
    "gn:name":"Ojo Carvajale\u00f1o",
    "gn:population":0,
    "gn:timezone":"America/Chihuahua",
    "iso:country":"MX",
    "name:spa_x_preferred":[
        "Ojo Carvajale\u00f1o"
    ],
    "name:und_x_variant":[
        "Carbajale\u00f1o",
        "Ojo Carbajale\u00f1o"
    ],
    "wof:name":"Ojo Carvajaleno",
    "wof:placetype":"locality"
},
  "geometry": {"coordinates":[-107.64176,29.95777],"type":"Point"}
}