{
  "type": "Feature",
  "properties": {
    "gn:admin1_code":"13",
    "gn:admin2_code":"73.0",
    "gn:asciiname":"La Garrapata",
    "gn:country_code":"MX",
    "gn:dem":1352,
    "gn:feature_class":"P",
    "gn:feature_code":"PPL",
    "gn:name":"La Garrapata",
    "gn:population":0,
    "gn:timezone":"America/Mexico_City",
    "iso:country":"MX",
    "name:spa_x_preferred":[
        "La Garrapata"
    ],
    "wof:name":"La Garrapata",
    "wof:placetype":"locality"
},
  "geometry": {"coordinates":[-98.68028,21.027],"type":"Point"}
}