{
  "type": "Feature",
  "properties": {
    "gn:admin1_code":"16.0",
    "gn:admin2_code":"10.0",
    "gn:asciiname":"El Bordonal",
    "gn:country_code":"MX",
    "gn:dem":561,
    "gn:feature_class":"P",
    "gn:feature_code":"PPL",
    "gn:name":"El Bordonal",
    "gn:population":0,
    "gn:timezone":"America/Mexico_City",
    "iso:country":"MX",
    "name:spa_x_preferred":[
        "El Bordonal"
    ],
    "wof:name":"El Bordonal",
    "wof:placetype":"locality"
},
  "geometry": {"coordinates":[-102.30426,18.28299],"type":"Point"}
}