{
  "type": "Feature",
  "properties": {
    "gn:admin1_code":"24",
    "gn:admin2_code":"12.0",
    "gn:asciiname":"Cuaquentla",
    "gn:country_code":"MX",
    "gn:dem":420,
    "gn:feature_class":"P",
    "gn:feature_code":"PPL",
    "gn:name":"Cuaquentla",
    "gn:population":5,
    "gn:timezone":"America/Mexico_City",
    "iso:country":"MX",
    "wof:name":"Cuaquentla",
    "wof:placetype":"locality",
    "wof:population":5
},
  "geometry": {"coordinates":[-98.94333,21.56417],"type":"Point"}
}