{
  "type": "Feature",
  "properties": {
    "gn:admin1_code":"30",
    "gn:admin2_code":"198.0",
    "gn:asciiname":"Cuarta Manzana",
    "gn:country_code":"MX",
    "gn:dem":1801,
    "gn:feature_class":"P",
    "gn:feature_code":"PPL",
    "gn:name":"Cuarta Manzana",
    "gn:population":229,
    "gn:timezone":"America/Mexico_City",
    "iso:country":"MX",
    "wof:name":"Cuarta Manzana",
    "wof:placetype":"locality",
    "wof:population":229
},
  "geometry": {"coordinates":[-98.36083000000001,20.43667],"type":"Point"}
}