{
  "type": "Feature",
  "properties": {
    "gn:admin1_code":"11",
    "gn:admin2_code":"33",
    "gn:asciiname":"La Nueva Victoria",
    "gn:country_code":"MX",
    "gn:dem":1987,
    "gn:feature_class":"P",
    "gn:feature_code":"PPL",
    "gn:name":"La Nueva Victoria",
    "gn:population":10,
    "gn:timezone":"America/Mexico_City",
    "iso:country":"MX",
    "wof:name":"La Nueva Victoria",
    "wof:placetype":"locality",
    "wof:population":10
},
  "geometry": {"coordinates":[-100.60639,21.28444],"type":"Point"}
}