{
  "type": "Feature",
  "properties": {
    "gn:admin1_code":"9",
    "gn:admin2_code":"9",
    "gn:asciiname":"Tlaloxtutienco (Montesinos)",
    "gn:country_code":"MX",
    "gn:dem":2530,
    "gn:feature_class":"P",
    "gn:feature_code":"PPL",
    "gn:name":"Tlaloxtutienco (Montesinos)",
    "gn:population":30,
    "gn:timezone":"America/Mexico_City",
    "iso:country":"MX",
    "wof:name":"Tlaloxtutienco (Montesinos)",
    "wof:placetype":"locality",
    "wof:population":30
},
  "geometry": {"coordinates":[-99.06291,19.19658],"type":"Point"}
}