{
  "type": "Feature",
  "properties": {
    "gn:admin1_code":"24",
    "gn:admin2_code":"14.0",
    "gn:asciiname":"Los Jobos Primera Seccion",
    "gn:country_code":"MX",
    "gn:dem":139,
    "gn:feature_class":"P",
    "gn:feature_code":"PPL",
    "gn:name":"Los Jobos Primera Secci\u00f3n",
    "gn:population":121,
    "gn:timezone":"America/Mexico_City",
    "iso:country":"MX",
    "name:und_x_variant":[
        "Los Jobos Primera Secci\u00f3n"
    ],
    "wof:name":"Los Jobos Primera Seccion",
    "wof:placetype":"locality",
    "wof:population":121
},
  "geometry": {"coordinates":[-98.89778,21.56],"type":"Point"}
}