{
  "type": "Feature",
  "properties": {
    "gn:admin1_code":"7",
    "gn:admin2_code":"31.0",
    "gn:asciiname":"Rancho El Tulillo",
    "gn:country_code":"MX",
    "gn:dem":560,
    "gn:feature_class":"P",
    "gn:feature_code":"PPL",
    "gn:name":"Rancho El Tulillo",
    "gn:population":0,
    "gn:timezone":"America/Monterrey",
    "iso:country":"MX",
    "wof:name":"Rancho El Tulillo",
    "wof:placetype":"locality"
},
  "geometry": {"coordinates":[-101.59999999999999,27.31667],"type":"Point"}
}