{
  "type": "Feature",
  "properties": {
    "gn:admin1_code":"16",
    "gn:admin2_code":"53.0",
    "gn:asciiname":"Residencial Fresnos",
    "gn:country_code":"MX",
    "gn:dem":1932,
    "gn:feature_class":"P",
    "gn:feature_code":"PPL",
    "gn:name":"Residencial Fresnos",
    "gn:population":108,
    "gn:timezone":"America/Mexico_City",
    "iso:country":"MX",
    "wof:name":"Residencial Fresnos",
    "wof:placetype":"locality",
    "wof:population":108
},
  "geometry": {"coordinates":[-101.11778,19.73194],"type":"Point"}
}