{
  "type": "Feature",
  "properties": {
    "gn:admin1_code":"14",
    "gn:admin2_code":"1",
    "gn:asciiname":"Carricillo",
    "gn:country_code":"MX",
    "gn:dem":1707,
    "gn:feature_class":"P",
    "gn:feature_code":"PPL",
    "gn:name":"Carricillo",
    "gn:population":36,
    "gn:timezone":"America/Mexico_City",
    "iso:country":"MX",
    "wof:name":"Carricillo",
    "wof:placetype":"locality",
    "wof:population":36
},
  "geometry": {"coordinates":[-102.86806,20.77],"type":"Point"}
}