{
  "type": "Feature",
  "properties": {
    "gn:admin1_code":"28.0",
    "gn:admin2_code":"37.0",
    "gn:asciiname":"Los Pescadores",
    "gn:country_code":"MX",
    "gn:dem":62,
    "gn:feature_class":"P",
    "gn:feature_code":"PPL",
    "gn:name":"Los Pescadores",
    "gn:population":3,
    "gn:timezone":"America/Monterrey",
    "iso:country":"MX",
    "name:spa_x_preferred":[
        "Los Pescadores"
    ],
    "wof:name":"Los Pescadores",
    "wof:placetype":"locality",
    "wof:population":3
},
  "geometry": {"coordinates":[-98.03278,23.4725],"type":"Point"}
}