{
  "type": "Feature",
  "properties": {
    "gn:admin1_code":"13",
    "gn:admin2_code":"36.0",
    "gn:asciiname":"Arroyo Hondo",
    "gn:country_code":"MX",
    "gn:dem":2117,
    "gn:feature_class":"P",
    "gn:feature_code":"PPL",
    "gn:name":"Arroyo Hondo",
    "gn:population":0,
    "gn:timezone":"America/Mexico_City",
    "iso:country":"MX",
    "name:ceb_x_preferred":[
        "Arroyo Hondo"
    ],
    "name:spa_x_preferred":[
        "Arroyo Hondo"
    ],
    "name:swe_x_preferred":[
        "Arroyo Hondo"
    ],
    "wof:name":"Arroyo Hondo",
    "wof:placetype":"locality"
},
  "geometry": {"coordinates":[-98.54586,20.53026],"type":"Point"}
}