{
  "type": "Feature",
  "properties": {
    "gn:admin1_code":"14.0",
    "gn:admin2_code":"51.0",
    "gn:asciiname":"Juanacaxtle",
    "gn:country_code":"MX",
    "gn:dem":1532,
    "gn:feature_class":"P",
    "gn:feature_code":"PPL",
    "gn:name":"Juanacaxtle",
    "gn:population":0,
    "gn:timezone":"America/Mexico_City",
    "iso:country":"MX",
    "wof:name":"Juanacaxtle",
    "wof:placetype":"locality"
},
  "geometry": {"coordinates":[-103.15631,20.53055],"type":"Point"}
}