{
  "type": "Feature",
  "properties": {
    "gn:admin1_code":"11",
    "gn:admin2_code":"4",
    "gn:asciiname":"Granja la Gloria",
    "gn:country_code":"MX",
    "gn:dem":1796,
    "gn:feature_class":"P",
    "gn:feature_code":"PPL",
    "gn:name":"Granja la Gloria",
    "gn:population":22,
    "gn:timezone":"America/Mexico_City",
    "iso:country":"MX",
    "wof:name":"Granja la Gloria",
    "wof:placetype":"locality",
    "wof:population":22
},
  "geometry": {"coordinates":[-100.64610999999999,20.49417],"type":"Point"}
}