{
  "type": "Feature",
  "properties": {
    "gn:admin1_code":"26",
    "gn:admin2_code":"30",
    "gn:asciiname":"Semillas del Pacifico",
    "gn:country_code":"MX",
    "gn:dem":39,
    "gn:feature_class":"P",
    "gn:feature_code":"PPL",
    "gn:name":"Semillas del Pac\u00edfico",
    "gn:population":18,
    "gn:timezone":"America/Hermosillo",
    "iso:country":"MX",
    "name:und_x_variant":[
        "Semillas del Pac\u00edfico"
    ],
    "wof:name":"Semillas del Pacifico",
    "wof:placetype":"locality",
    "wof:population":18
},
  "geometry": {"coordinates":[-111.61778,28.83361],"type":"Point"}
}