{
  "type": "Feature",
  "properties": {
    "gn:admin1_code":"30",
    "gn:admin2_code":"181",
    "gn:asciiname":"La Josefina",
    "gn:country_code":"MX",
    "gn:dem":15,
    "gn:feature_class":"P",
    "gn:feature_code":"PPL",
    "gn:name":"La Josefina",
    "gn:population":32,
    "gn:timezone":"America/Mexico_City",
    "iso:country":"MX",
    "wof:name":"La Josefina",
    "wof:placetype":"locality",
    "wof:population":32
},
  "geometry": {"coordinates":[-96.08944,18.61722],"type":"Point"}
}