{
  "type": "Feature",
  "properties": {
    "gn:admin1_code":"8",
    "gn:admin2_code":"2.0",
    "gn:asciiname":"Las Carmelitas",
    "gn:country_code":"MX",
    "gn:dem":565,
    "gn:feature_class":"P",
    "gn:feature_code":"PPL",
    "gn:name":"Las Carmelitas",
    "gn:population":5,
    "gn:timezone":"America/Mexico_City",
    "iso:country":"MX",
    "wof:name":"Las Carmelitas",
    "wof:placetype":"locality",
    "wof:population":5
},
  "geometry": {"coordinates":[-103.53888999999999,19.16472000000001],"type":"Point"}
}