{
  "type": "Feature",
  "properties": {
    "gn:admin1_code":"19",
    "gn:admin2_code":"22.0",
    "gn:asciiname":"El Bagre",
    "gn:country_code":"MX",
    "gn:dem":276,
    "gn:feature_class":"P",
    "gn:feature_code":"PPL",
    "gn:name":"El Bagre",
    "gn:population":0,
    "gn:timezone":"America/Monterrey",
    "iso:country":"MX",
    "name:und_x_variant":[
        "Bagre",
        "El Bagre"
    ],
    "wof:name":"El Bagre",
    "wof:placetype":"locality"
},
  "geometry": {"coordinates":[-99.64557000000001,25.36016],"type":"Point"}
}