{
  "type": "Feature",
  "properties": {
    "gn:admin1_code":"7",
    "gn:admin2_code":"33.0",
    "gn:asciiname":"La Majada",
    "gn:country_code":"MX",
    "gn:dem":1102,
    "gn:feature_class":"P",
    "gn:feature_code":"PPL",
    "gn:name":"La Majada",
    "gn:population":7,
    "gn:timezone":"America/Monterrey",
    "iso:country":"MX",
    "wof:name":"La Majada",
    "wof:placetype":"locality",
    "wof:population":7
},
  "geometry": {"coordinates":[-103.12730000000001,25.94694],"type":"Point"}
}