{
  "type": "Feature",
  "properties": {
    "gn:admin1_code":"6",
    "gn:admin2_code":"8.0",
    "gn:asciiname":"Ejido San Ignacio",
    "gn:country_code":"MX",
    "gn:dem":353,
    "gn:feature_class":"P",
    "gn:feature_code":"PPL",
    "gn:name":"Ejido San Ignacio",
    "gn:population":0,
    "gn:timezone":"America/Chihuahua",
    "iso:country":"MX",
    "name:spa_x_preferred":[
        "Ejido San Ignacio"
    ],
    "name:und_x_variant":[
        "San Ignacio"
    ],
    "wof:name":"Ejido San Ignacio",
    "wof:placetype":"locality"
},
  "geometry": {"coordinates":[-107.84689,26.84976],"type":"Point"}
}