{
  "type": "Feature",
  "properties": {
    "gn:admin1_code":"13",
    "gn:admin2_code":"84.0",
    "gn:asciiname":"El Salitre",
    "gn:country_code":"MX",
    "gn:dem":1592,
    "gn:feature_class":"P",
    "gn:feature_code":"PPL",
    "gn:name":"El Salitre",
    "gn:population":5,
    "gn:timezone":"America/Mexico_City",
    "iso:country":"MX",
    "wof:name":"El Salitre",
    "wof:placetype":"locality",
    "wof:population":5
},
  "geometry": {"coordinates":[-99.36057,20.84539],"type":"Point"}
}