{
  "type": "Feature",
  "properties": {
    "gn:admin1_code":"20",
    "gn:admin2_code":"184",
    "gn:asciiname":"Licenciado Ignacio Martinez Bautista",
    "gn:country_code":"MX",
    "gn:dem":38,
    "gn:feature_class":"P",
    "gn:feature_code":"PPL",
    "gn:name":"Licenciado Ignacio Mart\u00ednez Bautista",
    "gn:population":32,
    "gn:timezone":"America/Mexico_City",
    "iso:country":"MX",
    "name:und_x_variant":[
        "Licenciado Ignacio Mart\u00ednez Bautista"
    ],
    "wof:name":"Licenciado Ignacio Martinez Bautista",
    "wof:placetype":"locality",
    "wof:population":32
},
  "geometry": {"coordinates":[-96.00082999999999,17.99722000000001],"type":"Point"}
}