{
  "type": "Feature",
  "properties": {
    "gn:admin1_code":"20",
    "gn:admin2_code":"385",
    "gn:asciiname":"Colonia San Jose Comunal",
    "gn:country_code":"MX",
    "gn:dem":1647,
    "gn:feature_class":"P",
    "gn:feature_code":"PPL",
    "gn:name":"Colonia San Jos\u00e9 Comunal",
    "gn:population":31,
    "gn:timezone":"America/Mexico_City",
    "iso:country":"MX",
    "name:und_x_variant":[
        "Colonia San Jos\u00e9 Comunal"
    ],
    "wof:name":"Colonia San Jose Comunal",
    "wof:placetype":"locality",
    "wof:population":31
},
  "geometry": {"coordinates":[-96.75861,17.03389],"type":"Point"}
}