{
  "type": "Feature",
  "properties": {
    "gn:admin1_code":"17",
    "gn:admin2_code":"7.0",
    "gn:asciiname":"Los Ailes",
    "gn:country_code":"MX",
    "gn:dem":2032,
    "gn:feature_class":"P",
    "gn:feature_code":"PPL",
    "gn:name":"Los Ailes",
    "gn:population":57,
    "gn:timezone":"America/Mexico_City",
    "iso:country":"MX",
    "wof:name":"Los Ailes",
    "wof:placetype":"locality",
    "wof:population":57
},
  "geometry": {"coordinates":[-99.26333,18.98444],"type":"Point"}
}