{
  "type": "Feature",
  "properties": {
    "gn:admin1_code":"6",
    "gn:admin2_code":"65.0",
    "gn:asciiname":"Chihuirabo",
    "gn:country_code":"MX",
    "gn:dem":2316,
    "gn:feature_class":"P",
    "gn:feature_code":"PPL",
    "gn:name":"Chihuirabo",
    "gn:population":7,
    "gn:timezone":"America/Chihuahua",
    "iso:country":"MX",
    "wof:name":"Chihuirabo",
    "wof:placetype":"locality",
    "wof:population":7
},
  "geometry": {"coordinates":[-107.90992,27.32215],"type":"Point"}
}