{
  "type": "Feature",
  "properties": {
    "gn:admin1_code":"13",
    "gn:admin2_code":"71.0",
    "gn:asciiname":"Los Frijolares",
    "gn:country_code":"MX",
    "gn:dem":1621,
    "gn:feature_class":"P",
    "gn:feature_code":"PPL",
    "gn:name":"Los Frijolares",
    "gn:population":7,
    "gn:timezone":"America/Mexico_City",
    "iso:country":"MX",
    "wof:name":"Los Frijolares",
    "wof:placetype":"locality",
    "wof:population":7
},
  "geometry": {"coordinates":[-98.95806,20.9725],"type":"Point"}
}