{
  "type": "Feature",
  "properties": {
    "gn:admin1_code":"10",
    "gn:admin2_code":"5.0",
    "gn:asciiname":"El Rosario [Granja]",
    "gn:country_code":"MX",
    "gn:dem":1869,
    "gn:feature_class":"P",
    "gn:feature_code":"PPL",
    "gn:name":"El Rosario [Granja]",
    "gn:population":4,
    "gn:timezone":"America/Monterrey",
    "iso:country":"MX",
    "wof:name":"El Rosario [Granja]",
    "wof:placetype":"locality",
    "wof:population":4
},
  "geometry": {"coordinates":[-104.55195000000001,23.97641],"type":"Point"}
}