{
  "type": "Feature",
  "properties": {
    "gn:admin1_code":"29",
    "gn:admin2_code":"33.0",
    "gn:asciiname":"Rancho Cruz Blanca (San Isidro)",
    "gn:country_code":"MX",
    "gn:dem":2398,
    "gn:feature_class":"P",
    "gn:feature_code":"PPL",
    "gn:name":"Rancho Cruz Blanca (San Isidro)",
    "gn:population":6,
    "gn:timezone":"America/Mexico_City",
    "iso:country":"MX",
    "wof:name":"Rancho Cruz Blanca (San Isidro)",
    "wof:placetype":"locality",
    "wof:population":6
},
  "geometry": {"coordinates":[-98.21225,19.35493],"type":"Point"}
}