{
  "type": "Feature",
  "properties": {
    "gn:admin1_code":"6",
    "gn:admin2_code":"60.0",
    "gn:asciiname":"San Pedro (Ejido San Rafael)",
    "gn:country_code":"MX",
    "gn:dem":1801,
    "gn:feature_class":"P",
    "gn:feature_code":"PPL",
    "gn:name":"San Pedro (Ejido San Rafael)",
    "gn:population":165,
    "gn:timezone":"America/Chihuahua",
    "iso:country":"MX",
    "wof:name":"San Pedro (Ejido San Rafael)",
    "wof:placetype":"locality",
    "wof:population":165
},
  "geometry": {"coordinates":[-105.77417,26.91583],"type":"Point"}
}