{
  "type": "Feature",
  "properties": {
    "gn:admin1_code":"6",
    "gn:admin2_code":"58.0",
    "gn:asciiname":"El Campo",
    "gn:country_code":"MX",
    "gn:dem":1244,
    "gn:feature_class":"P",
    "gn:feature_code":"PPL",
    "gn:name":"El Campo",
    "gn:population":1,
    "gn:timezone":"America/Chihuahua",
    "iso:country":"MX",
    "name:ceb_x_preferred":[
        "El Campo"
    ],
    "name:fra_x_preferred":[
        "El Campo"
    ],
    "name:ita_x_preferred":[
        "El campo"
    ],
    "name:pol_x_preferred":[
        "El Campo"
    ],
    "name:spa_x_preferred":[
        "El Campo"
    ],
    "name:swe_x_preferred":[
        "El Campo"
    ],
    "wof:name":"El Campo",
    "wof:placetype":"locality",
    "wof:population":1
},
  "geometry": {"coordinates":[-105.37389,27.57706],"type":"Point"}
}