{
  "type": "Feature",
  "properties": {
    "gn:admin1_code":"12",
    "gn:admin2_code":"45.0",
    "gn:asciiname":"Colotiopa",
    "gn:country_code":"MX",
    "gn:dem":1807,
    "gn:feature_class":"P",
    "gn:feature_code":"PPL",
    "gn:name":"Colotiopa",
    "gn:population":6,
    "gn:timezone":"America/Mexico_City",
    "iso:country":"MX",
    "wof:name":"Colotiopa",
    "wof:placetype":"locality",
    "wof:population":6
},
  "geometry": {"coordinates":[-98.77473000000001,17.86967000000001],"type":"Point"}
}