{
  "type": "Feature",
  "properties": {
    "gn:admin1_code":"21",
    "gn:admin2_code":"3.0",
    "gn:asciiname":"Colonia Allende",
    "gn:country_code":"MX",
    "gn:dem":1341,
    "gn:feature_class":"P",
    "gn:feature_code":"PPL",
    "gn:name":"Colonia Allende",
    "gn:population":134,
    "gn:timezone":"America/Mexico_City",
    "iso:country":"MX",
    "wof:name":"Colonia Allende",
    "wof:placetype":"locality",
    "wof:population":134
},
  "geometry": {"coordinates":[-98.00861,18.12111],"type":"Point"}
}