{
  "type": "Feature",
  "properties": {
    "gn:admin1_code":"30",
    "gn:admin2_code":"209",
    "gn:asciiname":"General Emiliano Zapata",
    "gn:country_code":"MX",
    "gn:dem":547,
    "gn:feature_class":"P",
    "gn:feature_code":"PPL",
    "gn:name":"General Emiliano Zapata",
    "gn:population":36,
    "gn:timezone":"America/Mexico_City",
    "iso:country":"MX",
    "wof:name":"General Emiliano Zapata",
    "wof:placetype":"locality",
    "wof:population":36
},
  "geometry": {"coordinates":[-94.81667,18.39583],"type":"Point"}
}