{
  "type": "Feature",
  "properties": {
    "gn:admin1_code":"13",
    "gn:admin2_code":"84",
    "gn:asciiname":"La Cebada",
    "gn:country_code":"MX",
    "gn:dem":2001,
    "gn:feature_class":"P",
    "gn:feature_code":"PPL",
    "gn:name":"La Cebada",
    "gn:population":17,
    "gn:timezone":"America/Mexico_City",
    "iso:country":"MX",
    "wof:name":"La Cebada",
    "wof:placetype":"locality",
    "wof:population":17
},
  "geometry": {"coordinates":[-99.38894999999999,20.64061],"type":"Point"}
}