{
  "type": "Feature",
  "properties": {
    "gn:admin1_code":"5",
    "gn:admin2_code":"32.0",
    "gn:asciiname":"Rosarito la Pinuela",
    "gn:country_code":"MX",
    "gn:dem":367,
    "gn:feature_class":"P",
    "gn:feature_code":"PPL",
    "gn:name":"Rosarito la Pi\u00f1uela",
    "gn:population":60,
    "gn:timezone":"America/Mexico_City",
    "iso:country":"MX",
    "name:und_x_variant":[
        "Rosarito la Pi\u00f1uela"
    ],
    "wof:name":"Rosarito la Pinuela",
    "wof:placetype":"locality",
    "wof:population":60
},
  "geometry": {"coordinates":[-92.57832999999999,15.38806],"type":"Point"}
}