{
  "type": "Feature",
  "properties": {
    "gn:admin1_code":"20.0",
    "gn:asciiname":"Zongolica Chilchotla",
    "gn:country_code":"MX",
    "gn:dem":1623,
    "gn:feature_class":"P",
    "gn:feature_code":"PPL",
    "gn:name":"Zongolica Chilchotla",
    "gn:population":0,
    "gn:timezone":"America/Mexico_City",
    "iso:country":"MX",
    "name:spa_x_preferred":[
        "Zongolica Chilchotla"
    ],
    "wof:name":"Zongolica Chilchotla",
    "wof:placetype":"locality"
},
  "geometry": {"coordinates":[-96.81153,18.19674],"type":"Point"}
}