{
  "type": "Feature",
  "properties": {
    "gn:admin1_code":"19",
    "gn:admin2_code":"38.0",
    "gn:asciiname":"Ladrillera",
    "gn:country_code":"MX",
    "gn:dem":440,
    "gn:feature_class":"P",
    "gn:feature_code":"PPL",
    "gn:name":"Ladrillera",
    "gn:population":0,
    "gn:timezone":"America/Monterrey",
    "iso:country":"MX",
    "wof:name":"Ladrillera",
    "wof:placetype":"locality"
},
  "geometry": {"coordinates":[-99.83194,25.17013],"type":"Point"}
}