{
  "type": "Feature",
  "properties": {
    "gn:admin1_code":"20",
    "gn:admin2_code":"20.0",
    "gn:asciiname":"Santa Maria Pueblo Nuevo",
    "gn:country_code":"MX",
    "gn:dem":770,
    "gn:feature_class":"P",
    "gn:feature_code":"PPL",
    "gn:name":"Santa Mar\u00eda Pueblo Nuevo",
    "gn:population":368,
    "gn:timezone":"America/Mexico_City",
    "iso:country":"MX",
    "name:und_x_variant":[
        "Santa Mar\u00eda Pueblo Nuevo",
        "Nuevo"
    ],
    "wof:name":"Santa Maria Pueblo Nuevo",
    "wof:placetype":"locality",
    "wof:population":368
},
  "geometry": {"coordinates":[-97.96638,17.04999],"type":"Point"}
}