{
  "type": "Feature",
  "properties": {
    "gn:gn_country":"MX",
    "gn:gn_fcode":"PPL",
    "gn:gn_pop":3490,
    "gn:population":3490,
    "iso:country":"MX",
    "name:ast_x_preferred":[
        "Pahuatl\u00e1n"
    ],
    "name:ceb_x_preferred":[
        "Pahuatl\u00e1n"
    ],
    "name:eng_x_preferred":[
        "Pahuatl\u00e1n Municipality"
    ],
    "name:epo_x_preferred":[
        "Pahuatl\u00e1n"
    ],
    "name:eus_x_preferred":[
        "Pahuatl\u00e1n"
    ],
    "name:fra_x_preferred":[
        "Pahuatl\u00e1n"
    ],
    "name:jpn_x_preferred":[
        "\u30d1\u30ef\u30c8\u30a5\u30e9\u30f3"
    ],
    "name:nah_x_preferred":[
        "Pahuatl\u0101n"
    ],
    "name:nld_x_preferred":[
        "Pahuatl\u00e1n"
    ],
    "name:nob_x_preferred":[
        "Pahuatl\u00e1n"
    ],
    "name:rus_x_preferred":[
        "\u041f\u0430\u0443\u0430\u0442\u043b\u0430\u043d"
    ],
    "name:spa_x_preferred":[
        "Pahuatl\u00e1n de Valle"
    ],
    "name:spa_x_variant":[
        "Pahuatl\u00e1n"
    ],
    "name:swe_x_preferred":[
        "Pahuatl\u00e1n"
    ],
    "name:unk_x_variant":[
        "Pahuatlan"
    ],
    "name:vie_x_preferred":[
        "Pahuatl\u00e1n"
    ],
    "qs_pg:aaroncc":"MX",
    "qs_pg:gn_country":"MX",
    "qs_pg:gn_fcode":"PPL",
    "qs_pg:gn_pop":3490,
    "qs_pg:name":"Pahuatl\u00e1n del Valle",
    "qs_pg:name_adm0":"M\u00e9xico",
    "qs_pg:name_adm1":"Puebla",
    "qs_pg:photos":189,
    "qs_pg:photos_1k":38,
    "qs_pg:photos_9k":1,
    "qs_pg:photos_9r":4,
    "qs_pg:photos_all":200,
    "qs_pg:photos_sr":4,
    "qs_pg:pop_sr":4,
    "qs_pg:qs_pg_placetype":"locality",
    "qs_pg:qs_pg_placetype_gp":"Town",
    "qs_pg:woe_adm0":23424900,
    "woe:adm0_id":23424900,
    "woe:name_adm0":"M\u00e9xico",
    "woe:name_adm1":"Puebla",
    "woe:placetype":"Town",
    "wof:name":"Pahuatl\u00e1n del Valle",
    "wof:placetype":"locality",
    "wof:population":3490
},
  "geometry": {"coordinates":[-98.15036000000001,20.27787],"type":"Point"}
}