{
  "type": "Feature",
  "properties": {
    "gn:admin1_code":"7",
    "gn:admin2_code":"33.0",
    "gn:asciiname":"Santana de Arriba",
    "gn:country_code":"MX",
    "gn:dem":1102,
    "gn:feature_class":"P",
    "gn:feature_code":"PPL",
    "gn:name":"Santana de Arriba",
    "gn:population":0,
    "gn:timezone":"America/Monterrey",
    "iso:country":"MX",
    "wof:name":"Santana de Arriba",
    "wof:placetype":"locality"
},
  "geometry": {"coordinates":[-103.17254,25.91065],"type":"Point"}
}