{
  "type": "Feature",
  "properties": {
    "gn:admin1_code":"30",
    "gn:admin2_code":"173.0",
    "gn:asciiname":"Colonia Ignacio Allende",
    "gn:country_code":"MX",
    "gn:dem":1190,
    "gn:feature_class":"P",
    "gn:feature_code":"PPL",
    "gn:name":"Colonia Ignacio Allende",
    "gn:population":106,
    "gn:timezone":"America/Mexico_City",
    "iso:country":"MX",
    "wof:name":"Colonia Ignacio Allende",
    "wof:placetype":"locality",
    "wof:population":106
},
  "geometry": {"coordinates":[-96.87472,18.72333],"type":"Point"}
}