{
  "type": "Feature",
  "properties": {
    "gn:admin1_code":"8",
    "gn:admin2_code":"9.0",
    "gn:asciiname":"Microondas",
    "gn:country_code":"MX",
    "gn:dem":20,
    "gn:feature_class":"P",
    "gn:feature_code":"PPL",
    "gn:name":"Microondas",
    "gn:population":4,
    "gn:timezone":"America/Mexico_City",
    "iso:country":"MX",
    "wof:name":"Microondas",
    "wof:placetype":"locality",
    "wof:population":4
},
  "geometry": {"coordinates":[-103.8125,18.82639],"type":"Point"}
}