{
  "type": "Feature",
  "properties": {
    "gn:admin1_code":"13",
    "gn:admin2_code":"71.0",
    "gn:asciiname":"El Sarro",
    "gn:country_code":"MX",
    "gn:dem":496,
    "gn:feature_class":"P",
    "gn:feature_code":"PPL",
    "gn:name":"El Sarro",
    "gn:population":0,
    "gn:timezone":"America/Mexico_City",
    "iso:country":"MX",
    "name:spa_x_preferred":[
        "El Sarro"
    ],
    "wof:name":"El Sarro",
    "wof:placetype":"locality"
},
  "geometry": {"coordinates":[-98.97199000000001,21.00383],"type":"Point"}
}