{
  "type": "Feature",
  "properties": {
    "gn:admin1_code":"2",
    "gn:admin2_code":"1.0",
    "gn:asciiname":"Familia Vera (Nuevo Uruapan)",
    "gn:country_code":"MX",
    "gn:dem":71,
    "gn:feature_class":"P",
    "gn:feature_code":"PPL",
    "gn:name":"Familia Vera (Nuevo Uruapan)",
    "gn:population":4,
    "gn:timezone":"America/Tijuana",
    "iso:country":"MX",
    "wof:name":"Familia Vera (Nuevo Uruapan)",
    "wof:placetype":"locality",
    "wof:population":4
},
  "geometry": {"coordinates":[-115.64749999999999,30.105],"type":"Point"}
}