{
  "type": "Feature",
  "properties": {
    "gn:admin1_code":"6",
    "gn:admin2_code":"29.0",
    "gn:asciiname":"Las Lajas",
    "gn:country_code":"MX",
    "gn:dem":1896,
    "gn:feature_class":"P",
    "gn:feature_code":"PPL",
    "gn:name":"Las Lajas",
    "gn:population":6,
    "gn:timezone":"America/Chihuahua",
    "iso:country":"MX",
    "name:bre_x_preferred":[
        "Las Lajas"
    ],
    "name:ceb_x_preferred":[
        "Las Lajas"
    ],
    "name:deu_x_preferred":[
        "Las Lajas"
    ],
    "name:fra_x_preferred":[
        "Las Lajas"
    ],
    "name:ita_x_preferred":[
        "Las Lajas"
    ],
    "name:lit_x_preferred":[
        "Las Lachasas"
    ],
    "name:nld_x_preferred":[
        "Las Lajas"
    ],
    "name:pol_x_preferred":[
        "Las Lajas"
    ],
    "name:spa_x_preferred":[
        "Las Lajas"
    ],
    "name:swe_x_preferred":[
        "Las Lajas"
    ],
    "wof:name":"Las Lajas",
    "wof:placetype":"locality",
    "wof:population":6
},
  "geometry": {"coordinates":[-107.48848,26.17439],"type":"Point"}
}