{
  "type": "Feature",
  "properties": {
    "gn:admin1_code":"10.0",
    "gn:admin2_code":"24.0",
    "gn:asciiname":"El Realito",
    "gn:country_code":"MX",
    "gn:dem":1651,
    "gn:feature_class":"P",
    "gn:feature_code":"PPL",
    "gn:name":"El Realito",
    "gn:population":0,
    "gn:timezone":"America/Monterrey",
    "iso:country":"MX",
    "wof:name":"El Realito",
    "wof:placetype":"locality"
},
  "geometry": {"coordinates":[-104.66667,25.16667],"type":"Point"}
}