{
  "type": "Feature",
  "properties": {
    "gn:admin1_code":"28.0",
    "gn:admin2_code":"3.0",
    "gn:asciiname":"Carboneras",
    "gn:country_code":"MX",
    "gn:dem":32,
    "gn:feature_class":"P",
    "gn:feature_code":"PPL",
    "gn:name":"Carboneras",
    "gn:population":32,
    "gn:timezone":"America/Monterrey",
    "iso:country":"MX",
    "name:spa_x_preferred":[
        "Carboneras"
    ],
    "wof:name":"Carboneras",
    "wof:placetype":"locality",
    "wof:population":32
},
  "geometry": {"coordinates":[-98.31111,22.54417],"type":"Point"}
}