{
  "type": "Feature",
  "properties": {
    "gn:admin1_code":"30",
    "gn:admin2_code":"123.0",
    "gn:asciiname":"El Silencio",
    "gn:country_code":"MX",
    "gn:dem":32,
    "gn:feature_class":"P",
    "gn:feature_code":"PPL",
    "gn:name":"El Silencio",
    "gn:population":5,
    "gn:timezone":"America/Mexico_City",
    "iso:country":"MX",
    "name:ceb_x_preferred":[
        "El Silencio"
    ],
    "name:spa_x_preferred":[
        "El Silencio"
    ],
    "name:swe_x_preferred":[
        "El Silencio"
    ],
    "wof:name":"El Silencio",
    "wof:placetype":"locality",
    "wof:population":5
},
  "geometry": {"coordinates":[-98.29306,21.91278],"type":"Point"}
}