{
  "type": "Feature",
  "properties": {
    "gn:admin1_code":"30",
    "gn:admin2_code":"69.0",
    "gn:asciiname":"Rafael Valenzuela",
    "gn:country_code":"MX",
    "gn:dem":37,
    "gn:feature_class":"P",
    "gn:feature_code":"PPL",
    "gn:name":"Rafael Valenzuela",
    "gn:population":0,
    "gn:timezone":"America/Mexico_City",
    "iso:country":"MX",
    "wof:name":"Rafael Valenzuela",
    "wof:placetype":"locality"
},
  "geometry": {"coordinates":[-97.12779999999999,20.40536],"type":"Point"}
}