{
  "type": "Feature",
  "properties": {
    "gn:admin1_code":"32.0",
    "gn:admin2_code":"17.0",
    "gn:asciiname":"Santa Maria Magdalena",
    "gn:country_code":"MX",
    "gn:dem":2375,
    "gn:feature_class":"P",
    "gn:feature_code":"PPL",
    "gn:name":"Santa Maria Magdalena",
    "gn:population":0,
    "gn:timezone":"America/Mexico_City",
    "iso:country":"MX",
    "name:spa_x_preferred":[
        "Santa Maria Magdalena"
    ],
    "wof:name":"Santa Maria Magdalena",
    "wof:placetype":"locality"
},
  "geometry": {"coordinates":[-102.55371,22.62775],"type":"Point"}
}