{
  "type": "Feature",
  "properties": {
    "gn:admin1_code":"32",
    "gn:admin2_code":"26.0",
    "gn:asciiname":"Villita",
    "gn:country_code":"MX",
    "gn:dem":1805,
    "gn:feature_class":"P",
    "gn:feature_code":"PPL",
    "gn:name":"Villita",
    "gn:population":0,
    "gn:timezone":"America/Mexico_City",
    "iso:country":"MX",
    "wof:name":"Villita",
    "wof:placetype":"locality"
},
  "geometry": {"coordinates":[-102.26667,24.01667],"type":"Point"}
}