{
  "type": "Feature",
  "properties": {
    "gn:admin1_code":"30.0",
    "gn:admin2_code":"158.0",
    "gn:asciiname":"San Isidro el Hular",
    "gn:country_code":"MX",
    "gn:dem":58,
    "gn:feature_class":"P",
    "gn:feature_code":"PPL",
    "gn:name":"San Isidro el Hular",
    "gn:population":15,
    "gn:timezone":"America/Mexico_City",
    "iso:country":"MX",
    "name:spa_x_preferred":[
        "San Isidro el Hular"
    ],
    "wof:name":"San Isidro el Hular",
    "wof:placetype":"locality",
    "wof:population":15
},
  "geometry": {"coordinates":[-97.05249999999999,20.31722],"type":"Point"}
}