{
  "type": "Feature",
  "properties": {
    "gn:admin1_code":"7",
    "gn:admin2_code":"34.0",
    "gn:asciiname":"Pena Blanca",
    "gn:country_code":"MX",
    "gn:dem":1334,
    "gn:feature_class":"P",
    "gn:feature_code":"PPL",
    "gn:name":"Pe\u00f1a Blanca",
    "gn:population":1,
    "gn:timezone":"America/Monterrey",
    "iso:country":"MX",
    "wof:name":"Pena Blanca",
    "wof:placetype":"locality",
    "wof:population":1
},
  "geometry": {"coordinates":[-103.68418,27.39067],"type":"Point"}
}