{
  "type": "Feature",
  "properties": {
    "gn:admin1_code":"32",
    "gn:admin2_code":"48",
    "gn:asciiname":"Cofradia del Norte (Santa Ines)",
    "gn:country_code":"MX",
    "gn:dem":1860,
    "gn:feature_class":"P",
    "gn:feature_code":"PPL",
    "gn:name":"Cofrad\u00eda del Norte (Santa In\u00e9s)",
    "gn:population":20,
    "gn:timezone":"America/Mexico_City",
    "iso:country":"MX",
    "name:und_x_variant":[
        "Cofrad\u00eda del Norte (Santa In\u00e9s)"
    ],
    "wof:name":"Cofradia del Norte (Santa Ines)",
    "wof:placetype":"locality",
    "wof:population":20
},
  "geometry": {"coordinates":[-103.22889000000001,21.90722],"type":"Point"}
}