{
  "type": "Feature",
  "properties": {
    "gn:admin1_code":"11",
    "gn:admin2_code":"43",
    "gn:asciiname":"Los Colorados",
    "gn:country_code":"MX",
    "gn:dem":1406,
    "gn:feature_class":"P",
    "gn:feature_code":"PPL",
    "gn:name":"Los Colorados",
    "gn:population":15,
    "gn:timezone":"America/Mexico_City",
    "iso:country":"MX",
    "name:deu_x_preferred":[
        "Los Colorados"
    ],
    "name:est_x_preferred":[
        "Los Colorados"
    ],
    "name:nld_x_preferred":[
        "Los Colorados"
    ],
    "name:pol_x_preferred":[
        "Los Colorados"
    ],
    "name:spa_x_preferred":[
        "Los Colorados"
    ],
    "name:ukr_x_preferred":[
        "Los Colorados"
    ],
    "wof:name":"Los Colorados",
    "wof:placetype":"locality",
    "wof:population":15
},
  "geometry": {"coordinates":[-100.11667,21.48611],"type":"Point"}
}