{
  "type": "Feature",
  "properties": {
    "gn:admin1_code":"20",
    "gn:admin2_code":"171.0",
    "gn:asciiname":"Agua de Golondrina",
    "gn:country_code":"MX",
    "gn:dem":764,
    "gn:feature_class":"P",
    "gn:feature_code":"PPL",
    "gn:name":"Agua de Golondrina",
    "gn:population":344,
    "gn:timezone":"America/Mexico_City",
    "iso:country":"MX",
    "wof:name":"Agua de Golondrina",
    "wof:placetype":"locality",
    "wof:population":344
},
  "geometry": {"coordinates":[-96.69083000000001,18.19667],"type":"Point"}
}