{
  "type": "Feature",
  "properties": {
    "gn:admin1_code":"26",
    "gn:admin2_code":"33.0",
    "gn:asciiname":"El Vigia",
    "gn:country_code":"MX",
    "gn:dem":8,
    "gn:feature_class":"P",
    "gn:feature_code":"PPL",
    "gn:name":"El Vig\u00eda",
    "gn:population":23,
    "gn:timezone":"America/Hermosillo",
    "iso:country":"MX",
    "name:spa_x_preferred":[
        "El Vig\u00eda"
    ],
    "wof:name":"El Vigia",
    "wof:placetype":"locality",
    "wof:population":23
},
  "geometry": {"coordinates":[-109.71583,26.85389],"type":"Point"}
}