{
  "type": "Feature",
  "properties": {
    "gn:admin1_code":"14",
    "gn:admin2_code":"106.0",
    "gn:asciiname":"Zenzantla",
    "gn:country_code":"MX",
    "gn:dem":799,
    "gn:feature_class":"P",
    "gn:feature_code":"PPL",
    "gn:name":"Zenzantla",
    "gn:population":0,
    "gn:timezone":"America/Mexico_City",
    "iso:country":"MX",
    "wof:name":"Zenzantla",
    "wof:placetype":"locality"
},
  "geometry": {"coordinates":[-104.07708,19.65839],"type":"Point"}
}