{
  "type": "Feature",
  "properties": {
    "gn:admin1_code":"14",
    "gn:admin2_code":"101.0",
    "gn:asciiname":"El Ocotillo",
    "gn:country_code":"MX",
    "gn:dem":1596,
    "gn:feature_class":"P",
    "gn:feature_code":"PPL",
    "gn:name":"El Ocotillo",
    "gn:population":178,
    "gn:timezone":"America/Mexico_City",
    "iso:country":"MX",
    "wof:name":"El Ocotillo",
    "wof:placetype":"locality",
    "wof:population":178
},
  "geometry": {"coordinates":[-103.20722000000001,20.60306],"type":"Point"}
}