{
  "type": "Feature",
  "properties": {
    "gn:admin1_code":"24",
    "gn:admin2_code":"41",
    "gn:asciiname":"Las Mesas (Rancho Santa Monica)",
    "gn:country_code":"MX",
    "gn:dem":46,
    "gn:feature_class":"P",
    "gn:feature_code":"PPL",
    "gn:name":"Las Mesas (Rancho Santa M\u00f3nica)",
    "gn:population":13,
    "gn:timezone":"America/Mexico_City",
    "iso:country":"MX",
    "name:und_x_variant":[
        "Las Mesas (Rancho Santa M\u00f3nica)"
    ],
    "wof:name":"Las Mesas (Rancho Santa Monica)",
    "wof:placetype":"locality",
    "wof:population":13
},
  "geometry": {"coordinates":[-98.84444000000001,21.77111],"type":"Point"}
}