{
  "type": "Feature",
  "properties": {
    "gn:admin1_code":"7",
    "gn:admin2_code":"30",
    "gn:asciiname":"Nicolas Dominguez",
    "gn:country_code":"MX",
    "gn:dem":1761,
    "gn:feature_class":"P",
    "gn:feature_code":"PPL",
    "gn:name":"Nicol\u00e1s Dom\u00ednguez",
    "gn:population":17,
    "gn:timezone":"America/Monterrey",
    "iso:country":"MX",
    "name:und_x_variant":[
        "Nicol\u00e1s Dom\u00ednguez"
    ],
    "wof:name":"Nicolas Dominguez",
    "wof:placetype":"locality",
    "wof:population":17
},
  "geometry": {"coordinates":[-101.27892,25.28892],"type":"Point"}
}