{
  "type": "Feature",
  "properties": {
    "gn:admin1_code":"26.0",
    "gn:admin2_code":"27.0",
    "gn:asciiname":"Polleras",
    "gn:country_code":"MX",
    "gn:dem":1123,
    "gn:feature_class":"P",
    "gn:feature_code":"PPL",
    "gn:name":"Polleras",
    "gn:population":0,
    "gn:timezone":"America/Hermosillo",
    "iso:country":"MX",
    "name:spa_x_preferred":[
        "Polleras"
    ],
    "wof:name":"Polleras",
    "wof:placetype":"locality"
},
  "geometry": {"coordinates":[-109.55036,30.91925],"type":"Point"}
}