{
  "type": "Feature",
  "properties": {
    "gn:admin1_code":"29",
    "gn:admin2_code":"30.0",
    "gn:asciiname":"La Pera",
    "gn:country_code":"MX",
    "gn:dem":2836,
    "gn:feature_class":"P",
    "gn:feature_code":"PPL",
    "gn:name":"La Pera",
    "gn:population":8,
    "gn:timezone":"America/Mexico_City",
    "iso:country":"MX",
    "name:ara_x_preferred":[
        "\u0644\u0627 \u0628\u064a\u0631\u0627"
    ],
    "name:arg_x_preferred":[
        "La Pera"
    ],
    "name:cat_x_preferred":[
        "La Pera"
    ],
    "name:ceb_x_preferred":[
        "La Pera"
    ],
    "name:eus_x_preferred":[
        "La Pera"
    ],
    "name:fas_x_preferred":[
        "\u0644\u0627 \u067e\u0631\u0627"
    ],
    "name:fra_x_preferred":[
        "La Pera"
    ],
    "name:hun_x_preferred":[
        "La Pera"
    ],
    "name:hye_x_preferred":[
        "\u053c\u0561 \u054a\u0565\u0580\u0561"
    ],
    "name:ita_x_preferred":[
        "La Pera"
    ],
    "name:kaz_x_preferred":[
        "\u041b\u0430-\u041f\u0435\u0440\u0430"
    ],
    "name:lat_x_preferred":[
        "La Pera"
    ],
    "name:msa_x_preferred":[
        "La Pera"
    ],
    "name:nld_x_preferred":[
        "La Pera"
    ],
    "name:oci_x_preferred":[
        "La Pera"
    ],
    "name:pol_x_preferred":[
        "La Pera"
    ],
    "name:por_x_preferred":[
        "La Pera"
    ],
    "name:ron_x_preferred":[
        "La Pera"
    ],
    "name:rus_x_preferred":[
        "\u041b\u0430-\u041f\u0435\u0440\u0430"
    ],
    "name:spa_x_preferred":[
        "La Pera"
    ],
    "name:sqi_x_preferred":[
        "La Pera"
    ],
    "name:swe_x_preferred":[
        "La Pera"
    ],
    "name:ukr_x_preferred":[
        "\u041b\u0430-\u041f\u0435\u0440\u0430"
    ],
    "name:urd_x_preferred":[
        "\u0644\u0627 \u067e\u06cc\u0631\u0627"
    ],
    "name:uzb_x_preferred":[
        "La Pera"
    ],
    "name:war_x_preferred":[
        "La Pera"
    ],
    "name:zho_x_preferred":[
        "\u62c9\u4f69\u62c9"
    ],
    "wof:name":"La Pera",
    "wof:placetype":"locality",
    "wof:population":8
},
  "geometry": {"coordinates":[-97.88144,19.46497],"type":"Point"}
}