{
  "type": "Feature",
  "properties": {
    "gn:admin1_code":"10.0",
    "gn:asciiname":"Rancho Amole",
    "gn:country_code":"MX",
    "gn:dem":2275,
    "gn:feature_class":"P",
    "gn:feature_code":"PPL",
    "gn:name":"Rancho Amole",
    "gn:population":0,
    "gn:timezone":"America/Monterrey",
    "iso:country":"MX",
    "name:und_x_variant":[
        "Amotes",
        "Amoles"
    ],
    "wof:name":"Rancho Amole",
    "wof:placetype":"locality"
},
  "geometry": {"coordinates":[-106.346,24.38014],"type":"Point"}
}