{
  "type": "Feature",
  "properties": {
    "gn:admin1_code":"26",
    "gn:admin2_code":"10.0",
    "gn:asciiname":"La Cueva",
    "gn:country_code":"MX",
    "gn:dem":1267,
    "gn:feature_class":"P",
    "gn:feature_code":"PPL",
    "gn:name":"La Cueva",
    "gn:population":0,
    "gn:timezone":"America/Hermosillo",
    "iso:country":"MX",
    "name:und_x_variant":[
        "Cuevas",
        "Las Cuevas"
    ],
    "wof:name":"La Cueva",
    "wof:placetype":"locality"
},
  "geometry": {"coordinates":[-108.7988,30.36383],"type":"Point"}
}