{
  "type": "Feature",
  "properties": {
    "gn:admin1_code":"30",
    "gn:admin2_code":"60",
    "gn:asciiname":"Ejido Empalizada",
    "gn:country_code":"MX",
    "gn:dem":104,
    "gn:feature_class":"P",
    "gn:feature_code":"PPL",
    "gn:name":"Ejido Empalizada",
    "gn:population":10,
    "gn:timezone":"America/Mexico_City",
    "iso:country":"MX",
    "wof:name":"Ejido Empalizada",
    "wof:placetype":"locality",
    "wof:population":10
},
  "geometry": {"coordinates":[-97.69806,21.37389],"type":"Point"}
}