{
  "type": "Feature",
  "properties": {
    "gn:admin1_code":"2.0",
    "gn:admin2_code":"3.0",
    "gn:asciiname":"Agua Grande",
    "gn:country_code":"MX",
    "gn:dem":1303,
    "gn:feature_class":"P",
    "gn:feature_code":"PPL",
    "gn:name":"Agua Grande",
    "gn:population":0,
    "gn:timezone":"America/Tijuana",
    "iso:country":"MX",
    "wof:name":"Agua Grande",
    "wof:placetype":"locality"
},
  "geometry": {"coordinates":[-116.02339000000001,32.43099],"type":"Point"}
}