{
  "type": "Feature",
  "properties": {
    "gn:admin1_code":"31.0",
    "gn:asciiname":"Kankabdzonot",
    "gn:country_code":"MX",
    "gn:dem":23,
    "gn:feature_class":"P",
    "gn:feature_code":"PPL",
    "gn:name":"Kankabdzonot",
    "gn:population":0,
    "gn:timezone":"America/Merida",
    "iso:country":"MX",
    "name:spa_x_preferred":[
        "Kankabdzonot"
    ],
    "wof:name":"Kankabdzonot",
    "wof:placetype":"locality"
},
  "geometry": {"coordinates":[-88.03204000000002,21.01639],"type":"Point"}
}