{
  "type": "Feature",
  "properties": {
    "gn:admin1_code":"10",
    "gn:admin2_code":"23",
    "gn:asciiname":"El Tunal",
    "gn:country_code":"MX",
    "gn:dem":1406,
    "gn:feature_class":"P",
    "gn:feature_code":"PPL",
    "gn:name":"El Tunal",
    "gn:population":22,
    "gn:timezone":"America/Monterrey",
    "iso:country":"MX",
    "wof:name":"El Tunal",
    "wof:placetype":"locality",
    "wof:population":22
},
  "geometry": {"coordinates":[-105.15246999999999,23.15358],"type":"Point"}
}