{
  "type": "Feature",
  "properties": {
    "gn:admin1_code":"26",
    "gn:admin2_code":"35.0",
    "gn:asciiname":"El Crucero",
    "gn:country_code":"MX",
    "gn:dem":827,
    "gn:feature_class":"P",
    "gn:feature_code":"PPL",
    "gn:name":"El Crucero",
    "gn:population":674,
    "gn:timezone":"America/Hermosillo",
    "iso:country":"MX",
    "wof:name":"El Crucero",
    "wof:placetype":"locality",
    "wof:population":674
},
  "geometry": {"coordinates":[-110.87222,30.77306],"type":"Point"}
}