{
  "type": "Feature",
  "properties": {
    "gn:admin1_code":"6",
    "gn:admin2_code":"56.0",
    "gn:asciiname":"La Cueva Ahumada",
    "gn:country_code":"MX",
    "gn:dem":2009,
    "gn:feature_class":"P",
    "gn:feature_code":"PPL",
    "gn:name":"La Cueva Ahumada",
    "gn:population":0,
    "gn:timezone":"America/Chihuahua",
    "iso:country":"MX",
    "name:spa_x_preferred":[
        "La Cueva Ahumada"
    ],
    "wof:name":"La Cueva Ahumada",
    "wof:placetype":"locality"
},
  "geometry": {"coordinates":[-106.53455,27.19932],"type":"Point"}
}