{
  "type": "Feature",
  "properties": {
    "gn:admin1_code":"16",
    "gn:admin2_code":"19",
    "gn:asciiname":"Los Chapilis",
    "gn:country_code":"MX",
    "gn:dem":1673,
    "gn:feature_class":"P",
    "gn:feature_code":"PPL",
    "gn:name":"Los Chapilis",
    "gn:population":43,
    "gn:timezone":"America/Mexico_City",
    "iso:country":"MX",
    "wof:name":"Los Chapilis",
    "wof:placetype":"locality",
    "wof:population":43
},
  "geometry": {"coordinates":[-102.71832999999999,19.67472],"type":"Point"}
}