{
  "type": "Feature",
  "properties": {
    "gn:admin1_code":"21",
    "gn:admin2_code":"115",
    "gn:asciiname":"El Entronque",
    "gn:country_code":"MX",
    "gn:dem":2162,
    "gn:feature_class":"P",
    "gn:feature_code":"PPL",
    "gn:name":"El Entronque",
    "gn:population":10,
    "gn:timezone":"America/Mexico_City",
    "iso:country":"MX",
    "wof:name":"El Entronque",
    "wof:placetype":"locality",
    "wof:population":10
},
  "geometry": {"coordinates":[-97.67534999999999,18.95766],"type":"Point"}
}