{
  "type": "Feature",
  "properties": {
    "gn:admin1_code":"14",
    "gn:admin2_code":"94.0",
    "gn:asciiname":"El Alamo (Los Alamos)",
    "gn:country_code":"MX",
    "gn:dem":1314,
    "gn:feature_class":"P",
    "gn:feature_code":"PPL",
    "gn:name":"El \u00c1lamo (Los \u00c1lamos)",
    "gn:population":8,
    "gn:timezone":"America/Mexico_City",
    "iso:country":"MX",
    "name:und_x_variant":[
        "El \u00c1lamo (Los \u00c1lamos)"
    ],
    "wof:name":"El Alamo (Los Alamos)",
    "wof:placetype":"locality",
    "wof:population":8
},
  "geometry": {"coordinates":[-103.68111,21.22583],"type":"Point"}
}