{
  "type": "Feature",
  "properties": {
    "gn:admin1_code":"6",
    "gn:admin2_code":"31",
    "gn:asciiname":"Huerta Escondida",
    "gn:country_code":"MX",
    "gn:dem":2092,
    "gn:feature_class":"P",
    "gn:feature_code":"PPL",
    "gn:name":"Huerta Escondida",
    "gn:population":11,
    "gn:timezone":"America/Chihuahua",
    "iso:country":"MX",
    "wof:name":"Huerta Escondida",
    "wof:placetype":"locality",
    "wof:population":11
},
  "geometry": {"coordinates":[-107.24496000000001,28.46056],"type":"Point"}
}