{
  "type": "Feature",
  "properties": {
    "gn:admin1_code":"19.0",
    "gn:admin2_code":"40.0",
    "gn:asciiname":"Rancho Bonito",
    "gn:country_code":"MX",
    "gn:dem":184,
    "gn:feature_class":"P",
    "gn:feature_code":"PPL",
    "gn:name":"Rancho Bonito",
    "gn:population":0,
    "gn:timezone":"America/Monterrey",
    "iso:country":"MX",
    "name:spa_x_preferred":[
        "Rancho Bonito"
    ],
    "wof:name":"Rancho Bonito",
    "wof:placetype":"locality"
},
  "geometry": {"coordinates":[-99.69087,26.49592],"type":"Point"}
}