{
  "type": "Feature",
  "properties": {
    "gn:admin1_code":"6",
    "gn:admin2_code":"27.0",
    "gn:asciiname":"Los Napuchis",
    "gn:country_code":"MX",
    "gn:dem":2234,
    "gn:feature_class":"P",
    "gn:feature_code":"PPL",
    "gn:name":"Los Napuchis",
    "gn:population":0,
    "gn:timezone":"America/Chihuahua",
    "iso:country":"MX",
    "name:spa_x_preferred":[
        "Los Napuchis"
    ],
    "name:und_x_variant":[
        "Rancho Napuchic"
    ],
    "wof:name":"Los Napuchis",
    "wof:placetype":"locality"
},
  "geometry": {"coordinates":[-107.51347,27.31702],"type":"Point"}
}