{
  "type": "Feature",
  "properties": {
    "gn:admin1_code":"5",
    "gn:admin2_code":"47.0",
    "gn:asciiname":"Amor de Dios",
    "gn:country_code":"MX",
    "gn:dem":1166,
    "gn:feature_class":"P",
    "gn:feature_code":"PPL",
    "gn:name":"Amor de Dios",
    "gn:population":103,
    "gn:timezone":"America/Mexico_City",
    "iso:country":"MX",
    "wof:name":"Amor de Dios",
    "wof:placetype":"locality",
    "wof:population":103
},
  "geometry": {"coordinates":[-92.79137,17.11587],"type":"Point"}
}