{
  "type": "Feature",
  "properties": {
    "gn:admin1_code":"30",
    "gn:admin2_code":"95.0",
    "gn:asciiname":"El Zapotal",
    "gn:country_code":"MX",
    "gn:dem":438,
    "gn:feature_class":"P",
    "gn:feature_code":"PPL",
    "gn:name":"El Zapotal",
    "gn:population":192,
    "gn:timezone":"America/Mexico_City",
    "iso:country":"MX",
    "name:fra_x_preferred":[
        "El Zapotal"
    ],
    "name:spa_x_preferred":[
        "El Zapotal"
    ],
    "wof:name":"El Zapotal",
    "wof:placetype":"locality",
    "wof:population":192
},
  "geometry": {"coordinates":[-96.63417,19.83472],"type":"Point"}
}