{
  "type": "Feature",
  "properties": {
    "gn:admin1_code":"7",
    "gn:admin2_code":"13.0",
    "gn:asciiname":"La Pasadita",
    "gn:country_code":"MX",
    "gn:dem":163,
    "gn:feature_class":"P",
    "gn:feature_code":"PPL",
    "gn:name":"La Pasadita",
    "gn:population":5,
    "gn:timezone":"America/Monterrey",
    "iso:country":"MX",
    "wof:name":"La Pasadita",
    "wof:placetype":"locality",
    "wof:population":5
},
  "geometry": {"coordinates":[-99.91839,27.85249],"type":"Point"}
}