{
  "type": "Feature",
  "properties": {
    "gn:admin1_code":"28",
    "gn:admin2_code":"19.0",
    "gn:asciiname":"El Chijol",
    "gn:country_code":"MX",
    "gn:dem":904,
    "gn:feature_class":"P",
    "gn:feature_code":"PPL",
    "gn:name":"El Chijol",
    "gn:population":0,
    "gn:timezone":"America/Monterrey",
    "iso:country":"MX",
    "name:spa_x_preferred":[
        "El Chijol"
    ],
    "wof:name":"El Chijol",
    "wof:placetype":"locality"
},
  "geometry": {"coordinates":[-98.44158,23.21861],"type":"Point"}
}