{
  "type": "Feature",
  "properties": {
    "gn:admin1_code":"26",
    "gn:admin2_code":"12.0",
    "gn:asciiname":"Tucuri",
    "gn:country_code":"MX",
    "gn:dem":28,
    "gn:feature_class":"P",
    "gn:feature_code":"PPL",
    "gn:name":"Tucuri",
    "gn:population":0,
    "gn:timezone":"America/Hermosillo",
    "iso:country":"MX",
    "name:spa_x_preferred":[
        "Tucuri"
    ],
    "wof:name":"Tucuri",
    "wof:placetype":"locality"
},
  "geometry": {"coordinates":[-110.05331,27.60018],"type":"Point"}
}