{
  "type": "Feature",
  "properties": {
    "gn:admin1_code":"6.0",
    "gn:admin2_code":"64.0",
    "gn:asciiname":"El Lopeno",
    "gn:country_code":"MX",
    "gn:dem":1599,
    "gn:feature_class":"P",
    "gn:feature_code":"PPL",
    "gn:name":"El Lope\u00f1o",
    "gn:population":14,
    "gn:timezone":"America/Chihuahua",
    "iso:country":"MX",
    "wof:name":"El Lopeno",
    "wof:placetype":"locality",
    "wof:population":14
},
  "geometry": {"coordinates":[-106.25776,27.13583],"type":"Point"}
}