{
  "type": "Feature",
  "properties": {
    "gn:admin1_code":"13",
    "gn:admin2_code":"57.0",
    "gn:asciiname":"Colonia los Patos",
    "gn:country_code":"MX",
    "gn:dem":2722,
    "gn:feature_class":"P",
    "gn:feature_code":"PPL",
    "gn:name":"Colonia los Patos",
    "gn:population":100,
    "gn:timezone":"America/Mexico_City",
    "iso:country":"MX",
    "wof:name":"Colonia los Patos",
    "wof:placetype":"locality",
    "wof:population":100
},
  "geometry": {"coordinates":[-98.37361,19.95333],"type":"Point"}
}