{
  "type": "Feature",
  "properties": {
    "gn:admin1_code":"13",
    "gn:admin2_code":"25.0",
    "gn:asciiname":"Tepetzintla",
    "gn:country_code":"MX",
    "gn:dem":168,
    "gn:feature_class":"P",
    "gn:feature_code":"PPL",
    "gn:name":"Tepetzintla",
    "gn:population":180,
    "gn:timezone":"America/Mexico_City",
    "iso:country":"MX",
    "name:spa_x_preferred":[
        "Tepetzintla"
    ],
    "wof:name":"Tepetzintla",
    "wof:placetype":"locality",
    "wof:population":180
},
  "geometry": {"coordinates":[-98.17870000000001,21.07566],"type":"Point"}
}