{
  "type": "Feature",
  "properties": {
    "gn:admin1_code":"20.0",
    "gn:admin2_code":"327.0",
    "gn:asciiname":"Bellavista",
    "gn:country_code":"MX",
    "gn:dem":151,
    "gn:feature_class":"P",
    "gn:feature_code":"PPL",
    "gn:name":"Bellavista",
    "gn:population":0,
    "gn:timezone":"America/Mexico_City",
    "iso:country":"MX",
    "name:spa_x_preferred":[
        "Bellavista"
    ],
    "wof:name":"Bellavista",
    "wof:placetype":"locality"
},
  "geometry": {"coordinates":[-94.24717,16.39594],"type":"Point"}
}