{
  "type": "Feature",
  "properties": {
    "iso:country":"MX",
    "qs_pg:aaroncc":"MX",
    "qs_pg:name":"Sierra de Alica",
    "qs_pg:name_adm0":"M\u00e9xico",
    "qs_pg:name_adm1":"Zacatecas",
    "qs_pg:photos":915,
    "qs_pg:photos_1k":185,
    "qs_pg:photos_9k":4,
    "qs_pg:photos_9r":6,
    "qs_pg:photos_all":915,
    "qs_pg:photos_sr":10,
    "qs_pg:pop_sr":0,
    "qs_pg:qs_pg_placetype":"neighbourhood",
    "qs_pg:qs_pg_placetype_gp":"Suburb",
    "qs_pg:woe_adm0":23424900,
    "woe:adm0_id":23424900,
    "woe:name_adm0":"M\u00e9xico",
    "woe:name_adm1":"Zacatecas",
    "woe:placetype":"Suburb",
    "wof:name":"Sierra de Alica",
    "wof:placetype":"neighbourhood"
},
  "geometry": {"coordinates":[-102.57505399999999,22.769454],"type":"Point"}
}