{
  "type": "Feature",
  "properties": {
    "gn:admin1_code":"19.0",
    "gn:asciiname":"Diez Hermanos",
    "gn:country_code":"MX",
    "gn:dem":372,
    "gn:feature_class":"P",
    "gn:feature_code":"PPL",
    "gn:name":"Diez Hermanos",
    "gn:population":0,
    "gn:timezone":"America/Monterrey",
    "iso:country":"MX",
    "name:spa_x_preferred":[
        "Diez Hermanos"
    ],
    "wof:name":"Diez Hermanos",
    "wof:placetype":"locality"
},
  "geometry": {"coordinates":[-99.56206,24.83778],"type":"Point"}
}