{
  "type": "Feature",
  "properties": {
    "gn:admin1_code":"26",
    "gn:admin2_code":"67.0",
    "gn:asciiname":"Bacapin",
    "gn:country_code":"MX",
    "gn:dem":1305,
    "gn:feature_class":"P",
    "gn:feature_code":"PPL",
    "gn:name":"Bacapin",
    "gn:population":0,
    "gn:timezone":"America/Hermosillo",
    "iso:country":"MX",
    "name:spa_x_preferred":[
        "Bacapin"
    ],
    "wof:name":"Bacapin",
    "wof:placetype":"locality"
},
  "geometry": {"coordinates":[-109.20263,30.2109],"type":"Point"}
}