{
  "type": "Feature",
  "properties": {
    "gn:admin1_code":"12",
    "gn:admin2_code":"19.0",
    "gn:asciiname":"Zicapa",
    "gn:country_code":"MX",
    "gn:dem":1029,
    "gn:feature_class":"P",
    "gn:feature_code":"PPL",
    "gn:name":"Zicapa",
    "gn:population":0,
    "gn:timezone":"America/Mexico_City",
    "iso:country":"MX",
    "name:spa_x_preferred":[
        "Zicapa"
    ],
    "wof:name":"Zicapa",
    "wof:placetype":"locality"
},
  "geometry": {"coordinates":[-99.04082,17.92255],"type":"Point"}
}