{
  "type": "Feature",
  "properties": {
    "gn:admin1_code":"28",
    "gn:admin2_code":"37.0",
    "gn:asciiname":"San Ricardo",
    "gn:country_code":"MX",
    "gn:dem":144,
    "gn:feature_class":"P",
    "gn:feature_code":"PPL",
    "gn:name":"San Ricardo",
    "gn:population":9,
    "gn:timezone":"America/Monterrey",
    "iso:country":"MX",
    "name:spa_x_preferred":[
        "San Ricardo"
    ],
    "wof:name":"San Ricardo",
    "wof:placetype":"locality",
    "wof:population":9
},
  "geometry": {"coordinates":[-97.91039000000001,23.31424],"type":"Point"}
}