{
  "type": "Feature",
  "properties": {
    "gn:admin1_code":"28",
    "gn:admin2_code":"6.0",
    "gn:asciiname":"La Verdolaga",
    "gn:country_code":"MX",
    "gn:dem":1578,
    "gn:feature_class":"P",
    "gn:feature_code":"PPL",
    "gn:name":"La Verdolaga",
    "gn:population":0,
    "gn:timezone":"America/Monterrey",
    "iso:country":"MX",
    "name:spa_x_preferred":[
        "La Verdolaga"
    ],
    "wof:name":"La Verdolaga",
    "wof:placetype":"locality"
},
  "geometry": {"coordinates":[-99.87193000000001,23.28245],"type":"Point"}
}