{
  "type": "Feature",
  "properties": {
    "gn:admin1_code":"30",
    "gn:admin2_code":"141",
    "gn:asciiname":"Jaime Ortiz",
    "gn:country_code":"MX",
    "gn:dem":265,
    "gn:feature_class":"P",
    "gn:feature_code":"PPL",
    "gn:name":"Jaime Ortiz",
    "gn:population":25,
    "gn:timezone":"America/Mexico_City",
    "iso:country":"MX",
    "wof:name":"Jaime Ortiz",
    "wof:placetype":"locality",
    "wof:population":25
},
  "geometry": {"coordinates":[-95.20332999999999,18.43528],"type":"Point"}
}