{
  "type": "Feature",
  "properties": {
    "gn:admin1_code":"5",
    "gn:admin2_code":"97.0",
    "gn:asciiname":"Las Ilusiones",
    "gn:country_code":"MX",
    "gn:dem":28,
    "gn:feature_class":"P",
    "gn:feature_code":"PPL",
    "gn:name":"Las Ilusiones",
    "gn:population":8,
    "gn:timezone":"America/Mexico_City",
    "iso:country":"MX",
    "wof:name":"Las Ilusiones",
    "wof:placetype":"locality",
    "wof:population":8
},
  "geometry": {"coordinates":[-93.73444000000001,16.045],"type":"Point"}
}