{
  "type": "Feature",
  "properties": {
    "gn:admin1_code":"16",
    "gn:admin2_code":"101.0",
    "gn:asciiname":"El Pinzan Gacho",
    "gn:country_code":"MX",
    "gn:dem":621,
    "gn:feature_class":"P",
    "gn:feature_code":"PPL",
    "gn:name":"El Pinz\u00e1n Gacho",
    "gn:population":0,
    "gn:timezone":"America/Mexico_City",
    "iso:country":"MX",
    "name:spa_x_preferred":[
        "El Pinz\u00e1n Gacho"
    ],
    "wof:name":"El Pinzan Gacho",
    "wof:placetype":"locality"
},
  "geometry": {"coordinates":[-100.84896000000001,19.23978],"type":"Point"}
}