{
  "type": "Feature",
  "properties": {
    "gn:admin1_code":"26.0",
    "gn:admin2_code":"55.0",
    "gn:asciiname":"Ejido Lagunitas",
    "gn:country_code":"MX",
    "gn:dem":21,
    "gn:feature_class":"P",
    "gn:feature_code":"PPL",
    "gn:name":"Ejido Lagunitas",
    "gn:population":0,
    "gn:timezone":"America/Hermosillo",
    "iso:country":"MX",
    "name:spa_x_preferred":[
        "Ejido Lagunitas"
    ],
    "name:und_x_variant":[
        "Ejido Lagunita",
        "Lagunitas",
        "Lagunita"
    ],
    "wof:name":"Ejido Lagunitas",
    "wof:placetype":"locality"
},
  "geometry": {"coordinates":[-114.89568,32.31956],"type":"Point"}
}