{
  "type": "Feature",
  "properties": {
    "gn:admin1_code":"24.0",
    "gn:admin2_code":"16.0",
    "gn:asciiname":"La Buena Tierra",
    "gn:country_code":"MX",
    "gn:dem":39,
    "gn:feature_class":"P",
    "gn:feature_code":"PPL",
    "gn:name":"La Buena Tierra",
    "gn:population":5,
    "gn:timezone":"America/Mexico_City",
    "iso:country":"MX",
    "name:spa_x_preferred":[
        "La Buena Tierra"
    ],
    "wof:name":"La Buena Tierra",
    "wof:placetype":"locality",
    "wof:population":5
},
  "geometry": {"coordinates":[-98.52056,22.20028],"type":"Point"}
}