{
  "type": "Feature",
  "properties": {
    "gn:admin1_code":"6",
    "gn:admin2_code":"42.0",
    "gn:asciiname":"La Division",
    "gn:country_code":"MX",
    "gn:dem":1615,
    "gn:feature_class":"P",
    "gn:feature_code":"PPL",
    "gn:name":"La Divisi\u00f3n",
    "gn:population":4,
    "gn:timezone":"America/Chihuahua",
    "iso:country":"MX",
    "name:und_x_variant":[
        "La Divisi\u00f3n"
    ],
    "wof:name":"La Division",
    "wof:placetype":"locality",
    "wof:population":4
},
  "geometry": {"coordinates":[-103.62961,28.58272],"type":"Point"}
}