{
  "type": "Feature",
  "properties": {
    "gn:admin1_code":"23",
    "gn:admin2_code":"2.0",
    "gn:asciiname":"El Corozo",
    "gn:country_code":"MX",
    "gn:dem":21,
    "gn:feature_class":"P",
    "gn:feature_code":"PPL",
    "gn:name":"El Corozo",
    "gn:population":2,
    "gn:timezone":"America/Cancun",
    "iso:country":"MX",
    "wof:name":"El Corozo",
    "wof:placetype":"locality",
    "wof:population":2
},
  "geometry": {"coordinates":[-88.50235000000001,19.26752],"type":"Point"}
}