{
  "type": "Feature",
  "properties": {
    "gn:admin1_code":"18",
    "gn:admin2_code":"9",
    "gn:asciiname":"La Mesa de la Pitayera",
    "gn:country_code":"MX",
    "gn:dem":247,
    "gn:feature_class":"P",
    "gn:feature_code":"PPL",
    "gn:name":"La Mesa de la Pitayera",
    "gn:population":12,
    "gn:timezone":"America/Mazatlan",
    "iso:country":"MX",
    "wof:name":"La Mesa de la Pitayera",
    "wof:placetype":"locality",
    "wof:population":12
},
  "geometry": {"coordinates":[-104.50972,21.94806],"type":"Point"}
}