{
  "type": "Feature",
  "properties": {
    "gn:admin1_code":"28.0",
    "gn:admin2_code":"27.0",
    "gn:asciiname":"Kilometro Diez",
    "gn:country_code":"MX",
    "gn:dem":147,
    "gn:feature_class":"P",
    "gn:feature_code":"PPL",
    "gn:name":"Kil\u00f3metro Diez",
    "gn:population":0,
    "gn:timezone":"America/Matamoros",
    "iso:country":"MX",
    "name:spa_x_preferred":[
        "Kil\u00f3metro Diez"
    ],
    "wof:name":"Kilometro Diez",
    "wof:placetype":"locality"
},
  "geometry": {"coordinates":[-99.53771999999999,27.41734000000001],"type":"Point"}
}