{
  "type": "Feature",
  "properties": {
    "gn:admin1_code":"30",
    "gn:admin2_code":"50.0",
    "gn:asciiname":"Colonia Dante Delgado Rannauro",
    "gn:country_code":"MX",
    "gn:dem":165,
    "gn:feature_class":"P",
    "gn:feature_code":"PPL",
    "gn:name":"Colonia Dante Delgado Rannauro",
    "gn:population":439,
    "gn:timezone":"America/Mexico_City",
    "iso:country":"MX",
    "wof:name":"Colonia Dante Delgado Rannauro",
    "wof:placetype":"locality",
    "wof:population":439
},
  "geometry": {"coordinates":[-97.57639,20.19111],"type":"Point"}
}