{
  "type": "Feature",
  "properties": {
    "gn:admin1_code":"16.0",
    "gn:admin2_code":"26.0",
    "gn:asciiname":"La Real",
    "gn:country_code":"MX",
    "gn:dem":1242,
    "gn:feature_class":"P",
    "gn:feature_code":"PPL",
    "gn:name":"La Real",
    "gn:population":0,
    "gn:timezone":"America/Mexico_City",
    "iso:country":"MX",
    "name:spa_x_preferred":[
        "La Real"
    ],
    "wof:name":"La Real",
    "wof:placetype":"locality"
},
  "geometry": {"coordinates":[-103.33266999999999,18.69946],"type":"Point"}
}