{
  "type": "Feature",
  "properties": {
    "gn:admin1_code":"20",
    "gn:admin2_code":"386.0",
    "gn:asciiname":"Quinicuena",
    "gn:country_code":"MX",
    "gn:dem":711,
    "gn:feature_class":"P",
    "gn:feature_code":"PPL",
    "gn:name":"Quinicuena",
    "gn:population":0,
    "gn:timezone":"America/Mexico_City",
    "iso:country":"MX",
    "name:spa_x_preferred":[
        "Quincuan\u00e1"
    ],
    "name:spa_x_variant":[
        "Quinicuena"
    ],
    "wof:name":"Quinicuena",
    "wof:placetype":"locality"
},
  "geometry": {"coordinates":[-97.52385,16.53101],"type":"Point"}
}