{
  "type": "Feature",
  "properties": {
    "gn:admin1_code":"30",
    "gn:admin2_code":"121",
    "gn:asciiname":"El Cuarenta",
    "gn:country_code":"MX",
    "gn:dem":4,
    "gn:feature_class":"P",
    "gn:feature_code":"PPL",
    "gn:name":"El Cuarenta",
    "gn:population":12,
    "gn:timezone":"America/Mexico_City",
    "iso:country":"MX",
    "wof:name":"El Cuarenta",
    "wof:placetype":"locality",
    "wof:population":12
},
  "geometry": {"coordinates":[-97.67889,21.65833],"type":"Point"}
}