{
  "type": "Feature",
  "properties": {
    "gn:admin1_code":"32.0",
    "gn:admin2_code":"31.0",
    "gn:asciiname":"Crucero Santa Teresa",
    "gn:country_code":"MX",
    "gn:dem":1919,
    "gn:feature_class":"P",
    "gn:feature_code":"PPL",
    "gn:name":"Crucero Santa Teresa",
    "gn:population":0,
    "gn:timezone":"America/Mexico_City",
    "iso:country":"MX",
    "name:spa_x_preferred":[
        "Crucero Santa Teresa"
    ],
    "wof:name":"Crucero Santa Teresa",
    "wof:placetype":"locality"
},
  "geometry": {"coordinates":[-103.48083,22.31713],"type":"Point"}
}