{
  "type": "Feature",
  "properties": {
    "gn:admin1_code":"5",
    "gn:admin2_code":"31",
    "gn:asciiname":"Sepelton",
    "gn:country_code":"MX",
    "gn:dem":950,
    "gn:feature_class":"P",
    "gn:feature_code":"PPL",
    "gn:name":"Sepelt\u00f3n",
    "gn:population":49,
    "gn:timezone":"America/Mexico_City",
    "iso:country":"MX",
    "name:und_x_variant":[
        "Sepelt\u00f3n"
    ],
    "wof:name":"Sepelton",
    "wof:placetype":"locality",
    "wof:population":49
},
  "geometry": {"coordinates":[-92.16222,17.06528],"type":"Point"}
}