{
  "type": "Feature",
  "properties": {
    "gn:admin1_code":"11.0",
    "gn:admin2_code":"2.0",
    "gn:asciiname":"Nuevo Chupicuaro",
    "gn:country_code":"MX",
    "gn:dem":1918,
    "gn:feature_class":"P",
    "gn:feature_code":"PPL",
    "gn:name":"Nuevo Chup\u00edcuaro",
    "gn:population":0,
    "gn:timezone":"America/Mexico_City",
    "iso:country":"MX",
    "name:cat_x_preferred":[
        "Chup\u00edcuaro"
    ],
    "name:deu_x_preferred":[
        "Chup\u00edcuaro-Kultur"
    ],
    "name:fra_x_preferred":[
        "Culture Chup\u00edcuaro"
    ],
    "name:spa_x_preferred":[
        "Nuevo Chup\u00edcuaro"
    ],
    "name:spa_x_variant":[
        "Chup\u00edcuaro"
    ],
    "name:und_x_variant":[
        "Chup\u00edcuaro"
    ],
    "wof:name":"Nuevo Chupicuaro",
    "wof:placetype":"locality"
},
  "geometry": {"coordinates":[-100.69156,20.0692],"type":"Point"}
}