{
  "type": "Feature",
  "properties": {
    "gn:admin1_code":"4.0",
    "gn:admin2_code":"3.0",
    "gn:asciiname":"Plan de Guadalupe",
    "gn:country_code":"MX",
    "gn:dem":18,
    "gn:feature_class":"P",
    "gn:feature_code":"PPL",
    "gn:name":"Plan de Guadalupe",
    "gn:population":0,
    "gn:timezone":"America/Merida",
    "iso:country":"MX",
    "name:spa_x_preferred":[
        "Plan de Guadalupe"
    ],
    "wof:name":"Plan de Guadalupe",
    "wof:placetype":"locality"
},
  "geometry": {"coordinates":[-91.36565,18.23494],"type":"Point"}
}