{
  "type": "Feature",
  "properties": {
    "gn:admin1_code":"16.0",
    "gn:admin2_code":"99.0",
    "gn:asciiname":"Cieneguita",
    "gn:country_code":"MX",
    "gn:dem":744,
    "gn:feature_class":"P",
    "gn:feature_code":"PPL",
    "gn:name":"Cieneguita",
    "gn:population":0,
    "gn:timezone":"America/Mexico_City",
    "iso:country":"MX",
    "name:spa_x_preferred":[
        "Cieneguita"
    ],
    "wof:name":"Cieneguita",
    "wof:placetype":"locality"
},
  "geometry": {"coordinates":[-100.47824,19.06353],"type":"Point"}
}