{
  "type": "Feature",
  "properties": {
    "gn:admin1_code":"10",
    "gn:admin2_code":"5.0",
    "gn:asciiname":"Morga",
    "gn:cc2":"MX",
    "gn:country_code":"MX",
    "gn:dem":1914,
    "gn:feature_class":"P",
    "gn:feature_code":"PPL",
    "gn:name":"Morga",
    "gn:population":0,
    "gn:timezone":"America/Monterrey",
    "iso:country":"MX",
    "name:und_x_variant":[
        "Andres de Morga",
        "Morga"
    ],
    "wof:name":"Morga",
    "wof:placetype":"locality"
},
  "geometry": {"coordinates":[-104.68333,24.05],"type":"Point"}
}