{
  "type": "Feature",
  "properties": {
    "gn:admin1_code":"5",
    "gn:admin2_code":"89.0",
    "gn:asciiname":"Conquista Campesina",
    "gn:country_code":"MX",
    "gn:dem":10,
    "gn:feature_class":"P",
    "gn:feature_code":"PPL",
    "gn:name":"Conquista Campesina",
    "gn:population":0,
    "gn:timezone":"America/Mexico_City",
    "iso:country":"MX",
    "name:spa_x_preferred":[
        "Conquista Campesina"
    ],
    "name:und_x_variant":[
        "La Nueva Conquista"
    ],
    "wof:name":"Conquista Campesina",
    "wof:placetype":"locality"
},
  "geometry": {"coordinates":[-92.32908,14.67163],"type":"Point"}
}