{
  "type": "Feature",
  "properties": {
    "gn:admin1_code":"6",
    "gn:admin2_code":"34.0",
    "gn:asciiname":"Vaqueteros",
    "gn:country_code":"MX",
    "gn:dem":1858,
    "gn:feature_class":"P",
    "gn:feature_code":"PPL",
    "gn:name":"Vaqueteros",
    "gn:population":0,
    "gn:timezone":"America/Chihuahua",
    "iso:country":"MX",
    "name:und_x_variant":[
        "Vaqueteyos",
        "Vaqueteros"
    ],
    "wof:name":"Vaqueteros",
    "wof:placetype":"locality"
},
  "geometry": {"coordinates":[-107.96116000000001,29.79239],"type":"Point"}
}