{
  "type": "Feature",
  "properties": {
    "gn:admin1_code":"5.0",
    "gn:asciiname":"San Nicolas de Bari",
    "gn:country_code":"MX",
    "gn:dem":608,
    "gn:feature_class":"P",
    "gn:feature_code":"PPL",
    "gn:name":"San Nicol\u00e1s de Bari",
    "gn:population":0,
    "gn:timezone":"America/Mexico_City",
    "iso:country":"MX",
    "name:spa_x_preferred":[
        "San Nicol\u00e1s de Bari"
    ],
    "wof:name":"San Nicolas de Bari",
    "wof:placetype":"locality"
},
  "geometry": {"coordinates":[-92.73905000000001,15.90395],"type":"Point"}
}