{
  "type": "Feature",
  "properties": {
    "gn:admin1_code":"16",
    "gn:admin2_code":"101.0",
    "gn:asciiname":"Puerto el Astillero",
    "gn:country_code":"MX",
    "gn:dem":948,
    "gn:feature_class":"P",
    "gn:feature_code":"PPL",
    "gn:name":"Puerto el Astillero",
    "gn:population":0,
    "gn:timezone":"America/Mexico_City",
    "iso:country":"MX",
    "name:spa_x_preferred":[
        "Puerto el Astillero"
    ],
    "wof:name":"Puerto el Astillero",
    "wof:placetype":"locality"
},
  "geometry": {"coordinates":[-100.90186,19.25683],"type":"Point"}
}