{
  "type": "Feature",
  "properties": {
    "gn:admin1_code":"30.0",
    "gn:admin2_code":"141.0",
    "gn:asciiname":"Adolfo Ruiz Cortines",
    "gn:country_code":"MX",
    "gn:dem":81,
    "gn:feature_class":"P",
    "gn:feature_code":"PPL",
    "gn:name":"Adolfo Ruiz Cortines",
    "gn:population":28,
    "gn:timezone":"America/Mexico_City",
    "iso:country":"MX",
    "name:spa_x_preferred":[
        "Adolfo Ruiz Cortines"
    ],
    "wof:name":"Adolfo Ruiz Cortines",
    "wof:placetype":"locality",
    "wof:population":28
},
  "geometry": {"coordinates":[-95.12778,18.64306],"type":"Point"}
}