{
  "type": "Feature",
  "properties": {
    "gn:admin1_code":"5",
    "gn:admin2_code":"97",
    "gn:asciiname":"Altamira",
    "gn:country_code":"MX",
    "gn:dem":27,
    "gn:feature_class":"P",
    "gn:feature_code":"PPL",
    "gn:name":"Altamira",
    "gn:population":9,
    "gn:timezone":"America/Mexico_City",
    "iso:country":"MX",
    "wof:name":"Altamira",
    "wof:placetype":"locality",
    "wof:population":9
},
  "geometry": {"coordinates":[-93.87639,16.155],"type":"Point"}
}