{
  "type": "Feature",
  "properties": {
    "gn:admin1_code":"30",
    "gn:admin2_code":"81",
    "gn:asciiname":"La Tranca",
    "gn:country_code":"MX",
    "gn:dem":1444,
    "gn:feature_class":"P",
    "gn:feature_code":"PPL",
    "gn:name":"La Tranca",
    "gn:population":22,
    "gn:timezone":"America/Mexico_City",
    "iso:country":"MX",
    "wof:name":"La Tranca",
    "wof:placetype":"locality",
    "wof:population":22
},
  "geometry": {"coordinates":[-97.14806,18.90528],"type":"Point"}
}