{
  "type": "Feature",
  "properties": {
    "gn:admin1_code":"15.0",
    "gn:admin2_code":"82.0",
    "gn:asciiname":"La Cabecera",
    "gn:country_code":"MX",
    "gn:dem":1279,
    "gn:feature_class":"P",
    "gn:feature_code":"PPL",
    "gn:name":"La Cabecera",
    "gn:population":0,
    "gn:timezone":"America/Mexico_City",
    "iso:country":"MX",
    "name:und_x_variant":[
        "Los Arrayanes"
    ],
    "wof:name":"La Cabecera",
    "wof:placetype":"locality"
},
  "geometry": {"coordinates":[-100.19546,18.89887],"type":"Point"}
}