{
  "type": "Feature",
  "properties": {
    "gn:admin1_code":"7.0",
    "gn:asciiname":"Majada los Tanquitos",
    "gn:country_code":"MX",
    "gn:dem":2445,
    "gn:feature_class":"P",
    "gn:feature_code":"PPL",
    "gn:name":"Majada los Tanquitos",
    "gn:population":0,
    "gn:timezone":"America/Mexico_City",
    "iso:country":"MX",
    "name:spa_x_preferred":[
        "Majada los Tanquitos"
    ],
    "wof:name":"Majada los Tanquitos",
    "wof:placetype":"locality"
},
  "geometry": {"coordinates":[-101.07183000000001,24.56596],"type":"Point"}
}