{
  "type": "Feature",
  "properties": {
    "gn:admin1_code":"30",
    "gn:admin2_code":"147.0",
    "gn:asciiname":"Huitzila",
    "gn:country_code":"MX",
    "gn:dem":2332,
    "gn:feature_class":"P",
    "gn:feature_code":"PPL",
    "gn:name":"Huitzila",
    "gn:population":0,
    "gn:timezone":"America/Mexico_City",
    "iso:country":"MX",
    "name:spa_x_preferred":[
        "Huitzila"
    ],
    "wof:name":"Huitzila",
    "wof:placetype":"locality"
},
  "geometry": {"coordinates":[-97.17169,18.72394],"type":"Point"}
}