{
  "type": "Feature",
  "properties": {
    "gn:admin1_code":"5",
    "gn:admin2_code":"31.0",
    "gn:asciiname":"El Naranjo Liquilwitz",
    "gn:country_code":"MX",
    "gn:dem":728,
    "gn:feature_class":"P",
    "gn:feature_code":"PPL",
    "gn:name":"El Naranjo Liquilwitz",
    "gn:population":132,
    "gn:timezone":"America/Mexico_City",
    "iso:country":"MX",
    "wof:name":"El Naranjo Liquilwitz",
    "wof:placetype":"locality",
    "wof:population":132
},
  "geometry": {"coordinates":[-91.99472,17.1025],"type":"Point"}
}