{
  "type": "Feature",
  "properties": {
    "gn:admin1_code":"26.0",
    "gn:admin2_code":"21.0",
    "gn:asciiname":"Cordova",
    "gn:country_code":"MX",
    "gn:dem":389,
    "gn:feature_class":"P",
    "gn:feature_code":"PPL",
    "gn:name":"C\u00f3rdova",
    "gn:population":0,
    "gn:timezone":"America/Hermosillo",
    "iso:country":"MX",
    "name:azb_x_preferred":[
        "\u06a9\u0648\u0631\u062f\u0648\u0648\u0627"
    ],
    "name:cat_x_preferred":[
        "Cordova"
    ],
    "name:ceb_x_preferred":[
        "Cordova"
    ],
    "name:deu_x_preferred":[
        "Cordova"
    ],
    "name:fra_x_preferred":[
        "Cordova"
    ],
    "name:glg_x_preferred":[
        "Cordova"
    ],
    "name:ita_x_preferred":[
        "Cordova"
    ],
    "name:nld_x_preferred":[
        "Cordova"
    ],
    "name:pnb_x_preferred":[
        "\u0642\u0631\u0637\u0628\u06c1"
    ],
    "name:pol_x_preferred":[
        "Cordova"
    ],
    "name:por_x_preferred":[
        "Cordova"
    ],
    "name:ron_x_preferred":[
        "Cordova"
    ],
    "name:srp_x_preferred":[
        "\u041a\u043e\u0440\u0434\u043e\u0432\u0430"
    ],
    "name:vol_x_preferred":[
        "Cordova"
    ],
    "name:zho_x_preferred":[
        "\u79d1\u723e\u591a\u74e6"
    ],
    "wof:name":"Cordova",
    "wof:placetype":"locality"
},
  "geometry": {"coordinates":[-110.33333,28.76667],"type":"Point"}
}