{
  "type": "Feature",
  "properties": {
    "gn:admin1_code":"26.0",
    "gn:admin2_code":"21.0",
    "gn:asciiname":"Cordova",
    "gn:country_code":"MX",
    "gn:dem":389,
    "gn:feature_class":"P",
    "gn:feature_code":"PPL",
    "gn:name":"C\u00f3rdova",
    "gn:population":0,
    "gn:timezone":"America/Hermosillo",
    "iso:country":"MX",
    "wof:name":"Cordova",
    "wof:placetype":"locality"
},
  "geometry": {"coordinates":[-110.33333,28.76667],"type":"Point"}
}