{
  "type": "Feature",
  "properties": {
    "gn:admin1_code":"26.0",
    "gn:admin2_code":"21.0",
    "gn:asciiname":"Cordova",
    "gn:country_code":"MX",
    "gn:dem":389,
    "gn:feature_class":"P",
    "gn:feature_code":"PPL",
    "gn:name":"C\u00f3rdova",
    "gn:population":0,
    "gn:timezone":"America/Hermosillo",
    "iso:country":"MX",
    "name:azb_x_preferred":[
        "\u06a9\u0648\u0631\u062f\u0648\u0648\u0627"
    ],
    "name:ben_x_preferred":[
        "\u0995\u09cb\u09b0\u09cd\u09a1\u09cb\u09ad\u09be"
    ],
    "name:cat_x_preferred":[
        "Cordova"
    ],
    "name:ceb_x_preferred":[
        "Cordova"
    ],
    "name:deu_x_preferred":[
        "Cordova"
    ],
    "name:ell_x_preferred":[
        "\u039a\u03cc\u03c1\u03bd\u03c4\u03bf\u03b2\u03b1"
    ],
    "name:fra_x_preferred":[
        "Cordova"
    ],
    "name:glg_x_preferred":[
        "Cordova"
    ],
    "name:heb_x_preferred":[
        "\u05e7\u05d5\u05e8\u05d3\u05d5\u05d1\u05d4"
    ],
    "name:hin_x_preferred":[
        "\u0915\u094b\u0930\u094d\u0921\u094b\u0935\u093e"
    ],
    "name:hun_x_preferred":[
        "Cordova"
    ],
    "name:ind_x_preferred":[
        "Cordova"
    ],
    "name:ita_x_preferred":[
        "Cordova"
    ],
    "name:kor_x_preferred":[
        "\ucf54\ub974\ub3c4\ubc14"
    ],
    "name:nld_x_preferred":[
        "Cordova"
    ],
    "name:pnb_x_preferred":[
        "\u0642\u0631\u0637\u0628\u06c1"
    ],
    "name:pol_x_preferred":[
        "Cordova"
    ],
    "name:por_x_preferred":[
        "Cordova"
    ],
    "name:ron_x_preferred":[
        "Cordova"
    ],
    "name:srp_x_preferred":[
        "\u041a\u043e\u0440\u0434\u043e\u0432\u0430"
    ],
    "name:tur_x_preferred":[
        "Cordova"
    ],
    "name:urd_x_preferred":[
        "\u06a9\u0627\u0631\u0688\u0648\u0648\u0627"
    ],
    "name:vie_x_preferred":[
        "Cordova"
    ],
    "name:vol_x_preferred":[
        "Cordova"
    ],
    "name:zho_x_preferred":[
        "\u79d1\u723e\u591a\u74e6"
    ],
    "wof:name":"Cordova",
    "wof:placetype":"locality"
},
  "geometry": {"coordinates":[-110.33333,28.76667],"type":"Point"}
}