{
  "type": "Feature",
  "properties": {
    "gn:admin1_code":"21.0",
    "gn:admin2_code":"127.0",
    "gn:asciiname":"Canada Sandia",
    "gn:country_code":"MX",
    "gn:dem":1362,
    "gn:feature_class":"P",
    "gn:feature_code":"PPL",
    "gn:name":"Ca\u00f1ada Sand\u00eda",
    "gn:population":0,
    "gn:timezone":"America/Mexico_City",
    "iso:country":"MX",
    "name:spa_x_preferred":[
        "Ca\u00f1ada Sand\u00eda"
    ],
    "wof:name":"Canada Sandia",
    "wof:placetype":"locality"
},
  "geometry": {"coordinates":[-97.99478000000001,18.1338],"type":"Point"}
}