{
  "type": "Feature",
  "properties": {
    "gn:admin1_code":"6.0",
    "gn:admin2_code":"26.0",
    "gn:asciiname":"Cuates de Abajo",
    "gn:country_code":"MX",
    "gn:dem":1717,
    "gn:feature_class":"P",
    "gn:feature_code":"PPL",
    "gn:name":"Cuates de Abajo",
    "gn:population":0,
    "gn:timezone":"America/Chihuahua",
    "iso:country":"MX",
    "name:und_x_variant":[
        "Los Cuates",
        "Los Cuates De Abajo",
        "Cuates de Abajo"
    ],
    "wof:name":"Cuates de Abajo",
    "wof:placetype":"locality"
},
  "geometry": {"coordinates":[-106.61266999999999,28.24339],"type":"Point"}
}