{
  "type": "Feature",
  "properties": {
    "gn:admin1_code":"30.0",
    "gn:asciiname":"El Suchil",
    "gn:country_code":"MX",
    "gn:dem":46,
    "gn:feature_class":"P",
    "gn:feature_code":"PPL",
    "gn:name":"El S\u00fachil",
    "gn:population":0,
    "gn:timezone":"America/Mexico_City",
    "iso:country":"MX",
    "name:spa_x_preferred":[
        "El S\u00fachil"
    ],
    "name:spa_x_variant":[
        "El Xuchitl"
    ],
    "wof:name":"El Suchil",
    "wof:placetype":"locality"
},
  "geometry": {"coordinates":[-97.52872000000001,20.78429],"type":"Point"}
}