{
  "type": "Feature",
  "properties": {
    "gn:admin1_code":"20",
    "gn:admin2_code":"482.0",
    "gn:asciiname":"Rancho del Santo",
    "gn:country_code":"MX",
    "gn:dem":211,
    "gn:feature_class":"P",
    "gn:feature_code":"PPL",
    "gn:name":"Rancho del Santo",
    "gn:population":5,
    "gn:timezone":"America/Mexico_City",
    "iso:country":"MX",
    "name:spa_x_preferred":[
        "Rancho del Santo"
    ],
    "wof:name":"Rancho del Santo",
    "wof:placetype":"locality",
    "wof:population":5
},
  "geometry": {"coordinates":[-98.17639,16.37222],"type":"Point"}
}