{
  "type": "Feature",
  "properties": {
    "gn:admin1_code":"6",
    "gn:admin2_code":"7",
    "gn:asciiname":"Santana",
    "gn:country_code":"MX",
    "gn:dem":2248,
    "gn:feature_class":"P",
    "gn:feature_code":"PPL",
    "gn:name":"Santana",
    "gn:population":22,
    "gn:timezone":"America/Chihuahua",
    "iso:country":"MX",
    "name:bpy_x_preferred":[
        "\u09b8\u09be\u09a8\u09cd\u099f\u09be\u09a8\u09be"
    ],
    "name:bre_x_preferred":[
        "Santana"
    ],
    "name:bul_x_preferred":[
        "\u0421\u0430\u043d\u0442\u0430\u043d\u0430"
    ],
    "name:cat_x_preferred":[
        "Santana"
    ],
    "name:ceb_x_preferred":[
        "Santana"
    ],
    "name:ces_x_preferred":[
        "Santana"
    ],
    "name:deu_x_preferred":[
        "Santana"
    ],
    "name:eus_x_preferred":[
        "Santana"
    ],
    "name:fas_x_preferred":[
        "\u0633\u0627\u0646\u062a\u0627\u0646\u0627"
    ],
    "name:fin_x_preferred":[
        "Santana"
    ],
    "name:fra_x_preferred":[
        "Santana"
    ],
    "name:glg_x_preferred":[
        "Santana"
    ],
    "name:heb_x_preferred":[
        "\u05e1\u05e0\u05d8\u05e0\u05d4"
    ],
    "name:ita_x_preferred":[
        "Santana"
    ],
    "name:jpn_x_preferred":[
        "\u30b5\u30f3\u30bf\u30ca"
    ],
    "name:kat_x_preferred":[
        "\u10e1\u10d0\u10dc\u10e2\u10d0\u10dc\u10d0"
    ],
    "name:kor_x_preferred":[
        "\uc0b0\ud0c0\ub098"
    ],
    "name:mlg_x_preferred":[
        "Santana"
    ],
    "name:nds_x_preferred":[
        "Santana"
    ],
    "name:nld_x_preferred":[
        "Santana"
    ],
    "name:nor_x_preferred":[
        "Santana"
    ],
    "name:pol_x_preferred":[
        "Santana"
    ],
    "name:por_x_preferred":[
        "Santana"
    ],
    "name:rus_x_preferred":[
        "\u0421\u0430\u043d\u0442\u0430\u043d\u0430"
    ],
    "name:sco_x_preferred":[
        "Santana"
    ],
    "name:slk_x_preferred":[
        "Santana"
    ],
    "name:spa_x_preferred":[
        "Santana"
    ],
    "name:srp_x_preferred":[
        "\u0421\u0430\u043d\u0442\u0430\u043d\u0430"
    ],
    "name:swe_x_preferred":[
        "Santana"
    ],
    "name:tur_x_preferred":[
        "Santana"
    ],
    "name:ukr_x_preferred":[
        "\u0421\u0430\u043d\u0442\u0430\u043d\u0430"
    ],
    "name:vie_x_preferred":[
        "Santana"
    ],
    "name:vol_x_preferred":[
        "Santana"
    ],
    "name:war_x_preferred":[
        "Santana"
    ],
    "wof:name":"Santana",
    "wof:placetype":"locality",
    "wof:population":22
},
  "geometry": {"coordinates":[-106.79503,26.99388],"type":"Point"}
}