{
  "type": "Feature",
  "properties": {
    "gn:admin1_code":"6",
    "gn:admin2_code":"7",
    "gn:asciiname":"Santana",
    "gn:country_code":"MX",
    "gn:dem":2248,
    "gn:feature_class":"P",
    "gn:feature_code":"PPL",
    "gn:name":"Santana",
    "gn:population":22,
    "gn:timezone":"America/Chihuahua",
    "iso:country":"MX",
    "wof:name":"Santana",
    "wof:placetype":"locality",
    "wof:population":22
},
  "geometry": {"coordinates":[-106.79503,26.99388],"type":"Point"}
}