{
  "type": "Feature",
  "properties": {
    "gn:admin1_code":"6",
    "gn:admin2_code":"29.0",
    "gn:asciiname":"El Tascate",
    "gn:country_code":"MX",
    "gn:dem":2598,
    "gn:feature_class":"P",
    "gn:feature_code":"PPL",
    "gn:name":"El T\u00e1scate",
    "gn:population":0,
    "gn:timezone":"America/Chihuahua",
    "iso:country":"MX",
    "name:spa_x_preferred":[
        "El T\u00e1scate"
    ],
    "wof:name":"El Tascate",
    "wof:placetype":"locality"
},
  "geometry": {"coordinates":[-106.79389999999999,26.0389],"type":"Point"}
}