{
  "type": "Feature",
  "properties": {
    "gn:admin1_code":"2",
    "gn:admin2_code":"1.0",
    "gn:asciiname":"Familia Jimenez Lozano",
    "gn:country_code":"MX",
    "gn:dem":12,
    "gn:feature_class":"P",
    "gn:feature_code":"PPL",
    "gn:name":"Familia Jim\u00e9nez Lozano",
    "gn:population":4,
    "gn:timezone":"America/Tijuana",
    "iso:country":"MX",
    "name:und_x_variant":[
        "Familia Jim\u00e9nez Lozano"
    ],
    "wof:name":"Familia Jimenez Lozano",
    "wof:placetype":"locality",
    "wof:population":4
},
  "geometry": {"coordinates":[-115.92638999999998,30.47917],"type":"Point"}
}