{
  "type": "Feature",
  "properties": {
    "gn:admin1_code":"31",
    "gn:admin2_code":"90",
    "gn:asciiname":"Los Cocos",
    "gn:country_code":"MX",
    "gn:dem":16,
    "gn:feature_class":"P",
    "gn:feature_code":"PPL",
    "gn:name":"Los Cocos",
    "gn:population":11,
    "gn:timezone":"America/Merida",
    "iso:country":"MX",
    "name:nld_x_preferred":[
        "Los Cocos"
    ],
    "name:por_x_preferred":[
        "Los Cocos"
    ],
    "name:spa_x_preferred":[
        "Los Cocos"
    ],
    "wof:name":"Los Cocos",
    "wof:placetype":"locality",
    "wof:population":11
},
  "geometry": {"coordinates":[-89.52944000000002,20.81167],"type":"Point"}
}