{
  "type": "Feature",
  "properties": {
    "gn:admin1_code":"31",
    "gn:admin2_code":"17.0",
    "gn:asciiname":"Santa Brigida",
    "gn:country_code":"MX",
    "gn:dem":27,
    "gn:feature_class":"P",
    "gn:feature_code":"PPL",
    "gn:name":"Santa Brigida",
    "gn:population":0,
    "gn:timezone":"America/Merida",
    "iso:country":"MX",
    "name:spa_x_preferred":[
        "Santa Brigida"
    ],
    "wof:name":"Santa Brigida",
    "wof:placetype":"locality"
},
  "geometry": {"coordinates":[-88.48434,20.59389],"type":"Point"}
}