{
  "type": "Feature",
  "properties": {
    "gn:admin1_code":"18",
    "gn:admin2_code":"19",
    "gn:asciiname":"Mesa de la Colonia",
    "gn:country_code":"MX",
    "gn:dem":1279,
    "gn:feature_class":"P",
    "gn:feature_code":"PPL",
    "gn:name":"Mesa de la Colonia",
    "gn:population":19,
    "gn:timezone":"America/Mazatlan",
    "iso:country":"MX",
    "wof:name":"Mesa de la Colonia",
    "wof:placetype":"locality",
    "wof:population":19
},
  "geometry": {"coordinates":[-104.12222,21.77583],"type":"Point"}
}