{
  "type": "Feature",
  "properties": {
    "gn:admin1_code":"20",
    "gn:admin2_code":"498",
    "gn:asciiname":"La Ceiba",
    "gn:country_code":"MX",
    "gn:dem":49,
    "gn:feature_class":"P",
    "gn:feature_code":"PPL",
    "gn:name":"La Ceiba",
    "gn:population":18,
    "gn:timezone":"America/Mexico_City",
    "iso:country":"MX",
    "wof:name":"La Ceiba",
    "wof:placetype":"locality",
    "wof:population":18
},
  "geometry": {"coordinates":[-95.35306,17.66528],"type":"Point"}
}