{
  "type": "Feature",
  "properties": {
    "gn:admin1_code":"20",
    "gn:admin2_code":"498",
    "gn:asciiname":"La Ceiba",
    "gn:country_code":"MX",
    "gn:dem":49,
    "gn:feature_class":"P",
    "gn:feature_code":"PPL",
    "gn:name":"La Ceiba",
    "gn:population":18,
    "gn:timezone":"America/Mexico_City",
    "iso:country":"MX",
    "name:afr_x_preferred":[
        "La Ceiba"
    ],
    "name:ara_x_preferred":[
        "\u0644\u0627 \u0633\u064a\u0628\u0627"
    ],
    "name:bel_x_preferred":[
        "\u041b\u0430-\u0421\u0435\u0439\u0431\u0430"
    ],
    "name:bul_x_preferred":[
        "\u041b\u0430 \u0421\u0435\u0439\u0431\u0430"
    ],
    "name:cat_x_preferred":[
        "La Ceiba"
    ],
    "name:dan_x_preferred":[
        "La Ceiba"
    ],
    "name:deu_x_preferred":[
        "La Ceiba"
    ],
    "name:epo_x_preferred":[
        "La Ceiba"
    ],
    "name:est_x_preferred":[
        "La Ceiba"
    ],
    "name:fas_x_preferred":[
        "\u0644\u0627 \u0633\u06cc\u0628\u0627"
    ],
    "name:fin_x_preferred":[
        "La Ceiba"
    ],
    "name:fra_x_preferred":[
        "La Ceiba"
    ],
    "name:heb_x_preferred":[
        "\u05dc\u05d4 \u05e1\u05d9\u05d9\u05d1\u05d4"
    ],
    "name:ita_x_preferred":[
        "La Ceiba"
    ],
    "name:jpn_x_preferred":[
        "\u30e9\u30fb\u30bb\u30a4\u30d0"
    ],
    "name:kor_x_preferred":[
        "\ub77c\uc138\uc774\ubc14"
    ],
    "name:lit_x_preferred":[
        "La Seiba"
    ],
    "name:mar_x_preferred":[
        "\u0932\u093e \u0938\u0948\u092c\u093e"
    ],
    "name:nld_x_preferred":[
        "La Ceiba"
    ],
    "name:nor_x_preferred":[
        "La Ceiba"
    ],
    "name:pol_x_preferred":[
        "La Ceiba"
    ],
    "name:por_x_preferred":[
        "La Ceiba"
    ],
    "name:que_x_preferred":[
        "La Ceiba"
    ],
    "name:rus_x_preferred":[
        "\u041b\u0430-\u0421\u0435\u0439\u0431\u0430"
    ],
    "name:spa_x_preferred":[
        "La Ceiba"
    ],
    "name:swe_x_preferred":[
        "La Ceiba"
    ],
    "name:tur_x_preferred":[
        "La Ceiba"
    ],
    "name:ukr_x_preferred":[
        "\u041b\u0430-\u0421\u0435\u0439\u0431\u0430"
    ],
    "name:urd_x_preferred":[
        "\u0644\u0627 \u0633\u06cc\u06cc\u0628\u0627"
    ],
    "name:vie_x_preferred":[
        "La Ceiba"
    ],
    "name:war_x_preferred":[
        "La Ceiba"
    ],
    "name:zho_x_preferred":[
        "\u62c9\u585e\u74e6"
    ],
    "wof:name":"La Ceiba",
    "wof:placetype":"locality",
    "wof:population":18
},
  "geometry": {"coordinates":[-95.35306,17.66528],"type":"Point"}
}