{
  "type": "Feature",
  "properties": {
    "gn:admin1_code":"11.0",
    "gn:admin2_code":"30.0",
    "gn:asciiname":"La Deseada",
    "gn:country_code":"MX",
    "gn:dem":2059,
    "gn:feature_class":"P",
    "gn:feature_code":"PPL",
    "gn:name":"La Deseada",
    "gn:population":0,
    "gn:timezone":"America/Mexico_City",
    "iso:country":"MX",
    "name:spa_x_preferred":[
        "La Deseada"
    ],
    "wof:name":"La Deseada",
    "wof:placetype":"locality"
},
  "geometry": {"coordinates":[-101.23598,21.32249],"type":"Point"}
}