{
  "type": "Feature",
  "properties": {
    "gn:admin1_code":"4.0",
    "gn:admin2_code":"3.0",
    "gn:asciiname":"Las Granjas",
    "gn:country_code":"MX",
    "gn:dem":7,
    "gn:feature_class":"P",
    "gn:feature_code":"PPL",
    "gn:name":"Las Granjas",
    "gn:population":0,
    "gn:timezone":"America/Merida",
    "iso:country":"MX",
    "name:spa_x_preferred":[
        "Coconito"
    ],
    "name:spa_x_variant":[
        "Las Granjas",
        "El Caimito"
    ],
    "wof:name":"Las Granjas",
    "wof:placetype":"locality"
},
  "geometry": {"coordinates":[-91.5925,18.15321],"type":"Point"}
}