{
  "type": "Feature",
  "properties": {
    "gn:admin1_code":"17",
    "gn:admin2_code":"29.0",
    "gn:asciiname":"Colonia Campo la Providencia",
    "gn:country_code":"MX",
    "gn:dem":1239,
    "gn:feature_class":"P",
    "gn:feature_code":"PPL",
    "gn:name":"Colonia Campo la Providencia",
    "gn:population":103,
    "gn:timezone":"America/Mexico_City",
    "iso:country":"MX",
    "wof:name":"Colonia Campo la Providencia",
    "wof:placetype":"locality",
    "wof:population":103
},
  "geometry": {"coordinates":[-99.04277999999999,18.91944],"type":"Point"}
}