{
  "type": "Feature",
  "properties": {
    "gn:admin1_code":"20",
    "gn:admin2_code":"38",
    "gn:asciiname":"Tras del Cerro",
    "gn:country_code":"MX",
    "gn:dem":1503,
    "gn:feature_class":"P",
    "gn:feature_code":"PPL",
    "gn:name":"Tras del Cerro",
    "gn:population":21,
    "gn:timezone":"America/Mexico_City",
    "iso:country":"MX",
    "wof:name":"Tras del Cerro",
    "wof:placetype":"locality",
    "wof:population":21
},
  "geometry": {"coordinates":[-96.14111,17.16832999999999],"type":"Point"}
}