{
  "type": "Feature",
  "properties": {
    "gn:admin1_code":"19.0",
    "gn:asciiname":"La Llanura Infinita",
    "gn:country_code":"MX",
    "gn:dem":497,
    "gn:feature_class":"P",
    "gn:feature_code":"PPL",
    "gn:name":"La Llanura Infinita",
    "gn:population":0,
    "gn:timezone":"America/Monterrey",
    "iso:country":"MX",
    "name:spa_x_preferred":[
        "La Llanura Infinita"
    ],
    "wof:name":"La Llanura Infinita",
    "wof:placetype":"locality"
},
  "geometry": {"coordinates":[-100.3245,25.85324],"type":"Point"}
}