{
  "type": "Feature",
  "properties": {
    "gn:admin1_code":"20",
    "gn:admin2_code":"171.0",
    "gn:asciiname":"Cerro de Maiz",
    "gn:country_code":"MX",
    "gn:dem":1145,
    "gn:feature_class":"P",
    "gn:feature_code":"PPL",
    "gn:name":"Cerro de Ma\u00edz",
    "gn:population":79,
    "gn:timezone":"America/Mexico_City",
    "iso:country":"MX",
    "name:und_x_variant":[
        "Cerro de Ma\u00edz"
    ],
    "wof:name":"Cerro de Maiz",
    "wof:placetype":"locality",
    "wof:population":79
},
  "geometry": {"coordinates":[-96.7175,18.12778],"type":"Point"}
}