{
  "type": "Feature",
  "properties": {
    "gn:admin1_code":"30",
    "gn:admin2_code":"201.0",
    "gn:asciiname":"Nepopoalco",
    "gn:country_code":"MX",
    "gn:dem":1145,
    "gn:feature_class":"P",
    "gn:feature_code":"PPL",
    "gn:name":"Nepopoalco",
    "gn:population":205,
    "gn:timezone":"America/Mexico_City",
    "iso:country":"MX",
    "wof:name":"Nepopoalco",
    "wof:placetype":"locality",
    "wof:population":205
},
  "geometry": {"coordinates":[-96.98999999999999,18.68306],"type":"Point"}
}