{
  "type": "Feature",
  "properties": {
    "gn:admin1_code":"26",
    "gn:admin2_code":"30.0",
    "gn:asciiname":"San Roberto",
    "gn:country_code":"MX",
    "gn:dem":58,
    "gn:feature_class":"P",
    "gn:feature_code":"PPL",
    "gn:name":"San Roberto",
    "gn:population":4,
    "gn:timezone":"America/Hermosillo",
    "iso:country":"MX",
    "name:ara_x_preferred":[
        "\u0633\u0627\u0646 \u0631\u0648\u0628\u064a\u0631\u062a\u0648"
    ],
    "name:azb_x_preferred":[
        "\u0633\u0627\u0646 \u0631\u0648\u0628\u0631\u062a\u0648"
    ],
    "name:bcl_x_preferred":[
        "San Roberto"
    ],
    "name:bul_x_preferred":[
        "\u0421\u0430\u043d \u0420\u043e\u0431\u0435\u0440\u0442\u043e"
    ],
    "name:ceb_x_preferred":[
        "San Roberto"
    ],
    "name:deu_x_preferred":[
        "San Roberto"
    ],
    "name:epo_x_preferred":[
        "San Roberto"
    ],
    "name:eus_x_preferred":[
        "San Roberto"
    ],
    "name:fas_x_preferred":[
        "\u0633\u0627\u0646 \u0631\u0648\u0628\u0631\u062a\u0648"
    ],
    "name:fra_x_preferred":[
        "San Roberto"
    ],
    "name:hun_x_preferred":[
        "San Roberto"
    ],
    "name:hye_x_preferred":[
        "\u054d\u0561\u0576 \u054c\u0578\u0562\u0565\u0580\u057f\u0578"
    ],
    "name:ina_x_preferred":[
        "San Roberto"
    ],
    "name:ita_x_preferred":[
        "San Roberto"
    ],
    "name:jpn_x_preferred":[
        "\u30b5\u30f3\u30fb\u30ed\u30d9\u30eb\u30c8"
    ],
    "name:kaz_x_preferred":[
        "\u0421\u0430\u043d-\u0420\u043e\u0431\u0435\u0440\u0442\u043e"
    ],
    "name:lat_x_preferred":[
        "Fanum Sancti Ruberti"
    ],
    "name:lmo_x_preferred":[
        "San Roberto"
    ],
    "name:msa_x_preferred":[
        "San Roberto"
    ],
    "name:nap_x_preferred":[
        "San Roberto"
    ],
    "name:nld_x_preferred":[
        "San Roberto"
    ],
    "name:pms_x_preferred":[
        "San Roberto"
    ],
    "name:pol_x_preferred":[
        "San Roberto"
    ],
    "name:por_x_preferred":[
        "San Roberto"
    ],
    "name:ron_x_preferred":[
        "San Roberto"
    ],
    "name:rus_x_preferred":[
        "\u0421\u0430\u043d-\u0420\u043e\u0431\u0435\u0440\u0442\u043e"
    ],
    "name:scn_x_preferred":[
        "San Rubertu"
    ],
    "name:spa_x_preferred":[
        "San Roberto"
    ],
    "name:srp_x_preferred":[
        "\u0421\u0430\u043d \u0420\u043e\u0431\u0435\u0440\u0442\u043e"
    ],
    "name:ukr_x_preferred":[
        "\u0421\u0430\u043d-\u0420\u043e\u0431\u0435\u0440\u0442\u043e"
    ],
    "name:uzb_x_preferred":[
        "San Roberto"
    ],
    "name:vie_x_preferred":[
        "San Roberto"
    ],
    "name:vol_x_preferred":[
        "San Roberto"
    ],
    "name:war_x_preferred":[
        "San Roberto"
    ],
    "name:zho_x_preferred":[
        "\u5723\u7f57\u8d1d\u5c14\u6258"
    ],
    "wof:name":"San Roberto",
    "wof:placetype":"locality",
    "wof:population":4
},
  "geometry": {"coordinates":[-111.77361000000001,29.14],"type":"Point"}
}