{
  "type": "Feature",
  "properties": {
    "gn:admin1_code":"30.0",
    "gn:admin2_code":"161.0",
    "gn:asciiname":"Los Pichones",
    "gn:country_code":"MX",
    "gn:dem":97,
    "gn:feature_class":"P",
    "gn:feature_code":"PPL",
    "gn:name":"Los Pichones",
    "gn:population":30,
    "gn:timezone":"America/Mexico_City",
    "iso:country":"MX",
    "name:spa_x_preferred":[
        "Los Pichones"
    ],
    "wof:name":"Los Pichones",
    "wof:placetype":"locality",
    "wof:population":30
},
  "geometry": {"coordinates":[-98.24917000000001,21.56028],"type":"Point"}
}