{
  "type": "Feature",
  "properties": {
    "gn:admin1_code":"32",
    "gn:admin2_code":"51.0",
    "gn:asciiname":"Santa Cecilia",
    "gn:country_code":"MX",
    "gn:dem":1963,
    "gn:feature_class":"P",
    "gn:feature_code":"PPL",
    "gn:name":"Santa Cecilia",
    "gn:population":6,
    "gn:timezone":"America/Mexico_City",
    "iso:country":"MX",
    "wof:name":"Santa Cecilia",
    "wof:placetype":"locality",
    "wof:population":6
},
  "geometry": {"coordinates":[-102.17917,23.45722],"type":"Point"}
}