{
  "type": "Feature",
  "properties": {
    "gn:admin1_code":"6",
    "gn:admin2_code":"52.0",
    "gn:asciiname":"Pozo El Iman",
    "gn:country_code":"MX",
    "gn:dem":1294,
    "gn:feature_class":"P",
    "gn:feature_code":"PPL",
    "gn:name":"Pozo El Im\u00e1n",
    "gn:population":0,
    "gn:timezone":"America/Ojinaga",
    "iso:country":"MX",
    "name:spa_x_preferred":[
        "Pozo El Im\u00e1n"
    ],
    "name:und_x_variant":[
        "Rancho Pozo de la Iman"
    ],
    "wof:name":"Pozo El Iman",
    "wof:placetype":"locality"
},
  "geometry": {"coordinates":[-104.52634999999999,28.95074],"type":"Point"}
}