{
  "type": "Feature",
  "properties": {
    "gn:admin1_code":"6",
    "gn:admin2_code":"20.0",
    "gn:asciiname":"Corral de Piedras",
    "gn:country_code":"MX",
    "gn:dem":471,
    "gn:feature_class":"P",
    "gn:feature_code":"PPL",
    "gn:name":"Corral de Piedras",
    "gn:population":0,
    "gn:timezone":"America/Chihuahua",
    "iso:country":"MX",
    "name:spa_x_preferred":[
        "Corral de Piedras"
    ],
    "wof:name":"Corral de Piedras",
    "wof:placetype":"locality"
},
  "geometry": {"coordinates":[-108.56904,27.42849],"type":"Point"}
}