{
  "type": "Feature",
  "properties": {
    "gn:admin1_code":"30",
    "gn:admin2_code":"102.0",
    "gn:asciiname":"Rincon del Diablo",
    "gn:country_code":"MX",
    "gn:dem":97,
    "gn:feature_class":"P",
    "gn:feature_code":"PPL",
    "gn:name":"Rinc\u00f3n del Diablo",
    "gn:population":6,
    "gn:timezone":"America/Mexico_City",
    "iso:country":"MX",
    "name:und_x_variant":[
        "Rinc\u00f3n del Diablo"
    ],
    "wof:name":"Rincon del Diablo",
    "wof:placetype":"locality",
    "wof:population":6
},
  "geometry": {"coordinates":[-97.07917,20.11472],"type":"Point"}
}