{
  "type": "Feature",
  "properties": {
    "gn:admin1_code":"21",
    "gn:admin2_code":"71.0",
    "gn:asciiname":"Tzahuinco",
    "gn:country_code":"MX",
    "gn:dem":1320,
    "gn:feature_class":"P",
    "gn:feature_code":"PPL",
    "gn:name":"Tzahuinco",
    "gn:population":704,
    "gn:timezone":"America/Mexico_City",
    "iso:country":"MX",
    "wof:name":"Tzahuinco",
    "wof:placetype":"locality",
    "wof:population":704
},
  "geometry": {"coordinates":[-97.99799,20.2021],"type":"Point"}
}