{
  "type": "Feature",
  "properties": {
    "gn:admin1_code":"30",
    "gn:admin2_code":"9.0",
    "gn:asciiname":"Monte Verde de la Tasajera",
    "gn:country_code":"MX",
    "gn:dem":746,
    "gn:feature_class":"P",
    "gn:feature_code":"PPL",
    "gn:name":"Monte Verde de la Tasajera",
    "gn:population":9,
    "gn:timezone":"America/Mexico_City",
    "iso:country":"MX",
    "wof:name":"Monte Verde de la Tasajera",
    "wof:placetype":"locality",
    "wof:population":9
},
  "geometry": {"coordinates":[-96.62972000000001,19.71583],"type":"Point"}
}