{
  "type": "Feature",
  "properties": {
    "gn:admin1_code":"6.0",
    "gn:admin2_code":"40.0",
    "gn:asciiname":"Puerto las Tunas",
    "gn:country_code":"MX",
    "gn:dem":1738,
    "gn:feature_class":"P",
    "gn:feature_code":"PPL",
    "gn:name":"Puerto las Tunas",
    "gn:population":0,
    "gn:timezone":"America/Chihuahua",
    "iso:country":"MX",
    "name:spa_x_preferred":[
        "Puerto las Tunas"
    ],
    "wof:name":"Puerto las Tunas",
    "wof:placetype":"locality"
},
  "geometry": {"coordinates":[-108.50440999999999,29.23443],"type":"Point"}
}