{
  "type": "Feature",
  "properties": {
    "gn:admin1_code":"16.0",
    "gn:admin2_code":"10.0",
    "gn:asciiname":"La Fierreria",
    "gn:country_code":"MX",
    "gn:dem":1239,
    "gn:feature_class":"P",
    "gn:feature_code":"PPL",
    "gn:name":"La Fierrer\u00eda",
    "gn:population":0,
    "gn:timezone":"America/Mexico_City",
    "iso:country":"MX",
    "name:spa_x_preferred":[
        "La Fierrer\u00eda"
    ],
    "name:spa_x_variant":[
        "La Ferrer\u00eda"
    ],
    "wof:name":"La Fierreria",
    "wof:placetype":"locality"
},
  "geometry": {"coordinates":[-102.43476,18.32747],"type":"Point"}
}