{
  "type": "Feature",
  "properties": {
    "gn:admin1_code":"32",
    "gn:admin2_code":"13",
    "gn:asciiname":"Buenaventura",
    "gn:country_code":"MX",
    "gn:dem":2120,
    "gn:feature_class":"P",
    "gn:feature_code":"PPL",
    "gn:name":"Buenaventura",
    "gn:population":18,
    "gn:timezone":"America/Mexico_City",
    "iso:country":"MX",
    "name:cat_x_preferred":[
        "Buenaventura"
    ],
    "name:ceb_x_preferred":[
        "Buenaventura"
    ],
    "name:deu_x_preferred":[
        "Buenaventura"
    ],
    "name:fin_x_preferred":[
        "Buenaventura"
    ],
    "name:fra_x_preferred":[
        "Buenaventura"
    ],
    "name:heb_x_preferred":[
        "\u05d1\u05d5\u05d0\u05e0\u05d5\u05d5\u05e0\u05d8\u05d5\u05e8\u05d4"
    ],
    "name:hun_x_preferred":[
        "Buenaventura"
    ],
    "name:ita_x_preferred":[
        "Buenaventura"
    ],
    "name:mlg_x_preferred":[
        "Buenaventura"
    ],
    "name:nds_x_preferred":[
        "Buenaventura"
    ],
    "name:nld_x_preferred":[
        "Buenaventura"
    ],
    "name:pol_x_preferred":[
        "Buenaventura"
    ],
    "name:por_x_preferred":[
        "Buenaventura"
    ],
    "name:rus_x_preferred":[
        "\u0411\u0443\u044d\u043d\u0430\u0432\u0435\u043d\u0442\u0443\u0440\u0430"
    ],
    "name:sco_x_preferred":[
        "Buenaventura"
    ],
    "name:spa_x_preferred":[
        "Buenaventura"
    ],
    "name:srp_x_preferred":[
        "\u0411\u0443\u0435\u043d\u0430\u0432\u0435\u043d\u0442\u0443\u0440\u0430"
    ],
    "name:swe_x_preferred":[
        "Buenaventura"
    ],
    "name:ukr_x_preferred":[
        "\u0411\u0443\u0435\u043d\u0430\u0432\u0435\u043d\u0442\u0443\u0440\u0430"
    ],
    "wof:name":"Buenaventura",
    "wof:placetype":"locality",
    "wof:population":18
},
  "geometry": {"coordinates":[-102.68889,23.01583],"type":"Point"}
}