{
  "type": "Feature",
  "properties": {
    "gn:admin1_code":"32",
    "gn:admin2_code":"13",
    "gn:asciiname":"Buenaventura",
    "gn:country_code":"MX",
    "gn:dem":2120,
    "gn:feature_class":"P",
    "gn:feature_code":"PPL",
    "gn:name":"Buenaventura",
    "gn:population":18,
    "gn:timezone":"America/Mexico_City",
    "iso:country":"MX",
    "wof:name":"Buenaventura",
    "wof:placetype":"locality",
    "wof:population":18
},
  "geometry": {"coordinates":[-102.68889,23.01583],"type":"Point"}
}