{
  "type": "Feature",
  "properties": {
    "gn:admin1_code":"1",
    "gn:admin2_code":"9.0",
    "gn:asciiname":"Mesillas",
    "gn:country_code":"MX",
    "gn:dem":2000,
    "gn:feature_class":"P",
    "gn:feature_code":"PPL",
    "gn:name":"Mesillas",
    "gn:population":878,
    "gn:timezone":"America/Mexico_City",
    "iso:country":"MX",
    "name:spa_x_preferred":[
        "Mesillas"
    ],
    "wof:name":"Mesillas",
    "wof:placetype":"locality",
    "wof:population":878
},
  "geometry": {"coordinates":[-102.16867000000001,22.31497],"type":"Point"}
}