{
  "type": "Feature",
  "properties": {
    "gn:admin1_code":"13",
    "gn:asciiname":"El Cube",
    "gn:country_code":"MX",
    "gn:dem":64,
    "gn:feature_class":"P",
    "gn:feature_code":"PPL",
    "gn:name":"El Cube",
    "gn:population":0,
    "gn:timezone":"America/Mexico_City",
    "iso:country":"MX",
    "name:spa_x_preferred":[
        "El Cube"
    ],
    "wof:name":"El Cube",
    "wof:placetype":"locality"
},
  "geometry": {"coordinates":[-98.51505,21.36564],"type":"Point"}
}