{
  "type": "Feature",
  "properties": {
    "gn:admin1_code":"26.0",
    "gn:admin2_code":"66.0",
    "gn:asciiname":"La Aguilarena",
    "gn:country_code":"MX",
    "gn:dem":410,
    "gn:feature_class":"P",
    "gn:feature_code":"PPL",
    "gn:name":"La Aguilare\u00f1a",
    "gn:population":0,
    "gn:timezone":"America/Hermosillo",
    "iso:country":"MX",
    "name:spa_x_preferred":[
        "La Aguilare\u00f1a"
    ],
    "wof:name":"La Aguilarena",
    "wof:placetype":"locality"
},
  "geometry": {"coordinates":[-110.31097,29.454],"type":"Point"}
}