{
  "type": "Feature",
  "properties": {
    "gn:admin1_code":"30",
    "gn:admin2_code":"141.0",
    "gn:asciiname":"Eden Maya",
    "gn:country_code":"MX",
    "gn:dem":130,
    "gn:feature_class":"P",
    "gn:feature_code":"PPL",
    "gn:name":"Ed\u00e9n Maya",
    "gn:population":5,
    "gn:timezone":"America/Mexico_City",
    "iso:country":"MX",
    "name:und_x_variant":[
        "Ed\u00e9n Maya"
    ],
    "wof:name":"Eden Maya",
    "wof:placetype":"locality",
    "wof:population":5
},
  "geometry": {"coordinates":[-95.20917,18.37167],"type":"Point"}
}