{
  "type": "Feature",
  "properties": {
    "gn:admin1_code":"21",
    "gn:admin2_code":"77.0",
    "gn:asciiname":"Liyahu",
    "gn:country_code":"MX",
    "gn:dem":914,
    "gn:feature_class":"P",
    "gn:feature_code":"PPL",
    "gn:name":"Liyahu",
    "gn:population":6,
    "gn:timezone":"America/Mexico_City",
    "iso:country":"MX",
    "wof:name":"Liyahu",
    "wof:placetype":"locality",
    "wof:population":6
},
  "geometry": {"coordinates":[-97.67778,20.05],"type":"Point"}
}