{
  "type": "Feature",
  "properties": {
    "gn:admin1_code":"32",
    "gn:admin2_code":"55.0",
    "gn:asciiname":"Providencia",
    "gn:country_code":"MX",
    "gn:dem":1895,
    "gn:feature_class":"P",
    "gn:feature_code":"PPL",
    "gn:name":"Providencia",
    "gn:population":0,
    "gn:timezone":"America/Mexico_City",
    "iso:country":"MX",
    "name:cat_x_preferred":[
        "Provid\u00e8ncia"
    ],
    "name:ceb_x_preferred":[
        "Providencia"
    ],
    "name:deu_x_preferred":[
        "Providencia"
    ],
    "name:fra_x_preferred":[
        "Providencia"
    ],
    "name:ita_x_preferred":[
        "Providencia"
    ],
    "name:kor_x_preferred":[
        "\ud504\ub85c\ube44\ub374\uc2dc\uc544"
    ],
    "name:nld_x_preferred":[
        "Providencia"
    ],
    "name:pol_x_preferred":[
        "Providencia"
    ],
    "name:por_x_preferred":[
        "Provid\u00eancia"
    ],
    "name:rus_x_preferred":[
        "\u041f\u0440\u043e\u0432\u0438\u0434\u0435\u043d\u0441\u0438\u044f"
    ],
    "name:sco_x_preferred":[
        "Providencia"
    ],
    "name:spa_x_preferred":[
        "Providencia"
    ],
    "name:swe_x_preferred":[
        "Providencia"
    ],
    "name:zho_x_preferred":[
        "\u666e\u7f85\u7dad\u767b\u897f\u4e9e"
    ],
    "wof:name":"Providencia",
    "wof:placetype":"locality"
},
  "geometry": {"coordinates":[-102.82969,22.22056],"type":"Point"}
}