{
  "type": "Feature",
  "properties": {
    "gn:admin1_code":"32",
    "gn:admin2_code":"55.0",
    "gn:asciiname":"Providencia",
    "gn:country_code":"MX",
    "gn:dem":1895,
    "gn:feature_class":"P",
    "gn:feature_code":"PPL",
    "gn:name":"Providencia",
    "gn:population":0,
    "gn:timezone":"America/Mexico_City",
    "iso:country":"MX",
    "name:spa_x_preferred":[
        "Providencia"
    ],
    "wof:name":"Providencia",
    "wof:placetype":"locality"
},
  "geometry": {"coordinates":[-102.82969,22.22056],"type":"Point"}
}