{
  "type": "Feature",
  "properties": {
    "gn:admin1_code":"25.0",
    "gn:admin2_code":"1.0",
    "gn:asciiname":"Guachapore",
    "gn:country_code":"MX",
    "gn:dem":8,
    "gn:feature_class":"P",
    "gn:feature_code":"PPL",
    "gn:name":"Guachapore",
    "gn:population":0,
    "gn:timezone":"America/Mazatlan",
    "iso:country":"MX",
    "name:und_x_variant":[
        "Guachapare"
    ],
    "wof:name":"Guachapore",
    "wof:placetype":"locality"
},
  "geometry": {"coordinates":[-109.25453,25.75454],"type":"Point"}
}