{
  "type": "Feature",
  "properties": {
    "gn:admin1_code":"25.0",
    "gn:admin2_code":"3.0",
    "gn:asciiname":"Amoles",
    "gn:country_code":"MX",
    "gn:dem":539,
    "gn:feature_class":"P",
    "gn:feature_code":"PPL",
    "gn:name":"Amoles",
    "gn:population":0,
    "gn:timezone":"America/Mazatlan",
    "iso:country":"MX",
    "wof:name":"Amoles",
    "wof:placetype":"locality"
},
  "geometry": {"coordinates":[-107.58333,25.36667000000001],"type":"Point"}
}