{
  "type": "Feature",
  "properties": {
    "gn:admin1_code":"16",
    "gn:admin2_code":"8.0",
    "gn:asciiname":"Las Navajillas",
    "gn:country_code":"MX",
    "gn:dem":958,
    "gn:feature_class":"P",
    "gn:feature_code":"PPL",
    "gn:name":"Las Navajillas",
    "gn:population":5,
    "gn:timezone":"America/Mexico_City",
    "iso:country":"MX",
    "wof:name":"Las Navajillas",
    "wof:placetype":"locality",
    "wof:population":5
},
  "geometry": {"coordinates":[-103.14972,18.34556],"type":"Point"}
}