{
  "type": "Feature",
  "properties": {
    "gn:admin1_code":"3",
    "gn:admin2_code":"8.0",
    "gn:asciiname":"Cuentas Cuavil de Arriba",
    "gn:country_code":"MX",
    "gn:dem":96,
    "gn:feature_class":"P",
    "gn:feature_code":"PPL",
    "gn:name":"Cuentas Cuavil de Arriba",
    "gn:population":0,
    "gn:timezone":"America/Mazatlan",
    "iso:country":"MX",
    "name:spa_x_preferred":[
        "Cuentas Cuavil de Arriba"
    ],
    "wof:name":"Cuentas Cuavil de Arriba",
    "wof:placetype":"locality"
},
  "geometry": {"coordinates":[-109.69255,23.2351],"type":"Point"}
}