{
  "type": "Feature",
  "properties": {
    "gn:admin1_code":"30",
    "gn:admin2_code":"91.0",
    "gn:asciiname":"Coapiloloyita",
    "gn:country_code":"MX",
    "gn:dem":35,
    "gn:feature_class":"P",
    "gn:feature_code":"PPL",
    "gn:name":"Coapiloloyita",
    "gn:population":555,
    "gn:timezone":"America/Mexico_City",
    "iso:country":"MX",
    "wof:name":"Coapiloloyita",
    "wof:placetype":"locality",
    "wof:population":555
},
  "geometry": {"coordinates":[-95.00221999999999,17.42472],"type":"Point"}
}