{
  "type": "Feature",
  "properties": {
    "gn:admin1_code":"24",
    "gn:admin2_code":"46.0",
    "gn:asciiname":"San Jose de Fatima",
    "gn:country_code":"MX",
    "gn:dem":2199,
    "gn:feature_class":"P",
    "gn:feature_code":"PPL",
    "gn:name":"San Jos\u00e9 de F\u00e1tima",
    "gn:population":5,
    "gn:timezone":"America/Mexico_City",
    "iso:country":"MX",
    "name:und_x_variant":[
        "San Jos\u00e9 de F\u00e1tima"
    ],
    "wof:name":"San Jose de Fatima",
    "wof:placetype":"locality",
    "wof:population":5
},
  "geometry": {"coordinates":[-101.45806,21.83222],"type":"Point"}
}