{
  "type": "Feature",
  "properties": {
    "gn:admin1_code":"19.0",
    "gn:asciiname":"Las Comitas",
    "gn:country_code":"MX",
    "gn:dem":747,
    "gn:feature_class":"P",
    "gn:feature_code":"PPL",
    "gn:name":"Las Comitas",
    "gn:population":0,
    "gn:timezone":"America/Monterrey",
    "iso:country":"MX",
    "name:spa_x_preferred":[
        "Las Comitas"
    ],
    "wof:name":"Las Comitas",
    "wof:placetype":"locality"
},
  "geometry": {"coordinates":[-100.67014,25.87252],"type":"Point"}
}