{
  "type": "Feature",
  "properties": {
    "gn:admin1_code":"2.0",
    "gn:admin2_code":"1.0",
    "gn:asciiname":"Caballo Muerto",
    "gn:country_code":"MX",
    "gn:dem":1675,
    "gn:feature_class":"P",
    "gn:feature_code":"PPL",
    "gn:name":"Caballo Muerto",
    "gn:population":0,
    "gn:timezone":"America/Tijuana",
    "iso:country":"MX",
    "name:spa_x_preferred":[
        "Caballo Muerto"
    ],
    "name:und_x_variant":[
        "Rancho El Caballo Muerto"
    ],
    "wof:name":"Caballo Muerto",
    "wof:placetype":"locality"
},
  "geometry": {"coordinates":[-115.94,31.83539],"type":"Point"}
}