{
  "type": "Feature",
  "properties": {
    "gn:admin1_code":"30",
    "gn:admin2_code":"83.0",
    "gn:asciiname":"Puyecaco",
    "gn:country_code":"MX",
    "gn:dem":172,
    "gn:feature_class":"P",
    "gn:feature_code":"PPL",
    "gn:name":"Puyecaco",
    "gn:population":0,
    "gn:timezone":"America/Mexico_City",
    "iso:country":"MX",
    "name:spa_x_preferred":[
        "Puyecaco"
    ],
    "name:und_x_variant":[
        "Poyecaco"
    ],
    "wof:name":"Puyecaco",
    "wof:placetype":"locality"
},
  "geometry": {"coordinates":[-98.04338,20.75497],"type":"Point"}
}