{
  "type": "Feature",
  "properties": {
    "gn:admin1_code":"14",
    "gn:admin2_code":"94",
    "gn:asciiname":"La Presita",
    "gn:country_code":"MX",
    "gn:dem":1303,
    "gn:feature_class":"P",
    "gn:feature_code":"PPL",
    "gn:name":"La Presita",
    "gn:population":17,
    "gn:timezone":"America/Mexico_City",
    "iso:country":"MX",
    "wof:name":"La Presita",
    "wof:placetype":"locality",
    "wof:population":17
},
  "geometry": {"coordinates":[-103.78,20.95806],"type":"Point"}
}