{
  "type": "Feature",
  "properties": {
    "gn:admin1_code":"15",
    "gn:asciiname":"Las Estacas",
    "gn:country_code":"MX",
    "gn:dem":1794,
    "gn:feature_class":"P",
    "gn:feature_code":"PPL",
    "gn:name":"Las Estacas",
    "gn:population":0,
    "gn:timezone":"America/Mexico_City",
    "iso:country":"MX",
    "name:ast_x_preferred":[
        "Las Estacas"
    ],
    "name:deu_x_preferred":[
        "Las Estacas"
    ],
    "name:spa_x_preferred":[
        "Las Estacas"
    ],
    "name:urd_x_preferred":[
        "\u0644\u0627\u0633 \u06cc\u0633\u0679\u0627\u06a9\u0627\u0633"
    ],
    "wof:name":"Las Estacas",
    "wof:placetype":"locality"
},
  "geometry": {"coordinates":[-102.53567,19.91129],"type":"Point"}
}