{
  "type": "Feature",
  "properties": {
    "gn:admin1_code":"11",
    "gn:admin2_code":"7",
    "gn:asciiname":"Granja Santa Cecilia",
    "gn:country_code":"MX",
    "gn:dem":1763,
    "gn:feature_class":"P",
    "gn:feature_code":"PPL",
    "gn:name":"Granja Santa Cecilia",
    "gn:population":24,
    "gn:timezone":"America/Mexico_City",
    "iso:country":"MX",
    "wof:name":"Granja Santa Cecilia",
    "wof:placetype":"locality",
    "wof:population":24
},
  "geometry": {"coordinates":[-100.8725,20.59972],"type":"Point"}
}