{
  "type": "Feature",
  "properties": {
    "gn:admin1_code":"6",
    "gn:admin2_code":"63.0",
    "gn:asciiname":"Barranco Colorado",
    "gn:country_code":"MX",
    "gn:dem":1907,
    "gn:feature_class":"P",
    "gn:feature_code":"PPL",
    "gn:name":"Barranco Colorado",
    "gn:population":0,
    "gn:timezone":"America/Chihuahua",
    "iso:country":"MX",
    "name:spa_x_preferred":[
        "Barranco Colorado"
    ],
    "wof:name":"Barranco Colorado",
    "wof:placetype":"locality"
},
  "geometry": {"coordinates":[-107.83922,28.93496],"type":"Point"}
}