{
  "type": "Feature",
  "properties": {
    "gn:admin1_code":"11",
    "gn:admin2_code":"4",
    "gn:asciiname":"Numero 12 [Granja Avicola]",
    "gn:country_code":"MX",
    "gn:dem":1884,
    "gn:feature_class":"P",
    "gn:feature_code":"PPL",
    "gn:name":"N\u00famero 12 [Granja Av\u00edcola]",
    "gn:population":11,
    "gn:timezone":"America/Mexico_City",
    "iso:country":"MX",
    "name:und_x_variant":[
        "N\u00famero 12 [Granja Av\u00edcola]"
    ],
    "wof:name":"Numero 12 [Granja Avicola]",
    "wof:placetype":"locality",
    "wof:population":11
},
  "geometry": {"coordinates":[-100.56528,20.51222000000001],"type":"Point"}
}