{
  "type": "Feature",
  "properties": {
    "gn:admin1_code":"31",
    "gn:admin2_code":"95.0",
    "gn:asciiname":"Kilinche",
    "gn:country_code":"MX",
    "gn:dem":13,
    "gn:feature_class":"P",
    "gn:feature_code":"PPL",
    "gn:name":"Kilinch\u00e9",
    "gn:population":0,
    "gn:timezone":"America/Merida",
    "iso:country":"MX",
    "name:spa_x_preferred":[
        "Kilinch\u00e9"
    ],
    "wof:name":"Kilinche",
    "wof:placetype":"locality"
},
  "geometry": {"coordinates":[-89.43648,20.99669],"type":"Point"}
}