{
  "type": "Feature",
  "properties": {
    "gn:admin1_code":"14",
    "gn:admin2_code":"37.0",
    "gn:asciiname":"El Colomo",
    "gn:country_code":"MX",
    "gn:dem":892,
    "gn:feature_class":"P",
    "gn:feature_code":"PPL",
    "gn:name":"El Colomo",
    "gn:population":6,
    "gn:timezone":"America/Mexico_City",
    "iso:country":"MX",
    "wof:name":"El Colomo",
    "wof:placetype":"locality",
    "wof:population":6
},
  "geometry": {"coordinates":[-104.21556,19.8275],"type":"Point"}
}