{
  "type": "Feature",
  "properties": {
    "gn:admin1_code":"24",
    "gn:admin2_code":"8",
    "gn:asciiname":"La Labor de San Diego",
    "gn:country_code":"MX",
    "gn:dem":1578,
    "gn:feature_class":"P",
    "gn:feature_code":"PPL",
    "gn:name":"La Labor de San Diego",
    "gn:population":21,
    "gn:timezone":"America/Mexico_City",
    "iso:country":"MX",
    "wof:name":"La Labor de San Diego",
    "wof:placetype":"locality",
    "wof:population":21
},
  "geometry": {"coordinates":[-100.42610999999999,22.36417],"type":"Point"}
}