{
  "type": "Feature",
  "properties": {
    "gn:admin1_code":"31",
    "gn:admin2_code":"52.0",
    "gn:asciiname":"Chemal",
    "gn:country_code":"MX",
    "gn:dem":9,
    "gn:feature_class":"P",
    "gn:feature_code":"PPL",
    "gn:name":"Chemal",
    "gn:population":0,
    "gn:timezone":"America/Merida",
    "iso:country":"MX",
    "wof:name":"Chemal",
    "wof:placetype":"locality"
},
  "geometry": {"coordinates":[-89.26666999999998,21.05],"type":"Point"}
}