{
  "type": "Feature",
  "properties": {
    "gn:admin1_code":"31",
    "gn:admin2_code":"52.0",
    "gn:asciiname":"Chemal",
    "gn:country_code":"MX",
    "gn:dem":9,
    "gn:feature_class":"P",
    "gn:feature_code":"PPL",
    "gn:name":"Chemal",
    "gn:population":0,
    "gn:timezone":"America/Merida",
    "iso:country":"MX",
    "name:bel_x_preferred":[
        "\u0427\u044d\u043c\u0430\u043b"
    ],
    "name:ceb_x_preferred":[
        "Chemal"
    ],
    "name:che_x_preferred":[
        "\u0427\u0435\u043c\u0430\u043b"
    ],
    "name:deu_x_preferred":[
        "Tschemal"
    ],
    "name:fra_x_preferred":[
        "Tchemal"
    ],
    "name:hun_x_preferred":[
        "Csemal"
    ],
    "name:hye_x_preferred":[
        "\u0549\u0565\u0574\u0561\u056c"
    ],
    "name:ita_x_preferred":[
        "\u010cemal"
    ],
    "name:pol_x_preferred":[
        "Czema\u0142"
    ],
    "name:rus_x_preferred":[
        "\u0427\u0435\u043c\u0430\u043b"
    ],
    "name:tat_x_preferred":[
        "\u0427\u0435\u043c\u0430\u043b"
    ],
    "name:tur_x_preferred":[
        "\u00c7amal"
    ],
    "name:ukr_x_preferred":[
        "\u0427\u0435\u043c\u0430\u043b"
    ],
    "wof:name":"Chemal",
    "wof:placetype":"locality"
},
  "geometry": {"coordinates":[-89.26666999999998,21.05],"type":"Point"}
}