{
  "type": "Feature",
  "properties": {
    "gn:admin1_code":"19",
    "gn:admin2_code":"45",
    "gn:asciiname":"El Atoron",
    "gn:country_code":"MX",
    "gn:dem":490,
    "gn:feature_class":"P",
    "gn:feature_code":"PPL",
    "gn:name":"El Ator\u00f3n",
    "gn:population":10,
    "gn:timezone":"America/Monterrey",
    "iso:country":"MX",
    "name:und_x_variant":[
        "El Ator\u00f3n"
    ],
    "wof:name":"El Atoron",
    "wof:placetype":"locality",
    "wof:population":10
},
  "geometry": {"coordinates":[-100.32004000000001,26.08643],"type":"Point"}
}