{
  "type": "Feature",
  "properties": {
    "gn:admin1_code":"10",
    "gn:admin2_code":"26.0",
    "gn:asciiname":"El Rincon de Tierra Blanca",
    "gn:country_code":"MX",
    "gn:dem":2059,
    "gn:feature_class":"P",
    "gn:feature_code":"PPL",
    "gn:name":"El Rinc\u00f3n de Tierra Blanca",
    "gn:population":113,
    "gn:timezone":"America/Monterrey",
    "iso:country":"MX",
    "name:und_x_variant":[
        "El Rinc\u00f3n de Tierra Blanca"
    ],
    "wof:name":"El Rincon de Tierra Blanca",
    "wof:placetype":"locality",
    "wof:population":113
},
  "geometry": {"coordinates":[-105.81501000000002,23.64862],"type":"Point"}
}