{
  "type": "Feature",
  "properties": {
    "gn:admin1_code":"24",
    "gn:admin2_code":"34.0",
    "gn:asciiname":"Tantojon",
    "gn:country_code":"MX",
    "gn:dem":31,
    "gn:feature_class":"P",
    "gn:feature_code":"PPL",
    "gn:name":"Tantoj\u00f3n",
    "gn:population":0,
    "gn:timezone":"America/Mexico_City",
    "iso:country":"MX",
    "name:und_x_variant":[
        "Tantoj\u00f3n",
        "Paso Real Tantoj\u00f3n"
    ],
    "wof:name":"Tantojon",
    "wof:placetype":"locality"
},
  "geometry": {"coordinates":[-98.48636999999999,21.78568],"type":"Point"}
}