{
  "type": "Feature",
  "properties": {
    "gn:admin1_code":"5",
    "gn:admin2_code":"77",
    "gn:asciiname":"Nuevo Emiliano Zapata",
    "gn:country_code":"MX",
    "gn:dem":155,
    "gn:feature_class":"P",
    "gn:feature_code":"PPL",
    "gn:name":"Nuevo Emiliano Zapata",
    "gn:population":36,
    "gn:timezone":"America/Mexico_City",
    "iso:country":"MX",
    "wof:name":"Nuevo Emiliano Zapata",
    "wof:placetype":"locality",
    "wof:population":36
},
  "geometry": {"coordinates":[-92.20028000000001,17.54972],"type":"Point"}
}