{
  "type": "Feature",
  "properties": {
    "gn:admin1_code":"5",
    "gn:admin2_code":"47.0",
    "gn:asciiname":"El Ambar",
    "gn:country_code":"MX",
    "gn:dem":1605,
    "gn:feature_class":"P",
    "gn:feature_code":"PPL",
    "gn:name":"El \u00c1mbar",
    "gn:population":1157,
    "gn:timezone":"America/Mexico_City",
    "iso:country":"MX",
    "name:und_x_variant":[
        "El \u00c1mbar"
    ],
    "wof:name":"El Ambar",
    "wof:placetype":"locality",
    "wof:population":1157
},
  "geometry": {"coordinates":[-92.83417,17.025],"type":"Point"}
}