{
  "type": "Feature",
  "properties": {
    "gn:admin1_code":"12.0",
    "gn:asciiname":"Pumarrosa",
    "gn:country_code":"MX",
    "gn:dem":703,
    "gn:feature_class":"P",
    "gn:feature_code":"PPL",
    "gn:name":"Pumarrosa",
    "gn:population":0,
    "gn:timezone":"America/Mexico_City",
    "iso:country":"MX",
    "name:spa_x_preferred":[
        "Pumarrosa"
    ],
    "wof:name":"Pumarrosa",
    "wof:placetype":"locality"
},
  "geometry": {"coordinates":[-99.08396999999999,17.06726],"type":"Point"}
}