{
  "type": "Feature",
  "properties": {
    "gn:admin1_code":"14",
    "gn:admin2_code":"97.0",
    "gn:asciiname":"Tierra de la Esperanza (Rinconada de los Nogales)",
    "gn:country_code":"MX",
    "gn:dem":1562,
    "gn:feature_class":"P",
    "gn:feature_code":"PPL",
    "gn:name":"Tierra de la Esperanza (Rinconada de los Nogales)",
    "gn:population":269,
    "gn:timezone":"America/Mexico_City",
    "iso:country":"MX",
    "wof:name":"Tierra de la Esperanza (Rinconada de los Nogales)",
    "wof:placetype":"locality",
    "wof:population":269
},
  "geometry": {"coordinates":[-103.41500000000001,20.45778],"type":"Point"}
}