{
  "type": "Feature",
  "properties": {
    "gn:admin1_code":"13",
    "gn:admin2_code":"84",
    "gn:asciiname":"Botha",
    "gn:country_code":"MX",
    "gn:dem":1911,
    "gn:feature_class":"P",
    "gn:feature_code":"PPL",
    "gn:name":"Botha",
    "gn:population":37,
    "gn:timezone":"America/Mexico_City",
    "iso:country":"MX",
    "name:afr_x_preferred":[
        "Botha"
    ],
    "name:deu_x_preferred":[
        "Botha"
    ],
    "name:fin_x_preferred":[
        "Botha"
    ],
    "name:fra_x_preferred":[
        "Botha"
    ],
    "name:ita_x_preferred":[
        "Botha"
    ],
    "name:nld_x_preferred":[
        "Botha"
    ],
    "wof:name":"Botha",
    "wof:placetype":"locality",
    "wof:population":37
},
  "geometry": {"coordinates":[-99.46222,20.65528],"type":"Point"}
}