{
  "type": "Feature",
  "properties": {
    "gn:admin1_code":"25",
    "gn:admin2_code":"17.0",
    "gn:asciiname":"Porohui",
    "gn:country_code":"MX",
    "gn:dem":122,
    "gn:feature_class":"P",
    "gn:feature_code":"PPL",
    "gn:name":"Porohui",
    "gn:population":241,
    "gn:timezone":"America/Mazatlan",
    "iso:country":"MX",
    "wof:name":"Porohui",
    "wof:placetype":"locality",
    "wof:population":241
},
  "geometry": {"coordinates":[-107.98917,25.87056],"type":"Point"}
}