{
  "type": "Feature",
  "properties": {
    "gn:admin1_code":"10.0",
    "gn:asciiname":"El Chirimollo",
    "gn:country_code":"MX",
    "gn:dem":1745,
    "gn:feature_class":"P",
    "gn:feature_code":"PPL",
    "gn:name":"El Chirimollo",
    "gn:population":0,
    "gn:timezone":"America/Monterrey",
    "iso:country":"MX",
    "name:spa_x_preferred":[
        "El Chirimollo"
    ],
    "wof:name":"El Chirimollo",
    "wof:placetype":"locality"
},
  "geometry": {"coordinates":[-105.98873,24.21423],"type":"Point"}
}