{
  "type": "Feature",
  "properties": {
    "gn:admin1_code":"5",
    "gn:admin2_code":"23.0",
    "gn:asciiname":"El Pozo",
    "gn:country_code":"MX",
    "gn:dem":2309,
    "gn:feature_class":"P",
    "gn:feature_code":"PPL",
    "gn:name":"El Pozo",
    "gn:population":0,
    "gn:timezone":"America/Mexico_City",
    "iso:country":"MX",
    "name:deu_x_preferred":[
        "El Pozo"
    ],
    "name:spa_x_preferred":[
        "El Pozo"
    ],
    "name:spa_x_variant":[
        "Los Pozos"
    ],
    "name:srp_x_preferred":[
        "\u0415\u043b \u041f\u043e\u0437\u043e"
    ],
    "wof:name":"El Pozo",
    "wof:placetype":"locality",
    "wof:population":756
},
  "geometry": {"coordinates":[-92.57342,16.85076],"type":"Point"}
}