{
  "type": "Feature",
  "properties": {
    "gn:admin1_code":"30",
    "gn:admin2_code":"149",
    "gn:asciiname":"Beneficio Serrano (Kilometro 38)",
    "gn:country_code":"MX",
    "gn:dem":317,
    "gn:feature_class":"P",
    "gn:feature_code":"PPL",
    "gn:name":"Beneficio Serrano (Kil\u00f3metro 38)",
    "gn:population":14,
    "gn:timezone":"America/Mexico_City",
    "iso:country":"MX",
    "name:und_x_variant":[
        "Beneficio Serrano (Kil\u00f3metro 38)"
    ],
    "wof:name":"Beneficio Serrano (Kilometro 38)",
    "wof:placetype":"locality",
    "wof:population":14
},
  "geometry": {"coordinates":[-94.87444000000001,18.20389],"type":"Point"}
}