{
  "type": "Feature",
  "properties": {
    "gn:admin1_code":"27",
    "gn:admin2_code":"1.0",
    "gn:asciiname":"Isla Missicab",
    "gn:country_code":"MX",
    "gn:dem":12,
    "gn:feature_class":"P",
    "gn:feature_code":"PPL",
    "gn:name":"Isla Missicab",
    "gn:population":0,
    "gn:timezone":"America/Mexico_City",
    "iso:country":"MX",
    "name:spa_x_preferred":[
        "Isla Missicab"
    ],
    "name:spa_x_variant":[
        "Isla Misicab"
    ],
    "wof:name":"Isla Missicab",
    "wof:placetype":"locality"
},
  "geometry": {"coordinates":[-91.46053999999999,17.74802],"type":"Point"}
}