{
  "type": "Feature",
  "properties": {
    "gn:admin1_code":"12",
    "gn:admin2_code":"63.0",
    "gn:asciiname":"Cuatro Caminos (Tierra Colorada)",
    "gn:country_code":"MX",
    "gn:dem":2271,
    "gn:feature_class":"P",
    "gn:feature_code":"PPL",
    "gn:name":"Cuatro Caminos (Tierra Colorada)",
    "gn:population":66,
    "gn:timezone":"America/Mexico_City",
    "iso:country":"MX",
    "wof:name":"Cuatro Caminos (Tierra Colorada)",
    "wof:placetype":"locality",
    "wof:population":66
},
  "geometry": {"coordinates":[-98.72584999999999,17.31341],"type":"Point"}
}