{
  "type": "Feature",
  "properties": {
    "gn:admin1_code":"32.0",
    "gn:asciiname":"Agua Tinta de Arriba",
    "gn:country_code":"MX",
    "gn:dem":2013,
    "gn:feature_class":"P",
    "gn:feature_code":"PPL",
    "gn:name":"Agua Tinta de Arriba",
    "gn:population":0,
    "gn:timezone":"America/Mexico_City",
    "iso:country":"MX",
    "name:spa_x_preferred":[
        "Agua Tinta de Arriba"
    ],
    "wof:name":"Agua Tinta de Arriba",
    "wof:placetype":"locality"
},
  "geometry": {"coordinates":[-102.68266,21.54283],"type":"Point"}
}