{
  "type": "Feature",
  "properties": {
    "gn:admin1_code":"2",
    "gn:admin2_code":"2.0",
    "gn:asciiname":"Ejido Tehuantepec",
    "gn:country_code":"MX",
    "gn:dem":20,
    "gn:feature_class":"P",
    "gn:feature_code":"PPL",
    "gn:name":"Ejido Tehuantepec",
    "gn:population":0,
    "gn:timezone":"America/Tijuana",
    "iso:country":"MX",
    "name:spa_x_preferred":[
        "Ejido Tehuantepec"
    ],
    "name:und_x_variant":[
        "Tehuantepec"
    ],
    "wof:name":"Ejido Tehuantepec",
    "wof:placetype":"locality"
},
  "geometry": {"coordinates":[-115.03051000000001,32.55035],"type":"Point"}
}