{
  "type": "Feature",
  "properties": {
    "gn:admin1_code":"21.0",
    "gn:admin2_code":"114.0",
    "gn:asciiname":"El Arco",
    "gn:country_code":"MX",
    "gn:dem":2850,
    "gn:feature_class":"P",
    "gn:feature_code":"PPL",
    "gn:name":"El Arco",
    "gn:population":0,
    "gn:timezone":"America/Mexico_City",
    "iso:country":"MX",
    "name:ceb_x_preferred":[
        "El Arco"
    ],
    "name:spa_x_preferred":[
        "El Arco"
    ],
    "name:swe_x_preferred":[
        "El Arco"
    ],
    "wof:name":"El Arco",
    "wof:placetype":"locality"
},
  "geometry": {"coordinates":[-98.08001,19.17398],"type":"Point"}
}