{
  "type": "Feature",
  "properties": {
    "gn:admin1_code":"28",
    "gn:admin2_code":"33.0",
    "gn:asciiname":"Puerto las Flores",
    "gn:country_code":"MX",
    "gn:dem":38,
    "gn:feature_class":"P",
    "gn:feature_code":"PPL",
    "gn:name":"Puerto las Flores",
    "gn:population":86,
    "gn:timezone":"America/Monterrey",
    "iso:country":"MX",
    "wof:name":"Puerto las Flores",
    "wof:placetype":"locality",
    "wof:population":86
},
  "geometry": {"coordinates":[-98.10917000000001,25.50389],"type":"Point"}
}