{
  "type": "Feature",
  "properties": {
    "gn:admin1_code":"5",
    "gn:admin2_code":"38.0",
    "gn:asciiname":"Poblado Santa Rita",
    "gn:country_code":"MX",
    "gn:dem":1728,
    "gn:feature_class":"P",
    "gn:feature_code":"PPL",
    "gn:name":"Poblado Santa Rita",
    "gn:population":82,
    "gn:timezone":"America/Mexico_City",
    "iso:country":"MX",
    "wof:name":"Poblado Santa Rita",
    "wof:placetype":"locality",
    "wof:population":82
},
  "geometry": {"coordinates":[-92.34111,16.68889],"type":"Point"}
}