{
  "type": "Feature",
  "properties": {
    "gn:admin1_code":"6.0",
    "gn:admin2_code":"34.0",
    "gn:asciiname":"Anaya",
    "gn:country_code":"MX",
    "gn:dem":2321,
    "gn:feature_class":"P",
    "gn:feature_code":"PPL",
    "gn:name":"Anaya",
    "gn:population":0,
    "gn:timezone":"America/Chihuahua",
    "iso:country":"MX",
    "name:spa_x_preferred":[
        "Anaya"
    ],
    "wof:name":"Anaya",
    "wof:placetype":"locality"
},
  "geometry": {"coordinates":[-107.61192,29.54688],"type":"Point"}
}