{
  "type": "Feature",
  "properties": {
    "gn:admin1_code":"6.0",
    "gn:admin2_code":"34.0",
    "gn:asciiname":"Anaya",
    "gn:country_code":"MX",
    "gn:dem":2321,
    "gn:feature_class":"P",
    "gn:feature_code":"PPL",
    "gn:name":"Anaya",
    "gn:population":0,
    "gn:timezone":"America/Chihuahua",
    "iso:country":"MX",
    "name:arg_x_preferred":[
        "Anaya"
    ],
    "name:cat_x_preferred":[
        "Anaya"
    ],
    "name:ceb_x_preferred":[
        "Anaya"
    ],
    "name:eus_x_preferred":[
        "Anaya"
    ],
    "name:fas_x_preferred":[
        "\u0627\u0646\u0627\u06cc\u0627"
    ],
    "name:fra_x_preferred":[
        "Anaya"
    ],
    "name:hun_x_preferred":[
        "Anaya"
    ],
    "name:ina_x_preferred":[
        "Anaya"
    ],
    "name:ita_x_preferred":[
        "Anaya"
    ],
    "name:msa_x_preferred":[
        "Anaya"
    ],
    "name:nld_x_preferred":[
        "Anaya"
    ],
    "name:oci_x_preferred":[
        "Anaya"
    ],
    "name:pol_x_preferred":[
        "Anaya"
    ],
    "name:por_x_preferred":[
        "Anaya"
    ],
    "name:rus_x_preferred":[
        "\u0410\u043d\u0430\u044f"
    ],
    "name:spa_x_preferred":[
        "Anaya"
    ],
    "name:swe_x_preferred":[
        "Anaya"
    ],
    "name:ukr_x_preferred":[
        "\u0410\u043d\u0430\u044f"
    ],
    "name:vie_x_preferred":[
        "Anaya"
    ],
    "name:war_x_preferred":[
        "Anaya"
    ],
    "name:zho_x_preferred":[
        "\u963f\u5948\u963f"
    ],
    "wof:name":"Anaya",
    "wof:placetype":"locality"
},
  "geometry": {"coordinates":[-107.61192,29.54688],"type":"Point"}
}