{
  "type": "Feature",
  "properties": {
    "gn:admin1_code":"30.0",
    "gn:admin2_code":"143.0",
    "gn:asciiname":"Popoctepetl",
    "gn:country_code":"MX",
    "gn:dem":456,
    "gn:feature_class":"P",
    "gn:feature_code":"PPL",
    "gn:name":"Popoctepetl",
    "gn:population":0,
    "gn:timezone":"America/Mexico_City",
    "iso:country":"MX",
    "name:spa_x_preferred":[
        "Popoctepetl"
    ],
    "wof:name":"Popoctepetl",
    "wof:placetype":"locality"
},
  "geometry": {"coordinates":[-95.3159,18.51264],"type":"Point"}
}