{
  "type": "Feature",
  "properties": {
    "gn:admin1_code":"21",
    "gn:admin2_code":"43.0",
    "gn:asciiname":"Xalpantzingo",
    "gn:country_code":"MX",
    "gn:dem":759,
    "gn:feature_class":"P",
    "gn:feature_code":"PPL",
    "gn:name":"Xalpantzingo",
    "gn:population":601,
    "gn:timezone":"America/Mexico_City",
    "iso:country":"MX",
    "wof:name":"Xalpantzingo",
    "wof:placetype":"locality",
    "wof:population":601
},
  "geometry": {"coordinates":[-97.4713,20.02466],"type":"Point"}
}