{
  "type": "Feature",
  "properties": {
    "gn:admin1_code":"22",
    "gn:admin2_code":"16",
    "gn:asciiname":"Rancho el Colorado",
    "gn:country_code":"MX",
    "gn:dem":1999,
    "gn:feature_class":"P",
    "gn:feature_code":"PPL",
    "gn:name":"Rancho el Colorado",
    "gn:population":22,
    "gn:timezone":"America/Mexico_City",
    "iso:country":"MX",
    "wof:name":"Rancho el Colorado",
    "wof:placetype":"locality",
    "wof:population":22
},
  "geometry": {"coordinates":[-100.04000000000001,20.38139],"type":"Point"}
}