{
  "type": "Feature",
  "properties": {
    "gn:admin1_code":"26",
    "gn:admin2_code":"66.0",
    "gn:asciiname":"El Carrizo",
    "gn:country_code":"MX",
    "gn:dem":455,
    "gn:feature_class":"P",
    "gn:feature_code":"PPL",
    "gn:name":"El Carrizo",
    "gn:population":0,
    "gn:timezone":"America/Hermosillo",
    "iso:country":"MX",
    "name:spa_x_preferred":[
        "El Carrizo"
    ],
    "wof:name":"El Carrizo",
    "wof:placetype":"locality"
},
  "geometry": {"coordinates":[-110.30638999999999,29.42083],"type":"Point"}
}