{
  "type": "Feature",
  "properties": {
    "gn:admin1_code":"6",
    "gn:admin2_code":"67.0",
    "gn:asciiname":"El Tecolote",
    "gn:country_code":"MX",
    "gn:dem":1385,
    "gn:feature_class":"P",
    "gn:feature_code":"PPL",
    "gn:name":"El Tecolote",
    "gn:population":0,
    "gn:timezone":"America/Chihuahua",
    "iso:country":"MX",
    "name:ceb_x_preferred":[
        "El Tecolote"
    ],
    "name:spa_x_preferred":[
        "El Tecolote"
    ],
    "name:spa_x_variant":[
        "El Mirador"
    ],
    "name:swe_x_preferred":[
        "El Tecolote"
    ],
    "name:und_x_variant":[
        "Tecolote"
    ],
    "wof:name":"El Tecolote",
    "wof:placetype":"locality"
},
  "geometry": {"coordinates":[-105.86060000000001,27.53361],"type":"Point"}
}