{
  "type": "Feature",
  "properties": {
    "gn:admin1_code":"6.0",
    "gn:admin2_code":"17.0",
    "gn:asciiname":"Nueve Hermanos",
    "gn:country_code":"MX",
    "gn:dem":2014,
    "gn:feature_class":"P",
    "gn:feature_code":"PPL",
    "gn:name":"Nueve Hermanos",
    "gn:population":0,
    "gn:timezone":"America/Chihuahua",
    "iso:country":"MX",
    "name:spa_x_preferred":[
        "Nueve Hermanos"
    ],
    "wof:name":"Nueve Hermanos",
    "wof:placetype":"locality"
},
  "geometry": {"coordinates":[-106.94692000000001,28.77096],"type":"Point"}
}