{
  "type": "Feature",
  "properties": {
    "gn:admin1_code":"12",
    "gn:admin2_code":"42.0",
    "gn:asciiname":"San Juan Totolcintla",
    "gn:country_code":"MX",
    "gn:dem":585,
    "gn:elevation":"570.0",
    "gn:feature_class":"P",
    "gn:feature_code":"PPL",
    "gn:name":"San Juan Totolcintla",
    "gn:population":0,
    "gn:timezone":"America/Mexico_City",
    "iso:country":"MX",
    "wof:name":"San Juan Totolcintla",
    "wof:placetype":"locality"
},
  "geometry": {"coordinates":[-99.32693999999999,17.90667000000001],"type":"Point"}
}