{
  "type": "Feature",
  "properties": {
    "gn:admin1_code":"10",
    "gn:admin2_code":"22.0",
    "gn:asciiname":"Orizaba",
    "gn:country_code":"MX",
    "gn:dem":1891,
    "gn:feature_class":"P",
    "gn:feature_code":"PPL",
    "gn:name":"Orizaba",
    "gn:population":1452,
    "gn:timezone":"America/Monterrey",
    "iso:country":"MX",
    "wof:name":"Orizaba",
    "wof:placetype":"locality",
    "wof:population":1452
},
  "geometry": {"coordinates":[-104.07389000000001,23.9575],"type":"Point"}
}