{
  "type": "Feature",
  "properties": {
    "gn:admin1_code":"1",
    "gn:admin2_code":"2",
    "gn:asciiname":"La Soledad [Rancho]",
    "gn:country_code":"MX",
    "gn:dem":2004,
    "gn:feature_class":"P",
    "gn:feature_code":"PPL",
    "gn:name":"La Soledad [Rancho]",
    "gn:population":21,
    "gn:timezone":"America/Mexico_City",
    "iso:country":"MX",
    "wof:name":"La Soledad [Rancho]",
    "wof:placetype":"locality",
    "wof:population":21
},
  "geometry": {"coordinates":[-102.02583,22.19583],"type":"Point"}
}