{
  "type": "Feature",
  "properties": {
    "gn:admin1_code":"14",
    "gn:admin2_code":"100",
    "gn:asciiname":"El Caiman",
    "gn:country_code":"MX",
    "gn:dem":39,
    "gn:feature_class":"P",
    "gn:feature_code":"PPL",
    "gn:name":"El Caim\u00e1n",
    "gn:population":51,
    "gn:timezone":"America/Mexico_City",
    "iso:country":"MX",
    "name:und_x_variant":[
        "El Caim\u00e1n"
    ],
    "wof:name":"El Caiman",
    "wof:placetype":"locality",
    "wof:population":51
},
  "geometry": {"coordinates":[-105.29416999999999,20.00444],"type":"Point"}
}