{
  "type": "Feature",
  "properties": {
    "gn:admin1_code":"25.0",
    "gn:admin2_code":"7.0",
    "gn:asciiname":"Vinaterias",
    "gn:country_code":"MX",
    "gn:dem":405,
    "gn:feature_class":"P",
    "gn:feature_code":"PPL",
    "gn:name":"Vinaterias",
    "gn:population":0,
    "gn:timezone":"America/Mazatlan",
    "iso:country":"MX",
    "name:spa_x_preferred":[
        "Vinaterias"
    ],
    "wof:name":"Vinaterias",
    "wof:placetype":"locality"
},
  "geometry": {"coordinates":[-108.29298,26.62398],"type":"Point"}
}