{
  "type": "Feature",
  "properties": {
    "gn:admin1_code":"16",
    "gn:admin2_code":"35.0",
    "gn:asciiname":"Naranjo de Jorullo",
    "gn:country_code":"MX",
    "gn:dem":797,
    "gn:feature_class":"P",
    "gn:feature_code":"PPL",
    "gn:name":"Naranjo de Jorullo",
    "gn:population":216,
    "gn:timezone":"America/Mexico_City",
    "iso:country":"MX",
    "wof:name":"Naranjo de Jorullo",
    "wof:placetype":"locality",
    "wof:population":216
},
  "geometry": {"coordinates":[-101.73556000000001,18.9325],"type":"Point"}
}