{
  "type": "Feature",
  "properties": {
    "gn:admin1_code":"13",
    "gn:admin2_code":"37.0",
    "gn:asciiname":"Fontezuelas",
    "gn:country_code":"MX",
    "gn:dem":2040,
    "gn:feature_class":"P",
    "gn:feature_code":"PPL",
    "gn:name":"Fontezuelas",
    "gn:population":0,
    "gn:timezone":"America/Mexico_City",
    "iso:country":"MX",
    "name:spa_x_preferred":[
        "Fontezuelas"
    ],
    "wof:name":"Fontezuelas",
    "wof:placetype":"locality"
},
  "geometry": {"coordinates":[-98.87164,20.48853],"type":"Point"}
}