{
  "type": "Feature",
  "properties": {
    "gn:admin1_code":"7.0",
    "gn:admin2_code":"24.0",
    "gn:asciiname":"La Constancia",
    "gn:country_code":"MX",
    "gn:dem":1663,
    "gn:feature_class":"P",
    "gn:feature_code":"PPL",
    "gn:name":"La Constancia",
    "gn:population":0,
    "gn:timezone":"America/Monterrey",
    "iso:country":"MX",
    "wof:name":"La Constancia",
    "wof:placetype":"locality"
},
  "geometry": {"coordinates":[-101.98333,25.21667],"type":"Point"}
}