{
  "type": "Feature",
  "properties": {
    "gn:admin1_code":"26",
    "gn:admin2_code":"24.0",
    "gn:asciiname":"La Garita",
    "gn:country_code":"MX",
    "gn:dem":693,
    "gn:feature_class":"P",
    "gn:feature_code":"PPL",
    "gn:name":"La Garita",
    "gn:population":0,
    "gn:timezone":"America/Hermosillo",
    "iso:country":"MX",
    "name:spa_x_preferred":[
        "La Garita"
    ],
    "wof:name":"La Garita",
    "wof:placetype":"locality"
},
  "geometry": {"coordinates":[-109.46355,29.62257],"type":"Point"}
}