{
  "type": "Feature",
  "properties": {
    "gn:admin1_code":"25",
    "gn:admin2_code":"6",
    "gn:asciiname":"Puerto Rico",
    "gn:country_code":"MX",
    "gn:dem":76,
    "gn:feature_class":"P",
    "gn:feature_code":"PPL",
    "gn:name":"Puerto Rico",
    "gn:population":20,
    "gn:timezone":"America/Mazatlan",
    "iso:country":"MX",
    "wof:name":"Puerto Rico",
    "wof:placetype":"locality",
    "wof:population":20
},
  "geometry": {"coordinates":[-107.21775,24.50464],"type":"Point"}
}