{
  "type": "Feature",
  "properties": {
    "gn:admin1_code":"6",
    "gn:admin2_code":"65",
    "gn:asciiname":"Napuchi",
    "gn:country_code":"MX",
    "gn:dem":2190,
    "gn:feature_class":"P",
    "gn:feature_code":"PPL",
    "gn:name":"Napuchi",
    "gn:population":16,
    "gn:timezone":"America/Chihuahua",
    "iso:country":"MX",
    "wof:name":"Napuchi",
    "wof:placetype":"locality",
    "wof:population":16
},
  "geometry": {"coordinates":[-107.71492000000001,27.45631],"type":"Point"}
}