{
  "type": "Feature",
  "properties": {
    "gn:admin1_code":"16.0",
    "gn:admin2_code":"89.0",
    "gn:asciiname":"La Estanzuela",
    "gn:country_code":"MX",
    "gn:dem":457,
    "gn:feature_class":"P",
    "gn:feature_code":"PPL",
    "gn:name":"La Estanzuela",
    "gn:population":103,
    "gn:timezone":"America/Mexico_City",
    "iso:country":"MX",
    "wof:name":"La Estanzuela",
    "wof:placetype":"locality",
    "wof:population":103
},
  "geometry": {"coordinates":[-102.94861,19.16278],"type":"Point"}
}