{
  "type": "Feature",
  "properties": {
    "gn:admin1_code":"4.0",
    "gn:asciiname":"El Carmen",
    "gn:country_code":"MX",
    "gn:dem":10,
    "gn:feature_class":"P",
    "gn:feature_code":"PPL",
    "gn:name":"El Carmen",
    "gn:population":0,
    "gn:timezone":"America/Mexico_City",
    "iso:country":"MX",
    "name:spa_x_preferred":[
        "El Carmen"
    ],
    "wof:name":"El Carmen",
    "wof:placetype":"locality"
},
  "geometry": {"coordinates":[-91.67107,17.93274],"type":"Point"}
}