{
  "type": "Feature",
  "properties": {
    "gn:admin1_code":"16",
    "gn:admin2_code":"9",
    "gn:asciiname":"Lobos",
    "gn:country_code":"MX",
    "gn:dem":2144,
    "gn:feature_class":"P",
    "gn:feature_code":"PPL",
    "gn:name":"Lobos",
    "gn:population":13,
    "gn:timezone":"America/Mexico_City",
    "iso:country":"MX",
    "name:ara_x_preferred":[
        "\u0644\u0648\u0628\u0648\u0633"
    ],
    "name:cat_x_preferred":[
        "Lobos"
    ],
    "name:ceb_x_preferred":[
        "Lobos"
    ],
    "name:deu_x_preferred":[
        "Lobos"
    ],
    "name:fra_x_preferred":[
        "Lobos"
    ],
    "name:ita_x_preferred":[
        "Lobos"
    ],
    "name:lit_x_preferred":[
        "Lobosas"
    ],
    "name:nld_x_preferred":[
        "Lobos"
    ],
    "name:pol_x_preferred":[
        "Lobos"
    ],
    "name:por_x_preferred":[
        "Lobos"
    ],
    "name:slk_x_preferred":[
        "Lobos"
    ],
    "name:spa_x_preferred":[
        "Lobos"
    ],
    "name:swe_x_preferred":[
        "Lobos"
    ],
    "wof:name":"Lobos",
    "wof:placetype":"locality",
    "wof:population":13
},
  "geometry": {"coordinates":[-101.655,19.23333],"type":"Point"}
}