{
  "type": "Feature",
  "properties": {
    "gn:admin1_code":"16",
    "gn:admin2_code":"9",
    "gn:asciiname":"Lobos",
    "gn:country_code":"MX",
    "gn:dem":2144,
    "gn:feature_class":"P",
    "gn:feature_code":"PPL",
    "gn:name":"Lobos",
    "gn:population":13,
    "gn:timezone":"America/Mexico_City",
    "iso:country":"MX",
    "name:ara_x_preferred":[
        "\u0644\u0648\u0628\u0648\u0633"
    ],
    "name:ben_x_preferred":[
        "\u09b2\u09cb\u09ac\u09cb\u09b8"
    ],
    "name:cat_x_preferred":[
        "Lobos"
    ],
    "name:ceb_x_preferred":[
        "Lobos"
    ],
    "name:deu_x_preferred":[
        "Lobos"
    ],
    "name:ell_x_preferred":[
        "\u039b\u03cc\u03bc\u03c0\u03bf\u03c2"
    ],
    "name:fra_x_preferred":[
        "Lobos"
    ],
    "name:hin_x_preferred":[
        "\u0932\u094b\u092c\u094b\u0938"
    ],
    "name:hun_x_preferred":[
        "Lobos"
    ],
    "name:ind_x_preferred":[
        "Lobos"
    ],
    "name:ita_x_preferred":[
        "Lobos"
    ],
    "name:jpn_x_preferred":[
        "\u30ed\u30dc\u30b9"
    ],
    "name:kor_x_preferred":[
        "\ub85c\ubcf4\uc2a4"
    ],
    "name:lit_x_preferred":[
        "Lobosas"
    ],
    "name:nld_x_preferred":[
        "Lobos"
    ],
    "name:pol_x_preferred":[
        "Lobos"
    ],
    "name:por_x_preferred":[
        "Lobos"
    ],
    "name:slk_x_preferred":[
        "Lobos"
    ],
    "name:spa_x_preferred":[
        "Lobos"
    ],
    "name:swe_x_preferred":[
        "Lobos"
    ],
    "name:urd_x_preferred":[
        "\u0644\u0648\u0628\u0648\u0633"
    ],
    "name:vie_x_preferred":[
        "Lobos"
    ],
    "name:zho_cn_x_preferred":[
        "\u6d1b\u6c83\u65af"
    ],
    "name:zho_tw_x_preferred":[
        "\u7f85\u4f2f\u65af"
    ],
    "wof:name":"Lobos",
    "wof:placetype":"locality",
    "wof:population":13
},
  "geometry": {"coordinates":[-101.655,19.23333],"type":"Point"}
}