{
  "type": "Feature",
  "properties": {
    "gn:admin1_code":"30.0",
    "gn:admin2_code":"198.0",
    "gn:asciiname":"La Raiz",
    "gn:country_code":"MX",
    "gn:dem":1468,
    "gn:feature_class":"P",
    "gn:feature_code":"PPL",
    "gn:name":"La Ra\u00edz",
    "gn:population":0,
    "gn:timezone":"America/Mexico_City",
    "iso:country":"MX",
    "name:spa_x_preferred":[
        "La Ra\u00edz"
    ],
    "wof:name":"La Raiz",
    "wof:placetype":"locality"
},
  "geometry": {"coordinates":[-98.29194,20.56],"type":"Point"}
}