{
  "type": "Feature",
  "properties": {
    "gn:admin1_code":"25",
    "gn:admin2_code":"4",
    "gn:asciiname":"Las Porras",
    "gn:country_code":"MX",
    "gn:dem":118,
    "gn:feature_class":"P",
    "gn:feature_code":"PPL",
    "gn:name":"Las Porras",
    "gn:population":30,
    "gn:timezone":"America/Mazatlan",
    "iso:country":"MX",
    "wof:name":"Las Porras",
    "wof:placetype":"locality",
    "wof:population":30
},
  "geometry": {"coordinates":[-106.05368,23.27451],"type":"Point"}
}