{
  "type": "Feature",
  "properties": {
    "gn:admin1_code":"32",
    "gn:admin2_code":"25.0",
    "gn:asciiname":"Leyva [Granja]",
    "gn:country_code":"MX",
    "gn:dem":2021,
    "gn:feature_class":"P",
    "gn:feature_code":"PPL",
    "gn:name":"Leyva [Granja]",
    "gn:population":117,
    "gn:timezone":"America/Mexico_City",
    "iso:country":"MX",
    "wof:name":"Leyva [Granja]",
    "wof:placetype":"locality",
    "wof:population":117
},
  "geometry": {"coordinates":[-102.25639,22.49139],"type":"Point"}
}