{
  "type": "Feature",
  "properties": {
    "gn:admin1_code":"27",
    "gn:admin2_code":"1",
    "gn:asciiname":"El Silencio",
    "gn:country_code":"MX",
    "gn:dem":38,
    "gn:feature_class":"P",
    "gn:feature_code":"PPL",
    "gn:name":"El Silencio",
    "gn:population":46,
    "gn:timezone":"America/Mexico_City",
    "iso:country":"MX",
    "name:ceb_x_preferred":[
        "El Silencio"
    ],
    "name:spa_x_preferred":[
        "El Silencio"
    ],
    "name:swe_x_preferred":[
        "El Silencio"
    ],
    "wof:name":"El Silencio",
    "wof:placetype":"locality",
    "wof:population":46
},
  "geometry": {"coordinates":[-91.22360999999999,17.77306],"type":"Point"}
}