{
  "type": "Feature",
  "properties": {
    "gn:admin1_code":"15.0",
    "gn:admin2_code":"64.0",
    "gn:asciiname":"La Magdalena Morelos",
    "gn:country_code":"MX",
    "gn:dem":2747,
    "gn:feature_class":"P",
    "gn:feature_code":"PPL",
    "gn:name":"La Magdalena Morelos",
    "gn:population":0,
    "gn:timezone":"America/Mexico_City",
    "iso:country":"MX",
    "name:spa_x_preferred":[
        "La Magdalena Morelos"
    ],
    "name:und_x_variant":[
        "Magdalena",
        "La Magdalena"
    ],
    "wof:name":"La Magdalena Morelos",
    "wof:placetype":"locality"
},
  "geometry": {"coordinates":[-100.03739,19.77265],"type":"Point"}
}