{
  "type": "Feature",
  "properties": {
    "gn:admin1_code":"14.0",
    "gn:asciiname":"Metates",
    "gn:country_code":"MX",
    "gn:dem":2144,
    "gn:feature_class":"P",
    "gn:feature_code":"PPL",
    "gn:name":"Metates",
    "gn:population":0,
    "gn:timezone":"America/Mexico_City",
    "iso:country":"MX",
    "name:spa_x_preferred":[
        "Metates"
    ],
    "wof:name":"Metates",
    "wof:placetype":"locality"
},
  "geometry": {"coordinates":[-102.24670999999999,20.92325],"type":"Point"}
}