{
  "type": "Feature",
  "properties": {
    "gn:admin1_code":"25",
    "gn:admin2_code":"11.0",
    "gn:asciiname":"Las Isabeles",
    "gn:country_code":"MX",
    "gn:dem":14,
    "gn:feature_class":"P",
    "gn:feature_code":"PPL",
    "gn:name":"Las Isabeles",
    "gn:population":0,
    "gn:timezone":"America/Mazatlan",
    "iso:country":"MX",
    "name:spa_x_preferred":[
        "Las Isabeles"
    ],
    "wof:name":"Las Isabeles",
    "wof:placetype":"locality"
},
  "geometry": {"coordinates":[-108.65483999999999,25.63337000000001],"type":"Point"}
}