{
  "type": "Feature",
  "properties": {
    "gn:admin1_code":"12",
    "gn:admin2_code":"1.0",
    "gn:asciiname":"Loma Larga Tres",
    "gn:country_code":"MX",
    "gn:dem":207,
    "gn:feature_class":"P",
    "gn:feature_code":"PPL",
    "gn:name":"Loma Larga Tres",
    "gn:population":7,
    "gn:timezone":"America/Mexico_City",
    "iso:country":"MX",
    "wof:name":"Loma Larga Tres",
    "wof:placetype":"locality",
    "wof:population":7
},
  "geometry": {"coordinates":[-99.56054,16.88138],"type":"Point"}
}