{
  "type": "Feature",
  "properties": {
    "gn:admin1_code":"26",
    "gn:admin2_code":"18.0",
    "gn:asciiname":"Agua del Zacate",
    "gn:country_code":"MX",
    "gn:dem":207,
    "gn:feature_class":"P",
    "gn:feature_code":"PPL",
    "gn:name":"Agua del Zacate",
    "gn:population":0,
    "gn:timezone":"America/Hermosillo",
    "iso:country":"MX",
    "name:spa_x_preferred":[
        "Agua del Zacate"
    ],
    "wof:name":"Agua del Zacate",
    "wof:placetype":"locality"
},
  "geometry": {"coordinates":[-109.7294,28.20038],"type":"Point"}
}