{
  "type": "Feature",
  "properties": {
    "gn:admin1_code":"12",
    "gn:admin2_code":"57",
    "gn:asciiname":"Las Guacamayas",
    "gn:country_code":"MX",
    "gn:dem":1303,
    "gn:feature_class":"P",
    "gn:feature_code":"PPL",
    "gn:name":"Las Guacamayas",
    "gn:population":15,
    "gn:timezone":"America/Mexico_City",
    "iso:country":"MX",
    "wof:name":"Las Guacamayas",
    "wof:placetype":"locality",
    "wof:population":15
},
  "geometry": {"coordinates":[-100.6807,17.58857],"type":"Point"}
}