{
  "type": "Feature",
  "properties": {
    "gn:admin1_code":"5",
    "gn:admin2_code":"54.0",
    "gn:asciiname":"La Providencia",
    "gn:country_code":"MX",
    "gn:dem":21,
    "gn:feature_class":"P",
    "gn:feature_code":"PPL",
    "gn:name":"La Providencia",
    "gn:population":0,
    "gn:timezone":"America/Mexico_City",
    "iso:country":"MX",
    "name:spa_x_preferred":[
        "La Providencia"
    ],
    "name:und_x_variant":[
        "Providencia"
    ],
    "wof:name":"La Providencia",
    "wof:placetype":"locality",
    "wof:population":2
},
  "geometry": {"coordinates":[-92.42622,14.82165],"type":"Point"}
}