{
  "type": "Feature",
  "properties": {
    "gn:admin1_code":"11.0",
    "gn:admin2_code":"29.0",
    "gn:asciiname":"Xoconostle",
    "gn:country_code":"MX",
    "gn:dem":2008,
    "gn:feature_class":"P",
    "gn:feature_code":"PPL",
    "gn:name":"Xoconostle",
    "gn:population":0,
    "gn:timezone":"America/Mexico_City",
    "iso:country":"MX",
    "name:spa_x_preferred":[
        "Xoconostle"
    ],
    "wof:name":"Xoconostle",
    "wof:placetype":"locality"
},
  "geometry": {"coordinates":[-100.70166999999999,21.34146],"type":"Point"}
}