{
  "type": "Feature",
  "properties": {
    "gn:admin1_code":"24",
    "gn:admin2_code":"26.0",
    "gn:asciiname":"Cuechod",
    "gn:country_code":"MX",
    "gn:dem":245,
    "gn:feature_class":"P",
    "gn:feature_code":"PPL",
    "gn:name":"Cu\u00e9chod",
    "gn:population":290,
    "gn:timezone":"America/Mexico_City",
    "iso:country":"MX",
    "name:und_x_variant":[
        "Cu\u00e9chod"
    ],
    "wof:name":"Cuechod",
    "wof:placetype":"locality",
    "wof:population":290
},
  "geometry": {"coordinates":[-98.91167,21.62472],"type":"Point"}
}