{
  "type": "Feature",
  "properties": {
    "gn:admin1_code":"6",
    "gn:admin2_code":"42.0",
    "gn:asciiname":"La Selva",
    "gn:country_code":"MX",
    "gn:dem":993,
    "gn:feature_class":"P",
    "gn:feature_code":"PPL",
    "gn:name":"La Selva",
    "gn:population":0,
    "gn:timezone":"America/Chihuahua",
    "iso:country":"MX",
    "name:ceb_x_preferred":[
        "La Selva"
    ],
    "name:deu_x_preferred":[
        "La Selva"
    ],
    "name:spa_x_preferred":[
        "La Selva"
    ],
    "name:srp_x_preferred":[
        "La Selva"
    ],
    "name:swe_x_preferred":[
        "La Selva"
    ],
    "wof:name":"La Selva",
    "wof:placetype":"locality"
},
  "geometry": {"coordinates":[-103.51678,28.74447],"type":"Point"}
}