{
  "type": "Feature",
  "properties": {
    "gn:admin1_code":"11",
    "gn:admin2_code":"3.0",
    "gn:asciiname":"Corralejo de Abajo",
    "gn:country_code":"MX",
    "gn:dem":1909,
    "gn:feature_class":"P",
    "gn:feature_code":"PPL",
    "gn:name":"Corralejo de Abajo",
    "gn:population":193,
    "gn:timezone":"America/Mexico_City",
    "iso:country":"MX",
    "wof:name":"Corralejo de Abajo",
    "wof:placetype":"locality",
    "wof:population":193
},
  "geometry": {"coordinates":[-100.92167000000001,20.95222],"type":"Point"}
}