{
  "type": "Feature",
  "properties": {
    "gn:admin1_code":"30.0",
    "gn:admin2_code":"121.0",
    "gn:asciiname":"El Pino",
    "gn:country_code":"MX",
    "gn:dem":70,
    "gn:feature_class":"P",
    "gn:feature_code":"PPL",
    "gn:name":"El Pino",
    "gn:population":0,
    "gn:timezone":"America/Mexico_City",
    "iso:country":"MX",
    "name:spa_x_preferred":[
        "El Pino"
    ],
    "wof:name":"El Pino",
    "wof:placetype":"locality"
},
  "geometry": {"coordinates":[-97.9944,21.70839],"type":"Point"}
}