{
  "type": "Feature",
  "properties": {
    "gn:admin1_code":"28",
    "gn:admin2_code":"35.0",
    "gn:asciiname":"Dos de Junio",
    "gn:country_code":"MX",
    "gn:dem":82,
    "gn:feature_class":"P",
    "gn:feature_code":"PPL",
    "gn:name":"Dos de Junio",
    "gn:population":0,
    "gn:timezone":"America/Monterrey",
    "iso:country":"MX",
    "name:spa_x_preferred":[
        "Dos de Junio"
    ],
    "wof:name":"Dos de Junio",
    "wof:placetype":"locality"
},
  "geometry": {"coordinates":[-98.19398,25.15478],"type":"Point"}
}