{
  "type": "Feature",
  "properties": {
    "gn:admin1_code":"5",
    "gn:admin2_code":"34.0",
    "gn:asciiname":"Barrio Nuevo",
    "gn:country_code":"MX",
    "gn:dem":673,
    "gn:feature_class":"P",
    "gn:feature_code":"PPL",
    "gn:name":"Barrio Nuevo",
    "gn:population":154,
    "gn:timezone":"America/Mexico_City",
    "iso:country":"MX",
    "wof:name":"Barrio Nuevo",
    "wof:placetype":"locality",
    "wof:population":154
},
  "geometry": {"coordinates":[-92.13889,15.64861],"type":"Point"}
}