{
  "type": "Feature",
  "properties": {
    "gn:country":"MX",
    "gn:fcode":"PPLA",
    "gn:population":319581,
    "iso:country":"MX",
    "name:bul_x_preferred":[
        "\u041f\u0430\u0447\u0443\u043a\u0430"
    ],
    "name:cat_x_preferred":[
        "Pachuca"
    ],
    "name:deu_x_preferred":[
        "Pachuca de Soto"
    ],
    "name:eng_x_preferred":[
        "Pachuca"
    ],
    "name:fas_x_preferred":[
        "\u067e\u0627\u0686\u0648\u06a9\u0627\u066c \u0627\u06cc\u062f\u0627\u0644\u06af\u0648"
    ],
    "name:fra_x_preferred":[
        "Pachuca"
    ],
    "name:jpn_x_preferred":[
        "\u30d1\u30c1\u30e5\u30fc\u30ab"
    ],
    "name:kat_x_preferred":[
        "\u10de\u10d0\u10e9\u10e3\u10d9\u10d0"
    ],
    "name:kor_x_preferred":[
        "\ud30c\ucd94\uce74"
    ],
    "name:lat_x_preferred":[
        "Pasuca Sotoensis"
    ],
    "name:lit_x_preferred":[
        "Pa\u010duka"
    ],
    "name:nah_x_preferred":[
        "Pachyohc\u0101n Soto"
    ],
    "name:nld_x_preferred":[
        "Pachuca de Soto"
    ],
    "name:por_x_preferred":[
        "Pachuca"
    ],
    "name:rus_x_preferred":[
        "\u041f\u0430\u0447\u0443\u043a\u0430-\u0434\u0435-\u0421\u043e\u0442\u043e"
    ],
    "name:spa_x_preferred":[
        "Pachuca"
    ],
    "name:spa_x_variant":[
        "Pachuca de Soto"
    ],
    "name:srp_x_preferred":[
        "\u041f\u0430\u0447\u0443\u043a\u0430 \u0434\u0435 \u0421\u043e\u0442\u043e"
    ],
    "name:swe_x_preferred":[
        "Pachuca de Soto"
    ],
    "name:ukr_x_preferred":[
        "\u041f\u0430\u0447\u0443\u043a\u0430-\u0434\u0435-\u0421\u043e\u0442\u043e"
    ],
    "name:zho_x_preferred":[
        "\u5e15\u4e18\u5361"
    ],
    "qs_pg:aaroncc":"MX",
    "qs_pg:gn_country":"MX",
    "qs_pg:gn_fcode":"PPLA",
    "qs_pg:gn_pop":319581,
    "qs_pg:name":"Pachuca de Soto",
    "qs_pg:photos_9r":0,
    "qs_pg:photos_sr":0,
    "qs_pg:pop_sr":10,
    "qs_pg:qs_pg_placetype":"locality",
    "wof:name":"Pachuca de Soto",
    "wof:placetype":"locality",
    "wof:population":319581
},
  "geometry": {"coordinates":[-98.73329,20.11697],"type":"Point"}
}