{
  "type": "Feature",
  "properties": {
    "gn:country":"MX",
    "gn:fcode":"PPL",
    "gn:population":101558,
    "iso:country":"MX",
    "name:spa_x_preferred":[
        "Temapache"
    ],
    "qs_pg:aaroncc":"MX",
    "qs_pg:gn_country":"MX",
    "qs_pg:gn_fcode":"PPL",
    "qs_pg:gn_pop":101558,
    "qs_pg:name":"Mapache",
    "qs_pg:name_adm0":"M\u00e9xico",
    "qs_pg:name_adm1":"Puebla",
    "qs_pg:photos_9r":0,
    "qs_pg:photos_sr":0,
    "qs_pg:pop_sr":9,
    "qs_pg:qs_pg_placetype":"neighbourhood",
    "qs_pg:qs_pg_placetype_gp":"Suburb",
    "qs_pg:woe_adm0":23424900,
    "woe:adm0_id":23424900,
    "woe:name_adm0":"M\u00e9xico",
    "woe:name_adm1":"Puebla",
    "woe:placetype":"Suburb",
    "wof:name":"Mapache",
    "wof:placetype":"neighbourhood",
    "wof:population":101558
},
  "geometry": {"coordinates":[-97.64104,21.06583],"type":"Point"}
}