{
  "type": "Feature",
  "properties": {
    "gn:admin1_code":"21",
    "gn:admin2_code":"43.0",
    "gn:asciiname":"Kapola",
    "gn:country_code":"MX",
    "gn:dem":426,
    "gn:feature_class":"P",
    "gn:feature_code":"PPL",
    "gn:name":"Kapola",
    "gn:population":353,
    "gn:timezone":"America/Mexico_City",
    "iso:country":"MX",
    "wof:name":"Kapola",
    "wof:placetype":"locality",
    "wof:population":353
},
  "geometry": {"coordinates":[-97.50749999999999,20.07056],"type":"Point"}
}