{
  "type": "Feature",
  "properties": {
    "gn:admin1_code":"5.0",
    "gn:admin2_code":"77.0",
    "gn:asciiname":"Tentiul Grande",
    "gn:country_code":"MX",
    "gn:dem":318,
    "gn:feature_class":"P",
    "gn:feature_code":"PPL",
    "gn:name":"Tentiul Grande",
    "gn:population":0,
    "gn:timezone":"America/Mexico_City",
    "iso:country":"MX",
    "name:spa_x_preferred":[
        "Tentiul Grande"
    ],
    "wof:name":"Tentiul Grande",
    "wof:placetype":"locality"
},
  "geometry": {"coordinates":[-92.27919,17.39466],"type":"Point"}
}