{
  "type": "Feature",
  "properties": {
    "gn:admin1_code":"7",
    "gn:admin2_code":"4",
    "gn:asciiname":"Guadalupe",
    "gn:country_code":"MX",
    "gn:dem":1998,
    "gn:feature_class":"P",
    "gn:feature_code":"PPL",
    "gn:name":"Guadalupe",
    "gn:population":10,
    "gn:timezone":"America/Monterrey",
    "iso:country":"MX",
    "wof:name":"Guadalupe",
    "wof:placetype":"locality",
    "wof:population":10
},
  "geometry": {"coordinates":[-100.76697,25.20254],"type":"Point"}
}