{
  "type": "Feature",
  "properties": {
    "gn:admin1_code":"13",
    "gn:admin2_code":"45.0",
    "gn:asciiname":"Cruz de Mujer",
    "gn:country_code":"MX",
    "gn:dem":2691,
    "gn:feature_class":"P",
    "gn:feature_code":"PPL",
    "gn:name":"Cruz de Mujer",
    "gn:population":0,
    "gn:timezone":"America/Mexico_City",
    "iso:country":"MX",
    "name:spa_x_preferred":[
        "Cruz de Mujer"
    ],
    "wof:name":"Cruz de Mujer",
    "wof:placetype":"locality"
},
  "geometry": {"coordinates":[-98.59652,20.15562000000001],"type":"Point"}
}