{
  "type": "Feature",
  "properties": {
    "gn:admin1_code":"16",
    "gn:admin2_code":"53",
    "gn:asciiname":"Palo Amarillo",
    "gn:country_code":"MX",
    "gn:dem":2319,
    "gn:feature_class":"P",
    "gn:feature_code":"PPL",
    "gn:name":"Palo Amarillo",
    "gn:population":15,
    "gn:timezone":"America/Mexico_City",
    "iso:country":"MX",
    "wof:name":"Palo Amarillo",
    "wof:placetype":"locality",
    "wof:population":15
},
  "geometry": {"coordinates":[-101.20778,19.48972],"type":"Point"}
}