{
  "type": "Feature",
  "properties": {
    "gn:admin1_code":"28",
    "gn:admin2_code":"20",
    "gn:asciiname":"San Manuel",
    "gn:country_code":"MX",
    "gn:dem":733,
    "gn:feature_class":"P",
    "gn:feature_code":"PPL",
    "gn:name":"San Manuel",
    "gn:population":25,
    "gn:timezone":"America/Monterrey",
    "iso:country":"MX",
    "wof:name":"San Manuel",
    "wof:placetype":"locality",
    "wof:population":25
},
  "geometry": {"coordinates":[-99.68083,24.49917],"type":"Point"}
}