{
  "type": "Feature",
  "properties": {
    "gn:admin1_code":"20.0",
    "gn:admin2_code":"323.0",
    "gn:asciiname":"Rancho Polvo",
    "gn:country_code":"MX",
    "gn:dem":1209,
    "gn:feature_class":"P",
    "gn:feature_code":"PPL",
    "gn:name":"Rancho Polvo",
    "gn:population":0,
    "gn:timezone":"America/Mexico_City",
    "iso:country":"MX",
    "name:spa_x_preferred":[
        "Rancho Polvo"
    ],
    "wof:name":"Rancho Polvo",
    "wof:placetype":"locality"
},
  "geometry": {"coordinates":[-95.86257999999999,16.97488],"type":"Point"}
}