{
  "type": "Feature",
  "properties": {
    "gn:admin1_code":"30",
    "gn:admin2_code":"100",
    "gn:asciiname":"Ignacio Bernal",
    "gn:country_code":"MX",
    "gn:dem":77,
    "gn:feature_class":"P",
    "gn:feature_code":"PPL",
    "gn:name":"Ignacio Bernal",
    "gn:population":50,
    "gn:timezone":"America/Mexico_City",
    "iso:country":"MX",
    "name:ara_x_preferred":[
        "\u0625\u063a\u0646\u0627\u062b\u064a\u0648 \u0628\u064a\u0631\u0646\u0627\u0644"
    ],
    "name:fra_x_preferred":[
        "Ignacio Bernal"
    ],
    "name:nor_x_preferred":[
        "Ignacio Bernal"
    ],
    "wof:name":"Ignacio Bernal",
    "wof:placetype":"locality",
    "wof:population":50
},
  "geometry": {"coordinates":[-96.37972000000001,19.05806],"type":"Point"}
}