{
  "type": "Feature",
  "properties": {
    "gn:admin1_code":"16.0",
    "gn:admin2_code":"15.0",
    "gn:asciiname":"La Nieve",
    "gn:country_code":"MX",
    "gn:dem":2264,
    "gn:feature_class":"P",
    "gn:feature_code":"PPL",
    "gn:name":"La Nieve",
    "gn:population":0,
    "gn:timezone":"America/Mexico_City",
    "iso:country":"MX",
    "name:spa_x_preferred":[
        "La Nieve"
    ],
    "wof:name":"La Nieve",
    "wof:placetype":"locality"
},
  "geometry": {"coordinates":[-103.04428,18.81832],"type":"Point"}
}