{
  "type": "Feature",
  "properties": {
    "gn:admin1_code":"24",
    "gn:admin2_code":"23",
    "gn:asciiname":"Pozo de Moscas",
    "gn:country_code":"MX",
    "gn:dem":1079,
    "gn:feature_class":"P",
    "gn:feature_code":"PPL",
    "gn:name":"Pozo de Moscas",
    "gn:population":22,
    "gn:timezone":"America/Mexico_City",
    "iso:country":"MX",
    "wof:name":"Pozo de Moscas",
    "wof:placetype":"locality",
    "wof:population":22
},
  "geometry": {"coordinates":[-99.58722,21.82972],"type":"Point"}
}