{
  "type": "Feature",
  "properties": {
    "gn:admin1_code":"12.0",
    "gn:admin2_code":"48.0",
    "gn:asciiname":"Soledad de los Enanos",
    "gn:country_code":"MX",
    "gn:dem":1156,
    "gn:feature_class":"P",
    "gn:feature_code":"PPL",
    "gn:name":"Soledad de los Enanos",
    "gn:population":55,
    "gn:timezone":"America/Mexico_City",
    "iso:country":"MX",
    "name:spa_x_preferred":[
        "Soledad de los Enanos"
    ],
    "name:und_x_variant":[
        "La Soledad de los Enanos"
    ],
    "wof:name":"Soledad de los Enanos",
    "wof:placetype":"locality",
    "wof:population":55
},
  "geometry": {"coordinates":[-101.11014,17.56393],"type":"Point"}
}