{
  "type": "Feature",
  "properties": {
    "gn:admin1_code":"30",
    "gn:admin2_code":"128.0",
    "gn:asciiname":"Vidal Diaz Munoz",
    "gn:country_code":"MX",
    "gn:dem":2848,
    "gn:feature_class":"P",
    "gn:feature_code":"PPL",
    "gn:name":"Vidal D\u00edaz Mu\u00f1oz",
    "gn:population":0,
    "gn:timezone":"America/Mexico_City",
    "iso:country":"MX",
    "name:spa_x_preferred":[
        "Vidal D\u00edaz Mu\u00f1oz"
    ],
    "wof:name":"Vidal Diaz Munoz",
    "wof:placetype":"locality"
},
  "geometry": {"coordinates":[-97.16417,19.56919],"type":"Point"}
}