{
  "type": "Feature",
  "properties": {
    "gn:admin1_code":"30",
    "gn:admin2_code":"168.0",
    "gn:asciiname":"Coxititla",
    "gn:country_code":"MX",
    "gn:dem":1107,
    "gn:feature_class":"P",
    "gn:feature_code":"PPL",
    "gn:name":"Coxititla",
    "gn:population":270,
    "gn:timezone":"America/Mexico_City",
    "iso:country":"MX",
    "wof:name":"Coxititla",
    "wof:placetype":"locality",
    "wof:population":270
},
  "geometry": {"coordinates":[-96.96083,18.75389],"type":"Point"}
}