{
  "type": "Feature",
  "properties": {
    "gn:admin1_code":"6",
    "gn:admin2_code":"27.0",
    "gn:asciiname":"Guarianachi",
    "gn:country_code":"MX",
    "gn:dem":2424,
    "gn:feature_class":"P",
    "gn:feature_code":"PPL",
    "gn:name":"Guarianachi",
    "gn:population":0,
    "gn:timezone":"America/Chihuahua",
    "iso:country":"MX",
    "name:spa_x_preferred":[
        "Guarianachi"
    ],
    "name:spa_x_variant":[
        "Cab\u00f3rachi"
    ],
    "wof:name":"Guarianachi",
    "wof:placetype":"locality"
},
  "geometry": {"coordinates":[-107.44174,27.56514],"type":"Point"}
}