{
  "type": "Feature",
  "properties": {
    "gn:admin1_code":"28.0",
    "gn:admin2_code":"43.0",
    "gn:asciiname":"Ampliacion Benito Juarez",
    "gn:country_code":"MX",
    "gn:dem":90,
    "gn:feature_class":"P",
    "gn:feature_code":"PPL",
    "gn:name":"Ampliaci\u00f3n Benito Ju\u00e1rez",
    "gn:population":0,
    "gn:timezone":"America/Monterrey",
    "iso:country":"MX",
    "name:spa_x_preferred":[
        "Ampliaci\u00f3n Benito Ju\u00e1rez"
    ],
    "wof:name":"Ampliacion Benito Juarez",
    "wof:placetype":"locality"
},
  "geometry": {"coordinates":[-98.93894,22.97208],"type":"Point"}
}