{
  "type": "Feature",
  "properties": {
    "gn:admin1_code":"25",
    "gn:admin2_code":"14.0",
    "gn:asciiname":"Majahual",
    "gn:country_code":"MX",
    "gn:dem":3,
    "gn:feature_class":"P",
    "gn:feature_code":"PPL",
    "gn:name":"Majahual",
    "gn:population":0,
    "gn:timezone":"America/Mazatlan",
    "iso:country":"MX",
    "name:spa_x_preferred":[
        "Majahual"
    ],
    "wof:name":"Majahual",
    "wof:placetype":"locality"
},
  "geometry": {"coordinates":[-106.0258,22.83082000000001],"type":"Point"}
}