{
  "type": "Feature",
  "properties": {
    "gn:admin1_code":"21",
    "gn:asciiname":"Los Perales",
    "gn:country_code":"MX",
    "gn:dem":1843,
    "gn:feature_class":"P",
    "gn:feature_code":"PPL",
    "gn:name":"Los Perales",
    "gn:population":0,
    "gn:timezone":"America/Mexico_City",
    "iso:country":"MX",
    "name:spa_x_preferred":[
        "Los Perales"
    ],
    "wof:name":"Los Perales",
    "wof:placetype":"locality"
},
  "geometry": {"coordinates":[-97.30977,19.8135],"type":"Point"}
}