{
  "type": "Feature",
  "properties": {
    "gn:admin1_code":"30",
    "gn:admin2_code":"12.0",
    "gn:asciiname":"La Guadalupe",
    "gn:country_code":"MX",
    "gn:dem":5,
    "gn:feature_class":"P",
    "gn:feature_code":"PPL",
    "gn:name":"La Guadalupe",
    "gn:population":58,
    "gn:timezone":"America/Mexico_City",
    "iso:country":"MX",
    "wof:name":"La Guadalupe",
    "wof:placetype":"locality",
    "wof:population":58
},
  "geometry": {"coordinates":[-95.69694,18.50222],"type":"Point"}
}