{
  "type": "Feature",
  "properties": {
    "gn:admin1_code":"16",
    "gn:admin2_code":"101.0",
    "gn:asciiname":"Las Majadas",
    "gn:country_code":"MX",
    "gn:dem":2027,
    "gn:feature_class":"P",
    "gn:feature_code":"PPL",
    "gn:name":"Las Majadas",
    "gn:population":0,
    "gn:timezone":"America/Mexico_City",
    "iso:country":"MX",
    "name:ara_x_preferred":[
        "\u0644\u0627\u0633 \u0645\u0627\u062e\u0627\u062f\u0627\u0633"
    ],
    "name:arg_x_preferred":[
        "Las Majadas"
    ],
    "name:ast_x_preferred":[
        "Les Mayaes"
    ],
    "name:cat_x_preferred":[
        "Las Majadas"
    ],
    "name:ceb_x_preferred":[
        "Las Majadas"
    ],
    "name:epo_x_preferred":[
        "Las Majadas"
    ],
    "name:eus_x_preferred":[
        "Las Majadas"
    ],
    "name:fra_x_preferred":[
        "Las Majadas"
    ],
    "name:hun_x_preferred":[
        "Las Majadas"
    ],
    "name:ita_x_preferred":[
        "Las Majadas"
    ],
    "name:kaz_x_preferred":[
        "\u041b\u0430\u0441-\u041c\u0430\u0445\u0430\u0434\u0430\u0441"
    ],
    "name:msa_x_preferred":[
        "Las Majadas"
    ],
    "name:nld_x_preferred":[
        "Las Majadas"
    ],
    "name:oci_x_preferred":[
        "Las Majadas"
    ],
    "name:pol_x_preferred":[
        "Las Majadas"
    ],
    "name:por_x_preferred":[
        "Las Majadas"
    ],
    "name:rus_x_preferred":[
        "\u041b\u0430\u0441-\u041c\u0430\u0445\u0430\u0434\u0430\u0441"
    ],
    "name:spa_x_preferred":[
        "Las Majadas"
    ],
    "name:ukr_x_preferred":[
        "\u041b\u0430\u0441-\u041c\u0430\u0445\u0430\u0434\u0430\u0441"
    ],
    "name:vie_x_preferred":[
        "Las Majadas"
    ],
    "name:war_x_preferred":[
        "Las Majadas"
    ],
    "name:zho_x_preferred":[
        "\u62c9\u65af\u9a6c\u54c8\u8fbe\u65af"
    ],
    "wof:name":"Las Majadas",
    "wof:placetype":"locality"
},
  "geometry": {"coordinates":[-100.99747000000001,19.46242],"type":"Point"}
}