{
  "type": "Feature",
  "properties": {
    "gn:admin1_code":"16",
    "gn:admin2_code":"101.0",
    "gn:asciiname":"Las Majadas",
    "gn:country_code":"MX",
    "gn:dem":2027,
    "gn:feature_class":"P",
    "gn:feature_code":"PPL",
    "gn:name":"Las Majadas",
    "gn:population":0,
    "gn:timezone":"America/Mexico_City",
    "iso:country":"MX",
    "name:spa_x_preferred":[
        "Las Majadas"
    ],
    "wof:name":"Las Majadas",
    "wof:placetype":"locality"
},
  "geometry": {"coordinates":[-100.99747000000001,19.46242],"type":"Point"}
}