{
  "type": "Feature",
  "properties": {
    "gn:admin1_code":"14.0",
    "gn:admin2_code":"94.0",
    "gn:asciiname":"La Joya de Mochitiltic",
    "gn:country_code":"MX",
    "gn:dem":781,
    "gn:feature_class":"P",
    "gn:feature_code":"PPL",
    "gn:name":"La Joya de Mochitiltic",
    "gn:population":0,
    "gn:timezone":"America/Mexico_City",
    "iso:country":"MX",
    "name:spa_x_preferred":[
        "La Joya de Mochitiltic"
    ],
    "name:spa_x_variant":[
        "La Joya de Amuchiltite"
    ],
    "wof:name":"La Joya de Mochitiltic",
    "wof:placetype":"locality"
},
  "geometry": {"coordinates":[-103.82848,20.96175],"type":"Point"}
}