{
  "type": "Feature",
  "properties": {
    "gn:admin1_code":"26",
    "gn:admin2_code":"72.0",
    "gn:asciiname":"Bachoco (Postura Granja Pesada)",
    "gn:country_code":"MX",
    "gn:dem":14,
    "gn:feature_class":"P",
    "gn:feature_code":"PPL",
    "gn:name":"Bachoco (Postura Granja Pesada)",
    "gn:population":6,
    "gn:timezone":"America/Hermosillo",
    "iso:country":"MX",
    "wof:name":"Bachoco (Postura Granja Pesada)",
    "wof:placetype":"locality",
    "wof:population":6
},
  "geometry": {"coordinates":[-110.19722,27.46667],"type":"Point"}
}