{
  "type": "Feature",
  "properties": {
    "gn:admin1_code":"14",
    "gn:admin2_code":"91",
    "gn:asciiname":"Los Santiagos",
    "gn:country_code":"MX",
    "gn:dem":1852,
    "gn:feature_class":"P",
    "gn:feature_code":"PPL",
    "gn:name":"Los Santiagos",
    "gn:population":50,
    "gn:timezone":"America/Mexico_City",
    "iso:country":"MX",
    "wof:name":"Los Santiagos",
    "wof:placetype":"locality",
    "wof:population":50
},
  "geometry": {"coordinates":[-102.60389000000001,21.54583],"type":"Point"}
}