{
  "type": "Feature",
  "properties": {
    "gn:admin1_code":"22",
    "gn:admin2_code":"15.0",
    "gn:asciiname":"Las Tinajas",
    "gn:country_code":"MX",
    "gn:dem":1791,
    "gn:feature_class":"P",
    "gn:feature_code":"PPL",
    "gn:name":"Las Tinajas",
    "gn:population":112,
    "gn:timezone":"America/Mexico_City",
    "iso:country":"MX",
    "wof:name":"Las Tinajas",
    "wof:placetype":"locality",
    "wof:population":112
},
  "geometry": {"coordinates":[-99.40222,21.05417000000001],"type":"Point"}
}