{
  "type": "Feature",
  "properties": {
    "gn:admin1_code":"31",
    "gn:admin2_code":"2.0",
    "gn:asciiname":"Cibceh",
    "gn:country_code":"MX",
    "gn:dem":17,
    "gn:feature_class":"P",
    "gn:feature_code":"PPL",
    "gn:name":"Cibceh",
    "gn:population":64,
    "gn:timezone":"America/Merida",
    "iso:country":"MX",
    "wof:name":"Cibceh",
    "wof:placetype":"locality",
    "wof:population":64
},
  "geometry": {"coordinates":[-89.48772,20.82025],"type":"Point"}
}