{
  "type": "Feature",
  "properties": {
    "gn:admin1_code":"24",
    "gn:admin2_code":"32.0",
    "gn:asciiname":"Potrero los Gallos",
    "gn:country_code":"MX",
    "gn:dem":1636,
    "gn:feature_class":"P",
    "gn:feature_code":"PPL",
    "gn:name":"Potrero los Gallos",
    "gn:population":6,
    "gn:timezone":"America/Mexico_City",
    "iso:country":"MX",
    "wof:name":"Potrero los Gallos",
    "wof:placetype":"locality",
    "wof:population":6
},
  "geometry": {"coordinates":[-100.59222,21.77889],"type":"Point"}
}