{
  "type": "Feature",
  "properties": {
    "gn:admin1_code":"24",
    "gn:admin2_code":"47.0",
    "gn:asciiname":"El Aura",
    "gn:country_code":"MX",
    "gn:dem":1734,
    "gn:feature_class":"P",
    "gn:feature_code":"PPL",
    "gn:name":"El Aura",
    "gn:population":6,
    "gn:timezone":"America/Mexico_City",
    "iso:country":"MX",
    "wof:name":"El Aura",
    "wof:placetype":"locality",
    "wof:population":6
},
  "geometry": {"coordinates":[-100.77278,23.44556],"type":"Point"}
}