{
  "type": "Feature",
  "properties": {
    "gn:admin1_code":"30",
    "gn:admin2_code":"160.0",
    "gn:asciiname":"Las Flores Cinco Poblados",
    "gn:country_code":"MX",
    "gn:dem":42,
    "gn:feature_class":"P",
    "gn:feature_code":"PPL",
    "gn:name":"Las Flores Cinco Poblados",
    "gn:population":631,
    "gn:timezone":"America/Mexico_City",
    "iso:country":"MX",
    "name:spa_x_preferred":[
        "Las Flores Cinco Poblados"
    ],
    "wof:name":"Las Flores Cinco Poblados",
    "wof:placetype":"locality",
    "wof:population":631
},
  "geometry": {"coordinates":[-97.78,20.9325],"type":"Point"}
}