{
  "type": "Feature",
  "properties": {
    "gn:admin1_code":"21",
    "gn:admin2_code":"1",
    "gn:asciiname":"San Bernardino Citlaltepetl",
    "gn:country_code":"MX",
    "gn:dem":2376,
    "gn:feature_class":"P",
    "gn:feature_code":"PPL",
    "gn:name":"San Bernardino Citlalt\u00e9petl",
    "gn:population":39,
    "gn:timezone":"America/Mexico_City",
    "iso:country":"MX",
    "name:und_x_variant":[
        "San Bernardino Citlalt\u00e9petl"
    ],
    "wof:name":"San Bernardino Citlaltepetl",
    "wof:placetype":"locality",
    "wof:population":39
},
  "geometry": {"coordinates":[-97.91973,19.08968],"type":"Point"}
}