{
  "type": "Feature",
  "properties": {
    "gn:admin1_code":"6",
    "gn:admin2_code":"27.0",
    "gn:asciiname":"Rancheria Remochochi",
    "gn:country_code":"MX",
    "gn:dem":2223,
    "gn:feature_class":"P",
    "gn:feature_code":"PPL",
    "gn:name":"Rancher\u00eda Remochochi",
    "gn:population":32,
    "gn:timezone":"America/Chihuahua",
    "iso:country":"MX",
    "name:spa_x_preferred":[
        "Rancher\u00eda Remochochi"
    ],
    "wof:name":"Rancheria Remochochi",
    "wof:placetype":"locality",
    "wof:population":32
},
  "geometry": {"coordinates":[-107.38907,27.13521],"type":"Point"}
}