{
  "type": "Feature",
  "properties": {
    "gn:admin1_code":"21",
    "gn:admin2_code":"187.0",
    "gn:asciiname":"La Lagunilla",
    "gn:country_code":"MX",
    "gn:dem":865,
    "gn:feature_class":"P",
    "gn:feature_code":"PPL",
    "gn:name":"La Lagunilla",
    "gn:population":0,
    "gn:timezone":"America/Mexico_City",
    "iso:country":"MX",
    "name:spa_x_preferred":[
        "La Lagunilla"
    ],
    "name:und_x_variant":[
        "Lagunilla",
        "Lagunita"
    ],
    "wof:name":"La Lagunilla",
    "wof:placetype":"locality"
},
  "geometry": {"coordinates":[-98.01327000000001,20.39688],"type":"Point"}
}