{
  "type": "Feature",
  "properties": {
    "gn:admin1_code":"9",
    "gn:admin2_code":"9.0",
    "gn:asciiname":"Colonia Teziuhtepec",
    "gn:country_code":"MX",
    "gn:dem":2858,
    "gn:feature_class":"P",
    "gn:feature_code":"PPL",
    "gn:name":"Colonia Teziuhtepec",
    "gn:population":89,
    "gn:timezone":"America/Mexico_City",
    "iso:country":"MX",
    "wof:name":"Colonia Teziuhtepec",
    "wof:placetype":"locality",
    "wof:population":89
},
  "geometry": {"coordinates":[-99.07083,19.17194],"type":"Point"}
}