{
  "type": "Feature",
  "properties": {
    "gn:admin1_code":"10",
    "gn:admin2_code":"35",
    "gn:asciiname":"Bajio de Caballos",
    "gn:country_code":"MX",
    "gn:dem":2692,
    "gn:feature_class":"P",
    "gn:feature_code":"PPL",
    "gn:name":"Baj\u00edo de Caballos",
    "gn:population":25,
    "gn:timezone":"America/Monterrey",
    "iso:country":"MX",
    "name:und_x_variant":[
        "Baj\u00edo de Caballos"
    ],
    "wof:name":"Bajio de Caballos",
    "wof:placetype":"locality",
    "wof:population":25
},
  "geometry": {"coordinates":[-106.17455,25.77247],"type":"Point"}
}