{
  "type": "Feature",
  "properties": {
    "gn:admin1_code":"28.0",
    "gn:admin2_code":"42.0",
    "gn:asciiname":"Los Olivos",
    "gn:country_code":"MX",
    "gn:dem":447,
    "gn:feature_class":"P",
    "gn:feature_code":"PPL",
    "gn:name":"Los Olivos",
    "gn:population":0,
    "gn:timezone":"America/Monterrey",
    "iso:country":"MX",
    "name:spa_x_preferred":[
        "Los Olivos"
    ],
    "wof:name":"Los Olivos",
    "wof:placetype":"locality"
},
  "geometry": {"coordinates":[-99.53666,24.5102],"type":"Point"}
}