{
  "type": "Feature",
  "properties": {
    "gn:admin1_code":"28",
    "gn:admin2_code":"22.0",
    "gn:asciiname":"Primer Campo Pesquero",
    "gn:country_code":"MX",
    "gn:dem":6,
    "gn:feature_class":"P",
    "gn:feature_code":"PPL",
    "gn:name":"Primer Campo Pesquero",
    "gn:population":493,
    "gn:timezone":"America/Matamoros",
    "iso:country":"MX",
    "wof:name":"Primer Campo Pesquero",
    "wof:placetype":"locality",
    "wof:population":493
},
  "geometry": {"coordinates":[-97.15333,25.81778],"type":"Point"}
}