{
  "type": "Feature",
  "properties": {
    "gn:admin1_code":"13",
    "gn:admin2_code":"53.0",
    "gn:asciiname":"El Mavodo",
    "gn:country_code":"MX",
    "gn:dem":1222,
    "gn:feature_class":"P",
    "gn:feature_code":"PPL",
    "gn:name":"El Mavodo",
    "gn:population":343,
    "gn:timezone":"America/Mexico_City",
    "iso:country":"MX",
    "wof:name":"El Mavodo",
    "wof:placetype":"locality",
    "wof:population":343
},
  "geometry": {"coordinates":[-98.19806,20.41778],"type":"Point"}
}