{
  "type": "Feature",
  "properties": {
    "gn:admin1_code":"18.0",
    "gn:admin2_code":"17.0",
    "gn:asciiname":"Crucero de San Blas",
    "gn:country_code":"MX",
    "gn:dem":243,
    "gn:feature_class":"P",
    "gn:feature_code":"PPL",
    "gn:name":"Crucero de San Blas",
    "gn:population":57,
    "gn:timezone":"America/Mazatlan",
    "iso:country":"MX",
    "wof:name":"Crucero de San Blas",
    "wof:placetype":"locality",
    "wof:population":57
},
  "geometry": {"coordinates":[-105.05110999999999,21.69652],"type":"Point"}
}