{
  "type": "Feature",
  "properties": {
    "gn:admin1_code":"13.0",
    "gn:admin2_code":"26.0",
    "gn:asciiname":"Copaltitla",
    "gn:country_code":"MX",
    "gn:dem":459,
    "gn:feature_class":"P",
    "gn:feature_code":"PPL",
    "gn:name":"Copaltitla",
    "gn:population":379,
    "gn:timezone":"America/Mexico_City",
    "iso:country":"MX",
    "name:spa_x_preferred":[
        "Copaltitla"
    ],
    "wof:name":"Copaltitla",
    "wof:placetype":"locality",
    "wof:population":379
},
  "geometry": {"coordinates":[-98.45305999999999,21.01611],"type":"Point"}
}