{
  "type": "Feature",
  "properties": {
    "gn:admin1_code":"16.0",
    "gn:admin2_code":"107.0",
    "gn:asciiname":"Tirincaro",
    "gn:country_code":"MX",
    "gn:dem":1993,
    "gn:feature_class":"P",
    "gn:feature_code":"PPL",
    "gn:name":"Tirincaro",
    "gn:population":0,
    "gn:timezone":"America/Mexico_City",
    "iso:country":"MX",
    "wof:name":"Tirincaro",
    "wof:placetype":"locality"
},
  "geometry": {"coordinates":[-101.75,19.77083],"type":"Point"}
}