{
  "type": "Feature",
  "properties": {
    "gn:admin1_code":"15",
    "gn:admin2_code":"47.0",
    "gn:asciiname":"Moxteje",
    "gn:country_code":"MX",
    "gn:dem":2623,
    "gn:feature_class":"P",
    "gn:feature_code":"PPL",
    "gn:name":"Moxtej\u00e9",
    "gn:population":0,
    "gn:timezone":"America/Mexico_City",
    "iso:country":"MX",
    "name:und_x_variant":[
        "Mostej\u00e9",
        "Mosteg\u00e9",
        "Moxtej\u00e9",
        "Mastej\u00e9"
    ],
    "wof:name":"Moxteje",
    "wof:placetype":"locality"
},
  "geometry": {"coordinates":[-99.63057999999999,19.57287],"type":"Point"}
}