{
  "type": "Feature",
  "properties": {
    "gn:admin1_code":"14.0",
    "gn:admin2_code":"100.0",
    "gn:asciiname":"El Guayabillo",
    "gn:country_code":"MX",
    "gn:dem":37,
    "gn:feature_class":"P",
    "gn:feature_code":"PPL",
    "gn:name":"El Guayab\u00edllo",
    "gn:population":0,
    "gn:timezone":"America/Mexico_City",
    "iso:country":"MX",
    "name:spa_x_preferred":[
        "El Guayab\u00edllo"
    ],
    "wof:name":"El Guayabillo",
    "wof:placetype":"locality"
},
  "geometry": {"coordinates":[-105.22077,19.93244],"type":"Point"}
}