{
  "type": "Feature",
  "properties": {
    "gn:admin1_code":"5",
    "gn:admin2_code":"12.0",
    "gn:asciiname":"Piedras Leguas",
    "gn:country_code":"MX",
    "gn:dem":976,
    "gn:feature_class":"P",
    "gn:feature_code":"PPL",
    "gn:name":"Piedras Leguas",
    "gn:population":5,
    "gn:timezone":"America/Mexico_City",
    "iso:country":"MX",
    "wof:name":"Piedras Leguas",
    "wof:placetype":"locality",
    "wof:population":5
},
  "geometry": {"coordinates":[-93.29443999999999,16.81444],"type":"Point"}
}