{
  "type": "Feature",
  "properties": {
    "gn:admin1_code":"11.0",
    "gn:admin2_code":"19.0",
    "gn:asciiname":"El Sarampion",
    "gn:country_code":"MX",
    "gn:dem":2098,
    "gn:feature_class":"P",
    "gn:feature_code":"PPL",
    "gn:name":"El Sarampi\u00f3n",
    "gn:population":0,
    "gn:timezone":"America/Mexico_City",
    "iso:country":"MX",
    "name:spa_x_preferred":[
        "El Sarampi\u00f3n"
    ],
    "wof:name":"El Sarampion",
    "wof:placetype":"locality"
},
  "geometry": {"coordinates":[-100.53095999999999,20.21044],"type":"Point"}
}