{
  "type": "Feature",
  "properties": {
    "gn:admin1_code":"19.0",
    "gn:admin2_code":"23.0",
    "gn:asciiname":"El Cureno",
    "gn:country_code":"MX",
    "gn:dem":200,
    "gn:feature_class":"P",
    "gn:feature_code":"PPL",
    "gn:name":"El Cure\u00f1o",
    "gn:population":0,
    "gn:timezone":"America/Monterrey",
    "iso:country":"MX",
    "name:spa_x_preferred":[
        "El Cure\u00f1o"
    ],
    "wof:name":"El Cureno",
    "wof:placetype":"locality"
},
  "geometry": {"coordinates":[-99.55853999999999,26.19319],"type":"Point"}
}