{
  "type": "Feature",
  "properties": {
    "gn:admin1_code":"20",
    "gn:admin2_code":"171.0",
    "gn:asciiname":"Cerro Negro",
    "gn:country_code":"MX",
    "gn:dem":1077,
    "gn:feature_class":"P",
    "gn:feature_code":"PPL",
    "gn:name":"Cerro Negro",
    "gn:population":101,
    "gn:timezone":"America/Mexico_City",
    "iso:country":"MX",
    "wof:name":"Cerro Negro",
    "wof:placetype":"locality",
    "wof:population":101
},
  "geometry": {"coordinates":[-96.68944,18.16944],"type":"Point"}
}