{
  "type": "Feature",
  "properties": {
    "gn:admin1_code":"5",
    "gn:admin2_code":"107",
    "gn:asciiname":"El Zapotal (Villahermosa)",
    "gn:country_code":"MX",
    "gn:dem":926,
    "gn:feature_class":"P",
    "gn:feature_code":"PPL",
    "gn:name":"El Zapotal (Villahermosa)",
    "gn:population":15,
    "gn:timezone":"America/Mexico_City",
    "iso:country":"MX",
    "wof:name":"El Zapotal (Villahermosa)",
    "wof:placetype":"locality",
    "wof:population":15
},
  "geometry": {"coordinates":[-93.34583000000001,16.0425],"type":"Point"}
}