{
  "type": "Feature",
  "properties": {
    "gn:admin1_code":"32",
    "gn:admin2_code":"9.0",
    "gn:asciiname":"El Cura",
    "gn:country_code":"MX",
    "gn:dem":2167,
    "gn:feature_class":"P",
    "gn:feature_code":"PPL",
    "gn:name":"El Cura",
    "gn:population":0,
    "gn:timezone":"America/Mexico_City",
    "iso:country":"MX",
    "name:spa_x_preferred":[
        "El Cura"
    ],
    "wof:name":"El Cura",
    "wof:placetype":"locality"
},
  "geometry": {"coordinates":[-103.84744000000001,23.52895],"type":"Point"}
}