{
  "type": "Feature",
  "properties": {
    "gn:admin1_code":"3",
    "gn:admin2_code":"1.0",
    "gn:asciiname":"El Agua Relumbrosa",
    "gn:country_code":"MX",
    "gn:dem":235,
    "gn:feature_class":"P",
    "gn:feature_code":"PPL",
    "gn:name":"El Agua Relumbrosa",
    "gn:population":5,
    "gn:timezone":"America/Mazatlan",
    "iso:country":"MX",
    "wof:name":"El Agua Relumbrosa",
    "wof:placetype":"locality",
    "wof:population":5
},
  "geometry": {"coordinates":[-111.36662,25.40906],"type":"Point"}
}