{
  "type": "Feature",
  "properties": {
    "gn:admin1_code":"19",
    "gn:admin2_code":"41",
    "gn:asciiname":"La Florena [Avicola]",
    "gn:country_code":"MX",
    "gn:dem":292,
    "gn:feature_class":"P",
    "gn:feature_code":"PPL",
    "gn:name":"La Flore\u00f1a [Av\u00edcola]",
    "gn:population":52,
    "gn:timezone":"America/Monterrey",
    "iso:country":"MX",
    "name:und_x_variant":[
        "La Flore\u00f1a [Av\u00edcola]"
    ],
    "wof:name":"La Florena [Avicola]",
    "wof:placetype":"locality",
    "wof:population":52
},
  "geometry": {"coordinates":[-99.89279999999999,25.74228],"type":"Point"}
}