{
  "type": "Feature",
  "properties": {
    "gn:admin1_code":"10",
    "gn:admin2_code":"30.0",
    "gn:asciiname":"Puerto el Casco",
    "gn:country_code":"MX",
    "gn:dem":1957,
    "gn:feature_class":"P",
    "gn:feature_code":"PPL",
    "gn:name":"Puerto el Casco",
    "gn:population":0,
    "gn:timezone":"America/Monterrey",
    "iso:country":"MX",
    "name:spa_x_preferred":[
        "Puerto el Casco"
    ],
    "wof:name":"Puerto el Casco",
    "wof:placetype":"locality"
},
  "geometry": {"coordinates":[-104.58667,25.49978],"type":"Point"}
}