{
  "type": "Feature",
  "properties": {
    "gn:admin1_code":"32",
    "gn:admin2_code":"45.0",
    "gn:asciiname":"El Ocote",
    "gn:country_code":"MX",
    "gn:dem":2494,
    "gn:feature_class":"P",
    "gn:feature_code":"PPL",
    "gn:name":"El Ocote",
    "gn:population":0,
    "gn:timezone":"America/Mexico_City",
    "iso:country":"MX",
    "name:spa_x_preferred":[
        "El Ocote"
    ],
    "wof:name":"El Ocote",
    "wof:placetype":"locality"
},
  "geometry": {"coordinates":[-103.2593,21.56461],"type":"Point"}
}