{
  "type": "Feature",
  "properties": {
    "gn:admin1_code":"16",
    "gn:admin2_code":"49",
    "gn:asciiname":"Maravillas",
    "gn:country_code":"MX",
    "gn:dem":1532,
    "gn:feature_class":"P",
    "gn:feature_code":"PPL",
    "gn:name":"Maravillas",
    "gn:population":13,
    "gn:timezone":"America/Mexico_City",
    "iso:country":"MX",
    "name:ceb_x_preferred":[
        "Maravillas"
    ],
    "name:deu_x_preferred":[
        "Maravillas"
    ],
    "name:swe_x_preferred":[
        "Maravillas"
    ],
    "wof:name":"Maravillas",
    "wof:placetype":"locality",
    "wof:population":13
},
  "geometry": {"coordinates":[-101.11417,19.37833],"type":"Point"}
}