{
  "type": "Feature",
  "properties": {
    "gn:admin1_code":"30.0",
    "gn:admin2_code":"161.0",
    "gn:asciiname":"Los Manueles",
    "gn:country_code":"MX",
    "gn:dem":85,
    "gn:feature_class":"P",
    "gn:feature_code":"PPL",
    "gn:name":"Los Manueles",
    "gn:population":1,
    "gn:timezone":"America/Mexico_City",
    "iso:country":"MX",
    "name:spa_x_preferred":[
        "Los Manueles"
    ],
    "wof:name":"Los Manueles",
    "wof:placetype":"locality",
    "wof:population":1
},
  "geometry": {"coordinates":[-98.53055999999999,21.62528],"type":"Point"}
}