{
  "type": "Feature",
  "properties": {
    "gn:admin1_code":"11",
    "gn:admin2_code":"3.0",
    "gn:asciiname":"San Jeronimo de la Playa",
    "gn:country_code":"MX",
    "gn:dem":2051,
    "gn:feature_class":"P",
    "gn:feature_code":"PPL",
    "gn:name":"San Jer\u00f3nimo de la Playa",
    "gn:population":216,
    "gn:timezone":"America/Mexico_City",
    "iso:country":"MX",
    "name:und_x_variant":[
        "San Jer\u00f3nimo de la Playa"
    ],
    "wof:name":"San Jeronimo de la Playa",
    "wof:placetype":"locality",
    "wof:population":216
},
  "geometry": {"coordinates":[-100.67306000000001,20.95611],"type":"Point"}
}