{
  "type": "Feature",
  "properties": {
    "gn:admin1_code":"17",
    "gn:asciiname":"El Cohetero",
    "gn:country_code":"MX",
    "gn:dem":2566,
    "gn:feature_class":"P",
    "gn:feature_code":"PPL",
    "gn:name":"El Cohetero",
    "gn:population":0,
    "gn:timezone":"America/Mexico_City",
    "iso:country":"MX",
    "name:spa_x_preferred":[
        "El Cohetero"
    ],
    "wof:name":"El Cohetero",
    "wof:placetype":"locality"
},
  "geometry": {"coordinates":[-98.93474000000001,19.98903],"type":"Point"}
}