{
  "type": "Feature",
  "properties": {
    "gn:admin1_code":"6",
    "gn:admin2_code":"21.0",
    "gn:asciiname":"La Chabena (El Arete)",
    "gn:country_code":"MX",
    "gn:dem":1197,
    "gn:feature_class":"P",
    "gn:feature_code":"PPL",
    "gn:name":"La Chabe\u00f1a (El Arete)",
    "gn:population":6,
    "gn:timezone":"America/Chihuahua",
    "iso:country":"MX",
    "name:und_x_variant":[
        "La Chabe\u00f1a (El Arete)"
    ],
    "wof:name":"La Chabena (El Arete)",
    "wof:placetype":"locality",
    "wof:population":6
},
  "geometry": {"coordinates":[-105.43074,28.16659000000001],"type":"Point"}
}