{
  "type": "Feature",
  "properties": {
    "iso:country":"MX",
    "name:spa_x_preferred":[
        "Playas Del sur"
    ],
    "qs:gn_adm0_cc":"MX",
    "qs:gn_local":3996322,
    "qs:gn_nam_loc":"mazatlan",
    "qs:gn_namadm1":"25",
    "qs:local_max":927,
    "qs:local_sum":4580,
    "qs:localhoods":17,
    "qs:name":"Playas Del sur",
    "qs:name_adm0":"M\u00e9xico",
    "qs:name_adm1":"Sinaloa",
    "qs:name_adm2":"Mazatlan",
    "qs:name_local":"Mazatl\u00e1n",
    "qs:photo_max":47,
    "qs:photo_sum":260,
    "qs:placetype":"Suburb",
    "qs:quad_count":24,
    "qs:woe_adm0":23424900,
    "qs:woe_adm1":2346288,
    "qs:woe_adm2":12601538,
    "qs:woe_lau":0,
    "qs:woe_local":133233,
    "qs:woe_ver":"7.10.0",
    "qs_pg:name":"Playas Del sur",
    "qs_pg:name_adm0":"M\u00e9xico",
    "qs_pg:name_adm1":"Sinaloa",
    "qs_pg:photos":250,
    "qs_pg:photos_1k":51,
    "qs_pg:photos_9k":1,
    "qs_pg:photos_9r":4,
    "qs_pg:photos_all":250,
    "qs_pg:photos_sr":4,
    "qs_pg:pop_sr":0,
    "qs_pg:qs_pg_placetype":"neighbourhood",
    "qs_pg:qs_pg_placetype_gp":"Suburb",
    "qs_pg:woe_adm0":23424900,
    "woe:adm0_id":23424900,
    "woe:name_adm0":"M\u00e9xico",
    "woe:name_adm1":"Sinaloa",
    "woe:placetype":"Suburb",
    "wof:lang":[
        "spa"
    ],
    "wof:name":"Playas Del sur",
    "wof:placetype":"neighbourhood"
},
  "geometry": {"coordinates":[-106.426374,23.183875],"type":"Point"}
}