{
  "type": "Feature",
  "properties": {
    "gn:admin1_code":"30",
    "gn:admin2_code":"178.0",
    "gn:asciiname":"Cocina",
    "gn:country_code":"MX",
    "gn:dem":5,
    "gn:feature_class":"P",
    "gn:feature_code":"PPL",
    "gn:name":"Cocina",
    "gn:population":0,
    "gn:timezone":"America/Mexico_City",
    "iso:country":"MX",
    "name:ara_x_preferred":[
        "\u0645\u0637\u0628\u062e"
    ],
    "name:ast_x_preferred":[
        "Cocina"
    ],
    "name:cat_x_preferred":[
        "Cuina"
    ],
    "name:ceb_x_preferred":[
        "Cocina"
    ],
    "name:ita_x_preferred":[
        "Cucina"
    ],
    "name:lat_x_preferred":[
        "Cocina"
    ],
    "name:spa_x_preferred":[
        "Cocina"
    ],
    "name:swe_x_preferred":[
        "Cocina"
    ],
    "wof:name":"Cocina",
    "wof:placetype":"locality"
},
  "geometry": {"coordinates":[-95.53333000000001,18.45],"type":"Point"}
}