{
  "type": "Feature",
  "properties": {
    "gn:admin1_code":"16",
    "gn:admin2_code":"13.0",
    "gn:asciiname":"El Cuaulote",
    "gn:country_code":"MX",
    "gn:dem":745,
    "gn:feature_class":"P",
    "gn:feature_code":"PPL",
    "gn:name":"El Cuaulote",
    "gn:population":0,
    "gn:timezone":"America/Mexico_City",
    "iso:country":"MX",
    "name:spa_x_preferred":[
        "El Cuaulote"
    ],
    "wof:name":"El Cuaulote",
    "wof:placetype":"locality"
},
  "geometry": {"coordinates":[-100.9701,18.94525],"type":"Point"}
}