{
  "type": "Feature",
  "properties": {
    "gn:admin1_code":"5",
    "gn:admin2_code":"66",
    "gn:asciiname":"Yab Muctana",
    "gn:country_code":"MX",
    "gn:dem":1084,
    "gn:feature_class":"P",
    "gn:feature_code":"PPL",
    "gn:name":"Yab Muctana",
    "gn:population":30,
    "gn:timezone":"America/Mexico_City",
    "iso:country":"MX",
    "wof:name":"Yab Muctana",
    "wof:placetype":"locality",
    "wof:population":30
},
  "geometry": {"coordinates":[-92.49028,17.035],"type":"Point"}
}