{
  "type": "Feature",
  "properties": {
    "gn:admin1_code":"30",
    "gn:admin2_code":"160.0",
    "gn:asciiname":"La Esmeralda",
    "gn:country_code":"MX",
    "gn:dem":73,
    "gn:feature_class":"P",
    "gn:feature_code":"PPL",
    "gn:name":"La Esmeralda",
    "gn:population":5,
    "gn:timezone":"America/Mexico_City",
    "iso:country":"MX",
    "name:ceb_x_preferred":[
        "La Esmeralda"
    ],
    "name:deu_x_preferred":[
        "La Esmeralda"
    ],
    "name:ita_x_preferred":[
        "La Esmeralda"
    ],
    "name:sco_x_preferred":[
        "La Esmeralda"
    ],
    "name:spa_x_preferred":[
        "La Esmeralda"
    ],
    "name:srp_x_preferred":[
        "\u041b\u0430 \u0415\u0441\u043c\u0435\u0440\u0430\u043b\u0434\u0430"
    ],
    "name:swe_x_preferred":[
        "La Esmeralda"
    ],
    "wof:name":"La Esmeralda",
    "wof:placetype":"locality",
    "wof:population":5
},
  "geometry": {"coordinates":[-97.58917,20.82083],"type":"Point"}
}