{
  "type": "Feature",
  "properties": {
    "gn:admin1_code":"16",
    "gn:admin2_code":"13.0",
    "gn:asciiname":"Cahuirica",
    "gn:country_code":"MX",
    "gn:dem":624,
    "gn:feature_class":"P",
    "gn:feature_code":"PPL",
    "gn:name":"Cahuirica",
    "gn:population":8,
    "gn:timezone":"America/Mexico_City",
    "iso:country":"MX",
    "wof:name":"Cahuirica",
    "wof:placetype":"locality",
    "wof:population":8
},
  "geometry": {"coordinates":[-100.99139,18.91139],"type":"Point"}
}