{
  "type": "Feature",
  "properties": {
    "gn:admin1_code":"19",
    "gn:admin2_code":"43.0",
    "gn:asciiname":"La Hacienda",
    "gn:country_code":"MX",
    "gn:dem":827,
    "gn:feature_class":"P",
    "gn:feature_code":"PPL",
    "gn:name":"La Hacienda",
    "gn:population":5,
    "gn:timezone":"America/Monterrey",
    "iso:country":"MX",
    "name:spa_x_preferred":[
        "La Hacienda"
    ],
    "wof:name":"La Hacienda",
    "wof:placetype":"locality",
    "wof:population":5
},
  "geometry": {"coordinates":[-100.07084,25.02479],"type":"Point"}
}