{
  "type": "Feature",
  "properties": {
    "gn:admin1_code":"28.0",
    "gn:admin2_code":"6.0",
    "gn:asciiname":"Albercas",
    "gn:country_code":"MX",
    "gn:dem":1620,
    "gn:feature_class":"P",
    "gn:feature_code":"PPL",
    "gn:name":"Albercas",
    "gn:population":0,
    "gn:timezone":"America/Monterrey",
    "iso:country":"MX",
    "wof:name":"Albercas",
    "wof:placetype":"locality"
},
  "geometry": {"coordinates":[-100.06261000000001,23.27152],"type":"Point"}
}