{
  "type": "Feature",
  "properties": {
    "gn:admin1_code":"30.0",
    "gn:admin2_code":"151.0",
    "gn:asciiname":"Paso de San Lorenzo",
    "gn:country_code":"MX",
    "gn:dem":17,
    "gn:feature_class":"P",
    "gn:feature_code":"PPL",
    "gn:name":"Paso de San Lorenzo",
    "gn:population":315,
    "gn:timezone":"America/Mexico_City",
    "iso:country":"MX",
    "name:spa_x_preferred":[
        "Paso de San Lorenzo"
    ],
    "wof:name":"Paso de San Lorenzo",
    "wof:placetype":"locality",
    "wof:population":315
},
  "geometry": {"coordinates":[-97.47583,21.19972000000001],"type":"Point"}
}