{
  "type": "Feature",
  "properties": {
    "gn:admin1_code":"5",
    "gn:admin2_code":"59",
    "gn:asciiname":"Chic Lacanwi'Ts",
    "gn:country_code":"MX",
    "gn:dem":913,
    "gn:feature_class":"P",
    "gn:feature_code":"PPL",
    "gn:name":"Chic Lacanwi'Ts",
    "gn:population":21,
    "gn:timezone":"America/Mexico_City",
    "iso:country":"MX",
    "wof:name":"Chic Lacanwi'Ts",
    "wof:placetype":"locality",
    "wof:population":21
},
  "geometry": {"coordinates":[-92.06610999999999,16.87278],"type":"Point"}
}