{
  "type": "Feature",
  "properties": {
    "gn:admin1_code":"11",
    "gn:admin2_code":"17",
    "gn:asciiname":"Granja los Hernandez (Ignacio Hernandez)",
    "gn:country_code":"MX",
    "gn:dem":1742,
    "gn:feature_class":"P",
    "gn:feature_code":"PPL",
    "gn:name":"Granja los Hern\u00e1ndez (Ignacio Hern\u00e1ndez)",
    "gn:population":11,
    "gn:timezone":"America/Mexico_City",
    "iso:country":"MX",
    "name:und_x_variant":[
        "Granja los Hern\u00e1ndez (Ignacio Hern\u00e1ndez)"
    ],
    "wof:name":"Granja los Hernandez (Ignacio Hernandez)",
    "wof:placetype":"locality",
    "wof:population":11
},
  "geometry": {"coordinates":[-101.42,20.78583],"type":"Point"}
}