{
  "type": "Feature",
  "properties": {
    "gn:admin1_code":"3",
    "gn:admin2_code":"2",
    "gn:asciiname":"La Ramadita",
    "gn:country_code":"MX",
    "gn:dem":10,
    "gn:feature_class":"P",
    "gn:feature_code":"PPL",
    "gn:name":"La Ramadita",
    "gn:population":10,
    "gn:timezone":"America/Mazatlan",
    "iso:country":"MX",
    "name:spa_x_preferred":[
        "La Ramadita"
    ],
    "name:urd_x_preferred":[
        "\u0644\u0627 \u0631\u0627\u0645\u0627\u0688\u06cc\u0679\u0627"
    ],
    "wof:name":"La Ramadita",
    "wof:placetype":"locality",
    "wof:population":10
},
  "geometry": {"coordinates":[-111.56974,26.58426],"type":"Point"}
}