{
  "type": "Feature",
  "properties": {
    "gn:admin1_code":"30",
    "gn:admin2_code":"129",
    "gn:asciiname":"Coyolar",
    "gn:country_code":"MX",
    "gn:dem":58,
    "gn:feature_class":"P",
    "gn:feature_code":"PPL",
    "gn:name":"Coyolar",
    "gn:population":41,
    "gn:timezone":"America/Mexico_City",
    "iso:country":"MX",
    "wof:name":"Coyolar",
    "wof:placetype":"locality",
    "wof:population":41
},
  "geometry": {"coordinates":[-98.34305999999999,21.27972],"type":"Point"}
}