{
  "type": "Feature",
  "properties": {
    "gn:admin1_code":"5",
    "gn:admin2_code":"108.0",
    "gn:asciiname":"Alto de las Flores",
    "gn:country_code":"MX",
    "gn:dem":591,
    "gn:feature_class":"P",
    "gn:feature_code":"PPL",
    "gn:name":"Alto de las Flores",
    "gn:population":7,
    "gn:timezone":"America/Mexico_City",
    "iso:country":"MX",
    "wof:name":"Alto de las Flores",
    "wof:placetype":"locality",
    "wof:population":7
},
  "geometry": {"coordinates":[-93.26917,16.2875],"type":"Point"}
}