{
  "type": "Feature",
  "properties": {
    "gn:admin1_code":"12",
    "gn:admin2_code":"3",
    "gn:asciiname":"Los Tepetates",
    "gn:country_code":"MX",
    "gn:dem":283,
    "gn:feature_class":"P",
    "gn:feature_code":"PPL",
    "gn:name":"Los Tepetates",
    "gn:population":12,
    "gn:timezone":"America/Mexico_City",
    "iso:country":"MX",
    "wof:name":"Los Tepetates",
    "wof:placetype":"locality",
    "wof:population":12
},
  "geometry": {"coordinates":[-100.46944999999999,18.1748],"type":"Point"}
}