{
  "type": "Feature",
  "properties": {
    "gn:admin1_code":"27.0",
    "gn:asciiname":"Gustavo Adolfo Madero",
    "gn:country_code":"MX",
    "gn:dem":6,
    "gn:feature_class":"P",
    "gn:feature_code":"PPL",
    "gn:name":"Gustavo Adolfo Madero",
    "gn:population":0,
    "gn:timezone":"America/Mexico_City",
    "iso:country":"MX",
    "name:spa_x_preferred":[
        "Gustavo Adolfo Madero"
    ],
    "wof:name":"Gustavo Adolfo Madero",
    "wof:placetype":"locality"
},
  "geometry": {"coordinates":[-92.65828999999999,17.87012],"type":"Point"}
}