{
  "type": "Feature",
  "properties": {
    "gn:admin1_code":"23",
    "gn:admin2_code":"5.0",
    "gn:asciiname":"Lluvias de Oro",
    "gn:country_code":"MX",
    "gn:dem":18,
    "gn:feature_class":"P",
    "gn:feature_code":"PPL",
    "gn:name":"Lluvias de Oro",
    "gn:population":8,
    "gn:timezone":"America/Cancun",
    "iso:country":"MX",
    "wof:name":"Lluvias de Oro",
    "wof:placetype":"locality",
    "wof:population":8
},
  "geometry": {"coordinates":[-87.11015999999999,21.02982],"type":"Point"}
}