{
  "type": "Feature",
  "properties": {
    "gn:admin1_code":"6",
    "gn:admin2_code":"55.0",
    "gn:asciiname":"Catorce de Julio",
    "gn:country_code":"MX",
    "gn:dem":1172,
    "gn:feature_class":"P",
    "gn:feature_code":"PPL",
    "gn:name":"Catorce de Julio",
    "gn:population":5,
    "gn:timezone":"America/Chihuahua",
    "iso:country":"MX",
    "wof:name":"Catorce de Julio",
    "wof:placetype":"locality",
    "wof:population":5
},
  "geometry": {"coordinates":[-105.55158,28.21826],"type":"Point"}
}