{
  "type": "Feature",
  "properties": {
    "gn:admin1_code":"26.0",
    "gn:admin2_code":"13.0",
    "gn:asciiname":"El Ojo de Agua",
    "gn:cc2":"MX",
    "gn:country_code":"MX",
    "gn:dem":767,
    "gn:feature_class":"P",
    "gn:feature_code":"PPL",
    "gn:name":"El Ojo de Agua",
    "gn:population":0,
    "gn:timezone":"America/Hermosillo",
    "iso:country":"MX",
    "name:und_x_variant":[
        "Ojo de Agua",
        "El Ojo de Agua"
    ],
    "wof:name":"El Ojo de Agua",
    "wof:placetype":"locality"
},
  "geometry": {"coordinates":[-110.16667,29.95],"type":"Point"}
}