{
  "type": "Feature",
  "properties": {
    "gn:admin1_code":"19",
    "gn:admin2_code":"38.0",
    "gn:asciiname":"Huerta el Vergel",
    "gn:country_code":"MX",
    "gn:dem":403,
    "gn:feature_class":"P",
    "gn:feature_code":"PPL",
    "gn:name":"Huerta el Vergel",
    "gn:population":7,
    "gn:timezone":"America/Monterrey",
    "iso:country":"MX",
    "wof:name":"Huerta el Vergel",
    "wof:placetype":"locality",
    "wof:population":7
},
  "geometry": {"coordinates":[-99.81223,25.17674],"type":"Point"}
}