{
  "type": "Feature",
  "properties": {
    "gn:admin1_code":"30",
    "gn:admin2_code":"143.0",
    "gn:asciiname":"Alonzo Lazaro",
    "gn:country_code":"MX",
    "gn:dem":12,
    "gn:feature_class":"P",
    "gn:feature_code":"PPL",
    "gn:name":"Alonzo L\u00e1zaro",
    "gn:population":0,
    "gn:timezone":"America/Mexico_City",
    "iso:country":"MX",
    "wof:name":"Alonzo Lazaro",
    "wof:placetype":"locality"
},
  "geometry": {"coordinates":[-95.48642,18.41695],"type":"Point"}
}