{
  "type": "Feature",
  "properties": {
    "gn:admin1_code":"5.0",
    "gn:admin2_code":"12.0",
    "gn:asciiname":"Buena Vista",
    "gn:country_code":"MX",
    "gn:dem":978,
    "gn:feature_class":"P",
    "gn:feature_code":"PPL",
    "gn:name":"Buena Vista",
    "gn:population":0,
    "gn:timezone":"America/Mexico_City",
    "iso:country":"MX",
    "name:spa_x_preferred":[
        "Buena Vista"
    ],
    "wof:name":"Buena Vista",
    "wof:placetype":"locality"
},
  "geometry": {"coordinates":[-93.34444000000001,16.83792],"type":"Point"}
}