{
  "type": "Feature",
  "properties": {
    "gn:admin1_code":"18.0",
    "gn:admin2_code":"1.0",
    "gn:asciiname":"Anamorita de Abajo",
    "gn:country_code":"MX",
    "gn:dem":33,
    "gn:feature_class":"P",
    "gn:feature_code":"PPL",
    "gn:name":"Anamorita de Abajo",
    "gn:population":0,
    "gn:timezone":"America/Mazatlan",
    "iso:country":"MX",
    "wof:name":"Anamorita de Abajo",
    "wof:placetype":"locality"
},
  "geometry": {"coordinates":[-105.34583000000001,22.52917],"type":"Point"}
}