{
  "type": "Feature",
  "properties": {
    "gn:admin1_code":"14",
    "gn:admin2_code":"66.0",
    "gn:asciiname":"Los Guajes",
    "gn:country_code":"MX",
    "gn:dem":1534,
    "gn:feature_class":"P",
    "gn:feature_code":"PPL",
    "gn:name":"Los Guajes",
    "gn:population":50,
    "gn:timezone":"America/Mexico_City",
    "iso:country":"MX",
    "wof:name":"Los Guajes",
    "wof:placetype":"locality",
    "wof:population":50
},
  "geometry": {"coordinates":[-102.79028,20.32472000000001],"type":"Point"}
}