{
  "type": "Feature",
  "properties": {
    "gn:admin1_code":"30.0",
    "gn:admin2_code":"123.0",
    "gn:asciiname":"Loreto",
    "gn:country_code":"MX",
    "gn:dem":22,
    "gn:feature_class":"P",
    "gn:feature_code":"PPL",
    "gn:name":"Loreto",
    "gn:population":0,
    "gn:timezone":"America/Mexico_City",
    "iso:country":"MX",
    "name:spa_x_preferred":[
        "Loreto"
    ],
    "wof:name":"Loreto",
    "wof:placetype":"locality"
},
  "geometry": {"coordinates":[-98.16942,21.84685],"type":"Point"}
}