{
  "type": "Feature",
  "properties": {
    "gn:admin1_code":"10.0",
    "gn:admin2_code":"26.0",
    "gn:asciiname":"Agua Caliente",
    "gn:country_code":"MX",
    "gn:dem":2429,
    "gn:feature_class":"P",
    "gn:feature_code":"PPL",
    "gn:name":"Agua Caliente",
    "gn:population":0,
    "gn:timezone":"America/Monterrey",
    "iso:country":"MX",
    "name:bre_x_preferred":[
        "Agua Caliente"
    ],
    "name:ceb_x_preferred":[
        "Agua Caliente"
    ],
    "name:deu_x_preferred":[
        "Agua Caliente"
    ],
    "name:spa_x_preferred":[
        "Agua Caliente"
    ],
    "name:swe_x_preferred":[
        "Agua Caliente"
    ],
    "wof:name":"Agua Caliente",
    "wof:placetype":"locality"
},
  "geometry": {"coordinates":[-105.52448,24.39472],"type":"Point"}
}