{
  "type": "Feature",
  "properties": {
    "gn:admin1_code":"24",
    "gn:admin2_code":"28.0",
    "gn:asciiname":"Tanque Uresti",
    "gn:country_code":"MX",
    "gn:dem":1832,
    "gn:feature_class":"P",
    "gn:feature_code":"PPL",
    "gn:name":"Tanque Uresti",
    "gn:population":137,
    "gn:timezone":"America/Mexico_City",
    "iso:country":"MX",
    "wof:name":"Tanque Uresti",
    "wof:placetype":"locality",
    "wof:population":137
},
  "geometry": {"coordinates":[-100.94889000000001,22.29917],"type":"Point"}
}