{
  "type": "Feature",
  "properties": {
    "gn:admin1_code":"28",
    "gn:admin2_code":"35.0",
    "gn:asciiname":"San Ciprian",
    "gn:country_code":"MX",
    "gn:dem":20,
    "gn:feature_class":"P",
    "gn:feature_code":"PPL",
    "gn:name":"San Cipri\u00e1n",
    "gn:population":5,
    "gn:timezone":"America/Monterrey",
    "iso:country":"MX",
    "name:und_x_variant":[
        "San Cipri\u00e1n"
    ],
    "wof:name":"San Ciprian",
    "wof:placetype":"locality",
    "wof:population":5
},
  "geometry": {"coordinates":[-98.06917,25.20028],"type":"Point"}
}