{
  "type": "Feature",
  "properties": {
    "gn:admin1_code":"17",
    "gn:admin2_code":"29",
    "gn:asciiname":"Rancho las Trancas Amarillas",
    "gn:country_code":"MX",
    "gn:dem":1220,
    "gn:feature_class":"P",
    "gn:feature_code":"PPL",
    "gn:name":"Rancho las Trancas Amarillas",
    "gn:population":10,
    "gn:timezone":"America/Mexico_City",
    "iso:country":"MX",
    "wof:name":"Rancho las Trancas Amarillas",
    "wof:placetype":"locality",
    "wof:population":10
},
  "geometry": {"coordinates":[-99.03667,18.88111],"type":"Point"}
}