{
  "type": "Feature",
  "properties": {
    "gn:admin1_code":"11",
    "gn:admin2_code":"14.0",
    "gn:asciiname":"Rancho la Via Seca",
    "gn:country_code":"MX",
    "gn:dem":2008,
    "gn:feature_class":"P",
    "gn:feature_code":"PPL",
    "gn:name":"Rancho la V\u00eda Seca",
    "gn:population":5,
    "gn:timezone":"America/Mexico_City",
    "iso:country":"MX",
    "name:und_x_variant":[
        "Rancho la V\u00eda Seca"
    ],
    "wof:name":"Rancho la Via Seca",
    "wof:placetype":"locality",
    "wof:population":5
},
  "geometry": {"coordinates":[-100.93361,21.2925],"type":"Point"}
}