{
  "type": "Feature",
  "properties": {
    "gn:admin1_code":"12",
    "gn:admin2_code":"28.0",
    "gn:asciiname":"Sulchuchu",
    "gn:country_code":"MX",
    "gn:dem":1603,
    "gn:feature_class":"P",
    "gn:feature_code":"PPL",
    "gn:name":"Sulchuchu",
    "gn:population":0,
    "gn:timezone":"America/Mexico_City",
    "iso:country":"MX",
    "name:spa_x_preferred":[
        "Sulchuchu"
    ],
    "name:und_x_variant":[
        "Sulchuchio",
        "Sulchuch"
    ],
    "wof:name":"Sulchuchu",
    "wof:placetype":"locality"
},
  "geometry": {"coordinates":[-99.0992,17.61458],"type":"Point"}
}