{
  "type": "Feature",
  "properties": {
    "gn:admin1_code":"15",
    "gn:admin2_code":"96.0",
    "gn:asciiname":"La Esperanza",
    "gn:country_code":"MX",
    "gn:dem":2262,
    "gn:feature_class":"P",
    "gn:feature_code":"PPL",
    "gn:name":"La Esperanza",
    "gn:population":0,
    "gn:timezone":"America/Mexico_City",
    "iso:country":"MX",
    "wof:name":"La Esperanza",
    "wof:placetype":"locality"
},
  "geometry": {"coordinates":[-99.10861,19.93944],"type":"Point"}
}