{
  "type": "Feature",
  "properties": {
    "gn:admin1_code":"21",
    "gn:admin2_code":"145.0",
    "gn:asciiname":"Tecolotepec",
    "gn:country_code":"MX",
    "gn:dem":1179,
    "gn:feature_class":"P",
    "gn:feature_code":"PPL",
    "gn:name":"Tecolotepec",
    "gn:population":329,
    "gn:timezone":"America/Mexico_City",
    "iso:country":"MX",
    "wof:name":"Tecolotepec",
    "wof:placetype":"locality",
    "wof:population":329
},
  "geometry": {"coordinates":[-96.85906,18.2765],"type":"Point"}
}