{
  "type": "Feature",
  "properties": {
    "gn:admin1_code":"2.0",
    "gn:admin2_code":"2.0",
    "gn:asciiname":"Centinela Segunda Seccion",
    "gn:country_code":"MX",
    "gn:dem":-2,
    "gn:feature_class":"P",
    "gn:feature_code":"PPL",
    "gn:name":"Centinela Segunda Secci\u00f3n",
    "gn:population":0,
    "gn:timezone":"America/Tijuana",
    "iso:country":"MX",
    "name:spa_x_preferred":[
        "Centinela Segunda Secci\u00f3n"
    ],
    "wof:name":"Centinela Segunda Seccion",
    "wof:placetype":"locality"
},
  "geometry": {"coordinates":[-115.60187000000001,32.65009000000001],"type":"Point"}
}