{
  "type": "Feature",
  "properties": {
    "gn:admin1_code":"15",
    "gn:admin2_code":"93",
    "gn:asciiname":"Rancho Molino Blanco",
    "gn:country_code":"MX",
    "gn:dem":2330,
    "gn:feature_class":"P",
    "gn:feature_code":"PPL",
    "gn:name":"Rancho Molino Blanco",
    "gn:population":30,
    "gn:timezone":"America/Mexico_City",
    "iso:country":"MX",
    "wof:name":"Rancho Molino Blanco",
    "wof:placetype":"locality",
    "wof:population":30
},
  "geometry": {"coordinates":[-98.82145,19.55444],"type":"Point"}
}