{
  "type": "Feature",
  "properties": {
    "gn:admin1_code":"2",
    "gn:admin2_code":"1.0",
    "gn:asciiname":"Las Cabras",
    "gn:country_code":"MX",
    "gn:dem":606,
    "gn:feature_class":"P",
    "gn:feature_code":"PPL",
    "gn:name":"Las Cabras",
    "gn:population":0,
    "gn:timezone":"America/Tijuana",
    "iso:country":"MX",
    "name:ceb_x_preferred":[
        "Las Cabras"
    ],
    "name:kor_x_preferred":[
        "\ub77c\uc2a4\uce74\ube0c\ub77c\uc2a4"
    ],
    "name:swe_x_preferred":[
        "Las Cabras"
    ],
    "wof:name":"Las Cabras",
    "wof:placetype":"locality"
},
  "geometry": {"coordinates":[-115.84999999999999,31.01667],"type":"Point"}
}