{
  "type": "Feature",
  "properties": {
    "gn:admin1_code":"8",
    "gn:admin2_code":"9.0",
    "gn:asciiname":"El Columpio (Sergio Navarro)",
    "gn:country_code":"MX",
    "gn:dem":37,
    "gn:feature_class":"P",
    "gn:feature_code":"PPL",
    "gn:name":"El Columpio (Sergio Navarro)",
    "gn:population":4,
    "gn:timezone":"America/Mexico_City",
    "iso:country":"MX",
    "wof:name":"El Columpio (Sergio Navarro)",
    "wof:placetype":"locality",
    "wof:population":4
},
  "geometry": {"coordinates":[-103.9425,18.95139],"type":"Point"}
}