{
  "type": "Feature",
  "properties": {
    "gn:admin1_code":"16",
    "gn:admin2_code":"28.0",
    "gn:asciiname":"Torrecillas",
    "gn:country_code":"MX",
    "gn:dem":2031,
    "gn:feature_class":"P",
    "gn:feature_code":"PPL",
    "gn:name":"Torrecillas",
    "gn:population":0,
    "gn:timezone":"America/Mexico_City",
    "iso:country":"MX",
    "wof:name":"Torrecillas",
    "wof:placetype":"locality"
},
  "geometry": {"coordinates":[-102.01151,20.08523],"type":"Point"}
}