{
  "type": "Feature",
  "properties": {
    "gn:admin1_code":"14",
    "gn:admin2_code":"123.0",
    "gn:asciiname":"El Tejolote",
    "gn:country_code":"MX",
    "gn:dem":1689,
    "gn:feature_class":"P",
    "gn:feature_code":"PPL",
    "gn:name":"El Tejolote",
    "gn:population":5,
    "gn:timezone":"America/Mexico_City",
    "iso:country":"MX",
    "wof:name":"El Tejolote",
    "wof:placetype":"locality",
    "wof:population":5
},
  "geometry": {"coordinates":[-103.00028,20.47806],"type":"Point"}
}