{
  "type": "Feature",
  "properties": {
    "gn:admin1_code":"14",
    "gn:asciiname":"Puente",
    "gn:country_code":"MX",
    "gn:dem":1837,
    "gn:feature_class":"P",
    "gn:feature_code":"PPL",
    "gn:name":"Puente",
    "gn:population":0,
    "gn:timezone":"America/Mexico_City",
    "iso:country":"MX",
    "name:deu_x_preferred":[
        "Puente"
    ],
    "name:fra_x_preferred":[
        "Puente"
    ],
    "name:glg_x_preferred":[
        "Puente"
    ],
    "name:por_x_preferred":[
        "Puente"
    ],
    "name:spa_x_preferred":[
        "Puente"
    ],
    "wof:name":"Puente",
    "wof:placetype":"locality"
},
  "geometry": {"coordinates":[-103.86242,22.74808],"type":"Point"}
}