{
  "type": "Feature",
  "properties": {
    "gn:admin1_code":"7",
    "gn:admin2_code":"4.0",
    "gn:asciiname":"La Coyotera",
    "gn:country_code":"MX",
    "gn:dem":2307,
    "gn:feature_class":"P",
    "gn:feature_code":"PPL",
    "gn:name":"La Coyotera",
    "gn:population":0,
    "gn:timezone":"America/Monterrey",
    "iso:country":"MX",
    "name:spa_x_preferred":[
        "La Coyotera"
    ],
    "wof:name":"La Coyotera",
    "wof:placetype":"locality"
},
  "geometry": {"coordinates":[-100.62976999999999,25.42986],"type":"Point"}
}