{
  "type": "Feature",
  "properties": {
    "gn:admin1_code":"27",
    "gn:admin2_code":"4.0",
    "gn:asciiname":"El Rosario y el Quemado",
    "gn:country_code":"MX",
    "gn:dem":11,
    "gn:feature_class":"P",
    "gn:feature_code":"PPL",
    "gn:name":"El Rosario y el Quemado",
    "gn:population":943,
    "gn:timezone":"America/Mexico_City",
    "iso:country":"MX",
    "wof:name":"El Rosario y el Quemado",
    "wof:placetype":"locality",
    "wof:population":943
},
  "geometry": {"coordinates":[-92.92222,17.88722000000001],"type":"Point"}
}