{
  "type": "Feature",
  "properties": {
    "gn:admin1_code":"16.0",
    "gn:asciiname":"Las Mananas",
    "gn:country_code":"MX",
    "gn:dem":1888,
    "gn:feature_class":"P",
    "gn:feature_code":"PPL",
    "gn:name":"Las Ma\u00f1anas",
    "gn:population":0,
    "gn:timezone":"America/Mexico_City",
    "iso:country":"MX",
    "name:spa_x_preferred":[
        "Las Ma\u00f1anas"
    ],
    "wof:name":"Las Mananas",
    "wof:placetype":"locality"
},
  "geometry": {"coordinates":[-102.54337,20.08705],"type":"Point"}
}