{
  "type": "Feature",
  "properties": {
    "gn:admin1_code":"30",
    "gn:admin2_code":"56.0",
    "gn:asciiname":"El Cepillo",
    "gn:country_code":"MX",
    "gn:dem":92,
    "gn:feature_class":"P",
    "gn:feature_code":"PPL",
    "gn:name":"El Cepillo",
    "gn:population":192,
    "gn:timezone":"America/Mexico_City",
    "iso:country":"MX",
    "wof:name":"El Cepillo",
    "wof:placetype":"locality",
    "wof:population":192
},
  "geometry": {"coordinates":[-98.47221999999999,21.29833],"type":"Point"}
}