{
  "type": "Feature",
  "properties": {
    "gn:admin1_code":"6",
    "gn:admin2_code":"27.0",
    "gn:asciiname":"Rancho Repogueachi",
    "gn:country_code":"MX",
    "gn:dem":2196,
    "gn:feature_class":"P",
    "gn:feature_code":"PPL",
    "gn:name":"Rancho Repogueachi",
    "gn:population":0,
    "gn:timezone":"America/Chihuahua",
    "iso:country":"MX",
    "name:spa_x_preferred":[
        "Rancho Repogueachi"
    ],
    "wof:name":"Rancho Repogueachi",
    "wof:placetype":"locality"
},
  "geometry": {"coordinates":[-107.60769999999999,27.27909],"type":"Point"}
}