{
  "type": "Feature",
  "properties": {
    "gn:admin1_code":"5",
    "gn:admin2_code":"57.0",
    "gn:asciiname":"Las Cruces",
    "gn:country_code":"MX",
    "gn:dem":1941,
    "gn:feature_class":"P",
    "gn:feature_code":"PPL",
    "gn:name":"Las Cruces",
    "gn:population":172,
    "gn:timezone":"America/Mexico_City",
    "iso:country":"MX",
    "name:ast_x_preferred":[
        "Las Cruces"
    ],
    "name:bre_x_preferred":[
        "Cruces"
    ],
    "name:ceb_x_preferred":[
        "Las Cruces"
    ],
    "name:fra_x_preferred":[
        "Las Cruces"
    ],
    "name:ita_x_preferred":[
        "Las Cruces"
    ],
    "name:sco_x_preferred":[
        "Las Cruces"
    ],
    "name:spa_x_preferred":[
        "Cruces"
    ],
    "name:swe_x_preferred":[
        "Las Cruces"
    ],
    "wof:name":"Las Cruces",
    "wof:placetype":"locality",
    "wof:population":172
},
  "geometry": {"coordinates":[-92.27667,15.33361],"type":"Point"}
}