{
  "type": "Feature",
  "properties": {
    "gn:admin1_code":"25.0",
    "gn:admin2_code":"15.0",
    "gn:asciiname":"Gavilan",
    "gn:country_code":"MX",
    "gn:dem":178,
    "gn:feature_class":"P",
    "gn:feature_code":"PPL",
    "gn:name":"Gavil\u00e1n",
    "gn:population":0,
    "gn:timezone":"America/Mazatlan",
    "iso:country":"MX",
    "name:ceb_x_preferred":[
        "Gavilan"
    ],
    "name:ita_x_preferred":[
        "Gavilan"
    ],
    "name:swe_x_preferred":[
        "Gavilan"
    ],
    "wof:name":"Gavilan",
    "wof:placetype":"locality"
},
  "geometry": {"coordinates":[-107.93333,25.23333],"type":"Point"}
}