{
  "type": "Feature",
  "properties": {
    "gn:admin1_code":"4",
    "gn:admin2_code":"4.0",
    "gn:asciiname":"Cinco de Febrero",
    "gn:country_code":"MX",
    "gn:dem":35,
    "gn:feature_class":"P",
    "gn:feature_code":"PPL",
    "gn:name":"Cinco de Febrero",
    "gn:population":0,
    "gn:timezone":"America/Merida",
    "iso:country":"MX",
    "name:spa_x_preferred":[
        "Cinco de Febrero"
    ],
    "wof:name":"Cinco de Febrero",
    "wof:placetype":"locality"
},
  "geometry": {"coordinates":[-90.63366000000001,18.85621],"type":"Point"}
}