{
  "type": "Feature",
  "properties": {
    "gn:admin1_code":"11.0",
    "gn:admin2_code":"3.0",
    "gn:asciiname":"Jalpa",
    "gn:country_code":"MX",
    "gn:dem":2030,
    "gn:feature_class":"P",
    "gn:feature_code":"PPL",
    "gn:name":"Jalpa",
    "gn:population":0,
    "gn:timezone":"America/Mexico_City",
    "iso:country":"MX",
    "name:spa_x_preferred":[
        "Jalpa"
    ],
    "wof:name":"Jalpa",
    "wof:placetype":"locality"
},
  "geometry": {"coordinates":[-100.61273,20.77217000000001],"type":"Point"}
}