{
  "type": "Feature",
  "properties": {
    "gn:admin1_code":"20",
    "gn:admin2_code":"325",
    "gn:asciiname":"Nisayola",
    "gn:country_code":"MX",
    "gn:dem":824,
    "gn:feature_class":"P",
    "gn:feature_code":"PPL",
    "gn:name":"Nisayola",
    "gn:population":50,
    "gn:timezone":"America/Mexico_City",
    "iso:country":"MX",
    "wof:name":"Nisayola",
    "wof:placetype":"locality",
    "wof:population":50
},
  "geometry": {"coordinates":[-95.94833,16.70583],"type":"Point"}
}