{
  "type": "Feature",
  "properties": {
    "gn:admin1_code":"14.0",
    "gn:admin2_code":"4.0",
    "gn:asciiname":"El Jazmin",
    "gn:country_code":"MX",
    "gn:dem":1446,
    "gn:feature_class":"P",
    "gn:feature_code":"PPL",
    "gn:name":"El Jazm\u00edn",
    "gn:population":0,
    "gn:timezone":"America/Mexico_City",
    "iso:country":"MX",
    "name:spa_x_preferred":[
        "El Jazm\u00edn"
    ],
    "wof:name":"El Jazmin",
    "wof:placetype":"locality"
},
  "geometry": {"coordinates":[-103.62909999999999,19.92684],"type":"Point"}
}