{
  "type": "Feature",
  "properties": {
    "gn:admin1_code":"24",
    "gn:admin2_code":"49",
    "gn:asciiname":"Crucero",
    "gn:country_code":"MX",
    "gn:dem":1989,
    "gn:feature_class":"P",
    "gn:feature_code":"PPL",
    "gn:name":"Crucero",
    "gn:population":16,
    "gn:timezone":"America/Mexico_City",
    "iso:country":"MX",
    "name:ceb_x_preferred":[
        "Crucero"
    ],
    "name:fas_x_preferred":[
        "\u06a9\u0631\u0648\u062b\u0631\u0648"
    ],
    "name:swe_x_preferred":[
        "Crucero"
    ],
    "wof:name":"Crucero",
    "wof:placetype":"locality",
    "wof:population":16
},
  "geometry": {"coordinates":[-102.20193999999999,23.07528],"type":"Point"}
}