{
  "type": "Feature",
  "properties": {
    "gn:admin1_code":"24",
    "gn:admin2_code":"1",
    "gn:asciiname":"Los Llanitos",
    "gn:country_code":"MX",
    "gn:dem":2218,
    "gn:feature_class":"P",
    "gn:feature_code":"PPL",
    "gn:name":"Los Llanitos",
    "gn:population":26,
    "gn:timezone":"America/Mexico_City",
    "iso:country":"MX",
    "name:ita_x_preferred":[
        "Los Llanitos"
    ],
    "name:spa_x_preferred":[
        "Los Llanitos"
    ],
    "name:zho_x_preferred":[
        "\u6d1b\u65af\u5229\u4e9e\u5c3c\u6258\u65af"
    ],
    "wof:name":"Los Llanitos",
    "wof:placetype":"locality",
    "wof:population":26
},
  "geometry": {"coordinates":[-101.20556000000001,22.48833],"type":"Point"}
}