{
  "type": "Feature",
  "properties": {
    "gn:admin1_code":"19",
    "gn:admin2_code":"24",
    "gn:asciiname":"El Coronado",
    "gn:country_code":"MX",
    "gn:dem":1412,
    "gn:feature_class":"P",
    "gn:feature_code":"PPL",
    "gn:name":"El Coronado",
    "gn:population":18,
    "gn:timezone":"America/Monterrey",
    "iso:country":"MX",
    "wof:name":"El Coronado",
    "wof:placetype":"locality",
    "wof:population":18
},
  "geometry": {"coordinates":[-99.76327999999999,23.96925],"type":"Point"}
}