{
  "type": "Feature",
  "properties": {
    "gn:admin1_code":"19.0",
    "gn:admin2_code":"33.0",
    "gn:asciiname":"San Juanito de los Lagos",
    "gn:country_code":"MX",
    "gn:dem":377,
    "gn:feature_class":"P",
    "gn:feature_code":"PPL",
    "gn:name":"San Juanito de los Lagos",
    "gn:population":0,
    "gn:timezone":"America/Monterrey",
    "iso:country":"MX",
    "name:spa_x_preferred":[
        "San Juanita de los Lagos"
    ],
    "name:spa_x_variant":[
        "San Juanito de los Lagos"
    ],
    "wof:name":"San Juanito de los Lagos",
    "wof:placetype":"locality"
},
  "geometry": {"coordinates":[-99.53937999999999,24.65837],"type":"Point"}
}