{
  "type": "Feature",
  "properties": {
    "gn:admin1_code":"30",
    "gn:admin2_code":"4.0",
    "gn:asciiname":"El Ojital",
    "gn:country_code":"MX",
    "gn:dem":90,
    "gn:feature_class":"P",
    "gn:feature_code":"PPL",
    "gn:name":"El Ojital",
    "gn:population":317,
    "gn:timezone":"America/Mexico_City",
    "iso:country":"MX",
    "wof:name":"El Ojital",
    "wof:placetype":"locality",
    "wof:population":317
},
  "geometry": {"coordinates":[-96.47722,19.68917],"type":"Point"}
}