{
  "type": "Feature",
  "properties": {
    "gn:admin1_code":"11",
    "gn:admin2_code":"35.0",
    "gn:asciiname":"Ojo de Agua de Otates",
    "gn:country_code":"MX",
    "gn:dem":1857,
    "gn:feature_class":"P",
    "gn:feature_code":"PPL",
    "gn:name":"Ojo de Agua de Otates",
    "gn:population":227,
    "gn:timezone":"America/Mexico_City",
    "iso:country":"MX",
    "wof:name":"Ojo de Agua de Otates",
    "wof:placetype":"locality",
    "wof:population":227
},
  "geometry": {"coordinates":[-101.00917,20.69194],"type":"Point"}
}