{
  "type": "Feature",
  "properties": {
    "gn:admin1_code":"26.0",
    "gn:admin2_code":"56.0",
    "gn:asciiname":"El Pueblito",
    "gn:cc2":"MX",
    "gn:country_code":"MX",
    "gn:dem":418,
    "gn:feature_class":"P",
    "gn:feature_code":"PPL",
    "gn:name":"El Pueblito",
    "gn:population":0,
    "gn:timezone":"America/Hermosillo",
    "iso:country":"MX",
    "name:und_x_variant":[
        "Pueblito",
        "El Pueblito"
    ],
    "wof:name":"El Pueblito",
    "wof:placetype":"locality"
},
  "geometry": {"coordinates":[-110.68333,29.53333],"type":"Point"}
}