{
  "type": "Feature",
  "properties": {
    "gn:admin1_code":"11",
    "gn:admin2_code":"3",
    "gn:asciiname":"San Roque (Hacienda de Tirado)",
    "gn:country_code":"MX",
    "gn:dem":1850,
    "gn:feature_class":"P",
    "gn:feature_code":"PPL",
    "gn:name":"San Roque (Hacienda de Tirado)",
    "gn:population":10,
    "gn:timezone":"America/Mexico_City",
    "iso:country":"MX",
    "wof:name":"San Roque (Hacienda de Tirado)",
    "wof:placetype":"locality",
    "wof:population":10
},
  "geometry": {"coordinates":[-100.79889,20.91972],"type":"Point"}
}