{
  "type": "Feature",
  "properties": {
    "gn:admin1_code":"25.0",
    "gn:admin2_code":"17.0",
    "gn:asciiname":"Cabrera de Inzunza",
    "gn:country_code":"MX",
    "gn:dem":83,
    "gn:feature_class":"P",
    "gn:feature_code":"PPL",
    "gn:name":"Cabrera de Inzunza",
    "gn:population":0,
    "gn:timezone":"America/Mazatlan",
    "iso:country":"MX",
    "name:spa_x_preferred":[
        "Cabrera de Inzunza"
    ],
    "name:und_x_variant":[
        "Cabrera de Insunza",
        "Cabrera"
    ],
    "wof:name":"Cabrera de Inzunza",
    "wof:placetype":"locality"
},
  "geometry": {"coordinates":[-108.29501,25.90785],"type":"Point"}
}