{
  "type": "Feature",
  "properties": {
    "gn:admin1_code":"21",
    "gn:asciiname":"Tablones",
    "gn:country_code":"MX",
    "gn:dem":84,
    "gn:feature_class":"P",
    "gn:feature_code":"PPL",
    "gn:name":"Tablones",
    "gn:population":0,
    "gn:timezone":"America/Mexico_City",
    "iso:country":"MX",
    "name:spa_x_preferred":[
        "Tablones"
    ],
    "wof:name":"Tablones",
    "wof:placetype":"locality"
},
  "geometry": {"coordinates":[-97.78897000000001,20.83903],"type":"Point"}
}