{
  "type": "Feature",
  "properties": {
    "gn:admin1_code":"20",
    "gn:admin2_code":"482.0",
    "gn:asciiname":"Cuadrilla",
    "gn:country_code":"MX",
    "gn:dem":18,
    "gn:feature_class":"P",
    "gn:feature_code":"PPL",
    "gn:name":"Cuadrilla",
    "gn:population":0,
    "gn:timezone":"America/Mexico_City",
    "iso:country":"MX",
    "name:arg_x_preferred":[
        "Quadrilla"
    ],
    "name:eus_x_preferred":[
        "Kuadrilla"
    ],
    "name:spa_x_preferred":[
        "Cuadrilla"
    ],
    "wof:name":"Cuadrilla",
    "wof:placetype":"locality"
},
  "geometry": {"coordinates":[-98.28333000000001,16.31667],"type":"Point"}
}