{
  "type": "Feature",
  "properties": {
    "gn:admin1_code":"16",
    "gn:admin2_code":"112.0",
    "gn:asciiname":"La Colonia de Aputzio",
    "gn:country_code":"MX",
    "gn:dem":2240,
    "gn:feature_class":"P",
    "gn:feature_code":"PPL",
    "gn:name":"La Colonia de Aputzio",
    "gn:population":431,
    "gn:timezone":"America/Mexico_City",
    "iso:country":"MX",
    "wof:name":"La Colonia de Aputzio",
    "wof:placetype":"locality",
    "wof:population":431
},
  "geometry": {"coordinates":[-100.33444,19.35222000000001],"type":"Point"}
}