{
  "type": "Feature",
  "properties": {
    "gn:admin1_code":"6",
    "gn:admin2_code":"27.0",
    "gn:asciiname":"Huahuarare",
    "gn:country_code":"MX",
    "gn:dem":2276,
    "gn:feature_class":"P",
    "gn:feature_code":"PPL",
    "gn:name":"Huahuarare",
    "gn:population":19,
    "gn:timezone":"America/Chihuahua",
    "iso:country":"MX",
    "wof:name":"Huahuarare",
    "wof:placetype":"locality",
    "wof:population":19
},
  "geometry": {"coordinates":[-107.20905999999999,27.09271],"type":"Point"}
}