{
  "type": "Feature",
  "properties": {
    "gn:admin1_code":"28",
    "gn:admin2_code":"32.0",
    "gn:asciiname":"El Desmontito",
    "gn:country_code":"MX",
    "gn:dem":127,
    "gn:feature_class":"P",
    "gn:feature_code":"PPL",
    "gn:name":"El Desmontito",
    "gn:population":9,
    "gn:timezone":"America/Matamoros",
    "iso:country":"MX",
    "wof:name":"El Desmontito",
    "wof:placetype":"locality",
    "wof:population":9
},
  "geometry": {"coordinates":[-98.40861,25.78917],"type":"Point"}
}