{
  "type": "Feature",
  "properties": {
    "gn:admin1_code":"23",
    "gn:admin2_code":"4.0",
    "gn:asciiname":"La Gueera",
    "gn:country_code":"MX",
    "gn:dem":140,
    "gn:feature_class":"P",
    "gn:feature_code":"PPL",
    "gn:name":"La G\u00fcera",
    "gn:population":5,
    "gn:timezone":"America/Cancun",
    "iso:country":"MX",
    "name:und_x_variant":[
        "La G\u00fcera"
    ],
    "wof:name":"La Gueera",
    "wof:placetype":"locality",
    "wof:population":5
},
  "geometry": {"coordinates":[-89.10469000000001,18.4703],"type":"Point"}
}