{
  "type": "Feature",
  "properties": {
    "gn:admin1_code":"32",
    "gn:admin2_code":"19",
    "gn:asciiname":"Realito de Arriba",
    "gn:country_code":"MX",
    "gn:dem":1490,
    "gn:feature_class":"P",
    "gn:feature_code":"PPL",
    "gn:name":"Realito de Arriba",
    "gn:population":30,
    "gn:timezone":"America/Mexico_City",
    "iso:country":"MX",
    "wof:name":"Realito de Arriba",
    "wof:placetype":"locality",
    "wof:population":30
},
  "geometry": {"coordinates":[-102.96167,21.59639],"type":"Point"}
}