{
  "type": "Feature",
  "properties": {
    "gn:admin1_code":"17",
    "gn:admin2_code":"28",
    "gn:asciiname":"Plan de Tlazala",
    "gn:country_code":"MX",
    "gn:dem":1140,
    "gn:feature_class":"P",
    "gn:feature_code":"PPL",
    "gn:name":"Plan de Tlazala",
    "gn:population":14,
    "gn:timezone":"America/Mexico_City",
    "iso:country":"MX",
    "wof:name":"Plan de Tlazala",
    "wof:placetype":"locality",
    "wof:population":14
},
  "geometry": {"coordinates":[-99.24705,18.8051],"type":"Point"}
}