{
  "type": "Feature",
  "properties": {
    "gn:admin1_code":"20",
    "gn:admin2_code":"474.0",
    "gn:asciiname":"San Francisco del Maguey",
    "gn:country_code":"MX",
    "gn:dem":81,
    "gn:feature_class":"P",
    "gn:feature_code":"PPL",
    "gn:name":"San Francisco del Maguey",
    "gn:population":0,
    "gn:timezone":"America/Mexico_City",
    "iso:country":"MX",
    "name:und_x_variant":[
        "Maguey",
        "El Maguey"
    ],
    "wof:name":"San Francisco del Maguey",
    "wof:placetype":"locality"
},
  "geometry": {"coordinates":[-98.30426,16.51015],"type":"Point"}
}