{
  "type": "Feature",
  "properties": {
    "gn:admin1_code":"26",
    "gn:admin2_code":"27.0",
    "gn:asciiname":"El Diesel",
    "gn:country_code":"MX",
    "gn:dem":1266,
    "gn:feature_class":"P",
    "gn:feature_code":"PPL",
    "gn:name":"El Diesel",
    "gn:population":0,
    "gn:timezone":"America/Hermosillo",
    "iso:country":"MX",
    "name:spa_x_preferred":[
        "El Diesel"
    ],
    "name:und_x_variant":[
        "Rancho El Disel"
    ],
    "wof:name":"El Diesel",
    "wof:placetype":"locality"
},
  "geometry": {"coordinates":[-109.64825999999999,31.0428],"type":"Point"}
}