{
  "type": "Feature",
  "properties": {
    "gn:admin1_code":"28.0",
    "gn:admin2_code":"27.0",
    "gn:asciiname":"Las Conchas",
    "gn:country_code":"MX",
    "gn:dem":227,
    "gn:feature_class":"P",
    "gn:feature_code":"PPL",
    "gn:name":"Las Conchas",
    "gn:population":0,
    "gn:timezone":"America/Matamoros",
    "iso:country":"MX",
    "name:spa_x_preferred":[
        "Las Conchas"
    ],
    "wof:name":"Las Conchas",
    "wof:placetype":"locality"
},
  "geometry": {"coordinates":[-99.86681,27.47936],"type":"Point"}
}