{
  "type": "Feature",
  "properties": {
    "gn:admin1_code":"24",
    "gn:admin2_code":"39",
    "gn:asciiname":"Lanim",
    "gn:country_code":"MX",
    "gn:dem":192,
    "gn:feature_class":"P",
    "gn:feature_code":"PPL",
    "gn:name":"Lanim",
    "gn:population":46,
    "gn:timezone":"America/Mexico_City",
    "iso:country":"MX",
    "wof:name":"Lanim",
    "wof:placetype":"locality",
    "wof:population":46
},
  "geometry": {"coordinates":[-98.80611,21.62028],"type":"Point"}
}