{
  "type": "Feature",
  "properties": {
    "gn:admin1_code":"16.0",
    "gn:admin2_code":"63.0",
    "gn:asciiname":"Botello (Altamira)",
    "gn:country_code":"MX",
    "gn:dem":1780,
    "gn:feature_class":"P",
    "gn:feature_code":"PPL",
    "gn:name":"Botello (Altamira)",
    "gn:population":376,
    "gn:timezone":"America/Mexico_City",
    "iso:country":"MX",
    "wof:name":"Botello (Altamira)",
    "wof:placetype":"locality",
    "wof:population":376
},
  "geometry": {"coordinates":[-101.73278000000001,19.98028],"type":"Point"}
}