{
  "type": "Feature",
  "properties": {
    "gn:admin1_code":"23",
    "gn:admin2_code":"6.0",
    "gn:asciiname":"Tabasco",
    "gn:country_code":"MX",
    "gn:dem":26,
    "gn:feature_class":"P",
    "gn:feature_code":"PPL",
    "gn:name":"Tabasco",
    "gn:population":263,
    "gn:timezone":"America/Cancun",
    "iso:country":"MX",
    "wof:name":"Tabasco",
    "wof:placetype":"locality",
    "wof:population":263
},
  "geometry": {"coordinates":[-88.685,19.97861],"type":"Point"}
}