{
  "type": "Feature",
  "properties": {
    "gn:admin1_code":"30",
    "gn:admin2_code":"122",
    "gn:asciiname":"Doctor Lucho",
    "gn:country_code":"MX",
    "gn:dem":17,
    "gn:feature_class":"P",
    "gn:feature_code":"PPL",
    "gn:name":"Doctor Lucho",
    "gn:population":10,
    "gn:timezone":"America/Mexico_City",
    "iso:country":"MX",
    "wof:name":"Doctor Lucho",
    "wof:placetype":"locality",
    "wof:population":10
},
  "geometry": {"coordinates":[-94.68111,18.11361],"type":"Point"}
}