{
  "type": "Feature",
  "properties": {
    "gn:admin1_code":"5.0",
    "gn:asciiname":"La Fortuna Alta",
    "gn:country_code":"MX",
    "gn:dem":547,
    "gn:feature_class":"P",
    "gn:feature_code":"PPL",
    "gn:name":"La Fortuna Alta",
    "gn:population":0,
    "gn:timezone":"America/Mexico_City",
    "iso:country":"MX",
    "name:spa_x_preferred":[
        "La Fortuna Alta"
    ],
    "wof:name":"La Fortuna Alta",
    "wof:placetype":"locality"
},
  "geometry": {"coordinates":[-92.26613999999999,15.04508],"type":"Point"}
}