{
  "type": "Feature",
  "properties": {
    "gn:admin1_code":"5",
    "gn:admin2_code":"52",
    "gn:asciiname":"Cuatro de Octubre",
    "gn:country_code":"MX",
    "gn:dem":1501,
    "gn:feature_class":"P",
    "gn:feature_code":"PPL",
    "gn:name":"Cuatro de Octubre",
    "gn:population":36,
    "gn:timezone":"America/Mexico_City",
    "iso:country":"MX",
    "wof:name":"Cuatro de Octubre",
    "wof:placetype":"locality",
    "wof:population":36
},
  "geometry": {"coordinates":[-91.82805999999999,16.26556],"type":"Point"}
}