{
  "type": "Feature",
  "properties": {
    "gn:admin1_code":"16",
    "gn:admin2_code":"92",
    "gn:asciiname":"Charco el Ansia",
    "gn:country_code":"MX",
    "gn:dem":914,
    "gn:feature_class":"P",
    "gn:feature_code":"PPL",
    "gn:name":"Charco el Ansia",
    "gn:population":16,
    "gn:timezone":"America/Mexico_City",
    "iso:country":"MX",
    "wof:name":"Charco el Ansia",
    "wof:placetype":"locality",
    "wof:population":16
},
  "geometry": {"coordinates":[-100.98611,19.08778],"type":"Point"}
}