{
  "type": "Feature",
  "properties": {
    "gn:admin1_code":"12",
    "gn:admin2_code":"45.0",
    "gn:asciiname":"Vista Hermosa",
    "gn:country_code":"MX",
    "gn:dem":1553,
    "gn:feature_class":"P",
    "gn:feature_code":"PPL",
    "gn:name":"Vista Hermosa",
    "gn:population":219,
    "gn:timezone":"America/Mexico_City",
    "iso:country":"MX",
    "name:ceb_x_preferred":[
        "Vista Hermosa"
    ],
    "name:deu_x_preferred":[
        "Vista Hermosa"
    ],
    "name:spa_x_preferred":[
        "Vista Hermosa"
    ],
    "name:swe_x_preferred":[
        "Vista Hermosa"
    ],
    "name:vie_x_preferred":[
        "Vista Hermosa"
    ],
    "wof:name":"Vista Hermosa",
    "wof:placetype":"locality",
    "wof:population":219
},
  "geometry": {"coordinates":[-98.67945,17.90772999999999],"type":"Point"}
}