{
  "type": "Feature",
  "properties": {
    "gn:admin1_code":"26.0",
    "gn:admin2_code":"49.0",
    "gn:asciiname":"El Cobre",
    "gn:country_code":"MX",
    "gn:dem":190,
    "gn:feature_class":"P",
    "gn:feature_code":"PPL",
    "gn:name":"El Cobre",
    "gn:population":0,
    "gn:timezone":"America/Hermosillo",
    "iso:country":"MX",
    "name:bre_x_preferred":[
        "El Cobre"
    ],
    "name:ceb_x_preferred":[
        "El Cobre"
    ],
    "name:deu_x_preferred":[
        "El Cobre"
    ],
    "name:spa_x_preferred":[
        "El Cobre"
    ],
    "name:swe_x_preferred":[
        "El Cobre"
    ],
    "wof:name":"El Cobre",
    "wof:placetype":"locality"
},
  "geometry": {"coordinates":[-109.56491,27.51696],"type":"Point"}
}