{
  "type": "Feature",
  "properties": {
    "gn:admin1_code":"6",
    "gn:admin2_code":"62.0",
    "gn:asciiname":"Los Alvarado",
    "gn:country_code":"MX",
    "gn:dem":1215,
    "gn:feature_class":"P",
    "gn:feature_code":"PPL",
    "gn:name":"Los Alvarado",
    "gn:population":10,
    "gn:timezone":"America/Chihuahua",
    "iso:country":"MX",
    "name:spa_x_preferred":[
        "Los Alvarado"
    ],
    "wof:name":"Los Alvarado",
    "wof:placetype":"locality",
    "wof:population":10
},
  "geometry": {"coordinates":[-105.31852000000001,28.0391],"type":"Point"}
}