{
  "type": "Feature",
  "properties": {
    "gn:admin1_code":"11",
    "gn:admin2_code":"45.0",
    "gn:asciiname":"El Revolcadero",
    "gn:country_code":"MX",
    "gn:dem":2299,
    "gn:feature_class":"P",
    "gn:feature_code":"PPL",
    "gn:name":"El Revolcadero",
    "gn:population":187,
    "gn:timezone":"America/Mexico_City",
    "iso:country":"MX",
    "wof:name":"El Revolcadero",
    "wof:placetype":"locality",
    "wof:population":187
},
  "geometry": {"coordinates":[-100.10527999999999,21.26444],"type":"Point"}
}