{
  "type": "Feature",
  "properties": {
    "gn:admin1_code":"28",
    "gn:admin2_code":"32.0",
    "gn:asciiname":"El Pinto",
    "gn:country_code":"MX",
    "gn:dem":78,
    "gn:feature_class":"P",
    "gn:feature_code":"PPL",
    "gn:name":"El Pinto",
    "gn:population":0,
    "gn:timezone":"America/Matamoros",
    "iso:country":"MX",
    "name:spa_x_preferred":[
        "El Pinto"
    ],
    "name:und_x_variant":[
        "Pinto"
    ],
    "wof:name":"El Pinto",
    "wof:placetype":"locality"
},
  "geometry": {"coordinates":[-98.39905,26.03185],"type":"Point"}
}