{
  "type": "Feature",
  "properties": {
    "gn:admin1_code":"6",
    "gn:admin2_code":"49.0",
    "gn:asciiname":"Paraje Los Chabacanos",
    "gn:country_code":"MX",
    "gn:dem":1805,
    "gn:feature_class":"P",
    "gn:feature_code":"PPL",
    "gn:name":"Paraje Los Chabacanos",
    "gn:population":0,
    "gn:timezone":"America/Chihuahua",
    "iso:country":"MX",
    "name:spa_x_preferred":[
        "Paraje Los Chabacanos"
    ],
    "wof:name":"Paraje Los Chabacanos",
    "wof:placetype":"locality"
},
  "geometry": {"coordinates":[-106.72803999999999,27.56384000000001],"type":"Point"}
}