{
  "type": "Feature",
  "properties": {
    "gn:admin1_code":"15",
    "gn:admin2_code":"45.0",
    "gn:asciiname":"Dexcani Alto",
    "gn:country_code":"MX",
    "gn:dem":2476,
    "gn:feature_class":"P",
    "gn:feature_code":"PPL",
    "gn:name":"Dexcani Alto",
    "gn:population":0,
    "gn:timezone":"America/Mexico_City",
    "iso:country":"MX",
    "name:spa_x_preferred":[
        "Dexcani Alto"
    ],
    "wof:name":"Dexcani Alto",
    "wof:placetype":"locality"
},
  "geometry": {"coordinates":[-99.49303999999999,19.93578],"type":"Point"}
}