{
  "type": "Feature",
  "properties": {
    "gn:admin1_code":"28",
    "gn:admin2_code":"22.0",
    "gn:asciiname":"Isla las Malvinas",
    "gn:country_code":"MX",
    "gn:dem":5,
    "gn:feature_class":"P",
    "gn:feature_code":"PPL",
    "gn:name":"Isla las Malvinas",
    "gn:population":296,
    "gn:timezone":"America/Matamoros",
    "iso:country":"MX",
    "wof:name":"Isla las Malvinas",
    "wof:placetype":"locality",
    "wof:population":296
},
  "geometry": {"coordinates":[-97.44722,25.25278],"type":"Point"}
}