{
  "type": "Feature",
  "properties": {
    "gn:admin1_code":"5",
    "gn:admin2_code":"31.0",
    "gn:asciiname":"Guayaza",
    "gn:country_code":"MX",
    "gn:dem":1352,
    "gn:feature_class":"P",
    "gn:feature_code":"PPL",
    "gn:name":"Guayaza",
    "gn:population":353,
    "gn:timezone":"America/Mexico_City",
    "iso:country":"MX",
    "wof:name":"Guayaza",
    "wof:placetype":"locality",
    "wof:population":353
},
  "geometry": {"coordinates":[-92.25611000000001,17.16028],"type":"Point"}
}