{
  "type": "Feature",
  "properties": {
    "gn:admin1_code":"26.0",
    "gn:admin2_code":"27.0",
    "gn:asciiname":"Los Alamos",
    "gn:country_code":"MX",
    "gn:dem":1133,
    "gn:feature_class":"P",
    "gn:feature_code":"PPL",
    "gn:name":"Los \u00c1lamos",
    "gn:population":0,
    "gn:timezone":"America/Hermosillo",
    "iso:country":"MX",
    "name:spa_x_preferred":[
        "Los \u00c1lamos"
    ],
    "wof:name":"Los Alamos",
    "wof:placetype":"locality"
},
  "geometry": {"coordinates":[-109.46361,30.9775],"type":"Point"}
}