{
  "type": "Feature",
  "properties": {
    "gn:admin1_code":"30",
    "gn:asciiname":"Pesmayo",
    "gn:country_code":"MX",
    "gn:dem":641,
    "gn:feature_class":"P",
    "gn:feature_code":"PPL",
    "gn:name":"Pesmayo",
    "gn:population":0,
    "gn:timezone":"America/Mexico_City",
    "iso:country":"MX",
    "name:spa_x_preferred":[
        "Pesmayo"
    ],
    "wof:name":"Pesmayo",
    "wof:placetype":"locality"
},
  "geometry": {"coordinates":[-98.2891,20.82548],"type":"Point"}
}