{
  "type": "Feature",
  "properties": {
    "gn:admin1_code":"6",
    "gn:admin2_code":"27.0",
    "gn:asciiname":"Totorichi",
    "gn:country_code":"MX",
    "gn:dem":2254,
    "gn:feature_class":"P",
    "gn:feature_code":"PPL",
    "gn:name":"Totorichi",
    "gn:population":63,
    "gn:timezone":"America/Chihuahua",
    "iso:country":"MX",
    "name:spa_x_preferred":[
        "Totorichi"
    ],
    "wof:name":"Totorichi",
    "wof:placetype":"locality",
    "wof:population":63
},
  "geometry": {"coordinates":[-107.03448,27.39204],"type":"Point"}
}