{
  "type": "Feature",
  "properties": {
    "gn:admin1_code":"28",
    "gn:admin2_code":"35.0",
    "gn:asciiname":"El Nuevo Sauz",
    "gn:country_code":"MX",
    "gn:dem":59,
    "gn:feature_class":"P",
    "gn:feature_code":"PPL",
    "gn:name":"El Nuevo S\u00e1uz",
    "gn:population":0,
    "gn:timezone":"America/Monterrey",
    "iso:country":"MX",
    "name:spa_x_preferred":[
        "El Nuevo S\u00e1uz"
    ],
    "name:und_x_variant":[
        "Rancho El Sauz"
    ],
    "wof:name":"El Nuevo Sauz",
    "wof:placetype":"locality"
},
  "geometry": {"coordinates":[-98.18859,24.75754],"type":"Point"}
}