{
  "type": "Feature",
  "properties": {
    "gn:admin1_code":"5",
    "gn:admin2_code":"66",
    "gn:asciiname":"San Ramon",
    "gn:country_code":"MX",
    "gn:dem":428,
    "gn:feature_class":"P",
    "gn:feature_code":"PPL",
    "gn:name":"San Ram\u00f3n",
    "gn:population":9,
    "gn:timezone":"America/Mexico_City",
    "iso:country":"MX",
    "name:und_x_variant":[
        "San Ram\u00f3n"
    ],
    "wof:name":"San Ramon",
    "wof:placetype":"locality",
    "wof:population":9
},
  "geometry": {"coordinates":[-92.46889,17.08028],"type":"Point"}
}