{
  "type": "Feature",
  "properties": {
    "gn:admin1_code":"20",
    "gn:admin2_code":"44.0",
    "gn:asciiname":"Guadalupano (Los Negritos)",
    "gn:country_code":"MX",
    "gn:dem":50,
    "gn:feature_class":"P",
    "gn:feature_code":"PPL",
    "gn:name":"Guadalupano (Los Negritos)",
    "gn:population":9,
    "gn:timezone":"America/Mexico_City",
    "iso:country":"MX",
    "wof:name":"Guadalupano (Los Negritos)",
    "wof:placetype":"locality",
    "wof:population":9
},
  "geometry": {"coordinates":[-95.87111,18.05778],"type":"Point"}
}