{
  "type": "Feature",
  "properties": {
    "gn:admin1_code":"12.0",
    "gn:admin2_code":"38.0",
    "gn:asciiname":"El Escobillal",
    "gn:country_code":"MX",
    "gn:dem":494,
    "gn:feature_class":"P",
    "gn:feature_code":"PPL",
    "gn:name":"El Escobillal",
    "gn:population":0,
    "gn:timezone":"America/Mexico_City",
    "iso:country":"MX",
    "name:spa_x_preferred":[
        "El Escobillal"
    ],
    "wof:name":"El Escobillal",
    "wof:placetype":"locality"
},
  "geometry": {"coordinates":[-101.45948,17.78522000000001],"type":"Point"}
}