{
  "type": "Feature",
  "properties": {
    "gn:admin1_code":"16",
    "gn:admin2_code":"92.0",
    "gn:asciiname":"Cofradia",
    "gn:country_code":"MX",
    "gn:dem":468,
    "gn:feature_class":"P",
    "gn:feature_code":"PPL",
    "gn:name":"Cofrad\u00eda",
    "gn:population":9,
    "gn:timezone":"America/Mexico_City",
    "iso:country":"MX",
    "name:und_x_variant":[
        "Cofrad\u00eda"
    ],
    "wof:name":"Cofradia",
    "wof:placetype":"locality",
    "wof:population":9
},
  "geometry": {"coordinates":[-100.83944,19.00639],"type":"Point"}
}