{
  "type": "Feature",
  "properties": {
    "gn:admin1_code":"14",
    "gn:admin2_code":"44.0",
    "gn:asciiname":"El Sacrificio",
    "gn:country_code":"MX",
    "gn:dem":1531,
    "gn:feature_class":"P",
    "gn:feature_code":"PPL",
    "gn:name":"El Sacrificio",
    "gn:population":212,
    "gn:timezone":"America/Mexico_City",
    "iso:country":"MX",
    "wof:name":"El Sacrificio",
    "wof:placetype":"locality",
    "wof:population":212
},
  "geometry": {"coordinates":[-103.19667,20.40806],"type":"Point"}
}