{
  "type": "Feature",
  "properties": {
    "gn:admin1_code":"7",
    "gn:admin2_code":"10.0",
    "gn:asciiname":"Fresnillo",
    "gn:country_code":"MX",
    "gn:dem":590,
    "gn:feature_class":"P",
    "gn:feature_code":"PPL",
    "gn:name":"Fresnillo",
    "gn:population":0,
    "gn:timezone":"America/Monterrey",
    "iso:country":"MX",
    "name:dan_x_preferred":[
        "Fresnillo"
    ],
    "name:deu_x_preferred":[
        "Fresnillo"
    ],
    "name:epo_x_preferred":[
        "Fresnillo"
    ],
    "name:fas_x_preferred":[
        "\u0641\u0631\u0633\u0646\u06cc\u0644\u0648"
    ],
    "name:heb_x_preferred":[
        "\u05e4\u05e8\u05e1\u05e0\u05d9\u05dc\u05d5"
    ],
    "name:hun_x_preferred":[
        "Fresnillo"
    ],
    "name:ita_x_preferred":[
        "Fresnillo"
    ],
    "name:kaz_x_preferred":[
        "\u0424\u0440\u0435\u0441\u043d\u0438\u043b\u044c\u043e"
    ],
    "name:lit_x_preferred":[
        "Fresniljas"
    ],
    "name:nld_x_preferred":[
        "Fresnillo"
    ],
    "name:nor_x_preferred":[
        "Fresnillo"
    ],
    "name:pol_x_preferred":[
        "Fresnillo"
    ],
    "name:por_x_preferred":[
        "Fresnillo"
    ],
    "name:rus_x_preferred":[
        "\u0424\u0440\u0435\u0441\u043d\u0438\u043b\u044c\u043e"
    ],
    "name:spa_x_preferred":[
        "Fresnillo"
    ],
    "name:srp_x_preferred":[
        "\u0424\u0440\u0435\u0441\u043d\u0438\u0459\u043e"
    ],
    "name:swa_x_preferred":[
        "Fresnillo"
    ],
    "name:swe_x_preferred":[
        "Fresnillo"
    ],
    "name:und_x_variant":[
        "Rancho El Fresnillo"
    ],
    "name:urd_x_preferred":[
        "\u0641\u0631\u06cc\u0633\u0646\u06cc\u0648"
    ],
    "name:vie_x_preferred":[
        "Fresnillo"
    ],
    "name:war_x_preferred":[
        "Fresnillo"
    ],
    "name:zho_x_preferred":[
        "\u5f17\u96f7\u65af\u5c3c\u7d04"
    ],
    "wof:name":"Fresnillo",
    "wof:placetype":"locality"
},
  "geometry": {"coordinates":[-101.55202,26.93641],"type":"Point"}
}