{
  "type": "Feature",
  "properties": {
    "gn:admin1_code":"15",
    "gn:admin2_code":"115.0",
    "gn:asciiname":"Colonia Adolfo Lopez Mateos",
    "gn:country_code":"MX",
    "gn:dem":2583,
    "gn:feature_class":"P",
    "gn:feature_code":"PPL",
    "gn:name":"Colonia Adolfo L\u00f3pez Mateos",
    "gn:population":691,
    "gn:timezone":"America/Mexico_City",
    "iso:country":"MX",
    "name:und_x_variant":[
        "Colonia Adolfo L\u00f3pez Mateos"
    ],
    "wof:name":"Colonia Adolfo Lopez Mateos",
    "wof:placetype":"locality",
    "wof:population":691
},
  "geometry": {"coordinates":[-99.52793,19.41333],"type":"Point"}
}