{
  "type": "Feature",
  "properties": {
    "gn:admin1_code":"11",
    "gn:admin2_code":"46.0",
    "gn:asciiname":"El Sauz",
    "gn:cc2":"MX",
    "gn:country_code":"MX",
    "gn:dem":1857,
    "gn:feature_class":"P",
    "gn:feature_code":"PPL",
    "gn:name":"El Sauz",
    "gn:population":22,
    "gn:timezone":"America/Mexico_City",
    "iso:country":"MX",
    "name:und_x_variant":[
        "Sauz de Cerano"
    ],
    "wof:name":"El Sauz",
    "wof:placetype":"locality",
    "wof:population":22
},
  "geometry": {"coordinates":[-101.38806,20.12361],"type":"Point"}
}