{
  "type": "Feature",
  "properties": {
    "gn:admin1_code":"15",
    "gn:admin2_code":"60.0",
    "gn:asciiname":"Rancheria los Duraznos",
    "gn:country_code":"MX",
    "gn:dem":2621,
    "gn:feature_class":"P",
    "gn:feature_code":"PPL",
    "gn:name":"Rancher\u00eda los Duraznos",
    "gn:population":12,
    "gn:timezone":"America/Mexico_City",
    "iso:country":"MX",
    "wof:name":"Rancheria los Duraznos",
    "wof:placetype":"locality",
    "wof:population":12
},
  "geometry": {"coordinates":[-99.39529,19.66968],"type":"Point"}
}