{
  "type": "Feature",
  "properties": {
    "gn:admin1_code":"32",
    "gn:admin2_code":"27.0",
    "gn:asciiname":"Tanque de San Lucas",
    "gn:country_code":"MX",
    "gn:dem":1899,
    "gn:feature_class":"P",
    "gn:feature_code":"PPL",
    "gn:name":"Tanque de San Lucas",
    "gn:population":0,
    "gn:timezone":"America/Mexico_City",
    "iso:country":"MX",
    "wof:name":"Tanque de San Lucas",
    "wof:placetype":"locality"
},
  "geometry": {"coordinates":[-101.73333,24.76667],"type":"Point"}
}