{
  "type": "Feature",
  "properties": {
    "gn:admin1_code":"14",
    "gn:admin2_code":"105",
    "gn:asciiname":"El Puerto",
    "gn:country_code":"MX",
    "gn:dem":1608,
    "gn:feature_class":"P",
    "gn:feature_code":"PPL",
    "gn:name":"El Puerto",
    "gn:population":10,
    "gn:timezone":"America/Mexico_City",
    "iso:country":"MX",
    "name:ast_x_preferred":[
        "El Puertu"
    ],
    "name:ceb_x_preferred":[
        "El Puerto"
    ],
    "name:deu_x_preferred":[
        "El Puerto"
    ],
    "name:spa_x_preferred":[
        "El Puerto"
    ],
    "name:srp_x_preferred":[
        "\u0415\u043b \u041f\u0443\u0435\u0440\u0442\u043e"
    ],
    "name:swe_x_preferred":[
        "El Puerto"
    ],
    "wof:name":"El Puerto",
    "wof:placetype":"locality",
    "wof:population":10
},
  "geometry": {"coordinates":[-102.64861000000001,20.54722000000001],"type":"Point"}
}