{
  "type": "Feature",
  "properties": {
    "gn:admin1_code":"10",
    "gn:admin2_code":"23.0",
    "gn:asciiname":"Santa Lucia",
    "gn:country_code":"MX",
    "gn:dem":1925,
    "gn:feature_class":"P",
    "gn:feature_code":"PPL",
    "gn:name":"Santa Luc\u00eda",
    "gn:population":0,
    "gn:timezone":"America/Monterrey",
    "iso:country":"MX",
    "name:spa_x_preferred":[
        "Santa Luc\u00eda"
    ],
    "wof:name":"Santa Lucia",
    "wof:placetype":"locality"
},
  "geometry": {"coordinates":[-105.51012,23.61093],"type":"Point"}
}