{
  "type": "Feature",
  "properties": {
    "gn:admin1_code":"22.0",
    "gn:asciiname":"El Palo Bobar",
    "gn:country_code":"MX",
    "gn:dem":2053,
    "gn:feature_class":"P",
    "gn:feature_code":"PPL",
    "gn:name":"El Palo Bobar",
    "gn:population":0,
    "gn:timezone":"America/Mexico_City",
    "iso:country":"MX",
    "name:spa_x_preferred":[
        "El Palo Bobar"
    ],
    "wof:name":"El Palo Bobar",
    "wof:placetype":"locality"
},
  "geometry": {"coordinates":[-100.4855,20.43787],"type":"Point"}
}