{
  "type": "Feature",
  "properties": {
    "gn:admin1_code":"21",
    "gn:admin2_code":"16.0",
    "gn:asciiname":"La Loma",
    "gn:country_code":"MX",
    "gn:dem":2470,
    "gn:feature_class":"P",
    "gn:feature_code":"PPL",
    "gn:name":"La Loma",
    "gn:population":319,
    "gn:timezone":"America/Mexico_City",
    "iso:country":"MX",
    "wof:name":"La Loma",
    "wof:placetype":"locality",
    "wof:population":319
},
  "geometry": {"coordinates":[-97.95667,19.75889],"type":"Point"}
}