{
  "type": "Feature",
  "properties": {
    "gn:admin1_code":"32.0",
    "gn:admin2_code":"10.0",
    "gn:asciiname":"Colonia Plenitud",
    "gn:country_code":"MX",
    "gn:dem":2060,
    "gn:feature_class":"P",
    "gn:feature_code":"PPL",
    "gn:name":"Colonia Plenitud",
    "gn:population":1233,
    "gn:timezone":"America/Mexico_City",
    "iso:country":"MX",
    "wof:name":"Colonia Plenitud",
    "wof:placetype":"locality",
    "wof:population":1233
},
  "geometry": {"coordinates":[-103.075,23.2325],"type":"Point"}
}