{
  "type": "Feature",
  "properties": {
    "gn:admin1_code":"14",
    "gn:admin2_code":"90.0",
    "gn:asciiname":"La Ladera",
    "gn:country_code":"MX",
    "gn:dem":1477,
    "gn:feature_class":"P",
    "gn:feature_code":"PPL",
    "gn:name":"La Ladera",
    "gn:population":179,
    "gn:timezone":"America/Mexico_City",
    "iso:country":"MX",
    "wof:name":"La Ladera",
    "wof:placetype":"locality",
    "wof:population":179
},
  "geometry": {"coordinates":[-104.15139000000001,20.20722],"type":"Point"}
}