{
  "type": "Feature",
  "properties": {
    "gn:admin1_code":"6",
    "gn:admin2_code":"29",
    "gn:asciiname":"El Naranjito",
    "gn:country_code":"MX",
    "gn:dem":1204,
    "gn:feature_class":"P",
    "gn:feature_code":"PPL",
    "gn:name":"El Naranjito",
    "gn:population":47,
    "gn:timezone":"America/Chihuahua",
    "iso:country":"MX",
    "wof:name":"El Naranjito",
    "wof:placetype":"locality",
    "wof:population":47
},
  "geometry": {"coordinates":[-107.26347,26.1594],"type":"Point"}
}