{
  "type": "Feature",
  "properties": {
    "gn:admin1_code":"27",
    "gn:admin2_code":"17.0",
    "gn:asciiname":"Canitzan",
    "gn:country_code":"MX",
    "gn:dem":20,
    "gn:feature_class":"P",
    "gn:feature_code":"PPL",
    "gn:name":"Canitz\u00e1n",
    "gn:population":0,
    "gn:timezone":"America/Mexico_City",
    "iso:country":"MX",
    "name:und_x_variant":[
        "Canizan",
        "Canitz\u00e1n"
    ],
    "wof:name":"Canitzan",
    "wof:placetype":"locality"
},
  "geometry": {"coordinates":[-91.36445000000001,17.58513],"type":"Point"}
}