{
  "type": "Feature",
  "properties": {
    "gn:admin1_code":"30",
    "gn:admin2_code":"180.0",
    "gn:asciiname":"El Naranjal",
    "gn:country_code":"MX",
    "gn:dem":199,
    "gn:feature_class":"P",
    "gn:feature_code":"PPL",
    "gn:name":"El Naranjal",
    "gn:population":0,
    "gn:timezone":"America/Mexico_City",
    "iso:country":"MX",
    "name:spa_x_preferred":[
        "El Naranjal"
    ],
    "name:und_x_variant":[
        "Naranjal",
        "Naranjal de la Jabonera"
    ],
    "wof:name":"El Naranjal",
    "wof:placetype":"locality"
},
  "geometry": {"coordinates":[-98.16498,20.72958],"type":"Point"}
}