{
  "type": "Feature",
  "properties": {
    "gn:admin1_code":"11",
    "gn:admin2_code":"26.0",
    "gn:asciiname":"Granja Santa Rosa",
    "gn:country_code":"MX",
    "gn:dem":1753,
    "gn:feature_class":"P",
    "gn:feature_code":"PPL",
    "gn:name":"Granja Santa Rosa",
    "gn:population":5,
    "gn:timezone":"America/Mexico_City",
    "iso:country":"MX",
    "wof:name":"Granja Santa Rosa",
    "wof:placetype":"locality",
    "wof:population":5
},
  "geometry": {"coordinates":[-101.50306,20.88333],"type":"Point"}
}