{
  "type": "Feature",
  "properties": {
    "gn:admin1_code":"6.0",
    "gn:admin2_code":"42.0",
    "gn:asciiname":"El Gatun",
    "gn:country_code":"MX",
    "gn:dem":1502,
    "gn:feature_class":"P",
    "gn:feature_code":"PPL",
    "gn:name":"El Gat\u00fan",
    "gn:population":2,
    "gn:timezone":"America/Chihuahua",
    "iso:country":"MX",
    "name:und_x_variant":[
        "Gatun",
        "Rancho El Gat\u00fan",
        "El Gat\u00fan",
        "Gast\u00fan"
    ],
    "wof:name":"El Gatun",
    "wof:placetype":"locality",
    "wof:population":2
},
  "geometry": {"coordinates":[-104.11745000000001,29.03583],"type":"Point"}
}