{
  "type": "Feature",
  "properties": {
    "gn:admin1_code":"25",
    "gn:admin2_code":"10",
    "gn:asciiname":"Escuela Normal Experimental de El Fuerte",
    "gn:country_code":"MX",
    "gn:dem":123,
    "gn:feature_class":"P",
    "gn:feature_code":"PPL",
    "gn:name":"Escuela Normal Experimental de El Fuerte",
    "gn:population":43,
    "gn:timezone":"America/Mazatlan",
    "iso:country":"MX",
    "wof:name":"Escuela Normal Experimental de El Fuerte",
    "wof:placetype":"locality",
    "wof:population":43
},
  "geometry": {"coordinates":[-108.69183999999998,26.41744000000001],"type":"Point"}
}