{
  "type": "Feature",
  "properties": {
    "gn:admin1_code":"11",
    "gn:admin2_code":"23.0",
    "gn:asciiname":"Liebres de Suarez",
    "gn:country_code":"MX",
    "gn:dem":1704,
    "gn:feature_class":"P",
    "gn:feature_code":"PPL",
    "gn:name":"Liebres de Su\u00e1rez",
    "gn:population":545,
    "gn:timezone":"America/Mexico_City",
    "iso:country":"MX",
    "name:und_x_variant":[
        "Liebres de Su\u00e1rez"
    ],
    "wof:name":"Liebres de Suarez",
    "wof:placetype":"locality",
    "wof:population":545
},
  "geometry": {"coordinates":[-101.99833,20.41111],"type":"Point"}
}