{
  "type": "Feature",
  "properties": {
    "gn:admin1_code":"7",
    "gn:admin2_code":"2.0",
    "gn:asciiname":"Pablo Hernandez",
    "gn:country_code":"MX",
    "gn:dem":303,
    "gn:feature_class":"P",
    "gn:feature_code":"PPL",
    "gn:name":"Pablo Hern\u00e1ndez",
    "gn:population":7,
    "gn:timezone":"America/Matamoros",
    "iso:country":"MX",
    "name:und_x_variant":[
        "Pablo Hern\u00e1ndez"
    ],
    "wof:name":"Pablo Hernandez",
    "wof:placetype":"locality",
    "wof:population":7
},
  "geometry": {"coordinates":[-100.89009,29.2694],"type":"Point"}
}