{
  "type": "Feature",
  "properties": {
    "gn:admin1_code":"6",
    "gn:admin2_code":"30",
    "gn:asciiname":"Huiquerare",
    "gn:country_code":"MX",
    "gn:dem":579,
    "gn:feature_class":"P",
    "gn:feature_code":"PPL",
    "gn:name":"Huiquerare",
    "gn:population":15,
    "gn:timezone":"America/Chihuahua",
    "iso:country":"MX",
    "wof:name":"Huiquerare",
    "wof:placetype":"locality",
    "wof:population":15
},
  "geometry": {"coordinates":[-108.39715,27.50769],"type":"Point"}
}