{
  "type": "Feature",
  "properties": {
    "gn:admin1_code":"6",
    "gn:admin2_code":"65.0",
    "gn:asciiname":"Sagueerachi",
    "gn:country_code":"MX",
    "gn:dem":1568,
    "gn:feature_class":"P",
    "gn:feature_code":"PPL",
    "gn:name":"Sag\u00fcerachi",
    "gn:population":6,
    "gn:timezone":"America/Chihuahua",
    "iso:country":"MX",
    "name:und_x_variant":[
        "Sag\u00fcerachi"
    ],
    "wof:name":"Sagueerachi",
    "wof:placetype":"locality",
    "wof:population":6
},
  "geometry": {"coordinates":[-107.79131,27.39326],"type":"Point"}
}