{
  "type": "Feature",
  "properties": {
    "gn:admin1_code":"10.0",
    "gn:admin2_code":"14.0",
    "gn:asciiname":"Guacamayitas",
    "gn:country_code":"MX",
    "gn:dem":2492,
    "gn:feature_class":"P",
    "gn:feature_code":"PPL",
    "gn:name":"Guacamayitas",
    "gn:population":0,
    "gn:timezone":"America/Monterrey",
    "iso:country":"MX",
    "name:spa_x_preferred":[
        "Guacamayitas"
    ],
    "wof:name":"Guacamayitas",
    "wof:placetype":"locality"
},
  "geometry": {"coordinates":[-104.532,22.96307],"type":"Point"}
}