{
  "type": "Feature",
  "properties": {
    "gn:admin1_code":"14.0",
    "gn:admin2_code":"17.0",
    "gn:asciiname":"El Sombrerillo",
    "gn:country_code":"MX",
    "gn:dem":1511,
    "gn:feature_class":"P",
    "gn:feature_code":"PPL",
    "gn:name":"El Sombrerillo",
    "gn:population":0,
    "gn:timezone":"America/Mexico_City",
    "iso:country":"MX",
    "name:spa_x_preferred":[
        "El Sombrerillo"
    ],
    "wof:name":"El Sombrerillo",
    "wof:placetype":"locality"
},
  "geometry": {"coordinates":[-104.24857,20.17277],"type":"Point"}
}