{
  "type": "Feature",
  "properties": {
    "gn:admin1_code":"21",
    "gn:admin2_code":"44.0",
    "gn:asciiname":"El Calvario",
    "gn:country_code":"MX",
    "gn:dem":2462,
    "gn:feature_class":"P",
    "gn:feature_code":"PPL",
    "gn:name":"El Calvario",
    "gn:population":276,
    "gn:timezone":"America/Mexico_City",
    "iso:country":"MX",
    "wof:name":"El Calvario",
    "wof:placetype":"locality",
    "wof:population":276
},
  "geometry": {"coordinates":[-97.62111,19.61028],"type":"Point"}
}