{
  "type": "Feature",
  "properties": {
    "gn:admin1_code":"10",
    "gn:admin2_code":"35.0",
    "gn:asciiname":"Tierra Colorada",
    "gn:country_code":"MX",
    "gn:dem":1985,
    "gn:feature_class":"P",
    "gn:feature_code":"PPL",
    "gn:name":"Tierra Colorada",
    "gn:population":0,
    "gn:timezone":"America/Monterrey",
    "iso:country":"MX",
    "name:spa_x_preferred":[
        "Tierra Colorada"
    ],
    "wof:name":"Tierra Colorada",
    "wof:placetype":"locality"
},
  "geometry": {"coordinates":[-105.60418,25.31983],"type":"Point"}
}