{
  "type": "Feature",
  "properties": {
    "gn:admin1_code":"28",
    "gn:admin2_code":"42.0",
    "gn:asciiname":"El Faro",
    "gn:country_code":"MX",
    "gn:dem":272,
    "gn:feature_class":"P",
    "gn:feature_code":"PPL",
    "gn:name":"El Faro",
    "gn:population":0,
    "gn:timezone":"America/Monterrey",
    "iso:country":"MX",
    "name:spa_x_preferred":[
        "El Faro"
    ],
    "wof:name":"El Faro",
    "wof:placetype":"locality"
},
  "geometry": {"coordinates":[-99.29510000000001,24.45609],"type":"Point"}
}