{
  "type": "Feature",
  "properties": {
    "gn:admin1_code":"26.0",
    "gn:admin2_code":"6.0",
    "gn:asciiname":"El Pajarito",
    "gn:country_code":"MX",
    "gn:dem":980,
    "gn:feature_class":"P",
    "gn:feature_code":"PPL",
    "gn:name":"El Pajarito",
    "gn:population":0,
    "gn:timezone":"America/Hermosillo",
    "iso:country":"MX",
    "name:spa_x_preferred":[
        "El Pajarito"
    ],
    "wof:name":"El Pajarito",
    "wof:placetype":"locality"
},
  "geometry": {"coordinates":[-110.08172999999999,30.40099],"type":"Point"}
}