{
  "type": "Feature",
  "properties": {
    "gn:admin1_code":"13",
    "gn:admin2_code":"37",
    "gn:asciiname":"Palo Blanco (Cacaloco)",
    "gn:country_code":"MX",
    "gn:dem":1281,
    "gn:feature_class":"P",
    "gn:feature_code":"PPL",
    "gn:name":"Palo Blanco (Cacaloco)",
    "gn:population":22,
    "gn:timezone":"America/Mexico_City",
    "iso:country":"MX",
    "wof:name":"Palo Blanco (Cacaloco)",
    "wof:placetype":"locality",
    "wof:population":22
},
  "geometry": {"coordinates":[-98.82083,20.6175],"type":"Point"}
}