{
  "type": "Feature",
  "properties": {
    "gn:admin1_code":"30",
    "gn:admin2_code":"23.0",
    "gn:asciiname":"Equimite",
    "gn:country_code":"MX",
    "gn:dem":877,
    "gn:feature_class":"P",
    "gn:feature_code":"PPL",
    "gn:name":"Equimite",
    "gn:population":0,
    "gn:timezone":"America/Mexico_City",
    "iso:country":"MX",
    "name:spa_x_preferred":[
        "Equimite"
    ],
    "name:und_x_variant":[
        "El Quimite"
    ],
    "wof:name":"Equimite",
    "wof:placetype":"locality"
},
  "geometry": {"coordinates":[-97.03333000000001,19.88173],"type":"Point"}
}