{
  "type": "Feature",
  "properties": {
    "gn:admin1_code":"14",
    "gn:admin2_code":"82",
    "gn:asciiname":"Rancho Alegre",
    "gn:country_code":"MX",
    "gn:dem":1379,
    "gn:feature_class":"P",
    "gn:feature_code":"PPL",
    "gn:name":"Rancho Alegre",
    "gn:population":18,
    "gn:timezone":"America/Mexico_City",
    "iso:country":"MX",
    "name:ceb_x_preferred":[
        "Rancho Alegre"
    ],
    "name:nld_x_preferred":[
        "Rancho Alegre"
    ],
    "name:por_x_preferred":[
        "Rancho Alegre"
    ],
    "name:swe_x_preferred":[
        "Rancho Alegre"
    ],
    "name:vol_x_preferred":[
        "Rancho Alegre"
    ],
    "wof:name":"Rancho Alegre",
    "wof:placetype":"locality",
    "wof:population":18
},
  "geometry": {"coordinates":[-103.55249999999999,19.86528],"type":"Point"}
}