{
  "type": "Feature",
  "properties": {
    "gn:admin1_code":"19",
    "gn:admin2_code":"51.0",
    "gn:asciiname":"Los Galemes",
    "gn:country_code":"MX",
    "gn:dem":366,
    "gn:feature_class":"P",
    "gn:feature_code":"PPL",
    "gn:name":"Los Galemes",
    "gn:population":0,
    "gn:timezone":"America/Monterrey",
    "iso:country":"MX",
    "name:spa_x_preferred":[
        "Los Galemes"
    ],
    "name:und_x_variant":[
        "Rancho Los Galemes"
    ],
    "wof:name":"Los Galemes",
    "wof:placetype":"locality"
},
  "geometry": {"coordinates":[-100.27858000000001,26.49541],"type":"Point"}
}