{
  "type": "Feature",
  "properties": {
    "gn:admin1_code":"16.0",
    "gn:admin2_code":"26.0",
    "gn:asciiname":"Mesa de la Perdiz",
    "gn:country_code":"MX",
    "gn:dem":593,
    "gn:feature_class":"P",
    "gn:feature_code":"PPL",
    "gn:name":"Mesa de la Perdiz",
    "gn:population":0,
    "gn:timezone":"America/Mexico_City",
    "iso:country":"MX",
    "name:spa_x_preferred":[
        "Mesa de la Perdiz"
    ],
    "wof:name":"Mesa de la Perdiz",
    "wof:placetype":"locality"
},
  "geometry": {"coordinates":[-103.32826,18.84745],"type":"Point"}
}