{
  "type": "Feature",
  "properties": {
    "gn:admin1_code":"20",
    "gn:admin2_code":"190.0",
    "gn:asciiname":"El Gigante",
    "gn:country_code":"MX",
    "gn:dem":91,
    "gn:feature_class":"P",
    "gn:feature_code":"PPL",
    "gn:name":"El Gigante",
    "gn:population":6,
    "gn:timezone":"America/Mexico_City",
    "iso:country":"MX",
    "wof:name":"El Gigante",
    "wof:placetype":"locality",
    "wof:population":6
},
  "geometry": {"coordinates":[-95.255,17.44611],"type":"Point"}
}