{
  "type": "Feature",
  "properties": {
    "gn:admin1_code":"19",
    "gn:admin2_code":"13.0",
    "gn:asciiname":"Presa Nueva",
    "gn:country_code":"MX",
    "gn:dem":148,
    "gn:feature_class":"P",
    "gn:feature_code":"PPL",
    "gn:name":"Presa Nueva",
    "gn:population":0,
    "gn:timezone":"America/Monterrey",
    "iso:country":"MX",
    "wof:name":"Presa Nueva",
    "wof:placetype":"locality"
},
  "geometry": {"coordinates":[-98.89708,25.22565],"type":"Point"}
}