{
  "type": "Feature",
  "properties": {
    "gn:admin1_code":"20.0",
    "gn:admin2_code":"105.0",
    "gn:asciiname":"La Colonita",
    "gn:country_code":"MX",
    "gn:dem":2283,
    "gn:feature_class":"P",
    "gn:feature_code":"PPL",
    "gn:name":"La Colonita",
    "gn:population":0,
    "gn:timezone":"America/Mexico_City",
    "iso:country":"MX",
    "name:spa_x_preferred":[
        "La Colonita"
    ],
    "wof:name":"La Colonita",
    "wof:placetype":"locality"
},
  "geometry": {"coordinates":[-97.72105000000001,17.55269],"type":"Point"}
}