{
  "type": "Feature",
  "properties": {
    "gn:admin1_code":"30",
    "gn:admin2_code":"14.0",
    "gn:asciiname":"Atoyaquillo",
    "gn:country_code":"MX",
    "gn:dem":567,
    "gn:feature_class":"P",
    "gn:feature_code":"PPL",
    "gn:name":"Atoyaquillo",
    "gn:population":385,
    "gn:timezone":"America/Mexico_City",
    "iso:country":"MX",
    "wof:name":"Atoyaquillo",
    "wof:placetype":"locality",
    "wof:population":385
},
  "geometry": {"coordinates":[-96.8625,18.92361],"type":"Point"}
}