{
  "type": "Feature",
  "properties": {
    "gn:admin1_code":"31",
    "gn:admin2_code":"79.0",
    "gn:asciiname":"San Martin Hili",
    "gn:country_code":"MX",
    "gn:dem":132,
    "gn:feature_class":"P",
    "gn:feature_code":"PPL",
    "gn:name":"San Martin Hili",
    "gn:population":0,
    "gn:timezone":"America/Merida",
    "iso:country":"MX",
    "name:spa_x_preferred":[
        "San Martin Hili"
    ],
    "name:und_x_variant":[
        "San Mart\u00edn"
    ],
    "wof:name":"San Martin Hili",
    "wof:placetype":"locality"
},
  "geometry": {"coordinates":[-89.52535999999998,19.90375],"type":"Point"}
}