{
  "type": "Feature",
  "properties": {
    "gn:admin1_code":"13",
    "gn:asciiname":"Las Vigas",
    "gn:country_code":"MX",
    "gn:dem":2845,
    "gn:feature_class":"P",
    "gn:feature_code":"PPL",
    "gn:name":"Las Vigas",
    "gn:population":0,
    "gn:timezone":"America/Mexico_City",
    "iso:country":"MX",
    "name:spa_x_preferred":[
        "Las Vigas"
    ],
    "wof:name":"Las Vigas",
    "wof:placetype":"locality"
},
  "geometry": {"coordinates":[-98.26373,19.71655],"type":"Point"}
}