{
  "type": "Feature",
  "properties": {
    "gn:admin1_code":"31",
    "gn:admin2_code":"12.0",
    "gn:asciiname":"Yohdzadz",
    "gn:country_code":"MX",
    "gn:dem":18,
    "gn:feature_class":"P",
    "gn:feature_code":"PPL",
    "gn:name":"Yohdzadz",
    "gn:population":0,
    "gn:timezone":"America/Merida",
    "iso:country":"MX",
    "name:spa_x_preferred":[
        "Yohdzadz"
    ],
    "wof:name":"Yohdzadz",
    "wof:placetype":"locality"
},
  "geometry": {"coordinates":[-88.61953000000003,20.9805],"type":"Point"}
}