{
  "type": "Feature",
  "properties": {
    "gn:admin1_code":"27",
    "gn:admin2_code":"14.0",
    "gn:asciiname":"El Tortuguero",
    "gn:country_code":"MX",
    "gn:dem":11,
    "gn:feature_class":"P",
    "gn:feature_code":"PPL",
    "gn:name":"El Tortuguero",
    "gn:population":0,
    "gn:timezone":"America/Mexico_City",
    "iso:country":"MX",
    "name:fra_x_preferred":[
        "El Tortugero"
    ],
    "name:ita_x_preferred":[
        "El Tortuguero"
    ],
    "name:spa_x_preferred":[
        "Potrerito"
    ],
    "name:spa_x_variant":[
        "El Tortuguero",
        "Potreritos"
    ],
    "name:swe_x_preferred":[
        "El Tortuguero"
    ],
    "name:urd_x_preferred":[
        "\u0627\u06cc\u0644 \u062a\u0648\u0631\u062a\u0648\u06af\u06cc\u0631\u0648"
    ],
    "name:vie_x_preferred":[
        "El Tortuguero"
    ],
    "name:zho_x_preferred":[
        "\u57c3\u723e\u6258\u723e\u5716\u683c\u7f85"
    ],
    "wof:name":"El Tortuguero",
    "wof:placetype":"locality"
},
  "geometry": {"coordinates":[-93.28498999999999,18.31413],"type":"Point"}
}