{
  "type": "Feature",
  "properties": {
    "gn:admin1_code":"27",
    "gn:admin2_code":"14.0",
    "gn:asciiname":"El Tortuguero",
    "gn:country_code":"MX",
    "gn:dem":11,
    "gn:feature_class":"P",
    "gn:feature_code":"PPL",
    "gn:name":"El Tortuguero",
    "gn:population":0,
    "gn:timezone":"America/Mexico_City",
    "iso:country":"MX",
    "name:spa_x_preferred":[
        "Potrerito"
    ],
    "name:spa_x_variant":[
        "El Tortuguero",
        "Potreritos"
    ],
    "wof:name":"El Tortuguero",
    "wof:placetype":"locality"
},
  "geometry": {"coordinates":[-93.28498999999999,18.31413],"type":"Point"}
}