{
  "type": "Feature",
  "properties": {
    "gn:admin1_code":"10",
    "gn:admin2_code":"34.0",
    "gn:asciiname":"Mesa Colorada",
    "gn:country_code":"MX",
    "gn:dem":433,
    "gn:feature_class":"P",
    "gn:feature_code":"PPL",
    "gn:name":"Mesa Colorada",
    "gn:population":0,
    "gn:timezone":"America/Monterrey",
    "iso:country":"MX",
    "name:spa_x_preferred":[
        "Mesa Colorada"
    ],
    "wof:name":"Mesa Colorada",
    "wof:placetype":"locality"
},
  "geometry": {"coordinates":[-107.10684999999999,25.31272],"type":"Point"}
}