{
  "type": "Feature",
  "properties": {
    "gn:admin1_code":"32.0",
    "gn:asciiname":"El Cardo",
    "gn:country_code":"MX",
    "gn:dem":2146,
    "gn:feature_class":"P",
    "gn:feature_code":"PPL",
    "gn:name":"El Cardo",
    "gn:population":0,
    "gn:timezone":"America/Mexico_City",
    "iso:country":"MX",
    "name:spa_x_preferred":[
        "El Cardo"
    ],
    "wof:name":"El Cardo",
    "wof:placetype":"locality"
},
  "geometry": {"coordinates":[-102.77414,21.7178],"type":"Point"}
}