{
  "type": "Feature",
  "properties": {
    "gn:admin1_code":"32.0",
    "gn:admin2_code":"10.0",
    "gn:asciiname":"Laguna de los Bayos",
    "gn:country_code":"MX",
    "gn:dem":2075,
    "gn:feature_class":"P",
    "gn:feature_code":"PPL",
    "gn:name":"Laguna de los Bayos",
    "gn:population":0,
    "gn:timezone":"America/Mexico_City",
    "iso:country":"MX",
    "name:spa_x_preferred":[
        "Laguna de los Bayos"
    ],
    "wof:name":"Laguna de los Bayos",
    "wof:placetype":"locality"
},
  "geometry": {"coordinates":[-103.10098000000001,23.23599],"type":"Point"}
}