{
  "type": "Feature",
  "properties": {
    "gn:admin1_code":"4.0",
    "gn:asciiname":"El Piloto",
    "gn:country_code":"MX",
    "gn:dem":31,
    "gn:feature_class":"P",
    "gn:feature_code":"PPL",
    "gn:name":"El Piloto",
    "gn:population":0,
    "gn:timezone":"America/Merida",
    "iso:country":"MX",
    "name:spa_x_preferred":[
        "El Piloto"
    ],
    "wof:name":"El Piloto",
    "wof:placetype":"locality"
},
  "geometry": {"coordinates":[-90.27561,19.03803],"type":"Point"}
}