{
  "type": "Feature",
  "properties": {
    "gn:admin1_code":"19",
    "gn:admin2_code":"33.0",
    "gn:asciiname":"Purisima de Conchos",
    "gn:country_code":"MX",
    "gn:dem":224,
    "gn:feature_class":"P",
    "gn:feature_code":"PPL",
    "gn:name":"Pur\u00edsima de Conchos",
    "gn:population":0,
    "gn:timezone":"America/Monterrey",
    "iso:country":"MX",
    "name:und_x_variant":[
        "Pur\u00edsima de Conchas",
        "Pur\u00edsima de Conchos"
    ],
    "wof:name":"Purisima de Conchos",
    "wof:placetype":"locality"
},
  "geometry": {"coordinates":[-99.2662,24.92191],"type":"Point"}
}