{
  "type": "Feature",
  "properties": {
    "gn:admin1_code":"30.0",
    "gn:admin2_code":"151.0",
    "gn:asciiname":"Cinco Cienegas",
    "gn:country_code":"MX",
    "gn:dem":3,
    "gn:feature_class":"P",
    "gn:feature_code":"PPL",
    "gn:name":"Cinco Ci\u00e9negas",
    "gn:population":0,
    "gn:timezone":"America/Mexico_City",
    "iso:country":"MX",
    "name:spa_x_preferred":[
        "Cinco Ci\u00e9negas"
    ],
    "name:spa_x_variant":[
        "Las Vegas"
    ],
    "wof:name":"Cinco Cienegas",
    "wof:placetype":"locality"
},
  "geometry": {"coordinates":[-97.33144,21.51295],"type":"Point"}
}