{
  "type": "Feature",
  "properties": {
    "gn:admin1_code":"21",
    "gn:admin2_code":"42.0",
    "gn:asciiname":"Michapa",
    "gn:country_code":"MX",
    "gn:dem":1045,
    "gn:feature_class":"P",
    "gn:feature_code":"PPL",
    "gn:name":"Michapa",
    "gn:population":0,
    "gn:timezone":"America/Mexico_City",
    "iso:country":"MX",
    "name:spa_x_preferred":[
        "Michapa"
    ],
    "name:spa_x_variant":[
        "Mechapa"
    ],
    "wof:name":"Michapa",
    "wof:placetype":"locality"
},
  "geometry": {"coordinates":[-98.26676999999999,18.43586],"type":"Point"}
}