{
  "type": "Feature",
  "properties": {
    "gn:admin1_code":"20",
    "gn:admin2_code":"467.0",
    "gn:asciiname":"El Guineo",
    "gn:country_code":"MX",
    "gn:dem":20,
    "gn:feature_class":"P",
    "gn:feature_code":"PPL",
    "gn:name":"El Guineo",
    "gn:population":5,
    "gn:timezone":"America/Mexico_City",
    "iso:country":"MX",
    "wof:name":"El Guineo",
    "wof:placetype":"locality",
    "wof:population":5
},
  "geometry": {"coordinates":[-97.78722,16.0925],"type":"Point"}
}