{
  "type": "Feature",
  "properties": {
    "gn:admin1_code":"21",
    "gn:admin2_code":"83.0",
    "gn:asciiname":"Tecoltemic",
    "gn:country_code":"MX",
    "gn:dem":2574,
    "gn:feature_class":"P",
    "gn:feature_code":"PPL",
    "gn:name":"Tecolt\u00e9mic",
    "gn:population":151,
    "gn:timezone":"America/Mexico_City",
    "iso:country":"MX",
    "name:und_x_variant":[
        "Tecolt\u00e9mic"
    ],
    "wof:name":"Tecoltemic",
    "wof:placetype":"locality",
    "wof:population":151
},
  "geometry": {"coordinates":[-97.78361,19.65146],"type":"Point"}
}