{
  "type": "Feature",
  "properties": {
    "gn:admin1_code":"16",
    "gn:admin2_code":"97",
    "gn:asciiname":"La Yerbabuena",
    "gn:country_code":"MX",
    "gn:dem":872,
    "gn:feature_class":"P",
    "gn:feature_code":"PPL",
    "gn:name":"La Yerbabuena",
    "gn:population":12,
    "gn:timezone":"America/Mexico_City",
    "iso:country":"MX",
    "wof:name":"La Yerbabuena",
    "wof:placetype":"locality",
    "wof:population":12
},
  "geometry": {"coordinates":[-101.40389,18.89639],"type":"Point"}
}