{
  "type": "Feature",
  "properties": {
    "gn:admin1_code":"19",
    "gn:admin2_code":"9.0",
    "gn:asciiname":"La Presa (Salazar)",
    "gn:country_code":"MX",
    "gn:dem":300,
    "gn:feature_class":"P",
    "gn:feature_code":"PPL",
    "gn:name":"La Presa (Salazar)",
    "gn:population":6,
    "gn:timezone":"America/Monterrey",
    "iso:country":"MX",
    "wof:name":"La Presa (Salazar)",
    "wof:placetype":"locality",
    "wof:population":6
},
  "geometry": {"coordinates":[-99.90640999999999,25.4884],"type":"Point"}
}