{
  "type": "Feature",
  "properties": {
    "gn:admin1_code":"27",
    "gn:admin2_code":"1.0",
    "gn:asciiname":"Miguel Hidalgo Sacaola",
    "gn:country_code":"MX",
    "gn:dem":40,
    "gn:feature_class":"P",
    "gn:feature_code":"PPL",
    "gn:name":"Miguel Hidalgo Sacaola",
    "gn:population":0,
    "gn:timezone":"America/Mexico_City",
    "iso:country":"MX",
    "name:spa_x_preferred":[
        "Miguel Hidalgo Sacaola"
    ],
    "name:spa_x_variant":[
        "San Miguel Sacaola"
    ],
    "wof:name":"Miguel Hidalgo Sacaola",
    "wof:placetype":"locality"
},
  "geometry": {"coordinates":[-91.11183,17.64506],"type":"Point"}
}