{
  "type": "Feature",
  "properties": {
    "gn:admin1_code":"6",
    "gn:admin2_code":"9",
    "gn:asciiname":"San Elias",
    "gn:country_code":"MX",
    "gn:dem":2481,
    "gn:feature_class":"P",
    "gn:feature_code":"PPL",
    "gn:name":"San El\u00edas",
    "gn:population":12,
    "gn:timezone":"America/Chihuahua",
    "iso:country":"MX",
    "name:und_x_variant":[
        "San El\u00edas"
    ],
    "wof:name":"San Elias",
    "wof:placetype":"locality",
    "wof:population":12
},
  "geometry": {"coordinates":[-107.66798,27.73186],"type":"Point"}
}