{
  "type": "Feature",
  "properties": {
    "gn:admin1_code":"20",
    "gn:admin2_code":"217",
    "gn:asciiname":"Pena Colorada",
    "gn:country_code":"MX",
    "gn:dem":2030,
    "gn:feature_class":"P",
    "gn:feature_code":"PPL",
    "gn:name":"Pe\u00f1a Colorada",
    "gn:population":17,
    "gn:timezone":"America/Mexico_City",
    "iso:country":"MX",
    "name:und_x_variant":[
        "Pe\u00f1a Colorada"
    ],
    "wof:name":"Pena Colorada",
    "wof:placetype":"locality",
    "wof:population":17
},
  "geometry": {"coordinates":[-97.10833,17.06889],"type":"Point"}
}