{
  "type": "Feature",
  "properties": {
    "gn:admin1_code":"15.0",
    "gn:asciiname":"Los Pozos",
    "gn:country_code":"MX",
    "gn:dem":1572,
    "gn:feature_class":"P",
    "gn:feature_code":"PPL",
    "gn:name":"Los Pozos",
    "gn:population":0,
    "gn:timezone":"America/Mexico_City",
    "iso:country":"MX",
    "name:spa_x_preferred":[
        "Los Pozos"
    ],
    "wof:name":"Los Pozos",
    "wof:placetype":"locality"
},
  "geometry": {"coordinates":[-102.27296,19.97148],"type":"Point"}
}