{
  "type": "Feature",
  "properties": {
    "gn:admin1_code":"11",
    "gn:admin2_code":"11.0",
    "gn:asciiname":"Sauz de Fuentes",
    "gn:country_code":"MX",
    "gn:dem":1789,
    "gn:feature_class":"P",
    "gn:feature_code":"PPL",
    "gn:name":"Sauz de Fuentes",
    "gn:population":452,
    "gn:timezone":"America/Mexico_City",
    "iso:country":"MX",
    "wof:name":"Sauz de Fuentes",
    "wof:placetype":"locality",
    "wof:population":452
},
  "geometry": {"coordinates":[-100.96138999999999,20.42556],"type":"Point"}
}