{
  "type": "Feature",
  "properties": {
    "gn:admin1_code":"6",
    "gn:admin2_code":"9.0",
    "gn:asciiname":"Hutosagachi",
    "gn:country_code":"MX",
    "gn:dem":2372,
    "gn:feature_class":"P",
    "gn:feature_code":"PPL",
    "gn:name":"Hutos\u00e1gachi",
    "gn:population":0,
    "gn:timezone":"America/Chihuahua",
    "iso:country":"MX",
    "name:spa_x_preferred":[
        "Hutos\u00e1gachi"
    ],
    "wof:name":"Hutosagachi",
    "wof:placetype":"locality"
},
  "geometry": {"coordinates":[-107.69532,27.83207],"type":"Point"}
}