{
  "type": "Feature",
  "properties": {
    "gn:admin1_code":"30",
    "gn:admin2_code":"86.0",
    "gn:asciiname":"Cuartel Cuatro",
    "gn:country_code":"MX",
    "gn:dem":1787,
    "gn:feature_class":"P",
    "gn:feature_code":"PPL",
    "gn:name":"Cuartel Cuatro",
    "gn:population":114,
    "gn:timezone":"America/Mexico_City",
    "iso:country":"MX",
    "wof:name":"Cuartel Cuatro",
    "wof:placetype":"locality",
    "wof:population":114
},
  "geometry": {"coordinates":[-97.31111,19.82472000000001],"type":"Point"}
}