{
  "type": "Feature",
  "properties": {
    "gn:admin1_code":"20.0",
    "gn:admin2_code":"324.0",
    "gn:asciiname":"La Camaronada",
    "gn:country_code":"MX",
    "gn:dem":349,
    "gn:feature_class":"P",
    "gn:feature_code":"PPL",
    "gn:name":"La Camaronada",
    "gn:population":0,
    "gn:timezone":"America/Mexico_City",
    "iso:country":"MX",
    "name:spa_x_preferred":[
        "La Camaronada"
    ],
    "wof:name":"La Camaronada",
    "wof:placetype":"locality"
},
  "geometry": {"coordinates":[-96.41065999999999,15.82132],"type":"Point"}
}