{
  "type": "Feature",
  "properties": {
    "gn:admin1_code":"25",
    "gn:admin2_code":"1.0",
    "gn:asciiname":"El Encanto (Rancho del Temo)",
    "gn:country_code":"MX",
    "gn:dem":4,
    "gn:feature_class":"P",
    "gn:feature_code":"PPL",
    "gn:name":"El Encanto (Rancho del Temo)",
    "gn:population":6,
    "gn:timezone":"America/Mazatlan",
    "iso:country":"MX",
    "wof:name":"El Encanto (Rancho del Temo)",
    "wof:placetype":"locality",
    "wof:population":6
},
  "geometry": {"coordinates":[-109.04597,25.68238],"type":"Point"}
}