{
  "type": "Feature",
  "properties": {
    "gn:admin1_code":"12",
    "gn:admin2_code":"29",
    "gn:asciiname":"Ampliacion Trinchera",
    "gn:country_code":"MX",
    "gn:dem":1530,
    "gn:feature_class":"P",
    "gn:feature_code":"PPL",
    "gn:name":"Ampliaci\u00f3n Trinchera",
    "gn:population":10,
    "gn:timezone":"America/Mexico_City",
    "iso:country":"MX",
    "name:und_x_variant":[
        "Ampliaci\u00f3n Trinchera"
    ],
    "wof:name":"Ampliacion Trinchera",
    "wof:placetype":"locality",
    "wof:population":10
},
  "geometry": {"coordinates":[-99.47389,17.53917],"type":"Point"}
}