{
  "type": "Feature",
  "properties": {
    "gn:admin1_code":"6.0",
    "gn:asciiname":"Santa Martha",
    "gn:country_code":"MX",
    "gn:dem":1177,
    "gn:feature_class":"P",
    "gn:feature_code":"PPL",
    "gn:name":"Santa Martha",
    "gn:population":0,
    "gn:timezone":"America/Chihuahua",
    "iso:country":"MX",
    "name:spa_x_preferred":[
        "Santa Martha"
    ],
    "name:spa_x_variant":[
        "Santa Marta"
    ],
    "wof:name":"Santa Martha",
    "wof:placetype":"locality"
},
  "geometry": {"coordinates":[-105.53128999999998,28.17426],"type":"Point"}
}