{
  "type": "Feature",
  "properties": {
    "gn:admin1_code":"21",
    "gn:admin2_code":"4",
    "gn:asciiname":"Barranca San Jeronimo",
    "gn:country_code":"MX",
    "gn:dem":2126,
    "gn:feature_class":"P",
    "gn:feature_code":"PPL",
    "gn:name":"Barranca San Jer\u00f3nimo",
    "gn:population":23,
    "gn:timezone":"America/Mexico_City",
    "iso:country":"MX",
    "name:und_x_variant":[
        "Barranca San Jer\u00f3nimo"
    ],
    "wof:name":"Barranca San Jeronimo",
    "wof:placetype":"locality",
    "wof:population":23
},
  "geometry": {"coordinates":[-97.75355999999999,18.97904],"type":"Point"}
}