{
  "type": "Feature",
  "properties": {
    "gn:admin1_code":"16",
    "gn:admin2_code":"69.0",
    "gn:asciiname":"Tanque de Pena",
    "gn:country_code":"MX",
    "gn:dem":1980,
    "gn:feature_class":"P",
    "gn:feature_code":"PPL",
    "gn:name":"Tanque de Pe\u00f1a",
    "gn:population":0,
    "gn:timezone":"America/Mexico_City",
    "iso:country":"MX",
    "name:spa_x_preferred":[
        "Tanque de Pe\u00f1a"
    ],
    "wof:name":"Tanque de Pena",
    "wof:placetype":"locality"
},
  "geometry": {"coordinates":[-102.08851,20.31492],"type":"Point"}
}