{
  "type": "Feature",
  "properties": {
    "gn:admin1_code":"25.0",
    "gn:admin2_code":"13.0",
    "gn:asciiname":"Hacienda de Tres Hermanos",
    "gn:country_code":"MX",
    "gn:dem":72,
    "gn:feature_class":"P",
    "gn:feature_code":"PPL",
    "gn:name":"Hacienda de Tres Hermanos",
    "gn:population":0,
    "gn:timezone":"America/Mazatlan",
    "iso:country":"MX",
    "wof:name":"Hacienda de Tres Hermanos",
    "wof:placetype":"locality"
},
  "geometry": {"coordinates":[-107.98333,25.46667],"type":"Point"}
}