{
  "type": "Feature",
  "properties": {
    "gn:admin1_code":"18",
    "gn:admin2_code":"17.0",
    "gn:asciiname":"El Saladito",
    "gn:country_code":"MX",
    "gn:dem":236,
    "gn:feature_class":"P",
    "gn:feature_code":"PPL",
    "gn:name":"El Saladito",
    "gn:population":0,
    "gn:timezone":"America/Mazatlan",
    "iso:country":"MX",
    "name:spa_x_preferred":[
        "El Saladito"
    ],
    "wof:name":"El Saladito",
    "wof:placetype":"locality"
},
  "geometry": {"coordinates":[-104.82574,21.72586],"type":"Point"}
}