{
  "type": "Feature",
  "properties": {
    "gn:admin1_code":"5",
    "gn:admin2_code":"65.0",
    "gn:asciiname":"San Carlos",
    "gn:country_code":"MX",
    "gn:dem":41,
    "gn:feature_class":"P",
    "gn:feature_code":"PPL",
    "gn:name":"San Carlos",
    "gn:population":5,
    "gn:timezone":"America/Mexico_City",
    "iso:country":"MX",
    "name:bar_x_preferred":[
        "San Carlos"
    ],
    "name:bre_x_preferred":[
        "San Carlos"
    ],
    "name:cat_x_preferred":[
        "San Carlos"
    ],
    "name:ceb_x_preferred":[
        "San Carlos"
    ],
    "name:deu_x_preferred":[
        "San Carlos"
    ],
    "name:epo_x_preferred":[
        "San Carlos"
    ],
    "name:est_x_preferred":[
        "San Carlos"
    ],
    "name:fin_x_preferred":[
        "San Carlos"
    ],
    "name:fra_x_preferred":[
        "San Carlos"
    ],
    "name:heb_x_preferred":[
        "\u05e1\u05df \u05e7\u05e8\u05dc\u05d5\u05e1"
    ],
    "name:hun_x_preferred":[
        "San Carlos"
    ],
    "name:ilo_x_preferred":[
        "San Carlos"
    ],
    "name:ita_x_preferred":[
        "San Carlos"
    ],
    "name:jpn_x_preferred":[
        "\u30b5\u30f3\u30fb\u30ab\u30eb\u30ed\u30b9"
    ],
    "name:kat_x_preferred":[
        "\u10e1\u10d0\u10dc-\u10d9\u10d0\u10e0\u10da\u10dd\u10e1\u10d8"
    ],
    "name:kor_x_preferred":[
        "\uc0b0 \uce74\ub97c\ub85c\uc2a4"
    ],
    "name:kor_x_variant":[
        "\uc0b0\uce74\ub97c\ub85c\uc2a4"
    ],
    "name:lit_x_preferred":[
        "San Karlosas"
    ],
    "name:nds_x_preferred":[
        "San Carlos"
    ],
    "name:nld_x_preferred":[
        "San Carlos"
    ],
    "name:pol_x_preferred":[
        "San Carlos"
    ],
    "name:por_x_preferred":[
        "San Carlos"
    ],
    "name:rus_x_preferred":[
        "\u0421\u0430\u043d-\u041a\u0430\u0440\u043b\u043e\u0441"
    ],
    "name:sco_x_preferred":[
        "San Carlos"
    ],
    "name:slk_x_preferred":[
        "San Carlos"
    ],
    "name:spa_x_preferred":[
        "San Carlos"
    ],
    "name:srp_x_preferred":[
        "\u0421\u0430\u043d \u041a\u0430\u0440\u043b\u043e\u0441"
    ],
    "name:swe_x_preferred":[
        "San Carlos"
    ],
    "name:tur_x_preferred":[
        "San Carlos"
    ],
    "name:ukr_x_preferred":[
        "\u0421\u0430\u043d-\u041a\u0430\u0440\u043b\u043e\u0441"
    ],
    "name:urd_x_preferred":[
        "\u0633\u0627\u0646 \u06a9\u0627\u0631\u0644\u0648\u0633"
    ],
    "name:vie_x_preferred":[
        "San Carlos"
    ],
    "name:vol_x_preferred":[
        "San Carlos"
    ],
    "name:war_x_preferred":[
        "San Carlos"
    ],
    "name:zho_x_preferred":[
        "\u5723\u5361\u6d1b\u65af"
    ],
    "wof:name":"San Carlos",
    "wof:placetype":"locality",
    "wof:population":5
},
  "geometry": {"coordinates":[-92.11360999999999,17.52333],"type":"Point"}
}