{
  "type": "Feature",
  "properties": {
    "gn:admin1_code":"1",
    "gn:admin2_code":"5.0",
    "gn:asciiname":"Vinedos Eva (Fraccionamiento Paso Blanco)",
    "gn:country_code":"MX",
    "gn:dem":1881,
    "gn:feature_class":"P",
    "gn:feature_code":"PPL",
    "gn:name":"Vi\u00f1edos Eva (Fraccionamiento Paso Blanco)",
    "gn:population":238,
    "gn:timezone":"America/Mexico_City",
    "iso:country":"MX",
    "name:und_x_variant":[
        "Vi\u00f1edos Eva (Fraccionamiento Paso Blanco)"
    ],
    "wof:name":"Vinedos Eva (Fraccionamiento Paso Blanco)",
    "wof:placetype":"locality",
    "wof:population":238
},
  "geometry": {"coordinates":[-102.29722,21.95833],"type":"Point"}
}