{
  "type": "Feature",
  "properties": {
    "gn:admin1_code":"11.0",
    "gn:admin2_code":"33.0",
    "gn:asciiname":"La Alberca",
    "gn:country_code":"MX",
    "gn:dem":2034,
    "gn:feature_class":"P",
    "gn:feature_code":"PPL",
    "gn:name":"La Alberca",
    "gn:population":0,
    "gn:timezone":"America/Mexico_City",
    "iso:country":"MX",
    "name:und_x_variant":[
        "Alberca",
        "La Alberca"
    ],
    "wof:name":"La Alberca",
    "wof:placetype":"locality"
},
  "geometry": {"coordinates":[-100.57096,21.21701],"type":"Point"}
}