{
  "type": "Feature",
  "properties": {
    "gn:admin1_code":"26",
    "gn:admin2_code":"13.0",
    "gn:asciiname":"La Parada",
    "gn:country_code":"MX",
    "gn:dem":657,
    "gn:feature_class":"P",
    "gn:feature_code":"PPL",
    "gn:name":"La Parada",
    "gn:population":0,
    "gn:timezone":"America/Hermosillo",
    "iso:country":"MX",
    "name:spa_x_preferred":[
        "La Parada"
    ],
    "wof:name":"La Parada",
    "wof:placetype":"locality"
},
  "geometry": {"coordinates":[-110.20419,29.97337000000001],"type":"Point"}
}