{
  "type": "Feature",
  "properties": {
    "gn:admin1_code":"10.0",
    "gn:admin2_code":"5.0",
    "gn:asciiname":"La Joya",
    "gn:country_code":"MX",
    "gn:dem":1895,
    "gn:feature_class":"P",
    "gn:feature_code":"PPL",
    "gn:name":"La Joya",
    "gn:population":0,
    "gn:timezone":"America/Monterrey",
    "iso:country":"MX",
    "name:ceb_x_preferred":[
        "La Joya"
    ],
    "name:deu_x_preferred":[
        "La Joya"
    ],
    "name:nld_x_preferred":[
        "La Joya"
    ],
    "name:que_x_preferred":[
        "La Joya"
    ],
    "name:spa_x_preferred":[
        "La Joya"
    ],
    "name:srp_x_preferred":[
        "\u041b\u0430 \u0425\u043e\u0458\u0430"
    ],
    "name:swe_x_preferred":[
        "La Joya"
    ],
    "name:und_x_variant":[
        "Joya",
        "Ejido La Joya",
        "La Joya"
    ],
    "wof:name":"La Joya",
    "wof:placetype":"locality"
},
  "geometry": {"coordinates":[-104.71357,24.23849],"type":"Point"}
}