{
  "type": "Feature",
  "properties": {
    "gn:admin1_code":"5",
    "gn:admin2_code":"59.0",
    "gn:asciiname":"El Dorado",
    "gn:country_code":"MX",
    "gn:dem":871,
    "gn:feature_class":"P",
    "gn:feature_code":"PPL",
    "gn:name":"El Dorado",
    "gn:population":8,
    "gn:timezone":"America/Mexico_City",
    "iso:country":"MX",
    "wof:name":"El Dorado",
    "wof:placetype":"locality",
    "wof:population":8
},
  "geometry": {"coordinates":[-92.05083,16.90556],"type":"Point"}
}