{
  "type": "Feature",
  "properties": {
    "gn:admin1_code":"5",
    "gn:admin2_code":"72.0",
    "gn:asciiname":"San Felipe",
    "gn:country_code":"MX",
    "gn:dem":1696,
    "gn:feature_class":"P",
    "gn:feature_code":"PPL",
    "gn:name":"San Felipe",
    "gn:population":435,
    "gn:timezone":"America/Mexico_City",
    "iso:country":"MX",
    "name:deu_x_preferred":[
        "San Felipe"
    ],
    "name:fas_x_preferred":[
        "\u0633\u0627\u0646 \u0641\u06cc\u0644\u06cc\u067e\u0647"
    ],
    "name:heb_x_preferred":[
        "\u05e1\u05df \u05e4\u05dc\u05d9\u05e4\u05d4"
    ],
    "name:hun_x_preferred":[
        "San Felipe"
    ],
    "wof:name":"San Felipe",
    "wof:placetype":"locality",
    "wof:population":435
},
  "geometry": {"coordinates":[-92.94583,17.18389],"type":"Point"}
}