{
  "type": "Feature",
  "properties": {
    "gn:admin1_code":"5",
    "gn:admin2_code":"79.0",
    "gn:asciiname":"El Amatillo",
    "gn:country_code":"MX",
    "gn:dem":449,
    "gn:feature_class":"P",
    "gn:feature_code":"PPL",
    "gn:name":"El Amatillo",
    "gn:population":5,
    "gn:timezone":"America/Mexico_City",
    "iso:country":"MX",
    "wof:name":"El Amatillo",
    "wof:placetype":"locality",
    "wof:population":5
},
  "geometry": {"coordinates":[-93.29833000000001,16.93028],"type":"Point"}
}