{
  "type": "Feature",
  "properties": {
    "gn:admin1_code":"2.0",
    "gn:admin2_code":"1.0",
    "gn:asciiname":"Los Carlos",
    "gn:country_code":"MX",
    "gn:dem":82,
    "gn:feature_class":"P",
    "gn:feature_code":"PPL",
    "gn:name":"Los Carlos",
    "gn:population":0,
    "gn:timezone":"America/Tijuana",
    "iso:country":"MX",
    "name:spa_x_preferred":[
        "Los Carlos"
    ],
    "wof:name":"Los Carlos",
    "wof:placetype":"locality"
},
  "geometry": {"coordinates":[-116.14706,31.09122],"type":"Point"}
}