{
  "type": "Feature",
  "properties": {
    "gn:admin1_code":"10",
    "gn:admin2_code":"5.0",
    "gn:asciiname":"Alejandrina [Granja]",
    "gn:country_code":"MX",
    "gn:dem":2372,
    "gn:feature_class":"P",
    "gn:feature_code":"PPL",
    "gn:name":"Alejandrina [Granja]",
    "gn:population":6,
    "gn:timezone":"America/Monterrey",
    "iso:country":"MX",
    "wof:name":"Alejandrina [Granja]",
    "wof:placetype":"locality",
    "wof:population":6
},
  "geometry": {"coordinates":[-104.93446000000002,23.92612],"type":"Point"}
}