{
  "type": "Feature",
  "properties": {
    "gn:country":"MX",
    "gn:fcode":"PPL",
    "gn:population":0,
    "iso:country":"MX",
    "name:spa_x_preferred":[
        "Chiquil\u00e1"
    ],
    "name:spa_x_variant":[
        "Chiquila"
    ],
    "qs_pg:aaroncc":"MX",
    "qs_pg:gn_country":"MX",
    "qs_pg:gn_fcode":"PPL",
    "qs_pg:gn_pop":0,
    "qs_pg:name":"Chiquila",
    "qs_pg:name_adm0":"M\u00e9xico",
    "qs_pg:name_adm1":"Quintana Roo",
    "qs_pg:photos":584,
    "qs_pg:photos_1k":118,
    "qs_pg:photos_9k":3,
    "qs_pg:photos_9r":5,
    "qs_pg:photos_all":584,
    "qs_pg:photos_sr":8,
    "qs_pg:pop_sr":0,
    "qs_pg:qs_pg_placetype":"locality",
    "qs_pg:qs_pg_placetype_gp":"Town",
    "qs_pg:woe_adm0":23424900,
    "woe:adm0_id":23424900,
    "woe:name_adm0":"M\u00e9xico",
    "woe:name_adm1":"Quintana Roo",
    "woe:placetype":"Town",
    "wof:name":"Chiquila",
    "wof:placetype":"locality"
},
  "geometry": {"coordinates":[-87.33768999999999,21.42809],"type":"Point"}
}