{
  "type": "Feature",
  "properties": {
    "gn:admin1_code":"13",
    "gn:admin2_code":"40",
    "gn:asciiname":"Los Castros",
    "gn:country_code":"MX",
    "gn:dem":1445,
    "gn:feature_class":"P",
    "gn:feature_code":"PPL",
    "gn:name":"Los Castros",
    "gn:population":42,
    "gn:timezone":"America/Mexico_City",
    "iso:country":"MX",
    "wof:name":"Los Castros",
    "wof:placetype":"locality",
    "wof:population":42
},
  "geometry": {"coordinates":[-99.12316,21.10172],"type":"Point"}
}