{
  "type": "Feature",
  "properties": {
    "gn:admin1_code":"5",
    "gn:admin2_code":"73.0",
    "gn:asciiname":"El Vergel",
    "gn:country_code":"MX",
    "gn:dem":1009,
    "gn:feature_class":"P",
    "gn:feature_code":"PPL",
    "gn:name":"El Vergel",
    "gn:population":8,
    "gn:timezone":"America/Mexico_City",
    "iso:country":"MX",
    "wof:name":"El Vergel",
    "wof:placetype":"locality",
    "wof:population":8
},
  "geometry": {"coordinates":[-93.01889,17.23472000000001],"type":"Point"}
}