{
  "type": "Feature",
  "properties": {
    "gn:admin1_code":"3.0",
    "gn:admin2_code":"1.0",
    "gn:asciiname":"Santo Tomas",
    "gn:country_code":"MX",
    "gn:dem":310,
    "gn:feature_class":"P",
    "gn:feature_code":"PPL",
    "gn:name":"Santo Tom\u00e1s",
    "gn:population":6,
    "gn:timezone":"America/Mazatlan",
    "iso:country":"MX",
    "name:ceb_x_preferred":[
        "Santo Tomas"
    ],
    "name:deu_x_preferred":[
        "Santo Tomas"
    ],
    "name:ilo_x_preferred":[
        "Santo Tomas"
    ],
    "name:lit_x_preferred":[
        "Santo Tomas"
    ],
    "name:nld_x_preferred":[
        "Santo Tomas"
    ],
    "name:sco_x_preferred":[
        "Santo Tomas"
    ],
    "name:spa_x_preferred":[
        "Santo Tom\u00e1s"
    ],
    "name:srp_x_preferred":[
        "\u0421\u0430\u043d\u0442\u043e \u0422\u043e\u043c\u0430\u0441"
    ],
    "name:swe_x_preferred":[
        "Santo Tomas"
    ],
    "name:war_x_preferred":[
        "Santo Tomas"
    ],
    "wof:name":"Santo Tomas",
    "wof:placetype":"locality",
    "wof:population":6
},
  "geometry": {"coordinates":[-111.23321,25.38421],"type":"Point"}
}