{
  "type": "Feature",
  "properties": {
    "gn:admin1_code":"3.0",
    "gn:admin2_code":"1.0",
    "gn:asciiname":"Santo Tomas",
    "gn:country_code":"MX",
    "gn:dem":310,
    "gn:feature_class":"P",
    "gn:feature_code":"PPL",
    "gn:name":"Santo Tom\u00e1s",
    "gn:population":6,
    "gn:timezone":"America/Mazatlan",
    "iso:country":"MX",
    "name:spa_x_preferred":[
        "Santo Tom\u00e1s"
    ],
    "wof:name":"Santo Tomas",
    "wof:placetype":"locality",
    "wof:population":6
},
  "geometry": {"coordinates":[-111.23321,25.38421],"type":"Point"}
}