{
  "type": "Feature",
  "properties": {
    "gn:admin1_code":"3.0",
    "gn:admin2_code":"1.0",
    "gn:asciiname":"Santo Tomas",
    "gn:country_code":"MX",
    "gn:dem":310,
    "gn:feature_class":"P",
    "gn:feature_code":"PPL",
    "gn:name":"Santo Tom\u00e1s",
    "gn:population":6,
    "gn:timezone":"America/Mazatlan",
    "iso:country":"MX",
    "name:ara_x_preferred":[
        "\u0633\u0627\u0646\u062a \u062a\u0648\u0645\u0627\u0633"
    ],
    "name:ben_x_preferred":[
        "\u09b8\u09cd\u09af\u09be\u09a8\u09cd\u099f\u09cb \u099f\u09ae\u09be\u09b8"
    ],
    "name:ceb_x_preferred":[
        "Santo Tomas"
    ],
    "name:deu_x_preferred":[
        "Santo Tomas"
    ],
    "name:ell_x_preferred":[
        "\u03a3\u03ac\u03bd\u03c4\u03bf \u03a4\u03cc\u03bc\u03b1\u03c2"
    ],
    "name:heb_x_preferred":[
        "\u05e1\u05e0\u05d8\u05d5 \u05ea\u05d5\u05de\u05d0\u05e1"
    ],
    "name:hin_x_preferred":[
        "\u0938\u0948\u0902\u091f\u094b \u091f\u0949\u092e\u0938"
    ],
    "name:hun_x_preferred":[
        "Santo Tomas"
    ],
    "name:ilo_x_preferred":[
        "Santo Tomas"
    ],
    "name:ind_x_preferred":[
        "Santo Tomas"
    ],
    "name:ita_x_preferred":[
        "Santo Tom\u00e1s"
    ],
    "name:jpn_x_preferred":[
        "\u30b5\u30f3\u30c8\u30c8\u30fc\u30de\u30b9"
    ],
    "name:kor_x_preferred":[
        "\uc0b0\ud1a0 \ud1a0\ub9c8\uc2a4"
    ],
    "name:lit_x_preferred":[
        "Santo Tomas"
    ],
    "name:nld_x_preferred":[
        "Santo Tomas"
    ],
    "name:sco_x_preferred":[
        "Santo Tomas"
    ],
    "name:spa_x_preferred":[
        "Santo Tom\u00e1s"
    ],
    "name:srp_x_preferred":[
        "\u0421\u0430\u043d\u0442\u043e \u0422\u043e\u043c\u0430\u0441"
    ],
    "name:swe_x_preferred":[
        "Santo Tomas"
    ],
    "name:tur_x_preferred":[
        "Santo Tomas"
    ],
    "name:ukr_x_preferred":[
        "\u0421\u0430\u043d\u0442\u043e-\u0422\u043e\u043c\u0430\u0441"
    ],
    "name:urd_x_preferred":[
        "\u0633\u0627\u0646\u0679\u0648 \u0679\u0648\u0645\u0627\u0633"
    ],
    "name:vie_x_preferred":[
        "Santo Tomas"
    ],
    "name:war_x_preferred":[
        "Santo Tomas"
    ],
    "wof:name":"Santo Tomas",
    "wof:placetype":"locality",
    "wof:population":6
},
  "geometry": {"coordinates":[-111.23321,25.38421],"type":"Point"}
}