{
  "type": "Feature",
  "properties": {
    "gn:admin1_code":"8",
    "gn:admin2_code":"6.0",
    "gn:asciiname":"Rancho de Olivera (La Pena)",
    "gn:country_code":"MX",
    "gn:dem":117,
    "gn:feature_class":"P",
    "gn:feature_code":"PPL",
    "gn:name":"Rancho de Olivera (La Pe\u00f1a)",
    "gn:population":4,
    "gn:timezone":"America/Mexico_City",
    "iso:country":"MX",
    "name:und_x_variant":[
        "Rancho de Olivera (La Pe\u00f1a)"
    ],
    "wof:name":"Rancho de Olivera (La Pena)",
    "wof:placetype":"locality",
    "wof:population":4
},
  "geometry": {"coordinates":[-103.71028,19.00917],"type":"Point"}
}