{
  "type": "Feature",
  "properties": {
    "gn:admin1_code":"13",
    "gn:admin2_code":"34.0",
    "gn:asciiname":"Quimixtla",
    "gn:country_code":"MX",
    "gn:dem":758,
    "gn:feature_class":"P",
    "gn:feature_code":"PPL",
    "gn:name":"Quimixtla",
    "gn:population":76,
    "gn:timezone":"America/Mexico_City",
    "iso:country":"MX",
    "name:spa_x_preferred":[
        "Quinixtla"
    ],
    "name:spa_x_variant":[
        "Quimixtla"
    ],
    "wof:name":"Quimixtla",
    "wof:placetype":"locality",
    "wof:population":76
},
  "geometry": {"coordinates":[-98.73488,21.09545],"type":"Point"}
}