{
  "type": "Feature",
  "properties": {
    "gn:admin1_code":"11",
    "gn:admin2_code":"2.0",
    "gn:asciiname":"La Purisima Concepcion",
    "gn:country_code":"MX",
    "gn:dem":1910,
    "gn:feature_class":"P",
    "gn:feature_code":"PPL",
    "gn:name":"La Pur\u00edsima Concepci\u00f3n",
    "gn:population":241,
    "gn:timezone":"America/Mexico_City",
    "iso:country":"MX",
    "name:und_x_variant":[
        "La Pur\u00edsima Concepci\u00f3n"
    ],
    "wof:name":"La Purisima Concepcion",
    "wof:placetype":"locality",
    "wof:population":241
},
  "geometry": {"coordinates":[-100.65582999999999,20.08222],"type":"Point"}
}