{
  "type": "Feature",
  "properties": {
    "gn:admin1_code":"26.0",
    "gn:admin2_code":"13.0",
    "gn:asciiname":"La Talega",
    "gn:country_code":"MX",
    "gn:dem":681,
    "gn:feature_class":"P",
    "gn:feature_code":"PPL",
    "gn:name":"La Talega",
    "gn:population":0,
    "gn:timezone":"America/Hermosillo",
    "iso:country":"MX",
    "name:spa_x_preferred":[
        "La Talega"
    ],
    "wof:name":"La Talega",
    "wof:placetype":"locality"
},
  "geometry": {"coordinates":[-110.22399,30.04382],"type":"Point"}
}