{
  "type": "Feature",
  "properties": {
    "gn:admin1_code":"10",
    "gn:admin2_code":"32.0",
    "gn:asciiname":"Melchor Ocampo",
    "gn:country_code":"MX",
    "gn:dem":1650,
    "gn:feature_class":"P",
    "gn:feature_code":"PPL",
    "gn:name":"Melchor Ocampo",
    "gn:population":0,
    "gn:timezone":"America/Monterrey",
    "iso:country":"MX",
    "name:deu_x_preferred":[
        "Melchor Ocampo"
    ],
    "name:epo_x_preferred":[
        "Melchor Ocampo"
    ],
    "name:fra_x_preferred":[
        "Melchor Ocampo"
    ],
    "name:ita_x_preferred":[
        "Melchor Ocampo"
    ],
    "name:nld_x_preferred":[
        "Melchor Ocampo"
    ],
    "name:pol_x_preferred":[
        "Melchor Ocampo"
    ],
    "name:por_x_preferred":[
        "Melchor Ocampo"
    ],
    "name:que_x_preferred":[
        "Melchor Ocampo"
    ],
    "name:rus_x_preferred":[
        "\u041e\u043a\u0430\u043c\u043f\u043e"
    ],
    "name:spa_x_preferred":[
        "Melchor Ocampo"
    ],
    "name:und_x_variant":[
        "Melchorito",
        "Melchor"
    ],
    "wof:name":"Melchor Ocampo",
    "wof:placetype":"locality"
},
  "geometry": {"coordinates":[-105.26023000000001,25.36456],"type":"Point"}
}