{
  "type": "Feature",
  "properties": {
    "gn:admin1_code":"5",
    "gn:admin2_code":"92",
    "gn:asciiname":"Filemon Gonzalez",
    "gn:country_code":"MX",
    "gn:dem":249,
    "gn:feature_class":"P",
    "gn:feature_code":"PPL",
    "gn:name":"Filem\u00f3n Gonz\u00e1lez",
    "gn:population":13,
    "gn:timezone":"America/Mexico_City",
    "iso:country":"MX",
    "name:und_x_variant":[
        "Filem\u00f3n Gonz\u00e1lez"
    ],
    "wof:name":"Filemon Gonzalez",
    "wof:placetype":"locality",
    "wof:population":13
},
  "geometry": {"coordinates":[-93.41056,17.105],"type":"Point"}
}