{
  "type": "Feature",
  "properties": {
    "gn:admin1_code":"14.0",
    "gn:admin2_code":"87.0",
    "gn:asciiname":"La Relumbrosa",
    "gn:country_code":"MX",
    "gn:dem":1591,
    "gn:feature_class":"P",
    "gn:feature_code":"PPL",
    "gn:name":"La Relumbrosa",
    "gn:population":0,
    "gn:timezone":"America/Mexico_City",
    "iso:country":"MX",
    "name:spa_x_preferred":[
        "La Relumbrosa"
    ],
    "wof:name":"La Relumbrosa",
    "wof:placetype":"locality"
},
  "geometry": {"coordinates":[-103.14147,19.15381],"type":"Point"}
}