{
  "type": "Feature",
  "properties": {
    "gn:admin1_code":"31",
    "gn:admin2_code":"61.0",
    "gn:asciiname":"Soledad",
    "gn:country_code":"MX",
    "gn:dem":6,
    "gn:feature_class":"P",
    "gn:feature_code":"PPL",
    "gn:name":"Soledad",
    "gn:population":0,
    "gn:timezone":"America/Merida",
    "iso:country":"MX",
    "name:bre_x_preferred":[
        "Soledad"
    ],
    "name:cat_x_preferred":[
        "Soledad"
    ],
    "name:ceb_x_preferred":[
        "Soledad"
    ],
    "name:deu_x_preferred":[
        "Soledad"
    ],
    "name:fra_x_preferred":[
        "Soledad"
    ],
    "name:ita_x_preferred":[
        "Soledad"
    ],
    "name:lit_x_preferred":[
        "Soledad"
    ],
    "name:nld_x_preferred":[
        "Soledad"
    ],
    "name:pol_x_preferred":[
        "Soledad"
    ],
    "name:por_x_preferred":[
        "Soledad"
    ],
    "name:spa_x_preferred":[
        "Soledad"
    ],
    "name:srp_x_preferred":[
        "\u0421\u043e\u043b\u0435\u0434\u0430\u0434"
    ],
    "name:swe_x_preferred":[
        "Soledad"
    ],
    "name:vol_x_preferred":[
        "Soledad"
    ],
    "name:war_x_preferred":[
        "Soledad"
    ],
    "wof:name":"Soledad",
    "wof:placetype":"locality"
},
  "geometry": {"coordinates":[-88.11964,21.57139],"type":"Point"}
}