{
  "type": "Feature",
  "properties": {
    "gn:admin1_code":"15.0",
    "gn:asciiname":"Barrio de San Miguel",
    "gn:country_code":"MX",
    "gn:dem":2737,
    "gn:feature_class":"P",
    "gn:feature_code":"PPL",
    "gn:name":"Barrio de San Miguel",
    "gn:population":0,
    "gn:timezone":"America/Mexico_City",
    "iso:country":"MX",
    "name:spa_x_preferred":[
        "Barrio de San Miguel"
    ],
    "wof:name":"Barrio de San Miguel",
    "wof:placetype":"locality"
},
  "geometry": {"coordinates":[-99.95466999999999,19.51232000000001],"type":"Point"}
}