{
  "type": "Feature",
  "properties": {
    "gn:admin1_code":"26",
    "gn:admin2_code":"13.0",
    "gn:asciiname":"La Muralla",
    "gn:cc2":"MX",
    "gn:country_code":"MX",
    "gn:dem":814,
    "gn:feature_class":"P",
    "gn:feature_code":"PPL",
    "gn:name":"La Muralla",
    "gn:population":0,
    "gn:timezone":"America/Hermosillo",
    "iso:country":"MX",
    "name:und_x_variant":[
        "Muralla",
        "La Muralla"
    ],
    "wof:name":"La Muralla",
    "wof:placetype":"locality"
},
  "geometry": {"coordinates":[-110.18333,30.08333],"type":"Point"}
}