{
  "type": "Feature",
  "properties": {
    "gn:admin1_code":"12.0",
    "gn:admin2_code":"11.0",
    "gn:asciiname":"Nueva Delhi",
    "gn:country_code":"MX",
    "gn:dem":1354,
    "gn:feature_class":"P",
    "gn:feature_code":"PPL",
    "gn:name":"Nueva Delhi",
    "gn:population":0,
    "gn:timezone":"America/Mexico_City",
    "iso:country":"MX",
    "name:spa_x_preferred":[
        "Nueva Delhi"
    ],
    "wof:name":"Nueva Delhi",
    "wof:placetype":"locality"
},
  "geometry": {"coordinates":[-100.19421,17.41539],"type":"Point"}
}