{
  "type": "Feature",
  "properties": {
    "gn:admin1_code":"4",
    "gn:admin2_code":"6.0",
    "gn:asciiname":"Montecristo",
    "gn:country_code":"MX",
    "gn:dem":87,
    "gn:feature_class":"P",
    "gn:feature_code":"PPL",
    "gn:name":"Montecristo",
    "gn:population":0,
    "gn:timezone":"America/Merida",
    "iso:country":"MX",
    "name:spa_x_preferred":[
        "Montecristo"
    ],
    "wof:name":"Montecristo",
    "wof:placetype":"locality"
},
  "geometry": {"coordinates":[-89.69863000000002,19.62379],"type":"Point"}
}