{
  "type": "Feature",
  "properties": {
    "gn:admin1_code":"26",
    "gn:admin2_code":"30.0",
    "gn:asciiname":"Covadonga",
    "gn:country_code":"MX",
    "gn:dem":69,
    "gn:feature_class":"P",
    "gn:feature_code":"PPL",
    "gn:name":"Covadonga",
    "gn:population":11,
    "gn:timezone":"America/Hermosillo",
    "iso:country":"MX",
    "name:spa_x_preferred":[
        "Covadonga"
    ],
    "wof:name":"Covadonga",
    "wof:placetype":"locality",
    "wof:population":11
},
  "geometry": {"coordinates":[-111.48267,28.88038],"type":"Point"}
}