{
  "type": "Feature",
  "properties": {
    "gn:admin1_code":"20",
    "gn:admin2_code":"6.0",
    "gn:asciiname":"Santa Catarina Adequez",
    "gn:country_code":"MX",
    "gn:dem":2235,
    "gn:feature_class":"P",
    "gn:feature_code":"PPL",
    "gn:name":"Santa Catarina Ad\u00e9quez",
    "gn:population":0,
    "gn:timezone":"America/Mexico_City",
    "iso:country":"MX",
    "name:und_x_variant":[
        "Ad\u00e9quez",
        "Santa Catarina Ad\u00e9quez"
    ],
    "wof:name":"Santa Catarina Adequez",
    "wof:placetype":"locality"
},
  "geometry": {"coordinates":[-97.14637999999999,17.43577],"type":"Point"}
}