{
  "type": "Feature",
  "properties": {
    "gn:admin1_code":"3",
    "gn:admin2_code":"3.0",
    "gn:asciiname":"El Inquieto",
    "gn:country_code":"MX",
    "gn:dem":541,
    "gn:feature_class":"P",
    "gn:feature_code":"PPL",
    "gn:name":"El Inquieto",
    "gn:population":4,
    "gn:timezone":"America/Mazatlan",
    "iso:country":"MX",
    "wof:name":"El Inquieto",
    "wof:placetype":"locality",
    "wof:population":4
},
  "geometry": {"coordinates":[-109.83804000000001,23.70549],"type":"Point"}
}