{
  "type": "Feature",
  "properties": {
    "gn:admin1_code":"30",
    "gn:admin2_code":"158",
    "gn:asciiname":"Marbella",
    "gn:country_code":"MX",
    "gn:dem":10,
    "gn:feature_class":"P",
    "gn:feature_code":"PPL",
    "gn:name":"Marbella",
    "gn:population":13,
    "gn:timezone":"America/Mexico_City",
    "iso:country":"MX",
    "wof:name":"Marbella",
    "wof:placetype":"locality",
    "wof:population":13
},
  "geometry": {"coordinates":[-96.82722,20.28389],"type":"Point"}
}