{
  "type": "Feature",
  "properties": {
    "gn:admin1_code":"32",
    "gn:admin2_code":"49",
    "gn:asciiname":"La Turista (La Teneria)",
    "gn:country_code":"MX",
    "gn:dem":1985,
    "gn:feature_class":"P",
    "gn:feature_code":"PPL",
    "gn:name":"La Turista (La Tener\u00eda)",
    "gn:population":13,
    "gn:timezone":"America/Mexico_City",
    "iso:country":"MX",
    "name:und_x_variant":[
        "La Turista (La Tener\u00eda)"
    ],
    "wof:name":"La Turista (La Teneria)",
    "wof:placetype":"locality",
    "wof:population":13
},
  "geometry": {"coordinates":[-103.48999999999999,22.88861],"type":"Point"}
}