{
  "type": "Feature",
  "properties": {
    "gn:admin1_code":"7",
    "gn:admin2_code":"17.0",
    "gn:asciiname":"Santo Nino Aguanaval",
    "gn:country_code":"MX",
    "gn:dem":1141,
    "gn:feature_class":"P",
    "gn:feature_code":"PPL",
    "gn:name":"Santo Ni\u00f1o Aguanaval",
    "gn:population":0,
    "gn:timezone":"America/Monterrey",
    "iso:country":"MX",
    "name:und_x_variant":[
        "Santo Ni\u00f1o",
        "Santo Ni\u00f1o Aguanaval"
    ],
    "wof:name":"Santo Nino Aguanaval",
    "wof:placetype":"locality"
},
  "geometry": {"coordinates":[-103.27909,25.43118],"type":"Point"}
}