{
  "type": "Feature",
  "properties": {
    "gn:admin1_code":"12",
    "gn:admin2_code":"2.0",
    "gn:asciiname":"Loma Bonita",
    "gn:country_code":"MX",
    "gn:dem":1471,
    "gn:feature_class":"P",
    "gn:feature_code":"PPL",
    "gn:name":"Loma Bonita",
    "gn:population":113,
    "gn:timezone":"America/Mexico_City",
    "iso:country":"MX",
    "wof:name":"Loma Bonita",
    "wof:placetype":"locality",
    "wof:population":113
},
  "geometry": {"coordinates":[-98.81629,17.68119],"type":"Point"}
}