{
  "type": "Feature",
  "properties": {
    "gn:admin1_code":"20",
    "gn:admin2_code":"567.0",
    "gn:asciiname":"Tlalotepec Lagunas",
    "gn:country_code":"MX",
    "gn:dem":1520,
    "gn:feature_class":"P",
    "gn:feature_code":"PPL",
    "gn:name":"Tlalotepec Lagunas",
    "gn:population":110,
    "gn:timezone":"America/Mexico_City",
    "iso:country":"MX",
    "name:spa_x_preferred":[
        "Tlacotepec Lagunas"
    ],
    "name:spa_x_variant":[
        "Tlalotepec Lagunas"
    ],
    "wof:name":"Tlalotepec Lagunas",
    "wof:placetype":"locality",
    "wof:population":110
},
  "geometry": {"coordinates":[-98.3237,17.75583],"type":"Point"}
}