{
  "type": "Feature",
  "properties": {
    "gn:admin1_code":"5",
    "gn:admin2_code":"89",
    "gn:asciiname":"Toscanis",
    "gn:country_code":"MX",
    "gn:dem":1939,
    "gn:feature_class":"P",
    "gn:feature_code":"PPL",
    "gn:name":"Toscanis",
    "gn:population":23,
    "gn:timezone":"America/Mexico_City",
    "iso:country":"MX",
    "wof:name":"Toscanis",
    "wof:placetype":"locality",
    "wof:population":23
},
  "geometry": {"coordinates":[-92.20833,15.18417],"type":"Point"}
}