{
  "type": "Feature",
  "properties": {
    "gn:admin1_code":"19",
    "gn:admin2_code":"38.0",
    "gn:asciiname":"El Ebanito",
    "gn:country_code":"MX",
    "gn:dem":488,
    "gn:feature_class":"P",
    "gn:feature_code":"PPL",
    "gn:name":"El Ebanito",
    "gn:population":8,
    "gn:timezone":"America/Monterrey",
    "iso:country":"MX",
    "wof:name":"El Ebanito",
    "wof:placetype":"locality",
    "wof:population":8
},
  "geometry": {"coordinates":[-99.82111,25.11563],"type":"Point"}
}