{
  "type": "Feature",
  "properties": {
    "gn:admin1_code":"32",
    "gn:admin2_code":"33",
    "gn:asciiname":"La Boquilla",
    "gn:country_code":"MX",
    "gn:dem":1482,
    "gn:feature_class":"P",
    "gn:feature_code":"PPL",
    "gn:name":"La Boquilla",
    "gn:population":14,
    "gn:timezone":"America/Mexico_City",
    "iso:country":"MX",
    "wof:name":"La Boquilla",
    "wof:placetype":"locality",
    "wof:population":14
},
  "geometry": {"coordinates":[-103.15944,21.11667000000001],"type":"Point"}
}