{
  "type": "Feature",
  "properties": {
    "gn:admin1_code":"19",
    "gn:admin2_code":"4.0",
    "gn:asciiname":"El Cerrito",
    "gn:country_code":"MX",
    "gn:dem":419,
    "gn:feature_class":"P",
    "gn:feature_code":"PPL",
    "gn:name":"El Cerrito",
    "gn:population":286,
    "gn:timezone":"America/Monterrey",
    "iso:country":"MX",
    "name:spa_x_preferred":[
        "El Cerrito"
    ],
    "wof:name":"El Cerrito",
    "wof:placetype":"locality",
    "wof:population":286
},
  "geometry": {"coordinates":[-99.98675,25.29542],"type":"Point"}
}