{
  "type": "Feature",
  "properties": {
    "gn:admin1_code":"26",
    "gn:admin2_code":"9.0",
    "gn:asciiname":"La Mano",
    "gn:country_code":"MX",
    "gn:dem":561,
    "gn:feature_class":"P",
    "gn:feature_code":"PPL",
    "gn:name":"La Mano",
    "gn:population":0,
    "gn:timezone":"America/Hermosillo",
    "iso:country":"MX",
    "name:spa_x_preferred":[
        "La Mano"
    ],
    "wof:name":"La Mano",
    "wof:placetype":"locality"
},
  "geometry": {"coordinates":[-109.39831,28.86682],"type":"Point"}
}