{
  "type": "Feature",
  "properties": {
    "gn:admin1_code":"30",
    "gn:admin2_code":"105.0",
    "gn:asciiname":"La Bascula (La Union)",
    "gn:country_code":"MX",
    "gn:dem":20,
    "gn:feature_class":"P",
    "gn:feature_code":"PPL",
    "gn:name":"La B\u00e1scula (La Uni\u00f3n)",
    "gn:population":157,
    "gn:timezone":"America/Mexico_City",
    "iso:country":"MX",
    "name:und_x_variant":[
        "La B\u00e1scula (La Uni\u00f3n)"
    ],
    "wof:name":"La Bascula (La Union)",
    "wof:placetype":"locality",
    "wof:population":157
},
  "geometry": {"coordinates":[-96.09,18.98889],"type":"Point"}
}