{
  "type": "Feature",
  "properties": {
    "gn:admin1_code":"16",
    "gn:admin2_code":"52.0",
    "gn:asciiname":"Playas del Medio",
    "gn:country_code":"MX",
    "gn:dem":71,
    "gn:feature_class":"P",
    "gn:feature_code":"PPL",
    "gn:name":"Playas del Medio",
    "gn:population":0,
    "gn:timezone":"America/Mexico_City",
    "iso:country":"MX",
    "name:spa_x_preferred":[
        "Playas del Medio"
    ],
    "wof:name":"Playas del Medio",
    "wof:placetype":"locality"
},
  "geometry": {"coordinates":[-102.15922,18.16925],"type":"Point"}
}