{
  "type": "Feature",
  "properties": {
    "gn:admin1_code":"25",
    "gn:admin2_code":"11.0",
    "gn:asciiname":"Ejido Charco Largo",
    "gn:country_code":"MX",
    "gn:dem":22,
    "gn:feature_class":"P",
    "gn:feature_code":"PPL",
    "gn:name":"Ejido Charco Largo",
    "gn:population":152,
    "gn:timezone":"America/Mazatlan",
    "iso:country":"MX",
    "wof:name":"Ejido Charco Largo",
    "wof:placetype":"locality",
    "wof:population":152
},
  "geometry": {"coordinates":[-108.27278,25.53583],"type":"Point"}
}