{
  "type": "Feature",
  "properties": {
    "gn:admin1_code":"15",
    "gn:admin2_code":"5.0",
    "gn:asciiname":"Cerro San Mateo",
    "gn:country_code":"MX",
    "gn:dem":2782,
    "gn:feature_class":"P",
    "gn:feature_code":"PPL",
    "gn:name":"Cerro San Mateo",
    "gn:population":146,
    "gn:timezone":"America/Mexico_City",
    "iso:country":"MX",
    "wof:name":"Cerro San Mateo",
    "wof:placetype":"locality",
    "wof:population":146
},
  "geometry": {"coordinates":[-99.75111,19.33889],"type":"Point"}
}