{
  "type": "Feature",
  "properties": {
    "gn:admin1_code":"26.0",
    "gn:admin2_code":"6.0",
    "gn:asciiname":"El Jucarito",
    "gn:country_code":"MX",
    "gn:dem":1358,
    "gn:feature_class":"P",
    "gn:feature_code":"PPL",
    "gn:name":"El Jucarito",
    "gn:population":0,
    "gn:timezone":"America/Hermosillo",
    "iso:country":"MX",
    "name:spa_x_preferred":[
        "El Jucarito"
    ],
    "wof:name":"El Jucarito",
    "wof:placetype":"locality"
},
  "geometry": {"coordinates":[-110.07288,30.29625],"type":"Point"}
}