{
  "type": "Feature",
  "properties": {
    "gn:admin1_code":"10",
    "gn:admin2_code":"9.0",
    "gn:asciiname":"Hoya la Calabacilla",
    "gn:country_code":"MX",
    "gn:dem":2333,
    "gn:feature_class":"P",
    "gn:feature_code":"PPL",
    "gn:name":"Hoya la Calabacilla",
    "gn:population":0,
    "gn:timezone":"America/Monterrey",
    "iso:country":"MX",
    "name:spa_x_preferred":[
        "Hoya la Calabacilla"
    ],
    "wof:name":"Hoya la Calabacilla",
    "wof:placetype":"locality"
},
  "geometry": {"coordinates":[-105.97614,26.2898],"type":"Point"}
}