{
  "type": "Feature",
  "properties": {
    "gn:admin1_code":"14.0",
    "gn:admin2_code":"36.0",
    "gn:asciiname":"Los Guajes",
    "gn:country_code":"MX",
    "gn:dem":1555,
    "gn:feature_class":"P",
    "gn:feature_code":"PPL",
    "gn:name":"Los Guajes",
    "gn:population":0,
    "gn:timezone":"America/Mexico_City",
    "iso:country":"MX",
    "name:spa_x_preferred":[
        "Los Guajes"
    ],
    "wof:name":"Los Guajes",
    "wof:placetype":"locality"
},
  "geometry": {"coordinates":[-104.13782999999999,20.64966],"type":"Point"}
}