{
  "type": "Feature",
  "properties": {
    "gn:admin1_code":"30",
    "gn:admin2_code":"109.0",
    "gn:asciiname":"San Angel",
    "gn:country_code":"MX",
    "gn:dem":138,
    "gn:feature_class":"P",
    "gn:feature_code":"PPL",
    "gn:name":"San \u00c1ngel",
    "gn:population":5,
    "gn:timezone":"America/Mexico_City",
    "iso:country":"MX",
    "name:und_x_variant":[
        "San \u00c1ngel"
    ],
    "wof:name":"San Angel",
    "wof:placetype":"locality",
    "wof:population":5
},
  "geometry": {"coordinates":[-96.93917,19.98583],"type":"Point"}
}