{
  "type": "Feature",
  "properties": {
    "gn:admin1_code":"5",
    "gn:admin2_code":"59.0",
    "gn:asciiname":"Aurora Buenavista",
    "gn:country_code":"MX",
    "gn:dem":1316,
    "gn:feature_class":"P",
    "gn:feature_code":"PPL",
    "gn:name":"Aurora Buenavista",
    "gn:population":255,
    "gn:timezone":"America/Mexico_City",
    "iso:country":"MX",
    "wof:name":"Aurora Buenavista",
    "wof:placetype":"locality",
    "wof:population":255
},
  "geometry": {"coordinates":[-92.31467000000001,16.95119],"type":"Point"}
}