{
  "type": "Feature",
  "properties": {
    "gn:admin1_code":"32",
    "gn:admin2_code":"10.0",
    "gn:asciiname":"San Luis de Abrego",
    "gn:country_code":"MX",
    "gn:dem":2306,
    "gn:feature_class":"P",
    "gn:feature_code":"PPL",
    "gn:name":"San Luis de \u00c1brego",
    "gn:population":0,
    "gn:timezone":"America/Mexico_City",
    "iso:country":"MX",
    "name:spa_x_preferred":[
        "San Luis de \u00c1brego"
    ],
    "wof:name":"San Luis de Abrego",
    "wof:placetype":"locality"
},
  "geometry": {"coordinates":[-103.33360999999999,23.09144],"type":"Point"}
}