{
  "type": "Feature",
  "properties": {
    "gn:admin1_code":"26",
    "gn:admin2_code":"43.0",
    "gn:asciiname":"Santa Barbara",
    "gn:cc2":"MX",
    "gn:country_code":"MX",
    "gn:dem":1197,
    "gn:feature_class":"P",
    "gn:feature_code":"PPL",
    "gn:name":"Santa B\u00e1rbara",
    "gn:population":0,
    "gn:timezone":"America/Hermosillo",
    "iso:country":"MX",
    "name:und_x_variant":[
        "Rancho Santa Barbara",
        "Santa B\u00e1rbara"
    ],
    "wof:name":"Santa Barbara",
    "wof:placetype":"locality"
},
  "geometry": {"coordinates":[-110.76667,31.23333],"type":"Point"}
}