{
  "type": "Feature",
  "properties": {
    "gn:admin1_code":"12.0",
    "gn:admin2_code":"6.0",
    "gn:asciiname":"El Remolino",
    "gn:country_code":"MX",
    "gn:dem":386,
    "gn:feature_class":"P",
    "gn:feature_code":"PPL",
    "gn:name":"El Remolino",
    "gn:population":0,
    "gn:timezone":"America/Mexico_City",
    "iso:country":"MX",
    "name:fra_x_preferred":[
        "El Remolino"
    ],
    "name:spa_x_preferred":[
        "El Remolino"
    ],
    "wof:name":"El Remolino",
    "wof:placetype":"locality"
},
  "geometry": {"coordinates":[-100.04871,17.96852],"type":"Point"}
}