{
  "type": "Feature",
  "properties": {
    "gn:admin1_code":"20",
    "gn:admin2_code":"395.0",
    "gn:asciiname":"Llano del Sabino",
    "gn:country_code":"MX",
    "gn:dem":2173,
    "gn:feature_class":"P",
    "gn:feature_code":"PPL",
    "gn:name":"Llano del Sabino",
    "gn:population":145,
    "gn:timezone":"America/Mexico_City",
    "iso:country":"MX",
    "wof:name":"Llano del Sabino",
    "wof:placetype":"locality",
    "wof:population":145
},
  "geometry": {"coordinates":[-97.08499999999999,17.63417],"type":"Point"}
}