{
  "type": "Feature",
  "properties": {
    "gn:admin1_code":"11",
    "gn:admin2_code":"30",
    "gn:asciiname":"Espiritu Santo",
    "gn:country_code":"MX",
    "gn:dem":2151,
    "gn:feature_class":"P",
    "gn:feature_code":"PPL",
    "gn:name":"Esp\u00edritu Santo",
    "gn:population":11,
    "gn:timezone":"America/Mexico_City",
    "iso:country":"MX",
    "name:und_x_variant":[
        "Esp\u00edritu Santo"
    ],
    "wof:name":"Espiritu Santo",
    "wof:placetype":"locality",
    "wof:population":11
},
  "geometry": {"coordinates":[-101.29389,21.27083],"type":"Point"}
}