{
  "type": "Feature",
  "properties": {
    "gn:admin1_code":"15.0",
    "gn:admin2_code":"110.0",
    "gn:asciiname":"Acatitlan",
    "gn:country_code":"MX",
    "gn:dem":2001,
    "gn:feature_class":"P",
    "gn:feature_code":"PPL",
    "gn:name":"Acatitl\u00e1n",
    "gn:population":0,
    "gn:timezone":"America/Mexico_City",
    "iso:country":"MX",
    "name:spa_x_preferred":[
        "Acatitl\u00e1n"
    ],
    "name:spa_x_variant":[
        "San Mateo Acatitl\u00e1n"
    ],
    "wof:name":"Acatitlan",
    "wof:placetype":"locality"
},
  "geometry": {"coordinates":[-100.09426000000001,19.18771],"type":"Point"}
}