{
  "type": "Feature",
  "properties": {
    "gn:admin1_code":"15.0",
    "gn:asciiname":"Los Hornos de Cuatzingo",
    "gn:country_code":"MX",
    "gn:dem":2255,
    "gn:feature_class":"P",
    "gn:feature_code":"PPL",
    "gn:name":"Los Hornos de Cuatzingo",
    "gn:population":0,
    "gn:timezone":"America/Mexico_City",
    "iso:country":"MX",
    "name:spa_x_preferred":[
        "Los Hornos de Cuatzingo"
    ],
    "wof:name":"Los Hornos de Cuatzingo",
    "wof:placetype":"locality"
},
  "geometry": {"coordinates":[-98.84701,19.25709],"type":"Point"}
}