{
  "type": "Feature",
  "properties": {
    "gn:admin1_code":"6",
    "gn:admin2_code":"9.0",
    "gn:asciiname":"Los Basiguares",
    "gn:country_code":"MX",
    "gn:dem":2450,
    "gn:feature_class":"P",
    "gn:feature_code":"PPL",
    "gn:name":"Los Bas\u00edguares",
    "gn:population":7,
    "gn:timezone":"America/Chihuahua",
    "iso:country":"MX",
    "name:und_x_variant":[
        "Los Bas\u00edguares"
    ],
    "wof:name":"Los Basiguares",
    "wof:placetype":"locality",
    "wof:population":7
},
  "geometry": {"coordinates":[-107.55688000000001,27.9988],"type":"Point"}
}