{
  "type": "Feature",
  "properties": {
    "gn:admin1_code":"26.0",
    "gn:admin2_code":"36.0",
    "gn:asciiname":"Las Mochas",
    "gn:country_code":"MX",
    "gn:dem":833,
    "gn:feature_class":"P",
    "gn:feature_code":"PPL",
    "gn:name":"Las Mochas",
    "gn:population":0,
    "gn:timezone":"America/Hermosillo",
    "iso:country":"MX",
    "name:spa_x_preferred":[
        "Las Mochas"
    ],
    "wof:name":"Las Mochas",
    "wof:placetype":"locality"
},
  "geometry": {"coordinates":[-110.87860999999999,30.56067],"type":"Point"}
}