{
  "type": "Feature",
  "properties": {
    "gn:admin1_code":"14",
    "gn:admin2_code":"2",
    "gn:asciiname":"Santa Ana [Estacion]",
    "gn:country_code":"MX",
    "gn:dem":1361,
    "gn:feature_class":"P",
    "gn:feature_code":"PPL",
    "gn:name":"Santa Ana [Estaci\u00f3n]",
    "gn:population":50,
    "gn:timezone":"America/Mexico_City",
    "iso:country":"MX",
    "name:und_x_variant":[
        "Santa Ana [Estaci\u00f3n]"
    ],
    "wof:name":"Santa Ana [Estacion]",
    "wof:placetype":"locality",
    "wof:population":50
},
  "geometry": {"coordinates":[-103.61611000000001,20.41278],"type":"Point"}
}