{
  "type": "Feature",
  "properties": {
    "gn:admin1_code":"10.0",
    "gn:admin2_code":"36.0",
    "gn:asciiname":"El Chaparral",
    "gn:country_code":"MX",
    "gn:dem":1094,
    "gn:feature_class":"P",
    "gn:feature_code":"PPL",
    "gn:name":"El Chaparral",
    "gn:population":0,
    "gn:timezone":"America/Monterrey",
    "iso:country":"MX",
    "name:spa_x_preferred":[
        "El Chaparral"
    ],
    "wof:name":"El Chaparral",
    "wof:placetype":"locality"
},
  "geometry": {"coordinates":[-103.41182999999999,26.15996],"type":"Point"}
}