{
  "type": "Feature",
  "properties": {
    "gn:admin1_code":"31",
    "gn:admin2_code":"96.0",
    "gn:asciiname":"Cenote Azul",
    "gn:country_code":"MX",
    "gn:dem":13,
    "gn:feature_class":"P",
    "gn:feature_code":"PPL",
    "gn:name":"Cenote Azul",
    "gn:population":0,
    "gn:timezone":"America/Merida",
    "iso:country":"MX",
    "name:spa_x_preferred":[
        "Cenote Azul"
    ],
    "wof:name":"Cenote Azul",
    "wof:placetype":"locality"
},
  "geometry": {"coordinates":[-87.71935000000001,21.27648],"type":"Point"}
}