{
  "type": "Feature",
  "properties": {
    "gn:admin1_code":"15",
    "gn:admin2_code":"56.0",
    "gn:asciiname":"San Marcos Tlazalpan",
    "gn:cc2":"MX",
    "gn:country_code":"MX",
    "gn:dem":2731,
    "gn:feature_class":"P",
    "gn:feature_code":"PPL",
    "gn:name":"San Marcos Tlazalpan",
    "gn:population":2441,
    "gn:timezone":"America/Mexico_City",
    "iso:country":"MX",
    "name:und_x_variant":[
        "San Marcos Tlazalpa",
        "San Marcos Tlazalpan"
    ],
    "wof:name":"San Marcos Tlazalpan",
    "wof:placetype":"locality",
    "wof:population":2441
},
  "geometry": {"coordinates":[-99.7175,19.80611],"type":"Point"}
}