{
  "type": "Feature",
  "properties": {
    "gn:admin1_code":"19",
    "gn:admin2_code":"9.0",
    "gn:asciiname":"Hacienda Santa Isabel",
    "gn:country_code":"MX",
    "gn:dem":359,
    "gn:feature_class":"P",
    "gn:feature_code":"PPL",
    "gn:name":"Hacienda Santa Isabel",
    "gn:population":0,
    "gn:timezone":"America/Monterrey",
    "iso:country":"MX",
    "name:spa_x_preferred":[
        "Hacienda Santa Isabel"
    ],
    "name:und_x_variant":[
        "Santa Isabel"
    ],
    "wof:name":"Hacienda Santa Isabel",
    "wof:placetype":"locality"
},
  "geometry": {"coordinates":[-100.01445,25.47292],"type":"Point"}
}