{
  "type": "Feature",
  "properties": {
    "gn:admin1_code":"14",
    "gn:admin2_code":"61.0",
    "gn:asciiname":"Los Leones",
    "gn:country_code":"MX",
    "gn:dem":1846,
    "gn:feature_class":"P",
    "gn:feature_code":"PPL",
    "gn:name":"Los Leones",
    "gn:population":0,
    "gn:timezone":"America/Mexico_City",
    "iso:country":"MX",
    "name:spa_x_preferred":[
        "Los Leones"
    ],
    "wof:name":"Los Leones",
    "wof:placetype":"locality"
},
  "geometry": {"coordinates":[-103.64943,22.38619],"type":"Point"}
}