{
  "type": "Feature",
  "properties": {
    "gn:admin1_code":"28.0",
    "gn:admin2_code":"8.0",
    "gn:asciiname":"Campo Numero Tres",
    "gn:country_code":"MX",
    "gn:dem":169,
    "gn:feature_class":"P",
    "gn:feature_code":"PPL",
    "gn:name":"Campo N\u00famero Tres",
    "gn:population":257,
    "gn:timezone":"America/Monterrey",
    "iso:country":"MX",
    "name:spa_x_preferred":[
        "Campo N\u00famero Tres"
    ],
    "wof:name":"Campo Numero Tres",
    "wof:placetype":"locality",
    "wof:population":257
},
  "geometry": {"coordinates":[-98.74917000000001,23.55917],"type":"Point"}
}