{
  "type": "Feature",
  "properties": {
    "gn:admin1_code":"11.0",
    "gn:admin2_code":"2.0",
    "gn:asciiname":"Santa Ines",
    "gn:country_code":"MX",
    "gn:dem":1919,
    "gn:feature_class":"P",
    "gn:feature_code":"PPL",
    "gn:name":"Santa In\u00e9s",
    "gn:population":419,
    "gn:timezone":"America/Mexico_City",
    "iso:country":"MX",
    "name:ceb_x_preferred":[
        "Santa Ines"
    ],
    "name:nld_x_preferred":[
        "Santa Ines"
    ],
    "name:sco_x_preferred":[
        "Santa Ines"
    ],
    "name:spa_x_preferred":[
        "Santa In\u00e9s"
    ],
    "name:srp_x_preferred":[
        "\u0421\u0430\u043d\u0442\u0430 \u0418\u043d\u0435\u0441"
    ],
    "name:swe_x_preferred":[
        "Santa Ines"
    ],
    "name:war_x_preferred":[
        "Santa Ines"
    ],
    "wof:name":"Santa Ines",
    "wof:placetype":"locality",
    "wof:population":419
},
  "geometry": {"coordinates":[-100.5925,20.04612],"type":"Point"}
}