{
  "type": "Feature",
  "properties": {
    "gn:admin1_code":"11.0",
    "gn:admin2_code":"19.0",
    "gn:asciiname":"El Coporito",
    "gn:country_code":"MX",
    "gn:dem":2110,
    "gn:feature_class":"P",
    "gn:feature_code":"PPL",
    "gn:name":"El Coporito",
    "gn:population":0,
    "gn:timezone":"America/Mexico_City",
    "iso:country":"MX",
    "name:spa_x_preferred":[
        "El Coporito"
    ],
    "wof:name":"El Coporito",
    "wof:placetype":"locality"
},
  "geometry": {"coordinates":[-100.5389,20.21434],"type":"Point"}
}