{
  "type": "Feature",
  "properties": {
    "gn:admin1_code":"14",
    "gn:admin2_code":"84",
    "gn:asciiname":"La Canita",
    "gn:country_code":"MX",
    "gn:dem":285,
    "gn:feature_class":"P",
    "gn:feature_code":"PPL",
    "gn:name":"La Ca\u00f1ita",
    "gn:population":10,
    "gn:timezone":"America/Mexico_City",
    "iso:country":"MX",
    "name:und_x_variant":[
        "La Ca\u00f1ita"
    ],
    "wof:name":"La Canita",
    "wof:placetype":"locality",
    "wof:population":10
},
  "geometry": {"coordinates":[-105.005,20.13528],"type":"Point"}
}