{
  "type": "Feature",
  "properties": {
    "gn:admin1_code":"6",
    "gn:admin2_code":"29.0",
    "gn:asciiname":"El Canon",
    "gn:country_code":"MX",
    "gn:dem":1404,
    "gn:feature_class":"P",
    "gn:feature_code":"PPL",
    "gn:name":"El Ca\u00f1\u00f3n",
    "gn:population":4,
    "gn:timezone":"America/Chihuahua",
    "iso:country":"MX",
    "name:und_x_variant":[
        "El Ca\u00f1\u00f3n"
    ],
    "wof:name":"El Canon",
    "wof:placetype":"locality",
    "wof:population":4
},
  "geometry": {"coordinates":[-107.46375999999999,26.43911],"type":"Point"}
}