{
  "type": "Feature",
  "properties": {
    "gn:admin1_code":"4",
    "gn:admin2_code":"3.0",
    "gn:asciiname":"Bahamita [Jaibera]",
    "gn:country_code":"MX",
    "gn:dem":5,
    "gn:feature_class":"P",
    "gn:feature_code":"PPL",
    "gn:name":"Bahamita [Jaibera]",
    "gn:population":5,
    "gn:timezone":"America/Merida",
    "iso:country":"MX",
    "wof:name":"Bahamita [Jaibera]",
    "wof:placetype":"locality",
    "wof:population":5
},
  "geometry": {"coordinates":[-91.69750000000001,18.69972000000001],"type":"Point"}
}