{
  "type": "Feature",
  "properties": {
    "gn:admin1_code":"11.0",
    "gn:admin2_code":"4.0",
    "gn:asciiname":"El Salto de Espejo",
    "gn:country_code":"MX",
    "gn:dem":2012,
    "gn:feature_class":"P",
    "gn:feature_code":"PPL",
    "gn:name":"El Salto de Espejo",
    "gn:population":1052,
    "gn:timezone":"America/Mexico_City",
    "iso:country":"MX",
    "name:spa_x_preferred":[
        "El Salto de Espejo"
    ],
    "wof:name":"El Salto de Espejo",
    "wof:placetype":"locality",
    "wof:population":1052
},
  "geometry": {"coordinates":[-100.50587,20.45045],"type":"Point"}
}