{
  "type": "Feature",
  "properties": {
    "gn:admin1_code":"32",
    "gn:admin2_code":"5",
    "gn:asciiname":"Rancho de Jarillas",
    "gn:country_code":"MX",
    "gn:dem":2112,
    "gn:feature_class":"P",
    "gn:feature_code":"PPL",
    "gn:name":"Rancho de Jarillas",
    "gn:population":18,
    "gn:timezone":"America/Mexico_City",
    "iso:country":"MX",
    "wof:name":"Rancho de Jarillas",
    "wof:placetype":"locality",
    "wof:population":18
},
  "geometry": {"coordinates":[-102.63444,23.02056],"type":"Point"}
}