{
  "type": "Feature",
  "properties": {
    "gn:admin1_code":"11",
    "gn:admin2_code":"26",
    "gn:asciiname":"Buenavista de San Francisco",
    "gn:country_code":"MX",
    "gn:dem":1764,
    "gn:feature_class":"P",
    "gn:feature_code":"PPL",
    "gn:name":"Buenavista de San Francisco",
    "gn:population":22,
    "gn:timezone":"America/Mexico_City",
    "iso:country":"MX",
    "wof:name":"Buenavista de San Francisco",
    "wof:placetype":"locality",
    "wof:population":22
},
  "geometry": {"coordinates":[-101.63306,20.81583],"type":"Point"}
}