{
  "type": "Feature",
  "properties": {
    "gn:admin1_code":"26.0",
    "gn:admin2_code":"30.0",
    "gn:asciiname":"La Puntada",
    "gn:country_code":"MX",
    "gn:dem":125,
    "gn:feature_class":"P",
    "gn:feature_code":"PPL",
    "gn:name":"La Puntada",
    "gn:population":0,
    "gn:timezone":"America/Hermosillo",
    "iso:country":"MX",
    "name:spa_x_preferred":[
        "La Puntada"
    ],
    "wof:name":"La Puntada",
    "wof:placetype":"locality"
},
  "geometry": {"coordinates":[-111.18718,28.90595],"type":"Point"}
}