{
  "type": "Feature",
  "properties": {
    "gn:admin1_code":"30",
    "gn:admin2_code":"164",
    "gn:asciiname":"Paso del Obispo",
    "gn:country_code":"MX",
    "gn:dem":1383,
    "gn:feature_class":"P",
    "gn:feature_code":"PPL",
    "gn:name":"Paso del Obispo",
    "gn:population":16,
    "gn:timezone":"America/Mexico_City",
    "iso:country":"MX",
    "wof:name":"Paso del Obispo",
    "wof:placetype":"locality",
    "wof:population":16
},
  "geometry": {"coordinates":[-97.02388999999999,19.38694],"type":"Point"}
}