{
  "type": "Feature",
  "properties": {
    "gn:admin1_code":"28",
    "gn:admin2_code":"43.0",
    "gn:asciiname":"La Piedra",
    "gn:country_code":"MX",
    "gn:dem":108,
    "gn:feature_class":"P",
    "gn:feature_code":"PPL",
    "gn:name":"La Piedra",
    "gn:population":0,
    "gn:timezone":"America/Monterrey",
    "iso:country":"MX",
    "wof:name":"La Piedra",
    "wof:placetype":"locality"
},
  "geometry": {"coordinates":[-98.88333,23.01667],"type":"Point"}
}