{
  "type": "Feature",
  "properties": {
    "gn:admin1_code":"6",
    "gn:admin2_code":"46.0",
    "gn:asciiname":"Rancheria La Brea",
    "gn:country_code":"MX",
    "gn:dem":1893,
    "gn:feature_class":"P",
    "gn:feature_code":"PPL",
    "gn:name":"Rancher\u00eda La Brea",
    "gn:population":0,
    "gn:timezone":"America/Mazatlan",
    "iso:country":"MX",
    "name:spa_x_preferred":[
        "Rancher\u00eda La Brea"
    ],
    "wof:name":"Rancheria La Brea",
    "wof:placetype":"locality"
},
  "geometry": {"coordinates":[-107.93155,26.69708],"type":"Point"}
}