{
  "type": "Feature",
  "properties": {
    "gn:admin1_code":"15",
    "gn:admin2_code":"72.0",
    "gn:asciiname":"Ex-Hacienda Santiaguito",
    "gn:country_code":"MX",
    "gn:dem":2592,
    "gn:feature_class":"P",
    "gn:feature_code":"PPL",
    "gn:name":"Ex-Hacienda Santiaguito",
    "gn:population":511,
    "gn:timezone":"America/Mexico_City",
    "iso:country":"MX",
    "wof:name":"Ex-Hacienda Santiaguito",
    "wof:placetype":"locality",
    "wof:population":511
},
  "geometry": {"coordinates":[-99.57639,19.12472],"type":"Point"}
}