{
  "type": "Feature",
  "properties": {
    "gn:admin1_code":"27",
    "gn:admin2_code":"13.0",
    "gn:asciiname":"La Libertad",
    "gn:country_code":"MX",
    "gn:dem":7,
    "gn:feature_class":"P",
    "gn:feature_code":"PPL",
    "gn:name":"La Libertad",
    "gn:population":0,
    "gn:timezone":"America/Mexico_City",
    "iso:country":"MX",
    "name:ceb_x_preferred":[
        "La Libertad"
    ],
    "name:deu_x_preferred":[
        "La Libertad"
    ],
    "name:ell_x_preferred":[
        "\u039b\u03b1 \u039b\u03b9\u03bc\u03c0\u03b5\u03c1\u03c4\u03ac\u03b4"
    ],
    "name:epo_x_preferred":[
        "La Libertad"
    ],
    "name:fra_x_preferred":[
        "La Libertad"
    ],
    "name:glg_x_preferred":[
        "La Libertad"
    ],
    "name:ita_x_preferred":[
        "La Libertad"
    ],
    "name:kor_x_preferred":[
        "\ub77c\ub9ac\ubca0\ub974\ud0c0\ub4dc"
    ],
    "name:lit_x_preferred":[
        "La Libertadas"
    ],
    "name:nds_x_preferred":[
        "La Libertad"
    ],
    "name:nld_x_preferred":[
        "La Libertad"
    ],
    "name:pol_x_preferred":[
        "La Libertad"
    ],
    "name:por_x_preferred":[
        "La Libertad"
    ],
    "name:que_x_preferred":[
        "La Libertad"
    ],
    "name:rus_x_preferred":[
        "\u041b\u0430-\u041b\u0438\u0431\u0435\u0440\u0442\u0430\u0434"
    ],
    "name:sco_x_preferred":[
        "La Libertad"
    ],
    "name:spa_x_preferred":[
        "La Libertad"
    ],
    "name:srp_x_preferred":[
        "\u041b\u0430 \u041b\u0438\u0431\u0435\u0440\u0442\u0430\u0434"
    ],
    "name:swe_x_preferred":[
        "La Libertad"
    ],
    "name:ukr_x_preferred":[
        "\u041b\u0430-\u041b\u0456\u0431\u0435\u0440\u0442\u0430\u0434"
    ],
    "name:war_x_preferred":[
        "La Libertad"
    ],
    "wof:name":"La Libertad",
    "wof:placetype":"locality"
},
  "geometry": {"coordinates":[-92.95041999999999,18.02465],"type":"Point"}
}