{
  "type": "Feature",
  "properties": {
    "gn:admin1_code":"30",
    "gn:admin2_code":"152",
    "gn:asciiname":"Rancho Topila",
    "gn:country_code":"MX",
    "gn:dem":41,
    "gn:feature_class":"P",
    "gn:feature_code":"PPL",
    "gn:name":"Rancho Topila",
    "gn:population":23,
    "gn:timezone":"America/Mexico_City",
    "iso:country":"MX",
    "wof:name":"Rancho Topila",
    "wof:placetype":"locality",
    "wof:population":23
},
  "geometry": {"coordinates":[-97.97638999999999,22.09583],"type":"Point"}
}