{
  "type": "Feature",
  "properties": {
    "gn:admin1_code":"14",
    "gn:admin2_code":"22.0",
    "gn:asciiname":"Rancho la Esmeralda (Lo de Cuevas)",
    "gn:country_code":"MX",
    "gn:dem":14,
    "gn:feature_class":"P",
    "gn:feature_code":"PPL",
    "gn:name":"Rancho la Esmeralda (Lo de Cuevas)",
    "gn:population":5,
    "gn:timezone":"America/Mexico_City",
    "iso:country":"MX",
    "wof:name":"Rancho la Esmeralda (Lo de Cuevas)",
    "wof:placetype":"locality",
    "wof:population":5
},
  "geometry": {"coordinates":[-104.57944000000001,19.19222],"type":"Point"}
}