{
  "type": "Feature",
  "properties": {
    "gn:admin1_code":"7",
    "gn:admin2_code":"7.0",
    "gn:asciiname":"La Hoz",
    "gn:country_code":"MX",
    "gn:dem":724,
    "gn:feature_class":"P",
    "gn:feature_code":"PPL",
    "gn:name":"La Hoz",
    "gn:population":0,
    "gn:timezone":"America/Monterrey",
    "iso:country":"MX",
    "name:spa_x_preferred":[
        "La Hoz"
    ],
    "wof:name":"La Hoz",
    "wof:placetype":"locality"
},
  "geometry": {"coordinates":[-102.05163,26.96549000000001],"type":"Point"}
}