{
  "type": "Feature",
  "properties": {
    "gn:admin1_code":"28.0",
    "gn:admin2_code":"21.0",
    "gn:asciiname":"Arroyo del Nopal",
    "gn:country_code":"MX",
    "gn:dem":95,
    "gn:feature_class":"P",
    "gn:feature_code":"PPL",
    "gn:name":"Arroyo del Nopal",
    "gn:population":10,
    "gn:timezone":"America/Monterrey",
    "iso:country":"MX",
    "name:spa_x_preferred":[
        "Arroyo del Nopal"
    ],
    "wof:name":"Arroyo del Nopal",
    "wof:placetype":"locality",
    "wof:population":10
},
  "geometry": {"coordinates":[-98.94306,22.65139],"type":"Point"}
}