{
  "type": "Feature",
  "properties": {
    "gn:admin1_code":"7.0",
    "gn:admin2_code":"18.0",
    "gn:asciiname":"Ejido El Oro",
    "gn:country_code":"MX",
    "gn:dem":615,
    "gn:feature_class":"P",
    "gn:feature_code":"PPL",
    "gn:name":"Ejido El Oro",
    "gn:population":0,
    "gn:timezone":"America/Monterrey",
    "iso:country":"MX",
    "wof:name":"Ejido El Oro",
    "wof:placetype":"locality"
},
  "geometry": {"coordinates":[-101.28333000000001,26.91667],"type":"Point"}
}