{
  "type": "Feature",
  "properties": {
    "gn:admin1_code":"30",
    "gn:admin2_code":"152",
    "gn:asciiname":"Una de Gato",
    "gn:country_code":"MX",
    "gn:dem":20,
    "gn:feature_class":"P",
    "gn:feature_code":"PPL",
    "gn:name":"U\u00f1a de Gato",
    "gn:population":11,
    "gn:timezone":"America/Mexico_City",
    "iso:country":"MX",
    "name:und_x_variant":[
        "U\u00f1a de Gato"
    ],
    "wof:name":"Una de Gato",
    "wof:placetype":"locality",
    "wof:population":11
},
  "geometry": {"coordinates":[-97.90416999999999,22.00167],"type":"Point"}
}