{
  "type": "Feature",
  "properties": {
    "gn:admin1_code":"21",
    "gn:admin2_code":"25.0",
    "gn:asciiname":"Nanacatepec",
    "gn:country_code":"MX",
    "gn:dem":400,
    "gn:feature_class":"P",
    "gn:feature_code":"PPL",
    "gn:name":"Nanacatepec",
    "gn:population":238,
    "gn:timezone":"America/Mexico_City",
    "iso:country":"MX",
    "wof:name":"Nanacatepec",
    "wof:placetype":"locality",
    "wof:population":238
},
  "geometry": {"coordinates":[-97.38391,20.03316],"type":"Point"}
}