{
  "type": "Feature",
  "properties": {
    "gn:admin1_code":"14.0",
    "gn:admin2_code":"115.0",
    "gn:asciiname":"Rancho del Guayabo",
    "gn:country_code":"MX",
    "gn:dem":1120,
    "gn:feature_class":"P",
    "gn:feature_code":"PPL",
    "gn:name":"Rancho del Guayabo",
    "gn:population":0,
    "gn:timezone":"America/Mexico_City",
    "iso:country":"MX",
    "name:spa_x_preferred":[
        "Rancho del Guayabo"
    ],
    "wof:name":"Rancho del Guayabo",
    "wof:placetype":"locality"
},
  "geometry": {"coordinates":[-103.72387000000001,22.02887],"type":"Point"}
}