{
  "type": "Feature",
  "properties": {
    "gn:admin1_code":"30",
    "gn:admin2_code":"121.0",
    "gn:asciiname":"El Sacrificio",
    "gn:country_code":"MX",
    "gn:dem":43,
    "gn:feature_class":"P",
    "gn:feature_code":"PPL",
    "gn:name":"El Sacrificio",
    "gn:population":6,
    "gn:timezone":"America/Mexico_City",
    "iso:country":"MX",
    "wof:name":"El Sacrificio",
    "wof:placetype":"locality",
    "wof:population":6
},
  "geometry": {"coordinates":[-97.95471999999999,21.82611],"type":"Point"}
}