{
  "type": "Feature",
  "properties": {
    "gn:admin1_code":"5.0",
    "gn:asciiname":"Tres Poblados",
    "gn:country_code":"MX",
    "gn:dem":186,
    "gn:feature_class":"P",
    "gn:feature_code":"PPL",
    "gn:name":"Tres Poblados",
    "gn:population":0,
    "gn:timezone":"America/Mexico_City",
    "iso:country":"MX",
    "name:spa_x_preferred":[
        "Tres Poblados"
    ],
    "wof:name":"Tres Poblados",
    "wof:placetype":"locality"
},
  "geometry": {"coordinates":[-93.54402,15.94303],"type":"Point"}
}