{
  "type": "Feature",
  "properties": {
    "gn:admin1_code":"10",
    "gn:admin2_code":"14.0",
    "gn:asciiname":"El Madrono",
    "gn:country_code":"MX",
    "gn:dem":2446,
    "gn:feature_class":"P",
    "gn:feature_code":"PPL",
    "gn:name":"El Madro\u00f1o",
    "gn:population":7,
    "gn:timezone":"America/Monterrey",
    "iso:country":"MX",
    "name:und_x_variant":[
        "El Madro\u00f1o"
    ],
    "wof:name":"El Madrono",
    "wof:placetype":"locality",
    "wof:population":7
},
  "geometry": {"coordinates":[-104.68414,23.0642],"type":"Point"}
}