{
  "type": "Feature",
  "properties": {
    "gn:admin1_code":"1.0",
    "gn:admin2_code":"7.0",
    "gn:asciiname":"Las Anejas",
    "gn:country_code":"MX",
    "gn:dem":2085,
    "gn:feature_class":"P",
    "gn:feature_code":"PPL",
    "gn:name":"Las A\u00f1ejas",
    "gn:population":0,
    "gn:timezone":"America/Mexico_City",
    "iso:country":"MX",
    "name:spa_x_preferred":[
        "Las A\u00f1ejas"
    ],
    "wof:name":"Las Anejas",
    "wof:placetype":"locality"
},
  "geometry": {"coordinates":[-102.34898,22.29207],"type":"Point"}
}