{
  "type": "Feature",
  "properties": {
    "gn:gn_country":"MX",
    "gn:gn_fcode":"PPL",
    "gn:gn_pop":6522,
    "gn:population":6522,
    "iso:country":"MX",
    "name:spa_x_preferred":[
        "Villa Terrazas"
    ],
    "name:unk_x_variant":[
        "Axtla"
    ],
    "qs_pg:aaroncc":"MX",
    "qs_pg:gn_country":"MX",
    "qs_pg:gn_fcode":"PPL",
    "qs_pg:gn_pop":6522,
    "qs_pg:name":"Alfredo M. Terrazas",
    "qs_pg:name_adm0":"M\u00e9xico",
    "qs_pg:name_adm1":"San Luis Potosi",
    "qs_pg:photos_9k":1,
    "qs_pg:photos_9r":1,
    "qs_pg:photos_all":16,
    "qs_pg:photos_sr":0,
    "qs_pg:pop_sr":5,
    "qs_pg:qs_pg_placetype":"locality",
    "qs_pg:qs_pg_placetype_gp":"Town",
    "qs_pg:woe_adm0":23424900,
    "woe:adm0_id":23424900,
    "woe:name_adm0":"M\u00e9xico",
    "woe:name_adm1":"San Luis Potosi",
    "woe:placetype":"Town",
    "wof:name":"Alfredo M. Terrazas",
    "wof:placetype":"locality",
    "wof:population":6522
},
  "geometry": {"coordinates":[-98.87581,21.43916],"type":"Point"}
}