{
  "type": "Feature",
  "properties": {
    "gn:admin1_code":"6",
    "gn:admin2_code":"29",
    "gn:asciiname":"El Yerbanis",
    "gn:country_code":"MX",
    "gn:dem":2152,
    "gn:feature_class":"P",
    "gn:feature_code":"PPL",
    "gn:name":"El Yerban\u00eds",
    "gn:population":9,
    "gn:timezone":"America/Chihuahua",
    "iso:country":"MX",
    "name:und_x_variant":[
        "El Yerban\u00eds"
    ],
    "wof:name":"El Yerbanis",
    "wof:placetype":"locality",
    "wof:population":9
},
  "geometry": {"coordinates":[-106.90264000000001,26.2794],"type":"Point"}
}