{
  "type": "Feature",
  "properties": {
    "gn:admin1_code":"5",
    "gn:admin2_code":"64.0",
    "gn:asciiname":"Lelenchij",
    "gn:country_code":"MX",
    "gn:dem":2027,
    "gn:feature_class":"P",
    "gn:feature_code":"PPL",
    "gn:name":"Lelenchij",
    "gn:population":807,
    "gn:timezone":"America/Mexico_City",
    "iso:country":"MX",
    "wof:name":"Lelenchij",
    "wof:placetype":"locality",
    "wof:population":807
},
  "geometry": {"coordinates":[-92.41167,16.84],"type":"Point"}
}