{
  "type": "Feature",
  "properties": {
    "gn:admin1_code":"30.0",
    "gn:admin2_code":"123.0",
    "gn:asciiname":"Chapacao",
    "gn:country_code":"MX",
    "gn:dem":21,
    "gn:feature_class":"P",
    "gn:feature_code":"PPL",
    "gn:name":"Chapacao",
    "gn:population":0,
    "gn:timezone":"America/Mexico_City",
    "iso:country":"MX",
    "name:spa_x_preferred":[
        "Chapacao"
    ],
    "wof:name":"Chapacao",
    "wof:placetype":"locality"
},
  "geometry": {"coordinates":[-98.37578000000001,22.35723],"type":"Point"}
}