{
  "type": "Feature",
  "properties": {
    "gn:admin1_code":"6.0",
    "gn:admin2_code":"19.0",
    "gn:asciiname":"El Silencio",
    "gn:country_code":"MX",
    "gn:dem":1503,
    "gn:feature_class":"P",
    "gn:feature_code":"PPL",
    "gn:name":"El Silencio",
    "gn:population":0,
    "gn:timezone":"America/Chihuahua",
    "iso:country":"MX",
    "name:spa_x_preferred":[
        "El Silencio"
    ],
    "wof:name":"El Silencio",
    "wof:placetype":"locality"
},
  "geometry": {"coordinates":[-105.93162,28.45134],"type":"Point"}
}