{
  "type": "Feature",
  "properties": {
    "gn:admin1_code":"26.0",
    "gn:admin2_code":"46.0",
    "gn:asciiname":"Santa Eduwiges",
    "gn:country_code":"MX",
    "gn:dem":464,
    "gn:feature_class":"P",
    "gn:feature_code":"PPL",
    "gn:name":"Santa Eduwiges",
    "gn:population":0,
    "gn:timezone":"America/Hermosillo",
    "iso:country":"MX",
    "name:spa_x_preferred":[
        "Santa Eduwiges"
    ],
    "wof:name":"Santa Eduwiges",
    "wof:placetype":"locality"
},
  "geometry": {"coordinates":[-111.76312,30.73849],"type":"Point"}
}