{
  "type": "Feature",
  "properties": {
    "gn:admin1_code":"30",
    "gn:admin2_code":"172.0",
    "gn:asciiname":"Zacatal",
    "gn:country_code":"MX",
    "gn:dem":31,
    "gn:feature_class":"P",
    "gn:feature_code":"PPL",
    "gn:name":"Zacatal",
    "gn:population":61,
    "gn:timezone":"America/Mexico_City",
    "iso:country":"MX",
    "wof:name":"Zacatal",
    "wof:placetype":"locality",
    "wof:population":61
},
  "geometry": {"coordinates":[-94.85056,17.81222],"type":"Point"}
}