{
  "type": "Feature",
  "properties": {
    "gn:admin1_code":"1.0",
    "gn:admin2_code":"1.0",
    "gn:asciiname":"El Dominado (El Relicario)",
    "gn:country_code":"MX",
    "gn:dem":1973,
    "gn:feature_class":"P",
    "gn:feature_code":"PPL",
    "gn:name":"El Dominado (El Relicario)",
    "gn:population":111,
    "gn:timezone":"America/Mexico_City",
    "iso:country":"MX",
    "wof:name":"El Dominado (El Relicario)",
    "wof:placetype":"locality",
    "wof:population":111
},
  "geometry": {"coordinates":[-102.21778,21.83861],"type":"Point"}
}