{
  "type": "Feature",
  "properties": {
    "gn:admin1_code":"10.0",
    "gn:admin2_code":"9.0",
    "gn:asciiname":"La Labor de San Javier",
    "gn:country_code":"MX",
    "gn:dem":1946,
    "gn:feature_class":"P",
    "gn:feature_code":"PPL",
    "gn:name":"La Labor de San Javier",
    "gn:population":0,
    "gn:timezone":"America/Monterrey",
    "iso:country":"MX",
    "name:und_x_variant":[
        "Labor",
        "La Labor de San Javier",
        "La Labor"
    ],
    "wof:name":"La Labor de San Javier",
    "wof:placetype":"locality"
},
  "geometry": {"coordinates":[-105.828,25.85826],"type":"Point"}
}