{
  "type": "Feature",
  "properties": {
    "gn:admin1_code":"16",
    "gn:admin2_code":"97",
    "gn:asciiname":"Agua Fria",
    "gn:country_code":"MX",
    "gn:dem":824,
    "gn:feature_class":"P",
    "gn:feature_code":"PPL",
    "gn:name":"Agua Fr\u00eda",
    "gn:population":31,
    "gn:timezone":"America/Mexico_City",
    "iso:country":"MX",
    "name:und_x_variant":[
        "Agua Fr\u00eda"
    ],
    "wof:name":"Agua Fria",
    "wof:placetype":"locality",
    "wof:population":31
},
  "geometry": {"coordinates":[-101.51667,18.97361],"type":"Point"}
}