{
  "type": "Feature",
  "properties": {
    "gn:admin1_code":"6",
    "gn:admin2_code":"63.0",
    "gn:asciiname":"El Atravesado",
    "gn:country_code":"MX",
    "gn:dem":1931,
    "gn:feature_class":"P",
    "gn:feature_code":"PPL",
    "gn:name":"El Atravesado",
    "gn:population":0,
    "gn:timezone":"America/Chihuahua",
    "iso:country":"MX",
    "name:spa_x_preferred":[
        "El Atravesado"
    ],
    "wof:name":"El Atravesado",
    "wof:placetype":"locality"
},
  "geometry": {"coordinates":[-108.03091999999999,28.58553],"type":"Point"}
}