{
  "type": "Feature",
  "properties": {
    "gn:admin1_code":"27",
    "gn:admin2_code":"8.0",
    "gn:asciiname":"Zapotal 3ra. Seccion (El Corchal)",
    "gn:country_code":"MX",
    "gn:dem":12,
    "gn:feature_class":"P",
    "gn:feature_code":"PPL",
    "gn:name":"Zapotal 3ra. Secci\u00f3n (El Corchal)",
    "gn:population":418,
    "gn:timezone":"America/Mexico_City",
    "iso:country":"MX",
    "name:und_x_variant":[
        "Zapotal 3ra. Secci\u00f3n (El Corchal)"
    ],
    "wof:name":"Zapotal 3ra. Seccion (El Corchal)",
    "wof:placetype":"locality",
    "wof:population":418
},
  "geometry": {"coordinates":[-93.73361,18.04833],"type":"Point"}
}