{
  "type": "Feature",
  "properties": {
    "gn:admin1_code":"26",
    "gn:admin2_code":"18.0",
    "gn:asciiname":"Cuadrilatero Noveno",
    "gn:country_code":"MX",
    "gn:dem":30,
    "gn:feature_class":"P",
    "gn:feature_code":"PPL",
    "gn:name":"Cuadrilatero Noveno",
    "gn:population":6,
    "gn:timezone":"America/Hermosillo",
    "iso:country":"MX",
    "wof:name":"Cuadrilatero Noveno",
    "wof:placetype":"locality",
    "wof:population":6
},
  "geometry": {"coordinates":[-109.98056,27.56778],"type":"Point"}
}