{
  "type": "Feature",
  "properties": {
    "gn:admin1_code":"4",
    "gn:admin2_code":"4.0",
    "gn:asciiname":"San Antonio Yacasay",
    "gn:country_code":"MX",
    "gn:dem":59,
    "gn:feature_class":"P",
    "gn:feature_code":"PPL",
    "gn:name":"San Antonio Yacasay",
    "gn:population":0,
    "gn:timezone":"America/Merida",
    "iso:country":"MX",
    "wof:name":"San Antonio Yacasay",
    "wof:placetype":"locality"
},
  "geometry": {"coordinates":[-90.40000000000001,19.15],"type":"Point"}
}