{
  "type": "Feature",
  "properties": {
    "gn:admin1_code":"6",
    "gn:admin2_code":"27.0",
    "gn:asciiname":"Molirabo",
    "gn:country_code":"MX",
    "gn:dem":2112,
    "gn:feature_class":"P",
    "gn:feature_code":"PPL",
    "gn:name":"Molirabo",
    "gn:population":5,
    "gn:timezone":"America/Chihuahua",
    "iso:country":"MX",
    "wof:name":"Molirabo",
    "wof:placetype":"locality",
    "wof:population":5
},
  "geometry": {"coordinates":[-107.55768999999999,27.45242],"type":"Point"}
}