{
  "type": "Feature",
  "properties": {
    "gn:admin1_code":"14.0",
    "gn:admin2_code":"15.0",
    "gn:asciiname":"La Piedrera",
    "gn:country_code":"MX",
    "gn:dem":948,
    "gn:feature_class":"P",
    "gn:feature_code":"PPL",
    "gn:name":"La Piedrera",
    "gn:population":0,
    "gn:timezone":"America/Mexico_City",
    "iso:country":"MX",
    "name:spa_x_preferred":[
        "La Piedrera"
    ],
    "wof:name":"La Piedrera",
    "wof:placetype":"locality"
},
  "geometry": {"coordinates":[-104.29904999999999,19.84365],"type":"Point"}
}