{
  "type": "Feature",
  "properties": {
    "gn:admin1_code":"28",
    "gn:admin2_code":"2.0",
    "gn:asciiname":"El Dorado",
    "gn:country_code":"MX",
    "gn:dem":202,
    "gn:feature_class":"P",
    "gn:feature_code":"PPL",
    "gn:name":"El Dorado",
    "gn:population":5,
    "gn:timezone":"America/Monterrey",
    "iso:country":"MX",
    "wof:name":"El Dorado",
    "wof:placetype":"locality",
    "wof:population":5
},
  "geometry": {"coordinates":[-97.91278,22.99639],"type":"Point"}
}