{
  "type": "Feature",
  "properties": {
    "gn:admin1_code":"30",
    "gn:admin2_code":"21.0",
    "gn:asciiname":"La Angostura",
    "gn:country_code":"MX",
    "gn:dem":523,
    "gn:feature_class":"P",
    "gn:feature_code":"PPL",
    "gn:name":"La Angostura",
    "gn:population":335,
    "gn:timezone":"America/Mexico_City",
    "iso:country":"MX",
    "wof:name":"La Angostura",
    "wof:placetype":"locality",
    "wof:population":335
},
  "geometry": {"coordinates":[-96.79722,18.89833],"type":"Point"}
}