{
  "type": "Feature",
  "properties": {
    "gn:admin1_code":"20",
    "gn:admin2_code":"302.0",
    "gn:asciiname":"Zapote Blanco",
    "gn:country_code":"MX",
    "gn:dem":523,
    "gn:feature_class":"P",
    "gn:feature_code":"PPL",
    "gn:name":"Zapote Blanco",
    "gn:population":0,
    "gn:timezone":"America/Mexico_City",
    "iso:country":"MX",
    "name:spa_x_preferred":[
        "Zapote Blanco"
    ],
    "wof:name":"Zapote Blanco",
    "wof:placetype":"locality"
},
  "geometry": {"coordinates":[-97.96720999999999,16.54252],"type":"Point"}
}