{
  "type": "Feature",
  "properties": {
    "gn:admin1_code":"13",
    "gn:admin2_code":"36.0",
    "gn:asciiname":"El Banco",
    "gn:country_code":"MX",
    "gn:dem":1872,
    "gn:feature_class":"P",
    "gn:feature_code":"PPL",
    "gn:name":"El Banco",
    "gn:population":22,
    "gn:timezone":"America/Mexico_City",
    "iso:country":"MX",
    "name:spa_x_preferred":[
        "El Banco"
    ],
    "wof:name":"El Banco",
    "wof:placetype":"locality",
    "wof:population":22
},
  "geometry": {"coordinates":[-98.62634,20.55892],"type":"Point"}
}