{
  "type": "Feature",
  "properties": {
    "gn:admin1_code":"13",
    "gn:admin2_code":"36.0",
    "gn:asciiname":"El Banco",
    "gn:country_code":"MX",
    "gn:dem":1872,
    "gn:feature_class":"P",
    "gn:feature_code":"PPL",
    "gn:name":"El Banco",
    "gn:population":22,
    "gn:timezone":"America/Mexico_City",
    "iso:country":"MX",
    "name:ben_x_preferred":[
        "\u098f\u09b2 \u09ac\u09cd\u09af\u09be\u0999\u09cd\u0995\u09cb"
    ],
    "name:ell_x_preferred":[
        "\u0395\u03bb \u039c\u03c0\u03ac\u03bd\u03ba\u03bf"
    ],
    "name:hin_x_preferred":[
        "\u090f\u0932 \u092c\u0948\u0902\u0915\u094b"
    ],
    "name:hun_x_preferred":[
        "El Banco"
    ],
    "name:ind_x_preferred":[
        "El Banco"
    ],
    "name:kor_x_preferred":[
        "\uc5d8 \ubc29\ucf54"
    ],
    "name:spa_x_preferred":[
        "El Banco"
    ],
    "name:tur_x_preferred":[
        "El Banco"
    ],
    "name:urd_x_preferred":[
        "\u0627\u06cc\u0644 \u0628\u0627\u0646\u06a9\u0648"
    ],
    "wof:name":"El Banco",
    "wof:placetype":"locality",
    "wof:population":22
},
  "geometry": {"coordinates":[-98.62634,20.55892],"type":"Point"}
}