{
  "type": "Feature",
  "properties": {
    "gn:admin1_code":"14.0",
    "gn:admin2_code":"49.0",
    "gn:asciiname":"Corrajelo",
    "gn:country_code":"MX",
    "gn:dem":565,
    "gn:feature_class":"P",
    "gn:feature_code":"PPL",
    "gn:name":"Corrajelo",
    "gn:population":0,
    "gn:timezone":"America/Mexico_City",
    "iso:country":"MX",
    "name:spa_x_preferred":[
        "Corrajelo"
    ],
    "wof:name":"Corrajelo",
    "wof:placetype":"locality"
},
  "geometry": {"coordinates":[-102.65349999999999,19.30257000000001],"type":"Point"}
}