{
  "type": "Feature",
  "properties": {
    "gn:admin1_code":"24",
    "gn:admin2_code":"14",
    "gn:asciiname":"Cahameli",
    "gn:country_code":"MX",
    "gn:dem":384,
    "gn:feature_class":"P",
    "gn:feature_code":"PPL",
    "gn:name":"Cahameli",
    "gn:population":32,
    "gn:timezone":"America/Mexico_City",
    "iso:country":"MX",
    "wof:name":"Cahameli",
    "wof:placetype":"locality",
    "wof:population":32
},
  "geometry": {"coordinates":[-98.93861,21.51556],"type":"Point"}
}