{
  "type": "Feature",
  "properties": {
    "gn:admin1_code":"6",
    "gn:admin2_code":"36.0",
    "gn:asciiname":"El Fresno",
    "gn:country_code":"MX",
    "gn:dem":1641,
    "gn:feature_class":"P",
    "gn:feature_code":"PPL",
    "gn:name":"El Fresno",
    "gn:population":0,
    "gn:timezone":"America/Chihuahua",
    "iso:country":"MX",
    "name:spa_x_preferred":[
        "El Fresno"
    ],
    "name:spa_x_variant":[
        "San Antonio"
    ],
    "wof:name":"El Fresno",
    "wof:placetype":"locality"
},
  "geometry": {"coordinates":[-104.58798,27.0927],"type":"Point"}
}