{
  "type": "Feature",
  "properties": {
    "gn:admin1_code":"12",
    "gn:admin2_code":"58.0",
    "gn:asciiname":"Antonio Lopez Mateos",
    "gn:country_code":"MX",
    "gn:dem":846,
    "gn:feature_class":"P",
    "gn:feature_code":"PPL",
    "gn:name":"Antonio L\u00f3pez Mateos",
    "gn:population":0,
    "gn:timezone":"America/Mexico_City",
    "iso:country":"MX",
    "wof:name":"Antonio Lopez Mateos",
    "wof:placetype":"locality"
},
  "geometry": {"coordinates":[-99.63333,18.31667],"type":"Point"}
}