{
  "type": "Feature",
  "properties": {
    "gn:admin1_code":"10",
    "gn:admin2_code":"34.0",
    "gn:asciiname":"Acatitilla",
    "gn:country_code":"MX",
    "gn:dem":444,
    "gn:feature_class":"P",
    "gn:feature_code":"PPL",
    "gn:name":"Acatitilla",
    "gn:population":0,
    "gn:timezone":"America/Monterrey",
    "iso:country":"MX",
    "name:spa_x_preferred":[
        "Acatitilla"
    ],
    "wof:name":"Acatitilla",
    "wof:placetype":"locality"
},
  "geometry": {"coordinates":[-107.04277999999999,24.9982],"type":"Point"}
}