{
  "type": "Feature",
  "properties": {
    "gn:admin1_code":"6",
    "gn:admin2_code":"66.0",
    "gn:asciiname":"La Catarina",
    "gn:country_code":"MX",
    "gn:dem":1391,
    "gn:feature_class":"P",
    "gn:feature_code":"PPL",
    "gn:name":"La Catarina",
    "gn:population":0,
    "gn:timezone":"America/Chihuahua",
    "iso:country":"MX",
    "name:spa_x_preferred":[
        "La Catarina"
    ],
    "wof:name":"La Catarina",
    "wof:placetype":"locality"
},
  "geometry": {"coordinates":[-108.44349,27.83059],"type":"Point"}
}