{
  "type": "Feature",
  "properties": {
    "gn:admin1_code":"14.0",
    "gn:admin2_code":"58.0",
    "gn:asciiname":"El Cimarron Grande",
    "gn:country_code":"MX",
    "gn:dem":1667,
    "gn:feature_class":"P",
    "gn:feature_code":"PPL",
    "gn:name":"El Cimarr\u00f3n Grande",
    "gn:population":0,
    "gn:timezone":"America/Mexico_City",
    "iso:country":"MX",
    "name:spa_x_preferred":[
        "El Cimarr\u00f3n Grande"
    ],
    "wof:name":"El Cimarron Grande",
    "wof:placetype":"locality"
},
  "geometry": {"coordinates":[-104.7689,20.6666],"type":"Point"}
}