{
  "type": "Feature",
  "properties": {
    "gn:admin1_code":"13",
    "gn:admin2_code":"41.0",
    "gn:asciiname":"Arbol Grande",
    "gn:country_code":"MX",
    "gn:dem":2009,
    "gn:feature_class":"P",
    "gn:feature_code":"PPL",
    "gn:name":"Arbol Grande",
    "gn:population":0,
    "gn:timezone":"America/Mexico_City",
    "iso:country":"MX",
    "name:spa_x_preferred":[
        "Arbol Grande"
    ],
    "wof:name":"Arbol Grande",
    "wof:placetype":"locality"
},
  "geometry": {"coordinates":[-99.17415,20.21475],"type":"Point"}
}