{
  "type": "Feature",
  "properties": {
    "gn:admin1_code":"1",
    "gn:admin2_code":"9.0",
    "gn:asciiname":"El Gato 3ra. Seccion (El Socorro)",
    "gn:country_code":"MX",
    "gn:dem":1956,
    "gn:feature_class":"P",
    "gn:feature_code":"PPL",
    "gn:name":"El Gato 3ra. Secci\u00f3n (El Socorro)",
    "gn:population":4,
    "gn:timezone":"America/Mexico_City",
    "iso:country":"MX",
    "name:und_x_variant":[
        "El Gato 3ra. Secci\u00f3n (El Socorro)"
    ],
    "wof:name":"El Gato 3ra. Seccion (El Socorro)",
    "wof:placetype":"locality",
    "wof:population":4
},
  "geometry": {"coordinates":[-102.20999999999999,22.28361],"type":"Point"}
}