{
  "type": "Feature",
  "properties": {
    "gn:admin1_code":"6",
    "gn:admin2_code":"7.0",
    "gn:asciiname":"La Laborcita",
    "gn:country_code":"MX",
    "gn:dem":2028,
    "gn:feature_class":"P",
    "gn:feature_code":"PPL",
    "gn:name":"La Laborcita",
    "gn:population":73,
    "gn:timezone":"America/Chihuahua",
    "iso:country":"MX",
    "wof:name":"La Laborcita",
    "wof:placetype":"locality",
    "wof:population":73
},
  "geometry": {"coordinates":[-106.57351,26.8682],"type":"Point"}
}