{
  "type": "Feature",
  "properties": {
    "gn:admin1_code":"12",
    "gn:admin2_code":"73",
    "gn:asciiname":"La Parotita (La Parota del Barco)",
    "gn:country_code":"MX",
    "gn:dem":480,
    "gn:feature_class":"P",
    "gn:feature_code":"PPL",
    "gn:name":"La Parotita (La Parota del Barco)",
    "gn:population":44,
    "gn:timezone":"America/Mexico_City",
    "iso:country":"MX",
    "wof:name":"La Parotita (La Parota del Barco)",
    "wof:placetype":"locality",
    "wof:population":44
},
  "geometry": {"coordinates":[-101.15616,18.40742],"type":"Point"}
}