{
  "type": "Feature",
  "properties": {
    "gn:admin1_code":"14",
    "gn:admin2_code":"19.0",
    "gn:asciiname":"Rancho el Cuero",
    "gn:country_code":"MX",
    "gn:dem":1558,
    "gn:feature_class":"P",
    "gn:feature_code":"PPL",
    "gn:name":"Rancho el Cuero",
    "gn:population":0,
    "gn:timezone":"America/Mexico_City",
    "iso:country":"MX",
    "name:spa_x_preferred":[
        "Rancho el Cuero"
    ],
    "wof:name":"Rancho el Cuero",
    "wof:placetype":"locality"
},
  "geometry": {"coordinates":[-103.98399999999999,21.82162000000001],"type":"Point"}
}