{
  "type": "Feature",
  "properties": {
    "gn:admin1_code":"6",
    "gn:admin2_code":"63.0",
    "gn:asciiname":"Recomachi",
    "gn:country_code":"MX",
    "gn:dem":1876,
    "gn:feature_class":"P",
    "gn:feature_code":"PPL",
    "gn:name":"Recomachi",
    "gn:population":4,
    "gn:timezone":"America/Chihuahua",
    "iso:country":"MX",
    "wof:name":"Recomachi",
    "wof:placetype":"locality",
    "wof:population":4
},
  "geometry": {"coordinates":[-107.82222,28.93361],"type":"Point"}
}