{
  "type": "Feature",
  "properties": {
    "gn:admin1_code":"13",
    "gn:admin2_code":"28.0",
    "gn:asciiname":"Axcaco",
    "gn:country_code":"MX",
    "gn:dem":623,
    "gn:feature_class":"P",
    "gn:feature_code":"PPL",
    "gn:name":"Axcaco",
    "gn:population":821,
    "gn:timezone":"America/Mexico_City",
    "iso:country":"MX",
    "name:spa_x_preferred":[
        "Axcaco"
    ],
    "wof:name":"Axcaco",
    "wof:placetype":"locality",
    "wof:population":821
},
  "geometry": {"coordinates":[-98.54071,21.07018],"type":"Point"}
}