{
  "type": "Feature",
  "properties": {
    "gn:admin1_code":"4",
    "gn:admin2_code":"4.0",
    "gn:asciiname":"Churyas",
    "gn:cc2":"MX",
    "gn:country_code":"MX",
    "gn:dem":-2,
    "gn:feature_class":"P",
    "gn:feature_code":"PPL",
    "gn:name":"Churyas",
    "gn:population":0,
    "gn:timezone":"America/Merida",
    "iso:country":"MX",
    "name:und_x_variant":[
        "Churijas",
        "Churyas"
    ],
    "wof:name":"Churyas",
    "wof:placetype":"locality"
},
  "geometry": {"coordinates":[-90.61667,19.51667],"type":"Point"}
}