{
  "type": "Feature",
  "properties": {
    "gn:admin1_code":"3.0",
    "gn:admin2_code":"8.0",
    "gn:asciiname":"El Cardonal",
    "gn:country_code":"MX",
    "gn:dem":120,
    "gn:feature_class":"P",
    "gn:feature_code":"PPL",
    "gn:name":"El Cardonal",
    "gn:population":2,
    "gn:timezone":"America/Mazatlan",
    "iso:country":"MX",
    "wof:name":"El Cardonal",
    "wof:placetype":"locality",
    "wof:population":2
},
  "geometry": {"coordinates":[-109.76177,23.18964],"type":"Point"}
}