{
  "type": "Feature",
  "properties": {
    "gn:admin1_code":"5",
    "gn:admin2_code":"20.0",
    "gn:asciiname":"Los Alpes",
    "gn:country_code":"MX",
    "gn:dem":619,
    "gn:feature_class":"P",
    "gn:feature_code":"PPL",
    "gn:name":"Los Alpes",
    "gn:population":5,
    "gn:timezone":"America/Mexico_City",
    "iso:country":"MX",
    "wof:name":"Los Alpes",
    "wof:placetype":"locality",
    "wof:population":5
},
  "geometry": {"coordinates":[-92.91500000000001,16.03111],"type":"Point"}
}