{
  "type": "Feature",
  "properties": {
    "gn:admin1_code":"10",
    "gn:admin2_code":"37.0",
    "gn:asciiname":"La Pasadita",
    "gn:country_code":"MX",
    "gn:dem":2182,
    "gn:feature_class":"P",
    "gn:feature_code":"PPL",
    "gn:name":"La Pasadita",
    "gn:population":6,
    "gn:timezone":"America/Monterrey",
    "iso:country":"MX",
    "wof:name":"La Pasadita",
    "wof:placetype":"locality",
    "wof:population":6
},
  "geometry": {"coordinates":[-106.68453999999998,25.21025],"type":"Point"}
}