{
  "type": "Feature",
  "properties": {
    "gn:admin1_code":"10",
    "gn:admin2_code":"5.0",
    "gn:asciiname":"Los Alamos",
    "gn:country_code":"MX",
    "gn:dem":2310,
    "gn:feature_class":"P",
    "gn:feature_code":"PPL",
    "gn:name":"Los \u00c1lamos",
    "gn:population":0,
    "gn:timezone":"America/Monterrey",
    "iso:country":"MX",
    "name:spa_x_preferred":[
        "Los \u00c1lamos"
    ],
    "wof:name":"Los Alamos",
    "wof:placetype":"locality"
},
  "geometry": {"coordinates":[-104.77187000000001,23.847],"type":"Point"}
}