{
  "type": "Feature",
  "properties": {
    "gn:admin1_code":"24.0",
    "gn:admin2_code":"51.0",
    "gn:asciiname":"Llano del Carmen",
    "gn:cc2":"MX",
    "gn:country_code":"MX",
    "gn:dem":1603,
    "gn:feature_class":"P",
    "gn:feature_code":"PPL",
    "gn:name":"Llano del Carmen",
    "gn:population":210,
    "gn:timezone":"America/Mexico_City",
    "iso:country":"MX",
    "name:und_x_variant":[
        "Carmen",
        "El Carmen"
    ],
    "wof:name":"Llano del Carmen",
    "wof:placetype":"locality",
    "wof:population":210
},
  "geometry": {"coordinates":[-100.68917,22.86],"type":"Point"}
}