{
  "type": "Feature",
  "properties": {
    "gn:admin1_code":"18.0",
    "gn:admin2_code":"7.0",
    "gn:asciiname":"Las Bateas",
    "gn:country_code":"MX",
    "gn:dem":760,
    "gn:feature_class":"P",
    "gn:feature_code":"PPL",
    "gn:name":"Las Bateas",
    "gn:population":0,
    "gn:timezone":"America/Mazatlan",
    "iso:country":"MX",
    "name:spa_x_preferred":[
        "Las Bateas"
    ],
    "wof:name":"Las Bateas",
    "wof:placetype":"locality"
},
  "geometry": {"coordinates":[-104.44190999999999,21.24799],"type":"Point"}
}