{
  "type": "Feature",
  "properties": {
    "gn:admin1_code":"12",
    "gn:admin2_code":"71.0",
    "gn:asciiname":"Plan de los Muertos",
    "gn:country_code":"MX",
    "gn:dem":291,
    "gn:feature_class":"P",
    "gn:feature_code":"PPL",
    "gn:name":"Plan de los Muertos",
    "gn:population":646,
    "gn:timezone":"America/Mexico_City",
    "iso:country":"MX",
    "wof:name":"Plan de los Muertos",
    "wof:placetype":"locality",
    "wof:population":646
},
  "geometry": {"coordinates":[-98.235,16.75556],"type":"Point"}
}