{
  "type": "Feature",
  "properties": {
    "gn:admin1_code":"6",
    "gn:admin2_code":"29.0",
    "gn:asciiname":"El Puerto de los Alamitos",
    "gn:country_code":"MX",
    "gn:dem":2693,
    "gn:feature_class":"P",
    "gn:feature_code":"PPL",
    "gn:name":"El Puerto de los Alamitos",
    "gn:population":4,
    "gn:timezone":"America/Chihuahua",
    "iso:country":"MX",
    "wof:name":"El Puerto de los Alamitos",
    "wof:placetype":"locality",
    "wof:population":4
},
  "geometry": {"coordinates":[-106.81263,26.07218],"type":"Point"}
}