{
  "type": "Feature",
  "properties": {
    "gn:admin1_code":"26",
    "gn:admin2_code":"29.0",
    "gn:asciiname":"Los Madriles",
    "gn:country_code":"MX",
    "gn:dem":10,
    "gn:feature_class":"P",
    "gn:feature_code":"PPL",
    "gn:name":"Los Madriles",
    "gn:population":6,
    "gn:timezone":"America/Hermosillo",
    "iso:country":"MX",
    "name:spa_x_preferred":[
        "Los Madriles"
    ],
    "wof:name":"Los Madriles",
    "wof:placetype":"locality",
    "wof:population":6
},
  "geometry": {"coordinates":[-110.37083,27.64083],"type":"Point"}
}