{
  "type": "Feature",
  "properties": {
    "gn:country":"MX",
    "gn:fcode":"PPL",
    "gn:population":0,
    "iso:country":"MX",
    "name:ara_x_preferred":[
        "\u0633\u0627\u0646 \u0628\u064a\u062f\u0631\u0648 \u062f\u064a \u0644\u0627\u0633 \u0643\u0648\u0644\u0648\u0646\u064a\u0627\u0633"
    ],
    "name:ell_x_preferred":[
        "\u03a3\u03b1\u03bd \u03a0\u03ad\u03b4\u03c1\u03bf \u03b4\u03b5 \u03bb\u03b1\u03c2 \u039a\u03bf\u03bb\u03bf\u03bd\u03af\u03b1\u03c2"
    ],
    "name:fas_x_preferred":[
        "\u0633\u0627\u0646 \u067e\u062f\u0631\u0648 \u062f \u0644\u0627\u0633 \u06a9\u0644\u0648\u0646\u06cc\u0627"
    ],
    "name:fra_x_preferred":[
        "San Pedro"
    ],
    "name:heb_x_preferred":[
        "\u05e1\u05df \u05e4\u05d3\u05e8\u05d5 \u05d3\u05d4 \u05dc\u05d0\u05e1 \u05e7\u05d5\u05dc\u05d5\u05e0\u05d9\u05d0\u05e1"
    ],
    "name:hin_x_preferred":[
        "\u0938\u0948\u0928 \u092a\u0947\u0921\u094d\u0930\u094b \u0921\u0947 \u0932\u093e\u0938 \u0915\u094b\u0932\u094b\u0928\u093f\u092f\u093e\u0938"
    ],
    "name:ind_x_preferred":[
        "San Pedro de las Colonias"
    ],
    "name:jpn_x_preferred":[
        "\u30b5\u30f3\u30da\u30c9\u30ed\u30c7\u30e9\u30b9\u30b3\u30ed\u30cb\u30a2\u30b9"
    ],
    "name:kor_x_preferred":[
        "\uc0b0 \ud398\ub4dc\ub85c \ub370 \ub77c\uc2a4 \ucf5c\ub85c\ub2c8\uc544\uc2a4"
    ],
    "name:pol_x_preferred":[
        "San Pedro de las Colonias"
    ],
    "name:por_x_preferred":[
        "San Pedro de las Colonias"
    ],
    "name:spa_x_preferred":[
        "San Pedro de Las Colonias"
    ],
    "name:swe_x_preferred":[
        "San Pedro de las Colonias"
    ],
    "name:tur_x_preferred":[
        "San Pedro de las Colonias"
    ],
    "name:ukr_x_preferred":[
        "\u0421\u0430\u043d-\u041f\u0435\u0434\u0440\u043e-\u0434\u0435-\u043b\u0430\u0441-\u041a\u043e\u043b\u043e\u043d\u044c\u044f\u0441"
    ],
    "name:und_x_variant":[
        "San Pedro"
    ],
    "qs_pg:aaroncc":"MX",
    "qs_pg:gn_country":"MX",
    "qs_pg:gn_fcode":"PPL",
    "qs_pg:gn_pop":0,
    "qs_pg:name":"San Pedro de las Colonias",
    "qs_pg:name_adm0":"M\u00e9xico",
    "qs_pg:name_adm1":"Coahuila de Zaragoza",
    "qs_pg:photos_9r":0,
    "qs_pg:photos_sr":0,
    "qs_pg:pop_sr":8,
    "qs_pg:qs_pg_placetype":"locality",
    "qs_pg:qs_pg_placetype_gp":"Town",
    "qs_pg:woe_adm0":23424900,
    "woe:adm0_id":23424900,
    "woe:name_adm0":"M\u00e9xico",
    "woe:name_adm1":"Coahuila de Zaragoza",
    "woe:placetype":"Town",
    "wof:name":"San Pedro de las Colonias",
    "wof:placetype":"locality"
},
  "geometry": {"coordinates":[-102.98229000000001,25.75799],"type":"Point"}
}