{
  "type": "Feature",
  "properties": {
    "gn:gn_country":"MX",
    "gn:gn_fcode":"PPL",
    "gn:gn_pop":0,
    "iso:country":"MX",
    "name:spa_x_preferred":[
        "San Pedro de Las Colonias"
    ],
    "name:unk_x_variant":[
        "San Pedro"
    ],
    "qs_pg:aaroncc":"MX",
    "qs_pg:gn_country":"MX",
    "qs_pg:gn_fcode":"PPL",
    "qs_pg:gn_pop":0,
    "qs_pg:name":"San Pedro de las Colonias",
    "qs_pg:name_adm0":"M\u00e9xico",
    "qs_pg:name_adm1":"Coahuila de Zaragoza",
    "qs_pg:photos_9r":0,
    "qs_pg:photos_sr":0,
    "qs_pg:pop_sr":8,
    "qs_pg:qs_pg_placetype":"locality",
    "qs_pg:qs_pg_placetype_gp":"Town",
    "qs_pg:woe_adm0":23424900,
    "woe:adm0_id":23424900,
    "woe:name_adm0":"M\u00e9xico",
    "woe:name_adm1":"Coahuila de Zaragoza",
    "woe:placetype":"Town",
    "wof:name":"San Pedro de las Colonias",
    "wof:placetype":"locality"
},
  "geometry": {"coordinates":[-102.98229000000001,25.75799],"type":"Point"}
}