{
  "type": "Feature",
  "properties": {
    "gn:admin1_code":"7",
    "gn:admin2_code":"38.0",
    "gn:asciiname":"Cedro Solo",
    "gn:country_code":"MX",
    "gn:dem":744,
    "gn:feature_class":"P",
    "gn:feature_code":"PPL",
    "gn:name":"Cedro Solo",
    "gn:population":5,
    "gn:timezone":"America/Monterrey",
    "iso:country":"MX",
    "wof:name":"Cedro Solo",
    "wof:placetype":"locality",
    "wof:population":5
},
  "geometry": {"coordinates":[-101.43510999999999,28.50329],"type":"Point"}
}