{
  "type": "Feature",
  "properties": {
    "gn:admin1_code":"6",
    "gn:admin2_code":"31.0",
    "gn:asciiname":"Sayagui",
    "gn:country_code":"MX",
    "gn:dem":2161,
    "gn:feature_class":"P",
    "gn:feature_code":"PPL",
    "gn:name":"Sayagui",
    "gn:population":0,
    "gn:timezone":"America/Chihuahua",
    "iso:country":"MX",
    "name:und_x_variant":[
        "Sayag\u00fce",
        "Soyage",
        "Soy\u00e1g\u00fce",
        "Sayagui"
    ],
    "wof:name":"Sayagui",
    "wof:placetype":"locality"
},
  "geometry": {"coordinates":[-107.6795,28.58359],"type":"Point"}
}