{
  "type": "Feature",
  "properties": {
    "gn:admin1_code":"28.0",
    "gn:admin2_code":"25.0",
    "gn:asciiname":"Quintrin",
    "gn:country_code":"MX",
    "gn:dem":106,
    "gn:feature_class":"P",
    "gn:feature_code":"PPL",
    "gn:name":"Quintr\u00edn",
    "gn:population":0,
    "gn:timezone":"America/Monterrey",
    "iso:country":"MX",
    "name:spa_x_preferred":[
        "Quintr\u00edn"
    ],
    "wof:name":"Quintrin",
    "wof:placetype":"locality"
},
  "geometry": {"coordinates":[-98.99475,26.25944],"type":"Point"}
}