{
  "type": "Feature",
  "properties": {
    "gn:admin1_code":"12",
    "gn:admin2_code":"22",
    "gn:asciiname":"San Francisco",
    "gn:country_code":"MX",
    "gn:dem":371,
    "gn:feature_class":"P",
    "gn:feature_code":"PPL",
    "gn:name":"San Francisco",
    "gn:population":44,
    "gn:timezone":"America/Mexico_City",
    "iso:country":"MX",
    "wof:name":"San Francisco",
    "wof:placetype":"locality",
    "wof:population":44
},
  "geometry": {"coordinates":[-100.90412999999999,18.26391],"type":"Point"}
}