{
  "type": "Feature",
  "properties": {
    "gn:admin1_code":"15.0",
    "gn:asciiname":"Tzintzimacato Chico",
    "gn:country_code":"MX",
    "gn:dem":2148,
    "gn:feature_class":"P",
    "gn:feature_code":"PPL",
    "gn:name":"Tzintzimacato Chico",
    "gn:population":0,
    "gn:timezone":"America/Mexico_City",
    "iso:country":"MX",
    "name:spa_x_preferred":[
        "Tzintzimacato Chico"
    ],
    "wof:name":"Tzintzimacato Chico",
    "wof:placetype":"locality"
},
  "geometry": {"coordinates":[-101.43724,19.78455],"type":"Point"}
}