{
  "type": "Feature",
  "properties": {
    "gn:admin1_code":"11",
    "gn:admin2_code":"3.0",
    "gn:asciiname":"Tanque Blanco",
    "gn:country_code":"MX",
    "gn:dem":2038,
    "gn:feature_class":"P",
    "gn:feature_code":"PPL",
    "gn:name":"Tanque Blanco",
    "gn:population":88,
    "gn:timezone":"America/Mexico_City",
    "iso:country":"MX",
    "wof:name":"Tanque Blanco",
    "wof:placetype":"locality",
    "wof:population":88
},
  "geometry": {"coordinates":[-100.56667,21.04778],"type":"Point"}
}