{
  "type": "Feature",
  "properties": {
    "gn:admin1_code":"16",
    "gn:admin2_code":"86.0",
    "gn:asciiname":"Tarimoro",
    "gn:country_code":"MX",
    "gn:dem":1583,
    "gn:feature_class":"P",
    "gn:feature_code":"PPL",
    "gn:name":"Tarimoro",
    "gn:population":0,
    "gn:timezone":"America/Mexico_City",
    "iso:country":"MX",
    "name:spa_x_preferred":[
        "Tarimoro"
    ],
    "wof:name":"Tarimoro",
    "wof:placetype":"locality"
},
  "geometry": {"coordinates":[-102.33548,20.23893],"type":"Point"}
}