{
  "type": "Feature",
  "properties": {
    "gn:admin1_code":"24",
    "gn:admin2_code":"33.0",
    "gn:asciiname":"Calabacillas",
    "gn:country_code":"MX",
    "gn:dem":1992,
    "gn:feature_class":"P",
    "gn:feature_code":"PPL",
    "gn:name":"Calabacillas",
    "gn:population":0,
    "gn:timezone":"America/Mexico_City",
    "iso:country":"MX",
    "name:spa_x_preferred":[
        "Calabacillas"
    ],
    "wof:name":"Calabacillas",
    "wof:placetype":"locality"
},
  "geometry": {"coordinates":[-102.09577,23.18825],"type":"Point"}
}