{
  "type": "Feature",
  "properties": {
    "gn:admin1_code":"6",
    "gn:admin2_code":"7.0",
    "gn:asciiname":"El Bano",
    "gn:country_code":"MX",
    "gn:dem":2317,
    "gn:feature_class":"P",
    "gn:feature_code":"PPL",
    "gn:name":"El Ba\u00f1o",
    "gn:population":0,
    "gn:timezone":"America/Chihuahua",
    "iso:country":"MX",
    "name:spa_x_preferred":[
        "El Ba\u00f1o"
    ],
    "wof:name":"El Bano",
    "wof:placetype":"locality"
},
  "geometry": {"coordinates":[-106.6765,27.03192],"type":"Point"}
}