{
  "type": "Feature",
  "properties": {
    "gn:admin1_code":"12",
    "gn:admin2_code":"4.0",
    "gn:asciiname":"Acametla de Bravo",
    "gn:country_code":"MX",
    "gn:dem":1912,
    "gn:feature_class":"P",
    "gn:feature_code":"PPL",
    "gn:name":"Acametla de Bravo",
    "gn:population":433,
    "gn:timezone":"America/Mexico_City",
    "iso:country":"MX",
    "wof:name":"Acametla de Bravo",
    "wof:placetype":"locality",
    "wof:population":433
},
  "geometry": {"coordinates":[-98.36111,17.38389],"type":"Point"}
}