{
  "type": "Feature",
  "properties": {
    "gn:admin1_code":"29",
    "gn:admin2_code":"3.0",
    "gn:asciiname":"Villa de las Flores",
    "gn:country_code":"MX",
    "gn:dem":2585,
    "gn:feature_class":"P",
    "gn:feature_code":"PPL",
    "gn:name":"Villa de las Flores",
    "gn:population":0,
    "gn:timezone":"America/Mexico_City",
    "iso:country":"MX",
    "name:spa_x_preferred":[
        "Villa de las Flores"
    ],
    "wof:name":"Villa de las Flores",
    "wof:placetype":"locality"
},
  "geometry": {"coordinates":[-98.11651000000001,19.50894],"type":"Point"}
}