{
  "type": "Feature",
  "properties": {
    "gn:admin1_code":"6",
    "gn:admin2_code":"12.0",
    "gn:asciiname":"Rancho los Pinos",
    "gn:country_code":"MX",
    "gn:dem":2142,
    "gn:feature_class":"P",
    "gn:feature_code":"PPL",
    "gn:name":"Rancho los Pinos",
    "gn:population":6,
    "gn:timezone":"America/Chihuahua",
    "iso:country":"MX",
    "wof:name":"Rancho los Pinos",
    "wof:placetype":"locality",
    "wof:population":6
},
  "geometry": {"coordinates":[-106.95744000000001,28.07586],"type":"Point"}
}