{
  "type": "Feature",
  "properties": {
    "gn:admin1_code":"26",
    "gn:admin2_code":"29.0",
    "gn:asciiname":"San Jose de Guaymas",
    "gn:country_code":"MX",
    "gn:dem":7,
    "gn:feature_class":"P",
    "gn:feature_code":"PPL",
    "gn:name":"San Jos\u00e9 de Guaymas",
    "gn:population":0,
    "gn:timezone":"America/Hermosillo",
    "iso:country":"MX",
    "name:spa_x_preferred":[
        "San Jos\u00e9 de Guaymas"
    ],
    "name:und_x_variant":[
        "San Jos\u00e9 Guaymas"
    ],
    "wof:name":"San Jose de Guaymas",
    "wof:placetype":"locality"
},
  "geometry": {"coordinates":[-110.88064,27.98644],"type":"Point"}
}