{
  "type": "Feature",
  "properties": {
    "gn:admin1_code":"3",
    "gn:admin2_code":"3.0",
    "gn:asciiname":"San Martin de la Redencion",
    "gn:country_code":"MX",
    "gn:dem":148,
    "gn:feature_class":"P",
    "gn:feature_code":"PPL",
    "gn:name":"San Mart\u00edn de la Redenci\u00f3n",
    "gn:population":4,
    "gn:timezone":"America/Mazatlan",
    "iso:country":"MX",
    "name:und_x_variant":[
        "San Mart\u00edn de la Redenci\u00f3n"
    ],
    "wof:name":"San Martin de la Redencion",
    "wof:placetype":"locality",
    "wof:population":4
},
  "geometry": {"coordinates":[-111.14672,24.79626],"type":"Point"}
}