{
  "type": "Feature",
  "properties": {
    "gn:admin1_code":"1",
    "gn:admin2_code":"1",
    "gn:asciiname":"Esperanza [Rancho]",
    "gn:country_code":"MX",
    "gn:dem":1899,
    "gn:feature_class":"P",
    "gn:feature_code":"PPL",
    "gn:name":"Esperanza [Rancho]",
    "gn:population":15,
    "gn:timezone":"America/Mexico_City",
    "iso:country":"MX",
    "wof:name":"Esperanza [Rancho]",
    "wof:placetype":"locality",
    "wof:population":15
},
  "geometry": {"coordinates":[-102.2625,21.77361],"type":"Point"}
}