{
  "type": "Feature",
  "properties": {
    "gn:admin1_code":"29",
    "gn:admin2_code":"12.0",
    "gn:asciiname":"Madero Viejo",
    "gn:country_code":"MX",
    "gn:dem":2737,
    "gn:feature_class":"P",
    "gn:feature_code":"PPL",
    "gn:name":"Madero Viejo",
    "gn:population":0,
    "gn:timezone":"America/Mexico_City",
    "iso:country":"MX",
    "name:spa_x_preferred":[
        "Madero Viejo"
    ],
    "wof:name":"Madero Viejo",
    "wof:placetype":"locality"
},
  "geometry": {"coordinates":[-98.48379,19.48088],"type":"Point"}
}