{
  "type": "Feature",
  "properties": {
    "gn:admin1_code":"6",
    "gn:admin2_code":"27.0",
    "gn:asciiname":"Sarabeachi",
    "gn:country_code":"MX",
    "gn:dem":2574,
    "gn:feature_class":"P",
    "gn:feature_code":"PPL",
    "gn:name":"Sarabeachi",
    "gn:population":4,
    "gn:timezone":"America/Chihuahua",
    "iso:country":"MX",
    "wof:name":"Sarabeachi",
    "wof:placetype":"locality",
    "wof:population":4
},
  "geometry": {"coordinates":[-107.05463,27.50715],"type":"Point"}
}