{
  "type": "Feature",
  "properties": {
    "gn:admin1_code":"14",
    "gn:admin2_code":"78.0",
    "gn:asciiname":"El Ramblas",
    "gn:country_code":"MX",
    "gn:dem":2168,
    "gn:feature_class":"P",
    "gn:feature_code":"PPL",
    "gn:name":"El Ramblas",
    "gn:population":86,
    "gn:timezone":"America/Mexico_City",
    "iso:country":"MX",
    "wof:name":"El Ramblas",
    "wof:placetype":"locality",
    "wof:population":86
},
  "geometry": {"coordinates":[-102.36083000000001,20.92861],"type":"Point"}
}