{
  "type": "Feature",
  "properties": {
    "gn:admin1_code":"32",
    "gn:admin2_code":"49.0",
    "gn:asciiname":"Laguna del Durazno",
    "gn:country_code":"MX",
    "gn:dem":2323,
    "gn:feature_class":"P",
    "gn:feature_code":"PPL",
    "gn:name":"Laguna del Durazno",
    "gn:population":0,
    "gn:timezone":"America/Monterrey",
    "iso:country":"MX",
    "name:spa_x_preferred":[
        "Laguna del Durazno"
    ],
    "wof:name":"Laguna del Durazno",
    "wof:placetype":"locality"
},
  "geometry": {"coordinates":[-104.26505,22.53854],"type":"Point"}
}