{
  "type": "Feature",
  "properties": {
    "gn:admin1_code":"24",
    "gn:admin2_code":"19",
    "gn:asciiname":"La Ladrillera",
    "gn:country_code":"MX",
    "gn:dem":688,
    "gn:feature_class":"P",
    "gn:feature_code":"PPL",
    "gn:name":"La Ladrillera",
    "gn:population":15,
    "gn:timezone":"America/Mexico_City",
    "iso:country":"MX",
    "wof:name":"La Ladrillera",
    "wof:placetype":"locality",
    "wof:population":15
},
  "geometry": {"coordinates":[-99.58389,21.71694],"type":"Point"}
}