{
  "type": "Feature",
  "properties": {
    "gn:admin1_code":"11",
    "gn:admin2_code":"1.0",
    "gn:asciiname":"La Brisa",
    "gn:country_code":"MX",
    "gn:dem":1707,
    "gn:feature_class":"P",
    "gn:feature_code":"PPL",
    "gn:name":"La Brisa",
    "gn:population":440,
    "gn:timezone":"America/Mexico_City",
    "iso:country":"MX",
    "wof:name":"La Brisa",
    "wof:placetype":"locality",
    "wof:population":440
},
  "geometry": {"coordinates":[-101.39221999999999,20.44111],"type":"Point"}
}