{
  "type": "Feature",
  "properties": {
    "gn:admin1_code":"22",
    "gn:admin2_code":"2.0",
    "gn:asciiname":"Huilotla",
    "gn:country_code":"MX",
    "gn:dem":1244,
    "gn:feature_class":"P",
    "gn:feature_code":"PPL",
    "gn:name":"Huilotla",
    "gn:population":337,
    "gn:timezone":"America/Mexico_City",
    "iso:country":"MX",
    "wof:name":"Huilotla",
    "wof:placetype":"locality",
    "wof:population":337
},
  "geometry": {"coordinates":[-99.58360999999999,21.25],"type":"Point"}
}