{
  "type": "Feature",
  "properties": {
    "gn:admin1_code":"10.0",
    "gn:admin2_code":"14.0",
    "gn:asciiname":"La Joyanca",
    "gn:country_code":"MX",
    "gn:dem":1082,
    "gn:feature_class":"P",
    "gn:feature_code":"PPL",
    "gn:name":"La Joyanca",
    "gn:population":0,
    "gn:timezone":"America/Monterrey",
    "iso:country":"MX",
    "name:spa_x_preferred":[
        "La Joyanca"
    ],
    "name:ukr_x_preferred":[
        "\u041b\u0430-\u0425\u043e\u044f\u043d\u043a\u0430"
    ],
    "wof:name":"La Joyanca",
    "wof:placetype":"locality"
},
  "geometry": {"coordinates":[-104.58815,22.47222],"type":"Point"}
}