{
  "type": "Feature",
  "properties": {
    "gn:admin1_code":"20",
    "gn:admin2_code":"469.0",
    "gn:asciiname":"Coyuchi",
    "gn:country_code":"MX",
    "gn:dem":1328,
    "gn:feature_class":"P",
    "gn:feature_code":"PPL",
    "gn:name":"Coyuchi",
    "gn:population":339,
    "gn:timezone":"America/Mexico_City",
    "iso:country":"MX",
    "wof:name":"Coyuchi",
    "wof:placetype":"locality",
    "wof:population":339
},
  "geometry": {"coordinates":[-97.97111,17.14972],"type":"Point"}
}