{
  "type": "Feature",
  "properties": {
    "gn:admin1_code":"30",
    "gn:admin2_code":"48",
    "gn:asciiname":"El Soriano",
    "gn:country_code":"MX",
    "gn:dem":23,
    "gn:feature_class":"P",
    "gn:feature_code":"PPL",
    "gn:name":"El Soriano",
    "gn:population":23,
    "gn:timezone":"America/Mexico_City",
    "iso:country":"MX",
    "wof:name":"El Soriano",
    "wof:placetype":"locality",
    "wof:population":23
},
  "geometry": {"coordinates":[-94.67333000000001,17.92167000000001],"type":"Point"}
}