{
  "type": "Feature",
  "properties": {
    "gn:admin1_code":"30.0",
    "gn:admin2_code":"158.0",
    "gn:asciiname":"La Yola",
    "gn:country_code":"MX",
    "gn:dem":8,
    "gn:feature_class":"P",
    "gn:feature_code":"PPL",
    "gn:name":"La Yola",
    "gn:population":0,
    "gn:timezone":"America/Mexico_City",
    "iso:country":"MX",
    "name:spa_x_preferred":[
        "La Yola"
    ],
    "wof:name":"La Yola",
    "wof:placetype":"locality"
},
  "geometry": {"coordinates":[-96.80374999999999,20.25988],"type":"Point"}
}