{
  "type": "Feature",
  "properties": {
    "gn:admin1_code":"5",
    "gn:admin2_code":"9.0",
    "gn:asciiname":"La Ceiba (San Francisco)",
    "gn:country_code":"MX",
    "gn:dem":11,
    "gn:feature_class":"P",
    "gn:feature_code":"PPL",
    "gn:name":"La Ceiba (San Francisco)",
    "gn:population":4,
    "gn:timezone":"America/Mexico_City",
    "iso:country":"MX",
    "wof:name":"La Ceiba (San Francisco)",
    "wof:placetype":"locality",
    "wof:population":4
},
  "geometry": {"coordinates":[-93.93611,16.12833],"type":"Point"}
}