{
  "type": "Feature",
  "properties": {
    "gn:admin1_code":"26",
    "gn:admin2_code":"26.0",
    "gn:asciiname":"Jorge Larraguivel",
    "gn:country_code":"MX",
    "gn:dem":22,
    "gn:feature_class":"P",
    "gn:feature_code":"PPL",
    "gn:name":"Jorge Larraguivel",
    "gn:population":6,
    "gn:timezone":"America/Hermosillo",
    "iso:country":"MX",
    "wof:name":"Jorge Larraguivel",
    "wof:placetype":"locality",
    "wof:population":6
},
  "geometry": {"coordinates":[-109.56056,26.97972],"type":"Point"}
}