{
  "type": "Feature",
  "properties": {
    "gn:admin1_code":"7.0",
    "gn:admin2_code":"2.0",
    "gn:asciiname":"Margaritas",
    "gn:country_code":"MX",
    "gn:dem":391,
    "gn:feature_class":"P",
    "gn:feature_code":"PPL",
    "gn:name":"Margaritas",
    "gn:population":0,
    "gn:timezone":"America/Matamoros",
    "iso:country":"MX",
    "name:spa_x_preferred":[
        "Margaritas"
    ],
    "wof:name":"Margaritas",
    "wof:placetype":"locality"
},
  "geometry": {"coordinates":[-101.15474,29.18452000000001],"type":"Point"}
}