{
  "type": "Feature",
  "properties": {
    "gn:admin1_code":"12",
    "gn:admin2_code":"53.0",
    "gn:asciiname":"El Amazquite",
    "gn:country_code":"MX",
    "gn:dem":9,
    "gn:feature_class":"P",
    "gn:feature_code":"PPL",
    "gn:name":"El Amazquite",
    "gn:population":0,
    "gn:timezone":"America/Mexico_City",
    "iso:country":"MX",
    "name:spa_x_preferred":[
        "El Amazquite"
    ],
    "name:und_x_variant":[
        "El Mezquite"
    ],
    "wof:name":"El Amazquite",
    "wof:placetype":"locality"
},
  "geometry": {"coordinates":[-99.39116,16.67605],"type":"Point"}
}