{
  "type": "Feature",
  "properties": {
    "gn:admin1_code":"5.0",
    "gn:admin2_code":"101.0",
    "gn:asciiname":"Josefa Garrido de Gonzalez Blanco",
    "gn:country_code":"MX",
    "gn:dem":702,
    "gn:feature_class":"P",
    "gn:feature_code":"PPL",
    "gn:name":"Josefa Garrido de Gonz\u00e1lez Blanco",
    "gn:population":0,
    "gn:timezone":"America/Mexico_City",
    "iso:country":"MX",
    "name:spa_x_preferred":[
        "Josefa Garrido de Gonz\u00e1lez Blanco"
    ],
    "wof:name":"Josefa Garrido de Gonzalez Blanco",
    "wof:placetype":"locality"
},
  "geometry": {"coordinates":[-93.12483,16.72901],"type":"Point"}
}