{
  "type": "Feature",
  "properties": {
    "gn:admin1_code":"29",
    "gn:admin2_code":"8",
    "gn:asciiname":"Ejido de Allende",
    "gn:country_code":"MX",
    "gn:dem":2584,
    "gn:feature_class":"P",
    "gn:feature_code":"PPL",
    "gn:name":"Ejido de Allende",
    "gn:population":27,
    "gn:timezone":"America/Mexico_City",
    "iso:country":"MX",
    "wof:name":"Ejido de Allende",
    "wof:placetype":"locality",
    "wof:population":27
},
  "geometry": {"coordinates":[-97.84784000000001,19.37539],"type":"Point"}
}