{
  "type": "Feature",
  "properties": {
    "gn:admin1_code":"5",
    "gn:admin2_code":"66.0",
    "gn:asciiname":"San Martin Caballero",
    "gn:country_code":"MX",
    "gn:dem":818,
    "gn:feature_class":"P",
    "gn:feature_code":"PPL",
    "gn:name":"San Mart\u00edn Caballero",
    "gn:population":136,
    "gn:timezone":"America/Mexico_City",
    "iso:country":"MX",
    "name:und_x_variant":[
        "San Mart\u00edn Caballero"
    ],
    "wof:name":"San Martin Caballero",
    "wof:placetype":"locality",
    "wof:population":136
},
  "geometry": {"coordinates":[-92.47556,17.02639],"type":"Point"}
}