{
  "type": "Feature",
  "properties": {
    "gn:admin1_code":"30",
    "gn:admin2_code":"123.0",
    "gn:asciiname":"Tabalo",
    "gn:country_code":"MX",
    "gn:dem":5,
    "gn:feature_class":"P",
    "gn:feature_code":"PPL",
    "gn:name":"Tabal\u00f3",
    "gn:population":0,
    "gn:timezone":"America/Mexico_City",
    "iso:country":"MX",
    "name:spa_x_preferred":[
        "Tabal\u00f3"
    ],
    "name:und_x_variant":[
        "Tobal\u00f3"
    ],
    "wof:name":"Tabalo",
    "wof:placetype":"locality"
},
  "geometry": {"coordinates":[-98.04388,22.10646],"type":"Point"}
}