{
  "type": "Feature",
  "properties": {
    "gn:admin1_code":"16",
    "gn:admin2_code":"87.0",
    "gn:asciiname":"El Huamil (El Guamil)",
    "gn:country_code":"MX",
    "gn:dem":1283,
    "gn:feature_class":"P",
    "gn:feature_code":"PPL",
    "gn:name":"El Huamil (El Guamil)",
    "gn:population":5,
    "gn:timezone":"America/Mexico_City",
    "iso:country":"MX",
    "wof:name":"El Huamil (El Guamil)",
    "wof:placetype":"locality",
    "wof:population":5
},
  "geometry": {"coordinates":[-101.855,19.34333],"type":"Point"}
}