{
  "type": "Feature",
  "properties": {
    "gn:admin1_code":"13",
    "gn:admin2_code":"44.0",
    "gn:asciiname":"El Tejocote",
    "gn:country_code":"MX",
    "gn:dem":2432,
    "gn:feature_class":"P",
    "gn:feature_code":"PPL",
    "gn:name":"El Tejocote",
    "gn:population":56,
    "gn:timezone":"America/Mexico_City",
    "iso:country":"MX",
    "wof:name":"El Tejocote",
    "wof:placetype":"locality",
    "wof:population":56
},
  "geometry": {"coordinates":[-99.67353,20.20137],"type":"Point"}
}