{
  "type": "Feature",
  "properties": {
    "gn:admin1_code":"26",
    "gn:admin2_code":"49.0",
    "gn:asciiname":"Los Ajos",
    "gn:country_code":"MX",
    "gn:dem":341,
    "gn:feature_class":"P",
    "gn:feature_code":"PPL",
    "gn:name":"Los Ajos",
    "gn:population":0,
    "gn:timezone":"America/Hermosillo",
    "iso:country":"MX",
    "name:spa_x_preferred":[
        "Los Ajos"
    ],
    "name:und_x_variant":[
        "Rancho Los Ajos"
    ],
    "wof:name":"Los Ajos",
    "wof:placetype":"locality"
},
  "geometry": {"coordinates":[-109.59327,27.83728],"type":"Point"}
}