{
  "type": "Feature",
  "properties": {
    "gn:admin1_code":"15.0",
    "gn:asciiname":"Barrio del Progreso",
    "gn:country_code":"MX",
    "gn:dem":2659,
    "gn:feature_class":"P",
    "gn:feature_code":"PPL",
    "gn:name":"Barrio del Progreso",
    "gn:population":0,
    "gn:timezone":"America/Mexico_City",
    "iso:country":"MX",
    "name:spa_x_preferred":[
        "Barrio del Progreso"
    ],
    "wof:name":"Barrio del Progreso",
    "wof:placetype":"locality"
},
  "geometry": {"coordinates":[-99.77267999999999,19.69906],"type":"Point"}
}