{
  "type": "Feature",
  "properties": {
    "gn:admin1_code":"5",
    "gn:admin2_code":"20.0",
    "gn:asciiname":"Las Malvinas",
    "gn:country_code":"MX",
    "gn:dem":569,
    "gn:feature_class":"P",
    "gn:feature_code":"PPL",
    "gn:name":"Las Malvinas",
    "gn:population":4,
    "gn:timezone":"America/Mexico_City",
    "iso:country":"MX",
    "wof:name":"Las Malvinas",
    "wof:placetype":"locality",
    "wof:population":4
},
  "geometry": {"coordinates":[-92.85778000000001,16.03944],"type":"Point"}
}