{
  "type": "Feature",
  "properties": {
    "gn:admin1_code":"12",
    "gn:admin2_code":"11",
    "gn:asciiname":"Arroyo Grande",
    "gn:country_code":"MX",
    "gn:dem":582,
    "gn:feature_class":"P",
    "gn:feature_code":"PPL",
    "gn:name":"Arroyo Grande",
    "gn:population":28,
    "gn:timezone":"America/Mexico_City",
    "iso:country":"MX",
    "wof:name":"Arroyo Grande",
    "wof:placetype":"locality",
    "wof:population":28
},
  "geometry": {"coordinates":[-100.23266,17.25782],"type":"Point"}
}