{
  "type": "Feature",
  "properties": {
    "gn:admin1_code":"24",
    "gn:admin2_code":"23.0",
    "gn:asciiname":"Laguna del Saucillo",
    "gn:country_code":"MX",
    "gn:dem":1114,
    "gn:feature_class":"P",
    "gn:feature_code":"PPL",
    "gn:name":"Laguna del Saucillo",
    "gn:population":0,
    "gn:timezone":"America/Mexico_City",
    "iso:country":"MX",
    "name:spa_x_preferred":[
        "Laguna del Saucillo"
    ],
    "name:und_x_variant":[
        "Saucillo"
    ],
    "wof:name":"Laguna del Saucillo",
    "wof:placetype":"locality"
},
  "geometry": {"coordinates":[-99.52084000000001,21.88909],"type":"Point"}
}