{
  "type": "Feature",
  "properties": {
    "gn:admin1_code":"12",
    "gn:admin2_code":"77.0",
    "gn:asciiname":"Colonia el Panteon",
    "gn:country_code":"MX",
    "gn:dem":38,
    "gn:feature_class":"P",
    "gn:feature_code":"PPL",
    "gn:name":"Colonia el Pante\u00f3n",
    "gn:population":53,
    "gn:timezone":"America/Mexico_City",
    "iso:country":"MX",
    "name:und_x_variant":[
        "Colonia el Pante\u00f3n"
    ],
    "wof:name":"Colonia el Panteon",
    "wof:placetype":"locality",
    "wof:population":53
},
  "geometry": {"coordinates":[-98.81028000000001,16.58917000000001],"type":"Point"}
}