{
  "type": "Feature",
  "properties": {
    "gn:admin1_code":"14",
    "gn:admin2_code":"123.0",
    "gn:asciiname":"Los Cerritos",
    "gn:country_code":"MX",
    "gn:dem":1547,
    "gn:feature_class":"P",
    "gn:feature_code":"PPL",
    "gn:name":"Los Cerritos",
    "gn:population":0,
    "gn:timezone":"America/Mexico_City",
    "iso:country":"MX",
    "wof:name":"Los Cerritos",
    "wof:placetype":"locality"
},
  "geometry": {"coordinates":[-102.77593,20.47752],"type":"Point"}
}