{
  "type": "Feature",
  "properties": {
    "gn:admin1_code":"11",
    "gn:admin2_code":"20.0",
    "gn:asciiname":"Granja Jerico",
    "gn:country_code":"MX",
    "gn:dem":1780,
    "gn:feature_class":"P",
    "gn:feature_code":"PPL",
    "gn:name":"Granja Jeric\u00f3",
    "gn:population":55,
    "gn:timezone":"America/Mexico_City",
    "iso:country":"MX",
    "name:und_x_variant":[
        "Granja Jeric\u00f3"
    ],
    "wof:name":"Granja Jerico",
    "wof:placetype":"locality",
    "wof:population":55
},
  "geometry": {"coordinates":[-101.6575,20.99333],"type":"Point"}
}