{
  "type": "Feature",
  "properties": {
    "gn:admin1_code":"6",
    "gn:admin2_code":"67.0",
    "gn:asciiname":"El Barro",
    "gn:country_code":"MX",
    "gn:dem":1521,
    "gn:feature_class":"P",
    "gn:feature_code":"PPL",
    "gn:name":"El Barro",
    "gn:population":0,
    "gn:timezone":"America/Chihuahua",
    "iso:country":"MX",
    "name:spa_x_preferred":[
        "El Barro"
    ],
    "wof:name":"El Barro",
    "wof:placetype":"locality"
},
  "geometry": {"coordinates":[-105.82323999999998,27.34745],"type":"Point"}
}