{
  "type": "Feature",
  "properties": {
    "gn:admin1_code":"27",
    "gn:admin2_code":"4.0",
    "gn:asciiname":"Playas del Rosario",
    "gn:country_code":"MX",
    "gn:dem":18,
    "gn:feature_class":"P",
    "gn:feature_code":"PPL",
    "gn:name":"Playas del Rosario",
    "gn:population":0,
    "gn:timezone":"America/Mexico_City",
    "iso:country":"MX",
    "name:spa_x_preferred":[
        "Playas del Rosario"
    ],
    "name:spa_x_variant":[
        "Garc\u00eda"
    ],
    "wof:name":"Playas del Rosario",
    "wof:placetype":"locality"
},
  "geometry": {"coordinates":[-92.93219000000001,17.85308],"type":"Point"}
}