{
  "type": "Feature",
  "properties": {
    "gn:admin1_code":"16.0",
    "gn:admin2_code":"63.0",
    "gn:asciiname":"Ranchos de Epejan",
    "gn:country_code":"MX",
    "gn:dem":1761,
    "gn:feature_class":"P",
    "gn:feature_code":"PPL",
    "gn:name":"Ranchos de Epejan",
    "gn:population":0,
    "gn:timezone":"America/Mexico_City",
    "iso:country":"MX",
    "name:spa_x_preferred":[
        "Ranchos de Epejan"
    ],
    "name:spa_x_variant":[
        "La Loma"
    ],
    "name:und_x_variant":[
        "Ranchos Epej\u00e1n"
    ],
    "wof:name":"Ranchos de Epejan",
    "wof:placetype":"locality"
},
  "geometry": {"coordinates":[-101.8138,20.09824],"type":"Point"}
}