{
  "type": "Feature",
  "properties": {
    "gn:admin1_code":"10",
    "gn:admin2_code":"34",
    "gn:asciiname":"La Sirena",
    "gn:country_code":"MX",
    "gn:dem":1064,
    "gn:feature_class":"P",
    "gn:feature_code":"PPL",
    "gn:name":"La Sirena",
    "gn:population":15,
    "gn:timezone":"America/Monterrey",
    "iso:country":"MX",
    "wof:name":"La Sirena",
    "wof:placetype":"locality",
    "wof:population":15
},
  "geometry": {"coordinates":[-106.98009999999999,25.37608],"type":"Point"}
}