{
  "type": "Feature",
  "properties": {
    "gn:admin1_code":"16",
    "gn:admin2_code":"53.0",
    "gn:asciiname":"La Herradura (Antiguo Camino Real)",
    "gn:country_code":"MX",
    "gn:dem":1970,
    "gn:feature_class":"P",
    "gn:feature_code":"PPL",
    "gn:name":"La Herradura (Antiguo Camino Real)",
    "gn:population":65,
    "gn:timezone":"America/Mexico_City",
    "iso:country":"MX",
    "wof:name":"La Herradura (Antiguo Camino Real)",
    "wof:placetype":"locality",
    "wof:population":65
},
  "geometry": {"coordinates":[-101.29167,19.68833],"type":"Point"}
}