{
  "type": "Feature",
  "properties": {
    "gn:admin1_code":"13",
    "gn:admin2_code":"83.0",
    "gn:asciiname":"El Barrio Casas Coloradas",
    "gn:country_code":"MX",
    "gn:dem":2524,
    "gn:feature_class":"P",
    "gn:feature_code":"PPL",
    "gn:name":"El Barrio Casas Coloradas",
    "gn:population":415,
    "gn:timezone":"America/Mexico_City",
    "iso:country":"MX",
    "wof:name":"El Barrio Casas Coloradas",
    "wof:placetype":"locality",
    "wof:population":415
},
  "geometry": {"coordinates":[-98.65722,19.85528],"type":"Point"}
}