{
  "type": "Feature",
  "properties": {
    "gn:admin1_code":"20",
    "gn:admin2_code":"470.0",
    "gn:asciiname":"Llano Coyul",
    "gn:country_code":"MX",
    "gn:dem":961,
    "gn:feature_class":"P",
    "gn:feature_code":"PPL",
    "gn:name":"Llano Coyul",
    "gn:population":203,
    "gn:timezone":"America/Mexico_City",
    "iso:country":"MX",
    "wof:name":"Llano Coyul",
    "wof:placetype":"locality",
    "wof:population":203
},
  "geometry": {"coordinates":[-95.53417,16.78278],"type":"Point"}
}