{
  "type": "Feature",
  "properties": {
    "gn:admin1_code":"13",
    "gn:admin2_code":"84.0",
    "gn:asciiname":"La Calera",
    "gn:country_code":"MX",
    "gn:dem":2533,
    "gn:feature_class":"P",
    "gn:feature_code":"PPL",
    "gn:name":"La Calera",
    "gn:population":0,
    "gn:timezone":"America/Mexico_City",
    "iso:country":"MX",
    "name:spa_x_preferred":[
        "La Calera"
    ],
    "wof:name":"La Calera",
    "wof:placetype":"locality"
},
  "geometry": {"coordinates":[-99.22783,20.86485],"type":"Point"}
}