{
  "type": "Feature",
  "properties": {
    "gn:admin1_code":"6",
    "gn:admin2_code":"65.0",
    "gn:asciiname":"Baragomachi (El Terrero)",
    "gn:country_code":"MX",
    "gn:dem":1442,
    "gn:feature_class":"P",
    "gn:feature_code":"PPL",
    "gn:name":"Baragomachi (El Terrero)",
    "gn:population":71,
    "gn:timezone":"America/Chihuahua",
    "iso:country":"MX",
    "wof:name":"Baragomachi (El Terrero)",
    "wof:placetype":"locality",
    "wof:population":71
},
  "geometry": {"coordinates":[-108.20195,27.17618],"type":"Point"}
}