{
  "type": "Feature",
  "properties": {
    "gn:admin1_code":"30",
    "gn:admin2_code":"109",
    "gn:asciiname":"La Esperanza (Los Perez)",
    "gn:country_code":"MX",
    "gn:dem":477,
    "gn:feature_class":"P",
    "gn:feature_code":"PPL",
    "gn:name":"La Esperanza (Los P\u00e9rez)",
    "gn:population":30,
    "gn:timezone":"America/Mexico_City",
    "iso:country":"MX",
    "name:und_x_variant":[
        "La Esperanza (Los P\u00e9rez)"
    ],
    "wof:name":"La Esperanza (Los Perez)",
    "wof:placetype":"locality",
    "wof:population":30
},
  "geometry": {"coordinates":[-96.82917,19.88917],"type":"Point"}
}