{
  "type": "Feature",
  "properties": {
    "gn:admin1_code":"6.0",
    "gn:admin2_code":"18.0",
    "gn:asciiname":"El Ojo de la Canoa",
    "gn:cc2":"MX",
    "gn:country_code":"MX",
    "gn:dem":2216,
    "gn:feature_class":"P",
    "gn:feature_code":"PPL",
    "gn:name":"El Ojo de la Canoa",
    "gn:population":1,
    "gn:timezone":"America/Chihuahua",
    "iso:country":"MX",
    "name:und_x_variant":[
        "El Alto"
    ],
    "wof:name":"El Ojo de la Canoa",
    "wof:placetype":"locality",
    "wof:population":1
},
  "geometry": {"coordinates":[-107.09291,28.32417],"type":"Point"}
}