{
  "type": "Feature",
  "properties": {
    "gn:admin1_code":"21",
    "gn:admin2_code":"129.0",
    "gn:asciiname":"San Jeronimo Axochitlan",
    "gn:cc2":"MX",
    "gn:country_code":"MX",
    "gn:dem":1081,
    "gn:feature_class":"P",
    "gn:feature_code":"PPL",
    "gn:name":"San Jer\u00f3nimo Axochitl\u00e1n",
    "gn:population":1088,
    "gn:timezone":"America/Mexico_City",
    "iso:country":"MX",
    "name:und_x_variant":[
        "Axochitl\u00e1n",
        "San Jer\u00f3nimo Axochitl\u00e1n"
    ],
    "wof:name":"San Jeronimo Axochitlan",
    "wof:placetype":"locality",
    "wof:population":1088
},
  "geometry": {"coordinates":[-97.26278000000001,18.27833],"type":"Point"}
}