{
  "type": "Feature",
  "properties": {
    "gn:admin1_code":"15.0",
    "gn:admin2_code":"123.0",
    "gn:asciiname":"Caja de Agua",
    "gn:country_code":"MX",
    "gn:dem":1107,
    "gn:feature_class":"P",
    "gn:feature_code":"PPL",
    "gn:name":"Caja de Agua",
    "gn:population":0,
    "gn:timezone":"America/Mexico_City",
    "iso:country":"MX",
    "name:spa_x_preferred":[
        "Caja de Agua"
    ],
    "wof:name":"Caja de Agua",
    "wof:placetype":"locality"
},
  "geometry": {"coordinates":[-100.29434000000001,18.96109],"type":"Point"}
}