{
  "type": "Feature",
  "properties": {
    "gn:admin1_code":"5",
    "gn:admin2_code":"26.0",
    "gn:asciiname":"Bashequen",
    "gn:country_code":"MX",
    "gn:dem":2020,
    "gn:feature_class":"P",
    "gn:feature_code":"PPL",
    "gn:name":"Bashequen",
    "gn:population":649,
    "gn:timezone":"America/Mexico_City",
    "iso:country":"MX",
    "wof:name":"Bashequen",
    "wof:placetype":"locality",
    "wof:population":649
},
  "geometry": {"coordinates":[-92.61005,16.88452],"type":"Point"}
}