{
  "type": "Feature",
  "properties": {
    "gn:admin1_code":"9",
    "gn:admin2_code":"9",
    "gn:asciiname":"Zozotlac",
    "gn:country_code":"MX",
    "gn:dem":2772,
    "gn:feature_class":"P",
    "gn:feature_code":"PPL",
    "gn:name":"Zozotlac",
    "gn:population":52,
    "gn:timezone":"America/Mexico_City",
    "iso:country":"MX",
    "wof:name":"Zozotlac",
    "wof:placetype":"locality",
    "wof:population":52
},
  "geometry": {"coordinates":[-99.04485,19.17158],"type":"Point"}
}