{
  "type": "Feature",
  "properties": {
    "gn:admin1_code":"30",
    "gn:admin2_code":"102.0",
    "gn:asciiname":"La Isla",
    "gn:country_code":"MX",
    "gn:dem":90,
    "gn:feature_class":"P",
    "gn:feature_code":"PPL",
    "gn:name":"La Isla",
    "gn:population":16,
    "gn:timezone":"America/Mexico_City",
    "iso:country":"MX",
    "name:ceb_x_preferred":[
        "La Isla"
    ],
    "name:spa_x_preferred":[
        "La isla"
    ],
    "name:srp_x_preferred":[
        "\u041b\u0430 \u0418\u0441\u043b\u0430"
    ],
    "name:swe_x_preferred":[
        "La Isla"
    ],
    "wof:name":"La Isla",
    "wof:placetype":"locality",
    "wof:population":16
},
  "geometry": {"coordinates":[-97.06556,20.11667000000001],"type":"Point"}
}