{
  "type": "Feature",
  "properties": {
    "gn:admin1_code":"14.0",
    "gn:admin2_code":"20.0",
    "gn:asciiname":"Acatan",
    "gn:country_code":"MX",
    "gn:dem":534,
    "gn:feature_class":"P",
    "gn:feature_code":"PPL",
    "gn:name":"Acat\u00e1n",
    "gn:population":0,
    "gn:timezone":"America/Mexico_City",
    "iso:country":"MX",
    "name:spa_x_preferred":[
        "Acat\u00e1n"
    ],
    "wof:name":"Acatan",
    "wof:placetype":"locality"
},
  "geometry": {"coordinates":[-105.38491999999999,20.37694],"type":"Point"}
}