{
  "type": "Feature",
  "properties": {
    "gn:admin1_code":"5",
    "gn:admin2_code":"26.0",
    "gn:asciiname":"Beumpale",
    "gn:country_code":"MX",
    "gn:dem":1801,
    "gn:feature_class":"P",
    "gn:feature_code":"PPL",
    "gn:name":"Beumpale",
    "gn:population":390,
    "gn:timezone":"America/Mexico_City",
    "iso:country":"MX",
    "wof:name":"Beumpale",
    "wof:placetype":"locality",
    "wof:population":390
},
  "geometry": {"coordinates":[-92.56056,16.9175],"type":"Point"}
}