{
  "type": "Feature",
  "properties": {
    "gn:admin1_code":"14",
    "gn:admin2_code":"15.0",
    "gn:asciiname":"El Casco (El Arenal)",
    "gn:country_code":"MX",
    "gn:dem":879,
    "gn:feature_class":"P",
    "gn:feature_code":"PPL",
    "gn:name":"El Casco (El Arenal)",
    "gn:population":5,
    "gn:timezone":"America/Mexico_City",
    "iso:country":"MX",
    "wof:name":"El Casco (El Arenal)",
    "wof:placetype":"locality",
    "wof:population":5
},
  "geometry": {"coordinates":[-104.22056000000001,19.75333],"type":"Point"}
}