{
  "type": "Feature",
  "properties": {
    "gn:admin1_code":"13",
    "gn:admin2_code":"15.0",
    "gn:asciiname":"Los Pena",
    "gn:country_code":"MX",
    "gn:dem":1899,
    "gn:feature_class":"P",
    "gn:feature_code":"PPL",
    "gn:name":"Los Pe\u00f1a",
    "gn:population":308,
    "gn:timezone":"America/Mexico_City",
    "iso:country":"MX",
    "name:und_x_variant":[
        "Los Pe\u00f1a"
    ],
    "wof:name":"Los Pena",
    "wof:placetype":"locality",
    "wof:population":308
},
  "geometry": {"coordinates":[-99.13611,20.58806],"type":"Point"}
}