{
  "type": "Feature",
  "properties": {
    "gn:admin1_code":"25.0",
    "gn:admin2_code":"4.0",
    "gn:asciiname":"Calera",
    "gn:country_code":"MX",
    "gn:dem":1115,
    "gn:feature_class":"P",
    "gn:feature_code":"PPL",
    "gn:name":"Calera",
    "gn:population":0,
    "gn:timezone":"America/Mazatlan",
    "iso:country":"MX",
    "wof:name":"Calera",
    "wof:placetype":"locality"
},
  "geometry": {"coordinates":[-105.95,23.51667],"type":"Point"}
}