{
  "type": "Feature",
  "properties": {
    "gn:admin1_code":"16",
    "gn:admin2_code":"78.0",
    "gn:asciiname":"El Salto Dos",
    "gn:country_code":"MX",
    "gn:dem":1946,
    "gn:feature_class":"P",
    "gn:feature_code":"PPL",
    "gn:name":"El Salto Dos",
    "gn:population":217,
    "gn:timezone":"America/Mexico_City",
    "iso:country":"MX",
    "wof:name":"El Salto Dos",
    "wof:placetype":"locality",
    "wof:population":217
},
  "geometry": {"coordinates":[-101.08167,20.08028],"type":"Point"}
}