{
  "type": "Feature",
  "properties": {
    "gn:admin1_code":"30",
    "gn:admin2_code":"10.0",
    "gn:asciiname":"Temimilco",
    "gn:country_code":"MX",
    "gn:dem":937,
    "gn:feature_class":"P",
    "gn:feature_code":"PPL",
    "gn:name":"Temimilco",
    "gn:population":0,
    "gn:timezone":"America/Mexico_City",
    "iso:country":"MX",
    "name:spa_x_preferred":[
        "Temimilco"
    ],
    "wof:name":"Temimilco",
    "wof:placetype":"locality"
},
  "geometry": {"coordinates":[-97.09502999999999,19.80397],"type":"Point"}
}