{
  "type": "Feature",
  "properties": {
    "gn:admin1_code":"28.0",
    "gn:admin2_code":"12.0",
    "gn:asciiname":"La Barranca",
    "gn:country_code":"MX",
    "gn:dem":52,
    "gn:feature_class":"P",
    "gn:feature_code":"PPL",
    "gn:name":"La Barranca",
    "gn:population":5,
    "gn:timezone":"America/Monterrey",
    "iso:country":"MX",
    "name:fra_x_preferred":[
        "La Barranca"
    ],
    "name:spa_x_preferred":[
        "La Barranca"
    ],
    "wof:name":"La Barranca",
    "wof:placetype":"locality",
    "wof:population":5
},
  "geometry": {"coordinates":[-98.79722,22.81222],"type":"Point"}
}