{
  "type": "Feature",
  "properties": {
    "gn:admin1_code":"13",
    "gn:admin2_code":"47.0",
    "gn:asciiname":"Jiliapan",
    "gn:cc2":"MX",
    "gn:country_code":"MX",
    "gn:dem":1455,
    "gn:feature_class":"P",
    "gn:feature_code":"PPL",
    "gn:name":"Jiliapan",
    "gn:population":966,
    "gn:timezone":"America/Mexico_City",
    "iso:country":"MX",
    "name:und_x_variant":[
        "Jiliapa",
        "Jiliapan"
    ],
    "wof:name":"Jiliapan",
    "wof:placetype":"locality",
    "wof:population":966
},
  "geometry": {"coordinates":[-99.34361,20.98111],"type":"Point"}
}