{
  "type": "Feature",
  "properties": {
    "gn:admin1_code":"10.0",
    "gn:admin2_code":"9.0",
    "gn:asciiname":"Arroyo del Corral",
    "gn:country_code":"MX",
    "gn:dem":1982,
    "gn:feature_class":"P",
    "gn:feature_code":"PPL",
    "gn:name":"Arroyo del Corral",
    "gn:population":0,
    "gn:timezone":"America/Monterrey",
    "iso:country":"MX",
    "name:spa_x_preferred":[
        "Arroyo del Corral"
    ],
    "wof:name":"Arroyo del Corral",
    "wof:placetype":"locality"
},
  "geometry": {"coordinates":[-105.87576,25.8897],"type":"Point"}
}