{
  "type": "Feature",
  "properties": {
    "gn:admin1_code":"16.0",
    "gn:admin2_code":"15.0",
    "gn:asciiname":"Juntas del Saca Marin",
    "gn:country_code":"MX",
    "gn:dem":989,
    "gn:feature_class":"P",
    "gn:feature_code":"PPL",
    "gn:name":"Juntas del Saca Mar\u00edn",
    "gn:population":0,
    "gn:timezone":"America/Mexico_City",
    "iso:country":"MX",
    "name:spa_x_preferred":[
        "Juntas del Saca Mar\u00edn"
    ],
    "wof:name":"Juntas del Saca Marin",
    "wof:placetype":"locality"
},
  "geometry": {"coordinates":[-103.11151,18.45003],"type":"Point"}
}