{
  "type": "Feature",
  "properties": {
    "gn:admin1_code":"6.0",
    "gn:admin2_code":"11.0",
    "gn:asciiname":"Charco de Piedra",
    "gn:country_code":"MX",
    "gn:dem":1352,
    "gn:feature_class":"P",
    "gn:feature_code":"PPL",
    "gn:name":"Charco de Piedra",
    "gn:population":0,
    "gn:timezone":"America/Chihuahua",
    "iso:country":"MX",
    "name:und_x_variant":[
        "Rancho El Charco de Piedra",
        "Charco de Piedra"
    ],
    "wof:name":"Charco de Piedra",
    "wof:placetype":"locality"
},
  "geometry": {"coordinates":[-104.9101,27.7977],"type":"Point"}
}