{
  "type": "Feature",
  "properties": {
    "gn:admin1_code":"14.0",
    "gn:asciiname":"Agua Bendita",
    "gn:country_code":"MX",
    "gn:dem":1153,
    "gn:feature_class":"P",
    "gn:feature_code":"PPL",
    "gn:name":"Agua Bendita",
    "gn:population":0,
    "gn:timezone":"America/Mexico_City",
    "iso:country":"MX",
    "name:por_x_preferred":[
        "Agua Bendita"
    ],
    "name:spa_x_preferred":[
        "Agua Bendita"
    ],
    "name:tgl_x_preferred":[
        "Agua Bendita"
    ],
    "wof:name":"Agua Bendita",
    "wof:placetype":"locality"
},
  "geometry": {"coordinates":[-102.54714,19.46927],"type":"Point"}
}