{
  "type": "Feature",
  "properties": {
    "gn:admin1_code":"30.0",
    "gn:admin2_code":"158.0",
    "gn:asciiname":"Pez Uno",
    "gn:country_code":"MX",
    "gn:dem":6,
    "gn:feature_class":"P",
    "gn:feature_code":"PPL",
    "gn:name":"Pez Uno",
    "gn:population":0,
    "gn:timezone":"America/Mexico_City",
    "iso:country":"MX",
    "name:spa_x_preferred":[
        "Pez Uno"
    ],
    "wof:name":"Pez Uno",
    "wof:placetype":"locality"
},
  "geometry": {"coordinates":[-96.99524,20.44003],"type":"Point"}
}