{
  "type": "Feature",
  "properties": {
    "gn:admin1_code":"32",
    "gn:admin2_code":"5.0",
    "gn:asciiname":"Nueva Alianza (Nates)",
    "gn:country_code":"MX",
    "gn:dem":2306,
    "gn:feature_class":"P",
    "gn:feature_code":"PPL",
    "gn:name":"Nueva Alianza (\u00d1ates)",
    "gn:population":150,
    "gn:timezone":"America/Mexico_City",
    "iso:country":"MX",
    "name:und_x_variant":[
        "Nueva Alianza (\u00d1ates)"
    ],
    "wof:name":"Nueva Alianza (Nates)",
    "wof:placetype":"locality",
    "wof:population":150
},
  "geometry": {"coordinates":[-102.85833,22.8975],"type":"Point"}
}