{
  "type": "Feature",
  "properties": {
    "gn:admin1_code":"25",
    "gn:admin2_code":"10.0",
    "gn:asciiname":"Cuesta Alta",
    "gn:country_code":"MX",
    "gn:dem":61,
    "gn:feature_class":"P",
    "gn:feature_code":"PPL",
    "gn:name":"Cuesta Alta",
    "gn:population":396,
    "gn:timezone":"America/Mazatlan",
    "iso:country":"MX",
    "wof:name":"Cuesta Alta",
    "wof:placetype":"locality",
    "wof:population":396
},
  "geometry": {"coordinates":[-108.75167,26.3275],"type":"Point"}
}