{
  "type": "Feature",
  "properties": {
    "gn:admin1_code":"21.0",
    "gn:admin2_code":"15.0",
    "gn:asciiname":"San Miguel Cuauhtenco",
    "gn:country_code":"MX",
    "gn:dem":2554,
    "gn:feature_class":"P",
    "gn:feature_code":"PPL",
    "gn:name":"San Miguel Cuauhtenco",
    "gn:population":0,
    "gn:timezone":"America/Mexico_City",
    "iso:country":"MX",
    "name:spa_x_preferred":[
        "San Miguel Cuauhtenco"
    ],
    "wof:name":"San Miguel Cuauhtenco",
    "wof:placetype":"locality"
},
  "geometry": {"coordinates":[-98.01963000000001,19.11413],"type":"Point"}
}