{
  "type": "Feature",
  "properties": {
    "gn:admin1_code":"28",
    "gn:admin2_code":"4.0",
    "gn:asciiname":"San Jose",
    "gn:country_code":"MX",
    "gn:dem":287,
    "gn:feature_class":"P",
    "gn:feature_code":"PPL",
    "gn:name":"San Jos\u00e9",
    "gn:population":255,
    "gn:timezone":"America/Mexico_City",
    "iso:country":"MX",
    "wof:name":"San Jose",
    "wof:placetype":"locality",
    "wof:population":255
},
  "geometry": {"coordinates":[-99.0625,22.41778],"type":"Point"}
}