{
  "type": "Feature",
  "properties": {
    "gn:admin1_code":"11",
    "gn:admin2_code":"26.0",
    "gn:asciiname":"Colonia Rafael Corrales Ayala",
    "gn:country_code":"MX",
    "gn:dem":1763,
    "gn:feature_class":"P",
    "gn:feature_code":"PPL",
    "gn:name":"Colonia Rafael Corrales Ayala",
    "gn:population":1020,
    "gn:timezone":"America/Mexico_City",
    "iso:country":"MX",
    "wof:name":"Colonia Rafael Corrales Ayala",
    "wof:placetype":"locality",
    "wof:population":1020
},
  "geometry": {"coordinates":[-101.51611,20.90194],"type":"Point"}
}