{
  "type": "Feature",
  "properties": {
    "gn:admin1_code":"28",
    "gn:admin2_code":"5.0",
    "gn:asciiname":"El Quiote",
    "gn:country_code":"MX",
    "gn:dem":155,
    "gn:feature_class":"P",
    "gn:feature_code":"PPL",
    "gn:name":"El Quiote",
    "gn:population":0,
    "gn:timezone":"America/Monterrey",
    "iso:country":"MX",
    "name:spa_x_preferred":[
        "El Quiote"
    ],
    "name:und_x_variant":[
        "El Quijote"
    ],
    "wof:name":"El Quiote",
    "wof:placetype":"locality"
},
  "geometry": {"coordinates":[-98.90294,24.98218],"type":"Point"}
}