{
  "type": "Feature",
  "properties": {
    "gn:admin1_code":"21",
    "gn:admin2_code":"55.0",
    "gn:asciiname":"San Isidro",
    "gn:country_code":"MX",
    "gn:dem":1643,
    "gn:feature_class":"P",
    "gn:feature_code":"PPL",
    "gn:name":"San Isidro",
    "gn:population":99,
    "gn:timezone":"America/Mexico_City",
    "iso:country":"MX",
    "name:aze_x_preferred":[
        "San-\u0130sidro"
    ],
    "name:cat_x_preferred":[
        "San Isidro"
    ],
    "name:ceb_x_preferred":[
        "San Isidro"
    ],
    "name:deu_x_preferred":[
        "San Isidro"
    ],
    "name:eus_x_preferred":[
        "San Isidro"
    ],
    "name:fra_x_preferred":[
        "San Isidro"
    ],
    "name:ilo_x_preferred":[
        "San Isidro"
    ],
    "name:ita_x_preferred":[
        "San Isidro"
    ],
    "name:lit_x_preferred":[
        "San Isidras"
    ],
    "name:mlg_x_preferred":[
        "San Isidro"
    ],
    "name:nds_x_preferred":[
        "San Isidro"
    ],
    "name:nld_x_preferred":[
        "San Isidro"
    ],
    "name:pol_x_preferred":[
        "San Isidro"
    ],
    "name:por_x_preferred":[
        "San Isidro"
    ],
    "name:rus_x_preferred":[
        "\u0421\u0430\u043d-\u0418\u0441\u0438\u0434\u0440\u043e"
    ],
    "name:sco_x_preferred":[
        "San Isidro"
    ],
    "name:spa_x_preferred":[
        "San Isidro"
    ],
    "name:srp_x_preferred":[
        "\u0421\u0430\u043d \u0418\u0441\u0438\u0434\u0440\u043e"
    ],
    "name:swe_x_preferred":[
        "San Isidro"
    ],
    "name:vie_x_preferred":[
        "San Isidro"
    ],
    "name:war_x_preferred":[
        "San Isidro"
    ],
    "wof:name":"San Isidro",
    "wof:placetype":"locality",
    "wof:population":99
},
  "geometry": {"coordinates":[-97.83243,17.96191],"type":"Point"}
}