{
  "type": "Feature",
  "properties": {
    "gn:admin1_code":"7",
    "gn:admin2_code":"15.0",
    "gn:asciiname":"La Perla",
    "gn:country_code":"MX",
    "gn:dem":270,
    "gn:feature_class":"P",
    "gn:feature_code":"PPL",
    "gn:name":"La Perla",
    "gn:population":0,
    "gn:timezone":"America/Monterrey",
    "iso:country":"MX",
    "name:spa_x_preferred":[
        "La Perla"
    ],
    "name:und_x_variant":[
        "Rancho La Peria"
    ],
    "wof:name":"La Perla",
    "wof:placetype":"locality"
},
  "geometry": {"coordinates":[-100.47987000000001,27.75069],"type":"Point"}
}