{
  "type": "Feature",
  "properties": {
    "gn:admin1_code":"19.0",
    "gn:admin2_code":"37.0",
    "gn:asciiname":"El Cuarto",
    "gn:country_code":"MX",
    "gn:dem":640,
    "gn:feature_class":"P",
    "gn:feature_code":"PPL",
    "gn:name":"El Cuarto",
    "gn:population":0,
    "gn:timezone":"America/Monterrey",
    "iso:country":"MX",
    "name:und_x_variant":[
        "Cuato",
        "El Cuarto"
    ],
    "wof:name":"El Cuarto",
    "wof:placetype":"locality"
},
  "geometry": {"coordinates":[-100.58762,26.37017],"type":"Point"}
}