{
  "type": "Feature",
  "properties": {
    "gn:admin1_code":"10",
    "gn:admin2_code":"34",
    "gn:asciiname":"El Llano",
    "gn:country_code":"MX",
    "gn:dem":2543,
    "gn:feature_class":"P",
    "gn:feature_code":"PPL",
    "gn:name":"El Llano",
    "gn:population":39,
    "gn:timezone":"America/Monterrey",
    "iso:country":"MX",
    "name:ceb_x_preferred":[
        "El Llano"
    ],
    "name:deu_x_preferred":[
        "El Llano"
    ],
    "name:fra_x_preferred":[
        "El Llano"
    ],
    "name:ita_x_preferred":[
        "El Llano"
    ],
    "name:spa_x_preferred":[
        "El Llano"
    ],
    "name:swe_x_preferred":[
        "El Llano"
    ],
    "wof:name":"El Llano",
    "wof:placetype":"locality",
    "wof:population":39
},
  "geometry": {"coordinates":[-106.86454999999999,25.48302],"type":"Point"}
}