{
  "type": "Feature",
  "properties": {
    "gn:admin1_code":"2",
    "gn:admin2_code":"2.0",
    "gn:asciiname":"Emiliano Zapata (Colonia Progreso)",
    "gn:country_code":"MX",
    "gn:dem":2,
    "gn:feature_class":"P",
    "gn:feature_code":"PPL",
    "gn:name":"Emiliano Zapata (Colonia Progreso)",
    "gn:population":79,
    "gn:timezone":"America/Tijuana",
    "iso:country":"MX",
    "wof:name":"Emiliano Zapata (Colonia Progreso)",
    "wof:placetype":"locality",
    "wof:population":79
},
  "geometry": {"coordinates":[-115.61861,32.5925],"type":"Point"}
}