{
  "type": "Feature",
  "properties": {
    "gn:admin1_code":"27",
    "gn:admin2_code":"11",
    "gn:asciiname":"Prudencio Lopez Arias",
    "gn:country_code":"MX",
    "gn:dem":4,
    "gn:feature_class":"P",
    "gn:feature_code":"PPL",
    "gn:name":"Prudencio L\u00f3pez Arias",
    "gn:population":44,
    "gn:timezone":"America/Mexico_City",
    "iso:country":"MX",
    "name:und_x_variant":[
        "Prudencio L\u00f3pez Arias"
    ],
    "wof:name":"Prudencio Lopez Arias",
    "wof:placetype":"locality",
    "wof:population":44
},
  "geometry": {"coordinates":[-92.19444,18.26833],"type":"Point"}
}