{
  "type": "Feature",
  "properties": {
    "gn:admin1_code":"16",
    "gn:admin2_code":"15.0",
    "gn:asciiname":"Los Otatillos",
    "gn:country_code":"MX",
    "gn:dem":1164,
    "gn:feature_class":"P",
    "gn:feature_code":"PPL",
    "gn:name":"Los Otatillos",
    "gn:population":7,
    "gn:timezone":"America/Mexico_City",
    "iso:country":"MX",
    "wof:name":"Los Otatillos",
    "wof:placetype":"locality",
    "wof:population":7
},
  "geometry": {"coordinates":[-102.99361,18.39556],"type":"Point"}
}