{
  "type": "Feature",
  "properties": {
    "gn:admin1_code":"21",
    "gn:admin2_code":"165.0",
    "gn:asciiname":"San Juan Catzoc",
    "gn:country_code":"MX",
    "gn:dem":1905,
    "gn:feature_class":"P",
    "gn:feature_code":"PPL",
    "gn:name":"San Juan Catzoc",
    "gn:population":80,
    "gn:timezone":"America/Mexico_City",
    "iso:country":"MX",
    "wof:name":"San Juan Catzoc",
    "wof:placetype":"locality",
    "wof:population":80
},
  "geometry": {"coordinates":[-98.64255,18.77455],"type":"Point"}
}