{
  "type": "Feature",
  "properties": {
    "gn:admin1_code":"30",
    "gn:admin2_code":"6.0",
    "gn:asciiname":"Coxolitla de Abajo",
    "gn:country_code":"MX",
    "gn:dem":1428,
    "gn:feature_class":"P",
    "gn:feature_code":"PPL",
    "gn:name":"Coxolitla de Abajo",
    "gn:population":0,
    "gn:timezone":"America/Mexico_City",
    "iso:country":"MX",
    "name:spa_x_preferred":[
        "Coxolitla de Abajo"
    ],
    "wof:name":"Coxolitla de Abajo",
    "wof:placetype":"locality"
},
  "geometry": {"coordinates":[-97.24335000000001,18.74565],"type":"Point"}
}