{
  "type": "Feature",
  "properties": {
    "gn:admin1_code":"6",
    "gn:admin2_code":"34.0",
    "gn:asciiname":"La Yolanda",
    "gn:country_code":"MX",
    "gn:dem":2175,
    "gn:feature_class":"P",
    "gn:feature_code":"PPL",
    "gn:name":"La Yolanda",
    "gn:population":0,
    "gn:timezone":"America/Chihuahua",
    "iso:country":"MX",
    "name:spa_x_preferred":[
        "La Yolanda"
    ],
    "wof:name":"La Yolanda",
    "wof:placetype":"locality"
},
  "geometry": {"coordinates":[-107.96265,29.67948],"type":"Point"}
}