{
  "type": "Feature",
  "properties": {
    "gn:admin1_code":"28.0",
    "gn:admin2_code":"37.0",
    "gn:asciiname":"Balconcitos",
    "gn:country_code":"MX",
    "gn:dem":158,
    "gn:feature_class":"P",
    "gn:feature_code":"PPL",
    "gn:name":"Balconcitos",
    "gn:population":0,
    "gn:timezone":"America/Monterrey",
    "iso:country":"MX",
    "name:spa_x_preferred":[
        "Balconcitos"
    ],
    "wof:name":"Balconcitos",
    "wof:placetype":"locality"
},
  "geometry": {"coordinates":[-98.40571,23.82524],"type":"Point"}
}