{
  "type": "Feature",
  "properties": {
    "gn:admin1_code":"13",
    "gn:admin2_code":"45.0",
    "gn:asciiname":"Puentecillas",
    "gn:country_code":"MX",
    "gn:dem":2710,
    "gn:feature_class":"P",
    "gn:feature_code":"PPL",
    "gn:name":"Puentecillas",
    "gn:population":426,
    "gn:timezone":"America/Mexico_City",
    "iso:country":"MX",
    "wof:name":"Puentecillas",
    "wof:placetype":"locality",
    "wof:population":426
},
  "geometry": {"coordinates":[-98.63972,20.15],"type":"Point"}
}