{
  "type": "Feature",
  "properties": {
    "gn:admin1_code":"6",
    "gn:admin2_code":"65.0",
    "gn:asciiname":"Sicoratavo",
    "gn:country_code":"MX",
    "gn:dem":2315,
    "gn:feature_class":"P",
    "gn:feature_code":"PPL",
    "gn:name":"Sicoratavo",
    "gn:population":8,
    "gn:timezone":"America/Chihuahua",
    "iso:country":"MX",
    "wof:name":"Sicoratavo",
    "wof:placetype":"locality",
    "wof:population":8
},
  "geometry": {"coordinates":[-107.90603,27.43159],"type":"Point"}
}