{
  "type": "Feature",
  "properties": {
    "gn:admin1_code":"6",
    "gn:admin2_code":"27.0",
    "gn:asciiname":"El Puerto Blanco",
    "gn:country_code":"MX",
    "gn:dem":2200,
    "gn:feature_class":"P",
    "gn:feature_code":"PPL",
    "gn:name":"El Puerto Blanco",
    "gn:population":6,
    "gn:timezone":"America/Chihuahua",
    "iso:country":"MX",
    "wof:name":"El Puerto Blanco",
    "wof:placetype":"locality",
    "wof:population":6
},
  "geometry": {"coordinates":[-107.42878,26.76494000000001],"type":"Point"}
}