{
  "type": "Feature",
  "properties": {
    "gn:admin1_code":"20",
    "gn:admin2_code":"333.0",
    "gn:asciiname":"Colonia Colosio",
    "gn:country_code":"MX",
    "gn:dem":1012,
    "gn:feature_class":"P",
    "gn:feature_code":"PPL",
    "gn:name":"Colonia Colosio",
    "gn:population":68,
    "gn:timezone":"America/Mexico_City",
    "iso:country":"MX",
    "wof:name":"Colonia Colosio",
    "wof:placetype":"locality",
    "wof:population":68
},
  "geometry": {"coordinates":[-96.31305999999999,16.67167],"type":"Point"}
}