{
  "type": "Feature",
  "properties": {
    "gn:admin1_code":"15",
    "gn:admin2_code":"87",
    "gn:asciiname":"Hacienda las Trojes",
    "gn:country_code":"MX",
    "gn:dem":2573,
    "gn:feature_class":"P",
    "gn:feature_code":"PPL",
    "gn:name":"Hacienda las Trojes",
    "gn:population":32,
    "gn:timezone":"America/Mexico_City",
    "iso:country":"MX",
    "wof:name":"Hacienda las Trojes",
    "wof:placetype":"locality",
    "wof:population":32
},
  "geometry": {"coordinates":[-99.60971000000001,19.41341],"type":"Point"}
}