{
  "type": "Feature",
  "properties": {
    "gn:admin1_code":"30",
    "gn:admin2_code":"158",
    "gn:asciiname":"Ejido el Paraiso",
    "gn:country_code":"MX",
    "gn:dem":46,
    "gn:feature_class":"P",
    "gn:feature_code":"PPL",
    "gn:name":"Ejido el Para\u00edso",
    "gn:population":29,
    "gn:timezone":"America/Mexico_City",
    "iso:country":"MX",
    "name:und_x_variant":[
        "Ejido el Para\u00edso"
    ],
    "wof:name":"Ejido el Paraiso",
    "wof:placetype":"locality",
    "wof:population":29
},
  "geometry": {"coordinates":[-96.99028,20.36417],"type":"Point"}
}