{
  "type": "Feature",
  "properties": {
    "gn:admin1_code":"14.0",
    "gn:asciiname":"Cerro del Cuervo",
    "gn:country_code":"MX",
    "gn:dem":1328,
    "gn:feature_class":"P",
    "gn:feature_code":"PPL",
    "gn:name":"Cerro del Cuervo",
    "gn:population":0,
    "gn:timezone":"America/Mexico_City",
    "iso:country":"MX",
    "name:spa_x_preferred":[
        "Cerro del Cuervo"
    ],
    "wof:name":"Cerro del Cuervo",
    "wof:placetype":"locality"
},
  "geometry": {"coordinates":[-103.84976,21.47961],"type":"Point"}
}