{
  "type": "Feature",
  "properties": {
    "gn:admin1_code":"2",
    "gn:admin2_code":"1",
    "gn:asciiname":"Los Alamitos",
    "gn:country_code":"MX",
    "gn:dem":93,
    "gn:feature_class":"P",
    "gn:feature_code":"PPL",
    "gn:name":"Los Alamitos",
    "gn:population":10,
    "gn:timezone":"America/Tijuana",
    "iso:country":"MX",
    "name:ceb_x_preferred":[
        "Los Alamitos"
    ],
    "name:srp_x_preferred":[
        "\u041b\u043e\u0441 \u0410\u043b\u0430\u043c\u0438\u0442\u043e\u0441"
    ],
    "name:swe_x_preferred":[
        "Los Alamitos"
    ],
    "wof:name":"Los Alamitos",
    "wof:placetype":"locality",
    "wof:population":10
},
  "geometry": {"coordinates":[-116.50917,31.77083],"type":"Point"}
}