{
  "type": "Feature",
  "properties": {
    "gn:admin1_code":"14",
    "gn:admin2_code":"1",
    "gn:asciiname":"Codornices",
    "gn:country_code":"MX",
    "gn:dem":1744,
    "gn:feature_class":"P",
    "gn:feature_code":"PPL",
    "gn:name":"Codornices",
    "gn:population":50,
    "gn:timezone":"America/Mexico_City",
    "iso:country":"MX",
    "wof:name":"Codornices",
    "wof:placetype":"locality",
    "wof:population":50
},
  "geometry": {"coordinates":[-102.91611,20.71694],"type":"Point"}
}