{
  "type": "Feature",
  "properties": {
    "gn:admin1_code":"12.0",
    "gn:admin2_code":"58.0",
    "gn:asciiname":"San Antionio Ahuehuepan",
    "gn:country_code":"MX",
    "gn:dem":784,
    "gn:feature_class":"P",
    "gn:feature_code":"PPL",
    "gn:name":"San Antionio Ahuehuepan",
    "gn:population":0,
    "gn:timezone":"America/Mexico_City",
    "iso:country":"MX",
    "name:spa_x_preferred":[
        "San Antionio Ahuehuepan"
    ],
    "wof:name":"San Antionio Ahuehuepan",
    "wof:placetype":"locality"
},
  "geometry": {"coordinates":[-99.65415,18.35715],"type":"Point"}
}