{
  "type": "Feature",
  "properties": {
    "gn:admin1_code":"32",
    "gn:admin2_code":"12.0",
    "gn:asciiname":"Boquilla del Carmen",
    "gn:country_code":"MX",
    "gn:dem":2589,
    "gn:feature_class":"P",
    "gn:feature_code":"PPL",
    "gn:name":"Boquilla del Carmen",
    "gn:population":0,
    "gn:timezone":"America/Mexico_City",
    "iso:country":"MX",
    "wof:name":"Boquilla del Carmen",
    "wof:placetype":"locality"
},
  "geometry": {"coordinates":[-102.61667,22.41667],"type":"Point"}
}