{
  "type": "Feature",
  "properties": {
    "gn:admin1_code":"21",
    "gn:admin2_code":"39.0",
    "gn:asciiname":"Ahuatlan",
    "gn:country_code":"MX",
    "gn:dem":1421,
    "gn:feature_class":"P",
    "gn:feature_code":"PPL",
    "gn:name":"Ahuatl\u00e1n",
    "gn:population":516,
    "gn:timezone":"America/Mexico_City",
    "iso:country":"MX",
    "name:und_x_variant":[
        "Ahuatl\u00e1n"
    ],
    "wof:name":"Ahuatlan",
    "wof:placetype":"locality",
    "wof:population":516
},
  "geometry": {"coordinates":[-97.81028000000001,19.9175],"type":"Point"}
}