{
  "type": "Feature",
  "properties": {
    "gn:admin1_code":"14",
    "gn:admin2_code":"22",
    "gn:asciiname":"Melaque [Gasolinera]",
    "gn:country_code":"MX",
    "gn:dem":15,
    "gn:feature_class":"P",
    "gn:feature_code":"PPL",
    "gn:name":"Melaque [Gasolinera]",
    "gn:population":23,
    "gn:timezone":"America/Mexico_City",
    "iso:country":"MX",
    "wof:name":"Melaque [Gasolinera]",
    "wof:placetype":"locality",
    "wof:population":23
},
  "geometry": {"coordinates":[-104.70860999999999,19.23861],"type":"Point"}
}