{
  "type": "Feature",
  "properties": {
    "gn:admin1_code":"6.0",
    "gn:asciiname":"Campo Ochenta y Dos",
    "gn:country_code":"MX",
    "gn:dem":2106,
    "gn:feature_class":"P",
    "gn:feature_code":"PPL",
    "gn:name":"Campo Ochenta y Dos",
    "gn:population":0,
    "gn:timezone":"America/Chihuahua",
    "iso:country":"MX",
    "name:spa_x_preferred":[
        "Campo Ochenta y Dos"
    ],
    "wof:name":"Campo Ochenta y Dos",
    "wof:placetype":"locality"
},
  "geometry": {"coordinates":[-106.72848,29.22161],"type":"Point"}
}