{
  "type": "Feature",
  "properties": {
    "gn:admin1_code":"16.0",
    "gn:admin2_code":"96.0",
    "gn:asciiname":"Macias",
    "gn:country_code":"MX",
    "gn:dem":1112,
    "gn:feature_class":"P",
    "gn:feature_code":"PPL",
    "gn:name":"Mac\u00edas",
    "gn:population":0,
    "gn:timezone":"America/Mexico_City",
    "iso:country":"MX",
    "name:spa_x_preferred":[
        "Mac\u00edas"
    ],
    "name:spa_x_variant":[
        "El Ahijadero"
    ],
    "wof:name":"Macias",
    "wof:placetype":"locality"
},
  "geometry": {"coordinates":[-102.58732000000001,18.57766],"type":"Point"}
}