{
  "type": "Feature",
  "properties": {
    "gn:admin1_code":"19",
    "gn:admin2_code":"41",
    "gn:asciiname":"El Trece",
    "gn:country_code":"MX",
    "gn:dem":330,
    "gn:feature_class":"P",
    "gn:feature_code":"PPL",
    "gn:name":"El Trece",
    "gn:population":12,
    "gn:timezone":"America/Monterrey",
    "iso:country":"MX",
    "wof:name":"El Trece",
    "wof:placetype":"locality",
    "wof:population":12
},
  "geometry": {"coordinates":[-100.02167,25.78194],"type":"Point"}
}