{
  "type": "Feature",
  "properties": {
    "gn:admin1_code":"26",
    "gn:admin2_code":"18.0",
    "gn:asciiname":"Maria Cristina (Bloque 1203)",
    "gn:country_code":"MX",
    "gn:dem":15,
    "gn:feature_class":"P",
    "gn:feature_code":"PPL",
    "gn:name":"Mar\u00eda Cristina (Bloque 1203)",
    "gn:population":7,
    "gn:timezone":"America/Hermosillo",
    "iso:country":"MX",
    "name:und_x_variant":[
        "Mar\u00eda Cristina (Bloque 1203)"
    ],
    "wof:name":"Maria Cristina (Bloque 1203)",
    "wof:placetype":"locality",
    "wof:population":7
},
  "geometry": {"coordinates":[-110.03471999999999,27.31667],"type":"Point"}
}