{
  "type": "Feature",
  "properties": {
    "gn:admin1_code":"16",
    "gn:admin2_code":"51",
    "gn:asciiname":"La Loma del Soyate",
    "gn:country_code":"MX",
    "gn:dem":2046,
    "gn:feature_class":"P",
    "gn:feature_code":"PPL",
    "gn:name":"La Loma del Soyate",
    "gn:population":13,
    "gn:timezone":"America/Mexico_City",
    "iso:country":"MX",
    "wof:name":"La Loma del Soyate",
    "wof:placetype":"locality",
    "wof:population":13
},
  "geometry": {"coordinates":[-103.01694000000001,19.97056],"type":"Point"}
}