{
  "type": "Feature",
  "properties": {
    "gn:admin1_code":"13",
    "gn:admin2_code":"31.0",
    "gn:asciiname":"Las Duraznos",
    "gn:country_code":"MX",
    "gn:dem":1677,
    "gn:feature_class":"P",
    "gn:feature_code":"PPL",
    "gn:name":"Las Duraznos",
    "gn:population":0,
    "gn:timezone":"America/Mexico_City",
    "iso:country":"MX",
    "name:spa_x_preferred":[
        "Las Duraznos"
    ],
    "name:und_x_variant":[
        "El Durazno",
        "Los Duraznos"
    ],
    "wof:name":"Las Duraznos",
    "wof:placetype":"locality"
},
  "geometry": {"coordinates":[-99.13517,21.07096],"type":"Point"}
}