{
  "type": "Feature",
  "properties": {
    "gn:admin1_code":"20",
    "gn:admin2_code":"137.0",
    "gn:asciiname":"Loma Tigre",
    "gn:country_code":"MX",
    "gn:dem":1650,
    "gn:feature_class":"P",
    "gn:feature_code":"PPL",
    "gn:name":"Loma Tigre",
    "gn:population":157,
    "gn:timezone":"America/Mexico_City",
    "iso:country":"MX",
    "wof:name":"Loma Tigre",
    "wof:placetype":"locality",
    "wof:population":157
},
  "geometry": {"coordinates":[-97.3925,16.93333],"type":"Point"}
}