{
  "type": "Feature",
  "properties": {
    "gn:admin1_code":"5",
    "gn:admin2_code":"69",
    "gn:asciiname":"Las Nuevas Guacamayas",
    "gn:country_code":"MX",
    "gn:dem":48,
    "gn:feature_class":"P",
    "gn:feature_code":"PPL",
    "gn:name":"Las Nuevas Guacamayas",
    "gn:population":21,
    "gn:timezone":"America/Mexico_City",
    "iso:country":"MX",
    "wof:name":"Las Nuevas Guacamayas",
    "wof:placetype":"locality",
    "wof:population":21
},
  "geometry": {"coordinates":[-93.0475,15.57556],"type":"Point"}
}