{
  "type": "Feature",
  "properties": {
    "gn:admin1_code":"25",
    "gn:admin2_code":"9.0",
    "gn:asciiname":"Las Higueras",
    "gn:country_code":"MX",
    "gn:dem":208,
    "gn:feature_class":"P",
    "gn:feature_code":"PPL",
    "gn:name":"Las Higueras",
    "gn:population":1,
    "gn:timezone":"America/Mazatlan",
    "iso:country":"MX",
    "name:und_x_variant":[
        "Higueras"
    ],
    "wof:name":"Las Higueras",
    "wof:placetype":"locality",
    "wof:population":1
},
  "geometry": {"coordinates":[-105.64525999999999,22.89913],"type":"Point"}
}