{
  "type": "Feature",
  "properties": {
    "gn:admin1_code":"26",
    "gn:admin2_code":"2",
    "gn:asciiname":"La Rancheta del Alamito",
    "gn:country_code":"MX",
    "gn:dem":1273,
    "gn:feature_class":"P",
    "gn:feature_code":"PPL",
    "gn:name":"La Rancheta del Alamito",
    "gn:population":12,
    "gn:timezone":"America/Hermosillo",
    "iso:country":"MX",
    "wof:name":"La Rancheta del Alamito",
    "wof:placetype":"locality",
    "wof:population":12
},
  "geometry": {"coordinates":[-109.50082999999999,31.29778],"type":"Point"}
}