{
  "type": "Feature",
  "properties": {
    "gn:admin1_code":"16.0",
    "gn:admin2_code":"96.0",
    "gn:asciiname":"Mata de Platano",
    "gn:country_code":"MX",
    "gn:dem":1026,
    "gn:feature_class":"P",
    "gn:feature_code":"PPL",
    "gn:name":"Mata de Pl\u00e1tano",
    "gn:population":11,
    "gn:timezone":"America/Mexico_City",
    "iso:country":"MX",
    "wof:name":"Mata de Platano",
    "wof:placetype":"locality",
    "wof:population":11
},
  "geometry": {"coordinates":[-102.30695,18.57722],"type":"Point"}
}