{
  "type": "Feature",
  "properties": {
    "gn:admin1_code":"5",
    "gn:admin2_code":"34",
    "gn:asciiname":"El Azufre",
    "gn:country_code":"MX",
    "gn:dem":649,
    "gn:feature_class":"P",
    "gn:feature_code":"PPL",
    "gn:name":"El Azufre",
    "gn:population":9,
    "gn:timezone":"America/Mexico_City",
    "iso:country":"MX",
    "wof:name":"El Azufre",
    "wof:placetype":"locality",
    "wof:population":9
},
  "geometry": {"coordinates":[-92.14778,15.65128],"type":"Point"}
}