{
  "type": "Feature",
  "properties": {
    "gn:admin1_code":"30",
    "gn:admin2_code":"183.0",
    "gn:asciiname":"Vega de San Pedro",
    "gn:country_code":"MX",
    "gn:dem":185,
    "gn:feature_class":"P",
    "gn:feature_code":"PPL",
    "gn:name":"Vega de San Pedro",
    "gn:population":0,
    "gn:timezone":"America/Mexico_City",
    "iso:country":"MX",
    "wof:name":"Vega de San Pedro",
    "wof:placetype":"locality"
},
  "geometry": {"coordinates":[-97.16667,20.01667],"type":"Point"}
}