{
  "type": "Feature",
  "properties": {
    "gn:admin1_code":"25",
    "gn:admin2_code":"3.0",
    "gn:asciiname":"Los Arrayanes (Arroyo de la Higuera)",
    "gn:country_code":"MX",
    "gn:dem":712,
    "gn:feature_class":"P",
    "gn:feature_code":"PPL",
    "gn:name":"Los Arrayanes (Arroyo de la Higuera)",
    "gn:population":9,
    "gn:timezone":"America/Mazatlan",
    "iso:country":"MX",
    "wof:name":"Los Arrayanes (Arroyo de la Higuera)",
    "wof:placetype":"locality",
    "wof:population":9
},
  "geometry": {"coordinates":[-107.37009999999999,25.97096],"type":"Point"}
}