{
  "type": "Feature",
  "properties": {
    "gn:admin1_code":"30",
    "gn:admin2_code":"148.0",
    "gn:asciiname":"Tranca Negra",
    "gn:country_code":"MX",
    "gn:dem":68,
    "gn:feature_class":"P",
    "gn:feature_code":"PPL",
    "gn:name":"Tranca Negra",
    "gn:population":63,
    "gn:timezone":"America/Mexico_City",
    "iso:country":"MX",
    "wof:name":"Tranca Negra",
    "wof:placetype":"locality",
    "wof:population":63
},
  "geometry": {"coordinates":[-96.35666999999999,19.01639],"type":"Point"}
}