{
  "type": "Feature",
  "properties": {
    "gn:admin1_code":"19",
    "gn:admin2_code":"38.0",
    "gn:asciiname":"El Granjeno",
    "gn:country_code":"MX",
    "gn:dem":442,
    "gn:feature_class":"P",
    "gn:feature_code":"PPL",
    "gn:name":"El Granjeno",
    "gn:population":0,
    "gn:timezone":"America/Monterrey",
    "iso:country":"MX",
    "name:spa_x_preferred":[
        "El Granjeno"
    ],
    "wof:name":"El Granjeno",
    "wof:placetype":"locality"
},
  "geometry": {"coordinates":[-99.70986000000001,25.01249],"type":"Point"}
}