{
  "type": "Feature",
  "properties": {
    "gn:admin1_code":"24",
    "gn:admin2_code":"51.0",
    "gn:asciiname":"Lolita [Restaurante]",
    "gn:country_code":"MX",
    "gn:dem":1692,
    "gn:feature_class":"P",
    "gn:feature_code":"PPL",
    "gn:name":"Lolita [Restaurante]",
    "gn:population":5,
    "gn:timezone":"America/Mexico_City",
    "iso:country":"MX",
    "wof:name":"Lolita [Restaurante]",
    "wof:placetype":"locality",
    "wof:population":5
},
  "geometry": {"coordinates":[-100.69499999999999,22.43667],"type":"Point"}
}