{
  "type": "Feature",
  "properties": {
    "gn:admin1_code":"24",
    "gn:admin2_code":"24.0",
    "gn:asciiname":"La Tapona",
    "gn:country_code":"MX",
    "gn:dem":1120,
    "gn:feature_class":"P",
    "gn:feature_code":"PPL",
    "gn:name":"La Tapona",
    "gn:population":528,
    "gn:timezone":"America/Mexico_City",
    "iso:country":"MX",
    "wof:name":"La Tapona",
    "wof:placetype":"locality",
    "wof:population":528
},
  "geometry": {"coordinates":[-100.17778,21.99472],"type":"Point"}
}