{
  "type": "Feature",
  "properties": {
    "gn:admin1_code":"30.0",
    "gn:admin2_code":"123.0",
    "gn:asciiname":"Las Dos B",
    "gn:country_code":"MX",
    "gn:dem":27,
    "gn:feature_class":"P",
    "gn:feature_code":"PPL",
    "gn:name":"Las Dos B",
    "gn:population":0,
    "gn:timezone":"America/Mexico_City",
    "iso:country":"MX",
    "name:spa_x_preferred":[
        "Las Dos B"
    ],
    "wof:name":"Las Dos B",
    "wof:placetype":"locality"
},
  "geometry": {"coordinates":[-98.53728,21.90206],"type":"Point"}
}