{
  "type": "Feature",
  "properties": {
    "gn:admin1_code":"5",
    "gn:admin2_code":"81.0",
    "gn:asciiname":"Tepeyac",
    "gn:country_code":"MX",
    "gn:dem":460,
    "gn:feature_class":"P",
    "gn:feature_code":"PPL",
    "gn:name":"Tepeyac",
    "gn:population":195,
    "gn:timezone":"America/Mexico_City",
    "iso:country":"MX",
    "name:ces_x_preferred":[
        "Tepeyac"
    ],
    "name:deu_x_preferred":[
        "Tepeyac"
    ],
    "name:epo_x_preferred":[
        "Tepejako"
    ],
    "name:eus_x_preferred":[
        "Tepeyac"
    ],
    "name:fra_x_preferred":[
        "Tepeyac"
    ],
    "name:hun_x_preferred":[
        "Tepeyac"
    ],
    "name:ita_x_preferred":[
        "Tepeyac"
    ],
    "name:nor_x_preferred":[
        "Tepeyac"
    ],
    "name:por_x_preferred":[
        "Tepeyac"
    ],
    "name:swe_x_preferred":[
        "Tepeyac"
    ],
    "wof:name":"Tepeyac",
    "wof:placetype":"locality",
    "wof:population":195
},
  "geometry": {"coordinates":[-92.52889,17.13417],"type":"Point"}
}