{
  "type": "Feature",
  "properties": {
    "gn:admin1_code":"32",
    "gn:admin2_code":"21.0",
    "gn:asciiname":"Carretas (El Caracol)",
    "gn:country_code":"MX",
    "gn:dem":1625,
    "gn:feature_class":"P",
    "gn:feature_code":"PPL",
    "gn:name":"Carretas (El Caracol)",
    "gn:population":186,
    "gn:timezone":"America/Mexico_City",
    "iso:country":"MX",
    "wof:name":"Carretas (El Caracol)",
    "wof:placetype":"locality",
    "wof:population":186
},
  "geometry": {"coordinates":[-103.91,23.10528],"type":"Point"}
}