{
  "type": "Feature",
  "properties": {
    "gn:admin1_code":"18",
    "gn:admin2_code":"5.0",
    "gn:asciiname":"El Prudencial",
    "gn:country_code":"MX",
    "gn:dem":1872,
    "gn:feature_class":"P",
    "gn:feature_code":"PPL",
    "gn:name":"El Prudencial",
    "gn:population":8,
    "gn:timezone":"America/Mazatlan",
    "iso:country":"MX",
    "wof:name":"El Prudencial",
    "wof:placetype":"locality",
    "wof:population":8
},
  "geometry": {"coordinates":[-105.15778,22.82389],"type":"Point"}
}