{
  "type": "Feature",
  "properties": {
    "gn:admin1_code":"26.0",
    "gn:admin2_code":"64.0",
    "gn:asciiname":"El Ocuca",
    "gn:country_code":"MX",
    "gn:dem":593,
    "gn:feature_class":"P",
    "gn:feature_code":"PPL",
    "gn:name":"El Ocuca",
    "gn:population":0,
    "gn:timezone":"America/Hermosillo",
    "iso:country":"MX",
    "name:und_x_variant":[
        "Ocuca",
        "El Ocuca"
    ],
    "wof:name":"El Ocuca",
    "wof:placetype":"locality"
},
  "geometry": {"coordinates":[-111.43364,30.58544],"type":"Point"}
}