{
  "type": "Feature",
  "properties": {
    "gn:admin1_code":"7",
    "gn:admin2_code":"10.0",
    "gn:asciiname":"El Vivero",
    "gn:country_code":"MX",
    "gn:dem":532,
    "gn:feature_class":"P",
    "gn:feature_code":"PPL",
    "gn:name":"El Vivero",
    "gn:population":5,
    "gn:timezone":"America/Monterrey",
    "iso:country":"MX",
    "wof:name":"El Vivero",
    "wof:placetype":"locality",
    "wof:population":5
},
  "geometry": {"coordinates":[-101.50494,26.99054000000001],"type":"Point"}
}