{
  "type": "Feature",
  "properties": {
    "gn:admin1_code":"18",
    "gn:admin2_code":"17.0",
    "gn:asciiname":"Puga",
    "gn:country_code":"MX",
    "gn:dem":724,
    "gn:feature_class":"P",
    "gn:feature_code":"PPL",
    "gn:name":"Puga",
    "gn:population":6361,
    "gn:timezone":"America/Mazatlan",
    "iso:country":"MX",
    "wof:name":"Puga",
    "wof:placetype":"locality",
    "wof:population":6361
},
  "geometry": {"coordinates":[-104.82317999999999,21.58443],"type":"Point"}
}