{
  "type": "Feature",
  "properties": {
    "gn:admin1_code":"1.0",
    "gn:admin2_code":"7.0",
    "gn:asciiname":"Mirasoles",
    "gn:country_code":"MX",
    "gn:dem":2270,
    "gn:feature_class":"P",
    "gn:feature_code":"PPL",
    "gn:name":"Mirasoles",
    "gn:population":0,
    "gn:timezone":"America/Mexico_City",
    "iso:country":"MX",
    "name:spa_x_preferred":[
        "Mirasoles"
    ],
    "wof:name":"Mirasoles",
    "wof:placetype":"locality"
},
  "geometry": {"coordinates":[-102.43186,22.30744],"type":"Point"}
}