{
  "type": "Feature",
  "properties": {
    "gn:admin1_code":"12",
    "gn:admin2_code":"78.0",
    "gn:asciiname":"Rancho Juquila de los Pinos",
    "gn:country_code":"MX",
    "gn:dem":1463,
    "gn:feature_class":"P",
    "gn:feature_code":"PPL",
    "gn:name":"Rancho Juquila de los Pinos",
    "gn:population":5,
    "gn:timezone":"America/Mexico_City",
    "iso:country":"MX",
    "wof:name":"Rancho Juquila de los Pinos",
    "wof:placetype":"locality",
    "wof:population":5
},
  "geometry": {"coordinates":[-98.30028,17.10028],"type":"Point"}
}