{
  "type": "Feature",
  "properties": {
    "gn:admin1_code":"20",
    "gn:admin2_code":"36.0",
    "gn:asciiname":"Los Pinos (La Esmeralda)",
    "gn:country_code":"MX",
    "gn:dem":1176,
    "gn:feature_class":"P",
    "gn:feature_code":"PPL",
    "gn:name":"Los Pinos (La Esmeralda)",
    "gn:population":7,
    "gn:timezone":"America/Mexico_City",
    "iso:country":"MX",
    "wof:name":"Los Pinos (La Esmeralda)",
    "wof:placetype":"locality",
    "wof:population":7
},
  "geometry": {"coordinates":[-95.42722000000001,16.77528],"type":"Point"}
}