{
  "type": "Feature",
  "properties": {
    "gn:admin1_code":"30",
    "gn:admin2_code":"95.0",
    "gn:asciiname":"El Tacahuite",
    "gn:country_code":"MX",
    "gn:dem":591,
    "gn:feature_class":"P",
    "gn:feature_code":"PPL",
    "gn:name":"El Tacahuite",
    "gn:population":217,
    "gn:timezone":"America/Mexico_City",
    "iso:country":"MX",
    "wof:name":"El Tacahuite",
    "wof:placetype":"locality",
    "wof:population":217
},
  "geometry": {"coordinates":[-96.65861,19.82583],"type":"Point"}
}