{
  "type": "Feature",
  "properties": {
    "gn:admin1_code":"20",
    "gn:admin2_code":"227.0",
    "gn:asciiname":"Loma Cuache",
    "gn:country_code":"MX",
    "gn:dem":1596,
    "gn:feature_class":"P",
    "gn:feature_code":"PPL",
    "gn:name":"Loma Cuache",
    "gn:population":87,
    "gn:timezone":"America/Mexico_City",
    "iso:country":"MX",
    "wof:name":"Loma Cuache",
    "wof:placetype":"locality",
    "wof:population":87
},
  "geometry": {"coordinates":[-96.80389,17.13917],"type":"Point"}
}