{
  "type": "Feature",
  "properties": {
    "gn:admin1_code":"19",
    "gn:admin2_code":"22.0",
    "gn:asciiname":"Los Gringos",
    "gn:country_code":"MX",
    "gn:dem":201,
    "gn:feature_class":"P",
    "gn:feature_code":"PPL",
    "gn:name":"Los Gringos",
    "gn:population":0,
    "gn:timezone":"America/Monterrey",
    "iso:country":"MX",
    "name:spa_x_preferred":[
        "Los Gringos"
    ],
    "wof:name":"Los Gringos",
    "wof:placetype":"locality"
},
  "geometry": {"coordinates":[-99.36629000000001,25.40108],"type":"Point"}
}