{
  "type": "Feature",
  "properties": {
    "gn:admin1_code":"19",
    "gn:admin2_code":"17",
    "gn:asciiname":"Las Placetas",
    "gn:country_code":"MX",
    "gn:dem":2330,
    "gn:feature_class":"P",
    "gn:feature_code":"PPL",
    "gn:name":"Las Placetas",
    "gn:population":17,
    "gn:timezone":"America/Monterrey",
    "iso:country":"MX",
    "wof:name":"Las Placetas",
    "wof:placetype":"locality",
    "wof:population":17
},
  "geometry": {"coordinates":[-100.21722,24.92007000000001],"type":"Point"}
}