{
  "type": "Feature",
  "properties": {
    "gn:admin1_code":"26",
    "gn:admin2_code":"30.0",
    "gn:asciiname":"San Antonio Zacaton",
    "gn:country_code":"MX",
    "gn:dem":294,
    "gn:feature_class":"P",
    "gn:feature_code":"PPL",
    "gn:name":"San Antonio Zacat\u00f3n",
    "gn:population":0,
    "gn:timezone":"America/Hermosillo",
    "iso:country":"MX",
    "name:spa_x_preferred":[
        "San Antonio Zacat\u00f3n"
    ],
    "wof:name":"San Antonio Zacaton",
    "wof:placetype":"locality"
},
  "geometry": {"coordinates":[-110.84663999999999,29.28907],"type":"Point"}
}