{
  "type": "Feature",
  "properties": {
    "gn:admin1_code":"15",
    "gn:admin2_code":"21.0",
    "gn:asciiname":"Las Jaras",
    "gn:country_code":"MX",
    "gn:dem":3196,
    "gn:feature_class":"P",
    "gn:feature_code":"PPL",
    "gn:name":"Las Jaras",
    "gn:population":85,
    "gn:timezone":"America/Mexico_City",
    "iso:country":"MX",
    "wof:name":"Las Jaras",
    "wof:placetype":"locality",
    "wof:population":85
},
  "geometry": {"coordinates":[-99.80086,19.04876],"type":"Point"}
}