{
  "type": "Feature",
  "properties": {
    "gn:admin1_code":"26",
    "gn:admin2_code":"66.0",
    "gn:asciiname":"El Prado",
    "gn:country_code":"MX",
    "gn:dem":444,
    "gn:feature_class":"P",
    "gn:feature_code":"PPL",
    "gn:name":"El Prado",
    "gn:population":5,
    "gn:timezone":"America/Hermosillo",
    "iso:country":"MX",
    "name:ceb_x_preferred":[
        "El Prado"
    ],
    "name:spa_x_preferred":[
        "El Prado"
    ],
    "name:srp_x_preferred":[
        "\u0415\u043b \u041f\u0440\u0430\u0434\u043e"
    ],
    "name:swe_x_preferred":[
        "El Prado"
    ],
    "wof:name":"El Prado",
    "wof:placetype":"locality",
    "wof:population":5
},
  "geometry": {"coordinates":[-110.2975,29.435],"type":"Point"}
}