{
  "type": "Feature",
  "properties": {
    "gn:admin1_code":"2",
    "gn:admin2_code":"2.0",
    "gn:asciiname":"Familia Aguirre (Ejido San Luis Potosi)",
    "gn:country_code":"MX",
    "gn:dem":17,
    "gn:feature_class":"P",
    "gn:feature_code":"PPL",
    "gn:name":"Familia Aguirre (Ejido San Luis Potos\u00ed)",
    "gn:population":5,
    "gn:timezone":"America/Tijuana",
    "iso:country":"MX",
    "name:und_x_variant":[
        "Familia Aguirre (Ejido San Luis Potos\u00ed)"
    ],
    "wof:name":"Familia Aguirre (Ejido San Luis Potosi)",
    "wof:placetype":"locality",
    "wof:population":5
},
  "geometry": {"coordinates":[-115.10389000000001,32.51028],"type":"Point"}
}