{
  "type": "Feature",
  "properties": {
    "gn:admin1_code":"24",
    "gn:admin2_code":"20.0",
    "gn:asciiname":"Paso Blanco",
    "gn:country_code":"MX",
    "gn:dem":1808,
    "gn:feature_class":"P",
    "gn:feature_code":"PPL",
    "gn:name":"Paso Blanco",
    "gn:population":0,
    "gn:timezone":"America/Mexico_City",
    "iso:country":"MX",
    "name:spa_x_preferred":[
        "Paso Blanco"
    ],
    "wof:name":"Paso Blanco",
    "wof:placetype":"locality"
},
  "geometry": {"coordinates":[-100.75592,23.55705],"type":"Point"}
}