{
  "type": "Feature",
  "properties": {
    "gn:admin1_code":"11",
    "gn:admin2_code":"23.0",
    "gn:asciiname":"Cruces de Morales",
    "gn:country_code":"MX",
    "gn:dem":1833,
    "gn:feature_class":"P",
    "gn:feature_code":"PPL",
    "gn:name":"Cruces de Morales",
    "gn:population":0,
    "gn:timezone":"America/Mexico_City",
    "iso:country":"MX",
    "name:spa_x_preferred":[
        "Cruces de Morales"
    ],
    "name:spa_x_variant":[
        "Las Cruces"
    ],
    "wof:name":"Cruces de Morales",
    "wof:placetype":"locality"
},
  "geometry": {"coordinates":[-101.75136999999999,20.2853],"type":"Point"}
}