{
  "type": "Feature",
  "properties": {
    "gn:admin1_code":"14",
    "gn:admin2_code":"21.0",
    "gn:asciiname":"Coyamel (El Coyame)",
    "gn:country_code":"MX",
    "gn:dem":323,
    "gn:feature_class":"P",
    "gn:feature_code":"PPL",
    "gn:name":"Coyamel (El Coyame)",
    "gn:population":528,
    "gn:timezone":"America/Mexico_City",
    "iso:country":"MX",
    "wof:name":"Coyamel (El Coyame)",
    "wof:placetype":"locality",
    "wof:population":528
},
  "geometry": {"coordinates":[-104.52306,19.49806],"type":"Point"}
}