{
  "type": "Feature",
  "properties": {
    "gn:admin1_code":"5",
    "gn:admin2_code":"20",
    "gn:asciiname":"San Pedro",
    "gn:country_code":"MX",
    "gn:dem":1693,
    "gn:feature_class":"P",
    "gn:feature_code":"PPL",
    "gn:name":"San Pedro",
    "gn:population":44,
    "gn:timezone":"America/Mexico_City",
    "iso:country":"MX",
    "wof:name":"San Pedro",
    "wof:placetype":"locality",
    "wof:population":44
},
  "geometry": {"coordinates":[-92.88948000000001,15.71251],"type":"Point"}
}