{
  "type": "Feature",
  "properties": {
    "gn:admin1_code":"10.0",
    "gn:admin2_code":"19.0",
    "gn:asciiname":"Mesa del Jagueey",
    "gn:country_code":"MX",
    "gn:dem":1532,
    "gn:feature_class":"P",
    "gn:feature_code":"PPL",
    "gn:name":"Mesa del Jag\u00fcey",
    "gn:population":0,
    "gn:timezone":"America/Monterrey",
    "iso:country":"MX",
    "name:spa_x_preferred":[
        "Mesa del Jag\u00fcey"
    ],
    "wof:name":"Mesa del Jagueey",
    "wof:placetype":"locality"
},
  "geometry": {"coordinates":[-106.13984000000001,24.58437],"type":"Point"}
}