{
  "type": "Feature",
  "properties": {
    "gn:admin1_code":"21",
    "gn:admin2_code":"212.0",
    "gn:asciiname":"Pantijacan",
    "gn:country_code":"MX",
    "gn:dem":1972,
    "gn:feature_class":"P",
    "gn:feature_code":"PPL",
    "gn:name":"Pantijacan",
    "gn:population":54,
    "gn:timezone":"America/Mexico_City",
    "iso:country":"MX",
    "wof:name":"Pantijacan",
    "wof:placetype":"locality",
    "wof:population":54
},
  "geometry": {"coordinates":[-97.6786,19.70602],"type":"Point"}
}