{
  "type": "Feature",
  "properties": {
    "gn:admin1_code":"8",
    "gn:admin2_code":"9.0",
    "gn:asciiname":"Mocambo Dos",
    "gn:country_code":"MX",
    "gn:dem":15,
    "gn:feature_class":"P",
    "gn:feature_code":"PPL",
    "gn:name":"Mocambo Dos",
    "gn:population":8,
    "gn:timezone":"America/Mexico_City",
    "iso:country":"MX",
    "wof:name":"Mocambo Dos",
    "wof:placetype":"locality",
    "wof:population":8
},
  "geometry": {"coordinates":[-103.84111,18.82833],"type":"Point"}
}