{
  "type": "Feature",
  "properties": {
    "gn:admin1_code":"4",
    "gn:admin2_code":"3.0",
    "gn:asciiname":"Carlos Salinas de Gortari",
    "gn:country_code":"MX",
    "gn:dem":1,
    "gn:feature_class":"P",
    "gn:feature_code":"PPL",
    "gn:name":"Carlos Salinas de Gortari",
    "gn:population":142,
    "gn:timezone":"America/Merida",
    "iso:country":"MX",
    "wof:name":"Carlos Salinas de Gortari",
    "wof:placetype":"locality",
    "wof:population":142
},
  "geometry": {"coordinates":[-92.27222,18.62],"type":"Point"}
}