{
  "type": "Feature",
  "properties": {
    "gn:admin1_code":"4",
    "gn:admin2_code":"3.0",
    "gn:asciiname":"Carlos Salinas de Gortari",
    "gn:country_code":"MX",
    "gn:dem":1,
    "gn:feature_class":"P",
    "gn:feature_code":"PPL",
    "gn:name":"Carlos Salinas de Gortari",
    "gn:population":142,
    "gn:timezone":"America/Merida",
    "iso:country":"MX",
    "name:ara_x_preferred":[
        "\u0643\u0627\u0631\u0644\u0648\u0633 \u0633\u0627\u0644\u064a\u0646\u0627\u0633 \u062f\u064a \u063a\u0648\u0631\u062a\u0627\u0631\u064a"
    ],
    "name:bel_x_preferred":[
        "\u041a\u0430\u0440\u043b\u0430\u0441 \u0421\u0430\u043b\u0456\u043d\u0430\u0441"
    ],
    "name:fas_x_preferred":[
        "\u06a9\u0627\u0631\u0644\u0648\u0633 \u0633\u0627\u0644\u06cc\u0646\u0627\u0633 \u062f \u06af\u0648\u0631\u062a\u0627\u0631\u06cc"
    ],
    "name:heb_x_preferred":[
        "\u05e7\u05e8\u05dc\u05d5\u05e1 \u05e1\u05dc\u05d9\u05e0\u05e1"
    ],
    "name:ita_x_preferred":[
        "Carlos Salinas"
    ],
    "name:kat_x_preferred":[
        "\u10d9\u10d0\u10e0\u10da\u10dd\u10e1 \u10e1\u10d0\u10da\u10d8\u10dc\u10d0\u10e1 \u10d3\u10d4 \u10d2\u10dd\u10e0\u10e2\u10d0\u10e0\u10d8"
    ],
    "name:kor_x_preferred":[
        "\uce74\ub97c\ub85c\uc2a4 \uc0b4\ub9ac\ub098\uc2a4 \ub370 \uace0\ub974\ud0c0\ub9ac"
    ],
    "name:mar_x_preferred":[
        "\u0915\u093e\u0930\u094d\u0932\u094b\u0938 \u0938\u0932\u093f\u0928\u093e\u0938"
    ],
    "name:nld_x_preferred":[
        "Carlos Salinas"
    ],
    "name:nor_x_preferred":[
        "Carlos Salinas"
    ],
    "name:swe_x_preferred":[
        "Carlos Salinas"
    ],
    "name:ukr_x_preferred":[
        "\u041a\u0430\u0440\u043b\u043e\u0441 \u0421\u0430\u043b\u0456\u043d\u0430\u0441 \u0434\u0435 \u0413\u043e\u0440\u0442\u0430\u0440\u0456"
    ],
    "wof:name":"Carlos Salinas de Gortari",
    "wof:placetype":"locality",
    "wof:population":142
},
  "geometry": {"coordinates":[-92.27222,18.62],"type":"Point"}
}