{
  "type": "Feature",
  "properties": {
    "gn:admin1_code":"26",
    "gn:admin2_code":"17.0",
    "gn:asciiname":"Rodolfo Campodonico",
    "gn:country_code":"MX",
    "gn:dem":16,
    "gn:elevation":"14.0",
    "gn:feature_class":"P",
    "gn:feature_code":"PPL",
    "gn:name":"Rodolfo Campod\u00f3nico",
    "gn:population":325,
    "gn:timezone":"America/Hermosillo",
    "iso:country":"MX",
    "wof:name":"Rodolfo Campodonico",
    "wof:placetype":"locality",
    "wof:population":325
},
  "geometry": {"coordinates":[-113.01175000000001,30.95538],"type":"Point"}
}