{
  "type": "Feature",
  "properties": {
    "gn:admin1_code":"32",
    "gn:admin2_code":"10.0",
    "gn:asciiname":"Maria de Jesus",
    "gn:country_code":"MX",
    "gn:dem":2068,
    "gn:feature_class":"P",
    "gn:feature_code":"PPL",
    "gn:name":"Mar\u00eda de Jes\u00fas",
    "gn:population":0,
    "gn:timezone":"America/Mexico_City",
    "iso:country":"MX",
    "name:spa_x_preferred":[
        "Mar\u00eda de Jes\u00fas"
    ],
    "wof:name":"Maria de Jesus",
    "wof:placetype":"locality"
},
  "geometry": {"coordinates":[-102.96434000000001,23.35433],"type":"Point"}
}