{
  "type": "Feature",
  "properties": {
    "gn:admin1_code":"5",
    "gn:admin2_code":"99.0",
    "gn:asciiname":"El Porvenir Agrarista",
    "gn:country_code":"MX",
    "gn:dem":1495,
    "gn:feature_class":"P",
    "gn:feature_code":"PPL",
    "gn:name":"El Porvenir Agrarista",
    "gn:population":0,
    "gn:timezone":"America/Mexico_City",
    "iso:country":"MX",
    "name:spa_x_preferred":[
        "Porvenir Agrarista"
    ],
    "name:spa_x_variant":[
        "El Porvenir Agrarista"
    ],
    "wof:name":"El Porvenir Agrarista",
    "wof:placetype":"locality"
},
  "geometry": {"coordinates":[-91.83575,16.16465],"type":"Point"}
}