{
  "type": "Feature",
  "properties": {
    "gn:admin1_code":"28.0",
    "gn:admin2_code":"21.0",
    "gn:asciiname":"El Pintor",
    "gn:country_code":"MX",
    "gn:dem":71,
    "gn:feature_class":"P",
    "gn:feature_code":"PPL",
    "gn:name":"El Pintor",
    "gn:population":0,
    "gn:timezone":"America/Monterrey",
    "iso:country":"MX",
    "name:deu_x_preferred":[
        "El Pintor"
    ],
    "name:fin_x_preferred":[
        "El Pintor"
    ],
    "name:fra_x_preferred":[
        "El Pintor"
    ],
    "name:glg_x_preferred":[
        "El Pintor"
    ],
    "name:ita_x_preferred":[
        "El Pintor"
    ],
    "name:por_x_preferred":[
        "El Pintor"
    ],
    "name:spa_x_preferred":[
        "El Pintor"
    ],
    "wof:name":"El Pintor",
    "wof:placetype":"locality"
},
  "geometry": {"coordinates":[-99.02957000000001,22.83588],"type":"Point"}
}