{
  "type": "Feature",
  "properties": {
    "gn:admin1_code":"10.0",
    "gn:admin2_code":"1.0",
    "gn:asciiname":"Corona",
    "gn:country_code":"MX",
    "gn:dem":1915,
    "gn:feature_class":"P",
    "gn:feature_code":"PPL",
    "gn:name":"Corona",
    "gn:population":0,
    "gn:timezone":"America/Monterrey",
    "iso:country":"MX",
    "name:spa_x_preferred":[
        "Corona"
    ],
    "wof:name":"Corona",
    "wof:placetype":"locality"
},
  "geometry": {"coordinates":[-104.71444,24.35482],"type":"Point"}
}