{
  "type": "Feature",
  "properties": {
    "gn:admin1_code":"14",
    "gn:admin2_code":"84.0",
    "gn:asciiname":"El Izote",
    "gn:country_code":"MX",
    "gn:dem":1272,
    "gn:feature_class":"P",
    "gn:feature_code":"PPL",
    "gn:name":"El Izote",
    "gn:population":7,
    "gn:timezone":"America/Mexico_City",
    "iso:country":"MX",
    "wof:name":"El Izote",
    "wof:placetype":"locality",
    "wof:population":7
},
  "geometry": {"coordinates":[-104.80222000000001,20.32778],"type":"Point"}
}