{
  "type": "Feature",
  "properties": {
    "gn:admin1_code":"30",
    "gn:admin2_code":"16.0",
    "gn:asciiname":"La Catalina",
    "gn:country_code":"MX",
    "gn:dem":26,
    "gn:feature_class":"P",
    "gn:feature_code":"PPL",
    "gn:name":"La Catalina",
    "gn:population":0,
    "gn:timezone":"America/Mexico_City",
    "iso:country":"MX",
    "name:spa_x_preferred":[
        "La Catalina"
    ],
    "wof:name":"La Catalina",
    "wof:placetype":"locality"
},
  "geometry": {"coordinates":[-96.28919999999999,19.29049],"type":"Point"}
}