{
  "type": "Feature",
  "properties": {
    "gn:admin1_code":"24",
    "gn:admin2_code":"14.0",
    "gn:asciiname":"Barrio del Zocote",
    "gn:country_code":"MX",
    "gn:dem":172,
    "gn:feature_class":"P",
    "gn:feature_code":"PPL",
    "gn:name":"Barrio del Zocote",
    "gn:population":0,
    "gn:timezone":"America/Mexico_City",
    "iso:country":"MX",
    "name:spa_x_preferred":[
        "Barrio del Zocote"
    ],
    "wof:name":"Barrio del Zocote",
    "wof:placetype":"locality"
},
  "geometry": {"coordinates":[-98.91057000000001,21.54255],"type":"Point"}
}