{
  "type": "Feature",
  "properties": {
    "gn:admin1_code":"5",
    "gn:admin2_code":"90.0",
    "gn:asciiname":"Palestina",
    "gn:country_code":"MX",
    "gn:dem":1295,
    "gn:feature_class":"P",
    "gn:feature_code":"PPL",
    "gn:name":"Palestina",
    "gn:population":144,
    "gn:timezone":"America/Mexico_City",
    "iso:country":"MX",
    "wof:name":"Palestina",
    "wof:placetype":"locality",
    "wof:population":144
},
  "geometry": {"coordinates":[-93.12582999999999,17.24167000000001],"type":"Point"}
}