{
  "type": "Feature",
  "properties": {
    "gn:admin1_code":"21.0",
    "gn:admin2_code":"198.0",
    "gn:asciiname":"Texcatlan",
    "gn:country_code":"MX",
    "gn:dem":1119,
    "gn:feature_class":"P",
    "gn:feature_code":"PPL",
    "gn:name":"Texcatl\u00e1n",
    "gn:population":0,
    "gn:timezone":"America/Mexico_City",
    "iso:country":"MX",
    "name:spa_x_preferred":[
        "Texcatl\u00e1n"
    ],
    "wof:name":"Texcatlan",
    "wof:placetype":"locality"
},
  "geometry": {"coordinates":[-98.56769,18.12111],"type":"Point"}
}