{
  "type": "Feature",
  "properties": {
    "gn:admin1_code":"12.0",
    "gn:admin2_code":"16.0",
    "gn:asciiname":"Los Cascalotes",
    "gn:country_code":"MX",
    "gn:dem":249,
    "gn:feature_class":"P",
    "gn:feature_code":"PPL",
    "gn:name":"Los Cascalotes",
    "gn:population":0,
    "gn:timezone":"America/Mexico_City",
    "iso:country":"MX",
    "name:spa_x_preferred":[
        "Los Cascalotes"
    ],
    "wof:name":"Los Cascalotes",
    "wof:placetype":"locality"
},
  "geometry": {"coordinates":[-101.69051,18.26334],"type":"Point"}
}