{
  "type": "Feature",
  "properties": {
    "gn:admin1_code":"15",
    "gn:admin2_code":"65.0",
    "gn:asciiname":"Tlahuico",
    "gn:country_code":"MX",
    "gn:dem":2429,
    "gn:feature_class":"P",
    "gn:feature_code":"PPL",
    "gn:name":"Tlahuico",
    "gn:population":931,
    "gn:timezone":"America/Mexico_City",
    "iso:country":"MX",
    "wof:name":"Tlahuico",
    "wof:placetype":"locality",
    "wof:population":931
},
  "geometry": {"coordinates":[-98.75722,19.67111],"type":"Point"}
}