{
  "type": "Feature",
  "properties": {
    "gn:admin1_code":"28",
    "gn:admin2_code":"18.0",
    "gn:asciiname":"La Ceja de Caballeros",
    "gn:cc2":"MX",
    "gn:country_code":"MX",
    "gn:dem":194,
    "gn:feature_class":"P",
    "gn:feature_code":"PPL",
    "gn:name":"La Ceja de Caballeros",
    "gn:population":0,
    "gn:timezone":"America/Monterrey",
    "iso:country":"MX",
    "name:und_x_variant":[
        "Rancho La Ceja",
        "La Ceja",
        "Ceja de Caballeros",
        "La Ceja de Caballeros"
    ],
    "wof:name":"La Ceja de Caballeros",
    "wof:placetype":"locality"
},
  "geometry": {"coordinates":[-98.43333,24.28333],"type":"Point"}
}