{
  "type": "Feature",
  "properties": {
    "gn:admin1_code":"10.0",
    "gn:admin2_code":"5.0",
    "gn:asciiname":"El Toboso",
    "gn:country_code":"MX",
    "gn:dem":1887,
    "gn:feature_class":"P",
    "gn:feature_code":"PPL",
    "gn:name":"El Toboso",
    "gn:population":0,
    "gn:timezone":"America/Monterrey",
    "iso:country":"MX",
    "name:spa_x_preferred":[
        "El Toboso"
    ],
    "wof:name":"El Toboso",
    "wof:placetype":"locality"
},
  "geometry": {"coordinates":[-104.5778,24.273],"type":"Point"}
}