{
  "type": "Feature",
  "properties": {
    "gn:admin1_code":"10.0",
    "gn:admin2_code":"5.0",
    "gn:asciiname":"El Toboso",
    "gn:country_code":"MX",
    "gn:dem":1887,
    "gn:feature_class":"P",
    "gn:feature_code":"PPL",
    "gn:name":"El Toboso",
    "gn:population":0,
    "gn:timezone":"America/Monterrey",
    "iso:country":"MX",
    "name:ara_x_preferred":[
        "\u0627\u0644\u062a\u0648\u0628\u0648\u0633\u0648"
    ],
    "name:arg_x_preferred":[
        "El Toboso"
    ],
    "name:ast_x_preferred":[
        "El Toboso"
    ],
    "name:azb_x_preferred":[
        "\u0627\u0644 \u062a\u0628\u0633\u0648"
    ],
    "name:cat_x_preferred":[
        "El Toboso"
    ],
    "name:ceb_x_preferred":[
        "El Toboso"
    ],
    "name:deu_x_preferred":[
        "El Toboso"
    ],
    "name:epo_x_preferred":[
        "El Toboso"
    ],
    "name:eus_x_preferred":[
        "El Toboso"
    ],
    "name:fas_x_preferred":[
        "\u0627\u0644 \u062a\u0628\u0633\u0648"
    ],
    "name:fra_x_preferred":[
        "El Toboso"
    ],
    "name:hun_x_preferred":[
        "El Toboso"
    ],
    "name:hye_x_preferred":[
        "\u0537\u056c \u054f\u0578\u0562\u0578\u057d\u0578"
    ],
    "name:ina_x_preferred":[
        "El Toboso"
    ],
    "name:ita_x_preferred":[
        "El Toboso"
    ],
    "name:kaz_x_preferred":[
        "\u042d\u043b\u044c-\u0422\u043e\u0431\u043e\u0441\u043e"
    ],
    "name:msa_x_preferred":[
        "El Toboso"
    ],
    "name:nld_x_preferred":[
        "El Toboso"
    ],
    "name:oci_x_preferred":[
        "El Toboso"
    ],
    "name:pol_x_preferred":[
        "El Toboso"
    ],
    "name:por_x_preferred":[
        "El Toboso"
    ],
    "name:ron_x_preferred":[
        "El Toboso"
    ],
    "name:rus_x_preferred":[
        "\u042d\u043b\u044c-\u0422\u043e\u0431\u043e\u0441\u043e"
    ],
    "name:spa_x_preferred":[
        "El Toboso"
    ],
    "name:sqi_x_preferred":[
        "El Toboso"
    ],
    "name:swe_x_preferred":[
        "El Toboso"
    ],
    "name:ukr_x_preferred":[
        "\u0415\u043b\u044c-\u0422\u043e\u0431\u043e\u0441\u043e"
    ],
    "name:vie_x_preferred":[
        "El Toboso"
    ],
    "name:war_x_preferred":[
        "El Toboso"
    ],
    "name:zho_x_preferred":[
        "\u57c3\u5c14\u6258\u6c83\u7d22"
    ],
    "wof:name":"El Toboso",
    "wof:placetype":"locality"
},
  "geometry": {"coordinates":[-104.5778,24.273],"type":"Point"}
}