{
  "type": "Feature",
  "properties": {
    "gn:admin1_code":"15.0",
    "gn:admin2_code":"118.0",
    "gn:asciiname":"Valle de Zamarrero",
    "gn:country_code":"MX",
    "gn:dem":2716,
    "gn:feature_class":"P",
    "gn:feature_code":"PPL",
    "gn:name":"Valle de Zamarrero",
    "gn:population":0,
    "gn:timezone":"America/Mexico_City",
    "iso:country":"MX",
    "name:spa_x_preferred":[
        "Valle de Zamarrero"
    ],
    "wof:name":"Valle de Zamarrero",
    "wof:placetype":"locality"
},
  "geometry": {"coordinates":[-99.70761,19.30338],"type":"Point"}
}