{
  "type": "Feature",
  "properties": {
    "gn:admin1_code":"6.0",
    "gn:asciiname":"San Jose de Buenavista",
    "gn:country_code":"MX",
    "gn:dem":2020,
    "gn:feature_class":"P",
    "gn:feature_code":"PPL",
    "gn:name":"San Jos\u00e9 de Buenavista",
    "gn:population":0,
    "gn:timezone":"America/Chihuahua",
    "iso:country":"MX",
    "name:spa_x_preferred":[
        "San Jos\u00e9 de Buenavista"
    ],
    "wof:name":"San Jose de Buenavista",
    "wof:placetype":"locality"
},
  "geometry": {"coordinates":[-105.86982999999999,26.82521],"type":"Point"}
}