{
  "type": "Feature",
  "properties": {
    "gn:admin1_code":"5",
    "gn:admin2_code":"46.0",
    "gn:asciiname":"Palo Grande",
    "gn:country_code":"MX",
    "gn:dem":533,
    "gn:feature_class":"P",
    "gn:feature_code":"PPL",
    "gn:name":"Palo Grande",
    "gn:population":0,
    "gn:timezone":"America/Mexico_City",
    "iso:country":"MX",
    "name:ita_x_preferred":[
        "Palo Grande"
    ],
    "name:spa_x_preferred":[
        "Palo Grande"
    ],
    "name:zho_x_preferred":[
        "\u5e15\u6d1b\u683c\u5170\u5fb7"
    ],
    "wof:name":"Palo Grande",
    "wof:placetype":"locality"
},
  "geometry": {"coordinates":[-93.6173,16.67561],"type":"Point"}
}