{
  "type": "Feature",
  "properties": {
    "gn:admin1_code":"30.0",
    "gn:admin2_code":"134.0",
    "gn:asciiname":"El Rocio",
    "gn:country_code":"MX",
    "gn:dem":197,
    "gn:feature_class":"P",
    "gn:feature_code":"PPL",
    "gn:name":"El Roc\u00edo",
    "gn:population":0,
    "gn:timezone":"America/Mexico_City",
    "iso:country":"MX",
    "name:spa_x_preferred":[
        "El Roc\u00edo"
    ],
    "wof:name":"El Rocio",
    "wof:placetype":"locality"
},
  "geometry": {"coordinates":[-96.53868,19.34699],"type":"Point"}
}