{
  "type": "Feature",
  "properties": {
    "gn:admin1_code":"30",
    "gn:admin2_code":"72.0",
    "gn:asciiname":"Los Otates",
    "gn:cc2":"MX",
    "gn:country_code":"MX",
    "gn:dem":2640,
    "gn:feature_class":"P",
    "gn:feature_code":"PPL",
    "gn:name":"Los Otates",
    "gn:population":0,
    "gn:timezone":"America/Mexico_City",
    "iso:country":"MX",
    "name:und_x_variant":[
        "Otates",
        "Los Otates"
    ],
    "wof:name":"Los Otates",
    "wof:placetype":"locality"
},
  "geometry": {"coordinates":[-98.45,20.43333],"type":"Point"}
}