{
  "type": "Feature",
  "properties": {
    "gn:admin1_code":"5",
    "gn:admin2_code":"37.0",
    "gn:asciiname":"Canton los Suenos",
    "gn:country_code":"MX",
    "gn:dem":219,
    "gn:feature_class":"P",
    "gn:feature_code":"PPL",
    "gn:name":"Cant\u00f3n los Sue\u00f1os",
    "gn:population":0,
    "gn:timezone":"America/Mexico_City",
    "iso:country":"MX",
    "name:spa_x_preferred":[
        "Cant\u00f3n los Sue\u00f1os"
    ],
    "name:und_x_variant":[
        "Los Sue\u00f1os"
    ],
    "wof:name":"Canton los Suenos",
    "wof:placetype":"locality"
},
  "geometry": {"coordinates":[-92.36118,15.05622],"type":"Point"}
}