{
  "type": "Feature",
  "properties": {
    "gn:admin1_code":"10",
    "gn:admin2_code":"4.0",
    "gn:asciiname":"El Gavilan",
    "gn:country_code":"MX",
    "gn:dem":2120,
    "gn:feature_class":"P",
    "gn:feature_code":"PPL",
    "gn:name":"El Gavil\u00e1n",
    "gn:population":0,
    "gn:timezone":"America/Monterrey",
    "iso:country":"MX",
    "name:spa_x_preferred":[
        "El Gavil\u00e1n"
    ],
    "wof:name":"El Gavilan",
    "wof:placetype":"locality"
},
  "geometry": {"coordinates":[-103.60746,24.64421],"type":"Point"}
}