{
  "type": "Feature",
  "properties": {
    "gn:admin1_code":"6.0",
    "gn:admin2_code":"65.0",
    "gn:asciiname":"Pamorachi",
    "gn:country_code":"MX",
    "gn:dem":979,
    "gn:feature_class":"P",
    "gn:feature_code":"PPL",
    "gn:name":"Pamorachi",
    "gn:population":0,
    "gn:timezone":"America/Chihuahua",
    "iso:country":"MX",
    "name:spa_x_preferred":[
        "Pamorachi"
    ],
    "wof:name":"Pamorachi",
    "wof:placetype":"locality"
},
  "geometry": {"coordinates":[-107.84241000000002,27.4183],"type":"Point"}
}