{
  "type": "Feature",
  "properties": {
    "gn:admin1_code":"28",
    "gn:admin2_code":"41.0",
    "gn:asciiname":"Ojo Caliente",
    "gn:country_code":"MX",
    "gn:dem":372,
    "gn:feature_class":"P",
    "gn:feature_code":"PPL",
    "gn:name":"Ojo Caliente",
    "gn:population":4,
    "gn:timezone":"America/Monterrey",
    "iso:country":"MX",
    "wof:name":"Ojo Caliente",
    "wof:placetype":"locality",
    "wof:population":4
},
  "geometry": {"coordinates":[-99.09528,23.62111],"type":"Point"}
}