{
  "type": "Feature",
  "properties": {
    "gn:admin1_code":"11",
    "gn:admin2_code":"27",
    "gn:asciiname":"Familia Camacho Garcia",
    "gn:country_code":"MX",
    "gn:dem":1716,
    "gn:feature_class":"P",
    "gn:feature_code":"PPL",
    "gn:name":"Familia Camacho Garc\u00eda",
    "gn:population":31,
    "gn:timezone":"America/Mexico_City",
    "iso:country":"MX",
    "name:und_x_variant":[
        "Familia Camacho Garc\u00eda"
    ],
    "wof:name":"Familia Camacho Garcia",
    "wof:placetype":"locality",
    "wof:population":31
},
  "geometry": {"coordinates":[-101.22083000000001,20.64333],"type":"Point"}
}