{
  "type": "Feature",
  "properties": {
    "gn:admin1_code":"32",
    "gn:admin2_code":"14.0",
    "gn:asciiname":"San Lucas de Abajo",
    "gn:country_code":"MX",
    "gn:dem":1999,
    "gn:feature_class":"P",
    "gn:feature_code":"PPL",
    "gn:name":"San Lucas de Abajo",
    "gn:population":0,
    "gn:timezone":"America/Mexico_City",
    "iso:country":"MX",
    "name:spa_x_preferred":[
        "San Lucas de Abajo"
    ],
    "name:spa_x_variant":[
        "El Conejo"
    ],
    "name:und_x_variant":[
        "San Lucas"
    ],
    "wof:name":"San Lucas de Abajo",
    "wof:placetype":"locality"
},
  "geometry": {"coordinates":[-103.10108,24.19203],"type":"Point"}
}