{
  "type": "Feature",
  "properties": {
    "gn:admin1_code":"7",
    "gn:admin2_code":"9.0",
    "gn:asciiname":"Alberto Ibarra Moreno",
    "gn:country_code":"MX",
    "gn:dem":1108,
    "gn:feature_class":"P",
    "gn:feature_code":"PPL",
    "gn:name":"Alberto Ibarra Moreno",
    "gn:population":5,
    "gn:timezone":"America/Monterrey",
    "iso:country":"MX",
    "wof:name":"Alberto Ibarra Moreno",
    "wof:placetype":"locality",
    "wof:population":5
},
  "geometry": {"coordinates":[-103.27701999999999,25.82749],"type":"Point"}
}