{
  "type": "Feature",
  "properties": {
    "gn:admin1_code":"25",
    "gn:admin2_code":"1.0",
    "gn:asciiname":"Pajarola",
    "gn:country_code":"MX",
    "gn:dem":7,
    "gn:feature_class":"P",
    "gn:feature_code":"PPL",
    "gn:name":"Pajarola",
    "gn:population":0,
    "gn:timezone":"America/Mazatlan",
    "iso:country":"MX",
    "name:spa_x_preferred":[
        "Pajarola"
    ],
    "wof:name":"Pajarola",
    "wof:placetype":"locality"
},
  "geometry": {"coordinates":[-109.21857,25.78579],"type":"Point"}
}