{
  "type": "Feature",
  "properties": {
    "gn:admin1_code":"30.0",
    "gn:asciiname":"Ampliacion Francisco Villa",
    "gn:country_code":"MX",
    "gn:dem":59,
    "gn:feature_class":"P",
    "gn:feature_code":"PPL",
    "gn:name":"Ampliaci\u00f3n Francisco Villa",
    "gn:population":0,
    "gn:timezone":"America/Mexico_City",
    "iso:country":"MX",
    "name:spa_x_preferred":[
        "Ampliaci\u00f3n Francisco Villa"
    ],
    "wof:name":"Ampliacion Francisco Villa",
    "wof:placetype":"locality"
},
  "geometry": {"coordinates":[-97.52957000000001,20.76161],"type":"Point"}
}