{
  "type": "Feature",
  "properties": {
    "gn:admin1_code":"16",
    "gn:admin2_code":"97.0",
    "gn:asciiname":"Zihuatzio",
    "gn:country_code":"MX",
    "gn:dem":2219,
    "gn:feature_class":"P",
    "gn:feature_code":"PPL",
    "gn:name":"Zihuatzio",
    "gn:population":350,
    "gn:timezone":"America/Mexico_City",
    "iso:country":"MX",
    "wof:name":"Zihuatzio",
    "wof:placetype":"locality",
    "wof:population":350
},
  "geometry": {"coordinates":[-101.59278,19.16972],"type":"Point"}
}