{
  "type": "Feature",
  "properties": {
    "gn:admin1_code":"6.0",
    "gn:admin2_code":"11.0",
    "gn:asciiname":"El Venado",
    "gn:country_code":"MX",
    "gn:dem":1384,
    "gn:feature_class":"P",
    "gn:feature_code":"PPL",
    "gn:name":"El Venado",
    "gn:population":0,
    "gn:timezone":"America/Chihuahua",
    "iso:country":"MX",
    "name:spa_x_preferred":[
        "El Venado"
    ],
    "name:und_x_variant":[
        "Rancho El Venado"
    ],
    "wof:name":"El Venado",
    "wof:placetype":"locality"
},
  "geometry": {"coordinates":[-104.64824,27.7817],"type":"Point"}
}