{
  "type": "Feature",
  "properties": {
    "gn:admin1_code":"27",
    "gn:admin2_code":"4.0",
    "gn:asciiname":"Aztlan 2da. Seccion el Cuy",
    "gn:country_code":"MX",
    "gn:dem":9,
    "gn:feature_class":"P",
    "gn:feature_code":"PPL",
    "gn:name":"Aztl\u00e1n 2da. Secci\u00f3n el Cuy",
    "gn:population":65,
    "gn:timezone":"America/Mexico_City",
    "iso:country":"MX",
    "name:und_x_variant":[
        "Aztl\u00e1n 2da. Secci\u00f3n el Cuy"
    ],
    "wof:name":"Aztlan 2da. Seccion el Cuy",
    "wof:placetype":"locality",
    "wof:population":65
},
  "geometry": {"coordinates":[-92.69499999999999,18.05806],"type":"Point"}
}