{
  "type": "Feature",
  "properties": {
    "gn:admin1_code":"28.0",
    "gn:admin2_code":"21.0",
    "gn:asciiname":"Quinta Santa Rosa",
    "gn:country_code":"MX",
    "gn:dem":66,
    "gn:feature_class":"P",
    "gn:feature_code":"PPL",
    "gn:name":"Quinta Santa Rosa",
    "gn:population":3,
    "gn:timezone":"America/Monterrey",
    "iso:country":"MX",
    "name:spa_x_preferred":[
        "Quinta Santa Rosa"
    ],
    "wof:name":"Quinta Santa Rosa",
    "wof:placetype":"locality",
    "wof:population":3
},
  "geometry": {"coordinates":[-98.96111000000001,22.81917],"type":"Point"}
}