{
  "type": "Feature",
  "properties": {
    "gn:admin1_code":"5",
    "gn:admin2_code":"23.0",
    "gn:asciiname":"Jolchijtik",
    "gn:country_code":"MX",
    "gn:dem":2438,
    "gn:feature_class":"P",
    "gn:feature_code":"PPL",
    "gn:name":"Jolchijtik",
    "gn:population":284,
    "gn:timezone":"America/Mexico_City",
    "iso:country":"MX",
    "wof:name":"Jolchijtik",
    "wof:placetype":"locality",
    "wof:population":284
},
  "geometry": {"coordinates":[-92.71639999999999,16.82858],"type":"Point"}
}