{
  "type": "Feature",
  "properties": {
    "gn:admin1_code":"10.0",
    "gn:admin2_code":"36.0",
    "gn:asciiname":"Londres",
    "gn:country_code":"MX",
    "gn:dem":1095,
    "gn:feature_class":"P",
    "gn:feature_code":"PPL",
    "gn:name":"Londres",
    "gn:population":0,
    "gn:timezone":"America/Monterrey",
    "iso:country":"MX",
    "name:ceb_x_preferred":[
        "Londres"
    ],
    "name:deu_x_preferred":[
        "Londres"
    ],
    "name:fin_x_preferred":[
        "Londres"
    ],
    "name:fra_x_preferred":[
        "Londres"
    ],
    "name:oci_x_preferred":[
        "Londres"
    ],
    "name:por_x_preferred":[
        "Londres"
    ],
    "name:spa_x_preferred":[
        "Londres"
    ],
    "name:srp_x_preferred":[
        "\u041b\u043e\u043d\u0434\u0440\u0435\u0441"
    ],
    "name:swe_x_preferred":[
        "Londres"
    ],
    "name:und_x_variant":[
        "Ejido Londres"
    ],
    "wof:name":"Londres",
    "wof:placetype":"locality"
},
  "geometry": {"coordinates":[-103.41452,26.18208],"type":"Point"}
}