{
  "type": "Feature",
  "properties": {
    "gn:admin1_code":"3",
    "gn:admin2_code":"3.0",
    "gn:asciiname":"Ojo de Pajaro",
    "gn:country_code":"MX",
    "gn:dem":325,
    "gn:feature_class":"P",
    "gn:feature_code":"PPL",
    "gn:name":"Ojo de P\u00e1jaro",
    "gn:population":0,
    "gn:timezone":"America/Mazatlan",
    "iso:country":"MX",
    "name:spa_x_preferred":[
        "Ojo de P\u00e1jaro"
    ],
    "wof:name":"Ojo de Pajaro",
    "wof:placetype":"locality"
},
  "geometry": {"coordinates":[-110.84009,24.81203],"type":"Point"}
}