{
  "type": "Feature",
  "properties": {
    "gn:admin1_code":"19",
    "gn:admin2_code":"10",
    "gn:asciiname":"El Barril",
    "gn:country_code":"MX",
    "gn:dem":503,
    "gn:feature_class":"P",
    "gn:feature_code":"PPL",
    "gn:name":"El Barril",
    "gn:population":12,
    "gn:timezone":"America/Monterrey",
    "iso:country":"MX",
    "wof:name":"El Barril",
    "wof:placetype":"locality",
    "wof:population":12
},
  "geometry": {"coordinates":[-100.33587,25.84811],"type":"Point"}
}