{
  "type": "Feature",
  "properties": {
    "gn:admin1_code":"21.0",
    "gn:admin2_code":"166.0",
    "gn:asciiname":"Colonia Independencia",
    "gn:country_code":"MX",
    "gn:dem":1492,
    "gn:feature_class":"P",
    "gn:feature_code":"PPL",
    "gn:name":"Colonia Independencia",
    "gn:population":0,
    "gn:timezone":"America/Mexico_City",
    "iso:country":"MX",
    "name:ceb_x_preferred":[
        "Independencia"
    ],
    "name:deu_x_preferred":[
        "Independencia"
    ],
    "name:eus_x_preferred":[
        "Colonia Independencia"
    ],
    "name:ita_x_preferred":[
        "Independencia"
    ],
    "name:lit_x_preferred":[
        "Kolonia Independensija"
    ],
    "name:por_x_preferred":[
        "Independencia"
    ],
    "name:ron_x_preferred":[
        "Independencia"
    ],
    "name:sco_x_preferred":[
        "Colonia Independencia"
    ],
    "name:spa_x_preferred":[
        "Colonia Independencia"
    ],
    "name:zho_x_preferred":[
        "\u7368\u7acb\u79fb\u6c11\u93ae"
    ],
    "wof:name":"Colonia Independencia",
    "wof:placetype":"locality"
},
  "geometry": {"coordinates":[-98.45686000000001,18.72594],"type":"Point"}
}