{
  "type": "Feature",
  "properties": {
    "gn:admin1_code":"21",
    "gn:admin2_code":"156.0",
    "gn:asciiname":"Rancho Florindo",
    "gn:country_code":"MX",
    "gn:dem":2162,
    "gn:feature_class":"P",
    "gn:feature_code":"PPL",
    "gn:name":"Rancho Florindo",
    "gn:population":9,
    "gn:timezone":"America/Mexico_City",
    "iso:country":"MX",
    "wof:name":"Rancho Florindo",
    "wof:placetype":"locality",
    "wof:population":9
},
  "geometry": {"coordinates":[-97.60328,18.38824],"type":"Point"}
}