{
  "type": "Feature",
  "properties": {
    "gn:admin1_code":"19",
    "gn:admin2_code":"17.0",
    "gn:asciiname":"Los Alamos",
    "gn:country_code":"MX",
    "gn:dem":1768,
    "gn:feature_class":"P",
    "gn:feature_code":"PPL",
    "gn:name":"Los \u00c1lamos",
    "gn:population":8,
    "gn:timezone":"America/Monterrey",
    "iso:country":"MX",
    "name:und_x_variant":[
        "Los \u00c1lamos"
    ],
    "wof:name":"Los Alamos",
    "wof:placetype":"locality",
    "wof:population":8
},
  "geometry": {"coordinates":[-100.04971,24.71646],"type":"Point"}
}