{
  "type": "Feature",
  "properties": {
    "gn:admin1_code":"19",
    "gn:admin2_code":"17.0",
    "gn:asciiname":"Los Alamos",
    "gn:country_code":"MX",
    "gn:dem":1768,
    "gn:feature_class":"P",
    "gn:feature_code":"PPL",
    "gn:name":"Los \u00c1lamos",
    "gn:population":8,
    "gn:timezone":"America/Monterrey",
    "iso:country":"MX",
    "name:ceb_x_preferred":[
        "Los Alamos"
    ],
    "name:deu_x_preferred":[
        "Los Alamos"
    ],
    "name:nld_x_preferred":[
        "Los Alamos"
    ],
    "name:pol_x_preferred":[
        "Los Alamos"
    ],
    "name:por_x_preferred":[
        "Los Alamos"
    ],
    "name:rus_x_preferred":[
        "\u041b\u043e\u0441-\u0410\u043b\u0430\u043c\u043e\u0441"
    ],
    "name:swe_x_preferred":[
        "Los Alamos"
    ],
    "name:tur_x_preferred":[
        "Los Alamos"
    ],
    "name:ukr_x_preferred":[
        "\u041b\u043e\u0441-\u0410\u043b\u0430\u043c\u043e\u0441"
    ],
    "name:und_x_variant":[
        "Los \u00c1lamos"
    ],
    "name:vie_x_preferred":[
        "Los Alamos"
    ],
    "name:vol_x_preferred":[
        "Los Alamos"
    ],
    "wof:name":"Los Alamos",
    "wof:placetype":"locality",
    "wof:population":8
},
  "geometry": {"coordinates":[-100.04971,24.71646],"type":"Point"}
}