{
  "type": "Feature",
  "properties": {
    "gn:admin1_code":"25",
    "gn:admin2_code":"11",
    "gn:asciiname":"El Campito",
    "gn:country_code":"MX",
    "gn:dem":18,
    "gn:feature_class":"P",
    "gn:feature_code":"PPL",
    "gn:name":"El Campito",
    "gn:population":41,
    "gn:timezone":"America/Mazatlan",
    "iso:country":"MX",
    "wof:name":"El Campito",
    "wof:placetype":"locality",
    "wof:population":41
},
  "geometry": {"coordinates":[-108.53534999999999,25.59862],"type":"Point"}
}