{
  "type": "Feature",
  "properties": {
    "gn:admin1_code":"12",
    "gn:admin2_code":"41.0",
    "gn:asciiname":"El Cocoyul",
    "gn:country_code":"MX",
    "gn:dem":1069,
    "gn:feature_class":"P",
    "gn:feature_code":"PPL",
    "gn:name":"El Cocoyul",
    "gn:population":436,
    "gn:timezone":"America/Mexico_City",
    "iso:country":"MX",
    "wof:name":"El Cocoyul",
    "wof:placetype":"locality",
    "wof:population":436
},
  "geometry": {"coordinates":[-98.77889,17.02167],"type":"Point"}
}