{
  "type": "Feature",
  "properties": {
    "gn:admin1_code":"14.0",
    "gn:admin2_code":"20.0",
    "gn:asciiname":"La Jeringa",
    "gn:country_code":"MX",
    "gn:dem":642,
    "gn:feature_class":"P",
    "gn:feature_code":"PPL",
    "gn:name":"La Jeringa",
    "gn:population":0,
    "gn:timezone":"America/Mexico_City",
    "iso:country":"MX",
    "name:spa_x_preferred":[
        "La Jeringa"
    ],
    "wof:name":"La Jeringa",
    "wof:placetype":"locality"
},
  "geometry": {"coordinates":[-105.30785,20.32595],"type":"Point"}
}