{
  "type": "Feature",
  "properties": {
    "gn:admin1_code":"31",
    "gn:admin2_code":"48.0",
    "gn:asciiname":"Chencoh",
    "gn:country_code":"MX",
    "gn:dem":11,
    "gn:feature_class":"P",
    "gn:feature_code":"PPL",
    "gn:name":"Chencoh",
    "gn:population":0,
    "gn:timezone":"America/Merida",
    "iso:country":"MX",
    "name:spa_x_preferred":[
        "Chencoh"
    ],
    "wof:name":"Chencoh",
    "wof:placetype":"locality"
},
  "geometry": {"coordinates":[-90.03151,20.68275],"type":"Point"}
}