{
  "type": "Feature",
  "properties": {
    "iso:country":"MX",
    "name:spa_x_preferred":[
        "Rio Verde Centro"
    ],
    "qs:gn_adm0_cc":"MX",
    "qs:gn_local":3520235,
    "qs:gn_nam_loc":"rio verde",
    "qs:gn_namadm1":"24",
    "qs:local_max":142,
    "qs:local_sum":271,
    "qs:localhoods":4,
    "qs:name":"Rio Verde Centro",
    "qs:name_adm0":"M\u00e9xico",
    "qs:name_adm1":"San Luis Potosi",
    "qs:name_adm2":"Rioverde",
    "qs:name_local":"R\u00edo Verde",
    "qs:photo_max":45,
    "qs:photo_sum":118,
    "qs:placetype":"Suburb",
    "qs:quad_count":11,
    "qs:woe_adm0":23424900,
    "qs:woe_adm1":2346287,
    "qs:woe_adm2":12601494,
    "qs:woe_lau":0,
    "qs:woe_local":140832,
    "qs:woe_ver":"7.10.0",
    "wof:lang":[
        "spa"
    ],
    "wof:name":"Rio Verde Centro",
    "wof:placetype":"neighbourhood"
},
  "geometry": {"coordinates":[-99.992983,21.933475],"type":"Point"}
}