{
  "type": "Feature",
  "properties": {
    "iso:country":"MX",
    "name:ara_x_preferred":[
        "\u0633\u0627\u0646\u062a\u0627 \u0633\u064a\u0633\u064a\u0644\u064a\u0627"
    ],
    "name:arg_x_preferred":[
        "Santa Cecilia"
    ],
    "name:azb_x_preferred":[
        "\u0633\u0627\u0646\u062a\u0627 \u0633\u0633\u06cc\u0644\u06cc\u0627"
    ],
    "name:cat_x_preferred":[
        "Santa Cecilia"
    ],
    "name:ceb_x_preferred":[
        "Santa Cecilia"
    ],
    "name:epo_x_preferred":[
        "Santa Cecilia"
    ],
    "name:eus_x_preferred":[
        "Santa Cecilia"
    ],
    "name:fas_x_preferred":[
        "\u0633\u0627\u0646\u062a\u0627 \u0633\u0633\u06cc\u0644\u06cc\u0627"
    ],
    "name:fra_x_preferred":[
        "Santa Cecilia"
    ],
    "name:glg_x_preferred":[
        "Santa Cecilia"
    ],
    "name:haw_x_preferred":[
        "Santa Cecilia"
    ],
    "name:hun_x_preferred":[
        "Santa Cecilia"
    ],
    "name:ina_x_preferred":[
        "Santa Cecilia"
    ],
    "name:ita_x_preferred":[
        "Santa Cecilia"
    ],
    "name:msa_x_preferred":[
        "Santa Cecilia"
    ],
    "name:nld_x_preferred":[
        "Santa Cecilia"
    ],
    "name:oci_x_preferred":[
        "Santa Cecilia"
    ],
    "name:pol_x_preferred":[
        "Santa Cecilia"
    ],
    "name:por_x_preferred":[
        "Santa Cecilia"
    ],
    "name:rus_x_preferred":[
        "\u0421\u0430\u043d\u0442\u0430-\u0421\u0435\u0441\u0438\u043b\u0438\u044f"
    ],
    "name:spa_x_preferred":[
        "Santa Cecilia"
    ],
    "name:spa_x_variant":[
        "Santa Emilia"
    ],
    "name:swe_x_preferred":[
        "Santa Cecilia"
    ],
    "name:ukr_x_preferred":[
        "\u0421\u0430\u043d\u0442\u0430-\u0421\u0435\u0441\u0456\u043b\u0456\u044f"
    ],
    "name:vie_x_preferred":[
        "Santa Cecilia"
    ],
    "name:war_x_preferred":[
        "Santa Cecilia"
    ],
    "name:zho_min_nan_x_preferred":[
        "Santa Cecilia"
    ],
    "name:zho_x_preferred":[
        "\u5723\u585e\u897f\u5229\u4e9a"
    ],
    "qs:gn_adm0_cc":"MX",
    "qs:gn_local":3995465,
    "qs:gn_nam_loc":"Monterrey, Monterrey, Nuevo Leon, MX",
    "qs:gn_namadm1":"19",
    "qs:local_max":2766,
    "qs:local_sum":15661,
    "qs:localhoods":40,
    "qs:name":"Santa Cecilia",
    "qs:name_adm0":"M\u00e9xico",
    "qs:name_adm1":"Nuevo Leon",
    "qs:name_adm2":"Monterrey",
    "qs:name_local":"Monterrey",
    "qs:photo_max":18,
    "qs:photo_sum":26,
    "qs:placetype":"Suburb",
    "qs:quad_count":3,
    "qs:woe_adm0":23424900,
    "qs:woe_adm1":2346282,
    "qs:woe_adm2":12600645,
    "qs:woe_lau":0,
    "qs:woe_local":134047,
    "qs:woe_ver":"7.10.0",
    "wof:lang":[
        "spa"
    ],
    "wof:name":"Santa Cecilia",
    "wof:placetype":"neighbourhood"
},
  "geometry": {"coordinates":[-100.366446,25.728159],"type":"Point"}
}