{
  "type": "Feature",
  "properties": {
    "gn:admin1_code":"19",
    "gn:admin2_code":"9.0",
    "gn:asciiname":"El Castillo",
    "gn:country_code":"MX",
    "gn:dem":323,
    "gn:feature_class":"P",
    "gn:feature_code":"PPL",
    "gn:name":"El Castillo",
    "gn:population":0,
    "gn:timezone":"America/Monterrey",
    "iso:country":"MX",
    "name:ceb_x_preferred":[
        "El Castillo"
    ],
    "name:deu_x_preferred":[
        "El Castillo"
    ],
    "name:ita_x_preferred":[
        "El Castillo"
    ],
    "name:nld_x_preferred":[
        "El Castillo"
    ],
    "name:pol_x_preferred":[
        "El Castillo"
    ],
    "name:spa_x_preferred":[
        "El Castillo"
    ],
    "name:swe_x_preferred":[
        "El Castillo"
    ],
    "name:und_x_variant":[
        "Castillo",
        "Rancho El Castillo"
    ],
    "name:vie_x_preferred":[
        "El Castillo"
    ],
    "wof:name":"El Castillo",
    "wof:placetype":"locality"
},
  "geometry": {"coordinates":[-99.99952999999999,25.53177],"type":"Point"}
}