{
  "type": "Feature",
  "properties": {
    "gn:admin1_code":"12",
    "gn:admin2_code":"80.0",
    "gn:asciiname":"Los Callejones",
    "gn:country_code":"MX",
    "gn:dem":43,
    "gn:feature_class":"P",
    "gn:feature_code":"PPL",
    "gn:name":"Los Callejones",
    "gn:population":233,
    "gn:timezone":"America/Mexico_City",
    "iso:country":"MX",
    "wof:name":"Los Callejones",
    "wof:placetype":"locality",
    "wof:population":233
},
  "geometry": {"coordinates":[-98.77500000000001,16.58583],"type":"Point"}
}