{
  "type": "Feature",
  "properties": {
    "gn:admin1_code":"20.0",
    "gn:admin2_code":"549.0",
    "gn:asciiname":"El Portezuelo",
    "gn:country_code":"MX",
    "gn:dem":2251,
    "gn:feature_class":"P",
    "gn:feature_code":"PPL",
    "gn:name":"El Portezuelo",
    "gn:population":0,
    "gn:timezone":"America/Mexico_City",
    "iso:country":"MX",
    "name:spa_x_preferred":[
        "El Portezuelo"
    ],
    "wof:name":"El Portezuelo",
    "wof:placetype":"locality"
},
  "geometry": {"coordinates":[-97.88054,17.5061],"type":"Point"}
}