{
  "type": "Feature",
  "properties": {
    "gn:admin1_code":"30",
    "gn:admin2_code":"191.0",
    "gn:asciiname":"Real del Oro",
    "gn:country_code":"MX",
    "gn:dem":30,
    "gn:feature_class":"P",
    "gn:feature_code":"PPL",
    "gn:name":"Real del Oro",
    "gn:population":837,
    "gn:timezone":"America/Mexico_City",
    "iso:country":"MX",
    "wof:name":"Real del Oro",
    "wof:placetype":"locality",
    "wof:population":837
},
  "geometry": {"coordinates":[-96.40917,19.42389],"type":"Point"}
}