{
  "type": "Feature",
  "properties": {
    "gn:admin1_code":"16",
    "gn:admin2_code":"52",
    "gn:asciiname":"La Carpa",
    "gn:country_code":"MX",
    "gn:dem":9,
    "gn:feature_class":"P",
    "gn:feature_code":"PPL",
    "gn:name":"La Carpa",
    "gn:population":12,
    "gn:timezone":"America/Mexico_City",
    "iso:country":"MX",
    "wof:name":"La Carpa",
    "wof:placetype":"locality",
    "wof:population":12
},
  "geometry": {"coordinates":[-102.38222,17.99],"type":"Point"}
}