{
  "type": "Feature",
  "properties": {
    "gn:admin1_code":"14",
    "gn:admin2_code":"61.0",
    "gn:asciiname":"Ciruelillo",
    "gn:country_code":"MX",
    "gn:dem":1004,
    "gn:feature_class":"P",
    "gn:feature_code":"PPL",
    "gn:name":"Ciruelillo",
    "gn:population":8,
    "gn:timezone":"America/Mexico_City",
    "iso:country":"MX",
    "wof:name":"Ciruelillo",
    "wof:placetype":"locality",
    "wof:population":8
},
  "geometry": {"coordinates":[-104.23083,22.0125],"type":"Point"}
}