{
  "type": "Feature",
  "properties": {
    "gn:admin1_code":"11",
    "gn:admin2_code":"5",
    "gn:asciiname":"El Refugio",
    "gn:country_code":"MX",
    "gn:dem":1768,
    "gn:feature_class":"P",
    "gn:feature_code":"PPL",
    "gn:name":"El Refugio",
    "gn:population":14,
    "gn:timezone":"America/Mexico_City",
    "iso:country":"MX",
    "wof:name":"El Refugio",
    "wof:placetype":"locality",
    "wof:population":14
},
  "geometry": {"coordinates":[-100.69722,20.5625],"type":"Point"}
}