{
  "type": "Feature",
  "properties": {
    "gn:admin1_code":"10",
    "gn:admin2_code":"26.0",
    "gn:asciiname":"Sapioris",
    "gn:country_code":"MX",
    "gn:dem":1196,
    "gn:feature_class":"P",
    "gn:feature_code":"PPL",
    "gn:name":"Sapioris",
    "gn:population":0,
    "gn:timezone":"America/Monterrey",
    "iso:country":"MX",
    "name:und_x_variant":[
        "Sapiores",
        "Sapioris"
    ],
    "wof:name":"Sapioris",
    "wof:placetype":"locality"
},
  "geometry": {"coordinates":[-105.84733,24.54377],"type":"Point"}
}