{
  "type": "Feature",
  "properties": {
    "gn:admin1_code":"15",
    "gn:admin2_code":"82.0",
    "gn:asciiname":"Santa Maria de las Flores",
    "gn:country_code":"MX",
    "gn:dem":1211,
    "gn:feature_class":"P",
    "gn:feature_code":"PPL",
    "gn:name":"Santa Mar\u00eda de las Flores",
    "gn:population":248,
    "gn:timezone":"America/Mexico_City",
    "iso:country":"MX",
    "name:und_x_variant":[
        "Santa Mar\u00eda de las Flores"
    ],
    "wof:name":"Santa Maria de las Flores",
    "wof:placetype":"locality",
    "wof:population":248
},
  "geometry": {"coordinates":[-100.16697000000001,18.83829],"type":"Point"}
}