{
  "type": "Feature",
  "properties": {
    "gn:admin1_code":"14",
    "gn:admin2_code":"104.0",
    "gn:asciiname":"Arroyo del Tecolote",
    "gn:country_code":"MX",
    "gn:dem":1889,
    "gn:feature_class":"P",
    "gn:feature_code":"PPL",
    "gn:name":"Arroyo del Tecolote",
    "gn:population":0,
    "gn:timezone":"America/Mexico_City",
    "iso:country":"MX",
    "name:spa_x_preferred":[
        "Arroyo del Tecolote"
    ],
    "wof:name":"Arroyo del Tecolote",
    "wof:placetype":"locality"
},
  "geometry": {"coordinates":[-103.53422,21.97026],"type":"Point"}
}