{
  "type": "Feature",
  "properties": {
    "gn:admin1_code":"32.0",
    "gn:admin2_code":"49.0",
    "gn:asciiname":"Puerta Cadena del Sur",
    "gn:country_code":"MX",
    "gn:dem":1870,
    "gn:feature_class":"P",
    "gn:feature_code":"PPL",
    "gn:name":"Puerta Cadena del Sur",
    "gn:population":0,
    "gn:timezone":"America/Mexico_City",
    "iso:country":"MX",
    "name:spa_x_preferred":[
        "Puerta Cadena del Sur"
    ],
    "wof:name":"Puerta Cadena del Sur",
    "wof:placetype":"locality"
},
  "geometry": {"coordinates":[-103.57581,22.75021],"type":"Point"}
}