{
  "type": "Feature",
  "properties": {
    "gn:admin1_code":"26",
    "gn:admin2_code":"30.0",
    "gn:asciiname":"San Gustavo",
    "gn:country_code":"MX",
    "gn:dem":39,
    "gn:feature_class":"P",
    "gn:feature_code":"PPL",
    "gn:name":"San Gustavo",
    "gn:population":4,
    "gn:timezone":"America/Hermosillo",
    "iso:country":"MX",
    "name:spa_x_preferred":[
        "San Gustavo"
    ],
    "wof:name":"San Gustavo",
    "wof:placetype":"locality",
    "wof:population":4
},
  "geometry": {"coordinates":[-111.62264,28.85602],"type":"Point"}
}