{
  "type": "Feature",
  "properties": {
    "gn:admin1_code":"11",
    "gn:admin2_code":"24.0",
    "gn:asciiname":"Cerritos",
    "gn:country_code":"MX",
    "gn:dem":1707,
    "gn:feature_class":"P",
    "gn:feature_code":"PPL",
    "gn:name":"Cerritos",
    "gn:population":240,
    "gn:timezone":"America/Mexico_City",
    "iso:country":"MX",
    "wof:name":"Cerritos",
    "wof:placetype":"locality",
    "wof:population":240
},
  "geometry": {"coordinates":[-101.34139,20.54861],"type":"Point"}
}