{
  "type": "Feature",
  "properties": {
    "gn:admin1_code":"4",
    "gn:admin2_code":"3.0",
    "gn:asciiname":"Santa Beatriz",
    "gn:country_code":"MX",
    "gn:dem":19,
    "gn:feature_class":"P",
    "gn:feature_code":"PPL",
    "gn:name":"Santa Beatriz",
    "gn:population":6,
    "gn:timezone":"America/Merida",
    "iso:country":"MX",
    "wof:name":"Santa Beatriz",
    "wof:placetype":"locality",
    "wof:population":6
},
  "geometry": {"coordinates":[-91.22306,18.30222],"type":"Point"}
}