{
  "type": "Feature",
  "properties": {
    "gn:admin1_code":"11",
    "gn:admin2_code":"42.0",
    "gn:asciiname":"Loma Tendida",
    "gn:country_code":"MX",
    "gn:dem":1737,
    "gn:feature_class":"P",
    "gn:feature_code":"PPL",
    "gn:name":"Loma Tendida",
    "gn:population":0,
    "gn:timezone":"America/Mexico_City",
    "iso:country":"MX",
    "name:spa_x_preferred":[
        "Loma Tendida"
    ],
    "wof:name":"Loma Tendida",
    "wof:placetype":"locality"
},
  "geometry": {"coordinates":[-101.31057,20.3756],"type":"Point"}
}