{
  "type": "Feature",
  "properties": {
    "gn:admin1_code":"21",
    "gn:admin2_code":"184.0",
    "gn:asciiname":"Ahuacatlaya",
    "gn:country_code":"MX",
    "gn:dem":790,
    "gn:feature_class":"P",
    "gn:feature_code":"PPL",
    "gn:name":"Ahuacatlaya",
    "gn:population":552,
    "gn:timezone":"America/Mexico_City",
    "iso:country":"MX",
    "wof:name":"Ahuacatlaya",
    "wof:placetype":"locality",
    "wof:population":552
},
  "geometry": {"coordinates":[-97.82778,20.17833],"type":"Point"}
}