{
  "type": "Feature",
  "properties": {
    "gn:admin1_code":"26",
    "gn:admin2_code":"30.0",
    "gn:asciiname":"Lazaro Peraza",
    "gn:country_code":"MX",
    "gn:dem":278,
    "gn:feature_class":"P",
    "gn:feature_code":"PPL",
    "gn:name":"L\u00e1zaro Peraza",
    "gn:population":6,
    "gn:timezone":"America/Hermosillo",
    "iso:country":"MX",
    "name:und_x_variant":[
        "L\u00e1zaro Peraza"
    ],
    "wof:name":"Lazaro Peraza",
    "wof:placetype":"locality",
    "wof:population":6
},
  "geometry": {"coordinates":[-110.91110999999999,29.13806],"type":"Point"}
}