{
  "type": "Feature",
  "properties": {
    "gn:admin1_code":"7.0",
    "gn:admin2_code":"36.0",
    "gn:asciiname":"Buenavista",
    "gn:country_code":"MX",
    "gn:dem":1109,
    "gn:feature_class":"P",
    "gn:feature_code":"PPL",
    "gn:name":"Buenavista",
    "gn:population":0,
    "gn:timezone":"America/Monterrey",
    "iso:country":"MX",
    "name:spa_x_preferred":[
        "Buenavista"
    ],
    "wof:name":"Buenavista",
    "wof:placetype":"locality"
},
  "geometry": {"coordinates":[-103.10169999999999,25.42142],"type":"Point"}
}