{
  "type": "Feature",
  "properties": {
    "gn:admin1_code":"6",
    "gn:admin2_code":"20.0",
    "gn:asciiname":"Saucillo de los Lugo",
    "gn:country_code":"MX",
    "gn:dem":1370,
    "gn:feature_class":"P",
    "gn:feature_code":"PPL",
    "gn:name":"Saucillo de los Lugo",
    "gn:population":67,
    "gn:timezone":"America/Chihuahua",
    "iso:country":"MX",
    "wof:name":"Saucillo de los Lugo",
    "wof:placetype":"locality",
    "wof:population":67
},
  "geometry": {"coordinates":[-108.37132,27.38131],"type":"Point"}
}