{
  "type": "Feature",
  "properties": {
    "gn:admin1_code":"6",
    "gn:admin2_code":"27.0",
    "gn:asciiname":"Rojarare (El Encinal)",
    "gn:country_code":"MX",
    "gn:dem":1605,
    "gn:feature_class":"P",
    "gn:feature_code":"PPL",
    "gn:name":"Rojarare (El Encinal)",
    "gn:population":4,
    "gn:timezone":"America/Chihuahua",
    "iso:country":"MX",
    "wof:name":"Rojarare (El Encinal)",
    "wof:placetype":"locality",
    "wof:population":4
},
  "geometry": {"coordinates":[-107.64936000000002,27.48326],"type":"Point"}
}