{
  "type": "Feature",
  "properties": {
    "gn:country":"MX",
    "gn:fcode":"PPL",
    "gn:population":0,
    "iso:country":"MX",
    "name:bre_x_preferred":[
        "Agua Caliente"
    ],
    "name:ceb_x_preferred":[
        "Agua Caliente"
    ],
    "name:deu_x_preferred":[
        "Agua Caliente"
    ],
    "name:spa_x_preferred":[
        "Agua Caliente"
    ],
    "name:swe_x_preferred":[
        "Agua Caliente"
    ],
    "qs_pg:aaroncc":"MX",
    "qs_pg:gn_country":"MX",
    "qs_pg:gn_fcode":"PPL",
    "qs_pg:gn_pop":0,
    "qs_pg:name":"Agua Caliente",
    "qs_pg:name_adm0":"M\u00e9xico",
    "qs_pg:name_adm1":"Jalisco",
    "qs_pg:photos":24,
    "qs_pg:photos_1k":5,
    "qs_pg:photos_9k":1,
    "qs_pg:photos_9r":1,
    "qs_pg:photos_all":24,
    "qs_pg:photos_sr":1,
    "qs_pg:pop_sr":0,
    "qs_pg:qs_pg_placetype":"locality",
    "qs_pg:qs_pg_placetype_gp":"Town",
    "qs_pg:woe_adm0":23424900,
    "woe:adm0_id":23424900,
    "woe:name_adm0":"M\u00e9xico",
    "woe:name_adm1":"Jalisco",
    "woe:placetype":"Town",
    "wof:name":"Agua Caliente",
    "wof:placetype":"locality"
},
  "geometry": {"coordinates":[-102.91788,20.31039],"type":"Point"}
}