{
  "type": "Feature",
  "properties": {
    "gn:admin1_code":"14",
    "gn:admin2_code":"58.0",
    "gn:asciiname":"El Copal",
    "gn:country_code":"MX",
    "gn:dem":1241,
    "gn:feature_class":"P",
    "gn:feature_code":"PPL",
    "gn:name":"El Copal",
    "gn:population":73,
    "gn:timezone":"America/Mexico_City",
    "iso:country":"MX",
    "wof:name":"El Copal",
    "wof:placetype":"locality",
    "wof:population":73
},
  "geometry": {"coordinates":[-104.82333,20.57333],"type":"Point"}
}