{
  "type": "Feature",
  "properties": {
    "gn:admin1_code":"20",
    "gn:admin2_code":"275",
    "gn:asciiname":"Ocotal",
    "gn:country_code":"MX",
    "gn:dem":1084,
    "gn:feature_class":"P",
    "gn:feature_code":"PPL",
    "gn:name":"Ocotal",
    "gn:population":51,
    "gn:timezone":"America/Mexico_City",
    "iso:country":"MX",
    "wof:name":"Ocotal",
    "wof:placetype":"locality",
    "wof:population":51
},
  "geometry": {"coordinates":[-95.75221999999999,16.97306],"type":"Point"}
}