{
  "type": "Feature",
  "properties": {
    "gn:admin1_code":"6.0",
    "gn:admin2_code":"24.0",
    "gn:asciiname":"Cuevillas",
    "gn:country_code":"MX",
    "gn:dem":1595,
    "gn:feature_class":"P",
    "gn:feature_code":"PPL",
    "gn:name":"Cuevillas",
    "gn:population":0,
    "gn:timezone":"America/Chihuahua",
    "iso:country":"MX",
    "name:und_x_variant":[
        "Rancho Cuevecillas",
        "Cuevillas"
    ],
    "wof:name":"Cuevillas",
    "wof:placetype":"locality"
},
  "geometry": {"coordinates":[-106.28805,28.21848],"type":"Point"}
}