{
  "type": "Feature",
  "properties": {
    "gn:admin1_code":"13.0",
    "gn:asciiname":"Cerrito Blanco",
    "gn:country_code":"MX",
    "gn:dem":1722,
    "gn:feature_class":"P",
    "gn:feature_code":"PPL",
    "gn:name":"Cerrito Blanco",
    "gn:population":0,
    "gn:timezone":"America/Mexico_City",
    "iso:country":"MX",
    "name:spa_x_preferred":[
        "Cerrito Blanco"
    ],
    "wof:name":"Cerrito Blanco",
    "wof:placetype":"locality"
},
  "geometry": {"coordinates":[-99.72327,20.5525],"type":"Point"}
}