{
  "type": "Feature",
  "properties": {
    "gn:admin1_code":"11",
    "gn:admin2_code":"12",
    "gn:asciiname":"San Jose de la Esperanza [La Bodega]",
    "gn:country_code":"MX",
    "gn:dem":1734,
    "gn:feature_class":"P",
    "gn:feature_code":"PPL",
    "gn:name":"San Jos\u00e9 de la Esperanza [La Bodega]",
    "gn:population":15,
    "gn:timezone":"America/Mexico_City",
    "iso:country":"MX",
    "name:und_x_variant":[
        "San Jos\u00e9 de la Esperanza [La Bodega]"
    ],
    "wof:name":"San Jose de la Esperanza [La Bodega]",
    "wof:placetype":"locality",
    "wof:population":15
},
  "geometry": {"coordinates":[-101.70528,20.685],"type":"Point"}
}