{
  "type": "Feature",
  "properties": {
    "gn:admin1_code":"20",
    "gn:admin2_code":"379.0",
    "gn:asciiname":"Loma Nuhucua",
    "gn:country_code":"MX",
    "gn:dem":2644,
    "gn:feature_class":"P",
    "gn:feature_code":"PPL",
    "gn:name":"Loma \u00d1uhucua",
    "gn:population":227,
    "gn:timezone":"America/Mexico_City",
    "iso:country":"MX",
    "name:und_x_variant":[
        "Loma \u00d1uhucua"
    ],
    "wof:name":"Loma Nuhucua",
    "wof:placetype":"locality",
    "wof:population":227
},
  "geometry": {"coordinates":[-97.71969,17.12092],"type":"Point"}
}