{
  "type": "Feature",
  "properties": {
    "gn:admin1_code":"5.0",
    "gn:asciiname":"San Vicente del Villar",
    "gn:country_code":"MX",
    "gn:dem":812,
    "gn:feature_class":"P",
    "gn:feature_code":"PPL",
    "gn:name":"San Vicente del Villar",
    "gn:population":0,
    "gn:timezone":"America/Mexico_City",
    "iso:country":"MX",
    "name:spa_x_preferred":[
        "San Vicente del Villar"
    ],
    "wof:name":"San Vicente del Villar",
    "wof:placetype":"locality"
},
  "geometry": {"coordinates":[-93.43796,16.59352],"type":"Point"}
}