{
  "type": "Feature",
  "properties": {
    "gn:admin1_code":"14.0",
    "gn:admin2_code":"12.0",
    "gn:asciiname":"El Zacaton",
    "gn:country_code":"MX",
    "gn:dem":1640,
    "gn:feature_class":"P",
    "gn:feature_code":"PPL",
    "gn:name":"El Zacat\u00f3n",
    "gn:population":0,
    "gn:timezone":"America/Mexico_City",
    "iso:country":"MX",
    "name:spa_x_preferred":[
        "El Zacat\u00f3n"
    ],
    "wof:name":"El Zacaton",
    "wof:placetype":"locality"
},
  "geometry": {"coordinates":[-104.70869,20.24219],"type":"Point"}
}