{
  "type": "Feature",
  "properties": {
    "gn:admin1_code":"28",
    "gn:admin2_code":"35.0",
    "gn:asciiname":"Puerto Rico",
    "gn:country_code":"MX",
    "gn:dem":5,
    "gn:feature_class":"P",
    "gn:feature_code":"PPL",
    "gn:name":"Puerto Rico",
    "gn:population":0,
    "gn:timezone":"America/Monterrey",
    "iso:country":"MX",
    "name:spa_x_preferred":[
        "Puerto Rico"
    ],
    "name:und_x_variant":[
        "Rancho Puerto Rico"
    ],
    "wof:name":"Puerto Rico",
    "wof:placetype":"locality"
},
  "geometry": {"coordinates":[-97.74195,24.59464],"type":"Point"}
}