{
  "type": "Feature",
  "properties": {
    "gn:admin1_code":"24.0",
    "gn:admin2_code":"40.0",
    "gn:asciiname":"La Ilusion",
    "gn:country_code":"MX",
    "gn:dem":79,
    "gn:feature_class":"P",
    "gn:feature_code":"PPL",
    "gn:name":"La Ilusi\u00f3n",
    "gn:population":0,
    "gn:timezone":"America/Mexico_City",
    "iso:country":"MX",
    "name:spa_x_preferred":[
        "La Ilusi\u00f3n"
    ],
    "wof:name":"La Ilusion",
    "wof:placetype":"locality"
},
  "geometry": {"coordinates":[-98.87194,22.13639],"type":"Point"}
}