{
  "type": "Feature",
  "properties": {
    "gn:admin1_code":"14.0",
    "gn:admin2_code":"113.0",
    "gn:asciiname":"Apango",
    "gn:country_code":"MX",
    "gn:dem":1987,
    "gn:feature_class":"P",
    "gn:feature_code":"PPL",
    "gn:name":"Apango",
    "gn:population":0,
    "gn:timezone":"America/Mexico_City",
    "iso:country":"MX",
    "name:spa_x_preferred":[
        "Apango"
    ],
    "wof:name":"Apango",
    "wof:placetype":"locality"
},
  "geometry": {"coordinates":[-103.71136,19.78065],"type":"Point"}
}