{
  "type": "Feature",
  "properties": {
    "gn:admin1_code":"14.0",
    "gn:admin2_code":"113.0",
    "gn:asciiname":"Apango",
    "gn:country_code":"MX",
    "gn:dem":1987,
    "gn:feature_class":"P",
    "gn:feature_code":"PPL",
    "gn:name":"Apango",
    "gn:population":0,
    "gn:timezone":"America/Mexico_City",
    "iso:country":"MX",
    "name:bul_x_preferred":[
        "\u0410\u043f\u0430\u043d\u0433\u043e"
    ],
    "name:deu_x_preferred":[
        "Apango"
    ],
    "name:fra_x_preferred":[
        "Apango"
    ],
    "name:ita_x_preferred":[
        "Apango"
    ],
    "name:pap_x_preferred":[
        "Apango"
    ],
    "name:por_x_preferred":[
        "Apango"
    ],
    "name:rus_x_preferred":[
        "\u0410\u043f\u0430\u043d\u0433\u043e"
    ],
    "name:spa_x_preferred":[
        "Apango"
    ],
    "name:sqi_x_preferred":[
        "Apango"
    ],
    "name:swe_x_preferred":[
        "Apango"
    ],
    "name:tgl_x_preferred":[
        "Apango"
    ],
    "name:zho_x_preferred":[
        "\u963f\u6f58\u6208"
    ],
    "wof:name":"Apango",
    "wof:placetype":"locality"
},
  "geometry": {"coordinates":[-103.71136,19.78065],"type":"Point"}
}