{
  "type": "Feature",
  "properties": {
    "gn:admin1_code":"26",
    "gn:admin2_code":"43.0",
    "gn:asciiname":"Hebron",
    "gn:country_code":"MX",
    "gn:dem":1215,
    "gn:feature_class":"P",
    "gn:feature_code":"PPL",
    "gn:name":"Hebr\u00f3n",
    "gn:population":8,
    "gn:timezone":"America/Hermosillo",
    "iso:country":"MX",
    "name:und_x_variant":[
        "Hebr\u00f3n"
    ],
    "wof:name":"Hebron",
    "wof:placetype":"locality",
    "wof:population":8
},
  "geometry": {"coordinates":[-111.00333000000001,31.20167],"type":"Point"}
}