{
  "type": "Feature",
  "properties": {
    "gn:admin1_code":"19",
    "gn:admin2_code":"49.0",
    "gn:asciiname":"Chirrion Largo",
    "gn:country_code":"MX",
    "gn:dem":1915,
    "gn:feature_class":"P",
    "gn:feature_code":"PPL",
    "gn:name":"Chirri\u00f3n Largo",
    "gn:population":0,
    "gn:timezone":"America/Monterrey",
    "iso:country":"MX",
    "name:spa_x_preferred":[
        "Chirri\u00f3n Largo"
    ],
    "wof:name":"Chirrion Largo",
    "wof:placetype":"locality"
},
  "geometry": {"coordinates":[-100.39709000000001,25.36468],"type":"Point"}
}