{
  "type": "Feature",
  "properties": {
    "gn:admin1_code":"11",
    "gn:admin2_code":"36",
    "gn:asciiname":"La Jara",
    "gn:country_code":"MX",
    "gn:dem":1889,
    "gn:feature_class":"P",
    "gn:feature_code":"PPL",
    "gn:name":"La Jara",
    "gn:population":48,
    "gn:timezone":"America/Mexico_City",
    "iso:country":"MX",
    "wof:name":"La Jara",
    "wof:placetype":"locality",
    "wof:population":48
},
  "geometry": {"coordinates":[-101.0175,20.12667],"type":"Point"}
}