{
  "type": "Feature",
  "properties": {
    "gn:admin1_code":"14.0",
    "gn:admin2_code":"60.0",
    "gn:asciiname":"Portero de Mauro",
    "gn:country_code":"MX",
    "gn:dem":1796,
    "gn:feature_class":"P",
    "gn:feature_code":"PPL",
    "gn:name":"Portero de Mauro",
    "gn:population":0,
    "gn:timezone":"America/Mexico_City",
    "iso:country":"MX",
    "name:spa_x_preferred":[
        "Portero de Mauro"
    ],
    "wof:name":"Portero de Mauro",
    "wof:placetype":"locality"
},
  "geometry": {"coordinates":[-102.73497999999999,21.27899],"type":"Point"}
}