{
  "type": "Feature",
  "properties": {
    "gn:admin1_code":"30",
    "gn:admin2_code":"161.0",
    "gn:asciiname":"La Calzada (Oscar Hidalgo)",
    "gn:country_code":"MX",
    "gn:dem":62,
    "gn:feature_class":"P",
    "gn:feature_code":"PPL",
    "gn:name":"La Calzada (Oscar Hidalgo)",
    "gn:population":8,
    "gn:timezone":"America/Mexico_City",
    "iso:country":"MX",
    "wof:name":"La Calzada (Oscar Hidalgo)",
    "wof:placetype":"locality",
    "wof:population":8
},
  "geometry": {"coordinates":[-98.36917,21.44083],"type":"Point"}
}