{
  "type": "Feature",
  "properties": {
    "gn:admin1_code":"12.0",
    "gn:admin2_code":"21.0",
    "gn:asciiname":"Plan del Limon",
    "gn:country_code":"MX",
    "gn:dem":463,
    "gn:feature_class":"P",
    "gn:feature_code":"PPL",
    "gn:name":"Plan del Lim\u00f3n",
    "gn:population":0,
    "gn:timezone":"America/Mexico_City",
    "iso:country":"MX",
    "name:spa_x_preferred":[
        "Plan del Lim\u00f3n"
    ],
    "wof:name":"Plan del Limon",
    "wof:placetype":"locality"
},
  "geometry": {"coordinates":[-100.19448,17.07088],"type":"Point"}
}