{
  "type": "Feature",
  "properties": {
    "gn:admin1_code":"16",
    "gn:admin2_code":"43",
    "gn:asciiname":"Fraccionamiento Campestre Curutaran",
    "gn:country_code":"MX",
    "gn:dem":1649,
    "gn:feature_class":"P",
    "gn:feature_code":"PPL",
    "gn:name":"Fraccionamiento Campestre Curutar\u00e1n",
    "gn:population":17,
    "gn:timezone":"America/Mexico_City",
    "iso:country":"MX",
    "name:und_x_variant":[
        "Fraccionamiento Campestre Curutar\u00e1n"
    ],
    "wof:name":"Fraccionamiento Campestre Curutaran",
    "wof:placetype":"locality",
    "wof:population":17
},
  "geometry": {"coordinates":[-102.28639,19.93139],"type":"Point"}
}