{
  "type": "Feature",
  "properties": {
    "gn:admin1_code":"5",
    "gn:admin2_code":"16.0",
    "gn:asciiname":"San Francisco el Cuyo",
    "gn:country_code":"MX",
    "gn:dem":5,
    "gn:feature_class":"P",
    "gn:feature_code":"PPL",
    "gn:name":"San Francisco el Cuyo",
    "gn:population":155,
    "gn:timezone":"America/Mexico_City",
    "iso:country":"MX",
    "wof:name":"San Francisco el Cuyo",
    "wof:placetype":"locality",
    "wof:population":155
},
  "geometry": {"coordinates":[-92.00201,17.8533],"type":"Point"}
}