{
  "type": "Feature",
  "properties": {
    "gn:admin1_code":"30",
    "gn:admin2_code":"109.0",
    "gn:asciiname":"Palma Sola de Ramirez",
    "gn:country_code":"MX",
    "gn:dem":666,
    "gn:feature_class":"P",
    "gn:feature_code":"PPL",
    "gn:name":"Palma Sola de Ram\u00edrez",
    "gn:population":124,
    "gn:timezone":"America/Mexico_City",
    "iso:country":"MX",
    "wof:name":"Palma Sola de Ramirez",
    "wof:placetype":"locality",
    "wof:population":124
},
  "geometry": {"coordinates":[-96.92237,19.88793],"type":"Point"}
}