{
  "type": "Feature",
  "properties": {
    "gn:admin1_code":"29",
    "gn:admin2_code":"14.0",
    "gn:asciiname":"Playa Azul",
    "gn:country_code":"MX",
    "gn:dem":2608,
    "gn:feature_class":"P",
    "gn:feature_code":"PPL",
    "gn:name":"Playa Azul",
    "gn:population":0,
    "gn:timezone":"America/Mexico_City",
    "iso:country":"MX",
    "name:spa_x_preferred":[
        "Playa Azul"
    ],
    "wof:name":"Playa Azul",
    "wof:placetype":"locality"
},
  "geometry": {"coordinates":[-98.34908,19.48144],"type":"Point"}
}