{
  "type": "Feature",
  "properties": {
    "gn:admin1_code":"7",
    "gn:admin2_code":"6.0",
    "gn:asciiname":"Los Lirios",
    "gn:country_code":"MX",
    "gn:dem":851,
    "gn:feature_class":"P",
    "gn:feature_code":"PPL",
    "gn:name":"Los Lirios",
    "gn:population":0,
    "gn:timezone":"America/Monterrey",
    "iso:country":"MX",
    "name:spa_x_preferred":[
        "Los Lirios"
    ],
    "wof:name":"Los Lirios",
    "wof:placetype":"locality"
},
  "geometry": {"coordinates":[-101.16227000000001,26.53323],"type":"Point"}
}