{
  "type": "Feature",
  "properties": {
    "gn:admin1_code":"13",
    "gn:admin2_code":"28.0",
    "gn:asciiname":"Teacal",
    "gn:country_code":"MX",
    "gn:dem":235,
    "gn:feature_class":"P",
    "gn:feature_code":"PPL",
    "gn:name":"Teacal",
    "gn:population":0,
    "gn:timezone":"America/Mexico_City",
    "iso:country":"MX",
    "name:spa_x_preferred":[
        "Teacal"
    ],
    "wof:name":"Teacal",
    "wof:placetype":"locality"
},
  "geometry": {"coordinates":[-98.45480999999999,21.1666],"type":"Point"}
}