{
  "type": "Feature",
  "properties": {
    "gn:admin1_code":"10",
    "gn:admin2_code":"32.0",
    "gn:asciiname":"La Soledad",
    "gn:cc2":"MX",
    "gn:country_code":"MX",
    "gn:dem":1816,
    "gn:feature_class":"P",
    "gn:feature_code":"PPL",
    "gn:name":"La Soledad",
    "gn:population":42,
    "gn:timezone":"America/Monterrey",
    "iso:country":"MX",
    "name:und_x_variant":[
        "Soledad"
    ],
    "wof:name":"La Soledad",
    "wof:placetype":"locality",
    "wof:population":42
},
  "geometry": {"coordinates":[-105.49729000000001,25.10138],"type":"Point"}
}