{
  "type": "Feature",
  "properties": {
    "gn:admin1_code":"6",
    "gn:admin2_code":"29.0",
    "gn:asciiname":"Arroyo de San Andres",
    "gn:country_code":"MX",
    "gn:dem":614,
    "gn:feature_class":"P",
    "gn:feature_code":"PPL",
    "gn:name":"Arroyo de San Andr\u00e9s",
    "gn:population":70,
    "gn:timezone":"America/Chihuahua",
    "iso:country":"MX",
    "name:und_x_variant":[
        "Arroyo de San Andr\u00e9s"
    ],
    "wof:name":"Arroyo de San Andres",
    "wof:placetype":"locality",
    "wof:population":70
},
  "geometry": {"coordinates":[-107.63292,26.21606],"type":"Point"}
}