{
  "type": "Feature",
  "properties": {
    "gn:admin1_code":"14",
    "gn:admin2_code":"120.0",
    "gn:asciiname":"Rancho Contento",
    "gn:country_code":"MX",
    "gn:dem":1676,
    "gn:feature_class":"P",
    "gn:feature_code":"PPL",
    "gn:name":"Rancho Contento",
    "gn:population":789,
    "gn:timezone":"America/Mexico_City",
    "iso:country":"MX",
    "wof:name":"Rancho Contento",
    "wof:placetype":"locality",
    "wof:population":789
},
  "geometry": {"coordinates":[-103.47750000000001,20.7125],"type":"Point"}
}