{
  "type": "Feature",
  "properties": {
    "gn:admin1_code":"10",
    "gn:admin2_code":"14.0",
    "gn:asciiname":"Los Espejos",
    "gn:country_code":"MX",
    "gn:dem":2285,
    "gn:feature_class":"P",
    "gn:feature_code":"PPL",
    "gn:name":"Los Espejos",
    "gn:population":72,
    "gn:timezone":"America/Mazatlan",
    "iso:country":"MX",
    "wof:name":"Los Espejos",
    "wof:placetype":"locality",
    "wof:population":72
},
  "geometry": {"coordinates":[-104.70773,22.62615],"type":"Point"}
}