{
  "type": "Feature",
  "properties": {
    "gn:admin1_code":"11.0",
    "gn:admin2_code":"37.0",
    "gn:asciiname":"Maravillas de las Victorias",
    "gn:country_code":"MX",
    "gn:dem":1749,
    "gn:feature_class":"P",
    "gn:feature_code":"PPL",
    "gn:name":"Maravillas de las Victorias",
    "gn:population":667,
    "gn:timezone":"America/Mexico_City",
    "iso:country":"MX",
    "name:und_x_variant":[
        "Maravillas",
        "Maravillas de las Victorias"
    ],
    "wof:name":"Maravillas de las Victorias",
    "wof:placetype":"locality",
    "wof:population":667
},
  "geometry": {"coordinates":[-101.47002999999999,20.85273],"type":"Point"}
}