{
  "type": "Feature",
  "properties": {
    "gn:admin1_code":"11.0",
    "gn:admin2_code":"30.0",
    "gn:asciiname":"Las Cenizas",
    "gn:country_code":"MX",
    "gn:dem":2481,
    "gn:feature_class":"P",
    "gn:feature_code":"PPL",
    "gn:name":"Las Cenizas",
    "gn:population":0,
    "gn:timezone":"America/Mexico_City",
    "iso:country":"MX",
    "name:spa_x_preferred":[
        "Las Cenizas"
    ],
    "wof:name":"Las Cenizas",
    "wof:placetype":"locality"
},
  "geometry": {"coordinates":[-101.4943,21.2969],"type":"Point"}
}