{
  "type": "Feature",
  "properties": {
    "gn:admin1_code":"17",
    "gn:admin2_code":"24",
    "gn:asciiname":"Campo el Alferez",
    "gn:country_code":"MX",
    "gn:dem":958,
    "gn:feature_class":"P",
    "gn:feature_code":"PPL",
    "gn:name":"Campo el Alf\u00e9rez",
    "gn:population":16,
    "gn:timezone":"America/Mexico_City",
    "iso:country":"MX",
    "name:und_x_variant":[
        "Campo el Alf\u00e9rez"
    ],
    "wof:name":"Campo el Alferez",
    "wof:placetype":"locality",
    "wof:population":16
},
  "geometry": {"coordinates":[-99.16306,18.68167],"type":"Point"}
}