{
  "type": "Feature",
  "properties": {
    "gn:admin1_code":"14",
    "gn:admin2_code":"19.0",
    "gn:asciiname":"Bajio de la Venada",
    "gn:country_code":"MX",
    "gn:dem":1656,
    "gn:feature_class":"P",
    "gn:feature_code":"PPL",
    "gn:name":"Baj\u00edo de la Venada",
    "gn:population":8,
    "gn:timezone":"America/Mazatlan",
    "iso:country":"MX",
    "name:und_x_variant":[
        "Baj\u00edo de la Venada"
    ],
    "wof:name":"Bajio de la Venada",
    "wof:placetype":"locality",
    "wof:population":8
},
  "geometry": {"coordinates":[-104.15167,21.81556],"type":"Point"}
}