{
  "type": "Feature",
  "properties": {
    "gn:admin1_code":"27.0",
    "gn:admin2_code":"1.0",
    "gn:asciiname":"El Pucte",
    "gn:country_code":"MX",
    "gn:dem":38,
    "gn:feature_class":"P",
    "gn:feature_code":"PPL",
    "gn:name":"El Puct\u00e9",
    "gn:population":0,
    "gn:timezone":"America/Mexico_City",
    "iso:country":"MX",
    "name:spa_x_preferred":[
        "El Pucte"
    ],
    "name:spa_x_variant":[
        "El Puct\u00e9"
    ],
    "wof:name":"El Pucte",
    "wof:placetype":"locality"
},
  "geometry": {"coordinates":[-91.16112,17.77615],"type":"Point"}
}