{
  "type": "Feature",
  "properties": {
    "gn:admin1_code":"20",
    "gn:admin2_code":"486.0",
    "gn:asciiname":"Tejupan de la Union",
    "gn:country_code":"MX",
    "gn:dem":2117,
    "gn:feature_class":"P",
    "gn:feature_code":"PPL",
    "gn:name":"Tejupan de la Uni\u00f3n",
    "gn:population":0,
    "gn:timezone":"America/Mexico_City",
    "iso:country":"MX",
    "name:spa_x_preferred":[
        "Tejupan de la Uni\u00f3n"
    ],
    "name:spa_x_variant":[
        "Santiago Tejupan"
    ],
    "wof:name":"Tejupan de la Union",
    "wof:placetype":"locality"
},
  "geometry": {"coordinates":[-97.46803,17.6651],"type":"Point"}
}