{
  "type": "Feature",
  "properties": {
    "gn:admin1_code":"20",
    "gn:admin2_code":"318.0",
    "gn:asciiname":"La Alejandria",
    "gn:country_code":"MX",
    "gn:dem":13,
    "gn:feature_class":"P",
    "gn:feature_code":"PPL",
    "gn:name":"La Alejandr\u00eda",
    "gn:population":26,
    "gn:timezone":"America/Mexico_City",
    "iso:country":"MX",
    "name:spa_x_preferred":[
        "Alejandria"
    ],
    "wof:name":"La Alejandria",
    "wof:placetype":"locality",
    "wof:population":26
},
  "geometry": {"coordinates":[-97.16667,15.93944],"type":"Point"}
}