{
  "type": "Feature",
  "properties": {
    "gn:admin1_code":"30.0",
    "gn:admin2_code":"160.0",
    "gn:asciiname":"El Salto Viejo",
    "gn:country_code":"MX",
    "gn:dem":116,
    "gn:feature_class":"P",
    "gn:feature_code":"PPL",
    "gn:name":"El Salto Viejo",
    "gn:population":75,
    "gn:timezone":"America/Mexico_City",
    "iso:country":"MX",
    "name:spa_x_preferred":[
        "El Salto Viejo"
    ],
    "wof:name":"El Salto Viejo",
    "wof:placetype":"locality",
    "wof:population":75
},
  "geometry": {"coordinates":[-97.9175,21.02806],"type":"Point"}
}