{
  "type": "Feature",
  "properties": {
    "gn:admin1_code":"6.0",
    "gn:admin2_code":"29.0",
    "gn:asciiname":"La Mesa Colorada",
    "gn:country_code":"MX",
    "gn:dem":2545,
    "gn:feature_class":"P",
    "gn:feature_code":"PPL",
    "gn:name":"La Mesa Colorada",
    "gn:population":0,
    "gn:timezone":"America/Chihuahua",
    "iso:country":"MX",
    "wof:name":"La Mesa Colorada",
    "wof:placetype":"locality"
},
  "geometry": {"coordinates":[-106.65000000000001,25.86667000000001],"type":"Point"}
}