{
  "type": "Feature",
  "properties": {
    "gn:admin1_code":"10",
    "gn:admin2_code":"32.0",
    "gn:asciiname":"El Palomar",
    "gn:country_code":"MX",
    "gn:dem":1714,
    "gn:feature_class":"P",
    "gn:feature_code":"PPL",
    "gn:name":"El Palomar",
    "gn:population":5,
    "gn:timezone":"America/Monterrey",
    "iso:country":"MX",
    "wof:name":"El Palomar",
    "wof:placetype":"locality",
    "wof:population":5
},
  "geometry": {"coordinates":[-105.43228999999999,25.07777],"type":"Point"}
}