{
  "type": "Feature",
  "properties": {
    "gn:admin1_code":"15",
    "gn:admin2_code":"86.0",
    "gn:asciiname":"Cieneguillas de Labra",
    "gn:country_code":"MX",
    "gn:dem":2872,
    "gn:feature_class":"P",
    "gn:feature_code":"PPL",
    "gn:name":"Cieneguillas de Labra",
    "gn:population":0,
    "gn:timezone":"America/Mexico_City",
    "iso:country":"MX",
    "name:und_x_variant":[
        "Cieneguillas de Labras",
        "Cieneguillas de Labra"
    ],
    "wof:name":"Cieneguillas de Labra",
    "wof:placetype":"locality"
},
  "geometry": {"coordinates":[-99.92341999999999,19.0101],"type":"Point"}
}