{
  "type": "Feature",
  "properties": {
    "gn:admin1_code":"2.0",
    "gn:admin2_code":"1.0",
    "gn:asciiname":"La Paloma",
    "gn:country_code":"MX",
    "gn:dem":290,
    "gn:feature_class":"P",
    "gn:feature_code":"PPL",
    "gn:name":"La Paloma",
    "gn:population":0,
    "gn:timezone":"America/Tijuana",
    "iso:country":"MX",
    "name:spa_x_preferred":[
        "La Paloma"
    ],
    "wof:name":"La Paloma",
    "wof:placetype":"locality"
},
  "geometry": {"coordinates":[-116.58875999999999,31.53118],"type":"Point"}
}