{
  "type": "Feature",
  "properties": {
    "gn:admin1_code":"24",
    "gn:admin2_code":"13.0",
    "gn:asciiname":"Loma de las Conchas",
    "gn:country_code":"MX",
    "gn:dem":55,
    "gn:feature_class":"P",
    "gn:feature_code":"PPL",
    "gn:name":"Loma de las Conchas",
    "gn:population":102,
    "gn:timezone":"America/Mexico_City",
    "iso:country":"MX",
    "wof:name":"Loma de las Conchas",
    "wof:placetype":"locality",
    "wof:population":102
},
  "geometry": {"coordinates":[-99.00917,21.8575],"type":"Point"}
}