{
  "type": "Feature",
  "properties": {
    "gn:admin1_code":"6.0",
    "gn:admin2_code":"10.0",
    "gn:asciiname":"Penuelas",
    "gn:country_code":"MX",
    "gn:dem":1603,
    "gn:feature_class":"P",
    "gn:feature_code":"PPL",
    "gn:name":"Pe\u00f1uelas",
    "gn:population":0,
    "gn:timezone":"America/Chihuahua",
    "iso:country":"MX",
    "name:spa_x_preferred":[
        "Pe\u00f1uelas"
    ],
    "wof:name":"Penuelas",
    "wof:placetype":"locality"
},
  "geometry": {"coordinates":[-107.42494000000001,29.72279],"type":"Point"}
}