{
  "type": "Feature",
  "properties": {
    "gn:admin1_code":"30",
    "gn:admin2_code":"108.0",
    "gn:asciiname":"Adalberto Tejeda",
    "gn:country_code":"MX",
    "gn:dem":23,
    "gn:feature_class":"P",
    "gn:feature_code":"PPL",
    "gn:name":"Adalberto Tejeda",
    "gn:population":0,
    "gn:timezone":"America/Mexico_City",
    "iso:country":"MX",
    "name:spa_x_preferred":[
        "Adalberto Tejeda"
    ],
    "name:spa_x_variant":[
        "General Adalberto Tejeda"
    ],
    "wof:name":"Adalberto Tejeda",
    "wof:placetype":"locality"
},
  "geometry": {"coordinates":[-94.52947,17.65413999999999],"type":"Point"}
}