{
  "type": "Feature",
  "properties": {
    "gn:admin1_code":"21",
    "gn:admin2_code":"42.0",
    "gn:asciiname":"El Limon",
    "gn:country_code":"MX",
    "gn:dem":1208,
    "gn:feature_class":"P",
    "gn:feature_code":"PPL",
    "gn:name":"El Lim\u00f3n",
    "gn:population":73,
    "gn:timezone":"America/Mexico_City",
    "iso:country":"MX",
    "name:und_x_variant":[
        "El Lim\u00f3n"
    ],
    "wof:name":"El Limon",
    "wof:placetype":"locality",
    "wof:population":73
},
  "geometry": {"coordinates":[-98.20025,18.42074],"type":"Point"}
}