{
  "type": "Feature",
  "properties": {
    "gn:admin1_code":"30",
    "gn:admin2_code":"202.0",
    "gn:asciiname":"Tenamicoya",
    "gn:country_code":"MX",
    "gn:dem":1152,
    "gn:feature_class":"P",
    "gn:feature_code":"PPL",
    "gn:name":"Tenamicoya",
    "gn:population":322,
    "gn:timezone":"America/Mexico_City",
    "iso:country":"MX",
    "name:spa_x_preferred":[
        "Tenamicoya"
    ],
    "wof:name":"Tenamicoya",
    "wof:placetype":"locality",
    "wof:population":322
},
  "geometry": {"coordinates":[-98.32514,20.71553],"type":"Point"}
}