{
  "type": "Feature",
  "properties": {
    "gn:admin1_code":"20",
    "gn:admin2_code":"455.0",
    "gn:asciiname":"Mogote Colorado (San Isidro)",
    "gn:country_code":"MX",
    "gn:dem":1701,
    "gn:feature_class":"P",
    "gn:feature_code":"PPL",
    "gn:name":"Mogote Colorado (San Isidro)",
    "gn:population":303,
    "gn:timezone":"America/Mexico_City",
    "iso:country":"MX",
    "wof:name":"Mogote Colorado (San Isidro)",
    "wof:placetype":"locality",
    "wof:population":303
},
  "geometry": {"coordinates":[-97.96611,17.91417000000001],"type":"Point"}
}