{
  "type": "Feature",
  "properties": {
    "gn:admin1_code":"7.0",
    "gn:admin2_code":"30.0",
    "gn:asciiname":"El Meson",
    "gn:country_code":"MX",
    "gn:dem":1483,
    "gn:feature_class":"P",
    "gn:feature_code":"PPL",
    "gn:name":"El Mes\u00f3n",
    "gn:population":20,
    "gn:timezone":"America/Monterrey",
    "iso:country":"MX",
    "name:spa_x_preferred":[
        "El Mes\u00f3n"
    ],
    "name:und_x_variant":[
        "El Mez\u00f3n"
    ],
    "wof:name":"El Meson",
    "wof:placetype":"locality",
    "wof:population":20
},
  "geometry": {"coordinates":[-101.23068000000001,25.44176],"type":"Point"}
}