{
  "type": "Feature",
  "properties": {
    "gn:admin1_code":"14",
    "gn:admin2_code":"118.0",
    "gn:asciiname":"Tecoluta",
    "gn:country_code":"MX",
    "gn:dem":1806,
    "gn:feature_class":"P",
    "gn:feature_code":"PPL",
    "gn:name":"Tecoluta",
    "gn:population":337,
    "gn:timezone":"America/Mexico_City",
    "iso:country":"MX",
    "wof:name":"Tecoluta",
    "wof:placetype":"locality",
    "wof:population":337
},
  "geometry": {"coordinates":[-102.86972,21.18056],"type":"Point"}
}