{
  "type": "Feature",
  "properties": {
    "gn:admin1_code":"12",
    "gn:admin2_code":"18.0",
    "gn:asciiname":"Las Salinas",
    "gn:country_code":"MX",
    "gn:dem":20,
    "gn:feature_class":"P",
    "gn:feature_code":"PPL",
    "gn:name":"Las Salinas",
    "gn:population":0,
    "gn:timezone":"America/Mexico_City",
    "iso:country":"MX",
    "name:ceb_x_preferred":[
        "Las Salinas"
    ],
    "name:ita_x_preferred":[
        "Las Salinas"
    ],
    "name:por_x_preferred":[
        "Las Salinas"
    ],
    "name:spa_x_preferred":[
        "Las Salinas"
    ],
    "name:und_x_variant":[
        "Ojo de Agua las Salinas"
    ],
    "name:urd_x_preferred":[
        "\u0644\u0627\u0633 \u0633\u0627\u0644\u06cc\u0646\u0627\u0633"
    ],
    "name:zho_x_preferred":[
        "\u62c9\u65af\u85a9\u5229\u7d0d\u65af"
    ],
    "wof:name":"Las Salinas",
    "wof:placetype":"locality"
},
  "geometry": {"coordinates":[-98.85214000000001,16.56606],"type":"Point"}
}