{
  "type": "Feature",
  "properties": {
    "gn:admin1_code":"26.0",
    "gn:admin2_code":"46.0",
    "gn:asciiname":"Baldenegro",
    "gn:cc2":"MX",
    "gn:country_code":"MX",
    "gn:dem":488,
    "gn:feature_class":"P",
    "gn:feature_code":"PPL",
    "gn:name":"Baldenegro",
    "gn:population":0,
    "gn:timezone":"America/Hermosillo",
    "iso:country":"MX",
    "name:und_x_variant":[
        "Valdenegro",
        "Baldenegro"
    ],
    "wof:name":"Baldenegro",
    "wof:placetype":"locality"
},
  "geometry": {"coordinates":[-111.71666999999999,30.73333],"type":"Point"}
}