{
  "type": "Feature",
  "properties": {
    "gn:admin1_code":"20.0",
    "gn:asciiname":"Hierba Santa",
    "gn:country_code":"MX",
    "gn:dem":1500,
    "gn:feature_class":"P",
    "gn:feature_code":"PPL",
    "gn:name":"Hierba Santa",
    "gn:population":0,
    "gn:timezone":"America/Mexico_City",
    "iso:country":"MX",
    "name:spa_x_preferred":[
        "Hierba Santa"
    ],
    "wof:name":"Hierba Santa",
    "wof:placetype":"locality"
},
  "geometry": {"coordinates":[-96.20807000000001,16.01457000000001],"type":"Point"}
}