{
  "type": "Feature",
  "properties": {
    "gn:admin1_code":"6",
    "gn:admin2_code":"28.0",
    "gn:asciiname":"San Antonio",
    "gn:country_code":"MX",
    "gn:dem":1368,
    "gn:feature_class":"P",
    "gn:feature_code":"PPL",
    "gn:name":"San Antonio",
    "gn:population":3,
    "gn:timezone":"America/Chihuahua",
    "iso:country":"MX",
    "name:und_x_variant":[
        "Rancho San Antonio",
        "San Antonio"
    ],
    "wof:name":"San Antonio",
    "wof:placetype":"locality",
    "wof:population":3
},
  "geometry": {"coordinates":[-105.99843,31.00634],"type":"Point"}
}