{
  "type": "Feature",
  "properties": {
    "gn:admin1_code":"21",
    "gn:admin2_code":"195",
    "gn:asciiname":"Ahuatepec",
    "gn:country_code":"MX",
    "gn:dem":2288,
    "gn:feature_class":"P",
    "gn:feature_code":"PPL",
    "gn:name":"Ahuatepec",
    "gn:population":50,
    "gn:timezone":"America/Mexico_City",
    "iso:country":"MX",
    "wof:name":"Ahuatepec",
    "wof:placetype":"locality",
    "wof:population":50
},
  "geometry": {"coordinates":[-97.17305,18.45634],"type":"Point"}
}