{
  "type": "Feature",
  "properties": {
    "gn:admin1_code":"5",
    "gn:admin2_code":"99.0",
    "gn:asciiname":"Ruben Jaramillo",
    "gn:country_code":"MX",
    "gn:dem":798,
    "gn:feature_class":"P",
    "gn:feature_code":"PPL",
    "gn:name":"Rub\u00e9n Jaramillo",
    "gn:population":0,
    "gn:timezone":"America/Mexico_City",
    "iso:country":"MX",
    "name:spa_x_preferred":[
        "El Rosario"
    ],
    "name:spa_x_variant":[
        "Rub\u00e9n Jaramillo"
    ],
    "name:und_x_variant":[
        "Rosario"
    ],
    "wof:name":"Ruben Jaramillo",
    "wof:placetype":"locality"
},
  "geometry": {"coordinates":[-91.97593000000001,15.99041],"type":"Point"}
}