{
  "type": "Feature",
  "properties": {
    "gn:admin1_code":"5",
    "gn:admin2_code":"19.0",
    "gn:asciiname":"San Antonio Bellavista",
    "gn:country_code":"MX",
    "gn:dem":2145,
    "gn:feature_class":"P",
    "gn:feature_code":"PPL",
    "gn:name":"San Antonio Bellavista",
    "gn:population":211,
    "gn:timezone":"America/Mexico_City",
    "iso:country":"MX",
    "wof:name":"San Antonio Bellavista",
    "wof:placetype":"locality",
    "wof:population":211
},
  "geometry": {"coordinates":[-92.29222,16.47611],"type":"Point"}
}