{
  "type": "Feature",
  "properties": {
    "gn:admin1_code":"20",
    "gn:admin2_code":"134.0",
    "gn:asciiname":"Paso Carretero",
    "gn:country_code":"MX",
    "gn:dem":108,
    "gn:feature_class":"P",
    "gn:feature_code":"PPL",
    "gn:name":"Paso Carretero",
    "gn:population":396,
    "gn:timezone":"America/Mexico_City",
    "iso:country":"MX",
    "wof:name":"Paso Carretero",
    "wof:placetype":"locality",
    "wof:population":396
},
  "geometry": {"coordinates":[-96.53389,18.04722000000001],"type":"Point"}
}