{
  "type": "Feature",
  "properties": {
    "gn:admin1_code":"11.0",
    "gn:admin2_code":"22.0",
    "gn:asciiname":"La Alberca",
    "gn:country_code":"MX",
    "gn:dem":2178,
    "gn:feature_class":"P",
    "gn:feature_code":"PPL",
    "gn:name":"La Alberca",
    "gn:population":0,
    "gn:timezone":"America/Mexico_City",
    "iso:country":"MX",
    "name:spa_x_preferred":[
        "La Alberca"
    ],
    "name:spa_x_variant":[
        "Laguna la Alberca"
    ],
    "wof:name":"La Alberca",
    "wof:placetype":"locality"
},
  "geometry": {"coordinates":[-101.42127000000001,21.62362000000001],"type":"Point"}
}