{
  "type": "Feature",
  "properties": {
    "gn:admin1_code":"11.0",
    "gn:admin2_code":"22.0",
    "gn:asciiname":"La Alberca",
    "gn:country_code":"MX",
    "gn:dem":2178,
    "gn:feature_class":"P",
    "gn:feature_code":"PPL",
    "gn:name":"La Alberca",
    "gn:population":0,
    "gn:timezone":"America/Mexico_City",
    "iso:country":"MX",
    "name:arg_x_preferred":[
        "La Alberca"
    ],
    "name:ast_x_preferred":[
        "La Alberca"
    ],
    "name:cat_x_preferred":[
        "La Alberca"
    ],
    "name:ceb_x_preferred":[
        "La Alberca"
    ],
    "name:deu_x_preferred":[
        "La Alberca"
    ],
    "name:eus_x_preferred":[
        "La Alberca"
    ],
    "name:fra_x_preferred":[
        "La Alberca"
    ],
    "name:glg_x_preferred":[
        "La Alberca"
    ],
    "name:haw_x_preferred":[
        "La Alberca"
    ],
    "name:hun_x_preferred":[
        "La Alberca"
    ],
    "name:ina_x_preferred":[
        "La Alberca"
    ],
    "name:ita_x_preferred":[
        "La Alberca"
    ],
    "name:kaz_x_preferred":[
        "\u041b\u0430-\u0410\u043b\u044c\u0431\u0435\u0440\u043a\u0430"
    ],
    "name:msa_x_preferred":[
        "La Alberca"
    ],
    "name:nld_x_preferred":[
        "La Alberca"
    ],
    "name:oci_x_preferred":[
        "La Alberca"
    ],
    "name:pol_x_preferred":[
        "La Alberca"
    ],
    "name:por_x_preferred":[
        "La Alberca"
    ],
    "name:rus_x_preferred":[
        "\u041b\u0430-\u0410\u043b\u044c\u0431\u0435\u0440\u043a\u0430"
    ],
    "name:spa_x_preferred":[
        "La Alberca"
    ],
    "name:spa_x_variant":[
        "Laguna la Alberca"
    ],
    "name:swe_x_preferred":[
        "La Alberca"
    ],
    "name:ukr_x_preferred":[
        "\u041b\u0430-\u0410\u043b\u044c\u0431\u0435\u0440\u043a\u0430"
    ],
    "name:uzb_x_preferred":[
        "La Alberca"
    ],
    "name:war_x_preferred":[
        "La Alberca"
    ],
    "name:zho_x_preferred":[
        "\u62c9\u5c14\u97e6\u5c14\u5361"
    ],
    "wof:name":"La Alberca",
    "wof:placetype":"locality"
},
  "geometry": {"coordinates":[-101.42127000000001,21.62362000000001],"type":"Point"}
}