{
  "type": "Feature",
  "properties": {
    "gn:admin1_code":"16",
    "gn:admin2_code":"52.0",
    "gn:asciiname":"El Cayaquito",
    "gn:country_code":"MX",
    "gn:dem":485,
    "gn:feature_class":"P",
    "gn:feature_code":"PPL",
    "gn:name":"El Cayaquito",
    "gn:population":0,
    "gn:timezone":"America/Mexico_City",
    "iso:country":"MX",
    "name:spa_x_preferred":[
        "El Cayaquito"
    ],
    "wof:name":"El Cayaquito",
    "wof:placetype":"locality"
},
  "geometry": {"coordinates":[-102.26219,18.1844],"type":"Point"}
}