{
  "type": "Feature",
  "properties": {
    "gn:admin1_code":"4.0",
    "gn:asciiname":"Las Gradas",
    "gn:country_code":"MX",
    "gn:dem":4,
    "gn:feature_class":"P",
    "gn:feature_code":"PPL",
    "gn:name":"Las Gradas",
    "gn:population":0,
    "gn:timezone":"America/Merida",
    "iso:country":"MX",
    "name:spa_x_preferred":[
        "Las Gradas"
    ],
    "wof:name":"Las Gradas",
    "wof:placetype":"locality"
},
  "geometry": {"coordinates":[-91.75877,18.64322],"type":"Point"}
}