{
  "type": "Feature",
  "properties": {
    "gn:admin1_code":"5",
    "gn:admin2_code":"70.0",
    "gn:asciiname":"Cuatro Caminos",
    "gn:country_code":"MX",
    "gn:dem":2808,
    "gn:feature_class":"P",
    "gn:feature_code":"PPL",
    "gn:name":"Cuatro Caminos",
    "gn:population":301,
    "gn:timezone":"America/Mexico_City",
    "iso:country":"MX",
    "wof:name":"Cuatro Caminos",
    "wof:placetype":"locality",
    "wof:population":301
},
  "geometry": {"coordinates":[-92.24194,15.45444],"type":"Point"}
}