{
  "type": "Feature",
  "properties": {
    "gn:admin1_code":"18.0",
    "gn:asciiname":"La Curva",
    "gn:country_code":"MX",
    "gn:dem":1117,
    "gn:feature_class":"P",
    "gn:feature_code":"PPL",
    "gn:name":"La Curva",
    "gn:population":0,
    "gn:timezone":"America/Mazatlan",
    "iso:country":"MX",
    "wof:name":"La Curva",
    "wof:placetype":"locality"
},
  "geometry": {"coordinates":[-104.23316,21.06188],"type":"Point"}
}