{
  "type": "Feature",
  "properties": {
    "gn:admin1_code":"6",
    "gn:admin2_code":"31.0",
    "gn:asciiname":"Rancho Rascon",
    "gn:country_code":"MX",
    "gn:dem":2122,
    "gn:feature_class":"P",
    "gn:feature_code":"PPL",
    "gn:name":"Rancho Rasc\u00f3n",
    "gn:population":4,
    "gn:timezone":"America/Chihuahua",
    "iso:country":"MX",
    "name:und_x_variant":[
        "Rancho Rasc\u00f3n"
    ],
    "wof:name":"Rancho Rascon",
    "wof:placetype":"locality",
    "wof:population":4
},
  "geometry": {"coordinates":[-107.20556000000001,28.43056],"type":"Point"}
}