{
  "type": "Feature",
  "properties": {
    "gn:admin1_code":"3",
    "gn:admin2_code":"2.0",
    "gn:asciiname":"El Norte",
    "gn:country_code":"MX",
    "gn:dem":261,
    "gn:feature_class":"P",
    "gn:feature_code":"PPL",
    "gn:name":"El Norte",
    "gn:population":5,
    "gn:timezone":"America/Mazatlan",
    "iso:country":"MX",
    "name:ceb_x_preferred":[
        "El Norte"
    ],
    "name:srp_x_preferred":[
        "\u0415\u043b \u041d\u043e\u0440\u0442\u0435"
    ],
    "name:swe_x_preferred":[
        "El Norte"
    ],
    "wof:name":"El Norte",
    "wof:placetype":"locality",
    "wof:population":5
},
  "geometry": {"coordinates":[-112.2594,27.13654],"type":"Point"}
}