{
  "type": "Feature",
  "properties": {
    "gn:admin1_code":"26",
    "gn:admin2_code":"40.0",
    "gn:asciiname":"Las Delicias (Guadalupe Duran)",
    "gn:country_code":"MX",
    "gn:dem":1558,
    "gn:feature_class":"P",
    "gn:feature_code":"PPL",
    "gn:name":"Las Delicias (Guadalupe Duran)",
    "gn:population":6,
    "gn:timezone":"America/Hermosillo",
    "iso:country":"MX",
    "wof:name":"Las Delicias (Guadalupe Duran)",
    "wof:placetype":"locality",
    "wof:population":6
},
  "geometry": {"coordinates":[-108.63667,29.82361],"type":"Point"}
}