{
  "type": "Feature",
  "properties": {
    "gn:admin1_code":"20",
    "gn:admin2_code":"380.0",
    "gn:asciiname":"Primera Seccion",
    "gn:country_code":"MX",
    "gn:dem":1582,
    "gn:feature_class":"P",
    "gn:feature_code":"PPL",
    "gn:name":"Primera Secci\u00f3n",
    "gn:population":85,
    "gn:timezone":"America/Mexico_City",
    "iso:country":"MX",
    "name:und_x_variant":[
        "Primera Secci\u00f3n"
    ],
    "wof:name":"Primera Seccion",
    "wof:placetype":"locality",
    "wof:population":85
},
  "geometry": {"coordinates":[-96.58306,16.96222],"type":"Point"}
}