{
  "type": "Feature",
  "properties": {
    "gn:admin1_code":"16.0",
    "gn:admin2_code":"95.0",
    "gn:asciiname":"Palo Martinez",
    "gn:country_code":"MX",
    "gn:dem":1288,
    "gn:feature_class":"P",
    "gn:feature_code":"PPL",
    "gn:name":"Palo Mart\u00ednez",
    "gn:population":0,
    "gn:timezone":"America/Mexico_City",
    "iso:country":"MX",
    "name:spa_x_preferred":[
        "Palo Mart\u00ednez"
    ],
    "wof:name":"Palo Martinez",
    "wof:placetype":"locality"
},
  "geometry": {"coordinates":[-102.60176,19.62281],"type":"Point"}
}