{
  "type": "Feature",
  "properties": {
    "gn:admin1_code":"31",
    "gn:admin2_code":"38.0",
    "gn:asciiname":"Tacubaya",
    "gn:country_code":"MX",
    "gn:dem":2,
    "gn:feature_class":"P",
    "gn:feature_code":"PPL",
    "gn:name":"Tacubaya",
    "gn:population":2,
    "gn:timezone":"America/Merida",
    "iso:country":"MX",
    "name:ceb_x_preferred":[
        "Tacubaya"
    ],
    "name:deu_x_preferred":[
        "Tacubaya"
    ],
    "name:ind_x_preferred":[
        "Tacubaya"
    ],
    "name:nld_x_preferred":[
        "Tacubaya"
    ],
    "name:nor_x_preferred":[
        "Tacubaya"
    ],
    "name:spa_x_preferred":[
        "Tacubaya"
    ],
    "name:tam_x_preferred":[
        "\u0b87\u0b9f\u0bcd\u0b9f\u0bbe\u0b95\u0bcd\u0b95\u0bc1\u0baa\u0bc8\u0baf\u0bbe"
    ],
    "wof:name":"Tacubaya",
    "wof:placetype":"locality",
    "wof:population":2
},
  "geometry": {"coordinates":[-89.87639,21.08194],"type":"Point"}
}