{
  "type": "Feature",
  "properties": {
    "gn:admin1_code":"3",
    "gn:admin2_code":"3.0",
    "gn:asciiname":"Poza del Caballo",
    "gn:country_code":"MX",
    "gn:dem":419,
    "gn:feature_class":"P",
    "gn:feature_code":"PPL",
    "gn:name":"Poza del Caballo",
    "gn:population":0,
    "gn:timezone":"America/Mazatlan",
    "iso:country":"MX",
    "name:spa_x_preferred":[
        "Poza del Caballo"
    ],
    "wof:name":"Poza del Caballo",
    "wof:placetype":"locality"
},
  "geometry": {"coordinates":[-110.80046000000002,24.87159],"type":"Point"}
}