{
  "type": "Feature",
  "properties": {
    "gn:admin1_code":"30",
    "gn:admin2_code":"23.0",
    "gn:asciiname":"El Fortin",
    "gn:country_code":"MX",
    "gn:dem":439,
    "gn:feature_class":"P",
    "gn:feature_code":"PPL",
    "gn:name":"El Fort\u00edn",
    "gn:population":298,
    "gn:timezone":"America/Mexico_City",
    "iso:country":"MX",
    "name:und_x_variant":[
        "El Fort\u00edn"
    ],
    "wof:name":"El Fortin",
    "wof:placetype":"locality",
    "wof:population":298
},
  "geometry": {"coordinates":[-97.08167,19.91722],"type":"Point"}
}