{
  "type": "Feature",
  "properties": {
    "gn:admin1_code":"21",
    "gn:admin2_code":"43.0",
    "gn:asciiname":"Tepango",
    "gn:country_code":"MX",
    "gn:dem":594,
    "gn:feature_class":"P",
    "gn:feature_code":"PPL",
    "gn:name":"Tepango",
    "gn:population":279,
    "gn:timezone":"America/Mexico_City",
    "iso:country":"MX",
    "wof:name":"Tepango",
    "wof:placetype":"locality",
    "wof:population":279
},
  "geometry": {"coordinates":[-97.42780999999999,20.02954],"type":"Point"}
}