{
  "type": "Feature",
  "properties": {
    "gn:admin1_code":"28.0",
    "gn:admin2_code":"27.0",
    "gn:asciiname":"Don Ramon",
    "gn:country_code":"MX",
    "gn:dem":153,
    "gn:feature_class":"P",
    "gn:feature_code":"PPL",
    "gn:name":"Don Ram\u00f3n",
    "gn:population":3,
    "gn:timezone":"America/Matamoros",
    "iso:country":"MX",
    "name:spa_x_preferred":[
        "Don Ram\u00f3n"
    ],
    "wof:name":"Don Ramon",
    "wof:placetype":"locality",
    "wof:population":3
},
  "geometry": {"coordinates":[-99.60387,27.28912],"type":"Point"}
}