{
  "type": "Feature",
  "properties": {
    "gn:admin1_code":"16",
    "gn:admin2_code":"97.0",
    "gn:asciiname":"El Naranjito",
    "gn:country_code":"MX",
    "gn:dem":1213,
    "gn:feature_class":"P",
    "gn:feature_code":"PPL",
    "gn:name":"El Naranjito",
    "gn:population":0,
    "gn:timezone":"America/Mexico_City",
    "iso:country":"MX",
    "name:spa_x_preferred":[
        "El Naranjito"
    ],
    "wof:name":"El Naranjito",
    "wof:placetype":"locality"
},
  "geometry": {"coordinates":[-101.53995999999999,18.98],"type":"Point"}
}