{
  "type": "Feature",
  "properties": {
    "gn:admin1_code":"21",
    "gn:admin2_code":"4",
    "gn:asciiname":"San Miguel Dorantes (Xaltepec)",
    "gn:country_code":"MX",
    "gn:dem":2235,
    "gn:feature_class":"P",
    "gn:feature_code":"PPL",
    "gn:name":"San Miguel Dorantes (Xaltepec)",
    "gn:population":38,
    "gn:timezone":"America/Mexico_City",
    "iso:country":"MX",
    "wof:name":"San Miguel Dorantes (Xaltepec)",
    "wof:placetype":"locality",
    "wof:population":38
},
  "geometry": {"coordinates":[-97.72727,19.03366],"type":"Point"}
}