{
  "type": "Feature",
  "properties": {
    "gn:admin1_code":"19.0",
    "gn:asciiname":"Los Sabinos",
    "gn:country_code":"MX",
    "gn:dem":355,
    "gn:feature_class":"P",
    "gn:feature_code":"PPL",
    "gn:name":"Los Sabinos",
    "gn:population":0,
    "gn:timezone":"America/Monterrey",
    "iso:country":"MX",
    "name:spa_x_preferred":[
        "Los Sabinos"
    ],
    "wof:name":"Los Sabinos",
    "wof:placetype":"locality"
},
  "geometry": {"coordinates":[-99.59220999999999,24.88556],"type":"Point"}
}