{
  "type": "Feature",
  "properties": {
    "gn:admin1_code":"12",
    "gn:admin2_code":"13.0",
    "gn:asciiname":"San Isidro el Puente (El Puente)",
    "gn:country_code":"MX",
    "gn:dem":180,
    "gn:feature_class":"P",
    "gn:feature_code":"PPL",
    "gn:name":"San Isidro el Puente (El Puente)",
    "gn:population":656,
    "gn:timezone":"America/Mexico_City",
    "iso:country":"MX",
    "wof:name":"San Isidro el Puente (El Puente)",
    "wof:placetype":"locality",
    "wof:population":656
},
  "geometry": {"coordinates":[-98.62694,16.655],"type":"Point"}
}