{
  "type": "Feature",
  "properties": {
    "gn:admin1_code":"15",
    "gn:admin2_code":"48.0",
    "gn:asciiname":"Zacualpan",
    "gn:country_code":"MX",
    "gn:dem":2535,
    "gn:feature_class":"P",
    "gn:feature_code":"PPL",
    "gn:name":"Zacualpan",
    "gn:population":243,
    "gn:timezone":"America/Mexico_City",
    "iso:country":"MX",
    "wof:name":"Zacualpan",
    "wof:placetype":"locality",
    "wof:population":243
},
  "geometry": {"coordinates":[-99.84193999999999,19.74528],"type":"Point"}
}