{
  "type": "Feature",
  "properties": {
    "gn:admin1_code":"30",
    "gn:admin2_code":"73.0",
    "gn:asciiname":"Cuatotolapan Viejo",
    "gn:country_code":"MX",
    "gn:dem":33,
    "gn:feature_class":"P",
    "gn:feature_code":"PPL",
    "gn:name":"Cuatotolapan Viejo",
    "gn:population":0,
    "gn:timezone":"America/Mexico_City",
    "iso:country":"MX",
    "name:spa_x_preferred":[
        "Cuatotolapan Viejo"
    ],
    "wof:name":"Cuatotolapan Viejo",
    "wof:placetype":"locality"
},
  "geometry": {"coordinates":[-95.26627000000001,18.14596],"type":"Point"}
}