{
  "type": "Feature",
  "properties": {
    "gn:admin1_code":"31",
    "gn:asciiname":"X-Querol",
    "gn:country_code":"MX",
    "gn:dem":32,
    "gn:feature_class":"P",
    "gn:feature_code":"PPL",
    "gn:name":"X-Querol",
    "gn:population":0,
    "gn:timezone":"America/Cancun",
    "iso:country":"MX",
    "name:spa_x_preferred":[
        "X-Querol"
    ],
    "wof:name":"X-Querol",
    "wof:placetype":"locality"
},
  "geometry": {"coordinates":[-88.61666,20.13166],"type":"Point"}
}