{
  "type": "Feature",
  "properties": {
    "gn:admin1_code":"28",
    "gn:admin2_code":"5.0",
    "gn:asciiname":"Rancho El Perdido",
    "gn:country_code":"MX",
    "gn:dem":98,
    "gn:feature_class":"P",
    "gn:feature_code":"PPL",
    "gn:name":"Rancho El Perdido",
    "gn:population":0,
    "gn:timezone":"America/Monterrey",
    "iso:country":"MX",
    "wof:name":"Rancho El Perdido",
    "wof:placetype":"locality"
},
  "geometry": {"coordinates":[-98.68183999999999,25.03377],"type":"Point"}
}