{
  "type": "Feature",
  "properties": {
    "gn:admin1_code":"6",
    "gn:admin2_code":"48.0",
    "gn:asciiname":"La Raspadura",
    "gn:country_code":"MX",
    "gn:dem":1982,
    "gn:feature_class":"P",
    "gn:feature_code":"PPL",
    "gn:name":"La Raspadura",
    "gn:population":4,
    "gn:timezone":"America/Chihuahua",
    "iso:country":"MX",
    "wof:name":"La Raspadura",
    "wof:placetype":"locality",
    "wof:population":4
},
  "geometry": {"coordinates":[-107.57196999999999,29.0457],"type":"Point"}
}