{
  "type": "Feature",
  "properties": {
    "gn:admin1_code":"6",
    "gn:admin2_code":"9",
    "gn:asciiname":"El Rincon",
    "gn:country_code":"MX",
    "gn:dem":2476,
    "gn:feature_class":"P",
    "gn:feature_code":"PPL",
    "gn:name":"El Rinc\u00f3n",
    "gn:population":12,
    "gn:timezone":"America/Chihuahua",
    "iso:country":"MX",
    "name:und_x_variant":[
        "El Rinc\u00f3n"
    ],
    "wof:name":"El Rincon",
    "wof:placetype":"locality",
    "wof:population":12
},
  "geometry": {"coordinates":[-107.60993999999999,28.05102],"type":"Point"}
}