{
  "type": "Feature",
  "properties": {
    "gn:admin1_code":"26",
    "gn:admin2_code":"3.0",
    "gn:asciiname":"Sobia",
    "gn:country_code":"MX",
    "gn:dem":151,
    "gn:feature_class":"P",
    "gn:feature_code":"PPL",
    "gn:name":"Sobia",
    "gn:population":0,
    "gn:timezone":"America/Hermosillo",
    "iso:country":"MX",
    "name:spa_x_preferred":[
        "Sobia"
    ],
    "name:und_x_variant":[
        "Sob\u00eda"
    ],
    "wof:name":"Sobia",
    "wof:placetype":"locality"
},
  "geometry": {"coordinates":[-109.1678,27.29451],"type":"Point"}
}