{
  "type": "Feature",
  "properties": {
    "gn:admin1_code":"15.0",
    "gn:admin2_code":"123.0",
    "gn:asciiname":"Jaquinicuil",
    "gn:country_code":"MX",
    "gn:dem":1352,
    "gn:feature_class":"P",
    "gn:feature_code":"PPL",
    "gn:name":"Jaquinicuil",
    "gn:population":0,
    "gn:timezone":"America/Mexico_City",
    "iso:country":"MX",
    "name:spa_x_preferred":[
        "Jaquinicuil"
    ],
    "name:und_x_variant":[
        "Jequinicuil"
    ],
    "wof:name":"Jaquinicuil",
    "wof:placetype":"locality"
},
  "geometry": {"coordinates":[-100.25959,18.86129],"type":"Point"}
}