{
  "type": "Feature",
  "properties": {
    "gn:admin1_code":"14.0",
    "gn:admin2_code":"87.0",
    "gn:asciiname":"Piedra Iman",
    "gn:country_code":"MX",
    "gn:dem":766,
    "gn:feature_class":"P",
    "gn:feature_code":"PPL",
    "gn:name":"Piedra Im\u00e1n",
    "gn:population":0,
    "gn:timezone":"America/Mexico_City",
    "iso:country":"MX",
    "name:spa_x_preferred":[
        "Piedra Im\u00e1n"
    ],
    "wof:name":"Piedra Iman",
    "wof:placetype":"locality"
},
  "geometry": {"coordinates":[-103.16087,19.06063],"type":"Point"}
}