{
  "type": "Feature",
  "properties": {
    "gn:admin1_code":"10",
    "gn:admin2_code":"18.0",
    "gn:asciiname":"Jicorilla",
    "gn:country_code":"MX",
    "gn:dem":1435,
    "gn:feature_class":"P",
    "gn:feature_code":"PPL",
    "gn:name":"Jicorilla",
    "gn:population":0,
    "gn:timezone":"America/Monterrey",
    "iso:country":"MX",
    "name:spa_x_preferred":[
        "Jicorilla"
    ],
    "name:und_x_variant":[
        "Licorillas"
    ],
    "wof:name":"Jicorilla",
    "wof:placetype":"locality"
},
  "geometry": {"coordinates":[-104.83873,25.39915],"type":"Point"}
}