{
  "type": "Feature",
  "properties": {
    "gn:admin1_code":"21",
    "gn:admin2_code":"76.0",
    "gn:asciiname":"Limontitan Grande",
    "gn:country_code":"MX",
    "gn:dem":536,
    "gn:feature_class":"P",
    "gn:feature_code":"PPL",
    "gn:name":"Limontit\u00e1n Grande",
    "gn:population":548,
    "gn:timezone":"America/Mexico_City",
    "iso:country":"MX",
    "name:und_x_variant":[
        "Limontit\u00e1n Grande"
    ],
    "wof:name":"Limontitan Grande",
    "wof:placetype":"locality",
    "wof:population":548
},
  "geometry": {"coordinates":[-97.27889,19.98972],"type":"Point"}
}