{
  "type": "Feature",
  "properties": {
    "gn:admin1_code":"14.0",
    "gn:admin2_code":"84.0",
    "gn:asciiname":"El Rincon de Cabos",
    "gn:country_code":"MX",
    "gn:dem":1115,
    "gn:feature_class":"P",
    "gn:feature_code":"PPL",
    "gn:name":"El Rinc\u00f3n de Cabos",
    "gn:population":0,
    "gn:timezone":"America/Mexico_City",
    "iso:country":"MX",
    "name:spa_x_preferred":[
        "El Rinc\u00f3n de Cabos"
    ],
    "wof:name":"El Rincon de Cabos",
    "wof:placetype":"locality"
},
  "geometry": {"coordinates":[-104.89566000000001,20.52314],"type":"Point"}
}