{
  "type": "Feature",
  "properties": {
    "gn:admin1_code":"30",
    "gn:admin2_code":"188.0",
    "gn:asciiname":"Mata de Indio",
    "gn:country_code":"MX",
    "gn:dem":902,
    "gn:feature_class":"P",
    "gn:feature_code":"PPL",
    "gn:name":"Mata de Indio",
    "gn:population":1576,
    "gn:timezone":"America/Mexico_City",
    "iso:country":"MX",
    "name:spa_x_preferred":[
        "Mata de Indio"
    ],
    "wof:name":"Mata de Indio",
    "wof:placetype":"locality",
    "wof:population":1576
},
  "geometry": {"coordinates":[-96.84135999999999,19.23028],"type":"Point"}
}