{
  "type": "Feature",
  "properties": {
    "gn:admin1_code":"30",
    "gn:admin2_code":"174.0",
    "gn:asciiname":"El Tamarindo",
    "gn:country_code":"MX",
    "gn:dem":154,
    "gn:feature_class":"P",
    "gn:feature_code":"PPL",
    "gn:name":"El Tamarindo",
    "gn:population":0,
    "gn:timezone":"America/Mexico_City",
    "iso:country":"MX",
    "name:und_x_variant":[
        "Tamarindo",
        "El Tamarindo"
    ],
    "wof:name":"El Tamarindo",
    "wof:placetype":"locality",
    "wof:population":317
},
  "geometry": {"coordinates":[-96.52239,18.67318],"type":"Point"}
}