{
  "type": "Feature",
  "properties": {
    "gn:admin1_code":"13",
    "gn:admin2_code":"41.0",
    "gn:asciiname":"Los Angeles",
    "gn:country_code":"MX",
    "gn:dem":2019,
    "gn:feature_class":"P",
    "gn:feature_code":"PPL",
    "gn:name":"Los \u00c1ngeles",
    "gn:population":302,
    "gn:timezone":"America/Mexico_City",
    "iso:country":"MX",
    "name:und_x_variant":[
        "Los \u00c1ngeles"
    ],
    "wof:name":"Los Angeles",
    "wof:placetype":"locality",
    "wof:population":302
},
  "geometry": {"coordinates":[-99.18694000000001,20.19222],"type":"Point"}
}