{
  "type": "Feature",
  "properties": {
    "gn:admin1_code":"30",
    "gn:admin2_code":"116.0",
    "gn:asciiname":"Ojapa",
    "gn:country_code":"MX",
    "gn:dem":29,
    "gn:feature_class":"P",
    "gn:feature_code":"PPL",
    "gn:name":"Ojapa",
    "gn:population":0,
    "gn:timezone":"America/Mexico_City",
    "iso:country":"MX",
    "wof:name":"Ojapa",
    "wof:placetype":"locality"
},
  "geometry": {"coordinates":[-94.867,17.90018],"type":"Point"}
}