{
  "type": "Feature",
  "properties": {
    "gn:admin1_code":"30",
    "gn:admin2_code":"205.0",
    "gn:asciiname":"Primera Ampliacion del Chote",
    "gn:country_code":"MX",
    "gn:dem":35,
    "gn:feature_class":"P",
    "gn:feature_code":"PPL",
    "gn:name":"Primera Ampliaci\u00f3n del Chote",
    "gn:population":145,
    "gn:timezone":"America/Mexico_City",
    "iso:country":"MX",
    "name:und_x_variant":[
        "Primera Ampliaci\u00f3n del Chote"
    ],
    "wof:name":"Primera Ampliacion del Chote",
    "wof:placetype":"locality",
    "wof:population":145
},
  "geometry": {"coordinates":[-98.48193999999999,21.8275],"type":"Point"}
}