{
  "type": "Feature",
  "properties": {
    "gn:admin1_code":"24",
    "gn:admin2_code":"13",
    "gn:asciiname":"La Camelia",
    "gn:country_code":"MX",
    "gn:dem":54,
    "gn:feature_class":"P",
    "gn:feature_code":"PPL",
    "gn:name":"La Camelia",
    "gn:population":10,
    "gn:timezone":"America/Mexico_City",
    "iso:country":"MX",
    "wof:name":"La Camelia",
    "wof:placetype":"locality",
    "wof:population":10
},
  "geometry": {"coordinates":[-99.01056,21.86528],"type":"Point"}
}