{
  "type": "Feature",
  "properties": {
    "gn:admin1_code":"6.0",
    "gn:admin2_code":"61.0",
    "gn:asciiname":"El Puerto del Fresno",
    "gn:country_code":"MX",
    "gn:dem":1683,
    "gn:feature_class":"P",
    "gn:feature_code":"PPL",
    "gn:name":"El Puerto del Fresno",
    "gn:population":0,
    "gn:timezone":"America/Chihuahua",
    "iso:country":"MX",
    "name:spa_x_preferred":[
        "El Puerto del Fresno"
    ],
    "wof:name":"El Puerto del Fresno",
    "wof:placetype":"locality"
},
  "geometry": {"coordinates":[-106.19795000000001,27.52896],"type":"Point"}
}