{
  "type": "Feature",
  "properties": {
    "gn:admin1_code":"19",
    "gn:admin2_code":"33.0",
    "gn:asciiname":"Mesita de Rios",
    "gn:country_code":"MX",
    "gn:dem":260,
    "gn:feature_class":"P",
    "gn:feature_code":"PPL",
    "gn:name":"Mesita de R\u00edos",
    "gn:population":7,
    "gn:timezone":"America/Monterrey",
    "iso:country":"MX",
    "name:und_x_variant":[
        "Mesita de R\u00edos"
    ],
    "wof:name":"Mesita de Rios",
    "wof:placetype":"locality",
    "wof:population":7
},
  "geometry": {"coordinates":[-99.18665,24.90314],"type":"Point"}
}