{
  "type": "Feature",
  "properties": {
    "gn:admin1_code":"6.0",
    "gn:admin2_code":"8.0",
    "gn:asciiname":"Los Corralitos",
    "gn:cc2":"MX",
    "gn:country_code":"MX",
    "gn:dem":683,
    "gn:feature_class":"P",
    "gn:feature_code":"PPL",
    "gn:name":"Los Corralitos",
    "gn:population":2,
    "gn:timezone":"America/Chihuahua",
    "iso:country":"MX",
    "name:und_x_variant":[
        "Corralito",
        "Corralitos"
    ],
    "wof:name":"Los Corralitos",
    "wof:placetype":"locality",
    "wof:population":2
},
  "geometry": {"coordinates":[-107.75324000000001,27.0191],"type":"Point"}
}