{
  "type": "Feature",
  "properties": {
    "gn:admin1_code":"12",
    "gn:admin2_code":"2.0",
    "gn:asciiname":"Tlaquilcingo",
    "gn:country_code":"MX",
    "gn:dem":1142,
    "gn:feature_class":"P",
    "gn:feature_code":"PPL",
    "gn:name":"Tlaquilcingo",
    "gn:population":0,
    "gn:timezone":"America/Mexico_City",
    "iso:country":"MX",
    "name:spa_x_preferred":[
        "Tlaquilcingo"
    ],
    "name:spa_x_variant":[
        "Tlaquiltzingo"
    ],
    "wof:name":"Tlaquilcingo",
    "wof:placetype":"locality"
},
  "geometry": {"coordinates":[-98.91895,17.86181000000001],"type":"Point"}
}