{
  "type": "Feature",
  "properties": {
    "gn:admin1_code":"5",
    "gn:admin2_code":"101.0",
    "gn:asciiname":"Sacramento de Jesus",
    "gn:country_code":"MX",
    "gn:dem":487,
    "gn:feature_class":"P",
    "gn:feature_code":"PPL",
    "gn:name":"Sacramento de Jes\u00fas",
    "gn:population":118,
    "gn:timezone":"America/Mexico_City",
    "iso:country":"MX",
    "name:und_x_variant":[
        "Sacramento de Jes\u00fas"
    ],
    "wof:name":"Sacramento de Jesus",
    "wof:placetype":"locality",
    "wof:population":118
},
  "geometry": {"coordinates":[-93.04111,16.72],"type":"Point"}
}