{
  "type": "Feature",
  "properties": {
    "gn:admin1_code":"13",
    "gn:admin2_code":"84.0",
    "gn:asciiname":"El Mezquite Segundo",
    "gn:cc2":"MX",
    "gn:country_code":"MX",
    "gn:dem":2024,
    "gn:feature_class":"P",
    "gn:feature_code":"PPL",
    "gn:name":"El Mezquite Segundo",
    "gn:population":121,
    "gn:timezone":"America/Mexico_City",
    "iso:country":"MX",
    "name:und_x_variant":[
        "Mezquite",
        "El Mezquite"
    ],
    "wof:name":"El Mezquite Segundo",
    "wof:placetype":"locality",
    "wof:population":121
},
  "geometry": {"coordinates":[-99.45802999999999,20.75488],"type":"Point"}
}