{
  "type": "Feature",
  "properties": {
    "gn:admin1_code":"20",
    "gn:admin2_code":"208.0",
    "gn:asciiname":"La Batea",
    "gn:country_code":"MX",
    "gn:dem":1941,
    "gn:feature_class":"P",
    "gn:feature_code":"PPL",
    "gn:name":"La Batea",
    "gn:population":115,
    "gn:timezone":"America/Mexico_City",
    "iso:country":"MX",
    "wof:name":"La Batea",
    "wof:placetype":"locality",
    "wof:population":115
},
  "geometry": {"coordinates":[-97.83333,17.3575],"type":"Point"}
}