{
  "type": "Feature",
  "properties": {
    "gn:admin1_code":"20",
    "gn:admin2_code":"20.0",
    "gn:asciiname":"Cerro Pluma (Dos Plumas)",
    "gn:country_code":"MX",
    "gn:dem":1317,
    "gn:feature_class":"P",
    "gn:feature_code":"PPL",
    "gn:name":"Cerro Pluma (Dos Plumas)",
    "gn:population":8,
    "gn:timezone":"America/Mexico_City",
    "iso:country":"MX",
    "wof:name":"Cerro Pluma (Dos Plumas)",
    "wof:placetype":"locality",
    "wof:population":8
},
  "geometry": {"coordinates":[-98.03055999999999,17.08278],"type":"Point"}
}