{
  "type": "Feature",
  "properties": {
    "gn:admin1_code":"32",
    "gn:admin2_code":"45.0",
    "gn:asciiname":"Goteras",
    "gn:country_code":"MX",
    "gn:dem":1788,
    "gn:feature_class":"P",
    "gn:feature_code":"PPL",
    "gn:name":"Goteras",
    "gn:population":5,
    "gn:timezone":"America/Mexico_City",
    "iso:country":"MX",
    "wof:name":"Goteras",
    "wof:placetype":"locality",
    "wof:population":5
},
  "geometry": {"coordinates":[-103.28194000000001,21.64917],"type":"Point"}
}