{
  "type": "Feature",
  "properties": {
    "gn:admin1_code":"30",
    "gn:admin2_code":"201.0",
    "gn:asciiname":"Cuautlaxco",
    "gn:cc2":"MX",
    "gn:country_code":"MX",
    "gn:dem":1292,
    "gn:feature_class":"P",
    "gn:feature_code":"PPL",
    "gn:name":"Cuautlaxco",
    "gn:population":0,
    "gn:timezone":"America/Mexico_City",
    "iso:country":"MX",
    "name:und_x_variant":[
        "Cuauhtlaixco",
        "Cuautlaxco"
    ],
    "wof:name":"Cuautlaxco",
    "wof:placetype":"locality"
},
  "geometry": {"coordinates":[-96.96666999999999,18.68333],"type":"Point"}
}