{
  "type": "Feature",
  "properties": {
    "gn:admin1_code":"28",
    "gn:admin2_code":"7.0",
    "gn:asciiname":"El Ramireno",
    "gn:country_code":"MX",
    "gn:dem":48,
    "gn:feature_class":"P",
    "gn:feature_code":"PPL",
    "gn:name":"El Ramire\u00f1o",
    "gn:population":0,
    "gn:timezone":"America/Monterrey",
    "iso:country":"MX",
    "wof:name":"El Ramireno",
    "wof:placetype":"locality"
},
  "geometry": {"coordinates":[-98.78128,26.28562],"type":"Point"}
}