{
  "type": "Feature",
  "properties": {
    "gn:admin1_code":"5",
    "gn:admin2_code":"19.0",
    "gn:asciiname":"Buenavista (Gracias a Dios)",
    "gn:country_code":"MX",
    "gn:dem":1849,
    "gn:feature_class":"P",
    "gn:feature_code":"PPL",
    "gn:name":"Buenavista (Gracias a Dios)",
    "gn:population":133,
    "gn:timezone":"America/Mexico_City",
    "iso:country":"MX",
    "wof:name":"Buenavista (Gracias a Dios)",
    "wof:placetype":"locality",
    "wof:population":133
},
  "geometry": {"coordinates":[-92.21944000000001,16.26194],"type":"Point"}
}