{
  "type": "Feature",
  "properties": {
    "gn:admin1_code":"25",
    "gn:admin2_code":"18.0",
    "gn:asciiname":"Avandaro",
    "gn:country_code":"MX",
    "gn:dem":3,
    "gn:feature_class":"P",
    "gn:feature_code":"PPL",
    "gn:name":"Av\u00e1ndaro",
    "gn:population":8,
    "gn:timezone":"America/Mazatlan",
    "iso:country":"MX",
    "name:und_x_variant":[
        "Av\u00e1ndaro"
    ],
    "wof:name":"Avandaro",
    "wof:placetype":"locality",
    "wof:population":8
},
  "geometry": {"coordinates":[-107.92,24.6275],"type":"Point"}
}