{
  "type": "Feature",
  "properties": {
    "gn:admin1_code":"6",
    "gn:admin2_code":"29.0",
    "gn:asciiname":"La Canita",
    "gn:country_code":"MX",
    "gn:dem":679,
    "gn:feature_class":"P",
    "gn:feature_code":"PPL",
    "gn:name":"La Ca\u00f1ita",
    "gn:population":0,
    "gn:timezone":"America/Chihuahua",
    "iso:country":"MX",
    "name:spa_x_preferred":[
        "La Ca\u00f1ita"
    ],
    "wof:name":"La Canita",
    "wof:placetype":"locality"
},
  "geometry": {"coordinates":[-107.59153999999999,26.17022],"type":"Point"}
}