{
  "type": "Feature",
  "properties": {
    "gn:admin1_code":"7.0",
    "gn:admin2_code":"24.0",
    "gn:asciiname":"Madero",
    "gn:country_code":"MX",
    "gn:dem":1138,
    "gn:feature_class":"P",
    "gn:feature_code":"PPL",
    "gn:name":"Madero",
    "gn:population":0,
    "gn:timezone":"America/Monterrey",
    "iso:country":"MX",
    "name:spa_x_preferred":[
        "Madero"
    ],
    "name:und_x_variant":[
        "Estaci\u00f3n Madero"
    ],
    "wof:name":"Madero",
    "wof:placetype":"locality"
},
  "geometry": {"coordinates":[-102.18864000000001,25.71991],"type":"Point"}
}