{
  "type": "Feature",
  "properties": {
    "gn:admin1_code":"12.0",
    "gn:admin2_code":"57.0",
    "gn:asciiname":"El Para",
    "gn:country_code":"MX",
    "gn:dem":789,
    "gn:feature_class":"P",
    "gn:feature_code":"PPL",
    "gn:name":"El Para",
    "gn:population":0,
    "gn:timezone":"America/Mexico_City",
    "iso:country":"MX",
    "name:spa_x_preferred":[
        "El Para"
    ],
    "wof:name":"El Para",
    "wof:placetype":"locality"
},
  "geometry": {"coordinates":[-100.5031,17.33761],"type":"Point"}
}