{
  "type": "Feature",
  "properties": {
    "gn:admin1_code":"5",
    "gn:admin2_code":"75.0",
    "gn:asciiname":"Lazaro Cardenas del Rio",
    "gn:country_code":"MX",
    "gn:dem":1993,
    "gn:feature_class":"P",
    "gn:feature_code":"PPL",
    "gn:name":"L\u00e1zaro C\u00e1rdenas del R\u00edo",
    "gn:population":82,
    "gn:timezone":"America/Mexico_City",
    "iso:country":"MX",
    "name:und_x_variant":[
        "L\u00e1zaro C\u00e1rdenas del R\u00edo"
    ],
    "wof:name":"Lazaro Cardenas del Rio",
    "wof:placetype":"locality",
    "wof:population":82
},
  "geometry": {"coordinates":[-92.31305999999999,16.3475],"type":"Point"}
}