{
  "type": "Feature",
  "properties": {
    "gn:admin1_code":"6",
    "gn:admin2_code":"1.0",
    "gn:asciiname":"El Tobosal",
    "gn:country_code":"MX",
    "gn:dem":1217,
    "gn:feature_class":"P",
    "gn:feature_code":"PPL",
    "gn:name":"El Tobosal",
    "gn:population":0,
    "gn:timezone":"America/Chihuahua",
    "iso:country":"MX",
    "name:und_x_variant":[
        "Rancho Tobosal",
        "El Tobosal"
    ],
    "wof:name":"El Tobosal",
    "wof:placetype":"locality"
},
  "geometry": {"coordinates":[-106.44970000000001,30.84681],"type":"Point"}
}