{
  "type": "Feature",
  "properties": {
    "gn:admin1_code":"6",
    "gn:admin2_code":"66.0",
    "gn:asciiname":"Orisivo",
    "gn:country_code":"MX",
    "gn:dem":1337,
    "gn:feature_class":"P",
    "gn:feature_code":"PPL",
    "gn:name":"Orisivo",
    "gn:population":97,
    "gn:timezone":"America/Chihuahua",
    "iso:country":"MX",
    "wof:name":"Orisivo",
    "wof:placetype":"locality",
    "wof:population":97
},
  "geometry": {"coordinates":[-108.11827,27.80797],"type":"Point"}
}