{
  "type": "Feature",
  "properties": {
    "gn:admin1_code":"25",
    "gn:admin2_code":"1",
    "gn:asciiname":"Campo las Palmas",
    "gn:country_code":"MX",
    "gn:dem":19,
    "gn:feature_class":"P",
    "gn:feature_code":"PPL",
    "gn:name":"Campo las Palmas",
    "gn:population":11,
    "gn:timezone":"America/Mazatlan",
    "iso:country":"MX",
    "wof:name":"Campo las Palmas",
    "wof:placetype":"locality",
    "wof:population":11
},
  "geometry": {"coordinates":[-108.89005,25.83524],"type":"Point"}
}