{
  "type": "Feature",
  "properties": {
    "gn:admin1_code":"17",
    "gn:admin2_code":"4.0",
    "gn:asciiname":"Campo el Guajar",
    "gn:country_code":"MX",
    "gn:dem":1319,
    "gn:feature_class":"P",
    "gn:feature_code":"PPL",
    "gn:name":"Campo el Guajar",
    "gn:population":5,
    "gn:timezone":"America/Mexico_City",
    "iso:country":"MX",
    "wof:name":"Campo el Guajar",
    "wof:placetype":"locality",
    "wof:population":5
},
  "geometry": {"coordinates":[-98.99508,18.77534],"type":"Point"}
}