{
  "type": "Feature",
  "properties": {
    "gn:admin1_code":"4",
    "gn:admin2_code":"6.0",
    "gn:asciiname":"Santa Rosa Xtampak",
    "gn:country_code":"MX",
    "gn:dem":85,
    "gn:feature_class":"P",
    "gn:feature_code":"PPL",
    "gn:name":"Santa Rosa Xtampak",
    "gn:population":0,
    "gn:timezone":"America/Merida",
    "iso:country":"MX",
    "name:spa_x_preferred":[
        "Santa Rosa Xtampak"
    ],
    "wof:name":"Santa Rosa Xtampak",
    "wof:placetype":"locality"
},
  "geometry": {"coordinates":[-89.58678,19.78106],"type":"Point"}
}