{
  "type": "Feature",
  "properties": {
    "gn:admin1_code":"16.0",
    "gn:admin2_code":"97.0",
    "gn:asciiname":"Los Cuirindales",
    "gn:country_code":"MX",
    "gn:dem":730,
    "gn:feature_class":"P",
    "gn:feature_code":"PPL",
    "gn:name":"Los Cuirindales",
    "gn:population":10,
    "gn:timezone":"America/Mexico_City",
    "iso:country":"MX",
    "wof:name":"Los Cuirindales",
    "wof:placetype":"locality",
    "wof:population":10
},
  "geometry": {"coordinates":[-101.38114,18.95542],"type":"Point"}
}