{
  "type": "Feature",
  "properties": {
    "gn:admin1_code":"20",
    "gn:admin2_code":"397.0",
    "gn:asciiname":"El Terrero (Venustiano Carranza)",
    "gn:country_code":"MX",
    "gn:dem":2254,
    "gn:feature_class":"P",
    "gn:feature_code":"PPL",
    "gn:name":"El Terrero (Venustiano Carranza)",
    "gn:population":68,
    "gn:timezone":"America/Mexico_City",
    "iso:country":"MX",
    "wof:name":"El Terrero (Venustiano Carranza)",
    "wof:placetype":"locality",
    "wof:population":68
},
  "geometry": {"coordinates":[-97.63278,17.2275],"type":"Point"}
}