{
  "type": "Feature",
  "properties": {
    "gn:admin1_code":"5",
    "gn:admin2_code":"94.0",
    "gn:asciiname":"Flores Magon",
    "gn:country_code":"MX",
    "gn:dem":2311,
    "gn:feature_class":"P",
    "gn:feature_code":"PPL",
    "gn:name":"Flores Mag\u00f3n",
    "gn:population":0,
    "gn:timezone":"America/Mexico_City",
    "iso:country":"MX",
    "name:spa_x_preferred":[
        "Flores Mag\u00f3n"
    ],
    "wof:name":"Flores Magon",
    "wof:placetype":"locality"
},
  "geometry": {"coordinates":[-92.5241,16.63561],"type":"Point"}
}