{
  "type": "Feature",
  "properties": {
    "gn:admin1_code":"11.0",
    "gn:asciiname":"El Jaral",
    "gn:country_code":"MX",
    "gn:dem":1787,
    "gn:feature_class":"P",
    "gn:feature_code":"PPL",
    "gn:name":"El Jaral",
    "gn:population":0,
    "gn:timezone":"America/Mexico_City",
    "iso:country":"MX",
    "name:und_x_variant":[
        "Jaral",
        "El Jaral"
    ],
    "wof:name":"El Jaral",
    "wof:placetype":"locality"
},
  "geometry": {"coordinates":[-102.39453,21.32153],"type":"Point"}
}