{
  "type": "Feature",
  "properties": {
    "gn:admin1_code":"6",
    "gn:admin2_code":"26.0",
    "gn:asciiname":"Buenavista",
    "gn:country_code":"MX",
    "gn:dem":1753,
    "gn:feature_class":"P",
    "gn:feature_code":"PPL",
    "gn:name":"Buenavista",
    "gn:population":0,
    "gn:timezone":"America/Chihuahua",
    "iso:country":"MX",
    "name:spa_x_preferred":[
        "Buenavista"
    ],
    "name:spa_x_variant":[
        "La Majada"
    ],
    "wof:name":"Buenavista",
    "wof:placetype":"locality"
},
  "geometry": {"coordinates":[-106.59684,28.29517],"type":"Point"}
}