{
  "type": "Feature",
  "properties": {
    "gn:admin1_code":"19",
    "gn:admin2_code":"31",
    "gn:asciiname":"Los Naranjos",
    "gn:country_code":"MX",
    "gn:dem":468,
    "gn:feature_class":"P",
    "gn:feature_code":"PPL",
    "gn:name":"Los Naranjos",
    "gn:population":34,
    "gn:timezone":"America/Monterrey",
    "iso:country":"MX",
    "wof:name":"Los Naranjos",
    "wof:placetype":"locality",
    "wof:population":34
},
  "geometry": {"coordinates":[-100.16419,25.62978],"type":"Point"}
}