{
  "type": "Feature",
  "properties": {
    "gn:admin1_code":"16.0",
    "gn:admin2_code":"6.0",
    "gn:asciiname":"El Salate",
    "gn:country_code":"MX",
    "gn:dem":245,
    "gn:feature_class":"P",
    "gn:feature_code":"PPL",
    "gn:name":"El Salate",
    "gn:population":49,
    "gn:timezone":"America/Mexico_City",
    "iso:country":"MX",
    "name:spa_x_preferred":[
        "El Salate"
    ],
    "name:und_x_variant":[
        "El Sarate"
    ],
    "wof:name":"El Salate",
    "wof:placetype":"locality",
    "wof:population":49
},
  "geometry": {"coordinates":[-102.35216,18.86068],"type":"Point"}
}