{
  "type": "Feature",
  "properties": {
    "gn:admin1_code":"30",
    "gn:admin2_code":"25",
    "gn:asciiname":"El Potrero",
    "gn:country_code":"MX",
    "gn:dem":2638,
    "gn:feature_class":"P",
    "gn:feature_code":"PPL",
    "gn:name":"El Potrero",
    "gn:population":34,
    "gn:timezone":"America/Mexico_City",
    "iso:country":"MX",
    "wof:name":"El Potrero",
    "wof:placetype":"locality",
    "wof:population":34
},
  "geometry": {"coordinates":[-97.15472,19.39833],"type":"Point"}
}