{
  "type": "Feature",
  "properties": {
    "gn:admin1_code":"14",
    "gn:admin2_code":"27",
    "gn:asciiname":"Crucecitas",
    "gn:country_code":"MX",
    "gn:dem":833,
    "gn:feature_class":"P",
    "gn:feature_code":"PPL",
    "gn:name":"Crucecitas",
    "gn:population":29,
    "gn:timezone":"America/Mexico_City",
    "iso:country":"MX",
    "wof:name":"Crucecitas",
    "wof:placetype":"locality",
    "wof:population":29
},
  "geometry": {"coordinates":[-104.19722,19.4175],"type":"Point"}
}