{
  "type": "Feature",
  "properties": {
    "gn:admin1_code":"6.0",
    "gn:admin2_code":"52.0",
    "gn:asciiname":"Charco de Piedra",
    "gn:country_code":"MX",
    "gn:dem":1460,
    "gn:feature_class":"P",
    "gn:feature_code":"PPL",
    "gn:name":"Charco de Piedra",
    "gn:population":0,
    "gn:timezone":"America/Chihuahua",
    "iso:country":"MX",
    "name:spa_x_preferred":[
        "Charco de Piedra"
    ],
    "name:und_x_variant":[
        "Rancho Charco de Piedra"
    ],
    "wof:name":"Charco de Piedra",
    "wof:placetype":"locality"
},
  "geometry": {"coordinates":[-104.26185,28.73045],"type":"Point"}
}