{
  "type": "Feature",
  "properties": {
    "gn:admin1_code":"20",
    "gn:admin2_code":"64.0",
    "gn:asciiname":"Chihuiro",
    "gn:country_code":"MX",
    "gn:dem":767,
    "gn:feature_class":"P",
    "gn:feature_code":"PPL",
    "gn:name":"Chihuiro",
    "gn:population":0,
    "gn:timezone":"America/Mexico_City",
    "iso:country":"MX",
    "name:spa_x_preferred":[
        "Chiguro"
    ],
    "name:spa_x_variant":[
        "Chihuiro"
    ],
    "wof:name":"Chihuiro",
    "wof:placetype":"locality"
},
  "geometry": {"coordinates":[-96.03937999999999,16.51536],"type":"Point"}
}