{
  "type": "Feature",
  "properties": {
    "gn:admin1_code":"4",
    "gn:admin2_code":"10.0",
    "gn:asciiname":"Dos Naciones",
    "gn:country_code":"MX",
    "gn:dem":157,
    "gn:feature_class":"P",
    "gn:feature_code":"PPL",
    "gn:name":"Dos Naciones",
    "gn:population":0,
    "gn:timezone":"America/Cancun",
    "iso:country":"MX",
    "name:spa_x_preferred":[
        "Dos Naciones"
    ],
    "wof:name":"Dos Naciones",
    "wof:placetype":"locality"
},
  "geometry": {"coordinates":[-89.35502,17.9716],"type":"Point"}
}