{
  "type": "Feature",
  "properties": {
    "gn:admin1_code":"16",
    "gn:admin2_code":"4.0",
    "gn:asciiname":"San Pedro",
    "gn:country_code":"MX",
    "gn:dem":1729,
    "gn:feature_class":"P",
    "gn:feature_code":"PPL",
    "gn:name":"San Pedro",
    "gn:population":54,
    "gn:timezone":"America/Mexico_City",
    "iso:country":"MX",
    "name:arg_x_preferred":[
        "San Pedro"
    ],
    "name:ast_x_preferred":[
        "San Pedro"
    ],
    "name:bre_x_preferred":[
        "San Pedro"
    ],
    "name:cat_x_preferred":[
        "San Pedro"
    ],
    "name:ceb_x_preferred":[
        "San Pedro"
    ],
    "name:ces_x_preferred":[
        "San Pedro"
    ],
    "name:deu_x_preferred":[
        "San Pedro"
    ],
    "name:epo_x_preferred":[
        "San Pedro"
    ],
    "name:est_x_preferred":[
        "San Pedro"
    ],
    "name:fas_x_preferred":[
        "\u0633\u0646 \u067e\u062f\u0631\u0648"
    ],
    "name:fra_x_preferred":[
        "San Pedro"
    ],
    "name:glg_x_preferred":[
        "San Pedro"
    ],
    "name:heb_x_preferred":[
        "\u05e1\u05df \u05e4\u05d3\u05e8\u05d5"
    ],
    "name:hrv_x_preferred":[
        "San Pedro"
    ],
    "name:hye_x_preferred":[
        "\u054d\u0561\u0576 \u054a\u0565\u0564\u0580\u0578"
    ],
    "name:ilo_x_preferred":[
        "San Pedro"
    ],
    "name:ita_x_preferred":[
        "San Pedro"
    ],
    "name:jpn_x_preferred":[
        "\u30b5\u30f3\u30da\u30c9\u30ed"
    ],
    "name:kor_x_preferred":[
        "\uc0b0\ud398\ub4dc\ub85c"
    ],
    "name:lit_x_preferred":[
        "San Pedras"
    ],
    "name:nds_x_preferred":[
        "San Pedro"
    ],
    "name:nld_x_preferred":[
        "San Pedro"
    ],
    "name:nor_x_preferred":[
        "San Pedro"
    ],
    "name:pol_x_preferred":[
        "San Pedro"
    ],
    "name:por_x_preferred":[
        "San Pedro"
    ],
    "name:rus_x_preferred":[
        "\u0421\u0430\u043d-\u041f\u0435\u0434\u0440\u043e"
    ],
    "name:sco_x_preferred":[
        "San Pedro"
    ],
    "name:slk_x_preferred":[
        "San Pedro"
    ],
    "name:spa_x_preferred":[
        "San Pedro"
    ],
    "name:srp_x_preferred":[
        "\u0421\u0430\u043d \u041f\u0435\u0434\u0440\u043e"
    ],
    "name:swe_x_preferred":[
        "San Pedro"
    ],
    "name:ukr_x_preferred":[
        "\u0421\u0430\u043d-\u041f\u0435\u0434\u0440\u043e"
    ],
    "name:war_x_preferred":[
        "San Pedro"
    ],
    "wof:name":"San Pedro",
    "wof:placetype":"locality",
    "wof:population":54
},
  "geometry": {"coordinates":[-101.72611000000001,20.19972000000001],"type":"Point"}
}