{
  "type": "Feature",
  "properties": {
    "gn:admin1_code":"11.0",
    "gn:admin2_code":"30.0",
    "gn:asciiname":"Deseadilla",
    "gn:country_code":"MX",
    "gn:dem":2148,
    "gn:feature_class":"P",
    "gn:feature_code":"PPL",
    "gn:name":"Deseadilla",
    "gn:population":0,
    "gn:timezone":"America/Mexico_City",
    "iso:country":"MX",
    "name:spa_x_preferred":[
        "Deseadilla"
    ],
    "name:spa_x_variant":[
        "La Deseadilla"
    ],
    "wof:name":"Deseadilla",
    "wof:placetype":"locality"
},
  "geometry": {"coordinates":[-101.34092,21.24332],"type":"Point"}
}