{
  "type": "Feature",
  "properties": {
    "gn:admin1_code":"3",
    "gn:admin2_code":"1.0",
    "gn:asciiname":"Ines",
    "gn:country_code":"MX",
    "gn:dem":35,
    "gn:feature_class":"P",
    "gn:feature_code":"PPL",
    "gn:name":"In\u00e9s",
    "gn:population":0,
    "gn:timezone":"America/Mazatlan",
    "iso:country":"MX",
    "name:ceb_x_preferred":[
        "Ines"
    ],
    "name:deu_x_preferred":[
        "Ines"
    ],
    "name:fra_x_preferred":[
        "Ines"
    ],
    "name:spa_x_preferred":[
        "In\u00e9s"
    ],
    "wof:name":"Ines",
    "wof:placetype":"locality"
},
  "geometry": {"coordinates":[-111.76491,25.41485],"type":"Point"}
}