{
  "type": "Feature",
  "properties": {
    "gn:admin1_code":"21",
    "gn:admin2_code":"19.0",
    "gn:asciiname":"La Trinidad Tepango",
    "gn:country_code":"MX",
    "gn:dem":1782,
    "gn:feature_class":"P",
    "gn:feature_code":"PPL",
    "gn:name":"La Trinidad Tepango",
    "gn:population":0,
    "gn:timezone":"America/Mexico_City",
    "iso:country":"MX",
    "name:und_x_variant":[
        "Trinidad",
        "La Trinidad Tepango",
        "La Trinidad Tepanco"
    ],
    "wof:name":"La Trinidad Tepango",
    "wof:placetype":"locality"
},
  "geometry": {"coordinates":[-98.44589999999999,18.86304],"type":"Point"}
}