{
  "type": "Feature",
  "properties": {
    "gn:admin1_code":"5",
    "gn:admin2_code":"33.0",
    "gn:asciiname":"San Antonio Maspac",
    "gn:country_code":"MX",
    "gn:dem":444,
    "gn:feature_class":"P",
    "gn:feature_code":"PPL",
    "gn:name":"San Antonio Maspac",
    "gn:population":190,
    "gn:timezone":"America/Mexico_City",
    "iso:country":"MX",
    "wof:name":"San Antonio Maspac",
    "wof:placetype":"locality",
    "wof:population":190
},
  "geometry": {"coordinates":[-93.32886999999999,17.31417],"type":"Point"}
}