{
  "type": "Feature",
  "properties": {
    "gn:admin1_code":"11",
    "gn:admin2_code":"40",
    "gn:asciiname":"Puerto del Mezquite",
    "gn:country_code":"MX",
    "gn:dem":1879,
    "gn:feature_class":"P",
    "gn:feature_code":"PPL",
    "gn:name":"Puerto del Mezquite",
    "gn:population":32,
    "gn:timezone":"America/Mexico_City",
    "iso:country":"MX",
    "wof:name":"Puerto del Mezquite",
    "wof:placetype":"locality",
    "wof:population":32
},
  "geometry": {"coordinates":[-100.13861,21.05417000000001],"type":"Point"}
}