{
  "type": "Feature",
  "properties": {
    "gn:admin1_code":"25.0",
    "gn:admin2_code":"3.0",
    "gn:asciiname":"Los Aguajitos",
    "gn:country_code":"MX",
    "gn:dem":651,
    "gn:feature_class":"P",
    "gn:feature_code":"PPL",
    "gn:name":"Los Aguajitos",
    "gn:population":0,
    "gn:timezone":"America/Mazatlan",
    "iso:country":"MX",
    "name:spa_x_preferred":[
        "Los Aguajitos"
    ],
    "wof:name":"Los Aguajitos",
    "wof:placetype":"locality"
},
  "geometry": {"coordinates":[-107.491,25.57799],"type":"Point"}
}