{
  "type": "Feature",
  "properties": {
    "gn:admin1_code":"20",
    "gn:admin2_code":"176",
    "gn:asciiname":"La Mulata",
    "gn:country_code":"MX",
    "gn:dem":2266,
    "gn:feature_class":"P",
    "gn:feature_code":"PPL",
    "gn:name":"La Mulata",
    "gn:population":41,
    "gn:timezone":"America/Mexico_City",
    "iso:country":"MX",
    "wof:name":"La Mulata",
    "wof:placetype":"locality",
    "wof:population":41
},
  "geometry": {"coordinates":[-97.175,17.69944],"type":"Point"}
}