{
  "type": "Feature",
  "properties": {
    "gn:admin1_code":"10",
    "gn:admin2_code":"14.0",
    "gn:asciiname":"Las Manzanas",
    "gn:country_code":"MX",
    "gn:dem":2283,
    "gn:feature_class":"P",
    "gn:feature_code":"PPL",
    "gn:name":"Las Manzanas",
    "gn:population":5,
    "gn:timezone":"America/Monterrey",
    "iso:country":"MX",
    "wof:name":"Las Manzanas",
    "wof:placetype":"locality",
    "wof:population":5
},
  "geometry": {"coordinates":[-104.76667,22.93972],"type":"Point"}
}