{
  "type": "Feature",
  "properties": {
    "gn:admin1_code":"30.0",
    "gn:admin2_code":"63.0",
    "gn:asciiname":"Poeta",
    "gn:country_code":"MX",
    "gn:dem":76,
    "gn:feature_class":"P",
    "gn:feature_code":"PPL",
    "gn:name":"Poeta",
    "gn:population":0,
    "gn:timezone":"America/Mexico_City",
    "iso:country":"MX",
    "name:fra_x_preferred":[
        "Poeta"
    ],
    "name:ita_x_preferred":[
        "Poeta"
    ],
    "name:spa_x_preferred":[
        "Poeta"
    ],
    "wof:name":"Poeta",
    "wof:placetype":"locality"
},
  "geometry": {"coordinates":[-97.99762,21.54581],"type":"Point"}
}