{
  "type": "Feature",
  "properties": {
    "gn:admin1_code":"20",
    "gn:admin2_code":"310",
    "gn:asciiname":"La Verdura",
    "gn:country_code":"MX",
    "gn:dem":1621,
    "gn:feature_class":"P",
    "gn:feature_code":"PPL",
    "gn:name":"La Verdura",
    "gn:population":47,
    "gn:timezone":"America/Mexico_City",
    "iso:country":"MX",
    "wof:name":"La Verdura",
    "wof:placetype":"locality",
    "wof:population":47
},
  "geometry": {"coordinates":[-96.79917,17.05861],"type":"Point"}
}