{
  "type": "Feature",
  "properties": {
    "gn:admin1_code":"17",
    "gn:admin2_code":"9",
    "gn:asciiname":"Kilometro 54.8 (Columpios de Axoxoco)",
    "gn:country_code":"MX",
    "gn:dem":2680,
    "gn:feature_class":"P",
    "gn:feature_code":"PPL",
    "gn:name":"Kil\u00f3metro 54.8 (Columpios de Axoxoco)",
    "gn:population":19,
    "gn:timezone":"America/Mexico_City",
    "iso:country":"MX",
    "name:und_x_variant":[
        "Kil\u00f3metro 54.8 (Columpios de Axoxoco)"
    ],
    "wof:name":"Kilometro 54.8 (Columpios de Axoxoco)",
    "wof:placetype":"locality",
    "wof:population":19
},
  "geometry": {"coordinates":[-99.22776,19.03258],"type":"Point"}
}