{
  "type": "Feature",
  "properties": {
    "gn:admin1_code":"28",
    "gn:admin2_code":"22.0",
    "gn:asciiname":"Los Olmos",
    "gn:country_code":"MX",
    "gn:dem":22,
    "gn:feature_class":"P",
    "gn:feature_code":"PPL",
    "gn:name":"Los Olmos",
    "gn:population":0,
    "gn:timezone":"America/Matamoros",
    "iso:country":"MX",
    "wof:name":"Los Olmos",
    "wof:placetype":"locality"
},
  "geometry": {"coordinates":[-97.85889,25.98306],"type":"Point"}
}