{
  "type": "Feature",
  "properties": {
    "gn:admin1_code":"28",
    "gn:admin2_code":"22.0",
    "gn:asciiname":"Los Olmos",
    "gn:country_code":"MX",
    "gn:dem":22,
    "gn:feature_class":"P",
    "gn:feature_code":"PPL",
    "gn:name":"Los Olmos",
    "gn:population":0,
    "gn:timezone":"America/Matamoros",
    "iso:country":"MX",
    "name:arg_x_preferred":[
        "Los Olmos"
    ],
    "name:ast_x_preferred":[
        "Los Olmos"
    ],
    "name:azb_x_preferred":[
        "\u0644\u0633 \u0627\u0644\u0645\u0633"
    ],
    "name:cat_x_preferred":[
        "Los Olmos"
    ],
    "name:eus_x_preferred":[
        "Los Olmos"
    ],
    "name:fas_x_preferred":[
        "\u0644\u0633 \u0627\u0644\u0645\u0633"
    ],
    "name:fra_x_preferred":[
        "Los Olmos"
    ],
    "name:hun_x_preferred":[
        "Los Olmos"
    ],
    "name:ita_x_preferred":[
        "Los Olmos"
    ],
    "name:kaz_x_preferred":[
        "\u041b\u043e\u0441-\u041e\u043b\u044c\u043c\u043e\u0441"
    ],
    "name:msa_x_preferred":[
        "Los Olmos"
    ],
    "name:nld_x_preferred":[
        "Los Olmos"
    ],
    "name:oci_x_preferred":[
        "Los Olmos"
    ],
    "name:pol_x_preferred":[
        "Los Olmos"
    ],
    "name:por_x_preferred":[
        "Los Olmos"
    ],
    "name:rus_x_preferred":[
        "\u041b\u043e\u0441-\u041e\u043b\u044c\u043c\u043e\u0441"
    ],
    "name:spa_x_preferred":[
        "Los Olmos"
    ],
    "name:ukr_x_preferred":[
        "\u041b\u043e\u0441-\u041e\u043b\u044c\u043c\u043e\u0441"
    ],
    "name:uzb_x_preferred":[
        "Los Olmos"
    ],
    "name:vie_x_preferred":[
        "Los Olmos"
    ],
    "name:war_x_preferred":[
        "Los Olmos"
    ],
    "name:zho_x_preferred":[
        "\u6d1b\u7d22\u5c14\u83ab\u65af"
    ],
    "wof:name":"Los Olmos",
    "wof:placetype":"locality"
},
  "geometry": {"coordinates":[-97.85889,25.98306],"type":"Point"}
}