{
  "type": "Feature",
  "properties": {
    "gn:admin1_code":"10",
    "gn:admin2_code":"14",
    "gn:asciiname":"Cerros Juntos",
    "gn:country_code":"MX",
    "gn:dem":2198,
    "gn:feature_class":"P",
    "gn:feature_code":"PPL",
    "gn:name":"Cerros Juntos",
    "gn:population":37,
    "gn:timezone":"America/Monterrey",
    "iso:country":"MX",
    "wof:name":"Cerros Juntos",
    "wof:placetype":"locality",
    "wof:population":37
},
  "geometry": {"coordinates":[-104.64024000000001,22.86975],"type":"Point"}
}