{
  "type": "Feature",
  "properties": {
    "gn:admin1_code":"16.0",
    "gn:admin2_code":"94.0",
    "gn:asciiname":"Acuitzeramo",
    "gn:country_code":"MX",
    "gn:dem":1951,
    "gn:feature_class":"P",
    "gn:feature_code":"PPL",
    "gn:name":"Acuitzeramo",
    "gn:population":0,
    "gn:timezone":"America/Mexico_City",
    "iso:country":"MX",
    "name:spa_x_preferred":[
        "Acuitzeramo"
    ],
    "name:und_x_variant":[
        "Acuitzermo"
    ],
    "wof:name":"Acuitzeramo",
    "wof:placetype":"locality"
},
  "geometry": {"coordinates":[-101.97029000000001,19.99457],"type":"Point"}
}