{
  "type": "Feature",
  "properties": {
    "gn:admin1_code":"6",
    "gn:admin2_code":"1.0",
    "gn:asciiname":"La Equis",
    "gn:country_code":"MX",
    "gn:dem":1239,
    "gn:feature_class":"P",
    "gn:feature_code":"PPL",
    "gn:name":"La Equis",
    "gn:population":0,
    "gn:timezone":"America/Chihuahua",
    "iso:country":"MX",
    "wof:name":"La Equis",
    "wof:placetype":"locality"
},
  "geometry": {"coordinates":[-106.46872999999999,30.48548],"type":"Point"}
}