{
  "type": "Feature",
  "properties": {
    "gn:admin1_code":"31",
    "gn:admin2_code":"99.0",
    "gn:asciiname":"Xnohkancab",
    "gn:country_code":"MX",
    "gn:dem":32,
    "gn:feature_class":"P",
    "gn:feature_code":"PPL",
    "gn:name":"Xnohkancab",
    "gn:population":0,
    "gn:timezone":"America/Merida",
    "iso:country":"MX",
    "name:spa_x_preferred":[
        "Xnohkancab"
    ],
    "wof:name":"Xnohkancab",
    "wof:placetype":"locality"
},
  "geometry": {"coordinates":[-88.36123000000001,20.75283],"type":"Point"}
}