{
  "type": "Feature",
  "properties": {
    "gn:admin1_code":"6.0",
    "gn:admin2_code":"36.0",
    "gn:asciiname":"Miguel Hidalgo II",
    "gn:country_code":"MX",
    "gn:dem":1142,
    "gn:feature_class":"P",
    "gn:feature_code":"PPL",
    "gn:name":"Miguel Hidalgo II",
    "gn:population":0,
    "gn:timezone":"America/Chihuahua",
    "iso:country":"MX",
    "name:spa_x_preferred":[
        "Miguel Hidalgo II"
    ],
    "wof:name":"Miguel Hidalgo II",
    "wof:placetype":"locality"
},
  "geometry": {"coordinates":[-104.005,26.78694],"type":"Point"}
}