{
  "type": "Feature",
  "properties": {
    "gn:admin1_code":"28.0",
    "gn:admin2_code":"12.0",
    "gn:asciiname":"Gallinas",
    "gn:country_code":"MX",
    "gn:dem":131,
    "gn:feature_class":"P",
    "gn:feature_code":"PPL",
    "gn:name":"Gallinas",
    "gn:population":1,
    "gn:timezone":"America/Monterrey",
    "iso:country":"MX",
    "name:ceb_x_preferred":[
        "Gallinas"
    ],
    "name:spa_x_preferred":[
        "Gallinas"
    ],
    "name:swe_x_preferred":[
        "Gallinas"
    ],
    "wof:name":"Gallinas",
    "wof:placetype":"locality",
    "wof:population":1
},
  "geometry": {"coordinates":[-98.4575,22.885],"type":"Point"}
}