{
  "type": "Feature",
  "properties": {
    "gn:admin1_code":"26",
    "gn:admin2_code":"33.0",
    "gn:asciiname":"La Sabila",
    "gn:country_code":"MX",
    "gn:dem":5,
    "gn:feature_class":"P",
    "gn:feature_code":"PPL",
    "gn:name":"La S\u00e1bila",
    "gn:population":909,
    "gn:timezone":"America/Hermosillo",
    "iso:country":"MX",
    "wof:name":"La Sabila",
    "wof:placetype":"locality",
    "wof:population":909
},
  "geometry": {"coordinates":[-109.62472,26.76528],"type":"Point"}
}