{
  "type": "Feature",
  "properties": {
    "gn:admin1_code":"11",
    "gn:admin2_code":"23.0",
    "gn:asciiname":"Loma de Aceves Uno",
    "gn:country_code":"MX",
    "gn:dem":1694,
    "gn:feature_class":"P",
    "gn:feature_code":"PPL",
    "gn:name":"Loma de Aceves Uno",
    "gn:population":82,
    "gn:timezone":"America/Mexico_City",
    "iso:country":"MX",
    "wof:name":"Loma de Aceves Uno",
    "wof:placetype":"locality",
    "wof:population":82
},
  "geometry": {"coordinates":[-101.95806,20.4525],"type":"Point"}
}