{
  "type": "Feature",
  "properties": {
    "gn:admin1_code":"10",
    "gn:admin2_code":"23.0",
    "gn:asciiname":"Las Cebolletas",
    "gn:country_code":"MX",
    "gn:dem":2040,
    "gn:feature_class":"P",
    "gn:feature_code":"PPL",
    "gn:name":"Las Cebolletas",
    "gn:population":0,
    "gn:timezone":"America/Monterrey",
    "iso:country":"MX",
    "name:spa_x_preferred":[
        "Las Cebolletas"
    ],
    "wof:name":"Las Cebolletas",
    "wof:placetype":"locality"
},
  "geometry": {"coordinates":[-105.04689,23.25871],"type":"Point"}
}