{
  "type": "Feature",
  "properties": {
    "gn:admin1_code":"23",
    "gn:admin2_code":"6.0",
    "gn:asciiname":"La Pimientita",
    "gn:country_code":"MX",
    "gn:dem":60,
    "gn:feature_class":"P",
    "gn:feature_code":"PPL",
    "gn:name":"La Pimientita",
    "gn:population":260,
    "gn:timezone":"America/Cancun",
    "iso:country":"MX",
    "wof:name":"La Pimientita",
    "wof:placetype":"locality",
    "wof:population":260
},
  "geometry": {"coordinates":[-88.66972,19.50417],"type":"Point"}
}