{
  "type": "Feature",
  "properties": {
    "gn:admin1_code":"5",
    "gn:admin2_code":"12.0",
    "gn:asciiname":"Ciudad Maya",
    "gn:country_code":"MX",
    "gn:dem":1001,
    "gn:feature_class":"P",
    "gn:feature_code":"PPL",
    "gn:name":"Ciudad Maya",
    "gn:population":715,
    "gn:timezone":"America/Mexico_City",
    "iso:country":"MX",
    "wof:name":"Ciudad Maya",
    "wof:placetype":"locality",
    "wof:population":715
},
  "geometry": {"coordinates":[-93.31583000000001,16.73944],"type":"Point"}
}