{
  "type": "Feature",
  "properties": {
    "gn:admin1_code":"5",
    "gn:admin2_code":"81.0",
    "gn:asciiname":"San Jose las Granadas",
    "gn:country_code":"MX",
    "gn:dem":556,
    "gn:feature_class":"P",
    "gn:feature_code":"PPL",
    "gn:name":"San Jos\u00e9 las Granadas",
    "gn:population":54,
    "gn:timezone":"America/Mexico_City",
    "iso:country":"MX",
    "name:und_x_variant":[
        "San Jos\u00e9 las Granadas"
    ],
    "wof:name":"San Jose las Granadas",
    "wof:placetype":"locality",
    "wof:population":54
},
  "geometry": {"coordinates":[-92.74833,17.18028],"type":"Point"}
}