{
  "type": "Feature",
  "properties": {
    "gn:admin1_code":"11",
    "gn:admin2_code":"22",
    "gn:asciiname":"Desmonte de Gonzalez",
    "gn:country_code":"MX",
    "gn:dem":2221,
    "gn:feature_class":"P",
    "gn:feature_code":"PPL",
    "gn:name":"Desmonte de Gonz\u00e1lez",
    "gn:population":11,
    "gn:timezone":"America/Mexico_City",
    "iso:country":"MX",
    "name:und_x_variant":[
        "Desmonte de Gonz\u00e1lez"
    ],
    "wof:name":"Desmonte de Gonzalez",
    "wof:placetype":"locality",
    "wof:population":11
},
  "geometry": {"coordinates":[-101.45833,21.64444],"type":"Point"}
}