{
  "type": "Feature",
  "properties": {
    "gn:admin1_code":"20.0",
    "gn:asciiname":"Arroyo Caracol Ideal",
    "gn:country_code":"MX",
    "gn:dem":106,
    "gn:feature_class":"P",
    "gn:feature_code":"PPL",
    "gn:name":"Arroyo Caracol Ideal",
    "gn:population":0,
    "gn:timezone":"America/Mexico_City",
    "iso:country":"MX",
    "name:spa_x_preferred":[
        "Arroyo Caracol Ideal"
    ],
    "wof:name":"Arroyo Caracol Ideal",
    "wof:placetype":"locality"
},
  "geometry": {"coordinates":[-96.37418,18.10153],"type":"Point"}
}