{
  "type": "Feature",
  "properties": {
    "gn:admin1_code":"3.0",
    "gn:admin2_code":"3.0",
    "gn:asciiname":"El Potrero",
    "gn:country_code":"MX",
    "gn:dem":1189,
    "gn:feature_class":"P",
    "gn:feature_code":"PPL",
    "gn:name":"El Potrero",
    "gn:population":0,
    "gn:timezone":"America/Mazatlan",
    "iso:country":"MX",
    "wof:name":"El Potrero",
    "wof:placetype":"locality"
},
  "geometry": {"coordinates":[-110.0125,23.52833],"type":"Point"}
}