{
  "type": "Feature",
  "properties": {
    "gn:admin1_code":"4",
    "gn:admin2_code":"3.0",
    "gn:asciiname":"Abelardo Rodriguez",
    "gn:country_code":"MX",
    "gn:dem":62,
    "gn:feature_class":"P",
    "gn:feature_code":"PPL",
    "gn:name":"Abelardo Rodr\u00edguez",
    "gn:population":0,
    "gn:timezone":"America/Merida",
    "iso:country":"MX",
    "wof:name":"Abelardo Rodriguez",
    "wof:placetype":"locality"
},
  "geometry": {"coordinates":[-90.84999999999999,18.81111],"type":"Point"}
}