{
  "type": "Feature",
  "properties": {
    "gn:admin1_code":"5",
    "gn:admin2_code":"113.0",
    "gn:asciiname":"Sepelton",
    "gn:country_code":"MX",
    "gn:dem":1537,
    "gn:feature_class":"P",
    "gn:feature_code":"PPL",
    "gn:name":"Sepelt\u00f3n",
    "gn:population":227,
    "gn:timezone":"America/Mexico_City",
    "iso:country":"MX",
    "name:und_x_variant":[
        "Sepelt\u00f3n"
    ],
    "wof:name":"Sepelton",
    "wof:placetype":"locality",
    "wof:population":227
},
  "geometry": {"coordinates":[-92.70361,16.93056],"type":"Point"}
}