{
  "type": "Feature",
  "properties": {
    "gn:admin1_code":"5",
    "gn:admin2_code":"12.0",
    "gn:asciiname":"Los Manueles Uno",
    "gn:country_code":"MX",
    "gn:dem":1004,
    "gn:feature_class":"P",
    "gn:feature_code":"PPL",
    "gn:name":"Los Manueles Uno",
    "gn:population":5,
    "gn:timezone":"America/Mexico_City",
    "iso:country":"MX",
    "wof:name":"Los Manueles Uno",
    "wof:placetype":"locality",
    "wof:population":5
},
  "geometry": {"coordinates":[-93.31361,16.75111],"type":"Point"}
}