{
  "type": "Feature",
  "properties": {
    "gn:admin1_code":"14",
    "gn:admin2_code":"120",
    "gn:asciiname":"La Providencia",
    "gn:country_code":"MX",
    "gn:dem":1541,
    "gn:feature_class":"P",
    "gn:feature_code":"PPL",
    "gn:name":"La Providencia",
    "gn:population":13,
    "gn:timezone":"America/Mexico_City",
    "iso:country":"MX",
    "wof:name":"La Providencia",
    "wof:placetype":"locality",
    "wof:population":13
},
  "geometry": {"coordinates":[-103.60111000000001,20.76722],"type":"Point"}
}