{
  "type": "Feature",
  "properties": {
    "gn:admin1_code":"12.0",
    "gn:admin2_code":"19.0",
    "gn:asciiname":"Tecajco",
    "gn:country_code":"MX",
    "gn:dem":619,
    "gn:feature_class":"P",
    "gn:feature_code":"PPL",
    "gn:name":"Tecajco",
    "gn:population":0,
    "gn:timezone":"America/Mexico_City",
    "iso:country":"MX",
    "name:spa_x_preferred":[
        "Tecajco"
    ],
    "wof:name":"Tecajco",
    "wof:placetype":"locality"
},
  "geometry": {"coordinates":[-99.10937,18.06433],"type":"Point"}
}