{
  "type": "Feature",
  "properties": {
    "gn:admin1_code":"30.0",
    "gn:admin2_code":"160.0",
    "gn:asciiname":"El Chijolar",
    "gn:country_code":"MX",
    "gn:dem":96,
    "gn:feature_class":"P",
    "gn:feature_code":"PPL",
    "gn:name":"El Chijolar",
    "gn:population":1,
    "gn:timezone":"America/Mexico_City",
    "iso:country":"MX",
    "name:spa_x_preferred":[
        "El Chijolar"
    ],
    "wof:name":"El Chijolar",
    "wof:placetype":"locality",
    "wof:population":1
},
  "geometry": {"coordinates":[-97.83083000000001,21.04333],"type":"Point"}
}