{
  "type": "Feature",
  "properties": {
    "gn:admin1_code":"5",
    "gn:admin2_code":"80.0",
    "gn:asciiname":"Cumbre Ventanas",
    "gn:country_code":"MX",
    "gn:dem":2366,
    "gn:feature_class":"P",
    "gn:feature_code":"PPL",
    "gn:name":"Cumbre Ventanas",
    "gn:population":763,
    "gn:timezone":"America/Mexico_City",
    "iso:country":"MX",
    "wof:name":"Cumbre Ventanas",
    "wof:placetype":"locality",
    "wof:population":763
},
  "geometry": {"coordinates":[-92.29961,15.55092],"type":"Point"}
}