{
  "type": "Feature",
  "properties": {
    "gn:admin1_code":"21.0",
    "gn:asciiname":"Guadalupe Victoria",
    "gn:country_code":"MX",
    "gn:dem":1088,
    "gn:feature_class":"P",
    "gn:feature_code":"PPL",
    "gn:name":"Guadalupe Victoria",
    "gn:population":0,
    "gn:timezone":"America/Mexico_City",
    "iso:country":"MX",
    "name:spa_x_preferred":[
        "Guadalupe Victoria"
    ],
    "name:spa_x_variant":[
        "El Terrero"
    ],
    "wof:name":"Guadalupe Victoria",
    "wof:placetype":"locality"
},
  "geometry": {"coordinates":[-98.23933,18.44119],"type":"Point"}
}