{
  "type": "Feature",
  "properties": {
    "gn:admin1_code":"14",
    "gn:admin2_code":"87",
    "gn:asciiname":"Puerto Hondo",
    "gn:country_code":"MX",
    "gn:dem":1701,
    "gn:feature_class":"P",
    "gn:feature_code":"PPL",
    "gn:name":"Puerto Hondo",
    "gn:population":21,
    "gn:timezone":"America/Mexico_City",
    "iso:country":"MX",
    "wof:name":"Puerto Hondo",
    "wof:placetype":"locality",
    "wof:population":21
},
  "geometry": {"coordinates":[-103.13778000000001,19.15278],"type":"Point"}
}