{
  "type": "Feature",
  "properties": {
    "gn:admin1_code":"11",
    "gn:admin2_code":"17.0",
    "gn:asciiname":"Venado de San Lorenzo",
    "gn:country_code":"MX",
    "gn:dem":1745,
    "gn:feature_class":"P",
    "gn:feature_code":"PPL",
    "gn:name":"Venado de San Lorenzo",
    "gn:population":268,
    "gn:timezone":"America/Mexico_City",
    "iso:country":"MX",
    "wof:name":"Venado de San Lorenzo",
    "wof:placetype":"locality",
    "wof:population":268
},
  "geometry": {"coordinates":[-101.48027999999999,20.75917],"type":"Point"}
}