{
  "type": "Feature",
  "properties": {
    "gn:admin1_code":"1",
    "gn:admin2_code":"5",
    "gn:asciiname":"Camino Real [Granja]",
    "gn:country_code":"MX",
    "gn:dem":1888,
    "gn:feature_class":"P",
    "gn:feature_code":"PPL",
    "gn:name":"Camino Real [Granja]",
    "gn:population":12,
    "gn:timezone":"America/Mexico_City",
    "iso:country":"MX",
    "wof:name":"Camino Real [Granja]",
    "wof:placetype":"locality",
    "wof:population":12
},
  "geometry": {"coordinates":[-102.29333,22.00361],"type":"Point"}
}