{
  "type": "Feature",
  "properties": {
    "gn:admin1_code":"27",
    "gn:admin2_code":"10.0",
    "gn:asciiname":"Boquiapa",
    "gn:country_code":"MX",
    "gn:dem":15,
    "gn:feature_class":"P",
    "gn:feature_code":"PPL",
    "gn:name":"Boquiapa",
    "gn:population":1156,
    "gn:timezone":"America/Mexico_City",
    "iso:country":"MX",
    "wof:name":"Boquiapa",
    "wof:placetype":"locality",
    "wof:population":1156
},
  "geometry": {"coordinates":[-93.1375,18.16111],"type":"Point"}
}