{
  "type": "Feature",
  "properties": {
    "gn:admin1_code":"30.0",
    "gn:admin2_code":"155.0",
    "gn:asciiname":"Rancho el Padre",
    "gn:country_code":"MX",
    "gn:dem":208,
    "gn:feature_class":"P",
    "gn:feature_code":"PPL",
    "gn:name":"Rancho el Padre",
    "gn:population":0,
    "gn:timezone":"America/Mexico_City",
    "iso:country":"MX",
    "name:spa_x_preferred":[
        "Rancho el Padre"
    ],
    "wof:name":"Rancho el Padre",
    "wof:placetype":"locality"
},
  "geometry": {"coordinates":[-98.24324,21.36913],"type":"Point"}
}