{
  "type": "Feature",
  "properties": {
    "gn:admin1_code":"5",
    "gn:admin2_code":"53",
    "gn:asciiname":"Loma Grande",
    "gn:country_code":"MX",
    "gn:dem":2237,
    "gn:feature_class":"P",
    "gn:feature_code":"PPL",
    "gn:name":"Loma Grande",
    "gn:population":20,
    "gn:timezone":"America/Mexico_City",
    "iso:country":"MX",
    "wof:name":"Loma Grande",
    "wof:placetype":"locality",
    "wof:population":20
},
  "geometry": {"coordinates":[-92.1925,15.30194],"type":"Point"}
}