{
  "type": "Feature",
  "properties": {
    "gn:admin1_code":"12.0",
    "gn:admin2_code":"16.0",
    "gn:asciiname":"Rancho Bonito",
    "gn:country_code":"MX",
    "gn:dem":600,
    "gn:feature_class":"P",
    "gn:feature_code":"PPL",
    "gn:name":"Rancho Bonito",
    "gn:population":0,
    "gn:timezone":"America/Mexico_City",
    "iso:country":"MX",
    "name:spa_x_preferred":[
        "Rancho Bonito"
    ],
    "wof:name":"Rancho Bonito",
    "wof:placetype":"locality"
},
  "geometry": {"coordinates":[-101.81797,18.1842],"type":"Point"}
}