{
  "type": "Feature",
  "properties": {
    "gn:admin1_code":"11",
    "gn:admin2_code":"29",
    "gn:asciiname":"Las Mariolas (San Jose de la Montana)",
    "gn:country_code":"MX",
    "gn:dem":2009,
    "gn:feature_class":"P",
    "gn:feature_code":"PPL",
    "gn:name":"Las Mariolas (San Jos\u00e9 de la Monta\u00f1a)",
    "gn:population":23,
    "gn:timezone":"America/Mexico_City",
    "iso:country":"MX",
    "name:und_x_variant":[
        "Las Mariolas (San Jos\u00e9 de la Monta\u00f1a)"
    ],
    "wof:name":"Las Mariolas (San Jose de la Montana)",
    "wof:placetype":"locality",
    "wof:population":23
},
  "geometry": {"coordinates":[-100.68056,21.32583],"type":"Point"}
}