{
  "type": "Feature",
  "properties": {
    "gn:admin1_code":"25.0",
    "gn:asciiname":"Las Arenitas",
    "gn:country_code":"MX",
    "gn:dem":98,
    "gn:feature_class":"P",
    "gn:feature_code":"PPL",
    "gn:name":"Las Arenitas",
    "gn:population":0,
    "gn:timezone":"America/Mazatlan",
    "iso:country":"MX",
    "name:spa_x_preferred":[
        "Las Arenitas"
    ],
    "wof:name":"Las Arenitas",
    "wof:placetype":"locality"
},
  "geometry": {"coordinates":[-105.77822999999999,22.91998],"type":"Point"}
}