{
  "type": "Feature",
  "properties": {
    "gn:admin1_code":"11.0",
    "gn:asciiname":"San Rafael de Villasenor",
    "gn:country_code":"MX",
    "gn:dem":1754,
    "gn:feature_class":"P",
    "gn:feature_code":"PPL",
    "gn:name":"San Rafael de Villase\u00f1or",
    "gn:population":0,
    "gn:timezone":"America/Mexico_City",
    "iso:country":"MX",
    "name:spa_x_preferred":[
        "San Rafael de Villase\u00f1or"
    ],
    "wof:name":"San Rafael de Villasenor",
    "wof:placetype":"locality"
},
  "geometry": {"coordinates":[-101.73812,20.40691],"type":"Point"}
}