{
  "type": "Feature",
  "properties": {
    "gn:admin1_code":"14",
    "gn:admin2_code":"124",
    "gn:asciiname":"Noxtla",
    "gn:country_code":"MX",
    "gn:dem":1705,
    "gn:feature_class":"P",
    "gn:feature_code":"PPL",
    "gn:name":"Noxtla",
    "gn:population":10,
    "gn:timezone":"America/Mexico_City",
    "iso:country":"MX",
    "wof:name":"Noxtla",
    "wof:placetype":"locality",
    "wof:population":10
},
  "geometry": {"coordinates":[-103.10250000000001,20.74611],"type":"Point"}
}