{
  "type": "Feature",
  "properties": {
    "gn:admin1_code":"24.0",
    "gn:asciiname":"El Molino Cinco Senores",
    "gn:country_code":"MX",
    "gn:dem":1822,
    "gn:feature_class":"P",
    "gn:feature_code":"PPL",
    "gn:name":"El Molino Cinco Se\u00f1ores",
    "gn:population":0,
    "gn:timezone":"America/Mexico_City",
    "iso:country":"MX",
    "name:spa_x_preferred":[
        "El Molino Cinco Se\u00f1ores"
    ],
    "name:spa_x_variant":[
        "El Molino de Cinco Se\u00f1ores"
    ],
    "wof:name":"El Molino Cinco Senores",
    "wof:placetype":"locality"
},
  "geometry": {"coordinates":[-100.74760999999999,21.65097],"type":"Point"}
}