{
  "type": "Feature",
  "properties": {
    "gn:country":"MX",
    "gn:fcode":"PPL",
    "gn:population":3787,
    "iso:country":"MX",
    "name:ceb_x_preferred":[
        "Prax\u00e9dis Guerrero"
    ],
    "name:eng_x_preferred":[
        "Pr\u00e1xedis G. Guerrero"
    ],
    "name:nld_x_preferred":[
        "Pr\u00e1xedis G. Guerrero"
    ],
    "name:rus_x_preferred":[
        "\u041f\u0440\u0430\u0445\u0435\u0434\u0438\u0441-\u0413\u0435\u0440\u0440\u0435\u0440\u043e"
    ],
    "name:sco_x_preferred":[
        "Pr\u00e1xedis G. Guerrero"
    ],
    "name:spa_x_preferred":[
        "Pr\u00e1xedis G. Guerrero"
    ],
    "name:srp_x_preferred":[
        "\u041f\u0440\u0430\u043a\u0441\u0435\u0434\u0438\u0441 \u0413. \u0413\u0435\u0440\u0435\u0440\u043e"
    ],
    "name:swe_x_preferred":[
        "Prax\u00e9dis Guerrero"
    ],
    "qs_pg:aaroncc":"MX",
    "qs_pg:gn_country":"MX",
    "qs_pg:gn_fcode":"PPL",
    "qs_pg:gn_pop":3787,
    "qs_pg:name":"Prax\u00e9dis Guerrero",
    "qs_pg:photos_9r":0,
    "qs_pg:photos_sr":0,
    "qs_pg:pop_sr":4,
    "qs_pg:qs_pg_placetype":"locality",
    "wof:name":"Prax\u00e9dis Guerrero",
    "wof:placetype":"locality",
    "wof:population":3787
},
  "geometry": {"coordinates":[-106.01667,31.36667],"type":"Point"}
}