{
  "type": "Feature",
  "properties": {
    "gn:admin1_code":"31",
    "gn:admin2_code":"50.0",
    "gn:asciiname":"San Antonio Chuntuac",
    "gn:country_code":"MX",
    "gn:dem":9,
    "gn:feature_class":"P",
    "gn:feature_code":"PPL",
    "gn:name":"San Antonio Chuntuac",
    "gn:population":5,
    "gn:timezone":"America/Merida",
    "iso:country":"MX",
    "wof:name":"San Antonio Chuntuac",
    "wof:placetype":"locality",
    "wof:population":5
},
  "geometry": {"coordinates":[-89.64139,20.81528],"type":"Point"}
}