{
  "type": "Feature",
  "properties": {
    "gn:admin1_code":"24",
    "gn:admin2_code":"17.0",
    "gn:asciiname":"El Puerto de la Clavellina",
    "gn:country_code":"MX",
    "gn:dem":1269,
    "gn:feature_class":"P",
    "gn:feature_code":"PPL",
    "gn:name":"El Puerto de la Clavellina",
    "gn:population":0,
    "gn:timezone":"America/Mexico_City",
    "iso:country":"MX",
    "name:spa_x_preferred":[
        "El Puerto de la Clavellina"
    ],
    "wof:name":"El Puerto de la Clavellina",
    "wof:placetype":"locality"
},
  "geometry": {"coordinates":[-100.12114,23.12136],"type":"Point"}
}