{
  "type": "Feature",
  "properties": {
    "gn:admin1_code":"21",
    "gn:admin2_code":"58.0",
    "gn:asciiname":"La Reforma",
    "gn:country_code":"MX",
    "gn:dem":2638,
    "gn:feature_class":"P",
    "gn:feature_code":"PPL",
    "gn:name":"La Reforma",
    "gn:population":185,
    "gn:timezone":"America/Mexico_City",
    "iso:country":"MX",
    "wof:name":"La Reforma",
    "wof:placetype":"locality",
    "wof:population":185
},
  "geometry": {"coordinates":[-97.18799,19.2268],"type":"Point"}
}