{
  "type": "Feature",
  "properties": {
    "gn:admin1_code":"26",
    "gn:admin2_code":"44.0",
    "gn:asciiname":"El Recodo",
    "gn:country_code":"MX",
    "gn:dem":156,
    "gn:feature_class":"P",
    "gn:feature_code":"PPL",
    "gn:name":"El Recodo",
    "gn:population":0,
    "gn:timezone":"America/Hermosillo",
    "iso:country":"MX",
    "name:spa_x_preferred":[
        "El Recodo"
    ],
    "name:und_x_variant":[
        "Rancho Recodo"
    ],
    "wof:name":"El Recodo",
    "wof:placetype":"locality"
},
  "geometry": {"coordinates":[-109.5394,28.41236],"type":"Point"}
}