{
  "type": "Feature",
  "properties": {
    "gn:admin1_code":"5",
    "gn:admin2_code":"49.0",
    "gn:asciiname":"Pechton",
    "gn:country_code":"MX",
    "gn:dem":2209,
    "gn:feature_class":"P",
    "gn:feature_code":"PPL",
    "gn:name":"Pecht\u00f3n",
    "gn:population":106,
    "gn:timezone":"America/Mexico_City",
    "iso:country":"MX",
    "name:und_x_variant":[
        "Pecht\u00f3n"
    ],
    "wof:name":"Pechton",
    "wof:placetype":"locality",
    "wof:population":106
},
  "geometry": {"coordinates":[-92.78139,16.89306],"type":"Point"}
}