{
  "type": "Feature",
  "properties": {
    "gn:admin1_code":"10",
    "gn:admin2_code":"32.0",
    "gn:asciiname":"Los Alisos",
    "gn:cc2":"MX",
    "gn:country_code":"MX",
    "gn:dem":2167,
    "gn:feature_class":"P",
    "gn:feature_code":"PPL",
    "gn:name":"Los Alisos",
    "gn:population":0,
    "gn:timezone":"America/Monterrey",
    "iso:country":"MX",
    "name:und_x_variant":[
        "Alisos",
        "Los Alisos"
    ],
    "wof:name":"Los Alisos",
    "wof:placetype":"locality"
},
  "geometry": {"coordinates":[-105.41667,24.83333],"type":"Point"}
}