{
  "type": "Feature",
  "properties": {
    "gn:admin1_code":"32.0",
    "gn:admin2_code":"55.0",
    "gn:asciiname":"El Saucillo",
    "gn:cc2":"MX",
    "gn:country_code":"MX",
    "gn:dem":2262,
    "gn:feature_class":"P",
    "gn:feature_code":"PPL",
    "gn:name":"El Saucillo",
    "gn:population":0,
    "gn:timezone":"America/Mexico_City",
    "iso:country":"MX",
    "wof:name":"El Saucillo",
    "wof:placetype":"locality"
},
  "geometry": {"coordinates":[-102.76667,22.41667],"type":"Point"}
}