{
  "type": "Feature",
  "properties": {
    "gn:admin1_code":"10",
    "gn:admin2_code":"13.0",
    "gn:asciiname":"Puerta el Refugio",
    "gn:country_code":"MX",
    "gn:dem":1515,
    "gn:feature_class":"P",
    "gn:feature_code":"PPL",
    "gn:name":"Puerta el Refugio",
    "gn:population":7,
    "gn:timezone":"America/Monterrey",
    "iso:country":"MX",
    "wof:name":"Puerta el Refugio",
    "wof:placetype":"locality",
    "wof:population":7
},
  "geometry": {"coordinates":[-104.1639,25.87068],"type":"Point"}
}