{
  "type": "Feature",
  "properties": {
    "gn:admin1_code":"22",
    "gn:admin2_code":"12.0",
    "gn:asciiname":"Las Postas",
    "gn:country_code":"MX",
    "gn:dem":1938,
    "gn:feature_class":"P",
    "gn:feature_code":"PPL",
    "gn:name":"Las Postas",
    "gn:population":367,
    "gn:timezone":"America/Mexico_City",
    "iso:country":"MX",
    "wof:name":"Las Postas",
    "wof:placetype":"locality",
    "wof:population":367
},
  "geometry": {"coordinates":[-100.13806,20.45333],"type":"Point"}
}