{
  "type": "Feature",
  "properties": {
    "gn:admin1_code":"6.0",
    "gn:admin2_code":"61.0",
    "gn:asciiname":"Preson",
    "gn:country_code":"MX",
    "gn:dem":1702,
    "gn:feature_class":"P",
    "gn:feature_code":"PPL",
    "gn:name":"Pres\u00f3n",
    "gn:population":0,
    "gn:timezone":"America/Chihuahua",
    "iso:country":"MX",
    "name:spa_x_preferred":[
        "Pres\u00f3n"
    ],
    "wof:name":"Preson",
    "wof:placetype":"locality"
},
  "geometry": {"coordinates":[-106.38697000000001,27.55793],"type":"Point"}
}