{
  "type": "Feature",
  "properties": {
    "gn:admin1_code":"25",
    "gn:admin2_code":"3.0",
    "gn:asciiname":"Los Zapotes",
    "gn:country_code":"MX",
    "gn:dem":400,
    "gn:feature_class":"P",
    "gn:feature_code":"PPL",
    "gn:name":"Los Zapotes",
    "gn:population":0,
    "gn:timezone":"America/Mazatlan",
    "iso:country":"MX",
    "name:spa_x_preferred":[
        "Los Zapotes"
    ],
    "wof:name":"Los Zapotes",
    "wof:placetype":"locality"
},
  "geometry": {"coordinates":[-107.44457,25.43759],"type":"Point"}
}