{
  "type": "Feature",
  "properties": {
    "gn:admin1_code":"19",
    "gn:admin2_code":"20",
    "gn:asciiname":"Carta Blanca (El Negro)",
    "gn:country_code":"MX",
    "gn:dem":136,
    "gn:feature_class":"P",
    "gn:feature_code":"PPL",
    "gn:name":"Carta Blanca (El Negro)",
    "gn:population":16,
    "gn:timezone":"America/Monterrey",
    "iso:country":"MX",
    "wof:name":"Carta Blanca (El Negro)",
    "wof:placetype":"locality",
    "wof:population":16
},
  "geometry": {"coordinates":[-98.67556999999999,25.93563],"type":"Point"}
}