{
  "type": "Feature",
  "properties": {
    "gn:admin1_code":"23",
    "gn:admin2_code":"5",
    "gn:asciiname":"Los Coquitos",
    "gn:country_code":"MX",
    "gn:dem":12,
    "gn:feature_class":"P",
    "gn:feature_code":"PPL",
    "gn:name":"Los Coquitos",
    "gn:population":18,
    "gn:timezone":"America/Cancun",
    "iso:country":"MX",
    "wof:name":"Los Coquitos",
    "wof:placetype":"locality",
    "wof:population":18
},
  "geometry": {"coordinates":[-87.09362,21.07126],"type":"Point"}
}