{
  "type": "Feature",
  "properties": {
    "gn:admin1_code":"14",
    "gn:admin2_code":"46.0",
    "gn:asciiname":"Los Ladinos",
    "gn:country_code":"MX",
    "gn:dem":1762,
    "gn:feature_class":"P",
    "gn:feature_code":"PPL",
    "gn:name":"Los Ladinos",
    "gn:population":6,
    "gn:timezone":"America/Mexico_City",
    "iso:country":"MX",
    "wof:name":"Los Ladinos",
    "wof:placetype":"locality",
    "wof:population":6
},
  "geometry": {"coordinates":[-102.45639,21.31389],"type":"Point"}
}