{
  "type": "Feature",
  "properties": {
    "gn:admin1_code":"32.0",
    "gn:admin2_code":"49.0",
    "gn:asciiname":"Jacalitos",
    "gn:country_code":"MX",
    "gn:dem":2304,
    "gn:feature_class":"P",
    "gn:feature_code":"PPL",
    "gn:name":"Jacalitos",
    "gn:population":0,
    "gn:timezone":"America/Mexico_City",
    "iso:country":"MX",
    "name:spa_x_preferred":[
        "Jacalitos"
    ],
    "wof:name":"Jacalitos",
    "wof:placetype":"locality"
},
  "geometry": {"coordinates":[-103.68427,22.79309],"type":"Point"}
}