{
  "type": "Feature",
  "properties": {
    "gn:admin1_code":"15.0",
    "gn:asciiname":"Ejido Nuevo Coroneo Fraccion Salitrillo",
    "gn:country_code":"MX",
    "gn:dem":2300,
    "gn:feature_class":"P",
    "gn:feature_code":"PPL",
    "gn:name":"Ejido Nuevo Coroneo Fraccion Salitrillo",
    "gn:population":0,
    "gn:timezone":"America/Mexico_City",
    "iso:country":"MX",
    "name:spa_x_preferred":[
        "Ejido Nuevo Coroneo Fraccion Salitrillo"
    ],
    "wof:name":"Ejido Nuevo Coroneo Fraccion Salitrillo",
    "wof:placetype":"locality"
},
  "geometry": {"coordinates":[-100.34583000000001,20.16444],"type":"Point"}
}