{
  "type": "Feature",
  "properties": {
    "gn:admin1_code":"20.0",
    "gn:admin2_code":"470.0",
    "gn:asciiname":"Ocotal",
    "gn:country_code":"MX",
    "gn:dem":1314,
    "gn:feature_class":"P",
    "gn:feature_code":"PPL",
    "gn:name":"Ocotal",
    "gn:population":0,
    "gn:timezone":"America/Mexico_City",
    "iso:country":"MX",
    "name:bel_x_preferred":[
        "\u0410\u043a\u0430\u0442\u0430\u043b\u044c"
    ],
    "name:deu_x_preferred":[
        "Ocotal"
    ],
    "name:epo_x_preferred":[
        "Ocotal"
    ],
    "name:eus_x_preferred":[
        "Ocotal"
    ],
    "name:fra_x_preferred":[
        "Ocotal"
    ],
    "name:ita_x_preferred":[
        "Ocotal"
    ],
    "name:kat_x_preferred":[
        "\u10dd\u10d9\u10dd\u10e2\u10d0\u10da\u10d8"
    ],
    "name:kor_x_preferred":[
        "\uc624\ucf54\ud0c8"
    ],
    "name:lit_x_preferred":[
        "Okotalis"
    ],
    "name:nld_x_preferred":[
        "Ocotal"
    ],
    "name:oss_x_preferred":[
        "\u041e\u043a\u043e\u0442\u0430\u043b\u044c"
    ],
    "name:pol_x_preferred":[
        "Ocotal"
    ],
    "name:rus_x_preferred":[
        "\u041e\u043a\u043e\u0442\u0430\u043b\u044c"
    ],
    "name:spa_x_preferred":[
        "Ocotal"
    ],
    "name:swe_x_preferred":[
        "Ocotal"
    ],
    "name:ukr_x_preferred":[
        "\u041e\u043a\u043e\u0442\u0430\u043b\u044c"
    ],
    "name:urd_x_preferred":[
        "\u0627\u0648\u06a9\u0648\u062a\u0627\u0644"
    ],
    "name:vie_x_preferred":[
        "Ocotal"
    ],
    "name:zho_x_preferred":[
        "\u5967\u79d1\u5854\u723e"
    ],
    "wof:name":"Ocotal",
    "wof:placetype":"locality"
},
  "geometry": {"coordinates":[-95.50156,16.77086],"type":"Point"}
}