{
  "type": "Feature",
  "properties": {
    "gn:admin1_code":"20.0",
    "gn:admin2_code":"470.0",
    "gn:asciiname":"Ocotal",
    "gn:country_code":"MX",
    "gn:dem":1314,
    "gn:feature_class":"P",
    "gn:feature_code":"PPL",
    "gn:name":"Ocotal",
    "gn:population":0,
    "gn:timezone":"America/Mexico_City",
    "iso:country":"MX",
    "name:spa_x_preferred":[
        "Ocotal"
    ],
    "wof:name":"Ocotal",
    "wof:placetype":"locality"
},
  "geometry": {"coordinates":[-95.50156,16.77086],"type":"Point"}
}