{
  "type": "Feature",
  "properties": {
    "gn:admin1_code":"5.0",
    "gn:admin2_code":"96.0",
    "gn:asciiname":"El Escalon",
    "gn:country_code":"MX",
    "gn:dem":42,
    "gn:feature_class":"P",
    "gn:feature_code":"PPL",
    "gn:name":"El Escal\u00f3n",
    "gn:population":0,
    "gn:timezone":"America/Mexico_City",
    "iso:country":"MX",
    "name:spa_x_preferred":[
        "El Escal\u00f3n"
    ],
    "wof:name":"El Escalon",
    "wof:placetype":"locality"
},
  "geometry": {"coordinates":[-92.46951,17.4632],"type":"Point"}
}