{
  "type": "Feature",
  "properties": {
    "gn:admin1_code":"30",
    "gn:admin2_code":"58.0",
    "gn:asciiname":"Atlalco",
    "gn:country_code":"MX",
    "gn:dem":127,
    "gn:feature_class":"P",
    "gn:feature_code":"PPL",
    "gn:name":"Atlalco",
    "gn:population":132,
    "gn:timezone":"America/Mexico_City",
    "iso:country":"MX",
    "name:spa_x_preferred":[
        "Atlalco"
    ],
    "wof:name":"Atlalco",
    "wof:placetype":"locality",
    "wof:population":132
},
  "geometry": {"coordinates":[-97.95972,20.89389],"type":"Point"}
}