{
  "type": "Feature",
  "properties": {
    "gn:admin1_code":"15.0",
    "gn:asciiname":"Huerta el Jijiri",
    "gn:country_code":"MX",
    "gn:dem":2471,
    "gn:feature_class":"P",
    "gn:feature_code":"PPL",
    "gn:name":"Huerta el Jijiri",
    "gn:population":0,
    "gn:timezone":"America/Mexico_City",
    "iso:country":"MX",
    "name:spa_x_preferred":[
        "Huerta el Jijiri"
    ],
    "wof:name":"Huerta el Jijiri",
    "wof:placetype":"locality"
},
  "geometry": {"coordinates":[-98.80179,19.19307],"type":"Point"}
}