{
  "type": "Feature",
  "properties": {
    "gn:admin1_code":"11.0",
    "gn:admin2_code":"17.0",
    "gn:asciiname":"Molino de Santa Ana",
    "gn:country_code":"MX",
    "gn:dem":1763,
    "gn:feature_class":"P",
    "gn:feature_code":"PPL",
    "gn:name":"Molino de Santa Ana",
    "gn:population":0,
    "gn:timezone":"America/Mexico_City",
    "iso:country":"MX",
    "name:spa_x_preferred":[
        "Molino de Santa Ana"
    ],
    "wof:name":"Molino de Santa Ana",
    "wof:placetype":"locality"
},
  "geometry": {"coordinates":[-101.34929,20.82874],"type":"Point"}
}