{
  "type": "Feature",
  "properties": {
    "gn:admin1_code":"14",
    "gn:admin2_code":"52.0",
    "gn:asciiname":"Los Ranchitos (El Ranchito de Cobian)",
    "gn:country_code":"MX",
    "gn:dem":1335,
    "gn:feature_class":"P",
    "gn:feature_code":"PPL",
    "gn:name":"Los Ranchitos (El Ranchito de Cobi\u00e1n)",
    "gn:population":8,
    "gn:timezone":"America/Mexico_City",
    "iso:country":"MX",
    "name:und_x_variant":[
        "Los Ranchitos (El Ranchito de Cobi\u00e1n)"
    ],
    "wof:name":"Los Ranchitos (El Ranchito de Cobian)",
    "wof:placetype":"locality",
    "wof:population":8
},
  "geometry": {"coordinates":[-104.015,20.08861],"type":"Point"}
}