{
  "type": "Feature",
  "properties": {
    "gn:admin1_code":"6",
    "gn:admin2_code":"8.0",
    "gn:asciiname":"Noina",
    "gn:country_code":"MX",
    "gn:dem":2006,
    "gn:feature_class":"P",
    "gn:feature_code":"PPL",
    "gn:name":"Noina",
    "gn:population":79,
    "gn:timezone":"America/Chihuahua",
    "iso:country":"MX",
    "wof:name":"Noina",
    "wof:placetype":"locality",
    "wof:population":79
},
  "geometry": {"coordinates":[-107.59434,26.92799],"type":"Point"}
}