{
  "type": "Feature",
  "properties": {
    "gn:admin1_code":"12.0",
    "gn:admin2_code":"71.0",
    "gn:asciiname":"Rincon Pochota",
    "gn:country_code":"MX",
    "gn:dem":578,
    "gn:feature_class":"P",
    "gn:feature_code":"PPL",
    "gn:name":"Rinc\u00f3n Pochota",
    "gn:population":0,
    "gn:timezone":"America/Mexico_City",
    "iso:country":"MX",
    "name:spa_x_preferred":[
        "Rinc\u00f3n Pochota"
    ],
    "wof:name":"Rincon Pochota",
    "wof:placetype":"locality"
},
  "geometry": {"coordinates":[-98.11212999999999,16.9296],"type":"Point"}
}