{
  "type": "Feature",
  "properties": {
    "gn:admin1_code":"26",
    "gn:admin2_code":"54.0",
    "gn:asciiname":"El Sabino",
    "gn:country_code":"MX",
    "gn:dem":389,
    "gn:feature_class":"P",
    "gn:feature_code":"PPL",
    "gn:name":"El Sabino",
    "gn:population":0,
    "gn:timezone":"America/Hermosillo",
    "iso:country":"MX",
    "name:spa_x_preferred":[
        "El Sabino"
    ],
    "wof:name":"El Sabino",
    "wof:placetype":"locality"
},
  "geometry": {"coordinates":[-109.82402999999999,28.54908],"type":"Point"}
}