{
  "type": "Feature",
  "properties": {
    "gn:admin1_code":"11",
    "gn:admin2_code":"17",
    "gn:asciiname":"El Pistache",
    "gn:country_code":"MX",
    "gn:dem":1715,
    "gn:feature_class":"P",
    "gn:feature_code":"PPL",
    "gn:name":"El Pistache",
    "gn:population":25,
    "gn:timezone":"America/Mexico_City",
    "iso:country":"MX",
    "wof:name":"El Pistache",
    "wof:placetype":"locality",
    "wof:population":25
},
  "geometry": {"coordinates":[-101.36861,20.62611],"type":"Point"}
}