{
  "type": "Feature",
  "properties": {
    "gn:admin1_code":"10.0",
    "gn:admin2_code":"35.0",
    "gn:asciiname":"Cienega",
    "gn:country_code":"MX",
    "gn:dem":2305,
    "gn:feature_class":"P",
    "gn:feature_code":"PPL",
    "gn:name":"Ci\u00e9nega",
    "gn:population":0,
    "gn:timezone":"America/Monterrey",
    "iso:country":"MX",
    "name:spa_x_preferred":[
        "Ci\u00e9nega"
    ],
    "wof:name":"Cienega",
    "wof:placetype":"locality"
},
  "geometry": {"coordinates":[-106.24850000000001,25.21395],"type":"Point"}
}