{
  "type": "Feature",
  "properties": {
    "gn:admin1_code":"10.0",
    "gn:admin2_code":"9.0",
    "gn:asciiname":"Chupaderos",
    "gn:country_code":"MX",
    "gn:dem":2198,
    "gn:feature_class":"P",
    "gn:feature_code":"PPL",
    "gn:name":"Chupaderos",
    "gn:population":0,
    "gn:timezone":"America/Monterrey",
    "iso:country":"MX",
    "name:und_x_variant":[
        "Rancho Chupaderos",
        "Chupaderos"
    ],
    "wof:name":"Chupaderos",
    "wof:placetype":"locality"
},
  "geometry": {"coordinates":[-105.72580000000001,25.64249],"type":"Point"}
}