{
  "type": "Feature",
  "properties": {
    "gn:admin1_code":"12",
    "gn:admin2_code":"52",
    "gn:asciiname":"Atotonilco",
    "gn:country_code":"MX",
    "gn:dem":503,
    "gn:feature_class":"P",
    "gn:feature_code":"PPL",
    "gn:name":"Atotonilco",
    "gn:population":19,
    "gn:timezone":"America/Mexico_City",
    "iso:country":"MX",
    "name:ceb_x_preferred":[
        "Atotonilco"
    ],
    "name:deu_x_preferred":[
        "Atotonilco"
    ],
    "name:ita_x_preferred":[
        "Atotonilco"
    ],
    "name:sco_x_preferred":[
        "Atotonilco"
    ],
    "name:spa_x_preferred":[
        "Atotonilco"
    ],
    "name:swe_x_preferred":[
        "Atotonilco"
    ],
    "wof:name":"Atotonilco",
    "wof:placetype":"locality",
    "wof:population":19
},
  "geometry": {"coordinates":[-98.70112,16.92166],"type":"Point"}
}