{
  "type": "Feature",
  "properties": {
    "gn:admin1_code":"22",
    "gn:admin2_code":"13.0",
    "gn:asciiname":"Agua de Pedro",
    "gn:country_code":"MX",
    "gn:dem":1669,
    "gn:feature_class":"P",
    "gn:feature_code":"PPL",
    "gn:name":"Agua de Pedro",
    "gn:population":251,
    "gn:timezone":"America/Mexico_City",
    "iso:country":"MX",
    "wof:name":"Agua de Pedro",
    "wof:placetype":"locality",
    "wof:population":251
},
  "geometry": {"coordinates":[-99.80500000000001,21.12333],"type":"Point"}
}