{
  "type": "Feature",
  "properties": {
    "gn:admin1_code":"6",
    "gn:admin2_code":"7",
    "gn:asciiname":"Agua Azul",
    "gn:country_code":"MX",
    "gn:dem":2497,
    "gn:feature_class":"P",
    "gn:feature_code":"PPL",
    "gn:name":"Agua Azul",
    "gn:population":22,
    "gn:timezone":"America/Chihuahua",
    "iso:country":"MX",
    "name:bre_x_preferred":[
        "Agua Azul"
    ],
    "name:lit_x_preferred":[
        "Agua Asulio krioklys"
    ],
    "name:pol_x_preferred":[
        "Wodospady Agua Azul"
    ],
    "name:swe_x_preferred":[
        "Agua Azul"
    ],
    "name:ukr_x_preferred":[
        "\u0410\u0433\u0432\u0430 \u0410\u0441\u0443\u043b\u044c"
    ],
    "wof:name":"Agua Azul",
    "wof:placetype":"locality",
    "wof:population":22
},
  "geometry": {"coordinates":[-106.63482999999999,26.68709],"type":"Point"}
}