{
  "type": "Feature",
  "properties": {
    "gn:admin1_code":"5",
    "gn:admin2_code":"21.0",
    "gn:asciiname":"Angel Albino Corzo",
    "gn:country_code":"MX",
    "gn:dem":673,
    "gn:feature_class":"P",
    "gn:feature_code":"PPL",
    "gn:name":"Angel Albino Corzo",
    "gn:population":0,
    "gn:timezone":"America/Mexico_City",
    "iso:country":"MX",
    "name:spa_x_preferred":[
        "Angel Albino Corzo"
    ],
    "name:spa_x_variant":[
        "Guadalupe"
    ],
    "wof:name":"Angel Albino Corzo",
    "wof:placetype":"locality"
},
  "geometry": {"coordinates":[-93.26415,17.12639],"type":"Point"}
}