{
  "type": "Feature",
  "properties": {
    "gn:admin1_code":"15",
    "gn:admin2_code":"99.0",
    "gn:asciiname":"Los Sauces",
    "gn:country_code":"MX",
    "gn:dem":2246,
    "gn:feature_class":"P",
    "gn:feature_code":"PPL",
    "gn:name":"Los Sauces",
    "gn:population":129,
    "gn:timezone":"America/Mexico_City",
    "iso:country":"MX",
    "wof:name":"Los Sauces",
    "wof:placetype":"locality",
    "wof:population":129
},
  "geometry": {"coordinates":[-98.89776999999999,19.50455],"type":"Point"}
}