{
  "type": "Feature",
  "properties": {
    "gn:admin1_code":"26.0",
    "gn:admin2_code":"59.0",
    "gn:asciiname":"La Colorada",
    "gn:country_code":"MX",
    "gn:dem":1222,
    "gn:feature_class":"P",
    "gn:feature_code":"PPL",
    "gn:name":"La Colorada",
    "gn:population":0,
    "gn:timezone":"America/Hermosillo",
    "iso:country":"MX",
    "name:ceb_x_preferred":[
        "La Colorada"
    ],
    "name:deu_x_preferred":[
        "La Colorada"
    ],
    "name:ita_x_preferred":[
        "La Colorada"
    ],
    "name:spa_x_preferred":[
        "La Colorada"
    ],
    "name:swe_x_preferred":[
        "La Colorada"
    ],
    "wof:name":"La Colorada",
    "wof:placetype":"locality"
},
  "geometry": {"coordinates":[-110.65217,31.06871],"type":"Point"}
}