{
  "type": "Feature",
  "properties": {
    "gn:admin1_code":"7.0",
    "gn:admin2_code":"27.0",
    "gn:asciiname":"El Buey",
    "gn:country_code":"MX",
    "gn:dem":881,
    "gn:feature_class":"P",
    "gn:feature_code":"PPL",
    "gn:name":"El Buey",
    "gn:population":0,
    "gn:timezone":"America/Monterrey",
    "iso:country":"MX",
    "name:spa_x_preferred":[
        "El Buey"
    ],
    "wof:name":"El Buey",
    "wof:placetype":"locality"
},
  "geometry": {"coordinates":[-101.11109,25.9042],"type":"Point"}
}