{
  "type": "Feature",
  "properties": {
    "gn:admin1_code":"5",
    "gn:admin2_code":"59",
    "gn:asciiname":"Quintana Roo",
    "gn:country_code":"MX",
    "gn:dem":571,
    "gn:feature_class":"P",
    "gn:feature_code":"PPL",
    "gn:name":"Quintana Roo",
    "gn:population":9,
    "gn:timezone":"America/Mexico_City",
    "iso:country":"MX",
    "wof:name":"Quintana Roo",
    "wof:placetype":"locality",
    "wof:population":9
},
  "geometry": {"coordinates":[-91.6575,16.76556],"type":"Point"}
}