{
  "type": "Feature",
  "properties": {
    "gn:admin1_code":"10",
    "gn:admin2_code":"2.0",
    "gn:asciiname":"Tablas",
    "gn:country_code":"MX",
    "gn:dem":2621,
    "gn:feature_class":"P",
    "gn:feature_code":"PPL",
    "gn:name":"Tablas",
    "gn:population":0,
    "gn:timezone":"America/Monterrey",
    "iso:country":"MX",
    "name:ceb_x_preferred":[
        "Tablas"
    ],
    "name:deu_x_preferred":[
        "Tablas"
    ],
    "name:fra_x_preferred":[
        "Tablas"
    ],
    "name:swe_x_preferred":[
        "Tablas"
    ],
    "wof:name":"Tablas",
    "wof:placetype":"locality"
},
  "geometry": {"coordinates":[-106.46666999999999,25.11667000000001],"type":"Point"}
}