{
  "type": "Feature",
  "properties": {
    "gn:admin1_code":"31.0",
    "gn:asciiname":"San Diego",
    "gn:country_code":"MX",
    "gn:dem":12,
    "gn:feature_class":"P",
    "gn:feature_code":"PPL",
    "gn:name":"San Diego",
    "gn:population":0,
    "gn:timezone":"America/Merida",
    "iso:country":"MX",
    "name:spa_x_preferred":[
        "San Diego"
    ],
    "wof:name":"San Diego",
    "wof:placetype":"locality"
},
  "geometry": {"coordinates":[-88.33273,21.20176],"type":"Point"}
}