{
  "type": "Feature",
  "properties": {
    "gn:admin1_code":"7.0",
    "gn:admin2_code":"37.0",
    "gn:asciiname":"El Tule",
    "gn:country_code":"MX",
    "gn:dem":499,
    "gn:feature_class":"P",
    "gn:feature_code":"PPL",
    "gn:name":"El Tule",
    "gn:population":0,
    "gn:timezone":"America/Monterrey",
    "iso:country":"MX",
    "name:spa_x_preferred":[
        "El Tule"
    ],
    "wof:name":"El Tule",
    "wof:placetype":"locality"
},
  "geometry": {"coordinates":[-100.93497000000001,28.02623],"type":"Point"}
}