{
  "type": "Feature",
  "properties": {
    "gn:admin1_code":"22",
    "gn:admin2_code":"7.0",
    "gn:asciiname":"La Palma",
    "gn:country_code":"MX",
    "gn:dem":2173,
    "gn:feature_class":"P",
    "gn:feature_code":"PPL",
    "gn:name":"La Palma",
    "gn:population":0,
    "gn:timezone":"America/Mexico_City",
    "iso:country":"MX",
    "name:spa_x_preferred":[
        "La Palma"
    ],
    "wof:name":"La Palma",
    "wof:placetype":"locality"
},
  "geometry": {"coordinates":[-99.89999,20.75812],"type":"Point"}
}