{
  "type": "Feature",
  "properties": {
    "gn:admin1_code":"11",
    "gn:admin2_code":"12.0",
    "gn:asciiname":"Mexiquito",
    "gn:country_code":"MX",
    "gn:dem":1742,
    "gn:feature_class":"P",
    "gn:feature_code":"PPL",
    "gn:name":"Mexiquito",
    "gn:population":59,
    "gn:timezone":"America/Mexico_City",
    "iso:country":"MX",
    "wof:name":"Mexiquito",
    "wof:placetype":"locality",
    "wof:population":59
},
  "geometry": {"coordinates":[-101.68971999999999,20.63306],"type":"Point"}
}