{
  "type": "Feature",
  "properties": {
    "gn:admin1_code":"13",
    "gn:admin2_code":"59.0",
    "gn:asciiname":"La Lomita",
    "gn:country_code":"MX",
    "gn:dem":1677,
    "gn:feature_class":"P",
    "gn:feature_code":"PPL",
    "gn:name":"La Lomita",
    "gn:population":232,
    "gn:timezone":"America/Mexico_City",
    "iso:country":"MX",
    "wof:name":"La Lomita",
    "wof:placetype":"locality",
    "wof:population":232
},
  "geometry": {"coordinates":[-99.63083,20.56556],"type":"Point"}
}