{
  "type": "Feature",
  "properties": {
    "gn:admin1_code":"6",
    "gn:admin2_code":"47.0",
    "gn:asciiname":"Chavira",
    "gn:country_code":"MX",
    "gn:dem":1356,
    "gn:feature_class":"P",
    "gn:feature_code":"PPL",
    "gn:name":"Chavira",
    "gn:population":0,
    "gn:timezone":"America/Chihuahua",
    "iso:country":"MX",
    "name:spa_x_preferred":[
        "Chavira"
    ],
    "wof:name":"Chavira",
    "wof:placetype":"locality"
},
  "geometry": {"coordinates":[-108.95845,28.07693],"type":"Point"}
}