{
  "type": "Feature",
  "properties": {
    "gn:admin1_code":"30.0",
    "gn:admin2_code":"189.0",
    "gn:asciiname":"Espana",
    "gn:country_code":"MX",
    "gn:dem":28,
    "gn:feature_class":"P",
    "gn:feature_code":"PPL",
    "gn:name":"Espa\u00f1a",
    "gn:population":7,
    "gn:timezone":"America/Mexico_City",
    "iso:country":"MX",
    "name:spa_x_preferred":[
        "Espa\u00f1a"
    ],
    "wof:name":"Espana",
    "wof:placetype":"locality",
    "wof:population":7
},
  "geometry": {"coordinates":[-97.45722000000001,21.08889],"type":"Point"}
}