{
  "type": "Feature",
  "properties": {
    "gn:admin1_code":"4.0",
    "gn:asciiname":"El Novillero",
    "gn:country_code":"MX",
    "gn:dem":28,
    "gn:feature_class":"P",
    "gn:feature_code":"PPL",
    "gn:name":"El Novillero",
    "gn:population":0,
    "gn:timezone":"America/Merida",
    "iso:country":"MX",
    "name:spa_x_preferred":[
        "El Novillero"
    ],
    "wof:name":"El Novillero",
    "wof:placetype":"locality"
},
  "geometry": {"coordinates":[-90.32756000000001,19.10983],"type":"Point"}
}