{
  "type": "Feature",
  "properties": {
    "gn:admin1_code":"10.0",
    "gn:admin2_code":"1.0",
    "gn:asciiname":"Donato Guerra",
    "gn:country_code":"MX",
    "gn:dem":1978,
    "gn:feature_class":"P",
    "gn:feature_code":"PPL",
    "gn:name":"Donato Guerra",
    "gn:population":769,
    "gn:timezone":"America/Monterrey",
    "iso:country":"MX",
    "name:ara_x_preferred":[
        "\u062f\u0648\u0646\u0627\u062a\u0648 \u063a\u064a\u0631\u0627"
    ],
    "name:spa_x_preferred":[
        "Donato Guerra"
    ],
    "wof:name":"Donato Guerra",
    "wof:placetype":"locality",
    "wof:population":769
},
  "geometry": {"coordinates":[-104.6388,24.61481],"type":"Point"}
}