{
  "type": "Feature",
  "properties": {
    "gn:admin1_code":"11",
    "gn:admin2_code":"23.0",
    "gn:asciiname":"El Basilon",
    "gn:country_code":"MX",
    "gn:dem":2172,
    "gn:feature_class":"P",
    "gn:feature_code":"PPL",
    "gn:name":"El Basil\u00f3n",
    "gn:population":8,
    "gn:timezone":"America/Mexico_City",
    "iso:country":"MX",
    "name:und_x_variant":[
        "El Basil\u00f3n"
    ],
    "wof:name":"El Basilon",
    "wof:placetype":"locality",
    "wof:population":8
},
  "geometry": {"coordinates":[-101.76694000000001,20.47694],"type":"Point"}
}