{
  "type": "Feature",
  "properties": {
    "gn:admin1_code":"12.0",
    "gn:admin2_code":"73.0",
    "gn:asciiname":"Carachurio",
    "gn:country_code":"MX",
    "gn:dem":1070,
    "gn:feature_class":"P",
    "gn:feature_code":"PPL",
    "gn:name":"Carachurio",
    "gn:population":0,
    "gn:timezone":"America/Mexico_City",
    "iso:country":"MX",
    "wof:name":"Carachurio",
    "wof:placetype":"locality"
},
  "geometry": {"coordinates":[-101.26667,18.25],"type":"Point"}
}