{
  "type": "Feature",
  "properties": {
    "gn:admin1_code":"14.0",
    "gn:admin2_code":"119.0",
    "gn:asciiname":"El Camichin",
    "gn:country_code":"MX",
    "gn:dem":1361,
    "gn:feature_class":"P",
    "gn:feature_code":"PPL",
    "gn:name":"El Camich\u00edn",
    "gn:population":0,
    "gn:timezone":"America/Mexico_City",
    "iso:country":"MX",
    "wof:name":"El Camichin",
    "wof:placetype":"locality"
},
  "geometry": {"coordinates":[-103.54111,20.21892],"type":"Point"}
}