{
  "type": "Feature",
  "properties": {
    "gn:admin1_code":"28.0",
    "gn:admin2_code":"39.0",
    "gn:asciiname":"La Presa de Ramos",
    "gn:country_code":"MX",
    "gn:dem":1297,
    "gn:feature_class":"P",
    "gn:feature_code":"PPL",
    "gn:name":"La Presa de Ramos",
    "gn:population":108,
    "gn:timezone":"America/Monterrey",
    "iso:country":"MX",
    "name:spa_x_preferred":[
        "La Presa de Ramos"
    ],
    "wof:name":"La Presa de Ramos",
    "wof:placetype":"locality",
    "wof:population":108
},
  "geometry": {"coordinates":[-99.63222,23.00111],"type":"Point"}
}