{
  "type": "Feature",
  "properties": {
    "gn:admin1_code":"32",
    "gn:admin2_code":"40",
    "gn:asciiname":"Rancho Nuevo (El Ranchito)",
    "gn:country_code":"MX",
    "gn:dem":2143,
    "gn:feature_class":"P",
    "gn:feature_code":"PPL",
    "gn:name":"Rancho Nuevo (El Ranchito)",
    "gn:population":15,
    "gn:timezone":"America/Mexico_City",
    "iso:country":"MX",
    "wof:name":"Rancho Nuevo (El Ranchito)",
    "wof:placetype":"locality",
    "wof:population":15
},
  "geometry": {"coordinates":[-103.29611,23.64333],"type":"Point"}
}