{
  "type": "Feature",
  "properties": {
    "gn:admin1_code":"16.0",
    "gn:admin2_code":"8.0",
    "gn:asciiname":"El Casahuate",
    "gn:country_code":"MX",
    "gn:dem":792,
    "gn:feature_class":"P",
    "gn:feature_code":"PPL",
    "gn:name":"El Casahuate",
    "gn:population":0,
    "gn:timezone":"America/Mexico_City",
    "iso:country":"MX",
    "name:spa_x_preferred":[
        "El Casahuate"
    ],
    "wof:name":"El Casahuate",
    "wof:placetype":"locality"
},
  "geometry": {"coordinates":[-102.89302000000001,18.2913],"type":"Point"}
}