{
  "type": "Feature",
  "properties": {
    "gn:admin1_code":"24",
    "gn:admin2_code":"24.0",
    "gn:asciiname":"El Saucito",
    "gn:country_code":"MX",
    "gn:dem":1211,
    "gn:feature_class":"P",
    "gn:feature_code":"PPL",
    "gn:name":"El Saucito",
    "gn:population":0,
    "gn:timezone":"America/Mexico_City",
    "iso:country":"MX",
    "name:spa_x_preferred":[
        "El Saucito"
    ],
    "name:und_x_variant":[
        "Saucito"
    ],
    "wof:name":"El Saucito",
    "wof:placetype":"locality"
},
  "geometry": {"coordinates":[-100.08391,21.81326],"type":"Point"}
}