{
  "type": "Feature",
  "properties": {
    "gn:admin1_code":"30",
    "gn:admin2_code":"126.0",
    "gn:asciiname":"Yucatan",
    "gn:country_code":"MX",
    "gn:dem":16,
    "gn:feature_class":"P",
    "gn:feature_code":"PPL",
    "gn:name":"Yucat\u00e1n",
    "gn:population":543,
    "gn:timezone":"America/Mexico_City",
    "iso:country":"MX",
    "name:und_x_variant":[
        "Yucat\u00e1n"
    ],
    "wof:name":"Yucatan",
    "wof:placetype":"locality",
    "wof:population":543
},
  "geometry": {"coordinates":[-96.36167,19.34472],"type":"Point"}
}