{
  "type": "Feature",
  "properties": {
    "gn:admin1_code":"11",
    "gn:admin2_code":"20",
    "gn:asciiname":"Granja el Carmen",
    "gn:country_code":"MX",
    "gn:dem":1787,
    "gn:feature_class":"P",
    "gn:feature_code":"PPL",
    "gn:name":"Granja el Carmen",
    "gn:population":15,
    "gn:timezone":"America/Mexico_City",
    "iso:country":"MX",
    "wof:name":"Granja el Carmen",
    "wof:placetype":"locality",
    "wof:population":15
},
  "geometry": {"coordinates":[-101.66500000000001,21.02028],"type":"Point"}
}