{
  "type": "Feature",
  "properties": {
    "gn:admin1_code":"30",
    "gn:admin2_code":"181.0",
    "gn:asciiname":"El Cristo",
    "gn:country_code":"MX",
    "gn:dem":18,
    "gn:feature_class":"P",
    "gn:feature_code":"PPL",
    "gn:name":"El Cristo",
    "gn:population":7,
    "gn:timezone":"America/Mexico_City",
    "iso:country":"MX",
    "name:ceb_x_preferred":[
        "El Cristo"
    ],
    "name:glg_x_preferred":[
        "O Cristo"
    ],
    "name:spa_x_preferred":[
        "El Cristo"
    ],
    "name:swe_x_preferred":[
        "El Cristo"
    ],
    "wof:name":"El Cristo",
    "wof:placetype":"locality",
    "wof:population":7
},
  "geometry": {"coordinates":[-96.13611,18.80139],"type":"Point"}
}