{
  "type": "Feature",
  "properties": {
    "gn:admin1_code":"5.0",
    "gn:asciiname":"Esquipulas",
    "gn:country_code":"MX",
    "gn:dem":1327,
    "gn:feature_class":"P",
    "gn:feature_code":"PPL",
    "gn:name":"Esquipulas",
    "gn:population":0,
    "gn:timezone":"America/Mexico_City",
    "iso:country":"MX",
    "name:spa_x_preferred":[
        "Esquipulas"
    ],
    "wof:name":"Esquipulas",
    "wof:placetype":"locality"
},
  "geometry": {"coordinates":[-92.91707,15.76705],"type":"Point"}
}