{
  "type": "Feature",
  "properties": {
    "gn:admin1_code":"28",
    "gn:admin2_code":"32",
    "gn:asciiname":"Las Palmas",
    "gn:country_code":"MX",
    "gn:dem":153,
    "gn:feature_class":"P",
    "gn:feature_code":"PPL",
    "gn:name":"Las Palmas",
    "gn:population":12,
    "gn:timezone":"America/Matamoros",
    "iso:country":"MX",
    "wof:name":"Las Palmas",
    "wof:placetype":"locality",
    "wof:population":12
},
  "geometry": {"coordinates":[-98.46944000000001,25.78472],"type":"Point"}
}