{
  "type": "Feature",
  "properties": {
    "gn:admin1_code":"5.0",
    "gn:admin2_code":"92.0",
    "gn:asciiname":"Progreso Azapac",
    "gn:country_code":"MX",
    "gn:dem":190,
    "gn:feature_class":"P",
    "gn:feature_code":"PPL",
    "gn:name":"Progreso Azapac",
    "gn:population":0,
    "gn:timezone":"America/Mexico_City",
    "iso:country":"MX",
    "name:spa_x_preferred":[
        "Progreso Azapac"
    ],
    "wof:name":"Progreso Azapac",
    "wof:placetype":"locality"
},
  "geometry": {"coordinates":[-93.42927,17.25481],"type":"Point"}
}