{
  "type": "Feature",
  "properties": {
    "gn:admin1_code":"15",
    "gn:admin2_code":"106.0",
    "gn:asciiname":"Barrio Bordo Nuevo",
    "gn:country_code":"MX",
    "gn:dem":2606,
    "gn:feature_class":"P",
    "gn:feature_code":"PPL",
    "gn:name":"Barrio Bordo Nuevo",
    "gn:population":1718,
    "gn:timezone":"America/Mexico_City",
    "iso:country":"MX",
    "wof:name":"Barrio Bordo Nuevo",
    "wof:placetype":"locality",
    "wof:population":1718
},
  "geometry": {"coordinates":[-99.67333000000001,19.37917],"type":"Point"}
}