{
  "type": "Feature",
  "properties": {
    "gn:admin1_code":"14",
    "gn:admin2_code":"65",
    "gn:asciiname":"El Anil",
    "gn:country_code":"MX",
    "gn:dem":889,
    "gn:feature_class":"P",
    "gn:feature_code":"PPL",
    "gn:name":"El A\u00f1il",
    "gn:population":11,
    "gn:timezone":"America/Mexico_City",
    "iso:country":"MX",
    "name:und_x_variant":[
        "El A\u00f1il"
    ],
    "wof:name":"El Anil",
    "wof:placetype":"locality",
    "wof:population":11
},
  "geometry": {"coordinates":[-103.33389,19.29583],"type":"Point"}
}