{
  "type": "Feature",
  "properties": {
    "gn:admin1_code":"5",
    "gn:admin2_code":"107.0",
    "gn:asciiname":"Ocotlan",
    "gn:country_code":"MX",
    "gn:dem":625,
    "gn:feature_class":"P",
    "gn:feature_code":"PPL",
    "gn:name":"Ocotl\u00e1n",
    "gn:population":6,
    "gn:timezone":"America/Mexico_City",
    "iso:country":"MX",
    "name:und_x_variant":[
        "Ocotl\u00e1n"
    ],
    "wof:name":"Ocotlan",
    "wof:placetype":"locality",
    "wof:population":6
},
  "geometry": {"coordinates":[-93.32444,16.15556],"type":"Point"}
}