{
  "type": "Feature",
  "properties": {
    "gn:admin1_code":"7.0",
    "gn:asciiname":"Rodriguez",
    "gn:country_code":"MX",
    "gn:dem":1214,
    "gn:feature_class":"P",
    "gn:feature_code":"PPL",
    "gn:name":"Rodr\u00edguez",
    "gn:population":0,
    "gn:timezone":"America/Monterrey",
    "iso:country":"MX",
    "name:bel_x_preferred":[
        "\u0420\u0430\u0434\u0440\u044b\u0433\u0435\u0441"
    ],
    "name:ceb_x_preferred":[
        "Rodriguez"
    ],
    "name:deu_x_preferred":[
        "Rodriguez"
    ],
    "name:fin_x_preferred":[
        "Rodriguez"
    ],
    "name:heb_x_preferred":[
        "\u05e8\u05d5\u05d3\u05e8\u05d9\u05d2\u05d6"
    ],
    "name:jpn_x_preferred":[
        "\u30ed\u30c9\u30ea\u30b2\u30b9"
    ],
    "name:kor_x_preferred":[
        "\ub85c\ub4dc\ub9ac\uac8c\uc2a4"
    ],
    "name:nld_x_preferred":[
        "Rodriguez"
    ],
    "name:pol_x_preferred":[
        "Rodriguez"
    ],
    "name:rus_x_preferred":[
        "\u0420\u043e\u0434\u0440\u0438\u0433\u0435\u0441"
    ],
    "name:spa_x_preferred":[
        "Rodr\u00edguez"
    ],
    "name:swe_x_preferred":[
        "Rodriguez"
    ],
    "name:ukr_x_preferred":[
        "\u0420\u043e\u0434\u0440\u0456\u0433\u0435\u0441"
    ],
    "name:vie_x_preferred":[
        "Rodriguez"
    ],
    "name:zho_x_preferred":[
        "\u7f57\u5fb7\u91cc\u683c\u65af"
    ],
    "wof:name":"Rodriguez",
    "wof:placetype":"locality"
},
  "geometry": {"coordinates":[-102.48162000000001,27.85262],"type":"Point"}
}