{
  "type": "Feature",
  "properties": {
    "gn:admin1_code":"7.0",
    "gn:asciiname":"Rodriguez",
    "gn:country_code":"MX",
    "gn:dem":1214,
    "gn:feature_class":"P",
    "gn:feature_code":"PPL",
    "gn:name":"Rodr\u00edguez",
    "gn:population":0,
    "gn:timezone":"America/Monterrey",
    "iso:country":"MX",
    "name:spa_x_preferred":[
        "Rodr\u00edguez"
    ],
    "wof:name":"Rodriguez",
    "wof:placetype":"locality"
},
  "geometry": {"coordinates":[-102.48162000000001,27.85262],"type":"Point"}
}