{
  "type": "Feature",
  "properties": {
    "gn:admin1_code":"15.0",
    "gn:asciiname":"Las Cabezas",
    "gn:country_code":"MX",
    "gn:dem":2372,
    "gn:feature_class":"P",
    "gn:feature_code":"PPL",
    "gn:name":"Las Cabezas",
    "gn:population":0,
    "gn:timezone":"America/Mexico_City",
    "iso:country":"MX",
    "name:spa_x_preferred":[
        "Las Cabezas"
    ],
    "wof:name":"Las Cabezas",
    "wof:placetype":"locality"
},
  "geometry": {"coordinates":[-100.22920999999999,20.10741],"type":"Point"}
}