{
  "type": "Feature",
  "properties": {
    "gn:admin1_code":"16",
    "gn:admin2_code":"99",
    "gn:asciiname":"Puerto del Pilon",
    "gn:country_code":"MX",
    "gn:dem":849,
    "gn:feature_class":"P",
    "gn:feature_code":"PPL",
    "gn:name":"Puerto del Pil\u00f3n",
    "gn:population":15,
    "gn:timezone":"America/Mexico_City",
    "iso:country":"MX",
    "name:und_x_variant":[
        "Puerto del Pil\u00f3n"
    ],
    "wof:name":"Puerto del Pilon",
    "wof:placetype":"locality",
    "wof:population":15
},
  "geometry": {"coordinates":[-100.49278,19.12028],"type":"Point"}
}