{
  "type": "Feature",
  "properties": {
    "gn:admin1_code":"19.0",
    "gn:admin2_code":"17.0",
    "gn:asciiname":"Catarino Rodriguez",
    "gn:country_code":"MX",
    "gn:dem":1891,
    "gn:feature_class":"P",
    "gn:feature_code":"PPL",
    "gn:name":"Catarino Rodriguez",
    "gn:population":0,
    "gn:timezone":"America/Monterrey",
    "iso:country":"MX",
    "name:spa_x_preferred":[
        "Catarino Rodr\u00edguez"
    ],
    "name:und_x_variant":[
        "Potosi",
        "El Potos\u00ed",
        "Catarino Rodriguez"
    ],
    "wof:name":"Catarino Rodriguez",
    "wof:placetype":"locality"
},
  "geometry": {"coordinates":[-100.32080000000001,24.84526],"type":"Point"}
}