{
  "type": "Feature",
  "properties": {
    "gn:admin1_code":"28",
    "gn:admin2_code":"31.0",
    "gn:asciiname":"El Llano de Azuas",
    "gn:country_code":"MX",
    "gn:dem":1595,
    "gn:feature_class":"P",
    "gn:feature_code":"PPL",
    "gn:name":"El Llano de Azuas",
    "gn:population":208,
    "gn:timezone":"America/Monterrey",
    "iso:country":"MX",
    "name:spa_x_preferred":[
        "El Llano de Azuas"
    ],
    "wof:name":"El Llano de Azuas",
    "wof:placetype":"locality",
    "wof:population":208
},
  "geometry": {"coordinates":[-99.55971,23.16869],"type":"Point"}
}