{
  "type": "Feature",
  "properties": {
    "gn:admin1_code":"26",
    "gn:admin2_code":"12.0",
    "gn:asciiname":"Rancho el Alamo",
    "gn:country_code":"MX",
    "gn:dem":22,
    "gn:feature_class":"P",
    "gn:feature_code":"PPL",
    "gn:name":"Rancho el \u00c1lamo",
    "gn:population":7,
    "gn:timezone":"America/Hermosillo",
    "iso:country":"MX",
    "name:und_x_variant":[
        "Rancho el \u00c1lamo"
    ],
    "wof:name":"Rancho el Alamo",
    "wof:placetype":"locality",
    "wof:population":7
},
  "geometry": {"coordinates":[-110.10972,27.60361],"type":"Point"}
}