{
  "type": "Feature",
  "properties": {
    "gn:admin1_code":"21",
    "gn:admin2_code":"179.0",
    "gn:asciiname":"Colonia Agricola Bella Vista (San Vicente)",
    "gn:country_code":"MX",
    "gn:dem":2463,
    "gn:feature_class":"P",
    "gn:feature_code":"PPL",
    "gn:name":"Colonia Agr\u00edcola Bella Vista (San Vicente)",
    "gn:population":116,
    "gn:timezone":"America/Mexico_City",
    "iso:country":"MX",
    "name:und_x_variant":[
        "Colonia Agr\u00edcola Bella Vista (San Vicente)"
    ],
    "wof:name":"Colonia Agricola Bella Vista (San Vicente)",
    "wof:placetype":"locality",
    "wof:population":116
},
  "geometry": {"coordinates":[-97.41943999999999,19.24972],"type":"Point"}
}