{
  "type": "Feature",
  "properties": {
    "gn:admin1_code":"20.0",
    "gn:admin2_code":"12.0",
    "gn:asciiname":"Portillo Zacatal",
    "gn:country_code":"MX",
    "gn:dem":554,
    "gn:feature_class":"P",
    "gn:feature_code":"PPL",
    "gn:name":"Portillo Zacatal",
    "gn:population":0,
    "gn:timezone":"America/Mexico_City",
    "iso:country":"MX",
    "name:spa_x_preferred":[
        "Portillo Zacatal"
    ],
    "wof:name":"Portillo Zacatal",
    "wof:placetype":"locality"
},
  "geometry": {"coordinates":[-96.51147,15.91758],"type":"Point"}
}