{
  "type": "Feature",
  "properties": {
    "gn:admin1_code":"6.0",
    "gn:admin2_code":"15.0",
    "gn:asciiname":"Las Paredes",
    "gn:country_code":"MX",
    "gn:dem":1171,
    "gn:feature_class":"P",
    "gn:feature_code":"PPL",
    "gn:name":"Las Paredes",
    "gn:population":0,
    "gn:timezone":"America/Ojinaga",
    "iso:country":"MX",
    "name:spa_x_preferred":[
        "Las Paredes"
    ],
    "wof:name":"Las Paredes",
    "wof:placetype":"locality"
},
  "geometry": {"coordinates":[-104.88625,29.73104],"type":"Point"}
}