{
  "type": "Feature",
  "properties": {
    "gn:admin1_code":"14",
    "gn:admin2_code":"53",
    "gn:asciiname":"El Girasol",
    "gn:country_code":"MX",
    "gn:dem":1905,
    "gn:feature_class":"P",
    "gn:feature_code":"PPL",
    "gn:name":"El Girasol",
    "gn:population":22,
    "gn:timezone":"America/Mexico_City",
    "iso:country":"MX",
    "wof:name":"El Girasol",
    "wof:placetype":"locality",
    "wof:population":22
},
  "geometry": {"coordinates":[-101.83167,21.48194],"type":"Point"}
}