{
  "type": "Feature",
  "properties": {
    "gn:admin1_code":"30",
    "gn:admin2_code":"15.0",
    "gn:asciiname":"Marruan (Mario Dominguez)",
    "gn:country_code":"MX",
    "gn:dem":29,
    "gn:feature_class":"P",
    "gn:feature_code":"PPL",
    "gn:name":"Marruan (Mario Dom\u00ednguez)",
    "gn:population":5,
    "gn:timezone":"America/Mexico_City",
    "iso:country":"MX",
    "name:und_x_variant":[
        "Marruan (Mario Dom\u00ednguez)"
    ],
    "wof:name":"Marruan (Mario Dominguez)",
    "wof:placetype":"locality",
    "wof:population":5
},
  "geometry": {"coordinates":[-95.40889,18.65139],"type":"Point"}
}