{
  "type": "Feature",
  "properties": {
    "gn:admin1_code":"6.0",
    "gn:admin2_code":"14.0",
    "gn:asciiname":"Guadalupe de Bahues",
    "gn:country_code":"MX",
    "gn:dem":1556,
    "gn:feature_class":"P",
    "gn:feature_code":"PPL",
    "gn:name":"Guadalupe de Bahues",
    "gn:population":0,
    "gn:timezone":"America/Chihuahua",
    "iso:country":"MX",
    "name:und_x_variant":[
        "Guadalupe",
        "Guadalupe de Bag\u00fces"
    ],
    "wof:name":"Guadalupe de Bahues",
    "wof:placetype":"locality"
},
  "geometry": {"coordinates":[-105.17837,26.61731],"type":"Point"}
}