{
  "type": "Feature",
  "properties": {
    "gn:admin1_code":"10",
    "gn:admin2_code":"14.0",
    "gn:asciiname":"Mesa de Mirasoles",
    "gn:country_code":"MX",
    "gn:dem":2036,
    "gn:feature_class":"P",
    "gn:feature_code":"PPL",
    "gn:name":"Mesa de Mirasoles",
    "gn:population":0,
    "gn:timezone":"America/Monterrey",
    "iso:country":"MX",
    "name:spa_x_preferred":[
        "Mesa de Mirasoles"
    ],
    "wof:name":"Mesa de Mirasoles",
    "wof:placetype":"locality"
},
  "geometry": {"coordinates":[-104.40506999999999,22.67763],"type":"Point"}
}