{
  "type": "Feature",
  "properties": {
    "gn:admin1_code":"5",
    "gn:admin2_code":"77",
    "gn:asciiname":"La Palestina",
    "gn:country_code":"MX",
    "gn:dem":71,
    "gn:feature_class":"P",
    "gn:feature_code":"PPL",
    "gn:name":"La Palestina",
    "gn:population":21,
    "gn:timezone":"America/Mexico_City",
    "iso:country":"MX",
    "wof:name":"La Palestina",
    "wof:placetype":"locality",
    "wof:population":21
},
  "geometry": {"coordinates":[-92.12166999999999,17.33056],"type":"Point"}
}