{
  "type": "Feature",
  "properties": {
    "gn:admin1_code":"5",
    "gn:admin2_code":"79.0",
    "gn:asciiname":"Albania",
    "gn:country_code":"MX",
    "gn:dem":496,
    "gn:feature_class":"P",
    "gn:feature_code":"PPL",
    "gn:name":"Albania",
    "gn:population":6,
    "gn:timezone":"America/Mexico_City",
    "iso:country":"MX",
    "wof:name":"Albania",
    "wof:placetype":"locality",
    "wof:population":6
},
  "geometry": {"coordinates":[-93.29583,16.91194],"type":"Point"}
}