{
  "type": "Feature",
  "properties": {
    "gn:admin1_code":"30",
    "gn:admin2_code":"54.0",
    "gn:asciiname":"Las Mesas",
    "gn:country_code":"MX",
    "gn:dem":15,
    "gn:feature_class":"P",
    "gn:feature_code":"PPL",
    "gn:name":"Las Mesas",
    "gn:population":568,
    "gn:timezone":"America/Mexico_City",
    "iso:country":"MX",
    "wof:name":"Las Mesas",
    "wof:placetype":"locality",
    "wof:population":568
},
  "geometry": {"coordinates":[-95.72194,18.19667],"type":"Point"}
}