{
  "type": "Feature",
  "properties": {
    "gn:admin1_code":"25.0",
    "gn:admin2_code":"6.0",
    "gn:asciiname":"El Realito",
    "gn:country_code":"MX",
    "gn:dem":181,
    "gn:feature_class":"P",
    "gn:feature_code":"PPL",
    "gn:name":"El Realito",
    "gn:population":0,
    "gn:timezone":"America/Mazatlan",
    "iso:country":"MX",
    "name:spa_x_preferred":[
        "El Realito"
    ],
    "wof:name":"El Realito",
    "wof:placetype":"locality"
},
  "geometry": {"coordinates":[-107.0342,24.51462],"type":"Point"}
}