{
  "type": "Feature",
  "properties": {
    "gn:admin1_code":"4.0",
    "gn:asciiname":"Nuevo Marente",
    "gn:country_code":"MX",
    "gn:dem":65,
    "gn:feature_class":"P",
    "gn:feature_code":"PPL",
    "gn:name":"Nuevo Marente",
    "gn:population":0,
    "gn:timezone":"America/Mexico_City",
    "iso:country":"MX",
    "name:spa_x_preferred":[
        "Nuevo Marente"
    ],
    "wof:name":"Nuevo Marente",
    "wof:placetype":"locality"
},
  "geometry": {"coordinates":[-91.05692999999999,17.96346],"type":"Point"}
}