{
  "type": "Feature",
  "properties": {
    "gn:admin1_code":"28",
    "gn:admin2_code":"2.0",
    "gn:asciiname":"El Higuazu (El Becerro)",
    "gn:country_code":"MX",
    "gn:dem":67,
    "gn:feature_class":"P",
    "gn:feature_code":"PPL",
    "gn:name":"El Higuaz\u00fa (El Becerro)",
    "gn:population":7,
    "gn:timezone":"America/Monterrey",
    "iso:country":"MX",
    "name:und_x_variant":[
        "El Higuaz\u00fa (El Becerro)"
    ],
    "wof:name":"El Higuazu (El Becerro)",
    "wof:placetype":"locality",
    "wof:population":7
},
  "geometry": {"coordinates":[-97.87694999999999,22.99028],"type":"Point"}
}