{
  "type": "Feature",
  "properties": {
    "gn:admin1_code":"13",
    "gn:admin2_code":"76.0",
    "gn:asciiname":"El Paraje",
    "gn:country_code":"MX",
    "gn:dem":2120,
    "gn:feature_class":"P",
    "gn:feature_code":"PPL",
    "gn:name":"El Paraje",
    "gn:population":0,
    "gn:timezone":"America/Mexico_City",
    "iso:country":"MX",
    "name:spa_x_preferred":[
        "El Paraje"
    ],
    "wof:name":"El Paraje",
    "wof:placetype":"locality"
},
  "geometry": {"coordinates":[-99.40765,20.09909],"type":"Point"}
}