{
  "type": "Feature",
  "properties": {
    "gn:admin1_code":"28",
    "gn:admin2_code":"29.0",
    "gn:asciiname":"Nicolas Bravo",
    "gn:country_code":"MX",
    "gn:dem":418,
    "gn:feature_class":"P",
    "gn:feature_code":"PPL",
    "gn:name":"Nicolas Bravo",
    "gn:population":0,
    "gn:timezone":"America/Monterrey",
    "iso:country":"MX",
    "name:spa_x_preferred":[
        "Nicolas Bravo"
    ],
    "name:und_x_variant":[
        "Nicol\u00e1s Bravo"
    ],
    "wof:name":"Nicolas Bravo",
    "wof:placetype":"locality"
},
  "geometry": {"coordinates":[-99.43997,22.89097000000001],"type":"Point"}
}