{
  "type": "Feature",
  "properties": {
    "gn:admin1_code":"11.0",
    "gn:admin2_code":"42.0",
    "gn:asciiname":"Cenegal",
    "gn:country_code":"MX",
    "gn:dem":1702,
    "gn:feature_class":"P",
    "gn:feature_code":"PPL",
    "gn:name":"Cenegal",
    "gn:population":0,
    "gn:timezone":"America/Mexico_City",
    "iso:country":"MX",
    "name:spa_x_preferred":[
        "Cenegal"
    ],
    "wof:name":"Cenegal",
    "wof:placetype":"locality"
},
  "geometry": {"coordinates":[-101.38769000000001,20.45803],"type":"Point"}
}