{
  "type": "Feature",
  "properties": {
    "gn:admin1_code":"28",
    "gn:asciiname":"Nogalito",
    "gn:country_code":"MX",
    "gn:dem":139,
    "gn:feature_class":"P",
    "gn:feature_code":"PPL",
    "gn:name":"Nogalito",
    "gn:population":0,
    "gn:timezone":"America/Monterrey",
    "iso:country":"MX",
    "name:spa_x_preferred":[
        "Nogalito"
    ],
    "wof:name":"Nogalito",
    "wof:placetype":"locality"
},
  "geometry": {"coordinates":[-99.02084000000001,25.10044],"type":"Point"}
}