{
  "type": "Feature",
  "properties": {
    "gn:admin1_code":"14.0",
    "gn:admin2_code":"12.0",
    "gn:asciiname":"El Crucero",
    "gn:country_code":"MX",
    "gn:dem":1349,
    "gn:feature_class":"P",
    "gn:feature_code":"PPL",
    "gn:name":"El Crucero",
    "gn:population":0,
    "gn:timezone":"America/Mexico_City",
    "iso:country":"MX",
    "name:spa_x_preferred":[
        "El Crucero"
    ],
    "wof:name":"El Crucero",
    "wof:placetype":"locality"
},
  "geometry": {"coordinates":[-104.49735,20.42784],"type":"Point"}
}