{
  "type": "Feature",
  "properties": {
    "gn:admin1_code":"4.0",
    "gn:admin2_code":"3.0",
    "gn:asciiname":"El Agucate",
    "gn:country_code":"MX",
    "gn:dem":33,
    "gn:feature_class":"P",
    "gn:feature_code":"PPL",
    "gn:name":"El Agucate",
    "gn:population":0,
    "gn:timezone":"America/Merida",
    "iso:country":"MX",
    "name:spa_x_preferred":[
        "El Agucate"
    ],
    "wof:name":"El Agucate",
    "wof:placetype":"locality"
},
  "geometry": {"coordinates":[-91.14933000000001,18.32893],"type":"Point"}
}