{
  "type": "Feature",
  "properties": {
    "gn:admin1_code":"18",
    "gn:admin2_code":"9.0",
    "gn:asciiname":"El Pinito Nuevo (La Muneca)",
    "gn:country_code":"MX",
    "gn:dem":1189,
    "gn:feature_class":"P",
    "gn:feature_code":"PPL",
    "gn:name":"El Pinito Nuevo (La Mu\u00f1eca)",
    "gn:population":122,
    "gn:timezone":"America/Mazatlan",
    "iso:country":"MX",
    "name:und_x_variant":[
        "El Pinito Nuevo (La Mu\u00f1eca)"
    ],
    "wof:name":"El Pinito Nuevo (La Muneca)",
    "wof:placetype":"locality",
    "wof:population":122
},
  "geometry": {"coordinates":[-104.59472,22.14472],"type":"Point"}
}