{
  "type": "Feature",
  "properties": {
    "gn:admin1_code":"14.0",
    "gn:admin2_code":"65.0",
    "gn:asciiname":"El Nogal",
    "gn:country_code":"MX",
    "gn:dem":1160,
    "gn:feature_class":"P",
    "gn:feature_code":"PPL",
    "gn:name":"El Nogal",
    "gn:population":0,
    "gn:timezone":"America/Mexico_City",
    "iso:country":"MX",
    "name:spa_x_preferred":[
        "El Nogal"
    ],
    "wof:name":"El Nogal",
    "wof:placetype":"locality"
},
  "geometry": {"coordinates":[-103.31652,19.24257],"type":"Point"}
}