{
  "type": "Feature",
  "properties": {
    "gn:admin1_code":"32.0",
    "gn:admin2_code":"32.0",
    "gn:asciiname":"El Alamito",
    "gn:country_code":"MX",
    "gn:dem":2273,
    "gn:feature_class":"P",
    "gn:feature_code":"PPL",
    "gn:name":"El Alamito",
    "gn:population":0,
    "gn:timezone":"America/Mexico_City",
    "iso:country":"MX",
    "name:spa_x_preferred":[
        "El Alamito"
    ],
    "wof:name":"El Alamito",
    "wof:placetype":"locality"
},
  "geometry": {"coordinates":[-102.62166999999999,22.87646],"type":"Point"}
}