{
  "type": "Feature",
  "properties": {
    "gn:admin1_code":"12",
    "gn:admin2_code":"37",
    "gn:asciiname":"Barrio de los Tejas (Las Maravillas)",
    "gn:country_code":"MX",
    "gn:dem":1466,
    "gn:feature_class":"P",
    "gn:feature_code":"PPL",
    "gn:name":"Barrio de los Tejas (Las Maravillas)",
    "gn:population":18,
    "gn:timezone":"America/Mexico_City",
    "iso:country":"MX",
    "wof:name":"Barrio de los Tejas (Las Maravillas)",
    "wof:placetype":"locality",
    "wof:population":18
},
  "geometry": {"coordinates":[-99.8331,18.45853],"type":"Point"}
}