{
  "type": "Feature",
  "properties": {
    "gn:admin1_code":"10",
    "gn:admin2_code":"36.0",
    "gn:asciiname":"El Betel",
    "gn:country_code":"MX",
    "gn:dem":1102,
    "gn:feature_class":"P",
    "gn:feature_code":"PPL",
    "gn:name":"El Betel",
    "gn:population":0,
    "gn:timezone":"America/Monterrey",
    "iso:country":"MX",
    "name:spa_x_preferred":[
        "El Betel"
    ],
    "wof:name":"El Betel",
    "wof:placetype":"locality"
},
  "geometry": {"coordinates":[-103.56747,25.89203],"type":"Point"}
}