{
  "type": "Feature",
  "properties": {
    "gn:admin1_code":"3",
    "gn:admin2_code":"8.0",
    "gn:asciiname":"El Zorrillo",
    "gn:country_code":"MX",
    "gn:dem":490,
    "gn:feature_class":"P",
    "gn:feature_code":"PPL",
    "gn:name":"El Zorrillo",
    "gn:population":0,
    "gn:timezone":"America/Mazatlan",
    "iso:country":"MX",
    "name:spa_x_preferred":[
        "El Zorrillo"
    ],
    "wof:name":"El Zorrillo",
    "wof:placetype":"locality"
},
  "geometry": {"coordinates":[-109.95081999999999,23.04963],"type":"Point"}
}