{
  "type": "Feature",
  "properties": {
    "gn:admin1_code":"7.0",
    "gn:admin2_code":"14.0",
    "gn:asciiname":"El Tepeyac",
    "gn:country_code":"MX",
    "gn:dem":285,
    "gn:feature_class":"P",
    "gn:feature_code":"PPL",
    "gn:name":"El Tepeyac",
    "gn:population":0,
    "gn:timezone":"America/Monterrey",
    "iso:country":"MX",
    "wof:name":"El Tepeyac",
    "wof:placetype":"locality"
},
  "geometry": {"coordinates":[-100.71971000000001,28.98608],"type":"Point"}
}