{
  "type": "Feature",
  "properties": {
    "gn:admin1_code":"5.0",
    "gn:asciiname":"San Pedro Jomalchen",
    "gn:country_code":"MX",
    "gn:dem":1606,
    "gn:feature_class":"P",
    "gn:feature_code":"PPL",
    "gn:name":"San Pedro Jomalchen",
    "gn:population":0,
    "gn:timezone":"America/Mexico_City",
    "iso:country":"MX",
    "name:spa_x_preferred":[
        "San Pedro Jomalchen"
    ],
    "wof:name":"San Pedro Jomalchen",
    "wof:placetype":"locality"
},
  "geometry": {"coordinates":[-92.17,16.9022],"type":"Point"}
}