{
  "type": "Feature",
  "properties": {
    "gn:admin1_code":"23",
    "gn:admin2_code":"4.0",
    "gn:asciiname":"Serviliano Cohuo Medina",
    "gn:country_code":"MX",
    "gn:dem":11,
    "gn:feature_class":"P",
    "gn:feature_code":"PPL",
    "gn:name":"Serviliano Cohu\u00f3 Medina",
    "gn:population":5,
    "gn:timezone":"America/Cancun",
    "iso:country":"MX",
    "name:und_x_variant":[
        "Serviliano Cohu\u00f3 Medina"
    ],
    "wof:name":"Serviliano Cohuo Medina",
    "wof:placetype":"locality",
    "wof:population":5
},
  "geometry": {"coordinates":[-88.22944,19.00139],"type":"Point"}
}