{
  "type": "Feature",
  "properties": {
    "gn:admin1_code":"24",
    "gn:admin2_code":"21.0",
    "gn:asciiname":"El Cerrito",
    "gn:country_code":"MX",
    "gn:dem":2164,
    "gn:feature_class":"P",
    "gn:feature_code":"PPL",
    "gn:name":"El Cerrito",
    "gn:population":145,
    "gn:timezone":"America/Mexico_City",
    "iso:country":"MX",
    "wof:name":"El Cerrito",
    "wof:placetype":"locality",
    "wof:population":145
},
  "geometry": {"coordinates":[-101.21639,22.25611],"type":"Point"}
}