{
  "type": "Feature",
  "properties": {
    "gn:admin1_code":"6",
    "gn:admin2_code":"30.0",
    "gn:asciiname":"Rancho de Potrero",
    "gn:country_code":"MX",
    "gn:dem":1161,
    "gn:feature_class":"P",
    "gn:feature_code":"PPL",
    "gn:name":"Rancho de Potrero",
    "gn:population":0,
    "gn:timezone":"America/Chihuahua",
    "iso:country":"MX",
    "name:spa_x_preferred":[
        "Rancho de Potrero"
    ],
    "wof:name":"Rancho de Potrero",
    "wof:placetype":"locality"
},
  "geometry": {"coordinates":[-108.29627000000001,27.11173],"type":"Point"}
}