{
  "type": "Feature",
  "properties": {
    "gn:admin1_code":"30",
    "gn:admin2_code":"50.0",
    "gn:asciiname":"Jose Maria Morelos",
    "gn:country_code":"MX",
    "gn:dem":120,
    "gn:feature_class":"P",
    "gn:feature_code":"PPL",
    "gn:name":"Jos\u00e9 Mar\u00eda Morelos",
    "gn:population":0,
    "gn:timezone":"America/Mexico_City",
    "iso:country":"MX",
    "name:spa_x_preferred":[
        "Jos\u00e9 Mar\u00eda Morelos"
    ],
    "wof:name":"Jose Maria Morelos",
    "wof:placetype":"locality"
},
  "geometry": {"coordinates":[-97.54427,20.21526],"type":"Point"}
}