{
  "type": "Feature",
  "properties": {
    "gn:admin1_code":"28.0",
    "gn:admin2_code":"34.0",
    "gn:asciiname":"Las Chabelas",
    "gn:country_code":"MX",
    "gn:dem":182,
    "gn:feature_class":"P",
    "gn:feature_code":"PPL",
    "gn:name":"Las Chabelas",
    "gn:population":0,
    "gn:timezone":"America/Monterrey",
    "iso:country":"MX",
    "name:spa_x_preferred":[
        "Las Chabelas"
    ],
    "wof:name":"Las Chabelas",
    "wof:placetype":"locality"
},
  "geometry": {"coordinates":[-98.83344,24.19317],"type":"Point"}
}