{
  "type": "Feature",
  "properties": {
    "gn:admin1_code":"26",
    "gn:admin2_code":"30.0",
    "gn:asciiname":"Santa Julia",
    "gn:country_code":"MX",
    "gn:dem":126,
    "gn:feature_class":"P",
    "gn:feature_code":"PPL",
    "gn:name":"Santa Julia",
    "gn:population":0,
    "gn:timezone":"America/Hermosillo",
    "iso:country":"MX",
    "name:und_x_variant":[
        "Rancho Santa Julia"
    ],
    "wof:name":"Santa Julia",
    "wof:placetype":"locality"
},
  "geometry": {"coordinates":[-111.21344000000001,28.94074],"type":"Point"}
}