{
  "type": "Feature",
  "properties": {
    "gn:admin1_code":"28.0",
    "gn:admin2_code":"24.0",
    "gn:asciiname":"Don Tomas",
    "gn:country_code":"MX",
    "gn:dem":88,
    "gn:feature_class":"P",
    "gn:feature_code":"PPL",
    "gn:name":"Don Tom\u00e1s",
    "gn:population":0,
    "gn:timezone":"America/Monterrey",
    "iso:country":"MX",
    "name:ceb_x_preferred":[
        "Don Tomas"
    ],
    "name:spa_x_preferred":[
        "Don Tom\u00e1s"
    ],
    "name:srp_x_preferred":[
        "\u0414\u043e\u043d \u0422\u043e\u043c\u0430\u0441"
    ],
    "name:swe_x_preferred":[
        "Don Tomas"
    ],
    "wof:name":"Don Tomas",
    "wof:placetype":"locality"
},
  "geometry": {"coordinates":[-99.18549,26.32327],"type":"Point"}
}