{
  "type": "Feature",
  "properties": {
    "gn:admin1_code":"5.0",
    "gn:admin2_code":"65.0",
    "gn:asciiname":"Brasil",
    "gn:country_code":"MX",
    "gn:dem":35,
    "gn:feature_class":"P",
    "gn:feature_code":"PPL",
    "gn:name":"Brasil",
    "gn:population":0,
    "gn:timezone":"America/Mexico_City",
    "iso:country":"MX",
    "name:spa_x_preferred":[
        "Brasil"
    ],
    "wof:name":"Brasil",
    "wof:placetype":"locality"
},
  "geometry": {"coordinates":[-92.15743000000001,17.57957],"type":"Point"}
}