{
  "type": "Feature",
  "properties": {
    "gn:admin1_code":"28.0",
    "gn:admin2_code":"29.0",
    "gn:asciiname":"El Bejuco",
    "gn:country_code":"MX",
    "gn:dem":875,
    "gn:feature_class":"P",
    "gn:feature_code":"PPL",
    "gn:name":"El Bejuco",
    "gn:population":0,
    "gn:timezone":"America/Monterrey",
    "iso:country":"MX",
    "name:spa_x_preferred":[
        "El Bejuco"
    ],
    "wof:name":"El Bejuco",
    "wof:placetype":"locality"
},
  "geometry": {"coordinates":[-99.51322,22.92419],"type":"Point"}
}