{
  "type": "Feature",
  "properties": {
    "gn:admin1_code":"14",
    "gn:admin2_code":"53",
    "gn:asciiname":"Puerta del Llano",
    "gn:country_code":"MX",
    "gn:dem":1955,
    "gn:feature_class":"P",
    "gn:feature_code":"PPL",
    "gn:name":"Puerta del Llano",
    "gn:population":28,
    "gn:timezone":"America/Mexico_City",
    "iso:country":"MX",
    "wof:name":"Puerta del Llano",
    "wof:placetype":"locality",
    "wof:population":28
},
  "geometry": {"coordinates":[-102.11694,21.30139],"type":"Point"}
}