{
  "type": "Feature",
  "properties": {
    "gn:admin1_code":"32",
    "gn:admin2_code":"11.0",
    "gn:asciiname":"El Barranco",
    "gn:country_code":"MX",
    "gn:dem":1585,
    "gn:feature_class":"P",
    "gn:feature_code":"PPL",
    "gn:name":"El Barranco",
    "gn:population":0,
    "gn:timezone":"America/Mexico_City",
    "iso:country":"MX",
    "wof:name":"El Barranco",
    "wof:placetype":"locality"
},
  "geometry": {"coordinates":[-103.52135,21.25868],"type":"Point"}
}