{
  "type": "Feature",
  "properties": {
    "gn:admin1_code":"6",
    "gn:admin2_code":"12.0",
    "gn:asciiname":"Rancheria Guahuacherare",
    "gn:country_code":"MX",
    "gn:dem":2107,
    "gn:feature_class":"P",
    "gn:feature_code":"PPL",
    "gn:name":"Rancher\u00eda Guahuach\u00e9rare",
    "gn:population":0,
    "gn:timezone":"America/Chihuahua",
    "iso:country":"MX",
    "name:und_x_variant":[
        "Guaguacherare",
        "Rancher\u00eda Guahuach\u00e9rare",
        "Guahuach\u00e9rare"
    ],
    "wof:name":"Rancheria Guahuacherare",
    "wof:placetype":"locality"
},
  "geometry": {"coordinates":[-106.99487999999999,27.54067],"type":"Point"}
}