{
  "type": "Feature",
  "properties": {
    "gn:admin1_code":"28.0",
    "gn:admin2_code":"21.0",
    "gn:asciiname":"Tejeda",
    "gn:country_code":"MX",
    "gn:dem":75,
    "gn:feature_class":"P",
    "gn:feature_code":"PPL",
    "gn:name":"Tejeda",
    "gn:population":91,
    "gn:timezone":"America/Monterrey",
    "iso:country":"MX",
    "name:spa_x_preferred":[
        "Tejeda"
    ],
    "wof:name":"Tejeda",
    "wof:placetype":"locality",
    "wof:population":91
},
  "geometry": {"coordinates":[-99.03471999999999,22.81725],"type":"Point"}
}