{
  "type": "Feature",
  "properties": {
    "gn:country":"MX",
    "gn:fcode":"PPL",
    "gn:population":9832,
    "iso:country":"MX",
    "name:und_x_variant":[
        "San Francisco Tetlanohca"
    ],
    "qs_pg:aaroncc":"MX",
    "qs_pg:gn_country":"MX",
    "qs_pg:gn_fcode":"PPL",
    "qs_pg:gn_pop":9832,
    "qs_pg:name":"Tetlanohc\u00e1n",
    "qs_pg:photos_9r":0,
    "qs_pg:photos_sr":0,
    "qs_pg:pop_sr":5,
    "qs_pg:qs_pg_placetype":"locality",
    "wof:name":"Tetlanohc\u00e1n",
    "wof:placetype":"locality",
    "wof:population":9832
},
  "geometry": {"coordinates":[-98.16433000000001,19.2603],"type":"Point"}
}