{
  "type": "Feature",
  "properties": {
    "gn:admin1_code":"20",
    "gn:admin2_code":"397",
    "gn:asciiname":"El Capulin",
    "gn:country_code":"MX",
    "gn:dem":2419,
    "gn:feature_class":"P",
    "gn:feature_code":"PPL",
    "gn:name":"El Capul\u00edn",
    "gn:population":23,
    "gn:timezone":"America/Mexico_City",
    "iso:country":"MX",
    "name:und_x_variant":[
        "El Capul\u00edn"
    ],
    "wof:name":"El Capulin",
    "wof:placetype":"locality",
    "wof:population":23
},
  "geometry": {"coordinates":[-97.61861,17.20611],"type":"Point"}
}