{
  "type": "Feature",
  "properties": {
    "gn:admin1_code":"30",
    "gn:admin2_code":"61",
    "gn:asciiname":"Rosario Alvarez Alegria",
    "gn:country_code":"MX",
    "gn:dem":138,
    "gn:feature_class":"P",
    "gn:feature_code":"PPL",
    "gn:name":"Rosario \u00c1lvarez Alegr\u00eda",
    "gn:population":13,
    "gn:timezone":"America/Mexico_City",
    "iso:country":"MX",
    "name:und_x_variant":[
        "Rosario \u00c1lvarez Alegr\u00eda"
    ],
    "wof:name":"Rosario Alvarez Alegria",
    "wof:placetype":"locality",
    "wof:population":13
},
  "geometry": {"coordinates":[-93.71944000000001,17.49861],"type":"Point"}
}