{
  "type": "Feature",
  "properties": {
    "gn:admin1_code":"6",
    "gn:admin2_code":"27.0",
    "gn:asciiname":"El Pitorreal",
    "gn:country_code":"MX",
    "gn:dem":2446,
    "gn:feature_class":"P",
    "gn:feature_code":"PPL",
    "gn:name":"El Pitorreal",
    "gn:population":5,
    "gn:timezone":"America/Chihuahua",
    "iso:country":"MX",
    "wof:name":"El Pitorreal",
    "wof:placetype":"locality",
    "wof:population":5
},
  "geometry": {"coordinates":[-107.23877,26.68466],"type":"Point"}
}