{
  "type": "Feature",
  "properties": {
    "gn:admin1_code":"2.0",
    "gn:admin2_code":"3.0",
    "gn:asciiname":"Rancho Japa",
    "gn:country_code":"MX",
    "gn:dem":1259,
    "gn:feature_class":"P",
    "gn:feature_code":"PPL",
    "gn:name":"Rancho Japa",
    "gn:population":3,
    "gn:timezone":"America/Tijuana",
    "iso:country":"MX",
    "name:und_x_variant":[
        "Jap\u00e1"
    ],
    "wof:name":"Rancho Japa",
    "wof:placetype":"locality",
    "wof:population":3
},
  "geometry": {"coordinates":[-116.16006000000002,32.43465],"type":"Point"}
}