{
  "type": "Feature",
  "properties": {
    "gn:admin1_code":"6.0",
    "gn:asciiname":"Solis",
    "gn:country_code":"MX",
    "gn:dem":1553,
    "gn:feature_class":"P",
    "gn:feature_code":"PPL",
    "gn:name":"Sol\u00eds",
    "gn:population":0,
    "gn:timezone":"America/Chihuahua",
    "iso:country":"MX",
    "name:spa_x_preferred":[
        "Sol\u00eds"
    ],
    "wof:name":"Solis",
    "wof:placetype":"locality"
},
  "geometry": {"coordinates":[-106.22933,29.05605],"type":"Point"}
}