{
  "type": "Feature",
  "properties": {
    "gn:admin1_code":"5",
    "gn:admin2_code":"11.0",
    "gn:asciiname":"San Jose las Chicharras",
    "gn:country_code":"MX",
    "gn:dem":1510,
    "gn:feature_class":"P",
    "gn:feature_code":"PPL",
    "gn:name":"San Jos\u00e9 las Chicharras",
    "gn:population":0,
    "gn:timezone":"America/Mexico_City",
    "iso:country":"MX",
    "name:spa_x_preferred":[
        "San Jos\u00e9 las Chicharras"
    ],
    "name:und_x_variant":[
        "San Jos\u00e9 Chicharras"
    ],
    "wof:name":"San Jose las Chicharras",
    "wof:placetype":"locality"
},
  "geometry": {"coordinates":[-92.20659000000001,15.64363],"type":"Point"}
}