{
  "type": "Feature",
  "properties": {
    "gn:admin1_code":"3.0",
    "gn:admin2_code":"2.0",
    "gn:asciiname":"Las Palmas",
    "gn:country_code":"MX",
    "gn:dem":978,
    "gn:feature_class":"P",
    "gn:feature_code":"PPL",
    "gn:name":"Las Palmas",
    "gn:population":0,
    "gn:timezone":"America/Mazatlan",
    "iso:country":"MX",
    "name:spa_x_preferred":[
        "Las Palmas"
    ],
    "wof:name":"Las Palmas",
    "wof:placetype":"locality"
},
  "geometry": {"coordinates":[-112.48105,26.87171],"type":"Point"}
}