{
  "type": "Feature",
  "properties": {
    "gn:admin1_code":"14.0",
    "gn:asciiname":"El Zaguan",
    "gn:country_code":"MX",
    "gn:dem":1593,
    "gn:feature_class":"P",
    "gn:feature_code":"PPL",
    "gn:name":"El Zagu\u00e1n",
    "gn:population":0,
    "gn:timezone":"America/Mexico_City",
    "iso:country":"MX",
    "name:spa_x_preferred":[
        "El Zagu\u00e1n"
    ],
    "wof:name":"El Zaguan",
    "wof:placetype":"locality"
},
  "geometry": {"coordinates":[-103.76627000000001,22.25169],"type":"Point"}
}