{
  "type": "Feature",
  "properties": {
    "gn:admin1_code":"30",
    "gn:admin2_code":"86",
    "gn:asciiname":"El Cuetzalin",
    "gn:country_code":"MX",
    "gn:dem":1826,
    "gn:feature_class":"P",
    "gn:feature_code":"PPL",
    "gn:name":"El Cuetzal\u00edn",
    "gn:population":20,
    "gn:timezone":"America/Mexico_City",
    "iso:country":"MX",
    "name:und_x_variant":[
        "El Cuetzal\u00edn"
    ],
    "wof:name":"El Cuetzalin",
    "wof:placetype":"locality",
    "wof:population":20
},
  "geometry": {"coordinates":[-97.27889,19.83861],"type":"Point"}
}