{
  "type": "Feature",
  "properties": {
    "gn:admin1_code":"28",
    "gn:admin2_code":"17.0",
    "gn:asciiname":"Los Ebanos",
    "gn:country_code":"MX",
    "gn:dem":961,
    "gn:feature_class":"P",
    "gn:feature_code":"PPL",
    "gn:name":"Los Ebanos",
    "gn:population":0,
    "gn:timezone":"America/Monterrey",
    "iso:country":"MX",
    "name:spa_x_preferred":[
        "Los Ebanos"
    ],
    "name:und_x_variant":[
        "Los \u00c9banos"
    ],
    "wof:name":"Los Ebanos",
    "wof:placetype":"locality"
},
  "geometry": {"coordinates":[-99.45329,23.36715],"type":"Point"}
}