{
  "type": "Feature",
  "properties": {
    "gn:admin1_code":"6.0",
    "gn:admin2_code":"66.0",
    "gn:asciiname":"Guigorichic",
    "gn:cc2":"MX",
    "gn:country_code":"MX",
    "gn:dem":1320,
    "gn:feature_class":"P",
    "gn:feature_code":"PPL",
    "gn:name":"Guigorichic",
    "gn:population":0,
    "gn:timezone":"America/Chihuahua",
    "iso:country":"MX",
    "name:und_x_variant":[
        "Huicorichic",
        "Huicoriatio",
        "Guigorichic"
    ],
    "wof:name":"Guigorichic",
    "wof:placetype":"locality"
},
  "geometry": {"coordinates":[-108.65000000000001,27.73333],"type":"Point"}
}