{
  "type": "Feature",
  "properties": {
    "gn:admin1_code":"10",
    "gn:admin2_code":"26.0",
    "gn:asciiname":"Las Torres",
    "gn:country_code":"MX",
    "gn:dem":1149,
    "gn:feature_class":"P",
    "gn:feature_code":"PPL",
    "gn:name":"Las Torres",
    "gn:population":0,
    "gn:timezone":"America/Mazatlan",
    "iso:country":"MX",
    "name:spa_x_preferred":[
        "Las Torres"
    ],
    "wof:name":"Las Torres",
    "wof:placetype":"locality"
},
  "geometry": {"coordinates":[-105.92075,23.89266],"type":"Point"}
}