{
  "type": "Feature",
  "properties": {
    "gn:admin1_code":"14.0",
    "gn:admin2_code":"85.0",
    "gn:asciiname":"Agua de la Virgen",
    "gn:country_code":"MX",
    "gn:dem":1922,
    "gn:feature_class":"P",
    "gn:feature_code":"PPL",
    "gn:name":"Agua de la Virgen",
    "gn:population":0,
    "gn:timezone":"America/Mexico_City",
    "iso:country":"MX",
    "name:spa_x_preferred":[
        "Agua de la Virgen"
    ],
    "wof:name":"Agua de la Virgen",
    "wof:placetype":"locality"
},
  "geometry": {"coordinates":[-103.24391,19.8772],"type":"Point"}
}