{
  "type": "Feature",
  "properties": {
    "gn:admin1_code":"26",
    "gn:admin2_code":"49.0",
    "gn:asciiname":"Los Bajios",
    "gn:country_code":"MX",
    "gn:dem":395,
    "gn:feature_class":"P",
    "gn:feature_code":"PPL",
    "gn:name":"Los Baj\u00edos",
    "gn:population":0,
    "gn:timezone":"America/Hermosillo",
    "iso:country":"MX",
    "name:spa_x_preferred":[
        "Los Baj\u00edos"
    ],
    "wof:name":"Los Bajios",
    "wof:placetype":"locality"
},
  "geometry": {"coordinates":[-108.99191,27.67372],"type":"Point"}
}