{
  "type": "Feature",
  "properties": {
    "gn:admin1_code":"13",
    "gn:admin2_code":"44.0",
    "gn:asciiname":"Mangui",
    "gn:country_code":"MX",
    "gn:dem":2475,
    "gn:feature_class":"P",
    "gn:feature_code":"PPL",
    "gn:name":"Mangui",
    "gn:population":0,
    "gn:timezone":"America/Mexico_City",
    "iso:country":"MX",
    "name:spa_x_preferred":[
        "Mangui"
    ],
    "wof:name":"Mangui",
    "wof:placetype":"locality"
},
  "geometry": {"coordinates":[-99.60957000000001,20.22778],"type":"Point"}
}