{
  "type": "Feature",
  "properties": {
    "gn:admin1_code":"5",
    "gn:admin2_code":"61.0",
    "gn:asciiname":"San Joaquin",
    "gn:country_code":"MX",
    "gn:dem":826,
    "gn:feature_class":"P",
    "gn:feature_code":"PPL",
    "gn:name":"San Joaqu\u00edn",
    "gn:population":3,
    "gn:timezone":"America/Mexico_City",
    "iso:country":"MX",
    "wof:name":"San Joaquin",
    "wof:placetype":"locality",
    "wof:population":3
},
  "geometry": {"coordinates":[-93.42917,16.58278],"type":"Point"}
}