{
  "type": "Feature",
  "properties": {
    "gn:admin1_code":"25",
    "gn:admin2_code":"18.0",
    "gn:asciiname":"La Veintiuno",
    "gn:country_code":"MX",
    "gn:dem":14,
    "gn:feature_class":"P",
    "gn:feature_code":"PPL",
    "gn:name":"La Veintiuno",
    "gn:population":94,
    "gn:timezone":"America/Mazatlan",
    "iso:country":"MX",
    "wof:name":"La Veintiuno",
    "wof:placetype":"locality",
    "wof:population":94
},
  "geometry": {"coordinates":[-107.61167,24.72639],"type":"Point"}
}