{
  "type": "Feature",
  "properties": {
    "gn:admin1_code":"2",
    "gn:admin2_code":"2.0",
    "gn:asciiname":"Colinas de Mexicali",
    "gn:country_code":"MX",
    "gn:dem":5,
    "gn:feature_class":"P",
    "gn:feature_code":"PPL",
    "gn:name":"Colinas de Mexicali",
    "gn:population":124,
    "gn:timezone":"America/Tijuana",
    "iso:country":"MX",
    "wof:name":"Colinas de Mexicali",
    "wof:placetype":"locality",
    "wof:population":124
},
  "geometry": {"coordinates":[-115.55667,32.55778],"type":"Point"}
}