{
  "type": "Feature",
  "properties": {
    "gn:admin1_code":"5.0",
    "gn:admin2_code":"3.0",
    "gn:asciiname":"Sin Pensar",
    "gn:country_code":"MX",
    "gn:dem":21,
    "gn:feature_class":"P",
    "gn:feature_code":"PPL",
    "gn:name":"Sin Pensar",
    "gn:population":0,
    "gn:timezone":"America/Mexico_City",
    "iso:country":"MX",
    "name:spa_x_preferred":[
        "Sin Pensar"
    ],
    "wof:name":"Sin Pensar",
    "wof:placetype":"locality"
},
  "geometry": {"coordinates":[-92.68492000000001,15.22522],"type":"Point"}
}