{
  "type": "Feature",
  "properties": {
    "gn:admin1_code":"5",
    "gn:admin2_code":"108",
    "gn:asciiname":"San Julian",
    "gn:country_code":"MX",
    "gn:dem":596,
    "gn:feature_class":"P",
    "gn:feature_code":"PPL",
    "gn:name":"San Juli\u00e1n",
    "gn:population":21,
    "gn:timezone":"America/Mexico_City",
    "iso:country":"MX",
    "name:und_x_variant":[
        "San Juli\u00e1n"
    ],
    "wof:name":"San Julian",
    "wof:placetype":"locality",
    "wof:population":21
},
  "geometry": {"coordinates":[-93.26889,16.28833],"type":"Point"}
}