{
  "type": "Feature",
  "properties": {
    "gn:admin1_code":"6",
    "gn:admin2_code":"65",
    "gn:asciiname":"Maguechi",
    "gn:country_code":"MX",
    "gn:dem":2244,
    "gn:feature_class":"P",
    "gn:feature_code":"PPL",
    "gn:name":"Maguechi",
    "gn:population":22,
    "gn:timezone":"America/Chihuahua",
    "iso:country":"MX",
    "wof:name":"Maguechi",
    "wof:placetype":"locality",
    "wof:population":22
},
  "geometry": {"coordinates":[-107.84028000000001,27.50083],"type":"Point"}
}