{
  "type": "Feature",
  "properties": {
    "gn:admin1_code":"5",
    "gn:admin2_code":"31.0",
    "gn:asciiname":"Jol Paxila",
    "gn:country_code":"MX",
    "gn:dem":1295,
    "gn:feature_class":"P",
    "gn:feature_code":"PPL",
    "gn:name":"Jol Paxila",
    "gn:population":251,
    "gn:timezone":"America/Mexico_City",
    "iso:country":"MX",
    "wof:name":"Jol Paxila",
    "wof:placetype":"locality",
    "wof:population":251
},
  "geometry": {"coordinates":[-91.86417,17.01611],"type":"Point"}
}