{
  "type": "Feature",
  "properties": {
    "gn:admin1_code":"16.0",
    "gn:admin2_code":"89.0",
    "gn:asciiname":"El Manguito",
    "gn:country_code":"MX",
    "gn:dem":576,
    "gn:feature_class":"P",
    "gn:feature_code":"PPL",
    "gn:name":"El Manguito",
    "gn:population":0,
    "gn:timezone":"America/Mexico_City",
    "iso:country":"MX",
    "name:spa_x_preferred":[
        "El Manguito"
    ],
    "wof:name":"El Manguito",
    "wof:placetype":"locality"
},
  "geometry": {"coordinates":[-102.9618,19.09558],"type":"Point"}
}