{
  "type": "Feature",
  "properties": {
    "gn:admin1_code":"16",
    "gn:admin2_code":"111",
    "gn:asciiname":"Santa Teresa",
    "gn:country_code":"MX",
    "gn:dem":1262,
    "gn:feature_class":"P",
    "gn:feature_code":"PPL",
    "gn:name":"Santa Teresa",
    "gn:population":10,
    "gn:timezone":"America/Mexico_City",
    "iso:country":"MX",
    "wof:name":"Santa Teresa",
    "wof:placetype":"locality",
    "wof:population":10
},
  "geometry": {"coordinates":[-101.92278,19.39028],"type":"Point"}
}