{
  "type": "Feature",
  "properties": {
    "gn:admin1_code":"30.0",
    "gn:asciiname":"El Diamante",
    "gn:country_code":"MX",
    "gn:dem":123,
    "gn:feature_class":"P",
    "gn:feature_code":"PPL",
    "gn:name":"El Diamante",
    "gn:population":0,
    "gn:timezone":"America/Mexico_City",
    "iso:country":"MX",
    "name:spa_x_preferred":[
        "El Diamante"
    ],
    "wof:name":"El Diamante",
    "wof:placetype":"locality"
},
  "geometry": {"coordinates":[-95.02561,17.91084],"type":"Point"}
}