{
  "type": "Feature",
  "properties": {
    "gn:admin1_code":"12",
    "gn:admin2_code":"30.0",
    "gn:asciiname":"El Meson",
    "gn:country_code":"MX",
    "gn:dem":17,
    "gn:feature_class":"P",
    "gn:feature_code":"PPL",
    "gn:name":"El Mes\u00f3n",
    "gn:population":57,
    "gn:timezone":"America/Mexico_City",
    "iso:country":"MX",
    "name:und_x_variant":[
        "El Mes\u00f3n"
    ],
    "wof:name":"El Meson",
    "wof:placetype":"locality",
    "wof:population":57
},
  "geometry": {"coordinates":[-99.20688,16.67027],"type":"Point"}
}