{
  "type": "Feature",
  "properties": {
    "gn:admin1_code":"16",
    "gn:admin2_code":"10.0",
    "gn:asciiname":"El Guasimal",
    "gn:country_code":"MX",
    "gn:dem":412,
    "gn:feature_class":"P",
    "gn:feature_code":"PPL",
    "gn:name":"El Guasimal",
    "gn:population":0,
    "gn:timezone":"America/Mexico_City",
    "iso:country":"MX",
    "name:spa_x_preferred":[
        "El Guasimal"
    ],
    "wof:name":"El Guasimal",
    "wof:placetype":"locality"
},
  "geometry": {"coordinates":[-102.72445999999999,18.21889],"type":"Point"}
}