{
  "type": "Feature",
  "properties": {
    "gn:admin1_code":"24",
    "gn:admin2_code":"12.0",
    "gn:asciiname":"Timelia",
    "gn:country_code":"MX",
    "gn:dem":218,
    "gn:feature_class":"P",
    "gn:feature_code":"PPL",
    "gn:name":"Timelia",
    "gn:population":0,
    "gn:timezone":"America/Mexico_City",
    "iso:country":"MX",
    "name:spa_x_preferred":[
        "Timelia"
    ],
    "wof:name":"Timelia",
    "wof:placetype":"locality"
},
  "geometry": {"coordinates":[-98.93179000000001,21.5921],"type":"Point"}
}