{
  "type": "Feature",
  "properties": {
    "gn:admin1_code":"21",
    "gn:admin2_code":"77",
    "gn:asciiname":"Coyul",
    "gn:country_code":"MX",
    "gn:dem":723,
    "gn:feature_class":"P",
    "gn:feature_code":"PPL",
    "gn:name":"Coyul",
    "gn:population":16,
    "gn:timezone":"America/Mexico_City",
    "iso:country":"MX",
    "wof:name":"Coyul",
    "wof:placetype":"locality",
    "wof:population":16
},
  "geometry": {"coordinates":[-97.70862,20.03444],"type":"Point"}
}