{
  "type": "Feature",
  "properties": {
    "gn:admin1_code":"30",
    "gn:admin2_code":"183.0",
    "gn:asciiname":"Palmar Chico",
    "gn:country_code":"MX",
    "gn:dem":143,
    "gn:feature_class":"P",
    "gn:feature_code":"PPL",
    "gn:name":"Palmar Chico",
    "gn:population":0,
    "gn:timezone":"America/Mexico_City",
    "iso:country":"MX",
    "name:und_x_variant":[
        "Palmas",
        "Palmar Chico"
    ],
    "wof:name":"Palmar Chico",
    "wof:placetype":"locality"
},
  "geometry": {"coordinates":[-97.15961,20.0795],"type":"Point"}
}