{
  "type": "Feature",
  "properties": {
    "iso:country":"MX",
    "name:ara_x_preferred":[
        "\u0644\u064a\u0648\u0646 \u0643\u0648\u0631\u062a\u064a\u0633"
    ],
    "name:ceb_x_preferred":[
        "Cant\u00f3n de Le\u00f3n Cort\u00e9s"
    ],
    "name:fra_x_preferred":[
        "Le\u00f3n Cort\u00e9s"
    ],
    "name:ita_x_preferred":[
        "Cantone di Le\u00f3n Cort\u00e9s"
    ],
    "name:nor_x_preferred":[
        "Le\u00f3n Cort\u00e9s"
    ],
    "name:rus_x_preferred":[
        "\u041b\u0435\u043e\u043d-\u041a\u043e\u0440\u0442\u0435\u0441"
    ],
    "name:spa_x_preferred":[
        "Lomas de Cortes",
        "Cant\u00f3n de Le\u00f3n Cort\u00e9s Castro"
    ],
    "name:swe_x_preferred":[
        "Cant\u00f3n de Le\u00f3n Cort\u00e9s"
    ],
    "name:unk_x_variant":[
        "Lomas de Cortes"
    ],
    "name:vie_x_preferred":[
        "Le\u00f3n Cort\u00e9s"
    ],
    "name:zho_x_preferred":[
        "\u840a\u6602\u79d1\u723e\u7279\u65af\u5361\u65af\u7279\u7f85\u7e23"
    ],
    "qs:gn_adm0_cc":"MX",
    "qs:gn_local":4005143,
    "qs:gn_nam_loc":"guaymas",
    "qs:gn_namadm1":"26",
    "qs:local_max":497,
    "qs:local_sum":596,
    "qs:localhoods":4,
    "qs:name":"Lomas de Cortes",
    "qs:name_adm0":"M\u00e9xico",
    "qs:name_adm1":"Sonora",
    "qs:name_adm2":"Guaymas",
    "qs:name_local":"Guaymas",
    "qs:photo_max":37,
    "qs:photo_sum":75,
    "qs:placetype":"Suburb",
    "qs:quad_count":5,
    "qs:woe_adm0":23424900,
    "qs:woe_adm1":2346289,
    "qs:woe_adm2":12601573,
    "qs:woe_lau":0,
    "qs:woe_local":124552,
    "qs:woe_ver":"7.10.0",
    "wof:lang":[
        "spa"
    ],
    "wof:name":"Lomas de Cortes",
    "wof:placetype":"neighbourhood"
},
  "geometry": {"coordinates":[-110.948601,27.91141],"type":"Point"}
}