{
  "type": "Feature",
  "properties": {
    "gn:admin1_code":"5",
    "gn:admin2_code":"108.0",
    "gn:asciiname":"Orizaba",
    "gn:country_code":"MX",
    "gn:dem":565,
    "gn:feature_class":"P",
    "gn:feature_code":"PPL",
    "gn:name":"Orizaba",
    "gn:population":0,
    "gn:timezone":"America/Mexico_City",
    "iso:country":"MX",
    "name:spa_x_preferred":[
        "Orizaba"
    ],
    "wof:name":"Orizaba",
    "wof:placetype":"locality"
},
  "geometry": {"coordinates":[-93.23365,16.23939],"type":"Point"}
}