{
  "type": "Feature",
  "properties": {
    "gn:admin1_code":"30.0",
    "gn:asciiname":"Estero de Frijolillo",
    "gn:country_code":"MX",
    "gn:dem":6,
    "gn:feature_class":"P",
    "gn:feature_code":"PPL",
    "gn:name":"Estero de Frijolillo",
    "gn:population":0,
    "gn:timezone":"America/Mexico_City",
    "iso:country":"MX",
    "name:spa_x_preferred":[
        "Estero de Frijolillo"
    ],
    "wof:name":"Estero de Frijolillo",
    "wof:placetype":"locality"
},
  "geometry": {"coordinates":[-97.48421,20.90476],"type":"Point"}
}