{
  "type": "Feature",
  "properties": {
    "gn:admin1_code":"30",
    "gn:admin2_code":"201.0",
    "gn:asciiname":"Paraje Ayojapa",
    "gn:country_code":"MX",
    "gn:dem":995,
    "gn:feature_class":"P",
    "gn:feature_code":"PPL",
    "gn:name":"Paraje Ayojapa",
    "gn:population":154,
    "gn:timezone":"America/Mexico_City",
    "iso:country":"MX",
    "wof:name":"Paraje Ayojapa",
    "wof:placetype":"locality",
    "wof:population":154
},
  "geometry": {"coordinates":[-96.94583,18.69222],"type":"Point"}
}