{
  "type": "Feature",
  "properties": {
    "gn:admin1_code":"20",
    "gn:admin2_code":"474.0",
    "gn:asciiname":"El Trebol",
    "gn:country_code":"MX",
    "gn:dem":94,
    "gn:feature_class":"P",
    "gn:feature_code":"PPL",
    "gn:name":"El Tr\u00e9bol",
    "gn:population":5,
    "gn:timezone":"America/Mexico_City",
    "iso:country":"MX",
    "name:und_x_variant":[
        "El Tr\u00e9bol"
    ],
    "wof:name":"El Trebol",
    "wof:placetype":"locality",
    "wof:population":5
},
  "geometry": {"coordinates":[-98.29028,16.52361],"type":"Point"}
}