{
  "type": "Feature",
  "properties": {
    "gn:admin1_code":"26",
    "gn:admin2_code":"72.0",
    "gn:asciiname":"El Alto",
    "gn:country_code":"MX",
    "gn:dem":9,
    "gn:feature_class":"P",
    "gn:feature_code":"PPL",
    "gn:name":"El Alto",
    "gn:population":0,
    "gn:timezone":"America/Hermosillo",
    "iso:country":"MX",
    "name:spa_x_preferred":[
        "El Alto"
    ],
    "wof:name":"El Alto",
    "wof:placetype":"locality"
},
  "geometry": {"coordinates":[-110.18453,27.3058],"type":"Point"}
}