{
  "type": "Feature",
  "properties": {
    "gn:admin1_code":"20",
    "gn:admin2_code":"198.0",
    "gn:asciiname":"Encinal Colorado",
    "gn:country_code":"MX",
    "gn:dem":280,
    "gn:feature_class":"P",
    "gn:feature_code":"PPL",
    "gn:name":"Encinal Colorado",
    "gn:population":0,
    "gn:timezone":"America/Mexico_City",
    "iso:country":"MX",
    "name:spa_x_preferred":[
        "Encinal Colorado"
    ],
    "wof:name":"Encinal Colorado",
    "wof:placetype":"locality"
},
  "geometry": {"coordinates":[-95.10732,17.00995],"type":"Point"}
}