{
  "type": "Feature",
  "properties": {
    "gn:admin1_code":"7",
    "gn:admin2_code":"1.0",
    "gn:asciiname":"Las Adjuntas",
    "gn:country_code":"MX",
    "gn:dem":427,
    "gn:feature_class":"P",
    "gn:feature_code":"PPL",
    "gn:name":"Las Adjuntas",
    "gn:population":2,
    "gn:timezone":"America/Monterrey",
    "iso:country":"MX",
    "name:jpn_x_preferred":[
        "\u30e9\u30b9\u30fb\u30a2\u30c9\u30d5\u30f3\u30bf\u30b9\u99c5"
    ],
    "name:por_x_preferred":[
        "Esta\u00e7\u00e3o Las Adjuntas"
    ],
    "name:und_x_variant":[
        "Adjuntas",
        "Hacienda Las Adjuntas",
        "Las Adjuntas"
    ],
    "wof:name":"Las Adjuntas",
    "wof:placetype":"locality",
    "wof:population":2
},
  "geometry": {"coordinates":[-101.2757,27.11948],"type":"Point"}
}