{
  "type": "Feature",
  "properties": {
    "gn:admin1_code":"25",
    "gn:admin2_code":"7.0",
    "gn:asciiname":"Mina Fria",
    "gn:country_code":"MX",
    "gn:dem":1847,
    "gn:feature_class":"P",
    "gn:feature_code":"PPL",
    "gn:name":"Mina Fr\u00eda",
    "gn:population":98,
    "gn:timezone":"America/Mazatlan",
    "iso:country":"MX",
    "name:und_x_variant":[
        "Mina Fr\u00eda"
    ],
    "wof:name":"Mina Fria",
    "wof:placetype":"locality",
    "wof:population":98
},
  "geometry": {"coordinates":[-108.04567,26.77016],"type":"Point"}
}