{
  "type": "Feature",
  "properties": {
    "gn:admin1_code":"13",
    "gn:admin2_code":"53.0",
    "gn:asciiname":"Juntas del Rio",
    "gn:country_code":"MX",
    "gn:dem":1076,
    "gn:feature_class":"P",
    "gn:feature_code":"PPL",
    "gn:name":"Juntas del R\u00edo",
    "gn:population":71,
    "gn:timezone":"America/Mexico_City",
    "iso:country":"MX",
    "name:und_x_variant":[
        "Juntas del R\u00edo"
    ],
    "wof:name":"Juntas del Rio",
    "wof:placetype":"locality",
    "wof:population":71
},
  "geometry": {"coordinates":[-98.31520999999999,20.43252],"type":"Point"}
}