{
  "type": "Feature",
  "properties": {
    "gn:admin1_code":"26",
    "gn:admin2_code":"42.0",
    "gn:asciiname":"Tesia",
    "gn:country_code":"MX",
    "gn:dem":50,
    "gn:feature_class":"P",
    "gn:feature_code":"PPL",
    "gn:name":"Tesia",
    "gn:population":0,
    "gn:timezone":"America/Hermosillo",
    "iso:country":"MX",
    "name:bre_x_preferred":[
        "Tesia"
    ],
    "name:cat_x_preferred":[
        "Tesia"
    ],
    "name:ceb_x_preferred":[
        "Tesia"
    ],
    "name:epo_x_preferred":[
        "Tesiaoj"
    ],
    "name:fas_x_preferred":[
        "\u0633\u0633\u06a9\u200c\u0647\u0627\u06cc \u0632\u0645\u06cc\u0646\u06cc"
    ],
    "name:fin_x_preferred":[
        "Pittakerttuset"
    ],
    "name:fra_x_preferred":[
        "Tesia"
    ],
    "name:hun_x_preferred":[
        "Tesia"
    ],
    "name:nld_x_preferred":[
        "Tesia"
    ],
    "name:pol_x_preferred":[
        "Tesia"
    ],
    "name:por_x_preferred":[
        "Tesia"
    ],
    "name:rus_x_preferred":[
        "\u0422\u0435\u0437\u0438\u0438"
    ],
    "name:spa_x_preferred":[
        "Tesia"
    ],
    "name:swe_x_preferred":[
        "Tesior"
    ],
    "name:vie_x_preferred":[
        "Tesia"
    ],
    "name:war_x_preferred":[
        "Tesia"
    ],
    "wof:name":"Tesia",
    "wof:placetype":"locality"
},
  "geometry": {"coordinates":[-109.37184999999999,27.16414],"type":"Point"}
}