{
  "type": "Feature",
  "properties": {
    "gn:admin1_code":"10",
    "gn:admin2_code":"26",
    "gn:asciiname":"Los Parajes del Faisan",
    "gn:country_code":"MX",
    "gn:dem":2383,
    "gn:feature_class":"P",
    "gn:feature_code":"PPL",
    "gn:name":"Los Parajes del Fais\u00e1n",
    "gn:population":12,
    "gn:timezone":"America/Monterrey",
    "iso:country":"MX",
    "name:und_x_variant":[
        "Los Parajes del Fais\u00e1n"
    ],
    "wof:name":"Los Parajes del Faisan",
    "wof:placetype":"locality",
    "wof:population":12
},
  "geometry": {"coordinates":[-105.77391,23.75695],"type":"Point"}
}