{
  "type": "Feature",
  "properties": {
    "gn:admin1_code":"6.0",
    "gn:admin2_code":"67.0",
    "gn:asciiname":"El Alamillo",
    "gn:country_code":"MX",
    "gn:dem":1326,
    "gn:feature_class":"P",
    "gn:feature_code":"PPL",
    "gn:name":"El Alamillo",
    "gn:population":4,
    "gn:timezone":"America/Chihuahua",
    "iso:country":"MX",
    "name:spa_x_preferred":[
        "El Alamillo"
    ],
    "wof:name":"El Alamillo",
    "wof:placetype":"locality",
    "wof:population":4
},
  "geometry": {"coordinates":[-105.72013,27.51781],"type":"Point"}
}