{
  "type": "Feature",
  "properties": {
    "gn:admin1_code":"27",
    "gn:admin2_code":"8.0",
    "gn:asciiname":"Carlos A. Madrazo",
    "gn:country_code":"MX",
    "gn:dem":139,
    "gn:feature_class":"P",
    "gn:feature_code":"PPL",
    "gn:name":"Carlos A. Madrazo",
    "gn:population":170,
    "gn:timezone":"America/Mexico_City",
    "iso:country":"MX",
    "wof:name":"Carlos A. Madrazo",
    "wof:placetype":"locality",
    "wof:population":170
},
  "geometry": {"coordinates":[-93.66194,17.39583],"type":"Point"}
}