{
  "type": "Feature",
  "properties": {
    "gn:admin1_code":"30",
    "gn:admin2_code":"58.0",
    "gn:asciiname":"Alahualtitla",
    "gn:country_code":"MX",
    "gn:dem":521,
    "gn:feature_class":"P",
    "gn:feature_code":"PPL",
    "gn:name":"Alahualtitla",
    "gn:population":566,
    "gn:timezone":"America/Mexico_City",
    "iso:country":"MX",
    "name:spa_x_preferred":[
        "Alahualtitla"
    ],
    "name:und_x_variant":[
        "Atahualtitla"
    ],
    "wof:name":"Alahualtitla",
    "wof:placetype":"locality",
    "wof:population":566
},
  "geometry": {"coordinates":[-98.16732,20.92747],"type":"Point"}
}