{
  "type": "Feature",
  "properties": {
    "gn:admin1_code":"17",
    "gn:asciiname":"San Diego de los Padres",
    "gn:country_code":"MX",
    "gn:dem":2587,
    "gn:feature_class":"P",
    "gn:feature_code":"PPL",
    "gn:name":"San Diego de los Padres",
    "gn:population":0,
    "gn:timezone":"America/Mexico_City",
    "iso:country":"MX",
    "name:spa_x_preferred":[
        "San Diego de los Padres"
    ],
    "wof:name":"San Diego de los Padres",
    "wof:placetype":"locality"
},
  "geometry": {"coordinates":[-99.60630999999999,19.3725],"type":"Point"}
}