{
  "type": "Feature",
  "properties": {
    "gn:admin1_code":"30",
    "gn:admin2_code":"201.0",
    "gn:asciiname":"Tlacuilola",
    "gn:country_code":"MX",
    "gn:dem":836,
    "gn:feature_class":"P",
    "gn:feature_code":"PPL",
    "gn:name":"Tlacuilola",
    "gn:population":265,
    "gn:timezone":"America/Mexico_City",
    "iso:country":"MX",
    "wof:name":"Tlacuilola",
    "wof:placetype":"locality",
    "wof:population":265
},
  "geometry": {"coordinates":[-96.90694000000001,18.74194],"type":"Point"}
}