{
  "type": "Feature",
  "properties": {
    "gn:admin1_code":"5",
    "gn:admin2_code":"89.0",
    "gn:asciiname":"Cebadilla 1ra. Seccion",
    "gn:country_code":"MX",
    "gn:dem":114,
    "gn:feature_class":"P",
    "gn:feature_code":"PPL",
    "gn:name":"Cebadilla 1ra. Secci\u00f3n",
    "gn:population":1384,
    "gn:timezone":"America/Mexico_City",
    "iso:country":"MX",
    "name:und_x_variant":[
        "Cebadilla 1ra. Secci\u00f3n"
    ],
    "wof:name":"Cebadilla 1ra. Seccion",
    "wof:placetype":"locality",
    "wof:population":1384
},
  "geometry": {"coordinates":[-92.27969,14.86381],"type":"Point"}
}