{
  "type": "Feature",
  "properties": {
    "gn:admin1_code":"10",
    "gn:admin2_code":"13.0",
    "gn:asciiname":"San Isidro del Derrame",
    "gn:country_code":"MX",
    "gn:dem":1298,
    "gn:feature_class":"P",
    "gn:feature_code":"PPL",
    "gn:name":"San Isidro del Derrame",
    "gn:population":0,
    "gn:timezone":"America/Monterrey",
    "iso:country":"MX",
    "name:spa_x_preferred":[
        "San Isidro del Derrame"
    ],
    "name:und_x_variant":[
        "San Isidro"
    ],
    "wof:name":"San Isidro del Derrame",
    "wof:placetype":"locality"
},
  "geometry": {"coordinates":[-104.3302,26.33679],"type":"Point"}
}