{
  "type": "Feature",
  "properties": {
    "gn:admin1_code":"25",
    "gn:admin2_code":"3",
    "gn:asciiname":"El Guasimal",
    "gn:country_code":"MX",
    "gn:dem":327,
    "gn:feature_class":"P",
    "gn:feature_code":"PPL",
    "gn:name":"El Guasimal",
    "gn:population":51,
    "gn:timezone":"America/Mazatlan",
    "iso:country":"MX",
    "wof:name":"El Guasimal",
    "wof:placetype":"locality",
    "wof:population":51
},
  "geometry": {"coordinates":[-107.57147000000001,25.4885],"type":"Point"}
}