{
  "type": "Feature",
  "properties": {
    "gn:admin1_code":"6",
    "gn:admin2_code":"8.0",
    "gn:asciiname":"El Pinito",
    "gn:country_code":"MX",
    "gn:dem":1134,
    "gn:feature_class":"P",
    "gn:feature_code":"PPL",
    "gn:name":"El Pinito",
    "gn:population":4,
    "gn:timezone":"America/Chihuahua",
    "iso:country":"MX",
    "name:spa_x_preferred":[
        "El Pinito"
    ],
    "wof:name":"El Pinito",
    "wof:placetype":"locality",
    "wof:population":4
},
  "geometry": {"coordinates":[-107.91295,26.79771],"type":"Point"}
}