{
  "type": "Feature",
  "properties": {
    "gn:admin1_code":"11",
    "gn:admin2_code":"14",
    "gn:asciiname":"La Cercada",
    "gn:country_code":"MX",
    "gn:dem":1985,
    "gn:feature_class":"P",
    "gn:feature_code":"PPL",
    "gn:name":"La Cercada",
    "gn:population":25,
    "gn:timezone":"America/Mexico_City",
    "iso:country":"MX",
    "wof:name":"La Cercada",
    "wof:placetype":"locality",
    "wof:population":25
},
  "geometry": {"coordinates":[-100.86444,21.21806],"type":"Point"}
}