{
  "type": "Feature",
  "properties": {
    "gn:admin1_code":"18",
    "gn:admin2_code":"14",
    "gn:asciiname":"Jocota (Las de Amolar)",
    "gn:country_code":"MX",
    "gn:dem":225,
    "gn:feature_class":"P",
    "gn:feature_code":"PPL",
    "gn:name":"Jocota (Las de Amolar)",
    "gn:population":10,
    "gn:timezone":"America/Mazatlan",
    "iso:country":"MX",
    "wof:name":"Jocota (Las de Amolar)",
    "wof:placetype":"locality",
    "wof:population":10
},
  "geometry": {"coordinates":[-104.57528000000001,21.57528],"type":"Point"}
}