{
  "type": "Feature",
  "properties": {
    "gn:admin1_code":"20",
    "gn:admin2_code":"6",
    "gn:asciiname":"Loma Larga",
    "gn:country_code":"MX",
    "gn:dem":2203,
    "gn:feature_class":"P",
    "gn:feature_code":"PPL",
    "gn:name":"Loma Larga",
    "gn:population":11,
    "gn:timezone":"America/Mexico_City",
    "iso:country":"MX",
    "wof:name":"Loma Larga",
    "wof:placetype":"locality",
    "wof:population":11
},
  "geometry": {"coordinates":[-97.14806,17.35278],"type":"Point"}
}