{
  "type": "Feature",
  "properties": {
    "gn:admin1_code":"11",
    "gn:admin2_code":"22",
    "gn:asciiname":"El Garabato",
    "gn:country_code":"MX",
    "gn:dem":2170,
    "gn:feature_class":"P",
    "gn:feature_code":"PPL",
    "gn:name":"El Garabato",
    "gn:population":51,
    "gn:timezone":"America/Mexico_City",
    "iso:country":"MX",
    "wof:name":"El Garabato",
    "wof:placetype":"locality",
    "wof:population":51
},
  "geometry": {"coordinates":[-101.48389,21.47583],"type":"Point"}
}