{
  "type": "Feature",
  "properties": {
    "gn:admin1_code":"2",
    "gn:admin2_code":"1.0",
    "gn:asciiname":"Tres Encinos",
    "gn:country_code":"MX",
    "gn:dem":310,
    "gn:feature_class":"P",
    "gn:feature_code":"PPL",
    "gn:name":"Tres Encinos",
    "gn:population":6,
    "gn:timezone":"America/Tijuana",
    "iso:country":"MX",
    "wof:name":"Tres Encinos",
    "wof:placetype":"locality",
    "wof:population":6
},
  "geometry": {"coordinates":[-116.62639,31.97111],"type":"Point"}
}