{
  "type": "Feature",
  "properties": {
    "gn:admin1_code":"6",
    "gn:admin2_code":"27.0",
    "gn:asciiname":"Sitanachi",
    "gn:country_code":"MX",
    "gn:dem":2183,
    "gn:feature_class":"P",
    "gn:feature_code":"PPL",
    "gn:name":"Sit\u00e1nachi",
    "gn:population":0,
    "gn:timezone":"America/Chihuahua",
    "iso:country":"MX",
    "name:spa_x_preferred":[
        "Sit\u00e1nachi"
    ],
    "wof:name":"Sitanachi",
    "wof:placetype":"locality"
},
  "geometry": {"coordinates":[-107.27482999999999,27.23984],"type":"Point"}
}