{
  "type": "Feature",
  "properties": {
    "gn:admin1_code":"11.0",
    "gn:admin2_code":"3.0",
    "gn:asciiname":"Laguna Escondida",
    "gn:country_code":"MX",
    "gn:dem":2059,
    "gn:feature_class":"P",
    "gn:feature_code":"PPL",
    "gn:name":"Laguna Escondida",
    "gn:population":0,
    "gn:timezone":"America/Mexico_City",
    "iso:country":"MX",
    "name:spa_x_preferred":[
        "Laguna Escondida"
    ],
    "name:spa_x_variant":[
        "La Laguna"
    ],
    "wof:name":"Laguna Escondida",
    "wof:placetype":"locality"
},
  "geometry": {"coordinates":[-100.60463,20.93012],"type":"Point"}
}