{
  "type": "Feature",
  "properties": {
    "gn:admin1_code":"10",
    "gn:admin2_code":"14.0",
    "gn:asciiname":"Chimaltita",
    "gn:country_code":"MX",
    "gn:dem":651,
    "gn:feature_class":"P",
    "gn:feature_code":"PPL",
    "gn:name":"Chimaltita",
    "gn:population":84,
    "gn:timezone":"America/Monterrey",
    "iso:country":"MX",
    "wof:name":"Chimaltita",
    "wof:placetype":"locality",
    "wof:population":84
},
  "geometry": {"coordinates":[-104.4755,22.60087],"type":"Point"}
}