{
  "type": "Feature",
  "properties": {
    "gn:admin1_code":"22",
    "gn:admin2_code":"5",
    "gn:asciiname":"Los Naranjos [Fraccionamiento]",
    "gn:country_code":"MX",
    "gn:dem":1947,
    "gn:feature_class":"P",
    "gn:feature_code":"PPL",
    "gn:name":"Los Naranjos [Fraccionamiento]",
    "gn:population":43,
    "gn:timezone":"America/Mexico_City",
    "iso:country":"MX",
    "wof:name":"Los Naranjos [Fraccionamiento]",
    "wof:placetype":"locality",
    "wof:population":43
},
  "geometry": {"coordinates":[-100.04694000000001,20.76444],"type":"Point"}
}