{
  "type": "Feature",
  "properties": {
    "gn:admin1_code":"26",
    "gn:admin2_code":"49.0",
    "gn:asciiname":"La Huerta",
    "gn:country_code":"MX",
    "gn:dem":208,
    "gn:feature_class":"P",
    "gn:feature_code":"PPL",
    "gn:name":"La Huerta",
    "gn:population":5,
    "gn:timezone":"America/Hermosillo",
    "iso:country":"MX",
    "name:spa_x_preferred":[
        "La Huerta"
    ],
    "wof:name":"La Huerta",
    "wof:placetype":"locality",
    "wof:population":5
},
  "geometry": {"coordinates":[-109.23305999999999,27.52806],"type":"Point"}
}