{
  "type": "Feature",
  "properties": {
    "gn:admin1_code":"30",
    "gn:admin2_code":"4",
    "gn:asciiname":"El Soldado",
    "gn:country_code":"MX",
    "gn:dem":118,
    "gn:feature_class":"P",
    "gn:feature_code":"PPL",
    "gn:name":"El Soldado",
    "gn:population":10,
    "gn:timezone":"America/Mexico_City",
    "iso:country":"MX",
    "wof:name":"El Soldado",
    "wof:placetype":"locality",
    "wof:population":10
},
  "geometry": {"coordinates":[-96.51222,19.45806],"type":"Point"}
}