{
  "type": "Feature",
  "properties": {
    "gn:admin1_code":"25",
    "gn:admin2_code":"10",
    "gn:asciiname":"Pista Aerea",
    "gn:country_code":"MX",
    "gn:dem":95,
    "gn:feature_class":"P",
    "gn:feature_code":"PPL",
    "gn:name":"Pista A\u00e9rea",
    "gn:population":16,
    "gn:timezone":"America/Mazatlan",
    "iso:country":"MX",
    "name:und_x_variant":[
        "Pista A\u00e9rea"
    ],
    "wof:name":"Pista Aerea",
    "wof:placetype":"locality",
    "wof:population":16
},
  "geometry": {"coordinates":[-108.61426000000002,26.40014],"type":"Point"}
}