{
  "type": "Feature",
  "properties": {
    "gn:admin1_code":"24",
    "gn:admin2_code":"50.0",
    "gn:asciiname":"Socavon (El Carmen)",
    "gn:country_code":"MX",
    "gn:dem":1810,
    "gn:feature_class":"P",
    "gn:feature_code":"PPL",
    "gn:name":"Socav\u00f3n (El Carmen)",
    "gn:population":1588,
    "gn:timezone":"America/Mexico_City",
    "iso:country":"MX",
    "wof:name":"Socavon (El Carmen)",
    "wof:placetype":"locality",
    "wof:population":1588
},
  "geometry": {"coordinates":[-100.87184000000001,21.85139],"type":"Point"}
}