{
  "type": "Feature",
  "properties": {
    "gn:admin1_code":"11",
    "gn:admin2_code":"29",
    "gn:asciiname":"El Flechado",
    "gn:country_code":"MX",
    "gn:dem":2010,
    "gn:feature_class":"P",
    "gn:feature_code":"PPL",
    "gn:name":"El Flechado",
    "gn:population":27,
    "gn:timezone":"America/Mexico_City",
    "iso:country":"MX",
    "wof:name":"El Flechado",
    "wof:placetype":"locality",
    "wof:population":27
},
  "geometry": {"coordinates":[-100.97472,21.31667],"type":"Point"}
}