{
  "type": "Feature",
  "properties": {
    "gn:admin1_code":"6.0",
    "gn:asciiname":"San Fermin",
    "gn:country_code":"MX",
    "gn:dem":1167,
    "gn:feature_class":"P",
    "gn:feature_code":"PPL",
    "gn:name":"San Ferm\u00edn",
    "gn:population":0,
    "gn:timezone":"America/Chihuahua",
    "iso:country":"MX",
    "name:spa_x_preferred":[
        "San Ferm\u00edn"
    ],
    "wof:name":"San Fermin",
    "wof:placetype":"locality"
},
  "geometry": {"coordinates":[-105.54703000000001,28.40565],"type":"Point"}
}