{
  "type": "Feature",
  "properties": {
    "gn:admin1_code":"5",
    "gn:admin2_code":"64.0",
    "gn:asciiname":"Xlocaton",
    "gn:country_code":"MX",
    "gn:dem":1959,
    "gn:feature_class":"P",
    "gn:feature_code":"PPL",
    "gn:name":"Xlocat\u00f3n",
    "gn:population":302,
    "gn:timezone":"America/Mexico_City",
    "iso:country":"MX",
    "name:und_x_variant":[
        "Xlocat\u00f3n"
    ],
    "wof:name":"Xlocaton",
    "wof:placetype":"locality",
    "wof:population":302
},
  "geometry": {"coordinates":[-92.34560999999999,16.80079],"type":"Point"}
}