{
  "type": "Feature",
  "properties": {
    "gn:admin1_code":"5",
    "gn:admin2_code":"30",
    "gn:asciiname":"El Terronal",
    "gn:country_code":"MX",
    "gn:dem":652,
    "gn:feature_class":"P",
    "gn:feature_code":"PPL",
    "gn:name":"El Terronal",
    "gn:population":23,
    "gn:timezone":"America/Mexico_City",
    "iso:country":"MX",
    "wof:name":"El Terronal",
    "wof:placetype":"locality",
    "wof:population":23
},
  "geometry": {"coordinates":[-92.40971999999999,15.74],"type":"Point"}
}