{
  "type": "Feature",
  "properties": {
    "gn:admin1_code":"13",
    "gn:admin2_code":"37",
    "gn:asciiname":"Barrio el Calvario",
    "gn:country_code":"MX",
    "gn:dem":1466,
    "gn:feature_class":"P",
    "gn:feature_code":"PPL",
    "gn:name":"Barrio el Calvario",
    "gn:population":15,
    "gn:timezone":"America/Mexico_City",
    "iso:country":"MX",
    "wof:name":"Barrio el Calvario",
    "wof:placetype":"locality",
    "wof:population":15
},
  "geometry": {"coordinates":[-98.76260000000001,20.60426],"type":"Point"}
}