{
  "type": "Feature",
  "properties": {
    "gn:admin1_code":"15",
    "gn:admin2_code":"56.0",
    "gn:asciiname":"La Cruz (San Simon la Cruz)",
    "gn:country_code":"MX",
    "gn:dem":2782,
    "gn:feature_class":"P",
    "gn:feature_code":"PPL",
    "gn:name":"La Cruz (San Sim\u00f3n la Cruz)",
    "gn:population":667,
    "gn:timezone":"America/Mexico_City",
    "iso:country":"MX",
    "name:und_x_variant":[
        "La Cruz (San Sim\u00f3n la Cruz)"
    ],
    "wof:name":"La Cruz (San Simon la Cruz)",
    "wof:placetype":"locality",
    "wof:population":667
},
  "geometry": {"coordinates":[-99.58833,19.72889],"type":"Point"}
}