{
  "type": "Feature",
  "properties": {
    "gn:admin1_code":"14",
    "gn:admin2_code":"25.0",
    "gn:asciiname":"Tulimic de Guadalupe",
    "gn:country_code":"MX",
    "gn:dem":1633,
    "gn:feature_class":"P",
    "gn:feature_code":"PPL",
    "gn:name":"Tulimic de Guadalupe",
    "gn:population":101,
    "gn:timezone":"America/Mexico_City",
    "iso:country":"MX",
    "wof:name":"Tulimic de Guadalupe",
    "wof:placetype":"locality",
    "wof:population":101
},
  "geometry": {"coordinates":[-103.30889000000001,22.00389],"type":"Point"}
}