{
  "type": "Feature",
  "properties": {
    "gn:admin1_code":"6.0",
    "gn:admin2_code":"21.0",
    "gn:asciiname":"La Merced",
    "gn:country_code":"MX",
    "gn:dem":1188,
    "gn:feature_class":"P",
    "gn:feature_code":"PPL",
    "gn:name":"La Merced",
    "gn:population":124,
    "gn:timezone":"America/Chihuahua",
    "iso:country":"MX",
    "name:ceb_x_preferred":[
        "La Merced"
    ],
    "name:deu_x_preferred":[
        "La Merced"
    ],
    "name:fra_x_preferred":[
        "La Merced"
    ],
    "name:ita_x_preferred":[
        "La Merced"
    ],
    "name:nld_x_preferred":[
        "La Merced"
    ],
    "name:pol_x_preferred":[
        "La Merced"
    ],
    "name:por_x_preferred":[
        "La Merced"
    ],
    "name:spa_x_preferred":[
        "La Merced"
    ],
    "name:swe_x_preferred":[
        "La Merced"
    ],
    "name:vie_x_preferred":[
        "La Merced"
    ],
    "wof:name":"La Merced",
    "wof:placetype":"locality",
    "wof:population":124
},
  "geometry": {"coordinates":[-105.35572000000001,28.24836],"type":"Point"}
}