{
  "type": "Feature",
  "properties": {
    "gn:admin1_code":"17",
    "gn:admin2_code":"27",
    "gn:asciiname":"Paraiso del Conquistador",
    "gn:country_code":"MX",
    "gn:dem":1958,
    "gn:feature_class":"P",
    "gn:feature_code":"PPL",
    "gn:name":"Para\u00edso del Conquistador",
    "gn:population":17,
    "gn:timezone":"America/Mexico_City",
    "iso:country":"MX",
    "name:und_x_variant":[
        "Para\u00edso del Conquistador"
    ],
    "wof:name":"Paraiso del Conquistador",
    "wof:placetype":"locality",
    "wof:population":17
},
  "geometry": {"coordinates":[-98.90472,18.98444],"type":"Point"}
}