{
  "type": "Feature",
  "properties": {
    "gn:admin1_code":"24",
    "gn:admin2_code":"41.0",
    "gn:asciiname":"Dhokob",
    "gn:country_code":"MX",
    "gn:dem":179,
    "gn:feature_class":"P",
    "gn:feature_code":"PPL",
    "gn:name":"Dhokob",
    "gn:population":256,
    "gn:timezone":"America/Mexico_City",
    "iso:country":"MX",
    "wof:name":"Dhokob",
    "wof:placetype":"locality",
    "wof:population":256
},
  "geometry": {"coordinates":[-98.90861,21.66444],"type":"Point"}
}