{
  "type": "Feature",
  "properties": {
    "gn:admin1_code":"14",
    "gn:admin2_code":"87.0",
    "gn:asciiname":"Los Tepeguajes",
    "gn:country_code":"MX",
    "gn:dem":1221,
    "gn:feature_class":"P",
    "gn:feature_code":"PPL",
    "gn:name":"Los Tepeguajes",
    "gn:population":6,
    "gn:timezone":"America/Mexico_City",
    "iso:country":"MX",
    "wof:name":"Los Tepeguajes",
    "wof:placetype":"locality",
    "wof:population":6
},
  "geometry": {"coordinates":[-103.14417,19.40139],"type":"Point"}
}