{
  "type": "Feature",
  "properties": {
    "gn:admin1_code":"30",
    "gn:admin2_code":"208.0",
    "gn:asciiname":"Paso Real",
    "gn:country_code":"MX",
    "gn:dem":13,
    "gn:feature_class":"P",
    "gn:feature_code":"PPL",
    "gn:name":"Paso Real",
    "gn:population":0,
    "gn:timezone":"America/Mexico_City",
    "iso:country":"MX",
    "name:spa_x_preferred":[
        "Paso Real"
    ],
    "wof:name":"Paso Real",
    "wof:placetype":"locality"
},
  "geometry": {"coordinates":[-95.73562,18.36814],"type":"Point"}
}