{
  "type": "Feature",
  "properties": {
    "gn:admin1_code":"1.0",
    "gn:admin2_code":"5.0",
    "gn:asciiname":"Pedernal",
    "gn:country_code":"MX",
    "gn:dem":2021,
    "gn:feature_class":"P",
    "gn:feature_code":"PPL",
    "gn:name":"Pedernal",
    "gn:population":0,
    "gn:timezone":"America/Mexico_City",
    "iso:country":"MX",
    "wof:name":"Pedernal",
    "wof:placetype":"locality"
},
  "geometry": {"coordinates":[-102.49687,21.88974],"type":"Point"}
}