{
  "type": "Feature",
  "properties": {
    "gn:admin1_code":"23",
    "gn:admin2_code":"4.0",
    "gn:asciiname":"Chacanbacab",
    "gn:country_code":"MX",
    "gn:dem":159,
    "gn:feature_class":"P",
    "gn:feature_code":"PPL",
    "gn:name":"Chacanbacab",
    "gn:population":0,
    "gn:timezone":"America/Cancun",
    "iso:country":"MX",
    "wof:name":"Chacanbacab",
    "wof:placetype":"locality"
},
  "geometry": {"coordinates":[-89.11667,18.53333],"type":"Point"}
}