{
  "type": "Feature",
  "properties": {
    "gn:admin1_code":"20",
    "gn:admin2_code":"44.0",
    "gn:asciiname":"El Triunfo",
    "gn:country_code":"MX",
    "gn:dem":62,
    "gn:feature_class":"P",
    "gn:feature_code":"PPL",
    "gn:name":"El Triunfo",
    "gn:population":92,
    "gn:timezone":"America/Mexico_City",
    "iso:country":"MX",
    "wof:name":"El Triunfo",
    "wof:placetype":"locality",
    "wof:population":92
},
  "geometry": {"coordinates":[-95.86278,18.03611],"type":"Point"}
}