{
  "type": "Feature",
  "properties": {
    "gn:admin1_code":"12",
    "gn:admin2_code":"58.0",
    "gn:asciiname":"Huerta Grande Norte",
    "gn:country_code":"MX",
    "gn:dem":1333,
    "gn:feature_class":"P",
    "gn:feature_code":"PPL",
    "gn:name":"Huerta Grande Norte",
    "gn:population":217,
    "gn:timezone":"America/Mexico_City",
    "iso:country":"MX",
    "wof:name":"Huerta Grande Norte",
    "wof:placetype":"locality",
    "wof:population":217
},
  "geometry": {"coordinates":[-99.88424000000001,18.28935],"type":"Point"}
}