{
  "type": "Feature",
  "properties": {
    "gn:admin1_code":"21.0",
    "gn:admin2_code":"213.0",
    "gn:asciiname":"La Libertad",
    "gn:country_code":"MX",
    "gn:dem":626,
    "gn:feature_class":"P",
    "gn:feature_code":"PPL",
    "gn:name":"La Libertad",
    "gn:population":0,
    "gn:timezone":"America/Mexico_City",
    "iso:country":"MX",
    "name:spa_x_preferred":[
        "La Libertad"
    ],
    "wof:name":"La Libertad",
    "wof:placetype":"locality"
},
  "geometry": {"coordinates":[-97.76311,20.29085],"type":"Point"}
}