{
  "type": "Feature",
  "properties": {
    "gn:admin1_code":"30",
    "gn:admin2_code":"201.0",
    "gn:asciiname":"Atexoxocapa",
    "gn:country_code":"MX",
    "gn:dem":1154,
    "gn:feature_class":"P",
    "gn:feature_code":"PPL",
    "gn:name":"Atexoxocapa",
    "gn:population":0,
    "gn:timezone":"America/Mexico_City",
    "iso:country":"MX",
    "name:spa_x_preferred":[
        "Atexoxocapa"
    ],
    "wof:name":"Atexoxocapa",
    "wof:placetype":"locality"
},
  "geometry": {"coordinates":[-96.94436,18.68274],"type":"Point"}
}