{
  "type": "Feature",
  "properties": {
    "gn:admin1_code":"12",
    "gn:admin2_code":"80.0",
    "gn:asciiname":"La India (La India Calosa)",
    "gn:country_code":"MX",
    "gn:dem":28,
    "gn:feature_class":"P",
    "gn:feature_code":"PPL",
    "gn:name":"La India (La India Calosa)",
    "gn:population":7,
    "gn:timezone":"America/Mexico_City",
    "iso:country":"MX",
    "wof:name":"La India (La India Calosa)",
    "wof:placetype":"locality",
    "wof:population":7
},
  "geometry": {"coordinates":[-98.63357999999999,16.58698],"type":"Point"}
}