{
  "type": "Feature",
  "properties": {
    "gn:admin1_code":"6",
    "gn:admin2_code":"60.0",
    "gn:asciiname":"Real de Avila",
    "gn:country_code":"MX",
    "gn:dem":2013,
    "gn:feature_class":"P",
    "gn:feature_code":"PPL",
    "gn:name":"Real de Avila",
    "gn:population":0,
    "gn:timezone":"America/Chihuahua",
    "iso:country":"MX",
    "name:spa_x_preferred":[
        "Real de Avila"
    ],
    "wof:name":"Real de Avila",
    "wof:placetype":"locality"
},
  "geometry": {"coordinates":[-105.81126,26.72756],"type":"Point"}
}