{
  "type": "Feature",
  "properties": {
    "gn:admin1_code":"20",
    "gn:admin2_code":"489.0",
    "gn:asciiname":"Guadalupe del Tambor",
    "gn:country_code":"MX",
    "gn:dem":658,
    "gn:feature_class":"P",
    "gn:feature_code":"PPL",
    "gn:name":"Guadalupe del Tambor",
    "gn:population":437,
    "gn:timezone":"America/Mexico_City",
    "iso:country":"MX",
    "wof:name":"Guadalupe del Tambor",
    "wof:placetype":"locality",
    "wof:population":437
},
  "geometry": {"coordinates":[-97.64139,16.42306],"type":"Point"}
}