{
  "type": "Feature",
  "properties": {
    "gn:admin1_code":"15.0",
    "gn:admin2_code":"123.0",
    "gn:asciiname":"El Platano",
    "gn:country_code":"MX",
    "gn:dem":864,
    "gn:feature_class":"P",
    "gn:feature_code":"PPL",
    "gn:name":"El Pl\u00e1tano",
    "gn:population":0,
    "gn:timezone":"America/Mexico_City",
    "iso:country":"MX",
    "name:spa_x_preferred":[
        "El Pl\u00e1tano"
    ],
    "wof:name":"El Platano",
    "wof:placetype":"locality"
},
  "geometry": {"coordinates":[-100.53366,18.8975],"type":"Point"}
}