{
  "type": "Feature",
  "properties": {
    "gn:admin1_code":"30",
    "gn:admin2_code":"175.0",
    "gn:asciiname":"La Higuera",
    "gn:country_code":"MX",
    "gn:dem":113,
    "gn:feature_class":"P",
    "gn:feature_code":"PPL",
    "gn:name":"La Higuera",
    "gn:population":7,
    "gn:timezone":"America/Mexico_City",
    "iso:country":"MX",
    "wof:name":"La Higuera",
    "wof:placetype":"locality",
    "wof:population":7
},
  "geometry": {"coordinates":[-97.54611,20.57528],"type":"Point"}
}