{
  "type": "Feature",
  "properties": {
    "gn:admin1_code":"21",
    "gn:admin2_code":"195.0",
    "gn:asciiname":"Llano Grande Uno",
    "gn:country_code":"MX",
    "gn:dem":2345,
    "gn:feature_class":"P",
    "gn:feature_code":"PPL",
    "gn:name":"Llano Grande Uno",
    "gn:population":154,
    "gn:timezone":"America/Mexico_City",
    "iso:country":"MX",
    "wof:name":"Llano Grande Uno",
    "wof:placetype":"locality",
    "wof:population":154
},
  "geometry": {"coordinates":[-97.16618,18.48851],"type":"Point"}
}