{
  "type": "Feature",
  "properties": {
    "gn:admin1_code":"25",
    "gn:admin2_code":"6.0",
    "gn:asciiname":"Los Cascabeles",
    "gn:country_code":"MX",
    "gn:dem":61,
    "gn:feature_class":"P",
    "gn:feature_code":"PPL",
    "gn:name":"Los Cascabeles",
    "gn:population":0,
    "gn:timezone":"America/Mazatlan",
    "iso:country":"MX",
    "name:spa_x_preferred":[
        "Los Cascabeles"
    ],
    "wof:name":"Los Cascabeles",
    "wof:placetype":"locality"
},
  "geometry": {"coordinates":[-107.30456,24.59506],"type":"Point"}
}