{
  "type": "Feature",
  "properties": {
    "gn:admin1_code":"26",
    "gn:admin2_code":"18.0",
    "gn:asciiname":"Andres Lopez Castro",
    "gn:country_code":"MX",
    "gn:dem":22,
    "gn:feature_class":"P",
    "gn:feature_code":"PPL",
    "gn:name":"Andr\u00e9s L\u00f3pez Castro",
    "gn:population":7,
    "gn:timezone":"America/Hermosillo",
    "iso:country":"MX",
    "name:und_x_variant":[
        "Andr\u00e9s L\u00f3pez Castro"
    ],
    "wof:name":"Andres Lopez Castro",
    "wof:placetype":"locality",
    "wof:population":7
},
  "geometry": {"coordinates":[-110.07611,27.46278],"type":"Point"}
}