{
  "type": "Feature",
  "properties": {
    "gn:admin1_code":"6",
    "gn:admin2_code":"62.0",
    "gn:asciiname":"Colonia Altamirano",
    "gn:country_code":"MX",
    "gn:dem":1193,
    "gn:feature_class":"P",
    "gn:feature_code":"PPL",
    "gn:name":"Colonia Altamirano",
    "gn:population":0,
    "gn:timezone":"America/Chihuahua",
    "iso:country":"MX",
    "name:und_x_variant":[
        "Loma Altamirano",
        "Colonia Altamirano",
        "Loma Alta"
    ],
    "wof:name":"Colonia Altamirano",
    "wof:placetype":"locality"
},
  "geometry": {"coordinates":[-105.35006,28.12882],"type":"Point"}
}