{
  "type": "Feature",
  "properties": {
    "gn:admin1_code":"10.0",
    "gn:admin2_code":"2.0",
    "gn:asciiname":"El Salto de Camellones",
    "gn:country_code":"MX",
    "gn:dem":2300,
    "gn:feature_class":"P",
    "gn:feature_code":"PPL",
    "gn:name":"El Salto de Camellones",
    "gn:population":0,
    "gn:timezone":"America/Monterrey",
    "iso:country":"MX",
    "name:spa_x_preferred":[
        "El Salto de Camellones"
    ],
    "name:und_x_variant":[
        "El Salto"
    ],
    "wof:name":"El Salto de Camellones",
    "wof:placetype":"locality"
},
  "geometry": {"coordinates":[-106.24563999999999,25.0579],"type":"Point"}
}