{
  "type": "Feature",
  "properties": {
    "gn:admin1_code":"31",
    "gn:admin2_code":"52.0",
    "gn:asciiname":"Santa Cruz Pachon",
    "gn:country_code":"MX",
    "gn:dem":17,
    "gn:feature_class":"P",
    "gn:feature_code":"PPL",
    "gn:name":"Santa Cruz Pach\u00f3n",
    "gn:population":231,
    "gn:timezone":"America/Merida",
    "iso:country":"MX",
    "name:und_x_variant":[
        "Santa Cruz Pach\u00f3n"
    ],
    "wof:name":"Santa Cruz Pachon",
    "wof:placetype":"locality",
    "wof:population":231
},
  "geometry": {"coordinates":[-89.28194000000001,21.07722],"type":"Point"}
}