{
  "type": "Feature",
  "properties": {
    "gn:admin1_code":"5.0",
    "gn:admin2_code":"77.0",
    "gn:asciiname":"Istilja",
    "gn:country_code":"MX",
    "gn:dem":92,
    "gn:feature_class":"P",
    "gn:feature_code":"PPL",
    "gn:name":"Istilj\u00e1",
    "gn:population":0,
    "gn:timezone":"America/Mexico_City",
    "iso:country":"MX",
    "name:spa_x_preferred":[
        "Istilj\u00e1"
    ],
    "wof:name":"Istilja",
    "wof:placetype":"locality"
},
  "geometry": {"coordinates":[-92.16932,17.36694],"type":"Point"}
}