{
  "type": "Feature",
  "properties": {
    "gn:admin1_code":"10",
    "gn:admin2_code":"34",
    "gn:asciiname":"Las Joyas",
    "gn:country_code":"MX",
    "gn:dem":1742,
    "gn:feature_class":"P",
    "gn:feature_code":"PPL",
    "gn:name":"Las Joyas",
    "gn:population":24,
    "gn:timezone":"America/Monterrey",
    "iso:country":"MX",
    "wof:name":"Las Joyas",
    "wof:placetype":"locality",
    "wof:population":24
},
  "geometry": {"coordinates":[-106.27394,24.4711],"type":"Point"}
}