{
  "type": "Feature",
  "properties": {
    "gn:admin1_code":"26.0",
    "gn:admin2_code":"27.0",
    "gn:asciiname":"Puente Grande",
    "gn:country_code":"MX",
    "gn:dem":1149,
    "gn:feature_class":"P",
    "gn:feature_code":"PPL",
    "gn:name":"Puente Grande",
    "gn:population":0,
    "gn:timezone":"America/Hermosillo",
    "iso:country":"MX",
    "name:spa_x_preferred":[
        "Puente Grande"
    ],
    "wof:name":"Puente Grande",
    "wof:placetype":"locality"
},
  "geometry": {"coordinates":[-109.56901000000001,30.87461],"type":"Point"}
}