{
  "type": "Feature",
  "properties": {
    "gn:admin1_code":"10",
    "gn:admin2_code":"18.0",
    "gn:asciiname":"Las Tiendas",
    "gn:country_code":"MX",
    "gn:dem":1753,
    "gn:feature_class":"P",
    "gn:feature_code":"PPL",
    "gn:name":"Las Tiendas",
    "gn:population":0,
    "gn:timezone":"America/Monterrey",
    "iso:country":"MX",
    "name:und_x_variant":[
        "Rancho Las Tiendas",
        "Las Tiendas"
    ],
    "wof:name":"Las Tiendas",
    "wof:placetype":"locality"
},
  "geometry": {"coordinates":[-105.38826,25.58925],"type":"Point"}
}