{
  "type": "Feature",
  "properties": {
    "gn:admin1_code":"32",
    "gn:admin2_code":"29.0",
    "gn:asciiname":"Campo Dieciseis (La Honda)",
    "gn:country_code":"MX",
    "gn:dem":2127,
    "gn:feature_class":"P",
    "gn:feature_code":"PPL",
    "gn:name":"Campo Diecis\u00e9is (La Honda)",
    "gn:population":235,
    "gn:timezone":"America/Mexico_City",
    "iso:country":"MX",
    "wof:name":"Campo Dieciseis (La Honda)",
    "wof:placetype":"locality",
    "wof:population":235
},
  "geometry": {"coordinates":[-103.40754,24.05507],"type":"Point"}
}