{
  "type": "Feature",
  "properties": {
    "gn:admin1_code":"12",
    "gn:admin2_code":"53.0",
    "gn:asciiname":"Plan Grande",
    "gn:country_code":"MX",
    "gn:dem":184,
    "gn:feature_class":"P",
    "gn:feature_code":"PPL",
    "gn:name":"Plan Grande",
    "gn:population":111,
    "gn:timezone":"America/Mexico_City",
    "iso:country":"MX",
    "wof:name":"Plan Grande",
    "wof:placetype":"locality",
    "wof:population":111
},
  "geometry": {"coordinates":[-99.50139,17.02944],"type":"Point"}
}