{
  "type": "Feature",
  "properties": {
    "gn:admin1_code":"5",
    "gn:admin2_code":"57.0",
    "gn:asciiname":"Buenavista",
    "gn:country_code":"MX",
    "gn:dem":2435,
    "gn:feature_class":"P",
    "gn:feature_code":"PPL",
    "gn:name":"Buenavista",
    "gn:population":212,
    "gn:timezone":"America/Mexico_City",
    "iso:country":"MX",
    "wof:name":"Buenavista",
    "wof:placetype":"locality",
    "wof:population":212
},
  "geometry": {"coordinates":[-92.23667,15.28194],"type":"Point"}
}