{
  "type": "Feature",
  "properties": {
    "gn:admin1_code":"14.0",
    "gn:admin2_code":"103.0",
    "gn:asciiname":"Las Coronas",
    "gn:country_code":"MX",
    "gn:dem":1149,
    "gn:feature_class":"P",
    "gn:feature_code":"PPL",
    "gn:name":"Las Coronas",
    "gn:population":0,
    "gn:timezone":"America/Mexico_City",
    "iso:country":"MX",
    "name:spa_x_preferred":[
        "Las Coronas"
    ],
    "wof:name":"Las Coronas",
    "wof:placetype":"locality"
},
  "geometry": {"coordinates":[-103.54257,19.39895],"type":"Point"}
}