{
  "type": "Feature",
  "properties": {
    "gn:admin1_code":"25",
    "gn:admin2_code":"14",
    "gn:asciiname":"Las Mimbres",
    "gn:country_code":"MX",
    "gn:dem":256,
    "gn:feature_class":"P",
    "gn:feature_code":"PPL",
    "gn:name":"Las Mimbres",
    "gn:population":15,
    "gn:timezone":"America/Mazatlan",
    "iso:country":"MX",
    "wof:name":"Las Mimbres",
    "wof:placetype":"locality",
    "wof:population":15
},
  "geometry": {"coordinates":[-105.68777,23.14524],"type":"Point"}
}