{
  "type": "Feature",
  "properties": {
    "gn:admin1_code":"16",
    "gn:admin2_code":"102",
    "gn:asciiname":"Costo",
    "gn:country_code":"MX",
    "gn:dem":1851,
    "gn:feature_class":"P",
    "gn:feature_code":"PPL",
    "gn:name":"Costo",
    "gn:population":51,
    "gn:timezone":"America/Mexico_City",
    "iso:country":"MX",
    "wof:name":"Costo",
    "wof:placetype":"locality",
    "wof:population":51
},
  "geometry": {"coordinates":[-102.065,19.44778],"type":"Point"}
}