{
  "type": "Feature",
  "properties": {
    "gn:admin1_code":"14",
    "gn:admin2_code":"13",
    "gn:asciiname":"Los Mesones",
    "gn:country_code":"MX",
    "gn:dem":1902,
    "gn:feature_class":"P",
    "gn:feature_code":"PPL",
    "gn:name":"Los Mesones",
    "gn:population":42,
    "gn:timezone":"America/Mexico_City",
    "iso:country":"MX",
    "wof:name":"Los Mesones",
    "wof:placetype":"locality",
    "wof:population":42
},
  "geometry": {"coordinates":[-102.50194,20.57139],"type":"Point"}
}