{
  "type": "Feature",
  "properties": {
    "gn:admin1_code":"7",
    "gn:admin2_code":"31.0",
    "gn:asciiname":"El Paso (Maricela Martinez Martinez)",
    "gn:country_code":"MX",
    "gn:dem":488,
    "gn:feature_class":"P",
    "gn:feature_code":"PPL",
    "gn:name":"El Paso (Maricela Mart\u00ednez Mart\u00ednez)",
    "gn:population":7,
    "gn:timezone":"America/Monterrey",
    "iso:country":"MX",
    "name:und_x_variant":[
        "El Paso (Maricela Mart\u00ednez Mart\u00ednez)"
    ],
    "wof:name":"El Paso (Maricela Martinez Martinez)",
    "wof:placetype":"locality",
    "wof:population":7
},
  "geometry": {"coordinates":[-101.5637,27.07916],"type":"Point"}
}