{
  "type": "Feature",
  "properties": {
    "gn:admin1_code":"25",
    "gn:admin2_code":"14.0",
    "gn:asciiname":"La Mimbre",
    "gn:country_code":"MX",
    "gn:dem":604,
    "gn:feature_class":"P",
    "gn:feature_code":"PPL",
    "gn:name":"La Mimbre",
    "gn:population":0,
    "gn:timezone":"America/Mazatlan",
    "iso:country":"MX",
    "name:spa_x_preferred":[
        "La Mimbre"
    ],
    "wof:name":"La Mimbre",
    "wof:placetype":"locality"
},
  "geometry": {"coordinates":[-105.54718,23.07813],"type":"Point"}
}