{
  "type": "Feature",
  "properties": {
    "gn:admin1_code":"14.0",
    "gn:admin2_code":"58.0",
    "gn:asciiname":"Juanacatlan",
    "gn:country_code":"MX",
    "gn:dem":2261,
    "gn:feature_class":"P",
    "gn:feature_code":"PPL",
    "gn:name":"Juanacatl\u00e1n",
    "gn:population":0,
    "gn:timezone":"America/Mexico_City",
    "iso:country":"MX",
    "wof:name":"Juanacatlan",
    "wof:placetype":"locality"
},
  "geometry": {"coordinates":[-104.69750000000001,20.59616],"type":"Point"}
}