{
  "type": "Feature",
  "properties": {
    "gn:admin1_code":"19",
    "gn:admin2_code":"38.0",
    "gn:asciiname":"Cabezones",
    "gn:country_code":"MX",
    "gn:dem":462,
    "gn:feature_class":"P",
    "gn:feature_code":"PPL",
    "gn:name":"Cabezones",
    "gn:population":0,
    "gn:timezone":"America/Monterrey",
    "iso:country":"MX",
    "name:por_x_preferred":[
        "Cabezones"
    ],
    "name:spa_x_preferred":[
        "Cabezones"
    ],
    "wof:name":"Cabezones",
    "wof:placetype":"locality"
},
  "geometry": {"coordinates":[-99.74243,24.99152],"type":"Point"}
}