{
  "type": "Feature",
  "properties": {
    "gn:admin1_code":"30.0",
    "gn:admin2_code":"121.0",
    "gn:asciiname":"Las Palmas",
    "gn:country_code":"MX",
    "gn:dem":50,
    "gn:feature_class":"P",
    "gn:feature_code":"PPL",
    "gn:name":"Las Palmas",
    "gn:population":10,
    "gn:timezone":"America/Mexico_City",
    "iso:country":"MX",
    "name:spa_x_preferred":[
        "Las Palmas"
    ],
    "wof:name":"Las Palmas",
    "wof:placetype":"locality",
    "wof:population":10
},
  "geometry": {"coordinates":[-98.04443999999999,21.7125],"type":"Point"}
}