{
  "type": "Feature",
  "properties": {
    "gn:admin1_code":"21",
    "gn:admin2_code":"116.0",
    "gn:asciiname":"Rincon Progreso",
    "gn:country_code":"MX",
    "gn:dem":1690,
    "gn:feature_class":"P",
    "gn:feature_code":"PPL",
    "gn:name":"Rinc\u00f3n Progreso",
    "gn:population":83,
    "gn:timezone":"America/Mexico_City",
    "iso:country":"MX",
    "name:und_x_variant":[
        "Rinc\u00f3n Progreso"
    ],
    "wof:name":"Rincon Progreso",
    "wof:placetype":"locality",
    "wof:population":83
},
  "geometry": {"coordinates":[-97.03660000000001,19.26374],"type":"Point"}
}