{
  "type": "Feature",
  "properties": {
    "gn:admin1_code":"10.0",
    "gn:asciiname":"Cienega Grande",
    "gn:country_code":"MX",
    "gn:dem":2661,
    "gn:feature_class":"P",
    "gn:feature_code":"PPL",
    "gn:name":"Ci\u00e9nega Grande",
    "gn:population":0,
    "gn:timezone":"America/Chihuahua",
    "iso:country":"MX",
    "name:spa_x_preferred":[
        "Ci\u00e9nega Grande"
    ],
    "name:und_x_variant":[
        "Rancho Ci\u00e9nega Grande",
        "Ci\u00e9naga Grande"
    ],
    "wof:name":"Cienega Grande",
    "wof:placetype":"locality"
},
  "geometry": {"coordinates":[-106.37609,26.37737000000001],"type":"Point"}
}