{
  "type": "Feature",
  "properties": {
    "gn:admin1_code":"16",
    "gn:admin2_code":"61.0",
    "gn:asciiname":"Manzana la Cienega",
    "gn:country_code":"MX",
    "gn:dem":2438,
    "gn:feature_class":"P",
    "gn:feature_code":"PPL",
    "gn:name":"Manzana la Ci\u00e9nega",
    "gn:population":257,
    "gn:timezone":"America/Mexico_City",
    "iso:country":"MX",
    "name:und_x_variant":[
        "Manzana la Ci\u00e9nega"
    ],
    "wof:name":"Manzana la Cienega",
    "wof:placetype":"locality",
    "wof:population":257
},
  "geometry": {"coordinates":[-100.38916999999999,19.60528],"type":"Point"}
}