{
  "type": "Feature",
  "properties": {
    "gn:admin1_code":"6",
    "gn:admin2_code":"27",
    "gn:asciiname":"Repogueachi",
    "gn:country_code":"MX",
    "gn:dem":1908,
    "gn:feature_class":"P",
    "gn:feature_code":"PPL",
    "gn:name":"Repogueachi",
    "gn:population":43,
    "gn:timezone":"America/Chihuahua",
    "iso:country":"MX",
    "wof:name":"Repogueachi",
    "wof:placetype":"locality",
    "wof:population":43
},
  "geometry": {"coordinates":[-107.48186,27.46048],"type":"Point"}
}