{
  "type": "Feature",
  "properties": {
    "gn:admin1_code":"23.0",
    "gn:asciiname":"Sinai",
    "gn:country_code":"MX",
    "gn:dem":3,
    "gn:feature_class":"P",
    "gn:feature_code":"PPL",
    "gn:name":"Sina\u00ed",
    "gn:population":0,
    "gn:timezone":"America/Cancun",
    "iso:country":"MX",
    "name:spa_x_preferred":[
        "Sina\u00ed"
    ],
    "wof:name":"Sinai",
    "wof:placetype":"locality"
},
  "geometry": {"coordinates":[-86.98336999999999,20.74146],"type":"Point"}
}