{
  "type": "Feature",
  "properties": {
    "gn:admin1_code":"16",
    "gn:admin2_code":"29.0",
    "gn:asciiname":"El Sesteo",
    "gn:country_code":"MX",
    "gn:dem":971,
    "gn:feature_class":"P",
    "gn:feature_code":"PPL",
    "gn:name":"El Sesteo",
    "gn:population":0,
    "gn:timezone":"America/Mexico_City",
    "iso:country":"MX",
    "name:spa_x_preferred":[
        "El Sesteo"
    ],
    "wof:name":"El Sesteo",
    "wof:placetype":"locality"
},
  "geometry": {"coordinates":[-101.56265999999999,18.8737],"type":"Point"}
}