{
  "type": "Feature",
  "properties": {
    "iso:country":"MX",
    "name:spa_x_preferred":[
        "Barrio de Cata"
    ],
    "qs:gn_adm0_cc":"MX",
    "qs:gn_local":4005270,
    "qs:gn_nam_loc":"Guanajuato, Guanajuato, Guanajuato, MX",
    "qs:gn_namadm1":"11",
    "qs:local_max":2949,
    "qs:local_sum":12132,
    "qs:localhoods":16,
    "qs:name":"Barrio de Cata",
    "qs:name_adm0":"M\u00e9xico",
    "qs:name_adm1":"Guanajuato",
    "qs:name_adm2":"Guanajuato",
    "qs:name_local":"Guanajuato",
    "qs:photo_max":150,
    "qs:photo_sum":246,
    "qs:placetype":"Suburb",
    "qs:quad_count":7,
    "qs:woe_adm0":23424900,
    "qs:woe_adm1":2346274,
    "qs:woe_adm2":12600003,
    "qs:woe_lau":0,
    "qs:woe_local":124432,
    "qs:woe_ver":"7.10.0",
    "wof:lang":[
        "spa"
    ],
    "wof:name":"Barrio de Cata",
    "wof:placetype":"neighbourhood"
},
  "geometry": {"coordinates":[-101.255447,21.027975],"type":"Point"}
}