{
  "type": "Feature",
  "properties": {
    "gn:admin1_code":"23",
    "gn:admin2_code":"4.0",
    "gn:asciiname":"Blanca Flor",
    "gn:country_code":"MX",
    "gn:dem":25,
    "gn:feature_class":"P",
    "gn:feature_code":"PPL",
    "gn:name":"Blanca Flor",
    "gn:population":0,
    "gn:timezone":"America/Cancun",
    "iso:country":"MX",
    "name:spa_x_preferred":[
        "Blanca Flor"
    ],
    "wof:name":"Blanca Flor",
    "wof:placetype":"locality"
},
  "geometry": {"coordinates":[-88.50029000000001,18.92326],"type":"Point"}
}