{
  "type": "Feature",
  "properties": {
    "gn:admin1_code":"5",
    "gn:admin2_code":"52.0",
    "gn:asciiname":"Morelia",
    "gn:country_code":"MX",
    "gn:dem":1479,
    "gn:feature_class":"P",
    "gn:feature_code":"PPL",
    "gn:name":"Morelia",
    "gn:population":0,
    "gn:timezone":"America/Mexico_City",
    "iso:country":"MX",
    "wof:name":"Morelia",
    "wof:placetype":"locality"
},
  "geometry": {"coordinates":[-91.86763000000001,16.30922],"type":"Point"}
}