{
  "type": "Feature",
  "properties": {
    "gn:admin1_code":"5",
    "gn:admin2_code":"69.0",
    "gn:asciiname":"San Lazaro",
    "gn:country_code":"MX",
    "gn:dem":16,
    "gn:feature_class":"P",
    "gn:feature_code":"PPL",
    "gn:name":"San L\u00e1zaro",
    "gn:population":8,
    "gn:timezone":"America/Mexico_City",
    "iso:country":"MX",
    "name:und_x_variant":[
        "San L\u00e1zaro"
    ],
    "wof:name":"San Lazaro",
    "wof:placetype":"locality",
    "wof:population":8
},
  "geometry": {"coordinates":[-93.21805999999999,15.64528],"type":"Point"}
}