{
  "type": "Feature",
  "properties": {
    "gn:admin1_code":"30",
    "gn:admin2_code":"81.0",
    "gn:asciiname":"Los Capulines",
    "gn:country_code":"MX",
    "gn:dem":1427,
    "gn:feature_class":"P",
    "gn:feature_code":"PPL",
    "gn:name":"Los Capulines",
    "gn:population":89,
    "gn:timezone":"America/Mexico_City",
    "iso:country":"MX",
    "wof:name":"Los Capulines",
    "wof:placetype":"locality",
    "wof:population":89
},
  "geometry": {"coordinates":[-97.14082999999999,18.89361],"type":"Point"}
}