{
  "type": "Feature",
  "properties": {
    "gn:admin1_code":"12",
    "gn:admin2_code":"48.0",
    "gn:asciiname":"La Barrita (Playa la Barrita)",
    "gn:country_code":"MX",
    "gn:dem":11,
    "gn:feature_class":"P",
    "gn:feature_code":"PPL",
    "gn:name":"La Barrita (Playa la Barrita)",
    "gn:population":99,
    "gn:timezone":"America/Mexico_City",
    "iso:country":"MX",
    "wof:name":"La Barrita (Playa la Barrita)",
    "wof:placetype":"locality",
    "wof:population":99
},
  "geometry": {"coordinates":[-101.18114,17.41181],"type":"Point"}
}