{
  "type": "Feature",
  "properties": {
    "gn:admin1_code":"5",
    "gn:admin2_code":"82",
    "gn:asciiname":"Fraccion Recreo",
    "gn:country_code":"MX",
    "gn:dem":1364,
    "gn:feature_class":"P",
    "gn:feature_code":"PPL",
    "gn:name":"Fracci\u00f3n Recreo",
    "gn:population":41,
    "gn:timezone":"America/Mexico_City",
    "iso:country":"MX",
    "name:und_x_variant":[
        "Fracci\u00f3n Recreo"
    ],
    "wof:name":"Fraccion Recreo",
    "wof:placetype":"locality",
    "wof:population":41
},
  "geometry": {"coordinates":[-92.32722,17.03139],"type":"Point"}
}