{
  "type": "Feature",
  "properties": {
    "gn:admin1_code":"16.0",
    "gn:admin2_code":"8.0",
    "gn:asciiname":"La Cofradia de Ostula",
    "gn:country_code":"MX",
    "gn:dem":232,
    "gn:feature_class":"P",
    "gn:feature_code":"PPL",
    "gn:name":"La Cofrad\u00eda de Ostula",
    "gn:population":0,
    "gn:timezone":"America/Mexico_City",
    "iso:country":"MX",
    "name:spa_x_preferred":[
        "La Cofrad\u00eda de Ostula"
    ],
    "name:und_x_variant":[
        "Cofrad\u00eda",
        "Cofrad\u00eda de Ostula"
    ],
    "wof:name":"La Cofradia de Ostula",
    "wof:placetype":"locality"
},
  "geometry": {"coordinates":[-103.42372,18.55408],"type":"Point"}
}