{
  "type": "Feature",
  "properties": {
    "gn:admin1_code":"20",
    "gn:admin2_code":"261.0",
    "gn:asciiname":"Santa Cruz el Limon",
    "gn:country_code":"MX",
    "gn:dem":1623,
    "gn:feature_class":"P",
    "gn:feature_code":"PPL",
    "gn:name":"Santa Cruz el Lim\u00f3n",
    "gn:population":338,
    "gn:timezone":"America/Mexico_City",
    "iso:country":"MX",
    "name:und_x_variant":[
        "Santa Cruz el Lim\u00f3n"
    ],
    "wof:name":"Santa Cruz el Limon",
    "wof:placetype":"locality",
    "wof:population":338
},
  "geometry": {"coordinates":[-98.01278000000001,17.9025],"type":"Point"}
}