{
  "type": "Feature",
  "properties": {
    "gn:admin1_code":"5.0",
    "gn:admin2_code":"53.0",
    "gn:asciiname":"Matasanos",
    "gn:country_code":"MX",
    "gn:dem":1700,
    "gn:feature_class":"P",
    "gn:feature_code":"PPL",
    "gn:name":"Matasanos",
    "gn:population":0,
    "gn:timezone":"America/Mexico_City",
    "iso:country":"MX",
    "name:spa_x_preferred":[
        "Matasanos"
    ],
    "wof:name":"Matasanos",
    "wof:placetype":"locality"
},
  "geometry": {"coordinates":[-92.1872,15.31943],"type":"Point"}
}