{
  "type": "Feature",
  "properties": {
    "gn:admin1_code":"5",
    "gn:admin2_code":"80.0",
    "gn:asciiname":"El Bajio",
    "gn:country_code":"MX",
    "gn:dem":1883,
    "gn:feature_class":"P",
    "gn:feature_code":"PPL",
    "gn:name":"El Baj\u00edo",
    "gn:population":306,
    "gn:timezone":"America/Mexico_City",
    "iso:country":"MX",
    "name:und_x_variant":[
        "El Baj\u00edo"
    ],
    "wof:name":"El Bajio",
    "wof:placetype":"locality",
    "wof:population":306
},
  "geometry": {"coordinates":[-92.25639,15.53917],"type":"Point"}
}