{
  "type": "Feature",
  "properties": {
    "gn:admin1_code":"14.0",
    "gn:admin2_code":"28.0",
    "gn:asciiname":"Canada Grande",
    "gn:country_code":"MX",
    "gn:dem":2025,
    "gn:feature_class":"P",
    "gn:feature_code":"PPL",
    "gn:name":"Ca\u00f1ada Grande",
    "gn:population":0,
    "gn:timezone":"America/Mexico_City",
    "iso:country":"MX",
    "name:spa_x_preferred":[
        "Ca\u00f1ada Grande"
    ],
    "wof:name":"Canada Grande",
    "wof:placetype":"locality"
},
  "geometry": {"coordinates":[-104.39315999999999,20.25761],"type":"Point"}
}