{
  "type": "Feature",
  "properties": {
    "gn:admin1_code":"31",
    "gn:admin2_code":"55",
    "gn:asciiname":"San Claudio",
    "gn:country_code":"MX",
    "gn:dem":18,
    "gn:feature_class":"P",
    "gn:feature_code":"PPL",
    "gn:name":"San Claudio",
    "gn:population":17,
    "gn:timezone":"America/Merida",
    "iso:country":"MX",
    "wof:name":"San Claudio",
    "wof:placetype":"locality",
    "wof:population":17
},
  "geometry": {"coordinates":[-89.86583,20.54694],"type":"Point"}
}