{
  "type": "Feature",
  "properties": {
    "gn:admin1_code":"28.0",
    "gn:admin2_code":"2.0",
    "gn:asciiname":"Juliana",
    "gn:country_code":"MX",
    "gn:dem":15,
    "gn:feature_class":"P",
    "gn:feature_code":"PPL",
    "gn:name":"Juliana",
    "gn:population":3,
    "gn:timezone":"America/Monterrey",
    "iso:country":"MX",
    "name:deu_x_preferred":[
        "Juliana"
    ],
    "name:epo_x_preferred":[
        "Juliana"
    ],
    "name:fin_x_preferred":[
        "Juliana"
    ],
    "name:lat_x_preferred":[
        "Juliana"
    ],
    "name:ltz_x_preferred":[
        "Juliana"
    ],
    "name:nld_x_preferred":[
        "Juliana"
    ],
    "name:pol_x_preferred":[
        "Juliana"
    ],
    "name:slk_x_preferred":[
        "Juliana"
    ],
    "name:slv_x_preferred":[
        "Juliana"
    ],
    "name:spa_x_preferred":[
        "Juliana"
    ],
    "wof:name":"Juliana",
    "wof:placetype":"locality",
    "wof:population":3
},
  "geometry": {"coordinates":[-97.91404,22.71924],"type":"Point"}
}