{
  "type": "Feature",
  "properties": {
    "gn:admin1_code":"26.0",
    "gn:admin2_code":"30.0",
    "gn:asciiname":"Gorgus",
    "gn:country_code":"MX",
    "gn:dem":141,
    "gn:feature_class":"P",
    "gn:feature_code":"PPL",
    "gn:name":"Gorgus",
    "gn:population":0,
    "gn:timezone":"America/Hermosillo",
    "iso:country":"MX",
    "name:und_x_variant":[
        "Gargos",
        "Gargus",
        "Gorguz"
    ],
    "wof:name":"Gorgus",
    "wof:placetype":"locality"
},
  "geometry": {"coordinates":[-111.13338,28.93508],"type":"Point"}
}