{
  "type": "Feature",
  "properties": {
    "gn:admin1_code":"24",
    "gn:admin2_code":"33.0",
    "gn:asciiname":"La Cocinera",
    "gn:country_code":"MX",
    "gn:dem":2152,
    "gn:feature_class":"P",
    "gn:feature_code":"PPL",
    "gn:name":"La Cocinera",
    "gn:population":0,
    "gn:timezone":"America/Mexico_City",
    "iso:country":"MX",
    "wof:name":"La Cocinera",
    "wof:placetype":"locality"
},
  "geometry": {"coordinates":[-101.78333000000001,23.43333],"type":"Point"}
}