{
  "type": "Feature",
  "properties": {
    "gn:admin1_code":"6",
    "gn:admin2_code":"48.0",
    "gn:asciiname":"Los Ortega",
    "gn:country_code":"MX",
    "gn:dem":1716,
    "gn:feature_class":"P",
    "gn:feature_code":"PPL",
    "gn:name":"Los Ortega",
    "gn:population":0,
    "gn:timezone":"America/Chihuahua",
    "iso:country":"MX",
    "name:spa_x_preferred":[
        "Los Ortega"
    ],
    "wof:name":"Los Ortega",
    "wof:placetype":"locality"
},
  "geometry": {"coordinates":[-107.37278000000001,29.4847],"type":"Point"}
}