{
  "type": "Feature",
  "properties": {
    "gn:admin1_code":"4.0",
    "gn:asciiname":"La Giralda",
    "gn:country_code":"MX",
    "gn:dem":274,
    "gn:feature_class":"P",
    "gn:feature_code":"PPL",
    "gn:name":"La Giralda",
    "gn:population":0,
    "gn:timezone":"America/Merida",
    "iso:country":"MX",
    "name:spa_x_preferred":[
        "La Giralda"
    ],
    "wof:name":"La Giralda",
    "wof:placetype":"locality"
},
  "geometry": {"coordinates":[-89.50724,18.34768],"type":"Point"}
}