{
  "type": "Feature",
  "properties": {
    "gn:admin1_code":"20.0",
    "gn:admin2_code":"392.0",
    "gn:asciiname":"Cuauhtemoc Yutecosa",
    "gn:country_code":"MX",
    "gn:dem":2581,
    "gn:feature_class":"P",
    "gn:feature_code":"PPL",
    "gn:name":"Cuauht\u00e9moc Yutecosa",
    "gn:population":0,
    "gn:timezone":"America/Mexico_City",
    "iso:country":"MX",
    "name:spa_x_preferred":[
        "Cuauht\u00e9moc Yutecosa"
    ],
    "wof:name":"Cuauhtemoc Yutecosa",
    "wof:placetype":"locality"
},
  "geometry": {"coordinates":[-97.67336,16.935],"type":"Point"}
}