{
  "type": "Feature",
  "properties": {
    "gn:admin1_code":"1.0",
    "gn:admin2_code":"5.0",
    "gn:asciiname":"Corral Colorado",
    "gn:country_code":"MX",
    "gn:dem":2144,
    "gn:feature_class":"P",
    "gn:feature_code":"PPL",
    "gn:name":"Corral Colorado",
    "gn:population":0,
    "gn:timezone":"America/Mexico_City",
    "iso:country":"MX",
    "wof:name":"Corral Colorado",
    "wof:placetype":"locality"
},
  "geometry": {"coordinates":[-102.54577999999999,21.93151],"type":"Point"}
}