{
  "type": "Feature",
  "properties": {
    "gn:admin1_code":"25",
    "gn:admin2_code":"6.0",
    "gn:asciiname":"Contreras",
    "gn:country_code":"MX",
    "gn:dem":180,
    "gn:feature_class":"P",
    "gn:feature_code":"PPL",
    "gn:name":"Contreras",
    "gn:population":0,
    "gn:timezone":"America/Mazatlan",
    "iso:country":"MX",
    "name:spa_x_preferred":[
        "Contreras"
    ],
    "wof:name":"Contreras",
    "wof:placetype":"locality"
},
  "geometry": {"coordinates":[-107.13488,24.95517000000001],"type":"Point"}
}