{
  "type": "Feature",
  "properties": {
    "gn:admin1_code":"13",
    "gn:admin2_code":"4.0",
    "gn:asciiname":"Ejido de Calabazas",
    "gn:country_code":"MX",
    "gn:dem":2198,
    "gn:feature_class":"P",
    "gn:feature_code":"PPL",
    "gn:name":"Ejido de Calabazas",
    "gn:population":387,
    "gn:timezone":"America/Mexico_City",
    "iso:country":"MX",
    "wof:name":"Ejido de Calabazas",
    "wof:placetype":"locality",
    "wof:population":387
},
  "geometry": {"coordinates":[-98.39839000000001,20.33778],"type":"Point"}
}