{
  "type": "Feature",
  "properties": {
    "gn:admin1_code":"17",
    "gn:admin2_code":"9",
    "gn:asciiname":"Tezontlalpa",
    "gn:country_code":"MX",
    "gn:dem":2218,
    "gn:feature_class":"P",
    "gn:feature_code":"PPL",
    "gn:name":"Tezontlalpa",
    "gn:population":48,
    "gn:timezone":"America/Mexico_City",
    "iso:country":"MX",
    "wof:name":"Tezontlalpa",
    "wof:placetype":"locality",
    "wof:population":48
},
  "geometry": {"coordinates":[-99.24944000000001,19.00694],"type":"Point"}
}