{
  "type": "Feature",
  "properties": {
    "gn:admin1_code":"21",
    "gn:admin2_code":"186.0",
    "gn:asciiname":"Tepehican",
    "gn:country_code":"MX",
    "gn:dem":2193,
    "gn:feature_class":"P",
    "gn:feature_code":"PPL",
    "gn:name":"Tepehic\u00e1n",
    "gn:population":475,
    "gn:timezone":"America/Mexico_City",
    "iso:country":"MX",
    "name:und_x_variant":[
        "Tepehic\u00e1n"
    ],
    "wof:name":"Tepehican",
    "wof:placetype":"locality",
    "wof:population":475
},
  "geometry": {"coordinates":[-97.51694000000001,19.8575],"type":"Point"}
}