{
  "type": "Feature",
  "properties": {
    "gn:admin1_code":"30",
    "gn:admin2_code":"170",
    "gn:asciiname":"Cumbre del Lindero",
    "gn:country_code":"MX",
    "gn:dem":764,
    "gn:feature_class":"P",
    "gn:feature_code":"PPL",
    "gn:name":"Cumbre del Lindero",
    "gn:population":22,
    "gn:timezone":"America/Mexico_City",
    "iso:country":"MX",
    "wof:name":"Cumbre del Lindero",
    "wof:placetype":"locality",
    "wof:population":22
},
  "geometry": {"coordinates":[-98.27417,20.65667],"type":"Point"}
}