{
  "type": "Feature",
  "properties": {
    "gn:admin1_code":"26",
    "gn:admin2_code":"20.0",
    "gn:asciiname":"Pozo de Crisanto",
    "gn:country_code":"MX",
    "gn:dem":639,
    "gn:feature_class":"P",
    "gn:feature_code":"PPL",
    "gn:name":"Pozo de Crisanto",
    "gn:population":0,
    "gn:timezone":"America/Hermosillo",
    "iso:country":"MX",
    "name:und_x_variant":[
        "Rancho Pozo Cricanto",
        "Pozo Crisanto",
        "Pozo de Crisanto"
    ],
    "wof:name":"Pozo de Crisanto",
    "wof:placetype":"locality"
},
  "geometry": {"coordinates":[-111.17927,29.7269],"type":"Point"}
}