{
  "type": "Feature",
  "properties": {
    "gn:admin1_code":"13",
    "gn:admin2_code":"16.0",
    "gn:asciiname":"Las Isletas",
    "gn:country_code":"MX",
    "gn:dem":2539,
    "gn:feature_class":"P",
    "gn:feature_code":"PPL",
    "gn:name":"Las Isletas",
    "gn:population":0,
    "gn:timezone":"America/Mexico_City",
    "iso:country":"MX",
    "name:spa_x_preferred":[
        "Las Isletas"
    ],
    "wof:name":"Las Isletas",
    "wof:placetype":"locality"
},
  "geometry": {"coordinates":[-98.37688,19.88815],"type":"Point"}
}