{
  "type": "Feature",
  "properties": {
    "gn:admin1_code":"28.0",
    "gn:admin2_code":"21.0",
    "gn:asciiname":"San Felipe de Jesus",
    "gn:country_code":"MX",
    "gn:dem":90,
    "gn:feature_class":"P",
    "gn:feature_code":"PPL",
    "gn:name":"San Felipe de Jes\u00fas",
    "gn:population":0,
    "gn:timezone":"America/Monterrey",
    "iso:country":"MX",
    "name:spa_x_preferred":[
        "San Felipe de Jes\u00fas"
    ],
    "wof:name":"San Felipe de Jesus",
    "wof:placetype":"locality"
},
  "geometry": {"coordinates":[-98.91639000000001,22.63528],"type":"Point"}
}