{
  "type": "Feature",
  "properties": {
    "gn:admin1_code":"11",
    "gn:admin2_code":"31.0",
    "gn:asciiname":"San Antonio de la Paz",
    "gn:country_code":"MX",
    "gn:dem":1758,
    "gn:feature_class":"P",
    "gn:feature_code":"PPL",
    "gn:name":"San Antonio de la Paz",
    "gn:population":275,
    "gn:timezone":"America/Mexico_City",
    "iso:country":"MX",
    "wof:name":"San Antonio de la Paz",
    "wof:placetype":"locality",
    "wof:population":275
},
  "geometry": {"coordinates":[-101.79861,21.02667000000001],"type":"Point"}
}