{
  "type": "Feature",
  "properties": {
    "gn:admin1_code":"10",
    "gn:admin2_code":"23",
    "gn:asciiname":"Capomal",
    "gn:country_code":"MX",
    "gn:dem":1034,
    "gn:feature_class":"P",
    "gn:feature_code":"PPL",
    "gn:name":"Capomal",
    "gn:population":42,
    "gn:timezone":"America/Monterrey",
    "iso:country":"MX",
    "wof:name":"Capomal",
    "wof:placetype":"locality",
    "wof:population":42
},
  "geometry": {"coordinates":[-105.23026000000002,23.22889],"type":"Point"}
}