{
  "type": "Feature",
  "properties": {
    "gn:admin1_code":"31",
    "gn:admin2_code":"6.0",
    "gn:asciiname":"Santa Isabel",
    "gn:country_code":"MX",
    "gn:dem":9,
    "gn:feature_class":"P",
    "gn:feature_code":"PPL",
    "gn:name":"Santa Isabel",
    "gn:population":0,
    "gn:timezone":"America/Merida",
    "iso:country":"MX",
    "wof:name":"Santa Isabel",
    "wof:placetype":"locality"
},
  "geometry": {"coordinates":[-88.82916999999998,21.22944],"type":"Point"}
}