{
  "type": "Feature",
  "properties": {
    "gn:admin1_code":"15.0",
    "gn:admin2_code":"80.0",
    "gn:asciiname":"Hacienda de Guadalupe",
    "gn:country_code":"MX",
    "gn:dem":1834,
    "gn:feature_class":"P",
    "gn:feature_code":"PPL",
    "gn:name":"Hacienda de Guadalupe",
    "gn:population":0,
    "gn:timezone":"America/Mexico_City",
    "iso:country":"MX",
    "name:spa_x_preferred":[
        "Hacienda de Guadalupe"
    ],
    "wof:name":"Hacienda de Guadalupe",
    "wof:placetype":"locality"
},
  "geometry": {"coordinates":[-100.00071,18.86788],"type":"Point"}
}