{
  "type": "Feature",
  "properties": {
    "gn:admin1_code":"10",
    "gn:admin2_code":"28.0",
    "gn:asciiname":"La Coyotada",
    "gn:country_code":"MX",
    "gn:dem":1753,
    "gn:feature_class":"P",
    "gn:feature_code":"PPL",
    "gn:name":"La Coyotada",
    "gn:population":0,
    "gn:timezone":"America/Monterrey",
    "iso:country":"MX",
    "name:spa_x_preferred":[
        "La Coyotada"
    ],
    "wof:name":"La Coyotada",
    "wof:placetype":"locality"
},
  "geometry": {"coordinates":[-104.45775,24.74472],"type":"Point"}
}