{
  "type": "Feature",
  "properties": {
    "gn:admin1_code":"15.0",
    "gn:admin2_code":"8.0",
    "gn:asciiname":"El Huicume",
    "gn:country_code":"MX",
    "gn:dem":647,
    "gn:feature_class":"P",
    "gn:feature_code":"PPL",
    "gn:name":"El Huicume",
    "gn:population":0,
    "gn:timezone":"America/Mexico_City",
    "iso:country":"MX",
    "name:spa_x_preferred":[
        "El Huicume"
    ],
    "wof:name":"El Huicume",
    "wof:placetype":"locality"
},
  "geometry": {"coordinates":[-100.38943999999999,18.75913],"type":"Point"}
}