{
  "type": "Feature",
  "properties": {
    "gn:admin1_code":"13",
    "gn:admin2_code":"24.0",
    "gn:asciiname":"Palma Antigua el Vite",
    "gn:country_code":"MX",
    "gn:dem":2058,
    "gn:feature_class":"P",
    "gn:feature_code":"PPL",
    "gn:name":"Palma Antigua el Vite",
    "gn:population":160,
    "gn:timezone":"America/Mexico_City",
    "iso:country":"MX",
    "name:spa_x_preferred":[
        "El Vite"
    ],
    "wof:name":"Palma Antigua el Vite",
    "wof:placetype":"locality",
    "wof:population":160
},
  "geometry": {"coordinates":[-98.53055999999999,20.24975],"type":"Point"}
}