{
  "type": "Feature",
  "properties": {
    "gn:admin1_code":"26",
    "gn:admin2_code":"66.0",
    "gn:asciiname":"Monte Grande",
    "gn:country_code":"MX",
    "gn:dem":450,
    "gn:feature_class":"P",
    "gn:feature_code":"PPL",
    "gn:name":"Monte Grande",
    "gn:population":5,
    "gn:timezone":"America/Hermosillo",
    "iso:country":"MX",
    "name:spa_x_preferred":[
        "Monte Grande"
    ],
    "wof:name":"Monte Grande",
    "wof:placetype":"locality",
    "wof:population":5
},
  "geometry": {"coordinates":[-110.20556000000001,29.47972],"type":"Point"}
}