{
  "type": "Feature",
  "properties": {
    "gn:admin1_code":"10",
    "gn:admin2_code":"14.0",
    "gn:asciiname":"Santa Elena del Rio",
    "gn:country_code":"MX",
    "gn:dem":1427,
    "gn:feature_class":"P",
    "gn:feature_code":"PPL",
    "gn:name":"Santa Elena del R\u00edo",
    "gn:population":0,
    "gn:timezone":"America/Monterrey",
    "iso:country":"MX",
    "name:spa_x_preferred":[
        "Santa Elena del R\u00edo"
    ],
    "wof:name":"Santa Elena del Rio",
    "wof:placetype":"locality"
},
  "geometry": {"coordinates":[-104.38225,23.52192],"type":"Point"}
}