{
  "type": "Feature",
  "properties": {
    "gn:admin1_code":"14",
    "gn:admin2_code":"97",
    "gn:asciiname":"Las Crucitas",
    "gn:country_code":"MX",
    "gn:dem":1560,
    "gn:feature_class":"P",
    "gn:feature_code":"PPL",
    "gn:name":"Las Crucitas",
    "gn:population":20,
    "gn:timezone":"America/Mexico_City",
    "iso:country":"MX",
    "wof:name":"Las Crucitas",
    "wof:placetype":"locality",
    "wof:population":20
},
  "geometry": {"coordinates":[-103.32444,20.40389],"type":"Point"}
}