{
  "type": "Feature",
  "properties": {
    "gn:admin1_code":"7",
    "gn:admin2_code":"38.0",
    "gn:asciiname":"Margaritas",
    "gn:country_code":"MX",
    "gn:dem":877,
    "gn:feature_class":"P",
    "gn:feature_code":"PPL",
    "gn:name":"Margaritas",
    "gn:population":15,
    "gn:timezone":"America/Monterrey",
    "iso:country":"MX",
    "wof:name":"Margaritas",
    "wof:placetype":"locality",
    "wof:population":15
},
  "geometry": {"coordinates":[-101.77428,28.68907],"type":"Point"}
}