{
  "type": "Feature",
  "properties": {
    "gn:admin1_code":"32",
    "gn:admin2_code":"37.0",
    "gn:asciiname":"Agustin Ramos",
    "gn:country_code":"MX",
    "gn:dem":2028,
    "gn:feature_class":"P",
    "gn:feature_code":"PPL",
    "gn:name":"Agust\u00edn Ramos",
    "gn:population":7,
    "gn:timezone":"America/Mexico_City",
    "iso:country":"MX",
    "name:und_x_variant":[
        "Agust\u00edn Ramos"
    ],
    "wof:name":"Agustin Ramos",
    "wof:placetype":"locality",
    "wof:population":7
},
  "geometry": {"coordinates":[-102.35972,22.98583],"type":"Point"}
}