{
  "type": "Feature",
  "properties": {
    "gn:admin1_code":"13",
    "gn:admin2_code":"26.0",
    "gn:asciiname":"Tetlicuil",
    "gn:country_code":"MX",
    "gn:dem":635,
    "gn:feature_class":"P",
    "gn:feature_code":"PPL",
    "gn:name":"Tetlicuil",
    "gn:population":105,
    "gn:timezone":"America/Mexico_City",
    "iso:country":"MX",
    "wof:name":"Tetlicuil",
    "wof:placetype":"locality",
    "wof:population":105
},
  "geometry": {"coordinates":[-98.49861,20.97306],"type":"Point"}
}