{
  "type": "Feature",
  "properties": {
    "gn:admin1_code":"10",
    "gn:admin2_code":"7.0",
    "gn:asciiname":"La Tomatera",
    "gn:country_code":"MX",
    "gn:dem":1104,
    "gn:feature_class":"P",
    "gn:feature_code":"PPL",
    "gn:name":"La Tomatera",
    "gn:population":0,
    "gn:timezone":"America/Monterrey",
    "iso:country":"MX",
    "name:spa_x_preferred":[
        "La Tomatera"
    ],
    "wof:name":"La Tomatera",
    "wof:placetype":"locality"
},
  "geometry": {"coordinates":[-103.54115,25.87388],"type":"Point"}
}