{
  "type": "Feature",
  "properties": {
    "gn:admin1_code":"4",
    "gn:admin2_code":"10.0",
    "gn:asciiname":"Xculculche",
    "gn:country_code":"MX",
    "gn:dem":269,
    "gn:feature_class":"P",
    "gn:feature_code":"PPL",
    "gn:name":"Xculculche",
    "gn:population":0,
    "gn:timezone":"America/Merida",
    "iso:country":"MX",
    "wof:name":"Xculculche",
    "wof:placetype":"locality"
},
  "geometry": {"coordinates":[-89.63333,18.31667],"type":"Point"}
}