{
  "type": "Feature",
  "properties": {
    "gn:admin1_code":"5",
    "gn:admin2_code":"13.0",
    "gn:asciiname":"Yerbabuena",
    "gn:country_code":"MX",
    "gn:dem":1373,
    "gn:feature_class":"P",
    "gn:feature_code":"PPL",
    "gn:name":"Yerbabuena",
    "gn:population":0,
    "gn:timezone":"America/Mexico_City",
    "iso:country":"MX",
    "name:spa_x_preferred":[
        "La Yerbabuena"
    ],
    "name:spa_x_variant":[
        "Yerbabuena"
    ],
    "wof:name":"Yerbabuena",
    "wof:placetype":"locality"
},
  "geometry": {"coordinates":[-92.89679,16.93811],"type":"Point"}
}