{
  "type": "Feature",
  "properties": {
    "gn:admin1_code":"9",
    "gn:admin2_code":"9",
    "gn:asciiname":"Mecatzintla",
    "gn:country_code":"MX",
    "gn:dem":2451,
    "gn:feature_class":"P",
    "gn:feature_code":"PPL",
    "gn:name":"Mecatzintla",
    "gn:population":15,
    "gn:timezone":"America/Mexico_City",
    "iso:country":"MX",
    "wof:name":"Mecatzintla",
    "wof:placetype":"locality",
    "wof:population":15
},
  "geometry": {"coordinates":[-99.00846,19.18603],"type":"Point"}
}