{
  "type": "Feature",
  "properties": {
    "gn:admin1_code":"5",
    "gn:admin2_code":"39.0",
    "gn:asciiname":"Sombra Carrizal",
    "gn:country_code":"MX",
    "gn:dem":1334,
    "gn:feature_class":"P",
    "gn:feature_code":"PPL",
    "gn:name":"Sombra Carrizal",
    "gn:population":911,
    "gn:timezone":"America/Mexico_City",
    "iso:country":"MX",
    "wof:name":"Sombra Carrizal",
    "wof:placetype":"locality",
    "wof:population":911
},
  "geometry": {"coordinates":[-92.74666999999999,17.2975],"type":"Point"}
}