{
  "type": "Feature",
  "properties": {
    "gn:admin1_code":"17",
    "gn:admin2_code":"7.0",
    "gn:asciiname":"La Union",
    "gn:country_code":"MX",
    "gn:dem":1466,
    "gn:feature_class":"P",
    "gn:feature_code":"PPL",
    "gn:name":"La Uni\u00f3n",
    "gn:population":833,
    "gn:timezone":"America/Mexico_City",
    "iso:country":"MX",
    "name:und_x_variant":[
        "La Uni\u00f3n"
    ],
    "wof:name":"La Union",
    "wof:placetype":"locality",
    "wof:population":833
},
  "geometry": {"coordinates":[-99.24972,18.89583],"type":"Point"}
}