{
  "type": "Feature",
  "properties": {
    "gn:admin1_code":"28",
    "gn:admin2_code":"34.0",
    "gn:asciiname":"Las Huertas",
    "gn:country_code":"MX",
    "gn:dem":448,
    "gn:feature_class":"P",
    "gn:feature_code":"PPL",
    "gn:name":"Las Huertas",
    "gn:population":5,
    "gn:timezone":"America/Monterrey",
    "iso:country":"MX",
    "wof:name":"Las Huertas",
    "wof:placetype":"locality",
    "wof:population":5
},
  "geometry": {"coordinates":[-98.94472,24.57806],"type":"Point"}
}