{
  "type": "Feature",
  "properties": {
    "gn:admin1_code":"30",
    "gn:admin2_code":"124.0",
    "gn:asciiname":"La Presa",
    "gn:country_code":"MX",
    "gn:dem":154,
    "gn:feature_class":"P",
    "gn:feature_code":"PPL",
    "gn:name":"La Presa",
    "gn:population":5,
    "gn:timezone":"America/Mexico_City",
    "iso:country":"MX",
    "wof:name":"La Presa",
    "wof:placetype":"locality",
    "wof:population":5
},
  "geometry": {"coordinates":[-97.40000000000001,20.43833],"type":"Point"}
}