{
  "type": "Feature",
  "properties": {
    "gn:admin1_code":"13",
    "gn:admin2_code":"84.0",
    "gn:asciiname":"Los Duraznos",
    "gn:country_code":"MX",
    "gn:dem":2506,
    "gn:feature_class":"P",
    "gn:feature_code":"PPL",
    "gn:name":"Los Duraznos",
    "gn:population":0,
    "gn:timezone":"America/Mexico_City",
    "iso:country":"MX",
    "name:und_x_variant":[
        "Durazno",
        "Los Duraznos"
    ],
    "wof:name":"Los Duraznos",
    "wof:placetype":"locality"
},
  "geometry": {"coordinates":[-99.22614,20.86923],"type":"Point"}
}