{
  "type": "Feature",
  "properties": {
    "gn:admin1_code":"16",
    "gn:admin2_code":"3.0",
    "gn:asciiname":"El Zapote [Colonia Agricola]",
    "gn:country_code":"MX",
    "gn:dem":1842,
    "gn:feature_class":"P",
    "gn:feature_code":"PPL",
    "gn:name":"El Zapote [Colonia Agr\u00edcola]",
    "gn:population":159,
    "gn:timezone":"America/Mexico_City",
    "iso:country":"MX",
    "name:und_x_variant":[
        "El Zapote [Colonia Agr\u00edcola]"
    ],
    "wof:name":"El Zapote [Colonia Agricola]",
    "wof:placetype":"locality",
    "wof:population":159
},
  "geometry": {"coordinates":[-101.02110999999999,19.84056],"type":"Point"}
}