{
  "type": "Feature",
  "properties": {
    "gn:admin1_code":"28",
    "gn:admin2_code":"20.0",
    "gn:asciiname":"La Vaca",
    "gn:country_code":"MX",
    "gn:dem":286,
    "gn:feature_class":"P",
    "gn:feature_code":"PPL",
    "gn:name":"La Vaca",
    "gn:population":0,
    "gn:timezone":"America/Monterrey",
    "iso:country":"MX",
    "wof:name":"La Vaca",
    "wof:placetype":"locality"
},
  "geometry": {"coordinates":[-99.41667,24.73333],"type":"Point"}
}