{
  "type": "Feature",
  "properties": {
    "gn:admin1_code":"21",
    "gn:admin2_code":"10.0",
    "gn:asciiname":"Las Palmas (San Miguel)",
    "gn:country_code":"MX",
    "gn:dem":1237,
    "gn:feature_class":"P",
    "gn:feature_code":"PPL",
    "gn:name":"Las Palmas (San Miguel)",
    "gn:population":177,
    "gn:timezone":"America/Mexico_City",
    "iso:country":"MX",
    "wof:name":"Las Palmas (San Miguel)",
    "wof:placetype":"locality",
    "wof:population":177
},
  "geometry": {"coordinates":[-97.27257,18.38641],"type":"Point"}
}