{
  "type": "Feature",
  "properties": {
    "gn:admin1_code":"24",
    "gn:admin2_code":"39.0",
    "gn:asciiname":"Oshlom Chijol",
    "gn:country_code":"MX",
    "gn:dem":288,
    "gn:feature_class":"P",
    "gn:feature_code":"PPL",
    "gn:name":"Oshlom Chijol",
    "gn:population":0,
    "gn:timezone":"America/Mexico_City",
    "iso:country":"MX",
    "name:spa_x_preferred":[
        "Oshlom Chijol"
    ],
    "name:spa_x_variant":[
        "Los Tres Chijoles"
    ],
    "wof:name":"Oshlom Chijol",
    "wof:placetype":"locality"
},
  "geometry": {"coordinates":[-98.81958,21.59539],"type":"Point"}
}