{
  "type": "Feature",
  "properties": {
    "gn:admin1_code":"3.0",
    "gn:admin2_code":"3.0",
    "gn:asciiname":"Teculan",
    "gn:country_code":"MX",
    "gn:dem":210,
    "gn:feature_class":"P",
    "gn:feature_code":"PPL",
    "gn:name":"Tecul\u00e1n",
    "gn:population":0,
    "gn:timezone":"America/Mazatlan",
    "iso:country":"MX",
    "wof:name":"Teculan",
    "wof:placetype":"locality"
},
  "geometry": {"coordinates":[-109.94138999999998,23.82806],"type":"Point"}
}