{
  "type": "Feature",
  "properties": {
    "gn:admin1_code":"23.0",
    "gn:asciiname":"Xamach Dos",
    "gn:country_code":"MX",
    "gn:dem":1,
    "gn:feature_class":"P",
    "gn:feature_code":"PPL",
    "gn:name":"Xamach Dos",
    "gn:population":0,
    "gn:timezone":"America/Cancun",
    "iso:country":"MX",
    "name:spa_x_preferred":[
        "Xamach Dos"
    ],
    "name:spa_x_variant":[
        "Kil\u00f3metro Treinta y Dos"
    ],
    "wof:name":"Xamach Dos",
    "wof:placetype":"locality"
},
  "geometry": {"coordinates":[-87.45779,19.94482],"type":"Point"}
}