{
  "type": "Feature",
  "properties": {
    "gn:admin1_code":"13",
    "gn:admin2_code":"63.0",
    "gn:asciiname":"Hacienda Xajay",
    "gn:country_code":"MX",
    "gn:dem":2170,
    "gn:feature_class":"P",
    "gn:feature_code":"PPL",
    "gn:name":"Hacienda Xajay",
    "gn:population":0,
    "gn:timezone":"America/Mexico_City",
    "iso:country":"MX",
    "name:spa_x_preferred":[
        "Hacienda Xajay"
    ],
    "name:spa_x_variant":[
        "Shajay",
        "Xhajay"
    ],
    "wof:name":"Hacienda Xajay",
    "wof:placetype":"locality"
},
  "geometry": {"coordinates":[-99.36085,19.83962],"type":"Point"}
}