{
  "type": "Feature",
  "properties": {
    "gn:admin1_code":"28.0",
    "gn:admin2_code":"21.0",
    "gn:asciiname":"El Tigre",
    "gn:country_code":"MX",
    "gn:dem":81,
    "gn:feature_class":"P",
    "gn:feature_code":"PPL",
    "gn:name":"El Tigre",
    "gn:population":2,
    "gn:timezone":"America/Monterrey",
    "iso:country":"MX",
    "name:spa_x_preferred":[
        "El Tigre"
    ],
    "wof:name":"El Tigre",
    "wof:placetype":"locality",
    "wof:population":2
},
  "geometry": {"coordinates":[-98.94861,22.68667],"type":"Point"}
}