{
  "type": "Feature",
  "properties": {
    "gn:admin1_code":"12",
    "gn:admin2_code":"16",
    "gn:asciiname":"El Jazmin",
    "gn:country_code":"MX",
    "gn:dem":286,
    "gn:feature_class":"P",
    "gn:feature_code":"PPL",
    "gn:name":"El Jazm\u00edn",
    "gn:population":18,
    "gn:timezone":"America/Mexico_City",
    "iso:country":"MX",
    "name:und_x_variant":[
        "El Jazm\u00edn"
    ],
    "wof:name":"El Jazmin",
    "wof:placetype":"locality",
    "wof:population":18
},
  "geometry": {"coordinates":[-101.77279,18.2524],"type":"Point"}
}