{
  "type": "Feature",
  "properties": {
    "gn:admin1_code":"26",
    "gn:admin2_code":"49.0",
    "gn:asciiname":"El Guamuchil",
    "gn:country_code":"MX",
    "gn:dem":340,
    "gn:feature_class":"P",
    "gn:feature_code":"PPL",
    "gn:name":"El Guamuchil",
    "gn:population":3,
    "gn:timezone":"America/Hermosillo",
    "iso:country":"MX",
    "name:spa_x_preferred":[
        "El Guamuchil"
    ],
    "wof:name":"El Guamuchil",
    "wof:placetype":"locality",
    "wof:population":3
},
  "geometry": {"coordinates":[-108.97778,27.66111],"type":"Point"}
}