{
  "type": "Feature",
  "properties": {
    "gn:admin1_code":"11.0",
    "gn:admin2_code":"14.0",
    "gn:asciiname":"Galancillo",
    "gn:cc2":"MX",
    "gn:country_code":"MX",
    "gn:dem":2001,
    "gn:feature_class":"P",
    "gn:feature_code":"PPL",
    "gn:name":"Galancillo",
    "gn:population":150,
    "gn:timezone":"America/Mexico_City",
    "iso:country":"MX",
    "name:und_x_variant":[
        "Galoncillo"
    ],
    "wof:name":"Galancillo",
    "wof:placetype":"locality",
    "wof:population":150
},
  "geometry": {"coordinates":[-100.89444,21.28444],"type":"Point"}
}