{
  "type": "Feature",
  "properties": {
    "gn:admin1_code":"16",
    "gn:admin2_code":"97",
    "gn:asciiname":"El Terrero",
    "gn:country_code":"MX",
    "gn:dem":606,
    "gn:feature_class":"P",
    "gn:feature_code":"PPL",
    "gn:name":"El Terrero",
    "gn:population":26,
    "gn:timezone":"America/Mexico_City",
    "iso:country":"MX",
    "wof:name":"El Terrero",
    "wof:placetype":"locality",
    "wof:population":26
},
  "geometry": {"coordinates":[-101.35111000000001,18.99028],"type":"Point"}
}