{
  "type": "Feature",
  "properties": {
    "gn:admin1_code":"27",
    "gn:admin2_code":"17.0",
    "gn:asciiname":"El Guanal",
    "gn:country_code":"MX",
    "gn:dem":38,
    "gn:feature_class":"P",
    "gn:feature_code":"PPL",
    "gn:name":"El Guanal",
    "gn:population":0,
    "gn:timezone":"America/Mexico_City",
    "iso:country":"MX",
    "name:spa_x_preferred":[
        "El Huanal"
    ],
    "name:und_x_variant":[
        "Guanal",
        "El Guanal"
    ],
    "wof:name":"El Guanal",
    "wof:placetype":"locality"
},
  "geometry": {"coordinates":[-91.5123,17.58277],"type":"Point"}
}