{
  "type": "Feature",
  "properties": {
    "gn:admin1_code":"6",
    "gn:admin2_code":"65",
    "gn:asciiname":"Guaguequena",
    "gn:country_code":"MX",
    "gn:dem":2008,
    "gn:feature_class":"P",
    "gn:feature_code":"PPL",
    "gn:name":"Guaguequena",
    "gn:population":9,
    "gn:timezone":"America/Chihuahua",
    "iso:country":"MX",
    "wof:name":"Guaguequena",
    "wof:placetype":"locality",
    "wof:population":9
},
  "geometry": {"coordinates":[-107.75214,27.40881],"type":"Point"}
}