{
  "type": "Feature",
  "properties": {
    "gn:admin1_code":"6",
    "gn:admin2_code":"8.0",
    "gn:asciiname":"Citaborachi",
    "gn:country_code":"MX",
    "gn:dem":1740,
    "gn:feature_class":"P",
    "gn:feature_code":"PPL",
    "gn:name":"Citaborachi",
    "gn:population":0,
    "gn:timezone":"America/Chihuahua",
    "iso:country":"MX",
    "name:spa_x_preferred":[
        "Citaborachi"
    ],
    "wof:name":"Citaborachi",
    "wof:placetype":"locality"
},
  "geometry": {"coordinates":[-107.63221,26.94567],"type":"Point"}
}