{
  "type": "Feature",
  "properties": {
    "gn:admin1_code":"30.0",
    "gn:admin2_code":"78.0",
    "gn:asciiname":"La Cuchilia",
    "gn:country_code":"MX",
    "gn:dem":103,
    "gn:feature_class":"P",
    "gn:feature_code":"PPL",
    "gn:name":"La Cuchilia",
    "gn:population":0,
    "gn:timezone":"America/Mexico_City",
    "iso:country":"MX",
    "name:spa_x_preferred":[
        "La Cuchilia"
    ],
    "wof:name":"La Cuchilia",
    "wof:placetype":"locality"
},
  "geometry": {"coordinates":[-98.00785999999999,21.29484],"type":"Point"}
}