{
  "type": "Feature",
  "properties": {
    "gn:admin1_code":"14",
    "gn:admin2_code":"44",
    "gn:asciiname":"San Isidro (El Aguacate)",
    "gn:country_code":"MX",
    "gn:dem":1673,
    "gn:feature_class":"P",
    "gn:feature_code":"PPL",
    "gn:name":"San Isidro (El Aguacate)",
    "gn:population":38,
    "gn:timezone":"America/Mexico_City",
    "iso:country":"MX",
    "wof:name":"San Isidro (El Aguacate)",
    "wof:placetype":"locality",
    "wof:population":38
},
  "geometry": {"coordinates":[-103.28306000000001,20.36861],"type":"Point"}
}