{
  "type": "Feature",
  "properties": {
    "gn:admin1_code":"6",
    "gn:admin2_code":"65.0",
    "gn:asciiname":"Siguirabo",
    "gn:country_code":"MX",
    "gn:dem":2074,
    "gn:feature_class":"P",
    "gn:feature_code":"PPL",
    "gn:name":"Siguirabo",
    "gn:population":7,
    "gn:timezone":"America/Chihuahua",
    "iso:country":"MX",
    "wof:name":"Siguirabo",
    "wof:placetype":"locality",
    "wof:population":7
},
  "geometry": {"coordinates":[-107.85214999999999,27.60853],"type":"Point"}
}