{
  "type": "Feature",
  "properties": {
    "gn:admin1_code":"30",
    "gn:admin2_code":"13",
    "gn:asciiname":"Kilometro Noventa y Tres",
    "gn:country_code":"MX",
    "gn:dem":75,
    "gn:feature_class":"P",
    "gn:feature_code":"PPL",
    "gn:name":"Kil\u00f3metro Noventa y Tres",
    "gn:population":12,
    "gn:timezone":"America/Mexico_City",
    "iso:country":"MX",
    "name:und_x_variant":[
        "Kil\u00f3metro Noventa y Tres"
    ],
    "wof:name":"Kilometro Noventa y Tres",
    "wof:placetype":"locality",
    "wof:population":12
},
  "geometry": {"coordinates":[-97.67694,21.27556],"type":"Point"}
}