{
  "type": "Feature",
  "properties": {
    "gn:admin1_code":"32",
    "gn:admin2_code":"34",
    "gn:asciiname":"El Alto del Llano (Cruz Jimenez Armas)",
    "gn:country_code":"MX",
    "gn:dem":2009,
    "gn:feature_class":"P",
    "gn:feature_code":"PPL",
    "gn:name":"El Alto del Llano (Cruz Jim\u00e9nez Armas)",
    "gn:population":16,
    "gn:timezone":"America/Mexico_City",
    "iso:country":"MX",
    "name:und_x_variant":[
        "El Alto del Llano (Cruz Jim\u00e9nez Armas)"
    ],
    "wof:name":"El Alto del Llano (Cruz Jimenez Armas)",
    "wof:placetype":"locality",
    "wof:population":16
},
  "geometry": {"coordinates":[-102.75972,21.4125],"type":"Point"}
}