{
  "type": "Feature",
  "properties": {
    "gn:admin1_code":"28.0",
    "gn:admin2_code":"3.0",
    "gn:asciiname":"Las Galeras",
    "gn:country_code":"MX",
    "gn:dem":18,
    "gn:feature_class":"P",
    "gn:feature_code":"PPL",
    "gn:name":"Las Galeras",
    "gn:population":0,
    "gn:timezone":"America/Monterrey",
    "iso:country":"MX",
    "name:spa_x_preferred":[
        "Las Galeras"
    ],
    "name:spa_x_variant":[
        "El Potos\u00ed"
    ],
    "wof:name":"Las Galeras",
    "wof:placetype":"locality"
},
  "geometry": {"coordinates":[-98.18024,22.57892],"type":"Point"}
}