{
  "type": "Feature",
  "properties": {
    "gn:admin1_code":"18",
    "gn:admin2_code":"1.0",
    "gn:asciiname":"Motaje",
    "gn:country_code":"MX",
    "gn:dem":91,
    "gn:feature_class":"P",
    "gn:feature_code":"PPL",
    "gn:name":"Motaje",
    "gn:population":0,
    "gn:timezone":"America/Mazatlan",
    "iso:country":"MX",
    "name:und_x_variant":[
        "Mataje",
        "Motaje"
    ],
    "wof:name":"Motaje",
    "wof:placetype":"locality"
},
  "geometry": {"coordinates":[-105.24739,22.39764],"type":"Point"}
}