{
  "type": "Feature",
  "properties": {
    "gn:admin1_code":"6",
    "gn:admin2_code":"9",
    "gn:asciiname":"Las Jaritas",
    "gn:country_code":"MX",
    "gn:dem":2475,
    "gn:feature_class":"P",
    "gn:feature_code":"PPL",
    "gn:name":"Las Jaritas",
    "gn:population":18,
    "gn:timezone":"America/Chihuahua",
    "iso:country":"MX",
    "wof:name":"Las Jaritas",
    "wof:placetype":"locality",
    "wof:population":18
},
  "geometry": {"coordinates":[-107.45354,27.95936],"type":"Point"}
}