{
  "type": "Feature",
  "properties": {
    "gn:admin1_code":"6",
    "gn:admin2_code":"44.0",
    "gn:asciiname":"Los Amarraderos",
    "gn:country_code":"MX",
    "gn:dem":1801,
    "gn:feature_class":"P",
    "gn:feature_code":"PPL",
    "gn:name":"Los Amarraderos",
    "gn:population":0,
    "gn:timezone":"America/Monterrey",
    "iso:country":"MX",
    "name:spa_x_preferred":[
        "Los Amarraderos"
    ],
    "name:und_x_variant":[
        "Rancho Los Amarraderes",
        "Los Amarraderes"
    ],
    "wof:name":"Los Amarraderos",
    "wof:placetype":"locality"
},
  "geometry": {"coordinates":[-105.49513,26.53337],"type":"Point"}
}