{
  "type": "Feature",
  "properties": {
    "gn:admin1_code":"15",
    "gn:admin2_code":"63.0",
    "gn:asciiname":"Colonia Doctor Gustavo Baz",
    "gn:country_code":"MX",
    "gn:dem":2585,
    "gn:feature_class":"P",
    "gn:feature_code":"PPL",
    "gn:name":"Colonia Doctor Gustavo Baz",
    "gn:population":1077,
    "gn:timezone":"America/Mexico_City",
    "iso:country":"MX",
    "wof:name":"Colonia Doctor Gustavo Baz",
    "wof:placetype":"locality",
    "wof:population":1077
},
  "geometry": {"coordinates":[-99.39667,19.01306],"type":"Point"}
}