{
  "type": "Feature",
  "properties": {
    "gn:admin1_code":"26",
    "gn:admin2_code":"29.0",
    "gn:asciiname":"San Marcial",
    "gn:country_code":"MX",
    "gn:dem":265,
    "gn:feature_class":"P",
    "gn:feature_code":"PPL",
    "gn:name":"San Marcial",
    "gn:population":0,
    "gn:timezone":"America/Hermosillo",
    "iso:country":"MX",
    "name:spa_x_preferred":[
        "San Marcial"
    ],
    "wof:name":"San Marcial",
    "wof:placetype":"locality"
},
  "geometry": {"coordinates":[-110.30401000000001,28.50119],"type":"Point"}
}