{
  "type": "Feature",
  "properties": {
    "gn:admin1_code":"16.0",
    "gn:admin2_code":"23.0",
    "gn:asciiname":"El Tepehuaje",
    "gn:country_code":"MX",
    "gn:dem":1560,
    "gn:feature_class":"P",
    "gn:feature_code":"PPL",
    "gn:name":"El Tepehuaje",
    "gn:population":796,
    "gn:timezone":"America/Mexico_City",
    "iso:country":"MX",
    "wof:name":"El Tepehuaje",
    "wof:placetype":"locality",
    "wof:population":796
},
  "geometry": {"coordinates":[-102.39843,20.0707],"type":"Point"}
}