{
  "type": "Feature",
  "properties": {
    "gn:admin1_code":"2",
    "gn:admin2_code":"1.0",
    "gn:asciiname":"Cinco Islas [Campo]",
    "gn:country_code":"MX",
    "gn:dem":7,
    "gn:feature_class":"P",
    "gn:feature_code":"PPL",
    "gn:name":"Cinco Islas [Campo]",
    "gn:population":4,
    "gn:timezone":"America/Tijuana",
    "iso:country":"MX",
    "wof:name":"Cinco Islas [Campo]",
    "wof:placetype":"locality",
    "wof:population":4
},
  "geometry": {"coordinates":[-114.57944000000001,30.04167],"type":"Point"}
}