{
  "type": "Feature",
  "properties": {
    "gn:admin1_code":"14",
    "gn:admin2_code":"40.0",
    "gn:asciiname":"Sayulimita",
    "gn:country_code":"MX",
    "gn:dem":960,
    "gn:feature_class":"P",
    "gn:feature_code":"PPL",
    "gn:name":"Sayulimita",
    "gn:population":0,
    "gn:timezone":"America/Mexico_City",
    "iso:country":"MX",
    "wof:name":"Sayulimita",
    "wof:placetype":"locality"
},
  "geometry": {"coordinates":[-103.8831,21.05765],"type":"Point"}
}