{
  "type": "Feature",
  "properties": {
    "gn:admin1_code":"6",
    "gn:admin2_code":"2.0",
    "gn:asciiname":"Granja de los Lopez",
    "gn:country_code":"MX",
    "gn:dem":1264,
    "gn:feature_class":"P",
    "gn:feature_code":"PPL",
    "gn:name":"Granja de los L\u00f3pez",
    "gn:population":6,
    "gn:timezone":"America/Chihuahua",
    "iso:country":"MX",
    "name:und_x_variant":[
        "Granja de los L\u00f3pez"
    ],
    "wof:name":"Granja de los Lopez",
    "wof:placetype":"locality",
    "wof:population":6
},
  "geometry": {"coordinates":[-105.90669,28.84861],"type":"Point"}
}