{
  "type": "Feature",
  "properties": {
    "gn:admin1_code":"7.0",
    "gn:admin2_code":"32.0",
    "gn:asciiname":"Indalecio",
    "gn:country_code":"MX",
    "gn:dem":422,
    "gn:feature_class":"P",
    "gn:feature_code":"PPL",
    "gn:name":"Indalecio",
    "gn:population":0,
    "gn:timezone":"America/Monterrey",
    "iso:country":"MX",
    "wof:name":"Indalecio",
    "wof:placetype":"locality"
},
  "geometry": {"coordinates":[-101.43333,28.01667],"type":"Point"}
}