{
  "type": "Feature",
  "properties": {
    "gn:admin1_code":"16.0",
    "gn:admin2_code":"26.0",
    "gn:asciiname":"El Zapotito",
    "gn:country_code":"MX",
    "gn:dem":889,
    "gn:feature_class":"P",
    "gn:feature_code":"PPL",
    "gn:name":"El Zapotito",
    "gn:population":0,
    "gn:timezone":"America/Mexico_City",
    "iso:country":"MX",
    "name:spa_x_preferred":[
        "El Zapotito"
    ],
    "name:und_x_variant":[
        "El Zapatillo"
    ],
    "wof:name":"El Zapotito",
    "wof:placetype":"locality"
},
  "geometry": {"coordinates":[-103.32219000000001,18.80806],"type":"Point"}
}