{
  "type": "Feature",
  "properties": {
    "gn:admin1_code":"20",
    "gn:admin2_code":"364.0",
    "gn:asciiname":"El Coquito",
    "gn:country_code":"MX",
    "gn:dem":1437,
    "gn:feature_class":"P",
    "gn:feature_code":"PPL",
    "gn:name":"El Coquito",
    "gn:population":7,
    "gn:timezone":"America/Mexico_City",
    "iso:country":"MX",
    "wof:name":"El Coquito",
    "wof:placetype":"locality",
    "wof:population":7
},
  "geometry": {"coordinates":[-97.27972,16.23889],"type":"Point"}
}