{
  "type": "Feature",
  "properties": {
    "gn:admin1_code":"28.0",
    "gn:admin2_code":"34.0",
    "gn:asciiname":"Victor M. Bueno",
    "gn:country_code":"MX",
    "gn:dem":258,
    "gn:feature_class":"P",
    "gn:feature_code":"PPL",
    "gn:name":"V\u00edctor M. Bueno",
    "gn:population":0,
    "gn:timezone":"America/Monterrey",
    "iso:country":"MX",
    "name:spa_x_preferred":[
        "V\u00edctor M. Bueno"
    ],
    "wof:name":"Victor M. Bueno",
    "wof:placetype":"locality"
},
  "geometry": {"coordinates":[-99.01594,24.36578],"type":"Point"}
}