{
  "type": "Feature",
  "properties": {
    "gn:admin1_code":"19.0",
    "gn:admin2_code":"49.0",
    "gn:asciiname":"Quinta Chavalo",
    "gn:country_code":"MX",
    "gn:dem":515,
    "gn:feature_class":"P",
    "gn:feature_code":"PPL",
    "gn:name":"Quinta Chavalo",
    "gn:population":0,
    "gn:timezone":"America/Monterrey",
    "iso:country":"MX",
    "name:spa_x_preferred":[
        "Quinta Chavalo"
    ],
    "wof:name":"Quinta Chavalo",
    "wof:placetype":"locality"
},
  "geometry": {"coordinates":[-100.18291000000001,25.44875],"type":"Point"}
}