{
  "type": "Feature",
  "properties": {
    "gn:admin1_code":"25",
    "gn:admin2_code":"17.0",
    "gn:asciiname":"El Camichin",
    "gn:country_code":"MX",
    "gn:dem":297,
    "gn:feature_class":"P",
    "gn:feature_code":"PPL",
    "gn:name":"El Camich\u00edn",
    "gn:population":9,
    "gn:timezone":"America/Mazatlan",
    "iso:country":"MX",
    "name:und_x_variant":[
        "El Camich\u00edn"
    ],
    "wof:name":"El Camichin",
    "wof:placetype":"locality",
    "wof:population":9
},
  "geometry": {"coordinates":[-108.04111,25.80254],"type":"Point"}
}