{
  "type": "Feature",
  "properties": {
    "gn:admin1_code":"16.0",
    "gn:admin2_code":"52.0",
    "gn:asciiname":"Teolan",
    "gn:country_code":"MX",
    "gn:dem":9,
    "gn:feature_class":"P",
    "gn:feature_code":"PPL",
    "gn:name":"Teol\u00e1n",
    "gn:population":0,
    "gn:timezone":"America/Mexico_City",
    "iso:country":"MX",
    "name:spa_x_preferred":[
        "Teol\u00e1n"
    ],
    "wof:name":"Teolan",
    "wof:placetype":"locality"
},
  "geometry": {"coordinates":[-102.73027999999999,18.07946],"type":"Point"}
}