{
  "type": "Feature",
  "properties": {
    "gn:admin1_code":"15",
    "gn:admin2_code":"82.0",
    "gn:asciiname":"Potrero Grande",
    "gn:country_code":"MX",
    "gn:dem":1677,
    "gn:feature_class":"P",
    "gn:feature_code":"PPL",
    "gn:name":"Potrero Grande",
    "gn:population":56,
    "gn:timezone":"America/Mexico_City",
    "iso:country":"MX",
    "name:ceb_x_preferred":[
        "Potrero Grande"
    ],
    "wof:name":"Potrero Grande",
    "wof:placetype":"locality",
    "wof:population":56
},
  "geometry": {"coordinates":[-100.5051,18.83834],"type":"Point"}
}