{
  "type": "Feature",
  "properties": {
    "gn:admin1_code":"31.0",
    "gn:asciiname":"Remuda",
    "gn:country_code":"MX",
    "gn:dem":23,
    "gn:feature_class":"P",
    "gn:feature_code":"PPL",
    "gn:name":"Remuda",
    "gn:population":0,
    "gn:timezone":"America/Merida",
    "iso:country":"MX",
    "name:spa_x_preferred":[
        "Remuda"
    ],
    "name:spa_x_variant":[
        "La Remuda"
    ],
    "wof:name":"Remuda",
    "wof:placetype":"locality"
},
  "geometry": {"coordinates":[-88.05511,21.23896],"type":"Point"}
}