{
  "type": "Feature",
  "properties": {
    "gn:admin1_code":"17",
    "gn:admin2_code":"4.0",
    "gn:asciiname":"Palo Blanco",
    "gn:country_code":"MX",
    "gn:dem":1128,
    "gn:feature_class":"P",
    "gn:feature_code":"PPL",
    "gn:name":"Palo Blanco",
    "gn:population":395,
    "gn:timezone":"America/Mexico_City",
    "iso:country":"MX",
    "name:ceb_x_preferred":[
        "Palo Blanco"
    ],
    "name:spa_x_preferred":[
        "Palo blanco"
    ],
    "name:swe_x_preferred":[
        "Palo Blanco"
    ],
    "wof:name":"Palo Blanco",
    "wof:placetype":"locality",
    "wof:population":395
},
  "geometry": {"coordinates":[-98.94694,18.64889],"type":"Point"}
}