{
  "type": "Feature",
  "properties": {
    "gn:admin1_code":"5",
    "gn:admin2_code":"33.0",
    "gn:asciiname":"Nuevo Paraiso",
    "gn:country_code":"MX",
    "gn:dem":758,
    "gn:feature_class":"P",
    "gn:feature_code":"PPL",
    "gn:name":"Nuevo Para\u00edso",
    "gn:population":78,
    "gn:timezone":"America/Mexico_City",
    "iso:country":"MX",
    "name:und_x_variant":[
        "Nuevo Para\u00edso"
    ],
    "wof:name":"Nuevo Paraiso",
    "wof:placetype":"locality",
    "wof:population":78
},
  "geometry": {"coordinates":[-93.30694,17.26806],"type":"Point"}
}