{
  "type": "Feature",
  "properties": {
    "gn:admin1_code":"28.0",
    "gn:admin2_code":"12.0",
    "gn:asciiname":"La Esperanza",
    "gn:country_code":"MX",
    "gn:dem":9,
    "gn:feature_class":"P",
    "gn:feature_code":"PPL",
    "gn:name":"La Esperanza",
    "gn:population":4,
    "gn:timezone":"America/Mexico_City",
    "iso:country":"MX",
    "name:spa_x_preferred":[
        "La Esperanza"
    ],
    "wof:name":"La Esperanza",
    "wof:placetype":"locality",
    "wof:population":4
},
  "geometry": {"coordinates":[-98.34,22.39361],"type":"Point"}
}