{
  "type": "Feature",
  "properties": {
    "gn:admin1_code":"14.0",
    "gn:asciiname":"Las Crucitas",
    "gn:country_code":"MX",
    "gn:dem":1870,
    "gn:feature_class":"P",
    "gn:feature_code":"PPL",
    "gn:name":"Las Crucitas",
    "gn:population":0,
    "gn:timezone":"America/Mexico_City",
    "iso:country":"MX",
    "name:spa_x_preferred":[
        "Las Crucitas"
    ],
    "wof:name":"Las Crucitas",
    "wof:placetype":"locality"
},
  "geometry": {"coordinates":[-102.04443999999999,21.11509],"type":"Point"}
}