{
  "type": "Feature",
  "properties": {
    "gn:admin1_code":"27",
    "gn:admin2_code":"2.0",
    "gn:asciiname":"Poza Redonda Tercera Seccion",
    "gn:country_code":"MX",
    "gn:dem":9,
    "gn:feature_class":"P",
    "gn:feature_code":"PPL",
    "gn:name":"Poza Redonda Tercera Secci\u00f3n",
    "gn:population":0,
    "gn:timezone":"America/Mexico_City",
    "iso:country":"MX",
    "name:spa_x_preferred":[
        "Poza Redonda Tercera Secci\u00f3n"
    ],
    "wof:name":"Poza Redonda Tercera Seccion",
    "wof:placetype":"locality"
},
  "geometry": {"coordinates":[-93.49636,18.25077000000001],"type":"Point"}
}