{
  "type": "Feature",
  "properties": {
    "gn:admin1_code":"30",
    "gn:admin2_code":"63.0",
    "gn:asciiname":"Ochenta y Uno",
    "gn:country_code":"MX",
    "gn:dem":55,
    "gn:feature_class":"P",
    "gn:feature_code":"PPL",
    "gn:name":"Ochenta y Uno",
    "gn:population":5,
    "gn:timezone":"America/Mexico_City",
    "iso:country":"MX",
    "wof:name":"Ochenta y Uno",
    "wof:placetype":"locality",
    "wof:population":5
},
  "geometry": {"coordinates":[-97.98806,21.53167],"type":"Point"}
}