{
  "type": "Feature",
  "properties": {
    "gn:admin1_code":"30",
    "gn:admin2_code":"172.0",
    "gn:asciiname":"La Veronica",
    "gn:country_code":"MX",
    "gn:dem":26,
    "gn:feature_class":"P",
    "gn:feature_code":"PPL",
    "gn:name":"La Ver\u00f3nica",
    "gn:population":4,
    "gn:timezone":"America/Mexico_City",
    "iso:country":"MX",
    "wof:name":"La Veronica",
    "wof:placetype":"locality",
    "wof:population":4
},
  "geometry": {"coordinates":[-94.84139,17.84778],"type":"Point"}
}