{
  "type": "Feature",
  "properties": {
    "gn:admin1_code":"11",
    "gn:admin2_code":"31.0",
    "gn:asciiname":"El Centro",
    "gn:country_code":"MX",
    "gn:dem":1782,
    "gn:feature_class":"P",
    "gn:feature_code":"PPL",
    "gn:name":"El Centro",
    "gn:population":357,
    "gn:timezone":"America/Mexico_City",
    "iso:country":"MX",
    "wof:name":"El Centro",
    "wof:placetype":"locality",
    "wof:population":357
},
  "geometry": {"coordinates":[-101.81278,20.94083],"type":"Point"}
}