{
  "type": "Feature",
  "properties": {
    "gn:admin1_code":"30",
    "gn:admin2_code":"58",
    "gn:asciiname":"Tlaica",
    "gn:country_code":"MX",
    "gn:dem":472,
    "gn:feature_class":"P",
    "gn:feature_code":"PPL",
    "gn:name":"Tlaica",
    "gn:population":25,
    "gn:timezone":"America/Mexico_City",
    "iso:country":"MX",
    "wof:name":"Tlaica",
    "wof:placetype":"locality",
    "wof:population":25
},
  "geometry": {"coordinates":[-98.12278000000001,20.94],"type":"Point"}
}