{
  "type": "Feature",
  "properties": {
    "gn:admin1_code":"28",
    "gn:admin2_code":"23.0",
    "gn:asciiname":"Americo Villarreal Guerra",
    "gn:country_code":"MX",
    "gn:dem":65,
    "gn:feature_class":"P",
    "gn:feature_code":"PPL",
    "gn:name":"Am\u00e9rico Villarreal Guerra",
    "gn:population":142,
    "gn:timezone":"America/Monterrey",
    "iso:country":"MX",
    "name:und_x_variant":[
        "Am\u00e9rico Villarreal Guerra"
    ],
    "wof:name":"Americo Villarreal Guerra",
    "wof:placetype":"locality",
    "wof:population":142
},
  "geometry": {"coordinates":[-98.21361,25.31917],"type":"Point"}
}