{
  "type": "Feature",
  "properties": {
    "gn:admin1_code":"16.0",
    "gn:admin2_code":"89.0",
    "gn:asciiname":"El Tecolote",
    "gn:country_code":"MX",
    "gn:dem":439,
    "gn:feature_class":"P",
    "gn:feature_code":"PPL",
    "gn:name":"El Tecolote",
    "gn:population":0,
    "gn:timezone":"America/Mexico_City",
    "iso:country":"MX",
    "name:ceb_x_preferred":[
        "El Tecolote"
    ],
    "name:spa_x_preferred":[
        "El Tecolote"
    ],
    "name:swe_x_preferred":[
        "El Tecolote"
    ],
    "wof:name":"El Tecolote",
    "wof:placetype":"locality"
},
  "geometry": {"coordinates":[-102.91404,19.11524],"type":"Point"}
}