{
  "type": "Feature",
  "properties": {
    "gn:admin1_code":"5.0",
    "gn:admin2_code":"51.0",
    "gn:asciiname":"Brisas de Novillero",
    "gn:country_code":"MX",
    "gn:dem":63,
    "gn:feature_class":"P",
    "gn:feature_code":"PPL",
    "gn:name":"Br\u00edsas de Novillero",
    "gn:population":0,
    "gn:timezone":"America/Mexico_City",
    "iso:country":"MX",
    "name:spa_x_preferred":[
        "Br\u00edsas de Novillero"
    ],
    "wof:name":"Brisas de Novillero",
    "wof:placetype":"locality"
},
  "geometry": {"coordinates":[-92.95238999999999,15.50761],"type":"Point"}
}