{
  "type": "Feature",
  "properties": {
    "gn:admin1_code":"30",
    "gn:admin2_code":"115.0",
    "gn:asciiname":"Reforma",
    "gn:country_code":"MX",
    "gn:dem":1425,
    "gn:feature_class":"P",
    "gn:feature_code":"PPL",
    "gn:name":"Reforma",
    "gn:population":355,
    "gn:timezone":"America/Mexico_City",
    "iso:country":"MX",
    "name:cat_x_preferred":[
        "Reforma"
    ],
    "name:eus_x_preferred":[
        "Diario Reforma"
    ],
    "name:nld_x_preferred":[
        "Reforma"
    ],
    "name:nor_x_preferred":[
        "Reforma"
    ],
    "name:que_x_preferred":[
        "Reforma"
    ],
    "name:spa_x_preferred":[
        "Reforma"
    ],
    "wof:name":"Reforma",
    "wof:placetype":"locality",
    "wof:population":355
},
  "geometry": {"coordinates":[-97.18778,18.81806],"type":"Point"}
}