{
  "type": "Feature",
  "properties": {
    "gn:admin1_code":"13",
    "gn:admin2_code":"18.0",
    "gn:asciiname":"El Estero",
    "gn:country_code":"MX",
    "gn:dem":215,
    "gn:feature_class":"P",
    "gn:feature_code":"PPL",
    "gn:name":"El Estero",
    "gn:population":0,
    "gn:timezone":"America/Mexico_City",
    "iso:country":"MX",
    "name:spa_x_preferred":[
        "El Estero"
    ],
    "wof:name":"El Estero",
    "wof:placetype":"locality"
},
  "geometry": {"coordinates":[-98.84675,21.15629],"type":"Point"}
}