{
  "type": "Feature",
  "properties": {
    "gn:admin1_code":"28.0",
    "gn:admin2_code":"14.0",
    "gn:asciiname":"El Cacaiste",
    "gn:country_code":"MX",
    "gn:dem":113,
    "gn:feature_class":"P",
    "gn:feature_code":"PPL",
    "gn:name":"El Cacaiste",
    "gn:population":0,
    "gn:timezone":"America/Monterrey",
    "iso:country":"MX",
    "name:spa_x_preferred":[
        "El Cacaiste"
    ],
    "wof:name":"El Cacaiste",
    "wof:placetype":"locality"
},
  "geometry": {"coordinates":[-99.51167,27.00083],"type":"Point"}
}