{
  "type": "Feature",
  "properties": {
    "gn:admin1_code":"30",
    "gn:admin2_code":"54.0",
    "gn:asciiname":"Paso Carreta",
    "gn:country_code":"MX",
    "gn:dem":26,
    "gn:feature_class":"P",
    "gn:feature_code":"PPL",
    "gn:name":"Paso Carreta",
    "gn:population":0,
    "gn:timezone":"America/Mexico_City",
    "iso:country":"MX",
    "name:spa_x_preferred":[
        "Paso Carreta"
    ],
    "wof:name":"Paso Carreta",
    "wof:placetype":"locality"
},
  "geometry": {"coordinates":[-95.80898000000001,18.17584],"type":"Point"}
}