{
  "type": "Feature",
  "properties": {
    "gn:admin1_code":"2",
    "gn:admin2_code":"4.0",
    "gn:asciiname":"Ojo de Agua (El Florido)",
    "gn:country_code":"MX",
    "gn:dem":256,
    "gn:feature_class":"P",
    "gn:feature_code":"PPL",
    "gn:name":"Ojo de Agua (El Florido)",
    "gn:population":263,
    "gn:timezone":"America/Tijuana",
    "iso:country":"MX",
    "wof:name":"Ojo de Agua (El Florido)",
    "wof:placetype":"locality",
    "wof:population":263
},
  "geometry": {"coordinates":[-116.76806000000001,32.47639],"type":"Point"}
}