{
  "type": "Feature",
  "properties": {
    "gn:admin1_code":"1",
    "gn:admin2_code":"5.0",
    "gn:asciiname":"Las Cruces",
    "gn:country_code":"MX",
    "gn:dem":2129,
    "gn:feature_class":"P",
    "gn:feature_code":"PPL",
    "gn:name":"Las Cruces",
    "gn:population":4,
    "gn:timezone":"America/Mexico_City",
    "iso:country":"MX",
    "wof:name":"Las Cruces",
    "wof:placetype":"locality",
    "wof:population":4
},
  "geometry": {"coordinates":[-102.55361000000001,21.93139],"type":"Point"}
}