{
  "type": "Feature",
  "properties": {
    "gn:admin1_code":"28",
    "gn:admin2_code":"24.0",
    "gn:asciiname":"El Jabali",
    "gn:country_code":"MX",
    "gn:dem":100,
    "gn:feature_class":"P",
    "gn:feature_code":"PPL",
    "gn:name":"El Jabal\u00ed",
    "gn:population":0,
    "gn:timezone":"America/Monterrey",
    "iso:country":"MX",
    "name:spa_x_preferred":[
        "El Jabal\u00ed"
    ],
    "name:und_x_variant":[
        "Rancho Jabal\u00ed",
        "Jabal\u00ed"
    ],
    "wof:name":"El Jabali",
    "wof:placetype":"locality"
},
  "geometry": {"coordinates":[-99.31391000000001,26.40645],"type":"Point"}
}