{
  "type": "Feature",
  "properties": {
    "gn:admin1_code":"5",
    "gn:admin2_code":"26.0",
    "gn:asciiname":"Majumpepen",
    "gn:country_code":"MX",
    "gn:dem":1353,
    "gn:feature_class":"P",
    "gn:feature_code":"PPL",
    "gn:name":"Majumpepen",
    "gn:population":407,
    "gn:timezone":"America/Mexico_City",
    "iso:country":"MX",
    "wof:name":"Majumpepen",
    "wof:placetype":"locality",
    "wof:population":407
},
  "geometry": {"coordinates":[-92.54309000000001,16.97594],"type":"Point"}
}