{
  "type": "Feature",
  "properties": {
    "gn:admin1_code":"19.0",
    "gn:admin2_code":"50.0",
    "gn:asciiname":"La Paisana",
    "gn:country_code":"MX",
    "gn:dem":213,
    "gn:feature_class":"P",
    "gn:feature_code":"PPL",
    "gn:name":"La Paisana",
    "gn:population":0,
    "gn:timezone":"America/Monterrey",
    "iso:country":"MX",
    "name:spa_x_preferred":[
        "La Paisana"
    ],
    "wof:name":"La Paisana",
    "wof:placetype":"locality"
},
  "geometry": {"coordinates":[-99.89564,26.52895],"type":"Point"}
}