{
  "type": "Feature",
  "properties": {
    "gn:admin1_code":"25",
    "gn:admin2_code":"14",
    "gn:asciiname":"Agua Fria",
    "gn:country_code":"MX",
    "gn:dem":1824,
    "gn:feature_class":"P",
    "gn:feature_code":"PPL",
    "gn:name":"Agua Fr\u00eda",
    "gn:population":28,
    "gn:timezone":"America/Mazatlan",
    "iso:country":"MX",
    "name:ceb_x_preferred":[
        "Agua Fria"
    ],
    "name:deu_x_preferred":[
        "Agua Fria"
    ],
    "name:swe_x_preferred":[
        "Agua Fria"
    ],
    "name:und_x_variant":[
        "Agua Fr\u00eda"
    ],
    "wof:name":"Agua Fria",
    "wof:placetype":"locality",
    "wof:population":28
},
  "geometry": {"coordinates":[-105.42335,23.07087000000001],"type":"Point"}
}