{
  "type": "Feature",
  "properties": {
    "gn:admin1_code":"28",
    "gn:admin2_code":"16.0",
    "gn:asciiname":"Palo Alto",
    "gn:country_code":"MX",
    "gn:dem":251,
    "gn:feature_class":"P",
    "gn:feature_code":"PPL",
    "gn:name":"Palo Alto",
    "gn:population":0,
    "gn:timezone":"America/Monterrey",
    "iso:country":"MX",
    "name:und_x_variant":[
        "Palos Altos",
        "Palo Alto"
    ],
    "wof:name":"Palo Alto",
    "wof:placetype":"locality"
},
  "geometry": {"coordinates":[-99.28215,24.15351],"type":"Point"}
}