{
  "type": "Feature",
  "properties": {
    "gn:admin1_code":"32.0",
    "gn:admin2_code":"25.0",
    "gn:asciiname":"Cuisillo",
    "gn:country_code":"MX",
    "gn:dem":1973,
    "gn:feature_class":"P",
    "gn:feature_code":"PPL",
    "gn:name":"Cuisillo",
    "gn:population":0,
    "gn:timezone":"America/Mexico_City",
    "iso:country":"MX",
    "wof:name":"Cuisillo",
    "wof:placetype":"locality"
},
  "geometry": {"coordinates":[-102.23705,22.38278],"type":"Point"}
}