{
  "type": "Feature",
  "properties": {
    "gn:admin1_code":"5",
    "gn:admin2_code":"7.0",
    "gn:asciiname":"Estacion Guadalupe",
    "gn:country_code":"MX",
    "gn:dem":2269,
    "gn:feature_class":"P",
    "gn:feature_code":"PPL",
    "gn:name":"Estaci\u00f3n Guadalupe",
    "gn:population":7,
    "gn:timezone":"America/Mexico_City",
    "iso:country":"MX",
    "name:und_x_variant":[
        "Estaci\u00f3n Guadalupe"
    ],
    "wof:name":"Estacion Guadalupe",
    "wof:placetype":"locality",
    "wof:population":7
},
  "geometry": {"coordinates":[-92.32556,16.50583],"type":"Point"}
}