{
  "type": "Feature",
  "properties": {
    "gn:admin1_code":"12.0",
    "gn:admin2_code":"50.0",
    "gn:asciiname":"La Bolsa",
    "gn:country_code":"MX",
    "gn:dem":266,
    "gn:feature_class":"P",
    "gn:feature_code":"PPL",
    "gn:name":"La Bolsa",
    "gn:population":588,
    "gn:timezone":"America/Mexico_City",
    "iso:country":"MX",
    "name:spa_x_preferred":[
        "La Bolsa"
    ],
    "wof:name":"La Bolsa",
    "wof:placetype":"locality",
    "wof:population":588
},
  "geometry": {"coordinates":[-100.5962,18.39777],"type":"Point"}
}