{
  "type": "Feature",
  "properties": {
    "gn:admin1_code":"10.0",
    "gn:admin2_code":"14.0",
    "gn:asciiname":"Corralitos",
    "gn:country_code":"MX",
    "gn:dem":2257,
    "gn:feature_class":"P",
    "gn:feature_code":"PPL",
    "gn:name":"Corralitos",
    "gn:population":0,
    "gn:timezone":"America/Monterrey",
    "iso:country":"MX",
    "name:spa_x_preferred":[
        "Corralitos"
    ],
    "wof:name":"Corralitos",
    "wof:placetype":"locality"
},
  "geometry": {"coordinates":[-104.34632000000001,22.78093],"type":"Point"}
}