{
  "type": "Feature",
  "properties": {
    "gn:admin1_code":"10.0",
    "gn:admin2_code":"14.0",
    "gn:asciiname":"Los Marranos",
    "gn:country_code":"MX",
    "gn:dem":2098,
    "gn:feature_class":"P",
    "gn:feature_code":"PPL",
    "gn:name":"Los Marranos",
    "gn:population":0,
    "gn:timezone":"America/Monterrey",
    "iso:country":"MX",
    "name:spa_x_preferred":[
        "Los Marranos"
    ],
    "wof:name":"Los Marranos",
    "wof:placetype":"locality"
},
  "geometry": {"coordinates":[-104.36001,22.89196],"type":"Point"}
}