{
  "type": "Feature",
  "properties": {
    "gn:admin1_code":"26",
    "gn:admin2_code":"26.0",
    "gn:asciiname":"Trinidad Lopez",
    "gn:country_code":"MX",
    "gn:dem":39,
    "gn:feature_class":"P",
    "gn:feature_code":"PPL",
    "gn:name":"Trinidad L\u00f3pez",
    "gn:population":6,
    "gn:timezone":"America/Hermosillo",
    "iso:country":"MX",
    "name:und_x_variant":[
        "Trinidad L\u00f3pez"
    ],
    "wof:name":"Trinidad Lopez",
    "wof:placetype":"locality",
    "wof:population":6
},
  "geometry": {"coordinates":[-109.66611,27.15056],"type":"Point"}
}