{
  "type": "Feature",
  "properties": {
    "gn:admin1_code":"26",
    "gn:admin2_code":"57.0",
    "gn:asciiname":"La Concha",
    "gn:country_code":"MX",
    "gn:dem":674,
    "gn:feature_class":"P",
    "gn:feature_code":"PPL",
    "gn:name":"La Concha",
    "gn:population":0,
    "gn:timezone":"America/Hermosillo",
    "iso:country":"MX",
    "name:ceb_x_preferred":[
        "La Concha"
    ],
    "name:spa_x_preferred":[
        "La Concha"
    ],
    "name:swe_x_preferred":[
        "La Concha"
    ],
    "wof:name":"La Concha",
    "wof:placetype":"locality"
},
  "geometry": {"coordinates":[-109.71805999999999,29.41389],"type":"Point"}
}