{
  "type": "Feature",
  "properties": {
    "gn:admin1_code":"30",
    "gn:admin2_code":"159.0",
    "gn:asciiname":"Loma de los Pinos",
    "gn:country_code":"MX",
    "gn:dem":2275,
    "gn:feature_class":"P",
    "gn:feature_code":"PPL",
    "gn:name":"Loma de los Pinos",
    "gn:population":271,
    "gn:timezone":"America/Mexico_City",
    "iso:country":"MX",
    "wof:name":"Loma de los Pinos",
    "wof:placetype":"locality",
    "wof:population":271
},
  "geometry": {"coordinates":[-97.0925,18.52139],"type":"Point"}
}