{
  "type": "Feature",
  "properties": {
    "gn:admin1_code":"12",
    "gn:admin2_code":"68",
    "gn:asciiname":"Cervantes",
    "gn:country_code":"MX",
    "gn:dem":675,
    "gn:feature_class":"P",
    "gn:feature_code":"PPL",
    "gn:name":"Cervantes",
    "gn:population":27,
    "gn:timezone":"America/Mexico_City",
    "iso:country":"MX",
    "wof:name":"Cervantes",
    "wof:placetype":"locality",
    "wof:population":27
},
  "geometry": {"coordinates":[-101.51835,17.97853],"type":"Point"}
}