{
  "type": "Feature",
  "properties": {
    "gn:admin1_code":"14",
    "gn:admin2_code":"10.0",
    "gn:asciiname":"El Ecole",
    "gn:country_code":"MX",
    "gn:dem":2581,
    "gn:feature_class":"P",
    "gn:feature_code":"PPL",
    "gn:name":"El \u00c9cole",
    "gn:population":6,
    "gn:timezone":"America/Mexico_City",
    "iso:country":"MX",
    "name:und_x_variant":[
        "El \u00c9cole"
    ],
    "wof:name":"El Ecole",
    "wof:placetype":"locality",
    "wof:population":6
},
  "geometry": {"coordinates":[-103.66,20.10028],"type":"Point"}
}