{
  "type": "Feature",
  "properties": {
    "gn:admin1_code":"24",
    "gn:admin2_code":"36.0",
    "gn:asciiname":"Aguilares",
    "gn:country_code":"MX",
    "gn:dem":362,
    "gn:feature_class":"P",
    "gn:feature_code":"PPL",
    "gn:name":"Aguilares",
    "gn:population":9,
    "gn:timezone":"America/Mexico_City",
    "iso:country":"MX",
    "name:ceb_x_preferred":[
        "Aguilares"
    ],
    "name:fra_x_preferred":[
        "Aguilares"
    ],
    "name:glg_x_preferred":[
        "Aguilares"
    ],
    "name:nld_x_preferred":[
        "Aguilares"
    ],
    "name:por_x_preferred":[
        "Aguilares"
    ],
    "name:spa_x_preferred":[
        "Aguilares"
    ],
    "name:swe_x_preferred":[
        "Aguilares"
    ],
    "wof:name":"Aguilares",
    "wof:placetype":"locality",
    "wof:population":9
},
  "geometry": {"coordinates":[-99.35639,21.9625],"type":"Point"}
}