{
  "type": "Feature",
  "properties": {
    "gn:admin1_code":"7.0",
    "gn:admin2_code":"18.0",
    "gn:asciiname":"El Consuelo",
    "gn:country_code":"MX",
    "gn:dem":540,
    "gn:feature_class":"P",
    "gn:feature_code":"PPL",
    "gn:name":"El Consuelo",
    "gn:population":0,
    "gn:timezone":"America/Monterrey",
    "iso:country":"MX",
    "name:spa_x_preferred":[
        "El Consuelo"
    ],
    "wof:name":"El Consuelo",
    "wof:placetype":"locality"
},
  "geometry": {"coordinates":[-101.38647,26.96221],"type":"Point"}
}