{
  "type": "Feature",
  "properties": {
    "gn:admin1_code":"21",
    "gn:admin2_code":"208.0",
    "gn:asciiname":"Dos Cerritos",
    "gn:country_code":"MX",
    "gn:dem":2236,
    "gn:feature_class":"P",
    "gn:feature_code":"PPL",
    "gn:name":"Dos Cerritos",
    "gn:population":370,
    "gn:timezone":"America/Mexico_City",
    "iso:country":"MX",
    "wof:name":"Dos Cerritos",
    "wof:placetype":"locality",
    "wof:population":370
},
  "geometry": {"coordinates":[-97.99972,19.88],"type":"Point"}
}