{
  "type": "Feature",
  "properties": {
    "gn:admin1_code":"19",
    "gn:admin2_code":"49.0",
    "gn:asciiname":"San Jose Sur",
    "gn:country_code":"MX",
    "gn:dem":499,
    "gn:feature_class":"P",
    "gn:feature_code":"PPL",
    "gn:name":"San Jos\u00e9 Sur",
    "gn:population":0,
    "gn:timezone":"America/Monterrey",
    "iso:country":"MX",
    "name:spa_x_preferred":[
        "San Jos\u00e9 Sur"
    ],
    "wof:name":"San Jose Sur",
    "wof:placetype":"locality"
},
  "geometry": {"coordinates":[-100.11835000000001,25.37956],"type":"Point"}
}