{
  "type": "Feature",
  "properties": {
    "gn:admin1_code":"11.0",
    "gn:asciiname":"El Cabrito",
    "gn:country_code":"MX",
    "gn:dem":1760,
    "gn:feature_class":"P",
    "gn:feature_code":"PPL",
    "gn:name":"El Cabrito",
    "gn:population":0,
    "gn:timezone":"America/Mexico_City",
    "iso:country":"MX",
    "name:spa_x_preferred":[
        "El Cabrito"
    ],
    "wof:name":"El Cabrito",
    "wof:placetype":"locality"
},
  "geometry": {"coordinates":[-101.99185,20.83667],"type":"Point"}
}