{
  "type": "Feature",
  "properties": {
    "gn:admin1_code":"7.0",
    "gn:admin2_code":"3.0",
    "gn:asciiname":"Ojo de Esteban",
    "gn:country_code":"MX",
    "gn:dem":386,
    "gn:feature_class":"P",
    "gn:feature_code":"PPL",
    "gn:name":"Ojo de Esteban",
    "gn:population":0,
    "gn:timezone":"America/Monterrey",
    "iso:country":"MX",
    "name:spa_x_preferred":[
        "Ojo de Esteban"
    ],
    "wof:name":"Ojo de Esteban",
    "wof:placetype":"locality"
},
  "geometry": {"coordinates":[-100.88227999999999,28.35066],"type":"Point"}
}