{
  "type": "Feature",
  "properties": {
    "gn:admin1_code":"6",
    "gn:admin2_code":"40",
    "gn:asciiname":"Vino Trigo y Aceite [Casa Hogar]",
    "gn:country_code":"MX",
    "gn:dem":2114,
    "gn:feature_class":"P",
    "gn:feature_code":"PPL",
    "gn:name":"Vino Trigo y Aceite [Casa Hogar]",
    "gn:population":31,
    "gn:timezone":"America/Chihuahua",
    "iso:country":"MX",
    "wof:name":"Vino Trigo y Aceite [Casa Hogar]",
    "wof:placetype":"locality",
    "wof:population":31
},
  "geometry": {"coordinates":[-108.13611000000002,29.21528],"type":"Point"}
}