{
  "type": "Feature",
  "properties": {
    "gn:admin1_code":"6",
    "gn:admin2_code":"11.0",
    "gn:asciiname":"Las Pailas",
    "gn:country_code":"MX",
    "gn:dem":1316,
    "gn:feature_class":"P",
    "gn:feature_code":"PPL",
    "gn:name":"Las Pailas",
    "gn:population":0,
    "gn:timezone":"America/Chihuahua",
    "iso:country":"MX",
    "name:spa_x_preferred":[
        "Las Pailas"
    ],
    "wof:name":"Las Pailas",
    "wof:placetype":"locality"
},
  "geometry": {"coordinates":[-103.94750999999999,28.21014000000001],"type":"Point"}
}