{
  "type": "Feature",
  "properties": {
    "gn:admin1_code":"31",
    "gn:admin2_code":"50.0",
    "gn:asciiname":"El Ramonal",
    "gn:country_code":"MX",
    "gn:dem":13,
    "gn:feature_class":"P",
    "gn:feature_code":"PPL",
    "gn:name":"El Ramonal",
    "gn:population":7,
    "gn:timezone":"America/Merida",
    "iso:country":"MX",
    "wof:name":"El Ramonal",
    "wof:placetype":"locality",
    "wof:population":7
},
  "geometry": {"coordinates":[-89.60361,20.90472],"type":"Point"}
}