{
  "type": "Feature",
  "properties": {
    "gn:admin1_code":"15",
    "gn:admin2_code":"88.0",
    "gn:asciiname":"San Jose Teneria (Teneria)",
    "gn:country_code":"MX",
    "gn:dem":2061,
    "gn:feature_class":"P",
    "gn:feature_code":"PPL",
    "gn:name":"San Jos\u00e9 Tener\u00eda (Tener\u00eda)",
    "gn:population":2402,
    "gn:timezone":"America/Mexico_City",
    "iso:country":"MX",
    "name:und_x_variant":[
        "San Jos\u00e9 Tener\u00eda (Tener\u00eda)"
    ],
    "wof:name":"San Jose Teneria (Teneria)",
    "wof:placetype":"locality",
    "wof:population":2402
},
  "geometry": {"coordinates":[-99.54306,18.95028],"type":"Point"}
}