{
  "type": "Feature",
  "properties": {
    "gn:admin1_code":"11",
    "gn:admin2_code":"8.0",
    "gn:asciiname":"Vista Hermosa de Guillen",
    "gn:country_code":"MX",
    "gn:dem":1738,
    "gn:feature_class":"P",
    "gn:feature_code":"PPL",
    "gn:name":"Vista Hermosa de Guill\u00e9n",
    "gn:population":7,
    "gn:timezone":"America/Mexico_City",
    "iso:country":"MX",
    "name:und_x_variant":[
        "Vista Hermosa de Guill\u00e9n"
    ],
    "wof:name":"Vista Hermosa de Guillen",
    "wof:placetype":"locality",
    "wof:population":7
},
  "geometry": {"coordinates":[-101.76972000000001,20.73556],"type":"Point"}
}