{
  "type": "Feature",
  "properties": {
    "gn:admin1_code":"16",
    "gn:admin2_code":"82.0",
    "gn:asciiname":"San Agustin",
    "gn:country_code":"MX",
    "gn:dem":1719,
    "gn:feature_class":"P",
    "gn:feature_code":"PPL",
    "gn:name":"San Agust\u00edn",
    "gn:population":335,
    "gn:timezone":"America/Mexico_City",
    "iso:country":"MX",
    "name:und_x_variant":[
        "San Agust\u00edn"
    ],
    "wof:name":"San Agustin",
    "wof:placetype":"locality",
    "wof:population":335
},
  "geometry": {"coordinates":[-101.51389,19.2325],"type":"Point"}
}