{
  "type": "Feature",
  "properties": {
    "gn:admin1_code":"30",
    "gn:admin2_code":"155.0",
    "gn:asciiname":"Los Manantiales",
    "gn:country_code":"MX",
    "gn:dem":119,
    "gn:feature_class":"P",
    "gn:feature_code":"PPL",
    "gn:name":"Los Manantiales",
    "gn:population":0,
    "gn:timezone":"America/Mexico_City",
    "iso:country":"MX",
    "name:spa_x_preferred":[
        "Los Manantiales"
    ],
    "name:und_x_variant":[
        "Manantiales"
    ],
    "wof:name":"Los Manantiales",
    "wof:placetype":"locality"
},
  "geometry": {"coordinates":[-98.14881,21.14242],"type":"Point"}
}