{
  "type": "Feature",
  "properties": {
    "gn:admin1_code":"28.0",
    "gn:admin2_code":"3.0",
    "gn:asciiname":"Villa Manresa",
    "gn:country_code":"MX",
    "gn:dem":78,
    "gn:feature_class":"P",
    "gn:feature_code":"PPL",
    "gn:name":"Villa Manresa",
    "gn:population":4,
    "gn:timezone":"America/Monterrey",
    "iso:country":"MX",
    "name:spa_x_preferred":[
        "Villa Manresa"
    ],
    "wof:name":"Villa Manresa",
    "wof:placetype":"locality",
    "wof:population":4
},
  "geometry": {"coordinates":[-98.10944000000001,22.50917],"type":"Point"}
}