{
  "type": "Feature",
  "properties": {
    "gn:admin1_code":"6.0",
    "gn:asciiname":"El Siete",
    "gn:country_code":"MX",
    "gn:dem":1266,
    "gn:feature_class":"P",
    "gn:feature_code":"PPL",
    "gn:name":"El Siete",
    "gn:population":0,
    "gn:timezone":"America/Chihuahua",
    "iso:country":"MX",
    "name:spa_x_preferred":[
        "El Siete"
    ],
    "wof:name":"El Siete",
    "wof:placetype":"locality"
},
  "geometry": {"coordinates":[-105.42979,28.05191],"type":"Point"}
}