{
  "type": "Feature",
  "properties": {
    "gn:admin1_code":"14",
    "gn:admin2_code":"58.0",
    "gn:asciiname":"El Pantano (Galope)",
    "gn:country_code":"MX",
    "gn:dem":1543,
    "gn:feature_class":"P",
    "gn:feature_code":"PPL",
    "gn:name":"El Pantano (Galope)",
    "gn:population":128,
    "gn:timezone":"America/Mexico_City",
    "iso:country":"MX",
    "wof:name":"El Pantano (Galope)",
    "wof:placetype":"locality",
    "wof:population":128
},
  "geometry": {"coordinates":[-104.75472000000001,20.58],"type":"Point"}
}