{
  "type": "Feature",
  "properties": {
    "gn:admin1_code":"10",
    "gn:admin2_code":"34.0",
    "gn:asciiname":"La Junta",
    "gn:country_code":"MX",
    "gn:dem":437,
    "gn:feature_class":"P",
    "gn:feature_code":"PPL",
    "gn:name":"La Junta",
    "gn:population":0,
    "gn:timezone":"America/Monterrey",
    "iso:country":"MX",
    "name:und_x_variant":[
        "Las Juntas",
        "La Junta"
    ],
    "wof:name":"La Junta",
    "wof:placetype":"locality"
},
  "geometry": {"coordinates":[-106.74333,25.05623],"type":"Point"}
}