{
  "type": "Feature",
  "properties": {
    "gn:admin1_code":"15.0",
    "gn:asciiname":"Santa Maria Magdalena",
    "gn:country_code":"MX",
    "gn:dem":2687,
    "gn:feature_class":"P",
    "gn:feature_code":"PPL",
    "gn:name":"Santa Mar\u00eda Magdalena",
    "gn:population":0,
    "gn:timezone":"America/Mexico_City",
    "iso:country":"MX",
    "name:spa_x_preferred":[
        "Santa Mar\u00eda Magdalena"
    ],
    "wof:name":"Santa Maria Magdalena",
    "wof:placetype":"locality"
},
  "geometry": {"coordinates":[-98.75199000000001,19.53051],"type":"Point"}
}