{
  "type": "Feature",
  "properties": {
    "gn:admin1_code":"5",
    "gn:admin2_code":"93.0",
    "gn:asciiname":"Kokil",
    "gn:country_code":"MX",
    "gn:dem":1460,
    "gn:feature_class":"P",
    "gn:feature_code":"PPL",
    "gn:name":"Kokil",
    "gn:population":120,
    "gn:timezone":"America/Mexico_City",
    "iso:country":"MX",
    "wof:name":"Kokil",
    "wof:placetype":"locality",
    "wof:population":120
},
  "geometry": {"coordinates":[-92.47889000000001,16.91207],"type":"Point"}
}