{
  "type": "Feature",
  "properties": {
    "gn:admin1_code":"12",
    "gn:admin2_code":"35.0",
    "gn:asciiname":"Colonia Rancho del Cura (El Cura)",
    "gn:country_code":"MX",
    "gn:dem":898,
    "gn:feature_class":"P",
    "gn:feature_code":"PPL",
    "gn:name":"Colonia Rancho del Cura (El Cura)",
    "gn:population":699,
    "gn:timezone":"America/Mexico_City",
    "iso:country":"MX",
    "wof:name":"Colonia Rancho del Cura (El Cura)",
    "wof:placetype":"locality",
    "wof:population":699
},
  "geometry": {"coordinates":[-99.51111,18.29361],"type":"Point"}
}