{
  "type": "Feature",
  "properties": {
    "gn:admin1_code":"15",
    "gn:admin2_code":"57.0",
    "gn:asciiname":"Ampliacion el Tejocote",
    "gn:country_code":"MX",
    "gn:dem":2397,
    "gn:feature_class":"P",
    "gn:feature_code":"PPL",
    "gn:name":"Ampliaci\u00f3n el Tejocote",
    "gn:population":731,
    "gn:timezone":"America/Mexico_City",
    "iso:country":"MX",
    "name:und_x_variant":[
        "Ampliaci\u00f3n el Tejocote"
    ],
    "wof:name":"Ampliacion el Tejocote",
    "wof:placetype":"locality",
    "wof:population":731
},
  "geometry": {"coordinates":[-99.28989,19.48502],"type":"Point"}
}