{
  "type": "Feature",
  "properties": {
    "gn:admin1_code":"5",
    "gn:admin2_code":"118",
    "gn:asciiname":"El Palmar (San Miguel)",
    "gn:country_code":"MX",
    "gn:dem":1389,
    "gn:feature_class":"P",
    "gn:feature_code":"PPL",
    "gn:name":"El Palmar (San Miguel)",
    "gn:population":13,
    "gn:timezone":"America/Mexico_City",
    "iso:country":"MX",
    "wof:name":"El Palmar (San Miguel)",
    "wof:placetype":"locality",
    "wof:population":13
},
  "geometry": {"coordinates":[-92.795,17.1325],"type":"Point"}
}