{
  "type": "Feature",
  "properties": {
    "gn:admin1_code":"15",
    "gn:admin2_code":"81.0",
    "gn:asciiname":"Ejido San Francisco",
    "gn:country_code":"MX",
    "gn:dem":2265,
    "gn:feature_class":"P",
    "gn:feature_code":"PPL",
    "gn:name":"Ejido San Francisco",
    "gn:population":246,
    "gn:timezone":"America/Mexico_City",
    "iso:country":"MX",
    "wof:name":"Ejido San Francisco",
    "wof:placetype":"locality",
    "wof:population":246
},
  "geometry": {"coordinates":[-99.0166,19.66455],"type":"Point"}
}