{
  "type": "Feature",
  "properties": {
    "gn:admin1_code":"1",
    "gn:admin2_code":"9",
    "gn:asciiname":"Las Tapias",
    "gn:country_code":"MX",
    "gn:dem":1916,
    "gn:feature_class":"P",
    "gn:feature_code":"PPL",
    "gn:name":"Las Tapias",
    "gn:population":11,
    "gn:timezone":"America/Mexico_City",
    "iso:country":"MX",
    "wof:name":"Las Tapias",
    "wof:placetype":"locality",
    "wof:population":11
},
  "geometry": {"coordinates":[-102.26083,22.22611],"type":"Point"}
}