{
  "type": "Feature",
  "properties": {
    "gn:admin1_code":"12.0",
    "gn:admin2_code":"64.0",
    "gn:asciiname":"San Jacinto",
    "gn:country_code":"MX",
    "gn:dem":453,
    "gn:feature_class":"P",
    "gn:feature_code":"PPL",
    "gn:name":"San Jacinto",
    "gn:population":0,
    "gn:timezone":"America/Mexico_City",
    "iso:country":"MX",
    "name:spa_x_preferred":[
        "San Jacinto"
    ],
    "wof:name":"San Jacinto",
    "wof:placetype":"locality"
},
  "geometry": {"coordinates":[-100.48792,18.44457],"type":"Point"}
}