{
  "type": "Feature",
  "properties": {
    "gn:admin1_code":"5.0",
    "gn:admin2_code":"23.0",
    "gn:asciiname":"Muquen",
    "gn:country_code":"MX",
    "gn:dem":2331,
    "gn:feature_class":"P",
    "gn:feature_code":"PPL",
    "gn:name":"Muquen",
    "gn:population":0,
    "gn:timezone":"America/Mexico_City",
    "iso:country":"MX",
    "name:spa_x_preferred":[
        "Muquem"
    ],
    "name:spa_x_variant":[
        "Muquen"
    ],
    "wof:name":"Muquen",
    "wof:placetype":"locality"
},
  "geometry": {"coordinates":[-92.60951,16.80847],"type":"Point"}
}