{
  "type": "Feature",
  "properties": {
    "gn:admin1_code":"32.0",
    "gn:admin2_code":"26.0",
    "gn:asciiname":"Santa Ines",
    "gn:country_code":"MX",
    "gn:dem":1869,
    "gn:feature_class":"P",
    "gn:feature_code":"PPL",
    "gn:name":"Santa In\u00e9s",
    "gn:population":0,
    "gn:timezone":"America/Mexico_City",
    "iso:country":"MX",
    "name:spa_x_preferred":[
        "Santa In\u00e9s"
    ],
    "wof:name":"Santa Ines",
    "wof:placetype":"locality"
},
  "geometry": {"coordinates":[-102.35854999999999,24.16388],"type":"Point"}
}