{
  "type": "Feature",
  "properties": {
    "gn:admin1_code":"30",
    "gn:admin2_code":"125.0",
    "gn:asciiname":"Mata Calabaza",
    "gn:country_code":"MX",
    "gn:dem":375,
    "gn:feature_class":"P",
    "gn:feature_code":"PPL",
    "gn:name":"Mata Calabaza",
    "gn:population":0,
    "gn:timezone":"America/Mexico_City",
    "iso:country":"MX",
    "wof:name":"Mata Calabaza",
    "wof:placetype":"locality"
},
  "geometry": {"coordinates":[-96.64673999999999,18.96475],"type":"Point"}
}