{
  "type": "Feature",
  "properties": {
    "gn:admin1_code":"28.0",
    "gn:admin2_code":"11.0",
    "gn:asciiname":"Los Mateos",
    "gn:country_code":"MX",
    "gn:dem":89,
    "gn:feature_class":"P",
    "gn:feature_code":"PPL",
    "gn:name":"Los Mateos",
    "gn:population":2,
    "gn:timezone":"America/Monterrey",
    "iso:country":"MX",
    "name:spa_x_preferred":[
        "Los Mateos"
    ],
    "wof:name":"Los Mateos",
    "wof:placetype":"locality",
    "wof:population":2
},
  "geometry": {"coordinates":[-99.08389,22.93694],"type":"Point"}
}