{
  "type": "Feature",
  "properties": {
    "gn:admin1_code":"6.0",
    "gn:asciiname":"La Manga",
    "gn:country_code":"MX",
    "gn:dem":1562,
    "gn:feature_class":"P",
    "gn:feature_code":"PPL",
    "gn:name":"La Manga",
    "gn:population":0,
    "gn:timezone":"America/Chihuahua",
    "iso:country":"MX",
    "name:spa_x_preferred":[
        "La Manga"
    ],
    "wof:name":"La Manga",
    "wof:placetype":"locality"
},
  "geometry": {"coordinates":[-106.2685,29.04842],"type":"Point"}
}