{
  "type": "Feature",
  "properties": {
    "gn:admin1_code":"6",
    "gn:admin2_code":"11.0",
    "gn:asciiname":"Los Colorados",
    "gn:country_code":"MX",
    "gn:dem":1319,
    "gn:feature_class":"P",
    "gn:feature_code":"PPL",
    "gn:name":"Los Colorados",
    "gn:population":0,
    "gn:timezone":"America/Chihuahua",
    "iso:country":"MX",
    "name:deu_x_preferred":[
        "Los Colorados"
    ],
    "name:est_x_preferred":[
        "Los Colorados"
    ],
    "name:nld_x_preferred":[
        "Los Colorados"
    ],
    "name:pol_x_preferred":[
        "Los Colorados"
    ],
    "name:spa_x_preferred":[
        "Los Colorados"
    ],
    "name:ukr_x_preferred":[
        "Los Colorados"
    ],
    "wof:name":"Los Colorados",
    "wof:placetype":"locality"
},
  "geometry": {"coordinates":[-103.96704,28.25299],"type":"Point"}
}