{
  "type": "Feature",
  "properties": {
    "gn:admin1_code":"14",
    "gn:admin2_code":"120.0",
    "gn:asciiname":"El Placer",
    "gn:country_code":"MX",
    "gn:dem":996,
    "gn:feature_class":"P",
    "gn:feature_code":"PPL",
    "gn:name":"El Placer",
    "gn:population":7,
    "gn:timezone":"America/Mexico_City",
    "iso:country":"MX",
    "wof:name":"El Placer",
    "wof:placetype":"locality",
    "wof:population":7
},
  "geometry": {"coordinates":[-103.33278,20.84833],"type":"Point"}
}