{
  "type": "Feature",
  "properties": {
    "gn:admin1_code":"21.0",
    "gn:admin2_code":"86.0",
    "gn:asciiname":"La Luz",
    "gn:country_code":"MX",
    "gn:dem":583,
    "gn:feature_class":"P",
    "gn:feature_code":"PPL",
    "gn:name":"La Luz",
    "gn:population":0,
    "gn:timezone":"America/Mexico_City",
    "iso:country":"MX",
    "name:spa_x_preferred":[
        "La Luz"
    ],
    "wof:name":"La Luz",
    "wof:placetype":"locality"
},
  "geometry": {"coordinates":[-97.85229,20.4291],"type":"Point"}
}