{
  "type": "Feature",
  "properties": {
    "gn:admin1_code":"25",
    "gn:admin2_code":"4.0",
    "gn:asciiname":"La Colonia",
    "gn:country_code":"MX",
    "gn:dem":195,
    "gn:feature_class":"P",
    "gn:feature_code":"PPL",
    "gn:name":"La Colonia",
    "gn:population":0,
    "gn:timezone":"America/Mazatlan",
    "iso:country":"MX",
    "wof:name":"La Colonia",
    "wof:placetype":"locality"
},
  "geometry": {"coordinates":[-106.13333,23.46667],"type":"Point"}
}