{
  "type": "Feature",
  "properties": {
    "gn:admin1_code":"16",
    "gn:admin2_code":"102.0",
    "gn:asciiname":"Nuevo Zirosto",
    "gn:country_code":"MX",
    "gn:dem":1910,
    "gn:feature_class":"P",
    "gn:feature_code":"PPL",
    "gn:name":"Nuevo Zirosto",
    "gn:population":2239,
    "gn:timezone":"America/Mexico_City",
    "iso:country":"MX",
    "wof:name":"Nuevo Zirosto",
    "wof:placetype":"locality",
    "wof:population":2239
},
  "geometry": {"coordinates":[-102.34833,19.54806],"type":"Point"}
}