{
  "type": "Feature",
  "properties": {
    "gn:admin1_code":"1",
    "gn:admin2_code":"6",
    "gn:asciiname":"El Rosario [Granja]",
    "gn:country_code":"MX",
    "gn:dem":1884,
    "gn:feature_class":"P",
    "gn:feature_code":"PPL",
    "gn:name":"El Rosario [Granja]",
    "gn:population":20,
    "gn:timezone":"America/Mexico_City",
    "iso:country":"MX",
    "wof:name":"El Rosario [Granja]",
    "wof:placetype":"locality",
    "wof:population":20
},
  "geometry": {"coordinates":[-102.27472,22.0925],"type":"Point"}
}