{
  "type": "Feature",
  "properties": {
    "gn:admin1_code":"3.0",
    "gn:admin2_code":"8.0",
    "gn:asciiname":"El Paraje",
    "gn:cc2":"MX",
    "gn:country_code":"MX",
    "gn:dem":790,
    "gn:feature_class":"P",
    "gn:feature_code":"PPL",
    "gn:name":"El Paraje",
    "gn:population":0,
    "gn:timezone":"America/Mazatlan",
    "iso:country":"MX",
    "name:und_x_variant":[
        "Paraje",
        "El Paraje"
    ],
    "wof:name":"El Paraje",
    "wof:placetype":"locality"
},
  "geometry": {"coordinates":[-109.83333,23.08333],"type":"Point"}
}