{
  "type": "Feature",
  "properties": {
    "gn:admin1_code":"11",
    "gn:admin2_code":"23",
    "gn:asciiname":"Cerro Colorado",
    "gn:country_code":"MX",
    "gn:dem":2161,
    "gn:feature_class":"P",
    "gn:feature_code":"PPL",
    "gn:name":"Cerro Colorado",
    "gn:population":20,
    "gn:timezone":"America/Mexico_City",
    "iso:country":"MX",
    "wof:name":"Cerro Colorado",
    "wof:placetype":"locality",
    "wof:population":20
},
  "geometry": {"coordinates":[-101.77528,20.53639],"type":"Point"}
}