{
  "type": "Feature",
  "properties": {
    "gn:admin1_code":"7.0",
    "gn:asciiname":"Capichola",
    "gn:country_code":"MX",
    "gn:dem":641,
    "gn:feature_class":"P",
    "gn:feature_code":"PPL",
    "gn:name":"Capichola",
    "gn:population":0,
    "gn:timezone":"America/Monterrey",
    "iso:country":"MX",
    "name:spa_x_preferred":[
        "Capichola"
    ],
    "wof:name":"Capichola",
    "wof:placetype":"locality"
},
  "geometry": {"coordinates":[-101.24549,26.90756],"type":"Point"}
}