{
  "type": "Feature",
  "properties": {
    "gn:admin1_code":"31",
    "gn:admin2_code":"16.0",
    "gn:asciiname":"Sal",
    "gn:country_code":"MX",
    "gn:dem":27,
    "gn:feature_class":"P",
    "gn:feature_code":"PPL",
    "gn:name":"Sal",
    "gn:population":0,
    "gn:timezone":"America/Merida",
    "iso:country":"MX",
    "name:arg_x_preferred":[
        "Sal"
    ],
    "name:ast_x_preferred":[
        "Sal"
    ],
    "name:ben_x_preferred":[
        "\u09b8\u09be\u09b2"
    ],
    "name:cat_x_preferred":[
        "Sal"
    ],
    "name:ceb_x_preferred":[
        "Sal"
    ],
    "name:ces_x_preferred":[
        "Sal"
    ],
    "name:dan_x_preferred":[
        "Sal"
    ],
    "name:fas_x_preferred":[
        "\u0633\u0627\u0644"
    ],
    "name:fin_x_preferred":[
        "Sal"
    ],
    "name:fra_x_preferred":[
        "Sal"
    ],
    "name:glg_x_preferred":[
        "Sal"
    ],
    "name:hat_x_preferred":[
        "Sal"
    ],
    "name:heb_x_preferred":[
        "\u05e1\u05d0\u05dc"
    ],
    "name:hun_x_preferred":[
        "Sal"
    ],
    "name:nds_x_preferred":[
        "Sal"
    ],
    "name:nld_x_preferred":[
        "Sal"
    ],
    "name:nno_x_preferred":[
        "Sal"
    ],
    "name:nor_x_preferred":[
        "Sal"
    ],
    "name:por_x_preferred":[
        "Sal"
    ],
    "name:slk_x_preferred":[
        "Sal"
    ],
    "name:spa_x_preferred":[
        "Sal"
    ],
    "name:swe_x_preferred":[
        "Sal"
    ],
    "name:tur_x_preferred":[
        "Sal"
    ],
    "name:vie_x_preferred":[
        "\u0110\u1ea3o Sal"
    ],
    "wof:name":"Sal",
    "wof:placetype":"locality"
},
  "geometry": {"coordinates":[-88.98333,20.25],"type":"Point"}
}