{
  "type": "Feature",
  "properties": {
    "gn:admin1_code":"31",
    "gn:admin2_code":"16.0",
    "gn:asciiname":"Sal",
    "gn:country_code":"MX",
    "gn:dem":27,
    "gn:feature_class":"P",
    "gn:feature_code":"PPL",
    "gn:name":"Sal",
    "gn:population":0,
    "gn:timezone":"America/Merida",
    "iso:country":"MX",
    "wof:name":"Sal",
    "wof:placetype":"locality"
},
  "geometry": {"coordinates":[-88.98333000000002,20.25],"type":"Point"}
}