{
  "type": "Feature",
  "properties": {
    "gn:admin1_code":"5",
    "gn:admin2_code":"16.0",
    "gn:asciiname":"El Diamante",
    "gn:country_code":"MX",
    "gn:dem":14,
    "gn:feature_class":"P",
    "gn:feature_code":"PPL",
    "gn:name":"El Diamante",
    "gn:population":8,
    "gn:timezone":"America/Mexico_City",
    "iso:country":"MX",
    "wof:name":"El Diamante",
    "wof:placetype":"locality",
    "wof:population":8
},
  "geometry": {"coordinates":[-92.08083000000001,17.69917000000001],"type":"Point"}
}