{
  "type": "Feature",
  "properties": {
    "gn:admin1_code":"21",
    "gn:admin2_code":"44.0",
    "gn:asciiname":"Tetepongo",
    "gn:country_code":"MX",
    "gn:dem":2465,
    "gn:feature_class":"P",
    "gn:feature_code":"PPL",
    "gn:name":"Tetepongo",
    "gn:population":0,
    "gn:timezone":"America/Mexico_City",
    "iso:country":"MX",
    "name:spa_x_preferred":[
        "Tetepongo"
    ],
    "wof:name":"Tetepongo",
    "wof:placetype":"locality"
},
  "geometry": {"coordinates":[-97.60699,19.60953],"type":"Point"}
}