{
  "type": "Feature",
  "properties": {
    "gn:admin1_code":"15",
    "gn:admin2_code":"21.0",
    "gn:asciiname":"Las Mesas",
    "gn:country_code":"MX",
    "gn:dem":2321,
    "gn:feature_class":"P",
    "gn:feature_code":"PPL",
    "gn:name":"Las Mesas",
    "gn:population":0,
    "gn:timezone":"America/Mexico_City",
    "iso:country":"MX",
    "name:spa_x_preferred":[
        "Las Mesas"
    ],
    "wof:name":"Las Mesas",
    "wof:placetype":"locality"
},
  "geometry": {"coordinates":[-99.82781,18.92673],"type":"Point"}
}