{
  "type": "Feature",
  "properties": {
    "gn:admin1_code":"5",
    "gn:admin2_code":"50.0",
    "gn:asciiname":"El Guano 1ra. Seccion",
    "gn:country_code":"MX",
    "gn:dem":45,
    "gn:feature_class":"P",
    "gn:feature_code":"PPL",
    "gn:name":"El Guano 1ra. Secci\u00f3n",
    "gn:population":6,
    "gn:timezone":"America/Mexico_City",
    "iso:country":"MX",
    "name:und_x_variant":[
        "El Guano 1ra. Secci\u00f3n"
    ],
    "wof:name":"El Guano 1ra. Seccion",
    "wof:placetype":"locality",
    "wof:population":6
},
  "geometry": {"coordinates":[-91.71722,17.52556],"type":"Point"}
}