{
  "type": "Feature",
  "properties": {
    "gn:admin1_code":"6",
    "gn:admin2_code":"42.0",
    "gn:asciiname":"La Jarita",
    "gn:country_code":"MX",
    "gn:dem":1502,
    "gn:feature_class":"P",
    "gn:feature_code":"PPL",
    "gn:name":"La Jarita",
    "gn:population":0,
    "gn:timezone":"America/Chihuahua",
    "iso:country":"MX",
    "name:spa_x_preferred":[
        "La Jarita"
    ],
    "name:und_x_variant":[
        "Rancho La Jarita"
    ],
    "wof:name":"La Jarita",
    "wof:placetype":"locality"
},
  "geometry": {"coordinates":[-104.06905999999999,28.77375],"type":"Point"}
}