{
  "type": "Feature",
  "properties": {
    "gn:admin1_code":"6.0",
    "gn:admin2_code":"9.0",
    "gn:asciiname":"Bacarato",
    "gn:country_code":"MX",
    "gn:dem":2216,
    "gn:feature_class":"P",
    "gn:feature_code":"PPL",
    "gn:name":"Bacarato",
    "gn:population":0,
    "gn:timezone":"America/Chihuahua",
    "iso:country":"MX",
    "name:spa_x_preferred":[
        "Bacarato"
    ],
    "name:und_x_variant":[
        "Bacaratus"
    ],
    "wof:name":"Bacarato",
    "wof:placetype":"locality"
},
  "geometry": {"coordinates":[-107.49466,27.80895],"type":"Point"}
}