{
  "type": "Feature",
  "properties": {
    "gn:admin1_code":"15.0",
    "gn:admin2_code":"123.0",
    "gn:asciiname":"Palos Verdes",
    "gn:country_code":"MX",
    "gn:dem":562,
    "gn:feature_class":"P",
    "gn:feature_code":"PPL",
    "gn:name":"Palos Verdes",
    "gn:population":0,
    "gn:timezone":"America/Mexico_City",
    "iso:country":"MX",
    "name:spa_x_preferred":[
        "Palos Verdes"
    ],
    "wof:name":"Palos Verdes",
    "wof:placetype":"locality"
},
  "geometry": {"coordinates":[-100.52091,18.95483],"type":"Point"}
}