{
  "type": "Feature",
  "properties": {
    "gn:admin1_code":"20",
    "gn:admin2_code":"526",
    "gn:asciiname":"La Pitiona",
    "gn:country_code":"MX",
    "gn:dem":482,
    "gn:feature_class":"P",
    "gn:feature_code":"PPL",
    "gn:name":"La Pitiona",
    "gn:population":20,
    "gn:timezone":"America/Mexico_City",
    "iso:country":"MX",
    "wof:name":"La Pitiona",
    "wof:placetype":"locality",
    "wof:population":20
},
  "geometry": {"coordinates":[-97.14694,16.11833],"type":"Point"}
}