{
  "type": "Feature",
  "properties": {
    "gn:admin1_code":"26",
    "gn:admin2_code":"3.0",
    "gn:asciiname":"El Tepeguaje",
    "gn:country_code":"MX",
    "gn:dem":385,
    "gn:feature_class":"P",
    "gn:feature_code":"PPL",
    "gn:name":"El Tepeguaje",
    "gn:population":0,
    "gn:timezone":"America/Hermosillo",
    "iso:country":"MX",
    "name:spa_x_preferred":[
        "El Tepeguaje"
    ],
    "name:und_x_variant":[
        "Tepehuajes"
    ],
    "wof:name":"El Tepeguaje",
    "wof:placetype":"locality"
},
  "geometry": {"coordinates":[-108.77539,26.92987],"type":"Point"}
}