{
  "type": "Feature",
  "properties": {
    "gn:admin1_code":"6",
    "gn:admin2_code":"32.0",
    "gn:asciiname":"San Andres",
    "gn:country_code":"MX",
    "gn:dem":1782,
    "gn:feature_class":"P",
    "gn:feature_code":"PPL",
    "gn:name":"San Andr\u00e9s",
    "gn:population":0,
    "gn:timezone":"America/Chihuahua",
    "iso:country":"MX",
    "name:spa_x_preferred":[
        "San Andr\u00e9s"
    ],
    "wof:name":"San Andres",
    "wof:placetype":"locality"
},
  "geometry": {"coordinates":[-105.75530999999999,27.08756],"type":"Point"}
}