{
  "type": "Feature",
  "properties": {
    "gn:admin1_code":"30",
    "gn:admin2_code":"24.0",
    "gn:asciiname":"Kuapol",
    "gn:country_code":"MX",
    "gn:dem":1298,
    "gn:feature_class":"P",
    "gn:feature_code":"PPL",
    "gn:name":"Kuapol",
    "gn:population":150,
    "gn:timezone":"America/Mexico_City",
    "iso:country":"MX",
    "wof:name":"Kuapol",
    "wof:placetype":"locality",
    "wof:population":150
},
  "geometry": {"coordinates":[-96.96417,19.2475],"type":"Point"}
}