{
  "type": "Feature",
  "properties": {
    "gn:admin1_code":"20",
    "gn:admin2_code":"352.0",
    "gn:asciiname":"Canada del Tecolote",
    "gn:country_code":"MX",
    "gn:dem":1718,
    "gn:feature_class":"P",
    "gn:feature_code":"PPL",
    "gn:name":"Ca\u00f1ada del Tecolote",
    "gn:population":241,
    "gn:timezone":"America/Mexico_City",
    "iso:country":"MX",
    "name:und_x_variant":[
        "Ca\u00f1ada del Tecolote"
    ],
    "wof:name":"Canada del Tecolote",
    "wof:placetype":"locality",
    "wof:population":241
},
  "geometry": {"coordinates":[-97.98972000000001,17.85639],"type":"Point"}
}