{
  "type": "Feature",
  "properties": {
    "gn:admin1_code":"5",
    "gn:admin2_code":"92.0",
    "gn:asciiname":"Aguilar",
    "gn:country_code":"MX",
    "gn:dem":178,
    "gn:feature_class":"P",
    "gn:feature_code":"PPL",
    "gn:name":"Aguilar",
    "gn:population":0,
    "gn:timezone":"America/Mexico_City",
    "iso:country":"MX",
    "wof:name":"Aguilar",
    "wof:placetype":"locality"
},
  "geometry": {"coordinates":[-93.53333000000001,17.13332999999999],"type":"Point"}
}