{
  "type": "Feature",
  "properties": {
    "gn:admin1_code":"10",
    "gn:admin2_code":"12.0",
    "gn:asciiname":"Bonanza",
    "gn:country_code":"MX",
    "gn:dem":1187,
    "gn:feature_class":"P",
    "gn:feature_code":"PPL",
    "gn:name":"Bonanza",
    "gn:population":6,
    "gn:timezone":"America/Monterrey",
    "iso:country":"MX",
    "wof:name":"Bonanza",
    "wof:placetype":"locality",
    "wof:population":6
},
  "geometry": {"coordinates":[-103.46832999999999,25.38416],"type":"Point"}
}