{
  "type": "Feature",
  "properties": {
    "gn:admin1_code":"24",
    "gn:admin2_code":"21.0",
    "gn:asciiname":"San Pedro Ojo Zarco",
    "gn:cc2":"MX",
    "gn:country_code":"MX",
    "gn:dem":1875,
    "gn:feature_class":"P",
    "gn:feature_code":"PPL",
    "gn:name":"San Pedro Ojo Zarco",
    "gn:population":701,
    "gn:timezone":"America/Mexico_City",
    "iso:country":"MX",
    "name:und_x_variant":[
        "San Pedro",
        "San Pedro Ojo Zarco"
    ],
    "wof:name":"San Pedro Ojo Zarco",
    "wof:placetype":"locality",
    "wof:population":701
},
  "geometry": {"coordinates":[-101.02333,22.32806],"type":"Point"}
}