{
  "type": "Feature",
  "properties": {
    "gn:admin1_code":"22",
    "gn:admin2_code":"11",
    "gn:asciiname":"Familia Moreno Mercado",
    "gn:country_code":"MX",
    "gn:dem":1914,
    "gn:feature_class":"P",
    "gn:feature_code":"PPL",
    "gn:name":"Familia Moreno Mercado",
    "gn:population":14,
    "gn:timezone":"America/Mexico_City",
    "iso:country":"MX",
    "wof:name":"Familia Moreno Mercado",
    "wof:placetype":"locality",
    "wof:population":14
},
  "geometry": {"coordinates":[-100.19083000000001,20.52889],"type":"Point"}
}