{
  "type": "Feature",
  "properties": {
    "gn:admin1_code":"6",
    "gn:admin2_code":"36.0",
    "gn:asciiname":"Blanco",
    "gn:country_code":"MX",
    "gn:dem":1543,
    "gn:feature_class":"P",
    "gn:feature_code":"PPL",
    "gn:name":"Blanco",
    "gn:population":0,
    "gn:timezone":"America/Chihuahua",
    "iso:country":"MX",
    "name:cat_x_preferred":[
        "Blanco"
    ],
    "name:ceb_x_preferred":[
        "Blanco"
    ],
    "name:ces_x_preferred":[
        "Blanco"
    ],
    "name:deu_x_preferred":[
        "Blanco"
    ],
    "name:fin_x_preferred":[
        "Blanco"
    ],
    "name:fra_x_preferred":[
        "Blanco"
    ],
    "name:heb_x_preferred":[
        "\u05d1\u05dc\u05e0\u05e7\u05d5"
    ],
    "name:ita_x_preferred":[
        "Blanco"
    ],
    "name:nld_x_preferred":[
        "Blanco"
    ],
    "name:pol_x_preferred":[
        "Blanco"
    ],
    "name:slv_x_preferred":[
        "Blanco"
    ],
    "name:spa_x_preferred":[
        "Blanco"
    ],
    "name:swe_x_preferred":[
        "Blanco"
    ],
    "name:zho_x_preferred":[
        "\u5e03\u5170\u79d1"
    ],
    "wof:name":"Blanco",
    "wof:placetype":"locality"
},
  "geometry": {"coordinates":[-104.54618000000001,27.29736],"type":"Point"}
}