{
  "type": "Feature",
  "properties": {
    "gn:admin1_code":"19.0",
    "gn:asciiname":"Los Ligeros",
    "gn:country_code":"MX",
    "gn:dem":508,
    "gn:feature_class":"P",
    "gn:feature_code":"PPL",
    "gn:name":"Los Ligeros",
    "gn:population":0,
    "gn:timezone":"America/Monterrey",
    "iso:country":"MX",
    "name:spa_x_preferred":[
        "Los Ligeros"
    ],
    "wof:name":"Los Ligeros",
    "wof:placetype":"locality"
},
  "geometry": {"coordinates":[-100.39381,25.93199],"type":"Point"}
}