{
  "type": "Feature",
  "properties": {
    "gn:admin1_code":"17",
    "gn:admin2_code":"12",
    "gn:asciiname":"Rancho de Armando Ramirez",
    "gn:country_code":"MX",
    "gn:dem":934,
    "gn:feature_class":"P",
    "gn:feature_code":"PPL",
    "gn:name":"Rancho de Armando Ram\u00edrez",
    "gn:population":25,
    "gn:timezone":"America/Mexico_City",
    "iso:country":"MX",
    "name:und_x_variant":[
        "Rancho de Armando Ram\u00edrez"
    ],
    "wof:name":"Rancho de Armando Ramirez",
    "wof:placetype":"locality",
    "wof:population":25
},
  "geometry": {"coordinates":[-99.20389,18.59417],"type":"Point"}
}