{
  "type": "Feature",
  "properties": {
    "gn:admin1_code":"6",
    "gn:admin2_code":"25.0",
    "gn:asciiname":"La Martina",
    "gn:country_code":"MX",
    "gn:dem":2197,
    "gn:feature_class":"P",
    "gn:feature_code":"PPL",
    "gn:name":"La Mart\u00edna",
    "gn:population":0,
    "gn:timezone":"America/Chihuahua",
    "iso:country":"MX",
    "name:spa_x_preferred":[
        "La Mart\u00edna"
    ],
    "name:spa_x_variant":[
        "Buenavista"
    ],
    "name:und_x_variant":[
        "Maset Buena Vista"
    ],
    "wof:name":"La Martina",
    "wof:placetype":"locality"
},
  "geometry": {"coordinates":[-107.6795,29.40024],"type":"Point"}
}