{
  "type": "Feature",
  "properties": {
    "gn:admin1_code":"32",
    "gn:admin2_code":"26.0",
    "gn:asciiname":"Presa Valenciana",
    "gn:country_code":"MX",
    "gn:dem":1866,
    "gn:feature_class":"P",
    "gn:feature_code":"PPL",
    "gn:name":"Presa Valenciana",
    "gn:population":0,
    "gn:timezone":"America/Mexico_City",
    "iso:country":"MX",
    "name:spa_x_preferred":[
        "Presa Valenciana"
    ],
    "name:und_x_variant":[
        "La Presa Valenciana"
    ],
    "wof:name":"Presa Valenciana",
    "wof:placetype":"locality"
},
  "geometry": {"coordinates":[-102.22554,24.59661],"type":"Point"}
}