{
  "type": "Feature",
  "properties": {
    "gn:admin1_code":"27.0",
    "gn:admin2_code":"15.0",
    "gn:asciiname":"Asuncion",
    "gn:country_code":"MX",
    "gn:dem":16,
    "gn:feature_class":"P",
    "gn:feature_code":"PPL",
    "gn:name":"Asunci\u00f3n",
    "gn:population":0,
    "gn:timezone":"America/Mexico_City",
    "iso:country":"MX",
    "name:spa_x_preferred":[
        "Asunci\u00f3n"
    ],
    "name:spa_x_variant":[
        "Monta\u00f1a",
        "Segunda Secci\u00f3n"
    ],
    "wof:name":"Asuncion",
    "wof:placetype":"locality"
},
  "geometry": {"coordinates":[-92.85433,17.61449],"type":"Point"}
}