{
  "type": "Feature",
  "properties": {
    "gn:admin1_code":"30",
    "gn:admin2_code":"108.0",
    "gn:asciiname":"Plan de Limones",
    "gn:country_code":"MX",
    "gn:dem":24,
    "gn:feature_class":"P",
    "gn:feature_code":"PPL",
    "gn:name":"Plan de Limones",
    "gn:population":0,
    "gn:timezone":"America/Mexico_City",
    "iso:country":"MX",
    "name:spa_x_preferred":[
        "Plan de Limones"
    ],
    "wof:name":"Plan de Limones",
    "wof:placetype":"locality"
},
  "geometry": {"coordinates":[-94.43597,17.61808],"type":"Point"}
}