{
  "type": "Feature",
  "properties": {
    "gn:admin1_code":"26.0",
    "gn:asciiname":"La Pandura",
    "gn:country_code":"MX",
    "gn:dem":938,
    "gn:feature_class":"P",
    "gn:feature_code":"PPL",
    "gn:name":"La Pandura",
    "gn:population":0,
    "gn:timezone":"America/Hermosillo",
    "iso:country":"MX",
    "name:spa_x_preferred":[
        "La Pandura"
    ],
    "wof:name":"La Pandura",
    "wof:placetype":"locality"
},
  "geometry": {"coordinates":[-109.12953,27.84944],"type":"Point"}
}