{
  "type": "Feature",
  "properties": {
    "gn:admin1_code":"20",
    "gn:admin2_code":"43",
    "gn:asciiname":"Rancho de Luis Antonio Jimenez",
    "gn:country_code":"MX",
    "gn:dem":10,
    "gn:feature_class":"P",
    "gn:feature_code":"PPL",
    "gn:name":"Rancho de Luis Antonio Jim\u00e9nez",
    "gn:population":12,
    "gn:timezone":"America/Mexico_City",
    "iso:country":"MX",
    "name:und_x_variant":[
        "Rancho de Luis Antonio Jim\u00e9nez"
    ],
    "wof:name":"Rancho de Luis Antonio Jimenez",
    "wof:placetype":"locality",
    "wof:population":12
},
  "geometry": {"coordinates":[-95.11167,16.28582999999999],"type":"Point"}
}