{
  "type": "Feature",
  "properties": {
    "gn:admin1_code":"30",
    "gn:admin2_code":"72.0",
    "gn:asciiname":"Los Cajones",
    "gn:cc2":"MX",
    "gn:country_code":"MX",
    "gn:dem":1779,
    "gn:feature_class":"P",
    "gn:feature_code":"PPL",
    "gn:name":"Los Cajones",
    "gn:population":0,
    "gn:timezone":"America/Mexico_City",
    "iso:country":"MX",
    "name:und_x_variant":[
        "Cajones",
        "Los Cajones"
    ],
    "wof:name":"Los Cajones",
    "wof:placetype":"locality"
},
  "geometry": {"coordinates":[-98.40000000000001,20.68333],"type":"Point"}
}