{
  "type": "Feature",
  "properties": {
    "gn:admin1_code":"20",
    "gn:admin2_code":"397.0",
    "gn:asciiname":"Joya Grande",
    "gn:country_code":"MX",
    "gn:dem":2584,
    "gn:feature_class":"P",
    "gn:feature_code":"PPL",
    "gn:name":"Joya Grande",
    "gn:population":261,
    "gn:timezone":"America/Mexico_City",
    "iso:country":"MX",
    "wof:name":"Joya Grande",
    "wof:placetype":"locality",
    "wof:population":261
},
  "geometry": {"coordinates":[-97.68667000000001,17.16583],"type":"Point"}
}