{
  "type": "Feature",
  "properties": {
    "gn:admin1_code":"30",
    "gn:admin2_code":"173",
    "gn:asciiname":"Paso Tigre (La Union)",
    "gn:country_code":"MX",
    "gn:dem":174,
    "gn:feature_class":"P",
    "gn:feature_code":"PPL",
    "gn:name":"Paso Tigre (La Uni\u00f3n)",
    "gn:population":28,
    "gn:timezone":"America/Mexico_City",
    "iso:country":"MX",
    "name:und_x_variant":[
        "Paso Tigre (La Uni\u00f3n)"
    ],
    "wof:name":"Paso Tigre (La Union)",
    "wof:placetype":"locality",
    "wof:population":28
},
  "geometry": {"coordinates":[-96.72167,18.56472],"type":"Point"}
}