{
  "type": "Feature",
  "properties": {
    "gn:admin1_code":"19",
    "gn:admin2_code":"9.0",
    "gn:asciiname":"Charco Hondo",
    "gn:country_code":"MX",
    "gn:dem":305,
    "gn:feature_class":"P",
    "gn:feature_code":"PPL",
    "gn:name":"Charco Hondo",
    "gn:population":0,
    "gn:timezone":"America/Monterrey",
    "iso:country":"MX",
    "name:und_x_variant":[
        "Rancho Charco Hondo",
        "Charco Hondo"
    ],
    "wof:name":"Charco Hondo",
    "wof:placetype":"locality"
},
  "geometry": {"coordinates":[-99.95390999999999,25.61874],"type":"Point"}
}