{
  "type": "Feature",
  "properties": {
    "gn:admin1_code":"6",
    "gn:admin2_code":"41.0",
    "gn:asciiname":"Gurisichi",
    "gn:country_code":"MX",
    "gn:dem":1849,
    "gn:feature_class":"P",
    "gn:feature_code":"PPL",
    "gn:name":"Gurisichi",
    "gn:population":0,
    "gn:timezone":"America/Chihuahua",
    "iso:country":"MX",
    "name:spa_x_preferred":[
        "Gurisichi"
    ],
    "wof:name":"Gurisichi",
    "wof:placetype":"locality"
},
  "geometry": {"coordinates":[-108.04585,27.73611],"type":"Point"}
}