{
  "type": "Feature",
  "properties": {
    "gn:admin1_code":"26",
    "gn:admin2_code":"66.0",
    "gn:asciiname":"El Pozo de los Severo",
    "gn:country_code":"MX",
    "gn:dem":421,
    "gn:feature_class":"P",
    "gn:feature_code":"PPL",
    "gn:name":"El Pozo de los Severo",
    "gn:population":0,
    "gn:timezone":"America/Hermosillo",
    "iso:country":"MX",
    "name:spa_x_preferred":[
        "El Pozo de los Severo"
    ],
    "wof:name":"El Pozo de los Severo",
    "wof:placetype":"locality"
},
  "geometry": {"coordinates":[-110.48999999999999,29.43833],"type":"Point"}
}