{
  "type": "Feature",
  "properties": {
    "gn:admin1_code":"12",
    "gn:admin2_code":"21.0",
    "gn:asciiname":"Rancho las Graditas de la Ceiba",
    "gn:country_code":"MX",
    "gn:dem":94,
    "gn:feature_class":"P",
    "gn:feature_code":"PPL",
    "gn:name":"Rancho las Graditas de la Ceiba",
    "gn:population":7,
    "gn:timezone":"America/Mexico_City",
    "iso:country":"MX",
    "wof:name":"Rancho las Graditas de la Ceiba",
    "wof:placetype":"locality",
    "wof:population":7
},
  "geometry": {"coordinates":[-100.09936999999999,17.10774],"type":"Point"}
}