{
  "type": "Feature",
  "properties": {
    "gn:admin1_code":"13",
    "gn:admin2_code":"37.0",
    "gn:asciiname":"Tres Cruces",
    "gn:country_code":"MX",
    "gn:dem":1322,
    "gn:feature_class":"P",
    "gn:feature_code":"PPL",
    "gn:name":"Tres Cruces",
    "gn:population":0,
    "gn:timezone":"America/Mexico_City",
    "iso:country":"MX",
    "name:cat_x_preferred":[
        "Tres Cruces"
    ],
    "name:deu_x_preferred":[
        "Tres Cruces"
    ],
    "name:spa_x_preferred":[
        "Tres Cruces"
    ],
    "wof:name":"Tres Cruces",
    "wof:placetype":"locality"
},
  "geometry": {"coordinates":[-98.71124,20.51502],"type":"Point"}
}