{
  "type": "Feature",
  "properties": {
    "gn:admin1_code":"5",
    "gn:admin2_code":"19.0",
    "gn:asciiname":"Blanquita",
    "gn:country_code":"MX",
    "gn:dem":709,
    "gn:feature_class":"P",
    "gn:feature_code":"PPL",
    "gn:name":"Blanquita",
    "gn:population":6,
    "gn:timezone":"America/Mexico_City",
    "iso:country":"MX",
    "wof:name":"Blanquita",
    "wof:placetype":"locality",
    "wof:population":6
},
  "geometry": {"coordinates":[-92.1575,16.06889],"type":"Point"}
}