{
  "type": "Feature",
  "properties": {
    "gn:admin1_code":"18",
    "gn:admin2_code":"9.0",
    "gn:asciiname":"Roblera",
    "gn:country_code":"MX",
    "gn:dem":841,
    "gn:feature_class":"P",
    "gn:feature_code":"PPL",
    "gn:name":"Roblera",
    "gn:population":0,
    "gn:timezone":"America/Mazatlan",
    "iso:country":"MX",
    "name:spa_x_preferred":[
        "Roblera"
    ],
    "wof:name":"Roblera",
    "wof:placetype":"locality"
},
  "geometry": {"coordinates":[-104.42169,22.25914],"type":"Point"}
}