{
  "type": "Feature",
  "properties": {
    "gn:admin1_code":"25.0",
    "gn:admin2_code":"10.0",
    "gn:asciiname":"Crucerito de Sibajahui",
    "gn:country_code":"MX",
    "gn:dem":31,
    "gn:feature_class":"P",
    "gn:feature_code":"PPL",
    "gn:name":"Crucerito de Sibajahui",
    "gn:population":0,
    "gn:timezone":"America/Mazatlan",
    "iso:country":"MX",
    "name:spa_x_preferred":[
        "Crucerito de Sibajahui"
    ],
    "wof:name":"Crucerito de Sibajahui",
    "wof:placetype":"locality"
},
  "geometry": {"coordinates":[-108.73797999999999,26.1361],"type":"Point"}
}