{
  "type": "Feature",
  "properties": {
    "gn:admin1_code":"5",
    "gn:admin2_code":"19",
    "gn:asciiname":"Las Arenas",
    "gn:country_code":"MX",
    "gn:dem":1182,
    "gn:feature_class":"P",
    "gn:feature_code":"PPL",
    "gn:name":"Las Arenas",
    "gn:population":12,
    "gn:timezone":"America/Mexico_City",
    "iso:country":"MX",
    "name:cat_x_preferred":[
        "Areeta"
    ],
    "name:eus_x_preferred":[
        "Areeta"
    ],
    "name:fra_x_preferred":[
        "Areeta"
    ],
    "name:glg_x_preferred":[
        "Areeta"
    ],
    "name:ita_x_preferred":[
        "Las Arenas"
    ],
    "name:spa_x_preferred":[
        "Las Arenas"
    ],
    "wof:name":"Las Arenas",
    "wof:placetype":"locality",
    "wof:population":12
},
  "geometry": {"coordinates":[-92.16583,16.11472],"type":"Point"}
}