{
  "type": "Feature",
  "properties": {
    "gn:admin1_code":"18",
    "gn:admin2_code":"19",
    "gn:asciiname":"El Toro Prieto",
    "gn:country_code":"MX",
    "gn:dem":1234,
    "gn:feature_class":"P",
    "gn:feature_code":"PPL",
    "gn:name":"El Toro Prieto",
    "gn:population":10,
    "gn:timezone":"America/Mazatlan",
    "iso:country":"MX",
    "wof:name":"El Toro Prieto",
    "wof:placetype":"locality",
    "wof:population":10
},
  "geometry": {"coordinates":[-104.22444,21.26167],"type":"Point"}
}