{
  "type": "Feature",
  "properties": {
    "gn:admin1_code":"8.0",
    "gn:admin2_code":"7.0",
    "gn:asciiname":"La Huiscolotila",
    "gn:country_code":"MX",
    "gn:dem":331,
    "gn:feature_class":"P",
    "gn:feature_code":"PPL",
    "gn:name":"La Huiscolotila",
    "gn:population":0,
    "gn:timezone":"America/Mexico_City",
    "iso:country":"MX",
    "name:spa_x_preferred":[
        "La Huiscolotila"
    ],
    "name:und_x_variant":[
        "La Huiscocotila"
    ],
    "wof:name":"La Huiscolotila",
    "wof:placetype":"locality"
},
  "geometry": {"coordinates":[-104.37603,19.22385],"type":"Point"}
}