{
  "type": "Feature",
  "properties": {
    "gn:admin1_code":"6",
    "gn:admin2_code":"66.0",
    "gn:asciiname":"San Jose el Pinal",
    "gn:country_code":"MX",
    "gn:dem":1733,
    "gn:feature_class":"P",
    "gn:feature_code":"PPL",
    "gn:name":"San Jos\u00e9 el Pinal",
    "gn:population":0,
    "gn:timezone":"America/Chihuahua",
    "iso:country":"MX",
    "name:spa_x_preferred":[
        "San Jos\u00e9 el Pinal"
    ],
    "name:und_x_variant":[
        "San Jos\u00e9 del Pinal"
    ],
    "wof:name":"San Jose el Pinal",
    "wof:placetype":"locality"
},
  "geometry": {"coordinates":[-108.5104,27.82871],"type":"Point"}
}