{
  "type": "Feature",
  "properties": {
    "gn:admin1_code":"14",
    "gn:admin2_code":"49",
    "gn:asciiname":"La Pareja",
    "gn:country_code":"MX",
    "gn:dem":716,
    "gn:feature_class":"P",
    "gn:feature_code":"PPL",
    "gn:name":"La Pareja",
    "gn:population":12,
    "gn:timezone":"America/Mexico_City",
    "iso:country":"MX",
    "wof:name":"La Pareja",
    "wof:placetype":"locality",
    "wof:population":12
},
  "geometry": {"coordinates":[-102.95193999999999,19.29639],"type":"Point"}
}