{
  "type": "Feature",
  "properties": {
    "gn:admin1_code":"26.0",
    "gn:admin2_code":"65.0",
    "gn:asciiname":"La Aurora (Las Pilas)",
    "gn:cc2":"MX",
    "gn:country_code":"MX",
    "gn:dem":660,
    "gn:feature_class":"P",
    "gn:feature_code":"PPL",
    "gn:name":"La Aurora (Las Pilas)",
    "gn:population":2,
    "gn:timezone":"America/Hermosillo",
    "iso:country":"MX",
    "name:und_x_variant":[
        "Aurora",
        "La Aurora"
    ],
    "wof:name":"La Aurora (Las Pilas)",
    "wof:placetype":"locality",
    "wof:population":2
},
  "geometry": {"coordinates":[-111.42333000000001,30.92056],"type":"Point"}
}