{
  "type": "Feature",
  "properties": {
    "gn:admin1_code":"25.0",
    "gn:asciiname":"Las Tres Luces",
    "gn:country_code":"MX",
    "gn:dem":20,
    "gn:feature_class":"P",
    "gn:feature_code":"PPL",
    "gn:name":"Las Tres Luces",
    "gn:population":0,
    "gn:timezone":"America/Mazatlan",
    "iso:country":"MX",
    "name:spa_x_preferred":[
        "Las Tres Luces"
    ],
    "wof:name":"Las Tres Luces",
    "wof:placetype":"locality"
},
  "geometry": {"coordinates":[-108.88135,25.86208],"type":"Point"}
}