{
  "type": "Feature",
  "properties": {
    "gn:admin1_code":"30.0",
    "gn:admin2_code":"181.0",
    "gn:asciiname":"El Muchital",
    "gn:country_code":"MX",
    "gn:dem":10,
    "gn:feature_class":"P",
    "gn:feature_code":"PPL",
    "gn:name":"El Muchital",
    "gn:population":0,
    "gn:timezone":"America/Mexico_City",
    "iso:country":"MX",
    "name:spa_x_preferred":[
        "El Muchital"
    ],
    "wof:name":"El Muchital",
    "wof:placetype":"locality"
},
  "geometry": {"coordinates":[-96.07277000000001,18.67319],"type":"Point"}
}