{
  "type": "Feature",
  "properties": {
    "gn:admin1_code":"13",
    "gn:admin2_code":"84",
    "gn:asciiname":"Cajay",
    "gn:country_code":"MX",
    "gn:dem":1987,
    "gn:feature_class":"P",
    "gn:feature_code":"PPL",
    "gn:name":"Cajay",
    "gn:population":14,
    "gn:timezone":"America/Mexico_City",
    "iso:country":"MX",
    "wof:name":"Cajay",
    "wof:placetype":"locality",
    "wof:population":14
},
  "geometry": {"coordinates":[-99.33583,20.79222],"type":"Point"}
}