{
  "type": "Feature",
  "properties": {
    "gn:admin1_code":"30.0",
    "gn:asciiname":"Camino a Tlacotengo",
    "gn:country_code":"MX",
    "gn:dem":1044,
    "gn:feature_class":"P",
    "gn:feature_code":"PPL",
    "gn:name":"Camino a Tlacotengo",
    "gn:population":0,
    "gn:timezone":"America/Mexico_City",
    "iso:country":"MX",
    "name:spa_x_preferred":[
        "Camino a Tlacotengo"
    ],
    "wof:name":"Camino a Tlacotengo",
    "wof:placetype":"locality"
},
  "geometry": {"coordinates":[-96.98779999999999,18.91782000000001],"type":"Point"}
}