{
  "type": "Feature",
  "properties": {
    "gn:admin1_code":"15.0",
    "gn:asciiname":"Cerrito del Capire",
    "gn:country_code":"MX",
    "gn:dem":16,
    "gn:feature_class":"P",
    "gn:feature_code":"PPL",
    "gn:name":"Cerrito del Capire",
    "gn:population":0,
    "gn:timezone":"America/Mexico_City",
    "iso:country":"MX",
    "name:spa_x_preferred":[
        "Cerrito del Capire"
    ],
    "name:spa_x_variant":[
        "El Habillal"
    ],
    "name:und_x_variant":[
        "Cerrito del Capiri"
    ],
    "wof:name":"Cerrito del Capire",
    "wof:placetype":"locality"
},
  "geometry": {"coordinates":[-102.35808,18.00115],"type":"Point"}
}