{
  "type": "Feature",
  "properties": {
    "gn:admin1_code":"16",
    "gn:asciiname":"La Palma",
    "gn:country_code":"MX",
    "gn:dem":413,
    "gn:feature_class":"P",
    "gn:feature_code":"PPL",
    "gn:name":"La Palma",
    "gn:population":0,
    "gn:timezone":"America/Mexico_City",
    "iso:country":"MX",
    "name:spa_x_preferred":[
        "La Palma"
    ],
    "wof:name":"La Palma",
    "wof:placetype":"locality"
},
  "geometry": {"coordinates":[-100.76425999999999,18.85262],"type":"Point"}
}