{
  "type": "Feature",
  "properties": {
    "gn:admin1_code":"10",
    "gn:admin2_code":"23.0",
    "gn:asciiname":"El Tuche",
    "gn:country_code":"MX",
    "gn:dem":1165,
    "gn:feature_class":"P",
    "gn:feature_code":"PPL",
    "gn:name":"El Tuche",
    "gn:population":5,
    "gn:timezone":"America/Monterrey",
    "iso:country":"MX",
    "wof:name":"El Tuche",
    "wof:placetype":"locality",
    "wof:population":5
},
  "geometry": {"coordinates":[-105.09056,23.05438],"type":"Point"}
}