{
  "type": "Feature",
  "properties": {
    "gn:admin1_code":"21",
    "gn:admin2_code":"142",
    "gn:asciiname":"Jilotepec",
    "gn:country_code":"MX",
    "gn:dem":2360,
    "gn:feature_class":"P",
    "gn:feature_code":"PPL",
    "gn:name":"Jilotepec",
    "gn:population":22,
    "gn:timezone":"America/Mexico_City",
    "iso:country":"MX",
    "wof:name":"Jilotepec",
    "wof:placetype":"locality",
    "wof:population":22
},
  "geometry": {"coordinates":[-97.65551000000001,19.12875],"type":"Point"}
}