{
  "type": "Feature",
  "properties": {
    "gn:admin1_code":"32",
    "gn:admin2_code":"55.0",
    "gn:asciiname":"Las Trojes",
    "gn:country_code":"MX",
    "gn:dem":1647,
    "gn:feature_class":"P",
    "gn:feature_code":"PPL",
    "gn:name":"Las Trojes",
    "gn:population":2,
    "gn:timezone":"America/Mexico_City",
    "iso:country":"MX",
    "wof:name":"Las Trojes",
    "wof:placetype":"locality",
    "wof:population":2
},
  "geometry": {"coordinates":[-102.85889,22.03833],"type":"Point"}
}