{
  "type": "Feature",
  "properties": {
    "gn:admin1_code":"19",
    "gn:admin2_code":"9",
    "gn:asciiname":"Salitrillo",
    "gn:country_code":"MX",
    "gn:dem":306,
    "gn:feature_class":"P",
    "gn:feature_code":"PPL",
    "gn:name":"Salitrillo",
    "gn:population":43,
    "gn:timezone":"America/Monterrey",
    "iso:country":"MX",
    "wof:name":"Salitrillo",
    "wof:placetype":"locality",
    "wof:population":43
},
  "geometry": {"coordinates":[-99.94833,25.52889],"type":"Point"}
}