{
  "type": "Feature",
  "properties": {
    "gn:admin1_code":"6.0",
    "gn:admin2_code":"28.0",
    "gn:asciiname":"Doctor Porfiria Parra",
    "gn:country_code":"MX",
    "gn:dem":1092,
    "gn:feature_class":"P",
    "gn:feature_code":"PPL",
    "gn:name":"Doctor Porfiria Parra",
    "gn:population":0,
    "gn:timezone":"America/Chihuahua",
    "iso:country":"MX",
    "wof:name":"Doctor Porfiria Parra",
    "wof:placetype":"locality"
},
  "geometry": {"coordinates":[-106.14015000000001,31.4263],"type":"Point"}
}