{
  "type": "Feature",
  "properties": {
    "gn:admin1_code":"5",
    "gn:admin2_code":"103.0",
    "gn:asciiname":"El Mango Buenavista",
    "gn:country_code":"MX",
    "gn:dem":545,
    "gn:feature_class":"P",
    "gn:feature_code":"PPL",
    "gn:name":"El Mango Buenavista",
    "gn:population":146,
    "gn:timezone":"America/Mexico_City",
    "iso:country":"MX",
    "wof:name":"El Mango Buenavista",
    "wof:placetype":"locality",
    "wof:population":146
},
  "geometry": {"coordinates":[-92.37778,15.16194],"type":"Point"}
}