{
  "type": "Feature",
  "properties": {
    "gn:admin1_code":"3",
    "gn:admin2_code":"9.0",
    "gn:asciiname":"San Francisco de Asis",
    "gn:country_code":"MX",
    "gn:dem":281,
    "gn:feature_class":"P",
    "gn:feature_code":"PPL",
    "gn:name":"San Francisco de Asis",
    "gn:population":0,
    "gn:timezone":"America/Mazatlan",
    "iso:country":"MX",
    "name:spa_x_preferred":[
        "San Francisco de Asis"
    ],
    "name:und_x_variant":[
        "San Francisco"
    ],
    "wof:name":"San Francisco de Asis",
    "wof:placetype":"locality"
},
  "geometry": {"coordinates":[-111.56372,26.1474],"type":"Point"}
}