{
  "type": "Feature",
  "properties": {
    "gn:admin1_code":"21",
    "gn:admin2_code":"53.0",
    "gn:asciiname":"Rincon Verde",
    "gn:country_code":"MX",
    "gn:dem":2426,
    "gn:feature_class":"P",
    "gn:feature_code":"PPL",
    "gn:name":"Rinc\u00f3n Verde",
    "gn:population":0,
    "gn:timezone":"America/Mexico_City",
    "iso:country":"MX",
    "name:spa_x_preferred":[
        "Rinc\u00f3n Verde"
    ],
    "wof:name":"Rincon Verde",
    "wof:placetype":"locality"
},
  "geometry": {"coordinates":[-98.15900000000001,19.77009],"type":"Point"}
}