{
  "type": "Feature",
  "properties": {
    "gn:admin1_code":"18.0",
    "gn:admin2_code":"16.0",
    "gn:asciiname":"Aguas",
    "gn:country_code":"MX",
    "gn:dem":30,
    "gn:feature_class":"P",
    "gn:feature_code":"PPL",
    "gn:name":"Aguas",
    "gn:population":0,
    "gn:timezone":"America/Mazatlan",
    "iso:country":"MX",
    "wof:name":"Aguas",
    "wof:placetype":"locality"
},
  "geometry": {"coordinates":[-105.36667,22.31667],"type":"Point"}
}