{
  "type": "Feature",
  "properties": {
    "gn:admin1_code":"26",
    "gn:admin2_code":"25.0",
    "gn:asciiname":"Empalme el Aguila (El Ranchito)",
    "gn:country_code":"MX",
    "gn:dem":10,
    "gn:feature_class":"P",
    "gn:feature_code":"PPL",
    "gn:name":"Empalme el \u00c1guila (El Ranchito)",
    "gn:population":103,
    "gn:timezone":"America/Hermosillo",
    "iso:country":"MX",
    "name:und_x_variant":[
        "Empalme el \u00c1guila (El Ranchito)"
    ],
    "wof:name":"Empalme el Aguila (El Ranchito)",
    "wof:placetype":"locality",
    "wof:population":103
},
  "geometry": {"coordinates":[-110.75194,27.96306],"type":"Point"}
}