{
  "type": "Feature",
  "properties": {
    "gn:admin1_code":"28.0",
    "gn:admin2_code":"24.0",
    "gn:asciiname":"Los Ramos",
    "gn:country_code":"MX",
    "gn:dem":64,
    "gn:feature_class":"P",
    "gn:feature_code":"PPL",
    "gn:name":"Los Ramos",
    "gn:population":0,
    "gn:timezone":"America/Monterrey",
    "iso:country":"MX",
    "name:spa_x_preferred":[
        "Los Ramos"
    ],
    "wof:name":"Los Ramos",
    "wof:placetype":"locality"
},
  "geometry": {"coordinates":[-99.11228,26.45402],"type":"Point"}
}