{
  "type": "Feature",
  "properties": {
    "gn:admin1_code":"5",
    "gn:admin2_code":"100.0",
    "gn:asciiname":"Tehuacan",
    "gn:country_code":"MX",
    "gn:dem":1221,
    "gn:feature_class":"P",
    "gn:feature_code":"PPL",
    "gn:name":"Tehuacan",
    "gn:population":321,
    "gn:timezone":"America/Mexico_City",
    "iso:country":"MX",
    "wof:name":"Tehuacan",
    "wof:placetype":"locality",
    "wof:population":321
},
  "geometry": {"coordinates":[-92.30779,17.27625],"type":"Point"}
}