{
  "type": "Feature",
  "properties": {
    "gn:admin1_code":"5",
    "gn:admin2_code":"100.0",
    "gn:asciiname":"Tehuacan",
    "gn:country_code":"MX",
    "gn:dem":1221,
    "gn:feature_class":"P",
    "gn:feature_code":"PPL",
    "gn:name":"Tehuacan",
    "gn:population":321,
    "gn:timezone":"America/Mexico_City",
    "iso:country":"MX",
    "name:ara_x_preferred":[
        "\u062a\u0647\u0648\u0627\u0643\u0627\u0646"
    ],
    "name:ben_x_preferred":[
        "\u09a4\u09c7\u09b9\u09c1\u09df\u09be\u0995\u09be\u09a8"
    ],
    "name:ell_x_preferred":[
        "\u03a4\u03b5\u03bf\u03c5\u03b1\u03ba\u03ac\u03bd"
    ],
    "name:hin_x_preferred":[
        "\u0924\u0939\u0941\u0906\u0915\u0948\u0928"
    ],
    "name:kor_x_preferred":[
        "\ud14c\uc640\uce78"
    ],
    "name:tur_x_preferred":[
        "Tehuacan"
    ],
    "name:ukr_x_preferred":[
        "\u0422\u0435\u0443\u0430\u043a\u0430\u043d"
    ],
    "wof:name":"Tehuacan",
    "wof:placetype":"locality",
    "wof:population":321
},
  "geometry": {"coordinates":[-92.30779,17.27625],"type":"Point"}
}