{
  "type": "Feature",
  "properties": {
    "gn:admin1_code":"15.0",
    "gn:admin2_code":"123.0",
    "gn:asciiname":"El Mamey de Acatitlan",
    "gn:country_code":"MX",
    "gn:dem":1121,
    "gn:feature_class":"P",
    "gn:feature_code":"PPL",
    "gn:name":"El Mamey de Acatitl\u00e1n",
    "gn:population":0,
    "gn:timezone":"America/Mexico_City",
    "iso:country":"MX",
    "name:spa_x_preferred":[
        "El Mamey de Acatitl\u00e1n"
    ],
    "name:und_x_variant":[
        "El Mamey"
    ],
    "wof:name":"El Mamey de Acatitlan",
    "wof:placetype":"locality"
},
  "geometry": {"coordinates":[-100.35597,19.03823],"type":"Point"}
}