{
  "type": "Feature",
  "properties": {
    "gn:admin1_code":"19.0",
    "gn:admin2_code":"49.0",
    "gn:asciiname":"Los Terreros",
    "gn:country_code":"MX",
    "gn:dem":491,
    "gn:feature_class":"P",
    "gn:feature_code":"PPL",
    "gn:name":"Los Terreros",
    "gn:population":107,
    "gn:timezone":"America/Monterrey",
    "iso:country":"MX",
    "wof:name":"Los Terreros",
    "wof:placetype":"locality",
    "wof:population":107
},
  "geometry": {"coordinates":[-100.13891,25.39756],"type":"Point"}
}