{
  "type": "Feature",
  "properties": {
    "gn:admin1_code":"16",
    "gn:admin2_code":"92.0",
    "gn:asciiname":"La Baldovina",
    "gn:country_code":"MX",
    "gn:dem":427,
    "gn:feature_class":"P",
    "gn:feature_code":"PPL",
    "gn:name":"La Baldovina",
    "gn:population":0,
    "gn:timezone":"America/Mexico_City",
    "iso:country":"MX",
    "name:spa_x_preferred":[
        "La Baldovina"
    ],
    "wof:name":"La Baldovina",
    "wof:placetype":"locality"
},
  "geometry": {"coordinates":[-100.76351,18.91517],"type":"Point"}
}