{
  "type": "Feature",
  "properties": {
    "gn:admin1_code":"5",
    "gn:admin2_code":"9.0",
    "gn:asciiname":"El Arenal",
    "gn:country_code":"MX",
    "gn:dem":4,
    "gn:feature_class":"P",
    "gn:feature_code":"PPL",
    "gn:name":"El Arenal",
    "gn:population":215,
    "gn:timezone":"America/Mexico_City",
    "iso:country":"MX",
    "wof:name":"El Arenal",
    "wof:placetype":"locality",
    "wof:population":215
},
  "geometry": {"coordinates":[-94.00111,16.11139],"type":"Point"}
}