{
  "type": "Feature",
  "properties": {
    "gn:admin1_code":"30",
    "gn:admin2_code":"63.0",
    "gn:asciiname":"Paso Manantial",
    "gn:country_code":"MX",
    "gn:dem":191,
    "gn:feature_class":"P",
    "gn:feature_code":"PPL",
    "gn:name":"Paso Manantial",
    "gn:population":8,
    "gn:timezone":"America/Mexico_City",
    "iso:country":"MX",
    "wof:name":"Paso Manantial",
    "wof:placetype":"locality",
    "wof:population":8
},
  "geometry": {"coordinates":[-97.96167,21.26111],"type":"Point"}
}