{
  "type": "Feature",
  "properties": {
    "gn:admin1_code":"4.0",
    "gn:admin2_code":"9.0",
    "gn:asciiname":"La Polaina",
    "gn:country_code":"MX",
    "gn:dem":50,
    "gn:feature_class":"P",
    "gn:feature_code":"PPL",
    "gn:name":"La Polaina",
    "gn:population":0,
    "gn:timezone":"America/Merida",
    "iso:country":"MX",
    "name:spa_x_preferred":[
        "La Polaina"
    ],
    "wof:name":"La Polaina",
    "wof:placetype":"locality"
},
  "geometry": {"coordinates":[-90.87358999999999,18.62136],"type":"Point"}
}