{
  "type": "Feature",
  "properties": {
    "gn:admin1_code":"20",
    "gn:admin2_code":"260.0",
    "gn:asciiname":"San Isidro Aloapam",
    "gn:country_code":"MX",
    "gn:dem":2236,
    "gn:feature_class":"P",
    "gn:feature_code":"PPL",
    "gn:name":"San Isidro Alo\u00e1pam",
    "gn:population":761,
    "gn:timezone":"America/Mexico_City",
    "iso:country":"MX",
    "name:und_x_variant":[
        "San Isidro Alo\u00e1pam"
    ],
    "wof:name":"San Isidro Aloapam",
    "wof:placetype":"locality",
    "wof:population":761
},
  "geometry": {"coordinates":[-96.65778,17.43417],"type":"Point"}
}