{
  "type": "Feature",
  "properties": {
    "gn:admin1_code":"15.0",
    "gn:asciiname":"Fincas de Sayavedra",
    "gn:country_code":"MX",
    "gn:dem":2409,
    "gn:feature_class":"P",
    "gn:feature_code":"PPL",
    "gn:name":"Fincas de Sayavedra",
    "gn:population":0,
    "gn:timezone":"America/Mexico_City",
    "iso:country":"MX",
    "name:spa_x_preferred":[
        "Fincas de Sayavedra"
    ],
    "wof:name":"Fincas de Sayavedra",
    "wof:placetype":"locality"
},
  "geometry": {"coordinates":[-99.31102,19.58699],"type":"Point"}
}