{
  "type": "Feature",
  "properties": {
    "gn:admin1_code":"27",
    "gn:admin2_code":"8.0",
    "gn:asciiname":"Arce",
    "gn:country_code":"MX",
    "gn:dem":42,
    "gn:feature_class":"P",
    "gn:feature_code":"PPL",
    "gn:name":"Arce",
    "gn:population":0,
    "gn:timezone":"America/Mexico_City",
    "iso:country":"MX",
    "name:bre_x_preferred":[
        "Arce"
    ],
    "name:ceb_x_preferred":[
        "Arce"
    ],
    "name:deu_x_preferred":[
        "Arce"
    ],
    "name:fra_x_preferred":[
        "Arce"
    ],
    "name:ita_x_preferred":[
        "Arce"
    ],
    "name:lit_x_preferred":[
        "Arce"
    ],
    "name:nld_x_preferred":[
        "Arce"
    ],
    "name:por_x_preferred":[
        "Arce"
    ],
    "name:rus_x_preferred":[
        "\u0410\u0440\u0441\u0435"
    ],
    "name:slv_x_preferred":[
        "Arce"
    ],
    "name:spa_x_preferred":[
        "Arce"
    ],
    "name:swe_x_preferred":[
        "Arce"
    ],
    "wof:name":"Arce",
    "wof:placetype":"locality"
},
  "geometry": {"coordinates":[-93.63226,17.78926000000001],"type":"Point"}
}