{
  "type": "Feature",
  "properties": {
    "gn:admin1_code":"6.0",
    "gn:admin2_code":"38.0",
    "gn:asciiname":"El Cubano",
    "gn:country_code":"MX",
    "gn:dem":1266,
    "gn:feature_class":"P",
    "gn:feature_code":"PPL",
    "gn:name":"El Cubano",
    "gn:population":0,
    "gn:timezone":"America/Chihuahua",
    "iso:country":"MX",
    "name:und_x_variant":[
        "Rancho El Cubano",
        "El Cubano"
    ],
    "wof:name":"El Cubano",
    "wof:placetype":"locality"
},
  "geometry": {"coordinates":[-104.73668000000001,28.68242],"type":"Point"}
}