{
  "type": "Feature",
  "properties": {
    "gn:admin1_code":"6.0",
    "gn:admin2_code":"40.0",
    "gn:asciiname":"El Cocono",
    "gn:country_code":"MX",
    "gn:dem":2436,
    "gn:feature_class":"P",
    "gn:feature_code":"PPL",
    "gn:name":"El C\u00f3cono",
    "gn:population":0,
    "gn:timezone":"America/Chihuahua",
    "iso:country":"MX",
    "name:spa_x_preferred":[
        "El C\u00f3cono"
    ],
    "name:und_x_variant":[
        "Rancho El C\u00f3cono"
    ],
    "wof:name":"El Cocono",
    "wof:placetype":"locality"
},
  "geometry": {"coordinates":[-108.2538,29.83057],"type":"Point"}
}