{
  "type": "Feature",
  "properties": {
    "gn:admin1_code":"26.0",
    "gn:asciiname":"Jaime Torres Bodet",
    "gn:country_code":"MX",
    "gn:dem":755,
    "gn:feature_class":"P",
    "gn:feature_code":"PPL",
    "gn:name":"Jaime Torres Bodet",
    "gn:population":0,
    "gn:timezone":"America/Hermosillo",
    "iso:country":"MX",
    "name:spa_x_preferred":[
        "Jaime Torres Bodet"
    ],
    "wof:name":"Jaime Torres Bodet",
    "wof:placetype":"locality"
},
  "geometry": {"coordinates":[-109.05110000000001,27.90494],"type":"Point"}
}