{
  "type": "Feature",
  "properties": {
    "gn:admin1_code":"15",
    "gn:admin2_code":"80.0",
    "gn:asciiname":"Jalpan (Jalpa)",
    "gn:country_code":"MX",
    "gn:dem":1114,
    "gn:feature_class":"P",
    "gn:feature_code":"PPL",
    "gn:name":"Jalpan (Jalpa)",
    "gn:population":786,
    "gn:timezone":"America/Mexico_City",
    "iso:country":"MX",
    "wof:name":"Jalpan (Jalpa)",
    "wof:placetype":"locality",
    "wof:population":786
},
  "geometry": {"coordinates":[-99.98608,18.65354],"type":"Point"}
}