{
  "type": "Feature",
  "properties": {
    "gn:admin1_code":"6",
    "gn:admin2_code":"30",
    "gn:asciiname":"El Cusal",
    "gn:country_code":"MX",
    "gn:dem":550,
    "gn:feature_class":"P",
    "gn:feature_code":"PPL",
    "gn:name":"El Cusal",
    "gn:population":20,
    "gn:timezone":"America/Chihuahua",
    "iso:country":"MX",
    "wof:name":"El Cusal",
    "wof:placetype":"locality",
    "wof:population":20
},
  "geometry": {"coordinates":[-108.39382000000001,27.50186],"type":"Point"}
}