{
  "type": "Feature",
  "properties": {
    "gn:admin1_code":"26.0",
    "gn:admin2_code":"59.0",
    "gn:asciiname":"La Gavilonda",
    "gn:country_code":"MX",
    "gn:dem":1342,
    "gn:feature_class":"P",
    "gn:feature_code":"PPL",
    "gn:name":"La Gavilonda",
    "gn:population":0,
    "gn:timezone":"America/Hermosillo",
    "iso:country":"MX",
    "name:spa_x_preferred":[
        "La Gavilonda"
    ],
    "wof:name":"La Gavilonda",
    "wof:placetype":"locality"
},
  "geometry": {"coordinates":[-110.59519,31.2163],"type":"Point"}
}