{
  "type": "Feature",
  "properties": {
    "gn:admin1_code":"25",
    "gn:admin2_code":"10",
    "gn:asciiname":"Campo Tres Naciones",
    "gn:country_code":"MX",
    "gn:dem":14,
    "gn:feature_class":"P",
    "gn:feature_code":"PPL",
    "gn:name":"Campo Tres Naciones",
    "gn:population":37,
    "gn:timezone":"America/Mazatlan",
    "iso:country":"MX",
    "wof:name":"Campo Tres Naciones",
    "wof:placetype":"locality",
    "wof:population":37
},
  "geometry": {"coordinates":[-109.00894,26.23924],"type":"Point"}
}