{
  "type": "Feature",
  "properties": {
    "gn:admin1_code":"14",
    "gn:admin2_code":"53",
    "gn:asciiname":"Santo Domingo (Arroyo del Palo)",
    "gn:country_code":"MX",
    "gn:dem":1924,
    "gn:feature_class":"P",
    "gn:feature_code":"PPL",
    "gn:name":"Santo Domingo (Arroyo del Palo)",
    "gn:population":17,
    "gn:timezone":"America/Mexico_City",
    "iso:country":"MX",
    "wof:name":"Santo Domingo (Arroyo del Palo)",
    "wof:placetype":"locality",
    "wof:population":17
},
  "geometry": {"coordinates":[-102.09166999999999,21.29889],"type":"Point"}
}