{
  "type": "Feature",
  "properties": {
    "gn:admin1_code":"16",
    "gn:admin2_code":"97",
    "gn:asciiname":"Los Nunez (Rincon de los Nunez)",
    "gn:country_code":"MX",
    "gn:dem":830,
    "gn:feature_class":"P",
    "gn:feature_code":"PPL",
    "gn:name":"Los N\u00fa\u00f1ez (Rinc\u00f3n de los N\u00fa\u00f1ez)",
    "gn:population":27,
    "gn:timezone":"America/Mexico_City",
    "iso:country":"MX",
    "name:und_x_variant":[
        "Los N\u00fa\u00f1ez (Rinc\u00f3n de los N\u00fa\u00f1ez)"
    ],
    "wof:name":"Los Nunez (Rincon de los Nunez)",
    "wof:placetype":"locality",
    "wof:population":27
},
  "geometry": {"coordinates":[-101.44333,18.98361],"type":"Point"}
}