{
  "type": "Feature",
  "properties": {
    "gn:admin1_code":"13",
    "gn:admin2_code":"12.0",
    "gn:asciiname":"Santana Norte Amajac",
    "gn:country_code":"MX",
    "gn:dem":1931,
    "gn:feature_class":"P",
    "gn:feature_code":"PPL",
    "gn:name":"Santana Norte Amajac",
    "gn:population":0,
    "gn:timezone":"America/Mexico_City",
    "iso:country":"MX",
    "name:spa_x_preferred":[
        "Santana Norte Amajac"
    ],
    "name:spa_x_variant":[
        "Potrero de Enmedio"
    ],
    "wof:name":"Santana Norte Amajac",
    "wof:placetype":"locality"
},
  "geometry": {"coordinates":[-98.68865,20.36243],"type":"Point"}
}