{
  "type": "Feature",
  "properties": {
    "gn:admin1_code":"21",
    "gn:admin2_code":"53.0",
    "gn:asciiname":"El Sifon",
    "gn:country_code":"MX",
    "gn:dem":2390,
    "gn:feature_class":"P",
    "gn:feature_code":"PPL",
    "gn:name":"El Sif\u00f3n",
    "gn:population":160,
    "gn:timezone":"America/Mexico_City",
    "iso:country":"MX",
    "name:und_x_variant":[
        "El Sif\u00f3n"
    ],
    "wof:name":"El Sifon",
    "wof:placetype":"locality",
    "wof:population":160
},
  "geometry": {"coordinates":[-98.10829,19.78815],"type":"Point"}
}