{
  "type": "Feature",
  "properties": {
    "gn:admin1_code":"30",
    "gn:admin2_code":"144.0",
    "gn:asciiname":"Rancho Pimiango",
    "gn:country_code":"MX",
    "gn:dem":80,
    "gn:feature_class":"P",
    "gn:feature_code":"PPL",
    "gn:name":"Rancho Pimiango",
    "gn:population":5,
    "gn:timezone":"America/Mexico_City",
    "iso:country":"MX",
    "wof:name":"Rancho Pimiango",
    "wof:placetype":"locality",
    "wof:population":5
},
  "geometry": {"coordinates":[-94.94694,17.91444],"type":"Point"}
}