{
  "type": "Feature",
  "properties": {
    "gn:admin1_code":"16",
    "gn:admin2_code":"52.0",
    "gn:asciiname":"El Ahijadero",
    "gn:country_code":"MX",
    "gn:dem":404,
    "gn:feature_class":"P",
    "gn:feature_code":"PPL",
    "gn:name":"El Ahijadero",
    "gn:population":7,
    "gn:timezone":"America/Mexico_City",
    "iso:country":"MX",
    "wof:name":"El Ahijadero",
    "wof:placetype":"locality",
    "wof:population":7
},
  "geometry": {"coordinates":[-102.39778,18.12611],"type":"Point"}
}