{
  "type": "Feature",
  "properties": {
    "gn:admin1_code":"19",
    "gn:admin2_code":"13.0",
    "gn:asciiname":"San Juan de los Indios",
    "gn:country_code":"MX",
    "gn:dem":146,
    "gn:feature_class":"P",
    "gn:feature_code":"PPL",
    "gn:name":"San Juan de los Indios",
    "gn:population":0,
    "gn:timezone":"America/Monterrey",
    "iso:country":"MX",
    "name:spa_x_preferred":[
        "San Jos\u00e9 de los Indios"
    ],
    "name:spa_x_variant":[
        "San Juan de los Indios"
    ],
    "wof:name":"San Juan de los Indios",
    "wof:placetype":"locality"
},
  "geometry": {"coordinates":[-98.8092,25.59376],"type":"Point"}
}