{
  "type": "Feature",
  "properties": {
    "gn:admin1_code":"25.0",
    "gn:admin2_code":"13.0",
    "gn:asciiname":"Canutillos",
    "gn:country_code":"MX",
    "gn:dem":298,
    "gn:feature_class":"P",
    "gn:feature_code":"PPL",
    "gn:name":"Canutillos",
    "gn:population":82,
    "gn:timezone":"America/Mazatlan",
    "iso:country":"MX",
    "wof:name":"Canutillos",
    "wof:placetype":"locality",
    "wof:population":82
},
  "geometry": {"coordinates":[-107.74778000000001,25.675],"type":"Point"}
}