{
  "type": "Feature",
  "properties": {
    "gn:admin1_code":"5",
    "gn:admin2_code":"65.0",
    "gn:asciiname":"San Lorenzo (Chocolja)",
    "gn:country_code":"MX",
    "gn:dem":88,
    "gn:feature_class":"P",
    "gn:feature_code":"PPL",
    "gn:name":"San Lorenzo (Chocolj\u00e1)",
    "gn:population":472,
    "gn:timezone":"America/Mexico_City",
    "iso:country":"MX",
    "name:und_x_variant":[
        "San Lorenzo (Chocolj\u00e1)"
    ],
    "wof:name":"San Lorenzo (Chocolja)",
    "wof:placetype":"locality",
    "wof:population":472
},
  "geometry": {"coordinates":[-91.48889,17.23556],"type":"Point"}
}