{
  "type": "Feature",
  "properties": {
    "gn:admin1_code":"25",
    "gn:admin2_code":"7.0",
    "gn:asciiname":"Boca del Arroyo",
    "gn:country_code":"MX",
    "gn:dem":240,
    "gn:feature_class":"P",
    "gn:feature_code":"PPL",
    "gn:name":"Boca del Arroyo",
    "gn:population":0,
    "gn:timezone":"America/Mazatlan",
    "iso:country":"MX",
    "name:spa_x_preferred":[
        "Boca del Arroyo"
    ],
    "wof:name":"Boca del Arroyo",
    "wof:placetype":"locality"
},
  "geometry": {"coordinates":[-108.21278,26.88489],"type":"Point"}
}