{
  "type": "Feature",
  "properties": {
    "gn:admin1_code":"11",
    "gn:admin2_code":"37",
    "gn:asciiname":"El Tanque",
    "gn:country_code":"MX",
    "gn:dem":1864,
    "gn:feature_class":"P",
    "gn:feature_code":"PPL",
    "gn:name":"El Tanque",
    "gn:population":31,
    "gn:timezone":"America/Mexico_City",
    "iso:country":"MX",
    "wof:name":"El Tanque",
    "wof:placetype":"locality",
    "wof:population":31
},
  "geometry": {"coordinates":[-101.45806,21.05639],"type":"Point"}
}