{
  "type": "Feature",
  "properties": {
    "gn:admin1_code":"31.0",
    "gn:asciiname":"Yaxcaba",
    "gn:country_code":"MX",
    "gn:dem":15,
    "gn:feature_class":"P",
    "gn:feature_code":"PPL",
    "gn:name":"Yaxcab\u00e1",
    "gn:population":0,
    "gn:timezone":"America/Merida",
    "iso:country":"MX",
    "name:spa_x_preferred":[
        "Yaxcab\u00e1"
    ],
    "wof:name":"Yaxcaba",
    "wof:placetype":"locality"
},
  "geometry": {"coordinates":[-88.13776999999997,21.20554],"type":"Point"}
}