{
  "type": "Feature",
  "properties": {
    "gn:admin1_code":"10",
    "gn:admin2_code":"23.0",
    "gn:asciiname":"Los Bancos",
    "gn:country_code":"MX",
    "gn:dem":2653,
    "gn:feature_class":"P",
    "gn:feature_code":"PPL",
    "gn:name":"Los Bancos",
    "gn:population":0,
    "gn:timezone":"America/Monterrey",
    "iso:country":"MX",
    "name:spa_x_preferred":[
        "Los Bancos"
    ],
    "wof:name":"Los Bancos",
    "wof:placetype":"locality"
},
  "geometry": {"coordinates":[-105.43519000000001,23.54543],"type":"Point"}
}