{
  "type": "Feature",
  "properties": {
    "gn:admin1_code":"20",
    "gn:admin2_code":"85.0",
    "gn:asciiname":"Santa Cruz de las Flores",
    "gn:country_code":"MX",
    "gn:dem":1168,
    "gn:feature_class":"P",
    "gn:feature_code":"PPL",
    "gn:name":"Santa Cruz de las Flores",
    "gn:population":291,
    "gn:timezone":"America/Mexico_City",
    "iso:country":"MX",
    "wof:name":"Santa Cruz de las Flores",
    "wof:placetype":"locality",
    "wof:population":291
},
  "geometry": {"coordinates":[-96.65000000000001,16.01583],"type":"Point"}
}