{
  "type": "Feature",
  "properties": {
    "gn:admin1_code":"15.0",
    "gn:admin2_code":"105.0",
    "gn:asciiname":"Coahuayana",
    "gn:country_code":"MX",
    "gn:dem":969,
    "gn:feature_class":"P",
    "gn:feature_code":"PPL",
    "gn:name":"Coahuayana",
    "gn:population":0,
    "gn:timezone":"America/Mexico_City",
    "iso:country":"MX",
    "name:ceb_x_preferred":[
        "Coahuayana"
    ],
    "name:epo_x_preferred":[
        "Coahuayana"
    ],
    "name:eus_x_preferred":[
        "Coahuayana"
    ],
    "name:ita_x_preferred":[
        "Coahuayana"
    ],
    "name:spa_x_preferred":[
        "Coahuayana"
    ],
    "name:srp_x_preferred":[
        "\u041e\u043f\u0448\u0442\u0438\u043d\u0430 \u041a\u043e\u0430\u0432\u0430\u0458\u0430\u043d\u0430"
    ],
    "name:swe_x_preferred":[
        "Coahuayana"
    ],
    "name:vie_x_preferred":[
        "Coahuayana"
    ],
    "wof:name":"Coahuayana",
    "wof:placetype":"locality"
},
  "geometry": {"coordinates":[-100.3485,18.62129],"type":"Point"}
}