{
  "type": "Feature",
  "properties": {
    "gn:admin1_code":"28.0",
    "gn:admin2_code":"12.0",
    "gn:asciiname":"San Gabriel",
    "gn:country_code":"MX",
    "gn:dem":46,
    "gn:feature_class":"P",
    "gn:feature_code":"PPL",
    "gn:name":"San Gabriel",
    "gn:population":4,
    "gn:timezone":"America/Monterrey",
    "iso:country":"MX",
    "name:spa_x_preferred":[
        "San Gabriel"
    ],
    "wof:name":"San Gabriel",
    "wof:placetype":"locality",
    "wof:population":4
},
  "geometry": {"coordinates":[-98.67222,22.7625],"type":"Point"}
}