{
  "type": "Feature",
  "properties": {
    "gn:admin1_code":"5",
    "gn:admin2_code":"107.0",
    "gn:asciiname":"San Julian Fraccion II (Rizo de Oro)",
    "gn:country_code":"MX",
    "gn:dem":643,
    "gn:feature_class":"P",
    "gn:feature_code":"PPL",
    "gn:name":"San Juli\u00e1n Fracci\u00f3n II (Rizo de Oro)",
    "gn:population":5,
    "gn:timezone":"America/Mexico_City",
    "iso:country":"MX",
    "name:und_x_variant":[
        "San Juli\u00e1n Fracci\u00f3n II (Rizo de Oro)"
    ],
    "wof:name":"San Julian Fraccion II (Rizo de Oro)",
    "wof:placetype":"locality",
    "wof:population":5
},
  "geometry": {"coordinates":[-93.33667,16.10278],"type":"Point"}
}