{
  "type": "Feature",
  "properties": {
    "gn:admin1_code":"28",
    "gn:admin2_code":"22",
    "gn:asciiname":"Soledad",
    "gn:country_code":"MX",
    "gn:dem":15,
    "gn:feature_class":"P",
    "gn:feature_code":"PPL",
    "gn:name":"Soledad",
    "gn:population":31,
    "gn:timezone":"America/Matamoros",
    "iso:country":"MX",
    "wof:name":"Soledad",
    "wof:placetype":"locality",
    "wof:population":31
},
  "geometry": {"coordinates":[-97.61306,25.95611],"type":"Point"}
}