{
  "type": "Feature",
  "properties": {
    "gn:admin1_code":"16",
    "gn:admin2_code":"66",
    "gn:asciiname":"Colonia Melchor Ocampo (Tercera Ampliacion)",
    "gn:country_code":"MX",
    "gn:dem":2199,
    "gn:feature_class":"P",
    "gn:feature_code":"PPL",
    "gn:name":"Colonia Melchor Ocampo (Tercera Ampliaci\u00f3n)",
    "gn:population":27,
    "gn:timezone":"America/Mexico_City",
    "iso:country":"MX",
    "name:und_x_variant":[
        "Colonia Melchor Ocampo (Tercera Ampliaci\u00f3n)"
    ],
    "wof:name":"Colonia Melchor Ocampo (Tercera Ampliacion)",
    "wof:placetype":"locality",
    "wof:population":27
},
  "geometry": {"coordinates":[-101.63111000000001,19.50611],"type":"Point"}
}