{
  "type": "Feature",
  "properties": {
    "gn:admin1_code":"26",
    "gn:admin2_code":"40.0",
    "gn:asciiname":"La Venada",
    "gn:country_code":"MX",
    "gn:dem":2280,
    "gn:feature_class":"P",
    "gn:feature_code":"PPL",
    "gn:name":"La Venada",
    "gn:population":0,
    "gn:timezone":"America/Hermosillo",
    "iso:country":"MX",
    "name:spa_x_preferred":[
        "La Venada"
    ],
    "wof:name":"La Venada",
    "wof:placetype":"locality"
},
  "geometry": {"coordinates":[-108.83385,29.94107],"type":"Point"}
}