{
  "type": "Feature",
  "properties": {
    "gn:admin1_code":"20",
    "gn:admin2_code":"12",
    "gn:asciiname":"La Finca",
    "gn:country_code":"MX",
    "gn:dem":937,
    "gn:feature_class":"P",
    "gn:feature_code":"PPL",
    "gn:name":"La Finca",
    "gn:population":47,
    "gn:timezone":"America/Mexico_City",
    "iso:country":"MX",
    "wof:name":"La Finca",
    "wof:placetype":"locality",
    "wof:population":47
},
  "geometry": {"coordinates":[-96.56222,15.90139],"type":"Point"}
}