{
  "type": "Feature",
  "properties": {
    "gn:admin1_code":"13",
    "gn:admin2_code":"77.0",
    "gn:asciiname":"La Raya",
    "gn:country_code":"MX",
    "gn:dem":2208,
    "gn:feature_class":"P",
    "gn:feature_code":"PPL",
    "gn:name":"La Raya",
    "gn:population":133,
    "gn:timezone":"America/Mexico_City",
    "iso:country":"MX",
    "name:spa_x_preferred":[
        "La Raya"
    ],
    "wof:name":"La Raya",
    "wof:placetype":"locality",
    "wof:population":133
},
  "geometry": {"coordinates":[-98.30502,20.15362],"type":"Point"}
}