{
  "type": "Feature",
  "properties": {
    "gn:admin1_code":"5",
    "gn:admin2_code":"32.0",
    "gn:asciiname":"Tres Rios",
    "gn:country_code":"MX",
    "gn:dem":952,
    "gn:feature_class":"P",
    "gn:feature_code":"PPL",
    "gn:name":"Tres R\u00edos",
    "gn:population":55,
    "gn:timezone":"America/Mexico_City",
    "iso:country":"MX",
    "name:und_x_variant":[
        "Tres R\u00edos"
    ],
    "wof:name":"Tres Rios",
    "wof:placetype":"locality",
    "wof:population":55
},
  "geometry": {"coordinates":[-92.47028,15.31417],"type":"Point"}
}