{
  "type": "Feature",
  "properties": {
    "gn:admin1_code":"11.0",
    "gn:admin2_code":"23.0",
    "gn:asciiname":"Mezquite de Luna",
    "gn:country_code":"MX",
    "gn:dem":1682,
    "gn:feature_class":"P",
    "gn:feature_code":"PPL",
    "gn:name":"Mezquite de Luna",
    "gn:population":1191,
    "gn:timezone":"America/Mexico_City",
    "iso:country":"MX",
    "name:spa_x_preferred":[
        "Mezquite de Luna"
    ],
    "wof:name":"Mezquite de Luna",
    "wof:placetype":"locality",
    "wof:population":1191
},
  "geometry": {"coordinates":[-101.8926,20.29765],"type":"Point"}
}