{
  "type": "Feature",
  "properties": {
    "gn:admin1_code":"14.0",
    "gn:admin2_code":"56.0",
    "gn:asciiname":"El Ciruelo",
    "gn:country_code":"MX",
    "gn:dem":1032,
    "gn:feature_class":"P",
    "gn:feature_code":"PPL",
    "gn:name":"El Ciruelo",
    "gn:population":4,
    "gn:timezone":"America/Mexico_City",
    "iso:country":"MX",
    "name:ita_x_preferred":[
        "El Ciruelo"
    ],
    "name:spa_x_preferred":[
        "El Ciruelo"
    ],
    "name:und_x_variant":[
        "Ciruelo",
        "El Ciruelo"
    ],
    "name:zho_x_preferred":[
        "\u57c3\u723e\u897f\u9b6f\u57c3\u6d1b"
    ],
    "wof:name":"El Ciruelo",
    "wof:placetype":"locality",
    "wof:population":4
},
  "geometry": {"coordinates":[-102.94083000000001,19.46125],"type":"Point"}
}