{
  "type": "Feature",
  "properties": {
    "gn:admin1_code":"13",
    "gn:admin2_code":"15.0",
    "gn:asciiname":"Cerro Colorado",
    "gn:country_code":"MX",
    "gn:dem":1947,
    "gn:feature_class":"P",
    "gn:feature_code":"PPL",
    "gn:name":"Cerro Colorado",
    "gn:population":392,
    "gn:timezone":"America/Mexico_City",
    "iso:country":"MX",
    "name:ceb_x_preferred":[
        "Cerro Colorado"
    ],
    "name:deu_x_preferred":[
        "Cerro Colorado"
    ],
    "name:spa_x_preferred":[
        "Cerro Colorado"
    ],
    "name:swe_x_preferred":[
        "Cerro Colorado"
    ],
    "wof:name":"Cerro Colorado",
    "wof:placetype":"locality",
    "wof:population":392
},
  "geometry": {"coordinates":[-99.13472,20.60694],"type":"Point"}
}