{
  "type": "Feature",
  "properties": {
    "gn:admin1_code":"21",
    "gn:admin2_code":"187.0",
    "gn:asciiname":"Atlalpan",
    "gn:country_code":"MX",
    "gn:dem":826,
    "gn:feature_class":"P",
    "gn:feature_code":"PPL",
    "gn:name":"Atlalpan",
    "gn:population":0,
    "gn:timezone":"America/Mexico_City",
    "iso:country":"MX",
    "name:spa_x_preferred":[
        "Atlalpan"
    ],
    "wof:name":"Atlalpan",
    "wof:placetype":"locality"
},
  "geometry": {"coordinates":[-98.06544,20.39004],"type":"Point"}
}