{
  "type": "Feature",
  "properties": {
    "gn:admin1_code":"16",
    "gn:admin2_code":"14",
    "gn:asciiname":"El Sifon",
    "gn:country_code":"MX",
    "gn:dem":26,
    "gn:feature_class":"P",
    "gn:feature_code":"PPL",
    "gn:name":"El Sif\u00f3n",
    "gn:population":10,
    "gn:timezone":"America/Mexico_City",
    "iso:country":"MX",
    "name:und_x_variant":[
        "El Sif\u00f3n"
    ],
    "wof:name":"El Sifon",
    "wof:placetype":"locality",
    "wof:population":10
},
  "geometry": {"coordinates":[-103.65971999999999,18.75111],"type":"Point"}
}