{
  "type": "Feature",
  "properties": {
    "gn:admin1_code":"24",
    "gn:admin2_code":"7.0",
    "gn:asciiname":"El Refugio de las Monjas",
    "gn:country_code":"MX",
    "gn:dem":1789,
    "gn:feature_class":"P",
    "gn:feature_code":"PPL",
    "gn:name":"El Refugio de las Monjas",
    "gn:population":0,
    "gn:timezone":"America/Mexico_City",
    "iso:country":"MX",
    "wof:name":"El Refugio de las Monjas",
    "wof:placetype":"locality"
},
  "geometry": {"coordinates":[-100.72608,23.75603],"type":"Point"}
}