{
  "type": "Feature",
  "properties": {
    "gn:admin1_code":"6.0",
    "gn:admin2_code":"12.0",
    "gn:asciiname":"El Alamo de Ojos Azules",
    "gn:country_code":"MX",
    "gn:dem":2174,
    "gn:feature_class":"P",
    "gn:feature_code":"PPL",
    "gn:name":"El \u00c1lamo de Ojos Azules",
    "gn:population":134,
    "gn:timezone":"America/Chihuahua",
    "iso:country":"MX",
    "wof:name":"El Alamo de Ojos Azules",
    "wof:placetype":"locality",
    "wof:population":134
},
  "geometry": {"coordinates":[-106.99903999999999,28.02138],"type":"Point"}
}