{
  "type": "Feature",
  "properties": {
    "gn:admin1_code":"5",
    "gn:admin2_code":"65.0",
    "gn:asciiname":"Pueblo Nuevo Usumacinta",
    "gn:country_code":"MX",
    "gn:dem":100,
    "gn:feature_class":"P",
    "gn:feature_code":"PPL",
    "gn:name":"Pueblo Nuevo Usumacinta",
    "gn:population":139,
    "gn:timezone":"America/Mexico_City",
    "iso:country":"MX",
    "wof:name":"Pueblo Nuevo Usumacinta",
    "wof:placetype":"locality",
    "wof:population":139
},
  "geometry": {"coordinates":[-91.43805999999999,17.37028],"type":"Point"}
}