{
  "type": "Feature",
  "properties": {
    "gn:admin1_code":"27",
    "gn:admin2_code":"13.0",
    "gn:asciiname":"Tecoluta",
    "gn:country_code":"MX",
    "gn:dem":5,
    "gn:feature_class":"P",
    "gn:feature_code":"PPL",
    "gn:name":"Tecoluta",
    "gn:population":0,
    "gn:timezone":"America/Mexico_City",
    "iso:country":"MX",
    "name:spa_x_preferred":[
        "Tecoluta"
    ],
    "wof:name":"Tecoluta",
    "wof:placetype":"locality"
},
  "geometry": {"coordinates":[-93.0184,18.25431],"type":"Point"}
}