{
  "type": "Feature",
  "properties": {
    "gn:admin1_code":"12.0",
    "gn:admin2_code":"7.0",
    "gn:asciiname":"Rancho Zozontla",
    "gn:country_code":"MX",
    "gn:dem":375,
    "gn:feature_class":"P",
    "gn:feature_code":"PPL",
    "gn:name":"Rancho Zozontla",
    "gn:population":0,
    "gn:timezone":"America/Mexico_City",
    "iso:country":"MX",
    "name:spa_x_preferred":[
        "Rancho Zozontla"
    ],
    "wof:name":"Rancho Zozontla",
    "wof:placetype":"locality"
},
  "geometry": {"coordinates":[-100.30989,18.31517],"type":"Point"}
}