{
  "type": "Feature",
  "properties": {
    "gn:admin1_code":"24",
    "gn:admin2_code":"31.0",
    "gn:asciiname":"Cuesta del Carpintero",
    "gn:country_code":"MX",
    "gn:dem":589,
    "gn:feature_class":"P",
    "gn:feature_code":"PPL",
    "gn:name":"Cuesta del Carpintero",
    "gn:population":0,
    "gn:timezone":"America/Mexico_City",
    "iso:country":"MX",
    "wof:name":"Cuesta del Carpintero",
    "wof:placetype":"locality"
},
  "geometry": {"coordinates":[-99.48333,21.45],"type":"Point"}
}