{
  "type": "Feature",
  "properties": {
    "gn:admin1_code":"16.0",
    "gn:admin2_code":"10.0",
    "gn:asciiname":"La Cana Dulce",
    "gn:country_code":"MX",
    "gn:dem":736,
    "gn:feature_class":"P",
    "gn:feature_code":"PPL",
    "gn:name":"La Ca\u00f1a Dulce",
    "gn:population":0,
    "gn:timezone":"America/Mexico_City",
    "iso:country":"MX",
    "name:spa_x_preferred":[
        "La Ca\u00f1a Dulce"
    ],
    "wof:name":"La Cana Dulce",
    "wof:placetype":"locality"
},
  "geometry": {"coordinates":[-102.096,18.36387],"type":"Point"}
}