{
  "type": "Feature",
  "properties": {
    "gn:admin1_code":"26",
    "gn:admin2_code":"9.0",
    "gn:asciiname":"La Joyita",
    "gn:country_code":"MX",
    "gn:dem":962,
    "gn:feature_class":"P",
    "gn:feature_code":"PPL",
    "gn:name":"La Joyita",
    "gn:population":0,
    "gn:timezone":"America/Hermosillo",
    "iso:country":"MX",
    "name:spa_x_preferred":[
        "La Joyita"
    ],
    "wof:name":"La Joyita",
    "wof:placetype":"locality"
},
  "geometry": {"coordinates":[-109.28581,28.72729],"type":"Point"}
}