{
  "type": "Feature",
  "properties": {
    "gn:admin1_code":"13",
    "gn:admin2_code":"4.0",
    "gn:asciiname":"Sabanillas",
    "gn:country_code":"MX",
    "gn:dem":2153,
    "gn:feature_class":"P",
    "gn:feature_code":"PPL",
    "gn:name":"Sabanillas",
    "gn:population":175,
    "gn:timezone":"America/Mexico_City",
    "iso:country":"MX",
    "wof:name":"Sabanillas",
    "wof:placetype":"locality",
    "wof:population":175
},
  "geometry": {"coordinates":[-98.36175,20.33621],"type":"Point"}
}