{
  "type": "Feature",
  "properties": {
    "gn:admin1_code":"26.0",
    "gn:admin2_code":"30.0",
    "gn:asciiname":"Zacaton",
    "gn:country_code":"MX",
    "gn:dem":302,
    "gn:feature_class":"P",
    "gn:feature_code":"PPL",
    "gn:name":"Zacat\u00f3n",
    "gn:population":0,
    "gn:timezone":"America/Hermosillo",
    "iso:country":"MX",
    "name:und_x_variant":[
        "Zacat\u00f3n",
        "Rancho Zacat\u00f3n",
        "El Zacat\u00f3n"
    ],
    "wof:name":"Zacaton",
    "wof:placetype":"locality"
},
  "geometry": {"coordinates":[-110.84893,29.27483],"type":"Point"}
}