{
  "type": "Feature",
  "properties": {
    "gn:admin1_code":"15",
    "gn:admin2_code":"82",
    "gn:asciiname":"Cuevillas",
    "gn:country_code":"MX",
    "gn:dem":1202,
    "gn:feature_class":"P",
    "gn:feature_code":"PPL",
    "gn:name":"Cuevillas",
    "gn:population":52,
    "gn:timezone":"America/Mexico_City",
    "iso:country":"MX",
    "wof:name":"Cuevillas",
    "wof:placetype":"locality",
    "wof:population":52
},
  "geometry": {"coordinates":[-100.25785999999999,19.0049],"type":"Point"}
}