{
  "type": "Feature",
  "properties": {
    "gn:admin1_code":"17",
    "gn:admin2_code":"29",
    "gn:asciiname":"Conjunto Tepetlixpa",
    "gn:country_code":"MX",
    "gn:dem":1235,
    "gn:feature_class":"P",
    "gn:feature_code":"PPL",
    "gn:name":"Conjunto Tepetlixpa",
    "gn:population":39,
    "gn:timezone":"America/Mexico_City",
    "iso:country":"MX",
    "wof:name":"Conjunto Tepetlixpa",
    "wof:placetype":"locality",
    "wof:population":39
},
  "geometry": {"coordinates":[-99.04639,18.9125],"type":"Point"}
}