{
  "type": "Feature",
  "properties": {
    "gn:admin1_code":"27",
    "gn:admin2_code":"2.0",
    "gn:asciiname":"Ignacio Zaragoza",
    "gn:country_code":"MX",
    "gn:dem":11,
    "gn:feature_class":"P",
    "gn:feature_code":"PPL",
    "gn:name":"Ignacio Zaragoza",
    "gn:population":415,
    "gn:timezone":"America/Mexico_City",
    "iso:country":"MX",
    "wof:name":"Ignacio Zaragoza",
    "wof:placetype":"locality",
    "wof:population":415
},
  "geometry": {"coordinates":[-93.75694,18.15194],"type":"Point"}
}