{
  "type": "Feature",
  "properties": {
    "gn:admin1_code":"24",
    "gn:admin2_code":"44",
    "gn:asciiname":"Ampelio Rodriguez Banda (Lazaro Cardenas)",
    "gn:country_code":"MX",
    "gn:dem":1704,
    "gn:feature_class":"P",
    "gn:feature_code":"PPL",
    "gn:name":"Ampelio Rodr\u00edguez Banda (L\u00e1zaro C\u00e1rdenas)",
    "gn:population":12,
    "gn:timezone":"America/Monterrey",
    "iso:country":"MX",
    "name:und_x_variant":[
        "Ampelio Rodr\u00edguez Banda (L\u00e1zaro C\u00e1rdenas)"
    ],
    "wof:name":"Ampelio Rodriguez Banda (Lazaro Cardenas)",
    "wof:placetype":"locality",
    "wof:population":12
},
  "geometry": {"coordinates":[-100.62278000000001,24.35917],"type":"Point"}
}