{
  "type": "Feature",
  "properties": {
    "gn:admin1_code":"23",
    "gn:admin2_code":"4.0",
    "gn:asciiname":"El Cafetal",
    "gn:cc2":"MX",
    "gn:country_code":"MX",
    "gn:dem":18,
    "gn:feature_class":"P",
    "gn:feature_code":"PPL",
    "gn:name":"El Cafetal",
    "gn:population":0,
    "gn:timezone":"America/Cancun",
    "iso:country":"MX",
    "name:spa_x_preferred":[
        "El Cafetal"
    ],
    "name:und_x_variant":[
        "Cafetal"
    ],
    "wof:name":"El Cafetal",
    "wof:placetype":"locality"
},
  "geometry": {"coordinates":[-88.21666999999999,18.91667],"type":"Point"}
}