{
  "type": "Feature",
  "properties": {
    "gn:admin1_code":"24",
    "gn:admin2_code":"43.0",
    "gn:asciiname":"El Camaron",
    "gn:country_code":"MX",
    "gn:dem":1554,
    "gn:feature_class":"P",
    "gn:feature_code":"PPL",
    "gn:name":"El Camaron",
    "gn:population":0,
    "gn:timezone":"America/Mexico_City",
    "iso:country":"MX",
    "name:und_x_variant":[
        "El Camar\u00f3n",
        "Camar\u00f3n"
    ],
    "wof:name":"El Camaron",
    "wof:placetype":"locality"
},
  "geometry": {"coordinates":[-100.32489,21.69306],"type":"Point"}
}