{
  "type": "Feature",
  "properties": {
    "gn:admin1_code":"3",
    "gn:admin2_code":"1.0",
    "gn:asciiname":"Agua Relumbrosa",
    "gn:country_code":"MX",
    "gn:dem":238,
    "gn:feature_class":"P",
    "gn:feature_code":"PPL",
    "gn:name":"Agua Relumbrosa",
    "gn:population":0,
    "gn:timezone":"America/Mazatlan",
    "iso:country":"MX",
    "name:spa_x_preferred":[
        "La Vinater\u00eda Dos"
    ],
    "name:spa_x_variant":[
        "Agua Relumbrosa"
    ],
    "wof:name":"Agua Relumbrosa",
    "wof:placetype":"locality"
},
  "geometry": {"coordinates":[-111.36593999999999,25.4085],"type":"Point"}
}