{
  "type": "Feature",
  "properties": {
    "gn:admin1_code":"7.0",
    "gn:admin2_code":"20.0",
    "gn:asciiname":"El Socorro",
    "gn:country_code":"MX",
    "gn:dem":715,
    "gn:feature_class":"P",
    "gn:feature_code":"PPL",
    "gn:name":"El Socorro",
    "gn:population":0,
    "gn:timezone":"America/Monterrey",
    "iso:country":"MX",
    "name:ceb_x_preferred":[
        "El Socorro"
    ],
    "name:fra_x_preferred":[
        "El Socorro"
    ],
    "name:spa_x_preferred":[
        "El Socorro"
    ],
    "name:swe_x_preferred":[
        "El Socorro"
    ],
    "wof:name":"El Socorro",
    "wof:placetype":"locality"
},
  "geometry": {"coordinates":[-101.90474,28.0648],"type":"Point"}
}