{
  "type": "Feature",
  "properties": {
    "gn:admin1_code":"4",
    "gn:admin2_code":"3.0",
    "gn:asciiname":"El Polvoron (Los Dos Arbolitos)",
    "gn:country_code":"MX",
    "gn:dem":22,
    "gn:feature_class":"P",
    "gn:feature_code":"PPL",
    "gn:name":"El Polvor\u00f3n (Los Dos Arbolitos)",
    "gn:population":6,
    "gn:timezone":"America/Merida",
    "iso:country":"MX",
    "name:und_x_variant":[
        "El Polvor\u00f3n (Los Dos Arbolitos)"
    ],
    "wof:name":"El Polvoron (Los Dos Arbolitos)",
    "wof:placetype":"locality",
    "wof:population":6
},
  "geometry": {"coordinates":[-91.36833,18.24167000000001],"type":"Point"}
}