{
  "type": "Feature",
  "properties": {
    "gn:admin1_code":"5",
    "gn:admin2_code":"23.0",
    "gn:asciiname":"Takitetik",
    "gn:country_code":"MX",
    "gn:dem":2440,
    "gn:feature_class":"P",
    "gn:feature_code":"PPL",
    "gn:name":"Takitetik",
    "gn:population":0,
    "gn:timezone":"America/Mexico_City",
    "iso:country":"MX",
    "name:spa_x_preferred":[
        "Takitetik"
    ],
    "name:spa_x_variant":[
        "Taketekik"
    ],
    "wof:name":"Takitetik",
    "wof:placetype":"locality"
},
  "geometry": {"coordinates":[-92.76291000000001,16.83961],"type":"Point"}
}