{
  "type": "Feature",
  "properties": {
    "gn:admin1_code":"24",
    "gn:admin2_code":"15.0",
    "gn:asciiname":"Las Palomas",
    "gn:country_code":"MX",
    "gn:dem":2214,
    "gn:feature_class":"P",
    "gn:feature_code":"PPL",
    "gn:name":"Las Palomas",
    "gn:population":5,
    "gn:timezone":"America/Mexico_City",
    "iso:country":"MX",
    "wof:name":"Las Palomas",
    "wof:placetype":"locality",
    "wof:population":5
},
  "geometry": {"coordinates":[-101.20222,23.24528],"type":"Point"}
}