{
  "type": "Feature",
  "properties": {
    "gn:admin1_code":"14",
    "gn:admin2_code":"73.0",
    "gn:asciiname":"San Aparicio",
    "gn:country_code":"MX",
    "gn:dem":1819,
    "gn:feature_class":"P",
    "gn:feature_code":"PPL",
    "gn:name":"San Aparicio",
    "gn:population":38,
    "gn:timezone":"America/Mexico_City",
    "iso:country":"MX",
    "wof:name":"San Aparicio",
    "wof:placetype":"locality",
    "wof:population":38
},
  "geometry": {"coordinates":[-102.25278,21.34444],"type":"Point"}
}