{
  "type": "Feature",
  "properties": {
    "gn:admin1_code":"20",
    "gn:admin2_code":"139.0",
    "gn:asciiname":"Guadalupe Siete Cerros",
    "gn:country_code":"MX",
    "gn:dem":1499,
    "gn:feature_class":"P",
    "gn:feature_code":"PPL",
    "gn:name":"Guadalupe Siete Cerros",
    "gn:population":351,
    "gn:timezone":"America/Mexico_City",
    "iso:country":"MX",
    "wof:name":"Guadalupe Siete Cerros",
    "wof:placetype":"locality",
    "wof:population":351
},
  "geometry": {"coordinates":[-96.71194,17.8975],"type":"Point"}
}