{
  "type": "Feature",
  "properties": {
    "gn:admin1_code":"2",
    "gn:admin2_code":"1.0",
    "gn:asciiname":"La Mision",
    "gn:country_code":"MX",
    "gn:dem":92,
    "gn:feature_class":"P",
    "gn:feature_code":"PPL",
    "gn:name":"La Misi\u00f3n",
    "gn:population":7,
    "gn:timezone":"America/Tijuana",
    "iso:country":"MX",
    "name:und_x_variant":[
        "La Misi\u00f3n"
    ],
    "wof:name":"La Mision",
    "wof:placetype":"locality",
    "wof:population":7
},
  "geometry": {"coordinates":[-116.25556,31.33278],"type":"Point"}
}