{
  "type": "Feature",
  "properties": {
    "gn:admin1_code":"28.0",
    "gn:admin2_code":"11.0",
    "gn:asciiname":"La Pedrera",
    "gn:country_code":"MX",
    "gn:dem":101,
    "gn:feature_class":"P",
    "gn:feature_code":"PPL",
    "gn:name":"La Pedrera",
    "gn:population":10,
    "gn:timezone":"America/Monterrey",
    "iso:country":"MX",
    "name:spa_x_preferred":[
        "La Pedrera"
    ],
    "wof:name":"La Pedrera",
    "wof:placetype":"locality",
    "wof:population":10
},
  "geometry": {"coordinates":[-99.06389,22.985],"type":"Point"}
}