{
  "type": "Feature",
  "properties": {
    "gn:admin1_code":"10",
    "gn:admin2_code":"9.0",
    "gn:asciiname":"Nombre de Dios",
    "gn:country_code":"MX",
    "gn:dem":1869,
    "gn:feature_class":"P",
    "gn:feature_code":"PPL",
    "gn:name":"Nombre de Dios",
    "gn:population":0,
    "gn:timezone":"America/Monterrey",
    "iso:country":"MX",
    "name:spa_x_preferred":[
        "Nombre de Dios"
    ],
    "name:srp_x_preferred":[
        "\u041d\u043e\u043c\u0431\u0440\u0435 \u0434\u0435 \u0414\u0438\u043e\u0441"
    ],
    "wof:name":"Nombre de Dios",
    "wof:placetype":"locality"
},
  "geometry": {"coordinates":[-105.82773,26.03646],"type":"Point"}
}