{
  "type": "Feature",
  "properties": {
    "gn:admin1_code":"10",
    "gn:admin2_code":"9",
    "gn:asciiname":"La Mesa de Coscomate",
    "gn:country_code":"MX",
    "gn:dem":2816,
    "gn:feature_class":"P",
    "gn:feature_code":"PPL",
    "gn:name":"La Mesa de Coscomate",
    "gn:population":11,
    "gn:timezone":"America/Monterrey",
    "iso:country":"MX",
    "wof:name":"La Mesa de Coscomate",
    "wof:placetype":"locality",
    "wof:population":11
},
  "geometry": {"coordinates":[-106.17734,26.15691],"type":"Point"}
}