{
  "type": "Feature",
  "properties": {
    "gn:admin1_code":"15",
    "gn:admin2_code":"37.0",
    "gn:asciiname":"San Crisobal Texcalucan",
    "gn:country_code":"MX",
    "gn:dem":2586,
    "gn:feature_class":"P",
    "gn:feature_code":"PPL",
    "gn:name":"San Cris\u00f3bal Texcalucan",
    "gn:population":0,
    "gn:timezone":"America/Mexico_City",
    "iso:country":"MX",
    "wof:name":"San Crisobal Texcalucan",
    "wof:placetype":"locality"
},
  "geometry": {"coordinates":[-99.33028,19.39917],"type":"Point"}
}