{
  "type": "Feature",
  "properties": {
    "gn:admin1_code":"5.0",
    "gn:admin2_code":"10.0",
    "gn:asciiname":"Cal y Canto",
    "gn:country_code":"MX",
    "gn:dem":925,
    "gn:feature_class":"P",
    "gn:feature_code":"PPL",
    "gn:name":"Cal y Canto",
    "gn:population":0,
    "gn:timezone":"America/Mexico_City",
    "iso:country":"MX",
    "name:spa_x_preferred":[
        "Cal y Canto"
    ],
    "wof:name":"Cal y Canto",
    "wof:placetype":"locality"
},
  "geometry": {"coordinates":[-92.12336000000001,15.48938],"type":"Point"}
}