{
  "type": "Feature",
  "properties": {
    "gn:admin1_code":"30.0",
    "gn:admin2_code":"157.0",
    "gn:asciiname":"La Coca",
    "gn:country_code":"MX",
    "gn:dem":97,
    "gn:feature_class":"P",
    "gn:feature_code":"PPL",
    "gn:name":"La Coca",
    "gn:population":0,
    "gn:timezone":"America/Mexico_City",
    "iso:country":"MX",
    "name:spa_x_preferred":[
        "La Coca"
    ],
    "wof:name":"La Coca",
    "wof:placetype":"locality"
},
  "geometry": {"coordinates":[-97.61159000000001,20.74118],"type":"Point"}
}