{
  "type": "Feature",
  "properties": {
    "gn:admin1_code":"20",
    "gn:admin2_code":"532.0",
    "gn:asciiname":"Genaro V. Vasquez",
    "gn:country_code":"MX",
    "gn:dem":2125,
    "gn:feature_class":"P",
    "gn:feature_code":"PPL",
    "gn:name":"Genaro V. V\u00e1squez",
    "gn:population":196,
    "gn:timezone":"America/Mexico_City",
    "iso:country":"MX",
    "name:und_x_variant":[
        "Genaro V. V\u00e1squez"
    ],
    "wof:name":"Genaro V. Vasquez",
    "wof:placetype":"locality",
    "wof:population":196
},
  "geometry": {"coordinates":[-97.77056,17.16361],"type":"Point"}
}