{
  "type": "Feature",
  "properties": {
    "gn:admin1_code":"14",
    "gn:admin2_code":"44",
    "gn:asciiname":"El Tepache",
    "gn:country_code":"MX",
    "gn:dem":1535,
    "gn:feature_class":"P",
    "gn:feature_code":"PPL",
    "gn:name":"El Tepache",
    "gn:population":21,
    "gn:timezone":"America/Mexico_City",
    "iso:country":"MX",
    "wof:name":"El Tepache",
    "wof:placetype":"locality",
    "wof:population":21
},
  "geometry": {"coordinates":[-103.20999999999999,20.41139],"type":"Point"}
}