{
  "type": "Feature",
  "properties": {
    "gn:admin1_code":"14",
    "gn:admin2_code":"49",
    "gn:asciiname":"Huapala",
    "gn:country_code":"MX",
    "gn:dem":1437,
    "gn:feature_class":"P",
    "gn:feature_code":"PPL",
    "gn:name":"Huapala",
    "gn:population":43,
    "gn:timezone":"America/Mexico_City",
    "iso:country":"MX",
    "wof:name":"Huapala",
    "wof:placetype":"locality",
    "wof:population":43
},
  "geometry": {"coordinates":[-103.10361,19.3525],"type":"Point"}
}