{
  "type": "Feature",
  "properties": {
    "gn:admin1_code":"14",
    "gn:admin2_code":"40.0",
    "gn:asciiname":"Tequesquite",
    "gn:country_code":"MX",
    "gn:dem":1393,
    "gn:feature_class":"P",
    "gn:feature_code":"PPL",
    "gn:name":"Tequesquite",
    "gn:population":0,
    "gn:timezone":"America/Mexico_City",
    "iso:country":"MX",
    "name:nah_x_preferred":[
        "Tequixquitl"
    ],
    "name:spa_x_preferred":[
        "Tequesquite"
    ],
    "wof:name":"Tequesquite",
    "wof:placetype":"locality"
},
  "geometry": {"coordinates":[-104.05341,20.99247],"type":"Point"}
}