{
  "type": "Feature",
  "properties": {
    "gn:admin1_code":"13",
    "gn:admin2_code":"69.0",
    "gn:asciiname":"Loma Bonita",
    "gn:country_code":"MX",
    "gn:dem":2284,
    "gn:feature_class":"P",
    "gn:feature_code":"PPL",
    "gn:name":"Loma Bonita",
    "gn:population":283,
    "gn:timezone":"America/Mexico_City",
    "iso:country":"MX",
    "wof:name":"Loma Bonita",
    "wof:placetype":"locality",
    "wof:population":283
},
  "geometry": {"coordinates":[-98.95417,19.85389],"type":"Point"}
}