{
  "type": "Feature",
  "properties": {
    "gn:admin1_code":"13",
    "gn:admin2_code":"11.0",
    "gn:asciiname":"Tempexquite",
    "gn:country_code":"MX",
    "gn:dem":421,
    "gn:feature_class":"P",
    "gn:feature_code":"PPL",
    "gn:name":"Tempexquite",
    "gn:population":0,
    "gn:timezone":"America/Mexico_City",
    "iso:country":"MX",
    "name:spa_x_preferred":[
        "Tempexquite"
    ],
    "wof:name":"Tempexquite",
    "wof:placetype":"locality"
},
  "geometry": {"coordinates":[-98.35043,21.08255],"type":"Point"}
}