{
  "type": "Feature",
  "properties": {
    "iso:country":"MX",
    "name:cat_x_preferred":[
        "Villa San Jos\u00e9"
    ],
    "name:deu_x_preferred":[
        "Villa San Jos\u00e9"
    ],
    "name:nor_x_preferred":[
        "Villa San Jos\u00e9"
    ],
    "name:spa_x_preferred":[
        "Fracc Las Villas"
    ],
    "name:unk_x_variant":[
        "Fracc Las Villas"
    ],
    "qs:gn_adm0_cc":"MX",
    "qs:gn_local":3981254,
    "qs:gn_nam_loc":"Torreon, Torre\u00f3n, Coahuila de Zaragoza, MX",
    "qs:gn_namadm1":"07",
    "qs:local_max":363,
    "qs:local_sum":1329,
    "qs:localhoods":14,
    "qs:name":"Fracc Las Villas",
    "qs:name_adm0":"M\u00e9xico",
    "qs:name_adm1":"Coahuila de Zaragoza",
    "qs:name_adm2":"Torreon",
    "qs:name_local":"Torre\u00f3n",
    "qs:photo_max":21,
    "qs:photo_sum":25,
    "qs:placetype":"Suburb",
    "qs:quad_count":4,
    "qs:woe_adm0":23424900,
    "qs:woe_adm1":2346270,
    "qs:woe_adm2":12599920,
    "qs:woe_lau":0,
    "qs:woe_local":149893,
    "qs:woe_ver":"7.10.0",
    "wof:lang":[
        "spa"
    ],
    "wof:name":"Fracc Las Villas",
    "wof:placetype":"neighbourhood"
},
  "geometry": {"coordinates":[-103.412436,25.535007],"type":"Point"}
}