{
  "type": "Feature",
  "properties": {
    "gn:admin1_code":"20",
    "gn:admin2_code":"332.0",
    "gn:asciiname":"Yunduza",
    "gn:country_code":"MX",
    "gn:dem":2155,
    "gn:feature_class":"P",
    "gn:feature_code":"PPL",
    "gn:name":"Yunduza",
    "gn:population":6,
    "gn:timezone":"America/Mexico_City",
    "iso:country":"MX",
    "wof:name":"Yunduza",
    "wof:placetype":"locality",
    "wof:population":6
},
  "geometry": {"coordinates":[-97.35028,17.43139],"type":"Point"}
}