{
  "type": "Feature",
  "properties": {
    "gn:admin1_code":"15.0",
    "gn:asciiname":"El Fresno",
    "gn:country_code":"MX",
    "gn:dem":1968,
    "gn:feature_class":"P",
    "gn:feature_code":"PPL",
    "gn:name":"El Fresno",
    "gn:population":0,
    "gn:timezone":"America/Mexico_City",
    "iso:country":"MX",
    "name:spa_x_preferred":[
        "El Fresno"
    ],
    "wof:name":"El Fresno",
    "wof:placetype":"locality"
},
  "geometry": {"coordinates":[-102.80212,19.99427],"type":"Point"}
}