{
  "type": "Feature",
  "properties": {
    "gn:admin1_code":"11",
    "gn:admin2_code":"17.0",
    "gn:asciiname":"Purisima de Covarrubias",
    "gn:country_code":"MX",
    "gn:dem":1710,
    "gn:feature_class":"P",
    "gn:feature_code":"PPL",
    "gn:name":"Pur\u00edsima de Covarrubias",
    "gn:population":0,
    "gn:timezone":"America/Mexico_City",
    "iso:country":"MX",
    "name:und_x_variant":[
        "Pur\u00edsima",
        "Pur\u00edsima de Covarrubias"
    ],
    "wof:name":"Purisima de Covarrubias",
    "wof:placetype":"locality"
},
  "geometry": {"coordinates":[-101.4834,20.61932],"type":"Point"}
}