{
  "type": "Feature",
  "properties": {
    "gn:admin1_code":"21",
    "gn:admin2_code":"179.0",
    "gn:asciiname":"San Jose la Capilla",
    "gn:country_code":"MX",
    "gn:dem":2457,
    "gn:feature_class":"P",
    "gn:feature_code":"PPL",
    "gn:name":"San Jos\u00e9 la Capilla",
    "gn:population":0,
    "gn:timezone":"America/Mexico_City",
    "iso:country":"MX",
    "name:spa_x_preferred":[
        "San Jos\u00e9 la Capilla"
    ],
    "name:und_x_variant":[
        "San Jos\u00e9 Capilla",
        "La Capilla"
    ],
    "wof:name":"San Jose la Capilla",
    "wof:placetype":"locality"
},
  "geometry": {"coordinates":[-97.37927999999999,19.22408],"type":"Point"}
}