{
  "type": "Feature",
  "properties": {
    "gn:admin1_code":"32.0",
    "gn:admin2_code":"26.0",
    "gn:asciiname":"El Dormido",
    "gn:country_code":"MX",
    "gn:dem":2033,
    "gn:feature_class":"P",
    "gn:feature_code":"PPL",
    "gn:name":"El Dormido",
    "gn:population":0,
    "gn:timezone":"America/Mexico_City",
    "iso:country":"MX",
    "name:spa_x_preferred":[
        "El Dormido"
    ],
    "wof:name":"El Dormido",
    "wof:placetype":"locality"
},
  "geometry": {"coordinates":[-101.34468,24.0014],"type":"Point"}
}