{
  "type": "Feature",
  "properties": {
    "gn:admin1_code":"11",
    "gn:admin2_code":"20.0",
    "gn:asciiname":"Granja de Francisco Munoz",
    "gn:country_code":"MX",
    "gn:dem":1773,
    "gn:feature_class":"P",
    "gn:feature_code":"PPL",
    "gn:name":"Granja de Francisco Mu\u00f1oz",
    "gn:population":5,
    "gn:timezone":"America/Mexico_City",
    "iso:country":"MX",
    "name:und_x_variant":[
        "Granja de Francisco Mu\u00f1oz"
    ],
    "wof:name":"Granja de Francisco Munoz",
    "wof:placetype":"locality",
    "wof:population":5
},
  "geometry": {"coordinates":[-101.71917000000001,21.04389],"type":"Point"}
}