{
  "type": "Feature",
  "properties": {
    "gn:admin1_code":"25",
    "gn:admin2_code":"18.0",
    "gn:asciiname":"La Escobera",
    "gn:country_code":"MX",
    "gn:dem":15,
    "gn:feature_class":"P",
    "gn:feature_code":"PPL",
    "gn:name":"La Escobera",
    "gn:population":0,
    "gn:timezone":"America/Mazatlan",
    "iso:country":"MX",
    "name:spa_x_preferred":[
        "La Escobera"
    ],
    "wof:name":"La Escobera",
    "wof:placetype":"locality"
},
  "geometry": {"coordinates":[-107.72123999999999,24.76088],"type":"Point"}
}