{
  "type": "Feature",
  "properties": {
    "gn:admin1_code":"30.0",
    "gn:admin2_code":"123.0",
    "gn:asciiname":"El Chiflido",
    "gn:country_code":"MX",
    "gn:dem":19,
    "gn:feature_class":"P",
    "gn:feature_code":"PPL",
    "gn:name":"El Chiflido",
    "gn:population":2,
    "gn:timezone":"America/Mexico_City",
    "iso:country":"MX",
    "name:spa_x_preferred":[
        "El Chiflido"
    ],
    "wof:name":"El Chiflido",
    "wof:placetype":"locality",
    "wof:population":2
},
  "geometry": {"coordinates":[-98.27167,22.15361],"type":"Point"}
}