{
  "type": "Feature",
  "properties": {
    "gn:admin1_code":"18.0",
    "gn:admin2_code":"19.0",
    "gn:asciiname":"Arroyo de la Cueva",
    "gn:country_code":"MX",
    "gn:dem":1755,
    "gn:feature_class":"P",
    "gn:feature_code":"PPL",
    "gn:name":"Arroyo de la Cueva",
    "gn:population":0,
    "gn:timezone":"America/Mazatlan",
    "iso:country":"MX",
    "name:spa_x_preferred":[
        "Arroyo de la Cueva"
    ],
    "wof:name":"Arroyo de la Cueva",
    "wof:placetype":"locality"
},
  "geometry": {"coordinates":[-104.07968,21.37669],"type":"Point"}
}