{
  "type": "Feature",
  "properties": {
    "gn:admin1_code":"5",
    "gn:admin2_code":"51",
    "gn:asciiname":"Consejo Nacional de Fruticultura",
    "gn:country_code":"MX",
    "gn:dem":15,
    "gn:feature_class":"P",
    "gn:feature_code":"PPL",
    "gn:name":"Consejo Nacional de Fruticultura",
    "gn:population":25,
    "gn:timezone":"America/Mexico_City",
    "iso:country":"MX",
    "wof:name":"Consejo Nacional de Fruticultura",
    "wof:placetype":"locality",
    "wof:population":25
},
  "geometry": {"coordinates":[-92.87778,15.35],"type":"Point"}
}