{
  "type": "Feature",
  "properties": {
    "gn:admin1_code":"26",
    "gn:admin2_code":"18",
    "gn:asciiname":"Rosendo Portillo",
    "gn:country_code":"MX",
    "gn:dem":33,
    "gn:feature_class":"P",
    "gn:feature_code":"PPL",
    "gn:name":"Rosendo Portillo",
    "gn:population":16,
    "gn:timezone":"America/Hermosillo",
    "iso:country":"MX",
    "wof:name":"Rosendo Portillo",
    "wof:placetype":"locality",
    "wof:population":16
},
  "geometry": {"coordinates":[-109.93416999999999,27.33056],"type":"Point"}
}