{
  "type": "Feature",
  "properties": {
    "gn:admin1_code":"20",
    "gn:admin2_code":"66.0",
    "gn:asciiname":"El Zopilote",
    "gn:country_code":"MX",
    "gn:dem":28,
    "gn:feature_class":"P",
    "gn:feature_code":"PPL",
    "gn:name":"El Zopilote",
    "gn:population":0,
    "gn:timezone":"America/Mexico_City",
    "iso:country":"MX",
    "name:und_x_variant":[
        "TeotepecTeotepecTeotepec",
        "Teotepec"
    ],
    "wof:name":"El Zopilote",
    "wof:placetype":"locality"
},
  "geometry": {"coordinates":[-94.49055,16.46805],"type":"Point"}
}