{
  "type": "Feature",
  "properties": {
    "gn:admin1_code":"30",
    "gn:admin2_code":"25.0",
    "gn:asciiname":"Avaleta",
    "gn:country_code":"MX",
    "gn:dem":1325,
    "gn:feature_class":"P",
    "gn:feature_code":"PPL",
    "gn:name":"Avaleta",
    "gn:population":0,
    "gn:timezone":"America/Mexico_City",
    "iso:country":"MX",
    "name:spa_x_preferred":[
        "Avaleta"
    ],
    "wof:name":"Avaleta",
    "wof:placetype":"locality"
},
  "geometry": {"coordinates":[-97.01236,19.37751],"type":"Point"}
}