{
  "type": "Feature",
  "properties": {
    "gn:admin1_code":"3",
    "gn:admin2_code":"1.0",
    "gn:asciiname":"El Dulce",
    "gn:country_code":"MX",
    "gn:dem":313,
    "gn:feature_class":"P",
    "gn:feature_code":"PPL",
    "gn:name":"El Dulce",
    "gn:population":4,
    "gn:timezone":"America/Mazatlan",
    "iso:country":"MX",
    "wof:name":"El Dulce",
    "wof:placetype":"locality",
    "wof:population":4
},
  "geometry": {"coordinates":[-111.14058,25.32284],"type":"Point"}
}