{
  "type": "Feature",
  "properties": {
    "gn:admin1_code":"20",
    "gn:admin2_code":"537",
    "gn:asciiname":"Barrio de la Providencia",
    "gn:country_code":"MX",
    "gn:dem":1844,
    "gn:feature_class":"P",
    "gn:feature_code":"PPL",
    "gn:name":"Barrio de la Providencia",
    "gn:population":42,
    "gn:timezone":"America/Mexico_City",
    "iso:country":"MX",
    "wof:name":"Barrio de la Providencia",
    "wof:placetype":"locality",
    "wof:population":42
},
  "geometry": {"coordinates":[-98.14610999999999,17.53944],"type":"Point"}
}