{
  "type": "Feature",
  "properties": {
    "gn:admin1_code":"13",
    "gn:admin2_code":"49.0",
    "gn:asciiname":"Plan de Ayala",
    "gn:country_code":"MX",
    "gn:dem":243,
    "gn:feature_class":"P",
    "gn:feature_code":"PPL",
    "gn:name":"Plan de Ayala",
    "gn:population":198,
    "gn:timezone":"America/Mexico_City",
    "iso:country":"MX",
    "wof:name":"Plan de Ayala",
    "wof:placetype":"locality",
    "wof:population":198
},
  "geometry": {"coordinates":[-98.98721999999999,21.18167],"type":"Point"}
}