{
  "type": "Feature",
  "properties": {
    "gn:admin1_code":"30",
    "gn:admin2_code":"124",
    "gn:asciiname":"Ampliacion Antonio M. Quirazco",
    "gn:country_code":"MX",
    "gn:dem":189,
    "gn:feature_class":"P",
    "gn:feature_code":"PPL",
    "gn:name":"Ampliaci\u00f3n Antonio M. Quirazco",
    "gn:population":34,
    "gn:timezone":"America/Mexico_City",
    "iso:country":"MX",
    "name:und_x_variant":[
        "Ampliaci\u00f3n Antonio M. Quirazco"
    ],
    "wof:name":"Ampliacion Antonio M. Quirazco",
    "wof:placetype":"locality",
    "wof:population":34
},
  "geometry": {"coordinates":[-97.31305999999999,20.43389],"type":"Point"}
}