{
  "type": "Feature",
  "properties": {
    "gn:admin1_code":"21",
    "gn:admin2_code":"82.0",
    "gn:asciiname":"San Juan Nepomuceno (Rancho Chico)",
    "gn:country_code":"MX",
    "gn:dem":1874,
    "gn:feature_class":"P",
    "gn:feature_code":"PPL",
    "gn:name":"San Juan Nepomuceno (Rancho Chico)",
    "gn:population":449,
    "gn:timezone":"America/Mexico_City",
    "iso:country":"MX",
    "wof:name":"San Juan Nepomuceno (Rancho Chico)",
    "wof:placetype":"locality",
    "wof:population":449
},
  "geometry": {"coordinates":[-97.85417,18.4875],"type":"Point"}
}