{
  "type": "Feature",
  "properties": {
    "gn:admin1_code":"30.0",
    "gn:admin2_code":"155.0",
    "gn:asciiname":"El Manantial",
    "gn:country_code":"MX",
    "gn:dem":161,
    "gn:feature_class":"P",
    "gn:feature_code":"PPL",
    "gn:name":"El Manantial",
    "gn:population":132,
    "gn:timezone":"America/Mexico_City",
    "iso:country":"MX",
    "name:bul_x_preferred":[
        "\u0418\u0437\u0432\u043e\u0440\u044a\u0442"
    ],
    "name:cat_x_preferred":[
        "El manantial"
    ],
    "name:epo_x_preferred":[
        "El manantial"
    ],
    "name:fra_x_preferred":[
        "El manantial"
    ],
    "name:hat_x_preferred":[
        "El Manantial"
    ],
    "name:hun_x_preferred":[
        "Az \u0151sforr\u00e1s"
    ],
    "name:mkd_x_preferred":[
        "\u0418\u0437\u0432\u043e\u0440"
    ],
    "name:por_x_preferred":[
        "El manantial"
    ],
    "name:ron_x_preferred":[
        "Taina din ad\u00e2ncuri"
    ],
    "name:spa_x_preferred":[
        "El Manantial"
    ],
    "name:sqi_x_preferred":[
        "El manantial"
    ],
    "name:srp_x_preferred":[
        "\u0418\u0437\u0432\u043e\u0440"
    ],
    "name:tgl_x_preferred":[
        "El Manantial"
    ],
    "wof:name":"El Manantial",
    "wof:placetype":"locality",
    "wof:population":132
},
  "geometry": {"coordinates":[-98.15722,21.37333],"type":"Point"}
}