{
  "type": "Feature",
  "properties": {
    "gn:admin1_code":"16",
    "gn:admin2_code":"80.0",
    "gn:asciiname":"Ex-Hacienda de Soto",
    "gn:country_code":"MX",
    "gn:dem":2198,
    "gn:feature_class":"P",
    "gn:feature_code":"PPL",
    "gn:name":"Ex-Hacienda de Soto",
    "gn:population":64,
    "gn:timezone":"America/Mexico_City",
    "iso:country":"MX",
    "wof:name":"Ex-Hacienda de Soto",
    "wof:placetype":"locality",
    "wof:population":64
},
  "geometry": {"coordinates":[-100.34444000000001,19.78139],"type":"Point"}
}