{
  "type": "Feature",
  "properties": {
    "gn:admin1_code":"5",
    "gn:admin2_code":"96.0",
    "gn:asciiname":"La Preciosa",
    "gn:country_code":"MX",
    "gn:dem":613,
    "gn:feature_class":"P",
    "gn:feature_code":"PPL",
    "gn:name":"La Preciosa",
    "gn:population":112,
    "gn:timezone":"America/Mexico_City",
    "iso:country":"MX",
    "wof:name":"La Preciosa",
    "wof:placetype":"locality",
    "wof:population":112
},
  "geometry": {"coordinates":[-92.53917,17.29833],"type":"Point"}
}