{
  "type": "Feature",
  "properties": {
    "gn:admin1_code":"26",
    "gn:admin2_code":"58.0",
    "gn:asciiname":"La Polvareda",
    "gn:country_code":"MX",
    "gn:dem":711,
    "gn:feature_class":"P",
    "gn:feature_code":"PPL",
    "gn:name":"La Polvareda",
    "gn:population":0,
    "gn:timezone":"America/Hermosillo",
    "iso:country":"MX",
    "name:spa_x_preferred":[
        "La Polvareda"
    ],
    "name:und_x_variant":[
        "Polvareda",
        "La Palvadera",
        "La Polvadera"
    ],
    "wof:name":"La Polvareda",
    "wof:placetype":"locality"
},
  "geometry": {"coordinates":[-111.16122,30.65452],"type":"Point"}
}