{
  "type": "Feature",
  "properties": {
    "gn:admin1_code":"3",
    "gn:admin2_code":"8",
    "gn:asciiname":"El Corral de Piedra",
    "gn:country_code":"MX",
    "gn:dem":279,
    "gn:feature_class":"P",
    "gn:feature_code":"PPL",
    "gn:name":"El Corral de Piedra",
    "gn:population":12,
    "gn:timezone":"America/Mazatlan",
    "iso:country":"MX",
    "wof:name":"El Corral de Piedra",
    "wof:placetype":"locality",
    "wof:population":12
},
  "geometry": {"coordinates":[-109.9162,22.99028],"type":"Point"}
}