{
  "type": "Feature",
  "properties": {
    "gn:admin1_code":"5",
    "gn:admin2_code":"4.0",
    "gn:asciiname":"7 de Enero",
    "gn:country_code":"MX",
    "gn:dem":979,
    "gn:feature_class":"P",
    "gn:feature_code":"PPL",
    "gn:name":"7 de Enero",
    "gn:population":93,
    "gn:timezone":"America/Mexico_City",
    "iso:country":"MX",
    "wof:name":"7 de Enero",
    "wof:placetype":"locality",
    "wof:population":93
},
  "geometry": {"coordinates":[-91.90167,16.70833],"type":"Point"}
}