{
  "type": "Feature",
  "properties": {
    "gn:admin1_code":"12",
    "gn:admin2_code":"12.0",
    "gn:asciiname":"El Pinal",
    "gn:country_code":"MX",
    "gn:dem":686,
    "gn:feature_class":"P",
    "gn:feature_code":"PPL",
    "gn:name":"El Pi\u00f1al",
    "gn:population":130,
    "gn:timezone":"America/Mexico_City",
    "iso:country":"MX",
    "name:und_x_variant":[
        "El Pi\u00f1al"
    ],
    "wof:name":"El Pinal",
    "wof:placetype":"locality",
    "wof:population":130
},
  "geometry": {"coordinates":[-99.04055,16.95229],"type":"Point"}
}