{
  "type": "Feature",
  "properties": {
    "gn:admin1_code":"18.0",
    "gn:asciiname":"Banco de Palomas",
    "gn:country_code":"MX",
    "gn:dem":1301,
    "gn:feature_class":"P",
    "gn:feature_code":"PPL",
    "gn:name":"Banco de Palomas",
    "gn:population":0,
    "gn:timezone":"America/Mazatlan",
    "iso:country":"MX",
    "name:spa_x_preferred":[
        "Banco de Palomas"
    ],
    "wof:name":"Banco de Palomas",
    "wof:placetype":"locality"
},
  "geometry": {"coordinates":[-104.46393,21.69923],"type":"Point"}
}