{
  "type": "Feature",
  "properties": {
    "gn:admin1_code":"30",
    "gn:admin2_code":"121",
    "gn:asciiname":"La Reforma Tres",
    "gn:country_code":"MX",
    "gn:dem":11,
    "gn:feature_class":"P",
    "gn:feature_code":"PPL",
    "gn:name":"La Reforma Tres",
    "gn:population":11,
    "gn:timezone":"America/Mexico_City",
    "iso:country":"MX",
    "wof:name":"La Reforma Tres",
    "wof:placetype":"locality",
    "wof:population":11
},
  "geometry": {"coordinates":[-97.7475,21.58417],"type":"Point"}
}