{
  "type": "Feature",
  "properties": {
    "gn:admin1_code":"16",
    "gn:admin2_code":"112.0",
    "gn:asciiname":"Toma de Agua",
    "gn:country_code":"MX",
    "gn:dem":2337,
    "gn:feature_class":"P",
    "gn:feature_code":"PPL",
    "gn:name":"Toma de Agua",
    "gn:population":795,
    "gn:timezone":"America/Mexico_City",
    "iso:country":"MX",
    "wof:name":"Toma de Agua",
    "wof:placetype":"locality",
    "wof:population":795
},
  "geometry": {"coordinates":[-100.29056,19.43056],"type":"Point"}
}