{
  "type": "Feature",
  "properties": {
    "gn:admin1_code":"14.0",
    "gn:admin2_code":"35.0",
    "gn:asciiname":"El Pozo de Cuatro Vientos",
    "gn:country_code":"MX",
    "gn:dem":1995,
    "gn:feature_class":"P",
    "gn:feature_code":"PPL",
    "gn:name":"El Pozo de Cuatro Vientos",
    "gn:population":0,
    "gn:timezone":"America/Mexico_City",
    "iso:country":"MX",
    "name:spa_x_preferred":[
        "El Pozo de Cuatro Vientos"
    ],
    "wof:name":"El Pozo de Cuatro Vientos",
    "wof:placetype":"locality"
},
  "geometry": {"coordinates":[-102.10816,21.70778],"type":"Point"}
}