{
  "type": "Feature",
  "properties": {
    "gn:admin1_code":"15",
    "gn:admin2_code":"42.0",
    "gn:asciiname":"Colonia Luis Donaldo Colosio",
    "gn:country_code":"MX",
    "gn:dem":2533,
    "gn:feature_class":"P",
    "gn:feature_code":"PPL",
    "gn:name":"Colonia Luis Donaldo Colosio",
    "gn:population":189,
    "gn:timezone":"America/Mexico_City",
    "iso:country":"MX",
    "wof:name":"Colonia Luis Donaldo Colosio",
    "wof:placetype":"locality",
    "wof:population":189
},
  "geometry": {"coordinates":[-99.73166999999999,19.59778],"type":"Point"}
}