{
  "type": "Feature",
  "properties": {
    "gn:admin1_code":"26",
    "gn:admin2_code":"37.0",
    "gn:asciiname":"La Junta de Arriba",
    "gn:country_code":"MX",
    "gn:dem":491,
    "gn:feature_class":"P",
    "gn:feature_code":"PPL",
    "gn:name":"La Junta de Arriba",
    "gn:population":1,
    "gn:timezone":"America/Hermosillo",
    "iso:country":"MX",
    "name:spa_x_preferred":[
        "La Junta de Arriba"
    ],
    "wof:name":"La Junta de Arriba",
    "wof:placetype":"locality",
    "wof:population":1
},
  "geometry": {"coordinates":[-110.18194,28.93667],"type":"Point"}
}