{
  "type": "Feature",
  "properties": {
    "gn:admin1_code":"24",
    "gn:admin2_code":"39.0",
    "gn:asciiname":"Tut Tzen (Tiutzen)",
    "gn:country_code":"MX",
    "gn:dem":317,
    "gn:feature_class":"P",
    "gn:feature_code":"PPL",
    "gn:name":"Tut Tzen (Tiutz\u00e9n)",
    "gn:population":257,
    "gn:timezone":"America/Mexico_City",
    "iso:country":"MX",
    "name:und_x_variant":[
        "Tut Tzen (Tiutz\u00e9n)"
    ],
    "wof:name":"Tut Tzen (Tiutzen)",
    "wof:placetype":"locality",
    "wof:population":257
},
  "geometry": {"coordinates":[-98.83638999999999,21.60083],"type":"Point"}
}