{
  "type": "Feature",
  "properties": {
    "gn:admin1_code":"2.0",
    "gn:admin2_code":"3.0",
    "gn:asciiname":"El Pedregal",
    "gn:country_code":"MX",
    "gn:dem":584,
    "gn:feature_class":"P",
    "gn:feature_code":"PPL",
    "gn:name":"El Pedregal",
    "gn:population":4,
    "gn:timezone":"America/Tijuana",
    "iso:country":"MX",
    "name:spa_x_preferred":[
        "El Pedregal"
    ],
    "wof:name":"El Pedregal",
    "wof:placetype":"locality",
    "wof:population":4
},
  "geometry": {"coordinates":[-116.63139,32.53444],"type":"Point"}
}