{
  "type": "Feature",
  "properties": {
    "gn:country":"MX",
    "gn:fcode":"PPL",
    "gn:population":47321,
    "iso:country":"MX",
    "name:und_x_variant":[
        "San Luis de la Paz"
    ],
    "qs_pg:aaroncc":"MX",
    "qs_pg:gn_country":"MX",
    "qs_pg:gn_fcode":"PPL",
    "qs_pg:gn_pop":47321,
    "qs_pg:name":"San Luis de la Paz Centro",
    "qs_pg:name_adm0":"M\u00e9xico",
    "qs_pg:name_adm1":"Guanajuato",
    "qs_pg:photos":1,
    "qs_pg:photos_1k":1,
    "qs_pg:photos_9k":1,
    "qs_pg:photos_9r":1,
    "qs_pg:photos_all":1,
    "qs_pg:photos_sr":1,
    "qs_pg:pop_sr":7,
    "qs_pg:qs_pg_placetype":"neighbourhood",
    "qs_pg:qs_pg_placetype_gp":"Suburb",
    "qs_pg:woe_adm0":23424900,
    "woe:adm0_id":23424900,
    "woe:name_adm0":"M\u00e9xico",
    "woe:name_adm1":"Guanajuato",
    "woe:placetype":"Suburb",
    "wof:name":"San Luis de la Paz Centro",
    "wof:placetype":"neighbourhood",
    "wof:population":47321
},
  "geometry": {"coordinates":[-100.51676,21.29787],"type":"Point"}
}