{
  "type": "Feature",
  "properties": {
    "gn:admin1_code":"6.0",
    "gn:admin2_code":"52.0",
    "gn:asciiname":"El Chupadero",
    "gn:country_code":"MX",
    "gn:dem":1606,
    "gn:feature_class":"P",
    "gn:feature_code":"PPL",
    "gn:name":"El Chupadero",
    "gn:population":2,
    "gn:timezone":"America/Chihuahua",
    "iso:country":"MX",
    "name:spa_x_preferred":[
        "El Chupadero"
    ],
    "name:und_x_variant":[
        "Rancho El Chupadero",
        "Chupadero"
    ],
    "wof:name":"El Chupadero",
    "wof:placetype":"locality",
    "wof:population":2
},
  "geometry": {"coordinates":[-104.24562,28.87206],"type":"Point"}
}