{
  "type": "Feature",
  "properties": {
    "gn:admin1_code":"5.0",
    "gn:admin2_code":"52.0",
    "gn:asciiname":"La Cumbres",
    "gn:country_code":"MX",
    "gn:dem":1105,
    "gn:feature_class":"P",
    "gn:feature_code":"PPL",
    "gn:name":"La Cumbres",
    "gn:population":0,
    "gn:timezone":"America/Mexico_City",
    "iso:country":"MX",
    "name:spa_x_preferred":[
        "La Cumbres"
    ],
    "wof:name":"La Cumbres",
    "wof:placetype":"locality"
},
  "geometry": {"coordinates":[-91.66518000000001,16.34642],"type":"Point"}
}