{
  "type": "Feature",
  "properties": {
    "gn:admin1_code":"6.0",
    "gn:admin2_code":"27.0",
    "gn:asciiname":"El Fortin",
    "gn:cc2":"MX",
    "gn:country_code":"MX",
    "gn:dem":1990,
    "gn:feature_class":"P",
    "gn:feature_code":"PPL",
    "gn:name":"El Fort\u00edn",
    "gn:population":0,
    "gn:timezone":"America/Chihuahua",
    "iso:country":"MX",
    "name:und_x_variant":[
        "Fortin",
        "El Fort\u00edn"
    ],
    "wof:name":"El Fortin",
    "wof:placetype":"locality"
},
  "geometry": {"coordinates":[-107.11667,27.56667],"type":"Point"}
}