{
  "type": "Feature",
  "properties": {
    "gn:admin1_code":"5",
    "gn:admin2_code":"40.0",
    "gn:asciiname":"Canton las Lechugas 2",
    "gn:country_code":"MX",
    "gn:dem":27,
    "gn:feature_class":"P",
    "gn:feature_code":"PPL",
    "gn:name":"Cant\u00f3n las Lechugas 2",
    "gn:population":284,
    "gn:timezone":"America/Mexico_City",
    "iso:country":"MX",
    "name:und_x_variant":[
        "Cant\u00f3n las Lechugas 2"
    ],
    "wof:name":"Canton las Lechugas 2",
    "wof:placetype":"locality",
    "wof:population":284
},
  "geometry": {"coordinates":[-92.48444000000001,15.08556],"type":"Point"}
}