{
  "type": "Feature",
  "properties": {
    "gn:admin1_code":"6",
    "gn:admin2_code":"29.0",
    "gn:asciiname":"El Ocote",
    "gn:country_code":"MX",
    "gn:dem":2718,
    "gn:feature_class":"P",
    "gn:feature_code":"PPL",
    "gn:name":"El Ocote",
    "gn:population":173,
    "gn:timezone":"America/Chihuahua",
    "iso:country":"MX",
    "wof:name":"El Ocote",
    "wof:placetype":"locality",
    "wof:population":173
},
  "geometry": {"coordinates":[-106.78694,26.06778],"type":"Point"}
}