{
  "type": "Feature",
  "properties": {
    "gn:admin1_code":"16",
    "gn:admin2_code":"8",
    "gn:asciiname":"La Hujera",
    "gn:country_code":"MX",
    "gn:dem":307,
    "gn:feature_class":"P",
    "gn:feature_code":"PPL",
    "gn:name":"La Hujera",
    "gn:population":18,
    "gn:timezone":"America/Mexico_City",
    "iso:country":"MX",
    "wof:name":"La Hujera",
    "wof:placetype":"locality",
    "wof:population":18
},
  "geometry": {"coordinates":[-102.82194,18.17556],"type":"Point"}
}