{
  "type": "Feature",
  "properties": {
    "gn:admin1_code":"24.0",
    "gn:admin2_code":"16.0",
    "gn:asciiname":"El Cucucito",
    "gn:country_code":"MX",
    "gn:dem":20,
    "gn:feature_class":"P",
    "gn:feature_code":"PPL",
    "gn:name":"El Cucucito",
    "gn:population":0,
    "gn:timezone":"America/Mexico_City",
    "iso:country":"MX",
    "name:spa_x_preferred":[
        "El Cucucito"
    ],
    "wof:name":"El Cucucito",
    "wof:placetype":"locality"
},
  "geometry": {"coordinates":[-98.55264,21.97402],"type":"Point"}
}