{
  "type": "Feature",
  "properties": {
    "gn:admin1_code":"5",
    "gn:admin2_code":"71",
    "gn:asciiname":"San Pablo",
    "gn:country_code":"MX",
    "gn:dem":383,
    "gn:feature_class":"P",
    "gn:feature_code":"PPL",
    "gn:name":"San Pablo",
    "gn:population":19,
    "gn:timezone":"America/Mexico_City",
    "iso:country":"MX",
    "name:bre_x_preferred":[
        "San Pablo"
    ],
    "name:cat_x_preferred":[
        "San Pablo"
    ],
    "name:ceb_x_preferred":[
        "San Pablo"
    ],
    "name:ces_x_preferred":[
        "San Pablo"
    ],
    "name:deu_x_preferred":[
        "San Pablo"
    ],
    "name:fas_x_preferred":[
        "\u0633\u0627\u0646 \u067e\u0627\u0628\u0644\u0648"
    ],
    "name:fra_x_preferred":[
        "San Pablo"
    ],
    "name:ilo_x_preferred":[
        "San Pablo"
    ],
    "name:ita_x_preferred":[
        "San Pablo"
    ],
    "name:jpn_x_preferred":[
        "\u30b5\u30f3\u30fb\u30d1\u30d6\u30ed"
    ],
    "name:kor_x_preferred":[
        "\uc0b0\ud30c\ube14\ub85c"
    ],
    "name:nds_x_preferred":[
        "San Pablo"
    ],
    "name:nld_x_preferred":[
        "San Pablo"
    ],
    "name:pol_x_preferred":[
        "San Pablo"
    ],
    "name:por_x_preferred":[
        "San Pablo"
    ],
    "name:que_x_preferred":[
        "San Pawlu"
    ],
    "name:rus_x_preferred":[
        "\u0421\u0430\u043d-\u041f\u0430\u0431\u043b\u043e"
    ],
    "name:sco_x_preferred":[
        "San Pablo"
    ],
    "name:spa_x_preferred":[
        "San Pablo"
    ],
    "name:srp_x_preferred":[
        "\u0421\u0430\u043d \u041f\u0430\u0431\u043b\u043e"
    ],
    "name:swe_x_preferred":[
        "San Pablo"
    ],
    "name:tgl_x_preferred":[
        "San Pablo"
    ],
    "name:vol_x_preferred":[
        "San Pablo"
    ],
    "name:war_x_preferred":[
        "San Pablo"
    ],
    "wof:name":"San Pablo",
    "wof:placetype":"locality",
    "wof:population":19
},
  "geometry": {"coordinates":[-92.51581,15.24788],"type":"Point"}
}