{
  "type": "Feature",
  "properties": {
    "gn:admin1_code":"5",
    "gn:admin2_code":"71",
    "gn:asciiname":"San Pablo",
    "gn:country_code":"MX",
    "gn:dem":383,
    "gn:feature_class":"P",
    "gn:feature_code":"PPL",
    "gn:name":"San Pablo",
    "gn:population":19,
    "gn:timezone":"America/Mexico_City",
    "iso:country":"MX",
    "wof:name":"San Pablo",
    "wof:placetype":"locality",
    "wof:population":19
},
  "geometry": {"coordinates":[-92.51581,15.24788],"type":"Point"}
}