{
  "type": "Feature",
  "properties": {
    "gn:admin1_code":"15",
    "gn:admin2_code":"99",
    "gn:asciiname":"Rancho el Barco",
    "gn:country_code":"MX",
    "gn:dem":2236,
    "gn:feature_class":"P",
    "gn:feature_code":"PPL",
    "gn:name":"Rancho el Barco",
    "gn:population":29,
    "gn:timezone":"America/Mexico_City",
    "iso:country":"MX",
    "wof:name":"Rancho el Barco",
    "wof:placetype":"locality",
    "wof:population":29
},
  "geometry": {"coordinates":[-98.93527,19.4951],"type":"Point"}
}