{
  "type": "Feature",
  "properties": {
    "gn:admin1_code":"15",
    "gn:admin2_code":"93",
    "gn:asciiname":"Rancho Chiconcuajio",
    "gn:country_code":"MX",
    "gn:dem":2734,
    "gn:feature_class":"P",
    "gn:feature_code":"PPL",
    "gn:name":"Rancho Chiconcuajio",
    "gn:population":11,
    "gn:timezone":"America/Mexico_City",
    "iso:country":"MX",
    "wof:name":"Rancho Chiconcuajio",
    "wof:placetype":"locality",
    "wof:population":11
},
  "geometry": {"coordinates":[-98.76182,19.53489],"type":"Point"}
}