{
  "type": "Feature",
  "properties": {
    "gn:admin1_code":"19",
    "gn:admin2_code":"17.0",
    "gn:asciiname":"San Isidro de Cienega del Toro",
    "gn:country_code":"MX",
    "gn:dem":2203,
    "gn:feature_class":"P",
    "gn:feature_code":"PPL",
    "gn:name":"San Isidro de Ci\u00e9nega del Toro",
    "gn:population":0,
    "gn:timezone":"America/Monterrey",
    "iso:country":"MX",
    "name:spa_x_preferred":[
        "San Isidro de Ci\u00e9nega del Toro"
    ],
    "name:spa_x_variant":[
        "San Isidro de Ci\u00e9nega"
    ],
    "name:und_x_variant":[
        "Hacienda San Isidro"
    ],
    "wof:name":"San Isidro de Cienega del Toro",
    "wof:placetype":"locality"
},
  "geometry": {"coordinates":[-100.50976,25.20172],"type":"Point"}
}