{
  "type": "Feature",
  "properties": {
    "gn:admin1_code":"12",
    "gn:admin2_code":"53.0",
    "gn:asciiname":"Palomar de las Flores",
    "gn:country_code":"MX",
    "gn:dem":18,
    "gn:feature_class":"P",
    "gn:feature_code":"PPL",
    "gn:name":"Palomar de las Flores",
    "gn:population":239,
    "gn:timezone":"America/Mexico_City",
    "iso:country":"MX",
    "wof:name":"Palomar de las Flores",
    "wof:placetype":"locality",
    "wof:population":239
},
  "geometry": {"coordinates":[-99.25972,16.72028],"type":"Point"}
}