{
  "type": "Feature",
  "properties": {
    "gn:admin1_code":"16",
    "gn:admin2_code":"69.0",
    "gn:asciiname":"Las Barranquillas",
    "gn:country_code":"MX",
    "gn:dem":1683,
    "gn:feature_class":"P",
    "gn:feature_code":"PPL",
    "gn:name":"Las Barranquillas",
    "gn:population":64,
    "gn:timezone":"America/Mexico_City",
    "iso:country":"MX",
    "wof:name":"Las Barranquillas",
    "wof:placetype":"locality",
    "wof:population":64
},
  "geometry": {"coordinates":[-102.00444,20.3175],"type":"Point"}
}