{
  "type": "Feature",
  "properties": {
    "gn:admin1_code":"6",
    "gn:admin2_code":"29.0",
    "gn:asciiname":"Rancho Prieto",
    "gn:country_code":"MX",
    "gn:dem":2395,
    "gn:feature_class":"P",
    "gn:feature_code":"PPL",
    "gn:name":"Rancho Prieto",
    "gn:population":5,
    "gn:timezone":"America/Chihuahua",
    "iso:country":"MX",
    "wof:name":"Rancho Prieto",
    "wof:placetype":"locality",
    "wof:population":5
},
  "geometry": {"coordinates":[-106.89207,26.03079],"type":"Point"}
}