{
  "type": "Feature",
  "properties": {
    "gn:admin1_code":"10",
    "gn:admin2_code":"34",
    "gn:asciiname":"El Picacho",
    "gn:country_code":"MX",
    "gn:dem":898,
    "gn:feature_class":"P",
    "gn:feature_code":"PPL",
    "gn:name":"El Picacho",
    "gn:population":10,
    "gn:timezone":"America/Monterrey",
    "iso:country":"MX",
    "name:ceb_x_preferred":[
        "El Picacho"
    ],
    "name:spa_x_preferred":[
        "El Picacho"
    ],
    "name:swe_x_preferred":[
        "El Picacho"
    ],
    "wof:name":"El Picacho",
    "wof:placetype":"locality",
    "wof:population":10
},
  "geometry": {"coordinates":[-106.51785,24.80415],"type":"Point"}
}