{
  "type": "Feature",
  "properties": {
    "gn:admin1_code":"26.0",
    "gn:admin2_code":"12.0",
    "gn:asciiname":"Campo Ochenta",
    "gn:country_code":"MX",
    "gn:dem":18,
    "gn:feature_class":"P",
    "gn:feature_code":"PPL",
    "gn:name":"Campo Ochenta",
    "gn:population":0,
    "gn:timezone":"America/Hermosillo",
    "iso:country":"MX",
    "wof:name":"Campo Ochenta",
    "wof:placetype":"locality"
},
  "geometry": {"coordinates":[-110.11667,27.43333],"type":"Point"}
}