{
  "type": "Feature",
  "properties": {
    "gn:admin1_code":"14",
    "gn:admin2_code":"43.0",
    "gn:asciiname":"Las Piedras de Amolar",
    "gn:country_code":"MX",
    "gn:dem":56,
    "gn:feature_class":"P",
    "gn:feature_code":"PPL",
    "gn:name":"Las Piedras de Amolar",
    "gn:population":9,
    "gn:timezone":"America/Mexico_City",
    "iso:country":"MX",
    "wof:name":"Las Piedras de Amolar",
    "wof:placetype":"locality",
    "wof:population":9
},
  "geometry": {"coordinates":[-105.09166999999999,19.72806],"type":"Point"}
}