{
  "type": "Feature",
  "properties": {
    "gn:admin1_code":"27",
    "gn:admin2_code":"17.0",
    "gn:asciiname":"La Engorda",
    "gn:country_code":"MX",
    "gn:dem":63,
    "gn:feature_class":"P",
    "gn:feature_code":"PPL",
    "gn:name":"La Engorda",
    "gn:population":5,
    "gn:timezone":"America/Mexico_City",
    "iso:country":"MX",
    "name:spa_x_preferred":[
        "La Engorda"
    ],
    "wof:name":"La Engorda",
    "wof:placetype":"locality",
    "wof:population":5
},
  "geometry": {"coordinates":[-91.33759999999999,17.47664],"type":"Point"}
}