{
  "type": "Feature",
  "properties": {
    "gn:admin1_code":"20",
    "gn:admin2_code":"342",
    "gn:asciiname":"Paraje Saucipres",
    "gn:country_code":"MX",
    "gn:dem":1538,
    "gn:feature_class":"P",
    "gn:feature_code":"PPL",
    "gn:name":"Paraje Saucipres",
    "gn:population":41,
    "gn:timezone":"America/Mexico_City",
    "iso:country":"MX",
    "wof:name":"Paraje Saucipres",
    "wof:placetype":"locality",
    "wof:population":41
},
  "geometry": {"coordinates":[-96.76000000000001,16.99611],"type":"Point"}
}