{
  "type": "Feature",
  "properties": {
    "gn:admin1_code":"14",
    "gn:admin2_code":"58.0",
    "gn:asciiname":"San Carlos",
    "gn:country_code":"MX",
    "gn:dem":1474,
    "gn:feature_class":"P",
    "gn:feature_code":"PPL",
    "gn:name":"San Carlos",
    "gn:population":5,
    "gn:timezone":"America/Mexico_City",
    "iso:country":"MX",
    "wof:name":"San Carlos",
    "wof:placetype":"locality",
    "wof:population":5
},
  "geometry": {"coordinates":[-104.71222,20.37111],"type":"Point"}
}