{
  "type": "Feature",
  "properties": {
    "iso:country":"MX",
    "name:spa_x_preferred":[
        "Molino de Parras"
    ],
    "name:unk_x_variant":[
        "Molino de Parras"
    ],
    "qs:gn_adm0_cc":"MX",
    "qs:gn_local":3995402,
    "qs:gn_nam_loc":"Morelia, Morelia, Michoacan de Ocampo, MX",
    "qs:gn_namadm1":"16",
    "qs:local_max":1391,
    "qs:local_sum":3298,
    "qs:localhoods":8,
    "qs:name":"Molino de Parras",
    "qs:name_adm0":"M\u00e9xico",
    "qs:name_adm1":"Michoacan de Ocampo",
    "qs:name_adm2":"Morelia",
    "qs:name_local":"Morelia",
    "qs:photo_max":31,
    "qs:photo_sum":31,
    "qs:placetype":"Suburb",
    "qs:quad_count":1,
    "qs:woe_adm0":23424900,
    "qs:woe_adm1":2346279,
    "qs:woe_adm2":12600496,
    "qs:woe_lau":0,
    "qs:woe_local":134091,
    "qs:woe_ver":"7.10.0",
    "wof:lang":[
        "spa"
    ],
    "wof:name":"Molino de Parras",
    "wof:placetype":"neighbourhood"
},
  "geometry": {"coordinates":[-101.19369500000001,19.698193],"type":"Point"}
}