{
  "type": "Feature",
  "properties": {
    "gn:admin1_code":"30.0",
    "gn:admin2_code":"161.0",
    "gn:asciiname":"El Coposo",
    "gn:country_code":"MX",
    "gn:dem":50,
    "gn:feature_class":"P",
    "gn:feature_code":"PPL",
    "gn:name":"El Coposo",
    "gn:population":4,
    "gn:timezone":"America/Mexico_City",
    "iso:country":"MX",
    "name:spa_x_preferred":[
        "El Coposo"
    ],
    "wof:name":"El Coposo",
    "wof:placetype":"locality",
    "wof:population":4
},
  "geometry": {"coordinates":[-98.17972,21.65306],"type":"Point"}
}