{
  "type": "Feature",
  "properties": {
    "gn:admin1_code":"13",
    "gn:admin2_code":"35.0",
    "gn:asciiname":"Milpa Vieja",
    "gn:country_code":"MX",
    "gn:dem":2240,
    "gn:feature_class":"P",
    "gn:feature_code":"PPL",
    "gn:name":"Milpa Vieja",
    "gn:population":0,
    "gn:timezone":"America/Mexico_City",
    "iso:country":"MX",
    "name:und_x_variant":[
        "Apulco"
    ],
    "wof:name":"Milpa Vieja",
    "wof:placetype":"locality"
},
  "geometry": {"coordinates":[-98.34072999999999,20.31139],"type":"Point"}
}