{
  "type": "Feature",
  "properties": {
    "gn:admin1_code":"16",
    "gn:admin2_code":"35.0",
    "gn:asciiname":"Colonia Lazaro Cardenas",
    "gn:country_code":"MX",
    "gn:dem":476,
    "gn:feature_class":"P",
    "gn:feature_code":"PPL",
    "gn:name":"Colonia L\u00e1zaro C\u00e1rdenas",
    "gn:population":119,
    "gn:timezone":"America/Mexico_City",
    "iso:country":"MX",
    "name:und_x_variant":[
        "Colonia L\u00e1zaro C\u00e1rdenas"
    ],
    "wof:name":"Colonia Lazaro Cardenas",
    "wof:placetype":"locality",
    "wof:population":119
},
  "geometry": {"coordinates":[-101.81639,18.95333],"type":"Point"}
}