{
  "type": "Feature",
  "properties": {
    "gn:admin1_code":"16",
    "gn:admin2_code":"58.0",
    "gn:asciiname":"San Nicolas",
    "gn:country_code":"MX",
    "gn:dem":2734,
    "gn:feature_class":"P",
    "gn:feature_code":"PPL",
    "gn:name":"San Nicol\u00e1s",
    "gn:population":4,
    "gn:timezone":"America/Mexico_City",
    "iso:country":"MX",
    "name:spa_x_preferred":[
        "San Nicol\u00e1s"
    ],
    "wof:name":"San Nicolas",
    "wof:placetype":"locality",
    "wof:population":4
},
  "geometry": {"coordinates":[-102.23833,19.42123],"type":"Point"}
}