{
  "type": "Feature",
  "properties": {
    "gn:admin1_code":"32",
    "gn:admin2_code":"51",
    "gn:asciiname":"La Tijerita Tres",
    "gn:country_code":"MX",
    "gn:dem":1991,
    "gn:feature_class":"P",
    "gn:feature_code":"PPL",
    "gn:name":"La Tijerita Tres",
    "gn:population":12,
    "gn:timezone":"America/Mexico_City",
    "iso:country":"MX",
    "wof:name":"La Tijerita Tres",
    "wof:placetype":"locality",
    "wof:population":12
},
  "geometry": {"coordinates":[-102.39333000000001,23.20139],"type":"Point"}
}