{
  "type": "Feature",
  "properties": {
    "gn:admin1_code":"28.0",
    "gn:admin2_code":"35.0",
    "gn:asciiname":"Los Pericos",
    "gn:country_code":"MX",
    "gn:dem":38,
    "gn:feature_class":"P",
    "gn:feature_code":"PPL",
    "gn:name":"Los Pericos",
    "gn:population":6,
    "gn:timezone":"America/Monterrey",
    "iso:country":"MX",
    "name:spa_x_preferred":[
        "Los Pericos"
    ],
    "wof:name":"Los Pericos",
    "wof:placetype":"locality",
    "wof:population":6
},
  "geometry": {"coordinates":[-98.09166999999999,24.9875],"type":"Point"}
}