{
  "type": "Feature",
  "properties": {
    "gn:admin1_code":"6",
    "gn:admin2_code":"29.0",
    "gn:asciiname":"Paraje Trigo de Loyas",
    "gn:country_code":"MX",
    "gn:dem":1752,
    "gn:feature_class":"P",
    "gn:feature_code":"PPL",
    "gn:name":"Paraje Trigo de Loyas",
    "gn:population":0,
    "gn:timezone":"America/Chihuahua",
    "iso:country":"MX",
    "name:spa_x_preferred":[
        "Paraje Trigo de Loyas"
    ],
    "wof:name":"Paraje Trigo de Loyas",
    "wof:placetype":"locality"
},
  "geometry": {"coordinates":[-107.52849999999999,26.32965],"type":"Point"}
}