{
  "type": "Feature",
  "properties": {
    "gn:admin1_code":"8.0",
    "gn:admin2_code":"9.0",
    "gn:asciiname":"El Regimiento",
    "gn:country_code":"MX",
    "gn:dem":35,
    "gn:feature_class":"P",
    "gn:feature_code":"PPL",
    "gn:name":"El Regimiento",
    "gn:population":0,
    "gn:timezone":"America/Mexico_City",
    "iso:country":"MX",
    "name:spa_x_preferred":[
        "El Regimiento"
    ],
    "wof:name":"El Regimiento",
    "wof:placetype":"locality"
},
  "geometry": {"coordinates":[-103.84148999999999,18.917],"type":"Point"}
}