{
  "type": "Feature",
  "properties": {
    "gn:admin1_code":"23",
    "gn:admin2_code":"4.0",
    "gn:asciiname":"El Suspiro",
    "gn:country_code":"MX",
    "gn:dem":33,
    "gn:feature_class":"P",
    "gn:feature_code":"PPL",
    "gn:name":"El Suspiro",
    "gn:population":15,
    "gn:timezone":"America/Cancun",
    "iso:country":"MX",
    "name:und_x_variant":[
        "Suspiro"
    ],
    "wof:name":"El Suspiro",
    "wof:placetype":"locality",
    "wof:population":15
},
  "geometry": {"coordinates":[-88.52943999999999,18.75778],"type":"Point"}
}