{
  "type": "Feature",
  "properties": {
    "gn:admin1_code":"14",
    "gn:admin2_code":"64.0",
    "gn:asciiname":"Emiliano Zapata",
    "gn:country_code":"MX",
    "gn:dem":2154,
    "gn:feature_class":"P",
    "gn:feature_code":"PPL",
    "gn:name":"Emiliano Zapata",
    "gn:population":0,
    "gn:timezone":"America/Mexico_City",
    "iso:country":"MX",
    "name:spa_x_preferred":[
        "Nana \u00c1ngela"
    ],
    "name:und_x_variant":[
        "Nanangala",
        "Nanangela"
    ],
    "wof:name":"Emiliano Zapata",
    "wof:placetype":"locality"
},
  "geometry": {"coordinates":[-101.57411999999999,21.68599],"type":"Point"}
}