{
  "type": "Feature",
  "properties": {
    "gn:admin1_code":"5",
    "gn:admin2_code":"6.0",
    "gn:asciiname":"El Coyol",
    "gn:cc2":"MX",
    "gn:country_code":"MX",
    "gn:dem":883,
    "gn:feature_class":"P",
    "gn:feature_code":"PPL",
    "gn:name":"El Coyol",
    "gn:population":0,
    "gn:timezone":"America/Mexico_City",
    "iso:country":"MX",
    "name:und_x_variant":[
        "Coyol",
        "El Coyol"
    ],
    "wof:name":"El Coyol",
    "wof:placetype":"locality"
},
  "geometry": {"coordinates":[-92.09999999999999,15.56667],"type":"Point"}
}