{
  "type": "Feature",
  "properties": {
    "gn:admin1_code":"27",
    "gn:admin2_code":"12.0",
    "gn:asciiname":"El Triunfo Segunda Seccion",
    "gn:country_code":"MX",
    "gn:dem":21,
    "gn:feature_class":"P",
    "gn:feature_code":"PPL",
    "gn:name":"El Triunfo Segunda Secci\u00f3n",
    "gn:population":0,
    "gn:timezone":"America/Mexico_City",
    "iso:country":"MX",
    "name:spa_x_preferred":[
        "El Triunfo Segunda Secci\u00f3n"
    ],
    "name:spa_x_variant":[
        "El Triunfo",
        "Segunda Secci\u00f3n"
    ],
    "wof:name":"El Triunfo Segunda Seccion",
    "wof:placetype":"locality"
},
  "geometry": {"coordinates":[-92.46001,17.77585],"type":"Point"}
}