{
  "type": "Feature",
  "properties": {
    "gn:admin1_code":"11",
    "gn:admin2_code":"17",
    "gn:asciiname":"El Rosal",
    "gn:country_code":"MX",
    "gn:dem":1717,
    "gn:feature_class":"P",
    "gn:feature_code":"PPL",
    "gn:name":"El Rosal",
    "gn:population":18,
    "gn:timezone":"America/Mexico_City",
    "iso:country":"MX",
    "name:ceb_x_preferred":[
        "El Rosal"
    ],
    "name:deu_x_preferred":[
        "El Rosal"
    ],
    "name:fra_x_preferred":[
        "El Rosal"
    ],
    "name:sco_x_preferred":[
        "El Rosal"
    ],
    "name:spa_x_preferred":[
        "El Rosal"
    ],
    "name:srp_x_preferred":[
        "\u0415\u043b \u0420\u043e\u0441\u0430\u043b"
    ],
    "name:swe_x_preferred":[
        "El Rosal"
    ],
    "name:vie_x_preferred":[
        "El Rosal"
    ],
    "wof:name":"El Rosal",
    "wof:placetype":"locality",
    "wof:population":18
},
  "geometry": {"coordinates":[-101.34528,20.63917],"type":"Point"}
}