{
  "type": "Feature",
  "properties": {
    "gn:admin1_code":"30",
    "gn:admin2_code":"105.0",
    "gn:asciiname":"Finca Junior",
    "gn:country_code":"MX",
    "gn:dem":8,
    "gn:feature_class":"P",
    "gn:feature_code":"PPL",
    "gn:name":"Finca Junior",
    "gn:population":6,
    "gn:timezone":"America/Mexico_City",
    "iso:country":"MX",
    "wof:name":"Finca Junior",
    "wof:placetype":"locality",
    "wof:population":6
},
  "geometry": {"coordinates":[-96.1525,19.08944],"type":"Point"}
}