{
  "type": "Feature",
  "properties": {
    "gn:admin1_code":"20",
    "gn:admin2_code":"413.0",
    "gn:asciiname":"San Andres",
    "gn:country_code":"MX",
    "gn:dem":735,
    "gn:feature_class":"P",
    "gn:feature_code":"PPL",
    "gn:name":"San Andr\u00e9s",
    "gn:population":8,
    "gn:timezone":"America/Mexico_City",
    "iso:country":"MX",
    "name:und_x_variant":[
        "San Andr\u00e9s"
    ],
    "wof:name":"San Andres",
    "wof:placetype":"locality",
    "wof:population":8
},
  "geometry": {"coordinates":[-96.24472,15.90222],"type":"Point"}
}