{
  "type": "Feature",
  "properties": {
    "gn:admin1_code":"5",
    "gn:admin2_code":"20",
    "gn:asciiname":"Naranjo el Alto",
    "gn:country_code":"MX",
    "gn:dem":554,
    "gn:feature_class":"P",
    "gn:feature_code":"PPL",
    "gn:name":"Naranjo el Alto",
    "gn:population":11,
    "gn:timezone":"America/Mexico_City",
    "iso:country":"MX",
    "wof:name":"Naranjo el Alto",
    "wof:placetype":"locality",
    "wof:population":11
},
  "geometry": {"coordinates":[-92.8125,16.06111],"type":"Point"}
}