{
  "type": "Feature",
  "properties": {
    "gn:admin1_code":"32.0",
    "gn:asciiname":"La Cuesta del Coyote",
    "gn:country_code":"MX",
    "gn:dem":1357,
    "gn:feature_class":"P",
    "gn:feature_code":"PPL",
    "gn:name":"La Cuesta del Coyote",
    "gn:population":0,
    "gn:timezone":"America/Mexico_City",
    "iso:country":"MX",
    "name:spa_x_preferred":[
        "La Cuesta del Coyote"
    ],
    "wof:name":"La Cuesta del Coyote",
    "wof:placetype":"locality"
},
  "geometry": {"coordinates":[-102.99293,21.59895],"type":"Point"}
}