{
  "type": "Feature",
  "properties": {
    "gn:admin1_code":"4",
    "gn:admin2_code":"11.0",
    "gn:asciiname":"San Florencio",
    "gn:country_code":"MX",
    "gn:dem":105,
    "gn:feature_class":"P",
    "gn:feature_code":"PPL",
    "gn:name":"San Florencio",
    "gn:population":6,
    "gn:timezone":"America/Merida",
    "iso:country":"MX",
    "wof:name":"San Florencio",
    "wof:placetype":"locality",
    "wof:population":6
},
  "geometry": {"coordinates":[-90.87833000000001,18.22861],"type":"Point"}
}