{
  "type": "Feature",
  "properties": {
    "gn:admin1_code":"32",
    "gn:admin2_code":"38",
    "gn:asciiname":"Huertas de la Trinidad",
    "gn:country_code":"MX",
    "gn:dem":2164,
    "gn:feature_class":"P",
    "gn:feature_code":"PPL",
    "gn:name":"Huertas de la Trinidad",
    "gn:population":45,
    "gn:timezone":"America/Mexico_City",
    "iso:country":"MX",
    "wof:name":"Huertas de la Trinidad",
    "wof:placetype":"locality",
    "wof:population":45
},
  "geometry": {"coordinates":[-101.69638999999999,22.06694],"type":"Point"}
}