{
  "type": "Feature",
  "properties": {
    "gn:admin1_code":"16",
    "gn:admin2_code":"8",
    "gn:asciiname":"Ojos de Agua",
    "gn:country_code":"MX",
    "gn:dem":1042,
    "gn:feature_class":"P",
    "gn:feature_code":"PPL",
    "gn:name":"Ojos de Agua",
    "gn:population":16,
    "gn:timezone":"America/Mexico_City",
    "iso:country":"MX",
    "wof:name":"Ojos de Agua",
    "wof:placetype":"locality",
    "wof:population":16
},
  "geometry": {"coordinates":[-102.89694,18.26778],"type":"Point"}
}