{
  "type": "Feature",
  "properties": {
    "gn:admin1_code":"6.0",
    "gn:admin2_code":"13.0",
    "gn:asciiname":"Don Pedro",
    "gn:country_code":"MX",
    "gn:dem":1401,
    "gn:feature_class":"P",
    "gn:feature_code":"PPL",
    "gn:name":"Don Pedro",
    "gn:population":0,
    "gn:timezone":"America/Chihuahua",
    "iso:country":"MX",
    "name:spa_x_preferred":[
        "Don Pedro"
    ],
    "wof:name":"Don Pedro",
    "wof:placetype":"locality"
},
  "geometry": {"coordinates":[-107.97863,30.62567],"type":"Point"}
}