{
  "type": "Feature",
  "properties": {
    "gn:admin1_code":"20",
    "gn:admin2_code":"437.0",
    "gn:asciiname":"Yacochi",
    "gn:country_code":"MX",
    "gn:dem":2313,
    "gn:feature_class":"P",
    "gn:feature_code":"PPL",
    "gn:name":"Yacochi",
    "gn:population":0,
    "gn:timezone":"America/Mexico_City",
    "iso:country":"MX",
    "name:und_x_variant":[
        "Santa Mar\u00eda Yacochi"
    ],
    "wof:name":"Yacochi",
    "wof:placetype":"locality"
},
  "geometry": {"coordinates":[-96.05049,17.14083],"type":"Point"}
}