{
  "type": "Feature",
  "properties": {
    "gn:admin1_code":"20",
    "gn:admin2_code":"41.0",
    "gn:asciiname":"Plan de Lecho",
    "gn:country_code":"MX",
    "gn:dem":1678,
    "gn:feature_class":"P",
    "gn:feature_code":"PPL",
    "gn:name":"Plan de Lecho",
    "gn:population":62,
    "gn:timezone":"America/Mexico_City",
    "iso:country":"MX",
    "wof:name":"Plan de Lecho",
    "wof:placetype":"locality",
    "wof:population":62
},
  "geometry": {"coordinates":[-96.83360999999999,18.17583],"type":"Point"}
}