{
  "type": "Feature",
  "properties": {
    "gn:admin1_code":"14.0",
    "gn:admin2_code":"60.0",
    "gn:asciiname":"Las Tinajas",
    "gn:country_code":"MX",
    "gn:dem":1882,
    "gn:feature_class":"P",
    "gn:feature_code":"PPL",
    "gn:name":"Las Tinajas",
    "gn:population":0,
    "gn:timezone":"America/Mexico_City",
    "iso:country":"MX",
    "name:spa_x_preferred":[
        "Las Tinajas"
    ],
    "wof:name":"Las Tinajas",
    "wof:placetype":"locality"
},
  "geometry": {"coordinates":[-102.80022,21.29414],"type":"Point"}
}