{
  "type": "Feature",
  "properties": {
    "gn:admin1_code":"9",
    "gn:admin2_code":"12",
    "gn:asciiname":"El Crucero (SEDECO)",
    "gn:country_code":"MX",
    "gn:dem":2937,
    "gn:feature_class":"P",
    "gn:feature_code":"PPL",
    "gn:name":"El Crucero (SEDECO)",
    "gn:population":36,
    "gn:timezone":"America/Mexico_City",
    "iso:country":"MX",
    "wof:name":"El Crucero (SEDECO)",
    "wof:placetype":"locality",
    "wof:population":36
},
  "geometry": {"coordinates":[-99.16222,19.15472],"type":"Point"}
}