{
  "type": "Feature",
  "properties": {
    "gn:admin1_code":"31",
    "gn:admin2_code":"38.0",
    "gn:asciiname":"Chunhuas",
    "gn:country_code":"MX",
    "gn:dem":2,
    "gn:feature_class":"P",
    "gn:feature_code":"PPL",
    "gn:name":"Chunhu\u00e1s",
    "gn:population":0,
    "gn:timezone":"America/Merida",
    "iso:country":"MX",
    "wof:name":"Chunhuas",
    "wof:placetype":"locality"
},
  "geometry": {"coordinates":[-89.94083000000001,21.08389],"type":"Point"}
}