{
  "type": "Feature",
  "properties": {
    "gn:admin1_code":"26",
    "gn:admin2_code":"18",
    "gn:asciiname":"Agricola Espiritu Santo",
    "gn:country_code":"MX",
    "gn:dem":52,
    "gn:feature_class":"P",
    "gn:feature_code":"PPL",
    "gn:name":"Agr\u00edcola Esp\u00edritu Santo",
    "gn:population":12,
    "gn:timezone":"America/Hermosillo",
    "iso:country":"MX",
    "name:und_x_variant":[
        "Agr\u00edcola Esp\u00edritu Santo"
    ],
    "wof:name":"Agricola Espiritu Santo",
    "wof:placetype":"locality",
    "wof:population":12
},
  "geometry": {"coordinates":[-109.88943999999999,27.51944],"type":"Point"}
}