{
  "type": "Feature",
  "properties": {
    "gn:admin1_code":"12",
    "gn:admin2_code":"2",
    "gn:asciiname":"Vista Hermosa Tlaquilcingo",
    "gn:country_code":"MX",
    "gn:dem":1135,
    "gn:feature_class":"P",
    "gn:feature_code":"PPL",
    "gn:name":"Vista Hermosa Tlaquilcingo",
    "gn:population":40,
    "gn:timezone":"America/Mexico_City",
    "iso:country":"MX",
    "wof:name":"Vista Hermosa Tlaquilcingo",
    "wof:placetype":"locality",
    "wof:population":40
},
  "geometry": {"coordinates":[-98.92206,17.85934],"type":"Point"}
}