{
  "type": "Feature",
  "properties": {
    "gn:admin1_code":"6",
    "gn:admin2_code":"31.0",
    "gn:asciiname":"Rancho Miguel (El Puerto)",
    "gn:country_code":"MX",
    "gn:dem":2595,
    "gn:feature_class":"P",
    "gn:feature_code":"PPL",
    "gn:name":"Rancho Miguel (El Puerto)",
    "gn:population":5,
    "gn:timezone":"America/Chihuahua",
    "iso:country":"MX",
    "wof:name":"Rancho Miguel (El Puerto)",
    "wof:placetype":"locality",
    "wof:population":5
},
  "geometry": {"coordinates":[-107.95157,28.16906],"type":"Point"}
}