{
  "type": "Feature",
  "properties": {
    "gn:admin1_code":"16",
    "gn:admin2_code":"66.0",
    "gn:asciiname":"El Manzanillal (Colonia Enrique Ramirez)",
    "gn:country_code":"MX",
    "gn:dem":2080,
    "gn:feature_class":"P",
    "gn:feature_code":"PPL",
    "gn:name":"El Manzanillal (Colonia Enrique Ram\u00edrez)",
    "gn:population":377,
    "gn:timezone":"America/Mexico_City",
    "iso:country":"MX",
    "name:und_x_variant":[
        "El Manzanillal (Colonia Enrique Ram\u00edrez)"
    ],
    "wof:name":"El Manzanillal (Colonia Enrique Ramirez)",
    "wof:placetype":"locality",
    "wof:population":377
},
  "geometry": {"coordinates":[-101.57666999999999,19.53417],"type":"Point"}
}