{
  "type": "Feature",
  "properties": {
    "gn:admin1_code":"32.0",
    "gn:admin2_code":"38.0",
    "gn:asciiname":"Barrancas",
    "gn:country_code":"MX",
    "gn:dem":2230,
    "gn:feature_class":"P",
    "gn:feature_code":"PPL",
    "gn:name":"Barrancas",
    "gn:population":0,
    "gn:timezone":"America/Mexico_City",
    "iso:country":"MX",
    "name:bre_x_preferred":[
        "Barrancas"
    ],
    "name:ceb_x_preferred":[
        "Barrancas"
    ],
    "name:deu_x_preferred":[
        "Barrancas"
    ],
    "name:fra_x_preferred":[
        "Barrancas"
    ],
    "name:por_x_preferred":[
        "Barrancas"
    ],
    "name:spa_x_preferred":[
        "Barrancas"
    ],
    "name:swe_x_preferred":[
        "Barrancas"
    ],
    "wof:name":"Barrancas",
    "wof:placetype":"locality"
},
  "geometry": {"coordinates":[-101.72217000000001,22.12453],"type":"Point"}
}