{
  "type": "Feature",
  "properties": {
    "gn:admin1_code":"8.0",
    "gn:admin2_code":"10.0",
    "gn:asciiname":"Los Picachos",
    "gn:country_code":"MX",
    "gn:dem":448,
    "gn:feature_class":"P",
    "gn:feature_code":"PPL",
    "gn:name":"Los Picachos",
    "gn:population":93,
    "gn:timezone":"America/Mexico_City",
    "iso:country":"MX",
    "wof:name":"Los Picachos",
    "wof:placetype":"locality",
    "wof:population":93
},
  "geometry": {"coordinates":[-103.83944,19.30861],"type":"Point"}
}