{
  "type": "Feature",
  "properties": {
    "gn:admin1_code":"26",
    "gn:admin2_code":"51.0",
    "gn:asciiname":"El Nacimiento",
    "gn:country_code":"MX",
    "gn:dem":670,
    "gn:feature_class":"P",
    "gn:feature_code":"PPL",
    "gn:name":"El Nacimiento",
    "gn:population":5,
    "gn:timezone":"America/Hermosillo",
    "iso:country":"MX",
    "wof:name":"El Nacimiento",
    "wof:placetype":"locality",
    "wof:population":5
},
  "geometry": {"coordinates":[-109.08278,27.7875],"type":"Point"}
}