{
  "type": "Feature",
  "properties": {
    "gn:admin1_code":"14.0",
    "gn:asciiname":"La Corona",
    "gn:country_code":"MX",
    "gn:dem":2178,
    "gn:feature_class":"P",
    "gn:feature_code":"PPL",
    "gn:name":"La Corona",
    "gn:population":0,
    "gn:timezone":"America/Mexico_City",
    "iso:country":"MX",
    "name:spa_x_preferred":[
        "La Corona"
    ],
    "wof:name":"La Corona",
    "wof:placetype":"locality"
},
  "geometry": {"coordinates":[-102.27109,20.86397],"type":"Point"}
}