{
  "type": "Feature",
  "properties": {
    "gn:admin1_code":"5",
    "gn:admin2_code":"65.0",
    "gn:asciiname":"Miguel Hidalgo",
    "gn:country_code":"MX",
    "gn:dem":67,
    "gn:feature_class":"P",
    "gn:feature_code":"PPL",
    "gn:name":"Miguel Hidalgo",
    "gn:population":0,
    "gn:timezone":"America/Mexico_City",
    "iso:country":"MX",
    "name:spa_x_preferred":[
        "Miguel Hidalgo"
    ],
    "name:spa_x_variant":[
        "Lacand\u00f3n"
    ],
    "wof:name":"Miguel Hidalgo",
    "wof:placetype":"locality"
},
  "geometry": {"coordinates":[-91.82048,17.53238],"type":"Point"}
}