{
  "type": "Feature",
  "properties": {
    "gn:admin1_code":"30",
    "gn:admin2_code":"169.0",
    "gn:asciiname":"Seis Amigos",
    "gn:country_code":"MX",
    "gn:dem":11,
    "gn:feature_class":"P",
    "gn:feature_code":"PPL",
    "gn:name":"Seis Amigos",
    "gn:population":0,
    "gn:timezone":"America/Mexico_City",
    "iso:country":"MX",
    "name:spa_x_preferred":[
        "Seis Amigos"
    ],
    "wof:name":"Seis Amigos",
    "wof:placetype":"locality"
},
  "geometry": {"coordinates":[-95.65689999999999,18.22799],"type":"Point"}
}