{
  "type": "Feature",
  "properties": {
    "gn:admin1_code":"16.0",
    "gn:admin2_code":"2.0",
    "gn:asciiname":"El Charapo",
    "gn:country_code":"MX",
    "gn:dem":327,
    "gn:feature_class":"P",
    "gn:feature_code":"PPL",
    "gn:name":"El Charapo",
    "gn:population":0,
    "gn:timezone":"America/Mexico_City",
    "iso:country":"MX",
    "name:spa_x_preferred":[
        "El Charapo"
    ],
    "name:spa_x_variant":[
        "Palo Alto"
    ],
    "name:und_x_variant":[
        "Charapo"
    ],
    "wof:name":"El Charapo",
    "wof:placetype":"locality"
},
  "geometry": {"coordinates":[-102.73792,18.93467],"type":"Point"}
}