{
  "type": "Feature",
  "properties": {
    "gn:admin1_code":"5",
    "gn:admin2_code":"84.0",
    "gn:asciiname":"Santa Fe la Sacualpa",
    "gn:country_code":"MX",
    "gn:dem":346,
    "gn:feature_class":"P",
    "gn:feature_code":"PPL",
    "gn:name":"Santa Fe la Sacualpa",
    "gn:population":0,
    "gn:timezone":"America/Mexico_City",
    "iso:country":"MX",
    "name:spa_x_preferred":[
        "Santa Fe la Sacualpa"
    ],
    "name:und_x_variant":[
        "Zacualpan"
    ],
    "wof:name":"Santa Fe la Sacualpa",
    "wof:placetype":"locality"
},
  "geometry": {"coordinates":[-93.0026,17.33535],"type":"Point"}
}