{
  "type": "Feature",
  "properties": {
    "gn:admin1_code":"5",
    "gn:admin2_code":"89.0",
    "gn:asciiname":"San Antonio Nexapa",
    "gn:country_code":"MX",
    "gn:dem":555,
    "gn:feature_class":"P",
    "gn:feature_code":"PPL",
    "gn:name":"San Antonio Nexapa",
    "gn:population":144,
    "gn:timezone":"America/Mexico_City",
    "iso:country":"MX",
    "wof:name":"San Antonio Nexapa",
    "wof:placetype":"locality",
    "wof:population":144
},
  "geometry": {"coordinates":[-92.26163,15.03217],"type":"Point"}
}