{
  "type": "Feature",
  "properties": {
    "gn:admin1_code":"16",
    "gn:admin2_code":"53.0",
    "gn:asciiname":"Cointzio",
    "gn:country_code":"MX",
    "gn:dem":1920,
    "gn:feature_class":"P",
    "gn:feature_code":"PPL",
    "gn:name":"Co\u00edntzio",
    "gn:population":732,
    "gn:timezone":"America/Mexico_City",
    "iso:country":"MX",
    "name:und_x_variant":[
        "Co\u00edntzio"
    ],
    "wof:name":"Cointzio",
    "wof:placetype":"locality",
    "wof:population":732
},
  "geometry": {"coordinates":[-101.2625,19.64083],"type":"Point"}
}