{
  "type": "Feature",
  "properties": {
    "gn:admin1_code":"32.0",
    "gn:admin2_code":"23.0",
    "gn:asciiname":"El Garbanzal",
    "gn:country_code":"MX",
    "gn:dem":2044,
    "gn:feature_class":"P",
    "gn:feature_code":"PPL",
    "gn:name":"El Garbanzal",
    "gn:population":0,
    "gn:timezone":"America/Mexico_City",
    "iso:country":"MX",
    "name:spa_x_preferred":[
        "El Garbanzal"
    ],
    "wof:name":"El Garbanzal",
    "wof:placetype":"locality"
},
  "geometry": {"coordinates":[-103.00047000000001,21.38317],"type":"Point"}
}