{
  "type": "Feature",
  "properties": {
    "gn:admin1_code":"25",
    "gn:admin2_code":"8.0",
    "gn:asciiname":"Campo Nuevo Caimanes",
    "gn:country_code":"MX",
    "gn:dem":33,
    "gn:feature_class":"P",
    "gn:feature_code":"PPL",
    "gn:name":"Campo Nuevo Caimanes",
    "gn:population":182,
    "gn:timezone":"America/Mazatlan",
    "iso:country":"MX",
    "wof:name":"Campo Nuevo Caimanes",
    "wof:placetype":"locality",
    "wof:population":182
},
  "geometry": {"coordinates":[-106.90333,24.00944],"type":"Point"}
}