{
  "type": "Feature",
  "properties": {
    "gn:admin1_code":"25.0",
    "gn:admin2_code":"10.0",
    "gn:asciiname":"Cajon de los Lugos",
    "gn:country_code":"MX",
    "gn:dem":145,
    "gn:feature_class":"P",
    "gn:feature_code":"PPL",
    "gn:name":"Caj\u00f3n de los Lugos",
    "gn:population":0,
    "gn:timezone":"America/Mazatlan",
    "iso:country":"MX",
    "name:spa_x_preferred":[
        "Caj\u00f3n de los Lugos"
    ],
    "name:und_x_variant":[
        "Caj\u00f3n de los Lugo"
    ],
    "wof:name":"Cajon de los Lugos",
    "wof:placetype":"locality"
},
  "geometry": {"coordinates":[-108.51779999999999,26.3571],"type":"Point"}
}