{
  "type": "Feature",
  "properties": {
    "gn:admin1_code":"16.0",
    "gn:admin2_code":"8.0",
    "gn:asciiname":"El Chical",
    "gn:country_code":"MX",
    "gn:dem":521,
    "gn:feature_class":"P",
    "gn:feature_code":"PPL",
    "gn:name":"El Chical",
    "gn:population":0,
    "gn:timezone":"America/Mexico_City",
    "iso:country":"MX",
    "name:spa_x_preferred":[
        "El Chical"
    ],
    "wof:name":"El Chical",
    "wof:placetype":"locality"
},
  "geometry": {"coordinates":[-103.33343000000001,18.41232],"type":"Point"}
}