{
  "type": "Feature",
  "properties": {
    "gn:admin1_code":"7",
    "gn:admin2_code":"36.0",
    "gn:asciiname":"Sector Uno Gabino Vazquez",
    "gn:country_code":"MX",
    "gn:dem":1108,
    "gn:feature_class":"P",
    "gn:feature_code":"PPL",
    "gn:name":"Sector Uno Gabino V\u00e1zquez",
    "gn:population":5,
    "gn:timezone":"America/Monterrey",
    "iso:country":"MX",
    "name:und_x_variant":[
        "Sector Uno Gabino V\u00e1zquez"
    ],
    "wof:name":"Sector Uno Gabino Vazquez",
    "wof:placetype":"locality",
    "wof:population":5
},
  "geometry": {"coordinates":[-103.07673,25.46417000000001],"type":"Point"}
}