{
  "type": "Feature",
  "properties": {
    "gn:admin1_code":"30",
    "gn:admin2_code":"116.0",
    "gn:asciiname":"Ediz Castillo Cruz",
    "gn:country_code":"MX",
    "gn:dem":57,
    "gn:feature_class":"P",
    "gn:feature_code":"PPL",
    "gn:name":"\u00c9diz Castillo Cruz",
    "gn:population":5,
    "gn:timezone":"America/Mexico_City",
    "iso:country":"MX",
    "name:und_x_variant":[
        "\u00c9diz Castillo Cruz"
    ],
    "wof:name":"Ediz Castillo Cruz",
    "wof:placetype":"locality",
    "wof:population":5
},
  "geometry": {"coordinates":[-94.91222,17.90167000000001],"type":"Point"}
}