{
  "type": "Feature",
  "properties": {
    "gn:admin1_code":"25",
    "gn:admin2_code":"3.0",
    "gn:asciiname":"La Higuerita",
    "gn:country_code":"MX",
    "gn:dem":337,
    "gn:feature_class":"P",
    "gn:feature_code":"PPL",
    "gn:name":"La Higuerita",
    "gn:population":7,
    "gn:timezone":"America/Mazatlan",
    "iso:country":"MX",
    "wof:name":"La Higuerita",
    "wof:placetype":"locality",
    "wof:population":7
},
  "geometry": {"coordinates":[-107.28507,25.32764],"type":"Point"}
}