{
  "type": "Feature",
  "properties": {
    "gn:admin1_code":"6.0",
    "gn:admin2_code":"1.0",
    "gn:asciiname":"Rancho M y M",
    "gn:country_code":"MX",
    "gn:dem":1210,
    "gn:feature_class":"P",
    "gn:feature_code":"PPL",
    "gn:name":"Rancho M y M",
    "gn:population":0,
    "gn:timezone":"America/Chihuahua",
    "iso:country":"MX",
    "name:spa_x_preferred":[
        "Rancho M y M"
    ],
    "wof:name":"Rancho M y M",
    "wof:placetype":"locality"
},
  "geometry": {"coordinates":[-106.47857999999999,30.61979],"type":"Point"}
}