{
  "type": "Feature",
  "properties": {
    "gn:admin1_code":"15",
    "gn:admin2_code":"80.0",
    "gn:asciiname":"Cuatro Cruces",
    "gn:country_code":"MX",
    "gn:dem":2236,
    "gn:feature_class":"P",
    "gn:feature_code":"PPL",
    "gn:name":"Cuatro Cruces",
    "gn:population":186,
    "gn:timezone":"America/Mexico_City",
    "iso:country":"MX",
    "wof:name":"Cuatro Cruces",
    "wof:placetype":"locality",
    "wof:population":186
},
  "geometry": {"coordinates":[-100.04355,18.74689],"type":"Point"}
}