{
  "type": "Feature",
  "properties": {
    "gn:admin1_code":"10.0",
    "gn:admin2_code":"34.0",
    "gn:asciiname":"La Cienega de Acatita Grande",
    "gn:cc2":"MX",
    "gn:country_code":"MX",
    "gn:dem":498,
    "gn:feature_class":"P",
    "gn:feature_code":"PPL",
    "gn:name":"La Ci\u00e9nega de Acatita Grande",
    "gn:population":14,
    "gn:timezone":"America/Mazatlan",
    "iso:country":"MX",
    "name:und_x_variant":[
        "Acatita",
        "Acatita Grande"
    ],
    "wof:name":"La Cienega de Acatita Grande",
    "wof:placetype":"locality",
    "wof:population":14
},
  "geometry": {"coordinates":[-107.06480999999999,25.02247],"type":"Point"}
}