{
  "type": "Feature",
  "properties": {
    "gn:admin1_code":"13",
    "gn:admin2_code":"3",
    "gn:asciiname":"San Pedrito",
    "gn:country_code":"MX",
    "gn:dem":1978,
    "gn:feature_class":"P",
    "gn:feature_code":"PPL",
    "gn:name":"San Pedrito",
    "gn:population":15,
    "gn:timezone":"America/Mexico_City",
    "iso:country":"MX",
    "wof:name":"San Pedrito",
    "wof:placetype":"locality",
    "wof:population":15
},
  "geometry": {"coordinates":[-98.95498000000001,20.25825],"type":"Point"}
}