{
  "type": "Feature",
  "properties": {
    "gn:admin1_code":"25",
    "gn:admin2_code":"6.0",
    "gn:asciiname":"El Sauce",
    "gn:country_code":"MX",
    "gn:dem":15,
    "gn:feature_class":"P",
    "gn:feature_code":"PPL",
    "gn:name":"El Sauce",
    "gn:population":0,
    "gn:timezone":"America/Mazatlan",
    "iso:country":"MX",
    "name:ceb_x_preferred":[
        "El Sauce"
    ],
    "name:ita_x_preferred":[
        "El Sauce"
    ],
    "name:por_x_preferred":[
        "El Sauce"
    ],
    "name:spa_x_preferred":[
        "El Sauce"
    ],
    "name:zho_x_preferred":[
        "\u57c3\u723e\u7d39\u585e"
    ],
    "wof:name":"El Sauce",
    "wof:placetype":"locality"
},
  "geometry": {"coordinates":[-107.49876999999999,24.64661],"type":"Point"}
}