{
  "type": "Feature",
  "properties": {
    "gn:admin1_code":"28",
    "gn:admin2_code":"14.0",
    "gn:asciiname":"Cinco de Mayo",
    "gn:country_code":"MX",
    "gn:dem":110,
    "gn:feature_class":"P",
    "gn:feature_code":"PPL",
    "gn:name":"Cinco de Mayo",
    "gn:population":0,
    "gn:timezone":"America/Monterrey",
    "iso:country":"MX",
    "name:spa_x_preferred":[
        "Cinco de Mayo"
    ],
    "name:und_x_variant":[
        "Rancho Cinco de Mayo"
    ],
    "wof:name":"Cinco de Mayo",
    "wof:placetype":"locality"
},
  "geometry": {"coordinates":[-99.4739,26.99839],"type":"Point"}
}