{
  "type": "Feature",
  "properties": {
    "gn:admin1_code":"8",
    "gn:admin2_code":"4",
    "gn:asciiname":"Crucero de Quizalapa",
    "gn:country_code":"MX",
    "gn:dem":385,
    "gn:feature_class":"P",
    "gn:feature_code":"PPL",
    "gn:name":"Crucero de Quizalapa",
    "gn:population":14,
    "gn:timezone":"America/Mexico_City",
    "iso:country":"MX",
    "wof:name":"Crucero de Quizalapa",
    "wof:placetype":"locality",
    "wof:population":14
},
  "geometry": {"coordinates":[-103.79611,19.22278],"type":"Point"}
}