{
  "type": "Feature",
  "properties": {
    "gn:admin1_code":"30.0",
    "gn:asciiname":"Nuevo Jardin",
    "gn:country_code":"MX",
    "gn:dem":27,
    "gn:feature_class":"P",
    "gn:feature_code":"PPL",
    "gn:name":"Nuevo Jard\u00edn",
    "gn:population":0,
    "gn:timezone":"America/Mexico_City",
    "iso:country":"MX",
    "name:spa_x_preferred":[
        "Nuevo Jard\u00edn"
    ],
    "name:spa_x_variant":[
        "El Jard\u00edn",
        "Jard\u00edn Nuevo"
    ],
    "wof:name":"Nuevo Jardin",
    "wof:placetype":"locality"
},
  "geometry": {"coordinates":[-97.65928,20.89439],"type":"Point"}
}