{
  "type": "Feature",
  "properties": {
    "gn:admin1_code":"26",
    "gn:admin2_code":"66.0",
    "gn:asciiname":"San Andres",
    "gn:country_code":"MX",
    "gn:dem":384,
    "gn:feature_class":"P",
    "gn:feature_code":"PPL",
    "gn:name":"San Andr\u00e9s",
    "gn:population":0,
    "gn:timezone":"America/Hermosillo",
    "iso:country":"MX",
    "name:spa_x_preferred":[
        "San Andr\u00e9s"
    ],
    "wof:name":"San Andres",
    "wof:placetype":"locality"
},
  "geometry": {"coordinates":[-110.39261999999999,29.4175],"type":"Point"}
}