{
  "type": "Feature",
  "properties": {
    "gn:admin1_code":"19",
    "gn:admin2_code":"48.0",
    "gn:asciiname":"Los Granjenos",
    "gn:country_code":"MX",
    "gn:dem":967,
    "gn:feature_class":"P",
    "gn:feature_code":"PPL",
    "gn:name":"Los Granjenos",
    "gn:population":0,
    "gn:timezone":"America/Monterrey",
    "iso:country":"MX",
    "name:spa_x_preferred":[
        "Los Granjenos"
    ],
    "wof:name":"Los Granjenos",
    "wof:placetype":"locality"
},
  "geometry": {"coordinates":[-100.36615999999999,25.55063],"type":"Point"}
}