{
  "type": "Feature",
  "properties": {
    "gn:admin1_code":"5",
    "gn:admin2_code":"6.0",
    "gn:asciiname":"Flor de Mayo",
    "gn:country_code":"MX",
    "gn:dem":865,
    "gn:feature_class":"P",
    "gn:feature_code":"PPL",
    "gn:name":"Flor de Mayo",
    "gn:population":268,
    "gn:timezone":"America/Mexico_City",
    "iso:country":"MX",
    "wof:name":"Flor de Mayo",
    "wof:placetype":"locality",
    "wof:population":268
},
  "geometry": {"coordinates":[-92.09972,15.59667],"type":"Point"}
}