{
  "type": "Feature",
  "properties": {
    "gn:admin1_code":"28.0",
    "gn:admin2_code":"8.0",
    "gn:asciiname":"Los Cosacos",
    "gn:country_code":"MX",
    "gn:dem":510,
    "gn:feature_class":"P",
    "gn:feature_code":"PPL",
    "gn:name":"Los Cosacos",
    "gn:population":0,
    "gn:timezone":"America/Monterrey",
    "iso:country":"MX",
    "name:spa_x_preferred":[
        "Los Cosacos"
    ],
    "wof:name":"Los Cosacos",
    "wof:placetype":"locality"
},
  "geometry": {"coordinates":[-98.51083,23.71417000000001],"type":"Point"}
}