{
  "type": "Feature",
  "properties": {
    "gn:admin1_code":"6",
    "gn:admin2_code":"52.0",
    "gn:asciiname":"El Ancon",
    "gn:country_code":"MX",
    "gn:dem":1379,
    "gn:feature_class":"P",
    "gn:feature_code":"PPL",
    "gn:name":"El Anc\u00f3n",
    "gn:population":4,
    "gn:timezone":"America/Ojinaga",
    "iso:country":"MX",
    "name:und_x_variant":[
        "El Anc\u00f3n"
    ],
    "wof:name":"El Ancon",
    "wof:placetype":"locality",
    "wof:population":4
},
  "geometry": {"coordinates":[-104.40324,28.75409],"type":"Point"}
}