{
  "type": "Feature",
  "properties": {
    "gn:admin1_code":"18",
    "gn:admin2_code":"5",
    "gn:asciiname":"Las Juntitas",
    "gn:country_code":"MX",
    "gn:dem":154,
    "gn:feature_class":"P",
    "gn:feature_code":"PPL",
    "gn:name":"Las Juntitas",
    "gn:population":13,
    "gn:timezone":"America/Mazatlan",
    "iso:country":"MX",
    "wof:name":"Las Juntitas",
    "wof:placetype":"locality",
    "wof:population":13
},
  "geometry": {"coordinates":[-105.2525,22.65833],"type":"Point"}
}