{
  "type": "Feature",
  "properties": {
    "gn:admin1_code":"14.0",
    "gn:admin2_code":"91.0",
    "gn:asciiname":"Cerrito Colorado",
    "gn:country_code":"MX",
    "gn:dem":1775,
    "gn:feature_class":"P",
    "gn:feature_code":"PPL",
    "gn:name":"Cerrito Colorado",
    "gn:population":0,
    "gn:timezone":"America/Mexico_City",
    "iso:country":"MX",
    "name:spa_x_preferred":[
        "Cerrito Colorado"
    ],
    "name:spa_x_variant":[
        "El Cerrito Colorado"
    ],
    "wof:name":"Cerrito Colorado",
    "wof:placetype":"locality"
},
  "geometry": {"coordinates":[-102.47615,21.60841],"type":"Point"}
}