{
  "type": "Feature",
  "properties": {
    "gn:admin1_code":"31",
    "gn:admin2_code":"45.0",
    "gn:asciiname":"Kanachen",
    "gn:country_code":"MX",
    "gn:dem":18,
    "gn:feature_class":"P",
    "gn:feature_code":"PPL",
    "gn:name":"Kanachen",
    "gn:population":0,
    "gn:timezone":"America/Merida",
    "iso:country":"MX",
    "name:spa_x_preferred":[
        "Kanachen"
    ],
    "wof:name":"Kanachen",
    "wof:placetype":"locality"
},
  "geometry": {"coordinates":[-89.88784,20.60518],"type":"Point"}
}