{
  "type": "Feature",
  "properties": {
    "gn:admin1_code":"11",
    "gn:admin2_code":"14.0",
    "gn:asciiname":"La Ventilla",
    "gn:country_code":"MX",
    "gn:dem":1920,
    "gn:feature_class":"P",
    "gn:feature_code":"PPL",
    "gn:name":"La Ventilla",
    "gn:population":637,
    "gn:timezone":"America/Mexico_City",
    "iso:country":"MX",
    "wof:name":"La Ventilla",
    "wof:placetype":"locality",
    "wof:population":637
},
  "geometry": {"coordinates":[-100.93361,21.115],"type":"Point"}
}