{
  "type": "Feature",
  "properties": {
    "gn:admin1_code":"10",
    "gn:admin2_code":"7",
    "gn:asciiname":"Familia Sanchez Ramirez",
    "gn:country_code":"MX",
    "gn:dem":1115,
    "gn:feature_class":"P",
    "gn:feature_code":"PPL",
    "gn:name":"Familia S\u00e1nchez Ram\u00edrez",
    "gn:population":29,
    "gn:timezone":"America/Monterrey",
    "iso:country":"MX",
    "name:und_x_variant":[
        "Familia S\u00e1nchez Ram\u00edrez"
    ],
    "wof:name":"Familia Sanchez Ramirez",
    "wof:placetype":"locality",
    "wof:population":29
},
  "geometry": {"coordinates":[-103.44701000000001,25.71139],"type":"Point"}
}