{
  "type": "Feature",
  "properties": {
    "gn:admin1_code":"3",
    "gn:admin2_code":"3.0",
    "gn:asciiname":"Chivato",
    "gn:country_code":"MX",
    "gn:dem":138,
    "gn:feature_class":"P",
    "gn:feature_code":"PPL",
    "gn:name":"Chivato",
    "gn:population":0,
    "gn:timezone":"America/Mazatlan",
    "iso:country":"MX",
    "name:spa_x_preferred":[
        "Chivato"
    ],
    "wof:name":"Chivato",
    "wof:placetype":"locality"
},
  "geometry": {"coordinates":[-110.77139,24.04023],"type":"Point"}
}