{
  "type": "Feature",
  "properties": {
    "gn:admin1_code":"2.0",
    "gn:admin2_code":"3.0",
    "gn:asciiname":"Paredon Colorado",
    "gn:country_code":"MX",
    "gn:dem":713,
    "gn:feature_class":"P",
    "gn:feature_code":"PPL",
    "gn:name":"Pared\u00f3n Colorado",
    "gn:population":0,
    "gn:timezone":"America/Tijuana",
    "iso:country":"MX",
    "name:spa_x_preferred":[
        "Pared\u00f3n Colorado"
    ],
    "wof:name":"Paredon Colorado",
    "wof:placetype":"locality"
},
  "geometry": {"coordinates":[-116.58578,32.49055],"type":"Point"}
}