{
  "type": "Feature",
  "properties": {
    "gn:admin1_code":"21",
    "gn:admin2_code":"164.0",
    "gn:asciiname":"San Bartolome Hueyapan",
    "gn:country_code":"MX",
    "gn:dem":2285,
    "gn:feature_class":"P",
    "gn:feature_code":"PPL",
    "gn:name":"San Bartolom\u00e9 Hueyapan",
    "gn:population":1869,
    "gn:timezone":"America/Mexico_City",
    "iso:country":"MX",
    "name:und_x_variant":[
        "San Bartolom\u00e9 Hueyapan"
    ],
    "wof:name":"San Bartolome Hueyapan",
    "wof:placetype":"locality",
    "wof:population":1869
},
  "geometry": {"coordinates":[-97.93056,19.02528],"type":"Point"}
}