{
  "type": "Feature",
  "properties": {
    "gn:admin1_code":"15.0",
    "gn:asciiname":"Huecato",
    "gn:country_code":"MX",
    "gn:dem":2262,
    "gn:feature_class":"P",
    "gn:feature_code":"PPL",
    "gn:name":"Hu\u00e9cato",
    "gn:population":0,
    "gn:timezone":"America/Mexico_City",
    "iso:country":"MX",
    "name:spa_x_preferred":[
        "Hu\u00e9cato"
    ],
    "wof:name":"Huecato",
    "wof:placetype":"locality"
},
  "geometry": {"coordinates":[-102.14372,19.75093],"type":"Point"}
}