{
  "type": "Feature",
  "properties": {
    "gn:admin1_code":"26",
    "gn:admin2_code":"3.0",
    "gn:asciiname":"Paraje Colorado",
    "gn:country_code":"MX",
    "gn:dem":967,
    "gn:feature_class":"P",
    "gn:feature_code":"PPL",
    "gn:name":"Paraje Colorado",
    "gn:population":9,
    "gn:timezone":"America/Hermosillo",
    "iso:country":"MX",
    "wof:name":"Paraje Colorado",
    "wof:placetype":"locality",
    "wof:population":9
},
  "geometry": {"coordinates":[-108.68361000000002,27.49472],"type":"Point"}
}