{
  "type": "Feature",
  "properties": {
    "gn:admin1_code":"30",
    "gn:admin2_code":"152.0",
    "gn:asciiname":"Zapotal",
    "gn:country_code":"MX",
    "gn:dem":12,
    "gn:feature_class":"P",
    "gn:feature_code":"PPL",
    "gn:name":"Zapotal",
    "gn:population":0,
    "gn:timezone":"America/Mexico_City",
    "iso:country":"MX",
    "name:spa_x_preferred":[
        "Zapotal"
    ],
    "name:und_x_variant":[
        "El Zapotal"
    ],
    "wof:name":"Zapotal",
    "wof:placetype":"locality"
},
  "geometry": {"coordinates":[-97.58906,21.75314],"type":"Point"}
}