{
  "type": "Feature",
  "properties": {
    "gn:admin1_code":"25",
    "gn:admin2_code":"3.0",
    "gn:asciiname":"Baymuzari",
    "gn:country_code":"MX",
    "gn:dem":547,
    "gn:feature_class":"P",
    "gn:feature_code":"PPL",
    "gn:name":"Baymuzari",
    "gn:population":0,
    "gn:timezone":"America/Mazatlan",
    "iso:country":"MX",
    "name:spa_x_preferred":[
        "Baymuzari"
    ],
    "wof:name":"Baymuzari",
    "wof:placetype":"locality"
},
  "geometry": {"coordinates":[-107.37448000000001,25.43288],"type":"Point"}
}