{
  "type": "Feature",
  "properties": {
    "gn:admin1_code":"16",
    "gn:admin2_code":"8",
    "gn:asciiname":"El Zapote de las Viejas",
    "gn:country_code":"MX",
    "gn:dem":24,
    "gn:feature_class":"P",
    "gn:feature_code":"PPL",
    "gn:name":"El Zapote de las Viejas",
    "gn:population":20,
    "gn:timezone":"America/Mexico_City",
    "iso:country":"MX",
    "wof:name":"El Zapote de las Viejas",
    "wof:placetype":"locality",
    "wof:population":20
},
  "geometry": {"coordinates":[-103.03055999999999,18.18889],"type":"Point"}
}