{
  "type": "Feature",
  "properties": {
    "gn:admin1_code":"15",
    "gn:admin2_code":"29.0",
    "gn:asciiname":"Rancho la Cabana",
    "gn:country_code":"MX",
    "gn:dem":2255,
    "gn:feature_class":"P",
    "gn:feature_code":"PPL",
    "gn:name":"Rancho la Caba\u00f1a",
    "gn:population":679,
    "gn:timezone":"America/Mexico_City",
    "iso:country":"MX",
    "name:und_x_variant":[
        "Rancho la Caba\u00f1a"
    ],
    "wof:name":"Rancho la Cabana",
    "wof:placetype":"locality",
    "wof:population":679
},
  "geometry": {"coordinates":[-98.89707,19.42646],"type":"Point"}
}