{
  "type": "Feature",
  "properties": {
    "gn:admin1_code":"7",
    "gn:admin2_code":"28.0",
    "gn:asciiname":"El Durazno",
    "gn:country_code":"MX",
    "gn:dem":509,
    "gn:feature_class":"P",
    "gn:feature_code":"PPL",
    "gn:name":"El Durazno",
    "gn:population":6,
    "gn:timezone":"America/Monterrey",
    "iso:country":"MX",
    "wof:name":"El Durazno",
    "wof:placetype":"locality",
    "wof:population":6
},
  "geometry": {"coordinates":[-101.08565,28.18969],"type":"Point"}
}