{
  "type": "Feature",
  "properties": {
    "gn:admin1_code":"6",
    "gn:admin2_code":"62.0",
    "gn:asciiname":"El Salgadeno",
    "gn:country_code":"MX",
    "gn:dem":1270,
    "gn:feature_class":"P",
    "gn:feature_code":"PPL",
    "gn:name":"El Salgade\u00f1o",
    "gn:population":0,
    "gn:timezone":"America/Chihuahua",
    "iso:country":"MX",
    "name:spa_x_preferred":[
        "El Salgade\u00f1o"
    ],
    "wof:name":"El Salgadeno",
    "wof:placetype":"locality"
},
  "geometry": {"coordinates":[-105.21974,28.26594],"type":"Point"}
}