{
  "type": "Feature",
  "properties": {
    "gn:admin1_code":"30",
    "gn:admin2_code":"109.0",
    "gn:asciiname":"Francisco I. Madero",
    "gn:country_code":"MX",
    "gn:dem":935,
    "gn:feature_class":"P",
    "gn:feature_code":"PPL",
    "gn:name":"Francisco I. Madero",
    "gn:population":152,
    "gn:timezone":"America/Mexico_City",
    "iso:country":"MX",
    "wof:name":"Francisco I. Madero",
    "wof:placetype":"locality",
    "wof:population":152
},
  "geometry": {"coordinates":[-96.89111,19.8175],"type":"Point"}
}