{
  "type": "Feature",
  "properties": {
    "gn:admin1_code":"22",
    "gn:admin2_code":"3.0",
    "gn:asciiname":"El Paso de los Alamos",
    "gn:country_code":"MX",
    "gn:dem":554,
    "gn:feature_class":"P",
    "gn:feature_code":"PPL",
    "gn:name":"El Paso de los \u00c1lamos",
    "gn:population":6,
    "gn:timezone":"America/Mexico_City",
    "iso:country":"MX",
    "wof:name":"El Paso de los Alamos",
    "wof:placetype":"locality",
    "wof:population":6
},
  "geometry": {"coordinates":[-99.64261,21.43844],"type":"Point"}
}