{
  "type": "Feature",
  "properties": {
    "gn:admin1_code":"23.0",
    "gn:asciiname":"Artemio Landaverde Trejo",
    "gn:country_code":"MX",
    "gn:dem":66,
    "gn:feature_class":"P",
    "gn:feature_code":"PPL",
    "gn:name":"Artemio Landaverde Trejo",
    "gn:population":0,
    "gn:timezone":"America/Cancun",
    "iso:country":"MX",
    "name:spa_x_preferred":[
        "Artemio Landaverde Trejo"
    ],
    "wof:name":"Artemio Landaverde Trejo",
    "wof:placetype":"locality"
},
  "geometry": {"coordinates":[-88.79571999999997,18.63941],"type":"Point"}
}