{
  "type": "Feature",
  "properties": {
    "gn:admin1_code":"20",
    "gn:admin2_code":"45.0",
    "gn:asciiname":"La Pena",
    "gn:country_code":"MX",
    "gn:dem":1668,
    "gn:feature_class":"P",
    "gn:feature_code":"PPL",
    "gn:name":"La Pe\u00f1a",
    "gn:population":71,
    "gn:timezone":"America/Mexico_City",
    "iso:country":"MX",
    "name:und_x_variant":[
        "La Pe\u00f1a"
    ],
    "wof:name":"La Pena",
    "wof:placetype":"locality",
    "wof:population":71
},
  "geometry": {"coordinates":[-96.82611,17.24722],"type":"Point"}
}