{
  "type": "Feature",
  "properties": {
    "gn:admin1_code":"27",
    "gn:admin2_code":"9.0",
    "gn:asciiname":"Chipilinar Tercera Seccion",
    "gn:country_code":"MX",
    "gn:dem":15,
    "gn:feature_class":"P",
    "gn:feature_code":"PPL",
    "gn:name":"Chipilinar Tercera Secci\u00f3n",
    "gn:population":0,
    "gn:timezone":"America/Mexico_City",
    "iso:country":"MX",
    "name:spa_x_preferred":[
        "Chipilinar"
    ],
    "name:spa_x_variant":[
        "Chipilinar Tercera Secci\u00f3n",
        "Chipilinal T\u00e9rcera Secci\u00f3n"
    ],
    "wof:name":"Chipilinar Tercera Seccion",
    "wof:placetype":"locality"
},
  "geometry": {"coordinates":[-92.76885,17.78274],"type":"Point"}
}