{
  "type": "Feature",
  "properties": {
    "gn:admin1_code":"26",
    "gn:admin2_code":"49.0",
    "gn:asciiname":"Tescalamas",
    "gn:country_code":"MX",
    "gn:dem":209,
    "gn:feature_class":"P",
    "gn:feature_code":"PPL",
    "gn:name":"Tescalamas",
    "gn:population":5,
    "gn:timezone":"America/Hermosillo",
    "iso:country":"MX",
    "wof:name":"Tescalamas",
    "wof:placetype":"locality",
    "wof:population":5
},
  "geometry": {"coordinates":[-109.21278,27.33333],"type":"Point"}
}