{
  "type": "Feature",
  "properties": {
    "gn:admin1_code":"5",
    "gn:admin2_code":"64.0",
    "gn:asciiname":"Cholol",
    "gn:country_code":"MX",
    "gn:dem":1780,
    "gn:feature_class":"P",
    "gn:feature_code":"PPL",
    "gn:name":"Cholol",
    "gn:population":0,
    "gn:timezone":"America/Mexico_City",
    "iso:country":"MX",
    "name:spa_x_preferred":[
        "Cholol"
    ],
    "wof:name":"Cholol",
    "wof:placetype":"locality"
},
  "geometry": {"coordinates":[-92.29894,16.81122],"type":"Point"}
}