{
  "type": "Feature",
  "properties": {
    "gn:admin1_code":"16",
    "gn:admin2_code":"16.0",
    "gn:asciiname":"Presa",
    "gn:country_code":"MX",
    "gn:dem":2109,
    "gn:feature_class":"P",
    "gn:feature_code":"PPL",
    "gn:name":"Presa",
    "gn:population":0,
    "gn:timezone":"America/Mexico_City",
    "iso:country":"MX",
    "wof:name":"Presa",
    "wof:placetype":"locality"
},
  "geometry": {"coordinates":[-101.65000000000001,19.75],"type":"Point"}
}