{
  "type": "Feature",
  "properties": {
    "gn:admin1_code":"11",
    "gn:admin2_code":"34",
    "gn:asciiname":"El Aguacate",
    "gn:country_code":"MX",
    "gn:dem":1756,
    "gn:feature_class":"P",
    "gn:feature_code":"PPL",
    "gn:name":"El Aguacate",
    "gn:population":24,
    "gn:timezone":"America/Mexico_City",
    "iso:country":"MX",
    "wof:name":"El Aguacate",
    "wof:placetype":"locality",
    "wof:population":24
},
  "geometry": {"coordinates":[-100.06389,21.17583],"type":"Point"}
}