{
  "type": "Feature",
  "properties": {
    "gn:admin1_code":"28",
    "gn:admin2_code":"32.0",
    "gn:asciiname":"Charco Redondo",
    "gn:country_code":"MX",
    "gn:dem":97,
    "gn:feature_class":"P",
    "gn:feature_code":"PPL",
    "gn:name":"Charco Redondo",
    "gn:population":0,
    "gn:timezone":"America/Monterrey",
    "iso:country":"MX",
    "name:spa_x_preferred":[
        "Charco Redondo"
    ],
    "name:und_x_variant":[
        "Los Pozos"
    ],
    "wof:name":"Charco Redondo",
    "wof:placetype":"locality"
},
  "geometry": {"coordinates":[-98.55121,25.91085],"type":"Point"}
}