{
  "type": "Feature",
  "properties": {
    "gn:admin1_code":"10.0",
    "gn:admin2_code":"14.0",
    "gn:asciiname":"Arroyo del Gavilancillo",
    "gn:country_code":"MX",
    "gn:dem":2053,
    "gn:feature_class":"P",
    "gn:feature_code":"PPL",
    "gn:name":"Arroyo del Gavilancillo",
    "gn:population":0,
    "gn:timezone":"America/Monterrey",
    "iso:country":"MX",
    "name:spa_x_preferred":[
        "Arroyo del Gavilancillo"
    ],
    "wof:name":"Arroyo del Gavilancillo",
    "wof:placetype":"locality"
},
  "geometry": {"coordinates":[-104.59999999999999,22.93797],"type":"Point"}
}