{
  "type": "Feature",
  "properties": {
    "gn:admin1_code":"7",
    "gn:admin2_code":"9",
    "gn:asciiname":"El Chaparro",
    "gn:country_code":"MX",
    "gn:dem":1099,
    "gn:feature_class":"P",
    "gn:feature_code":"PPL",
    "gn:name":"El Chaparro",
    "gn:population":31,
    "gn:timezone":"America/Monterrey",
    "iso:country":"MX",
    "wof:name":"El Chaparro",
    "wof:placetype":"locality",
    "wof:population":31
},
  "geometry": {"coordinates":[-103.33953,25.94694],"type":"Point"}
}