{
  "type": "Feature",
  "properties": {
    "gn:admin1_code":"6",
    "gn:admin2_code":"9",
    "gn:asciiname":"El Potrero",
    "gn:country_code":"MX",
    "gn:dem":2428,
    "gn:feature_class":"P",
    "gn:feature_code":"PPL",
    "gn:name":"El Potrero",
    "gn:population":15,
    "gn:timezone":"America/Chihuahua",
    "iso:country":"MX",
    "wof:name":"El Potrero",
    "wof:placetype":"locality",
    "wof:population":15
},
  "geometry": {"coordinates":[-107.78660000000001,27.85019],"type":"Point"}
}