{
  "type": "Feature",
  "properties": {
    "gn:admin1_code":"10",
    "gn:admin2_code":"4.0",
    "gn:asciiname":"El Crucero (Crucero Pedricena)",
    "gn:country_code":"MX",
    "gn:dem":1332,
    "gn:feature_class":"P",
    "gn:feature_code":"PPL",
    "gn:name":"El Crucero (Crucero Pedrice\u00f1a)",
    "gn:population":4,
    "gn:timezone":"America/Monterrey",
    "iso:country":"MX",
    "name:und_x_variant":[
        "El Crucero (Crucero Pedrice\u00f1a)"
    ],
    "wof:name":"El Crucero (Crucero Pedricena)",
    "wof:placetype":"locality",
    "wof:population":4
},
  "geometry": {"coordinates":[-103.77155999999999,25.0868],"type":"Point"}
}