{
  "type": "Feature",
  "properties": {
    "gn:admin1_code":"30",
    "gn:admin2_code":"189",
    "gn:asciiname":"Pedro Baltazar",
    "gn:country_code":"MX",
    "gn:dem":8,
    "gn:feature_class":"P",
    "gn:feature_code":"PPL",
    "gn:name":"Pedro Baltazar",
    "gn:population":18,
    "gn:timezone":"America/Mexico_City",
    "iso:country":"MX",
    "wof:name":"Pedro Baltazar",
    "wof:placetype":"locality",
    "wof:population":18
},
  "geometry": {"coordinates":[-97.39167,20.93722],"type":"Point"}
}