{
  "type": "Feature",
  "properties": {
    "gn:admin1_code":"20",
    "gn:admin2_code":"33.0",
    "gn:asciiname":"Paraje la Resurreccion",
    "gn:country_code":"MX",
    "gn:dem":1651,
    "gn:feature_class":"P",
    "gn:feature_code":"PPL",
    "gn:name":"Paraje la Resurrecci\u00f3n",
    "gn:population":108,
    "gn:timezone":"America/Mexico_City",
    "iso:country":"MX",
    "name:und_x_variant":[
        "Paraje la Resurrecci\u00f3n"
    ],
    "wof:name":"Paraje la Resurreccion",
    "wof:placetype":"locality",
    "wof:population":108
},
  "geometry": {"coordinates":[-96.79416999999999,17.1825],"type":"Point"}
}