{
  "type": "Feature",
  "properties": {
    "gn:admin1_code":"6",
    "gn:admin2_code":"7.0",
    "gn:asciiname":"Gueichinachi",
    "gn:country_code":"MX",
    "gn:dem":2079,
    "gn:feature_class":"P",
    "gn:feature_code":"PPL",
    "gn:name":"G\u00fcichinachi",
    "gn:population":5,
    "gn:timezone":"America/Chihuahua",
    "iso:country":"MX",
    "name:und_x_variant":[
        "G\u00fcichinachi"
    ],
    "wof:name":"Gueichinachi",
    "wof:placetype":"locality",
    "wof:population":5
},
  "geometry": {"coordinates":[-106.82778,26.61652],"type":"Point"}
}