{
  "type": "Feature",
  "properties": {
    "gn:admin1_code":"2",
    "gn:admin2_code":"2.0",
    "gn:asciiname":"La Ladrillera (Colonia Centinela)",
    "gn:country_code":"MX",
    "gn:dem":-6,
    "gn:feature_class":"P",
    "gn:feature_code":"PPL",
    "gn:name":"La Ladrillera (Colonia Centinela)",
    "gn:population":6,
    "gn:timezone":"America/Los_Angeles",
    "iso:country":"MX",
    "wof:name":"La Ladrillera (Colonia Centinela)",
    "wof:placetype":"locality",
    "wof:population":6
},
  "geometry": {"coordinates":[-115.59166999999999,32.65722],"type":"Point"}
}