{
  "type": "Feature",
  "properties": {
    "gn:admin1_code":"10.0",
    "gn:admin2_code":"9.0",
    "gn:asciiname":"San Jose de la Trampa",
    "gn:country_code":"MX",
    "gn:dem":2646,
    "gn:feature_class":"P",
    "gn:feature_code":"PPL",
    "gn:name":"San Jos\u00e9 de la Trampa",
    "gn:population":0,
    "gn:timezone":"America/Monterrey",
    "iso:country":"MX",
    "name:spa_x_preferred":[
        "San Jos\u00e9 de la Trampa"
    ],
    "wof:name":"San Jose de la Trampa",
    "wof:placetype":"locality"
},
  "geometry": {"coordinates":[-106.13523000000001,25.76017],"type":"Point"}
}