{
  "type": "Feature",
  "properties": {
    "gn:admin1_code":"1.0",
    "gn:asciiname":"Los Azulitos",
    "gn:country_code":"MX",
    "gn:dem":2058,
    "gn:feature_class":"P",
    "gn:feature_code":"PPL",
    "gn:name":"Los Azulitos",
    "gn:population":0,
    "gn:timezone":"America/Mexico_City",
    "iso:country":"MX",
    "wof:name":"Los Azulitos",
    "wof:placetype":"locality"
},
  "geometry": {"coordinates":[-101.04443999999999,21.85],"type":"Point"}
}