{
  "type": "Feature",
  "properties": {
    "gn:admin1_code":"11",
    "gn:admin2_code":"32",
    "gn:asciiname":"Las Liebres",
    "gn:country_code":"MX",
    "gn:dem":2053,
    "gn:feature_class":"P",
    "gn:feature_code":"PPL",
    "gn:name":"Las Liebres",
    "gn:population":9,
    "gn:timezone":"America/Mexico_City",
    "iso:country":"MX",
    "wof:name":"Las Liebres",
    "wof:placetype":"locality",
    "wof:population":9
},
  "geometry": {"coordinates":[-100.50722,21.07333],"type":"Point"}
}