{
  "type": "Feature",
  "properties": {
    "gn:admin1_code":"10",
    "gn:admin2_code":"5.0",
    "gn:asciiname":"La Perla (Salcido)",
    "gn:country_code":"MX",
    "gn:dem":1900,
    "gn:feature_class":"P",
    "gn:feature_code":"PPL",
    "gn:name":"La Perla (Salcido)",
    "gn:population":81,
    "gn:timezone":"America/Monterrey",
    "iso:country":"MX",
    "wof:name":"La Perla (Salcido)",
    "wof:placetype":"locality",
    "wof:population":81
},
  "geometry": {"coordinates":[-104.70833,24.21778],"type":"Point"}
}