{
  "type": "Feature",
  "properties": {
    "gn:admin1_code":"7.0",
    "gn:admin2_code":"5.0",
    "gn:asciiname":"San Francisco",
    "gn:country_code":"MX",
    "gn:dem":400,
    "gn:feature_class":"P",
    "gn:feature_code":"PPL",
    "gn:name":"San Francisco",
    "gn:population":1,
    "gn:timezone":"America/Monterrey",
    "iso:country":"MX",
    "name:spa_x_preferred":[
        "San Francisco"
    ],
    "wof:name":"San Francisco",
    "wof:placetype":"locality",
    "wof:population":1
},
  "geometry": {"coordinates":[-100.59941999999999,26.83455],"type":"Point"}
}