{
  "type": "Feature",
  "properties": {
    "gn:admin1_code":"25",
    "gn:admin2_code":"14",
    "gn:asciiname":"Quebrada Verde",
    "gn:country_code":"MX",
    "gn:dem":948,
    "gn:feature_class":"P",
    "gn:feature_code":"PPL",
    "gn:name":"Quebrada Verde",
    "gn:population":27,
    "gn:timezone":"America/Mazatlan",
    "iso:country":"MX",
    "wof:name":"Quebrada Verde",
    "wof:placetype":"locality",
    "wof:population":27
},
  "geometry": {"coordinates":[-105.76147,23.21764],"type":"Point"}
}