{
  "type": "Feature",
  "properties": {
    "gn:admin1_code":"14",
    "gn:admin2_code":"67",
    "gn:asciiname":"Carboneras",
    "gn:country_code":"MX",
    "gn:dem":145,
    "gn:feature_class":"P",
    "gn:feature_code":"PPL",
    "gn:name":"Carboneras",
    "gn:population":26,
    "gn:timezone":"America/Mexico_City",
    "iso:country":"MX",
    "name:ara_x_preferred":[
        "\u0643\u0627\u0631\u0628\u0648\u0646\u064a\u0631\u0627\u0633"
    ],
    "name:arg_x_preferred":[
        "Carboneras"
    ],
    "name:azb_x_preferred":[
        "\u06a9\u0627\u0631\u0628\u0648\u0646\u0631\u0627\u0633"
    ],
    "name:bul_x_preferred":[
        "\u041a\u0430\u0440\u0431\u043e\u043d\u0435\u0440\u0430\u0441"
    ],
    "name:cat_x_preferred":[
        "Carboneras"
    ],
    "name:ceb_x_preferred":[
        "Carboneras"
    ],
    "name:epo_x_preferred":[
        "Carboneras"
    ],
    "name:eus_x_preferred":[
        "Carboneras"
    ],
    "name:fas_x_preferred":[
        "\u06a9\u0627\u0631\u0628\u0648\u0646\u0631\u0627\u0633"
    ],
    "name:fra_x_preferred":[
        "Carboneras"
    ],
    "name:glg_x_preferred":[
        "Carboneras"
    ],
    "name:hat_x_preferred":[
        "Carboneras"
    ],
    "name:hun_x_preferred":[
        "Carboneras"
    ],
    "name:hye_x_preferred":[
        "\u053f\u0561\u0580\u0562\u0578\u0576\u0565\u0580\u0561\u057d"
    ],
    "name:ina_x_preferred":[
        "Carboneras"
    ],
    "name:ita_x_preferred":[
        "Carboneras"
    ],
    "name:mkd_x_preferred":[
        "\u041a\u0430\u0440\u0431\u043e\u043d\u0435\u0440\u0430\u0441"
    ],
    "name:msa_x_preferred":[
        "Carboneras"
    ],
    "name:nld_x_preferred":[
        "Carboneras"
    ],
    "name:oci_x_preferred":[
        "Carboneras"
    ],
    "name:pol_x_preferred":[
        "Carboneras"
    ],
    "name:por_x_preferred":[
        "Carboneras"
    ],
    "name:ron_x_preferred":[
        "Carboneras"
    ],
    "name:rus_x_preferred":[
        "\u041a\u0430\u0440\u0431\u043e\u043d\u0435\u0440\u0430\u0441"
    ],
    "name:spa_x_preferred":[
        "Carboneras"
    ],
    "name:swe_x_preferred":[
        "Carboneras"
    ],
    "name:tur_x_preferred":[
        "Carboneras"
    ],
    "name:ukr_x_preferred":[
        "\u041a\u0430\u0440\u0431\u043e\u043d\u0435\u0440\u0430\u0441"
    ],
    "name:uzb_x_preferred":[
        "Carboneras"
    ],
    "name:vie_x_preferred":[
        "Carboneras"
    ],
    "name:war_x_preferred":[
        "Carboneras"
    ],
    "name:zho_x_preferred":[
        "\u5361\u5c14\u6c83\u5185\u62c9\u65af"
    ],
    "wof:name":"Carboneras",
    "wof:placetype":"locality",
    "wof:population":26
},
  "geometry": {"coordinates":[-105.17917,20.67361],"type":"Point"}
}