{
  "type": "Feature",
  "properties": {
    "gn:admin1_code":"14",
    "gn:admin2_code":"67",
    "gn:asciiname":"Carboneras",
    "gn:country_code":"MX",
    "gn:dem":145,
    "gn:feature_class":"P",
    "gn:feature_code":"PPL",
    "gn:name":"Carboneras",
    "gn:population":26,
    "gn:timezone":"America/Mexico_City",
    "iso:country":"MX",
    "wof:name":"Carboneras",
    "wof:placetype":"locality",
    "wof:population":26
},
  "geometry": {"coordinates":[-105.17917,20.67361],"type":"Point"}
}