{
  "type": "Feature",
  "properties": {
    "gn:admin1_code":"5",
    "gn:admin2_code":"34.0",
    "gn:asciiname":"San Jose Montenegro",
    "gn:country_code":"MX",
    "gn:dem":682,
    "gn:feature_class":"P",
    "gn:feature_code":"PPL",
    "gn:name":"San Jos\u00e9 Montenegro",
    "gn:population":0,
    "gn:timezone":"America/Mexico_City",
    "iso:country":"MX",
    "name:spa_x_preferred":[
        "San Jos\u00e9 Montenegro"
    ],
    "wof:name":"San Jose Montenegro",
    "wof:placetype":"locality"
},
  "geometry": {"coordinates":[-92.00613,15.68075],"type":"Point"}
}