{
  "type": "Feature",
  "properties": {
    "gn:admin1_code":"26",
    "gn:admin2_code":"18.0",
    "gn:asciiname":"Los Alamitos",
    "gn:country_code":"MX",
    "gn:dem":49,
    "gn:feature_class":"P",
    "gn:feature_code":"PPL",
    "gn:name":"Los Alamitos",
    "gn:population":6,
    "gn:timezone":"America/Hermosillo",
    "iso:country":"MX",
    "name:ceb_x_preferred":[
        "Los Alamitos"
    ],
    "name:srp_x_preferred":[
        "\u041b\u043e\u0441 \u0410\u043b\u0430\u043c\u0438\u0442\u043e\u0441"
    ],
    "name:swe_x_preferred":[
        "Los Alamitos"
    ],
    "wof:name":"Los Alamitos",
    "wof:placetype":"locality",
    "wof:population":6
},
  "geometry": {"coordinates":[-109.8575,27.42361],"type":"Point"}
}