{
  "type": "Feature",
  "properties": {
    "gn:admin1_code":"26",
    "gn:admin2_code":"18.0",
    "gn:asciiname":"Los Alamitos",
    "gn:country_code":"MX",
    "gn:dem":49,
    "gn:feature_class":"P",
    "gn:feature_code":"PPL",
    "gn:name":"Los Alamitos",
    "gn:population":6,
    "gn:timezone":"America/Hermosillo",
    "iso:country":"MX",
    "wof:name":"Los Alamitos",
    "wof:placetype":"locality",
    "wof:population":6
},
  "geometry": {"coordinates":[-109.8575,27.42361],"type":"Point"}
}