{
  "type": "Feature",
  "properties": {
    "gn:admin1_code":"5.0",
    "gn:admin2_code":"89.0",
    "gn:asciiname":"Nuevo Tesoro",
    "gn:country_code":"MX",
    "gn:dem":21,
    "gn:feature_class":"P",
    "gn:feature_code":"PPL",
    "gn:name":"Nuevo Tesoro",
    "gn:population":0,
    "gn:timezone":"America/Mexico_City",
    "iso:country":"MX",
    "name:spa_x_preferred":[
        "Nuevo Tesoro"
    ],
    "wof:name":"Nuevo Tesoro",
    "wof:placetype":"locality"
},
  "geometry": {"coordinates":[-92.33381,14.72449],"type":"Point"}
}