{
  "type": "Feature",
  "properties": {
    "gn:admin1_code":"30.0",
    "gn:admin2_code":"27.0",
    "gn:asciiname":"Coyoltzintla",
    "gn:country_code":"MX",
    "gn:dem":373,
    "gn:feature_class":"P",
    "gn:feature_code":"PPL",
    "gn:name":"Coyoltzintla",
    "gn:population":0,
    "gn:timezone":"America/Mexico_City",
    "iso:country":"MX",
    "name:spa_x_preferred":[
        "Coyoltzintla"
    ],
    "wof:name":"Coyoltzintla",
    "wof:placetype":"locality"
},
  "geometry": {"coordinates":[-98.17621,20.74358],"type":"Point"}
}