{
  "type": "Feature",
  "properties": {
    "gn:admin1_code":"16",
    "gn:admin2_code":"49",
    "gn:asciiname":"Cuindora",
    "gn:country_code":"MX",
    "gn:dem":1019,
    "gn:feature_class":"P",
    "gn:feature_code":"PPL",
    "gn:name":"Cuindora",
    "gn:population":45,
    "gn:timezone":"America/Mexico_City",
    "iso:country":"MX",
    "wof:name":"Cuindora",
    "wof:placetype":"locality",
    "wof:population":45
},
  "geometry": {"coordinates":[-101.12361,19.21889],"type":"Point"}
}