{
  "type": "Feature",
  "properties": {
    "gn:admin1_code":"1",
    "gn:admin2_code":"1",
    "gn:asciiname":"La Laguna [Granja]",
    "gn:country_code":"MX",
    "gn:dem":1873,
    "gn:feature_class":"P",
    "gn:feature_code":"PPL",
    "gn:name":"La Laguna [Granja]",
    "gn:population":9,
    "gn:timezone":"America/Mexico_City",
    "iso:country":"MX",
    "wof:name":"La Laguna [Granja]",
    "wof:placetype":"locality",
    "wof:population":9
},
  "geometry": {"coordinates":[-102.33806,21.89028],"type":"Point"}
}