{
  "type": "Feature",
  "properties": {
    "gn:admin1_code":"5",
    "gn:admin2_code":"65.0",
    "gn:asciiname":"Nezahualcoyotl",
    "gn:country_code":"MX",
    "gn:dem":198,
    "gn:feature_class":"P",
    "gn:feature_code":"PPL",
    "gn:name":"Nezahualc\u00f3yotl",
    "gn:population":0,
    "gn:timezone":"America/Mexico_City",
    "iso:country":"MX",
    "name:ara_x_preferred":[
        "\u0646\u064a\u0632\u0627\u0647\u0648\u0627\u0644 \u0643\u0648\u064a\u0648\u062a\u0644"
    ],
    "name:ben_x_preferred":[
        "\u09a8\u09c7\u099c\u09be\u09b9\u09c1\u09df\u09be\u09b2\u0995\u09cb\u09df\u09cb\u09a4\u09cb"
    ],
    "name:ces_x_preferred":[
        "Nezahualc\u00f3yotl"
    ],
    "name:deu_x_preferred":[
        "Nezahualc\u00f3yotl"
    ],
    "name:heb_x_preferred":[
        "\u05e0\u05d6\u05d7\u05d5\u05d0\u05dc\u05e7\u05d5\u05d9\u05d9\u05d5\u05d8\u05dc"
    ],
    "name:hin_x_preferred":[
        "\u0928\u0947\u091c\u093e\u0939\u0941\u0906\u0932\u0915\u094b\u092f\u094b\u0932"
    ],
    "name:hun_x_preferred":[
        "Nezahualc\u00f3yotl"
    ],
    "name:ind_x_preferred":[
        "Nezahualc\u00f3yotl"
    ],
    "name:ita_x_preferred":[
        "Nezahualc\u00f3yotl"
    ],
    "name:pol_x_preferred":[
        "Nezahualcoyotl"
    ],
    "name:rus_x_preferred":[
        "\u041d\u0435\u0441\u0430\u0443\u0430\u043b\u044c\u043a\u043e\u0439\u043e\u0442\u043b\u044c"
    ],
    "name:spa_x_preferred":[
        "Nezahualc\u00f3yotl"
    ],
    "name:ukr_x_preferred":[
        "\u041d\u0435\u0441\u0430\u0443\u0430\u043b\u044c\u043a\u043e\u0439\u043e\u0442\u043b\u044c"
    ],
    "name:vie_x_preferred":[
        "Nezahualc\u00f3yotl"
    ],
    "wof:name":"Nezahualcoyotl",
    "wof:placetype":"locality"
},
  "geometry": {"coordinates":[-91.45559,17.25375],"type":"Point"}
}