{
  "type": "Feature",
  "properties": {
    "gn:admin1_code":"5",
    "gn:admin2_code":"65.0",
    "gn:asciiname":"Nezahualcoyotl",
    "gn:country_code":"MX",
    "gn:dem":198,
    "gn:feature_class":"P",
    "gn:feature_code":"PPL",
    "gn:name":"Nezahualc\u00f3yotl",
    "gn:population":0,
    "gn:timezone":"America/Mexico_City",
    "iso:country":"MX",
    "wof:name":"Nezahualcoyotl",
    "wof:placetype":"locality"
},
  "geometry": {"coordinates":[-91.45559,17.25375],"type":"Point"}
}