{
  "type": "Feature",
  "properties": {
    "gn:admin1_code":"24",
    "gn:admin2_code":"58.0",
    "gn:asciiname":"Abraham Garcia",
    "gn:country_code":"MX",
    "gn:dem":282,
    "gn:feature_class":"P",
    "gn:feature_code":"PPL",
    "gn:name":"Abraham Garc\u00eda",
    "gn:population":5,
    "gn:timezone":"America/Mexico_City",
    "iso:country":"MX",
    "name:und_x_variant":[
        "Abraham Garc\u00eda"
    ],
    "wof:name":"Abraham Garcia",
    "wof:placetype":"locality",
    "wof:population":5
},
  "geometry": {"coordinates":[-99.33638999999999,22.52694],"type":"Point"}
}