{
  "type": "Feature",
  "properties": {
    "gn:admin1_code":"19",
    "gn:admin2_code":"45.0",
    "gn:asciiname":"Roquin",
    "gn:country_code":"MX",
    "gn:dem":466,
    "gn:feature_class":"P",
    "gn:feature_code":"PPL",
    "gn:name":"Roqu\u00edn",
    "gn:population":5,
    "gn:timezone":"America/Monterrey",
    "iso:country":"MX",
    "name:und_x_variant":[
        "Roqu\u00edn"
    ],
    "wof:name":"Roquin",
    "wof:placetype":"locality",
    "wof:population":5
},
  "geometry": {"coordinates":[-100.30337,26.02255],"type":"Point"}
}