{
  "type": "Feature",
  "properties": {
    "gn:admin1_code":"29",
    "gn:admin2_code":"34.0",
    "gn:asciiname":"San Baltazar",
    "gn:country_code":"MX",
    "gn:dem":2498,
    "gn:feature_class":"P",
    "gn:feature_code":"PPL",
    "gn:name":"San Baltazar",
    "gn:population":6,
    "gn:timezone":"America/Mexico_City",
    "iso:country":"MX",
    "name:spa_x_preferred":[
        "San Baltazar"
    ],
    "name:und_x_variant":[
        "San Baltzar"
    ],
    "wof:name":"San Baltazar",
    "wof:placetype":"locality",
    "wof:population":6
},
  "geometry": {"coordinates":[-98.15425999999999,19.57731],"type":"Point"}
}