{
  "type": "Feature",
  "properties": {
    "gn:admin1_code":"21",
    "gn:admin2_code":"217.0",
    "gn:asciiname":"Zoquitlanzacualco",
    "gn:country_code":"MX",
    "gn:dem":2187,
    "gn:feature_class":"P",
    "gn:feature_code":"PPL",
    "gn:name":"Zoquitlanzacualco",
    "gn:population":517,
    "gn:timezone":"America/Mexico_City",
    "iso:country":"MX",
    "wof:name":"Zoquitlanzacualco",
    "wof:placetype":"locality",
    "wof:population":517
},
  "geometry": {"coordinates":[-97.03333000000001,18.32806],"type":"Point"}
}