{
  "type": "Feature",
  "properties": {
    "gn:admin1_code":"14",
    "gn:admin2_code":"15",
    "gn:asciiname":"Los Pozos",
    "gn:country_code":"MX",
    "gn:dem":1770,
    "gn:feature_class":"P",
    "gn:feature_code":"PPL",
    "gn:name":"Los Pozos",
    "gn:population":42,
    "gn:timezone":"America/Mexico_City",
    "iso:country":"MX",
    "wof:name":"Los Pozos",
    "wof:placetype":"locality",
    "wof:population":42
},
  "geometry": {"coordinates":[-104.37194,19.85361],"type":"Point"}
}