{
  "type": "Feature",
  "properties": {
    "gn:admin1_code":"21",
    "gn:admin2_code":"186.0",
    "gn:asciiname":"Macuicuila",
    "gn:country_code":"MX",
    "gn:dem":1143,
    "gn:feature_class":"P",
    "gn:feature_code":"PPL",
    "gn:name":"Macuicuila",
    "gn:population":0,
    "gn:timezone":"America/Mexico_City",
    "iso:country":"MX",
    "name:spa_x_preferred":[
        "Macuicuila"
    ],
    "wof:name":"Macuicuila",
    "wof:placetype":"locality"
},
  "geometry": {"coordinates":[-97.46765000000001,19.95175],"type":"Point"}
}