{
  "type": "Feature",
  "properties": {
    "gn:admin1_code":"30",
    "gn:admin2_code":"83.0",
    "gn:asciiname":"Paso de Alamo",
    "gn:country_code":"MX",
    "gn:dem":75,
    "gn:feature_class":"P",
    "gn:feature_code":"PPL",
    "gn:name":"Paso de \u00c1lamo",
    "gn:population":55,
    "gn:timezone":"America/Mexico_City",
    "iso:country":"MX",
    "name:spa_x_preferred":[
        "Paso de \u00c1lamo"
    ],
    "wof:name":"Paso de Alamo",
    "wof:placetype":"locality",
    "wof:population":55
},
  "geometry": {"coordinates":[-97.88889,20.85167],"type":"Point"}
}