{
  "type": "Feature",
  "properties": {
    "gn:admin1_code":"5.0",
    "gn:asciiname":"Las Camelias",
    "gn:country_code":"MX",
    "gn:dem":964,
    "gn:feature_class":"P",
    "gn:feature_code":"PPL",
    "gn:name":"Las Camelias",
    "gn:population":0,
    "gn:timezone":"America/Mexico_City",
    "iso:country":"MX",
    "name:spa_x_preferred":[
        "Las Camelias"
    ],
    "wof:name":"Las Camelias",
    "wof:placetype":"locality"
},
  "geometry": {"coordinates":[-93.38905,15.98396],"type":"Point"}
}