{
  "type": "Feature",
  "properties": {
    "gn:admin1_code":"12",
    "gn:admin2_code":"48.0",
    "gn:asciiname":"El Habillal",
    "gn:country_code":"MX",
    "gn:dem":139,
    "gn:feature_class":"P",
    "gn:feature_code":"PPL",
    "gn:name":"El Habillal",
    "gn:population":8,
    "gn:timezone":"America/Mexico_City",
    "iso:country":"MX",
    "wof:name":"El Habillal",
    "wof:placetype":"locality",
    "wof:population":8
},
  "geometry": {"coordinates":[-101.19132999999999,17.58044],"type":"Point"}
}