{
  "type": "Feature",
  "properties": {
    "iso:country":"MX",
    "name:por_x_preferred":[
        "Enga\u00f1ada"
    ],
    "name:spa_x_preferred":[
        "Hacienda Santa Teresa",
        "Enga\u00f1ada"
    ],
    "name:unk_x_variant":[
        "Hacienda Santa Teresa"
    ],
    "qs:gn_adm0_cc":"MX",
    "qs:gn_local":3530757,
    "qs:gn_nam_loc":"cholula",
    "qs:gn_namadm1":"21",
    "qs:local_max":137,
    "qs:local_sum":404,
    "qs:localhoods":5,
    "qs:name":"Hacienda Santa Teresa",
    "qs:name_adm0":"M\u00e9xico",
    "qs:name_adm1":"Puebla",
    "qs:name_adm2":"San Andres Cholula",
    "qs:name_local":"Cholula",
    "qs:photo_max":100,
    "qs:photo_sum":134,
    "qs:placetype":"Suburb",
    "qs:quad_count":7,
    "qs:woe_adm0":23424900,
    "qs:woe_adm1":2346284,
    "qs:woe_adm2":12601346,
    "qs:woe_lau":0,
    "qs:woe_local":116182,
    "qs:woe_ver":"7.10.0",
    "wof:lang":[
        "spa"
    ],
    "wof:name":"Hacienda Santa Teresa",
    "wof:placetype":"neighbourhood"
},
  "geometry": {"coordinates":[-98.284961,19.055637],"type":"Point"}
}