{
  "type": "Feature",
  "properties": {
    "gn:admin1_code":"7.0",
    "gn:admin2_code":"30.0",
    "gn:asciiname":"El Sauz",
    "gn:country_code":"MX",
    "gn:dem":1606,
    "gn:feature_class":"P",
    "gn:feature_code":"PPL",
    "gn:name":"El S\u00e1uz",
    "gn:population":22,
    "gn:timezone":"America/Monterrey",
    "iso:country":"MX",
    "name:spa_x_preferred":[
        "El S\u00e1uz"
    ],
    "wof:name":"El Sauz",
    "wof:placetype":"locality",
    "wof:population":22
},
  "geometry": {"coordinates":[-101.21493,25.42015],"type":"Point"}
}