{
  "type": "Feature",
  "properties": {
    "gn:admin1_code":"10",
    "gn:admin2_code":"5",
    "gn:asciiname":"El Porvenir",
    "gn:country_code":"MX",
    "gn:dem":1862,
    "gn:feature_class":"P",
    "gn:feature_code":"PPL",
    "gn:name":"El Porvenir",
    "gn:population":15,
    "gn:timezone":"America/Monterrey",
    "iso:country":"MX",
    "wof:name":"El Porvenir",
    "wof:placetype":"locality",
    "wof:population":15
},
  "geometry": {"coordinates":[-104.49946,24.1439],"type":"Point"}
}