{
  "type": "Feature",
  "properties": {
    "gn:admin1_code":"32",
    "gn:admin2_code":"22.0",
    "gn:asciiname":"Los Garcia",
    "gn:country_code":"MX",
    "gn:dem":1956,
    "gn:feature_class":"P",
    "gn:feature_code":"PPL",
    "gn:name":"Los Garc\u00eda",
    "gn:population":0,
    "gn:timezone":"America/Mexico_City",
    "iso:country":"MX",
    "name:spa_x_preferred":[
        "Los Garc\u00eda"
    ],
    "name:und_x_variant":[
        "Rancho Los Garc\u00edas"
    ],
    "wof:name":"Los Garcia",
    "wof:placetype":"locality"
},
  "geometry": {"coordinates":[-103.41115000000001,24.31594],"type":"Point"}
}