{
  "type": "Feature",
  "properties": {
    "gn:admin1_code":"6",
    "gn:admin2_code":"45.0",
    "gn:asciiname":"Granja el Indio (Rancho de Jesus Terrazas)",
    "gn:country_code":"MX",
    "gn:dem":1152,
    "gn:feature_class":"P",
    "gn:feature_code":"PPL",
    "gn:name":"Granja el Indio (Rancho de Jes\u00fas Terrazas)",
    "gn:population":4,
    "gn:timezone":"America/Chihuahua",
    "iso:country":"MX",
    "name:und_x_variant":[
        "Granja el Indio (Rancho de Jes\u00fas Terrazas)"
    ],
    "wof:name":"Granja el Indio (Rancho de Jesus Terrazas)",
    "wof:placetype":"locality",
    "wof:population":4
},
  "geometry": {"coordinates":[-105.46575,28.24298],"type":"Point"}
}