{
  "type": "Feature",
  "properties": {
    "gn:admin1_code":"4.0",
    "gn:asciiname":"San Miguelito",
    "gn:country_code":"MX",
    "gn:dem":31,
    "gn:feature_class":"P",
    "gn:feature_code":"PPL",
    "gn:name":"San Miguelito",
    "gn:population":0,
    "gn:timezone":"America/Merida",
    "iso:country":"MX",
    "name:ceb_x_preferred":[
        "San Miguelito"
    ],
    "name:deu_x_preferred":[
        "San Miguelito"
    ],
    "name:ita_x_preferred":[
        "San Miguelito"
    ],
    "name:nld_x_preferred":[
        "San Miguelito"
    ],
    "name:pol_x_preferred":[
        "San Miguelito"
    ],
    "name:spa_x_preferred":[
        "San Miguelito"
    ],
    "name:swe_x_preferred":[
        "San Miguelito"
    ],
    "wof:name":"San Miguelito",
    "wof:placetype":"locality"
},
  "geometry": {"coordinates":[-90.57759,18.97033],"type":"Point"}
}