{
  "type": "Feature",
  "properties": {
    "gn:admin1_code":"28.0",
    "gn:admin2_code":"16.0",
    "gn:asciiname":"La Barrerita",
    "gn:country_code":"MX",
    "gn:dem":320,
    "gn:feature_class":"P",
    "gn:feature_code":"PPL",
    "gn:name":"La Barrerita",
    "gn:population":0,
    "gn:timezone":"America/Monterrey",
    "iso:country":"MX",
    "name:spa_x_preferred":[
        "La Barrerita"
    ],
    "wof:name":"La Barrerita",
    "wof:placetype":"locality"
},
  "geometry": {"coordinates":[-99.41584,24.23101],"type":"Point"}
}