{
  "type": "Feature",
  "properties": {
    "gn:admin1_code":"7",
    "gn:admin2_code":"33.0",
    "gn:asciiname":"Allende",
    "gn:country_code":"MX",
    "gn:dem":1100,
    "gn:feature_class":"P",
    "gn:feature_code":"PPL",
    "gn:name":"Allende",
    "gn:population":6,
    "gn:timezone":"America/Monterrey",
    "iso:country":"MX",
    "name:bel_x_preferred":[
        "\u0410\u043b\u044c\u0435\u043d\u0434\u044d"
    ],
    "name:cat_x_preferred":[
        "Allende"
    ],
    "name:ceb_x_preferred":[
        "Allende"
    ],
    "name:ces_x_preferred":[
        "Allende"
    ],
    "name:deu_x_preferred":[
        "Allende"
    ],
    "name:epo_x_preferred":[
        "Allende"
    ],
    "name:fas_x_preferred":[
        "\u0622\u0644\u0646\u062f\u0647"
    ],
    "name:fin_x_preferred":[
        "Allende"
    ],
    "name:fra_x_preferred":[
        "Allende"
    ],
    "name:heb_x_preferred":[
        "\u05d0\u05d9\u05d9\u05e0\u05d3\u05d4"
    ],
    "name:ita_x_preferred":[
        "Allende"
    ],
    "name:jpn_x_preferred":[
        "\u30a2\u30b8\u30a7\u30f3\u30c7"
    ],
    "name:kor_x_preferred":[
        "\uc544\uc60c\ub370"
    ],
    "name:nds_x_preferred":[
        "Allende"
    ],
    "name:nld_x_preferred":[
        "Allende"
    ],
    "name:pol_x_preferred":[
        "Allende"
    ],
    "name:por_x_preferred":[
        "Allende"
    ],
    "name:rus_x_preferred":[
        "\u0410\u043b\u044c\u0435\u043d\u0434\u0435"
    ],
    "name:sco_x_preferred":[
        "Allende"
    ],
    "name:slk_x_preferred":[
        "Allende"
    ],
    "name:slv_x_preferred":[
        "Allende"
    ],
    "name:spa_x_preferred":[
        "Allende"
    ],
    "name:swe_x_preferred":[
        "Allende"
    ],
    "name:tur_x_preferred":[
        "Allende"
    ],
    "name:ukr_x_preferred":[
        "\u0410\u043b\u044c\u0454\u043d\u0434\u0435"
    ],
    "name:vie_x_preferred":[
        "Allende"
    ],
    "wof:name":"Allende",
    "wof:placetype":"locality",
    "wof:population":6
},
  "geometry": {"coordinates":[-102.92729,25.69555],"type":"Point"}
}