{
  "type": "Feature",
  "properties": {
    "gn:admin1_code":"31",
    "gn:admin2_code":"96.0",
    "gn:asciiname":"San Matias",
    "gn:country_code":"MX",
    "gn:dem":17,
    "gn:feature_class":"P",
    "gn:feature_code":"PPL",
    "gn:name":"San Mat\u00edas",
    "gn:population":0,
    "gn:timezone":"America/Merida",
    "iso:country":"MX",
    "name:ara_x_preferred":[
        "\u0633\u0627\u0646 \u0645\u0627\u062a\u064a\u0627\u0633"
    ],
    "name:ben_x_preferred":[
        "\u09b8\u09be\u09a8 \u09ae\u09be\u09a4\u09bf\u09df\u09be\u09b8"
    ],
    "name:ell_x_preferred":[
        "\u03a3\u03b1\u03bd \u039c\u03b1\u03c4\u03af\u03b1\u03c2"
    ],
    "name:fas_x_preferred":[
        "\u0633\u0627\u0646 \u0645\u0627\u062a\u06cc\u0627\u0633"
    ],
    "name:heb_x_preferred":[
        "\u05e1\u05df \u05de\u05ea\u05d9\u05d0\u05e1"
    ],
    "name:hin_x_preferred":[
        "\u0938\u0948\u0928 \u092e\u093e\u091f\u093f\u092f\u093e\u0938"
    ],
    "name:hun_x_preferred":[
        "San Matias"
    ],
    "name:ind_x_preferred":[
        "San Matias"
    ],
    "name:ita_x_preferred":[
        "San Mat\u00edas"
    ],
    "name:jpn_x_preferred":[
        "\u30b5\u30f3\u30de\u30c6\u30a3\u30a2\u30b9"
    ],
    "name:kor_x_preferred":[
        "\uc0b0 \ub9c8\ud2f0\uc544\uc2a4"
    ],
    "name:rus_x_preferred":[
        "\u0421\u0430\u043d-\u041c\u0430\u0442\u0438\u0430\u0441"
    ],
    "name:swe_x_preferred":[
        "San Matias"
    ],
    "name:tur_x_preferred":[
        "San Matias"
    ],
    "name:ukr_x_preferred":[
        "\u0421\u0430\u043d-\u041c\u0430\u0442\u0456\u0430\u0441"
    ],
    "name:urd_x_preferred":[
        "\u0633\u0627\u0646 \u0645\u06cc\u0679\u06cc\u0627\u0633"
    ],
    "name:vie_x_preferred":[
        "San Matias"
    ],
    "wof:name":"San Matias",
    "wof:placetype":"locality"
},
  "geometry": {"coordinates":[-87.77123,21.14345],"type":"Point"}
}