{
  "type": "Feature",
  "properties": {
    "gn:admin1_code":"5",
    "gn:admin2_code":"59.0",
    "gn:asciiname":"Los Limares",
    "gn:country_code":"MX",
    "gn:dem":1445,
    "gn:feature_class":"P",
    "gn:feature_code":"PPL",
    "gn:name":"Los Limares",
    "gn:population":151,
    "gn:timezone":"America/Mexico_City",
    "iso:country":"MX",
    "wof:name":"Los Limares",
    "wof:placetype":"locality",
    "wof:population":151
},
  "geometry": {"coordinates":[-92.19806,16.84417],"type":"Point"}
}