{
  "type": "Feature",
  "properties": {
    "gn:admin1_code":"5",
    "gn:admin2_code":"1",
    "gn:asciiname":"Viejo Soconusco",
    "gn:country_code":"MX",
    "gn:dem":183,
    "gn:feature_class":"P",
    "gn:feature_code":"PPL",
    "gn:name":"Viejo Soconusco",
    "gn:population":32,
    "gn:timezone":"America/Mexico_City",
    "iso:country":"MX",
    "wof:name":"Viejo Soconusco",
    "wof:placetype":"locality",
    "wof:population":32
},
  "geometry": {"coordinates":[-92.68277999999999,15.37472],"type":"Point"}
}