{
  "type": "Feature",
  "properties": {
    "gn:admin1_code":"20",
    "gn:admin2_code":"151.0",
    "gn:asciiname":"Loma Larga (Rancho Aquilino Mendoza)",
    "gn:country_code":"MX",
    "gn:dem":2292,
    "gn:feature_class":"P",
    "gn:feature_code":"PPL",
    "gn:name":"Loma Larga (Rancho Aquilino Mendoza)",
    "gn:population":5,
    "gn:timezone":"America/Mexico_City",
    "iso:country":"MX",
    "wof:name":"Loma Larga (Rancho Aquilino Mendoza)",
    "wof:placetype":"locality",
    "wof:population":5
},
  "geometry": {"coordinates":[-97.50139,17.84917],"type":"Point"}
}