{
  "type": "Feature",
  "properties": {
    "gn:admin1_code":"6.0",
    "gn:admin2_code":"15.0",
    "gn:asciiname":"La Boquillita",
    "gn:country_code":"MX",
    "gn:dem":1165,
    "gn:feature_class":"P",
    "gn:feature_code":"PPL",
    "gn:name":"La Boquillita",
    "gn:population":2,
    "gn:timezone":"America/Chihuahua",
    "iso:country":"MX",
    "name:spa_x_preferred":[
        "La Boquillita"
    ],
    "wof:name":"La Boquillita",
    "wof:placetype":"locality",
    "wof:population":2
},
  "geometry": {"coordinates":[-105.11216,29.34212],"type":"Point"}
}