{
  "type": "Feature",
  "properties": {
    "gn:admin1_code":"21.0",
    "gn:admin2_code":"83.0",
    "gn:asciiname":"Canoas",
    "gn:country_code":"MX",
    "gn:dem":2855,
    "gn:feature_class":"P",
    "gn:feature_code":"PPL",
    "gn:name":"Canoas",
    "gn:population":0,
    "gn:timezone":"America/Mexico_City",
    "iso:country":"MX",
    "name:spa_x_preferred":[
        "Canoas"
    ],
    "wof:name":"Canoas",
    "wof:placetype":"locality"
},
  "geometry": {"coordinates":[-97.84564,19.5836],"type":"Point"}
}