{
  "type": "Feature",
  "properties": {
    "gn:admin1_code":"21.0",
    "gn:admin2_code":"83.0",
    "gn:asciiname":"Canoas",
    "gn:country_code":"MX",
    "gn:dem":2855,
    "gn:feature_class":"P",
    "gn:feature_code":"PPL",
    "gn:name":"Canoas",
    "gn:population":0,
    "gn:timezone":"America/Mexico_City",
    "iso:country":"MX",
    "name:ara_x_preferred":[
        "\u0643\u0627\u0646\u0648\u0627\u0633"
    ],
    "name:bpy_x_preferred":[
        "\u0995\u09be\u09a8\u09cb\u09af\u09bc\u09be\u09b8"
    ],
    "name:bre_x_preferred":[
        "Canoas"
    ],
    "name:bul_x_preferred":[
        "\u041a\u0430\u043d\u043e\u0430\u0441"
    ],
    "name:cat_x_preferred":[
        "Canoas"
    ],
    "name:deu_x_preferred":[
        "Canoas"
    ],
    "name:epo_x_preferred":[
        "Canoas"
    ],
    "name:est_x_preferred":[
        "Canoas"
    ],
    "name:eus_x_preferred":[
        "Canoas"
    ],
    "name:fas_x_preferred":[
        "\u06a9\u0627\u0646\u0648\u0627\u0633"
    ],
    "name:fin_x_preferred":[
        "Canoas"
    ],
    "name:fra_x_preferred":[
        "Canoas"
    ],
    "name:glg_x_preferred":[
        "Canoas"
    ],
    "name:grn_x_preferred":[
        "Canoas"
    ],
    "name:hak_x_preferred":[
        "Canoas"
    ],
    "name:ido_x_preferred":[
        "Canoas"
    ],
    "name:ita_x_preferred":[
        "Canoas"
    ],
    "name:jpn_x_preferred":[
        "\u30ab\u30ce\u30a2\u30b9"
    ],
    "name:kaz_x_preferred":[
        "\u041a\u0430\u043d\u043e\u0430\u0441"
    ],
    "name:kor_x_preferred":[
        "\uce74\ub178\uc544\uc2a4"
    ],
    "name:lit_x_preferred":[
        "Kanoasas"
    ],
    "name:mlg_x_preferred":[
        "Canoas"
    ],
    "name:nor_x_preferred":[
        "Canoas"
    ],
    "name:oci_x_preferred":[
        "Canoas"
    ],
    "name:pol_x_preferred":[
        "Canoas"
    ],
    "name:por_x_preferred":[
        "Canoas"
    ],
    "name:ron_x_preferred":[
        "Canoas"
    ],
    "name:rus_x_preferred":[
        "\u041a\u0430\u043d\u043e\u0430\u0441"
    ],
    "name:spa_x_preferred":[
        "Canoas"
    ],
    "name:srp_x_preferred":[
        "\u041a\u0430\u043d\u043e\u0430\u0441"
    ],
    "name:swe_x_preferred":[
        "Canoas"
    ],
    "name:szl_x_preferred":[
        "Canoas"
    ],
    "name:tat_x_preferred":[
        "\u041a\u0430\u043d\u043e\u0430\u0441"
    ],
    "name:vie_x_preferred":[
        "Canoas"
    ],
    "name:vol_x_preferred":[
        "Canoas"
    ],
    "name:war_x_preferred":[
        "Canoas"
    ],
    "name:zho_x_preferred":[
        "\u5361\u8afe\u963f\u65af"
    ],
    "wof:name":"Canoas",
    "wof:placetype":"locality"
},
  "geometry": {"coordinates":[-97.84564,19.5836],"type":"Point"}
}