{
  "type": "Feature",
  "properties": {
    "gn:admin1_code":"15.0",
    "gn:admin2_code":"124.0",
    "gn:asciiname":"San Francisco la Loma",
    "gn:country_code":"MX",
    "gn:dem":2716,
    "gn:feature_class":"P",
    "gn:feature_code":"PPL",
    "gn:name":"San Francisco la Loma",
    "gn:population":0,
    "gn:timezone":"America/Mexico_City",
    "iso:country":"MX",
    "name:spa_x_preferred":[
        "San Francisco la Loma"
    ],
    "wof:name":"San Francisco la Loma",
    "wof:placetype":"locality"
},
  "geometry": {"coordinates":[-100.08459999999999,19.69021],"type":"Point"}
}