{
  "type": "Feature",
  "properties": {
    "gn:admin1_code":"6",
    "gn:admin2_code":"8.0",
    "gn:asciiname":"La Sierrita de Barraza",
    "gn:country_code":"MX",
    "gn:dem":1514,
    "gn:feature_class":"P",
    "gn:feature_code":"PPL",
    "gn:name":"La Sierrita de Barraza",
    "gn:population":0,
    "gn:timezone":"America/Chihuahua",
    "iso:country":"MX",
    "name:spa_x_preferred":[
        "Rancher\u00eda Casa Quemada"
    ],
    "name:spa_x_variant":[
        "La Sierrita de Barraza"
    ],
    "wof:name":"La Sierrita de Barraza",
    "wof:placetype":"locality"
},
  "geometry": {"coordinates":[-107.83427,26.68857],"type":"Point"}
}