{
  "type": "Feature",
  "properties": {
    "gn:admin1_code":"6",
    "gn:admin2_code":"65.0",
    "gn:asciiname":"Ralogopana",
    "gn:country_code":"MX",
    "gn:dem":1978,
    "gn:feature_class":"P",
    "gn:feature_code":"PPL",
    "gn:name":"Ralogopana",
    "gn:population":4,
    "gn:timezone":"America/Chihuahua",
    "iso:country":"MX",
    "wof:name":"Ralogopana",
    "wof:placetype":"locality",
    "wof:population":4
},
  "geometry": {"coordinates":[-107.83242,27.45659],"type":"Point"}
}