{
  "type": "Feature",
  "properties": {
    "gn:admin1_code":"10",
    "gn:admin2_code":"5.0",
    "gn:asciiname":"La Moneda",
    "gn:country_code":"MX",
    "gn:dem":2274,
    "gn:feature_class":"P",
    "gn:feature_code":"PPL",
    "gn:name":"La Moneda",
    "gn:population":0,
    "gn:timezone":"America/Monterrey",
    "iso:country":"MX",
    "name:spa_x_preferred":[
        "La Moneda"
    ],
    "wof:name":"La Moneda",
    "wof:placetype":"locality"
},
  "geometry": {"coordinates":[-104.94949,23.92375],"type":"Point"}
}