{
  "type": "Feature",
  "properties": {
    "gn:admin1_code":"21",
    "gn:admin2_code":"158.0",
    "gn:asciiname":"El Tecajete",
    "gn:country_code":"MX",
    "gn:dem":179,
    "gn:feature_class":"P",
    "gn:feature_code":"PPL",
    "gn:name":"El Tecajete",
    "gn:population":165,
    "gn:timezone":"America/Mexico_City",
    "iso:country":"MX",
    "wof:name":"El Tecajete",
    "wof:placetype":"locality",
    "wof:population":165
},
  "geometry": {"coordinates":[-97.40855999999999,20.16896],"type":"Point"}
}