{
  "type": "Feature",
  "properties": {
    "gn:admin1_code":"10",
    "gn:admin2_code":"14.0",
    "gn:asciiname":"Los Asqueles",
    "gn:country_code":"MX",
    "gn:dem":1594,
    "gn:feature_class":"P",
    "gn:feature_code":"PPL",
    "gn:name":"Los Asqueles",
    "gn:population":6,
    "gn:timezone":"America/Monterrey",
    "iso:country":"MX",
    "wof:name":"Los Asqueles",
    "wof:placetype":"locality",
    "wof:population":6
},
  "geometry": {"coordinates":[-104.48524999999999,23.13809],"type":"Point"}
}