{
  "type": "Feature",
  "properties": {
    "gn:admin1_code":"31",
    "gn:admin2_code":"96.0",
    "gn:asciiname":"Odzceh",
    "gn:country_code":"MX",
    "gn:dem":9,
    "gn:feature_class":"P",
    "gn:feature_code":"PPL",
    "gn:name":"Odzceh",
    "gn:population":0,
    "gn:timezone":"America/Merida",
    "iso:country":"MX",
    "name:spa_x_preferred":[
        "Odzceh"
    ],
    "wof:name":"Odzceh",
    "wof:placetype":"locality"
},
  "geometry": {"coordinates":[-87.86839999999999,21.26849],"type":"Point"}
}