{
  "type": "Feature",
  "properties": {
    "gn:admin1_code":"22",
    "gn:admin2_code":"9.0",
    "gn:asciiname":"Soledad del Refugio",
    "gn:country_code":"MX",
    "gn:dem":1185,
    "gn:feature_class":"P",
    "gn:feature_code":"PPL",
    "gn:name":"Soledad del Refugio",
    "gn:population":8,
    "gn:timezone":"America/Mexico_City",
    "iso:country":"MX",
    "wof:name":"Soledad del Refugio",
    "wof:placetype":"locality",
    "wof:population":8
},
  "geometry": {"coordinates":[-99.43222,21.41389],"type":"Point"}
}