{
  "type": "Feature",
  "properties": {
    "gn:admin1_code":"27",
    "gn:admin2_code":"8.0",
    "gn:asciiname":"Zapotal Primera Seccion",
    "gn:country_code":"MX",
    "gn:dem":16,
    "gn:feature_class":"P",
    "gn:feature_code":"PPL",
    "gn:name":"Zapotal Primera Secci\u00f3n",
    "gn:population":0,
    "gn:timezone":"America/Mexico_City",
    "iso:country":"MX",
    "name:spa_x_preferred":[
        "San Miguel"
    ],
    "name:spa_x_variant":[
        "Zapotal Primera Secci\u00f3n",
        "Zapotal San Miguel Primera Secci\u00f3n"
    ],
    "wof:name":"Zapotal Primera Seccion",
    "wof:placetype":"locality"
},
  "geometry": {"coordinates":[-93.72956000000001,17.9984],"type":"Point"}
}