{
  "type": "Feature",
  "properties": {
    "gn:admin1_code":"10",
    "gn:admin2_code":"13.0",
    "gn:asciiname":"Rancho Canada Honda",
    "gn:country_code":"MX",
    "gn:dem":1518,
    "gn:feature_class":"P",
    "gn:feature_code":"PPL",
    "gn:name":"Rancho Ca\u00f1ada Honda",
    "gn:population":0,
    "gn:timezone":"America/Monterrey",
    "iso:country":"MX",
    "wof:name":"Rancho Canada Honda",
    "wof:placetype":"locality"
},
  "geometry": {"coordinates":[-104.40000000000001,26.11667000000001],"type":"Point"}
}