{
  "type": "Feature",
  "properties": {
    "gn:admin1_code":"12",
    "gn:admin2_code":"51.0",
    "gn:asciiname":"Coscamila",
    "gn:country_code":"MX",
    "gn:dem":825,
    "gn:feature_class":"P",
    "gn:feature_code":"PPL",
    "gn:name":"Coscamila",
    "gn:population":643,
    "gn:timezone":"America/Mexico_City",
    "iso:country":"MX",
    "wof:name":"Coscamila",
    "wof:placetype":"locality",
    "wof:population":643
},
  "geometry": {"coordinates":[-99.2197,17.41783],"type":"Point"}
}