{
  "type": "Feature",
  "properties": {
    "gn:admin1_code":"14",
    "gn:admin2_code":"9.0",
    "gn:asciiname":"Las Tortugas [Fraccionamiento]",
    "gn:country_code":"MX",
    "gn:dem":1468,
    "gn:feature_class":"P",
    "gn:feature_code":"PPL",
    "gn:name":"Las Tortugas [Fraccionamiento]",
    "gn:population":76,
    "gn:timezone":"America/Mexico_City",
    "iso:country":"MX",
    "wof:name":"Las Tortugas [Fraccionamiento]",
    "wof:placetype":"locality",
    "wof:population":76
},
  "geometry": {"coordinates":[-103.62944,20.72667],"type":"Point"}
}