{
  "type": "Feature",
  "properties": {
    "gn:admin1_code":"16",
    "gn:admin2_code":"10.0",
    "gn:asciiname":"Espinosa",
    "gn:country_code":"MX",
    "gn:dem":847,
    "gn:feature_class":"P",
    "gn:feature_code":"PPL",
    "gn:name":"Espinosa",
    "gn:population":458,
    "gn:timezone":"America/Mexico_City",
    "iso:country":"MX",
    "name:und_x_variant":[
        "Espinazo del Diablo"
    ],
    "wof:name":"Espinosa",
    "wof:placetype":"locality",
    "wof:population":458
},
  "geometry": {"coordinates":[-102.25778,18.47583],"type":"Point"}
}