{
  "type": "Feature",
  "properties": {
    "gn:admin1_code":"19",
    "gn:admin2_code":"27.0",
    "gn:asciiname":"El Olmo",
    "gn:country_code":"MX",
    "gn:dem":157,
    "gn:feature_class":"P",
    "gn:feature_code":"PPL",
    "gn:name":"El Olmo",
    "gn:population":0,
    "gn:timezone":"America/Monterrey",
    "iso:country":"MX",
    "name:spa_x_preferred":[
        "El Olmo"
    ],
    "wof:name":"El Olmo",
    "wof:placetype":"locality"
},
  "geometry": {"coordinates":[-99.32523999999999,25.82647],"type":"Point"}
}