{
  "type": "Feature",
  "properties": {
    "gn:admin1_code":"19",
    "gn:admin2_code":"49.0",
    "gn:asciiname":"Agua Fria",
    "gn:country_code":"MX",
    "gn:dem":2003,
    "gn:feature_class":"P",
    "gn:feature_code":"PPL",
    "gn:name":"Agua Fr\u00eda",
    "gn:population":1,
    "gn:timezone":"America/Monterrey",
    "iso:country":"MX",
    "name:ceb_x_preferred":[
        "Agua Fria"
    ],
    "name:deu_x_preferred":[
        "Agua Fria"
    ],
    "name:spa_x_preferred":[
        "Agua Fr\u00eda"
    ],
    "name:swe_x_preferred":[
        "Agua Fria"
    ],
    "wof:name":"Agua Fria",
    "wof:placetype":"locality",
    "wof:population":1
},
  "geometry": {"coordinates":[-100.42724,25.41561],"type":"Point"}
}