{
  "type": "Feature",
  "properties": {
    "gn:admin1_code":"13",
    "gn:admin2_code":"3.0",
    "gn:asciiname":"Santa Maria Magdalena",
    "gn:country_code":"MX",
    "gn:dem":2413,
    "gn:feature_class":"P",
    "gn:feature_code":"PPL",
    "gn:name":"Santa Mar\u00eda Magdalena",
    "gn:population":341,
    "gn:timezone":"America/Mexico_City",
    "iso:country":"MX",
    "name:und_x_variant":[
        "Santa Mar\u00eda",
        "Magdalena"
    ],
    "wof:name":"Santa Maria Magdalena",
    "wof:placetype":"locality",
    "wof:population":341
},
  "geometry": {"coordinates":[-98.85854,20.29725],"type":"Point"}
}