{
  "type": "Feature",
  "properties": {
    "gn:admin1_code":"2",
    "gn:admin2_code":"1",
    "gn:asciiname":"La Mesa",
    "gn:country_code":"MX",
    "gn:dem":265,
    "gn:feature_class":"P",
    "gn:feature_code":"PPL",
    "gn:name":"La Mesa",
    "gn:population":9,
    "gn:timezone":"America/Tijuana",
    "iso:country":"MX",
    "wof:name":"La Mesa",
    "wof:placetype":"locality",
    "wof:population":9
},
  "geometry": {"coordinates":[-115.73139,30.08889000000001],"type":"Point"}
}