{
  "type": "Feature",
  "properties": {
    "gn:admin1_code":"5",
    "gn:admin2_code":"71.0",
    "gn:asciiname":"23 de Enero",
    "gn:country_code":"MX",
    "gn:dem":32,
    "gn:feature_class":"P",
    "gn:feature_code":"PPL",
    "gn:name":"23 de Enero",
    "gn:population":192,
    "gn:timezone":"America/Mexico_City",
    "iso:country":"MX",
    "wof:name":"23 de Enero",
    "wof:placetype":"locality",
    "wof:population":192
},
  "geometry": {"coordinates":[-92.54474999999999,15.17938],"type":"Point"}
}