{
  "type": "Feature",
  "properties": {
    "gn:admin1_code":"24",
    "gn:admin2_code":"44.0",
    "gn:asciiname":"El Desparramadero",
    "gn:country_code":"MX",
    "gn:dem":1766,
    "gn:feature_class":"P",
    "gn:feature_code":"PPL",
    "gn:name":"El Desparramadero",
    "gn:population":0,
    "gn:timezone":"America/Mexico_City",
    "iso:country":"MX",
    "name:spa_x_preferred":[
        "El Desparramadero"
    ],
    "wof:name":"El Desparramadero",
    "wof:placetype":"locality"
},
  "geometry": {"coordinates":[-100.98609999999999,24.08621],"type":"Point"}
}