{
  "type": "Feature",
  "properties": {
    "gn:admin1_code":"19",
    "gn:admin2_code":"16.0",
    "gn:asciiname":"Papagayos",
    "gn:country_code":"MX",
    "gn:dem":377,
    "gn:feature_class":"P",
    "gn:feature_code":"PPL",
    "gn:name":"Papagayos",
    "gn:population":0,
    "gn:timezone":"America/Monterrey",
    "iso:country":"MX",
    "name:spa_x_preferred":[
        "Papagayos"
    ],
    "wof:name":"Papagayos",
    "wof:placetype":"locality"
},
  "geometry": {"coordinates":[-99.83799999999999,25.87126],"type":"Point"}
}