{
  "type": "Feature",
  "properties": {
    "gn:admin1_code":"10",
    "gn:admin2_code":"35.0",
    "gn:asciiname":"El Arquito de Enmedio",
    "gn:country_code":"MX",
    "gn:dem":2196,
    "gn:feature_class":"P",
    "gn:feature_code":"PPL",
    "gn:name":"El Arquito de Enmedio",
    "gn:population":4,
    "gn:timezone":"America/Monterrey",
    "iso:country":"MX",
    "wof:name":"El Arquito de Enmedio",
    "wof:placetype":"locality",
    "wof:population":4
},
  "geometry": {"coordinates":[-106.1174,25.54322],"type":"Point"}
}