{
  "type": "Feature",
  "properties": {
    "gn:admin1_code":"21.0",
    "gn:admin2_code":"111.0",
    "gn:asciiname":"Mixun",
    "gn:country_code":"MX",
    "gn:dem":337,
    "gn:feature_class":"P",
    "gn:feature_code":"PPL",
    "gn:name":"Mix\u00fan",
    "gn:population":0,
    "gn:timezone":"America/Mexico_City",
    "iso:country":"MX",
    "name:spa_x_preferred":[
        "Mix\u00fan"
    ],
    "wof:name":"Mixun",
    "wof:placetype":"locality"
},
  "geometry": {"coordinates":[-97.90468,20.5204],"type":"Point"}
}