{
  "type": "Feature",
  "properties": {
    "gn:admin1_code":"5",
    "gn:admin2_code":"59",
    "gn:asciiname":"Las Conchitas",
    "gn:country_code":"MX",
    "gn:dem":923,
    "gn:feature_class":"P",
    "gn:feature_code":"PPL",
    "gn:name":"Las Conchitas",
    "gn:population":47,
    "gn:timezone":"America/Mexico_City",
    "iso:country":"MX",
    "wof:name":"Las Conchitas",
    "wof:placetype":"locality",
    "wof:population":47
},
  "geometry": {"coordinates":[-91.93333,16.97806],"type":"Point"}
}