{
  "type": "Feature",
  "properties": {
    "gn:admin1_code":"6",
    "gn:admin2_code":"48.0",
    "gn:asciiname":"Los Pinos",
    "gn:country_code":"MX",
    "gn:dem":1967,
    "gn:feature_class":"P",
    "gn:feature_code":"PPL",
    "gn:name":"Los Pinos",
    "gn:population":0,
    "gn:timezone":"America/Chihuahua",
    "iso:country":"MX",
    "name:spa_x_preferred":[
        "Los Pinos"
    ],
    "wof:name":"Los Pinos",
    "wof:placetype":"locality"
},
  "geometry": {"coordinates":[-107.29012,29.12813],"type":"Point"}
}