{
  "type": "Feature",
  "properties": {
    "iso:country":"MX",
    "name:spa_x_preferred":[
        "Hda Las Palomas"
    ],
    "qs:gn_adm0_cc":"MX",
    "qs:gn_fcode":"PPL",
    "qs:gn_local":3981609,
    "qs:gn_nam_loc":"Tijuana, Tijuana, Baja California, MX",
    "qs:gn_namadm1":"02",
    "qs:gn_name":"Las Palomas",
    "qs:local_max":2893,
    "qs:local_sum":14029,
    "qs:localhoods":36,
    "qs:name":"Hda Las Palomas",
    "qs:name_adm0":"M\u00e9xico",
    "qs:name_adm1":"Baja California",
    "qs:name_adm2":"Tijuana",
    "qs:name_local":"Tijuana",
    "qs:photo_max":113,
    "qs:photo_sum":126,
    "qs:placetype":"Suburb",
    "qs:quad_count":4,
    "qs:woe_adm0":23424900,
    "qs:woe_adm1":2346265,
    "qs:woe_adm2":12599694,
    "qs:woe_lau":0,
    "qs:woe_local":149361,
    "qs:woe_ver":"7.10.0",
    "wof:lang":[
        "spa"
    ],
    "wof:name":"Hda Las Palomas",
    "wof:placetype":"neighbourhood"
},
  "geometry": {"coordinates":[-117.003044,32.494448],"type":"Point"}
}