{
  "type": "Feature",
  "properties": {
    "gn:admin1_code":"11.0",
    "gn:admin2_code":"30.0",
    "gn:asciiname":"Tampiquito",
    "gn:country_code":"MX",
    "gn:dem":2225,
    "gn:feature_class":"P",
    "gn:feature_code":"PPL",
    "gn:name":"Tampiquito",
    "gn:population":0,
    "gn:timezone":"America/Mexico_City",
    "iso:country":"MX",
    "name:spa_x_preferred":[
        "Tampiquito"
    ],
    "name:spa_x_variant":[
        "Tampiquillo"
    ],
    "wof:name":"Tampiquito",
    "wof:placetype":"locality"
},
  "geometry": {"coordinates":[-101.35483000000001,21.73629],"type":"Point"}
}