{
  "type": "Feature",
  "properties": {
    "gn:admin1_code":"32",
    "gn:admin2_code":"20.0",
    "gn:asciiname":"Ermita de los Murillo (Los Murillo)",
    "gn:country_code":"MX",
    "gn:dem":2230,
    "gn:feature_class":"P",
    "gn:feature_code":"PPL",
    "gn:name":"Ermita de los Murillo (Los Murillo)",
    "gn:population":110,
    "gn:timezone":"America/Mexico_City",
    "iso:country":"MX",
    "wof:name":"Ermita de los Murillo (Los Murillo)",
    "wof:placetype":"locality",
    "wof:population":110
},
  "geometry": {"coordinates":[-103.01333,22.89194],"type":"Point"}
}