{
  "type": "Feature",
  "properties": {
    "gn:admin1_code":"5",
    "gn:admin2_code":"32.0",
    "gn:asciiname":"Santa Isabel",
    "gn:country_code":"MX",
    "gn:dem":859,
    "gn:feature_class":"P",
    "gn:feature_code":"PPL",
    "gn:name":"Santa Isabel",
    "gn:population":120,
    "gn:timezone":"America/Mexico_City",
    "iso:country":"MX",
    "wof:name":"Santa Isabel",
    "wof:placetype":"locality",
    "wof:population":120
},
  "geometry": {"coordinates":[-92.47472,15.32361],"type":"Point"}
}