{
  "type": "Feature",
  "properties": {
    "gn:admin1_code":"10",
    "gn:admin2_code":"7.0",
    "gn:asciiname":"Los Catarrines",
    "gn:country_code":"MX",
    "gn:dem":1107,
    "gn:feature_class":"P",
    "gn:feature_code":"PPL",
    "gn:name":"Los Catarrines",
    "gn:population":0,
    "gn:timezone":"America/Monterrey",
    "iso:country":"MX",
    "name:spa_x_preferred":[
        "Los Catarrines"
    ],
    "wof:name":"Los Catarrines",
    "wof:placetype":"locality"
},
  "geometry": {"coordinates":[-103.42431000000001,25.81786],"type":"Point"}
}