{
  "type": "Feature",
  "properties": {
    "gn:admin1_code":"10",
    "gn:admin2_code":"34.0",
    "gn:asciiname":"Los Cimientos",
    "gn:country_code":"MX",
    "gn:dem":1334,
    "gn:feature_class":"P",
    "gn:feature_code":"PPL",
    "gn:name":"Los Cimientos",
    "gn:population":8,
    "gn:timezone":"America/Monterrey",
    "iso:country":"MX",
    "wof:name":"Los Cimientos",
    "wof:placetype":"locality",
    "wof:population":8
},
  "geometry": {"coordinates":[-106.23505,24.44249],"type":"Point"}
}