{
  "type": "Feature",
  "properties": {
    "gn:admin1_code":"13",
    "gn:admin2_code":"76.0",
    "gn:asciiname":"Yijay de Cuauhtemoc",
    "gn:country_code":"MX",
    "gn:dem":2067,
    "gn:feature_class":"P",
    "gn:feature_code":"PPL",
    "gn:name":"Yijay de Cuauhtemoc",
    "gn:population":0,
    "gn:timezone":"America/Mexico_City",
    "iso:country":"MX",
    "name:spa_x_preferred":[
        "Xijay de Cuauht\u00e9moc"
    ],
    "name:spa_x_variant":[
        "Yijay de Cuauhtemoc"
    ],
    "wof:name":"Yijay de Cuauhtemoc",
    "wof:placetype":"locality"
},
  "geometry": {"coordinates":[-99.40058000000001,20.12016],"type":"Point"}
}