{
  "type": "Feature",
  "properties": {
    "gn:admin1_code":"21",
    "gn:admin2_code":"145.0",
    "gn:asciiname":"Zesecapa",
    "gn:country_code":"MX",
    "gn:dem":1306,
    "gn:feature_class":"P",
    "gn:feature_code":"PPL",
    "gn:name":"Zesecapa",
    "gn:population":74,
    "gn:timezone":"America/Mexico_City",
    "iso:country":"MX",
    "wof:name":"Zesecapa",
    "wof:placetype":"locality",
    "wof:population":74
},
  "geometry": {"coordinates":[-96.89421,18.24741],"type":"Point"}
}