{
  "type": "Feature",
  "properties": {
    "gn:admin1_code":"14",
    "gn:admin2_code":"110",
    "gn:asciiname":"Santa Catarina",
    "gn:country_code":"MX",
    "gn:dem":1458,
    "gn:feature_class":"P",
    "gn:feature_code":"PPL",
    "gn:name":"Santa Catarina",
    "gn:population":17,
    "gn:timezone":"America/Mexico_City",
    "iso:country":"MX",
    "wof:name":"Santa Catarina",
    "wof:placetype":"locality",
    "wof:population":17
},
  "geometry": {"coordinates":[-104.20417,19.99778],"type":"Point"}
}