{
  "type": "Feature",
  "properties": {
    "gn:admin1_code":"16",
    "gn:admin2_code":"82.0",
    "gn:asciiname":"San Rafael Tecario",
    "gn:country_code":"MX",
    "gn:dem":1538,
    "gn:feature_class":"P",
    "gn:feature_code":"PPL",
    "gn:name":"San Rafael Tecario",
    "gn:population":0,
    "gn:timezone":"America/Mexico_City",
    "iso:country":"MX",
    "name:spa_x_preferred":[
        "San Rafael Tecario"
    ],
    "wof:name":"San Rafael Tecario",
    "wof:placetype":"locality"
},
  "geometry": {"coordinates":[-101.50627,19.2108],"type":"Point"}
}