{
  "type": "Feature",
  "properties": {
    "gn:admin1_code":"14",
    "gn:admin2_code":"85",
    "gn:asciiname":"Real del Favor",
    "gn:country_code":"MX",
    "gn:dem":1312,
    "gn:feature_class":"P",
    "gn:feature_code":"PPL",
    "gn:name":"Real del Favor",
    "gn:population":19,
    "gn:timezone":"America/Mexico_City",
    "iso:country":"MX",
    "wof:name":"Real del Favor",
    "wof:placetype":"locality",
    "wof:population":19
},
  "geometry": {"coordinates":[-103.14139,19.49833],"type":"Point"}
}