{
  "type": "Feature",
  "properties": {
    "gn:admin1_code":"19.0",
    "gn:admin2_code":"17.0",
    "gn:asciiname":"El Coyote",
    "gn:country_code":"MX",
    "gn:dem":1899,
    "gn:feature_class":"P",
    "gn:feature_code":"PPL",
    "gn:name":"El Coyote",
    "gn:population":0,
    "gn:timezone":"America/Monterrey",
    "iso:country":"MX",
    "name:spa_x_preferred":[
        "El Coyote"
    ],
    "name:spa_x_variant":[
        "La Esperanza"
    ],
    "wof:name":"El Coyote",
    "wof:placetype":"locality"
},
  "geometry": {"coordinates":[-100.56028000000001,24.71481],"type":"Point"}
}