{
  "type": "Feature",
  "properties": {
    "gn:admin1_code":"25",
    "gn:admin2_code":"2.0",
    "gn:asciiname":"Mercedes",
    "gn:country_code":"MX",
    "gn:dem":52,
    "gn:feature_class":"P",
    "gn:feature_code":"PPL",
    "gn:name":"Mercedes",
    "gn:population":0,
    "gn:timezone":"America/Mazatlan",
    "iso:country":"MX",
    "name:bre_x_preferred":[
        "Mercedes"
    ],
    "name:cat_x_preferred":[
        "Mercedes"
    ],
    "name:ceb_x_preferred":[
        "Mercedes"
    ],
    "name:ces_x_preferred":[
        "Mercedes"
    ],
    "name:dan_x_preferred":[
        "Mercedes"
    ],
    "name:deu_x_preferred":[
        "Mercedes"
    ],
    "name:fas_x_preferred":[
        "\u0645\u0631\u0633\u062f\u0633"
    ],
    "name:fin_x_preferred":[
        "Mercedes"
    ],
    "name:fra_x_preferred":[
        "Mercedes"
    ],
    "name:heb_x_preferred":[
        "\u05de\u05e8\u05e1\u05d3\u05e1"
    ],
    "name:hrv_x_preferred":[
        "Mercedes"
    ],
    "name:ilo_x_preferred":[
        "Mercedes"
    ],
    "name:ita_x_preferred":[
        "Mercedes"
    ],
    "name:jpn_x_preferred":[
        "\u30e1\u30eb\u30bb\u30c7\u30b9"
    ],
    "name:kor_x_preferred":[
        "\uba54\ub974\uc138\ub370\uc2a4"
    ],
    "name:lit_x_preferred":[
        "Mersedesas"
    ],
    "name:mlg_x_preferred":[
        "Mercedes"
    ],
    "name:nld_x_preferred":[
        "Mercedes"
    ],
    "name:nor_x_preferred":[
        "Mercedes"
    ],
    "name:pol_x_preferred":[
        "Mercedes"
    ],
    "name:por_x_preferred":[
        "Mercedes"
    ],
    "name:ron_x_preferred":[
        "Mercedes"
    ],
    "name:rus_x_preferred":[
        "\u041c\u0435\u0440\u0441\u0435\u0434\u0435\u0441"
    ],
    "name:sco_x_preferred":[
        "Mercedes"
    ],
    "name:slk_x_preferred":[
        "Mercedes"
    ],
    "name:spa_x_preferred":[
        "Mercedes"
    ],
    "name:srp_x_preferred":[
        "\u041c\u0435\u0440\u0441\u0435\u0434\u0435\u0441"
    ],
    "name:swe_x_preferred":[
        "Mercedes"
    ],
    "name:tur_x_preferred":[
        "Mercedes"
    ],
    "name:ukr_x_preferred":[
        "\u041c\u0435\u0440\u0441\u0435\u0434\u0435\u0441"
    ],
    "name:vol_x_preferred":[
        "Mercedes"
    ],
    "name:war_x_preferred":[
        "Mercedes"
    ],
    "name:zho_x_preferred":[
        "\u6885\u8d5b\u5fb7\u65af"
    ],
    "wof:name":"Mercedes",
    "wof:placetype":"locality"
},
  "geometry": {"coordinates":[-108.0967,25.43174],"type":"Point"}
}