{
  "type": "Feature",
  "properties": {
    "gn:admin1_code":"10",
    "gn:admin2_code":"2.0",
    "gn:asciiname":"Guasimitas",
    "gn:country_code":"MX",
    "gn:dem":2365,
    "gn:feature_class":"P",
    "gn:feature_code":"PPL",
    "gn:name":"Guasimitas",
    "gn:population":0,
    "gn:timezone":"America/Monterrey",
    "iso:country":"MX",
    "name:spa_x_preferred":[
        "Guasimitas"
    ],
    "wof:name":"Guasimitas",
    "wof:placetype":"locality"
},
  "geometry": {"coordinates":[-106.41582,25.07003],"type":"Point"}
}