{
  "type": "Feature",
  "properties": {
    "gn:admin1_code":"10.0",
    "gn:admin2_code":"37.0",
    "gn:asciiname":"Casas Viejas",
    "gn:country_code":"MX",
    "gn:dem":861,
    "gn:feature_class":"P",
    "gn:feature_code":"PPL",
    "gn:name":"Casas Viejas",
    "gn:population":7,
    "gn:timezone":"America/Monterrey",
    "iso:country":"MX",
    "wof:name":"Casas Viejas",
    "wof:placetype":"locality",
    "wof:population":7
},
  "geometry": {"coordinates":[-106.83565,25.21969],"type":"Point"}
}