{
  "type": "Feature",
  "properties": {
    "gn:admin1_code":"10",
    "gn:admin2_code":"32.0",
    "gn:asciiname":"Pachon de Arriba",
    "gn:country_code":"MX",
    "gn:dem":1885,
    "gn:feature_class":"P",
    "gn:feature_code":"PPL",
    "gn:name":"Pach\u00f3n de Arriba",
    "gn:population":0,
    "gn:timezone":"America/Monterrey",
    "iso:country":"MX",
    "name:und_x_variant":[
        "San Jos\u00e9 del Pach\u00f3n",
        "Pach\u00f3n de Arriba",
        "Pach\u00f3n"
    ],
    "wof:name":"Pachon de Arriba",
    "wof:placetype":"locality"
},
  "geometry": {"coordinates":[-105.36356000000001,24.80031],"type":"Point"}
}