{
  "type": "Feature",
  "properties": {
    "gn:admin1_code":"5",
    "gn:admin2_code":"61.0",
    "gn:asciiname":"Juan de Grijalva Dos",
    "gn:country_code":"MX",
    "gn:dem":359,
    "gn:feature_class":"P",
    "gn:feature_code":"PPL",
    "gn:name":"Juan de Grijalva Dos",
    "gn:population":105,
    "gn:timezone":"America/Mexico_City",
    "iso:country":"MX",
    "wof:name":"Juan de Grijalva Dos",
    "wof:placetype":"locality",
    "wof:population":105
},
  "geometry": {"coordinates":[-93.40278000000001,16.96306],"type":"Point"}
}