{
  "type": "Feature",
  "properties": {
    "gn:admin1_code":"28.0",
    "gn:admin2_code":"13.0",
    "gn:asciiname":"Seis de Octubre",
    "gn:country_code":"MX",
    "gn:dem":219,
    "gn:feature_class":"P",
    "gn:feature_code":"PPL",
    "gn:name":"Seis de Octubre",
    "gn:population":1,
    "gn:timezone":"America/Monterrey",
    "iso:country":"MX",
    "name:spa_x_preferred":[
        "Seis de Octubre"
    ],
    "wof:name":"Seis de Octubre",
    "wof:placetype":"locality",
    "wof:population":1
},
  "geometry": {"coordinates":[-98.93889,23.71972],"type":"Point"}
}