{
  "type": "Feature",
  "properties": {
    "gn:admin1_code":"14",
    "gn:admin2_code":"56.0",
    "gn:asciiname":"La Brena",
    "gn:country_code":"MX",
    "gn:dem":728,
    "gn:feature_class":"P",
    "gn:feature_code":"PPL",
    "gn:name":"La Bre\u00f1a",
    "gn:population":9,
    "gn:timezone":"America/Mexico_City",
    "iso:country":"MX",
    "name:und_x_variant":[
        "La Bre\u00f1a"
    ],
    "wof:name":"La Brena",
    "wof:placetype":"locality",
    "wof:population":9
},
  "geometry": {"coordinates":[-102.79861,19.59917],"type":"Point"}
}