{
  "type": "Feature",
  "properties": {
    "gn:admin1_code":"17",
    "gn:admin2_code":"6.0",
    "gn:asciiname":"Colonia el Sifon",
    "gn:country_code":"MX",
    "gn:dem":1316,
    "gn:feature_class":"P",
    "gn:feature_code":"PPL",
    "gn:name":"Colonia el Sif\u00f3n",
    "gn:population":70,
    "gn:timezone":"America/Mexico_City",
    "iso:country":"MX",
    "name:und_x_variant":[
        "Colonia el Sif\u00f3n"
    ],
    "wof:name":"Colonia el Sifon",
    "wof:placetype":"locality",
    "wof:population":70
},
  "geometry": {"coordinates":[-98.96115,18.82698],"type":"Point"}
}