{
  "type": "Feature",
  "properties": {
    "gn:admin1_code":"20",
    "gn:admin2_code":"255.0",
    "gn:asciiname":"San Isidro (Agua de Lobo)",
    "gn:country_code":"MX",
    "gn:dem":1452,
    "gn:feature_class":"P",
    "gn:feature_code":"PPL",
    "gn:name":"San Isidro (Agua de Lobo)",
    "gn:population":265,
    "gn:timezone":"America/Mexico_City",
    "iso:country":"MX",
    "wof:name":"San Isidro (Agua de Lobo)",
    "wof:placetype":"locality",
    "wof:population":265
},
  "geometry": {"coordinates":[-97.34694,17.01472],"type":"Point"}
}