{
  "type": "Feature",
  "properties": {
    "gn:admin1_code":"26",
    "gn:asciiname":"Sinaloa de Leyva",
    "gn:country_code":"MX",
    "gn:dem":48,
    "gn:feature_class":"P",
    "gn:feature_code":"PPL",
    "gn:name":"Sinaloa de Leyva",
    "gn:population":0,
    "gn:timezone":"America/Mazatlan",
    "iso:country":"MX",
    "name:por_x_preferred":[
        "Sinaloa"
    ],
    "name:rus_x_preferred":[
        "\u0421\u0438\u043d\u0430\u043b\u043e\u0430-\u0434\u0435-\u041b\u0435\u0439\u0432\u0430"
    ],
    "name:spa_x_preferred":[
        "Sinaloa de Leyva"
    ],
    "name:spa_x_variant":[
        "El Venadillo"
    ],
    "name:srp_x_preferred":[
        "\u0421\u0438\u043d\u0430\u043b\u043e\u0430 \u0434\u0435 \u041b\u0435\u0458\u0432\u0430"
    ],
    "wof:name":"Sinaloa de Leyva",
    "wof:placetype":"locality"
},
  "geometry": {"coordinates":[-108.98044,26.37773],"type":"Point"}
}