{
  "type": "Feature",
  "properties": {
    "gn:admin1_code":"26",
    "gn:asciiname":"Sinaloa de Leyva",
    "gn:country_code":"MX",
    "gn:dem":48,
    "gn:feature_class":"P",
    "gn:feature_code":"PPL",
    "gn:name":"Sinaloa de Leyva",
    "gn:population":0,
    "gn:timezone":"America/Mazatlan",
    "iso:country":"MX",
    "name:spa_x_preferred":[
        "Sinaloa de Leyva"
    ],
    "name:spa_x_variant":[
        "El Venadillo"
    ],
    "wof:name":"Sinaloa de Leyva",
    "wof:placetype":"locality"
},
  "geometry": {"coordinates":[-108.98044,26.37773],"type":"Point"}
}