{
  "type": "Feature",
  "properties": {
    "gn:admin1_code":"14.0",
    "gn:asciiname":"La Guera Hilaria",
    "gn:country_code":"MX",
    "gn:dem":1354,
    "gn:feature_class":"P",
    "gn:feature_code":"PPL",
    "gn:name":"La G\u00fcera Hilaria",
    "gn:population":0,
    "gn:timezone":"America/Mexico_City",
    "iso:country":"MX",
    "name:spa_x_preferred":[
        "La G\u00fcera Hilaria"
    ],
    "wof:name":"La Guera Hilaria",
    "wof:placetype":"locality"
},
  "geometry": {"coordinates":[-103.73119,22.39872],"type":"Point"}
}