{
  "type": "Feature",
  "properties": {
    "gn:admin1_code":"30.0",
    "gn:asciiname":"El Chiflon",
    "gn:country_code":"MX",
    "gn:dem":10,
    "gn:feature_class":"P",
    "gn:feature_code":"PPL",
    "gn:name":"El Chifl\u00f3n",
    "gn:population":0,
    "gn:timezone":"America/Mexico_City",
    "iso:country":"MX",
    "name:spa_x_preferred":[
        "El Chifl\u00f3n"
    ],
    "wof:name":"El Chiflon",
    "wof:placetype":"locality"
},
  "geometry": {"coordinates":[-95.52316999999999,18.32437],"type":"Point"}
}