{
  "type": "Feature",
  "properties": {
    "gn:admin1_code":"5.0",
    "gn:asciiname":"San Antonio Buenavista",
    "gn:country_code":"MX",
    "gn:dem":886,
    "gn:feature_class":"P",
    "gn:feature_code":"PPL",
    "gn:name":"San Antonio Buenavista",
    "gn:population":0,
    "gn:timezone":"America/Mexico_City",
    "iso:country":"MX",
    "name:spa_x_preferred":[
        "San Antonio Buenavista"
    ],
    "wof:name":"San Antonio Buenavista",
    "wof:placetype":"locality"
},
  "geometry": {"coordinates":[-91.99909,16.90312999999999],"type":"Point"}
}