{
  "type": "Feature",
  "properties": {
    "gn:admin1_code":"4",
    "gn:admin2_code":"7.0",
    "gn:asciiname":"San Juliancito",
    "gn:country_code":"MX",
    "gn:dem":4,
    "gn:feature_class":"P",
    "gn:feature_code":"PPL",
    "gn:name":"San Juliancito",
    "gn:population":0,
    "gn:timezone":"America/Mexico_City",
    "iso:country":"MX",
    "name:spa_x_preferred":[
        "San Juliancito"
    ],
    "wof:name":"San Juliancito",
    "wof:placetype":"locality"
},
  "geometry": {"coordinates":[-92.00381,18.04859],"type":"Point"}
}