{
  "type": "Feature",
  "properties": {
    "gn:admin1_code":"5",
    "gn:admin2_code":"108.0",
    "gn:asciiname":"Ursulo Galvan",
    "gn:country_code":"MX",
    "gn:dem":700,
    "gn:feature_class":"P",
    "gn:feature_code":"PPL",
    "gn:name":"\u00darsulo Galv\u00e1n",
    "gn:population":935,
    "gn:timezone":"America/Mexico_City",
    "iso:country":"MX",
    "wof:name":"Ursulo Galvan",
    "wof:placetype":"locality",
    "wof:population":935
},
  "geometry": {"coordinates":[-93.41472,16.27972],"type":"Point"}
}