{
  "type": "Feature",
  "properties": {
    "gn:admin1_code":"10",
    "gn:admin2_code":"14.0",
    "gn:asciiname":"Magueyes",
    "gn:country_code":"MX",
    "gn:dem":2455,
    "gn:feature_class":"P",
    "gn:feature_code":"PPL",
    "gn:name":"Magueyes",
    "gn:population":0,
    "gn:timezone":"America/Monterrey",
    "iso:country":"MX",
    "name:spa_x_preferred":[
        "Magueyes"
    ],
    "wof:name":"Magueyes",
    "wof:placetype":"locality"
},
  "geometry": {"coordinates":[-104.28863,22.72297],"type":"Point"}
}