{
  "type": "Feature",
  "properties": {
    "gn:admin1_code":"20",
    "gn:admin2_code":"386.0",
    "gn:asciiname":"La Aurora",
    "gn:country_code":"MX",
    "gn:dem":762,
    "gn:feature_class":"P",
    "gn:feature_code":"PPL",
    "gn:name":"La Aurora",
    "gn:population":378,
    "gn:timezone":"America/Mexico_City",
    "iso:country":"MX",
    "wof:name":"La Aurora",
    "wof:placetype":"locality",
    "wof:population":378
},
  "geometry": {"coordinates":[-97.42247,16.43186],"type":"Point"}
}