{
  "type": "Feature",
  "properties": {
    "gn:admin1_code":"6.0",
    "gn:admin2_code":"10.0",
    "gn:asciiname":"La Purisima",
    "gn:country_code":"MX",
    "gn:dem":1564,
    "gn:feature_class":"P",
    "gn:feature_code":"PPL",
    "gn:name":"La Purisima",
    "gn:population":0,
    "gn:timezone":"America/Chihuahua",
    "iso:country":"MX",
    "name:spa_x_preferred":[
        "La Purisima"
    ],
    "wof:name":"La Purisima",
    "wof:placetype":"locality"
},
  "geometry": {"coordinates":[-107.44792,29.82009],"type":"Point"}
}