{
  "type": "Feature",
  "properties": {
    "gn:admin1_code":"6",
    "gn:admin2_code":"46.0",
    "gn:asciiname":"La Nopalera",
    "gn:country_code":"MX",
    "gn:dem":1767,
    "gn:feature_class":"P",
    "gn:feature_code":"PPL",
    "gn:name":"La Nopalera",
    "gn:population":0,
    "gn:timezone":"America/Chihuahua",
    "iso:country":"MX",
    "name:spa_x_preferred":[
        "La Nopalera"
    ],
    "wof:name":"La Nopalera",
    "wof:placetype":"locality"
},
  "geometry": {"coordinates":[-107.73241000000002,26.48123],"type":"Point"}
}