{
  "type": "Feature",
  "properties": {
    "gn:admin1_code":"11",
    "gn:admin2_code":"33.0",
    "gn:asciiname":"Salto",
    "gn:country_code":"MX",
    "gn:dem":2077,
    "gn:feature_class":"P",
    "gn:feature_code":"PPL",
    "gn:name":"Salto",
    "gn:population":0,
    "gn:timezone":"America/Mexico_City",
    "iso:country":"MX",
    "name:ast_x_preferred":[
        "Saltu"
    ],
    "name:bpy_x_preferred":[
        "\u09b8\u09be\u09b2\u09cd\u099f\u09cb"
    ],
    "name:bul_x_preferred":[
        "\u0421\u0430\u043b\u0442\u043e"
    ],
    "name:ceb_x_preferred":[
        "Salto"
    ],
    "name:ces_x_preferred":[
        "Salto"
    ],
    "name:deu_x_preferred":[
        "Salto"
    ],
    "name:epo_x_preferred":[
        "Salto"
    ],
    "name:est_x_preferred":[
        "Salto"
    ],
    "name:fin_x_preferred":[
        "Salto"
    ],
    "name:fra_x_preferred":[
        "Salto"
    ],
    "name:glg_x_preferred":[
        "Salto"
    ],
    "name:ind_x_preferred":[
        "Salto"
    ],
    "name:ita_x_preferred":[
        "Salto"
    ],
    "name:jpn_x_preferred":[
        "\u30b5\u30eb\u30c8"
    ],
    "name:mlg_x_preferred":[
        "Salto"
    ],
    "name:nld_x_preferred":[
        "Salto"
    ],
    "name:nor_x_preferred":[
        "Salto"
    ],
    "name:pol_x_preferred":[
        "Salto"
    ],
    "name:por_x_preferred":[
        "Salto"
    ],
    "name:rus_x_preferred":[
        "\u0421\u0430\u043b\u044c\u0442\u043e"
    ],
    "name:sco_x_preferred":[
        "Salto"
    ],
    "name:slk_x_preferred":[
        "Salto"
    ],
    "name:spa_x_preferred":[
        "Salto"
    ],
    "name:srp_x_preferred":[
        "\u0421\u0430\u043b\u0442\u043e"
    ],
    "name:swe_x_preferred":[
        "Salto"
    ],
    "name:ukr_x_preferred":[
        "\u0421\u0430\u043b\u044c\u0442\u043e"
    ],
    "name:vep_x_preferred":[
        "Sal'to"
    ],
    "name:vol_x_preferred":[
        "Salto"
    ],
    "name:zho_x_preferred":[
        "\u8428\u5c14\u56fe"
    ],
    "wof:name":"Salto",
    "wof:placetype":"locality"
},
  "geometry": {"coordinates":[-100.73333,21.55],"type":"Point"}
}