{
  "type": "Feature",
  "properties": {
    "gn:admin1_code":"20",
    "gn:admin2_code":"12.0",
    "gn:asciiname":"San Lucas",
    "gn:country_code":"MX",
    "gn:dem":785,
    "gn:feature_class":"P",
    "gn:feature_code":"PPL",
    "gn:name":"San Lucas",
    "gn:population":182,
    "gn:timezone":"America/Mexico_City",
    "iso:country":"MX",
    "wof:name":"San Lucas",
    "wof:placetype":"locality",
    "wof:population":182
},
  "geometry": {"coordinates":[-96.47333,15.95389],"type":"Point"}
}