{
  "type": "Feature",
  "properties": {
    "gn:admin1_code":"10",
    "gn:admin2_code":"37",
    "gn:asciiname":"La Cieneguita",
    "gn:country_code":"MX",
    "gn:dem":2242,
    "gn:feature_class":"P",
    "gn:feature_code":"PPL",
    "gn:name":"La Cieneguita",
    "gn:population":9,
    "gn:timezone":"America/Monterrey",
    "iso:country":"MX",
    "wof:name":"La Cieneguita",
    "wof:placetype":"locality",
    "wof:population":9
},
  "geometry": {"coordinates":[-106.59231,25.28414],"type":"Point"}
}