{
  "type": "Feature",
  "properties": {
    "gn:admin1_code":"30",
    "gn:admin2_code":"121.0",
    "gn:asciiname":"Santa Diana",
    "gn:country_code":"MX",
    "gn:dem":48,
    "gn:feature_class":"P",
    "gn:feature_code":"PPL",
    "gn:name":"Santa Diana",
    "gn:population":0,
    "gn:timezone":"America/Mexico_City",
    "iso:country":"MX",
    "name:spa_x_preferred":[
        "Agua Marina"
    ],
    "name:spa_x_variant":[
        "Santa Diana"
    ],
    "wof:name":"Santa Diana",
    "wof:placetype":"locality"
},
  "geometry": {"coordinates":[-97.85344000000001,21.75793],"type":"Point"}
}