{
  "type": "Feature",
  "properties": {
    "gn:admin1_code":"6",
    "gn:admin2_code":"18.0",
    "gn:asciiname":"Rancho Alto de Chavez (Rancho Alto Grande)",
    "gn:country_code":"MX",
    "gn:dem":2155,
    "gn:feature_class":"P",
    "gn:feature_code":"PPL",
    "gn:name":"Rancho Alto de Ch\u00e1vez (Rancho Alto Grande)",
    "gn:population":3,
    "gn:timezone":"America/Chihuahua",
    "iso:country":"MX",
    "wof:name":"Rancho Alto de Chavez (Rancho Alto Grande)",
    "wof:placetype":"locality",
    "wof:population":3
},
  "geometry": {"coordinates":[-106.93865,28.24145],"type":"Point"}
}