{
  "type": "Feature",
  "properties": {
    "gn:admin1_code":"6",
    "gn:admin2_code":"20.0",
    "gn:asciiname":"Las Calabazas",
    "gn:country_code":"MX",
    "gn:dem":1425,
    "gn:feature_class":"P",
    "gn:feature_code":"PPL",
    "gn:name":"Las Calabazas",
    "gn:population":0,
    "gn:timezone":"America/Chihuahua",
    "iso:country":"MX",
    "name:spa_x_preferred":[
        "Las Calabazas"
    ],
    "wof:name":"Las Calabazas",
    "wof:placetype":"locality"
},
  "geometry": {"coordinates":[-108.36920000000001,27.35471],"type":"Point"}
}