{
  "type": "Feature",
  "properties": {
    "gn:admin1_code":"11",
    "gn:admin2_code":"12.0",
    "gn:asciiname":"Bordo Ciego",
    "gn:country_code":"MX",
    "gn:dem":1692,
    "gn:feature_class":"P",
    "gn:feature_code":"PPL",
    "gn:name":"Bordo Ciego",
    "gn:population":6,
    "gn:timezone":"America/Mexico_City",
    "iso:country":"MX",
    "wof:name":"Bordo Ciego",
    "wof:placetype":"locality",
    "wof:population":6
},
  "geometry": {"coordinates":[-101.60250000000001,20.55306],"type":"Point"}
}