{
  "type": "Feature",
  "properties": {
    "gn:admin1_code":"16",
    "gn:admin2_code":"112.0",
    "gn:asciiname":"La Joya de Manzanillo (Segunda Manzana)",
    "gn:country_code":"MX",
    "gn:dem":2203,
    "gn:feature_class":"P",
    "gn:feature_code":"PPL",
    "gn:name":"La Joya de Manzanillo (Segunda Manzana)",
    "gn:population":505,
    "gn:timezone":"America/Mexico_City",
    "iso:country":"MX",
    "wof:name":"La Joya de Manzanillo (Segunda Manzana)",
    "wof:placetype":"locality",
    "wof:population":505
},
  "geometry": {"coordinates":[-100.30249999999999,19.44167],"type":"Point"}
}