{
  "type": "Feature",
  "properties": {
    "gn:admin1_code":"30",
    "gn:admin2_code":"197.0",
    "gn:asciiname":"Nueva Reforma",
    "gn:country_code":"MX",
    "gn:dem":981,
    "gn:feature_class":"P",
    "gn:feature_code":"PPL",
    "gn:name":"Nueva Reforma",
    "gn:population":139,
    "gn:timezone":"America/Mexico_City",
    "iso:country":"MX",
    "wof:name":"Nueva Reforma",
    "wof:placetype":"locality",
    "wof:population":139
},
  "geometry": {"coordinates":[-96.79139000000001,19.79972],"type":"Point"}
}