{
  "type": "Feature",
  "properties": {
    "gn:admin1_code":"2.0",
    "gn:admin2_code":"1.0",
    "gn:asciiname":"Costa Rica",
    "gn:country_code":"MX",
    "gn:dem":17,
    "gn:feature_class":"P",
    "gn:feature_code":"PPL",
    "gn:name":"Costa Rica",
    "gn:population":0,
    "gn:timezone":"America/Tijuana",
    "iso:country":"MX",
    "name:spa_x_preferred":[
        "Costa Rica"
    ],
    "name:spa_x_variant":[
        "Seis Hermanos"
    ],
    "wof:name":"Costa Rica",
    "wof:placetype":"locality"
},
  "geometry": {"coordinates":[-115.80506,30.29691],"type":"Point"}
}