{
  "type": "Feature",
  "properties": {
    "gn:admin1_code":"20",
    "gn:asciiname":"Huajintepec",
    "gn:country_code":"MX",
    "gn:dem":333,
    "gn:feature_class":"P",
    "gn:feature_code":"PPL",
    "gn:name":"Huajintepec",
    "gn:population":0,
    "gn:timezone":"America/Mexico_City",
    "iso:country":"MX",
    "name:und_x_variant":[
        "Guajintepec",
        "Huajintepec"
    ],
    "wof:name":"Huajintepec",
    "wof:placetype":"locality"
},
  "geometry": {"coordinates":[-98.23027999999999,16.61003],"type":"Point"}
}