{
  "type": "Feature",
  "properties": {
    "gn:admin1_code":"2.0",
    "gn:admin2_code":"2.0",
    "gn:asciiname":"Cucapah Mestizo",
    "gn:country_code":"MX",
    "gn:dem":9,
    "gn:feature_class":"P",
    "gn:feature_code":"PPL",
    "gn:name":"Cucap\u00e1h Mestizo",
    "gn:population":0,
    "gn:timezone":"America/Tijuana",
    "iso:country":"MX",
    "name:spa_x_preferred":[
        "Cucap\u00e1h Mestizo"
    ],
    "name:und_x_variant":[
        "Ejido Cucapa Mestizo",
        "Cucap\u00e1 Mestizos",
        "Cucap\u00e1 Mestizo",
        "Ejido Cucapah Mestizo"
    ],
    "wof:name":"Cucapah Mestizo",
    "wof:placetype":"locality"
},
  "geometry": {"coordinates":[-115.28106,32.24788],"type":"Point"}
}