{
  "type": "Feature",
  "properties": {
    "gn:admin1_code":"5",
    "gn:admin2_code":"43.0",
    "gn:asciiname":"Emiliano Zapata",
    "gn:country_code":"MX",
    "gn:dem":95,
    "gn:feature_class":"P",
    "gn:feature_code":"PPL",
    "gn:name":"Emiliano Zapata",
    "gn:population":540,
    "gn:timezone":"America/Mexico_City",
    "iso:country":"MX",
    "wof:name":"Emiliano Zapata",
    "wof:placetype":"locality",
    "wof:population":540
},
  "geometry": {"coordinates":[-93.10028,17.45917],"type":"Point"}
}