{
  "type": "Feature",
  "properties": {
    "gn:admin1_code":"19.0",
    "gn:admin2_code":"5.0",
    "gn:asciiname":"San Martin",
    "gn:country_code":"MX",
    "gn:dem":219,
    "gn:feature_class":"P",
    "gn:feature_code":"PPL",
    "gn:name":"San Martin",
    "gn:population":0,
    "gn:timezone":"America/Matamoros",
    "iso:country":"MX",
    "name:ara_x_preferred":[
        "\u0633\u0627\u0646 \u0645\u0627\u0631\u062a\u0646"
    ],
    "name:ben_x_preferred":[
        "\u09b8\u09be\u09a8 \u09ae\u09be\u09b0\u09cd\u099f\u09bf\u09a8"
    ],
    "name:deu_x_preferred":[
        "San Mart\u00edn River"
    ],
    "name:ell_x_preferred":[
        "\u03a3\u03b1\u03bd \u039c\u03b1\u03c1\u03c4\u03af\u03bd"
    ],
    "name:fas_x_preferred":[
        "\u0633\u0627\u0646 \u0645\u0627\u0631\u062a\u06cc\u0646"
    ],
    "name:fra_x_preferred":[
        "San Martin"
    ],
    "name:heb_x_preferred":[
        "\u05e1\u05df \u05de\u05e8\u05d8\u05d9\u05df"
    ],
    "name:hin_x_preferred":[
        "\u0938\u0948\u0928 \u092e\u093e\u0930\u094d\u091f\u093f\u0928"
    ],
    "name:hun_x_preferred":[
        "San Martin"
    ],
    "name:ind_x_preferred":[
        "San Martin"
    ],
    "name:ita_x_preferred":[
        "San Martin"
    ],
    "name:jpn_x_preferred":[
        "\u30b5\u30f3\u30de\u30eb\u30c6\u30a3\u30f3\u5ddd"
    ],
    "name:kor_x_preferred":[
        "\uc0b0 \ub9c8\ud2f4"
    ],
    "name:nld_x_preferred":[
        "San Mart\u00edn"
    ],
    "name:pol_x_preferred":[
        "San Martin"
    ],
    "name:por_x_preferred":[
        "San Mart\u00edn"
    ],
    "name:rus_x_preferred":[
        "\u0440\u0435\u043a\u0430 \u0421\u0430\u043d-\u041c\u0430\u0440\u0442\u0438\u043d"
    ],
    "name:spa_x_preferred":[
        "San Mart\u00edn"
    ],
    "name:spa_x_variant":[
        "San Martin"
    ],
    "name:swe_x_preferred":[
        "R\u00edo San Martin"
    ],
    "name:tur_x_preferred":[
        "San Martin"
    ],
    "name:ukr_x_preferred":[
        "\u0421\u0430\u043d-\u041c\u0430\u0440\u0442\u0438\u043d"
    ],
    "name:urd_x_preferred":[
        "\u0633\u0627\u0646 \u0645\u0627\u0631\u0679\u0646"
    ],
    "name:vie_x_preferred":[
        "S\u00f4ng San Martin"
    ],
    "name:zho_cn_x_preferred":[
        "\u5723\u9a6c\u4e01\u6cb3"
    ],
    "name:zho_tw_x_preferred":[
        "\u8056\u99ac\u4e01\u6cb3"
    ],
    "wof:name":"San Martin",
    "wof:placetype":"locality"
},
  "geometry": {"coordinates":[-99.8865,27.62173],"type":"Point"}
}