{
  "type": "Feature",
  "properties": {
    "gn:admin1_code":"27",
    "gn:admin2_code":"2.0",
    "gn:asciiname":"Gutierrez Gomez",
    "gn:country_code":"MX",
    "gn:dem":12,
    "gn:feature_class":"P",
    "gn:feature_code":"PPL",
    "gn:name":"Gutierrez G\u00f3mez",
    "gn:population":0,
    "gn:timezone":"America/Mexico_City",
    "iso:country":"MX",
    "name:spa_x_preferred":[
        "Gutierrez G\u00f3mez"
    ],
    "wof:name":"Gutierrez Gomez",
    "wof:placetype":"locality"
},
  "geometry": {"coordinates":[-93.74169999999999,18.1529],"type":"Point"}
}