{
  "type": "Feature",
  "properties": {
    "gn:admin1_code":"17",
    "gn:asciiname":"San Miguel Atepoxco",
    "gn:country_code":"MX",
    "gn:dem":2415,
    "gn:feature_class":"P",
    "gn:feature_code":"PPL",
    "gn:name":"San Miguel Atepoxco",
    "gn:population":0,
    "gn:timezone":"America/Mexico_City",
    "iso:country":"MX",
    "name:spa_x_preferred":[
        "San Miguel Atepoxco"
    ],
    "wof:name":"San Miguel Atepoxco",
    "wof:placetype":"locality"
},
  "geometry": {"coordinates":[-98.74038,19.74498],"type":"Point"}
}