{
  "type": "Feature",
  "properties": {
    "gn:admin1_code":"6.0",
    "gn:admin2_code":"27.0",
    "gn:asciiname":"Corohuachi",
    "gn:country_code":"MX",
    "gn:dem":2009,
    "gn:feature_class":"P",
    "gn:feature_code":"PPL",
    "gn:name":"Corohuachi",
    "gn:population":0,
    "gn:timezone":"America/Chihuahua",
    "iso:country":"MX",
    "name:spa_x_preferred":[
        "Corohuachi"
    ],
    "wof:name":"Corohuachi",
    "wof:placetype":"locality"
},
  "geometry": {"coordinates":[-107.60999,27.49998],"type":"Point"}
}