{
  "type": "Feature",
  "properties": {
    "gn:admin1_code":"11.0",
    "gn:admin2_code":"40.0",
    "gn:asciiname":"Puerto de la Palma",
    "gn:country_code":"MX",
    "gn:dem":2032,
    "gn:feature_class":"P",
    "gn:feature_code":"PPL",
    "gn:name":"Puerto de la Palma",
    "gn:population":0,
    "gn:timezone":"America/Mexico_City",
    "iso:country":"MX",
    "name:spa_x_preferred":[
        "Puerto de la Palma"
    ],
    "wof:name":"Puerto de la Palma",
    "wof:placetype":"locality"
},
  "geometry": {"coordinates":[-100.12396,21.07349],"type":"Point"}
}