{
  "type": "Feature",
  "properties": {
    "gn:admin1_code":"2",
    "gn:admin2_code":"2.0",
    "gn:asciiname":"Las Palmas (Colonia Abasolo)",
    "gn:country_code":"MX",
    "gn:dem":8,
    "gn:feature_class":"P",
    "gn:feature_code":"PPL",
    "gn:name":"Las Palmas (Colonia Abasolo)",
    "gn:population":6,
    "gn:timezone":"America/Tijuana",
    "iso:country":"MX",
    "wof:name":"Las Palmas (Colonia Abasolo)",
    "wof:placetype":"locality",
    "wof:population":6
},
  "geometry": {"coordinates":[-115.34111,32.63694],"type":"Point"}
}