{
  "type": "Feature",
  "properties": {
    "gn:admin1_code":"6",
    "gn:admin2_code":"9.0",
    "gn:asciiname":"Rancheria San Jose de Guacayvo",
    "gn:country_code":"MX",
    "gn:dem":2287,
    "gn:feature_class":"P",
    "gn:feature_code":"PPLF",
    "gn:name":"Rancher\u00eda San Jos\u00e9 de Guacayvo",
    "gn:population":0,
    "gn:timezone":"America/Chihuahua",
    "iso:country":"MX",
    "name:spa_x_preferred":[
        "Rancher\u00eda San Jos\u00e9 de Guacayvo"
    ],
    "wof:name":"Rancheria San Jose de Guacayvo",
    "wof:placetype":"locality"
},
  "geometry": {"coordinates":[-107.82299,27.75253],"type":"Point"}
}