{
  "type": "Feature",
  "properties": {
    "gn:admin1_code":"15.0",
    "gn:asciiname":"Monte Oreb",
    "gn:country_code":"MX",
    "gn:dem":2597,
    "gn:feature_class":"P",
    "gn:feature_code":"PPL",
    "gn:name":"Monte Oreb",
    "gn:population":0,
    "gn:timezone":"America/Mexico_City",
    "iso:country":"MX",
    "name:spa_x_preferred":[
        "Monte Oreb"
    ],
    "wof:name":"Monte Oreb",
    "wof:placetype":"locality"
},
  "geometry": {"coordinates":[-98.81296,19.18581],"type":"Point"}
}