{
  "type": "Feature",
  "properties": {
    "gn:admin1_code":"6",
    "gn:admin2_code":"9.0",
    "gn:asciiname":"Huatosachi",
    "gn:country_code":"MX",
    "gn:dem":2263,
    "gn:feature_class":"P",
    "gn:feature_code":"PPL",
    "gn:name":"Huatosachi",
    "gn:population":8,
    "gn:timezone":"America/Chihuahua",
    "iso:country":"MX",
    "wof:name":"Huatosachi",
    "wof:placetype":"locality",
    "wof:population":8
},
  "geometry": {"coordinates":[-107.78659,27.58131],"type":"Point"}
}