{
  "type": "Feature",
  "properties": {
    "gn:admin1_code":"10",
    "gn:admin2_code":"37",
    "gn:asciiname":"Agua Prieta",
    "gn:country_code":"MX",
    "gn:dem":2126,
    "gn:feature_class":"P",
    "gn:feature_code":"PPL",
    "gn:name":"Agua Prieta",
    "gn:population":10,
    "gn:timezone":"America/Monterrey",
    "iso:country":"MX",
    "name:cat_x_preferred":[
        "Agua Prieta"
    ],
    "name:ces_x_preferred":[
        "Agua Prieta"
    ],
    "name:deu_x_preferred":[
        "Agua Prieta"
    ],
    "name:fra_x_preferred":[
        "Agua Prieta"
    ],
    "name:heb_x_preferred":[
        "\u05d0\u05d2\u05d5\u05d0\u05d4 \u05e4\u05e8\u05d9\u05d0\u05d8\u05d4"
    ],
    "name:ita_x_preferred":[
        "Agua Prieta"
    ],
    "name:nld_x_preferred":[
        "Agua Prieta"
    ],
    "name:pol_x_preferred":[
        "Agua Prieta"
    ],
    "name:ron_x_preferred":[
        "Agua Prieta"
    ],
    "name:rus_x_preferred":[
        "\u0410\u0433\u0443\u0430-\u041f\u0440\u0438\u0435\u0442\u0430"
    ],
    "name:spa_x_preferred":[
        "Agua Prieta"
    ],
    "name:srp_x_preferred":[
        "\u0410\u0433\u0432\u0430 \u041f\u0440\u0438\u0458\u0435\u0442\u0430"
    ],
    "wof:name":"Agua Prieta",
    "wof:placetype":"locality",
    "wof:population":10
},
  "geometry": {"coordinates":[-106.70453999999999,25.19581],"type":"Point"}
}