{
  "type": "Feature",
  "properties": {
    "gn:admin1_code":"22",
    "gn:admin2_code":"14.0",
    "gn:asciiname":"Lomas del Mirador",
    "gn:country_code":"MX",
    "gn:dem":1955,
    "gn:feature_class":"P",
    "gn:feature_code":"PPL",
    "gn:name":"Lomas del Mirador",
    "gn:population":111,
    "gn:timezone":"America/Mexico_City",
    "iso:country":"MX",
    "name:ara_x_preferred":[
        "\u0644\u0648\u0645\u0627\u0633 \u062f\u064a\u0644 \u0645\u064a\u0631\u0627\u062f\u0648\u0631"
    ],
    "name:azb_x_preferred":[
        "\u0644\u0648\u0645\u0627\u0633 \u062f\u0644 \u0645\u06cc\u0631\u0627\u062f\u0648\u0631"
    ],
    "name:ceb_x_preferred":[
        "Lomas del Mirador"
    ],
    "name:fas_x_preferred":[
        "\u0644\u0648\u0645\u0627\u0633 \u062f\u0644 \u0645\u06cc\u0631\u0627\u062f\u0648\u0631"
    ],
    "name:ita_x_preferred":[
        "Lomas del Mirador"
    ],
    "name:nld_x_preferred":[
        "Lomas del Mirador"
    ],
    "name:por_x_preferred":[
        "Lomas del Mirador"
    ],
    "name:rus_x_preferred":[
        "\u041b\u043e\u043c\u0430\u0441-\u0434\u0435-\u041c\u0438\u0440\u0430\u0434\u043e\u0440"
    ],
    "name:sco_x_preferred":[
        "Lomas del Mirador"
    ],
    "name:spa_x_preferred":[
        "Lomas del Mirador"
    ],
    "name:zho_x_preferred":[
        "\u6d1b\u99ac\u65af\u5fb7\u723e\u7c73\u62c9\u591a\u723e"
    ],
    "wof:name":"Lomas del Mirador",
    "wof:placetype":"locality",
    "wof:population":111
},
  "geometry": {"coordinates":[-100.42111,20.64],"type":"Point"}
}