{
  "type": "Feature",
  "properties": {
    "gn:admin1_code":"17",
    "gn:admin2_code":"30.0",
    "gn:asciiname":"Huexca",
    "gn:cc2":"MX",
    "gn:country_code":"MX",
    "gn:dem":1421,
    "gn:feature_class":"P",
    "gn:feature_code":"PPL",
    "gn:name":"Huexca",
    "gn:population":969,
    "gn:timezone":"America/Mexico_City",
    "iso:country":"MX",
    "name:und_x_variant":[
        "Huesca",
        "Huexca"
    ],
    "wof:name":"Huexca",
    "wof:placetype":"locality",
    "wof:population":969
},
  "geometry": {"coordinates":[-98.86944,18.80472],"type":"Point"}
}