{
  "type": "Feature",
  "properties": {
    "gn:admin1_code":"25",
    "gn:admin2_code":"6.0",
    "gn:asciiname":"Granja Santa Monica",
    "gn:country_code":"MX",
    "gn:dem":90,
    "gn:feature_class":"P",
    "gn:feature_code":"PPL",
    "gn:name":"Granja Santa M\u00f3nica",
    "gn:population":6,
    "gn:timezone":"America/Mazatlan",
    "iso:country":"MX",
    "name:und_x_variant":[
        "Granja Santa M\u00f3nica"
    ],
    "wof:name":"Granja Santa Monica",
    "wof:placetype":"locality",
    "wof:population":6
},
  "geometry": {"coordinates":[-107.27171,24.76028],"type":"Point"}
}