{
  "type": "Feature",
  "properties": {
    "gn:admin1_code":"16.0",
    "gn:admin2_code":"6.0",
    "gn:asciiname":"Morataya",
    "gn:country_code":"MX",
    "gn:dem":235,
    "gn:feature_class":"P",
    "gn:feature_code":"PPL",
    "gn:name":"Morataya",
    "gn:population":0,
    "gn:timezone":"America/Mexico_City",
    "iso:country":"MX",
    "name:spa_x_preferred":[
        "Morataya"
    ],
    "wof:name":"Morataya",
    "wof:placetype":"locality"
},
  "geometry": {"coordinates":[-102.47184,19.06296],"type":"Point"}
}