{
  "type": "Feature",
  "properties": {
    "gn:admin1_code":"24",
    "gn:admin2_code":"3",
    "gn:asciiname":"Cueva del Tiwi (Cueva de la Gavilucha)",
    "gn:country_code":"MX",
    "gn:dem":1216,
    "gn:feature_class":"P",
    "gn:feature_code":"PPL",
    "gn:name":"Cueva del Tiwi (Cueva de la Gavilucha)",
    "gn:population":10,
    "gn:timezone":"America/Mexico_City",
    "iso:country":"MX",
    "wof:name":"Cueva del Tiwi (Cueva de la Gavilucha)",
    "wof:placetype":"locality",
    "wof:population":10
},
  "geometry": {"coordinates":[-99.11111,21.59639],"type":"Point"}
}