{
  "type": "Feature",
  "properties": {
    "gn:admin1_code":"11.0",
    "gn:admin2_code":"22.0",
    "gn:asciiname":"Desmonte de los Banda",
    "gn:country_code":"MX",
    "gn:dem":2206,
    "gn:feature_class":"P",
    "gn:feature_code":"PPL",
    "gn:name":"Desmonte de los Banda",
    "gn:population":0,
    "gn:timezone":"America/Mexico_City",
    "iso:country":"MX",
    "name:spa_x_preferred":[
        "Desmonte de los Banda"
    ],
    "wof:name":"Desmonte de los Banda",
    "wof:placetype":"locality"
},
  "geometry": {"coordinates":[-101.45308,21.63369],"type":"Point"}
}