{
  "type": "Feature",
  "properties": {
    "gn:admin1_code":"30",
    "gn:admin2_code":"204.0",
    "gn:asciiname":"La Hondonada",
    "gn:country_code":"MX",
    "gn:dem":34,
    "gn:feature_class":"P",
    "gn:feature_code":"PPL",
    "gn:name":"La Hondonada",
    "gn:population":0,
    "gn:timezone":"America/Mexico_City",
    "iso:country":"MX",
    "name:spa_x_preferred":[
        "La Hondonada"
    ],
    "name:urd_x_preferred":[
        "\u0644\u0627 \u06c1\u0648\u0646\u062f\u0648\u0646\u0627\u0688\u0627"
    ],
    "wof:name":"La Hondonada",
    "wof:placetype":"locality"
},
  "geometry": {"coordinates":[-94.17194000000001,18.14105],"type":"Point"}
}