{
  "type": "Feature",
  "properties": {
    "gn:admin1_code":"10",
    "gn:admin2_code":"23.0",
    "gn:asciiname":"Portales de Milpillas",
    "gn:country_code":"MX",
    "gn:dem":2508,
    "gn:feature_class":"P",
    "gn:feature_code":"PPL",
    "gn:name":"Portales de Milpillas",
    "gn:population":0,
    "gn:timezone":"America/Monterrey",
    "iso:country":"MX",
    "name:spa_x_preferred":[
        "Portales de Milpillas"
    ],
    "wof:name":"Portales de Milpillas",
    "wof:placetype":"locality"
},
  "geometry": {"coordinates":[-105.08396999999999,23.54131],"type":"Point"}
}