{
  "type": "Feature",
  "properties": {
    "gn:admin1_code":"10.0",
    "gn:admin2_code":"35.0",
    "gn:asciiname":"Los Coconos",
    "gn:country_code":"MX",
    "gn:dem":2282,
    "gn:feature_class":"P",
    "gn:feature_code":"PPL",
    "gn:name":"Los C\u00f3conos",
    "gn:population":0,
    "gn:timezone":"America/Monterrey",
    "iso:country":"MX",
    "name:spa_x_preferred":[
        "Los C\u00f3conos"
    ],
    "wof:name":"Los Coconos",
    "wof:placetype":"locality"
},
  "geometry": {"coordinates":[-105.75602000000001,25.57996],"type":"Point"}
}