{
  "type": "Feature",
  "properties": {
    "gn:admin1_code":"20",
    "gn:admin2_code":"121",
    "gn:asciiname":"Santa Cruz Pipila",
    "gn:country_code":"MX",
    "gn:dem":2558,
    "gn:feature_class":"P",
    "gn:feature_code":"PPL",
    "gn:name":"Santa Cruz P\u00edpila",
    "gn:population":32,
    "gn:timezone":"America/Mexico_City",
    "iso:country":"MX",
    "name:und_x_variant":[
        "Santa Cruz P\u00edpila"
    ],
    "wof:name":"Santa Cruz Pipila",
    "wof:placetype":"locality",
    "wof:population":32
},
  "geometry": {"coordinates":[-97.26889,17.61722],"type":"Point"}
}