{
  "type": "Feature",
  "properties": {
    "gn:admin1_code":"15.0",
    "gn:asciiname":"Los Yuguitos",
    "gn:country_code":"MX",
    "gn:dem":626,
    "gn:feature_class":"P",
    "gn:feature_code":"PPL",
    "gn:name":"Los Yuguitos",
    "gn:population":0,
    "gn:timezone":"America/Mexico_City",
    "iso:country":"MX",
    "name:spa_x_preferred":[
        "Los Yuguitos"
    ],
    "wof:name":"Los Yuguitos",
    "wof:placetype":"locality"
},
  "geometry": {"coordinates":[-102.44897,18.21509],"type":"Point"}
}