{
  "type": "Feature",
  "properties": {
    "gn:admin1_code":"14",
    "gn:admin2_code":"20.0",
    "gn:asciiname":"El Viscoyul",
    "gn:country_code":"MX",
    "gn:dem":12,
    "gn:feature_class":"P",
    "gn:feature_code":"PPL",
    "gn:name":"El Viscoyul",
    "gn:population":0,
    "gn:timezone":"America/Mexico_City",
    "iso:country":"MX",
    "name:spa_x_preferred":[
        "El Viscoyul"
    ],
    "wof:name":"El Viscoyul",
    "wof:placetype":"locality"
},
  "geometry": {"coordinates":[-105.48233,20.4934],"type":"Point"}
}