{
  "type": "Feature",
  "properties": {
    "gn:admin1_code":"6.0",
    "gn:admin2_code":"29.0",
    "gn:asciiname":"Arroyo del Agua",
    "gn:country_code":"MX",
    "gn:dem":1836,
    "gn:feature_class":"P",
    "gn:feature_code":"PPL",
    "gn:name":"Arroyo del Agua",
    "gn:population":0,
    "gn:timezone":"America/Chihuahua",
    "iso:country":"MX",
    "name:spa_x_preferred":[
        "Arroyo del Agua"
    ],
    "wof:name":"Arroyo del Agua",
    "wof:placetype":"locality"
},
  "geometry": {"coordinates":[-107.40398,26.40999],"type":"Point"}
}