{
  "type": "Feature",
  "properties": {
    "gn:admin1_code":"14.0",
    "gn:admin2_code":"68.0",
    "gn:asciiname":"Salazar",
    "gn:country_code":"MX",
    "gn:dem":126,
    "gn:feature_class":"P",
    "gn:feature_code":"PPL",
    "gn:name":"Salazar",
    "gn:population":0,
    "gn:timezone":"America/Mexico_City",
    "iso:country":"MX",
    "name:bre_x_preferred":[
        "Salazar"
    ],
    "name:cat_x_preferred":[
        "Salazar"
    ],
    "name:ceb_x_preferred":[
        "Salazar"
    ],
    "name:eus_x_preferred":[
        "Salazar"
    ],
    "name:fin_x_preferred":[
        "Salazar"
    ],
    "name:fra_x_preferred":[
        "Salazar"
    ],
    "name:ind_x_preferred":[
        "Salazar"
    ],
    "name:ita_x_preferred":[
        "Salazar"
    ],
    "name:jpn_x_preferred":[
        "\u30b5\u30e9\u30b6\u30fc\u30eb"
    ],
    "name:lav_x_preferred":[
        "Salazars"
    ],
    "name:nld_x_preferred":[
        "Salazar"
    ],
    "name:pol_x_preferred":[
        "Salazar"
    ],
    "name:por_x_preferred":[
        "Salazar"
    ],
    "name:rus_x_preferred":[
        "\u0421\u0430\u043b\u0430\u0441\u0430\u0440"
    ],
    "name:sco_x_preferred":[
        "Salazar"
    ],
    "name:spa_x_preferred":[
        "Salazar"
    ],
    "name:srp_x_preferred":[
        "\u0421\u0430\u043b\u0430\u0437\u0430\u0440"
    ],
    "name:swe_x_preferred":[
        "Salazar"
    ],
    "name:tur_x_preferred":[
        "Salazar"
    ],
    "name:ukr_x_preferred":[
        "\u0421\u0430\u043b\u0430\u0441\u0430\u0440"
    ],
    "wof:name":"Salazar",
    "wof:placetype":"locality"
},
  "geometry": {"coordinates":[-104.97311999999999,19.88168],"type":"Point"}
}