{
  "type": "Feature",
  "properties": {
    "gn:admin1_code":"30",
    "gn:admin2_code":"127.0",
    "gn:asciiname":"El Minero",
    "gn:country_code":"MX",
    "gn:dem":2911,
    "gn:feature_class":"P",
    "gn:feature_code":"PPL",
    "gn:name":"El Minero",
    "gn:population":72,
    "gn:timezone":"America/Mexico_City",
    "iso:country":"MX",
    "wof:name":"El Minero",
    "wof:placetype":"locality",
    "wof:population":72
},
  "geometry": {"coordinates":[-97.21028,19.01861],"type":"Point"}
}