{
  "type": "Feature",
  "properties": {
    "gn:admin1_code":"26.0",
    "gn:admin2_code":"6.0",
    "gn:asciiname":"Los Gueerigos",
    "gn:country_code":"MX",
    "gn:dem":955,
    "gn:feature_class":"P",
    "gn:feature_code":"PPL",
    "gn:name":"Los G\u00fc\u00e9rigos",
    "gn:population":0,
    "gn:timezone":"America/Hermosillo",
    "iso:country":"MX",
    "name:spa_x_preferred":[
        "Los G\u00fc\u00e9rigos"
    ],
    "wof:name":"Los Gueerigos",
    "wof:placetype":"locality"
},
  "geometry": {"coordinates":[-110.30793,30.24077],"type":"Point"}
}