{
  "type": "Feature",
  "properties": {
    "gn:admin1_code":"19",
    "gn:admin2_code":"33.0",
    "gn:asciiname":"Santa Veronica",
    "gn:country_code":"MX",
    "gn:dem":489,
    "gn:feature_class":"P",
    "gn:feature_code":"PPL",
    "gn:name":"Santa Ver\u00f3nica",
    "gn:population":5,
    "gn:timezone":"America/Monterrey",
    "iso:country":"MX",
    "name:und_x_variant":[
        "Santa Ver\u00f3nica"
    ],
    "wof:name":"Santa Veronica",
    "wof:placetype":"locality",
    "wof:population":5
},
  "geometry": {"coordinates":[-99.64778,24.72306],"type":"Point"}
}