{
  "type": "Feature",
  "properties": {
    "gn:admin1_code":"32",
    "gn:admin2_code":"12",
    "gn:asciiname":"San Miguel de Agua Zarca (San Miguel)",
    "gn:country_code":"MX",
    "gn:dem":2217,
    "gn:feature_class":"P",
    "gn:feature_code":"PPL",
    "gn:name":"San Miguel de Agua Zarca (San Miguel)",
    "gn:population":21,
    "gn:timezone":"America/Mexico_City",
    "iso:country":"MX",
    "wof:name":"San Miguel de Agua Zarca (San Miguel)",
    "wof:placetype":"locality",
    "wof:population":21
},
  "geometry": {"coordinates":[-102.45917,22.49889],"type":"Point"}
}