{
  "type": "Feature",
  "properties": {
    "gn:admin1_code":"10",
    "gn:admin2_code":"12",
    "gn:asciiname":"La Vega (Apolonio Palacios)",
    "gn:country_code":"MX",
    "gn:dem":1173,
    "gn:feature_class":"P",
    "gn:feature_code":"PPL",
    "gn:name":"La Vega (Apolonio Palacios)",
    "gn:population":15,
    "gn:timezone":"America/Monterrey",
    "iso:country":"MX",
    "wof:name":"La Vega (Apolonio Palacios)",
    "wof:placetype":"locality",
    "wof:population":15
},
  "geometry": {"coordinates":[-103.74173,25.41028],"type":"Point"}
}