{
  "type": "Feature",
  "properties": {
    "gn:admin1_code":"18.0",
    "gn:admin2_code":"9.0",
    "gn:asciiname":"Las Azucenas",
    "gn:country_code":"MX",
    "gn:dem":773,
    "gn:feature_class":"P",
    "gn:feature_code":"PPL",
    "gn:name":"Las Azucenas",
    "gn:population":0,
    "gn:timezone":"America/Mazatlan",
    "iso:country":"MX",
    "wof:name":"Las Azucenas",
    "wof:placetype":"locality"
},
  "geometry": {"coordinates":[-104.62331,21.76098],"type":"Point"}
}