{
  "type": "Feature",
  "properties": {
    "gn:admin1_code":"25.0",
    "gn:admin2_code":"7.0",
    "gn:asciiname":"Bajosori",
    "gn:country_code":"MX",
    "gn:dem":343,
    "gn:feature_class":"P",
    "gn:feature_code":"PPL",
    "gn:name":"Bajosori",
    "gn:population":0,
    "gn:timezone":"America/Mazatlan",
    "iso:country":"MX",
    "name:spa_x_preferred":[
        "Bajosori"
    ],
    "wof:name":"Bajosori",
    "wof:placetype":"locality"
},
  "geometry": {"coordinates":[-108.39417,26.68706],"type":"Point"}
}