{
  "type": "Feature",
  "properties": {
    "gn:admin1_code":"10.0",
    "gn:admin2_code":"26.0",
    "gn:asciiname":"Los Carditos",
    "gn:country_code":"MX",
    "gn:dem":2541,
    "gn:feature_class":"P",
    "gn:feature_code":"PPL",
    "gn:name":"Los Carditos",
    "gn:population":0,
    "gn:timezone":"America/Monterrey",
    "iso:country":"MX",
    "name:spa_x_preferred":[
        "Los Carditos"
    ],
    "wof:name":"Los Carditos",
    "wof:placetype":"locality"
},
  "geometry": {"coordinates":[-105.95901000000001,24.30775],"type":"Point"}
}