{
  "type": "Feature",
  "properties": {
    "gn:admin1_code":"32",
    "gn:admin2_code":"36.0",
    "gn:asciiname":"Sauceda de Mulatos",
    "gn:country_code":"MX",
    "gn:dem":2190,
    "gn:feature_class":"P",
    "gn:feature_code":"PPL",
    "gn:name":"Sauceda de Mulatos",
    "gn:population":0,
    "gn:timezone":"America/Mexico_City",
    "iso:country":"MX",
    "name:und_x_variant":[
        "Sauceda",
        "Sauceda de Mulatos"
    ],
    "wof:name":"Sauceda de Mulatos",
    "wof:placetype":"locality"
},
  "geometry": {"coordinates":[-102.08028,22.45653],"type":"Point"}
}