{
  "type": "Feature",
  "properties": {
    "gn:admin1_code":"32",
    "gn:admin2_code":"31.0",
    "gn:asciiname":"Coyotes",
    "gn:country_code":"MX",
    "gn:dem":2351,
    "gn:feature_class":"P",
    "gn:feature_code":"PPL",
    "gn:name":"Coyotes",
    "gn:population":0,
    "gn:timezone":"America/Mexico_City",
    "iso:country":"MX",
    "name:spa_x_preferred":[
        "Coyotes"
    ],
    "wof:name":"Coyotes",
    "wof:placetype":"locality"
},
  "geometry": {"coordinates":[-103.58583,22.3053],"type":"Point"}
}