{
  "type": "Feature",
  "properties": {
    "gn:admin1_code":"12",
    "gn:admin2_code":"1.0",
    "gn:asciiname":"Huerta Marcelino Flores Bailon",
    "gn:country_code":"MX",
    "gn:dem":17,
    "gn:feature_class":"P",
    "gn:feature_code":"PPL",
    "gn:name":"Huerta Marcelino Flores Bail\u00f3n",
    "gn:population":6,
    "gn:timezone":"America/Mexico_City",
    "iso:country":"MX",
    "name:und_x_variant":[
        "Huerta Marcelino Flores Bail\u00f3n"
    ],
    "wof:name":"Huerta Marcelino Flores Bailon",
    "wof:placetype":"locality",
    "wof:population":6
},
  "geometry": {"coordinates":[-99.7872,16.83082000000001],"type":"Point"}
}