{
  "type": "Feature",
  "properties": {
    "gn:admin1_code":"20",
    "gn:admin2_code":"273.0",
    "gn:asciiname":"Pensamiento Liberal Mexicano",
    "gn:country_code":"MX",
    "gn:dem":2068,
    "gn:feature_class":"P",
    "gn:feature_code":"PPL",
    "gn:name":"Pensamiento Liberal Mexicano",
    "gn:population":517,
    "gn:timezone":"America/Mexico_City",
    "iso:country":"MX",
    "wof:name":"Pensamiento Liberal Mexicano",
    "wof:placetype":"locality",
    "wof:population":517
},
  "geometry": {"coordinates":[-97.04472,16.92472],"type":"Point"}
}