{
  "type": "Feature",
  "properties": {
    "gn:admin1_code":"15.0",
    "gn:admin2_code":"105.0",
    "gn:asciiname":"San Mateo (San Mateo Guayatenco)",
    "gn:country_code":"MX",
    "gn:dem":1222,
    "gn:feature_class":"P",
    "gn:feature_code":"PPL",
    "gn:name":"San Mateo (San Mateo Guayatenco)",
    "gn:population":950,
    "gn:timezone":"America/Mexico_City",
    "iso:country":"MX",
    "wof:name":"San Mateo (San Mateo Guayatenco)",
    "wof:placetype":"locality",
    "wof:population":950
},
  "geometry": {"coordinates":[-100.15056,18.63333],"type":"Point"}
}