{
  "type": "Feature",
  "properties": {
    "gn:admin1_code":"15",
    "gn:admin2_code":"12.0",
    "gn:asciiname":"El Tepiololco",
    "gn:country_code":"MX",
    "gn:dem":2575,
    "gn:feature_class":"P",
    "gn:feature_code":"PPL",
    "gn:name":"El Tepiololco",
    "gn:population":466,
    "gn:timezone":"America/Mexico_City",
    "iso:country":"MX",
    "wof:name":"El Tepiololco",
    "wof:placetype":"locality",
    "wof:population":466
},
  "geometry": {"coordinates":[-99.49944000000001,19.17556],"type":"Point"}
}