{
  "type": "Feature",
  "properties": {
    "gn:admin1_code":"19.0",
    "gn:asciiname":"Monclova Segundo Sector",
    "gn:country_code":"MX",
    "gn:dem":554,
    "gn:feature_class":"P",
    "gn:feature_code":"PPL",
    "gn:name":"Monclova Segundo Sector",
    "gn:population":0,
    "gn:timezone":"America/Monterrey",
    "iso:country":"MX",
    "name:spa_x_preferred":[
        "Monclova Segundo Sector"
    ],
    "wof:name":"Monclova Segundo Sector",
    "wof:placetype":"locality"
},
  "geometry": {"coordinates":[-100.39682000000001,25.81531],"type":"Point"}
}