{
  "type": "Feature",
  "properties": {
    "gn:admin1_code":"5",
    "gn:admin2_code":"102.0",
    "gn:asciiname":"El Rosario Izapa",
    "gn:country_code":"MX",
    "gn:dem":443,
    "gn:feature_class":"P",
    "gn:feature_code":"PPL",
    "gn:name":"El Rosario Izapa",
    "gn:population":0,
    "gn:timezone":"America/Mexico_City",
    "iso:country":"MX",
    "wof:name":"El Rosario Izapa",
    "wof:placetype":"locality"
},
  "geometry": {"coordinates":[-92.15633,14.97526],"type":"Point"}
}