{
  "type": "Feature",
  "properties": {
    "gn:admin1_code":"10.0",
    "gn:admin2_code":"2.0",
    "gn:asciiname":"Minitas de Palomas",
    "gn:country_code":"MX",
    "gn:dem":2421,
    "gn:feature_class":"P",
    "gn:feature_code":"PPL",
    "gn:name":"Minitas de Palomas",
    "gn:population":0,
    "gn:timezone":"America/Monterrey",
    "iso:country":"MX",
    "name:spa_x_preferred":[
        "Minitas de Palomas"
    ],
    "wof:name":"Minitas de Palomas",
    "wof:placetype":"locality"
},
  "geometry": {"coordinates":[-106.19588,25.10937],"type":"Point"}
}