{
  "type": "Feature",
  "properties": {
    "gn:admin1_code":"24",
    "gn:admin2_code":"17.0",
    "gn:asciiname":"San Juan sin Agua",
    "gn:country_code":"MX",
    "gn:dem":1362,
    "gn:feature_class":"P",
    "gn:feature_code":"PPL",
    "gn:name":"San Juan sin Agua",
    "gn:population":0,
    "gn:timezone":"America/Mexico_City",
    "iso:country":"MX",
    "name:und_x_variant":[
        "Sin Agua",
        "San Juan sin Agua"
    ],
    "wof:name":"San Juan sin Agua",
    "wof:placetype":"locality"
},
  "geometry": {"coordinates":[-100.48759,22.93719],"type":"Point"}
}