{
  "type": "Feature",
  "properties": {
    "gn:admin1_code":"24",
    "gn:admin2_code":"25",
    "gn:asciiname":"Martinez (Las Timias)",
    "gn:country_code":"MX",
    "gn:dem":2050,
    "gn:feature_class":"P",
    "gn:feature_code":"PPL",
    "gn:name":"Mart\u00ednez (Las Timias)",
    "gn:population":39,
    "gn:timezone":"America/Mexico_City",
    "iso:country":"MX",
    "name:und_x_variant":[
        "Mart\u00ednez (Las Timias)"
    ],
    "wof:name":"Martinez (Las Timias)",
    "wof:placetype":"locality",
    "wof:population":39
},
  "geometry": {"coordinates":[-101.63472,22.70611],"type":"Point"}
}