{
  "type": "Feature",
  "properties": {
    "gn:admin1_code":"20",
    "gn:admin2_code":"166.0",
    "gn:asciiname":"Fortino J. Pinacho",
    "gn:country_code":"MX",
    "gn:dem":51,
    "gn:feature_class":"P",
    "gn:feature_code":"PPL",
    "gn:name":"Fortino J. Pinacho",
    "gn:population":0,
    "gn:timezone":"America/Mexico_City",
    "iso:country":"MX",
    "name:spa_x_preferred":[
        "Fortino V. Pinacho"
    ],
    "name:spa_x_variant":[
        "Fortino J. Pinacho"
    ],
    "wof:name":"Fortino J. Pinacho",
    "wof:placetype":"locality"
},
  "geometry": {"coordinates":[-96.17425,17.99037000000001],"type":"Point"}
}