{
  "type": "Feature",
  "properties": {
    "gn:admin1_code":"21",
    "gn:admin2_code":"158.0",
    "gn:asciiname":"Arroyo Zarco",
    "gn:country_code":"MX",
    "gn:dem":158,
    "gn:feature_class":"P",
    "gn:feature_code":"PPL",
    "gn:name":"Arroyo Zarco",
    "gn:population":0,
    "gn:timezone":"America/Mexico_City",
    "iso:country":"MX",
    "name:und_x_variant":[
        "La Junta Arroyo Zarco"
    ],
    "wof:name":"Arroyo Zarco",
    "wof:placetype":"locality"
},
  "geometry": {"coordinates":[-97.45618,20.15109],"type":"Point"}
}