{
  "type": "Feature",
  "properties": {
    "gn:admin1_code":"30",
    "gn:admin2_code":"61",
    "gn:asciiname":"El Infiernillo",
    "gn:country_code":"MX",
    "gn:dem":24,
    "gn:feature_class":"P",
    "gn:feature_code":"PPL",
    "gn:name":"El Infiernillo",
    "gn:population":24,
    "gn:timezone":"America/Mexico_City",
    "iso:country":"MX",
    "wof:name":"El Infiernillo",
    "wof:placetype":"locality",
    "wof:population":24
},
  "geometry": {"coordinates":[-94.07028,17.68806],"type":"Point"}
}