{
  "type": "Feature",
  "properties": {
    "gn:admin1_code":"10",
    "gn:admin2_code":"5.0",
    "gn:asciiname":"San Vicente de Chupaderos",
    "gn:country_code":"MX",
    "gn:dem":1958,
    "gn:feature_class":"P",
    "gn:feature_code":"PPL",
    "gn:name":"San Vicente de Chupaderos",
    "gn:population":0,
    "gn:timezone":"America/Monterrey",
    "iso:country":"MX",
    "name:und_x_variant":[
        "Chupaderos",
        "San Vicente Chupaderos",
        "San Vicente de Chupaderos"
    ],
    "wof:name":"San Vicente de Chupaderos",
    "wof:placetype":"locality"
},
  "geometry": {"coordinates":[-104.71321,24.11845],"type":"Point"}
}