{
  "type": "Feature",
  "properties": {
    "gn:admin1_code":"2.0",
    "gn:admin2_code":"2.0",
    "gn:asciiname":"Colonia Cerro Prieto Seccion Cuatro",
    "gn:country_code":"MX",
    "gn:dem":7,
    "gn:feature_class":"P",
    "gn:feature_code":"PPL",
    "gn:name":"Colonia Cerro Prieto Secci\u00f3n Cuatro",
    "gn:population":0,
    "gn:timezone":"America/Tijuana",
    "iso:country":"MX",
    "name:spa_x_preferred":[
        "Colonia Cerro Prieto Secci\u00f3n Cuatro"
    ],
    "wof:name":"Colonia Cerro Prieto Seccion Cuatro",
    "wof:placetype":"locality"
},
  "geometry": {"coordinates":[-115.39256,32.46185],"type":"Point"}
}