{
  "type": "Feature",
  "properties": {
    "gn:admin1_code":"22",
    "gn:admin2_code":"15.0",
    "gn:asciiname":"Puerto Hondo",
    "gn:country_code":"MX",
    "gn:dem":1897,
    "gn:feature_class":"P",
    "gn:feature_code":"PPL",
    "gn:name":"Puerto Hondo",
    "gn:population":92,
    "gn:timezone":"America/Mexico_City",
    "iso:country":"MX",
    "wof:name":"Puerto Hondo",
    "wof:placetype":"locality",
    "wof:population":92
},
  "geometry": {"coordinates":[-99.55389,20.97111],"type":"Point"}
}