{
  "type": "Feature",
  "properties": {
    "gn:admin1_code":"14.0",
    "gn:admin2_code":"53.0",
    "gn:asciiname":"San Jose de la Isla",
    "gn:country_code":"MX",
    "gn:dem":1945,
    "gn:feature_class":"P",
    "gn:feature_code":"PPL",
    "gn:name":"San Jos\u00e9 de la Isla",
    "gn:population":0,
    "gn:timezone":"America/Mexico_City",
    "iso:country":"MX",
    "name:spa_x_preferred":[
        "San Jos\u00e9 de la Isla"
    ],
    "wof:name":"San Jose de la Isla",
    "wof:placetype":"locality"
},
  "geometry": {"coordinates":[-102.10253,21.31255],"type":"Point"}
}