{
  "type": "Feature",
  "properties": {
    "gn:admin1_code":"6.0",
    "gn:asciiname":"Trevizo",
    "gn:country_code":"MX",
    "gn:dem":1935,
    "gn:feature_class":"P",
    "gn:feature_code":"PPL",
    "gn:name":"Trevizo",
    "gn:population":0,
    "gn:timezone":"America/Chihuahua",
    "iso:country":"MX",
    "name:spa_x_preferred":[
        "Trevizo"
    ],
    "wof:name":"Trevizo",
    "wof:placetype":"locality"
},
  "geometry": {"coordinates":[-106.92377999999999,29.15637000000001],"type":"Point"}
}