{
  "type": "Feature",
  "properties": {
    "gn:admin1_code":"15",
    "gn:admin2_code":"81.0",
    "gn:asciiname":"Ampliacion de la Concepcion",
    "gn:country_code":"MX",
    "gn:dem":2247,
    "gn:feature_class":"P",
    "gn:feature_code":"PPL",
    "gn:name":"Ampliaci\u00f3n de la Concepci\u00f3n",
    "gn:population":80,
    "gn:timezone":"America/Mexico_City",
    "iso:country":"MX",
    "name:und_x_variant":[
        "Ampliaci\u00f3n de la Concepci\u00f3n"
    ],
    "wof:name":"Ampliacion de la Concepcion",
    "wof:placetype":"locality",
    "wof:population":80
},
  "geometry": {"coordinates":[-99.04224000000001,19.68731],"type":"Point"}
}