{
  "type": "Feature",
  "properties": {
    "gn:admin1_code":"26",
    "gn:admin2_code":"66.0",
    "gn:asciiname":"Huichuchi",
    "gn:country_code":"MX",
    "gn:dem":672,
    "gn:feature_class":"P",
    "gn:feature_code":"PPL",
    "gn:name":"Huichuchi",
    "gn:population":0,
    "gn:timezone":"America/Hermosillo",
    "iso:country":"MX",
    "name:spa_x_preferred":[
        "Huichuchi"
    ],
    "wof:name":"Huichuchi",
    "wof:placetype":"locality"
},
  "geometry": {"coordinates":[-110.07612,29.21084],"type":"Point"}
}