{
  "type": "Feature",
  "properties": {
    "gn:admin1_code":"11",
    "gn:admin2_code":"11.0",
    "gn:asciiname":"El Laurel",
    "gn:country_code":"MX",
    "gn:dem":1742,
    "gn:feature_class":"P",
    "gn:feature_code":"PPL",
    "gn:name":"El Laurel",
    "gn:population":8,
    "gn:timezone":"America/Mexico_City",
    "iso:country":"MX",
    "wof:name":"El Laurel",
    "wof:placetype":"locality",
    "wof:population":8
},
  "geometry": {"coordinates":[-100.93861,20.51111],"type":"Point"}
}