{
  "type": "Feature",
  "properties": {
    "gn:admin1_code":"28.0",
    "gn:admin2_code":"8.0",
    "gn:asciiname":"El Moro",
    "gn:country_code":"MX",
    "gn:dem":299,
    "gn:feature_class":"P",
    "gn:feature_code":"PPL",
    "gn:name":"El Moro",
    "gn:population":8,
    "gn:timezone":"America/Monterrey",
    "iso:country":"MX",
    "name:spa_x_preferred":[
        "El Moro"
    ],
    "wof:name":"El Moro",
    "wof:placetype":"locality",
    "wof:population":8
},
  "geometry": {"coordinates":[-98.58889000000001,23.57806],"type":"Point"}
}