{
  "type": "Feature",
  "properties": {
    "gn:admin1_code":"14",
    "gn:admin2_code":"30",
    "gn:asciiname":"El Cuije",
    "gn:country_code":"MX",
    "gn:dem":1599,
    "gn:feature_class":"P",
    "gn:feature_code":"PPL",
    "gn:name":"El Cuije",
    "gn:population":11,
    "gn:timezone":"America/Mexico_City",
    "iso:country":"MX",
    "wof:name":"El Cuije",
    "wof:placetype":"locality",
    "wof:population":11
},
  "geometry": {"coordinates":[-103.20556000000001,20.30722],"type":"Point"}
}