{
  "type": "Feature",
  "properties": {
    "iso:country":"MX",
    "qs_pg:aaroncc":"MX",
    "qs_pg:name":"Fracc Los Candiles",
    "qs_pg:name_adm0":"M\u00e9xico",
    "qs_pg:name_adm1":"Queretaro de Arteaga",
    "qs_pg:photos":1,
    "qs_pg:photos_1k":1,
    "qs_pg:photos_9k":1,
    "qs_pg:photos_9r":1,
    "qs_pg:photos_all":17,
    "qs_pg:photos_sr":1,
    "qs_pg:pop_sr":0,
    "qs_pg:qs_pg_placetype":"locality",
    "qs_pg:qs_pg_placetype_gp":"Town",
    "qs_pg:woe_adm0":23424900,
    "woe:adm0_id":23424900,
    "woe:name_adm0":"M\u00e9xico",
    "woe:name_adm1":"Queretaro de Arteaga",
    "woe:placetype":"Town",
    "wof:name":"Fracc Los Candiles",
    "wof:placetype":"locality"
},
  "geometry": {"coordinates":[-100.38208,20.556456],"type":"Point"}
}