{
  "type": "Feature",
  "properties": {
    "gn:admin1_code":"24.0",
    "gn:admin2_code":"42.0",
    "gn:asciiname":"La Persiana",
    "gn:country_code":"MX",
    "gn:dem":86,
    "gn:feature_class":"P",
    "gn:feature_code":"PPL",
    "gn:name":"La Persiana",
    "gn:population":11,
    "gn:timezone":"America/Mexico_City",
    "iso:country":"MX",
    "name:spa_x_preferred":[
        "La Persiana"
    ],
    "wof:name":"La Persiana",
    "wof:placetype":"locality",
    "wof:population":11
},
  "geometry": {"coordinates":[-98.63254999999999,21.56599],"type":"Point"}
}