{
  "type": "Feature",
  "properties": {
    "gn:admin1_code":"22",
    "gn:admin2_code":"16",
    "gn:asciiname":"Ninguno [Union de Artesanos la Corregidora]",
    "gn:country_code":"MX",
    "gn:dem":1918,
    "gn:feature_class":"P",
    "gn:feature_code":"PPL",
    "gn:name":"Ninguno [Uni\u00f3n de Artesanos la Corregidora]",
    "gn:population":51,
    "gn:timezone":"America/Mexico_City",
    "iso:country":"MX",
    "name:und_x_variant":[
        "Ninguno [Uni\u00f3n de Artesanos la Corregidora]"
    ],
    "wof:name":"Ninguno [Union de Artesanos la Corregidora]",
    "wof:placetype":"locality",
    "wof:population":51
},
  "geometry": {"coordinates":[-100.05389,20.42444],"type":"Point"}
}