{
  "type": "Feature",
  "properties": {
    "gn:admin1_code":"12",
    "gn:admin2_code":"11.0",
    "gn:asciiname":"Colonia Vicente Guerrero",
    "gn:country_code":"MX",
    "gn:dem":33,
    "gn:feature_class":"P",
    "gn:feature_code":"PPL",
    "gn:name":"Colonia Vicente Guerrero",
    "gn:population":442,
    "gn:timezone":"America/Mexico_City",
    "iso:country":"MX",
    "wof:name":"Colonia Vicente Guerrero",
    "wof:placetype":"locality",
    "wof:population":442
},
  "geometry": {"coordinates":[-100.30361000000001,17.06861],"type":"Point"}
}