{
  "type": "Feature",
  "properties": {
    "gn:admin1_code":"18",
    "gn:admin2_code":"4.0",
    "gn:asciiname":"La Noria",
    "gn:country_code":"MX",
    "gn:dem":15,
    "gn:feature_class":"P",
    "gn:feature_code":"PPL",
    "gn:name":"La Noria",
    "gn:population":9,
    "gn:timezone":"America/Mazatlan",
    "iso:country":"MX",
    "wof:name":"La Noria",
    "wof:placetype":"locality",
    "wof:population":9
},
  "geometry": {"coordinates":[-105.23694,21.03611],"type":"Point"}
}