{
  "type": "Feature",
  "properties": {
    "gn:admin1_code":"26",
    "gn:admin2_code":"68.0",
    "gn:asciiname":"El Sahuaral",
    "gn:country_code":"MX",
    "gn:dem":567,
    "gn:feature_class":"P",
    "gn:feature_code":"PPL",
    "gn:name":"El Sahuaral",
    "gn:population":0,
    "gn:timezone":"America/Hermosillo",
    "iso:country":"MX",
    "name:spa_x_preferred":[
        "El Sahuaral"
    ],
    "wof:name":"El Sahuaral",
    "wof:placetype":"locality"
},
  "geometry": {"coordinates":[-110.07889,28.90833],"type":"Point"}
}