{
  "type": "Feature",
  "properties": {
    "gn:admin1_code":"13",
    "gn:admin2_code":"62",
    "gn:asciiname":"Tlaxcala",
    "gn:country_code":"MX",
    "gn:dem":1422,
    "gn:feature_class":"P",
    "gn:feature_code":"PPL",
    "gn:name":"Tlaxcala",
    "gn:population":9,
    "gn:timezone":"America/Mexico_City",
    "iso:country":"MX",
    "wof:name":"Tlaxcala",
    "wof:placetype":"locality",
    "wof:population":9
},
  "geometry": {"coordinates":[-98.91088000000001,21.02397],"type":"Point"}
}