{
  "type": "Feature",
  "properties": {
    "gn:admin1_code":"5",
    "gn:admin2_code":"4.0",
    "gn:asciiname":"Nuevo Progreso",
    "gn:country_code":"MX",
    "gn:dem":1029,
    "gn:feature_class":"P",
    "gn:feature_code":"PPL",
    "gn:name":"Nuevo Progreso",
    "gn:population":153,
    "gn:timezone":"America/Mexico_City",
    "iso:country":"MX",
    "wof:name":"Nuevo Progreso",
    "wof:placetype":"locality",
    "wof:population":153
},
  "geometry": {"coordinates":[-91.76000000000001,16.65306],"type":"Point"}
}