{
  "type": "Feature",
  "properties": {
    "gn:admin1_code":"32",
    "gn:admin2_code":"24.0",
    "gn:asciiname":"Norias de la Venta",
    "gn:cc2":"MX",
    "gn:country_code":"MX",
    "gn:dem":2022,
    "gn:feature_class":"P",
    "gn:feature_code":"PPL",
    "gn:name":"Norias de la Venta",
    "gn:population":235,
    "gn:timezone":"America/Mexico_City",
    "iso:country":"MX",
    "name:und_x_variant":[
        "Maravillas",
        "La Venta",
        "Venta de la Carrera"
    ],
    "wof:name":"Norias de la Venta",
    "wof:placetype":"locality",
    "wof:population":235
},
  "geometry": {"coordinates":[-102.02417,22.2875],"type":"Point"}
}