{
  "type": "Feature",
  "properties": {
    "gn:admin1_code":"11",
    "gn:admin2_code":"23.0",
    "gn:asciiname":"El Gato",
    "gn:country_code":"MX",
    "gn:dem":2289,
    "gn:feature_class":"P",
    "gn:feature_code":"PPL",
    "gn:name":"El Gato",
    "gn:population":8,
    "gn:timezone":"America/Mexico_City",
    "iso:country":"MX",
    "wof:name":"El Gato",
    "wof:placetype":"locality",
    "wof:population":8
},
  "geometry": {"coordinates":[-101.77361000000001,20.52833],"type":"Point"}
}