{
  "type": "Feature",
  "properties": {
    "gn:admin1_code":"2.0",
    "gn:admin2_code":"2.0",
    "gn:asciiname":"Ejido Hipolito Renteria",
    "gn:country_code":"MX",
    "gn:dem":15,
    "gn:feature_class":"P",
    "gn:feature_code":"PPL",
    "gn:name":"Ejido Hip\u00f3lito Renter\u00eda",
    "gn:population":491,
    "gn:timezone":"America/Tijuana",
    "iso:country":"MX",
    "name:spa_x_preferred":[
        "Ejido Hipolito Renteria"
    ],
    "wof:name":"Ejido Hipolito Renteria",
    "wof:placetype":"locality",
    "wof:population":491
},
  "geometry": {"coordinates":[-115.37222,32.43056],"type":"Point"}
}