{
  "type": "Feature",
  "properties": {
    "gn:admin1_code":"6",
    "gn:admin2_code":"5.0",
    "gn:asciiname":"San Manuel (Cerros Prietos)",
    "gn:country_code":"MX",
    "gn:dem":1246,
    "gn:feature_class":"P",
    "gn:feature_code":"PPL",
    "gn:name":"San Manuel (Cerros Prietos)",
    "gn:population":1,
    "gn:timezone":"America/Chihuahua",
    "iso:country":"MX",
    "wof:name":"San Manuel (Cerros Prietos)",
    "wof:placetype":"locality",
    "wof:population":1
},
  "geometry": {"coordinates":[-107.34039,31.23779],"type":"Point"}
}