{
  "type": "Feature",
  "properties": {
    "gn:admin1_code":"7.0",
    "gn:admin2_code":"15.0",
    "gn:asciiname":"El Cochi",
    "gn:country_code":"MX",
    "gn:dem":270,
    "gn:feature_class":"P",
    "gn:feature_code":"PPL",
    "gn:name":"El Cochi",
    "gn:population":0,
    "gn:timezone":"America/Monterrey",
    "iso:country":"MX",
    "name:spa_x_preferred":[
        "El Cochi"
    ],
    "wof:name":"El Cochi",
    "wof:placetype":"locality"
},
  "geometry": {"coordinates":[-100.71617999999999,27.56084],"type":"Point"}
}