{
  "type": "Feature",
  "properties": {
    "gn:admin1_code":"29",
    "gn:admin2_code":"12.0",
    "gn:asciiname":"El Ocotal",
    "gn:country_code":"MX",
    "gn:dem":2541,
    "gn:feature_class":"P",
    "gn:feature_code":"PPL",
    "gn:name":"El Ocotal",
    "gn:population":0,
    "gn:timezone":"America/Mexico_City",
    "iso:country":"MX",
    "name:spa_x_preferred":[
        "El Ocotal"
    ],
    "wof:name":"El Ocotal",
    "wof:placetype":"locality"
},
  "geometry": {"coordinates":[-98.42668999999999,19.41086],"type":"Point"}
}