{
  "type": "Feature",
  "properties": {
    "gn:admin1_code":"11",
    "gn:admin2_code":"27.0",
    "gn:asciiname":"Santa Catarina de Conejo",
    "gn:country_code":"MX",
    "gn:dem":1720,
    "gn:feature_class":"P",
    "gn:feature_code":"PPL",
    "gn:name":"Santa Catarina de Conejo",
    "gn:population":0,
    "gn:timezone":"America/Mexico_City",
    "iso:country":"MX",
    "name:spa_x_preferred":[
        "Santa Catarina de Conejo"
    ],
    "name:spa_x_variant":[
        "Santo Domingo"
    ],
    "wof:name":"Santa Catarina de Conejo",
    "wof:placetype":"locality"
},
  "geometry": {"coordinates":[-101.10821,20.54534],"type":"Point"}
}