{
  "type": "Feature",
  "properties": {
    "gn:admin1_code":"12.0",
    "gn:admin2_code":"68.0",
    "gn:asciiname":"Limoncito",
    "gn:country_code":"MX",
    "gn:dem":330,
    "gn:feature_class":"P",
    "gn:feature_code":"PPL",
    "gn:name":"Limoncito",
    "gn:population":0,
    "gn:timezone":"America/Mexico_City",
    "iso:country":"MX",
    "name:ceb_x_preferred":[
        "Limoncito"
    ],
    "name:deu_x_preferred":[
        "Limoncito"
    ],
    "name:und_x_variant":[
        "El Limoncito"
    ],
    "name:zho_x_preferred":[
        "\u5229\u8499\u897f\u6258"
    ],
    "wof:name":"Limoncito",
    "wof:placetype":"locality"
},
  "geometry": {"coordinates":[-101.82384999999999,18.06864],"type":"Point"}
}