{
  "type": "Feature",
  "properties": {
    "gn:admin1_code":"1",
    "gn:admin2_code":"7",
    "gn:asciiname":"La Cruz",
    "gn:country_code":"MX",
    "gn:dem":1915,
    "gn:feature_class":"P",
    "gn:feature_code":"PPL",
    "gn:name":"La Cruz",
    "gn:population":9,
    "gn:timezone":"America/Mexico_City",
    "iso:country":"MX",
    "wof:name":"La Cruz",
    "wof:placetype":"locality",
    "wof:population":9
},
  "geometry": {"coordinates":[-102.28917,22.17],"type":"Point"}
}