{
  "type": "Feature",
  "properties": {
    "gn:admin1_code":"21",
    "gn:admin2_code":"55.0",
    "gn:asciiname":"Santa Ana los Vazquez",
    "gn:country_code":"MX",
    "gn:dem":1666,
    "gn:feature_class":"P",
    "gn:feature_code":"PPL",
    "gn:name":"Santa Ana los V\u00e1zquez",
    "gn:population":75,
    "gn:timezone":"America/Mexico_City",
    "iso:country":"MX",
    "name:und_x_variant":[
        "Santa Ana los V\u00e1zquez"
    ],
    "wof:name":"Santa Ana los Vazquez",
    "wof:placetype":"locality",
    "wof:population":75
},
  "geometry": {"coordinates":[-97.92482,17.92797999999999],"type":"Point"}
}