{
  "type": "Feature",
  "properties": {
    "gn:admin1_code":"5",
    "gn:admin2_code":"109",
    "gn:asciiname":"Buenavista la Cueva",
    "gn:country_code":"MX",
    "gn:dem":998,
    "gn:feature_class":"P",
    "gn:feature_code":"PPL",
    "gn:name":"Buenavista la Cueva",
    "gn:population":36,
    "gn:timezone":"America/Mexico_City",
    "iso:country":"MX",
    "wof:name":"Buenavista la Cueva",
    "wof:placetype":"locality",
    "wof:population":36
},
  "geometry": {"coordinates":[-92.32611,17.20917],"type":"Point"}
}