{
  "type": "Feature",
  "properties": {
    "gn:admin1_code":"30",
    "gn:admin2_code":"58.0",
    "gn:asciiname":"Sasaltitla",
    "gn:country_code":"MX",
    "gn:dem":269,
    "gn:feature_class":"P",
    "gn:feature_code":"PPL",
    "gn:name":"Sasaltitla",
    "gn:population":0,
    "gn:timezone":"America/Mexico_City",
    "iso:country":"MX",
    "name:und_x_variant":[
        "Salsaltitla",
        "Sasaltitla"
    ],
    "wof:name":"Sasaltitla",
    "wof:placetype":"locality"
},
  "geometry": {"coordinates":[-98.19703,20.93518],"type":"Point"}
}