{
  "type": "Feature",
  "properties": {
    "gn:admin1_code":"18",
    "gn:admin2_code":"2.0",
    "gn:asciiname":"Uzeta",
    "gn:country_code":"MX",
    "gn:dem":775,
    "gn:feature_class":"P",
    "gn:feature_code":"PPL",
    "gn:name":"Uzeta",
    "gn:population":0,
    "gn:timezone":"America/Mazatlan",
    "iso:country":"MX",
    "name:spa_x_preferred":[
        "Uzeta"
    ],
    "wof:name":"Uzeta",
    "wof:placetype":"locality"
},
  "geometry": {"coordinates":[-104.60171,21.11497],"type":"Point"}
}