{
  "type": "Feature",
  "properties": {
    "gn:admin1_code":"12",
    "gn:admin2_code":"73.0",
    "gn:asciiname":"Las Juntas",
    "gn:country_code":"MX",
    "gn:dem":180,
    "gn:feature_class":"P",
    "gn:feature_code":"PPL",
    "gn:name":"Las Juntas",
    "gn:population":0,
    "gn:timezone":"America/Mexico_City",
    "iso:country":"MX",
    "name:ceb_x_preferred":[
        "Las Juntas"
    ],
    "name:deu_x_preferred":[
        "Las Juntas"
    ],
    "name:spa_x_preferred":[
        "Las Juntas"
    ],
    "name:swe_x_preferred":[
        "Las Juntas"
    ],
    "wof:name":"Las Juntas",
    "wof:placetype":"locality"
},
  "geometry": {"coordinates":[-101.47072,18.47753],"type":"Point"}
}