{
  "type": "Feature",
  "properties": {
    "gn:admin1_code":"20",
    "gn:admin2_code":"44",
    "gn:asciiname":"El Pomelar (El Olvido Dos)",
    "gn:country_code":"MX",
    "gn:dem":80,
    "gn:feature_class":"P",
    "gn:feature_code":"PPL",
    "gn:name":"El Pomelar (El Olvido Dos)",
    "gn:population":42,
    "gn:timezone":"America/Mexico_City",
    "iso:country":"MX",
    "wof:name":"El Pomelar (El Olvido Dos)",
    "wof:placetype":"locality",
    "wof:population":42
},
  "geometry": {"coordinates":[-95.88361,17.97861],"type":"Point"}
}