{
  "type": "Feature",
  "properties": {
    "gn:admin1_code":"6.0",
    "gn:admin2_code":"2.0",
    "gn:asciiname":"El Cacahuate",
    "gn:country_code":"MX",
    "gn:dem":1090,
    "gn:feature_class":"P",
    "gn:feature_code":"PPL",
    "gn:name":"El Cacahuate",
    "gn:population":0,
    "gn:timezone":"America/Chihuahua",
    "iso:country":"MX",
    "name:und_x_variant":[
        "Rancho El Cacahuate",
        "El Cacahuate"
    ],
    "wof:name":"El Cacahuate",
    "wof:placetype":"locality"
},
  "geometry": {"coordinates":[-105.45019000000001,28.90393],"type":"Point"}
}