{
  "type": "Feature",
  "properties": {
    "gn:admin1_code":"21",
    "gn:admin2_code":"207.0",
    "gn:asciiname":"Texocoyohuac",
    "gn:country_code":"MX",
    "gn:dem":2321,
    "gn:feature_class":"P",
    "gn:feature_code":"PPL",
    "gn:name":"Texocoyohuac",
    "gn:population":1040,
    "gn:timezone":"America/Mexico_City",
    "iso:country":"MX",
    "wof:name":"Texocoyohuac",
    "wof:placetype":"locality",
    "wof:population":1040
},
  "geometry": {"coordinates":[-97.59028000000001,19.77778],"type":"Point"}
}