{
  "type": "Feature",
  "properties": {
    "gn:admin1_code":"10.0",
    "gn:asciiname":"Cuchilla Larga",
    "gn:country_code":"MX",
    "gn:dem":340,
    "gn:feature_class":"P",
    "gn:feature_code":"PPL",
    "gn:name":"Cuchilla Larga",
    "gn:population":0,
    "gn:timezone":"America/Monterrey",
    "iso:country":"MX",
    "name:spa_x_preferred":[
        "Cuchilla Larga"
    ],
    "wof:name":"Cuchilla Larga",
    "wof:placetype":"locality"
},
  "geometry": {"coordinates":[-106.51091,24.73121],"type":"Point"}
}