{
  "type": "Feature",
  "properties": {
    "gn:admin1_code":"31",
    "gn:admin2_code":"11.0",
    "gn:asciiname":"Cholul",
    "gn:country_code":"MX",
    "gn:dem":5,
    "gn:feature_class":"P",
    "gn:feature_code":"PPL",
    "gn:name":"Cholul",
    "gn:population":0,
    "gn:timezone":"America/Merida",
    "iso:country":"MX",
    "name:spa_x_preferred":[
        "Cholul"
    ],
    "wof:name":"Cholul",
    "wof:placetype":"locality"
},
  "geometry": {"coordinates":[-90.37716,20.92388],"type":"Point"}
}