{
  "type": "Feature",
  "properties": {
    "gn:admin1_code":"30.0",
    "gn:asciiname":"Alto los Novios",
    "gn:country_code":"MX",
    "gn:dem":51,
    "gn:feature_class":"P",
    "gn:feature_code":"PPL",
    "gn:name":"Alto los Novios",
    "gn:population":0,
    "gn:timezone":"America/Mexico_City",
    "iso:country":"MX",
    "name:spa_x_preferred":[
        "Alto los Novios"
    ],
    "wof:name":"Alto los Novios",
    "wof:placetype":"locality"
},
  "geometry": {"coordinates":[-97.99505000000001,21.80781],"type":"Point"}
}