{
  "type": "Feature",
  "properties": {
    "gn:admin1_code":"5",
    "gn:admin2_code":"59.0",
    "gn:asciiname":"El Trapichito",
    "gn:country_code":"MX",
    "gn:dem":871,
    "gn:feature_class":"P",
    "gn:feature_code":"PPL",
    "gn:name":"El Trapichito",
    "gn:population":5,
    "gn:timezone":"America/Mexico_City",
    "iso:country":"MX",
    "wof:name":"El Trapichito",
    "wof:placetype":"locality",
    "wof:population":5
},
  "geometry": {"coordinates":[-91.99306,16.89861],"type":"Point"}
}