{
  "type": "Feature",
  "properties": {
    "gn:admin1_code":"30",
    "gn:admin2_code":"48",
    "gn:asciiname":"Mozapan",
    "gn:country_code":"MX",
    "gn:dem":9,
    "gn:feature_class":"P",
    "gn:feature_code":"PPL",
    "gn:name":"Mozapan",
    "gn:population":26,
    "gn:timezone":"America/Mexico_City",
    "iso:country":"MX",
    "wof:name":"Mozapan",
    "wof:placetype":"locality",
    "wof:population":26
},
  "geometry": {"coordinates":[-94.68194,17.88556],"type":"Point"}
}