{
  "type": "Feature",
  "properties": {
    "gn:admin1_code":"3",
    "gn:admin2_code":"8",
    "gn:asciiname":"Misiones del Cabo Baja [Hotel]",
    "gn:country_code":"MX",
    "gn:dem":21,
    "gn:feature_class":"P",
    "gn:feature_code":"PPL",
    "gn:name":"Misiones del Cabo Baja [Hotel]",
    "gn:population":28,
    "gn:timezone":"America/Mazatlan",
    "iso:country":"MX",
    "wof:name":"Misiones del Cabo Baja [Hotel]",
    "wof:placetype":"locality",
    "wof:population":28
},
  "geometry": {"coordinates":[-109.86596000000002,22.89801],"type":"Point"}
}