{
  "type": "Feature",
  "properties": {
    "gn:admin1_code":"14.0",
    "gn:admin2_code":"55.0",
    "gn:asciiname":"Tecuanapa",
    "gn:country_code":"MX",
    "gn:dem":1629,
    "gn:feature_class":"P",
    "gn:feature_code":"PPL",
    "gn:name":"Tecuanapa",
    "gn:population":0,
    "gn:timezone":"America/Mexico_City",
    "iso:country":"MX",
    "name:spa_x_preferred":[
        "Tecuanapa"
    ],
    "wof:name":"Tecuanapa",
    "wof:placetype":"locality"
},
  "geometry": {"coordinates":[-103.94071,20.8393],"type":"Point"}
}