{
  "type": "Feature",
  "properties": {
    "gn:admin1_code":"10",
    "gn:admin2_code":"2",
    "gn:asciiname":"La Mora (Cuesta de Pinitos)",
    "gn:country_code":"MX",
    "gn:dem":1070,
    "gn:feature_class":"P",
    "gn:feature_code":"PPL",
    "gn:name":"La Mora (Cuesta de Pinitos)",
    "gn:population":9,
    "gn:timezone":"America/Monterrey",
    "iso:country":"MX",
    "wof:name":"La Mora (Cuesta de Pinitos)",
    "wof:placetype":"locality",
    "wof:population":9
},
  "geometry": {"coordinates":[-106.58398,25.13914],"type":"Point"}
}