{
  "type": "Feature",
  "properties": {
    "gn:admin1_code":"30",
    "gn:admin2_code":"57",
    "gn:asciiname":"Loma Alta",
    "gn:country_code":"MX",
    "gn:dem":2225,
    "gn:feature_class":"P",
    "gn:feature_code":"PPL",
    "gn:name":"Loma Alta",
    "gn:population":25,
    "gn:timezone":"America/Mexico_City",
    "iso:country":"MX",
    "wof:name":"Loma Alta",
    "wof:placetype":"locality",
    "wof:population":25
},
  "geometry": {"coordinates":[-96.77639000000001,19.75583],"type":"Point"}
}