{
  "type": "Feature",
  "properties": {
    "gn:admin1_code":"20",
    "gn:admin2_code":"463.0",
    "gn:asciiname":"Ixtlahuaca",
    "gn:country_code":"MX",
    "gn:dem":1748,
    "gn:feature_class":"P",
    "gn:feature_code":"PPL",
    "gn:name":"Ixtlahuaca",
    "gn:population":0,
    "gn:timezone":"America/Mexico_City",
    "iso:country":"MX",
    "name:spa_x_preferred":[
        "Ixtlahuaca"
    ],
    "wof:name":"Ixtlahuaca",
    "wof:placetype":"locality"
},
  "geometry": {"coordinates":[-96.99827000000001,17.53952],"type":"Point"}
}