{
  "type": "Feature",
  "properties": {
    "gn:admin1_code":"10",
    "gn:admin2_code":"13.0",
    "gn:asciiname":"Rancho Grande",
    "gn:country_code":"MX",
    "gn:dem":1257,
    "gn:feature_class":"P",
    "gn:feature_code":"PPL",
    "gn:name":"Rancho Grande",
    "gn:population":0,
    "gn:timezone":"America/Monterrey",
    "iso:country":"MX",
    "name:spa_x_preferred":[
        "Rancho Grande"
    ],
    "name:spa_x_variant":[
        "Los Camacho"
    ],
    "wof:name":"Rancho Grande",
    "wof:placetype":"locality"
},
  "geometry": {"coordinates":[-104.28066,26.40153],"type":"Point"}
}