{
  "type": "Feature",
  "properties": {
    "gn:admin1_code":"10",
    "gn:admin2_code":"15.0",
    "gn:asciiname":"Los Lugo",
    "gn:country_code":"MX",
    "gn:dem":1668,
    "gn:feature_class":"P",
    "gn:feature_code":"PPL",
    "gn:name":"Los Lugo",
    "gn:population":0,
    "gn:timezone":"America/Monterrey",
    "iso:country":"MX",
    "name:spa_x_preferred":[
        "Los Lugo"
    ],
    "wof:name":"Los Lugo",
    "wof:placetype":"locality"
},
  "geometry": {"coordinates":[-104.11472000000001,25.51011],"type":"Point"}
}