{
  "type": "Feature",
  "properties": {
    "gn:admin1_code":"32",
    "gn:admin2_code":"42.0",
    "gn:asciiname":"San Francisco de Organos",
    "gn:country_code":"MX",
    "gn:dem":2346,
    "gn:feature_class":"P",
    "gn:feature_code":"PPL",
    "gn:name":"San Francisco de \u00d3rganos",
    "gn:population":0,
    "gn:timezone":"America/Mexico_City",
    "iso:country":"MX",
    "name:spa_x_preferred":[
        "San Francisco de \u00d3rganos"
    ],
    "wof:name":"San Francisco de Organos",
    "wof:placetype":"locality"
},
  "geometry": {"coordinates":[-103.77945,23.7522],"type":"Point"}
}