{
  "type": "Feature",
  "properties": {
    "gn:admin1_code":"24",
    "gn:admin2_code":"54.0",
    "gn:asciiname":"Sierra Mojada",
    "gn:country_code":"MX",
    "gn:dem":1442,
    "gn:feature_class":"P",
    "gn:feature_code":"PPL",
    "gn:name":"Sierra Mojada",
    "gn:population":99,
    "gn:timezone":"America/Mexico_City",
    "iso:country":"MX",
    "wof:name":"Sierra Mojada",
    "wof:placetype":"locality",
    "wof:population":99
},
  "geometry": {"coordinates":[-99.045,21.30917],"type":"Point"}
}