{
  "type": "Feature",
  "properties": {
    "gn:admin1_code":"24",
    "gn:admin2_code":"54.0",
    "gn:asciiname":"Sierra Mojada",
    "gn:country_code":"MX",
    "gn:dem":1442,
    "gn:feature_class":"P",
    "gn:feature_code":"PPL",
    "gn:name":"Sierra Mojada",
    "gn:population":99,
    "gn:timezone":"America/Mexico_City",
    "iso:country":"MX",
    "name:ceb_x_preferred":[
        "Sierra Mojada"
    ],
    "name:rus_x_preferred":[
        "\u0421\u044c\u0435\u0440\u0440\u0430-\u041c\u043e\u0445\u0430\u0434\u0430"
    ],
    "name:sco_x_preferred":[
        "Sierra Mojada"
    ],
    "name:spa_x_preferred":[
        "Sierra Mojada"
    ],
    "name:srp_x_preferred":[
        "\u0421\u0438\u0458\u0435\u0440\u0430 \u041c\u043e\u0445\u0430\u0434\u0430"
    ],
    "name:swe_x_preferred":[
        "Sierra Mojada"
    ],
    "name:vie_x_preferred":[
        "Sierra Mojada"
    ],
    "wof:name":"Sierra Mojada",
    "wof:placetype":"locality",
    "wof:population":99
},
  "geometry": {"coordinates":[-99.045,21.30917],"type":"Point"}
}