{
  "type": "Feature",
  "properties": {
    "gn:admin1_code":"12",
    "gn:admin2_code":"66.0",
    "gn:asciiname":"Xalatzala",
    "gn:country_code":"MX",
    "gn:dem":1703,
    "gn:feature_class":"P",
    "gn:feature_code":"PPL",
    "gn:name":"Xalatzala",
    "gn:population":2042,
    "gn:timezone":"America/Mexico_City",
    "iso:country":"MX",
    "name:spa_x_preferred":[
        "Xalatzala"
    ],
    "wof:name":"Xalatzala",
    "wof:placetype":"locality",
    "wof:population":2042
},
  "geometry": {"coordinates":[-98.57355,17.47355],"type":"Point"}
}