{
  "type": "Feature",
  "properties": {
    "gn:admin1_code":"7",
    "gn:admin2_code":"24.0",
    "gn:asciiname":"San Francisco del Barreal",
    "gn:country_code":"MX",
    "gn:dem":1266,
    "gn:feature_class":"P",
    "gn:feature_code":"PPL",
    "gn:name":"San Francisco del Barreal",
    "gn:population":0,
    "gn:timezone":"America/Monterrey",
    "iso:country":"MX",
    "name:spa_x_preferred":[
        "San Francisco del Barreal"
    ],
    "name:und_x_variant":[
        "San Francisco del Barrial"
    ],
    "wof:name":"San Francisco del Barreal",
    "wof:placetype":"locality"
},
  "geometry": {"coordinates":[-102.13706999999999,25.18551],"type":"Point"}
}