{
  "type": "Feature",
  "properties": {
    "gn:admin1_code":"25",
    "gn:admin2_code":"8",
    "gn:asciiname":"La Papalota",
    "gn:country_code":"MX",
    "gn:dem":121,
    "gn:feature_class":"P",
    "gn:feature_code":"PPL",
    "gn:name":"La Papalota",
    "gn:population":14,
    "gn:timezone":"America/Mazatlan",
    "iso:country":"MX",
    "wof:name":"La Papalota",
    "wof:placetype":"locality",
    "wof:population":14
},
  "geometry": {"coordinates":[-106.78309,24.08249],"type":"Point"}
}