{
  "type": "Feature",
  "properties": {
    "gn:admin1_code":"19",
    "gn:admin2_code":"14.0",
    "gn:asciiname":"Santa Teresa de San Juan (Rancho de Juana)",
    "gn:country_code":"MX",
    "gn:dem":1793,
    "gn:feature_class":"P",
    "gn:feature_code":"PPL",
    "gn:name":"Santa Teresa de San Juan (Rancho de Juana)",
    "gn:population":11,
    "gn:timezone":"America/Monterrey",
    "iso:country":"MX",
    "wof:name":"Santa Teresa de San Juan (Rancho de Juana)",
    "wof:placetype":"locality",
    "wof:population":11
},
  "geometry": {"coordinates":[-100.16327,23.65619],"type":"Point"}
}