{
  "type": "Feature",
  "properties": {
    "gn:admin1_code":"6",
    "gn:admin2_code":"29.0",
    "gn:asciiname":"Cabeza de Borrego",
    "gn:country_code":"MX",
    "gn:dem":2479,
    "gn:feature_class":"P",
    "gn:feature_code":"PPL",
    "gn:name":"Cabeza de Borrego",
    "gn:population":5,
    "gn:timezone":"America/Chihuahua",
    "iso:country":"MX",
    "wof:name":"Cabeza de Borrego",
    "wof:placetype":"locality",
    "wof:population":5
},
  "geometry": {"coordinates":[-106.82402999999999,26.28495],"type":"Point"}
}