{
  "type": "Feature",
  "properties": {
    "gn:admin1_code":"5",
    "gn:admin2_code":"4.0",
    "gn:asciiname":"Ocho de Marzo",
    "gn:country_code":"MX",
    "gn:dem":1194,
    "gn:feature_class":"P",
    "gn:feature_code":"PPL",
    "gn:name":"Ocho de Marzo",
    "gn:population":99,
    "gn:timezone":"America/Mexico_City",
    "iso:country":"MX",
    "wof:name":"Ocho de Marzo",
    "wof:placetype":"locality",
    "wof:population":99
},
  "geometry": {"coordinates":[-91.83778,16.68778],"type":"Point"}
}