{
  "type": "Feature",
  "properties": {
    "gn:admin1_code":"30",
    "gn:admin2_code":"175.0",
    "gn:asciiname":"Buenos Aires",
    "gn:country_code":"MX",
    "gn:dem":135,
    "gn:feature_class":"P",
    "gn:feature_code":"PPL",
    "gn:name":"Buenos Aires",
    "gn:population":7,
    "gn:timezone":"America/Mexico_City",
    "iso:country":"MX",
    "wof:name":"Buenos Aires",
    "wof:placetype":"locality",
    "wof:population":7
},
  "geometry": {"coordinates":[-97.60778000000001,20.6525],"type":"Point"}
}