{
  "type": "Feature",
  "properties": {
    "gn:admin1_code":"30",
    "gn:admin2_code":"70.0",
    "gn:asciiname":"Ninos Heroes",
    "gn:country_code":"MX",
    "gn:dem":56,
    "gn:feature_class":"P",
    "gn:feature_code":"PPL",
    "gn:name":"Ni\u00f1os H\u00e9roes",
    "gn:population":0,
    "gn:timezone":"America/Mexico_City",
    "iso:country":"MX",
    "name:spa_x_preferred":[
        "Ni\u00f1os H\u00e9roes"
    ],
    "wof:name":"Ninos Heroes",
    "wof:placetype":"locality"
},
  "geometry": {"coordinates":[-94.55379000000001,17.45311],"type":"Point"}
}