{
  "type": "Feature",
  "properties": {
    "gn:admin1_code":"20",
    "gn:admin2_code":"41.0",
    "gn:asciiname":"Plan Carlota",
    "gn:country_code":"MX",
    "gn:dem":1540,
    "gn:feature_class":"P",
    "gn:feature_code":"PPL",
    "gn:name":"Plan Carlota",
    "gn:population":41,
    "gn:timezone":"America/Mexico_City",
    "iso:country":"MX",
    "name:spa_x_preferred":[
        "Plan Camota"
    ],
    "name:spa_x_variant":[
        "Plan Carlota"
    ],
    "wof:name":"Plan Carlota",
    "wof:placetype":"locality",
    "wof:population":41
},
  "geometry": {"coordinates":[-96.77715999999999,18.13406],"type":"Point"}
}