{
  "type": "Feature",
  "properties": {
    "gn:admin1_code":"30",
    "gn:admin2_code":"122.0",
    "gn:asciiname":"Lorenzo Azua Torres",
    "gn:country_code":"MX",
    "gn:dem":13,
    "gn:feature_class":"P",
    "gn:feature_code":"PPL",
    "gn:name":"Lorenzo Azua Torres",
    "gn:population":96,
    "gn:timezone":"America/Mexico_City",
    "iso:country":"MX",
    "wof:name":"Lorenzo Azua Torres",
    "wof:placetype":"locality",
    "wof:population":96
},
  "geometry": {"coordinates":[-94.64972,18.10944],"type":"Point"}
}