{
  "type": "Feature",
  "properties": {
    "gn:admin1_code":"10",
    "gn:admin2_code":"7.0",
    "gn:asciiname":"Santona",
    "gn:country_code":"MX",
    "gn:dem":1119,
    "gn:feature_class":"P",
    "gn:feature_code":"PPL",
    "gn:name":"Santo\u00f1a",
    "gn:population":0,
    "gn:timezone":"America/Monterrey",
    "iso:country":"MX",
    "name:und_x_variant":[
        "Sante\u00f1a",
        "Santo\u00f1a"
    ],
    "wof:name":"Santona",
    "wof:placetype":"locality"
},
  "geometry": {"coordinates":[-103.36429,25.68662],"type":"Point"}
}