{
  "type": "Feature",
  "properties": {
    "gn:admin1_code":"16",
    "gn:admin2_code":"99.0",
    "gn:asciiname":"La Pinzanera",
    "gn:country_code":"MX",
    "gn:dem":601,
    "gn:feature_class":"P",
    "gn:feature_code":"PPL",
    "gn:name":"La Pinzanera",
    "gn:population":110,
    "gn:timezone":"America/Mexico_City",
    "iso:country":"MX",
    "wof:name":"La Pinzanera",
    "wof:placetype":"locality",
    "wof:population":110
},
  "geometry": {"coordinates":[-100.56610999999999,19.215],"type":"Point"}
}