{
  "type": "Feature",
  "properties": {
    "gn:admin1_code":"15",
    "gn:admin2_code":"114.0",
    "gn:asciiname":"Loma del Lienzo",
    "gn:country_code":"MX",
    "gn:dem":2644,
    "gn:feature_class":"P",
    "gn:feature_code":"PPL",
    "gn:name":"Loma del Lienzo",
    "gn:population":0,
    "gn:timezone":"America/Mexico_City",
    "iso:country":"MX",
    "name:spa_x_preferred":[
        "Loma del Lienzo"
    ],
    "name:und_x_variant":[
        "Loma El Lienzo"
    ],
    "wof:name":"Loma del Lienzo",
    "wof:placetype":"locality"
},
  "geometry": {"coordinates":[-99.96592,19.49168],"type":"Point"}
}