{
  "type": "Feature",
  "properties": {
    "gn:admin1_code":"4",
    "gn:admin2_code":"4.0",
    "gn:asciiname":"Tres Jobos",
    "gn:country_code":"MX",
    "gn:dem":22,
    "gn:feature_class":"P",
    "gn:feature_code":"PPL",
    "gn:name":"Tres Jobos",
    "gn:population":0,
    "gn:timezone":"America/Merida",
    "iso:country":"MX",
    "name:spa_x_preferred":[
        "Tres Jobos"
    ],
    "wof:name":"Tres Jobos",
    "wof:placetype":"locality"
},
  "geometry": {"coordinates":[-90.63764,19.13209],"type":"Point"}
}