{
  "type": "Feature",
  "properties": {
    "gn:admin1_code":"26",
    "gn:admin2_code":"33.0",
    "gn:asciiname":"Jitosiaric",
    "gn:country_code":"MX",
    "gn:dem":43,
    "gn:feature_class":"P",
    "gn:feature_code":"PPL",
    "gn:name":"Jitosi\u00e1ric",
    "gn:population":6,
    "gn:timezone":"America/Hermosillo",
    "iso:country":"MX",
    "name:und_x_variant":[
        "Jitosi\u00e1ric"
    ],
    "wof:name":"Jitosiaric",
    "wof:placetype":"locality",
    "wof:population":6
},
  "geometry": {"coordinates":[-109.29306,26.70556],"type":"Point"}
}