{
  "type": "Feature",
  "properties": {
    "gn:admin1_code":"10",
    "gn:admin2_code":"23.0",
    "gn:asciiname":"Las Pintas",
    "gn:country_code":"MX",
    "gn:dem":2546,
    "gn:feature_class":"P",
    "gn:feature_code":"PPL",
    "gn:name":"Las Pintas",
    "gn:population":0,
    "gn:timezone":"America/Monterrey",
    "iso:country":"MX",
    "name:spa_x_preferred":[
        "Las Pintas"
    ],
    "wof:name":"Las Pintas",
    "wof:placetype":"locality"
},
  "geometry": {"coordinates":[-105.42289,23.85431],"type":"Point"}
}