{
  "type": "Feature",
  "properties": {
    "gn:admin1_code":"5",
    "gn:admin2_code":"57.0",
    "gn:asciiname":"San Fernando",
    "gn:country_code":"MX",
    "gn:dem":1470,
    "gn:feature_class":"P",
    "gn:feature_code":"PPL",
    "gn:name":"San Fernando",
    "gn:population":232,
    "gn:timezone":"America/Mexico_City",
    "iso:country":"MX",
    "wof:name":"San Fernando",
    "wof:placetype":"locality",
    "wof:population":232
},
  "geometry": {"coordinates":[-92.42833,15.37306],"type":"Point"}
}