{
  "type": "Feature",
  "properties": {
    "gn:admin1_code":"1",
    "gn:admin2_code":"10.0",
    "gn:asciiname":"Tanque el Coyote (El Coyote)",
    "gn:country_code":"MX",
    "gn:dem":2025,
    "gn:feature_class":"P",
    "gn:feature_code":"PPL",
    "gn:name":"Tanque el Coyote (El Coyote)",
    "gn:population":80,
    "gn:timezone":"America/Mexico_City",
    "iso:country":"MX",
    "wof:name":"Tanque el Coyote (El Coyote)",
    "wof:placetype":"locality",
    "wof:population":80
},
  "geometry": {"coordinates":[-102.05389,21.89722],"type":"Point"}
}