{
  "type": "Feature",
  "properties": {
    "gn:admin1_code":"26.0",
    "gn:admin2_code":"30.0",
    "gn:asciiname":"El Sapo",
    "gn:country_code":"MX",
    "gn:dem":56,
    "gn:feature_class":"P",
    "gn:feature_code":"PPL",
    "gn:name":"El Sapo",
    "gn:population":24,
    "gn:timezone":"America/Hermosillo",
    "iso:country":"MX",
    "name:und_x_variant":[
        "Zapo",
        "Rancho El Sapo",
        "Sapo",
        "El Sapo"
    ],
    "wof:name":"El Sapo",
    "wof:placetype":"locality",
    "wof:population":24
},
  "geometry": {"coordinates":[-111.31682000000001,28.63291],"type":"Point"}
}