{
  "type": "Feature",
  "properties": {
    "gn:admin1_code":"20",
    "gn:admin2_code":"180.0",
    "gn:asciiname":"San Pedro Orizaba",
    "gn:country_code":"MX",
    "gn:dem":85,
    "gn:feature_class":"P",
    "gn:feature_code":"PPL",
    "gn:name":"San Pedro Orizaba",
    "gn:population":423,
    "gn:timezone":"America/Mexico_City",
    "iso:country":"MX",
    "name:spa_x_preferred":[
        "San Pedro Orizaba"
    ],
    "wof:name":"San Pedro Orizaba",
    "wof:placetype":"locality",
    "wof:population":423
},
  "geometry": {"coordinates":[-98.33139,16.46917],"type":"Point"}
}