{
  "type": "Feature",
  "properties": {
    "gn:admin1_code":"14.0",
    "gn:admin2_code":"97.0",
    "gn:asciiname":"Cruz Vieja",
    "gn:country_code":"MX",
    "gn:dem":1499,
    "gn:feature_class":"P",
    "gn:feature_code":"PPL",
    "gn:name":"Cruz Vieja",
    "gn:population":0,
    "gn:timezone":"America/Mexico_City",
    "iso:country":"MX",
    "wof:name":"Cruz Vieja",
    "wof:placetype":"locality"
},
  "geometry": {"coordinates":[-103.57371000000001,20.49536],"type":"Point"}
}