{
  "type": "Feature",
  "properties": {
    "gn:admin1_code":"6",
    "gn:admin2_code":"26.0",
    "gn:asciiname":"Majalca",
    "gn:country_code":"MX",
    "gn:dem":1686,
    "gn:feature_class":"P",
    "gn:feature_code":"PPL",
    "gn:name":"Majalca",
    "gn:population":0,
    "gn:timezone":"America/Chihuahua",
    "iso:country":"MX",
    "wof:name":"Majalca",
    "wof:placetype":"locality"
},
  "geometry": {"coordinates":[-106.56946000000001,28.22464],"type":"Point"}
}