{
  "type": "Feature",
  "properties": {
    "gn:admin1_code":"30",
    "gn:admin2_code":"110.0",
    "gn:asciiname":"Barrio Segundo",
    "gn:country_code":"MX",
    "gn:dem":1694,
    "gn:feature_class":"P",
    "gn:feature_code":"PPL",
    "gn:name":"Barrio Segundo",
    "gn:population":962,
    "gn:timezone":"America/Mexico_City",
    "iso:country":"MX",
    "wof:name":"Barrio Segundo",
    "wof:placetype":"locality",
    "wof:population":962
},
  "geometry": {"coordinates":[-96.98806,18.59611],"type":"Point"}
}