{
  "type": "Feature",
  "properties": {
    "gn:admin1_code":"20",
    "gn:admin2_code":"473.0",
    "gn:asciiname":"Santa Catarina",
    "gn:country_code":"MX",
    "gn:dem":2187,
    "gn:feature_class":"P",
    "gn:feature_code":"PPL",
    "gn:name":"Santa Catarina",
    "gn:population":0,
    "gn:timezone":"America/Mexico_City",
    "iso:country":"MX",
    "name:spa_x_preferred":[
        "Yahuis"
    ],
    "name:spa_x_variant":[
        "Santa Catarina",
        "Santa Catarina Yahu\u00edo"
    ],
    "name:und_x_variant":[
        "Santa Catarina Yahuio",
        "Yahuio"
    ],
    "wof:name":"Santa Catarina",
    "wof:placetype":"locality"
},
  "geometry": {"coordinates":[-96.29613000000001,17.22143],"type":"Point"}
}