{
  "type": "Feature",
  "properties": {
    "gn:admin1_code":"30",
    "gn:admin2_code":"174.0",
    "gn:asciiname":"El Torito",
    "gn:country_code":"MX",
    "gn:dem":95,
    "gn:feature_class":"P",
    "gn:feature_code":"PPL",
    "gn:name":"El Torito",
    "gn:population":5,
    "gn:timezone":"America/Mexico_City",
    "iso:country":"MX",
    "name:dan_x_preferred":[
        "El Torito"
    ],
    "name:pol_x_preferred":[
        "El Torito"
    ],
    "name:por_x_preferred":[
        "El Torito"
    ],
    "wof:name":"El Torito",
    "wof:placetype":"locality",
    "wof:population":5
},
  "geometry": {"coordinates":[-96.41249999999999,18.61389],"type":"Point"}
}