{
  "type": "Feature",
  "properties": {
    "gn:admin1_code":"16",
    "gn:admin2_code":"93.0",
    "gn:asciiname":"Puerto de las Huertas (Ejido Tlalpujahuilla)",
    "gn:country_code":"MX",
    "gn:dem":2791,
    "gn:feature_class":"P",
    "gn:feature_code":"PPL",
    "gn:name":"Puerto de las Huertas (Ejido Tlalpujahuilla)",
    "gn:population":113,
    "gn:timezone":"America/Mexico_City",
    "iso:country":"MX",
    "wof:name":"Puerto de las Huertas (Ejido Tlalpujahuilla)",
    "wof:placetype":"locality",
    "wof:population":113
},
  "geometry": {"coordinates":[-100.16083,19.735],"type":"Point"}
}