{
  "type": "Feature",
  "properties": {
    "gn:admin1_code":"27",
    "gn:admin2_code":"17.0",
    "gn:asciiname":"Santa Dolores",
    "gn:country_code":"MX",
    "gn:dem":57,
    "gn:feature_class":"P",
    "gn:feature_code":"PPL",
    "gn:name":"Santa Dolores",
    "gn:population":0,
    "gn:timezone":"America/Mexico_City",
    "iso:country":"MX",
    "name:spa_x_preferred":[
        "Santa Dolores"
    ],
    "wof:name":"Santa Dolores",
    "wof:placetype":"locality"
},
  "geometry": {"coordinates":[-91.29167,17.48333],"type":"Point"}
}