{
  "type": "Feature",
  "properties": {
    "gn:admin1_code":"24",
    "gn:admin2_code":"52.0",
    "gn:asciiname":"San Jose del Matorral",
    "gn:country_code":"MX",
    "gn:dem":1125,
    "gn:feature_class":"P",
    "gn:feature_code":"PPL",
    "gn:name":"San Jos\u00e9 del Matorral",
    "gn:population":174,
    "gn:timezone":"America/Mexico_City",
    "iso:country":"MX",
    "wof:name":"San Jose del Matorral",
    "wof:placetype":"locality",
    "wof:population":174
},
  "geometry": {"coordinates":[-100.28175,22.36348],"type":"Point"}
}