{
  "type": "Feature",
  "properties": {
    "gn:admin1_code":"7",
    "gn:admin2_code":"28.0",
    "gn:asciiname":"Norita",
    "gn:country_code":"MX",
    "gn:dem":345,
    "gn:feature_class":"P",
    "gn:feature_code":"PPL",
    "gn:name":"Norita",
    "gn:population":0,
    "gn:timezone":"America/Monterrey",
    "iso:country":"MX",
    "name:jpn_x_preferred":[
        "\u30ce\u30ea\u30bf\u5149\u5b66"
    ],
    "name:spa_x_preferred":[
        "Norita"
    ],
    "wof:name":"Norita",
    "wof:placetype":"locality"
},
  "geometry": {"coordinates":[-101.09085,27.69806],"type":"Point"}
}