{
  "type": "Feature",
  "properties": {
    "gn:admin1_code":"6",
    "gn:admin2_code":"24.0",
    "gn:asciiname":"La Tinaja",
    "gn:cc2":"MX",
    "gn:country_code":"MX",
    "gn:dem":1683,
    "gn:feature_class":"P",
    "gn:feature_code":"PPL",
    "gn:name":"La Tinaja",
    "gn:population":2,
    "gn:timezone":"America/Chihuahua",
    "iso:country":"MX",
    "name:und_x_variant":[
        "San Fernando",
        "Rancho Tinajas",
        "Tinajas",
        "Tinaja"
    ],
    "wof:name":"La Tinaja",
    "wof:placetype":"locality",
    "wof:population":2
},
  "geometry": {"coordinates":[-106.2877,28.36047],"type":"Point"}
}