{
  "type": "Feature",
  "properties": {
    "gn:admin1_code":"28",
    "gn:admin2_code":"17.0",
    "gn:asciiname":"Monte Redondo",
    "gn:country_code":"MX",
    "gn:dem":981,
    "gn:feature_class":"P",
    "gn:feature_code":"PPL",
    "gn:name":"Monte Redondo",
    "gn:population":0,
    "gn:timezone":"America/Monterrey",
    "iso:country":"MX",
    "name:spa_x_preferred":[
        "Monte Redondo"
    ],
    "wof:name":"Monte Redondo",
    "wof:placetype":"locality"
},
  "geometry": {"coordinates":[-99.47615,23.36809],"type":"Point"}
}