{
  "type": "Feature",
  "properties": {
    "gn:admin1_code":"12.0",
    "gn:admin2_code":"57.0",
    "gn:asciiname":"La Cana",
    "gn:country_code":"MX",
    "gn:dem":409,
    "gn:feature_class":"P",
    "gn:feature_code":"PPL",
    "gn:name":"La Ca\u00f1a",
    "gn:population":91,
    "gn:timezone":"America/Mexico_City",
    "iso:country":"MX",
    "wof:name":"La Cana",
    "wof:placetype":"locality",
    "wof:population":91
},
  "geometry": {"coordinates":[-100.54080999999999,17.24783],"type":"Point"}
}