{
  "type": "Feature",
  "properties": {
    "gn:admin1_code":"30",
    "gn:admin2_code":"127.0",
    "gn:asciiname":"Tuzantla",
    "gn:country_code":"MX",
    "gn:dem":2026,
    "gn:feature_class":"P",
    "gn:feature_code":"PPL",
    "gn:name":"Tuzantla",
    "gn:population":875,
    "gn:timezone":"America/Mexico_City",
    "iso:country":"MX",
    "wof:name":"Tuzantla",
    "wof:placetype":"locality",
    "wof:population":875
},
  "geometry": {"coordinates":[-97.15639,18.95722],"type":"Point"}
}