{
  "type": "Feature",
  "properties": {
    "gn:admin1_code":"30",
    "gn:admin2_code":"127.0",
    "gn:asciiname":"Tuzantla",
    "gn:country_code":"MX",
    "gn:dem":2026,
    "gn:feature_class":"P",
    "gn:feature_code":"PPL",
    "gn:name":"Tuzantla",
    "gn:population":875,
    "gn:timezone":"America/Mexico_City",
    "iso:country":"MX",
    "name:ceb_x_preferred":[
        "Tuzantla"
    ],
    "name:epo_x_preferred":[
        "Tuzantla"
    ],
    "name:eus_x_preferred":[
        "Tuzantla"
    ],
    "name:ita_x_preferred":[
        "Tuzantla"
    ],
    "name:sco_x_preferred":[
        "Tuzantla"
    ],
    "name:srp_x_preferred":[
        "\u041e\u043f\u0448\u0442\u0438\u043d\u0430 \u0422\u0443\u0437\u0430\u043d\u0442\u043b\u0430"
    ],
    "name:swe_x_preferred":[
        "Tuzantla"
    ],
    "name:vie_x_preferred":[
        "Tuzantla"
    ],
    "wof:name":"Tuzantla",
    "wof:placetype":"locality",
    "wof:population":875
},
  "geometry": {"coordinates":[-97.15639,18.95722],"type":"Point"}
}