{
  "type": "Feature",
  "properties": {
    "gn:admin1_code":"5",
    "gn:admin2_code":"44.0",
    "gn:asciiname":"El Zapotillo",
    "gn:country_code":"MX",
    "gn:dem":1012,
    "gn:feature_class":"P",
    "gn:feature_code":"PPL",
    "gn:name":"El Zapotillo",
    "gn:population":0,
    "gn:timezone":"America/Mexico_City",
    "iso:country":"MX",
    "name:spa_x_preferred":[
        "El Zapotillo"
    ],
    "name:spa_x_variant":[
        "Zapotillo"
    ],
    "wof:name":"El Zapotillo",
    "wof:placetype":"locality"
},
  "geometry": {"coordinates":[-92.95152,16.837],"type":"Point"}
}