{
  "type": "Feature",
  "properties": {
    "gn:admin1_code":"19.0",
    "gn:admin2_code":"24.0",
    "gn:asciiname":"Las Mesitas",
    "gn:country_code":"MX",
    "gn:dem":2046,
    "gn:feature_class":"P",
    "gn:feature_code":"PPL",
    "gn:name":"Las Mesitas",
    "gn:population":10,
    "gn:timezone":"America/Monterrey",
    "iso:country":"MX",
    "name:spa_x_preferred":[
        "Las Mesitas"
    ],
    "wof:name":"Las Mesitas",
    "wof:placetype":"locality",
    "wof:population":10
},
  "geometry": {"coordinates":[-99.66106000000001,23.97703],"type":"Point"}
}