{
  "type": "Feature",
  "properties": {
    "gn:admin1_code":"14.0",
    "gn:admin2_code":"37.0",
    "gn:asciiname":"Rancho El Porvenir",
    "gn:country_code":"MX",
    "gn:dem":892,
    "gn:feature_class":"P",
    "gn:feature_code":"PPL",
    "gn:name":"Rancho El Porvenir",
    "gn:population":0,
    "gn:timezone":"America/Mexico_City",
    "iso:country":"MX",
    "name:spa_x_preferred":[
        "Rancho El Porvenir"
    ],
    "wof:name":"Rancho El Porvenir",
    "wof:placetype":"locality"
},
  "geometry": {"coordinates":[-104.16691,19.79956],"type":"Point"}
}