{
  "type": "Feature",
  "properties": {
    "gn:admin1_code":"5",
    "gn:admin2_code":"23.0",
    "gn:asciiname":"Jtzav",
    "gn:country_code":"MX",
    "gn:dem":2456,
    "gn:feature_class":"P",
    "gn:feature_code":"PPL",
    "gn:name":"Jtzav",
    "gn:population":341,
    "gn:timezone":"America/Mexico_City",
    "iso:country":"MX",
    "wof:name":"Jtzav",
    "wof:placetype":"locality",
    "wof:population":341
},
  "geometry": {"coordinates":[-92.54833000000001,16.7675],"type":"Point"}
}