{
  "type": "Feature",
  "properties": {
    "gn:admin1_code":"21",
    "gn:admin2_code":"112",
    "gn:asciiname":"La Pila Verde",
    "gn:country_code":"MX",
    "gn:dem":1258,
    "gn:feature_class":"P",
    "gn:feature_code":"PPL",
    "gn:name":"La Pila Verde",
    "gn:population":10,
    "gn:timezone":"America/Mexico_City",
    "iso:country":"MX",
    "wof:name":"La Pila Verde",
    "wof:placetype":"locality",
    "wof:population":10
},
  "geometry": {"coordinates":[-97.98652,18.08551],"type":"Point"}
}