{
  "type": "Feature",
  "properties": {
    "gn:admin1_code":"31",
    "gn:admin2_code":"22.0",
    "gn:asciiname":"Yodzonot",
    "gn:country_code":"MX",
    "gn:dem":33,
    "gn:feature_class":"P",
    "gn:feature_code":"PPL",
    "gn:name":"Yodzonot",
    "gn:population":0,
    "gn:timezone":"America/Merida",
    "iso:country":"MX",
    "name:spa_x_preferred":[
        "Yodzonot"
    ],
    "wof:name":"Yodzonot",
    "wof:placetype":"locality"
},
  "geometry": {"coordinates":[-88.57899,20.24346],"type":"Point"}
}