{
  "type": "Feature",
  "properties": {
    "gn:admin1_code":"5",
    "gn:admin2_code":"22.0",
    "gn:asciiname":"Pom",
    "gn:country_code":"MX",
    "gn:dem":1552,
    "gn:feature_class":"P",
    "gn:feature_code":"PPL",
    "gn:name":"Pom",
    "gn:population":214,
    "gn:timezone":"America/Mexico_City",
    "iso:country":"MX",
    "wof:name":"Pom",
    "wof:placetype":"locality",
    "wof:population":214
},
  "geometry": {"coordinates":[-92.57333,16.96444],"type":"Point"}
}