{
  "type": "Feature",
  "properties": {
    "gn:admin1_code":"10",
    "gn:admin2_code":"17.0",
    "gn:asciiname":"Saltillo",
    "gn:country_code":"MX",
    "gn:dem":1957,
    "gn:feature_class":"P",
    "gn:feature_code":"PPL",
    "gn:name":"Saltillo",
    "gn:population":29,
    "gn:timezone":"America/Monterrey",
    "iso:country":"MX",
    "wof:name":"Saltillo",
    "wof:placetype":"locality",
    "wof:population":29
},
  "geometry": {"coordinates":[-105.8952,26.65406],"type":"Point"}
}