{
  "type": "Feature",
  "properties": {
    "gn:admin1_code":"19",
    "gn:admin2_code":"38.0",
    "gn:asciiname":"La Cantera",
    "gn:country_code":"MX",
    "gn:dem":388,
    "gn:feature_class":"P",
    "gn:feature_code":"PPL",
    "gn:name":"La Cantera",
    "gn:population":0,
    "gn:timezone":"America/Monterrey",
    "iso:country":"MX",
    "name:spa_x_preferred":[
        "Puerto La Cantera"
    ],
    "name:und_x_variant":[
        "Cantera",
        "La Cantera"
    ],
    "wof:name":"La Cantera",
    "wof:placetype":"locality"
},
  "geometry": {"coordinates":[-99.78281,25.21728],"type":"Point"}
}