{
  "type": "Feature",
  "properties": {
    "gn:admin1_code":"19",
    "gn:admin2_code":"11.0",
    "gn:asciiname":"El Muerto",
    "gn:country_code":"MX",
    "gn:dem":289,
    "gn:feature_class":"P",
    "gn:feature_code":"PPL",
    "gn:name":"El Muerto",
    "gn:population":0,
    "gn:timezone":"America/Monterrey",
    "iso:country":"MX",
    "name:spa_x_preferred":[
        "El Muerto"
    ],
    "name:und_x_variant":[
        "Muerto"
    ],
    "wof:name":"El Muerto",
    "wof:placetype":"locality"
},
  "geometry": {"coordinates":[-99.64318,25.96708],"type":"Point"}
}