{
  "type": "Feature",
  "properties": {
    "gn:admin1_code":"11",
    "gn:admin2_code":"11",
    "gn:asciiname":"Colonia Alameda San Jose de los Amoles",
    "gn:country_code":"MX",
    "gn:dem":1734,
    "gn:feature_class":"P",
    "gn:feature_code":"PPL",
    "gn:name":"Colonia Alameda San Jos\u00e9 de los Amoles",
    "gn:population":29,
    "gn:timezone":"America/Mexico_City",
    "iso:country":"MX",
    "name:und_x_variant":[
        "Colonia Alameda San Jos\u00e9 de los Amoles"
    ],
    "wof:name":"Colonia Alameda San Jose de los Amoles",
    "wof:placetype":"locality",
    "wof:population":29
},
  "geometry": {"coordinates":[-100.995,20.50111],"type":"Point"}
}