{
  "type": "Feature",
  "properties": {
    "gn:admin1_code":"3",
    "gn:admin2_code":"3.0",
    "gn:asciiname":"Las Artesanias",
    "gn:country_code":"MX",
    "gn:dem":8,
    "gn:feature_class":"P",
    "gn:feature_code":"PPL",
    "gn:name":"Las Artesan\u00edas",
    "gn:population":5,
    "gn:timezone":"America/Mazatlan",
    "iso:country":"MX",
    "name:und_x_variant":[
        "Las Artesan\u00edas"
    ],
    "wof:name":"Las Artesanias",
    "wof:placetype":"locality",
    "wof:population":5
},
  "geometry": {"coordinates":[-110.15904999999999,23.30525],"type":"Point"}
}