{
  "type": "Feature",
  "properties": {
    "gn:admin1_code":"10",
    "gn:admin2_code":"32.0",
    "gn:asciiname":"Santa Cruz de los Ojitos (Los Ojitos)",
    "gn:country_code":"MX",
    "gn:dem":1863,
    "gn:feature_class":"P",
    "gn:feature_code":"PPL",
    "gn:name":"Santa Cruz de los Ojitos (Los Ojitos)",
    "gn:population":59,
    "gn:timezone":"America/Monterrey",
    "iso:country":"MX",
    "name:und_x_variant":[
        "Rancho Ojitos",
        "Ojitos",
        "Los Ojitos"
    ],
    "wof:name":"Santa Cruz de los Ojitos (Los Ojitos)",
    "wof:placetype":"locality",
    "wof:population":59
},
  "geometry": {"coordinates":[-105.32446000000002,24.76056],"type":"Point"}
}