{
  "type": "Feature",
  "properties": {
    "gn:admin1_code":"11",
    "gn:admin2_code":"15",
    "gn:asciiname":"Mineral de Santo Nino",
    "gn:country_code":"MX",
    "gn:dem":2401,
    "gn:feature_class":"P",
    "gn:feature_code":"PPL",
    "gn:name":"Mineral de Santo Ni\u00f1o",
    "gn:population":34,
    "gn:timezone":"America/Mexico_City",
    "iso:country":"MX",
    "name:und_x_variant":[
        "Mineral de Santo Ni\u00f1o"
    ],
    "wof:name":"Mineral de Santo Nino",
    "wof:placetype":"locality",
    "wof:population":34
},
  "geometry": {"coordinates":[-101.33139,21.04611],"type":"Point"}
}