{
  "type": "Feature",
  "properties": {
    "gn:admin1_code":"20",
    "gn:admin2_code":"426.0",
    "gn:asciiname":"Tierra Caliente Tepantepec",
    "gn:country_code":"MX",
    "gn:dem":2288,
    "gn:feature_class":"P",
    "gn:feature_code":"PPL",
    "gn:name":"Tierra Caliente Tepantepec",
    "gn:population":236,
    "gn:timezone":"America/Mexico_City",
    "iso:country":"MX",
    "wof:name":"Tierra Caliente Tepantepec",
    "wof:placetype":"locality",
    "wof:population":236
},
  "geometry": {"coordinates":[-97.04611,17.00889],"type":"Point"}
}