{
  "type": "Feature",
  "properties": {
    "gn:admin1_code":"20",
    "gn:admin2_code":"324",
    "gn:asciiname":"Paso los Indios",
    "gn:country_code":"MX",
    "gn:dem":209,
    "gn:feature_class":"P",
    "gn:feature_code":"PPL",
    "gn:name":"Paso los Indios",
    "gn:population":29,
    "gn:timezone":"America/Mexico_City",
    "iso:country":"MX",
    "wof:name":"Paso los Indios",
    "wof:placetype":"locality",
    "wof:population":29
},
  "geometry": {"coordinates":[-96.47722,15.82778],"type":"Point"}
}