{
  "type": "Feature",
  "properties": {
    "gn:admin1_code":"11",
    "gn:admin2_code":"17",
    "gn:asciiname":"Puente Blanco",
    "gn:country_code":"MX",
    "gn:dem":1704,
    "gn:feature_class":"P",
    "gn:feature_code":"PPL",
    "gn:name":"Puente Blanco",
    "gn:population":24,
    "gn:timezone":"America/Mexico_City",
    "iso:country":"MX",
    "name:spa_x_preferred":[
        "Puente Blanco"
    ],
    "wof:name":"Puente Blanco",
    "wof:placetype":"locality",
    "wof:population":24
},
  "geometry": {"coordinates":[-101.405,20.53222],"type":"Point"}
}