{
  "type": "Feature",
  "properties": {
    "gn:admin1_code":"6",
    "gn:admin2_code":"49.0",
    "gn:asciiname":"Los Cajones",
    "gn:country_code":"MX",
    "gn:dem":1775,
    "gn:feature_class":"P",
    "gn:feature_code":"PPL",
    "gn:name":"Los Cajones",
    "gn:population":0,
    "gn:timezone":"America/Chihuahua",
    "iso:country":"MX",
    "name:spa_x_preferred":[
        "Los Cajones"
    ],
    "wof:name":"Los Cajones",
    "wof:placetype":"locality"
},
  "geometry": {"coordinates":[-106.57478999999999,27.46453],"type":"Point"}
}