{
  "type": "Feature",
  "properties": {
    "gn:admin1_code":"10.0",
    "gn:admin2_code":"33.0",
    "gn:asciiname":"Aleman (Aleman Viejo)",
    "gn:country_code":"MX",
    "gn:dem":2182,
    "gn:feature_class":"P",
    "gn:feature_code":"PPL",
    "gn:name":"Alem\u00e1n (Alem\u00e1n Viejo)",
    "gn:population":38,
    "gn:timezone":"America/Monterrey",
    "iso:country":"MX",
    "wof:name":"Aleman (Aleman Viejo)",
    "wof:placetype":"locality",
    "wof:population":38
},
  "geometry": {"coordinates":[-104.16692,23.33503],"type":"Point"}
}