{
  "type": "Feature",
  "properties": {
    "gn:admin1_code":"18.0",
    "gn:admin2_code":"5.0",
    "gn:asciiname":"La Quebrada",
    "gn:country_code":"MX",
    "gn:dem":835,
    "gn:feature_class":"P",
    "gn:feature_code":"PPL",
    "gn:name":"La Quebrada",
    "gn:population":0,
    "gn:timezone":"America/Mazatlan",
    "iso:country":"MX",
    "name:ceb_x_preferred":[
        "La Quebrada"
    ],
    "name:spa_x_preferred":[
        "La Quebrada"
    ],
    "name:swe_x_preferred":[
        "La Quebrada"
    ],
    "wof:name":"La Quebrada",
    "wof:placetype":"locality"
},
  "geometry": {"coordinates":[-105.21286000000001,22.75943],"type":"Point"}
}