{
  "type": "Feature",
  "properties": {
    "gn:admin1_code":"16",
    "gn:admin2_code":"14.0",
    "gn:asciiname":"Los Perez",
    "gn:country_code":"MX",
    "gn:dem":15,
    "gn:feature_class":"P",
    "gn:feature_code":"PPL",
    "gn:name":"Los P\u00e9rez",
    "gn:population":6,
    "gn:timezone":"America/Mexico_City",
    "iso:country":"MX",
    "name:und_x_variant":[
        "Los P\u00e9rez"
    ],
    "wof:name":"Los Perez",
    "wof:placetype":"locality",
    "wof:population":6
},
  "geometry": {"coordinates":[-103.70193999999999,18.71861],"type":"Point"}
}