{
  "type": "Feature",
  "properties": {
    "gn:admin1_code":"2.0",
    "gn:admin2_code":"1.0",
    "gn:asciiname":"Las Polvaredas",
    "gn:country_code":"MX",
    "gn:dem":759,
    "gn:feature_class":"P",
    "gn:feature_code":"PPL",
    "gn:name":"Las Polvaredas",
    "gn:population":0,
    "gn:timezone":"America/Tijuana",
    "iso:country":"MX",
    "name:spa_x_preferred":[
        "Las Polvaredas"
    ],
    "wof:name":"Las Polvaredas",
    "wof:placetype":"locality"
},
  "geometry": {"coordinates":[-115.73421,31.36758],"type":"Point"}
}