{
  "type": "Feature",
  "properties": {
    "gn:admin1_code":"26.0",
    "gn:admin2_code":"52.0",
    "gn:asciiname":"El Cordon",
    "gn:country_code":"MX",
    "gn:dem":1364,
    "gn:feature_class":"P",
    "gn:feature_code":"PPL",
    "gn:name":"El Cord\u00f3n",
    "gn:population":0,
    "gn:timezone":"America/Hermosillo",
    "iso:country":"MX",
    "name:spa_x_preferred":[
        "El Cord\u00f3n"
    ],
    "wof:name":"El Cordon",
    "wof:placetype":"locality"
},
  "geometry": {"coordinates":[-108.95001000000001,28.61798],"type":"Point"}
}