{
  "type": "Feature",
  "properties": {
    "gn:admin1_code":"30.0",
    "gn:admin2_code":"155.0",
    "gn:asciiname":"El Chijolito",
    "gn:country_code":"MX",
    "gn:dem":90,
    "gn:feature_class":"P",
    "gn:feature_code":"PPL",
    "gn:name":"El Chijolito",
    "gn:population":151,
    "gn:timezone":"America/Mexico_City",
    "iso:country":"MX",
    "name:spa_x_preferred":[
        "El Chijolito"
    ],
    "wof:name":"El Chijolito",
    "wof:placetype":"locality",
    "wof:population":151
},
  "geometry": {"coordinates":[-98.13916999999999,21.36361],"type":"Point"}
}