{
  "type": "Feature",
  "properties": {
    "gn:admin1_code":"32",
    "gn:admin2_code":"14",
    "gn:asciiname":"Luis Moya (Estacion Alamillo)",
    "gn:country_code":"MX",
    "gn:dem":1803,
    "gn:feature_class":"P",
    "gn:feature_code":"PPL",
    "gn:name":"Luis Moya (Estaci\u00f3n Alamillo)",
    "gn:population":34,
    "gn:timezone":"America/Mexico_City",
    "iso:country":"MX",
    "name:und_x_variant":[
        "Luis Moya (Estaci\u00f3n Alamillo)"
    ],
    "wof:name":"Luis Moya (Estacion Alamillo)",
    "wof:placetype":"locality",
    "wof:population":34
},
  "geometry": {"coordinates":[-102.47139,24.175],"type":"Point"}
}