{
  "type": "Feature",
  "properties": {
    "gn:admin1_code":"7",
    "gn:admin2_code":"4.0",
    "gn:asciiname":"Buenavista de la Roja",
    "gn:country_code":"MX",
    "gn:dem":2184,
    "gn:feature_class":"P",
    "gn:feature_code":"PPL",
    "gn:name":"Buenavista de la Roja",
    "gn:population":4,
    "gn:timezone":"America/Monterrey",
    "iso:country":"MX",
    "wof:name":"Buenavista de la Roja",
    "wof:placetype":"locality",
    "wof:population":4
},
  "geometry": {"coordinates":[-100.70837,25.50504],"type":"Point"}
}