{
  "type": "Feature",
  "properties": {
    "gn:admin1_code":"10",
    "gn:admin2_code":"36.0",
    "gn:asciiname":"Rancho San Rafael",
    "gn:country_code":"MX",
    "gn:dem":1096,
    "gn:feature_class":"P",
    "gn:feature_code":"PPL",
    "gn:name":"Rancho San Rafael",
    "gn:population":0,
    "gn:timezone":"America/Monterrey",
    "iso:country":"MX",
    "wof:name":"Rancho San Rafael",
    "wof:placetype":"locality"
},
  "geometry": {"coordinates":[-103.61667,26.01667],"type":"Point"}
}