{
  "type": "Feature",
  "properties": {
    "gn:admin1_code":"2.0",
    "gn:admin2_code":"1.0",
    "gn:asciiname":"El Papalote",
    "gn:country_code":"MX",
    "gn:dem":329,
    "gn:feature_class":"P",
    "gn:feature_code":"PPL",
    "gn:name":"El Papalote",
    "gn:population":7,
    "gn:timezone":"America/Tijuana",
    "iso:country":"MX",
    "name:spa_x_preferred":[
        "El Papalote"
    ],
    "wof:name":"El Papalote",
    "wof:placetype":"locality",
    "wof:population":7
},
  "geometry": {"coordinates":[-116.58889000000001,32.07111],"type":"Point"}
}