{
  "type": "Feature",
  "properties": {
    "gn:admin1_code":"7",
    "gn:admin2_code":"14.0",
    "gn:asciiname":"Clamor en el Barrio",
    "gn:country_code":"MX",
    "gn:dem":338,
    "gn:feature_class":"P",
    "gn:feature_code":"PPL",
    "gn:name":"Clamor en el Barrio",
    "gn:population":71,
    "gn:timezone":"America/Matamoros",
    "iso:country":"MX",
    "wof:name":"Clamor en el Barrio",
    "wof:placetype":"locality",
    "wof:population":71
},
  "geometry": {"coordinates":[-100.89404999999999,29.20213],"type":"Point"}
}