{
  "type": "Feature",
  "properties": {
    "gn:admin1_code":"27",
    "gn:admin2_code":"16",
    "gn:asciiname":"Santa Elena",
    "gn:country_code":"MX",
    "gn:dem":44,
    "gn:feature_class":"P",
    "gn:feature_code":"PPL",
    "gn:name":"Santa Elena",
    "gn:population":25,
    "gn:timezone":"America/Mexico_City",
    "iso:country":"MX",
    "wof:name":"Santa Elena",
    "wof:placetype":"locality",
    "wof:population":25
},
  "geometry": {"coordinates":[-92.95583000000001,17.54917],"type":"Point"}
}