{
  "type": "Feature",
  "properties": {
    "gn:admin1_code":"24",
    "gn:admin2_code":"15.0",
    "gn:asciiname":"Genaro Bustos Ramirez",
    "gn:country_code":"MX",
    "gn:dem":2102,
    "gn:feature_class":"P",
    "gn:feature_code":"PPL",
    "gn:name":"Genaro Bustos Ram\u00edrez",
    "gn:population":6,
    "gn:timezone":"America/Mexico_City",
    "iso:country":"MX",
    "name:und_x_variant":[
        "Genaro Bustos Ram\u00edrez"
    ],
    "wof:name":"Genaro Bustos Ramirez",
    "wof:placetype":"locality",
    "wof:population":6
},
  "geometry": {"coordinates":[-101.04139000000001,23.20917],"type":"Point"}
}