{
  "type": "Feature",
  "properties": {
    "gn:admin1_code":"26.0",
    "gn:admin2_code":"27.0",
    "gn:asciiname":"Cuquiarichi",
    "gn:country_code":"MX",
    "gn:dem":1214,
    "gn:feature_class":"P",
    "gn:feature_code":"PPL",
    "gn:name":"Cuquiarichi",
    "gn:population":0,
    "gn:timezone":"America/Hermosillo",
    "iso:country":"MX",
    "name:spa_x_preferred":[
        "Cuquiarichi"
    ],
    "name:und_x_variant":[
        "Cuchiarichic"
    ],
    "wof:name":"Cuquiarichi",
    "wof:placetype":"locality"
},
  "geometry": {"coordinates":[-109.66974,30.87416],"type":"Point"}
}