{
  "type": "Feature",
  "properties": {
    "gn:admin1_code":"1",
    "gn:admin2_code":"9",
    "gn:asciiname":"Potrero la Esperanza",
    "gn:country_code":"MX",
    "gn:dem":1923,
    "gn:feature_class":"P",
    "gn:feature_code":"PPL",
    "gn:name":"Potrero la Esperanza",
    "gn:population":25,
    "gn:timezone":"America/Mexico_City",
    "iso:country":"MX",
    "wof:name":"Potrero la Esperanza",
    "wof:placetype":"locality",
    "wof:population":25
},
  "geometry": {"coordinates":[-102.24028,22.17056],"type":"Point"}
}