{
  "type": "Feature",
  "properties": {
    "gn:admin1_code":"30",
    "gn:admin2_code":"105.0",
    "gn:asciiname":"Lomas de Guerrero",
    "gn:country_code":"MX",
    "gn:dem":16,
    "gn:feature_class":"P",
    "gn:feature_code":"PPL",
    "gn:name":"Lomas de Guerrero",
    "gn:population":90,
    "gn:timezone":"America/Mexico_City",
    "iso:country":"MX",
    "wof:name":"Lomas de Guerrero",
    "wof:placetype":"locality",
    "wof:population":90
},
  "geometry": {"coordinates":[-96.18083,19.01111],"type":"Point"}
}