{
  "type": "Feature",
  "properties": {
    "gn:admin1_code":"4",
    "gn:admin2_code":"3.0",
    "gn:asciiname":"La Pimienta",
    "gn:country_code":"MX",
    "gn:dem":10,
    "gn:feature_class":"P",
    "gn:feature_code":"PPL",
    "gn:name":"La Pimienta",
    "gn:population":0,
    "gn:timezone":"America/Merida",
    "iso:country":"MX",
    "name:spa_x_preferred":[
        "La Pimienta"
    ],
    "wof:name":"La Pimienta",
    "wof:placetype":"locality"
},
  "geometry": {"coordinates":[-91.69497,18.03125],"type":"Point"}
}