{
  "type": "Feature",
  "properties": {
    "gn:admin1_code":"16",
    "gn:admin2_code":"61",
    "gn:asciiname":"Manzana el Fresno",
    "gn:country_code":"MX",
    "gn:dem":2243,
    "gn:feature_class":"P",
    "gn:feature_code":"PPL",
    "gn:name":"Manzana el Fresno",
    "gn:population":21,
    "gn:timezone":"America/Mexico_City",
    "iso:country":"MX",
    "wof:name":"Manzana el Fresno",
    "wof:placetype":"locality",
    "wof:population":21
},
  "geometry": {"coordinates":[-100.38333,19.56972],"type":"Point"}
}