{
  "type": "Feature",
  "properties": {
    "gn:admin1_code":"10",
    "gn:admin2_code":"14.0",
    "gn:asciiname":"Minas Negras",
    "gn:country_code":"MX",
    "gn:dem":2321,
    "gn:feature_class":"P",
    "gn:feature_code":"PPL",
    "gn:name":"Minas Negras",
    "gn:population":0,
    "gn:timezone":"America/Monterrey",
    "iso:country":"MX",
    "name:spa_x_preferred":[
        "Minas Negras"
    ],
    "wof:name":"Minas Negras",
    "wof:placetype":"locality"
},
  "geometry": {"coordinates":[-104.50538,23.39989],"type":"Point"}
}