{
  "type": "Feature",
  "properties": {
    "gn:admin1_code":"6",
    "gn:admin2_code":"27.0",
    "gn:asciiname":"Yahuirachi",
    "gn:country_code":"MX",
    "gn:dem":2273,
    "gn:feature_class":"P",
    "gn:feature_code":"PPL",
    "gn:name":"Yahu\u00edrachi",
    "gn:population":0,
    "gn:timezone":"America/Chihuahua",
    "iso:country":"MX",
    "name:und_x_variant":[
        "Yahu\u00edrachi"
    ],
    "wof:name":"Yahuirachi",
    "wof:placetype":"locality"
},
  "geometry": {"coordinates":[-107.48828,27.592],"type":"Point"}
}