{
  "type": "Feature",
  "properties": {
    "gn:admin1_code":"13",
    "gn:admin2_code":"7",
    "gn:asciiname":"El Sabinal",
    "gn:country_code":"MX",
    "gn:dem":2783,
    "gn:feature_class":"P",
    "gn:feature_code":"PPL",
    "gn:name":"El Sabinal",
    "gn:population":13,
    "gn:timezone":"America/Mexico_City",
    "iso:country":"MX",
    "wof:name":"El Sabinal",
    "wof:placetype":"locality",
    "wof:population":13
},
  "geometry": {"coordinates":[-98.35269,19.74928],"type":"Point"}
}