{
  "type": "Feature",
  "properties": {
    "gn:admin1_code":"14",
    "gn:admin2_code":"20.0",
    "gn:asciiname":"La Parota",
    "gn:country_code":"MX",
    "gn:dem":381,
    "gn:feature_class":"P",
    "gn:feature_code":"PPL",
    "gn:name":"La Parota",
    "gn:population":8,
    "gn:timezone":"America/Mexico_City",
    "iso:country":"MX",
    "wof:name":"La Parota",
    "wof:placetype":"locality",
    "wof:population":8
},
  "geometry": {"coordinates":[-105.3125,20.25444],"type":"Point"}
}