{
  "type": "Feature",
  "properties": {
    "gn:admin1_code":"3",
    "gn:admin2_code":"2.0",
    "gn:asciiname":"Las Higueras",
    "gn:country_code":"MX",
    "gn:dem":630,
    "gn:feature_class":"P",
    "gn:feature_code":"PPL",
    "gn:name":"Las Higueras",
    "gn:population":7,
    "gn:timezone":"America/Mazatlan",
    "iso:country":"MX",
    "wof:name":"Las Higueras",
    "wof:placetype":"locality",
    "wof:population":7
},
  "geometry": {"coordinates":[-112.51561,27.08797],"type":"Point"}
}