{
  "type": "Feature",
  "properties": {
    "gn:admin1_code":"20",
    "gn:admin2_code":"520.0",
    "gn:asciiname":"San Juan Reyes",
    "gn:country_code":"MX",
    "gn:dem":1412,
    "gn:feature_class":"P",
    "gn:feature_code":"PPL",
    "gn:name":"San Juan Reyes",
    "gn:population":0,
    "gn:timezone":"America/Mexico_City",
    "iso:country":"MX",
    "name:spa_x_preferred":[
        "San Juan Reyes"
    ],
    "wof:name":"San Juan Reyes",
    "wof:placetype":"locality"
},
  "geometry": {"coordinates":[-97.97687999999999,17.72847],"type":"Point"}
}