{
  "type": "Feature",
  "properties": {
    "gn:admin1_code":"16",
    "gn:admin2_code":"81",
    "gn:asciiname":"Los Teposanes",
    "gn:country_code":"MX",
    "gn:dem":2305,
    "gn:feature_class":"P",
    "gn:feature_code":"PPL",
    "gn:name":"Los Teposanes",
    "gn:population":10,
    "gn:timezone":"America/Mexico_City",
    "iso:country":"MX",
    "wof:name":"Los Teposanes",
    "wof:placetype":"locality",
    "wof:population":10
},
  "geometry": {"coordinates":[-100.33750000000001,19.30917],"type":"Point"}
}