{
  "type": "Feature",
  "properties": {
    "gn:admin1_code":"21",
    "gn:admin2_code":"197.0",
    "gn:asciiname":"Tlapehuala",
    "gn:country_code":"MX",
    "gn:dem":826,
    "gn:feature_class":"P",
    "gn:feature_code":"PPL",
    "gn:name":"Tlapehuala",
    "gn:population":0,
    "gn:timezone":"America/Mexico_City",
    "iso:country":"MX",
    "name:und_x_variant":[
        "Tlalpehuala",
        "Tlapehuala"
    ],
    "wof:name":"Tlapehuala",
    "wof:placetype":"locality"
},
  "geometry": {"coordinates":[-98.02891,20.31283],"type":"Point"}
}