{
  "type": "Feature",
  "properties": {
    "gn:admin1_code":"10",
    "gn:admin2_code":"34.0",
    "gn:asciiname":"Los Tejabanes",
    "gn:country_code":"MX",
    "gn:dem":2414,
    "gn:feature_class":"P",
    "gn:feature_code":"PPL",
    "gn:name":"Los Tejabanes",
    "gn:population":62,
    "gn:timezone":"America/Monterrey",
    "iso:country":"MX",
    "wof:name":"Los Tejabanes",
    "wof:placetype":"locality",
    "wof:population":62
},
  "geometry": {"coordinates":[-106.94789,25.51691],"type":"Point"}
}