{
  "type": "Feature",
  "properties": {
    "gn:admin1_code":"25",
    "gn:admin2_code":"17.0",
    "gn:asciiname":"Los Nescos",
    "gn:country_code":"MX",
    "gn:dem":186,
    "gn:feature_class":"P",
    "gn:feature_code":"PPL",
    "gn:name":"Los Nescos",
    "gn:population":0,
    "gn:timezone":"America/Mazatlan",
    "iso:country":"MX",
    "name:spa_x_preferred":[
        "Los Nescos"
    ],
    "wof:name":"Los Nescos",
    "wof:placetype":"locality"
},
  "geometry": {"coordinates":[-108.05343999999999,25.86416],"type":"Point"}
}