{
  "type": "Feature",
  "properties": {
    "gn:admin1_code":"30",
    "gn:admin2_code":"141.0",
    "gn:asciiname":"Texalpan de Arriba",
    "gn:country_code":"MX",
    "gn:dem":319,
    "gn:feature_class":"P",
    "gn:feature_code":"PPL",
    "gn:name":"Texalpan de Arriba",
    "gn:population":2142,
    "gn:timezone":"America/Mexico_City",
    "iso:country":"MX",
    "wof:name":"Texalpan de Arriba",
    "wof:placetype":"locality",
    "wof:population":2142
},
  "geometry": {"coordinates":[-95.24417,18.42944],"type":"Point"}
}