{
  "type": "Feature",
  "properties": {
    "gn:admin1_code":"30",
    "gn:admin2_code":"188.0",
    "gn:asciiname":"Rincon de Calcahualco",
    "gn:country_code":"MX",
    "gn:dem":982,
    "gn:feature_class":"P",
    "gn:feature_code":"PPL",
    "gn:name":"Rinc\u00f3n de Calcahualco",
    "gn:population":0,
    "gn:timezone":"America/Mexico_City",
    "iso:country":"MX",
    "wof:name":"Rincon de Calcahualco",
    "wof:placetype":"locality"
},
  "geometry": {"coordinates":[-96.88684000000001,19.26449],"type":"Point"}
}