{
  "type": "Feature",
  "properties": {
    "gn:admin1_code":"20",
    "gn:admin2_code":"207",
    "gn:asciiname":"Las Palomas",
    "gn:country_code":"MX",
    "gn:dem":157,
    "gn:feature_class":"P",
    "gn:feature_code":"PPL",
    "gn:name":"Las Palomas",
    "gn:population":11,
    "gn:timezone":"America/Mexico_City",
    "iso:country":"MX",
    "wof:name":"Las Palomas",
    "wof:placetype":"locality",
    "wof:population":11
},
  "geometry": {"coordinates":[-95.2775,17.22722000000001],"type":"Point"}
}