{
  "type": "Feature",
  "properties": {
    "gn:admin1_code":"20",
    "gn:admin2_code":"407.0",
    "gn:asciiname":"Cal y Mayor",
    "gn:country_code":"MX",
    "gn:dem":759,
    "gn:feature_class":"P",
    "gn:feature_code":"PPL",
    "gn:name":"Cal y Mayor",
    "gn:population":543,
    "gn:timezone":"America/Mexico_City",
    "iso:country":"MX",
    "name:spa_x_preferred":[
        "Rafael Cal y Mayor"
    ],
    "name:spa_x_variant":[
        "Cal y Mayor"
    ],
    "wof:name":"Cal y Mayor",
    "wof:placetype":"locality",
    "wof:population":543
},
  "geometry": {"coordinates":[-94.01575,16.96187],"type":"Point"}
}