{
  "type": "Feature",
  "properties": {
    "gn:admin1_code":"7.0",
    "gn:admin2_code":"21.0",
    "gn:asciiname":"El Coloso",
    "gn:country_code":"MX",
    "gn:dem":509,
    "gn:feature_class":"P",
    "gn:feature_code":"PPL",
    "gn:name":"El Coloso",
    "gn:population":0,
    "gn:timezone":"America/Monterrey",
    "iso:country":"MX",
    "name:und_x_variant":[
        "Rancho El Coloso",
        "Coloso",
        "El Coloso"
    ],
    "wof:name":"El Coloso",
    "wof:placetype":"locality"
},
  "geometry": {"coordinates":[-101.61023,27.05111],"type":"Point"}
}