{
  "type": "Feature",
  "properties": {
    "gn:admin1_code":"30",
    "gn:admin2_code":"121",
    "gn:asciiname":"La Brisa",
    "gn:country_code":"MX",
    "gn:dem":37,
    "gn:feature_class":"P",
    "gn:feature_code":"PPL",
    "gn:name":"La Brisa",
    "gn:population":15,
    "gn:timezone":"America/Mexico_City",
    "iso:country":"MX",
    "wof:name":"La Brisa",
    "wof:placetype":"locality",
    "wof:population":15
},
  "geometry": {"coordinates":[-97.94638999999999,21.88333],"type":"Point"}
}