{
  "type": "Feature",
  "properties": {
    "gn:admin1_code":"5",
    "gn:admin2_code":"109.0",
    "gn:asciiname":"Ocot Yashwinic",
    "gn:country_code":"MX",
    "gn:dem":1470,
    "gn:feature_class":"P",
    "gn:feature_code":"PPL",
    "gn:name":"Ocot Yashwinic",
    "gn:population":90,
    "gn:timezone":"America/Mexico_City",
    "iso:country":"MX",
    "wof:name":"Ocot Yashwinic",
    "wof:placetype":"locality",
    "wof:population":90
},
  "geometry": {"coordinates":[-92.2775,17.17611],"type":"Point"}
}