{
  "type": "Feature",
  "properties": {
    "gn:admin1_code":"15.0",
    "gn:admin2_code":"82.0",
    "gn:asciiname":"El Llano Grande",
    "gn:country_code":"MX",
    "gn:dem":1418,
    "gn:feature_class":"P",
    "gn:feature_code":"PPL",
    "gn:name":"El Llano Grande",
    "gn:population":0,
    "gn:timezone":"America/Mexico_City",
    "iso:country":"MX",
    "name:spa_x_preferred":[
        "El Llano Grande"
    ],
    "wof:name":"El Llano Grande",
    "wof:placetype":"locality"
},
  "geometry": {"coordinates":[-100.20936,18.95362],"type":"Point"}
}