{
  "type": "Feature",
  "properties": {
    "gn:admin1_code":"30",
    "gn:admin2_code":"210.0",
    "gn:asciiname":"Luis Echeverria Alvarez",
    "gn:country_code":"MX",
    "gn:dem":91,
    "gn:feature_class":"P",
    "gn:feature_code":"PPL",
    "gn:name":"Luis Echeverr\u00eda \u00c1lvarez",
    "gn:population":84,
    "gn:timezone":"America/Mexico_City",
    "iso:country":"MX",
    "name:und_x_variant":[
        "Luis Echeverr\u00eda \u00c1lvarez"
    ],
    "wof:name":"Luis Echeverria Alvarez",
    "wof:placetype":"locality",
    "wof:population":84
},
  "geometry": {"coordinates":[-94.495,17.37889],"type":"Point"}
}