{
  "type": "Feature",
  "properties": {
    "gn:admin1_code":"16.0",
    "gn:admin2_code":"95.0",
    "gn:asciiname":"El Ojo Agua",
    "gn:country_code":"MX",
    "gn:dem":1257,
    "gn:feature_class":"P",
    "gn:feature_code":"PPL",
    "gn:name":"El Ojo Agua",
    "gn:population":0,
    "gn:timezone":"America/Mexico_City",
    "iso:country":"MX",
    "name:spa_x_preferred":[
        "El Ojo Agua"
    ],
    "wof:name":"El Ojo Agua",
    "wof:placetype":"locality"
},
  "geometry": {"coordinates":[-102.5142,19.62302],"type":"Point"}
}