{
  "type": "Feature",
  "properties": {
    "gn:admin1_code":"7",
    "gn:admin2_code":"33.0",
    "gn:asciiname":"San Rafael de Abajo",
    "gn:country_code":"MX",
    "gn:dem":1102,
    "gn:feature_class":"P",
    "gn:feature_code":"PPL",
    "gn:name":"San Rafael de Abajo",
    "gn:population":0,
    "gn:timezone":"America/Monterrey",
    "iso:country":"MX",
    "name:spa_x_preferred":[
        "San Rafael de Abajo"
    ],
    "name:und_x_variant":[
        "San Rafael"
    ],
    "wof:name":"San Rafael de Abajo",
    "wof:placetype":"locality"
},
  "geometry": {"coordinates":[-103.0091,25.65969],"type":"Point"}
}