{
  "type": "Feature",
  "properties": {
    "gn:admin1_code":"14.0",
    "gn:asciiname":"La Cebolleta",
    "gn:country_code":"MX",
    "gn:dem":2080,
    "gn:feature_class":"P",
    "gn:feature_code":"PPL",
    "gn:name":"La Cebolleta",
    "gn:population":0,
    "gn:timezone":"America/Mexico_City",
    "iso:country":"MX",
    "name:spa_x_preferred":[
        "La Cebolleta"
    ],
    "wof:name":"La Cebolleta",
    "wof:placetype":"locality"
},
  "geometry": {"coordinates":[-102.30772,20.86824],"type":"Point"}
}