{
  "type": "Feature",
  "properties": {
    "gn:admin1_code":"18",
    "gn:admin2_code":"4.0",
    "gn:asciiname":"Santa Maria de Jaltemba",
    "gn:country_code":"MX",
    "gn:dem":230,
    "gn:feature_class":"P",
    "gn:feature_code":"PPL",
    "gn:name":"Santa Mar\u00eda de Jaltemba",
    "gn:population":61,
    "gn:timezone":"America/Mazatlan",
    "iso:country":"MX",
    "name:spa_x_preferred":[
        "Santa Maria de Jaltemba"
    ],
    "name:spa_x_variant":[
        "Santa Maria Jaltemba"
    ],
    "name:und_x_variant":[
        "Santa Mar\u00eda de Jaltemba"
    ],
    "wof:name":"Santa Maria de Jaltemba",
    "wof:placetype":"locality",
    "wof:population":61
},
  "geometry": {"coordinates":[-105.10805999999999,21.03611],"type":"Point"}
}