{
  "type": "Feature",
  "properties": {
    "gn:admin1_code":"16",
    "gn:admin2_code":"38.0",
    "gn:asciiname":"El Pinzanal",
    "gn:country_code":"MX",
    "gn:dem":190,
    "gn:feature_class":"P",
    "gn:feature_code":"PPL",
    "gn:name":"El Pinzanal",
    "gn:population":5,
    "gn:timezone":"America/Mexico_City",
    "iso:country":"MX",
    "wof:name":"El Pinzanal",
    "wof:placetype":"locality",
    "wof:population":5
},
  "geometry": {"coordinates":[-101.21917000000001,18.53861],"type":"Point"}
}