{
  "type": "Feature",
  "properties": {
    "gn:admin1_code":"5",
    "gn:admin2_code":"117.0",
    "gn:asciiname":"Rio Negro",
    "gn:country_code":"MX",
    "gn:dem":1340,
    "gn:feature_class":"P",
    "gn:feature_code":"PPL",
    "gn:name":"R\u00edo Negro",
    "gn:population":133,
    "gn:timezone":"America/Mexico_City",
    "iso:country":"MX",
    "name:ara_x_preferred":[
        "\u0631\u064a\u0648 \u0646\u064a\u062c\u0631\u0648"
    ],
    "name:bre_x_preferred":[
        "Rio Negro"
    ],
    "name:cat_x_preferred":[
        "R\u00edo Negro"
    ],
    "name:ceb_x_preferred":[
        "R\u00edo Negro"
    ],
    "name:ces_x_preferred":[
        "R\u00edo Negro"
    ],
    "name:cym_x_preferred":[
        "Rio Negro"
    ],
    "name:dan_x_preferred":[
        "Rio Negro"
    ],
    "name:deu_x_preferred":[
        "Rio Negro"
    ],
    "name:epo_x_preferred":[
        "R\u00edo Negro"
    ],
    "name:est_x_preferred":[
        "Rio Negro"
    ],
    "name:fas_x_preferred":[
        "\u0631\u06cc\u0648 \u0646\u06af\u0631\u0648"
    ],
    "name:fra_x_preferred":[
        "R\u00edo Negro"
    ],
    "name:glg_x_preferred":[
        "R\u00edo Negro"
    ],
    "name:heb_x_preferred":[
        "\u05e8\u05d9\u05d5 \u05e0\u05d2\u05e8\u05d5"
    ],
    "name:hrv_x_preferred":[
        "Rio Negro"
    ],
    "name:hun_x_preferred":[
        "Rio Negro"
    ],
    "name:ita_x_preferred":[
        "Rio Negro"
    ],
    "name:jpn_x_preferred":[
        "\u30ea\u30aa\u30cd\u30b0\u30ed"
    ],
    "name:kir_x_preferred":[
        "\u0420\u0438\u043e-\u041d\u0435\u0433\u0440\u043e"
    ],
    "name:kor_x_preferred":[
        "\ub9ac\uc624\ub124\uadf8\ub85c"
    ],
    "name:nds_x_preferred":[
        "Rio Negro"
    ],
    "name:nld_x_preferred":[
        "Rio Negro"
    ],
    "name:nor_x_preferred":[
        "Rio Negro"
    ],
    "name:oss_x_preferred":[
        "\u0420\u0438\u043e-\u041d\u0435\u0433\u0440\u043e"
    ],
    "name:pol_x_preferred":[
        "R\u00edo Negro"
    ],
    "name:por_x_preferred":[
        "Rio Negro"
    ],
    "name:ron_x_preferred":[
        "Rio Negro"
    ],
    "name:rus_x_preferred":[
        "\u0420\u0438\u043e-\u041d\u0435\u0433\u0440\u043e"
    ],
    "name:sco_x_preferred":[
        "Rio Negro"
    ],
    "name:slk_x_preferred":[
        "R\u00edo Negro"
    ],
    "name:spa_x_preferred":[
        "R\u00edo Negro"
    ],
    "name:srp_x_preferred":[
        "\u0420\u0438\u043e \u041d\u0435\u0433\u0440\u043e"
    ],
    "name:swe_x_preferred":[
        "Rio Negro"
    ],
    "name:ukr_x_preferred":[
        "\u0420\u0456\u043e-\u041d\u0435\u0433\u0440\u043e"
    ],
    "name:vie_x_preferred":[
        "R\u00edo Negro"
    ],
    "name:vol_x_preferred":[
        "Rio Negro"
    ],
    "name:war_x_preferred":[
        "Rio Negro"
    ],
    "name:zho_x_preferred":[
        "\u5185\u683c\u7f57\u6cb3"
    ],
    "wof:name":"Rio Negro",
    "wof:placetype":"locality",
    "wof:population":133
},
  "geometry": {"coordinates":[-92.71889,15.63917],"type":"Point"}
}