{
  "type": "Feature",
  "properties": {
    "gn:admin1_code":"5",
    "gn:admin2_code":"117.0",
    "gn:asciiname":"Rio Negro",
    "gn:country_code":"MX",
    "gn:dem":1340,
    "gn:feature_class":"P",
    "gn:feature_code":"PPL",
    "gn:name":"R\u00edo Negro",
    "gn:population":133,
    "gn:timezone":"America/Mexico_City",
    "iso:country":"MX",
    "wof:name":"Rio Negro",
    "wof:placetype":"locality",
    "wof:population":133
},
  "geometry": {"coordinates":[-92.71889,15.63917],"type":"Point"}
}