{
  "type": "Feature",
  "properties": {
    "gn:admin1_code":"14",
    "gn:admin2_code":"93.0",
    "gn:asciiname":"Rancho Quemado (Buenavista)",
    "gn:country_code":"MX",
    "gn:dem":1989,
    "gn:feature_class":"P",
    "gn:feature_code":"PPL",
    "gn:name":"Rancho Quemado (Buenavista)",
    "gn:population":9,
    "gn:timezone":"America/Mexico_City",
    "iso:country":"MX",
    "wof:name":"Rancho Quemado (Buenavista)",
    "wof:placetype":"locality",
    "wof:population":9
},
  "geometry": {"coordinates":[-102.62833000000001,20.71861],"type":"Point"}
}