{
  "type": "Feature",
  "properties": {
    "gn:admin1_code":"30",
    "gn:admin2_code":"160.0",
    "gn:asciiname":"La Mata",
    "gn:country_code":"MX",
    "gn:dem":76,
    "gn:feature_class":"P",
    "gn:feature_code":"PPL",
    "gn:name":"La Mata",
    "gn:population":129,
    "gn:timezone":"America/Mexico_City",
    "iso:country":"MX",
    "name:spa_x_preferred":[
        "La Mata"
    ],
    "wof:name":"La Mata",
    "wof:placetype":"locality",
    "wof:population":129
},
  "geometry": {"coordinates":[-97.83725,20.81605],"type":"Point"}
}