{
  "type": "Feature",
  "properties": {
    "gn:admin1_code":"13",
    "gn:admin2_code":"40.0",
    "gn:asciiname":"El Roa",
    "gn:country_code":"MX",
    "gn:dem":1375,
    "gn:feature_class":"P",
    "gn:feature_code":"PPL",
    "gn:name":"El Roa",
    "gn:population":175,
    "gn:timezone":"America/Mexico_City",
    "iso:country":"MX",
    "wof:name":"El Roa",
    "wof:placetype":"locality",
    "wof:population":175
},
  "geometry": {"coordinates":[-99.09974,21.10118],"type":"Point"}
}