{
  "type": "Feature",
  "properties": {
    "gn:admin1_code":"17",
    "gn:asciiname":"San Jose Comalco",
    "gn:country_code":"MX",
    "gn:dem":2594,
    "gn:feature_class":"P",
    "gn:feature_code":"PPL",
    "gn:name":"San Jos\u00e9 Comalco",
    "gn:population":0,
    "gn:timezone":"America/Mexico_City",
    "iso:country":"MX",
    "name:spa_x_preferred":[
        "San Jos\u00e9 Comalco"
    ],
    "wof:name":"San Jose Comalco",
    "wof:placetype":"locality"
},
  "geometry": {"coordinates":[-99.62627000000001,19.47097],"type":"Point"}
}