{
  "type": "Feature",
  "properties": {
    "gn:admin1_code":"32",
    "gn:admin2_code":"48.0",
    "gn:asciiname":"Los Alisos",
    "gn:country_code":"MX",
    "gn:dem":2220,
    "gn:feature_class":"P",
    "gn:feature_code":"PPL",
    "gn:name":"Los Alisos",
    "gn:population":0,
    "gn:timezone":"America/Mexico_City",
    "iso:country":"MX",
    "name:spa_x_preferred":[
        "Los Alisos"
    ],
    "wof:name":"Los Alisos",
    "wof:placetype":"locality"
},
  "geometry": {"coordinates":[-103.09327999999999,21.73614],"type":"Point"}
}