{
  "type": "Feature",
  "properties": {
    "gn:admin1_code":"25",
    "gn:admin2_code":"5",
    "gn:asciiname":"Tachichilte",
    "gn:country_code":"MX",
    "gn:dem":403,
    "gn:feature_class":"P",
    "gn:feature_code":"PPL",
    "gn:name":"Tachichilte",
    "gn:population":16,
    "gn:timezone":"America/Mazatlan",
    "iso:country":"MX",
    "wof:name":"Tachichilte",
    "wof:placetype":"locality",
    "wof:population":16
},
  "geometry": {"coordinates":[-106.86556000000002,24.6734],"type":"Point"}
}