{
  "type": "Feature",
  "properties": {
    "gn:admin1_code":"14.0",
    "gn:admin2_code":"84.0",
    "gn:asciiname":"La Cuestecita",
    "gn:country_code":"MX",
    "gn:dem":1142,
    "gn:feature_class":"P",
    "gn:feature_code":"PPL",
    "gn:name":"La Cuestecita",
    "gn:population":0,
    "gn:timezone":"America/Mexico_City",
    "iso:country":"MX",
    "name:spa_x_preferred":[
        "La Cuestecita"
    ],
    "wof:name":"La Cuestecita",
    "wof:placetype":"locality"
},
  "geometry": {"coordinates":[-104.8695,20.50891],"type":"Point"}
}