{
  "type": "Feature",
  "properties": {
    "gn:admin1_code":"27",
    "gn:admin2_code":"3.0",
    "gn:asciiname":"Chichicastle Primera Seccion",
    "gn:country_code":"MX",
    "gn:dem":1,
    "gn:feature_class":"P",
    "gn:feature_code":"PPL",
    "gn:name":"Chichicastle Primera Secci\u00f3n",
    "gn:population":0,
    "gn:timezone":"America/Mexico_City",
    "iso:country":"MX",
    "name:spa_x_preferred":[
        "Chichicostle Primera Secci\u00f3n"
    ],
    "name:spa_x_variant":[
        "Chichicastle Primera Secci\u00f3n"
    ],
    "wof:name":"Chichicastle Primera Seccion",
    "wof:placetype":"locality"
},
  "geometry": {"coordinates":[-92.47147,18.31264],"type":"Point"}
}