{
  "type": "Feature",
  "properties": {
    "gn:admin1_code":"11.0",
    "gn:admin2_code":"23.0",
    "gn:asciiname":"La Barranca del Chilar",
    "gn:country_code":"MX",
    "gn:dem":1833,
    "gn:feature_class":"P",
    "gn:feature_code":"PPL",
    "gn:name":"La Barranca del Chilar",
    "gn:population":0,
    "gn:timezone":"America/Mexico_City",
    "iso:country":"MX",
    "name:spa_x_preferred":[
        "La Barranca del Chilar"
    ],
    "name:und_x_variant":[
        "La Barranca"
    ],
    "wof:name":"La Barranca del Chilar",
    "wof:placetype":"locality"
},
  "geometry": {"coordinates":[-101.90089,20.52757],"type":"Point"}
}