{
  "type": "Feature",
  "properties": {
    "gn:admin1_code":"6",
    "gn:admin2_code":"45",
    "gn:asciiname":"Rancho Paraiso",
    "gn:country_code":"MX",
    "gn:dem":1151,
    "gn:feature_class":"P",
    "gn:feature_code":"PPL",
    "gn:name":"Rancho Para\u00edso",
    "gn:population":12,
    "gn:timezone":"America/Chihuahua",
    "iso:country":"MX",
    "name:und_x_variant":[
        "Rancho Para\u00edso"
    ],
    "wof:name":"Rancho Paraiso",
    "wof:placetype":"locality",
    "wof:population":12
},
  "geometry": {"coordinates":[-105.50632,28.25502],"type":"Point"}
}