{
  "type": "Feature",
  "properties": {
    "gn:admin1_code":"6.0",
    "gn:admin2_code":"15.0",
    "gn:asciiname":"El Milagro",
    "gn:country_code":"MX",
    "gn:dem":1597,
    "gn:feature_class":"P",
    "gn:feature_code":"PPL",
    "gn:name":"El Milagro",
    "gn:population":8,
    "gn:timezone":"America/Chihuahua",
    "iso:country":"MX",
    "name:spa_x_preferred":[
        "El Milagro"
    ],
    "wof:name":"El Milagro",
    "wof:placetype":"locality",
    "wof:population":8
},
  "geometry": {"coordinates":[-105.35744,29.57017],"type":"Point"}
}