{
  "type": "Feature",
  "properties": {
    "gn:admin1_code":"11.0",
    "gn:admin2_code":"15.0",
    "gn:asciiname":"El Mogote",
    "gn:country_code":"MX",
    "gn:dem":2375,
    "gn:feature_class":"P",
    "gn:feature_code":"PPL",
    "gn:name":"El Mogote",
    "gn:population":14,
    "gn:timezone":"America/Mexico_City",
    "iso:country":"MX",
    "wof:name":"El Mogote",
    "wof:placetype":"locality",
    "wof:population":14
},
  "geometry": {"coordinates":[-101.35028,21.02472],"type":"Point"}
}