{
  "type": "Feature",
  "properties": {
    "gn:admin1_code":"14",
    "gn:admin2_code":"16",
    "gn:asciiname":"Monte Largo de los Garcia (Monte Largo)",
    "gn:country_code":"MX",
    "gn:dem":1886,
    "gn:feature_class":"P",
    "gn:feature_code":"PPL",
    "gn:name":"Monte Largo de los Garc\u00eda (Monte Largo)",
    "gn:population":52,
    "gn:timezone":"America/Mexico_City",
    "iso:country":"MX",
    "name:und_x_variant":[
        "Monte Largo de los Garc\u00eda (Monte Largo)"
    ],
    "wof:name":"Monte Largo de los Garcia (Monte Largo)",
    "wof:placetype":"locality",
    "wof:population":52
},
  "geometry": {"coordinates":[-102.41388999999999,20.57861],"type":"Point"}
}