{
  "type": "Feature",
  "properties": {
    "gn:admin1_code":"5",
    "gn:admin2_code":"107.0",
    "gn:asciiname":"La Ermita",
    "gn:country_code":"MX",
    "gn:dem":822,
    "gn:feature_class":"P",
    "gn:feature_code":"PPL",
    "gn:name":"La Ermita",
    "gn:population":0,
    "gn:timezone":"America/Mexico_City",
    "iso:country":"MX",
    "name:ita_x_preferred":[
        "La Ermita"
    ],
    "name:spa_x_preferred":[
        "La Ermita"
    ],
    "name:und_x_variant":[
        "El Primor"
    ],
    "name:zho_x_preferred":[
        "\u62c9\u57c3\u723e\u7c73\u5854"
    ],
    "wof:name":"La Ermita",
    "wof:placetype":"locality"
},
  "geometry": {"coordinates":[-93.1117,16.02709],"type":"Point"}
}