{
  "type": "Feature",
  "properties": {
    "gn:admin1_code":"10",
    "gn:admin2_code":"37",
    "gn:asciiname":"El Venado",
    "gn:country_code":"MX",
    "gn:dem":933,
    "gn:feature_class":"P",
    "gn:feature_code":"PPL",
    "gn:name":"El Venado",
    "gn:population":21,
    "gn:timezone":"America/Monterrey",
    "iso:country":"MX",
    "wof:name":"El Venado",
    "wof:placetype":"locality",
    "wof:population":21
},
  "geometry": {"coordinates":[-106.75758999999999,25.15942],"type":"Point"}
}