{
  "type": "Feature",
  "properties": {
    "gn:admin1_code":"30.0",
    "gn:admin2_code":"121.0",
    "gn:asciiname":"La Tigra",
    "gn:country_code":"MX",
    "gn:dem":36,
    "gn:feature_class":"P",
    "gn:feature_code":"PPL",
    "gn:name":"La Tigra",
    "gn:population":0,
    "gn:timezone":"America/Mexico_City",
    "iso:country":"MX",
    "name:spa_x_preferred":[
        "La Tigra"
    ],
    "wof:name":"La Tigra",
    "wof:placetype":"locality"
},
  "geometry": {"coordinates":[-97.74611,21.70361],"type":"Point"}
}