{
  "type": "Feature",
  "properties": {
    "gn:admin1_code":"6",
    "gn:admin2_code":"28.0",
    "gn:asciiname":"Cieneguita",
    "gn:country_code":"MX",
    "gn:dem":1018,
    "gn:feature_class":"P",
    "gn:feature_code":"PPL",
    "gn:name":"Cieneguita",
    "gn:population":0,
    "gn:timezone":"America/Chihuahua",
    "iso:country":"MX",
    "name:und_x_variant":[
        "Cieneguilla"
    ],
    "wof:name":"Cieneguita",
    "wof:placetype":"locality"
},
  "geometry": {"coordinates":[-105.24767,30.78109000000001],"type":"Point"}
}