{
  "type": "Feature",
  "properties": {
    "gn:admin1_code":"6.0",
    "gn:admin2_code":"51.0",
    "gn:asciiname":"La Huerta",
    "gn:country_code":"MX",
    "gn:dem":1441,
    "gn:feature_class":"P",
    "gn:feature_code":"PPL",
    "gn:name":"La Huerta",
    "gn:population":0,
    "gn:timezone":"America/Chihuahua",
    "iso:country":"MX",
    "name:spa_x_preferred":[
        "La Huerta"
    ],
    "wof:name":"La Huerta",
    "wof:placetype":"locality"
},
  "geometry": {"coordinates":[-108.44844999999999,28.29647000000001],"type":"Point"}
}