{
  "type": "Feature",
  "properties": {
    "gn:admin1_code":"20",
    "gn:admin2_code":"348.0",
    "gn:asciiname":"Santo Nino Jesus Yucuyi",
    "gn:country_code":"MX",
    "gn:dem":2291,
    "gn:feature_class":"P",
    "gn:feature_code":"PPL",
    "gn:name":"Santo Ni\u00f1o Jes\u00fas Yucuyi",
    "gn:population":231,
    "gn:timezone":"America/Mexico_City",
    "iso:country":"MX",
    "name:und_x_variant":[
        "Santo Ni\u00f1o Jes\u00fas Yucuyi"
    ],
    "wof:name":"Santo Nino Jesus Yucuyi",
    "wof:placetype":"locality",
    "wof:population":231
},
  "geometry": {"coordinates":[-98.10639,17.28694],"type":"Point"}
}