{
  "type": "Feature",
  "properties": {
    "gn:admin1_code":"5",
    "gn:admin2_code":"61.0",
    "gn:asciiname":"El Capulin",
    "gn:country_code":"MX",
    "gn:dem":766,
    "gn:feature_class":"P",
    "gn:feature_code":"PPL",
    "gn:name":"El Capul\u00edn",
    "gn:population":5,
    "gn:timezone":"America/Mexico_City",
    "iso:country":"MX",
    "name:und_x_variant":[
        "El Capul\u00edn"
    ],
    "wof:name":"El Capulin",
    "wof:placetype":"locality",
    "wof:population":5
},
  "geometry": {"coordinates":[-93.43667000000001,16.77056],"type":"Point"}
}