{
  "type": "Feature",
  "properties": {
    "gn:admin1_code":"31",
    "gn:admin2_code":"63.0",
    "gn:asciiname":"Cuzumal",
    "gn:country_code":"MX",
    "gn:dem":10,
    "gn:feature_class":"P",
    "gn:feature_code":"PPL",
    "gn:name":"Cuzumal",
    "gn:population":0,
    "gn:timezone":"America/Merida",
    "iso:country":"MX",
    "wof:name":"Cuzumal",
    "wof:placetype":"locality"
},
  "geometry": {"coordinates":[-89.95721999999998,20.7975],"type":"Point"}
}