{
  "type": "Feature",
  "properties": {
    "gn:admin1_code":"30.0",
    "gn:admin2_code":"205.0",
    "gn:asciiname":"El Oro",
    "gn:country_code":"MX",
    "gn:dem":56,
    "gn:feature_class":"P",
    "gn:feature_code":"PPL",
    "gn:name":"El Oro",
    "gn:population":0,
    "gn:timezone":"America/Mexico_City",
    "iso:country":"MX",
    "name:ceb_x_preferred":[
        "El Oro"
    ],
    "name:deu_x_preferred":[
        "El Oro"
    ],
    "name:epo_x_preferred":[
        "El Oro"
    ],
    "name:ita_x_preferred":[
        "El Oro"
    ],
    "name:lad_x_preferred":[
        "El Oro"
    ],
    "name:sco_x_preferred":[
        "El Oro"
    ],
    "name:spa_x_preferred":[
        "El Oro"
    ],
    "name:srp_x_preferred":[
        "\u0415\u043b \u041e\u0440\u043e"
    ],
    "name:swe_x_preferred":[
        "El Oro"
    ],
    "wof:name":"El Oro",
    "wof:placetype":"locality"
},
  "geometry": {"coordinates":[-98.42601000000001,21.85284],"type":"Point"}
}