{
  "type": "Feature",
  "properties": {
    "gn:admin1_code":"15",
    "gn:admin2_code":"114.0",
    "gn:asciiname":"El Panteon",
    "gn:country_code":"MX",
    "gn:dem":2662,
    "gn:feature_class":"P",
    "gn:feature_code":"PPL",
    "gn:name":"El Pante\u00f3n",
    "gn:population":456,
    "gn:timezone":"America/Mexico_City",
    "iso:country":"MX",
    "name:und_x_variant":[
        "El Pante\u00f3n"
    ],
    "wof:name":"El Panteon",
    "wof:placetype":"locality",
    "wof:population":456
},
  "geometry": {"coordinates":[-100.03111,19.50333],"type":"Point"}
}