{
  "type": "Feature",
  "properties": {
    "gn:admin1_code":"2.0",
    "gn:admin2_code":"3.0",
    "gn:asciiname":"El Testorazo",
    "gn:country_code":"MX",
    "gn:dem":974,
    "gn:feature_class":"P",
    "gn:feature_code":"PPL",
    "gn:name":"El Testorazo",
    "gn:population":0,
    "gn:timezone":"America/Tijuana",
    "iso:country":"MX",
    "name:spa_x_preferred":[
        "El Testorazo"
    ],
    "name:und_x_variant":[
        "Rancho El Testorazo"
    ],
    "wof:name":"El Testorazo",
    "wof:placetype":"locality"
},
  "geometry": {"coordinates":[-116.2782,32.32942],"type":"Point"}
}