{
  "type": "Feature",
  "properties": {
    "gn:admin1_code":"10",
    "gn:admin2_code":"2",
    "gn:asciiname":"El Encinal",
    "gn:country_code":"MX",
    "gn:dem":1427,
    "gn:feature_class":"P",
    "gn:feature_code":"PPL",
    "gn:name":"El Encinal",
    "gn:population":19,
    "gn:timezone":"America/Monterrey",
    "iso:country":"MX",
    "wof:name":"El Encinal",
    "wof:placetype":"locality",
    "wof:population":19
},
  "geometry": {"coordinates":[-106.52306000000002,25.06055],"type":"Point"}
}