{
  "type": "Feature",
  "properties": {
    "gn:admin1_code":"30",
    "gn:admin2_code":"126.0",
    "gn:asciiname":"El Mango",
    "gn:country_code":"MX",
    "gn:dem":16,
    "gn:feature_class":"P",
    "gn:feature_code":"PPL",
    "gn:name":"El Mango",
    "gn:population":650,
    "gn:timezone":"America/Mexico_City",
    "iso:country":"MX",
    "wof:name":"El Mango",
    "wof:placetype":"locality",
    "wof:population":650
},
  "geometry": {"coordinates":[-96.38667,19.32306],"type":"Point"}
}