{
  "type": "Feature",
  "properties": {
    "gn:admin1_code":"30",
    "gn:admin2_code":"111.0",
    "gn:asciiname":"La Tolva",
    "gn:country_code":"MX",
    "gn:dem":46,
    "gn:feature_class":"P",
    "gn:feature_code":"PPL",
    "gn:name":"La Tolva",
    "gn:population":9,
    "gn:timezone":"America/Mexico_City",
    "iso:country":"MX",
    "wof:name":"La Tolva",
    "wof:placetype":"locality",
    "wof:population":9
},
  "geometry": {"coordinates":[-94.27139,17.98832999999999],"type":"Point"}
}