{
  "type": "Feature",
  "properties": {
    "gn:admin1_code":"27",
    "gn:admin2_code":"5.0",
    "gn:asciiname":"Leon Zarate Primera Seccion",
    "gn:country_code":"MX",
    "gn:dem":15,
    "gn:feature_class":"P",
    "gn:feature_code":"PPL",
    "gn:name":"Le\u00f3n Z\u00e1rate Primera Secci\u00f3n",
    "gn:population":0,
    "gn:timezone":"America/Mexico_City",
    "iso:country":"MX",
    "name:spa_x_preferred":[
        "Le\u00f3n Zarate"
    ],
    "name:spa_x_variant":[
        "Le\u00f3n Z\u00e1rate Primera Secci\u00f3n"
    ],
    "wof:name":"Leon Zarate Primera Seccion",
    "wof:placetype":"locality"
},
  "geometry": {"coordinates":[-93.30695,18.23021],"type":"Point"}
}