{
  "type": "Feature",
  "properties": {
    "gn:admin1_code":"20",
    "gn:admin2_code":"59.0",
    "gn:asciiname":"San Felipe Yegachin",
    "gn:country_code":"MX",
    "gn:dem":1564,
    "gn:feature_class":"P",
    "gn:feature_code":"PPL",
    "gn:name":"San Felipe Yegach\u00edn",
    "gn:population":0,
    "gn:timezone":"America/Mexico_City",
    "iso:country":"MX",
    "name:spa_x_preferred":[
        "Yegachin"
    ],
    "name:spa_x_variant":[
        "San Felipe Yegach\u00edn"
    ],
    "wof:name":"San Felipe Yegachin",
    "wof:placetype":"locality"
},
  "geometry": {"coordinates":[-96.60101,16.37699],"type":"Point"}
}