{
  "type": "Feature",
  "properties": {
    "gn:admin1_code":"30",
    "gn:admin2_code":"152.0",
    "gn:asciiname":"La Rivera de Tampico Alto",
    "gn:country_code":"MX",
    "gn:dem":11,
    "gn:feature_class":"P",
    "gn:feature_code":"PPL",
    "gn:name":"La Rivera de Tampico Alto",
    "gn:population":0,
    "gn:timezone":"America/Mexico_City",
    "iso:country":"MX",
    "name:und_x_variant":[
        "La Rivera de Tampoco Alto",
        "La Rivera de Tampico Alto",
        "Rivera de Tampico Alto"
    ],
    "wof:name":"La Rivera de Tampico Alto",
    "wof:placetype":"locality"
},
  "geometry": {"coordinates":[-97.78124,22.10533],"type":"Point"}
}