{
  "type": "Feature",
  "properties": {
    "gn:admin1_code":"4.0",
    "gn:admin2_code":"11.0",
    "gn:asciiname":"Santa Amelia",
    "gn:country_code":"MX",
    "gn:dem":42,
    "gn:feature_class":"P",
    "gn:feature_code":"PPL",
    "gn:name":"Santa Amelia",
    "gn:population":3,
    "gn:timezone":"America/Merida",
    "iso:country":"MX",
    "name:spa_x_preferred":[
        "Santa Amelia"
    ],
    "wof:name":"Santa Amelia",
    "wof:placetype":"locality",
    "wof:population":3
},
  "geometry": {"coordinates":[-90.82222,18.13556],"type":"Point"}
}