{
  "type": "Feature",
  "properties": {
    "gn:admin1_code":"25.0",
    "gn:admin2_code":"10.0",
    "gn:asciiname":"Campo Liberato",
    "gn:country_code":"MX",
    "gn:dem":18,
    "gn:feature_class":"P",
    "gn:feature_code":"PPL",
    "gn:name":"Campo Liberato",
    "gn:population":0,
    "gn:timezone":"America/Mazatlan",
    "iso:country":"MX",
    "name:spa_x_preferred":[
        "Campo Liberato"
    ],
    "wof:name":"Campo Liberato",
    "wof:placetype":"locality"
},
  "geometry": {"coordinates":[-108.98599,26.13300000000001],"type":"Point"}
}