{
  "type": "Feature",
  "properties": {
    "gn:admin1_code":"14.0",
    "gn:admin2_code":"12.0",
    "gn:asciiname":"Piedra Grande",
    "gn:country_code":"MX",
    "gn:dem":1420,
    "gn:feature_class":"P",
    "gn:feature_code":"PPL",
    "gn:name":"Piedra Grande",
    "gn:population":0,
    "gn:timezone":"America/Mexico_City",
    "iso:country":"MX",
    "name:spa_x_preferred":[
        "Piedra Grande"
    ],
    "name:spa_x_variant":[
        "Piedra Parada"
    ],
    "wof:name":"Piedra Grande",
    "wof:placetype":"locality"
},
  "geometry": {"coordinates":[-104.51309999999999,20.50861],"type":"Point"}
}