{
  "type": "Feature",
  "properties": {
    "gn:admin1_code":"6",
    "gn:admin2_code":"56.0",
    "gn:asciiname":"Milpillas",
    "gn:country_code":"MX",
    "gn:dem":1494,
    "gn:feature_class":"P",
    "gn:feature_code":"PPL",
    "gn:name":"Milpillas",
    "gn:population":0,
    "gn:timezone":"America/Chihuahua",
    "iso:country":"MX",
    "wof:name":"Milpillas",
    "wof:placetype":"locality"
},
  "geometry": {"coordinates":[-106.34999999999999,27.36667000000001],"type":"Point"}
}