{
  "type": "Feature",
  "properties": {
    "gn:admin1_code":"12.0",
    "gn:admin2_code":"14.0",
    "gn:asciiname":"Huerta las Palmas Cuatas",
    "gn:country_code":"MX",
    "gn:dem":21,
    "gn:feature_class":"P",
    "gn:feature_code":"PPL",
    "gn:name":"Huerta las Palmas Cuatas",
    "gn:population":0,
    "gn:timezone":"America/Mexico_City",
    "iso:country":"MX",
    "name:spa_x_preferred":[
        "Huerta las Palmas Cuatas"
    ],
    "wof:name":"Huerta las Palmas Cuatas",
    "wof:placetype":"locality"
},
  "geometry": {"coordinates":[-100.47637,17.12713],"type":"Point"}
}