{
  "type": "Feature",
  "properties": {
    "gn:admin1_code":"14.0",
    "gn:admin2_code":"35.0",
    "gn:asciiname":"La Labor de Abajo",
    "gn:country_code":"MX",
    "gn:dem":1777,
    "gn:feature_class":"P",
    "gn:feature_code":"PPL",
    "gn:name":"La Labor de Abajo",
    "gn:population":0,
    "gn:timezone":"America/Mexico_City",
    "iso:country":"MX",
    "name:spa_x_preferred":[
        "La Labor de Abajo"
    ],
    "wof:name":"La Labor de Abajo",
    "wof:placetype":"locality"
},
  "geometry": {"coordinates":[-102.28708,21.54154],"type":"Point"}
}