{
  "type": "Feature",
  "properties": {
    "gn:admin1_code":"5.0",
    "gn:admin2_code":"23.0",
    "gn:asciiname":"Saclamanton",
    "gn:country_code":"MX",
    "gn:dem":2446,
    "gn:feature_class":"P",
    "gn:feature_code":"PPL",
    "gn:name":"Saclamant\u00f3n",
    "gn:population":0,
    "gn:timezone":"America/Mexico_City",
    "iso:country":"MX",
    "name:spa_x_preferred":[
        "Tzaclamant\u00f3n"
    ],
    "name:spa_x_variant":[
        "Saclamant\u00f3n"
    ],
    "wof:name":"Saclamanton",
    "wof:placetype":"locality"
},
  "geometry": {"coordinates":[-92.63355,16.78828],"type":"Point"}
}