{
  "type": "Feature",
  "properties": {
    "gn:admin1_code":"11",
    "gn:admin2_code":"31.0",
    "gn:asciiname":"Fraccionamiento la Mezquitera",
    "gn:country_code":"MX",
    "gn:dem":1756,
    "gn:feature_class":"P",
    "gn:feature_code":"PPL",
    "gn:name":"Fraccionamiento la Mezquitera",
    "gn:population":1034,
    "gn:timezone":"America/Mexico_City",
    "iso:country":"MX",
    "wof:name":"Fraccionamiento la Mezquitera",
    "wof:placetype":"locality",
    "wof:population":1034
},
  "geometry": {"coordinates":[-101.83472,21.00972],"type":"Point"}
}