{
  "type": "Feature",
  "properties": {
    "gn:admin1_code":"6.0",
    "gn:admin2_code":"62.0",
    "gn:asciiname":"Los Depositos",
    "gn:country_code":"MX",
    "gn:dem":1358,
    "gn:feature_class":"P",
    "gn:feature_code":"PPL",
    "gn:name":"Los Dep\u00f3sitos",
    "gn:population":0,
    "gn:timezone":"America/Chihuahua",
    "iso:country":"MX",
    "name:spa_x_preferred":[
        "Los Dep\u00f3sitos"
    ],
    "wof:name":"Los Depositos",
    "wof:placetype":"locality"
},
  "geometry": {"coordinates":[-105.66909,27.83173],"type":"Point"}
}