{
  "type": "Feature",
  "properties": {
    "gn:admin1_code":"1",
    "gn:admin2_code":"1",
    "gn:asciiname":"La Sociedad",
    "gn:country_code":"MX",
    "gn:dem":1984,
    "gn:feature_class":"P",
    "gn:feature_code":"PPL",
    "gn:name":"La Sociedad",
    "gn:population":9,
    "gn:timezone":"America/Mexico_City",
    "iso:country":"MX",
    "name:spa_x_preferred":[
        "La Sociedad"
    ],
    "wof:name":"La Sociedad",
    "wof:placetype":"locality",
    "wof:population":9
},
  "geometry": {"coordinates":[-102.13167,22.05722],"type":"Point"}
}