{
  "type": "Feature",
  "properties": {
    "gn:admin1_code":"10",
    "gn:admin2_code":"28.0",
    "gn:asciiname":"Potrero las Parras",
    "gn:country_code":"MX",
    "gn:dem":1834,
    "gn:feature_class":"P",
    "gn:feature_code":"PPL",
    "gn:name":"Potrero las Parras",
    "gn:population":0,
    "gn:timezone":"America/Monterrey",
    "iso:country":"MX",
    "name:spa_x_preferred":[
        "Potrero las Parras"
    ],
    "wof:name":"Potrero las Parras",
    "wof:placetype":"locality"
},
  "geometry": {"coordinates":[-104.44401999999999,24.67009],"type":"Point"}
}