{
  "type": "Feature",
  "properties": {
    "gn:admin1_code":"26",
    "gn:admin2_code":"33.0",
    "gn:asciiname":"Loma de Moroncarit",
    "gn:country_code":"MX",
    "gn:dem":8,
    "gn:feature_class":"P",
    "gn:feature_code":"PPL",
    "gn:name":"Loma de Moroncarit",
    "gn:population":0,
    "gn:timezone":"America/Hermosillo",
    "iso:country":"MX",
    "name:spa_x_preferred":[
        "Loma de Moroncarit"
    ],
    "wof:name":"Loma de Moroncarit",
    "wof:placetype":"locality"
},
  "geometry": {"coordinates":[-109.67447,26.75176],"type":"Point"}
}