{
  "type": "Feature",
  "properties": {
    "gn:admin1_code":"7",
    "gn:admin2_code":"14.0",
    "gn:asciiname":"Rancho Ciudad de Dios",
    "gn:country_code":"MX",
    "gn:dem":258,
    "gn:feature_class":"P",
    "gn:feature_code":"PPL",
    "gn:name":"Rancho Ciudad de Dios",
    "gn:population":4,
    "gn:timezone":"America/Monterrey",
    "iso:country":"MX",
    "wof:name":"Rancho Ciudad de Dios",
    "wof:placetype":"locality",
    "wof:population":4
},
  "geometry": {"coordinates":[-100.68841999999999,29.07939],"type":"Point"}
}