{
  "type": "Feature",
  "properties": {
    "gn:admin1_code":"10",
    "gn:admin2_code":"9",
    "gn:asciiname":"El Pinal",
    "gn:country_code":"MX",
    "gn:dem":2840,
    "gn:feature_class":"P",
    "gn:feature_code":"PPL",
    "gn:name":"El Pinal",
    "gn:population":13,
    "gn:timezone":"America/Monterrey",
    "iso:country":"MX",
    "wof:name":"El Pinal",
    "wof:placetype":"locality",
    "wof:population":13
},
  "geometry": {"coordinates":[-106.32067000000001,25.87969],"type":"Point"}
}