{
  "type": "Feature",
  "properties": {
    "gn:admin1_code":"28.0",
    "gn:admin2_code":"11.0",
    "gn:asciiname":"El Fuste",
    "gn:country_code":"MX",
    "gn:dem":77,
    "gn:feature_class":"P",
    "gn:feature_code":"PPL",
    "gn:name":"El Fuste",
    "gn:population":4,
    "gn:timezone":"America/Monterrey",
    "iso:country":"MX",
    "name:spa_x_preferred":[
        "El Fuste"
    ],
    "wof:name":"El Fuste",
    "wof:placetype":"locality",
    "wof:population":4
},
  "geometry": {"coordinates":[-99.04857,22.93438],"type":"Point"}
}