{
  "type": "Feature",
  "properties": {
    "gn:admin1_code":"6",
    "gn:admin2_code":"36",
    "gn:asciiname":"Chapacache",
    "gn:country_code":"MX",
    "gn:dem":1363,
    "gn:feature_class":"P",
    "gn:feature_code":"PPL",
    "gn:name":"Chapacache",
    "gn:population":11,
    "gn:timezone":"America/Chihuahua",
    "iso:country":"MX",
    "wof:name":"Chapacache",
    "wof:placetype":"locality",
    "wof:population":11
},
  "geometry": {"coordinates":[-104.87465,27.17511],"type":"Point"}
}