{
  "type": "Feature",
  "properties": {
    "gn:admin1_code":"16",
    "gn:admin2_code":"97",
    "gn:asciiname":"El Limon de Paranguaro",
    "gn:country_code":"MX",
    "gn:dem":592,
    "gn:feature_class":"P",
    "gn:feature_code":"PPL",
    "gn:name":"El Lim\u00f3n de Par\u00e1nguaro",
    "gn:population":24,
    "gn:timezone":"America/Mexico_City",
    "iso:country":"MX",
    "name:und_x_variant":[
        "El Lim\u00f3n de Par\u00e1nguaro"
    ],
    "wof:name":"El Limon de Paranguaro",
    "wof:placetype":"locality",
    "wof:population":24
},
  "geometry": {"coordinates":[-101.25888999999999,18.74639],"type":"Point"}
}