{
  "type": "Feature",
  "properties": {
    "gn:admin1_code":"5",
    "gn:admin2_code":"32",
    "gn:asciiname":"Armenia",
    "gn:country_code":"MX",
    "gn:dem":1063,
    "gn:feature_class":"P",
    "gn:feature_code":"PPL",
    "gn:name":"Armenia",
    "gn:population":40,
    "gn:timezone":"America/Mexico_City",
    "iso:country":"MX",
    "wof:name":"Armenia",
    "wof:placetype":"locality",
    "wof:population":40
},
  "geometry": {"coordinates":[-92.52139,15.375],"type":"Point"}
}