{
  "type": "Feature",
  "properties": {
    "gn:admin1_code":"14.0",
    "gn:admin2_code":"85.0",
    "gn:asciiname":"Las Guasimas",
    "gn:country_code":"MX",
    "gn:dem":1460,
    "gn:feature_class":"P",
    "gn:feature_code":"PPL",
    "gn:name":"Las Gu\u00e1simas",
    "gn:population":0,
    "gn:timezone":"America/Mexico_City",
    "iso:country":"MX",
    "name:spa_x_preferred":[
        "Las Gu\u00e1simas"
    ],
    "wof:name":"Las Guasimas",
    "wof:placetype":"locality"
},
  "geometry": {"coordinates":[-103.21539,19.54346],"type":"Point"}
}