{
  "type": "Feature",
  "properties": {
    "gn:admin1_code":"30",
    "gn:admin2_code":"8.0",
    "gn:asciiname":"San Martin Caballero",
    "gn:country_code":"MX",
    "gn:dem":2014,
    "gn:feature_class":"P",
    "gn:feature_code":"PPL",
    "gn:name":"San Mart\u00edn Caballero",
    "gn:population":76,
    "gn:timezone":"America/Mexico_City",
    "iso:country":"MX",
    "name:und_x_variant":[
        "San Mart\u00edn Caballero"
    ],
    "wof:name":"San Martin Caballero",
    "wof:placetype":"locality",
    "wof:population":76
},
  "geometry": {"coordinates":[-97.11667,19.06889],"type":"Point"}
}