{
  "type": "Feature",
  "properties": {
    "gn:admin1_code":"20",
    "gn:admin2_code":"386.0",
    "gn:asciiname":"Agua Ceniza",
    "gn:country_code":"MX",
    "gn:dem":1052,
    "gn:feature_class":"P",
    "gn:feature_code":"PPL",
    "gn:name":"Agua Ceniza",
    "gn:population":204,
    "gn:timezone":"America/Mexico_City",
    "iso:country":"MX",
    "wof:name":"Agua Ceniza",
    "wof:placetype":"locality",
    "wof:population":204
},
  "geometry": {"coordinates":[-97.39472000000001,16.50139],"type":"Point"}
}