{
  "type": "Feature",
  "properties": {
    "gn:admin1_code":"4.0",
    "gn:asciiname":"El Diamante",
    "gn:country_code":"MX",
    "gn:dem":266,
    "gn:feature_class":"P",
    "gn:feature_code":"PPL",
    "gn:name":"El Diamante",
    "gn:population":0,
    "gn:timezone":"America/Cancun",
    "iso:country":"MX",
    "name:spa_x_preferred":[
        "El Diamante"
    ],
    "wof:name":"El Diamante",
    "wof:placetype":"locality"
},
  "geometry": {"coordinates":[-89.37993,18.06654],"type":"Point"}
}