{
  "type": "Feature",
  "properties": {
    "gn:admin1_code":"2",
    "gn:admin2_code":"3",
    "gn:asciiname":"Villa Soledad",
    "gn:country_code":"MX",
    "gn:dem":950,
    "gn:feature_class":"P",
    "gn:feature_code":"PPL",
    "gn:name":"Villa Soledad",
    "gn:population":13,
    "gn:timezone":"America/Tijuana",
    "iso:country":"MX",
    "wof:name":"Villa Soledad",
    "wof:placetype":"locality",
    "wof:population":13
},
  "geometry": {"coordinates":[-116.37806,32.53556],"type":"Point"}
}