{
  "type": "Feature",
  "properties": {
    "gn:admin1_code":"7",
    "gn:admin2_code":"31.0",
    "gn:asciiname":"Luis Romo Gutierrez",
    "gn:country_code":"MX",
    "gn:dem":518,
    "gn:feature_class":"P",
    "gn:feature_code":"PPL",
    "gn:name":"Luis Romo Guti\u00e9rrez",
    "gn:population":5,
    "gn:timezone":"America/Monterrey",
    "iso:country":"MX",
    "name:und_x_variant":[
        "Luis Romo Guti\u00e9rrez"
    ],
    "wof:name":"Luis Romo Gutierrez",
    "wof:placetype":"locality",
    "wof:population":5
},
  "geometry": {"coordinates":[-101.52036,27.01666],"type":"Point"}
}