{
  "type": "Feature",
  "properties": {
    "gn:admin1_code":"26.0",
    "gn:admin2_code":"61.0",
    "gn:asciiname":"El Baiburin",
    "gn:country_code":"MX",
    "gn:dem":384,
    "gn:feature_class":"P",
    "gn:feature_code":"PPL",
    "gn:name":"El Baiburin",
    "gn:population":0,
    "gn:timezone":"America/Hermosillo",
    "iso:country":"MX",
    "name:spa_x_preferred":[
        "El Baiburin"
    ],
    "wof:name":"El Baiburin",
    "wof:placetype":"locality"
},
  "geometry": {"coordinates":[-109.45901000000001,28.59199000000001],"type":"Point"}
}