{
  "type": "Feature",
  "properties": {
    "gn:admin1_code":"5.0",
    "gn:asciiname":"El Trebol",
    "gn:country_code":"MX",
    "gn:dem":32,
    "gn:feature_class":"P",
    "gn:feature_code":"PPL",
    "gn:name":"El Tr\u00e9bol",
    "gn:population":0,
    "gn:timezone":"America/Mexico_City",
    "iso:country":"MX",
    "name:spa_x_preferred":[
        "El Tr\u00e9bol"
    ],
    "wof:name":"El Trebol",
    "wof:placetype":"locality"
},
  "geometry": {"coordinates":[-92.27204999999999,14.74393],"type":"Point"}
}