{
  "type": "Feature",
  "properties": {
    "gn:admin1_code":"10",
    "gn:admin2_code":"19.0",
    "gn:asciiname":"La Trinidad",
    "gn:country_code":"MX",
    "gn:dem":2485,
    "gn:feature_class":"P",
    "gn:feature_code":"PPL",
    "gn:name":"La Trinidad",
    "gn:population":0,
    "gn:timezone":"America/Monterrey",
    "iso:country":"MX",
    "name:und_x_variant":[
        "Trinidad",
        "La Trinidad"
    ],
    "wof:name":"La Trinidad",
    "wof:placetype":"locality"
},
  "geometry": {"coordinates":[-105.98913,24.62066],"type":"Point"}
}