{
  "type": "Feature",
  "properties": {
    "gn:admin1_code":"26",
    "gn:admin2_code":"18.0",
    "gn:asciiname":"Yucuribampo",
    "gn:country_code":"MX",
    "gn:dem":78,
    "gn:feature_class":"P",
    "gn:feature_code":"PPL",
    "gn:name":"Yucuribampo",
    "gn:population":0,
    "gn:timezone":"America/Hermosillo",
    "iso:country":"MX",
    "name:und_x_variant":[
        "Rancho Yucuribampo",
        "Yucuribampo"
    ],
    "wof:name":"Yucuribampo",
    "wof:placetype":"locality"
},
  "geometry": {"coordinates":[-109.8116,27.4574],"type":"Point"}
}