{
  "type": "Feature",
  "properties": {
    "gn:admin1_code":"11",
    "gn:admin2_code":"3.0",
    "gn:asciiname":"Manantiales",
    "gn:cc2":"MX",
    "gn:country_code":"MX",
    "gn:dem":2035,
    "gn:feature_class":"P",
    "gn:feature_code":"PPL",
    "gn:name":"Manantiales",
    "gn:population":406,
    "gn:timezone":"America/Mexico_City",
    "iso:country":"MX",
    "name:und_x_variant":[
        "Manantial",
        "Manantiales"
    ],
    "wof:name":"Manantiales",
    "wof:placetype":"locality",
    "wof:population":406
},
  "geometry": {"coordinates":[-101.00360999999999,20.89417000000001],"type":"Point"}
}