{
  "type": "Feature",
  "properties": {
    "gn:admin1_code":"25.0",
    "gn:asciiname":"Cruz Pinta",
    "gn:country_code":"MX",
    "gn:dem":23,
    "gn:feature_class":"P",
    "gn:feature_code":"PPL",
    "gn:name":"Cruz Pinta",
    "gn:population":0,
    "gn:timezone":"America/Mazatlan",
    "iso:country":"MX",
    "name:spa_x_preferred":[
        "Cruz Pinta"
    ],
    "wof:name":"Cruz Pinta",
    "wof:placetype":"locality"
},
  "geometry": {"coordinates":[-108.96402,25.9585],"type":"Point"}
}