{
  "type": "Feature",
  "properties": {
    "gn:admin1_code":"20",
    "gn:admin2_code":"133.0",
    "gn:asciiname":"Ndoyocoyo",
    "gn:country_code":"MX",
    "gn:dem":2587,
    "gn:feature_class":"P",
    "gn:feature_code":"PPL",
    "gn:name":"Ndoyocoyo",
    "gn:population":0,
    "gn:timezone":"America/Mexico_City",
    "iso:country":"MX",
    "name:spa_x_preferred":[
        "Ndoyocoyo"
    ],
    "wof:name":"Ndoyocoyo",
    "wof:placetype":"locality"
},
  "geometry": {"coordinates":[-97.73165,17.11112],"type":"Point"}
}