{
  "type": "Feature",
  "properties": {
    "gn:admin1_code":"25",
    "gn:admin2_code":"7.0",
    "gn:asciiname":"El Jupari",
    "gn:country_code":"MX",
    "gn:dem":424,
    "gn:feature_class":"P",
    "gn:feature_code":"PPL",
    "gn:name":"El Jupari",
    "gn:population":0,
    "gn:timezone":"America/Mazatlan",
    "iso:country":"MX",
    "name:spa_x_preferred":[
        "El Jupari"
    ],
    "wof:name":"El Jupari",
    "wof:placetype":"locality"
},
  "geometry": {"coordinates":[-108.36732000000001,26.66728],"type":"Point"}
}