{
  "type": "Feature",
  "properties": {
    "gn:admin1_code":"5",
    "gn:admin2_code":"108",
    "gn:asciiname":"Matamoros (Cuilco)",
    "gn:country_code":"MX",
    "gn:dem":603,
    "gn:feature_class":"P",
    "gn:feature_code":"PPL",
    "gn:name":"Matamoros (Cuilco)",
    "gn:population":12,
    "gn:timezone":"America/Mexico_City",
    "iso:country":"MX",
    "wof:name":"Matamoros (Cuilco)",
    "wof:placetype":"locality",
    "wof:population":12
},
  "geometry": {"coordinates":[-93.36,16.43444],"type":"Point"}
}