{
  "type": "Feature",
  "properties": {
    "gn:admin1_code":"6.0",
    "gn:admin2_code":"52.0",
    "gn:asciiname":"Chivarrias Blancas",
    "gn:country_code":"MX",
    "gn:dem":885,
    "gn:feature_class":"P",
    "gn:feature_code":"PPL",
    "gn:name":"Chivarrias Blancas",
    "gn:population":0,
    "gn:timezone":"America/Ojinaga",
    "iso:country":"MX",
    "wof:name":"Chivarrias Blancas",
    "wof:placetype":"locality"
},
  "geometry": {"coordinates":[-104.68478,29.9532],"type":"Point"}
}