{
  "type": "Feature",
  "properties": {
    "gn:admin1_code":"5",
    "gn:admin2_code":"89",
    "gn:asciiname":"Santa Fe",
    "gn:country_code":"MX",
    "gn:dem":7,
    "gn:feature_class":"P",
    "gn:feature_code":"PPL",
    "gn:name":"Santa Fe",
    "gn:population":27,
    "gn:timezone":"America/Mexico_City",
    "iso:country":"MX",
    "wof:name":"Santa Fe",
    "wof:placetype":"locality",
    "wof:population":27
},
  "geometry": {"coordinates":[-92.41667,14.72611],"type":"Point"}
}