{
  "type": "Feature",
  "properties": {
    "gn:admin1_code":"9",
    "gn:admin2_code":"13.0",
    "gn:asciiname":"Apatlaco",
    "gn:country_code":"MX",
    "gn:dem":2238,
    "gn:feature_class":"P",
    "gn:feature_code":"PPL",
    "gn:name":"Apatlaco",
    "gn:population":69,
    "gn:timezone":"America/Mexico_City",
    "iso:country":"MX",
    "wof:name":"Apatlaco",
    "wof:placetype":"locality",
    "wof:population":69
},
  "geometry": {"coordinates":[-99.08611000000001,19.26361],"type":"Point"}
}