{
  "type": "Feature",
  "properties": {
    "gn:admin1_code":"16",
    "gn:admin2_code":"82.0",
    "gn:asciiname":"Romero",
    "gn:country_code":"MX",
    "gn:dem":1340,
    "gn:feature_class":"P",
    "gn:feature_code":"PPL",
    "gn:name":"Romero",
    "gn:population":5,
    "gn:timezone":"America/Mexico_City",
    "iso:country":"MX",
    "name:cat_x_preferred":[
        "Romero"
    ],
    "name:ces_x_preferred":[
        "Romero"
    ],
    "name:deu_x_preferred":[
        "Romero"
    ],
    "name:fra_x_preferred":[
        "Romero"
    ],
    "name:ita_x_preferred":[
        "Romero"
    ],
    "name:jpn_x_preferred":[
        "\u30ed\u30e1\u30ed"
    ],
    "name:lit_x_preferred":[
        "Romero"
    ],
    "name:nld_x_preferred":[
        "Romero"
    ],
    "name:por_x_preferred":[
        "Romero"
    ],
    "name:rus_x_preferred":[
        "\u0420\u043e\u043c\u0435\u0440\u043e"
    ],
    "name:spa_x_preferred":[
        "Romero"
    ],
    "name:swe_x_preferred":[
        "Romero"
    ],
    "name:tgl_x_preferred":[
        "Romero"
    ],
    "wof:name":"Romero",
    "wof:placetype":"locality",
    "wof:population":5
},
  "geometry": {"coordinates":[-101.47667,19.17361],"type":"Point"}
}