{
  "type": "Feature",
  "properties": {
    "gn:admin1_code":"26.0",
    "gn:admin2_code":"42.0",
    "gn:asciiname":"Agua Nueva",
    "gn:country_code":"MX",
    "gn:dem":174,
    "gn:feature_class":"P",
    "gn:feature_code":"PPL",
    "gn:name":"Agua Nueva",
    "gn:population":0,
    "gn:timezone":"America/Hermosillo",
    "iso:country":"MX",
    "name:spa_x_preferred":[
        "Agua Nueva"
    ],
    "name:spa_x_variant":[
        "Agua nueva"
    ],
    "wof:name":"Agua Nueva",
    "wof:placetype":"locality"
},
  "geometry": {"coordinates":[-109.06658,26.75022],"type":"Point"}
}