{
  "type": "Feature",
  "properties": {
    "gn:admin1_code":"26",
    "gn:admin2_code":"17.0",
    "gn:asciiname":"Menechi",
    "gn:country_code":"MX",
    "gn:dem":746,
    "gn:feature_class":"P",
    "gn:feature_code":"PPL",
    "gn:name":"Menechi",
    "gn:population":0,
    "gn:timezone":"America/Hermosillo",
    "iso:country":"MX",
    "wof:name":"Menechi",
    "wof:placetype":"locality"
},
  "geometry": {"coordinates":[-112.32762,31.33741],"type":"Point"}
}