{
  "type": "Feature",
  "properties": {
    "gn:admin1_code":"28.0",
    "gn:admin2_code":"32.0",
    "gn:asciiname":"El Guaje",
    "gn:country_code":"MX",
    "gn:dem":72,
    "gn:feature_class":"P",
    "gn:feature_code":"PPL",
    "gn:name":"El Guaje",
    "gn:population":0,
    "gn:timezone":"America/Matamoros",
    "iso:country":"MX",
    "name:spa_x_preferred":[
        "El Guaje"
    ],
    "wof:name":"El Guaje",
    "wof:placetype":"locality"
},
  "geometry": {"coordinates":[-98.2512,25.62731],"type":"Point"}
}