{
  "type": "Feature",
  "properties": {
    "gn:admin1_code":"10",
    "gn:admin2_code":"12",
    "gn:asciiname":"Dos Hermanos (Santa Eloisa)",
    "gn:country_code":"MX",
    "gn:dem":1165,
    "gn:feature_class":"P",
    "gn:feature_code":"PPL",
    "gn:name":"Dos Hermanos (Santa Elo\u00edsa)",
    "gn:population":9,
    "gn:timezone":"America/Monterrey",
    "iso:country":"MX",
    "name:und_x_variant":[
        "Dos Hermanos (Santa Elo\u00edsa)"
    ],
    "wof:name":"Dos Hermanos (Santa Eloisa)",
    "wof:placetype":"locality",
    "wof:population":9
},
  "geometry": {"coordinates":[-103.72617,25.46056],"type":"Point"}
}