{
  "type": "Feature",
  "properties": {
    "gn:admin1_code":"26.0",
    "gn:admin2_code":"30.0",
    "gn:asciiname":"El Xochitl",
    "gn:country_code":"MX",
    "gn:dem":12,
    "gn:feature_class":"P",
    "gn:feature_code":"PPL",
    "gn:name":"El X\u00f3chitl",
    "gn:population":0,
    "gn:timezone":"America/Hermosillo",
    "iso:country":"MX",
    "name:spa_x_preferred":[
        "El X\u00f3chitl"
    ],
    "wof:name":"El Xochitl",
    "wof:placetype":"locality"
},
  "geometry": {"coordinates":[-111.32689000000001,28.35067],"type":"Point"}
}