{
  "type": "Feature",
  "properties": {
    "gn:admin1_code":"31",
    "gn:admin2_code":"104.0",
    "gn:asciiname":"Kixteka",
    "gn:country_code":"MX",
    "gn:dem":22,
    "gn:feature_class":"P",
    "gn:feature_code":"PPL",
    "gn:name":"Kixteka",
    "gn:population":0,
    "gn:timezone":"America/Merida",
    "iso:country":"MX",
    "name:spa_x_preferred":[
        "Kixteka"
    ],
    "wof:name":"Kixteka",
    "wof:placetype":"locality"
},
  "geometry": {"coordinates":[-88.84350999999999,20.31874],"type":"Point"}
}