{
  "type": "Feature",
  "properties": {
    "gn:admin1_code":"19",
    "gn:admin2_code":"16.0",
    "gn:asciiname":"La Nueva Gloria",
    "gn:cc2":"MX",
    "gn:country_code":"MX",
    "gn:dem":423,
    "gn:feature_class":"P",
    "gn:feature_code":"PPL",
    "gn:name":"La Nueva Gloria",
    "gn:population":0,
    "gn:timezone":"America/Monterrey",
    "iso:country":"MX",
    "name:und_x_variant":[
        "Nueva Gloria",
        "La Nueva Gloria"
    ],
    "wof:name":"La Nueva Gloria",
    "wof:placetype":"locality"
},
  "geometry": {"coordinates":[-99.88333,25.88333],"type":"Point"}
}