{
  "type": "Feature",
  "properties": {
    "gn:admin1_code":"30",
    "gn:admin2_code":"23.0",
    "gn:asciiname":"El Rio Bobos (El Filo)",
    "gn:country_code":"MX",
    "gn:dem":286,
    "gn:feature_class":"P",
    "gn:feature_code":"PPL",
    "gn:name":"El R\u00edo Bobos (El Filo)",
    "gn:population":69,
    "gn:timezone":"America/Mexico_City",
    "iso:country":"MX",
    "name:und_x_variant":[
        "El R\u00edo Bobos (El Filo)"
    ],
    "wof:name":"El Rio Bobos (El Filo)",
    "wof:placetype":"locality",
    "wof:population":69
},
  "geometry": {"coordinates":[-97.16361000000001,19.92694],"type":"Point"}
}