{
  "type": "Feature",
  "properties": {
    "gn:admin1_code":"19",
    "gn:admin2_code":"22.0",
    "gn:asciiname":"Las Blancas",
    "gn:country_code":"MX",
    "gn:dem":234,
    "gn:feature_class":"P",
    "gn:feature_code":"PPL",
    "gn:name":"Las Blancas",
    "gn:population":0,
    "gn:timezone":"America/Monterrey",
    "iso:country":"MX",
    "name:spa_x_preferred":[
        "Las Blancas"
    ],
    "wof:name":"Las Blancas",
    "wof:placetype":"locality"
},
  "geometry": {"coordinates":[-99.32799,25.2141],"type":"Point"}
}