{
  "type": "Feature",
  "properties": {
    "gn:admin1_code":"6",
    "gn:admin2_code":"27.0",
    "gn:asciiname":"Bajio del Cebollin",
    "gn:country_code":"MX",
    "gn:dem":2289,
    "gn:feature_class":"P",
    "gn:feature_code":"PPL",
    "gn:name":"Baj\u00edo del Ceboll\u00edn",
    "gn:population":0,
    "gn:timezone":"America/Chihuahua",
    "iso:country":"MX",
    "name:spa_x_preferred":[
        "Baj\u00edo del Ceboll\u00edn"
    ],
    "wof:name":"Bajio del Cebollin",
    "wof:placetype":"locality"
},
  "geometry": {"coordinates":[-107.03363,27.21517],"type":"Point"}
}