{
  "type": "Feature",
  "properties": {
    "gn:admin1_code":"30",
    "gn:admin2_code":"40.0",
    "gn:asciiname":"Dos Glorias",
    "gn:country_code":"MX",
    "gn:dem":89,
    "gn:feature_class":"P",
    "gn:feature_code":"PPL",
    "gn:name":"Dos Glorias",
    "gn:population":5,
    "gn:timezone":"America/Mexico_City",
    "iso:country":"MX",
    "wof:name":"Dos Glorias",
    "wof:placetype":"locality",
    "wof:population":5
},
  "geometry": {"coordinates":[-97.47194,20.47111],"type":"Point"}
}