{
  "type": "Feature",
  "properties": {
    "gn:admin1_code":"7",
    "gn:admin2_code":"36",
    "gn:asciiname":"La Colorada",
    "gn:country_code":"MX",
    "gn:dem":1163,
    "gn:feature_class":"P",
    "gn:feature_code":"PPL",
    "gn:name":"La Colorada",
    "gn:population":19,
    "gn:timezone":"America/Monterrey",
    "iso:country":"MX",
    "wof:name":"La Colorada",
    "wof:placetype":"locality",
    "wof:population":19
},
  "geometry": {"coordinates":[-103.21867,25.27833],"type":"Point"}
}