{
  "type": "Feature",
  "properties": {
    "gn:admin1_code":"14.0",
    "gn:asciiname":"Los Horcones",
    "gn:country_code":"MX",
    "gn:dem":1879,
    "gn:feature_class":"P",
    "gn:feature_code":"PPL",
    "gn:name":"Los Horcones",
    "gn:population":0,
    "gn:timezone":"America/Mexico_City",
    "iso:country":"MX",
    "name:spa_x_preferred":[
        "Los Horcones"
    ],
    "wof:name":"Los Horcones",
    "wof:placetype":"locality"
},
  "geometry": {"coordinates":[-102.11584999999999,20.80456],"type":"Point"}
}