{
  "type": "Feature",
  "properties": {
    "gn:admin1_code":"6.0",
    "gn:admin2_code":"11.0",
    "gn:asciiname":"Las Minas",
    "gn:country_code":"MX",
    "gn:dem":1459,
    "gn:feature_class":"P",
    "gn:feature_code":"PPL",
    "gn:name":"Las Minas",
    "gn:population":0,
    "gn:timezone":"America/Chihuahua",
    "iso:country":"MX",
    "name:ceb_x_preferred":[
        "Las Minas"
    ],
    "name:deu_x_preferred":[
        "Las Minas"
    ],
    "name:spa_x_preferred":[
        "Las Minas"
    ],
    "name:swe_x_preferred":[
        "Las Minas"
    ],
    "wof:name":"Las Minas",
    "wof:placetype":"locality"
},
  "geometry": {"coordinates":[-104.09453999999999,28.62068],"type":"Point"}
}