{
  "type": "Feature",
  "properties": {
    "gn:admin1_code":"5",
    "gn:admin2_code":"31",
    "gn:asciiname":"Nuevo Villaflores",
    "gn:country_code":"MX",
    "gn:dem":896,
    "gn:feature_class":"P",
    "gn:feature_code":"PPL",
    "gn:name":"Nuevo Villaflores",
    "gn:population":19,
    "gn:timezone":"America/Mexico_City",
    "iso:country":"MX",
    "wof:name":"Nuevo Villaflores",
    "wof:placetype":"locality",
    "wof:population":19
},
  "geometry": {"coordinates":[-91.79667000000001,17.04167],"type":"Point"}
}