{
  "type": "Feature",
  "properties": {
    "gn:admin1_code":"21",
    "gn:admin2_code":"38",
    "gn:asciiname":"San Jose Torija",
    "gn:country_code":"MX",
    "gn:dem":2071,
    "gn:feature_class":"P",
    "gn:feature_code":"PPL",
    "gn:name":"San Jos\u00e9 Torija",
    "gn:population":18,
    "gn:timezone":"America/Mexico_City",
    "iso:country":"MX",
    "name:und_x_variant":[
        "San Jos\u00e9 Torija"
    ],
    "wof:name":"San Jose Torija",
    "wof:placetype":"locality",
    "wof:population":18
},
  "geometry": {"coordinates":[-97.8544,18.91598],"type":"Point"}
}