{
  "type": "Feature",
  "properties": {
    "gn:admin1_code":"30",
    "gn:admin2_code":"51.0",
    "gn:asciiname":"El Vinazco",
    "gn:country_code":"MX",
    "gn:dem":128,
    "gn:feature_class":"P",
    "gn:feature_code":"PPL",
    "gn:name":"El Vi\u00f1azco",
    "gn:population":20,
    "gn:timezone":"America/Mexico_City",
    "iso:country":"MX",
    "wof:name":"El Vinazco",
    "wof:placetype":"locality",
    "wof:population":20
},
  "geometry": {"coordinates":[-97.68633,20.37696],"type":"Point"}
}