{
  "type": "Feature",
  "properties": {
    "gn:admin1_code":"14",
    "gn:admin2_code":"122",
    "gn:asciiname":"La Estancia",
    "gn:country_code":"MX",
    "gn:dem":1381,
    "gn:feature_class":"P",
    "gn:feature_code":"PPL",
    "gn:name":"La Estancia",
    "gn:population":10,
    "gn:timezone":"America/Mexico_City",
    "iso:country":"MX",
    "wof:name":"La Estancia",
    "wof:placetype":"locality",
    "wof:population":10
},
  "geometry": {"coordinates":[-103.71861,19.46889],"type":"Point"}
}