{
  "type": "Feature",
  "properties": {
    "gn:admin1_code":"21",
    "gn:admin2_code":"53.0",
    "gn:asciiname":"Llanetillo",
    "gn:country_code":"MX",
    "gn:dem":2375,
    "gn:feature_class":"P",
    "gn:feature_code":"PPL",
    "gn:name":"Llanetillo",
    "gn:population":275,
    "gn:timezone":"America/Mexico_City",
    "iso:country":"MX",
    "wof:name":"Llanetillo",
    "wof:placetype":"locality",
    "wof:population":275
},
  "geometry": {"coordinates":[-98.04416999999999,19.76944],"type":"Point"}
}