{
  "type": "Feature",
  "properties": {
    "gn:admin1_code":"1.0",
    "gn:admin2_code":"5.0",
    "gn:asciiname":"La Coloradita",
    "gn:country_code":"MX",
    "gn:dem":1949,
    "gn:feature_class":"P",
    "gn:feature_code":"PPL",
    "gn:name":"La Coloradita",
    "gn:population":0,
    "gn:timezone":"America/Mexico_City",
    "iso:country":"MX",
    "wof:name":"La Coloradita",
    "wof:placetype":"locality"
},
  "geometry": {"coordinates":[-102.39019999999999,21.93473],"type":"Point"}
}