{
  "type": "Feature",
  "properties": {
    "gn:admin1_code":"28",
    "gn:admin2_code":"19.0",
    "gn:asciiname":"El Aquichal",
    "gn:country_code":"MX",
    "gn:dem":231,
    "gn:feature_class":"P",
    "gn:feature_code":"PPL",
    "gn:name":"El Aquichal",
    "gn:population":0,
    "gn:timezone":"America/Monterrey",
    "iso:country":"MX",
    "name:und_x_variant":[
        "Aquichal",
        "El Aquichal"
    ],
    "wof:name":"El Aquichal",
    "wof:placetype":"locality"
},
  "geometry": {"coordinates":[-99.05191000000001,23.15446],"type":"Point"}
}