{
  "type": "Feature",
  "properties": {
    "gn:admin1_code":"28",
    "gn:admin2_code":"8.0",
    "gn:asciiname":"San Diego",
    "gn:country_code":"MX",
    "gn:dem":291,
    "gn:feature_class":"P",
    "gn:feature_code":"PPL",
    "gn:name":"San Diego",
    "gn:population":0,
    "gn:timezone":"America/Monterrey",
    "iso:country":"MX",
    "name:spa_x_preferred":[
        "San Diego"
    ],
    "wof:name":"San Diego",
    "wof:placetype":"locality"
},
  "geometry": {"coordinates":[-98.71749,23.2168],"type":"Point"}
}