{
  "type": "Feature",
  "properties": {
    "gn:admin1_code":"28",
    "gn:admin2_code":"6.0",
    "gn:asciiname":"Joya de San Francisco",
    "gn:country_code":"MX",
    "gn:dem":1805,
    "gn:feature_class":"P",
    "gn:feature_code":"PPL",
    "gn:name":"Joya de San Francisco",
    "gn:population":0,
    "gn:timezone":"America/Monterrey",
    "iso:country":"MX",
    "name:und_x_variant":[
        "Joya"
    ],
    "wof:name":"Joya de San Francisco",
    "wof:placetype":"locality"
},
  "geometry": {"coordinates":[-99.93635,23.31342],"type":"Point"}
}