{
  "type": "Feature",
  "properties": {
    "iso:country":"MX",
    "name:spa_x_preferred":[
        "Emiliano Zapata"
    ],
    "name:unk_x_variant":[
        "Emilano Zapata",
        "Emiliano Zapata"
    ],
    "qs:gn_adm0_cc":"MX",
    "qs:gn_fcode":"PPL",
    "qs:gn_local":3988086,
    "qs:gn_namadm1":"07",
    "qs:gn_name":"Emilano Zapata",
    "qs:local_max":498,
    "qs:local_sum":790,
    "qs:localhoods":6,
    "qs:name":"Emiliano Zapata",
    "qs:name_adm0":"M\u00e9xico",
    "qs:name_adm1":"Coahuila de Zaragoza",
    "qs:name_adm2":"Saltillo",
    "qs:name_local":"Saltillo",
    "qs:photo_max":17,
    "qs:photo_sum":20,
    "qs:placetype":"Suburb",
    "qs:quad_count":2,
    "qs:woe_adm0":23424900,
    "qs:woe_adm1":2346270,
    "qs:woe_adm2":12599915,
    "qs:woe_lau":0,
    "qs:woe_local":141272,
    "qs:woe_ver":"7.10.0",
    "wof:lang":[
        "spa"
    ],
    "wof:name":"Emiliano Zapata",
    "wof:placetype":"neighbourhood"
},
  "geometry": {"coordinates":[-100.918488,25.451458],"type":"Point"}
}