{
  "type": "Feature",
  "properties": {
    "gn:admin1_code":"6",
    "gn:admin2_code":"27.0",
    "gn:asciiname":"Boquirare",
    "gn:country_code":"MX",
    "gn:dem":2187,
    "gn:feature_class":"P",
    "gn:feature_code":"PPL",
    "gn:name":"Boqu\u00edrare",
    "gn:population":0,
    "gn:timezone":"America/Chihuahua",
    "iso:country":"MX",
    "name:spa_x_preferred":[
        "Boqu\u00edrare"
    ],
    "wof:name":"Boquirare",
    "wof:placetype":"locality"
},
  "geometry": {"coordinates":[-107.08036,27.32338],"type":"Point"}
}