{
  "type": "Feature",
  "properties": {
    "gn:admin1_code":"26.0",
    "gn:admin2_code":"42.0",
    "gn:asciiname":"Brecha Colosio",
    "gn:country_code":"MX",
    "gn:dem":41,
    "gn:feature_class":"P",
    "gn:feature_code":"PPL",
    "gn:name":"Brecha Colosio",
    "gn:population":0,
    "gn:timezone":"America/Hermosillo",
    "iso:country":"MX",
    "name:spa_x_preferred":[
        "Brecha Colosio"
    ],
    "wof:name":"Brecha Colosio",
    "wof:placetype":"locality"
},
  "geometry": {"coordinates":[-109.38800000000001,26.83898],"type":"Point"}
}