{
  "type": "Feature",
  "properties": {
    "gn:admin1_code":"11",
    "gn:admin2_code":"13.0",
    "gn:asciiname":"Puerto de la Oveja",
    "gn:country_code":"MX",
    "gn:dem":2146,
    "gn:feature_class":"P",
    "gn:feature_code":"PPL",
    "gn:name":"Puerto de la Oveja",
    "gn:population":70,
    "gn:timezone":"America/Mexico_City",
    "iso:country":"MX",
    "wof:name":"Puerto de la Oveja",
    "wof:placetype":"locality",
    "wof:population":70
},
  "geometry": {"coordinates":[-100.31,21.11556],"type":"Point"}
}