{
  "type": "Feature",
  "properties": {
    "gn:admin1_code":"15",
    "gn:admin2_code":"78.0",
    "gn:asciiname":"Las Fincas",
    "gn:country_code":"MX",
    "gn:dem":1514,
    "gn:feature_class":"P",
    "gn:feature_code":"PPL",
    "gn:name":"Las Fincas",
    "gn:population":668,
    "gn:timezone":"America/Mexico_City",
    "iso:country":"MX",
    "wof:name":"Las Fincas",
    "wof:placetype":"locality",
    "wof:population":668
},
  "geometry": {"coordinates":[-100.25766,19.1739],"type":"Point"}
}