{
  "type": "Feature",
  "properties": {
    "gn:admin1_code":"16",
    "gn:admin2_code":"97",
    "gn:asciiname":"Aguacates (El Aguacate)",
    "gn:country_code":"MX",
    "gn:dem":965,
    "gn:feature_class":"P",
    "gn:feature_code":"PPL",
    "gn:name":"Aguacates (El Aguacate)",
    "gn:population":17,
    "gn:timezone":"America/Mexico_City",
    "iso:country":"MX",
    "wof:name":"Aguacates (El Aguacate)",
    "wof:placetype":"locality",
    "wof:population":17
},
  "geometry": {"coordinates":[-101.50306,18.78583],"type":"Point"}
}