{
  "type": "Feature",
  "properties": {
    "gn:admin1_code":"15",
    "gn:admin2_code":"51.0",
    "gn:asciiname":"Colonia Ojo de Agua",
    "gn:country_code":"MX",
    "gn:dem":2674,
    "gn:feature_class":"P",
    "gn:feature_code":"PPL",
    "gn:name":"Colonia Ojo de Agua",
    "gn:population":403,
    "gn:timezone":"America/Mexico_City",
    "iso:country":"MX",
    "wof:name":"Colonia Ojo de Agua",
    "wof:placetype":"locality",
    "wof:population":403
},
  "geometry": {"coordinates":[-99.45582,19.31002],"type":"Point"}
}