{
  "type": "Feature",
  "properties": {
    "gn:admin1_code":"6",
    "gn:admin2_code":"8",
    "gn:asciiname":"Ranchito de Osorio",
    "gn:country_code":"MX",
    "gn:dem":572,
    "gn:feature_class":"P",
    "gn:feature_code":"PPL",
    "gn:name":"Ranchito de Osorio",
    "gn:population":17,
    "gn:timezone":"America/Chihuahua",
    "iso:country":"MX",
    "wof:name":"Ranchito de Osorio",
    "wof:placetype":"locality",
    "wof:population":17
},
  "geometry": {"coordinates":[-107.85462,26.9266],"type":"Point"}
}