{
  "type": "Feature",
  "properties": {
    "gn:admin1_code":"20",
    "gn:admin2_code":"207.0",
    "gn:asciiname":"El Pipila",
    "gn:country_code":"MX",
    "gn:dem":115,
    "gn:feature_class":"P",
    "gn:feature_code":"PPL",
    "gn:name":"El P\u00edpila",
    "gn:population":255,
    "gn:timezone":"America/Mexico_City",
    "iso:country":"MX",
    "name:und_x_variant":[
        "El P\u00edpila"
    ],
    "wof:name":"El Pipila",
    "wof:placetype":"locality",
    "wof:population":255
},
  "geometry": {"coordinates":[-95.24611,17.28194],"type":"Point"}
}