{
  "type": "Feature",
  "properties": {
    "gn:admin1_code":"6",
    "gn:admin2_code":"19.0",
    "gn:asciiname":"Rancho Enmedio  (Estacion Mueller)",
    "gn:country_code":"MX",
    "gn:dem":1347,
    "gn:feature_class":"P",
    "gn:feature_code":"PPL",
    "gn:name":"Rancho Enmedio  (Estaci\u00f3n M\u00fcller)",
    "gn:population":206,
    "gn:timezone":"America/Chihuahua",
    "iso:country":"MX",
    "name:und_x_variant":[
        "Rancho Enmedio (Estaci\u00f3n M\u00fcller)"
    ],
    "wof:name":"Rancho Enmedio (Estacion Mueller)",
    "wof:placetype":"locality",
    "wof:population":206
},
  "geometry": {"coordinates":[-105.97750000000001,28.70583],"type":"Point"}
}