{
  "type": "Feature",
  "properties": {
    "gn:admin1_code":"7.0",
    "gn:asciiname":"Chagusa",
    "gn:country_code":"MX",
    "gn:dem":606,
    "gn:feature_class":"P",
    "gn:feature_code":"PPL",
    "gn:name":"Chagusa",
    "gn:population":0,
    "gn:timezone":"America/Monterrey",
    "iso:country":"MX",
    "name:spa_x_preferred":[
        "Chagusa"
    ],
    "wof:name":"Chagusa",
    "wof:placetype":"locality"
},
  "geometry": {"coordinates":[-101.29342,26.93215],"type":"Point"}
}