{
  "type": "Feature",
  "properties": {
    "gn:admin1_code":"6",
    "gn:admin2_code":"56.0",
    "gn:asciiname":"La Sardina",
    "gn:country_code":"MX",
    "gn:dem":1619,
    "gn:feature_class":"P",
    "gn:feature_code":"PPL",
    "gn:name":"La Sardina",
    "gn:population":0,
    "gn:timezone":"America/Chihuahua",
    "iso:country":"MX",
    "name:spa_x_preferred":[
        "La Sardina"
    ],
    "name:und_x_variant":[
        "Sardinas",
        "Sardina"
    ],
    "wof:name":"La Sardina",
    "wof:placetype":"locality"
},
  "geometry": {"coordinates":[-106.42628000000001,27.35088],"type":"Point"}
}