{
  "type": "Feature",
  "properties": {
    "gn:admin1_code":"26",
    "gn:admin2_code":"30",
    "gn:asciiname":"El Pocito (Orebalma)",
    "gn:country_code":"MX",
    "gn:dem":43,
    "gn:feature_class":"P",
    "gn:feature_code":"PPL",
    "gn:name":"El Pocito (Orebalma)",
    "gn:population":42,
    "gn:timezone":"America/Hermosillo",
    "iso:country":"MX",
    "wof:name":"El Pocito (Orebalma)",
    "wof:placetype":"locality",
    "wof:population":42
},
  "geometry": {"coordinates":[-111.60167,28.83889000000001],"type":"Point"}
}