{
  "type": "Feature",
  "properties": {
    "gn:admin1_code":"6",
    "gn:admin2_code":"21.0",
    "gn:asciiname":"Los Herrera",
    "gn:country_code":"MX",
    "gn:dem":1188,
    "gn:feature_class":"P",
    "gn:feature_code":"PPL",
    "gn:name":"Los Herrera",
    "gn:population":4,
    "gn:timezone":"America/Chihuahua",
    "iso:country":"MX",
    "wof:name":"Los Herrera",
    "wof:placetype":"locality",
    "wof:population":4
},
  "geometry": {"coordinates":[-105.42102,28.24298],"type":"Point"}
}