{
  "type": "Feature",
  "properties": {
    "gn:admin1_code":"23",
    "gn:admin2_code":"3",
    "gn:asciiname":"Escenica",
    "gn:country_code":"MX",
    "gn:dem":4,
    "gn:feature_class":"P",
    "gn:feature_code":"PPL",
    "gn:name":"Esc\u00e9nica",
    "gn:population":19,
    "gn:timezone":"America/Cancun",
    "iso:country":"MX",
    "name:und_x_variant":[
        "Esc\u00e9nica"
    ],
    "wof:name":"Escenica",
    "wof:placetype":"locality",
    "wof:population":19
},
  "geometry": {"coordinates":[-86.80249000000001,21.22621],"type":"Point"}
}