{
  "type": "Feature",
  "properties": {
    "gn:admin1_code":"4",
    "gn:admin2_code":"3.0",
    "gn:asciiname":"El Jobo",
    "gn:country_code":"MX",
    "gn:dem":5,
    "gn:feature_class":"P",
    "gn:feature_code":"PPL",
    "gn:name":"El Jobo",
    "gn:population":7,
    "gn:timezone":"America/Merida",
    "iso:country":"MX",
    "name:spa_x_preferred":[
        "El Jobo"
    ],
    "wof:name":"El Jobo",
    "wof:placetype":"locality",
    "wof:population":7
},
  "geometry": {"coordinates":[-90.99977,18.84412],"type":"Point"}
}