{
  "type": "Feature",
  "properties": {
    "gn:admin1_code":"19.0",
    "gn:admin2_code":"37.0",
    "gn:asciiname":"Laguna",
    "gn:country_code":"MX",
    "gn:dem":945,
    "gn:feature_class":"P",
    "gn:feature_code":"PPL",
    "gn:name":"Laguna",
    "gn:population":0,
    "gn:timezone":"America/Monterrey",
    "iso:country":"MX",
    "wof:name":"Laguna",
    "wof:placetype":"locality"
},
  "geometry": {"coordinates":[-100.98333,26.21667],"type":"Point"}
}