{
  "type": "Feature",
  "properties": {
    "gn:admin1_code":"19.0",
    "gn:admin2_code":"37.0",
    "gn:asciiname":"Laguna",
    "gn:country_code":"MX",
    "gn:dem":945,
    "gn:feature_class":"P",
    "gn:feature_code":"PPL",
    "gn:name":"Laguna",
    "gn:population":0,
    "gn:timezone":"America/Monterrey",
    "iso:country":"MX",
    "name:ben_x_preferred":[
        "\u09b2\u09be\u0997\u09c1\u09a8\u09be"
    ],
    "name:cat_x_preferred":[
        "Laguna"
    ],
    "name:ceb_x_preferred":[
        "Laguna"
    ],
    "name:ces_x_preferred":[
        "Laguna"
    ],
    "name:deu_x_preferred":[
        "Laguna"
    ],
    "name:ell_x_preferred":[
        "\u039b\u03b1\u03b3\u03ba\u03bf\u03cd\u03bd\u03b1"
    ],
    "name:fra_x_preferred":[
        "Laguna"
    ],
    "name:heb_x_preferred":[
        "\u05dc\u05d2\u05d5\u05e0\u05d4"
    ],
    "name:hin_x_preferred":[
        "\u0932\u0917\u0942\u0928\u093e"
    ],
    "name:hun_x_preferred":[
        "Laguna"
    ],
    "name:ind_x_preferred":[
        "Laguna"
    ],
    "name:ita_x_preferred":[
        "Laguna"
    ],
    "name:jpn_x_preferred":[
        "\u30e9\u30b0\u30ca"
    ],
    "name:kat_x_preferred":[
        "\u10da\u10d0\u10d2\u10e3\u10dc\u10d0"
    ],
    "name:kor_x_preferred":[
        "\ub77c\uad6c\ub098"
    ],
    "name:nds_x_preferred":[
        "Laguna"
    ],
    "name:nld_x_preferred":[
        "Laguna"
    ],
    "name:nor_x_preferred":[
        "Laguna"
    ],
    "name:pol_x_preferred":[
        "Laguna"
    ],
    "name:por_x_preferred":[
        "Laguna"
    ],
    "name:ron_x_preferred":[
        "Laguna"
    ],
    "name:rus_x_preferred":[
        "\u041b\u0430\u0433\u0443\u043d\u0430"
    ],
    "name:sco_x_preferred":[
        "Laguna"
    ],
    "name:slk_x_preferred":[
        "Lag\u00fana"
    ],
    "name:slv_x_preferred":[
        "Laguna"
    ],
    "name:spa_x_preferred":[
        "Laguna"
    ],
    "name:swe_x_preferred":[
        "Laguna"
    ],
    "name:tgl_x_preferred":[
        "Laguna"
    ],
    "name:tur_x_preferred":[
        "Laguna"
    ],
    "name:urd_x_preferred":[
        "\u0644\u06af\u0648\u0646\u0627"
    ],
    "name:vol_x_preferred":[
        "Laguna"
    ],
    "name:zho_cn_x_preferred":[
        "\u62c9\u53e4\u7eb3"
    ],
    "name:zho_tw_x_preferred":[
        "\u62c9\u53e4\u7d0d"
    ],
    "wof:name":"Laguna",
    "wof:placetype":"locality"
},
  "geometry": {"coordinates":[-100.98333,26.21667],"type":"Point"}
}