{
  "type": "Feature",
  "properties": {
    "gn:admin1_code":"4",
    "gn:admin2_code":"6.0",
    "gn:asciiname":"Campo Menonita Numero Uno",
    "gn:country_code":"MX",
    "gn:dem":75,
    "gn:feature_class":"P",
    "gn:feature_code":"PPL",
    "gn:name":"Campo Menonita N\u00famero Uno",
    "gn:population":0,
    "gn:timezone":"America/Merida",
    "iso:country":"MX",
    "name:spa_x_preferred":[
        "Campo Menonita N\u00famero Uno"
    ],
    "wof:name":"Campo Menonita Numero Uno",
    "wof:placetype":"locality"
},
  "geometry": {"coordinates":[-89.69656999999999,19.69095],"type":"Point"}
}