{
  "type": "Feature",
  "properties": {
    "gn:admin1_code":"14.0",
    "gn:admin2_code":"109.0",
    "gn:asciiname":"Mesillas de Arriba",
    "gn:country_code":"MX",
    "gn:dem":1899,
    "gn:feature_class":"P",
    "gn:feature_code":"PPL",
    "gn:name":"Mesillas de Arriba",
    "gn:population":0,
    "gn:timezone":"America/Mexico_City",
    "iso:country":"MX",
    "name:spa_x_preferred":[
        "Mesillas de Arriba"
    ],
    "wof:name":"Mesillas de Arriba",
    "wof:placetype":"locality"
},
  "geometry": {"coordinates":[-101.95368999999999,21.0594],"type":"Point"}
}