{
  "type": "Feature",
  "properties": {
    "gn:admin1_code":"28",
    "gn:admin2_code":"23.0",
    "gn:asciiname":"Pedro J. Mendez",
    "gn:country_code":"MX",
    "gn:dem":67,
    "gn:feature_class":"P",
    "gn:feature_code":"PPL",
    "gn:name":"Pedro J. M\u00e9ndez",
    "gn:population":0,
    "gn:timezone":"America/Monterrey",
    "iso:country":"MX",
    "wof:name":"Pedro J. Mendez",
    "wof:placetype":"locality"
},
  "geometry": {"coordinates":[-98.2124,25.33891],"type":"Point"}
}