{
  "type": "Feature",
  "properties": {
    "gn:admin1_code":"6",
    "gn:admin2_code":"65",
    "gn:asciiname":"Salitrera",
    "gn:country_code":"MX",
    "gn:dem":311,
    "gn:feature_class":"P",
    "gn:feature_code":"PPL",
    "gn:name":"Salitrera",
    "gn:population":13,
    "gn:timezone":"America/Chihuahua",
    "iso:country":"MX",
    "wof:name":"Salitrera",
    "wof:placetype":"locality",
    "wof:population":13
},
  "geometry": {"coordinates":[-107.97378999999999,26.95465],"type":"Point"}
}