{
  "type": "Feature",
  "properties": {
    "gn:admin1_code":"21",
    "gn:admin2_code":"89",
    "gn:asciiname":"Patango",
    "gn:country_code":"MX",
    "gn:dem":580,
    "gn:feature_class":"P",
    "gn:feature_code":"PPL",
    "gn:name":"Patango",
    "gn:population":47,
    "gn:timezone":"America/Mexico_City",
    "iso:country":"MX",
    "wof:name":"Patango",
    "wof:placetype":"locality",
    "wof:population":47
},
  "geometry": {"coordinates":[-97.68628,20.16164],"type":"Point"}
}