{
  "type": "Feature",
  "properties": {
    "gn:admin1_code":"21.0",
    "gn:admin2_code":"194.0",
    "gn:asciiname":"Casa Blanca",
    "gn:country_code":"MX",
    "gn:dem":313,
    "gn:feature_class":"P",
    "gn:feature_code":"PPL",
    "gn:name":"Casa Blanca",
    "gn:population":7,
    "gn:timezone":"America/Mexico_City",
    "iso:country":"MX",
    "name:spa_x_preferred":[
        "Casa Blanca"
    ],
    "wof:name":"Casa Blanca",
    "wof:placetype":"locality",
    "wof:population":7
},
  "geometry": {"coordinates":[-97.67358,20.48086],"type":"Point"}
}