{
  "type": "Feature",
  "properties": {
    "gn:admin1_code":"12.0",
    "gn:admin2_code":"7.0",
    "gn:asciiname":"Los Ladrillos",
    "gn:country_code":"MX",
    "gn:dem":814,
    "gn:feature_class":"P",
    "gn:feature_code":"PPL",
    "gn:name":"Los Ladrillos",
    "gn:population":0,
    "gn:timezone":"America/Mexico_City",
    "iso:country":"MX",
    "name:spa_x_preferred":[
        "Los Ladrillos"
    ],
    "wof:name":"Los Ladrillos",
    "wof:placetype":"locality"
},
  "geometry": {"coordinates":[-100.22821999999999,18.34462000000001],"type":"Point"}
}