{
  "type": "Feature",
  "properties": {
    "gn:admin1_code":"10",
    "gn:admin2_code":"26",
    "gn:asciiname":"Las Gueeritas",
    "gn:country_code":"MX",
    "gn:dem":2476,
    "gn:feature_class":"P",
    "gn:feature_code":"PPL",
    "gn:name":"Las G\u00fceritas",
    "gn:population":13,
    "gn:timezone":"America/Monterrey",
    "iso:country":"MX",
    "name:und_x_variant":[
        "Las G\u00fceritas"
    ],
    "wof:name":"Las Gueeritas",
    "wof:placetype":"locality",
    "wof:population":13
},
  "geometry": {"coordinates":[-105.50328,24.3558],"type":"Point"}
}