{
  "type": "Feature",
  "properties": {
    "gn:admin1_code":"11",
    "gn:asciiname":"El Charco",
    "gn:country_code":"MX",
    "gn:dem":1742,
    "gn:feature_class":"P",
    "gn:feature_code":"PPL",
    "gn:name":"El Charco",
    "gn:population":0,
    "gn:timezone":"America/Mexico_City",
    "iso:country":"MX",
    "name:spa_x_preferred":[
        "El Charco"
    ],
    "wof:name":"El Charco",
    "wof:placetype":"locality"
},
  "geometry": {"coordinates":[-99.71417,21.29085],"type":"Point"}
}