{
  "type": "Feature",
  "properties": {
    "gn:admin1_code":"30",
    "gn:admin2_code":"145.0",
    "gn:asciiname":"Chalcomulco",
    "gn:country_code":"MX",
    "gn:dem":58,
    "gn:feature_class":"P",
    "gn:feature_code":"PPL",
    "gn:name":"Chalcomulco",
    "gn:population":0,
    "gn:timezone":"America/Mexico_City",
    "iso:country":"MX",
    "name:spa_x_preferred":[
        "Chalcomulco"
    ],
    "wof:name":"Chalcomulco",
    "wof:placetype":"locality"
},
  "geometry": {"coordinates":[-94.78257000000001,18.01889],"type":"Point"}
}