{
  "type": "Feature",
  "properties": {
    "gn:admin1_code":"11.0",
    "gn:asciiname":"Las Penas",
    "gn:country_code":"MX",
    "gn:dem":1755,
    "gn:feature_class":"P",
    "gn:feature_code":"PPL",
    "gn:name":"Las Pe\u00f1as",
    "gn:population":0,
    "gn:timezone":"America/Mexico_City",
    "iso:country":"MX",
    "name:spa_x_preferred":[
        "Las Pe\u00f1as"
    ],
    "wof:name":"Las Penas",
    "wof:placetype":"locality"
},
  "geometry": {"coordinates":[-101.98204,20.40739],"type":"Point"}
}