{
  "type": "Feature",
  "properties": {
    "gn:admin1_code":"12",
    "gn:admin2_code":"55.0",
    "gn:asciiname":"San Pedro Chichila",
    "gn:country_code":"MX",
    "gn:dem":1772,
    "gn:feature_class":"P",
    "gn:feature_code":"PPL",
    "gn:name":"San Pedro Chichila",
    "gn:population":224,
    "gn:timezone":"America/Mexico_City",
    "iso:country":"MX",
    "wof:name":"San Pedro Chichila",
    "wof:placetype":"locality",
    "wof:population":224
},
  "geometry": {"coordinates":[-99.67222,18.54],"type":"Point"}
}