{
  "type": "Feature",
  "properties": {
    "gn:admin1_code":"4.0",
    "gn:asciiname":"Siete Lenguas",
    "gn:country_code":"MX",
    "gn:dem":66,
    "gn:feature_class":"P",
    "gn:feature_code":"PPL",
    "gn:name":"Siete Lenguas",
    "gn:population":0,
    "gn:timezone":"America/Merida",
    "iso:country":"MX",
    "name:spa_x_preferred":[
        "Siete Lenguas"
    ],
    "wof:name":"Siete Lenguas",
    "wof:placetype":"locality"
},
  "geometry": {"coordinates":[-90.41271999999999,19.09465],"type":"Point"}
}