{
  "type": "Feature",
  "properties": {
    "gn:admin1_code":"6",
    "gn:admin2_code":"37.0",
    "gn:asciiname":"San Francisco (Tres Jacales)",
    "gn:country_code":"MX",
    "gn:dem":1102,
    "gn:feature_class":"P",
    "gn:feature_code":"PPL",
    "gn:name":"San Francisco (Tres Jacales)",
    "gn:population":236,
    "gn:timezone":"America/Ojinaga",
    "iso:country":"MX",
    "wof:name":"San Francisco (Tres Jacales)",
    "wof:placetype":"locality",
    "wof:population":236
},
  "geometry": {"coordinates":[-106.22360999999999,31.47361],"type":"Point"}
}