{
  "type": "Feature",
  "properties": {
    "gn:admin1_code":"13",
    "gn:admin2_code":"15.0",
    "gn:asciiname":"San Miguel Tlazintla",
    "gn:country_code":"MX",
    "gn:dem":2126,
    "gn:feature_class":"P",
    "gn:feature_code":"PPL",
    "gn:name":"San Miguel Tlazintla",
    "gn:population":0,
    "gn:timezone":"America/Mexico_City",
    "iso:country":"MX",
    "name:spa_x_preferred":[
        "San Miguel Tlazintla"
    ],
    "name:spa_x_variant":[
        "San Miguel"
    ],
    "wof:name":"San Miguel Tlazintla",
    "wof:placetype":"locality"
},
  "geometry": {"coordinates":[-99.09407,20.63639],"type":"Point"}
}