{
  "type": "Feature",
  "properties": {
    "gn:admin1_code":"6",
    "gn:admin2_code":"46.0",
    "gn:asciiname":"Resuchi",
    "gn:country_code":"MX",
    "gn:dem":929,
    "gn:feature_class":"P",
    "gn:feature_code":"PPL",
    "gn:name":"Resuchi",
    "gn:population":4,
    "gn:timezone":"America/Chihuahua",
    "iso:country":"MX",
    "wof:name":"Resuchi",
    "wof:placetype":"locality",
    "wof:population":4
},
  "geometry": {"coordinates":[-107.46127,26.70522],"type":"Point"}
}