{
  "type": "Feature",
  "properties": {
    "gn:admin1_code":"20",
    "gn:admin2_code":"95.0",
    "gn:asciiname":"La Venta",
    "gn:country_code":"MX",
    "gn:dem":2355,
    "gn:feature_class":"P",
    "gn:feature_code":"PPL",
    "gn:name":"La Venta",
    "gn:population":468,
    "gn:timezone":"America/Mexico_City",
    "iso:country":"MX",
    "wof:name":"La Venta",
    "wof:placetype":"locality",
    "wof:population":468
},
  "geometry": {"coordinates":[-96.51975,16.19528],"type":"Point"}
}