{
  "type": "Feature",
  "properties": {
    "gn:admin1_code":"10",
    "gn:admin2_code":"7",
    "gn:asciiname":"Las Cuatitas",
    "gn:country_code":"MX",
    "gn:dem":1118,
    "gn:feature_class":"P",
    "gn:feature_code":"PPL",
    "gn:name":"Las Cuatitas",
    "gn:population":15,
    "gn:timezone":"America/Monterrey",
    "iso:country":"MX",
    "wof:name":"Las Cuatitas",
    "wof:placetype":"locality",
    "wof:population":15
},
  "geometry": {"coordinates":[-103.44535,25.69639],"type":"Point"}
}