{
  "type": "Feature",
  "properties": {
    "gn:admin1_code":"13",
    "gn:admin2_code":"44",
    "gn:asciiname":"La Lechuga",
    "gn:country_code":"MX",
    "gn:dem":2376,
    "gn:feature_class":"P",
    "gn:feature_code":"PPL",
    "gn:name":"La Lechuga",
    "gn:population":24,
    "gn:timezone":"America/Mexico_City",
    "iso:country":"MX",
    "name:deu_x_preferred":[
        "La Lechuga"
    ],
    "wof:name":"La Lechuga",
    "wof:placetype":"locality",
    "wof:population":24
},
  "geometry": {"coordinates":[-99.63374,20.22485],"type":"Point"}
}