{
  "type": "Feature",
  "properties": {
    "gn:admin1_code":"32",
    "gn:admin2_code":"18",
    "gn:asciiname":"La Guayaba",
    "gn:country_code":"MX",
    "gn:dem":1462,
    "gn:feature_class":"P",
    "gn:feature_code":"PPL",
    "gn:name":"La Guayaba",
    "gn:population":12,
    "gn:timezone":"America/Mexico_City",
    "iso:country":"MX",
    "wof:name":"La Guayaba",
    "wof:placetype":"locality",
    "wof:population":12
},
  "geometry": {"coordinates":[-102.88028,21.73139],"type":"Point"}
}