{
  "type": "Feature",
  "properties": {
    "gn:admin1_code":"5",
    "gn:admin2_code":"97.0",
    "gn:asciiname":"San Andres Buenavista",
    "gn:country_code":"MX",
    "gn:dem":9,
    "gn:feature_class":"P",
    "gn:feature_code":"PPL",
    "gn:name":"San Andr\u00e9s Buenavista",
    "gn:population":0,
    "gn:timezone":"America/Mexico_City",
    "iso:country":"MX",
    "name:spa_x_preferred":[
        "San Andr\u00e9s Buenavista"
    ],
    "name:spa_x_variant":[
        "Buenavista"
    ],
    "wof:name":"San Andres Buenavista",
    "wof:placetype":"locality"
},
  "geometry": {"coordinates":[-93.57239,15.86499],"type":"Point"}
}