{
  "type": "Feature",
  "properties": {
    "gn:admin1_code":"12",
    "gn:admin2_code":"27",
    "gn:asciiname":"Las Escobitas",
    "gn:country_code":"MX",
    "gn:dem":295,
    "gn:feature_class":"P",
    "gn:feature_code":"PPL",
    "gn:name":"Las Escobitas",
    "gn:population":31,
    "gn:timezone":"America/Mexico_City",
    "iso:country":"MX",
    "wof:name":"Las Escobitas",
    "wof:placetype":"locality",
    "wof:population":31
},
  "geometry": {"coordinates":[-100.58668,18.47866],"type":"Point"}
}