{
  "type": "Feature",
  "properties": {
    "gn:admin1_code":"6",
    "gn:admin2_code":"41.0",
    "gn:asciiname":"Villeachic",
    "gn:country_code":"MX",
    "gn:dem":2299,
    "gn:feature_class":"P",
    "gn:feature_code":"PPL",
    "gn:name":"Villeachic",
    "gn:population":0,
    "gn:timezone":"America/Chihuahua",
    "iso:country":"MX",
    "name:und_x_variant":[
        "Billeachic",
        "Villeachic"
    ],
    "wof:name":"Villeachic",
    "wof:placetype":"locality"
},
  "geometry": {"coordinates":[-107.86632,27.91182],"type":"Point"}
}