{
  "type": "Feature",
  "properties": {
    "gn:admin1_code":"25",
    "gn:admin2_code":"17.0",
    "gn:asciiname":"Batayaqui",
    "gn:country_code":"MX",
    "gn:dem":851,
    "gn:feature_class":"P",
    "gn:feature_code":"PPL",
    "gn:name":"Batayaqui",
    "gn:population":0,
    "gn:timezone":"America/Mazatlan",
    "iso:country":"MX",
    "name:spa_x_preferred":[
        "Batayaqui"
    ],
    "wof:name":"Batayaqui",
    "wof:placetype":"locality"
},
  "geometry": {"coordinates":[-108.20549,26.3635],"type":"Point"}
}