{
  "type": "Feature",
  "properties": {
    "gn:admin1_code":"5",
    "gn:admin2_code":"82",
    "gn:asciiname":"San AntonioTanial",
    "gn:country_code":"MX",
    "gn:dem":811,
    "gn:feature_class":"P",
    "gn:feature_code":"PPL",
    "gn:name":"San AntonioTanial",
    "gn:population":24,
    "gn:timezone":"America/Mexico_City",
    "iso:country":"MX",
    "wof:name":"San AntonioTanial",
    "wof:placetype":"locality",
    "wof:population":24
},
  "geometry": {"coordinates":[-92.34278,17.00611],"type":"Point"}
}