{
  "type": "Feature",
  "properties": {
    "gn:admin1_code":"4.0",
    "gn:asciiname":"San Jose Uno",
    "gn:country_code":"MX",
    "gn:dem":-4,
    "gn:feature_class":"P",
    "gn:feature_code":"PPL",
    "gn:name":"San Jos\u00e9 Uno",
    "gn:population":0,
    "gn:timezone":"America/Merida",
    "iso:country":"MX",
    "name:spa_x_preferred":[
        "San Jos\u00e9 Uno"
    ],
    "wof:name":"San Jose Uno",
    "wof:placetype":"locality"
},
  "geometry": {"coordinates":[-91.12307,19.0035],"type":"Point"}
}