{
  "type": "Feature",
  "properties": {
    "gn:admin1_code":"13",
    "gn:admin2_code":"29.0",
    "gn:asciiname":"El Cajon",
    "gn:country_code":"MX",
    "gn:dem":2107,
    "gn:feature_class":"P",
    "gn:feature_code":"PPL",
    "gn:name":"El Caj\u00f3n",
    "gn:population":0,
    "gn:timezone":"America/Mexico_City",
    "iso:country":"MX",
    "name:und_x_variant":[
        "Caj\u00f3n",
        "El Caj\u00f3n"
    ],
    "wof:name":"El Cajon",
    "wof:placetype":"locality"
},
  "geometry": {"coordinates":[-99.62666,20.38688],"type":"Point"}
}