{
  "type": "Feature",
  "properties": {
    "gn:admin1_code":"16.0",
    "gn:admin2_code":"89.0",
    "gn:asciiname":"El Camichin",
    "gn:country_code":"MX",
    "gn:dem":520,
    "gn:feature_class":"P",
    "gn:feature_code":"PPL",
    "gn:name":"El Camich\u00edn",
    "gn:population":0,
    "gn:timezone":"America/Mexico_City",
    "iso:country":"MX",
    "name:spa_x_preferred":[
        "El Camich\u00edn"
    ],
    "wof:name":"El Camichin",
    "wof:placetype":"locality"
},
  "geometry": {"coordinates":[-102.97476,19.14581],"type":"Point"}
}