{
  "type": "Feature",
  "properties": {
    "gn:admin1_code":"32",
    "gn:admin2_code":"3.0",
    "gn:asciiname":"Ojo de Agua de Bugarin (Ojo de Agua)",
    "gn:country_code":"MX",
    "gn:dem":2171,
    "gn:feature_class":"P",
    "gn:feature_code":"PPL",
    "gn:name":"Ojo de Agua de Bugar\u00edn (Ojo de Agua)",
    "gn:population":9,
    "gn:timezone":"America/Mexico_City",
    "iso:country":"MX",
    "name:und_x_variant":[
        "Ojo de Agua de Bugar\u00edn (Ojo de Agua)"
    ],
    "wof:name":"Ojo de Agua de Bugarin (Ojo de Agua)",
    "wof:placetype":"locality",
    "wof:population":9
},
  "geometry": {"coordinates":[-103.48917,21.73806],"type":"Point"}
}