{
  "type": "Feature",
  "properties": {
    "gn:admin1_code":"14",
    "gn:admin2_code":"19.0",
    "gn:asciiname":"Estaflate",
    "gn:country_code":"MX",
    "gn:dem":1598,
    "gn:feature_class":"P",
    "gn:feature_code":"PPL",
    "gn:name":"Estaflate",
    "gn:population":0,
    "gn:timezone":"America/Mexico_City",
    "iso:country":"MX",
    "name:spa_x_preferred":[
        "Estaflate"
    ],
    "wof:name":"Estaflate",
    "wof:placetype":"locality"
},
  "geometry": {"coordinates":[-103.93662,21.83588],"type":"Point"}
}