{
  "type": "Feature",
  "properties": {
    "gn:admin1_code":"5",
    "gn:admin2_code":"77",
    "gn:asciiname":"Lindavista y Santa Monica",
    "gn:country_code":"MX",
    "gn:dem":135,
    "gn:feature_class":"P",
    "gn:feature_code":"PPL",
    "gn:name":"Lindavista y Santa M\u00f3nica",
    "gn:population":12,
    "gn:timezone":"America/Mexico_City",
    "iso:country":"MX",
    "name:und_x_variant":[
        "Lindavista y Santa M\u00f3nica"
    ],
    "wof:name":"Lindavista y Santa Monica",
    "wof:placetype":"locality",
    "wof:population":12
},
  "geometry": {"coordinates":[-92.01139000000001,17.24306],"type":"Point"}
}