{
  "type": "Feature",
  "properties": {
    "gn:admin1_code":"30",
    "gn:admin2_code":"123.0",
    "gn:asciiname":"El Higueron (Dique Rosario)",
    "gn:country_code":"MX",
    "gn:dem":19,
    "gn:feature_class":"P",
    "gn:feature_code":"PPL",
    "gn:name":"El Higuer\u00f3n (Dique Rosario)",
    "gn:population":8,
    "gn:timezone":"America/Mexico_City",
    "iso:country":"MX",
    "name:und_x_variant":[
        "El Higuer\u00f3n (Dique Rosario)"
    ],
    "wof:name":"El Higueron (Dique Rosario)",
    "wof:placetype":"locality",
    "wof:population":8
},
  "geometry": {"coordinates":[-98.16139,21.88167],"type":"Point"}
}