{
  "type": "Feature",
  "properties": {
    "gn:admin1_code":"26",
    "gn:admin2_code":"32.0",
    "gn:asciiname":"La Huerta",
    "gn:country_code":"MX",
    "gn:dem":1233,
    "gn:feature_class":"P",
    "gn:feature_code":"PPL",
    "gn:name":"La Huerta",
    "gn:population":0,
    "gn:timezone":"America/Hermosillo",
    "iso:country":"MX",
    "name:ceb_x_preferred":[
        "La Huerta"
    ],
    "name:spa_x_preferred":[
        "La Huerta"
    ],
    "name:swe_x_preferred":[
        "La Huerta"
    ],
    "wof:name":"La Huerta",
    "wof:placetype":"locality"
},
  "geometry": {"coordinates":[-109.4927,29.96545],"type":"Point"}
}