{
  "type": "Feature",
  "properties": {
    "gn:admin1_code":"26.0",
    "gn:admin2_code":"26.0",
    "gn:asciiname":"Huitchaca",
    "gn:country_code":"MX",
    "gn:dem":18,
    "gn:feature_class":"P",
    "gn:feature_code":"PPL",
    "gn:name":"Huitchaca",
    "gn:population":624,
    "gn:timezone":"America/Hermosillo",
    "iso:country":"MX",
    "name:spa_x_preferred":[
        "Huitchaca"
    ],
    "name:und_x_variant":[
        "Huichaca"
    ],
    "wof:name":"Huitchaca",
    "wof:placetype":"locality",
    "wof:population":624
},
  "geometry": {"coordinates":[-109.69298000000001,26.88098],"type":"Point"}
}