{
  "type": "Feature",
  "properties": {
    "gn:admin1_code":"14",
    "gn:admin2_code":"48.0",
    "gn:asciiname":"Pomas",
    "gn:country_code":"MX",
    "gn:dem":2189,
    "gn:feature_class":"P",
    "gn:feature_code":"PPL",
    "gn:name":"Pomas",
    "gn:population":0,
    "gn:timezone":"America/Mexico_City",
    "iso:country":"MX",
    "wof:name":"Pomas",
    "wof:placetype":"locality"
},
  "geometry": {"coordinates":[-102.18333,20.66667],"type":"Point"}
}