{
  "type": "Feature",
  "properties": {
    "gn:admin1_code":"6",
    "gn:admin2_code":"10.0",
    "gn:asciiname":"Rancho el Manzano",
    "gn:country_code":"MX",
    "gn:dem":1546,
    "gn:feature_class":"P",
    "gn:feature_code":"PPL",
    "gn:name":"Rancho el Manzano",
    "gn:population":4,
    "gn:timezone":"America/Chihuahua",
    "iso:country":"MX",
    "wof:name":"Rancho el Manzano",
    "wof:placetype":"locality",
    "wof:population":4
},
  "geometry": {"coordinates":[-107.48332000000001,29.8457],"type":"Point"}
}