{
  "type": "Feature",
  "properties": {
    "gn:admin1_code":"16.0",
    "gn:admin2_code":"77.0",
    "gn:asciiname":"Tacupa",
    "gn:country_code":"MX",
    "gn:dem":244,
    "gn:feature_class":"P",
    "gn:feature_code":"PPL",
    "gn:name":"Tacupa",
    "gn:population":616,
    "gn:timezone":"America/Mexico_City",
    "iso:country":"MX",
    "name:spa_x_preferred":[
        "Tacupa"
    ],
    "wof:name":"Tacupa",
    "wof:placetype":"locality",
    "wof:population":616
},
  "geometry": {"coordinates":[-100.68149,18.40847],"type":"Point"}
}