{
  "type": "Feature",
  "properties": {
    "gn:admin1_code":"7.0",
    "gn:admin2_code":"26.0",
    "gn:asciiname":"Puente del Columpio",
    "gn:country_code":"MX",
    "gn:dem":360,
    "gn:feature_class":"P",
    "gn:feature_code":"PPL",
    "gn:name":"Puente del Columpio",
    "gn:population":0,
    "gn:timezone":"America/Monterrey",
    "iso:country":"MX",
    "name:spa_x_preferred":[
        "Puente del Columpio"
    ],
    "wof:name":"Puente del Columpio",
    "wof:placetype":"locality"
},
  "geometry": {"coordinates":[-101.21195,27.40571],"type":"Point"}
}