{
  "type": "Feature",
  "properties": {
    "gn:admin1_code":"7",
    "gn:admin2_code":"6.0",
    "gn:asciiname":"La Negrita",
    "gn:country_code":"MX",
    "gn:dem":936,
    "gn:feature_class":"P",
    "gn:feature_code":"PPL",
    "gn:name":"La Negrita",
    "gn:population":0,
    "gn:timezone":"America/Monterrey",
    "iso:country":"MX",
    "wof:name":"La Negrita",
    "wof:placetype":"locality"
},
  "geometry": {"coordinates":[-101.16735,26.28754],"type":"Point"}
}