{
  "type": "Feature",
  "properties": {
    "gn:admin1_code":"30.0",
    "gn:asciiname":"Los Castanos",
    "gn:country_code":"MX",
    "gn:dem":8,
    "gn:feature_class":"P",
    "gn:feature_code":"PPL",
    "gn:name":"Los Casta\u00f1os",
    "gn:population":0,
    "gn:timezone":"America/Mexico_City",
    "iso:country":"MX",
    "name:spa_x_preferred":[
        "Los Casta\u00f1os"
    ],
    "wof:name":"Los Castanos",
    "wof:placetype":"locality"
},
  "geometry": {"coordinates":[-94.5017,17.96495],"type":"Point"}
}