{
  "type": "Feature",
  "properties": {
    "gn:admin1_code":"4.0",
    "gn:admin2_code":"9.0",
    "gn:asciiname":"Don Samuel",
    "gn:country_code":"MX",
    "gn:dem":88,
    "gn:feature_class":"P",
    "gn:feature_code":"PPL",
    "gn:name":"Don Samuel",
    "gn:population":1081,
    "gn:timezone":"America/Merida",
    "iso:country":"MX",
    "name:spa_x_preferred":[
        "Don Samuel"
    ],
    "wof:name":"Don Samuel",
    "wof:placetype":"locality",
    "wof:population":1081
},
  "geometry": {"coordinates":[-90.85722,18.36],"type":"Point"}
}