{
  "type": "Feature",
  "properties": {
    "gn:admin1_code":"17",
    "gn:asciiname":"Ignacio Zaragoza",
    "gn:country_code":"MX",
    "gn:dem":2359,
    "gn:feature_class":"P",
    "gn:feature_code":"PPL",
    "gn:name":"Ignacio Zaragoza",
    "gn:population":0,
    "gn:timezone":"America/Mexico_City",
    "iso:country":"MX",
    "name:spa_x_preferred":[
        "Ignacio Zaragoza"
    ],
    "wof:name":"Ignacio Zaragoza",
    "wof:placetype":"locality"
},
  "geometry": {"coordinates":[-99.50038000000001,20.06876],"type":"Point"}
}