{
  "type": "Feature",
  "properties": {
    "gn:admin1_code":"24",
    "gn:admin2_code":"41.0",
    "gn:asciiname":"El May",
    "gn:country_code":"MX",
    "gn:dem":135,
    "gn:feature_class":"P",
    "gn:feature_code":"PPL",
    "gn:name":"El May",
    "gn:population":313,
    "gn:timezone":"America/Mexico_City",
    "iso:country":"MX",
    "wof:name":"El May",
    "wof:placetype":"locality",
    "wof:population":313
},
  "geometry": {"coordinates":[-98.83417,21.7175],"type":"Point"}
}