{
  "type": "Feature",
  "properties": {
    "gn:admin1_code":"2.0",
    "gn:admin2_code":"1.0",
    "gn:asciiname":"Santa Rosa",
    "gn:country_code":"MX",
    "gn:dem":2015,
    "gn:feature_class":"P",
    "gn:feature_code":"PPL",
    "gn:name":"Santa Rosa",
    "gn:population":0,
    "gn:timezone":"America/Tijuana",
    "iso:country":"MX",
    "name:spa_x_preferred":[
        "Santa Rosa"
    ],
    "wof:name":"Santa Rosa",
    "wof:placetype":"locality"
},
  "geometry": {"coordinates":[-115.34639,30.78056],"type":"Point"}
}