{
  "type": "Feature",
  "properties": {
    "gn:admin1_code":"5",
    "gn:admin2_code":"61",
    "gn:asciiname":"La Mesa del Rinconcito",
    "gn:country_code":"MX",
    "gn:dem":733,
    "gn:feature_class":"P",
    "gn:feature_code":"PPL",
    "gn:name":"La Mesa del Rinconcito",
    "gn:population":10,
    "gn:timezone":"America/Mexico_City",
    "iso:country":"MX",
    "wof:name":"La Mesa del Rinconcito",
    "wof:placetype":"locality",
    "wof:population":10
},
  "geometry": {"coordinates":[-93.48278000000001,16.49722],"type":"Point"}
}