{
  "type": "Feature",
  "properties": {
    "gn:admin1_code":"31",
    "gn:admin2_code":"6.0",
    "gn:asciiname":"Granito de Oro",
    "gn:country_code":"MX",
    "gn:dem":9,
    "gn:feature_class":"P",
    "gn:feature_code":"PPL",
    "gn:name":"Granito de Oro",
    "gn:population":0,
    "gn:timezone":"America/Merida",
    "iso:country":"MX",
    "name:spa_x_preferred":[
        "Granito de Oro"
    ],
    "wof:name":"Granito de Oro",
    "wof:placetype":"locality"
},
  "geometry": {"coordinates":[-88.53446,21.23941],"type":"Point"}
}