{
  "type": "Feature",
  "properties": {
    "gn:admin1_code":"25",
    "gn:admin2_code":"6",
    "gn:asciiname":"Los Solares",
    "gn:country_code":"MX",
    "gn:dem":10,
    "gn:feature_class":"P",
    "gn:feature_code":"PPL",
    "gn:name":"Los Solares",
    "gn:population":16,
    "gn:timezone":"America/Mazatlan",
    "iso:country":"MX",
    "wof:name":"Los Solares",
    "wof:placetype":"locality",
    "wof:population":16
},
  "geometry": {"coordinates":[-107.36642000000001,24.39844],"type":"Point"}
}