{
  "type": "Feature",
  "properties": {
    "gn:admin1_code":"16.0",
    "gn:admin2_code":"13.0",
    "gn:asciiname":"Frontera de San Juan",
    "gn:country_code":"MX",
    "gn:dem":821,
    "gn:feature_class":"P",
    "gn:feature_code":"PPL",
    "gn:name":"Frontera de San Juan",
    "gn:population":50,
    "gn:timezone":"America/Mexico_City",
    "iso:country":"MX",
    "wof:name":"Frontera de San Juan",
    "wof:placetype":"locality",
    "wof:population":50
},
  "geometry": {"coordinates":[-101.07734000000001,19.16476],"type":"Point"}
}