{
  "type": "Feature",
  "properties": {
    "gn:admin1_code":"19",
    "gn:admin2_code":"7.0",
    "gn:asciiname":"Laredo",
    "gn:country_code":"MX",
    "gn:dem":2037,
    "gn:feature_class":"P",
    "gn:feature_code":"PPL",
    "gn:name":"Laredo",
    "gn:population":0,
    "gn:timezone":"America/Monterrey",
    "iso:country":"MX",
    "name:spa_x_preferred":[
        "Laredo"
    ],
    "wof:name":"Laredo",
    "wof:placetype":"locality"
},
  "geometry": {"coordinates":[-100.01185,24.38877],"type":"Point"}
}