{
  "type": "Feature",
  "properties": {
    "gn:admin1_code":"28",
    "gn:admin2_code":"35.0",
    "gn:asciiname":"Banuelos [Graneros]",
    "gn:country_code":"MX",
    "gn:dem":17,
    "gn:feature_class":"P",
    "gn:feature_code":"PPL",
    "gn:name":"Ba\u00f1uelos [Graneros]",
    "gn:population":5,
    "gn:timezone":"America/Monterrey",
    "iso:country":"MX",
    "name:und_x_variant":[
        "Ba\u00f1uelos [Graneros]"
    ],
    "wof:name":"Banuelos [Graneros]",
    "wof:placetype":"locality",
    "wof:population":5
},
  "geometry": {"coordinates":[-97.98027999999999,25.34417],"type":"Point"}
}