{
  "type": "Feature",
  "properties": {
    "iso:country":"MX",
    "name:ceb_x_preferred":[
        "Vista Hermosa"
    ],
    "name:deu_x_preferred":[
        "Vista Hermosa"
    ],
    "name:spa_x_preferred":[
        "Vista Hermosa"
    ],
    "name:swe_x_preferred":[
        "Vista Hermosa"
    ],
    "name:vie_x_preferred":[
        "Vista Hermosa"
    ],
    "qs:gn_adm0_cc":"MX",
    "qs:gn_fcode":"PPL",
    "qs:gn_local":3991164,
    "qs:gn_nam_loc":"Santiago de Queretaro, Queretaro de Arteaga, Queretaro, MX",
    "qs:gn_namadm1":"22",
    "qs:gn_name":"Vista Hermosa",
    "qs:local_max":2920,
    "qs:local_sum":11708,
    "qs:localhoods":28,
    "qs:name":"Vista Hermosa",
    "qs:name_adm0":"M\u00e9xico",
    "qs:name_adm1":"Queretaro de Arteaga",
    "qs:name_adm2":"Queretaro",
    "qs:name_local":"Santiago de Queretaro",
    "qs:photo_max":107,
    "qs:photo_sum":386,
    "qs:placetype":"Suburb",
    "qs:quad_count":20,
    "qs:woe_adm0":23424900,
    "qs:woe_adm1":2346285,
    "qs:woe_adm2":12601457,
    "qs:woe_lau":0,
    "qs:woe_local":55903790,
    "qs:woe_ver":"7.10.0",
    "wof:lang":[
        "spa"
    ],
    "wof:name":"Vista Hermosa",
    "wof:placetype":"neighbourhood"
},
  "geometry": {"coordinates":[-100.35733500000001,20.581905],"type":"Point"}
}