{
  "type": "Feature",
  "properties": {
    "gn:admin1_code":"11",
    "gn:admin2_code":"23.0",
    "gn:asciiname":"Rancho los Rodriguez",
    "gn:country_code":"MX",
    "gn:dem":1683,
    "gn:feature_class":"P",
    "gn:feature_code":"PPL",
    "gn:name":"Rancho los Rodr\u00edguez",
    "gn:population":7,
    "gn:timezone":"America/Mexico_City",
    "iso:country":"MX",
    "name:und_x_variant":[
        "Rancho los Rodr\u00edguez"
    ],
    "wof:name":"Rancho los Rodriguez",
    "wof:placetype":"locality",
    "wof:population":7
},
  "geometry": {"coordinates":[-101.88167,20.33639],"type":"Point"}
}