{
  "type": "Feature",
  "properties": {
    "gn:admin1_code":"25",
    "gn:admin2_code":"7.0",
    "gn:asciiname":"Huepaco",
    "gn:country_code":"MX",
    "gn:dem":421,
    "gn:feature_class":"P",
    "gn:feature_code":"PPL",
    "gn:name":"Huepaco",
    "gn:population":14,
    "gn:timezone":"America/Mazatlan",
    "iso:country":"MX",
    "name:spa_x_preferred":[
        "Huepaco"
    ],
    "wof:name":"Huepaco",
    "wof:placetype":"locality",
    "wof:population":14
},
  "geometry": {"coordinates":[-108.27296,26.96792],"type":"Point"}
}