{
  "type": "Feature",
  "properties": {
    "gn:admin1_code":"16",
    "gn:admin2_code":"49.0",
    "gn:asciiname":"La Yerbabuena",
    "gn:country_code":"MX",
    "gn:dem":2366,
    "gn:feature_class":"P",
    "gn:feature_code":"PPL",
    "gn:name":"La Yerbabuena",
    "gn:population":0,
    "gn:timezone":"America/Mexico_City",
    "iso:country":"MX",
    "name:spa_x_preferred":[
        "La Yerbabuena"
    ],
    "wof:name":"La Yerbabuena",
    "wof:placetype":"locality"
},
  "geometry": {"coordinates":[-101.30240000000001,19.36586],"type":"Point"}
}