{
  "type": "Feature",
  "properties": {
    "gn:admin1_code":"11",
    "gn:admin2_code":"19",
    "gn:asciiname":"Arroyo del Fresno",
    "gn:country_code":"MX",
    "gn:dem":2045,
    "gn:feature_class":"P",
    "gn:feature_code":"PPL",
    "gn:name":"Arroyo del Fresno",
    "gn:population":43,
    "gn:timezone":"America/Mexico_City",
    "iso:country":"MX",
    "wof:name":"Arroyo del Fresno",
    "wof:placetype":"locality",
    "wof:population":43
},
  "geometry": {"coordinates":[-100.43556,20.04556],"type":"Point"}
}