{
  "type": "Feature",
  "properties": {
    "gn:admin1_code":"19",
    "gn:admin2_code":"40.0",
    "gn:asciiname":"Palos Blancos",
    "gn:country_code":"MX",
    "gn:dem":173,
    "gn:feature_class":"P",
    "gn:feature_code":"PPL",
    "gn:name":"Palos Blancos",
    "gn:population":2,
    "gn:timezone":"America/Monterrey",
    "iso:country":"MX",
    "name:deu_x_preferred":[
        "Palos Blancos"
    ],
    "name:spa_x_preferred":[
        "Paso Blanco"
    ],
    "name:zho_x_preferred":[
        "\u5e15\u6d1b\u65af\u5e03\u862d\u79d1\u65af"
    ],
    "wof:name":"Palos Blancos",
    "wof:placetype":"locality",
    "wof:population":2
},
  "geometry": {"coordinates":[-99.53482,26.41019],"type":"Point"}
}