{
  "type": "Feature",
  "properties": {
    "gn:admin1_code":"20",
    "gn:admin2_code":"329.0",
    "gn:asciiname":"San Antonio del Progreso",
    "gn:country_code":"MX",
    "gn:dem":1581,
    "gn:feature_class":"P",
    "gn:feature_code":"PPL",
    "gn:name":"San Antonio del Progreso",
    "gn:population":0,
    "gn:timezone":"America/Mexico_City",
    "iso:country":"MX",
    "name:spa_x_preferred":[
        "San Antonio El Progreso"
    ],
    "name:spa_x_variant":[
        "San Antonio del Progreso"
    ],
    "wof:name":"San Antonio del Progreso",
    "wof:placetype":"locality"
},
  "geometry": {"coordinates":[-97.25054,16.977],"type":"Point"}
}