{
  "type": "Feature",
  "properties": {
    "gn:admin1_code":"6",
    "gn:admin2_code":"21.0",
    "gn:asciiname":"Las Maravillas",
    "gn:country_code":"MX",
    "gn:dem":1196,
    "gn:feature_class":"P",
    "gn:feature_code":"PPL",
    "gn:name":"Las Maravillas",
    "gn:population":5,
    "gn:timezone":"America/Chihuahua",
    "iso:country":"MX",
    "wof:name":"Las Maravillas",
    "wof:placetype":"locality",
    "wof:population":5
},
  "geometry": {"coordinates":[-105.37035,28.12366],"type":"Point"}
}