{
  "type": "Feature",
  "properties": {
    "gn:admin1_code":"30",
    "gn:admin2_code":"91",
    "gn:asciiname":"Brecha Numero Veintiuno",
    "gn:country_code":"MX",
    "gn:dem":58,
    "gn:feature_class":"P",
    "gn:feature_code":"PPL",
    "gn:name":"Brecha N\u00famero Veintiuno",
    "gn:population":31,
    "gn:timezone":"America/Mexico_City",
    "iso:country":"MX",
    "name:und_x_variant":[
        "Brecha N\u00famero Veintiuno"
    ],
    "wof:name":"Brecha Numero Veintiuno",
    "wof:placetype":"locality",
    "wof:population":31
},
  "geometry": {"coordinates":[-95.08333,17.45611],"type":"Point"}
}