{
  "type": "Feature",
  "properties": {
    "gn:admin1_code":"14",
    "gn:admin2_code":"2.0",
    "gn:asciiname":"El Platanarillo",
    "gn:country_code":"MX",
    "gn:dem":1442,
    "gn:feature_class":"P",
    "gn:feature_code":"PPL",
    "gn:name":"El Platanarillo",
    "gn:population":6,
    "gn:timezone":"America/Mexico_City",
    "iso:country":"MX",
    "wof:name":"El Platanarillo",
    "wof:placetype":"locality",
    "wof:population":6
},
  "geometry": {"coordinates":[-103.5675,20.40917],"type":"Point"}
}