{
  "type": "Feature",
  "properties": {
    "gn:admin1_code":"20.0",
    "gn:admin2_code":"300.0",
    "gn:asciiname":"Cuadrilla Santiago",
    "gn:country_code":"MX",
    "gn:dem":630,
    "gn:feature_class":"P",
    "gn:feature_code":"PPL",
    "gn:name":"Cuadrilla Santiago",
    "gn:population":0,
    "gn:timezone":"America/Mexico_City",
    "iso:country":"MX",
    "name:spa_x_preferred":[
        "Cuadrilla Santiago"
    ],
    "name:spa_x_variant":[
        "La Encinera"
    ],
    "wof:name":"Cuadrilla Santiago",
    "wof:placetype":"locality"
},
  "geometry": {"coordinates":[-98.07787999999999,16.64034],"type":"Point"}
}