{
  "type": "Feature",
  "properties": {
    "gn:admin1_code":"15.0",
    "gn:admin2_code":"124.0",
    "gn:asciiname":"El Deposito San Antonio",
    "gn:country_code":"MX",
    "gn:dem":2744,
    "gn:feature_class":"P",
    "gn:feature_code":"PPL",
    "gn:name":"El Dep\u00f3sito San Antonio",
    "gn:population":0,
    "gn:timezone":"America/Mexico_City",
    "iso:country":"MX",
    "name:spa_x_preferred":[
        "El Dep\u00f3sito San Antonio"
    ],
    "wof:name":"El Deposito San Antonio",
    "wof:placetype":"locality"
},
  "geometry": {"coordinates":[-100.12424,19.53273],"type":"Point"}
}