{
  "type": "Feature",
  "properties": {
    "gn:admin1_code":"19.0",
    "gn:asciiname":"Las Tres R",
    "gn:country_code":"MX",
    "gn:dem":442,
    "gn:feature_class":"P",
    "gn:feature_code":"PPL",
    "gn:name":"Las Tres R",
    "gn:population":0,
    "gn:timezone":"America/Monterrey",
    "iso:country":"MX",
    "name:spa_x_preferred":[
        "Las Tres R"
    ],
    "wof:name":"Las Tres R",
    "wof:placetype":"locality"
},
  "geometry": {"coordinates":[-100.22573,25.85345],"type":"Point"}
}