{
  "type": "Feature",
  "properties": {
    "gn:admin1_code":"6",
    "gn:admin2_code":"8.0",
    "gn:asciiname":"Huetebachi",
    "gn:country_code":"MX",
    "gn:dem":2300,
    "gn:feature_class":"P",
    "gn:feature_code":"PPL",
    "gn:name":"Huetebachi",
    "gn:population":0,
    "gn:timezone":"America/Chihuahua",
    "iso:country":"MX",
    "name:spa_x_preferred":[
        "Huetebachi"
    ],
    "wof:name":"Huetebachi",
    "wof:placetype":"locality"
},
  "geometry": {"coordinates":[-107.60303,27.09295],"type":"Point"}
}