{
  "type": "Feature",
  "properties": {
    "gn:admin1_code":"20",
    "gn:admin2_code":"28",
    "gn:asciiname":"La Capilla",
    "gn:country_code":"MX",
    "gn:dem":1486,
    "gn:feature_class":"P",
    "gn:feature_code":"PPL",
    "gn:name":"La Capilla",
    "gn:population":13,
    "gn:timezone":"America/Mexico_City",
    "iso:country":"MX",
    "wof:name":"La Capilla",
    "wof:placetype":"locality",
    "wof:population":13
},
  "geometry": {"coordinates":[-96.70361,16.55667],"type":"Point"}
}