{
  "type": "Feature",
  "properties": {
    "gn:admin1_code":"21",
    "gn:admin2_code":"127.0",
    "gn:asciiname":"El Mosco",
    "gn:country_code":"MX",
    "gn:dem":1389,
    "gn:feature_class":"P",
    "gn:feature_code":"PPL",
    "gn:name":"El Mosco",
    "gn:population":86,
    "gn:timezone":"America/Mexico_City",
    "iso:country":"MX",
    "wof:name":"El Mosco",
    "wof:placetype":"locality",
    "wof:population":86
},
  "geometry": {"coordinates":[-97.89443,18.22817],"type":"Point"}
}