{
  "type": "Feature",
  "properties": {
    "gn:admin1_code":"2.0",
    "gn:admin2_code":"1.0",
    "gn:asciiname":"Agua Amarga",
    "gn:country_code":"MX",
    "gn:dem":339,
    "gn:feature_class":"P",
    "gn:feature_code":"PPL",
    "gn:name":"Agua Amarga",
    "gn:population":0,
    "gn:timezone":"America/Tijuana",
    "iso:country":"MX",
    "name:spa_x_preferred":[
        "Agua Amarga"
    ],
    "wof:name":"Agua Amarga",
    "wof:placetype":"locality"
},
  "geometry": {"coordinates":[-113.69443,28.96497],"type":"Point"}
}