{
  "type": "Feature",
  "properties": {
    "gn:admin1_code":"30",
    "gn:admin2_code":"169",
    "gn:asciiname":"La Puente",
    "gn:country_code":"MX",
    "gn:dem":18,
    "gn:feature_class":"P",
    "gn:feature_code":"PPL",
    "gn:name":"La Puente",
    "gn:population":16,
    "gn:timezone":"America/Mexico_City",
    "iso:country":"MX",
    "wof:name":"La Puente",
    "wof:placetype":"locality",
    "wof:population":16
},
  "geometry": {"coordinates":[-95.66639000000001,18.18583],"type":"Point"}
}