{
  "type": "Feature",
  "properties": {
    "gn:admin1_code":"20",
    "gn:admin2_code":"70",
    "gn:asciiname":"El Jicaral",
    "gn:country_code":"MX",
    "gn:dem":267,
    "gn:feature_class":"P",
    "gn:feature_code":"PPL",
    "gn:name":"El Jicaral",
    "gn:population":20,
    "gn:timezone":"America/Mexico_City",
    "iso:country":"MX",
    "wof:name":"El Jicaral",
    "wof:placetype":"locality",
    "wof:population":20
},
  "geometry": {"coordinates":[-97.94028,16.40556],"type":"Point"}
}