{
  "type": "Feature",
  "properties": {
    "gn:admin1_code":"20",
    "gn:admin2_code":"70",
    "gn:asciiname":"El Jicaral",
    "gn:country_code":"MX",
    "gn:dem":267,
    "gn:feature_class":"P",
    "gn:feature_code":"PPL",
    "gn:name":"El Jicaral",
    "gn:population":20,
    "gn:timezone":"America/Mexico_City",
    "iso:country":"MX",
    "name:ell_x_preferred":[
        "\u0395\u03bb \u03a7\u03b9\u03ba\u03b1\u03c1\u03ac\u03bb"
    ],
    "name:fra_x_preferred":[
        "El Jicaral"
    ],
    "name:ita_x_preferred":[
        "El Jicaral"
    ],
    "name:spa_x_preferred":[
        "El Jicaral"
    ],
    "name:swe_x_preferred":[
        "El Jicaral"
    ],
    "name:urd_x_preferred":[
        "\u0627\u06cc\u0644 \u062e\u06cc\u06a9\u0627\u0631\u0627\u0644"
    ],
    "name:vie_x_preferred":[
        "El Jicaral"
    ],
    "name:zho_x_preferred":[
        "\u57c3\u723e\u5e0c\u5361\u62c9\u723e"
    ],
    "wof:name":"El Jicaral",
    "wof:placetype":"locality",
    "wof:population":20
},
  "geometry": {"coordinates":[-97.94028,16.40556],"type":"Point"}
}