{
  "type": "Feature",
  "properties": {
    "gn:admin1_code":"30",
    "gn:admin2_code":"172.0",
    "gn:asciiname":"Venustiano Carranza",
    "gn:country_code":"MX",
    "gn:dem":18,
    "gn:feature_class":"P",
    "gn:feature_code":"PPL",
    "gn:name":"Venustiano Carranza",
    "gn:population":0,
    "gn:timezone":"America/Mexico_City",
    "iso:country":"MX",
    "name:spa_x_preferred":[
        "Venustiano Carranza"
    ],
    "name:und_x_variant":[
        "Pe\u00f1as Blancas",
        "Pe\u00f1a Blanca"
    ],
    "wof:name":"Venustiano Carranza",
    "wof:placetype":"locality"
},
  "geometry": {"coordinates":[-94.75144,17.64212000000001],"type":"Point"}
}