{
  "type": "Feature",
  "properties": {
    "gn:admin1_code":"23",
    "gn:admin2_code":"4.0",
    "gn:asciiname":"La Nueva Esperanza",
    "gn:country_code":"MX",
    "gn:dem":28,
    "gn:feature_class":"P",
    "gn:feature_code":"PPL",
    "gn:name":"La Nueva Esperanza",
    "gn:population":59,
    "gn:timezone":"America/Cancun",
    "iso:country":"MX",
    "wof:name":"La Nueva Esperanza",
    "wof:placetype":"locality",
    "wof:population":59
},
  "geometry": {"coordinates":[-88.46028000000003,18.74667],"type":"Point"}
}