{
  "type": "Feature",
  "properties": {
    "gn:admin1_code":"30",
    "gn:admin2_code":"114.0",
    "gn:asciiname":"El Rincon",
    "gn:country_code":"MX",
    "gn:dem":53,
    "gn:feature_class":"P",
    "gn:feature_code":"PPL",
    "gn:name":"El Rinc\u00f3n",
    "gn:population":0,
    "gn:timezone":"America/Mexico_City",
    "iso:country":"MX",
    "wof:name":"El Rincon",
    "wof:placetype":"locality"
},
  "geometry": {"coordinates":[-96.75511,20.089],"type":"Point"}
}