{
  "type": "Feature",
  "properties": {
    "gn:admin1_code":"26.0",
    "gn:admin2_code":"52.0",
    "gn:asciiname":"El Paredon",
    "gn:country_code":"MX",
    "gn:dem":1319,
    "gn:feature_class":"P",
    "gn:feature_code":"PPL",
    "gn:name":"El Pared\u00f3n",
    "gn:population":0,
    "gn:timezone":"America/Hermosillo",
    "iso:country":"MX",
    "name:spa_x_preferred":[
        "El Pared\u00f3n"
    ],
    "wof:name":"El Paredon",
    "wof:placetype":"locality"
},
  "geometry": {"coordinates":[-108.76201,28.64396],"type":"Point"}
}