{
  "type": "Feature",
  "properties": {
    "gn:admin1_code":"11.0",
    "gn:admin2_code":"29.0",
    "gn:asciiname":"El Refugio",
    "gn:country_code":"MX",
    "gn:dem":2014,
    "gn:feature_class":"P",
    "gn:feature_code":"PPL",
    "gn:name":"El Refugio",
    "gn:population":0,
    "gn:timezone":"America/Mexico_City",
    "iso:country":"MX",
    "name:spa_x_preferred":[
        "El Refugio"
    ],
    "wof:name":"El Refugio",
    "wof:placetype":"locality"
},
  "geometry": {"coordinates":[-100.71953999999999,21.3757],"type":"Point"}
}