{
  "type": "Feature",
  "properties": {
    "gn:admin1_code":"21",
    "gn:admin2_code":"132.0",
    "gn:asciiname":"San Miguel Lardizabal (Colonia Altamirano)",
    "gn:country_code":"MX",
    "gn:dem":2292,
    "gn:feature_class":"P",
    "gn:feature_code":"PPL",
    "gn:name":"San Miguel Lardiz\u00e1bal (Colonia Altamirano)",
    "gn:population":324,
    "gn:timezone":"America/Mexico_City",
    "iso:country":"MX",
    "name:und_x_variant":[
        "San Miguel Lardiz\u00e1bal (Colonia Altamirano)"
    ],
    "wof:name":"San Miguel Lardizabal (Colonia Altamirano)",
    "wof:placetype":"locality",
    "wof:population":324
},
  "geometry": {"coordinates":[-98.43778,19.30361],"type":"Point"}
}