{
  "type": "Feature",
  "properties": {
    "gn:admin1_code":"19.0",
    "gn:asciiname":"Las Ventanas",
    "gn:country_code":"MX",
    "gn:dem":636,
    "gn:feature_class":"P",
    "gn:feature_code":"PPL",
    "gn:name":"Las Ventanas",
    "gn:population":0,
    "gn:timezone":"America/Monterrey",
    "iso:country":"MX",
    "name:ast_x_preferred":[
        "Les Ventanes"
    ],
    "name:ceb_x_preferred":[
        "Ventanas"
    ],
    "name:spa_x_preferred":[
        "Las Ventanas"
    ],
    "wof:name":"Las Ventanas",
    "wof:placetype":"locality"
},
  "geometry": {"coordinates":[-100.59072,25.95015],"type":"Point"}
}