{
  "type": "Feature",
  "properties": {
    "gn:admin1_code":"1",
    "gn:admin2_code":"11",
    "gn:asciiname":"Las Carmelitas",
    "gn:country_code":"MX",
    "gn:dem":1885,
    "gn:feature_class":"P",
    "gn:feature_code":"PPL",
    "gn:name":"Las Carmelitas",
    "gn:population":15,
    "gn:timezone":"America/Mexico_City",
    "iso:country":"MX",
    "wof:name":"Las Carmelitas",
    "wof:placetype":"locality",
    "wof:population":15
},
  "geometry": {"coordinates":[-102.28028,22.06417],"type":"Point"}
}