{
  "type": "Feature",
  "properties": {
    "gn:admin1_code":"16",
    "gn:admin2_code":"34.0",
    "gn:asciiname":"La Calavera",
    "gn:country_code":"MX",
    "gn:dem":2587,
    "gn:feature_class":"P",
    "gn:feature_code":"PPL",
    "gn:name":"La Calavera",
    "gn:population":7,
    "gn:timezone":"America/Mexico_City",
    "iso:country":"MX",
    "wof:name":"La Calavera",
    "wof:placetype":"locality",
    "wof:population":7
},
  "geometry": {"coordinates":[-100.65389,19.52917],"type":"Point"}
}