{
  "type": "Feature",
  "properties": {
    "gn:admin1_code":"2",
    "gn:admin2_code":"1.0",
    "gn:asciiname":"Los Bataques",
    "gn:cc2":"MX",
    "gn:country_code":"MX",
    "gn:dem":1084,
    "gn:feature_class":"P",
    "gn:feature_code":"PPL",
    "gn:name":"Los Bataques",
    "gn:population":0,
    "gn:timezone":"America/Tijuana",
    "iso:country":"MX",
    "name:und_x_variant":[
        "Las Batequis",
        "Batequis",
        "Bataques",
        "Los Bataques"
    ],
    "wof:name":"Los Bataques",
    "wof:placetype":"locality"
},
  "geometry": {"coordinates":[-115.84999999999999,31.56667],"type":"Point"}
}