{
  "type": "Feature",
  "properties": {
    "gn:admin1_code":"11.0",
    "gn:asciiname":"Pozo Lazaro Cardenas",
    "gn:country_code":"MX",
    "gn:dem":1764,
    "gn:feature_class":"P",
    "gn:feature_code":"PPL",
    "gn:name":"Pozo L\u00e1zaro C\u00e1rdenas",
    "gn:population":0,
    "gn:timezone":"America/Mexico_City",
    "iso:country":"MX",
    "name:spa_x_preferred":[
        "Pozo L\u00e1zaro C\u00e1rdenas"
    ],
    "wof:name":"Pozo Lazaro Cardenas",
    "wof:placetype":"locality"
},
  "geometry": {"coordinates":[-101.03012,20.42731],"type":"Point"}
}