{
  "type": "Feature",
  "properties": {
    "iso:country":"MX",
    "name:spa_x_preferred":[
        "Fundo Legal"
    ],
    "qs:gn_adm0_cc":"MX",
    "qs:gn_local":4004886,
    "qs:gn_nam_loc":"heroica nogales",
    "qs:gn_namadm1":"26",
    "qs:local_max":648,
    "qs:local_sum":1223,
    "qs:localhoods":4,
    "qs:name":"Fundo Legal",
    "qs:name_adm0":"M\u00e9xico",
    "qs:name_adm1":"Sonora",
    "qs:name_adm2":"Nogales",
    "qs:name_local":"Heroica Nogales",
    "qs:photo_max":152,
    "qs:photo_sum":540,
    "qs:placetype":"Suburb",
    "qs:quad_count":13,
    "qs:woe_adm0":23424900,
    "qs:woe_adm1":2346289,
    "qs:woe_adm2":12601588,
    "qs:woe_lau":0,
    "qs:woe_local":124797,
    "qs:woe_ver":"7.10.0",
    "wof:lang":[
        "spa"
    ],
    "wof:name":"Fundo Legal",
    "wof:placetype":"neighbourhood"
},
  "geometry": {"coordinates":[-110.945438,31.331486],"type":"Point"}
}