{
  "type": "Feature",
  "properties": {
    "gn:admin1_code":"5",
    "gn:admin2_code":"1.0",
    "gn:asciiname":"Los Amates",
    "gn:country_code":"MX",
    "gn:dem":66,
    "gn:feature_class":"P",
    "gn:feature_code":"PPL",
    "gn:name":"Los Amates",
    "gn:population":527,
    "gn:timezone":"America/Mexico_City",
    "iso:country":"MX",
    "name:ceb_x_preferred":[
        "Los Amates"
    ],
    "name:deu_x_preferred":[
        "Los Amates"
    ],
    "name:fra_x_preferred":[
        "Los Amates"
    ],
    "name:ita_x_preferred":[
        "Los Amates"
    ],
    "name:pol_x_preferred":[
        "Los Amates"
    ],
    "name:por_x_preferred":[
        "Los Amates"
    ],
    "name:sco_x_preferred":[
        "Los Amates"
    ],
    "name:spa_x_preferred":[
        "Los Amates"
    ],
    "name:zho_x_preferred":[
        "\u6d1b\u65af\u963f\u99ac\u7279\u65af"
    ],
    "wof:name":"Los Amates",
    "wof:placetype":"locality",
    "wof:population":527
},
  "geometry": {"coordinates":[-92.69338999999999,15.34613],"type":"Point"}
}