{
  "type": "Feature",
  "properties": {
    "gn:admin1_code":"12.0",
    "gn:admin2_code":"50.0",
    "gn:asciiname":"La Conchita",
    "gn:country_code":"MX",
    "gn:dem":245,
    "gn:feature_class":"P",
    "gn:feature_code":"PPL",
    "gn:name":"La Conchita",
    "gn:population":0,
    "gn:timezone":"America/Mexico_City",
    "iso:country":"MX",
    "name:spa_x_preferred":[
        "La Conchita"
    ],
    "wof:name":"La Conchita",
    "wof:placetype":"locality"
},
  "geometry": {"coordinates":[-100.69786000000001,18.34966],"type":"Point"}
}