{
  "type": "Feature",
  "properties": {
    "gn:admin1_code":"1",
    "gn:admin2_code":"3.0",
    "gn:asciiname":"El Puertecito",
    "gn:country_code":"MX",
    "gn:dem":1616,
    "gn:feature_class":"P",
    "gn:feature_code":"PPL",
    "gn:name":"El Puertecito",
    "gn:population":71,
    "gn:timezone":"America/Mexico_City",
    "iso:country":"MX",
    "wof:name":"El Puertecito",
    "wof:placetype":"locality",
    "wof:population":71
},
  "geometry": {"coordinates":[-102.75528,21.84861],"type":"Point"}
}