{
  "type": "Feature",
  "properties": {
    "gn:admin1_code":"28",
    "gn:admin2_code":"22.0",
    "gn:asciiname":"El Chapeno",
    "gn:country_code":"MX",
    "gn:dem":7,
    "gn:feature_class":"P",
    "gn:feature_code":"PPL",
    "gn:name":"El Chape\u00f1o",
    "gn:population":0,
    "gn:timezone":"America/Matamoros",
    "iso:country":"MX",
    "wof:name":"El Chapeno",
    "wof:placetype":"locality"
},
  "geometry": {"coordinates":[-97.6135,25.43795],"type":"Point"}
}