{
  "type": "Feature",
  "properties": {
    "gn:admin1_code":"13",
    "gn:admin2_code":"26.0",
    "gn:asciiname":"La Ceiba",
    "gn:country_code":"MX",
    "gn:dem":249,
    "gn:feature_class":"P",
    "gn:feature_code":"PPL",
    "gn:name":"La Ceiba",
    "gn:population":210,
    "gn:timezone":"America/Mexico_City",
    "iso:country":"MX",
    "wof:name":"La Ceiba",
    "wof:placetype":"locality",
    "wof:population":210
},
  "geometry": {"coordinates":[-98.425,21.04528],"type":"Point"}
}