{
  "type": "Feature",
  "properties": {
    "gn:admin1_code":"14",
    "gn:admin2_code":"53.0",
    "gn:asciiname":"Cantera de Torres",
    "gn:country_code":"MX",
    "gn:dem":1816,
    "gn:feature_class":"P",
    "gn:feature_code":"PPL",
    "gn:name":"Cantera de Torres",
    "gn:population":57,
    "gn:timezone":"America/Mexico_City",
    "iso:country":"MX",
    "wof:name":"Cantera de Torres",
    "wof:placetype":"locality",
    "wof:population":57
},
  "geometry": {"coordinates":[-101.85333,21.19278],"type":"Point"}
}