{
  "type": "Feature",
  "properties": {
    "gn:admin1_code":"21",
    "gn:admin2_code":"60",
    "gn:asciiname":"Axaxalpa",
    "gn:country_code":"MX",
    "gn:dem":2485,
    "gn:feature_class":"P",
    "gn:feature_code":"PPL",
    "gn:name":"Axaxalpa",
    "gn:population":43,
    "gn:timezone":"America/Mexico_City",
    "iso:country":"MX",
    "wof:name":"Axaxalpa",
    "wof:placetype":"locality",
    "wof:population":43
},
  "geometry": {"coordinates":[-98.4693,19.14129],"type":"Point"}
}