{
  "type": "Feature",
  "properties": {
    "gn:admin1_code":"24",
    "gn:admin2_code":"37.0",
    "gn:asciiname":"Pemucho",
    "gn:country_code":"MX",
    "gn:dem":794,
    "gn:feature_class":"P",
    "gn:feature_code":"PPL",
    "gn:name":"Pemucho",
    "gn:population":0,
    "gn:timezone":"America/Mexico_City",
    "iso:country":"MX",
    "name:spa_x_preferred":[
        "Pemucho"
    ],
    "name:spa_x_variant":[
        "Permucho"
    ],
    "wof:name":"Pemucho",
    "wof:placetype":"locality"
},
  "geometry": {"coordinates":[-98.83015,21.19738],"type":"Point"}
}