{
  "type": "Feature",
  "properties": {
    "gn:admin1_code":"6",
    "gn:admin2_code":"27.0",
    "gn:asciiname":"Rancheria la Mesa",
    "gn:country_code":"MX",
    "gn:dem":2377,
    "gn:feature_class":"P",
    "gn:feature_code":"PPL",
    "gn:name":"Rancher\u00eda la Mesa",
    "gn:population":0,
    "gn:timezone":"America/Chihuahua",
    "iso:country":"MX",
    "name:spa_x_preferred":[
        "Rancher\u00eda la Mesa"
    ],
    "wof:name":"Rancheria la Mesa",
    "wof:placetype":"locality"
},
  "geometry": {"coordinates":[-107.19764000000001,27.09826],"type":"Point"}
}