{
  "type": "Feature",
  "properties": {
    "gn:admin1_code":"30.0",
    "gn:admin2_code":"205.0",
    "gn:asciiname":"El Retonito",
    "gn:country_code":"MX",
    "gn:dem":76,
    "gn:feature_class":"P",
    "gn:feature_code":"PPL",
    "gn:name":"El Retonito",
    "gn:population":0,
    "gn:timezone":"America/Mexico_City",
    "iso:country":"MX",
    "name:spa_x_preferred":[
        "El Retonito"
    ],
    "wof:name":"El Retonito",
    "wof:placetype":"locality"
},
  "geometry": {"coordinates":[-98.52243,21.64645],"type":"Point"}
}