{
  "type": "Feature",
  "properties": {
    "gn:admin1_code":"19.0",
    "gn:admin2_code":"50.0",
    "gn:asciiname":"Santa Elena",
    "gn:country_code":"MX",
    "gn:dem":219,
    "gn:feature_class":"P",
    "gn:feature_code":"PPL",
    "gn:name":"Santa Elena",
    "gn:population":0,
    "gn:timezone":"America/Monterrey",
    "iso:country":"MX",
    "name:spa_x_preferred":[
        "Santa Elena"
    ],
    "wof:name":"Santa Elena",
    "wof:placetype":"locality"
},
  "geometry": {"coordinates":[-100.04667000000001,26.82639],"type":"Point"}
}