{
  "type": "Feature",
  "properties": {
    "gn:admin1_code":"32",
    "gn:admin2_code":"5.0",
    "gn:asciiname":"La Esperanza (Antonio A. R.) [Deshidratadora]",
    "gn:country_code":"MX",
    "gn:dem":2144,
    "gn:feature_class":"P",
    "gn:feature_code":"PPL",
    "gn:name":"La Esperanza (Antonio A. R.) [Deshidratadora]",
    "gn:population":7,
    "gn:timezone":"America/Mexico_City",
    "iso:country":"MX",
    "wof:name":"La Esperanza (Antonio A. R.) [Deshidratadora]",
    "wof:placetype":"locality",
    "wof:population":7
},
  "geometry": {"coordinates":[-102.67583,22.9675],"type":"Point"}
}