{
  "type": "Feature",
  "properties": {
    "gn:admin1_code":"28",
    "gn:admin2_code":"22",
    "gn:asciiname":"La Rosita (Federico Garcia)",
    "gn:country_code":"MX",
    "gn:dem":12,
    "gn:feature_class":"P",
    "gn:feature_code":"PPL",
    "gn:name":"La Rosita (Federico Garc\u00eda)",
    "gn:population":23,
    "gn:timezone":"America/Matamoros",
    "iso:country":"MX",
    "name:und_x_variant":[
        "La Rosita (Federico Garc\u00eda)"
    ],
    "wof:name":"La Rosita (Federico Garcia)",
    "wof:placetype":"locality",
    "wof:population":23
},
  "geometry": {"coordinates":[-97.62139000000001,25.85778],"type":"Point"}
}