{
  "type": "Feature",
  "properties": {
    "gn:admin1_code":"5.0",
    "gn:admin2_code":"99.0",
    "gn:asciiname":"Santa Lucia la Galera",
    "gn:country_code":"MX",
    "gn:dem":721,
    "gn:feature_class":"P",
    "gn:feature_code":"PPL",
    "gn:name":"Santa Lucia la Galera",
    "gn:population":0,
    "gn:timezone":"America/Mexico_City",
    "iso:country":"MX",
    "name:spa_x_preferred":[
        "Santa Lucia la Galera"
    ],
    "wof:name":"Santa Lucia la Galera",
    "wof:placetype":"locality"
},
  "geometry": {"coordinates":[-91.9875,15.90682],"type":"Point"}
}