{
  "type": "Feature",
  "properties": {
    "gn:admin1_code":"28",
    "gn:admin2_code":"35.0",
    "gn:asciiname":"La Rosita",
    "gn:country_code":"MX",
    "gn:dem":131,
    "gn:feature_class":"P",
    "gn:feature_code":"PPL",
    "gn:name":"La Rosita",
    "gn:population":0,
    "gn:timezone":"America/Monterrey",
    "iso:country":"MX",
    "wof:name":"La Rosita",
    "wof:placetype":"locality"
},
  "geometry": {"coordinates":[-98.25,25.08333],"type":"Point"}
}