{
  "type": "Feature",
  "properties": {
    "gn:admin1_code":"28.0",
    "gn:admin2_code":"32.0",
    "gn:asciiname":"El Chapul Uno",
    "gn:country_code":"MX",
    "gn:dem":74,
    "gn:feature_class":"P",
    "gn:feature_code":"PPL",
    "gn:name":"El Chapul Uno",
    "gn:population":0,
    "gn:timezone":"America/Matamoros",
    "iso:country":"MX",
    "name:spa_x_preferred":[
        "El Chapul Uno"
    ],
    "wof:name":"El Chapul Uno",
    "wof:placetype":"locality"
},
  "geometry": {"coordinates":[-98.27912999999999,25.60659],"type":"Point"}
}