{
  "type": "Feature",
  "properties": {
    "gn:admin1_code":"15.0",
    "gn:asciiname":"San Isidro Labrador",
    "gn:country_code":"MX",
    "gn:dem":2334,
    "gn:feature_class":"P",
    "gn:feature_code":"PPL",
    "gn:name":"San Isidro Labrador",
    "gn:population":0,
    "gn:timezone":"America/Mexico_City",
    "iso:country":"MX",
    "name:spa_x_preferred":[
        "San Isidro Labrador"
    ],
    "wof:name":"San Isidro Labrador",
    "wof:placetype":"locality"
},
  "geometry": {"coordinates":[-98.866,19.17218],"type":"Point"}
}