{
  "type": "Feature",
  "properties": {
    "gn:admin1_code":"4",
    "gn:admin2_code":"2.0",
    "gn:asciiname":"Guanajuato",
    "gn:country_code":"MX",
    "gn:dem":23,
    "gn:feature_class":"P",
    "gn:feature_code":"PPL",
    "gn:name":"Guanajuato",
    "gn:population":0,
    "gn:timezone":"America/Merida",
    "iso:country":"MX",
    "name:spa_x_preferred":[
        "El Guanajuato"
    ],
    "name:spa_x_variant":[
        "Guanajuato"
    ],
    "wof:name":"Guanajuato",
    "wof:placetype":"locality"
},
  "geometry": {"coordinates":[-90.42726999999999,19.87826],"type":"Point"}
}