{
  "type": "Feature",
  "properties": {
    "gn:admin1_code":"32.0",
    "gn:admin2_code":"20.0",
    "gn:asciiname":"La Labor",
    "gn:country_code":"MX",
    "gn:dem":1979,
    "gn:feature_class":"P",
    "gn:feature_code":"PPL",
    "gn:name":"La Labor",
    "gn:population":0,
    "gn:timezone":"America/Mexico_City",
    "iso:country":"MX",
    "name:fra_x_preferred":[
        "La Labor"
    ],
    "name:ita_x_preferred":[
        "La Labor"
    ],
    "name:nld_x_preferred":[
        "La Labor"
    ],
    "name:por_x_preferred":[
        "La Labor"
    ],
    "name:spa_x_preferred":[
        "La Labor"
    ],
    "name:zho_x_preferred":[
        "\u62c9\u62c9\u6c83\u723e"
    ],
    "wof:name":"La Labor",
    "wof:placetype":"locality"
},
  "geometry": {"coordinates":[-103.00536,22.59448],"type":"Point"}
}