{
  "type": "Feature",
  "properties": {
    "gn:admin1_code":"22",
    "gn:admin2_code":"10.0",
    "gn:asciiname":"Mesa de la Cruz",
    "gn:country_code":"MX",
    "gn:dem":1872,
    "gn:feature_class":"P",
    "gn:feature_code":"PPL",
    "gn:name":"Mesa de la Cruz",
    "gn:population":68,
    "gn:timezone":"America/Mexico_City",
    "iso:country":"MX",
    "wof:name":"Mesa de la Cruz",
    "wof:placetype":"locality",
    "wof:population":68
},
  "geometry": {"coordinates":[-99.18389000000001,21.39722],"type":"Point"}
}