{
  "type": "Feature",
  "properties": {
    "gn:admin1_code":"5",
    "gn:admin2_code":"55.0",
    "gn:asciiname":"Metapa",
    "gn:country_code":"MX",
    "gn:dem":99,
    "gn:feature_class":"P",
    "gn:feature_code":"PPL",
    "gn:name":"Metapa",
    "gn:population":0,
    "gn:timezone":"America/Mexico_City",
    "iso:country":"MX",
    "wof:name":"Metapa",
    "wof:placetype":"locality"
},
  "geometry": {"coordinates":[-92.18333,14.83333],"type":"Point"}
}