{
  "type": "Feature",
  "properties": {
    "gn:admin1_code":"25",
    "gn:admin2_code":"17.0",
    "gn:asciiname":"Los Mautos",
    "gn:country_code":"MX",
    "gn:dem":216,
    "gn:feature_class":"P",
    "gn:feature_code":"PPL",
    "gn:name":"Los Mautos",
    "gn:population":6,
    "gn:timezone":"America/Mazatlan",
    "iso:country":"MX",
    "wof:name":"Los Mautos",
    "wof:placetype":"locality",
    "wof:population":6
},
  "geometry": {"coordinates":[-107.84174,25.77039],"type":"Point"}
}