{
  "type": "Feature",
  "properties": {
    "gn:admin1_code":"6.0",
    "gn:admin2_code":"8.0",
    "gn:asciiname":"Junta de Arroyos",
    "gn:country_code":"MX",
    "gn:dem":590,
    "gn:feature_class":"P",
    "gn:feature_code":"PPL",
    "gn:name":"Junta de Arroyos",
    "gn:population":0,
    "gn:timezone":"America/Chihuahua",
    "iso:country":"MX",
    "name:spa_x_preferred":[
        "Junta de Arroyos"
    ],
    "wof:name":"Junta de Arroyos",
    "wof:placetype":"locality"
},
  "geometry": {"coordinates":[-107.92401,26.82999],"type":"Point"}
}