{
  "type": "Feature",
  "properties": {
    "gn:admin1_code":"25.0",
    "gn:admin2_code":"1.0",
    "gn:asciiname":"Goros Numero Uno",
    "gn:country_code":"MX",
    "gn:dem":14,
    "gn:feature_class":"P",
    "gn:feature_code":"PPL",
    "gn:name":"Goros N\u00famero Uno",
    "gn:population":0,
    "gn:timezone":"America/Mazatlan",
    "iso:country":"MX",
    "name:spa_x_preferred":[
        "Goros N\u00famero Uno"
    ],
    "wof:name":"Goros Numero Uno",
    "wof:placetype":"locality"
},
  "geometry": {"coordinates":[-109.06797,25.92192],"type":"Point"}
}