{
  "type": "Feature",
  "properties": {
    "gn:admin1_code":"20",
    "gn:admin2_code":"269.0",
    "gn:asciiname":"Santo Domingo Tomaltepec",
    "gn:cc2":"MX",
    "gn:country_code":"MX",
    "gn:dem":2555,
    "gn:feature_class":"P",
    "gn:feature_code":"PPL",
    "gn:name":"Santo Domingo Tomaltepec",
    "gn:population":0,
    "gn:timezone":"America/Mexico_City",
    "iso:country":"MX",
    "name:und_x_variant":[
        "Tomaltepec",
        "Santo Domingo Tomaltepec"
    ],
    "wof:name":"Santo Domingo Tomaltepec",
    "wof:placetype":"locality"
},
  "geometry": {"coordinates":[-97.61667,17.06667],"type":"Point"}
}