{
  "type": "Feature",
  "properties": {
    "gn:admin1_code":"20",
    "gn:admin2_code":"269.0",
    "gn:asciiname":"Santo Domingo Tomaltepec",
    "gn:cc2":"MX",
    "gn:country_code":"MX",
    "gn:dem":2555,
    "gn:feature_class":"P",
    "gn:feature_code":"PPL",
    "gn:name":"Santo Domingo Tomaltepec",
    "gn:population":0,
    "gn:timezone":"America/Mexico_City",
    "iso:country":"MX",
    "name:ceb_x_preferred":[
        "Santo Domingo Tomaltepec"
    ],
    "name:epo_x_preferred":[
        "Santo Domingo Tomaltepec"
    ],
    "name:eus_x_preferred":[
        "Santo Domingo Tomaltepec"
    ],
    "name:sco_x_preferred":[
        "Santo Domingo Tomaltepec"
    ],
    "name:srp_x_preferred":[
        "\u041e\u043f\u0448\u0442\u0438\u043d\u0430 \u0421\u0430\u043d\u0442\u043e \u0414\u043e\u043c\u0438\u043d\u0433\u043e \u0422\u043e\u043c\u0430\u043b\u0442\u0435\u043f\u0435\u043a"
    ],
    "name:swe_x_preferred":[
        "Santo Domingo Tomaltepec"
    ],
    "name:und_x_variant":[
        "Tomaltepec"
    ],
    "name:vie_x_preferred":[
        "Santo Domingo Tomaltepec"
    ],
    "wof:name":"Santo Domingo Tomaltepec",
    "wof:placetype":"locality"
},
  "geometry": {"coordinates":[-97.61667,17.06667],"type":"Point"}
}