{
  "type": "Feature",
  "properties": {
    "gn:admin1_code":"20",
    "gn:admin2_code":"231",
    "gn:asciiname":"Pedregal",
    "gn:country_code":"MX",
    "gn:dem":1392,
    "gn:feature_class":"P",
    "gn:feature_code":"PPL",
    "gn:name":"Pedregal",
    "gn:population":19,
    "gn:timezone":"America/Mexico_City",
    "iso:country":"MX",
    "name:ceb_x_preferred":[
        "Pedregal"
    ],
    "name:fra_x_preferred":[
        "Pedregal"
    ],
    "name:ita_x_preferred":[
        "Pedregal"
    ],
    "name:pol_x_preferred":[
        "Pedregal"
    ],
    "name:por_x_preferred":[
        "Pedregal"
    ],
    "name:spa_x_preferred":[
        "Pedregal"
    ],
    "name:srp_x_preferred":[
        "\u041f\u0435\u0434\u0440\u0435\u0433\u0430\u043b"
    ],
    "name:swe_x_preferred":[
        "Pedregal"
    ],
    "wof:name":"Pedregal",
    "wof:placetype":"locality",
    "wof:population":19
},
  "geometry": {"coordinates":[-95.71693999999999,16.94722],"type":"Point"}
}