{
  "type": "Feature",
  "properties": {
    "gn:admin1_code":"31",
    "gn:admin2_code":"29.0",
    "gn:asciiname":"Ixnail",
    "gn:country_code":"MX",
    "gn:dem":5,
    "gn:feature_class":"P",
    "gn:feature_code":"PPL",
    "gn:name":"Ixnail",
    "gn:population":0,
    "gn:timezone":"America/Merida",
    "iso:country":"MX",
    "name:spa_x_preferred":[
        "Ixnail"
    ],
    "name:spa_x_variant":[
        "Xnail"
    ],
    "wof:name":"Ixnail",
    "wof:placetype":"locality"
},
  "geometry": {"coordinates":[-88.64359,21.34433],"type":"Point"}
}