{
  "type": "Feature",
  "properties": {
    "gn:admin1_code":"25",
    "gn:admin2_code":"6.0",
    "gn:asciiname":"La Perla",
    "gn:country_code":"MX",
    "gn:dem":4,
    "gn:feature_class":"P",
    "gn:feature_code":"PPL",
    "gn:name":"La Perla",
    "gn:population":0,
    "gn:timezone":"America/Mazatlan",
    "iso:country":"MX",
    "name:ceb_x_preferred":[
        "La Perla"
    ],
    "name:deu_x_preferred":[
        "La Perla"
    ],
    "name:epo_x_preferred":[
        "La Perla"
    ],
    "name:fra_x_preferred":[
        "La Perla"
    ],
    "name:ita_x_preferred":[
        "La perla"
    ],
    "name:nld_x_preferred":[
        "La Perla"
    ],
    "name:spa_x_preferred":[
        "La Perla"
    ],
    "name:srp_x_preferred":[
        "\u041b\u0430 \u041f\u0435\u0440\u043b\u0430"
    ],
    "name:swe_x_preferred":[
        "La Perla"
    ],
    "wof:name":"La Perla",
    "wof:placetype":"locality"
},
  "geometry": {"coordinates":[-107.43547,24.4628],"type":"Point"}
}