{
  "type": "Feature",
  "properties": {
    "gn:admin1_code":"27",
    "gn:admin2_code":"8.0",
    "gn:asciiname":"Francisco I. Madero",
    "gn:country_code":"MX",
    "gn:dem":27,
    "gn:feature_class":"P",
    "gn:feature_code":"PPL",
    "gn:name":"Francisco I. Madero",
    "gn:population":0,
    "gn:timezone":"America/Mexico_City",
    "iso:country":"MX",
    "name:spa_x_preferred":[
        "Francisco I. Madero"
    ],
    "wof:name":"Francisco I. Madero",
    "wof:placetype":"locality"
},
  "geometry": {"coordinates":[-93.76318000000001,17.7019],"type":"Point"}
}