{
  "type": "Feature",
  "properties": {
    "gn:admin1_code":"30.0",
    "gn:admin2_code":"27.0",
    "gn:asciiname":"Amecatipa",
    "gn:country_code":"MX",
    "gn:dem":243,
    "gn:feature_class":"P",
    "gn:feature_code":"PPL",
    "gn:name":"Amecatipa",
    "gn:population":322,
    "gn:timezone":"America/Mexico_City",
    "iso:country":"MX",
    "name:spa_x_preferred":[
        "Amecatipa"
    ],
    "wof:name":"Amecatipa",
    "wof:placetype":"locality",
    "wof:population":322
},
  "geometry": {"coordinates":[-98.10056,20.77056],"type":"Point"}
}