{
  "type": "Feature",
  "properties": {
    "gn:admin1_code":"26",
    "gn:admin2_code":"66.0",
    "gn:asciiname":"La Bolsa",
    "gn:country_code":"MX",
    "gn:dem":453,
    "gn:feature_class":"P",
    "gn:feature_code":"PPL",
    "gn:name":"La Bolsa",
    "gn:population":0,
    "gn:timezone":"America/Hermosillo",
    "iso:country":"MX",
    "name:spa_x_preferred":[
        "La Bolsa"
    ],
    "wof:name":"La Bolsa",
    "wof:placetype":"locality"
},
  "geometry": {"coordinates":[-110.30361000000001,29.11917],"type":"Point"}
}