{
  "type": "Feature",
  "properties": {
    "gn:admin1_code":"6",
    "gn:admin2_code":"48.0",
    "gn:asciiname":"Rancho de Cesar",
    "gn:country_code":"MX",
    "gn:dem":1915,
    "gn:feature_class":"P",
    "gn:feature_code":"PPL",
    "gn:name":"Rancho de C\u00e9sar",
    "gn:population":5,
    "gn:timezone":"America/Chihuahua",
    "iso:country":"MX",
    "name:und_x_variant":[
        "Rancho de C\u00e9sar"
    ],
    "wof:name":"Rancho de Cesar",
    "wof:placetype":"locality",
    "wof:population":5
},
  "geometry": {"coordinates":[-107.51056,29.06917],"type":"Point"}
}