{
  "type": "Feature",
  "properties": {
    "gn:admin1_code":"18.0",
    "gn:admin2_code":"9.0",
    "gn:asciiname":"El Anonito",
    "gn:country_code":"MX",
    "gn:dem":507,
    "gn:feature_class":"P",
    "gn:feature_code":"PPL",
    "gn:name":"El Anonito",
    "gn:population":20,
    "gn:timezone":"America/Mazatlan",
    "iso:country":"MX",
    "wof:name":"El Anonito",
    "wof:placetype":"locality",
    "wof:population":20
},
  "geometry": {"coordinates":[-104.51139000000001,21.68194],"type":"Point"}
}