{
  "type": "Feature",
  "properties": {
    "gn:admin1_code":"5",
    "gn:admin2_code":"66.0",
    "gn:asciiname":"San Jose Chactu",
    "gn:country_code":"MX",
    "gn:dem":468,
    "gn:feature_class":"P",
    "gn:feature_code":"PPL",
    "gn:name":"San Jos\u00e9 Chact\u00fa",
    "gn:population":86,
    "gn:timezone":"America/Mexico_City",
    "iso:country":"MX",
    "name:und_x_variant":[
        "San Jos\u00e9 Chact\u00fa"
    ],
    "wof:name":"San Jose Chactu",
    "wof:placetype":"locality",
    "wof:population":86
},
  "geometry": {"coordinates":[-92.41417,17.04332999999999],"type":"Point"}
}