{
  "type": "Feature",
  "properties": {
    "gn:admin1_code":"17",
    "gn:admin2_code":"18",
    "gn:asciiname":"Paraje del Cerro Mazatepetongo",
    "gn:country_code":"MX",
    "gn:dem":1530,
    "gn:feature_class":"P",
    "gn:feature_code":"PPL",
    "gn:name":"Paraje del Cerro Mazatepetongo",
    "gn:population":11,
    "gn:timezone":"America/Mexico_City",
    "iso:country":"MX",
    "wof:name":"Paraje del Cerro Mazatepetongo",
    "wof:placetype":"locality",
    "wof:population":11
},
  "geometry": {"coordinates":[-99.26694000000001,18.90056],"type":"Point"}
}