{
  "type": "Feature",
  "properties": {
    "gn:admin1_code":"13",
    "gn:admin2_code":"48",
    "gn:asciiname":"Los Chavez",
    "gn:country_code":"MX",
    "gn:dem":2508,
    "gn:feature_class":"P",
    "gn:feature_code":"PPL",
    "gn:name":"Los Ch\u00e1vez",
    "gn:population":12,
    "gn:timezone":"America/Mexico_City",
    "iso:country":"MX",
    "name:und_x_variant":[
        "Los Ch\u00e1vez"
    ],
    "wof:name":"Los Chavez",
    "wof:placetype":"locality",
    "wof:population":12
},
  "geometry": {"coordinates":[-98.74139,20.13167],"type":"Point"}
}