{
  "type": "Feature",
  "properties": {
    "gn:admin1_code":"32",
    "gn:admin2_code":"19.0",
    "gn:asciiname":"Las Amarillas",
    "gn:country_code":"MX",
    "gn:dem":1721,
    "gn:feature_class":"P",
    "gn:feature_code":"PPL",
    "gn:name":"Las Amarillas",
    "gn:population":0,
    "gn:timezone":"America/Mexico_City",
    "iso:country":"MX",
    "name:spa_x_preferred":[
        "Las Amarillas"
    ],
    "wof:name":"Las Amarillas",
    "wof:placetype":"locality"
},
  "geometry": {"coordinates":[-103.07629,21.5892],"type":"Point"}
}