{
  "type": "Feature",
  "properties": {
    "gn:admin1_code":"2.0",
    "gn:admin2_code":"1.0",
    "gn:asciiname":"El Sauce",
    "gn:country_code":"MX",
    "gn:dem":322,
    "gn:feature_class":"P",
    "gn:feature_code":"PPL",
    "gn:name":"El Sauce",
    "gn:population":0,
    "gn:timezone":"America/Tijuana",
    "iso:country":"MX",
    "name:ceb_x_preferred":[
        "El Sauce"
    ],
    "name:ita_x_preferred":[
        "El Sauce"
    ],
    "name:por_x_preferred":[
        "El Sauce"
    ],
    "name:spa_x_preferred":[
        "El Sauce"
    ],
    "name:und_x_variant":[
        "Sauce"
    ],
    "name:zho_x_preferred":[
        "\u57c3\u723e\u7d39\u585e"
    ],
    "wof:name":"El Sauce",
    "wof:placetype":"locality"
},
  "geometry": {"coordinates":[-116.59616,32.08219],"type":"Point"}
}