{
  "type": "Feature",
  "properties": {
    "gn:admin1_code":"16.0",
    "gn:admin2_code":"101.0",
    "gn:asciiname":"El Devanador",
    "gn:country_code":"MX",
    "gn:dem":1045,
    "gn:feature_class":"P",
    "gn:feature_code":"PPL",
    "gn:name":"El Devanador",
    "gn:population":0,
    "gn:timezone":"America/Mexico_City",
    "iso:country":"MX",
    "name:spa_x_preferred":[
        "El Devanador"
    ],
    "name:und_x_variant":[
        "Puerto el Devanador de la Paz"
    ],
    "wof:name":"El Devanador",
    "wof:placetype":"locality"
},
  "geometry": {"coordinates":[-100.82631000000001,19.38513],"type":"Point"}
}