{
  "type": "Feature",
  "properties": {
    "gn:admin1_code":"32",
    "gn:admin2_code":"49.0",
    "gn:asciiname":"Manga del Chorro",
    "gn:country_code":"MX",
    "gn:dem":2553,
    "gn:feature_class":"P",
    "gn:feature_code":"PPL",
    "gn:name":"Manga del Chorro",
    "gn:population":0,
    "gn:timezone":"America/Mexico_City",
    "iso:country":"MX",
    "name:spa_x_preferred":[
        "Manga del Chorro"
    ],
    "wof:name":"Manga del Chorro",
    "wof:placetype":"locality"
},
  "geometry": {"coordinates":[-103.68552,23.02142000000001],"type":"Point"}
}