{
  "type": "Feature",
  "properties": {
    "gn:admin1_code":"10",
    "gn:admin2_code":"34",
    "gn:asciiname":"El Rebaje",
    "gn:country_code":"MX",
    "gn:dem":2506,
    "gn:feature_class":"P",
    "gn:feature_code":"PPL",
    "gn:name":"El Rebaje",
    "gn:population":11,
    "gn:timezone":"America/Monterrey",
    "iso:country":"MX",
    "wof:name":"El Rebaje",
    "wof:placetype":"locality",
    "wof:population":11
},
  "geometry": {"coordinates":[-106.78427000000001,25.43608],"type":"Point"}
}