{
  "type": "Feature",
  "properties": {
    "gn:admin1_code":"6.0",
    "gn:admin2_code":"1.0",
    "gn:asciiname":"Cafetal",
    "gn:country_code":"MX",
    "gn:dem":1193,
    "gn:feature_class":"P",
    "gn:feature_code":"PPL",
    "gn:name":"Cafetal",
    "gn:population":0,
    "gn:timezone":"America/Chihuahua",
    "iso:country":"MX",
    "name:und_x_variant":[
        "Rancho El Cafetal",
        "Cafetal",
        "El Cafetal"
    ],
    "wof:name":"Cafetal",
    "wof:placetype":"locality"
},
  "geometry": {"coordinates":[-106.49066999999999,30.64474],"type":"Point"}
}