{
  "type": "Feature",
  "properties": {
    "gn:admin1_code":"7",
    "gn:admin2_code":"4.0",
    "gn:asciiname":"Karibu",
    "gn:country_code":"MX",
    "gn:dem":2062,
    "gn:feature_class":"P",
    "gn:feature_code":"PPL",
    "gn:name":"Karib\u00fa",
    "gn:population":5,
    "gn:timezone":"America/Monterrey",
    "iso:country":"MX",
    "name:und_x_variant":[
        "Karib\u00fa"
    ],
    "wof:name":"Karibu",
    "wof:placetype":"locality",
    "wof:population":5
},
  "geometry": {"coordinates":[-100.83669,25.36393],"type":"Point"}
}