{
  "type": "Feature",
  "properties": {
    "gn:admin1_code":"25.0",
    "gn:admin2_code":"10.0",
    "gn:asciiname":"Camajoa",
    "gn:cc2":"MX",
    "gn:country_code":"MX",
    "gn:dem":29,
    "gn:feature_class":"P",
    "gn:feature_code":"PPL",
    "gn:name":"Camajoa",
    "gn:population":755,
    "gn:timezone":"America/Mazatlan",
    "iso:country":"MX",
    "name:und_x_variant":[
        "Bomba de Camojoa",
        "Camajoa"
    ],
    "wof:name":"Camajoa",
    "wof:placetype":"locality",
    "wof:population":755
},
  "geometry": {"coordinates":[-108.85611000000002,25.98806],"type":"Point"}
}