{
  "type": "Feature",
  "properties": {
    "gn:admin1_code":"3",
    "gn:admin2_code":"9.0",
    "gn:asciiname":"Lote Ocho",
    "gn:country_code":"MX",
    "gn:dem":52,
    "gn:feature_class":"P",
    "gn:feature_code":"PPL",
    "gn:name":"Lote Ocho",
    "gn:population":0,
    "gn:timezone":"America/Mazatlan",
    "iso:country":"MX",
    "name:spa_x_preferred":[
        "Lote Ocho"
    ],
    "wof:name":"Lote Ocho",
    "wof:placetype":"locality"
},
  "geometry": {"coordinates":[-111.5501,26.27626],"type":"Point"}
}