{
  "type": "Feature",
  "properties": {
    "gn:admin1_code":"11",
    "gn:admin2_code":"7.0",
    "gn:asciiname":"Palo Blanco",
    "gn:country_code":"MX",
    "gn:dem":1863,
    "gn:feature_class":"P",
    "gn:feature_code":"PPL",
    "gn:name":"Palo Blanco",
    "gn:population":6,
    "gn:timezone":"America/Mexico_City",
    "iso:country":"MX",
    "name:ceb_x_preferred":[
        "Palo Blanco"
    ],
    "name:spa_x_preferred":[
        "Palo blanco"
    ],
    "name:swe_x_preferred":[
        "Palo Blanco"
    ],
    "wof:name":"Palo Blanco",
    "wof:placetype":"locality",
    "wof:population":6
},
  "geometry": {"coordinates":[-100.70444000000001,20.47278],"type":"Point"}
}