{
  "type": "Feature",
  "properties": {
    "gn:admin1_code":"5",
    "gn:admin2_code":"108.0",
    "gn:asciiname":"Champerico",
    "gn:country_code":"MX",
    "gn:dem":947,
    "gn:feature_class":"P",
    "gn:feature_code":"PPL",
    "gn:name":"Champerico",
    "gn:population":95,
    "gn:timezone":"America/Mexico_City",
    "iso:country":"MX",
    "wof:name":"Champerico",
    "wof:placetype":"locality",
    "wof:population":95
},
  "geometry": {"coordinates":[-93.59972,16.37556],"type":"Point"}
}