{
  "type": "Feature",
  "properties": {
    "gn:admin1_code":"5",
    "gn:admin2_code":"108.0",
    "gn:asciiname":"Champerico",
    "gn:country_code":"MX",
    "gn:dem":947,
    "gn:feature_class":"P",
    "gn:feature_code":"PPL",
    "gn:name":"Champerico",
    "gn:population":95,
    "gn:timezone":"America/Mexico_City",
    "iso:country":"MX",
    "name:ast_x_preferred":[
        "Champerico"
    ],
    "name:bul_x_preferred":[
        "\u0427\u0430\u043c\u043f\u0435\u0440\u0438\u043a\u043e"
    ],
    "name:ceb_x_preferred":[
        "Champerico"
    ],
    "name:dan_x_preferred":[
        "Champerico"
    ],
    "name:deu_x_preferred":[
        "Champerico"
    ],
    "name:fra_x_preferred":[
        "Champerico"
    ],
    "name:ita_x_preferred":[
        "Champerico"
    ],
    "name:lit_x_preferred":[
        "\u010camperikas"
    ],
    "name:pol_x_preferred":[
        "Champerico"
    ],
    "name:por_x_preferred":[
        "Champerico"
    ],
    "name:spa_x_preferred":[
        "Champerico"
    ],
    "name:swe_x_preferred":[
        "Champerico"
    ],
    "name:ukr_x_preferred":[
        "\u0427\u0430\u043c\u043f\u0435\u0440\u0456\u043a\u043e"
    ],
    "name:zho_x_preferred":[
        "\u9322\u4f69\u91cc\u79d1"
    ],
    "wof:name":"Champerico",
    "wof:placetype":"locality",
    "wof:population":95
},
  "geometry": {"coordinates":[-93.59972,16.37556],"type":"Point"}
}