{
  "type": "Feature",
  "properties": {
    "gn:admin1_code":"14",
    "gn:admin2_code":"33",
    "gn:asciiname":"Cerrito de Villasenor",
    "gn:country_code":"MX",
    "gn:dem":1760,
    "gn:feature_class":"P",
    "gn:feature_code":"PPL",
    "gn:name":"Cerrito de Villase\u00f1or",
    "gn:population":41,
    "gn:timezone":"America/Mexico_City",
    "iso:country":"MX",
    "name:und_x_variant":[
        "Cerrito de Villase\u00f1or"
    ],
    "wof:name":"Cerrito de Villasenor",
    "wof:placetype":"locality",
    "wof:population":41
},
  "geometry": {"coordinates":[-102.105,20.43583],"type":"Point"}
}