{
  "type": "Feature",
  "properties": {
    "gn:admin1_code":"5",
    "gn:admin2_code":"92.0",
    "gn:asciiname":"Chintulito Campamento",
    "gn:country_code":"MX",
    "gn:dem":97,
    "gn:feature_class":"P",
    "gn:feature_code":"PPL",
    "gn:name":"Chintulito Campamento",
    "gn:population":65,
    "gn:timezone":"America/Mexico_City",
    "iso:country":"MX",
    "wof:name":"Chintulito Campamento",
    "wof:placetype":"locality",
    "wof:population":65
},
  "geometry": {"coordinates":[-93.57306,17.22694],"type":"Point"}
}