{
  "type": "Feature",
  "properties": {
    "gn:admin1_code":"20",
    "gn:admin2_code":"159.0",
    "gn:asciiname":"San Lucas",
    "gn:country_code":"MX",
    "gn:dem":1894,
    "gn:feature_class":"P",
    "gn:feature_code":"PPL",
    "gn:name":"San Lucas",
    "gn:population":100,
    "gn:timezone":"America/Mexico_City",
    "iso:country":"MX",
    "wof:name":"San Lucas",
    "wof:placetype":"locality",
    "wof:population":100
},
  "geometry": {"coordinates":[-96.89333000000001,16.25361],"type":"Point"}
}