{
  "type": "Feature",
  "properties": {
    "gn:admin1_code":"26.0",
    "gn:admin2_code":"69.0",
    "gn:asciiname":"El Cebollin",
    "gn:country_code":"MX",
    "gn:dem":1505,
    "gn:feature_class":"P",
    "gn:feature_code":"PPL",
    "gn:name":"El Ceboll\u00edn",
    "gn:population":0,
    "gn:timezone":"America/Chihuahua",
    "iso:country":"MX",
    "name:spa_x_preferred":[
        "El Ceboll\u00edn"
    ],
    "wof:name":"El Cebollin",
    "wof:placetype":"locality"
},
  "geometry": {"coordinates":[-108.58593,28.45681],"type":"Point"}
}