{
  "type": "Feature",
  "properties": {
    "gn:admin1_code":"10",
    "gn:admin2_code":"12",
    "gn:asciiname":"Noria 1847",
    "gn:country_code":"MX",
    "gn:dem":1184,
    "gn:feature_class":"P",
    "gn:feature_code":"PPL",
    "gn:name":"Noria 1847",
    "gn:population":13,
    "gn:timezone":"America/Monterrey",
    "iso:country":"MX",
    "wof:name":"Noria 1847",
    "wof:placetype":"locality",
    "wof:population":13
},
  "geometry": {"coordinates":[-103.46089000000001,25.38362],"type":"Point"}
}