{
  "type": "Feature",
  "properties": {
    "gn:admin1_code":"28",
    "gn:admin2_code":"22.0",
    "gn:asciiname":"Los Fresnos",
    "gn:country_code":"MX",
    "gn:dem":9,
    "gn:feature_class":"P",
    "gn:feature_code":"PPL",
    "gn:name":"Los Fresnos",
    "gn:population":8,
    "gn:timezone":"America/Matamoros",
    "iso:country":"MX",
    "wof:name":"Los Fresnos",
    "wof:placetype":"locality",
    "wof:population":8
},
  "geometry": {"coordinates":[-97.72111,25.51972],"type":"Point"}
}