{
  "type": "Feature",
  "properties": {
    "gn:admin1_code":"24",
    "gn:admin2_code":"55",
    "gn:asciiname":"El Recodo",
    "gn:country_code":"MX",
    "gn:dem":1871,
    "gn:feature_class":"P",
    "gn:feature_code":"PPL",
    "gn:name":"El Recodo",
    "gn:population":10,
    "gn:timezone":"America/Mexico_City",
    "iso:country":"MX",
    "wof:name":"El Recodo",
    "wof:placetype":"locality",
    "wof:population":10
},
  "geometry": {"coordinates":[-100.57250000000001,21.93806],"type":"Point"}
}