{
  "type": "Feature",
  "properties": {
    "gn:admin1_code":"7",
    "gn:admin2_code":"15.0",
    "gn:asciiname":"Rancho Coyotillo",
    "gn:country_code":"MX",
    "gn:dem":280,
    "gn:feature_class":"P",
    "gn:feature_code":"PPL",
    "gn:name":"Rancho Coyotillo",
    "gn:population":0,
    "gn:timezone":"America/Monterrey",
    "iso:country":"MX",
    "wof:name":"Rancho Coyotillo",
    "wof:placetype":"locality"
},
  "geometry": {"coordinates":[-100.59999999999999,27.66667],"type":"Point"}
}