{
  "type": "Feature",
  "properties": {
    "gn:admin1_code":"30.0",
    "gn:admin2_code":"4.0",
    "gn:asciiname":"Gallo Verde",
    "gn:country_code":"MX",
    "gn:dem":39,
    "gn:feature_class":"P",
    "gn:feature_code":"PPL",
    "gn:name":"Gallo Verde",
    "gn:population":0,
    "gn:timezone":"America/Mexico_City",
    "iso:country":"MX",
    "name:spa_x_preferred":[
        "Gallo Verde"
    ],
    "wof:name":"Gallo Verde",
    "wof:placetype":"locality"
},
  "geometry": {"coordinates":[-96.42246,19.48492],"type":"Point"}
}