{
  "type": "Feature",
  "properties": {
    "gn:admin1_code":"25",
    "gn:admin2_code":"17",
    "gn:asciiname":"Severechi",
    "gn:country_code":"MX",
    "gn:dem":728,
    "gn:feature_class":"P",
    "gn:feature_code":"PPL",
    "gn:name":"Severechi",
    "gn:population":17,
    "gn:timezone":"America/Mazatlan",
    "iso:country":"MX",
    "wof:name":"Severechi",
    "wof:placetype":"locality",
    "wof:population":17
},
  "geometry": {"coordinates":[-108.05259,26.18256],"type":"Point"}
}