{
  "type": "Feature",
  "properties": {
    "gn:admin1_code":"26",
    "gn:admin2_code":"8.0",
    "gn:asciiname":"El Oso",
    "gn:country_code":"MX",
    "gn:dem":1288,
    "gn:feature_class":"P",
    "gn:feature_code":"PPL",
    "gn:name":"El Oso",
    "gn:population":0,
    "gn:timezone":"America/Hermosillo",
    "iso:country":"MX",
    "name:spa_x_preferred":[
        "El Oso"
    ],
    "wof:name":"El Oso",
    "wof:placetype":"locality"
},
  "geometry": {"coordinates":[-109.04154,30.02061],"type":"Point"}
}