{
  "type": "Feature",
  "properties": {
    "gn:admin1_code":"28",
    "gn:admin2_code":"2.0",
    "gn:asciiname":"El Dollar",
    "gn:country_code":"MX",
    "gn:dem":2,
    "gn:feature_class":"P",
    "gn:feature_code":"PPL",
    "gn:name":"El Dollar",
    "gn:population":5,
    "gn:timezone":"America/Monterrey",
    "iso:country":"MX",
    "wof:name":"El Dollar",
    "wof:placetype":"locality",
    "wof:population":5
},
  "geometry": {"coordinates":[-97.87555999999999,22.70972],"type":"Point"}
}