{
  "type": "Feature",
  "properties": {
    "gn:admin1_code":"6.0",
    "gn:admin2_code":"52.0",
    "gn:asciiname":"El Dorado",
    "gn:country_code":"MX",
    "gn:dem":1369,
    "gn:feature_class":"P",
    "gn:feature_code":"PPL",
    "gn:name":"El Dorado",
    "gn:population":0,
    "gn:timezone":"America/Ojinaga",
    "iso:country":"MX",
    "name:spa_x_preferred":[
        "El Dorado"
    ],
    "wof:name":"El Dorado",
    "wof:placetype":"locality"
},
  "geometry": {"coordinates":[-104.39519,28.71271],"type":"Point"}
}