{
  "type": "Feature",
  "properties": {
    "gn:admin1_code":"1",
    "gn:admin2_code":"4.0",
    "gn:asciiname":"El Refugio de Providencia",
    "gn:country_code":"MX",
    "gn:dem":1951,
    "gn:feature_class":"P",
    "gn:feature_code":"PPL",
    "gn:name":"El Refugio de Providencia",
    "gn:population":0,
    "gn:timezone":"America/Mexico_City",
    "iso:country":"MX",
    "name:spa_x_preferred":[
        "El Refugio de Providencia"
    ],
    "name:und_x_variant":[
        "Providencia",
        "La Providencia",
        "Refugio de Providencia"
    ],
    "wof:name":"El Refugio de Providencia",
    "wof:placetype":"locality"
},
  "geometry": {"coordinates":[-102.25771,22.34655],"type":"Point"}
}