{
  "type": "Feature",
  "properties": {
    "gn:admin1_code":"28",
    "gn:admin2_code":"22.0",
    "gn:asciiname":"El Galaneno",
    "gn:country_code":"MX",
    "gn:dem":14,
    "gn:feature_class":"P",
    "gn:feature_code":"PPL",
    "gn:name":"El Galane\u00f1o",
    "gn:population":0,
    "gn:timezone":"America/Matamoros",
    "iso:country":"MX",
    "name:spa_x_preferred":[
        "El Galane\u00f1o"
    ],
    "name:und_x_variant":[
        "Galane\u00f1o"
    ],
    "wof:name":"El Galaneno",
    "wof:placetype":"locality"
},
  "geometry": {"coordinates":[-97.54507,25.76091],"type":"Point"}
}