{
  "type": "Feature",
  "properties": {
    "gn:admin1_code":"16",
    "gn:admin2_code":"101",
    "gn:asciiname":"Trojitas (Las Trojas)",
    "gn:country_code":"MX",
    "gn:dem":2040,
    "gn:feature_class":"P",
    "gn:feature_code":"PPL",
    "gn:name":"Trojitas (Las Trojas)",
    "gn:population":25,
    "gn:timezone":"America/Mexico_City",
    "iso:country":"MX",
    "wof:name":"Trojitas (Las Trojas)",
    "wof:placetype":"locality",
    "wof:population":25
},
  "geometry": {"coordinates":[-100.88194,19.62806],"type":"Point"}
}