{
  "type": "Feature",
  "properties": {
    "gn:admin1_code":"7",
    "gn:admin2_code":"12.0",
    "gn:asciiname":"Los Griegos",
    "gn:country_code":"MX",
    "gn:dem":208,
    "gn:feature_class":"P",
    "gn:feature_code":"PPL",
    "gn:name":"Los Griegos",
    "gn:population":0,
    "gn:timezone":"America/Monterrey",
    "iso:country":"MX",
    "name:und_x_variant":[
        "Griego",
        "Los Griegos"
    ],
    "wof:name":"Los Griegos",
    "wof:placetype":"locality"
},
  "geometry": {"coordinates":[-100.34079,28.36616],"type":"Point"}
}