{
  "type": "Feature",
  "properties": {
    "gn:admin1_code":"2",
    "gn:admin2_code":"5.0",
    "gn:asciiname":"Mina de Aceite",
    "gn:country_code":"MX",
    "gn:dem":122,
    "gn:feature_class":"P",
    "gn:feature_code":"PPL",
    "gn:name":"Mina de Aceite",
    "gn:population":4,
    "gn:timezone":"America/Tijuana",
    "iso:country":"MX",
    "wof:name":"Mina de Aceite",
    "wof:placetype":"locality",
    "wof:population":4
},
  "geometry": {"coordinates":[-117.07361000000002,32.40361],"type":"Point"}
}