{
  "type": "Feature",
  "properties": {
    "gn:admin1_code":"6",
    "gn:admin2_code":"36",
    "gn:asciiname":"Los Hangares [Pista Aerea]",
    "gn:country_code":"MX",
    "gn:dem":1393,
    "gn:feature_class":"P",
    "gn:feature_code":"PPL",
    "gn:name":"Los Hangares [Pista A\u00e9rea]",
    "gn:population":11,
    "gn:timezone":"America/Chihuahua",
    "iso:country":"MX",
    "name:und_x_variant":[
        "Los Hangares [Pista A\u00e9rea]"
    ],
    "wof:name":"Los Hangares [Pista Aerea]",
    "wof:placetype":"locality",
    "wof:population":11
},
  "geometry": {"coordinates":[-104.94989,27.12566],"type":"Point"}
}