{
  "type": "Feature",
  "properties": {
    "gn:admin1_code":"17",
    "gn:admin2_code":"6",
    "gn:asciiname":"Campo Carrizal",
    "gn:country_code":"MX",
    "gn:dem":1347,
    "gn:feature_class":"P",
    "gn:feature_code":"PPL",
    "gn:name":"Campo Carrizal",
    "gn:population":24,
    "gn:timezone":"America/Mexico_City",
    "iso:country":"MX",
    "wof:name":"Campo Carrizal",
    "wof:placetype":"locality",
    "wof:population":24
},
  "geometry": {"coordinates":[-98.90582999999999,18.77778],"type":"Point"}
}