{
  "type": "Feature",
  "properties": {
    "gn:admin1_code":"30.0",
    "gn:admin2_code":"61.0",
    "gn:asciiname":"Dos Hermanos",
    "gn:country_code":"MX",
    "gn:dem":35,
    "gn:feature_class":"P",
    "gn:feature_code":"PPL",
    "gn:name":"Dos Hermanos",
    "gn:population":0,
    "gn:timezone":"America/Mexico_City",
    "iso:country":"MX",
    "name:spa_x_preferred":[
        "Dos Hermanos"
    ],
    "wof:name":"Dos Hermanos",
    "wof:placetype":"locality"
},
  "geometry": {"coordinates":[-93.71287,17.56655],"type":"Point"}
}