{
  "type": "Feature",
  "properties": {
    "gn:admin1_code":"12.0",
    "gn:asciiname":"Loma de la Yacua",
    "gn:country_code":"MX",
    "gn:dem":1208,
    "gn:feature_class":"P",
    "gn:feature_code":"PPL",
    "gn:name":"Loma de la Yacua",
    "gn:population":0,
    "gn:timezone":"America/Mexico_City",
    "iso:country":"MX",
    "name:spa_x_preferred":[
        "Loma de la Yacua"
    ],
    "wof:name":"Loma de la Yacua",
    "wof:placetype":"locality"
},
  "geometry": {"coordinates":[-98.37645000000001,17.06119],"type":"Point"}
}