{
  "type": "Feature",
  "properties": {
    "gn:admin1_code":"20",
    "gn:admin2_code":"137",
    "gn:asciiname":"El Aserradero",
    "gn:country_code":"MX",
    "gn:dem":1302,
    "gn:feature_class":"P",
    "gn:feature_code":"PPL",
    "gn:name":"El Aserradero",
    "gn:population":21,
    "gn:timezone":"America/Mexico_City",
    "iso:country":"MX",
    "wof:name":"El Aserradero",
    "wof:placetype":"locality",
    "wof:population":21
},
  "geometry": {"coordinates":[-97.31,16.90306],"type":"Point"}
}