{
  "type": "Feature",
  "properties": {
    "gn:admin1_code":"20.0",
    "gn:asciiname":"Agua Flor Fria de Arriba",
    "gn:country_code":"MX",
    "gn:dem":1847,
    "gn:feature_class":"P",
    "gn:feature_code":"PPL",
    "gn:name":"Agua Flor Fr\u00eda de Arriba",
    "gn:population":0,
    "gn:timezone":"America/Mexico_City",
    "iso:country":"MX",
    "name:spa_x_preferred":[
        "Agua Flor Fr\u00eda de Arriba"
    ],
    "wof:name":"Agua Flor Fria de Arriba",
    "wof:placetype":"locality"
},
  "geometry": {"coordinates":[-96.78663,18.17497],"type":"Point"}
}