{
  "type": "Feature",
  "properties": {
    "gn:admin1_code":"10.0",
    "gn:admin2_code":"2.0",
    "gn:asciiname":"El Molino",
    "gn:country_code":"MX",
    "gn:dem":1581,
    "gn:feature_class":"P",
    "gn:feature_code":"PPL",
    "gn:name":"El Molino",
    "gn:population":0,
    "gn:timezone":"America/Monterrey",
    "iso:country":"MX",
    "name:spa_x_preferred":[
        "El Molino"
    ],
    "wof:name":"El Molino",
    "wof:placetype":"locality"
},
  "geometry": {"coordinates":[-106.52819,25.12475],"type":"Point"}
}