{
  "type": "Feature",
  "properties": {
    "gn:admin1_code":"5",
    "gn:admin2_code":"59",
    "gn:asciiname":"San Antonio del Monte",
    "gn:country_code":"MX",
    "gn:dem":402,
    "gn:feature_class":"P",
    "gn:feature_code":"PPL",
    "gn:name":"San Antonio del Monte",
    "gn:population":34,
    "gn:timezone":"America/Mexico_City",
    "iso:country":"MX",
    "wof:name":"San Antonio del Monte",
    "wof:placetype":"locality",
    "wof:population":34
},
  "geometry": {"coordinates":[-91.37917,16.58833],"type":"Point"}
}