{
  "type": "Feature",
  "properties": {
    "gn:admin1_code":"11",
    "gn:admin2_code":"29",
    "gn:asciiname":"Miramar",
    "gn:country_code":"MX",
    "gn:dem":2042,
    "gn:feature_class":"P",
    "gn:feature_code":"PPL",
    "gn:name":"Miramar",
    "gn:population":39,
    "gn:timezone":"America/Mexico_City",
    "iso:country":"MX",
    "wof:name":"Miramar",
    "wof:placetype":"locality",
    "wof:population":39
},
  "geometry": {"coordinates":[-100.97333,21.35917],"type":"Point"}
}