{
  "type": "Feature",
  "properties": {
    "gn:admin1_code":"14",
    "gn:admin2_code":"21.0",
    "gn:asciiname":"Ninguno [Union Agricola Regional Costa de Jalisco]",
    "gn:country_code":"MX",
    "gn:dem":326,
    "gn:feature_class":"P",
    "gn:feature_code":"PPL",
    "gn:name":"Ninguno [Uni\u00f3n Agr\u00edcola Regional Costa de Jalisco]",
    "gn:population":6,
    "gn:timezone":"America/Mexico_City",
    "iso:country":"MX",
    "name:und_x_variant":[
        "Ninguno [Uni\u00f3n Agr\u00edcola Regional Costa de Jalisco]"
    ],
    "wof:name":"Ninguno [Union Agricola Regional Costa de Jalisco]",
    "wof:placetype":"locality",
    "wof:population":6
},
  "geometry": {"coordinates":[-104.45193999999999,19.62111],"type":"Point"}
}