{
  "type": "Feature",
  "properties": {
    "gn:admin1_code":"16",
    "gn:admin2_code":"12",
    "gn:asciiname":"El Tepehuaje",
    "gn:country_code":"MX",
    "gn:dem":1057,
    "gn:feature_class":"P",
    "gn:feature_code":"PPL",
    "gn:name":"El Tepehuaje",
    "gn:population":10,
    "gn:timezone":"America/Mexico_City",
    "iso:country":"MX",
    "wof:name":"El Tepehuaje",
    "wof:placetype":"locality",
    "wof:population":10
},
  "geometry": {"coordinates":[-102.56028000000001,19.39111],"type":"Point"}
}