{
  "type": "Feature",
  "properties": {
    "gn:admin1_code":"5",
    "gn:admin2_code":"59",
    "gn:asciiname":"Pichucalco",
    "gn:country_code":"MX",
    "gn:dem":536,
    "gn:feature_class":"P",
    "gn:feature_code":"PPL",
    "gn:name":"Pichucalco",
    "gn:population":31,
    "gn:timezone":"America/Mexico_City",
    "iso:country":"MX",
    "name:ceb_x_preferred":[
        "Pichucalco"
    ],
    "name:deu_x_preferred":[
        "Municipio Pichucalco"
    ],
    "name:epo_x_preferred":[
        "Pichucalco"
    ],
    "name:eus_x_preferred":[
        "Pichucalco"
    ],
    "name:fra_x_preferred":[
        "Pichucalco"
    ],
    "name:por_x_preferred":[
        "Pichucalco"
    ],
    "name:rus_x_preferred":[
        "\u041f\u0438\u0447\u0443\u043a\u0430\u043b\u044c\u043a\u043e"
    ],
    "name:sco_x_preferred":[
        "Pichucalco"
    ],
    "name:spa_x_preferred":[
        "Pichucalco"
    ],
    "name:srp_x_preferred":[
        "\u041e\u043f\u0448\u0442\u0438\u043d\u0430 \u041f\u0438\u0447\u0443\u043a\u0430\u043b\u043a\u043e"
    ],
    "name:swe_x_preferred":[
        "Pichucalco"
    ],
    "name:vie_x_preferred":[
        "Pichucalco"
    ],
    "wof:name":"Pichucalco",
    "wof:placetype":"locality",
    "wof:population":31
},
  "geometry": {"coordinates":[-91.67083,16.79],"type":"Point"}
}