{
  "type": "Feature",
  "properties": {
    "gn:admin1_code":"26.0",
    "gn:admin2_code":"59.0",
    "gn:asciiname":"Alamo Gordo",
    "gn:country_code":"MX",
    "gn:dem":1511,
    "gn:feature_class":"P",
    "gn:feature_code":"PPL",
    "gn:name":"\u00c1lamo Gordo",
    "gn:population":0,
    "gn:timezone":"America/Hermosillo",
    "iso:country":"MX",
    "name:spa_x_preferred":[
        "\u00c1lamo Gordo"
    ],
    "wof:name":"Alamo Gordo",
    "wof:placetype":"locality"
},
  "geometry": {"coordinates":[-110.39198,31.27632],"type":"Point"}
}