{
  "type": "Feature",
  "properties": {
    "gn:admin1_code":"30.0",
    "gn:admin2_code":"129.0",
    "gn:asciiname":"La Martinica",
    "gn:country_code":"MX",
    "gn:dem":61,
    "gn:feature_class":"P",
    "gn:feature_code":"PPL",
    "gn:name":"La Martinica",
    "gn:population":4,
    "gn:timezone":"America/Mexico_City",
    "iso:country":"MX",
    "name:spa_x_preferred":[
        "La Martinica"
    ],
    "wof:name":"La Martinica",
    "wof:placetype":"locality",
    "wof:population":4
},
  "geometry": {"coordinates":[-98.32624,21.27183],"type":"Point"}
}