{
  "type": "Feature",
  "properties": {
    "gn:admin1_code":"28",
    "gn:admin2_code":"32",
    "gn:asciiname":"Joel Garza",
    "gn:country_code":"MX",
    "gn:dem":69,
    "gn:feature_class":"P",
    "gn:feature_code":"PPL",
    "gn:name":"Joel Garza",
    "gn:population":10,
    "gn:timezone":"America/Matamoros",
    "iso:country":"MX",
    "wof:name":"Joel Garza",
    "wof:placetype":"locality",
    "wof:population":10
},
  "geometry": {"coordinates":[-98.26528,25.78333],"type":"Point"}
}