{
  "type": "Feature",
  "properties": {
    "gn:admin1_code":"5",
    "gn:admin2_code":"9.0",
    "gn:asciiname":"El Engano",
    "gn:country_code":"MX",
    "gn:dem":65,
    "gn:feature_class":"P",
    "gn:feature_code":"PPL",
    "gn:name":"El Enga\u00f1o",
    "gn:population":5,
    "gn:timezone":"America/Mexico_City",
    "iso:country":"MX",
    "name:und_x_variant":[
        "El Enga\u00f1o"
    ],
    "wof:name":"El Engano",
    "wof:placetype":"locality",
    "wof:population":5
},
  "geometry": {"coordinates":[-93.96778,16.28361],"type":"Point"}
}