{
  "type": "Feature",
  "properties": {
    "gn:admin1_code":"30",
    "gn:admin2_code":"116.0",
    "gn:asciiname":"Correa",
    "gn:cc2":"MX",
    "gn:country_code":"MX",
    "gn:dem":49,
    "gn:feature_class":"P",
    "gn:feature_code":"PPL",
    "gn:name":"Correa",
    "gn:population":331,
    "gn:timezone":"America/Mexico_City",
    "iso:country":"MX",
    "name:ceb_x_preferred":[
        "Correa"
    ],
    "name:deu_x_preferred":[
        "Correa"
    ],
    "name:fra_x_preferred":[
        "Correa"
    ],
    "name:heb_x_preferred":[
        "\u05e7\u05d5\u05e8\u05d0\u05d4"
    ],
    "name:ita_x_preferred":[
        "Correa"
    ],
    "name:jpn_x_preferred":[
        "\u30b3\u30ec\u30a2"
    ],
    "name:nld_x_preferred":[
        "Correa"
    ],
    "name:por_x_preferred":[
        "Correa"
    ],
    "name:rus_x_preferred":[
        "\u041a\u043e\u0440\u0440\u0435\u0430"
    ],
    "name:spa_x_preferred":[
        "Correa"
    ],
    "name:swe_x_preferred":[
        "Correa"
    ],
    "name:ukr_x_preferred":[
        "\u041a\u043e\u0440\u0440\u0435\u044f"
    ],
    "name:und_x_variant":[
        "Correo",
        "Correa"
    ],
    "wof:name":"Correa",
    "wof:placetype":"locality",
    "wof:population":331
},
  "geometry": {"coordinates":[-94.89221999999999,17.86332999999999],"type":"Point"}
}