{
  "type": "Feature",
  "properties": {
    "gn:admin1_code":"25",
    "gn:admin2_code":"1.0",
    "gn:asciiname":"Ejido Zapotillo Numero Uno",
    "gn:country_code":"MX",
    "gn:dem":20,
    "gn:feature_class":"P",
    "gn:feature_code":"PPL",
    "gn:name":"Ejido Zapotillo N\u00famero Uno",
    "gn:population":0,
    "gn:timezone":"America/Mazatlan",
    "iso:country":"MX",
    "name:spa_x_preferred":[
        "Zapotillo Viejo"
    ],
    "name:spa_x_variant":[
        "Zapotillo Uno",
        "Ejido Zapotillo N\u00famero Uno"
    ],
    "name:und_x_variant":[
        "Zapotillo"
    ],
    "wof:name":"Ejido Zapotillo Numero Uno",
    "wof:placetype":"locality"
},
  "geometry": {"coordinates":[-108.99636,25.92666],"type":"Point"}
}