{
  "type": "Feature",
  "properties": {
    "gn:admin1_code":"5",
    "gn:admin2_code":"59.0",
    "gn:asciiname":"Rancho Desempeno",
    "gn:country_code":"MX",
    "gn:dem":82,
    "gn:feature_class":"P",
    "gn:feature_code":"PPL",
    "gn:name":"Rancho Desempe\u00f1o",
    "gn:population":0,
    "gn:timezone":"America/Mexico_City",
    "iso:country":"MX",
    "name:spa_x_preferred":[
        "Rancho Desempe\u00f1o"
    ],
    "name:und_x_variant":[
        "Desempe\u00f1o"
    ],
    "wof:name":"Rancho Desempeno",
    "wof:placetype":"locality"
},
  "geometry": {"coordinates":[-91.21731,17.06253],"type":"Point"}
}