{
  "type": "Feature",
  "properties": {
    "gn:admin1_code":"13",
    "gn:admin2_code":"46.0",
    "gn:asciiname":"Guayalan",
    "gn:cc2":"MX",
    "gn:country_code":"MX",
    "gn:dem":180,
    "gn:feature_class":"P",
    "gn:feature_code":"PPL",
    "gn:name":"Guayalan",
    "gn:population":0,
    "gn:timezone":"America/Mexico_City",
    "iso:country":"MX",
    "name:und_x_variant":[
        "Guayalar",
        "Guayalan"
    ],
    "wof:name":"Guayalan",
    "wof:placetype":"locality"
},
  "geometry": {"coordinates":[-98.61667,21.31667],"type":"Point"}
}