{
  "type": "Feature",
  "properties": {
    "gn:admin1_code":"30",
    "gn:admin2_code":"61.0",
    "gn:asciiname":"San Miguel de Allende",
    "gn:country_code":"MX",
    "gn:dem":39,
    "gn:feature_class":"P",
    "gn:feature_code":"PPL",
    "gn:name":"San Miguel de Allende",
    "gn:population":357,
    "gn:timezone":"America/Mexico_City",
    "iso:country":"MX",
    "wof:name":"San Miguel de Allende",
    "wof:placetype":"locality",
    "wof:population":357
},
  "geometry": {"coordinates":[-93.93194,17.50944],"type":"Point"}
}