{
  "type": "Feature",
  "properties": {
    "gn:admin1_code":"16.0",
    "gn:admin2_code":"32.0",
    "gn:asciiname":"Guinicuicho",
    "gn:country_code":"MX",
    "gn:dem":2412,
    "gn:feature_class":"P",
    "gn:feature_code":"PPL",
    "gn:name":"Guinicuicho",
    "gn:population":0,
    "gn:timezone":"America/Mexico_City",
    "iso:country":"MX",
    "wof:name":"Guinicuicho",
    "wof:placetype":"locality"
},
  "geometry": {"coordinates":[-101.75,19.66667],"type":"Point"}
}