{
  "type": "Feature",
  "properties": {
    "gn:admin1_code":"19",
    "gn:admin2_code":"13.0",
    "gn:asciiname":"Las Hormigas",
    "gn:country_code":"MX",
    "gn:dem":112,
    "gn:feature_class":"P",
    "gn:feature_code":"PPL",
    "gn:name":"Las Hormigas",
    "gn:population":0,
    "gn:timezone":"America/Monterrey",
    "iso:country":"MX",
    "name:spa_x_preferred":[
        "Las Hormigas"
    ],
    "wof:name":"Las Hormigas",
    "wof:placetype":"locality"
},
  "geometry": {"coordinates":[-98.66931,25.43641],"type":"Point"}
}