{
  "type": "Feature",
  "properties": {
    "gn:admin1_code":"15.0",
    "gn:asciiname":"El Cerrito",
    "gn:country_code":"MX",
    "gn:dem":2414,
    "gn:feature_class":"P",
    "gn:feature_code":"PPL",
    "gn:name":"El Cerrito",
    "gn:population":0,
    "gn:timezone":"America/Mexico_City",
    "iso:country":"MX",
    "name:spa_x_preferred":[
        "El Cerrito"
    ],
    "wof:name":"El Cerrito",
    "wof:placetype":"locality"
},
  "geometry": {"coordinates":[-99.15675,19.5832],"type":"Point"}
}