{
  "type": "Feature",
  "properties": {
    "gn:admin1_code":"14",
    "gn:admin2_code":"46.0",
    "gn:asciiname":"Santa Martha (Los Canos)",
    "gn:country_code":"MX",
    "gn:dem":1831,
    "gn:feature_class":"P",
    "gn:feature_code":"PPL",
    "gn:name":"Santa Martha (Los Ca\u00f1os)",
    "gn:population":124,
    "gn:timezone":"America/Mexico_City",
    "iso:country":"MX",
    "name:und_x_variant":[
        "Santa Martha (Los Ca\u00f1os)"
    ],
    "wof:name":"Santa Martha (Los Canos)",
    "wof:placetype":"locality",
    "wof:population":124
},
  "geometry": {"coordinates":[-102.41806,21.20694],"type":"Point"}
}