{
  "type": "Feature",
  "properties": {
    "gn:admin1_code":"28",
    "gn:admin2_code":"39.0",
    "gn:asciiname":"San Jose de las Flores",
    "gn:country_code":"MX",
    "gn:dem":1374,
    "gn:feature_class":"P",
    "gn:feature_code":"PPL",
    "gn:name":"San Jose de las Flores",
    "gn:population":0,
    "gn:timezone":"America/Monterrey",
    "iso:country":"MX",
    "name:spa_x_preferred":[
        "San Jose de las Flores"
    ],
    "name:und_x_variant":[
        "San Jos\u00e9 de las Flores"
    ],
    "wof:name":"San Jose de las Flores",
    "wof:placetype":"locality"
},
  "geometry": {"coordinates":[-99.63151000000001,22.92256],"type":"Point"}
}