{
  "type": "Feature",
  "properties": {
    "gn:admin1_code":"28.0",
    "gn:admin2_code":"27.0",
    "gn:asciiname":"Los Garza (Los Toros)",
    "gn:country_code":"MX",
    "gn:dem":174,
    "gn:feature_class":"P",
    "gn:feature_code":"PPL",
    "gn:name":"Los Garza (Los Toros)",
    "gn:population":4,
    "gn:timezone":"America/Matamoros",
    "iso:country":"MX",
    "name:spa_x_preferred":[
        "Los Garza"
    ],
    "name:und_x_variant":[
        "El Toro"
    ],
    "wof:name":"Los Garza (Los Toros)",
    "wof:placetype":"locality",
    "wof:population":4
},
  "geometry": {"coordinates":[-99.60889,27.37889],"type":"Point"}
}