{
  "type": "Feature",
  "properties": {
    "gn:admin1_code":"32",
    "gn:admin2_code":"21.0",
    "gn:asciiname":"El Canon de la Matrera",
    "gn:country_code":"MX",
    "gn:dem":1325,
    "gn:feature_class":"P",
    "gn:feature_code":"PPL",
    "gn:name":"El Ca\u00f1\u00f3n de la Matrera",
    "gn:population":0,
    "gn:timezone":"America/Mexico_City",
    "iso:country":"MX",
    "name:spa_x_preferred":[
        "El Ca\u00f1\u00f3n de la Matrera"
    ],
    "wof:name":"El Canon de la Matrera",
    "wof:placetype":"locality"
},
  "geometry": {"coordinates":[-104.13048000000001,22.98069],"type":"Point"}
}