{
  "type": "Feature",
  "properties": {
    "gn:admin1_code":"26",
    "gn:admin2_code":"49.0",
    "gn:asciiname":"El Nanchi",
    "gn:country_code":"MX",
    "gn:dem":218,
    "gn:feature_class":"P",
    "gn:feature_code":"PPL",
    "gn:name":"El Nanchi",
    "gn:population":0,
    "gn:timezone":"America/Hermosillo",
    "iso:country":"MX",
    "name:spa_x_preferred":[
        "El Nanchi"
    ],
    "name:und_x_variant":[
        "El Nanche"
    ],
    "wof:name":"El Nanchi",
    "wof:placetype":"locality"
},
  "geometry": {"coordinates":[-109.12057,27.43015],"type":"Point"}
}