{
  "type": "Feature",
  "properties": {
    "gn:admin1_code":"14.0",
    "gn:admin2_code":"28.0",
    "gn:asciiname":"Cuautla",
    "gn:country_code":"MX",
    "gn:dem":1719,
    "gn:feature_class":"P",
    "gn:feature_code":"PPL",
    "gn:name":"Cuautla",
    "gn:population":1253,
    "gn:timezone":"America/Mexico_City",
    "iso:country":"MX",
    "wof:name":"Cuautla",
    "wof:placetype":"locality",
    "wof:population":1253
},
  "geometry": {"coordinates":[-104.4075,20.20139],"type":"Point"}
}