{
  "type": "Feature",
  "properties": {
    "gn:admin1_code":"7",
    "gn:admin2_code":"35",
    "gn:asciiname":"La Colonia",
    "gn:country_code":"MX",
    "gn:dem":1483,
    "gn:feature_class":"P",
    "gn:feature_code":"PPL",
    "gn:name":"La Colonia",
    "gn:population":43,
    "gn:timezone":"America/Monterrey",
    "iso:country":"MX",
    "wof:name":"La Colonia",
    "wof:placetype":"locality",
    "wof:population":43
},
  "geometry": {"coordinates":[-103.10171,25.07862],"type":"Point"}
}