{
  "type": "Feature",
  "properties": {
    "gn:admin1_code":"14",
    "gn:admin2_code":"69.0",
    "gn:asciiname":"La Tocusera",
    "gn:country_code":"MX",
    "gn:dem":1232,
    "gn:feature_class":"P",
    "gn:feature_code":"PPL",
    "gn:name":"La Tocusera",
    "gn:population":5,
    "gn:timezone":"America/Mexico_City",
    "iso:country":"MX",
    "wof:name":"La Tocusera",
    "wof:placetype":"locality",
    "wof:population":5
},
  "geometry": {"coordinates":[-102.88694,19.65222],"type":"Point"}
}