{
  "type": "Feature",
  "properties": {
    "gn:admin1_code":"12",
    "gn:asciiname":"Tlanipatla",
    "gn:country_code":"MX",
    "gn:dem":1104,
    "gn:feature_class":"P",
    "gn:feature_code":"PPL",
    "gn:name":"Tlanipatla",
    "gn:population":0,
    "gn:timezone":"America/Mexico_City",
    "iso:country":"MX",
    "name:spa_x_preferred":[
        "Tlanipatla"
    ],
    "wof:name":"Tlanipatla",
    "wof:placetype":"locality"
},
  "geometry": {"coordinates":[-98.76678,18.01727],"type":"Point"}
}