{
  "type": "Feature",
  "properties": {
    "gn:admin1_code":"15",
    "gn:admin2_code":"117.0",
    "gn:asciiname":"Piedra Parada",
    "gn:country_code":"MX",
    "gn:dem":1723,
    "gn:feature_class":"P",
    "gn:feature_code":"PPL",
    "gn:name":"Piedra Parada",
    "gn:population":572,
    "gn:timezone":"America/Mexico_City",
    "iso:country":"MX",
    "wof:name":"Piedra Parada",
    "wof:placetype":"locality",
    "wof:population":572
},
  "geometry": {"coordinates":[-99.73454,18.77904],"type":"Point"}
}