{
  "type": "Feature",
  "properties": {
    "gn:admin1_code":"30",
    "gn:admin2_code":"195.0",
    "gn:asciiname":"Tenexapa",
    "gn:country_code":"MX",
    "gn:dem":2410,
    "gn:feature_class":"P",
    "gn:feature_code":"PPL",
    "gn:name":"Tenexapa",
    "gn:population":427,
    "gn:timezone":"America/Mexico_City",
    "iso:country":"MX",
    "wof:name":"Tenexapa",
    "wof:placetype":"locality",
    "wof:population":427
},
  "geometry": {"coordinates":[-97.15278000000001,18.62694],"type":"Point"}
}