{
  "type": "Feature",
  "properties": {
    "gn:admin1_code":"13",
    "gn:admin2_code":"14.0",
    "gn:asciiname":"Amatepetl",
    "gn:country_code":"MX",
    "gn:dem":1008,
    "gn:feature_class":"P",
    "gn:feature_code":"PPL",
    "gn:name":"Amat\u00e9petl",
    "gn:population":6,
    "gn:timezone":"America/Mexico_City",
    "iso:country":"MX",
    "name:und_x_variant":[
        "Amat\u00e9petl"
    ],
    "wof:name":"Amatepetl",
    "wof:placetype":"locality",
    "wof:population":6
},
  "geometry": {"coordinates":[-98.60984000000001,20.89299],"type":"Point"}
}