{
  "type": "Feature",
  "properties": {
    "gn:admin1_code":"30",
    "gn:admin2_code":"156",
    "gn:asciiname":"El Boqueron",
    "gn:country_code":"MX",
    "gn:dem":1564,
    "gn:feature_class":"P",
    "gn:feature_code":"PPL",
    "gn:name":"El Boquer\u00f3n",
    "gn:population":16,
    "gn:timezone":"America/Mexico_City",
    "iso:country":"MX",
    "name:und_x_variant":[
        "El Boquer\u00f3n"
    ],
    "wof:name":"El Boqueron",
    "wof:placetype":"locality",
    "wof:population":16
},
  "geometry": {"coordinates":[-97.06278,19.75611],"type":"Point"}
}