{
  "type": "Feature",
  "properties": {
    "gn:admin1_code":"19",
    "gn:admin2_code":"45",
    "gn:asciiname":"Los Pujidos [Granja Porcicola]",
    "gn:country_code":"MX",
    "gn:dem":470,
    "gn:feature_class":"P",
    "gn:feature_code":"PPL",
    "gn:name":"Los Pujidos [Granja Porc\u00edcola]",
    "gn:population":13,
    "gn:timezone":"America/Monterrey",
    "iso:country":"MX",
    "name:und_x_variant":[
        "Los Pujidos [Granja Porc\u00edcola]"
    ],
    "wof:name":"Los Pujidos [Granja Porcicola]",
    "wof:placetype":"locality",
    "wof:population":13
},
  "geometry": {"coordinates":[-100.31004,26.06227],"type":"Point"}
}