{
  "type": "Feature",
  "properties": {
    "gn:admin1_code":"6",
    "gn:admin2_code":"8",
    "gn:asciiname":"Sapareachi",
    "gn:country_code":"MX",
    "gn:dem":1692,
    "gn:feature_class":"P",
    "gn:feature_code":"PPL",
    "gn:name":"Sapareachi",
    "gn:population":52,
    "gn:timezone":"America/Chihuahua",
    "iso:country":"MX",
    "wof:name":"Sapareachi",
    "wof:placetype":"locality",
    "wof:population":52
},
  "geometry": {"coordinates":[-107.70769,27.19104],"type":"Point"}
}