{
  "type": "Feature",
  "properties": {
    "gn:admin1_code":"30",
    "gn:admin2_code":"121.0",
    "gn:asciiname":"Jagueey Prieto",
    "gn:country_code":"MX",
    "gn:dem":49,
    "gn:feature_class":"P",
    "gn:feature_code":"PPL",
    "gn:name":"Jag\u00fcey Prieto",
    "gn:population":0,
    "gn:timezone":"America/Mexico_City",
    "iso:country":"MX",
    "wof:name":"Jagueey Prieto",
    "wof:placetype":"locality"
},
  "geometry": {"coordinates":[-97.98333,21.85],"type":"Point"}
}