{
  "type": "Feature",
  "properties": {
    "gn:admin1_code":"24",
    "gn:admin2_code":"55",
    "gn:asciiname":"El Panal",
    "gn:country_code":"MX",
    "gn:dem":1976,
    "gn:feature_class":"P",
    "gn:feature_code":"PPL",
    "gn:name":"El Panal",
    "gn:population":11,
    "gn:timezone":"America/Mexico_City",
    "iso:country":"MX",
    "wof:name":"El Panal",
    "wof:placetype":"locality",
    "wof:population":11
},
  "geometry": {"coordinates":[-100.71389000000001,21.95444],"type":"Point"}
}