{
  "type": "Feature",
  "properties": {
    "gn:admin1_code":"12.0",
    "gn:admin2_code":"48.0",
    "gn:asciiname":"Temixco de las Palmas",
    "gn:country_code":"MX",
    "gn:dem":654,
    "gn:feature_class":"P",
    "gn:feature_code":"PPL",
    "gn:name":"Temixco de las Palmas",
    "gn:population":0,
    "gn:timezone":"America/Mexico_City",
    "iso:country":"MX",
    "name:spa_x_preferred":[
        "Temixco de las Palmas"
    ],
    "wof:name":"Temixco de las Palmas",
    "wof:placetype":"locality"
},
  "geometry": {"coordinates":[-101.0946,17.70328],"type":"Point"}
}