{
  "type": "Feature",
  "properties": {
    "gn:admin1_code":"26",
    "gn:admin2_code":"18.0",
    "gn:asciiname":"Francisco Pacheco Valenzuela",
    "gn:country_code":"MX",
    "gn:dem":10,
    "gn:feature_class":"P",
    "gn:feature_code":"PPL",
    "gn:name":"Francisco Pacheco Valenzuela",
    "gn:population":6,
    "gn:timezone":"America/Hermosillo",
    "iso:country":"MX",
    "wof:name":"Francisco Pacheco Valenzuela",
    "wof:placetype":"locality",
    "wof:population":6
},
  "geometry": {"coordinates":[-109.95139,27.16417],"type":"Point"}
}