{
  "type": "Feature",
  "properties": {
    "gn:admin1_code":"14",
    "gn:admin2_code":"79.0",
    "gn:asciiname":"Ejido Primero de Febrero",
    "gn:country_code":"MX",
    "gn:dem":1522,
    "gn:feature_class":"P",
    "gn:feature_code":"PPL",
    "gn:name":"Ejido Primero de Febrero",
    "gn:population":0,
    "gn:timezone":"America/Mexico_City",
    "iso:country":"MX",
    "name:spa_x_preferred":[
        "Ejido Primero de Febrero"
    ],
    "name:und_x_variant":[
        "San Nicol\u00e1s"
    ],
    "wof:name":"Ejido Primero de Febrero",
    "wof:placetype":"locality"
},
  "geometry": {"coordinates":[-103.49303,19.8151],"type":"Point"}
}