{
  "type": "Feature",
  "properties": {
    "gn:admin1_code":"22.0",
    "gn:admin2_code":"5.0",
    "gn:asciiname":"Amarral",
    "gn:country_code":"MX",
    "gn:dem":2047,
    "gn:feature_class":"P",
    "gn:feature_code":"PPL",
    "gn:name":"Amarral",
    "gn:population":0,
    "gn:timezone":"America/Mexico_City",
    "iso:country":"MX",
    "name:spa_x_preferred":[
        "Amarral"
    ],
    "wof:name":"Amarral",
    "wof:placetype":"locality"
},
  "geometry": {"coordinates":[-100.06571,20.65714],"type":"Point"}
}