{
  "type": "Feature",
  "properties": {
    "gn:admin1_code":"12.0",
    "gn:admin2_code":"4.0",
    "gn:asciiname":"Lomasoyatl",
    "gn:country_code":"MX",
    "gn:dem":1682,
    "gn:feature_class":"P",
    "gn:feature_code":"PPL",
    "gn:name":"Lomasoyatl",
    "gn:population":0,
    "gn:timezone":"America/Mexico_City",
    "iso:country":"MX",
    "name:spa_x_preferred":[
        "Lomasoyatl"
    ],
    "wof:name":"Lomasoyatl",
    "wof:placetype":"locality"
},
  "geometry": {"coordinates":[-98.46123,17.35423],"type":"Point"}
}