{
  "type": "Feature",
  "properties": {
    "gn:admin1_code":"6",
    "gn:admin2_code":"63.0",
    "gn:asciiname":"Tejibechi",
    "gn:country_code":"MX",
    "gn:dem":2505,
    "gn:feature_class":"P",
    "gn:feature_code":"PPL",
    "gn:name":"Tejibechi",
    "gn:population":0,
    "gn:timezone":"America/Chihuahua",
    "iso:country":"MX",
    "name:spa_x_preferred":[
        "Tejibechi"
    ],
    "wof:name":"Tejibechi",
    "wof:placetype":"locality"
},
  "geometry": {"coordinates":[-108.05867000000001,28.44661],"type":"Point"}
}