{
  "type": "Feature",
  "properties": {
    "gn:admin1_code":"26.0",
    "gn:admin2_code":"30.0",
    "gn:asciiname":"Comita",
    "gn:cc2":"MX",
    "gn:country_code":"MX",
    "gn:dem":195,
    "gn:feature_class":"P",
    "gn:feature_code":"PPL",
    "gn:name":"Comita",
    "gn:population":0,
    "gn:timezone":"America/Hermosillo",
    "iso:country":"MX",
    "name:und_x_variant":[
        "Rancho Comito",
        "Comita"
    ],
    "wof:name":"Comita",
    "wof:placetype":"locality"
},
  "geometry": {"coordinates":[-111.45,29.25],"type":"Point"}
}