{
  "type": "Feature",
  "properties": {
    "gn:admin1_code":"15",
    "gn:admin2_code":"107.0",
    "gn:asciiname":"San Miguel",
    "gn:country_code":"MX",
    "gn:dem":1620,
    "gn:feature_class":"P",
    "gn:feature_code":"PPL",
    "gn:name":"San Miguel",
    "gn:population":254,
    "gn:timezone":"America/Mexico_City",
    "iso:country":"MX",
    "wof:name":"San Miguel",
    "wof:placetype":"locality",
    "wof:population":254
},
  "geometry": {"coordinates":[-99.66906,18.79034],"type":"Point"}
}