{
  "type": "Feature",
  "properties": {
    "gn:admin1_code":"22",
    "gn:admin2_code":"17.0",
    "gn:asciiname":"Los Arquitos",
    "gn:country_code":"MX",
    "gn:dem":1904,
    "gn:feature_class":"P",
    "gn:feature_code":"PPL",
    "gn:name":"Los Arquitos",
    "gn:population":96,
    "gn:timezone":"America/Mexico_City",
    "iso:country":"MX",
    "wof:name":"Los Arquitos",
    "wof:placetype":"locality",
    "wof:population":96
},
  "geometry": {"coordinates":[-99.93222,20.57333],"type":"Point"}
}