{
  "type": "Feature",
  "properties": {
    "gn:admin1_code":"30",
    "gn:admin2_code":"189.0",
    "gn:asciiname":"Alto de San Lorenzo",
    "gn:cc2":"MX",
    "gn:country_code":"MX",
    "gn:dem":21,
    "gn:feature_class":"P",
    "gn:feature_code":"PPL",
    "gn:name":"Alto de San Lorenzo",
    "gn:population":123,
    "gn:timezone":"America/Mexico_City",
    "iso:country":"MX",
    "name:und_x_variant":[
        "San Lorenzo",
        "Paso de San Lorenzo",
        "Paso de Lorenzo"
    ],
    "wof:name":"Alto de San Lorenzo",
    "wof:placetype":"locality",
    "wof:population":123
},
  "geometry": {"coordinates":[-97.44889000000001,21.07806],"type":"Point"}
}