{
  "type": "Feature",
  "properties": {
    "gn:admin1_code":"11.0",
    "gn:admin2_code":"5.0",
    "gn:asciiname":"Caleras de Obrajuelo",
    "gn:country_code":"MX",
    "gn:dem":1793,
    "gn:feature_class":"P",
    "gn:feature_code":"PPL",
    "gn:name":"Caleras de Obrajuelo",
    "gn:population":0,
    "gn:timezone":"America/Mexico_City",
    "iso:country":"MX",
    "name:spa_x_preferred":[
        "Caleras de Obrajuelo"
    ],
    "name:spa_x_variant":[
        "Mariscala"
    ],
    "wof:name":"Caleras de Obrajuelo",
    "wof:placetype":"locality"
},
  "geometry": {"coordinates":[-100.55654,20.56866],"type":"Point"}
}