{
  "type": "Feature",
  "properties": {
    "gn:admin1_code":"6",
    "gn:admin2_code":"40.0",
    "gn:asciiname":"Corral Quemado",
    "gn:country_code":"MX",
    "gn:dem":1950,
    "gn:feature_class":"P",
    "gn:feature_code":"PPL",
    "gn:name":"Corral Quemado",
    "gn:population":0,
    "gn:timezone":"America/Chihuahua",
    "iso:country":"MX",
    "name:spa_x_preferred":[
        "Corral Quemado"
    ],
    "wof:name":"Corral Quemado",
    "wof:placetype":"locality"
},
  "geometry": {"coordinates":[-108.24988999999999,28.95064],"type":"Point"}
}