{
  "type": "Feature",
  "properties": {
    "gn:admin1_code":"16",
    "gn:admin2_code":"9.0",
    "gn:asciiname":"Araparicuaro",
    "gn:country_code":"MX",
    "gn:dem":1153,
    "gn:feature_class":"P",
    "gn:feature_code":"PPL",
    "gn:name":"Arapar\u00edcuaro",
    "gn:population":360,
    "gn:timezone":"America/Mexico_City",
    "iso:country":"MX",
    "name:und_x_variant":[
        "Arapar\u00edcuaro"
    ],
    "wof:name":"Araparicuaro",
    "wof:placetype":"locality",
    "wof:population":360
},
  "geometry": {"coordinates":[-101.79861,19.21806],"type":"Point"}
}