{
  "type": "Feature",
  "properties": {
    "gn:admin1_code":"32",
    "gn:admin2_code":"7.0",
    "gn:asciiname":"El Coleadero",
    "gn:country_code":"MX",
    "gn:dem":1865,
    "gn:feature_class":"P",
    "gn:feature_code":"PPL",
    "gn:name":"El Coleadero",
    "gn:population":7,
    "gn:timezone":"America/Mexico_City",
    "iso:country":"MX",
    "name:spa_x_preferred":[
        "El Coleadero"
    ],
    "wof:name":"El Coleadero",
    "wof:placetype":"locality",
    "wof:population":7
},
  "geometry": {"coordinates":[-101.36333,24.60917],"type":"Point"}
}