{
  "type": "Feature",
  "properties": {
    "gn:admin1_code":"30",
    "gn:admin2_code":"183.0",
    "gn:asciiname":"Tomata",
    "gn:country_code":"MX",
    "gn:dem":601,
    "gn:feature_class":"P",
    "gn:feature_code":"PPL",
    "gn:name":"Tomata",
    "gn:population":0,
    "gn:timezone":"America/Mexico_City",
    "iso:country":"MX",
    "name:spa_x_preferred":[
        "Tomata"
    ],
    "wof:name":"Tomata",
    "wof:placetype":"locality"
},
  "geometry": {"coordinates":[-97.22302999999999,19.92506],"type":"Point"}
}