{
  "type": "Feature",
  "properties": {
    "gn:admin1_code":"20",
    "gn:admin2_code":"482.0",
    "gn:asciiname":"Corralero",
    "gn:country_code":"MX",
    "gn:dem":6,
    "gn:feature_class":"P",
    "gn:feature_code":"PPL",
    "gn:name":"Corralero",
    "gn:population":0,
    "gn:timezone":"America/Mexico_City",
    "iso:country":"MX",
    "name:und_x_variant":[
        "El Corralero",
        "Corralero"
    ],
    "wof:name":"Corralero",
    "wof:placetype":"locality"
},
  "geometry": {"coordinates":[-98.18952,16.23846],"type":"Point"}
}