{
  "type": "Feature",
  "properties": {
    "gn:admin1_code":"1.0",
    "gn:admin2_code":"1.0",
    "gn:asciiname":"San Geronimo",
    "gn:country_code":"MX",
    "gn:dem":1935,
    "gn:feature_class":"P",
    "gn:feature_code":"PPL",
    "gn:name":"San Ger\u00f3nimo",
    "gn:population":5,
    "gn:timezone":"America/Mexico_City",
    "iso:country":"MX",
    "name:fra_x_preferred":[
        "V\u00e9n\u00e9rable G\u00e9ronimo"
    ],
    "wof:name":"San Geronimo",
    "wof:placetype":"locality",
    "wof:population":5
},
  "geometry": {"coordinates":[-102.41667,21.795],"type":"Point"}
}