{
  "type": "Feature",
  "properties": {
    "gn:admin1_code":"5",
    "gn:admin2_code":"13.0",
    "gn:asciiname":"Guayaba Lagunita",
    "gn:country_code":"MX",
    "gn:dem":1452,
    "gn:feature_class":"P",
    "gn:feature_code":"PPL",
    "gn:name":"Guayaba Lagunita",
    "gn:population":6,
    "gn:timezone":"America/Mexico_City",
    "iso:country":"MX",
    "wof:name":"Guayaba Lagunita",
    "wof:placetype":"locality",
    "wof:population":6
},
  "geometry": {"coordinates":[-92.88596,16.97361],"type":"Point"}
}