{
  "type": "Feature",
  "properties": {
    "gn:admin1_code":"12",
    "gn:admin2_code":"1.0",
    "gn:asciiname":"Cerro de Piedra",
    "gn:country_code":"MX",
    "gn:dem":45,
    "gn:feature_class":"P",
    "gn:feature_code":"PPL",
    "gn:name":"Cerro de Piedra",
    "gn:population":1487,
    "gn:timezone":"America/Mexico_City",
    "iso:country":"MX",
    "name:spa_x_preferred":[
        "Cerro de Piedra"
    ],
    "wof:name":"Cerro de Piedra",
    "wof:placetype":"locality",
    "wof:population":1487
},
  "geometry": {"coordinates":[-99.63037,16.77646],"type":"Point"}
}