{
  "type": "Feature",
  "properties": {
    "gn:admin1_code":"7",
    "gn:admin2_code":"30.0",
    "gn:asciiname":"Tinajuela",
    "gn:country_code":"MX",
    "gn:dem":1998,
    "gn:feature_class":"P",
    "gn:feature_code":"PPL",
    "gn:name":"Tinajuela",
    "gn:population":0,
    "gn:timezone":"America/Monterrey",
    "iso:country":"MX",
    "name:spa_x_preferred":[
        "Tinajuela"
    ],
    "wof:name":"Tinajuela",
    "wof:placetype":"locality"
},
  "geometry": {"coordinates":[-101.32890999999999,25.07696],"type":"Point"}
}