{
  "type": "Feature",
  "properties": {
    "gn:admin1_code":"31.0",
    "gn:asciiname":"Diana Milan",
    "gn:country_code":"MX",
    "gn:dem":1,
    "gn:feature_class":"P",
    "gn:feature_code":"PPL",
    "gn:name":"Diana Mil\u00e1n",
    "gn:population":0,
    "gn:timezone":"America/Merida",
    "iso:country":"MX",
    "name:spa_x_preferred":[
        "Diana Mil\u00e1n"
    ],
    "wof:name":"Diana Milan",
    "wof:placetype":"locality"
},
  "geometry": {"coordinates":[-89.56433,21.30185],"type":"Point"}
}