{
  "type": "Feature",
  "properties": {
    "gn:admin1_code":"3",
    "gn:admin2_code":"9.0",
    "gn:asciiname":"San Javier",
    "gn:country_code":"MX",
    "gn:dem":409,
    "gn:feature_class":"P",
    "gn:feature_code":"PPL",
    "gn:name":"San Javier",
    "gn:population":0,
    "gn:timezone":"America/Mazatlan",
    "iso:country":"MX",
    "wof:name":"San Javier",
    "wof:placetype":"locality"
},
  "geometry": {"coordinates":[-111.54367999999999,25.8615],"type":"Point"}
}