{
  "type": "Feature",
  "properties": {
    "gn:admin1_code":"5",
    "gn:admin2_code":"116.0",
    "gn:asciiname":"America Libre",
    "gn:country_code":"MX",
    "gn:dem":181,
    "gn:feature_class":"P",
    "gn:feature_code":"PPL",
    "gn:name":"Am\u00e9rica Libre",
    "gn:population":0,
    "gn:timezone":"America/Mexico_City",
    "iso:country":"MX",
    "name:spa_x_preferred":[
        "Am\u00e9rica Libre"
    ],
    "wof:name":"America Libre",
    "wof:placetype":"locality"
},
  "geometry": {"coordinates":[-90.73869000000001,16.21733],"type":"Point"}
}