{
  "type": "Feature",
  "properties": {
    "iso:country":"MX",
    "name:spa_x_preferred":[
        "Unidad Modelo"
    ],
    "qs:gn_adm0_cc":"MX",
    "qs:gn_local":3522507,
    "qs:gn_nam_loc":"Oaxaca de Juarez, Oaxaca de Ju\u00e1rez, Oaxaca, MX",
    "qs:gn_namadm1":"20",
    "qs:local_max":5236,
    "qs:local_sum":18801,
    "qs:localhoods":12,
    "qs:name":"Unidad Modelo",
    "qs:name_adm0":"M\u00e9xico",
    "qs:name_adm1":"Oaxaca",
    "qs:name_adm2":"Oaxaca de Juarez",
    "qs:name_local":"Oaxaca de Ju\u00e1rez",
    "qs:photo_max":135,
    "qs:photo_sum":586,
    "qs:placetype":"Suburb",
    "qs:quad_count":12,
    "qs:woe_adm0":23424900,
    "qs:woe_adm1":2346283,
    "qs:woe_adm2":12600729,
    "qs:woe_lau":0,
    "qs:woe_local":134889,
    "qs:woe_ver":"7.10.0",
    "wof:lang":[
        "spa"
    ],
    "wof:name":"Unidad Modelo",
    "wof:placetype":"neighbourhood"
},
  "geometry": {"coordinates":[-96.721119,17.060225],"type":"Point"}
}