{
  "type": "Feature",
  "properties": {
    "gn:admin1_code":"5",
    "gn:admin2_code":"80.0",
    "gn:asciiname":"Capitan Luis A. Vidal",
    "gn:country_code":"MX",
    "gn:dem":1553,
    "gn:feature_class":"P",
    "gn:feature_code":"PPL",
    "gn:name":"Capit\u00e1n Luis A. Vidal",
    "gn:population":563,
    "gn:timezone":"America/Mexico_City",
    "iso:country":"MX",
    "name:und_x_variant":[
        "Capit\u00e1n Luis A. Vidal"
    ],
    "wof:name":"Capitan Luis A. Vidal",
    "wof:placetype":"locality",
    "wof:population":563
},
  "geometry": {"coordinates":[-92.62889,15.60083],"type":"Point"}
}