{
  "type": "Feature",
  "properties": {
    "gn:admin1_code":"6",
    "gn:admin2_code":"31.0",
    "gn:asciiname":"Ninguno [CERESO]",
    "gn:country_code":"MX",
    "gn:dem":2031,
    "gn:feature_class":"P",
    "gn:feature_code":"PPL",
    "gn:name":"Ninguno [CERESO]",
    "gn:population":61,
    "gn:timezone":"America/Chihuahua",
    "iso:country":"MX",
    "wof:name":"Ninguno [CERESO]",
    "wof:placetype":"locality",
    "wof:population":61
},
  "geometry": {"coordinates":[-107.50745999999999,28.56111],"type":"Point"}
}