{
  "type": "Feature",
  "properties": {
    "gn:admin1_code":"6",
    "gn:admin2_code":"27",
    "gn:asciiname":"Bitozachi",
    "gn:country_code":"MX",
    "gn:dem":2137,
    "gn:feature_class":"P",
    "gn:feature_code":"PPL",
    "gn:name":"Bitozachi",
    "gn:population":10,
    "gn:timezone":"America/Chihuahua",
    "iso:country":"MX",
    "wof:name":"Bitozachi",
    "wof:placetype":"locality",
    "wof:population":10
},
  "geometry": {"coordinates":[-107.44072,26.75994],"type":"Point"}
}