{
  "type": "Feature",
  "properties": {
    "gn:admin1_code":"15",
    "gn:admin2_code":"21.0",
    "gn:asciiname":"El Potrerito (El Potrero)",
    "gn:country_code":"MX",
    "gn:dem":2574,
    "gn:feature_class":"P",
    "gn:feature_code":"PPL",
    "gn:name":"El Potrerito (El Potrero)",
    "gn:population":615,
    "gn:timezone":"America/Mexico_City",
    "iso:country":"MX",
    "wof:name":"El Potrerito (El Potrero)",
    "wof:placetype":"locality",
    "wof:population":615
},
  "geometry": {"coordinates":[-99.77249999999999,18.97194],"type":"Point"}
}