{
  "type": "Feature",
  "properties": {
    "gn:admin1_code":"20",
    "gn:admin2_code":"227",
    "gn:asciiname":"Rancho el Ensueno",
    "gn:country_code":"MX",
    "gn:dem":1582,
    "gn:feature_class":"P",
    "gn:feature_code":"PPL",
    "gn:name":"Rancho el Ensue\u00f1o",
    "gn:population":21,
    "gn:timezone":"America/Mexico_City",
    "iso:country":"MX",
    "name:und_x_variant":[
        "Rancho el Ensue\u00f1o"
    ],
    "wof:name":"Rancho el Ensueno",
    "wof:placetype":"locality",
    "wof:population":21
},
  "geometry": {"coordinates":[-96.78306000000001,17.13889],"type":"Point"}
}