{
  "type": "Feature",
  "properties": {
    "gn:admin1_code":"5",
    "gn:admin2_code":"59",
    "gn:asciiname":"Michoacan",
    "gn:country_code":"MX",
    "gn:dem":564,
    "gn:feature_class":"P",
    "gn:feature_code":"PPL",
    "gn:name":"Michoac\u00e1n",
    "gn:population":25,
    "gn:timezone":"America/Mexico_City",
    "iso:country":"MX",
    "name:und_x_variant":[
        "Michoac\u00e1n"
    ],
    "wof:name":"Michoacan",
    "wof:placetype":"locality",
    "wof:population":25
},
  "geometry": {"coordinates":[-91.67917,16.81556],"type":"Point"}
}