{
  "type": "Feature",
  "properties": {
    "gn:admin1_code":"28.0",
    "gn:admin2_code":"2.0",
    "gn:asciiname":"Revolucion",
    "gn:country_code":"MX",
    "gn:dem":18,
    "gn:feature_class":"P",
    "gn:feature_code":"PPL",
    "gn:name":"Revoluci\u00f3n",
    "gn:population":34,
    "gn:timezone":"America/Monterrey",
    "iso:country":"MX",
    "name:spa_x_preferred":[
        "Revoluci\u00f3n"
    ],
    "wof:name":"Revolucion",
    "wof:placetype":"locality",
    "wof:population":34
},
  "geometry": {"coordinates":[-97.91777999999999,22.87444],"type":"Point"}
}