{
  "type": "Feature",
  "properties": {
    "gn:admin1_code":"26.0",
    "gn:admin2_code":"6.0",
    "gn:asciiname":"Nueva Colonia Chinapa",
    "gn:country_code":"MX",
    "gn:dem":924,
    "gn:feature_class":"P",
    "gn:feature_code":"PPL",
    "gn:name":"Nueva Colonia Chinapa",
    "gn:population":0,
    "gn:timezone":"America/Hermosillo",
    "iso:country":"MX",
    "name:spa_x_preferred":[
        "Nueva Colonia Chinapa"
    ],
    "wof:name":"Nueva Colonia Chinapa",
    "wof:placetype":"locality"
},
  "geometry": {"coordinates":[-110.01563,30.45944],"type":"Point"}
}