{
  "type": "Feature",
  "properties": {
    "gn:admin1_code":"16",
    "gn:admin2_code":"64.0",
    "gn:asciiname":"La Casa de los Otates",
    "gn:country_code":"MX",
    "gn:dem":279,
    "gn:feature_class":"P",
    "gn:feature_code":"PPL",
    "gn:name":"La Casa de los Otates",
    "gn:population":5,
    "gn:timezone":"America/Mexico_City",
    "iso:country":"MX",
    "wof:name":"La Casa de los Otates",
    "wof:placetype":"locality",
    "wof:population":5
},
  "geometry": {"coordinates":[-102.22583,18.95222],"type":"Point"}
}