{
  "type": "Feature",
  "properties": {
    "gn:admin1_code":"7",
    "gn:admin2_code":"18.0",
    "gn:asciiname":"Salitrillos",
    "gn:country_code":"MX",
    "gn:dem":549,
    "gn:feature_class":"P",
    "gn:feature_code":"PPL",
    "gn:name":"Salitrillos",
    "gn:population":0,
    "gn:timezone":"America/Monterrey",
    "iso:country":"MX",
    "name:und_x_variant":[
        "Salitrillo"
    ],
    "wof:name":"Salitrillos",
    "wof:placetype":"locality"
},
  "geometry": {"coordinates":[-101.11077,26.88706],"type":"Point"}
}