{
  "type": "Feature",
  "properties": {
    "gn:admin1_code":"14",
    "gn:admin2_code":"33",
    "gn:asciiname":"La Tabla",
    "gn:country_code":"MX",
    "gn:dem":1679,
    "gn:feature_class":"P",
    "gn:feature_code":"PPL",
    "gn:name":"La Tabla",
    "gn:population":16,
    "gn:timezone":"America/Mexico_City",
    "iso:country":"MX",
    "wof:name":"La Tabla",
    "wof:placetype":"locality",
    "wof:population":16
},
  "geometry": {"coordinates":[-102.18556,20.425],"type":"Point"}
}