{
  "type": "Feature",
  "properties": {
    "gn:admin1_code":"30",
    "gn:admin2_code":"24.0",
    "gn:asciiname":"Axoyatla",
    "gn:country_code":"MX",
    "gn:dem":1507,
    "gn:feature_class":"P",
    "gn:feature_code":"PPL",
    "gn:name":"Axoyatla",
    "gn:population":452,
    "gn:timezone":"America/Mexico_City",
    "iso:country":"MX",
    "wof:name":"Axoyatla",
    "wof:placetype":"locality",
    "wof:population":452
},
  "geometry": {"coordinates":[-96.98833,19.22806],"type":"Point"}
}