{
  "type": "Feature",
  "properties": {
    "gn:admin1_code":"10.0",
    "gn:admin2_code":"35.0",
    "gn:asciiname":"Cienega de Escobar",
    "gn:country_code":"MX",
    "gn:dem":2166,
    "gn:feature_class":"P",
    "gn:feature_code":"PPL",
    "gn:name":"Ci\u00e9nega de Escobar",
    "gn:population":0,
    "gn:timezone":"America/Monterrey",
    "iso:country":"MX",
    "name:und_x_variant":[
        "Cienega Escobar",
        "Ci\u00e9nega de Escobar"
    ],
    "wof:name":"Cienega de Escobar",
    "wof:placetype":"locality"
},
  "geometry": {"coordinates":[-105.74494,25.61123],"type":"Point"}
}