{
  "type": "Feature",
  "properties": {
    "gn:admin1_code":"20",
    "gn:admin2_code":"330",
    "gn:asciiname":"Piedra Colorada",
    "gn:country_code":"MX",
    "gn:dem":1179,
    "gn:feature_class":"P",
    "gn:feature_code":"PPL",
    "gn:name":"Piedra Colorada",
    "gn:population":21,
    "gn:timezone":"America/Mexico_City",
    "iso:country":"MX",
    "wof:name":"Piedra Colorada",
    "wof:placetype":"locality",
    "wof:population":21
},
  "geometry": {"coordinates":[-96.59611,17.95556000000001],"type":"Point"}
}