{
  "type": "Feature",
  "properties": {
    "gn:admin1_code":"13",
    "gn:admin2_code":"12",
    "gn:asciiname":"Barrio de Cabrera",
    "gn:country_code":"MX",
    "gn:dem":2053,
    "gn:feature_class":"P",
    "gn:feature_code":"PPL",
    "gn:name":"Barrio de Cabrera",
    "gn:population":15,
    "gn:timezone":"America/Mexico_City",
    "iso:country":"MX",
    "wof:name":"Barrio de Cabrera",
    "wof:placetype":"locality",
    "wof:population":15
},
  "geometry": {"coordinates":[-98.74935000000001,20.41123],"type":"Point"}
}