{
  "type": "Feature",
  "properties": {
    "gn:admin1_code":"20.0",
    "gn:asciiname":"Agua Caballero",
    "gn:country_code":"MX",
    "gn:dem":691,
    "gn:feature_class":"P",
    "gn:feature_code":"PPL",
    "gn:name":"Agua Caballero",
    "gn:population":0,
    "gn:timezone":"America/Mexico_City",
    "iso:country":"MX",
    "name:spa_x_preferred":[
        "Agua Caballero"
    ],
    "wof:name":"Agua Caballero",
    "wof:placetype":"locality"
},
  "geometry": {"coordinates":[-96.71092,18.15911],"type":"Point"}
}