{
  "type": "Feature",
  "properties": {
    "gn:admin1_code":"32",
    "gn:admin2_code":"10.0",
    "gn:asciiname":"Tapias de Santa Cruz (Pedro Ruiz Gonzalez)",
    "gn:country_code":"MX",
    "gn:dem":2087,
    "gn:feature_class":"P",
    "gn:feature_code":"PPL",
    "gn:name":"Tapias de Santa Cruz (Pedro Ruiz Gonz\u00e1lez)",
    "gn:population":1495,
    "gn:timezone":"America/Mexico_City",
    "iso:country":"MX",
    "name:und_x_variant":[
        "Tapias de Santa Cruz (Pedro Ruiz Gonz\u00e1lez)"
    ],
    "wof:name":"Tapias de Santa Cruz (Pedro Ruiz Gonzalez)",
    "wof:placetype":"locality",
    "wof:population":1495
},
  "geometry": {"coordinates":[-103.13111000000001,23.18889],"type":"Point"}
}