{
  "type": "Feature",
  "properties": {
    "gn:admin1_code":"29",
    "gn:admin2_code":"30.0",
    "gn:asciiname":"Villarreal",
    "gn:country_code":"MX",
    "gn:dem":3079,
    "gn:feature_class":"P",
    "gn:feature_code":"PPL",
    "gn:name":"Villarreal",
    "gn:population":0,
    "gn:timezone":"America/Mexico_City",
    "iso:country":"MX",
    "name:spa_x_preferred":[
        "Villarreal"
    ],
    "name:und_x_variant":[
        "Villareal"
    ],
    "wof:name":"Villarreal",
    "wof:placetype":"locality"
},
  "geometry": {"coordinates":[-97.89708,19.53362000000001],"type":"Point"}
}