{
  "type": "Feature",
  "properties": {
    "gn:admin1_code":"5.0",
    "gn:asciiname":"El Desprecio",
    "gn:country_code":"MX",
    "gn:dem":12,
    "gn:feature_class":"P",
    "gn:feature_code":"PPL",
    "gn:name":"El Desprecio",
    "gn:population":0,
    "gn:timezone":"America/Mexico_City",
    "iso:country":"MX",
    "name:spa_x_preferred":[
        "El Desprecio"
    ],
    "wof:name":"El Desprecio",
    "wof:placetype":"locality"
},
  "geometry": {"coordinates":[-93.53471999999999,15.82119],"type":"Point"}
}