{
  "type": "Feature",
  "properties": {
    "gn:admin1_code":"16",
    "gn:admin2_code":"95",
    "gn:asciiname":"El Rodeo de Andrade",
    "gn:country_code":"MX",
    "gn:dem":1181,
    "gn:feature_class":"P",
    "gn:feature_code":"PPL",
    "gn:name":"El Rodeo de Andrade",
    "gn:population":11,
    "gn:timezone":"America/Mexico_City",
    "iso:country":"MX",
    "wof:name":"El Rodeo de Andrade",
    "wof:placetype":"locality",
    "wof:population":11
},
  "geometry": {"coordinates":[-102.60306,19.59556],"type":"Point"}
}