{
  "type": "Feature",
  "properties": {
    "gn:admin1_code":"12",
    "gn:admin2_code":"48.0",
    "gn:asciiname":"Puente la Barrita",
    "gn:country_code":"MX",
    "gn:dem":17,
    "gn:feature_class":"P",
    "gn:feature_code":"PPL",
    "gn:name":"Puente la Barrita",
    "gn:population":139,
    "gn:timezone":"America/Mexico_City",
    "iso:country":"MX",
    "wof:name":"Puente la Barrita",
    "wof:placetype":"locality",
    "wof:population":139
},
  "geometry": {"coordinates":[-101.18458,17.42005],"type":"Point"}
}