{
  "type": "Feature",
  "properties": {
    "gn:admin1_code":"6",
    "gn:admin2_code":"19.0",
    "gn:asciiname":"Granjas los Trigales",
    "gn:country_code":"MX",
    "gn:dem":1565,
    "gn:feature_class":"P",
    "gn:feature_code":"PPL",
    "gn:name":"Granjas los Trigales",
    "gn:population":5,
    "gn:timezone":"America/Chihuahua",
    "iso:country":"MX",
    "wof:name":"Granjas los Trigales",
    "wof:placetype":"locality",
    "wof:population":5
},
  "geometry": {"coordinates":[-106.2105,28.86879],"type":"Point"}
}