{
  "type": "Feature",
  "properties": {
    "gn:admin1_code":"5",
    "gn:admin2_code":"107",
    "gn:asciiname":"Tres Marias",
    "gn:country_code":"MX",
    "gn:dem":737,
    "gn:feature_class":"P",
    "gn:feature_code":"PPL",
    "gn:name":"Tres Mar\u00edas",
    "gn:population":43,
    "gn:timezone":"America/Mexico_City",
    "iso:country":"MX",
    "name:und_x_variant":[
        "Tres Mar\u00edas"
    ],
    "wof:name":"Tres Marias",
    "wof:placetype":"locality",
    "wof:population":43
},
  "geometry": {"coordinates":[-93.05278,16.00333],"type":"Point"}
}