{
  "type": "Feature",
  "properties": {
    "gn:admin1_code":"32",
    "gn:admin2_code":"10.0",
    "gn:asciiname":"El Refugio",
    "gn:country_code":"MX",
    "gn:dem":2039,
    "gn:feature_class":"P",
    "gn:feature_code":"PPL",
    "gn:name":"El Refugio",
    "gn:population":0,
    "gn:timezone":"America/Mexico_City",
    "iso:country":"MX",
    "name:ceb_x_preferred":[
        "El Refugio"
    ],
    "name:deu_x_preferred":[
        "El Refugio"
    ],
    "name:ita_x_preferred":[
        "El Refugio"
    ],
    "name:nld_x_preferred":[
        "El Refugio"
    ],
    "name:por_x_preferred":[
        "El Refugio"
    ],
    "name:spa_x_preferred":[
        "El Refugio"
    ],
    "name:spa_x_variant":[
        "El refugio"
    ],
    "name:swe_x_preferred":[
        "El Refugio"
    ],
    "wof:name":"El Refugio",
    "wof:placetype":"locality"
},
  "geometry": {"coordinates":[-102.98180000000001,23.30704],"type":"Point"}
}