{
  "type": "Feature",
  "properties": {
    "gn:admin1_code":"6",
    "gn:admin2_code":"29",
    "gn:asciiname":"Mesa de San Francisco",
    "gn:country_code":"MX",
    "gn:dem":2694,
    "gn:feature_class":"P",
    "gn:feature_code":"PPL",
    "gn:name":"Mesa de San Francisco",
    "gn:population":51,
    "gn:timezone":"America/Chihuahua",
    "iso:country":"MX",
    "wof:name":"Mesa de San Francisco",
    "wof:placetype":"locality",
    "wof:population":51
},
  "geometry": {"coordinates":[-106.61861,26.21806],"type":"Point"}
}