{
  "type": "Feature",
  "properties": {
    "gn:admin1_code":"32",
    "gn:admin2_code":"51",
    "gn:asciiname":"La Estrella",
    "gn:country_code":"MX",
    "gn:dem":1996,
    "gn:feature_class":"P",
    "gn:feature_code":"PPL",
    "gn:name":"La Estrella",
    "gn:population":13,
    "gn:timezone":"America/Mexico_City",
    "iso:country":"MX",
    "wof:name":"La Estrella",
    "wof:placetype":"locality",
    "wof:population":13
},
  "geometry": {"coordinates":[-102.04694000000001,23.64],"type":"Point"}
}