{
  "type": "Feature",
  "properties": {
    "gn:admin1_code":"7",
    "gn:admin2_code":"2.0",
    "gn:asciiname":"San Gustavo",
    "gn:country_code":"MX",
    "gn:dem":447,
    "gn:feature_class":"P",
    "gn:feature_code":"PPL",
    "gn:name":"San Gustavo",
    "gn:population":0,
    "gn:timezone":"America/Matamoros",
    "iso:country":"MX",
    "wof:name":"San Gustavo",
    "wof:placetype":"locality"
},
  "geometry": {"coordinates":[-101.23958,29.30798],"type":"Point"}
}