{
  "type": "Feature",
  "properties": {
    "gn:admin1_code":"6",
    "gn:asciiname":"La Cienega del Trigo",
    "gn:country_code":"MX",
    "gn:dem":1417,
    "gn:feature_class":"P",
    "gn:feature_code":"PPL",
    "gn:name":"La Ci\u00e9nega del Trigo",
    "gn:population":0,
    "gn:timezone":"America/Hermosillo",
    "iso:country":"MX",
    "name:spa_x_preferred":[
        "La Ci\u00e9nega del Trigo"
    ],
    "wof:name":"La Cienega del Trigo",
    "wof:placetype":"locality"
},
  "geometry": {"coordinates":[-108.79147,28.30118],"type":"Point"}
}