{
  "type": "Feature",
  "properties": {
    "gn:admin1_code":"16",
    "gn:admin2_code":"88.0",
    "gn:asciiname":"El Cuitzillo Grande",
    "gn:country_code":"MX",
    "gn:dem":1858,
    "gn:feature_class":"P",
    "gn:feature_code":"PPL",
    "gn:name":"El Cuitzillo Grande",
    "gn:population":1130,
    "gn:timezone":"America/Mexico_City",
    "iso:country":"MX",
    "wof:name":"El Cuitzillo Grande",
    "wof:placetype":"locality",
    "wof:population":1130
},
  "geometry": {"coordinates":[-101.11694,19.77972],"type":"Point"}
}