{
  "type": "Feature",
  "properties": {
    "gn:admin1_code":"6.0",
    "gn:admin2_code":"63.0",
    "gn:asciiname":"La Cebadilla",
    "gn:country_code":"MX",
    "gn:dem":2611,
    "gn:feature_class":"P",
    "gn:feature_code":"PPL",
    "gn:name":"La Cebadilla",
    "gn:population":0,
    "gn:timezone":"America/Chihuahua",
    "iso:country":"MX",
    "name:spa_x_preferred":[
        "La Cebadilla"
    ],
    "name:und_x_variant":[
        "Rancho Cebadilla",
        "Cebadilla"
    ],
    "wof:name":"La Cebadilla",
    "wof:placetype":"locality"
},
  "geometry": {"coordinates":[-108.26137,28.62859000000001],"type":"Point"}
}