{
  "type": "Feature",
  "properties": {
    "gn:admin1_code":"4",
    "gn:admin2_code":"11.0",
    "gn:asciiname":"Jose Antonio",
    "gn:country_code":"MX",
    "gn:dem":35,
    "gn:feature_class":"P",
    "gn:feature_code":"PPL",
    "gn:name":"Jos\u00e9 Antonio",
    "gn:population":5,
    "gn:timezone":"America/Merida",
    "iso:country":"MX",
    "name:und_x_variant":[
        "Jos\u00e9 Antonio"
    ],
    "wof:name":"Jose Antonio",
    "wof:placetype":"locality",
    "wof:population":5
},
  "geometry": {"coordinates":[-90.78583,18.04028],"type":"Point"}
}