{
  "type": "Feature",
  "properties": {
    "gn:admin1_code":"26.0",
    "gn:admin2_code":"58.0",
    "gn:asciiname":"Santo Nino",
    "gn:country_code":"MX",
    "gn:dem":641,
    "gn:feature_class":"P",
    "gn:feature_code":"PPL",
    "gn:name":"Santo Ni\u00f1o",
    "gn:population":0,
    "gn:timezone":"America/Hermosillo",
    "iso:country":"MX",
    "name:spa_x_preferred":[
        "Santo Ni\u00f1o"
    ],
    "wof:name":"Santo Nino",
    "wof:placetype":"locality"
},
  "geometry": {"coordinates":[-111.23069,30.52086],"type":"Point"}
}