{
  "type": "Feature",
  "properties": {
    "gn:admin1_code":"28.0",
    "gn:admin2_code":"21.0",
    "gn:asciiname":"Manuel Avila Camacho",
    "gn:country_code":"MX",
    "gn:dem":68,
    "gn:feature_class":"P",
    "gn:feature_code":"PPL",
    "gn:name":"Manuel \u00c1vila Camacho",
    "gn:population":60,
    "gn:timezone":"America/Monterrey",
    "iso:country":"MX",
    "name:spa_x_preferred":[
        "Manuel \u00c1vila Camacho"
    ],
    "wof:name":"Manuel Avila Camacho",
    "wof:placetype":"locality",
    "wof:population":60
},
  "geometry": {"coordinates":[-99.01667,22.79833],"type":"Point"}
}