{
  "type": "Feature",
  "properties": {
    "gn:admin1_code":"25",
    "gn:admin2_code":"11.0",
    "gn:asciiname":"Campo Seis",
    "gn:country_code":"MX",
    "gn:dem":41,
    "gn:feature_class":"P",
    "gn:feature_code":"PPL",
    "gn:name":"Campo Seis",
    "gn:population":0,
    "gn:timezone":"America/Mazatlan",
    "iso:country":"MX",
    "name:spa_x_preferred":[
        "Campo Seis"
    ],
    "wof:name":"Campo Seis",
    "wof:placetype":"locality"
},
  "geometry": {"coordinates":[-108.42909,25.7612],"type":"Point"}
}