{
  "type": "Feature",
  "properties": {
    "gn:admin1_code":"5",
    "gn:admin2_code":"57.0",
    "gn:asciiname":"Veintitres de Abril",
    "gn:country_code":"MX",
    "gn:dem":1269,
    "gn:feature_class":"P",
    "gn:feature_code":"PPL",
    "gn:name":"Veintitr\u00e9s de Abril",
    "gn:population":97,
    "gn:timezone":"America/Mexico_City",
    "iso:country":"MX",
    "name:und_x_variant":[
        "Veintitr\u00e9s de Abril"
    ],
    "wof:name":"Veintitres de Abril",
    "wof:placetype":"locality",
    "wof:population":97
},
  "geometry": {"coordinates":[-92.41667,15.38222],"type":"Point"}
}