{
  "type": "Feature",
  "properties": {
    "gn:admin1_code":"7",
    "gn:admin2_code":"4.0",
    "gn:asciiname":"Chamacueros",
    "gn:country_code":"MX",
    "gn:dem":2055,
    "gn:feature_class":"P",
    "gn:feature_code":"PPL",
    "gn:name":"Chamacueros",
    "gn:population":0,
    "gn:timezone":"America/Monterrey",
    "iso:country":"MX",
    "name:spa_x_preferred":[
        "Chamacueros"
    ],
    "wof:name":"Chamacueros",
    "wof:placetype":"locality"
},
  "geometry": {"coordinates":[-100.7003,25.33715],"type":"Point"}
}