{
  "type": "Feature",
  "properties": {
    "gn:admin1_code":"21.0",
    "gn:admin2_code":"154.0",
    "gn:asciiname":"San Jose la Portilla",
    "gn:country_code":"MX",
    "gn:dem":1982,
    "gn:feature_class":"P",
    "gn:feature_code":"PPL",
    "gn:name":"San Jos\u00e9 la Portilla",
    "gn:population":0,
    "gn:timezone":"America/Mexico_City",
    "iso:country":"MX",
    "name:spa_x_preferred":[
        "San Jos\u00e9 la Portilla"
    ],
    "wof:name":"San Jose la Portilla",
    "wof:placetype":"locality"
},
  "geometry": {"coordinates":[-97.7568,18.81982],"type":"Point"}
}