{
  "type": "Feature",
  "properties": {
    "gn:admin1_code":"26",
    "gn:admin2_code":"56.0",
    "gn:asciiname":"Campo Nunez",
    "gn:country_code":"MX",
    "gn:dem":459,
    "gn:feature_class":"P",
    "gn:feature_code":"PPL",
    "gn:name":"Campo N\u00fa\u00f1ez",
    "gn:population":0,
    "gn:timezone":"America/Hermosillo",
    "iso:country":"MX",
    "name:spa_x_preferred":[
        "Campo N\u00fa\u00f1ez"
    ],
    "wof:name":"Campo Nunez",
    "wof:placetype":"locality"
},
  "geometry": {"coordinates":[-110.97308,29.37157],"type":"Point"}
}