{
  "type": "Feature",
  "properties": {
    "gn:admin1_code":"20",
    "gn:admin2_code":"481",
    "gn:asciiname":"El Paraiso Nopalera",
    "gn:country_code":"MX",
    "gn:dem":861,
    "gn:feature_class":"P",
    "gn:feature_code":"PPL",
    "gn:name":"El Para\u00edso Nopalera",
    "gn:population":20,
    "gn:timezone":"America/Mexico_City",
    "iso:country":"MX",
    "name:und_x_variant":[
        "El Para\u00edso Nopalera"
    ],
    "wof:name":"El Paraiso Nopalera",
    "wof:placetype":"locality",
    "wof:population":20
},
  "geometry": {"coordinates":[-97.82111,16.95277999999999],"type":"Point"}
}