{
  "type": "Feature",
  "properties": {
    "gn:admin1_code":"12",
    "gn:admin2_code":"79.0",
    "gn:asciiname":"Ahuacosijtic",
    "gn:country_code":"MX",
    "gn:dem":1048,
    "gn:feature_class":"P",
    "gn:feature_code":"PPL",
    "gn:name":"Ahuacosijtic",
    "gn:population":60,
    "gn:timezone":"America/Mexico_City",
    "iso:country":"MX",
    "wof:name":"Ahuacosijtic",
    "wof:placetype":"locality",
    "wof:population":60
},
  "geometry": {"coordinates":[-99.00082999999999,17.39694],"type":"Point"}
}