{
  "type": "Feature",
  "properties": {
    "gn:admin1_code":"25",
    "gn:admin2_code":"6.0",
    "gn:asciiname":"Campo el Huarache",
    "gn:country_code":"MX",
    "gn:dem":14,
    "gn:feature_class":"P",
    "gn:feature_code":"PPL",
    "gn:name":"Campo el Huarache",
    "gn:population":154,
    "gn:timezone":"America/Mazatlan",
    "iso:country":"MX",
    "wof:name":"Campo el Huarache",
    "wof:placetype":"locality",
    "wof:population":154
},
  "geometry": {"coordinates":[-107.47750000000001,24.66],"type":"Point"}
}