{
  "type": "Feature",
  "properties": {
    "gn:admin1_code":"24",
    "gn:admin2_code":"52.0",
    "gn:asciiname":"El Palote",
    "gn:country_code":"MX",
    "gn:dem":1510,
    "gn:feature_class":"P",
    "gn:feature_code":"PPL",
    "gn:name":"El Palote",
    "gn:population":0,
    "gn:timezone":"America/Mexico_City",
    "iso:country":"MX",
    "wof:name":"El Palote",
    "wof:placetype":"locality"
},
  "geometry": {"coordinates":[-100.32971000000001,22.16443],"type":"Point"}
}