{
  "type": "Feature",
  "properties": {
    "gn:admin1_code":"26",
    "gn:admin2_code":"17.0",
    "gn:asciiname":"Yaqui Justiciero",
    "gn:country_code":"MX",
    "gn:dem":188,
    "gn:feature_class":"P",
    "gn:feature_code":"PPL",
    "gn:name":"Yaqui Justiciero",
    "gn:population":199,
    "gn:timezone":"America/Hermosillo",
    "iso:country":"MX",
    "wof:name":"Yaqui Justiciero",
    "wof:placetype":"locality",
    "wof:population":199
},
  "geometry": {"coordinates":[-112.40056,30.70694],"type":"Point"}
}