{
  "type": "Feature",
  "properties": {
    "gn:admin1_code":"5",
    "gn:admin2_code":"48.0",
    "gn:asciiname":"Galeana 2da. Seccion (Joaquin M. Gutierrez)",
    "gn:country_code":"MX",
    "gn:dem":65,
    "gn:feature_class":"P",
    "gn:feature_code":"PPL",
    "gn:name":"Galeana 2da. Secci\u00f3n (Joaqu\u00edn M. Guti\u00e9rrez)",
    "gn:population":183,
    "gn:timezone":"America/Mexico_City",
    "iso:country":"MX",
    "name:und_x_variant":[
        "Galeana 2da. Secci\u00f3n (Joaqu\u00edn M. Guti\u00e9rrez)"
    ],
    "wof:name":"Galeana 2da. Seccion (Joaquin M. Gutierrez)",
    "wof:placetype":"locality",
    "wof:population":183
},
  "geometry": {"coordinates":[-93.12944,17.58361],"type":"Point"}
}