{
  "type": "Feature",
  "properties": {
    "gn:admin1_code":"10",
    "gn:admin2_code":"1.0",
    "gn:asciiname":"Lirios de la Sierra",
    "gn:country_code":"MX",
    "gn:dem":2564,
    "gn:feature_class":"P",
    "gn:feature_code":"PPL",
    "gn:name":"Lirios de la Sierra",
    "gn:population":0,
    "gn:timezone":"America/Monterrey",
    "iso:country":"MX",
    "name:spa_x_preferred":[
        "Lirios de la Sierra"
    ],
    "wof:name":"Lirios de la Sierra",
    "wof:placetype":"locality"
},
  "geometry": {"coordinates":[-105.45303,24.51062],"type":"Point"}
}