{
  "type": "Feature",
  "properties": {
    "gn:admin1_code":"21",
    "gn:admin2_code":"39",
    "gn:asciiname":"Texamanila",
    "gn:country_code":"MX",
    "gn:dem":2528,
    "gn:feature_class":"P",
    "gn:feature_code":"PPL",
    "gn:name":"Texamanila",
    "gn:population":47,
    "gn:timezone":"America/Mexico_City",
    "iso:country":"MX",
    "wof:name":"Texamanila",
    "wof:placetype":"locality",
    "wof:population":47
},
  "geometry": {"coordinates":[-97.78059,19.8801],"type":"Point"}
}