{
  "type": "Feature",
  "properties": {
    "gn:admin1_code":"11",
    "gn:admin2_code":"32",
    "gn:asciiname":"Arroyo del Gachupin",
    "gn:country_code":"MX",
    "gn:dem":2111,
    "gn:feature_class":"P",
    "gn:feature_code":"PPL",
    "gn:name":"Arroyo del Gachup\u00edn",
    "gn:population":24,
    "gn:timezone":"America/Mexico_City",
    "iso:country":"MX",
    "name:und_x_variant":[
        "Arroyo del Gachup\u00edn"
    ],
    "wof:name":"Arroyo del Gachupin",
    "wof:placetype":"locality",
    "wof:population":24
},
  "geometry": {"coordinates":[-100.38639000000001,20.98556],"type":"Point"}
}