{
  "type": "Feature",
  "properties": {
    "gn:admin1_code":"17",
    "gn:admin2_code":"17",
    "gn:asciiname":"El Abanico",
    "gn:country_code":"MX",
    "gn:dem":913,
    "gn:feature_class":"P",
    "gn:feature_code":"PPL",
    "gn:name":"El Abanico",
    "gn:population":26,
    "gn:timezone":"America/Mexico_City",
    "iso:country":"MX",
    "wof:name":"El Abanico",
    "wof:placetype":"locality",
    "wof:population":26
},
  "geometry": {"coordinates":[-99.31,18.64],"type":"Point"}
}