{
  "type": "Feature",
  "properties": {
    "gn:admin1_code":"9",
    "gn:admin2_code":"12.0",
    "gn:asciiname":"Santo Tomas Ajusco",
    "gn:country_code":"MX",
    "gn:dem":2838,
    "gn:feature_class":"P",
    "gn:feature_code":"PPL",
    "gn:name":"Santo Tom\u00e1s Ajusco",
    "gn:population":0,
    "gn:timezone":"America/Mexico_City",
    "iso:country":"MX",
    "name:spa_x_preferred":[
        "Santo Tom\u00e1s Ajusco"
    ],
    "wof:name":"Santo Tomas Ajusco",
    "wof:placetype":"locality"
},
  "geometry": {"coordinates":[-99.19483,19.22123],"type":"Point"}
}