{
  "type": "Feature",
  "properties": {
    "gn:admin1_code":"15",
    "gn:admin2_code":"26.0",
    "gn:asciiname":"La Cienega",
    "gn:country_code":"MX",
    "gn:dem":2900,
    "gn:feature_class":"P",
    "gn:feature_code":"PPL",
    "gn:name":"La Ci\u00e9nega",
    "gn:population":0,
    "gn:timezone":"America/Mexico_City",
    "iso:country":"MX",
    "name:ceb_x_preferred":[
        "La Cienega"
    ],
    "name:swe_x_preferred":[
        "La Cienega"
    ],
    "wof:name":"La Cienega",
    "wof:placetype":"locality"
},
  "geometry": {"coordinates":[-99.65000000000001,19.84167],"type":"Point"}
}