{
  "type": "Feature",
  "properties": {
    "gn:admin1_code":"19.0",
    "gn:admin2_code":"5.0",
    "gn:asciiname":"La Mojonera",
    "gn:country_code":"MX",
    "gn:dem":208,
    "gn:feature_class":"P",
    "gn:feature_code":"PPL",
    "gn:name":"La Mojonera",
    "gn:population":0,
    "gn:timezone":"America/Matamoros",
    "iso:country":"MX",
    "name:spa_x_preferred":[
        "La Mojonera"
    ],
    "wof:name":"La Mojonera",
    "wof:placetype":"locality"
},
  "geometry": {"coordinates":[-99.93237000000001,27.67466],"type":"Point"}
}