{
  "type": "Feature",
  "properties": {
    "gn:admin1_code":"6",
    "gn:admin2_code":"65.0",
    "gn:asciiname":"La Higuerita",
    "gn:country_code":"MX",
    "gn:dem":1296,
    "gn:feature_class":"P",
    "gn:feature_code":"PPL",
    "gn:name":"La Higuerita",
    "gn:population":6,
    "gn:timezone":"America/Chihuahua",
    "iso:country":"MX",
    "name:spa_x_preferred":[
        "La Higuerita"
    ],
    "wof:name":"La Higuerita",
    "wof:placetype":"locality",
    "wof:population":6
},
  "geometry": {"coordinates":[-108.13435,27.00493],"type":"Point"}
}