{
  "type": "Feature",
  "properties": {
    "gn:admin1_code":"32",
    "gn:admin2_code":"38",
    "gn:asciiname":"Las Jaboneras",
    "gn:country_code":"MX",
    "gn:dem":2239,
    "gn:feature_class":"P",
    "gn:feature_code":"PPL",
    "gn:name":"Las Jaboneras",
    "gn:population":36,
    "gn:timezone":"America/Mexico_City",
    "iso:country":"MX",
    "wof:name":"Las Jaboneras",
    "wof:placetype":"locality",
    "wof:population":36
},
  "geometry": {"coordinates":[-101.60556,22.41],"type":"Point"}
}