{
  "type": "Feature",
  "properties": {
    "gn:admin1_code":"13",
    "gn:admin2_code":"40",
    "gn:asciiname":"Vado Hondo",
    "gn:country_code":"MX",
    "gn:dem":555,
    "gn:feature_class":"P",
    "gn:feature_code":"PPL",
    "gn:name":"Vado Hondo",
    "gn:population":9,
    "gn:timezone":"America/Mexico_City",
    "iso:country":"MX",
    "wof:name":"Vado Hondo",
    "wof:placetype":"locality",
    "wof:population":9
},
  "geometry": {"coordinates":[-99.03833,20.96207],"type":"Point"}
}