{
  "type": "Feature",
  "properties": {
    "gn:admin1_code":"3.0",
    "gn:admin2_code":"9.0",
    "gn:asciiname":"Juncalito",
    "gn:country_code":"MX",
    "gn:dem":14,
    "gn:feature_class":"P",
    "gn:feature_code":"PPL",
    "gn:name":"Juncalito",
    "gn:population":0,
    "gn:timezone":"America/Mazatlan",
    "iso:country":"MX",
    "name:spa_x_preferred":[
        "Juncalito"
    ],
    "wof:name":"Juncalito",
    "wof:placetype":"locality"
},
  "geometry": {"coordinates":[-111.33523999999998,25.83478],"type":"Point"}
}