{
  "type": "Feature",
  "properties": {
    "gn:admin1_code":"16",
    "gn:admin2_code":"98.0",
    "gn:asciiname":"Las Canoas",
    "gn:country_code":"MX",
    "gn:dem":2079,
    "gn:feature_class":"P",
    "gn:feature_code":"PPL",
    "gn:name":"Las Canoas",
    "gn:population":147,
    "gn:timezone":"America/Mexico_City",
    "iso:country":"MX",
    "wof:name":"Las Canoas",
    "wof:placetype":"locality",
    "wof:population":147
},
  "geometry": {"coordinates":[-100.44638999999999,19.53306],"type":"Point"}
}