{
  "type": "Feature",
  "properties": {
    "gn:admin1_code":"25",
    "gn:admin2_code":"17.0",
    "gn:asciiname":"La Pila",
    "gn:country_code":"MX",
    "gn:dem":137,
    "gn:feature_class":"P",
    "gn:feature_code":"PPL",
    "gn:name":"La Pila",
    "gn:population":0,
    "gn:timezone":"America/Mazatlan",
    "iso:country":"MX",
    "name:ceb_x_preferred":[
        "La Pila"
    ],
    "name:ita_x_preferred":[
        "La Pila"
    ],
    "name:spa_x_preferred":[
        "La Pila"
    ],
    "name:srp_x_preferred":[
        "\u041b\u0430 \u041f\u0438\u043b\u0430"
    ],
    "name:und_x_variant":[
        "Rancho La Pila"
    ],
    "wof:name":"La Pila",
    "wof:placetype":"locality"
},
  "geometry": {"coordinates":[-108.46725000000001,26.02553],"type":"Point"}
}