{
  "type": "Feature",
  "properties": {
    "gn:admin1_code":"7",
    "gn:admin2_code":"31.0",
    "gn:asciiname":"San Patricio",
    "gn:country_code":"MX",
    "gn:dem":1405,
    "gn:feature_class":"P",
    "gn:feature_code":"PPL",
    "gn:name":"San Patricio",
    "gn:population":0,
    "gn:timezone":"America/Monterrey",
    "iso:country":"MX",
    "name:ceb_x_preferred":[
        "San Patricio"
    ],
    "name:deu_x_preferred":[
        "San Patricio"
    ],
    "name:ita_x_preferred":[
        "San Patricio"
    ],
    "name:pol_x_preferred":[
        "San Patricio"
    ],
    "name:por_x_preferred":[
        "San Patricio"
    ],
    "name:spa_x_preferred":[
        "San Patricio"
    ],
    "name:srp_x_preferred":[
        "\u0421\u0430\u043d \u041f\u0430\u0442\u0440\u0438\u0448\u0438\u043e"
    ],
    "name:swe_x_preferred":[
        "San Patricio"
    ],
    "wof:name":"San Patricio",
    "wof:placetype":"locality"
},
  "geometry": {"coordinates":[-102.33812,28.2155],"type":"Point"}
}