{
  "type": "Feature",
  "properties": {
    "gn:admin1_code":"25",
    "gn:admin2_code":"6",
    "gn:asciiname":"Campo Sarita",
    "gn:country_code":"MX",
    "gn:dem":15,
    "gn:feature_class":"P",
    "gn:feature_code":"PPL",
    "gn:name":"Campo Sarita",
    "gn:population":32,
    "gn:timezone":"America/Mazatlan",
    "iso:country":"MX",
    "wof:name":"Campo Sarita",
    "wof:placetype":"locality",
    "wof:population":32
},
  "geometry": {"coordinates":[-107.38261,24.45191],"type":"Point"}
}