{
  "type": "Feature",
  "properties": {
    "gn:admin1_code":"25",
    "gn:admin2_code":"18",
    "gn:asciiname":"San Emilion",
    "gn:country_code":"MX",
    "gn:dem":30,
    "gn:feature_class":"P",
    "gn:feature_code":"PPL",
    "gn:name":"San Emili\u00f3n",
    "gn:population":49,
    "gn:timezone":"America/Mazatlan",
    "iso:country":"MX",
    "name:und_x_variant":[
        "San Emili\u00f3n"
    ],
    "wof:name":"San Emilion",
    "wof:placetype":"locality",
    "wof:population":49
},
  "geometry": {"coordinates":[-107.51639,24.75444],"type":"Point"}
}