{
  "type": "Feature",
  "properties": {
    "gn:admin1_code":"20.0",
    "gn:asciiname":"Yutidecue",
    "gn:country_code":"MX",
    "gn:dem":2354,
    "gn:feature_class":"P",
    "gn:feature_code":"PPL",
    "gn:name":"Yutidecue",
    "gn:population":0,
    "gn:timezone":"America/Mexico_City",
    "iso:country":"MX",
    "name:spa_x_preferred":[
        "Yutidecue"
    ],
    "wof:name":"Yutidecue",
    "wof:placetype":"locality"
},
  "geometry": {"coordinates":[-97.19333,17.55088],"type":"Point"}
}