{
  "type": "Feature",
  "properties": {
    "gn:admin1_code":"20",
    "gn:admin2_code":"565",
    "gn:asciiname":"Colonia Jardines del Sur",
    "gn:country_code":"MX",
    "gn:dem":1530,
    "gn:feature_class":"P",
    "gn:feature_code":"PPL",
    "gn:name":"Colonia Jardines del Sur",
    "gn:population":10,
    "gn:timezone":"America/Mexico_City",
    "iso:country":"MX",
    "wof:name":"Colonia Jardines del Sur",
    "wof:placetype":"locality",
    "wof:population":10
},
  "geometry": {"coordinates":[-96.71444,16.91278],"type":"Point"}
}