{
  "type": "Feature",
  "properties": {
    "gn:admin1_code":"13",
    "gn:admin2_code":"84.0",
    "gn:asciiname":"Pelillos",
    "gn:country_code":"MX",
    "gn:dem":2229,
    "gn:feature_class":"P",
    "gn:feature_code":"PPL",
    "gn:name":"Pelillos",
    "gn:population":121,
    "gn:timezone":"America/Mexico_City",
    "iso:country":"MX",
    "wof:name":"Pelillos",
    "wof:placetype":"locality",
    "wof:population":121
},
  "geometry": {"coordinates":[-99.25001,20.85048],"type":"Point"}
}