{
  "type": "Feature",
  "properties": {
    "gn:admin1_code":"14",
    "gn:admin2_code":"35",
    "gn:asciiname":"El Pariancito",
    "gn:country_code":"MX",
    "gn:dem":1876,
    "gn:feature_class":"P",
    "gn:feature_code":"PPL",
    "gn:name":"El Pariancito",
    "gn:population":20,
    "gn:timezone":"America/Mexico_City",
    "iso:country":"MX",
    "wof:name":"El Pariancito",
    "wof:placetype":"locality",
    "wof:population":20
},
  "geometry": {"coordinates":[-102.13833,21.585],"type":"Point"}
}