{
  "type": "Feature",
  "properties": {
    "gn:admin1_code":"14",
    "gn:admin2_code":"19.0",
    "gn:asciiname":"La Mesa del Pino",
    "gn:country_code":"MX",
    "gn:dem":1484,
    "gn:feature_class":"P",
    "gn:feature_code":"PPL",
    "gn:name":"La Mesa del Pino",
    "gn:population":93,
    "gn:timezone":"America/Mexico_City",
    "iso:country":"MX",
    "wof:name":"La Mesa del Pino",
    "wof:placetype":"locality",
    "wof:population":93
},
  "geometry": {"coordinates":[-104.10917000000001,21.81806],"type":"Point"}
}