{
  "type": "Feature",
  "properties": {
    "gn:admin1_code":"15",
    "gn:admin2_code":"66.0",
    "gn:asciiname":"Tingambato",
    "gn:country_code":"MX",
    "gn:dem":1134,
    "gn:feature_class":"P",
    "gn:feature_code":"PPL",
    "gn:name":"Tingambato",
    "gn:population":0,
    "gn:timezone":"America/Mexico_City",
    "iso:country":"MX",
    "name:ceb_x_preferred":[
        "Tingambato"
    ],
    "name:epo_x_preferred":[
        "Tingambato"
    ],
    "name:eus_x_preferred":[
        "Tingambato"
    ],
    "name:fra_x_preferred":[
        "Tingambato"
    ],
    "name:ita_x_preferred":[
        "Tingambato"
    ],
    "name:rus_x_preferred":[
        "\u0422\u0438\u043d\u0433\u0430\u043c\u0431\u0430\u0442\u043e"
    ],
    "name:srp_x_preferred":[
        "\u041e\u043f\u0448\u0442\u0438\u043d\u0430 \u0422\u0438\u043d\u0433\u0430\u043c\u0431\u0430\u0442\u043e"
    ],
    "name:swe_x_preferred":[
        "Tingambato"
    ],
    "name:vie_x_preferred":[
        "Tingambato"
    ],
    "wof:name":"Tingambato",
    "wof:placetype":"locality"
},
  "geometry": {"coordinates":[-100.33333,19.08333],"type":"Point"}
}