{
  "type": "Feature",
  "properties": {
    "gn:admin1_code":"20",
    "gn:admin2_code":"266.0",
    "gn:asciiname":"El Mirador",
    "gn:country_code":"MX",
    "gn:dem":656,
    "gn:feature_class":"P",
    "gn:feature_code":"PPL",
    "gn:name":"El Mirador",
    "gn:population":0,
    "gn:timezone":"America/Mexico_City",
    "iso:country":"MX",
    "name:spa_x_preferred":[
        "Mirador"
    ],
    "name:spa_x_variant":[
        "El Mirador"
    ],
    "wof:name":"El Mirador",
    "wof:placetype":"locality"
},
  "geometry": {"coordinates":[-96.17887,15.95355],"type":"Point"}
}