{
  "type": "Feature",
  "properties": {
    "gn:admin1_code":"11.0",
    "gn:admin2_code":"16.0",
    "gn:asciiname":"San Antonio Buenavista",
    "gn:country_code":"MX",
    "gn:dem":1717,
    "gn:feature_class":"P",
    "gn:feature_code":"PPL",
    "gn:name":"San Antonio Buenavista",
    "gn:population":0,
    "gn:timezone":"America/Mexico_City",
    "iso:country":"MX",
    "name:spa_x_preferred":[
        "San Antonio Buenavista"
    ],
    "wof:name":"San Antonio Buenavista",
    "wof:placetype":"locality"
},
  "geometry": {"coordinates":[-101.55798,20.37885],"type":"Point"}
}