{
  "type": "Feature",
  "properties": {
    "gn:admin1_code":"28",
    "gn:admin2_code":"32",
    "gn:asciiname":"Rosalinda Guerrero (El Limon)",
    "gn:country_code":"MX",
    "gn:dem":92,
    "gn:feature_class":"P",
    "gn:feature_code":"PPL",
    "gn:name":"Rosalinda Guerrero (El Lim\u00f3n)",
    "gn:population":13,
    "gn:timezone":"America/Matamoros",
    "iso:country":"MX",
    "name:und_x_variant":[
        "Rosalinda Guerrero (El Lim\u00f3n)"
    ],
    "wof:name":"Rosalinda Guerrero (El Limon)",
    "wof:placetype":"locality",
    "wof:population":13
},
  "geometry": {"coordinates":[-98.35583,25.86972],"type":"Point"}
}