{
  "type": "Feature",
  "properties": {
    "gn:admin1_code":"20",
    "gn:admin2_code":"334.0",
    "gn:asciiname":"La Plata",
    "gn:country_code":"MX",
    "gn:dem":23,
    "gn:feature_class":"P",
    "gn:feature_code":"PPL",
    "gn:name":"La Plata",
    "gn:population":43,
    "gn:timezone":"America/Mexico_City",
    "iso:country":"MX",
    "name:spa_x_preferred":[
        "La Plata"
    ],
    "wof:name":"La Plata",
    "wof:placetype":"locality",
    "wof:population":43
},
  "geometry": {"coordinates":[-97.21673,15.95728],"type":"Point"}
}