{
  "type": "Feature",
  "properties": {
    "gn:admin1_code":"15",
    "gn:admin2_code":"74.0",
    "gn:asciiname":"Colonia Guadalupe",
    "gn:country_code":"MX",
    "gn:dem":2558,
    "gn:feature_class":"P",
    "gn:feature_code":"PPL",
    "gn:name":"Colonia Guadalupe",
    "gn:population":199,
    "gn:timezone":"America/Mexico_City",
    "iso:country":"MX",
    "wof:name":"Colonia Guadalupe",
    "wof:placetype":"locality",
    "wof:population":199
},
  "geometry": {"coordinates":[-99.92921,19.71756],"type":"Point"}
}