{
  "type": "Feature",
  "properties": {
    "gn:admin1_code":"14",
    "gn:admin2_code":"87.0",
    "gn:asciiname":"Mezcalitos",
    "gn:country_code":"MX",
    "gn:dem":1338,
    "gn:feature_class":"P",
    "gn:feature_code":"PPL",
    "gn:name":"Mezcalitos",
    "gn:population":0,
    "gn:timezone":"America/Mexico_City",
    "iso:country":"MX",
    "name:spa_x_preferred":[
        "Mezcalitos"
    ],
    "wof:name":"Mezcalitos",
    "wof:placetype":"locality",
    "wof:population":17
},
  "geometry": {"coordinates":[-103.20779,19.40483],"type":"Point"}
}