{
  "type": "Feature",
  "properties": {
    "gn:admin1_code":"16.0",
    "gn:admin2_code":"2.0",
    "gn:asciiname":"El Granadillo",
    "gn:country_code":"MX",
    "gn:dem":893,
    "gn:feature_class":"P",
    "gn:feature_code":"PPL",
    "gn:name":"El Granadillo",
    "gn:population":0,
    "gn:timezone":"America/Mexico_City",
    "iso:country":"MX",
    "name:spa_x_preferred":[
        "El Granadillo"
    ],
    "wof:name":"El Granadillo",
    "wof:placetype":"locality"
},
  "geometry": {"coordinates":[-102.84811999999999,18.81503],"type":"Point"}
}