{
  "type": "Feature",
  "properties": {
    "gn:admin1_code":"12",
    "gn:admin2_code":"47.0",
    "gn:asciiname":"Salitre Chiquito",
    "gn:country_code":"MX",
    "gn:dem":1716,
    "gn:feature_class":"P",
    "gn:feature_code":"PPL",
    "gn:name":"Salitre Chiquito",
    "gn:population":74,
    "gn:timezone":"America/Mexico_City",
    "iso:country":"MX",
    "wof:name":"Salitre Chiquito",
    "wof:placetype":"locality",
    "wof:population":74
},
  "geometry": {"coordinates":[-99.81865999999999,18.5677],"type":"Point"}
}