{
  "type": "Feature",
  "properties": {
    "gn:admin1_code":"10",
    "gn:admin2_code":"14.0",
    "gn:asciiname":"Las Joyas",
    "gn:country_code":"MX",
    "gn:dem":2070,
    "gn:feature_class":"P",
    "gn:feature_code":"PPL",
    "gn:name":"Las Joyas",
    "gn:population":0,
    "gn:timezone":"America/Monterrey",
    "iso:country":"MX",
    "wof:name":"Las Joyas",
    "wof:placetype":"locality"
},
  "geometry": {"coordinates":[-104.78402,23.32393],"type":"Point"}
}