{
  "type": "Feature",
  "properties": {
    "gn:admin1_code":"10",
    "gn:admin2_code":"4.0",
    "gn:asciiname":"La Manga de Garcia",
    "gn:country_code":"MX",
    "gn:dem":2186,
    "gn:feature_class":"P",
    "gn:feature_code":"PPL",
    "gn:name":"La Manga de Garc\u00eda",
    "gn:population":0,
    "gn:timezone":"America/Monterrey",
    "iso:country":"MX",
    "name:spa_x_preferred":[
        "La Manga de Garc\u00eda"
    ],
    "wof:name":"La Manga de Garcia",
    "wof:placetype":"locality"
},
  "geometry": {"coordinates":[-103.81338,24.34362],"type":"Point"}
}