{
  "type": "Feature",
  "properties": {
    "gn:admin1_code":"20",
    "gn:admin2_code":"559.0",
    "gn:asciiname":"Arroyo de Banco",
    "gn:country_code":"MX",
    "gn:dem":168,
    "gn:feature_class":"P",
    "gn:feature_code":"PPL",
    "gn:name":"Arroyo de Banco",
    "gn:population":0,
    "gn:timezone":"America/Mexico_City",
    "iso:country":"MX",
    "name:spa_x_preferred":[
        "Arroyo de Banco"
    ],
    "wof:name":"Arroyo de Banco",
    "wof:placetype":"locality"
},
  "geometry": {"coordinates":[-96.34793999999999,17.80312],"type":"Point"}
}