{
  "type": "Feature",
  "properties": {
    "gn:admin1_code":"26.0",
    "gn:admin2_code":"29.0",
    "gn:asciiname":"Tres Marias",
    "gn:country_code":"MX",
    "gn:dem":40,
    "gn:feature_class":"P",
    "gn:feature_code":"PPL",
    "gn:name":"Tres Marias",
    "gn:population":0,
    "gn:timezone":"America/Hermosillo",
    "iso:country":"MX",
    "name:spa_x_preferred":[
        "Tres Marias"
    ],
    "wof:name":"Tres Marias",
    "wof:placetype":"locality"
},
  "geometry": {"coordinates":[-110.93895999999999,28.08285],"type":"Point"}
}