{
  "type": "Feature",
  "properties": {
    "gn:admin1_code":"2",
    "gn:admin2_code":"1.0",
    "gn:asciiname":"Familia Rios",
    "gn:country_code":"MX",
    "gn:dem":7,
    "gn:feature_class":"P",
    "gn:feature_code":"PPL",
    "gn:name":"Familia R\u00edos",
    "gn:population":5,
    "gn:timezone":"America/Tijuana",
    "iso:country":"MX",
    "name:und_x_variant":[
        "Familia R\u00edos"
    ],
    "wof:name":"Familia Rios",
    "wof:placetype":"locality",
    "wof:population":5
},
  "geometry": {"coordinates":[-115.98806,30.53944000000001],"type":"Point"}
}