{
  "type": "Feature",
  "properties": {
    "gn:admin1_code":"25",
    "gn:admin2_code":"3.0",
    "gn:asciiname":"Palmar de los Rios",
    "gn:country_code":"MX",
    "gn:dem":249,
    "gn:feature_class":"P",
    "gn:feature_code":"PPL",
    "gn:name":"Palmar de los R\u00edos",
    "gn:population":228,
    "gn:timezone":"America/Mazatlan",
    "iso:country":"MX",
    "name:und_x_variant":[
        "Palmar de los R\u00edos"
    ],
    "wof:name":"Palmar de los Rios",
    "wof:placetype":"locality",
    "wof:population":228
},
  "geometry": {"coordinates":[-107.45222,25.32222],"type":"Point"}
}