{
  "type": "Feature",
  "properties": {
    "gn:admin1_code":"29",
    "gn:admin2_code":"34",
    "gn:asciiname":"Tlacotla",
    "gn:country_code":"MX",
    "gn:dem":2647,
    "gn:feature_class":"P",
    "gn:feature_code":"PPL",
    "gn:name":"Tlacotla",
    "gn:population":10,
    "gn:timezone":"America/Mexico_City",
    "iso:country":"MX",
    "wof:name":"Tlacotla",
    "wof:placetype":"locality",
    "wof:population":10
},
  "geometry": {"coordinates":[-98.10187999999999,19.6239],"type":"Point"}
}