{
  "type": "Feature",
  "properties": {
    "gn:admin1_code":"5",
    "gn:admin2_code":"9",
    "gn:asciiname":"Buenaventura",
    "gn:country_code":"MX",
    "gn:dem":57,
    "gn:feature_class":"P",
    "gn:feature_code":"PPL",
    "gn:name":"Buenaventura",
    "gn:population":13,
    "gn:timezone":"America/Mexico_City",
    "iso:country":"MX",
    "wof:name":"Buenaventura",
    "wof:placetype":"locality",
    "wof:population":13
},
  "geometry": {"coordinates":[-93.86083000000001,16.21694],"type":"Point"}
}