{
  "type": "Feature",
  "properties": {
    "gn:admin1_code":"28",
    "gn:admin2_code":"34.0",
    "gn:asciiname":"El Carrizo de Uriegas",
    "gn:country_code":"MX",
    "gn:dem":557,
    "gn:feature_class":"P",
    "gn:feature_code":"PPL",
    "gn:name":"El Carrizo de Uriegas",
    "gn:population":0,
    "gn:timezone":"America/Monterrey",
    "iso:country":"MX",
    "name:spa_x_preferred":[
        "El Carrizo de Uriegas"
    ],
    "name:und_x_variant":[
        "Rancho El Carrizo",
        "Carrizos"
    ],
    "wof:name":"El Carrizo de Uriegas",
    "wof:placetype":"locality"
},
  "geometry": {"coordinates":[-98.99986,24.81656],"type":"Point"}
}