{
  "type": "Feature",
  "properties": {
    "gn:admin1_code":"7",
    "gn:admin2_code":"34.0",
    "gn:asciiname":"San Rafael",
    "gn:country_code":"MX",
    "gn:dem":1314,
    "gn:feature_class":"P",
    "gn:feature_code":"PPL",
    "gn:name":"San Rafael",
    "gn:population":6,
    "gn:timezone":"America/Monterrey",
    "iso:country":"MX",
    "wof:name":"San Rafael",
    "wof:placetype":"locality",
    "wof:population":6
},
  "geometry": {"coordinates":[-103.67711,28.09466],"type":"Point"}
}