{
  "type": "Feature",
  "properties": {
    "gn:admin1_code":"17",
    "gn:asciiname":"La Golondrina",
    "gn:country_code":"MX",
    "gn:dem":2323,
    "gn:feature_class":"P",
    "gn:feature_code":"PPL",
    "gn:name":"La Golondrina",
    "gn:population":0,
    "gn:timezone":"America/Mexico_City",
    "iso:country":"MX",
    "name:spa_x_preferred":[
        "La Golondrina"
    ],
    "wof:name":"La Golondrina",
    "wof:placetype":"locality"
},
  "geometry": {"coordinates":[-98.93792000000001,19.86905],"type":"Point"}
}