{
  "type": "Feature",
  "properties": {
    "gn:admin1_code":"5",
    "gn:admin2_code":"52",
    "gn:asciiname":"27 de Marzo del 94 (El Quis)",
    "gn:country_code":"MX",
    "gn:dem":1548,
    "gn:feature_class":"P",
    "gn:feature_code":"PPL",
    "gn:name":"27 de Marzo del 94 (El Quis)",
    "gn:population":45,
    "gn:timezone":"America/Mexico_City",
    "iso:country":"MX",
    "wof:name":"27 de Marzo del 94 (El Quis)",
    "wof:placetype":"locality",
    "wof:population":45
},
  "geometry": {"coordinates":[-91.98472,16.42361],"type":"Point"}
}