{
  "type": "Feature",
  "properties": {
    "gn:admin1_code":"2.0",
    "gn:admin2_code":"1.0",
    "gn:asciiname":"Calmalli",
    "gn:country_code":"MX",
    "gn:dem":342,
    "gn:feature_class":"P",
    "gn:feature_code":"PPL",
    "gn:name":"Calmalli",
    "gn:population":0,
    "gn:timezone":"America/Tijuana",
    "iso:country":"MX",
    "name:und_x_variant":[
        "Calimali",
        "Calmell\u00ed"
    ],
    "wof:name":"Calmalli",
    "wof:placetype":"locality"
},
  "geometry": {"coordinates":[-113.43219000000001,28.11567],"type":"Point"}
}