{
  "type": "Feature",
  "properties": {
    "gn:admin1_code":"6",
    "gn:admin2_code":"65.0",
    "gn:asciiname":"El Potrerito",
    "gn:country_code":"MX",
    "gn:dem":1482,
    "gn:feature_class":"P",
    "gn:feature_code":"PPL",
    "gn:name":"El Potrerito",
    "gn:population":1,
    "gn:timezone":"America/Chihuahua",
    "iso:country":"MX",
    "name:spa_x_preferred":[
        "El Potrerito"
    ],
    "wof:name":"El Potrerito",
    "wof:placetype":"locality",
    "wof:population":1
},
  "geometry": {"coordinates":[-108.22046,27.17304],"type":"Point"}
}