{
  "type": "Feature",
  "properties": {
    "gn:admin1_code":"12",
    "gn:admin2_code":"48",
    "gn:asciiname":"La Bolsa",
    "gn:country_code":"MX",
    "gn:dem":398,
    "gn:feature_class":"P",
    "gn:feature_code":"PPL",
    "gn:name":"La Bolsa",
    "gn:population":35,
    "gn:timezone":"America/Mexico_City",
    "iso:country":"MX",
    "wof:name":"La Bolsa",
    "wof:placetype":"locality",
    "wof:population":35
},
  "geometry": {"coordinates":[-101.26142,17.77388],"type":"Point"}
}