{
  "type": "Feature",
  "properties": {
    "gn:admin1_code":"12",
    "gn:admin2_code":"28.0",
    "gn:asciiname":"Tecongo",
    "gn:country_code":"MX",
    "gn:dem":1121,
    "gn:feature_class":"P",
    "gn:feature_code":"PPL",
    "gn:name":"Tecongo",
    "gn:population":340,
    "gn:timezone":"America/Mexico_City",
    "iso:country":"MX",
    "wof:name":"Tecongo",
    "wof:placetype":"locality",
    "wof:population":340
},
  "geometry": {"coordinates":[-99.03222,17.33861],"type":"Point"}
}