{
  "type": "Feature",
  "properties": {
    "gn:admin1_code":"5",
    "gn:admin2_code":"103.0",
    "gn:asciiname":"Medio Dia",
    "gn:country_code":"MX",
    "gn:dem":332,
    "gn:feature_class":"P",
    "gn:feature_code":"PPL",
    "gn:name":"Medio D\u00eda",
    "gn:population":0,
    "gn:timezone":"America/Mexico_City",
    "iso:country":"MX",
    "name:spa_x_preferred":[
        "Medio D\u00eda"
    ],
    "name:und_x_variant":[
        "Mediod\u00eda"
    ],
    "wof:name":"Medio Dia",
    "wof:placetype":"locality"
},
  "geometry": {"coordinates":[-92.41695,15.21046],"type":"Point"}
}