{
  "type": "Feature",
  "properties": {
    "gn:admin1_code":"14.0",
    "gn:admin2_code":"86.0",
    "gn:asciiname":"El Monte",
    "gn:country_code":"MX",
    "gn:dem":2293,
    "gn:feature_class":"P",
    "gn:feature_code":"PPL",
    "gn:name":"El Monte",
    "gn:population":0,
    "gn:timezone":"America/Mexico_City",
    "iso:country":"MX",
    "name:spa_x_preferred":[
        "El Monte"
    ],
    "wof:name":"El Monte",
    "wof:placetype":"locality"
},
  "geometry": {"coordinates":[-103.68485,19.91689],"type":"Point"}
}