{
  "type": "Feature",
  "properties": {
    "gn:admin1_code":"5",
    "gn:admin2_code":"59",
    "gn:asciiname":"Patria Nueva (La Laguna)",
    "gn:country_code":"MX",
    "gn:dem":656,
    "gn:feature_class":"P",
    "gn:feature_code":"PPL",
    "gn:name":"Patria Nueva (La Laguna)",
    "gn:population":28,
    "gn:timezone":"America/Mexico_City",
    "iso:country":"MX",
    "wof:name":"Patria Nueva (La Laguna)",
    "wof:placetype":"locality",
    "wof:population":28
},
  "geometry": {"coordinates":[-91.7525,17.12944],"type":"Point"}
}