{
  "type": "Feature",
  "properties": {
    "gn:admin1_code":"14",
    "gn:admin2_code":"19.0",
    "gn:asciiname":"Ventanilla",
    "gn:country_code":"MX",
    "gn:dem":1309,
    "gn:feature_class":"P",
    "gn:feature_code":"PPL",
    "gn:name":"Ventanilla",
    "gn:population":6,
    "gn:timezone":"America/Mexico_City",
    "iso:country":"MX",
    "name:ceb_x_preferred":[
        "Ventanilla"
    ],
    "name:spa_x_preferred":[
        "Ventanilla"
    ],
    "name:swe_x_preferred":[
        "Ventanilla"
    ],
    "wof:name":"Ventanilla",
    "wof:placetype":"locality",
    "wof:population":6
},
  "geometry": {"coordinates":[-103.99527999999999,21.86111],"type":"Point"}
}