{
  "type": "Feature",
  "properties": {
    "gn:admin1_code":"20",
    "gn:admin2_code":"21",
    "gn:asciiname":"La Aurora",
    "gn:country_code":"MX",
    "gn:dem":172,
    "gn:feature_class":"P",
    "gn:feature_code":"PPL",
    "gn:name":"La Aurora",
    "gn:population":35,
    "gn:timezone":"America/Mexico_City",
    "iso:country":"MX",
    "wof:name":"La Aurora",
    "wof:placetype":"locality",
    "wof:population":35
},
  "geometry": {"coordinates":[-96.66583,18.56694],"type":"Point"}
}