{
  "type": "Feature",
  "properties": {
    "gn:admin1_code":"18",
    "gn:admin2_code":"2.0",
    "gn:asciiname":"Las Norias",
    "gn:country_code":"MX",
    "gn:dem":1016,
    "gn:feature_class":"P",
    "gn:feature_code":"PPL",
    "gn:name":"Las Norias",
    "gn:population":8,
    "gn:timezone":"America/Mazatlan",
    "iso:country":"MX",
    "wof:name":"Las Norias",
    "wof:placetype":"locality",
    "wof:population":8
},
  "geometry": {"coordinates":[-104.45556000000001,21.03917],"type":"Point"}
}