{
  "type": "Feature",
  "properties": {
    "gn:admin1_code":"24",
    "gn:admin2_code":"15.0",
    "gn:asciiname":"San Elias",
    "gn:country_code":"MX",
    "gn:dem":2224,
    "gn:feature_class":"P",
    "gn:feature_code":"PPL",
    "gn:name":"San El\u00edas",
    "gn:population":5,
    "gn:timezone":"America/Mexico_City",
    "iso:country":"MX",
    "name:und_x_variant":[
        "San El\u00edas"
    ],
    "wof:name":"San Elias",
    "wof:placetype":"locality",
    "wof:population":5
},
  "geometry": {"coordinates":[-101.10666999999999,23.20472],"type":"Point"}
}