{
  "type": "Feature",
  "properties": {
    "gn:admin1_code":"12",
    "gn:admin2_code":"41.0",
    "gn:asciiname":"Atlamajalcingo del Monte",
    "gn:cc2":"MX",
    "gn:country_code":"MX",
    "gn:dem":1818,
    "gn:feature_class":"P",
    "gn:feature_code":"PPL",
    "gn:name":"Atlamajalcingo del Monte",
    "gn:population":0,
    "gn:timezone":"America/Mexico_City",
    "iso:country":"MX",
    "name:und_x_variant":[
        "Atlamajaicingo",
        "Atlamajalcingo",
        "Atlamajaicingo del Monte",
        "Atlamajalcingo del Monte"
    ],
    "wof:name":"Atlamajalcingo del Monte",
    "wof:placetype":"locality"
},
  "geometry": {"coordinates":[-98.68333,17.18333],"type":"Point"}
}