{
  "type": "Feature",
  "properties": {
    "gn:admin1_code":"12",
    "gn:admin2_code":"41.0",
    "gn:asciiname":"Atlamajalcingo del Monte",
    "gn:cc2":"MX",
    "gn:country_code":"MX",
    "gn:dem":1818,
    "gn:feature_class":"P",
    "gn:feature_code":"PPL",
    "gn:name":"Atlamajalcingo del Monte",
    "gn:population":0,
    "gn:timezone":"America/Mexico_City",
    "iso:country":"MX",
    "name:ceb_x_preferred":[
        "Atlamajalcingo del Monte"
    ],
    "name:ita_x_preferred":[
        "Atlamajalcingo del Monte"
    ],
    "name:por_x_preferred":[
        "Atlamajalcingo del Monte"
    ],
    "name:sco_x_preferred":[
        "Atlamajalcingo del Monte"
    ],
    "name:spa_x_preferred":[
        "Atlamajalcingo del Monte"
    ],
    "name:srp_x_preferred":[
        "\u0410\u0442\u043b\u0430\u043c\u0430\u0445\u0430\u043b\u0441\u0438\u043d\u0433\u043e \u0434\u0435\u043b \u041c\u043e\u043d\u0442\u0435"
    ],
    "name:swe_x_preferred":[
        "Atlamajalcingo del Monte"
    ],
    "name:und_x_variant":[
        "Atlamajaicingo",
        "Atlamajalcingo",
        "Atlamajaicingo del Monte",
        "Atlamajalcingo del Monte"
    ],
    "wof:name":"Atlamajalcingo del Monte",
    "wof:placetype":"locality"
},
  "geometry": {"coordinates":[-98.68333,17.18333],"type":"Point"}
}