{
  "type": "Feature",
  "properties": {
    "gn:admin1_code":"19",
    "gn:admin2_code":"20.0",
    "gn:asciiname":"Las Tranquitas",
    "gn:country_code":"MX",
    "gn:dem":128,
    "gn:feature_class":"P",
    "gn:feature_code":"PPL",
    "gn:name":"Las Tranquitas",
    "gn:population":0,
    "gn:timezone":"America/Monterrey",
    "iso:country":"MX",
    "name:spa_x_preferred":[
        "Las Tranquilas"
    ],
    "name:spa_x_variant":[
        "Las Tranquitas"
    ],
    "wof:name":"Las Tranquitas",
    "wof:placetype":"locality"
},
  "geometry": {"coordinates":[-99.09416,25.84455],"type":"Point"}
}