{
  "type": "Feature",
  "properties": {
    "gn:admin1_code":"30",
    "gn:admin2_code":"44.0",
    "gn:asciiname":"Villa Rica",
    "gn:country_code":"MX",
    "gn:dem":912,
    "gn:feature_class":"P",
    "gn:feature_code":"PPL",
    "gn:name":"Villa Rica",
    "gn:population":54,
    "gn:timezone":"America/Mexico_City",
    "iso:country":"MX",
    "wof:name":"Villa Rica",
    "wof:placetype":"locality",
    "wof:population":54
},
  "geometry": {"coordinates":[-96.94,18.91333],"type":"Point"}
}