{
  "type": "Feature",
  "properties": {
    "gn:admin1_code":"30",
    "gn:admin2_code":"91.0",
    "gn:asciiname":"Los Milagros",
    "gn:country_code":"MX",
    "gn:dem":74,
    "gn:feature_class":"P",
    "gn:feature_code":"PPL",
    "gn:name":"Los Milagros",
    "gn:population":6,
    "gn:timezone":"America/Mexico_City",
    "iso:country":"MX",
    "name:ita_x_preferred":[
        "Los Milagros"
    ],
    "name:spa_x_preferred":[
        "Los Milagros"
    ],
    "name:zho_x_preferred":[
        "\u6d1b\u65af\u7c73\u62c9\u683c\u7f57\u65af"
    ],
    "wof:name":"Los Milagros",
    "wof:placetype":"locality",
    "wof:population":6
},
  "geometry": {"coordinates":[-95.13083,17.48972],"type":"Point"}
}