{
  "type": "Feature",
  "properties": {
    "gn:admin1_code":"13.0",
    "gn:admin2_code":"27.0",
    "gn:asciiname":"Tierra Amarilla",
    "gn:country_code":"MX",
    "gn:dem":335,
    "gn:feature_class":"P",
    "gn:feature_code":"PPL",
    "gn:name":"Tierra Amarilla",
    "gn:population":36,
    "gn:timezone":"America/Mexico_City",
    "iso:country":"MX",
    "name:spa_x_preferred":[
        "Tierra Amarilla"
    ],
    "wof:name":"Tierra Amarilla",
    "wof:placetype":"locality",
    "wof:population":36
},
  "geometry": {"coordinates":[-98.02231,20.56527],"type":"Point"}
}