{
  "type": "Feature",
  "properties": {
    "gn:admin1_code":"3",
    "gn:admin2_code":"3.0",
    "gn:asciiname":"El Manantial",
    "gn:country_code":"MX",
    "gn:dem":128,
    "gn:feature_class":"P",
    "gn:feature_code":"PPL",
    "gn:name":"El Manantial",
    "gn:population":4,
    "gn:timezone":"America/Mazatlan",
    "iso:country":"MX",
    "wof:name":"El Manantial",
    "wof:placetype":"locality",
    "wof:population":4
},
  "geometry": {"coordinates":[-111.22083000000001,24.8183],"type":"Point"}
}