{
  "type": "Feature",
  "properties": {
    "gn:admin1_code":"14",
    "gn:admin2_code":"69.0",
    "gn:asciiname":"Puerta de Agujas",
    "gn:country_code":"MX",
    "gn:dem":2022,
    "gn:feature_class":"P",
    "gn:feature_code":"PPL",
    "gn:name":"Puerta de Agujas",
    "gn:population":59,
    "gn:timezone":"America/Mexico_City",
    "iso:country":"MX",
    "wof:name":"Puerta de Agujas",
    "wof:placetype":"locality",
    "wof:population":59
},
  "geometry": {"coordinates":[-102.92306000000001,19.87],"type":"Point"}
}