{
  "type": "Feature",
  "properties": {
    "gn:admin1_code":"10.0",
    "gn:admin2_code":"35.0",
    "gn:asciiname":"La Mesa del Chorro",
    "gn:country_code":"MX",
    "gn:dem":2369,
    "gn:feature_class":"P",
    "gn:feature_code":"PPL",
    "gn:name":"La Mesa del Chorro",
    "gn:population":0,
    "gn:timezone":"America/Monterrey",
    "iso:country":"MX",
    "name:spa_x_preferred":[
        "La Mesa del Chorro"
    ],
    "wof:name":"La Mesa del Chorro",
    "wof:placetype":"locality"
},
  "geometry": {"coordinates":[-106.12133,25.20442],"type":"Point"}
}