{
  "type": "Feature",
  "properties": {
    "gn:admin1_code":"15.0",
    "gn:admin2_code":"8.0",
    "gn:asciiname":"Los Amolar",
    "gn:country_code":"MX",
    "gn:dem":1015,
    "gn:feature_class":"P",
    "gn:feature_code":"PPL",
    "gn:name":"Los Amolar",
    "gn:population":0,
    "gn:timezone":"America/Mexico_City",
    "iso:country":"MX",
    "wof:name":"Los Amolar",
    "wof:placetype":"locality"
},
  "geometry": {"coordinates":[-100.37166000000001,18.65986],"type":"Point"}
}