{
  "type": "Feature",
  "properties": {
    "gn:admin1_code":"13",
    "gn:admin2_code":"80.0",
    "gn:asciiname":"Hueyactetl",
    "gn:country_code":"MX",
    "gn:dem":215,
    "gn:feature_class":"P",
    "gn:feature_code":"PPL",
    "gn:name":"Hueyact\u00e9tl",
    "gn:population":123,
    "gn:timezone":"America/Mexico_City",
    "iso:country":"MX",
    "name:und_x_variant":[
        "Hueyact\u00e9tl"
    ],
    "wof:name":"Hueyactetl",
    "wof:placetype":"locality",
    "wof:population":123
},
  "geometry": {"coordinates":[-98.39972,20.96611],"type":"Point"}
}