{
  "type": "Feature",
  "properties": {
    "gn:admin1_code":"10",
    "gn:admin2_code":"9.0",
    "gn:asciiname":"Aguaje las Palomas",
    "gn:country_code":"MX",
    "gn:dem":2332,
    "gn:feature_class":"P",
    "gn:feature_code":"PPL",
    "gn:name":"Aguaje las Palomas",
    "gn:population":0,
    "gn:timezone":"America/Monterrey",
    "iso:country":"MX",
    "name:spa_x_preferred":[
        "Aguaje las Palomas"
    ],
    "wof:name":"Aguaje las Palomas",
    "wof:placetype":"locality"
},
  "geometry": {"coordinates":[-105.58175,25.63467],"type":"Point"}
}