{
  "type": "Feature",
  "properties": {
    "gn:admin1_code":"3",
    "gn:admin2_code":"2.0",
    "gn:asciiname":"La Tinaja de San Pedro",
    "gn:country_code":"MX",
    "gn:dem":768,
    "gn:feature_class":"P",
    "gn:feature_code":"PPL",
    "gn:name":"La Tinaja de San Pedro",
    "gn:population":0,
    "gn:timezone":"America/Mazatlan",
    "iso:country":"MX",
    "name:spa_x_preferred":[
        "La Tinaja de San Pedro"
    ],
    "wof:name":"La Tinaja de San Pedro",
    "wof:placetype":"locality"
},
  "geometry": {"coordinates":[-112.07238999999998,26.54367],"type":"Point"}
}