{
  "type": "Feature",
  "properties": {
    "gn:admin1_code":"24",
    "gn:admin2_code":"32.0",
    "gn:asciiname":"Balneario de Lourdes [Centro Vacacional]",
    "gn:country_code":"MX",
    "gn:dem":1664,
    "gn:feature_class":"P",
    "gn:feature_code":"PPL",
    "gn:name":"Balneario de Lourdes [Centro Vacacional]",
    "gn:population":124,
    "gn:timezone":"America/Mexico_City",
    "iso:country":"MX",
    "wof:name":"Balneario de Lourdes [Centro Vacacional]",
    "wof:placetype":"locality",
    "wof:population":124
},
  "geometry": {"coordinates":[-100.63,21.78056],"type":"Point"}
}