{
  "type": "Feature",
  "properties": {
    "gn:admin1_code":"19",
    "gn:admin2_code":"24",
    "gn:asciiname":"El Alamo (La Casena y la Pajarena)",
    "gn:country_code":"MX",
    "gn:dem":1394,
    "gn:feature_class":"P",
    "gn:feature_code":"PPL",
    "gn:name":"El \u00c1lamo (La Case\u00f1a y la Pajare\u00f1a)",
    "gn:population":10,
    "gn:timezone":"America/Monterrey",
    "iso:country":"MX",
    "name:und_x_variant":[
        "El \u00c1lamo (La Case\u00f1a y la Pajare\u00f1a)"
    ],
    "wof:name":"El Alamo (La Casena y la Pajarena)",
    "wof:placetype":"locality",
    "wof:population":10
},
  "geometry": {"coordinates":[-99.76939,23.96703],"type":"Point"}
}