{
  "type": "Feature",
  "properties": {
    "gn:admin1_code":"16.0",
    "gn:admin2_code":"10.0",
    "gn:asciiname":"La Fundicion",
    "gn:country_code":"MX",
    "gn:dem":639,
    "gn:feature_class":"P",
    "gn:feature_code":"PPL",
    "gn:name":"La Fundici\u00f3n",
    "gn:population":0,
    "gn:timezone":"America/Mexico_City",
    "iso:country":"MX",
    "name:spa_x_preferred":[
        "La Fundici\u00f3n"
    ],
    "wof:name":"La Fundicion",
    "wof:placetype":"locality"
},
  "geometry": {"coordinates":[-102.1139,18.65514],"type":"Point"}
}