{
  "type": "Feature",
  "properties": {
    "gn:admin1_code":"10",
    "gn:admin2_code":"7.0",
    "gn:asciiname":"Jolo (Diecinueve de Octubre)",
    "gn:country_code":"MX",
    "gn:dem":1118,
    "gn:feature_class":"P",
    "gn:feature_code":"PPL",
    "gn:name":"Jolo (Diecinueve de Octubre)",
    "gn:population":310,
    "gn:timezone":"America/Monterrey",
    "iso:country":"MX",
    "wof:name":"Jolo (Diecinueve de Octubre)",
    "wof:placetype":"locality",
    "wof:population":310
},
  "geometry": {"coordinates":[-103.51639,25.67833],"type":"Point"}
}