{
  "type": "Feature",
  "properties": {
    "gn:admin1_code":"14.0",
    "gn:admin2_code":"8.0",
    "gn:asciiname":"Caracol",
    "gn:country_code":"MX",
    "gn:dem":2134,
    "gn:feature_class":"P",
    "gn:feature_code":"PPL",
    "gn:name":"Caracol",
    "gn:population":0,
    "gn:timezone":"America/Mexico_City",
    "iso:country":"MX",
    "wof:name":"Caracol",
    "wof:placetype":"locality"
},
  "geometry": {"coordinates":[-102.44062,20.85516],"type":"Point"}
}