{
  "type": "Feature",
  "properties": {
    "gn:admin1_code":"27",
    "gn:admin2_code":"6.0",
    "gn:asciiname":"Marin (Rampa de Panuncio)",
    "gn:country_code":"MX",
    "gn:dem":19,
    "gn:feature_class":"P",
    "gn:feature_code":"PPL",
    "gn:name":"Mar\u00edn (Rampa de Panuncio)",
    "gn:population":945,
    "gn:timezone":"America/Mexico_City",
    "iso:country":"MX",
    "name:und_x_variant":[
        "Mar\u00edn (Rampa de Panuncio)"
    ],
    "wof:name":"Marin (Rampa de Panuncio)",
    "wof:placetype":"locality",
    "wof:population":945
},
  "geometry": {"coordinates":[-93.20473,17.98875],"type":"Point"}
}