{
  "type": "Feature",
  "properties": {
    "gn:admin1_code":"15",
    "gn:admin2_code":"3.0",
    "gn:asciiname":"El Azafran",
    "gn:country_code":"MX",
    "gn:dem":2648,
    "gn:feature_class":"P",
    "gn:feature_code":"PPL",
    "gn:name":"El Azafr\u00e1n",
    "gn:population":0,
    "gn:timezone":"America/Mexico_City",
    "iso:country":"MX",
    "name:spa_x_preferred":[
        "El Azafr\u00e1n"
    ],
    "wof:name":"El Azafran",
    "wof:placetype":"locality"
},
  "geometry": {"coordinates":[-99.71827,20.03742],"type":"Point"}
}