{
  "type": "Feature",
  "properties": {
    "gn:admin1_code":"6",
    "gn:admin2_code":"7.0",
    "gn:asciiname":"Rancho La Tableta",
    "gn:country_code":"MX",
    "gn:dem":1984,
    "gn:feature_class":"P",
    "gn:feature_code":"PPL",
    "gn:name":"Rancho La Tableta",
    "gn:population":0,
    "gn:timezone":"America/Chihuahua",
    "iso:country":"MX",
    "name:spa_x_preferred":[
        "Rancho La Tableta"
    ],
    "wof:name":"Rancho La Tableta",
    "wof:placetype":"locality"
},
  "geometry": {"coordinates":[-106.21984,26.83995],"type":"Point"}
}