{
  "type": "Feature",
  "properties": {
    "gn:admin1_code":"22",
    "gn:admin2_code":"16.0",
    "gn:asciiname":"Guadalupe Helgueros",
    "gn:country_code":"MX",
    "gn:dem":2141,
    "gn:feature_class":"P",
    "gn:feature_code":"PPL",
    "gn:name":"Guadalupe Helgueros",
    "gn:population":0,
    "gn:timezone":"America/Mexico_City",
    "iso:country":"MX",
    "name:spa_x_preferred":[
        "Guadalupe Helgueros"
    ],
    "name:und_x_variant":[
        "Guadalupe",
        "Guadalupe Helqueva"
    ],
    "wof:name":"Guadalupe Helgueros",
    "wof:placetype":"locality"
},
  "geometry": {"coordinates":[-99.93854,20.34977],"type":"Point"}
}