{
  "type": "Feature",
  "properties": {
    "gn:admin1_code":"12",
    "gn:admin2_code":"28.0",
    "gn:asciiname":"Tlatempa",
    "gn:country_code":"MX",
    "gn:dem":2143,
    "gn:feature_class":"P",
    "gn:feature_code":"PPL",
    "gn:name":"Tlatempa",
    "gn:population":148,
    "gn:timezone":"America/Mexico_City",
    "iso:country":"MX",
    "wof:name":"Tlatempa",
    "wof:placetype":"locality",
    "wof:population":148
},
  "geometry": {"coordinates":[-99.05634999999999,17.57195],"type":"Point"}
}