{
  "type": "Feature",
  "properties": {
    "gn:admin1_code":"19.0",
    "gn:admin2_code":"17.0",
    "gn:asciiname":"San Juan de Mimbres",
    "gn:country_code":"MX",
    "gn:dem":2077,
    "gn:feature_class":"P",
    "gn:feature_code":"PPL",
    "gn:name":"San Juan de Mimbres",
    "gn:population":0,
    "gn:timezone":"America/Monterrey",
    "iso:country":"MX",
    "name:spa_x_preferred":[
        "San Juan del Mimbre"
    ],
    "name:spa_x_variant":[
        "San Juan de Mimbres"
    ],
    "wof:name":"San Juan de Mimbres",
    "wof:placetype":"locality"
},
  "geometry": {"coordinates":[-100.23323000000001,25.02409],"type":"Point"}
}