{
  "type": "Feature",
  "properties": {
    "gn:admin1_code":"4",
    "gn:admin2_code":"3.0",
    "gn:asciiname":"Maria Isabel",
    "gn:country_code":"MX",
    "gn:dem":10,
    "gn:feature_class":"P",
    "gn:feature_code":"PPL",
    "gn:name":"Mar\u00eda Isabel",
    "gn:population":5,
    "gn:timezone":"America/Merida",
    "iso:country":"MX",
    "name:spa_x_preferred":[
        "El Pajal y las Truchas"
    ],
    "name:spa_x_variant":[
        "Mar\u00eda Isabel"
    ],
    "name:und_x_variant":[
        "Mar\u00eda Isabel"
    ],
    "wof:name":"Maria Isabel",
    "wof:placetype":"locality",
    "wof:population":5
},
  "geometry": {"coordinates":[-91.44167,18.23139],"type":"Point"}
}