{
  "type": "Feature",
  "properties": {
    "gn:admin1_code":"26.0",
    "gn:admin2_code":"52.0",
    "gn:asciiname":"Puerto Venado",
    "gn:country_code":"MX",
    "gn:dem":1911,
    "gn:feature_class":"P",
    "gn:feature_code":"PPL",
    "gn:name":"Puerto Venado",
    "gn:population":0,
    "gn:timezone":"America/Chihuahua",
    "iso:country":"MX",
    "name:spa_x_preferred":[
        "Puerto Venado"
    ],
    "wof:name":"Puerto Venado",
    "wof:placetype":"locality"
},
  "geometry": {"coordinates":[-108.58401000000001,28.58697],"type":"Point"}
}