{
  "type": "Feature",
  "properties": {
    "gn:admin1_code":"28",
    "gn:admin2_code":"4",
    "gn:asciiname":"San Francisco Uno",
    "gn:country_code":"MX",
    "gn:dem":221,
    "gn:feature_class":"P",
    "gn:feature_code":"PPL",
    "gn:name":"San Francisco Uno",
    "gn:population":11,
    "gn:timezone":"America/Monterrey",
    "iso:country":"MX",
    "wof:name":"San Francisco Uno",
    "wof:placetype":"locality",
    "wof:population":11
},
  "geometry": {"coordinates":[-99.1125,22.55583],"type":"Point"}
}