{
  "type": "Feature",
  "properties": {
    "gn:admin1_code":"24.0",
    "gn:admin2_code":"11.0",
    "gn:asciiname":"Labor Vieja",
    "gn:country_code":"MX",
    "gn:dem":1035,
    "gn:feature_class":"P",
    "gn:feature_code":"PPL",
    "gn:name":"Labor Vieja",
    "gn:population":0,
    "gn:timezone":"America/Mexico_City",
    "iso:country":"MX",
    "wof:name":"Labor Vieja",
    "wof:placetype":"locality"
},
  "geometry": {"coordinates":[-100.14288000000001,22.01293],"type":"Point"}
}