{
  "type": "Feature",
  "properties": {
    "gn:admin1_code":"30.0",
    "gn:admin2_code":"121.0",
    "gn:asciiname":"La Hormiga",
    "gn:country_code":"MX",
    "gn:dem":60,
    "gn:feature_class":"P",
    "gn:feature_code":"PPL",
    "gn:name":"La Hormiga",
    "gn:population":0,
    "gn:timezone":"America/Mexico_City",
    "iso:country":"MX",
    "name:spa_x_preferred":[
        "La Hormiga"
    ],
    "wof:name":"La Hormiga",
    "wof:placetype":"locality"
},
  "geometry": {"coordinates":[-97.96583,21.72556],"type":"Point"}
}