{
  "type": "Feature",
  "properties": {
    "gn:admin1_code":"28.0",
    "gn:admin2_code":"43.0",
    "gn:asciiname":"La Revancha",
    "gn:country_code":"MX",
    "gn:dem":115,
    "gn:feature_class":"P",
    "gn:feature_code":"PPL",
    "gn:name":"La Revancha",
    "gn:population":0,
    "gn:timezone":"America/Monterrey",
    "iso:country":"MX",
    "name:spa_x_preferred":[
        "La Revancha"
    ],
    "wof:name":"La Revancha",
    "wof:placetype":"locality"
},
  "geometry": {"coordinates":[-98.92476000000001,23.06153],"type":"Point"}
}