{
  "type": "Feature",
  "properties": {
    "gn:admin1_code":"20",
    "gn:admin2_code":"297.0",
    "gn:asciiname":"San Cristobal Linda Vista",
    "gn:country_code":"MX",
    "gn:dem":2034,
    "gn:feature_class":"P",
    "gn:feature_code":"PPL",
    "gn:name":"San Crist\u00f3bal Linda Vista",
    "gn:population":72,
    "gn:timezone":"America/Mexico_City",
    "iso:country":"MX",
    "name:und_x_variant":[
        "San Crist\u00f3bal Linda Vista"
    ],
    "wof:name":"San Cristobal Linda Vista",
    "wof:placetype":"locality",
    "wof:population":72
},
  "geometry": {"coordinates":[-97.47083000000001,17.05528],"type":"Point"}
}