{
  "type": "Feature",
  "properties": {
    "gn:admin1_code":"21.0",
    "gn:admin2_code":"86.0",
    "gn:asciiname":"El Pinal",
    "gn:country_code":"MX",
    "gn:dem":540,
    "gn:feature_class":"P",
    "gn:feature_code":"PPL",
    "gn:name":"El Pi\u00f1al",
    "gn:population":192,
    "gn:timezone":"America/Mexico_City",
    "iso:country":"MX",
    "name:spa_x_preferred":[
        "El Pi\u00f1al"
    ],
    "wof:name":"El Pinal",
    "wof:placetype":"locality",
    "wof:population":192
},
  "geometry": {"coordinates":[-97.83963,20.45762],"type":"Point"}
}