{
  "type": "Feature",
  "properties": {
    "gn:admin1_code":"11",
    "gn:admin2_code":"13.0",
    "gn:asciiname":"La Fortuna",
    "gn:country_code":"MX",
    "gn:dem":2094,
    "gn:feature_class":"P",
    "gn:feature_code":"PPL",
    "gn:name":"La Fortuna",
    "gn:population":240,
    "gn:timezone":"America/Mexico_City",
    "iso:country":"MX",
    "name:ceb_x_preferred":[
        "La Fortuna"
    ],
    "name:deu_x_preferred":[
        "O Fortuna"
    ],
    "name:fra_x_preferred":[
        "La Fortuna"
    ],
    "name:spa_x_preferred":[
        "La Fortuna"
    ],
    "name:srp_x_preferred":[
        "\u041b\u0430 \u0424\u043e\u0440\u0442\u0443\u043d\u0430"
    ],
    "name:swe_x_preferred":[
        "La Fortuna"
    ],
    "wof:name":"La Fortuna",
    "wof:placetype":"locality",
    "wof:population":240
},
  "geometry": {"coordinates":[-100.34305999999999,21.13639],"type":"Point"}
}