{
  "type": "Feature",
  "properties": {
    "gn:admin1_code":"16.0",
    "gn:admin2_code":"15.0",
    "gn:asciiname":"El Ojo de Agua del Cobre",
    "gn:country_code":"MX",
    "gn:dem":748,
    "gn:feature_class":"P",
    "gn:feature_code":"PPL",
    "gn:name":"El Ojo de Agua del Cobre",
    "gn:population":0,
    "gn:timezone":"America/Mexico_City",
    "iso:country":"MX",
    "name:spa_x_preferred":[
        "El Ojo de Agua del Cobre"
    ],
    "name:und_x_variant":[
        "Ojo de Agua",
        "El Ojo de Agua"
    ],
    "wof:name":"El Ojo de Agua del Cobre",
    "wof:placetype":"locality"
},
  "geometry": {"coordinates":[-103.27556,18.88233],"type":"Point"}
}