{
  "type": "Feature",
  "properties": {
    "gn:admin1_code":"27",
    "gn:admin2_code":"8",
    "gn:asciiname":"Ogarrio (Rancho de los Manzanilla)",
    "gn:country_code":"MX",
    "gn:dem":10,
    "gn:feature_class":"P",
    "gn:feature_code":"PPL",
    "gn:name":"Ogarrio (Rancho de los Manzanilla)",
    "gn:population":13,
    "gn:timezone":"America/Mexico_City",
    "iso:country":"MX",
    "wof:name":"Ogarrio (Rancho de los Manzanilla)",
    "wof:placetype":"locality",
    "wof:population":13
},
  "geometry": {"coordinates":[-93.99806,18.06639],"type":"Point"}
}