{
  "type": "Feature",
  "properties": {
    "gn:admin1_code":"10",
    "gn:admin2_code":"30.0",
    "gn:asciiname":"Santa Ana",
    "gn:country_code":"MX",
    "gn:dem":1490,
    "gn:feature_class":"P",
    "gn:feature_code":"PPL",
    "gn:name":"Santa Ana",
    "gn:population":0,
    "gn:timezone":"America/Monterrey",
    "iso:country":"MX",
    "name:spa_x_preferred":[
        "Santa Ana"
    ],
    "wof:name":"Santa Ana",
    "wof:placetype":"locality"
},
  "geometry": {"coordinates":[-104.21887,25.46629],"type":"Point"}
}