{
  "type": "Feature",
  "properties": {
    "gn:admin1_code":"30",
    "gn:admin2_code":"207.0",
    "gn:asciiname":"El Tapatio (Rafael Arreguin Rodriguez)",
    "gn:country_code":"MX",
    "gn:dem":60,
    "gn:feature_class":"P",
    "gn:feature_code":"PPL",
    "gn:name":"El Tapat\u00edo (Rafael Arregu\u00edn Rodr\u00edguez)",
    "gn:population":7,
    "gn:timezone":"America/Mexico_City",
    "iso:country":"MX",
    "name:und_x_variant":[
        "El Tapat\u00edo (Rafael Arregu\u00edn Rodr\u00edguez)"
    ],
    "wof:name":"El Tapatio (Rafael Arreguin Rodriguez)",
    "wof:placetype":"locality",
    "wof:population":7
},
  "geometry": {"coordinates":[-96.19389,18.31472],"type":"Point"}
}