{
  "type": "Feature",
  "properties": {
    "gn:admin1_code":"25",
    "gn:admin2_code":"11.0",
    "gn:asciiname":"Flor de Mayo",
    "gn:country_code":"MX",
    "gn:dem":7,
    "gn:feature_class":"P",
    "gn:feature_code":"PPL",
    "gn:name":"Flor de Mayo",
    "gn:population":327,
    "gn:timezone":"America/Mazatlan",
    "iso:country":"MX",
    "wof:name":"Flor de Mayo",
    "wof:placetype":"locality",
    "wof:population":327
},
  "geometry": {"coordinates":[-108.66083,25.53306],"type":"Point"}
}