{
  "type": "Feature",
  "properties": {
    "gn:admin1_code":"11",
    "gn:admin2_code":"41.0",
    "gn:asciiname":"Lagunilla del Encinal",
    "gn:country_code":"MX",
    "gn:dem":2259,
    "gn:feature_class":"P",
    "gn:feature_code":"PPL",
    "gn:name":"Lagunilla del Encinal",
    "gn:population":186,
    "gn:timezone":"America/Mexico_City",
    "iso:country":"MX",
    "wof:name":"Lagunilla del Encinal",
    "wof:placetype":"locality",
    "wof:population":186
},
  "geometry": {"coordinates":[-101.09583000000001,20.12444],"type":"Point"}
}