{
  "type": "Feature",
  "properties": {
    "gn:admin1_code":"3",
    "gn:admin2_code":"8",
    "gn:asciiname":"Rancho Escondido",
    "gn:country_code":"MX",
    "gn:dem":153,
    "gn:feature_class":"P",
    "gn:feature_code":"PPL",
    "gn:name":"Rancho Escondido",
    "gn:population":9,
    "gn:timezone":"America/Mazatlan",
    "iso:country":"MX",
    "wof:name":"Rancho Escondido",
    "wof:placetype":"locality",
    "wof:population":9
},
  "geometry": {"coordinates":[-109.68947,23.3209],"type":"Point"}
}