{
  "type": "Feature",
  "properties": {
    "gn:admin1_code":"25",
    "gn:admin2_code":"7.0",
    "gn:asciiname":"Tabucahui",
    "gn:country_code":"MX",
    "gn:dem":298,
    "gn:feature_class":"P",
    "gn:feature_code":"PPL",
    "gn:name":"Tabucahui",
    "gn:population":0,
    "gn:timezone":"America/Mazatlan",
    "iso:country":"MX",
    "name:spa_x_preferred":[
        "Tabucahui"
    ],
    "wof:name":"Tabucahui",
    "wof:placetype":"locality"
},
  "geometry": {"coordinates":[-108.41549999999999,26.72583],"type":"Point"}
}