{
  "type": "Feature",
  "properties": {
    "gn:admin1_code":"30",
    "gn:admin2_code":"210.0",
    "gn:asciiname":"El Luchador",
    "gn:country_code":"MX",
    "gn:dem":319,
    "gn:feature_class":"P",
    "gn:feature_code":"PPL",
    "gn:name":"El Luchador",
    "gn:population":80,
    "gn:timezone":"America/Mexico_City",
    "iso:country":"MX",
    "wof:name":"El Luchador",
    "wof:placetype":"locality",
    "wof:population":80
},
  "geometry": {"coordinates":[-94.35805999999999,17.20528],"type":"Point"}
}