{
  "type": "Feature",
  "properties": {
    "gn:admin1_code":"30",
    "gn:admin2_code":"115",
    "gn:asciiname":"La Lluvia",
    "gn:country_code":"MX",
    "gn:dem":1485,
    "gn:feature_class":"P",
    "gn:feature_code":"PPL",
    "gn:name":"La Lluvia",
    "gn:population":14,
    "gn:timezone":"America/Mexico_City",
    "iso:country":"MX",
    "wof:name":"La Lluvia",
    "wof:placetype":"locality",
    "wof:population":14
},
  "geometry": {"coordinates":[-97.18528000000001,18.82111],"type":"Point"}
}