{
  "type": "Feature",
  "properties": {
    "gn:admin1_code":"30.0",
    "gn:admin2_code":"58.0",
    "gn:asciiname":"Campo Siete",
    "gn:country_code":"MX",
    "gn:dem":161,
    "gn:feature_class":"P",
    "gn:feature_code":"PPL",
    "gn:name":"Campo Siete",
    "gn:population":6,
    "gn:timezone":"America/Mexico_City",
    "iso:country":"MX",
    "name:spa_x_preferred":[
        "Campo Siete"
    ],
    "wof:name":"Campo Siete",
    "wof:placetype":"locality",
    "wof:population":6
},
  "geometry": {"coordinates":[-97.97889000000001,21.07333],"type":"Point"}
}