{
  "type": "Feature",
  "properties": {
    "gn:admin1_code":"24.0",
    "gn:admin2_code":"24.0",
    "gn:asciiname":"San Jose de Canoas",
    "gn:country_code":"MX",
    "gn:dem":1171,
    "gn:feature_class":"P",
    "gn:feature_code":"PPL",
    "gn:name":"San Jos\u00e9 de Canoas",
    "gn:population":0,
    "gn:timezone":"America/Mexico_City",
    "iso:country":"MX",
    "name:spa_x_preferred":[
        "San Jos\u00e9 de Canoas"
    ],
    "name:und_x_variant":[
        "Canoas"
    ],
    "wof:name":"San Jose de Canoas",
    "wof:placetype":"locality"
},
  "geometry": {"coordinates":[-100.29006,21.9993],"type":"Point"}
}