{
  "type": "Feature",
  "properties": {
    "gn:admin1_code":"20",
    "gn:admin2_code":"532.0",
    "gn:asciiname":"Loma Larga",
    "gn:country_code":"MX",
    "gn:dem":2329,
    "gn:feature_class":"P",
    "gn:feature_code":"PPL",
    "gn:name":"Loma Larga",
    "gn:population":0,
    "gn:timezone":"America/Mexico_City",
    "iso:country":"MX",
    "wof:name":"Loma Larga",
    "wof:placetype":"locality"
},
  "geometry": {"coordinates":[-97.73333,17.13332999999999],"type":"Point"}
}