{
  "type": "Feature",
  "properties": {
    "gn:admin1_code":"12.0",
    "gn:admin2_code":"48.0",
    "gn:asciiname":"La Aguacatera",
    "gn:country_code":"MX",
    "gn:dem":1162,
    "gn:feature_class":"P",
    "gn:feature_code":"PPL",
    "gn:name":"La Aguacatera",
    "gn:population":0,
    "gn:timezone":"America/Mexico_City",
    "iso:country":"MX",
    "name:spa_x_preferred":[
        "La Aguacatera"
    ],
    "wof:name":"La Aguacatera",
    "wof:placetype":"locality"
},
  "geometry": {"coordinates":[-101.02943999999999,17.6442],"type":"Point"}
}