{
  "type": "Feature",
  "properties": {
    "gn:admin1_code":"10",
    "gn:admin2_code":"5.0",
    "gn:asciiname":"Casas de Alto",
    "gn:country_code":"MX",
    "gn:dem":1863,
    "gn:feature_class":"P",
    "gn:feature_code":"PPL",
    "gn:name":"Casas de Alto",
    "gn:population":6,
    "gn:timezone":"America/Monterrey",
    "iso:country":"MX",
    "wof:name":"Casas de Alto",
    "wof:placetype":"locality",
    "wof:population":6
},
  "geometry": {"coordinates":[-104.53612,24.07002],"type":"Point"}
}