{
  "type": "Feature",
  "properties": {
    "gn:admin1_code":"10",
    "gn:admin2_code":"25.0",
    "gn:asciiname":"Celaya",
    "gn:country_code":"MX",
    "gn:dem":1907,
    "gn:feature_class":"P",
    "gn:feature_code":"PPL",
    "gn:name":"Celaya",
    "gn:population":0,
    "gn:timezone":"America/Monterrey",
    "iso:country":"MX",
    "name:afr_x_preferred":[
        "Celaya"
    ],
    "name:ara_x_preferred":[
        "\u0633\u064a\u0644\u0627\u064a\u0627"
    ],
    "name:bul_x_preferred":[
        "\u0421\u0435\u043b\u0430\u044f"
    ],
    "name:dan_x_preferred":[
        "Celaya"
    ],
    "name:deu_x_preferred":[
        "Celaya"
    ],
    "name:epo_x_preferred":[
        "Celaya"
    ],
    "name:eus_x_preferred":[
        "Celaya"
    ],
    "name:fas_x_preferred":[
        "\u0633\u0644\u0627\u06cc\u0627"
    ],
    "name:fra_x_preferred":[
        "Celaya"
    ],
    "name:hun_x_preferred":[
        "Celaya"
    ],
    "name:hye_x_preferred":[
        "\u054d\u0565\u056c\u0561\u0575\u0561"
    ],
    "name:ita_x_preferred":[
        "Celaya"
    ],
    "name:kat_x_preferred":[
        "\u10e1\u10d4\u10da\u10d0\u10d8\u10d0"
    ],
    "name:lit_x_preferred":[
        "Selaja"
    ],
    "name:nld_x_preferred":[
        "Celaya"
    ],
    "name:nor_x_preferred":[
        "Celaya"
    ],
    "name:pol_x_preferred":[
        "Celaya"
    ],
    "name:por_x_preferred":[
        "Celaya"
    ],
    "name:rus_x_preferred":[
        "\u0421\u0435\u043b\u0430\u044f"
    ],
    "name:spa_x_preferred":[
        "Celaya"
    ],
    "name:srp_x_preferred":[
        "\u0421\u0435\u043b\u0430\u0458\u0430"
    ],
    "name:swe_x_preferred":[
        "Celaya"
    ],
    "name:tgl_x_preferred":[
        "Celaya"
    ],
    "name:tur_x_preferred":[
        "Celaya"
    ],
    "name:urd_x_preferred":[
        "\u0633\u06cc\u0644\u0627\u0626\u06cc\u0627"
    ],
    "name:vie_x_preferred":[
        "Celaya"
    ],
    "name:war_x_preferred":[
        "Celaya"
    ],
    "name:zho_x_preferred":[
        "\u585e\u62c9\u4e9e"
    ],
    "wof:name":"Celaya",
    "wof:placetype":"locality"
},
  "geometry": {"coordinates":[-105.75532,26.39475],"type":"Point"}
}