{
  "type": "Feature",
  "properties": {
    "gn:admin1_code":"12",
    "gn:admin2_code":"7.0",
    "gn:asciiname":"Texcaltitlan (El Capire)",
    "gn:country_code":"MX",
    "gn:dem":1324,
    "gn:feature_class":"P",
    "gn:feature_code":"PPL",
    "gn:name":"Texcaltitl\u00e1n (El Capire)",
    "gn:population":8,
    "gn:timezone":"America/Mexico_City",
    "iso:country":"MX",
    "name:und_x_variant":[
        "Texcaltitl\u00e1n (El Capire)"
    ],
    "wof:name":"Texcaltitlan (El Capire)",
    "wof:placetype":"locality",
    "wof:population":8
},
  "geometry": {"coordinates":[-100.10561,18.30216],"type":"Point"}
}