{
  "type": "Feature",
  "properties": {
    "gn:admin1_code":"14",
    "gn:admin2_code":"67.0",
    "gn:asciiname":"El Agua Zarca",
    "gn:country_code":"MX",
    "gn:dem":895,
    "gn:feature_class":"P",
    "gn:feature_code":"PPL",
    "gn:name":"El Agua Zarca",
    "gn:population":7,
    "gn:timezone":"America/Mexico_City",
    "iso:country":"MX",
    "wof:name":"El Agua Zarca",
    "wof:placetype":"locality",
    "wof:population":7
},
  "geometry": {"coordinates":[-105.14528,20.56389],"type":"Point"}
}