{
  "type": "Feature",
  "properties": {
    "gn:admin1_code":"12",
    "gn:admin2_code":"58",
    "gn:asciiname":"Arroyo Grande",
    "gn:country_code":"MX",
    "gn:dem":1034,
    "gn:feature_class":"P",
    "gn:feature_code":"PPL",
    "gn:name":"Arroyo Grande",
    "gn:population":45,
    "gn:timezone":"America/Mexico_City",
    "iso:country":"MX",
    "wof:name":"Arroyo Grande",
    "wof:placetype":"locality",
    "wof:population":45
},
  "geometry": {"coordinates":[-100.09394,18.21383],"type":"Point"}
}