{
  "type": "Feature",
  "properties": {
    "gn:admin1_code":"30",
    "gn:admin2_code":"177.0",
    "gn:asciiname":"San Andres",
    "gn:country_code":"MX",
    "gn:dem":2196,
    "gn:feature_class":"P",
    "gn:feature_code":"PPL",
    "gn:name":"San Andr\u00e9s",
    "gn:population":136,
    "gn:timezone":"America/Mexico_City",
    "iso:country":"MX",
    "name:und_x_variant":[
        "San Andr\u00e9s"
    ],
    "wof:name":"San Andres",
    "wof:placetype":"locality",
    "wof:population":136
},
  "geometry": {"coordinates":[-97.01611,19.77722],"type":"Point"}
}