{
  "type": "Feature",
  "properties": {
    "gn:admin1_code":"11.0",
    "gn:admin2_code":"45.0",
    "gn:asciiname":"Catarina",
    "gn:country_code":"MX",
    "gn:dem":1217,
    "gn:feature_class":"P",
    "gn:feature_code":"PPL",
    "gn:name":"Catarina",
    "gn:population":0,
    "gn:timezone":"America/Mexico_City",
    "iso:country":"MX",
    "name:und_x_variant":[
        "Santa Catarina",
        "Catarina"
    ],
    "wof:name":"Catarina",
    "wof:placetype":"locality"
},
  "geometry": {"coordinates":[-100.0792,21.37183],"type":"Point"}
}