{
  "type": "Feature",
  "properties": {
    "gn:admin1_code":"31",
    "gn:admin2_code":"79.0",
    "gn:asciiname":"Aristeo",
    "gn:country_code":"MX",
    "gn:dem":32,
    "gn:feature_class":"P",
    "gn:feature_code":"PPL",
    "gn:name":"Aristeo",
    "gn:population":5,
    "gn:timezone":"America/Merida",
    "iso:country":"MX",
    "wof:name":"Aristeo",
    "wof:placetype":"locality",
    "wof:population":5
},
  "geometry": {"coordinates":[-89.24916999999998,20.17222000000001],"type":"Point"}
}