{
  "type": "Feature",
  "properties": {
    "gn:admin1_code":"26",
    "gn:admin2_code":"25",
    "gn:asciiname":"Margarita (Agricola Omega)",
    "gn:country_code":"MX",
    "gn:dem":27,
    "gn:feature_class":"P",
    "gn:feature_code":"PPL",
    "gn:name":"Margarita (Agr\u00edcola Omega)",
    "gn:population":10,
    "gn:timezone":"America/Hermosillo",
    "iso:country":"MX",
    "name:und_x_variant":[
        "Margarita (Agr\u00edcola Omega)"
    ],
    "wof:name":"Margarita (Agricola Omega)",
    "wof:placetype":"locality",
    "wof:population":10
},
  "geometry": {"coordinates":[-110.69167,28.01639],"type":"Point"}
}