{
  "type": "Feature",
  "properties": {
    "gn:admin1_code":"32",
    "gn:admin2_code":"51.0",
    "gn:asciiname":"Salvador",
    "gn:country_code":"MX",
    "gn:dem":2191,
    "gn:feature_class":"P",
    "gn:feature_code":"PPL",
    "gn:name":"Salvador",
    "gn:population":0,
    "gn:timezone":"America/Mexico_City",
    "iso:country":"MX",
    "wof:name":"Salvador",
    "wof:placetype":"locality"
},
  "geometry": {"coordinates":[-102.51667,23.95],"type":"Point"}
}