{
  "type": "Feature",
  "properties": {
    "gn:admin1_code":"29",
    "gn:admin2_code":"6",
    "gn:asciiname":"La Palma",
    "gn:country_code":"MX",
    "gn:dem":2754,
    "gn:feature_class":"P",
    "gn:feature_code":"PPL",
    "gn:name":"La Palma",
    "gn:population":32,
    "gn:timezone":"America/Mexico_City",
    "iso:country":"MX",
    "wof:name":"La Palma",
    "wof:placetype":"locality",
    "wof:population":32
},
  "geometry": {"coordinates":[-98.56898,19.52993],"type":"Point"}
}