{
  "type": "Feature",
  "properties": {
    "gn:admin1_code":"5",
    "gn:admin2_code":"107",
    "gn:asciiname":"Joaquin Miguel Gutierrez",
    "gn:country_code":"MX",
    "gn:dem":1036,
    "gn:feature_class":"P",
    "gn:feature_code":"PPL",
    "gn:name":"Joaqu\u00edn Miguel Guti\u00e9rrez",
    "gn:population":49,
    "gn:timezone":"America/Mexico_City",
    "iso:country":"MX",
    "name:und_x_variant":[
        "Joaqu\u00edn Miguel Guti\u00e9rrez"
    ],
    "wof:name":"Joaquin Miguel Gutierrez",
    "wof:placetype":"locality",
    "wof:population":49
},
  "geometry": {"coordinates":[-93.16833,15.95306],"type":"Point"}
}