{
  "type": "Feature",
  "properties": {
    "gn:admin1_code":"28",
    "gn:admin2_code":"2.0",
    "gn:asciiname":"La Cabecera",
    "gn:country_code":"MX",
    "gn:dem":81,
    "gn:feature_class":"P",
    "gn:feature_code":"PPL",
    "gn:name":"La Cabecera",
    "gn:population":0,
    "gn:timezone":"America/Monterrey",
    "iso:country":"MX",
    "name:und_x_variant":[
        "Cabecera",
        "La Cabecera"
    ],
    "wof:name":"La Cabecera",
    "wof:placetype":"locality"
},
  "geometry": {"coordinates":[-97.93655,22.9581],"type":"Point"}
}