{
  "type": "Feature",
  "properties": {
    "gn:admin1_code":"5",
    "gn:admin2_code":"40",
    "gn:asciiname":"Senor Esquipulas",
    "gn:country_code":"MX",
    "gn:dem":69,
    "gn:feature_class":"P",
    "gn:feature_code":"PPL",
    "gn:name":"Se\u00f1or Esquipulas",
    "gn:population":16,
    "gn:timezone":"America/Mexico_City",
    "iso:country":"MX",
    "name:und_x_variant":[
        "Se\u00f1or Esquipulas"
    ],
    "wof:name":"Senor Esquipulas",
    "wof:placetype":"locality",
    "wof:population":16
},
  "geometry": {"coordinates":[-92.50639,15.16667],"type":"Point"}
}