{
  "type": "Feature",
  "properties": {
    "gn:admin1_code":"25",
    "gn:admin2_code":"6.0",
    "gn:asciiname":"San Simon",
    "gn:country_code":"MX",
    "gn:dem":189,
    "gn:feature_class":"P",
    "gn:feature_code":"PPL",
    "gn:name":"San Sim\u00f3n",
    "gn:population":0,
    "gn:timezone":"America/Mazatlan",
    "iso:country":"MX",
    "name:spa_x_preferred":[
        "San Sim\u00f3n"
    ],
    "wof:name":"San Simon",
    "wof:placetype":"locality"
},
  "geometry": {"coordinates":[-107.05634000000001,24.81058],"type":"Point"}
}