{
  "type": "Feature",
  "properties": {
    "gn:admin1_code":"20",
    "gn:admin2_code":"548",
    "gn:asciiname":"Rio Blanco (La Matanza)",
    "gn:country_code":"MX",
    "gn:dem":2009,
    "gn:feature_class":"P",
    "gn:feature_code":"PPL",
    "gn:name":"R\u00edo Blanco (La Matanza)",
    "gn:population":34,
    "gn:timezone":"America/Mexico_City",
    "iso:country":"MX",
    "name:und_x_variant":[
        "R\u00edo Blanco (La Matanza)"
    ],
    "wof:name":"Rio Blanco (La Matanza)",
    "wof:placetype":"locality",
    "wof:population":34
},
  "geometry": {"coordinates":[-97.39082999999999,17.96611],"type":"Point"}
}