{
  "type": "Feature",
  "properties": {
    "gn:admin1_code":"32",
    "gn:admin2_code":"5.0",
    "gn:asciiname":"Las Auras",
    "gn:country_code":"MX",
    "gn:dem":2106,
    "gn:feature_class":"P",
    "gn:feature_code":"PPL",
    "gn:name":"Las Auras",
    "gn:population":199,
    "gn:timezone":"America/Mexico_City",
    "iso:country":"MX",
    "wof:name":"Las Auras",
    "wof:placetype":"locality",
    "wof:population":199
},
  "geometry": {"coordinates":[-102.64361,23.03917],"type":"Point"}
}