{
  "type": "Feature",
  "properties": {
    "gn:admin1_code":"5",
    "gn:admin2_code":"108",
    "gn:asciiname":"Los Dos Arbolitos",
    "gn:country_code":"MX",
    "gn:dem":596,
    "gn:feature_class":"P",
    "gn:feature_code":"PPL",
    "gn:name":"Los Dos Arbolitos",
    "gn:population":34,
    "gn:timezone":"America/Mexico_City",
    "iso:country":"MX",
    "wof:name":"Los Dos Arbolitos",
    "wof:placetype":"locality",
    "wof:population":34
},
  "geometry": {"coordinates":[-93.32917,16.21389],"type":"Point"}
}