{
  "type": "Feature",
  "properties": {
    "gn:admin1_code":"32.0",
    "gn:admin2_code":"10.0",
    "gn:asciiname":"Los Robles",
    "gn:country_code":"MX",
    "gn:dem":2110,
    "gn:feature_class":"P",
    "gn:feature_code":"PPL",
    "gn:name":"Los Robles",
    "gn:population":0,
    "gn:timezone":"America/Mexico_City",
    "iso:country":"MX",
    "name:spa_x_preferred":[
        "Los Robles"
    ],
    "wof:name":"Los Robles",
    "wof:placetype":"locality"
},
  "geometry": {"coordinates":[-103.02685,23.17664],"type":"Point"}
}