{
  "type": "Feature",
  "properties": {
    "gn:admin1_code":"21",
    "gn:admin2_code":"76",
    "gn:asciiname":"La Esperanza Tenexapa",
    "gn:country_code":"MX",
    "gn:dem":156,
    "gn:feature_class":"P",
    "gn:feature_code":"PPL",
    "gn:name":"La Esperanza Tenexapa",
    "gn:population":38,
    "gn:timezone":"America/Mexico_City",
    "iso:country":"MX",
    "wof:name":"La Esperanza Tenexapa",
    "wof:placetype":"locality",
    "wof:population":38
},
  "geometry": {"coordinates":[-97.32106,20.16674],"type":"Point"}
}