{
  "type": "Feature",
  "properties": {
    "gn:admin1_code":"6.0",
    "gn:admin2_code":"5.0",
    "gn:asciiname":"Los Muertos",
    "gn:country_code":"MX",
    "gn:dem":1179,
    "gn:feature_class":"P",
    "gn:feature_code":"PPL",
    "gn:name":"Los Muertos",
    "gn:population":0,
    "gn:timezone":"America/Chihuahua",
    "iso:country":"MX",
    "name:spa_x_preferred":[
        "Los Muertos"
    ],
    "wof:name":"Los Muertos",
    "wof:placetype":"locality"
},
  "geometry": {"coordinates":[-106.91903000000001,31.11817000000001],"type":"Point"}
}