{
  "type": "Feature",
  "properties": {
    "gn:admin1_code":"2",
    "gn:admin2_code":"1",
    "gn:asciiname":"Familia Patino",
    "gn:country_code":"MX",
    "gn:dem":15,
    "gn:feature_class":"P",
    "gn:feature_code":"PPL",
    "gn:name":"Familia Pati\u00f1o",
    "gn:population":9,
    "gn:timezone":"America/Tijuana",
    "iso:country":"MX",
    "name:und_x_variant":[
        "Familia Pati\u00f1o"
    ],
    "wof:name":"Familia Patino",
    "wof:placetype":"locality",
    "wof:population":9
},
  "geometry": {"coordinates":[-115.97278,30.6675],"type":"Point"}
}