{
  "type": "Feature",
  "properties": {
    "gn:admin1_code":"6",
    "gn:admin2_code":"20",
    "gn:asciiname":"La Mesa del Rosario",
    "gn:country_code":"MX",
    "gn:dem":512,
    "gn:feature_class":"P",
    "gn:feature_code":"PPL",
    "gn:name":"La Mesa del Rosario",
    "gn:population":16,
    "gn:timezone":"America/Chihuahua",
    "iso:country":"MX",
    "wof:name":"La Mesa del Rosario",
    "wof:placetype":"locality",
    "wof:population":16
},
  "geometry": {"coordinates":[-108.54882000000001,27.3802],"type":"Point"}
}