{
  "type": "Feature",
  "properties": {
    "gn:admin1_code":"10.0",
    "gn:admin2_code":"36.0",
    "gn:asciiname":"Juaja",
    "gn:country_code":"MX",
    "gn:dem":1099,
    "gn:feature_class":"P",
    "gn:feature_code":"PPL",
    "gn:name":"Juaja",
    "gn:population":0,
    "gn:timezone":"America/Monterrey",
    "iso:country":"MX",
    "wof:name":"Juaja",
    "wof:placetype":"locality"
},
  "geometry": {"coordinates":[-103.36667,25.91667],"type":"Point"}
}