{
  "type": "Feature",
  "properties": {
    "gn:admin1_code":"12",
    "gn:admin2_code":"12.0",
    "gn:asciiname":"Colonia Yerba Santa",
    "gn:country_code":"MX",
    "gn:dem":1445,
    "gn:feature_class":"P",
    "gn:feature_code":"PPL",
    "gn:name":"Colonia Yerba Santa",
    "gn:population":116,
    "gn:timezone":"America/Mexico_City",
    "iso:country":"MX",
    "wof:name":"Colonia Yerba Santa",
    "wof:placetype":"locality",
    "wof:population":116
},
  "geometry": {"coordinates":[-98.9769,17.02555],"type":"Point"}
}