{
  "type": "Feature",
  "properties": {
    "gn:admin1_code":"25",
    "gn:admin2_code":"10",
    "gn:asciiname":"Chino de los Gamez",
    "gn:country_code":"MX",
    "gn:dem":336,
    "gn:feature_class":"P",
    "gn:feature_code":"PPL",
    "gn:name":"Chino de los G\u00e1mez",
    "gn:population":26,
    "gn:timezone":"America/Mazatlan",
    "iso:country":"MX",
    "name:und_x_variant":[
        "Chino de los G\u00e1mez"
    ],
    "wof:name":"Chino de los Gamez",
    "wof:placetype":"locality",
    "wof:population":26
},
  "geometry": {"coordinates":[-108.38141,26.44138],"type":"Point"}
}