{
  "type": "Feature",
  "properties": {
    "gn:admin1_code":"6",
    "gn:admin2_code":"36.0",
    "gn:asciiname":"Ojo de Almoloya",
    "gn:country_code":"MX",
    "gn:dem":1370,
    "gn:feature_class":"P",
    "gn:feature_code":"PPL",
    "gn:name":"Ojo de Almoloya",
    "gn:population":0,
    "gn:timezone":"America/Chihuahua",
    "iso:country":"MX",
    "name:und_x_variant":[
        "Texcoco"
    ],
    "wof:name":"Ojo de Almoloya",
    "wof:placetype":"locality"
},
  "geometry": {"coordinates":[-104.39230999999999,26.99712],"type":"Point"}
}