{
  "type": "Feature",
  "properties": {
    "gn:admin1_code":"28",
    "gn:admin2_code":"43.0",
    "gn:asciiname":"Benito Juarez",
    "gn:country_code":"MX",
    "gn:dem":174,
    "gn:feature_class":"P",
    "gn:feature_code":"PPL",
    "gn:name":"Benito Ju\u00e1rez",
    "gn:population":304,
    "gn:timezone":"America/Monterrey",
    "iso:country":"MX",
    "name:und_x_variant":[
        "Benito Ju\u00e1rez"
    ],
    "wof:name":"Benito Juarez",
    "wof:placetype":"locality",
    "wof:population":304
},
  "geometry": {"coordinates":[-99.04083,23.09306],"type":"Point"}
}