{
  "type": "Feature",
  "properties": {
    "gn:admin1_code":"12",
    "gn:admin2_code":"48",
    "gn:asciiname":"Barranca del Patacual",
    "gn:country_code":"MX",
    "gn:dem":317,
    "gn:feature_class":"P",
    "gn:feature_code":"PPL",
    "gn:name":"Barranca del Patacual",
    "gn:population":32,
    "gn:timezone":"America/Mexico_City",
    "iso:country":"MX",
    "wof:name":"Barranca del Patacual",
    "wof:placetype":"locality",
    "wof:population":32
},
  "geometry": {"coordinates":[-101.14931,17.49036],"type":"Point"}
}