{
  "type": "Feature",
  "properties": {
    "gn:admin1_code":"6",
    "gn:admin2_code":"17",
    "gn:asciiname":"Los Amanes",
    "gn:country_code":"MX",
    "gn:dem":2058,
    "gn:feature_class":"P",
    "gn:feature_code":"PPL",
    "gn:name":"Los Amanes",
    "gn:population":46,
    "gn:timezone":"America/Chihuahua",
    "iso:country":"MX",
    "wof:name":"Los Amanes",
    "wof:placetype":"locality",
    "wof:population":46
},
  "geometry": {"coordinates":[-106.59493000000001,28.45352],"type":"Point"}
}