{
  "type": "Feature",
  "properties": {
    "gn:admin1_code":"22",
    "gn:admin2_code":"7",
    "gn:asciiname":"Familia Montes Trejo",
    "gn:country_code":"MX",
    "gn:dem":1952,
    "gn:feature_class":"P",
    "gn:feature_code":"PPL",
    "gn:name":"Familia Montes Trejo",
    "gn:population":13,
    "gn:timezone":"America/Mexico_City",
    "iso:country":"MX",
    "wof:name":"Familia Montes Trejo",
    "wof:placetype":"locality",
    "wof:population":13
},
  "geometry": {"coordinates":[-99.88972,20.64417000000001],"type":"Point"}
}