{
  "type": "Feature",
  "properties": {
    "gn:admin1_code":"10",
    "gn:admin2_code":"4.0",
    "gn:asciiname":"Salinoso",
    "gn:country_code":"MX",
    "gn:dem":2228,
    "gn:feature_class":"P",
    "gn:feature_code":"PPL",
    "gn:name":"Salinoso",
    "gn:population":0,
    "gn:timezone":"America/Monterrey",
    "iso:country":"MX",
    "name:spa_x_preferred":[
        "Salinoso"
    ],
    "wof:name":"Salinoso",
    "wof:placetype":"locality"
},
  "geometry": {"coordinates":[-103.58922,24.62396],"type":"Point"}
}