{
  "type": "Feature",
  "properties": {
    "gn:admin1_code":"10.0",
    "gn:admin2_code":"1.0",
    "gn:asciiname":"Guadalupe Marquezote",
    "gn:country_code":"MX",
    "gn:dem":2583,
    "gn:feature_class":"P",
    "gn:feature_code":"PPL",
    "gn:name":"Guadalupe Marquezote",
    "gn:population":0,
    "gn:timezone":"America/Monterrey",
    "iso:country":"MX",
    "wof:name":"Guadalupe Marquezote",
    "wof:placetype":"locality"
},
  "geometry": {"coordinates":[-105.39417,24.46528],"type":"Point"}
}