{
  "type": "Feature",
  "properties": {
    "gn:admin1_code":"11.0",
    "gn:admin2_code":"5.0",
    "gn:asciiname":"Obraje de Ixtla",
    "gn:country_code":"MX",
    "gn:dem":2014,
    "gn:feature_class":"P",
    "gn:feature_code":"PPL",
    "gn:name":"Obraje de Ixtla",
    "gn:population":0,
    "gn:timezone":"America/Mexico_City",
    "iso:country":"MX",
    "name:und_x_variant":[
        "El Obraje",
        "Obraje de Ixtla"
    ],
    "wof:name":"Obraje de Ixtla",
    "wof:placetype":"locality"
},
  "geometry": {"coordinates":[-100.60827999999999,20.66931],"type":"Point"}
}