{
  "type": "Feature",
  "properties": {
    "gn:admin1_code":"11",
    "gn:admin2_code":"32.0",
    "gn:asciiname":"Las Pomas (San Rafael de las Pomas)",
    "gn:country_code":"MX",
    "gn:dem":2078,
    "gn:feature_class":"P",
    "gn:feature_code":"PPL",
    "gn:name":"Las Pomas (San Rafael de las Pomas)",
    "gn:population":199,
    "gn:timezone":"America/Mexico_City",
    "iso:country":"MX",
    "wof:name":"Las Pomas (San Rafael de las Pomas)",
    "wof:placetype":"locality",
    "wof:population":199
},
  "geometry": {"coordinates":[-100.48444000000001,21.03583],"type":"Point"}
}