{
  "type": "Feature",
  "properties": {
    "gn:admin1_code":"28",
    "gn:admin2_code":"34.0",
    "gn:asciiname":"Tantayuca",
    "gn:country_code":"MX",
    "gn:dem":242,
    "gn:feature_class":"P",
    "gn:feature_code":"PPL",
    "gn:name":"Tantayuca",
    "gn:population":0,
    "gn:timezone":"America/Monterrey",
    "iso:country":"MX",
    "name:spa_x_preferred":[
        "Tantayuca"
    ],
    "name:und_x_variant":[
        "Tantovuca"
    ],
    "wof:name":"Tantayuca",
    "wof:placetype":"locality"
},
  "geometry": {"coordinates":[-99.21393999999999,24.42437],"type":"Point"}
}