{
  "type": "Feature",
  "properties": {
    "gn:admin1_code":"21",
    "gn:admin2_code":"179.0",
    "gn:asciiname":"Agua Escondida",
    "gn:country_code":"MX",
    "gn:dem":2503,
    "gn:feature_class":"P",
    "gn:feature_code":"PPL",
    "gn:name":"Agua Escondida",
    "gn:population":0,
    "gn:timezone":"America/Mexico_City",
    "iso:country":"MX",
    "name:spa_x_preferred":[
        "Agua Escondida"
    ],
    "wof:name":"Agua Escondida",
    "wof:placetype":"locality"
},
  "geometry": {"coordinates":[-97.46343,19.13254],"type":"Point"}
}