{
  "type": "Feature",
  "properties": {
    "gn:admin1_code":"12.0",
    "gn:admin2_code":"34.0",
    "gn:asciiname":"Amatitlan Grande",
    "gn:country_code":"MX",
    "gn:dem":1047,
    "gn:feature_class":"P",
    "gn:feature_code":"PPL",
    "gn:name":"Amatitl\u00e1n Grande",
    "gn:population":0,
    "gn:timezone":"America/Mexico_City",
    "iso:country":"MX",
    "name:spa_x_preferred":[
        "Amatitl\u00e1n Grande"
    ],
    "wof:name":"Amatitlan Grande",
    "wof:placetype":"locality"
},
  "geometry": {"coordinates":[-99.28333000000001,18.26253],"type":"Point"}
}