{
  "type": "Feature",
  "properties": {
    "gn:admin1_code":"13",
    "gn:admin2_code":"59",
    "gn:asciiname":"La Polvadera",
    "gn:country_code":"MX",
    "gn:dem":1685,
    "gn:feature_class":"P",
    "gn:feature_code":"PPL",
    "gn:name":"La Polvadera",
    "gn:population":13,
    "gn:timezone":"America/Mexico_City",
    "iso:country":"MX",
    "wof:name":"La Polvadera",
    "wof:placetype":"locality",
    "wof:population":13
},
  "geometry": {"coordinates":[-99.60472,20.56063],"type":"Point"}
}