{
  "type": "Feature",
  "properties": {
    "gn:admin1_code":"26",
    "gn:admin2_code":"55.0",
    "gn:asciiname":"Josefina Galindo",
    "gn:country_code":"MX",
    "gn:dem":20,
    "gn:feature_class":"P",
    "gn:feature_code":"PPL",
    "gn:name":"Josefina Galindo",
    "gn:population":6,
    "gn:timezone":"America/Hermosillo",
    "iso:country":"MX",
    "wof:name":"Josefina Galindo",
    "wof:placetype":"locality",
    "wof:population":6
},
  "geometry": {"coordinates":[-114.92917,32.39556],"type":"Point"}
}