{
  "type": "Feature",
  "properties": {
    "gn:admin1_code":"12.0",
    "gn:admin2_code":"32.0",
    "gn:asciiname":"Pena Prieta",
    "gn:country_code":"MX",
    "gn:dem":613,
    "gn:feature_class":"P",
    "gn:feature_code":"PPL",
    "gn:name":"Pe\u00f1a Prieta",
    "gn:population":0,
    "gn:timezone":"America/Mexico_City",
    "iso:country":"MX",
    "name:spa_x_preferred":[
        "Pe\u00f1a Prieta"
    ],
    "wof:name":"Pena Prieta",
    "wof:placetype":"locality"
},
  "geometry": {"coordinates":[-100.1024,17.95072],"type":"Point"}
}