{
  "type": "Feature",
  "properties": {
    "gn:admin1_code":"3.0",
    "gn:admin2_code":"3.0",
    "gn:asciiname":"San Benito",
    "gn:country_code":"MX",
    "gn:dem":22,
    "gn:feature_class":"P",
    "gn:feature_code":"PPL",
    "gn:name":"San Benito",
    "gn:population":0,
    "gn:timezone":"America/Mazatlan",
    "iso:country":"MX",
    "name:bre_x_preferred":[
        "San Benito"
    ],
    "name:cat_x_preferred":[
        "San Benito"
    ],
    "name:ceb_x_preferred":[
        "San Benito"
    ],
    "name:deu_x_preferred":[
        "San Benito"
    ],
    "name:fas_x_preferred":[
        "\u0633\u0646 \u0628\u0646\u06cc\u062a\u0648"
    ],
    "name:fra_x_preferred":[
        "San Benito"
    ],
    "name:ita_x_preferred":[
        "San Benito"
    ],
    "name:lit_x_preferred":[
        "San Benitas"
    ],
    "name:nds_x_preferred":[
        "San Benito"
    ],
    "name:nld_x_preferred":[
        "San Benito"
    ],
    "name:pol_x_preferred":[
        "San Benito"
    ],
    "name:por_x_preferred":[
        "San Benito"
    ],
    "name:spa_x_preferred":[
        "San Benito"
    ],
    "name:srp_x_preferred":[
        "\u0421\u0430\u043d \u0411\u0435\u043d\u0438\u0442\u043e"
    ],
    "name:swe_x_preferred":[
        "San Benito"
    ],
    "name:ukr_x_preferred":[
        "\u0421\u0430\u043d-\u0411\u0435\u043d\u0456\u0442\u043e"
    ],
    "name:war_x_preferred":[
        "San Benito"
    ],
    "wof:name":"San Benito",
    "wof:placetype":"locality"
},
  "geometry": {"coordinates":[-109.89232,23.96332],"type":"Point"}
}