{
  "type": "Feature",
  "properties": {
    "gn:admin1_code":"2",
    "gn:admin2_code":"5.0",
    "gn:asciiname":"El Capitan",
    "gn:country_code":"MX",
    "gn:dem":78,
    "gn:feature_class":"P",
    "gn:feature_code":"PPL",
    "gn:name":"El Capit\u00e1n",
    "gn:population":4,
    "gn:timezone":"America/Tijuana",
    "iso:country":"MX",
    "name:und_x_variant":[
        "El Capit\u00e1n"
    ],
    "wof:name":"El Capitan",
    "wof:placetype":"locality",
    "wof:population":4
},
  "geometry": {"coordinates":[-116.99861,32.33333],"type":"Point"}
}