{
  "type": "Feature",
  "properties": {
    "gn:admin1_code":"11",
    "gn:admin2_code":"33.0",
    "gn:asciiname":"Dolores San Juan",
    "gn:country_code":"MX",
    "gn:dem":2059,
    "gn:feature_class":"P",
    "gn:feature_code":"PPL",
    "gn:name":"Dolores San Juan",
    "gn:population":454,
    "gn:timezone":"America/Mexico_City",
    "iso:country":"MX",
    "wof:name":"Dolores San Juan",
    "wof:placetype":"locality",
    "wof:population":454
},
  "geometry": {"coordinates":[-100.46556,21.12861],"type":"Point"}
}