{
  "type": "Feature",
  "properties": {
    "gn:admin1_code":"5",
    "gn:admin2_code":"31.0",
    "gn:asciiname":"Cololteel",
    "gn:country_code":"MX",
    "gn:dem":1120,
    "gn:feature_class":"P",
    "gn:feature_code":"PPL",
    "gn:name":"Cololteel",
    "gn:population":217,
    "gn:timezone":"America/Mexico_City",
    "iso:country":"MX",
    "wof:name":"Cololteel",
    "wof:placetype":"locality",
    "wof:population":217
},
  "geometry": {"coordinates":[-92.13833,17.09832999999999],"type":"Point"}
}