{
  "type": "Feature",
  "properties": {
    "gn:admin1_code":"11",
    "gn:admin2_code":"8.0",
    "gn:asciiname":"Rancho Viejo del Sauz",
    "gn:country_code":"MX",
    "gn:dem":1792,
    "gn:feature_class":"P",
    "gn:feature_code":"PPL",
    "gn:name":"Rancho Viejo del Sauz",
    "gn:population":126,
    "gn:timezone":"America/Mexico_City",
    "iso:country":"MX",
    "wof:name":"Rancho Viejo del Sauz",
    "wof:placetype":"locality",
    "wof:population":126
},
  "geometry": {"coordinates":[-101.96341,20.70034],"type":"Point"}
}