{
  "type": "Feature",
  "properties": {
    "gn:admin1_code":"8.0",
    "gn:admin2_code":"7.0",
    "gn:asciiname":"El Chocohuiztle",
    "gn:country_code":"MX",
    "gn:dem":8,
    "gn:feature_class":"P",
    "gn:feature_code":"PPL",
    "gn:name":"El Chocohuiztle",
    "gn:population":2,
    "gn:timezone":"America/Mexico_City",
    "iso:country":"MX",
    "wof:name":"El Chocohuiztle",
    "wof:placetype":"locality",
    "wof:population":2
},
  "geometry": {"coordinates":[-104.19083000000001,18.97944],"type":"Point"}
}