{
  "type": "Feature",
  "properties": {
    "gn:admin1_code":"7.0",
    "gn:admin2_code":"2.0",
    "gn:asciiname":"La Viborita",
    "gn:country_code":"MX",
    "gn:dem":377,
    "gn:feature_class":"P",
    "gn:feature_code":"PPL",
    "gn:name":"La Viborita",
    "gn:population":0,
    "gn:timezone":"America/Matamoros",
    "iso:country":"MX",
    "name:spa_x_preferred":[
        "La Viborita"
    ],
    "wof:name":"La Viborita",
    "wof:placetype":"locality"
},
  "geometry": {"coordinates":[-101.61808000000001,29.76825],"type":"Point"}
}