{
  "type": "Feature",
  "properties": {
    "gn:admin1_code":"10",
    "gn:admin2_code":"9.0",
    "gn:asciiname":"Aserradero Rancho Viejo",
    "gn:country_code":"MX",
    "gn:dem":2633,
    "gn:feature_class":"P",
    "gn:feature_code":"PPL",
    "gn:name":"Aserradero Rancho Viejo",
    "gn:population":0,
    "gn:timezone":"America/Monterrey",
    "iso:country":"MX",
    "name:spa_x_preferred":[
        "Aserradero Rancho Viejo"
    ],
    "wof:name":"Aserradero Rancho Viejo",
    "wof:placetype":"locality"
},
  "geometry": {"coordinates":[-106.2542,26.17862],"type":"Point"}
}