{
  "type": "Feature",
  "properties": {
    "gn:admin1_code":"12",
    "gn:admin2_code":"19",
    "gn:asciiname":"Tepango",
    "gn:country_code":"MX",
    "gn:dem":607,
    "gn:feature_class":"P",
    "gn:feature_code":"PPL",
    "gn:name":"Tepango",
    "gn:population":15,
    "gn:timezone":"America/Mexico_City",
    "iso:country":"MX",
    "wof:name":"Tepango",
    "wof:placetype":"locality",
    "wof:population":15
},
  "geometry": {"coordinates":[-99.11071,18.04385],"type":"Point"}
}