{
  "type": "Feature",
  "properties": {
    "gn:admin1_code":"30",
    "gn:admin2_code":"160.0",
    "gn:asciiname":"Paso de Alamo",
    "gn:country_code":"MX",
    "gn:dem":80,
    "gn:feature_class":"P",
    "gn:feature_code":"PPL",
    "gn:name":"Paso de \u00c1lamo",
    "gn:population":0,
    "gn:timezone":"America/Mexico_City",
    "iso:country":"MX",
    "name:spa_x_preferred":[
        "Paso de \u00c1lamo"
    ],
    "name:spa_x_variant":[
        "La Pita"
    ],
    "wof:name":"Paso de Alamo",
    "wof:placetype":"locality"
},
  "geometry": {"coordinates":[-97.86476999999999,20.85882],"type":"Point"}
}