{
  "type": "Feature",
  "properties": {
    "gn:admin1_code":"26",
    "gn:admin2_code":"17.0",
    "gn:asciiname":"Los Hermanos",
    "gn:country_code":"MX",
    "gn:dem":30,
    "gn:feature_class":"P",
    "gn:feature_code":"PPL",
    "gn:name":"Los Hermanos",
    "gn:population":0,
    "gn:timezone":"America/Hermosillo",
    "iso:country":"MX",
    "name:afr_x_preferred":[
        "Los Hermanos"
    ],
    "name:cat_x_preferred":[
        "Los Hermanos"
    ],
    "name:cym_x_preferred":[
        "Los Hermanos"
    ],
    "name:deu_x_preferred":[
        "Los Hermanos"
    ],
    "name:epo_x_preferred":[
        "Los Hermanos"
    ],
    "name:eus_x_preferred":[
        "Los Hermanos"
    ],
    "name:fra_x_preferred":[
        "Los Hermanos"
    ],
    "name:glg_x_preferred":[
        "Los Hermanos"
    ],
    "name:hun_x_preferred":[
        "Los Hermanos"
    ],
    "name:pcd_x_preferred":[
        "Los Hermanos"
    ],
    "name:pol_x_preferred":[
        "Los Hermanos"
    ],
    "name:por_x_preferred":[
        "Los Hermanos"
    ],
    "name:spa_x_preferred":[
        "Los Hermanos"
    ],
    "name:tur_x_preferred":[
        "Los Hermanos"
    ],
    "wof:name":"Los Hermanos",
    "wof:placetype":"locality"
},
  "geometry": {"coordinates":[-112.91771,30.96429],"type":"Point"}
}