{
  "type": "Feature",
  "properties": {
    "gn:admin1_code":"6",
    "gn:admin2_code":"27.0",
    "gn:asciiname":"Mesa del Alamo",
    "gn:country_code":"MX",
    "gn:dem":2568,
    "gn:feature_class":"P",
    "gn:feature_code":"PPL",
    "gn:name":"Mesa del Alamo",
    "gn:population":0,
    "gn:timezone":"America/Chihuahua",
    "iso:country":"MX",
    "name:spa_x_preferred":[
        "Mesa del Alamo"
    ],
    "wof:name":"Mesa del Alamo",
    "wof:placetype":"locality"
},
  "geometry": {"coordinates":[-107.21951,26.7712],"type":"Point"}
}