{
  "type": "Feature",
  "properties": {
    "gn:admin1_code":"11",
    "gn:admin2_code":"5",
    "gn:asciiname":"Los Mirasoles",
    "gn:country_code":"MX",
    "gn:dem":1764,
    "gn:feature_class":"P",
    "gn:feature_code":"PPL",
    "gn:name":"Los Mirasoles",
    "gn:population":26,
    "gn:timezone":"America/Mexico_City",
    "iso:country":"MX",
    "wof:name":"Los Mirasoles",
    "wof:placetype":"locality",
    "wof:population":26
},
  "geometry": {"coordinates":[-100.72667,20.52806],"type":"Point"}
}