{
  "type": "Feature",
  "properties": {
    "gn:admin1_code":"20",
    "gn:admin2_code":"137.0",
    "gn:asciiname":"Morelos",
    "gn:country_code":"MX",
    "gn:dem":1267,
    "gn:feature_class":"P",
    "gn:feature_code":"PPL",
    "gn:name":"Morelos",
    "gn:population":157,
    "gn:timezone":"America/Mexico_City",
    "iso:country":"MX",
    "wof:name":"Morelos",
    "wof:placetype":"locality",
    "wof:population":157
},
  "geometry": {"coordinates":[-97.32277999999999,16.92361],"type":"Point"}
}