{
  "type": "Feature",
  "properties": {
    "gn:admin1_code":"5",
    "gn:admin2_code":"17",
    "gn:asciiname":"Martin Rios",
    "gn:country_code":"MX",
    "gn:dem":594,
    "gn:feature_class":"P",
    "gn:feature_code":"PPL",
    "gn:name":"Mart\u00edn R\u00edos",
    "gn:population":9,
    "gn:timezone":"America/Mexico_City",
    "iso:country":"MX",
    "name:deu_x_preferred":[
        "Martin Rios"
    ],
    "name:fra_x_preferred":[
        "Martin Rios"
    ],
    "name:ita_x_preferred":[
        "Martin Rios"
    ],
    "name:nor_x_preferred":[
        "Martin Rios"
    ],
    "name:rus_x_preferred":[
        "\u0420\u0438\u043e\u0441"
    ],
    "name:spa_x_preferred":[
        "Martin Rios"
    ],
    "name:ukr_x_preferred":[
        "\u041c\u0430\u0440\u0442\u0456\u043d \u0420\u0456\u043e\u0441"
    ],
    "name:und_x_variant":[
        "Mart\u00edn R\u00edos"
    ],
    "wof:name":"Martin Rios",
    "wof:placetype":"locality",
    "wof:population":9
},
  "geometry": {"coordinates":[-93.75611000000001,16.71194],"type":"Point"}
}