{
  "type": "Feature",
  "properties": {
    "gn:admin1_code":"11",
    "gn:admin2_code":"20.0",
    "gn:asciiname":"Real de la Joya",
    "gn:country_code":"MX",
    "gn:dem":1979,
    "gn:feature_class":"P",
    "gn:feature_code":"PPL",
    "gn:name":"Real de la Joya",
    "gn:population":618,
    "gn:timezone":"America/Mexico_City",
    "iso:country":"MX",
    "wof:name":"Real de la Joya",
    "wof:placetype":"locality",
    "wof:population":618
},
  "geometry": {"coordinates":[-101.75888999999999,21.1525],"type":"Point"}
}