{
  "type": "Feature",
  "properties": {
    "gn:admin1_code":"14",
    "gn:admin2_code":"114",
    "gn:asciiname":"Potrero del Campo Santo (Agua Caliente)",
    "gn:country_code":"MX",
    "gn:dem":1358,
    "gn:feature_class":"P",
    "gn:feature_code":"PPL",
    "gn:name":"Potrero del Campo Santo (Agua Caliente)",
    "gn:population":43,
    "gn:timezone":"America/Mexico_City",
    "iso:country":"MX",
    "wof:name":"Potrero del Campo Santo (Agua Caliente)",
    "wof:placetype":"locality",
    "wof:population":43
},
  "geometry": {"coordinates":[-103.67,20.42583],"type":"Point"}
}