{
  "type": "Feature",
  "properties": {
    "gn:admin1_code":"5",
    "gn:admin2_code":"108.0",
    "gn:asciiname":"El Cuajilote",
    "gn:country_code":"MX",
    "gn:dem":715,
    "gn:feature_class":"P",
    "gn:feature_code":"PPL",
    "gn:name":"El Cuajilote",
    "gn:population":6,
    "gn:timezone":"America/Mexico_City",
    "iso:country":"MX",
    "name:spa_x_preferred":[
        "El Cuajilote"
    ],
    "wof:name":"El Cuajilote",
    "wof:placetype":"locality",
    "wof:population":6
},
  "geometry": {"coordinates":[-93.52694,16.37917],"type":"Point"}
}