{
  "type": "Feature",
  "properties": {
    "gn:admin1_code":"25",
    "gn:admin2_code":"6",
    "gn:asciiname":"La Huerta de Polo (La Huerta)",
    "gn:country_code":"MX",
    "gn:dem":27,
    "gn:feature_class":"P",
    "gn:feature_code":"PPL",
    "gn:name":"La Huerta de Polo (La Huerta)",
    "gn:population":10,
    "gn:timezone":"America/Mazatlan",
    "iso:country":"MX",
    "wof:name":"La Huerta de Polo (La Huerta)",
    "wof:placetype":"locality",
    "wof:population":10
},
  "geometry": {"coordinates":[-107.53315000000001,24.81654],"type":"Point"}
}