{
  "type": "Feature",
  "properties": {
    "gn:admin1_code":"21",
    "gn:admin2_code":"82",
    "gn:asciiname":"Cerro Carreta",
    "gn:country_code":"MX",
    "gn:dem":1852,
    "gn:feature_class":"P",
    "gn:feature_code":"PPL",
    "gn:name":"Cerro Carreta",
    "gn:population":11,
    "gn:timezone":"America/Mexico_City",
    "iso:country":"MX",
    "wof:name":"Cerro Carreta",
    "wof:placetype":"locality",
    "wof:population":11
},
  "geometry": {"coordinates":[-97.87191,18.50295],"type":"Point"}
}