{
  "type": "Feature",
  "properties": {
    "gn:admin1_code":"5",
    "gn:admin2_code":"86.0",
    "gn:asciiname":"El Brasilar",
    "gn:country_code":"MX",
    "gn:dem":454,
    "gn:feature_class":"P",
    "gn:feature_code":"PPL",
    "gn:name":"El Brasilar",
    "gn:population":4,
    "gn:timezone":"America/Mexico_City",
    "iso:country":"MX",
    "wof:name":"El Brasilar",
    "wof:placetype":"locality",
    "wof:population":4
},
  "geometry": {"coordinates":[-93.08278,16.60582999999999],"type":"Point"}
}