{
  "type": "Feature",
  "properties": {
    "gn:admin1_code":"31",
    "gn:admin2_code":"97",
    "gn:asciiname":"Yaxha",
    "gn:country_code":"MX",
    "gn:dem":33,
    "gn:feature_class":"P",
    "gn:feature_code":"PPL",
    "gn:name":"Yaxh\u00e1",
    "gn:population":18,
    "gn:timezone":"America/Merida",
    "iso:country":"MX",
    "name:und_x_variant":[
        "Yaxh\u00e1"
    ],
    "wof:name":"Yaxha",
    "wof:placetype":"locality",
    "wof:population":18
},
  "geometry": {"coordinates":[-88.72917,20.78611],"type":"Point"}
}