{
  "type": "Feature",
  "properties": {
    "gn:admin1_code":"31",
    "gn:admin2_code":"97",
    "gn:asciiname":"Yaxha",
    "gn:country_code":"MX",
    "gn:dem":33,
    "gn:feature_class":"P",
    "gn:feature_code":"PPL",
    "gn:name":"Yaxh\u00e1",
    "gn:population":18,
    "gn:timezone":"America/Merida",
    "iso:country":"MX",
    "name:deu_x_preferred":[
        "Yaxha"
    ],
    "name:fra_x_preferred":[
        "Yaxha"
    ],
    "name:ind_x_preferred":[
        "Yaxh\u00e1"
    ],
    "name:ita_x_preferred":[
        "Yaxh\u00e1"
    ],
    "name:jpn_x_preferred":[
        "\u30e4\u30b7\u30e5\u30cf"
    ],
    "name:lit_x_preferred":[
        "Ja\u0161ha"
    ],
    "name:nor_x_preferred":[
        "Yaxha"
    ],
    "name:rus_x_preferred":[
        "\u0419\u0430\u0448\u0445\u0430"
    ],
    "name:spa_x_preferred":[
        "Yaxh\u00e1"
    ],
    "name:ukr_x_preferred":[
        "\u042f\u0448\u0445\u0430"
    ],
    "name:und_x_variant":[
        "Yaxh\u00e1"
    ],
    "wof:name":"Yaxha",
    "wof:placetype":"locality",
    "wof:population":18
},
  "geometry": {"coordinates":[-88.72917,20.78611],"type":"Point"}
}