{
  "type": "Feature",
  "properties": {
    "gn:admin1_code":"14.0",
    "gn:admin2_code":"64.0",
    "gn:asciiname":"Rancho Viejo",
    "gn:country_code":"MX",
    "gn:dem":2132,
    "gn:feature_class":"P",
    "gn:feature_code":"PPL",
    "gn:name":"Rancho Viejo",
    "gn:population":0,
    "gn:timezone":"America/Mexico_City",
    "iso:country":"MX",
    "name:ceb_x_preferred":[
        "Rancho Viejo"
    ],
    "name:deu_x_preferred":[
        "Rancho Viejo"
    ],
    "name:ita_x_preferred":[
        "Rancho Viejo"
    ],
    "name:spa_x_preferred":[
        "Rancho Viejo"
    ],
    "name:srp_x_preferred":[
        "\u0420\u0430\u043d\u0447\u043e \u0412\u0438\u0458\u0435\u0445\u043e"
    ],
    "name:swe_x_preferred":[
        "Rancho Viejo"
    ],
    "wof:name":"Rancho Viejo",
    "wof:placetype":"locality"
},
  "geometry": {"coordinates":[-101.78771999999999,21.87579],"type":"Point"}
}