{
  "type": "Feature",
  "properties": {
    "gn:admin1_code":"30",
    "gn:asciiname":"La Candelaria",
    "gn:country_code":"MX",
    "gn:dem":45,
    "gn:feature_class":"P",
    "gn:feature_code":"PPL",
    "gn:name":"La Candelaria",
    "gn:population":0,
    "gn:timezone":"America/Mexico_City",
    "iso:country":"MX",
    "name:und_x_variant":[
        "Candelaria",
        "La Candelaria"
    ],
    "wof:name":"La Candelaria",
    "wof:placetype":"locality"
},
  "geometry": {"coordinates":[-95.81368000000001,17.84389],"type":"Point"}
}