{
  "type": "Feature",
  "properties": {
    "gn:admin1_code":"7",
    "gn:admin2_code":"18.0",
    "gn:asciiname":"El Recuerdo (Jesus Mauricio Celedon Campos)",
    "gn:country_code":"MX",
    "gn:dem":502,
    "gn:feature_class":"P",
    "gn:feature_code":"PPL",
    "gn:name":"El Recuerdo (Jes\u00fas Mauricio Celed\u00f3n Campos)",
    "gn:population":7,
    "gn:timezone":"America/Monterrey",
    "iso:country":"MX",
    "name:und_x_variant":[
        "El Recuerdo (Jes\u00fas Mauricio Celed\u00f3n Campos)"
    ],
    "wof:name":"El Recuerdo (Jesus Mauricio Celedon Campos)",
    "wof:placetype":"locality",
    "wof:population":7
},
  "geometry": {"coordinates":[-101.35424999999999,27.00611],"type":"Point"}
}