{
  "type": "Feature",
  "properties": {
    "gn:admin1_code":"11",
    "gn:admin2_code":"3",
    "gn:asciiname":"Cerro del Agua",
    "gn:country_code":"MX",
    "gn:dem":2449,
    "gn:feature_class":"P",
    "gn:feature_code":"PPL",
    "gn:name":"Cerro del Agua",
    "gn:population":32,
    "gn:timezone":"America/Mexico_City",
    "iso:country":"MX",
    "wof:name":"Cerro del Agua",
    "wof:placetype":"locality",
    "wof:population":32
},
  "geometry": {"coordinates":[-100.57805999999999,20.79333],"type":"Point"}
}