{
  "type": "Feature",
  "properties": {
    "gn:admin1_code":"10",
    "gn:admin2_code":"35.0",
    "gn:asciiname":"El Indio de Abajo",
    "gn:country_code":"MX",
    "gn:dem":2430,
    "gn:feature_class":"P",
    "gn:feature_code":"PPL",
    "gn:name":"El Indio de Abajo",
    "gn:population":0,
    "gn:timezone":"America/Monterrey",
    "iso:country":"MX",
    "name:spa_x_preferred":[
        "El Indio de Abajo"
    ],
    "name:und_x_variant":[
        "El Indio"
    ],
    "wof:name":"El Indio de Abajo",
    "wof:placetype":"locality"
},
  "geometry": {"coordinates":[-106.31287,25.42088],"type":"Point"}
}