{
  "type": "Feature",
  "properties": {
    "gn:admin1_code":"5",
    "gn:admin2_code":"72",
    "gn:asciiname":"El Vergel",
    "gn:country_code":"MX",
    "gn:dem":623,
    "gn:feature_class":"P",
    "gn:feature_code":"PPL",
    "gn:name":"El Vergel",
    "gn:population":16,
    "gn:timezone":"America/Mexico_City",
    "iso:country":"MX",
    "wof:name":"El Vergel",
    "wof:placetype":"locality",
    "wof:population":16
},
  "geometry": {"coordinates":[-92.81167000000001,17.21694],"type":"Point"}
}