{
  "type": "Feature",
  "properties": {
    "gn:admin1_code":"11.0",
    "gn:admin2_code":"37.0",
    "gn:asciiname":"Jesus Maria",
    "gn:country_code":"MX",
    "gn:dem":1752,
    "gn:feature_class":"P",
    "gn:feature_code":"PPL",
    "gn:name":"Jes\u00fas Mar\u00eda",
    "gn:population":0,
    "gn:timezone":"America/Mexico_City",
    "iso:country":"MX",
    "wof:name":"Jesus Maria",
    "wof:placetype":"locality"
},
  "geometry": {"coordinates":[-101.43333,20.86667000000001],"type":"Point"}
}