{
  "type": "Feature",
  "properties": {
    "gn:admin1_code":"19.0",
    "gn:admin2_code":"17.0",
    "gn:asciiname":"El Tajo (Base Janet)",
    "gn:country_code":"MX",
    "gn:dem":1828,
    "gn:feature_class":"P",
    "gn:feature_code":"PPL",
    "gn:name":"El Tajo (Base Janet)",
    "gn:population":5,
    "gn:timezone":"America/Monterrey",
    "iso:country":"MX",
    "name:spa_x_preferred":[
        "El Tajo"
    ],
    "wof:name":"El Tajo (Base Janet)",
    "wof:placetype":"locality",
    "wof:population":5
},
  "geometry": {"coordinates":[-100.39359,24.36396],"type":"Point"}
}