{
  "type": "Feature",
  "properties": {
    "gn:admin1_code":"12",
    "gn:admin2_code":"78.0",
    "gn:asciiname":"Itiatio",
    "gn:country_code":"MX",
    "gn:dem":1059,
    "gn:feature_class":"P",
    "gn:feature_code":"PPL",
    "gn:name":"Itiatio",
    "gn:population":144,
    "gn:timezone":"America/Mexico_City",
    "iso:country":"MX",
    "wof:name":"Itiatio",
    "wof:placetype":"locality",
    "wof:population":144
},
  "geometry": {"coordinates":[-98.34859,16.99473],"type":"Point"}
}