{
  "type": "Feature",
  "properties": {
    "gn:admin1_code":"8",
    "gn:admin2_code":"7.0",
    "gn:asciiname":"Casa Culin",
    "gn:country_code":"MX",
    "gn:dem":15,
    "gn:feature_class":"P",
    "gn:feature_code":"PPL",
    "gn:name":"Casa Culin",
    "gn:population":5,
    "gn:timezone":"America/Mexico_City",
    "iso:country":"MX",
    "wof:name":"Casa Culin",
    "wof:placetype":"locality",
    "wof:population":5
},
  "geometry": {"coordinates":[-104.41943999999999,19.12417],"type":"Point"}
}