{
  "type": "Feature",
  "properties": {
    "gn:admin1_code":"5.0",
    "gn:admin2_code":"34.0",
    "gn:asciiname":"Desvio Verapaz",
    "gn:country_code":"MX",
    "gn:dem":809,
    "gn:feature_class":"P",
    "gn:feature_code":"PPL",
    "gn:name":"Desv\u00edo Verapaz",
    "gn:population":0,
    "gn:timezone":"America/Mexico_City",
    "iso:country":"MX",
    "name:spa_x_preferred":[
        "Desv\u00edo a Verapaz"
    ],
    "name:spa_x_variant":[
        "Desv\u00edo Verapaz"
    ],
    "wof:name":"Desvio Verapaz",
    "wof:placetype":"locality"
},
  "geometry": {"coordinates":[-92.06234000000001,15.69348],"type":"Point"}
}