{
  "type": "Feature",
  "properties": {
    "gn:admin1_code":"4.0",
    "gn:asciiname":"Grano de Oro",
    "gn:country_code":"MX",
    "gn:dem":14,
    "gn:feature_class":"P",
    "gn:feature_code":"PPL",
    "gn:name":"Grano de Oro",
    "gn:population":0,
    "gn:timezone":"America/Merida",
    "iso:country":"MX",
    "name:spa_x_preferred":[
        "Grano de Oro"
    ],
    "wof:name":"Grano de Oro",
    "wof:placetype":"locality"
},
  "geometry": {"coordinates":[-91.00691999999999,18.56006],"type":"Point"}
}