{
  "type": "Feature",
  "properties": {
    "gn:admin1_code":"6",
    "gn:admin2_code":"31.0",
    "gn:asciiname":"Huerta San Joaquin (Lote Cinco)",
    "gn:country_code":"MX",
    "gn:dem":1999,
    "gn:feature_class":"P",
    "gn:feature_code":"PPL",
    "gn:name":"Huerta San Joaqu\u00edn (Lote Cinco)",
    "gn:population":6,
    "gn:timezone":"America/Chihuahua",
    "iso:country":"MX",
    "name:und_x_variant":[
        "Huerta San Joaqu\u00edn (Lote Cinco)"
    ],
    "wof:name":"Huerta San Joaquin (Lote Cinco)",
    "wof:placetype":"locality",
    "wof:population":6
},
  "geometry": {"coordinates":[-107.48385,28.59027],"type":"Point"}
}