{
  "type": "Feature",
  "properties": {
    "gn:admin1_code":"10",
    "gn:admin2_code":"36.0",
    "gn:asciiname":"Torreoncito",
    "gn:country_code":"MX",
    "gn:dem":1099,
    "gn:feature_class":"P",
    "gn:feature_code":"PPL",
    "gn:name":"Torreoncito",
    "gn:population":0,
    "gn:timezone":"America/Monterrey",
    "iso:country":"MX",
    "name:spa_x_preferred":[
        "Torreoncito"
    ],
    "wof:name":"Torreoncito",
    "wof:placetype":"locality"
},
  "geometry": {"coordinates":[-103.55197,25.9552],"type":"Point"}
}