{
  "type": "Feature",
  "properties": {
    "gn:admin1_code":"10",
    "gn:admin2_code":"34.0",
    "gn:asciiname":"Aguatita",
    "gn:country_code":"MX",
    "gn:dem":661,
    "gn:feature_class":"P",
    "gn:feature_code":"PPL",
    "gn:name":"Aguatita",
    "gn:population":61,
    "gn:timezone":"America/Monterrey",
    "iso:country":"MX",
    "wof:name":"Aguatita",
    "wof:placetype":"locality",
    "wof:population":61
},
  "geometry": {"coordinates":[-106.38894999999999,24.66971],"type":"Point"}
}