{
  "type": "Feature",
  "properties": {
    "gn:admin1_code":"7.0",
    "gn:admin2_code":"7.0",
    "gn:asciiname":"Australia",
    "gn:country_code":"MX",
    "gn:dem":1750,
    "gn:feature_class":"P",
    "gn:feature_code":"PPL",
    "gn:name":"Australia",
    "gn:population":0,
    "gn:timezone":"America/Monterrey",
    "iso:country":"MX",
    "name:und_x_variant":[
        "Rancho Australia",
        "Australia"
    ],
    "wof:name":"Australia",
    "wof:placetype":"locality"
},
  "geometry": {"coordinates":[-102.32624,26.28279],"type":"Point"}
}