{
  "type": "Feature",
  "properties": {
    "gn:admin1_code":"21.0",
    "gn:admin2_code":"85.0",
    "gn:asciiname":"Piedra Molida",
    "gn:country_code":"MX",
    "gn:dem":1317,
    "gn:feature_class":"P",
    "gn:feature_code":"PPL",
    "gn:name":"Piedra Molida",
    "gn:population":0,
    "gn:timezone":"America/Mexico_City",
    "iso:country":"MX",
    "name:spa_x_preferred":[
        "Piedra Molida"
    ],
    "wof:name":"Piedra Molida",
    "wof:placetype":"locality"
},
  "geometry": {"coordinates":[-98.42809,18.62217],"type":"Point"}
}