{
  "type": "Feature",
  "properties": {
    "gn:admin1_code":"6",
    "gn:admin2_code":"65.0",
    "gn:asciiname":"Rincon del Triguito",
    "gn:country_code":"MX",
    "gn:dem":2139,
    "gn:feature_class":"P",
    "gn:feature_code":"PPL",
    "gn:name":"Rinc\u00f3n del Triguito",
    "gn:population":5,
    "gn:timezone":"America/Chihuahua",
    "iso:country":"MX",
    "name:spa_x_preferred":[
        "Rinc\u00f3n del Triguito"
    ],
    "wof:name":"Rincon del Triguito",
    "wof:placetype":"locality",
    "wof:population":5
},
  "geometry": {"coordinates":[-107.99972,27.19167],"type":"Point"}
}