{
  "type": "Feature",
  "properties": {
    "gn:admin1_code":"13",
    "gn:admin2_code":"6",
    "gn:asciiname":"Los Trejo",
    "gn:country_code":"MX",
    "gn:dem":1957,
    "gn:feature_class":"P",
    "gn:feature_code":"PPL",
    "gn:name":"Los Trejo",
    "gn:population":50,
    "gn:timezone":"America/Mexico_City",
    "iso:country":"MX",
    "wof:name":"Los Trejo",
    "wof:placetype":"locality",
    "wof:population":50
},
  "geometry": {"coordinates":[-99.35713,20.37239],"type":"Point"}
}