{
  "type": "Feature",
  "properties": {
    "gn:admin1_code":"26.0",
    "gn:admin2_code":"66.0",
    "gn:asciiname":"Bajio las Palmas",
    "gn:country_code":"MX",
    "gn:dem":625,
    "gn:feature_class":"P",
    "gn:feature_code":"PPL",
    "gn:name":"Baj\u00edo las Palmas",
    "gn:population":0,
    "gn:timezone":"America/Hermosillo",
    "iso:country":"MX",
    "name:spa_x_preferred":[
        "Baj\u00edo las Palmas"
    ],
    "wof:name":"Bajio las Palmas",
    "wof:placetype":"locality"
},
  "geometry": {"coordinates":[-110.21398000000001,29.27498],"type":"Point"}
}