{
  "type": "Feature",
  "properties": {
    "gn:admin1_code":"32.0",
    "gn:admin2_code":"16.0",
    "gn:asciiname":"Guanajuatillo",
    "gn:country_code":"MX",
    "gn:dem":2186,
    "gn:feature_class":"P",
    "gn:feature_code":"PPL",
    "gn:name":"Guanajuatillo",
    "gn:population":0,
    "gn:timezone":"America/Mexico_City",
    "iso:country":"MX",
    "name:spa_x_preferred":[
        "Guanajuatillo"
    ],
    "wof:name":"Guanajuatillo",
    "wof:placetype":"locality"
},
  "geometry": {"coordinates":[-102.1433,22.71649],"type":"Point"}
}