{
  "type": "Feature",
  "properties": {
    "gn:admin1_code":"15.0",
    "gn:admin2_code":"85.0",
    "gn:asciiname":"San Juanico Centro",
    "gn:country_code":"MX",
    "gn:dem":2552,
    "gn:feature_class":"P",
    "gn:feature_code":"PPL",
    "gn:name":"San Juanico Centro",
    "gn:population":934,
    "gn:timezone":"America/Mexico_City",
    "iso:country":"MX",
    "wof:name":"San Juanico Centro",
    "wof:placetype":"locality",
    "wof:population":934
},
  "geometry": {"coordinates":[-100.03333000000001,19.85278],"type":"Point"}
}