{
  "type": "Feature",
  "properties": {
    "gn:admin1_code":"24",
    "gn:admin2_code":"19.0",
    "gn:asciiname":"Capulincito",
    "gn:country_code":"MX",
    "gn:dem":938,
    "gn:feature_class":"P",
    "gn:feature_code":"PPL",
    "gn:name":"Capulincito",
    "gn:population":0,
    "gn:timezone":"America/Mexico_City",
    "iso:country":"MX",
    "name:spa_x_preferred":[
        "Capulincito"
    ],
    "wof:name":"Capulincito",
    "wof:placetype":"locality"
},
  "geometry": {"coordinates":[-99.50931,21.53976],"type":"Point"}
}