{
  "type": "Feature",
  "properties": {
    "gn:admin1_code":"13",
    "gn:admin2_code":"2.0",
    "gn:asciiname":"Tlalmimilolpan",
    "gn:country_code":"MX",
    "gn:dem":2332,
    "gn:feature_class":"P",
    "gn:feature_code":"PPL",
    "gn:name":"Tlalmimilolpan",
    "gn:population":0,
    "gn:timezone":"America/Mexico_City",
    "iso:country":"MX",
    "name:spa_x_preferred":[
        "Tlamiminolpa"
    ],
    "name:spa_x_variant":[
        "Tlalmimilolpan"
    ],
    "wof:name":"Tlalmimilolpan",
    "wof:placetype":"locality"
},
  "geometry": {"coordinates":[-98.21908999999999,20.13856],"type":"Point"}
}