{
  "type": "Feature",
  "properties": {
    "gn:admin1_code":"19.0",
    "gn:asciiname":"San Ignacio",
    "gn:country_code":"MX",
    "gn:dem":436,
    "gn:feature_class":"P",
    "gn:feature_code":"PPL",
    "gn:name":"San Ignacio",
    "gn:population":0,
    "gn:timezone":"America/Monterrey",
    "iso:country":"MX",
    "name:spa_x_preferred":[
        "San Ignacio"
    ],
    "wof:name":"San Ignacio",
    "wof:placetype":"locality"
},
  "geometry": {"coordinates":[-100.22451,25.88017],"type":"Point"}
}