{
  "type": "Feature",
  "properties": {
    "gn:admin1_code":"6",
    "gn:admin2_code":"12.0",
    "gn:asciiname":"Paraje San Lazaro",
    "gn:country_code":"MX",
    "gn:dem":2186,
    "gn:feature_class":"P",
    "gn:feature_code":"PPL",
    "gn:name":"Paraje San Lazaro",
    "gn:population":0,
    "gn:timezone":"America/Chihuahua",
    "iso:country":"MX",
    "name:spa_x_preferred":[
        "Paraje San Lazaro"
    ],
    "wof:name":"Paraje San Lazaro",
    "wof:placetype":"locality"
},
  "geometry": {"coordinates":[-107.18608999999999,27.80973],"type":"Point"}
}