{
  "type": "Feature",
  "properties": {
    "gn:admin1_code":"24",
    "gn:admin2_code":"54.0",
    "gn:asciiname":"Barrio de Cristo Rey (Apetzco)",
    "gn:country_code":"MX",
    "gn:dem":872,
    "gn:feature_class":"P",
    "gn:feature_code":"PPL",
    "gn:name":"Barrio de Cristo Rey (Apetzco)",
    "gn:population":467,
    "gn:timezone":"America/Mexico_City",
    "iso:country":"MX",
    "wof:name":"Barrio de Cristo Rey (Apetzco)",
    "wof:placetype":"locality",
    "wof:population":467
},
  "geometry": {"coordinates":[-99.0125,21.39972],"type":"Point"}
}