{
  "type": "Feature",
  "properties": {
    "gn:admin1_code":"28.0",
    "gn:admin2_code":"2.0",
    "gn:asciiname":"Zanapeno",
    "gn:country_code":"MX",
    "gn:dem":228,
    "gn:feature_class":"P",
    "gn:feature_code":"PPL",
    "gn:name":"Zanape\u00f1o",
    "gn:population":0,
    "gn:timezone":"America/Monterrey",
    "iso:country":"MX",
    "name:spa_x_preferred":[
        "Zanape\u00f1o"
    ],
    "wof:name":"Zanapeno",
    "wof:placetype":"locality"
},
  "geometry": {"coordinates":[-98.07752000000001,23.09121],"type":"Point"}
}