{
  "type": "Feature",
  "properties": {
    "gn:admin1_code":"10",
    "gn:admin2_code":"5.0",
    "gn:asciiname":"Rancho los Arcos del Vergel",
    "gn:country_code":"MX",
    "gn:dem":1889,
    "gn:feature_class":"P",
    "gn:feature_code":"PPL",
    "gn:name":"Rancho los Arcos del Vergel",
    "gn:population":4,
    "gn:timezone":"America/Monterrey",
    "iso:country":"MX",
    "wof:name":"Rancho los Arcos del Vergel",
    "wof:placetype":"locality",
    "wof:population":4
},
  "geometry": {"coordinates":[-104.48528,23.89585],"type":"Point"}
}