{
  "type": "Feature",
  "properties": {
    "gn:admin1_code":"19.0",
    "gn:admin2_code":"13.0",
    "gn:asciiname":"El Gonzaleno",
    "gn:country_code":"MX",
    "gn:dem":187,
    "gn:feature_class":"P",
    "gn:feature_code":"PPL",
    "gn:name":"El Gonzale\u00f1o",
    "gn:population":0,
    "gn:timezone":"America/Monterrey",
    "iso:country":"MX",
    "name:spa_x_preferred":[
        "El Gonzale\u00f1o"
    ],
    "wof:name":"El Gonzaleno",
    "wof:placetype":"locality"
},
  "geometry": {"coordinates":[-99.17523,25.53064],"type":"Point"}
}