{
  "type": "Feature",
  "properties": {
    "gn:admin1_code":"24",
    "gn:admin2_code":"55.0",
    "gn:asciiname":"Los Pilares",
    "gn:country_code":"MX",
    "gn:dem":1897,
    "gn:feature_class":"P",
    "gn:feature_code":"PPL",
    "gn:name":"Los Pilares",
    "gn:population":210,
    "gn:timezone":"America/Mexico_City",
    "iso:country":"MX",
    "wof:name":"Los Pilares",
    "wof:placetype":"locality",
    "wof:population":210
},
  "geometry": {"coordinates":[-100.78055999999999,21.92889],"type":"Point"}
}