{
  "type": "Feature",
  "properties": {
    "gn:admin1_code":"32",
    "gn:admin2_code":"48.0",
    "gn:asciiname":"Guadalupe Victoria (La Mezquitera)",
    "gn:country_code":"MX",
    "gn:dem":1685,
    "gn:feature_class":"P",
    "gn:feature_code":"PPL",
    "gn:name":"Guadalupe Victoria (La Mezquitera)",
    "gn:population":153,
    "gn:timezone":"America/Mexico_City",
    "iso:country":"MX",
    "wof:name":"Guadalupe Victoria (La Mezquitera)",
    "wof:placetype":"locality",
    "wof:population":153
},
  "geometry": {"coordinates":[-103.28333000000001,21.82861],"type":"Point"}
}