{
  "type": "Feature",
  "properties": {
    "gn:admin1_code":"16.0",
    "gn:asciiname":"El Pinal",
    "gn:country_code":"MX",
    "gn:dem":2251,
    "gn:feature_class":"P",
    "gn:feature_code":"PPL",
    "gn:name":"El Pinal",
    "gn:population":0,
    "gn:timezone":"America/Mexico_City",
    "iso:country":"MX",
    "name:spa_x_preferred":[
        "El Pinal"
    ],
    "wof:name":"El Pinal",
    "wof:placetype":"locality"
},
  "geometry": {"coordinates":[-100.55486999999999,19.57712],"type":"Point"}
}