{
  "type": "Feature",
  "properties": {
    "gn:admin1_code":"30",
    "gn:admin2_code":"139.0",
    "gn:asciiname":"Las Blancas",
    "gn:country_code":"MX",
    "gn:dem":5,
    "gn:feature_class":"P",
    "gn:feature_code":"PPL",
    "gn:name":"Las Blancas",
    "gn:population":0,
    "gn:timezone":"America/Mexico_City",
    "iso:country":"MX",
    "name:spa_x_preferred":[
        "Las Blancas"
    ],
    "wof:name":"Las Blancas",
    "wof:placetype":"locality"
},
  "geometry": {"coordinates":[-95.54566,18.60461],"type":"Point"}
}