{
  "type": "Feature",
  "properties": {
    "gn:admin1_code":"21",
    "gn:admin2_code":"114",
    "gn:asciiname":"Pochote de Tetela",
    "gn:country_code":"MX",
    "gn:dem":2140,
    "gn:feature_class":"P",
    "gn:feature_code":"PPL",
    "gn:name":"Pochote de Tetela",
    "gn:population":49,
    "gn:timezone":"America/Mexico_City",
    "iso:country":"MX",
    "wof:name":"Pochote de Tetela",
    "wof:placetype":"locality",
    "wof:population":49
},
  "geometry": {"coordinates":[-98.20719,18.88821],"type":"Point"}
}