{
  "type": "Feature",
  "properties": {
    "gn:admin1_code":"6",
    "gn:admin2_code":"27.0",
    "gn:asciiname":"Nachacachi",
    "gn:country_code":"MX",
    "gn:dem":2429,
    "gn:feature_class":"P",
    "gn:feature_code":"PPL",
    "gn:name":"Nachacachi",
    "gn:population":141,
    "gn:timezone":"America/Chihuahua",
    "iso:country":"MX",
    "name:spa_x_preferred":[
        "Nachacachi"
    ],
    "wof:name":"Nachacachi",
    "wof:placetype":"locality",
    "wof:population":141
},
  "geometry": {"coordinates":[-107.13290000000001,26.90883],"type":"Point"}
}