{
  "type": "Feature",
  "properties": {
    "gn:admin1_code":"5",
    "gn:admin2_code":"31",
    "gn:asciiname":"Fraccion Xaquila",
    "gn:country_code":"MX",
    "gn:dem":977,
    "gn:feature_class":"P",
    "gn:feature_code":"PPL",
    "gn:name":"Fracci\u00f3n Xaquila",
    "gn:population":48,
    "gn:timezone":"America/Mexico_City",
    "iso:country":"MX",
    "name:und_x_variant":[
        "Fracci\u00f3n Xaquila"
    ],
    "wof:name":"Fraccion Xaquila",
    "wof:placetype":"locality",
    "wof:population":48
},
  "geometry": {"coordinates":[-92.2775,17.08111],"type":"Point"}
}