{
  "type": "Feature",
  "properties": {
    "gn:admin1_code":"30",
    "gn:admin2_code":"159.0",
    "gn:asciiname":"Tepetlampa",
    "gn:country_code":"MX",
    "gn:dem":1991,
    "gn:feature_class":"P",
    "gn:feature_code":"PPL",
    "gn:name":"Tepetlampa",
    "gn:population":221,
    "gn:timezone":"America/Mexico_City",
    "iso:country":"MX",
    "wof:name":"Tepetlampa",
    "wof:placetype":"locality",
    "wof:population":221
},
  "geometry": {"coordinates":[-97.04389,18.57444],"type":"Point"}
}