{
  "type": "Feature",
  "properties": {
    "gn:admin1_code":"10",
    "gn:admin2_code":"18.0",
    "gn:asciiname":"Campo Agrario (El Bronco)",
    "gn:country_code":"MX",
    "gn:dem":1609,
    "gn:feature_class":"P",
    "gn:feature_code":"PPL",
    "gn:name":"Campo Agrario (El Bronco)",
    "gn:population":96,
    "gn:timezone":"America/Monterrey",
    "iso:country":"MX",
    "wof:name":"Campo Agrario (El Bronco)",
    "wof:placetype":"locality",
    "wof:population":96
},
  "geometry": {"coordinates":[-105.34424,25.32832],"type":"Point"}
}