{
  "type": "Feature",
  "properties": {
    "gn:admin1_code":"28.0",
    "gn:admin2_code":"37.0",
    "gn:asciiname":"Guerrero",
    "gn:country_code":"MX",
    "gn:dem":129,
    "gn:feature_class":"P",
    "gn:feature_code":"PPL",
    "gn:name":"Guerrero",
    "gn:population":1,
    "gn:timezone":"America/Monterrey",
    "iso:country":"MX",
    "name:spa_x_preferred":[
        "Guerrero"
    ],
    "wof:name":"Guerrero",
    "wof:placetype":"locality",
    "wof:population":1
},
  "geometry": {"coordinates":[-98.06997,23.3489],"type":"Point"}
}