{
  "type": "Feature",
  "properties": {
    "gn:admin1_code":"21",
    "gn:admin2_code":"2.0",
    "gn:asciiname":"El Aguila",
    "gn:country_code":"MX",
    "gn:dem":258,
    "gn:feature_class":"P",
    "gn:feature_code":"PPL",
    "gn:name":"El \u00c1guila",
    "gn:population":94,
    "gn:timezone":"America/Mexico_City",
    "iso:country":"MX",
    "name:fas_x_preferred":[
        "\u0627\u0644\u06af\u0648\u0626\u0644\u0627"
    ],
    "name:fra_x_preferred":[
        "El Aguila"
    ],
    "name:ita_x_preferred":[
        "Aguila"
    ],
    "name:und_x_variant":[
        "El \u00c1guila"
    ],
    "wof:name":"El Aguila",
    "wof:placetype":"locality",
    "wof:population":94
},
  "geometry": {"coordinates":[-97.22078,20.08619],"type":"Point"}
}