{
  "type": "Feature",
  "properties": {
    "gn:admin1_code":"16.0",
    "gn:asciiname":"Huajumbarito",
    "gn:country_code":"MX",
    "gn:dem":2558,
    "gn:feature_class":"P",
    "gn:feature_code":"PPL",
    "gn:name":"Huajumbarito",
    "gn:population":0,
    "gn:timezone":"America/Mexico_City",
    "iso:country":"MX",
    "name:spa_x_preferred":[
        "Huajumbarito"
    ],
    "wof:name":"Huajumbarito",
    "wof:placetype":"locality"
},
  "geometry": {"coordinates":[-100.59604,19.86858],"type":"Point"}
}