{
  "type": "Feature",
  "properties": {
    "gn:admin1_code":"10.0",
    "gn:admin2_code":"9.0",
    "gn:asciiname":"El Pajaro",
    "gn:country_code":"MX",
    "gn:dem":2076,
    "gn:feature_class":"P",
    "gn:feature_code":"PPL",
    "gn:name":"El P\u00e1jaro",
    "gn:population":0,
    "gn:timezone":"America/Monterrey",
    "iso:country":"MX",
    "name:spa_x_preferred":[
        "El P\u00e1jaro"
    ],
    "wof:name":"El Pajaro",
    "wof:placetype":"locality"
},
  "geometry": {"coordinates":[-105.9414,25.93397],"type":"Point"}
}