{
  "type": "Feature",
  "properties": {
    "gn:admin1_code":"13",
    "gn:admin2_code":"36.0",
    "gn:asciiname":"Xoxoteco",
    "gn:country_code":"MX",
    "gn:dem":1389,
    "gn:feature_class":"P",
    "gn:feature_code":"PPL",
    "gn:name":"Xoxoteco",
    "gn:population":597,
    "gn:timezone":"America/Mexico_City",
    "iso:country":"MX",
    "name:spa_x_preferred":[
        "Xoxoteco"
    ],
    "name:spa_x_variant":[
        "Santa Mar\u00eda"
    ],
    "name:und_x_variant":[
        "Xocoteco",
        "Santa Mar\u00eda Xoxoteca",
        "Santa Mar\u00eda Xoxoteco"
    ],
    "wof:name":"Xoxoteco",
    "wof:placetype":"locality",
    "wof:population":597
},
  "geometry": {"coordinates":[-98.62511000000001,20.51521],"type":"Point"}
}