{
  "type": "Feature",
  "properties": {
    "gn:admin1_code":"30",
    "gn:admin2_code":"82",
    "gn:asciiname":"Cadete Juan de la Barrera",
    "gn:country_code":"MX",
    "gn:dem":21,
    "gn:feature_class":"P",
    "gn:feature_code":"PPL",
    "gn:name":"Cadete Juan de la Barrera",
    "gn:population":43,
    "gn:timezone":"America/Mexico_City",
    "iso:country":"MX",
    "wof:name":"Cadete Juan de la Barrera",
    "wof:placetype":"locality",
    "wof:population":43
},
  "geometry": {"coordinates":[-94.42610999999999,18.0325],"type":"Point"}
}