{
  "type": "Feature",
  "properties": {
    "gn:admin1_code":"6",
    "gn:admin2_code":"21.0",
    "gn:asciiname":"El Triangulo",
    "gn:country_code":"MX",
    "gn:dem":1173,
    "gn:feature_class":"P",
    "gn:feature_code":"PPL",
    "gn:name":"El Tri\u00e1ngulo",
    "gn:population":6,
    "gn:timezone":"America/Chihuahua",
    "iso:country":"MX",
    "name:und_x_variant":[
        "El Tri\u00e1ngulo"
    ],
    "wof:name":"El Triangulo",
    "wof:placetype":"locality",
    "wof:population":6
},
  "geometry": {"coordinates":[-105.45296999999999,28.23409],"type":"Point"}
}