{
  "type": "Feature",
  "properties": {
    "gn:admin1_code":"16.0",
    "gn:admin2_code":"8.0",
    "gn:asciiname":"Ahuindillo",
    "gn:country_code":"MX",
    "gn:dem":99,
    "gn:feature_class":"P",
    "gn:feature_code":"PPL",
    "gn:name":"Ahuindillo",
    "gn:population":0,
    "gn:timezone":"America/Mexico_City",
    "iso:country":"MX",
    "name:spa_x_preferred":[
        "Ahuindillo"
    ],
    "wof:name":"Ahuindillo",
    "wof:placetype":"locality"
},
  "geometry": {"coordinates":[-103.28261999999999,18.34733],"type":"Point"}
}