{
  "type": "Feature",
  "properties": {
    "gn:admin1_code":"6.0",
    "gn:admin2_code":"63.0",
    "gn:asciiname":"Arroyo del Padre",
    "gn:country_code":"MX",
    "gn:dem":2185,
    "gn:feature_class":"P",
    "gn:feature_code":"PPL",
    "gn:name":"Arroyo del Padre",
    "gn:population":0,
    "gn:timezone":"America/Chihuahua",
    "iso:country":"MX",
    "name:spa_x_preferred":[
        "Arroyo del Padre"
    ],
    "wof:name":"Arroyo del Padre",
    "wof:placetype":"locality"
},
  "geometry": {"coordinates":[-108.31797,28.71992],"type":"Point"}
}