{
  "type": "Feature",
  "properties": {
    "gn:admin1_code":"21.0",
    "gn:admin2_code":"111.0",
    "gn:asciiname":"El Zapotal",
    "gn:country_code":"MX",
    "gn:dem":216,
    "gn:feature_class":"P",
    "gn:feature_code":"PPL",
    "gn:name":"El Zapotal",
    "gn:population":70,
    "gn:timezone":"America/Mexico_City",
    "iso:country":"MX",
    "name:fra_x_preferred":[
        "El Zapotal"
    ],
    "name:spa_x_preferred":[
        "El Zapotal"
    ],
    "wof:name":"El Zapotal",
    "wof:placetype":"locality",
    "wof:population":70
},
  "geometry": {"coordinates":[-97.88341,20.5979],"type":"Point"}
}