{
  "type": "Feature",
  "properties": {
    "gn:admin1_code":"30",
    "gn:admin2_code":"86.0",
    "gn:asciiname":"Loma de Hidalgo",
    "gn:country_code":"MX",
    "gn:dem":2187,
    "gn:feature_class":"P",
    "gn:feature_code":"PPL",
    "gn:name":"Loma de Hidalgo",
    "gn:population":832,
    "gn:timezone":"America/Mexico_City",
    "iso:country":"MX",
    "wof:name":"Loma de Hidalgo",
    "wof:placetype":"locality",
    "wof:population":832
},
  "geometry": {"coordinates":[-97.29583,19.7475],"type":"Point"}
}