{
  "type": "Feature",
  "properties": {
    "gn:admin1_code":"19.0",
    "gn:admin2_code":"27.0",
    "gn:asciiname":"Santa Dominga",
    "gn:country_code":"MX",
    "gn:dem":184,
    "gn:feature_class":"P",
    "gn:feature_code":"PPL",
    "gn:name":"Santa Dominga",
    "gn:population":0,
    "gn:timezone":"America/Monterrey",
    "iso:country":"MX",
    "name:spa_x_preferred":[
        "Santa Dominga"
    ],
    "wof:name":"Santa Dominga",
    "wof:placetype":"locality"
},
  "geometry": {"coordinates":[-99.47889000000001,25.97148],"type":"Point"}
}