{
  "type": "Feature",
  "properties": {
    "gn:admin1_code":"6",
    "gn:admin2_code":"47.0",
    "gn:asciiname":"Arroyo de la Yegua",
    "gn:country_code":"MX",
    "gn:dem":1045,
    "gn:feature_class":"P",
    "gn:feature_code":"PPL",
    "gn:name":"Arroyo de la Yegua",
    "gn:population":0,
    "gn:timezone":"America/Chihuahua",
    "iso:country":"MX",
    "name:spa_x_preferred":[
        "El Piloncillo"
    ],
    "name:spa_x_variant":[
        "Arroyo de la Yegua"
    ],
    "wof:name":"Arroyo de la Yegua",
    "wof:placetype":"locality"
},
  "geometry": {"coordinates":[-108.87967,28.11394],"type":"Point"}
}