{
  "type": "Feature",
  "properties": {
    "gn:admin1_code":"32.0",
    "gn:admin2_code":"31.0",
    "gn:asciiname":"Las Tinajitas",
    "gn:country_code":"MX",
    "gn:dem":2271,
    "gn:feature_class":"P",
    "gn:feature_code":"PPL",
    "gn:name":"Las Tinajitas",
    "gn:population":0,
    "gn:timezone":"America/Mexico_City",
    "iso:country":"MX",
    "name:spa_x_preferred":[
        "Las Tinajitas"
    ],
    "wof:name":"Las Tinajitas",
    "wof:placetype":"locality"
},
  "geometry": {"coordinates":[-103.60163,22.25573],"type":"Point"}
}