{
  "type": "Feature",
  "properties": {
    "gn:admin1_code":"30.0",
    "gn:admin2_code":"152.0",
    "gn:asciiname":"Maderas",
    "gn:country_code":"MX",
    "gn:dem":6,
    "gn:feature_class":"P",
    "gn:feature_code":"PPL",
    "gn:name":"Maderas",
    "gn:population":37,
    "gn:timezone":"America/Mexico_City",
    "iso:country":"MX",
    "name:spa_x_preferred":[
        "Maderas"
    ],
    "wof:name":"Maderas",
    "wof:placetype":"locality",
    "wof:population":37
},
  "geometry": {"coordinates":[-97.60083,21.76444],"type":"Point"}
}