{
  "type": "Feature",
  "properties": {
    "gn:admin1_code":"24",
    "gn:admin2_code":"2.0",
    "gn:asciiname":"Mesa de San Francisco (Mesa de San Jose)",
    "gn:country_code":"MX",
    "gn:dem":1417,
    "gn:feature_class":"P",
    "gn:feature_code":"PPL",
    "gn:name":"Mesa de San Francisco (Mesa de San Jos\u00e9)",
    "gn:population":89,
    "gn:timezone":"America/Mexico_City",
    "iso:country":"MX",
    "name:und_x_variant":[
        "Mesa de San Francisco (Mesa de San Jos\u00e9)"
    ],
    "wof:name":"Mesa de San Francisco (Mesa de San Jose)",
    "wof:placetype":"locality",
    "wof:population":89
},
  "geometry": {"coordinates":[-99.59833,22.1175],"type":"Point"}
}