{
  "type": "Feature",
  "properties": {
    "gn:admin1_code":"14",
    "gn:admin2_code":"116.0",
    "gn:asciiname":"Llano de la Cienega",
    "gn:country_code":"MX",
    "gn:dem":2391,
    "gn:feature_class":"P",
    "gn:feature_code":"PPL",
    "gn:name":"Llano de la Ci\u00e9nega",
    "gn:population":8,
    "gn:timezone":"America/Mexico_City",
    "iso:country":"MX",
    "name:und_x_variant":[
        "Llano de la Ci\u00e9nega"
    ],
    "wof:name":"Llano de la Cienega",
    "wof:placetype":"locality",
    "wof:population":8
},
  "geometry": {"coordinates":[-102.69917,21.7075],"type":"Point"}
}