{
  "type": "Feature",
  "properties": {
    "gn:admin1_code":"13",
    "gn:admin2_code":"54.0",
    "gn:asciiname":"El Durazno (El Durazno de Flores Magon)",
    "gn:country_code":"MX",
    "gn:dem":1970,
    "gn:feature_class":"P",
    "gn:feature_code":"PPL",
    "gn:name":"El Durazno (El Durazno de Flores Mag\u00f3n)",
    "gn:population":121,
    "gn:timezone":"America/Mexico_City",
    "iso:country":"MX",
    "name:und_x_variant":[
        "El Durazno (El Durazno de Flores Mag\u00f3n)"
    ],
    "wof:name":"El Durazno (El Durazno de Flores Magon)",
    "wof:placetype":"locality",
    "wof:population":121
},
  "geometry": {"coordinates":[-99.02528,20.28278],"type":"Point"}
}