{
  "type": "Feature",
  "properties": {
    "gn:admin1_code":"16",
    "gn:admin2_code":"99.0",
    "gn:asciiname":"Las Juntas del Tanque",
    "gn:country_code":"MX",
    "gn:dem":538,
    "gn:feature_class":"P",
    "gn:feature_code":"PPL",
    "gn:name":"Las Juntas del Tanque",
    "gn:population":508,
    "gn:timezone":"America/Mexico_City",
    "iso:country":"MX",
    "wof:name":"Las Juntas del Tanque",
    "wof:placetype":"locality",
    "wof:population":508
},
  "geometry": {"coordinates":[-100.65971999999999,19.17278],"type":"Point"}
}