{
  "type": "Feature",
  "properties": {
    "gn:admin1_code":"28",
    "gn:admin2_code":"18.0",
    "gn:asciiname":"Sor Juana Ines de la Cruz",
    "gn:country_code":"MX",
    "gn:dem":145,
    "gn:feature_class":"P",
    "gn:feature_code":"PPL",
    "gn:name":"Sor Juana In\u00e9s de la Cruz",
    "gn:population":93,
    "gn:timezone":"America/Monterrey",
    "iso:country":"MX",
    "name:und_x_variant":[
        "Sor Juana In\u00e9s de la Cruz"
    ],
    "wof:name":"Sor Juana Ines de la Cruz",
    "wof:placetype":"locality",
    "wof:population":93
},
  "geometry": {"coordinates":[-98.46194,24.27389],"type":"Point"}
}