{
  "type": "Feature",
  "properties": {
    "gn:admin1_code":"30",
    "gn:admin2_code":"189.0",
    "gn:asciiname":"Cobos",
    "gn:country_code":"MX",
    "gn:dem":5,
    "gn:feature_class":"P",
    "gn:feature_code":"PPL",
    "gn:name":"Cobos",
    "gn:population":587,
    "gn:timezone":"America/Mexico_City",
    "iso:country":"MX",
    "wof:name":"Cobos",
    "wof:placetype":"locality",
    "wof:population":587
},
  "geometry": {"coordinates":[-97.3625,20.93944],"type":"Point"}
}