{
  "type": "Feature",
  "properties": {
    "gn:admin1_code":"5",
    "gn:admin2_code":"65.0",
    "gn:asciiname":"El Guayacan",
    "gn:country_code":"MX",
    "gn:dem":46,
    "gn:feature_class":"P",
    "gn:feature_code":"PPL",
    "gn:name":"El Guayac\u00e1n",
    "gn:population":125,
    "gn:timezone":"America/Mexico_City",
    "iso:country":"MX",
    "name:und_x_variant":[
        "El Guayac\u00e1n"
    ],
    "wof:name":"El Guayacan",
    "wof:placetype":"locality",
    "wof:population":125
},
  "geometry": {"coordinates":[-91.72472,17.47278],"type":"Point"}
}