{
  "type": "Feature",
  "properties": {
    "gn:admin1_code":"6",
    "gn:admin2_code":"45.0",
    "gn:asciiname":"Estrella",
    "gn:country_code":"MX",
    "gn:dem":1130,
    "gn:feature_class":"P",
    "gn:feature_code":"PPL",
    "gn:name":"Estrella",
    "gn:population":5,
    "gn:timezone":"America/Chihuahua",
    "iso:country":"MX",
    "wof:name":"Estrella",
    "wof:placetype":"locality",
    "wof:population":5
},
  "geometry": {"coordinates":[-105.46332,28.34195],"type":"Point"}
}