{
  "type": "Feature",
  "properties": {
    "gn:admin1_code":"30",
    "gn:admin2_code":"77.0",
    "gn:asciiname":"Poza Honda",
    "gn:country_code":"MX",
    "gn:dem":14,
    "gn:feature_class":"P",
    "gn:feature_code":"PPL",
    "gn:name":"Poza Honda",
    "gn:population":0,
    "gn:timezone":"America/Mexico_City",
    "iso:country":"MX",
    "name:spa_x_preferred":[
        "Poza Honda"
    ],
    "wof:name":"Poza Honda",
    "wof:placetype":"locality"
},
  "geometry": {"coordinates":[-95.62568,18.18547],"type":"Point"}
}