{
  "type": "Feature",
  "properties": {
    "gn:admin1_code":"6",
    "gn:asciiname":"Cornelio",
    "gn:country_code":"MX",
    "gn:dem":386,
    "gn:feature_class":"P",
    "gn:feature_code":"PPL",
    "gn:name":"Cornelio",
    "gn:population":0,
    "gn:timezone":"America/Mazatlan",
    "iso:country":"MX",
    "name:spa_x_preferred":[
        "Cornelio"
    ],
    "wof:name":"Cornelio",
    "wof:placetype":"locality"
},
  "geometry": {"coordinates":[-107.70462000000001,26.16841],"type":"Point"}
}