{
  "type": "Feature",
  "properties": {
    "gn:admin1_code":"12",
    "gn:admin2_code":"62.0",
    "gn:asciiname":"Plan Mamey",
    "gn:country_code":"MX",
    "gn:dem":1215,
    "gn:feature_class":"P",
    "gn:feature_code":"PPL",
    "gn:name":"Plan Mamey",
    "gn:population":73,
    "gn:timezone":"America/Mexico_City",
    "iso:country":"MX",
    "wof:name":"Plan Mamey",
    "wof:placetype":"locality",
    "wof:population":73
},
  "geometry": {"coordinates":[-98.09238999999999,17.05387],"type":"Point"}
}