{
  "type": "Feature",
  "properties": {
    "gn:admin1_code":"16",
    "gn:admin2_code":"22",
    "gn:asciiname":"El Limoncito",
    "gn:country_code":"MX",
    "gn:dem":1263,
    "gn:feature_class":"P",
    "gn:feature_code":"PPL",
    "gn:name":"El Limoncito",
    "gn:population":18,
    "gn:timezone":"America/Mexico_City",
    "iso:country":"MX",
    "wof:name":"El Limoncito",
    "wof:placetype":"locality",
    "wof:population":18
},
  "geometry": {"coordinates":[-100.9825,19.58667],"type":"Point"}
}