{
  "type": "Feature",
  "properties": {
    "gn:admin1_code":"25",
    "gn:admin2_code":"4.0",
    "gn:asciiname":"La Llantera",
    "gn:country_code":"MX",
    "gn:dem":2004,
    "gn:feature_class":"P",
    "gn:feature_code":"PPL",
    "gn:name":"La Llantera",
    "gn:population":0,
    "gn:timezone":"America/Mazatlan",
    "iso:country":"MX",
    "name:spa_x_preferred":[
        "La Llantera"
    ],
    "wof:name":"La Llantera",
    "wof:placetype":"locality"
},
  "geometry": {"coordinates":[-105.8524,23.56534],"type":"Point"}
}