{
  "type": "Feature",
  "properties": {
    "gn:admin1_code":"14",
    "gn:admin2_code":"84",
    "gn:asciiname":"Santa Julia (Rajas Paradas)",
    "gn:country_code":"MX",
    "gn:dem":377,
    "gn:feature_class":"P",
    "gn:feature_code":"PPL",
    "gn:name":"Santa Julia (Rajas Paradas)",
    "gn:population":29,
    "gn:timezone":"America/Mexico_City",
    "iso:country":"MX",
    "wof:name":"Santa Julia (Rajas Paradas)",
    "wof:placetype":"locality",
    "wof:population":29
},
  "geometry": {"coordinates":[-104.87860999999999,20.12194],"type":"Point"}
}