{
  "type": "Feature",
  "properties": {
    "gn:admin1_code":"10",
    "gn:admin2_code":"14.0",
    "gn:asciiname":"Mojolotita",
    "gn:country_code":"MX",
    "gn:dem":572,
    "gn:feature_class":"P",
    "gn:feature_code":"PPL",
    "gn:name":"Mojolotita",
    "gn:population":0,
    "gn:timezone":"America/Monterrey",
    "iso:country":"MX",
    "name:spa_x_preferred":[
        "Mojolotita"
    ],
    "wof:name":"Mojolotita",
    "wof:placetype":"locality"
},
  "geometry": {"coordinates":[-104.50614,22.51386],"type":"Point"}
}