{
  "type": "Feature",
  "properties": {
    "gn:admin1_code":"6",
    "gn:admin2_code":"61.0",
    "gn:asciiname":"La Tinaja Pananena",
    "gn:country_code":"MX",
    "gn:dem":1591,
    "gn:feature_class":"P",
    "gn:feature_code":"PPL",
    "gn:name":"La Tinaja Pa\u00f1anena",
    "gn:population":0,
    "gn:timezone":"America/Chihuahua",
    "iso:country":"MX",
    "name:spa_x_preferred":[
        "La Tinaja Pa\u00f1anena"
    ],
    "wof:name":"La Tinaja Pananena",
    "wof:placetype":"locality"
},
  "geometry": {"coordinates":[-106.28676000000002,27.45854000000001],"type":"Point"}
}