{
  "type": "Feature",
  "properties": {
    "gn:admin1_code":"19.0",
    "gn:asciiname":"El Manantial",
    "gn:country_code":"MX",
    "gn:dem":450,
    "gn:feature_class":"P",
    "gn:feature_code":"PPL",
    "gn:name":"El Manantial",
    "gn:population":0,
    "gn:timezone":"America/Monterrey",
    "iso:country":"MX",
    "name:spa_x_preferred":[
        "El Manantial"
    ],
    "wof:name":"El Manantial",
    "wof:placetype":"locality"
},
  "geometry": {"coordinates":[-100.21250999999999,25.76987],"type":"Point"}
}