{
  "type": "Feature",
  "properties": {
    "gn:admin1_code":"16",
    "gn:admin2_code":"88.0",
    "gn:asciiname":"Santa Ana del Arco",
    "gn:country_code":"MX",
    "gn:dem":1853,
    "gn:feature_class":"P",
    "gn:feature_code":"PPL",
    "gn:name":"Santa Ana del Arco",
    "gn:population":401,
    "gn:timezone":"America/Mexico_City",
    "iso:country":"MX",
    "wof:name":"Santa Ana del Arco",
    "wof:placetype":"locality",
    "wof:population":401
},
  "geometry": {"coordinates":[-101.13556,19.81778],"type":"Point"}
}