{
  "type": "Feature",
  "properties": {
    "gn:admin1_code":"19.0",
    "gn:asciiname":"La Colmena",
    "gn:country_code":"MX",
    "gn:dem":555,
    "gn:feature_class":"P",
    "gn:feature_code":"PPL",
    "gn:name":"La Colmena",
    "gn:population":0,
    "gn:timezone":"America/Monterrey",
    "iso:country":"MX",
    "name:spa_x_preferred":[
        "La Colmena"
    ],
    "wof:name":"La Colmena",
    "wof:placetype":"locality"
},
  "geometry": {"coordinates":[-99.70705,24.71101],"type":"Point"}
}