{
  "type": "Feature",
  "properties": {
    "gn:admin1_code":"26.0",
    "gn:admin2_code":"40.0",
    "gn:asciiname":"El Ancon",
    "gn:country_code":"MX",
    "gn:dem":1334,
    "gn:feature_class":"P",
    "gn:feature_code":"PPL",
    "gn:name":"El Anc\u00f3n",
    "gn:population":0,
    "gn:timezone":"America/Hermosillo",
    "iso:country":"MX",
    "name:spa_x_preferred":[
        "El Anc\u00f3n"
    ],
    "wof:name":"El Ancon",
    "wof:placetype":"locality"
},
  "geometry": {"coordinates":[-108.74399,29.65592],"type":"Point"}
}