{
  "type": "Feature",
  "properties": {
    "gn:admin1_code":"32",
    "gn:admin2_code":"26.0",
    "gn:asciiname":"Mendez",
    "gn:country_code":"MX",
    "gn:dem":1737,
    "gn:feature_class":"P",
    "gn:feature_code":"PPL",
    "gn:name":"M\u00e9ndez",
    "gn:population":0,
    "gn:timezone":"America/Mexico_City",
    "iso:country":"MX",
    "name:srp_x_preferred":[
        "\u041c\u0435\u043d\u0434\u0435\u0437"
    ],
    "wof:name":"Mendez",
    "wof:placetype":"locality"
},
  "geometry": {"coordinates":[-102.08333,24.15],"type":"Point"}
}