{
  "type": "Feature",
  "properties": {
    "gn:admin1_code":"11.0",
    "gn:admin2_code":"24.0",
    "gn:asciiname":"Casa Blanca",
    "gn:country_code":"MX",
    "gn:dem":1723,
    "gn:feature_class":"P",
    "gn:feature_code":"PPL",
    "gn:name":"Casa Blanca",
    "gn:population":286,
    "gn:timezone":"America/Mexico_City",
    "iso:country":"MX",
    "name:spa_x_preferred":[
        "Casa Blanca"
    ],
    "wof:name":"Casa Blanca",
    "wof:placetype":"locality",
    "wof:population":286
},
  "geometry": {"coordinates":[-101.31907,20.57008],"type":"Point"}
}