{
  "type": "Feature",
  "properties": {
    "gn:admin1_code":"5",
    "gn:admin2_code":"17",
    "gn:asciiname":"Cuatro de Agosto",
    "gn:country_code":"MX",
    "gn:dem":559,
    "gn:feature_class":"P",
    "gn:feature_code":"PPL",
    "gn:name":"Cuatro de Agosto",
    "gn:population":16,
    "gn:timezone":"America/Mexico_City",
    "iso:country":"MX",
    "wof:name":"Cuatro de Agosto",
    "wof:placetype":"locality",
    "wof:population":16
},
  "geometry": {"coordinates":[-93.895,16.84778],"type":"Point"}
}