{
  "type": "Feature",
  "properties": {
    "gn:admin1_code":"30",
    "gn:admin2_code":"173.0",
    "gn:asciiname":"El Suspiro",
    "gn:country_code":"MX",
    "gn:dem":106,
    "gn:feature_class":"P",
    "gn:feature_code":"PPL",
    "gn:name":"El Suspiro",
    "gn:population":523,
    "gn:timezone":"America/Mexico_City",
    "iso:country":"MX",
    "wof:name":"El Suspiro",
    "wof:placetype":"locality",
    "wof:population":523
},
  "geometry": {"coordinates":[-96.77806,18.46583],"type":"Point"}
}