{
  "type": "Feature",
  "properties": {
    "gn:admin1_code":"15.0",
    "gn:asciiname":"San Francisco de los Reyes",
    "gn:country_code":"MX",
    "gn:dem":2651,
    "gn:feature_class":"P",
    "gn:feature_code":"PPL",
    "gn:name":"San Francisco de los Reyes",
    "gn:population":0,
    "gn:timezone":"America/Mexico_City",
    "iso:country":"MX",
    "name:spa_x_preferred":[
        "San Francisco de los Reyes"
    ],
    "wof:name":"San Francisco de los Reyes",
    "wof:placetype":"locality"
},
  "geometry": {"coordinates":[-100.2366,19.7873],"type":"Point"}
}