{
  "type": "Feature",
  "properties": {
    "gn:admin1_code":"6.0",
    "gn:admin2_code":"37.0",
    "gn:asciiname":"Flores",
    "gn:cc2":"MX",
    "gn:country_code":"MX",
    "gn:dem":1337,
    "gn:feature_class":"P",
    "gn:feature_code":"PPL",
    "gn:name":"Flores",
    "gn:population":0,
    "gn:timezone":"America/Ojinaga",
    "iso:country":"MX",
    "name:und_x_variant":[
        "Rancho Flores",
        "Flores"
    ],
    "wof:name":"Flores",
    "wof:placetype":"locality"
},
  "geometry": {"coordinates":[-106.56667,31.71667],"type":"Point"}
}