{
  "type": "Feature",
  "properties": {
    "gn:admin1_code":"19",
    "gn:admin2_code":"25",
    "gn:asciiname":"Primero de Marzo",
    "gn:country_code":"MX",
    "gn:dem":366,
    "gn:feature_class":"P",
    "gn:feature_code":"PPL",
    "gn:name":"Primero de Marzo",
    "gn:population":10,
    "gn:timezone":"America/Monterrey",
    "iso:country":"MX",
    "name:zho_x_preferred":[
        "\u4e09\u6708\u4e00\u65e5\u93ae"
    ],
    "wof:name":"Primero de Marzo",
    "wof:placetype":"locality",
    "wof:population":10
},
  "geometry": {"coordinates":[-100.09917,25.86472],"type":"Point"}
}