{
  "type": "Feature",
  "properties": {
    "gn:admin1_code":"25",
    "gn:admin2_code":"7.0",
    "gn:asciiname":"Charco Verde",
    "gn:country_code":"MX",
    "gn:dem":711,
    "gn:feature_class":"P",
    "gn:feature_code":"PPL",
    "gn:name":"Charco Verde",
    "gn:population":0,
    "gn:timezone":"America/Mazatlan",
    "iso:country":"MX",
    "name:spa_x_preferred":[
        "Charco Verde"
    ],
    "wof:name":"Charco Verde",
    "wof:placetype":"locality"
},
  "geometry": {"coordinates":[-108.26002,26.54417],"type":"Point"}
}