{
  "type": "Feature",
  "properties": {
    "gn:admin1_code":"11",
    "gn:admin2_code":"40.0",
    "gn:asciiname":"La Mesita (La Grana)",
    "gn:country_code":"MX",
    "gn:dem":2073,
    "gn:feature_class":"P",
    "gn:feature_code":"PPL",
    "gn:name":"La Mesita (La Grana)",
    "gn:population":86,
    "gn:timezone":"America/Mexico_City",
    "iso:country":"MX",
    "wof:name":"La Mesita (La Grana)",
    "wof:placetype":"locality",
    "wof:population":86
},
  "geometry": {"coordinates":[-100.14888999999999,20.99083],"type":"Point"}
}