{
  "type": "Feature",
  "properties": {
    "gn:admin1_code":"6",
    "gn:admin2_code":"30",
    "gn:asciiname":"La Suiza",
    "gn:country_code":"MX",
    "gn:dem":1570,
    "gn:feature_class":"P",
    "gn:feature_code":"PPL",
    "gn:name":"La Suiza",
    "gn:population":42,
    "gn:timezone":"America/Chihuahua",
    "iso:country":"MX",
    "wof:name":"La Suiza",
    "wof:placetype":"locality",
    "wof:population":42
},
  "geometry": {"coordinates":[-108.27854000000001,27.37742],"type":"Point"}
}