{
  "type": "Feature",
  "properties": {
    "gn:admin1_code":"5",
    "gn:admin2_code":"59",
    "gn:asciiname":"Italia",
    "gn:country_code":"MX",
    "gn:dem":807,
    "gn:feature_class":"P",
    "gn:feature_code":"PPL",
    "gn:name":"Italia",
    "gn:population":25,
    "gn:timezone":"America/Mexico_City",
    "iso:country":"MX",
    "wof:name":"Italia",
    "wof:placetype":"locality",
    "wof:population":25
},
  "geometry": {"coordinates":[-91.86,16.98583],"type":"Point"}
}