{
  "type": "Feature",
  "properties": {
    "gn:admin1_code":"19",
    "gn:admin2_code":"24",
    "gn:asciiname":"El Puertecito Laguna",
    "gn:country_code":"MX",
    "gn:dem":1367,
    "gn:feature_class":"P",
    "gn:feature_code":"PPL",
    "gn:name":"El Puertecito Laguna",
    "gn:population":30,
    "gn:timezone":"America/Monterrey",
    "iso:country":"MX",
    "wof:name":"El Puertecito Laguna",
    "wof:placetype":"locality",
    "wof:population":30
},
  "geometry": {"coordinates":[-99.78273,23.98703],"type":"Point"}
}