{
  "type": "Feature",
  "properties": {
    "gn:admin1_code":"24",
    "gn:admin2_code":"20.0",
    "gn:asciiname":"San Miguelito",
    "gn:country_code":"MX",
    "gn:dem":1653,
    "gn:feature_class":"P",
    "gn:feature_code":"PPL",
    "gn:name":"San Miguelito",
    "gn:population":0,
    "gn:timezone":"America/Mexico_City",
    "iso:country":"MX",
    "name:ceb_x_preferred":[
        "San Miguelito"
    ],
    "name:deu_x_preferred":[
        "San Miguelito"
    ],
    "name:ita_x_preferred":[
        "San Miguelito"
    ],
    "name:nld_x_preferred":[
        "San Miguelito"
    ],
    "name:pol_x_preferred":[
        "San Miguelito"
    ],
    "name:spa_x_preferred":[
        "San Miguelito"
    ],
    "name:spa_x_variant":[
        "El Rodeo"
    ],
    "name:swe_x_preferred":[
        "San Miguelito"
    ],
    "wof:name":"San Miguelito",
    "wof:placetype":"locality"
},
  "geometry": {"coordinates":[-100.67363,23.63009],"type":"Point"}
}