{
  "type": "Feature",
  "properties": {
    "gn:admin1_code":"14",
    "gn:admin2_code":"90.0",
    "gn:asciiname":"El Tanque",
    "gn:country_code":"MX",
    "gn:dem":1460,
    "gn:feature_class":"P",
    "gn:feature_code":"PPL",
    "gn:name":"El Tanque",
    "gn:population":9,
    "gn:timezone":"America/Mexico_City",
    "iso:country":"MX",
    "wof:name":"El Tanque",
    "wof:placetype":"locality",
    "wof:population":9
},
  "geometry": {"coordinates":[-104.17389,20.21944],"type":"Point"}
}