{
  "type": "Feature",
  "properties": {
    "gn:admin1_code":"21",
    "gn:admin2_code":"43.0",
    "gn:asciiname":"Tahuil",
    "gn:country_code":"MX",
    "gn:dem":305,
    "gn:feature_class":"P",
    "gn:feature_code":"PPL",
    "gn:name":"Tahuil",
    "gn:population":66,
    "gn:timezone":"America/Mexico_City",
    "iso:country":"MX",
    "wof:name":"Tahuil",
    "wof:placetype":"locality",
    "wof:population":66
},
  "geometry": {"coordinates":[-97.46777,20.07445],"type":"Point"}
}