{
  "type": "Feature",
  "properties": {
    "gn:admin1_code":"15.0",
    "gn:admin2_code":"74.0",
    "gn:asciiname":"Purisima Concepcion Mayorazgo",
    "gn:country_code":"MX",
    "gn:dem":2723,
    "gn:feature_class":"P",
    "gn:feature_code":"PPL",
    "gn:name":"Pur\u00edsima Concepci\u00f3n Mayorazgo",
    "gn:population":0,
    "gn:timezone":"America/Mexico_City",
    "iso:country":"MX",
    "name:spa_x_preferred":[
        "Pur\u00edsima Concepci\u00f3n Mayorazgo"
    ],
    "name:und_x_variant":[
        "Mayorazgo",
        "El Mayorazgo"
    ],
    "wof:name":"Purisima Concepcion Mayorazgo",
    "wof:placetype":"locality"
},
  "geometry": {"coordinates":[-100.00211,19.69159],"type":"Point"}
}