{
  "type": "Feature",
  "properties": {
    "gn:admin1_code":"30",
    "gn:admin2_code":"181",
    "gn:asciiname":"La Rosalia",
    "gn:country_code":"MX",
    "gn:dem":16,
    "gn:feature_class":"P",
    "gn:feature_code":"PPL",
    "gn:name":"La Rosal\u00eda",
    "gn:population":14,
    "gn:timezone":"America/Mexico_City",
    "iso:country":"MX",
    "name:und_x_variant":[
        "La Rosal\u00eda"
    ],
    "wof:name":"La Rosalia",
    "wof:placetype":"locality",
    "wof:population":14
},
  "geometry": {"coordinates":[-96.13527999999999,18.82833],"type":"Point"}
}