{
  "type": "Feature",
  "properties": {
    "gn:admin1_code":"20",
    "gn:admin2_code":"406.0",
    "gn:asciiname":"San Jose Lindavista",
    "gn:country_code":"MX",
    "gn:dem":1053,
    "gn:feature_class":"P",
    "gn:feature_code":"PPL",
    "gn:name":"San Jos\u00e9 Lindavista",
    "gn:population":177,
    "gn:timezone":"America/Mexico_City",
    "iso:country":"MX",
    "name:und_x_variant":[
        "San Jos\u00e9 Lindavista"
    ],
    "wof:name":"San Jose Lindavista",
    "wof:placetype":"locality",
    "wof:population":177
},
  "geometry": {"coordinates":[-96.7825,18.28306],"type":"Point"}
}