{
  "type": "Feature",
  "properties": {
    "gn:admin1_code":"32",
    "gn:admin2_code":"48.0",
    "gn:asciiname":"Estancia de los Correa",
    "gn:country_code":"MX",
    "gn:dem":1747,
    "gn:feature_class":"P",
    "gn:feature_code":"PPL",
    "gn:name":"Estancia de los Correa",
    "gn:population":0,
    "gn:timezone":"America/Mexico_City",
    "iso:country":"MX",
    "name:spa_x_preferred":[
        "Estancia de los Correa"
    ],
    "wof:name":"Estancia de los Correa",
    "wof:placetype":"locality"
},
  "geometry": {"coordinates":[-103.26254,21.84384],"type":"Point"}
}