{
  "type": "Feature",
  "properties": {
    "gn:admin1_code":"16",
    "gn:admin2_code":"96.0",
    "gn:asciiname":"Palo Dulce",
    "gn:country_code":"MX",
    "gn:dem":1335,
    "gn:feature_class":"P",
    "gn:feature_code":"PPL",
    "gn:name":"Palo Dulce",
    "gn:population":0,
    "gn:timezone":"America/Mexico_City",
    "iso:country":"MX",
    "name:spa_x_preferred":[
        "Palo Dulce"
    ],
    "wof:name":"Palo Dulce",
    "wof:placetype":"locality"
},
  "geometry": {"coordinates":[-102.56535,18.44178],"type":"Point"}
}