{
  "type": "Feature",
  "properties": {
    "gn:admin1_code":"4.0",
    "gn:asciiname":"El Guayacan",
    "gn:country_code":"MX",
    "gn:dem":268,
    "gn:feature_class":"P",
    "gn:feature_code":"PPL",
    "gn:name":"El Guayac\u00e1n",
    "gn:population":0,
    "gn:timezone":"America/Cancun",
    "iso:country":"MX",
    "name:spa_x_preferred":[
        "El Guayac\u00e1n"
    ],
    "wof:name":"El Guayacan",
    "wof:placetype":"locality"
},
  "geometry": {"coordinates":[-89.38114,18.06765],"type":"Point"}
}