{
  "type": "Feature",
  "properties": {
    "gn:admin1_code":"12",
    "gn:admin2_code":"30",
    "gn:asciiname":"Colonia la Libertad",
    "gn:country_code":"MX",
    "gn:dem":34,
    "gn:feature_class":"P",
    "gn:feature_code":"PPL",
    "gn:name":"Colonia la Libertad",
    "gn:population":35,
    "gn:timezone":"America/Mexico_City",
    "iso:country":"MX",
    "wof:name":"Colonia la Libertad",
    "wof:placetype":"locality",
    "wof:population":35
},
  "geometry": {"coordinates":[-99.11172999999999,16.70834],"type":"Point"}
}