{
  "type": "Feature",
  "properties": {
    "gn:admin1_code":"6",
    "gn:admin2_code":"49.0",
    "gn:asciiname":"Paraje La Tinaja",
    "gn:country_code":"MX",
    "gn:dem":2118,
    "gn:feature_class":"P",
    "gn:feature_code":"PPL",
    "gn:name":"Paraje La Tinaja",
    "gn:population":0,
    "gn:timezone":"America/Chihuahua",
    "iso:country":"MX",
    "name:spa_x_preferred":[
        "Paraje La Tinaja"
    ],
    "wof:name":"Paraje La Tinaja",
    "wof:placetype":"locality"
},
  "geometry": {"coordinates":[-106.76682,27.61262],"type":"Point"}
}