{
  "type": "Feature",
  "properties": {
    "gn:admin1_code":"14",
    "gn:admin2_code":"104.0",
    "gn:asciiname":"Mesa de San Jose",
    "gn:country_code":"MX",
    "gn:dem":1954,
    "gn:feature_class":"P",
    "gn:feature_code":"PPL",
    "gn:name":"Mesa de San Jos\u00e9",
    "gn:population":0,
    "gn:timezone":"America/Mexico_City",
    "iso:country":"MX",
    "name:spa_x_preferred":[
        "Mesa de San Jos\u00e9"
    ],
    "name:und_x_variant":[
        "Mesa de Ure\u00f1a"
    ],
    "wof:name":"Mesa de San Jose",
    "wof:placetype":"locality"
},
  "geometry": {"coordinates":[-103.42402,21.91174],"type":"Point"}
}