{
  "type": "Feature",
  "properties": {
    "gn:admin1_code":"20.0",
    "gn:asciiname":"Tepecatempa",
    "gn:country_code":"MX",
    "gn:dem":1634,
    "gn:feature_class":"P",
    "gn:feature_code":"PPL",
    "gn:name":"Tepecatempa",
    "gn:population":0,
    "gn:timezone":"America/Mexico_City",
    "iso:country":"MX",
    "name:spa_x_preferred":[
        "Tepecatempa"
    ],
    "wof:name":"Tepecatempa",
    "wof:placetype":"locality"
},
  "geometry": {"coordinates":[-96.96141,18.17964],"type":"Point"}
}