{
  "type": "Feature",
  "properties": {
    "gn:admin1_code":"14",
    "gn:admin2_code":"87.0",
    "gn:asciiname":"Corales",
    "gn:country_code":"MX",
    "gn:dem":2049,
    "gn:feature_class":"P",
    "gn:feature_code":"PPL",
    "gn:name":"Corales",
    "gn:population":5,
    "gn:timezone":"America/Mexico_City",
    "iso:country":"MX",
    "wof:name":"Corales",
    "wof:placetype":"locality",
    "wof:population":5
},
  "geometry": {"coordinates":[-103.14861000000001,19.20667000000001],"type":"Point"}
}