{
  "type": "Feature",
  "properties": {
    "gn:admin1_code":"6",
    "gn:admin2_code":"17.0",
    "gn:asciiname":"Granja Hogar Casa de la Esperanza",
    "gn:country_code":"MX",
    "gn:dem":2005,
    "gn:feature_class":"P",
    "gn:feature_code":"PPL",
    "gn:name":"Granja Hogar Casa de la Esperanza",
    "gn:population":61,
    "gn:timezone":"America/Chihuahua",
    "iso:country":"MX",
    "wof:name":"Granja Hogar Casa de la Esperanza",
    "wof:placetype":"locality",
    "wof:population":61
},
  "geometry": {"coordinates":[-106.73888999999998,28.46111],"type":"Point"}
}