{
  "type": "Feature",
  "properties": {
    "gn:admin1_code":"17",
    "gn:admin2_code":"20.0",
    "gn:asciiname":"Acolapan",
    "gn:country_code":"MX",
    "gn:dem":1403,
    "gn:feature_class":"P",
    "gn:feature_code":"PPL",
    "gn:name":"Acolapan",
    "gn:population":5,
    "gn:timezone":"America/Mexico_City",
    "iso:country":"MX",
    "wof:name":"Acolapan",
    "wof:placetype":"locality",
    "wof:population":5
},
  "geometry": {"coordinates":[-99.13028,18.90028],"type":"Point"}
}