{
  "type": "Feature",
  "properties": {
    "gn:admin1_code":"14",
    "gn:admin2_code":"86.0",
    "gn:asciiname":"Loma Alta",
    "gn:country_code":"MX",
    "gn:dem":2075,
    "gn:feature_class":"P",
    "gn:feature_code":"PPL",
    "gn:name":"Loma Alta",
    "gn:population":457,
    "gn:timezone":"America/Mexico_City",
    "iso:country":"MX",
    "wof:name":"Loma Alta",
    "wof:placetype":"locality",
    "wof:population":457
},
  "geometry": {"coordinates":[-103.76389,19.9375],"type":"Point"}
}