{
  "type": "Feature",
  "properties": {
    "gn:admin1_code":"20",
    "gn:admin2_code":"105",
    "gn:asciiname":"Cocoyo",
    "gn:country_code":"MX",
    "gn:dem":2235,
    "gn:feature_class":"P",
    "gn:feature_code":"PPL",
    "gn:name":"Cocoyo",
    "gn:population":43,
    "gn:timezone":"America/Mexico_City",
    "iso:country":"MX",
    "wof:name":"Cocoyo",
    "wof:placetype":"locality",
    "wof:population":43
},
  "geometry": {"coordinates":[-97.715,17.53139],"type":"Point"}
}