{
  "type": "Feature",
  "properties": {
    "gn:admin1_code":"6",
    "gn:admin2_code":"48.0",
    "gn:asciiname":"Rancho Jacobo Newfeld",
    "gn:country_code":"MX",
    "gn:dem":1909,
    "gn:feature_class":"P",
    "gn:feature_code":"PPL",
    "gn:name":"Rancho Jacobo Newfeld",
    "gn:population":4,
    "gn:timezone":"America/Chihuahua",
    "iso:country":"MX",
    "wof:name":"Rancho Jacobo Newfeld",
    "wof:placetype":"locality",
    "wof:population":4
},
  "geometry": {"coordinates":[-107.52249999999999,29.02315],"type":"Point"}
}