{
  "type": "Feature",
  "properties": {
    "gn:admin1_code":"5",
    "gn:admin2_code":"61.0",
    "gn:asciiname":"Lindavista",
    "gn:country_code":"MX",
    "gn:dem":680,
    "gn:feature_class":"P",
    "gn:feature_code":"PPL",
    "gn:name":"Lindavista",
    "gn:population":8,
    "gn:timezone":"America/Mexico_City",
    "iso:country":"MX",
    "name:fra_x_preferred":[
        "Lindavista"
    ],
    "name:nor_x_preferred":[
        "Lindavista"
    ],
    "name:spa_x_preferred":[
        "Lindavista"
    ],
    "wof:name":"Lindavista",
    "wof:placetype":"locality",
    "wof:population":8
},
  "geometry": {"coordinates":[-93.45222,16.94917],"type":"Point"}
}