{
  "type": "Feature",
  "properties": {
    "gn:admin1_code":"30.0",
    "gn:admin2_code":"161.0",
    "gn:asciiname":"El Bejin",
    "gn:country_code":"MX",
    "gn:dem":105,
    "gn:feature_class":"P",
    "gn:feature_code":"PPL",
    "gn:name":"El Bej\u00edn",
    "gn:population":4,
    "gn:timezone":"America/Mexico_City",
    "iso:country":"MX",
    "name:spa_x_preferred":[
        "El Bej\u00edn"
    ],
    "wof:name":"El Bejin",
    "wof:placetype":"locality",
    "wof:population":4
},
  "geometry": {"coordinates":[-98.46611,21.53528],"type":"Point"}
}