{
  "type": "Feature",
  "properties": {
    "gn:admin1_code":"30",
    "gn:admin2_code":"121.0",
    "gn:asciiname":"Taninul",
    "gn:country_code":"MX",
    "gn:dem":54,
    "gn:feature_class":"P",
    "gn:feature_code":"PPL",
    "gn:name":"Taninul",
    "gn:population":0,
    "gn:timezone":"America/Mexico_City",
    "iso:country":"MX",
    "name:spa_x_preferred":[
        "Taninul"
    ],
    "name:spa_x_variant":[
        "Tanimul"
    ],
    "wof:name":"Taninul",
    "wof:placetype":"locality"
},
  "geometry": {"coordinates":[-97.87035,21.52153],"type":"Point"}
}