{
  "type": "Feature",
  "properties": {
    "gn:admin1_code":"30.0",
    "gn:admin2_code":"155.0",
    "gn:asciiname":"Cornizuelos",
    "gn:country_code":"MX",
    "gn:dem":120,
    "gn:feature_class":"P",
    "gn:feature_code":"PPL",
    "gn:name":"Cornizuelos",
    "gn:population":305,
    "gn:timezone":"America/Mexico_City",
    "iso:country":"MX",
    "name:spa_x_preferred":[
        "Cornizuelos"
    ],
    "wof:name":"Cornizuelos",
    "wof:placetype":"locality",
    "wof:population":305
},
  "geometry": {"coordinates":[-98.20471999999999,21.45111],"type":"Point"}
}