{
  "type": "Feature",
  "properties": {
    "gn:admin1_code":"24.0",
    "gn:admin2_code":"16.0",
    "gn:asciiname":"Los Amigos",
    "gn:country_code":"MX",
    "gn:dem":59,
    "gn:feature_class":"P",
    "gn:feature_code":"PPL",
    "gn:name":"Los Amigos",
    "gn:population":0,
    "gn:timezone":"America/Mexico_City",
    "iso:country":"MX",
    "name:ita_x_preferred":[
        "Los amigos"
    ],
    "name:spa_x_preferred":[
        "Los Amigos"
    ],
    "name:srp_x_preferred":[
        "\u041b\u043e\u0441 \u0410\u043c\u0438\u0433\u043e\u0441"
    ],
    "wof:name":"Los Amigos",
    "wof:placetype":"locality"
},
  "geometry": {"coordinates":[-98.58365999999999,22.2374],"type":"Point"}
}