{
  "type": "Feature",
  "properties": {
    "gn:admin1_code":"6",
    "gn:admin2_code":"7.0",
    "gn:asciiname":"Cerro Blanco",
    "gn:country_code":"MX",
    "gn:dem":2194,
    "gn:feature_class":"P",
    "gn:feature_code":"PPL",
    "gn:name":"Cerro Blanco",
    "gn:population":4,
    "gn:timezone":"America/Chihuahua",
    "iso:country":"MX",
    "wof:name":"Cerro Blanco",
    "wof:placetype":"locality",
    "wof:population":4
},
  "geometry": {"coordinates":[-106.81146,26.65234],"type":"Point"}
}