{
  "type": "Feature",
  "properties": {
    "gn:admin1_code":"5",
    "gn:admin2_code":"117.0",
    "gn:asciiname":"Vista Alegre",
    "gn:country_code":"MX",
    "gn:dem":1270,
    "gn:feature_class":"P",
    "gn:feature_code":"PPL",
    "gn:name":"Vista Alegre",
    "gn:population":152,
    "gn:timezone":"America/Mexico_City",
    "iso:country":"MX",
    "wof:name":"Vista Alegre",
    "wof:placetype":"locality",
    "wof:population":152
},
  "geometry": {"coordinates":[-92.67944,15.65639],"type":"Point"}
}