{
  "type": "Feature",
  "properties": {
    "gn:admin1_code":"30",
    "gn:admin2_code":"202.0",
    "gn:asciiname":"El Progreso",
    "gn:country_code":"MX",
    "gn:dem":681,
    "gn:feature_class":"P",
    "gn:feature_code":"PPL",
    "gn:name":"El Progreso",
    "gn:population":162,
    "gn:timezone":"America/Mexico_City",
    "iso:country":"MX",
    "wof:name":"El Progreso",
    "wof:placetype":"locality",
    "wof:population":162
},
  "geometry": {"coordinates":[-98.23305999999999,20.75722],"type":"Point"}
}