{
  "type": "Feature",
  "properties": {
    "gn:admin1_code":"3",
    "gn:admin2_code":"2.0",
    "gn:asciiname":"La Playa",
    "gn:country_code":"MX",
    "gn:dem":-9999,
    "gn:feature_class":"P",
    "gn:feature_code":"PPL",
    "gn:name":"La Playa",
    "gn:population":0,
    "gn:timezone":"America/Mazatlan",
    "iso:country":"MX",
    "name:ceb_x_preferred":[
        "La Playa"
    ],
    "name:fra_x_preferred":[
        "La Playa"
    ],
    "name:nld_x_preferred":[
        "La Playa"
    ],
    "name:spa_x_preferred":[
        "La Playa"
    ],
    "name:swe_x_preferred":[
        "La Playa"
    ],
    "wof:name":"La Playa",
    "wof:placetype":"locality"
},
  "geometry": {"coordinates":[-113.18333,26.96667],"type":"Point"}
}