{
  "type": "Feature",
  "properties": {
    "gn:admin1_code":"31",
    "gn:admin2_code":"41.0",
    "gn:asciiname":"Teuitz",
    "gn:country_code":"MX",
    "gn:dem":13,
    "gn:feature_class":"P",
    "gn:feature_code":"PPL",
    "gn:name":"Teuitz",
    "gn:population":0,
    "gn:timezone":"America/Merida",
    "iso:country":"MX",
    "wof:name":"Teuitz",
    "wof:placetype":"locality"
},
  "geometry": {"coordinates":[-89.51666999999998,20.88333],"type":"Point"}
}