{
  "type": "Feature",
  "properties": {
    "gn:admin1_code":"7.0",
    "gn:admin2_code":"14.0",
    "gn:asciiname":"La Pila Blanca",
    "gn:country_code":"MX",
    "gn:dem":399,
    "gn:feature_class":"P",
    "gn:feature_code":"PPL",
    "gn:name":"La Pila Blanca",
    "gn:population":0,
    "gn:timezone":"America/Monterrey",
    "iso:country":"MX",
    "name:spa_x_preferred":[
        "La Pila Blanca"
    ],
    "wof:name":"La Pila Blanca",
    "wof:placetype":"locality"
},
  "geometry": {"coordinates":[-100.99036,28.86587],"type":"Point"}
}