{
  "type": "Feature",
  "properties": {
    "gn:admin1_code":"15.0",
    "gn:admin2_code":"124.0",
    "gn:asciiname":"El Deposito",
    "gn:country_code":"MX",
    "gn:dem":2866,
    "gn:feature_class":"P",
    "gn:feature_code":"PPL",
    "gn:name":"El Deposito",
    "gn:population":0,
    "gn:timezone":"America/Mexico_City",
    "iso:country":"MX",
    "name:spa_x_preferred":[
        "El Deposito"
    ],
    "name:und_x_variant":[
        "Ramej\u00e9",
        "El Dep\u00f3sito"
    ],
    "wof:name":"El Deposito",
    "wof:placetype":"locality"
},
  "geometry": {"coordinates":[-100.1434,19.51658],"type":"Point"}
}