{
  "type": "Feature",
  "properties": {
    "gn:admin1_code":"16",
    "gn:admin2_code":"13.0",
    "gn:asciiname":"Piedra del Pato",
    "gn:country_code":"MX",
    "gn:dem":756,
    "gn:feature_class":"P",
    "gn:feature_code":"PPL",
    "gn:name":"Piedra del Pato",
    "gn:population":0,
    "gn:timezone":"America/Mexico_City",
    "iso:country":"MX",
    "name:spa_x_preferred":[
        "Piedra del Pato"
    ],
    "wof:name":"Piedra del Pato",
    "wof:placetype":"locality"
},
  "geometry": {"coordinates":[-101.08378999999999,19.15483],"type":"Point"}
}