{
  "type": "Feature",
  "properties": {
    "gn:admin1_code":"12.0",
    "gn:admin2_code":"16.0",
    "gn:asciiname":"Cana Hedionda",
    "gn:country_code":"MX",
    "gn:dem":220,
    "gn:feature_class":"P",
    "gn:feature_code":"PPL",
    "gn:name":"Ca\u00f1a Hedionda",
    "gn:population":0,
    "gn:timezone":"America/Mexico_City",
    "iso:country":"MX",
    "wof:name":"Cana Hedionda",
    "wof:placetype":"locality"
},
  "geometry": {"coordinates":[-101.83333,18.46667],"type":"Point"}
}