{
  "type": "Feature",
  "properties": {
    "gn:admin1_code":"11",
    "gn:admin2_code":"5",
    "gn:asciiname":"Jesus Hiraldo Gallegos",
    "gn:country_code":"MX",
    "gn:dem":1785,
    "gn:feature_class":"P",
    "gn:feature_code":"PPL",
    "gn:name":"Jes\u00fas Hiraldo Gallegos",
    "gn:population":36,
    "gn:timezone":"America/Mexico_City",
    "iso:country":"MX",
    "name:und_x_variant":[
        "Jes\u00fas Hiraldo Gallegos"
    ],
    "wof:name":"Jesus Hiraldo Gallegos",
    "wof:placetype":"locality",
    "wof:population":36
},
  "geometry": {"coordinates":[-100.59166999999999,20.55139],"type":"Point"}
}