{
  "type": "Feature",
  "properties": {
    "gn:admin1_code":"26.0",
    "gn:admin2_code":"42.0",
    "gn:asciiname":"Ejido Plano Oriente",
    "gn:country_code":"MX",
    "gn:dem":17,
    "gn:feature_class":"P",
    "gn:feature_code":"PPL",
    "gn:name":"Ejido Plano Oriente",
    "gn:population":0,
    "gn:timezone":"America/Hermosillo",
    "iso:country":"MX",
    "name:spa_x_preferred":[
        "Ejido Plano Oriente"
    ],
    "wof:name":"Ejido Plano Oriente",
    "wof:placetype":"locality"
},
  "geometry": {"coordinates":[-109.50903999999998,26.84996],"type":"Point"}
}