{
  "type": "Feature",
  "properties": {
    "gn:admin1_code":"22.0",
    "gn:admin2_code":"2.0",
    "gn:asciiname":"Las Joyas",
    "gn:country_code":"MX",
    "gn:dem":2430,
    "gn:feature_class":"P",
    "gn:feature_code":"PPL",
    "gn:name":"Las Joyas",
    "gn:population":0,
    "gn:timezone":"America/Mexico_City",
    "iso:country":"MX",
    "name:spa_x_preferred":[
        "Las Joyas"
    ],
    "wof:name":"Las Joyas",
    "wof:placetype":"locality"
},
  "geometry": {"coordinates":[-99.64519,21.1015],"type":"Point"}
}