{
  "type": "Feature",
  "properties": {
    "gn:admin1_code":"30",
    "gn:admin2_code":"54",
    "gn:asciiname":"Carolino Anaya",
    "gn:country_code":"MX",
    "gn:dem":50,
    "gn:feature_class":"P",
    "gn:feature_code":"PPL",
    "gn:name":"Carolino Anaya",
    "gn:population":40,
    "gn:timezone":"America/Mexico_City",
    "iso:country":"MX",
    "wof:name":"Carolino Anaya",
    "wof:placetype":"locality",
    "wof:population":40
},
  "geometry": {"coordinates":[-95.79416999999999,18.15611],"type":"Point"}
}