{
  "type": "Feature",
  "properties": {
    "gn:admin1_code":"25",
    "gn:admin2_code":"14.0",
    "gn:asciiname":"Los Pinos de Jonatan (Los Pinos)",
    "gn:country_code":"MX",
    "gn:dem":51,
    "gn:feature_class":"P",
    "gn:feature_code":"PPL",
    "gn:name":"Los Pinos de Jonat\u00e1n (Los Pinos)",
    "gn:population":5,
    "gn:timezone":"America/Mazatlan",
    "iso:country":"MX",
    "name:und_x_variant":[
        "Los Pinos de Jonat\u00e1n (Los Pinos)"
    ],
    "wof:name":"Los Pinos de Jonatan (Los Pinos)",
    "wof:placetype":"locality",
    "wof:population":5
},
  "geometry": {"coordinates":[-106.00094,23.06932],"type":"Point"}
}