{
  "type": "Feature",
  "properties": {
    "gn:admin1_code":"21",
    "gn:admin2_code":"164.0",
    "gn:asciiname":"Los Carreones",
    "gn:country_code":"MX",
    "gn:dem":2247,
    "gn:feature_class":"P",
    "gn:feature_code":"PPL",
    "gn:name":"Los Carreones",
    "gn:population":84,
    "gn:timezone":"America/Mexico_City",
    "iso:country":"MX",
    "wof:name":"Los Carreones",
    "wof:placetype":"locality",
    "wof:population":84
},
  "geometry": {"coordinates":[-97.8419,19.00736],"type":"Point"}
}