{
  "type": "Feature",
  "properties": {
    "gn:admin1_code":"22",
    "gn:admin2_code":"9.0",
    "gn:asciiname":"El Invernadero",
    "gn:country_code":"MX",
    "gn:dem":753,
    "gn:feature_class":"P",
    "gn:feature_code":"PPL",
    "gn:name":"El Invernadero",
    "gn:population":6,
    "gn:timezone":"America/Mexico_City",
    "iso:country":"MX",
    "wof:name":"El Invernadero",
    "wof:placetype":"locality",
    "wof:population":6
},
  "geometry": {"coordinates":[-99.47667,21.22778],"type":"Point"}
}