{
  "type": "Feature",
  "properties": {
    "gn:admin1_code":"21",
    "gn:asciiname":"Xololoyan",
    "gn:country_code":"MX",
    "gn:dem":2393,
    "gn:feature_class":"P",
    "gn:feature_code":"PPL",
    "gn:name":"Xolol\u00f3yan",
    "gn:population":0,
    "gn:timezone":"America/Mexico_City",
    "iso:country":"MX",
    "name:spa_x_preferred":[
        "Xolol\u00f3yan"
    ],
    "name:und_x_variant":[
        "Chololoyan"
    ],
    "wof:name":"Xololoyan",
    "wof:placetype":"locality"
},
  "geometry": {"coordinates":[-97.19015,19.3689],"type":"Point"}
}