{
  "type": "Feature",
  "properties": {
    "gn:admin1_code":"20.0",
    "gn:admin2_code":"401.0",
    "gn:asciiname":"El Banco",
    "gn:country_code":"MX",
    "gn:dem":37,
    "gn:feature_class":"P",
    "gn:feature_code":"PPL",
    "gn:name":"El Banco",
    "gn:population":0,
    "gn:timezone":"America/Mexico_City",
    "iso:country":"MX",
    "name:spa_x_preferred":[
        "El Banco"
    ],
    "wof:name":"El Banco",
    "wof:placetype":"locality"
},
  "geometry": {"coordinates":[-96.98276,15.88506],"type":"Point"}
}