{
  "type": "Feature",
  "properties": {
    "gn:admin1_code":"6",
    "gn:admin2_code":"35.0",
    "gn:asciiname":"Lazaro Cardenas",
    "gn:country_code":"MX",
    "gn:dem":1591,
    "gn:feature_class":"P",
    "gn:feature_code":"PPL",
    "gn:name":"L\u00e1zaro C\u00e1rdenas",
    "gn:population":0,
    "gn:timezone":"America/Chihuahua",
    "iso:country":"MX",
    "name:spa_x_preferred":[
        "L\u00e1zaro C\u00e1rdenas"
    ],
    "name:und_x_variant":[
        "Ojo Fr\u00edo",
        "El Ojo Fr\u00edo"
    ],
    "wof:name":"Lazaro Cardenas",
    "wof:placetype":"locality"
},
  "geometry": {"coordinates":[-108.46632,30.5599],"type":"Point"}
}