{
  "type": "Feature",
  "properties": {
    "gn:admin1_code":"16.0",
    "gn:admin2_code":"34.0",
    "gn:asciiname":"Puente de Tierra",
    "gn:country_code":"MX",
    "gn:dem":2499,
    "gn:feature_class":"P",
    "gn:feature_code":"PPL",
    "gn:name":"Puente de Tierra",
    "gn:population":623,
    "gn:timezone":"America/Mexico_City",
    "iso:country":"MX",
    "name:spa_x_preferred":[
        "Puente de Tierra"
    ],
    "wof:name":"Puente de Tierra",
    "wof:placetype":"locality",
    "wof:population":623
},
  "geometry": {"coordinates":[-100.71064,19.50566],"type":"Point"}
}