{
  "type": "Feature",
  "properties": {
    "gn:admin1_code":"5",
    "gn:admin2_code":"59.0",
    "gn:asciiname":"Nueva Providencia",
    "gn:country_code":"MX",
    "gn:dem":852,
    "gn:feature_class":"P",
    "gn:feature_code":"PPL",
    "gn:name":"Nueva Providencia",
    "gn:population":263,
    "gn:timezone":"America/Mexico_City",
    "iso:country":"MX",
    "name:ind_x_preferred":[
        "Nueva Providencia"
    ],
    "name:ita_x_preferred":[
        "Nueva Providencia"
    ],
    "name:spa_x_preferred":[
        "Nueva Providencia"
    ],
    "name:zho_x_preferred":[
        "\u65b0\u666e\u7f85\u7dad\u767b\u897f\u4e9e"
    ],
    "wof:name":"Nueva Providencia",
    "wof:placetype":"locality",
    "wof:population":263
},
  "geometry": {"coordinates":[-91.78417,17.03778],"type":"Point"}
}