{
  "type": "Feature",
  "properties": {
    "gn:admin1_code":"5",
    "gn:admin2_code":"59.0",
    "gn:asciiname":"Nueva Providencia",
    "gn:country_code":"MX",
    "gn:dem":852,
    "gn:feature_class":"P",
    "gn:feature_code":"PPL",
    "gn:name":"Nueva Providencia",
    "gn:population":263,
    "gn:timezone":"America/Mexico_City",
    "iso:country":"MX",
    "wof:name":"Nueva Providencia",
    "wof:placetype":"locality",
    "wof:population":263
},
  "geometry": {"coordinates":[-91.78417,17.03778],"type":"Point"}
}