{
  "type": "Feature",
  "properties": {
    "gn:admin1_code":"4",
    "gn:admin2_code":"1.0",
    "gn:asciiname":"Pucnachen",
    "gn:country_code":"MX",
    "gn:dem":5,
    "gn:feature_class":"P",
    "gn:feature_code":"PPL",
    "gn:name":"Pucnach\u00e9n",
    "gn:population":0,
    "gn:timezone":"America/Merida",
    "iso:country":"MX",
    "name:spa_x_preferred":[
        "Pucnach\u00e9n"
    ],
    "wof:name":"Pucnachen",
    "wof:placetype":"locality"
},
  "geometry": {"coordinates":[-90.21811,20.36485],"type":"Point"}
}