{
  "type": "Feature",
  "properties": {
    "gn:admin1_code":"13",
    "gn:admin2_code":"32.0",
    "gn:asciiname":"Nuevo Rosario",
    "gn:country_code":"MX",
    "gn:dem":254,
    "gn:feature_class":"P",
    "gn:feature_code":"PPL",
    "gn:name":"Nuevo Rosario",
    "gn:population":5,
    "gn:timezone":"America/Mexico_City",
    "iso:country":"MX",
    "wof:name":"Nuevo Rosario",
    "wof:placetype":"locality",
    "wof:population":5
},
  "geometry": {"coordinates":[-98.54509,21.13545],"type":"Point"}
}