{
  "type": "Feature",
  "properties": {
    "gn:admin1_code":"3",
    "gn:admin2_code":"1.0",
    "gn:asciiname":"Salvatierra Lote 1",
    "gn:country_code":"MX",
    "gn:dem":46,
    "gn:feature_class":"P",
    "gn:feature_code":"PPL",
    "gn:name":"Salvatierra Lote 1",
    "gn:population":5,
    "gn:timezone":"America/Mazatlan",
    "iso:country":"MX",
    "wof:name":"Salvatierra Lote 1",
    "wof:placetype":"locality",
    "wof:population":5
},
  "geometry": {"coordinates":[-111.71048,25.14412],"type":"Point"}
}