{
  "type": "Feature",
  "properties": {
    "gn:admin1_code":"7",
    "gn:admin2_code":"30.0",
    "gn:asciiname":"Blanco Estela",
    "gn:country_code":"MX",
    "gn:dem":1909,
    "gn:feature_class":"P",
    "gn:feature_code":"PPL",
    "gn:name":"Blanco Estela",
    "gn:population":0,
    "gn:timezone":"America/Monterrey",
    "iso:country":"MX",
    "name:spa_x_preferred":[
        "Blanco Estela"
    ],
    "wof:name":"Blanco Estela",
    "wof:placetype":"locality"
},
  "geometry": {"coordinates":[-101.1052,25.24976],"type":"Point"}
}