{
  "type": "Feature",
  "properties": {
    "gn:admin1_code":"11",
    "gn:admin2_code":"14.0",
    "gn:asciiname":"Labor de Gallardo",
    "gn:country_code":"MX",
    "gn:dem":1930,
    "gn:feature_class":"P",
    "gn:feature_code":"PPL",
    "gn:name":"Labor de Gallardo",
    "gn:population":5,
    "gn:timezone":"America/Mexico_City",
    "iso:country":"MX",
    "wof:name":"Labor de Gallardo",
    "wof:placetype":"locality",
    "wof:population":5
},
  "geometry": {"coordinates":[-100.94944,21.255],"type":"Point"}
}