{
  "type": "Feature",
  "properties": {
    "gn:admin1_code":"20",
    "gn:admin2_code":"434",
    "gn:asciiname":"Vista Hermosa (Xonotla)",
    "gn:country_code":"MX",
    "gn:dem":1829,
    "gn:feature_class":"P",
    "gn:feature_code":"PPL",
    "gn:name":"Vista Hermosa (Xonotla)",
    "gn:population":49,
    "gn:timezone":"America/Mexico_City",
    "iso:country":"MX",
    "wof:name":"Vista Hermosa (Xonotla)",
    "wof:placetype":"locality",
    "wof:population":49
},
  "geometry": {"coordinates":[-96.97056000000001,18.18639],"type":"Point"}
}