{
  "type": "Feature",
  "properties": {
    "gn:admin1_code":"14",
    "gn:admin2_code":"76",
    "gn:asciiname":"Los Pilarcitos (Chicalzate)",
    "gn:country_code":"MX",
    "gn:dem":826,
    "gn:feature_class":"P",
    "gn:feature_code":"PPL",
    "gn:name":"Los Pilarcitos (Chicalzate)",
    "gn:population":10,
    "gn:timezone":"America/Mexico_City",
    "iso:country":"MX",
    "wof:name":"Los Pilarcitos (Chicalzate)",
    "wof:placetype":"locality",
    "wof:population":10
},
  "geometry": {"coordinates":[-103.80444,21.60278],"type":"Point"}
}