{
  "type": "Feature",
  "properties": {
    "gn:admin1_code":"21",
    "gn:admin2_code":"180",
    "gn:asciiname":"Atlimatla (Sierra Chica)",
    "gn:country_code":"MX",
    "gn:dem":2479,
    "gn:feature_class":"P",
    "gn:feature_code":"PPL",
    "gn:name":"Atlimatla (Sierra Chica)",
    "gn:population":10,
    "gn:timezone":"America/Mexico_City",
    "iso:country":"MX",
    "wof:name":"Atlimatla (Sierra Chica)",
    "wof:placetype":"locality",
    "wof:population":10
},
  "geometry": {"coordinates":[-98.55062,19.35941],"type":"Point"}
}