{
  "type": "Feature",
  "properties": {
    "gn:admin1_code":"29",
    "gn:admin2_code":"3.0",
    "gn:asciiname":"Villa Quinta Olivares [Centro Vacacional]",
    "gn:country_code":"MX",
    "gn:dem":2485,
    "gn:feature_class":"P",
    "gn:feature_code":"PPL",
    "gn:name":"Villa Quinta Olivares [Centro Vacacional]",
    "gn:population":8,
    "gn:timezone":"America/Mexico_City",
    "iso:country":"MX",
    "wof:name":"Villa Quinta Olivares [Centro Vacacional]",
    "wof:placetype":"locality",
    "wof:population":8
},
  "geometry": {"coordinates":[-98.20589,19.50234],"type":"Point"}
}