{
  "type": "Feature",
  "properties": {
    "gn:admin1_code":"30",
    "gn:admin2_code":"38",
    "gn:asciiname":"Tixtla",
    "gn:country_code":"MX",
    "gn:dem":1377,
    "gn:feature_class":"P",
    "gn:feature_code":"PPL",
    "gn:name":"Tixtla",
    "gn:population":26,
    "gn:timezone":"America/Mexico_City",
    "iso:country":"MX",
    "name:ita_x_preferred":[
        "Tixtla"
    ],
    "name:rus_x_preferred":[
        "\u0422\u0438\u0441\u0442\u043b\u0430-\u0434\u0435-\u0413\u0435\u0440\u0440\u0435\u0440\u043e"
    ],
    "name:sco_x_preferred":[
        "Tixtla"
    ],
    "wof:name":"Tixtla",
    "wof:placetype":"locality",
    "wof:population":26
},
  "geometry": {"coordinates":[-96.97333,19.49778],"type":"Point"}
}