{
  "type": "Feature",
  "properties": {
    "gn:admin1_code":"30",
    "gn:admin2_code":"38",
    "gn:asciiname":"Tixtla",
    "gn:country_code":"MX",
    "gn:dem":1377,
    "gn:feature_class":"P",
    "gn:feature_code":"PPL",
    "gn:name":"Tixtla",
    "gn:population":26,
    "gn:timezone":"America/Mexico_City",
    "iso:country":"MX",
    "wof:name":"Tixtla",
    "wof:placetype":"locality",
    "wof:population":26
},
  "geometry": {"coordinates":[-96.97333,19.49778],"type":"Point"}
}