{
  "type": "Feature",
  "properties": {
    "gn:admin1_code":"6",
    "gn:admin2_code":"46.0",
    "gn:asciiname":"Casa Quemada",
    "gn:country_code":"MX",
    "gn:dem":450,
    "gn:feature_class":"P",
    "gn:feature_code":"PPL",
    "gn:name":"Casa Quemada",
    "gn:population":6,
    "gn:timezone":"America/Chihuahua",
    "iso:country":"MX",
    "wof:name":"Casa Quemada",
    "wof:placetype":"locality",
    "wof:population":6
},
  "geometry": {"coordinates":[-107.77462,26.79244000000001],"type":"Point"}
}