{
  "type": "Feature",
  "properties": {
    "gn:admin1_code":"32",
    "gn:admin2_code":"42.0",
    "gn:asciiname":"Caldo Sordo",
    "gn:country_code":"MX",
    "gn:dem":2373,
    "gn:feature_class":"P",
    "gn:feature_code":"PPL",
    "gn:name":"Caldo Sordo",
    "gn:population":0,
    "gn:timezone":"America/Mexico_City",
    "iso:country":"MX",
    "name:spa_x_preferred":[
        "Caldo Sordo"
    ],
    "name:und_x_variant":[
        "Caldo Gordo"
    ],
    "wof:name":"Caldo Sordo",
    "wof:placetype":"locality"
},
  "geometry": {"coordinates":[-103.63451000000001,23.6624],"type":"Point"}
}