{
  "type": "Feature",
  "properties": {
    "gn:admin1_code":"5.0",
    "gn:asciiname":"El Convidado",
    "gn:country_code":"MX",
    "gn:dem":16,
    "gn:feature_class":"P",
    "gn:feature_code":"PPL",
    "gn:name":"El Convidado",
    "gn:population":0,
    "gn:timezone":"America/Mexico_City",
    "iso:country":"MX",
    "name:spa_x_preferred":[
        "El Convidado"
    ],
    "wof:name":"El Convidado",
    "wof:placetype":"locality"
},
  "geometry": {"coordinates":[-93.53701,15.83602],"type":"Point"}
}