{
  "type": "Feature",
  "properties": {
    "gn:admin1_code":"27",
    "gn:admin2_code":"12.0",
    "gn:asciiname":"Lerdo de Tejada 2da. Seccion",
    "gn:country_code":"MX",
    "gn:dem":20,
    "gn:feature_class":"P",
    "gn:feature_code":"PPL",
    "gn:name":"Lerdo de Tejada 2da. Secci\u00f3n",
    "gn:population":578,
    "gn:timezone":"America/Mexico_City",
    "iso:country":"MX",
    "name:und_x_variant":[
        "Lerdo de Tejada 2da. Secci\u00f3n"
    ],
    "wof:name":"Lerdo de Tejada 2da. Seccion",
    "wof:placetype":"locality",
    "wof:population":578
},
  "geometry": {"coordinates":[-92.64972,17.78528],"type":"Point"}
}