{
  "type": "Feature",
  "properties": {
    "gn:admin1_code":"2",
    "gn:admin2_code":"5.0",
    "gn:asciiname":"Hacienda del Sol",
    "gn:country_code":"MX",
    "gn:dem":167,
    "gn:feature_class":"P",
    "gn:feature_code":"PPL",
    "gn:name":"Hacienda del Sol",
    "gn:population":89,
    "gn:timezone":"America/Tijuana",
    "iso:country":"MX",
    "wof:name":"Hacienda del Sol",
    "wof:placetype":"locality",
    "wof:population":89
},
  "geometry": {"coordinates":[-116.99250000000001,32.285],"type":"Point"}
}