{
  "type": "Feature",
  "properties": {
    "gn:admin1_code":"19",
    "gn:admin2_code":"45.0",
    "gn:asciiname":"Cuatro de Abril",
    "gn:country_code":"MX",
    "gn:dem":457,
    "gn:feature_class":"P",
    "gn:feature_code":"PPL",
    "gn:name":"Cuatro de Abril",
    "gn:population":5,
    "gn:timezone":"America/Monterrey",
    "iso:country":"MX",
    "wof:name":"Cuatro de Abril",
    "wof:placetype":"locality",
    "wof:population":5
},
  "geometry": {"coordinates":[-100.29809,25.93199],"type":"Point"}
}