{
  "type": "Feature",
  "properties": {
    "gn:admin1_code":"30",
    "gn:admin2_code":"149.0",
    "gn:asciiname":"Las Palomas (Rutilo Garcia)",
    "gn:country_code":"MX",
    "gn:dem":845,
    "gn:feature_class":"P",
    "gn:feature_code":"PPL",
    "gn:name":"Las Palomas (Rutilo Garc\u00eda)",
    "gn:population":5,
    "gn:timezone":"America/Mexico_City",
    "iso:country":"MX",
    "name:und_x_variant":[
        "Las Palomas (Rutilo Garc\u00eda)"
    ],
    "wof:name":"Las Palomas (Rutilo Garcia)",
    "wof:placetype":"locality",
    "wof:population":5
},
  "geometry": {"coordinates":[-94.9725,18.3375],"type":"Point"}
}