{
  "type": "Feature",
  "properties": {
    "gn:admin1_code":"25",
    "gn:admin2_code":"12.0",
    "gn:asciiname":"Tepehuaje",
    "gn:country_code":"MX",
    "gn:dem":112,
    "gn:feature_class":"P",
    "gn:feature_code":"PPL",
    "gn:name":"Tepehuaje",
    "gn:population":0,
    "gn:timezone":"America/Mazatlan",
    "iso:country":"MX",
    "name:spa_x_preferred":[
        "Tepehuaje"
    ],
    "wof:name":"Tepehuaje",
    "wof:placetype":"locality"
},
  "geometry": {"coordinates":[-106.18563,23.52995],"type":"Point"}
}