{
  "type": "Feature",
  "properties": {
    "gn:admin1_code":"10",
    "gn:admin2_code":"5.0",
    "gn:asciiname":"Patos",
    "gn:country_code":"MX",
    "gn:dem":2354,
    "gn:feature_class":"P",
    "gn:feature_code":"PPL",
    "gn:name":"Patos",
    "gn:population":0,
    "gn:timezone":"America/Monterrey",
    "iso:country":"MX",
    "name:ara_x_preferred":[
        "\u0628\u0627\u062a\u0648\u0633"
    ],
    "name:bpy_x_preferred":[
        "\u09aa\u09be\u099f\u09cb\u09b8"
    ],
    "name:ceb_x_preferred":[
        "Patos"
    ],
    "name:epo_x_preferred":[
        "Patos"
    ],
    "name:eus_x_preferred":[
        "Patos"
    ],
    "name:fra_x_preferred":[
        "Patos"
    ],
    "name:hye_x_preferred":[
        "\u054a\u0561\u057f\u0578\u0582\u057d"
    ],
    "name:ita_x_preferred":[
        "Patos"
    ],
    "name:kat_x_preferred":[
        "\u10de\u10d0\u10e2\u10e3\u10e1\u10d8"
    ],
    "name:kaz_x_preferred":[
        "\u041f\u0430\u0442\u0443\u0441"
    ],
    "name:lit_x_preferred":[
        "Patosas"
    ],
    "name:mlg_x_preferred":[
        "Patos"
    ],
    "name:nld_x_preferred":[
        "Patos"
    ],
    "name:nor_x_preferred":[
        "Patos"
    ],
    "name:pol_x_preferred":[
        "Patos"
    ],
    "name:por_x_preferred":[
        "Patos"
    ],
    "name:ron_x_preferred":[
        "Patos"
    ],
    "name:rus_x_preferred":[
        "\u041f\u0430\u0442\u0443\u0441"
    ],
    "name:spa_x_preferred":[
        "Patos"
    ],
    "name:swe_x_preferred":[
        "Patos"
    ],
    "name:tat_x_preferred":[
        "\u041f\u0430\u0442\u0443\u0441"
    ],
    "name:vol_x_preferred":[
        "Patos"
    ],
    "name:war_x_preferred":[
        "Patos"
    ],
    "name:zho_x_preferred":[
        "\u5e15\u56fe\u65af"
    ],
    "wof:name":"Patos",
    "wof:placetype":"locality"
},
  "geometry": {"coordinates":[-105.22423000000001,23.9246],"type":"Point"}
}