{
  "type": "Feature",
  "properties": {
    "gn:admin1_code":"10",
    "gn:admin2_code":"5.0",
    "gn:asciiname":"Patos",
    "gn:country_code":"MX",
    "gn:dem":2354,
    "gn:feature_class":"P",
    "gn:feature_code":"PPL",
    "gn:name":"Patos",
    "gn:population":0,
    "gn:timezone":"America/Monterrey",
    "iso:country":"MX",
    "name:spa_x_preferred":[
        "Patos"
    ],
    "wof:name":"Patos",
    "wof:placetype":"locality"
},
  "geometry": {"coordinates":[-105.22423000000001,23.9246],"type":"Point"}
}