{
  "type": "Feature",
  "properties": {
    "gn:admin1_code":"20",
    "gn:admin2_code":"8.0",
    "gn:asciiname":"Ecatepec",
    "gn:country_code":"MX",
    "gn:dem":676,
    "gn:feature_class":"P",
    "gn:feature_code":"PPL",
    "gn:name":"Ecatepec",
    "gn:population":0,
    "gn:timezone":"America/Mexico_City",
    "iso:country":"MX",
    "wof:name":"Ecatepec",
    "wof:placetype":"locality"
},
  "geometry": {"coordinates":[-95.78333000000001,16.25],"type":"Point"}
}