{
  "type": "Feature",
  "properties": {
    "gn:admin1_code":"28",
    "gn:admin2_code":"24.0",
    "gn:asciiname":"Lampacitos",
    "gn:country_code":"MX",
    "gn:dem":103,
    "gn:feature_class":"P",
    "gn:feature_code":"PPL",
    "gn:name":"Lampacitos",
    "gn:population":0,
    "gn:timezone":"America/Monterrey",
    "iso:country":"MX",
    "name:spa_x_preferred":[
        "Lampacitos"
    ],
    "wof:name":"Lampacitos",
    "wof:placetype":"locality"
},
  "geometry": {"coordinates":[-99.17007,26.28863],"type":"Point"}
}