{
  "type": "Feature",
  "properties": {
    "gn:admin1_code":"11",
    "gn:admin2_code":"38.0",
    "gn:asciiname":"Las Penitas",
    "gn:country_code":"MX",
    "gn:dem":1990,
    "gn:feature_class":"P",
    "gn:feature_code":"PPL",
    "gn:name":"Las Pe\u00f1itas",
    "gn:population":5,
    "gn:timezone":"America/Mexico_City",
    "iso:country":"MX",
    "name:und_x_variant":[
        "Las Pe\u00f1itas"
    ],
    "wof:name":"Las Penitas",
    "wof:placetype":"locality",
    "wof:population":5
},
  "geometry": {"coordinates":[-100.54861,20.07056],"type":"Point"}
}