{
  "type": "Feature",
  "properties": {
    "gn:admin1_code":"30",
    "gn:admin2_code":"108.0",
    "gn:asciiname":"Los Reyes",
    "gn:country_code":"MX",
    "gn:dem":36,
    "gn:feature_class":"P",
    "gn:feature_code":"PPL",
    "gn:name":"Los Reyes",
    "gn:population":0,
    "gn:timezone":"America/Mexico_City",
    "iso:country":"MX",
    "name:ceb_x_preferred":[
        "Los Reyes"
    ],
    "name:deu_x_preferred":[
        "Los Reyes"
    ],
    "name:epo_x_preferred":[
        "Los Reyes"
    ],
    "name:nds_x_preferred":[
        "Los Reyes"
    ],
    "name:spa_x_preferred":[
        "Los Reyes"
    ],
    "name:swe_x_preferred":[
        "Los Reyes"
    ],
    "wof:name":"Los Reyes",
    "wof:placetype":"locality"
},
  "geometry": {"coordinates":[-94.2625,17.70388999999999],"type":"Point"}
}