{
  "type": "Feature",
  "properties": {
    "gn:admin1_code":"16",
    "gn:admin2_code":"101",
    "gn:asciiname":"Agua Zarca Dos",
    "gn:country_code":"MX",
    "gn:dem":1329,
    "gn:feature_class":"P",
    "gn:feature_code":"PPL",
    "gn:name":"Agua Zarca Dos",
    "gn:population":30,
    "gn:timezone":"America/Mexico_City",
    "iso:country":"MX",
    "wof:name":"Agua Zarca Dos",
    "wof:placetype":"locality",
    "wof:population":30
},
  "geometry": {"coordinates":[-100.95556000000001,19.36528],"type":"Point"}
}