{
  "type": "Feature",
  "properties": {
    "gn:admin1_code":"18.0",
    "gn:asciiname":"La Guasima Gacha",
    "gn:country_code":"MX",
    "gn:dem":466,
    "gn:feature_class":"P",
    "gn:feature_code":"PPL",
    "gn:name":"La Guasima Gacha",
    "gn:population":0,
    "gn:timezone":"America/Mazatlan",
    "iso:country":"MX",
    "name:spa_x_preferred":[
        "La Guasima Gacha"
    ],
    "wof:name":"La Guasima Gacha",
    "wof:placetype":"locality"
},
  "geometry": {"coordinates":[-104.59892000000001,21.53557],"type":"Point"}
}