{
  "type": "Feature",
  "properties": {
    "gn:admin1_code":"5",
    "gn:admin2_code":"59",
    "gn:asciiname":"San Francisco Uno",
    "gn:country_code":"MX",
    "gn:dem":947,
    "gn:feature_class":"P",
    "gn:feature_code":"PPL",
    "gn:name":"San Francisco Uno",
    "gn:population":43,
    "gn:timezone":"America/Mexico_City",
    "iso:country":"MX",
    "wof:name":"San Francisco Uno",
    "wof:placetype":"locality",
    "wof:population":43
},
  "geometry": {"coordinates":[-91.61861,16.9375],"type":"Point"}
}