{
  "type": "Feature",
  "properties": {
    "gn:admin1_code":"6",
    "gn:admin2_code":"4.0",
    "gn:asciiname":"El Quipurito",
    "gn:country_code":"MX",
    "gn:dem":1931,
    "gn:feature_class":"P",
    "gn:feature_code":"PPL",
    "gn:name":"El Quipurito",
    "gn:population":0,
    "gn:timezone":"America/Chihuahua",
    "iso:country":"MX",
    "name:spa_x_preferred":[
        "El Quipurito"
    ],
    "wof:name":"El Quipurito",
    "wof:placetype":"locality"
},
  "geometry": {"coordinates":[-105.87344,28.62138],"type":"Point"}
}