{
  "type": "Feature",
  "properties": {
    "gn:admin1_code":"5.0",
    "gn:admin2_code":"89.0",
    "gn:asciiname":"California",
    "gn:country_code":"MX",
    "gn:dem":455,
    "gn:feature_class":"P",
    "gn:feature_code":"PPL",
    "gn:name":"California",
    "gn:population":0,
    "gn:timezone":"America/Mexico_City",
    "iso:country":"MX",
    "name:spa_x_preferred":[
        "California"
    ],
    "wof:name":"California",
    "wof:placetype":"locality"
},
  "geometry": {"coordinates":[-92.21449,15.00457],"type":"Point"}
}