{
  "type": "Feature",
  "properties": {
    "gn:admin1_code":"18",
    "gn:admin2_code":"2.0",
    "gn:asciiname":"Las Guasimas",
    "gn:country_code":"MX",
    "gn:dem":1146,
    "gn:feature_class":"P",
    "gn:feature_code":"PPL",
    "gn:name":"Las Gu\u00e1simas",
    "gn:population":134,
    "gn:timezone":"America/Mazatlan",
    "iso:country":"MX",
    "wof:name":"Las Guasimas",
    "wof:placetype":"locality",
    "wof:population":134
},
  "geometry": {"coordinates":[-104.60760000000001,20.99826],"type":"Point"}
}