{
  "type": "Feature",
  "properties": {
    "gn:admin1_code":"19",
    "gn:admin2_code":"5.0",
    "gn:asciiname":"Perfecto Lopez",
    "gn:country_code":"MX",
    "gn:dem":216,
    "gn:feature_class":"P",
    "gn:feature_code":"PPL",
    "gn:name":"Perfecto L\u00f3pez",
    "gn:population":5,
    "gn:timezone":"America/Matamoros",
    "iso:country":"MX",
    "name:und_x_variant":[
        "Perfecto L\u00f3pez"
    ],
    "wof:name":"Perfecto Lopez",
    "wof:placetype":"locality",
    "wof:population":5
},
  "geometry": {"coordinates":[-100.31256,27.30224],"type":"Point"}
}