{
  "type": "Feature",
  "properties": {
    "gn:admin1_code":"30",
    "gn:admin2_code":"207.0",
    "gn:asciiname":"Santa Sofia",
    "gn:country_code":"MX",
    "gn:dem":43,
    "gn:feature_class":"P",
    "gn:feature_code":"PPL",
    "gn:name":"Santa Sof\u00eda",
    "gn:population":5,
    "gn:timezone":"America/Mexico_City",
    "iso:country":"MX",
    "name:und_x_variant":[
        "Santa Sof\u00eda"
    ],
    "wof:name":"Santa Sofia",
    "wof:placetype":"locality",
    "wof:population":5
},
  "geometry": {"coordinates":[-96.14833,18.23278],"type":"Point"}
}