{
  "type": "Feature",
  "properties": {
    "gn:admin1_code":"15",
    "gn:admin2_code":"109.0",
    "gn:asciiname":"San Pablo de las Salinas",
    "gn:country_code":"MX",
    "gn:dem":2248,
    "gn:feature_class":"P",
    "gn:feature_code":"PPL",
    "gn:name":"San Pablo de las Salinas",
    "gn:population":173557,
    "gn:timezone":"America/Mexico_City",
    "iso:country":"MX",
    "name:bul_x_preferred":[
        "\u0421\u0430\u043d \u041f\u0430\u0431\u043b\u043e \u0434\u0435 \u043b\u0430\u0441 \u0421\u0430\u043b\u0438\u043d\u0430\u0441"
    ],
    "name:srp_x_preferred":[
        "\u0421\u0430\u043d \u041f\u0430\u0431\u043b\u043e \u0434\u0435 \u043b\u0430\u0441 \u0421\u0430\u043b\u0438\u043d\u0430\u0441"
    ],
    "name:und_x_variant":[
        "Salinas",
        "San Pablo",
        "San Pablo de Salinas",
        "San Pablo de las Salinas"
    ],
    "wof:name":"San Pablo de las Salinas",
    "wof:placetype":"locality",
    "wof:population":173557
},
  "geometry": {"coordinates":[-99.09477,19.66658],"type":"Point"}
}