{
  "type": "Feature",
  "properties": {
    "gn:admin1_code":"28",
    "gn:admin2_code":"28.0",
    "gn:asciiname":"Ampliacion de la Reforma",
    "gn:country_code":"MX",
    "gn:dem":298,
    "gn:feature_class":"P",
    "gn:feature_code":"PPL",
    "gn:name":"Ampliaci\u00f3n de la Reforma",
    "gn:population":232,
    "gn:timezone":"America/Monterrey",
    "iso:country":"MX",
    "name:und_x_variant":[
        "Ampliaci\u00f3n de la Reforma"
    ],
    "wof:name":"Ampliacion de la Reforma",
    "wof:placetype":"locality",
    "wof:population":232
},
  "geometry": {"coordinates":[-99.22889000000001,22.47194],"type":"Point"}
}