{
  "type": "Feature",
  "properties": {
    "gn:admin1_code":"12",
    "gn:admin2_code":"76.0",
    "gn:asciiname":"Rio Grande",
    "gn:country_code":"MX",
    "gn:dem":581,
    "gn:feature_class":"P",
    "gn:feature_code":"PPL",
    "gn:name":"R\u00edo Grande",
    "gn:population":75,
    "gn:timezone":"America/Mexico_City",
    "iso:country":"MX",
    "name:und_x_variant":[
        "R\u00edo Grande"
    ],
    "wof:name":"Rio Grande",
    "wof:placetype":"locality",
    "wof:population":75
},
  "geometry": {"coordinates":[-99.03657,17.10623],"type":"Point"}
}