{
  "type": "Feature",
  "properties": {
    "gn:admin1_code":"6.0",
    "gn:admin2_code":"42.0",
    "gn:asciiname":"Barrenos",
    "gn:country_code":"MX",
    "gn:dem":1241,
    "gn:feature_class":"P",
    "gn:feature_code":"PPL",
    "gn:name":"Barrenos",
    "gn:population":0,
    "gn:timezone":"America/Chihuahua",
    "iso:country":"MX",
    "name:spa_x_preferred":[
        "Barrenos"
    ],
    "wof:name":"Barrenos",
    "wof:placetype":"locality"
},
  "geometry": {"coordinates":[-104.20411,29.17557],"type":"Point"}
}