{
  "type": "Feature",
  "properties": {
    "gn:admin1_code":"21",
    "gn:admin2_code":"76",
    "gn:asciiname":"Valle Roncal",
    "gn:country_code":"MX",
    "gn:dem":508,
    "gn:feature_class":"P",
    "gn:feature_code":"PPL",
    "gn:name":"Valle Roncal",
    "gn:population":26,
    "gn:timezone":"America/Mexico_City",
    "iso:country":"MX",
    "wof:name":"Valle Roncal",
    "wof:placetype":"locality",
    "wof:population":26
},
  "geometry": {"coordinates":[-97.35503,20.03685],"type":"Point"}
}