{
  "type": "Feature",
  "properties": {
    "gn:admin1_code":"6",
    "gn:admin2_code":"40.0",
    "gn:asciiname":"Dos de Abril",
    "gn:country_code":"MX",
    "gn:dem":2181,
    "gn:feature_class":"P",
    "gn:feature_code":"PPL",
    "gn:name":"Dos de Abril",
    "gn:population":0,
    "gn:timezone":"America/Chihuahua",
    "iso:country":"MX",
    "name:spa_x_preferred":[
        "Dos de Abril"
    ],
    "wof:name":"Dos de Abril",
    "wof:placetype":"locality"
},
  "geometry": {"coordinates":[-108.22117,29.69635],"type":"Point"}
}