{
  "type": "Feature",
  "properties": {
    "gn:admin1_code":"19",
    "gn:admin2_code":"20.0",
    "gn:asciiname":"San Mateo",
    "gn:country_code":"MX",
    "gn:dem":94,
    "gn:feature_class":"P",
    "gn:feature_code":"PPL",
    "gn:name":"San Mateo",
    "gn:population":7,
    "gn:timezone":"America/Monterrey",
    "iso:country":"MX",
    "wof:name":"San Mateo",
    "wof:placetype":"locality",
    "wof:population":7
},
  "geometry": {"coordinates":[-98.61167,25.92944],"type":"Point"}
}