{
  "type": "Feature",
  "properties": {
    "gn:admin1_code":"4",
    "gn:admin2_code":"6.0",
    "gn:asciiname":"Campo Menonita Santa Rosa",
    "gn:country_code":"MX",
    "gn:dem":116,
    "gn:feature_class":"P",
    "gn:feature_code":"PPL",
    "gn:name":"Campo Menonita Santa Rosa",
    "gn:population":185,
    "gn:timezone":"America/Merida",
    "iso:country":"MX",
    "wof:name":"Campo Menonita Santa Rosa",
    "wof:placetype":"locality",
    "wof:population":185
},
  "geometry": {"coordinates":[-89.76666999999998,19.93778],"type":"Point"}
}