{
  "type": "Feature",
  "properties": {
    "gn:admin1_code":"10.0",
    "gn:admin2_code":"34.0",
    "gn:asciiname":"Los Patos",
    "gn:country_code":"MX",
    "gn:dem":320,
    "gn:feature_class":"P",
    "gn:feature_code":"PPL",
    "gn:name":"Los Patos",
    "gn:population":0,
    "gn:timezone":"America/Monterrey",
    "iso:country":"MX",
    "name:spa_x_preferred":[
        "Los Patos"
    ],
    "wof:name":"Los Patos",
    "wof:placetype":"locality"
},
  "geometry": {"coordinates":[-107.04198999999998,25.27498],"type":"Point"}
}