{
  "type": "Feature",
  "properties": {
    "gn:admin1_code":"28",
    "gn:admin2_code":"22.0",
    "gn:asciiname":"Daniel Ayala",
    "gn:country_code":"MX",
    "gn:dem":11,
    "gn:feature_class":"P",
    "gn:feature_code":"PPL",
    "gn:name":"Daniel Ayala",
    "gn:population":7,
    "gn:timezone":"America/Matamoros",
    "iso:country":"MX",
    "name:ara_x_preferred":[
        "\u062f\u0627\u0646\u064a\u064a\u0644 \u0633\u0627\u0646\u062a\u0634\u064a\u0632 \u0623\u064a\u0627\u0644\u0627"
    ],
    "name:azb_x_preferred":[
        "\u062f\u0646\u06cc\u0644 \u0622\u06cc\u0627\u0644\u0627"
    ],
    "name:deu_x_preferred":[
        "Daniel S\u00e1nchez Ayala"
    ],
    "name:fas_x_preferred":[
        "\u062f\u0646\u06cc\u0644 \u0622\u06cc\u0627\u0644\u0627"
    ],
    "name:fin_x_preferred":[
        "Daniel Ayala"
    ],
    "name:fra_x_preferred":[
        "Daniel Ayala"
    ],
    "name:hun_x_preferred":[
        "Daniel S\u00e1nchez Ayala"
    ],
    "name:ind_x_preferred":[
        "Daniel Ayala"
    ],
    "name:ita_x_preferred":[
        "Daniel S\u00e1nchez Ayala"
    ],
    "name:jpn_x_preferred":[
        "\u30c0\u30cb\u30a8\u30eb\u30fb\u30a2\u30b8\u30e3\u30e9"
    ],
    "name:kor_x_preferred":[
        "\ub2e4\ub2c8\uc5d8 \uc544\uc584\ub77c"
    ],
    "name:lav_x_preferred":[
        "Danjels San\u010dess Ajala"
    ],
    "name:mlg_x_preferred":[
        "Daniel Ayala"
    ],
    "name:msa_x_preferred":[
        "Daniel Ayala"
    ],
    "name:nld_x_preferred":[
        "Daniel S\u00e1nchez Ayala"
    ],
    "name:nor_x_preferred":[
        "Daniel S\u00e1nchez Ayala"
    ],
    "name:pol_x_preferred":[
        "Daniel Ayala"
    ],
    "name:por_x_preferred":[
        "Daniel S\u00e1nchez Ayala"
    ],
    "name:rus_x_preferred":[
        "\u0410\u0439\u044f\u043b\u0430"
    ],
    "name:spa_x_preferred":[
        "Daniel S\u00e1nchez Ayala"
    ],
    "name:swe_x_preferred":[
        "Daniel Ayala"
    ],
    "name:tgk_x_preferred":[
        "\u0414\u0430\u043d\u0438\u044d\u043b \u0410\u044f\u043b\u0430"
    ],
    "name:tur_x_preferred":[
        "Daniel Ayala"
    ],
    "name:vie_x_preferred":[
        "Daniel Ayala"
    ],
    "name:zho_x_preferred":[
        "\u4e39\u5c3c\u723e\u00b7\u827e\u8036\u62c9"
    ],
    "wof:name":"Daniel Ayala",
    "wof:placetype":"locality",
    "wof:population":7
},
  "geometry": {"coordinates":[-97.69528,25.71278],"type":"Point"}
}