{
  "type": "Feature",
  "properties": {
    "gn:admin1_code":"28",
    "gn:admin2_code":"22.0",
    "gn:asciiname":"Daniel Ayala",
    "gn:country_code":"MX",
    "gn:dem":11,
    "gn:feature_class":"P",
    "gn:feature_code":"PPL",
    "gn:name":"Daniel Ayala",
    "gn:population":7,
    "gn:timezone":"America/Matamoros",
    "iso:country":"MX",
    "wof:name":"Daniel Ayala",
    "wof:placetype":"locality",
    "wof:population":7
},
  "geometry": {"coordinates":[-97.69528,25.71278],"type":"Point"}
}