{
  "type": "Feature",
  "properties": {
    "gn:admin1_code":"15",
    "gn:admin2_code":"38.0",
    "gn:asciiname":"Canada de Onofres",
    "gn:country_code":"MX",
    "gn:dem":2512,
    "gn:feature_class":"P",
    "gn:feature_code":"PPL",
    "gn:name":"Ca\u00f1ada de Onofres",
    "gn:population":652,
    "gn:timezone":"America/Mexico_City",
    "iso:country":"MX",
    "wof:name":"Canada de Onofres",
    "wof:placetype":"locality",
    "wof:population":652
},
  "geometry": {"coordinates":[-99.348,19.56417],"type":"Point"}
}