{
  "type": "Feature",
  "properties": {
    "gn:admin1_code":"14",
    "gn:admin2_code":"8",
    "gn:asciiname":"El Guajolote",
    "gn:country_code":"MX",
    "gn:dem":2221,
    "gn:feature_class":"P",
    "gn:feature_code":"PPL",
    "gn:name":"El Guajolote",
    "gn:population":15,
    "gn:timezone":"America/Mexico_City",
    "iso:country":"MX",
    "wof:name":"El Guajolote",
    "wof:placetype":"locality",
    "wof:population":15
},
  "geometry": {"coordinates":[-102.27,20.7375],"type":"Point"}
}