{
  "type": "Feature",
  "properties": {
    "gn:admin1_code":"20",
    "gn:admin2_code":"446.0",
    "gn:asciiname":"Takava",
    "gn:country_code":"MX",
    "gn:dem":2816,
    "gn:feature_class":"P",
    "gn:feature_code":"PPL",
    "gn:name":"Takava",
    "gn:population":153,
    "gn:timezone":"America/Mexico_City",
    "iso:country":"MX",
    "wof:name":"Takava",
    "wof:placetype":"locality",
    "wof:population":153
},
  "geometry": {"coordinates":[-97.77916999999999,17.06417],"type":"Point"}
}