{
  "type": "Feature",
  "properties": {
    "gn:admin1_code":"15",
    "gn:admin2_code":"14.0",
    "gn:asciiname":"Maye el Fresno",
    "gn:country_code":"MX",
    "gn:dem":2510,
    "gn:feature_class":"P",
    "gn:feature_code":"PPL",
    "gn:name":"Maye el Fresno",
    "gn:population":125,
    "gn:timezone":"America/Mexico_City",
    "iso:country":"MX",
    "wof:name":"Maye el Fresno",
    "wof:placetype":"locality",
    "wof:population":125
},
  "geometry": {"coordinates":[-99.85892,19.85169],"type":"Point"}
}