{
  "type": "Feature",
  "properties": {
    "gn:admin1_code":"13.0",
    "gn:admin2_code":"27.0",
    "gn:asciiname":"Milpa Redonda",
    "gn:country_code":"MX",
    "gn:dem":490,
    "gn:feature_class":"P",
    "gn:feature_code":"PPL",
    "gn:name":"Milpa Redonda",
    "gn:population":31,
    "gn:timezone":"America/Mexico_City",
    "iso:country":"MX",
    "name:spa_x_preferred":[
        "Milpa Redonda"
    ],
    "wof:name":"Milpa Redonda",
    "wof:placetype":"locality",
    "wof:population":31
},
  "geometry": {"coordinates":[-98.02619,20.5551],"type":"Point"}
}