{
  "type": "Feature",
  "properties": {
    "gn:admin1_code":"26.0",
    "gn:admin2_code":"47.0",
    "gn:asciiname":"El Testerazo",
    "gn:country_code":"MX",
    "gn:dem":551,
    "gn:feature_class":"P",
    "gn:feature_code":"PPL",
    "gn:name":"El Testerazo",
    "gn:population":0,
    "gn:timezone":"America/Hermosillo",
    "iso:country":"MX",
    "name:spa_x_preferred":[
        "El Testerazo"
    ],
    "name:und_x_variant":[
        "Rancho El Testerazo"
    ],
    "wof:name":"El Testerazo",
    "wof:placetype":"locality"
},
  "geometry": {"coordinates":[-112.03785999999999,29.92436],"type":"Point"}
}