{
  "type": "Feature",
  "properties": {
    "gn:admin1_code":"10",
    "gn:admin2_code":"14.0",
    "gn:asciiname":"Banco Colorado",
    "gn:country_code":"MX",
    "gn:dem":2291,
    "gn:feature_class":"P",
    "gn:feature_code":"PPL",
    "gn:name":"Banco Colorado",
    "gn:population":0,
    "gn:timezone":"America/Monterrey",
    "iso:country":"MX",
    "name:spa_x_preferred":[
        "Banco Colorado"
    ],
    "wof:name":"Banco Colorado",
    "wof:placetype":"locality"
},
  "geometry": {"coordinates":[-104.36201,22.48598],"type":"Point"}
}