{
  "type": "Feature",
  "properties": {
    "gn:admin1_code":"20",
    "gn:admin2_code":"413.0",
    "gn:asciiname":"Sector U-Dos Sur",
    "gn:country_code":"MX",
    "gn:dem":49,
    "gn:feature_class":"P",
    "gn:feature_code":"PPL",
    "gn:name":"Sector U-Dos Sur",
    "gn:population":255,
    "gn:timezone":"America/Mexico_City",
    "iso:country":"MX",
    "wof:name":"Sector U-Dos Sur",
    "wof:placetype":"locality",
    "wof:population":255
},
  "geometry": {"coordinates":[-96.14194000000001,15.77917],"type":"Point"}
}