{
  "type": "Feature",
  "properties": {
    "gn:admin1_code":"27",
    "gn:admin2_code":"1.0",
    "gn:asciiname":"Miguel Hidalgo 2da. Seccion",
    "gn:country_code":"MX",
    "gn:dem":16,
    "gn:feature_class":"P",
    "gn:feature_code":"PPL",
    "gn:name":"Miguel Hidalgo 2da. Secci\u00f3n",
    "gn:population":96,
    "gn:timezone":"America/Mexico_City",
    "iso:country":"MX",
    "name:und_x_variant":[
        "Miguel Hidalgo 2da. Secci\u00f3n"
    ],
    "wof:name":"Miguel Hidalgo 2da. Seccion",
    "wof:placetype":"locality",
    "wof:population":96
},
  "geometry": {"coordinates":[-91.55667,18.00361000000001],"type":"Point"}
}