{
  "type": "Feature",
  "properties": {
    "gn:admin1_code":"6",
    "gn:admin2_code":"41.0",
    "gn:asciiname":"El Magueche",
    "gn:country_code":"MX",
    "gn:dem":2179,
    "gn:feature_class":"P",
    "gn:feature_code":"PPL",
    "gn:name":"El Magueche",
    "gn:population":5,
    "gn:timezone":"America/Chihuahua",
    "iso:country":"MX",
    "wof:name":"El Magueche",
    "wof:placetype":"locality",
    "wof:population":5
},
  "geometry": {"coordinates":[-107.92439,27.98824],"type":"Point"}
}