{
  "type": "Feature",
  "properties": {
    "gn:admin1_code":"17",
    "gn:admin2_code":"9",
    "gn:asciiname":"Kilometro 55",
    "gn:country_code":"MX",
    "gn:dem":2639,
    "gn:feature_class":"P",
    "gn:feature_code":"PPL",
    "gn:name":"Kil\u00f3metro 55",
    "gn:population":21,
    "gn:timezone":"America/Mexico_City",
    "iso:country":"MX",
    "name:und_x_variant":[
        "Kil\u00f3metro 55"
    ],
    "wof:name":"Kilometro 55",
    "wof:placetype":"locality",
    "wof:population":21
},
  "geometry": {"coordinates":[-99.22499999999999,19.02917],"type":"Point"}
}