{
  "type": "Feature",
  "properties": {
    "gn:admin1_code":"6",
    "gn:admin2_code":"47.0",
    "gn:asciiname":"Sahuayacan",
    "gn:country_code":"MX",
    "gn:dem":824,
    "gn:feature_class":"P",
    "gn:feature_code":"PPL",
    "gn:name":"Sahuayacan",
    "gn:population":0,
    "gn:timezone":"America/Chihuahua",
    "iso:country":"MX",
    "name:spa_x_preferred":[
        "Sahuayacan"
    ],
    "wof:name":"Sahuayacan",
    "wof:placetype":"locality"
},
  "geometry": {"coordinates":[-108.67461000000002,28.11932],"type":"Point"}
}