{
  "type": "Feature",
  "properties": {
    "gn:admin1_code":"29",
    "gn:admin2_code":"34.0",
    "gn:asciiname":"Las Zarandelas",
    "gn:country_code":"MX",
    "gn:dem":3112,
    "gn:feature_class":"P",
    "gn:feature_code":"PPL",
    "gn:name":"Las Zarandelas",
    "gn:population":5,
    "gn:timezone":"America/Mexico_City",
    "iso:country":"MX",
    "wof:name":"Las Zarandelas",
    "wof:placetype":"locality",
    "wof:population":5
},
  "geometry": {"coordinates":[-98.03197,19.59556],"type":"Point"}
}