{
  "type": "Feature",
  "properties": {
    "gn:admin1_code":"16.0",
    "gn:admin2_code":"15.0",
    "gn:asciiname":"Casas Quemadas",
    "gn:country_code":"MX",
    "gn:dem":837,
    "gn:feature_class":"P",
    "gn:feature_code":"PPL",
    "gn:name":"Casas Quemadas",
    "gn:population":0,
    "gn:timezone":"America/Mexico_City",
    "iso:country":"MX",
    "name:spa_x_preferred":[
        "Casas Quemadas"
    ],
    "wof:name":"Casas Quemadas",
    "wof:placetype":"locality"
},
  "geometry": {"coordinates":[-103.14870000000001,18.42139],"type":"Point"}
}