{
  "type": "Feature",
  "properties": {
    "gn:admin1_code":"5",
    "gn:admin2_code":"76.0",
    "gn:asciiname":"Quintana Roo",
    "gn:country_code":"MX",
    "gn:dem":684,
    "gn:feature_class":"P",
    "gn:feature_code":"PPL",
    "gn:name":"Quintana Roo",
    "gn:population":0,
    "gn:timezone":"America/Mexico_City",
    "iso:country":"MX",
    "name:spa_x_preferred":[
        "Quintana Roo"
    ],
    "wof:name":"Quintana Roo",
    "wof:placetype":"locality"
},
  "geometry": {"coordinates":[-92.70304,17.35673],"type":"Point"}
}