{
  "type": "Feature",
  "properties": {
    "gn:admin1_code":"27",
    "gn:admin2_code":"1.0",
    "gn:asciiname":"Santa Clara",
    "gn:country_code":"MX",
    "gn:dem":32,
    "gn:feature_class":"P",
    "gn:feature_code":"PPL",
    "gn:name":"Santa Clara",
    "gn:population":8,
    "gn:timezone":"America/Mexico_City",
    "iso:country":"MX",
    "wof:name":"Santa Clara",
    "wof:placetype":"locality",
    "wof:population":8
},
  "geometry": {"coordinates":[-91.46972,17.87],"type":"Point"}
}