{
  "type": "Feature",
  "properties": {
    "gn:admin1_code":"2.0",
    "gn:admin2_code":"1.0",
    "gn:asciiname":"El Conejo",
    "gn:country_code":"MX",
    "gn:dem":393,
    "gn:feature_class":"P",
    "gn:feature_code":"PPL",
    "gn:name":"El Conejo",
    "gn:population":0,
    "gn:timezone":"America/Tijuana",
    "iso:country":"MX",
    "name:spa_x_preferred":[
        "El Conejo"
    ],
    "wof:name":"El Conejo",
    "wof:placetype":"locality"
},
  "geometry": {"coordinates":[-116.63782999999999,32.1665],"type":"Point"}
}