{
  "type": "Feature",
  "properties": {
    "gn:admin1_code":"30",
    "gn:admin2_code":"92.0",
    "gn:asciiname":"San Jose Paso Nuevo",
    "gn:country_code":"MX",
    "gn:dem":2376,
    "gn:feature_class":"P",
    "gn:feature_code":"PPL",
    "gn:name":"San Jos\u00e9 Paso Nuevo",
    "gn:population":130,
    "gn:timezone":"America/Mexico_City",
    "iso:country":"MX",
    "name:und_x_variant":[
        "San Jos\u00e9 Paso Nuevo"
    ],
    "wof:name":"San Jose Paso Nuevo",
    "wof:placetype":"locality",
    "wof:population":130
},
  "geometry": {"coordinates":[-97.10583,19.45139],"type":"Point"}
}