{
  "type": "Feature",
  "properties": {
    "gn:admin1_code":"30",
    "gn:admin2_code":"169",
    "gn:asciiname":"La Carmelita",
    "gn:country_code":"MX",
    "gn:dem":111,
    "gn:feature_class":"P",
    "gn:feature_code":"PPL",
    "gn:name":"La Carmelita",
    "gn:population":11,
    "gn:timezone":"America/Mexico_City",
    "iso:country":"MX",
    "wof:name":"La Carmelita",
    "wof:placetype":"locality",
    "wof:population":11
},
  "geometry": {"coordinates":[-95.75360999999999,18.00417000000001],"type":"Point"}
}