{
  "type": "Feature",
  "properties": {
    "gn:admin1_code":"25",
    "gn:admin2_code":"11",
    "gn:asciiname":"Campo el Porvenir",
    "gn:country_code":"MX",
    "gn:dem":17,
    "gn:feature_class":"P",
    "gn:feature_code":"PPL",
    "gn:name":"Campo el Porvenir",
    "gn:population":49,
    "gn:timezone":"America/Mazatlan",
    "iso:country":"MX",
    "wof:name":"Campo el Porvenir",
    "wof:placetype":"locality",
    "wof:population":49
},
  "geometry": {"coordinates":[-108.73569999999999,25.72356],"type":"Point"}
}