{
  "type": "Feature",
  "properties": {
    "gn:admin1_code":"30",
    "gn:admin2_code":"143.0",
    "gn:asciiname":"Vista Hermosa",
    "gn:country_code":"MX",
    "gn:dem":123,
    "gn:feature_class":"P",
    "gn:feature_code":"PPL",
    "gn:name":"Vista Hermosa",
    "gn:population":826,
    "gn:timezone":"America/Mexico_City",
    "iso:country":"MX",
    "wof:name":"Vista Hermosa",
    "wof:placetype":"locality",
    "wof:population":826
},
  "geometry": {"coordinates":[-95.31999999999999,18.42694],"type":"Point"}
}