{
  "type": "Feature",
  "properties": {
    "gn:admin1_code":"12",
    "gn:admin2_code":"68.0",
    "gn:asciiname":"Junta de los Rios (Las Juntas)",
    "gn:country_code":"MX",
    "gn:dem":104,
    "gn:feature_class":"P",
    "gn:feature_code":"PPL",
    "gn:name":"Junta de los R\u00edos (Las Juntas)",
    "gn:population":355,
    "gn:timezone":"America/Mexico_City",
    "iso:country":"MX",
    "name:und_x_variant":[
        "Junta de los R\u00edos (Las Juntas)"
    ],
    "wof:name":"Junta de los Rios (Las Juntas)",
    "wof:placetype":"locality",
    "wof:population":355
},
  "geometry": {"coordinates":[-101.74822,18.03401],"type":"Point"}
}