{
  "type": "Feature",
  "properties": {
    "gn:admin1_code":"18",
    "gn:admin2_code":"18.0",
    "gn:asciiname":"Rancho de Vicente Acuna",
    "gn:country_code":"MX",
    "gn:dem":15,
    "gn:feature_class":"P",
    "gn:feature_code":"PPL",
    "gn:name":"Rancho de Vicente Acu\u00f1a",
    "gn:population":5,
    "gn:timezone":"America/Mazatlan",
    "iso:country":"MX",
    "name:und_x_variant":[
        "Rancho de Vicente Acu\u00f1a"
    ],
    "wof:name":"Rancho de Vicente Acuna",
    "wof:placetype":"locality",
    "wof:population":5
},
  "geometry": {"coordinates":[-105.25722,21.92611],"type":"Point"}
}