{
  "type": "Feature",
  "properties": {
    "gn:admin1_code":"28.0",
    "gn:admin2_code":"11.0",
    "gn:asciiname":"Americo Villarreal Guerra",
    "gn:country_code":"MX",
    "gn:dem":91,
    "gn:feature_class":"P",
    "gn:feature_code":"PPL",
    "gn:name":"Am\u00e9rico Villarreal Guerra",
    "gn:population":0,
    "gn:timezone":"America/Monterrey",
    "iso:country":"MX",
    "name:spa_x_preferred":[
        "Am\u00e9rico Villarreal Guerra"
    ],
    "wof:name":"Americo Villarreal Guerra",
    "wof:placetype":"locality"
},
  "geometry": {"coordinates":[-99.13394,22.92231],"type":"Point"}
}