{
  "type": "Feature",
  "properties": {
    "gn:admin1_code":"11.0",
    "gn:admin2_code":"23.0",
    "gn:asciiname":"Guayabo de Origel",
    "gn:country_code":"MX",
    "gn:dem":1838,
    "gn:feature_class":"P",
    "gn:feature_code":"PPL",
    "gn:name":"Guayabo de Origel",
    "gn:population":0,
    "gn:timezone":"America/Mexico_City",
    "iso:country":"MX",
    "name:spa_x_preferred":[
        "Guayabo de Origel"
    ],
    "name:und_x_variant":[
        "El Guayabo",
        "El Guayabo de Origel"
    ],
    "wof:name":"Guayabo de Origel",
    "wof:placetype":"locality"
},
  "geometry": {"coordinates":[-101.72918,20.28895],"type":"Point"}
}