{
  "type": "Feature",
  "properties": {
    "gn:admin1_code":"5",
    "gn:admin2_code":"89.0",
    "gn:asciiname":"Bojoncito",
    "gn:country_code":"MX",
    "gn:dem":1356,
    "gn:feature_class":"P",
    "gn:feature_code":"PPL",
    "gn:name":"Bojoncito",
    "gn:population":75,
    "gn:timezone":"America/Mexico_City",
    "iso:country":"MX",
    "wof:name":"Bojoncito",
    "wof:placetype":"locality",
    "wof:population":75
},
  "geometry": {"coordinates":[-92.25472000000001,15.14667],"type":"Point"}
}