{
  "type": "Feature",
  "properties": {
    "gn:admin1_code":"10",
    "gn:admin2_code":"20.0",
    "gn:asciiname":"La Luz",
    "gn:country_code":"MX",
    "gn:dem":1959,
    "gn:feature_class":"P",
    "gn:feature_code":"PPL",
    "gn:name":"La Luz",
    "gn:population":0,
    "gn:timezone":"America/Monterrey",
    "iso:country":"MX",
    "name:spa_x_preferred":[
        "La Luz"
    ],
    "name:und_x_variant":[
        "Rancho La Luz"
    ],
    "wof:name":"La Luz",
    "wof:placetype":"locality"
},
  "geometry": {"coordinates":[-104.39912,24.41558],"type":"Point"}
}