{
  "type": "Feature",
  "properties": {
    "gn:admin1_code":"10",
    "gn:admin2_code":"2",
    "gn:asciiname":"La Ermita",
    "gn:country_code":"MX",
    "gn:dem":1276,
    "gn:feature_class":"P",
    "gn:feature_code":"PPL",
    "gn:name":"La Ermita",
    "gn:population":12,
    "gn:timezone":"America/Monterrey",
    "iso:country":"MX",
    "name:ita_x_preferred":[
        "La Ermita"
    ],
    "name:spa_x_preferred":[
        "La Ermita"
    ],
    "name:zho_x_preferred":[
        "\u62c9\u57c3\u723e\u7c73\u5854"
    ],
    "wof:name":"La Ermita",
    "wof:placetype":"locality",
    "wof:population":12
},
  "geometry": {"coordinates":[-106.55568,25.13153],"type":"Point"}
}