{
  "type": "Feature",
  "properties": {
    "gn:admin1_code":"19",
    "gn:admin2_code":"22.0",
    "gn:asciiname":"Los Cuates",
    "gn:country_code":"MX",
    "gn:dem":156,
    "gn:feature_class":"P",
    "gn:feature_code":"PPL",
    "gn:name":"Los Cuates",
    "gn:population":4,
    "gn:timezone":"America/Monterrey",
    "iso:country":"MX",
    "name:spa_x_preferred":[
        "Los Cuales"
    ],
    "name:spa_x_variant":[
        "Los Cuates"
    ],
    "wof:name":"Los Cuates",
    "wof:placetype":"locality",
    "wof:population":4
},
  "geometry": {"coordinates":[-99.16133000000001,25.2852],"type":"Point"}
}