{
  "type": "Feature",
  "properties": {
    "gn:admin1_code":"19.0",
    "gn:admin2_code":"45.0",
    "gn:asciiname":"El Sinai",
    "gn:country_code":"MX",
    "gn:dem":459,
    "gn:feature_class":"P",
    "gn:feature_code":"PPL",
    "gn:name":"El Sina\u00ed",
    "gn:population":0,
    "gn:timezone":"America/Monterrey",
    "iso:country":"MX",
    "name:spa_x_preferred":[
        "El Sina\u00ed"
    ],
    "wof:name":"El Sinai",
    "wof:placetype":"locality"
},
  "geometry": {"coordinates":[-100.28243000000001,26.05715],"type":"Point"}
}