{
  "type": "Feature",
  "properties": {
    "gn:admin1_code":"25",
    "gn:admin2_code":"6.0",
    "gn:asciiname":"Palos Blancos",
    "gn:country_code":"MX",
    "gn:dem":63,
    "gn:feature_class":"P",
    "gn:feature_code":"PPL",
    "gn:name":"Palos Blancos",
    "gn:population":0,
    "gn:timezone":"America/Mazatlan",
    "iso:country":"MX",
    "name:spa_x_preferred":[
        "Palos Blancos"
    ],
    "wof:name":"Palos Blancos",
    "wof:placetype":"locality"
},
  "geometry": {"coordinates":[-107.38896,24.92554],"type":"Point"}
}