{
  "type": "Feature",
  "properties": {
    "gn:admin1_code":"6",
    "gn:admin2_code":"5.0",
    "gn:asciiname":"San Blas",
    "gn:country_code":"MX",
    "gn:dem":1253,
    "gn:feature_class":"P",
    "gn:feature_code":"PPL",
    "gn:name":"San Blas",
    "gn:population":0,
    "gn:timezone":"America/Chihuahua",
    "iso:country":"MX",
    "name:spa_x_preferred":[
        "San Blas"
    ],
    "name:und_x_variant":[
        "Rancho San Blas"
    ],
    "wof:name":"San Blas",
    "wof:placetype":"locality"
},
  "geometry": {"coordinates":[-107.24079,31.24339],"type":"Point"}
}