{
  "type": "Feature",
  "properties": {
    "gn:admin1_code":"30",
    "gn:admin2_code":"48",
    "gn:asciiname":"Rastro",
    "gn:country_code":"MX",
    "gn:dem":32,
    "gn:feature_class":"P",
    "gn:feature_code":"PPL",
    "gn:name":"Rastro",
    "gn:population":24,
    "gn:timezone":"America/Mexico_City",
    "iso:country":"MX",
    "wof:name":"Rastro",
    "wof:placetype":"locality",
    "wof:population":24
},
  "geometry": {"coordinates":[-94.64111,17.98306000000001],"type":"Point"}
}