{
  "type": "Feature",
  "properties": {
    "gn:admin1_code":"11",
    "gn:admin2_code":"37",
    "gn:asciiname":"Ejido del Bajio",
    "gn:country_code":"MX",
    "gn:dem":1782,
    "gn:feature_class":"P",
    "gn:feature_code":"PPL",
    "gn:name":"Ejido del Baj\u00edo",
    "gn:population":17,
    "gn:timezone":"America/Mexico_City",
    "iso:country":"MX",
    "name:und_x_variant":[
        "Ejido del Baj\u00edo"
    ],
    "wof:name":"Ejido del Bajio",
    "wof:placetype":"locality",
    "wof:population":17
},
  "geometry": {"coordinates":[-101.47583,20.94472],"type":"Point"}
}