{
  "type": "Feature",
  "properties": {
    "gn:admin1_code":"27",
    "gn:admin2_code":"3.0",
    "gn:asciiname":"Boca de Pantoja",
    "gn:country_code":"MX",
    "gn:dem":0,
    "gn:feature_class":"P",
    "gn:feature_code":"PPL",
    "gn:name":"Boca de Pantoja",
    "gn:population":473,
    "gn:timezone":"America/Mexico_City",
    "iso:country":"MX",
    "wof:name":"Boca de Pantoja",
    "wof:placetype":"locality",
    "wof:population":473
},
  "geometry": {"coordinates":[-92.50167,18.31778],"type":"Point"}
}