{
  "type": "Feature",
  "properties": {
    "gn:admin1_code":"30",
    "gn:admin2_code":"121.0",
    "gn:asciiname":"Horconcitos",
    "gn:country_code":"MX",
    "gn:dem":23,
    "gn:feature_class":"P",
    "gn:feature_code":"PPL",
    "gn:name":"Horconcitos",
    "gn:population":0,
    "gn:timezone":"America/Mexico_City",
    "iso:country":"MX",
    "name:spa_x_preferred":[
        "Horconcitos"
    ],
    "name:spa_x_variant":[
        "Horcocitos",
        "Jopoyal"
    ],
    "wof:name":"Horconcitos",
    "wof:placetype":"locality"
},
  "geometry": {"coordinates":[-97.74482,21.85233],"type":"Point"}
}