{
  "type": "Feature",
  "properties": {
    "gn:admin1_code":"29",
    "gn:admin2_code":"30.0",
    "gn:asciiname":"Nicolas Bravo",
    "gn:country_code":"MX",
    "gn:dem":2518,
    "gn:feature_class":"P",
    "gn:feature_code":"PPL",
    "gn:name":"Nicol\u00e1s Bravo",
    "gn:population":0,
    "gn:timezone":"America/Mexico_City",
    "iso:country":"MX",
    "name:spa_x_preferred":[
        "Nicol\u00e1s Bravo"
    ],
    "wof:name":"Nicolas Bravo",
    "wof:placetype":"locality"
},
  "geometry": {"coordinates":[-97.96759,19.42213],"type":"Point"}
}