{
  "type": "Feature",
  "properties": {
    "gn:admin1_code":"21",
    "gn:admin2_code":"32.0",
    "gn:asciiname":"Zepatla",
    "gn:country_code":"MX",
    "gn:dem":1147,
    "gn:feature_class":"P",
    "gn:feature_code":"PPL",
    "gn:name":"Zepatla",
    "gn:population":0,
    "gn:timezone":"America/Mexico_City",
    "iso:country":"MX",
    "name:spa_x_preferred":[
        "Zepatla"
    ],
    "name:spa_x_variant":[
        "Santa Cruz Xepatla"
    ],
    "name:und_x_variant":[
        "Xepatl\u00e1"
    ],
    "wof:name":"Zepatla",
    "wof:placetype":"locality"
},
  "geometry": {"coordinates":[-98.74899000000001,18.29885],"type":"Point"}
}