{
  "type": "Feature",
  "properties": {
    "gn:admin1_code":"16",
    "gn:admin2_code":"97.0",
    "gn:asciiname":"Cuirindales de Maritangacho",
    "gn:country_code":"MX",
    "gn:dem":655,
    "gn:feature_class":"P",
    "gn:feature_code":"PPL",
    "gn:name":"Cuirindales de Maritangacho",
    "gn:population":130,
    "gn:timezone":"America/Mexico_City",
    "iso:country":"MX",
    "wof:name":"Cuirindales de Maritangacho",
    "wof:placetype":"locality",
    "wof:population":130
},
  "geometry": {"coordinates":[-101.38417,18.87694],"type":"Point"}
}