{
  "type": "Feature",
  "properties": {
    "gn:admin1_code":"30.0",
    "gn:admin2_code":"141.0",
    "gn:asciiname":"Totlalli",
    "gn:country_code":"MX",
    "gn:dem":860,
    "gn:feature_class":"P",
    "gn:feature_code":"PPL",
    "gn:name":"Totlalli",
    "gn:population":0,
    "gn:timezone":"America/Mexico_City",
    "iso:country":"MX",
    "name:spa_x_preferred":[
        "Totlalli"
    ],
    "wof:name":"Totlalli",
    "wof:placetype":"locality"
},
  "geometry": {"coordinates":[-95.14218,18.50024],"type":"Point"}
}