{
  "type": "Feature",
  "properties": {
    "gn:admin1_code":"32.0",
    "gn:admin2_code":"10.0",
    "gn:asciiname":"Santa Elena de los Carrera",
    "gn:country_code":"MX",
    "gn:dem":2089,
    "gn:feature_class":"P",
    "gn:feature_code":"PPL",
    "gn:name":"Santa Elena de los Carrera",
    "gn:population":0,
    "gn:timezone":"America/Mexico_City",
    "iso:country":"MX",
    "name:spa_x_preferred":[
        "Santa Elena de los Carrera"
    ],
    "wof:name":"Santa Elena de los Carrera",
    "wof:placetype":"locality"
},
  "geometry": {"coordinates":[-103.09365,23.17048],"type":"Point"}
}