{
  "type": "Feature",
  "properties": {
    "gn:admin1_code":"5",
    "gn:admin2_code":"44.0",
    "gn:asciiname":"Francisco Romo Serrano",
    "gn:country_code":"MX",
    "gn:dem":1345,
    "gn:feature_class":"P",
    "gn:feature_code":"PPL",
    "gn:name":"Francisco Romo Serrano",
    "gn:population":0,
    "gn:timezone":"America/Mexico_City",
    "iso:country":"MX",
    "name:spa_x_preferred":[
        "Francisco Romo Serrano"
    ],
    "wof:name":"Francisco Romo Serrano",
    "wof:placetype":"locality"
},
  "geometry": {"coordinates":[-92.82867,16.78708],"type":"Point"}
}