{
  "type": "Feature",
  "properties": {
    "gn:admin1_code":"21",
    "gn:admin2_code":"83.0",
    "gn:asciiname":"La Tronconera",
    "gn:country_code":"MX",
    "gn:dem":2769,
    "gn:feature_class":"P",
    "gn:feature_code":"PPL",
    "gn:name":"La Tronconera",
    "gn:population":56,
    "gn:timezone":"America/Mexico_City",
    "iso:country":"MX",
    "wof:name":"La Tronconera",
    "wof:placetype":"locality",
    "wof:population":56
},
  "geometry": {"coordinates":[-97.9823,19.65607],"type":"Point"}
}