{
  "type": "Feature",
  "properties": {
    "gn:admin1_code":"12",
    "gn:admin2_code":"13.0",
    "gn:asciiname":"El Macahuite",
    "gn:country_code":"MX",
    "gn:dem":263,
    "gn:feature_class":"P",
    "gn:feature_code":"PPL",
    "gn:name":"El Macahuite",
    "gn:population":473,
    "gn:timezone":"America/Mexico_City",
    "iso:country":"MX",
    "wof:name":"El Macahuite",
    "wof:placetype":"locality",
    "wof:population":473
},
  "geometry": {"coordinates":[-98.58,16.69611],"type":"Point"}
}