{
  "type": "Feature",
  "properties": {
    "gn:admin1_code":"10",
    "gn:admin2_code":"14.0",
    "gn:asciiname":"Platano Enterrado",
    "gn:country_code":"MX",
    "gn:dem":2551,
    "gn:feature_class":"P",
    "gn:feature_code":"PPL",
    "gn:name":"Pl\u00e1tano Enterrado",
    "gn:population":4,
    "gn:timezone":"America/Monterrey",
    "iso:country":"MX",
    "name:und_x_variant":[
        "Pl\u00e1tano Enterrado"
    ],
    "wof:name":"Platano Enterrado",
    "wof:placetype":"locality",
    "wof:population":4
},
  "geometry": {"coordinates":[-104.68386,22.9817],"type":"Point"}
}