{
  "type": "Feature",
  "properties": {
    "gn:admin1_code":"27",
    "gn:admin2_code":"13.0",
    "gn:asciiname":"Tapotzingo",
    "gn:country_code":"MX",
    "gn:dem":6,
    "gn:feature_class":"P",
    "gn:feature_code":"PPL",
    "gn:name":"Tapotzingo",
    "gn:population":0,
    "gn:timezone":"America/Mexico_City",
    "iso:country":"MX",
    "name:und_x_variant":[
        "Tapacingo",
        "Tapotzingo"
    ],
    "wof:name":"Tapotzingo",
    "wof:placetype":"locality"
},
  "geometry": {"coordinates":[-93.01421000000001,18.20443],"type":"Point"}
}