{
  "type": "Feature",
  "properties": {
    "gn:admin1_code":"5",
    "gn:admin2_code":"84",
    "gn:asciiname":"La Carretera",
    "gn:country_code":"MX",
    "gn:dem":229,
    "gn:feature_class":"P",
    "gn:feature_code":"PPL",
    "gn:name":"La Carretera",
    "gn:population":48,
    "gn:timezone":"America/Mexico_City",
    "iso:country":"MX",
    "name:por_x_preferred":[
        "La Carretera"
    ],
    "name:rus_x_preferred":[
        "La carretera"
    ],
    "wof:name":"La Carretera",
    "wof:placetype":"locality",
    "wof:population":48
},
  "geometry": {"coordinates":[-93.02333,17.39417000000001],"type":"Point"}
}