{
  "type": "Feature",
  "properties": {
    "gn:admin1_code":"12",
    "gn:admin2_code":"47",
    "gn:asciiname":"El Copal",
    "gn:country_code":"MX",
    "gn:dem":1294,
    "gn:feature_class":"P",
    "gn:feature_code":"PPL",
    "gn:name":"El Copal",
    "gn:population":27,
    "gn:timezone":"America/Mexico_City",
    "iso:country":"MX",
    "wof:name":"El Copal",
    "wof:placetype":"locality",
    "wof:population":27
},
  "geometry": {"coordinates":[-99.86912,18.58911],"type":"Point"}
}