{
  "type": "Feature",
  "properties": {
    "gn:admin1_code":"11",
    "gn:admin2_code":"17.0",
    "gn:asciiname":"La Arena (Jose Luis Cabrera Martinez)",
    "gn:country_code":"MX",
    "gn:dem":1746,
    "gn:feature_class":"P",
    "gn:feature_code":"PPL",
    "gn:name":"La Arena (Jos\u00e9 Luis Cabrera Mart\u00ednez)",
    "gn:population":6,
    "gn:timezone":"America/Mexico_City",
    "iso:country":"MX",
    "name:und_x_variant":[
        "La Arena (Jos\u00e9 Luis Cabrera Mart\u00ednez)"
    ],
    "wof:name":"La Arena (Jose Luis Cabrera Martinez)",
    "wof:placetype":"locality",
    "wof:population":6
},
  "geometry": {"coordinates":[-101.35583,20.7675],"type":"Point"}
}