{
  "type": "Feature",
  "properties": {
    "gn:admin1_code":"19.0",
    "gn:admin2_code":"17.0",
    "gn:asciiname":"La Noria de la Soledad",
    "gn:country_code":"MX",
    "gn:dem":1864,
    "gn:feature_class":"P",
    "gn:feature_code":"PPL",
    "gn:name":"La Noria de la Soledad",
    "gn:population":0,
    "gn:timezone":"America/Monterrey",
    "iso:country":"MX",
    "name:spa_x_preferred":[
        "La Noria de la Soledad"
    ],
    "wof:name":"La Noria de la Soledad",
    "wof:placetype":"locality"
},
  "geometry": {"coordinates":[-100.67355000000001,24.77424],"type":"Point"}
}