{
  "type": "Feature",
  "properties": {
    "gn:admin1_code":"5",
    "gn:admin2_code":"96",
    "gn:asciiname":"Cerro Alto",
    "gn:country_code":"MX",
    "gn:dem":1290,
    "gn:feature_class":"P",
    "gn:feature_code":"PPL",
    "gn:name":"Cerro Alto",
    "gn:population":11,
    "gn:timezone":"America/Mexico_City",
    "iso:country":"MX",
    "name:ceb_x_preferred":[
        "Cerro Alto"
    ],
    "name:swe_x_preferred":[
        "Cerro Alto"
    ],
    "wof:name":"Cerro Alto",
    "wof:placetype":"locality",
    "wof:population":11
},
  "geometry": {"coordinates":[-92.49583,17.29361],"type":"Point"}
}