{
  "type": "Feature",
  "properties": {
    "gn:admin1_code":"21",
    "gn:admin2_code":"19.0",
    "gn:asciiname":"San Jeronimo Caleras",
    "gn:country_code":"MX",
    "gn:dem":1764,
    "gn:feature_class":"P",
    "gn:feature_code":"PPL",
    "gn:name":"San Jer\u00f3nimo Caleras",
    "gn:population":617,
    "gn:timezone":"America/Mexico_City",
    "iso:country":"MX",
    "name:und_x_variant":[
        "San Jer\u00f3nimo Caleras"
    ],
    "wof:name":"San Jeronimo Caleras",
    "wof:placetype":"locality",
    "wof:population":617
},
  "geometry": {"coordinates":[-98.34166999999999,18.845],"type":"Point"}
}