{
  "type": "Feature",
  "properties": {
    "gn:admin1_code":"3",
    "gn:admin2_code":"2.0",
    "gn:asciiname":"La Travesia",
    "gn:country_code":"MX",
    "gn:dem":17,
    "gn:feature_class":"P",
    "gn:feature_code":"PPL",
    "gn:name":"La Traves\u00eda",
    "gn:population":0,
    "gn:timezone":"America/Mazatlan",
    "iso:country":"MX",
    "name:spa_x_preferred":[
        "La Traves\u00eda"
    ],
    "wof:name":"La Travesia",
    "wof:placetype":"locality"
},
  "geometry": {"coordinates":[-111.6628,26.56001],"type":"Point"}
}