{
  "type": "Feature",
  "properties": {
    "gn:admin1_code":"31",
    "gn:admin2_code":"57.0",
    "gn:asciiname":"Nueva Rosita",
    "gn:country_code":"MX",
    "gn:dem":9,
    "gn:feature_class":"P",
    "gn:feature_code":"PPL",
    "gn:name":"Nueva Rosita",
    "gn:population":0,
    "gn:timezone":"America/Merida",
    "iso:country":"MX",
    "name:ita_x_preferred":[
        "Nueva Rosita"
    ],
    "name:nld_x_preferred":[
        "Nueva Rosita"
    ],
    "name:pol_x_preferred":[
        "Nueva Rosita"
    ],
    "name:rus_x_preferred":[
        "\u041d\u0443\u044d\u0432\u0430-\u0420\u043e\u0441\u0438\u0442\u0430"
    ],
    "name:sco_x_preferred":[
        "Nueva Rosita"
    ],
    "name:spa_x_preferred":[
        "Nueva Rosita"
    ],
    "name:srp_x_preferred":[
        "\u041d\u0443\u0435\u0432\u0430 \u0420\u043e\u0441\u0438\u0442\u0430"
    ],
    "wof:name":"Nueva Rosita",
    "wof:placetype":"locality"
},
  "geometry": {"coordinates":[-88.41555,21.34893],"type":"Point"}
}