{
  "type": "Feature",
  "properties": {
    "gn:admin1_code":"31",
    "gn:admin2_code":"57.0",
    "gn:asciiname":"Nueva Rosita",
    "gn:country_code":"MX",
    "gn:dem":9,
    "gn:feature_class":"P",
    "gn:feature_code":"PPL",
    "gn:name":"Nueva Rosita",
    "gn:population":0,
    "gn:timezone":"America/Merida",
    "iso:country":"MX",
    "name:ara_x_preferred":[
        "\u0646\u0648\u064a\u0641\u0627 \u0631\u0648\u0632\u064a\u062a\u0627"
    ],
    "name:deu_x_preferred":[
        "Nueva Rosita"
    ],
    "name:ell_x_preferred":[
        "\u039d\u03bf\u03c5\u03ad\u03b2\u03b1 \u03a1\u03bf\u03b6\u03af\u03c4\u03b1"
    ],
    "name:fas_x_preferred":[
        "\u0646\u0648\u0626\u0648\u0627 \u0631\u0632\u06cc\u062a\u0627"
    ],
    "name:fra_x_preferred":[
        "Nueva Rosita"
    ],
    "name:heb_x_preferred":[
        "\u05e0\u05d5\u05d0\u05d1\u05d4 \u05e8\u05d5\u05d6\u05d9\u05d8\u05d4"
    ],
    "name:hin_x_preferred":[
        "\u0928\u094d\u092f\u0942\u0935 \u0930\u094b\u091c\u093c\u093f\u091f\u093e"
    ],
    "name:hun_x_preferred":[
        "Nueva Rosita"
    ],
    "name:ind_x_preferred":[
        "Nueva Rosita"
    ],
    "name:ita_x_preferred":[
        "Nueva Rosita"
    ],
    "name:jpn_x_preferred":[
        "\u30cc\u30a8\u30d0\u30fb\u30ed\u30b7\u30fc\u30bf"
    ],
    "name:kor_x_preferred":[
        "\ub204\uc5d0\ubc14 \ub85c\uc9c0\ud0c0"
    ],
    "name:nld_x_preferred":[
        "Nueva Rosita"
    ],
    "name:pol_x_preferred":[
        "Nueva Rosita"
    ],
    "name:por_x_preferred":[
        "Nueva Rosita"
    ],
    "name:rus_x_preferred":[
        "\u041d\u0443\u044d\u0432\u0430-\u0420\u043e\u0441\u0438\u0442\u0430"
    ],
    "name:sco_x_preferred":[
        "Nueva Rosita"
    ],
    "name:spa_x_preferred":[
        "Nueva Rosita"
    ],
    "name:srp_x_preferred":[
        "\u041d\u0443\u0435\u0432\u0430 \u0420\u043e\u0441\u0438\u0442\u0430"
    ],
    "name:tur_x_preferred":[
        "Nueva Rosita"
    ],
    "name:ukr_x_preferred":[
        "\u041d\u0443\u0435\u0432\u0430-\u0420\u043e\u0441\u0456\u0442\u0430"
    ],
    "name:urd_x_preferred":[
        "\u0646\u06cc\u0648\u0627 \u0631\u0648\u0632\u06cc\u0679\u06c1"
    ],
    "name:vie_x_preferred":[
        "Nueva Rosita"
    ],
    "name:zho_cn_x_preferred":[
        "\u65b0\u7f57\u897f\u5854"
    ],
    "name:zho_tw_x_preferred":[
        "\u65b0\u7f85\u897f\u5854"
    ],
    "wof:name":"Nueva Rosita",
    "wof:placetype":"locality"
},
  "geometry": {"coordinates":[-88.41555,21.34893],"type":"Point"}
}