{
  "type": "Feature",
  "properties": {
    "gn:admin1_code":"30",
    "gn:admin2_code":"193.0",
    "gn:asciiname":"Colonia del Proletariado (Pica Pica)",
    "gn:country_code":"MX",
    "gn:dem":45,
    "gn:feature_class":"P",
    "gn:feature_code":"PPL",
    "gn:name":"Colonia del Proletariado (Pica Pica)",
    "gn:population":446,
    "gn:timezone":"America/Mexico_City",
    "iso:country":"MX",
    "wof:name":"Colonia del Proletariado (Pica Pica)",
    "wof:placetype":"locality",
    "wof:population":446
},
  "geometry": {"coordinates":[-96.22750000000001,19.20889],"type":"Point"}
}