{
  "type": "Feature",
  "properties": {
    "gn:admin1_code":"16",
    "gn:admin2_code":"8",
    "gn:asciiname":"La Coralilla",
    "gn:country_code":"MX",
    "gn:dem":849,
    "gn:feature_class":"P",
    "gn:feature_code":"PPL",
    "gn:name":"La Coralilla",
    "gn:population":29,
    "gn:timezone":"America/Mexico_City",
    "iso:country":"MX",
    "wof:name":"La Coralilla",
    "wof:placetype":"locality",
    "wof:population":29
},
  "geometry": {"coordinates":[-102.825,18.30056],"type":"Point"}
}