{
  "type": "Feature",
  "properties": {
    "gn:admin1_code":"27",
    "gn:admin2_code":"3.0",
    "gn:asciiname":"Caparroso",
    "gn:country_code":"MX",
    "gn:dem":5,
    "gn:feature_class":"P",
    "gn:feature_code":"PPL",
    "gn:name":"Caparroso",
    "gn:population":1886,
    "gn:timezone":"America/Mexico_City",
    "iso:country":"MX",
    "name:arg_x_preferred":[
        "Caparroso"
    ],
    "name:bre_x_preferred":[
        "Caparroso"
    ],
    "name:cat_x_preferred":[
        "Caparroso"
    ],
    "name:ceb_x_preferred":[
        "Caparroso"
    ],
    "name:eus_x_preferred":[
        "Caparroso"
    ],
    "name:fra_x_preferred":[
        "Caparroso"
    ],
    "name:glg_x_preferred":[
        "Caparroso"
    ],
    "name:hun_x_preferred":[
        "Caparroso"
    ],
    "name:ita_x_preferred":[
        "Caparroso"
    ],
    "name:msa_x_preferred":[
        "Caparroso"
    ],
    "name:nld_x_preferred":[
        "Caparroso"
    ],
    "name:oci_x_preferred":[
        "Caparroso"
    ],
    "name:pol_x_preferred":[
        "Caparroso"
    ],
    "name:por_x_preferred":[
        "Caparroso"
    ],
    "name:rus_x_preferred":[
        "\u041a\u0430\u043f\u0430\u0440\u0440\u043e\u0441\u043e"
    ],
    "name:spa_x_preferred":[
        "Caparroso"
    ],
    "name:swe_x_preferred":[
        "Caparroso"
    ],
    "name:ukr_x_preferred":[
        "\u041a\u0430\u043f\u0430\u0440\u0440\u043e\u0441\u043e"
    ],
    "name:uzb_x_preferred":[
        "Caparroso"
    ],
    "name:vie_x_preferred":[
        "Caparroso"
    ],
    "name:war_x_preferred":[
        "Caparroso"
    ],
    "name:zho_x_preferred":[
        "\u5361\u5e15\u7f57\u7d22"
    ],
    "wof:name":"Caparroso",
    "wof:placetype":"locality",
    "wof:population":1886
},
  "geometry": {"coordinates":[-92.80361000000001,18.345],"type":"Point"}
}