{
  "type": "Feature",
  "properties": {
    "gn:admin1_code":"27",
    "gn:admin2_code":"3.0",
    "gn:asciiname":"Caparroso",
    "gn:country_code":"MX",
    "gn:dem":5,
    "gn:feature_class":"P",
    "gn:feature_code":"PPL",
    "gn:name":"Caparroso",
    "gn:population":1886,
    "gn:timezone":"America/Mexico_City",
    "iso:country":"MX",
    "wof:name":"Caparroso",
    "wof:placetype":"locality",
    "wof:population":1886
},
  "geometry": {"coordinates":[-92.80361000000001,18.345],"type":"Point"}
}