{
  "type": "Feature",
  "properties": {
    "gn:admin1_code":"5.0",
    "gn:admin2_code":"76.0",
    "gn:asciiname":"Arroyo Frio",
    "gn:country_code":"MX",
    "gn:dem":166,
    "gn:feature_class":"P",
    "gn:feature_code":"PPL",
    "gn:name":"Arroyo Fr\u00edo",
    "gn:population":0,
    "gn:timezone":"America/Mexico_City",
    "iso:country":"MX",
    "name:spa_x_preferred":[
        "Arroyo Fr\u00edo"
    ],
    "wof:name":"Arroyo Frio",
    "wof:placetype":"locality"
},
  "geometry": {"coordinates":[-92.61476999999999,17.35268],"type":"Point"}
}