{
  "type": "Feature",
  "properties": {
    "gn:admin1_code":"14.0",
    "gn:admin2_code":"18.0",
    "gn:asciiname":"Condiro",
    "gn:country_code":"MX",
    "gn:dem":1574,
    "gn:feature_class":"P",
    "gn:feature_code":"PPL",
    "gn:name":"C\u00f3ndiro",
    "gn:population":0,
    "gn:timezone":"America/Mexico_City",
    "iso:country":"MX",
    "name:spa_x_preferred":[
        "C\u00f3ndiro"
    ],
    "name:und_x_variant":[
        "Candiro"
    ],
    "wof:name":"Condiro",
    "wof:placetype":"locality"
},
  "geometry": {"coordinates":[-102.54957,20.4061],"type":"Point"}
}