{
  "type": "Feature",
  "properties": {
    "gn:admin1_code":"22.0",
    "gn:admin2_code":"11.0",
    "gn:asciiname":"El Conejo",
    "gn:country_code":"MX",
    "gn:dem":1979,
    "gn:feature_class":"P",
    "gn:feature_code":"PPL",
    "gn:name":"El Conejo",
    "gn:population":0,
    "gn:timezone":"America/Mexico_City",
    "iso:country":"MX",
    "name:spa_x_preferred":[
        "El Conejo"
    ],
    "wof:name":"El Conejo",
    "wof:placetype":"locality"
},
  "geometry": {"coordinates":[-100.30162,20.6465],"type":"Point"}
}