{
  "type": "Feature",
  "properties": {
    "gn:admin1_code":"11",
    "gn:admin2_code":"23.0",
    "gn:asciiname":"Colonia Emiliano Zapata (La Rasca)",
    "gn:country_code":"MX",
    "gn:dem":1680,
    "gn:feature_class":"P",
    "gn:feature_code":"PPL",
    "gn:name":"Colonia Emiliano Zapata (La Rasca)",
    "gn:population":386,
    "gn:timezone":"America/Mexico_City",
    "iso:country":"MX",
    "wof:name":"Colonia Emiliano Zapata (La Rasca)",
    "wof:placetype":"locality",
    "wof:population":386
},
  "geometry": {"coordinates":[-101.97306,20.36528],"type":"Point"}
}