{
  "type": "Feature",
  "properties": {
    "gn:admin1_code":"10.0",
    "gn:asciiname":"El Penol",
    "gn:country_code":"MX",
    "gn:dem":899,
    "gn:feature_class":"P",
    "gn:feature_code":"PPL",
    "gn:name":"El Pe\u00f1ol",
    "gn:population":0,
    "gn:timezone":"America/Monterrey",
    "iso:country":"MX",
    "name:spa_x_preferred":[
        "El Pe\u00f1ol"
    ],
    "wof:name":"El Penol",
    "wof:placetype":"locality"
},
  "geometry": {"coordinates":[-106.45515,24.40998],"type":"Point"}
}