{
  "type": "Feature",
  "properties": {
    "gn:admin1_code":"27.0",
    "gn:asciiname":"Carmen Segunda Seccion",
    "gn:country_code":"MX",
    "gn:dem":159,
    "gn:feature_class":"P",
    "gn:feature_code":"PPL",
    "gn:name":"Carmen Segunda Secci\u00f3n",
    "gn:population":0,
    "gn:timezone":"America/Mexico_City",
    "iso:country":"MX",
    "name:spa_x_preferred":[
        "Carmen Segunda Secci\u00f3n"
    ],
    "wof:name":"Carmen Segunda Seccion",
    "wof:placetype":"locality"
},
  "geometry": {"coordinates":[-92.49393000000001,17.55355],"type":"Point"}
}