{
  "type": "Feature",
  "properties": {
    "gn:admin1_code":"21",
    "gn:admin2_code":"20",
    "gn:asciiname":"Victoria (Ex-Hacienda Caloca)",
    "gn:country_code":"MX",
    "gn:dem":1979,
    "gn:feature_class":"P",
    "gn:feature_code":"PPL",
    "gn:name":"Victoria (Ex-Hacienda Caloca)",
    "gn:population":13,
    "gn:timezone":"America/Mexico_City",
    "iso:country":"MX",
    "wof:name":"Victoria (Ex-Hacienda Caloca)",
    "wof:placetype":"locality",
    "wof:population":13
},
  "geometry": {"coordinates":[-97.91552,18.83544],"type":"Point"}
}