{
  "type": "Feature",
  "properties": {
    "gn:admin1_code":"13",
    "gn:admin2_code":"34.0",
    "gn:asciiname":"Cuatitlanapa",
    "gn:country_code":"MX",
    "gn:dem":531,
    "gn:feature_class":"P",
    "gn:feature_code":"PPL",
    "gn:name":"Cuatitlanapa",
    "gn:population":73,
    "gn:timezone":"America/Mexico_City",
    "iso:country":"MX",
    "wof:name":"Cuatitlanapa",
    "wof:placetype":"locality",
    "wof:population":73
},
  "geometry": {"coordinates":[-98.7461,21.0856],"type":"Point"}
}