{
  "type": "Feature",
  "properties": {
    "gn:gn_country":"MX",
    "gn:gn_fcode":"PPL",
    "gn:gn_pop":0,
    "iso:country":"MX",
    "name:spa_x_preferred":[
        "San Germ\u00e1n"
    ],
    "qs_pg:aaroncc":"MX",
    "qs_pg:gn_country":"MX",
    "qs_pg:gn_fcode":"PPL",
    "qs_pg:gn_pop":0,
    "qs_pg:name":"San Germ\u00e1n",
    "qs_pg:name_adm0":"M\u00e9xico",
    "qs_pg:name_adm1":"Sonora",
    "qs_pg:photos":64,
    "qs_pg:photos_1k":13,
    "qs_pg:photos_9k":1,
    "qs_pg:photos_9r":2,
    "qs_pg:photos_all":64,
    "qs_pg:photos_sr":2,
    "qs_pg:pop_sr":0,
    "qs_pg:qs_pg_placetype":"locality",
    "qs_pg:qs_pg_placetype_gp":"Town",
    "qs_pg:woe_adm0":23424900,
    "woe:adm0_id":23424900,
    "woe:name_adm0":"M\u00e9xico",
    "woe:name_adm1":"Sonora",
    "woe:placetype":"Town",
    "wof:name":"San Germ\u00e1n",
    "wof:placetype":"locality"
},
  "geometry": {"coordinates":[-110.92954,27.95271],"type":"Point"}
}