{
  "type": "Feature",
  "properties": {
    "gn:admin1_code":"15",
    "gn:admin2_code":"17.0",
    "gn:asciiname":"Las Casitas (Tepexpan)",
    "gn:country_code":"MX",
    "gn:dem":2447,
    "gn:feature_class":"P",
    "gn:feature_code":"PPL",
    "gn:name":"Las Casitas (Tepexpan)",
    "gn:population":69,
    "gn:timezone":"America/Mexico_City",
    "iso:country":"MX",
    "wof:name":"Las Casitas (Tepexpan)",
    "wof:placetype":"locality",
    "wof:population":69
},
  "geometry": {"coordinates":[-98.79664,19.1295],"type":"Point"}
}