{
  "type": "Feature",
  "properties": {
    "gn:admin1_code":"19.0",
    "gn:admin2_code":"11.0",
    "gn:asciiname":"Las Siete Comas",
    "gn:country_code":"MX",
    "gn:dem":254,
    "gn:feature_class":"P",
    "gn:feature_code":"PPL",
    "gn:name":"Las Siete Comas",
    "gn:population":0,
    "gn:timezone":"America/Monterrey",
    "iso:country":"MX",
    "name:spa_x_preferred":[
        "Las Siete Comas"
    ],
    "wof:name":"Las Siete Comas",
    "wof:placetype":"locality"
},
  "geometry": {"coordinates":[-99.59972999999999,26.11452],"type":"Point"}
}