{
  "type": "Feature",
  "properties": {
    "gn:admin1_code":"30",
    "gn:admin2_code":"90.0",
    "gn:asciiname":"El Embudo",
    "gn:country_code":"MX",
    "gn:dem":31,
    "gn:feature_class":"P",
    "gn:feature_code":"PPL",
    "gn:name":"El Embudo",
    "gn:population":54,
    "gn:timezone":"America/Mexico_City",
    "iso:country":"MX",
    "wof:name":"El Embudo",
    "wof:placetype":"locality",
    "wof:population":54
},
  "geometry": {"coordinates":[-96.29611,18.95972],"type":"Point"}
}