{
  "type": "Feature",
  "properties": {
    "gn:admin1_code":"5.0",
    "gn:admin2_code":"104.0",
    "gn:asciiname":"La Trinidad",
    "gn:country_code":"MX",
    "gn:dem":727,
    "gn:feature_class":"P",
    "gn:feature_code":"PPL",
    "gn:name":"La Trinidad",
    "gn:population":0,
    "gn:timezone":"America/Mexico_City",
    "iso:country":"MX",
    "name:spa_x_preferred":[
        "La Trinidad"
    ],
    "wof:name":"La Trinidad",
    "wof:placetype":"locality"
},
  "geometry": {"coordinates":[-92.22255,16.12989],"type":"Point"}
}