{
  "type": "Feature",
  "properties": {
    "gn:admin1_code":"2",
    "gn:admin2_code":"1.0",
    "gn:asciiname":"Tepeyac (Campamento Weste)",
    "gn:country_code":"MX",
    "gn:dem":12,
    "gn:feature_class":"P",
    "gn:feature_code":"PPL",
    "gn:name":"Tepeyac (Campamento Weste)",
    "gn:population":77,
    "gn:timezone":"America/Tijuana",
    "iso:country":"MX",
    "wof:name":"Tepeyac (Campamento Weste)",
    "wof:placetype":"locality",
    "wof:population":77
},
  "geometry": {"coordinates":[-118.30110999999999,28.97333],"type":"Point"}
}