{
  "type": "Feature",
  "properties": {
    "gn:admin1_code":"11",
    "gn:admin2_code":"14.0",
    "gn:asciiname":"Colonia Villas del Sol",
    "gn:country_code":"MX",
    "gn:dem":1917,
    "gn:feature_class":"P",
    "gn:feature_code":"PPL",
    "gn:name":"Colonia Villas del Sol",
    "gn:population":84,
    "gn:timezone":"America/Mexico_City",
    "iso:country":"MX",
    "wof:name":"Colonia Villas del Sol",
    "wof:placetype":"locality",
    "wof:population":84
},
  "geometry": {"coordinates":[-100.87944,21.16278],"type":"Point"}
}