{
  "type": "Feature",
  "properties": {
    "iso:country":"MX",
    "name:hbs_x_preferred":[
        "Lagunas"
    ],
    "name:por_x_preferred":[
        "Lagunas"
    ],
    "name:spa_x_preferred":[
        "Lagunas"
    ],
    "name:unk_x_variant":[
        "Lagunas"
    ],
    "qs:gn_adm0_cc":"MX",
    "qs:gn_fcode":"PPL",
    "qs:gn_local":3514670,
    "qs:gn_nam_loc":"Villahermosa",
    "qs:gn_namadm1":"27",
    "qs:gn_name":"Laguna",
    "qs:local_max":404,
    "qs:local_sum":957,
    "qs:localhoods":7,
    "qs:name":"Lagunas",
    "qs:name_adm0":"M\u00e9xico",
    "qs:name_adm1":"Tabasco",
    "qs:name_adm2":"Centro",
    "qs:name_local":"Villahermosa",
    "qs:photo_max":13,
    "qs:photo_sum":13,
    "qs:placetype":"Suburb",
    "qs:quad_count":1,
    "qs:woe_adm0":23424900,
    "qs:woe_adm1":2346290,
    "qs:woe_adm2":12601618,
    "qs:woe_lau":0,
    "qs:woe_local":150920,
    "qs:woe_ver":"7.10.0",
    "wof:lang":[
        "spa"
    ],
    "wof:name":"Lagunas",
    "wof:placetype":"neighbourhood"
},
  "geometry": {"coordinates":[-92.897644,18.033587],"type":"Point"}
}