{
  "type": "Feature",
  "properties": {
    "gn:admin1_code":"14.0",
    "gn:admin2_code":"15.0",
    "gn:asciiname":"Rancho la Lima",
    "gn:country_code":"MX",
    "gn:dem":908,
    "gn:feature_class":"P",
    "gn:feature_code":"PPL",
    "gn:name":"Rancho la Lima",
    "gn:population":0,
    "gn:timezone":"America/Mexico_City",
    "iso:country":"MX",
    "name:spa_x_preferred":[
        "Rancho la Lima"
    ],
    "wof:name":"Rancho la Lima",
    "wof:placetype":"locality"
},
  "geometry": {"coordinates":[-104.33959,19.76672],"type":"Point"}
}