{
  "type": "Feature",
  "properties": {
    "gn:admin1_code":"25",
    "gn:admin2_code":"3.0",
    "gn:asciiname":"Encinal",
    "gn:country_code":"MX",
    "gn:dem":621,
    "gn:feature_class":"P",
    "gn:feature_code":"PPL",
    "gn:name":"Encinal",
    "gn:population":5,
    "gn:timezone":"America/Mazatlan",
    "iso:country":"MX",
    "name:ceb_x_preferred":[
        "Encinal"
    ],
    "name:deu_x_preferred":[
        "Encinal"
    ],
    "name:fra_x_preferred":[
        "Encinal"
    ],
    "name:ita_x_preferred":[
        "Encinal"
    ],
    "name:nld_x_preferred":[
        "Encinal"
    ],
    "name:pol_x_preferred":[
        "Encinal"
    ],
    "name:spa_x_preferred":[
        "Encinal"
    ],
    "name:swe_x_preferred":[
        "Encinal"
    ],
    "wof:name":"Encinal",
    "wof:placetype":"locality",
    "wof:population":5
},
  "geometry": {"coordinates":[-107.31868,25.78417],"type":"Point"}
}