{
  "type": "Feature",
  "properties": {
    "gn:admin1_code":"14",
    "gn:admin2_code":"61.0",
    "gn:asciiname":"Popotita",
    "gn:country_code":"MX",
    "gn:dem":1587,
    "gn:feature_class":"P",
    "gn:feature_code":"PPL",
    "gn:name":"Popotita",
    "gn:population":145,
    "gn:timezone":"America/Mexico_City",
    "iso:country":"MX",
    "wof:name":"Popotita",
    "wof:placetype":"locality",
    "wof:population":145
},
  "geometry": {"coordinates":[-104.29194,22.04361],"type":"Point"}
}