{
  "type": "Feature",
  "properties": {
    "gn:admin1_code":"32.0",
    "gn:admin2_code":"29.0",
    "gn:asciiname":"Campo Cuatro",
    "gn:country_code":"MX",
    "gn:dem":2132,
    "gn:feature_class":"P",
    "gn:feature_code":"PPL",
    "gn:name":"Campo Cuatro",
    "gn:population":0,
    "gn:timezone":"America/Mexico_City",
    "iso:country":"MX",
    "name:spa_x_preferred":[
        "Campo Cuatro"
    ],
    "name:spa_x_variant":[
        "La Honda"
    ],
    "wof:name":"Campo Cuatro",
    "wof:placetype":"locality"
},
  "geometry": {"coordinates":[-103.40599,24.02154],"type":"Point"}
}