{
  "type": "Feature",
  "properties": {
    "gn:admin1_code":"22",
    "gn:admin2_code":"14.0",
    "gn:asciiname":"Proyeccion 2000",
    "gn:country_code":"MX",
    "gn:dem":1926,
    "gn:feature_class":"P",
    "gn:feature_code":"PPL",
    "gn:name":"Proyecci\u00f3n 2000",
    "gn:population":75,
    "gn:timezone":"America/Mexico_City",
    "iso:country":"MX",
    "name:und_x_variant":[
        "Proyecci\u00f3n 2000"
    ],
    "wof:name":"Proyeccion 2000",
    "wof:placetype":"locality",
    "wof:population":75
},
  "geometry": {"coordinates":[-100.41722,20.63556],"type":"Point"}
}