{
  "type": "Feature",
  "properties": {
    "gn:admin1_code":"15",
    "gn:admin2_code":"5.0",
    "gn:asciiname":"San Antonio Atotonilco",
    "gn:country_code":"MX",
    "gn:dem":2561,
    "gn:feature_class":"P",
    "gn:feature_code":"PPL",
    "gn:name":"San Antonio Atotonilco",
    "gn:population":0,
    "gn:timezone":"America/Mexico_City",
    "iso:country":"MX",
    "name:spa_x_preferred":[
        "San Antonio Atotonilco"
    ],
    "wof:name":"San Antonio Atotonilco",
    "wof:placetype":"locality"
},
  "geometry": {"coordinates":[-99.77737999999999,19.46435],"type":"Point"}
}