{
  "type": "Feature",
  "properties": {
    "gn:admin1_code":"23",
    "gn:admin2_code":"1",
    "gn:asciiname":"Iberostar",
    "gn:country_code":"MX",
    "gn:dem":6,
    "gn:feature_class":"P",
    "gn:feature_code":"PPL",
    "gn:name":"Iberostar",
    "gn:population":52,
    "gn:timezone":"America/Cancun",
    "iso:country":"MX",
    "wof:name":"Iberostar",
    "wof:placetype":"locality",
    "wof:population":52
},
  "geometry": {"coordinates":[-87.02060999999998,20.37014],"type":"Point"}
}