{
  "type": "Feature",
  "properties": {
    "gn:admin1_code":"23",
    "gn:admin2_code":"4.0",
    "gn:asciiname":"Angelo Cortez",
    "gn:country_code":"MX",
    "gn:dem":21,
    "gn:feature_class":"P",
    "gn:feature_code":"PPL",
    "gn:name":"\u00c1ngelo Cortez",
    "gn:population":5,
    "gn:timezone":"America/Cancun",
    "iso:country":"MX",
    "name:und_x_variant":[
        "\u00c1ngelo Cortez"
    ],
    "wof:name":"Angelo Cortez",
    "wof:placetype":"locality",
    "wof:population":5
},
  "geometry": {"coordinates":[-88.42806,18.63083],"type":"Point"}
}