{
  "type": "Feature",
  "properties": {
    "gn:admin1_code":"11.0",
    "gn:admin2_code":"27.0",
    "gn:asciiname":"Conejos",
    "gn:country_code":"MX",
    "gn:dem":1722,
    "gn:feature_class":"P",
    "gn:feature_code":"PPL",
    "gn:name":"Conejos",
    "gn:population":0,
    "gn:timezone":"America/Mexico_City",
    "iso:country":"MX",
    "name:ceb_x_preferred":[
        "Conejos"
    ],
    "name:deu_x_preferred":[
        "Conejos"
    ],
    "name:fra_x_preferred":[
        "Conejos"
    ],
    "name:pol_x_preferred":[
        "Conejos"
    ],
    "name:spa_x_preferred":[
        "Conejos"
    ],
    "name:srp_x_preferred":[
        "\u041a\u043e\u043d\u0435\u0445\u043e\u0441"
    ],
    "name:swe_x_preferred":[
        "Conejos"
    ],
    "wof:name":"Conejos",
    "wof:placetype":"locality"
},
  "geometry": {"coordinates":[-101.09516000000001,20.55571],"type":"Point"}
}