{
  "type": "Feature",
  "properties": {
    "gn:admin1_code":"20",
    "gn:admin2_code":"386.0",
    "gn:asciiname":"Piedra Grande",
    "gn:country_code":"MX",
    "gn:dem":722,
    "gn:feature_class":"P",
    "gn:feature_code":"PPL",
    "gn:name":"Piedra Grande",
    "gn:population":0,
    "gn:timezone":"America/Mexico_City",
    "iso:country":"MX",
    "name:spa_x_preferred":[
        "Piedra Grande"
    ],
    "wof:name":"Piedra Grande",
    "wof:placetype":"locality"
},
  "geometry": {"coordinates":[-97.53601,16.56454],"type":"Point"}
}