{
  "type": "Feature",
  "properties": {
    "gn:admin1_code":"24",
    "gn:admin2_code":"45.0",
    "gn:asciiname":"La Esquina Gongora",
    "gn:country_code":"MX",
    "gn:dem":1764,
    "gn:feature_class":"P",
    "gn:feature_code":"PPL",
    "gn:name":"La Esquina G\u00f3ngora",
    "gn:population":0,
    "gn:timezone":"America/Mexico_City",
    "iso:country":"MX",
    "name:spa_x_preferred":[
        "La Esquina G\u00f3ngora"
    ],
    "name:spa_x_variant":[
        "La Conedra"
    ],
    "wof:name":"La Esquina Gongora",
    "wof:placetype":"locality"
},
  "geometry": {"coordinates":[-100.93477,22.96282],"type":"Point"}
}