{
  "type": "Feature",
  "properties": {
    "gn:admin1_code":"11",
    "gn:admin2_code":"43",
    "gn:asciiname":"Jaboncillos",
    "gn:country_code":"MX",
    "gn:dem":1942,
    "gn:feature_class":"P",
    "gn:feature_code":"PPL",
    "gn:name":"Jaboncillos",
    "gn:population":16,
    "gn:timezone":"America/Mexico_City",
    "iso:country":"MX",
    "wof:name":"Jaboncillos",
    "wof:placetype":"locality",
    "wof:population":16
},
  "geometry": {"coordinates":[-100.2525,21.20194],"type":"Point"}
}