{
  "type": "Feature",
  "properties": {
    "gn:admin1_code":"26.0",
    "gn:admin2_code":"18.0",
    "gn:asciiname":"Huamuchil",
    "gn:country_code":"MX",
    "gn:dem":70,
    "gn:feature_class":"P",
    "gn:feature_code":"PPL",
    "gn:name":"Huam\u00fachil",
    "gn:population":0,
    "gn:timezone":"America/Hermosillo",
    "iso:country":"MX",
    "wof:name":"Huamuchil",
    "wof:placetype":"locality"
},
  "geometry": {"coordinates":[-109.84999999999999,27.88333],"type":"Point"}
}