{
  "type": "Feature",
  "properties": {
    "gn:admin1_code":"21.0",
    "gn:admin2_code":"19.0",
    "gn:asciiname":"Coatepetci",
    "gn:country_code":"MX",
    "gn:dem":1908,
    "gn:feature_class":"P",
    "gn:feature_code":"PPL",
    "gn:name":"Coatepetci",
    "gn:population":0,
    "gn:timezone":"America/Mexico_City",
    "iso:country":"MX",
    "name:spa_x_preferred":[
        "Coatepetci"
    ],
    "wof:name":"Coatepetci",
    "wof:placetype":"locality"
},
  "geometry": {"coordinates":[-98.42747,18.9388],"type":"Point"}
}