{
  "type": "Feature",
  "properties": {
    "gn:admin1_code":"24.0",
    "gn:asciiname":"Cofradia Chica",
    "gn:country_code":"MX",
    "gn:dem":1079,
    "gn:feature_class":"P",
    "gn:feature_code":"PPL",
    "gn:name":"Cofrad\u00eda Chica",
    "gn:population":0,
    "gn:timezone":"America/Mexico_City",
    "iso:country":"MX",
    "name:spa_x_preferred":[
        "Cofrad\u00eda Chica"
    ],
    "wof:name":"Cofradia Chica",
    "wof:placetype":"locality"
},
  "geometry": {"coordinates":[-99.85514999999999,21.89383],"type":"Point"}
}