{
  "type": "Feature",
  "properties": {
    "gn:admin1_code":"30",
    "gn:admin2_code":"9",
    "gn:asciiname":"El Platanar",
    "gn:country_code":"MX",
    "gn:dem":14,
    "gn:feature_class":"P",
    "gn:feature_code":"PPL",
    "gn:name":"El Platanar",
    "gn:population":13,
    "gn:timezone":"America/Mexico_City",
    "iso:country":"MX",
    "wof:name":"El Platanar",
    "wof:placetype":"locality",
    "wof:population":13
},
  "geometry": {"coordinates":[-96.44861,19.79694],"type":"Point"}
}