{
  "type": "Feature",
  "properties": {
    "gn:admin1_code":"30.0",
    "gn:admin2_code":"160.0",
    "gn:asciiname":"Tenango",
    "gn:country_code":"MX",
    "gn:dem":120,
    "gn:feature_class":"P",
    "gn:feature_code":"PPL",
    "gn:name":"Tenango",
    "gn:population":6,
    "gn:timezone":"America/Mexico_City",
    "iso:country":"MX",
    "name:spa_x_preferred":[
        "Tenango"
    ],
    "wof:name":"Tenango",
    "wof:placetype":"locality",
    "wof:population":6
},
  "geometry": {"coordinates":[-97.8475,21.07611],"type":"Point"}
}