{
  "type": "Feature",
  "properties": {
    "gn:admin1_code":"6",
    "gn:admin2_code":"24.0",
    "gn:asciiname":"Los Grajeda",
    "gn:cc2":"MX",
    "gn:country_code":"MX",
    "gn:dem":1528,
    "gn:feature_class":"P",
    "gn:feature_code":"PPL",
    "gn:name":"Los Grajeda",
    "gn:population":0,
    "gn:timezone":"America/Chihuahua",
    "iso:country":"MX",
    "name:und_x_variant":[
        "Grajedas",
        "Los Grajeda"
    ],
    "wof:name":"Los Grajeda",
    "wof:placetype":"locality"
},
  "geometry": {"coordinates":[-106.25,28.26667],"type":"Point"}
}