{
  "type": "Feature",
  "properties": {
    "gn:admin1_code":"16.0",
    "gn:admin2_code":"2.0",
    "gn:asciiname":"Colonia la Paz",
    "gn:country_code":"MX",
    "gn:dem":808,
    "gn:feature_class":"P",
    "gn:feature_code":"PPL",
    "gn:name":"Colonia la Paz",
    "gn:population":0,
    "gn:timezone":"America/Mexico_City",
    "iso:country":"MX",
    "name:spa_x_preferred":[
        "Colonia la Paz"
    ],
    "name:spa_x_variant":[
        "Crucero de Dos Aguas"
    ],
    "wof:name":"Colonia la Paz",
    "wof:placetype":"locality"
},
  "geometry": {"coordinates":[-102.7715,18.79872],"type":"Point"}
}