{
  "type": "Feature",
  "properties": {
    "gn:admin1_code":"3.0",
    "gn:admin2_code":"3.0",
    "gn:asciiname":"Matancita",
    "gn:country_code":"MX",
    "gn:dem":310,
    "gn:feature_class":"P",
    "gn:feature_code":"PPL",
    "gn:name":"Matancita",
    "gn:population":0,
    "gn:timezone":"America/Mazatlan",
    "iso:country":"MX",
    "name:spa_x_preferred":[
        "Matancita"
    ],
    "name:und_x_variant":[
        "Matanc\u00edtas",
        "La Matancitas",
        "La Matancita",
        "Los Llanos"
    ],
    "wof:name":"Matancita",
    "wof:placetype":"locality"
},
  "geometry": {"coordinates":[-110.07344999999999,23.15318],"type":"Point"}
}