{
  "type": "Feature",
  "properties": {
    "gn:admin1_code":"32",
    "gn:admin2_code":"38",
    "gn:asciiname":"Refugio de los Vazquez",
    "gn:country_code":"MX",
    "gn:dem":2344,
    "gn:feature_class":"P",
    "gn:feature_code":"PPL",
    "gn:name":"Refugio de los V\u00e1zquez",
    "gn:population":24,
    "gn:timezone":"America/Mexico_City",
    "iso:country":"MX",
    "name:und_x_variant":[
        "Refugio de los V\u00e1zquez"
    ],
    "wof:name":"Refugio de los Vazquez",
    "wof:placetype":"locality",
    "wof:population":24
},
  "geometry": {"coordinates":[-101.55194,22.25861],"type":"Point"}
}