{
  "type": "Feature",
  "properties": {
    "gn:admin1_code":"12",
    "gn:admin2_code":"59.0",
    "gn:asciiname":"Teo [Restaurante]",
    "gn:country_code":"MX",
    "gn:dem":708,
    "gn:feature_class":"P",
    "gn:feature_code":"PPL",
    "gn:name":"Teo [Restaurante]",
    "gn:population":8,
    "gn:timezone":"America/Mexico_City",
    "iso:country":"MX",
    "wof:name":"Teo [Restaurante]",
    "wof:placetype":"locality",
    "wof:population":8
},
  "geometry": {"coordinates":[-99.55699,18.12007],"type":"Point"}
}