{
  "type": "Feature",
  "properties": {
    "gn:admin1_code":"26.0",
    "gn:admin2_code":"50.0",
    "gn:asciiname":"San Fernando",
    "gn:country_code":"MX",
    "gn:dem":545,
    "gn:feature_class":"P",
    "gn:feature_code":"PPL",
    "gn:name":"San Fernando",
    "gn:population":0,
    "gn:timezone":"America/Hermosillo",
    "iso:country":"MX",
    "name:spa_x_preferred":[
        "San Fernando"
    ],
    "name:und_x_variant":[
        "Fern\u00e1ndez"
    ],
    "wof:name":"San Fernando",
    "wof:placetype":"locality"
},
  "geometry": {"coordinates":[-110.58253999999999,29.72705],"type":"Point"}
}