{
  "type": "Feature",
  "properties": {
    "gn:admin1_code":"2",
    "gn:admin2_code":"3.0",
    "gn:asciiname":"Los Caballos",
    "gn:country_code":"MX",
    "gn:dem":920,
    "gn:feature_class":"P",
    "gn:feature_code":"PPL",
    "gn:name":"Los Caballos",
    "gn:population":8,
    "gn:timezone":"America/Tijuana",
    "iso:country":"MX",
    "wof:name":"Los Caballos",
    "wof:placetype":"locality",
    "wof:population":8
},
  "geometry": {"coordinates":[-116.33,32.41917],"type":"Point"}
}