{
  "type": "Feature",
  "properties": {
    "gn:admin1_code":"30",
    "gn:admin2_code":"151.0",
    "gn:asciiname":"Nicolas",
    "gn:country_code":"MX",
    "gn:dem":3,
    "gn:feature_class":"P",
    "gn:feature_code":"PPL",
    "gn:name":"Nicol\u00e1s",
    "gn:population":5,
    "gn:timezone":"America/Mexico_City",
    "iso:country":"MX",
    "name:und_x_variant":[
        "Nicol\u00e1s",
        "San Nicol\u00e1s",
        "Nicolases"
    ],
    "wof:name":"Nicolas",
    "wof:placetype":"locality",
    "wof:population":5
},
  "geometry": {"coordinates":[-97.41901,21.40026],"type":"Point"}
}