{
  "type": "Feature",
  "properties": {
    "gn:admin1_code":"30",
    "gn:admin2_code":"151.0",
    "gn:asciiname":"Nicolas",
    "gn:country_code":"MX",
    "gn:dem":3,
    "gn:feature_class":"P",
    "gn:feature_code":"PPL",
    "gn:name":"Nicol\u00e1s",
    "gn:population":5,
    "gn:timezone":"America/Mexico_City",
    "iso:country":"MX",
    "name:ceb_x_preferred":[
        "Nicolas"
    ],
    "name:deu_x_preferred":[
        "Nicolas"
    ],
    "name:fin_x_preferred":[
        "Nicolas"
    ],
    "name:fra_x_preferred":[
        "Nicolas"
    ],
    "name:ita_x_preferred":[
        "Nicolas"
    ],
    "name:jpn_x_preferred":[
        "\u30cb\u30b3\u30e9\u30b9"
    ],
    "name:nld_x_preferred":[
        "Nicolas"
    ],
    "name:ron_x_preferred":[
        "Nicolas"
    ],
    "name:swe_x_preferred":[
        "Nicolas"
    ],
    "name:und_x_variant":[
        "Nicol\u00e1s",
        "San Nicol\u00e1s",
        "Nicolases"
    ],
    "name:zho_x_preferred":[
        "\u5c3c\u53e4\u62c9\u65af"
    ],
    "wof:name":"Nicolas",
    "wof:placetype":"locality",
    "wof:population":5
},
  "geometry": {"coordinates":[-97.41901,21.40026],"type":"Point"}
}