{
  "type": "Feature",
  "properties": {
    "gn:admin1_code":"15",
    "gn:admin2_code":"114.0",
    "gn:asciiname":"Sitio Ejido",
    "gn:country_code":"MX",
    "gn:dem":2595,
    "gn:feature_class":"P",
    "gn:feature_code":"PPL",
    "gn:name":"Sitio Ejido",
    "gn:population":2725,
    "gn:timezone":"America/Mexico_City",
    "iso:country":"MX",
    "wof:name":"Sitio Ejido",
    "wof:placetype":"locality",
    "wof:population":2725
},
  "geometry": {"coordinates":[-99.90069,19.45334],"type":"Point"}
}