{
  "type": "Feature",
  "properties": {
    "gn:admin1_code":"20.0",
    "gn:asciiname":"Paso Armadillo",
    "gn:country_code":"MX",
    "gn:dem":123,
    "gn:feature_class":"P",
    "gn:feature_code":"PPL",
    "gn:name":"Paso Armadillo",
    "gn:population":0,
    "gn:timezone":"America/Mexico_City",
    "iso:country":"MX",
    "name:spa_x_preferred":[
        "Paso Armadillo"
    ],
    "wof:name":"Paso Armadillo",
    "wof:placetype":"locality"
},
  "geometry": {"coordinates":[-96.50991999999999,17.88677999999999],"type":"Point"}
}