{
  "type": "Feature",
  "properties": {
    "gn:admin1_code":"24",
    "gn:admin2_code":"57.0",
    "gn:asciiname":"Atlamaxatl",
    "gn:country_code":"MX",
    "gn:dem":179,
    "gn:feature_class":"P",
    "gn:feature_code":"PPL",
    "gn:name":"Atlamax\u00e1tl",
    "gn:population":885,
    "gn:timezone":"America/Mexico_City",
    "iso:country":"MX",
    "name:und_x_variant":[
        "Atlamax\u00e1tl"
    ],
    "wof:name":"Atlamaxatl",
    "wof:placetype":"locality",
    "wof:population":885
},
  "geometry": {"coordinates":[-98.82528000000001,21.31083],"type":"Point"}
}