{
  "type": "Feature",
  "properties": {
    "gn:admin1_code":"13",
    "gn:admin2_code":"24.0",
    "gn:asciiname":"La Bolsa",
    "gn:country_code":"MX",
    "gn:dem":2090,
    "gn:feature_class":"P",
    "gn:feature_code":"PPL",
    "gn:name":"La Bolsa",
    "gn:population":106,
    "gn:timezone":"America/Mexico_City",
    "iso:country":"MX",
    "wof:name":"La Bolsa",
    "wof:placetype":"locality",
    "wof:population":106
},
  "geometry": {"coordinates":[-98.57665,20.23151],"type":"Point"}
}