{
  "type": "Feature",
  "properties": {
    "gn:admin1_code":"30",
    "gn:admin2_code":"195.0",
    "gn:asciiname":"Cuxtepec",
    "gn:country_code":"MX",
    "gn:dem":2285,
    "gn:feature_class":"P",
    "gn:feature_code":"PPL",
    "gn:name":"Cuxtepec",
    "gn:population":244,
    "gn:timezone":"America/Mexico_City",
    "iso:country":"MX",
    "wof:name":"Cuxtepec",
    "wof:placetype":"locality",
    "wof:population":244
},
  "geometry": {"coordinates":[-97.14139,18.64889],"type":"Point"}
}