{
  "type": "Feature",
  "properties": {
    "gn:admin1_code":"11.0",
    "gn:admin2_code":"26.0",
    "gn:asciiname":"Velenciana de Gavia",
    "gn:country_code":"MX",
    "gn:dem":1766,
    "gn:feature_class":"P",
    "gn:feature_code":"PPL",
    "gn:name":"Velenciana de Gavia",
    "gn:population":0,
    "gn:timezone":"America/Mexico_City",
    "iso:country":"MX",
    "name:spa_x_preferred":[
        "Velenciana de Gavia"
    ],
    "name:und_x_variant":[
        "Valenciana de Gavia"
    ],
    "wof:name":"Velenciana de Gavia",
    "wof:placetype":"locality"
},
  "geometry": {"coordinates":[-101.59627,20.85371],"type":"Point"}
}