{
  "type": "Feature",
  "properties": {
    "gn:admin1_code":"26",
    "gn:admin2_code":"3.0",
    "gn:asciiname":"Paredones",
    "gn:country_code":"MX",
    "gn:dem":242,
    "gn:feature_class":"P",
    "gn:feature_code":"PPL",
    "gn:name":"Paredones",
    "gn:population":0,
    "gn:timezone":"America/Hermosillo",
    "iso:country":"MX",
    "name:bak_x_preferred":[
        "\u041f\u0430\u0440\u0435\u0434\u043e\u043d\u0435\u0441"
    ],
    "name:ceb_x_preferred":[
        "Paredones"
    ],
    "name:eus_x_preferred":[
        "Paredones"
    ],
    "name:fas_x_preferred":[
        "\u067e\u0627\u0631\u062f\u0648\u0646\u0633"
    ],
    "name:fra_x_preferred":[
        "Paredones"
    ],
    "name:glg_x_preferred":[
        "Paredones"
    ],
    "name:ita_x_preferred":[
        "Paredones"
    ],
    "name:kor_x_preferred":[
        "\ud30c\ub808\ub3c4\ub124\uc2a4"
    ],
    "name:nld_x_preferred":[
        "Paredones"
    ],
    "name:por_x_preferred":[
        "Paredones"
    ],
    "name:ron_x_preferred":[
        "Paredones"
    ],
    "name:rus_x_preferred":[
        "\u041f\u0430\u0440\u0435\u0434\u043e\u043d\u0435\u0441"
    ],
    "name:sco_x_preferred":[
        "Paredones"
    ],
    "name:spa_x_preferred":[
        "Paredones"
    ],
    "name:swe_x_preferred":[
        "Paredones"
    ],
    "name:und_x_variant":[
        "Rancho Paredones",
        "Paredones"
    ],
    "name:zho_x_preferred":[
        "\u5e15\u96f7\u591a\u5167\u65af"
    ],
    "wof:name":"Paredones",
    "wof:placetype":"locality"
},
  "geometry": {"coordinates":[-108.94580999999999,26.86201],"type":"Point"}
}