{
  "type": "Feature",
  "properties": {
    "gn:admin1_code":"20",
    "gn:admin2_code":"361.0",
    "gn:asciiname":"Santa Catalina Quieri",
    "gn:country_code":"MX",
    "gn:dem":1965,
    "gn:feature_class":"P",
    "gn:feature_code":"PPLA2",
    "gn:name":"Santa Catalina Quieri",
    "gn:population":0,
    "gn:timezone":"America/Mexico_City",
    "iso:country":"MX",
    "name:spa_x_preferred":[
        "Quieri"
    ],
    "name:spa_x_variant":[
        "Santa Mar\u00eda",
        "Santa Catalina Quieri"
    ],
    "wof:name":"Santa Catalina Quieri",
    "wof:placetype":"locality"
},
  "geometry": {"coordinates":[-96.26618000000001,16.32141],"type":"Point"}
}