{
  "type": "Feature",
  "properties": {
    "gn:admin1_code":"30",
    "gn:admin2_code":"122.0",
    "gn:asciiname":"El Mangal",
    "gn:country_code":"MX",
    "gn:dem":10,
    "gn:feature_class":"P",
    "gn:feature_code":"PPL",
    "gn:name":"El Mangal",
    "gn:population":0,
    "gn:timezone":"America/Mexico_City",
    "iso:country":"MX",
    "name:spa_x_preferred":[
        "El Mangal"
    ],
    "wof:name":"El Mangal",
    "wof:placetype":"locality"
},
  "geometry": {"coordinates":[-94.66623,18.18206],"type":"Point"}
}