{
  "type": "Feature",
  "properties": {
    "gn:admin1_code":"7",
    "gn:admin2_code":"33.0",
    "gn:asciiname":"Santa Sofia",
    "gn:country_code":"MX",
    "gn:dem":1100,
    "gn:feature_class":"P",
    "gn:feature_code":"PPL",
    "gn:name":"Santa Sof\u00eda",
    "gn:population":0,
    "gn:timezone":"America/Monterrey",
    "iso:country":"MX",
    "name:spa_x_preferred":[
        "Santa Sof\u00eda"
    ],
    "wof:name":"Santa Sofia",
    "wof:placetype":"locality"
},
  "geometry": {"coordinates":[-102.9606,25.65137],"type":"Point"}
}