{
  "type": "Feature",
  "properties": {
    "gn:admin1_code":"4",
    "gn:admin2_code":"4.0",
    "gn:asciiname":"San Juan Carpizo",
    "gn:country_code":"MX",
    "gn:dem":11,
    "gn:feature_class":"P",
    "gn:feature_code":"PPL",
    "gn:name":"San Juan Carpizo",
    "gn:population":355,
    "gn:timezone":"America/Merida",
    "iso:country":"MX",
    "wof:name":"San Juan Carpizo",
    "wof:placetype":"locality",
    "wof:population":355
},
  "geometry": {"coordinates":[-90.46972,19.30028],"type":"Point"}
}