{
  "type": "Feature",
  "properties": {
    "gn:admin1_code":"4.0",
    "gn:admin2_code":"3.0",
    "gn:asciiname":"El Desengano",
    "gn:country_code":"MX",
    "gn:dem":4,
    "gn:feature_class":"P",
    "gn:feature_code":"PPL",
    "gn:name":"El Desenga\u00f1o",
    "gn:population":0,
    "gn:timezone":"America/Merida",
    "iso:country":"MX",
    "name:spa_x_preferred":[
        "El Desenga\u00f1o"
    ],
    "wof:name":"El Desengano",
    "wof:placetype":"locality"
},
  "geometry": {"coordinates":[-91.76841,18.65374],"type":"Point"}
}