{
  "type": "Feature",
  "properties": {
    "gn:admin1_code":"18",
    "gn:admin2_code":"12.0",
    "gn:asciiname":"La Convalecencia",
    "gn:country_code":"MX",
    "gn:dem":110,
    "gn:feature_class":"P",
    "gn:feature_code":"PPL",
    "gn:name":"La Convalecencia",
    "gn:population":5,
    "gn:timezone":"America/Mazatlan",
    "iso:country":"MX",
    "wof:name":"La Convalecencia",
    "wof:placetype":"locality",
    "wof:population":5
},
  "geometry": {"coordinates":[-105.12778,21.59972],"type":"Point"}
}