{
  "type": "Feature",
  "properties": {
    "gn:admin1_code":"31",
    "gn:admin2_code":"32.0",
    "gn:asciiname":"Kancab-dzonot",
    "gn:country_code":"MX",
    "gn:dem":20,
    "gn:feature_class":"P",
    "gn:feature_code":"PPL",
    "gn:name":"Kancab-dzonot",
    "gn:population":0,
    "gn:timezone":"America/Merida",
    "iso:country":"MX",
    "name:spa_x_preferred":[
        "Kancab-dzonot"
    ],
    "wof:name":"Kancab-dzonot",
    "wof:placetype":"locality"
},
  "geometry": {"coordinates":[-88.46092,20.99258],"type":"Point"}
}