{
  "type": "Feature",
  "properties": {
    "gn:admin1_code":"16",
    "gn:admin2_code":"57.0",
    "gn:asciiname":"El Capire",
    "gn:country_code":"MX",
    "gn:dem":852,
    "gn:feature_class":"P",
    "gn:feature_code":"PPL",
    "gn:name":"El Capire",
    "gn:population":0,
    "gn:timezone":"America/Mexico_City",
    "iso:country":"MX",
    "name:spa_x_preferred":[
        "El Capire"
    ],
    "wof:name":"El Capire",
    "wof:placetype":"locality"
},
  "geometry": {"coordinates":[-101.21630999999999,19.16006],"type":"Point"}
}