{
  "type": "Feature",
  "properties": {
    "gn:admin1_code":"14.0",
    "gn:admin2_code":"35.0",
    "gn:asciiname":"Las Barreras",
    "gn:country_code":"MX",
    "gn:dem":1869,
    "gn:feature_class":"P",
    "gn:feature_code":"PPL",
    "gn:name":"Las Barreras",
    "gn:population":0,
    "gn:timezone":"America/Mexico_City",
    "iso:country":"MX",
    "name:spa_x_preferred":[
        "Las Barreras"
    ],
    "wof:name":"Las Barreras",
    "wof:placetype":"locality"
},
  "geometry": {"coordinates":[-102.25897999999999,21.50564],"type":"Point"}
}