{
  "type": "Feature",
  "properties": {
    "gn:admin1_code":"19",
    "gn:admin2_code":"5.0",
    "gn:asciiname":"Bernabe",
    "gn:country_code":"MX",
    "gn:dem":239,
    "gn:feature_class":"P",
    "gn:feature_code":"PPL",
    "gn:name":"Bernab\u00e9",
    "gn:population":0,
    "gn:timezone":"America/Matamoros",
    "iso:country":"MX",
    "name:spa_x_preferred":[
        "Bernab\u00e9"
    ],
    "name:und_x_variant":[
        "Tanque Bernab\u00e9"
    ],
    "wof:name":"Bernabe",
    "wof:placetype":"locality"
},
  "geometry": {"coordinates":[-100.31771999999999,27.52418],"type":"Point"}
}