{
  "type": "Feature",
  "properties": {
    "gn:admin1_code":"21.0",
    "gn:admin2_code":"194.0",
    "gn:asciiname":"La Tinta",
    "gn:country_code":"MX",
    "gn:dem":124,
    "gn:feature_class":"P",
    "gn:feature_code":"PPL",
    "gn:name":"La Tinta",
    "gn:population":0,
    "gn:timezone":"America/Mexico_City",
    "iso:country":"MX",
    "name:spa_x_preferred":[
        "La Tinta"
    ],
    "wof:name":"La Tinta",
    "wof:placetype":"locality"
},
  "geometry": {"coordinates":[-97.63827999999999,20.51985],"type":"Point"}
}