{
  "type": "Feature",
  "properties": {
    "gn:admin1_code":"20",
    "gn:admin2_code":"516",
    "gn:asciiname":"El Naranjo",
    "gn:country_code":"MX",
    "gn:dem":904,
    "gn:feature_class":"P",
    "gn:feature_code":"PPL",
    "gn:name":"El Naranjo",
    "gn:population":26,
    "gn:timezone":"America/Mexico_City",
    "iso:country":"MX",
    "wof:name":"El Naranjo",
    "wof:placetype":"locality",
    "wof:population":26
},
  "geometry": {"coordinates":[-97.28417,16.56694],"type":"Point"}
}