{
  "type": "Feature",
  "properties": {
    "gn:admin1_code":"3",
    "gn:admin2_code":"1.0",
    "gn:asciiname":"Las Animas",
    "gn:country_code":"MX",
    "gn:dem":20,
    "gn:feature_class":"P",
    "gn:feature_code":"PPL",
    "gn:name":"Las Animas",
    "gn:population":0,
    "gn:timezone":"America/Mazatlan",
    "iso:country":"MX",
    "name:spa_x_preferred":[
        "Las Animas"
    ],
    "wof:name":"Las Animas",
    "wof:placetype":"locality"
},
  "geometry": {"coordinates":[-112.02767,25.68828],"type":"Point"}
}