{
  "type": "Feature",
  "properties": {
    "gn:admin1_code":"25",
    "gn:admin2_code":"6.0",
    "gn:asciiname":"Campo San Miguel",
    "gn:country_code":"MX",
    "gn:dem":7,
    "gn:feature_class":"P",
    "gn:feature_code":"PPL",
    "gn:name":"Campo San Miguel",
    "gn:population":9,
    "gn:timezone":"America/Mazatlan",
    "iso:country":"MX",
    "wof:name":"Campo San Miguel",
    "wof:placetype":"locality",
    "wof:population":9
},
  "geometry": {"coordinates":[-107.53246,24.55371],"type":"Point"}
}