{
  "type": "Feature",
  "properties": {
    "gn:admin1_code":"6",
    "gn:admin2_code":"20.0",
    "gn:asciiname":"La Finca",
    "gn:country_code":"MX",
    "gn:dem":1394,
    "gn:feature_class":"P",
    "gn:feature_code":"PPL",
    "gn:name":"La Finca",
    "gn:population":0,
    "gn:timezone":"America/Chihuahua",
    "iso:country":"MX",
    "name:spa_x_preferred":[
        "La Finca"
    ],
    "wof:name":"La Finca",
    "wof:placetype":"locality"
},
  "geometry": {"coordinates":[-108.31189000000001,27.71742],"type":"Point"}
}