{
  "type": "Feature",
  "properties": {
    "gn:admin1_code":"16.0",
    "gn:admin2_code":"15.0",
    "gn:asciiname":"Las Penas",
    "gn:country_code":"MX",
    "gn:dem":1670,
    "gn:feature_class":"P",
    "gn:feature_code":"PPL",
    "gn:name":"Las Pe\u00f1as",
    "gn:population":0,
    "gn:timezone":"America/Mexico_City",
    "iso:country":"MX",
    "name:spa_x_preferred":[
        "Las Pe\u00f1as"
    ],
    "wof:name":"Las Penas",
    "wof:placetype":"locality"
},
  "geometry": {"coordinates":[-103.06269,18.77571],"type":"Point"}
}