{
  "type": "Feature",
  "properties": {
    "gn:admin1_code":"20",
    "gn:admin2_code":"95.0",
    "gn:asciiname":"Agua del Sol",
    "gn:country_code":"MX",
    "gn:dem":2381,
    "gn:feature_class":"P",
    "gn:feature_code":"PPL",
    "gn:name":"Agua del Sol",
    "gn:population":57,
    "gn:timezone":"America/Mexico_City",
    "iso:country":"MX",
    "wof:name":"Agua del Sol",
    "wof:placetype":"locality",
    "wof:population":57
},
  "geometry": {"coordinates":[-96.53361,16.21083],"type":"Point"}
}