{
  "type": "Feature",
  "properties": {
    "gn:admin1_code":"6",
    "gn:admin2_code":"63",
    "gn:asciiname":"La Salitrera",
    "gn:country_code":"MX",
    "gn:dem":1815,
    "gn:feature_class":"P",
    "gn:feature_code":"PPL",
    "gn:name":"La Salitrera",
    "gn:population":30,
    "gn:timezone":"America/Chihuahua",
    "iso:country":"MX",
    "wof:name":"La Salitrera",
    "wof:placetype":"locality",
    "wof:population":30
},
  "geometry": {"coordinates":[-108.34885,28.41184],"type":"Point"}
}