{
  "type": "Feature",
  "properties": {
    "gn:admin1_code":"12",
    "gn:admin2_code":"16",
    "gn:asciiname":"Coacoyul",
    "gn:country_code":"MX",
    "gn:dem":609,
    "gn:feature_class":"P",
    "gn:feature_code":"PPL",
    "gn:name":"Coacoy\u00fal",
    "gn:population":11,
    "gn:timezone":"America/Mexico_City",
    "iso:country":"MX",
    "name:und_x_variant":[
        "Coacoy\u00fal"
    ],
    "wof:name":"Coacoyul",
    "wof:placetype":"locality",
    "wof:population":11
},
  "geometry": {"coordinates":[-101.75251,18.18018],"type":"Point"}
}