{
  "type": "Feature",
  "properties": {
    "gn:admin1_code":"15.0",
    "gn:asciiname":"San Francisco Tepojaco",
    "gn:country_code":"MX",
    "gn:dem":2337,
    "gn:feature_class":"P",
    "gn:feature_code":"PPL",
    "gn:name":"San Francisco Tepojaco",
    "gn:population":0,
    "gn:timezone":"America/Mexico_City",
    "iso:country":"MX",
    "name:spa_x_preferred":[
        "San Francisco Tepojaco"
    ],
    "name:spa_x_variant":[
        "Tepojaco"
    ],
    "wof:name":"San Francisco Tepojaco",
    "wof:placetype":"locality"
},
  "geometry": {"coordinates":[-99.24672,19.64912],"type":"Point"}
}