{
  "type": "Feature",
  "properties": {
    "gn:admin1_code":"30",
    "gn:admin2_code":"109.0",
    "gn:asciiname":"El Pozon",
    "gn:country_code":"MX",
    "gn:dem":387,
    "gn:feature_class":"P",
    "gn:feature_code":"PPL",
    "gn:name":"El Poz\u00f3n",
    "gn:population":0,
    "gn:timezone":"America/Mexico_City",
    "iso:country":"MX",
    "name:spa_x_preferred":[
        "El Poz\u00f3n"
    ],
    "wof:name":"El Pozon",
    "wof:placetype":"locality"
},
  "geometry": {"coordinates":[-96.86982,19.89192],"type":"Point"}
}