{
  "type": "Feature",
  "properties": {
    "gn:admin1_code":"9",
    "gn:admin2_code":"12.0",
    "gn:asciiname":"Colonia Aguayoto",
    "gn:country_code":"MX",
    "gn:dem":3129,
    "gn:feature_class":"P",
    "gn:feature_code":"PPL",
    "gn:name":"Colonia Aguayoto",
    "gn:population":284,
    "gn:timezone":"America/Mexico_City",
    "iso:country":"MX",
    "wof:name":"Colonia Aguayoto",
    "wof:placetype":"locality",
    "wof:population":284
},
  "geometry": {"coordinates":[-99.21693999999999,19.20528],"type":"Point"}
}