{
  "type": "Feature",
  "properties": {
    "gn:admin1_code":"20",
    "gn:admin2_code":"498.0",
    "gn:asciiname":"Plan de Mazate",
    "gn:country_code":"MX",
    "gn:dem":146,
    "gn:feature_class":"P",
    "gn:feature_code":"PPL",
    "gn:name":"Plan de Mazate",
    "gn:population":6,
    "gn:timezone":"America/Mexico_City",
    "iso:country":"MX",
    "wof:name":"Plan de Mazate",
    "wof:placetype":"locality",
    "wof:population":6
},
  "geometry": {"coordinates":[-95.57222,17.41222],"type":"Point"}
}