{
  "type": "Feature",
  "properties": {
    "gn:admin1_code":"30",
    "gn:admin2_code":"58.0",
    "gn:asciiname":"El Barranco",
    "gn:country_code":"MX",
    "gn:dem":144,
    "gn:feature_class":"P",
    "gn:feature_code":"PPL",
    "gn:name":"El Barranco",
    "gn:population":0,
    "gn:timezone":"America/Mexico_City",
    "iso:country":"MX",
    "name:spa_x_preferred":[
        "El Barranco"
    ],
    "name:spa_x_variant":[
        "La Zorra"
    ],
    "wof:name":"El Barranco",
    "wof:placetype":"locality"
},
  "geometry": {"coordinates":[-98.09524,21.15377],"type":"Point"}
}