{
  "type": "Feature",
  "properties": {
    "gn:admin1_code":"32",
    "gn:admin2_code":"5.0",
    "gn:asciiname":"Los Isabeles (Maria del Consuelo Sotero)",
    "gn:country_code":"MX",
    "gn:dem":2193,
    "gn:feature_class":"P",
    "gn:feature_code":"PPL",
    "gn:name":"Los Isabeles (Mar\u00eda del Consuelo Sotero)",
    "gn:population":6,
    "gn:timezone":"America/Mexico_City",
    "iso:country":"MX",
    "name:und_x_variant":[
        "Los Isabeles (Mar\u00eda del Consuelo Sotero)"
    ],
    "wof:name":"Los Isabeles (Maria del Consuelo Sotero)",
    "wof:placetype":"locality",
    "wof:population":6
},
  "geometry": {"coordinates":[-102.71861,22.90111],"type":"Point"}
}