{
  "type": "Feature",
  "properties": {
    "gn:admin1_code":"13",
    "gn:admin2_code":"25.0",
    "gn:asciiname":"Tempexquisco",
    "gn:country_code":"MX",
    "gn:dem":133,
    "gn:feature_class":"P",
    "gn:feature_code":"PPL",
    "gn:name":"Tempexquisco",
    "gn:population":62,
    "gn:timezone":"America/Mexico_City",
    "iso:country":"MX",
    "name:spa_x_preferred":[
        "Tempexquisco"
    ],
    "wof:name":"Tempexquisco",
    "wof:placetype":"locality",
    "wof:population":62
},
  "geometry": {"coordinates":[-98.20523,21.04732000000001],"type":"Point"}
}