{
  "type": "Feature",
  "properties": {
    "gn:admin1_code":"17",
    "gn:admin2_code":"6",
    "gn:asciiname":"Tierra y Libertad",
    "gn:country_code":"MX",
    "gn:dem":1349,
    "gn:feature_class":"P",
    "gn:feature_code":"PPL",
    "gn:name":"Tierra y Libertad",
    "gn:population":42,
    "gn:timezone":"America/Mexico_City",
    "iso:country":"MX",
    "wof:name":"Tierra y Libertad",
    "wof:placetype":"locality",
    "wof:population":42
},
  "geometry": {"coordinates":[-98.93472,18.83111],"type":"Point"}
}