{
  "type": "Feature",
  "properties": {
    "gn:admin1_code":"24.0",
    "gn:admin2_code":"13.0",
    "gn:asciiname":"La Flor",
    "gn:country_code":"MX",
    "gn:dem":222,
    "gn:feature_class":"P",
    "gn:feature_code":"PPL",
    "gn:name":"La Flor",
    "gn:population":0,
    "gn:timezone":"America/Mexico_City",
    "iso:country":"MX",
    "name:spa_x_preferred":[
        "La Flor"
    ],
    "wof:name":"La Flor",
    "wof:placetype":"locality"
},
  "geometry": {"coordinates":[-99.1816,22.12182],"type":"Point"}
}