{
  "type": "Feature",
  "properties": {
    "gn:admin1_code":"20",
    "gn:admin2_code":"52.0",
    "gn:asciiname":"Magdalena Tequisistlan",
    "gn:country_code":"MX",
    "gn:dem":204,
    "gn:feature_class":"P",
    "gn:feature_code":"PPLA2",
    "gn:name":"Magdalena Tequisistl\u00e1n",
    "gn:population":0,
    "gn:timezone":"America/Mexico_City",
    "iso:country":"MX",
    "name:ceb_x_preferred":[
        "Magdalena Tequisistl\u00e1n"
    ],
    "name:epo_x_preferred":[
        "Magdalena Tequisistl\u00e1n"
    ],
    "name:eus_x_preferred":[
        "Magdalena Tequisistl\u00e1n"
    ],
    "name:ita_x_preferred":[
        "Magdalena Tequisistl\u00e1n"
    ],
    "name:rus_x_preferred":[
        "\u041c\u0430\u0433\u0434\u0430\u043b\u0435\u043d\u0430-\u0422\u0435\u043a\u0438\u0441\u0438\u0441\u0442\u043b\u0430\u043d"
    ],
    "name:sco_x_preferred":[
        "Magdalena Tequisistl\u00e1n"
    ],
    "name:spa_x_preferred":[
        "Mixtequilla"
    ],
    "name:spa_x_variant":[
        "Magdalena Tequistl\u00e1n",
        "Magdalena Tequisistl\u00e1n"
    ],
    "name:srp_x_preferred":[
        "\u041e\u043f\u0448\u0442\u0438\u043d\u0430 \u041c\u0430\u0433\u0434\u0430\u043b\u0435\u043d\u0430 \u0422\u0435\u043a\u0438\u0441\u0438\u0441\u0442\u043b\u0430\u043d"
    ],
    "name:swe_x_preferred":[
        "Magdalena Tequisistl\u00e1n"
    ],
    "name:vie_x_preferred":[
        "Magdalena Tequisistl\u00e1n"
    ],
    "wof:name":"Magdalena Tequisistlan",
    "wof:placetype":"locality"
},
  "geometry": {"coordinates":[-95.60204,16.39929],"type":"Point"}
}