{
  "type": "Feature",
  "properties": {
    "gn:admin1_code":"20",
    "gn:admin2_code":"52.0",
    "gn:asciiname":"Magdalena Tequisistlan",
    "gn:country_code":"MX",
    "gn:dem":204,
    "gn:feature_class":"P",
    "gn:feature_code":"PPLA2",
    "gn:name":"Magdalena Tequisistl\u00e1n",
    "gn:population":0,
    "gn:timezone":"America/Mexico_City",
    "iso:country":"MX",
    "name:spa_x_preferred":[
        "Mixtequilla"
    ],
    "name:spa_x_variant":[
        "Magdalena Tequistl\u00e1n",
        "Magdalena Tequisistl\u00e1n"
    ],
    "wof:name":"Magdalena Tequisistlan",
    "wof:placetype":"locality"
},
  "geometry": {"coordinates":[-95.60204,16.39929],"type":"Point"}
}