{
  "type": "Feature",
  "properties": {
    "gn:admin1_code":"12",
    "gn:admin2_code":"39.0",
    "gn:asciiname":"El Tepehuaje",
    "gn:cc2":"MX",
    "gn:country_code":"MX",
    "gn:dem":320,
    "gn:feature_class":"P",
    "gn:feature_code":"PPL",
    "gn:name":"El Tepehuaje",
    "gn:population":131,
    "gn:timezone":"America/Mexico_City",
    "iso:country":"MX",
    "name:und_x_variant":[
        "El Tepeguaje",
        "El Tepehuaje"
    ],
    "wof:name":"El Tepehuaje",
    "wof:placetype":"locality",
    "wof:population":131
},
  "geometry": {"coordinates":[-99.4975,17.10666],"type":"Point"}
}