{
  "type": "Feature",
  "properties": {
    "gn:admin1_code":"30",
    "gn:admin2_code":"77.0",
    "gn:asciiname":"Oscar Pitol Zamate",
    "gn:country_code":"MX",
    "gn:dem":84,
    "gn:feature_class":"P",
    "gn:feature_code":"PPL",
    "gn:name":"Oscar Pitol Zamate",
    "gn:population":6,
    "gn:timezone":"America/Mexico_City",
    "iso:country":"MX",
    "wof:name":"Oscar Pitol Zamate",
    "wof:placetype":"locality",
    "wof:population":6
},
  "geometry": {"coordinates":[-95.65278000000001,17.93417],"type":"Point"}
}