{
  "type": "Feature",
  "properties": {
    "gn:admin1_code":"4",
    "gn:admin2_code":"9.0",
    "gn:asciiname":"El Encanto",
    "gn:country_code":"MX",
    "gn:dem":26,
    "gn:feature_class":"P",
    "gn:feature_code":"PPL",
    "gn:name":"El Encanto",
    "gn:population":5,
    "gn:timezone":"America/Merida",
    "iso:country":"MX",
    "wof:name":"El Encanto",
    "wof:placetype":"locality",
    "wof:population":5
},
  "geometry": {"coordinates":[-90.98778,18.525],"type":"Point"}
}