{
  "type": "Feature",
  "properties": {
    "gn:admin1_code":"30",
    "gn:admin2_code":"143.0",
    "gn:asciiname":"Bonanza",
    "gn:country_code":"MX",
    "gn:dem":381,
    "gn:feature_class":"P",
    "gn:feature_code":"PPL",
    "gn:name":"Bonanza",
    "gn:population":5,
    "gn:timezone":"America/Mexico_City",
    "iso:country":"MX",
    "name:afr_x_preferred":[
        "Bonanza"
    ],
    "name:ara_x_preferred":[
        "\u0628\u0648\u0646\u0627\u0646\u0632\u0627"
    ],
    "name:ast_x_preferred":[
        "Bonanza"
    ],
    "name:dan_x_preferred":[
        "Br\u00f8drene Cartwright"
    ],
    "name:deu_x_preferred":[
        "Bonanza"
    ],
    "name:ell_x_preferred":[
        "\u039c\u03c0\u03bf\u03bd\u03ac\u03bd\u03c4\u03c3\u03b1"
    ],
    "name:epo_x_preferred":[
        "Bonanza"
    ],
    "name:eus_x_preferred":[
        "Bonanza"
    ],
    "name:fas_x_preferred":[
        "\u0628\u0648\u0646\u0627\u0646\u0632\u0627"
    ],
    "name:fin_x_preferred":[
        "Bonanza"
    ],
    "name:fra_x_preferred":[
        "Bonanza"
    ],
    "name:glg_x_preferred":[
        "Bonanza"
    ],
    "name:heb_x_preferred":[
        "\u05d1\u05d5\u05e0\u05e0\u05d6\u05d4"
    ],
    "name:ita_x_preferred":[
        "Bonanza"
    ],
    "name:jpn_x_preferred":[
        "\u30dc\u30ca\u30f3\u30b6"
    ],
    "name:kor_x_preferred":[
        "\ubcf4\ub09c\uc790"
    ],
    "name:nld_x_preferred":[
        "Bonanza"
    ],
    "name:nor_x_preferred":[
        "Bonanza"
    ],
    "name:pol_x_preferred":[
        "Bonanza"
    ],
    "name:por_x_preferred":[
        "Bonanza"
    ],
    "name:rus_x_preferred":[
        "\u0411\u043e\u043d\u0430\u043d\u0446\u0430"
    ],
    "name:spa_x_preferred":[
        "Bonanza"
    ],
    "name:swe_x_preferred":[
        "Br\u00f6derna Cartwright"
    ],
    "name:tur_x_preferred":[
        "Bonanza"
    ],
    "wof:name":"Bonanza",
    "wof:placetype":"locality",
    "wof:population":5
},
  "geometry": {"coordinates":[-95.27110999999999,18.45417],"type":"Point"}
}