{
  "type": "Feature",
  "properties": {
    "gn:admin1_code":"30",
    "gn:admin2_code":"143.0",
    "gn:asciiname":"Bonanza",
    "gn:country_code":"MX",
    "gn:dem":381,
    "gn:feature_class":"P",
    "gn:feature_code":"PPL",
    "gn:name":"Bonanza",
    "gn:population":5,
    "gn:timezone":"America/Mexico_City",
    "iso:country":"MX",
    "wof:name":"Bonanza",
    "wof:placetype":"locality",
    "wof:population":5
},
  "geometry": {"coordinates":[-95.27110999999999,18.45417],"type":"Point"}
}