{
  "type": "Feature",
  "properties": {
    "gn:admin1_code":"5",
    "gn:admin2_code":"31.0",
    "gn:asciiname":"Lemlajanton",
    "gn:country_code":"MX",
    "gn:dem":894,
    "gn:feature_class":"P",
    "gn:feature_code":"PPL",
    "gn:name":"Lemlajant\u00f3n",
    "gn:population":76,
    "gn:timezone":"America/Mexico_City",
    "iso:country":"MX",
    "name:und_x_variant":[
        "Lemlajant\u00f3n"
    ],
    "wof:name":"Lemlajanton",
    "wof:placetype":"locality",
    "wof:population":76
},
  "geometry": {"coordinates":[-92.19139,17.07722],"type":"Point"}
}