{
  "type": "Feature",
  "properties": {
    "gn:admin1_code":"10",
    "gn:admin2_code":"5.0",
    "gn:asciiname":"El Campeon",
    "gn:country_code":"MX",
    "gn:dem":1860,
    "gn:feature_class":"P",
    "gn:feature_code":"PPL",
    "gn:name":"El Campe\u00f3n",
    "gn:population":4,
    "gn:timezone":"America/Monterrey",
    "iso:country":"MX",
    "name:und_x_variant":[
        "El Campe\u00f3n"
    ],
    "wof:name":"El Campeon",
    "wof:placetype":"locality",
    "wof:population":4
},
  "geometry": {"coordinates":[-104.5239,24.1489],"type":"Point"}
}