{
  "type": "Feature",
  "properties": {
    "gn:admin1_code":"20",
    "gn:admin2_code":"510.0",
    "gn:asciiname":"Reyes Ixcatlan",
    "gn:country_code":"MX",
    "gn:dem":2819,
    "gn:feature_class":"P",
    "gn:feature_code":"PPL",
    "gn:name":"Reyes Ixcatl\u00e1n",
    "gn:population":194,
    "gn:timezone":"America/Mexico_City",
    "iso:country":"MX",
    "name:und_x_variant":[
        "Reyes Ixcatl\u00e1n"
    ],
    "wof:name":"Reyes Ixcatlan",
    "wof:placetype":"locality",
    "wof:population":194
},
  "geometry": {"coordinates":[-97.53667,16.92944],"type":"Point"}
}