{
  "type": "Feature",
  "properties": {
    "gn:admin1_code":"10.0",
    "gn:admin2_code":"37.0",
    "gn:asciiname":"Cuevecillas",
    "gn:country_code":"MX",
    "gn:dem":2542,
    "gn:feature_class":"P",
    "gn:feature_code":"PPL",
    "gn:name":"Cuevecillas",
    "gn:population":0,
    "gn:timezone":"America/Monterrey",
    "iso:country":"MX",
    "name:spa_x_preferred":[
        "Cuevecillas"
    ],
    "wof:name":"Cuevecillas",
    "wof:placetype":"locality"
},
  "geometry": {"coordinates":[-106.41583,25.14975],"type":"Point"}
}