{
  "type": "Feature",
  "properties": {
    "gn:admin1_code":"30",
    "gn:admin2_code":"174.0",
    "gn:asciiname":"Mata Anonilla",
    "gn:country_code":"MX",
    "gn:dem":116,
    "gn:feature_class":"P",
    "gn:feature_code":"PPL",
    "gn:name":"Mata Anonilla",
    "gn:population":310,
    "gn:timezone":"America/Mexico_City",
    "iso:country":"MX",
    "wof:name":"Mata Anonilla",
    "wof:placetype":"locality",
    "wof:population":310
},
  "geometry": {"coordinates":[-96.47111,18.61278],"type":"Point"}
}