{
  "type": "Feature",
  "properties": {
    "gn:admin1_code":"25",
    "gn:admin2_code":"11.0",
    "gn:asciiname":"Diaz",
    "gn:country_code":"MX",
    "gn:dem":15,
    "gn:feature_class":"P",
    "gn:feature_code":"PPL",
    "gn:name":"D\u00edaz",
    "gn:population":0,
    "gn:timezone":"America/Mazatlan",
    "iso:country":"MX",
    "name:spa_x_preferred":[
        "D\u00edaz"
    ],
    "wof:name":"Diaz",
    "wof:placetype":"locality"
},
  "geometry": {"coordinates":[-108.50141000000001,25.52292000000001],"type":"Point"}
}