{
  "type": "Feature",
  "properties": {
    "gn:admin1_code":"6",
    "gn:admin2_code":"55",
    "gn:asciiname":"Comunidad el Mirador",
    "gn:country_code":"MX",
    "gn:dem":1186,
    "gn:feature_class":"P",
    "gn:feature_code":"PPL",
    "gn:name":"Comunidad el Mirador",
    "gn:population":21,
    "gn:timezone":"America/Chihuahua",
    "iso:country":"MX",
    "wof:name":"Comunidad el Mirador",
    "wof:placetype":"locality",
    "wof:population":21
},
  "geometry": {"coordinates":[-105.58437000000001,28.48936],"type":"Point"}
}