{
  "type": "Feature",
  "properties": {
    "gn:admin1_code":"6.0",
    "gn:admin2_code":"1.0",
    "gn:asciiname":"Las Praderas",
    "gn:country_code":"MX",
    "gn:dem":1210,
    "gn:feature_class":"P",
    "gn:feature_code":"PPL",
    "gn:name":"Las Praderas",
    "gn:population":4,
    "gn:timezone":"America/Chihuahua",
    "iso:country":"MX",
    "name:spa_x_preferred":[
        "Las Praderas"
    ],
    "wof:name":"Las Praderas",
    "wof:placetype":"locality",
    "wof:population":4
},
  "geometry": {"coordinates":[-106.52343999999999,30.52331],"type":"Point"}
}