{
  "type": "Feature",
  "properties": {
    "gn:admin1_code":"10",
    "gn:admin2_code":"5.0",
    "gn:asciiname":"Totonilquillo",
    "gn:country_code":"MX",
    "gn:dem":2486,
    "gn:feature_class":"P",
    "gn:feature_code":"PPL",
    "gn:name":"Totonilquillo",
    "gn:population":0,
    "gn:timezone":"America/Monterrey",
    "iso:country":"MX",
    "name:spa_x_preferred":[
        "Totonilquillo"
    ],
    "wof:name":"Totonilquillo",
    "wof:placetype":"locality"
},
  "geometry": {"coordinates":[-105.21576,23.82823],"type":"Point"}
}