{
  "type": "Feature",
  "properties": {
    "gn:admin1_code":"30",
    "gn:admin2_code":"180",
    "gn:asciiname":"Cerca de Piedra",
    "gn:country_code":"MX",
    "gn:dem":735,
    "gn:feature_class":"P",
    "gn:feature_code":"PPL",
    "gn:name":"Cerca de Piedra",
    "gn:population":10,
    "gn:timezone":"America/Mexico_City",
    "iso:country":"MX",
    "wof:name":"Cerca de Piedra",
    "wof:placetype":"locality",
    "wof:population":10
},
  "geometry": {"coordinates":[-98.16056,20.59],"type":"Point"}
}