{
  "type": "Feature",
  "properties": {
    "gn:admin1_code":"15.0",
    "gn:admin2_code":"64.0",
    "gn:asciiname":"Francisco I. Madero",
    "gn:country_code":"MX",
    "gn:dem":2842,
    "gn:feature_class":"P",
    "gn:feature_code":"PPL",
    "gn:name":"Francisco I. Madero",
    "gn:population":0,
    "gn:timezone":"America/Mexico_City",
    "iso:country":"MX",
    "name:spa_x_preferred":[
        "Francisco I. Madero"
    ],
    "name:spa_x_variant":[
        "El Ator\u00f3n"
    ],
    "wof:name":"Francisco I. Madero",
    "wof:placetype":"locality"
},
  "geometry": {"coordinates":[-100.13923,19.79462],"type":"Point"}
}