{
  "type": "Feature",
  "properties": {
    "gn:admin1_code":"30",
    "gn:admin2_code":"125",
    "gn:asciiname":"Paso Vaquero",
    "gn:country_code":"MX",
    "gn:dem":199,
    "gn:feature_class":"P",
    "gn:feature_code":"PPL",
    "gn:name":"Paso Vaquero",
    "gn:population":29,
    "gn:timezone":"America/Mexico_City",
    "iso:country":"MX",
    "wof:name":"Paso Vaquero",
    "wof:placetype":"locality",
    "wof:population":29
},
  "geometry": {"coordinates":[-96.56417,18.89917],"type":"Point"}
}