{
  "type": "Feature",
  "properties": {
    "gn:admin1_code":"29",
    "gn:admin2_code":"4.0",
    "gn:asciiname":"San Antonio Zoapila",
    "gn:country_code":"MX",
    "gn:dem":2507,
    "gn:feature_class":"P",
    "gn:feature_code":"PPL",
    "gn:name":"San Antonio Zoapila",
    "gn:population":0,
    "gn:timezone":"America/Mexico_City",
    "iso:country":"MX",
    "name:spa_x_preferred":[
        "San Antonio Zoapila"
    ],
    "name:und_x_variant":[
        "Zoapila",
        "Santa Mar\u00eda Zoapila"
    ],
    "wof:name":"San Antonio Zoapila",
    "wof:placetype":"locality"
},
  "geometry": {"coordinates":[-97.77293,19.36944],"type":"Point"}
}