{
  "type": "Feature",
  "properties": {
    "gn:admin1_code":"12",
    "gn:admin2_code":"22",
    "gn:asciiname":"La Era",
    "gn:country_code":"MX",
    "gn:dem":2159,
    "gn:feature_class":"P",
    "gn:feature_code":"PPL",
    "gn:name":"La Era",
    "gn:population":11,
    "gn:timezone":"America/Mexico_City",
    "iso:country":"MX",
    "wof:name":"La Era",
    "wof:placetype":"locality",
    "wof:population":11
},
  "geometry": {"coordinates":[-101.24382,18.1537],"type":"Point"}
}