{
  "type": "Feature",
  "properties": {
    "gn:admin1_code":"21",
    "gn:admin2_code":"88",
    "gn:asciiname":"Molinagco",
    "gn:country_code":"MX",
    "gn:dem":255,
    "gn:feature_class":"P",
    "gn:feature_code":"PPL",
    "gn:name":"Molinagco",
    "gn:population":24,
    "gn:timezone":"America/Mexico_City",
    "iso:country":"MX",
    "wof:name":"Molinagco",
    "wof:placetype":"locality",
    "wof:population":24
},
  "geometry": {"coordinates":[-97.48972000000001,20.09639],"type":"Point"}
}