{
  "type": "Feature",
  "properties": {
    "gn:admin1_code":"26",
    "gn:admin2_code":"44.0",
    "gn:asciiname":"Potrero de Galindo",
    "gn:country_code":"MX",
    "gn:dem":362,
    "gn:feature_class":"P",
    "gn:feature_code":"PPL",
    "gn:name":"Potrero de Galindo",
    "gn:population":3,
    "gn:timezone":"America/Hermosillo",
    "iso:country":"MX",
    "wof:name":"Potrero de Galindo",
    "wof:placetype":"locality",
    "wof:population":3
},
  "geometry": {"coordinates":[-109.42168999999998,28.36586],"type":"Point"}
}