{
  "type": "Feature",
  "properties": {
    "gn:admin1_code":"30.0",
    "gn:admin2_code":"155.0",
    "gn:asciiname":"Jacubal",
    "gn:country_code":"MX",
    "gn:dem":156,
    "gn:feature_class":"P",
    "gn:feature_code":"PPL",
    "gn:name":"Jacubal",
    "gn:population":283,
    "gn:timezone":"America/Mexico_City",
    "iso:country":"MX",
    "name:spa_x_preferred":[
        "Jacubal"
    ],
    "wof:name":"Jacubal",
    "wof:placetype":"locality",
    "wof:population":283
},
  "geometry": {"coordinates":[-98.205,21.3825],"type":"Point"}
}