{
  "type": "Feature",
  "properties": {
    "gn:admin1_code":"32",
    "gn:admin2_code":"52.0",
    "gn:asciiname":"La Cruz",
    "gn:country_code":"MX",
    "gn:dem":2129,
    "gn:feature_class":"P",
    "gn:feature_code":"PPL",
    "gn:name":"La Cruz",
    "gn:population":57,
    "gn:timezone":"America/Mexico_City",
    "iso:country":"MX",
    "wof:name":"La Cruz",
    "wof:placetype":"locality",
    "wof:population":57
},
  "geometry": {"coordinates":[-101.90278000000001,22.11722],"type":"Point"}
}