{
  "type": "Feature",
  "properties": {
    "gn:admin1_code":"14.0",
    "gn:admin2_code":"86.0",
    "gn:asciiname":"Ferreria de Tula",
    "gn:country_code":"MX",
    "gn:dem":2361,
    "gn:feature_class":"P",
    "gn:feature_code":"PPL",
    "gn:name":"Ferrer\u00eda de Tula",
    "gn:population":547,
    "gn:timezone":"America/Mexico_City",
    "iso:country":"MX",
    "wof:name":"Ferreria de Tula",
    "wof:placetype":"locality",
    "wof:population":547
},
  "geometry": {"coordinates":[-103.7298,20.06529],"type":"Point"}
}