{
  "type": "Feature",
  "properties": {
    "gn:admin1_code":"6",
    "gn:admin2_code":"2.0",
    "gn:asciiname":"El Chaparral",
    "gn:country_code":"MX",
    "gn:dem":1167,
    "gn:feature_class":"P",
    "gn:feature_code":"PPL",
    "gn:name":"El Chaparral",
    "gn:population":0,
    "gn:timezone":"America/Chihuahua",
    "iso:country":"MX",
    "name:spa_x_preferred":[
        "El Chaparral"
    ],
    "wof:name":"El Chaparral",
    "wof:placetype":"locality"
},
  "geometry": {"coordinates":[-104.78564,28.85455],"type":"Point"}
}