{
  "type": "Feature",
  "properties": {
    "gn:gn_country":"MX",
    "gn:gn_fcode":"PPL",
    "gn:gn_pop":5812,
    "gn:population":5812,
    "iso:country":"MX",
    "name:unk_x_variant":[
        "Domingo Arenas"
    ],
    "qs_pg:aaroncc":"MX",
    "qs_pg:gn_country":"MX",
    "qs_pg:gn_fcode":"PPL",
    "qs_pg:gn_pop":5812,
    "qs_pg:name":"Ampl Domingo Arenas",
    "qs_pg:name_adm0":"M\u00e9xico",
    "qs_pg:name_adm1":"Puebla",
    "qs_pg:photos":8,
    "qs_pg:photos_1k":2,
    "qs_pg:photos_9k":1,
    "qs_pg:photos_9r":1,
    "qs_pg:photos_all":8,
    "qs_pg:photos_sr":1,
    "qs_pg:pop_sr":5,
    "qs_pg:qs_pg_placetype":"neighbourhood",
    "qs_pg:qs_pg_placetype_gp":"Suburb",
    "qs_pg:woe_adm0":23424900,
    "woe:adm0_id":23424900,
    "woe:name_adm0":"M\u00e9xico",
    "woe:name_adm1":"Puebla",
    "woe:placetype":"Suburb",
    "wof:name":"Ampl Domingo Arenas",
    "wof:placetype":"neighbourhood",
    "wof:population":5812
},
  "geometry": {"coordinates":[-98.45751,19.14064],"type":"Point"}
}