{
  "type": "Feature",
  "properties": {
    "gn:admin1_code":"11.0",
    "gn:admin2_code":"46.0",
    "gn:asciiname":"Loma de Zempoala",
    "gn:country_code":"MX",
    "gn:dem":1741,
    "gn:feature_class":"P",
    "gn:feature_code":"PPL",
    "gn:name":"Loma de Zempoala",
    "gn:population":0,
    "gn:timezone":"America/Mexico_City",
    "iso:country":"MX",
    "name:spa_x_preferred":[
        "Loma de Zempoala"
    ],
    "wof:name":"Loma de Zempoala",
    "wof:placetype":"locality"
},
  "geometry": {"coordinates":[-101.08023,20.29182],"type":"Point"}
}