{
  "type": "Feature",
  "properties": {
    "gn:admin1_code":"5",
    "gn:admin2_code":"108",
    "gn:asciiname":"Rincon San Antonio",
    "gn:country_code":"MX",
    "gn:dem":664,
    "gn:feature_class":"P",
    "gn:feature_code":"PPL",
    "gn:name":"Rinc\u00f3n San Antonio",
    "gn:population":12,
    "gn:timezone":"America/Mexico_City",
    "iso:country":"MX",
    "name:und_x_variant":[
        "Rinc\u00f3n San Antonio"
    ],
    "wof:name":"Rincon San Antonio",
    "wof:placetype":"locality",
    "wof:population":12
},
  "geometry": {"coordinates":[-93.37582999999999,16.29472],"type":"Point"}
}