{
  "type": "Feature",
  "properties": {
    "gn:admin1_code":"19",
    "gn:admin2_code":"29.0",
    "gn:asciiname":"Hacienda de Hoyos",
    "gn:country_code":"MX",
    "gn:dem":422,
    "gn:feature_class":"P",
    "gn:feature_code":"PPL",
    "gn:name":"Hacienda de Hoyos",
    "gn:population":7,
    "gn:timezone":"America/Monterrey",
    "iso:country":"MX",
    "wof:name":"Hacienda de Hoyos",
    "wof:placetype":"locality",
    "wof:population":7
},
  "geometry": {"coordinates":[-99.69333,24.89167],"type":"Point"}
}