{
  "type": "Feature",
  "properties": {
    "gn:admin1_code":"4",
    "gn:admin2_code":"2.0",
    "gn:asciiname":"Los Mangos",
    "gn:country_code":"MX",
    "gn:dem":31,
    "gn:feature_class":"P",
    "gn:feature_code":"PPL",
    "gn:name":"Los Mangos",
    "gn:population":6,
    "gn:timezone":"America/Merida",
    "iso:country":"MX",
    "wof:name":"Los Mangos",
    "wof:placetype":"locality",
    "wof:population":6
},
  "geometry": {"coordinates":[-90.17361,19.52389],"type":"Point"}
}