{
  "type": "Feature",
  "properties": {
    "gn:admin1_code":"14",
    "gn:admin2_code":"61",
    "gn:asciiname":"Corral Blanco",
    "gn:country_code":"MX",
    "gn:dem":1311,
    "gn:feature_class":"P",
    "gn:feature_code":"PPL",
    "gn:name":"Corral Blanco",
    "gn:population":11,
    "gn:timezone":"America/Mexico_City",
    "iso:country":"MX",
    "wof:name":"Corral Blanco",
    "wof:placetype":"locality",
    "wof:population":11
},
  "geometry": {"coordinates":[-103.73860999999999,22.28889],"type":"Point"}
}