{
  "type": "Feature",
  "properties": {
    "gn:admin1_code":"22.0",
    "gn:admin2_code":"1.0",
    "gn:asciiname":"La Isla",
    "gn:country_code":"MX",
    "gn:dem":2571,
    "gn:feature_class":"P",
    "gn:feature_code":"PPL",
    "gn:name":"La Isla",
    "gn:population":0,
    "gn:timezone":"America/Mexico_City",
    "iso:country":"MX",
    "name:ceb_x_preferred":[
        "La Isla"
    ],
    "name:spa_x_preferred":[
        "La Isla"
    ],
    "name:spa_x_variant":[
        "La isla"
    ],
    "name:srp_x_preferred":[
        "\u041b\u0430 \u0418\u0441\u043b\u0430"
    ],
    "name:swe_x_preferred":[
        "La Isla"
    ],
    "wof:name":"La Isla",
    "wof:placetype":"locality"
},
  "geometry": {"coordinates":[-100.17976,20.21424],"type":"Point"}
}