{
  "type": "Feature",
  "properties": {
    "gn:admin1_code":"32.0",
    "gn:admin2_code":"55.0",
    "gn:asciiname":"Varela",
    "gn:country_code":"MX",
    "gn:dem":1749,
    "gn:feature_class":"P",
    "gn:feature_code":"PPL",
    "gn:name":"Varela",
    "gn:population":0,
    "gn:timezone":"America/Mexico_City",
    "iso:country":"MX",
    "name:spa_x_preferred":[
        "Varela"
    ],
    "wof:name":"Varela",
    "wof:placetype":"locality"
},
  "geometry": {"coordinates":[-102.81999999999999,22.03895],"type":"Point"}
}