{
  "type": "Feature",
  "properties": {
    "gn:admin1_code":"32.0",
    "gn:admin2_code":"55.0",
    "gn:asciiname":"Varela",
    "gn:country_code":"MX",
    "gn:dem":1749,
    "gn:feature_class":"P",
    "gn:feature_code":"PPL",
    "gn:name":"Varela",
    "gn:population":0,
    "gn:timezone":"America/Mexico_City",
    "iso:country":"MX",
    "name:cat_x_preferred":[
        "Varela"
    ],
    "name:ceb_x_preferred":[
        "Varela"
    ],
    "name:ces_x_preferred":[
        "Varela"
    ],
    "name:deu_x_preferred":[
        "Varela"
    ],
    "name:fin_x_preferred":[
        "Varela"
    ],
    "name:fra_x_preferred":[
        "Varela"
    ],
    "name:glg_x_preferred":[
        "Varela"
    ],
    "name:heb_x_preferred":[
        "\u05d5\u05d0\u05e8\u05dc\u05d4"
    ],
    "name:ita_x_preferred":[
        "Varela"
    ],
    "name:jpn_x_preferred":[
        "\u30d0\u30ec\u30e9"
    ],
    "name:nld_x_preferred":[
        "Varela"
    ],
    "name:pol_x_preferred":[
        "Varela"
    ],
    "name:rus_x_preferred":[
        "\u0412\u0430\u0440\u0435\u043b\u0430"
    ],
    "name:spa_x_preferred":[
        "Varela"
    ],
    "name:srp_x_preferred":[
        "\u0412\u0430\u0440\u0435\u043b\u0430"
    ],
    "name:swe_x_preferred":[
        "Varela"
    ],
    "name:ukr_x_preferred":[
        "\u0412\u0430\u0440\u0435\u043b\u0430"
    ],
    "wof:name":"Varela",
    "wof:placetype":"locality"
},
  "geometry": {"coordinates":[-102.81999999999999,22.03895],"type":"Point"}
}