{
  "type": "Feature",
  "properties": {
    "gn:admin1_code":"28.0",
    "gn:admin2_code":"21.0",
    "gn:asciiname":"Chapingo",
    "gn:country_code":"MX",
    "gn:dem":56,
    "gn:feature_class":"P",
    "gn:feature_code":"PPL",
    "gn:name":"Chapingo",
    "gn:population":0,
    "gn:timezone":"America/Monterrey",
    "iso:country":"MX",
    "name:fra_x_preferred":[
        "Chapingo"
    ],
    "name:spa_x_preferred":[
        "Chapingo"
    ],
    "wof:name":"Chapingo",
    "wof:placetype":"locality"
},
  "geometry": {"coordinates":[-98.90722,22.72472],"type":"Point"}
}