{
  "type": "Feature",
  "properties": {
    "gn:admin1_code":"28.0",
    "gn:admin2_code":"29.0",
    "gn:asciiname":"Veinte de Noviembre",
    "gn:country_code":"MX",
    "gn:dem":392,
    "gn:feature_class":"P",
    "gn:feature_code":"PPL",
    "gn:name":"Veinte de Noviembre",
    "gn:population":0,
    "gn:timezone":"America/Monterrey",
    "iso:country":"MX",
    "name:spa_x_preferred":[
        "Veinte de Noviembre"
    ],
    "wof:name":"Veinte de Noviembre",
    "wof:placetype":"locality"
},
  "geometry": {"coordinates":[-99.4213,22.86032],"type":"Point"}
}