{
  "type": "Feature",
  "properties": {
    "gn:admin1_code":"14",
    "gn:admin2_code":"46.0",
    "gn:asciiname":"Canada de Gomez",
    "gn:cc2":"MX",
    "gn:country_code":"MX",
    "gn:dem":1784,
    "gn:feature_class":"P",
    "gn:feature_code":"PPL",
    "gn:name":"Ca\u00f1ada de G\u00f3mez",
    "gn:population":64,
    "gn:timezone":"America/Mexico_City",
    "iso:country":"MX",
    "name:und_x_variant":[
        "Ranchito G\u00f3mez",
        "Rancho de G\u00f3mez",
        "Ranchito de G\u00f3mez"
    ],
    "wof:name":"Canada de Gomez",
    "wof:placetype":"locality",
    "wof:population":64
},
  "geometry": {"coordinates":[-102.44139,21.18333],"type":"Point"}
}