{
  "type": "Feature",
  "properties": {
    "gn:admin1_code":"14",
    "gn:admin2_code":"125.0",
    "gn:asciiname":"San Ignacio Cerro Gordo",
    "gn:country_code":"MX",
    "gn:dem":2076,
    "gn:feature_class":"P",
    "gn:feature_code":"PPLA2",
    "gn:name":"San Ignacio Cerro Gordo",
    "gn:population":0,
    "gn:timezone":"America/Mexico_City",
    "iso:country":"MX",
    "name:und_x_variant":[
        "San Ignacio"
    ],
    "wof:name":"San Ignacio Cerro Gordo",
    "wof:placetype":"locality"
},
  "geometry": {"coordinates":[-102.53466,20.74558],"type":"Point"}
}