{
  "type": "Feature",
  "properties": {
    "gn:admin1_code":"14",
    "gn:admin2_code":"125.0",
    "gn:asciiname":"San Ignacio Cerro Gordo",
    "gn:country_code":"MX",
    "gn:dem":2076,
    "gn:feature_class":"P",
    "gn:feature_code":"PPLA2",
    "gn:name":"San Ignacio Cerro Gordo",
    "gn:population":0,
    "gn:timezone":"America/Mexico_City",
    "iso:country":"MX",
    "name:ceb_x_preferred":[
        "San Ignacio Cerro Gordo"
    ],
    "name:deu_x_preferred":[
        "Municipio San Ignacio Cerro Gordo"
    ],
    "name:epo_x_preferred":[
        "San Ignacio Cerro Gordo"
    ],
    "name:eus_x_preferred":[
        "San Ignacio Cerro Gordo"
    ],
    "name:ita_x_preferred":[
        "San Ignacio Cerro Gordo"
    ],
    "name:por_x_preferred":[
        "San Ignacio Cerro Gordo"
    ],
    "name:spa_x_preferred":[
        "San Ignacio Cerro Gordo"
    ],
    "name:srp_x_preferred":[
        "\u041e\u043f\u0448\u0442\u0438\u043d\u0430 \u0421\u0430\u043d \u0418\u0433\u043d\u0430\u0441\u0438\u043e \u0421\u0435\u0440\u043e \u0413\u043e\u0440\u0434\u043e"
    ],
    "name:swe_x_preferred":[
        "San Ignacio Cerro Gordo"
    ],
    "name:und_x_variant":[
        "San Ignacio"
    ],
    "wof:name":"San Ignacio Cerro Gordo",
    "wof:placetype":"locality"
},
  "geometry": {"coordinates":[-102.53466,20.74558],"type":"Point"}
}