{
  "type": "Feature",
  "properties": {
    "gn:admin1_code":"10",
    "gn:admin2_code":"32.0",
    "gn:asciiname":"San Miguel de los Pinos (Rancho Viejo)",
    "gn:country_code":"MX",
    "gn:dem":2075,
    "gn:feature_class":"P",
    "gn:feature_code":"PPL",
    "gn:name":"San Miguel de los Pinos (Rancho Viejo)",
    "gn:population":67,
    "gn:timezone":"America/Monterrey",
    "iso:country":"MX",
    "name:und_x_variant":[
        "Rancho Viejo",
        "San Miguel de los Pinos"
    ],
    "wof:name":"San Miguel de los Pinos (Rancho Viejo)",
    "wof:placetype":"locality",
    "wof:population":67
},
  "geometry": {"coordinates":[-105.23835,25.16363],"type":"Point"}
}