{
  "type": "Feature",
  "properties": {
    "gn:admin1_code":"14",
    "gn:admin2_code":"81.0",
    "gn:asciiname":"Las Liebres",
    "gn:country_code":"MX",
    "gn:dem":1758,
    "gn:feature_class":"P",
    "gn:feature_code":"PPL",
    "gn:name":"Las Liebres",
    "gn:population":0,
    "gn:timezone":"America/Mexico_City",
    "iso:country":"MX",
    "name:spa_x_preferred":[
        "Las Liebres"
    ],
    "wof:name":"Las Liebres",
    "wof:placetype":"locality"
},
  "geometry": {"coordinates":[-103.22883,22.26392],"type":"Point"}
}