{
  "type": "Feature",
  "properties": {
    "gn:admin1_code":"28.0",
    "gn:admin2_code":"21.0",
    "gn:asciiname":"El Siete",
    "gn:country_code":"MX",
    "gn:dem":61,
    "gn:feature_class":"P",
    "gn:feature_code":"PPL",
    "gn:name":"El Siete",
    "gn:population":8,
    "gn:timezone":"America/Monterrey",
    "iso:country":"MX",
    "name:spa_x_preferred":[
        "El Siete"
    ],
    "wof:name":"El Siete",
    "wof:placetype":"locality",
    "wof:population":8
},
  "geometry": {"coordinates":[-98.9006,22.71545],"type":"Point"}
}