{
  "type": "Feature",
  "properties": {
    "gn:admin1_code":"10.0",
    "gn:admin2_code":"10.0",
    "gn:asciiname":"Potrero de las Mulas",
    "gn:country_code":"MX",
    "gn:dem":1896,
    "gn:feature_class":"P",
    "gn:feature_code":"PPL",
    "gn:name":"Potrero de las Mulas",
    "gn:population":0,
    "gn:timezone":"America/Monterrey",
    "iso:country":"MX",
    "name:spa_x_preferred":[
        "Potrero de las Mulas"
    ],
    "wof:name":"Potrero de las Mulas",
    "wof:placetype":"locality"
},
  "geometry": {"coordinates":[-104.86287,25.9608],"type":"Point"}
}