{
  "type": "Feature",
  "properties": {
    "gn:admin1_code":"18.0",
    "gn:admin2_code":"9.0",
    "gn:asciiname":"La Cienaga",
    "gn:country_code":"MX",
    "gn:dem":1261,
    "gn:feature_class":"P",
    "gn:feature_code":"PPL",
    "gn:name":"La Ci\u00e9naga",
    "gn:population":0,
    "gn:timezone":"America/Mazatlan",
    "iso:country":"MX",
    "name:spa_x_preferred":[
        "La Ci\u00e9naga"
    ],
    "wof:name":"La Cienaga",
    "wof:placetype":"locality"
},
  "geometry": {"coordinates":[-104.61924999999999,22.08571],"type":"Point"}
}