{
  "type": "Feature",
  "properties": {
    "gn:admin1_code":"11.0",
    "gn:asciiname":"La Hoyita",
    "gn:country_code":"MX",
    "gn:dem":1930,
    "gn:feature_class":"P",
    "gn:feature_code":"PPL",
    "gn:name":"La Hoyita",
    "gn:population":0,
    "gn:timezone":"America/Mexico_City",
    "iso:country":"MX",
    "name:spa_x_preferred":[
        "La Hoyita"
    ],
    "name:spa_x_variant":[
        "Los Sauces"
    ],
    "wof:name":"La Hoyita",
    "wof:placetype":"locality"
},
  "geometry": {"coordinates":[-100.51357,19.99442],"type":"Point"}
}