{
  "type": "Feature",
  "properties": {
    "gn:admin1_code":"32",
    "gn:admin2_code":"26.0",
    "gn:asciiname":"San Eligio",
    "gn:country_code":"MX",
    "gn:dem":2835,
    "gn:feature_class":"P",
    "gn:feature_code":"PPL",
    "gn:name":"San Eligio",
    "gn:population":0,
    "gn:timezone":"America/Mexico_City",
    "iso:country":"MX",
    "name:spa_x_preferred":[
        "San Eligio"
    ],
    "wof:name":"San Eligio",
    "wof:placetype":"locality"
},
  "geometry": {"coordinates":[-101.47837,24.63847],"type":"Point"}
}