{
  "type": "Feature",
  "properties": {
    "gn:admin1_code":"24",
    "gn:admin2_code":"21.0",
    "gn:asciiname":"Rincon del Porvenir",
    "gn:country_code":"MX",
    "gn:dem":1893,
    "gn:feature_class":"P",
    "gn:feature_code":"PPL",
    "gn:name":"Rinc\u00f3n del Porvenir",
    "gn:population":1162,
    "gn:timezone":"America/Mexico_City",
    "iso:country":"MX",
    "name:und_x_variant":[
        "Rinc\u00f3n del Porvenir"
    ],
    "wof:name":"Rincon del Porvenir",
    "wof:placetype":"locality",
    "wof:population":1162
},
  "geometry": {"coordinates":[-101.17639,22.32306],"type":"Point"}
}