{
  "type": "Feature",
  "properties": {
    "gn:admin1_code":"19",
    "gn:admin2_code":"22.0",
    "gn:asciiname":"La Cucaracha",
    "gn:country_code":"MX",
    "gn:dem":244,
    "gn:feature_class":"P",
    "gn:feature_code":"PPL",
    "gn:name":"La Cucaracha",
    "gn:population":0,
    "gn:timezone":"America/Monterrey",
    "iso:country":"MX",
    "name:bre_x_preferred":[
        "La cucaracha"
    ],
    "name:dan_x_preferred":[
        "La Cucaracha"
    ],
    "name:deu_x_preferred":[
        "La Cucaracha"
    ],
    "name:epo_x_preferred":[
        "La lerta blato"
    ],
    "name:fas_x_preferred":[
        "\u0644\u0627 \u06a9\u0648\u06a9\u0627\u0631\u0686\u0627"
    ],
    "name:fin_x_preferred":[
        "La Cucaracha"
    ],
    "name:fra_x_preferred":[
        "La cucaracha"
    ],
    "name:hun_x_preferred":[
        "La cucaracha"
    ],
    "name:ind_x_preferred":[
        "La Cucaracha"
    ],
    "name:ita_x_preferred":[
        "La cucaracha"
    ],
    "name:jpn_x_preferred":[
        "\u30e9\u30fb\u30af\u30ab\u30e9\u30fc\u30c1\u30e3"
    ],
    "name:nld_x_preferred":[
        "La Cucaracha"
    ],
    "name:por_x_preferred":[
        "La Cucaracha"
    ],
    "name:rus_x_preferred":[
        "\u041a\u0443\u043a\u0430\u0440\u0430\u0447\u0430"
    ],
    "name:slk_x_preferred":[
        "La Cucaracha"
    ],
    "name:spa_x_preferred":[
        "La Cucaracha"
    ],
    "name:spa_x_variant":[
        "La cucaracha"
    ],
    "name:srp_x_preferred":[
        "La Cucaracha"
    ],
    "name:swe_x_preferred":[
        "La Cucaracha"
    ],
    "name:tur_x_preferred":[
        "La Cucaracha"
    ],
    "name:ukr_x_preferred":[
        "\u041a\u0443\u043a\u0430\u0440\u0430\u0447\u0430"
    ],
    "wof:name":"La Cucaracha",
    "wof:placetype":"locality"
},
  "geometry": {"coordinates":[-99.53306000000001,25.34179],"type":"Point"}
}