{
  "type": "Feature",
  "properties": {
    "gn:admin1_code":"19",
    "gn:admin2_code":"22.0",
    "gn:asciiname":"La Cucaracha",
    "gn:country_code":"MX",
    "gn:dem":244,
    "gn:feature_class":"P",
    "gn:feature_code":"PPL",
    "gn:name":"La Cucaracha",
    "gn:population":0,
    "gn:timezone":"America/Monterrey",
    "iso:country":"MX",
    "name:spa_x_preferred":[
        "La Cucaracha"
    ],
    "wof:name":"La Cucaracha",
    "wof:placetype":"locality"
},
  "geometry": {"coordinates":[-99.53306000000001,25.34179],"type":"Point"}
}