{
  "type": "Feature",
  "properties": {
    "gn:admin1_code":"12",
    "gn:admin2_code":"57.0",
    "gn:asciiname":"El Pantano",
    "gn:country_code":"MX",
    "gn:dem":525,
    "gn:feature_class":"P",
    "gn:feature_code":"PPL",
    "gn:name":"El Pantano",
    "gn:population":61,
    "gn:timezone":"America/Mexico_City",
    "iso:country":"MX",
    "name:ita_x_preferred":[
        "El Pantano"
    ],
    "name:spa_x_preferred":[
        "El Pantano"
    ],
    "name:zho_x_preferred":[
        "\u57c3\u5c14\u6f58\u5854\u8bfa"
    ],
    "wof:name":"El Pantano",
    "wof:placetype":"locality",
    "wof:population":61
},
  "geometry": {"coordinates":[-100.92112,17.49217],"type":"Point"}
}