{
  "type": "Feature",
  "properties": {
    "gn:admin1_code":"10",
    "gn:admin2_code":"14.0",
    "gn:asciiname":"Mesa de Platanitos",
    "gn:country_code":"MX",
    "gn:dem":1593,
    "gn:feature_class":"P",
    "gn:feature_code":"PPL",
    "gn:name":"Mesa de Platanitos",
    "gn:population":0,
    "gn:timezone":"America/Monterrey",
    "iso:country":"MX",
    "name:spa_x_preferred":[
        "Mesa de Platanitos"
    ],
    "wof:name":"Mesa de Platanitos",
    "wof:placetype":"locality"
},
  "geometry": {"coordinates":[-104.58045,23.15432],"type":"Point"}
}