{
  "type": "Feature",
  "properties": {
    "gn:admin1_code":"15",
    "gn:admin2_code":"103.0",
    "gn:asciiname":"Rancho San Luis",
    "gn:country_code":"MX",
    "gn:dem":2526,
    "gn:feature_class":"P",
    "gn:feature_code":"PPL",
    "gn:name":"Rancho San Luis",
    "gn:population":9,
    "gn:timezone":"America/Mexico_City",
    "iso:country":"MX",
    "wof:name":"Rancho San Luis",
    "wof:placetype":"locality",
    "wof:population":9
},
  "geometry": {"coordinates":[-98.81064000000001,19.19105],"type":"Point"}
}