{
  "type": "Feature",
  "properties": {
    "gn:admin1_code":"25",
    "gn:admin2_code":"3.0",
    "gn:asciiname":"La Mesa",
    "gn:country_code":"MX",
    "gn:dem":709,
    "gn:feature_class":"P",
    "gn:feature_code":"PPL",
    "gn:name":"La Mesa",
    "gn:population":6,
    "gn:timezone":"America/Mazatlan",
    "iso:country":"MX",
    "wof:name":"La Mesa",
    "wof:placetype":"locality",
    "wof:population":6
},
  "geometry": {"coordinates":[-107.29662999999999,25.90302],"type":"Point"}
}