{
  "type": "Feature",
  "properties": {
    "gn:admin1_code":"15",
    "gn:admin2_code":"81.0",
    "gn:asciiname":"Ampliacion San Jeronimo",
    "gn:country_code":"MX",
    "gn:dem":2283,
    "gn:feature_class":"P",
    "gn:feature_code":"PPL",
    "gn:name":"Ampliaci\u00f3n San Jer\u00f3nimo",
    "gn:population":232,
    "gn:timezone":"America/Mexico_City",
    "iso:country":"MX",
    "name:und_x_variant":[
        "Ampliaci\u00f3n San Jer\u00f3nimo"
    ],
    "wof:name":"Ampliacion San Jeronimo",
    "wof:placetype":"locality",
    "wof:population":232
},
  "geometry": {"coordinates":[-98.94167,19.73639],"type":"Point"}
}