{
  "type": "Feature",
  "properties": {
    "gn:admin1_code":"19",
    "gn:admin2_code":"49.0",
    "gn:asciiname":"Rodolfo Martinez Lozano",
    "gn:country_code":"MX",
    "gn:dem":419,
    "gn:feature_class":"P",
    "gn:feature_code":"PPL",
    "gn:name":"Rodolfo Mart\u00ednez Lozano",
    "gn:population":6,
    "gn:timezone":"America/Monterrey",
    "iso:country":"MX",
    "name:und_x_variant":[
        "Rodolfo Mart\u00ednez Lozano"
    ],
    "wof:name":"Rodolfo Martinez Lozano",
    "wof:placetype":"locality",
    "wof:population":6
},
  "geometry": {"coordinates":[-100.07168,25.44506],"type":"Point"}
}