{
  "type": "Feature",
  "properties": {
    "gn:admin1_code":"20",
    "gn:admin2_code":"525.0",
    "gn:asciiname":"Yolanda",
    "gn:country_code":"MX",
    "gn:dem":107,
    "gn:feature_class":"P",
    "gn:feature_code":"PPL",
    "gn:name":"Yolanda",
    "gn:population":0,
    "gn:timezone":"America/Mexico_City",
    "iso:country":"MX",
    "name:spa_x_preferred":[
        "Yolanda"
    ],
    "wof:name":"Yolanda",
    "wof:placetype":"locality"
},
  "geometry": {"coordinates":[-94.26555999999999,16.4375],"type":"Point"}
}