{
  "type": "Feature",
  "properties": {
    "gn:admin1_code":"5",
    "gn:admin2_code":"19.0",
    "gn:asciiname":"Trapich",
    "gn:country_code":"MX",
    "gn:dem":1252,
    "gn:feature_class":"P",
    "gn:feature_code":"PPL",
    "gn:name":"Trapich",
    "gn:population":0,
    "gn:timezone":"America/Mexico_City",
    "iso:country":"MX",
    "name:spa_x_preferred":[
        "Trapich"
    ],
    "name:spa_x_variant":[
        "Santa Rita Un\u00ednajab"
    ],
    "name:und_x_variant":[
        "Santa Rita"
    ],
    "wof:name":"Trapich",
    "wof:placetype":"locality"
},
  "geometry": {"coordinates":[-92.14635,16.11212],"type":"Point"}
}