{
  "type": "Feature",
  "properties": {
    "gn:admin1_code":"12",
    "gn:admin2_code":"4.0",
    "gn:asciiname":"Nuevo Zaragoza",
    "gn:country_code":"MX",
    "gn:dem":2609,
    "gn:feature_class":"P",
    "gn:feature_code":"PPL",
    "gn:name":"Nuevo Zaragoza",
    "gn:population":169,
    "gn:timezone":"America/Mexico_City",
    "iso:country":"MX",
    "wof:name":"Nuevo Zaragoza",
    "wof:placetype":"locality",
    "wof:population":169
},
  "geometry": {"coordinates":[-98.39028,17.30083],"type":"Point"}
}