{
  "type": "Feature",
  "properties": {
    "gn:admin1_code":"6",
    "gn:admin2_code":"44",
    "gn:asciiname":"La Parra",
    "gn:country_code":"MX",
    "gn:dem":1893,
    "gn:feature_class":"P",
    "gn:feature_code":"PPL",
    "gn:name":"La Parra",
    "gn:population":31,
    "gn:timezone":"America/Chihuahua",
    "iso:country":"MX",
    "wof:name":"La Parra",
    "wof:placetype":"locality",
    "wof:population":31
},
  "geometry": {"coordinates":[-105.72624999999999,26.73218],"type":"Point"}
}