{
  "type": "Feature",
  "properties": {
    "gn:admin1_code":"16.0",
    "gn:admin2_code":"83.0",
    "gn:asciiname":"El Cuate",
    "gn:country_code":"MX",
    "gn:dem":1778,
    "gn:feature_class":"P",
    "gn:feature_code":"PPL",
    "gn:name":"El Cuate",
    "gn:population":0,
    "gn:timezone":"America/Mexico_City",
    "iso:country":"MX",
    "name:spa_x_preferred":[
        "El Cuate"
    ],
    "wof:name":"El Cuate",
    "wof:placetype":"locality"
},
  "geometry": {"coordinates":[-102.28685,19.23908],"type":"Point"}
}