{
  "type": "Feature",
  "properties": {
    "gn:admin1_code":"30",
    "gn:admin2_code":"200.0",
    "gn:asciiname":"Contadero",
    "gn:country_code":"MX",
    "gn:dem":297,
    "gn:feature_class":"P",
    "gn:feature_code":"PPL",
    "gn:name":"Contadero",
    "gn:population":81,
    "gn:timezone":"America/Mexico_City",
    "iso:country":"MX",
    "name:ceb_x_preferred":[
        "Contadero"
    ],
    "name:fra_x_preferred":[
        "Contadero"
    ],
    "name:ita_x_preferred":[
        "Contadero"
    ],
    "name:kat_x_preferred":[
        "\u10d9\u10dd\u10dc\u10e2\u10d0\u10dc\u10d3\u10d4\u10e0\u10dd"
    ],
    "name:msa_x_preferred":[
        "Contadero"
    ],
    "name:nld_x_preferred":[
        "Contadero"
    ],
    "name:por_x_preferred":[
        "Contadero"
    ],
    "name:spa_x_preferred":[
        "Contadero"
    ],
    "name:swe_x_preferred":[
        "Contadero"
    ],
    "name:tgl_x_preferred":[
        "Contadero"
    ],
    "name:vie_x_preferred":[
        "Contadero"
    ],
    "name:war_x_preferred":[
        "Contadero"
    ],
    "name:zho_x_preferred":[
        "\u5b54\u5854\u5fb7\u7f85"
    ],
    "wof:name":"Contadero",
    "wof:placetype":"locality",
    "wof:population":81
},
  "geometry": {"coordinates":[-96.58177999999999,19.07296],"type":"Point"}
}