{
  "type": "Feature",
  "properties": {
    "gn:admin1_code":"28.0",
    "gn:admin2_code":"3.0",
    "gn:asciiname":"San Luisito",
    "gn:country_code":"MX",
    "gn:dem":18,
    "gn:feature_class":"P",
    "gn:feature_code":"PPL",
    "gn:name":"San Luisito",
    "gn:population":0,
    "gn:timezone":"America/Monterrey",
    "iso:country":"MX",
    "name:spa_x_preferred":[
        "San Luisito"
    ],
    "wof:name":"San Luisito",
    "wof:placetype":"locality"
},
  "geometry": {"coordinates":[-98.15457000000001,22.57196],"type":"Point"}
}