{
  "type": "Feature",
  "properties": {
    "gn:admin1_code":"28.0",
    "gn:admin2_code":"21.0",
    "gn:asciiname":"La Nueva Union",
    "gn:country_code":"MX",
    "gn:dem":97,
    "gn:feature_class":"P",
    "gn:feature_code":"PPL",
    "gn:name":"La Nueva Uni\u00f3n",
    "gn:population":203,
    "gn:timezone":"America/Monterrey",
    "iso:country":"MX",
    "name:spa_x_preferred":[
        "La Nueva Uni\u00f3n"
    ],
    "wof:name":"La Nueva Union",
    "wof:placetype":"locality",
    "wof:population":203
},
  "geometry": {"coordinates":[-98.9375,22.50722],"type":"Point"}
}