{
  "type": "Feature",
  "properties": {
    "gn:admin1_code":"31",
    "gn:admin2_code":"61.0",
    "gn:asciiname":"Villa de Guadalupe",
    "gn:country_code":"MX",
    "gn:dem":7,
    "gn:feature_class":"P",
    "gn:feature_code":"PPL",
    "gn:name":"Villa de Guadalupe",
    "gn:population":0,
    "gn:timezone":"America/Merida",
    "iso:country":"MX",
    "name:spa_x_preferred":[
        "Villa de Guadalupe"
    ],
    "wof:name":"Villa de Guadalupe",
    "wof:placetype":"locality"
},
  "geometry": {"coordinates":[-88.10513,21.45381],"type":"Point"}
}