{
  "type": "Feature",
  "properties": {
    "gn:admin1_code":"12",
    "gn:admin2_code":"58.0",
    "gn:asciiname":"Ranchos Nuevos",
    "gn:country_code":"MX",
    "gn:dem":1626,
    "gn:feature_class":"P",
    "gn:feature_code":"PPL",
    "gn:name":"Ranchos Nuevos",
    "gn:population":0,
    "gn:timezone":"America/Mexico_City",
    "iso:country":"MX",
    "name:spa_x_preferred":[
        "Ranchos Nuevos"
    ],
    "name:und_x_variant":[
        "Rancho Nuevos"
    ],
    "wof:name":"Ranchos Nuevos",
    "wof:placetype":"locality"
},
  "geometry": {"coordinates":[-100.00467,18.41592],"type":"Point"}
}