{
  "type": "Feature",
  "properties": {
    "gn:admin1_code":"29",
    "gn:admin2_code":"3",
    "gn:asciiname":"San Jose Atlanga",
    "gn:country_code":"MX",
    "gn:dem":2497,
    "gn:feature_class":"P",
    "gn:feature_code":"PPL",
    "gn:name":"San Jos\u00e9 Atlanga",
    "gn:population":50,
    "gn:timezone":"America/Mexico_City",
    "iso:country":"MX",
    "name:und_x_variant":[
        "San Jos\u00e9 Atlanga"
    ],
    "wof:name":"San Jose Atlanga",
    "wof:placetype":"locality",
    "wof:population":50
},
  "geometry": {"coordinates":[-98.20480999999999,19.55082],"type":"Point"}
}