{
  "type": "Feature",
  "properties": {
    "gn:admin1_code":"30.0",
    "gn:admin2_code":"154.0",
    "gn:asciiname":"El Varal",
    "gn:country_code":"MX",
    "gn:dem":24,
    "gn:feature_class":"P",
    "gn:feature_code":"PPL",
    "gn:name":"El Varal",
    "gn:population":114,
    "gn:timezone":"America/Mexico_City",
    "iso:country":"MX",
    "name:spa_x_preferred":[
        "El Varal"
    ],
    "wof:name":"El Varal",
    "wof:placetype":"locality",
    "wof:population":114
},
  "geometry": {"coordinates":[-97.81194000000001,21.46361],"type":"Point"}
}