{
  "type": "Feature",
  "properties": {
    "gn:admin1_code":"24",
    "gn:admin2_code":"43.0",
    "gn:asciiname":"Sandoval",
    "gn:cc2":"MX",
    "gn:country_code":"MX",
    "gn:dem":1471,
    "gn:feature_class":"P",
    "gn:feature_code":"PPL",
    "gn:name":"Sandoval",
    "gn:population":12,
    "gn:timezone":"America/Mexico_City",
    "iso:country":"MX",
    "name:heb_x_preferred":[
        "\u05e1\u05e0\u05d3\u05d5\u05d1\u05dc"
    ],
    "name:rus_x_preferred":[
        "\u0421\u0430\u043d\u0434\u043e\u0432\u0430\u043b"
    ],
    "name:und_x_variant":[
        "Sandobal",
        "Sandoval"
    ],
    "wof:name":"Sandoval",
    "wof:placetype":"locality",
    "wof:population":12
},
  "geometry": {"coordinates":[-100.44611,21.67222000000001],"type":"Point"}
}