{
  "type": "Feature",
  "properties": {
    "gn:admin1_code":"5.0",
    "gn:asciiname":"Montecristo Huanacatal",
    "gn:country_code":"MX",
    "gn:dem":574,
    "gn:feature_class":"P",
    "gn:feature_code":"PPL",
    "gn:name":"Montecristo Huanacatal",
    "gn:population":0,
    "gn:timezone":"America/Mexico_City",
    "iso:country":"MX",
    "name:spa_x_preferred":[
        "Montecristo Huanacatal"
    ],
    "wof:name":"Montecristo Huanacatal",
    "wof:placetype":"locality"
},
  "geometry": {"coordinates":[-92.88702000000001,16.257],"type":"Point"}
}