{
  "type": "Feature",
  "properties": {
    "gn:admin1_code":"6",
    "gn:admin2_code":"46.0",
    "gn:asciiname":"Chicuritas",
    "gn:country_code":"MX",
    "gn:dem":1023,
    "gn:feature_class":"P",
    "gn:feature_code":"PPL",
    "gn:name":"Chicuritas",
    "gn:population":0,
    "gn:timezone":"America/Chihuahua",
    "iso:country":"MX",
    "name:spa_x_preferred":[
        "Chicuritas"
    ],
    "wof:name":"Chicuritas",
    "wof:placetype":"locality"
},
  "geometry": {"coordinates":[-107.54477,26.52723],"type":"Point"}
}