{
  "type": "Feature",
  "properties": {
    "gn:admin1_code":"23",
    "gn:admin2_code":"5.0",
    "gn:asciiname":"Flamingos",
    "gn:country_code":"MX",
    "gn:dem":10,
    "gn:feature_class":"P",
    "gn:feature_code":"PPL",
    "gn:name":"Flamingos",
    "gn:population":0,
    "gn:timezone":"America/Cancun",
    "iso:country":"MX",
    "name:spa_x_preferred":[
        "Flamingos"
    ],
    "wof:name":"Flamingos",
    "wof:placetype":"locality"
},
  "geometry": {"coordinates":[-86.87125,20.94322],"type":"Point"}
}