{
  "type": "Feature",
  "properties": {
    "gn:admin1_code":"25",
    "gn:admin2_code":"14.0",
    "gn:asciiname":"Ojo de Agua de Osuna",
    "gn:country_code":"MX",
    "gn:dem":35,
    "gn:feature_class":"P",
    "gn:feature_code":"PPL",
    "gn:name":"Ojo de Agua de Osuna",
    "gn:population":340,
    "gn:timezone":"America/Mazatlan",
    "iso:country":"MX",
    "wof:name":"Ojo de Agua de Osuna",
    "wof:placetype":"locality",
    "wof:population":340
},
  "geometry": {"coordinates":[-105.96444,23.02833],"type":"Point"}
}