{
  "type": "Feature",
  "properties": {
    "gn:admin1_code":"10",
    "gn:admin2_code":"12",
    "gn:asciiname":"El Cerrito de la Cruz",
    "gn:country_code":"MX",
    "gn:dem":1148,
    "gn:feature_class":"P",
    "gn:feature_code":"PPL",
    "gn:name":"El Cerrito de la Cruz",
    "gn:population":18,
    "gn:timezone":"America/Monterrey",
    "iso:country":"MX",
    "wof:name":"El Cerrito de la Cruz",
    "wof:placetype":"locality",
    "wof:population":18
},
  "geometry": {"coordinates":[-103.59562,25.52501],"type":"Point"}
}