{
  "type": "Feature",
  "properties": {
    "gn:admin1_code":"16.0",
    "gn:admin2_code":"22.0",
    "gn:asciiname":"Pie de la Mesa",
    "gn:country_code":"MX",
    "gn:dem":1972,
    "gn:feature_class":"P",
    "gn:feature_code":"PPL",
    "gn:name":"Pie de la Mesa",
    "gn:population":0,
    "gn:timezone":"America/Mexico_City",
    "iso:country":"MX",
    "name:spa_x_preferred":[
        "Pie de la Mesa"
    ],
    "wof:name":"Pie de la Mesa",
    "wof:placetype":"locality"
},
  "geometry": {"coordinates":[-100.94450000000001,19.61391],"type":"Point"}
}