{
  "type": "Feature",
  "properties": {
    "gn:admin1_code":"32",
    "gn:admin2_code":"19.0",
    "gn:asciiname":"Teocaltichillo",
    "gn:country_code":"MX",
    "gn:dem":1404,
    "gn:feature_class":"P",
    "gn:feature_code":"PPL",
    "gn:name":"Teocaltichillo",
    "gn:population":0,
    "gn:timezone":"America/Mexico_City",
    "iso:country":"MX",
    "name:spa_x_preferred":[
        "Teocaltichillo"
    ],
    "wof:name":"Teocaltichillo",
    "wof:placetype":"locality"
},
  "geometry": {"coordinates":[-102.94776,21.68599],"type":"Point"}
}