{
  "type": "Feature",
  "properties": {
    "gn:admin1_code":"21.0",
    "gn:admin2_code":"217.0",
    "gn:asciiname":"Tenextlacotla",
    "gn:country_code":"MX",
    "gn:dem":1743,
    "gn:feature_class":"P",
    "gn:feature_code":"PPL",
    "gn:name":"Tenextlacotla",
    "gn:population":0,
    "gn:timezone":"America/Mexico_City",
    "iso:country":"MX",
    "name:spa_x_preferred":[
        "Tenextlacotla"
    ],
    "wof:name":"Tenextlacotla",
    "wof:placetype":"locality"
},
  "geometry": {"coordinates":[-97.13612999999999,18.35693],"type":"Point"}
}