{
  "type": "Feature",
  "properties": {
    "gn:admin1_code":"19.0",
    "gn:admin2_code":"44.0",
    "gn:asciiname":"Paloma Blanca",
    "gn:country_code":"MX",
    "gn:dem":331,
    "gn:feature_class":"P",
    "gn:feature_code":"PPL",
    "gn:name":"Paloma Blanca",
    "gn:population":0,
    "gn:timezone":"America/Monterrey",
    "iso:country":"MX",
    "name:spa_x_preferred":[
        "Paloma Blanca"
    ],
    "wof:name":"Paloma Blanca",
    "wof:placetype":"locality"
},
  "geometry": {"coordinates":[-100.12685,26.40856],"type":"Point"}
}