{
  "type": "Feature",
  "properties": {
    "gn:admin1_code":"26",
    "gn:admin2_code":"66.0",
    "gn:asciiname":"Rancho las Sillas",
    "gn:country_code":"MX",
    "gn:dem":450,
    "gn:feature_class":"P",
    "gn:feature_code":"PPL",
    "gn:name":"Rancho las Sillas",
    "gn:population":0,
    "gn:timezone":"America/Hermosillo",
    "iso:country":"MX",
    "name:spa_x_preferred":[
        "Rancho Las Sillas"
    ],
    "wof:name":"Rancho las Sillas",
    "wof:placetype":"locality"
},
  "geometry": {"coordinates":[-110.30194,29.1275],"type":"Point"}
}