{
  "type": "Feature",
  "properties": {
    "gn:admin1_code":"32",
    "gn:admin2_code":"5",
    "gn:asciiname":"San Isidro",
    "gn:country_code":"MX",
    "gn:dem":2114,
    "gn:feature_class":"P",
    "gn:feature_code":"PPL",
    "gn:name":"San Isidro",
    "gn:population":12,
    "gn:timezone":"America/Mexico_City",
    "iso:country":"MX",
    "wof:name":"San Isidro",
    "wof:placetype":"locality",
    "wof:population":12
},
  "geometry": {"coordinates":[-102.62860999999999,23.01833],"type":"Point"}
}