{
  "type": "Feature",
  "properties": {
    "gn:admin1_code":"5.0",
    "gn:asciiname":"La Guadalupe",
    "gn:country_code":"MX",
    "gn:dem":357,
    "gn:feature_class":"P",
    "gn:feature_code":"PPL",
    "gn:name":"La Guadalupe",
    "gn:population":0,
    "gn:timezone":"America/Mexico_City",
    "iso:country":"MX",
    "name:spa_x_preferred":[
        "La Guadalupe"
    ],
    "wof:name":"La Guadalupe",
    "wof:placetype":"locality"
},
  "geometry": {"coordinates":[-93.15203,15.796],"type":"Point"}
}