{
  "type": "Feature",
  "properties": {
    "gn:admin1_code":"32",
    "gn:admin2_code":"16.0",
    "gn:asciiname":"San Antonio del Bordo",
    "gn:country_code":"MX",
    "gn:dem":2058,
    "gn:feature_class":"P",
    "gn:feature_code":"PPL",
    "gn:name":"San Antonio del Bordo",
    "gn:population":6,
    "gn:timezone":"America/Mexico_City",
    "iso:country":"MX",
    "wof:name":"San Antonio del Bordo",
    "wof:placetype":"locality",
    "wof:population":6
},
  "geometry": {"coordinates":[-102.08694,22.60833],"type":"Point"}
}