{
  "type": "Feature",
  "properties": {
    "gn:admin1_code":"11",
    "gn:admin2_code":"29.0",
    "gn:asciiname":"San Jose de Monjas",
    "gn:country_code":"MX",
    "gn:dem":2013,
    "gn:feature_class":"P",
    "gn:feature_code":"PPL",
    "gn:name":"San Jos\u00e9 de Monjas",
    "gn:population":99,
    "gn:timezone":"America/Mexico_City",
    "iso:country":"MX",
    "name:und_x_variant":[
        "San Jos\u00e9 de Monjas"
    ],
    "wof:name":"San Jose de Monjas",
    "wof:placetype":"locality",
    "wof:population":99
},
  "geometry": {"coordinates":[-100.92444,21.32167],"type":"Point"}
}