{
  "type": "Feature",
  "properties": {
    "gn:admin1_code":"20.0",
    "gn:admin2_code":"318.0",
    "gn:asciiname":"Las Salinas",
    "gn:country_code":"MX",
    "gn:dem":9,
    "gn:feature_class":"P",
    "gn:feature_code":"PPL",
    "gn:name":"Las Salinas",
    "gn:population":0,
    "gn:timezone":"America/Mexico_City",
    "iso:country":"MX",
    "name:spa_x_preferred":[
        "Las Salinas"
    ],
    "wof:name":"Las Salinas",
    "wof:placetype":"locality"
},
  "geometry": {"coordinates":[-97.1525,15.9281],"type":"Point"}
}