{
  "type": "Feature",
  "properties": {
    "gn:admin1_code":"16.0",
    "gn:admin2_code":"82.0",
    "gn:asciiname":"Puente de Tierra",
    "gn:country_code":"MX",
    "gn:dem":2022,
    "gn:feature_class":"P",
    "gn:feature_code":"PPL",
    "gn:name":"Puente de Tierra",
    "gn:population":0,
    "gn:timezone":"America/Mexico_City",
    "iso:country":"MX",
    "name:spa_x_preferred":[
        "Puente de Tierra"
    ],
    "wof:name":"Puente de Tierra",
    "wof:placetype":"locality"
},
  "geometry": {"coordinates":[-101.42881,19.29846],"type":"Point"}
}