{
  "type": "Feature",
  "properties": {
    "gn:admin1_code":"21",
    "gn:admin2_code":"83",
    "gn:asciiname":"El Sillero",
    "gn:country_code":"MX",
    "gn:dem":2789,
    "gn:feature_class":"P",
    "gn:feature_code":"PPL",
    "gn:name":"El Sillero",
    "gn:population":27,
    "gn:timezone":"America/Mexico_City",
    "iso:country":"MX",
    "wof:name":"El Sillero",
    "wof:placetype":"locality",
    "wof:population":27
},
  "geometry": {"coordinates":[-97.98984,19.66925],"type":"Point"}
}