{
  "type": "Feature",
  "properties": {
    "gn:admin1_code":"30.0",
    "gn:admin2_code":"192.0",
    "gn:asciiname":"La Planilla",
    "gn:country_code":"MX",
    "gn:dem":54,
    "gn:feature_class":"P",
    "gn:feature_code":"PPL",
    "gn:name":"La Planilla",
    "gn:population":2,
    "gn:timezone":"America/Mexico_City",
    "iso:country":"MX",
    "name:spa_x_preferred":[
        "La Planilla"
    ],
    "wof:name":"La Planilla",
    "wof:placetype":"locality",
    "wof:population":2
},
  "geometry": {"coordinates":[-96.69917,20.03611],"type":"Point"}
}