{
  "type": "Feature",
  "properties": {
    "gn:admin1_code":"25.0",
    "gn:admin2_code":"17.0",
    "gn:asciiname":"El Ranchito de Castro",
    "gn:country_code":"MX",
    "gn:dem":1267,
    "gn:feature_class":"P",
    "gn:feature_code":"PPL",
    "gn:name":"El Ranchito de Castro",
    "gn:population":0,
    "gn:timezone":"America/Mazatlan",
    "iso:country":"MX",
    "name:spa_x_preferred":[
        "El Ranchito de Castro"
    ],
    "wof:name":"El Ranchito de Castro",
    "wof:placetype":"locality"
},
  "geometry": {"coordinates":[-108.09896000000001,26.145],"type":"Point"}
}