{
  "type": "Feature",
  "properties": {
    "gn:admin1_code":"19",
    "gn:admin2_code":"40.0",
    "gn:asciiname":"Porfirio Abrego",
    "gn:country_code":"MX",
    "gn:dem":184,
    "gn:feature_class":"P",
    "gn:feature_code":"PPL",
    "gn:name":"Porfirio \u00c1brego",
    "gn:population":5,
    "gn:timezone":"America/Monterrey",
    "iso:country":"MX",
    "name:und_x_variant":[
        "Porfirio \u00c1brego"
    ],
    "wof:name":"Porfirio Abrego",
    "wof:placetype":"locality",
    "wof:population":5
},
  "geometry": {"coordinates":[-99.70837,26.49699],"type":"Point"}
}