{
  "type": "Feature",
  "properties": {
    "gn:admin1_code":"5",
    "gn:admin2_code":"17.0",
    "gn:asciiname":"El Horizonte",
    "gn:country_code":"MX",
    "gn:dem":689,
    "gn:feature_class":"P",
    "gn:feature_code":"PPL",
    "gn:name":"El Horizonte",
    "gn:population":7,
    "gn:timezone":"America/Mexico_City",
    "iso:country":"MX",
    "wof:name":"El Horizonte",
    "wof:placetype":"locality",
    "wof:population":7
},
  "geometry": {"coordinates":[-93.9875,16.48806],"type":"Point"}
}