{
  "type": "Feature",
  "properties": {
    "gn:admin1_code":"30.0",
    "gn:admin2_code":"121.0",
    "gn:asciiname":"Chapopote",
    "gn:country_code":"MX",
    "gn:dem":82,
    "gn:feature_class":"P",
    "gn:feature_code":"PPL",
    "gn:name":"Chapopote",
    "gn:population":0,
    "gn:timezone":"America/Mexico_City",
    "iso:country":"MX",
    "name:spa_x_preferred":[
        "Chapopote"
    ],
    "wof:name":"Chapopote",
    "wof:placetype":"locality"
},
  "geometry": {"coordinates":[-97.95377000000001,21.4851],"type":"Point"}
}