{
  "type": "Feature",
  "properties": {
    "gn:admin1_code":"24",
    "gn:admin2_code":"49.0",
    "gn:asciiname":"El Duraznillo",
    "gn:country_code":"MX",
    "gn:dem":2175,
    "gn:feature_class":"P",
    "gn:feature_code":"PPL",
    "gn:name":"El Duraznillo",
    "gn:population":7,
    "gn:timezone":"America/Mexico_City",
    "iso:country":"MX",
    "wof:name":"El Duraznillo",
    "wof:placetype":"locality",
    "wof:population":7
},
  "geometry": {"coordinates":[-101.78333000000001,23.00722],"type":"Point"}
}