{
  "type": "Feature",
  "properties": {
    "gn:admin1_code":"16.0",
    "gn:admin2_code":"99.0",
    "gn:asciiname":"Mesita Redonda",
    "gn:country_code":"MX",
    "gn:dem":1418,
    "gn:feature_class":"P",
    "gn:feature_code":"PPL",
    "gn:name":"Mesita Redonda",
    "gn:population":0,
    "gn:timezone":"America/Mexico_City",
    "iso:country":"MX",
    "name:spa_x_preferred":[
        "Mesita Redonda"
    ],
    "wof:name":"Mesita Redonda",
    "wof:placetype":"locality"
},
  "geometry": {"coordinates":[-100.59099000000001,19.37149],"type":"Point"}
}