{
  "type": "Feature",
  "properties": {
    "gn:admin1_code":"6",
    "gn:admin2_code":"28.0",
    "gn:asciiname":"Luis Leon de Abajo",
    "gn:country_code":"MX",
    "gn:dem":1063,
    "gn:feature_class":"P",
    "gn:feature_code":"PPL",
    "gn:name":"Luis Leon de Abajo",
    "gn:population":0,
    "gn:timezone":"America/Chihuahua",
    "iso:country":"MX",
    "name:spa_x_preferred":[
        "Luis Le\u00f3n de Abajo"
    ],
    "wof:name":"Luis Leon de Abajo",
    "wof:placetype":"locality"
},
  "geometry": {"coordinates":[-105.64221000000001,31.09263],"type":"Point"}
}