{
  "type": "Feature",
  "properties": {
    "gn:admin1_code":"6",
    "gn:admin2_code":"44.0",
    "gn:asciiname":"Las Pompas",
    "gn:country_code":"MX",
    "gn:dem":1804,
    "gn:feature_class":"P",
    "gn:feature_code":"PPL",
    "gn:name":"Las Pompas",
    "gn:population":0,
    "gn:timezone":"America/Monterrey",
    "iso:country":"MX",
    "name:spa_x_preferred":[
        "Cerro Colorado"
    ],
    "name:und_x_variant":[
        "Rancho Las Pompas",
        "Las Pompas"
    ],
    "wof:name":"Las Pompas",
    "wof:placetype":"locality"
},
  "geometry": {"coordinates":[-105.61551,26.64752],"type":"Point"}
}