{
  "type": "Feature",
  "properties": {
    "gn:admin1_code":"5.0",
    "gn:admin2_code":"51.0",
    "gn:asciiname":"Santa Rosita",
    "gn:country_code":"MX",
    "gn:dem":32,
    "gn:feature_class":"P",
    "gn:feature_code":"PPL",
    "gn:name":"Santa Rosita",
    "gn:population":0,
    "gn:timezone":"America/Mexico_City",
    "iso:country":"MX",
    "name:ceb_x_preferred":[
        "Santa Rosita"
    ],
    "name:spa_x_preferred":[
        "Santa Rosita"
    ],
    "name:srp_x_preferred":[
        "\u0421\u0430\u043d\u0442\u0430 \u0420\u043e\u0441\u0438\u0442\u0430"
    ],
    "name:swe_x_preferred":[
        "Santa Rosita"
    ],
    "wof:name":"Santa Rosita",
    "wof:placetype":"locality"
},
  "geometry": {"coordinates":[-92.95429,15.44263],"type":"Point"}
}