{
  "type": "Feature",
  "properties": {
    "gn:admin1_code":"25",
    "gn:admin2_code":"17.0",
    "gn:asciiname":"Los Mezcales",
    "gn:country_code":"MX",
    "gn:dem":225,
    "gn:feature_class":"P",
    "gn:feature_code":"PPL",
    "gn:name":"Los Mezcales",
    "gn:population":0,
    "gn:timezone":"America/Mazatlan",
    "iso:country":"MX",
    "name:spa_x_preferred":[
        "Los Mezcales"
    ],
    "wof:name":"Los Mezcales",
    "wof:placetype":"locality"
},
  "geometry": {"coordinates":[-107.87887000000001,25.99837],"type":"Point"}
}