{
  "type": "Feature",
  "properties": {
    "gn:admin1_code":"23",
    "gn:admin2_code":"3.0",
    "gn:asciiname":"El Palomo",
    "gn:country_code":"MX",
    "gn:dem":9,
    "gn:feature_class":"P",
    "gn:feature_code":"PPL",
    "gn:name":"El Palomo",
    "gn:population":7,
    "gn:timezone":"America/Cancun",
    "iso:country":"MX",
    "wof:name":"El Palomo",
    "wof:placetype":"locality",
    "wof:population":7
},
  "geometry": {"coordinates":[-87.08794,21.2121],"type":"Point"}
}