{
  "type": "Feature",
  "properties": {
    "gn:admin1_code":"5.0",
    "gn:admin2_code":"64.0",
    "gn:asciiname":"Chenchauc",
    "gn:country_code":"MX",
    "gn:dem":2018,
    "gn:feature_class":"P",
    "gn:feature_code":"PPL",
    "gn:name":"Chenchauc",
    "gn:population":0,
    "gn:timezone":"America/Mexico_City",
    "iso:country":"MX",
    "name:spa_x_preferred":[
        "Chenchauc"
    ],
    "wof:name":"Chenchauc",
    "wof:placetype":"locality"
},
  "geometry": {"coordinates":[-92.3201,16.78588],"type":"Point"}
}