{
  "type": "Feature",
  "properties": {
    "gn:admin1_code":"7",
    "gn:admin2_code":"30.0",
    "gn:asciiname":"La Campamocha",
    "gn:country_code":"MX",
    "gn:dem":1724,
    "gn:feature_class":"P",
    "gn:feature_code":"PPL",
    "gn:name":"La Campamocha",
    "gn:population":7,
    "gn:timezone":"America/Monterrey",
    "iso:country":"MX",
    "wof:name":"La Campamocha",
    "wof:placetype":"locality",
    "wof:population":7
},
  "geometry": {"coordinates":[-101.04892,25.3806],"type":"Point"}
}