{
  "type": "Feature",
  "properties": {
    "gn:admin1_code":"25",
    "gn:admin2_code":"3.0",
    "gn:asciiname":"El Reparo",
    "gn:country_code":"MX",
    "gn:dem":898,
    "gn:feature_class":"P",
    "gn:feature_code":"PPL",
    "gn:name":"El Reparo",
    "gn:population":54,
    "gn:timezone":"America/Mazatlan",
    "iso:country":"MX",
    "wof:name":"El Reparo",
    "wof:placetype":"locality",
    "wof:population":54
},
  "geometry": {"coordinates":[-107.33228,25.64069],"type":"Point"}
}