{
  "type": "Feature",
  "properties": {
    "gn:admin1_code":"14.0",
    "gn:admin2_code":"12.0",
    "gn:asciiname":"La Guasima",
    "gn:country_code":"MX",
    "gn:dem":1354,
    "gn:feature_class":"P",
    "gn:feature_code":"PPL",
    "gn:name":"La Gu\u00e1sima",
    "gn:population":0,
    "gn:timezone":"America/Mexico_City",
    "iso:country":"MX",
    "name:spa_x_preferred":[
        "La Gu\u00e1sima"
    ],
    "wof:name":"La Guasima",
    "wof:placetype":"locality"
},
  "geometry": {"coordinates":[-104.47803999999999,20.47419],"type":"Point"}
}