{
  "type": "Feature",
  "properties": {
    "gn:admin1_code":"26",
    "gn:admin2_code":"29.0",
    "gn:asciiname":"Guasimas (De Belem)",
    "gn:country_code":"MX",
    "gn:dem":5,
    "gn:feature_class":"P",
    "gn:feature_code":"PPL",
    "gn:name":"Gu\u00e1simas (De Belem)",
    "gn:population":1804,
    "gn:timezone":"America/Hermosillo",
    "iso:country":"MX",
    "name:und_x_variant":[
        "Gu\u00e1simas (De Belem)"
    ],
    "wof:name":"Guasimas (De Belem)",
    "wof:placetype":"locality",
    "wof:population":1804
},
  "geometry": {"coordinates":[-110.58167,27.88583],"type":"Point"}
}