{
  "type": "Feature",
  "properties": {
    "gn:admin1_code":"26",
    "gn:admin2_code":"17",
    "gn:asciiname":"Santa Silvia",
    "gn:country_code":"MX",
    "gn:dem":45,
    "gn:feature_class":"P",
    "gn:feature_code":"PPL",
    "gn:name":"Santa Silvia",
    "gn:population":10,
    "gn:timezone":"America/Hermosillo",
    "iso:country":"MX",
    "wof:name":"Santa Silvia",
    "wof:placetype":"locality",
    "wof:population":10
},
  "geometry": {"coordinates":[-112.86806,30.94194],"type":"Point"}
}