{
  "type": "Feature",
  "properties": {
    "gn:admin1_code":"20",
    "gn:admin2_code":"397.0",
    "gn:asciiname":"Canada Maria (Segunda Seccion)",
    "gn:country_code":"MX",
    "gn:dem":2206,
    "gn:feature_class":"P",
    "gn:feature_code":"PPL",
    "gn:name":"Ca\u00f1ada Mar\u00eda (Segunda Secci\u00f3n)",
    "gn:population":146,
    "gn:timezone":"America/Mexico_City",
    "iso:country":"MX",
    "name:und_x_variant":[
        "Ca\u00f1ada Mar\u00eda (Segunda Secci\u00f3n)"
    ],
    "wof:name":"Canada Maria (Segunda Seccion)",
    "wof:placetype":"locality",
    "wof:population":146
},
  "geometry": {"coordinates":[-97.60111000000001,17.29361],"type":"Point"}
}