{
  "type": "Feature",
  "properties": {
    "gn:admin1_code":"12.0",
    "gn:admin2_code":"59.0",
    "gn:asciiname":"Soyacruz",
    "gn:country_code":"MX",
    "gn:dem":1058,
    "gn:feature_class":"P",
    "gn:feature_code":"PPL",
    "gn:name":"Soyacruz",
    "gn:population":0,
    "gn:timezone":"America/Mexico_City",
    "iso:country":"MX",
    "name:spa_x_preferred":[
        "Soyacruz"
    ],
    "wof:name":"Soyacruz",
    "wof:placetype":"locality"
},
  "geometry": {"coordinates":[-99.40797000000001,18.08039],"type":"Point"}
}