{
  "type": "Feature",
  "properties": {
    "gn:admin1_code":"20.0",
    "gn:asciiname":"Agua Dulce",
    "gn:country_code":"MX",
    "gn:dem":16,
    "gn:feature_class":"P",
    "gn:feature_code":"PPL",
    "gn:name":"Agua Dulce",
    "gn:population":0,
    "gn:timezone":"America/Mexico_City",
    "iso:country":"MX",
    "name:cat_x_preferred":[
        "Agua Dulce"
    ],
    "name:ceb_x_preferred":[
        "Agua Dulce"
    ],
    "name:deu_x_preferred":[
        "Agua Dulce"
    ],
    "name:fra_x_preferred":[
        "Agua Dulce"
    ],
    "name:ita_x_preferred":[
        "Agua Dulce"
    ],
    "name:nld_x_preferred":[
        "Agua Dulce"
    ],
    "name:pol_x_preferred":[
        "Agua Dulce"
    ],
    "name:por_x_preferred":[
        "Agua Dulce"
    ],
    "name:rus_x_preferred":[
        "\u0410\u0433\u0443\u0430-\u0414\u0443\u043b\u044c\u0441\u0435"
    ],
    "name:spa_x_preferred":[
        "Agua Dulce"
    ],
    "name:swe_x_preferred":[
        "Agua Dulce"
    ],
    "name:ukr_x_preferred":[
        "\u0410\u0433\u0432\u0430-\u0414\u0443\u043b\u044c\u0441\u0435"
    ],
    "name:vie_x_preferred":[
        "Agua Dulce"
    ],
    "name:vol_x_preferred":[
        "Agua Dulce"
    ],
    "wof:name":"Agua Dulce",
    "wof:placetype":"locality"
},
  "geometry": {"coordinates":[-98.21263999999999,16.2725],"type":"Point"}
}