{
  "type": "Feature",
  "properties": {
    "gn:admin1_code":"20.0",
    "gn:asciiname":"Agua Dulce",
    "gn:country_code":"MX",
    "gn:dem":16,
    "gn:feature_class":"P",
    "gn:feature_code":"PPL",
    "gn:name":"Agua Dulce",
    "gn:population":0,
    "gn:timezone":"America/Mexico_City",
    "iso:country":"MX",
    "name:spa_x_preferred":[
        "Agua Dulce"
    ],
    "wof:name":"Agua Dulce",
    "wof:placetype":"locality"
},
  "geometry": {"coordinates":[-98.21263999999999,16.2725],"type":"Point"}
}