{
  "type": "Feature",
  "properties": {
    "gn:admin1_code":"14.0",
    "gn:admin2_code":"100.0",
    "gn:asciiname":"Amacueca",
    "gn:country_code":"MX",
    "gn:dem":924,
    "gn:feature_class":"P",
    "gn:feature_code":"PPLL",
    "gn:name":"Amacueca",
    "gn:population":0,
    "gn:timezone":"America/Mexico_City",
    "iso:country":"MX",
    "name:ceb_x_preferred":[
        "Amacueca"
    ],
    "name:epo_x_preferred":[
        "Amacueca"
    ],
    "name:eus_x_preferred":[
        "Amacueca"
    ],
    "name:fas_x_preferred":[
        "\u0627\u0645\u0627\u06a9\u0648\u0626\u06a9\u0627"
    ],
    "name:ita_x_preferred":[
        "Amacueca"
    ],
    "name:pol_x_preferred":[
        "Amacueca"
    ],
    "name:por_x_preferred":[
        "Amacueca"
    ],
    "name:sco_x_preferred":[
        "Amacueca"
    ],
    "name:spa_x_preferred":[
        "Amacueca"
    ],
    "name:srp_x_preferred":[
        "\u041e\u043f\u0448\u0442\u0438\u043d\u0430 \u0410\u043c\u0430\u043a\u0443\u0435\u043a\u0430"
    ],
    "name:swe_x_preferred":[
        "Amacueca"
    ],
    "name:vie_x_preferred":[
        "Amacueca"
    ],
    "wof:name":"Amacueca",
    "wof:placetype":"locality"
},
  "geometry": {"coordinates":[-104.67541,20.08072],"type":"Point"}
}