{
  "type": "Feature",
  "properties": {
    "gn:admin1_code":"14.0",
    "gn:admin2_code":"100.0",
    "gn:asciiname":"Amacueca",
    "gn:country_code":"MX",
    "gn:dem":924,
    "gn:feature_class":"P",
    "gn:feature_code":"PPLL",
    "gn:name":"Amacueca",
    "gn:population":0,
    "gn:timezone":"America/Mexico_City",
    "iso:country":"MX",
    "name:spa_x_preferred":[
        "Amacueca"
    ],
    "wof:name":"Amacueca",
    "wof:placetype":"locality"
},
  "geometry": {"coordinates":[-104.67541,20.08072],"type":"Point"}
}