{
  "type": "Feature",
  "properties": {
    "gn:admin1_code":"15",
    "gn:admin2_code":"114.0",
    "gn:asciiname":"Piedras Blancas (Piedras Blancas Centro)",
    "gn:country_code":"MX",
    "gn:dem":2883,
    "gn:feature_class":"P",
    "gn:feature_code":"PPL",
    "gn:name":"Piedras Blancas (Piedras Blancas Centro)",
    "gn:population":756,
    "gn:timezone":"America/Mexico_City",
    "iso:country":"MX",
    "wof:name":"Piedras Blancas (Piedras Blancas Centro)",
    "wof:placetype":"locality",
    "wof:population":756
},
  "geometry": {"coordinates":[-99.935,19.52639],"type":"Point"}
}