{
  "type": "Feature",
  "properties": {
    "gn:admin1_code":"14.0",
    "gn:admin2_code":"5.0",
    "gn:asciiname":"Sacamecate",
    "gn:country_code":"MX",
    "gn:dem":1299,
    "gn:feature_class":"P",
    "gn:feature_code":"PPL",
    "gn:name":"Sacamecate",
    "gn:population":0,
    "gn:timezone":"America/Mexico_City",
    "iso:country":"MX",
    "name:spa_x_preferred":[
        "Sacamecate"
    ],
    "name:spa_x_variant":[
        "El Zacamecate"
    ],
    "wof:name":"Sacamecate",
    "wof:placetype":"locality"
},
  "geometry": {"coordinates":[-103.74883,20.82893],"type":"Point"}
}