{
  "type": "Feature",
  "properties": {
    "gn:admin1_code":"10.0",
    "gn:admin2_code":"28.0",
    "gn:asciiname":"Jose Maria Patoni",
    "gn:country_code":"MX",
    "gn:dem":1603,
    "gn:feature_class":"P",
    "gn:feature_code":"PPL",
    "gn:name":"Jos\u00e9 Mar\u00eda Patoni",
    "gn:population":0,
    "gn:timezone":"America/Monterrey",
    "iso:country":"MX",
    "name:und_x_variant":[
        "Menores de Arriba",
        "Jos\u00e9 Mar\u00eda Pathoni",
        "Jos\u00e9 Mar\u00eda Patoni"
    ],
    "wof:name":"Jose Maria Patoni",
    "wof:placetype":"locality"
},
  "geometry": {"coordinates":[-104.44681,24.87816],"type":"Point"}
}