{
  "type": "Feature",
  "properties": {
    "gn:admin1_code":"27",
    "gn:admin2_code":"2.0",
    "gn:asciiname":"La Encrucijada Primera Seccion",
    "gn:country_code":"MX",
    "gn:dem":10,
    "gn:feature_class":"P",
    "gn:feature_code":"PPL",
    "gn:name":"La Encrucijada Primera Secci\u00f3n",
    "gn:population":0,
    "gn:timezone":"America/Mexico_City",
    "iso:country":"MX",
    "name:spa_x_preferred":[
        "La Encrucijada Primera Secci\u00f3n"
    ],
    "wof:name":"La Encrucijada Primera Seccion",
    "wof:placetype":"locality"
},
  "geometry": {"coordinates":[-93.57083,18.20833],"type":"Point"}
}