{
  "type": "Feature",
  "properties": {
    "gn:admin1_code":"26",
    "gn:admin2_code":"52.0",
    "gn:asciiname":"Tiopare",
    "gn:country_code":"MX",
    "gn:dem":1550,
    "gn:feature_class":"P",
    "gn:feature_code":"PPL",
    "gn:name":"Tiopare",
    "gn:population":0,
    "gn:timezone":"America/Hermosillo",
    "iso:country":"MX",
    "wof:name":"Tiopare",
    "wof:placetype":"locality"
},
  "geometry": {"coordinates":[-108.96666999999999,29.08333],"type":"Point"}
}