{
  "type": "Feature",
  "properties": {
    "gn:admin1_code":"30",
    "gn:admin2_code":"72",
    "gn:asciiname":"Las Joyas",
    "gn:country_code":"MX",
    "gn:dem":1147,
    "gn:feature_class":"P",
    "gn:feature_code":"PPL",
    "gn:name":"Las Joyas",
    "gn:population":29,
    "gn:timezone":"America/Mexico_City",
    "iso:country":"MX",
    "wof:name":"Las Joyas",
    "wof:placetype":"locality",
    "wof:population":29
},
  "geometry": {"coordinates":[-98.35306,20.68611],"type":"Point"}
}