{
  "type": "Feature",
  "properties": {
    "gn:admin1_code":"6.0",
    "gn:admin2_code":"67.0",
    "gn:asciiname":"Las Tinajitas",
    "gn:country_code":"MX",
    "gn:dem":1322,
    "gn:feature_class":"P",
    "gn:feature_code":"PPL",
    "gn:name":"Las Tinajitas",
    "gn:population":0,
    "gn:timezone":"America/Chihuahua",
    "iso:country":"MX",
    "name:spa_x_preferred":[
        "Las Tinajitas"
    ],
    "wof:name":"Las Tinajitas",
    "wof:placetype":"locality"
},
  "geometry": {"coordinates":[-105.68074,27.56249],"type":"Point"}
}