{
  "type": "Feature",
  "properties": {
    "gn:admin1_code":"2.0",
    "gn:admin2_code":"2.0",
    "gn:asciiname":"Campo Rio Hardy",
    "gn:country_code":"MX",
    "gn:dem":8,
    "gn:feature_class":"P",
    "gn:feature_code":"PPL",
    "gn:name":"Campo R\u00edo Hardy",
    "gn:population":0,
    "gn:timezone":"America/Tijuana",
    "iso:country":"MX",
    "wof:name":"Campo Rio Hardy",
    "wof:placetype":"locality"
},
  "geometry": {"coordinates":[-115.28297999999999,32.14021],"type":"Point"}
}