{
  "type": "Feature",
  "properties": {
    "gn:admin1_code":"3.0",
    "gn:admin2_code":"3.0",
    "gn:asciiname":"El Medano",
    "gn:country_code":"MX",
    "gn:dem":13,
    "gn:feature_class":"P",
    "gn:feature_code":"PPL",
    "gn:name":"El M\u00e9dano",
    "gn:population":0,
    "gn:timezone":"America/Mazatlan",
    "iso:country":"MX",
    "name:spa_x_preferred":[
        "El M\u00e9dano"
    ],
    "wof:name":"El Medano",
    "wof:placetype":"locality"
},
  "geometry": {"coordinates":[-111.50296000000002,24.53781],"type":"Point"}
}