{
  "type": "Feature",
  "properties": {
    "gn:admin1_code":"26.0",
    "gn:admin2_code":"66.0",
    "gn:asciiname":"Hacienda de Romo",
    "gn:country_code":"MX",
    "gn:dem":387,
    "gn:feature_class":"P",
    "gn:feature_code":"PPL",
    "gn:name":"Hacienda de Romo",
    "gn:population":0,
    "gn:timezone":"America/Hermosillo",
    "iso:country":"MX",
    "name:spa_x_preferred":[
        "Hacienda de Romo"
    ],
    "wof:name":"Hacienda de Romo",
    "wof:placetype":"locality"
},
  "geometry": {"coordinates":[-110.38867999999999,29.44946],"type":"Point"}
}