{
  "type": "Feature",
  "properties": {
    "gn:admin1_code":"6.0",
    "gn:asciiname":"El Recuerdo",
    "gn:country_code":"MX",
    "gn:dem":1162,
    "gn:feature_class":"P",
    "gn:feature_code":"PPL",
    "gn:name":"El Recuerdo",
    "gn:population":0,
    "gn:timezone":"America/Chihuahua",
    "iso:country":"MX",
    "name:spa_x_preferred":[
        "El Recuerdo"
    ],
    "wof:name":"El Recuerdo",
    "wof:placetype":"locality"
},
  "geometry": {"coordinates":[-105.50207,28.2056],"type":"Point"}
}