{
  "type": "Feature",
  "properties": {
    "gn:admin1_code":"12",
    "gn:admin2_code":"22.0",
    "gn:asciiname":"Los Pinzones",
    "gn:cc2":"MX",
    "gn:country_code":"MX",
    "gn:dem":853,
    "gn:feature_class":"P",
    "gn:feature_code":"PPL",
    "gn:name":"Los Pinzones",
    "gn:population":0,
    "gn:timezone":"America/Mexico_City",
    "iso:country":"MX",
    "name:und_x_variant":[
        "Pinzones",
        "Los Pinzanes",
        "Los Pinzones"
    ],
    "wof:name":"Los Pinzones",
    "wof:placetype":"locality"
},
  "geometry": {"coordinates":[-100.76667,17.91667],"type":"Point"}
}