{
  "type": "Feature",
  "properties": {
    "gn:admin1_code":"16",
    "gn:admin2_code":"49",
    "gn:asciiname":"El Cuirindal",
    "gn:country_code":"MX",
    "gn:dem":806,
    "gn:feature_class":"P",
    "gn:feature_code":"PPL",
    "gn:name":"El Cuirindal",
    "gn:population":19,
    "gn:timezone":"America/Mexico_City",
    "iso:country":"MX",
    "wof:name":"El Cuirindal",
    "wof:placetype":"locality",
    "wof:population":19
},
  "geometry": {"coordinates":[-101.07222,19.18944],"type":"Point"}
}