{
  "type": "Feature",
  "properties": {
    "gn:admin1_code":"13",
    "gn:admin2_code":"34",
    "gn:asciiname":"La Pimienta",
    "gn:country_code":"MX",
    "gn:dem":598,
    "gn:feature_class":"P",
    "gn:feature_code":"PPL",
    "gn:name":"La Pimienta",
    "gn:population":36,
    "gn:timezone":"America/Mexico_City",
    "iso:country":"MX",
    "wof:name":"La Pimienta",
    "wof:placetype":"locality",
    "wof:population":36
},
  "geometry": {"coordinates":[-98.73502000000001,21.10867],"type":"Point"}
}