{
  "type": "Feature",
  "properties": {
    "gn:admin1_code":"20",
    "gn:admin2_code":"272",
    "gn:asciiname":"Mazaqueztla",
    "gn:country_code":"MX",
    "gn:dem":489,
    "gn:feature_class":"P",
    "gn:feature_code":"PPL",
    "gn:name":"Mazaqueztla",
    "gn:population":49,
    "gn:timezone":"America/Mexico_City",
    "iso:country":"MX",
    "wof:name":"Mazaqueztla",
    "wof:placetype":"locality",
    "wof:population":49
},
  "geometry": {"coordinates":[-97.45417,16.26889],"type":"Point"}
}