{
  "type": "Feature",
  "properties": {
    "gn:admin1_code":"24",
    "gn:admin2_code":"2.0",
    "gn:asciiname":"Olla del Durazno (Joya del Durazno)",
    "gn:country_code":"MX",
    "gn:dem":1183,
    "gn:feature_class":"P",
    "gn:feature_code":"PPL",
    "gn:name":"Olla del Durazno (Joya del Durazno)",
    "gn:population":263,
    "gn:timezone":"America/Mexico_City",
    "iso:country":"MX",
    "wof:name":"Olla del Durazno (Joya del Durazno)",
    "wof:placetype":"locality",
    "wof:population":263
},
  "geometry": {"coordinates":[-99.46361,21.98806],"type":"Point"}
}