{
  "type": "Feature",
  "properties": {
    "gn:admin1_code":"5",
    "gn:admin2_code":"16.0",
    "gn:asciiname":"Cuauhtemoc",
    "gn:country_code":"MX",
    "gn:dem":33,
    "gn:feature_class":"P",
    "gn:feature_code":"PPL",
    "gn:name":"Cuauht\u00e9moc",
    "gn:population":728,
    "gn:timezone":"America/Mexico_City",
    "iso:country":"MX",
    "name:und_x_variant":[
        "Cuauht\u00e9moc"
    ],
    "wof:name":"Cuauhtemoc",
    "wof:placetype":"locality",
    "wof:population":728
},
  "geometry": {"coordinates":[-92.09667,17.69889],"type":"Point"}
}