{
  "type": "Feature",
  "properties": {
    "gn:admin1_code":"14",
    "gn:admin2_code":"124.0",
    "gn:asciiname":"Senoritas",
    "gn:country_code":"MX",
    "gn:dem":1698,
    "gn:feature_class":"P",
    "gn:feature_code":"PPL",
    "gn:name":"Se\u00f1oritas",
    "gn:population":173,
    "gn:timezone":"America/Mexico_City",
    "iso:country":"MX",
    "name:und_x_variant":[
        "Se\u00f1oritas"
    ],
    "wof:name":"Senoritas",
    "wof:placetype":"locality",
    "wof:population":173
},
  "geometry": {"coordinates":[-103.07528000000001,20.73167],"type":"Point"}
}