{
  "type": "Feature",
  "properties": {
    "gn:admin1_code":"16.0",
    "gn:admin2_code":"10.0",
    "gn:asciiname":"Barranca Prieta",
    "gn:country_code":"MX",
    "gn:dem":828,
    "gn:feature_class":"P",
    "gn:feature_code":"PPL",
    "gn:name":"Barranca Prieta",
    "gn:population":0,
    "gn:timezone":"America/Mexico_City",
    "iso:country":"MX",
    "name:spa_x_preferred":[
        "Barranca Prieta"
    ],
    "wof:name":"Barranca Prieta",
    "wof:placetype":"locality"
},
  "geometry": {"coordinates":[-102.59632000000001,18.33868],"type":"Point"}
}