{
  "type": "Feature",
  "properties": {
    "gn:admin1_code":"24",
    "gn:admin2_code":"13.0",
    "gn:asciiname":"El Sabino",
    "gn:cc2":"MX",
    "gn:country_code":"MX",
    "gn:dem":116,
    "gn:feature_class":"P",
    "gn:feature_code":"PPL",
    "gn:name":"El Sabino",
    "gn:population":0,
    "gn:timezone":"America/Mexico_City",
    "iso:country":"MX",
    "name:und_x_variant":[
        "Sabino",
        "Sabido",
        "El Sabino"
    ],
    "wof:name":"El Sabino",
    "wof:placetype":"locality"
},
  "geometry": {"coordinates":[-99.08333,21.91667],"type":"Point"}
}