{
  "type": "Feature",
  "properties": {
    "gn:admin1_code":"26.0",
    "gn:admin2_code":"49.0",
    "gn:asciiname":"El Bateve",
    "gn:country_code":"MX",
    "gn:dem":261,
    "gn:feature_class":"P",
    "gn:feature_code":"PPL",
    "gn:name":"El Bateve",
    "gn:population":0,
    "gn:timezone":"America/Hermosillo",
    "iso:country":"MX",
    "name:spa_x_preferred":[
        "El Bateve"
    ],
    "wof:name":"El Bateve",
    "wof:placetype":"locality"
},
  "geometry": {"coordinates":[-109.40300000000001,27.58282],"type":"Point"}
}