{
  "type": "Feature",
  "properties": {
    "gn:admin1_code":"19.0",
    "gn:admin2_code":"11.0",
    "gn:asciiname":"La Diana",
    "gn:country_code":"MX",
    "gn:dem":433,
    "gn:feature_class":"P",
    "gn:feature_code":"PPL",
    "gn:name":"La Diana",
    "gn:population":0,
    "gn:timezone":"America/Monterrey",
    "iso:country":"MX",
    "name:spa_x_preferred":[
        "La Diana"
    ],
    "name:und_x_variant":[
        "Las Vallas"
    ],
    "wof:name":"La Diana",
    "wof:placetype":"locality"
},
  "geometry": {"coordinates":[-99.74115,25.98621],"type":"Point"}
}