{
  "type": "Feature",
  "properties": {
    "gn:admin1_code":"5",
    "gn:admin2_code":"69.0",
    "gn:asciiname":"Sin Pensar",
    "gn:country_code":"MX",
    "gn:dem":36,
    "gn:feature_class":"P",
    "gn:feature_code":"PPL",
    "gn:name":"Sin Pensar",
    "gn:population":8,
    "gn:timezone":"America/Mexico_City",
    "iso:country":"MX",
    "wof:name":"Sin Pensar",
    "wof:placetype":"locality",
    "wof:population":8
},
  "geometry": {"coordinates":[-92.99806,15.4975],"type":"Point"}
}