{
  "type": "Feature",
  "properties": {
    "gn:admin1_code":"7",
    "gn:admin2_code":"23.0",
    "gn:asciiname":"Pena Alba",
    "gn:country_code":"MX",
    "gn:dem":1282,
    "gn:feature_class":"P",
    "gn:feature_code":"PPL",
    "gn:name":"Pe\u00f1a Alba",
    "gn:population":0,
    "gn:timezone":"America/Monterrey",
    "iso:country":"MX",
    "wof:name":"Pena Alba",
    "wof:placetype":"locality"
},
  "geometry": {"coordinates":[-102.49939999999999,27.47178],"type":"Point"}
}