{
  "type": "Feature",
  "properties": {
    "gn:admin1_code":"12",
    "gn:admin2_code":"58",
    "gn:asciiname":"Las Neblinas",
    "gn:country_code":"MX",
    "gn:dem":1823,
    "gn:feature_class":"P",
    "gn:feature_code":"PPL",
    "gn:name":"Las Neblinas",
    "gn:population":52,
    "gn:timezone":"America/Mexico_City",
    "iso:country":"MX",
    "wof:name":"Las Neblinas",
    "wof:placetype":"locality",
    "wof:population":52
},
  "geometry": {"coordinates":[-99.98848,18.43302000000001],"type":"Point"}
}