{
  "type": "Feature",
  "properties": {
    "gn:admin1_code":"10",
    "gn:admin2_code":"29.0",
    "gn:asciiname":"El Alamito",
    "gn:country_code":"MX",
    "gn:dem":1583,
    "gn:feature_class":"P",
    "gn:feature_code":"PPL",
    "gn:name":"El Alamito",
    "gn:population":0,
    "gn:timezone":"America/Monterrey",
    "iso:country":"MX",
    "name:spa_x_preferred":[
        "El Alamito"
    ],
    "wof:name":"El Alamito",
    "wof:placetype":"locality"
},
  "geometry": {"coordinates":[-104.30365999999999,25.33893],"type":"Point"}
}