{
  "type": "Feature",
  "properties": {
    "gn:admin1_code":"10",
    "gn:admin2_code":"14",
    "gn:asciiname":"La Nopalera",
    "gn:country_code":"MX",
    "gn:dem":1602,
    "gn:feature_class":"P",
    "gn:feature_code":"PPL",
    "gn:name":"La Nopalera",
    "gn:population":15,
    "gn:timezone":"America/Monterrey",
    "iso:country":"MX",
    "wof:name":"La Nopalera",
    "wof:placetype":"locality",
    "wof:population":15
},
  "geometry": {"coordinates":[-104.46912,22.80531],"type":"Point"}
}