{
  "type": "Feature",
  "properties": {
    "gn:admin1_code":"20.0",
    "gn:admin2_code":"401.0",
    "gn:asciiname":"La Cazuela",
    "gn:country_code":"MX",
    "gn:dem":61,
    "gn:feature_class":"P",
    "gn:feature_code":"PPL",
    "gn:name":"La Cazuela",
    "gn:population":0,
    "gn:timezone":"America/Mexico_City",
    "iso:country":"MX",
    "name:spa_x_preferred":[
        "La Cazuela"
    ],
    "wof:name":"La Cazuela",
    "wof:placetype":"locality"
},
  "geometry": {"coordinates":[-96.94945,15.896],"type":"Point"}
}