{
  "type": "Feature",
  "properties": {
    "gn:admin1_code":"6",
    "gn:admin2_code":"40.0",
    "gn:asciiname":"San Pedro Mills",
    "gn:cc2":"MX",
    "gn:country_code":"MX",
    "gn:dem":2104,
    "gn:feature_class":"P",
    "gn:feature_code":"PPL",
    "gn:name":"San Pedro Mills",
    "gn:population":0,
    "gn:timezone":"America/Chihuahua",
    "iso:country":"MX",
    "name:und_x_variant":[
        "San Pedro Mille",
        "San Pedro Mills"
    ],
    "wof:name":"San Pedro Mills",
    "wof:placetype":"locality"
},
  "geometry": {"coordinates":[-108.09999999999999,29.21667],"type":"Point"}
}