{
  "type": "Feature",
  "properties": {
    "gn:admin1_code":"30.0",
    "gn:admin2_code":"155.0",
    "gn:asciiname":"Zapotal Segundo",
    "gn:country_code":"MX",
    "gn:dem":148,
    "gn:feature_class":"P",
    "gn:feature_code":"PPL",
    "gn:name":"Zapotal Segundo",
    "gn:population":189,
    "gn:timezone":"America/Mexico_City",
    "iso:country":"MX",
    "name:spa_x_preferred":[
        "Zapotal Segundo"
    ],
    "wof:name":"Zapotal Segundo",
    "wof:placetype":"locality",
    "wof:population":189
},
  "geometry": {"coordinates":[-98.33056000000001,21.39722],"type":"Point"}
}