{
  "type": "Feature",
  "properties": {
    "gn:admin1_code":"12",
    "gn:admin2_code":"12",
    "gn:asciiname":"Crucero Ojo de Agua (Rancho los Patriarca)",
    "gn:country_code":"MX",
    "gn:dem":1009,
    "gn:feature_class":"P",
    "gn:feature_code":"PPL",
    "gn:name":"Crucero Ojo de Agua (Rancho los Patriarca)",
    "gn:population":13,
    "gn:timezone":"America/Mexico_City",
    "iso:country":"MX",
    "wof:name":"Crucero Ojo de Agua (Rancho los Patriarca)",
    "wof:placetype":"locality",
    "wof:population":13
},
  "geometry": {"coordinates":[-98.99173999999999,16.9815],"type":"Point"}
}