{
  "type": "Feature",
  "properties": {
    "gn:admin1_code":"7",
    "gn:admin2_code":"33",
    "gn:asciiname":"Las Galeras",
    "gn:country_code":"MX",
    "gn:dem":1108,
    "gn:feature_class":"P",
    "gn:feature_code":"PPL",
    "gn:name":"Las Galeras",
    "gn:population":16,
    "gn:timezone":"America/Monterrey",
    "iso:country":"MX",
    "name:spa_x_preferred":[
        "Las Galeras"
    ],
    "wof:name":"Las Galeras",
    "wof:placetype":"locality",
    "wof:population":16
},
  "geometry": {"coordinates":[-103.08313,25.70111],"type":"Point"}
}