{
  "type": "Feature",
  "properties": {
    "gn:admin1_code":"14",
    "gn:admin2_code":"89",
    "gn:asciiname":"La Barranca del Espiritu Santo",
    "gn:country_code":"MX",
    "gn:dem":1743,
    "gn:feature_class":"P",
    "gn:feature_code":"PPL",
    "gn:name":"La Barranca del Esp\u00edritu Santo",
    "gn:population":12,
    "gn:timezone":"America/Mexico_City",
    "iso:country":"MX",
    "name:und_x_variant":[
        "La Barranca del Esp\u00edritu Santo"
    ],
    "wof:name":"La Barranca del Espiritu Santo",
    "wof:placetype":"locality",
    "wof:population":12
},
  "geometry": {"coordinates":[-103.56583000000001,20.13028],"type":"Point"}
}