{
  "type": "Feature",
  "properties": {
    "gn:admin1_code":"6",
    "gn:admin2_code":"29.0",
    "gn:asciiname":"El Pirame",
    "gn:country_code":"MX",
    "gn:dem":2318,
    "gn:feature_class":"P",
    "gn:feature_code":"PPL",
    "gn:name":"El P\u00edrame",
    "gn:population":6,
    "gn:timezone":"America/Chihuahua",
    "iso:country":"MX",
    "name:und_x_variant":[
        "El P\u00edrame"
    ],
    "wof:name":"El Pirame",
    "wof:placetype":"locality",
    "wof:population":6
},
  "geometry": {"coordinates":[-106.79345000000001,25.76496],"type":"Point"}
}