{
  "type": "Feature",
  "properties": {
    "gn:admin1_code":"6",
    "gn:admin2_code":"27",
    "gn:asciiname":"Bajichi",
    "gn:country_code":"MX",
    "gn:dem":2370,
    "gn:feature_class":"P",
    "gn:feature_code":"PPL",
    "gn:name":"Bajichi",
    "gn:population":20,
    "gn:timezone":"America/Chihuahua",
    "iso:country":"MX",
    "wof:name":"Bajichi",
    "wof:placetype":"locality",
    "wof:population":20
},
  "geometry": {"coordinates":[-107.60630999999999,27.66909],"type":"Point"}
}