{
  "type": "Feature",
  "properties": {
    "gn:admin1_code":"30",
    "gn:admin2_code":"212.0",
    "gn:asciiname":"Las Carmelitas",
    "gn:country_code":"MX",
    "gn:dem":117,
    "gn:feature_class":"P",
    "gn:feature_code":"PPL",
    "gn:name":"Las Carmelitas",
    "gn:population":5,
    "gn:timezone":"America/Mexico_City",
    "iso:country":"MX",
    "wof:name":"Las Carmelitas",
    "wof:placetype":"locality",
    "wof:population":5
},
  "geometry": {"coordinates":[-95.69110999999999,17.67027999999999],"type":"Point"}
}