{
  "type": "Feature",
  "properties": {
    "gn:admin1_code":"31",
    "gn:admin2_code":"101.0",
    "gn:asciiname":"Los Colorines",
    "gn:country_code":"MX",
    "gn:dem":10,
    "gn:feature_class":"P",
    "gn:feature_code":"PPL",
    "gn:name":"Los Colorines",
    "gn:population":5,
    "gn:timezone":"America/Merida",
    "iso:country":"MX",
    "wof:name":"Los Colorines",
    "wof:placetype":"locality",
    "wof:population":5
},
  "geometry": {"coordinates":[-89.74528000000002,20.865],"type":"Point"}
}