{
  "type": "Feature",
  "properties": {
    "gn:admin1_code":"7.0",
    "gn:admin2_code":"23.0",
    "gn:asciiname":"Charco de la Mula",
    "gn:country_code":"MX",
    "gn:dem":1396,
    "gn:feature_class":"P",
    "gn:feature_code":"PPL",
    "gn:name":"Charco de la Mula",
    "gn:population":0,
    "gn:timezone":"America/Monterrey",
    "iso:country":"MX",
    "name:und_x_variant":[
        "Mula",
        "Charco de la Mula"
    ],
    "wof:name":"Charco de la Mula",
    "wof:placetype":"locality"
},
  "geometry": {"coordinates":[-102.25717,27.52981],"type":"Point"}
}