{
  "type": "Feature",
  "properties": {
    "gn:admin1_code":"10",
    "gn:admin2_code":"32.0",
    "gn:asciiname":"Santa Rita",
    "gn:country_code":"MX",
    "gn:dem":1994,
    "gn:feature_class":"P",
    "gn:feature_code":"PPL",
    "gn:name":"Santa Rita",
    "gn:population":0,
    "gn:timezone":"America/Monterrey",
    "iso:country":"MX",
    "name:bul_x_preferred":[
        "\u0421\u0430\u043d\u0442\u0430 \u0420\u0438\u0442\u0430"
    ],
    "name:ceb_x_preferred":[
        "Santa Rita"
    ],
    "name:deu_x_preferred":[
        "Santa Rita"
    ],
    "name:fra_x_preferred":[
        "Santa Rita"
    ],
    "name:ilo_x_preferred":[
        "Santa Rita"
    ],
    "name:ita_x_preferred":[
        "Santa Rita"
    ],
    "name:kat_x_preferred":[
        "\u10e1\u10d0\u10dc\u10e2\u10d0-\u10e0\u10d8\u10e2\u10d0"
    ],
    "name:lit_x_preferred":[
        "Santa Rita"
    ],
    "name:mlg_x_preferred":[
        "Santa Rita"
    ],
    "name:nds_x_preferred":[
        "Santa Rita"
    ],
    "name:nld_x_preferred":[
        "Santa Rita"
    ],
    "name:nor_x_preferred":[
        "Santa Rita"
    ],
    "name:pol_x_preferred":[
        "Santa Rita"
    ],
    "name:por_x_preferred":[
        "Santa Rita"
    ],
    "name:ron_x_preferred":[
        "Santa Rita"
    ],
    "name:rus_x_preferred":[
        "\u0421\u0430\u043d\u0442\u0430-\u0420\u0438\u0442\u0430"
    ],
    "name:sco_x_preferred":[
        "Santa Rita"
    ],
    "name:spa_x_preferred":[
        "Santa Rita"
    ],
    "name:srp_x_preferred":[
        "\u0421\u0430\u043d\u0442\u0430 \u0420\u0438\u0442\u0430"
    ],
    "name:swe_x_preferred":[
        "Santa Rita"
    ],
    "name:und_x_variant":[
        "Rancho Santa Rita"
    ],
    "name:vol_x_preferred":[
        "Santa Rita"
    ],
    "name:war_x_preferred":[
        "Santa Rita"
    ],
    "wof:name":"Santa Rita",
    "wof:placetype":"locality"
},
  "geometry": {"coordinates":[-105.16160000000001,25.04325],"type":"Point"}
}