{
  "type": "Feature",
  "properties": {
    "gn:admin1_code":"30.0",
    "gn:admin2_code":"155.0",
    "gn:asciiname":"Palo Verde",
    "gn:country_code":"MX",
    "gn:dem":155,
    "gn:feature_class":"P",
    "gn:feature_code":"PPL",
    "gn:name":"Palo Verde",
    "gn:population":169,
    "gn:timezone":"America/Mexico_City",
    "iso:country":"MX",
    "name:spa_x_preferred":[
        "Palo Verde"
    ],
    "wof:name":"Palo Verde",
    "wof:placetype":"locality",
    "wof:population":169
},
  "geometry": {"coordinates":[-98.17055999999999,21.42],"type":"Point"}
}