{
  "type": "Feature",
  "properties": {
    "gn:admin1_code":"24",
    "gn:admin2_code":"32.0",
    "gn:asciiname":"Estancia de San Juan",
    "gn:country_code":"MX",
    "gn:dem":1967,
    "gn:feature_class":"P",
    "gn:feature_code":"PPL",
    "gn:name":"Estancia de San Juan",
    "gn:population":7,
    "gn:timezone":"America/Mexico_City",
    "iso:country":"MX",
    "wof:name":"Estancia de San Juan",
    "wof:placetype":"locality",
    "wof:population":7
},
  "geometry": {"coordinates":[-100.33360999999999,21.80667],"type":"Point"}
}