{
  "type": "Feature",
  "properties": {
    "gn:admin1_code":"30.0",
    "gn:admin2_code":"153.0",
    "gn:asciiname":"La Mora",
    "gn:country_code":"MX",
    "gn:dem":222,
    "gn:feature_class":"P",
    "gn:feature_code":"PPL",
    "gn:name":"La Mora",
    "gn:population":331,
    "gn:timezone":"America/Mexico_City",
    "iso:country":"MX",
    "name:spa_x_preferred":[
        "La Mora"
    ],
    "wof:name":"La Mora",
    "wof:placetype":"locality",
    "wof:population":331
},
  "geometry": {"coordinates":[-97.74639000000001,21.21583],"type":"Point"}
}