{
  "type": "Feature",
  "properties": {
    "gn:admin1_code":"21.0",
    "gn:admin2_code":"64.0",
    "gn:asciiname":"Pantepec",
    "gn:country_code":"MX",
    "gn:dem":116,
    "gn:feature_class":"P",
    "gn:feature_code":"PPL",
    "gn:name":"Pantepec",
    "gn:population":7,
    "gn:timezone":"America/Mexico_City",
    "iso:country":"MX",
    "name:spa_x_preferred":[
        "Pantepec"
    ],
    "wof:name":"Pantepec",
    "wof:placetype":"locality",
    "wof:population":7
},
  "geometry": {"coordinates":[-97.88639999999999,20.74137],"type":"Point"}
}