{
  "type": "Feature",
  "properties": {
    "gn:admin1_code":"22.0",
    "gn:admin2_code":"14.0",
    "gn:asciiname":"Carrillo",
    "gn:country_code":"MX",
    "gn:dem":1807,
    "gn:feature_class":"P",
    "gn:feature_code":"PPL",
    "gn:name":"Carrillo",
    "gn:population":0,
    "gn:timezone":"America/Mexico_City",
    "iso:country":"MX",
    "wof:name":"Carrillo",
    "wof:placetype":"locality"
},
  "geometry": {"coordinates":[-100.43136,20.61064],"type":"Point"}
}