{
  "type": "Feature",
  "properties": {
    "gn:admin1_code":"20.0",
    "gn:admin2_code":"328.0",
    "gn:asciiname":"Gegorene",
    "gn:country_code":"MX",
    "gn:dem":1479,
    "gn:feature_class":"P",
    "gn:feature_code":"PPL",
    "gn:name":"Gegorene",
    "gn:population":0,
    "gn:timezone":"America/Mexico_City",
    "iso:country":"MX",
    "name:spa_x_preferred":[
        "Gegorene"
    ],
    "wof:name":"Gegorene",
    "wof:placetype":"locality"
},
  "geometry": {"coordinates":[-96.52658,16.68004],"type":"Point"}
}