{
  "type": "Feature",
  "properties": {
    "gn:admin1_code":"5.0",
    "gn:asciiname":"Huisizil",
    "gn:country_code":"MX",
    "gn:dem":1276,
    "gn:feature_class":"P",
    "gn:feature_code":"PPL",
    "gn:name":"Huisizil",
    "gn:population":0,
    "gn:timezone":"America/Mexico_City",
    "iso:country":"MX",
    "name:spa_x_preferred":[
        "Huisizil"
    ],
    "wof:name":"Huisizil",
    "wof:placetype":"locality"
},
  "geometry": {"coordinates":[-93.10898,15.86898],"type":"Point"}
}