{
  "type": "Feature",
  "properties": {
    "gn:admin1_code":"11",
    "gn:admin2_code":"7",
    "gn:asciiname":"La Casa de las Cuatas",
    "gn:country_code":"MX",
    "gn:dem":1747,
    "gn:feature_class":"P",
    "gn:feature_code":"PPL",
    "gn:name":"La Casa de las Cuatas",
    "gn:population":9,
    "gn:timezone":"America/Mexico_City",
    "iso:country":"MX",
    "wof:name":"La Casa de las Cuatas",
    "wof:placetype":"locality",
    "wof:population":9
},
  "geometry": {"coordinates":[-100.87972000000001,20.51111],"type":"Point"}
}