{
  "type": "Feature",
  "properties": {
    "gn:admin1_code":"16",
    "gn:admin2_code":"53.0",
    "gn:asciiname":"Tarehuicho",
    "gn:country_code":"MX",
    "gn:dem":2155,
    "gn:feature_class":"P",
    "gn:feature_code":"PPL",
    "gn:name":"Tarehuicho",
    "gn:population":124,
    "gn:timezone":"America/Mexico_City",
    "iso:country":"MX",
    "wof:name":"Tarehuicho",
    "wof:placetype":"locality",
    "wof:population":124
},
  "geometry": {"coordinates":[-101.46528000000001,19.78417],"type":"Point"}
}