{
  "type": "Feature",
  "properties": {
    "gn:admin1_code":"5",
    "gn:admin2_code":"27.0",
    "gn:asciiname":"Santa Gertrudis",
    "gn:country_code":"MX",
    "gn:dem":439,
    "gn:feature_class":"P",
    "gn:feature_code":"PPL",
    "gn:name":"Santa Gertrudis",
    "gn:population":5,
    "gn:timezone":"America/Mexico_City",
    "iso:country":"MX",
    "name:cat_x_preferred":[
        "Santa Gertrudis"
    ],
    "name:ceb_x_preferred":[
        "Santa Gertrudis"
    ],
    "name:deu_x_preferred":[
        "Santa Gertrudis"
    ],
    "name:sco_x_preferred":[
        "Santa Gertrudis"
    ],
    "name:spa_x_preferred":[
        "Santa Gertrudis"
    ],
    "name:swe_x_preferred":[
        "Santa Gertrudis"
    ],
    "wof:name":"Santa Gertrudis",
    "wof:placetype":"locality",
    "wof:population":5
},
  "geometry": {"coordinates":[-92.99194,16.61889],"type":"Point"}
}