{
  "type": "Feature",
  "properties": {
    "gn:admin1_code":"5",
    "gn:admin2_code":"114.0",
    "gn:asciiname":"Francisco Julian Grajales",
    "gn:country_code":"MX",
    "gn:dem":189,
    "gn:feature_class":"P",
    "gn:feature_code":"PPL",
    "gn:name":"Francisco Juli\u00e1n Grajales",
    "gn:population":368,
    "gn:timezone":"America/Mexico_City",
    "iso:country":"MX",
    "name:und_x_variant":[
        "Francisco Juli\u00e1n Grajales"
    ],
    "wof:name":"Francisco Julian Grajales",
    "wof:placetype":"locality",
    "wof:population":368
},
  "geometry": {"coordinates":[-90.75888999999999,16.08667],"type":"Point"}
}