{
  "type": "Feature",
  "properties": {
    "gn:admin1_code":"28.0",
    "gn:admin2_code":"1.0",
    "gn:asciiname":"El Circuco",
    "gn:country_code":"MX",
    "gn:dem":61,
    "gn:feature_class":"P",
    "gn:feature_code":"PPL",
    "gn:name":"El Circuco",
    "gn:population":0,
    "gn:timezone":"America/Monterrey",
    "iso:country":"MX",
    "name:spa_x_preferred":[
        "El Circuco"
    ],
    "wof:name":"El Circuco",
    "wof:placetype":"locality"
},
  "geometry": {"coordinates":[-98.42462999999999,24.02669],"type":"Point"}
}