{
  "type": "Feature",
  "properties": {
    "gn:admin1_code":"32",
    "gn:admin2_code":"42.0",
    "gn:asciiname":"San Isidro del Divisadero",
    "gn:country_code":"MX",
    "gn:dem":2321,
    "gn:feature_class":"P",
    "gn:feature_code":"PPL",
    "gn:name":"San Isidro del Divisadero",
    "gn:population":9,
    "gn:timezone":"America/Mexico_City",
    "iso:country":"MX",
    "wof:name":"San Isidro del Divisadero",
    "wof:placetype":"locality",
    "wof:population":9
},
  "geometry": {"coordinates":[-103.66528,23.72194],"type":"Point"}
}