{
  "type": "Feature",
  "properties": {
    "gn:admin1_code":"15.0",
    "gn:admin2_code":"77.0",
    "gn:asciiname":"Pena Redonda",
    "gn:country_code":"MX",
    "gn:dem":2096,
    "gn:feature_class":"P",
    "gn:feature_code":"PPL",
    "gn:name":"Pe\u00f1a Redonda",
    "gn:population":0,
    "gn:timezone":"America/Mexico_City",
    "iso:country":"MX",
    "name:spa_x_preferred":[
        "Pe\u00f1a Redonda"
    ],
    "wof:name":"Pena Redonda",
    "wof:placetype":"locality"
},
  "geometry": {"coordinates":[-100.02977,18.95197000000001],"type":"Point"}
}