{
  "type": "Feature",
  "properties": {
    "gn:admin1_code":"5.0",
    "gn:admin2_code":"83.0",
    "gn:asciiname":"Vistahermosa las Aguilas",
    "gn:country_code":"MX",
    "gn:dem":781,
    "gn:feature_class":"P",
    "gn:feature_code":"PPL",
    "gn:name":"Vistahermosa las \u00c1guilas",
    "gn:population":0,
    "gn:timezone":"America/Mexico_City",
    "iso:country":"MX",
    "name:spa_x_preferred":[
        "Vistahermosa las \u00c1guilas"
    ],
    "wof:name":"Vistahermosa las Aguilas",
    "wof:placetype":"locality"
},
  "geometry": {"coordinates":[-92.43035999999999,16.15587],"type":"Point"}
}