{
  "type": "Feature",
  "properties": {
    "gn:admin1_code":"21",
    "gn:admin2_code":"144.0",
    "gn:asciiname":"Dolores",
    "gn:country_code":"MX",
    "gn:dem":2055,
    "gn:feature_class":"P",
    "gn:feature_code":"PPL",
    "gn:name":"Dolores",
    "gn:population":389,
    "gn:timezone":"America/Mexico_City",
    "iso:country":"MX",
    "wof:name":"Dolores",
    "wof:placetype":"locality",
    "wof:population":389
},
  "geometry": {"coordinates":[-97.75611000000001,18.92361],"type":"Point"}
}