{
  "type": "Feature",
  "properties": {
    "gn:admin1_code":"24",
    "gn:admin2_code":"1.0",
    "gn:asciiname":"Canada Grande",
    "gn:country_code":"MX",
    "gn:dem":1771,
    "gn:feature_class":"P",
    "gn:feature_code":"PPL",
    "gn:name":"Ca\u00f1ada Grande",
    "gn:population":395,
    "gn:timezone":"America/Mexico_City",
    "iso:country":"MX",
    "name:und_x_variant":[
        "Ca\u00f1ada Grande"
    ],
    "wof:name":"Canada Grande",
    "wof:placetype":"locality",
    "wof:population":395
},
  "geometry": {"coordinates":[-101.07472,22.44917],"type":"Point"}
}