{
  "type": "Feature",
  "properties": {
    "gn:admin1_code":"13",
    "gn:admin2_code":"8.0",
    "gn:asciiname":"Aviles",
    "gn:country_code":"MX",
    "gn:dem":2850,
    "gn:feature_class":"P",
    "gn:feature_code":"PPL",
    "gn:name":"Avil\u00e9s",
    "gn:population":0,
    "gn:timezone":"America/Mexico_City",
    "iso:country":"MX",
    "name:spa_x_preferred":[
        "Avil\u00e9s"
    ],
    "wof:name":"Aviles",
    "wof:placetype":"locality"
},
  "geometry": {"coordinates":[-98.40817,19.7543],"type":"Point"}
}