{
  "type": "Feature",
  "properties": {
    "gn:admin1_code":"3",
    "gn:admin2_code":"3",
    "gn:asciiname":"San Marcos (La Ayuquita)",
    "gn:country_code":"MX",
    "gn:dem":47,
    "gn:feature_class":"P",
    "gn:feature_code":"PPL",
    "gn:name":"San Marcos (La Ayuquita)",
    "gn:population":9,
    "gn:timezone":"America/Mazatlan",
    "iso:country":"MX",
    "wof:name":"San Marcos (La Ayuquita)",
    "wof:placetype":"locality",
    "wof:population":9
},
  "geometry": {"coordinates":[-109.96066999999999,23.94558],"type":"Point"}
}