{
  "type": "Feature",
  "properties": {
    "gn:admin1_code":"4",
    "gn:admin2_code":"4",
    "gn:asciiname":"Villa de las Flores",
    "gn:country_code":"MX",
    "gn:dem":3,
    "gn:feature_class":"P",
    "gn:feature_code":"PPL",
    "gn:name":"Villa de las Flores",
    "gn:population":13,
    "gn:timezone":"America/Merida",
    "iso:country":"MX",
    "wof:name":"Villa de las Flores",
    "wof:placetype":"locality",
    "wof:population":13
},
  "geometry": {"coordinates":[-90.71194,19.32889],"type":"Point"}
}