{
  "type": "Feature",
  "properties": {
    "gn:admin1_code":"30",
    "gn:admin2_code":"144",
    "gn:asciiname":"Bernardo Reyes Celdo (Vargas)",
    "gn:country_code":"MX",
    "gn:dem":91,
    "gn:feature_class":"P",
    "gn:feature_code":"PPL",
    "gn:name":"Bernardo Reyes Celdo (Vargas)",
    "gn:population":11,
    "gn:timezone":"America/Mexico_City",
    "iso:country":"MX",
    "wof:name":"Bernardo Reyes Celdo (Vargas)",
    "wof:placetype":"locality",
    "wof:population":11
},
  "geometry": {"coordinates":[-94.96889,17.86667000000001],"type":"Point"}
}