{
  "type": "Feature",
  "properties": {
    "gn:admin1_code":"11",
    "gn:admin2_code":"4",
    "gn:asciiname":"El Pintor (Cervantes)",
    "gn:country_code":"MX",
    "gn:dem":2090,
    "gn:feature_class":"P",
    "gn:feature_code":"PPL",
    "gn:name":"El Pintor (Cervantes)",
    "gn:population":14,
    "gn:timezone":"America/Mexico_City",
    "iso:country":"MX",
    "wof:name":"El Pintor (Cervantes)",
    "wof:placetype":"locality",
    "wof:population":14
},
  "geometry": {"coordinates":[-100.52667,20.33417],"type":"Point"}
}