{
  "type": "Feature",
  "properties": {
    "gn:admin1_code":"7.0",
    "gn:admin2_code":"20.0",
    "gn:asciiname":"La Amistad",
    "gn:country_code":"MX",
    "gn:dem":810,
    "gn:feature_class":"P",
    "gn:feature_code":"PPL",
    "gn:name":"La Amistad",
    "gn:population":0,
    "gn:timezone":"America/Monterrey",
    "iso:country":"MX",
    "name:spa_x_preferred":[
        "La Amistad"
    ],
    "wof:name":"La Amistad",
    "wof:placetype":"locality"
},
  "geometry": {"coordinates":[-101.77813999999999,28.61073],"type":"Point"}
}