{
  "type": "Feature",
  "properties": {
    "gn:admin1_code":"7.0",
    "gn:admin2_code":"20.0",
    "gn:asciiname":"La Amistad",
    "gn:country_code":"MX",
    "gn:dem":810,
    "gn:feature_class":"P",
    "gn:feature_code":"PPL",
    "gn:name":"La Amistad",
    "gn:population":0,
    "gn:timezone":"America/Monterrey",
    "iso:country":"MX",
    "name:afr_x_preferred":[
        "La Amistad"
    ],
    "name:ara_x_preferred":[
        "\u0623\u0645\u064a\u0633\u062a\u0627\u062f"
    ],
    "name:bul_x_preferred":[
        "\u0410\u043c\u0438\u0441\u0442\u0430\u0434"
    ],
    "name:cym_x_preferred":[
        "La Amistad"
    ],
    "name:deu_x_preferred":[
        "Amistad"
    ],
    "name:fas_x_preferred":[
        "\u0644\u0627 \u0622\u0645\u06cc\u0633\u062a\u0627\u062f"
    ],
    "name:fin_x_preferred":[
        "Amistad"
    ],
    "name:fra_x_preferred":[
        "La Amistad"
    ],
    "name:glg_x_preferred":[
        "La Amistad"
    ],
    "name:heb_x_preferred":[
        "\u05dc\u05d4 \u05d0\u05de\u05d9\u05e1\u05d8\u05d0\u05d3"
    ],
    "name:hun_x_preferred":[
        "La Amistad"
    ],
    "name:ita_x_preferred":[
        "Amistad"
    ],
    "name:kor_x_preferred":[
        "\ub77c \uc544\ubbf8\uc2a4\ud0c0\ub4dc"
    ],
    "name:msa_x_preferred":[
        "La Amistad"
    ],
    "name:nld_x_preferred":[
        "La Amistad"
    ],
    "name:nor_x_preferred":[
        "\u00abLa Amistad\u00bb"
    ],
    "name:por_x_preferred":[
        "La Amistad"
    ],
    "name:rus_x_preferred":[
        "\u0410\u043c\u0438\u0441\u0442\u0430\u0434"
    ],
    "name:slk_x_preferred":[
        "Amistad"
    ],
    "name:spa_x_preferred":[
        "La Amistad"
    ],
    "name:srp_x_preferred":[
        "\u0410\u043c\u0438\u0441\u0442\u0430\u0434"
    ],
    "name:swe_x_preferred":[
        "La Amistad"
    ],
    "name:tur_x_preferred":[
        "La Amistad"
    ],
    "wof:name":"La Amistad",
    "wof:placetype":"locality"
},
  "geometry": {"coordinates":[-101.77813999999999,28.61073],"type":"Point"}
}