{
  "type": "Feature",
  "properties": {
    "gn:admin1_code":"30",
    "gn:admin2_code":"161.0",
    "gn:asciiname":"Manantiales",
    "gn:country_code":"MX",
    "gn:dem":87,
    "gn:feature_class":"P",
    "gn:feature_code":"PPL",
    "gn:name":"Manantiales",
    "gn:population":163,
    "gn:timezone":"America/Mexico_City",
    "iso:country":"MX",
    "name:ceb_x_preferred":[
        "Manantiales"
    ],
    "name:deu_x_preferred":[
        "Manantiales"
    ],
    "name:spa_x_preferred":[
        "Manantiales"
    ],
    "name:swe_x_preferred":[
        "Manantiales"
    ],
    "wof:name":"Manantiales",
    "wof:placetype":"locality",
    "wof:population":163
},
  "geometry": {"coordinates":[-98.34639,21.40444],"type":"Point"}
}