{
  "type": "Feature",
  "properties": {
    "gn:admin1_code":"6",
    "gn:admin2_code":"40",
    "gn:asciiname":"Los Desmontes",
    "gn:country_code":"MX",
    "gn:dem":2133,
    "gn:feature_class":"P",
    "gn:feature_code":"PPL",
    "gn:name":"Los Desmontes",
    "gn:population":21,
    "gn:timezone":"America/Chihuahua",
    "iso:country":"MX",
    "wof:name":"Los Desmontes",
    "wof:placetype":"locality",
    "wof:population":21
},
  "geometry": {"coordinates":[-108.43334,29.25134000000001],"type":"Point"}
}