{
  "type": "Feature",
  "properties": {
    "gn:admin1_code":"29",
    "gn:admin2_code":"15.0",
    "gn:asciiname":"San Lucas (El Campirano)",
    "gn:country_code":"MX",
    "gn:dem":2469,
    "gn:feature_class":"P",
    "gn:feature_code":"PPL",
    "gn:name":"San Lucas (El Campirano)",
    "gn:population":5,
    "gn:timezone":"America/Mexico_City",
    "iso:country":"MX",
    "wof:name":"San Lucas (El Campirano)",
    "wof:placetype":"locality",
    "wof:population":5
},
  "geometry": {"coordinates":[-98.42704999999999,19.3783],"type":"Point"}
}