{
  "type": "Feature",
  "properties": {
    "gn:admin1_code":"11.0",
    "gn:admin2_code":"30.0",
    "gn:asciiname":"El Gato",
    "gn:country_code":"MX",
    "gn:dem":2016,
    "gn:feature_class":"P",
    "gn:feature_code":"PPL",
    "gn:name":"El Gato",
    "gn:population":12,
    "gn:timezone":"America/Mexico_City",
    "iso:country":"MX",
    "wof:name":"El Gato",
    "wof:placetype":"locality",
    "wof:population":12
},
  "geometry": {"coordinates":[-101.12833000000001,21.33444],"type":"Point"}
}