{
  "type": "Feature",
  "properties": {
    "gn:admin1_code":"5",
    "gn:admin2_code":"99.0",
    "gn:asciiname":"El Rincon",
    "gn:country_code":"MX",
    "gn:dem":1487,
    "gn:feature_class":"P",
    "gn:feature_code":"PPL",
    "gn:name":"El Rinc\u00f3n",
    "gn:population":12,
    "gn:timezone":"America/Mexico_City",
    "iso:country":"MX",
    "wof:name":"El Rincon",
    "wof:placetype":"locality",
    "wof:population":12
},
  "geometry": {"coordinates":[-91.78471999999999,16.1225],"type":"Point"}
}