{
  "type": "Feature",
  "properties": {
    "gn:admin1_code":"14.0",
    "gn:admin2_code":"35.0",
    "gn:asciiname":"Los Magueyes de Arriba",
    "gn:country_code":"MX",
    "gn:dem":1871,
    "gn:feature_class":"P",
    "gn:feature_code":"PPL",
    "gn:name":"Los Magueyes de Arriba",
    "gn:population":0,
    "gn:timezone":"America/Mexico_City",
    "iso:country":"MX",
    "name:spa_x_preferred":[
        "Los Magueyes de Arriba"
    ],
    "wof:name":"Los Magueyes de Arriba",
    "wof:placetype":"locality"
},
  "geometry": {"coordinates":[-102.2042,21.48722],"type":"Point"}
}