{
  "type": "Feature",
  "properties": {
    "gn:admin1_code":"30",
    "gn:admin2_code":"43.0",
    "gn:asciiname":"La Divina Providencia",
    "gn:country_code":"MX",
    "gn:dem":976,
    "gn:feature_class":"P",
    "gn:feature_code":"PPL",
    "gn:name":"La Divina Providencia",
    "gn:population":158,
    "gn:timezone":"America/Mexico_City",
    "iso:country":"MX",
    "wof:name":"La Divina Providencia",
    "wof:placetype":"locality",
    "wof:population":158
},
  "geometry": {"coordinates":[-96.85778000000001,19.16833],"type":"Point"}
}