{
  "type": "Feature",
  "properties": {
    "gn:admin1_code":"5",
    "gn:admin2_code":"20.0",
    "gn:asciiname":"Los Altos de Jesus",
    "gn:country_code":"MX",
    "gn:dem":545,
    "gn:feature_class":"P",
    "gn:feature_code":"PPL",
    "gn:name":"Los Altos de Jes\u00fas",
    "gn:population":5,
    "gn:timezone":"America/Mexico_City",
    "iso:country":"MX",
    "name:und_x_variant":[
        "Los Altos de Jes\u00fas"
    ],
    "wof:name":"Los Altos de Jesus",
    "wof:placetype":"locality",
    "wof:population":5
},
  "geometry": {"coordinates":[-92.83889000000001,16.06139],"type":"Point"}
}