{
  "type": "Feature",
  "properties": {
    "gn:admin1_code":"11",
    "gn:admin2_code":"33.0",
    "gn:asciiname":"Jaralillo",
    "gn:country_code":"MX",
    "gn:dem":2248,
    "gn:feature_class":"P",
    "gn:feature_code":"PPL",
    "gn:name":"Jaralillo",
    "gn:population":57,
    "gn:timezone":"America/Mexico_City",
    "iso:country":"MX",
    "wof:name":"Jaralillo",
    "wof:placetype":"locality",
    "wof:population":57
},
  "geometry": {"coordinates":[-100.62166999999999,21.49028],"type":"Point"}
}