{
  "type": "Feature",
  "properties": {
    "gn:admin1_code":"31",
    "gn:admin2_code":"104",
    "gn:asciiname":"Kancabchen",
    "gn:country_code":"MX",
    "gn:dem":31,
    "gn:feature_class":"P",
    "gn:feature_code":"PPL",
    "gn:name":"Kancabch\u00e9n",
    "gn:population":16,
    "gn:timezone":"America/Merida",
    "iso:country":"MX",
    "name:und_x_variant":[
        "Kancabch\u00e9n"
    ],
    "wof:name":"Kancabchen",
    "wof:placetype":"locality",
    "wof:population":16
},
  "geometry": {"coordinates":[-88.87361,20.32639],"type":"Point"}
}