{
  "type": "Feature",
  "properties": {
    "gn:admin1_code":"10",
    "gn:admin2_code":"32.0",
    "gn:asciiname":"Los Pirames",
    "gn:country_code":"MX",
    "gn:dem":2114,
    "gn:feature_class":"P",
    "gn:feature_code":"PPL",
    "gn:name":"Los Pirames",
    "gn:population":0,
    "gn:timezone":"America/Monterrey",
    "iso:country":"MX",
    "name:spa_x_preferred":[
        "Los Pirames"
    ],
    "wof:name":"Los Pirames",
    "wof:placetype":"locality"
},
  "geometry": {"coordinates":[-105.36985,24.68049],"type":"Point"}
}