{
  "type": "Feature",
  "properties": {
    "iso:country":"MX",
    "name:cat_x_preferred":[
        "Tur\u00f3 del Tepeyac"
    ],
    "name:ces_x_preferred":[
        "Tepeyac"
    ],
    "name:deu_x_preferred":[
        "Tepeyac"
    ],
    "name:epo_x_preferred":[
        "Tepejako"
    ],
    "name:eus_x_preferred":[
        "Tepeyac"
    ],
    "name:fra_x_preferred":[
        "Tepeyac"
    ],
    "name:hun_x_preferred":[
        "Tepeyac"
    ],
    "name:ita_x_preferred":[
        "Tepeyac"
    ],
    "name:nor_x_preferred":[
        "Tepeyac"
    ],
    "name:por_x_preferred":[
        "Tepeyac"
    ],
    "name:spa_x_preferred":[
        "Tepeyac",
        "Cerro del Tepeyac"
    ],
    "name:spa_x_variant":[
        "Tepeaca"
    ],
    "name:swe_x_preferred":[
        "Tepeyac"
    ],
    "name:unk_x_variant":[
        "Tepeyac"
    ],
    "qs:gn_adm0_cc":"MX",
    "qs:gn_fcode":"PPL",
    "qs:gn_local":3985606,
    "qs:gn_nam_loc":"San Luis Potosi, San Luis Potosi, San Luis Potos\u00ed, MX",
    "qs:gn_namadm1":"11",
    "qs:gn_name":"Tepeaca",
    "qs:local_max":1936,
    "qs:local_sum":4960,
    "qs:localhoods":18,
    "qs:name":"Tepeyac",
    "qs:name_adm0":"M\u00e9xico",
    "qs:name_adm1":"San Luis Potosi",
    "qs:name_adm2":"San Luis Potosi",
    "qs:name_local":"San Luis Potos\u00ed",
    "qs:photo_max":117,
    "qs:photo_sum":167,
    "qs:placetype":"Suburb",
    "qs:quad_count":6,
    "qs:woe_adm0":23424900,
    "qs:woe_adm1":2346287,
    "qs:woe_adm2":12601498,
    "qs:woe_lau":0,
    "qs:woe_local":144265,
    "qs:woe_ver":"7.10.0",
    "wd:wordcount":261,
    "wof:lang":[
        "spa"
    ],
    "wof:name":"Tepeyac",
    "wof:placetype":"neighbourhood"
},
  "geometry": {"coordinates":[-100.955387,22.109267],"type":"Point"}
}