{
  "type": "Feature",
  "properties": {
    "gn:admin1_code":"20",
    "gn:admin2_code":"421",
    "gn:asciiname":"Nizabiguidi",
    "gn:country_code":"MX",
    "gn:dem":84,
    "gn:feature_class":"P",
    "gn:feature_code":"PPL",
    "gn:name":"Nizabiguidi",
    "gn:population":30,
    "gn:timezone":"America/Mexico_City",
    "iso:country":"MX",
    "wof:name":"Nizabiguidi",
    "wof:placetype":"locality",
    "wof:population":30
},
  "geometry": {"coordinates":[-95.25667,16.38889],"type":"Point"}
}