{
  "type": "Feature",
  "properties": {
    "gn:admin1_code":"19.0",
    "gn:asciiname":"Cuatro Vientos",
    "gn:country_code":"MX",
    "gn:dem":496,
    "gn:feature_class":"P",
    "gn:feature_code":"PPL",
    "gn:name":"Cuatro Vientos",
    "gn:population":0,
    "gn:timezone":"America/Monterrey",
    "iso:country":"MX",
    "name:cat_x_preferred":[
        "Cuatro Vientos"
    ],
    "name:eus_x_preferred":[
        "Cuatro Vientos"
    ],
    "name:por_x_preferred":[
        "Cuatro Vientos"
    ],
    "name:spa_x_preferred":[
        "Cuatro Vientos"
    ],
    "wof:name":"Cuatro Vientos",
    "wof:placetype":"locality"
},
  "geometry": {"coordinates":[-100.38596,25.93859],"type":"Point"}
}