{
  "type": "Feature",
  "properties": {
    "gn:admin1_code":"12",
    "gn:admin2_code":"30.0",
    "gn:asciiname":"Llano de la Barra",
    "gn:country_code":"MX",
    "gn:dem":4,
    "gn:feature_class":"P",
    "gn:feature_code":"PPL",
    "gn:name":"Llano de la Barra",
    "gn:population":149,
    "gn:timezone":"America/Mexico_City",
    "iso:country":"MX",
    "wof:name":"Llano de la Barra",
    "wof:placetype":"locality",
    "wof:population":149
},
  "geometry": {"coordinates":[-99.10887,16.60158],"type":"Point"}
}