{
  "type": "Feature",
  "properties": {
    "gn:admin1_code":"21",
    "gn:admin2_code":"181",
    "gn:asciiname":"Huitango",
    "gn:country_code":"MX",
    "gn:dem":2193,
    "gn:feature_class":"P",
    "gn:feature_code":"PPL",
    "gn:name":"Huitango",
    "gn:population":10,
    "gn:timezone":"America/Mexico_City",
    "iso:country":"MX",
    "wof:name":"Huitango",
    "wof:placetype":"locality",
    "wof:population":10
},
  "geometry": {"coordinates":[-98.32635999999999,19.16957],"type":"Point"}
}