{
  "type": "Feature",
  "properties": {
    "gn:admin1_code":"30",
    "gn:admin2_code":"175.0",
    "gn:asciiname":"El Cerro",
    "gn:cc2":"MX",
    "gn:country_code":"MX",
    "gn:dem":206,
    "gn:feature_class":"P",
    "gn:feature_code":"PPL",
    "gn:name":"El Cerro",
    "gn:population":17,
    "gn:timezone":"America/Mexico_City",
    "iso:country":"MX",
    "name:und_x_variant":[
        "Velador",
        "Veladero"
    ],
    "wof:name":"El Cerro",
    "wof:placetype":"locality",
    "wof:population":17
},
  "geometry": {"coordinates":[-97.63472,20.57556],"type":"Point"}
}