{
  "type": "Feature",
  "properties": {
    "gn:admin1_code":"6",
    "gn:admin2_code":"29.0",
    "gn:asciiname":"Las Fresas",
    "gn:country_code":"MX",
    "gn:dem":2335,
    "gn:feature_class":"P",
    "gn:feature_code":"PPL",
    "gn:name":"Las Fresas",
    "gn:population":76,
    "gn:timezone":"America/Chihuahua",
    "iso:country":"MX",
    "wof:name":"Las Fresas",
    "wof:placetype":"locality",
    "wof:population":76
},
  "geometry": {"coordinates":[-107.11125,26.30106],"type":"Point"}
}