{
  "type": "Feature",
  "properties": {
    "gn:admin1_code":"11.0",
    "gn:admin2_code":"17.0",
    "gn:asciiname":"Ampliacion Malvas",
    "gn:country_code":"MX",
    "gn:dem":1730,
    "gn:feature_class":"P",
    "gn:feature_code":"PPL",
    "gn:name":"Ampliaci\u00f3n Malvas",
    "gn:population":0,
    "gn:timezone":"America/Mexico_City",
    "iso:country":"MX",
    "name:spa_x_preferred":[
        "Ampliaci\u00f3n Malvas"
    ],
    "name:spa_x_variant":[
        "San Vicente de Malvas"
    ],
    "wof:name":"Ampliacion Malvas",
    "wof:placetype":"locality"
},
  "geometry": {"coordinates":[-101.29143999999999,20.68074],"type":"Point"}
}