{
  "type": "Feature",
  "properties": {
    "gn:admin1_code":"12",
    "gn:admin2_code":"28.0",
    "gn:asciiname":"Zoyacomulco",
    "gn:country_code":"MX",
    "gn:dem":1739,
    "gn:feature_class":"P",
    "gn:feature_code":"PPL",
    "gn:name":"Zoyacomulco",
    "gn:population":97,
    "gn:timezone":"America/Mexico_City",
    "iso:country":"MX",
    "wof:name":"Zoyacomulco",
    "wof:placetype":"locality",
    "wof:population":97
},
  "geometry": {"coordinates":[-99.06386999999999,17.52616],"type":"Point"}
}