{
  "type": "Feature",
  "properties": {
    "gn:admin1_code":"27",
    "gn:admin2_code":"2.0",
    "gn:asciiname":"Las Coloradas Primera Seccion",
    "gn:country_code":"MX",
    "gn:dem":10,
    "gn:feature_class":"P",
    "gn:feature_code":"PPL",
    "gn:name":"Las Coloradas Primera Secci\u00f3n",
    "gn:population":0,
    "gn:timezone":"America/Mexico_City",
    "iso:country":"MX",
    "name:spa_x_preferred":[
        "Las Coloradas"
    ],
    "name:spa_x_variant":[
        "Las Coloradas Primera Secci\u00f3n"
    ],
    "wof:name":"Las Coloradas Primera Seccion",
    "wof:placetype":"locality"
},
  "geometry": {"coordinates":[-93.53203999999999,18.2811],"type":"Point"}
}