{
  "type": "Feature",
  "properties": {
    "gn:admin1_code":"12.0",
    "gn:admin2_code":"48.0",
    "gn:asciiname":"La Vainilla",
    "gn:country_code":"MX",
    "gn:dem":298,
    "gn:feature_class":"P",
    "gn:feature_code":"PPL",
    "gn:name":"La Vainilla",
    "gn:population":0,
    "gn:timezone":"America/Mexico_City",
    "iso:country":"MX",
    "name:spa_x_preferred":[
        "La Vainilla"
    ],
    "wof:name":"La Vainilla",
    "wof:placetype":"locality"
},
  "geometry": {"coordinates":[-101.21769999999999,17.69285],"type":"Point"}
}