{
  "type": "Feature",
  "properties": {
    "gn:admin1_code":"6",
    "gn:admin2_code":"9.0",
    "gn:asciiname":"Talayotes",
    "gn:country_code":"MX",
    "gn:dem":2446,
    "gn:feature_class":"P",
    "gn:feature_code":"PPL",
    "gn:name":"Talayotes",
    "gn:population":25,
    "gn:timezone":"America/Chihuahua",
    "iso:country":"MX",
    "wof:name":"Talayotes",
    "wof:placetype":"locality",
    "wof:population":25
},
  "geometry": {"coordinates":[-107.53382000000001,27.99713],"type":"Point"}
}