{
  "type": "Feature",
  "properties": {
    "gn:admin1_code":"14.0",
    "gn:asciiname":"Tepeguajes",
    "gn:country_code":"MX",
    "gn:dem":1536,
    "gn:feature_class":"P",
    "gn:feature_code":"PPL",
    "gn:name":"Tepeguajes",
    "gn:population":0,
    "gn:timezone":"America/Mexico_City",
    "iso:country":"MX",
    "name:spa_x_preferred":[
        "Tepeguajes"
    ],
    "wof:name":"Tepeguajes",
    "wof:placetype":"locality"
},
  "geometry": {"coordinates":[-103.70747,22.48914],"type":"Point"}
}