{
  "type": "Feature",
  "properties": {
    "gn:admin1_code":"13",
    "gn:admin2_code":"11.0",
    "gn:asciiname":"Tlachapa",
    "gn:country_code":"MX",
    "gn:dem":214,
    "gn:feature_class":"P",
    "gn:feature_code":"PPL",
    "gn:name":"Tlachapa",
    "gn:population":0,
    "gn:timezone":"America/Mexico_City",
    "iso:country":"MX",
    "name:spa_x_preferred":[
        "Tlachapa"
    ],
    "wof:name":"Tlachapa",
    "wof:placetype":"locality"
},
  "geometry": {"coordinates":[-98.38267999999999,20.99182],"type":"Point"}
}