{
  "type": "Feature",
  "properties": {
    "gn:admin1_code":"3",
    "gn:admin2_code":"1.0",
    "gn:asciiname":"Rancho Escondido",
    "gn:country_code":"MX",
    "gn:dem":323,
    "gn:feature_class":"P",
    "gn:feature_code":"PPL",
    "gn:name":"Rancho Escondido",
    "gn:population":4,
    "gn:timezone":"America/Mazatlan",
    "iso:country":"MX",
    "wof:name":"Rancho Escondido",
    "wof:placetype":"locality",
    "wof:population":4
},
  "geometry": {"coordinates":[-111.17373000000001,25.36446],"type":"Point"}
}