{
  "type": "Feature",
  "properties": {
    "gn:admin1_code":"17",
    "gn:admin2_code":"29.0",
    "gn:asciiname":"Ampliacion Santa Rosa",
    "gn:country_code":"MX",
    "gn:dem":1449,
    "gn:feature_class":"P",
    "gn:feature_code":"PPL",
    "gn:name":"Ampliaci\u00f3n Santa Rosa",
    "gn:population":331,
    "gn:timezone":"America/Mexico_City",
    "iso:country":"MX",
    "name:und_x_variant":[
        "Ampliaci\u00f3n Santa Rosa"
    ],
    "wof:name":"Ampliacion Santa Rosa",
    "wof:placetype":"locality",
    "wof:population":331
},
  "geometry": {"coordinates":[-98.9696,18.92282],"type":"Point"}
}