{
  "type": "Feature",
  "properties": {
    "gn:admin1_code":"6.0",
    "gn:admin2_code":"7.0",
    "gn:asciiname":"Cerro Prieto",
    "gn:country_code":"MX",
    "gn:dem":2320,
    "gn:feature_class":"P",
    "gn:feature_code":"PPL",
    "gn:name":"Cerro Prieto",
    "gn:population":0,
    "gn:timezone":"America/Chihuahua",
    "iso:country":"MX",
    "wof:name":"Cerro Prieto",
    "wof:placetype":"locality"
},
  "geometry": {"coordinates":[-106.58333,27.01667],"type":"Point"}
}