{
  "type": "Feature",
  "properties": {
    "gn:admin1_code":"5.0",
    "gn:admin2_code":"87.0",
    "gn:asciiname":"Adriana",
    "gn:country_code":"MX",
    "gn:dem":19,
    "gn:feature_class":"P",
    "gn:feature_code":"PPL",
    "gn:name":"Adriana",
    "gn:population":0,
    "gn:timezone":"America/Mexico_City",
    "iso:country":"MX",
    "name:bre_x_preferred":[
        "Adriana"
    ],
    "name:bul_x_preferred":[
        "\u0410\u0434\u0440\u0438\u0430\u043d\u0430"
    ],
    "name:cat_x_preferred":[
        "Adriana"
    ],
    "name:ces_x_preferred":[
        "Adriana"
    ],
    "name:deu_x_preferred":[
        "Adriana"
    ],
    "name:hun_x_preferred":[
        "Adri\u00e1na"
    ],
    "name:ita_x_preferred":[
        "Adriana"
    ],
    "name:jpn_x_preferred":[
        "\u30a2\u30c9\u30ea\u30a2\u30fc\u30ca"
    ],
    "name:nor_x_preferred":[
        "Adriana"
    ],
    "name:pol_x_preferred":[
        "Adrianna"
    ],
    "name:slk_x_preferred":[
        "Adri\u00e1na"
    ],
    "name:slv_x_preferred":[
        "Adriana"
    ],
    "name:spa_x_preferred":[
        "Adriana"
    ],
    "name:swe_x_preferred":[
        "Adriana"
    ],
    "wof:name":"Adriana",
    "wof:placetype":"locality"
},
  "geometry": {"coordinates":[-92.24495,14.67236],"type":"Point"}
}