{
  "type": "Feature",
  "properties": {
    "gn:admin1_code":"14",
    "gn:asciiname":"La Ordena",
    "gn:country_code":"MX",
    "gn:dem":2400,
    "gn:feature_class":"P",
    "gn:feature_code":"PPL",
    "gn:name":"La Orde\u00f1a",
    "gn:population":0,
    "gn:timezone":"America/Mexico_City",
    "iso:country":"MX",
    "name:spa_x_preferred":[
        "La Orde\u00f1a"
    ],
    "wof:name":"La Ordena",
    "wof:placetype":"locality"
},
  "geometry": {"coordinates":[-103.617,22.29194],"type":"Point"}
}