{
  "type": "Feature",
  "properties": {
    "gn:admin1_code":"16",
    "gn:admin2_code":"22",
    "gn:asciiname":"El Pedregal",
    "gn:country_code":"MX",
    "gn:dem":1926,
    "gn:feature_class":"P",
    "gn:feature_code":"PPL",
    "gn:name":"El Pedregal",
    "gn:population":51,
    "gn:timezone":"America/Mexico_City",
    "iso:country":"MX",
    "wof:name":"El Pedregal",
    "wof:placetype":"locality",
    "wof:population":51
},
  "geometry": {"coordinates":[-101.03471999999999,19.73778],"type":"Point"}
}