{
  "type": "Feature",
  "properties": {
    "gn:admin1_code":"20",
    "gn:admin2_code":"406.0",
    "gn:asciiname":"Rio Sapo",
    "gn:country_code":"MX",
    "gn:dem":119,
    "gn:feature_class":"P",
    "gn:feature_code":"PPL",
    "gn:name":"R\u00edo Sapo",
    "gn:population":681,
    "gn:timezone":"America/Mexico_City",
    "iso:country":"MX",
    "name:spa_x_preferred":[
        "R\u00edo Sapo"
    ],
    "wof:name":"Rio Sapo",
    "wof:placetype":"locality",
    "wof:population":681
},
  "geometry": {"coordinates":[-96.71905,18.27197],"type":"Point"}
}