{
  "type": "Feature",
  "properties": {
    "gn:admin1_code":"10",
    "gn:admin2_code":"23.0",
    "gn:asciiname":"El Taller",
    "gn:country_code":"MX",
    "gn:dem":2302,
    "gn:feature_class":"P",
    "gn:feature_code":"PPL",
    "gn:name":"El Taller",
    "gn:population":8,
    "gn:timezone":"America/Monterrey",
    "iso:country":"MX",
    "wof:name":"El Taller",
    "wof:placetype":"locality",
    "wof:population":8
},
  "geometry": {"coordinates":[-105.75020000000001,23.64607],"type":"Point"}
}