{
  "type": "Feature",
  "properties": {
    "gn:admin1_code":"21",
    "gn:admin2_code":"207.0",
    "gn:asciiname":"El Progreso",
    "gn:country_code":"MX",
    "gn:dem":2060,
    "gn:feature_class":"P",
    "gn:feature_code":"PPL",
    "gn:name":"El Progreso",
    "gn:population":792,
    "gn:timezone":"America/Mexico_City",
    "iso:country":"MX",
    "wof:name":"El Progreso",
    "wof:placetype":"locality",
    "wof:population":792
},
  "geometry": {"coordinates":[-97.54333,19.89694],"type":"Point"}
}