{
  "type": "Feature",
  "properties": {
    "gn:admin1_code":"30",
    "gn:admin2_code":"183",
    "gn:asciiname":"Finca Flor de Maria",
    "gn:country_code":"MX",
    "gn:dem":103,
    "gn:feature_class":"P",
    "gn:feature_code":"PPL",
    "gn:name":"Finca Flor de Mar\u00eda",
    "gn:population":12,
    "gn:timezone":"America/Mexico_City",
    "iso:country":"MX",
    "name:und_x_variant":[
        "Finca Flor de Mar\u00eda"
    ],
    "wof:name":"Finca Flor de Maria",
    "wof:placetype":"locality",
    "wof:population":12
},
  "geometry": {"coordinates":[-97.12582999999999,20.10556],"type":"Point"}
}