{
  "type": "Feature",
  "properties": {
    "gn:admin1_code":"5",
    "gn:admin2_code":"74.0",
    "gn:asciiname":"Zapotal 2da. Seccion",
    "gn:country_code":"MX",
    "gn:dem":51,
    "gn:feature_class":"P",
    "gn:feature_code":"PPL",
    "gn:name":"Zapotal 2da. Secci\u00f3n",
    "gn:population":243,
    "gn:timezone":"America/Mexico_City",
    "iso:country":"MX",
    "name:und_x_variant":[
        "Zapotal 2da. Secci\u00f3n"
    ],
    "wof:name":"Zapotal 2da. Seccion",
    "wof:placetype":"locality",
    "wof:population":243
},
  "geometry": {"coordinates":[-93.24694,17.82832999999999],"type":"Point"}
}