{
  "type": "Feature",
  "properties": {
    "gn:admin1_code":"30",
    "gn:admin2_code":"43.0",
    "gn:asciiname":"Paso Carretas",
    "gn:country_code":"MX",
    "gn:dem":496,
    "gn:feature_class":"P",
    "gn:feature_code":"PPL",
    "gn:name":"Paso Carretas",
    "gn:population":0,
    "gn:timezone":"America/Mexico_City",
    "iso:country":"MX",
    "name:spa_x_preferred":[
        "Paso Carretas"
    ],
    "wof:name":"Paso Carretas",
    "wof:placetype":"locality"
},
  "geometry": {"coordinates":[-96.67663,19.11729],"type":"Point"}
}