{
  "type": "Feature",
  "properties": {
    "gn:admin1_code":"5",
    "gn:admin2_code":"92.0",
    "gn:asciiname":"La Nueva Jerusalen",
    "gn:country_code":"MX",
    "gn:dem":495,
    "gn:feature_class":"P",
    "gn:feature_code":"PPL",
    "gn:name":"La Nueva Jerusal\u00e9n",
    "gn:population":108,
    "gn:timezone":"America/Mexico_City",
    "iso:country":"MX",
    "name:und_x_variant":[
        "La Nueva Jerusal\u00e9n"
    ],
    "wof:name":"La Nueva Jerusalen",
    "wof:placetype":"locality",
    "wof:population":108
},
  "geometry": {"coordinates":[-93.31721,17.18097],"type":"Point"}
}