{
  "type": "Feature",
  "properties": {
    "gn:admin1_code":"20",
    "gn:admin2_code":"499",
    "gn:asciiname":"Nduayoo",
    "gn:country_code":"MX",
    "gn:dem":2116,
    "gn:feature_class":"P",
    "gn:feature_code":"PPL",
    "gn:name":"Nduayoo",
    "gn:population":12,
    "gn:timezone":"America/Mexico_City",
    "iso:country":"MX",
    "wof:name":"Nduayoo",
    "wof:placetype":"locality",
    "wof:population":12
},
  "geometry": {"coordinates":[-97.56694,17.43972],"type":"Point"}
}