{
  "type": "Feature",
  "properties": {
    "gn:admin1_code":"11",
    "gn:admin2_code":"37.0",
    "gn:asciiname":"Playa Azul",
    "gn:country_code":"MX",
    "gn:dem":1795,
    "gn:feature_class":"P",
    "gn:feature_code":"PPL",
    "gn:name":"Playa Azul",
    "gn:population":444,
    "gn:timezone":"America/Mexico_City",
    "iso:country":"MX",
    "wof:name":"Playa Azul",
    "wof:placetype":"locality",
    "wof:population":444
},
  "geometry": {"coordinates":[-101.44361000000001,20.9825],"type":"Point"}
}