{
  "type": "Feature",
  "properties": {
    "gn:admin1_code":"20",
    "gn:admin2_code":"498.0",
    "gn:asciiname":"El Coyolito",
    "gn:country_code":"MX",
    "gn:dem":86,
    "gn:feature_class":"P",
    "gn:feature_code":"PPL",
    "gn:name":"El Coyolito",
    "gn:population":0,
    "gn:timezone":"America/Mexico_City",
    "iso:country":"MX",
    "name:spa_x_preferred":[
        "El Coyolito"
    ],
    "wof:name":"El Coyolito",
    "wof:placetype":"locality"
},
  "geometry": {"coordinates":[-95.51599,17.45129],"type":"Point"}
}