{
  "type": "Feature",
  "properties": {
    "gn:admin1_code":"18",
    "gn:admin2_code":"19.0",
    "gn:asciiname":"Las Golondrinas",
    "gn:country_code":"MX",
    "gn:dem":1594,
    "gn:feature_class":"P",
    "gn:feature_code":"PPL",
    "gn:name":"Las Golondrinas",
    "gn:population":6,
    "gn:timezone":"America/Mazatlan",
    "iso:country":"MX",
    "wof:name":"Las Golondrinas",
    "wof:placetype":"locality",
    "wof:population":6
},
  "geometry": {"coordinates":[-104.14972,21.775],"type":"Point"}
}