{
  "type": "Feature",
  "properties": {
    "gn:admin1_code":"20",
    "gn:admin2_code":"6.0",
    "gn:asciiname":"La Union Libertad Ixtaltepec",
    "gn:country_code":"MX",
    "gn:dem":2374,
    "gn:feature_class":"P",
    "gn:feature_code":"PPL",
    "gn:name":"La Uni\u00f3n Libertad Ixtaltepec",
    "gn:population":79,
    "gn:timezone":"America/Mexico_City",
    "iso:country":"MX",
    "name:und_x_variant":[
        "La Uni\u00f3n Libertad Ixtaltepec"
    ],
    "wof:name":"La Union Libertad Ixtaltepec",
    "wof:placetype":"locality",
    "wof:population":79
},
  "geometry": {"coordinates":[-97.09667,17.56861],"type":"Point"}
}