{
  "type": "Feature",
  "properties": {
    "gn:admin1_code":"6",
    "gn:admin2_code":"35",
    "gn:asciiname":"San Pedro de la Pradera",
    "gn:country_code":"MX",
    "gn:dem":1559,
    "gn:feature_class":"P",
    "gn:feature_code":"PPL",
    "gn:name":"San Pedro de la Pradera",
    "gn:population":13,
    "gn:timezone":"America/Chihuahua",
    "iso:country":"MX",
    "wof:name":"San Pedro de la Pradera",
    "wof:placetype":"locality",
    "wof:population":13
},
  "geometry": {"coordinates":[-108.54546000000001,30.69809],"type":"Point"}
}