{
  "type": "Feature",
  "properties": {
    "gn:admin1_code":"5",
    "gn:admin2_code":"64.0",
    "gn:asciiname":"Pacvilna",
    "gn:country_code":"MX",
    "gn:dem":1943,
    "gn:feature_class":"P",
    "gn:feature_code":"PPL",
    "gn:name":"Pacvilna",
    "gn:population":0,
    "gn:timezone":"America/Mexico_City",
    "iso:country":"MX",
    "name:spa_x_preferred":[
        "Pacvilna"
    ],
    "name:spa_x_variant":[
        "Pacuin\u00e1"
    ],
    "wof:name":"Pacvilna",
    "wof:placetype":"locality"
},
  "geometry": {"coordinates":[-92.37801,16.81699],"type":"Point"}
}