{
  "type": "Feature",
  "properties": {
    "gn:admin1_code":"16",
    "gn:admin2_code":"8",
    "gn:asciiname":"El Balsamo",
    "gn:country_code":"MX",
    "gn:dem":1204,
    "gn:feature_class":"P",
    "gn:feature_code":"PPL",
    "gn:name":"El B\u00e1lsamo",
    "gn:population":14,
    "gn:timezone":"America/Mexico_City",
    "iso:country":"MX",
    "name:und_x_variant":[
        "El B\u00e1lsamo"
    ],
    "wof:name":"El Balsamo",
    "wof:placetype":"locality",
    "wof:population":14
},
  "geometry": {"coordinates":[-102.90361,18.27056],"type":"Point"}
}