{
  "type": "Feature",
  "properties": {
    "gn:admin1_code":"16.0",
    "gn:admin2_code":"38.0",
    "gn:asciiname":"La Quetzeria (La Queseria)",
    "gn:country_code":"MX",
    "gn:dem":193,
    "gn:feature_class":"P",
    "gn:feature_code":"PPL",
    "gn:name":"La Quetzer\u00eda (La Queser\u00eda)",
    "gn:population":496,
    "gn:timezone":"America/Mexico_City",
    "iso:country":"MX",
    "wof:name":"La Quetzeria (La Queseria)",
    "wof:placetype":"locality",
    "wof:population":496
},
  "geometry": {"coordinates":[-101.29111,18.55056],"type":"Point"}
}