{
  "type": "Feature",
  "properties": {
    "gn:admin1_code":"11",
    "gn:admin2_code":"8",
    "gn:asciiname":"El Atravesano",
    "gn:country_code":"MX",
    "gn:dem":1734,
    "gn:feature_class":"P",
    "gn:feature_code":"PPL",
    "gn:name":"El Atravesa\u00f1o",
    "gn:population":21,
    "gn:timezone":"America/Mexico_City",
    "iso:country":"MX",
    "name:und_x_variant":[
        "El Atravesa\u00f1o"
    ],
    "wof:name":"El Atravesano",
    "wof:placetype":"locality",
    "wof:population":21
},
  "geometry": {"coordinates":[-101.75,20.73833],"type":"Point"}
}