{
  "type": "Feature",
  "properties": {
    "gn:admin1_code":"16",
    "gn:admin2_code":"26.0",
    "gn:asciiname":"La Limonera (La Limonera del Pozo)",
    "gn:country_code":"MX",
    "gn:dem":678,
    "gn:feature_class":"P",
    "gn:feature_code":"PPL",
    "gn:name":"La Limonera (La Limonera del Pozo)",
    "gn:population":5,
    "gn:timezone":"America/Mexico_City",
    "iso:country":"MX",
    "wof:name":"La Limonera (La Limonera del Pozo)",
    "wof:placetype":"locality",
    "wof:population":5
},
  "geometry": {"coordinates":[-103.35805999999999,18.78167],"type":"Point"}
}