{
  "type": "Feature",
  "properties": {
    "gn:admin1_code":"32.0",
    "gn:admin2_code":"17.0",
    "gn:asciiname":"El Quintero",
    "gn:country_code":"MX",
    "gn:dem":2429,
    "gn:feature_class":"P",
    "gn:feature_code":"PPL",
    "gn:name":"El Quintero",
    "gn:population":0,
    "gn:timezone":"America/Mexico_City",
    "iso:country":"MX",
    "name:spa_x_preferred":[
        "El Quintero"
    ],
    "wof:name":"El Quintero",
    "wof:placetype":"locality"
},
  "geometry": {"coordinates":[-102.56901000000001,22.63222],"type":"Point"}
}