{
  "type": "Feature",
  "properties": {
    "gn:admin1_code":"12",
    "gn:admin2_code":"40.0",
    "gn:asciiname":"Camotlan",
    "gn:country_code":"MX",
    "gn:dem":2336,
    "gn:feature_class":"P",
    "gn:feature_code":"PPL",
    "gn:name":"Camotl\u00e1n",
    "gn:population":0,
    "gn:timezone":"America/Mexico_City",
    "iso:country":"MX",
    "wof:name":"Camotlan",
    "wof:placetype":"locality"
},
  "geometry": {"coordinates":[-99.81667,17.56667],"type":"Point"}
}