{
  "type": "Feature",
  "properties": {
    "gn:admin1_code":"18",
    "gn:admin2_code":"7.0",
    "gn:asciiname":"Colonia Lindavista",
    "gn:country_code":"MX",
    "gn:dem":1935,
    "gn:feature_class":"P",
    "gn:feature_code":"PPL",
    "gn:name":"Colonia Lindavista",
    "gn:population":297,
    "gn:timezone":"America/Mazatlan",
    "iso:country":"MX",
    "wof:name":"Colonia Lindavista",
    "wof:placetype":"locality",
    "wof:population":297
},
  "geometry": {"coordinates":[-104.34611,21.11694],"type":"Point"}
}