{
  "type": "Feature",
  "properties": {
    "gn:admin1_code":"16",
    "gn:admin2_code":"10",
    "gn:asciiname":"La Catedral",
    "gn:country_code":"MX",
    "gn:dem":473,
    "gn:feature_class":"P",
    "gn:feature_code":"PPL",
    "gn:name":"La Catedral",
    "gn:population":26,
    "gn:timezone":"America/Mexico_City",
    "iso:country":"MX",
    "wof:name":"La Catedral",
    "wof:placetype":"locality",
    "wof:population":26
},
  "geometry": {"coordinates":[-102.66388999999999,18.23528],"type":"Point"}
}