{
  "type": "Feature",
  "properties": {
    "gn:admin1_code":"16",
    "gn:admin2_code":"10",
    "gn:asciiname":"La Catedral",
    "gn:country_code":"MX",
    "gn:dem":473,
    "gn:feature_class":"P",
    "gn:feature_code":"PPL",
    "gn:name":"La Catedral",
    "gn:population":26,
    "gn:timezone":"America/Mexico_City",
    "iso:country":"MX",
    "name:ara_x_preferred":[
        "\u0644\u0627 \u0643\u0627\u062a\u062f\u0631\u0627\u0644"
    ],
    "name:cym_x_preferred":[
        "La Catedral"
    ],
    "name:deu_x_preferred":[
        "La Catedral"
    ],
    "name:fra_x_preferred":[
        "La Catedral"
    ],
    "name:ita_x_preferred":[
        "La Catedral"
    ],
    "name:pol_x_preferred":[
        "La Catedral"
    ],
    "name:por_x_preferred":[
        "La Catedral"
    ],
    "name:rus_x_preferred":[
        "\u041b\u0430 \u041a\u0430\u0442\u0435\u0434\u0440\u0430\u043b\u044c"
    ],
    "name:spa_x_preferred":[
        "La Catedral"
    ],
    "wof:name":"La Catedral",
    "wof:placetype":"locality",
    "wof:population":26
},
  "geometry": {"coordinates":[-102.66388999999999,18.23528],"type":"Point"}
}