{
  "type": "Feature",
  "properties": {
    "gn:admin1_code":"15",
    "gn:admin2_code":"78.0",
    "gn:asciiname":"El Sifon",
    "gn:country_code":"MX",
    "gn:dem":1586,
    "gn:feature_class":"P",
    "gn:feature_code":"PPL",
    "gn:name":"El Sif\u00f3n",
    "gn:population":622,
    "gn:timezone":"America/Mexico_City",
    "iso:country":"MX",
    "name:und_x_variant":[
        "El Sif\u00f3n"
    ],
    "wof:name":"El Sifon",
    "wof:placetype":"locality",
    "wof:population":622
},
  "geometry": {"coordinates":[-100.23202000000001,19.17717],"type":"Point"}
}