{
  "type": "Feature",
  "properties": {
    "gn:admin1_code":"30",
    "gn:admin2_code":"143.0",
    "gn:asciiname":"San Marquitos",
    "gn:country_code":"MX",
    "gn:dem":26,
    "gn:feature_class":"P",
    "gn:feature_code":"PPL",
    "gn:name":"San Marquitos",
    "gn:population":199,
    "gn:timezone":"America/Mexico_City",
    "iso:country":"MX",
    "wof:name":"San Marquitos",
    "wof:placetype":"locality",
    "wof:population":199
},
  "geometry": {"coordinates":[-95.44139,18.46278],"type":"Point"}
}