{
  "type": "Feature",
  "properties": {
    "gn:admin1_code":"21.0",
    "gn:admin2_code":"114.0",
    "gn:asciiname":"Xaltecacahuayo",
    "gn:country_code":"MX",
    "gn:dem":2823,
    "gn:feature_class":"P",
    "gn:feature_code":"PPL",
    "gn:name":"Xaltecacahuayo",
    "gn:population":0,
    "gn:timezone":"America/Mexico_City",
    "iso:country":"MX",
    "name:spa_x_preferred":[
        "Tecamachalco"
    ],
    "name:spa_x_variant":[
        "Xaltecacahuayo"
    ],
    "wof:name":"Xaltecacahuayo",
    "wof:placetype":"locality"
},
  "geometry": {"coordinates":[-98.05262999999999,19.157],"type":"Point"}
}