{
  "type": "Feature",
  "properties": {
    "gn:admin1_code":"20",
    "gn:admin2_code":"31.0",
    "gn:asciiname":"Cuatro Palos",
    "gn:country_code":"MX",
    "gn:dem":2606,
    "gn:feature_class":"P",
    "gn:feature_code":"PPL",
    "gn:name":"Cuatro Palos",
    "gn:population":355,
    "gn:timezone":"America/Mexico_City",
    "iso:country":"MX",
    "wof:name":"Cuatro Palos",
    "wof:placetype":"locality",
    "wof:population":355
},
  "geometry": {"coordinates":[-96.00082999999999,17.05167],"type":"Point"}
}