{
  "type": "Feature",
  "properties": {
    "gn:admin1_code":"16.0",
    "gn:admin2_code":"96.0",
    "gn:asciiname":"El Chupadero",
    "gn:country_code":"MX",
    "gn:dem":1061,
    "gn:feature_class":"P",
    "gn:feature_code":"PPL",
    "gn:name":"El Chupadero",
    "gn:population":0,
    "gn:timezone":"America/Mexico_City",
    "iso:country":"MX",
    "name:spa_x_preferred":[
        "El Chupadero"
    ],
    "wof:name":"El Chupadero",
    "wof:placetype":"locality"
},
  "geometry": {"coordinates":[-102.62166000000001,18.67065],"type":"Point"}
}