{
  "type": "Feature",
  "properties": {
    "gn:admin1_code":"7",
    "gn:admin2_code":"13.0",
    "gn:asciiname":"La Zacatosa",
    "gn:country_code":"MX",
    "gn:dem":237,
    "gn:feature_class":"P",
    "gn:feature_code":"PPL",
    "gn:name":"La Zacatosa",
    "gn:population":0,
    "gn:timezone":"America/Monterrey",
    "iso:country":"MX",
    "name:spa_x_preferred":[
        "La Zacatosa"
    ],
    "name:und_x_variant":[
        "Rancho La Zacatosa"
    ],
    "wof:name":"La Zacatosa",
    "wof:placetype":"locality"
},
  "geometry": {"coordinates":[-100.19929999999999,27.82307],"type":"Point"}
}