{
  "type": "Feature",
  "properties": {
    "gn:admin1_code":"24.0",
    "gn:admin2_code":"11.0",
    "gn:asciiname":"La Reformita",
    "gn:country_code":"MX",
    "gn:dem":1018,
    "gn:feature_class":"P",
    "gn:feature_code":"PPL",
    "gn:name":"La Reformita",
    "gn:population":0,
    "gn:timezone":"America/Mexico_City",
    "iso:country":"MX",
    "name:spa_x_preferred":[
        "La Reformita"
    ],
    "wof:name":"La Reformita",
    "wof:placetype":"locality"
},
  "geometry": {"coordinates":[-100.08450000000001,21.98161],"type":"Point"}
}