{
  "type": "Feature",
  "properties": {
    "gn:admin1_code":"32",
    "gn:admin2_code":"14.0",
    "gn:asciiname":"San Juan de Ahorcados",
    "gn:country_code":"MX",
    "gn:dem":1787,
    "gn:feature_class":"P",
    "gn:feature_code":"PPL",
    "gn:name":"San Juan de Ahorcados",
    "gn:population":0,
    "gn:timezone":"America/Mexico_City",
    "iso:country":"MX",
    "name:und_x_variant":[
        "San Juan de Ahorcadas",
        "San Juan de Ahorcados"
    ],
    "wof:name":"San Juan de Ahorcados",
    "wof:placetype":"locality"
},
  "geometry": {"coordinates":[-102.3021,24.01472],"type":"Point"}
}