{
  "type": "Feature",
  "properties": {
    "gn:admin1_code":"10",
    "gn:admin2_code":"7.0",
    "gn:asciiname":"San Jose del Vinedo [Propiedad Privada]",
    "gn:country_code":"MX",
    "gn:dem":1120,
    "gn:feature_class":"P",
    "gn:feature_code":"PPL",
    "gn:name":"San Jos\u00e9 del Vi\u00f1edo [Propiedad Privada]",
    "gn:population":4,
    "gn:timezone":"America/Monterrey",
    "iso:country":"MX",
    "name:und_x_variant":[
        "San Jos\u00e9 del Vi\u00f1edo [Propiedad Privada]"
    ],
    "wof:name":"San Jose del Vinedo [Propiedad Privada]",
    "wof:placetype":"locality",
    "wof:population":4
},
  "geometry": {"coordinates":[-103.41701,25.65751],"type":"Point"}
}