{
  "type": "Feature",
  "properties": {
    "gn:admin1_code":"30",
    "gn:admin2_code":"40",
    "gn:asciiname":"Enrique Decuir",
    "gn:country_code":"MX",
    "gn:dem":113,
    "gn:feature_class":"P",
    "gn:feature_code":"PPL",
    "gn:name":"Enrique Decuir",
    "gn:population":10,
    "gn:timezone":"America/Mexico_City",
    "iso:country":"MX",
    "wof:name":"Enrique Decuir",
    "wof:placetype":"locality",
    "wof:population":10
},
  "geometry": {"coordinates":[-97.55556,20.40611],"type":"Point"}
}