{
  "type": "Feature",
  "properties": {
    "gn:admin1_code":"5",
    "gn:admin2_code":"57",
    "gn:asciiname":"Belgica",
    "gn:country_code":"MX",
    "gn:dem":984,
    "gn:feature_class":"P",
    "gn:feature_code":"PPL",
    "gn:name":"B\u00e9lgica",
    "gn:population":15,
    "gn:timezone":"America/Mexico_City",
    "iso:country":"MX",
    "name:und_x_variant":[
        "B\u00e9lgica"
    ],
    "wof:name":"Belgica",
    "wof:placetype":"locality",
    "wof:population":15
},
  "geometry": {"coordinates":[-92.37972000000001,15.25861],"type":"Point"}
}