{
  "type": "Feature",
  "properties": {
    "gn:admin1_code":"20",
    "gn:admin2_code":"277.0",
    "gn:asciiname":"Arroyo del Pajarito",
    "gn:country_code":"MX",
    "gn:dem":1401,
    "gn:feature_class":"P",
    "gn:feature_code":"PPL",
    "gn:name":"Arroyo del Pajarito",
    "gn:population":198,
    "gn:timezone":"America/Mexico_City",
    "iso:country":"MX",
    "wof:name":"Arroyo del Pajarito",
    "wof:placetype":"locality",
    "wof:population":198
},
  "geometry": {"coordinates":[-96.92722000000001,16.46722],"type":"Point"}
}