{
  "type": "Feature",
  "properties": {
    "gn:admin1_code":"30",
    "gn:admin2_code":"19.0",
    "gn:asciiname":"Tepantla",
    "gn:country_code":"MX",
    "gn:dem":2445,
    "gn:feature_class":"P",
    "gn:feature_code":"PPL",
    "gn:name":"Tepantla",
    "gn:population":141,
    "gn:timezone":"America/Mexico_City",
    "iso:country":"MX",
    "wof:name":"Tepantla",
    "wof:placetype":"locality",
    "wof:population":141
},
  "geometry": {"coordinates":[-97.12889,18.56778],"type":"Point"}
}