{
  "type": "Feature",
  "properties": {
    "gn:admin1_code":"6",
    "gn:admin2_code":"67.0",
    "gn:asciiname":"San Agustin",
    "gn:country_code":"MX",
    "gn:dem":1414,
    "gn:feature_class":"P",
    "gn:feature_code":"PPL",
    "gn:name":"San Agust\u00edn",
    "gn:population":0,
    "gn:timezone":"America/Chihuahua",
    "iso:country":"MX",
    "name:spa_x_preferred":[
        "San Agust\u00edn"
    ],
    "name:und_x_variant":[
        "Rancho San Agustin"
    ],
    "wof:name":"San Agustin",
    "wof:placetype":"locality"
},
  "geometry": {"coordinates":[-105.81712,27.61214],"type":"Point"}
}