{
  "type": "Feature",
  "properties": {
    "gn:admin1_code":"6.0",
    "gn:admin2_code":"47.0",
    "gn:asciiname":"El Pulpito",
    "gn:country_code":"MX",
    "gn:dem":723,
    "gn:feature_class":"P",
    "gn:feature_code":"PPL",
    "gn:name":"El P\u00falpito",
    "gn:population":0,
    "gn:timezone":"America/Chihuahua",
    "iso:country":"MX",
    "wof:name":"El Pulpito",
    "wof:placetype":"locality"
},
  "geometry": {"coordinates":[-108.49939999999999,28.08463],"type":"Point"}
}