{
  "type": "Feature",
  "properties": {
    "gn:admin1_code":"4",
    "gn:admin2_code":"10.0",
    "gn:asciiname":"Unidad y Trabajo",
    "gn:country_code":"MX",
    "gn:dem":241,
    "gn:feature_class":"P",
    "gn:feature_code":"PPL",
    "gn:name":"Unidad y Trabajo",
    "gn:population":151,
    "gn:timezone":"America/Cancun",
    "iso:country":"MX",
    "wof:name":"Unidad y Trabajo",
    "wof:placetype":"locality",
    "wof:population":151
},
  "geometry": {"coordinates":[-89.40056,18.1175],"type":"Point"}
}