{
  "type": "Feature",
  "properties": {
    "gn:admin1_code":"26",
    "gn:admin2_code":"33",
    "gn:asciiname":"Los Boquivos",
    "gn:country_code":"MX",
    "gn:dem":4,
    "gn:feature_class":"P",
    "gn:feature_code":"PPL",
    "gn:name":"Los Boquivos",
    "gn:population":10,
    "gn:timezone":"America/Hermosillo",
    "iso:country":"MX",
    "wof:name":"Los Boquivos",
    "wof:placetype":"locality",
    "wof:population":10
},
  "geometry": {"coordinates":[-109.66943999999999,26.76611],"type":"Point"}
}