{
  "type": "Feature",
  "properties": {
    "gn:admin1_code":"19",
    "gn:admin2_code":"50.0",
    "gn:asciiname":"Rancho La Lajilla",
    "gn:country_code":"MX",
    "gn:dem":205,
    "gn:feature_class":"P",
    "gn:feature_code":"PPL",
    "gn:name":"Rancho La Lajilla",
    "gn:population":0,
    "gn:timezone":"America/Monterrey",
    "iso:country":"MX",
    "wof:name":"Rancho La Lajilla",
    "wof:placetype":"locality"
},
  "geometry": {"coordinates":[-99.91667,26.61667000000001],"type":"Point"}
}