{
  "type": "Feature",
  "properties": {
    "gn:admin1_code":"30",
    "gn:admin2_code":"209.0",
    "gn:asciiname":"Venustiano Carranza",
    "gn:country_code":"MX",
    "gn:dem":220,
    "gn:feature_class":"P",
    "gn:feature_code":"PPL",
    "gn:name":"Venustiano Carranza",
    "gn:population":0,
    "gn:timezone":"America/Mexico_City",
    "iso:country":"MX",
    "name:spa_x_preferred":[
        "Venustiano Carranza"
    ],
    "wof:name":"Venustiano Carranza",
    "wof:placetype":"locality"
},
  "geometry": {"coordinates":[-94.7615,18.34343],"type":"Point"}
}