{
  "type": "Feature",
  "properties": {
    "gn:admin1_code":"28.0",
    "gn:admin2_code":"4.0",
    "gn:asciiname":"La Curva",
    "gn:country_code":"MX",
    "gn:dem":182,
    "gn:feature_class":"P",
    "gn:feature_code":"PPL",
    "gn:name":"La Curva",
    "gn:population":0,
    "gn:timezone":"America/Monterrey",
    "iso:country":"MX",
    "name:spa_x_preferred":[
        "La Curva"
    ],
    "wof:name":"La Curva",
    "wof:placetype":"locality"
},
  "geometry": {"coordinates":[-99.05315,22.59391],"type":"Point"}
}