{
  "type": "Feature",
  "properties": {
    "gn:admin1_code":"25.0",
    "gn:admin2_code":"11.0",
    "gn:asciiname":"Santa Veneranda Dos",
    "gn:country_code":"MX",
    "gn:dem":19,
    "gn:feature_class":"P",
    "gn:feature_code":"PPL",
    "gn:name":"Santa Veneranda Dos",
    "gn:population":0,
    "gn:timezone":"America/Mazatlan",
    "iso:country":"MX",
    "name:spa_x_preferred":[
        "Santa Veneranda Dos"
    ],
    "wof:name":"Santa Veneranda Dos",
    "wof:placetype":"locality"
},
  "geometry": {"coordinates":[-108.72879,25.7319],"type":"Point"}
}