{
  "type": "Feature",
  "properties": {
    "gn:admin1_code":"3",
    "gn:admin2_code":"1.0",
    "gn:asciiname":"Los Dormideros",
    "gn:country_code":"MX",
    "gn:dem":535,
    "gn:feature_class":"P",
    "gn:feature_code":"PPL",
    "gn:name":"Los Dormideros",
    "gn:population":5,
    "gn:timezone":"America/Mazatlan",
    "iso:country":"MX",
    "wof:name":"Los Dormideros",
    "wof:placetype":"locality",
    "wof:population":5
},
  "geometry": {"coordinates":[-111.95187,26.17809],"type":"Point"}
}