{
  "type": "Feature",
  "properties": {
    "gn:admin1_code":"8",
    "gn:admin2_code":"9.0",
    "gn:asciiname":"La Era (Lucio Leon)",
    "gn:country_code":"MX",
    "gn:dem":34,
    "gn:feature_class":"P",
    "gn:feature_code":"PPL",
    "gn:name":"La Era (Lucio Le\u00f3n)",
    "gn:population":4,
    "gn:timezone":"America/Mexico_City",
    "iso:country":"MX",
    "name:und_x_variant":[
        "La Era (Lucio Le\u00f3n)"
    ],
    "wof:name":"La Era (Lucio Leon)",
    "wof:placetype":"locality",
    "wof:population":4
},
  "geometry": {"coordinates":[-103.89444,18.90806],"type":"Point"}
}