{
  "type": "Feature",
  "properties": {
    "gn:admin1_code":"16",
    "gn:admin2_code":"101",
    "gn:asciiname":"La Jabonera (El Zapote)",
    "gn:country_code":"MX",
    "gn:dem":1226,
    "gn:feature_class":"P",
    "gn:feature_code":"PPL",
    "gn:name":"La Jabonera (El Zapote)",
    "gn:population":19,
    "gn:timezone":"America/Mexico_City",
    "iso:country":"MX",
    "wof:name":"La Jabonera (El Zapote)",
    "wof:placetype":"locality",
    "wof:population":19
},
  "geometry": {"coordinates":[-100.82583,19.41333],"type":"Point"}
}