{
  "type": "Feature",
  "properties": {
    "gn:admin1_code":"23",
    "gn:admin2_code":"8.0",
    "gn:asciiname":"Sajacanchen",
    "gn:country_code":"MX",
    "gn:dem":27,
    "gn:feature_class":"P",
    "gn:feature_code":"PPL",
    "gn:name":"Sajacanch\u00e9n",
    "gn:population":0,
    "gn:timezone":"America/Cancun",
    "iso:country":"MX",
    "wof:name":"Sajacanchen",
    "wof:placetype":"locality"
},
  "geometry": {"coordinates":[-87.61667,20.65],"type":"Point"}
}