{
  "type": "Feature",
  "properties": {
    "gn:admin1_code":"21",
    "gn:admin2_code":"177.0",
    "gn:asciiname":"De Rojas",
    "gn:country_code":"MX",
    "gn:dem":1904,
    "gn:feature_class":"P",
    "gn:feature_code":"PPL",
    "gn:name":"De Rojas",
    "gn:population":607,
    "gn:timezone":"America/Mexico_City",
    "iso:country":"MX",
    "wof:name":"De Rojas",
    "wof:placetype":"locality",
    "wof:population":607
},
  "geometry": {"coordinates":[-97.65667000000001,18.63],"type":"Point"}
}