{
  "type": "Feature",
  "properties": {
    "gn:admin1_code":"22",
    "gn:admin2_code":"13",
    "gn:asciiname":"Las Flores",
    "gn:country_code":"MX",
    "gn:dem":1363,
    "gn:feature_class":"P",
    "gn:feature_code":"PPL",
    "gn:name":"Las Flores",
    "gn:population":13,
    "gn:timezone":"America/Mexico_City",
    "iso:country":"MX",
    "wof:name":"Las Flores",
    "wof:placetype":"locality",
    "wof:population":13
},
  "geometry": {"coordinates":[-99.81889,21.05639],"type":"Point"}
}