{
  "type": "Feature",
  "properties": {
    "gn:admin1_code":"16",
    "gn:admin2_code":"6.0",
    "gn:asciiname":"San Mateo",
    "gn:country_code":"MX",
    "gn:dem":429,
    "gn:feature_class":"P",
    "gn:feature_code":"PPL",
    "gn:name":"San Mateo",
    "gn:population":0,
    "gn:timezone":"America/Mexico_City",
    "iso:country":"MX",
    "wof:name":"San Mateo",
    "wof:placetype":"locality"
},
  "geometry": {"coordinates":[-102.48333,18.85],"type":"Point"}
}