{
  "type": "Feature",
  "properties": {
    "gn:admin1_code":"26.0",
    "gn:admin2_code":"3.0",
    "gn:asciiname":"Gerocoa",
    "gn:country_code":"MX",
    "gn:dem":187,
    "gn:feature_class":"P",
    "gn:feature_code":"PPL",
    "gn:name":"Gerocoa",
    "gn:population":0,
    "gn:timezone":"America/Hermosillo",
    "iso:country":"MX",
    "name:und_x_variant":[
        "Jerocoa"
    ],
    "wof:name":"Gerocoa",
    "wof:placetype":"locality"
},
  "geometry": {"coordinates":[-108.89946,26.80266],"type":"Point"}
}