{
  "type": "Feature",
  "properties": {
    "gn:admin1_code":"21",
    "gn:admin2_code":"166.0",
    "gn:asciiname":"La Magdalena",
    "gn:country_code":"MX",
    "gn:dem":1454,
    "gn:feature_class":"P",
    "gn:feature_code":"PPL",
    "gn:name":"La Magdalena",
    "gn:population":346,
    "gn:timezone":"America/Mexico_City",
    "iso:country":"MX",
    "wof:name":"La Magdalena",
    "wof:placetype":"locality",
    "wof:population":346
},
  "geometry": {"coordinates":[-98.43944,18.70194],"type":"Point"}
}