{
  "type": "Feature",
  "properties": {
    "gn:admin1_code":"16",
    "gn:admin2_code":"35.0",
    "gn:asciiname":"Manga de Chavez",
    "gn:country_code":"MX",
    "gn:dem":426,
    "gn:feature_class":"P",
    "gn:feature_code":"PPL",
    "gn:name":"Manga de Ch\u00e1vez",
    "gn:population":65,
    "gn:timezone":"America/Mexico_City",
    "iso:country":"MX",
    "name:und_x_variant":[
        "Manga de Ch\u00e1vez"
    ],
    "wof:name":"Manga de Chavez",
    "wof:placetype":"locality",
    "wof:population":65
},
  "geometry": {"coordinates":[-101.85778000000001,18.96778],"type":"Point"}
}