{
  "type": "Feature",
  "properties": {
    "gn:admin1_code":"6",
    "gn:admin2_code":"7",
    "gn:asciiname":"La Mesa de Talayotes",
    "gn:country_code":"MX",
    "gn:dem":2577,
    "gn:feature_class":"P",
    "gn:feature_code":"PPL",
    "gn:name":"La Mesa de Talayotes",
    "gn:population":27,
    "gn:timezone":"America/Chihuahua",
    "iso:country":"MX",
    "wof:name":"La Mesa de Talayotes",
    "wof:placetype":"locality",
    "wof:population":27
},
  "geometry": {"coordinates":[-106.56981,26.4533],"type":"Point"}
}