{
  "type": "Feature",
  "properties": {
    "gn:admin1_code":"19.0",
    "gn:admin2_code":"11.0",
    "gn:asciiname":"La Vuelta del Encinal",
    "gn:country_code":"MX",
    "gn:dem":314,
    "gn:feature_class":"P",
    "gn:feature_code":"PPL",
    "gn:name":"La Vuelta del Encinal",
    "gn:population":0,
    "gn:timezone":"America/Monterrey",
    "iso:country":"MX",
    "name:spa_x_preferred":[
        "La Vuelta del Encinal"
    ],
    "wof:name":"La Vuelta del Encinal",
    "wof:placetype":"locality"
},
  "geometry": {"coordinates":[-99.70323,26.18049],"type":"Point"}
}