{
  "type": "Feature",
  "properties": {
    "gn:admin1_code":"16",
    "gn:admin2_code":"97",
    "gn:asciiname":"Las Calabazas (Las Calabacitas)",
    "gn:country_code":"MX",
    "gn:dem":1070,
    "gn:feature_class":"P",
    "gn:feature_code":"PPL",
    "gn:name":"Las Calabazas (Las Calabacitas)",
    "gn:population":21,
    "gn:timezone":"America/Mexico_City",
    "iso:country":"MX",
    "wof:name":"Las Calabazas (Las Calabacitas)",
    "wof:placetype":"locality",
    "wof:population":21
},
  "geometry": {"coordinates":[-101.45111,18.80806],"type":"Point"}
}