{
  "type": "Feature",
  "properties": {
    "gn:admin1_code":"12",
    "gn:admin2_code":"41.0",
    "gn:asciiname":"Moyotepec (Moyotepec de Juarez)",
    "gn:country_code":"MX",
    "gn:dem":2264,
    "gn:feature_class":"P",
    "gn:feature_code":"PPL",
    "gn:name":"Moyotepec (Moyotepec de Ju\u00e1rez)",
    "gn:population":1007,
    "gn:timezone":"America/Mexico_City",
    "iso:country":"MX",
    "name:und_x_variant":[
        "Moyotepec (Moyotepec de Ju\u00e1rez)"
    ],
    "wof:name":"Moyotepec (Moyotepec de Juarez)",
    "wof:placetype":"locality",
    "wof:population":1007
},
  "geometry": {"coordinates":[-98.68556,17.33167000000001],"type":"Point"}
}