{
  "type": "Feature",
  "properties": {
    "gn:admin1_code":"12.0",
    "gn:admin2_code":"22.0",
    "gn:asciiname":"Las Pilas",
    "gn:country_code":"MX",
    "gn:dem":1525,
    "gn:feature_class":"P",
    "gn:feature_code":"PPL",
    "gn:name":"Las Pilas",
    "gn:population":0,
    "gn:timezone":"America/Mexico_City",
    "iso:country":"MX",
    "name:spa_x_preferred":[
        "Las Pilas"
    ],
    "wof:name":"Las Pilas",
    "wof:placetype":"locality"
},
  "geometry": {"coordinates":[-100.83477999999999,17.85429],"type":"Point"}
}