{
  "type": "Feature",
  "properties": {
    "gn:admin1_code":"19",
    "gn:admin2_code":"32.0",
    "gn:asciiname":"Piedra Parada",
    "gn:cc2":"MX",
    "gn:country_code":"MX",
    "gn:dem":236,
    "gn:feature_class":"P",
    "gn:feature_code":"PPL",
    "gn:name":"Piedra Parada",
    "gn:population":0,
    "gn:timezone":"America/Monterrey",
    "iso:country":"MX",
    "name:und_x_variant":[
        "Hedra Parada",
        "Piedra Parada"
    ],
    "wof:name":"Piedra Parada",
    "wof:placetype":"locality"
},
  "geometry": {"coordinates":[-100.09999999999999,26.86667000000001],"type":"Point"}
}