{
  "type": "Feature",
  "properties": {
    "gn:admin1_code":"5",
    "gn:admin2_code":"2.0",
    "gn:asciiname":"El Amatal",
    "gn:country_code":"MX",
    "gn:dem":428,
    "gn:feature_class":"P",
    "gn:feature_code":"PPL",
    "gn:name":"El Amatal",
    "gn:population":4,
    "gn:timezone":"America/Mexico_City",
    "iso:country":"MX",
    "wof:name":"El Amatal",
    "wof:placetype":"locality",
    "wof:population":4
},
  "geometry": {"coordinates":[-92.76944,16.45556],"type":"Point"}
}