{
  "type": "Feature",
  "properties": {
    "gn:admin1_code":"20",
    "gn:admin2_code":"159.0",
    "gn:asciiname":"Santo Domingo Coatlan",
    "gn:country_code":"MX",
    "gn:dem":2063,
    "gn:feature_class":"P",
    "gn:feature_code":"PPL",
    "gn:name":"Santo Domingo Coatl\u00e1n",
    "gn:population":0,
    "gn:timezone":"America/Mexico_City",
    "iso:country":"MX",
    "name:spa_x_preferred":[
        "Santo Domingo Coatl\u00e1n"
    ],
    "wof:name":"Santo Domingo Coatlan",
    "wof:placetype":"locality"
},
  "geometry": {"coordinates":[-96.89667,16.20167],"type":"Point"}
}