{
  "type": "Feature",
  "properties": {
    "gn:admin1_code":"5",
    "gn:admin2_code":"17.0",
    "gn:asciiname":"Hermanos Cervantes",
    "gn:country_code":"MX",
    "gn:dem":572,
    "gn:feature_class":"P",
    "gn:feature_code":"PPL",
    "gn:name":"Hermanos Cervantes",
    "gn:population":5,
    "gn:timezone":"America/Mexico_City",
    "iso:country":"MX",
    "wof:name":"Hermanos Cervantes",
    "wof:placetype":"locality",
    "wof:population":5
},
  "geometry": {"coordinates":[-93.76222,16.67722],"type":"Point"}
}