{
  "type": "Feature",
  "properties": {
    "gn:admin1_code":"30.0",
    "gn:admin2_code":"191.0",
    "gn:asciiname":"Bara de Chachalacas",
    "gn:country_code":"MX",
    "gn:dem":13,
    "gn:feature_class":"P",
    "gn:feature_code":"PPL",
    "gn:name":"Bara de Chachalacas",
    "gn:population":0,
    "gn:timezone":"America/Mexico_City",
    "iso:country":"MX",
    "name:spa_x_preferred":[
        "Bara de Chachalacas"
    ],
    "wof:name":"Bara de Chachalacas",
    "wof:placetype":"locality"
},
  "geometry": {"coordinates":[-96.34159,19.40643],"type":"Point"}
}