{
  "type": "Feature",
  "properties": {
    "gn:admin1_code":"5",
    "gn:admin2_code":"51.0",
    "gn:asciiname":"La Cabana",
    "gn:country_code":"MX",
    "gn:dem":10,
    "gn:feature_class":"P",
    "gn:feature_code":"PPL",
    "gn:name":"La Caba\u00f1a",
    "gn:population":6,
    "gn:timezone":"America/Mexico_City",
    "iso:country":"MX",
    "name:und_x_variant":[
        "La Caba\u00f1a"
    ],
    "wof:name":"La Cabana",
    "wof:placetype":"locality",
    "wof:population":6
},
  "geometry": {"coordinates":[-92.84528,15.30861],"type":"Point"}
}