{
  "type": "Feature",
  "properties": {
    "gn:admin1_code":"5",
    "gn:admin2_code":"108",
    "gn:asciiname":"Las Tres Palmas",
    "gn:country_code":"MX",
    "gn:dem":806,
    "gn:feature_class":"P",
    "gn:feature_code":"PPL",
    "gn:name":"Las Tres Palmas",
    "gn:population":11,
    "gn:timezone":"America/Mexico_City",
    "iso:country":"MX",
    "wof:name":"Las Tres Palmas",
    "wof:placetype":"locality",
    "wof:population":11
},
  "geometry": {"coordinates":[-93.22833,16.36111],"type":"Point"}
}