{
  "type": "Feature",
  "properties": {
    "gn:admin1_code":"25",
    "gn:admin2_code":"7.0",
    "gn:asciiname":"El Platano",
    "gn:country_code":"MX",
    "gn:dem":381,
    "gn:feature_class":"P",
    "gn:feature_code":"PPL",
    "gn:name":"El Pl\u00e1tano",
    "gn:population":0,
    "gn:timezone":"America/Mazatlan",
    "iso:country":"MX",
    "name:spa_x_preferred":[
        "El Pl\u00e1tano"
    ],
    "wof:name":"El Platano",
    "wof:placetype":"locality"
},
  "geometry": {"coordinates":[-108.28603,26.73917],"type":"Point"}
}