{
  "type": "Feature",
  "properties": {
    "gn:admin1_code":"11",
    "gn:admin2_code":"44.0",
    "gn:asciiname":"Suchitlan",
    "gn:country_code":"MX",
    "gn:dem":1730,
    "gn:feature_class":"P",
    "gn:feature_code":"PPL",
    "gn:name":"Suchitl\u00e1n",
    "gn:population":1676,
    "gn:timezone":"America/Mexico_City",
    "iso:country":"MX",
    "name:spa_x_preferred":[
        "Suchitl\u00e1n"
    ],
    "wof:name":"Suchitlan",
    "wof:placetype":"locality",
    "wof:population":1676
},
  "geometry": {"coordinates":[-101.0236,20.5332],"type":"Point"}
}