{
  "type": "Feature",
  "properties": {
    "gn:admin1_code":"24.0",
    "gn:admin2_code":"13.0",
    "gn:asciiname":"El Huisachito",
    "gn:country_code":"MX",
    "gn:dem":228,
    "gn:feature_class":"P",
    "gn:feature_code":"PPL",
    "gn:name":"El Huisachito",
    "gn:population":0,
    "gn:timezone":"America/Mexico_City",
    "iso:country":"MX",
    "name:spa_x_preferred":[
        "El Huisachito"
    ],
    "wof:name":"El Huisachito",
    "wof:placetype":"locality"
},
  "geometry": {"coordinates":[-99.21993999999999,22.16699],"type":"Point"}
}