{
  "type": "Feature",
  "properties": {
    "gn:admin1_code":"10",
    "gn:admin2_code":"4.0",
    "gn:asciiname":"El Tepetate",
    "gn:country_code":"MX",
    "gn:dem":1928,
    "gn:feature_class":"P",
    "gn:feature_code":"PPL",
    "gn:name":"El Tepetate",
    "gn:population":0,
    "gn:timezone":"America/Monterrey",
    "iso:country":"MX",
    "name:spa_x_preferred":[
        "El Tepetate"
    ],
    "wof:name":"El Tepetate",
    "wof:placetype":"locality"
},
  "geometry": {"coordinates":[-103.84372999999999,24.6751],"type":"Point"}
}