{
  "type": "Feature",
  "properties": {
    "gn:admin1_code":"12",
    "gn:admin2_code":"58.0",
    "gn:asciiname":"Laguna Seca",
    "gn:country_code":"MX",
    "gn:dem":1482,
    "gn:feature_class":"P",
    "gn:feature_code":"PPL",
    "gn:name":"Laguna Seca",
    "gn:population":0,
    "gn:timezone":"America/Mexico_City",
    "iso:country":"MX",
    "name:ceb_x_preferred":[
        "Laguna Seca"
    ],
    "name:deu_x_preferred":[
        "Laguna Seca"
    ],
    "name:nld_x_preferred":[
        "Laguna Seca"
    ],
    "name:spa_x_preferred":[
        "Laguna Seca"
    ],
    "name:srp_x_preferred":[
        "\u041b\u0430\u0433\u0443\u043d\u0430 \u0421\u0435\u043a\u0430"
    ],
    "name:swe_x_preferred":[
        "Laguna Seca"
    ],
    "name:und_x_variant":[
        "La Laguna Seca"
    ],
    "wof:name":"Laguna Seca",
    "wof:placetype":"locality"
},
  "geometry": {"coordinates":[-99.97324,18.27121],"type":"Point"}
}