{
  "type": "Feature",
  "properties": {
    "gn:admin1_code":"12",
    "gn:admin2_code":"58.0",
    "gn:asciiname":"Laguna Seca",
    "gn:country_code":"MX",
    "gn:dem":1482,
    "gn:feature_class":"P",
    "gn:feature_code":"PPL",
    "gn:name":"Laguna Seca",
    "gn:population":0,
    "gn:timezone":"America/Mexico_City",
    "iso:country":"MX",
    "name:spa_x_preferred":[
        "Laguna Seca"
    ],
    "name:und_x_variant":[
        "La Laguna Seca"
    ],
    "wof:name":"Laguna Seca",
    "wof:placetype":"locality"
},
  "geometry": {"coordinates":[-99.97324,18.27121],"type":"Point"}
}