{
  "type": "Feature",
  "properties": {
    "gn:admin1_code":"15.0",
    "gn:admin2_code":"32.0",
    "gn:asciiname":"San Juan Xoconusco",
    "gn:country_code":"MX",
    "gn:dem":2067,
    "gn:feature_class":"P",
    "gn:feature_code":"PPL",
    "gn:name":"San Juan Xoconusco",
    "gn:population":0,
    "gn:timezone":"America/Mexico_City",
    "iso:country":"MX",
    "name:spa_x_preferred":[
        "San Juan Xoconusco"
    ],
    "wof:name":"San Juan Xoconusco",
    "wof:placetype":"locality"
},
  "geometry": {"coordinates":[-100.2593,19.31159],"type":"Point"}
}