{
  "type": "Feature",
  "properties": {
    "gn:admin1_code":"10",
    "gn:admin2_code":"7.0",
    "gn:asciiname":"Elpidio",
    "gn:country_code":"MX",
    "gn:dem":1123,
    "gn:feature_class":"P",
    "gn:feature_code":"PPL",
    "gn:name":"Elpidio",
    "gn:population":0,
    "gn:timezone":"America/Monterrey",
    "iso:country":"MX",
    "name:deu_x_preferred":[
        "Elpidio"
    ],
    "name:ita_x_preferred":[
        "Elpidio"
    ],
    "name:spa_x_preferred":[
        "Elpidio"
    ],
    "wof:name":"Elpidio",
    "wof:placetype":"locality"
},
  "geometry": {"coordinates":[-103.55755000000001,25.62104],"type":"Point"}
}