{
  "type": "Feature",
  "properties": {
    "gn:admin1_code":"5",
    "gn:admin2_code":"77.0",
    "gn:asciiname":"San Antonio (La Ciria)",
    "gn:country_code":"MX",
    "gn:dem":408,
    "gn:feature_class":"P",
    "gn:feature_code":"PPL",
    "gn:name":"San Antonio (La Ciria)",
    "gn:population":6,
    "gn:timezone":"America/Mexico_City",
    "iso:country":"MX",
    "wof:name":"San Antonio (La Ciria)",
    "wof:placetype":"locality",
    "wof:population":6
},
  "geometry": {"coordinates":[-92.02,17.23417],"type":"Point"}
}