{
  "type": "Feature",
  "properties": {
    "gn:admin1_code":"5",
    "gn:admin2_code":"100.0",
    "gn:asciiname":"Panchen Dos",
    "gn:country_code":"MX",
    "gn:dem":1410,
    "gn:feature_class":"P",
    "gn:feature_code":"PPL",
    "gn:name":"Panch\u00e9n Dos",
    "gn:population":103,
    "gn:timezone":"America/Mexico_City",
    "iso:country":"MX",
    "name:und_x_variant":[
        "Panch\u00e9n Dos"
    ],
    "wof:name":"Panchen Dos",
    "wof:placetype":"locality",
    "wof:population":103
},
  "geometry": {"coordinates":[-92.33389,17.26167],"type":"Point"}
}