{
  "type": "Feature",
  "properties": {
    "gn:admin1_code":"6",
    "gn:admin2_code":"56.0",
    "gn:asciiname":"El Fresno",
    "gn:country_code":"MX",
    "gn:dem":1462,
    "gn:feature_class":"P",
    "gn:feature_code":"PPL",
    "gn:name":"El Fresno",
    "gn:population":7,
    "gn:timezone":"America/Chihuahua",
    "iso:country":"MX",
    "name:ara_x_preferred":[
        "\u0625\u0644 \u0641\u0631\u064a\u0633\u0646\u0648"
    ],
    "name:ast_x_preferred":[
        "El Fresno"
    ],
    "name:cat_x_preferred":[
        "El Fresno"
    ],
    "name:ceb_x_preferred":[
        "El Fresno"
    ],
    "name:deu_x_preferred":[
        "El Fresno"
    ],
    "name:eus_x_preferred":[
        "El Fresno"
    ],
    "name:fas_x_preferred":[
        "\u0627\u0644 \u0641\u0631\u0633\u0646\u0648"
    ],
    "name:fra_x_preferred":[
        "El Fresno"
    ],
    "name:hun_x_preferred":[
        "El Fresno"
    ],
    "name:ina_x_preferred":[
        "El Fresno"
    ],
    "name:ita_x_preferred":[
        "El Fresno"
    ],
    "name:kaz_x_preferred":[
        "\u042d\u043b\u044c-\u0424\u0440\u0435\u0441\u043d\u043e"
    ],
    "name:mkd_x_preferred":[
        "\u0415\u043b \u0424\u0440\u0435\u0441\u043d\u043e"
    ],
    "name:msa_x_preferred":[
        "El Fresno"
    ],
    "name:nld_x_preferred":[
        "El Fresno"
    ],
    "name:oci_x_preferred":[
        "El Fresno"
    ],
    "name:pol_x_preferred":[
        "El Fresno"
    ],
    "name:por_x_preferred":[
        "El Fresno"
    ],
    "name:rus_x_preferred":[
        "\u042d\u043b\u044c-\u0424\u0440\u0435\u0441\u043d\u043e"
    ],
    "name:spa_x_preferred":[
        "El Fresno"
    ],
    "name:ukr_x_preferred":[
        "\u0415\u043b\u044c-\u0424\u0440\u0435\u0441\u043d\u043e"
    ],
    "name:uzb_x_preferred":[
        "El Fresno"
    ],
    "name:vie_x_preferred":[
        "El Fresno"
    ],
    "name:war_x_preferred":[
        "El Fresno"
    ],
    "name:zho_x_preferred":[
        "\u57c3\u5c14\u592b\u96f7\u65af\u8bfa"
    ],
    "wof:name":"El Fresno",
    "wof:placetype":"locality",
    "wof:population":7
},
  "geometry": {"coordinates":[-106.306,27.31216],"type":"Point"}
}