{
  "type": "Feature",
  "properties": {
    "gn:admin1_code":"6",
    "gn:admin2_code":"56.0",
    "gn:asciiname":"El Fresno",
    "gn:country_code":"MX",
    "gn:dem":1462,
    "gn:feature_class":"P",
    "gn:feature_code":"PPL",
    "gn:name":"El Fresno",
    "gn:population":7,
    "gn:timezone":"America/Chihuahua",
    "iso:country":"MX",
    "name:spa_x_preferred":[
        "El Fresno"
    ],
    "wof:name":"El Fresno",
    "wof:placetype":"locality",
    "wof:population":7
},
  "geometry": {"coordinates":[-106.306,27.31216],"type":"Point"}
}