{
  "type": "Feature",
  "properties": {
    "gn:admin1_code":"12.0",
    "gn:asciiname":"Tlalcinga",
    "gn:country_code":"MX",
    "gn:dem":1191,
    "gn:feature_class":"P",
    "gn:feature_code":"PPL",
    "gn:name":"Tlalcinga",
    "gn:population":0,
    "gn:timezone":"America/Mexico_City",
    "iso:country":"MX",
    "name:spa_x_preferred":[
        "Tlalcinga"
    ],
    "wof:name":"Tlalcinga",
    "wof:placetype":"locality"
},
  "geometry": {"coordinates":[-99.47508000000001,17.50812],"type":"Point"}
}