{
  "type": "Feature",
  "properties": {
    "gn:admin1_code":"30",
    "gn:admin2_code":"129.0",
    "gn:asciiname":"Ejido Monte Grande",
    "gn:country_code":"MX",
    "gn:dem":102,
    "gn:feature_class":"P",
    "gn:feature_code":"PPL",
    "gn:name":"Ejido Monte Grande",
    "gn:population":0,
    "gn:timezone":"America/Mexico_City",
    "iso:country":"MX",
    "name:spa_x_preferred":[
        "Ejido Monte Grande"
    ],
    "wof:name":"Ejido Monte Grande",
    "wof:placetype":"locality"
},
  "geometry": {"coordinates":[-98.41840999999999,21.29977],"type":"Point"}
}