{
  "type": "Feature",
  "properties": {
    "gn:admin1_code":"16",
    "gn:admin2_code":"112.0",
    "gn:asciiname":"Chimusda (Cuarta Manzana de Donaciano Ojeda)",
    "gn:country_code":"MX",
    "gn:dem":2210,
    "gn:feature_class":"P",
    "gn:feature_code":"PPL",
    "gn:name":"Chimusd\u00e1 (Cuarta Manzana de Donaciano Ojeda)",
    "gn:population":774,
    "gn:timezone":"America/Mexico_City",
    "iso:country":"MX",
    "name:und_x_variant":[
        "Chimusd\u00e1 (Cuarta Manzana de Donaciano Ojeda)"
    ],
    "wof:name":"Chimusda (Cuarta Manzana de Donaciano Ojeda)",
    "wof:placetype":"locality",
    "wof:population":774
},
  "geometry": {"coordinates":[-100.29889,19.47333],"type":"Point"}
}