{
  "type": "Feature",
  "properties": {
    "gn:admin1_code":"6",
    "gn:admin2_code":"62.0",
    "gn:asciiname":"Palos Clavados",
    "gn:country_code":"MX",
    "gn:dem":1183,
    "gn:feature_class":"P",
    "gn:feature_code":"PPL",
    "gn:name":"Palos Clavados",
    "gn:population":3,
    "gn:timezone":"America/Chihuahua",
    "iso:country":"MX",
    "name:spa_x_preferred":[
        "Palos Clavados"
    ],
    "name:und_x_variant":[
        "Rancho Palos Clavados"
    ],
    "wof:name":"Palos Clavados",
    "wof:placetype":"locality",
    "wof:population":3
},
  "geometry": {"coordinates":[-105.24165000000001,27.99941],"type":"Point"}
}