{
  "type": "Feature",
  "properties": {
    "gn:admin1_code":"6",
    "gn:admin2_code":"35.0",
    "gn:asciiname":"Campo Cinco",
    "gn:country_code":"MX",
    "gn:dem":2101,
    "gn:feature_class":"P",
    "gn:feature_code":"PPL",
    "gn:name":"Campo Cinco",
    "gn:population":0,
    "gn:timezone":"America/Hermosillo",
    "iso:country":"MX",
    "wof:name":"Campo Cinco",
    "wof:placetype":"locality"
},
  "geometry": {"coordinates":[-108.88333,30.73333],"type":"Point"}
}