{
  "type": "Feature",
  "properties": {
    "gn:admin1_code":"1",
    "gn:admin2_code":"1",
    "gn:asciiname":"El Caracol (La Mesa)",
    "gn:country_code":"MX",
    "gn:dem":2008,
    "gn:feature_class":"P",
    "gn:feature_code":"PPL",
    "gn:name":"El Caracol (La Mesa)",
    "gn:population":22,
    "gn:timezone":"America/Mexico_City",
    "iso:country":"MX",
    "wof:name":"El Caracol (La Mesa)",
    "wof:placetype":"locality",
    "wof:population":22
},
  "geometry": {"coordinates":[-102.17722000000001,21.82361],"type":"Point"}
}