{
  "type": "Feature",
  "properties": {
    "gn:admin1_code":"20",
    "gn:admin2_code":"248",
    "gn:asciiname":"Deor Pin (Lodo Blanco)",
    "gn:country_code":"MX",
    "gn:dem":9,
    "gn:feature_class":"P",
    "gn:feature_code":"PPL",
    "gn:name":"Deor Pin (Lodo Blanco)",
    "gn:population":27,
    "gn:timezone":"America/Mexico_City",
    "iso:country":"MX",
    "wof:name":"Deor Pin (Lodo Blanco)",
    "wof:placetype":"locality",
    "wof:population":27
},
  "geometry": {"coordinates":[-94.99167,16.21667],"type":"Point"}
}