{
  "type": "Feature",
  "properties": {
    "gn:admin1_code":"14",
    "gn:admin2_code":"111",
    "gn:asciiname":"Medina [Granja]",
    "gn:country_code":"MX",
    "gn:dem":1845,
    "gn:feature_class":"P",
    "gn:feature_code":"PPL",
    "gn:name":"Medina [Granja]",
    "gn:population":10,
    "gn:timezone":"America/Mexico_City",
    "iso:country":"MX",
    "wof:name":"Medina [Granja]",
    "wof:placetype":"locality",
    "wof:population":10
},
  "geometry": {"coordinates":[-102.58722,21.05639],"type":"Point"}
}