{
  "type": "Feature",
  "properties": {
    "gn:admin1_code":"26",
    "gn:admin2_code":"30",
    "gn:asciiname":"El Quetzal (El Cholay)",
    "gn:country_code":"MX",
    "gn:dem":37,
    "gn:feature_class":"P",
    "gn:feature_code":"PPL",
    "gn:name":"El Quetzal (El Cholay)",
    "gn:population":10,
    "gn:timezone":"America/Hermosillo",
    "iso:country":"MX",
    "wof:name":"El Quetzal (El Cholay)",
    "wof:placetype":"locality",
    "wof:population":10
},
  "geometry": {"coordinates":[-111.35556,28.56472],"type":"Point"}
}