{
  "type": "Feature",
  "properties": {
    "gn:admin1_code":"12.0",
    "gn:admin2_code":"38.0",
    "gn:asciiname":"Las Higueritas",
    "gn:country_code":"MX",
    "gn:dem":278,
    "gn:feature_class":"P",
    "gn:feature_code":"PPL",
    "gn:name":"Las Higueritas",
    "gn:population":58,
    "gn:timezone":"America/Mexico_City",
    "iso:country":"MX",
    "name:spa_x_preferred":[
        "Las Higueritas"
    ],
    "wof:name":"Las Higueritas",
    "wof:placetype":"locality",
    "wof:population":58
},
  "geometry": {"coordinates":[-101.41551,17.81417],"type":"Point"}
}