{
  "type": "Feature",
  "properties": {
    "gn:admin1_code":"5",
    "gn:admin2_code":"77.0",
    "gn:asciiname":"San Agustin",
    "gn:country_code":"MX",
    "gn:dem":697,
    "gn:feature_class":"P",
    "gn:feature_code":"PPL",
    "gn:name":"San Agust\u00edn",
    "gn:population":296,
    "gn:timezone":"America/Mexico_City",
    "iso:country":"MX",
    "name:und_x_variant":[
        "San Agust\u00edn"
    ],
    "wof:name":"San Agustin",
    "wof:placetype":"locality",
    "wof:population":296
},
  "geometry": {"coordinates":[-92.11722,17.42944],"type":"Point"}
}