{
  "type": "Feature",
  "properties": {
    "gn:admin1_code":"24",
    "gn:admin2_code":"55.0",
    "gn:asciiname":"Rincon de Santa Eduwiges",
    "gn:country_code":"MX",
    "gn:dem":2140,
    "gn:feature_class":"P",
    "gn:feature_code":"PPL",
    "gn:name":"Rinc\u00f3n de Santa Eduwiges",
    "gn:population":110,
    "gn:timezone":"America/Mexico_City",
    "iso:country":"MX",
    "name:und_x_variant":[
        "Rinc\u00f3n de Santa Eduwiges"
    ],
    "wof:name":"Rincon de Santa Eduwiges",
    "wof:placetype":"locality",
    "wof:population":110
},
  "geometry": {"coordinates":[-100.6875,22.07194],"type":"Point"}
}