{
  "type": "Feature",
  "properties": {
    "gn:admin1_code":"32.0",
    "gn:admin2_code":"49.0",
    "gn:asciiname":"Los Conejos",
    "gn:country_code":"MX",
    "gn:dem":1938,
    "gn:feature_class":"P",
    "gn:feature_code":"PPL",
    "gn:name":"Los Conejos",
    "gn:population":0,
    "gn:timezone":"America/Mexico_City",
    "iso:country":"MX",
    "name:spa_x_preferred":[
        "Los Conejos"
    ],
    "wof:name":"Los Conejos",
    "wof:placetype":"locality"
},
  "geometry": {"coordinates":[-103.5881,22.75202],"type":"Point"}
}