{
  "type": "Feature",
  "properties": {
    "gn:admin1_code":"27",
    "gn:admin2_code":"12.0",
    "gn:asciiname":"El Pinacal",
    "gn:country_code":"MX",
    "gn:dem":2,
    "gn:feature_class":"P",
    "gn:feature_code":"PPL",
    "gn:name":"El Pinacal",
    "gn:population":0,
    "gn:timezone":"America/Mexico_City",
    "iso:country":"MX",
    "name:spa_x_preferred":[
        "El Pinal"
    ],
    "name:spa_x_variant":[
        "El Pinacal"
    ],
    "wof:name":"El Pinacal",
    "wof:placetype":"locality"
},
  "geometry": {"coordinates":[-92.40081000000001,17.99007000000001],"type":"Point"}
}