{
  "type": "Feature",
  "properties": {
    "gn:admin1_code":"5",
    "gn:admin2_code":"89.0",
    "gn:asciiname":"Nueva Reforma",
    "gn:cc2":"MX",
    "gn:country_code":"MX",
    "gn:dem":457,
    "gn:feature_class":"P",
    "gn:feature_code":"PPL",
    "gn:name":"Nueva Reforma",
    "gn:population":68,
    "gn:timezone":"America/Mexico_City",
    "iso:country":"MX",
    "name:und_x_variant":[
        "Reforma",
        "La Reforma"
    ],
    "wof:name":"Nueva Reforma",
    "wof:placetype":"locality",
    "wof:population":68
},
  "geometry": {"coordinates":[-92.32389000000001,15.08528],"type":"Point"}
}