{
  "type": "Feature",
  "properties": {
    "gn:admin1_code":"20",
    "gn:admin2_code":"266",
    "gn:asciiname":"El Mamey",
    "gn:country_code":"MX",
    "gn:dem":543,
    "gn:feature_class":"P",
    "gn:feature_code":"PPL",
    "gn:name":"El Mamey",
    "gn:population":14,
    "gn:timezone":"America/Mexico_City",
    "iso:country":"MX",
    "wof:name":"El Mamey",
    "wof:placetype":"locality",
    "wof:population":14
},
  "geometry": {"coordinates":[-96.09056,15.98278],"type":"Point"}
}