{
  "type": "Feature",
  "properties": {
    "gn:admin1_code":"14",
    "gn:admin2_code":"48",
    "gn:asciiname":"El Regladero",
    "gn:country_code":"MX",
    "gn:dem":2214,
    "gn:feature_class":"P",
    "gn:feature_code":"PPL",
    "gn:name":"El Regladero",
    "gn:population":17,
    "gn:timezone":"America/Mexico_City",
    "iso:country":"MX",
    "wof:name":"El Regladero",
    "wof:placetype":"locality",
    "wof:population":17
},
  "geometry": {"coordinates":[-102.13527999999999,20.6925],"type":"Point"}
}