{
  "type": "Feature",
  "properties": {
    "gn:admin1_code":"1",
    "gn:admin2_code":"10.0",
    "gn:asciiname":"Los Aguilares",
    "gn:country_code":"MX",
    "gn:dem":2008,
    "gn:feature_class":"P",
    "gn:feature_code":"PPL",
    "gn:name":"Los Aguilares",
    "gn:population":0,
    "gn:timezone":"America/Mexico_City",
    "iso:country":"MX",
    "name:und_x_variant":[
        "Aguilares",
        "Los Aguilares"
    ],
    "wof:name":"Los Aguilares",
    "wof:placetype":"locality"
},
  "geometry": {"coordinates":[-102.11642999999999,21.84051],"type":"Point"}
}