{
  "type": "Feature",
  "properties": {
    "gn:admin1_code":"14",
    "gn:admin2_code":"15.0",
    "gn:asciiname":"La Limonera",
    "gn:country_code":"MX",
    "gn:dem":888,
    "gn:feature_class":"P",
    "gn:feature_code":"PPL",
    "gn:name":"La Limonera",
    "gn:population":9,
    "gn:timezone":"America/Mexico_City",
    "iso:country":"MX",
    "wof:name":"La Limonera",
    "wof:placetype":"locality",
    "wof:population":9
},
  "geometry": {"coordinates":[-104.31444,19.7675],"type":"Point"}
}