{
  "type": "Feature",
  "properties": {
    "gn:admin1_code":"16",
    "gn:admin2_code":"49.0",
    "gn:asciiname":"Talmito (El Maguey)",
    "gn:country_code":"MX",
    "gn:dem":1068,
    "gn:feature_class":"P",
    "gn:feature_code":"PPL",
    "gn:name":"Talmito (El Maguey)",
    "gn:population":7,
    "gn:timezone":"America/Mexico_City",
    "iso:country":"MX",
    "wof:name":"Talmito (El Maguey)",
    "wof:placetype":"locality",
    "wof:population":7
},
  "geometry": {"coordinates":[-101.05249999999999,19.19444],"type":"Point"}
}