{
  "type": "Feature",
  "properties": {
    "gn:admin1_code":"16.0",
    "gn:admin2_code":"33.0",
    "gn:asciiname":"El Cobano",
    "gn:country_code":"MX",
    "gn:dem":573,
    "gn:feature_class":"P",
    "gn:feature_code":"PPL",
    "gn:name":"El C\u00f3bano",
    "gn:population":0,
    "gn:timezone":"America/Mexico_City",
    "iso:country":"MX",
    "name:spa_x_preferred":[
        "El C\u00f3bano"
    ],
    "wof:name":"El Cobano",
    "wof:placetype":"locality"
},
  "geometry": {"coordinates":[-102.00985,19.16093],"type":"Point"}
}