{
  "type": "Feature",
  "properties": {
    "gn:admin1_code":"30",
    "gn:admin2_code":"170.0",
    "gn:asciiname":"Amaxac",
    "gn:country_code":"MX",
    "gn:dem":1092,
    "gn:feature_class":"P",
    "gn:feature_code":"PPL",
    "gn:name":"Amaxac",
    "gn:population":0,
    "gn:timezone":"America/Mexico_City",
    "iso:country":"MX",
    "name:und_x_variant":[
        "Amaj\u00e1c",
        "Amaxac"
    ],
    "wof:name":"Amaxac",
    "wof:placetype":"locality"
},
  "geometry": {"coordinates":[-98.26391,20.61939],"type":"Point"}
}