{
  "type": "Feature",
  "properties": {
    "gn:admin1_code":"15.0",
    "gn:asciiname":"La Raya",
    "gn:country_code":"MX",
    "gn:dem":1950,
    "gn:feature_class":"P",
    "gn:feature_code":"PPL",
    "gn:name":"La Raya",
    "gn:population":0,
    "gn:timezone":"America/Mexico_City",
    "iso:country":"MX",
    "name:spa_x_preferred":[
        "La Raya"
    ],
    "wof:name":"La Raya",
    "wof:placetype":"locality"
},
  "geometry": {"coordinates":[-102.64545,19.87822],"type":"Point"}
}