{
  "type": "Feature",
  "properties": {
    "gn:admin1_code":"14",
    "gn:admin2_code":"74",
    "gn:asciiname":"Bernabela",
    "gn:country_code":"MX",
    "gn:dem":2051,
    "gn:feature_class":"P",
    "gn:feature_code":"PPL",
    "gn:name":"Bernabela",
    "gn:population":15,
    "gn:timezone":"America/Mexico_City",
    "iso:country":"MX",
    "wof:name":"Bernabela",
    "wof:placetype":"locality",
    "wof:population":15
},
  "geometry": {"coordinates":[-102.11750000000001,20.99361],"type":"Point"}
}