{
  "type": "Feature",
  "properties": {
    "gn:admin1_code":"28.0",
    "gn:admin2_code":"13.0",
    "gn:asciiname":"El Ecuanil",
    "gn:country_code":"MX",
    "gn:dem":183,
    "gn:feature_class":"P",
    "gn:feature_code":"PPL",
    "gn:name":"El Ecuanil",
    "gn:population":0,
    "gn:timezone":"America/Monterrey",
    "iso:country":"MX",
    "name:spa_x_preferred":[
        "El Ecuanil"
    ],
    "wof:name":"El Ecuanil",
    "wof:placetype":"locality"
},
  "geometry": {"coordinates":[-99.04461999999999,23.89445],"type":"Point"}
}