{
  "type": "Feature",
  "properties": {
    "gn:admin1_code":"5.0",
    "gn:admin2_code":"86.0",
    "gn:asciiname":"El Pitutal",
    "gn:country_code":"MX",
    "gn:dem":826,
    "gn:feature_class":"P",
    "gn:feature_code":"PPL",
    "gn:name":"El Pitutal",
    "gn:population":0,
    "gn:timezone":"America/Mexico_City",
    "iso:country":"MX",
    "name:spa_x_preferred":[
        "El Pitutal"
    ],
    "wof:name":"El Pitutal",
    "wof:placetype":"locality"
},
  "geometry": {"coordinates":[-93.18001,16.59017],"type":"Point"}
}