{
  "type": "Feature",
  "properties": {
    "gn:admin1_code":"20",
    "gn:admin2_code":"5.0",
    "gn:asciiname":"La Purisima",
    "gn:country_code":"MX",
    "gn:dem":34,
    "gn:feature_class":"P",
    "gn:feature_code":"PPL",
    "gn:name":"La Pur\u00edsima",
    "gn:population":5,
    "gn:timezone":"America/Mexico_City",
    "iso:country":"MX",
    "name:und_x_variant":[
        "La Pur\u00edsima"
    ],
    "wof:name":"La Purisima",
    "wof:placetype":"locality",
    "wof:population":5
},
  "geometry": {"coordinates":[-95.08694,16.48082999999999],"type":"Point"}
}