{
  "type": "Feature",
  "properties": {
    "gn:admin1_code":"16.0",
    "gn:admin2_code":"35.0",
    "gn:asciiname":"El Terrerito de Zicuiran",
    "gn:country_code":"MX",
    "gn:dem":199,
    "gn:feature_class":"P",
    "gn:feature_code":"PPL",
    "gn:name":"El Terrerito de Zicuir\u00e1n",
    "gn:population":0,
    "gn:timezone":"America/Mexico_City",
    "iso:country":"MX",
    "name:spa_x_preferred":[
        "El Terrerito de Zicuir\u00e1n"
    ],
    "wof:name":"El Terrerito de Zicuiran",
    "wof:placetype":"locality"
},
  "geometry": {"coordinates":[-101.98334,18.88475],"type":"Point"}
}