{
  "type": "Feature",
  "properties": {
    "gn:admin1_code":"26",
    "gn:admin2_code":"63.0",
    "gn:asciiname":"Cieneguilla",
    "gn:country_code":"MX",
    "gn:dem":772,
    "gn:feature_class":"P",
    "gn:feature_code":"PPL",
    "gn:name":"Cieneguilla",
    "gn:population":0,
    "gn:timezone":"America/Hermosillo",
    "iso:country":"MX",
    "name:spa_x_preferred":[
        "Cieneguilla"
    ],
    "wof:name":"Cieneguilla",
    "wof:placetype":"locality"
},
  "geometry": {"coordinates":[-109.40557,29.52048],"type":"Point"}
}