{
  "type": "Feature",
  "properties": {
    "gn:admin1_code":"9",
    "gn:admin2_code":"12.0",
    "gn:asciiname":"Los Tlapancos",
    "gn:country_code":"MX",
    "gn:dem":2872,
    "gn:feature_class":"P",
    "gn:feature_code":"PPL",
    "gn:name":"Los Tlapancos",
    "gn:population":79,
    "gn:timezone":"America/Mexico_City",
    "iso:country":"MX",
    "wof:name":"Los Tlapancos",
    "wof:placetype":"locality",
    "wof:population":79
},
  "geometry": {"coordinates":[-99.19167,19.20472],"type":"Point"}
}