{
  "type": "Feature",
  "properties": {
    "gn:admin1_code":"14",
    "gn:admin2_code":"27",
    "gn:asciiname":"Llano de Guatelcruz",
    "gn:country_code":"MX",
    "gn:dem":945,
    "gn:feature_class":"P",
    "gn:feature_code":"PPL",
    "gn:name":"Llano de Guatelcruz",
    "gn:population":17,
    "gn:timezone":"America/Mexico_City",
    "iso:country":"MX",
    "wof:name":"Llano de Guatelcruz",
    "wof:placetype":"locality",
    "wof:population":17
},
  "geometry": {"coordinates":[-104.15111,19.465],"type":"Point"}
}