{
  "type": "Feature",
  "properties": {
    "gn:admin1_code":"12",
    "gn:admin2_code":"11",
    "gn:asciiname":"El Estudio",
    "gn:country_code":"MX",
    "gn:dem":944,
    "gn:feature_class":"P",
    "gn:feature_code":"PPL",
    "gn:name":"El Estudio",
    "gn:population":12,
    "gn:timezone":"America/Mexico_City",
    "iso:country":"MX",
    "wof:name":"El Estudio",
    "wof:placetype":"locality",
    "wof:population":12
},
  "geometry": {"coordinates":[-100.25297999999999,17.29834],"type":"Point"}
}