{
  "type": "Feature",
  "properties": {
    "gn:admin1_code":"26.0",
    "gn:admin2_code":"27.0",
    "gn:asciiname":"Magallanes",
    "gn:country_code":"MX",
    "gn:dem":1388,
    "gn:feature_class":"P",
    "gn:feature_code":"PPL",
    "gn:name":"Magallanes",
    "gn:population":0,
    "gn:timezone":"America/Hermosillo",
    "iso:country":"MX",
    "name:spa_x_preferred":[
        "Magallanes"
    ],
    "wof:name":"Magallanes",
    "wof:placetype":"locality"
},
  "geometry": {"coordinates":[-109.75229,31.06343],"type":"Point"}
}