{
  "type": "Feature",
  "properties": {
    "gn:admin1_code":"6",
    "gn:admin2_code":"11.0",
    "gn:asciiname":"La Tinaja",
    "gn:country_code":"MX",
    "gn:dem":1432,
    "gn:feature_class":"P",
    "gn:feature_code":"PPL",
    "gn:name":"La Tinaja",
    "gn:population":0,
    "gn:timezone":"America/Chihuahua",
    "iso:country":"MX",
    "name:spa_x_preferred":[
        "La Tinaja"
    ],
    "name:und_x_variant":[
        "Rancho La Tinaja"
    ],
    "wof:name":"La Tinaja",
    "wof:placetype":"locality"
},
  "geometry": {"coordinates":[-104.9404,27.74052],"type":"Point"}
}