{
  "type": "Feature",
  "properties": {
    "gn:admin1_code":"14.0",
    "gn:admin2_code":"90.0",
    "gn:asciiname":"El Bordo",
    "gn:country_code":"MX",
    "gn:dem":1511,
    "gn:feature_class":"P",
    "gn:feature_code":"PPL",
    "gn:name":"El Bordo",
    "gn:population":0,
    "gn:timezone":"America/Mexico_City",
    "iso:country":"MX",
    "name:spa_x_preferred":[
        "El Bordo"
    ],
    "wof:name":"El Bordo",
    "wof:placetype":"locality"
},
  "geometry": {"coordinates":[-104.24558,20.17892],"type":"Point"}
}