{
  "type": "Feature",
  "properties": {
    "gn:admin1_code":"11",
    "gn:admin2_code":"17",
    "gn:asciiname":"Residencial Capilla Mendoza",
    "gn:country_code":"MX",
    "gn:dem":1724,
    "gn:feature_class":"P",
    "gn:feature_code":"PPL",
    "gn:name":"Residencial Capilla Mendoza",
    "gn:population":13,
    "gn:timezone":"America/Mexico_City",
    "iso:country":"MX",
    "wof:name":"Residencial Capilla Mendoza",
    "wof:placetype":"locality",
    "wof:population":13
},
  "geometry": {"coordinates":[-101.38972,20.67972],"type":"Point"}
}