{
  "type": "Feature",
  "properties": {
    "gn:admin1_code":"15.0",
    "gn:admin2_code":"123.0",
    "gn:asciiname":"Rincon de San Lucas",
    "gn:country_code":"MX",
    "gn:dem":1287,
    "gn:feature_class":"P",
    "gn:feature_code":"PPL",
    "gn:name":"Rinc\u00f3n de San Lucas",
    "gn:population":142,
    "gn:timezone":"America/Mexico_City",
    "iso:country":"MX",
    "name:und_x_variant":[
        "Rinc\u00f3n de San Lucas",
        "El Rinc\u00f3n",
        "Rinc\u00f3n de S\u00e1nchez"
    ],
    "wof:name":"Rincon de San Lucas",
    "wof:placetype":"locality",
    "wof:population":142
},
  "geometry": {"coordinates":[-100.24366999999999,18.96691],"type":"Point"}
}