{
  "type": "Feature",
  "properties": {
    "gn:admin1_code":"32",
    "gn:admin2_code":"28.0",
    "gn:asciiname":"Presa del Zapote",
    "gn:country_code":"MX",
    "gn:dem":1381,
    "gn:feature_class":"P",
    "gn:feature_code":"PPL",
    "gn:name":"Presa del Zapote",
    "gn:population":59,
    "gn:timezone":"America/Mexico_City",
    "iso:country":"MX",
    "wof:name":"Presa del Zapote",
    "wof:placetype":"locality",
    "wof:population":59
},
  "geometry": {"coordinates":[-103.32861,21.24722],"type":"Point"}
}