{
  "type": "Feature",
  "properties": {
    "gn:admin1_code":"28",
    "gn:admin2_code":"33.0",
    "gn:asciiname":"El Moro (Rosalio Vega Perez)",
    "gn:country_code":"MX",
    "gn:dem":30,
    "gn:feature_class":"P",
    "gn:feature_code":"PPL",
    "gn:name":"El Moro (Rosal\u00edo Vega P\u00e9rez)",
    "gn:population":6,
    "gn:timezone":"America/Monterrey",
    "iso:country":"MX",
    "name:und_x_variant":[
        "El Moro (Rosal\u00edo Vega P\u00e9rez)"
    ],
    "wof:name":"El Moro (Rosalio Vega Perez)",
    "wof:placetype":"locality",
    "wof:population":6
},
  "geometry": {"coordinates":[-98.11917,25.82833],"type":"Point"}
}