{
  "type": "Feature",
  "properties": {
    "gn:admin1_code":"5",
    "gn:admin2_code":"27",
    "gn:asciiname":"Humboldt",
    "gn:country_code":"MX",
    "gn:dem":416,
    "gn:feature_class":"P",
    "gn:feature_code":"PPL",
    "gn:name":"Humboldt",
    "gn:population":10,
    "gn:timezone":"America/Mexico_City",
    "iso:country":"MX",
    "wof:name":"Humboldt",
    "wof:placetype":"locality",
    "wof:population":10
},
  "geometry": {"coordinates":[-93.00528,16.58861],"type":"Point"}
}