{
  "type": "Feature",
  "properties": {
    "gn:admin1_code":"5",
    "gn:admin2_code":"27",
    "gn:asciiname":"Humboldt",
    "gn:country_code":"MX",
    "gn:dem":416,
    "gn:feature_class":"P",
    "gn:feature_code":"PPL",
    "gn:name":"Humboldt",
    "gn:population":10,
    "gn:timezone":"America/Mexico_City",
    "iso:country":"MX",
    "name:als_x_preferred":[
        "Humboldt"
    ],
    "name:bul_x_preferred":[
        "\u0425\u0443\u043c\u0431\u043e\u043b\u0442"
    ],
    "name:cat_x_preferred":[
        "Humboldt"
    ],
    "name:ceb_x_preferred":[
        "Humboldt"
    ],
    "name:ces_x_preferred":[
        "Humboldt"
    ],
    "name:deu_x_preferred":[
        "Humboldt"
    ],
    "name:eus_x_preferred":[
        "Humboldt"
    ],
    "name:fas_x_preferred":[
        "\u0647\u0648\u0645\u0628\u0648\u0644\u062a"
    ],
    "name:fin_x_preferred":[
        "Humboldt"
    ],
    "name:fra_x_preferred":[
        "Humboldt"
    ],
    "name:heb_x_preferred":[
        "\u05d4\u05d5\u05de\u05d1\u05d5\u05dc\u05d3\u05d8"
    ],
    "name:hun_x_preferred":[
        "Humboldt"
    ],
    "name:ita_x_preferred":[
        "Humboldt"
    ],
    "name:jpn_x_preferred":[
        "\u30d5\u30f3\u30dc\u30eb\u30c8"
    ],
    "name:kat_x_preferred":[
        "\u10f0\u10e3\u10db\u10d1\u10dd\u10da\u10d3\u10e2\u10d8"
    ],
    "name:kor_x_preferred":[
        "\ud6d4\ubcfc\ud2b8"
    ],
    "name:lav_x_preferred":[
        "Humbolts"
    ],
    "name:nld_x_preferred":[
        "Humboldt"
    ],
    "name:nor_x_preferred":[
        "Humboldt"
    ],
    "name:pol_x_preferred":[
        "Humboldt"
    ],
    "name:por_x_preferred":[
        "Humboldt"
    ],
    "name:que_x_preferred":[
        "Humboldt"
    ],
    "name:ron_x_preferred":[
        "Humboldt"
    ],
    "name:rus_x_preferred":[
        "\u0413\u0443\u043c\u0431\u043e\u043b\u044c\u0434\u0442"
    ],
    "name:slv_x_preferred":[
        "Humboldt"
    ],
    "name:spa_x_preferred":[
        "Humboldt"
    ],
    "name:srp_x_preferred":[
        "\u0425\u0443\u043c\u0431\u043e\u043b\u0442"
    ],
    "name:swe_x_preferred":[
        "Humboldt"
    ],
    "name:tat_x_preferred":[
        "\u04ba\u0443\u043c\u0431\u043e\u043b\u044c\u0434\u0442"
    ],
    "name:tur_x_preferred":[
        "Humboldt"
    ],
    "name:ukr_x_preferred":[
        "\u0413\u0443\u043c\u0431\u043e\u043b\u044c\u0442"
    ],
    "name:ukr_x_variant":[
        "\u0413\u0443\u043c\u0431\u043e\u043b\u044c\u0434\u0442"
    ],
    "name:vie_x_preferred":[
        "S\u00f4ng Humboldt"
    ],
    "name:vol_x_preferred":[
        "Humboldt"
    ],
    "wof:name":"Humboldt",
    "wof:placetype":"locality",
    "wof:population":10
},
  "geometry": {"coordinates":[-93.00528,16.58861],"type":"Point"}
}