{
  "type": "Feature",
  "properties": {
    "gn:admin1_code":"16",
    "gn:admin2_code":"99",
    "gn:asciiname":"La Calera",
    "gn:country_code":"MX",
    "gn:dem":1560,
    "gn:feature_class":"P",
    "gn:feature_code":"PPL",
    "gn:name":"La Calera",
    "gn:population":17,
    "gn:timezone":"America/Mexico_City",
    "iso:country":"MX",
    "wof:name":"La Calera",
    "wof:placetype":"locality",
    "wof:population":17
},
  "geometry": {"coordinates":[-100.67972,19.34056],"type":"Point"}
}