{
  "type": "Feature",
  "properties": {
    "gn:admin1_code":"5.0",
    "gn:asciiname":"Tunalito el Recuerdo",
    "gn:country_code":"MX",
    "gn:dem":1548,
    "gn:feature_class":"P",
    "gn:feature_code":"PPL",
    "gn:name":"Tunalito el Recuerdo",
    "gn:population":0,
    "gn:timezone":"America/Mexico_City",
    "iso:country":"MX",
    "name:spa_x_preferred":[
        "Tunalito el Recuerdo"
    ],
    "wof:name":"Tunalito el Recuerdo",
    "wof:placetype":"locality"
},
  "geometry": {"coordinates":[-92.06601000000001,16.22395],"type":"Point"}
}