{
  "type": "Feature",
  "properties": {
    "gn:admin1_code":"30",
    "gn:admin2_code":"43.0",
    "gn:asciiname":"Lagunilla",
    "gn:country_code":"MX",
    "gn:dem":480,
    "gn:feature_class":"P",
    "gn:feature_code":"PPL",
    "gn:name":"Lagunilla",
    "gn:population":0,
    "gn:timezone":"America/Mexico_City",
    "iso:country":"MX",
    "name:spa_x_preferred":[
        "Lagunilla"
    ],
    "wof:name":"Lagunilla",
    "wof:placetype":"locality"
},
  "geometry": {"coordinates":[-96.6751,19.0996],"type":"Point"}
}