{
  "type": "Feature",
  "properties": {
    "gn:admin1_code":"24",
    "gn:admin2_code":"57.0",
    "gn:asciiname":"Papatlas",
    "gn:country_code":"MX",
    "gn:dem":128,
    "gn:feature_class":"P",
    "gn:feature_code":"PPL",
    "gn:name":"Papatlas",
    "gn:population":523,
    "gn:timezone":"America/Mexico_City",
    "iso:country":"MX",
    "wof:name":"Papatlas",
    "wof:placetype":"locality",
    "wof:population":523
},
  "geometry": {"coordinates":[-98.79861,21.36667000000001],"type":"Point"}
}