{
  "type": "Feature",
  "properties": {
    "gn:admin1_code":"20",
    "gn:admin2_code":"307.0",
    "gn:asciiname":"San Francisco de Asis",
    "gn:country_code":"MX",
    "gn:dem":333,
    "gn:feature_class":"P",
    "gn:feature_code":"PPL",
    "gn:name":"San Francisco de As\u00eds",
    "gn:population":85,
    "gn:timezone":"America/Mexico_City",
    "iso:country":"MX",
    "name:spa_x_preferred":[
        "San Francisco"
    ],
    "wof:name":"San Francisco de Asis",
    "wof:placetype":"locality",
    "wof:population":85
},
  "geometry": {"coordinates":[-95.62018999999999,16.101],"type":"Point"}
}