{
  "type": "Feature",
  "properties": {
    "gn:admin1_code":"4.0",
    "gn:asciiname":"Las Avestruces",
    "gn:country_code":"MX",
    "gn:dem":5,
    "gn:feature_class":"P",
    "gn:feature_code":"PPL",
    "gn:name":"Las Avestruces",
    "gn:population":0,
    "gn:timezone":"America/Merida",
    "iso:country":"MX",
    "name:spa_x_preferred":[
        "Las Avestruces"
    ],
    "wof:name":"Las Avestruces",
    "wof:placetype":"locality"
},
  "geometry": {"coordinates":[-90.53975,19.74444],"type":"Point"}
}