{
  "type": "Feature",
  "properties": {
    "gn:admin1_code":"14",
    "gn:admin2_code":"125.0",
    "gn:asciiname":"San Nicolas",
    "gn:country_code":"MX",
    "gn:dem":2009,
    "gn:feature_class":"P",
    "gn:feature_code":"PPL",
    "gn:name":"San Nicol\u00e1s",
    "gn:population":179,
    "gn:timezone":"America/Mexico_City",
    "iso:country":"MX",
    "name:und_x_variant":[
        "San Nicol\u00e1s"
    ],
    "wof:name":"San Nicolas",
    "wof:placetype":"locality",
    "wof:population":179
},
  "geometry": {"coordinates":[-102.49583,20.70361],"type":"Point"}
}