{
  "type": "Feature",
  "properties": {
    "gn:admin1_code":"32",
    "gn:admin2_code":"36",
    "gn:asciiname":"Jacarandas",
    "gn:country_code":"MX",
    "gn:dem":2065,
    "gn:feature_class":"P",
    "gn:feature_code":"PPL",
    "gn:name":"Jacarandas",
    "gn:population":11,
    "gn:timezone":"America/Mexico_City",
    "iso:country":"MX",
    "wof:name":"Jacarandas",
    "wof:placetype":"locality",
    "wof:population":11
},
  "geometry": {"coordinates":[-102.2475,22.58889],"type":"Point"}
}