{
  "type": "Feature",
  "properties": {
    "gn:admin1_code":"32",
    "gn:admin2_code":"10.0",
    "gn:asciiname":"Colonia Santa Anita",
    "gn:country_code":"MX",
    "gn:dem":2060,
    "gn:feature_class":"P",
    "gn:feature_code":"PPL",
    "gn:name":"Colonia Santa Anita",
    "gn:population":518,
    "gn:timezone":"America/Mexico_City",
    "iso:country":"MX",
    "wof:name":"Colonia Santa Anita",
    "wof:placetype":"locality",
    "wof:population":518
},
  "geometry": {"coordinates":[-102.76721999999999,23.22861],"type":"Point"}
}