{
  "type": "Feature",
  "properties": {
    "gn:admin1_code":"12.0",
    "gn:admin2_code":"27.0",
    "gn:asciiname":"La Cienega",
    "gn:country_code":"MX",
    "gn:dem":1203,
    "gn:feature_class":"P",
    "gn:feature_code":"PPL",
    "gn:name":"La Ci\u00e9nega",
    "gn:population":0,
    "gn:timezone":"America/Mexico_City",
    "iso:country":"MX",
    "name:ceb_x_preferred":[
        "La Cienega"
    ],
    "name:spa_x_preferred":[
        "La Ci\u00e9nega"
    ],
    "name:swe_x_preferred":[
        "La Cienega"
    ],
    "wof:name":"La Cienega",
    "wof:placetype":"locality"
},
  "geometry": {"coordinates":[-100.46977,18.69724],"type":"Point"}
}