{
  "type": "Feature",
  "properties": {
    "gn:admin1_code":"29",
    "gn:admin2_code":"34.0",
    "gn:asciiname":"Profesor Graciano Sanchez",
    "gn:country_code":"MX",
    "gn:dem":2914,
    "gn:feature_class":"P",
    "gn:feature_code":"PPL",
    "gn:name":"Profesor Graciano S\u00e1nchez",
    "gn:population":0,
    "gn:timezone":"America/Mexico_City",
    "iso:country":"MX",
    "name:spa_x_preferred":[
        "Profesor Graciano S\u00e1nchez"
    ],
    "name:und_x_variant":[
        "Graciano S\u00e1nchez"
    ],
    "wof:name":"Profesor Graciano Sanchez",
    "wof:placetype":"locality"
},
  "geometry": {"coordinates":[-98.3141,19.71057],"type":"Point"}
}