{
  "type": "Feature",
  "properties": {
    "gn:admin1_code":"15.0",
    "gn:admin2_code":"77.0",
    "gn:asciiname":"Cerro del Momoxtle",
    "gn:country_code":"MX",
    "gn:dem":1893,
    "gn:feature_class":"P",
    "gn:feature_code":"PPL",
    "gn:name":"Cerro del Momoxtle",
    "gn:population":0,
    "gn:timezone":"America/Mexico_City",
    "iso:country":"MX",
    "name:spa_x_preferred":[
        "Cerro del Momoxtle"
    ],
    "wof:name":"Cerro del Momoxtle",
    "wof:placetype":"locality"
},
  "geometry": {"coordinates":[-100.08671,18.95232],"type":"Point"}
}