{
  "type": "Feature",
  "properties": {
    "gn:admin1_code":"11.0",
    "gn:asciiname":"Rancho Arroyo",
    "gn:country_code":"MX",
    "gn:dem":1725,
    "gn:feature_class":"P",
    "gn:feature_code":"PPL",
    "gn:name":"Rancho Arroyo",
    "gn:population":0,
    "gn:timezone":"America/Mexico_City",
    "iso:country":"MX",
    "name:spa_x_preferred":[
        "Rancho Arroyo"
    ],
    "wof:name":"Rancho Arroyo",
    "wof:placetype":"locality"
},
  "geometry": {"coordinates":[-101.19862000000001,20.41706],"type":"Point"}
}