{
  "type": "Feature",
  "properties": {
    "gn:admin1_code":"20",
    "gn:admin2_code":"283.0",
    "gn:asciiname":"Palo Solo",
    "gn:country_code":"MX",
    "gn:dem":2075,
    "gn:feature_class":"P",
    "gn:feature_code":"PPL",
    "gn:name":"Palo Solo",
    "gn:population":0,
    "gn:timezone":"America/Mexico_City",
    "iso:country":"MX",
    "name:spa_x_preferred":[
        "Palo Solo"
    ],
    "wof:name":"Palo Solo",
    "wof:placetype":"locality"
},
  "geometry": {"coordinates":[-97.26045999999999,17.83577],"type":"Point"}
}