{
  "type": "Feature",
  "properties": {
    "gn:admin1_code":"11.0",
    "gn:admin2_code":"22.0",
    "gn:asciiname":"Cabras de Guadalupe",
    "gn:country_code":"MX",
    "gn:dem":2170,
    "gn:feature_class":"P",
    "gn:feature_code":"PPL",
    "gn:name":"Cabras de Guadalupe",
    "gn:population":0,
    "gn:timezone":"America/Mexico_City",
    "iso:country":"MX",
    "name:spa_x_preferred":[
        "Cabras de Guadalupe"
    ],
    "name:und_x_variant":[
        "Cabras"
    ],
    "wof:name":"Cabras de Guadalupe",
    "wof:placetype":"locality"
},
  "geometry": {"coordinates":[-101.49704,21.45031],"type":"Point"}
}