{
  "type": "Feature",
  "properties": {
    "gn:admin1_code":"18.0",
    "gn:admin2_code":"1.0",
    "gn:asciiname":"Los Morillo",
    "gn:country_code":"MX",
    "gn:dem":52,
    "gn:feature_class":"P",
    "gn:feature_code":"PPL",
    "gn:name":"Los Morillo",
    "gn:population":0,
    "gn:timezone":"America/Mazatlan",
    "iso:country":"MX",
    "name:spa_x_preferred":[
        "Los Morillo"
    ],
    "name:und_x_variant":[
        "Los Murillo"
    ],
    "wof:name":"Los Morillo",
    "wof:placetype":"locality"
},
  "geometry": {"coordinates":[-105.2932,22.45917],"type":"Point"}
}