{
  "type": "Feature",
  "properties": {
    "gn:admin1_code":"6",
    "gn:admin2_code":"11.0",
    "gn:asciiname":"Los Reyes",
    "gn:country_code":"MX",
    "gn:dem":1220,
    "gn:feature_class":"P",
    "gn:feature_code":"PPL",
    "gn:name":"Los Reyes",
    "gn:population":295,
    "gn:timezone":"America/Chihuahua",
    "iso:country":"MX",
    "wof:name":"Los Reyes",
    "wof:placetype":"locality",
    "wof:population":295
},
  "geometry": {"coordinates":[-105.16417,27.73278],"type":"Point"}
}