{
  "type": "Feature",
  "properties": {
    "gn:admin1_code":"6",
    "gn:admin2_code":"11.0",
    "gn:asciiname":"Los Reyes",
    "gn:country_code":"MX",
    "gn:dem":1220,
    "gn:feature_class":"P",
    "gn:feature_code":"PPL",
    "gn:name":"Los Reyes",
    "gn:population":295,
    "gn:timezone":"America/Chihuahua",
    "iso:country":"MX",
    "name:ceb_x_preferred":[
        "Los Reyes"
    ],
    "name:deu_x_preferred":[
        "Los Reyes"
    ],
    "name:epo_x_preferred":[
        "Los Reyes"
    ],
    "name:nds_x_preferred":[
        "Los Reyes"
    ],
    "name:spa_x_preferred":[
        "Los Reyes"
    ],
    "name:swe_x_preferred":[
        "Los Reyes"
    ],
    "wof:name":"Los Reyes",
    "wof:placetype":"locality",
    "wof:population":295
},
  "geometry": {"coordinates":[-105.16417,27.73278],"type":"Point"}
}