{
  "type": "Feature",
  "properties": {
    "gn:admin1_code":"28",
    "gn:admin2_code":"37.0",
    "gn:asciiname":"La Cobra",
    "gn:country_code":"MX",
    "gn:dem":164,
    "gn:feature_class":"P",
    "gn:feature_code":"PPL",
    "gn:name":"La Cobra",
    "gn:population":5,
    "gn:timezone":"America/Monterrey",
    "iso:country":"MX",
    "wof:name":"La Cobra",
    "wof:placetype":"locality",
    "wof:population":5
},
  "geometry": {"coordinates":[-97.93194,23.49194],"type":"Point"}
}