{
  "type": "Feature",
  "properties": {
    "gn:admin1_code":"10",
    "gn:admin2_code":"34.0",
    "gn:asciiname":"Amachane",
    "gn:country_code":"MX",
    "gn:dem":287,
    "gn:feature_class":"P",
    "gn:feature_code":"PPL",
    "gn:name":"Amachane",
    "gn:population":0,
    "gn:timezone":"America/Monterrey",
    "iso:country":"MX",
    "name:spa_x_preferred":[
        "Amachane"
    ],
    "name:und_x_variant":[
        "Amacuable"
    ],
    "wof:name":"Amachane",
    "wof:placetype":"locality"
},
  "geometry": {"coordinates":[-106.89446,25.02222],"type":"Point"}
}