{
  "type": "Feature",
  "properties": {
    "gn:admin1_code":"3",
    "gn:admin2_code":"3.0",
    "gn:asciiname":"Canada la Lena",
    "gn:country_code":"MX",
    "gn:dem":85,
    "gn:feature_class":"P",
    "gn:feature_code":"PPL",
    "gn:name":"Ca\u00f1ada la Le\u00f1a",
    "gn:population":8,
    "gn:timezone":"America/Mazatlan",
    "iso:country":"MX",
    "name:und_x_variant":[
        "Ca\u00f1ada la Le\u00f1a"
    ],
    "wof:name":"Canada la Lena",
    "wof:placetype":"locality",
    "wof:population":8
},
  "geometry": {"coordinates":[-110.23044,24.26749],"type":"Point"}
}