{
  "type": "Feature",
  "properties": {
    "gn:admin1_code":"30",
    "gn:admin2_code":"108",
    "gn:asciiname":"Isla del Paraiso",
    "gn:country_code":"MX",
    "gn:dem":11,
    "gn:feature_class":"P",
    "gn:feature_code":"PPL",
    "gn:name":"Isla del Para\u00edso",
    "gn:population":19,
    "gn:timezone":"America/Mexico_City",
    "iso:country":"MX",
    "name:und_x_variant":[
        "Isla del Para\u00edso"
    ],
    "wof:name":"Isla del Paraiso",
    "wof:placetype":"locality",
    "wof:population":19
},
  "geometry": {"coordinates":[-94.42028000000001,17.84917],"type":"Point"}
}