{
  "type": "Feature",
  "properties": {
    "gn:admin1_code":"30",
    "gn:admin2_code":"137.0",
    "gn:asciiname":"Cuacaballo",
    "gn:country_code":"MX",
    "gn:dem":1404,
    "gn:feature_class":"P",
    "gn:feature_code":"PPL",
    "gn:name":"Cuacaballo",
    "gn:population":379,
    "gn:timezone":"America/Mexico_City",
    "iso:country":"MX",
    "wof:name":"Cuacaballo",
    "wof:placetype":"locality",
    "wof:population":379
},
  "geometry": {"coordinates":[-97.02167,18.68833],"type":"Point"}
}