{
  "type": "Feature",
  "properties": {
    "gn:admin1_code":"10",
    "gn:admin2_code":"5.0",
    "gn:asciiname":"San Ignacio de Loyola",
    "gn:country_code":"MX",
    "gn:dem":1885,
    "gn:feature_class":"P",
    "gn:feature_code":"PPL",
    "gn:name":"San Ignacio de Loyola",
    "gn:population":0,
    "gn:timezone":"America/Monterrey",
    "iso:country":"MX",
    "name:spa_x_preferred":[
        "San Ignacio de Loyola"
    ],
    "name:und_x_variant":[
        "San Ignacio"
    ],
    "wof:name":"San Ignacio de Loyola",
    "wof:placetype":"locality"
},
  "geometry": {"coordinates":[-104.62624,24.06526],"type":"Point"}
}