{
  "type": "Feature",
  "properties": {
    "gn:admin1_code":"30",
    "gn:admin2_code":"94.0",
    "gn:asciiname":"Miguel Hidalgo",
    "gn:country_code":"MX",
    "gn:dem":122,
    "gn:feature_class":"P",
    "gn:feature_code":"PPL",
    "gn:name":"Miguel Hidalgo",
    "gn:population":439,
    "gn:timezone":"America/Mexico_City",
    "iso:country":"MX",
    "wof:name":"Miguel Hidalgo",
    "wof:placetype":"locality",
    "wof:population":439
},
  "geometry": {"coordinates":[-95.46083,17.79917],"type":"Point"}
}