{
  "type": "Feature",
  "properties": {
    "gn:admin1_code":"13",
    "gn:admin2_code":"18",
    "gn:asciiname":"La Joya del Zopilote",
    "gn:country_code":"MX",
    "gn:dem":968,
    "gn:feature_class":"P",
    "gn:feature_code":"PPL",
    "gn:name":"La Joya del Zopilote",
    "gn:population":22,
    "gn:timezone":"America/Mexico_City",
    "iso:country":"MX",
    "wof:name":"La Joya del Zopilote",
    "wof:placetype":"locality",
    "wof:population":22
},
  "geometry": {"coordinates":[-98.93683,21.15015],"type":"Point"}
}