{
  "type": "Feature",
  "properties": {
    "gn:admin1_code":"26",
    "gn:admin2_code":"3.0",
    "gn:asciiname":"El Rincon Viejo",
    "gn:country_code":"MX",
    "gn:dem":442,
    "gn:feature_class":"P",
    "gn:feature_code":"PPL",
    "gn:name":"El Rinc\u00f3n Viejo",
    "gn:population":10,
    "gn:timezone":"America/Hermosillo",
    "iso:country":"MX",
    "name:spa_x_preferred":[
        "El Rinc\u00f3n Viejo"
    ],
    "wof:name":"El Rincon Viejo",
    "wof:placetype":"locality",
    "wof:population":10
},
  "geometry": {"coordinates":[-108.94167,27.0625],"type":"Point"}
}