{
  "type": "Feature",
  "properties": {
    "gn:admin1_code":"13",
    "gn:admin2_code":"47.0",
    "gn:asciiname":"Mixquiahuales",
    "gn:country_code":"MX",
    "gn:dem":1718,
    "gn:feature_class":"P",
    "gn:feature_code":"PPL",
    "gn:name":"Mixquiahuales",
    "gn:population":154,
    "gn:timezone":"America/Mexico_City",
    "iso:country":"MX",
    "name:spa_x_preferred":[
        "Mixquiahuales"
    ],
    "wof:name":"Mixquiahuales",
    "wof:placetype":"locality",
    "wof:population":154
},
  "geometry": {"coordinates":[-99.36111,21.00972],"type":"Point"}
}