{
  "type": "Feature",
  "properties": {
    "gn:admin1_code":"14",
    "gn:admin2_code":"53",
    "gn:asciiname":"Labor de Padilla",
    "gn:country_code":"MX",
    "gn:dem":1895,
    "gn:feature_class":"P",
    "gn:feature_code":"PPL",
    "gn:name":"Labor de Padilla",
    "gn:population":15,
    "gn:timezone":"America/Mexico_City",
    "iso:country":"MX",
    "wof:name":"Labor de Padilla",
    "wof:placetype":"locality",
    "wof:population":15
},
  "geometry": {"coordinates":[-101.87639,21.43194],"type":"Point"}
}