{
  "type": "Feature",
  "properties": {
    "gn:admin1_code":"20",
    "gn:admin2_code":"342",
    "gn:asciiname":"Camino al Tanque II (El Puente)",
    "gn:country_code":"MX",
    "gn:dem":1530,
    "gn:feature_class":"P",
    "gn:feature_code":"PPL",
    "gn:name":"Camino al Tanque II (El Puente)",
    "gn:population":36,
    "gn:timezone":"America/Mexico_City",
    "iso:country":"MX",
    "wof:name":"Camino al Tanque II (El Puente)",
    "wof:placetype":"locality",
    "wof:population":36
},
  "geometry": {"coordinates":[-96.75139,16.97583],"type":"Point"}
}