{
  "type": "Feature",
  "properties": {
    "gn:admin1_code":"30",
    "gn:admin2_code":"40.0",
    "gn:asciiname":"Troncones y Potrerillos",
    "gn:country_code":"MX",
    "gn:dem":76,
    "gn:feature_class":"P",
    "gn:feature_code":"PPL",
    "gn:name":"Troncones y Potrerillos",
    "gn:population":848,
    "gn:timezone":"America/Mexico_City",
    "iso:country":"MX",
    "wof:name":"Troncones y Potrerillos",
    "wof:placetype":"locality",
    "wof:population":848
},
  "geometry": {"coordinates":[-97.47221999999999,20.4775],"type":"Point"}
}