{
  "type": "Feature",
  "properties": {
    "gn:admin1_code":"30",
    "gn:admin2_code":"144",
    "gn:asciiname":"Nuevo Rastro (La Orqueta)",
    "gn:country_code":"MX",
    "gn:dem":77,
    "gn:feature_class":"P",
    "gn:feature_code":"PPL",
    "gn:name":"Nuevo Rastro (La Orqueta)",
    "gn:population":25,
    "gn:timezone":"America/Mexico_City",
    "iso:country":"MX",
    "wof:name":"Nuevo Rastro (La Orqueta)",
    "wof:placetype":"locality",
    "wof:population":25
},
  "geometry": {"coordinates":[-94.95556000000001,17.86972],"type":"Point"}
}