{
  "type": "Feature",
  "properties": {
    "gn:admin1_code":"3.0",
    "gn:admin2_code":"9.0",
    "gn:asciiname":"Rosarito",
    "gn:country_code":"MX",
    "gn:dem":133,
    "gn:feature_class":"P",
    "gn:feature_code":"PPL",
    "gn:name":"Rosarito",
    "gn:population":0,
    "gn:timezone":"America/Mazatlan",
    "iso:country":"MX",
    "name:spa_x_preferred":[
        "Rosarito"
    ],
    "wof:name":"Rosarito",
    "wof:placetype":"locality"
},
  "geometry": {"coordinates":[-111.64843,26.45637],"type":"Point"}
}