{
  "type": "Feature",
  "properties": {
    "gn:admin1_code":"1.0",
    "gn:admin2_code":"3.0",
    "gn:asciiname":"El Llano Blanco",
    "gn:country_code":"MX",
    "gn:dem":2044,
    "gn:feature_class":"P",
    "gn:feature_code":"PPL",
    "gn:name":"El Llano Blanco",
    "gn:population":0,
    "gn:timezone":"America/Mexico_City",
    "iso:country":"MX",
    "wof:name":"El Llano Blanco",
    "wof:placetype":"locality"
},
  "geometry": {"coordinates":[-102.60396,21.75951],"type":"Point"}
}