{
  "type": "Feature",
  "properties": {
    "gn:admin1_code":"28.0",
    "gn:admin2_code":"19.0",
    "gn:asciiname":"El Picacho",
    "gn:country_code":"MX",
    "gn:dem":308,
    "gn:feature_class":"P",
    "gn:feature_code":"PPL",
    "gn:name":"El Picacho",
    "gn:population":4,
    "gn:timezone":"America/Monterrey",
    "iso:country":"MX",
    "name:ceb_x_preferred":[
        "El Picacho"
    ],
    "name:spa_x_preferred":[
        "El Picacho"
    ],
    "name:swe_x_preferred":[
        "El Picacho"
    ],
    "wof:name":"El Picacho",
    "wof:placetype":"locality",
    "wof:population":4
},
  "geometry": {"coordinates":[-99.03167000000001,23.23611],"type":"Point"}
}