{
  "type": "Feature",
  "properties": {
    "gn:admin1_code":"15",
    "gn:admin2_code":"24.0",
    "gn:asciiname":"Fraccion San Roque (El Prieto)",
    "gn:country_code":"MX",
    "gn:dem":2254,
    "gn:feature_class":"P",
    "gn:feature_code":"PPL",
    "gn:name":"Fracci\u00f3n San Roque (El Prieto)",
    "gn:population":1219,
    "gn:timezone":"America/Mexico_City",
    "iso:country":"MX",
    "name:und_x_variant":[
        "Fracci\u00f3n San Roque (El Prieto)"
    ],
    "wof:name":"Fraccion San Roque (El Prieto)",
    "wof:placetype":"locality",
    "wof:population":1219
},
  "geometry": {"coordinates":[-99.17222,19.68722],"type":"Point"}
}