{
  "type": "Feature",
  "properties": {
    "gn:admin1_code":"18.0",
    "gn:admin2_code":"9.0",
    "gn:asciiname":"Dolores Viejo",
    "gn:country_code":"MX",
    "gn:dem":907,
    "gn:feature_class":"P",
    "gn:feature_code":"PPL",
    "gn:name":"Dolores Viejo",
    "gn:population":0,
    "gn:timezone":"America/Mazatlan",
    "iso:country":"MX",
    "name:spa_x_preferred":[
        "Dolores Viejo"
    ],
    "wof:name":"Dolores Viejo",
    "wof:placetype":"locality"
},
  "geometry": {"coordinates":[-104.95723,22.39517],"type":"Point"}
}