{
  "type": "Feature",
  "properties": {
    "gn:admin1_code":"5",
    "gn:admin2_code":"97.0",
    "gn:asciiname":"Miguel Hidalgo Numero Dos (Veinte de Noviembre)",
    "gn:country_code":"MX",
    "gn:dem":8,
    "gn:feature_class":"P",
    "gn:feature_code":"PPL",
    "gn:name":"Miguel Hidalgo N\u00famero Dos (Veinte de Noviembre)",
    "gn:population":678,
    "gn:timezone":"America/Mexico_City",
    "iso:country":"MX",
    "name:und_x_variant":[
        "Miguel Hidalgo N\u00famero Dos (Veinte de Noviembre)"
    ],
    "wof:name":"Miguel Hidalgo Numero Dos (Veinte de Noviembre)",
    "wof:placetype":"locality",
    "wof:population":678
},
  "geometry": {"coordinates":[-93.80972,15.95139],"type":"Point"}
}