{
  "type": "Feature",
  "properties": {
    "gn:admin1_code":"2",
    "gn:admin2_code":"1",
    "gn:asciiname":"Familia Raygoza",
    "gn:country_code":"MX",
    "gn:dem":9,
    "gn:feature_class":"P",
    "gn:feature_code":"PPL",
    "gn:name":"Familia Raygoza",
    "gn:population":9,
    "gn:timezone":"America/Tijuana",
    "iso:country":"MX",
    "wof:name":"Familia Raygoza",
    "wof:placetype":"locality",
    "wof:population":9
},
  "geometry": {"coordinates":[-115.95833,30.51361],"type":"Point"}
}