{
  "type": "Feature",
  "properties": {
    "gn:admin1_code":"19",
    "gn:admin2_code":"38.0",
    "gn:asciiname":"Lerdo de Tejada",
    "gn:country_code":"MX",
    "gn:dem":418,
    "gn:feature_class":"P",
    "gn:feature_code":"PPL",
    "gn:name":"Lerdo de Tejada",
    "gn:population":0,
    "gn:timezone":"America/Monterrey",
    "iso:country":"MX",
    "name:rus_x_preferred":[
        "\u041b\u0435\u0440\u0434\u043e-\u0434\u0435-\u0422\u0435\u0445\u0430\u0434\u0430"
    ],
    "name:srp_x_preferred":[
        "\u041e\u043f\u0448\u0442\u0438\u043d\u0430 \u041b\u0435\u0440\u0434\u043e \u0434\u0435 \u0422\u0435\u0445\u0430\u0434\u0430"
    ],
    "wof:name":"Lerdo de Tejada",
    "wof:placetype":"locality"
},
  "geometry": {"coordinates":[-99.76667,25.16667],"type":"Point"}
}