{
  "type": "Feature",
  "properties": {
    "gn:admin1_code":"5",
    "gn:admin2_code":"18.0",
    "gn:asciiname":"San Sebastian",
    "gn:country_code":"MX",
    "gn:dem":1034,
    "gn:feature_class":"P",
    "gn:feature_code":"PPL",
    "gn:name":"San Sebasti\u00e1n",
    "gn:population":207,
    "gn:timezone":"America/Mexico_City",
    "iso:country":"MX",
    "name:und_x_variant":[
        "San Sebasti\u00e1n"
    ],
    "wof:name":"San Sebastian",
    "wof:placetype":"locality",
    "wof:population":207
},
  "geometry": {"coordinates":[-93.11722,17.06472],"type":"Point"}
}