{
  "type": "Feature",
  "properties": {
    "gn:admin1_code":"20",
    "gn:admin2_code":"511.0",
    "gn:asciiname":"El Sabinal",
    "gn:country_code":"MX",
    "gn:dem":1930,
    "gn:feature_class":"P",
    "gn:feature_code":"PPL",
    "gn:name":"El Sabinal",
    "gn:population":185,
    "gn:timezone":"America/Mexico_City",
    "iso:country":"MX",
    "wof:name":"El Sabinal",
    "wof:placetype":"locality",
    "wof:population":185
},
  "geometry": {"coordinates":[-97.07306,17.20583],"type":"Point"}
}