{
  "type": "Feature",
  "properties": {
    "gn:admin1_code":"6",
    "gn:admin2_code":"65.0",
    "gn:asciiname":"El Pabellon",
    "gn:country_code":"MX",
    "gn:dem":656,
    "gn:feature_class":"P",
    "gn:feature_code":"PPL",
    "gn:name":"El Pabell\u00f3n",
    "gn:population":7,
    "gn:timezone":"America/Chihuahua",
    "iso:country":"MX",
    "name:und_x_variant":[
        "El Pabell\u00f3n"
    ],
    "wof:name":"El Pabellon",
    "wof:placetype":"locality",
    "wof:population":7
},
  "geometry": {"coordinates":[-107.92768999999998,27.21104],"type":"Point"}
}