{
  "type": "Feature",
  "properties": {
    "gn:admin1_code":"4",
    "gn:admin2_code":"3.0",
    "gn:asciiname":"Ninguno [Vulcanizadora]",
    "gn:country_code":"MX",
    "gn:dem":4,
    "gn:feature_class":"P",
    "gn:feature_code":"PPL",
    "gn:name":"Ninguno [Vulcanizadora]",
    "gn:population":4,
    "gn:timezone":"America/Merida",
    "iso:country":"MX",
    "wof:name":"Ninguno [Vulcanizadora]",
    "wof:placetype":"locality",
    "wof:population":4
},
  "geometry": {"coordinates":[-92.21639,18.61972],"type":"Point"}
}