{
  "type": "Feature",
  "properties": {
    "gn:admin1_code":"28.0",
    "gn:admin2_code":"37.0",
    "gn:asciiname":"Tres Hermanos",
    "gn:country_code":"MX",
    "gn:dem":36,
    "gn:feature_class":"P",
    "gn:feature_code":"PPL",
    "gn:name":"Tres Hermanos",
    "gn:population":11,
    "gn:timezone":"America/Monterrey",
    "iso:country":"MX",
    "name:spa_x_preferred":[
        "Tres Hermanos"
    ],
    "wof:name":"Tres Hermanos",
    "wof:placetype":"locality",
    "wof:population":11
},
  "geometry": {"coordinates":[-97.84222,23.64917],"type":"Point"}
}