{
  "type": "Feature",
  "properties": {
    "gn:admin1_code":"6",
    "gn:admin2_code":"36.0",
    "gn:asciiname":"Parras de los Sanchez",
    "gn:country_code":"MX",
    "gn:dem":1300,
    "gn:feature_class":"P",
    "gn:feature_code":"PPL",
    "gn:name":"Parras de los S\u00e1nchez",
    "gn:population":0,
    "gn:timezone":"America/Chihuahua",
    "iso:country":"MX",
    "name:spa_x_preferred":[
        "Parras de los S\u00e1nchez"
    ],
    "wof:name":"Parras de los Sanchez",
    "wof:placetype":"locality"
},
  "geometry": {"coordinates":[-104.91112,27.4408],"type":"Point"}
}