{
  "type": "Feature",
  "properties": {
    "gn:admin1_code":"32",
    "gn:admin2_code":"51",
    "gn:asciiname":"San Juan de la Cruz",
    "gn:country_code":"MX",
    "gn:dem":1982,
    "gn:feature_class":"P",
    "gn:feature_code":"PPL",
    "gn:name":"San Juan de la Cruz",
    "gn:population":52,
    "gn:timezone":"America/Mexico_City",
    "iso:country":"MX",
    "wof:name":"San Juan de la Cruz",
    "wof:placetype":"locality",
    "wof:population":52
},
  "geometry": {"coordinates":[-102.32917,23.69694],"type":"Point"}
}