{
  "type": "Feature",
  "properties": {
    "gn:admin1_code":"4",
    "gn:admin2_code":"3.0",
    "gn:asciiname":"Kilometro Tres",
    "gn:country_code":"MX",
    "gn:dem":20,
    "gn:feature_class":"P",
    "gn:feature_code":"PPL",
    "gn:name":"Kil\u00f3metro Tres",
    "gn:population":4,
    "gn:timezone":"America/Merida",
    "iso:country":"MX",
    "name:und_x_variant":[
        "Kil\u00f3metro Tres"
    ],
    "wof:name":"Kilometro Tres",
    "wof:placetype":"locality",
    "wof:population":4
},
  "geometry": {"coordinates":[-90.98083,18.65528],"type":"Point"}
}