{
  "type": "Feature",
  "properties": {
    "gn:admin1_code":"26.0",
    "gn:admin2_code":"52.0",
    "gn:asciiname":"El Gueerigo Gordo",
    "gn:country_code":"MX",
    "gn:dem":1481,
    "gn:feature_class":"P",
    "gn:feature_code":"PPL",
    "gn:name":"El G\u00fc\u00e9rigo Gordo",
    "gn:population":0,
    "gn:timezone":"America/Hermosillo",
    "iso:country":"MX",
    "name:spa_x_preferred":[
        "El G\u00fc\u00e9rigo Gordo"
    ],
    "wof:name":"El Gueerigo Gordo",
    "wof:placetype":"locality"
},
  "geometry": {"coordinates":[-108.95502,28.65096],"type":"Point"}
}