{
  "type": "Feature",
  "properties": {
    "gn:admin1_code":"28.0",
    "gn:admin2_code":"2.0",
    "gn:asciiname":"Lindero",
    "gn:country_code":"MX",
    "gn:dem":145,
    "gn:feature_class":"P",
    "gn:feature_code":"PPL",
    "gn:name":"Lindero",
    "gn:population":0,
    "gn:timezone":"America/Monterrey",
    "iso:country":"MX",
    "name:spa_x_preferred":[
        "Lindero"
    ],
    "wof:name":"Lindero",
    "wof:placetype":"locality"
},
  "geometry": {"coordinates":[-98.01596000000001,22.9247],"type":"Point"}
}