{
  "type": "Feature",
  "properties": {
    "gn:admin1_code":"21",
    "gn:admin2_code":"64.0",
    "gn:asciiname":"La Mina",
    "gn:country_code":"MX",
    "gn:dem":166,
    "gn:feature_class":"P",
    "gn:feature_code":"PPL",
    "gn:name":"La Mina",
    "gn:population":256,
    "gn:timezone":"America/Mexico_City",
    "iso:country":"MX",
    "name:spa_x_preferred":[
        "La Mina"
    ],
    "wof:name":"La Mina",
    "wof:placetype":"locality",
    "wof:population":256
},
  "geometry": {"coordinates":[-97.80389,20.79694],"type":"Point"}
}