{
  "type": "Feature",
  "properties": {
    "gn:admin1_code":"30",
    "gn:admin2_code":"61.0",
    "gn:asciiname":"Antonio Ribon Hernandez",
    "gn:country_code":"MX",
    "gn:dem":38,
    "gn:feature_class":"P",
    "gn:feature_code":"PPL",
    "gn:name":"Antonio Rib\u00f3n Hern\u00e1ndez",
    "gn:population":5,
    "gn:timezone":"America/Mexico_City",
    "iso:country":"MX",
    "name:und_x_variant":[
        "Antonio Rib\u00f3n Hern\u00e1ndez"
    ],
    "wof:name":"Antonio Ribon Hernandez",
    "wof:placetype":"locality",
    "wof:population":5
},
  "geometry": {"coordinates":[-93.95999999999999,17.57528],"type":"Point"}
}