{
  "type": "Feature",
  "properties": {
    "gn:admin1_code":"12",
    "gn:admin2_code":"67",
    "gn:asciiname":"El Guayabal",
    "gn:country_code":"MX",
    "gn:dem":565,
    "gn:feature_class":"P",
    "gn:feature_code":"PPL",
    "gn:name":"El Guayabal",
    "gn:population":13,
    "gn:timezone":"America/Mexico_City",
    "iso:country":"MX",
    "wof:name":"El Guayabal",
    "wof:placetype":"locality",
    "wof:population":13
},
  "geometry": {"coordinates":[-100.49616,18.29032],"type":"Point"}
}