{
  "type": "Feature",
  "properties": {
    "gn:admin1_code":"27",
    "gn:admin2_code":"8.0",
    "gn:asciiname":"Encomendero",
    "gn:country_code":"MX",
    "gn:dem":40,
    "gn:feature_class":"P",
    "gn:feature_code":"PPL",
    "gn:name":"Encomendero",
    "gn:population":0,
    "gn:timezone":"America/Mexico_City",
    "iso:country":"MX",
    "name:spa_x_preferred":[
        "El Encomendadero"
    ],
    "name:spa_x_variant":[
        "Encomendero",
        "El Encomendero"
    ],
    "wof:name":"Encomendero",
    "wof:placetype":"locality"
},
  "geometry": {"coordinates":[-93.59021,17.79736],"type":"Point"}
}