{
  "type": "Feature",
  "properties": {
    "gn:admin1_code":"16.0",
    "gn:admin2_code":"69.0",
    "gn:asciiname":"El Algodonal",
    "gn:country_code":"MX",
    "gn:dem":1749,
    "gn:feature_class":"P",
    "gn:feature_code":"PPL",
    "gn:name":"El Algodonal",
    "gn:population":314,
    "gn:timezone":"America/Mexico_City",
    "iso:country":"MX",
    "wof:name":"El Algodonal",
    "wof:placetype":"locality",
    "wof:population":314
},
  "geometry": {"coordinates":[-102.10111000000001,20.25417],"type":"Point"}
}