{
  "type": "Feature",
  "properties": {
    "gn:admin1_code":"5",
    "gn:admin2_code":"89.0",
    "gn:asciiname":"El Cuadrito",
    "gn:country_code":"MX",
    "gn:dem":450,
    "gn:feature_class":"P",
    "gn:feature_code":"PPL",
    "gn:name":"El Cuadrito",
    "gn:population":6,
    "gn:timezone":"America/Mexico_City",
    "iso:country":"MX",
    "wof:name":"El Cuadrito",
    "wof:placetype":"locality",
    "wof:population":6
},
  "geometry": {"coordinates":[-92.23556000000001,15.03028],"type":"Point"}
}