{
  "type": "Feature",
  "properties": {
    "gn:admin1_code":"30.0",
    "gn:admin2_code":"34.0",
    "gn:asciiname":"La Adelaida",
    "gn:country_code":"MX",
    "gn:dem":152,
    "gn:feature_class":"P",
    "gn:feature_code":"PPL",
    "gn:name":"La Adelaida",
    "gn:population":0,
    "gn:timezone":"America/Mexico_City",
    "iso:country":"MX",
    "name:spa_x_preferred":[
        "La Adelaida"
    ],
    "wof:name":"La Adelaida",
    "wof:placetype":"locality"
},
  "geometry": {"coordinates":[-97.7428,21.15961],"type":"Point"}
}