{
  "type": "Feature",
  "properties": {
    "gn:admin1_code":"30",
    "gn:admin2_code":"144",
    "gn:asciiname":"Los Limones",
    "gn:country_code":"MX",
    "gn:dem":71,
    "gn:feature_class":"P",
    "gn:feature_code":"PPL",
    "gn:name":"Los Limones",
    "gn:population":25,
    "gn:timezone":"America/Mexico_City",
    "iso:country":"MX",
    "wof:name":"Los Limones",
    "wof:placetype":"locality",
    "wof:population":25
},
  "geometry": {"coordinates":[-95.00888999999999,17.76222000000001],"type":"Point"}
}