{
  "type": "Feature",
  "properties": {
    "gn:admin1_code":"28.0",
    "gn:admin2_code":"7.0",
    "gn:asciiname":"Seccion Veintiseis",
    "gn:country_code":"MX",
    "gn:dem":69,
    "gn:feature_class":"P",
    "gn:feature_code":"PPL",
    "gn:name":"Secci\u00f3n Veintis\u00e9is",
    "gn:population":0,
    "gn:timezone":"America/Monterrey",
    "iso:country":"MX",
    "name:spa_x_preferred":[
        "Secci\u00f3n Veintis\u00e9is"
    ],
    "wof:name":"Seccion Veintiseis",
    "wof:placetype":"locality"
},
  "geometry": {"coordinates":[-98.91632,26.19662000000001],"type":"Point"}
}