{
  "type": "Feature",
  "properties": {
    "gn:admin1_code":"11.0",
    "gn:admin2_code":"14.0",
    "gn:asciiname":"El Rosalito",
    "gn:country_code":"MX",
    "gn:dem":1999,
    "gn:feature_class":"P",
    "gn:feature_code":"PPL",
    "gn:name":"El Rosalito",
    "gn:population":73,
    "gn:timezone":"America/Mexico_City",
    "iso:country":"MX",
    "name:und_x_variant":[
        "Rosalito",
        "El Rosalito"
    ],
    "wof:name":"El Rosalito",
    "wof:placetype":"locality",
    "wof:population":73
},
  "geometry": {"coordinates":[-100.73907,21.25167],"type":"Point"}
}