{
  "type": "Feature",
  "properties": {
    "gn:admin1_code":"10",
    "gn:admin2_code":"2.0",
    "gn:asciiname":"Valuarte",
    "gn:country_code":"MX",
    "gn:dem":2470,
    "gn:feature_class":"P",
    "gn:feature_code":"PPL",
    "gn:name":"Valuarte",
    "gn:population":8,
    "gn:timezone":"America/Monterrey",
    "iso:country":"MX",
    "wof:name":"Valuarte",
    "wof:placetype":"locality",
    "wof:population":8
},
  "geometry": {"coordinates":[-106.34202999999999,25.08803],"type":"Point"}
}