{
  "type": "Feature",
  "properties": {
    "gn:admin1_code":"26",
    "gn:admin2_code":"23.0",
    "gn:asciiname":"Agua Buena",
    "gn:country_code":"MX",
    "gn:dem":961,
    "gn:feature_class":"P",
    "gn:feature_code":"PPL",
    "gn:name":"Agua Buena",
    "gn:population":0,
    "gn:timezone":"America/Hermosillo",
    "iso:country":"MX",
    "name:ceb_x_preferred":[
        "Agua Buena"
    ],
    "name:fas_x_preferred":[
        "\u0627\u06af\u0648\u0627 \u0628\u0648\u0646\u0627"
    ],
    "name:ita_x_preferred":[
        "Agua Buena"
    ],
    "name:kat_x_preferred":[
        "\u10d0\u10d2\u10e3\u10d0-\u10d1\u10e3\u10d4\u10dc\u10d0"
    ],
    "name:nld_x_preferred":[
        "Agua Buena"
    ],
    "name:spa_x_preferred":[
        "Agua Buena"
    ],
    "name:urd_x_preferred":[
        "\u0627\u06af\u0648\u0627 \u0628\u06cc\u0648\u0646\u0627"
    ],
    "name:zho_x_preferred":[
        "\u963f\u74dc\u5e03\u57c3\u7d0d"
    ],
    "wof:name":"Agua Buena",
    "wof:placetype":"locality"
},
  "geometry": {"coordinates":[-109.91374,29.87579],"type":"Point"}
}