{
  "type": "Feature",
  "properties": {
    "gn:admin1_code":"10",
    "gn:admin2_code":"9",
    "gn:asciiname":"Austrebertha Bustillos",
    "gn:country_code":"MX",
    "gn:dem":2950,
    "gn:feature_class":"P",
    "gn:feature_code":"PPL",
    "gn:name":"Austrebertha Bustillos",
    "gn:population":9,
    "gn:timezone":"America/Monterrey",
    "iso:country":"MX",
    "wof:name":"Austrebertha Bustillos",
    "wof:placetype":"locality",
    "wof:population":9
},
  "geometry": {"coordinates":[-106.38291,26.23357],"type":"Point"}
}