{
  "type": "Feature",
  "properties": {
    "gn:admin1_code":"14",
    "gn:admin2_code":"118.0",
    "gn:asciiname":"La Loma",
    "gn:country_code":"MX",
    "gn:dem":1919,
    "gn:feature_class":"P",
    "gn:feature_code":"PPL",
    "gn:name":"La Loma",
    "gn:population":8,
    "gn:timezone":"America/Mexico_City",
    "iso:country":"MX",
    "name:ceb_x_preferred":[
        "La Loma"
    ],
    "name:deu_x_preferred":[
        "La Loma"
    ],
    "name:spa_x_preferred":[
        "La Loma"
    ],
    "name:srp_x_preferred":[
        "\u041b\u0430 \u041b\u043e\u043c\u0430"
    ],
    "name:swe_x_preferred":[
        "La Loma"
    ],
    "wof:name":"La Loma",
    "wof:placetype":"locality",
    "wof:population":8
},
  "geometry": {"coordinates":[-102.93889,21.18083],"type":"Point"}
}