{
  "type": "Feature",
  "properties": {
    "gn:admin1_code":"24",
    "gn:admin2_code":"35.0",
    "gn:asciiname":"Don Ines [Establo]",
    "gn:country_code":"MX",
    "gn:dem":1838,
    "gn:feature_class":"P",
    "gn:feature_code":"PPL",
    "gn:name":"Don In\u00e9s [Establo]",
    "gn:population":8,
    "gn:timezone":"America/Mexico_City",
    "iso:country":"MX",
    "name:und_x_variant":[
        "Don In\u00e9s [Establo]"
    ],
    "wof:name":"Don Ines [Establo]",
    "wof:placetype":"locality",
    "wof:population":8
},
  "geometry": {"coordinates":[-100.87444000000001,22.20583],"type":"Point"}
}