{
  "type": "Feature",
  "properties": {
    "gn:admin1_code":"14.0",
    "gn:asciiname":"El Agostadero Dos",
    "gn:country_code":"MX",
    "gn:dem":1769,
    "gn:feature_class":"P",
    "gn:feature_code":"PPL",
    "gn:name":"El Agostadero Dos",
    "gn:population":0,
    "gn:timezone":"America/Mexico_City",
    "iso:country":"MX",
    "name:spa_x_preferred":[
        "El Agostadero Dos"
    ],
    "wof:name":"El Agostadero Dos",
    "wof:placetype":"locality"
},
  "geometry": {"coordinates":[-103.20406,18.95657000000001],"type":"Point"}
}