{
  "type": "Feature",
  "properties": {
    "gn:admin1_code":"16",
    "gn:admin2_code":"52.0",
    "gn:asciiname":"Isla de la Palma",
    "gn:country_code":"MX",
    "gn:dem":20,
    "gn:feature_class":"P",
    "gn:feature_code":"PPL",
    "gn:name":"Isla de la Palma",
    "gn:population":0,
    "gn:timezone":"America/Mexico_City",
    "iso:country":"MX",
    "name:spa_x_preferred":[
        "Isla de la Palma"
    ],
    "wof:name":"Isla de la Palma",
    "wof:placetype":"locality"
},
  "geometry": {"coordinates":[-102.19032,18.02073],"type":"Point"}
}