{
  "type": "Feature",
  "properties": {
    "gn:admin1_code":"21",
    "gn:admin2_code":"43",
    "gn:asciiname":"Xala",
    "gn:country_code":"MX",
    "gn:dem":293,
    "gn:feature_class":"P",
    "gn:feature_code":"PPL",
    "gn:name":"Xala",
    "gn:population":34,
    "gn:timezone":"America/Mexico_City",
    "iso:country":"MX",
    "name:ben_x_preferred":[
        "\u0995\u09cd\u09b7\u09be\u09b2\u09be"
    ],
    "name:deu_x_preferred":[
        "Xala"
    ],
    "name:fra_x_preferred":[
        "Xala"
    ],
    "name:hat_x_preferred":[
        "Xala"
    ],
    "name:ita_x_preferred":[
        "Xala"
    ],
    "name:lat_x_preferred":[
        "Xala"
    ],
    "name:msa_x_preferred":[
        "Filem Xala"
    ],
    "name:spa_x_preferred":[
        "Xala"
    ],
    "wof:name":"Xala",
    "wof:placetype":"locality",
    "wof:population":34
},
  "geometry": {"coordinates":[-97.42305,20.04805],"type":"Point"}
}