{
  "type": "Feature",
  "properties": {
    "gn:admin1_code":"21",
    "gn:admin2_code":"43",
    "gn:asciiname":"Xala",
    "gn:country_code":"MX",
    "gn:dem":293,
    "gn:feature_class":"P",
    "gn:feature_code":"PPL",
    "gn:name":"Xala",
    "gn:population":34,
    "gn:timezone":"America/Mexico_City",
    "iso:country":"MX",
    "wof:name":"Xala",
    "wof:placetype":"locality",
    "wof:population":34
},
  "geometry": {"coordinates":[-97.42305,20.04805],"type":"Point"}
}