{
  "type": "Feature",
  "properties": {
    "gn:admin1_code":"7",
    "gn:admin2_code":"19.0",
    "gn:asciiname":"Ninguno [Lienzo Charro]",
    "gn:country_code":"MX",
    "gn:dem":368,
    "gn:feature_class":"P",
    "gn:feature_code":"PPL",
    "gn:name":"Ninguno [Lienzo Charro]",
    "gn:population":4,
    "gn:timezone":"America/Monterrey",
    "iso:country":"MX",
    "wof:name":"Ninguno [Lienzo Charro]",
    "wof:placetype":"locality",
    "wof:population":4
},
  "geometry": {"coordinates":[-100.89259,28.42636],"type":"Point"}
}