{
  "type": "Feature",
  "properties": {
    "gn:admin1_code":"30",
    "gn:admin2_code":"124.0",
    "gn:asciiname":"Arroyo del Arco",
    "gn:country_code":"MX",
    "gn:dem":77,
    "gn:feature_class":"P",
    "gn:feature_code":"PPL",
    "gn:name":"Arroyo del Arco",
    "gn:population":0,
    "gn:timezone":"America/Mexico_City",
    "iso:country":"MX",
    "name:spa_x_preferred":[
        "Arroyo del Arco"
    ],
    "wof:name":"Arroyo del Arco",
    "wof:placetype":"locality"
},
  "geometry": {"coordinates":[-97.33864,20.35913],"type":"Point"}
}