{
  "type": "Feature",
  "properties": {
    "gn:admin1_code":"21.0",
    "gn:admin2_code":"213.0",
    "gn:asciiname":"Ernesto Hernandez",
    "gn:country_code":"MX",
    "gn:dem":405,
    "gn:feature_class":"P",
    "gn:feature_code":"PPL",
    "gn:name":"Ernesto Hern\u00e1ndez",
    "gn:population":0,
    "gn:timezone":"America/Mexico_City",
    "iso:country":"MX",
    "name:spa_x_preferred":[
        "Ernesto Hern\u00e1ndez"
    ],
    "name:spa_x_variant":[
        "Tlacoyuco"
    ],
    "wof:name":"Ernesto Hernandez",
    "wof:placetype":"locality"
},
  "geometry": {"coordinates":[-97.75948,20.33058],"type":"Point"}
}