{
  "type": "Feature",
  "properties": {
    "gn:admin1_code":"6",
    "gn:admin2_code":"7.0",
    "gn:asciiname":"San Jose",
    "gn:country_code":"MX",
    "gn:dem":2358,
    "gn:feature_class":"P",
    "gn:feature_code":"PPL",
    "gn:name":"San Jos\u00e9",
    "gn:population":23,
    "gn:timezone":"America/Chihuahua",
    "iso:country":"MX",
    "wof:name":"San Jose",
    "wof:placetype":"locality",
    "wof:population":23
},
  "geometry": {"coordinates":[-106.62018999999999,26.97135],"type":"Point"}
}