{
  "type": "Feature",
  "properties": {
    "gn:admin1_code":"5",
    "gn:admin2_code":"52",
    "gn:asciiname":"Paso Hondo",
    "gn:country_code":"MX",
    "gn:dem":717,
    "gn:feature_class":"P",
    "gn:feature_code":"PPL",
    "gn:name":"Paso Hondo",
    "gn:population":27,
    "gn:timezone":"America/Mexico_City",
    "iso:country":"MX",
    "wof:name":"Paso Hondo",
    "wof:placetype":"locality",
    "wof:population":27
},
  "geometry": {"coordinates":[-91.47499999999999,16.28333],"type":"Point"}
}