{
  "type": "Feature",
  "properties": {
    "gn:admin1_code":"5",
    "gn:admin2_code":"97",
    "gn:asciiname":"Guatemalita",
    "gn:country_code":"MX",
    "gn:dem":6,
    "gn:feature_class":"P",
    "gn:feature_code":"PPL",
    "gn:name":"Guatemalita",
    "gn:population":22,
    "gn:timezone":"America/Mexico_City",
    "iso:country":"MX",
    "wof:name":"Guatemalita",
    "wof:placetype":"locality",
    "wof:population":22
},
  "geometry": {"coordinates":[-93.86750000000001,16.04417],"type":"Point"}
}