{
  "type": "Feature",
  "properties": {
    "gn:admin1_code":"10.0",
    "gn:asciiname":"La Presa",
    "gn:country_code":"MX",
    "gn:dem":728,
    "gn:feature_class":"P",
    "gn:feature_code":"PPL",
    "gn:name":"La Presa",
    "gn:population":0,
    "gn:timezone":"America/Monterrey",
    "iso:country":"MX",
    "name:spa_x_preferred":[
        "La Presa"
    ],
    "wof:name":"La Presa",
    "wof:placetype":"locality"
},
  "geometry": {"coordinates":[-105.86165,24.19404],"type":"Point"}
}