{
  "type": "Feature",
  "properties": {
    "gn:admin1_code":"10",
    "gn:admin2_code":"14",
    "gn:asciiname":"Tierra Blanca",
    "gn:country_code":"MX",
    "gn:dem":2094,
    "gn:feature_class":"P",
    "gn:feature_code":"PPL",
    "gn:name":"Tierra Blanca",
    "gn:population":27,
    "gn:timezone":"America/Monterrey",
    "iso:country":"MX",
    "wof:name":"Tierra Blanca",
    "wof:placetype":"locality",
    "wof:population":27
},
  "geometry": {"coordinates":[-104.62719,23.00836],"type":"Point"}
}