{
  "type": "Feature",
  "properties": {
    "gn:admin1_code":"30",
    "gn:admin2_code":"83.0",
    "gn:asciiname":"Apachahual",
    "gn:country_code":"MX",
    "gn:dem":428,
    "gn:feature_class":"P",
    "gn:feature_code":"PPL",
    "gn:name":"Apachahual",
    "gn:population":178,
    "gn:timezone":"America/Mexico_City",
    "iso:country":"MX",
    "wof:name":"Apachahual",
    "wof:placetype":"locality",
    "wof:population":178
},
  "geometry": {"coordinates":[-98.0675,20.81028],"type":"Point"}
}