{
  "type": "Feature",
  "properties": {
    "gn:admin1_code":"30",
    "gn:admin2_code":"164.0",
    "gn:asciiname":"Isla Grande",
    "gn:country_code":"MX",
    "gn:dem":1010,
    "gn:feature_class":"P",
    "gn:feature_code":"PPL",
    "gn:name":"Isla Grande",
    "gn:population":0,
    "gn:timezone":"America/Mexico_City",
    "iso:country":"MX",
    "name:ceb_x_preferred":[
        "Isla Grande"
    ],
    "name:fra_x_preferred":[
        "Isla Grande"
    ],
    "name:ita_x_preferred":[
        "Isla Grande"
    ],
    "name:nor_x_preferred":[
        "Isla Grande"
    ],
    "name:pol_x_preferred":[
        "Isla Grande"
    ],
    "name:por_x_preferred":[
        "Ilha Grande"
    ],
    "name:spa_x_preferred":[
        "Isla Grande"
    ],
    "wof:name":"Isla Grande",
    "wof:placetype":"locality"
},
  "geometry": {"coordinates":[-96.93917999999999,19.37057],"type":"Point"}
}