{
  "type": "Feature",
  "properties": {
    "gn:admin1_code":"11",
    "gn:admin2_code":"29.0",
    "gn:asciiname":"Ex-Hacienda de Ojuelos",
    "gn:country_code":"MX",
    "gn:dem":2019,
    "gn:feature_class":"P",
    "gn:feature_code":"PPL",
    "gn:name":"Ex-Hacienda de Ojuelos",
    "gn:population":163,
    "gn:timezone":"America/Mexico_City",
    "iso:country":"MX",
    "wof:name":"Ex-Hacienda de Ojuelos",
    "wof:placetype":"locality",
    "wof:population":163
},
  "geometry": {"coordinates":[-100.84575,21.37648],"type":"Point"}
}