{
  "type": "Feature",
  "properties": {
    "gn:admin1_code":"6",
    "gn:admin2_code":"55.0",
    "gn:asciiname":"El Ojo de la Morita",
    "gn:country_code":"MX",
    "gn:dem":1326,
    "gn:feature_class":"P",
    "gn:feature_code":"PPL",
    "gn:name":"El Ojo de la Morita",
    "gn:population":0,
    "gn:timezone":"America/Chihuahua",
    "iso:country":"MX",
    "name:spa_x_preferred":[
        "El Ojo de la Morita"
    ],
    "wof:name":"El Ojo de la Morita",
    "wof:placetype":"locality"
},
  "geometry": {"coordinates":[-105.81316,28.09411],"type":"Point"}
}