{
  "type": "Feature",
  "properties": {
    "gn:admin1_code":"27",
    "gn:admin2_code":"4.0",
    "gn:asciiname":"El Amate Segunda Seccion",
    "gn:country_code":"MX",
    "gn:dem":42,
    "gn:feature_class":"P",
    "gn:feature_code":"PPL",
    "gn:name":"El Amate Segunda Secci\u00f3n",
    "gn:population":0,
    "gn:timezone":"America/Mexico_City",
    "iso:country":"MX",
    "name:spa_x_preferred":[
        "Barrancas de Amate"
    ],
    "name:spa_x_variant":[
        "El Amate Segunda Secci\u00f3n"
    ],
    "wof:name":"El Amate Segunda Seccion",
    "wof:placetype":"locality"
},
  "geometry": {"coordinates":[-92.75360000000001,17.9562],"type":"Point"}
}