{
  "type": "Feature",
  "properties": {
    "gn:admin1_code":"25",
    "gn:admin2_code":"12.0",
    "gn:asciiname":"Los Panales",
    "gn:country_code":"MX",
    "gn:dem":243,
    "gn:feature_class":"P",
    "gn:feature_code":"PPL",
    "gn:name":"Los Panales",
    "gn:population":0,
    "gn:timezone":"America/Mazatlan",
    "iso:country":"MX",
    "name:spa_x_preferred":[
        "Los Panales"
    ],
    "wof:name":"Los Panales",
    "wof:placetype":"locality"
},
  "geometry": {"coordinates":[-106.02298999999999,23.70255],"type":"Point"}
}