{
  "type": "Feature",
  "properties": {
    "gn:admin1_code":"26.0",
    "gn:admin2_code":"3.0",
    "gn:asciiname":"Tecoripa",
    "gn:country_code":"MX",
    "gn:dem":283,
    "gn:feature_class":"P",
    "gn:feature_code":"PPL",
    "gn:name":"Tecoripa",
    "gn:population":0,
    "gn:timezone":"America/Hermosillo",
    "iso:country":"MX",
    "name:spa_x_preferred":[
        "Tecoripa"
    ],
    "wof:name":"Tecoripa",
    "wof:placetype":"locality"
},
  "geometry": {"coordinates":[-108.84742,27.72363],"type":"Point"}
}