{
  "type": "Feature",
  "properties": {
    "gn:admin1_code":"5.0",
    "gn:admin2_code":"52.0",
    "gn:asciiname":"Barrio Yalcok",
    "gn:country_code":"MX",
    "gn:dem":1554,
    "gn:feature_class":"P",
    "gn:feature_code":"PPL",
    "gn:name":"Barrio Yalcok",
    "gn:population":0,
    "gn:timezone":"America/Mexico_City",
    "iso:country":"MX",
    "name:spa_x_preferred":[
        "Barrio Yalcok"
    ],
    "wof:name":"Barrio Yalcok",
    "wof:placetype":"locality"
},
  "geometry": {"coordinates":[-91.99012999999999,16.33646],"type":"Point"}
}