{
  "type": "Feature",
  "properties": {
    "gn:admin1_code":"4",
    "gn:admin2_code":"2.0",
    "gn:asciiname":"Oxa",
    "gn:country_code":"MX",
    "gn:dem":96,
    "gn:feature_class":"P",
    "gn:feature_code":"PPL",
    "gn:name":"Oxa",
    "gn:population":0,
    "gn:timezone":"America/Merida",
    "iso:country":"MX",
    "name:spa_x_preferred":[
        "Oxa"
    ],
    "wof:name":"Oxa",
    "wof:placetype":"locality"
},
  "geometry": {"coordinates":[-90.09117999999999,19.62708],"type":"Point"}
}