{
  "type": "Feature",
  "properties": {
    "gn:admin1_code":"21",
    "gn:admin2_code":"12.0",
    "gn:asciiname":"San Antonio Jalapasco",
    "gn:country_code":"MX",
    "gn:dem":2515,
    "gn:feature_class":"P",
    "gn:feature_code":"PPL",
    "gn:name":"San Antonio Jalapasco",
    "gn:population":251,
    "gn:timezone":"America/Mexico_City",
    "iso:country":"MX",
    "wof:name":"San Antonio Jalapasco",
    "wof:placetype":"locality",
    "wof:population":251
},
  "geometry": {"coordinates":[-97.48083,19.09667],"type":"Point"}
}