{
  "type": "Feature",
  "properties": {
    "gn:admin1_code":"6.0",
    "gn:admin2_code":"51.0",
    "gn:asciiname":"Los Topes",
    "gn:country_code":"MX",
    "gn:dem":1332,
    "gn:feature_class":"P",
    "gn:feature_code":"PPL",
    "gn:name":"Los Topes",
    "gn:population":0,
    "gn:timezone":"America/Chihuahua",
    "iso:country":"MX",
    "name:spa_x_preferred":[
        "Los Topes"
    ],
    "wof:name":"Los Topes",
    "wof:placetype":"locality"
},
  "geometry": {"coordinates":[-108.32386,28.08097],"type":"Point"}
}