{
  "type": "Feature",
  "properties": {
    "gn:admin1_code":"6",
    "gn:admin2_code":"65",
    "gn:asciiname":"Rohuerachi",
    "gn:country_code":"MX",
    "gn:dem":2239,
    "gn:feature_class":"P",
    "gn:feature_code":"PPL",
    "gn:name":"Rohuerachi",
    "gn:population":14,
    "gn:timezone":"America/Chihuahua",
    "iso:country":"MX",
    "wof:name":"Rohuerachi",
    "wof:placetype":"locality",
    "wof:population":14
},
  "geometry": {"coordinates":[-107.7402,27.4627],"type":"Point"}
}