{
  "type": "Feature",
  "properties": {
    "gn:admin1_code":"32",
    "gn:admin2_code":"31.0",
    "gn:asciiname":"Ojuelos",
    "gn:country_code":"MX",
    "gn:dem":2397,
    "gn:feature_class":"P",
    "gn:feature_code":"PPL",
    "gn:name":"Ojuelos",
    "gn:population":0,
    "gn:timezone":"America/Mexico_City",
    "iso:country":"MX",
    "name:spa_x_preferred":[
        "Ojuelos"
    ],
    "wof:name":"Ojuelos",
    "wof:placetype":"locality"
},
  "geometry": {"coordinates":[-103.58949,22.31846],"type":"Point"}
}