{
  "type": "Feature",
  "properties": {
    "gn:admin1_code":"14",
    "gn:admin2_code":"31",
    "gn:asciiname":"Mesa del Capulin",
    "gn:country_code":"MX",
    "gn:dem":2102,
    "gn:feature_class":"P",
    "gn:feature_code":"PPL",
    "gn:name":"Mesa del Capul\u00edn",
    "gn:population":24,
    "gn:timezone":"America/Mexico_City",
    "iso:country":"MX",
    "name:und_x_variant":[
        "Mesa del Capul\u00edn"
    ],
    "wof:name":"Mesa del Capulin",
    "wof:placetype":"locality",
    "wof:population":24
},
  "geometry": {"coordinates":[-103.62472,21.59694],"type":"Point"}
}