{
  "type": "Feature",
  "properties": {
    "gn:admin1_code":"14",
    "gn:admin2_code":"120.0",
    "gn:asciiname":"El Nabo",
    "gn:country_code":"MX",
    "gn:dem":1536,
    "gn:feature_class":"P",
    "gn:feature_code":"PPL",
    "gn:name":"El Nabo",
    "gn:population":5,
    "gn:timezone":"America/Mexico_City",
    "iso:country":"MX",
    "wof:name":"El Nabo",
    "wof:placetype":"locality",
    "wof:population":5
},
  "geometry": {"coordinates":[-103.58222000000001,20.72806],"type":"Point"}
}