{
  "type": "Feature",
  "properties": {
    "gn:admin1_code":"14",
    "gn:admin2_code":"19.0",
    "gn:asciiname":"Huizaista",
    "gn:country_code":"MX",
    "gn:dem":1044,
    "gn:feature_class":"P",
    "gn:feature_code":"PPL",
    "gn:name":"Huizaista",
    "gn:population":73,
    "gn:timezone":"America/Mexico_City",
    "iso:country":"MX",
    "wof:name":"Huizaista",
    "wof:placetype":"locality",
    "wof:population":73
},
  "geometry": {"coordinates":[-104.03972,21.85972000000001],"type":"Point"}
}