{
  "type": "Feature",
  "properties": {
    "gn:admin1_code":"20",
    "gn:admin2_code":"135.0",
    "gn:asciiname":"Jalapa del Valle",
    "gn:country_code":"MX",
    "gn:dem":1732,
    "gn:feature_class":"P",
    "gn:feature_code":"PPL",
    "gn:name":"Jalapa del Valle",
    "gn:population":0,
    "gn:timezone":"America/Mexico_City",
    "iso:country":"MX",
    "name:ceb_x_preferred":[
        "Jalapa del Valle"
    ],
    "name:spa_x_preferred":[
        "Jalapilla"
    ],
    "name:spa_x_variant":[
        "Jalapa del Valle"
    ],
    "name:srp_x_preferred":[
        "\u0425\u0430\u043b\u0430\u043f\u0430 \u0434\u0435\u043b \u0412\u0430\u0459\u0435"
    ],
    "name:swe_x_preferred":[
        "Jalapa del Valle"
    ],
    "wof:name":"Jalapa del Valle",
    "wof:placetype":"locality"
},
  "geometry": {"coordinates":[-96.87752,17.06758],"type":"Point"}
}