{
  "type": "Feature",
  "properties": {
    "gn:admin1_code":"30",
    "gn:admin2_code":"71",
    "gn:asciiname":"Felipe Reyes",
    "gn:country_code":"MX",
    "gn:dem":1505,
    "gn:feature_class":"P",
    "gn:feature_code":"PPL",
    "gn:name":"Felipe Reyes",
    "gn:population":29,
    "gn:timezone":"America/Mexico_City",
    "iso:country":"MX",
    "name:ara_x_preferred":[
        "\u0641\u064a\u0644\u064a\u0628\u064a \u0631\u064a\u064a\u0633"
    ],
    "name:cat_x_preferred":[
        "Felipe Reyes Cabanas"
    ],
    "name:deu_x_preferred":[
        "Felipe Reyes"
    ],
    "name:ell_x_preferred":[
        "\u03a6\u03b5\u03bb\u03af\u03c0\u03b5 \u03a1\u03ad\u03b3\u03b9\u03b5\u03c2"
    ],
    "name:fas_x_preferred":[
        "\u0641\u06cc\u0644\u06cc\u067e\u0647 \u0631\u06cc\u0633"
    ],
    "name:fin_x_preferred":[
        "Felipe Reyes"
    ],
    "name:fra_x_preferred":[
        "Felipe Reyes"
    ],
    "name:glg_x_preferred":[
        "Felipe Reyes"
    ],
    "name:heb_x_preferred":[
        "\u05e4\u05dc\u05d9\u05e4\u05d4 \u05e8\u05d9\u05d9\u05e1"
    ],
    "name:hrv_x_preferred":[
        "Felipe Reyes"
    ],
    "name:ind_x_preferred":[
        "Felipe Reyes"
    ],
    "name:ita_x_preferred":[
        "Felipe Reyes"
    ],
    "name:jpn_x_preferred":[
        "\u30d5\u30a7\u30ea\u30da\u30fb\u30ec\u30b8\u30a7\u30b9"
    ],
    "name:lav_x_preferred":[
        "Felipe Rejess"
    ],
    "name:mlg_x_preferred":[
        "Felipe Reyes"
    ],
    "name:nor_x_preferred":[
        "Felipe Reyes"
    ],
    "name:pol_x_preferred":[
        "Felipe Reyes"
    ],
    "name:por_x_preferred":[
        "Felipe Reyes"
    ],
    "name:rus_x_preferred":[
        "\u0420\u0435\u0439\u0435\u0441"
    ],
    "name:spa_x_preferred":[
        "Felipe Reyes"
    ],
    "name:srp_x_preferred":[
        "\u0424\u0435\u043b\u0438\u043f\u0435 \u0420\u0435\u0458\u0435\u0441"
    ],
    "name:swe_x_preferred":[
        "Felipe Reyes"
    ],
    "name:tur_x_preferred":[
        "Felipe Reyes"
    ],
    "name:ukr_x_preferred":[
        "\u0424\u0435\u043b\u0456\u043f\u0435 \u0420\u0435\u0454\u0441"
    ],
    "name:vol_x_preferred":[
        "Felipe Reyes"
    ],
    "name:zho_x_preferred":[
        "\u8d39\u5229\u4f69\u00b7\u96f7\u8036\u65af"
    ],
    "wof:name":"Felipe Reyes",
    "wof:placetype":"locality",
    "wof:population":29
},
  "geometry": {"coordinates":[-97.00667,19.18333],"type":"Point"}
}