{
  "type": "Feature",
  "properties": {
    "gn:admin1_code":"30",
    "gn:admin2_code":"71",
    "gn:asciiname":"Felipe Reyes",
    "gn:country_code":"MX",
    "gn:dem":1505,
    "gn:feature_class":"P",
    "gn:feature_code":"PPL",
    "gn:name":"Felipe Reyes",
    "gn:population":29,
    "gn:timezone":"America/Mexico_City",
    "iso:country":"MX",
    "wof:name":"Felipe Reyes",
    "wof:placetype":"locality",
    "wof:population":29
},
  "geometry": {"coordinates":[-97.00667,19.18333],"type":"Point"}
}