{
  "type": "Feature",
  "properties": {
    "gn:admin1_code":"21",
    "gn:admin2_code":"36.0",
    "gn:asciiname":"Aticpac",
    "gn:country_code":"MX",
    "gn:dem":1078,
    "gn:feature_class":"P",
    "gn:feature_code":"PPL",
    "gn:name":"Aticpac",
    "gn:population":152,
    "gn:timezone":"America/Mexico_City",
    "iso:country":"MX",
    "wof:name":"Aticpac",
    "wof:placetype":"locality",
    "wof:population":152
},
  "geometry": {"coordinates":[-96.92327,18.34834],"type":"Point"}
}