{
  "type": "Feature",
  "properties": {
    "gn:admin1_code":"28.0",
    "gn:admin2_code":"16.0",
    "gn:asciiname":"Izaguirre",
    "gn:country_code":"MX",
    "gn:dem":247,
    "gn:feature_class":"P",
    "gn:feature_code":"PPL",
    "gn:name":"Izaguirre",
    "gn:population":0,
    "gn:timezone":"America/Monterrey",
    "iso:country":"MX",
    "name:spa_x_preferred":[
        "Izaguirre"
    ],
    "wof:name":"Izaguirre",
    "wof:placetype":"locality"
},
  "geometry": {"coordinates":[-99.27540999999999,24.14667],"type":"Point"}
}