{
  "type": "Feature",
  "properties": {
    "gn:admin1_code":"26",
    "gn:admin2_code":"42.0",
    "gn:asciiname":"Los Caritos",
    "gn:country_code":"MX",
    "gn:dem":64,
    "gn:feature_class":"P",
    "gn:feature_code":"PPL",
    "gn:name":"Los Caritos",
    "gn:population":0,
    "gn:timezone":"America/Hermosillo",
    "iso:country":"MX",
    "name:spa_x_preferred":[
        "Los Caritos"
    ],
    "wof:name":"Los Caritos",
    "wof:placetype":"locality"
},
  "geometry": {"coordinates":[-109.72096999999999,27.27288],"type":"Point"}
}