{
  "type": "Feature",
  "properties": {
    "gn:admin1_code":"6",
    "gn:admin2_code":"29.0",
    "gn:asciiname":"Boca de Arroyo",
    "gn:country_code":"MX",
    "gn:dem":399,
    "gn:feature_class":"P",
    "gn:feature_code":"PPL",
    "gn:name":"Boca de Arroyo",
    "gn:population":6,
    "gn:timezone":"America/Chihuahua",
    "iso:country":"MX",
    "wof:name":"Boca de Arroyo",
    "wof:placetype":"locality",
    "wof:population":6
},
  "geometry": {"coordinates":[-107.76931999999999,26.25495],"type":"Point"}
}