{
  "type": "Feature",
  "properties": {
    "gn:admin1_code":"30",
    "gn:admin2_code":"160.0",
    "gn:asciiname":"Las Flores",
    "gn:country_code":"MX",
    "gn:dem":61,
    "gn:feature_class":"P",
    "gn:feature_code":"PPL",
    "gn:name":"Las Flores",
    "gn:population":0,
    "gn:timezone":"America/Mexico_City",
    "iso:country":"MX",
    "name:spa_x_preferred":[
        "Las Flores"
    ],
    "name:spa_x_variant":[
        "El Mante"
    ],
    "wof:name":"Las Flores",
    "wof:placetype":"locality"
},
  "geometry": {"coordinates":[-97.82723,20.93066],"type":"Point"}
}