{
  "type": "Feature",
  "properties": {
    "gn:admin1_code":"13",
    "gn:admin2_code":"3.0",
    "gn:asciiname":"El Boxtha",
    "gn:country_code":"MX",
    "gn:dem":1971,
    "gn:feature_class":"P",
    "gn:feature_code":"PPL",
    "gn:name":"El Boxtha",
    "gn:population":0,
    "gn:timezone":"America/Mexico_City",
    "iso:country":"MX",
    "name:spa_x_preferred":[
        "El Boxtha"
    ],
    "name:und_x_variant":[
        "Boxhe",
        "Box\u00ed"
    ],
    "wof:name":"El Boxtha",
    "wof:placetype":"locality"
},
  "geometry": {"coordinates":[-98.97736999999999,20.2572],"type":"Point"}
}