{
  "type": "Feature",
  "properties": {
    "gn:admin1_code":"5",
    "gn:admin2_code":"27.0",
    "gn:asciiname":"Playa Vista",
    "gn:country_code":"MX",
    "gn:dem":439,
    "gn:feature_class":"P",
    "gn:feature_code":"PPL",
    "gn:name":"Playa Vista",
    "gn:population":0,
    "gn:timezone":"America/Mexico_City",
    "iso:country":"MX",
    "name:spa_x_preferred":[
        "Playa Vista"
    ],
    "wof:name":"Playa Vista",
    "wof:placetype":"locality"
},
  "geometry": {"coordinates":[-93.03484,16.71691],"type":"Point"}
}