{
  "type": "Feature",
  "properties": {
    "gn:admin1_code":"29.0",
    "gn:admin2_code":"13.0",
    "gn:asciiname":"Colonia Agricola San Martin Notario",
    "gn:country_code":"MX",
    "gn:dem":2452,
    "gn:feature_class":"P",
    "gn:feature_code":"PPL",
    "gn:name":"Colonia Agr\u00edcola San Mart\u00edn Notario",
    "gn:population":0,
    "gn:timezone":"America/Mexico_City",
    "iso:country":"MX",
    "name:spa_x_preferred":[
        "Colonia Agr\u00edcola San Mart\u00edn Notario"
    ],
    "wof:name":"Colonia Agricola San Martin Notario",
    "wof:placetype":"locality"
},
  "geometry": {"coordinates":[-97.91876000000001,19.34796],"type":"Point"}
}