{
  "type": "Feature",
  "properties": {
    "gn:admin1_code":"6",
    "gn:admin2_code":"7.0",
    "gn:asciiname":"Los Lirios",
    "gn:country_code":"MX",
    "gn:dem":2600,
    "gn:feature_class":"P",
    "gn:feature_code":"PPL",
    "gn:name":"Los Lirios",
    "gn:population":0,
    "gn:timezone":"America/Chihuahua",
    "iso:country":"MX",
    "name:spa_x_preferred":[
        "Los Lirios"
    ],
    "name:und_x_variant":[
        "Rancho Los Lirios"
    ],
    "wof:name":"Los Lirios",
    "wof:placetype":"locality"
},
  "geometry": {"coordinates":[-106.45177,26.28139],"type":"Point"}
}