{
  "type": "Feature",
  "properties": {
    "gn:admin1_code":"5",
    "gn:admin2_code":"46.0",
    "gn:asciiname":"El Girasol",
    "gn:country_code":"MX",
    "gn:dem":671,
    "gn:feature_class":"P",
    "gn:feature_code":"PPL",
    "gn:name":"El Girasol",
    "gn:population":7,
    "gn:timezone":"America/Mexico_City",
    "iso:country":"MX",
    "wof:name":"El Girasol",
    "wof:placetype":"locality",
    "wof:population":7
},
  "geometry": {"coordinates":[-93.67889,16.39389],"type":"Point"}
}