{
  "type": "Feature",
  "properties": {
    "gn:admin1_code":"20",
    "gn:admin2_code":"500.0",
    "gn:asciiname":"Imperio",
    "gn:country_code":"MX",
    "gn:dem":2310,
    "gn:feature_class":"P",
    "gn:feature_code":"PPL",
    "gn:name":"Imperio",
    "gn:population":567,
    "gn:timezone":"America/Mexico_City",
    "iso:country":"MX",
    "name:deu_x_preferred":[
        "Imperio"
    ],
    "name:por_x_preferred":[
        "Imp\u00e9rio"
    ],
    "name:spa_x_preferred":[
        "Imperio"
    ],
    "wof:name":"Imperio",
    "wof:placetype":"locality",
    "wof:population":567
},
  "geometry": {"coordinates":[-97.59721999999999,16.91722],"type":"Point"}
}