{
  "type": "Feature",
  "properties": {
    "gn:admin1_code":"18.0",
    "gn:admin2_code":"10.0",
    "gn:asciiname":"Llano del Tigre",
    "gn:country_code":"MX",
    "gn:dem":8,
    "gn:feature_class":"P",
    "gn:feature_code":"PPL",
    "gn:name":"Llano del Tigre",
    "gn:population":0,
    "gn:timezone":"America/Mazatlan",
    "iso:country":"MX",
    "name:spa_x_preferred":[
        "Llano del Tigre"
    ],
    "wof:name":"Llano del Tigre",
    "wof:placetype":"locality"
},
  "geometry": {"coordinates":[-105.30580999999999,22.12707],"type":"Point"}
}