{
  "type": "Feature",
  "properties": {
    "gn:admin1_code":"5",
    "gn:admin2_code":"78.0",
    "gn:asciiname":"Unidad Habitacional 31 ZM",
    "gn:country_code":"MX",
    "gn:dem":2325,
    "gn:feature_class":"P",
    "gn:feature_code":"PPL",
    "gn:name":"Unidad Habitacional 31 ZM",
    "gn:population":478,
    "gn:timezone":"America/Mexico_City",
    "iso:country":"MX",
    "wof:name":"Unidad Habitacional 31 ZM",
    "wof:placetype":"locality",
    "wof:population":478
},
  "geometry": {"coordinates":[-92.56861000000001,16.66806],"type":"Point"}
}