{
  "type": "Feature",
  "properties": {
    "gn:admin1_code":"28.0",
    "gn:admin2_code":"18.0",
    "gn:asciiname":"El Ruidoso",
    "gn:country_code":"MX",
    "gn:dem":89,
    "gn:feature_class":"P",
    "gn:feature_code":"PPL",
    "gn:name":"El Ruidoso",
    "gn:population":4,
    "gn:timezone":"America/Monterrey",
    "iso:country":"MX",
    "name:spa_x_preferred":[
        "El Ruidoso"
    ],
    "wof:name":"El Ruidoso",
    "wof:placetype":"locality",
    "wof:population":4
},
  "geometry": {"coordinates":[-98.44278,24.15917],"type":"Point"}
}