{
  "type": "Feature",
  "properties": {
    "gn:admin1_code":"19.0",
    "gn:admin2_code":"5.0",
    "gn:asciiname":"Jesus",
    "gn:country_code":"MX",
    "gn:dem":173,
    "gn:feature_class":"P",
    "gn:feature_code":"PPL",
    "gn:name":"Jes\u00fas",
    "gn:population":0,
    "gn:timezone":"America/Matamoros",
    "iso:country":"MX",
    "name:spa_x_preferred":[
        "Jes\u00fas"
    ],
    "wof:name":"Jesus",
    "wof:placetype":"locality"
},
  "geometry": {"coordinates":[-99.94526,27.18186],"type":"Point"}
}