{
  "type": "Feature",
  "properties": {
    "gn:admin1_code":"6",
    "gn:admin2_code":"66.0",
    "gn:asciiname":"Ocoviachi",
    "gn:country_code":"MX",
    "gn:dem":1459,
    "gn:feature_class":"P",
    "gn:feature_code":"PPL",
    "gn:name":"Ocoviachi",
    "gn:population":0,
    "gn:timezone":"America/Chihuahua",
    "iso:country":"MX",
    "name:spa_x_preferred":[
        "Ocoviachi"
    ],
    "name:und_x_variant":[
        "Ocobiachic",
        "Ocoviachic"
    ],
    "wof:name":"Ocoviachi",
    "wof:placetype":"locality"
},
  "geometry": {"coordinates":[-108.40825,27.81139000000001],"type":"Point"}
}