{
  "type": "Feature",
  "properties": {
    "gn:admin1_code":"15",
    "gn:admin2_code":"8",
    "gn:asciiname":"Las Pailas",
    "gn:country_code":"MX",
    "gn:dem":871,
    "gn:feature_class":"P",
    "gn:feature_code":"PPL",
    "gn:name":"Las Pailas",
    "gn:population":27,
    "gn:timezone":"America/Mexico_City",
    "iso:country":"MX",
    "wof:name":"Las Pailas",
    "wof:placetype":"locality",
    "wof:population":27
},
  "geometry": {"coordinates":[-100.32031000000001,18.66976],"type":"Point"}
}