{
  "type": "Feature",
  "properties": {
    "gn:admin1_code":"12.0",
    "gn:admin2_code":"34.0",
    "gn:asciiname":"La Tijera",
    "gn:country_code":"MX",
    "gn:dem":1334,
    "gn:feature_class":"P",
    "gn:feature_code":"PPL",
    "gn:name":"La Tijera",
    "gn:population":0,
    "gn:timezone":"America/Mexico_City",
    "iso:country":"MX",
    "name:spa_x_preferred":[
        "La Tijera"
    ],
    "wof:name":"La Tijera",
    "wof:placetype":"locality"
},
  "geometry": {"coordinates":[-99.31545,18.35791],"type":"Point"}
}