{
  "type": "Feature",
  "properties": {
    "gn:admin1_code":"6.0",
    "gn:admin2_code":"16.0",
    "gn:asciiname":"San Silvestre",
    "gn:country_code":"MX",
    "gn:dem":1196,
    "gn:feature_class":"P",
    "gn:feature_code":"PPL",
    "gn:name":"San Silvestre",
    "gn:population":0,
    "gn:timezone":"America/Chihuahua",
    "iso:country":"MX",
    "name:fra_x_preferred":[
        "San Silvestre"
    ],
    "name:glg_x_preferred":[
        "San Silvestre"
    ],
    "name:por_x_preferred":[
        "San Silvestre"
    ],
    "name:spa_x_preferred":[
        "San Silvestre"
    ],
    "name:srp_x_preferred":[
        "\u0421\u0430\u043d \u0421\u0438\u043b\u0432\u0435\u0441\u0442\u0440\u0435"
    ],
    "name:tgl_x_preferred":[
        "San Silvestre"
    ],
    "wof:name":"San Silvestre",
    "wof:placetype":"locality"
},
  "geometry": {"coordinates":[-105.1867,27.93769],"type":"Point"}
}