{
  "type": "Feature",
  "properties": {
    "gn:admin1_code":"30",
    "gn:admin2_code":"201.0",
    "gn:asciiname":"Choapa",
    "gn:country_code":"MX",
    "gn:dem":904,
    "gn:feature_class":"P",
    "gn:feature_code":"PPL",
    "gn:name":"Choapa",
    "gn:population":726,
    "gn:timezone":"America/Mexico_City",
    "iso:country":"MX",
    "wof:name":"Choapa",
    "wof:placetype":"locality",
    "wof:population":726
},
  "geometry": {"coordinates":[-96.96222,18.73611],"type":"Point"}
}