{
  "type": "Feature",
  "properties": {
    "gn:admin1_code":"6",
    "gn:admin2_code":"62.0",
    "gn:asciiname":"La Frontera",
    "gn:country_code":"MX",
    "gn:dem":1179,
    "gn:feature_class":"P",
    "gn:feature_code":"PPL",
    "gn:name":"La Frontera",
    "gn:population":0,
    "gn:timezone":"America/Chihuahua",
    "iso:country":"MX",
    "name:spa_x_preferred":[
        "La Frontera"
    ],
    "wof:name":"La Frontera",
    "wof:placetype":"locality"
},
  "geometry": {"coordinates":[-105.27741,28.03917],"type":"Point"}
}