{
  "type": "Feature",
  "properties": {
    "gn:admin1_code":"5",
    "gn:admin2_code":"71.0",
    "gn:asciiname":"Zapote Mocho",
    "gn:country_code":"MX",
    "gn:dem":123,
    "gn:feature_class":"P",
    "gn:feature_code":"PPL",
    "gn:name":"Zapote Mocho",
    "gn:population":76,
    "gn:timezone":"America/Mexico_City",
    "iso:country":"MX",
    "wof:name":"Zapote Mocho",
    "wof:placetype":"locality",
    "wof:population":76
},
  "geometry": {"coordinates":[-92.53179,15.24125],"type":"Point"}
}