{
  "type": "Feature",
  "properties": {
    "gn:admin1_code":"25.0",
    "gn:asciiname":"El Chupando",
    "gn:country_code":"MX",
    "gn:dem":387,
    "gn:feature_class":"P",
    "gn:feature_code":"PPL",
    "gn:name":"El Chupando",
    "gn:population":0,
    "gn:timezone":"America/Mazatlan",
    "iso:country":"MX",
    "name:spa_x_preferred":[
        "El Chupando"
    ],
    "wof:name":"El Chupando",
    "wof:placetype":"locality"
},
  "geometry": {"coordinates":[-106.83665999999999,24.67548],"type":"Point"}
}