{
  "type": "Feature",
  "properties": {
    "gn:admin1_code":"6",
    "gn:admin2_code":"52",
    "gn:asciiname":"Ejido Toribio Ortega (Kilometro Cinco)",
    "gn:country_code":"MX",
    "gn:dem":825,
    "gn:feature_class":"P",
    "gn:feature_code":"PPL",
    "gn:name":"Ejido Toribio Ortega (Kil\u00f3metro Cinco)",
    "gn:population":47,
    "gn:timezone":"America/Ojinaga",
    "iso:country":"MX",
    "name:und_x_variant":[
        "Ejido Toribio Ortega (Kil\u00f3metro Cinco)"
    ],
    "wof:name":"Ejido Toribio Ortega (Kilometro Cinco)",
    "wof:placetype":"locality",
    "wof:population":47
},
  "geometry": {"coordinates":[-104.42381,29.52129],"type":"Point"}
}