{
  "type": "Feature",
  "properties": {
    "gn:admin1_code":"28.0",
    "gn:admin2_code":"8.0",
    "gn:asciiname":"Los Vergeles",
    "gn:country_code":"MX",
    "gn:dem":180,
    "gn:feature_class":"P",
    "gn:feature_code":"PPL",
    "gn:name":"Los Vergeles",
    "gn:population":1,
    "gn:timezone":"America/Monterrey",
    "iso:country":"MX",
    "name:spa_x_preferred":[
        "Los Vergeles"
    ],
    "wof:name":"Los Vergeles",
    "wof:placetype":"locality",
    "wof:population":1
},
  "geometry": {"coordinates":[-98.7975,23.52639],"type":"Point"}
}