{
  "type": "Feature",
  "properties": {
    "gn:admin1_code":"12",
    "gn:admin2_code":"35",
    "gn:asciiname":"Colonia del Angel",
    "gn:country_code":"MX",
    "gn:dem":800,
    "gn:feature_class":"P",
    "gn:feature_code":"PPL",
    "gn:name":"Colonia del \u00c1ngel",
    "gn:population":22,
    "gn:timezone":"America/Mexico_City",
    "iso:country":"MX",
    "name:und_x_variant":[
        "Colonia del \u00c1ngel"
    ],
    "wof:name":"Colonia del Angel",
    "wof:placetype":"locality",
    "wof:population":22
},
  "geometry": {"coordinates":[-99.526,18.37754],"type":"Point"}
}