{
  "type": "Feature",
  "properties": {
    "gn:admin1_code":"26.0",
    "gn:admin2_code":"64.0",
    "gn:asciiname":"Alamito",
    "gn:cc2":"MX",
    "gn:country_code":"MX",
    "gn:dem":505,
    "gn:feature_class":"P",
    "gn:feature_code":"PPL",
    "gn:name":"Alamito",
    "gn:population":0,
    "gn:timezone":"America/Hermosillo",
    "iso:country":"MX",
    "name:und_x_variant":[
        "El Alamito",
        "Alamito"
    ],
    "wof:name":"Alamito",
    "wof:placetype":"locality"
},
  "geometry": {"coordinates":[-111.51667,30.41667],"type":"Point"}
}