{
  "type": "Feature",
  "properties": {
    "gn:admin1_code":"32",
    "gn:admin2_code":"24",
    "gn:asciiname":"El Cajetillo",
    "gn:country_code":"MX",
    "gn:dem":2144,
    "gn:feature_class":"P",
    "gn:feature_code":"PPL",
    "gn:name":"El Cajetillo",
    "gn:population":13,
    "gn:timezone":"America/Mexico_City",
    "iso:country":"MX",
    "wof:name":"El Cajetillo",
    "wof:placetype":"locality",
    "wof:population":13
},
  "geometry": {"coordinates":[-101.79917,22.29333],"type":"Point"}
}