{
  "type": "Feature",
  "properties": {
    "gn:admin1_code":"7.0",
    "gn:admin2_code":"8.0",
    "gn:asciiname":"Ejido Veintinueve de Noviembre",
    "gn:country_code":"MX",
    "gn:dem":567,
    "gn:feature_class":"P",
    "gn:feature_code":"PPL",
    "gn:name":"Ejido Veintinueve de Noviembre",
    "gn:population":0,
    "gn:timezone":"America/Monterrey",
    "iso:country":"MX",
    "wof:name":"Ejido Veintinueve de Noviembre",
    "wof:placetype":"locality"
},
  "geometry": {"coordinates":[-101.46666999999999,27.43333],"type":"Point"}
}