{
  "type": "Feature",
  "properties": {
    "gn:admin1_code":"6",
    "gn:admin2_code":"51",
    "gn:asciiname":"La Lampara",
    "gn:country_code":"MX",
    "gn:dem":2329,
    "gn:feature_class":"P",
    "gn:feature_code":"PPL",
    "gn:name":"La L\u00e1mpara",
    "gn:population":11,
    "gn:timezone":"America/Chihuahua",
    "iso:country":"MX",
    "name:und_x_variant":[
        "La L\u00e1mpara"
    ],
    "wof:name":"La Lampara",
    "wof:placetype":"locality",
    "wof:population":11
},
  "geometry": {"coordinates":[-107.94189,28.06491],"type":"Point"}
}