{
  "type": "Feature",
  "properties": {
    "gn:admin1_code":"19",
    "gn:admin2_code":"33.0",
    "gn:asciiname":"Mucho Gusto",
    "gn:country_code":"MX",
    "gn:dem":368,
    "gn:feature_class":"P",
    "gn:feature_code":"PPL",
    "gn:name":"Mucho Gusto",
    "gn:population":0,
    "gn:timezone":"America/Monterrey",
    "iso:country":"MX",
    "name:swe_x_preferred":[
        "Mucho gusto"
    ],
    "name:und_x_variant":[
        "Rancho Mucho Gusto",
        "Mucho Gusto"
    ],
    "wof:name":"Mucho Gusto",
    "wof:placetype":"locality"
},
  "geometry": {"coordinates":[-99.52889,24.76298],"type":"Point"}
}