{
  "type": "Feature",
  "properties": {
    "gn:admin1_code":"11.0",
    "gn:admin2_code":"23.0",
    "gn:asciiname":"Dique Alto de Corralejo",
    "gn:country_code":"MX",
    "gn:dem":1687,
    "gn:feature_class":"P",
    "gn:feature_code":"PPL",
    "gn:name":"Dique Alto de Corralejo",
    "gn:population":12,
    "gn:timezone":"America/Mexico_City",
    "iso:country":"MX",
    "wof:name":"Dique Alto de Corralejo",
    "wof:placetype":"locality",
    "wof:population":12
},
  "geometry": {"coordinates":[-101.60805999999999,20.50806],"type":"Point"}
}