{
  "type": "Feature",
  "properties": {
    "gn:admin1_code":"30",
    "gn:admin2_code":"81",
    "gn:asciiname":"Timbral Axupanapa",
    "gn:country_code":"MX",
    "gn:dem":1417,
    "gn:feature_class":"P",
    "gn:feature_code":"PPL",
    "gn:name":"Timbral Axupanapa",
    "gn:population":13,
    "gn:timezone":"America/Mexico_City",
    "iso:country":"MX",
    "wof:name":"Timbral Axupanapa",
    "wof:placetype":"locality",
    "wof:population":13
},
  "geometry": {"coordinates":[-97.14833,18.88917],"type":"Point"}
}