{
  "type": "Feature",
  "properties": {
    "gn:admin1_code":"28",
    "gn:admin2_code":"14.0",
    "gn:asciiname":"El Venadito",
    "gn:country_code":"MX",
    "gn:dem":163,
    "gn:feature_class":"P",
    "gn:feature_code":"PPL",
    "gn:name":"El Venadito",
    "gn:population":0,
    "gn:timezone":"America/Matamoros",
    "iso:country":"MX",
    "name:spa_x_preferred":[
        "El Venadito"
    ],
    "name:und_x_variant":[
        "Rancho El Venadito"
    ],
    "wof:name":"El Venadito",
    "wof:placetype":"locality"
},
  "geometry": {"coordinates":[-99.72114999999999,27.28622],"type":"Point"}
}