{
  "type": "Feature",
  "properties": {
    "gn:admin1_code":"18",
    "gn:admin2_code":"5",
    "gn:asciiname":"El Pantano",
    "gn:country_code":"MX",
    "gn:dem":565,
    "gn:feature_class":"P",
    "gn:feature_code":"PPL",
    "gn:name":"El Pantano",
    "gn:population":13,
    "gn:timezone":"America/Mazatlan",
    "iso:country":"MX",
    "name:ita_x_preferred":[
        "El Pantano"
    ],
    "name:spa_x_preferred":[
        "El Pantano"
    ],
    "name:zho_x_preferred":[
        "\u57c3\u5c14\u6f58\u5854\u8bfa"
    ],
    "wof:name":"El Pantano",
    "wof:placetype":"locality",
    "wof:population":13
},
  "geometry": {"coordinates":[-105.22889000000001,22.72694],"type":"Point"}
}