{
  "type": "Feature",
  "properties": {
    "gn:admin1_code":"10",
    "gn:admin2_code":"5.0",
    "gn:asciiname":"El Tunal",
    "gn:country_code":"MX",
    "gn:dem":1906,
    "gn:feature_class":"P",
    "gn:feature_code":"PPL",
    "gn:name":"El Tunal",
    "gn:population":0,
    "gn:timezone":"America/Monterrey",
    "iso:country":"MX",
    "name:spa_x_preferred":[
        "El Tunal"
    ],
    "name:und_x_variant":[
        "Tunal"
    ],
    "wof:name":"El Tunal",
    "wof:placetype":"locality"
},
  "geometry": {"coordinates":[-104.71407000000001,23.96224],"type":"Point"}
}