{
  "type": "Feature",
  "properties": {
    "gn:admin1_code":"16",
    "gn:admin2_code":"61.0",
    "gn:asciiname":"Cieneguillas",
    "gn:country_code":"MX",
    "gn:dem":2656,
    "gn:feature_class":"P",
    "gn:feature_code":"PPL",
    "gn:name":"Cieneguillas",
    "gn:population":601,
    "gn:timezone":"America/Mexico_City",
    "iso:country":"MX",
    "wof:name":"Cieneguillas",
    "wof:placetype":"locality",
    "wof:population":601
},
  "geometry": {"coordinates":[-100.30389,19.57917],"type":"Point"}
}