{
  "type": "Feature",
  "properties": {
    "gn:admin1_code":"5.0",
    "gn:asciiname":"La Argentina Dos",
    "gn:country_code":"MX",
    "gn:dem":22,
    "gn:feature_class":"P",
    "gn:feature_code":"PPL",
    "gn:name":"La Argentina Dos",
    "gn:population":0,
    "gn:timezone":"America/Mexico_City",
    "iso:country":"MX",
    "name:spa_x_preferred":[
        "La Argentina Dos"
    ],
    "wof:name":"La Argentina Dos",
    "wof:placetype":"locality"
},
  "geometry": {"coordinates":[-93.44803,15.81399],"type":"Point"}
}