{
  "type": "Feature",
  "properties": {
    "gn:admin1_code":"18",
    "gn:admin2_code":"15.0",
    "gn:asciiname":"Pantano Grande",
    "gn:country_code":"MX",
    "gn:dem":44,
    "gn:feature_class":"P",
    "gn:feature_code":"PPL",
    "gn:name":"Pantano Grande",
    "gn:population":0,
    "gn:timezone":"America/Mazatlan",
    "iso:country":"MX",
    "name:spa_x_preferred":[
        "Pantano Grande"
    ],
    "wof:name":"Pantano Grande",
    "wof:placetype":"locality"
},
  "geometry": {"coordinates":[-105.1352,21.8635],"type":"Point"}
}