{
  "type": "Feature",
  "properties": {
    "gn:admin1_code":"18",
    "gn:admin2_code":"15.0",
    "gn:asciiname":"Pantano Grande",
    "gn:country_code":"MX",
    "gn:dem":44,
    "gn:feature_class":"P",
    "gn:feature_code":"PPL",
    "gn:name":"Pantano Grande",
    "gn:population":0,
    "gn:timezone":"America/Mazatlan",
    "iso:country":"MX",
    "name:bpy_x_preferred":[
        "\u09aa\u09be\u09a8\u09cd\u099f\u09be\u09a8\u09cb \u0997\u09cd\u09b0\u09be\u09a8\u09cd\u09a1\u09c7"
    ],
    "name:epo_x_preferred":[
        "Pantano Grande"
    ],
    "name:eus_x_preferred":[
        "Pantano Grande"
    ],
    "name:fra_x_preferred":[
        "Pantano Grande"
    ],
    "name:ita_x_preferred":[
        "Pantano Grande"
    ],
    "name:kaz_x_preferred":[
        "\u041f\u0430\u043d\u0442\u0430\u043d\u0443-\u0413\u0440\u0430\u043d\u0434\u0438"
    ],
    "name:mlg_x_preferred":[
        "Pantano Grande"
    ],
    "name:nld_x_preferred":[
        "Pantano Grande"
    ],
    "name:nor_x_preferred":[
        "Pantano Grande"
    ],
    "name:pol_x_preferred":[
        "Pantano Grande"
    ],
    "name:por_x_preferred":[
        "Pantano Grande"
    ],
    "name:ron_x_preferred":[
        "P\u00e2ntano Grande"
    ],
    "name:rus_x_preferred":[
        "\u041f\u0430\u043d\u0442\u0430\u043d\u0443-\u0413\u0440\u0430\u043d\u0434\u0438"
    ],
    "name:spa_x_preferred":[
        "Pantano Grande"
    ],
    "name:vie_x_preferred":[
        "Pantano Grande"
    ],
    "name:vol_x_preferred":[
        "Pantano Grande"
    ],
    "name:war_x_preferred":[
        "Pantano Grande"
    ],
    "name:zho_x_preferred":[
        "\u5927\u6f58\u5854\u52aa"
    ],
    "wof:name":"Pantano Grande",
    "wof:placetype":"locality"
},
  "geometry": {"coordinates":[-105.1352,21.8635],"type":"Point"}
}