{
  "type": "Feature",
  "properties": {
    "gn:admin1_code":"6",
    "gn:admin2_code":"46.0",
    "gn:asciiname":"El Tablon",
    "gn:country_code":"MX",
    "gn:dem":1704,
    "gn:feature_class":"P",
    "gn:feature_code":"PPL",
    "gn:name":"El Tabl\u00f3n",
    "gn:population":394,
    "gn:timezone":"America/Chihuahua",
    "iso:country":"MX",
    "name:und_x_variant":[
        "El Tabl\u00f3n"
    ],
    "wof:name":"El Tablon",
    "wof:placetype":"locality",
    "wof:population":394
},
  "geometry": {"coordinates":[-107.81999999999999,26.50889],"type":"Point"}
}