{
  "type": "Feature",
  "properties": {
    "gn:admin1_code":"14",
    "gn:admin2_code":"53.0",
    "gn:asciiname":"Primero de Mayo (Chupaderos)",
    "gn:country_code":"MX",
    "gn:dem":1916,
    "gn:feature_class":"P",
    "gn:feature_code":"PPL",
    "gn:name":"Primero de Mayo (Chupaderos)",
    "gn:population":1210,
    "gn:timezone":"America/Mexico_City",
    "iso:country":"MX",
    "wof:name":"Primero de Mayo (Chupaderos)",
    "wof:placetype":"locality",
    "wof:population":1210
},
  "geometry": {"coordinates":[-101.82722,21.46611],"type":"Point"}
}