{
  "type": "Feature",
  "properties": {
    "gn:admin1_code":"14",
    "gn:admin2_code":"58",
    "gn:asciiname":"San Ignacio",
    "gn:country_code":"MX",
    "gn:dem":1231,
    "gn:feature_class":"P",
    "gn:feature_code":"PPL",
    "gn:name":"San Ignacio",
    "gn:population":37,
    "gn:timezone":"America/Mexico_City",
    "iso:country":"MX",
    "wof:name":"San Ignacio",
    "wof:placetype":"locality",
    "wof:population":37
},
  "geometry": {"coordinates":[-104.83111,20.56444],"type":"Point"}
}