{
  "type": "Feature",
  "properties": {
    "gn:admin1_code":"4",
    "gn:admin2_code":"11",
    "gn:asciiname":"Ignacio Zaragoza (Pulguero)",
    "gn:country_code":"MX",
    "gn:dem":45,
    "gn:feature_class":"P",
    "gn:feature_code":"PPL",
    "gn:name":"Ignacio Zaragoza (Pulguero)",
    "gn:population":9,
    "gn:timezone":"America/Merida",
    "iso:country":"MX",
    "wof:name":"Ignacio Zaragoza (Pulguero)",
    "wof:placetype":"locality",
    "wof:population":9
},
  "geometry": {"coordinates":[-90.59778,18.18389],"type":"Point"}
}