{
  "type": "Feature",
  "properties": {
    "gn:admin1_code":"24.0",
    "gn:admin2_code":"2.0",
    "gn:asciiname":"Nogales",
    "gn:country_code":"MX",
    "gn:dem":1383,
    "gn:feature_class":"P",
    "gn:feature_code":"PPL",
    "gn:name":"Nogales",
    "gn:population":24,
    "gn:timezone":"America/Mexico_City",
    "iso:country":"MX",
    "name:ben_x_preferred":[
        "\u09a8\u09cb\u0997\u09be\u09b2\u09c7\u09b8"
    ],
    "name:cat_x_preferred":[
        "Nogales"
    ],
    "name:ceb_x_preferred":[
        "Nogales"
    ],
    "name:ces_x_preferred":[
        "Nogales"
    ],
    "name:deu_x_preferred":[
        "Nogales"
    ],
    "name:epo_x_preferred":[
        "Nogales"
    ],
    "name:est_x_preferred":[
        "Nogales"
    ],
    "name:eus_x_preferred":[
        "Nogales"
    ],
    "name:fra_x_preferred":[
        "Nogales"
    ],
    "name:glg_x_preferred":[
        "Nogales"
    ],
    "name:heb_x_preferred":[
        "\u05e0\u05d5\u05d2\u05dc\u05e1"
    ],
    "name:hin_x_preferred":[
        "\u0928\u094b\u0917\u093e\u0932\u0947\u0938"
    ],
    "name:hun_x_preferred":[
        "Nogales"
    ],
    "name:ita_x_preferred":[
        "Nogales"
    ],
    "name:jpn_x_preferred":[
        "\u30ce\u30ac\u30fc\u30ec\u30b9"
    ],
    "name:kor_x_preferred":[
        "\ub178\uac08\ub808\uc2a4"
    ],
    "name:lit_x_preferred":[
        "Nogalesas"
    ],
    "name:msa_x_preferred":[
        "Nogales"
    ],
    "name:nld_x_preferred":[
        "Nogales"
    ],
    "name:nor_x_preferred":[
        "Nogales"
    ],
    "name:pol_x_preferred":[
        "Nogales"
    ],
    "name:por_x_preferred":[
        "Nogales"
    ],
    "name:rus_x_preferred":[
        "\u041d\u043e\u0433\u0430\u043b\u0435\u0441"
    ],
    "name:sco_x_preferred":[
        "Nogales"
    ],
    "name:spa_x_preferred":[
        "Nogales"
    ],
    "name:srp_x_preferred":[
        "\u041d\u043e\u0433\u0430\u043b\u0435\u0441"
    ],
    "name:swe_x_preferred":[
        "Nogales"
    ],
    "name:urd_x_preferred":[
        "\u0646\u0648\u06af\u0627\u0644\u06cc\u0632"
    ],
    "name:vie_x_preferred":[
        "Nogales"
    ],
    "name:war_x_preferred":[
        "Nogales"
    ],
    "wof:name":"Nogales",
    "wof:placetype":"locality",
    "wof:population":24
},
  "geometry": {"coordinates":[-99.55139,22.15528],"type":"Point"}
}