{
  "type": "Feature",
  "properties": {
    "gn:admin1_code":"24.0",
    "gn:admin2_code":"2.0",
    "gn:asciiname":"Nogales",
    "gn:country_code":"MX",
    "gn:dem":1383,
    "gn:feature_class":"P",
    "gn:feature_code":"PPL",
    "gn:name":"Nogales",
    "gn:population":24,
    "gn:timezone":"America/Mexico_City",
    "iso:country":"MX",
    "name:spa_x_preferred":[
        "Nogales"
    ],
    "wof:name":"Nogales",
    "wof:placetype":"locality",
    "wof:population":24
},
  "geometry": {"coordinates":[-99.55139,22.15528],"type":"Point"}
}