{
  "type": "Feature",
  "properties": {
    "gn:admin1_code":"14.0",
    "gn:admin2_code":"92.0",
    "gn:asciiname":"Huejotitlan",
    "gn:country_code":"MX",
    "gn:dem":1753,
    "gn:feature_class":"P",
    "gn:feature_code":"PPL",
    "gn:name":"Huejotitl\u00e1n",
    "gn:population":0,
    "gn:timezone":"America/Mexico_City",
    "iso:country":"MX",
    "wof:name":"Huejotitlan",
    "wof:placetype":"locality"
},
  "geometry": {"coordinates":[-103.33701000000001,20.05286],"type":"Point"}
}