{
  "type": "Feature",
  "properties": {
    "gn:admin1_code":"27",
    "gn:admin2_code":"1.0",
    "gn:asciiname":"La Camaronera",
    "gn:country_code":"MX",
    "gn:dem":40,
    "gn:feature_class":"P",
    "gn:feature_code":"PPL",
    "gn:name":"La Camaronera",
    "gn:population":8,
    "gn:timezone":"America/Mexico_City",
    "iso:country":"MX",
    "name:spa_x_preferred":[
        "Agua Fr\u00eda"
    ],
    "name:spa_x_variant":[
        "La Camaronera"
    ],
    "wof:name":"La Camaronera",
    "wof:placetype":"locality",
    "wof:population":8
},
  "geometry": {"coordinates":[-91.29443999999999,17.62056],"type":"Point"}
}