{
  "type": "Feature",
  "properties": {
    "gn:admin1_code":"13",
    "gn:admin2_code":"28.0",
    "gn:asciiname":"Tetzacuatl",
    "gn:country_code":"MX",
    "gn:dem":283,
    "gn:feature_class":"P",
    "gn:feature_code":"PPL",
    "gn:name":"Tetzacuatl",
    "gn:population":0,
    "gn:timezone":"America/Mexico_City",
    "iso:country":"MX",
    "name:spa_x_preferred":[
        "Tetzacuatl"
    ],
    "wof:name":"Tetzacuatl",
    "wof:placetype":"locality"
},
  "geometry": {"coordinates":[-98.48097,21.08841],"type":"Point"}
}