{
  "type": "Feature",
  "properties": {
    "gn:admin1_code":"28",
    "gn:admin2_code":"1.0",
    "gn:asciiname":"Nicolas Bravo",
    "gn:country_code":"MX",
    "gn:dem":51,
    "gn:feature_class":"P",
    "gn:feature_code":"PPL",
    "gn:name":"Nicol\u00e1s Bravo",
    "gn:population":0,
    "gn:timezone":"America/Monterrey",
    "iso:country":"MX",
    "name:spa_x_preferred":[
        "Nicol\u00e1s Bravo"
    ],
    "name:spa_x_variant":[
        "Palo Alto"
    ],
    "wof:name":"Nicolas Bravo",
    "wof:placetype":"locality"
},
  "geometry": {"coordinates":[-98.25927,24.0018],"type":"Point"}
}