{
  "type": "Feature",
  "properties": {
    "gn:admin1_code":"7",
    "gn:admin2_code":"8.0",
    "gn:asciiname":"Ramon Daniel Sanchez",
    "gn:country_code":"MX",
    "gn:dem":442,
    "gn:feature_class":"P",
    "gn:feature_code":"PPL",
    "gn:name":"Ram\u00f3n Daniel S\u00e1nchez",
    "gn:population":4,
    "gn:timezone":"America/Monterrey",
    "iso:country":"MX",
    "name:und_x_variant":[
        "Ram\u00f3n Daniel S\u00e1nchez"
    ],
    "wof:name":"Ramon Daniel Sanchez",
    "wof:placetype":"locality",
    "wof:population":4
},
  "geometry": {"coordinates":[-101.41759,27.22055],"type":"Point"}
}