{
  "type": "Feature",
  "properties": {
    "gn:admin1_code":"7",
    "gn:admin2_code":"28.0",
    "gn:asciiname":"Ricardo Chavarria",
    "gn:country_code":"MX",
    "gn:dem":338,
    "gn:feature_class":"P",
    "gn:feature_code":"PPL",
    "gn:name":"Ricardo Chavarr\u00eda",
    "gn:population":6,
    "gn:timezone":"America/Monterrey",
    "iso:country":"MX",
    "name:und_x_variant":[
        "Ricardo Chavarr\u00eda"
    ],
    "wof:name":"Ricardo Chavarria",
    "wof:placetype":"locality",
    "wof:population":6
},
  "geometry": {"coordinates":[-101.11897,27.82027],"type":"Point"}
}