{
  "type": "Feature",
  "properties": {
    "gn:admin1_code":"18",
    "gn:admin2_code":"11.0",
    "gn:asciiname":"Presidio de los Reyes",
    "gn:country_code":"MX",
    "gn:dem":98,
    "gn:feature_class":"P",
    "gn:feature_code":"PPL",
    "gn:name":"Presidio de los Reyes",
    "gn:population":832,
    "gn:timezone":"America/Mazatlan",
    "iso:country":"MX",
    "wof:name":"Presidio de los Reyes",
    "wof:placetype":"locality",
    "wof:population":832
},
  "geometry": {"coordinates":[-104.92749999999999,22.03806],"type":"Point"}
}