{
  "type": "Feature",
  "properties": {
    "gn:admin1_code":"6.0",
    "gn:admin2_code":"52.0",
    "gn:asciiname":"Saburniaga",
    "gn:country_code":"MX",
    "gn:dem":819,
    "gn:feature_class":"P",
    "gn:feature_code":"PPL",
    "gn:name":"Saburniaga",
    "gn:population":20,
    "gn:timezone":"America/Ojinaga",
    "iso:country":"MX",
    "name:spa_x_preferred":[
        "Saburniaga"
    ],
    "wof:name":"Saburniaga",
    "wof:placetype":"locality",
    "wof:population":20
},
  "geometry": {"coordinates":[-104.64465,29.5699],"type":"Point"}
}