{
  "type": "Feature",
  "properties": {
    "gn:admin1_code":"6",
    "gn:admin2_code":"40.0",
    "gn:asciiname":"Piedras Verdes",
    "gn:country_code":"MX",
    "gn:dem":2174,
    "gn:feature_class":"P",
    "gn:feature_code":"PPL",
    "gn:name":"Piedras Verdes",
    "gn:population":0,
    "gn:timezone":"America/Chihuahua",
    "iso:country":"MX",
    "name:spa_x_preferred":[
        "Piedras Verdes"
    ],
    "name:und_x_variant":[
        "Rancho Piedras Verdes"
    ],
    "wof:name":"Piedras Verdes",
    "wof:placetype":"locality"
},
  "geometry": {"coordinates":[-108.26430000000001,29.95294],"type":"Point"}
}