{
  "type": "Feature",
  "properties": {
    "gn:admin1_code":"11.0",
    "gn:admin2_code":"2.0",
    "gn:asciiname":"Cutaro",
    "gn:country_code":"MX",
    "gn:dem":1920,
    "gn:feature_class":"P",
    "gn:feature_code":"PPL",
    "gn:name":"C\u00fataro",
    "gn:population":0,
    "gn:timezone":"America/Mexico_City",
    "iso:country":"MX",
    "name:spa_x_preferred":[
        "C\u00fataro"
    ],
    "wof:name":"Cutaro",
    "wof:placetype":"locality"
},
  "geometry": {"coordinates":[-100.84751,19.99632],"type":"Point"}
}