{
  "type": "Feature",
  "properties": {
    "gn:admin1_code":"26.0",
    "gn:admin2_code":"19.0",
    "gn:asciiname":"El Sauz",
    "gn:country_code":"MX",
    "gn:dem":1451,
    "gn:feature_class":"P",
    "gn:feature_code":"PPL",
    "gn:name":"El Sauz",
    "gn:population":0,
    "gn:timezone":"America/Hermosillo",
    "iso:country":"MX",
    "name:und_x_variant":[
        "El S\u00e1uz",
        "El Sauz"
    ],
    "wof:name":"El Sauz",
    "wof:placetype":"locality"
},
  "geometry": {"coordinates":[-110.06255,31.1465],"type":"Point"}
}