{
  "type": "Feature",
  "properties": {
    "gn:admin1_code":"28",
    "gn:admin2_code":"42.0",
    "gn:asciiname":"Ranchito",
    "gn:country_code":"MX",
    "gn:dem":350,
    "gn:feature_class":"P",
    "gn:feature_code":"PPL",
    "gn:name":"Ranchito",
    "gn:population":0,
    "gn:timezone":"America/Monterrey",
    "iso:country":"MX",
    "wof:name":"Ranchito",
    "wof:placetype":"locality"
},
  "geometry": {"coordinates":[-99.45332999999999,24.53167],"type":"Point"}
}