{
  "type": "Feature",
  "properties": {
    "gn:country":"MX",
    "gn:fcode":"PPL",
    "gn:population":0,
    "iso:country":"MX",
    "name:ara_x_preferred":[
        "\u0628\u064a\u0644\u0627 \u0641\u064a\u0633\u062a\u0627"
    ],
    "name:ben_x_preferred":[
        "\u09ac\u09c7\u09b2\u09cd\u09b2\u09be \u09ad\u09bf\u09b8\u09cd\u09a4\u09be"
    ],
    "name:cat_x_preferred":[
        "Bella Vista"
    ],
    "name:ceb_x_preferred":[
        "Bella Vista"
    ],
    "name:deu_x_preferred":[
        "Bella Vista"
    ],
    "name:ell_x_preferred":[
        "\u039c\u03c0\u03ad\u03bb\u03b1 \u0392\u03af\u03c3\u03c4\u03b1"
    ],
    "name:fas_x_preferred":[
        "\u0628\u0644\u0627 \u0648\u06cc\u0633\u062a\u0627"
    ],
    "name:heb_x_preferred":[
        "\u05d1\u05dc\u05d4 \u05d5\u05d5\u05d9\u05e1\u05d8\u05d4"
    ],
    "name:hin_x_preferred":[
        "\u092c\u0947\u0932\u093e \u0935\u093f\u0938\u094d\u091f\u093e"
    ],
    "name:hun_x_preferred":[
        "Bella Vista"
    ],
    "name:ind_x_preferred":[
        "Bella Vista"
    ],
    "name:ita_x_preferred":[
        "Bella Vista"
    ],
    "name:jpn_x_preferred":[
        "\u30d9\u30e9\u30d3\u30b9\u30bf"
    ],
    "name:kor_x_preferred":[
        "\ubca8\ub77c \ube44\uc2a4\ud0c0"
    ],
    "name:lit_x_preferred":[
        "Belja Vista"
    ],
    "name:nds_x_preferred":[
        "Bella Vista"
    ],
    "name:nld_x_preferred":[
        "Bella Vista"
    ],
    "name:pol_x_preferred":[
        "Bella Vista"
    ],
    "name:por_x_preferred":[
        "Bella Vista"
    ],
    "name:rus_x_preferred":[
        "\u0411\u0435\u043b\u044c\u044f-\u0412\u0438\u0441\u0442\u0430"
    ],
    "name:sco_x_preferred":[
        "Bella Vista"
    ],
    "name:slk_x_preferred":[
        "Bella Vista"
    ],
    "name:spa_x_preferred":[
        "Buenavista"
    ],
    "name:spa_x_variant":[
        "Bella Vista"
    ],
    "name:srp_x_preferred":[
        "\u0411\u0435\u043b\u0430 \u0412\u0438\u0441\u0442\u0430"
    ],
    "name:swe_x_preferred":[
        "Bella Vista"
    ],
    "name:tur_x_preferred":[
        "Bella Vista"
    ],
    "name:ukr_x_preferred":[
        "\u0411\u0435\u043b\u043b\u0430-\u0412\u0456\u0441\u0442\u0430"
    ],
    "name:urd_x_preferred":[
        "\u0628\u06cc\u0644\u0627 \u0648\u0633\u0679\u0627"
    ],
    "name:vie_x_preferred":[
        "Bella Vista"
    ],
    "name:vol_x_preferred":[
        "Bella Vista"
    ],
    "qs_pg:aaroncc":"MX",
    "qs_pg:gn_country":"MX",
    "qs_pg:gn_fcode":"PPL",
    "qs_pg:gn_pop":0,
    "qs_pg:name":"Bella Vista",
    "qs_pg:name_adm0":"M\u00e9xico",
    "qs_pg:name_adm1":"Sonora",
    "qs_pg:photos":3,
    "qs_pg:photos_1k":1,
    "qs_pg:photos_9k":1,
    "qs_pg:photos_9r":1,
    "qs_pg:photos_all":3,
    "qs_pg:photos_sr":1,
    "qs_pg:pop_sr":0,
    "qs_pg:qs_pg_placetype":"neighbourhood",
    "qs_pg:qs_pg_placetype_gp":"Suburb",
    "qs_pg:woe_adm0":23424900,
    "woe:adm0_id":23424900,
    "woe:name_adm0":"M\u00e9xico",
    "woe:name_adm1":"Sonora",
    "woe:placetype":"Suburb",
    "wof:name":"Bella Vista",
    "wof:placetype":"neighbourhood"
},
  "geometry": {"coordinates":[-110.19951,28.52648],"type":"Point"}
}