{
  "type": "Feature",
  "properties": {
    "gn:gn_country":"MX",
    "gn:gn_fcode":"PPL",
    "gn:gn_pop":0,
    "iso:country":"MX",
    "name:cat_x_preferred":[
        "Bella Vista"
    ],
    "name:ceb_x_preferred":[
        "Bella Vista"
    ],
    "name:deu_x_preferred":[
        "Bella Vista"
    ],
    "name:ita_x_preferred":[
        "Bella Vista"
    ],
    "name:lit_x_preferred":[
        "Belja Vista"
    ],
    "name:nds_x_preferred":[
        "Bella Vista"
    ],
    "name:nld_x_preferred":[
        "Bella Vista"
    ],
    "name:pol_x_preferred":[
        "Bella Vista"
    ],
    "name:por_x_preferred":[
        "Bella Vista"
    ],
    "name:rus_x_preferred":[
        "\u0411\u0435\u043b\u044c\u044f-\u0412\u0438\u0441\u0442\u0430"
    ],
    "name:sco_x_preferred":[
        "Bella Vista"
    ],
    "name:slk_x_preferred":[
        "Bella Vista"
    ],
    "name:spa_x_preferred":[
        "Buenavista"
    ],
    "name:spa_x_variant":[
        "Bella Vista"
    ],
    "name:srp_x_preferred":[
        "\u0411\u0435\u043b\u0430 \u0412\u0438\u0441\u0442\u0430"
    ],
    "name:swe_x_preferred":[
        "Bella Vista"
    ],
    "name:ukr_x_preferred":[
        "\u0411\u0435\u043b\u043b\u0430-\u0412\u0456\u0441\u0442\u0430"
    ],
    "name:vol_x_preferred":[
        "Bella Vista"
    ],
    "qs_pg:aaroncc":"MX",
    "qs_pg:gn_country":"MX",
    "qs_pg:gn_fcode":"PPL",
    "qs_pg:gn_pop":0,
    "qs_pg:name":"Bella Vista",
    "qs_pg:name_adm0":"M\u00e9xico",
    "qs_pg:name_adm1":"Sonora",
    "qs_pg:photos":3,
    "qs_pg:photos_1k":1,
    "qs_pg:photos_9k":1,
    "qs_pg:photos_9r":1,
    "qs_pg:photos_all":3,
    "qs_pg:photos_sr":1,
    "qs_pg:pop_sr":0,
    "qs_pg:qs_pg_placetype":"neighbourhood",
    "qs_pg:qs_pg_placetype_gp":"Suburb",
    "qs_pg:woe_adm0":23424900,
    "woe:adm0_id":23424900,
    "woe:name_adm0":"M\u00e9xico",
    "woe:name_adm1":"Sonora",
    "woe:placetype":"Suburb",
    "wof:name":"Bella Vista",
    "wof:placetype":"neighbourhood"
},
  "geometry": {"coordinates":[-110.19951,28.52648],"type":"Point"}
}