{
  "type": "Feature",
  "properties": {
    "gn:admin1_code":"7.0",
    "gn:admin2_code":"38.0",
    "gn:asciiname":"Minerva",
    "gn:country_code":"MX",
    "gn:dem":364,
    "gn:feature_class":"P",
    "gn:feature_code":"PPL",
    "gn:name":"Minerva",
    "gn:population":0,
    "gn:timezone":"America/Monterrey",
    "iso:country":"MX",
    "name:und_x_variant":[
        "Ejido Minerva",
        "Minerva"
    ],
    "wof:name":"Minerva",
    "wof:placetype":"locality"
},
  "geometry": {"coordinates":[-100.95449000000001,28.53462],"type":"Point"}
}