{
  "type": "Feature",
  "properties": {
    "gn:admin1_code":"6",
    "gn:admin2_code":"20.0",
    "gn:asciiname":"La Vinateria",
    "gn:country_code":"MX",
    "gn:dem":772,
    "gn:feature_class":"P",
    "gn:feature_code":"PPL",
    "gn:name":"La Vinateria",
    "gn:population":0,
    "gn:timezone":"America/Chihuahua",
    "iso:country":"MX",
    "name:spa_x_preferred":[
        "La Vinateria"
    ],
    "name:und_x_variant":[
        "Vuateria",
        "Vinater\u00eda"
    ],
    "wof:name":"La Vinateria",
    "wof:placetype":"locality"
},
  "geometry": {"coordinates":[-108.5646,27.56107],"type":"Point"}
}