{
  "type": "Feature",
  "properties": {
    "gn:admin1_code":"14",
    "gn:admin2_code":"8",
    "gn:asciiname":"El Chiquihuitillo",
    "gn:country_code":"MX",
    "gn:dem":2037,
    "gn:feature_class":"P",
    "gn:feature_code":"PPL",
    "gn:name":"El Chiquihuitillo",
    "gn:population":23,
    "gn:timezone":"America/Mexico_City",
    "iso:country":"MX",
    "wof:name":"El Chiquihuitillo",
    "wof:placetype":"locality",
    "wof:population":23
},
  "geometry": {"coordinates":[-102.3775,20.79583],"type":"Point"}
}