{
  "type": "Feature",
  "properties": {
    "gn:admin1_code":"14",
    "gn:admin2_code":"78.0",
    "gn:asciiname":"Sauz de los Ramirez",
    "gn:country_code":"MX",
    "gn:dem":1975,
    "gn:feature_class":"P",
    "gn:feature_code":"PPL",
    "gn:name":"Sauz de los Ram\u00edrez",
    "gn:population":12,
    "gn:timezone":"America/Mexico_City",
    "iso:country":"MX",
    "wof:name":"Sauz de los Ramirez",
    "wof:placetype":"locality",
    "wof:population":12
},
  "geometry": {"coordinates":[-102.24028,21.06806],"type":"Point"}
}