{
  "type": "Feature",
  "properties": {
    "gn:admin1_code":"16",
    "gn:admin2_code":"89.0",
    "gn:asciiname":"La Ordenita",
    "gn:country_code":"MX",
    "gn:dem":307,
    "gn:feature_class":"P",
    "gn:feature_code":"PPL",
    "gn:name":"La Orde\u00f1ita",
    "gn:population":139,
    "gn:timezone":"America/Mexico_City",
    "iso:country":"MX",
    "name:spa_x_preferred":[
        "La Orde\u00f1ita"
    ],
    "name:und_x_variant":[
        "La Orde\u00f1ita"
    ],
    "wof:name":"La Ordenita",
    "wof:placetype":"locality",
    "wof:population":139
},
  "geometry": {"coordinates":[-102.755,19.1425],"type":"Point"}
}