{
  "type": "Feature",
  "properties": {
    "gn:admin1_code":"5.0",
    "gn:admin2_code":"14.0",
    "gn:asciiname":"Pamalhuitz",
    "gn:country_code":"MX",
    "gn:dem":1239,
    "gn:feature_class":"P",
    "gn:feature_code":"PPL",
    "gn:name":"Pamalhuitz",
    "gn:population":0,
    "gn:timezone":"America/Mexico_City",
    "iso:country":"MX",
    "name:spa_x_preferred":[
        "Pamalhuitz"
    ],
    "wof:name":"Pamalhuitz",
    "wof:placetype":"locality"
},
  "geometry": {"coordinates":[-92.80553999999999,16.99162],"type":"Point"}
}