{
  "type": "Feature",
  "properties": {
    "gn:admin1_code":"1",
    "gn:admin2_code":"9.0",
    "gn:asciiname":"La Aurora Dos",
    "gn:country_code":"MX",
    "gn:dem":1945,
    "gn:feature_class":"P",
    "gn:feature_code":"PPL",
    "gn:name":"La Aurora Dos",
    "gn:population":6,
    "gn:timezone":"America/Mexico_City",
    "iso:country":"MX",
    "wof:name":"La Aurora Dos",
    "wof:placetype":"locality",
    "wof:population":6
},
  "geometry": {"coordinates":[-102.20999999999999,22.29194],"type":"Point"}
}