{
  "type": "Feature",
  "properties": {
    "gn:admin1_code":"19.0",
    "gn:admin2_code":"17.0",
    "gn:asciiname":"La Avena",
    "gn:cc2":"MX",
    "gn:country_code":"MX",
    "gn:dem":1892,
    "gn:feature_class":"P",
    "gn:feature_code":"PPL",
    "gn:name":"La Avena",
    "gn:population":0,
    "gn:timezone":"America/Monterrey",
    "iso:country":"MX",
    "name:und_x_variant":[
        "La Averia",
        "La Avena"
    ],
    "wof:name":"La Avena",
    "wof:placetype":"locality"
},
  "geometry": {"coordinates":[-100.43333,24.58333],"type":"Point"}
}