{
  "type": "Feature",
  "properties": {
    "gn:admin1_code":"4",
    "gn:admin2_code":"11.0",
    "gn:asciiname":"Los Ramonales",
    "gn:country_code":"MX",
    "gn:dem":59,
    "gn:feature_class":"P",
    "gn:feature_code":"PPL",
    "gn:name":"Los Ramonales",
    "gn:population":5,
    "gn:timezone":"America/Merida",
    "iso:country":"MX",
    "wof:name":"Los Ramonales",
    "wof:placetype":"locality",
    "wof:population":5
},
  "geometry": {"coordinates":[-90.58694,17.98944],"type":"Point"}
}