{
  "type": "Feature",
  "properties": {
    "gn:admin1_code":"12",
    "gn:admin2_code":"76",
    "gn:asciiname":"Tlacuache",
    "gn:country_code":"MX",
    "gn:dem":945,
    "gn:feature_class":"P",
    "gn:feature_code":"PPL",
    "gn:name":"Tlacuache",
    "gn:population":9,
    "gn:timezone":"America/Mexico_City",
    "iso:country":"MX",
    "wof:name":"Tlacuache",
    "wof:placetype":"locality",
    "wof:population":9
},
  "geometry": {"coordinates":[-99.09716,17.13245],"type":"Point"}
}