{
  "type": "Feature",
  "properties": {
    "gn:admin1_code":"30.0",
    "gn:admin2_code":"144.0",
    "gn:asciiname":"Ampliacion la Providencia",
    "gn:country_code":"MX",
    "gn:dem":36,
    "gn:feature_class":"P",
    "gn:feature_code":"PPL",
    "gn:name":"Ampliaci\u00f3n la Providencia",
    "gn:population":0,
    "gn:timezone":"America/Mexico_City",
    "iso:country":"MX",
    "name:spa_x_preferred":[
        "Ampliaci\u00f3n la Providencia"
    ],
    "name:spa_x_variant":[
        "El Oriente"
    ],
    "wof:name":"Ampliacion la Providencia",
    "wof:placetype":"locality"
},
  "geometry": {"coordinates":[-94.86341,17.62781],"type":"Point"}
}