{
  "type": "Feature",
  "properties": {
    "gn:admin1_code":"14",
    "gn:admin2_code":"106.0",
    "gn:asciiname":"Los Noxtles",
    "gn:country_code":"MX",
    "gn:dem":859,
    "gn:feature_class":"P",
    "gn:feature_code":"PPL",
    "gn:name":"Los Noxtles",
    "gn:population":99,
    "gn:timezone":"America/Mexico_City",
    "iso:country":"MX",
    "name:spa_x_preferred":[
        "Los Noxtles"
    ],
    "wof:name":"Los Noxtles",
    "wof:placetype":"locality",
    "wof:population":99
},
  "geometry": {"coordinates":[-103.92806,19.72972],"type":"Point"}
}