{
  "type": "Feature",
  "properties": {
    "gn:admin1_code":"23",
    "gn:admin2_code":"5.0",
    "gn:asciiname":"Nueva Jerusalen",
    "gn:country_code":"MX",
    "gn:dem":12,
    "gn:feature_class":"P",
    "gn:feature_code":"PPL",
    "gn:name":"Nueva Jerusal\u00e9n",
    "gn:population":71,
    "gn:timezone":"America/Cancun",
    "iso:country":"MX",
    "name:und_x_variant":[
        "Nueva Jerusal\u00e9n"
    ],
    "wof:name":"Nueva Jerusalen",
    "wof:placetype":"locality",
    "wof:population":71
},
  "geometry": {"coordinates":[-87.05258000000001,21.06175],"type":"Point"}
}