{
  "type": "Feature",
  "properties": {
    "gn:admin1_code":"5",
    "gn:admin2_code":"15.0",
    "gn:asciiname":"Plata Uno",
    "gn:country_code":"MX",
    "gn:dem":535,
    "gn:feature_class":"P",
    "gn:feature_code":"PPL",
    "gn:name":"Plata Uno",
    "gn:population":4,
    "gn:timezone":"America/Mexico_City",
    "iso:country":"MX",
    "wof:name":"Plata Uno",
    "wof:placetype":"locality",
    "wof:population":4
},
  "geometry": {"coordinates":[-92.17471999999999,15.00528],"type":"Point"}
}