{
  "type": "Feature",
  "properties": {
    "gn:admin1_code":"5.0",
    "gn:asciiname":"El Recuerdo",
    "gn:country_code":"MX",
    "gn:dem":1555,
    "gn:feature_class":"P",
    "gn:feature_code":"PPL",
    "gn:name":"El Recuerdo",
    "gn:population":0,
    "gn:timezone":"America/Mexico_City",
    "iso:country":"MX",
    "name:spa_x_preferred":[
        "El Recuerdo"
    ],
    "wof:name":"El Recuerdo",
    "wof:placetype":"locality"
},
  "geometry": {"coordinates":[-92.07201999999999,16.15401],"type":"Point"}
}