{
  "type": "Feature",
  "properties": {
    "gn:admin1_code":"24",
    "gn:admin2_code":"37.0",
    "gn:asciiname":"Tlachihualamel",
    "gn:country_code":"MX",
    "gn:dem":676,
    "gn:feature_class":"P",
    "gn:feature_code":"PPL",
    "gn:name":"Tlachihualamel",
    "gn:population":93,
    "gn:timezone":"America/Mexico_City",
    "iso:country":"MX",
    "wof:name":"Tlachihualamel",
    "wof:placetype":"locality",
    "wof:population":93
},
  "geometry": {"coordinates":[-98.82889,21.18167],"type":"Point"}
}