{
  "type": "Feature",
  "properties": {
    "gn:admin1_code":"26.0",
    "gn:admin2_code":"38.0",
    "gn:asciiname":"Bacachi",
    "gn:country_code":"MX",
    "gn:dem":893,
    "gn:feature_class":"P",
    "gn:feature_code":"PPL",
    "gn:name":"B\u00e1cachi",
    "gn:population":0,
    "gn:timezone":"America/Hermosillo",
    "iso:country":"MX",
    "name:spa_x_preferred":[
        "B\u00e1cachi"
    ],
    "name:und_x_variant":[
        "Rancho Bacachi"
    ],
    "wof:name":"Bacachi",
    "wof:placetype":"locality"
},
  "geometry": {"coordinates":[-109.80681,29.76172],"type":"Point"}
}