{
  "type": "Feature",
  "properties": {
    "gn:admin1_code":"5",
    "gn:admin2_code":"27.0",
    "gn:asciiname":"Las Flechas",
    "gn:country_code":"MX",
    "gn:dem":401,
    "gn:feature_class":"P",
    "gn:feature_code":"PPL",
    "gn:name":"Las Flechas",
    "gn:population":1579,
    "gn:timezone":"America/Mexico_City",
    "iso:country":"MX",
    "wof:name":"Las Flechas",
    "wof:placetype":"locality",
    "wof:population":1579
},
  "geometry": {"coordinates":[-93.02639000000001,16.70028],"type":"Point"}
}