{
  "type": "Feature",
  "properties": {
    "gn:admin1_code":"24",
    "gn:admin2_code":"17.0",
    "gn:asciiname":"Los Angeles Numero Dos",
    "gn:country_code":"MX",
    "gn:dem":1373,
    "gn:feature_class":"P",
    "gn:feature_code":"PPL",
    "gn:name":"Los \u00c1ngeles N\u00famero Dos",
    "gn:population":71,
    "gn:timezone":"America/Mexico_City",
    "iso:country":"MX",
    "name:und_x_variant":[
        "Los \u00c1ngeles N\u00famero Dos"
    ],
    "wof:name":"Los Angeles Numero Dos",
    "wof:placetype":"locality",
    "wof:population":71
},
  "geometry": {"coordinates":[-100.14806,23.11472],"type":"Point"}
}