{
  "type": "Feature",
  "properties": {
    "gn:admin1_code":"6",
    "gn:admin2_code":"27.0",
    "gn:asciiname":"Turuceachi",
    "gn:country_code":"MX",
    "gn:dem":2366,
    "gn:feature_class":"P",
    "gn:feature_code":"PPL",
    "gn:name":"Turuceachi",
    "gn:population":31,
    "gn:timezone":"America/Chihuahua",
    "iso:country":"MX",
    "name:spa_x_preferred":[
        "Turuceachi"
    ],
    "wof:name":"Turuceachi",
    "wof:placetype":"locality",
    "wof:population":31
},
  "geometry": {"coordinates":[-107.23684,26.98994],"type":"Point"}
}