{
  "type": "Feature",
  "properties": {
    "gn:admin1_code":"21",
    "gn:admin2_code":"64.0",
    "gn:asciiname":"Agua Zarca",
    "gn:country_code":"MX",
    "gn:dem":301,
    "gn:feature_class":"P",
    "gn:feature_code":"PPL",
    "gn:name":"Agua Zarca",
    "gn:population":3,
    "gn:timezone":"America/Mexico_City",
    "iso:country":"MX",
    "name:spa_x_preferred":[
        "Agua Zarca"
    ],
    "wof:name":"Agua Zarca",
    "wof:placetype":"locality",
    "wof:population":3
},
  "geometry": {"coordinates":[-97.85586000000001,20.79498],"type":"Point"}
}