{
  "type": "Feature",
  "properties": {
    "gn:admin1_code":"12",
    "gn:admin2_code":"76.0",
    "gn:asciiname":"Barranca Pina",
    "gn:country_code":"MX",
    "gn:dem":1438,
    "gn:feature_class":"P",
    "gn:feature_code":"PPL",
    "gn:name":"Barranca Pi\u00f1a",
    "gn:population":437,
    "gn:timezone":"America/Mexico_City",
    "iso:country":"MX",
    "name:und_x_variant":[
        "Barranca Pi\u00f1a"
    ],
    "wof:name":"Barranca Pina",
    "wof:placetype":"locality",
    "wof:population":437
},
  "geometry": {"coordinates":[-98.91833,17.29722000000001],"type":"Point"}
}