{
  "type": "Feature",
  "properties": {
    "gn:admin1_code":"15",
    "gn:admin2_code":"4.0",
    "gn:asciiname":"Triguillos",
    "gn:country_code":"MX",
    "gn:dem":2296,
    "gn:feature_class":"P",
    "gn:feature_code":"PPL",
    "gn:name":"Triguillos",
    "gn:population":0,
    "gn:timezone":"America/Mexico_City",
    "iso:country":"MX",
    "name:spa_x_preferred":[
        "Triguillos"
    ],
    "wof:name":"Triguillos",
    "wof:placetype":"locality"
},
  "geometry": {"coordinates":[-99.83446000000001,18.7672],"type":"Point"}
}