{
  "type": "Feature",
  "properties": {
    "gn:admin1_code":"22.0",
    "gn:admin2_code":"8.0",
    "gn:asciiname":"Ceja de Bravo",
    "gn:country_code":"MX",
    "gn:dem":2171,
    "gn:feature_class":"P",
    "gn:feature_code":"PPL",
    "gn:name":"Ceja de Bravo",
    "gn:population":0,
    "gn:timezone":"America/Mexico_City",
    "iso:country":"MX",
    "name:spa_x_preferred":[
        "Ceja de Bravo"
    ],
    "name:und_x_variant":[
        "La Ceja",
        "La Ceja de Bravo"
    ],
    "wof:name":"Ceja de Bravo",
    "wof:placetype":"locality"
},
  "geometry": {"coordinates":[-100.39422999999999,20.37856],"type":"Point"}
}