{
  "type": "Feature",
  "properties": {
    "gn:admin1_code":"4",
    "gn:admin2_code":"11",
    "gn:asciiname":"El Otono",
    "gn:country_code":"MX",
    "gn:dem":21,
    "gn:feature_class":"P",
    "gn:feature_code":"PPL",
    "gn:name":"El Oto\u00f1o",
    "gn:population":42,
    "gn:timezone":"America/Merida",
    "iso:country":"MX",
    "name:und_x_variant":[
        "El Oto\u00f1o"
    ],
    "wof:name":"El Otono",
    "wof:placetype":"locality",
    "wof:population":42
},
  "geometry": {"coordinates":[-91.21417,18.10111],"type":"Point"}
}