{
  "type": "Feature",
  "properties": {
    "gn:admin1_code":"10.0",
    "gn:admin2_code":"35.0",
    "gn:asciiname":"El Durazno",
    "gn:cc2":"MX",
    "gn:country_code":"MX",
    "gn:dem":2190,
    "gn:feature_class":"P",
    "gn:feature_code":"PPL",
    "gn:name":"El Durazno",
    "gn:population":0,
    "gn:timezone":"America/Monterrey",
    "iso:country":"MX",
    "name:ceb_x_preferred":[
        "El Durazno"
    ],
    "name:swe_x_preferred":[
        "El Durazno"
    ],
    "name:und_x_variant":[
        "Durazno"
    ],
    "wof:name":"El Durazno",
    "wof:placetype":"locality"
},
  "geometry": {"coordinates":[-105.73333,25.53333],"type":"Point"}
}