{
  "type": "Feature",
  "properties": {
    "gn:admin1_code":"24",
    "gn:admin2_code":"56.0",
    "gn:asciiname":"El Charquito",
    "gn:country_code":"MX",
    "gn:dem":1550,
    "gn:feature_class":"P",
    "gn:feature_code":"PPL",
    "gn:name":"El Charquito",
    "gn:population":0,
    "gn:timezone":"America/Mexico_City",
    "iso:country":"MX",
    "wof:name":"El Charquito",
    "wof:placetype":"locality"
},
  "geometry": {"coordinates":[-100.69298999999999,22.62783],"type":"Point"}
}