{
  "type": "Feature",
  "properties": {
    "gn:admin1_code":"5",
    "gn:admin2_code":"61",
    "gn:asciiname":"El Olimpo",
    "gn:country_code":"MX",
    "gn:dem":1195,
    "gn:feature_class":"P",
    "gn:feature_code":"PPL",
    "gn:name":"El Olimpo",
    "gn:population":11,
    "gn:timezone":"America/Mexico_City",
    "iso:country":"MX",
    "wof:name":"El Olimpo",
    "wof:placetype":"locality",
    "wof:population":11
},
  "geometry": {"coordinates":[-93.40806000000001,16.52889],"type":"Point"}
}