{
  "type": "Feature",
  "properties": {
    "gn:admin1_code":"11.0",
    "gn:admin2_code":"33.0",
    "gn:asciiname":"Las Negritas",
    "gn:country_code":"MX",
    "gn:dem":2246,
    "gn:feature_class":"P",
    "gn:feature_code":"PPL",
    "gn:name":"Las Negritas",
    "gn:population":0,
    "gn:timezone":"America/Mexico_City",
    "iso:country":"MX",
    "name:spa_x_preferred":[
        "Las Negritas"
    ],
    "wof:name":"Las Negritas",
    "wof:placetype":"locality"
},
  "geometry": {"coordinates":[-100.61518,21.45993],"type":"Point"}
}