{
  "type": "Feature",
  "properties": {
    "gn:admin1_code":"26",
    "gn:admin2_code":"71.0",
    "gn:asciiname":"Campo de Alejandro Rocha",
    "gn:country_code":"MX",
    "gn:dem":2,
    "gn:feature_class":"P",
    "gn:feature_code":"PPL",
    "gn:name":"Campo de Alejandro Rocha",
    "gn:population":5,
    "gn:timezone":"America/Hermosillo",
    "iso:country":"MX",
    "wof:name":"Campo de Alejandro Rocha",
    "wof:placetype":"locality",
    "wof:population":5
},
  "geometry": {"coordinates":[-109.92389,27.08056],"type":"Point"}
}