{
  "type": "Feature",
  "properties": {
    "gn:admin1_code":"6",
    "gn:admin2_code":"27",
    "gn:asciiname":"Paraje la Cuesta del Gato",
    "gn:country_code":"MX",
    "gn:dem":2457,
    "gn:feature_class":"P",
    "gn:feature_code":"PPL",
    "gn:name":"Paraje la Cuesta del Gato",
    "gn:population":18,
    "gn:timezone":"America/Chihuahua",
    "iso:country":"MX",
    "wof:name":"Paraje la Cuesta del Gato",
    "wof:placetype":"locality",
    "wof:population":18
},
  "geometry": {"coordinates":[-106.92294,26.86633],"type":"Point"}
}