{
  "type": "Feature",
  "properties": {
    "gn:admin1_code":"18.0",
    "gn:admin2_code":"12.0",
    "gn:asciiname":"La Chiripa",
    "gn:country_code":"MX",
    "gn:dem":7,
    "gn:feature_class":"P",
    "gn:feature_code":"PPL",
    "gn:name":"La Chiripa",
    "gn:population":0,
    "gn:timezone":"America/Mazatlan",
    "iso:country":"MX",
    "name:spa_x_preferred":[
        "La Chiripa"
    ],
    "wof:name":"La Chiripa",
    "wof:placetype":"locality"
},
  "geometry": {"coordinates":[-105.3125,21.6257],"type":"Point"}
}