{
  "type": "Feature",
  "properties": {
    "gn:admin1_code":"24",
    "gn:admin2_code":"3.0",
    "gn:asciiname":"La Union de Guadalupe",
    "gn:country_code":"MX",
    "gn:dem":1031,
    "gn:feature_class":"P",
    "gn:feature_code":"PPL",
    "gn:name":"La Uni\u00f3n de Guadalupe",
    "gn:population":336,
    "gn:timezone":"America/Mexico_City",
    "iso:country":"MX",
    "name:und_x_variant":[
        "La Uni\u00f3n de Guadalupe"
    ],
    "wof:name":"La Union de Guadalupe",
    "wof:placetype":"locality",
    "wof:population":336
},
  "geometry": {"coordinates":[-99.10556,21.60194],"type":"Point"}
}