{
  "type": "Feature",
  "properties": {
    "gn:admin1_code":"16",
    "gn:admin2_code":"35.0",
    "gn:asciiname":"Fraccionamiento Ramiro Rubio",
    "gn:country_code":"MX",
    "gn:dem":469,
    "gn:feature_class":"P",
    "gn:feature_code":"PPL",
    "gn:name":"Fraccionamiento Ramiro Rubio",
    "gn:population":5,
    "gn:timezone":"America/Mexico_City",
    "iso:country":"MX",
    "wof:name":"Fraccionamiento Ramiro Rubio",
    "wof:placetype":"locality",
    "wof:population":5
},
  "geometry": {"coordinates":[-101.81944,18.94861],"type":"Point"}
}