{
  "type": "Feature",
  "properties": {
    "gn:admin1_code":"16",
    "gn:admin2_code":"98.0",
    "gn:asciiname":"Rincon de Corucha",
    "gn:country_code":"MX",
    "gn:dem":1962,
    "gn:feature_class":"P",
    "gn:feature_code":"PPL",
    "gn:name":"Rinc\u00f3n de Corucha",
    "gn:population":532,
    "gn:timezone":"America/Mexico_City",
    "iso:country":"MX",
    "name:und_x_variant":[
        "Rinc\u00f3n de Corucha"
    ],
    "wof:name":"Rincon de Corucha",
    "wof:placetype":"locality",
    "wof:population":532
},
  "geometry": {"coordinates":[-100.43277999999999,19.54083],"type":"Point"}
}