{
  "type": "Feature",
  "properties": {
    "gn:admin1_code":"25",
    "gn:admin2_code":"3.0",
    "gn:asciiname":"El Camichin",
    "gn:country_code":"MX",
    "gn:dem":257,
    "gn:feature_class":"P",
    "gn:feature_code":"PPL",
    "gn:name":"El Camich\u00edn",
    "gn:population":77,
    "gn:timezone":"America/Mazatlan",
    "iso:country":"MX",
    "name:und_x_variant":[
        "El Camich\u00edn"
    ],
    "wof:name":"El Camichin",
    "wof:placetype":"locality",
    "wof:population":77
},
  "geometry": {"coordinates":[-107.55898999999999,25.3462],"type":"Point"}
}