{
  "type": "Feature",
  "properties": {
    "gn:admin1_code":"6",
    "gn:admin2_code":"29",
    "gn:asciiname":"Arroyo de Andres",
    "gn:country_code":"MX",
    "gn:dem":2307,
    "gn:feature_class":"P",
    "gn:feature_code":"PPL",
    "gn:name":"Arroyo de Andr\u00e9s",
    "gn:population":11,
    "gn:timezone":"America/Chihuahua",
    "iso:country":"MX",
    "name:und_x_variant":[
        "Arroyo de Andr\u00e9s"
    ],
    "wof:name":"Arroyo de Andres",
    "wof:placetype":"locality",
    "wof:population":11
},
  "geometry": {"coordinates":[-106.94013,26.12134],"type":"Point"}
}