{
  "type": "Feature",
  "properties": {
    "gn:admin1_code":"5.0",
    "gn:admin2_code":"32.0",
    "gn:asciiname":"Ampliacion el Triunfo",
    "gn:country_code":"MX",
    "gn:dem":277,
    "gn:feature_class":"P",
    "gn:feature_code":"PPL",
    "gn:name":"Ampliaci\u00f3n el Triunfo",
    "gn:population":0,
    "gn:timezone":"America/Mexico_City",
    "iso:country":"MX",
    "name:spa_x_preferred":[
        "Ampliaci\u00f3n el Trunfo"
    ],
    "name:spa_x_variant":[
        "Ampliaci\u00f3n el Triunfo"
    ],
    "wof:name":"Ampliacion el Triunfo",
    "wof:placetype":"locality"
},
  "geometry": {"coordinates":[-92.58825,15.3659],"type":"Point"}
}