{
  "type": "Feature",
  "properties": {
    "gn:admin1_code":"25",
    "gn:admin2_code":"7.0",
    "gn:asciiname":"El Altillo",
    "gn:country_code":"MX",
    "gn:dem":249,
    "gn:feature_class":"P",
    "gn:feature_code":"PPL",
    "gn:name":"El Altillo",
    "gn:population":8,
    "gn:timezone":"America/Mazatlan",
    "iso:country":"MX",
    "name:spa_x_preferred":[
        "El Altillo"
    ],
    "wof:name":"El Altillo",
    "wof:placetype":"locality",
    "wof:population":8
},
  "geometry": {"coordinates":[-108.42122999999999,26.76512],"type":"Point"}
}