{
  "type": "Feature",
  "properties": {
    "gn:admin1_code":"11",
    "gn:admin2_code":"17.0",
    "gn:asciiname":"San Antonio de Ayala",
    "gn:country_code":"MX",
    "gn:dem":1730,
    "gn:feature_class":"P",
    "gn:feature_code":"PPL",
    "gn:name":"San Antonio de Ayala",
    "gn:population":0,
    "gn:timezone":"America/Mexico_City",
    "iso:country":"MX",
    "name:spa_x_preferred":[
        "San Antonio de Ayala"
    ],
    "name:und_x_variant":[
        "San Antonio"
    ],
    "wof:name":"San Antonio de Ayala",
    "wof:placetype":"locality"
},
  "geometry": {"coordinates":[-101.37501,20.70023],"type":"Point"}
}