{
  "type": "Feature",
  "properties": {
    "gn:admin1_code":"16.0",
    "gn:admin2_code":"8.0",
    "gn:asciiname":"El Bonete",
    "gn:country_code":"MX",
    "gn:dem":544,
    "gn:feature_class":"P",
    "gn:feature_code":"PPL",
    "gn:name":"El Bonete",
    "gn:population":0,
    "gn:timezone":"America/Mexico_City",
    "iso:country":"MX",
    "name:spa_x_preferred":[
        "El Bonete"
    ],
    "wof:name":"El Bonete",
    "wof:placetype":"locality"
},
  "geometry": {"coordinates":[-103.13708,18.28912],"type":"Point"}
}