{
  "type": "Feature",
  "properties": {
    "gn:admin1_code":"5",
    "gn:admin2_code":"59",
    "gn:asciiname":"Santa Maria Jol-Ja",
    "gn:country_code":"MX",
    "gn:dem":812,
    "gn:feature_class":"P",
    "gn:feature_code":"PPL",
    "gn:name":"Santa Mar\u00eda Jol-J\u00e1",
    "gn:population":12,
    "gn:timezone":"America/Mexico_City",
    "iso:country":"MX",
    "name:und_x_variant":[
        "Santa Mar\u00eda Jol-J\u00e1"
    ],
    "wof:name":"Santa Maria Jol-Ja",
    "wof:placetype":"locality",
    "wof:population":12
},
  "geometry": {"coordinates":[-91.85556,16.99056],"type":"Point"}
}