{
  "type": "Feature",
  "properties": {
    "gn:admin1_code":"26",
    "gn:admin2_code":"70.0",
    "gn:asciiname":"Serventi",
    "gn:country_code":"MX",
    "gn:dem":416,
    "gn:feature_class":"P",
    "gn:feature_code":"PPL",
    "gn:name":"Serventi",
    "gn:population":0,
    "gn:timezone":"America/Hermosillo",
    "iso:country":"MX",
    "wof:name":"Serventi",
    "wof:placetype":"locality"
},
  "geometry": {"coordinates":[-112.78333000000001,31.85],"type":"Point"}
}