{
  "type": "Feature",
  "properties": {
    "gn:admin1_code":"3",
    "gn:admin2_code":"1.0",
    "gn:asciiname":"Chihuahua Lote 4",
    "gn:country_code":"MX",
    "gn:dem":30,
    "gn:feature_class":"P",
    "gn:feature_code":"PPL",
    "gn:name":"Chihuahua Lote 4",
    "gn:population":7,
    "gn:timezone":"America/Mazatlan",
    "iso:country":"MX",
    "wof:name":"Chihuahua Lote 4",
    "wof:placetype":"locality",
    "wof:population":7
},
  "geometry": {"coordinates":[-111.8493,25.29802],"type":"Point"}
}