{
  "type": "Feature",
  "properties": {
    "gn:admin1_code":"12",
    "gn:admin2_code":"2",
    "gn:asciiname":"Motuapa",
    "gn:country_code":"MX",
    "gn:dem":1336,
    "gn:feature_class":"P",
    "gn:feature_code":"PPL",
    "gn:name":"Motuapa",
    "gn:population":49,
    "gn:timezone":"America/Mexico_City",
    "iso:country":"MX",
    "wof:name":"Motuapa",
    "wof:placetype":"locality",
    "wof:population":49
},
  "geometry": {"coordinates":[-99.03842,17.74311],"type":"Point"}
}