{
  "type": "Feature",
  "properties": {
    "gn:admin1_code":"5",
    "gn:admin2_code":"92.0",
    "gn:asciiname":"Fraccion Concepcion",
    "gn:country_code":"MX",
    "gn:dem":560,
    "gn:feature_class":"P",
    "gn:feature_code":"PPL",
    "gn:name":"Fracci\u00f3n Concepci\u00f3n",
    "gn:population":5,
    "gn:timezone":"America/Mexico_City",
    "iso:country":"MX",
    "wof:name":"Fraccion Concepcion",
    "wof:placetype":"locality",
    "wof:population":5
},
  "geometry": {"coordinates":[-93.37361,17.15472],"type":"Point"}
}