{
  "type": "Feature",
  "properties": {
    "gn:admin1_code":"6",
    "gn:admin2_code":"27.0",
    "gn:asciiname":"Basuchi",
    "gn:country_code":"MX",
    "gn:dem":1889,
    "gn:feature_class":"P",
    "gn:feature_code":"PPL",
    "gn:name":"Basuchi",
    "gn:population":0,
    "gn:timezone":"America/Chihuahua",
    "iso:country":"MX",
    "name:spa_x_preferred":[
        "Basuchi"
    ],
    "wof:name":"Basuchi",
    "wof:placetype":"locality"
},
  "geometry": {"coordinates":[-107.28436000000001,27.32161],"type":"Point"}
}