{
  "type": "Feature",
  "properties": {
    "gn:admin1_code":"16.0",
    "gn:admin2_code":"14.0",
    "gn:asciiname":"El Cerrito de las Compuertas",
    "gn:country_code":"MX",
    "gn:dem":28,
    "gn:feature_class":"P",
    "gn:feature_code":"PPL",
    "gn:name":"El Cerrito de las Compuertas",
    "gn:population":0,
    "gn:timezone":"America/Mexico_City",
    "iso:country":"MX",
    "name:spa_x_preferred":[
        "El Cerrito de las Compuertas"
    ],
    "name:und_x_variant":[
        "El Cerrito"
    ],
    "wof:name":"El Cerrito de las Compuertas",
    "wof:placetype":"locality"
},
  "geometry": {"coordinates":[-103.64,18.7814],"type":"Point"}
}