{
  "type": "Feature",
  "properties": {
    "gn:admin1_code":"15.0",
    "gn:admin2_code":"105.0",
    "gn:asciiname":"El Zopilote",
    "gn:country_code":"MX",
    "gn:dem":557,
    "gn:feature_class":"P",
    "gn:feature_code":"PPL",
    "gn:name":"El Zopilote",
    "gn:population":0,
    "gn:timezone":"America/Mexico_City",
    "iso:country":"MX",
    "name:spa_x_preferred":[
        "El Zopilote"
    ],
    "wof:name":"El Zopilote",
    "wof:placetype":"locality"
},
  "geometry": {"coordinates":[-100.19293999999999,18.50051],"type":"Point"}
}