{
  "type": "Feature",
  "properties": {
    "gn:admin1_code":"20",
    "gn:admin2_code":"57.0",
    "gn:asciiname":"Nuevo Ubero",
    "gn:country_code":"MX",
    "gn:dem":96,
    "gn:feature_class":"P",
    "gn:feature_code":"PPL",
    "gn:name":"Nuevo Ubero",
    "gn:population":418,
    "gn:timezone":"America/Mexico_City",
    "iso:country":"MX",
    "wof:name":"Nuevo Ubero",
    "wof:placetype":"locality",
    "wof:population":418
},
  "geometry": {"coordinates":[-95.05056,17.32028],"type":"Point"}
}