{
  "type": "Feature",
  "properties": {
    "gn:admin1_code":"12",
    "gn:admin2_code":"35.0",
    "gn:asciiname":"Platanillo",
    "gn:country_code":"MX",
    "gn:dem":878,
    "gn:feature_class":"P",
    "gn:feature_code":"PPL",
    "gn:name":"Platanillo",
    "gn:population":0,
    "gn:timezone":"America/Mexico_City",
    "iso:country":"MX",
    "name:ceb_x_preferred":[
        "Platanillo"
    ],
    "name:spa_x_preferred":[
        "Platanillo"
    ],
    "name:swe_x_preferred":[
        "Platanillo"
    ],
    "wof:name":"Platanillo",
    "wof:placetype":"locality"
},
  "geometry": {"coordinates":[-99.50570999999999,18.38976],"type":"Point"}
}