{
  "type": "Feature",
  "properties": {
    "gn:admin1_code":"24",
    "gn:admin2_code":"37",
    "gn:asciiname":"Barrio la Cruz",
    "gn:country_code":"MX",
    "gn:dem":232,
    "gn:feature_class":"P",
    "gn:feature_code":"PPL",
    "gn:name":"Barrio la Cruz",
    "gn:population":27,
    "gn:timezone":"America/Mexico_City",
    "iso:country":"MX",
    "wof:name":"Barrio la Cruz",
    "wof:placetype":"locality",
    "wof:population":27
},
  "geometry": {"coordinates":[-98.85278,21.24806],"type":"Point"}
}