{
  "type": "Feature",
  "properties": {
    "gn:admin1_code":"7.0",
    "gn:admin2_code":"37.0",
    "gn:asciiname":"Ejido Guadalupe",
    "gn:country_code":"MX",
    "gn:dem":326,
    "gn:feature_class":"P",
    "gn:feature_code":"PPL",
    "gn:name":"Ejido Guadalupe",
    "gn:population":0,
    "gn:timezone":"America/Monterrey",
    "iso:country":"MX",
    "wof:name":"Ejido Guadalupe",
    "wof:placetype":"locality"
},
  "geometry": {"coordinates":[-100.56667,28.11667000000001],"type":"Point"}
}