{
  "type": "Feature",
  "properties": {
    "gn:admin1_code":"12",
    "gn:admin2_code":"47",
    "gn:asciiname":"El Cuahuilote",
    "gn:country_code":"MX",
    "gn:dem":1411,
    "gn:feature_class":"P",
    "gn:feature_code":"PPL",
    "gn:name":"El Cuahuilote",
    "gn:population":19,
    "gn:timezone":"America/Mexico_City",
    "iso:country":"MX",
    "wof:name":"El Cuahuilote",
    "wof:placetype":"locality",
    "wof:population":19
},
  "geometry": {"coordinates":[-99.85829,18.57796],"type":"Point"}
}