{
  "type": "Feature",
  "properties": {
    "gn:admin1_code":"31.0",
    "gn:asciiname":"Las Rejas",
    "gn:country_code":"MX",
    "gn:dem":19,
    "gn:feature_class":"P",
    "gn:feature_code":"PPL",
    "gn:name":"Las Rejas",
    "gn:population":0,
    "gn:timezone":"America/Merida",
    "iso:country":"MX",
    "name:spa_x_preferred":[
        "Las Rejas"
    ],
    "wof:name":"Las Rejas",
    "wof:placetype":"locality"
},
  "geometry": {"coordinates":[-88.16804999999999,21.19019],"type":"Point"}
}