{
  "type": "Feature",
  "properties": {
    "gn:admin1_code":"16",
    "gn:admin2_code":"49",
    "gn:asciiname":"La Sierrita",
    "gn:country_code":"MX",
    "gn:dem":1162,
    "gn:feature_class":"P",
    "gn:feature_code":"PPL",
    "gn:name":"La Sierrita",
    "gn:population":34,
    "gn:timezone":"America/Mexico_City",
    "iso:country":"MX",
    "wof:name":"La Sierrita",
    "wof:placetype":"locality",
    "wof:population":34
},
  "geometry": {"coordinates":[-101.06972,19.29944],"type":"Point"}
}