{
  "type": "Feature",
  "properties": {
    "gn:admin1_code":"4",
    "gn:admin2_code":"11.0",
    "gn:asciiname":"Justo Sierra Mendez",
    "gn:country_code":"MX",
    "gn:dem":42,
    "gn:feature_class":"P",
    "gn:feature_code":"PPL",
    "gn:name":"Justo Sierra M\u00e9ndez",
    "gn:population":0,
    "gn:timezone":"America/Merida",
    "iso:country":"MX",
    "name:und_x_variant":[
        "Justo Sierra M\u00e9ndez",
        "Licenciado Justo Sierra M\u00e9ndez"
    ],
    "wof:name":"Justo Sierra Mendez",
    "wof:placetype":"locality"
},
  "geometry": {"coordinates":[-90.74505000000001,17.95935],"type":"Point"}
}