{
  "type": "Feature",
  "properties": {
    "gn:admin1_code":"32",
    "gn:admin2_code":"34",
    "gn:asciiname":"Piedras Coloradas",
    "gn:country_code":"MX",
    "gn:dem":2015,
    "gn:feature_class":"P",
    "gn:feature_code":"PPL",
    "gn:name":"Piedras Coloradas",
    "gn:population":16,
    "gn:timezone":"America/Mexico_City",
    "iso:country":"MX",
    "name:cat_x_preferred":[
        "Piedras Coloradas"
    ],
    "name:deu_x_preferred":[
        "Piedras Coloradas"
    ],
    "name:fra_x_preferred":[
        "Piedras Coloradas"
    ],
    "name:hye_x_preferred":[
        "\u054a\u0565\u0564\u0580\u0561\u057d \u053f\u0578\u056c\u0578\u0580\u0561\u0564\u0561\u057d"
    ],
    "name:ita_x_preferred":[
        "Piedras Coloradas"
    ],
    "name:nor_x_preferred":[
        "Piedras Coloradas"
    ],
    "name:rus_x_preferred":[
        "\u041f\u044c\u0435\u0434\u0440\u0430\u0441-\u041a\u043e\u043b\u043e\u0440\u0430\u0434\u0430\u0441"
    ],
    "name:spa_x_preferred":[
        "Piedras Coloradas"
    ],
    "wof:name":"Piedras Coloradas",
    "wof:placetype":"locality",
    "wof:population":16
},
  "geometry": {"coordinates":[-102.90971999999999,21.48139],"type":"Point"}
}