{
  "type": "Feature",
  "properties": {
    "gn:admin1_code":"32",
    "gn:admin2_code":"34",
    "gn:asciiname":"Piedras Coloradas",
    "gn:country_code":"MX",
    "gn:dem":2015,
    "gn:feature_class":"P",
    "gn:feature_code":"PPL",
    "gn:name":"Piedras Coloradas",
    "gn:population":16,
    "gn:timezone":"America/Mexico_City",
    "iso:country":"MX",
    "wof:name":"Piedras Coloradas",
    "wof:placetype":"locality",
    "wof:population":16
},
  "geometry": {"coordinates":[-102.90971999999999,21.48139],"type":"Point"}
}