{
  "type": "Feature",
  "properties": {
    "gn:admin1_code":"6",
    "gn:admin2_code":"7.0",
    "gn:asciiname":"Puerto Nazario (La Laja)",
    "gn:country_code":"MX",
    "gn:dem":2639,
    "gn:feature_class":"P",
    "gn:feature_code":"PPL",
    "gn:name":"Puerto Nazario (La Laja)",
    "gn:population":8,
    "gn:timezone":"America/Chihuahua",
    "iso:country":"MX",
    "wof:name":"Puerto Nazario (La Laja)",
    "wof:placetype":"locality",
    "wof:population":8
},
  "geometry": {"coordinates":[-106.64829,26.53998],"type":"Point"}
}