{
  "type": "Feature",
  "properties": {
    "gn:admin1_code":"19",
    "gn:admin2_code":"38.0",
    "gn:asciiname":"Los Tres Ases",
    "gn:country_code":"MX",
    "gn:dem":411,
    "gn:feature_class":"P",
    "gn:feature_code":"PPL",
    "gn:name":"Los Tres Ases",
    "gn:population":6,
    "gn:timezone":"America/Monterrey",
    "iso:country":"MX",
    "wof:name":"Los Tres Ases",
    "wof:placetype":"locality",
    "wof:population":6
},
  "geometry": {"coordinates":[-99.69861,25.04722000000001],"type":"Point"}
}