{
  "type": "Feature",
  "properties": {
    "gn:admin1_code":"15",
    "gn:admin2_code":"50",
    "gn:asciiname":"Rancho Santo Domingo",
    "gn:country_code":"MX",
    "gn:dem":2553,
    "gn:feature_class":"P",
    "gn:feature_code":"PPL",
    "gn:name":"Rancho Santo Domingo",
    "gn:population":27,
    "gn:timezone":"America/Mexico_City",
    "iso:country":"MX",
    "wof:name":"Rancho Santo Domingo",
    "wof:placetype":"locality",
    "wof:population":27
},
  "geometry": {"coordinates":[-98.889,19.11229],"type":"Point"}
}