{
  "type": "Feature",
  "properties": {
    "gn:admin1_code":"20",
    "gn:admin2_code":"198.0",
    "gn:asciiname":"Maluco",
    "gn:country_code":"MX",
    "gn:dem":114,
    "gn:feature_class":"P",
    "gn:feature_code":"PPL",
    "gn:name":"Maluco",
    "gn:population":494,
    "gn:timezone":"America/Mexico_City",
    "iso:country":"MX",
    "wof:name":"Maluco",
    "wof:placetype":"locality",
    "wof:population":494
},
  "geometry": {"coordinates":[-94.99833,16.99222],"type":"Point"}
}