{
  "type": "Feature",
  "properties": {
    "gn:admin1_code":"26.0",
    "gn:admin2_code":"30.0",
    "gn:asciiname":"El Cajon del Diablo",
    "gn:country_code":"MX",
    "gn:dem":197,
    "gn:feature_class":"P",
    "gn:feature_code":"PPL",
    "gn:name":"El Caj\u00f3n del Diablo",
    "gn:population":0,
    "gn:timezone":"America/Hermosillo",
    "iso:country":"MX",
    "name:spa_x_preferred":[
        "El Caj\u00f3n del Diablo"
    ],
    "name:spa_x_variant":[
        "Rancho El Cajon del Diablo"
    ],
    "wof:name":"El Cajon del Diablo",
    "wof:placetype":"locality"
},
  "geometry": {"coordinates":[-111.05835999999999,28.46778],"type":"Point"}
}