{
  "type": "Feature",
  "properties": {
    "gn:admin1_code":"7",
    "gn:admin2_code":"6.0",
    "gn:asciiname":"Santo Domingo",
    "gn:country_code":"MX",
    "gn:dem":1063,
    "gn:feature_class":"P",
    "gn:feature_code":"PPL",
    "gn:name":"Santo Domingo",
    "gn:population":2,
    "gn:timezone":"America/Monterrey",
    "iso:country":"MX",
    "wof:name":"Santo Domingo",
    "wof:placetype":"locality",
    "wof:population":2
},
  "geometry": {"coordinates":[-101.57778,26.62978],"type":"Point"}
}