{
  "type": "Feature",
  "properties": {
    "gn:admin1_code":"12.0",
    "gn:admin2_code":"22.0",
    "gn:asciiname":"Marichi",
    "gn:country_code":"MX",
    "gn:dem":336,
    "gn:feature_class":"P",
    "gn:feature_code":"PPL",
    "gn:name":"Marichi",
    "gn:population":0,
    "gn:timezone":"America/Mexico_City",
    "iso:country":"MX",
    "name:deu_x_preferred":[
        "Marichi"
    ],
    "name:fin_x_preferred":[
        "Marichi"
    ],
    "name:guj_x_preferred":[
        "\u0aae\u0ab0\u0ac0\u0a9a\u0abf"
    ],
    "name:hin_x_preferred":[
        "\u092e\u0930\u0940\u091a\u093f"
    ],
    "name:hrv_x_preferred":[
        "Marichi"
    ],
    "name:lit_x_preferred":[
        "Mari\u010dis"
    ],
    "name:mar_x_preferred":[
        "\u092e\u0930\u0940\u091a\u093f"
    ],
    "name:nep_x_preferred":[
        "\u092e\u0930\u093f\u091a\u0940"
    ],
    "name:nld_x_preferred":[
        "Marichi"
    ],
    "name:pol_x_preferred":[
        "Mari\u0107i"
    ],
    "name:rus_x_preferred":[
        "\u041c\u0430\u0440\u0438\u0447\u0438"
    ],
    "name:slv_x_preferred":[
        "Mari\u010di"
    ],
    "name:spa_x_preferred":[
        "Marichi"
    ],
    "name:spa_x_variant":[
        "M\u00e1richi"
    ],
    "name:tam_x_preferred":[
        "\u0bae\u0bb0\u0bc0\u0b9a\u0bbf"
    ],
    "name:tel_x_preferred":[
        "\u0c2e\u0c30\u0c40\u0c1a\u0c3f"
    ],
    "name:ukr_x_preferred":[
        "\u041c\u0430\u0440\u0456\u0447\u0430"
    ],
    "name:zho_x_preferred":[
        "\u6469\u5229\u652f"
    ],
    "wof:name":"Marichi",
    "wof:placetype":"locality"
},
  "geometry": {"coordinates":[-100.91677,18.30654],"type":"Point"}
}