{
  "type": "Feature",
  "properties": {
    "gn:admin1_code":"12.0",
    "gn:admin2_code":"22.0",
    "gn:asciiname":"Marichi",
    "gn:country_code":"MX",
    "gn:dem":336,
    "gn:feature_class":"P",
    "gn:feature_code":"PPL",
    "gn:name":"Marichi",
    "gn:population":0,
    "gn:timezone":"America/Mexico_City",
    "iso:country":"MX",
    "name:spa_x_preferred":[
        "Marichi"
    ],
    "wof:name":"Marichi",
    "wof:placetype":"locality"
},
  "geometry": {"coordinates":[-100.91677,18.30654],"type":"Point"}
}