{
  "type": "Feature",
  "properties": {
    "gn:admin1_code":"32",
    "gn:admin2_code":"16.0",
    "gn:asciiname":"San Ramon",
    "gn:country_code":"MX",
    "gn:dem":2120,
    "gn:feature_class":"P",
    "gn:feature_code":"PPL",
    "gn:name":"San Ram\u00f3n",
    "gn:population":635,
    "gn:timezone":"America/Mexico_City",
    "iso:country":"MX",
    "name:und_x_variant":[
        "San Ram\u00f3n"
    ],
    "wof:name":"San Ramon",
    "wof:placetype":"locality",
    "wof:population":635
},
  "geometry": {"coordinates":[-102.13500000000001,22.63972],"type":"Point"}
}