{
  "type": "Feature",
  "properties": {
    "gn:admin1_code":"28.0",
    "gn:admin2_code":"22.0",
    "gn:asciiname":"La Loca",
    "gn:country_code":"MX",
    "gn:dem":6,
    "gn:feature_class":"P",
    "gn:feature_code":"PPL",
    "gn:name":"La Loca",
    "gn:population":0,
    "gn:timezone":"America/Matamoros",
    "iso:country":"MX",
    "name:spa_x_preferred":[
        "La Loca"
    ],
    "wof:name":"La Loca",
    "wof:placetype":"locality"
},
  "geometry": {"coordinates":[-97.31822,25.74314],"type":"Point"}
}