{
  "type": "Feature",
  "properties": {
    "gn:admin1_code":"30",
    "gn:admin2_code":"202.0",
    "gn:asciiname":"Leogi",
    "gn:country_code":"MX",
    "gn:dem":721,
    "gn:feature_class":"P",
    "gn:feature_code":"PPL",
    "gn:name":"Leogi",
    "gn:population":66,
    "gn:timezone":"America/Mexico_City",
    "iso:country":"MX",
    "wof:name":"Leogi",
    "wof:placetype":"locality",
    "wof:population":66
},
  "geometry": {"coordinates":[-98.28278,20.6875],"type":"Point"}
}