{
  "type": "Feature",
  "properties": {
    "gn:admin1_code":"5",
    "gn:admin2_code":"57.0",
    "gn:asciiname":"Sinaltepec",
    "gn:country_code":"MX",
    "gn:dem":1275,
    "gn:feature_class":"P",
    "gn:feature_code":"PPL",
    "gn:name":"Sinaltepec",
    "gn:population":63,
    "gn:timezone":"America/Mexico_City",
    "iso:country":"MX",
    "wof:name":"Sinaltepec",
    "wof:placetype":"locality",
    "wof:population":63
},
  "geometry": {"coordinates":[-92.32832999999999,15.29361],"type":"Point"}
}