{
  "type": "Feature",
  "properties": {
    "gn:admin1_code":"7",
    "gn:admin2_code":"9.0",
    "gn:asciiname":"Parritas",
    "gn:country_code":"MX",
    "gn:dem":1120,
    "gn:feature_class":"P",
    "gn:feature_code":"PPL",
    "gn:name":"Parritas",
    "gn:population":0,
    "gn:timezone":"America/Monterrey",
    "iso:country":"MX",
    "wof:name":"Parritas",
    "wof:placetype":"locality"
},
  "geometry": {"coordinates":[-103.03333000000001,26.38333],"type":"Point"}
}