{
  "type": "Feature",
  "properties": {
    "gn:admin1_code":"32",
    "gn:admin2_code":"10.0",
    "gn:asciiname":"Rancho Nuevo las Palmas (Lorenzo Garcia)",
    "gn:country_code":"MX",
    "gn:dem":2066,
    "gn:feature_class":"P",
    "gn:feature_code":"PPL",
    "gn:name":"Rancho Nuevo las Palmas (Lorenzo Garc\u00eda)",
    "gn:population":5,
    "gn:timezone":"America/Mexico_City",
    "iso:country":"MX",
    "name:und_x_variant":[
        "Rancho Nuevo las Palmas (Lorenzo Garc\u00eda)"
    ],
    "wof:name":"Rancho Nuevo las Palmas (Lorenzo Garcia)",
    "wof:placetype":"locality",
    "wof:population":5
},
  "geometry": {"coordinates":[-102.91110999999999,23.37222],"type":"Point"}
}