{
  "type": "Feature",
  "properties": {
    "gn:admin1_code":"10",
    "gn:admin2_code":"37.0",
    "gn:asciiname":"Chupaderas",
    "gn:country_code":"MX",
    "gn:dem":2612,
    "gn:feature_class":"P",
    "gn:feature_code":"PPL",
    "gn:name":"Chupaderas",
    "gn:population":0,
    "gn:timezone":"America/Monterrey",
    "iso:country":"MX",
    "name:spa_x_preferred":[
        "Chupaderas"
    ],
    "wof:name":"Chupaderas",
    "wof:placetype":"locality"
},
  "geometry": {"coordinates":[-106.51486,25.23714],"type":"Point"}
}