{
  "type": "Feature",
  "properties": {
    "gn:admin1_code":"30",
    "gn:admin2_code":"189.0",
    "gn:asciiname":"El Salto de la Reforma",
    "gn:country_code":"MX",
    "gn:dem":31,
    "gn:feature_class":"P",
    "gn:feature_code":"PPL",
    "gn:name":"El Salto de la Reforma",
    "gn:population":511,
    "gn:timezone":"America/Mexico_City",
    "iso:country":"MX",
    "wof:name":"El Salto de la Reforma",
    "wof:placetype":"locality",
    "wof:population":511
},
  "geometry": {"coordinates":[-97.375,20.79083],"type":"Point"}
}