{
  "type": "Feature",
  "properties": {
    "gn:admin1_code":"14",
    "gn:admin2_code":"53.0",
    "gn:asciiname":"Las Penitas",
    "gn:country_code":"MX",
    "gn:dem":1940,
    "gn:feature_class":"P",
    "gn:feature_code":"PPL",
    "gn:name":"Las Pe\u00f1itas",
    "gn:population":60,
    "gn:timezone":"America/Mexico_City",
    "iso:country":"MX",
    "name:und_x_variant":[
        "Las Pe\u00f1itas"
    ],
    "wof:name":"Las Penitas",
    "wof:placetype":"locality",
    "wof:population":60
},
  "geometry": {"coordinates":[-101.93389000000001,21.46139],"type":"Point"}
}