{
  "type": "Feature",
  "properties": {
    "gn:admin1_code":"11.0",
    "gn:asciiname":"Ex-Estacion de Villasenor",
    "gn:country_code":"MX",
    "gn:dem":1697,
    "gn:feature_class":"P",
    "gn:feature_code":"PPL",
    "gn:name":"Ex-Estaci\u00f3n de Villase\u00f1or",
    "gn:population":0,
    "gn:timezone":"America/Mexico_City",
    "iso:country":"MX",
    "name:spa_x_preferred":[
        "Ex-Estaci\u00f3n de Villase\u00f1or"
    ],
    "wof:name":"Ex-Estacion de Villasenor",
    "wof:placetype":"locality"
},
  "geometry": {"coordinates":[-101.78769,20.31103],"type":"Point"}
}