{
  "type": "Feature",
  "properties": {
    "gn:admin1_code":"2.0",
    "gn:admin2_code":"2.0",
    "gn:asciiname":"Crucero de Miguel Hidalgo",
    "gn:country_code":"MX",
    "gn:dem":26,
    "gn:feature_class":"P",
    "gn:feature_code":"PPL",
    "gn:name":"Crucero de Miguel Hidalgo",
    "gn:population":0,
    "gn:timezone":"America/Tijuana",
    "iso:country":"MX",
    "name:spa_x_preferred":[
        "Crucero de Miguel Hidalgo"
    ],
    "wof:name":"Crucero de Miguel Hidalgo",
    "wof:placetype":"locality"
},
  "geometry": {"coordinates":[-114.84404000000001,32.50187],"type":"Point"}
}