{
  "type": "Feature",
  "properties": {
    "gn:admin1_code":"5",
    "gn:admin2_code":"89.0",
    "gn:asciiname":"Vega del Carmen",
    "gn:country_code":"MX",
    "gn:dem":481,
    "gn:feature_class":"P",
    "gn:feature_code":"PPL",
    "gn:name":"Vega del Carmen",
    "gn:population":5,
    "gn:timezone":"America/Mexico_City",
    "iso:country":"MX",
    "wof:name":"Vega del Carmen",
    "wof:placetype":"locality",
    "wof:population":5
},
  "geometry": {"coordinates":[-92.31528,15.05278],"type":"Point"}
}