{
  "type": "Feature",
  "properties": {
    "gn:admin1_code":"1.0",
    "gn:admin2_code":"8.0",
    "gn:asciiname":"El Pelon",
    "gn:country_code":"MX",
    "gn:dem":2337,
    "gn:feature_class":"P",
    "gn:feature_code":"PPL",
    "gn:name":"El Pel\u00f3n",
    "gn:population":0,
    "gn:timezone":"America/Mexico_City",
    "iso:country":"MX",
    "name:spa_x_preferred":[
        "El Pel\u00f3n"
    ],
    "wof:name":"El Pelon",
    "wof:placetype":"locality"
},
  "geometry": {"coordinates":[-102.49011,22.29544],"type":"Point"}
}