{
  "type": "Feature",
  "properties": {
    "gn:admin1_code":"16",
    "gn:admin2_code":"38.0",
    "gn:asciiname":"Arroyo de las Caramicuas",
    "gn:country_code":"MX",
    "gn:dem":246,
    "gn:feature_class":"P",
    "gn:feature_code":"PPL",
    "gn:name":"Arroyo de las Caramicuas",
    "gn:population":0,
    "gn:timezone":"America/Mexico_City",
    "iso:country":"MX",
    "name:spa_x_preferred":[
        "Arroyo de las Caramicuas"
    ],
    "wof:name":"Arroyo de las Caramicuas",
    "wof:placetype":"locality"
},
  "geometry": {"coordinates":[-100.8661,18.54918],"type":"Point"}
}