{
  "type": "Feature",
  "properties": {
    "gn:admin1_code":"30.0",
    "gn:admin2_code":"161.0",
    "gn:asciiname":"Abel Escobar Vicencio",
    "gn:country_code":"MX",
    "gn:dem":75,
    "gn:feature_class":"P",
    "gn:feature_code":"PPL",
    "gn:name":"Abel Escobar Vicencio",
    "gn:population":81,
    "gn:timezone":"America/Mexico_City",
    "iso:country":"MX",
    "name:spa_x_preferred":[
        "Abel Escobar Vicencio"
    ],
    "wof:name":"Abel Escobar Vicencio",
    "wof:placetype":"locality",
    "wof:population":81
},
  "geometry": {"coordinates":[-98.32682,21.62794],"type":"Point"}
}