{
  "type": "Feature",
  "properties": {
    "gn:admin1_code":"29",
    "gn:admin2_code":"30",
    "gn:asciiname":"Paso Hondo",
    "gn:country_code":"MX",
    "gn:dem":2653,
    "gn:feature_class":"P",
    "gn:feature_code":"PPL",
    "gn:name":"Paso Hondo",
    "gn:population":29,
    "gn:timezone":"America/Mexico_City",
    "iso:country":"MX",
    "wof:name":"Paso Hondo",
    "wof:placetype":"locality",
    "wof:population":29
},
  "geometry": {"coordinates":[-97.91076,19.4677],"type":"Point"}
}