{
  "type": "Feature",
  "properties": {
    "gn:admin1_code":"6.0",
    "gn:admin2_code":"2.0",
    "gn:asciiname":"La Virgen",
    "gn:country_code":"MX",
    "gn:dem":1291,
    "gn:feature_class":"P",
    "gn:feature_code":"PPL",
    "gn:name":"La Virgen",
    "gn:population":0,
    "gn:timezone":"America/Chihuahua",
    "iso:country":"MX",
    "name:spa_x_preferred":[
        "La Virgen"
    ],
    "wof:name":"La Virgen",
    "wof:placetype":"locality"
},
  "geometry": {"coordinates":[-105.61265,29.07043],"type":"Point"}
}