{
  "type": "Feature",
  "properties": {
    "gn:admin1_code":"5.0",
    "gn:admin2_code":"26.0",
    "gn:asciiname":"Bashulum",
    "gn:country_code":"MX",
    "gn:dem":1979,
    "gn:feature_class":"P",
    "gn:feature_code":"PPL",
    "gn:name":"Bashulum",
    "gn:population":0,
    "gn:timezone":"America/Mexico_City",
    "iso:country":"MX",
    "name:spa_x_preferred":[
        "Bashulum"
    ],
    "wof:name":"Bashulum",
    "wof:placetype":"locality"
},
  "geometry": {"coordinates":[-92.61411,16.90967],"type":"Point"}
}