{
  "type": "Feature",
  "properties": {
    "gn:admin1_code":"6.0",
    "gn:admin2_code":"7.0",
    "gn:asciiname":"El Obispo",
    "gn:country_code":"MX",
    "gn:dem":2625,
    "gn:feature_class":"P",
    "gn:feature_code":"PPL",
    "gn:name":"El Obispo",
    "gn:population":0,
    "gn:timezone":"America/Chihuahua",
    "iso:country":"MX",
    "name:spa_x_preferred":[
        "El Obispo"
    ],
    "wof:name":"El Obispo",
    "wof:placetype":"locality"
},
  "geometry": {"coordinates":[-106.51799,26.37798],"type":"Point"}
}