{
  "type": "Feature",
  "properties": {
    "gn:admin1_code":"5.0",
    "gn:asciiname":"Gonzalez Rio",
    "gn:country_code":"MX",
    "gn:dem":6,
    "gn:feature_class":"P",
    "gn:feature_code":"PPL",
    "gn:name":"Gonz\u00e1lez R\u00edo",
    "gn:population":0,
    "gn:timezone":"America/Mexico_City",
    "iso:country":"MX",
    "name:spa_x_preferred":[
        "Gonz\u00e1lez R\u00edo"
    ],
    "wof:name":"Gonzalez Rio",
    "wof:placetype":"locality"
},
  "geometry": {"coordinates":[-91.96854,17.80963],"type":"Point"}
}