{
  "type": "Feature",
  "properties": {
    "gn:admin1_code":"12",
    "gn:admin2_code":"57",
    "gn:asciiname":"Colonia la Providencia",
    "gn:country_code":"MX",
    "gn:dem":20,
    "gn:feature_class":"P",
    "gn:feature_code":"PPL",
    "gn:name":"Colonia la Providencia",
    "gn:population":52,
    "gn:timezone":"America/Mexico_City",
    "iso:country":"MX",
    "wof:name":"Colonia la Providencia",
    "wof:placetype":"locality",
    "wof:population":52
},
  "geometry": {"coordinates":[-100.60056,17.18],"type":"Point"}
}