{
  "type": "Feature",
  "properties": {
    "gn:admin1_code":"5",
    "gn:admin2_code":"59",
    "gn:asciiname":"Las Orquideas",
    "gn:country_code":"MX",
    "gn:dem":1189,
    "gn:feature_class":"P",
    "gn:feature_code":"PPL",
    "gn:name":"Las Orqu\u00eddeas",
    "gn:population":17,
    "gn:timezone":"America/Mexico_City",
    "iso:country":"MX",
    "name:und_x_variant":[
        "Las Orqu\u00eddeas"
    ],
    "wof:name":"Las Orquideas",
    "wof:placetype":"locality",
    "wof:population":17
},
  "geometry": {"coordinates":[-92.11389,16.89027999999999],"type":"Point"}
}