{
  "type": "Feature",
  "properties": {
    "gn:admin1_code":"30",
    "gn:admin2_code":"100.0",
    "gn:asciiname":"Colonia el Mango (Anexo de la Cantera)",
    "gn:country_code":"MX",
    "gn:dem":74,
    "gn:feature_class":"P",
    "gn:feature_code":"PPL",
    "gn:name":"Colonia el Mango (Anexo de la Cantera)",
    "gn:population":91,
    "gn:timezone":"America/Mexico_City",
    "iso:country":"MX",
    "wof:name":"Colonia el Mango (Anexo de la Cantera)",
    "wof:placetype":"locality",
    "wof:population":91
},
  "geometry": {"coordinates":[-96.33861,19.05556],"type":"Point"}
}