{
  "type": "Feature",
  "properties": {
    "gn:admin1_code":"12",
    "gn:admin2_code":"66.0",
    "gn:asciiname":"Tenango Tepexi",
    "gn:country_code":"MX",
    "gn:dem":1686,
    "gn:feature_class":"P",
    "gn:feature_code":"PPL",
    "gn:name":"Tenango Tepexi",
    "gn:population":0,
    "gn:timezone":"America/Mexico_City",
    "iso:country":"MX",
    "name:und_x_variant":[
        "Tenango Atepexi",
        "Tenango Tepexi"
    ],
    "wof:name":"Tenango Tepexi",
    "wof:placetype":"locality"
},
  "geometry": {"coordinates":[-98.63686,17.60775],"type":"Point"}
}