{
  "type": "Feature",
  "properties": {
    "gn:admin1_code":"30",
    "gn:admin2_code":"77",
    "gn:asciiname":"Licenciado Alfredo V. Bonfil",
    "gn:country_code":"MX",
    "gn:dem":75,
    "gn:feature_class":"P",
    "gn:feature_code":"PPL",
    "gn:name":"Licenciado Alfredo V. Bonfil",
    "gn:population":26,
    "gn:timezone":"America/Mexico_City",
    "iso:country":"MX",
    "wof:name":"Licenciado Alfredo V. Bonfil",
    "wof:placetype":"locality",
    "wof:population":26
},
  "geometry": {"coordinates":[-95.48999999999999,17.94306],"type":"Point"}
}