{
  "type": "Feature",
  "properties": {
    "gn:admin1_code":"16.0",
    "gn:admin2_code":"26.0",
    "gn:asciiname":"La Galeana",
    "gn:country_code":"MX",
    "gn:dem":1347,
    "gn:feature_class":"P",
    "gn:feature_code":"PPL",
    "gn:name":"La Galeana",
    "gn:population":0,
    "gn:timezone":"America/Mexico_City",
    "iso:country":"MX",
    "name:spa_x_preferred":[
        "La Galeana"
    ],
    "wof:name":"La Galeana",
    "wof:placetype":"locality"
},
  "geometry": {"coordinates":[-103.27897,18.67396],"type":"Point"}
}