{
  "type": "Feature",
  "properties": {
    "gn:admin1_code":"2.0",
    "gn:admin2_code":"2.0",
    "gn:asciiname":"Ejido Luchadores del Desierto",
    "gn:country_code":"MX",
    "gn:dem":26,
    "gn:feature_class":"P",
    "gn:feature_code":"PPL",
    "gn:name":"Ejido Luchadores del Desierto",
    "gn:population":0,
    "gn:timezone":"America/Tijuana",
    "iso:country":"MX",
    "name:spa_x_preferred":[
        "Ejido Luchadores del Desierto"
    ],
    "wof:name":"Ejido Luchadores del Desierto",
    "wof:placetype":"locality"
},
  "geometry": {"coordinates":[-115.78694,32.57056],"type":"Point"}
}