{
  "type": "Feature",
  "properties": {
    "gn:admin1_code":"13",
    "gn:admin2_code":"51.0",
    "gn:asciiname":"Azoyatla",
    "gn:country_code":"MX",
    "gn:dem":2474,
    "gn:feature_class":"P",
    "gn:feature_code":"PPL",
    "gn:name":"Azoyatla",
    "gn:population":0,
    "gn:timezone":"America/Mexico_City",
    "iso:country":"MX",
    "name:und_x_variant":[
        "Azovatla",
        "Azoyatla",
        "Azayatla"
    ],
    "wof:name":"Azoyatla",
    "wof:placetype":"locality"
},
  "geometry": {"coordinates":[-98.69464000000001,20.09903],"type":"Point"}
}