{
  "type": "Feature",
  "properties": {
    "gn:admin1_code":"5",
    "gn:admin2_code":"59.0",
    "gn:asciiname":"Las Golondrinas",
    "gn:country_code":"MX",
    "gn:dem":871,
    "gn:feature_class":"P",
    "gn:feature_code":"PPL",
    "gn:name":"Las Golondrinas",
    "gn:population":185,
    "gn:timezone":"America/Mexico_City",
    "iso:country":"MX",
    "wof:name":"Las Golondrinas",
    "wof:placetype":"locality",
    "wof:population":185
},
  "geometry": {"coordinates":[-92.08028,16.88611],"type":"Point"}
}