{
  "type": "Feature",
  "properties": {
    "gn:admin1_code":"16",
    "gn:admin2_code":"65.0",
    "gn:asciiname":"Pomacuaran",
    "gn:country_code":"MX",
    "gn:dem":2241,
    "gn:feature_class":"P",
    "gn:feature_code":"PPL",
    "gn:name":"Pomacuar\u00e1n",
    "gn:population":0,
    "gn:timezone":"America/Mexico_City",
    "iso:country":"MX",
    "name:und_x_variant":[
        "Pamecuaran",
        "Pomacuar\u00e1n"
    ],
    "wof:name":"Pomacuaran",
    "wof:placetype":"locality"
},
  "geometry": {"coordinates":[-102.10286000000001,19.62198],"type":"Point"}
}