{
  "type": "Feature",
  "properties": {
    "gn:admin1_code":"28",
    "gn:admin2_code":"11.0",
    "gn:asciiname":"Camacho",
    "gn:country_code":"MX",
    "gn:dem":83,
    "gn:feature_class":"P",
    "gn:feature_code":"PPL",
    "gn:name":"Camacho",
    "gn:population":0,
    "gn:timezone":"America/Monterrey",
    "iso:country":"MX",
    "wof:name":"Camacho",
    "wof:placetype":"locality"
},
  "geometry": {"coordinates":[-99.11667,22.95],"type":"Point"}
}