{
  "type": "Feature",
  "properties": {
    "gn:admin1_code":"20",
    "gn:admin2_code":"494.0",
    "gn:asciiname":"Canada de Yukcimil",
    "gn:country_code":"MX",
    "gn:dem":2547,
    "gn:feature_class":"P",
    "gn:feature_code":"PPL",
    "gn:name":"Ca\u00f1ada de Yukcimil",
    "gn:population":129,
    "gn:timezone":"America/Mexico_City",
    "iso:country":"MX",
    "name:und_x_variant":[
        "Ca\u00f1ada de Yukcimil"
    ],
    "wof:name":"Canada de Yukcimil",
    "wof:placetype":"locality",
    "wof:population":129
},
  "geometry": {"coordinates":[-96.97611000000001,17.00861],"type":"Point"}
}