{
  "type": "Feature",
  "properties": {
    "gn:admin1_code":"13",
    "gn:admin2_code":"30.0",
    "gn:asciiname":"Cantinela",
    "gn:country_code":"MX",
    "gn:dem":1757,
    "gn:feature_class":"P",
    "gn:feature_code":"PPL",
    "gn:name":"Cantinela",
    "gn:population":1136,
    "gn:timezone":"America/Mexico_City",
    "iso:country":"MX",
    "wof:name":"Cantinela",
    "wof:placetype":"locality",
    "wof:population":1136
},
  "geometry": {"coordinates":[-99.21028,20.45778],"type":"Point"}
}