{
  "type": "Feature",
  "properties": {
    "gn:admin1_code":"6",
    "gn:admin2_code":"8.0",
    "gn:asciiname":"Alamitos",
    "gn:country_code":"MX",
    "gn:dem":2230,
    "gn:feature_class":"P",
    "gn:feature_code":"PPL",
    "gn:name":"Alamitos",
    "gn:population":0,
    "gn:timezone":"America/Chihuahua",
    "iso:country":"MX",
    "name:spa_x_preferred":[
        "Alamitos"
    ],
    "wof:name":"Alamitos",
    "wof:placetype":"locality"
},
  "geometry": {"coordinates":[-107.43906,27.03799],"type":"Point"}
}