{
  "type": "Feature",
  "properties": {
    "gn:admin1_code":"25",
    "gn:admin2_code":"5",
    "gn:asciiname":"Las Truchas",
    "gn:country_code":"MX",
    "gn:dem":322,
    "gn:feature_class":"P",
    "gn:feature_code":"PPL",
    "gn:name":"Las Truchas",
    "gn:population":38,
    "gn:timezone":"America/Mazatlan",
    "iso:country":"MX",
    "wof:name":"Las Truchas",
    "wof:placetype":"locality",
    "wof:population":38
},
  "geometry": {"coordinates":[-106.73361,24.53418],"type":"Point"}
}