{
  "type": "Feature",
  "properties": {
    "gn:admin1_code":"18.0",
    "gn:admin2_code":"9.0",
    "gn:asciiname":"Mesa de Platanitos",
    "gn:country_code":"MX",
    "gn:dem":918,
    "gn:feature_class":"P",
    "gn:feature_code":"PPL",
    "gn:name":"Mesa de Platanitos",
    "gn:population":0,
    "gn:timezone":"America/Mazatlan",
    "iso:country":"MX",
    "name:spa_x_preferred":[
        "Mesa de Platanitos"
    ],
    "name:spa_x_variant":[
        "La Mesa del Nogal",
        "Mesa del Nogal"
    ],
    "wof:name":"Mesa de Platanitos",
    "wof:placetype":"locality"
},
  "geometry": {"coordinates":[-104.598,21.7448],"type":"Point"}
}