{
  "type": "Feature",
  "properties": {
    "gn:admin1_code":"12",
    "gn:admin2_code":"3.0",
    "gn:asciiname":"San Sebastian (Las Lomas)",
    "gn:country_code":"MX",
    "gn:dem":335,
    "gn:feature_class":"P",
    "gn:feature_code":"PPL",
    "gn:name":"San Sebasti\u00e1n (Las Lomas)",
    "gn:population":127,
    "gn:timezone":"America/Mexico_City",
    "iso:country":"MX",
    "name:und_x_variant":[
        "San Sebasti\u00e1n (Las Lomas)"
    ],
    "wof:name":"San Sebastian (Las Lomas)",
    "wof:placetype":"locality",
    "wof:population":127
},
  "geometry": {"coordinates":[-100.47306,18.09611],"type":"Point"}
}