{
  "type": "Feature",
  "properties": {
    "gn:admin1_code":"10",
    "gn:admin2_code":"2.0",
    "gn:asciiname":"Rancho Santo Nino",
    "gn:country_code":"MX",
    "gn:dem":2441,
    "gn:feature_class":"P",
    "gn:feature_code":"PPL",
    "gn:name":"Rancho Santo Ni\u00f1o",
    "gn:population":15,
    "gn:timezone":"America/Monterrey",
    "iso:country":"MX",
    "wof:name":"Rancho Santo Nino",
    "wof:placetype":"locality",
    "wof:population":15
},
  "geometry": {"coordinates":[-106.1427,25.09108],"type":"Point"}
}