{
  "type": "Feature",
  "properties": {
    "gn:admin1_code":"5",
    "gn:admin2_code":"108.0",
    "gn:asciiname":"Zitacuaro (Las Carmelitas)",
    "gn:country_code":"MX",
    "gn:dem":665,
    "gn:feature_class":"P",
    "gn:feature_code":"PPL",
    "gn:name":"Zit\u00e1cuaro (Las Carmelitas)",
    "gn:population":8,
    "gn:timezone":"America/Mexico_City",
    "iso:country":"MX",
    "name:und_x_variant":[
        "Zit\u00e1cuaro (Las Carmelitas)"
    ],
    "wof:name":"Zitacuaro (Las Carmelitas)",
    "wof:placetype":"locality",
    "wof:population":8
},
  "geometry": {"coordinates":[-93.36028,16.22944],"type":"Point"}
}