{
  "type": "Feature",
  "properties": {
    "gn:admin1_code":"21",
    "gn:admin2_code":"152.0",
    "gn:asciiname":"Colonia Benito Juarez",
    "gn:country_code":"MX",
    "gn:dem":2382,
    "gn:feature_class":"P",
    "gn:feature_code":"PPL",
    "gn:name":"Colonia Benito Ju\u00e1rez",
    "gn:population":720,
    "gn:timezone":"America/Mexico_City",
    "iso:country":"MX",
    "name:und_x_variant":[
        "Colonia Benito Ju\u00e1rez"
    ],
    "wof:name":"Colonia Benito Juarez",
    "wof:placetype":"locality",
    "wof:population":720
},
  "geometry": {"coordinates":[-97.78539000000001,19.15496],"type":"Point"}
}