{
  "type": "Feature",
  "properties": {
    "gn:admin1_code":"30",
    "gn:admin2_code":"24.0",
    "gn:asciiname":"Monte Chico",
    "gn:country_code":"MX",
    "gn:dem":1082,
    "gn:feature_class":"P",
    "gn:feature_code":"PPL",
    "gn:name":"Monte Chico",
    "gn:population":0,
    "gn:timezone":"America/Mexico_City",
    "iso:country":"MX",
    "wof:name":"Monte Chico",
    "wof:placetype":"locality"
},
  "geometry": {"coordinates":[-96.93382,19.29802],"type":"Point"}
}