{
  "type": "Feature",
  "properties": {
    "gn:admin1_code":"5.0",
    "gn:admin2_code":"102.0",
    "gn:asciiname":"Primera Seccion de Guillen Poniente",
    "gn:country_code":"MX",
    "gn:dem":239,
    "gn:feature_class":"P",
    "gn:feature_code":"PPL",
    "gn:name":"Primera Secci\u00f3n de Guill\u00e9n Poniente",
    "gn:population":0,
    "gn:timezone":"America/Mexico_City",
    "iso:country":"MX",
    "name:spa_x_preferred":[
        "Primera Secci\u00f3n de Guill\u00e9n Poniente"
    ],
    "wof:name":"Primera Seccion de Guillen Poniente",
    "wof:placetype":"locality"
},
  "geometry": {"coordinates":[-92.1609,14.90338],"type":"Point"}
}