{
  "type": "Feature",
  "properties": {
    "gn:admin1_code":"5",
    "gn:admin2_code":"99.0",
    "gn:asciiname":"Las Flores Dos",
    "gn:country_code":"MX",
    "gn:dem":778,
    "gn:feature_class":"P",
    "gn:feature_code":"PPL",
    "gn:name":"Las Flores Dos",
    "gn:population":6,
    "gn:timezone":"America/Mexico_City",
    "iso:country":"MX",
    "wof:name":"Las Flores Dos",
    "wof:placetype":"locality",
    "wof:population":6
},
  "geometry": {"coordinates":[-92.00194,15.95694],"type":"Point"}
}