{
  "type": "Feature",
  "properties": {
    "gn:admin1_code":"31",
    "gn:admin2_code":"65.0",
    "gn:asciiname":"Buena Esperanza",
    "gn:country_code":"MX",
    "gn:dem":8,
    "gn:feature_class":"P",
    "gn:feature_code":"PPL",
    "gn:name":"Buena Esperanza",
    "gn:population":0,
    "gn:timezone":"America/Merida",
    "iso:country":"MX",
    "name:ceb_x_preferred":[
        "Buena Esperanza"
    ],
    "name:deu_x_preferred":[
        "Buena Esperanza"
    ],
    "name:fra_x_preferred":[
        "Buena Esperanza"
    ],
    "name:nld_x_preferred":[
        "Buena Esperanza"
    ],
    "name:por_x_preferred":[
        "Buena Esperanza"
    ],
    "name:spa_x_preferred":[
        "Buena Esperanza"
    ],
    "name:swe_x_preferred":[
        "Buena Esperanza"
    ],
    "name:zho_x_preferred":[
        "\u5e03\u57c3\u7d0d\u57c3\u65af\u4f69\u862d\u85a9"
    ],
    "wof:name":"Buena Esperanza",
    "wof:placetype":"locality"
},
  "geometry": {"coordinates":[-88.26571,21.42538],"type":"Point"}
}