{
  "type": "Feature",
  "properties": {
    "gn:admin1_code":"25",
    "gn:admin2_code":"10.0",
    "gn:asciiname":"Mulanjey (Estacion Vega)",
    "gn:country_code":"MX",
    "gn:dem":46,
    "gn:feature_class":"P",
    "gn:feature_code":"PPL",
    "gn:name":"Mulanjey (Estaci\u00f3n Vega)",
    "gn:population":595,
    "gn:timezone":"America/Mazatlan",
    "iso:country":"MX",
    "name:und_x_variant":[
        "Mulanjey (Estaci\u00f3n Vega)"
    ],
    "wof:name":"Mulanjey (Estacion Vega)",
    "wof:placetype":"locality",
    "wof:population":595
},
  "geometry": {"coordinates":[-108.73027999999999,26.16917],"type":"Point"}
}