{
  "type": "Feature",
  "properties": {
    "gn:admin1_code":"15",
    "gn:admin2_code":"78.0",
    "gn:asciiname":"Salitre de la Cal (El Zapote)",
    "gn:country_code":"MX",
    "gn:dem":1685,
    "gn:feature_class":"P",
    "gn:feature_code":"PPL",
    "gn:name":"Salitre de la Cal (El Zapote)",
    "gn:population":156,
    "gn:timezone":"America/Mexico_City",
    "iso:country":"MX",
    "wof:name":"Salitre de la Cal (El Zapote)",
    "wof:placetype":"locality",
    "wof:population":156
},
  "geometry": {"coordinates":[-100.33822000000001,19.21466],"type":"Point"}
}