{
  "type": "Feature",
  "properties": {
    "gn:admin1_code":"30.0",
    "gn:asciiname":"El Tesoro",
    "gn:country_code":"MX",
    "gn:dem":46,
    "gn:feature_class":"P",
    "gn:feature_code":"PPL",
    "gn:name":"El Tesoro",
    "gn:population":0,
    "gn:timezone":"America/Mexico_City",
    "iso:country":"MX",
    "name:spa_x_preferred":[
        "El Tesoro"
    ],
    "wof:name":"El Tesoro",
    "wof:placetype":"locality"
},
  "geometry": {"coordinates":[-95.20396,17.81234],"type":"Point"}
}