{
  "type": "Feature",
  "properties": {
    "gn:admin1_code":"10",
    "gn:admin2_code":"8",
    "gn:asciiname":"Lucio Saldivar",
    "gn:country_code":"MX",
    "gn:dem":2014,
    "gn:feature_class":"P",
    "gn:feature_code":"PPL",
    "gn:name":"Lucio Sald\u00edvar",
    "gn:population":21,
    "gn:timezone":"America/Monterrey",
    "iso:country":"MX",
    "name:und_x_variant":[
        "Lucio Sald\u00edvar"
    ],
    "wof:name":"Lucio Saldivar",
    "wof:placetype":"locality",
    "wof:population":21
},
  "geometry": {"coordinates":[-104.08614,24.4864],"type":"Point"}
}