{
  "type": "Feature",
  "properties": {
    "gn:gn_country":"MX",
    "gn:gn_fcode":"PPL",
    "gn:gn_pop":0,
    "iso:country":"MX",
    "name:ceb_x_preferred":[
        "Boquillas del Carmen"
    ],
    "name:nld_x_preferred":[
        "Boquillas del Carmen"
    ],
    "name:rus_x_preferred":[
        "\u0411\u043e\u043a\u0438\u043b\u044c\u044f\u0441-\u0434\u0435\u043b\u044c-\u041a\u0430\u0440\u043c\u0435\u043d"
    ],
    "name:spa_x_preferred":[
        "Boquillas del Carmen"
    ],
    "name:swe_x_preferred":[
        "Boquillas del Carmen"
    ],
    "name:unk_x_variant":[
        "Boquillas"
    ],
    "qs_pg:aaroncc":"MX",
    "qs_pg:gn_country":"MX",
    "qs_pg:gn_fcode":"PPL",
    "qs_pg:gn_pop":0,
    "qs_pg:name":"Boquillas del Carmen",
    "qs_pg:name_adm0":"M\u00e9xico",
    "qs_pg:name_adm1":"Coahuila de Zaragoza",
    "qs_pg:photos":792,
    "qs_pg:photos_1k":160,
    "qs_pg:photos_9k":4,
    "qs_pg:photos_9r":6,
    "qs_pg:photos_all":792,
    "qs_pg:photos_sr":9,
    "qs_pg:pop_sr":0,
    "qs_pg:qs_pg_placetype":"locality",
    "qs_pg:qs_pg_placetype_gp":"Town",
    "qs_pg:woe_adm0":23424900,
    "woe:adm0_id":23424900,
    "woe:name_adm0":"M\u00e9xico",
    "woe:name_adm1":"Coahuila de Zaragoza",
    "woe:placetype":"Town",
    "wof:name":"Boquillas del Carmen",
    "wof:placetype":"locality"
},
  "geometry": {"coordinates":[-102.93375,29.18805],"type":"Point"}
}