{
  "type": "Feature",
  "properties": {
    "gn:admin1_code":"5",
    "gn:admin2_code":"31.0",
    "gn:asciiname":"Mapil",
    "gn:country_code":"MX",
    "gn:dem":1055,
    "gn:feature_class":"P",
    "gn:feature_code":"PPL",
    "gn:name":"Mapil",
    "gn:population":203,
    "gn:timezone":"America/Mexico_City",
    "iso:country":"MX",
    "wof:name":"Mapil",
    "wof:placetype":"locality",
    "wof:population":203
},
  "geometry": {"coordinates":[-91.86888999999999,17.04472],"type":"Point"}
}