{
  "type": "Feature",
  "properties": {
    "gn:admin1_code":"31",
    "gn:admin2_code":"52.0",
    "gn:asciiname":"Pixoy",
    "gn:country_code":"MX",
    "gn:dem":4,
    "gn:feature_class":"P",
    "gn:feature_code":"PPL",
    "gn:name":"Pixoy",
    "gn:population":0,
    "gn:timezone":"America/Merida",
    "iso:country":"MX",
    "wof:name":"Pixoy",
    "wof:placetype":"locality"
},
  "geometry": {"coordinates":[-89.41667,21.28333],"type":"Point"}
}