{
  "type": "Feature",
  "properties": {
    "gn:admin1_code":"22",
    "gn:admin2_code":"4.0",
    "gn:asciiname":"Xodhe",
    "gn:country_code":"MX",
    "gn:dem":1691,
    "gn:feature_class":"P",
    "gn:feature_code":"PPL",
    "gn:name":"Xodh\u00e9",
    "gn:population":122,
    "gn:timezone":"America/Mexico_City",
    "iso:country":"MX",
    "name:und_x_variant":[
        "Xodh\u00e9"
    ],
    "wof:name":"Xodhe",
    "wof:placetype":"locality",
    "wof:population":122
},
  "geometry": {"coordinates":[-99.62417000000001,20.60389],"type":"Point"}
}