{
  "type": "Feature",
  "properties": {
    "gn:admin1_code":"30",
    "gn:admin2_code":"15",
    "gn:asciiname":"El Jobo",
    "gn:country_code":"MX",
    "gn:dem":101,
    "gn:feature_class":"P",
    "gn:feature_code":"PPL",
    "gn:name":"El Jobo",
    "gn:population":11,
    "gn:timezone":"America/Mexico_City",
    "iso:country":"MX",
    "wof:name":"El Jobo",
    "wof:placetype":"locality",
    "wof:population":11
},
  "geometry": {"coordinates":[-95.35944000000001,18.58639],"type":"Point"}
}