{
  "type": "Feature",
  "properties": {
    "gn:admin1_code":"2",
    "gn:admin2_code":"2.0",
    "gn:asciiname":"Ejido Irapuato",
    "gn:country_code":"MX",
    "gn:dem":17,
    "gn:feature_class":"P",
    "gn:feature_code":"PPL",
    "gn:name":"Ejido Irapuato",
    "gn:population":0,
    "gn:timezone":"America/Tijuana",
    "iso:country":"MX",
    "name:spa_x_preferred":[
        "Ejido Irapuato"
    ],
    "name:und_x_variant":[
        "Irapuato"
    ],
    "wof:name":"Ejido Irapuato",
    "wof:placetype":"locality"
},
  "geometry": {"coordinates":[-115.12514,32.59387],"type":"Point"}
}