{
  "type": "Feature",
  "properties": {
    "gn:admin1_code":"26",
    "gn:admin2_code":"30.0",
    "gn:asciiname":"El Repecho",
    "gn:country_code":"MX",
    "gn:dem":273,
    "gn:feature_class":"P",
    "gn:feature_code":"PPL",
    "gn:name":"El Repecho",
    "gn:population":0,
    "gn:timezone":"America/Hermosillo",
    "iso:country":"MX",
    "name:spa_x_preferred":[
        "El Repecho"
    ],
    "wof:name":"El Repecho",
    "wof:placetype":"locality"
},
  "geometry": {"coordinates":[-110.87027999999999,29.24778],"type":"Point"}
}