{
  "type": "Feature",
  "properties": {
    "gn:admin1_code":"16",
    "gn:admin2_code":"82.0",
    "gn:asciiname":"Parocho (Las Paredes)",
    "gn:country_code":"MX",
    "gn:dem":1236,
    "gn:feature_class":"P",
    "gn:feature_code":"PPL",
    "gn:name":"Parocho (Las Paredes)",
    "gn:population":407,
    "gn:timezone":"America/Mexico_City",
    "iso:country":"MX",
    "wof:name":"Parocho (Las Paredes)",
    "wof:placetype":"locality",
    "wof:population":407
},
  "geometry": {"coordinates":[-101.47,19.16972],"type":"Point"}
}