{
  "type": "Feature",
  "properties": {
    "gn:admin1_code":"28.0",
    "gn:admin2_code":"3.0",
    "gn:asciiname":"El Bonete",
    "gn:country_code":"MX",
    "gn:dem":49,
    "gn:feature_class":"P",
    "gn:feature_code":"PPL",
    "gn:name":"El Bonete",
    "gn:population":7,
    "gn:timezone":"America/Monterrey",
    "iso:country":"MX",
    "name:spa_x_preferred":[
        "El Bonete"
    ],
    "wof:name":"El Bonete",
    "wof:placetype":"locality",
    "wof:population":7
},
  "geometry": {"coordinates":[-98.1075,22.58917000000001],"type":"Point"}
}