{
  "type": "Feature",
  "properties": {
    "gn:admin1_code":"20",
    "gn:admin2_code":"198",
    "gn:asciiname":"Las Malvinas",
    "gn:country_code":"MX",
    "gn:dem":94,
    "gn:feature_class":"P",
    "gn:feature_code":"PPL",
    "gn:name":"Las Malvinas",
    "gn:population":12,
    "gn:timezone":"America/Mexico_City",
    "iso:country":"MX",
    "wof:name":"Las Malvinas",
    "wof:placetype":"locality",
    "wof:population":12
},
  "geometry": {"coordinates":[-95.04222,17.10389],"type":"Point"}
}