{
  "type": "Feature",
  "properties": {
    "gn:admin1_code":"31.0",
    "gn:asciiname":"Los Almendros",
    "gn:country_code":"MX",
    "gn:dem":16,
    "gn:feature_class":"P",
    "gn:feature_code":"PPL",
    "gn:name":"Los Almendros",
    "gn:population":0,
    "gn:timezone":"America/Merida",
    "iso:country":"MX",
    "name:spa_x_preferred":[
        "Los Almendros"
    ],
    "wof:name":"Los Almendros",
    "wof:placetype":"locality"
},
  "geometry": {"coordinates":[-88.20947,21.15618],"type":"Point"}
}