{
  "type": "Feature",
  "properties": {
    "gn:admin1_code":"26",
    "gn:admin2_code":"21.0",
    "gn:asciiname":"San Juanico",
    "gn:country_code":"MX",
    "gn:dem":461,
    "gn:feature_class":"P",
    "gn:feature_code":"PPL",
    "gn:name":"San Juanico",
    "gn:population":0,
    "gn:timezone":"America/Hermosillo",
    "iso:country":"MX",
    "name:und_x_variant":[
        "Rancho San Juanico",
        "San Juanico"
    ],
    "wof:name":"San Juanico",
    "wof:placetype":"locality"
},
  "geometry": {"coordinates":[-109.8622,28.61762],"type":"Point"}
}