{
  "type": "Feature",
  "properties": {
    "gn:admin1_code":"7",
    "gn:admin2_code":"9.0",
    "gn:asciiname":"Beta San Gabriel",
    "gn:country_code":"MX",
    "gn:dem":1108,
    "gn:feature_class":"P",
    "gn:feature_code":"PPL",
    "gn:name":"Beta San Gabriel",
    "gn:population":5,
    "gn:timezone":"America/Monterrey",
    "iso:country":"MX",
    "wof:name":"Beta San Gabriel",
    "wof:placetype":"locality",
    "wof:population":5
},
  "geometry": {"coordinates":[-103.22563,25.80694],"type":"Point"}
}