{
  "type": "Feature",
  "properties": {
    "gn:admin1_code":"17",
    "gn:admin2_code":"16.0",
    "gn:asciiname":"Huejotengo (San Marcos)",
    "gn:country_code":"MX",
    "gn:dem":2173,
    "gn:feature_class":"P",
    "gn:feature_code":"PPL",
    "gn:name":"Huejotengo (San Marcos)",
    "gn:population":979,
    "gn:timezone":"America/Mexico_City",
    "iso:country":"MX",
    "wof:name":"Huejotengo (San Marcos)",
    "wof:placetype":"locality",
    "wof:population":979
},
  "geometry": {"coordinates":[-98.75444,18.89917],"type":"Point"}
}