{
  "type": "Feature",
  "properties": {
    "gn:admin1_code":"19.0",
    "gn:admin2_code":"11.0",
    "gn:asciiname":"Saliceno",
    "gn:country_code":"MX",
    "gn:dem":312,
    "gn:feature_class":"P",
    "gn:feature_code":"PPL",
    "gn:name":"Salice\u00f1o",
    "gn:population":0,
    "gn:timezone":"America/Monterrey",
    "iso:country":"MX",
    "name:spa_x_preferred":[
        "Salice\u00f1o"
    ],
    "wof:name":"Saliceno",
    "wof:placetype":"locality"
},
  "geometry": {"coordinates":[-99.67447,26.12067],"type":"Point"}
}