{
  "type": "Feature",
  "properties": {
    "gn:admin1_code":"27.0",
    "gn:asciiname":"Emiliano Zapata Primera Seccion",
    "gn:country_code":"MX",
    "gn:dem":25,
    "gn:feature_class":"P",
    "gn:feature_code":"PPL",
    "gn:name":"Emiliano Zapata Primera Secci\u00f3n",
    "gn:population":0,
    "gn:timezone":"America/Mexico_City",
    "iso:country":"MX",
    "name:spa_x_preferred":[
        "Emiliano Zapata Primera Secci\u00f3n"
    ],
    "wof:name":"Emiliano Zapata Primera Seccion",
    "wof:placetype":"locality"
},
  "geometry": {"coordinates":[-91.36369999999999,17.42788],"type":"Point"}
}