{
  "type": "Feature",
  "properties": {
    "gn:admin1_code":"1",
    "gn:admin2_code":"11",
    "gn:asciiname":"Sociedad Maria Elena",
    "gn:country_code":"MX",
    "gn:dem":1925,
    "gn:feature_class":"P",
    "gn:feature_code":"PPL",
    "gn:name":"Sociedad Mar\u00eda Elena",
    "gn:population":14,
    "gn:timezone":"America/Mexico_City",
    "iso:country":"MX",
    "name:und_x_variant":[
        "Sociedad Mar\u00eda Elena"
    ],
    "wof:name":"Sociedad Maria Elena",
    "wof:placetype":"locality",
    "wof:population":14
},
  "geometry": {"coordinates":[-102.25194,22.03806],"type":"Point"}
}