{
  "type": "Feature",
  "properties": {
    "gn:admin1_code":"25",
    "gn:admin2_code":"3.0",
    "gn:asciiname":"San Jose de la Puerta",
    "gn:country_code":"MX",
    "gn:dem":370,
    "gn:feature_class":"P",
    "gn:feature_code":"PPL",
    "gn:name":"San Jos\u00e9 de la Puerta",
    "gn:population":162,
    "gn:timezone":"America/Mazatlan",
    "iso:country":"MX",
    "name:spa_x_preferred":[
        "San Jos\u00e9 de la Puerta"
    ],
    "wof:name":"San Jose de la Puerta",
    "wof:placetype":"locality",
    "wof:population":162
},
  "geometry": {"coordinates":[-107.65680999999999,25.41687],"type":"Point"}
}