{
  "type": "Feature",
  "properties": {
    "gn:admin1_code":"12",
    "gn:admin2_code":"21.0",
    "gn:asciiname":"La Barra",
    "gn:country_code":"MX",
    "gn:dem":11,
    "gn:feature_class":"P",
    "gn:feature_code":"PPL",
    "gn:name":"La Barra",
    "gn:population":907,
    "gn:timezone":"America/Mexico_City",
    "iso:country":"MX",
    "name:cat_x_preferred":[
        "La Barra"
    ],
    "name:ceb_x_preferred":[
        "La Barra"
    ],
    "name:deu_x_preferred":[
        "La Barra"
    ],
    "name:fra_x_preferred":[
        "La Barra"
    ],
    "name:spa_x_preferred":[
        "La Barra"
    ],
    "name:urd_x_preferred":[
        "\u0644\u0627 \u0628\u0627\u0631\u0627"
    ],
    "wof:name":"La Barra",
    "wof:placetype":"locality",
    "wof:population":907
},
  "geometry": {"coordinates":[-100.09999999999999,16.94639],"type":"Point"}
}