{
  "type": "Feature",
  "properties": {
    "gn:admin1_code":"14.0",
    "gn:admin2_code":"15.0",
    "gn:asciiname":"Las Mancornadas",
    "gn:country_code":"MX",
    "gn:dem":1064,
    "gn:feature_class":"P",
    "gn:feature_code":"PPL",
    "gn:name":"Las Mancornadas",
    "gn:population":0,
    "gn:timezone":"America/Mexico_City",
    "iso:country":"MX",
    "name:spa_x_preferred":[
        "Las Mancornadas"
    ],
    "wof:name":"Las Mancornadas",
    "wof:placetype":"locality"
},
  "geometry": {"coordinates":[-104.39169,19.80876],"type":"Point"}
}