{
  "type": "Feature",
  "properties": {
    "gn:admin1_code":"10",
    "gn:admin2_code":"23.0",
    "gn:asciiname":"El Infierno",
    "gn:country_code":"MX",
    "gn:dem":2689,
    "gn:feature_class":"P",
    "gn:feature_code":"PPL",
    "gn:name":"El Infierno",
    "gn:population":0,
    "gn:timezone":"America/Monterrey",
    "iso:country":"MX",
    "name:spa_x_preferred":[
        "El Infierno"
    ],
    "wof:name":"El Infierno",
    "wof:placetype":"locality"
},
  "geometry": {"coordinates":[-105.41417,23.72243],"type":"Point"}
}