{
  "type": "Feature",
  "properties": {
    "gn:admin1_code":"6",
    "gn:admin2_code":"48.0",
    "gn:asciiname":"Campo Setenta y Cinco",
    "gn:country_code":"MX",
    "gn:dem":2039,
    "gn:feature_class":"P",
    "gn:feature_code":"PPL",
    "gn:name":"Campo Setenta y Cinco",
    "gn:population":0,
    "gn:timezone":"America/Chihuahua",
    "iso:country":"MX",
    "name:spa_x_preferred":[
        "Campo Setenta y Cinco"
    ],
    "name:spa_x_variant":[
        "Santa Rita Vieja"
    ],
    "name:und_x_variant":[
        "Rancho Santa Rita Vieja"
    ],
    "wof:name":"Campo Setenta y Cinco",
    "wof:placetype":"locality"
},
  "geometry": {"coordinates":[-106.79228999999999,29.21691],"type":"Point"}
}