{
  "type": "Feature",
  "properties": {
    "gn:admin1_code":"23",
    "gn:admin2_code":"4.0",
    "gn:asciiname":"La Pantera",
    "gn:country_code":"MX",
    "gn:dem":20,
    "gn:feature_class":"P",
    "gn:feature_code":"PPL",
    "gn:name":"La Pantera",
    "gn:population":865,
    "gn:timezone":"America/Cancun",
    "iso:country":"MX",
    "wof:name":"La Pantera",
    "wof:placetype":"locality",
    "wof:population":865
},
  "geometry": {"coordinates":[-88.49250000000001,19.14056],"type":"Point"}
}