{
  "type": "Feature",
  "properties": {
    "gn:admin1_code":"10",
    "gn:admin2_code":"39.0",
    "gn:asciiname":"Campo de Flores",
    "gn:country_code":"MX",
    "gn:dem":1971,
    "gn:feature_class":"P",
    "gn:feature_code":"PPL",
    "gn:name":"Campo de Flores",
    "gn:population":59,
    "gn:timezone":"America/Monterrey",
    "iso:country":"MX",
    "wof:name":"Campo de Flores",
    "wof:placetype":"locality",
    "wof:population":59
},
  "geometry": {"coordinates":[-105.02645,24.95333],"type":"Point"}
}