{
  "type": "Feature",
  "properties": {
    "gn:admin1_code":"24",
    "gn:admin2_code":"54.0",
    "gn:asciiname":"Nuevo Miramar",
    "gn:country_code":"MX",
    "gn:dem":1331,
    "gn:feature_class":"P",
    "gn:feature_code":"PPL",
    "gn:name":"Nuevo Miramar",
    "gn:population":780,
    "gn:timezone":"America/Mexico_City",
    "iso:country":"MX",
    "wof:name":"Nuevo Miramar",
    "wof:placetype":"locality",
    "wof:population":780
},
  "geometry": {"coordinates":[-99.03306000000001,21.38111],"type":"Point"}
}