{
  "type": "Feature",
  "properties": {
    "gn:admin1_code":"21",
    "gn:admin2_code":"212.0",
    "gn:asciiname":"Ixtactenango",
    "gn:country_code":"MX",
    "gn:dem":1894,
    "gn:feature_class":"P",
    "gn:feature_code":"PPL",
    "gn:name":"Ixtactenango",
    "gn:population":0,
    "gn:timezone":"America/Mexico_City",
    "iso:country":"MX",
    "name:und_x_variant":[
        "Ixtatengo",
        "Ixtactenango"
    ],
    "wof:name":"Ixtactenango",
    "wof:placetype":"locality"
},
  "geometry": {"coordinates":[-97.71526,19.75514],"type":"Point"}
}