{
  "type": "Feature",
  "properties": {
    "gn:admin1_code":"19.0",
    "gn:admin2_code":"32.0",
    "gn:asciiname":"Juan Garza",
    "gn:country_code":"MX",
    "gn:dem":236,
    "gn:feature_class":"P",
    "gn:feature_code":"PPL",
    "gn:name":"Juan Garza",
    "gn:population":0,
    "gn:timezone":"America/Monterrey",
    "iso:country":"MX",
    "name:spa_x_preferred":[
        "Juan Garza"
    ],
    "wof:name":"Juan Garza",
    "wof:placetype":"locality"
},
  "geometry": {"coordinates":[-100.45484999999999,27.2317],"type":"Point"}
}