{
  "type": "Feature",
  "properties": {
    "gn:admin1_code":"20",
    "gn:admin2_code":"334",
    "gn:asciiname":"Barrio de la Playa (Tololote)",
    "gn:country_code":"MX",
    "gn:dem":288,
    "gn:feature_class":"P",
    "gn:feature_code":"PPL",
    "gn:name":"Barrio de la Playa (Tololote)",
    "gn:population":20,
    "gn:timezone":"America/Mexico_City",
    "iso:country":"MX",
    "wof:name":"Barrio de la Playa (Tololote)",
    "wof:placetype":"locality",
    "wof:population":20
},
  "geometry": {"coordinates":[-97.60861,16.13889],"type":"Point"}
}