{
  "type": "Feature",
  "properties": {
    "gn:admin1_code":"11",
    "gn:admin2_code":"19.0",
    "gn:asciiname":"La Estancia (La Presa)",
    "gn:country_code":"MX",
    "gn:dem":2237,
    "gn:feature_class":"P",
    "gn:feature_code":"PPL",
    "gn:name":"La Estancia (La Presa)",
    "gn:population":490,
    "gn:timezone":"America/Mexico_City",
    "iso:country":"MX",
    "wof:name":"La Estancia (La Presa)",
    "wof:placetype":"locality",
    "wof:population":490
},
  "geometry": {"coordinates":[-100.41139,20.32944],"type":"Point"}
}