{
  "type": "Feature",
  "properties": {
    "gn:admin1_code":"12.0",
    "gn:asciiname":"El Columpio",
    "gn:country_code":"MX",
    "gn:dem":23,
    "gn:feature_class":"P",
    "gn:feature_code":"PPL",
    "gn:name":"El Columpio",
    "gn:population":0,
    "gn:timezone":"America/Mexico_City",
    "iso:country":"MX",
    "name:spa_x_preferred":[
        "El Columpio"
    ],
    "wof:name":"El Columpio",
    "wof:placetype":"locality"
},
  "geometry": {"coordinates":[-101.45950999999999,17.62041],"type":"Point"}
}