{
  "type": "Feature",
  "properties": {
    "gn:admin1_code":"11",
    "gn:admin2_code":"7.0",
    "gn:asciiname":"Colonia Benito Juarez",
    "gn:country_code":"MX",
    "gn:dem":1747,
    "gn:feature_class":"P",
    "gn:feature_code":"PPL",
    "gn:name":"Colonia Benito Ju\u00e1rez",
    "gn:population":8,
    "gn:timezone":"America/Mexico_City",
    "iso:country":"MX",
    "name:und_x_variant":[
        "Colonia Benito Ju\u00e1rez"
    ],
    "wof:name":"Colonia Benito Juarez",
    "wof:placetype":"locality",
    "wof:population":8
},
  "geometry": {"coordinates":[-100.86167,20.51917000000001],"type":"Point"}
}