{
  "type": "Feature",
  "properties": {
    "gn:admin1_code":"30.0",
    "gn:admin2_code":"158.0",
    "gn:asciiname":"Etiopia",
    "gn:country_code":"MX",
    "gn:dem":3,
    "gn:feature_class":"P",
    "gn:feature_code":"PPL",
    "gn:name":"Etiop\u00eda",
    "gn:population":17,
    "gn:timezone":"America/Mexico_City",
    "iso:country":"MX",
    "name:spa_x_preferred":[
        "Etiop\u00eda"
    ],
    "wof:name":"Etiopia",
    "wof:placetype":"locality",
    "wof:population":17
},
  "geometry": {"coordinates":[-96.97667,20.44167],"type":"Point"}
}