{
  "type": "Feature",
  "properties": {
    "gn:admin1_code":"11",
    "gn:admin2_code":"26.0",
    "gn:asciiname":"Fraccion del Sillero (Los Barroso)",
    "gn:country_code":"MX",
    "gn:dem":1750,
    "gn:feature_class":"P",
    "gn:feature_code":"PPL",
    "gn:name":"Fracci\u00f3n del Sillero (Los Barroso)",
    "gn:population":5,
    "gn:timezone":"America/Mexico_City",
    "iso:country":"MX",
    "name:und_x_variant":[
        "Fracci\u00f3n del Sillero (Los Barroso)"
    ],
    "wof:name":"Fraccion del Sillero (Los Barroso)",
    "wof:placetype":"locality",
    "wof:population":5
},
  "geometry": {"coordinates":[-101.52306,20.86167],"type":"Point"}
}