{
  "type": "Feature",
  "properties": {
    "gn:admin1_code":"10",
    "gn:admin2_code":"27.0",
    "gn:asciiname":"Palmas Verdes",
    "gn:country_code":"MX",
    "gn:dem":1764,
    "gn:feature_class":"P",
    "gn:feature_code":"PPL",
    "gn:name":"Palmas Verdes",
    "gn:population":7,
    "gn:timezone":"America/Monterrey",
    "iso:country":"MX",
    "wof:name":"Palmas Verdes",
    "wof:placetype":"locality",
    "wof:population":7
},
  "geometry": {"coordinates":[-102.59085,24.47967],"type":"Point"}
}