{
  "type": "Feature",
  "properties": {
    "gn:admin1_code":"28.0",
    "gn:admin2_code":"21.0",
    "gn:asciiname":"El Orejon",
    "gn:country_code":"MX",
    "gn:dem":101,
    "gn:feature_class":"P",
    "gn:feature_code":"PPL",
    "gn:name":"El Orej\u00f3n",
    "gn:population":0,
    "gn:timezone":"America/Monterrey",
    "iso:country":"MX",
    "name:spa_x_preferred":[
        "El Orej\u00f3n"
    ],
    "wof:name":"El Orejon",
    "wof:placetype":"locality"
},
  "geometry": {"coordinates":[-98.97083000000001,22.66444],"type":"Point"}
}