{
  "type": "Feature",
  "properties": {
    "gn:admin1_code":"32.0",
    "gn:asciiname":"El Bajio",
    "gn:country_code":"MX",
    "gn:dem":2283,
    "gn:feature_class":"P",
    "gn:feature_code":"PPL",
    "gn:name":"El Baj\u00edo",
    "gn:population":0,
    "gn:timezone":"America/Mexico_City",
    "iso:country":"MX",
    "name:spa_x_preferred":[
        "El Baj\u00edo"
    ],
    "wof:name":"El Bajio",
    "wof:placetype":"locality"
},
  "geometry": {"coordinates":[-102.83376,21.59258],"type":"Point"}
}