{
  "type": "Feature",
  "properties": {
    "gn:admin1_code":"2.0",
    "gn:admin2_code":"1.0",
    "gn:asciiname":"Rancho Sinay",
    "gn:country_code":"MX",
    "gn:dem":189,
    "gn:feature_class":"P",
    "gn:feature_code":"PPL",
    "gn:name":"Rancho Sinay",
    "gn:population":0,
    "gn:timezone":"America/Tijuana",
    "iso:country":"MX",
    "name:spa_x_preferred":[
        "Rancho Sinay"
    ],
    "wof:name":"Rancho Sinay",
    "wof:placetype":"locality"
},
  "geometry": {"coordinates":[-116.13338,31.19766],"type":"Point"}
}