{
  "type": "Feature",
  "properties": {
    "gn:admin1_code":"21",
    "gn:admin2_code":"54.0",
    "gn:asciiname":"Analco",
    "gn:country_code":"MX",
    "gn:dem":2082,
    "gn:feature_class":"P",
    "gn:feature_code":"PPL",
    "gn:name":"Analco",
    "gn:population":890,
    "gn:timezone":"America/Mexico_City",
    "iso:country":"MX",
    "wof:name":"Analco",
    "wof:placetype":"locality",
    "wof:population":890
},
  "geometry": {"coordinates":[-97.39972,19.81833],"type":"Point"}
}