{
  "type": "Feature",
  "properties": {
    "gn:admin1_code":"1.0",
    "gn:admin2_code":"1.0",
    "gn:asciiname":"Ex-Hacienda de Agostaderito",
    "gn:country_code":"MX",
    "gn:dem":1813,
    "gn:feature_class":"P",
    "gn:feature_code":"PPL",
    "gn:name":"Ex-Hacienda de Agostaderito",
    "gn:population":16,
    "gn:timezone":"America/Mexico_City",
    "iso:country":"MX",
    "wof:name":"Ex-Hacienda de Agostaderito",
    "wof:placetype":"locality",
    "wof:population":16
},
  "geometry": {"coordinates":[-102.36166,21.7676],"type":"Point"}
}