{
  "type": "Feature",
  "properties": {
    "gn:admin1_code":"17",
    "gn:admin2_code":"24",
    "gn:asciiname":"Los Cajetes",
    "gn:country_code":"MX",
    "gn:dem":1040,
    "gn:feature_class":"P",
    "gn:feature_code":"PPL",
    "gn:name":"Los Cajetes",
    "gn:population":32,
    "gn:timezone":"America/Mexico_City",
    "iso:country":"MX",
    "wof:name":"Los Cajetes",
    "wof:placetype":"locality",
    "wof:population":32
},
  "geometry": {"coordinates":[-99.12056,18.69806],"type":"Point"}
}