{
  "type": "Feature",
  "properties": {
    "gn:admin1_code":"6.0",
    "gn:admin2_code":"30.0",
    "gn:asciiname":"El Terrero",
    "gn:country_code":"MX",
    "gn:dem":2282,
    "gn:feature_class":"P",
    "gn:feature_code":"PPL",
    "gn:name":"El Terrero",
    "gn:population":0,
    "gn:timezone":"America/Chihuahua",
    "iso:country":"MX",
    "name:spa_x_preferred":[
        "El Terrero"
    ],
    "wof:name":"El Terrero",
    "wof:placetype":"locality"
},
  "geometry": {"coordinates":[-108.24999,27.61701],"type":"Point"}
}