{
  "type": "Feature",
  "properties": {
    "gn:admin1_code":"9.0",
    "gn:asciiname":"La Bodega",
    "gn:country_code":"MX",
    "gn:dem":3058,
    "gn:feature_class":"P",
    "gn:feature_code":"PPL",
    "gn:name":"La Bodega",
    "gn:population":0,
    "gn:timezone":"America/Mexico_City",
    "iso:country":"MX",
    "name:spa_x_preferred":[
        "La Bodega"
    ],
    "wof:name":"La Bodega",
    "wof:placetype":"locality"
},
  "geometry": {"coordinates":[-99.28709000000001,19.26655],"type":"Point"}
}