{
  "type": "Feature",
  "properties": {
    "gn:admin1_code":"12.0",
    "gn:admin2_code":"16.0",
    "gn:asciiname":"El Chiflido",
    "gn:country_code":"MX",
    "gn:dem":431,
    "gn:feature_class":"P",
    "gn:feature_code":"PPL",
    "gn:name":"El Chiflido",
    "gn:population":0,
    "gn:timezone":"America/Mexico_City",
    "iso:country":"MX",
    "name:spa_x_preferred":[
        "El Chiflido"
    ],
    "name:spa_x_variant":[
        "Tanc\u00edtaro"
    ],
    "wof:name":"El Chiflido",
    "wof:placetype":"locality"
},
  "geometry": {"coordinates":[-101.50697,18.03706],"type":"Point"}
}