{
  "type": "Feature",
  "properties": {
    "gn:admin1_code":"3",
    "gn:admin2_code":"1.0",
    "gn:asciiname":"La Duradora",
    "gn:country_code":"MX",
    "gn:dem":316,
    "gn:feature_class":"P",
    "gn:feature_code":"PPL",
    "gn:name":"La Duradora",
    "gn:population":0,
    "gn:timezone":"America/Mazatlan",
    "iso:country":"MX",
    "name:spa_x_preferred":[
        "La Duradora"
    ],
    "wof:name":"La Duradora",
    "wof:placetype":"locality"
},
  "geometry": {"coordinates":[-112.00485,26.42802],"type":"Point"}
}