{
  "type": "Feature",
  "properties": {
    "gn:admin1_code":"10",
    "gn:admin2_code":"14",
    "gn:asciiname":"Las Viboras",
    "gn:country_code":"MX",
    "gn:dem":516,
    "gn:feature_class":"P",
    "gn:feature_code":"PPL",
    "gn:name":"Las V\u00edboras",
    "gn:population":10,
    "gn:timezone":"America/Mazatlan",
    "iso:country":"MX",
    "name:und_x_variant":[
        "Las V\u00edboras"
    ],
    "wof:name":"Las Viboras",
    "wof:placetype":"locality",
    "wof:population":10
},
  "geometry": {"coordinates":[-104.50105000000001,22.40198],"type":"Point"}
}