{
  "type": "Feature",
  "properties": {
    "gn:admin1_code":"16",
    "gn:admin2_code":"68.0",
    "gn:asciiname":"El Chupadero",
    "gn:country_code":"MX",
    "gn:dem":1810,
    "gn:feature_class":"P",
    "gn:feature_code":"PPL",
    "gn:name":"El Chupadero",
    "gn:population":7,
    "gn:timezone":"America/Mexico_City",
    "iso:country":"MX",
    "wof:name":"El Chupadero",
    "wof:placetype":"locality",
    "wof:population":7
},
  "geometry": {"coordinates":[-102.44167,19.44444],"type":"Point"}
}