{
  "type": "Feature",
  "properties": {
    "gn:admin1_code":"13",
    "gn:admin2_code":"53",
    "gn:asciiname":"Piedra Blanca",
    "gn:country_code":"MX",
    "gn:dem":1625,
    "gn:feature_class":"P",
    "gn:feature_code":"PPL",
    "gn:name":"Piedra Blanca",
    "gn:population":33,
    "gn:timezone":"America/Mexico_City",
    "iso:country":"MX",
    "wof:name":"Piedra Blanca",
    "wof:placetype":"locality",
    "wof:population":33
},
  "geometry": {"coordinates":[-98.24679999999999,20.39761],"type":"Point"}
}