{
  "type": "Feature",
  "properties": {
    "gn:admin1_code":"5",
    "gn:admin2_code":"107",
    "gn:asciiname":"Los Mangos",
    "gn:country_code":"MX",
    "gn:dem":610,
    "gn:feature_class":"P",
    "gn:feature_code":"PPL",
    "gn:name":"Los Mangos",
    "gn:population":10,
    "gn:timezone":"America/Mexico_City",
    "iso:country":"MX",
    "wof:name":"Los Mangos",
    "wof:placetype":"locality",
    "wof:population":10
},
  "geometry": {"coordinates":[-93.25749999999999,16.15],"type":"Point"}
}