{
  "type": "Feature",
  "properties": {
    "gn:admin1_code":"10",
    "gn:admin2_code":"7.0",
    "gn:asciiname":"Noria la Cuatro",
    "gn:country_code":"MX",
    "gn:dem":1114,
    "gn:feature_class":"P",
    "gn:feature_code":"PPL",
    "gn:name":"Noria la Cuatro",
    "gn:population":4,
    "gn:timezone":"America/Monterrey",
    "iso:country":"MX",
    "wof:name":"Noria la Cuatro",
    "wof:placetype":"locality",
    "wof:population":4
},
  "geometry": {"coordinates":[-103.42896,25.72278],"type":"Point"}
}