{
  "type": "Feature",
  "properties": {
    "gn:admin1_code":"21",
    "gn:admin2_code":"15",
    "gn:asciiname":"El Tepeyac",
    "gn:country_code":"MX",
    "gn:dem":2418,
    "gn:feature_class":"P",
    "gn:feature_code":"PPL",
    "gn:name":"El Tepeyac",
    "gn:population":12,
    "gn:timezone":"America/Mexico_City",
    "iso:country":"MX",
    "wof:name":"El Tepeyac",
    "wof:placetype":"locality",
    "wof:population":12
},
  "geometry": {"coordinates":[-98.0544,19.03125],"type":"Point"}
}