{
  "type": "Feature",
  "properties": {
    "gn:admin1_code":"10",
    "gn:admin2_code":"5.0",
    "gn:asciiname":"El Dos",
    "gn:country_code":"MX",
    "gn:dem":2592,
    "gn:feature_class":"P",
    "gn:feature_code":"PPL",
    "gn:name":"El Dos",
    "gn:population":0,
    "gn:timezone":"America/Monterrey",
    "iso:country":"MX",
    "name:spa_x_preferred":[
        "El Dos"
    ],
    "wof:name":"El Dos",
    "wof:placetype":"locality"
},
  "geometry": {"coordinates":[-105.22141000000001,23.68442000000001],"type":"Point"}
}