{
  "type": "Feature",
  "properties": {
    "gn:admin1_code":"12",
    "gn:admin2_code":"32.0",
    "gn:asciiname":"Las Vinatas",
    "gn:cc2":"MX",
    "gn:country_code":"MX",
    "gn:dem":1356,
    "gn:feature_class":"P",
    "gn:feature_code":"PPL",
    "gn:name":"Las Vinatas",
    "gn:population":565,
    "gn:timezone":"America/Mexico_City",
    "iso:country":"MX",
    "name:und_x_variant":[
        "Vinatas",
        "Las Vinatas"
    ],
    "wof:name":"Las Vinatas",
    "wof:placetype":"locality",
    "wof:population":565
},
  "geometry": {"coordinates":[-99.85138999999999,17.86],"type":"Point"}
}