{
  "type": "Feature",
  "properties": {
    "gn:admin1_code":"5",
    "gn:admin2_code":"80.0",
    "gn:asciiname":"Canacales",
    "gn:country_code":"MX",
    "gn:dem":1934,
    "gn:feature_class":"P",
    "gn:feature_code":"PPL",
    "gn:name":"Canacales",
    "gn:population":258,
    "gn:timezone":"America/Mexico_City",
    "iso:country":"MX",
    "wof:name":"Canacales",
    "wof:placetype":"locality",
    "wof:population":258
},
  "geometry": {"coordinates":[-92.25,15.54778],"type":"Point"}
}