{
  "type": "Feature",
  "properties": {
    "gn:admin1_code":"16.0",
    "gn:admin2_code":"10.0",
    "gn:asciiname":"El Descansadero",
    "gn:country_code":"MX",
    "gn:dem":257,
    "gn:feature_class":"P",
    "gn:feature_code":"PPL",
    "gn:name":"El Descansadero",
    "gn:population":0,
    "gn:timezone":"America/Mexico_City",
    "iso:country":"MX",
    "name:spa_x_preferred":[
        "El Descansadero"
    ],
    "wof:name":"El Descansadero",
    "wof:placetype":"locality"
},
  "geometry": {"coordinates":[-101.96550000000001,18.65008],"type":"Point"}
}