{
  "type": "Feature",
  "properties": {
    "gn:admin1_code":"31.0",
    "gn:asciiname":"El Garanon",
    "gn:country_code":"MX",
    "gn:dem":21,
    "gn:feature_class":"P",
    "gn:feature_code":"PPL",
    "gn:name":"El Gara\u00f1\u00f3n",
    "gn:population":0,
    "gn:timezone":"America/Merida",
    "iso:country":"MX",
    "name:spa_x_preferred":[
        "El Gara\u00f1\u00f3n"
    ],
    "wof:name":"El Garanon",
    "wof:placetype":"locality"
},
  "geometry": {"coordinates":[-88.29995,21.08232000000001],"type":"Point"}
}