{
  "type": "Feature",
  "properties": {
    "gn:admin1_code":"7.0",
    "gn:admin2_code":"38.0",
    "gn:asciiname":"La Esmeralda",
    "gn:country_code":"MX",
    "gn:dem":333,
    "gn:feature_class":"P",
    "gn:feature_code":"PPL",
    "gn:name":"La Esmeralda",
    "gn:population":1,
    "gn:timezone":"America/Monterrey",
    "iso:country":"MX",
    "wof:name":"La Esmeralda",
    "wof:placetype":"locality",
    "wof:population":1
},
  "geometry": {"coordinates":[-100.92064999999999,28.69579],"type":"Point"}
}