{
  "type": "Feature",
  "properties": {
    "gn:admin1_code":"16",
    "gn:admin2_code":"8.0",
    "gn:asciiname":"Cuirindo",
    "gn:country_code":"MX",
    "gn:dem":98,
    "gn:feature_class":"P",
    "gn:feature_code":"PPL",
    "gn:name":"Cuirindo",
    "gn:population":5,
    "gn:timezone":"America/Mexico_City",
    "iso:country":"MX",
    "wof:name":"Cuirindo",
    "wof:placetype":"locality",
    "wof:population":5
},
  "geometry": {"coordinates":[-103.24194,18.30194],"type":"Point"}
}