{
  "type": "Feature",
  "properties": {
    "gn:admin1_code":"10",
    "gn:admin2_code":"14.0",
    "gn:asciiname":"Canoitas",
    "gn:country_code":"MX",
    "gn:dem":1633,
    "gn:feature_class":"P",
    "gn:feature_code":"PPL",
    "gn:name":"Cano\u00edtas",
    "gn:population":64,
    "gn:timezone":"America/Monterrey",
    "iso:country":"MX",
    "name:und_x_variant":[
        "Cano\u00edtas"
    ],
    "wof:name":"Canoitas",
    "wof:placetype":"locality",
    "wof:population":64
},
  "geometry": {"coordinates":[-104.66357000000001,22.74587],"type":"Point"}
}