{
  "type": "Feature",
  "properties": {
    "gn:admin1_code":"12.0",
    "gn:admin2_code":"22.0",
    "gn:asciiname":"San Antonio de las Tejas",
    "gn:country_code":"MX",
    "gn:dem":1881,
    "gn:feature_class":"P",
    "gn:feature_code":"PPL",
    "gn:name":"San Antonio de las Tejas",
    "gn:population":0,
    "gn:timezone":"America/Mexico_City",
    "iso:country":"MX",
    "name:spa_x_preferred":[
        "San Antonio de las Tejas"
    ],
    "wof:name":"San Antonio de las Tejas",
    "wof:placetype":"locality"
},
  "geometry": {"coordinates":[-100.87554,17.72383],"type":"Point"}
}