{
  "type": "Feature",
  "properties": {
    "gn:admin1_code":"10",
    "gn:admin2_code":"11.0",
    "gn:asciiname":"La Loma",
    "gn:country_code":"MX",
    "gn:dem":1825,
    "gn:feature_class":"P",
    "gn:feature_code":"PPL",
    "gn:name":"La Loma",
    "gn:population":207,
    "gn:timezone":"America/Monterrey",
    "iso:country":"MX",
    "wof:name":"La Loma",
    "wof:placetype":"locality",
    "wof:population":207
},
  "geometry": {"coordinates":[-105.19556,25.96556],"type":"Point"}
}