{
  "type": "Feature",
  "properties": {
    "gn:admin1_code":"30",
    "gn:admin2_code":"105.0",
    "gn:asciiname":"Marono",
    "gn:country_code":"MX",
    "gn:dem":47,
    "gn:feature_class":"P",
    "gn:feature_code":"PPL",
    "gn:name":"Maro\u00f1o",
    "gn:population":0,
    "gn:timezone":"America/Mexico_City",
    "iso:country":"MX",
    "name:spa_x_preferred":[
        "Maro\u00f1o"
    ],
    "wof:name":"Marono",
    "wof:placetype":"locality"
},
  "geometry": {"coordinates":[-96.24249,19.10537],"type":"Point"}
}