{
  "type": "Feature",
  "properties": {
    "gn:admin1_code":"17",
    "gn:admin2_code":"9.0",
    "gn:asciiname":"El Trece",
    "gn:country_code":"MX",
    "gn:dem":2309,
    "gn:feature_class":"P",
    "gn:feature_code":"PPL",
    "gn:name":"El Trece",
    "gn:population":5,
    "gn:timezone":"America/Mexico_City",
    "iso:country":"MX",
    "wof:name":"El Trece",
    "wof:placetype":"locality",
    "wof:population":5
},
  "geometry": {"coordinates":[-99.26306,19.01167],"type":"Point"}
}