{
  "type": "Feature",
  "properties": {
    "gn:admin1_code":"20",
    "gn:admin2_code":"59.0",
    "gn:asciiname":"Barrio del Carrizal",
    "gn:country_code":"MX",
    "gn:dem":1564,
    "gn:feature_class":"P",
    "gn:feature_code":"PPL",
    "gn:name":"Barrio del Carrizal",
    "gn:population":159,
    "gn:timezone":"America/Mexico_City",
    "iso:country":"MX",
    "wof:name":"Barrio del Carrizal",
    "wof:placetype":"locality",
    "wof:population":159
},
  "geometry": {"coordinates":[-96.59917,16.3575],"type":"Point"}
}