{
  "type": "Feature",
  "properties": {
    "gn:admin1_code":"22",
    "gn:admin2_code":"7.0",
    "gn:asciiname":"Rancho San Carlos",
    "gn:country_code":"MX",
    "gn:dem":1984,
    "gn:feature_class":"P",
    "gn:feature_code":"PPL",
    "gn:name":"Rancho San Carlos",
    "gn:population":8,
    "gn:timezone":"America/Mexico_City",
    "iso:country":"MX",
    "wof:name":"Rancho San Carlos",
    "wof:placetype":"locality",
    "wof:population":8
},
  "geometry": {"coordinates":[-99.94028,20.68528],"type":"Point"}
}