{
  "type": "Feature",
  "properties": {
    "gn:admin1_code":"12",
    "gn:asciiname":"San Francisco Tlapancingo",
    "gn:country_code":"MX",
    "gn:dem":1385,
    "gn:feature_class":"P",
    "gn:feature_code":"PPL",
    "gn:name":"San Francisco Tlapancingo",
    "gn:population":0,
    "gn:timezone":"America/Mexico_City",
    "iso:country":"MX",
    "name:ceb_x_preferred":[
        "San Francisco Tlapancingo"
    ],
    "name:epo_x_preferred":[
        "San Francisco Tlapancingo"
    ],
    "name:eus_x_preferred":[
        "San Francisco Tlapancingo"
    ],
    "name:ita_x_preferred":[
        "San Francisco Tlapancingo"
    ],
    "name:sco_x_preferred":[
        "San Francisco Tlapancingo"
    ],
    "name:spa_x_preferred":[
        "San Francisco Tlapancingo"
    ],
    "name:srp_x_preferred":[
        "\u041e\u043f\u0448\u0442\u0438\u043d\u0430 \u0421\u0430\u043d \u0424\u0440\u0430\u043d\u0441\u0438\u0441\u043a\u043e \u0422\u043b\u0430\u043f\u0430\u043d\u0441\u0438\u043d\u0433\u043e"
    ],
    "name:swe_x_preferred":[
        "San Francisco Tlapancingo"
    ],
    "name:und_x_variant":[
        "Tlapancingo",
        "Tlapacingo",
        "San Francisco Tlapancingo"
    ],
    "name:vie_x_preferred":[
        "San Francisco Tlapancingo"
    ],
    "wof:name":"San Francisco Tlapancingo",
    "wof:placetype":"locality"
},
  "geometry": {"coordinates":[-98.26936000000001,17.48465],"type":"Point"}
}