{
  "type": "Feature",
  "properties": {
    "gn:admin1_code":"12",
    "gn:asciiname":"San Francisco Tlapancingo",
    "gn:country_code":"MX",
    "gn:dem":1385,
    "gn:feature_class":"P",
    "gn:feature_code":"PPL",
    "gn:name":"San Francisco Tlapancingo",
    "gn:population":0,
    "gn:timezone":"America/Mexico_City",
    "iso:country":"MX",
    "name:und_x_variant":[
        "Tlapancingo",
        "Tlapacingo",
        "San Francisco Tlapancingo"
    ],
    "wof:name":"San Francisco Tlapancingo",
    "wof:placetype":"locality"
},
  "geometry": {"coordinates":[-98.26936000000001,17.48465],"type":"Point"}
}