{
  "type": "Feature",
  "properties": {
    "gn:admin1_code":"14",
    "gn:admin2_code":"83",
    "gn:asciiname":"Rancho Country Ramirez",
    "gn:country_code":"MX",
    "gn:dem":1475,
    "gn:feature_class":"P",
    "gn:feature_code":"PPL",
    "gn:name":"Rancho Country Ram\u00edrez",
    "gn:population":37,
    "gn:timezone":"America/Mexico_City",
    "iso:country":"MX",
    "name:und_x_variant":[
        "Rancho Country Ram\u00edrez"
    ],
    "wof:name":"Rancho Country Ramirez",
    "wof:placetype":"locality",
    "wof:population":37
},
  "geometry": {"coordinates":[-103.61499999999999,20.51139],"type":"Point"}
}