{
  "type": "Feature",
  "properties": {
    "gn:admin1_code":"24.0",
    "gn:admin2_code":"20.0",
    "gn:asciiname":"La Concepcion",
    "gn:country_code":"MX",
    "gn:dem":1525,
    "gn:feature_class":"P",
    "gn:feature_code":"PPL",
    "gn:name":"La Concepci\u00f3n",
    "gn:population":0,
    "gn:timezone":"America/Mexico_City",
    "iso:country":"MX",
    "name:spa_x_preferred":[
        "La Concepci\u00f3n"
    ],
    "name:und_x_variant":[
        "Concepci\u00f3n"
    ],
    "wof:name":"La Concepcion",
    "wof:placetype":"locality"
},
  "geometry": {"coordinates":[-100.66538,23.47886],"type":"Point"}
}