{
  "type": "Feature",
  "properties": {
    "gn:admin1_code":"12.0",
    "gn:admin2_code":"68.0",
    "gn:asciiname":"El Coco",
    "gn:cc2":"MX",
    "gn:country_code":"MX",
    "gn:dem":105,
    "gn:feature_class":"P",
    "gn:feature_code":"PPL",
    "gn:name":"El Coco",
    "gn:population":0,
    "gn:timezone":"America/Mexico_City",
    "iso:country":"MX",
    "name:und_x_variant":[
        "Coco",
        "El Coco"
    ],
    "wof:name":"El Coco",
    "wof:placetype":"locality"
},
  "geometry": {"coordinates":[-101.87306,18.01462],"type":"Point"}
}