{
  "type": "Feature",
  "properties": {
    "gn:admin1_code":"2.0",
    "gn:admin2_code":"3.0",
    "gn:asciiname":"La Perdiz",
    "gn:country_code":"MX",
    "gn:dem":1396,
    "gn:feature_class":"P",
    "gn:feature_code":"PPL",
    "gn:name":"La Perd\u00edz",
    "gn:population":0,
    "gn:timezone":"America/Tijuana",
    "iso:country":"MX",
    "name:spa_x_preferred":[
        "La Perd\u00edz"
    ],
    "wof:name":"La Perdiz",
    "wof:placetype":"locality"
},
  "geometry": {"coordinates":[-116.01125999999999,32.39052],"type":"Point"}
}