{
  "type": "Feature",
  "properties": {
    "gn:admin1_code":"12",
    "gn:admin2_code":"27.0",
    "gn:asciiname":"Pie de la Cuesta",
    "gn:country_code":"MX",
    "gn:dem":639,
    "gn:feature_class":"P",
    "gn:feature_code":"PPL",
    "gn:name":"Pie de la Cuesta",
    "gn:population":6,
    "gn:timezone":"America/Mexico_City",
    "iso:country":"MX",
    "wof:name":"Pie de la Cuesta",
    "wof:placetype":"locality",
    "wof:population":6
},
  "geometry": {"coordinates":[-100.54004999999999,18.62852],"type":"Point"}
}