{
  "type": "Feature",
  "properties": {
    "gn:admin1_code":"25",
    "gn:admin2_code":"17.0",
    "gn:asciiname":"La Mojonera",
    "gn:country_code":"MX",
    "gn:dem":556,
    "gn:feature_class":"P",
    "gn:feature_code":"PPL",
    "gn:name":"La Mojonera",
    "gn:population":0,
    "gn:timezone":"America/Mazatlan",
    "iso:country":"MX",
    "name:ara_x_preferred":[
        "\u0644\u0627 \u0645\u0648\u062c\u0648\u0646\u064a\u0631\u0627"
    ],
    "name:arg_x_preferred":[
        "La Mojonera"
    ],
    "name:ast_x_preferred":[
        "La Mojonera"
    ],
    "name:azb_x_preferred":[
        "\u0644\u0627 \u0645\u0648\u062e\u0648\u0646\u0631\u0627"
    ],
    "name:bul_x_preferred":[
        "\u041b\u0430 \u041c\u043e\u0445\u043e\u043d\u0435\u0440\u0430"
    ],
    "name:cat_x_preferred":[
        "La Mojonera"
    ],
    "name:eus_x_preferred":[
        "La Mojonera"
    ],
    "name:fas_x_preferred":[
        "\u0644\u0627 \u0645\u0648\u062e\u0648\u0646\u0631\u0627"
    ],
    "name:fra_x_preferred":[
        "La Mojonera"
    ],
    "name:hat_x_preferred":[
        "La Mojonera"
    ],
    "name:hun_x_preferred":[
        "La Mojonera"
    ],
    "name:hye_x_preferred":[
        "\u053c\u0561 \u0544\u0578\u056d\u0578\u0576\u0565\u0580\u0561"
    ],
    "name:ina_x_preferred":[
        "La Mojonera"
    ],
    "name:ita_x_preferred":[
        "La Mojonera"
    ],
    "name:mkd_x_preferred":[
        "\u041b\u0430 \u041c\u043e\u0445\u043e\u043d\u0435\u0440\u0430"
    ],
    "name:msa_x_preferred":[
        "La Mojonera"
    ],
    "name:nld_x_preferred":[
        "La Mojonera"
    ],
    "name:oci_x_preferred":[
        "La Mojonera"
    ],
    "name:pol_x_preferred":[
        "La Mojonera"
    ],
    "name:por_x_preferred":[
        "La Mojonera"
    ],
    "name:ron_x_preferred":[
        "La Mojonera"
    ],
    "name:rus_x_preferred":[
        "\u041b\u0430-\u041c\u043e\u0445\u043e\u043d\u0435\u0440\u0430"
    ],
    "name:spa_x_preferred":[
        "La Mojonera"
    ],
    "name:tur_x_preferred":[
        "La Mojonera"
    ],
    "name:ukr_x_preferred":[
        "\u041b\u0430-\u041c\u043e\u0445\u043e\u043d\u0435\u0440\u0430"
    ],
    "name:urd_x_preferred":[
        "\u0644\u0627 \u0645\u0648\u062c\u0648\u0646\u06cc\u0631\u0627"
    ],
    "name:uzb_x_preferred":[
        "La Mojonera"
    ],
    "name:vie_x_preferred":[
        "La Mojonera"
    ],
    "name:war_x_preferred":[
        "La Mojonera"
    ],
    "name:zho_x_preferred":[
        "\u62c9\u83ab\u970d\u5185\u62c9"
    ],
    "wof:name":"La Mojonera",
    "wof:placetype":"locality"
},
  "geometry": {"coordinates":[-107.71304000000001,25.85118],"type":"Point"}
}