{
  "type": "Feature",
  "properties": {
    "gn:admin1_code":"24.0",
    "gn:admin2_code":"46.0",
    "gn:asciiname":"Los Reyna",
    "gn:country_code":"MX",
    "gn:dem":2271,
    "gn:feature_class":"P",
    "gn:feature_code":"PPL",
    "gn:name":"Los Reyna",
    "gn:population":0,
    "gn:timezone":"America/Mexico_City",
    "iso:country":"MX",
    "name:spa_x_preferred":[
        "Los Reyna"
    ],
    "wof:name":"Los Reyna",
    "wof:placetype":"locality"
},
  "geometry": {"coordinates":[-101.39776000000001,21.86307],"type":"Point"}
}