{
  "type": "Feature",
  "properties": {
    "gn:admin1_code":"26",
    "gn:admin2_code":"57.0",
    "gn:asciiname":"Padilla",
    "gn:country_code":"MX",
    "gn:dem":898,
    "gn:feature_class":"P",
    "gn:feature_code":"PPL",
    "gn:name":"Padilla",
    "gn:population":0,
    "gn:timezone":"America/Hermosillo",
    "iso:country":"MX",
    "name:ceb_x_preferred":[
        "Padilla"
    ],
    "name:deu_x_preferred":[
        "Padilla"
    ],
    "name:fra_x_preferred":[
        "Padilla"
    ],
    "name:ita_x_preferred":[
        "Padilla"
    ],
    "name:nds_x_preferred":[
        "Padilla"
    ],
    "name:nld_x_preferred":[
        "Padilla"
    ],
    "name:rus_x_preferred":[
        "\u041f\u0430\u0434\u0438\u043b\u044c\u044f"
    ],
    "name:spa_x_preferred":[
        "Padilla"
    ],
    "name:swe_x_preferred":[
        "Padilla"
    ],
    "wof:name":"Padilla",
    "wof:placetype":"locality"
},
  "geometry": {"coordinates":[-109.71693999999999,29.45611],"type":"Point"}
}