{
  "type": "Feature",
  "properties": {
    "gn:admin1_code":"26",
    "gn:admin2_code":"57.0",
    "gn:asciiname":"Padilla",
    "gn:country_code":"MX",
    "gn:dem":898,
    "gn:feature_class":"P",
    "gn:feature_code":"PPL",
    "gn:name":"Padilla",
    "gn:population":0,
    "gn:timezone":"America/Hermosillo",
    "iso:country":"MX",
    "name:spa_x_preferred":[
        "Padilla"
    ],
    "wof:name":"Padilla",
    "wof:placetype":"locality"
},
  "geometry": {"coordinates":[-109.71693999999999,29.45611],"type":"Point"}
}