{
  "type": "Feature",
  "properties": {
    "gn:admin1_code":"6",
    "gn:admin2_code":"29",
    "gn:asciiname":"El Aguajito",
    "gn:country_code":"MX",
    "gn:dem":2370,
    "gn:feature_class":"P",
    "gn:feature_code":"PPL",
    "gn:name":"El Aguajito",
    "gn:population":42,
    "gn:timezone":"America/Chihuahua",
    "iso:country":"MX",
    "wof:name":"El Aguajito",
    "wof:placetype":"locality",
    "wof:population":42
},
  "geometry": {"coordinates":[-106.92095999999999,25.92357],"type":"Point"}
}