{
  "type": "Feature",
  "properties": {
    "gn:admin1_code":"6.0",
    "gn:admin2_code":"61.0",
    "gn:asciiname":"Ejido Mendoceno",
    "gn:country_code":"MX",
    "gn:dem":1349,
    "gn:feature_class":"P",
    "gn:feature_code":"PPL",
    "gn:name":"Ejido Mendoce\u00f1o",
    "gn:population":0,
    "gn:timezone":"America/Chihuahua",
    "iso:country":"MX",
    "name:spa_x_preferred":[
        "Ejido Mendoce\u00f1o"
    ],
    "wof:name":"Ejido Mendoceno",
    "wof:placetype":"locality"
},
  "geometry": {"coordinates":[-106.03147,27.93066],"type":"Point"}
}