{
  "type": "Feature",
  "properties": {
    "gn:admin1_code":"2.0",
    "gn:admin2_code":"4.0",
    "gn:asciiname":"Los Gavilanes",
    "gn:country_code":"MX",
    "gn:dem":128,
    "gn:feature_class":"P",
    "gn:feature_code":"PPL",
    "gn:name":"Los Gavilanes",
    "gn:population":4,
    "gn:timezone":"America/Tijuana",
    "iso:country":"MX",
    "name:spa_x_preferred":[
        "Los Gavilanes"
    ],
    "wof:name":"Los Gavilanes",
    "wof:placetype":"locality",
    "wof:population":4
},
  "geometry": {"coordinates":[-117.07111,32.47083],"type":"Point"}
}