{
  "type": "Feature",
  "properties": {
    "gn:admin1_code":"12.0",
    "gn:admin2_code":"55.0",
    "gn:asciiname":"Los Ocotes",
    "gn:country_code":"MX",
    "gn:dem":1933,
    "gn:feature_class":"P",
    "gn:feature_code":"PPL",
    "gn:name":"Los Ocotes",
    "gn:population":0,
    "gn:timezone":"America/Mexico_City",
    "iso:country":"MX",
    "name:spa_x_preferred":[
        "Los Ocotes"
    ],
    "wof:name":"Los Ocotes",
    "wof:placetype":"locality"
},
  "geometry": {"coordinates":[-99.63232000000001,18.56067],"type":"Point"}
}