{
  "type": "Feature",
  "properties": {
    "gn:admin1_code":"15",
    "gn:admin2_code":"114.0",
    "gn:asciiname":"La Presa",
    "gn:country_code":"MX",
    "gn:dem":2592,
    "gn:feature_class":"P",
    "gn:feature_code":"PPL",
    "gn:name":"La Presa",
    "gn:population":176,
    "gn:timezone":"America/Mexico_City",
    "iso:country":"MX",
    "wof:name":"La Presa",
    "wof:placetype":"locality",
    "wof:population":176
},
  "geometry": {"coordinates":[-100.05373,19.45551],"type":"Point"}
}