{
  "type": "Feature",
  "properties": {
    "gn:admin1_code":"20.0",
    "gn:admin2_code":"477.0",
    "gn:asciiname":"Cigala",
    "gn:country_code":"MX",
    "gn:dem":1299,
    "gn:feature_class":"P",
    "gn:feature_code":"PPL",
    "gn:name":"Cigala",
    "gn:population":0,
    "gn:timezone":"America/Mexico_City",
    "iso:country":"MX",
    "name:spa_x_preferred":[
        "Cigala"
    ],
    "wof:name":"Cigala",
    "wof:placetype":"locality"
},
  "geometry": {"coordinates":[-97.21073,16.47937],"type":"Point"}
}