{
  "type": "Feature",
  "properties": {
    "gn:admin1_code":"6",
    "gn:admin2_code":"19",
    "gn:asciiname":"Rancho San Francisco",
    "gn:country_code":"MX",
    "gn:dem":1585,
    "gn:feature_class":"P",
    "gn:feature_code":"PPL",
    "gn:name":"Rancho San Francisco",
    "gn:population":25,
    "gn:timezone":"America/Chihuahua",
    "iso:country":"MX",
    "name:fra_x_preferred":[
        "Rancho San Francisco"
    ],
    "wof:name":"Rancho San Francisco",
    "wof:placetype":"locality",
    "wof:population":25
},
  "geometry": {"coordinates":[-106.25027,28.94792],"type":"Point"}
}