{
  "type": "Feature",
  "properties": {
    "gn:admin1_code":"32",
    "gn:admin2_code":"8.0",
    "gn:asciiname":"Beto [Vinedos]",
    "gn:country_code":"MX",
    "gn:dem":2027,
    "gn:feature_class":"P",
    "gn:feature_code":"PPL",
    "gn:name":"Beto [Vi\u00f1edos]",
    "gn:population":5,
    "gn:timezone":"America/Mexico_City",
    "iso:country":"MX",
    "name:und_x_variant":[
        "Beto [Vi\u00f1edos]"
    ],
    "wof:name":"Beto [Vinedos]",
    "wof:placetype":"locality",
    "wof:population":5
},
  "geometry": {"coordinates":[-102.28361,22.51667],"type":"Point"}
}