{
  "type": "Feature",
  "properties": {
    "gn:gn_country":"MX",
    "gn:gn_fcode":"PPL",
    "gn:gn_pop":0,
    "iso:country":"MX",
    "name:aze_x_preferred":[
        "San-\u0130sidro"
    ],
    "name:cat_x_preferred":[
        "San Isidro"
    ],
    "name:ceb_x_preferred":[
        "San Isidro"
    ],
    "name:deu_x_preferred":[
        "San Isidro"
    ],
    "name:eus_x_preferred":[
        "San Isidro"
    ],
    "name:fra_x_preferred":[
        "San Isidro"
    ],
    "name:ilo_x_preferred":[
        "San Isidro"
    ],
    "name:ita_x_preferred":[
        "San Isidro"
    ],
    "name:lit_x_preferred":[
        "San Isidras"
    ],
    "name:mlg_x_preferred":[
        "San Isidro"
    ],
    "name:nds_x_preferred":[
        "San Isidro"
    ],
    "name:nld_x_preferred":[
        "San Isidro"
    ],
    "name:pol_x_preferred":[
        "San Isidro"
    ],
    "name:por_x_preferred":[
        "San Isidro"
    ],
    "name:rus_x_preferred":[
        "\u0421\u0430\u043d-\u0418\u0441\u0438\u0434\u0440\u043e"
    ],
    "name:sco_x_preferred":[
        "San Isidro"
    ],
    "name:spa_x_preferred":[
        "San Isidro"
    ],
    "name:spa_x_variant":[
        "San Isidro Zegache"
    ],
    "name:srp_x_preferred":[
        "\u0421\u0430\u043d \u0418\u0441\u0438\u0434\u0440\u043e"
    ],
    "name:swe_x_preferred":[
        "San Isidro"
    ],
    "name:vie_x_preferred":[
        "San Isidro"
    ],
    "name:war_x_preferred":[
        "San Isidro"
    ],
    "qs_pg:aaroncc":"MX",
    "qs_pg:gn_country":"MX",
    "qs_pg:gn_fcode":"PPL",
    "qs_pg:gn_pop":0,
    "qs_pg:name":"San Isidro",
    "qs_pg:name_adm0":"M\u00e9xico",
    "qs_pg:name_adm1":"Oaxaca",
    "qs_pg:photos":1,
    "qs_pg:photos_1k":1,
    "qs_pg:photos_9k":1,
    "qs_pg:photos_9r":1,
    "qs_pg:photos_all":1,
    "qs_pg:photos_sr":1,
    "qs_pg:pop_sr":0,
    "qs_pg:qs_pg_placetype":"neighbourhood",
    "qs_pg:qs_pg_placetype_gp":"Suburb",
    "qs_pg:woe_adm0":23424900,
    "woe:adm0_id":23424900,
    "woe:name_adm0":"M\u00e9xico",
    "woe:name_adm1":"Oaxaca",
    "woe:placetype":"Suburb",
    "wof:name":"San Isidro",
    "wof:placetype":"neighbourhood"
},
  "geometry": {"coordinates":[-96.70688,16.83021],"type":"Point"}
}