{
  "type": "Feature",
  "properties": {
    "gn:admin1_code":"11",
    "gn:admin2_code":"40.0",
    "gn:asciiname":"Las Moras",
    "gn:country_code":"MX",
    "gn:dem":1746,
    "gn:feature_class":"P",
    "gn:feature_code":"PPL",
    "gn:name":"Las Moras",
    "gn:population":666,
    "gn:timezone":"America/Mexico_City",
    "iso:country":"MX",
    "wof:name":"Las Moras",
    "wof:placetype":"locality",
    "wof:population":666
},
  "geometry": {"coordinates":[-100.16292,21.07385],"type":"Point"}
}