{
  "type": "Feature",
  "properties": {
    "gn:admin1_code":"18",
    "gn:admin2_code":"17.0",
    "gn:asciiname":"Piedras Verdes",
    "gn:country_code":"MX",
    "gn:dem":153,
    "gn:feature_class":"P",
    "gn:feature_code":"PPL",
    "gn:name":"Piedras Verdes",
    "gn:population":0,
    "gn:timezone":"America/Mazatlan",
    "iso:country":"MX",
    "name:spa_x_preferred":[
        "Piedras Verdes"
    ],
    "wof:name":"Piedras Verdes",
    "wof:placetype":"locality"
},
  "geometry": {"coordinates":[-104.90221,21.70485],"type":"Point"}
}