{
  "type": "Feature",
  "properties": {
    "gn:admin1_code":"3",
    "gn:admin2_code":"1.0",
    "gn:asciiname":"Fernando de la Toba Lote Ciento Cuarenta",
    "gn:country_code":"MX",
    "gn:dem":38,
    "gn:feature_class":"P",
    "gn:feature_code":"PPL",
    "gn:name":"Fernando de la Toba Lote Ciento Cuarenta",
    "gn:population":0,
    "gn:timezone":"America/Mazatlan",
    "iso:country":"MX",
    "name:spa_x_preferred":[
        "Santa Elena"
    ],
    "name:spa_x_variant":[
        "Fernando de la Toba Lote Ciento Cuarenta"
    ],
    "wof:name":"Fernando de la Toba Lote Ciento Cuarenta",
    "wof:placetype":"locality"
},
  "geometry": {"coordinates":[-111.77319,25.28273],"type":"Point"}
}