{
  "type": "Feature",
  "properties": {
    "gn:admin1_code":"30",
    "gn:admin2_code":"125.0",
    "gn:asciiname":"El Pedregal",
    "gn:country_code":"MX",
    "gn:dem":422,
    "gn:feature_class":"P",
    "gn:feature_code":"PPL",
    "gn:name":"El Pedregal",
    "gn:population":5,
    "gn:timezone":"America/Mexico_City",
    "iso:country":"MX",
    "wof:name":"El Pedregal",
    "wof:placetype":"locality",
    "wof:population":5
},
  "geometry": {"coordinates":[-96.67806,18.96667],"type":"Point"}
}