{
  "type": "Feature",
  "properties": {
    "gn:admin1_code":"24",
    "gn:admin2_code":"32",
    "gn:asciiname":"Maltrata",
    "gn:country_code":"MX",
    "gn:dem":1941,
    "gn:feature_class":"P",
    "gn:feature_code":"PPL",
    "gn:name":"Maltrata",
    "gn:population":11,
    "gn:timezone":"America/Mexico_City",
    "iso:country":"MX",
    "name:ceb_x_preferred":[
        "Maltrata"
    ],
    "name:epo_x_preferred":[
        "Maltrata"
    ],
    "name:eus_x_preferred":[
        "Maltrata"
    ],
    "name:spa_x_preferred":[
        "Maltrata"
    ],
    "name:srp_x_preferred":[
        "\u041e\u043f\u0448\u0442\u0438\u043d\u0430 \u041c\u0430\u043b\u0442\u0440\u0430\u0442\u0430"
    ],
    "name:swe_x_preferred":[
        "Maltrata"
    ],
    "name:vie_x_preferred":[
        "Maltrata"
    ],
    "wof:name":"Maltrata",
    "wof:placetype":"locality",
    "wof:population":11
},
  "geometry": {"coordinates":[-100.4575,21.8125],"type":"Point"}
}