{
  "type": "Feature",
  "properties": {
    "gn:admin1_code":"5.0",
    "gn:admin2_code":"5.0",
    "gn:asciiname":"El Limoncito",
    "gn:country_code":"MX",
    "gn:dem":745,
    "gn:feature_class":"P",
    "gn:feature_code":"PPL",
    "gn:name":"El Limoncito",
    "gn:population":0,
    "gn:timezone":"America/Mexico_City",
    "iso:country":"MX",
    "name:spa_x_preferred":[
        "El Limoncito"
    ],
    "wof:name":"El Limoncito",
    "wof:placetype":"locality"
},
  "geometry": {"coordinates":[-92.82566,17.32237000000001],"type":"Point"}
}