{
  "type": "Feature",
  "properties": {
    "gn:admin1_code":"10",
    "gn:admin2_code":"26.0",
    "gn:asciiname":"La Valenciana",
    "gn:country_code":"MX",
    "gn:dem":1796,
    "gn:feature_class":"P",
    "gn:feature_code":"PPL",
    "gn:name":"La Valenciana",
    "gn:population":0,
    "gn:timezone":"America/Monterrey",
    "iso:country":"MX",
    "name:spa_x_preferred":[
        "La Valenciana"
    ],
    "wof:name":"La Valenciana",
    "wof:placetype":"locality"
},
  "geometry": {"coordinates":[-105.75315999999999,23.92977],"type":"Point"}
}