{
  "type": "Feature",
  "properties": {
    "gn:admin1_code":"32",
    "gn:admin2_code":"55.0",
    "gn:asciiname":"Boca de Rivera",
    "gn:country_code":"MX",
    "gn:dem":2099,
    "gn:feature_class":"P",
    "gn:feature_code":"PPL",
    "gn:name":"Boca de Rivera",
    "gn:population":424,
    "gn:timezone":"America/Mexico_City",
    "iso:country":"MX",
    "wof:name":"Boca de Rivera",
    "wof:placetype":"locality",
    "wof:population":424
},
  "geometry": {"coordinates":[-102.90000000000001,22.50444],"type":"Point"}
}