{
  "type": "Feature",
  "properties": {
    "gn:admin1_code":"21",
    "gn:admin2_code":"194",
    "gn:asciiname":"Rancho las Palmas",
    "gn:country_code":"MX",
    "gn:dem":118,
    "gn:feature_class":"P",
    "gn:feature_code":"PPL",
    "gn:name":"Rancho las Palmas",
    "gn:population":50,
    "gn:timezone":"America/Mexico_City",
    "iso:country":"MX",
    "wof:name":"Rancho las Palmas",
    "wof:placetype":"locality",
    "wof:population":50
},
  "geometry": {"coordinates":[-97.64247,20.50512],"type":"Point"}
}