{
  "type": "Feature",
  "properties": {
    "gn:admin1_code":"12.0",
    "gn:admin2_code":"67.0",
    "gn:asciiname":"San Juan Mina",
    "gn:country_code":"MX",
    "gn:dem":274,
    "gn:feature_class":"P",
    "gn:feature_code":"PPL",
    "gn:name":"San Juan Mina",
    "gn:population":0,
    "gn:timezone":"America/Mexico_City",
    "iso:country":"MX",
    "name:spa_x_preferred":[
        "San Juan Mina"
    ],
    "wof:name":"San Juan Mina",
    "wof:placetype":"locality"
},
  "geometry": {"coordinates":[-100.52791999999999,18.23752],"type":"Point"}
}