{
  "type": "Feature",
  "properties": {
    "gn:admin1_code":"14.0",
    "gn:admin2_code":"85.0",
    "gn:asciiname":"El Atascoso",
    "gn:country_code":"MX",
    "gn:dem":1610,
    "gn:feature_class":"P",
    "gn:feature_code":"PPL",
    "gn:name":"El Atascoso",
    "gn:population":0,
    "gn:timezone":"America/Mexico_City",
    "iso:country":"MX",
    "name:spa_x_preferred":[
        "El Atascoso"
    ],
    "name:und_x_variant":[
        "La Atascosa"
    ],
    "wof:name":"El Atascoso",
    "wof:placetype":"locality"
},
  "geometry": {"coordinates":[-103.15111,19.83701],"type":"Point"}
}