{
  "type": "Feature",
  "properties": {
    "gn:admin1_code":"7",
    "gn:admin2_code":"33",
    "gn:asciiname":"El Capri",
    "gn:country_code":"MX",
    "gn:dem":1110,
    "gn:feature_class":"P",
    "gn:feature_code":"PPL",
    "gn:name":"El Capri",
    "gn:population":11,
    "gn:timezone":"America/Monterrey",
    "iso:country":"MX",
    "wof:name":"El Capri",
    "wof:placetype":"locality",
    "wof:population":11
},
  "geometry": {"coordinates":[-103.1473,25.76638],"type":"Point"}
}