{
  "type": "Feature",
  "properties": {
    "gn:admin1_code":"15.0",
    "gn:asciiname":"Llano Largo",
    "gn:country_code":"MX",
    "gn:dem":1982,
    "gn:feature_class":"P",
    "gn:feature_code":"PPL",
    "gn:name":"Llano Largo",
    "gn:population":0,
    "gn:timezone":"America/Mexico_City",
    "iso:country":"MX",
    "name:spa_x_preferred":[
        "Llano Largo"
    ],
    "wof:name":"Llano Largo",
    "wof:placetype":"locality"
},
  "geometry": {"coordinates":[-102.74033,19.9335],"type":"Point"}
}