{
  "type": "Feature",
  "properties": {
    "gn:admin1_code":"5",
    "gn:admin2_code":"107.0",
    "gn:asciiname":"Las Mariposas",
    "gn:country_code":"MX",
    "gn:dem":826,
    "gn:feature_class":"P",
    "gn:feature_code":"PPL",
    "gn:name":"Las Mariposas",
    "gn:population":5,
    "gn:timezone":"America/Mexico_City",
    "iso:country":"MX",
    "wof:name":"Las Mariposas",
    "wof:placetype":"locality",
    "wof:population":5
},
  "geometry": {"coordinates":[-93.33194,16.00861],"type":"Point"}
}