{
  "type": "Feature",
  "properties": {
    "gn:admin1_code":"5",
    "gn:admin2_code":"71.0",
    "gn:asciiname":"Saltillito",
    "gn:country_code":"MX",
    "gn:dem":28,
    "gn:feature_class":"P",
    "gn:feature_code":"PPL",
    "gn:name":"Saltillito",
    "gn:population":140,
    "gn:timezone":"America/Mexico_City",
    "iso:country":"MX",
    "wof:name":"Saltillito",
    "wof:placetype":"locality",
    "wof:population":140
},
  "geometry": {"coordinates":[-92.55103,15.17676],"type":"Point"}
}