{
  "type": "Feature",
  "properties": {
    "gn:admin1_code":"21",
    "gn:admin2_code":"183.0",
    "gn:asciiname":"Tlapitzalapa",
    "gn:country_code":"MX",
    "gn:dem":691,
    "gn:feature_class":"P",
    "gn:feature_code":"PPL",
    "gn:name":"Tlapitzalapa",
    "gn:population":438,
    "gn:timezone":"America/Mexico_City",
    "iso:country":"MX",
    "wof:name":"Tlapitzalapa",
    "wof:placetype":"locality",
    "wof:population":438
},
  "geometry": {"coordinates":[-97.84350999999999,20.18405],"type":"Point"}
}