{
  "type": "Feature",
  "properties": {
    "gn:admin1_code":"18",
    "gn:admin2_code":"11.0",
    "gn:asciiname":"El Vado de San Pedro",
    "gn:country_code":"MX",
    "gn:dem":24,
    "gn:feature_class":"P",
    "gn:feature_code":"PPL",
    "gn:name":"El Vado de San Pedro",
    "gn:population":0,
    "gn:timezone":"America/Mazatlan",
    "iso:country":"MX",
    "name:und_x_variant":[
        "San Pedro",
        "Vado Pedro",
        "El Vado de San Pedro"
    ],
    "wof:name":"El Vado de San Pedro",
    "wof:placetype":"locality"
},
  "geometry": {"coordinates":[-105.18004999999999,21.94742],"type":"Point"}
}