{
  "type": "Feature",
  "properties": {
    "gn:admin1_code":"10",
    "gn:admin2_code":"14.0",
    "gn:asciiname":"Yerbaniz",
    "gn:country_code":"MX",
    "gn:dem":1325,
    "gn:feature_class":"P",
    "gn:feature_code":"PPL",
    "gn:name":"Yerban\u00edz",
    "gn:population":120,
    "gn:timezone":"America/Monterrey",
    "iso:country":"MX",
    "name:und_x_variant":[
        "Yerban\u00edz"
    ],
    "wof:name":"Yerbaniz",
    "wof:placetype":"locality",
    "wof:population":120
},
  "geometry": {"coordinates":[-104.66968,22.69587000000001],"type":"Point"}
}