{
  "type": "Feature",
  "properties": {
    "gn:admin1_code":"10",
    "gn:admin2_code":"9.0",
    "gn:asciiname":"Palomas",
    "gn:country_code":"MX",
    "gn:dem":2236,
    "gn:feature_class":"P",
    "gn:feature_code":"PPL",
    "gn:name":"Palomas",
    "gn:population":1,
    "gn:timezone":"America/Monterrey",
    "iso:country":"MX",
    "name:cat_x_preferred":[
        "Palomas"
    ],
    "name:ceb_x_preferred":[
        "Palomas"
    ],
    "name:deu_x_preferred":[
        "Palomas"
    ],
    "name:nld_x_preferred":[
        "Palomas"
    ],
    "name:pol_x_preferred":[
        "Palomas"
    ],
    "name:spa_x_preferred":[
        "Palomas"
    ],
    "name:srp_x_preferred":[
        "\u041f\u0430\u043b\u043e\u043c\u0430\u0441"
    ],
    "name:swe_x_preferred":[
        "Palomas"
    ],
    "name:und_x_variant":[
        "Rancho Paloma",
        "Palomas"
    ],
    "wof:name":"Palomas",
    "wof:placetype":"locality",
    "wof:population":1
},
  "geometry": {"coordinates":[-105.63633,25.70057000000001],"type":"Point"}
}