{
  "type": "Feature",
  "properties": {
    "gn:admin1_code":"10",
    "gn:admin2_code":"4.0",
    "gn:asciiname":"La Bruja",
    "gn:country_code":"MX",
    "gn:dem":2043,
    "gn:feature_class":"P",
    "gn:feature_code":"PPL",
    "gn:name":"La Bruja",
    "gn:population":0,
    "gn:timezone":"America/Monterrey",
    "iso:country":"MX",
    "name:spa_x_preferred":[
        "La Bruja"
    ],
    "wof:name":"La Bruja",
    "wof:placetype":"locality"
},
  "geometry": {"coordinates":[-103.67797,24.59164],"type":"Point"}
}