{
  "type": "Feature",
  "properties": {
    "gn:admin1_code":"26",
    "gn:admin2_code":"45.0",
    "gn:asciiname":"Los Graseros",
    "gn:country_code":"MX",
    "gn:dem":1234,
    "gn:feature_class":"P",
    "gn:feature_code":"PPL",
    "gn:name":"Los Graseros",
    "gn:population":0,
    "gn:timezone":"America/Hermosillo",
    "iso:country":"MX",
    "name:spa_x_preferred":[
        "Los Graseros"
    ],
    "name:und_x_variant":[
        "Rancho Los Graseros"
    ],
    "wof:name":"Los Graseros",
    "wof:placetype":"locality"
},
  "geometry": {"coordinates":[-110.47629999999999,30.20068],"type":"Point"}
}