{
  "type": "Feature",
  "properties": {
    "gn:admin1_code":"6",
    "gn:admin2_code":"13.0",
    "gn:asciiname":"Los Nielsen (La Tinaja)",
    "gn:country_code":"MX",
    "gn:dem":1553,
    "gn:feature_class":"P",
    "gn:feature_code":"PPL",
    "gn:name":"Los Nielsen (La Tinaja)",
    "gn:population":5,
    "gn:timezone":"America/Chihuahua",
    "iso:country":"MX",
    "wof:name":"Los Nielsen (La Tinaja)",
    "wof:placetype":"locality",
    "wof:population":5
},
  "geometry": {"coordinates":[-108.05116,30.32781],"type":"Point"}
}