{
  "type": "Feature",
  "properties": {
    "gn:admin1_code":"32",
    "gn:admin2_code":"3.0",
    "gn:asciiname":"Nacaxquilco",
    "gn:country_code":"MX",
    "gn:dem":2254,
    "gn:feature_class":"P",
    "gn:feature_code":"PPL",
    "gn:name":"Nacaxquilco",
    "gn:population":6,
    "gn:timezone":"America/Mexico_City",
    "iso:country":"MX",
    "wof:name":"Nacaxquilco",
    "wof:placetype":"locality",
    "wof:population":6
},
  "geometry": {"coordinates":[-103.47139,21.69639],"type":"Point"}
}