{
  "type": "Feature",
  "properties": {
    "gn:admin1_code":"5",
    "gn:admin2_code":"2.0",
    "gn:asciiname":"San Pedro Nichi",
    "gn:country_code":"MX",
    "gn:dem":475,
    "gn:feature_class":"P",
    "gn:feature_code":"PPL",
    "gn:name":"San Pedro Nichi",
    "gn:population":72,
    "gn:timezone":"America/Mexico_City",
    "iso:country":"MX",
    "wof:name":"San Pedro Nichi",
    "wof:placetype":"locality",
    "wof:population":72
},
  "geometry": {"coordinates":[-92.78556,16.57528],"type":"Point"}
}