{
  "type": "Feature",
  "properties": {
    "gn:admin1_code":"5",
    "gn:admin2_code":"41.0",
    "gn:asciiname":"Monte los Olivos",
    "gn:country_code":"MX",
    "gn:dem":1191,
    "gn:feature_class":"P",
    "gn:feature_code":"PPL",
    "gn:name":"Monte los Olivos",
    "gn:population":68,
    "gn:timezone":"America/Mexico_City",
    "iso:country":"MX",
    "wof:name":"Monte los Olivos",
    "wof:placetype":"locality",
    "wof:population":68
},
  "geometry": {"coordinates":[-91.63444,16.245],"type":"Point"}
}