{
  "type": "Feature",
  "properties": {
    "gn:admin1_code":"22",
    "gn:admin2_code":"2.0",
    "gn:asciiname":"Coatlan de los Angeles",
    "gn:country_code":"MX",
    "gn:dem":1367,
    "gn:feature_class":"P",
    "gn:feature_code":"PPL",
    "gn:name":"Coatl\u00e1n de los \u00c1ngeles",
    "gn:population":267,
    "gn:timezone":"America/Mexico_City",
    "iso:country":"MX",
    "name:und_x_variant":[
        "Coatl\u00e1n de los \u00c1ngeles"
    ],
    "wof:name":"Coatlan de los Angeles",
    "wof:placetype":"locality",
    "wof:population":267
},
  "geometry": {"coordinates":[-99.59858,21.24013],"type":"Point"}
}