{
  "type": "Feature",
  "properties": {
    "gn:admin1_code":"5",
    "gn:admin2_code":"39.0",
    "gn:asciiname":"San Pedro Pabuchil Uno (Francisco I. Madero)",
    "gn:country_code":"MX",
    "gn:dem":934,
    "gn:feature_class":"P",
    "gn:feature_code":"PPL",
    "gn:name":"San Pedro Pabuchil Uno (Francisco I. Madero)",
    "gn:population":150,
    "gn:timezone":"America/Mexico_City",
    "iso:country":"MX",
    "wof:name":"San Pedro Pabuchil Uno (Francisco I. Madero)",
    "wof:placetype":"locality",
    "wof:population":150
},
  "geometry": {"coordinates":[-92.7675,17.28306],"type":"Point"}
}