{
  "type": "Feature",
  "properties": {
    "gn:admin1_code":"5",
    "gn:admin2_code":"107",
    "gn:asciiname":"Villalen",
    "gn:country_code":"MX",
    "gn:dem":1221,
    "gn:feature_class":"P",
    "gn:feature_code":"PPL",
    "gn:name":"Villal\u00e9n",
    "gn:population":34,
    "gn:timezone":"America/Mexico_City",
    "iso:country":"MX",
    "name:und_x_variant":[
        "Villal\u00e9n"
    ],
    "wof:name":"Villalen",
    "wof:placetype":"locality",
    "wof:population":34
},
  "geometry": {"coordinates":[-93.39028,15.94583],"type":"Point"}
}