{
  "type": "Feature",
  "properties": {
    "gn:admin1_code":"14",
    "gn:admin2_code":"104.0",
    "gn:asciiname":"La Bolsa",
    "gn:country_code":"MX",
    "gn:dem":2072,
    "gn:feature_class":"P",
    "gn:feature_code":"PPL",
    "gn:name":"La Bolsa",
    "gn:population":0,
    "gn:timezone":"America/Mexico_City",
    "iso:country":"MX",
    "name:spa_x_preferred":[
        "La Bolsa"
    ],
    "wof:name":"La Bolsa",
    "wof:placetype":"locality"
},
  "geometry": {"coordinates":[-103.50139,21.88821],"type":"Point"}
}