{
  "type": "Feature",
  "properties": {
    "gn:admin1_code":"5",
    "gn:admin2_code":"1.0",
    "gn:asciiname":"La Nueva Reforma",
    "gn:country_code":"MX",
    "gn:dem":515,
    "gn:feature_class":"P",
    "gn:feature_code":"PPL",
    "gn:name":"La Nueva Reforma",
    "gn:population":0,
    "gn:timezone":"America/Mexico_City",
    "iso:country":"MX",
    "name:spa_x_preferred":[
        "Reforma"
    ],
    "name:spa_x_variant":[
        "La Nueva Reforma"
    ],
    "wof:name":"La Nueva Reforma",
    "wof:placetype":"locality"
},
  "geometry": {"coordinates":[-92.75042000000001,15.43589],"type":"Point"}
}