{
  "type": "Feature",
  "properties": {
    "gn:admin1_code":"24",
    "gn:admin2_code":"57.0",
    "gn:asciiname":"Barrio de En Medio",
    "gn:country_code":"MX",
    "gn:dem":157,
    "gn:feature_class":"P",
    "gn:feature_code":"PPL",
    "gn:name":"Barrio de En Medio",
    "gn:population":714,
    "gn:timezone":"America/Mexico_City",
    "iso:country":"MX",
    "wof:name":"Barrio de En Medio",
    "wof:placetype":"locality",
    "wof:population":714
},
  "geometry": {"coordinates":[-98.83638999999999,21.33694],"type":"Point"}
}