{
  "type": "Feature",
  "properties": {
    "gn:admin1_code":"16",
    "gn:admin2_code":"49.0",
    "gn:asciiname":"El Terranate",
    "gn:country_code":"MX",
    "gn:dem":1579,
    "gn:feature_class":"P",
    "gn:feature_code":"PPL",
    "gn:name":"El Terranate",
    "gn:population":62,
    "gn:timezone":"America/Mexico_City",
    "iso:country":"MX",
    "wof:name":"El Terranate",
    "wof:placetype":"locality",
    "wof:population":62
},
  "geometry": {"coordinates":[-101.19750000000001,19.38778],"type":"Point"}
}