{
  "type": "Feature",
  "properties": {
    "gn:admin1_code":"6.0",
    "gn:admin2_code":"65.0",
    "gn:asciiname":"La Cueva",
    "gn:country_code":"MX",
    "gn:dem":2024,
    "gn:feature_class":"P",
    "gn:feature_code":"PPL",
    "gn:name":"La Cueva",
    "gn:population":0,
    "gn:timezone":"America/Chihuahua",
    "iso:country":"MX",
    "name:spa_x_preferred":[
        "La Cueva"
    ],
    "wof:name":"La Cueva",
    "wof:placetype":"locality"
},
  "geometry": {"coordinates":[-107.98215,27.42997],"type":"Point"}
}