{
  "type": "Feature",
  "properties": {
    "gn:admin1_code":"30",
    "gn:admin2_code":"44.0",
    "gn:asciiname":"La Ermita (Santa Maria de Guadalupe)",
    "gn:country_code":"MX",
    "gn:dem":972,
    "gn:feature_class":"P",
    "gn:feature_code":"PPL",
    "gn:name":"La Ermita (Santa Mar\u00eda de Guadalupe)",
    "gn:population":78,
    "gn:timezone":"America/Mexico_City",
    "iso:country":"MX",
    "name:und_x_variant":[
        "La Ermita (Santa Mar\u00eda de Guadalupe)"
    ],
    "wof:name":"La Ermita (Santa Maria de Guadalupe)",
    "wof:placetype":"locality",
    "wof:population":78
},
  "geometry": {"coordinates":[-96.95972,18.91583],"type":"Point"}
}