{
  "type": "Feature",
  "properties": {
    "gn:admin1_code":"7",
    "gn:admin2_code":"2",
    "gn:asciiname":"Pedro Chavez Uribe (Las Cuevas)",
    "gn:country_code":"MX",
    "gn:dem":285,
    "gn:feature_class":"P",
    "gn:feature_code":"PPL",
    "gn:name":"Pedro Ch\u00e1vez Uribe (Las Cuevas)",
    "gn:population":15,
    "gn:timezone":"America/Matamoros",
    "iso:country":"MX",
    "name:und_x_variant":[
        "Pedro Ch\u00e1vez Uribe (Las Cuevas)"
    ],
    "wof:name":"Pedro Chavez Uribe (Las Cuevas)",
    "wof:placetype":"locality",
    "wof:population":15
},
  "geometry": {"coordinates":[-100.97371,29.31412000000001],"type":"Point"}
}