{
  "type": "Feature",
  "properties": {
    "gn:admin1_code":"14",
    "gn:admin2_code":"61.0",
    "gn:asciiname":"El Puerto",
    "gn:country_code":"MX",
    "gn:dem":1636,
    "gn:feature_class":"P",
    "gn:feature_code":"PPL",
    "gn:name":"El Puerto",
    "gn:population":0,
    "gn:timezone":"America/Mexico_City",
    "iso:country":"MX",
    "name:spa_x_preferred":[
        "El Puerto"
    ],
    "wof:name":"El Puerto",
    "wof:placetype":"locality"
},
  "geometry": {"coordinates":[-103.76662,22.23617],"type":"Point"}
}