{
  "type": "Feature",
  "properties": {
    "gn:admin1_code":"19",
    "gn:admin2_code":"36.0",
    "gn:asciiname":"San Juanito",
    "gn:country_code":"MX",
    "gn:dem":1488,
    "gn:feature_class":"P",
    "gn:feature_code":"PPL",
    "gn:name":"San Juanito",
    "gn:population":0,
    "gn:timezone":"America/Monterrey",
    "iso:country":"MX",
    "name:ceb_x_preferred":[
        "San Juanito"
    ],
    "name:deu_x_preferred":[
        "San Juanito"
    ],
    "name:msa_x_preferred":[
        "San Juanito"
    ],
    "name:spa_x_preferred":[
        "San Juanito"
    ],
    "name:swe_x_preferred":[
        "San Juanito"
    ],
    "name:tgl_x_preferred":[
        "San Juanito"
    ],
    "name:vie_x_preferred":[
        "San Juanito"
    ],
    "wof:name":"San Juanito",
    "wof:placetype":"locality"
},
  "geometry": {"coordinates":[-100.11667,23.36667000000001],"type":"Point"}
}