{
  "type": "Feature",
  "properties": {
    "gn:admin1_code":"18",
    "gn:admin2_code":"9",
    "gn:asciiname":"Sixto Santiago Lincer",
    "gn:country_code":"MX",
    "gn:dem":772,
    "gn:feature_class":"P",
    "gn:feature_code":"PPL",
    "gn:name":"Sixto Santiago Lincer",
    "gn:population":15,
    "gn:timezone":"America/Mazatlan",
    "iso:country":"MX",
    "wof:name":"Sixto Santiago Lincer",
    "wof:placetype":"locality",
    "wof:population":15
},
  "geometry": {"coordinates":[-104.97556000000002,22.29806],"type":"Point"}
}