{
  "type": "Feature",
  "properties": {
    "gn:admin1_code":"20",
    "gn:admin2_code":"277.0",
    "gn:asciiname":"Rancho del Cura",
    "gn:country_code":"MX",
    "gn:dem":1396,
    "gn:feature_class":"P",
    "gn:feature_code":"PPL",
    "gn:name":"Rancho del Cura",
    "gn:population":128,
    "gn:timezone":"America/Mexico_City",
    "iso:country":"MX",
    "wof:name":"Rancho del Cura",
    "wof:placetype":"locality",
    "wof:population":128
},
  "geometry": {"coordinates":[-96.935,16.46917],"type":"Point"}
}