{
  "type": "Feature",
  "properties": {
    "gn:admin1_code":"25",
    "gn:admin2_code":"6.0",
    "gn:asciiname":"Agua Cercada",
    "gn:country_code":"MX",
    "gn:dem":71,
    "gn:feature_class":"P",
    "gn:feature_code":"PPL",
    "gn:name":"Agua Cercada",
    "gn:population":0,
    "gn:timezone":"America/Mazatlan",
    "iso:country":"MX",
    "name:spa_x_preferred":[
        "Agua Cercada"
    ],
    "wof:name":"Agua Cercada",
    "wof:placetype":"locality"
},
  "geometry": {"coordinates":[-107.5513,24.91773],"type":"Point"}
}