{
  "type": "Feature",
  "properties": {
    "gn:admin1_code":"14.0",
    "gn:admin2_code":"58.0",
    "gn:asciiname":"Arroyo del Pie",
    "gn:country_code":"MX",
    "gn:dem":2170,
    "gn:feature_class":"P",
    "gn:feature_code":"PPL",
    "gn:name":"Arroyo del Pie",
    "gn:population":0,
    "gn:timezone":"America/Mexico_City",
    "iso:country":"MX",
    "name:spa_x_preferred":[
        "Arroyo del Pie"
    ],
    "wof:name":"Arroyo del Pie",
    "wof:placetype":"locality"
},
  "geometry": {"coordinates":[-104.69118,20.57988],"type":"Point"}
}