{
  "type": "Feature",
  "properties": {
    "gn:admin1_code":"17",
    "gn:admin2_code":"1",
    "gn:asciiname":"Tula",
    "gn:country_code":"MX",
    "gn:dem":911,
    "gn:feature_class":"P",
    "gn:feature_code":"PPL",
    "gn:name":"Tula",
    "gn:population":11,
    "gn:timezone":"America/Mexico_City",
    "iso:country":"MX",
    "wof:name":"Tula",
    "wof:placetype":"locality",
    "wof:population":11
},
  "geometry": {"coordinates":[-99.34611,18.6175],"type":"Point"}
}