{
  "type": "Feature",
  "properties": {
    "gn:admin1_code":"17",
    "gn:admin2_code":"1",
    "gn:asciiname":"Tula",
    "gn:country_code":"MX",
    "gn:dem":911,
    "gn:feature_class":"P",
    "gn:feature_code":"PPL",
    "gn:name":"Tula",
    "gn:population":11,
    "gn:timezone":"America/Mexico_City",
    "iso:country":"MX",
    "name:ara_x_preferred":[
        "\u062a\u0648\u0644\u0627"
    ],
    "name:arg_x_preferred":[
        "Tula"
    ],
    "name:ben_x_preferred":[
        "\u09a4\u09c1\u09b2\u09be"
    ],
    "name:cat_x_preferred":[
        "Tula"
    ],
    "name:ceb_x_preferred":[
        "Tula"
    ],
    "name:ces_x_preferred":[
        "Tula"
    ],
    "name:chv_x_preferred":[
        "\u0422\u0443\u043b\u0103"
    ],
    "name:dan_x_preferred":[
        "Tula"
    ],
    "name:deu_x_preferred":[
        "Tula"
    ],
    "name:ell_x_preferred":[
        "\u03a4\u03bf\u03cd\u03bb\u03b1"
    ],
    "name:epo_x_preferred":[
        "Tula"
    ],
    "name:eus_x_preferred":[
        "Tula"
    ],
    "name:fas_x_preferred":[
        "\u062a\u0648\u0644\u0627"
    ],
    "name:fra_x_preferred":[
        "Tula"
    ],
    "name:heb_x_preferred":[
        "\u05d8\u05d5\u05dc\u05d4"
    ],
    "name:hin_x_preferred":[
        "\u0924\u0941\u0932\u093e"
    ],
    "name:hun_x_preferred":[
        "Tula"
    ],
    "name:hye_x_preferred":[
        "\u054f\u0578\u0582\u056c\u0561"
    ],
    "name:ind_x_preferred":[
        "Tula"
    ],
    "name:ita_x_preferred":[
        "Tula"
    ],
    "name:kor_x_preferred":[
        "\ud234\ub77c"
    ],
    "name:lat_x_preferred":[
        "Tula"
    ],
    "name:nld_x_preferred":[
        "Tula"
    ],
    "name:nor_x_preferred":[
        "Tula"
    ],
    "name:pol_x_preferred":[
        "Tula"
    ],
    "name:por_x_preferred":[
        "Tula"
    ],
    "name:ron_x_preferred":[
        "Tula"
    ],
    "name:rus_x_preferred":[
        "\u0422\u0443\u043b\u0430"
    ],
    "name:sco_x_preferred":[
        "Tula"
    ],
    "name:slk_x_preferred":[
        "Tula"
    ],
    "name:spa_x_preferred":[
        "Tula"
    ],
    "name:srp_x_preferred":[
        "\u0422\u0443\u043b\u0430"
    ],
    "name:swe_x_preferred":[
        "Tula"
    ],
    "name:tat_x_preferred":[
        "\u0422\u0443\u043b\u0430"
    ],
    "name:tur_x_preferred":[
        "Tula"
    ],
    "name:ukr_x_preferred":[
        "\u0422\u0443\u043b\u0430"
    ],
    "name:urd_x_preferred":[
        "\u062a\u0648\u0644\u0627"
    ],
    "name:uzb_x_preferred":[
        "Tula"
    ],
    "name:war_x_preferred":[
        "Tula"
    ],
    "name:zho_cn_x_preferred":[
        "\u56fe\u62c9"
    ],
    "name:zho_tw_x_preferred":[
        "\u5716\u62c9"
    ],
    "wof:name":"Tula",
    "wof:placetype":"locality",
    "wof:population":11
},
  "geometry": {"coordinates":[-99.34611,18.6175],"type":"Point"}
}