{
  "type": "Feature",
  "properties": {
    "gn:admin1_code":"17",
    "gn:admin2_code":"1",
    "gn:asciiname":"Tula",
    "gn:country_code":"MX",
    "gn:dem":911,
    "gn:feature_class":"P",
    "gn:feature_code":"PPL",
    "gn:name":"Tula",
    "gn:population":11,
    "gn:timezone":"America/Mexico_City",
    "iso:country":"MX",
    "name:arg_x_preferred":[
        "Tula"
    ],
    "name:cat_x_preferred":[
        "Tula"
    ],
    "name:ceb_x_preferred":[
        "Tula"
    ],
    "name:ces_x_preferred":[
        "Tula"
    ],
    "name:chv_x_preferred":[
        "\u0422\u0443\u043b\u0103"
    ],
    "name:dan_x_preferred":[
        "Tula"
    ],
    "name:deu_x_preferred":[
        "Tula"
    ],
    "name:epo_x_preferred":[
        "Tula"
    ],
    "name:eus_x_preferred":[
        "Tula"
    ],
    "name:fra_x_preferred":[
        "Tula"
    ],
    "name:heb_x_preferred":[
        "\u05d8\u05d5\u05dc\u05d4"
    ],
    "name:hun_x_preferred":[
        "Tula"
    ],
    "name:hye_x_preferred":[
        "\u054f\u0578\u0582\u056c\u0561"
    ],
    "name:ind_x_preferred":[
        "Tula"
    ],
    "name:ita_x_preferred":[
        "Tula"
    ],
    "name:lat_x_preferred":[
        "Tula"
    ],
    "name:nld_x_preferred":[
        "Tula"
    ],
    "name:nor_x_preferred":[
        "Tula"
    ],
    "name:pol_x_preferred":[
        "Tula"
    ],
    "name:por_x_preferred":[
        "Tula"
    ],
    "name:ron_x_preferred":[
        "Tula"
    ],
    "name:rus_x_preferred":[
        "\u0422\u0443\u043b\u0430"
    ],
    "name:sco_x_preferred":[
        "Tula"
    ],
    "name:slk_x_preferred":[
        "Tula"
    ],
    "name:spa_x_preferred":[
        "Tula"
    ],
    "name:srp_x_preferred":[
        "\u0422\u0443\u043b\u0430"
    ],
    "name:swe_x_preferred":[
        "Tula"
    ],
    "name:tat_x_preferred":[
        "\u0422\u0443\u043b\u0430"
    ],
    "name:ukr_x_preferred":[
        "\u0422\u0443\u043b\u0430"
    ],
    "name:uzb_x_preferred":[
        "Tula"
    ],
    "name:war_x_preferred":[
        "Tula"
    ],
    "wof:name":"Tula",
    "wof:placetype":"locality",
    "wof:population":11
},
  "geometry": {"coordinates":[-99.34611,18.6175],"type":"Point"}
}