{
  "type": "Feature",
  "properties": {
    "gn:admin1_code":"24",
    "gn:admin2_code":"32.0",
    "gn:asciiname":"Los Cuartos",
    "gn:country_code":"MX",
    "gn:dem":1799,
    "gn:feature_class":"P",
    "gn:feature_code":"PPL",
    "gn:name":"Los Cuartos",
    "gn:population":106,
    "gn:timezone":"America/Mexico_City",
    "iso:country":"MX",
    "wof:name":"Los Cuartos",
    "wof:placetype":"locality",
    "wof:population":106
},
  "geometry": {"coordinates":[-100.70528,21.66611],"type":"Point"}
}