{
  "type": "Feature",
  "properties": {
    "gn:admin1_code":"19",
    "gn:admin2_code":"17",
    "gn:asciiname":"Palma los Monos (San Juan de Dios)",
    "gn:country_code":"MX",
    "gn:dem":2022,
    "gn:feature_class":"P",
    "gn:feature_code":"PPL",
    "gn:name":"Palma los Monos (San Juan de Dios)",
    "gn:population":19,
    "gn:timezone":"America/Monterrey",
    "iso:country":"MX",
    "wof:name":"Palma los Monos (San Juan de Dios)",
    "wof:placetype":"locality",
    "wof:population":19
},
  "geometry": {"coordinates":[-100.00832,24.6373],"type":"Point"}
}