{
  "type": "Feature",
  "properties": {
    "gn:admin1_code":"28.0",
    "gn:admin2_code":"5.0",
    "gn:asciiname":"La Muralla",
    "gn:country_code":"MX",
    "gn:dem":150,
    "gn:feature_class":"P",
    "gn:feature_code":"PPL",
    "gn:name":"La Muralla",
    "gn:population":4,
    "gn:timezone":"America/Monterrey",
    "iso:country":"MX",
    "name:spa_x_preferred":[
        "La Muralla"
    ],
    "wof:name":"La Muralla",
    "wof:placetype":"locality",
    "wof:population":4
},
  "geometry": {"coordinates":[-98.50225,24.85523],"type":"Point"}
}