{
  "type": "Feature",
  "properties": {
    "gn:admin1_code":"16",
    "gn:admin2_code":"22.0",
    "gn:asciiname":"El Cafe",
    "gn:country_code":"MX",
    "gn:dem":1859,
    "gn:feature_class":"P",
    "gn:feature_code":"PPL",
    "gn:name":"El Caf\u00e9",
    "gn:population":8,
    "gn:timezone":"America/Mexico_City",
    "iso:country":"MX",
    "name:und_x_variant":[
        "El Caf\u00e9"
    ],
    "wof:name":"El Cafe",
    "wof:placetype":"locality",
    "wof:population":8
},
  "geometry": {"coordinates":[-101.00833,19.61972],"type":"Point"}
}