{
  "type": "Feature",
  "properties": {
    "gn:admin1_code":"6.0",
    "gn:admin2_code":"11.0",
    "gn:asciiname":"Alicia",
    "gn:country_code":"MX",
    "gn:dem":1218,
    "gn:feature_class":"P",
    "gn:feature_code":"PPL",
    "gn:name":"Alicia",
    "gn:population":10,
    "gn:timezone":"America/Chihuahua",
    "iso:country":"MX",
    "name:spa_x_preferred":[
        "Alicia"
    ],
    "wof:name":"Alicia",
    "wof:placetype":"locality",
    "wof:population":10
},
  "geometry": {"coordinates":[-105.1785,27.75688],"type":"Point"}
}