{
  "type": "Feature",
  "properties": {
    "gn:admin1_code":"6.0",
    "gn:admin2_code":"11.0",
    "gn:asciiname":"Alicia",
    "gn:country_code":"MX",
    "gn:dem":1218,
    "gn:feature_class":"P",
    "gn:feature_code":"PPL",
    "gn:name":"Alicia",
    "gn:population":10,
    "gn:timezone":"America/Chihuahua",
    "iso:country":"MX",
    "name:bre_x_preferred":[
        "Alicia"
    ],
    "name:ceb_x_preferred":[
        "Alicia"
    ],
    "name:deu_x_preferred":[
        "Alicia"
    ],
    "name:epo_x_preferred":[
        "Alica"
    ],
    "name:fra_x_preferred":[
        "Alicia"
    ],
    "name:hun_x_preferred":[
        "Alicia"
    ],
    "name:ita_x_preferred":[
        "Alicia"
    ],
    "name:jpn_x_preferred":[
        "\u30a2\u30ea\u30b7\u30a2"
    ],
    "name:kor_x_preferred":[
        "\uc5bc\ub9ac\uc0e4"
    ],
    "name:nld_x_preferred":[
        "Alicia"
    ],
    "name:por_x_preferred":[
        "Alicia"
    ],
    "name:rus_x_preferred":[
        "\u0410\u043b\u0438\u0441\u0438\u044f"
    ],
    "name:spa_x_preferred":[
        "Alicia"
    ],
    "name:swe_x_preferred":[
        "Alicia"
    ],
    "name:war_x_preferred":[
        "Alicia"
    ],
    "wof:name":"Alicia",
    "wof:placetype":"locality",
    "wof:population":10
},
  "geometry": {"coordinates":[-105.1785,27.75688],"type":"Point"}
}