{
  "type": "Feature",
  "properties": {
    "gn:admin1_code":"14",
    "gn:admin2_code":"87.0",
    "gn:asciiname":"Los Juarez",
    "gn:country_code":"MX",
    "gn:dem":1380,
    "gn:feature_class":"P",
    "gn:feature_code":"PPL",
    "gn:name":"Los Ju\u00e1rez",
    "gn:population":5,
    "gn:timezone":"America/Mexico_City",
    "iso:country":"MX",
    "name:und_x_variant":[
        "Los Ju\u00e1rez"
    ],
    "wof:name":"Los Juarez",
    "wof:placetype":"locality",
    "wof:population":5
},
  "geometry": {"coordinates":[-103.19583,19.44806],"type":"Point"}
}