{
  "type": "Feature",
  "properties": {
    "gn:admin1_code":"20",
    "gn:admin2_code":"189.0",
    "gn:asciiname":"Hondura Lucero",
    "gn:country_code":"MX",
    "gn:dem":1095,
    "gn:feature_class":"P",
    "gn:feature_code":"PPL",
    "gn:name":"Hondura Lucero",
    "gn:population":179,
    "gn:timezone":"America/Mexico_City",
    "iso:country":"MX",
    "wof:name":"Hondura Lucero",
    "wof:placetype":"locality",
    "wof:population":179
},
  "geometry": {"coordinates":[-95.92556,17.27639],"type":"Point"}
}