{
  "type": "Feature",
  "properties": {
    "gn:admin1_code":"4",
    "gn:admin2_code":"7",
    "gn:asciiname":"La Guadalupe",
    "gn:country_code":"MX",
    "gn:dem":7,
    "gn:feature_class":"P",
    "gn:feature_code":"PPL",
    "gn:name":"La Guadalupe",
    "gn:population":16,
    "gn:timezone":"America/Merida",
    "iso:country":"MX",
    "wof:name":"La Guadalupe",
    "wof:placetype":"locality",
    "wof:population":16
},
  "geometry": {"coordinates":[-91.82250000000001,18.025],"type":"Point"}
}