{
  "type": "Feature",
  "properties": {
    "gn:admin1_code":"6",
    "gn:admin2_code":"9",
    "gn:asciiname":"Maquibo",
    "gn:country_code":"MX",
    "gn:dem":2365,
    "gn:feature_class":"P",
    "gn:feature_code":"PPL",
    "gn:name":"Maquibo",
    "gn:population":14,
    "gn:timezone":"America/Chihuahua",
    "iso:country":"MX",
    "wof:name":"Maquibo",
    "wof:placetype":"locality",
    "wof:population":14
},
  "geometry": {"coordinates":[-107.55631,27.72131],"type":"Point"}
}