{
  "type": "Feature",
  "properties": {
    "gn:admin1_code":"22.0",
    "gn:admin2_code":"5.0",
    "gn:asciiname":"Tierra Adentro",
    "gn:country_code":"MX",
    "gn:dem":2632,
    "gn:feature_class":"P",
    "gn:feature_code":"PPL",
    "gn:name":"Tierra Adentro",
    "gn:population":0,
    "gn:timezone":"America/Mexico_City",
    "iso:country":"MX",
    "name:spa_x_preferred":[
        "Tierra Adentro"
    ],
    "wof:name":"Tierra Adentro",
    "wof:placetype":"locality"
},
  "geometry": {"coordinates":[-100.13842,20.92603],"type":"Point"}
}