{
  "type": "Feature",
  "properties": {
    "gn:admin1_code":"6.0",
    "gn:admin2_code":"28.0",
    "gn:asciiname":"El Milagro",
    "gn:country_code":"MX",
    "gn:dem":1457,
    "gn:feature_class":"P",
    "gn:feature_code":"PPL",
    "gn:name":"El Milagro",
    "gn:population":3,
    "gn:timezone":"America/Chihuahua",
    "iso:country":"MX",
    "name:spa_x_preferred":[
        "El Milagro"
    ],
    "wof:name":"El Milagro",
    "wof:placetype":"locality",
    "wof:population":3
},
  "geometry": {"coordinates":[-106.09875,31.01002],"type":"Point"}
}