{
  "type": "Feature",
  "properties": {
    "gn:gn_country":"MX",
    "gn:gn_fcode":"PPL",
    "gn:gn_pop":0,
    "iso:country":"MX",
    "name:fas_x_preferred":[
        "\u062f\u06cc\u0648\u06cc\u0633\u0648\u0646 \u062f\u0644 \u0646\u0648\u0631\u062a\u0647"
    ],
    "name:ita_x_preferred":[
        "Divisi\u00f3n del Norte"
    ],
    "name:kor_x_preferred":[
        "\ubd81\ubd80\uc0ac\ub2e8"
    ],
    "name:nld_x_preferred":[
        "Divisie van het Noorden"
    ],
    "name:spa_x_preferred":[
        "Divisi\u00f3n del Norte"
    ],
    "qs_pg:aaroncc":"MX",
    "qs_pg:gn_country":"MX",
    "qs_pg:gn_fcode":"PPL",
    "qs_pg:gn_pop":0,
    "qs_pg:name":"Divisi\u00f3n del Norte",
    "qs_pg:name_adm0":"M\u00e9xico",
    "qs_pg:name_adm1":"Coahuila de Zaragoza",
    "qs_pg:photos":67,
    "qs_pg:photos_1k":14,
    "qs_pg:photos_9k":1,
    "qs_pg:photos_9r":2,
    "qs_pg:photos_all":67,
    "qs_pg:photos_sr":2,
    "qs_pg:pop_sr":0,
    "qs_pg:qs_pg_placetype":"locality",
    "qs_pg:qs_pg_placetype_gp":"Town",
    "qs_pg:woe_adm0":23424900,
    "woe:adm0_id":23424900,
    "woe:name_adm0":"M\u00e9xico",
    "woe:name_adm1":"Coahuila de Zaragoza",
    "woe:placetype":"Town",
    "wof:name":"Divisi\u00f3n del Norte",
    "wof:placetype":"locality"
},
  "geometry": {"coordinates":[-103.38333,25.51667],"type":"Point"}
}