{
  "type": "Feature",
  "properties": {
    "gn:admin1_code":"13",
    "gn:admin2_code":"34",
    "gn:asciiname":"El Coyol",
    "gn:country_code":"MX",
    "gn:dem":915,
    "gn:feature_class":"P",
    "gn:feature_code":"PPL",
    "gn:name":"El Coyol",
    "gn:population":10,
    "gn:timezone":"America/Mexico_City",
    "iso:country":"MX",
    "wof:name":"El Coyol",
    "wof:placetype":"locality",
    "wof:population":10
},
  "geometry": {"coordinates":[-98.72445999999999,20.95833],"type":"Point"}
}