{
  "type": "Feature",
  "properties": {
    "gn:admin1_code":"21",
    "gn:asciiname":"Josefa Ortiz de Dominguez",
    "gn:country_code":"MX",
    "gn:dem":114,
    "gn:feature_class":"P",
    "gn:feature_code":"PPL",
    "gn:name":"Josefa Ort\u00edz de Dom\u00ednguez",
    "gn:population":0,
    "gn:timezone":"America/Mexico_City",
    "iso:country":"MX",
    "name:spa_x_preferred":[
        "Josefa Ort\u00edz de Dom\u00ednguez"
    ],
    "name:spa_x_variant":[
        "Tabasquito"
    ],
    "wof:name":"Josefa Ortiz de Dominguez",
    "wof:placetype":"locality"
},
  "geometry": {"coordinates":[-97.77981,20.83791],"type":"Point"}
}