{
  "type": "Feature",
  "properties": {
    "gn:admin1_code":"14.0",
    "gn:admin2_code":"37.0",
    "gn:asciiname":"Aguacates",
    "gn:country_code":"MX",
    "gn:dem":865,
    "gn:feature_class":"P",
    "gn:feature_code":"PPL",
    "gn:name":"Aguacates",
    "gn:population":0,
    "gn:timezone":"America/Mexico_City",
    "iso:country":"MX",
    "name:und_x_variant":[
        "Ahuacates",
        "Aguacate",
        "Aguacates"
    ],
    "wof:name":"Aguacates",
    "wof:placetype":"locality"
},
  "geometry": {"coordinates":[-104.14737,19.71521],"type":"Point"}
}