{
  "type": "Feature",
  "properties": {
    "gn:admin1_code":"27",
    "gn:admin2_code":"5.0",
    "gn:asciiname":"Reyes Hernandez Segunda Seccion",
    "gn:country_code":"MX",
    "gn:dem":14,
    "gn:feature_class":"P",
    "gn:feature_code":"PPL",
    "gn:name":"Reyes Hern\u00e1ndez Segunda Secci\u00f3n",
    "gn:population":0,
    "gn:timezone":"America/Mexico_City",
    "iso:country":"MX",
    "name:spa_x_preferred":[
        "Reyes Hernandez Segunda Secci\u00f3n"
    ],
    "name:spa_x_variant":[
        "Reyes Hern\u00e1ndez Segunda Secci\u00f3n"
    ],
    "wof:name":"Reyes Hernandez Segunda Seccion",
    "wof:placetype":"locality"
},
  "geometry": {"coordinates":[-93.25614,18.23831],"type":"Point"}
}