{
  "type": "Feature",
  "properties": {
    "gn:admin1_code":"23",
    "gn:admin2_code":"4.0",
    "gn:asciiname":"Moreno",
    "gn:country_code":"MX",
    "gn:dem":42,
    "gn:feature_class":"P",
    "gn:feature_code":"PPL",
    "gn:name":"Moreno",
    "gn:population":0,
    "gn:timezone":"America/Cancun",
    "iso:country":"MX",
    "name:ara_x_preferred":[
        "\u0645\u0648\u0631\u064a\u0646\u0648"
    ],
    "name:bul_x_preferred":[
        "\u041c\u043e\u0440\u0435\u043d\u043e"
    ],
    "name:cat_x_preferred":[
        "Moreno"
    ],
    "name:ceb_x_preferred":[
        "Moreno"
    ],
    "name:ces_x_preferred":[
        "Moreno"
    ],
    "name:deu_x_preferred":[
        "Moreno"
    ],
    "name:fin_x_preferred":[
        "Moreno"
    ],
    "name:fra_x_preferred":[
        "Moreno"
    ],
    "name:heb_x_preferred":[
        "\u05de\u05d5\u05e8\u05e0\u05d5"
    ],
    "name:ita_x_preferred":[
        "Moreno"
    ],
    "name:jpn_x_preferred":[
        "\u30e2\u30ec\u30ce"
    ],
    "name:kor_x_preferred":[
        "\ubaa8\ub808\ub178"
    ],
    "name:lav_x_preferred":[
        "Moreno"
    ],
    "name:lit_x_preferred":[
        "Morenas"
    ],
    "name:nld_x_preferred":[
        "Moreno"
    ],
    "name:pol_x_preferred":[
        "Moreno"
    ],
    "name:por_x_preferred":[
        "Moreno"
    ],
    "name:rus_x_preferred":[
        "\u041c\u043e\u0440\u0435\u043d\u043e"
    ],
    "name:sco_x_preferred":[
        "Moreno"
    ],
    "name:slk_x_preferred":[
        "Moreno"
    ],
    "name:spa_x_preferred":[
        "Moreno"
    ],
    "name:srp_x_preferred":[
        "\u041c\u043e\u0440\u0435\u043d\u043e"
    ],
    "name:swe_x_preferred":[
        "Moreno"
    ],
    "name:ukr_x_preferred":[
        "\u041c\u043e\u0440\u0435\u043d\u043e"
    ],
    "wof:name":"Moreno",
    "wof:placetype":"locality"
},
  "geometry": {"coordinates":[-88.76666999999998,18.36667000000001],"type":"Point"}
}