{
  "type": "Feature",
  "properties": {
    "gn:admin1_code":"6.0",
    "gn:admin2_code":"19.0",
    "gn:asciiname":"Coyamito Sur",
    "gn:country_code":"MX",
    "gn:dem":1552,
    "gn:feature_class":"P",
    "gn:feature_code":"PPL",
    "gn:name":"Coyamito Sur",
    "gn:population":0,
    "gn:timezone":"America/Chihuahua",
    "iso:country":"MX",
    "name:und_x_variant":[
        "Rancho El Coyamito",
        "Coyamito Sur"
    ],
    "wof:name":"Coyamito Sur",
    "wof:placetype":"locality"
},
  "geometry": {"coordinates":[-106.21219000000001,29.73174],"type":"Point"}
}