{
  "type": "Feature",
  "properties": {
    "gn:admin1_code":"28",
    "gn:admin2_code":"6.0",
    "gn:asciiname":"Tanquecillo",
    "gn:country_code":"MX",
    "gn:dem":1763,
    "gn:feature_class":"P",
    "gn:feature_code":"PPL",
    "gn:name":"Tanquecillo",
    "gn:population":0,
    "gn:timezone":"America/Monterrey",
    "iso:country":"MX",
    "wof:name":"Tanquecillo",
    "wof:placetype":"locality"
},
  "geometry": {"coordinates":[-99.78333000000001,23.28333],"type":"Point"}
}