{
  "type": "Feature",
  "properties": {
    "gn:admin1_code":"30",
    "gn:admin2_code":"172.0",
    "gn:asciiname":"La Joya",
    "gn:country_code":"MX",
    "gn:dem":42,
    "gn:feature_class":"P",
    "gn:feature_code":"PPL",
    "gn:name":"La Joya",
    "gn:population":6,
    "gn:timezone":"America/Mexico_City",
    "iso:country":"MX",
    "name:ceb_x_preferred":[
        "La Joya"
    ],
    "name:deu_x_preferred":[
        "La Joya"
    ],
    "name:nld_x_preferred":[
        "La Joya"
    ],
    "name:que_x_preferred":[
        "La Joya"
    ],
    "name:spa_x_preferred":[
        "La Joya"
    ],
    "name:srp_x_preferred":[
        "\u041b\u0430 \u0425\u043e\u0458\u0430"
    ],
    "name:swe_x_preferred":[
        "La Joya"
    ],
    "wof:name":"La Joya",
    "wof:placetype":"locality",
    "wof:population":6
},
  "geometry": {"coordinates":[-94.83278,17.90306],"type":"Point"}
}