{
  "type": "Feature",
  "properties": {
    "gn:admin1_code":"25",
    "gn:admin2_code":"12.0",
    "gn:asciiname":"El Tamarindo",
    "gn:country_code":"MX",
    "gn:dem":36,
    "gn:feature_class":"P",
    "gn:feature_code":"PPL",
    "gn:name":"El Tamarindo",
    "gn:population":6,
    "gn:timezone":"America/Mazatlan",
    "iso:country":"MX",
    "wof:name":"El Tamarindo",
    "wof:placetype":"locality",
    "wof:population":6
},
  "geometry": {"coordinates":[-106.39493,23.29978],"type":"Point"}
}