{
  "type": "Feature",
  "properties": {
    "gn:admin1_code":"24",
    "gn:admin2_code":"10.0",
    "gn:asciiname":"Magdaleno Cedillo",
    "gn:country_code":"MX",
    "gn:dem":1262,
    "gn:feature_class":"P",
    "gn:feature_code":"PPL",
    "gn:name":"Magdaleno Cedillo",
    "gn:population":0,
    "gn:timezone":"America/Mexico_City",
    "iso:country":"MX",
    "name:spa_x_preferred":[
        "Magdaleno Cedillo"
    ],
    "wof:name":"Magdaleno Cedillo",
    "wof:placetype":"locality"
},
  "geometry": {"coordinates":[-99.5947,22.4736],"type":"Point"}
}