{
  "type": "Feature",
  "properties": {
    "iso:country":"MX",
    "name:cat_x_preferred":[
        "Jardines del Hip\u00f3dromo"
    ],
    "name:deu_x_preferred":[
        "Jardines del Hip\u00f3dromo"
    ],
    "name:spa_x_preferred":[
        "Jardines Del Cerro",
        "Jardines del Hip\u00f3dromo"
    ],
    "name:urd_x_preferred":[
        "\u062c\u0631\u062f\u0646\u0633 \u062f\u0644 \u06c1\u067e\u0648\u062f\u0631\u0648\u0645\u0648\u060c \u0645\u0648\u0646\u0679\u06cc\u0648\u06cc\u0688\u06cc\u0648"
    ],
    "qs:gn_adm0_cc":"MX",
    "qs:gn_local":3995465,
    "qs:gn_nam_loc":"Monterrey, Monterrey, Nuevo Leon, MX",
    "qs:gn_namadm1":"19",
    "qs:local_max":2766,
    "qs:local_sum":15661,
    "qs:localhoods":40,
    "qs:name":"Jardines Del Cerro",
    "qs:name_adm0":"M\u00e9xico",
    "qs:name_adm1":"Nuevo Leon",
    "qs:name_adm2":"Monterrey",
    "qs:name_local":"Monterrey",
    "qs:photo_max":24,
    "qs:photo_sum":85,
    "qs:placetype":"Suburb",
    "qs:quad_count":8,
    "qs:woe_adm0":23424900,
    "qs:woe_adm1":2346282,
    "qs:woe_adm2":12600645,
    "qs:woe_lau":0,
    "qs:woe_local":134047,
    "qs:woe_ver":"7.10.0",
    "wof:lang":[
        "spa"
    ],
    "wof:name":"Jardines Del Cerro",
    "wof:placetype":"neighbourhood"
},
  "geometry": {"coordinates":[-100.353424,25.679286],"type":"Point"}
}