{
  "type": "Feature",
  "properties": {
    "gn:admin1_code":"20",
    "gn:admin2_code":"302",
    "gn:asciiname":"Barrio San Nicolas",
    "gn:country_code":"MX",
    "gn:dem":235,
    "gn:feature_class":"P",
    "gn:feature_code":"PPL",
    "gn:name":"Barrio San Nicol\u00e1s",
    "gn:population":16,
    "gn:timezone":"America/Mexico_City",
    "iso:country":"MX",
    "name:und_x_variant":[
        "Barrio San Nicol\u00e1s"
    ],
    "wof:name":"Barrio San Nicolas",
    "wof:placetype":"locality",
    "wof:population":16
},
  "geometry": {"coordinates":[-97.98917,16.49167000000001],"type":"Point"}
}