{
  "type": "Feature",
  "properties": {
    "gn:admin1_code":"7",
    "gn:admin2_code":"36.0",
    "gn:asciiname":"Nuevos Margaritas",
    "gn:country_code":"MX",
    "gn:dem":1109,
    "gn:feature_class":"P",
    "gn:feature_code":"PPL",
    "gn:name":"Nuevos Margaritas",
    "gn:population":0,
    "gn:timezone":"America/Monterrey",
    "iso:country":"MX",
    "wof:name":"Nuevos Margaritas",
    "wof:placetype":"locality"
},
  "geometry": {"coordinates":[-103.06667,25.53333],"type":"Point"}
}