{
  "type": "Feature",
  "properties": {
    "gn:admin1_code":"15",
    "gn:admin2_code":"14.0",
    "gn:asciiname":"San Luis",
    "gn:country_code":"MX",
    "gn:dem":2672,
    "gn:feature_class":"P",
    "gn:feature_code":"PPL",
    "gn:name":"San Luis",
    "gn:population":0,
    "gn:timezone":"America/Mexico_City",
    "iso:country":"MX",
    "wof:name":"San Luis",
    "wof:placetype":"locality"
},
  "geometry": {"coordinates":[-99.8292,19.85684],"type":"Point"}
}