{
  "type": "Feature",
  "properties": {
    "gn:admin1_code":"25",
    "gn:admin2_code":"14.0",
    "gn:asciiname":"Los Huanacaxtles",
    "gn:country_code":"MX",
    "gn:dem":21,
    "gn:feature_class":"P",
    "gn:feature_code":"PPL",
    "gn:name":"Los Huanacaxtles",
    "gn:population":6,
    "gn:timezone":"America/Mazatlan",
    "iso:country":"MX",
    "wof:name":"Los Huanacaxtles",
    "wof:placetype":"locality",
    "wof:population":6
},
  "geometry": {"coordinates":[-105.88391,22.95111],"type":"Point"}
}