{
  "type": "Feature",
  "properties": {
    "gn:admin1_code":"16.0",
    "gn:admin2_code":"10.0",
    "gn:asciiname":"Las Parotas",
    "gn:country_code":"MX",
    "gn:dem":293,
    "gn:feature_class":"P",
    "gn:feature_code":"PPL",
    "gn:name":"Las Parotas",
    "gn:population":0,
    "gn:timezone":"America/Mexico_City",
    "iso:country":"MX",
    "name:spa_x_preferred":[
        "Las Parotas"
    ],
    "wof:name":"Las Parotas",
    "wof:placetype":"locality"
},
  "geometry": {"coordinates":[-102.07120999999999,18.29176],"type":"Point"}
}