{
  "type": "Feature",
  "properties": {
    "gn:admin1_code":"26.0",
    "gn:admin2_code":"57.0",
    "gn:asciiname":"El Aguajito",
    "gn:country_code":"MX",
    "gn:dem":601,
    "gn:feature_class":"P",
    "gn:feature_code":"PPL",
    "gn:name":"El Aguajito",
    "gn:population":0,
    "gn:timezone":"America/Hermosillo",
    "iso:country":"MX",
    "name:spa_x_preferred":[
        "El Aguajito"
    ],
    "wof:name":"El Aguajito",
    "wof:placetype":"locality"
},
  "geometry": {"coordinates":[-109.91998999999998,29.41006],"type":"Point"}
}