{
  "type": "Feature",
  "properties": {
    "gn:admin1_code":"16",
    "gn:admin2_code":"50",
    "gn:asciiname":"San Juanito",
    "gn:country_code":"MX",
    "gn:dem":2027,
    "gn:feature_class":"P",
    "gn:feature_code":"PPL",
    "gn:name":"San Juanito",
    "gn:population":51,
    "gn:timezone":"America/Mexico_City",
    "iso:country":"MX",
    "wof:name":"San Juanito",
    "wof:placetype":"locality",
    "wof:population":51
},
  "geometry": {"coordinates":[-100.41361000000001,19.93028],"type":"Point"}
}