{
  "type": "Feature",
  "properties": {
    "gn:admin1_code":"5",
    "gn:admin2_code":"62.0",
    "gn:asciiname":"Grano de Oro",
    "gn:country_code":"MX",
    "gn:dem":67,
    "gn:feature_class":"P",
    "gn:feature_code":"PPL",
    "gn:name":"Grano de Oro",
    "gn:population":7,
    "gn:timezone":"America/Mexico_City",
    "iso:country":"MX",
    "wof:name":"Grano de Oro",
    "wof:placetype":"locality",
    "wof:population":7
},
  "geometry": {"coordinates":[-93.50528,17.47361],"type":"Point"}
}