{
  "type": "Feature",
  "properties": {
    "gn:admin1_code":"19.0",
    "gn:asciiname":"Cuatro Hermanos",
    "gn:country_code":"MX",
    "gn:dem":420,
    "gn:feature_class":"P",
    "gn:feature_code":"PPL",
    "gn:name":"Cuatro Hermanos",
    "gn:population":0,
    "gn:timezone":"America/Monterrey",
    "iso:country":"MX",
    "name:spa_x_preferred":[
        "Cuatro Hermanos"
    ],
    "wof:name":"Cuatro Hermanos",
    "wof:placetype":"locality"
},
  "geometry": {"coordinates":[-100.19849000000001,25.90044],"type":"Point"}
}