{
  "type": "Feature",
  "properties": {
    "gn:admin1_code":"25.0",
    "gn:admin2_code":"6.0",
    "gn:asciiname":"Aguaruto",
    "gn:country_code":"MX",
    "gn:dem":32,
    "gn:feature_class":"P",
    "gn:feature_code":"PPL",
    "gn:name":"Aguaruto",
    "gn:population":0,
    "gn:timezone":"America/Mazatlan",
    "iso:country":"MX",
    "wof:name":"Aguaruto",
    "wof:placetype":"locality"
},
  "geometry": {"coordinates":[-107.51136,24.77895],"type":"Point"}
}