{
  "type": "Feature",
  "properties": {
    "gn:admin1_code":"30",
    "gn:admin2_code":"115.0",
    "gn:asciiname":"Santa Cruz Muyuapan",
    "gn:country_code":"MX",
    "gn:dem":2353,
    "gn:feature_class":"P",
    "gn:feature_code":"PPL",
    "gn:name":"Santa Cruz Muyuapan",
    "gn:population":270,
    "gn:timezone":"America/Mexico_City",
    "iso:country":"MX",
    "wof:name":"Santa Cruz Muyuapan",
    "wof:placetype":"locality",
    "wof:population":270
},
  "geometry": {"coordinates":[-97.21194,18.88306],"type":"Point"}
}