{
  "type": "Feature",
  "properties": {
    "gn:admin1_code":"6",
    "gn:admin2_code":"9.0",
    "gn:asciiname":"Rolirabo",
    "gn:country_code":"MX",
    "gn:dem":2184,
    "gn:feature_class":"P",
    "gn:feature_code":"PPL",
    "gn:name":"Rolirabo",
    "gn:population":5,
    "gn:timezone":"America/Chihuahua",
    "iso:country":"MX",
    "wof:name":"Rolirabo",
    "wof:placetype":"locality",
    "wof:population":5
},
  "geometry": {"coordinates":[-107.73583000000001,27.63667],"type":"Point"}
}