{
  "type": "Feature",
  "properties": {
    "gn:admin1_code":"6",
    "gn:admin2_code":"27.0",
    "gn:asciiname":"Rihuisuchi",
    "gn:country_code":"MX",
    "gn:dem":2270,
    "gn:feature_class":"P",
    "gn:feature_code":"PPL",
    "gn:name":"Rihuisuchi",
    "gn:population":0,
    "gn:timezone":"America/Chihuahua",
    "iso:country":"MX",
    "name:spa_x_preferred":[
        "Rihuisuchi"
    ],
    "wof:name":"Rihuisuchi",
    "wof:placetype":"locality"
},
  "geometry": {"coordinates":[-107.47855,27.50967],"type":"Point"}
}