{
  "type": "Feature",
  "properties": {
    "gn:admin1_code":"23",
    "gn:admin2_code":"6.0",
    "gn:asciiname":"Los Cuatre Hermanos",
    "gn:country_code":"MX",
    "gn:dem":33,
    "gn:feature_class":"P",
    "gn:feature_code":"PPL",
    "gn:name":"Los Cuatre Hermanos",
    "gn:population":0,
    "gn:timezone":"America/Cancun",
    "iso:country":"MX",
    "name:spa_x_preferred":[
        "Los Cuatre Hermanos"
    ],
    "wof:name":"Los Cuatre Hermanos",
    "wof:placetype":"locality"
},
  "geometry": {"coordinates":[-88.69006999999998,19.73369],"type":"Point"}
}