{
  "type": "Feature",
  "properties": {
    "gn:admin1_code":"13",
    "gn:admin2_code":"67.0",
    "gn:asciiname":"El Solis",
    "gn:country_code":"MX",
    "gn:dem":2072,
    "gn:feature_class":"P",
    "gn:feature_code":"PPL",
    "gn:name":"El Sol\u00eds",
    "gn:population":8,
    "gn:timezone":"America/Mexico_City",
    "iso:country":"MX",
    "name:und_x_variant":[
        "El Sol\u00eds"
    ],
    "wof:name":"El Solis",
    "wof:placetype":"locality",
    "wof:population":8
},
  "geometry": {"coordinates":[-99.29134999999999,20.09399],"type":"Point"}
}