{
  "type": "Feature",
  "properties": {
    "gn:admin1_code":"19",
    "gn:admin2_code":"32.0",
    "gn:asciiname":"El Chapote",
    "gn:country_code":"MX",
    "gn:dem":394,
    "gn:feature_class":"P",
    "gn:feature_code":"PPL",
    "gn:name":"El Chapote",
    "gn:population":0,
    "gn:timezone":"America/Monterrey",
    "iso:country":"MX",
    "name:spa_x_preferred":[
        "El Chapote"
    ],
    "name:und_x_variant":[
        "Rancho Chapote"
    ],
    "wof:name":"El Chapote",
    "wof:placetype":"locality"
},
  "geometry": {"coordinates":[-100.43065,27.02581],"type":"Point"}
}