{
  "type": "Feature",
  "properties": {
    "gn:admin1_code":"13",
    "gn:admin2_code":"44.0",
    "gn:asciiname":"Barrio La Sala",
    "gn:country_code":"MX",
    "gn:dem":2618,
    "gn:feature_class":"P",
    "gn:feature_code":"PPL",
    "gn:name":"Barrio La Sala",
    "gn:population":0,
    "gn:timezone":"America/Mexico_City",
    "iso:country":"MX",
    "name:spa_x_preferred":[
        "Barrio La Sala"
    ],
    "wof:name":"Barrio La Sala",
    "wof:placetype":"locality"
},
  "geometry": {"coordinates":[-99.61927,20.25889],"type":"Point"}
}