{
  "type": "Feature",
  "properties": {
    "gn:admin1_code":"30.0",
    "gn:admin2_code":"123.0",
    "gn:asciiname":"Las Potrancas",
    "gn:country_code":"MX",
    "gn:dem":5,
    "gn:feature_class":"P",
    "gn:feature_code":"PPL",
    "gn:name":"Las Potrancas",
    "gn:population":0,
    "gn:timezone":"America/Mexico_City",
    "iso:country":"MX",
    "name:spa_x_preferred":[
        "Las Potrancas"
    ],
    "wof:name":"Las Potrancas",
    "wof:placetype":"locality"
},
  "geometry": {"coordinates":[-98.02500000000001,22.16944],"type":"Point"}
}