{
  "type": "Feature",
  "properties": {
    "gn:admin1_code":"5",
    "gn:admin2_code":"101.0",
    "gn:asciiname":"San Juan",
    "gn:country_code":"MX",
    "gn:dem":698,
    "gn:feature_class":"P",
    "gn:feature_code":"PPL",
    "gn:name":"San Juan",
    "gn:population":64,
    "gn:timezone":"America/Mexico_City",
    "iso:country":"MX",
    "wof:name":"San Juan",
    "wof:placetype":"locality",
    "wof:population":64
},
  "geometry": {"coordinates":[-93.12917,16.80139],"type":"Point"}
}