{
  "type": "Feature",
  "properties": {
    "gn:admin1_code":"14",
    "gn:admin2_code":"92",
    "gn:asciiname":"Agua Honda",
    "gn:country_code":"MX",
    "gn:dem":1361,
    "gn:feature_class":"P",
    "gn:feature_code":"PPL",
    "gn:name":"Agua Honda",
    "gn:population":49,
    "gn:timezone":"America/Mexico_City",
    "iso:country":"MX",
    "wof:name":"Agua Honda",
    "wof:placetype":"locality",
    "wof:population":49
},
  "geometry": {"coordinates":[-103.38556,20.13417],"type":"Point"}
}