{
  "type": "Feature",
  "properties": {
    "gn:admin1_code":"14.0",
    "gn:asciiname":"Ringlera",
    "gn:country_code":"MX",
    "gn:dem":1918,
    "gn:feature_class":"P",
    "gn:feature_code":"PPL",
    "gn:name":"Ringlera",
    "gn:population":0,
    "gn:timezone":"America/Mexico_City",
    "iso:country":"MX",
    "name:spa_x_preferred":[
        "Ringlera"
    ],
    "wof:name":"Ringlera",
    "wof:placetype":"locality"
},
  "geometry": {"coordinates":[-102.32605,21.02445],"type":"Point"}
}