{
  "type": "Feature",
  "properties": {
    "gn:admin1_code":"14.0",
    "gn:admin2_code":"86.0",
    "gn:asciiname":"La Tuna",
    "gn:country_code":"MX",
    "gn:dem":2216,
    "gn:feature_class":"P",
    "gn:feature_code":"PPL",
    "gn:name":"La Tuna",
    "gn:population":0,
    "gn:timezone":"America/Mexico_City",
    "iso:country":"MX",
    "name:spa_x_preferred":[
        "La Tuna"
    ],
    "wof:name":"La Tuna",
    "wof:placetype":"locality"
},
  "geometry": {"coordinates":[-103.74345,19.98187],"type":"Point"}
}