{
  "type": "Feature",
  "properties": {
    "gn:admin1_code":"13",
    "gn:admin2_code":"34.0",
    "gn:asciiname":"La Union",
    "gn:country_code":"MX",
    "gn:dem":231,
    "gn:feature_class":"P",
    "gn:feature_code":"PPL",
    "gn:name":"La Uni\u00f3n",
    "gn:population":90,
    "gn:timezone":"America/Mexico_City",
    "iso:country":"MX",
    "name:und_x_variant":[
        "La Uni\u00f3n"
    ],
    "wof:name":"La Union",
    "wof:placetype":"locality",
    "wof:population":90
},
  "geometry": {"coordinates":[-98.75273,21.10489],"type":"Point"}
}