{
  "type": "Feature",
  "properties": {
    "gn:admin1_code":"11",
    "gn:admin2_code":"15",
    "gn:asciiname":"San Jose del Gacho",
    "gn:country_code":"MX",
    "gn:dem":2414,
    "gn:feature_class":"P",
    "gn:feature_code":"PPL",
    "gn:name":"San Jos\u00e9 del Gacho",
    "gn:population":48,
    "gn:timezone":"America/Mexico_City",
    "iso:country":"MX",
    "name:und_x_variant":[
        "San Jos\u00e9 del Gacho"
    ],
    "wof:name":"San Jose del Gacho",
    "wof:placetype":"locality",
    "wof:population":48
},
  "geometry": {"coordinates":[-101.29167,21.11611],"type":"Point"}
}