{
  "type": "Feature",
  "properties": {
    "gn:admin1_code":"30",
    "gn:admin2_code":"23.0",
    "gn:asciiname":"El Azotal",
    "gn:country_code":"MX",
    "gn:dem":730,
    "gn:feature_class":"P",
    "gn:feature_code":"PPL",
    "gn:name":"El Azotal",
    "gn:population":0,
    "gn:timezone":"America/Mexico_City",
    "iso:country":"MX",
    "name:spa_x_preferred":[
        "El Azotal"
    ],
    "name:und_x_variant":[
        "El Azota"
    ],
    "wof:name":"El Azotal",
    "wof:placetype":"locality"
},
  "geometry": {"coordinates":[-97.00230999999999,19.91465],"type":"Point"}
}