{
  "type": "Feature",
  "properties": {
    "gn:admin1_code":"14",
    "gn:admin2_code":"11.0",
    "gn:asciiname":"La Natividad",
    "gn:country_code":"MX",
    "gn:dem":1575,
    "gn:feature_class":"P",
    "gn:feature_code":"PPL",
    "gn:name":"La Natividad",
    "gn:population":7,
    "gn:timezone":"America/Mexico_City",
    "iso:country":"MX",
    "wof:name":"La Natividad",
    "wof:placetype":"locality",
    "wof:population":7
},
  "geometry": {"coordinates":[-104.21083,20.32583],"type":"Point"}
}