{
  "type": "Feature",
  "properties": {
    "gn:admin1_code":"23",
    "gn:admin2_code":"7.0",
    "gn:asciiname":"Delirios",
    "gn:country_code":"MX",
    "gn:dem":16,
    "gn:feature_class":"P",
    "gn:feature_code":"PPL",
    "gn:name":"Delirios",
    "gn:population":0,
    "gn:timezone":"America/Cancun",
    "iso:country":"MX",
    "name:spa_x_preferred":[
        "Delirios"
    ],
    "name:spa_x_variant":[
        "El Delirio"
    ],
    "wof:name":"Delirios",
    "wof:placetype":"locality"
},
  "geometry": {"coordinates":[-87.19051999999998,20.84596],"type":"Point"}
}