{
  "type": "Feature",
  "properties": {
    "gn:admin1_code":"27.0",
    "gn:asciiname":"El Desecho Seccion Playas",
    "gn:country_code":"MX",
    "gn:dem":36,
    "gn:feature_class":"P",
    "gn:feature_code":"PPL",
    "gn:name":"El Desecho Secci\u00f3n Playas",
    "gn:population":0,
    "gn:timezone":"America/Mexico_City",
    "iso:country":"MX",
    "name:spa_x_preferred":[
        "El Desecho Secci\u00f3n Playas"
    ],
    "wof:name":"El Desecho Seccion Playas",
    "wof:placetype":"locality"
},
  "geometry": {"coordinates":[-93.38991,17.84982999999999],"type":"Point"}
}