{
  "type": "Feature",
  "properties": {
    "gn:admin1_code":"6.0",
    "gn:admin2_code":"29.0",
    "gn:asciiname":"El Frijolar",
    "gn:country_code":"MX",
    "gn:dem":1686,
    "gn:feature_class":"P",
    "gn:feature_code":"PPL",
    "gn:name":"El Frijolar",
    "gn:population":0,
    "gn:timezone":"America/Chihuahua",
    "iso:country":"MX",
    "name:spa_x_preferred":[
        "El Frijolar"
    ],
    "name:und_x_variant":[
        "Frijolar"
    ],
    "wof:name":"El Frijolar",
    "wof:placetype":"locality"
},
  "geometry": {"coordinates":[-107.13621999999999,26.14095],"type":"Point"}
}