{
  "type": "Feature",
  "properties": {
    "gn:admin1_code":"32.0",
    "gn:admin2_code":"21.0",
    "gn:asciiname":"El Romerillo",
    "gn:country_code":"MX",
    "gn:dem":1925,
    "gn:feature_class":"P",
    "gn:feature_code":"PPL",
    "gn:name":"El Romerillo",
    "gn:population":0,
    "gn:timezone":"America/Mexico_City",
    "iso:country":"MX",
    "name:spa_x_preferred":[
        "El Romerillo"
    ],
    "wof:name":"El Romerillo",
    "wof:placetype":"locality"
},
  "geometry": {"coordinates":[-104.01233999999999,23.08484],"type":"Point"}
}