{
  "type": "Feature",
  "properties": {
    "gn:admin1_code":"26",
    "gn:admin2_code":"18.0",
    "gn:asciiname":"Margarita Valenzuela",
    "gn:country_code":"MX",
    "gn:dem":28,
    "gn:feature_class":"P",
    "gn:feature_code":"PPL",
    "gn:name":"Margarita Valenzuela",
    "gn:population":6,
    "gn:timezone":"America/Hermosillo",
    "iso:country":"MX",
    "wof:name":"Margarita Valenzuela",
    "wof:placetype":"locality",
    "wof:population":6
},
  "geometry": {"coordinates":[-110.00778,27.56194],"type":"Point"}
}