{
  "type": "Feature",
  "properties": {
    "gn:admin1_code":"24",
    "gn:admin2_code":"8.0",
    "gn:asciiname":"Tanquito de Banda",
    "gn:country_code":"MX",
    "gn:dem":1228,
    "gn:feature_class":"P",
    "gn:feature_code":"PPL",
    "gn:name":"Tanquito de Banda",
    "gn:population":91,
    "gn:timezone":"America/Mexico_City",
    "iso:country":"MX",
    "wof:name":"Tanquito de Banda",
    "wof:placetype":"locality",
    "wof:population":91
},
  "geometry": {"coordinates":[-100.34999999999999,22.42028],"type":"Point"}
}