{
  "type": "Feature",
  "properties": {
    "gn:admin1_code":"28.0",
    "gn:admin2_code":"16.0",
    "gn:asciiname":"La Bajada Alta",
    "gn:country_code":"MX",
    "gn:dem":370,
    "gn:feature_class":"P",
    "gn:feature_code":"PPL",
    "gn:name":"La Bajada Alta",
    "gn:population":0,
    "gn:timezone":"America/Monterrey",
    "iso:country":"MX",
    "name:spa_x_preferred":[
        "La Bajada Alta"
    ],
    "wof:name":"La Bajada Alta",
    "wof:placetype":"locality"
},
  "geometry": {"coordinates":[-99.51499,24.17364],"type":"Point"}
}