{
  "type": "Feature",
  "properties": {
    "gn:admin1_code":"30",
    "gn:admin2_code":"4.0",
    "gn:asciiname":"Villa Rica",
    "gn:country_code":"MX",
    "gn:dem":362,
    "gn:feature_class":"P",
    "gn:feature_code":"PPL",
    "gn:name":"Villa Rica",
    "gn:population":0,
    "gn:timezone":"America/Mexico_City",
    "iso:country":"MX",
    "name:ceb_x_preferred":[
        "Villa Rica"
    ],
    "name:deu_x_preferred":[
        "Villa Rica"
    ],
    "name:fra_x_preferred":[
        "Villa Rica"
    ],
    "name:ita_x_preferred":[
        "Villa Rica"
    ],
    "name:nld_x_preferred":[
        "Villa Rica"
    ],
    "name:por_x_preferred":[
        "Villa Rica"
    ],
    "name:swe_x_preferred":[
        "Villa Rica"
    ],
    "name:und_x_variant":[
        "San Juan de Villa Rica"
    ],
    "wof:name":"Villa Rica",
    "wof:placetype":"locality"
},
  "geometry": {"coordinates":[-96.48587000000001,19.60758],"type":"Point"}
}