{
  "type": "Feature",
  "properties": {
    "gn:admin1_code":"7.0",
    "gn:admin2_code":"18.0",
    "gn:asciiname":"La Junta",
    "gn:country_code":"MX",
    "gn:dem":523,
    "gn:feature_class":"P",
    "gn:feature_code":"PPL",
    "gn:name":"La Junta",
    "gn:population":5,
    "gn:timezone":"America/Monterrey",
    "iso:country":"MX",
    "name:spa_x_preferred":[
        "La Junta"
    ],
    "wof:name":"La Junta",
    "wof:placetype":"locality",
    "wof:population":5
},
  "geometry": {"coordinates":[-101.37612,26.97917],"type":"Point"}
}