{
  "type": "Feature",
  "properties": {
    "gn:admin1_code":"7",
    "gn:admin2_code":"30.0",
    "gn:asciiname":"Ostos",
    "gn:country_code":"MX",
    "gn:dem":1747,
    "gn:feature_class":"P",
    "gn:feature_code":"PPL",
    "gn:name":"Ostos",
    "gn:population":0,
    "gn:timezone":"America/Monterrey",
    "iso:country":"MX",
    "name:spa_x_preferred":[
        "Ostos"
    ],
    "wof:name":"Ostos",
    "wof:placetype":"locality"
},
  "geometry": {"coordinates":[-101.3001,25.29483],"type":"Point"}
}