{
  "type": "Feature",
  "properties": {
    "gn:admin1_code":"13.0",
    "gn:asciiname":"Potrero",
    "gn:country_code":"MX",
    "gn:dem":145,
    "gn:feature_class":"P",
    "gn:feature_code":"PPL",
    "gn:name":"Potrero",
    "gn:population":0,
    "gn:timezone":"America/Mexico_City",
    "iso:country":"MX",
    "name:ceb_x_preferred":[
        "Potrero"
    ],
    "name:deu_x_preferred":[
        "Potrero"
    ],
    "name:ita_x_preferred":[
        "Potrero"
    ],
    "name:spa_x_preferred":[
        "Potrero"
    ],
    "name:srp_x_preferred":[
        "\u041f\u043e\u0442\u0440\u0435\u0440\u043e"
    ],
    "name:swe_x_preferred":[
        "Potrero"
    ],
    "wof:name":"Potrero",
    "wof:placetype":"locality"
},
  "geometry": {"coordinates":[-98.63164999999999,21.24205],"type":"Point"}
}