{
  "type": "Feature",
  "properties": {
    "gn:admin1_code":"16",
    "gn:admin2_code":"57.0",
    "gn:asciiname":"Penas Sardas",
    "gn:country_code":"MX",
    "gn:dem":1469,
    "gn:feature_class":"P",
    "gn:feature_code":"PPL",
    "gn:name":"Pe\u00f1as Sardas",
    "gn:population":0,
    "gn:timezone":"America/Mexico_City",
    "iso:country":"MX",
    "name:spa_x_preferred":[
        "Pe\u00f1as Sardas"
    ],
    "wof:name":"Penas Sardas",
    "wof:placetype":"locality"
},
  "geometry": {"coordinates":[-101.25537,19.20757],"type":"Point"}
}