{
  "type": "Feature",
  "properties": {
    "gn:admin1_code":"10",
    "gn:admin2_code":"5.0",
    "gn:asciiname":"El Rey",
    "gn:country_code":"MX",
    "gn:dem":1868,
    "gn:feature_class":"P",
    "gn:feature_code":"PPL",
    "gn:name":"El Rey",
    "gn:population":5,
    "gn:timezone":"America/Monterrey",
    "iso:country":"MX",
    "name:ceb_x_preferred":[
        "El Rey"
    ],
    "name:hun_x_preferred":[
        "El Rey"
    ],
    "name:spa_x_preferred":[
        "El Rey"
    ],
    "name:swe_x_preferred":[
        "El Rey"
    ],
    "wof:name":"El Rey",
    "wof:placetype":"locality",
    "wof:population":5
},
  "geometry": {"coordinates":[-104.52528,23.98694],"type":"Point"}
}