{
  "type": "Feature",
  "properties": {
    "gn:admin1_code":"5.0",
    "gn:admin2_code":"44.0",
    "gn:asciiname":"Las Canoitas",
    "gn:country_code":"MX",
    "gn:dem":1092,
    "gn:feature_class":"P",
    "gn:feature_code":"PPL",
    "gn:name":"Las Canoitas",
    "gn:population":0,
    "gn:timezone":"America/Mexico_City",
    "iso:country":"MX",
    "name:spa_x_preferred":[
        "Las Ca\u00f1itas"
    ],
    "name:spa_x_variant":[
        "Las Canoitas"
    ],
    "wof:name":"Las Canoitas",
    "wof:placetype":"locality"
},
  "geometry": {"coordinates":[-92.92037000000001,16.79973],"type":"Point"}
}