{
  "type": "Feature",
  "properties": {
    "gn:admin1_code":"14.0",
    "gn:admin2_code":"53.0",
    "gn:asciiname":"Lomita Alta",
    "gn:country_code":"MX",
    "gn:dem":1876,
    "gn:feature_class":"P",
    "gn:feature_code":"PPL",
    "gn:name":"Lomita Alta",
    "gn:population":0,
    "gn:timezone":"America/Mexico_City",
    "iso:country":"MX",
    "name:spa_x_preferred":[
        "Lomita Alta"
    ],
    "wof:name":"Lomita Alta",
    "wof:placetype":"locality"
},
  "geometry": {"coordinates":[-101.91567999999999,21.32711],"type":"Point"}
}