{
  "type": "Feature",
  "properties": {
    "gn:admin1_code":"11",
    "gn:admin2_code":"23.0",
    "gn:asciiname":"Cerro Prieto (Las Letras)",
    "gn:country_code":"MX",
    "gn:dem":2318,
    "gn:feature_class":"P",
    "gn:feature_code":"PPL",
    "gn:name":"Cerro Prieto (Las Letras)",
    "gn:population":83,
    "gn:timezone":"America/Mexico_City",
    "iso:country":"MX",
    "wof:name":"Cerro Prieto (Las Letras)",
    "wof:placetype":"locality",
    "wof:population":83
},
  "geometry": {"coordinates":[-101.74611,20.46222],"type":"Point"}
}