{
  "type": "Feature",
  "properties": {
    "gn:admin1_code":"30",
    "gn:admin2_code":"175.0",
    "gn:asciiname":"La Linea",
    "gn:country_code":"MX",
    "gn:dem":77,
    "gn:feature_class":"P",
    "gn:feature_code":"PPL",
    "gn:name":"La L\u00ednea",
    "gn:population":6,
    "gn:timezone":"America/Mexico_City",
    "iso:country":"MX",
    "name:ceb_x_preferred":[
        "La Linea"
    ],
    "name:deu_x_preferred":[
        "La Linea"
    ],
    "name:ita_x_preferred":[
        "La Linea"
    ],
    "name:nld_x_preferred":[
        "La Linea"
    ],
    "name:spa_x_preferred":[
        "La l\u00ednea"
    ],
    "name:srp_x_preferred":[
        "\u041b\u0430 \u041b\u0438\u043d\u0435\u0430"
    ],
    "name:swe_x_preferred":[
        "La Linea"
    ],
    "name:und_x_variant":[
        "La L\u00ednea"
    ],
    "wof:name":"La Linea",
    "wof:placetype":"locality",
    "wof:population":6
},
  "geometry": {"coordinates":[-97.57556,20.67611],"type":"Point"}
}