{
  "type": "Feature",
  "properties": {
    "gn:admin1_code":"6.0",
    "gn:admin2_code":"1.0",
    "gn:asciiname":"La Pila Vieja",
    "gn:country_code":"MX",
    "gn:dem":1461,
    "gn:feature_class":"P",
    "gn:feature_code":"PPL",
    "gn:name":"La Pila Vieja",
    "gn:population":0,
    "gn:timezone":"America/Chihuahua",
    "iso:country":"MX",
    "name:spa_x_preferred":[
        "La Pila Vieja"
    ],
    "wof:name":"La Pila Vieja",
    "wof:placetype":"locality"
},
  "geometry": {"coordinates":[-105.75503,30.72391],"type":"Point"}
}