{
  "type": "Feature",
  "properties": {
    "gn:admin1_code":"16.0",
    "gn:admin2_code":"22.0",
    "gn:asciiname":"El Platanito",
    "gn:country_code":"MX",
    "gn:dem":1433,
    "gn:feature_class":"P",
    "gn:feature_code":"PPL",
    "gn:name":"El Platanito",
    "gn:population":0,
    "gn:timezone":"America/Mexico_City",
    "iso:country":"MX",
    "name:spa_x_preferred":[
        "El Platanito"
    ],
    "wof:name":"El Platanito",
    "wof:placetype":"locality"
},
  "geometry": {"coordinates":[-100.98059000000001,19.57517],"type":"Point"}
}