{
  "type": "Feature",
  "properties": {
    "gn:admin1_code":"26",
    "gn:admin2_code":"32.0",
    "gn:asciiname":"La Palmita",
    "gn:country_code":"MX",
    "gn:dem":1013,
    "gn:feature_class":"P",
    "gn:feature_code":"PPL",
    "gn:name":"La Palmita",
    "gn:population":0,
    "gn:timezone":"America/Hermosillo",
    "iso:country":"MX",
    "name:und_x_variant":[
        "Rancho La Palmita",
        "La Palmita"
    ],
    "wof:name":"La Palmita",
    "wof:placetype":"locality"
},
  "geometry": {"coordinates":[-109.44007999999999,29.87117000000001],"type":"Point"}
}