{
  "type": "Feature",
  "properties": {
    "gn:admin1_code":"30",
    "gn:admin2_code":"189.0",
    "gn:asciiname":"Pena de Afuera",
    "gn:country_code":"MX",
    "gn:dem":30,
    "gn:feature_class":"P",
    "gn:feature_code":"PPL",
    "gn:name":"Pe\u00f1a de Afuera",
    "gn:population":0,
    "gn:timezone":"America/Mexico_City",
    "iso:country":"MX",
    "name:spa_x_preferred":[
        "Pe\u00f1a de Afuera"
    ],
    "name:und_x_variant":[
        "Pe\u00f1a de Alvera"
    ],
    "wof:name":"Pena de Afuera",
    "wof:placetype":"locality"
},
  "geometry": {"coordinates":[-97.36591,20.83475],"type":"Point"}
}