{
  "type": "Feature",
  "properties": {
    "gn:admin1_code":"14.0",
    "gn:admin2_code":"80.0",
    "gn:asciiname":"El Pueblito",
    "gn:cc2":"MX",
    "gn:country_code":"MX",
    "gn:dem":421,
    "gn:feature_class":"P",
    "gn:feature_code":"PPL",
    "gn:name":"El Pueblito",
    "gn:population":0,
    "gn:timezone":"America/Mexico_City",
    "iso:country":"MX",
    "name:und_x_variant":[
        "Pueblito",
        "El Pueblito"
    ],
    "wof:name":"El Pueblito",
    "wof:placetype":"locality"
},
  "geometry": {"coordinates":[-104.91667,20.88333],"type":"Point"}
}