{
  "type": "Feature",
  "properties": {
    "gn:admin1_code":"12.0",
    "gn:admin2_code":"64.0",
    "gn:asciiname":"La Lata",
    "gn:country_code":"MX",
    "gn:dem":1060,
    "gn:feature_class":"P",
    "gn:feature_code":"PPL",
    "gn:name":"La Lata",
    "gn:population":0,
    "gn:timezone":"America/Mexico_City",
    "iso:country":"MX",
    "name:spa_x_preferred":[
        "La Lata"
    ],
    "wof:name":"La Lata",
    "wof:placetype":"locality"
},
  "geometry": {"coordinates":[-100.38693000000001,18.49988],"type":"Point"}
}