{
  "type": "Feature",
  "properties": {
    "gn:admin1_code":"15.0",
    "gn:asciiname":"El Chalmita",
    "gn:country_code":"MX",
    "gn:dem":2760,
    "gn:feature_class":"P",
    "gn:feature_code":"PPL",
    "gn:name":"El Chalmita",
    "gn:population":0,
    "gn:timezone":"America/Mexico_City",
    "iso:country":"MX",
    "name:spa_x_preferred":[
        "El Chalmita"
    ],
    "wof:name":"El Chalmita",
    "wof:placetype":"locality"
},
  "geometry": {"coordinates":[-100.24088999999999,19.79489],"type":"Point"}
}