{
  "type": "Feature",
  "properties": {
    "gn:admin1_code":"6",
    "gn:admin2_code":"48.0",
    "gn:asciiname":"Huerta Dos Hermanos",
    "gn:country_code":"MX",
    "gn:dem":1864,
    "gn:feature_class":"P",
    "gn:feature_code":"PPL",
    "gn:name":"Huerta Dos Hermanos",
    "gn:population":8,
    "gn:timezone":"America/Chihuahua",
    "iso:country":"MX",
    "wof:name":"Huerta Dos Hermanos",
    "wof:placetype":"locality",
    "wof:population":8
},
  "geometry": {"coordinates":[-107.40031,29.0874],"type":"Point"}
}