{
  "type": "Feature",
  "properties": {
    "gn:admin1_code":"23",
    "gn:admin2_code":"4.0",
    "gn:asciiname":"Cubano",
    "gn:country_code":"MX",
    "gn:dem":8,
    "gn:feature_class":"P",
    "gn:feature_code":"PPL",
    "gn:name":"Cubano",
    "gn:population":6,
    "gn:timezone":"America/Cancun",
    "iso:country":"MX",
    "wof:name":"Cubano",
    "wof:placetype":"locality",
    "wof:population":6
},
  "geometry": {"coordinates":[-88.24778000000001,18.63026],"type":"Point"}
}