{
  "type": "Feature",
  "properties": {
    "gn:admin1_code":"26",
    "gn:admin2_code":"49.0",
    "gn:asciiname":"Las Canoas",
    "gn:country_code":"MX",
    "gn:dem":443,
    "gn:feature_class":"P",
    "gn:feature_code":"PPL",
    "gn:name":"Las Canoas",
    "gn:population":0,
    "gn:timezone":"America/Hermosillo",
    "iso:country":"MX",
    "name:spa_x_preferred":[
        "Las Canoas"
    ],
    "wof:name":"Las Canoas",
    "wof:placetype":"locality"
},
  "geometry": {"coordinates":[-109.33266,27.68965],"type":"Point"}
}