{
  "type": "Feature",
  "properties": {
    "gn:admin1_code":"12",
    "gn:admin2_code":"73",
    "gn:asciiname":"El Guayabo",
    "gn:country_code":"MX",
    "gn:dem":622,
    "gn:feature_class":"P",
    "gn:feature_code":"PPL",
    "gn:name":"El Guayabo",
    "gn:population":18,
    "gn:timezone":"America/Mexico_City",
    "iso:country":"MX",
    "wof:name":"El Guayabo",
    "wof:placetype":"locality",
    "wof:population":18
},
  "geometry": {"coordinates":[-101.04512,18.21252],"type":"Point"}
}