{
  "type": "Feature",
  "properties": {
    "gn:admin1_code":"25",
    "gn:admin2_code":"17.0",
    "gn:asciiname":"Las Minas",
    "gn:country_code":"MX",
    "gn:dem":615,
    "gn:feature_class":"P",
    "gn:feature_code":"PPL",
    "gn:name":"Las Minas",
    "gn:population":0,
    "gn:timezone":"America/Mazatlan",
    "iso:country":"MX",
    "name:ceb_x_preferred":[
        "Las Minas"
    ],
    "name:deu_x_preferred":[
        "Las Minas"
    ],
    "name:spa_x_preferred":[
        "Lagunita"
    ],
    "name:spa_x_variant":[
        "Las Minas"
    ],
    "name:swe_x_preferred":[
        "Las Minas"
    ],
    "wof:name":"Las Minas",
    "wof:placetype":"locality"
},
  "geometry": {"coordinates":[-107.55202,26.0906],"type":"Point"}
}