{
  "type": "Feature",
  "properties": {
    "gn:admin1_code":"32",
    "gn:admin2_code":"49.0",
    "gn:asciiname":"La Torrecilla",
    "gn:country_code":"MX",
    "gn:dem":1726,
    "gn:feature_class":"P",
    "gn:feature_code":"PPL",
    "gn:name":"La Torrecilla",
    "gn:population":98,
    "gn:timezone":"America/Mexico_City",
    "iso:country":"MX",
    "wof:name":"La Torrecilla",
    "wof:placetype":"locality",
    "wof:population":98
},
  "geometry": {"coordinates":[-103.99694,22.45056],"type":"Point"}
}