{
  "type": "Feature",
  "properties": {
    "gn:admin1_code":"5",
    "gn:admin2_code":"1.0",
    "gn:asciiname":"Los Cacaos",
    "gn:country_code":"MX",
    "gn:dem":453,
    "gn:feature_class":"P",
    "gn:feature_code":"PPL",
    "gn:name":"Los Cacaos",
    "gn:population":0,
    "gn:timezone":"America/Mexico_City",
    "iso:country":"MX",
    "name:spa_x_preferred":[
        "Los Cacaos"
    ],
    "wof:name":"Los Cacaos",
    "wof:placetype":"locality"
},
  "geometry": {"coordinates":[-92.65685000000001,15.38947],"type":"Point"}
}