{
  "type": "Feature",
  "properties": {
    "gn:admin1_code":"22",
    "gn:admin2_code":"10",
    "gn:asciiname":"Barrio las Ortigas",
    "gn:country_code":"MX",
    "gn:dem":1053,
    "gn:feature_class":"P",
    "gn:feature_code":"PPL",
    "gn:name":"Barrio las Ortigas",
    "gn:population":36,
    "gn:timezone":"America/Mexico_City",
    "iso:country":"MX",
    "wof:name":"Barrio las Ortigas",
    "wof:placetype":"locality",
    "wof:population":36
},
  "geometry": {"coordinates":[-99.32306,21.17722],"type":"Point"}
}