{
  "type": "Feature",
  "properties": {
    "gn:admin1_code":"5",
    "gn:admin2_code":"107",
    "gn:asciiname":"La Sombra",
    "gn:country_code":"MX",
    "gn:dem":588,
    "gn:feature_class":"P",
    "gn:feature_code":"PPL",
    "gn:name":"La Sombra",
    "gn:population":23,
    "gn:timezone":"America/Mexico_City",
    "iso:country":"MX",
    "wof:name":"La Sombra",
    "wof:placetype":"locality",
    "wof:population":23
},
  "geometry": {"coordinates":[-93.14639,16.12639],"type":"Point"}
}