{
  "type": "Feature",
  "properties": {
    "gn:admin1_code":"16.0",
    "gn:admin2_code":"100.0",
    "gn:asciiname":"Puerto el Tigre",
    "gn:country_code":"MX",
    "gn:dem":2423,
    "gn:feature_class":"P",
    "gn:feature_code":"PPL",
    "gn:name":"Puerto el Tigre",
    "gn:population":0,
    "gn:timezone":"America/Mexico_City",
    "iso:country":"MX",
    "name:spa_x_preferred":[
        "Puerto el Tigre"
    ],
    "wof:name":"Puerto el Tigre",
    "wof:placetype":"locality"
},
  "geometry": {"coordinates":[-101.44812,19.62989],"type":"Point"}
}