{
  "type": "Feature",
  "properties": {
    "gn:admin1_code":"11",
    "gn:admin2_code":"4",
    "gn:asciiname":"Torreon de los Angeles",
    "gn:country_code":"MX",
    "gn:dem":2059,
    "gn:feature_class":"P",
    "gn:feature_code":"PPL",
    "gn:name":"Torre\u00f3n de los \u00c1ngeles",
    "gn:population":19,
    "gn:timezone":"America/Mexico_City",
    "iso:country":"MX",
    "name:und_x_variant":[
        "Torre\u00f3n de los \u00c1ngeles"
    ],
    "wof:name":"Torreon de los Angeles",
    "wof:placetype":"locality",
    "wof:population":19
},
  "geometry": {"coordinates":[-100.47583,20.37861],"type":"Point"}
}