{
  "type": "Feature",
  "properties": {
    "gn:admin1_code":"6",
    "gn:admin2_code":"15.0",
    "gn:asciiname":"Alto de Puerto",
    "gn:country_code":"MX",
    "gn:dem":1114,
    "gn:feature_class":"P",
    "gn:feature_code":"PPL",
    "gn:name":"Alto de Puerto",
    "gn:population":0,
    "gn:timezone":"America/Chihuahua",
    "iso:country":"MX",
    "name:und_x_variant":[
        "Rancho Alto del Puerto",
        "Puerto Alto",
        "Alto de Puerto"
    ],
    "wof:name":"Alto de Puerto",
    "wof:placetype":"locality"
},
  "geometry": {"coordinates":[-105.05240999999999,30.44858],"type":"Point"}
}