{
  "type": "Feature",
  "properties": {
    "gn:admin1_code":"25",
    "gn:admin2_code":"12.0",
    "gn:asciiname":"Las Guasimas",
    "gn:country_code":"MX",
    "gn:dem":313,
    "gn:feature_class":"P",
    "gn:feature_code":"PPL",
    "gn:name":"Las Gu\u00e1simas",
    "gn:population":55,
    "gn:timezone":"America/Mazatlan",
    "iso:country":"MX",
    "name:spa_x_preferred":[
        "Las Gu\u00e1simas"
    ],
    "wof:name":"Las Guasimas",
    "wof:placetype":"locality",
    "wof:population":55
},
  "geometry": {"coordinates":[-106.05474,23.71392],"type":"Point"}
}