{
  "type": "Feature",
  "properties": {
    "gn:admin1_code":"5",
    "gn:admin2_code":"109",
    "gn:asciiname":"El Faro",
    "gn:country_code":"MX",
    "gn:dem":911,
    "gn:feature_class":"P",
    "gn:feature_code":"PPL",
    "gn:name":"El Faro",
    "gn:population":45,
    "gn:timezone":"America/Mexico_City",
    "iso:country":"MX",
    "name:ceb_x_preferred":[
        "El Faro"
    ],
    "name:srp_x_preferred":[
        "\u0415\u043b \u0424\u0430\u0440\u043e"
    ],
    "name:swe_x_preferred":[
        "El Faro"
    ],
    "wof:name":"El Faro",
    "wof:placetype":"locality",
    "wof:population":45
},
  "geometry": {"coordinates":[-92.37694,17.18944],"type":"Point"}
}