{
  "type": "Feature",
  "properties": {
    "gn:admin1_code":"6",
    "gn:admin2_code":"50.0",
    "gn:asciiname":"El Palomar",
    "gn:country_code":"MX",
    "gn:dem":1495,
    "gn:feature_class":"P",
    "gn:feature_code":"PPL",
    "gn:name":"El Palomar",
    "gn:population":0,
    "gn:timezone":"America/Chihuahua",
    "iso:country":"MX",
    "wof:name":"El Palomar",
    "wof:placetype":"locality"
},
  "geometry": {"coordinates":[-107.66016999999999,30.42631],"type":"Point"}
}