{
  "type": "Feature",
  "properties": {
    "gn:admin1_code":"19.0",
    "gn:asciiname":"Presa de los Cervantes",
    "gn:country_code":"MX",
    "gn:dem":1993,
    "gn:feature_class":"P",
    "gn:feature_code":"PPL",
    "gn:name":"Presa de los Cervantes",
    "gn:population":0,
    "gn:timezone":"America/Monterrey",
    "iso:country":"MX",
    "name:spa_x_preferred":[
        "Presa de los Cervantes"
    ],
    "wof:name":"Presa de los Cervantes",
    "wof:placetype":"locality"
},
  "geometry": {"coordinates":[-100.26935,23.77444],"type":"Point"}
}