{
  "type": "Feature",
  "properties": {
    "gn:admin1_code":"6",
    "gn:admin2_code":"29.0",
    "gn:asciiname":"Batallapa",
    "gn:country_code":"MX",
    "gn:dem":747,
    "gn:feature_class":"P",
    "gn:feature_code":"PPL",
    "gn:name":"Batallapa",
    "gn:population":137,
    "gn:timezone":"America/Chihuahua",
    "iso:country":"MX",
    "wof:name":"Batallapa",
    "wof:placetype":"locality",
    "wof:population":137
},
  "geometry": {"coordinates":[-107.23027999999999,26.00611],"type":"Point"}
}