{
  "type": "Feature",
  "properties": {
    "gn:admin1_code":"30",
    "gn:admin2_code":"102.0",
    "gn:asciiname":"Vega Redonda",
    "gn:country_code":"MX",
    "gn:dem":67,
    "gn:feature_class":"P",
    "gn:feature_code":"PPL",
    "gn:name":"Vega Redonda",
    "gn:population":458,
    "gn:timezone":"America/Mexico_City",
    "iso:country":"MX",
    "wof:name":"Vega Redonda",
    "wof:placetype":"locality",
    "wof:population":458
},
  "geometry": {"coordinates":[-97.03306000000001,20.06028],"type":"Point"}
}