{
  "type": "Feature",
  "properties": {
    "gn:admin1_code":"30.0",
    "gn:admin2_code":"161.0",
    "gn:asciiname":"La Encantada",
    "gn:country_code":"MX",
    "gn:dem":79,
    "gn:feature_class":"P",
    "gn:feature_code":"PPL",
    "gn:name":"La Encantada",
    "gn:population":5,
    "gn:timezone":"America/Mexico_City",
    "iso:country":"MX",
    "name:ceb_x_preferred":[
        "La Encantada"
    ],
    "name:spa_x_preferred":[
        "La Encantada"
    ],
    "name:swe_x_preferred":[
        "La Encantada"
    ],
    "wof:name":"La Encantada",
    "wof:placetype":"locality",
    "wof:population":5
},
  "geometry": {"coordinates":[-98.24028,21.62361],"type":"Point"}
}