{
  "type": "Feature",
  "properties": {
    "gn:admin1_code":"26",
    "gn:asciiname":"Gloriapan",
    "gn:country_code":"MX",
    "gn:dem":526,
    "gn:feature_class":"P",
    "gn:feature_code":"PPL",
    "gn:name":"Gloriapan",
    "gn:population":0,
    "gn:timezone":"America/Chihuahua",
    "iso:country":"MX",
    "name:spa_x_preferred":[
        "Gloriapan"
    ],
    "wof:name":"Gloriapan",
    "wof:placetype":"locality"
},
  "geometry": {"coordinates":[-108.46387,27.00083],"type":"Point"}
}