{
  "type": "Feature",
  "properties": {
    "gn:admin1_code":"22.0",
    "gn:admin2_code":"16.0",
    "gn:asciiname":"San Antonio los Pirules",
    "gn:country_code":"MX",
    "gn:dem":1902,
    "gn:feature_class":"P",
    "gn:feature_code":"PPL",
    "gn:name":"San Antonio los Pirules",
    "gn:population":0,
    "gn:timezone":"America/Mexico_City",
    "iso:country":"MX",
    "name:spa_x_preferred":[
        "San Antonio los Pirules"
    ],
    "name:spa_x_variant":[
        "San Antonio de los Pirules"
    ],
    "wof:name":"San Antonio los Pirules",
    "wof:placetype":"locality"
},
  "geometry": {"coordinates":[-100.04513,20.45798],"type":"Point"}
}