{
  "type": "Feature",
  "properties": {
    "gn:admin1_code":"4",
    "gn:admin2_code":"3.0",
    "gn:asciiname":"La Tercia",
    "gn:country_code":"MX",
    "gn:dem":-2,
    "gn:feature_class":"P",
    "gn:feature_code":"PPL",
    "gn:name":"La Tercia",
    "gn:population":0,
    "gn:timezone":"America/Merida",
    "iso:country":"MX",
    "name:spa_x_preferred":[
        "La Tercia"
    ],
    "wof:name":"La Tercia",
    "wof:placetype":"locality"
},
  "geometry": {"coordinates":[-91.81797,18.23203],"type":"Point"}
}