{
  "type": "Feature",
  "properties": {
    "gn:admin1_code":"30",
    "gn:admin2_code":"137.0",
    "gn:asciiname":"Ocotepec",
    "gn:country_code":"MX",
    "gn:dem":1614,
    "gn:feature_class":"P",
    "gn:feature_code":"PPL",
    "gn:name":"Ocotepec",
    "gn:population":295,
    "gn:timezone":"America/Mexico_City",
    "iso:country":"MX",
    "wof:name":"Ocotepec",
    "wof:placetype":"locality",
    "wof:population":295
},
  "geometry": {"coordinates":[-97.01472,18.6825],"type":"Point"}
}