{
  "type": "Feature",
  "properties": {
    "gn:admin1_code":"26",
    "gn:admin2_code":"30.0",
    "gn:asciiname":"Juan Luis",
    "gn:country_code":"MX",
    "gn:dem":56,
    "gn:feature_class":"P",
    "gn:feature_code":"PPL",
    "gn:name":"Juan Luis",
    "gn:population":18,
    "gn:timezone":"America/Hermosillo",
    "iso:country":"MX",
    "name:spa_x_preferred":[
        "Juan Luis"
    ],
    "wof:name":"Juan Luis",
    "wof:placetype":"locality",
    "wof:population":18
},
  "geometry": {"coordinates":[-111.76111000000002,29.12361],"type":"Point"}
}