{
  "type": "Feature",
  "properties": {
    "gn:admin1_code":"12.0",
    "gn:asciiname":"Guarichicahuaro",
    "gn:country_code":"MX",
    "gn:dem":223,
    "gn:feature_class":"P",
    "gn:feature_code":"PPL",
    "gn:name":"Guarichicahuaro",
    "gn:population":0,
    "gn:timezone":"America/Mexico_City",
    "iso:country":"MX",
    "wof:name":"Guarichicahuaro",
    "wof:placetype":"locality"
},
  "geometry": {"coordinates":[-101.18333,18.53333],"type":"Point"}
}