{
  "type": "Feature",
  "properties": {
    "gn:admin1_code":"7",
    "gn:admin2_code":"20.0",
    "gn:asciiname":"Los Tres Sabinos",
    "gn:cc2":"MX",
    "gn:country_code":"MX",
    "gn:dem":509,
    "gn:feature_class":"P",
    "gn:feature_code":"PPL",
    "gn:name":"Los Tres Sabinos",
    "gn:population":0,
    "gn:timezone":"America/Monterrey",
    "iso:country":"MX",
    "name:und_x_variant":[
        "Rancho Los Tres Sabinos",
        "Tres Sabinas",
        "Los Tres Sabinos"
    ],
    "wof:name":"Los Tres Sabinos",
    "wof:placetype":"locality"
},
  "geometry": {"coordinates":[-101.68261,27.92191],"type":"Point"}
}