{
  "type": "Feature",
  "properties": {
    "gn:admin1_code":"2.0",
    "gn:admin2_code":"2.0",
    "gn:asciiname":"El Malo (Ejido Tabasco)",
    "gn:country_code":"MX",
    "gn:dem":22,
    "gn:feature_class":"P",
    "gn:feature_code":"PPL",
    "gn:name":"El Malo (Ejido Tabasco)",
    "gn:population":117,
    "gn:timezone":"America/Tijuana",
    "iso:country":"MX",
    "name:spa_x_preferred":[
        "El Malo"
    ],
    "wof:name":"El Malo (Ejido Tabasco)",
    "wof:placetype":"locality",
    "wof:population":117
},
  "geometry": {"coordinates":[-114.91028,32.54167],"type":"Point"}
}