{
  "type": "Feature",
  "properties": {
    "gn:admin1_code":"26",
    "gn:asciiname":"Mesa la Casa",
    "gn:country_code":"MX",
    "gn:dem":1778,
    "gn:feature_class":"P",
    "gn:feature_code":"PPL",
    "gn:name":"Mesa la Casa",
    "gn:population":0,
    "gn:timezone":"America/Chihuahua",
    "iso:country":"MX",
    "name:spa_x_preferred":[
        "Mesa la Casa"
    ],
    "wof:name":"Mesa la Casa",
    "wof:placetype":"locality"
},
  "geometry": {"coordinates":[-109.03623,28.12456],"type":"Point"}
}