{
  "type": "Feature",
  "properties": {
    "gn:admin1_code":"25.0",
    "gn:admin2_code":"12.0",
    "gn:asciiname":"El Berro",
    "gn:cc2":"MX",
    "gn:country_code":"MX",
    "gn:dem":270,
    "gn:feature_class":"P",
    "gn:feature_code":"PPL",
    "gn:name":"El Berro",
    "gn:population":0,
    "gn:timezone":"America/Mazatlan",
    "iso:country":"MX",
    "name:und_x_variant":[
        "Berro",
        "El Berro"
    ],
    "wof:name":"El Berro",
    "wof:placetype":"locality"
},
  "geometry": {"coordinates":[-106.36667,23.58333],"type":"Point"}
}