{
  "type": "Feature",
  "properties": {
    "gn:admin1_code":"32",
    "gn:admin2_code":"19.0",
    "gn:asciiname":"Chalchisco de Abajo (San Rafael)",
    "gn:country_code":"MX",
    "gn:dem":1499,
    "gn:feature_class":"P",
    "gn:feature_code":"PPL",
    "gn:name":"Chalchisco de Abajo (San Rafael)",
    "gn:population":241,
    "gn:timezone":"America/Mexico_City",
    "iso:country":"MX",
    "wof:name":"Chalchisco de Abajo (San Rafael)",
    "wof:placetype":"locality",
    "wof:population":241
},
  "geometry": {"coordinates":[-103.00972,21.67472],"type":"Point"}
}