{
  "type": "Feature",
  "properties": {
    "gn:admin1_code":"11.0",
    "gn:admin2_code":"30.0",
    "gn:asciiname":"Los Cuartos",
    "gn:country_code":"MX",
    "gn:dem":2117,
    "gn:feature_class":"P",
    "gn:feature_code":"PPL",
    "gn:name":"Los Cuartos",
    "gn:population":0,
    "gn:timezone":"America/Mexico_City",
    "iso:country":"MX",
    "name:spa_x_preferred":[
        "Los Cuartos"
    ],
    "wof:name":"Los Cuartos",
    "wof:placetype":"locality"
},
  "geometry": {"coordinates":[-101.22839999999999,21.59491],"type":"Point"}
}