{
  "type": "Feature",
  "properties": {
    "gn:admin1_code":"10",
    "gn:admin2_code":"4.0",
    "gn:asciiname":"El Elefante",
    "gn:country_code":"MX",
    "gn:dem":1881,
    "gn:feature_class":"P",
    "gn:feature_code":"PPL",
    "gn:name":"El Elefante",
    "gn:population":0,
    "gn:timezone":"America/Monterrey",
    "iso:country":"MX",
    "name:spa_x_preferred":[
        "El Elefante"
    ],
    "wof:name":"El Elefante",
    "wof:placetype":"locality"
},
  "geometry": {"coordinates":[-103.72492,24.74501],"type":"Point"}
}