{
  "type": "Feature",
  "properties": {
    "gn:admin1_code":"15",
    "gn:admin2_code":"120.0",
    "gn:asciiname":"Barrio de Espana",
    "gn:country_code":"MX",
    "gn:dem":2327,
    "gn:feature_class":"P",
    "gn:feature_code":"PPL",
    "gn:name":"Barrio de Espa\u00f1a",
    "gn:population":1995,
    "gn:timezone":"America/Mexico_City",
    "iso:country":"MX",
    "name:und_x_variant":[
        "Barrio de Espa\u00f1a"
    ],
    "wof:name":"Barrio de Espana",
    "wof:placetype":"locality",
    "wof:population":1995
},
  "geometry": {"coordinates":[-99.08167,19.86139],"type":"Point"}
}