{
  "type": "Feature",
  "properties": {
    "gn:admin1_code":"28.0",
    "gn:admin2_code":"4.0",
    "gn:asciiname":"San Antolin",
    "gn:country_code":"MX",
    "gn:dem":168,
    "gn:feature_class":"P",
    "gn:feature_code":"PPL",
    "gn:name":"San Antolin",
    "gn:population":0,
    "gn:timezone":"America/Monterrey",
    "iso:country":"MX",
    "name:spa_x_preferred":[
        "San Antolin"
    ],
    "wof:name":"San Antolin",
    "wof:placetype":"locality"
},
  "geometry": {"coordinates":[-99.07424,22.63261],"type":"Point"}
}