{
  "type": "Feature",
  "properties": {
    "gn:admin1_code":"11",
    "gn:admin2_code":"7",
    "gn:asciiname":"Fraccionamiento Porta Magiore",
    "gn:country_code":"MX",
    "gn:dem":1764,
    "gn:feature_class":"P",
    "gn:feature_code":"PPL",
    "gn:name":"Fraccionamiento Porta Magiore",
    "gn:population":28,
    "gn:timezone":"America/Mexico_City",
    "iso:country":"MX",
    "wof:name":"Fraccionamiento Porta Magiore",
    "wof:placetype":"locality",
    "wof:population":28
},
  "geometry": {"coordinates":[-100.82472,20.57389],"type":"Point"}
}