{
  "type": "Feature",
  "properties": {
    "gn:admin1_code":"28",
    "gn:admin2_code":"1.0",
    "gn:asciiname":"Parras de la Fuente",
    "gn:country_code":"MX",
    "gn:dem":191,
    "gn:feature_class":"P",
    "gn:feature_code":"PPL",
    "gn:name":"Parras de la Fuente",
    "gn:population":144,
    "gn:timezone":"America/Monterrey",
    "iso:country":"MX",
    "wof:name":"Parras de la Fuente",
    "wof:placetype":"locality",
    "wof:population":144
},
  "geometry": {"coordinates":[-98.49250000000001,23.90111],"type":"Point"}
}