{
  "type": "Feature",
  "properties": {
    "gn:admin1_code":"13",
    "gn:admin2_code":"70",
    "gn:asciiname":"Dexhe",
    "gn:country_code":"MX",
    "gn:dem":2053,
    "gn:feature_class":"P",
    "gn:feature_code":"PPL",
    "gn:name":"Dexhe",
    "gn:population":16,
    "gn:timezone":"America/Mexico_City",
    "iso:country":"MX",
    "wof:name":"Dexhe",
    "wof:placetype":"locality",
    "wof:population":16
},
  "geometry": {"coordinates":[-99.23273,20.12149],"type":"Point"}
}