{
  "type": "Feature",
  "properties": {
    "gn:admin1_code":"16",
    "gn:admin2_code":"8",
    "gn:asciiname":"Guasigenes",
    "gn:country_code":"MX",
    "gn:dem":345,
    "gn:feature_class":"P",
    "gn:feature_code":"PPL",
    "gn:name":"Guasigenes",
    "gn:population":32,
    "gn:timezone":"America/Mexico_City",
    "iso:country":"MX",
    "wof:name":"Guasigenes",
    "wof:placetype":"locality",
    "wof:population":32
},
  "geometry": {"coordinates":[-103.25556,18.40167000000001],"type":"Point"}
}