{
  "type": "Feature",
  "properties": {
    "gn:admin1_code":"1.0",
    "gn:admin2_code":"2.0",
    "gn:asciiname":"Guadalupe de Atlas",
    "gn:country_code":"MX",
    "gn:dem":2024,
    "gn:feature_class":"P",
    "gn:feature_code":"PPL",
    "gn:name":"Guadalupe de Atlas",
    "gn:population":2259,
    "gn:timezone":"America/Mexico_City",
    "iso:country":"MX",
    "wof:name":"Guadalupe de Atlas",
    "wof:placetype":"locality",
    "wof:population":2259
},
  "geometry": {"coordinates":[-102.03139,22.26778],"type":"Point"}
}