{
  "type": "Feature",
  "properties": {
    "gn:admin1_code":"11",
    "gn:admin2_code":"31",
    "gn:asciiname":"Rancho Mocho",
    "gn:country_code":"MX",
    "gn:dem":1854,
    "gn:feature_class":"P",
    "gn:feature_code":"PPL",
    "gn:name":"Rancho Mocho",
    "gn:population":22,
    "gn:timezone":"America/Mexico_City",
    "iso:country":"MX",
    "wof:name":"Rancho Mocho",
    "wof:placetype":"locality",
    "wof:population":22
},
  "geometry": {"coordinates":[-101.78194000000001,20.8625],"type":"Point"}
}