{
  "type": "Feature",
  "properties": {
    "gn:admin1_code":"5.0",
    "gn:asciiname":"Soledad las Cuevas",
    "gn:country_code":"MX",
    "gn:dem":1443,
    "gn:feature_class":"P",
    "gn:feature_code":"PPL",
    "gn:name":"Soledad las Cuevas",
    "gn:population":0,
    "gn:timezone":"America/Mexico_City",
    "iso:country":"MX",
    "name:spa_x_preferred":[
        "Soledad las Cuevas"
    ],
    "wof:name":"Soledad las Cuevas",
    "wof:placetype":"locality"
},
  "geometry": {"coordinates":[-92.98612,15.7236],"type":"Point"}
}