{
  "type": "Feature",
  "properties": {
    "gn:admin1_code":"20",
    "gn:admin2_code":"499",
    "gn:asciiname":"Barrio San Jose",
    "gn:country_code":"MX",
    "gn:dem":2175,
    "gn:feature_class":"P",
    "gn:feature_code":"PPL",
    "gn:name":"Barrio San Jos\u00e9",
    "gn:population":31,
    "gn:timezone":"America/Mexico_City",
    "iso:country":"MX",
    "name:und_x_variant":[
        "Barrio San Jos\u00e9"
    ],
    "wof:name":"Barrio San Jose",
    "wof:placetype":"locality",
    "wof:population":31
},
  "geometry": {"coordinates":[-97.575,17.47722000000001],"type":"Point"}
}