{
  "type": "Feature",
  "properties": {
    "gn:admin1_code":"26",
    "gn:admin2_code":"22.0",
    "gn:asciiname":"Santa Eulalia",
    "gn:country_code":"MX",
    "gn:dem":792,
    "gn:feature_class":"P",
    "gn:feature_code":"PPL",
    "gn:name":"Santa Eulalia",
    "gn:population":0,
    "gn:timezone":"America/Hermosillo",
    "iso:country":"MX",
    "name:und_x_variant":[
        "Rancho Santa Eulalia",
        "Santa Eulalia"
    ],
    "wof:name":"Santa Eulalia",
    "wof:placetype":"locality"
},
  "geometry": {"coordinates":[-110.69871999999999,30.19106],"type":"Point"}
}