{
  "type": "Feature",
  "properties": {
    "gn:admin1_code":"28",
    "gn:admin2_code":"22.0",
    "gn:asciiname":"El Mogote de Santiago",
    "gn:country_code":"MX",
    "gn:dem":12,
    "gn:feature_class":"P",
    "gn:feature_code":"PPL",
    "gn:name":"El Mogote de Santiago",
    "gn:population":2,
    "gn:timezone":"America/Matamoros",
    "iso:country":"MX",
    "wof:name":"El Mogote de Santiago",
    "wof:placetype":"locality",
    "wof:population":2
},
  "geometry": {"coordinates":[-97.67083,25.77444],"type":"Point"}
}