{
  "type": "Feature",
  "properties": {
    "gn:admin1_code":"11.0",
    "gn:admin2_code":"7.0",
    "gn:asciiname":"Los Capulines",
    "gn:country_code":"MX",
    "gn:dem":1963,
    "gn:feature_class":"P",
    "gn:feature_code":"PPL",
    "gn:name":"Los Capulines",
    "gn:population":0,
    "gn:timezone":"America/Mexico_City",
    "iso:country":"MX",
    "name:spa_x_preferred":[
        "Los Capulines"
    ],
    "name:spa_x_variant":[
        "Capulines"
    ],
    "wof:name":"Los Capulines",
    "wof:placetype":"locality"
},
  "geometry": {"coordinates":[-100.67563,20.64411],"type":"Point"}
}