{
  "type": "Feature",
  "properties": {
    "gn:admin1_code":"10",
    "gn:admin2_code":"17.0",
    "gn:asciiname":"Los Atascaderos",
    "gn:country_code":"MX",
    "gn:dem":1733,
    "gn:feature_class":"P",
    "gn:feature_code":"PPL",
    "gn:name":"Los Atascaderos",
    "gn:population":0,
    "gn:timezone":"America/Monterrey",
    "iso:country":"MX",
    "name:spa_x_preferred":[
        "Los Atascaderos"
    ],
    "wof:name":"Los Atascaderos",
    "wof:placetype":"locality"
},
  "geometry": {"coordinates":[-105.35787999999999,26.31374000000001],"type":"Point"}
}