{
  "type": "Feature",
  "properties": {
    "gn:admin1_code":"20",
    "gn:admin2_code":"102.0",
    "gn:asciiname":"Rancho Buenavista",
    "gn:country_code":"MX",
    "gn:dem":1645,
    "gn:feature_class":"P",
    "gn:feature_code":"PPL",
    "gn:name":"Rancho Buenavista",
    "gn:population":79,
    "gn:timezone":"America/Mexico_City",
    "iso:country":"MX",
    "wof:name":"Rancho Buenavista",
    "wof:placetype":"locality",
    "wof:population":79
},
  "geometry": {"coordinates":[-96.8625,17.18139],"type":"Point"}
}