{
  "type": "Feature",
  "properties": {
    "gn:admin1_code":"10",
    "gn:admin2_code":"9.0",
    "gn:asciiname":"Canada Verde de Abajo",
    "gn:country_code":"MX",
    "gn:dem":2645,
    "gn:feature_class":"P",
    "gn:feature_code":"PPL",
    "gn:name":"Ca\u00f1ada Verde de Abajo",
    "gn:population":0,
    "gn:timezone":"America/Monterrey",
    "iso:country":"MX",
    "name:spa_x_preferred":[
        "Ca\u00f1ada Verde de Abajo"
    ],
    "wof:name":"Canada Verde de Abajo",
    "wof:placetype":"locality"
},
  "geometry": {"coordinates":[-106.25629000000001,26.19533],"type":"Point"}
}