{
  "type": "Feature",
  "properties": {
    "gn:admin1_code":"13",
    "gn:admin2_code":"64.0",
    "gn:asciiname":"Tepetitlan",
    "gn:country_code":"MX",
    "gn:dem":2025,
    "gn:feature_class":"P",
    "gn:feature_code":"PPL",
    "gn:name":"Tepetitlan",
    "gn:population":836,
    "gn:timezone":"America/Mexico_City",
    "iso:country":"MX",
    "name:spa_x_preferred":[
        "Tepetitlan"
    ],
    "name:und_x_variant":[
        "Tepetitl\u00e1n"
    ],
    "wof:name":"Tepetitlan",
    "wof:placetype":"locality",
    "wof:population":836
},
  "geometry": {"coordinates":[-99.38054,20.18718],"type":"Point"}
}