{
  "type": "Feature",
  "properties": {
    "gn:admin1_code":"16.0",
    "gn:admin2_code":"15.0",
    "gn:asciiname":"Piedra Colorada",
    "gn:country_code":"MX",
    "gn:dem":1209,
    "gn:feature_class":"P",
    "gn:feature_code":"PPL",
    "gn:name":"Piedra Colorada",
    "gn:population":0,
    "gn:timezone":"America/Mexico_City",
    "iso:country":"MX",
    "name:spa_x_preferred":[
        "Piedra Colorada"
    ],
    "wof:name":"Piedra Colorada",
    "wof:placetype":"locality"
},
  "geometry": {"coordinates":[-103.22114999999999,18.92587],"type":"Point"}
}