{
  "type": "Feature",
  "properties": {
    "gn:admin1_code":"6",
    "gn:admin2_code":"46.0",
    "gn:asciiname":"Ejido Sorobuena",
    "gn:country_code":"MX",
    "gn:dem":1047,
    "gn:feature_class":"P",
    "gn:feature_code":"PPL",
    "gn:name":"Ejido Sorobuena",
    "gn:population":0,
    "gn:timezone":"America/Mazatlan",
    "iso:country":"MX",
    "name:spa_x_preferred":[
        "Ejido Sorobuena"
    ],
    "name:und_x_variant":[
        "Sorobuena"
    ],
    "wof:name":"Ejido Sorobuena",
    "wof:placetype":"locality"
},
  "geometry": {"coordinates":[-107.90143999999999,26.53573],"type":"Point"}
}