{
  "type": "Feature",
  "properties": {
    "gn:admin1_code":"20",
    "gn:admin2_code":"366",
    "gn:asciiname":"Arroyo Hueso",
    "gn:country_code":"MX",
    "gn:dem":782,
    "gn:feature_class":"P",
    "gn:feature_code":"PPL",
    "gn:name":"Arroyo Hueso",
    "gn:population":13,
    "gn:timezone":"America/Mexico_City",
    "iso:country":"MX",
    "wof:name":"Arroyo Hueso",
    "wof:placetype":"locality",
    "wof:population":13
},
  "geometry": {"coordinates":[-96.70944,16.07167],"type":"Point"}
}