{
  "type": "Feature",
  "properties": {
    "gn:admin1_code":"25",
    "gn:admin2_code":"13.0",
    "gn:asciiname":"Pitaruto",
    "gn:country_code":"MX",
    "gn:dem":23,
    "gn:feature_class":"P",
    "gn:feature_code":"PPL",
    "gn:name":"Pitaruto",
    "gn:population":0,
    "gn:timezone":"America/Mazatlan",
    "iso:country":"MX",
    "wof:name":"Pitaruto",
    "wof:placetype":"locality"
},
  "geometry": {"coordinates":[-107.72917,24.97417],"type":"Point"}
}