{
  "type": "Feature",
  "properties": {
    "gn:admin1_code":"30",
    "gn:admin2_code":"38.0",
    "gn:asciiname":"La Mascota",
    "gn:country_code":"MX",
    "gn:dem":1283,
    "gn:feature_class":"P",
    "gn:feature_code":"PPL",
    "gn:name":"La Mascota",
    "gn:population":0,
    "gn:timezone":"America/Mexico_City",
    "iso:country":"MX",
    "wof:name":"La Mascota",
    "wof:placetype":"locality"
},
  "geometry": {"coordinates":[-96.99299000000001,19.46279],"type":"Point"}
}