{
  "type": "Feature",
  "properties": {
    "gn:admin1_code":"6",
    "gn:admin2_code":"1.0",
    "gn:asciiname":"El Galleguito",
    "gn:country_code":"MX",
    "gn:dem":1661,
    "gn:feature_class":"P",
    "gn:feature_code":"PPL",
    "gn:name":"El Galleguito",
    "gn:population":0,
    "gn:timezone":"America/Chihuahua",
    "iso:country":"MX",
    "name:spa_x_preferred":[
        "El Galleguito"
    ],
    "name:spa_x_variant":[
        "Los \u00c1lamos"
    ],
    "wof:name":"El Galleguito",
    "wof:placetype":"locality"
},
  "geometry": {"coordinates":[-106.35623,29.82461],"type":"Point"}
}