{
  "type": "Feature",
  "properties": {
    "gn:admin1_code":"19",
    "gn:admin2_code":"9.0",
    "gn:asciiname":"El Sabinito",
    "gn:country_code":"MX",
    "gn:dem":244,
    "gn:feature_class":"P",
    "gn:feature_code":"PPL",
    "gn:name":"El Sabinito",
    "gn:population":0,
    "gn:timezone":"America/Monterrey",
    "iso:country":"MX",
    "name:spa_x_preferred":[
        "El Sabinito"
    ],
    "wof:name":"El Sabinito",
    "wof:placetype":"locality"
},
  "geometry": {"coordinates":[-99.72807,25.4834],"type":"Point"}
}