{
  "type": "Feature",
  "properties": {
    "gn:admin1_code":"13",
    "gn:admin2_code":"28.0",
    "gn:asciiname":"Capane",
    "gn:country_code":"MX",
    "gn:dem":205,
    "gn:feature_class":"P",
    "gn:feature_code":"PPL",
    "gn:name":"Cap\u00e1ne",
    "gn:population":77,
    "gn:timezone":"America/Mexico_City",
    "iso:country":"MX",
    "name:und_x_variant":[
        "Cap\u00e1ne"
    ],
    "wof:name":"Capane",
    "wof:placetype":"locality",
    "wof:population":77
},
  "geometry": {"coordinates":[-98.48222,21.21333],"type":"Point"}
}