{
  "type": "Feature",
  "properties": {
    "gn:admin1_code":"32.0",
    "gn:asciiname":"Rio de Abajo",
    "gn:country_code":"MX",
    "gn:dem":2093,
    "gn:feature_class":"P",
    "gn:feature_code":"PPL",
    "gn:name":"R\u00edo de Abajo",
    "gn:population":0,
    "gn:timezone":"America/Mexico_City",
    "iso:country":"MX",
    "name:spa_x_preferred":[
        "R\u00edo de Abajo"
    ],
    "wof:name":"Rio de Abajo",
    "wof:placetype":"locality"
},
  "geometry": {"coordinates":[-102.77405,21.56521],"type":"Point"}
}