{
  "type": "Feature",
  "properties": {
    "gn:admin1_code":"32.0",
    "gn:admin2_code":"38.0",
    "gn:asciiname":"El Refugio de los Ortiz",
    "gn:country_code":"MX",
    "gn:dem":2266,
    "gn:feature_class":"P",
    "gn:feature_code":"PPL",
    "gn:name":"El Refugio de los Ort\u00edz",
    "gn:population":0,
    "gn:timezone":"America/Mexico_City",
    "iso:country":"MX",
    "name:spa_x_preferred":[
        "El Refugio de los Ort\u00edz"
    ],
    "name:und_x_variant":[
        "Refugio",
        "El Refugio"
    ],
    "wof:name":"El Refugio de los Ortiz",
    "wof:placetype":"locality"
},
  "geometry": {"coordinates":[-101.51528,22.00021],"type":"Point"}
}