{
  "type": "Feature",
  "properties": {
    "gn:admin1_code":"30.0",
    "gn:admin2_code":"91.0",
    "gn:asciiname":"La Triplay",
    "gn:country_code":"MX",
    "gn:dem":50,
    "gn:feature_class":"P",
    "gn:feature_code":"PPL",
    "gn:name":"La Triplay",
    "gn:population":0,
    "gn:timezone":"America/Mexico_City",
    "iso:country":"MX",
    "name:spa_x_preferred":[
        "La Triplay"
    ],
    "name:spa_x_variant":[
        "Suchilapa de C\u00e1rdenas"
    ],
    "wof:name":"La Triplay",
    "wof:placetype":"locality"
},
  "geometry": {"coordinates":[-95.02809000000001,17.36753],"type":"Point"}
}