{
  "type": "Feature",
  "properties": {
    "gn:admin1_code":"24.0",
    "gn:admin2_code":"20.0",
    "gn:asciiname":"Alegre",
    "gn:country_code":"MX",
    "gn:dem":1592,
    "gn:feature_class":"P",
    "gn:feature_code":"PPL",
    "gn:name":"Alegre",
    "gn:population":0,
    "gn:timezone":"America/Mexico_City",
    "iso:country":"MX",
    "name:cat_x_preferred":[
        "Alegre"
    ],
    "name:ceb_x_preferred":[
        "Alegre"
    ],
    "name:deu_x_preferred":[
        "Alegre"
    ],
    "name:fra_x_preferred":[
        "Alegre"
    ],
    "name:nld_x_preferred":[
        "Alegre"
    ],
    "name:srp_x_preferred":[
        "\u0410\u043b\u0435\u0433\u0440\u0435"
    ],
    "name:swe_x_preferred":[
        "Alegre"
    ],
    "wof:name":"Alegre",
    "wof:placetype":"locality"
},
  "geometry": {"coordinates":[-100.59036,23.74134],"type":"Point"}
}