{
  "type": "Feature",
  "properties": {
    "gn:admin1_code":"1.0",
    "gn:admin2_code":"4.0",
    "gn:asciiname":"Los Arenales",
    "gn:country_code":"MX",
    "gn:dem":1983,
    "gn:feature_class":"P",
    "gn:feature_code":"PPL",
    "gn:name":"Los Arenales",
    "gn:population":0,
    "gn:timezone":"America/Mexico_City",
    "iso:country":"MX",
    "name:spa_x_preferred":[
        "Los Arenales"
    ],
    "wof:name":"Los Arenales",
    "wof:placetype":"locality"
},
  "geometry": {"coordinates":[-102.29583,22.42377],"type":"Point"}
}