{
  "type": "Feature",
  "properties": {
    "gn:admin1_code":"28.0",
    "gn:admin2_code":"37.0",
    "gn:asciiname":"El Mirador",
    "gn:country_code":"MX",
    "gn:dem":83,
    "gn:feature_class":"P",
    "gn:feature_code":"PPL",
    "gn:name":"El Mirador",
    "gn:population":3,
    "gn:timezone":"America/Monterrey",
    "iso:country":"MX",
    "name:spa_x_preferred":[
        "El Mirador"
    ],
    "wof:name":"El Mirador",
    "wof:placetype":"locality",
    "wof:population":3
},
  "geometry": {"coordinates":[-97.93644,23.85485],"type":"Point"}
}