{
  "type": "Feature",
  "properties": {
    "gn:admin1_code":"6",
    "gn:admin2_code":"36.0",
    "gn:asciiname":"Texcoco",
    "gn:country_code":"MX",
    "gn:dem":1397,
    "gn:feature_class":"P",
    "gn:feature_code":"PPL",
    "gn:name":"Texcoco",
    "gn:population":0,
    "gn:timezone":"America/Chihuahua",
    "iso:country":"MX",
    "name:ceb_x_preferred":[
        "Texcoco"
    ],
    "name:eus_x_preferred":[
        "Texcoco"
    ],
    "name:ind_x_preferred":[
        "Texcoco"
    ],
    "name:kat_x_preferred":[
        "\u10e2\u10d4\u10e1\u10d9\u10dd\u10d9\u10dd"
    ],
    "name:lit_x_preferred":[
        "Teskokas"
    ],
    "name:ron_x_preferred":[
        "Texcoco"
    ],
    "name:rus_x_preferred":[
        "\u0422\u0435\u0441\u043a\u043e\u043a\u043e"
    ],
    "name:sco_x_preferred":[
        "Texcoco"
    ],
    "name:spa_x_preferred":[
        "Texcoco"
    ],
    "name:swe_x_preferred":[
        "Texcoco"
    ],
    "name:tur_x_preferred":[
        "Texcoco"
    ],
    "name:ukr_x_preferred":[
        "\u0422\u0435\u0441\u043a\u043e\u043a\u043e"
    ],
    "wof:name":"Texcoco",
    "wof:placetype":"locality"
},
  "geometry": {"coordinates":[-104.38333,26.98333],"type":"Point"}
}