{
  "type": "Feature",
  "properties": {
    "gn:admin1_code":"30.0",
    "gn:admin2_code":"13.0",
    "gn:asciiname":"Melchor Ocampo",
    "gn:country_code":"MX",
    "gn:dem":52,
    "gn:feature_class":"P",
    "gn:feature_code":"PPL",
    "gn:name":"Melchor Ocampo",
    "gn:population":231,
    "gn:timezone":"America/Mexico_City",
    "iso:country":"MX",
    "name:deu_x_preferred":[
        "Melchor Ocampo"
    ],
    "name:epo_x_preferred":[
        "Melchor Ocampo"
    ],
    "name:fra_x_preferred":[
        "Melchor Ocampo"
    ],
    "name:ita_x_preferred":[
        "Melchor Ocampo"
    ],
    "name:nld_x_preferred":[
        "Melchor Ocampo"
    ],
    "name:pol_x_preferred":[
        "Melchor Ocampo"
    ],
    "name:por_x_preferred":[
        "Melchor Ocampo"
    ],
    "name:que_x_preferred":[
        "Melchor Ocampo"
    ],
    "name:rus_x_preferred":[
        "\u041e\u043a\u0430\u043c\u043f\u043e"
    ],
    "name:spa_x_preferred":[
        "Melchor Ocampo"
    ],
    "wof:name":"Melchor Ocampo",
    "wof:placetype":"locality",
    "wof:population":231
},
  "geometry": {"coordinates":[-97.61278,21.325],"type":"Point"}
}