{
  "type": "Feature",
  "properties": {
    "gn:admin1_code":"9",
    "gn:admin2_code":"13.0",
    "gn:asciiname":"Axayopa",
    "gn:country_code":"MX",
    "gn:dem":2246,
    "gn:feature_class":"P",
    "gn:feature_code":"PPL",
    "gn:name":"Axayopa",
    "gn:population":72,
    "gn:timezone":"America/Mexico_City",
    "iso:country":"MX",
    "wof:name":"Axayopa",
    "wof:placetype":"locality",
    "wof:population":72
},
  "geometry": {"coordinates":[-99.05944,19.25694],"type":"Point"}
}