{
  "type": "Feature",
  "properties": {
    "gn:admin1_code":"20",
    "gn:admin2_code":"463",
    "gn:asciiname":"La Rosa",
    "gn:country_code":"MX",
    "gn:dem":1480,
    "gn:feature_class":"P",
    "gn:feature_code":"PPL",
    "gn:name":"La Rosa",
    "gn:population":19,
    "gn:timezone":"America/Mexico_City",
    "iso:country":"MX",
    "wof:name":"La Rosa",
    "wof:placetype":"locality",
    "wof:population":19
},
  "geometry": {"coordinates":[-97.03222,17.46611],"type":"Point"}
}