{
  "type": "Feature",
  "properties": {
    "gn:admin1_code":"30",
    "gn:admin2_code":"175",
    "gn:asciiname":"Pedro Garcia Rosas",
    "gn:country_code":"MX",
    "gn:dem":106,
    "gn:feature_class":"P",
    "gn:feature_code":"PPL",
    "gn:name":"Pedro Garc\u00eda Rosas",
    "gn:population":38,
    "gn:timezone":"America/Mexico_City",
    "iso:country":"MX",
    "name:und_x_variant":[
        "Pedro Garc\u00eda Rosas"
    ],
    "wof:name":"Pedro Garcia Rosas",
    "wof:placetype":"locality",
    "wof:population":38
},
  "geometry": {"coordinates":[-97.51472,20.74222],"type":"Point"}
}