{
  "type": "Feature",
  "properties": {
    "gn:admin1_code":"26.0",
    "gn:admin2_code":"36.0",
    "gn:asciiname":"Mision Viejo",
    "gn:country_code":"MX",
    "gn:dem":777,
    "gn:feature_class":"P",
    "gn:feature_code":"PPL",
    "gn:name":"Misi\u00f3n Viejo",
    "gn:population":0,
    "gn:timezone":"America/Hermosillo",
    "iso:country":"MX",
    "name:spa_x_preferred":[
        "Misi\u00f3n Viejo"
    ],
    "wof:name":"Mision Viejo",
    "wof:placetype":"locality"
},
  "geometry": {"coordinates":[-110.9499,30.67168],"type":"Point"}
}