{
  "type": "Feature",
  "properties": {
    "gn:admin1_code":"5",
    "gn:admin2_code":"59.0",
    "gn:asciiname":"La Era Kantulan",
    "gn:country_code":"MX",
    "gn:dem":673,
    "gn:feature_class":"P",
    "gn:feature_code":"PPL",
    "gn:name":"La Era Kantulan",
    "gn:population":7,
    "gn:timezone":"America/Mexico_City",
    "iso:country":"MX",
    "wof:name":"La Era Kantulan",
    "wof:placetype":"locality",
    "wof:population":7
},
  "geometry": {"coordinates":[-91.84972,16.93583],"type":"Point"}
}