{
  "type": "Feature",
  "properties": {
    "gn:admin1_code":"5.0",
    "gn:admin2_code":"23.0",
    "gn:asciiname":"Chikbil Tenal",
    "gn:country_code":"MX",
    "gn:dem":2376,
    "gn:feature_class":"P",
    "gn:feature_code":"PPL",
    "gn:name":"Chikbil Tenal",
    "gn:population":0,
    "gn:timezone":"America/Mexico_City",
    "iso:country":"MX",
    "name:spa_x_preferred":[
        "Chikbil Tenal"
    ],
    "wof:name":"Chikbil Tenal",
    "wof:placetype":"locality"
},
  "geometry": {"coordinates":[-92.66994,16.82499],"type":"Point"}
}