{
  "type": "Feature",
  "properties": {
    "gn:admin1_code":"3",
    "gn:admin2_code":"2.0",
    "gn:asciiname":"Ninguno [CERESO]",
    "gn:country_code":"MX",
    "gn:dem":77,
    "gn:feature_class":"P",
    "gn:feature_code":"PPL",
    "gn:name":"Ninguno [CERESO]",
    "gn:population":121,
    "gn:timezone":"America/Mazatlan",
    "iso:country":"MX",
    "wof:name":"Ninguno [CERESO]",
    "wof:placetype":"locality",
    "wof:population":121
},
  "geometry": {"coordinates":[-112.24334,27.28382],"type":"Point"}
}