{
  "type": "Feature",
  "properties": {
    "gn:admin1_code":"14",
    "gn:admin2_code":"120.0",
    "gn:asciiname":"La Mesita",
    "gn:country_code":"MX",
    "gn:dem":1664,
    "gn:feature_class":"P",
    "gn:feature_code":"PPL",
    "gn:name":"La Mesita",
    "gn:population":235,
    "gn:timezone":"America/Mexico_City",
    "iso:country":"MX",
    "wof:name":"La Mesita",
    "wof:placetype":"locality",
    "wof:population":235
},
  "geometry": {"coordinates":[-103.50667,20.83889],"type":"Point"}
}