{
  "type": "Feature",
  "properties": {
    "gn:admin1_code":"11.0",
    "gn:admin2_code":"27.0",
    "gn:asciiname":"San Rafael de Uruetaro",
    "gn:country_code":"MX",
    "gn:dem":1719,
    "gn:feature_class":"P",
    "gn:feature_code":"PPL",
    "gn:name":"San Rafael de Uru\u00e9taro",
    "gn:population":0,
    "gn:timezone":"America/Mexico_City",
    "iso:country":"MX",
    "name:spa_x_preferred":[
        "San Rafael de Uru\u00e9taro"
    ],
    "wof:name":"San Rafael de Uruetaro",
    "wof:placetype":"locality"
},
  "geometry": {"coordinates":[-101.17751,20.5053],"type":"Point"}
}