{
  "type": "Feature",
  "properties": {
    "gn:admin1_code":"18",
    "gn:admin2_code":"9",
    "gn:asciiname":"El Banco",
    "gn:country_code":"MX",
    "gn:dem":690,
    "gn:feature_class":"P",
    "gn:feature_code":"PPL",
    "gn:name":"El Banco",
    "gn:population":17,
    "gn:timezone":"America/Mazatlan",
    "iso:country":"MX",
    "wof:name":"El Banco",
    "wof:placetype":"locality",
    "wof:population":17
},
  "geometry": {"coordinates":[-104.46194,22.27306],"type":"Point"}
}