{
  "type": "Feature",
  "properties": {
    "gn:admin1_code":"27",
    "gn:admin2_code":"6.0",
    "gn:asciiname":"Once de Febrero Segunda Seccion",
    "gn:country_code":"MX",
    "gn:dem":22,
    "gn:feature_class":"P",
    "gn:feature_code":"PPL",
    "gn:name":"Once de Febrero Segunda Secci\u00f3n",
    "gn:population":0,
    "gn:timezone":"America/Mexico_City",
    "iso:country":"MX",
    "name:spa_x_preferred":[
        "Once de Febrero Segunda Secci\u00f3n"
    ],
    "wof:name":"Once de Febrero Segunda Seccion",
    "wof:placetype":"locality"
},
  "geometry": {"coordinates":[-93.32577999999999,18.0621],"type":"Point"}
}