{
  "type": "Feature",
  "properties": {
    "gn:admin1_code":"5",
    "gn:admin2_code":"19",
    "gn:asciiname":"Islapa (Guadalupe)",
    "gn:country_code":"MX",
    "gn:dem":1670,
    "gn:feature_class":"P",
    "gn:feature_code":"PPL",
    "gn:name":"Islap\u00e1 (Guadalupe)",
    "gn:population":33,
    "gn:timezone":"America/Mexico_City",
    "iso:country":"MX",
    "name:und_x_variant":[
        "Islap\u00e1 (Guadalupe)"
    ],
    "wof:name":"Islapa (Guadalupe)",
    "wof:placetype":"locality",
    "wof:population":33
},
  "geometry": {"coordinates":[-92.14461,16.15519],"type":"Point"}
}