{
  "type": "Feature",
  "properties": {
    "gn:admin1_code":"25",
    "gn:admin2_code":"6.0",
    "gn:asciiname":"Tule 5",
    "gn:country_code":"MX",
    "gn:dem":95,
    "gn:feature_class":"P",
    "gn:feature_code":"PPL",
    "gn:name":"Tule 5",
    "gn:population":5,
    "gn:timezone":"America/Mazatlan",
    "iso:country":"MX",
    "wof:name":"Tule 5",
    "wof:placetype":"locality",
    "wof:population":5
},
  "geometry": {"coordinates":[-107.34058,24.71289],"type":"Point"}
}