{
  "type": "Feature",
  "properties": {
    "gn:admin1_code":"26",
    "gn:admin2_code":"30.0",
    "gn:asciiname":"Cocori",
    "gn:country_code":"MX",
    "gn:dem":17,
    "gn:feature_class":"P",
    "gn:feature_code":"PPL",
    "gn:name":"C\u00f3cori",
    "gn:population":0,
    "gn:timezone":"America/Hermosillo",
    "iso:country":"MX",
    "name:spa_x_preferred":[
        "C\u00f3cori"
    ],
    "name:spa_x_variant":[
        "C\u00f3corit"
    ],
    "wof:name":"Cocori",
    "wof:placetype":"locality"
},
  "geometry": {"coordinates":[-111.6879,28.65973],"type":"Point"}
}