{
  "type": "Feature",
  "properties": {
    "gn:admin1_code":"30",
    "gn:admin2_code":"141.0",
    "gn:asciiname":"Los Merida",
    "gn:country_code":"MX",
    "gn:dem":127,
    "gn:feature_class":"P",
    "gn:feature_code":"PPL",
    "gn:name":"Los M\u00e9rida",
    "gn:population":770,
    "gn:timezone":"America/Mexico_City",
    "iso:country":"MX",
    "name:und_x_variant":[
        "Los M\u00e9rida"
    ],
    "wof:name":"Los Merida",
    "wof:placetype":"locality",
    "wof:population":770
},
  "geometry": {"coordinates":[-95.27583,18.38],"type":"Point"}
}