{
  "type": "Feature",
  "properties": {
    "gn:admin1_code":"12",
    "gn:admin2_code":"4.0",
    "gn:asciiname":"Almolonga de Ocampo (Almolonga)",
    "gn:country_code":"MX",
    "gn:dem":1451,
    "gn:feature_class":"P",
    "gn:feature_code":"PPL",
    "gn:name":"Almolonga de Ocampo (Almolonga)",
    "gn:population":878,
    "gn:timezone":"America/Mexico_City",
    "iso:country":"MX",
    "wof:name":"Almolonga de Ocampo (Almolonga)",
    "wof:placetype":"locality",
    "wof:population":878
},
  "geometry": {"coordinates":[-98.35444,17.42],"type":"Point"}
}