{
  "type": "Feature",
  "properties": {
    "gn:admin1_code":"20",
    "gn:admin2_code":"412.0",
    "gn:asciiname":"Los Valles",
    "gn:country_code":"MX",
    "gn:dem":463,
    "gn:feature_class":"P",
    "gn:feature_code":"PPL",
    "gn:name":"Los Valles",
    "gn:population":0,
    "gn:timezone":"America/Mexico_City",
    "iso:country":"MX",
    "name:spa_x_preferred":[
        "Los Valles"
    ],
    "wof:name":"Los Valles",
    "wof:placetype":"locality"
},
  "geometry": {"coordinates":[-95.33423000000001,16.93672999999999],"type":"Point"}
}