{
  "type": "Feature",
  "properties": {
    "gn:admin1_code":"12",
    "gn:admin2_code":"33.0",
    "gn:asciiname":"Conhuaxo",
    "gn:country_code":"MX",
    "gn:dem":896,
    "gn:feature_class":"P",
    "gn:feature_code":"PPL",
    "gn:name":"Conhuaxo",
    "gn:population":414,
    "gn:timezone":"America/Mexico_City",
    "iso:country":"MX",
    "wof:name":"Conhuaxo",
    "wof:placetype":"locality",
    "wof:population":414
},
  "geometry": {"coordinates":[-98.57832999999999,17.79083],"type":"Point"}
}