{
  "type": "Feature",
  "properties": {
    "gn:admin1_code":"14",
    "gn:admin2_code":"61",
    "gn:asciiname":"Culecuapo (Cueuncalpa)",
    "gn:country_code":"MX",
    "gn:dem":1335,
    "gn:feature_class":"P",
    "gn:feature_code":"PPL",
    "gn:name":"Culecuapo (Cueuncalpa)",
    "gn:population":14,
    "gn:timezone":"America/Mexico_City",
    "iso:country":"MX",
    "wof:name":"Culecuapo (Cueuncalpa)",
    "wof:placetype":"locality",
    "wof:population":14
},
  "geometry": {"coordinates":[-104.29361,22.17806],"type":"Point"}
}