{
  "type": "Feature",
  "properties": {
    "gn:admin1_code":"7",
    "gn:admin2_code":"22.0",
    "gn:asciiname":"El Gavilan",
    "gn:country_code":"MX",
    "gn:dem":316,
    "gn:feature_class":"P",
    "gn:feature_code":"PPL",
    "gn:name":"El Gavil\u00e1n",
    "gn:population":0,
    "gn:timezone":"America/Monterrey",
    "iso:country":"MX",
    "name:und_x_variant":[
        "El Gavil\u00e1n",
        "Rancho El Gavil\u00e1n",
        "Gavil\u00e1n"
    ],
    "wof:name":"El Gavilan",
    "wof:placetype":"locality"
},
  "geometry": {"coordinates":[-100.74888,28.51256],"type":"Point"}
}