{
  "type": "Feature",
  "properties": {
    "gn:admin1_code":"11.0",
    "gn:admin2_code":"20.0",
    "gn:asciiname":"San Gabriel",
    "gn:country_code":"MX",
    "gn:dem":1784,
    "gn:feature_class":"P",
    "gn:feature_code":"PPL",
    "gn:name":"San Gabriel",
    "gn:population":0,
    "gn:timezone":"America/Mexico_City",
    "iso:country":"MX",
    "name:cat_x_preferred":[
        "San Gabriel"
    ],
    "name:ceb_x_preferred":[
        "San Gabriel"
    ],
    "name:deu_x_preferred":[
        "San Gabriel"
    ],
    "name:eus_x_preferred":[
        "San Gabriel"
    ],
    "name:fra_x_preferred":[
        "San Gabriel"
    ],
    "name:glg_x_preferred":[
        "San Gabriel"
    ],
    "name:heb_x_preferred":[
        "\u05e1\u05df \u05d2\u05d1\u05e8\u05d9\u05d0\u05dc"
    ],
    "name:ita_x_preferred":[
        "San Gabriel"
    ],
    "name:nld_x_preferred":[
        "San Gabriel"
    ],
    "name:pol_x_preferred":[
        "San Gabriel"
    ],
    "name:por_x_preferred":[
        "San Gabriel"
    ],
    "name:rus_x_preferred":[
        "\u0421\u0430\u043d-\u0413\u0435\u0439\u0431\u0440\u0438\u0435\u043b"
    ],
    "name:sco_x_preferred":[
        "San Gabriel"
    ],
    "name:spa_x_preferred":[
        "San Gabriel"
    ],
    "name:srp_x_preferred":[
        "San Gabriel"
    ],
    "name:swe_x_preferred":[
        "San Gabriel"
    ],
    "name:war_x_preferred":[
        "San Gabriel"
    ],
    "wof:name":"San Gabriel",
    "wof:placetype":"locality"
},
  "geometry": {"coordinates":[-101.69596,21.05541],"type":"Point"}
}