{
  "type": "Feature",
  "properties": {
    "gn:admin1_code":"13",
    "gn:admin2_code":"22",
    "gn:asciiname":"San Jose el Tecolote",
    "gn:country_code":"MX",
    "gn:dem":2517,
    "gn:feature_class":"P",
    "gn:feature_code":"PPL",
    "gn:name":"San Jos\u00e9 el Tecolote",
    "gn:population":26,
    "gn:timezone":"America/Mexico_City",
    "iso:country":"MX",
    "name:und_x_variant":[
        "San Jos\u00e9 el Tecolote"
    ],
    "wof:name":"San Jose el Tecolote",
    "wof:placetype":"locality",
    "wof:population":26
},
  "geometry": {"coordinates":[-98.62103999999999,20.03291],"type":"Point"}
}