{
  "type": "Feature",
  "properties": {
    "gn:admin1_code":"11.0",
    "gn:admin2_code":"37.0",
    "gn:asciiname":"Playas de Sotelo",
    "gn:country_code":"MX",
    "gn:dem":1783,
    "gn:feature_class":"P",
    "gn:feature_code":"PPL",
    "gn:name":"Playas de Sotelo",
    "gn:population":0,
    "gn:timezone":"America/Mexico_City",
    "iso:country":"MX",
    "name:und_x_variant":[
        "Las Rayas de Sotelo"
    ],
    "wof:name":"Playas de Sotelo",
    "wof:placetype":"locality"
},
  "geometry": {"coordinates":[-101.54986,20.96765],"type":"Point"}
}