{
  "type": "Feature",
  "properties": {
    "gn:admin1_code":"20",
    "gn:admin2_code":"202.0",
    "gn:asciiname":"El Doscientos Uno",
    "gn:country_code":"MX",
    "gn:dem":1107,
    "gn:feature_class":"P",
    "gn:feature_code":"PPL",
    "gn:name":"El Doscientos Uno",
    "gn:population":71,
    "gn:timezone":"America/Mexico_City",
    "iso:country":"MX",
    "wof:name":"El Doscientos Uno",
    "wof:placetype":"locality",
    "wof:population":71
},
  "geometry": {"coordinates":[-97.08778,16.16194],"type":"Point"}
}