{
  "type": "Feature",
  "properties": {
    "gn:admin1_code":"21",
    "gn:admin2_code":"188.0",
    "gn:asciiname":"Santa Catalina Cuilotepec",
    "gn:country_code":"MX",
    "gn:dem":2409,
    "gn:feature_class":"P",
    "gn:feature_code":"PPL",
    "gn:name":"Santa Catalina Cuilotepec",
    "gn:population":0,
    "gn:timezone":"America/Mexico_City",
    "iso:country":"MX",
    "name:spa_x_preferred":[
        "Santa Catalina Cuilotepec"
    ],
    "name:spa_x_variant":[
        "Colonia Guadalupe"
    ],
    "name:und_x_variant":[
        "Cuilotepee"
    ],
    "wof:name":"Santa Catalina Cuilotepec",
    "wof:placetype":"locality"
},
  "geometry": {"coordinates":[-98.61803999999999,18.90999],"type":"Point"}
}