{
  "type": "Feature",
  "properties": {
    "gn:admin1_code":"5",
    "gn:admin2_code":"99.0",
    "gn:asciiname":"Montecarlo",
    "gn:country_code":"MX",
    "gn:dem":611,
    "gn:feature_class":"P",
    "gn:feature_code":"PPL",
    "gn:name":"Montecarlo",
    "gn:population":7,
    "gn:timezone":"America/Mexico_City",
    "iso:country":"MX",
    "wof:name":"Montecarlo",
    "wof:placetype":"locality",
    "wof:population":7
},
  "geometry": {"coordinates":[-91.94110999999999,15.85917],"type":"Point"}
}