{
  "type": "Feature",
  "properties": {
    "gn:admin1_code":"26",
    "gn:admin2_code":"68.0",
    "gn:asciiname":"Las Botellas",
    "gn:country_code":"MX",
    "gn:dem":598,
    "gn:feature_class":"P",
    "gn:feature_code":"PPL",
    "gn:name":"Las Botellas",
    "gn:population":0,
    "gn:timezone":"America/Hermosillo",
    "iso:country":"MX",
    "name:spa_x_preferred":[
        "Las Botellas"
    ],
    "wof:name":"Las Botellas",
    "wof:placetype":"locality"
},
  "geometry": {"coordinates":[-110.03397,28.97972],"type":"Point"}
}