{
  "type": "Feature",
  "properties": {
    "gn:admin1_code":"14",
    "gn:admin2_code":"70",
    "gn:asciiname":"El Gigante",
    "gn:country_code":"MX",
    "gn:dem":1509,
    "gn:feature_class":"P",
    "gn:feature_code":"PPL",
    "gn:name":"El Gigante",
    "gn:population":18,
    "gn:timezone":"America/Mexico_City",
    "iso:country":"MX",
    "wof:name":"El Gigante",
    "wof:placetype":"locality",
    "wof:population":18
},
  "geometry": {"coordinates":[-103.17749999999999,20.50556],"type":"Point"}
}