{
  "type": "Feature",
  "properties": {
    "gn:admin1_code":"26",
    "gn:admin2_code":"18.0",
    "gn:asciiname":"Campo Garcia Preciado",
    "gn:country_code":"MX",
    "gn:dem":20,
    "gn:feature_class":"P",
    "gn:feature_code":"PPL",
    "gn:name":"Campo Garc\u00eda Preciado",
    "gn:population":5,
    "gn:timezone":"America/Hermosillo",
    "iso:country":"MX",
    "name:und_x_variant":[
        "Campo Garc\u00eda Preciado"
    ],
    "wof:name":"Campo Garcia Preciado",
    "wof:placetype":"locality",
    "wof:population":5
},
  "geometry": {"coordinates":[-109.99388999999999,27.29056],"type":"Point"}
}