{
  "type": "Feature",
  "properties": {
    "gn:admin1_code":"5",
    "gn:admin2_code":"34",
    "gn:asciiname":"San Antonio Playa Grande",
    "gn:country_code":"MX",
    "gn:dem":589,
    "gn:feature_class":"P",
    "gn:feature_code":"PPL",
    "gn:name":"San Antonio Playa Grande",
    "gn:population":41,
    "gn:timezone":"America/Mexico_City",
    "iso:country":"MX",
    "wof:name":"San Antonio Playa Grande",
    "wof:placetype":"locality",
    "wof:population":41
},
  "geometry": {"coordinates":[-92.00055999999999,15.83278],"type":"Point"}
}