{
  "type": "Feature",
  "properties": {
    "gn:admin1_code":"5",
    "gn:admin2_code":"109",
    "gn:asciiname":"Sierra Morena",
    "gn:country_code":"MX",
    "gn:dem":1289,
    "gn:feature_class":"P",
    "gn:feature_code":"PPL",
    "gn:name":"Sierra Morena",
    "gn:population":10,
    "gn:timezone":"America/Mexico_City",
    "iso:country":"MX",
    "name:ara_x_preferred":[
        "\u0633\u064a\u064a\u0631\u0627 \u0645\u0648\u0631\u064a\u0646\u0627"
    ],
    "name:ben_x_preferred":[
        "\u09b8\u09bf\u09af\u09bc\u09c7\u09b0\u09be \u09ae\u09cb\u09b0\u09c7\u09a8\u09be"
    ],
    "name:bul_x_preferred":[
        "\u0421\u0438\u0435\u0440\u0430 \u041c\u043e\u0440\u0435\u043d\u0430"
    ],
    "name:cat_x_preferred":[
        "Sierra Morena"
    ],
    "name:ces_x_preferred":[
        "Sierra Morena"
    ],
    "name:deu_x_preferred":[
        "Sierra Morena"
    ],
    "name:epo_x_preferred":[
        "Sierra Morena"
    ],
    "name:eus_x_preferred":[
        "Sierra Morena"
    ],
    "name:ext_x_preferred":[
        "Sierra Morena"
    ],
    "name:fas_x_preferred":[
        "\u0633\u06cc\u0631\u0627 \u0645\u0648\u0631\u0646\u0627"
    ],
    "name:fin_x_preferred":[
        "Sierra Morena"
    ],
    "name:fra_x_preferred":[
        "Sierra Morena"
    ],
    "name:glg_x_preferred":[
        "Serra Morena"
    ],
    "name:heb_x_preferred":[
        "\u05e8\u05db\u05e1 \u05e1\u05d9\u05d9\u05e8\u05d4 \u05de\u05d5\u05e8\u05e0\u05d4"
    ],
    "name:hin_x_preferred":[
        "\u0938\u093f\u090f\u0930\u094d\u0930\u093e \u092e\u094b\u0930\u0947\u0928\u093e"
    ],
    "name:hun_x_preferred":[
        "Sierra Morena"
    ],
    "name:ind_x_preferred":[
        "Sierra Morena"
    ],
    "name:ita_x_preferred":[
        "Sierra Morena"
    ],
    "name:jpn_x_preferred":[
        "\u30b7\u30a8\u30e9\u30fb\u30e2\u30ec\u30ca\u5c71\u8108"
    ],
    "name:kat_x_preferred":[
        "\u10e1\u10d8\u10d4\u10e0\u10d0-\u10db\u10dd\u10e0\u10d4\u10dc\u10d0"
    ],
    "name:kor_x_preferred":[
        "\uc2dc\uc5d0\ub77c \ubaa8\ub808\ub098"
    ],
    "name:lat_x_preferred":[
        "Mons Mariorum"
    ],
    "name:lit_x_preferred":[
        "Siera Morena"
    ],
    "name:nld_x_preferred":[
        "Sierra Morena"
    ],
    "name:nno_x_preferred":[
        "Sierra Morena"
    ],
    "name:nor_x_preferred":[
        "Sierra Morena"
    ],
    "name:pnb_x_preferred":[
        "\u0633\u06cc\u0631\u0627 \u0645\u0648\u0631\u06cc\u0646\u0627"
    ],
    "name:pol_x_preferred":[
        "Sierra Morena"
    ],
    "name:por_x_preferred":[
        "Serra Morena"
    ],
    "name:rus_x_preferred":[
        "\u0421\u044c\u0435\u0440\u0440\u0430-\u041c\u043e\u0440\u0435\u043d\u0430"
    ],
    "name:spa_x_preferred":[
        "Sierra Morena"
    ],
    "name:swe_x_preferred":[
        "Sierra Morena"
    ],
    "name:tur_x_preferred":[
        "Sierra Morena"
    ],
    "name:ukr_x_preferred":[
        "\u0421\u2019\u0454\u0440\u0440\u0430-\u041c\u043e\u0440\u0435\u043d\u0430"
    ],
    "name:urd_x_preferred":[
        "\u0633\u06cc\u0626\u0631\u0627 \u0645\u0648\u0631\u06cc\u0646\u0627"
    ],
    "name:vie_x_preferred":[
        "D\u00e3y Sierra Morena"
    ],
    "name:xmf_x_preferred":[
        "\u10e1\u10d8\u10d4\u10e0\u10d0-\u10db\u10dd\u10e0\u10d4\u10dc\u10d0"
    ],
    "name:zho_x_preferred":[
        "\u83ab\u96f7\u7d0d\u5c71\u8108"
    ],
    "wof:name":"Sierra Morena",
    "wof:placetype":"locality",
    "wof:population":10
},
  "geometry": {"coordinates":[-92.295,17.17278],"type":"Point"}
}