{
  "type": "Feature",
  "properties": {
    "gn:admin1_code":"16",
    "gn:admin2_code":"77.0",
    "gn:asciiname":"Buena Vista",
    "gn:country_code":"MX",
    "gn:dem":265,
    "gn:feature_class":"P",
    "gn:feature_code":"PPL",
    "gn:name":"Buena Vista",
    "gn:population":103,
    "gn:timezone":"America/Mexico_City",
    "iso:country":"MX",
    "wof:name":"Buena Vista",
    "wof:placetype":"locality",
    "wof:population":103
},
  "geometry": {"coordinates":[-100.60083,18.40472],"type":"Point"}
}