{
  "type": "Feature",
  "properties": {
    "gn:admin1_code":"10.0",
    "gn:admin2_code":"34.0",
    "gn:asciiname":"Mesa Blanca",
    "gn:country_code":"MX",
    "gn:dem":1730,
    "gn:feature_class":"P",
    "gn:feature_code":"PPL",
    "gn:name":"Mesa Blanca",
    "gn:population":0,
    "gn:timezone":"America/Monterrey",
    "iso:country":"MX",
    "name:spa_x_preferred":[
        "Mesa Blanca"
    ],
    "wof:name":"Mesa Blanca",
    "wof:placetype":"locality"
},
  "geometry": {"coordinates":[-106.6434,24.82791],"type":"Point"}
}