{
  "type": "Feature",
  "properties": {
    "gn:admin1_code":"20",
    "gn:admin2_code":"198",
    "gn:asciiname":"El Robalo",
    "gn:country_code":"MX",
    "gn:dem":108,
    "gn:feature_class":"P",
    "gn:feature_code":"PPL",
    "gn:name":"El Robalo",
    "gn:population":19,
    "gn:timezone":"America/Mexico_City",
    "iso:country":"MX",
    "wof:name":"El Robalo",
    "wof:placetype":"locality",
    "wof:population":19
},
  "geometry": {"coordinates":[-95.16556,17.16611],"type":"Point"}
}