{
  "type": "Feature",
  "properties": {
    "gn:admin1_code":"31",
    "gn:admin2_code":"102.0",
    "gn:asciiname":"San Juan Bubul",
    "gn:country_code":"MX",
    "gn:dem":23,
    "gn:feature_class":"P",
    "gn:feature_code":"PPL",
    "gn:name":"San Juan Bubul",
    "gn:population":7,
    "gn:timezone":"America/Merida",
    "iso:country":"MX",
    "wof:name":"San Juan Bubul",
    "wof:placetype":"locality",
    "wof:population":7
},
  "geometry": {"coordinates":[-88.23833,20.69722],"type":"Point"}
}