{
  "type": "Feature",
  "properties": {
    "gn:admin1_code":"10",
    "gn:admin2_code":"26.0",
    "gn:asciiname":"Charco Puerco",
    "gn:country_code":"MX",
    "gn:dem":2459,
    "gn:feature_class":"P",
    "gn:feature_code":"PPL",
    "gn:name":"Charco Puerco",
    "gn:population":0,
    "gn:timezone":"America/Monterrey",
    "iso:country":"MX",
    "name:spa_x_preferred":[
        "Charco Puerco"
    ],
    "wof:name":"Charco Puerco",
    "wof:placetype":"locality"
},
  "geometry": {"coordinates":[-105.73877,24.43054],"type":"Point"}
}