{
  "type": "Feature",
  "properties": {
    "gn:admin1_code":"14",
    "gn:admin2_code":"44.0",
    "gn:asciiname":"Pegaso [Gas]",
    "gn:country_code":"MX",
    "gn:dem":1546,
    "gn:feature_class":"P",
    "gn:feature_code":"PPL",
    "gn:name":"Pegaso [Gas]",
    "gn:population":6,
    "gn:timezone":"America/Mexico_City",
    "iso:country":"MX",
    "wof:name":"Pegaso [Gas]",
    "wof:placetype":"locality",
    "wof:population":6
},
  "geometry": {"coordinates":[-103.22889000000001,20.43889],"type":"Point"}
}