{
  "type": "Feature",
  "properties": {
    "gn:admin1_code":"16",
    "gn:admin2_code":"26",
    "gn:asciiname":"La Higuerita",
    "gn:country_code":"MX",
    "gn:dem":1650,
    "gn:feature_class":"P",
    "gn:feature_code":"PPL",
    "gn:name":"La Higuerita",
    "gn:population":11,
    "gn:timezone":"America/Mexico_City",
    "iso:country":"MX",
    "wof:name":"La Higuerita",
    "wof:placetype":"locality",
    "wof:population":11
},
  "geometry": {"coordinates":[-103.30833,18.66167],"type":"Point"}
}