{
  "type": "Feature",
  "properties": {
    "gn:admin1_code":"14",
    "gn:admin2_code":"117.0",
    "gn:asciiname":"Rincon de Guzman",
    "gn:country_code":"MX",
    "gn:dem":1689,
    "gn:feature_class":"P",
    "gn:feature_code":"PPL",
    "gn:name":"Rinc\u00f3n de Guzm\u00e1n",
    "gn:population":71,
    "gn:timezone":"America/Mexico_City",
    "iso:country":"MX",
    "wof:name":"Rincon de Guzman",
    "wof:placetype":"locality",
    "wof:population":71
},
  "geometry": {"coordinates":[-102.63437999999999,21.2455],"type":"Point"}
}