{
  "type": "Feature",
  "properties": {
    "gn:admin1_code":"24.0",
    "gn:admin2_code":"29.0",
    "gn:asciiname":"La Lajuela",
    "gn:country_code":"MX",
    "gn:dem":103,
    "gn:feature_class":"P",
    "gn:feature_code":"PPL",
    "gn:name":"La Lajuela",
    "gn:population":1,
    "gn:timezone":"America/Mexico_City",
    "iso:country":"MX",
    "name:spa_x_preferred":[
        "La Lajuela"
    ],
    "wof:name":"La Lajuela",
    "wof:placetype":"locality",
    "wof:population":1
},
  "geometry": {"coordinates":[-98.64278,21.51583],"type":"Point"}
}