{
  "type": "Feature",
  "properties": {
    "gn:admin1_code":"11",
    "gn:admin2_code":"23.0",
    "gn:asciiname":"Pino Solo",
    "gn:country_code":"MX",
    "gn:dem":1895,
    "gn:feature_class":"P",
    "gn:feature_code":"PPL",
    "gn:name":"Pino Solo",
    "gn:population":0,
    "gn:timezone":"America/Mexico_City",
    "iso:country":"MX",
    "name:spa_x_preferred":[
        "Pino Solo"
    ],
    "wof:name":"Pino Solo",
    "wof:placetype":"locality"
},
  "geometry": {"coordinates":[-101.99997999999999,20.5098],"type":"Point"}
}