{
  "type": "Feature",
  "properties": {
    "gn:admin1_code":"14",
    "gn:admin2_code":"117",
    "gn:asciiname":"El Palo de la Cruz",
    "gn:country_code":"MX",
    "gn:dem":1830,
    "gn:feature_class":"P",
    "gn:feature_code":"PPL",
    "gn:name":"El Palo de la Cruz",
    "gn:population":24,
    "gn:timezone":"America/Mexico_City",
    "iso:country":"MX",
    "wof:name":"El Palo de la Cruz",
    "wof:placetype":"locality",
    "wof:population":24
},
  "geometry": {"coordinates":[-102.63278,21.12639],"type":"Point"}
}