{
  "type": "Feature",
  "properties": {
    "gn:admin1_code":"26.0",
    "gn:admin2_code":"21.0",
    "gn:asciiname":"Chivato",
    "gn:country_code":"MX",
    "gn:dem":348,
    "gn:feature_class":"P",
    "gn:feature_code":"PPL",
    "gn:name":"Chivato",
    "gn:population":0,
    "gn:timezone":"America/Hermosillo",
    "iso:country":"MX",
    "wof:name":"Chivato",
    "wof:placetype":"locality"
},
  "geometry": {"coordinates":[-110.59999999999999,28.75],"type":"Point"}
}