{
  "type": "Feature",
  "properties": {
    "gn:admin1_code":"6.0",
    "gn:admin2_code":"46.0",
    "gn:asciiname":"La Mata de Chile",
    "gn:country_code":"MX",
    "gn:dem":906,
    "gn:feature_class":"P",
    "gn:feature_code":"PPL",
    "gn:name":"La Mata de Chile",
    "gn:population":0,
    "gn:timezone":"America/Chihuahua",
    "iso:country":"MX",
    "name:spa_x_preferred":[
        "La Mata de Chile"
    ],
    "wof:name":"La Mata de Chile",
    "wof:placetype":"locality"
},
  "geometry": {"coordinates":[-107.57281,26.6078],"type":"Point"}
}