{
  "type": "Feature",
  "properties": {
    "gn:admin1_code":"30",
    "gn:admin2_code":"117.0",
    "gn:asciiname":"Atolka",
    "gn:country_code":"MX",
    "gn:dem":1275,
    "gn:feature_class":"P",
    "gn:feature_code":"PPL",
    "gn:name":"Atolka",
    "gn:population":164,
    "gn:timezone":"America/Mexico_City",
    "iso:country":"MX",
    "wof:name":"Atolka",
    "wof:placetype":"locality",
    "wof:population":164
},
  "geometry": {"coordinates":[-96.89917,18.76333],"type":"Point"}
}