{
  "type": "Feature",
  "properties": {
    "gn:admin1_code":"15.0",
    "gn:asciiname":"Paso del Cascalote",
    "gn:country_code":"MX",
    "gn:dem":451,
    "gn:feature_class":"P",
    "gn:feature_code":"PPL",
    "gn:name":"Paso del Cascalote",
    "gn:population":0,
    "gn:timezone":"America/Mexico_City",
    "iso:country":"MX",
    "name:spa_x_preferred":[
        "Paso del Cascalote"
    ],
    "wof:name":"Paso del Cascalote",
    "wof:placetype":"locality"
},
  "geometry": {"coordinates":[-100.47098,18.55165],"type":"Point"}
}