{
  "type": "Feature",
  "properties": {
    "gn:admin1_code":"5",
    "gn:admin2_code":"40.0",
    "gn:asciiname":"El Manacal",
    "gn:country_code":"MX",
    "gn:dem":613,
    "gn:feature_class":"P",
    "gn:feature_code":"PPL",
    "gn:name":"El Manacal",
    "gn:population":66,
    "gn:timezone":"America/Mexico_City",
    "iso:country":"MX",
    "wof:name":"El Manacal",
    "wof:placetype":"locality",
    "wof:population":66
},
  "geometry": {"coordinates":[-92.49889,15.21389],"type":"Point"}
}