{
  "type": "Feature",
  "properties": {
    "gn:admin1_code":"17.0",
    "gn:asciiname":"Lago San Nicolas",
    "gn:country_code":"MX",
    "gn:dem":2584,
    "gn:feature_class":"P",
    "gn:feature_code":"PPL",
    "gn:name":"Lago San Nicol\u00e1s",
    "gn:population":0,
    "gn:timezone":"America/Mexico_City",
    "iso:country":"MX",
    "name:spa_x_preferred":[
        "Lago San Nicol\u00e1s"
    ],
    "wof:name":"Lago San Nicolas",
    "wof:placetype":"locality"
},
  "geometry": {"coordinates":[-99.5729,19.359],"type":"Point"}
}