{
  "type": "Feature",
  "properties": {
    "gn:admin1_code":"8.0",
    "gn:admin2_code":"4.0",
    "gn:asciiname":"Piedras Gordas",
    "gn:country_code":"MX",
    "gn:dem":782,
    "gn:feature_class":"P",
    "gn:feature_code":"PPL",
    "gn:name":"Piedras Gordas",
    "gn:population":0,
    "gn:timezone":"America/Mexico_City",
    "iso:country":"MX",
    "name:ita_x_preferred":[
        "Piedras Gordas"
    ],
    "name:spa_x_preferred":[
        "Piedras Gordas"
    ],
    "name:zho_x_preferred":[
        "\u5f7c\u5fb7\u62c9\u65af\u6208\u723e\u9054\u65af"
    ],
    "wof:name":"Piedras Gordas",
    "wof:placetype":"locality"
},
  "geometry": {"coordinates":[-104.04082,19.15299],"type":"Point"}
}