{
  "type": "Feature",
  "properties": {
    "gn:admin1_code":"21",
    "gn:admin2_code":"86.0",
    "gn:asciiname":"El Otate",
    "gn:country_code":"MX",
    "gn:dem":414,
    "gn:feature_class":"P",
    "gn:feature_code":"PPL",
    "gn:name":"El Otate",
    "gn:population":9,
    "gn:timezone":"America/Mexico_City",
    "iso:country":"MX",
    "wof:name":"El Otate",
    "wof:placetype":"locality",
    "wof:population":9
},
  "geometry": {"coordinates":[-97.91583,20.48417],"type":"Point"}
}