{
  "type": "Feature",
  "properties": {
    "gn:admin1_code":"10",
    "gn:admin2_code":"34.0",
    "gn:asciiname":"Quenibas",
    "gn:cc2":"MX",
    "gn:country_code":"MX",
    "gn:dem":479,
    "gn:feature_class":"P",
    "gn:feature_code":"PPL",
    "gn:name":"Quenibas",
    "gn:population":64,
    "gn:timezone":"America/Monterrey",
    "iso:country":"MX",
    "name:und_x_variant":[
        "Quenivas"
    ],
    "wof:name":"Quenibas",
    "wof:placetype":"locality",
    "wof:population":64
},
  "geometry": {"coordinates":[-106.35366999999999,24.64776],"type":"Point"}
}