{
  "type": "Feature",
  "properties": {
    "gn:admin1_code":"6",
    "gn:admin2_code":"65.0",
    "gn:asciiname":"Segorachic",
    "gn:country_code":"MX",
    "gn:dem":1378,
    "gn:feature_class":"P",
    "gn:feature_code":"PPL",
    "gn:name":"Segorachic",
    "gn:population":0,
    "gn:timezone":"America/Chihuahua",
    "iso:country":"MX",
    "name:spa_x_preferred":[
        "Segorachic"
    ],
    "wof:name":"Segorachic",
    "wof:placetype":"locality"
},
  "geometry": {"coordinates":[-108.22433999999998,27.18643],"type":"Point"}
}