{
  "type": "Feature",
  "properties": {
    "gn:admin1_code":"1",
    "gn:admin2_code":"7.0",
    "gn:asciiname":"Rancho de los de Anda",
    "gn:country_code":"MX",
    "gn:dem":1940,
    "gn:feature_class":"P",
    "gn:feature_code":"PPL",
    "gn:name":"Rancho de los de Anda",
    "gn:population":6,
    "gn:timezone":"America/Mexico_City",
    "iso:country":"MX",
    "wof:name":"Rancho de los de Anda",
    "wof:placetype":"locality",
    "wof:population":6
},
  "geometry": {"coordinates":[-102.21056,22.3225],"type":"Point"}
}