{
  "type": "Feature",
  "properties": {
    "gn:admin1_code":"27",
    "gn:admin2_code":"2.0",
    "gn:asciiname":"Encrucijada Tercera Seccion",
    "gn:country_code":"MX",
    "gn:dem":7,
    "gn:feature_class":"P",
    "gn:feature_code":"PPL",
    "gn:name":"Encrucijada Tercera Secci\u00f3n",
    "gn:population":0,
    "gn:timezone":"America/Mexico_City",
    "iso:country":"MX",
    "name:spa_x_preferred":[
        "La Encrucijada Tercera Secci\u00f3n"
    ],
    "name:spa_x_variant":[
        "Encrucijada Tercera Secci\u00f3n",
        "Calzada"
    ],
    "wof:name":"Encrucijada Tercera Seccion",
    "wof:placetype":"locality"
},
  "geometry": {"coordinates":[-93.55174,18.2452],"type":"Point"}
}