{
  "type": "Feature",
  "properties": {
    "gn:admin1_code":"29",
    "gn:admin2_code":"15.0",
    "gn:asciiname":"Las Huertas",
    "gn:country_code":"MX",
    "gn:dem":2407,
    "gn:feature_class":"P",
    "gn:feature_code":"PPL",
    "gn:name":"Las Huertas",
    "gn:population":6,
    "gn:timezone":"America/Mexico_City",
    "iso:country":"MX",
    "wof:name":"Las Huertas",
    "wof:placetype":"locality",
    "wof:population":6
},
  "geometry": {"coordinates":[-98.44761,19.3816],"type":"Point"}
}