{
  "type": "Feature",
  "properties": {
    "gn:admin1_code":"4",
    "gn:admin2_code":"10.0",
    "gn:asciiname":"Once de Mayo",
    "gn:country_code":"MX",
    "gn:dem":259,
    "gn:feature_class":"P",
    "gn:feature_code":"PPL",
    "gn:name":"Once de Mayo",
    "gn:population":350,
    "gn:timezone":"America/Merida",
    "iso:country":"MX",
    "wof:name":"Once de Mayo",
    "wof:placetype":"locality",
    "wof:population":350
},
  "geometry": {"coordinates":[-89.46083,18.09111],"type":"Point"}
}