{
  "type": "Feature",
  "properties": {
    "gn:admin1_code":"30",
    "gn:admin2_code":"210.0",
    "gn:asciiname":"Francisco Villa Dos",
    "gn:country_code":"MX",
    "gn:dem":84,
    "gn:feature_class":"P",
    "gn:feature_code":"PPL",
    "gn:name":"Francisco Villa Dos",
    "gn:population":105,
    "gn:timezone":"America/Mexico_City",
    "iso:country":"MX",
    "wof:name":"Francisco Villa Dos",
    "wof:placetype":"locality",
    "wof:population":105
},
  "geometry": {"coordinates":[-94.55611,17.22472],"type":"Point"}
}