{
  "type": "Feature",
  "properties": {
    "gn:admin1_code":"24",
    "gn:admin2_code":"15.0",
    "gn:asciiname":"Pocitos",
    "gn:country_code":"MX",
    "gn:dem":1986,
    "gn:feature_class":"P",
    "gn:feature_code":"PPL",
    "gn:name":"Pocitos",
    "gn:population":341,
    "gn:timezone":"America/Mexico_City",
    "iso:country":"MX",
    "wof:name":"Pocitos",
    "wof:placetype":"locality",
    "wof:population":341
},
  "geometry": {"coordinates":[-100.97787,23.18649],"type":"Point"}
}