{
  "type": "Feature",
  "properties": {
    "gn:admin1_code":"28.0",
    "gn:admin2_code":"10.0",
    "gn:asciiname":"La Sierrita",
    "gn:country_code":"MX",
    "gn:dem":395,
    "gn:feature_class":"P",
    "gn:feature_code":"PPL",
    "gn:name":"La Sierrita",
    "gn:population":0,
    "gn:timezone":"America/Monterrey",
    "iso:country":"MX",
    "name:spa_x_preferred":[
        "La Sierrita"
    ],
    "wof:name":"La Sierrita",
    "wof:placetype":"locality"
},
  "geometry": {"coordinates":[-98.60702999999999,24.47916],"type":"Point"}
}