{
  "type": "Feature",
  "properties": {
    "gn:admin1_code":"3",
    "gn:admin2_code":"2.0",
    "gn:asciiname":"El Batequi",
    "gn:country_code":"MX",
    "gn:dem":414,
    "gn:feature_class":"P",
    "gn:feature_code":"PPL",
    "gn:name":"El Batequi",
    "gn:population":4,
    "gn:timezone":"America/Mazatlan",
    "iso:country":"MX",
    "wof:name":"El Batequi",
    "wof:placetype":"locality",
    "wof:population":4
},
  "geometry": {"coordinates":[-113.07123,27.46451],"type":"Point"}
}