{
  "type": "Feature",
  "properties": {
    "gn:admin1_code":"6",
    "gn:admin2_code":"9",
    "gn:asciiname":"Rancho Green",
    "gn:country_code":"MX",
    "gn:dem":2408,
    "gn:feature_class":"P",
    "gn:feature_code":"PPL",
    "gn:name":"Rancho Green",
    "gn:population":12,
    "gn:timezone":"America/Chihuahua",
    "iso:country":"MX",
    "wof:name":"Rancho Green",
    "wof:placetype":"locality",
    "wof:population":12
},
  "geometry": {"coordinates":[-107.5775,28.00556],"type":"Point"}
}