{
  "type": "Feature",
  "properties": {
    "gn:admin1_code":"6.0",
    "gn:admin2_code":"19.0",
    "gn:asciiname":"Los Nogales",
    "gn:country_code":"MX",
    "gn:dem":1482,
    "gn:feature_class":"P",
    "gn:feature_code":"PPL",
    "gn:name":"Los Nogales",
    "gn:population":0,
    "gn:timezone":"America/Chihuahua",
    "iso:country":"MX",
    "name:und_x_variant":[
        "Rancho Agua Nueva",
        "Los Nogales",
        "Agua Nueva"
    ],
    "wof:name":"Los Nogales",
    "wof:placetype":"locality"
},
  "geometry": {"coordinates":[-106.20856000000001,29.67156],"type":"Point"}
}