{
  "type": "Feature",
  "properties": {
    "gn:admin1_code":"30",
    "gn:admin2_code":"124",
    "gn:asciiname":"Jose Santiago Pacheco",
    "gn:country_code":"MX",
    "gn:dem":55,
    "gn:feature_class":"P",
    "gn:feature_code":"PPL",
    "gn:name":"Jos\u00e9 Santiago Pacheco",
    "gn:population":33,
    "gn:timezone":"America/Mexico_City",
    "iso:country":"MX",
    "name:und_x_variant":[
        "Jos\u00e9 Santiago Pacheco"
    ],
    "wof:name":"Jose Santiago Pacheco",
    "wof:placetype":"locality",
    "wof:population":33
},
  "geometry": {"coordinates":[-97.20389,20.56472],"type":"Point"}
}