{
  "type": "Feature",
  "properties": {
    "gn:admin1_code":"14",
    "gn:admin2_code":"78",
    "gn:asciiname":"Las Presitas",
    "gn:country_code":"MX",
    "gn:dem":2015,
    "gn:feature_class":"P",
    "gn:feature_code":"PPL",
    "gn:name":"Las Presitas",
    "gn:population":13,
    "gn:timezone":"America/Mexico_City",
    "iso:country":"MX",
    "wof:name":"Las Presitas",
    "wof:placetype":"locality",
    "wof:population":13
},
  "geometry": {"coordinates":[-102.42694,20.92639],"type":"Point"}
}