{
  "type": "Feature",
  "properties": {
    "gn:admin1_code":"11",
    "gn:admin2_code":"27.0",
    "gn:asciiname":"San Antonio Capetillo",
    "gn:country_code":"MX",
    "gn:dem":1724,
    "gn:feature_class":"P",
    "gn:feature_code":"PPL",
    "gn:name":"San Antonio Capetillo",
    "gn:population":111,
    "gn:timezone":"America/Mexico_City",
    "iso:country":"MX",
    "wof:name":"San Antonio Capetillo",
    "wof:placetype":"locality",
    "wof:population":111
},
  "geometry": {"coordinates":[-101.14221999999999,20.63389],"type":"Point"}
}