{
  "type": "Feature",
  "properties": {
    "gn:admin1_code":"5",
    "gn:admin2_code":"108",
    "gn:asciiname":"Los Tulipanes",
    "gn:country_code":"MX",
    "gn:dem":668,
    "gn:feature_class":"P",
    "gn:feature_code":"PPL",
    "gn:name":"Los Tulipanes",
    "gn:population":10,
    "gn:timezone":"America/Mexico_City",
    "iso:country":"MX",
    "wof:name":"Los Tulipanes",
    "wof:placetype":"locality",
    "wof:population":10
},
  "geometry": {"coordinates":[-93.36472000000001,16.29444],"type":"Point"}
}