{
  "type": "Feature",
  "properties": {
    "gn:admin1_code":"30",
    "gn:admin2_code":"121.0",
    "gn:asciiname":"Santo Tomas",
    "gn:country_code":"MX",
    "gn:dem":35,
    "gn:feature_class":"P",
    "gn:feature_code":"PPL",
    "gn:name":"Santo Tom\u00e1s",
    "gn:population":6,
    "gn:timezone":"America/Mexico_City",
    "iso:country":"MX",
    "name:und_x_variant":[
        "Santo Tom\u00e1s"
    ],
    "wof:name":"Santo Tomas",
    "wof:placetype":"locality",
    "wof:population":6
},
  "geometry": {"coordinates":[-97.91943999999999,21.91111],"type":"Point"}
}