{
  "type": "Feature",
  "properties": {
    "gn:admin1_code":"26.0",
    "gn:admin2_code":"67.0",
    "gn:asciiname":"La Valenzuela",
    "gn:country_code":"MX",
    "gn:dem":1005,
    "gn:feature_class":"P",
    "gn:feature_code":"PPL",
    "gn:name":"La Valenzuela",
    "gn:population":0,
    "gn:timezone":"America/Hermosillo",
    "iso:country":"MX",
    "name:spa_x_preferred":[
        "La Valenzuela"
    ],
    "wof:name":"La Valenzuela",
    "wof:placetype":"locality"
},
  "geometry": {"coordinates":[-109.29056,30.34417],"type":"Point"}
}