{
  "type": "Feature",
  "properties": {
    "gn:admin1_code":"7",
    "gn:admin2_code":"11.0",
    "gn:asciiname":"Heredita",
    "gn:country_code":"MX",
    "gn:dem":1199,
    "gn:feature_class":"P",
    "gn:feature_code":"PPL",
    "gn:name":"Heredita",
    "gn:population":0,
    "gn:timezone":"America/Monterrey",
    "iso:country":"MX",
    "name:spa_x_preferred":[
        "Heredita"
    ],
    "name:spa_x_variant":[
        "Hedionda de los Morales"
    ],
    "wof:name":"Heredita",
    "wof:placetype":"locality"
},
  "geometry": {"coordinates":[-101.40227,25.55079],"type":"Point"}
}