{
  "type": "Feature",
  "properties": {
    "gn:admin1_code":"16",
    "gn:admin2_code":"52",
    "gn:asciiname":"El Rio de Nexpa",
    "gn:country_code":"MX",
    "gn:dem":11,
    "gn:feature_class":"P",
    "gn:feature_code":"PPL",
    "gn:name":"El R\u00edo de Nexpa",
    "gn:population":18,
    "gn:timezone":"America/Mexico_City",
    "iso:country":"MX",
    "name:und_x_variant":[
        "El R\u00edo de Nexpa"
    ],
    "wof:name":"El Rio de Nexpa",
    "wof:placetype":"locality",
    "wof:population":18
},
  "geometry": {"coordinates":[-102.78861000000001,18.09583],"type":"Point"}
}