{
  "type": "Feature",
  "properties": {
    "gn:admin1_code":"5",
    "gn:admin2_code":"57.0",
    "gn:asciiname":"El Injerto",
    "gn:country_code":"MX",
    "gn:dem":1055,
    "gn:feature_class":"P",
    "gn:feature_code":"PPL",
    "gn:name":"El Injerto",
    "gn:population":63,
    "gn:timezone":"America/Mexico_City",
    "iso:country":"MX",
    "wof:name":"El Injerto",
    "wof:placetype":"locality",
    "wof:population":63
},
  "geometry": {"coordinates":[-92.35666999999999,15.29],"type":"Point"}
}