{
  "type": "Feature",
  "properties": {
    "gn:admin1_code":"10",
    "gn:admin2_code":"9.0",
    "gn:asciiname":"El Saltito",
    "gn:country_code":"MX",
    "gn:dem":2784,
    "gn:feature_class":"P",
    "gn:feature_code":"PPL",
    "gn:name":"El Saltito",
    "gn:population":0,
    "gn:timezone":"America/Monterrey",
    "iso:country":"MX",
    "name:spa_x_preferred":[
        "El Saltito"
    ],
    "wof:name":"El Saltito",
    "wof:placetype":"locality"
},
  "geometry": {"coordinates":[-106.2561,26.04291],"type":"Point"}
}