{
  "type": "Feature",
  "properties": {
    "gn:admin1_code":"24",
    "gn:admin2_code":"56.0",
    "gn:asciiname":"Pelotera",
    "gn:country_code":"MX",
    "gn:dem":1622,
    "gn:feature_class":"P",
    "gn:feature_code":"PPL",
    "gn:name":"Pelotera",
    "gn:population":0,
    "gn:timezone":"America/Mexico_City",
    "iso:country":"MX",
    "name:und_x_variant":[
        "Pelotero",
        "Pelotera"
    ],
    "wof:name":"Pelotera",
    "wof:placetype":"locality"
},
  "geometry": {"coordinates":[-100.88256,22.6458],"type":"Point"}
}