{
  "type": "Feature",
  "properties": {
    "gn:admin1_code":"13",
    "gn:admin2_code":"55.0",
    "gn:asciiname":"Hermosillo",
    "gn:country_code":"MX",
    "gn:dem":2083,
    "gn:feature_class":"P",
    "gn:feature_code":"PPL",
    "gn:name":"Hermosillo",
    "gn:population":0,
    "gn:timezone":"America/Mexico_City",
    "iso:country":"MX",
    "name:spa_x_preferred":[
        "Hermosillo"
    ],
    "wof:name":"Hermosillo",
    "wof:placetype":"locality"
},
  "geometry": {"coordinates":[-98.94833,20.4141],"type":"Point"}
}