{
  "type": "Feature",
  "properties": {
    "gn:admin1_code":"18",
    "gn:admin2_code":"9.0",
    "gn:asciiname":"Gabino Severiano",
    "gn:country_code":"MX",
    "gn:dem":1269,
    "gn:feature_class":"P",
    "gn:feature_code":"PPL",
    "gn:name":"Gabino Severiano",
    "gn:population":8,
    "gn:timezone":"America/Mazatlan",
    "iso:country":"MX",
    "wof:name":"Gabino Severiano",
    "wof:placetype":"locality",
    "wof:population":8
},
  "geometry": {"coordinates":[-104.66333,22.03472],"type":"Point"}
}