{
  "type": "Feature",
  "properties": {
    "gn:admin1_code":"25",
    "gn:admin2_code":"7.0",
    "gn:asciiname":"La Higuerita",
    "gn:country_code":"MX",
    "gn:dem":1021,
    "gn:feature_class":"P",
    "gn:feature_code":"PPL",
    "gn:name":"La Higuerita",
    "gn:population":8,
    "gn:timezone":"America/Mazatlan",
    "iso:country":"MX",
    "wof:name":"La Higuerita",
    "wof:placetype":"locality",
    "wof:population":8
},
  "geometry": {"coordinates":[-108.05656,26.51911],"type":"Point"}
}