{
  "type": "Feature",
  "properties": {
    "gn:admin1_code":"13",
    "gn:admin2_code":"43.0",
    "gn:asciiname":"Las Pilas",
    "gn:country_code":"MX",
    "gn:dem":1726,
    "gn:feature_class":"P",
    "gn:feature_code":"PPL",
    "gn:name":"Las Pilas",
    "gn:population":110,
    "gn:timezone":"America/Mexico_City",
    "iso:country":"MX",
    "name:fra_x_preferred":[
        "Las Pilas"
    ],
    "name:lit_x_preferred":[
        "Las Pilasas"
    ],
    "name:nld_x_preferred":[
        "Las Pilas"
    ],
    "name:rus_x_preferred":[
        "\u041b\u0430\u0441-\u041f\u0438\u043b\u0430\u0441"
    ],
    "name:slk_x_preferred":[
        "Las Pilas"
    ],
    "wof:name":"Las Pilas",
    "wof:placetype":"locality",
    "wof:population":110
},
  "geometry": {"coordinates":[-99.17194000000001,20.82528],"type":"Point"}
}