{
  "type": "Feature",
  "properties": {
    "gn:admin1_code":"20",
    "gn:admin2_code":"427.0",
    "gn:asciiname":"Llano Suchiapa",
    "gn:country_code":"MX",
    "gn:dem":227,
    "gn:feature_class":"P",
    "gn:feature_code":"PPL",
    "gn:name":"Llano Suchiapa",
    "gn:population":2465,
    "gn:timezone":"America/Mexico_City",
    "iso:country":"MX",
    "wof:name":"Llano Suchiapa",
    "wof:placetype":"locality",
    "wof:population":2465
},
  "geometry": {"coordinates":[-95.05389,16.86611],"type":"Point"}
}