{
  "type": "Feature",
  "properties": {
    "gn:admin1_code":"13",
    "gn:admin2_code":"71.0",
    "gn:asciiname":"Boca de Leon",
    "gn:country_code":"MX",
    "gn:dem":476,
    "gn:feature_class":"P",
    "gn:feature_code":"PPL",
    "gn:name":"Boca de Le\u00f3n",
    "gn:population":0,
    "gn:timezone":"America/Mexico_City",
    "iso:country":"MX",
    "name:spa_x_preferred":[
        "Boca de Le\u00f3n"
    ],
    "wof:name":"Boca de Leon",
    "wof:placetype":"locality"
},
  "geometry": {"coordinates":[-98.99563999999999,20.99069],"type":"Point"}
}