{
  "type": "Feature",
  "properties": {
    "gn:admin1_code":"10",
    "gn:admin2_code":"4.0",
    "gn:asciiname":"El Rayo",
    "gn:country_code":"MX",
    "gn:dem":2204,
    "gn:feature_class":"P",
    "gn:feature_code":"PPL",
    "gn:name":"El Rayo",
    "gn:population":0,
    "gn:timezone":"America/Monterrey",
    "iso:country":"MX",
    "name:spa_x_preferred":[
        "El Rayo"
    ],
    "wof:name":"El Rayo",
    "wof:placetype":"locality"
},
  "geometry": {"coordinates":[-103.85241000000001,24.29869],"type":"Point"}
}