{
  "type": "Feature",
  "properties": {
    "gn:admin1_code":"19",
    "gn:admin2_code":"3.0",
    "gn:asciiname":"La Sandia",
    "gn:country_code":"MX",
    "gn:dem":146,
    "gn:feature_class":"P",
    "gn:feature_code":"PPL",
    "gn:name":"La Sand\u00eda",
    "gn:population":18,
    "gn:timezone":"America/Monterrey",
    "iso:country":"MX",
    "name:spa_x_preferred":[
        "La Sand\u00eda"
    ],
    "wof:name":"La Sandia",
    "wof:placetype":"locality",
    "wof:population":18
},
  "geometry": {"coordinates":[-99.32218,25.98008],"type":"Point"}
}