{
  "type": "Feature",
  "properties": {
    "gn:admin1_code":"28",
    "gn:admin2_code":"15.0",
    "gn:asciiname":"Valadeces",
    "gn:country_code":"MX",
    "gn:dem":48,
    "gn:feature_class":"P",
    "gn:feature_code":"PPL",
    "gn:name":"Valadeces",
    "gn:population":0,
    "gn:timezone":"America/Monterrey",
    "iso:country":"MX",
    "name:und_x_variant":[
        "Valadeces Chico",
        "Valadeces"
    ],
    "wof:name":"Valadeces",
    "wof:placetype":"locality"
},
  "geometry": {"coordinates":[-98.67726,26.23176],"type":"Point"}
}