{
  "type": "Feature",
  "properties": {
    "gn:admin1_code":"7",
    "gn:admin2_code":"36.0",
    "gn:asciiname":"Las Mieleras",
    "gn:country_code":"MX",
    "gn:dem":1143,
    "gn:feature_class":"P",
    "gn:feature_code":"PPL",
    "gn:name":"Las Mieleras",
    "gn:population":0,
    "gn:timezone":"America/Monterrey",
    "iso:country":"MX",
    "name:spa_x_preferred":[
        "Las Mieleras"
    ],
    "name:und_x_variant":[
        "Mielera",
        "Mieleras"
    ],
    "wof:name":"Las Mieleras",
    "wof:placetype":"locality"
},
  "geometry": {"coordinates":[-103.26739999999999,25.39948],"type":"Point"}
}