{
  "type": "Feature",
  "properties": {
    "gn:admin1_code":"7",
    "gn:admin2_code":"35.0",
    "gn:asciiname":"El Pozo de Calvo",
    "gn:country_code":"MX",
    "gn:dem":1481,
    "gn:feature_class":"P",
    "gn:feature_code":"PPL",
    "gn:name":"El Pozo de Calvo",
    "gn:population":0,
    "gn:timezone":"America/Monterrey",
    "iso:country":"MX",
    "name:spa_x_preferred":[
        "El Pozo de Calvo"
    ],
    "name:und_x_variant":[
        "Pozo Calvo",
        "Pozo Chico",
        "Pozo del Calvo",
        "Pozo de Calvo"
    ],
    "wof:name":"El Pozo de Calvo",
    "wof:placetype":"locality"
},
  "geometry": {"coordinates":[-103.1015,25.07662],"type":"Point"}
}