{
  "type": "Feature",
  "properties": {
    "gn:admin1_code":"14",
    "gn:admin2_code":"83.0",
    "gn:asciiname":"Los Naranjos",
    "gn:cc2":"MX",
    "gn:country_code":"MX",
    "gn:dem":1511,
    "gn:feature_class":"P",
    "gn:feature_code":"PPL",
    "gn:name":"Los Naranjos",
    "gn:population":0,
    "gn:timezone":"America/Mexico_City",
    "iso:country":"MX",
    "name:und_x_variant":[
        "Naranjos",
        "Los Naranjos"
    ],
    "wof:name":"Los Naranjos",
    "wof:placetype":"locality"
},
  "geometry": {"coordinates":[-103.68333,20.53333],"type":"Point"}
}