{
  "type": "Feature",
  "properties": {
    "gn:admin1_code":"14.0",
    "gn:admin2_code":"35.0",
    "gn:asciiname":"Las Majadas",
    "gn:country_code":"MX",
    "gn:dem":1925,
    "gn:feature_class":"P",
    "gn:feature_code":"PPL",
    "gn:name":"Las Majadas",
    "gn:population":0,
    "gn:timezone":"America/Mexico_City",
    "iso:country":"MX",
    "name:spa_x_preferred":[
        "Las Majadas"
    ],
    "wof:name":"Las Majadas",
    "wof:placetype":"locality"
},
  "geometry": {"coordinates":[-102.09681999999999,21.64892],"type":"Point"}
}