{
  "type": "Feature",
  "properties": {
    "gn:admin1_code":"6",
    "gn:admin2_code":"40",
    "gn:asciiname":"Cienega del Oso (El Coyote)",
    "gn:country_code":"MX",
    "gn:dem":2256,
    "gn:feature_class":"P",
    "gn:feature_code":"PPL",
    "gn:name":"Ci\u00e9nega del Oso (El Coyote)",
    "gn:population":25,
    "gn:timezone":"America/Chihuahua",
    "iso:country":"MX",
    "name:und_x_variant":[
        "Ci\u00e9nega del Oso (El Coyote)"
    ],
    "wof:name":"Cienega del Oso (El Coyote)",
    "wof:placetype":"locality",
    "wof:population":25
},
  "geometry": {"coordinates":[-108.25302000000001,28.87552],"type":"Point"}
}