{
  "type": "Feature",
  "properties": {
    "gn:admin1_code":"12.0",
    "gn:admin2_code":"38.0",
    "gn:asciiname":"El Abrojal",
    "gn:country_code":"MX",
    "gn:dem":245,
    "gn:feature_class":"P",
    "gn:feature_code":"PPL",
    "gn:name":"El Abrojal",
    "gn:population":4,
    "gn:timezone":"America/Mexico_City",
    "iso:country":"MX",
    "wof:name":"El Abrojal",
    "wof:placetype":"locality",
    "wof:population":4
},
  "geometry": {"coordinates":[-101.57742,17.82894],"type":"Point"}
}