{
  "type": "Feature",
  "properties": {
    "gn:admin1_code":"5",
    "gn:admin2_code":"54.0",
    "gn:asciiname":"Dorados de Villa",
    "gn:country_code":"MX",
    "gn:dem":12,
    "gn:feature_class":"P",
    "gn:feature_code":"PPL",
    "gn:name":"Dorados de Villa",
    "gn:population":177,
    "gn:timezone":"America/Mexico_City",
    "iso:country":"MX",
    "wof:name":"Dorados de Villa",
    "wof:placetype":"locality",
    "wof:population":177
},
  "geometry": {"coordinates":[-92.42966,14.79001],"type":"Point"}
}