{
  "type": "Feature",
  "properties": {
    "gn:admin1_code":"5",
    "gn:admin2_code":"61.0",
    "gn:asciiname":"El Herradero",
    "gn:country_code":"MX",
    "gn:dem":929,
    "gn:feature_class":"P",
    "gn:feature_code":"PPL",
    "gn:name":"El Herradero",
    "gn:population":5,
    "gn:timezone":"America/Mexico_City",
    "iso:country":"MX",
    "wof:name":"El Herradero",
    "wof:placetype":"locality",
    "wof:population":5
},
  "geometry": {"coordinates":[-93.325,16.70277999999999],"type":"Point"}
}