{
  "type": "Feature",
  "properties": {
    "gn:admin1_code":"3",
    "gn:admin2_code":"3",
    "gn:asciiname":"Ninguno [COPLAMAR]",
    "gn:country_code":"MX",
    "gn:dem":60,
    "gn:feature_class":"P",
    "gn:feature_code":"PPL",
    "gn:name":"Ninguno [COPLAMAR]",
    "gn:population":12,
    "gn:timezone":"America/Mazatlan",
    "iso:country":"MX",
    "wof:name":"Ninguno [COPLAMAR]",
    "wof:placetype":"locality",
    "wof:population":12
},
  "geometry": {"coordinates":[-110.214,23.46971],"type":"Point"}
}