{
  "type": "Feature",
  "properties": {
    "gn:admin1_code":"20",
    "gn:admin2_code":"482.0",
    "gn:asciiname":"Celestino Acevedo",
    "gn:country_code":"MX",
    "gn:dem":7,
    "gn:feature_class":"P",
    "gn:feature_code":"PPL",
    "gn:name":"Celestino Acevedo",
    "gn:population":6,
    "gn:timezone":"America/Mexico_City",
    "iso:country":"MX",
    "wof:name":"Celestino Acevedo",
    "wof:placetype":"locality",
    "wof:population":6
},
  "geometry": {"coordinates":[-98.04056,16.16],"type":"Point"}
}