{
  "type": "Feature",
  "properties": {
    "gn:admin1_code":"14",
    "gn:admin2_code":"78.0",
    "gn:asciiname":"San Jorge",
    "gn:country_code":"MX",
    "gn:dem":2103,
    "gn:feature_class":"P",
    "gn:feature_code":"PPL",
    "gn:name":"San Jorge",
    "gn:population":130,
    "gn:timezone":"America/Mexico_City",
    "iso:country":"MX",
    "wof:name":"San Jorge",
    "wof:placetype":"locality",
    "wof:population":130
},
  "geometry": {"coordinates":[-102.41667,20.93917],"type":"Point"}
}