{
  "type": "Feature",
  "properties": {
    "gn:admin1_code":"2",
    "gn:admin2_code":"4",
    "gn:asciiname":"Villa Corona",
    "gn:country_code":"MX",
    "gn:dem":172,
    "gn:feature_class":"P",
    "gn:feature_code":"PPL",
    "gn:name":"Villa Corona",
    "gn:population":10,
    "gn:timezone":"America/Tijuana",
    "iso:country":"MX",
    "name:ceb_x_preferred":[
        "Villa Corona"
    ],
    "name:deu_x_preferred":[
        "Municipio Villa Corona"
    ],
    "name:epo_x_preferred":[
        "Villa Corona"
    ],
    "name:eus_x_preferred":[
        "Villa Corona"
    ],
    "name:fra_x_preferred":[
        "Villa Corona"
    ],
    "name:ita_x_preferred":[
        "Villa Corona"
    ],
    "name:por_x_preferred":[
        "Villa Corona"
    ],
    "name:spa_x_preferred":[
        "Villa Corona"
    ],
    "name:srp_x_preferred":[
        "\u041e\u043f\u0448\u0442\u0438\u043d\u0430 \u0412\u0438\u0459\u0430 \u041a\u043e\u0440\u043e\u043d\u0430"
    ],
    "name:swe_x_preferred":[
        "Villa Corona"
    ],
    "name:vie_x_preferred":[
        "Villa Corona"
    ],
    "wof:name":"Villa Corona",
    "wof:placetype":"locality",
    "wof:population":10
},
  "geometry": {"coordinates":[-116.80444,32.48806],"type":"Point"}
}