{
  "type": "Feature",
  "properties": {
    "gn:admin1_code":"2",
    "gn:admin2_code":"4",
    "gn:asciiname":"Villa Corona",
    "gn:country_code":"MX",
    "gn:dem":172,
    "gn:feature_class":"P",
    "gn:feature_code":"PPL",
    "gn:name":"Villa Corona",
    "gn:population":10,
    "gn:timezone":"America/Tijuana",
    "iso:country":"MX",
    "wof:name":"Villa Corona",
    "wof:placetype":"locality",
    "wof:population":10
},
  "geometry": {"coordinates":[-116.80444,32.48806],"type":"Point"}
}