{
  "type": "Feature",
  "properties": {
    "gn:admin1_code":"24",
    "gn:admin2_code":"54.0",
    "gn:asciiname":"San Pedro Huitzquilico",
    "gn:country_code":"MX",
    "gn:dem":973,
    "gn:feature_class":"P",
    "gn:feature_code":"PPL",
    "gn:name":"San Pedro Huitzquilico",
    "gn:population":0,
    "gn:timezone":"America/Mexico_City",
    "iso:country":"MX",
    "name:spa_x_preferred":[
        "San Pedro Huitzquilico"
    ],
    "wof:name":"San Pedro Huitzquilico",
    "wof:placetype":"locality"
},
  "geometry": {"coordinates":[-99.01159,21.45669],"type":"Point"}
}