{
  "type": "Feature",
  "properties": {
    "gn:admin1_code":"26.0",
    "gn:admin2_code":"41.0",
    "gn:asciiname":"La Caridad",
    "gn:country_code":"MX",
    "gn:dem":1512,
    "gn:feature_class":"P",
    "gn:feature_code":"PPL",
    "gn:name":"La Caridad",
    "gn:population":0,
    "gn:timezone":"America/Hermosillo",
    "iso:country":"MX",
    "name:spa_x_preferred":[
        "La Caridad"
    ],
    "name:und_x_variant":[
        "Fracci\u00f3n G"
    ],
    "wof:name":"La Caridad",
    "wof:placetype":"locality"
},
  "geometry": {"coordinates":[-109.62134,30.36172],"type":"Point"}
}