{
  "type": "Feature",
  "properties": {
    "gn:admin1_code":"13",
    "gn:admin2_code":"42.0",
    "gn:asciiname":"Tepetlapa",
    "gn:country_code":"MX",
    "gn:dem":1124,
    "gn:feature_class":"P",
    "gn:feature_code":"PPL",
    "gn:name":"Tepetlapa",
    "gn:population":72,
    "gn:timezone":"America/Mexico_City",
    "iso:country":"MX",
    "wof:name":"Tepetlapa",
    "wof:placetype":"locality",
    "wof:population":72
},
  "geometry": {"coordinates":[-98.73765,20.87643],"type":"Point"}
}