{
  "type": "Feature",
  "properties": {
    "gn:admin1_code":"30.0",
    "gn:admin2_code":"161.0",
    "gn:asciiname":"El Jhonny",
    "gn:country_code":"MX",
    "gn:dem":83,
    "gn:feature_class":"P",
    "gn:feature_code":"PPL",
    "gn:name":"El Jhonny",
    "gn:population":7,
    "gn:timezone":"America/Mexico_City",
    "iso:country":"MX",
    "name:spa_x_preferred":[
        "El Jhonny"
    ],
    "wof:name":"El Jhonny",
    "wof:placetype":"locality",
    "wof:population":7
},
  "geometry": {"coordinates":[-98.47333,21.59222],"type":"Point"}
}