{
  "type": "Feature",
  "properties": {
    "gn:admin1_code":"2",
    "gn:admin2_code":"2.0",
    "gn:asciiname":"Saturno (Colonia Abasolo)",
    "gn:country_code":"MX",
    "gn:dem":10,
    "gn:feature_class":"P",
    "gn:feature_code":"PPL",
    "gn:name":"Saturno (Colonia Abasolo)",
    "gn:population":99,
    "gn:timezone":"America/Tijuana",
    "iso:country":"MX",
    "wof:name":"Saturno (Colonia Abasolo)",
    "wof:placetype":"locality",
    "wof:population":99
},
  "geometry": {"coordinates":[-115.36667,32.61694],"type":"Point"}
}