{
  "type": "Feature",
  "properties": {
    "gn:admin1_code":"32",
    "gn:admin2_code":"58.0",
    "gn:asciiname":"Santa Maria de la Paz",
    "gn:country_code":"MX",
    "gn:dem":1920,
    "gn:feature_class":"P",
    "gn:feature_code":"PPLA2",
    "gn:name":"Santa Mar\u00eda de la Paz",
    "gn:population":0,
    "gn:timezone":"America/Mexico_City",
    "iso:country":"MX",
    "name:und_x_variant":[
        "Ignacio Allende",
        "Santa Mar\u00eda",
        "Santa Mar\u00eda de la Paz"
    ],
    "wof:name":"Santa Maria de la Paz",
    "wof:placetype":"locality"
},
  "geometry": {"coordinates":[-103.40804,21.51205],"type":"Point"}
}