{
  "type": "Feature",
  "properties": {
    "gn:admin1_code":"12.0",
    "gn:admin2_code":"11.0",
    "gn:asciiname":"Las Guajes",
    "gn:country_code":"MX",
    "gn:dem":752,
    "gn:feature_class":"P",
    "gn:feature_code":"PPL",
    "gn:name":"Las Guajes",
    "gn:population":0,
    "gn:timezone":"America/Mexico_City",
    "iso:country":"MX",
    "name:spa_x_preferred":[
        "Las Guajes"
    ],
    "wof:name":"Las Guajes",
    "wof:placetype":"locality"
},
  "geometry": {"coordinates":[-100.24129000000001,17.36522],"type":"Point"}
}