{
  "type": "Feature",
  "properties": {
    "gn:admin1_code":"6.0",
    "gn:admin2_code":"67.0",
    "gn:asciiname":"El Vallecillo",
    "gn:country_code":"MX",
    "gn:dem":1610,
    "gn:feature_class":"P",
    "gn:feature_code":"PPL",
    "gn:name":"El Vallecillo",
    "gn:population":0,
    "gn:timezone":"America/Chihuahua",
    "iso:country":"MX",
    "name:spa_x_preferred":[
        "El Vallecillo"
    ],
    "wof:name":"El Vallecillo",
    "wof:placetype":"locality"
},
  "geometry": {"coordinates":[-105.78095999999999,27.68058],"type":"Point"}
}