{
  "type": "Feature",
  "properties": {
    "gn:admin1_code":"2",
    "gn:admin2_code":"1.0",
    "gn:asciiname":"El Carrizo",
    "gn:country_code":"MX",
    "gn:dem":735,
    "gn:feature_class":"P",
    "gn:feature_code":"PPL",
    "gn:name":"El Carrizo",
    "gn:population":2,
    "gn:timezone":"America/Tijuana",
    "iso:country":"MX",
    "wof:name":"El Carrizo",
    "wof:placetype":"locality",
    "wof:population":2
},
  "geometry": {"coordinates":[-113.6127,28.30555],"type":"Point"}
}