{
  "type": "Feature",
  "properties": {
    "gn:admin1_code":"32.0",
    "gn:admin2_code":"34.0",
    "gn:asciiname":"Saucillo",
    "gn:country_code":"MX",
    "gn:dem":1791,
    "gn:feature_class":"P",
    "gn:feature_code":"PPL",
    "gn:name":"Saucillo",
    "gn:population":0,
    "gn:timezone":"America/Mexico_City",
    "iso:country":"MX",
    "name:spa_x_preferred":[
        "Saucillo"
    ],
    "name:spa_x_variant":[
        "El Saucillo"
    ],
    "wof:name":"Saucillo",
    "wof:placetype":"locality"
},
  "geometry": {"coordinates":[-102.89574,21.25298],"type":"Point"}
}