{
  "type": "Feature",
  "properties": {
    "gn:admin1_code":"32",
    "gn:admin2_code":"17.0",
    "gn:asciiname":"Rancho los Laureles",
    "gn:country_code":"MX",
    "gn:dem":2215,
    "gn:feature_class":"P",
    "gn:feature_code":"PPL",
    "gn:name":"Rancho los Laureles",
    "gn:population":6,
    "gn:timezone":"America/Mexico_City",
    "iso:country":"MX",
    "wof:name":"Rancho los Laureles",
    "wof:placetype":"locality",
    "wof:population":6
},
  "geometry": {"coordinates":[-102.465,22.71694],"type":"Point"}
}