{
  "type": "Feature",
  "properties": {
    "gn:admin1_code":"18",
    "gn:admin2_code":"5.0",
    "gn:asciiname":"Llano de Tenepanta",
    "gn:country_code":"MX",
    "gn:dem":186,
    "gn:feature_class":"P",
    "gn:feature_code":"PPL",
    "gn:name":"Llano de Tenepanta",
    "gn:population":107,
    "gn:timezone":"America/Mazatlan",
    "iso:country":"MX",
    "wof:name":"Llano de Tenepanta",
    "wof:placetype":"locality",
    "wof:population":107
},
  "geometry": {"coordinates":[-105.33417,22.83528],"type":"Point"}
}