{
  "type": "Feature",
  "properties": {
    "gn:admin1_code":"14.0",
    "gn:admin2_code":"53.0",
    "gn:asciiname":"Estancia Grande",
    "gn:country_code":"MX",
    "gn:dem":2145,
    "gn:feature_class":"P",
    "gn:feature_code":"PPL",
    "gn:name":"Estancia Grande",
    "gn:population":0,
    "gn:timezone":"America/Mexico_City",
    "iso:country":"MX",
    "wof:name":"Estancia Grande",
    "wof:placetype":"locality"
},
  "geometry": {"coordinates":[-101.93333,21.53333],"type":"Point"}
}