{
  "type": "Feature",
  "properties": {
    "gn:admin1_code":"30.0",
    "gn:admin2_code":"123.0",
    "gn:asciiname":"Tampuche",
    "gn:country_code":"MX",
    "gn:dem":8,
    "gn:feature_class":"P",
    "gn:feature_code":"PPL",
    "gn:name":"Tampuche",
    "gn:population":557,
    "gn:timezone":"America/Mexico_City",
    "iso:country":"MX",
    "name:spa_x_preferred":[
        "Tampuche"
    ],
    "wof:name":"Tampuche",
    "wof:placetype":"locality",
    "wof:population":557
},
  "geometry": {"coordinates":[-98.15167,22.07139],"type":"Point"}
}