{
  "type": "Feature",
  "properties": {
    "gn:admin1_code":"6",
    "gn:admin2_code":"12",
    "gn:asciiname":"Huicochi",
    "gn:country_code":"MX",
    "gn:dem":2159,
    "gn:feature_class":"P",
    "gn:feature_code":"PPL",
    "gn:name":"Huicochi",
    "gn:population":36,
    "gn:timezone":"America/Chihuahua",
    "iso:country":"MX",
    "wof:name":"Huicochi",
    "wof:placetype":"locality",
    "wof:population":36
},
  "geometry": {"coordinates":[-107.00881,27.54312],"type":"Point"}
}