{
  "type": "Feature",
  "properties": {
    "gn:admin1_code":"20",
    "gn:admin2_code":"150",
    "gn:asciiname":"El Nuevo Manzanito",
    "gn:country_code":"MX",
    "gn:dem":2140,
    "gn:feature_class":"P",
    "gn:feature_code":"PPL",
    "gn:name":"El Nuevo Manzanito",
    "gn:population":42,
    "gn:timezone":"America/Mexico_City",
    "iso:country":"MX",
    "wof:name":"El Nuevo Manzanito",
    "wof:placetype":"locality",
    "wof:population":42
},
  "geometry": {"coordinates":[-96.93277999999999,17.41583],"type":"Point"}
}