{
  "type": "Feature",
  "properties": {
    "gn:admin1_code":"28.0",
    "gn:admin2_code":"16.0",
    "gn:asciiname":"Palmillas",
    "gn:country_code":"MX",
    "gn:dem":263,
    "gn:feature_class":"P",
    "gn:feature_code":"PPL",
    "gn:name":"Palmillas",
    "gn:population":0,
    "gn:timezone":"America/Monterrey",
    "iso:country":"MX",
    "name:spa_x_preferred":[
        "Palmillas"
    ],
    "name:srp_x_preferred":[
        "\u041f\u0430\u043b\u043c\u0438\u0459\u0430\u0441"
    ],
    "wof:name":"Palmillas",
    "wof:placetype":"locality"
},
  "geometry": {"coordinates":[-99.34472,24.23972],"type":"Point"}
}