{
  "type": "Feature",
  "properties": {
    "gn:admin1_code":"15",
    "gn:admin2_code":"117.0",
    "gn:asciiname":"La Hacienda",
    "gn:country_code":"MX",
    "gn:dem":1832,
    "gn:feature_class":"P",
    "gn:feature_code":"PPL",
    "gn:name":"La Hacienda",
    "gn:population":86,
    "gn:timezone":"America/Mexico_City",
    "iso:country":"MX",
    "wof:name":"La Hacienda",
    "wof:placetype":"locality",
    "wof:population":86
},
  "geometry": {"coordinates":[-99.86114999999999,18.68546],"type":"Point"}
}