{
  "type": "Feature",
  "properties": {
    "gn:admin1_code":"15",
    "gn:asciiname":"Tlaltecahuacan",
    "gn:country_code":"MX",
    "gn:dem":2268,
    "gn:feature_class":"P",
    "gn:feature_code":"PPL",
    "gn:name":"Tlaltecahuac\u00e1n",
    "gn:population":0,
    "gn:timezone":"America/Mexico_City",
    "iso:country":"MX",
    "name:und_x_variant":[
        "Tlaltecahuac\u00e1n",
        "Tlatecahuaca"
    ],
    "wof:name":"Tlaltecahuacan",
    "wof:placetype":"locality"
},
  "geometry": {"coordinates":[-98.88066999999999,19.57896],"type":"Point"}
}