{
  "type": "Feature",
  "properties": {
    "gn:admin1_code":"29",
    "gn:admin2_code":"14.0",
    "gn:asciiname":"Recoba",
    "gn:country_code":"MX",
    "gn:dem":2582,
    "gn:feature_class":"P",
    "gn:feature_code":"PPL",
    "gn:name":"Recoba",
    "gn:population":0,
    "gn:timezone":"America/Mexico_City",
    "iso:country":"MX",
    "name:und_x_variant":[
        "Recova"
    ],
    "wof:name":"Recoba",
    "wof:placetype":"locality"
},
  "geometry": {"coordinates":[-98.37302,19.48578],"type":"Point"}
}