{
  "type": "Feature",
  "properties": {
    "gn:admin1_code":"11.0",
    "gn:admin2_code":"37.0",
    "gn:asciiname":"La Esperanza del Refugio",
    "gn:country_code":"MX",
    "gn:dem":1797,
    "gn:feature_class":"P",
    "gn:feature_code":"PPL",
    "gn:name":"La Esperanza del Refugio",
    "gn:population":0,
    "gn:timezone":"America/Mexico_City",
    "iso:country":"MX",
    "name:spa_x_preferred":[
        "La Esperanza del Refugio"
    ],
    "name:und_x_variant":[
        "Esperanza",
        "La Esperanza"
    ],
    "wof:name":"La Esperanza del Refugio",
    "wof:placetype":"locality"
},
  "geometry": {"coordinates":[-101.52112,21.01176],"type":"Point"}
}