{
  "type": "Feature",
  "properties": {
    "gn:admin1_code":"20",
    "gn:admin2_code":"50",
    "gn:asciiname":"Corona Siniti",
    "gn:country_code":"MX",
    "gn:dem":2069,
    "gn:feature_class":"P",
    "gn:feature_code":"PPL",
    "gn:name":"Corona Siniti",
    "gn:population":34,
    "gn:timezone":"America/Mexico_City",
    "iso:country":"MX",
    "wof:name":"Corona Siniti",
    "wof:placetype":"locality",
    "wof:population":34
},
  "geometry": {"coordinates":[-97.53361,17.23972],"type":"Point"}
}