{
  "type": "Feature",
  "properties": {
    "gn:admin1_code":"20",
    "gn:admin2_code":"46",
    "gn:asciiname":"Loma Carrera",
    "gn:country_code":"MX",
    "gn:dem":1828,
    "gn:feature_class":"P",
    "gn:feature_code":"PPL",
    "gn:name":"Loma Carrera",
    "gn:population":19,
    "gn:timezone":"America/Mexico_City",
    "iso:country":"MX",
    "wof:name":"Loma Carrera",
    "wof:placetype":"locality",
    "wof:population":19
},
  "geometry": {"coordinates":[-97.26416999999999,17.15889],"type":"Point"}
}