{
  "type": "Feature",
  "properties": {
    "gn:admin1_code":"23.0",
    "gn:asciiname":"Dos Pozos",
    "gn:country_code":"MX",
    "gn:dem":127,
    "gn:feature_class":"P",
    "gn:feature_code":"PPL",
    "gn:name":"Dos Pozos",
    "gn:population":0,
    "gn:timezone":"America/Cancun",
    "iso:country":"MX",
    "name:spa_x_preferred":[
        "Dos Pozos"
    ],
    "wof:name":"Dos Pozos",
    "wof:placetype":"locality"
},
  "geometry": {"coordinates":[-88.96436,18.45814],"type":"Point"}
}