{
  "type": "Feature",
  "properties": {
    "gn:admin1_code":"26.0",
    "gn:admin2_code":"33.0",
    "gn:asciiname":"Los Martinez",
    "gn:country_code":"MX",
    "gn:dem":7,
    "gn:feature_class":"P",
    "gn:feature_code":"PPL",
    "gn:name":"Los Mart\u00ednez",
    "gn:population":0,
    "gn:timezone":"America/Hermosillo",
    "iso:country":"MX",
    "name:spa_x_preferred":[
        "Los Mart\u00ednez"
    ],
    "wof:name":"Los Martinez",
    "wof:placetype":"locality"
},
  "geometry": {"coordinates":[-109.52670000000001,26.81056],"type":"Point"}
}