{
  "type": "Feature",
  "properties": {
    "gn:admin1_code":"6.0",
    "gn:admin2_code":"1.0",
    "gn:asciiname":"Riva Palacio",
    "gn:country_code":"MX",
    "gn:dem":1250,
    "gn:feature_class":"P",
    "gn:feature_code":"PPL",
    "gn:name":"Riva Palacio",
    "gn:population":1,
    "gn:timezone":"America/Chihuahua",
    "iso:country":"MX",
    "name:ceb_x_preferred":[
        "Riva Palacio"
    ],
    "name:deu_x_preferred":[
        "Riva Palacio"
    ],
    "name:rus_x_preferred":[
        "\u0420\u0438\u0432\u0430-\u041f\u0430\u043b\u0430\u0441\u0438\u043e"
    ],
    "name:spa_x_preferred":[
        "Riva Palacio"
    ],
    "name:swe_x_preferred":[
        "Riva Palacio"
    ],
    "wof:name":"Riva Palacio",
    "wof:placetype":"locality",
    "wof:population":1
},
  "geometry": {"coordinates":[-106.75165,30.51264],"type":"Point"}
}