{
  "type": "Feature",
  "properties": {
    "gn:admin1_code":"21",
    "gn:admin2_code":"103.0",
    "gn:asciiname":"Loma de los Camotes",
    "gn:country_code":"MX",
    "gn:dem":2713,
    "gn:feature_class":"P",
    "gn:feature_code":"PPL",
    "gn:name":"Loma de los Camotes",
    "gn:population":75,
    "gn:timezone":"America/Mexico_City",
    "iso:country":"MX",
    "wof:name":"Loma de los Camotes",
    "wof:placetype":"locality",
    "wof:population":75
},
  "geometry": {"coordinates":[-97.32105,18.61322],"type":"Point"}
}