{
  "type": "Feature",
  "properties": {
    "gn:admin1_code":"19.0",
    "gn:admin2_code":"17.0",
    "gn:asciiname":"El Milagro",
    "gn:country_code":"MX",
    "gn:dem":1893,
    "gn:feature_class":"P",
    "gn:feature_code":"PPL",
    "gn:name":"El Milagro",
    "gn:population":0,
    "gn:timezone":"America/Monterrey",
    "iso:country":"MX",
    "name:spa_x_preferred":[
        "El Milagro"
    ],
    "name:und_x_variant":[
        "Ejido El Milagro"
    ],
    "wof:name":"El Milagro",
    "wof:placetype":"locality"
},
  "geometry": {"coordinates":[-100.56610999999999,24.9658],"type":"Point"}
}