{
  "type": "Feature",
  "properties": {
    "gn:admin1_code":"3.0",
    "gn:admin2_code":"8.0",
    "gn:asciiname":"Las Parritas",
    "gn:country_code":"MX",
    "gn:dem":416,
    "gn:feature_class":"P",
    "gn:feature_code":"PPL",
    "gn:name":"Las Parritas",
    "gn:population":0,
    "gn:timezone":"America/Mazatlan",
    "iso:country":"MX",
    "name:spa_x_preferred":[
        "Las Parritas"
    ],
    "wof:name":"Las Parritas",
    "wof:placetype":"locality"
},
  "geometry": {"coordinates":[-109.81829999999999,23.10015],"type":"Point"}
}