{
  "type": "Feature",
  "properties": {
    "gn:admin1_code":"2.0",
    "gn:admin2_code":"4.0",
    "gn:asciiname":"El Rinconcito",
    "gn:country_code":"MX",
    "gn:dem":263,
    "gn:feature_class":"P",
    "gn:feature_code":"PPL",
    "gn:name":"El Rinconcito",
    "gn:population":1,
    "gn:timezone":"America/Tijuana",
    "iso:country":"MX",
    "name:spa_x_preferred":[
        "El Rinconcito"
    ],
    "wof:name":"El Rinconcito",
    "wof:placetype":"locality",
    "wof:population":1
},
  "geometry": {"coordinates":[-116.74472,32.52944],"type":"Point"}
}