{
  "type": "Feature",
  "properties": {
    "gn:admin1_code":"5",
    "gn:admin2_code":"79.0",
    "gn:asciiname":"Chahuipac",
    "gn:country_code":"MX",
    "gn:dem":898,
    "gn:feature_class":"P",
    "gn:feature_code":"PPL",
    "gn:name":"Chahuipac",
    "gn:population":81,
    "gn:timezone":"America/Mexico_City",
    "iso:country":"MX",
    "wof:name":"Chahuipac",
    "wof:placetype":"locality",
    "wof:population":81
},
  "geometry": {"coordinates":[-93.22611000000001,16.86917],"type":"Point"}
}