{
  "type": "Feature",
  "properties": {
    "gn:admin1_code":"11",
    "gn:admin2_code":"42",
    "gn:asciiname":"Santa Rosa de Vallejo",
    "gn:country_code":"MX",
    "gn:dem":1721,
    "gn:feature_class":"P",
    "gn:feature_code":"PPL",
    "gn:name":"Santa Rosa de Vallejo",
    "gn:population":37,
    "gn:timezone":"America/Mexico_City",
    "iso:country":"MX",
    "wof:name":"Santa Rosa de Vallejo",
    "wof:placetype":"locality",
    "wof:population":37
},
  "geometry": {"coordinates":[-101.10361,20.42306],"type":"Point"}
}