{
  "type": "Feature",
  "properties": {
    "iso:country":"MX",
    "name:spa_x_preferred":[
        "Union Obrera"
    ],
    "name:unk_x_variant":[
        "Union Obrera"
    ],
    "qs:gn_adm0_cc":"MX",
    "qs:gn_local":3522307,
    "qs:gn_nam_loc":"Orizaba, Orizaba, Veracruz-Llave, MX",
    "qs:gn_namadm1":"30",
    "qs:local_max":54,
    "qs:local_sum":98,
    "qs:localhoods":2,
    "qs:name":"Union Obrera",
    "qs:name_adm0":"M\u00e9xico",
    "qs:name_adm1":"Veracruz-Llave",
    "qs:name_adm2":"Orizaba",
    "qs:name_local":"Orizaba",
    "qs:photo_max":16,
    "qs:photo_sum":44,
    "qs:placetype":"Suburb",
    "qs:quad_count":5,
    "qs:woe_adm0":23424900,
    "qs:woe_adm1":2346293,
    "qs:woe_adm2":12601841,
    "qs:woe_lau":0,
    "qs:woe_local":135338,
    "qs:woe_ver":"7.10.0",
    "wof:lang":[
        "spa"
    ],
    "wof:name":"Union Obrera",
    "wof:placetype":"neighbourhood"
},
  "geometry": {"coordinates":[-97.10466,18.849231],"type":"Point"}
}