{
  "type": "Feature",
  "properties": {
    "gn:admin1_code":"5",
    "gn:admin2_code":"89.0",
    "gn:asciiname":"Laguna del Carmen",
    "gn:country_code":"MX",
    "gn:dem":508,
    "gn:feature_class":"P",
    "gn:feature_code":"PPL",
    "gn:name":"Laguna del Carmen",
    "gn:population":21,
    "gn:timezone":"America/Mexico_City",
    "iso:country":"MX",
    "wof:name":"Laguna del Carmen",
    "wof:placetype":"locality",
    "wof:population":21
},
  "geometry": {"coordinates":[-92.28082999999999,15.04389],"type":"Point"}
}