{
  "type": "Feature",
  "properties": {
    "gn:admin1_code":"5.0",
    "gn:admin2_code":"96.0",
    "gn:asciiname":"Morelia",
    "gn:country_code":"MX",
    "gn:dem":61,
    "gn:feature_class":"P",
    "gn:feature_code":"PPL",
    "gn:name":"Morelia",
    "gn:population":0,
    "gn:timezone":"America/Mexico_City",
    "iso:country":"MX",
    "name:spa_x_preferred":[
        "Morelia"
    ],
    "name:spa_x_variant":[
        "Yaqui"
    ],
    "wof:name":"Morelia",
    "wof:placetype":"locality"
},
  "geometry": {"coordinates":[-92.43486,17.44791],"type":"Point"}
}