{
  "type": "Feature",
  "properties": {
    "gn:admin1_code":"5",
    "gn:admin2_code":"69",
    "gn:asciiname":"San Fernando",
    "gn:country_code":"MX",
    "gn:dem":42,
    "gn:feature_class":"P",
    "gn:feature_code":"PPL",
    "gn:name":"San Fernando",
    "gn:population":16,
    "gn:timezone":"America/Mexico_City",
    "iso:country":"MX",
    "wof:name":"San Fernando",
    "wof:placetype":"locality",
    "wof:population":16
},
  "geometry": {"coordinates":[-93.15000000000001,15.65778],"type":"Point"}
}