{
  "type": "Feature",
  "properties": {
    "gn:admin1_code":"20",
    "gn:admin2_code":"547.0",
    "gn:asciiname":"La Luz",
    "gn:country_code":"MX",
    "gn:dem":2130,
    "gn:feature_class":"P",
    "gn:feature_code":"PPL",
    "gn:name":"La Luz",
    "gn:population":113,
    "gn:timezone":"America/Mexico_City",
    "iso:country":"MX",
    "wof:name":"La Luz",
    "wof:placetype":"locality",
    "wof:population":113
},
  "geometry": {"coordinates":[-97.54528000000001,17.76083],"type":"Point"}
}