{
  "type": "Feature",
  "properties": {
    "gn:admin1_code":"6.0",
    "gn:admin2_code":"14.0",
    "gn:asciiname":"El Dieciseis",
    "gn:country_code":"MX",
    "gn:dem":1527,
    "gn:feature_class":"P",
    "gn:feature_code":"PPL",
    "gn:name":"El Diecis\u00e9is",
    "gn:population":0,
    "gn:timezone":"America/Chihuahua",
    "iso:country":"MX",
    "name:spa_x_preferred":[
        "El Diecis\u00e9is"
    ],
    "wof:name":"El Dieciseis",
    "wof:placetype":"locality"
},
  "geometry": {"coordinates":[-105.14446,26.68386],"type":"Point"}
}