{
  "type": "Feature",
  "properties": {
    "gn:admin1_code":"16",
    "gn:admin2_code":"35",
    "gn:asciiname":"La Pinzanera",
    "gn:country_code":"MX",
    "gn:dem":464,
    "gn:feature_class":"P",
    "gn:feature_code":"PPL",
    "gn:name":"La Pinzanera",
    "gn:population":36,
    "gn:timezone":"America/Mexico_City",
    "iso:country":"MX",
    "wof:name":"La Pinzanera",
    "wof:placetype":"locality",
    "wof:population":36
},
  "geometry": {"coordinates":[-101.81917,18.95639],"type":"Point"}
}