{
  "type": "Feature",
  "properties": {
    "gn:admin1_code":"11",
    "gn:admin2_code":"44",
    "gn:asciiname":"Tecoripa",
    "gn:country_code":"MX",
    "gn:dem":1740,
    "gn:feature_class":"P",
    "gn:feature_code":"PPL",
    "gn:name":"Tecoripa",
    "gn:population":20,
    "gn:timezone":"America/Mexico_City",
    "iso:country":"MX",
    "wof:name":"Tecoripa",
    "wof:placetype":"locality",
    "wof:population":20
},
  "geometry": {"coordinates":[-100.97972,20.53972000000001],"type":"Point"}
}