{
  "type": "Feature",
  "properties": {
    "gn:admin1_code":"24",
    "gn:admin2_code":"37.0",
    "gn:asciiname":"Barrio Progreso",
    "gn:country_code":"MX",
    "gn:dem":496,
    "gn:feature_class":"P",
    "gn:feature_code":"PPL",
    "gn:name":"Barrio Progreso",
    "gn:population":560,
    "gn:timezone":"America/Mexico_City",
    "iso:country":"MX",
    "wof:name":"Barrio Progreso",
    "wof:placetype":"locality",
    "wof:population":560
},
  "geometry": {"coordinates":[-98.87027999999999,21.20972],"type":"Point"}
}