{
  "type": "Feature",
  "properties": {
    "gn:admin1_code":"5",
    "gn:admin2_code":"1.0",
    "gn:asciiname":"Las Truchas",
    "gn:country_code":"MX",
    "gn:dem":100,
    "gn:feature_class":"P",
    "gn:feature_code":"PPL",
    "gn:name":"Las Truchas",
    "gn:population":8,
    "gn:timezone":"America/Mexico_City",
    "iso:country":"MX",
    "wof:name":"Las Truchas",
    "wof:placetype":"locality",
    "wof:population":8
},
  "geometry": {"coordinates":[-92.70999999999999,15.375],"type":"Point"}
}