{
  "type": "Feature",
  "properties": {
    "gn:admin1_code":"14",
    "gn:admin2_code":"104",
    "gn:asciiname":"Acaspulquillo",
    "gn:country_code":"MX",
    "gn:dem":1970,
    "gn:feature_class":"P",
    "gn:feature_code":"PPL",
    "gn:name":"Acaspulquillo",
    "gn:population":20,
    "gn:timezone":"America/Mexico_City",
    "iso:country":"MX",
    "wof:name":"Acaspulquillo",
    "wof:placetype":"locality",
    "wof:population":20
},
  "geometry": {"coordinates":[-103.545,21.94194],"type":"Point"}
}