{
  "type": "Feature",
  "properties": {
    "gn:admin1_code":"12",
    "gn:admin2_code":"2.0",
    "gn:asciiname":"Lambedero",
    "gn:country_code":"MX",
    "gn:dem":1228,
    "gn:feature_class":"P",
    "gn:feature_code":"PPL",
    "gn:name":"Lambedero",
    "gn:population":57,
    "gn:timezone":"America/Mexico_City",
    "iso:country":"MX",
    "wof:name":"Lambedero",
    "wof:placetype":"locality",
    "wof:population":57
},
  "geometry": {"coordinates":[-98.87667999999999,17.79968],"type":"Point"}
}