{
  "type": "Feature",
  "properties": {
    "gn:admin1_code":"28",
    "gn:admin2_code":"32",
    "gn:asciiname":"San Modesto",
    "gn:country_code":"MX",
    "gn:dem":57,
    "gn:feature_class":"P",
    "gn:feature_code":"PPL",
    "gn:name":"San Modesto",
    "gn:population":10,
    "gn:timezone":"America/Matamoros",
    "iso:country":"MX",
    "wof:name":"San Modesto",
    "wof:placetype":"locality",
    "wof:population":10
},
  "geometry": {"coordinates":[-98.27110999999999,25.94861],"type":"Point"}
}