{
  "type": "Feature",
  "properties": {
    "gn:admin1_code":"14",
    "gn:admin2_code":"86.0",
    "gn:asciiname":"Santa Ines",
    "gn:country_code":"MX",
    "gn:dem":2087,
    "gn:feature_class":"P",
    "gn:feature_code":"PPL",
    "gn:name":"Santa In\u00e9s",
    "gn:population":85,
    "gn:timezone":"America/Mexico_City",
    "iso:country":"MX",
    "name:und_x_variant":[
        "Santa In\u00e9s"
    ],
    "wof:name":"Santa Ines",
    "wof:placetype":"locality",
    "wof:population":85
},
  "geometry": {"coordinates":[-103.72056000000001,19.88972],"type":"Point"}
}