{
  "type": "Feature",
  "properties": {
    "gn:admin1_code":"28",
    "gn:admin2_code":"23.0",
    "gn:asciiname":"Espiaderos Dos (Chapeno Dos)",
    "gn:country_code":"MX",
    "gn:dem":46,
    "gn:feature_class":"P",
    "gn:feature_code":"PPL",
    "gn:name":"Espiaderos Dos (Chape\u00f1o Dos)",
    "gn:population":177,
    "gn:timezone":"America/Monterrey",
    "iso:country":"MX",
    "name:und_x_variant":[
        "Espiaderos Dos (Chape\u00f1o Dos)"
    ],
    "wof:name":"Espiaderos Dos (Chapeno Dos)",
    "wof:placetype":"locality",
    "wof:population":177
},
  "geometry": {"coordinates":[-98.15278000000001,25.275],"type":"Point"}
}