{
  "type": "Feature",
  "properties": {
    "gn:admin1_code":"14",
    "gn:admin2_code":"61.0",
    "gn:asciiname":"La Guacamaya",
    "gn:country_code":"MX",
    "gn:dem":2057,
    "gn:feature_class":"P",
    "gn:feature_code":"PPL",
    "gn:name":"La Guacamaya",
    "gn:population":6,
    "gn:timezone":"America/Mexico_City",
    "iso:country":"MX",
    "wof:name":"La Guacamaya",
    "wof:placetype":"locality",
    "wof:population":6
},
  "geometry": {"coordinates":[-104.03444,22.28889],"type":"Point"}
}