{
  "type": "Feature",
  "properties": {
    "gn:admin1_code":"27.0",
    "gn:asciiname":"Zapotal Quinta Seccion",
    "gn:country_code":"MX",
    "gn:dem":18,
    "gn:feature_class":"P",
    "gn:feature_code":"PPL",
    "gn:name":"Zapotal Quinta Secci\u00f3n",
    "gn:population":0,
    "gn:timezone":"America/Mexico_City",
    "iso:country":"MX",
    "name:spa_x_preferred":[
        "Zapotal Quinta Secci\u00f3n"
    ],
    "wof:name":"Zapotal Quinta Seccion",
    "wof:placetype":"locality"
},
  "geometry": {"coordinates":[-93.74865,18.00812999999999],"type":"Point"}
}