{
  "type": "Feature",
  "properties": {
    "gn:admin1_code":"14",
    "gn:admin2_code":"13.0",
    "gn:asciiname":"La Estancia de Navarro",
    "gn:country_code":"MX",
    "gn:dem":1603,
    "gn:feature_class":"P",
    "gn:feature_code":"PPL",
    "gn:name":"La Estancia de Navarro",
    "gn:population":170,
    "gn:timezone":"America/Mexico_City",
    "iso:country":"MX",
    "wof:name":"La Estancia de Navarro",
    "wof:placetype":"locality",
    "wof:population":170
},
  "geometry": {"coordinates":[-102.60944000000001,20.54917],"type":"Point"}
}