{
  "type": "Feature",
  "properties": {
    "gn:admin1_code":"11.0",
    "gn:admin2_code":"17.0",
    "gn:asciiname":"El Conejo",
    "gn:country_code":"MX",
    "gn:dem":1744,
    "gn:feature_class":"P",
    "gn:feature_code":"PPL",
    "gn:name":"El Conejo",
    "gn:population":530,
    "gn:timezone":"America/Mexico_City",
    "iso:country":"MX",
    "name:spa_x_preferred":[
        "El Conejo"
    ],
    "wof:name":"El Conejo",
    "wof:placetype":"locality",
    "wof:population":530
},
  "geometry": {"coordinates":[-101.42149999999999,20.73011],"type":"Point"}
}