{
  "type": "Feature",
  "properties": {
    "gn:admin1_code":"26.0",
    "gn:admin2_code":"11.0",
    "gn:asciiname":"Choyoqui",
    "gn:country_code":"MX",
    "gn:dem":1148,
    "gn:feature_class":"P",
    "gn:feature_code":"PPL",
    "gn:name":"Choyoqui",
    "gn:population":0,
    "gn:timezone":"America/Hermosillo",
    "iso:country":"MX",
    "name:spa_x_preferred":[
        "Choyoqui"
    ],
    "wof:name":"Choyoqui",
    "wof:placetype":"locality"
},
  "geometry": {"coordinates":[-109.89698,30.56294],"type":"Point"}
}