{
  "type": "Feature",
  "properties": {
    "gn:admin1_code":"31",
    "gn:admin2_code":"58.0",
    "gn:asciiname":"Progresito",
    "gn:country_code":"MX",
    "gn:dem":37,
    "gn:feature_class":"P",
    "gn:feature_code":"PPL",
    "gn:name":"Progresito",
    "gn:population":0,
    "gn:timezone":"America/Merida",
    "iso:country":"MX",
    "name:spa_x_preferred":[
        "Progresito"
    ],
    "name:spa_x_variant":[
        "Progreso"
    ],
    "wof:name":"Progresito",
    "wof:placetype":"locality"
},
  "geometry": {"coordinates":[-88.84963,20.09009],"type":"Point"}
}