{
  "type": "Feature",
  "properties": {
    "gn:admin1_code":"26.0",
    "gn:admin2_code":"8.0",
    "gn:asciiname":"Piedra de Lumbre",
    "gn:country_code":"MX",
    "gn:dem":1156,
    "gn:feature_class":"P",
    "gn:feature_code":"PPL",
    "gn:name":"Piedra de Lumbre",
    "gn:population":0,
    "gn:timezone":"America/Hermosillo",
    "iso:country":"MX",
    "name:spa_x_preferred":[
        "Piedra de Lumbre"
    ],
    "wof:name":"Piedra de Lumbre",
    "wof:placetype":"locality"
},
  "geometry": {"coordinates":[-109.134,30.00998],"type":"Point"}
}