{
  "type": "Feature",
  "properties": {
    "gn:admin1_code":"22",
    "gn:admin2_code":"4",
    "gn:asciiname":"Seccion Sureste de Cadereyta",
    "gn:country_code":"MX",
    "gn:dem":2046,
    "gn:feature_class":"P",
    "gn:feature_code":"PPL",
    "gn:name":"Secci\u00f3n Sureste de Cadereyta",
    "gn:population":11,
    "gn:timezone":"America/Mexico_City",
    "iso:country":"MX",
    "name:und_x_variant":[
        "Secci\u00f3n Sureste de Cadereyta"
    ],
    "wof:name":"Seccion Sureste de Cadereyta",
    "wof:placetype":"locality",
    "wof:population":11
},
  "geometry": {"coordinates":[-99.80722,20.68889],"type":"Point"}
}