{
  "type": "Feature",
  "properties": {
    "gn:admin1_code":"30",
    "gn:admin2_code":"86.0",
    "gn:asciiname":"El Veinticinco",
    "gn:country_code":"MX",
    "gn:dem":776,
    "gn:feature_class":"P",
    "gn:feature_code":"PPL",
    "gn:name":"El Veinticinco",
    "gn:population":140,
    "gn:timezone":"America/Mexico_City",
    "iso:country":"MX",
    "wof:name":"El Veinticinco",
    "wof:placetype":"locality",
    "wof:population":140
},
  "geometry": {"coordinates":[-97.25055999999999,19.92694],"type":"Point"}
}