{
  "type": "Feature",
  "properties": {
    "gn:admin1_code":"14",
    "gn:admin2_code":"19.0",
    "gn:asciiname":"Cienega de la Mesa del Robloso (Cienega Chica)",
    "gn:country_code":"MX",
    "gn:dem":1918,
    "gn:feature_class":"P",
    "gn:feature_code":"PPL",
    "gn:name":"Ci\u00e9nega de la Mesa del Robloso (Ci\u00e9nega Chica)",
    "gn:population":8,
    "gn:timezone":"America/Mexico_City",
    "iso:country":"MX",
    "name:und_x_variant":[
        "Ci\u00e9nega de la Mesa del Robloso (Ci\u00e9nega Chica)"
    ],
    "wof:name":"Cienega de la Mesa del Robloso (Cienega Chica)",
    "wof:placetype":"locality",
    "wof:population":8
},
  "geometry": {"coordinates":[-103.96611,21.91361],"type":"Point"}
}