{
  "type": "Feature",
  "properties": {
    "gn:admin1_code":"8.0",
    "gn:admin2_code":"9.0",
    "gn:asciiname":"La Maquina",
    "gn:country_code":"MX",
    "gn:dem":14,
    "gn:feature_class":"P",
    "gn:feature_code":"PPL",
    "gn:name":"La M\u00e1quina",
    "gn:population":0,
    "gn:timezone":"America/Mexico_City",
    "iso:country":"MX",
    "name:spa_x_preferred":[
        "La M\u00e1quina"
    ],
    "wof:name":"La Maquina",
    "wof:placetype":"locality"
},
  "geometry": {"coordinates":[-103.9061,18.84898],"type":"Point"}
}