{
  "type": "Feature",
  "properties": {
    "gn:admin1_code":"11",
    "gn:admin2_code":"9.0",
    "gn:asciiname":"La Purisima",
    "gn:country_code":"MX",
    "gn:dem":1826,
    "gn:feature_class":"P",
    "gn:feature_code":"PPL",
    "gn:name":"La Pur\u00edsima",
    "gn:population":7,
    "gn:timezone":"America/Mexico_City",
    "iso:country":"MX",
    "name:und_x_variant":[
        "La Pur\u00edsima"
    ],
    "wof:name":"La Purisima",
    "wof:placetype":"locality",
    "wof:population":7
},
  "geometry": {"coordinates":[-100.79083,20.72333],"type":"Point"}
}