{
  "type": "Feature",
  "properties": {
    "gn:admin1_code":"14.0",
    "gn:admin2_code":"34.0",
    "gn:asciiname":"El Limoncillo",
    "gn:country_code":"MX",
    "gn:dem":1192,
    "gn:feature_class":"P",
    "gn:feature_code":"PPL",
    "gn:name":"El Limoncillo",
    "gn:population":0,
    "gn:timezone":"America/Mexico_City",
    "iso:country":"MX",
    "name:spa_x_preferred":[
        "El Limoncillo"
    ],
    "wof:name":"El Limoncillo",
    "wof:placetype":"locality"
},
  "geometry": {"coordinates":[-103.97454,19.9418],"type":"Point"}
}