{
  "type": "Feature",
  "properties": {
    "gn:admin1_code":"30.0",
    "gn:asciiname":"Las Gardenias",
    "gn:country_code":"MX",
    "gn:dem":29,
    "gn:feature_class":"P",
    "gn:feature_code":"PPL",
    "gn:name":"Las Gardenias",
    "gn:population":0,
    "gn:timezone":"America/Mexico_City",
    "iso:country":"MX",
    "name:spa_x_preferred":[
        "Las Gardenias"
    ],
    "wof:name":"Las Gardenias",
    "wof:placetype":"locality"
},
  "geometry": {"coordinates":[-97.91176,21.95663],"type":"Point"}
}