{
  "type": "Feature",
  "properties": {
    "gn:admin1_code":"10",
    "gn:admin2_code":"14",
    "gn:asciiname":"Los Bosques",
    "gn:country_code":"MX",
    "gn:dem":2263,
    "gn:feature_class":"P",
    "gn:feature_code":"PPL",
    "gn:name":"Los Bosques",
    "gn:population":12,
    "gn:timezone":"America/Monterrey",
    "iso:country":"MX",
    "wof:name":"Los Bosques",
    "wof:placetype":"locality",
    "wof:population":12
},
  "geometry": {"coordinates":[-104.31828,22.61476],"type":"Point"}
}