{
  "type": "Feature",
  "properties": {
    "gn:admin1_code":"18",
    "gn:admin2_code":"15",
    "gn:asciiname":"El Matadero",
    "gn:country_code":"MX",
    "gn:dem":6,
    "gn:feature_class":"P",
    "gn:feature_code":"PPL",
    "gn:name":"El Matadero",
    "gn:population":12,
    "gn:timezone":"America/Mazatlan",
    "iso:country":"MX",
    "wof:name":"El Matadero",
    "wof:placetype":"locality",
    "wof:population":12
},
  "geometry": {"coordinates":[-105.47889000000001,21.90639],"type":"Point"}
}