{
  "type": "Feature",
  "properties": {
    "gn:admin1_code":"6",
    "gn:admin2_code":"17.0",
    "gn:asciiname":"Campo Numero Ciento Nueve",
    "gn:country_code":"MX",
    "gn:dem":2019,
    "gn:feature_class":"P",
    "gn:feature_code":"PPL",
    "gn:name":"Campo N\u00famero Ciento Nueve",
    "gn:population":204,
    "gn:timezone":"America/Chihuahua",
    "iso:country":"MX",
    "name:und_x_variant":[
        "Campo Ciento Nueve",
        "Campo 109"
    ],
    "wof:name":"Campo Numero Ciento Nueve",
    "wof:placetype":"locality",
    "wof:population":204
},
  "geometry": {"coordinates":[-107.07666999999999,28.79722000000001],"type":"Point"}
}