{
  "type": "Feature",
  "properties": {
    "gn:admin1_code":"12.0",
    "gn:admin2_code":"11.0",
    "gn:asciiname":"Rancho Zapotitan",
    "gn:country_code":"MX",
    "gn:dem":50,
    "gn:feature_class":"P",
    "gn:feature_code":"PPL",
    "gn:name":"Rancho Zapotit\u00e1n",
    "gn:population":0,
    "gn:timezone":"America/Mexico_City",
    "iso:country":"MX",
    "name:spa_x_preferred":[
        "Rancho Zapotit\u00e1n"
    ],
    "wof:name":"Rancho Zapotitan",
    "wof:placetype":"locality"
},
  "geometry": {"coordinates":[-100.42337999999999,17.1868],"type":"Point"}
}