{
  "type": "Feature",
  "properties": {
    "gn:admin1_code":"20",
    "gn:admin2_code":"366.0",
    "gn:asciiname":"Cerro el Gigante",
    "gn:country_code":"MX",
    "gn:dem":813,
    "gn:feature_class":"P",
    "gn:feature_code":"PPL",
    "gn:name":"Cerro el Gigante",
    "gn:population":5,
    "gn:timezone":"America/Mexico_City",
    "iso:country":"MX",
    "wof:name":"Cerro el Gigante",
    "wof:placetype":"locality",
    "wof:population":5
},
  "geometry": {"coordinates":[-96.70361,16.05944],"type":"Point"}
}