{
  "type": "Feature",
  "properties": {
    "gn:admin1_code":"10",
    "gn:admin2_code":"35.0",
    "gn:asciiname":"San Nicolas de Presidio",
    "gn:country_code":"MX",
    "gn:dem":1769,
    "gn:feature_class":"P",
    "gn:feature_code":"PPL",
    "gn:name":"San Nicol\u00e1s de Presidio",
    "gn:population":0,
    "gn:timezone":"America/Monterrey",
    "iso:country":"MX",
    "name:spa_x_preferred":[
        "San Nicol\u00e1s de Presidio"
    ],
    "name:spa_x_variant":[
        "Presidio de Arriba"
    ],
    "name:und_x_variant":[
        "San Nicol\u00e1s",
        "Presidios",
        "Presidio",
        "Presidios de San Nicol\u00e1s"
    ],
    "wof:name":"San Nicolas de Presidio",
    "wof:placetype":"locality"
},
  "geometry": {"coordinates":[-105.63111000000001,25.2836],"type":"Point"}
}