{
  "type": "Feature",
  "properties": {
    "gn:admin1_code":"26",
    "gn:admin2_code":"33.0",
    "gn:asciiname":"Capazeta (Buelna)",
    "gn:country_code":"MX",
    "gn:dem":9,
    "gn:feature_class":"P",
    "gn:feature_code":"PPL",
    "gn:name":"Capazeta (Buelna)",
    "gn:population":8,
    "gn:timezone":"America/Hermosillo",
    "iso:country":"MX",
    "wof:name":"Capazeta (Buelna)",
    "wof:placetype":"locality",
    "wof:population":8
},
  "geometry": {"coordinates":[-109.71556,26.81194],"type":"Point"}
}