{
  "type": "Feature",
  "properties": {
    "gn:admin1_code":"11",
    "gn:admin2_code":"29",
    "gn:asciiname":"El Extranjero",
    "gn:country_code":"MX",
    "gn:dem":2010,
    "gn:feature_class":"P",
    "gn:feature_code":"PPL",
    "gn:name":"El Extranjero",
    "gn:population":28,
    "gn:timezone":"America/Mexico_City",
    "iso:country":"MX",
    "wof:name":"El Extranjero",
    "wof:placetype":"locality",
    "wof:population":28
},
  "geometry": {"coordinates":[-100.855,21.36778],"type":"Point"}
}