{
  "type": "Feature",
  "properties": {
    "gn:admin1_code":"10",
    "gn:admin2_code":"13.0",
    "gn:asciiname":"La Vaca",
    "gn:country_code":"MX",
    "gn:dem":1308,
    "gn:feature_class":"P",
    "gn:feature_code":"PPL",
    "gn:name":"La Vaca",
    "gn:population":0,
    "gn:timezone":"America/Monterrey",
    "iso:country":"MX",
    "name:spa_x_preferred":[
        "La Vaca"
    ],
    "wof:name":"La Vaca",
    "wof:placetype":"locality"
},
  "geometry": {"coordinates":[-103.98860000000001,25.99102],"type":"Point"}
}