{
  "type": "Feature",
  "properties": {
    "gn:admin1_code":"31.0",
    "gn:asciiname":"Buenaventura Kunchebila",
    "gn:country_code":"MX",
    "gn:dem":20,
    "gn:feature_class":"P",
    "gn:feature_code":"PPL",
    "gn:name":"Buenaventura Kunchebil\u00e1",
    "gn:population":0,
    "gn:timezone":"America/Merida",
    "iso:country":"MX",
    "name:spa_x_preferred":[
        "Buenaventura Kunchebil\u00e1"
    ],
    "name:spa_x_variant":[
        "Buenavista Kunchebila"
    ],
    "wof:name":"Buenaventura Kunchebila",
    "wof:placetype":"locality"
},
  "geometry": {"coordinates":[-88.00286,21.12445],"type":"Point"}
}