{
  "type": "Feature",
  "properties": {
    "gn:admin1_code":"30.0",
    "gn:admin2_code":"161.0",
    "gn:asciiname":"Cristo Negro",
    "gn:country_code":"MX",
    "gn:dem":98,
    "gn:feature_class":"P",
    "gn:feature_code":"PPL",
    "gn:name":"Cristo Negro",
    "gn:population":0,
    "gn:timezone":"America/Mexico_City",
    "iso:country":"MX",
    "name:spa_x_preferred":[
        "Cristo Negro"
    ],
    "wof:name":"Cristo Negro",
    "wof:placetype":"locality"
},
  "geometry": {"coordinates":[-98.26219,21.64039],"type":"Point"}
}