{
  "type": "Feature",
  "properties": {
    "gn:admin1_code":"6.0",
    "gn:admin2_code":"35.0",
    "gn:asciiname":"El Ano Nuevo",
    "gn:country_code":"MX",
    "gn:dem":1405,
    "gn:feature_class":"P",
    "gn:feature_code":"PPL",
    "gn:name":"El A\u00f1o Nuevo",
    "gn:population":0,
    "gn:timezone":"America/Chihuahua",
    "iso:country":"MX",
    "name:spa_x_preferred":[
        "El A\u00f1o Nuevo"
    ],
    "wof:name":"El Ano Nuevo",
    "wof:placetype":"locality"
},
  "geometry": {"coordinates":[-108.39754000000001,30.86321],"type":"Point"}
}