{
  "type": "Feature",
  "properties": {
    "gn:admin1_code":"3",
    "gn:admin2_code":"3.0",
    "gn:asciiname":"Tortuga del Sol",
    "gn:country_code":"MX",
    "gn:dem":16,
    "gn:feature_class":"P",
    "gn:feature_code":"PPL",
    "gn:name":"Tortuga del Sol",
    "gn:population":7,
    "gn:timezone":"America/Mazatlan",
    "iso:country":"MX",
    "wof:name":"Tortuga del Sol",
    "wof:placetype":"locality",
    "wof:population":7
},
  "geometry": {"coordinates":[-110.16558999999999,23.32017],"type":"Point"}
}