{
  "type": "Feature",
  "properties": {
    "gn:admin1_code":"6",
    "gn:admin2_code":"5.0",
    "gn:asciiname":"El Montoso",
    "gn:country_code":"MX",
    "gn:dem":1500,
    "gn:feature_class":"P",
    "gn:feature_code":"PPL",
    "gn:name":"El Montoso",
    "gn:population":0,
    "gn:timezone":"America/Chihuahua",
    "iso:country":"MX",
    "wof:name":"El Montoso",
    "wof:placetype":"locality"
},
  "geometry": {"coordinates":[-107.69756,30.95668],"type":"Point"}
}