{
  "type": "Feature",
  "properties": {
    "gn:admin1_code":"20",
    "gn:admin2_code":"321",
    "gn:asciiname":"Agua Negra",
    "gn:country_code":"MX",
    "gn:dem":2224,
    "gn:feature_class":"P",
    "gn:feature_code":"PPL",
    "gn:name":"Agua Negra",
    "gn:population":11,
    "gn:timezone":"America/Mexico_City",
    "iso:country":"MX",
    "wof:name":"Agua Negra",
    "wof:placetype":"locality",
    "wof:population":11
},
  "geometry": {"coordinates":[-97.54806000000001,17.81833],"type":"Point"}
}