{
  "type": "Feature",
  "properties": {
    "gn:admin1_code":"6",
    "gn:admin2_code":"65",
    "gn:asciiname":"Ririnapuchi",
    "gn:country_code":"MX",
    "gn:dem":1871,
    "gn:feature_class":"P",
    "gn:feature_code":"PPL",
    "gn:name":"Ririnapuchi",
    "gn:population":10,
    "gn:timezone":"America/Chihuahua",
    "iso:country":"MX",
    "wof:name":"Ririnapuchi",
    "wof:placetype":"locality",
    "wof:population":10
},
  "geometry": {"coordinates":[-107.72852,27.28215],"type":"Point"}
}