{
  "type": "Feature",
  "properties": {
    "gn:admin1_code":"13",
    "gn:admin2_code":"37",
    "gn:asciiname":"La Trampa",
    "gn:country_code":"MX",
    "gn:dem":2129,
    "gn:feature_class":"P",
    "gn:feature_code":"PPL",
    "gn:name":"La Trampa",
    "gn:population":14,
    "gn:timezone":"America/Mexico_City",
    "iso:country":"MX",
    "name:spa_x_preferred":[
        "La Trampa"
    ],
    "wof:name":"La Trampa",
    "wof:placetype":"locality",
    "wof:population":14
},
  "geometry": {"coordinates":[-98.77737,20.45482],"type":"Point"}
}