{
  "type": "Feature",
  "properties": {
    "gn:admin1_code":"7.0",
    "gn:admin2_code":"30.0",
    "gn:asciiname":"Agua Nueva",
    "gn:country_code":"MX",
    "gn:dem":1935,
    "gn:feature_class":"P",
    "gn:feature_code":"PPL",
    "gn:name":"Agua Nueva",
    "gn:population":0,
    "gn:timezone":"America/Monterrey",
    "iso:country":"MX",
    "name:spa_x_preferred":[
        "Agua Nueva"
    ],
    "wof:name":"Agua Nueva",
    "wof:placetype":"locality"
},
  "geometry": {"coordinates":[-101.08839999999999,25.18934],"type":"Point"}
}