{
  "type": "Feature",
  "properties": {
    "gn:admin1_code":"5",
    "gn:admin2_code":"106.0",
    "gn:asciiname":"San Francisco la Herradura",
    "gn:country_code":"MX",
    "gn:dem":648,
    "gn:feature_class":"P",
    "gn:feature_code":"PPL",
    "gn:name":"San Francisco la Herradura",
    "gn:population":7,
    "gn:timezone":"America/Mexico_City",
    "iso:country":"MX",
    "wof:name":"San Francisco la Herradura",
    "wof:placetype":"locality",
    "wof:population":7
},
  "geometry": {"coordinates":[-92.50111,16.30556],"type":"Point"}
}