{
  "type": "Feature",
  "properties": {
    "gn:admin1_code":"5",
    "gn:admin2_code":"87.0",
    "gn:asciiname":"General Manuel Avila Camacho",
    "gn:country_code":"MX",
    "gn:dem":13,
    "gn:feature_class":"P",
    "gn:feature_code":"PPL",
    "gn:name":"General Manuel \u00c1vila Camacho",
    "gn:population":510,
    "gn:timezone":"America/Mexico_City",
    "iso:country":"MX",
    "name:und_x_variant":[
        "General Manuel \u00c1vila Camacho"
    ],
    "wof:name":"General Manuel Avila Camacho",
    "wof:placetype":"locality",
    "wof:population":510
},
  "geometry": {"coordinates":[-92.23556000000001,14.64278],"type":"Point"}
}