{
  "type": "Feature",
  "properties": {
    "gn:admin1_code":"14",
    "gn:admin2_code":"35.0",
    "gn:asciiname":"La Casita",
    "gn:country_code":"MX",
    "gn:dem":1937,
    "gn:feature_class":"P",
    "gn:feature_code":"PPL",
    "gn:name":"La Casita",
    "gn:population":9,
    "gn:timezone":"America/Mexico_City",
    "iso:country":"MX",
    "wof:name":"La Casita",
    "wof:placetype":"locality",
    "wof:population":9
},
  "geometry": {"coordinates":[-102.15361,21.58667],"type":"Point"}
}