{
  "type": "Feature",
  "properties": {
    "gn:admin1_code":"30",
    "gn:admin2_code":"210.0",
    "gn:asciiname":"Loma de Oro",
    "gn:country_code":"MX",
    "gn:dem":72,
    "gn:feature_class":"P",
    "gn:feature_code":"PPL",
    "gn:name":"Loma de Oro",
    "gn:population":123,
    "gn:timezone":"America/Mexico_City",
    "iso:country":"MX",
    "wof:name":"Loma de Oro",
    "wof:placetype":"locality",
    "wof:population":123
},
  "geometry": {"coordinates":[-94.37417000000001,17.26167],"type":"Point"}
}