{
  "type": "Feature",
  "properties": {
    "gn:admin1_code":"5",
    "gn:admin2_code":"31",
    "gn:asciiname":"Moel Baxil",
    "gn:country_code":"MX",
    "gn:dem":1343,
    "gn:feature_class":"P",
    "gn:feature_code":"PPL",
    "gn:name":"Moel Baxil",
    "gn:population":42,
    "gn:timezone":"America/Mexico_City",
    "iso:country":"MX",
    "wof:name":"Moel Baxil",
    "wof:placetype":"locality",
    "wof:population":42
},
  "geometry": {"coordinates":[-92.31999999999999,17.11],"type":"Point"}
}