{
  "type": "Feature",
  "properties": {
    "gn:admin1_code":"7.0",
    "gn:asciiname":"El Chilpitin",
    "gn:country_code":"MX",
    "gn:dem":1081,
    "gn:feature_class":"P",
    "gn:feature_code":"PPL",
    "gn:name":"El Chilpit\u00edn",
    "gn:population":0,
    "gn:timezone":"America/Monterrey",
    "iso:country":"MX",
    "name:spa_x_preferred":[
        "El Chilpit\u00edn"
    ],
    "wof:name":"El Chilpitin",
    "wof:placetype":"locality"
},
  "geometry": {"coordinates":[-101.29653999999999,26.80846],"type":"Point"}
}