{
  "type": "Feature",
  "properties": {
    "gn:admin1_code":"11.0",
    "gn:admin2_code":"32.0",
    "gn:asciiname":"Huisachal",
    "gn:country_code":"MX",
    "gn:dem":2038,
    "gn:feature_class":"P",
    "gn:feature_code":"PPL",
    "gn:name":"Huisachal",
    "gn:population":0,
    "gn:timezone":"America/Mexico_City",
    "iso:country":"MX",
    "name:und_x_variant":[
        "Huizachal",
        "Huisachal"
    ],
    "wof:name":"Huisachal",
    "wof:placetype":"locality"
},
  "geometry": {"coordinates":[-100.4396,21.10317],"type":"Point"}
}