{
  "type": "Feature",
  "properties": {
    "gn:admin1_code":"18.0",
    "gn:admin2_code":"9.0",
    "gn:asciiname":"El Nogal",
    "gn:country_code":"MX",
    "gn:dem":917,
    "gn:feature_class":"P",
    "gn:feature_code":"PPL",
    "gn:name":"El Nogal",
    "gn:population":2,
    "gn:timezone":"America/Mazatlan",
    "iso:country":"MX",
    "name:spa_x_preferred":[
        "El Nogal"
    ],
    "wof:name":"El Nogal",
    "wof:placetype":"locality",
    "wof:population":2
},
  "geometry": {"coordinates":[-104.49612,21.73402],"type":"Point"}
}