{
  "type": "Feature",
  "properties": {
    "gn:admin1_code":"17",
    "gn:admin2_code":"26.0",
    "gn:asciiname":"Colonia Jerico",
    "gn:country_code":"MX",
    "gn:dem":1771,
    "gn:feature_class":"P",
    "gn:feature_code":"PPL",
    "gn:name":"Colonia Jeric\u00f3",
    "gn:population":133,
    "gn:timezone":"America/Mexico_City",
    "iso:country":"MX",
    "name:und_x_variant":[
        "Colonia Jeric\u00f3"
    ],
    "wof:name":"Colonia Jerico",
    "wof:placetype":"locality",
    "wof:population":133
},
  "geometry": {"coordinates":[-98.93087,18.95876],"type":"Point"}
}