{
  "type": "Feature",
  "properties": {
    "gn:admin1_code":"24",
    "gn:admin2_code":"2",
    "gn:asciiname":"El Pelillo",
    "gn:country_code":"MX",
    "gn:dem":889,
    "gn:feature_class":"P",
    "gn:feature_code":"PPL",
    "gn:name":"El Pelillo",
    "gn:population":15,
    "gn:timezone":"America/Mexico_City",
    "iso:country":"MX",
    "wof:name":"El Pelillo",
    "wof:placetype":"locality",
    "wof:population":15
},
  "geometry": {"coordinates":[-99.4325,21.98778],"type":"Point"}
}