{
  "type": "Feature",
  "properties": {
    "gn:admin1_code":"6.0",
    "gn:admin2_code":"28.0",
    "gn:asciiname":"El Huerfano",
    "gn:country_code":"MX",
    "gn:dem":1023,
    "gn:feature_class":"P",
    "gn:feature_code":"PPL",
    "gn:name":"El Hu\u00e9rfano",
    "gn:population":0,
    "gn:timezone":"America/Chihuahua",
    "iso:country":"MX",
    "wof:name":"El Huerfano",
    "wof:placetype":"locality"
},
  "geometry": {"coordinates":[-105.06667,30.56667],"type":"Point"}
}