{
  "type": "Feature",
  "properties": {
    "gn:admin1_code":"32",
    "gn:admin2_code":"19.0",
    "gn:asciiname":"El Gueenchillo",
    "gn:country_code":"MX",
    "gn:dem":1597,
    "gn:feature_class":"P",
    "gn:feature_code":"PPL",
    "gn:name":"El G\u00fcenchillo",
    "gn:population":0,
    "gn:timezone":"America/Mexico_City",
    "iso:country":"MX",
    "name:spa_x_preferred":[
        "El G\u00fcenchillo"
    ],
    "wof:name":"El Gueenchillo",
    "wof:placetype":"locality"
},
  "geometry": {"coordinates":[-103.06735,21.61642],"type":"Point"}
}