{
  "type": "Feature",
  "properties": {
    "gn:admin1_code":"6",
    "gn:admin2_code":"11.0",
    "gn:asciiname":"La Ternera",
    "gn:country_code":"MX",
    "gn:dem":1534,
    "gn:feature_class":"P",
    "gn:feature_code":"PPL",
    "gn:name":"La Ternera",
    "gn:population":2,
    "gn:timezone":"America/Chihuahua",
    "iso:country":"MX",
    "name:spa_x_preferred":[
        "La Ternera"
    ],
    "wof:name":"La Ternera",
    "wof:placetype":"locality",
    "wof:population":2
},
  "geometry": {"coordinates":[-104.15472,27.73053],"type":"Point"}
}