{
  "type": "Feature",
  "properties": {
    "gn:admin1_code":"30",
    "gn:admin2_code":"139.0",
    "gn:asciiname":"La Piedra",
    "gn:country_code":"MX",
    "gn:dem":8,
    "gn:feature_class":"P",
    "gn:feature_code":"PPL",
    "gn:name":"La Piedra",
    "gn:population":8,
    "gn:timezone":"America/Mexico_City",
    "iso:country":"MX",
    "wof:name":"La Piedra",
    "wof:placetype":"locality",
    "wof:population":8
},
  "geometry": {"coordinates":[-95.52833,18.58167000000001],"type":"Point"}
}