{
  "type": "Feature",
  "properties": {
    "gn:admin1_code":"30",
    "gn:admin2_code":"123.0",
    "gn:asciiname":"El Lucero de Panuco",
    "gn:country_code":"MX",
    "gn:dem":24,
    "gn:feature_class":"P",
    "gn:feature_code":"PPL",
    "gn:name":"El Lucero de P\u00e1nuco",
    "gn:population":6,
    "gn:timezone":"America/Mexico_City",
    "iso:country":"MX",
    "name:und_x_variant":[
        "El Lucero de P\u00e1nuco"
    ],
    "wof:name":"El Lucero de Panuco",
    "wof:placetype":"locality",
    "wof:population":6
},
  "geometry": {"coordinates":[-98.04833000000001,22.29972],"type":"Point"}
}