{
  "type": "Feature",
  "properties": {
    "gn:admin1_code":"11",
    "gn:admin2_code":"14.0",
    "gn:asciiname":"Bordo de San Pedro",
    "gn:country_code":"MX",
    "gn:dem":1956,
    "gn:feature_class":"P",
    "gn:feature_code":"PPL",
    "gn:name":"Bordo de San Pedro",
    "gn:population":94,
    "gn:timezone":"America/Mexico_City",
    "iso:country":"MX",
    "wof:name":"Bordo de San Pedro",
    "wof:placetype":"locality",
    "wof:population":94
},
  "geometry": {"coordinates":[-100.8475,21.17361],"type":"Point"}
}