{
  "type": "Feature",
  "properties": {
    "gn:admin1_code":"25.0",
    "gn:admin2_code":"11.0",
    "gn:asciiname":"Tamazula Tercero",
    "gn:country_code":"MX",
    "gn:dem":7,
    "gn:feature_class":"P",
    "gn:feature_code":"PPL",
    "gn:name":"Tamazula Tercero",
    "gn:population":0,
    "gn:timezone":"America/Mazatlan",
    "iso:country":"MX",
    "name:spa_x_preferred":[
        "Tamazula Tercero"
    ],
    "wof:name":"Tamazula Tercero",
    "wof:placetype":"locality"
},
  "geometry": {"coordinates":[-108.55503,25.43198],"type":"Point"}
}