{
  "type": "Feature",
  "properties": {
    "gn:admin1_code":"13",
    "gn:admin2_code":"53.0",
    "gn:asciiname":"La Segunda Rancheria",
    "gn:country_code":"MX",
    "gn:dem":1423,
    "gn:feature_class":"P",
    "gn:feature_code":"PPL",
    "gn:name":"La Segunda Rancher\u00eda",
    "gn:population":91,
    "gn:timezone":"America/Mexico_City",
    "iso:country":"MX",
    "name:und_x_variant":[
        "La Segunda Rancher\u00eda"
    ],
    "wof:name":"La Segunda Rancheria",
    "wof:placetype":"locality",
    "wof:population":91
},
  "geometry": {"coordinates":[-98.15804,20.42667],"type":"Point"}
}