{
  "type": "Feature",
  "properties": {
    "gn:admin1_code":"30",
    "gn:admin2_code":"189.0",
    "gn:asciiname":"Las Gaviotas",
    "gn:country_code":"MX",
    "gn:dem":8,
    "gn:feature_class":"P",
    "gn:feature_code":"PPL",
    "gn:name":"Las Gaviotas",
    "gn:population":5,
    "gn:timezone":"America/Mexico_City",
    "iso:country":"MX",
    "wof:name":"Las Gaviotas",
    "wof:placetype":"locality",
    "wof:population":5
},
  "geometry": {"coordinates":[-97.45806,20.90222],"type":"Point"}
}