{
  "type": "Feature",
  "properties": {
    "gn:admin1_code":"11",
    "gn:admin2_code":"33.0",
    "gn:asciiname":"Nuevo San Luis",
    "gn:country_code":"MX",
    "gn:dem":2003,
    "gn:feature_class":"P",
    "gn:feature_code":"PPL",
    "gn:name":"Nuevo San Luis",
    "gn:population":260,
    "gn:timezone":"America/Mexico_City",
    "iso:country":"MX",
    "wof:name":"Nuevo San Luis",
    "wof:placetype":"locality",
    "wof:population":260
},
  "geometry": {"coordinates":[-100.53639,21.29639],"type":"Point"}
}