{
  "type": "Feature",
  "properties": {
    "gn:admin1_code":"5",
    "gn:admin2_code":"59.0",
    "gn:asciiname":"Cantajal",
    "gn:country_code":"MX",
    "gn:dem":1016,
    "gn:feature_class":"P",
    "gn:feature_code":"PPL",
    "gn:name":"Cantajal",
    "gn:population":4,
    "gn:timezone":"America/Mexico_City",
    "iso:country":"MX",
    "wof:name":"Cantajal",
    "wof:placetype":"locality",
    "wof:population":4
},
  "geometry": {"coordinates":[-92.11583,16.90667],"type":"Point"}
}