{
  "type": "Feature",
  "properties": {
    "gn:admin1_code":"6",
    "gn:admin2_code":"65.0",
    "gn:asciiname":"Carrillo",
    "gn:country_code":"MX",
    "gn:dem":1850,
    "gn:feature_class":"P",
    "gn:feature_code":"PPL",
    "gn:name":"Carrillo",
    "gn:population":6,
    "gn:timezone":"America/Chihuahua",
    "iso:country":"MX",
    "name:cat_x_preferred":[
        "Carrillo"
    ],
    "name:ceb_x_preferred":[
        "Carrillo"
    ],
    "name:deu_x_preferred":[
        "Carrillo"
    ],
    "name:fra_x_preferred":[
        "Carrillo"
    ],
    "name:glg_x_preferred":[
        "Carrillo"
    ],
    "name:ita_x_preferred":[
        "Carrillo"
    ],
    "name:nds_x_preferred":[
        "Carrillo"
    ],
    "name:ron_x_preferred":[
        "Carrillo"
    ],
    "name:rus_x_preferred":[
        "\u041a\u0430\u0440\u0440\u0438\u043b\u044c\u043e"
    ],
    "name:spa_x_preferred":[
        "Carrillo"
    ],
    "name:swe_x_preferred":[
        "Carrillo"
    ],
    "name:war_x_preferred":[
        "Carrillo"
    ],
    "wof:name":"Carrillo",
    "wof:placetype":"locality",
    "wof:population":6
},
  "geometry": {"coordinates":[-107.94213999999999,27.2627],"type":"Point"}
}