{
  "type": "Feature",
  "properties": {
    "gn:admin1_code":"14",
    "gn:admin2_code":"97.0",
    "gn:asciiname":"La Fortuna [Fraccionamiento]",
    "gn:country_code":"MX",
    "gn:dem":1561,
    "gn:feature_class":"P",
    "gn:feature_code":"PPL",
    "gn:name":"La Fortuna [Fraccionamiento]",
    "gn:population":573,
    "gn:timezone":"America/Mexico_City",
    "iso:country":"MX",
    "wof:name":"La Fortuna [Fraccionamiento]",
    "wof:placetype":"locality",
    "wof:population":573
},
  "geometry": {"coordinates":[-103.39583,20.48472000000001],"type":"Point"}
}