{
  "type": "Feature",
  "properties": {
    "gn:admin1_code":"10.0",
    "gn:admin2_code":"29.0",
    "gn:asciiname":"Cerro Blanco",
    "gn:country_code":"MX",
    "gn:dem":1528,
    "gn:feature_class":"P",
    "gn:feature_code":"PPL",
    "gn:name":"Cerro Blanco",
    "gn:population":0,
    "gn:timezone":"America/Monterrey",
    "iso:country":"MX",
    "wof:name":"Cerro Blanco",
    "wof:placetype":"locality"
},
  "geometry": {"coordinates":[-104.25,25.35],"type":"Point"}
}