{
  "type": "Feature",
  "properties": {
    "gn:admin1_code":"20",
    "gn:admin2_code":"516.0",
    "gn:asciiname":"Acahual",
    "gn:country_code":"MX",
    "gn:dem":1190,
    "gn:feature_class":"P",
    "gn:feature_code":"PPL",
    "gn:name":"Acahual",
    "gn:population":117,
    "gn:timezone":"America/Mexico_City",
    "iso:country":"MX",
    "wof:name":"Acahual",
    "wof:placetype":"locality",
    "wof:population":117
},
  "geometry": {"coordinates":[-97.23361,16.58472],"type":"Point"}
}