{
  "type": "Feature",
  "properties": {
    "gn:admin1_code":"19",
    "gn:admin2_code":"42.0",
    "gn:asciiname":"Los Gomez",
    "gn:country_code":"MX",
    "gn:dem":198,
    "gn:feature_class":"P",
    "gn:feature_code":"PPL",
    "gn:name":"Los G\u00f3mez",
    "gn:population":0,
    "gn:timezone":"America/Monterrey",
    "iso:country":"MX",
    "name:spa_x_preferred":[
        "G\u00f3mez Ochoa"
    ],
    "name:spa_x_variant":[
        "Los G\u00f3mez"
    ],
    "wof:name":"Los Gomez",
    "wof:placetype":"locality"
},
  "geometry": {"coordinates":[-99.60912999999999,25.81243],"type":"Point"}
}