{
  "type": "Feature",
  "properties": {
    "gn:admin1_code":"10.0",
    "gn:admin2_code":"26.0",
    "gn:asciiname":"Chavarria de Abajo",
    "gn:country_code":"MX",
    "gn:dem":2424,
    "gn:feature_class":"P",
    "gn:feature_code":"PPL",
    "gn:name":"Chavarr\u00eda de Abajo",
    "gn:population":4,
    "gn:timezone":"America/Monterrey",
    "iso:country":"MX",
    "wof:name":"Chavarria de Abajo",
    "wof:placetype":"locality",
    "wof:population":4
},
  "geometry": {"coordinates":[-105.53286,24.36785],"type":"Point"}
}