{
  "type": "Feature",
  "properties": {
    "gn:admin1_code":"18",
    "gn:admin2_code":"19.0",
    "gn:asciiname":"La Ladrillera",
    "gn:country_code":"MX",
    "gn:dem":1317,
    "gn:feature_class":"P",
    "gn:feature_code":"PPL",
    "gn:name":"La Ladrillera",
    "gn:population":7,
    "gn:timezone":"America/Mazatlan",
    "iso:country":"MX",
    "wof:name":"La Ladrillera",
    "wof:placetype":"locality",
    "wof:population":7
},
  "geometry": {"coordinates":[-104.12972000000001,21.39694],"type":"Point"}
}