{
  "type": "Feature",
  "properties": {
    "gn:admin1_code":"6",
    "gn:admin2_code":"20.0",
    "gn:asciiname":"San Agustin",
    "gn:country_code":"MX",
    "gn:dem":800,
    "gn:feature_class":"P",
    "gn:feature_code":"PPL",
    "gn:name":"San Agust\u00edn",
    "gn:population":0,
    "gn:timezone":"America/Chihuahua",
    "iso:country":"MX",
    "name:und_x_variant":[
        "San Agustins",
        "San Agust\u00edn"
    ],
    "wof:name":"San Agustin",
    "wof:placetype":"locality"
},
  "geometry": {"coordinates":[-108.5878,27.57984],"type":"Point"}
}