{
  "type": "Feature",
  "properties": {
    "gn:admin1_code":"11",
    "gn:admin2_code":"46",
    "gn:asciiname":"Santa Rosa",
    "gn:country_code":"MX",
    "gn:dem":1751,
    "gn:feature_class":"P",
    "gn:feature_code":"PPL",
    "gn:name":"Santa Rosa",
    "gn:population":14,
    "gn:timezone":"America/Mexico_City",
    "iso:country":"MX",
    "wof:name":"Santa Rosa",
    "wof:placetype":"locality",
    "wof:population":14
},
  "geometry": {"coordinates":[-101.17778,20.21722],"type":"Point"}
}