{
  "type": "Feature",
  "properties": {
    "gn:admin1_code":"30.0",
    "gn:admin2_code":"155.0",
    "gn:asciiname":"Huizachal",
    "gn:country_code":"MX",
    "gn:dem":108,
    "gn:feature_class":"P",
    "gn:feature_code":"PPL",
    "gn:name":"Huizachal",
    "gn:population":208,
    "gn:timezone":"America/Mexico_City",
    "iso:country":"MX",
    "name:spa_x_preferred":[
        "Huizachal"
    ],
    "wof:name":"Huizachal",
    "wof:placetype":"locality",
    "wof:population":208
},
  "geometry": {"coordinates":[-98.20833,21.43111],"type":"Point"}
}