{
  "type": "Feature",
  "properties": {
    "gn:admin1_code":"5",
    "gn:admin2_code":"59.0",
    "gn:asciiname":"Nuevo Pedregal",
    "gn:country_code":"MX",
    "gn:dem":111,
    "gn:feature_class":"P",
    "gn:feature_code":"PPL",
    "gn:name":"Nuevo Pedregal",
    "gn:population":197,
    "gn:timezone":"America/Mexico_City",
    "iso:country":"MX",
    "wof:name":"Nuevo Pedregal",
    "wof:placetype":"locality",
    "wof:population":197
},
  "geometry": {"coordinates":[-91.16500000000001,16.96306],"type":"Point"}
}