{
  "type": "Feature",
  "properties": {
    "gn:admin1_code":"22",
    "gn:admin2_code":"8.0",
    "gn:asciiname":"Neveria Sector Norte (Neverias los Martinez)",
    "gn:country_code":"MX",
    "gn:dem":2353,
    "gn:feature_class":"P",
    "gn:feature_code":"PPL",
    "gn:name":"Never\u00eda Sector Norte (Never\u00edas los Mart\u00ednez)",
    "gn:population":134,
    "gn:timezone":"America/Mexico_City",
    "iso:country":"MX",
    "name:und_x_variant":[
        "Never\u00eda Sector Norte (Never\u00edas los Mart\u00ednez)"
    ],
    "wof:name":"Neveria Sector Norte (Neverias los Martinez)",
    "wof:placetype":"locality",
    "wof:population":134
},
  "geometry": {"coordinates":[-100.27861,20.33861],"type":"Point"}
}