{
  "type": "Feature",
  "properties": {
    "gn:admin1_code":"7",
    "gn:admin2_code":"33.0",
    "gn:asciiname":"La Lucecita (La Luz Nueva)",
    "gn:country_code":"MX",
    "gn:dem":1099,
    "gn:feature_class":"P",
    "gn:feature_code":"PPL",
    "gn:name":"La Lucecita (La Luz Nueva)",
    "gn:population":57,
    "gn:timezone":"America/Monterrey",
    "iso:country":"MX",
    "wof:name":"La Lucecita (La Luz Nueva)",
    "wof:placetype":"locality",
    "wof:population":57
},
  "geometry": {"coordinates":[-102.91646,25.70778],"type":"Point"}
}