{
  "type": "Feature",
  "properties": {
    "gn:admin1_code":"32",
    "gn:admin2_code":"3.0",
    "gn:asciiname":"Charcuelos",
    "gn:country_code":"MX",
    "gn:dem":2148,
    "gn:feature_class":"P",
    "gn:feature_code":"PPL",
    "gn:name":"Charcuelos",
    "gn:population":85,
    "gn:timezone":"America/Mexico_City",
    "iso:country":"MX",
    "wof:name":"Charcuelos",
    "wof:placetype":"locality",
    "wof:population":85
},
  "geometry": {"coordinates":[-103.40361,21.80583],"type":"Point"}
}