{
  "type": "Feature",
  "properties": {
    "gn:admin1_code":"3.0",
    "gn:admin2_code":"1.0",
    "gn:asciiname":"Ignacio Zaragoza",
    "gn:country_code":"MX",
    "gn:dem":30,
    "gn:feature_class":"P",
    "gn:feature_code":"PPL",
    "gn:name":"Ignacio Zaragoza",
    "gn:population":0,
    "gn:timezone":"America/Mazatlan",
    "iso:country":"MX",
    "name:ara_x_preferred":[
        "\u0627\u062c\u0646\u0627\u0633\u064a\u0648 \u0633\u0627\u0631\u0627\u062c\u0648\u0632\u0627"
    ],
    "name:cat_x_preferred":[
        "Ignacio Zaragoza"
    ],
    "name:ces_x_preferred":[
        "Ignacio Zaragoza"
    ],
    "name:deu_x_preferred":[
        "Ignacio Zaragoza"
    ],
    "name:fra_x_preferred":[
        "Ignacio Zaragoza"
    ],
    "name:hun_x_preferred":[
        "Ignacio Zaragoza"
    ],
    "name:ita_x_preferred":[
        "Ignacio Zaragoza"
    ],
    "name:kat_x_preferred":[
        "\u10d8\u10d2\u10dc\u10d0\u10e1\u10d8\u10dd \u10e1\u10d0\u10e0\u10d0\u10d2\u10dd\u10e1\u10d0"
    ],
    "name:kor_x_preferred":[
        "\uc774\uadf8\ub098\uc2dc\uc624 \uc0ac\ub77c\uace0\uc0ac"
    ],
    "name:msa_x_preferred":[
        "Ignacio Zaragoza"
    ],
    "name:nah_x_preferred":[
        "Ignacio Zaragoza"
    ],
    "name:nld_x_preferred":[
        "Ignacio Zaragoza"
    ],
    "name:nor_x_preferred":[
        "Ignacio Zaragoza"
    ],
    "name:pol_x_preferred":[
        "Ignacio Zaragoza"
    ],
    "name:por_x_preferred":[
        "Ignacio Zaragoza"
    ],
    "name:rus_x_preferred":[
        "\u0421\u0430\u0440\u0430\u0433\u043e\u0441\u0430"
    ],
    "name:spa_x_preferred":[
        "Ignacio Zaragoza"
    ],
    "name:spa_x_variant":[
        "Las Flores"
    ],
    "name:vie_x_preferred":[
        "General Zaragoza"
    ],
    "name:war_x_preferred":[
        "Ignacio Zaragoza"
    ],
    "wof:name":"Ignacio Zaragoza",
    "wof:placetype":"locality"
},
  "geometry": {"coordinates":[-111.84314000000001,25.39801],"type":"Point"}
}