{
  "type": "Feature",
  "properties": {
    "gn:admin1_code":"18.0",
    "gn:admin2_code":"19.0",
    "gn:asciiname":"El Limoncito",
    "gn:country_code":"MX",
    "gn:dem":1543,
    "gn:feature_class":"P",
    "gn:feature_code":"PPL",
    "gn:name":"El Limoncito",
    "gn:population":0,
    "gn:timezone":"America/Mexico_City",
    "iso:country":"MX",
    "name:spa_x_preferred":[
        "El Limoncito"
    ],
    "name:spa_x_variant":[
        "La Osa"
    ],
    "wof:name":"El Limoncito",
    "wof:placetype":"locality"
},
  "geometry": {"coordinates":[-104.00924999999999,21.42733],"type":"Point"}
}