{
  "type": "Feature",
  "properties": {
    "gn:admin1_code":"28",
    "gn:admin2_code":"11",
    "gn:asciiname":"Gomez Farias Dos",
    "gn:country_code":"MX",
    "gn:dem":126,
    "gn:feature_class":"P",
    "gn:feature_code":"PPL",
    "gn:name":"G\u00f3mez Far\u00edas Dos",
    "gn:population":49,
    "gn:timezone":"America/Monterrey",
    "iso:country":"MX",
    "name:und_x_variant":[
        "G\u00f3mez Far\u00edas Dos"
    ],
    "wof:name":"Gomez Farias Dos",
    "wof:placetype":"locality",
    "wof:population":49
},
  "geometry": {"coordinates":[-99.13639000000001,23.08889],"type":"Point"}
}