{
  "type": "Feature",
  "properties": {
    "gn:admin1_code":"25.0",
    "gn:admin2_code":"7.0",
    "gn:asciiname":"Mesa Redonda",
    "gn:country_code":"MX",
    "gn:dem":894,
    "gn:feature_class":"P",
    "gn:feature_code":"PPL",
    "gn:name":"Mesa Redonda",
    "gn:population":0,
    "gn:timezone":"America/Mazatlan",
    "iso:country":"MX",
    "name:spa_x_preferred":[
        "Mesa Redonda"
    ],
    "wof:name":"Mesa Redonda",
    "wof:placetype":"locality"
},
  "geometry": {"coordinates":[-108.01843,26.69156],"type":"Point"}
}