{
  "type": "Feature",
  "properties": {
    "gn:admin1_code":"16",
    "gn:admin2_code":"99.0",
    "gn:asciiname":"Plaza de Gallos",
    "gn:country_code":"MX",
    "gn:dem":1330,
    "gn:feature_class":"P",
    "gn:feature_code":"PPL",
    "gn:name":"Plaza de Gallos",
    "gn:population":0,
    "gn:timezone":"America/Mexico_City",
    "iso:country":"MX",
    "name:spa_x_preferred":[
        "Plaza de Gallos"
    ],
    "wof:name":"Plaza de Gallos",
    "wof:placetype":"locality"
},
  "geometry": {"coordinates":[-100.7111,19.33458],"type":"Point"}
}