{
  "type": "Feature",
  "properties": {
    "gn:admin1_code":"10",
    "gn:admin2_code":"32",
    "gn:asciiname":"San Agustin del Fresno (El Hipazote)",
    "gn:country_code":"MX",
    "gn:dem":1996,
    "gn:feature_class":"P",
    "gn:feature_code":"PPL",
    "gn:name":"San Agust\u00edn del Fresno (El Hipazote)",
    "gn:population":15,
    "gn:timezone":"America/Monterrey",
    "iso:country":"MX",
    "name:und_x_variant":[
        "San Agust\u00edn del Fresno (El Hipazote)"
    ],
    "wof:name":"San Agustin del Fresno (El Hipazote)",
    "wof:placetype":"locality",
    "wof:population":15
},
  "geometry": {"coordinates":[-105.41228,24.76805],"type":"Point"}
}