{
  "type": "Feature",
  "properties": {
    "gn:admin1_code":"4",
    "gn:admin2_code":"2.0",
    "gn:asciiname":"Cayal",
    "gn:country_code":"MX",
    "gn:dem":44,
    "gn:feature_class":"P",
    "gn:feature_code":"PPL",
    "gn:name":"Cayal",
    "gn:population":0,
    "gn:timezone":"America/Merida",
    "iso:country":"MX",
    "name:spa_x_preferred":[
        "San Antonio Cayal"
    ],
    "name:spa_x_variant":[
        "Cayal"
    ],
    "wof:name":"Cayal",
    "wof:placetype":"locality"
},
  "geometry": {"coordinates":[-90.17542,19.74215],"type":"Point"}
}