{
  "type": "Feature",
  "properties": {
    "gn:admin1_code":"26",
    "gn:asciiname":"La Cebolla",
    "gn:country_code":"MX",
    "gn:dem":1629,
    "gn:feature_class":"P",
    "gn:feature_code":"PPL",
    "gn:name":"La Cebolla",
    "gn:population":0,
    "gn:timezone":"America/Chihuahua",
    "iso:country":"MX",
    "name:spa_x_preferred":[
        "La Cebolla"
    ],
    "wof:name":"La Cebolla",
    "wof:placetype":"locality"
},
  "geometry": {"coordinates":[-109.0645,28.28401],"type":"Point"}
}