{
  "type": "Feature",
  "properties": {
    "gn:admin1_code":"20",
    "gn:admin2_code":"31",
    "gn:asciiname":"Rancho Zopilote",
    "gn:country_code":"MX",
    "gn:dem":1973,
    "gn:feature_class":"P",
    "gn:feature_code":"PPL",
    "gn:name":"Rancho Zopilote",
    "gn:population":32,
    "gn:timezone":"America/Mexico_City",
    "iso:country":"MX",
    "wof:name":"Rancho Zopilote",
    "wof:placetype":"locality",
    "wof:population":32
},
  "geometry": {"coordinates":[-96.02889,16.97222],"type":"Point"}
}