{
  "type": "Feature",
  "properties": {
    "gn:admin1_code":"19",
    "gn:admin2_code":"4.0",
    "gn:asciiname":"Arco Iris",
    "gn:country_code":"MX",
    "gn:dem":446,
    "gn:feature_class":"P",
    "gn:feature_code":"PPL",
    "gn:name":"Arco Iris",
    "gn:population":0,
    "gn:timezone":"America/Monterrey",
    "iso:country":"MX",
    "name:spa_x_preferred":[
        "Arco Iris"
    ],
    "wof:name":"Arco Iris",
    "wof:placetype":"locality"
},
  "geometry": {"coordinates":[-100.0138,25.28792],"type":"Point"}
}