{
  "type": "Feature",
  "properties": {
    "gn:admin1_code":"11",
    "gn:admin2_code":"29",
    "gn:asciiname":"San Rafael",
    "gn:country_code":"MX",
    "gn:dem":2014,
    "gn:feature_class":"P",
    "gn:feature_code":"PPL",
    "gn:name":"San Rafael",
    "gn:population":17,
    "gn:timezone":"America/Mexico_City",
    "iso:country":"MX",
    "wof:name":"San Rafael",
    "wof:placetype":"locality",
    "wof:population":17
},
  "geometry": {"coordinates":[-100.70193999999999,21.39389],"type":"Point"}
}