{
  "type": "Feature",
  "properties": {
    "gn:admin1_code":"10",
    "gn:admin2_code":"18.0",
    "gn:asciiname":"Potrerillas",
    "gn:country_code":"MX",
    "gn:dem":1592,
    "gn:feature_class":"P",
    "gn:feature_code":"PPL",
    "gn:name":"Potrerillas",
    "gn:population":0,
    "gn:timezone":"America/Monterrey",
    "iso:country":"MX",
    "name:spa_x_preferred":[
        "Potrerillas"
    ],
    "wof:name":"Potrerillas",
    "wof:placetype":"locality"
},
  "geometry": {"coordinates":[-104.87748000000001,25.35596],"type":"Point"}
}