{
  "type": "Feature",
  "properties": {
    "gn:admin1_code":"5",
    "gn:admin2_code":"59.0",
    "gn:asciiname":"El Censo",
    "gn:country_code":"MX",
    "gn:dem":680,
    "gn:feature_class":"P",
    "gn:feature_code":"PPL",
    "gn:name":"El Censo",
    "gn:population":0,
    "gn:timezone":"America/Mexico_City",
    "iso:country":"MX",
    "name:spa_x_preferred":[
        "El Censo"
    ],
    "wof:name":"El Censo",
    "wof:placetype":"locality"
},
  "geometry": {"coordinates":[-91.55988000000001,16.86287],"type":"Point"}
}