{
  "type": "Feature",
  "properties": {
    "gn:admin1_code":"6",
    "gn:admin2_code":"27.0",
    "gn:asciiname":"La Reforma",
    "gn:country_code":"MX",
    "gn:dem":2484,
    "gn:feature_class":"P",
    "gn:feature_code":"PPL",
    "gn:name":"La Reforma",
    "gn:population":0,
    "gn:timezone":"America/Chihuahua",
    "iso:country":"MX",
    "name:cym_x_preferred":[
        "La Reforma"
    ],
    "name:nld_x_preferred":[
        "Reforma"
    ],
    "name:por_x_preferred":[
        "La Reforma"
    ],
    "name:und_x_variant":[
        "Reforma",
        "La Reforma"
    ],
    "wof:name":"La Reforma",
    "wof:placetype":"locality"
},
  "geometry": {"coordinates":[-107.25275999999999,26.83911],"type":"Point"}
}