{
  "type": "Feature",
  "properties": {
    "gn:admin1_code":"30",
    "gn:admin2_code":"70.0",
    "gn:asciiname":"Monterrosa",
    "gn:country_code":"MX",
    "gn:dem":27,
    "gn:feature_class":"P",
    "gn:feature_code":"PPL",
    "gn:name":"Monterrosa",
    "gn:population":266,
    "gn:timezone":"America/Mexico_City",
    "iso:country":"MX",
    "wof:name":"Monterrosa",
    "wof:placetype":"locality",
    "wof:population":266
},
  "geometry": {"coordinates":[-94.67556,17.56944],"type":"Point"}
}