{
  "type": "Feature",
  "properties": {
    "gn:admin1_code":"25",
    "gn:admin2_code":"6.0",
    "gn:asciiname":"Campo La Cobra",
    "gn:country_code":"MX",
    "gn:dem":25,
    "gn:feature_class":"P",
    "gn:feature_code":"PPL",
    "gn:name":"Campo La Cobra",
    "gn:population":0,
    "gn:timezone":"America/Mazatlan",
    "iso:country":"MX",
    "name:spa_x_preferred":[
        "Campo La Cobra"
    ],
    "wof:name":"Campo La Cobra",
    "wof:placetype":"locality"
},
  "geometry": {"coordinates":[-107.68844,24.9208],"type":"Point"}
}