{
  "type": "Feature",
  "properties": {
    "gn:admin1_code":"16",
    "gn:admin2_code":"53",
    "gn:asciiname":"La Laguna (Los Caracoles)",
    "gn:country_code":"MX",
    "gn:dem":2315,
    "gn:feature_class":"P",
    "gn:feature_code":"PPL",
    "gn:name":"La Laguna (Los Caracoles)",
    "gn:population":13,
    "gn:timezone":"America/Mexico_City",
    "iso:country":"MX",
    "wof:name":"La Laguna (Los Caracoles)",
    "wof:placetype":"locality",
    "wof:population":13
},
  "geometry": {"coordinates":[-101.17889,19.58583],"type":"Point"}
}