{
  "type": "Feature",
  "properties": {
    "gn:admin1_code":"15",
    "gn:admin2_code":"110.0",
    "gn:asciiname":"Loma Bonita",
    "gn:country_code":"MX",
    "gn:dem":1660,
    "gn:feature_class":"P",
    "gn:feature_code":"PPL",
    "gn:name":"Loma Bonita",
    "gn:population":2244,
    "gn:timezone":"America/Mexico_City",
    "iso:country":"MX",
    "wof:name":"Loma Bonita",
    "wof:placetype":"locality",
    "wof:population":2244
},
  "geometry": {"coordinates":[-100.215,19.18722],"type":"Point"}
}