{
  "type": "Feature",
  "properties": {
    "gn:admin1_code":"5",
    "gn:admin2_code":"19.0",
    "gn:asciiname":"Francisco J. Mujica",
    "gn:country_code":"MX",
    "gn:dem":679,
    "gn:feature_class":"P",
    "gn:feature_code":"PPL",
    "gn:name":"Francisco J. M\u00fajica",
    "gn:population":0,
    "gn:timezone":"America/Mexico_City",
    "iso:country":"MX",
    "name:spa_x_preferred":[
        "Francisco J. M\u00fajica"
    ],
    "name:und_x_variant":[
        "Francisco J. M\u00fagica"
    ],
    "wof:name":"Francisco J. Mujica",
    "wof:placetype":"locality"
},
  "geometry": {"coordinates":[-92.21845,16.0514],"type":"Point"}
}