{
  "type": "Feature",
  "properties": {
    "gn:admin1_code":"30",
    "gn:admin2_code":"147.0",
    "gn:asciiname":"Benito Juarez",
    "gn:country_code":"MX",
    "gn:dem":2231,
    "gn:feature_class":"P",
    "gn:feature_code":"PPL",
    "gn:name":"Benito Ju\u00e1rez",
    "gn:population":223,
    "gn:timezone":"America/Mexico_City",
    "iso:country":"MX",
    "name:und_x_variant":[
        "Benito Ju\u00e1rez"
    ],
    "wof:name":"Benito Juarez",
    "wof:placetype":"locality",
    "wof:population":223
},
  "geometry": {"coordinates":[-97.15722,18.75361],"type":"Point"}
}