{
  "type": "Feature",
  "properties": {
    "gn:admin1_code":"32",
    "gn:admin2_code":"36.0",
    "gn:asciiname":"Rancho el Trebol (Ingeniro Alfonso Tamez Mireles)",
    "gn:country_code":"MX",
    "gn:dem":2049,
    "gn:feature_class":"P",
    "gn:feature_code":"PPL",
    "gn:name":"Rancho el Tr\u00e9bol (Ingeniro Alfonso T\u00e1mez Mireles)",
    "gn:population":7,
    "gn:timezone":"America/Mexico_City",
    "iso:country":"MX",
    "name:und_x_variant":[
        "Rancho el Tr\u00e9bol (Ingeniro Alfonso T\u00e1mez Mireles)"
    ],
    "wof:name":"Rancho el Trebol (Ingeniro Alfonso Tamez Mireles)",
    "wof:placetype":"locality",
    "wof:population":7
},
  "geometry": {"coordinates":[-102.24527999999999,22.57],"type":"Point"}
}