{
  "type": "Feature",
  "properties": {
    "gn:admin1_code":"5",
    "gn:admin2_code":"65.0",
    "gn:asciiname":"Cerro Norte",
    "gn:country_code":"MX",
    "gn:dem":358,
    "gn:feature_class":"P",
    "gn:feature_code":"PPL",
    "gn:name":"Cerro Norte",
    "gn:population":0,
    "gn:timezone":"America/Mexico_City",
    "iso:country":"MX",
    "wof:name":"Cerro Norte",
    "wof:placetype":"locality"
},
  "geometry": {"coordinates":[-92.10833,17.49167000000001],"type":"Point"}
}