{
  "type": "Feature",
  "properties": {
    "gn:admin1_code":"6",
    "gn:admin2_code":"8",
    "gn:asciiname":"Tierra Blanca",
    "gn:country_code":"MX",
    "gn:dem":2130,
    "gn:feature_class":"P",
    "gn:feature_code":"PPL",
    "gn:name":"Tierra Blanca",
    "gn:population":16,
    "gn:timezone":"America/Chihuahua",
    "iso:country":"MX",
    "name:ceb_x_preferred":[
        "Tierra Blanca"
    ],
    "name:deu_x_preferred":[
        "Tierra Blanca"
    ],
    "name:ita_x_preferred":[
        "Tierra Blanca"
    ],
    "name:pol_x_preferred":[
        "Tierra Blanca"
    ],
    "name:por_x_preferred":[
        "Tierra Blanca"
    ],
    "name:sco_x_preferred":[
        "Tierra Blanca"
    ],
    "name:spa_x_preferred":[
        "Tierra Blanca"
    ],
    "name:swe_x_preferred":[
        "Tierra Blanca"
    ],
    "wof:name":"Tierra Blanca",
    "wof:placetype":"locality",
    "wof:population":16
},
  "geometry": {"coordinates":[-107.57156999999999,27.08382000000001],"type":"Point"}
}