{
  "type": "Feature",
  "properties": {
    "gn:admin1_code":"3",
    "gn:admin2_code":"3",
    "gn:asciiname":"El Comitan",
    "gn:country_code":"MX",
    "gn:dem":5,
    "gn:feature_class":"P",
    "gn:feature_code":"PPL",
    "gn:name":"El Comit\u00e1n",
    "gn:population":35,
    "gn:timezone":"America/Mazatlan",
    "iso:country":"MX",
    "name:und_x_variant":[
        "El Comit\u00e1n"
    ],
    "wof:name":"El Comitan",
    "wof:placetype":"locality",
    "wof:population":35
},
  "geometry": {"coordinates":[-110.42361,24.13222],"type":"Point"}
}