{
  "type": "Feature",
  "properties": {
    "gn:admin1_code":"4.0",
    "gn:admin2_code":"3.0",
    "gn:asciiname":"Bonastre",
    "gn:country_code":"MX",
    "gn:dem":28,
    "gn:feature_class":"P",
    "gn:feature_code":"PPL",
    "gn:name":"Bonastre",
    "gn:population":0,
    "gn:timezone":"America/Merida",
    "iso:country":"MX",
    "name:arg_x_preferred":[
        "Bonastre"
    ],
    "name:cat_x_preferred":[
        "Bonastre"
    ],
    "name:ceb_x_preferred":[
        "Bonastre"
    ],
    "name:eus_x_preferred":[
        "Bonastre"
    ],
    "name:fas_x_preferred":[
        "\u0628\u0646\u0627\u0633\u062a\u0631\u0647"
    ],
    "name:fra_x_preferred":[
        "Bonastre"
    ],
    "name:glg_x_preferred":[
        "Bonastre"
    ],
    "name:hun_x_preferred":[
        "Bonastre"
    ],
    "name:hye_x_preferred":[
        "\u0532\u0578\u0576\u0561\u057d\u057f\u0580\u0565"
    ],
    "name:ita_x_preferred":[
        "Bonastre"
    ],
    "name:lat_x_preferred":[
        "Bonastre"
    ],
    "name:msa_x_preferred":[
        "Bonastre"
    ],
    "name:nld_x_preferred":[
        "Bonastre"
    ],
    "name:oci_x_preferred":[
        "Bonastre"
    ],
    "name:pol_x_preferred":[
        "Bonastre"
    ],
    "name:por_x_preferred":[
        "Bonastre"
    ],
    "name:rus_x_preferred":[
        "\u0411\u043e\u043d\u0430\u0441\u0442\u0440\u0435"
    ],
    "name:spa_x_preferred":[
        "Bonastre"
    ],
    "name:sqi_x_preferred":[
        "Bonastre"
    ],
    "name:swe_x_preferred":[
        "Bonastre"
    ],
    "name:ukr_x_preferred":[
        "\u0411\u0443\u043d\u0430\u0441\u0442\u0440\u0430"
    ],
    "name:uzb_x_preferred":[
        "Bonastre"
    ],
    "name:vie_x_preferred":[
        "Bonastre"
    ],
    "name:war_x_preferred":[
        "Bonastre"
    ],
    "name:zho_x_preferred":[
        "\u535a\u7eb3\u65af\u7279\u96f7"
    ],
    "wof:name":"Bonastre",
    "wof:placetype":"locality"
},
  "geometry": {"coordinates":[-91.19934000000001,18.27339],"type":"Point"}
}