{
  "type": "Feature",
  "properties": {
    "gn:admin1_code":"4.0",
    "gn:admin2_code":"3.0",
    "gn:asciiname":"Bonastre",
    "gn:country_code":"MX",
    "gn:dem":28,
    "gn:feature_class":"P",
    "gn:feature_code":"PPL",
    "gn:name":"Bonastre",
    "gn:population":0,
    "gn:timezone":"America/Merida",
    "iso:country":"MX",
    "name:spa_x_preferred":[
        "Bonastre"
    ],
    "wof:name":"Bonastre",
    "wof:placetype":"locality"
},
  "geometry": {"coordinates":[-91.19934000000001,18.27339],"type":"Point"}
}