{
  "type": "Feature",
  "properties": {
    "gn:admin1_code":"25",
    "gn:admin2_code":"4.0",
    "gn:asciiname":"Las Nanches",
    "gn:country_code":"MX",
    "gn:dem":95,
    "gn:feature_class":"P",
    "gn:feature_code":"PPL",
    "gn:name":"Las Nanches",
    "gn:population":0,
    "gn:timezone":"America/Mazatlan",
    "iso:country":"MX",
    "name:spa_x_preferred":[
        "Las Nanches"
    ],
    "wof:name":"Las Nanches",
    "wof:placetype":"locality"
},
  "geometry": {"coordinates":[-106.09102,23.34031],"type":"Point"}
}