{
  "type": "Feature",
  "properties": {
    "gn:admin1_code":"2",
    "gn:admin2_code":"1.0",
    "gn:asciiname":"Rancho Grande",
    "gn:country_code":"MX",
    "gn:dem":55,
    "gn:feature_class":"P",
    "gn:feature_code":"PPL",
    "gn:name":"Rancho Grande",
    "gn:population":0,
    "gn:timezone":"America/Tijuana",
    "iso:country":"MX",
    "name:fra_x_preferred":[
        "Rancho Grande"
    ],
    "name:ita_x_preferred":[
        "Rancho Grande"
    ],
    "name:spa_x_preferred":[
        "Rancho Grande"
    ],
    "name:swe_x_preferred":[
        "Rancho Grande"
    ],
    "name:urd_x_preferred":[
        "\u0631\u0627\u0646\u0686\u0648 \u06af\u0631\u0627\u0646\u062f\u06d2"
    ],
    "name:vie_x_preferred":[
        "Rancho Grande"
    ],
    "name:zho_x_preferred":[
        "\u862d\u55ac\u683c\u862d\u5fb7"
    ],
    "wof:name":"Rancho Grande",
    "wof:placetype":"locality"
},
  "geometry": {"coordinates":[-116.20335,31.08074],"type":"Point"}
}