{
  "type": "Feature",
  "properties": {
    "gn:admin1_code":"10.0",
    "gn:asciiname":"El Pando de la Burra",
    "gn:country_code":"MX",
    "gn:dem":2353,
    "gn:feature_class":"P",
    "gn:feature_code":"PPL",
    "gn:name":"El Pando de la Burra",
    "gn:population":0,
    "gn:timezone":"America/Monterrey",
    "iso:country":"MX",
    "name:spa_x_preferred":[
        "El Pando de la Burra"
    ],
    "wof:name":"El Pando de la Burra",
    "wof:placetype":"locality"
},
  "geometry": {"coordinates":[-106.26058,24.38946],"type":"Point"}
}