{
  "type": "Feature",
  "properties": {
    "gn:admin1_code":"12",
    "gn:admin2_code":"32.0",
    "gn:asciiname":"El Organo",
    "gn:country_code":"MX",
    "gn:dem":465,
    "gn:feature_class":"P",
    "gn:feature_code":"PPL",
    "gn:name":"El \u00d3rgano",
    "gn:population":85,
    "gn:timezone":"America/Mexico_City",
    "iso:country":"MX",
    "name:und_x_variant":[
        "El \u00d3rgano"
    ],
    "wof:name":"El Organo",
    "wof:placetype":"locality",
    "wof:population":85
},
  "geometry": {"coordinates":[-100.11792,17.90139],"type":"Point"}
}