{
  "type": "Feature",
  "properties": {
    "gn:admin1_code":"27",
    "gn:admin2_code":"8.0",
    "gn:asciiname":"Aureo L. Calles",
    "gn:country_code":"MX",
    "gn:dem":53,
    "gn:feature_class":"P",
    "gn:feature_code":"PPL",
    "gn:name":"Aureo L. Calles",
    "gn:population":238,
    "gn:timezone":"America/Mexico_City",
    "iso:country":"MX",
    "wof:name":"Aureo L. Calles",
    "wof:placetype":"locality",
    "wof:population":238
},
  "geometry": {"coordinates":[-93.46160999999999,17.55437],"type":"Point"}
}