{
  "type": "Feature",
  "properties": {
    "gn:admin1_code":"12",
    "gn:admin2_code":"16.0",
    "gn:asciiname":"Pueblo Viejo",
    "gn:country_code":"MX",
    "gn:dem":846,
    "gn:feature_class":"P",
    "gn:feature_code":"PPL",
    "gn:name":"Pueblo Viejo",
    "gn:population":8,
    "gn:timezone":"America/Mexico_City",
    "iso:country":"MX",
    "wof:name":"Pueblo Viejo",
    "wof:placetype":"locality",
    "wof:population":8
},
  "geometry": {"coordinates":[-101.64666,18.37688],"type":"Point"}
}