{
  "type": "Feature",
  "properties": {
    "gn:admin1_code":"10",
    "gn:admin2_code":"12.0",
    "gn:asciiname":"El Salitral",
    "gn:country_code":"MX",
    "gn:dem":1163,
    "gn:feature_class":"P",
    "gn:feature_code":"PPL",
    "gn:name":"El Salitral",
    "gn:population":0,
    "gn:timezone":"America/Monterrey",
    "iso:country":"MX",
    "name:spa_x_preferred":[
        "El Salitral"
    ],
    "wof:name":"El Salitral",
    "wof:placetype":"locality"
},
  "geometry": {"coordinates":[-103.69078,25.49674],"type":"Point"}
}