{
  "type": "Feature",
  "properties": {
    "gn:admin1_code":"28",
    "gn:admin2_code":"41.0",
    "gn:asciiname":"San Manuel",
    "gn:country_code":"MX",
    "gn:dem":335,
    "gn:feature_class":"P",
    "gn:feature_code":"PPL",
    "gn:name":"San Manuel",
    "gn:population":6,
    "gn:timezone":"America/Monterrey",
    "iso:country":"MX",
    "wof:name":"San Manuel",
    "wof:placetype":"locality",
    "wof:population":6
},
  "geometry": {"coordinates":[-99.07472,23.62611],"type":"Point"}
}