{
  "type": "Feature",
  "properties": {
    "gn:admin1_code":"30",
    "gn:admin2_code":"72.0",
    "gn:asciiname":"La Paloma",
    "gn:country_code":"MX",
    "gn:dem":1398,
    "gn:feature_class":"P",
    "gn:feature_code":"PPL",
    "gn:name":"La Paloma",
    "gn:population":86,
    "gn:timezone":"America/Mexico_City",
    "iso:country":"MX",
    "wof:name":"La Paloma",
    "wof:placetype":"locality",
    "wof:population":86
},
  "geometry": {"coordinates":[-98.43667000000001,20.54417],"type":"Point"}
}