{
  "type": "Feature",
  "properties": {
    "gn:admin1_code":"24",
    "gn:admin2_code":"32.0",
    "gn:asciiname":"Temascalillo",
    "gn:country_code":"MX",
    "gn:dem":1881,
    "gn:feature_class":"P",
    "gn:feature_code":"PPL",
    "gn:name":"Temascalillo",
    "gn:population":94,
    "gn:timezone":"America/Mexico_City",
    "iso:country":"MX",
    "wof:name":"Temascalillo",
    "wof:placetype":"locality",
    "wof:population":94
},
  "geometry": {"coordinates":[-100.66056,21.61722],"type":"Point"}
}