{
  "type": "Feature",
  "properties": {
    "gn:admin1_code":"16",
    "gn:admin2_code":"97.0",
    "gn:asciiname":"Cruz de Caminos",
    "gn:country_code":"MX",
    "gn:dem":671,
    "gn:feature_class":"P",
    "gn:feature_code":"PPL",
    "gn:name":"Cruz de Caminos",
    "gn:population":58,
    "gn:timezone":"America/Mexico_City",
    "iso:country":"MX",
    "wof:name":"Cruz de Caminos",
    "wof:placetype":"locality",
    "wof:population":58
},
  "geometry": {"coordinates":[-101.38139,18.98917],"type":"Point"}
}