{
  "type": "Feature",
  "properties": {
    "gn:admin1_code":"2.0",
    "gn:admin2_code":"4.0",
    "gn:asciiname":"Colonia Ruben Corona",
    "gn:country_code":"MX",
    "gn:dem":242,
    "gn:feature_class":"P",
    "gn:feature_code":"PPL",
    "gn:name":"Colonia Rub\u00e9n Corona",
    "gn:population":0,
    "gn:timezone":"America/Tijuana",
    "iso:country":"MX",
    "wof:name":"Colonia Ruben Corona",
    "wof:placetype":"locality"
},
  "geometry": {"coordinates":[-117.03333000000001,32.48333],"type":"Point"}
}