{
  "type": "Feature",
  "properties": {
    "gn:admin1_code":"7.0",
    "gn:admin2_code":"7.0",
    "gn:asciiname":"Ejido Estanque de Norias",
    "gn:country_code":"MX",
    "gn:dem":1319,
    "gn:feature_class":"P",
    "gn:feature_code":"PPL",
    "gn:name":"Ejido Estanque de Norias",
    "gn:population":0,
    "gn:timezone":"America/Monterrey",
    "iso:country":"MX",
    "wof:name":"Ejido Estanque de Norias",
    "wof:placetype":"locality"
},
  "geometry": {"coordinates":[-101.59999999999999,26.48333],"type":"Point"}
}