{
  "type": "Feature",
  "properties": {
    "gn:admin1_code":"27",
    "gn:admin2_code":"2.0",
    "gn:asciiname":"Mario Morales (De los Morales)",
    "gn:country_code":"MX",
    "gn:dem":14,
    "gn:feature_class":"P",
    "gn:feature_code":"PPL",
    "gn:name":"Mario Morales (De los Morales)",
    "gn:population":5,
    "gn:timezone":"America/Mexico_City",
    "iso:country":"MX",
    "wof:name":"Mario Morales (De los Morales)",
    "wof:placetype":"locality",
    "wof:population":5
},
  "geometry": {"coordinates":[-93.55528,18.03056],"type":"Point"}
}