{
  "type": "Feature",
  "properties": {
    "gn:admin1_code":"14",
    "gn:admin2_code":"58",
    "gn:asciiname":"Mesas de Juan y Pablo",
    "gn:country_code":"MX",
    "gn:dem":734,
    "gn:feature_class":"P",
    "gn:feature_code":"PPL",
    "gn:name":"Mesas de Juan y Pablo",
    "gn:population":10,
    "gn:timezone":"America/Mexico_City",
    "iso:country":"MX",
    "wof:name":"Mesas de Juan y Pablo",
    "wof:placetype":"locality",
    "wof:population":10
},
  "geometry": {"coordinates":[-105.00749999999999,20.70083],"type":"Point"}
}