{
  "type": "Feature",
  "properties": {
    "gn:admin1_code":"5",
    "gn:admin2_code":"77.0",
    "gn:asciiname":"Chivaltic Viejo",
    "gn:country_code":"MX",
    "gn:dem":85,
    "gn:feature_class":"P",
    "gn:feature_code":"PPL",
    "gn:name":"Chivaltic Viejo",
    "gn:population":59,
    "gn:timezone":"America/Mexico_City",
    "iso:country":"MX",
    "wof:name":"Chivaltic Viejo",
    "wof:placetype":"locality",
    "wof:population":59
},
  "geometry": {"coordinates":[-92.07056,17.38111],"type":"Point"}
}