{
  "type": "Feature",
  "properties": {
    "gn:admin1_code":"14.0",
    "gn:admin2_code":"91.0",
    "gn:asciiname":"El Pueblito",
    "gn:country_code":"MX",
    "gn:dem":1711,
    "gn:feature_class":"P",
    "gn:feature_code":"PPL",
    "gn:name":"El Pueblito",
    "gn:population":210,
    "gn:timezone":"America/Mexico_City",
    "iso:country":"MX",
    "name:ceb_x_preferred":[
        "El Pueblito"
    ],
    "name:deu_x_preferred":[
        "El Pueblito"
    ],
    "name:spa_x_preferred":[
        "El Pueblito"
    ],
    "name:srp_x_preferred":[
        "\u0415\u043b \u041f\u0443\u0435\u0431\u043b\u0438\u0442\u043e"
    ],
    "name:swe_x_preferred":[
        "El Pueblito"
    ],
    "wof:name":"El Pueblito",
    "wof:placetype":"locality",
    "wof:population":210
},
  "geometry": {"coordinates":[-102.46056,21.4625],"type":"Point"}
}