{
  "type": "Feature",
  "properties": {
    "gn:admin1_code":"26.0",
    "gn:admin2_code":"17.0",
    "gn:asciiname":"Cortijo de la Morena",
    "gn:country_code":"MX",
    "gn:dem":233,
    "gn:feature_class":"P",
    "gn:feature_code":"PPL",
    "gn:name":"Cortijo de la Morena",
    "gn:population":0,
    "gn:timezone":"America/Hermosillo",
    "iso:country":"MX",
    "name:spa_x_preferred":[
        "Cortijo de la Morena"
    ],
    "wof:name":"Cortijo de la Morena",
    "wof:placetype":"locality"
},
  "geometry": {"coordinates":[-112.2967,30.69478],"type":"Point"}
}