{
  "type": "Feature",
  "properties": {
    "gn:admin1_code":"13",
    "gn:admin2_code":"26.0",
    "gn:asciiname":"Mazahapa",
    "gn:country_code":"MX",
    "gn:dem":763,
    "gn:feature_class":"P",
    "gn:feature_code":"PPL",
    "gn:name":"Mazahapa",
    "gn:population":201,
    "gn:timezone":"America/Mexico_City",
    "iso:country":"MX",
    "wof:name":"Mazahapa",
    "wof:placetype":"locality",
    "wof:population":201
},
  "geometry": {"coordinates":[-98.49917000000001,20.99028],"type":"Point"}
}