{
  "type": "Feature",
  "properties": {
    "gn:admin1_code":"15",
    "gn:admin2_code":"117.0",
    "gn:asciiname":"Yolotepec",
    "gn:country_code":"MX",
    "gn:dem":1593,
    "gn:feature_class":"P",
    "gn:feature_code":"PPL",
    "gn:name":"Yolotepec",
    "gn:population":247,
    "gn:timezone":"America/Mexico_City",
    "iso:country":"MX",
    "wof:name":"Yolotepec",
    "wof:placetype":"locality",
    "wof:population":247
},
  "geometry": {"coordinates":[-99.88754,18.70907],"type":"Point"}
}