{
  "type": "Feature",
  "properties": {
    "gn:admin1_code":"18",
    "gn:admin2_code":"4",
    "gn:asciiname":"El Crucero de Chacala",
    "gn:country_code":"MX",
    "gn:dem":27,
    "gn:feature_class":"P",
    "gn:feature_code":"PPL",
    "gn:name":"El Crucero de Chacala",
    "gn:population":18,
    "gn:timezone":"America/Mazatlan",
    "iso:country":"MX",
    "wof:name":"El Crucero de Chacala",
    "wof:placetype":"locality",
    "wof:population":18
},
  "geometry": {"coordinates":[-105.15472,21.16694],"type":"Point"}
}