{
  "type": "Feature",
  "properties": {
    "gn:admin1_code":"26.0",
    "gn:admin2_code":"33.0",
    "gn:asciiname":"Los Ortega",
    "gn:country_code":"MX",
    "gn:dem":18,
    "gn:feature_class":"P",
    "gn:feature_code":"PPL",
    "gn:name":"Los Ortega",
    "gn:population":0,
    "gn:timezone":"America/Hermosillo",
    "iso:country":"MX",
    "name:spa_x_preferred":[
        "Los Ortega"
    ],
    "wof:name":"Los Ortega",
    "wof:placetype":"locality"
},
  "geometry": {"coordinates":[-109.30549000000001,26.61938],"type":"Point"}
}