{
  "type": "Feature",
  "properties": {
    "gn:admin1_code":"28",
    "gn:admin2_code":"36.0",
    "gn:asciiname":"Las Animas",
    "gn:country_code":"MX",
    "gn:dem":750,
    "gn:feature_class":"P",
    "gn:feature_code":"PPL",
    "gn:name":"Las \u00c1nimas",
    "gn:population":0,
    "gn:timezone":"America/Monterrey",
    "iso:country":"MX",
    "wof:name":"Las Animas",
    "wof:placetype":"locality"
},
  "geometry": {"coordinates":[-98.76222,24.65859],"type":"Point"}
}