{
  "type": "Feature",
  "properties": {
    "gn:admin1_code":"1",
    "gn:admin2_code":"11",
    "gn:asciiname":"Sector de Produccion Licenciado Jose Lopez Portillo",
    "gn:country_code":"MX",
    "gn:dem":1928,
    "gn:feature_class":"P",
    "gn:feature_code":"PPL",
    "gn:name":"Sector de Producci\u00f3n Licenciado Jos\u00e9 L\u00f3pez Portillo",
    "gn:population":14,
    "gn:timezone":"America/Mexico_City",
    "iso:country":"MX",
    "name:und_x_variant":[
        "Sector de Producci\u00f3n Licenciado Jos\u00e9 L\u00f3pez Portillo"
    ],
    "wof:name":"Sector de Produccion Licenciado Jose Lopez Portillo",
    "wof:placetype":"locality",
    "wof:population":14
},
  "geometry": {"coordinates":[-102.25221999999999,21.9825],"type":"Point"}
}