{
  "type": "Feature",
  "properties": {
    "gn:admin1_code":"26",
    "gn:admin2_code":"65.0",
    "gn:asciiname":"Santa Teresa (San Javier)",
    "gn:country_code":"MX",
    "gn:dem":602,
    "gn:feature_class":"P",
    "gn:feature_code":"PPL",
    "gn:name":"Santa Teresa (San Javier)",
    "gn:population":3,
    "gn:timezone":"America/Hermosillo",
    "iso:country":"MX",
    "wof:name":"Santa Teresa (San Javier)",
    "wof:placetype":"locality",
    "wof:population":3
},
  "geometry": {"coordinates":[-111.52397000000001,30.86617],"type":"Point"}
}