{
  "type": "Feature",
  "properties": {
    "gn:admin1_code":"18.0",
    "gn:admin2_code":"9.0",
    "gn:asciiname":"Santa Cruz del Guaibel",
    "gn:country_code":"MX",
    "gn:dem":901,
    "gn:feature_class":"P",
    "gn:feature_code":"PPL",
    "gn:name":"Santa Cruz del Guaibel",
    "gn:population":0,
    "gn:timezone":"America/Mazatlan",
    "iso:country":"MX",
    "name:spa_x_preferred":[
        "Santa Cruz del Guaibel"
    ],
    "name:und_x_variant":[
        "Palos Colorados"
    ],
    "wof:name":"Santa Cruz del Guaibel",
    "wof:placetype":"locality"
},
  "geometry": {"coordinates":[-104.80618,22.06281],"type":"Point"}
}