{
  "type": "Feature",
  "properties": {
    "gn:admin1_code":"28",
    "gn:admin2_code":"40.0",
    "gn:asciiname":"Raul Garza",
    "gn:country_code":"MX",
    "gn:dem":18,
    "gn:feature_class":"P",
    "gn:feature_code":"PPL",
    "gn:name":"Ra\u00fal Garza",
    "gn:population":7,
    "gn:timezone":"America/Monterrey",
    "iso:country":"MX",
    "name:und_x_variant":[
        "Ra\u00fal Garza"
    ],
    "wof:name":"Raul Garza",
    "wof:placetype":"locality",
    "wof:population":7
},
  "geometry": {"coordinates":[-97.90917,25.80444],"type":"Point"}
}