{
  "type": "Feature",
  "properties": {
    "gn:admin1_code":"30",
    "gn:admin2_code":"71.0",
    "gn:asciiname":"Chalchitepec",
    "gn:country_code":"MX",
    "gn:dem":1809,
    "gn:feature_class":"P",
    "gn:feature_code":"PPL",
    "gn:name":"Chalchitepec",
    "gn:population":632,
    "gn:timezone":"America/Mexico_City",
    "iso:country":"MX",
    "wof:name":"Chalchitepec",
    "wof:placetype":"locality",
    "wof:population":632
},
  "geometry": {"coordinates":[-97.03389,19.15667],"type":"Point"}
}