{
  "type": "Feature",
  "properties": {
    "gn:admin1_code":"20",
    "gn:admin2_code":"426.0",
    "gn:asciiname":"Santa Catarina Estetla",
    "gn:country_code":"MX",
    "gn:dem":1886,
    "gn:feature_class":"P",
    "gn:feature_code":"PPL",
    "gn:name":"Santa Catarina Estetla",
    "gn:population":0,
    "gn:timezone":"America/Mexico_City",
    "iso:country":"MX",
    "name:spa_x_preferred":[
        "Santa Catarina Estetla"
    ],
    "name:und_x_variant":[
        "Estetla"
    ],
    "wof:name":"Santa Catarina Estetla",
    "wof:placetype":"locality"
},
  "geometry": {"coordinates":[-97.09743,17.02649],"type":"Point"}
}