{
  "type": "Feature",
  "properties": {
    "gn:admin1_code":"12",
    "gn:admin2_code":"53.0",
    "gn:asciiname":"Tierra y Libertad",
    "gn:country_code":"MX",
    "gn:dem":48,
    "gn:feature_class":"P",
    "gn:feature_code":"PPL",
    "gn:name":"Tierra y Libertad",
    "gn:population":61,
    "gn:timezone":"America/Mexico_City",
    "iso:country":"MX",
    "wof:name":"Tierra y Libertad",
    "wof:placetype":"locality",
    "wof:population":61
},
  "geometry": {"coordinates":[-99.2222,16.77174],"type":"Point"}
}