{
  "type": "Feature",
  "properties": {
    "gn:admin1_code":"6.0",
    "gn:admin2_code":"15.0",
    "gn:asciiname":"Pila Chica",
    "gn:country_code":"MX",
    "gn:dem":1575,
    "gn:feature_class":"P",
    "gn:feature_code":"PPL",
    "gn:name":"Pila Chica",
    "gn:population":0,
    "gn:timezone":"America/Chihuahua",
    "iso:country":"MX",
    "name:spa_x_preferred":[
        "Pila Chica"
    ],
    "wof:name":"Pila Chica",
    "wof:placetype":"locality"
},
  "geometry": {"coordinates":[-105.17577,29.73264],"type":"Point"}
}