{
  "type": "Feature",
  "properties": {
    "gn:admin1_code":"5",
    "gn:admin2_code":"2",
    "gn:asciiname":"Montes Azules",
    "gn:country_code":"MX",
    "gn:dem":647,
    "gn:feature_class":"P",
    "gn:feature_code":"PPL",
    "gn:name":"Montes Azules",
    "gn:population":20,
    "gn:timezone":"America/Mexico_City",
    "iso:country":"MX",
    "wof:name":"Montes Azules",
    "wof:placetype":"locality",
    "wof:population":20
},
  "geometry": {"coordinates":[-92.79583,16.42083],"type":"Point"}
}