{
  "type": "Feature",
  "properties": {
    "gn:admin1_code":"30",
    "gn:admin2_code":"58.0",
    "gn:asciiname":"Callejon Carrizalillo",
    "gn:country_code":"MX",
    "gn:dem":170,
    "gn:feature_class":"P",
    "gn:feature_code":"PPL",
    "gn:name":"Callej\u00f3n Carrizalillo",
    "gn:population":0,
    "gn:timezone":"America/Mexico_City",
    "iso:country":"MX",
    "name:spa_x_preferred":[
        "Callej\u00f3n Carrizalillo"
    ],
    "name:und_x_variant":[
        "Carrizalillo"
    ],
    "wof:name":"Callejon Carrizalillo",
    "wof:placetype":"locality"
},
  "geometry": {"coordinates":[-98.10056,21.12281],"type":"Point"}
}