{
  "type": "Feature",
  "properties": {
    "gn:admin1_code":"32.0",
    "gn:asciiname":"Las Huertas",
    "gn:country_code":"MX",
    "gn:dem":1426,
    "gn:feature_class":"P",
    "gn:feature_code":"PPL",
    "gn:name":"Las Huertas",
    "gn:population":0,
    "gn:timezone":"America/Mexico_City",
    "iso:country":"MX",
    "name:spa_x_preferred":[
        "Las Huertas"
    ],
    "wof:name":"Las Huertas",
    "wof:placetype":"locality"
},
  "geometry": {"coordinates":[-102.91376,21.70715],"type":"Point"}
}