{
  "type": "Feature",
  "properties": {
    "gn:admin1_code":"6",
    "gn:admin2_code":"29",
    "gn:asciiname":"Curvas Coloradas",
    "gn:country_code":"MX",
    "gn:dem":2557,
    "gn:feature_class":"P",
    "gn:feature_code":"PPL",
    "gn:name":"Curvas Coloradas",
    "gn:population":9,
    "gn:timezone":"America/Chihuahua",
    "iso:country":"MX",
    "wof:name":"Curvas Coloradas",
    "wof:placetype":"locality",
    "wof:population":9
},
  "geometry": {"coordinates":[-106.5018,26.28023],"type":"Point"}
}