{
  "type": "Feature",
  "properties": {
    "gn:admin1_code":"14.0",
    "gn:admin2_code":"49.0",
    "gn:asciiname":"El Pozo",
    "gn:country_code":"MX",
    "gn:dem":867,
    "gn:feature_class":"P",
    "gn:feature_code":"PPL",
    "gn:name":"El Pozo",
    "gn:population":0,
    "gn:timezone":"America/Mexico_City",
    "iso:country":"MX",
    "name:spa_x_preferred":[
        "El Pozo"
    ],
    "wof:name":"El Pozo",
    "wof:placetype":"locality"
},
  "geometry": {"coordinates":[-102.64551,19.378],"type":"Point"}
}