{
  "type": "Feature",
  "properties": {
    "gn:admin1_code":"23.0",
    "gn:admin2_code":"4.0",
    "gn:asciiname":"Maya Balam",
    "gn:country_code":"MX",
    "gn:dem":23,
    "gn:feature_class":"P",
    "gn:feature_code":"PPL",
    "gn:name":"Maya Balam",
    "gn:population":2018,
    "gn:timezone":"America/Cancun",
    "iso:country":"MX",
    "name:spa_x_preferred":[
        "Maya Balam"
    ],
    "wof:name":"Maya Balam",
    "wof:placetype":"locality",
    "wof:population":2018
},
  "geometry": {"coordinates":[-88.39972,18.93917],"type":"Point"}
}