{
  "type": "Feature",
  "properties": {
    "gn:admin1_code":"30",
    "gn:admin2_code":"172.0",
    "gn:asciiname":"Ixtepec",
    "gn:country_code":"MX",
    "gn:dem":15,
    "gn:feature_class":"P",
    "gn:feature_code":"PPL",
    "gn:name":"Ixtepec",
    "gn:population":195,
    "gn:timezone":"America/Mexico_City",
    "iso:country":"MX",
    "name:ceb_x_preferred":[
        "Ixtepec"
    ],
    "name:spa_x_preferred":[
        "Ixtepec"
    ],
    "name:swe_x_preferred":[
        "Ixtepec"
    ],
    "name:vie_x_preferred":[
        "Ixtepec"
    ],
    "wof:name":"Ixtepec",
    "wof:placetype":"locality",
    "wof:population":195
},
  "geometry": {"coordinates":[-94.7175,17.69056],"type":"Point"}
}