{
  "type": "Feature",
  "properties": {
    "gn:admin1_code":"6",
    "gn:admin2_code":"37.0",
    "gn:asciiname":"Pomposo Urrutia",
    "gn:country_code":"MX",
    "gn:dem":1103,
    "gn:feature_class":"P",
    "gn:feature_code":"PPL",
    "gn:name":"Pomposo Urrutia",
    "gn:population":0,
    "gn:timezone":"America/Chihuahua",
    "iso:country":"MX",
    "wof:name":"Pomposo Urrutia",
    "wof:placetype":"locality"
},
  "geometry": {"coordinates":[-106.28333000000001,31.56667],"type":"Point"}
}