{
  "type": "Feature",
  "properties": {
    "gn:admin1_code":"6",
    "gn:admin2_code":"43.0",
    "gn:asciiname":"Los Pinitos [Cabanas]",
    "gn:country_code":"MX",
    "gn:dem":1912,
    "gn:feature_class":"P",
    "gn:feature_code":"PPL",
    "gn:name":"Los Pinitos [Caba\u00f1as]",
    "gn:population":6,
    "gn:timezone":"America/Chihuahua",
    "iso:country":"MX",
    "name:und_x_variant":[
        "Los Pinitos [Caba\u00f1as]"
    ],
    "wof:name":"Los Pinitos [Cabanas]",
    "wof:placetype":"locality",
    "wof:population":6
},
  "geometry": {"coordinates":[-107.74083,28.83667],"type":"Point"}
}