{
  "type": "Feature",
  "properties": {
    "gn:admin1_code":"10",
    "gn:admin2_code":"1",
    "gn:asciiname":"Carmen Ortega",
    "gn:country_code":"MX",
    "gn:dem":1932,
    "gn:feature_class":"P",
    "gn:feature_code":"PPL",
    "gn:name":"Carmen Ortega",
    "gn:population":10,
    "gn:timezone":"America/Monterrey",
    "iso:country":"MX",
    "wof:name":"Carmen Ortega",
    "wof:placetype":"locality",
    "wof:population":10
},
  "geometry": {"coordinates":[-104.71559000000001,24.4764],"type":"Point"}
}