{
  "type": "Feature",
  "properties": {
    "gn:admin1_code":"30",
    "gn:admin2_code":"175",
    "gn:asciiname":"Valle Verde (El Paraiso San Roman)",
    "gn:country_code":"MX",
    "gn:dem":72,
    "gn:feature_class":"P",
    "gn:feature_code":"PPL",
    "gn:name":"Valle Verde (El Para\u00edso San Rom\u00e1n)",
    "gn:population":36,
    "gn:timezone":"America/Mexico_City",
    "iso:country":"MX",
    "name:und_x_variant":[
        "Valle Verde (El Para\u00edso San Rom\u00e1n)"
    ],
    "wof:name":"Valle Verde (El Paraiso San Roman)",
    "wof:placetype":"locality",
    "wof:population":36
},
  "geometry": {"coordinates":[-97.49444,20.76472],"type":"Point"}
}