{
  "type": "Feature",
  "properties": {
    "gn:admin1_code":"26",
    "gn:admin2_code":"61.0",
    "gn:asciiname":"Viejo",
    "gn:cc2":"MX",
    "gn:country_code":"MX",
    "gn:dem":341,
    "gn:feature_class":"P",
    "gn:feature_code":"PPL",
    "gn:name":"Viejo",
    "gn:population":0,
    "gn:timezone":"America/Hermosillo",
    "iso:country":"MX",
    "name:und_x_variant":[
        "Rancho Real Viejo",
        "Viejo"
    ],
    "wof:name":"Viejo",
    "wof:placetype":"locality"
},
  "geometry": {"coordinates":[-109.65000000000001,28.73333],"type":"Point"}
}