{
  "type": "Feature",
  "properties": {
    "gn:admin1_code":"30.0",
    "gn:asciiname":"Tampachiche",
    "gn:country_code":"MX",
    "gn:dem":11,
    "gn:feature_class":"P",
    "gn:feature_code":"PPL",
    "gn:name":"Tampachiche",
    "gn:population":0,
    "gn:timezone":"America/Mexico_City",
    "iso:country":"MX",
    "name:spa_x_preferred":[
        "Tampachiche"
    ],
    "wof:name":"Tampachiche",
    "wof:placetype":"locality"
},
  "geometry": {"coordinates":[-97.72759000000001,21.99333],"type":"Point"}
}