{
  "type": "Feature",
  "properties": {
    "gn:admin1_code":"16",
    "gn:admin2_code":"55",
    "gn:asciiname":"Los Serapios",
    "gn:country_code":"MX",
    "gn:dem":242,
    "gn:feature_class":"P",
    "gn:feature_code":"PPL",
    "gn:name":"Los Serapios",
    "gn:population":11,
    "gn:timezone":"America/Mexico_City",
    "iso:country":"MX",
    "wof:name":"Los Serapios",
    "wof:placetype":"locality",
    "wof:population":11
},
  "geometry": {"coordinates":[-102.14861000000001,18.88722000000001],"type":"Point"}
}