{
  "type": "Feature",
  "properties": {
    "gn:admin1_code":"24",
    "gn:admin2_code":"24.0",
    "gn:asciiname":"Albarquilla",
    "gn:country_code":"MX",
    "gn:dem":1438,
    "gn:feature_class":"P",
    "gn:feature_code":"PPL",
    "gn:name":"Albarquilla",
    "gn:population":0,
    "gn:timezone":"America/Mexico_City",
    "iso:country":"MX",
    "wof:name":"Albarquilla",
    "wof:placetype":"locality"
},
  "geometry": {"coordinates":[-99.93333,21.68333],"type":"Point"}
}