{
  "type": "Feature",
  "properties": {
    "gn:admin1_code":"25",
    "gn:asciiname":"El Duraznito",
    "gn:country_code":"MX",
    "gn:dem":1497,
    "gn:feature_class":"P",
    "gn:feature_code":"PPL",
    "gn:name":"El Duraznito",
    "gn:population":0,
    "gn:timezone":"America/Mazatlan",
    "iso:country":"MX",
    "name:spa_x_preferred":[
        "El Duraznito"
    ],
    "wof:name":"El Duraznito",
    "wof:placetype":"locality"
},
  "geometry": {"coordinates":[-108.01787,26.63799],"type":"Point"}
}