{
  "type": "Feature",
  "properties": {
    "gn:admin1_code":"25.0",
    "gn:asciiname":"San Jose del Favor",
    "gn:country_code":"MX",
    "gn:dem":363,
    "gn:feature_class":"P",
    "gn:feature_code":"PPL",
    "gn:name":"San Jos\u00e9 del Favor",
    "gn:population":0,
    "gn:timezone":"America/Mazatlan",
    "iso:country":"MX",
    "name:und_x_variant":[
        "San Jos\u00e9 del Favor",
        "El Favor"
    ],
    "wof:name":"San Jose del Favor",
    "wof:placetype":"locality"
},
  "geometry": {"coordinates":[-105.91783999999998,23.76748],"type":"Point"}
}