{
  "type": "Feature",
  "properties": {
    "gn:admin1_code":"20",
    "gn:admin2_code":"413.0",
    "gn:asciiname":"Piedra de Moros",
    "gn:country_code":"MX",
    "gn:dem":159,
    "gn:feature_class":"P",
    "gn:feature_code":"PPL",
    "gn:name":"Piedra de Moros",
    "gn:population":0,
    "gn:timezone":"America/Mexico_City",
    "iso:country":"MX",
    "name:und_x_variant":[
        "Piedra Mora",
        "Piedra de Moros",
        "Piedra de los Moros"
    ],
    "wof:name":"Piedra de Moros",
    "wof:placetype":"locality"
},
  "geometry": {"coordinates":[-96.23137,15.79951],"type":"Point"}
}