{
  "type": "Feature",
  "properties": {
    "gn:admin1_code":"20",
    "gn:admin2_code":"324.0",
    "gn:asciiname":"Barrio Mendillo",
    "gn:country_code":"MX",
    "gn:dem":149,
    "gn:feature_class":"P",
    "gn:feature_code":"PPL",
    "gn:name":"Barrio Mendillo",
    "gn:population":315,
    "gn:timezone":"America/Mexico_City",
    "iso:country":"MX",
    "wof:name":"Barrio Mendillo",
    "wof:placetype":"locality",
    "wof:population":315
},
  "geometry": {"coordinates":[-96.47306,15.74306],"type":"Point"}
}