{
  "type": "Feature",
  "properties": {
    "gn:admin1_code":"10",
    "gn:admin2_code":"9.0",
    "gn:asciiname":"Murguia",
    "gn:country_code":"MX",
    "gn:dem":2631,
    "gn:feature_class":"P",
    "gn:feature_code":"PPL",
    "gn:name":"Murgu\u00eda",
    "gn:population":0,
    "gn:timezone":"America/Monterrey",
    "iso:country":"MX",
    "name:spa_x_preferred":[
        "Murgu\u00eda"
    ],
    "wof:name":"Murguia",
    "wof:placetype":"locality"
},
  "geometry": {"coordinates":[-105.57898,25.66928],"type":"Point"}
}