{
  "type": "Feature",
  "properties": {
    "gn:admin1_code":"5",
    "gn:admin2_code":"87",
    "gn:asciiname":"La Esmeralda",
    "gn:country_code":"MX",
    "gn:dem":15,
    "gn:feature_class":"P",
    "gn:feature_code":"PPL",
    "gn:name":"La Esmeralda",
    "gn:population":14,
    "gn:timezone":"America/Mexico_City",
    "iso:country":"MX",
    "name:ara_x_preferred":[
        "\u0644\u0627 \u0625\u0632\u0645\u064a\u0631\u0627\u0644\u062f\u0627"
    ],
    "name:ben_x_preferred":[
        "\u09b2\u09be \u098f\u09b8\u09ae\u09c7\u09b0\u09be\u09b2\u09cd\u09a1\u09be"
    ],
    "name:ceb_x_preferred":[
        "La Esmeralda"
    ],
    "name:deu_x_preferred":[
        "La Esmeralda"
    ],
    "name:ell_x_preferred":[
        "\u039b\u03b1 \u0395\u03c3\u03bc\u03b5\u03c1\u03ac\u03bb\u03bd\u03c4\u03b1"
    ],
    "name:fas_x_preferred":[
        "\u0644\u0627 \u0627\u0633\u0645\u0631\u0627\u0644\u062f\u0627"
    ],
    "name:heb_x_preferred":[
        "\u05dc\u05d4 \u05d0\u05e1\u05de\u05e8\u05dc\u05d3\u05d4"
    ],
    "name:hin_x_preferred":[
        "\u0932\u093e \u090f\u0938\u094d\u092e\u0930\u093e\u0932\u094d\u0921\u093e"
    ],
    "name:hun_x_preferred":[
        "La Esmeralda"
    ],
    "name:ind_x_preferred":[
        "La Esmeralda"
    ],
    "name:ita_x_preferred":[
        "La Esmeralda"
    ],
    "name:jpn_x_preferred":[
        "\u30e9\u30a8\u30b9\u30e1\u30e9\u30eb\u30c0"
    ],
    "name:kor_x_preferred":[
        "\ub77c \uc5d0\uc2a4\uba54\ub784\ub2e4"
    ],
    "name:pol_x_preferred":[
        "La Esmeralda"
    ],
    "name:sco_x_preferred":[
        "La Esmeralda"
    ],
    "name:spa_x_preferred":[
        "La Esmeralda"
    ],
    "name:srp_x_preferred":[
        "\u041b\u0430 \u0415\u0441\u043c\u0435\u0440\u0430\u043b\u0434\u0430"
    ],
    "name:swe_x_preferred":[
        "La Esmeralda"
    ],
    "name:tur_x_preferred":[
        "La Esmeralda"
    ],
    "name:ukr_x_preferred":[
        "\u041b\u0430-\u0415\u0441\u043c\u0435\u0440\u0430\u043b\u044c\u0434\u0430"
    ],
    "name:urd_x_preferred":[
        "\u0644\u06cc \u0627\u06cc\u0633\u0645\u06cc\u0631\u0627\u0644\u0688\u0627"
    ],
    "name:vie_x_preferred":[
        "La Esmeralda"
    ],
    "wof:name":"La Esmeralda",
    "wof:placetype":"locality",
    "wof:population":14
},
  "geometry": {"coordinates":[-92.20944,14.58361],"type":"Point"}
}