{
  "type": "Feature",
  "properties": {
    "gn:admin1_code":"5",
    "gn:admin2_code":"87",
    "gn:asciiname":"La Esmeralda",
    "gn:country_code":"MX",
    "gn:dem":15,
    "gn:feature_class":"P",
    "gn:feature_code":"PPL",
    "gn:name":"La Esmeralda",
    "gn:population":14,
    "gn:timezone":"America/Mexico_City",
    "iso:country":"MX",
    "wof:name":"La Esmeralda",
    "wof:placetype":"locality",
    "wof:population":14
},
  "geometry": {"coordinates":[-92.20944,14.58361],"type":"Point"}
}