{
  "type": "Feature",
  "properties": {
    "gn:admin1_code":"5",
    "gn:admin2_code":"40",
    "gn:asciiname":"Salto de Agua",
    "gn:country_code":"MX",
    "gn:dem":26,
    "gn:feature_class":"P",
    "gn:feature_code":"PPL",
    "gn:name":"Salto de Agua",
    "gn:population":35,
    "gn:timezone":"America/Mexico_City",
    "iso:country":"MX",
    "wof:name":"Salto de Agua",
    "wof:placetype":"locality",
    "wof:population":35
},
  "geometry": {"coordinates":[-92.53055999999999,15.15917],"type":"Point"}
}