{
  "type": "Feature",
  "properties": {
    "gn:admin1_code":"6",
    "gn:admin2_code":"27.0",
    "gn:asciiname":"Tonachi",
    "gn:country_code":"MX",
    "gn:dem":2040,
    "gn:feature_class":"P",
    "gn:feature_code":"PPL",
    "gn:name":"Tonachi",
    "gn:population":0,
    "gn:timezone":"America/Chihuahua",
    "iso:country":"MX",
    "name:spa_x_preferred":[
        "Tonachi"
    ],
    "name:und_x_variant":[
        "Tonachic"
    ],
    "wof:name":"Tonachi",
    "wof:placetype":"locality"
},
  "geometry": {"coordinates":[-107.27731,26.94719000000001],"type":"Point"}
}