{
  "type": "Feature",
  "properties": {
    "gn:admin1_code":"7",
    "gn:admin2_code":"38.0",
    "gn:asciiname":"Rancho La Asuncion",
    "gn:country_code":"MX",
    "gn:dem":302,
    "gn:feature_class":"P",
    "gn:feature_code":"PPL",
    "gn:name":"Rancho La Asunci\u00f3n",
    "gn:population":0,
    "gn:timezone":"America/Matamoros",
    "iso:country":"MX",
    "wof:name":"Rancho La Asuncion",
    "wof:placetype":"locality"
},
  "geometry": {"coordinates":[-100.78333000000001,28.73333],"type":"Point"}
}