{
  "type": "Feature",
  "properties": {
    "gn:admin1_code":"5",
    "gn:admin2_code":"65.0",
    "gn:asciiname":"La Joya",
    "gn:country_code":"MX",
    "gn:dem":34,
    "gn:feature_class":"P",
    "gn:feature_code":"PPL",
    "gn:name":"La Joya",
    "gn:population":4,
    "gn:timezone":"America/Mexico_City",
    "iso:country":"MX",
    "name:ceb_x_preferred":[
        "La Joya"
    ],
    "name:deu_x_preferred":[
        "La Joya"
    ],
    "name:nld_x_preferred":[
        "La Joya"
    ],
    "name:que_x_preferred":[
        "La Joya"
    ],
    "name:spa_x_preferred":[
        "La Joya"
    ],
    "name:srp_x_preferred":[
        "\u041b\u0430 \u0425\u043e\u0458\u0430"
    ],
    "name:swe_x_preferred":[
        "La Joya"
    ],
    "wof:name":"La Joya",
    "wof:placetype":"locality",
    "wof:population":4
},
  "geometry": {"coordinates":[-92.09305999999999,17.53417],"type":"Point"}
}