{
  "type": "Feature",
  "properties": {
    "gn:admin1_code":"20.0",
    "gn:admin2_code":"525.0",
    "gn:asciiname":"Los Naranjos",
    "gn:country_code":"MX",
    "gn:dem":72,
    "gn:feature_class":"P",
    "gn:feature_code":"PPL",
    "gn:name":"Los Naranjos",
    "gn:population":0,
    "gn:timezone":"America/Mexico_City",
    "iso:country":"MX",
    "name:bre_x_preferred":[
        "Los Naranjos"
    ],
    "name:ceb_x_preferred":[
        "Los Naranjos"
    ],
    "name:deu_x_preferred":[
        "Los Naranjos"
    ],
    "name:spa_x_preferred":[
        "Los Naranjos"
    ],
    "name:swe_x_preferred":[
        "Los Naranjos"
    ],
    "wof:name":"Los Naranjos",
    "wof:placetype":"locality"
},
  "geometry": {"coordinates":[-94.31115,16.46719],"type":"Point"}
}