{
  "type": "Feature",
  "properties": {
    "gn:admin1_code":"12",
    "gn:admin2_code":"53.0",
    "gn:asciiname":"El Arenal (Huerta los Ramirez)",
    "gn:country_code":"MX",
    "gn:dem":20,
    "gn:feature_class":"P",
    "gn:feature_code":"PPL",
    "gn:name":"El Arenal (Huerta los Ram\u00edrez)",
    "gn:population":94,
    "gn:timezone":"America/Mexico_City",
    "iso:country":"MX",
    "name:und_x_variant":[
        "El Arenal (Huerta los Ram\u00edrez)"
    ],
    "wof:name":"El Arenal (Huerta los Ramirez)",
    "wof:placetype":"locality",
    "wof:population":94
},
  "geometry": {"coordinates":[-99.2097,16.70195],"type":"Point"}
}