{
  "type": "Feature",
  "properties": {
    "gn:admin1_code":"10",
    "gn:admin2_code":"34",
    "gn:asciiname":"El Pueblo Nuevo",
    "gn:country_code":"MX",
    "gn:dem":280,
    "gn:feature_class":"P",
    "gn:feature_code":"PPL",
    "gn:name":"El Pueblo Nuevo",
    "gn:population":16,
    "gn:timezone":"America/Monterrey",
    "iso:country":"MX",
    "wof:name":"El Pueblo Nuevo",
    "wof:placetype":"locality",
    "wof:population":16
},
  "geometry": {"coordinates":[-107.09593,25.2958],"type":"Point"}
}