{
  "type": "Feature",
  "properties": {
    "gn:admin1_code":"26.0",
    "gn:admin2_code":"22.0",
    "gn:asciiname":"El Retiro",
    "gn:country_code":"MX",
    "gn:dem":896,
    "gn:feature_class":"P",
    "gn:feature_code":"PPL",
    "gn:name":"El Retiro",
    "gn:population":0,
    "gn:timezone":"America/Hermosillo",
    "iso:country":"MX",
    "name:ceb_x_preferred":[
        "El Retiro"
    ],
    "name:glg_x_preferred":[
        "O Retiro"
    ],
    "name:spa_x_preferred":[
        "El Retiro"
    ],
    "name:srp_x_preferred":[
        "\u0415\u043b \u0420\u0435\u0442\u0438\u0440\u043e"
    ],
    "name:swe_x_preferred":[
        "El Retiro"
    ],
    "wof:name":"El Retiro",
    "wof:placetype":"locality"
},
  "geometry": {"coordinates":[-110.69138999999998,30.37861],"type":"Point"}
}