{
  "type": "Feature",
  "properties": {
    "gn:admin1_code":"20",
    "gn:admin2_code":"190.0",
    "gn:asciiname":"Arroyo Aguacate",
    "gn:country_code":"MX",
    "gn:dem":453,
    "gn:feature_class":"P",
    "gn:feature_code":"PPL",
    "gn:name":"Arroyo Aguacate",
    "gn:population":0,
    "gn:timezone":"America/Mexico_City",
    "iso:country":"MX",
    "name:spa_x_preferred":[
        "Arroyo Aguacate"
    ],
    "wof:name":"Arroyo Aguacate",
    "wof:placetype":"locality"
},
  "geometry": {"coordinates":[-95.60556,17.21861],"type":"Point"}
}