{
  "type": "Feature",
  "properties": {
    "gn:admin1_code":"13",
    "gn:admin2_code":"62.0",
    "gn:asciiname":"Tzinangal",
    "gn:country_code":"MX",
    "gn:dem":245,
    "gn:feature_class":"P",
    "gn:feature_code":"PPL",
    "gn:name":"Tzinangal",
    "gn:population":0,
    "gn:timezone":"America/Mexico_City",
    "iso:country":"MX",
    "name:spa_x_preferred":[
        "Tzinangal"
    ],
    "wof:name":"Tzinangal",
    "wof:placetype":"locality"
},
  "geometry": {"coordinates":[-98.74863000000001,21.10874],"type":"Point"}
}