{
  "type": "Feature",
  "properties": {
    "gn:admin1_code":"28",
    "gn:admin2_code":"27.0",
    "gn:asciiname":"El Frances",
    "gn:country_code":"MX",
    "gn:dem":133,
    "gn:feature_class":"P",
    "gn:feature_code":"PPL",
    "gn:name":"El Franc\u00e9s",
    "gn:population":0,
    "gn:timezone":"America/Monterrey",
    "iso:country":"MX",
    "name:und_x_variant":[
        "Franc\u00e9s",
        "El Franc\u00e9s"
    ],
    "wof:name":"El Frances",
    "wof:placetype":"locality"
},
  "geometry": {"coordinates":[-99.53006000000001,27.57836],"type":"Point"}
}