{
  "type": "Feature",
  "properties": {
    "gn:admin1_code":"16",
    "gn:admin2_code":"77.0",
    "gn:asciiname":"Los Brasiles",
    "gn:country_code":"MX",
    "gn:dem":238,
    "gn:feature_class":"P",
    "gn:feature_code":"PPL",
    "gn:name":"Los Brasiles",
    "gn:population":141,
    "gn:timezone":"America/Mexico_City",
    "iso:country":"MX",
    "wof:name":"Los Brasiles",
    "wof:placetype":"locality",
    "wof:population":141
},
  "geometry": {"coordinates":[-100.82944000000001,18.505],"type":"Point"}
}