{
  "type": "Feature",
  "properties": {
    "gn:admin1_code":"31",
    "gn:admin2_code":"40.0",
    "gn:asciiname":"San Dimas",
    "gn:country_code":"MX",
    "gn:dem":18,
    "gn:feature_class":"P",
    "gn:feature_code":"PPL",
    "gn:name":"San Dimas",
    "gn:population":0,
    "gn:timezone":"America/Merida",
    "iso:country":"MX",
    "name:spa_x_preferred":[
        "San Dimas"
    ],
    "wof:name":"San Dimas",
    "wof:placetype":"locality"
},
  "geometry": {"coordinates":[-89.0371,20.83242000000001],"type":"Point"}
}