{
  "type": "Feature",
  "properties": {
    "gn:admin1_code":"14",
    "gn:admin2_code":"73",
    "gn:asciiname":"La Loma Bonita",
    "gn:country_code":"MX",
    "gn:dem":1835,
    "gn:feature_class":"P",
    "gn:feature_code":"PPL",
    "gn:name":"La Loma Bonita",
    "gn:population":38,
    "gn:timezone":"America/Mexico_City",
    "iso:country":"MX",
    "wof:name":"La Loma Bonita",
    "wof:placetype":"locality",
    "wof:population":38
},
  "geometry": {"coordinates":[-102.33528,21.32583],"type":"Point"}
}