{
  "type": "Feature",
  "properties": {
    "gn:admin1_code":"26.0",
    "gn:admin2_code":"62.0",
    "gn:asciiname":"Aguaje del Picheleto",
    "gn:country_code":"MX",
    "gn:dem":318,
    "gn:feature_class":"P",
    "gn:feature_code":"PPL",
    "gn:name":"Aguaje del Picheleto",
    "gn:population":0,
    "gn:timezone":"America/Hermosillo",
    "iso:country":"MX",
    "name:spa_x_preferred":[
        "Aguaje del Picheleto"
    ],
    "wof:name":"Aguaje del Picheleto",
    "wof:placetype":"locality"
},
  "geometry": {"coordinates":[-109.64994,28.48998],"type":"Point"}
}