{
  "type": "Feature",
  "properties": {
    "gn:admin1_code":"23",
    "gn:admin2_code":"9.0",
    "gn:asciiname":"Kukulkan",
    "gn:country_code":"MX",
    "gn:dem":18,
    "gn:feature_class":"P",
    "gn:feature_code":"PPL",
    "gn:name":"Kukulk\u00e1n",
    "gn:population":6,
    "gn:timezone":"America/Cancun",
    "iso:country":"MX",
    "name:und_x_variant":[
        "Kukulk\u00e1n"
    ],
    "wof:name":"Kukulkan",
    "wof:placetype":"locality",
    "wof:population":6
},
  "geometry": {"coordinates":[-87.49636,20.2841],"type":"Point"}
}