{
  "type": "Feature",
  "properties": {
    "gn:admin1_code":"14.0",
    "gn:admin2_code":"69.0",
    "gn:asciiname":"La Torrecilla",
    "gn:country_code":"MX",
    "gn:dem":1446,
    "gn:feature_class":"P",
    "gn:feature_code":"PPL",
    "gn:name":"La Torrecilla",
    "gn:population":0,
    "gn:timezone":"America/Mexico_City",
    "iso:country":"MX",
    "name:spa_x_preferred":[
        "La Torrecilla"
    ],
    "wof:name":"La Torrecilla",
    "wof:placetype":"locality"
},
  "geometry": {"coordinates":[-102.8764,19.77433],"type":"Point"}
}