{
  "type": "Feature",
  "properties": {
    "gn:admin1_code":"20",
    "gn:admin2_code":"242.0",
    "gn:asciiname":"San Juan del Rio",
    "gn:country_code":"MX",
    "gn:dem":1583,
    "gn:feature_class":"P",
    "gn:feature_code":"PPL",
    "gn:name":"San Juan del R\u00edo",
    "gn:population":249,
    "gn:timezone":"America/Mexico_City",
    "iso:country":"MX",
    "name:und_x_variant":[
        "San Juan del R\u00edo"
    ],
    "wof:name":"San Juan del Rio",
    "wof:placetype":"locality",
    "wof:population":249
},
  "geometry": {"coordinates":[-98.26306,17.40389],"type":"Point"}
}