{
  "type": "Feature",
  "properties": {
    "gn:admin1_code":"32",
    "gn:admin2_code":"18",
    "gn:asciiname":"Zapote de Arriba",
    "gn:country_code":"MX",
    "gn:dem":1571,
    "gn:feature_class":"P",
    "gn:feature_code":"PPL",
    "gn:name":"Zapote de Arriba",
    "gn:population":33,
    "gn:timezone":"America/Mexico_City",
    "iso:country":"MX",
    "wof:name":"Zapote de Arriba",
    "wof:placetype":"locality",
    "wof:population":33
},
  "geometry": {"coordinates":[-102.84139,21.70472],"type":"Point"}
}