{
  "type": "Feature",
  "properties": {
    "gn:admin1_code":"29.0",
    "gn:admin2_code":"47.0",
    "gn:asciiname":"San Jose de la Laguna",
    "gn:country_code":"MX",
    "gn:dem":2520,
    "gn:feature_class":"P",
    "gn:feature_code":"PPL",
    "gn:name":"San Jos\u00e9 de la Laguna",
    "gn:population":0,
    "gn:timezone":"America/Mexico_City",
    "iso:country":"MX",
    "name:spa_x_preferred":[
        "San Jos\u00e9 de la Laguna"
    ],
    "name:spa_x_variant":[
        "San Jos\u00e9 la Laguna"
    ],
    "wof:name":"San Jose de la Laguna",
    "wof:placetype":"locality"
},
  "geometry": {"coordinates":[-97.99427,19.51744],"type":"Point"}
}