{
  "type": "Feature",
  "properties": {
    "gn:admin1_code":"16.0",
    "gn:asciiname":"La Estacion",
    "gn:country_code":"MX",
    "gn:dem":2113,
    "gn:feature_class":"P",
    "gn:feature_code":"PPL",
    "gn:name":"La Estaci\u00f3n",
    "gn:population":0,
    "gn:timezone":"America/Mexico_City",
    "iso:country":"MX",
    "name:spa_x_preferred":[
        "La Estaci\u00f3n"
    ],
    "wof:name":"La Estacion",
    "wof:placetype":"locality"
},
  "geometry": {"coordinates":[-100.4122,19.51717],"type":"Point"}
}