{
  "type": "Feature",
  "properties": {
    "gn:admin1_code":"30",
    "gn:admin2_code":"125.0",
    "gn:asciiname":"Mata Naranjo",
    "gn:country_code":"MX",
    "gn:dem":587,
    "gn:feature_class":"P",
    "gn:feature_code":"PPL",
    "gn:name":"Mata Naranjo",
    "gn:population":511,
    "gn:timezone":"America/Mexico_City",
    "iso:country":"MX",
    "wof:name":"Mata Naranjo",
    "wof:placetype":"locality",
    "wof:population":511
},
  "geometry": {"coordinates":[-96.76443999999999,19.005],"type":"Point"}
}