{
  "type": "Feature",
  "properties": {
    "gn:admin1_code":"5",
    "gn:admin2_code":"52",
    "gn:asciiname":"Jerico",
    "gn:country_code":"MX",
    "gn:dem":1482,
    "gn:feature_class":"P",
    "gn:feature_code":"PPL",
    "gn:name":"Jeric\u00f3",
    "gn:population":12,
    "gn:timezone":"America/Mexico_City",
    "iso:country":"MX",
    "name:und_x_variant":[
        "Jeric\u00f3"
    ],
    "wof:name":"Jerico",
    "wof:placetype":"locality",
    "wof:population":12
},
  "geometry": {"coordinates":[-91.85028,16.28944],"type":"Point"}
}