{
  "type": "Feature",
  "properties": {
    "gn:admin1_code":"3",
    "gn:admin2_code":"2.0",
    "gn:asciiname":"La Cueva Colorada",
    "gn:country_code":"MX",
    "gn:dem":293,
    "gn:feature_class":"P",
    "gn:feature_code":"PPL",
    "gn:name":"La Cueva Colorada",
    "gn:population":5,
    "gn:timezone":"America/Mazatlan",
    "iso:country":"MX",
    "name:spa_x_preferred":[
        "La Cueva Colorada"
    ],
    "wof:name":"La Cueva Colorada",
    "wof:placetype":"locality",
    "wof:population":5
},
  "geometry": {"coordinates":[-112.65466000000001,27.31893],"type":"Point"}
}