{
  "type": "Feature",
  "properties": {
    "gn:admin1_code":"14",
    "gn:admin2_code":"61.0",
    "gn:asciiname":"Pinos Altos",
    "gn:country_code":"MX",
    "gn:dem":2359,
    "gn:feature_class":"P",
    "gn:feature_code":"PPL",
    "gn:name":"Pinos Altos",
    "gn:population":0,
    "gn:timezone":"America/Mexico_City",
    "iso:country":"MX",
    "name:spa_x_preferred":[
        "Pinos Altos"
    ],
    "wof:name":"Pinos Altos",
    "wof:placetype":"locality"
},
  "geometry": {"coordinates":[-103.95986000000001,22.1875],"type":"Point"}
}