{
  "type": "Feature",
  "properties": {
    "gn:admin1_code":"1.0",
    "gn:admin2_code":"4.0",
    "gn:asciiname":"Ejido Cosio",
    "gn:country_code":"MX",
    "gn:dem":1942,
    "gn:feature_class":"P",
    "gn:feature_code":"PPL",
    "gn:name":"Ejido Cos\u00edo",
    "gn:population":0,
    "gn:timezone":"America/Mexico_City",
    "iso:country":"MX",
    "wof:name":"Ejido Cosio",
    "wof:placetype":"locality"
},
  "geometry": {"coordinates":[-102.27500000000001,22.32083],"type":"Point"}
}