{
  "type": "Feature",
  "properties": {
    "gn:admin1_code":"11",
    "gn:admin2_code":"5",
    "gn:asciiname":"Colonia Villa Colombia",
    "gn:country_code":"MX",
    "gn:dem":1798,
    "gn:feature_class":"P",
    "gn:feature_code":"PPL",
    "gn:name":"Colonia Villa Colombia",
    "gn:population":52,
    "gn:timezone":"America/Mexico_City",
    "iso:country":"MX",
    "wof:name":"Colonia Villa Colombia",
    "wof:placetype":"locality",
    "wof:population":52
},
  "geometry": {"coordinates":[-100.65582999999999,20.49556],"type":"Point"}
}