{
  "type": "Feature",
  "properties": {
    "gn:admin1_code":"15",
    "gn:admin2_code":"71.0",
    "gn:asciiname":"San Isidrito",
    "gn:country_code":"MX",
    "gn:dem":2339,
    "gn:feature_class":"P",
    "gn:feature_code":"PPL",
    "gn:name":"San Isidrito",
    "gn:population":62,
    "gn:timezone":"America/Mexico_City",
    "iso:country":"MX",
    "wof:name":"San Isidrito",
    "wof:placetype":"locality",
    "wof:population":62
},
  "geometry": {"coordinates":[-99.80471,20.19752],"type":"Point"}
}