{
  "type": "Feature",
  "properties": {
    "gn:admin1_code":"16",
    "gn:admin2_code":"82.0",
    "gn:asciiname":"El Zarzal",
    "gn:country_code":"MX",
    "gn:dem":2131,
    "gn:feature_class":"P",
    "gn:feature_code":"PPL",
    "gn:name":"El Zarzal",
    "gn:population":9,
    "gn:timezone":"America/Mexico_City",
    "iso:country":"MX",
    "wof:name":"El Zarzal",
    "wof:placetype":"locality",
    "wof:population":9
},
  "geometry": {"coordinates":[-101.40722,19.31111],"type":"Point"}
}