{
  "type": "Feature",
  "properties": {
    "gn:admin1_code":"13",
    "gn:admin2_code":"46.0",
    "gn:asciiname":"Melchor Ocampo",
    "gn:country_code":"MX",
    "gn:dem":261,
    "gn:feature_class":"P",
    "gn:feature_code":"PPL",
    "gn:name":"Melchor Ocampo",
    "gn:population":135,
    "gn:timezone":"America/Mexico_City",
    "iso:country":"MX",
    "wof:name":"Melchor Ocampo",
    "wof:placetype":"locality",
    "wof:population":135
},
  "geometry": {"coordinates":[-98.64861000000001,21.13333],"type":"Point"}
}