{
  "type": "Feature",
  "properties": {
    "gn:admin1_code":"7",
    "gn:admin2_code":"38.0",
    "gn:asciiname":"El Mulato Viejo",
    "gn:country_code":"MX",
    "gn:dem":626,
    "gn:feature_class":"P",
    "gn:feature_code":"PPL",
    "gn:name":"El Mulato Viejo",
    "gn:population":0,
    "gn:timezone":"America/Monterrey",
    "iso:country":"MX",
    "name:spa_x_preferred":[
        "El Mulato Viejo"
    ],
    "name:und_x_variant":[
        "Rancho El Mulato"
    ],
    "wof:name":"El Mulato Viejo",
    "wof:placetype":"locality"
},
  "geometry": {"coordinates":[-101.58566,28.48475],"type":"Point"}
}