{
  "type": "Feature",
  "properties": {
    "gn:admin1_code":"12",
    "gn:admin2_code":"36.0",
    "gn:asciiname":"Llano Grande de los Hilarios",
    "gn:country_code":"MX",
    "gn:dem":699,
    "gn:feature_class":"P",
    "gn:feature_code":"PPL",
    "gn:name":"Llano Grande de los Hilarios",
    "gn:population":0,
    "gn:timezone":"America/Mexico_City",
    "iso:country":"MX",
    "name:spa_x_preferred":[
        "Llano Grande de los Hilarios"
    ],
    "name:spa_x_variant":[
        "Llano Grande de los Hilario"
    ],
    "name:und_x_variant":[
        "Llano Grande"
    ],
    "wof:name":"Llano Grande de los Hilarios",
    "wof:placetype":"locality"
},
  "geometry": {"coordinates":[-98.43944999999999,16.76039],"type":"Point"}
}