{
  "type": "Feature",
  "properties": {
    "gn:admin1_code":"26.0",
    "gn:admin2_code":"42.0",
    "gn:asciiname":"La Cruz",
    "gn:country_code":"MX",
    "gn:dem":40,
    "gn:feature_class":"P",
    "gn:feature_code":"PPL",
    "gn:name":"La Cruz",
    "gn:population":59,
    "gn:timezone":"America/Hermosillo",
    "iso:country":"MX",
    "wof:name":"La Cruz",
    "wof:placetype":"locality",
    "wof:population":59
},
  "geometry": {"coordinates":[-109.42471999999999,27.13972],"type":"Point"}
}