{
  "type": "Feature",
  "properties": {
    "gn:admin1_code":"2",
    "gn:admin2_code":"2",
    "gn:asciiname":"Rancho Viejo (Progreso Cuarta Seccion)",
    "gn:country_code":"MX",
    "gn:dem":0,
    "gn:feature_class":"P",
    "gn:feature_code":"PPL",
    "gn:name":"Rancho Viejo (Progreso Cuarta Secci\u00f3n)",
    "gn:population":10,
    "gn:timezone":"America/Tijuana",
    "iso:country":"MX",
    "name:und_x_variant":[
        "Rancho Viejo (Progreso Cuarta Secci\u00f3n)"
    ],
    "wof:name":"Rancho Viejo (Progreso Cuarta Seccion)",
    "wof:placetype":"locality",
    "wof:population":10
},
  "geometry": {"coordinates":[-115.60972,32.58917],"type":"Point"}
}