{
  "type": "Feature",
  "properties": {
    "gn:admin1_code":"14.0",
    "gn:admin2_code":"53.0",
    "gn:asciiname":"San Isidro del Jagueey",
    "gn:country_code":"MX",
    "gn:dem":1911,
    "gn:feature_class":"P",
    "gn:feature_code":"PPL",
    "gn:name":"San Isidro del Jag\u00fcey",
    "gn:population":0,
    "gn:timezone":"America/Mexico_City",
    "iso:country":"MX",
    "name:spa_x_preferred":[
        "San Isidro del Jag\u00fcey"
    ],
    "wof:name":"San Isidro del Jagueey",
    "wof:placetype":"locality"
},
  "geometry": {"coordinates":[-101.99433999999999,21.35322],"type":"Point"}
}