{
  "type": "Feature",
  "properties": {
    "gn:admin1_code":"6.0",
    "gn:admin2_code":"31.0",
    "gn:asciiname":"La Diana",
    "gn:country_code":"MX",
    "gn:dem":2277,
    "gn:feature_class":"P",
    "gn:feature_code":"PPL",
    "gn:name":"La Diana",
    "gn:population":0,
    "gn:timezone":"America/Chihuahua",
    "iso:country":"MX",
    "name:spa_x_preferred":[
        "La Diana"
    ],
    "name:spa_x_variant":[
        "Rancho la Diana"
    ],
    "wof:name":"La Diana",
    "wof:placetype":"locality"
},
  "geometry": {"coordinates":[-107.08512,28.41471],"type":"Point"}
}