{
  "type": "Feature",
  "properties": {
    "gn:admin1_code":"3.0",
    "gn:admin2_code":"3.0",
    "gn:asciiname":"Boca del Alamo",
    "gn:country_code":"MX",
    "gn:dem":16,
    "gn:feature_class":"P",
    "gn:feature_code":"PPL",
    "gn:name":"Boca del Alamo",
    "gn:population":0,
    "gn:timezone":"America/Mazatlan",
    "iso:country":"MX",
    "name:spa_x_preferred":[
        "Boca del Alamo"
    ],
    "name:spa_x_variant":[
        "Boca de \u00c1lamo"
    ],
    "wof:name":"Boca del Alamo",
    "wof:placetype":"locality"
},
  "geometry": {"coordinates":[-109.80389,23.89424],"type":"Point"}
}