{
  "type": "Feature",
  "properties": {
    "gn:admin1_code":"7.0",
    "gn:admin2_code":"35.0",
    "gn:asciiname":"Barrial de Guadalupe",
    "gn:country_code":"MX",
    "gn:dem":1325,
    "gn:feature_class":"P",
    "gn:feature_code":"PPL",
    "gn:name":"Barrial de Guadalupe",
    "gn:population":0,
    "gn:timezone":"America/Monterrey",
    "iso:country":"MX",
    "name:spa_x_preferred":[
        "Barrial de Guadalupe"
    ],
    "wof:name":"Barrial de Guadalupe",
    "wof:placetype":"locality"
},
  "geometry": {"coordinates":[-103.24651,24.99951],"type":"Point"}
}