{
  "type": "Feature",
  "properties": {
    "gn:admin1_code":"15",
    "gn:admin2_code":"38.0",
    "gn:asciiname":"Caixte",
    "gn:country_code":"MX",
    "gn:dem":2997,
    "gn:feature_class":"P",
    "gn:feature_code":"PPL",
    "gn:name":"Caixte",
    "gn:population":114,
    "gn:timezone":"America/Mexico_City",
    "iso:country":"MX",
    "wof:name":"Caixte",
    "wof:placetype":"locality",
    "wof:population":114
},
  "geometry": {"coordinates":[-99.42912,19.55959],"type":"Point"}
}