{
  "type": "Feature",
  "properties": {
    "gn:admin1_code":"14",
    "gn:admin2_code":"93.0",
    "gn:asciiname":"La Loma (Loma de Enmedio)",
    "gn:country_code":"MX",
    "gn:dem":1842,
    "gn:feature_class":"P",
    "gn:feature_code":"PPL",
    "gn:name":"La Loma (Loma de Enmedio)",
    "gn:population":652,
    "gn:timezone":"America/Mexico_City",
    "iso:country":"MX",
    "wof:name":"La Loma (Loma de Enmedio)",
    "wof:placetype":"locality",
    "wof:population":652
},
  "geometry": {"coordinates":[-102.73917,20.79806],"type":"Point"}
}