{
  "type": "Feature",
  "properties": {
    "gn:admin1_code":"25.0",
    "gn:admin2_code":"12.0",
    "gn:asciiname":"Coacoyoles",
    "gn:country_code":"MX",
    "gn:dem":271,
    "gn:feature_class":"P",
    "gn:feature_code":"PPL",
    "gn:name":"Coacoyoles",
    "gn:population":0,
    "gn:timezone":"America/Mazatlan",
    "iso:country":"MX",
    "name:spa_x_preferred":[
        "Coacoyoles"
    ],
    "name:und_x_variant":[
        "Coacoyol",
        "Cocoyoles"
    ],
    "wof:name":"Coacoyoles",
    "wof:placetype":"locality"
},
  "geometry": {"coordinates":[-106.17395999999999,23.61895],"type":"Point"}
}