{
  "type": "Feature",
  "properties": {
    "gn:admin1_code":"5.0",
    "gn:admin2_code":"107.0",
    "gn:asciiname":"Acambaro",
    "gn:country_code":"MX",
    "gn:dem":624,
    "gn:feature_class":"P",
    "gn:feature_code":"PPL",
    "gn:name":"Ac\u00e1mbaro",
    "gn:population":0,
    "gn:timezone":"America/Mexico_City",
    "iso:country":"MX",
    "name:spa_x_preferred":[
        "Ac\u00e1mbaro"
    ],
    "wof:name":"Acambaro",
    "wof:placetype":"locality"
},
  "geometry": {"coordinates":[-93.31954,16.12294],"type":"Point"}
}