{
  "type": "Feature",
  "properties": {
    "gn:admin1_code":"5",
    "gn:admin2_code":"65.0",
    "gn:asciiname":"La Asuncion",
    "gn:country_code":"MX",
    "gn:dem":179,
    "gn:feature_class":"P",
    "gn:feature_code":"PPL",
    "gn:name":"La Asunci\u00f3n",
    "gn:population":129,
    "gn:timezone":"America/Mexico_City",
    "iso:country":"MX",
    "name:und_x_variant":[
        "La Asunci\u00f3n"
    ],
    "wof:name":"La Asuncion",
    "wof:placetype":"locality",
    "wof:population":129
},
  "geometry": {"coordinates":[-91.67083,17.28472],"type":"Point"}
}