{
  "type": "Feature",
  "properties": {
    "gn:admin1_code":"6.0",
    "gn:admin2_code":"30.0",
    "gn:asciiname":"Guazapares",
    "gn:country_code":"MX",
    "gn:dem":1589,
    "gn:feature_class":"P",
    "gn:feature_code":"PPL",
    "gn:name":"Guazapares",
    "gn:population":0,
    "gn:timezone":"America/Chihuahua",
    "iso:country":"MX",
    "name:und_x_variant":[
        "Guazaparez",
        "Guazapares"
    ],
    "wof:name":"Guazapares",
    "wof:placetype":"locality"
},
  "geometry": {"coordinates":[-108.28069000000001,27.37251],"type":"Point"}
}