{
  "type": "Feature",
  "properties": {
    "gn:admin1_code":"25",
    "gn:admin2_code":"7.0",
    "gn:asciiname":"Las Igualamas",
    "gn:country_code":"MX",
    "gn:dem":640,
    "gn:feature_class":"P",
    "gn:feature_code":"PPL",
    "gn:name":"Las Igualamas",
    "gn:population":0,
    "gn:timezone":"America/Mazatlan",
    "iso:country":"MX",
    "name:spa_x_preferred":[
        "Las Igualamas"
    ],
    "wof:name":"Las Igualamas",
    "wof:placetype":"locality"
},
  "geometry": {"coordinates":[-108.10974,26.81597],"type":"Point"}
}