{
  "type": "Feature",
  "properties": {
    "gn:admin1_code":"2.0",
    "gn:admin2_code":"4.0",
    "gn:asciiname":"Ejido General Francisco Villa",
    "gn:country_code":"MX",
    "gn:dem":232,
    "gn:feature_class":"P",
    "gn:feature_code":"PPL",
    "gn:name":"Ejido General Francisco Villa",
    "gn:population":0,
    "gn:timezone":"America/Tijuana",
    "iso:country":"MX",
    "name:spa_x_preferred":[
        "Ejido General Francisco Villa"
    ],
    "wof:name":"Ejido General Francisco Villa",
    "wof:placetype":"locality"
},
  "geometry": {"coordinates":[-116.84863,32.49293],"type":"Point"}
}