{
  "type": "Feature",
  "properties": {
    "gn:admin1_code":"21",
    "gn:admin2_code":"164.0",
    "gn:asciiname":"El Paraiso",
    "gn:country_code":"MX",
    "gn:dem":2188,
    "gn:feature_class":"P",
    "gn:feature_code":"PPL",
    "gn:name":"El Para\u00edso",
    "gn:population":8,
    "gn:timezone":"America/Mexico_City",
    "iso:country":"MX",
    "name:und_x_variant":[
        "El Para\u00edso"
    ],
    "wof:name":"El Paraiso",
    "wof:placetype":"locality",
    "wof:population":8
},
  "geometry": {"coordinates":[-97.9169,18.93487],"type":"Point"}
}