{
  "type": "Feature",
  "properties": {
    "gn:admin1_code":"5",
    "gn:admin2_code":"20",
    "gn:asciiname":"Isla del Carmen",
    "gn:country_code":"MX",
    "gn:dem":532,
    "gn:feature_class":"P",
    "gn:feature_code":"PPL",
    "gn:name":"Isla del Carmen",
    "gn:population":10,
    "gn:timezone":"America/Mexico_City",
    "iso:country":"MX",
    "wof:name":"Isla del Carmen",
    "wof:placetype":"locality",
    "wof:population":10
},
  "geometry": {"coordinates":[-92.51917,15.98056],"type":"Point"}
}