{
  "type": "Feature",
  "properties": {
    "gn:admin1_code":"20",
    "gn:admin2_code":"451.0",
    "gn:asciiname":"Rio Jimenez",
    "gn:country_code":"MX",
    "gn:dem":2322,
    "gn:feature_class":"P",
    "gn:feature_code":"PPL",
    "gn:name":"R\u00edo Jim\u00e9nez",
    "gn:population":0,
    "gn:timezone":"America/Mexico_City",
    "iso:country":"MX",
    "wof:name":"Rio Jimenez",
    "wof:placetype":"locality"
},
  "geometry": {"coordinates":[-97.16667,17.68332999999999],"type":"Point"}
}