{
  "type": "Feature",
  "properties": {
    "gn:admin1_code":"5",
    "gn:admin2_code":"18.0",
    "gn:asciiname":"Buenavista (Matasanos)",
    "gn:country_code":"MX",
    "gn:dem":1421,
    "gn:feature_class":"P",
    "gn:feature_code":"PPL",
    "gn:name":"Buenavista (Matasanos)",
    "gn:population":1198,
    "gn:timezone":"America/Mexico_City",
    "iso:country":"MX",
    "wof:name":"Buenavista (Matasanos)",
    "wof:placetype":"locality",
    "wof:population":1198
},
  "geometry": {"coordinates":[-93.06694,17.10778],"type":"Point"}
}