{
  "type": "Feature",
  "properties": {
    "gn:admin1_code":"32",
    "gn:admin2_code":"2.0",
    "gn:asciiname":"El Quelele",
    "gn:country_code":"MX",
    "gn:dem":1930,
    "gn:feature_class":"P",
    "gn:feature_code":"PPL",
    "gn:name":"El Quelele",
    "gn:population":6,
    "gn:timezone":"America/Mexico_City",
    "iso:country":"MX",
    "wof:name":"El Quelele",
    "wof:placetype":"locality",
    "wof:population":6
},
  "geometry": {"coordinates":[-102.68222,21.485],"type":"Point"}
}