{
  "type": "Feature",
  "properties": {
    "gn:admin1_code":"21",
    "gn:admin2_code":"89.0",
    "gn:asciiname":"Cuamaxalco",
    "gn:country_code":"MX",
    "gn:dem":1207,
    "gn:feature_class":"P",
    "gn:feature_code":"PPL",
    "gn:name":"Cuamaxalco",
    "gn:population":301,
    "gn:timezone":"America/Mexico_City",
    "iso:country":"MX",
    "wof:name":"Cuamaxalco",
    "wof:placetype":"locality",
    "wof:population":301
},
  "geometry": {"coordinates":[-97.85563,20.19863],"type":"Point"}
}