{
  "type": "Feature",
  "properties": {
    "gn:admin1_code":"26",
    "gn:admin2_code":"4",
    "gn:asciiname":"Maria Eugenia (Los Chacuales)",
    "gn:country_code":"MX",
    "gn:dem":378,
    "gn:feature_class":"P",
    "gn:feature_code":"PPL",
    "gn:name":"Mar\u00eda Eugenia (Los Chacuales)",
    "gn:population":13,
    "gn:timezone":"America/Hermosillo",
    "iso:country":"MX",
    "name:und_x_variant":[
        "Mar\u00eda Eugenia (Los Chacuales)"
    ],
    "wof:name":"Maria Eugenia (Los Chacuales)",
    "wof:placetype":"locality",
    "wof:population":13
},
  "geometry": {"coordinates":[-111.82306,30.59556],"type":"Point"}
}