{
  "type": "Feature",
  "properties": {
    "gn:admin1_code":"30",
    "gn:admin2_code":"108.0",
    "gn:asciiname":"Rio Coatzacoalcos",
    "gn:country_code":"MX",
    "gn:dem":9,
    "gn:feature_class":"P",
    "gn:feature_code":"PPL",
    "gn:name":"R\u00edo Coatzacoalcos",
    "gn:population":0,
    "gn:timezone":"America/Mexico_City",
    "iso:country":"MX",
    "wof:name":"Rio Coatzacoalcos",
    "wof:placetype":"locality"
},
  "geometry": {"coordinates":[-94.46528000000001,18.01667],"type":"Point"}
}