{
  "type": "Feature",
  "properties": {
    "gn:admin1_code":"10",
    "gn:admin2_code":"8.0",
    "gn:asciiname":"San Francisco de la Palmita (La Palmita)",
    "gn:country_code":"MX",
    "gn:dem":2089,
    "gn:feature_class":"P",
    "gn:feature_code":"PPL",
    "gn:name":"San Francisco de la Palmita (La Palmita)",
    "gn:population":179,
    "gn:timezone":"America/Monterrey",
    "iso:country":"MX",
    "name:und_x_variant":[
        "La Palma",
        "San Francisco de la Palmita"
    ],
    "wof:name":"San Francisco de la Palmita (La Palmita)",
    "wof:placetype":"locality",
    "wof:population":179
},
  "geometry": {"coordinates":[-104.06227,24.59049],"type":"Point"}
}