{
  "type": "Feature",
  "properties": {
    "gn:admin1_code":"11",
    "gn:admin2_code":"33.0",
    "gn:asciiname":"San Jose de Guerrero (El Chiquito)",
    "gn:country_code":"MX",
    "gn:dem":1995,
    "gn:feature_class":"P",
    "gn:feature_code":"PPL",
    "gn:name":"San Jos\u00e9 de Guerrero (El Chiquito)",
    "gn:population":180,
    "gn:timezone":"America/Mexico_City",
    "iso:country":"MX",
    "name:und_x_variant":[
        "San Jos\u00e9 de Guerrero (El Chiquito)"
    ],
    "wof:name":"San Jose de Guerrero (El Chiquito)",
    "wof:placetype":"locality",
    "wof:population":180
},
  "geometry": {"coordinates":[-100.59139,21.16111],"type":"Point"}
}