{
  "type": "Feature",
  "properties": {
    "gn:admin1_code":"26",
    "gn:admin2_code":"33.0",
    "gn:asciiname":"Mochibampo",
    "gn:country_code":"MX",
    "gn:dem":5,
    "gn:feature_class":"P",
    "gn:feature_code":"PPL",
    "gn:name":"Mochibampo",
    "gn:population":0,
    "gn:timezone":"America/Hermosillo",
    "iso:country":"MX",
    "name:spa_x_preferred":[
        "Mochibampo"
    ],
    "wof:name":"Mochibampo",
    "wof:placetype":"locality"
},
  "geometry": {"coordinates":[-109.6116,26.75107],"type":"Point"}
}