{
  "type": "Feature",
  "properties": {
    "gn:admin1_code":"14",
    "gn:admin2_code":"35",
    "gn:asciiname":"El Correo",
    "gn:country_code":"MX",
    "gn:dem":2030,
    "gn:feature_class":"P",
    "gn:feature_code":"PPL",
    "gn:name":"El Correo",
    "gn:population":11,
    "gn:timezone":"America/Mexico_City",
    "iso:country":"MX",
    "name:ast_x_preferred":[
        "El Correo"
    ],
    "name:cat_x_preferred":[
        "El Correo"
    ],
    "name:deu_x_preferred":[
        "El Correo"
    ],
    "name:eus_x_preferred":[
        "El Correo"
    ],
    "name:fra_x_preferred":[
        "El Correo"
    ],
    "name:jpn_x_preferred":[
        "\u30a8\u30eb\u30fb\u30b3\u30ec\u30aa"
    ],
    "name:spa_x_preferred":[
        "El Correo"
    ],
    "wof:name":"El Correo",
    "wof:placetype":"locality",
    "wof:population":11
},
  "geometry": {"coordinates":[-102.16472,21.68861],"type":"Point"}
}