{
  "type": "Feature",
  "properties": {
    "gn:admin1_code":"14",
    "gn:admin2_code":"53",
    "gn:asciiname":"Lagunillas",
    "gn:country_code":"MX",
    "gn:dem":2208,
    "gn:feature_class":"P",
    "gn:feature_code":"PPL",
    "gn:name":"Lagunillas",
    "gn:population":27,
    "gn:timezone":"America/Mexico_City",
    "iso:country":"MX",
    "wof:name":"Lagunillas",
    "wof:placetype":"locality",
    "wof:population":27
},
  "geometry": {"coordinates":[-101.70944,21.34778],"type":"Point"}
}