{
  "type": "Feature",
  "properties": {
    "gn:admin1_code":"5",
    "gn:admin2_code":"69.0",
    "gn:asciiname":"Corralejo",
    "gn:country_code":"MX",
    "gn:dem":39,
    "gn:feature_class":"P",
    "gn:feature_code":"PPL",
    "gn:name":"Corralejo",
    "gn:population":4,
    "gn:timezone":"America/Mexico_City",
    "iso:country":"MX",
    "name:ceb_x_preferred":[
        "Corralejo"
    ],
    "name:deu_x_preferred":[
        "Corralejo"
    ],
    "name:fin_x_preferred":[
        "Corralejo"
    ],
    "name:fra_x_preferred":[
        "Corralejo"
    ],
    "name:glg_x_preferred":[
        "Corralejo"
    ],
    "name:ita_x_preferred":[
        "Corralejo"
    ],
    "name:nld_x_preferred":[
        "Corralejo"
    ],
    "name:pol_x_preferred":[
        "Corralejo"
    ],
    "name:spa_x_preferred":[
        "Corralejo"
    ],
    "wof:name":"Corralejo",
    "wof:placetype":"locality",
    "wof:population":4
},
  "geometry": {"coordinates":[-93.26806000000001,15.72917],"type":"Point"}
}