{
  "type": "Feature",
  "properties": {
    "gn:admin1_code":"30",
    "gn:admin2_code":"38.0",
    "gn:asciiname":"Llano de la Virgen",
    "gn:country_code":"MX",
    "gn:dem":882,
    "gn:feature_class":"P",
    "gn:feature_code":"PPL",
    "gn:name":"Llano de la Virgen",
    "gn:population":0,
    "gn:timezone":"America/Mexico_City",
    "iso:country":"MX",
    "name:spa_x_preferred":[
        "Llano de la Virgen"
    ],
    "wof:name":"Llano de la Virgen",
    "wof:placetype":"locality"
},
  "geometry": {"coordinates":[-96.91123,19.3924],"type":"Point"}
}