{
  "type": "Feature",
  "properties": {
    "gn:admin1_code":"14.0",
    "gn:admin2_code":"100.0",
    "gn:asciiname":"Los Coyotes",
    "gn:country_code":"MX",
    "gn:dem":50,
    "gn:feature_class":"P",
    "gn:feature_code":"PPL",
    "gn:name":"Los Coyotes",
    "gn:population":0,
    "gn:timezone":"America/Mexico_City",
    "iso:country":"MX",
    "name:spa_x_preferred":[
        "Los Coyotes"
    ],
    "wof:name":"Los Coyotes",
    "wof:placetype":"locality"
},
  "geometry": {"coordinates":[-105.2698,19.95511],"type":"Point"}
}