{
  "type": "Feature",
  "properties": {
    "gn:admin1_code":"15",
    "gn:admin2_code":"71.0",
    "gn:asciiname":"Barrio Lazaro Cardenas (San Rafael)",
    "gn:country_code":"MX",
    "gn:dem":2270,
    "gn:feature_class":"P",
    "gn:feature_code":"PPL",
    "gn:name":"Barrio L\u00e1zaro C\u00e1rdenas (San Rafael)",
    "gn:population":616,
    "gn:timezone":"America/Mexico_City",
    "iso:country":"MX",
    "wof:name":"Barrio Lazaro Cardenas (San Rafael)",
    "wof:placetype":"locality",
    "wof:population":616
},
  "geometry": {"coordinates":[-99.83556,20.24861],"type":"Point"}
}