{
  "type": "Feature",
  "properties": {
    "gn:admin1_code":"31.0",
    "gn:asciiname":"Los Reyes",
    "gn:country_code":"MX",
    "gn:dem":20,
    "gn:feature_class":"P",
    "gn:feature_code":"PPL",
    "gn:name":"Los Reyes",
    "gn:population":0,
    "gn:timezone":"America/Merida",
    "iso:country":"MX",
    "name:spa_x_preferred":[
        "Los Reyes"
    ],
    "wof:name":"Los Reyes",
    "wof:placetype":"locality"
},
  "geometry": {"coordinates":[-88.29355,21.16316],"type":"Point"}
}