{
  "type": "Feature",
  "properties": {
    "gn:admin1_code":"10.0",
    "gn:admin2_code":"9.0",
    "gn:asciiname":"El Mortero",
    "gn:country_code":"MX",
    "gn:dem":1958,
    "gn:feature_class":"P",
    "gn:feature_code":"PPL",
    "gn:name":"El Mortero",
    "gn:population":0,
    "gn:timezone":"America/Monterrey",
    "iso:country":"MX",
    "name:spa_x_preferred":[
        "El Mortero"
    ],
    "wof:name":"El Mortero",
    "wof:placetype":"locality"
},
  "geometry": {"coordinates":[-105.88423,25.89877000000001],"type":"Point"}
}