{
  "type": "Feature",
  "properties": {
    "gn:admin1_code":"20",
    "gn:admin2_code":"277",
    "gn:asciiname":"Santa Catarina la Canada",
    "gn:country_code":"MX",
    "gn:dem":1736,
    "gn:feature_class":"P",
    "gn:feature_code":"PPL",
    "gn:name":"Santa Catarina la Ca\u00f1ada",
    "gn:population":44,
    "gn:timezone":"America/Mexico_City",
    "iso:country":"MX",
    "name:und_x_variant":[
        "Santa Catarina la Ca\u00f1ada"
    ],
    "wof:name":"Santa Catarina la Canada",
    "wof:placetype":"locality",
    "wof:population":44
},
  "geometry": {"coordinates":[-97.08972,16.54694],"type":"Point"}
}