{
  "type": "Feature",
  "properties": {
    "gn:admin1_code":"30",
    "gn:admin2_code":"107.0",
    "gn:asciiname":"Molinillo",
    "gn:country_code":"MX",
    "gn:dem":1319,
    "gn:feature_class":"P",
    "gn:feature_code":"PPL",
    "gn:name":"Molinillo",
    "gn:population":386,
    "gn:timezone":"America/Mexico_City",
    "iso:country":"MX",
    "wof:name":"Molinillo",
    "wof:placetype":"locality",
    "wof:population":386
},
  "geometry": {"coordinates":[-97.12833000000001,19.70889],"type":"Point"}
}