{
  "type": "Feature",
  "properties": {
    "gn:admin1_code":"14",
    "gn:admin2_code":"93",
    "gn:asciiname":"Puerta del Cuatro",
    "gn:country_code":"MX",
    "gn:dem":1992,
    "gn:feature_class":"P",
    "gn:feature_code":"PPL",
    "gn:name":"Puerta del Cuatro",
    "gn:population":27,
    "gn:timezone":"America/Mexico_City",
    "iso:country":"MX",
    "wof:name":"Puerta del Cuatro",
    "wof:placetype":"locality",
    "wof:population":27
},
  "geometry": {"coordinates":[-102.64361,20.87667],"type":"Point"}
}