{
  "type": "Feature",
  "properties": {
    "gn:admin1_code":"6",
    "gn:admin2_code":"9.0",
    "gn:asciiname":"Recamachi",
    "gn:country_code":"MX",
    "gn:dem":2141,
    "gn:feature_class":"P",
    "gn:feature_code":"PPL",
    "gn:name":"Recamachi",
    "gn:population":0,
    "gn:timezone":"America/Chihuahua",
    "iso:country":"MX",
    "name:spa_x_preferred":[
        "Recamachi"
    ],
    "wof:name":"Recamachi",
    "wof:placetype":"locality"
},
  "geometry": {"coordinates":[-107.40186,27.65977],"type":"Point"}
}