{
  "type": "Feature",
  "properties": {
    "gn:admin1_code":"4",
    "gn:admin2_code":"8.0",
    "gn:asciiname":"La Costa",
    "gn:country_code":"MX",
    "gn:dem":2,
    "gn:feature_class":"P",
    "gn:feature_code":"PPL",
    "gn:name":"La Costa",
    "gn:population":0,
    "gn:timezone":"America/Merida",
    "iso:country":"MX",
    "name:ara_x_preferred":[
        "\u0644\u0627 \u0643\u0648\u0633\u062a\u0627"
    ],
    "wof:name":"La Costa",
    "wof:placetype":"locality"
},
  "geometry": {"coordinates":[-90.48081999999999,20.06037],"type":"Point"}
}