{
  "type": "Feature",
  "properties": {
    "gn:admin1_code":"32.0",
    "gn:asciiname":"El Con",
    "gn:country_code":"MX",
    "gn:dem":2200,
    "gn:feature_class":"P",
    "gn:feature_code":"PPL",
    "gn:name":"El Con",
    "gn:population":0,
    "gn:timezone":"America/Mexico_City",
    "iso:country":"MX",
    "name:spa_x_preferred":[
        "El Con"
    ],
    "wof:name":"El Con",
    "wof:placetype":"locality"
},
  "geometry": {"coordinates":[-101.57142,21.89675],"type":"Point"}
}