{
  "type": "Feature",
  "properties": {
    "gn:admin1_code":"2.0",
    "gn:admin2_code":"3.0",
    "gn:asciiname":"San Pablo",
    "gn:country_code":"MX",
    "gn:dem":603,
    "gn:feature_class":"P",
    "gn:feature_code":"PPL",
    "gn:name":"San Pablo",
    "gn:population":2,
    "gn:timezone":"America/Tijuana",
    "iso:country":"MX",
    "name:spa_x_preferred":[
        "San Pablo"
    ],
    "name:und_x_variant":[
        "La Norte\u00f1a"
    ],
    "wof:name":"San Pablo",
    "wof:placetype":"locality",
    "wof:population":2
},
  "geometry": {"coordinates":[-116.52916999999999,32.56028],"type":"Point"}
}