{
  "type": "Feature",
  "properties": {
    "gn:admin1_code":"26.0",
    "gn:admin2_code":"15.0",
    "gn:asciiname":"El Morado",
    "gn:country_code":"MX",
    "gn:dem":1625,
    "gn:feature_class":"P",
    "gn:feature_code":"PPL",
    "gn:name":"El Morado",
    "gn:population":0,
    "gn:timezone":"America/Hermosillo",
    "iso:country":"MX",
    "name:spa_x_preferred":[
        "El Morado"
    ],
    "wof:name":"El Morado",
    "wof:placetype":"locality"
},
  "geometry": {"coordinates":[-108.89472000000001,30.61944],"type":"Point"}
}