{
  "type": "Feature",
  "properties": {
    "gn:admin1_code":"28",
    "gn:admin2_code":"32.0",
    "gn:asciiname":"El Becerro",
    "gn:country_code":"MX",
    "gn:dem":129,
    "gn:feature_class":"P",
    "gn:feature_code":"PPL",
    "gn:name":"El Becerro",
    "gn:population":0,
    "gn:timezone":"America/Monterrey",
    "iso:country":"MX",
    "name:spa_x_preferred":[
        "El Becerro"
    ],
    "wof:name":"El Becerro",
    "wof:placetype":"locality"
},
  "geometry": {"coordinates":[-98.55988000000001,25.60375],"type":"Point"}
}