{
  "type": "Feature",
  "properties": {
    "gn:admin1_code":"14.0",
    "gn:admin2_code":"15.0",
    "gn:asciiname":"Los Paredones",
    "gn:country_code":"MX",
    "gn:dem":1235,
    "gn:feature_class":"P",
    "gn:feature_code":"PPL",
    "gn:name":"Los Paredones",
    "gn:population":0,
    "gn:timezone":"America/Mexico_City",
    "iso:country":"MX",
    "name:spa_x_preferred":[
        "Los Paredones"
    ],
    "wof:name":"Los Paredones",
    "wof:placetype":"locality"
},
  "geometry": {"coordinates":[-104.41543,19.81946],"type":"Point"}
}