{
  "type": "Feature",
  "properties": {
    "gn:admin1_code":"9",
    "gn:admin2_code":"9.0",
    "gn:asciiname":"Metenco",
    "gn:country_code":"MX",
    "gn:dem":2643,
    "gn:feature_class":"P",
    "gn:feature_code":"PPL",
    "gn:name":"Metenco",
    "gn:population":226,
    "gn:timezone":"America/Mexico_City",
    "iso:country":"MX",
    "wof:name":"Metenco",
    "wof:placetype":"locality",
    "wof:population":226
},
  "geometry": {"coordinates":[-99.08068,19.20436],"type":"Point"}
}