{
  "type": "Feature",
  "properties": {
    "gn:admin1_code":"11",
    "gn:admin2_code":"23",
    "gn:asciiname":"Tepamal de Pimentel",
    "gn:country_code":"MX",
    "gn:dem":1811,
    "gn:feature_class":"P",
    "gn:feature_code":"PPL",
    "gn:name":"Tepamal de Pimentel",
    "gn:population":24,
    "gn:timezone":"America/Mexico_City",
    "iso:country":"MX",
    "wof:name":"Tepamal de Pimentel",
    "wof:placetype":"locality",
    "wof:population":24
},
  "geometry": {"coordinates":[-101.75444,20.28333],"type":"Point"}
}