{
  "type": "Feature",
  "properties": {
    "gn:admin1_code":"10",
    "gn:admin2_code":"32",
    "gn:asciiname":"La Batea",
    "gn:country_code":"MX",
    "gn:dem":2417,
    "gn:feature_class":"P",
    "gn:feature_code":"PPL",
    "gn:name":"La Batea",
    "gn:population":39,
    "gn:timezone":"America/Monterrey",
    "iso:country":"MX",
    "wof:name":"La Batea",
    "wof:placetype":"locality",
    "wof:population":39
},
  "geometry": {"coordinates":[-106.30785,24.95998],"type":"Point"}
}