{
  "type": "Feature",
  "properties": {
    "gn:admin1_code":"16",
    "gn:admin2_code":"82.0",
    "gn:asciiname":"Pueblo Viejo de Aramutaro",
    "gn:country_code":"MX",
    "gn:dem":1917,
    "gn:feature_class":"P",
    "gn:feature_code":"PPL",
    "gn:name":"Pueblo Viejo de Aramutaro",
    "gn:population":0,
    "gn:timezone":"America/Mexico_City",
    "iso:country":"MX",
    "name:spa_x_preferred":[
        "Pueblo Viejo de Aramutaro"
    ],
    "wof:name":"Pueblo Viejo de Aramutaro",
    "wof:placetype":"locality"
},
  "geometry": {"coordinates":[-101.5748,19.19751],"type":"Point"}
}