{
  "type": "Feature",
  "properties": {
    "gn:admin1_code":"14.0",
    "gn:asciiname":"Las Pintas",
    "gn:country_code":"MX",
    "gn:dem":1898,
    "gn:feature_class":"P",
    "gn:feature_code":"PPL",
    "gn:name":"Las Pintas",
    "gn:population":0,
    "gn:timezone":"America/Mexico_City",
    "iso:country":"MX",
    "name:spa_x_preferred":[
        "Las Pintas"
    ],
    "wof:name":"Las Pintas",
    "wof:placetype":"locality"
},
  "geometry": {"coordinates":[-102.02699,21.1948],"type":"Point"}
}