{
  "type": "Feature",
  "properties": {
    "gn:admin1_code":"27",
    "gn:admin2_code":"12.0",
    "gn:asciiname":"Guacamaya",
    "gn:country_code":"MX",
    "gn:dem":4,
    "gn:feature_class":"P",
    "gn:feature_code":"PPL",
    "gn:name":"Guacamaya",
    "gn:population":72,
    "gn:timezone":"America/Mexico_City",
    "iso:country":"MX",
    "wof:name":"Guacamaya",
    "wof:placetype":"locality",
    "wof:population":72
},
  "geometry": {"coordinates":[-92.28028,17.84806],"type":"Point"}
}