{
  "type": "Feature",
  "properties": {
    "gn:admin1_code":"14.0",
    "gn:admin2_code":"62.0",
    "gn:asciiname":"Arroyo Zarco",
    "gn:country_code":"MX",
    "gn:dem":1533,
    "gn:feature_class":"P",
    "gn:feature_code":"PPL",
    "gn:name":"Arroyo Zarco",
    "gn:population":0,
    "gn:timezone":"America/Mexico_City",
    "iso:country":"MX",
    "name:spa_x_preferred":[
        "Arroyo Zarco"
    ],
    "wof:name":"Arroyo Zarco",
    "wof:placetype":"locality"
},
  "geometry": {"coordinates":[-104.41422,20.45856],"type":"Point"}
}