{
  "type": "Feature",
  "properties": {
    "gn:admin1_code":"6.0",
    "gn:asciiname":"El Doce",
    "gn:country_code":"MX",
    "gn:dem":1237,
    "gn:feature_class":"P",
    "gn:feature_code":"PPL",
    "gn:name":"El Doce",
    "gn:population":0,
    "gn:timezone":"America/Chihuahua",
    "iso:country":"MX",
    "name:spa_x_preferred":[
        "El Doce"
    ],
    "wof:name":"El Doce",
    "wof:placetype":"locality"
},
  "geometry": {"coordinates":[-105.52737,28.06406],"type":"Point"}
}