{
  "type": "Feature",
  "properties": {
    "gn:admin1_code":"10",
    "gn:admin2_code":"21.0",
    "gn:asciiname":"San Juan de Mogotes",
    "gn:country_code":"MX",
    "gn:dem":1937,
    "gn:feature_class":"P",
    "gn:feature_code":"PPL",
    "gn:name":"San Juan de Mogotes",
    "gn:population":0,
    "gn:timezone":"America/Monterrey",
    "iso:country":"MX",
    "name:spa_x_preferred":[
        "San Juan de Mogotes"
    ],
    "name:spa_x_variant":[
        "Las Escobas"
    ],
    "name:und_x_variant":[
        "San Juan de los Mogotes"
    ],
    "wof:name":"San Juan de Mogotes",
    "wof:placetype":"locality"
},
  "geometry": {"coordinates":[-104.07170000000001,24.67562],"type":"Point"}
}