{
  "type": "Feature",
  "properties": {
    "gn:admin1_code":"16.0",
    "gn:admin2_code":"82.0",
    "gn:asciiname":"Paso de Serrano",
    "gn:country_code":"MX",
    "gn:dem":2030,
    "gn:feature_class":"P",
    "gn:feature_code":"PPL",
    "gn:name":"Paso de Serrano",
    "gn:population":0,
    "gn:timezone":"America/Mexico_City",
    "iso:country":"MX",
    "name:spa_x_preferred":[
        "Paso de Serrano"
    ],
    "wof:name":"Paso de Serrano",
    "wof:placetype":"locality"
},
  "geometry": {"coordinates":[-101.51917,19.26192],"type":"Point"}
}