{
  "type": "Feature",
  "properties": {
    "gn:admin1_code":"2.0",
    "gn:admin2_code":"2.0",
    "gn:asciiname":"Colonia Ahumada",
    "gn:country_code":"MX",
    "gn:dem":4,
    "gn:feature_class":"P",
    "gn:feature_code":"PPL",
    "gn:name":"Colonia Ahumada",
    "gn:population":13,
    "gn:timezone":"America/Tijuana",
    "iso:country":"MX",
    "name:spa_x_preferred":[
        "Ahumada"
    ],
    "wof:name":"Colonia Ahumada",
    "wof:placetype":"locality",
    "wof:population":13
},
  "geometry": {"coordinates":[-115.50028,32.59],"type":"Point"}
}