{
  "type": "Feature",
  "properties": {
    "gn:admin1_code":"4.0",
    "gn:admin2_code":"3.0",
    "gn:asciiname":"San Andres",
    "gn:country_code":"MX",
    "gn:dem":49,
    "gn:feature_class":"P",
    "gn:feature_code":"PPL",
    "gn:name":"San Andr\u00e9s",
    "gn:population":0,
    "gn:timezone":"America/Merida",
    "iso:country":"MX",
    "name:spa_x_preferred":[
        "San Andr\u00e9s"
    ],
    "wof:name":"San Andres",
    "wof:placetype":"locality"
},
  "geometry": {"coordinates":[-91.06446,18.42007000000001],"type":"Point"}
}