{
  "type": "Feature",
  "properties": {
    "gn:admin1_code":"31",
    "gn:admin2_code":"48.0",
    "gn:asciiname":"Boxol",
    "gn:country_code":"MX",
    "gn:dem":8,
    "gn:feature_class":"P",
    "gn:feature_code":"PPL",
    "gn:name":"Boxol",
    "gn:population":0,
    "gn:timezone":"America/Merida",
    "iso:country":"MX",
    "name:spa_x_preferred":[
        "Boxol"
    ],
    "wof:name":"Boxol",
    "wof:placetype":"locality"
},
  "geometry": {"coordinates":[-90.09696,20.73122],"type":"Point"}
}