{
  "type": "Feature",
  "properties": {
    "gn:admin1_code":"32",
    "gn:admin2_code":"20",
    "gn:asciiname":"Rancho de los Ortiz",
    "gn:country_code":"MX",
    "gn:dem":2048,
    "gn:feature_class":"P",
    "gn:feature_code":"PPL",
    "gn:name":"Rancho de los Ortiz",
    "gn:population":16,
    "gn:timezone":"America/Mexico_City",
    "iso:country":"MX",
    "wof:name":"Rancho de los Ortiz",
    "wof:placetype":"locality",
    "wof:population":16
},
  "geometry": {"coordinates":[-103.02833,22.68611],"type":"Point"}
}