{
  "type": "Feature",
  "properties": {
    "gn:admin1_code":"10",
    "gn:admin2_code":"13.0",
    "gn:asciiname":"Las Golondrinas",
    "gn:country_code":"MX",
    "gn:dem":1189,
    "gn:feature_class":"P",
    "gn:feature_code":"PPL",
    "gn:name":"Las Golondrinas",
    "gn:population":0,
    "gn:timezone":"America/Monterrey",
    "iso:country":"MX",
    "name:spa_x_preferred":[
        "Las Golondrinas"
    ],
    "wof:name":"Las Golondrinas",
    "wof:placetype":"locality"
},
  "geometry": {"coordinates":[-104.19683000000001,26.58517],"type":"Point"}
}