{
  "type": "Feature",
  "properties": {
    "gn:admin1_code":"17",
    "gn:admin2_code":"29.0",
    "gn:asciiname":"El Copalar",
    "gn:country_code":"MX",
    "gn:dem":1193,
    "gn:feature_class":"P",
    "gn:feature_code":"PPL",
    "gn:name":"El Copalar",
    "gn:population":162,
    "gn:timezone":"America/Mexico_City",
    "iso:country":"MX",
    "wof:name":"El Copalar",
    "wof:placetype":"locality",
    "wof:population":162
},
  "geometry": {"coordinates":[-99.10617999999999,18.853],"type":"Point"}
}