{
  "type": "Feature",
  "properties": {
    "gn:admin1_code":"6.0",
    "gn:admin2_code":"11.0",
    "gn:asciiname":"La Sierrita",
    "gn:country_code":"MX",
    "gn:dem":1461,
    "gn:feature_class":"P",
    "gn:feature_code":"PPL",
    "gn:name":"La Sierrita",
    "gn:population":0,
    "gn:timezone":"America/Chihuahua",
    "iso:country":"MX",
    "name:spa_x_preferred":[
        "La Sierrita"
    ],
    "name:und_x_variant":[
        "Guadalupe"
    ],
    "wof:name":"La Sierrita",
    "wof:placetype":"locality"
},
  "geometry": {"coordinates":[-104.54697,28.42904],"type":"Point"}
}