{
  "type": "Feature",
  "properties": {
    "gn:admin1_code":"28.0",
    "gn:admin2_code":"11.0",
    "gn:asciiname":"El Calamaco",
    "gn:country_code":"MX",
    "gn:dem":90,
    "gn:feature_class":"P",
    "gn:feature_code":"PPL",
    "gn:name":"El Calamaco",
    "gn:population":0,
    "gn:timezone":"America/Monterrey",
    "iso:country":"MX",
    "name:spa_x_preferred":[
        "El Calamaco"
    ],
    "wof:name":"El Calamaco",
    "wof:placetype":"locality"
},
  "geometry": {"coordinates":[-99.10250000000001,22.9375],"type":"Point"}
}