{
  "type": "Feature",
  "properties": {
    "gn:admin1_code":"32",
    "gn:admin2_code":"49.0",
    "gn:asciiname":"San Pedro de La Sierra",
    "gn:country_code":"MX",
    "gn:dem":1872,
    "gn:feature_class":"P",
    "gn:feature_code":"PPL",
    "gn:name":"San Pedro de La Sierra",
    "gn:population":0,
    "gn:timezone":"America/Mexico_City",
    "iso:country":"MX",
    "name:spa_x_preferred":[
        "San Pedro de La Sierra"
    ],
    "wof:name":"San Pedro de La Sierra",
    "wof:placetype":"locality"
},
  "geometry": {"coordinates":[-103.94302999999999,22.76972],"type":"Point"}
}