{
  "type": "Feature",
  "properties": {
    "gn:admin1_code":"6.0",
    "gn:admin2_code":"50.0",
    "gn:asciiname":"La Amelia",
    "gn:country_code":"MX",
    "gn:dem":1555,
    "gn:feature_class":"P",
    "gn:feature_code":"PPL",
    "gn:name":"La Amelia",
    "gn:population":0,
    "gn:timezone":"America/Chihuahua",
    "iso:country":"MX",
    "name:ceb_x_preferred":[
        "La Amelia"
    ],
    "name:ita_x_preferred":[
        "La Amelia"
    ],
    "name:spa_x_preferred":[
        "La Amelia"
    ],
    "name:swe_x_preferred":[
        "La Amelia"
    ],
    "name:und_x_variant":[
        "Rancho Amel\u00eda"
    ],
    "wof:name":"La Amelia",
    "wof:placetype":"locality"
},
  "geometry": {"coordinates":[-107.63578,30.72637000000001],"type":"Point"}
}