{
  "type": "Feature",
  "properties": {
    "gn:admin1_code":"25",
    "gn:admin2_code":"4.0",
    "gn:asciiname":"Los Bueyes",
    "gn:country_code":"MX",
    "gn:dem":600,
    "gn:feature_class":"P",
    "gn:feature_code":"PPL",
    "gn:name":"Los Bueyes",
    "gn:population":0,
    "gn:timezone":"America/Mazatlan",
    "iso:country":"MX",
    "name:spa_x_preferred":[
        "Los Bueyes"
    ],
    "wof:name":"Los Bueyes",
    "wof:placetype":"locality"
},
  "geometry": {"coordinates":[-105.96908000000001,23.62299],"type":"Point"}
}