{
  "type": "Feature",
  "properties": {
    "gn:admin1_code":"6.0",
    "gn:admin2_code":"29.0",
    "gn:asciiname":"La Cienega",
    "gn:cc2":"MX",
    "gn:country_code":"MX",
    "gn:dem":1431,
    "gn:feature_class":"P",
    "gn:feature_code":"PPL",
    "gn:name":"La Ci\u00e9nega",
    "gn:population":0,
    "gn:timezone":"America/Chihuahua",
    "iso:country":"MX",
    "name:ceb_x_preferred":[
        "La Cienega"
    ],
    "name:swe_x_preferred":[
        "La Cienega"
    ],
    "name:und_x_variant":[
        "Cienega",
        "La Ci\u00e9nega"
    ],
    "wof:name":"La Cienega",
    "wof:placetype":"locality"
},
  "geometry": {"coordinates":[-107.28333000000001,26.61667000000001],"type":"Point"}
}