{
  "type": "Feature",
  "properties": {
    "gn:admin1_code":"2.0",
    "gn:asciiname":"La Burra",
    "gn:country_code":"MX",
    "gn:dem":575,
    "gn:feature_class":"P",
    "gn:feature_code":"PPL",
    "gn:name":"La Burra",
    "gn:population":0,
    "gn:timezone":"America/Tijuana",
    "iso:country":"MX",
    "name:spa_x_preferred":[
        "La Burra"
    ],
    "wof:name":"La Burra",
    "wof:placetype":"locality"
},
  "geometry": {"coordinates":[-116.41404,31.93599],"type":"Point"}
}