{
  "type": "Feature",
  "properties": {
    "gn:admin1_code":"5.0",
    "gn:admin2_code":"57.0",
    "gn:asciiname":"San Antonio Tuixcum",
    "gn:country_code":"MX",
    "gn:dem":2182,
    "gn:feature_class":"P",
    "gn:feature_code":"PPL",
    "gn:name":"San Antonio Tuixc\u00fam",
    "gn:population":0,
    "gn:timezone":"America/Mexico_City",
    "iso:country":"MX",
    "name:spa_x_preferred":[
        "San Antonio Tulxc\u00e1m"
    ],
    "name:spa_x_variant":[
        "San Antonio Tuixc\u00fam"
    ],
    "wof:name":"San Antonio Tuixcum",
    "wof:placetype":"locality"
},
  "geometry": {"coordinates":[-92.23179,15.32223],"type":"Point"}
}