{
  "type": "Feature",
  "properties": {
    "gn:admin1_code":"30.0",
    "gn:admin2_code":"4.0",
    "gn:asciiname":"La Galera",
    "gn:country_code":"MX",
    "gn:dem":63,
    "gn:feature_class":"P",
    "gn:feature_code":"PPL",
    "gn:name":"La Galera",
    "gn:population":0,
    "gn:timezone":"America/Mexico_City",
    "iso:country":"MX",
    "name:spa_x_preferred":[
        "La Galera"
    ],
    "wof:name":"La Galera",
    "wof:placetype":"locality"
},
  "geometry": {"coordinates":[-96.45677000000001,19.49193],"type":"Point"}
}