{
  "type": "Feature",
  "properties": {
    "gn:admin1_code":"28.0",
    "gn:admin2_code":"8.0",
    "gn:asciiname":"Las Viboras",
    "gn:country_code":"MX",
    "gn:dem":178,
    "gn:feature_class":"P",
    "gn:feature_code":"PPL",
    "gn:name":"Las Viboras",
    "gn:population":0,
    "gn:timezone":"America/Monterrey",
    "iso:country":"MX",
    "name:spa_x_preferred":[
        "Las Viboras"
    ],
    "wof:name":"Las Viboras",
    "wof:placetype":"locality"
},
  "geometry": {"coordinates":[-98.83946,23.6408],"type":"Point"}
}