{
  "type": "Feature",
  "properties": {
    "gn:admin1_code":"25",
    "gn:admin2_code":"18.0",
    "gn:asciiname":"Otameto",
    "gn:cc2":"MX",
    "gn:country_code":"MX",
    "gn:dem":15,
    "gn:feature_class":"P",
    "gn:feature_code":"PPL",
    "gn:name":"Otameto",
    "gn:population":664,
    "gn:timezone":"America/Mazatlan",
    "iso:country":"MX",
    "name:und_x_variant":[
        "Otamento",
        "Otameto"
    ],
    "wof:name":"Otameto",
    "wof:placetype":"locality",
    "wof:population":664
},
  "geometry": {"coordinates":[-107.74028,24.72889],"type":"Point"}
}