{
  "type": "Feature",
  "properties": {
    "gn:admin1_code":"26",
    "gn:admin2_code":"26.0",
    "gn:asciiname":"Mayocahui",
    "gn:country_code":"MX",
    "gn:dem":36,
    "gn:feature_class":"P",
    "gn:feature_code":"PPL",
    "gn:name":"Mayocahui",
    "gn:population":0,
    "gn:timezone":"America/Hermosillo",
    "iso:country":"MX",
    "name:spa_x_preferred":[
        "Mayocahui"
    ],
    "wof:name":"Mayocahui",
    "wof:placetype":"locality"
},
  "geometry": {"coordinates":[-109.73625,27.04088],"type":"Point"}
}