{
  "type": "Feature",
  "properties": {
    "gn:admin1_code":"19.0",
    "gn:admin2_code":"50.0",
    "gn:asciiname":"La Graniza",
    "gn:country_code":"MX",
    "gn:dem":260,
    "gn:feature_class":"P",
    "gn:feature_code":"PPL",
    "gn:name":"La Graniza",
    "gn:population":0,
    "gn:timezone":"America/Monterrey",
    "iso:country":"MX",
    "name:spa_x_preferred":[
        "La Graniza"
    ],
    "wof:name":"La Graniza",
    "wof:placetype":"locality"
},
  "geometry": {"coordinates":[-100.03628,26.79658],"type":"Point"}
}