{
  "type": "Feature",
  "properties": {
    "gn:admin1_code":"5.0",
    "gn:asciiname":"Loma Bonita",
    "gn:country_code":"MX",
    "gn:dem":609,
    "gn:feature_class":"P",
    "gn:feature_code":"PPL",
    "gn:name":"Loma Bonita",
    "gn:population":0,
    "gn:timezone":"America/Mexico_City",
    "iso:country":"MX",
    "name:epo_x_preferred":[
        "Loma Bonita"
    ],
    "name:eus_x_preferred":[
        "Loma Bonita"
    ],
    "name:hun_x_preferred":[
        "Loma Bonita"
    ],
    "name:ita_x_preferred":[
        "Loma Bonita"
    ],
    "name:rus_x_preferred":[
        "\u041b\u043e\u043c\u0430-\u0411\u043e\u043d\u0438\u0442\u0430"
    ],
    "name:sco_x_preferred":[
        "Loma Bonita"
    ],
    "name:spa_x_preferred":[
        "Loma Bonita"
    ],
    "name:srp_x_preferred":[
        "\u041e\u043f\u0448\u0442\u0438\u043d\u0430 \u041b\u043e\u043c\u0430 \u0411\u043e\u043d\u0438\u0442\u0430"
    ],
    "name:vie_x_preferred":[
        "Loma Bonita"
    ],
    "wof:name":"Loma Bonita",
    "wof:placetype":"locality"
},
  "geometry": {"coordinates":[-92.87889,16.29023],"type":"Point"}
}