{
  "type": "Feature",
  "properties": {
    "gn:admin1_code":"10.0",
    "gn:admin2_code":"5.0",
    "gn:asciiname":"Dieciseis de Septiembre",
    "gn:country_code":"MX",
    "gn:dem":2262,
    "gn:feature_class":"P",
    "gn:feature_code":"PPL",
    "gn:name":"Diecis\u00e9is de Septiembre",
    "gn:population":0,
    "gn:timezone":"America/Monterrey",
    "iso:country":"MX",
    "name:und_x_variant":[
        "Cienguita de F"
    ],
    "wof:name":"Dieciseis de Septiembre",
    "wof:placetype":"locality"
},
  "geometry": {"coordinates":[-104.81153999999999,24.00813],"type":"Point"}
}