{
  "type": "Feature",
  "properties": {
    "gn:admin1_code":"5",
    "gn:admin2_code":"97.0",
    "gn:asciiname":"El Congreso",
    "gn:country_code":"MX",
    "gn:dem":22,
    "gn:feature_class":"P",
    "gn:feature_code":"PPL",
    "gn:name":"El Congreso",
    "gn:population":616,
    "gn:timezone":"America/Mexico_City",
    "iso:country":"MX",
    "wof:name":"El Congreso",
    "wof:placetype":"locality",
    "wof:population":616
},
  "geometry": {"coordinates":[-93.79000000000001,16.04972],"type":"Point"}
}