{
  "type": "Feature",
  "properties": {
    "gn:admin1_code":"11",
    "gn:admin2_code":"1.0",
    "gn:asciiname":"Las Masas (La Luz Masas)",
    "gn:country_code":"MX",
    "gn:dem":1699,
    "gn:feature_class":"P",
    "gn:feature_code":"PPL",
    "gn:name":"Las Masas (La Luz Masas)",
    "gn:population":1396,
    "gn:timezone":"America/Mexico_City",
    "iso:country":"MX",
    "wof:name":"Las Masas (La Luz Masas)",
    "wof:placetype":"locality",
    "wof:population":1396
},
  "geometry": {"coordinates":[-101.54277999999999,20.59917],"type":"Point"}
}