{
  "type": "Feature",
  "properties": {
    "gn:admin1_code":"14",
    "gn:admin2_code":"73.0",
    "gn:asciiname":"Paso de Trujillos",
    "gn:country_code":"MX",
    "gn:dem":1810,
    "gn:feature_class":"P",
    "gn:feature_code":"PPL",
    "gn:name":"Paso de Trujillos",
    "gn:population":183,
    "gn:timezone":"America/Mexico_City",
    "iso:country":"MX",
    "wof:name":"Paso de Trujillos",
    "wof:placetype":"locality",
    "wof:population":183
},
  "geometry": {"coordinates":[-102.28,21.32611],"type":"Point"}
}