{
  "type": "Feature",
  "properties": {
    "gn:admin1_code":"30.0",
    "gn:admin2_code":"205.0",
    "gn:asciiname":"Sante Ene",
    "gn:country_code":"MX",
    "gn:dem":56,
    "gn:feature_class":"P",
    "gn:feature_code":"PPL",
    "gn:name":"Sante Ene",
    "gn:population":0,
    "gn:timezone":"America/Mexico_City",
    "iso:country":"MX",
    "name:spa_x_preferred":[
        "Sante Ene"
    ],
    "wof:name":"Sante Ene",
    "wof:placetype":"locality"
},
  "geometry": {"coordinates":[-98.35767,21.69461],"type":"Point"}
}