{
  "type": "Feature",
  "properties": {
    "gn:admin1_code":"5.0",
    "gn:admin2_code":"69.0",
    "gn:asciiname":"Cochepelon",
    "gn:country_code":"MX",
    "gn:dem":23,
    "gn:feature_class":"P",
    "gn:feature_code":"PPL",
    "gn:name":"Cochepel\u00f3n",
    "gn:population":0,
    "gn:timezone":"America/Mexico_City",
    "iso:country":"MX",
    "name:spa_x_preferred":[
        "Cochepel\u00f3n"
    ],
    "wof:name":"Cochepelon",
    "wof:placetype":"locality"
},
  "geometry": {"coordinates":[-93.22331,15.65137],"type":"Point"}
}