{
  "type": "Feature",
  "properties": {
    "gn:admin1_code":"2",
    "gn:admin2_code":"2",
    "gn:asciiname":"Familia Barrera (Colonia Villarreal)",
    "gn:country_code":"MX",
    "gn:dem":21,
    "gn:feature_class":"P",
    "gn:feature_code":"PPL",
    "gn:name":"Familia Barrera (Colonia Villarreal)",
    "gn:population":26,
    "gn:timezone":"America/Tijuana",
    "iso:country":"MX",
    "wof:name":"Familia Barrera (Colonia Villarreal)",
    "wof:placetype":"locality",
    "wof:population":26
},
  "geometry": {"coordinates":[-115.01333,32.42944],"type":"Point"}
}