{
  "type": "Feature",
  "properties": {
    "gn:admin1_code":"12",
    "gn:admin2_code":"12.0",
    "gn:asciiname":"La Sidra",
    "gn:country_code":"MX",
    "gn:dem":483,
    "gn:feature_class":"P",
    "gn:feature_code":"PPL",
    "gn:name":"La Sidra",
    "gn:population":284,
    "gn:timezone":"America/Mexico_City",
    "iso:country":"MX",
    "name:ast_x_preferred":[
        "La Sidra"
    ],
    "name:glg_x_preferred":[
        "La Sidra"
    ],
    "wof:name":"La Sidra",
    "wof:placetype":"locality",
    "wof:population":284
},
  "geometry": {"coordinates":[-99.0475,16.995],"type":"Point"}
}