{
  "type": "Feature",
  "properties": {
    "gn:admin1_code":"5",
    "gn:admin2_code":"66",
    "gn:asciiname":"La Mesa Buenavista",
    "gn:country_code":"MX",
    "gn:dem":496,
    "gn:feature_class":"P",
    "gn:feature_code":"PPL",
    "gn:name":"La Mesa Buenavista",
    "gn:population":21,
    "gn:timezone":"America/Mexico_City",
    "iso:country":"MX",
    "wof:name":"La Mesa Buenavista",
    "wof:placetype":"locality",
    "wof:population":21
},
  "geometry": {"coordinates":[-92.46666999999999,17.05611],"type":"Point"}
}