{
  "type": "Feature",
  "properties": {
    "gn:admin1_code":"28.0",
    "gn:admin2_code":"41.0",
    "gn:asciiname":"Mancilla",
    "gn:country_code":"MX",
    "gn:dem":268,
    "gn:feature_class":"P",
    "gn:feature_code":"PPL",
    "gn:name":"Mancilla",
    "gn:population":0,
    "gn:timezone":"America/Monterrey",
    "iso:country":"MX",
    "name:spa_x_preferred":[
        "Mancilla"
    ],
    "wof:name":"Mancilla",
    "wof:placetype":"locality"
},
  "geometry": {"coordinates":[-99.23593,23.89956],"type":"Point"}
}