{
  "type": "Feature",
  "properties": {
    "gn:admin1_code":"13",
    "gn:admin2_code":"81.0",
    "gn:asciiname":"Fraccionamiento Cozapa",
    "gn:country_code":"MX",
    "gn:dem":1916,
    "gn:feature_class":"P",
    "gn:feature_code":"PPL",
    "gn:name":"Fraccionamiento Cozapa",
    "gn:population":215,
    "gn:timezone":"America/Mexico_City",
    "iso:country":"MX",
    "wof:name":"Fraccionamiento Cozapa",
    "wof:placetype":"locality",
    "wof:population":215
},
  "geometry": {"coordinates":[-98.64528,20.645],"type":"Point"}
}