{
  "type": "Feature",
  "properties": {
    "gn:admin1_code":"11",
    "gn:admin2_code":"23.0",
    "gn:asciiname":"El Nacimiento de Ortiz",
    "gn:country_code":"MX",
    "gn:dem":1706,
    "gn:feature_class":"P",
    "gn:feature_code":"PPL",
    "gn:name":"El Nacimiento de Ortiz",
    "gn:population":54,
    "gn:timezone":"America/Mexico_City",
    "iso:country":"MX",
    "wof:name":"El Nacimiento de Ortiz",
    "wof:placetype":"locality",
    "wof:population":54
},
  "geometry": {"coordinates":[-101.64667,20.4675],"type":"Point"}
}