{
  "type": "Feature",
  "properties": {
    "gn:admin1_code":"7.0",
    "gn:admin2_code":"38.0",
    "gn:asciiname":"Ojo las Animas",
    "gn:country_code":"MX",
    "gn:dem":379,
    "gn:feature_class":"P",
    "gn:feature_code":"PPL",
    "gn:name":"Ojo las \u00c1nimas",
    "gn:population":0,
    "gn:timezone":"America/Monterrey",
    "iso:country":"MX",
    "name:spa_x_preferred":[
        "Ojo las \u00c1nimas"
    ],
    "wof:name":"Ojo las Animas",
    "wof:placetype":"locality"
},
  "geometry": {"coordinates":[-100.98139,28.4568],"type":"Point"}
}