{
  "type": "Feature",
  "properties": {
    "gn:admin1_code":"26",
    "gn:admin2_code":"30.0",
    "gn:asciiname":"Las Animas",
    "gn:country_code":"MX",
    "gn:dem":265,
    "gn:feature_class":"P",
    "gn:feature_code":"PPL",
    "gn:name":"Las \u00c1nimas",
    "gn:population":0,
    "gn:timezone":"America/Hermosillo",
    "iso:country":"MX",
    "name:ceb_x_preferred":[
        "Las Animas"
    ],
    "name:deu_x_preferred":[
        "Las \u00c1nimas"
    ],
    "name:nld_x_preferred":[
        "Las Animas"
    ],
    "name:pol_x_preferred":[
        "Las Animas"
    ],
    "name:spa_x_preferred":[
        "Las \u00c1nimas"
    ],
    "name:srp_x_preferred":[
        "\u041b\u0430\u0441 \u0410\u043d\u0438\u043c\u0430\u0441"
    ],
    "name:swe_x_preferred":[
        "Las Animas"
    ],
    "wof:name":"Las Animas",
    "wof:placetype":"locality"
},
  "geometry": {"coordinates":[-110.75163999999999,29.19216],"type":"Point"}
}