{
  "type": "Feature",
  "properties": {
    "gn:admin1_code":"2",
    "gn:admin2_code":"1.0",
    "gn:asciiname":"Familia Rendon",
    "gn:country_code":"MX",
    "gn:dem":74,
    "gn:feature_class":"P",
    "gn:feature_code":"PPL",
    "gn:name":"Familia Rend\u00f3n",
    "gn:population":6,
    "gn:timezone":"America/Tijuana",
    "iso:country":"MX",
    "name:und_x_variant":[
        "Familia Rend\u00f3n"
    ],
    "wof:name":"Familia Rendon",
    "wof:placetype":"locality",
    "wof:population":6
},
  "geometry": {"coordinates":[-116.54528000000001,31.67556],"type":"Point"}
}