{
  "type": "Feature",
  "properties": {
    "gn:admin1_code":"28",
    "gn:admin2_code":"20",
    "gn:asciiname":"Las Anacuas",
    "gn:country_code":"MX",
    "gn:dem":456,
    "gn:feature_class":"P",
    "gn:feature_code":"PPL",
    "gn:name":"Las Anacuas",
    "gn:population":10,
    "gn:timezone":"America/Monterrey",
    "iso:country":"MX",
    "wof:name":"Las Anacuas",
    "wof:placetype":"locality",
    "wof:population":10
},
  "geometry": {"coordinates":[-99.58111,24.54528],"type":"Point"}
}