{
  "type": "Feature",
  "properties": {
    "gn:admin1_code":"24.0",
    "gn:admin2_code":"2.0",
    "gn:asciiname":"Reforma",
    "gn:country_code":"MX",
    "gn:dem":1398,
    "gn:feature_class":"P",
    "gn:feature_code":"PPL",
    "gn:name":"Reforma",
    "gn:population":0,
    "gn:timezone":"America/Mexico_City",
    "iso:country":"MX",
    "name:cat_x_preferred":[
        "Reforma"
    ],
    "name:eus_x_preferred":[
        "Diario Reforma"
    ],
    "name:nld_x_preferred":[
        "Reforma"
    ],
    "name:nor_x_preferred":[
        "Reforma"
    ],
    "name:que_x_preferred":[
        "Reforma"
    ],
    "name:spa_x_preferred":[
        "Reforma"
    ],
    "wof:name":"Reforma",
    "wof:placetype":"locality"
},
  "geometry": {"coordinates":[-99.51987,22.11244],"type":"Point"}
}