{
  "type": "Feature",
  "properties": {
    "gn:admin1_code":"32",
    "gn:admin2_code":"10.0",
    "gn:asciiname":"Los Alamitos",
    "gn:country_code":"MX",
    "gn:dem":2339,
    "gn:feature_class":"P",
    "gn:feature_code":"PPL",
    "gn:name":"Los Alamitos",
    "gn:population":0,
    "gn:timezone":"America/Mexico_City",
    "iso:country":"MX",
    "wof:name":"Los Alamitos",
    "wof:placetype":"locality"
},
  "geometry": {"coordinates":[-103.08333,23.03333],"type":"Point"}
}