{
  "type": "Feature",
  "properties": {
    "gn:admin1_code":"16",
    "gn:admin2_code":"14",
    "gn:asciiname":"El Zapotal",
    "gn:country_code":"MX",
    "gn:dem":16,
    "gn:feature_class":"P",
    "gn:feature_code":"PPL",
    "gn:name":"El Zapotal",
    "gn:population":19,
    "gn:timezone":"America/Mexico_City",
    "iso:country":"MX",
    "name:fra_x_preferred":[
        "El Zapotal"
    ],
    "name:spa_x_preferred":[
        "El Zapotal"
    ],
    "wof:name":"El Zapotal",
    "wof:placetype":"locality",
    "wof:population":19
},
  "geometry": {"coordinates":[-103.67195,18.66167],"type":"Point"}
}