{
  "type": "Feature",
  "properties": {
    "gn:admin1_code":"31",
    "gn:admin2_code":"22",
    "gn:asciiname":"Chan Santa Maria",
    "gn:country_code":"MX",
    "gn:dem":24,
    "gn:feature_class":"P",
    "gn:feature_code":"PPL",
    "gn:name":"Chan Santa Mar\u00eda",
    "gn:population":49,
    "gn:timezone":"America/Merida",
    "iso:country":"MX",
    "name:und_x_variant":[
        "Chan Santa Mar\u00eda"
    ],
    "wof:name":"Chan Santa Maria",
    "wof:placetype":"locality",
    "wof:population":49
},
  "geometry": {"coordinates":[-88.55778000000002,20.38194],"type":"Point"}
}