{
  "type": "Feature",
  "properties": {
    "gn:admin1_code":"26",
    "gn:admin2_code":"55.0",
    "gn:asciiname":"Ninguno [J. Dolores Monroy Patino]",
    "gn:country_code":"MX",
    "gn:dem":23,
    "gn:feature_class":"P",
    "gn:feature_code":"PPL",
    "gn:name":"Ninguno [J. Dolores Monroy Pati\u00f1o]",
    "gn:population":7,
    "gn:timezone":"America/Hermosillo",
    "iso:country":"MX",
    "name:und_x_variant":[
        "Ninguno [J. Dolores Monroy Pati\u00f1o]"
    ],
    "wof:name":"Ninguno [J. Dolores Monroy Patino]",
    "wof:placetype":"locality",
    "wof:population":7
},
  "geometry": {"coordinates":[-114.825,32.42667],"type":"Point"}
}