{
  "type": "Feature",
  "properties": {
    "gn:admin1_code":"20",
    "gn:admin2_code":"134.0",
    "gn:asciiname":"Agua de Olla",
    "gn:country_code":"MX",
    "gn:dem":127,
    "gn:feature_class":"P",
    "gn:feature_code":"PPL",
    "gn:name":"Agua de Olla",
    "gn:population":195,
    "gn:timezone":"America/Mexico_City",
    "iso:country":"MX",
    "wof:name":"Agua de Olla",
    "wof:placetype":"locality",
    "wof:population":195
},
  "geometry": {"coordinates":[-96.53610999999999,18.03889],"type":"Point"}
}