{
  "type": "Feature",
  "properties": {
    "gn:admin1_code":"30",
    "gn:admin2_code":"81.0",
    "gn:asciiname":"Union y Progreso",
    "gn:country_code":"MX",
    "gn:dem":1334,
    "gn:feature_class":"P",
    "gn:feature_code":"PPL",
    "gn:name":"Uni\u00f3n y Progreso",
    "gn:population":8181,
    "gn:timezone":"America/Mexico_City",
    "iso:country":"MX",
    "name:und_x_variant":[
        "Uni\u00f3n y Progreso"
    ],
    "wof:name":"Union y Progreso",
    "wof:placetype":"locality",
    "wof:population":8181
},
  "geometry": {"coordinates":[-97.11917,18.87278],"type":"Point"}
}