{
  "type": "Feature",
  "properties": {
    "gn:admin1_code":"3",
    "gn:admin2_code":"9.0",
    "gn:asciiname":"San Rafael",
    "gn:country_code":"MX",
    "gn:dem":555,
    "gn:feature_class":"P",
    "gn:feature_code":"PPL",
    "gn:name":"San Rafael",
    "gn:population":0,
    "gn:timezone":"America/Mazatlan",
    "iso:country":"MX",
    "name:bre_x_preferred":[
        "San Rafael"
    ],
    "name:ceb_x_preferred":[
        "San Rafael"
    ],
    "name:ces_x_preferred":[
        "San Rafael"
    ],
    "name:deu_x_preferred":[
        "San Rafael"
    ],
    "name:fas_x_preferred":[
        "\u0633\u0627\u0646 \u0631\u0627\u0641\u0627\u0626\u0644"
    ],
    "name:fin_x_preferred":[
        "San Rafael"
    ],
    "name:fra_x_preferred":[
        "San Rafael"
    ],
    "name:hun_x_preferred":[
        "San Rafael"
    ],
    "name:hye_x_preferred":[
        "\u054d\u0561\u0576 \u054c\u0561\u0586\u0561\u0575\u0565\u056c"
    ],
    "name:ilo_x_preferred":[
        "San Rafael"
    ],
    "name:ita_x_preferred":[
        "San Rafael"
    ],
    "name:jpn_x_preferred":[
        "\u30b5\u30f3\u30fb\u30e9\u30d5\u30a1\u30a8\u30eb"
    ],
    "name:kor_x_preferred":[
        "\uc0b0\ub77c\ud30c\uc5d8"
    ],
    "name:mlg_x_preferred":[
        "San Rafael"
    ],
    "name:nld_x_preferred":[
        "San Rafael"
    ],
    "name:pol_x_preferred":[
        "San Rafael"
    ],
    "name:por_x_preferred":[
        "San Rafael"
    ],
    "name:rus_x_preferred":[
        "\u0421\u0430\u043d-\u0420\u0430\u0444\u0430\u044d\u043b\u044c"
    ],
    "name:sco_x_preferred":[
        "San Rafael"
    ],
    "name:spa_x_preferred":[
        "San Rafael"
    ],
    "name:srp_x_preferred":[
        "\u0421\u0430\u043d \u0420\u0430\u0444\u0430\u0435\u043b"
    ],
    "name:swe_x_preferred":[
        "San Rafael"
    ],
    "name:vie_x_preferred":[
        "San Rafael"
    ],
    "name:war_x_preferred":[
        "San Rafael"
    ],
    "wof:name":"San Rafael",
    "wof:placetype":"locality"
},
  "geometry": {"coordinates":[-111.50321,25.85674],"type":"Point"}
}