{
  "type": "Feature",
  "properties": {
    "gn:admin1_code":"2.0",
    "gn:admin2_code":"2.0",
    "gn:asciiname":"Sonora Primera Seccion",
    "gn:country_code":"MX",
    "gn:dem":4,
    "gn:feature_class":"P",
    "gn:feature_code":"PPL",
    "gn:name":"Sonora Primera Secci\u00f3n",
    "gn:population":0,
    "gn:timezone":"America/Tijuana",
    "iso:country":"MX",
    "name:spa_x_preferred":[
        "Sonora Primera Secci\u00f3n"
    ],
    "wof:name":"Sonora Primera Seccion",
    "wof:placetype":"locality"
},
  "geometry": {"coordinates":[-115.62217,32.57995],"type":"Point"}
}