{
  "type": "Feature",
  "properties": {
    "gn:admin1_code":"5",
    "gn:admin2_code":"107.0",
    "gn:asciiname":"Los Carlos",
    "gn:country_code":"MX",
    "gn:dem":680,
    "gn:feature_class":"P",
    "gn:feature_code":"PPL",
    "gn:name":"Los Carlos",
    "gn:population":8,
    "gn:timezone":"America/Mexico_City",
    "iso:country":"MX",
    "wof:name":"Los Carlos",
    "wof:placetype":"locality",
    "wof:population":8
},
  "geometry": {"coordinates":[-93.21917000000001,16.04028],"type":"Point"}
}