{
  "type": "Feature",
  "properties": {
    "gn:admin1_code":"5",
    "gn:admin2_code":"4.0",
    "gn:asciiname":"Nueva Virginia",
    "gn:country_code":"MX",
    "gn:dem":1236,
    "gn:feature_class":"P",
    "gn:feature_code":"PPL",
    "gn:name":"Nueva Virginia",
    "gn:population":0,
    "gn:timezone":"America/Mexico_City",
    "iso:country":"MX",
    "name:spa_x_preferred":[
        "Nueva Virginia"
    ],
    "wof:name":"Nueva Virginia",
    "wof:placetype":"locality"
},
  "geometry": {"coordinates":[-91.71905,16.5487],"type":"Point"}
}