{
  "type": "Feature",
  "properties": {
    "gn:admin1_code":"12.0",
    "gn:asciiname":"Ometepec Chiquito",
    "gn:country_code":"MX",
    "gn:dem":2150,
    "gn:feature_class":"P",
    "gn:feature_code":"PPL",
    "gn:name":"Ometepec Chiquito",
    "gn:population":0,
    "gn:timezone":"America/Mexico_City",
    "iso:country":"MX",
    "name:spa_x_preferred":[
        "Ometepec Chiquito"
    ],
    "wof:name":"Ometepec Chiquito",
    "wof:placetype":"locality"
},
  "geometry": {"coordinates":[-98.47736999999999,17.2018],"type":"Point"}
}