{
  "type": "Feature",
  "properties": {
    "gn:admin1_code":"7.0",
    "gn:admin2_code":"34.0",
    "gn:asciiname":"La Parrena",
    "gn:country_code":"MX",
    "gn:dem":1382,
    "gn:feature_class":"P",
    "gn:feature_code":"PPL",
    "gn:name":"La Parre\u00f1a",
    "gn:population":0,
    "gn:timezone":"America/Monterrey",
    "iso:country":"MX",
    "name:spa_x_preferred":[
        "La Parre\u00f1a"
    ],
    "wof:name":"La Parrena",
    "wof:placetype":"locality"
},
  "geometry": {"coordinates":[-103.65403000000001,27.28522],"type":"Point"}
}