{
  "type": "Feature",
  "properties": {
    "gn:admin1_code":"24",
    "gn:admin2_code":"28.0",
    "gn:asciiname":"Terrero Norte",
    "gn:country_code":"MX",
    "gn:dem":1850,
    "gn:feature_class":"P",
    "gn:feature_code":"PPL",
    "gn:name":"Terrero Norte",
    "gn:population":64,
    "gn:timezone":"America/Mexico_City",
    "iso:country":"MX",
    "name:und_x_variant":[
        "Terrero",
        "Ternero"
    ],
    "wof:name":"Terrero Norte",
    "wof:placetype":"locality",
    "wof:population":64
},
  "geometry": {"coordinates":[-100.88711000000001,22.40026],"type":"Point"}
}