{
  "type": "Feature",
  "properties": {
    "gn:admin1_code":"6",
    "gn:admin2_code":"11.0",
    "gn:asciiname":"Corea",
    "gn:country_code":"MX",
    "gn:dem":1337,
    "gn:feature_class":"P",
    "gn:feature_code":"PPL",
    "gn:name":"Corea",
    "gn:population":6,
    "gn:timezone":"America/Chihuahua",
    "iso:country":"MX",
    "name:spa_x_preferred":[
        "Corea"
    ],
    "wof:name":"Corea",
    "wof:placetype":"locality",
    "wof:population":6
},
  "geometry": {"coordinates":[-105.15843,27.43649000000001],"type":"Point"}
}