{
  "type": "Feature",
  "properties": {
    "gn:admin1_code":"22.0",
    "gn:admin2_code":"8.0",
    "gn:asciiname":"El Salto",
    "gn:country_code":"MX",
    "gn:dem":2270,
    "gn:feature_class":"P",
    "gn:feature_code":"PPL",
    "gn:name":"El Salto",
    "gn:population":226,
    "gn:timezone":"America/Mexico_City",
    "iso:country":"MX",
    "wof:name":"El Salto",
    "wof:placetype":"locality",
    "wof:population":226
},
  "geometry": {"coordinates":[-100.28028,20.38778],"type":"Point"}
}