{
  "type": "Feature",
  "properties": {
    "gn:admin1_code":"25",
    "gn:admin2_code":"8.0",
    "gn:asciiname":"Corachis",
    "gn:country_code":"MX",
    "gn:dem":171,
    "gn:feature_class":"P",
    "gn:feature_code":"PPL",
    "gn:name":"Corachis",
    "gn:population":0,
    "gn:timezone":"America/Mazatlan",
    "iso:country":"MX",
    "name:spa_x_preferred":[
        "Corachis"
    ],
    "name:und_x_variant":[
        "Coroches"
    ],
    "wof:name":"Corachis",
    "wof:placetype":"locality"
},
  "geometry": {"coordinates":[-106.63245999999999,24.16309],"type":"Point"}
}