{
  "type": "Feature",
  "properties": {
    "gn:admin1_code":"6.0",
    "gn:admin2_code":"62.0",
    "gn:asciiname":"El Aturdido",
    "gn:cc2":"MX",
    "gn:country_code":"MX",
    "gn:dem":1178,
    "gn:feature_class":"P",
    "gn:feature_code":"PPL",
    "gn:name":"El Aturdido",
    "gn:population":0,
    "gn:timezone":"America/Chihuahua",
    "iso:country":"MX",
    "name:und_x_variant":[
        "Aturdido",
        "Rancho Aturdido",
        "El Aturdido"
    ],
    "wof:name":"El Aturdido",
    "wof:placetype":"locality"
},
  "geometry": {"coordinates":[-105.27463,28.03688],"type":"Point"}
}