{
  "type": "Feature",
  "properties": {
    "gn:admin1_code":"25",
    "gn:admin2_code":"13",
    "gn:asciiname":"Boca de Guamuchil",
    "gn:country_code":"MX",
    "gn:dem":421,
    "gn:feature_class":"P",
    "gn:feature_code":"PPL",
    "gn:name":"Boca de Guam\u00fachil",
    "gn:population":15,
    "gn:timezone":"America/Mazatlan",
    "iso:country":"MX",
    "name:und_x_variant":[
        "Boca de Guam\u00fachil"
    ],
    "wof:name":"Boca de Guamuchil",
    "wof:placetype":"locality",
    "wof:population":15
},
  "geometry": {"coordinates":[-107.72596,25.74559],"type":"Point"}
}