{
  "type": "Feature",
  "properties": {
    "gn:admin1_code":"19",
    "gn:admin2_code":"17.0",
    "gn:asciiname":"Las Pintas",
    "gn:country_code":"MX",
    "gn:dem":2481,
    "gn:feature_class":"P",
    "gn:feature_code":"PPL",
    "gn:name":"Las Pintas",
    "gn:population":0,
    "gn:timezone":"America/Monterrey",
    "iso:country":"MX",
    "name:spa_x_preferred":[
        "Las Pintas"
    ],
    "wof:name":"Las Pintas",
    "wof:placetype":"locality"
},
  "geometry": {"coordinates":[-100.31973000000001,25.15617],"type":"Point"}
}