{
  "type": "Feature",
  "properties": {
    "gn:admin1_code":"20",
    "gn:admin2_code":"270.0",
    "gn:asciiname":"Boqueron",
    "gn:country_code":"MX",
    "gn:dem":2049,
    "gn:feature_class":"P",
    "gn:feature_code":"PPL",
    "gn:name":"Boquer\u00f3n",
    "gn:population":54,
    "gn:timezone":"America/Mexico_City",
    "iso:country":"MX",
    "name:und_x_variant":[
        "Boquer\u00f3n"
    ],
    "wof:name":"Boqueron",
    "wof:placetype":"locality",
    "wof:population":54
},
  "geometry": {"coordinates":[-97.14583,17.72722000000001],"type":"Point"}
}