{
  "type": "Feature",
  "properties": {
    "gn:admin1_code":"23",
    "gn:admin2_code":"2.0",
    "gn:asciiname":"San Francisco Ake",
    "gn:country_code":"MX",
    "gn:dem":28,
    "gn:feature_class":"P",
    "gn:feature_code":"PPL",
    "gn:name":"San Francisco Ake",
    "gn:population":0,
    "gn:timezone":"America/Cancun",
    "iso:country":"MX",
    "name:spa_x_preferred":[
        "San Francisco Ake"
    ],
    "wof:name":"San Francisco Ake",
    "wof:placetype":"locality"
},
  "geometry": {"coordinates":[-88.34569,19.95611],"type":"Point"}
}