{
  "type": "Feature",
  "properties": {
    "gn:admin1_code":"30.0",
    "gn:admin2_code":"69.0",
    "gn:asciiname":"Paguas de Coronado",
    "gn:country_code":"MX",
    "gn:dem":38,
    "gn:feature_class":"P",
    "gn:feature_code":"PPL",
    "gn:name":"Paguas de Coronado",
    "gn:population":144,
    "gn:timezone":"America/Mexico_City",
    "iso:country":"MX",
    "name:spa_x_preferred":[
        "Paguas de Coronado"
    ],
    "wof:name":"Paguas de Coronado",
    "wof:placetype":"locality",
    "wof:population":144
},
  "geometry": {"coordinates":[-97.14556,20.38],"type":"Point"}
}