{
  "type": "Feature",
  "properties": {
    "gn:admin1_code":"5",
    "gn:admin2_code":"30.0",
    "gn:asciiname":"Navarra",
    "gn:country_code":"MX",
    "gn:dem":1293,
    "gn:feature_class":"P",
    "gn:feature_code":"PPL",
    "gn:name":"Navarra",
    "gn:population":0,
    "gn:timezone":"America/Mexico_City",
    "iso:country":"MX",
    "name:und_x_variant":[
        "Navarro",
        "Navarra"
    ],
    "wof:name":"Navarra",
    "wof:placetype":"locality"
},
  "geometry": {"coordinates":[-92.43411999999999,15.68079],"type":"Point"}
}