{
  "type": "Feature",
  "properties": {
    "gn:admin1_code":"6.0",
    "gn:admin2_code":"9.0",
    "gn:asciiname":"Sohibriachi",
    "gn:country_code":"MX",
    "gn:dem":2541,
    "gn:feature_class":"P",
    "gn:feature_code":"PPL",
    "gn:name":"Sohibriachi",
    "gn:population":0,
    "gn:timezone":"America/Chihuahua",
    "iso:country":"MX",
    "name:spa_x_preferred":[
        "Sohibriachi"
    ],
    "wof:name":"Sohibriachi",
    "wof:placetype":"locality"
},
  "geometry": {"coordinates":[-107.352,27.73495],"type":"Point"}
}