{
  "type": "Feature",
  "properties": {
    "gn:admin1_code":"31",
    "gn:admin2_code":"102",
    "gn:asciiname":"Yokdzonot",
    "gn:country_code":"MX",
    "gn:dem":25,
    "gn:feature_class":"P",
    "gn:feature_code":"PPL",
    "gn:name":"Yokdzonot",
    "gn:population":27,
    "gn:timezone":"America/Merida",
    "iso:country":"MX",
    "wof:name":"Yokdzonot",
    "wof:placetype":"locality",
    "wof:population":27
},
  "geometry": {"coordinates":[-88.02,20.65944],"type":"Point"}
}