{
  "type": "Feature",
  "properties": {
    "gn:admin1_code":"14.0",
    "gn:asciiname":"Mexiquito",
    "gn:country_code":"MX",
    "gn:dem":1120,
    "gn:feature_class":"P",
    "gn:feature_code":"PPL",
    "gn:name":"Mexiquito",
    "gn:population":0,
    "gn:timezone":"America/Mexico_City",
    "iso:country":"MX",
    "name:spa_x_preferred":[
        "Mexiquito"
    ],
    "name:spa_x_variant":[
        "Mexquitito"
    ],
    "wof:name":"Mexiquito",
    "wof:placetype":"locality"
},
  "geometry": {"coordinates":[-103.97893000000001,21.42733],"type":"Point"}
}