{
  "type": "Feature",
  "properties": {
    "gn:admin1_code":"31",
    "gn:admin2_code":"36.0",
    "gn:asciiname":"San Isidro Ochil",
    "gn:country_code":"MX",
    "gn:dem":17,
    "gn:feature_class":"P",
    "gn:feature_code":"PPL",
    "gn:name":"San Isidro Ochil",
    "gn:population":965,
    "gn:timezone":"America/Merida",
    "iso:country":"MX",
    "name:und_x_variant":[
        "Ochil"
    ],
    "wof:name":"San Isidro Ochil",
    "wof:placetype":"locality",
    "wof:population":965
},
  "geometry": {"coordinates":[-89.34222,20.63611],"type":"Point"}
}