{
  "type": "Feature",
  "properties": {
    "gn:admin1_code":"32.0",
    "gn:admin2_code":"26.0",
    "gn:asciiname":"Apizolaya",
    "gn:country_code":"MX",
    "gn:dem":1839,
    "gn:feature_class":"P",
    "gn:feature_code":"PPL",
    "gn:name":"Apizolaya",
    "gn:population":0,
    "gn:timezone":"America/Mexico_City",
    "iso:country":"MX",
    "name:spa_x_preferred":[
        "Apizolaya"
    ],
    "name:und_x_variant":[
        "Apisolaya"
    ],
    "wof:name":"Apizolaya",
    "wof:placetype":"locality"
},
  "geometry": {"coordinates":[-102.27688000000001,24.81443],"type":"Point"}
}