{
  "type": "Feature",
  "properties": {
    "gn:admin1_code":"14",
    "gn:admin2_code":"97",
    "gn:asciiname":"Lomas del Pedregal",
    "gn:country_code":"MX",
    "gn:dem":1584,
    "gn:feature_class":"P",
    "gn:feature_code":"PPL",
    "gn:name":"Lomas del Pedregal",
    "gn:population":45,
    "gn:timezone":"America/Mexico_City",
    "iso:country":"MX",
    "wof:name":"Lomas del Pedregal",
    "wof:placetype":"locality",
    "wof:population":45
},
  "geometry": {"coordinates":[-103.40861,20.47917],"type":"Point"}
}