{
  "type": "Feature",
  "properties": {
    "gn:admin1_code":"24",
    "gn:admin2_code":"28",
    "gn:asciiname":"El Minguinero",
    "gn:country_code":"MX",
    "gn:dem":1830,
    "gn:feature_class":"P",
    "gn:feature_code":"PPL",
    "gn:name":"El Minguinero",
    "gn:population":18,
    "gn:timezone":"America/Mexico_City",
    "iso:country":"MX",
    "wof:name":"El Minguinero",
    "wof:placetype":"locality",
    "wof:population":18
},
  "geometry": {"coordinates":[-100.93832999999999,22.31222],"type":"Point"}
}