{
  "type": "Feature",
  "properties": {
    "gn:admin1_code":"24",
    "gn:admin2_code":"32.0",
    "gn:asciiname":"Matanzas",
    "gn:cc2":"MX",
    "gn:country_code":"MX",
    "gn:dem":2162,
    "gn:feature_class":"P",
    "gn:feature_code":"PPL",
    "gn:name":"Matanzas",
    "gn:population":0,
    "gn:timezone":"America/Mexico_City",
    "iso:country":"MX",
    "name:und_x_variant":[
        "Matancillas",
        "Matanzas"
    ],
    "wof:name":"Matanzas",
    "wof:placetype":"locality"
},
  "geometry": {"coordinates":[-100.28333000000001,21.83333],"type":"Point"}
}