{
  "type": "Feature",
  "properties": {
    "gn:admin1_code":"30",
    "gn:admin2_code":"22.0",
    "gn:asciiname":"Matlalapa",
    "gn:country_code":"MX",
    "gn:dem":1336,
    "gn:feature_class":"P",
    "gn:feature_code":"PPL",
    "gn:name":"Matlalapa",
    "gn:population":477,
    "gn:timezone":"America/Mexico_City",
    "iso:country":"MX",
    "wof:name":"Matlalapa",
    "wof:placetype":"locality",
    "wof:population":477
},
  "geometry": {"coordinates":[-97.07389000000001,18.95222],"type":"Point"}
}