{
  "type": "Feature",
  "properties": {
    "gn:admin1_code":"30",
    "gn:admin2_code":"91.0",
    "gn:asciiname":"Rafael Juarez",
    "gn:country_code":"MX",
    "gn:dem":84,
    "gn:feature_class":"P",
    "gn:feature_code":"PPL",
    "gn:name":"Rafael Ju\u00e1rez",
    "gn:population":7,
    "gn:timezone":"America/Mexico_City",
    "iso:country":"MX",
    "name:und_x_variant":[
        "Rafael Ju\u00e1rez"
    ],
    "wof:name":"Rafael Juarez",
    "wof:placetype":"locality",
    "wof:population":7
},
  "geometry": {"coordinates":[-95.16056,17.50832999999999],"type":"Point"}
}