{
  "type": "Feature",
  "properties": {
    "gn:admin1_code":"20",
    "gn:admin2_code":"2.0",
    "gn:asciiname":"El Porvenir",
    "gn:country_code":"MX",
    "gn:dem":115,
    "gn:feature_class":"P",
    "gn:feature_code":"PPL",
    "gn:name":"El Porvenir",
    "gn:population":879,
    "gn:timezone":"America/Mexico_City",
    "iso:country":"MX",
    "wof:name":"El Porvenir",
    "wof:placetype":"locality",
    "wof:population":879
},
  "geometry": {"coordinates":[-96.47806,18.50778],"type":"Point"}
}