{
  "type": "Feature",
  "properties": {
    "gn:admin1_code":"20",
    "gn:admin2_code":"2.0",
    "gn:asciiname":"El Porvenir",
    "gn:country_code":"MX",
    "gn:dem":115,
    "gn:feature_class":"P",
    "gn:feature_code":"PPL",
    "gn:name":"El Porvenir",
    "gn:population":879,
    "gn:timezone":"America/Mexico_City",
    "iso:country":"MX",
    "name:ceb_x_preferred":[
        "El Porvenir"
    ],
    "name:deu_x_preferred":[
        "El Porvenir"
    ],
    "name:epo_x_preferred":[
        "El Porvenir"
    ],
    "name:fra_x_preferred":[
        "El Porvenir"
    ],
    "name:glg_x_preferred":[
        "El Porvenir"
    ],
    "name:ita_x_preferred":[
        "El Porvenir"
    ],
    "name:nld_x_preferred":[
        "El Porvenir"
    ],
    "name:pol_x_preferred":[
        "El Porvenir"
    ],
    "name:rus_x_preferred":[
        "\u042d\u043b\u044c-\u041f\u043e\u0440\u0432\u0435\u043d\u0438\u0440"
    ],
    "name:spa_x_preferred":[
        "El Porvenir"
    ],
    "name:srp_x_preferred":[
        "\u0415\u043b \u041f\u043e\u0440\u0432\u0435\u043d\u0438\u0440"
    ],
    "name:swe_x_preferred":[
        "El Porvenir"
    ],
    "wof:name":"El Porvenir",
    "wof:placetype":"locality",
    "wof:population":879
},
  "geometry": {"coordinates":[-96.47806,18.50778],"type":"Point"}
}