{
  "type": "Feature",
  "properties": {
    "gn:admin1_code":"10",
    "gn:admin2_code":"7.0",
    "gn:asciiname":"Noria de la Virginia",
    "gn:country_code":"MX",
    "gn:dem":1106,
    "gn:feature_class":"P",
    "gn:feature_code":"PPL",
    "gn:name":"Noria de la Virginia",
    "gn:population":6,
    "gn:timezone":"America/Monterrey",
    "iso:country":"MX",
    "wof:name":"Noria de la Virginia",
    "wof:placetype":"locality",
    "wof:population":6
},
  "geometry": {"coordinates":[-103.35285,25.82473],"type":"Point"}
}