{
  "type": "Feature",
  "properties": {
    "gn:admin1_code":"11",
    "gn:admin2_code":"1",
    "gn:asciiname":"Las Liebres",
    "gn:country_code":"MX",
    "gn:dem":1693,
    "gn:feature_class":"P",
    "gn:feature_code":"PPL",
    "gn:name":"Las Liebres",
    "gn:population":35,
    "gn:timezone":"America/Mexico_City",
    "iso:country":"MX",
    "wof:name":"Las Liebres",
    "wof:placetype":"locality",
    "wof:population":35
},
  "geometry": {"coordinates":[-101.60556,20.34528],"type":"Point"}
}