{
  "type": "Feature",
  "properties": {
    "gn:admin1_code":"1",
    "gn:admin2_code":"6",
    "gn:asciiname":"Los Ibarra",
    "gn:country_code":"MX",
    "gn:dem":1907,
    "gn:feature_class":"P",
    "gn:feature_code":"PPL",
    "gn:name":"Los Ibarra",
    "gn:population":23,
    "gn:timezone":"America/Mexico_City",
    "iso:country":"MX",
    "wof:name":"Los Ibarra",
    "wof:placetype":"locality",
    "wof:population":23
},
  "geometry": {"coordinates":[-102.31722000000001,22.12472],"type":"Point"}
}