{
  "type": "Feature",
  "properties": {
    "gn:admin1_code":"10",
    "gn:admin2_code":"26",
    "gn:asciiname":"Potreros de Bueyes",
    "gn:country_code":"MX",
    "gn:dem":2392,
    "gn:feature_class":"P",
    "gn:feature_code":"PPL",
    "gn:name":"Potreros de Bueyes",
    "gn:population":17,
    "gn:timezone":"America/Monterrey",
    "iso:country":"MX",
    "wof:name":"Potreros de Bueyes",
    "wof:placetype":"locality",
    "wof:population":17
},
  "geometry": {"coordinates":[-105.60921,24.515],"type":"Point"}
}