{
  "type": "Feature",
  "properties": {
    "gn:admin1_code":"24",
    "gn:admin2_code":"19.0",
    "gn:asciiname":"La Escondida de Puerto Hondo",
    "gn:country_code":"MX",
    "gn:dem":1112,
    "gn:feature_class":"P",
    "gn:feature_code":"PPL",
    "gn:name":"La Escondida de Puerto Hondo",
    "gn:population":17,
    "gn:timezone":"America/Mexico_City",
    "iso:country":"MX",
    "wof:name":"La Escondida de Puerto Hondo",
    "wof:placetype":"locality",
    "wof:population":17
},
  "geometry": {"coordinates":[-99.68889,21.62833],"type":"Point"}
}