{
  "type": "Feature",
  "properties": {
    "gn:admin1_code":"28",
    "gn:admin2_code":"33.0",
    "gn:asciiname":"Estacion Canales",
    "gn:country_code":"MX",
    "gn:dem":32,
    "gn:feature_class":"P",
    "gn:feature_code":"PPL",
    "gn:name":"Estaci\u00f3n Canales",
    "gn:population":112,
    "gn:timezone":"America/Monterrey",
    "iso:country":"MX",
    "name:und_x_variant":[
        "Estaci\u00f3n Canales"
    ],
    "wof:name":"Estacion Canales",
    "wof:placetype":"locality",
    "wof:population":112
},
  "geometry": {"coordinates":[-97.95444000000001,25.99139],"type":"Point"}
}