{
  "type": "Feature",
  "properties": {
    "gn:admin1_code":"15",
    "gn:admin2_code":"82",
    "gn:asciiname":"Paso de San Juan",
    "gn:country_code":"MX",
    "gn:dem":640,
    "gn:feature_class":"P",
    "gn:feature_code":"PPL",
    "gn:name":"Paso de San Juan",
    "gn:population":26,
    "gn:timezone":"America/Mexico_City",
    "iso:country":"MX",
    "wof:name":"Paso de San Juan",
    "wof:placetype":"locality",
    "wof:population":26
},
  "geometry": {"coordinates":[-100.33812,18.77229],"type":"Point"}
}