{
  "type": "Feature",
  "properties": {
    "gn:admin1_code":"14",
    "gn:admin2_code":"105.0",
    "gn:asciiname":"El Dique (San Jose de los Rios)",
    "gn:country_code":"MX",
    "gn:dem":1540,
    "gn:feature_class":"P",
    "gn:feature_code":"PPL",
    "gn:name":"El Dique (San Jos\u00e9 de los R\u00edos)",
    "gn:population":323,
    "gn:timezone":"America/Mexico_City",
    "iso:country":"MX",
    "name:und_x_variant":[
        "El Dique (San Jos\u00e9 de los R\u00edos)"
    ],
    "wof:name":"El Dique (San Jose de los Rios)",
    "wof:placetype":"locality",
    "wof:population":323
},
  "geometry": {"coordinates":[-102.73860999999999,20.45694],"type":"Point"}
}