{
  "type": "Feature",
  "properties": {
    "gn:admin1_code":"25.0",
    "gn:asciiname":"El Tocador",
    "gn:country_code":"MX",
    "gn:dem":856,
    "gn:feature_class":"P",
    "gn:feature_code":"PPL",
    "gn:name":"El Tocador",
    "gn:population":0,
    "gn:timezone":"America/Mazatlan",
    "iso:country":"MX",
    "name:spa_x_preferred":[
        "El Tocador"
    ],
    "wof:name":"El Tocador",
    "wof:placetype":"locality"
},
  "geometry": {"coordinates":[-106.34871,24.25174],"type":"Point"}
}