{
  "type": "Feature",
  "properties": {
    "gn:admin1_code":"6",
    "gn:admin2_code":"16.0",
    "gn:asciiname":"Morieleno",
    "gn:country_code":"MX",
    "gn:dem":1210,
    "gn:feature_class":"P",
    "gn:feature_code":"PPL",
    "gn:name":"Moriele\u00f1o",
    "gn:population":190,
    "gn:timezone":"America/Chihuahua",
    "iso:country":"MX",
    "name:spa_x_preferred":[
        "Moriele\u00f1o"
    ],
    "wof:name":"Morieleno",
    "wof:placetype":"locality",
    "wof:population":190
},
  "geometry": {"coordinates":[-105.16731,27.8331],"type":"Point"}
}