{
  "type": "Feature",
  "properties": {
    "gn:admin1_code":"13",
    "gn:admin2_code":"13.0",
    "gn:asciiname":"Praderas del Potrero",
    "gn:country_code":"MX",
    "gn:dem":2319,
    "gn:feature_class":"P",
    "gn:feature_code":"PPL",
    "gn:name":"Praderas del Potrero",
    "gn:population":1066,
    "gn:timezone":"America/Mexico_City",
    "iso:country":"MX",
    "wof:name":"Praderas del Potrero",
    "wof:placetype":"locality",
    "wof:population":1066
},
  "geometry": {"coordinates":[-99.23027999999999,19.88472],"type":"Point"}
}