{
  "type": "Feature",
  "properties": {
    "gn:admin1_code":"11",
    "gn:admin2_code":"8",
    "gn:asciiname":"Granja Porras",
    "gn:country_code":"MX",
    "gn:dem":1744,
    "gn:feature_class":"P",
    "gn:feature_code":"PPL",
    "gn:name":"Granja Porras",
    "gn:population":33,
    "gn:timezone":"America/Mexico_City",
    "iso:country":"MX",
    "wof:name":"Granja Porras",
    "wof:placetype":"locality",
    "wof:population":33
},
  "geometry": {"coordinates":[-101.95806,20.71472],"type":"Point"}
}