{
  "type": "Feature",
  "properties": {
    "gn:admin1_code":"19",
    "gn:admin2_code":"14",
    "gn:asciiname":"La Trinidad de Zuniga",
    "gn:country_code":"MX",
    "gn:dem":1784,
    "gn:feature_class":"P",
    "gn:feature_code":"PPL",
    "gn:name":"La Trinidad de Z\u00fa\u00f1iga",
    "gn:population":22,
    "gn:timezone":"America/Monterrey",
    "iso:country":"MX",
    "name:und_x_variant":[
        "La Trinidad de Z\u00fa\u00f1iga"
    ],
    "wof:name":"La Trinidad de Zuniga",
    "wof:placetype":"locality",
    "wof:population":22
},
  "geometry": {"coordinates":[-100.43217,23.78924],"type":"Point"}
}