{
  "type": "Feature",
  "properties": {
    "gn:admin1_code":"7.0",
    "gn:admin2_code":"31.0",
    "gn:asciiname":"Altavista",
    "gn:country_code":"MX",
    "gn:dem":1089,
    "gn:feature_class":"P",
    "gn:feature_code":"PPL",
    "gn:name":"Altavista",
    "gn:population":0,
    "gn:timezone":"America/Monterrey",
    "iso:country":"MX",
    "name:spa_x_preferred":[
        "Altavista"
    ],
    "wof:name":"Altavista",
    "wof:placetype":"locality"
},
  "geometry": {"coordinates":[-102.13102000000001,28.04817],"type":"Point"}
}