{
  "type": "Feature",
  "properties": {
    "gn:admin1_code":"16.0",
    "gn:admin2_code":"26.0",
    "gn:asciiname":"El Maicillo",
    "gn:country_code":"MX",
    "gn:dem":401,
    "gn:feature_class":"P",
    "gn:feature_code":"PPL",
    "gn:name":"El Maicillo",
    "gn:population":0,
    "gn:timezone":"America/Mexico_City",
    "iso:country":"MX",
    "name:spa_x_preferred":[
        "El Maicillo"
    ],
    "wof:name":"El Maicillo",
    "wof:placetype":"locality"
},
  "geometry": {"coordinates":[-103.34019000000001,18.88267],"type":"Point"}
}