{
  "type": "Feature",
  "properties": {
    "gn:admin1_code":"6",
    "gn:admin2_code":"67.0",
    "gn:asciiname":"Santa Lucrecia",
    "gn:country_code":"MX",
    "gn:dem":1377,
    "gn:feature_class":"P",
    "gn:feature_code":"PPL",
    "gn:name":"Santa Lucrecia",
    "gn:population":0,
    "gn:timezone":"America/Chihuahua",
    "iso:country":"MX",
    "name:und_x_variant":[
        "Lucrecia"
    ],
    "wof:name":"Santa Lucrecia",
    "wof:placetype":"locality"
},
  "geometry": {"coordinates":[-105.62108000000001,27.63985],"type":"Point"}
}