{
  "type": "Feature",
  "properties": {
    "gn:admin1_code":"20.0",
    "gn:admin2_code":"28.0",
    "gn:asciiname":"Xiguiche",
    "gn:country_code":"MX",
    "gn:dem":1580,
    "gn:feature_class":"P",
    "gn:feature_code":"PPL",
    "gn:name":"Xiguiche",
    "gn:population":0,
    "gn:timezone":"America/Mexico_City",
    "iso:country":"MX",
    "name:spa_x_preferred":[
        "Xiguiche"
    ],
    "wof:name":"Xiguiche",
    "wof:placetype":"locality"
},
  "geometry": {"coordinates":[-96.85039999999999,16.46722999999999],"type":"Point"}
}