{
  "type": "Feature",
  "properties": {
    "gn:admin1_code":"31",
    "gn:admin2_code":"41.0",
    "gn:asciiname":"San Pedro Nompat",
    "gn:country_code":"MX",
    "gn:dem":13,
    "gn:feature_class":"P",
    "gn:feature_code":"PPL",
    "gn:name":"San Pedro Nompat",
    "gn:population":0,
    "gn:timezone":"America/Merida",
    "iso:country":"MX",
    "name:spa_x_preferred":[
        "San Pedro Nompat"
    ],
    "name:und_x_variant":[
        "San Pedro"
    ],
    "wof:name":"San Pedro Nompat",
    "wof:placetype":"locality"
},
  "geometry": {"coordinates":[-89.55329,20.94984],"type":"Point"}
}