{
  "type": "Feature",
  "properties": {
    "gn:admin1_code":"6",
    "gn:admin2_code":"29.0",
    "gn:asciiname":"Recodo",
    "gn:country_code":"MX",
    "gn:dem":669,
    "gn:feature_class":"P",
    "gn:feature_code":"PPL",
    "gn:name":"Recodo",
    "gn:population":0,
    "gn:timezone":"America/Chihuahua",
    "iso:country":"MX",
    "wof:name":"Recodo",
    "wof:placetype":"locality"
},
  "geometry": {"coordinates":[-107.18333,25.91667],"type":"Point"}
}