{
  "type": "Feature",
  "properties": {
    "gn:admin1_code":"26",
    "gn:admin2_code":"30.0",
    "gn:asciiname":"San Cuilmas",
    "gn:country_code":"MX",
    "gn:dem":409,
    "gn:feature_class":"P",
    "gn:feature_code":"PPL",
    "gn:name":"San Cuilmas",
    "gn:population":0,
    "gn:timezone":"America/Hermosillo",
    "iso:country":"MX",
    "name:spa_x_preferred":[
        "San Cuilmas"
    ],
    "wof:name":"San Cuilmas",
    "wof:placetype":"locality"
},
  "geometry": {"coordinates":[-111.25388,29.41972],"type":"Point"}
}