{
  "type": "Feature",
  "properties": {
    "gn:admin1_code":"11",
    "gn:admin2_code":"20.0",
    "gn:asciiname":"Blas Vargas",
    "gn:country_code":"MX",
    "gn:dem":2156,
    "gn:feature_class":"P",
    "gn:feature_code":"PPL",
    "gn:name":"Blas Vargas",
    "gn:population":8,
    "gn:timezone":"America/Mexico_City",
    "iso:country":"MX",
    "wof:name":"Blas Vargas",
    "wof:placetype":"locality",
    "wof:population":8
},
  "geometry": {"coordinates":[-101.60527999999999,21.16917],"type":"Point"}
}