{
  "type": "Feature",
  "properties": {
    "gn:admin1_code":"5",
    "gn:admin2_code":"18",
    "gn:asciiname":"Pomarrosa",
    "gn:country_code":"MX",
    "gn:dem":1390,
    "gn:feature_class":"P",
    "gn:feature_code":"PPL",
    "gn:name":"Pomarrosa",
    "gn:population":22,
    "gn:timezone":"America/Mexico_City",
    "iso:country":"MX",
    "wof:name":"Pomarrosa",
    "wof:placetype":"locality",
    "wof:population":22
},
  "geometry": {"coordinates":[-93.06972,17.11583],"type":"Point"}
}