{
  "type": "Feature",
  "properties": {
    "gn:admin1_code":"16",
    "gn:admin2_code":"98.0",
    "gn:asciiname":"Colonia Puerto del Obispo",
    "gn:country_code":"MX",
    "gn:dem":1884,
    "gn:feature_class":"P",
    "gn:feature_code":"PPL",
    "gn:name":"Colonia Puerto del Obispo",
    "gn:population":681,
    "gn:timezone":"America/Mexico_City",
    "iso:country":"MX",
    "wof:name":"Colonia Puerto del Obispo",
    "wof:placetype":"locality",
    "wof:population":681
},
  "geometry": {"coordinates":[-100.46556,19.53556],"type":"Point"}
}