{
  "type": "Feature",
  "properties": {
    "gn:admin1_code":"21",
    "gn:admin2_code":"72.0",
    "gn:asciiname":"Putaxcat",
    "gn:country_code":"MX",
    "gn:dem":499,
    "gn:feature_class":"P",
    "gn:feature_code":"PPL",
    "gn:name":"Putaxcat",
    "gn:population":890,
    "gn:timezone":"America/Mexico_City",
    "iso:country":"MX",
    "wof:name":"Putaxcat",
    "wof:placetype":"locality",
    "wof:population":890
},
  "geometry": {"coordinates":[-97.62508,20.09348],"type":"Point"}
}