{
  "type": "Feature",
  "properties": {
    "gn:admin1_code":"5",
    "gn:admin2_code":"59.0",
    "gn:asciiname":"5 de Mayo",
    "gn:country_code":"MX",
    "gn:dem":1012,
    "gn:feature_class":"P",
    "gn:feature_code":"PPL",
    "gn:name":"5 de Mayo",
    "gn:population":57,
    "gn:timezone":"America/Mexico_City",
    "iso:country":"MX",
    "wof:name":"5 de Mayo",
    "wof:placetype":"locality",
    "wof:population":57
},
  "geometry": {"coordinates":[-91.92583,16.9125],"type":"Point"}
}