{
  "type": "Feature",
  "properties": {
    "gn:admin1_code":"28",
    "gn:admin2_code":"12.0",
    "gn:asciiname":"Promesa de Mexico",
    "gn:country_code":"MX",
    "gn:dem":42,
    "gn:feature_class":"P",
    "gn:feature_code":"PPL",
    "gn:name":"Promesa de M\u00e9xico",
    "gn:population":5,
    "gn:timezone":"America/Monterrey",
    "iso:country":"MX",
    "name:und_x_variant":[
        "Promesa de M\u00e9xico"
    ],
    "wof:name":"Promesa de Mexico",
    "wof:placetype":"locality",
    "wof:population":5
},
  "geometry": {"coordinates":[-98.70583000000001,22.79667],"type":"Point"}
}