{
  "type": "Feature",
  "properties": {
    "gn:admin1_code":"8.0",
    "gn:admin2_code":"9.0",
    "gn:asciiname":"El Dorado",
    "gn:country_code":"MX",
    "gn:dem":16,
    "gn:feature_class":"P",
    "gn:feature_code":"PPL",
    "gn:name":"El Dorado",
    "gn:population":0,
    "gn:timezone":"America/Mexico_City",
    "iso:country":"MX",
    "name:spa_x_preferred":[
        "El Dorado"
    ],
    "wof:name":"El Dorado",
    "wof:placetype":"locality"
},
  "geometry": {"coordinates":[-103.80547,18.81518],"type":"Point"}
}