{
  "type": "Feature",
  "properties": {
    "gn:admin1_code":"12",
    "gn:admin2_code":"23.0",
    "gn:asciiname":"Altos de Barana",
    "gn:country_code":"MX",
    "gn:dem":36,
    "gn:feature_class":"P",
    "gn:feature_code":"PPL",
    "gn:name":"Altos de Bara\u00f1a",
    "gn:population":62,
    "gn:timezone":"America/Mexico_City",
    "iso:country":"MX",
    "name:und_x_variant":[
        "Altos de Bara\u00f1a"
    ],
    "wof:name":"Altos de Barana",
    "wof:placetype":"locality",
    "wof:population":62
},
  "geometry": {"coordinates":[-98.59216000000001,16.48156],"type":"Point"}
}