{
  "type": "Feature",
  "properties": {
    "gn:admin1_code":"15",
    "gn:admin2_code":"79.0",
    "gn:asciiname":"Tercera Manzana de San Juan del Cuervo",
    "gn:country_code":"MX",
    "gn:dem":2333,
    "gn:feature_class":"P",
    "gn:feature_code":"PPL",
    "gn:name":"Tercera Manzana de San Juan del Cuervo",
    "gn:population":79,
    "gn:timezone":"America/Mexico_City",
    "iso:country":"MX",
    "wof:name":"Tercera Manzana de San Juan del Cuervo",
    "wof:placetype":"locality",
    "wof:population":79
},
  "geometry": {"coordinates":[-99.44166,20.00068],"type":"Point"}
}