{
  "type": "Feature",
  "properties": {
    "gn:admin1_code":"26.0",
    "gn:admin2_code":"20.0",
    "gn:asciiname":"Campo Chula Vista",
    "gn:country_code":"MX",
    "gn:dem":442,
    "gn:feature_class":"P",
    "gn:feature_code":"PPL",
    "gn:name":"Campo Chula Vista",
    "gn:population":0,
    "gn:timezone":"America/Hermosillo",
    "iso:country":"MX",
    "name:spa_x_preferred":[
        "Campo Chula Vista"
    ],
    "name:spa_x_variant":[
        "Chula Vista"
    ],
    "wof:name":"Campo Chula Vista",
    "wof:placetype":"locality"
},
  "geometry": {"coordinates":[-110.94193,29.62391],"type":"Point"}
}