{
  "type": "Feature",
  "properties": {
    "gn:admin1_code":"6.0",
    "gn:admin2_code":"66.0",
    "gn:asciiname":"Babarocos",
    "gn:country_code":"MX",
    "gn:dem":634,
    "gn:feature_class":"P",
    "gn:feature_code":"PPL",
    "gn:name":"Babarocos",
    "gn:population":1,
    "gn:timezone":"America/Chihuahua",
    "iso:country":"MX",
    "wof:name":"Babarocos",
    "wof:placetype":"locality",
    "wof:population":1
},
  "geometry": {"coordinates":[-108.88800999999999,27.9724],"type":"Point"}
}