{
  "type": "Feature",
  "properties": {
    "gn:admin1_code":"30",
    "gn:admin2_code":"49.0",
    "gn:asciiname":"Paso Acahual",
    "gn:country_code":"MX",
    "gn:dem":38,
    "gn:feature_class":"P",
    "gn:feature_code":"PPL",
    "gn:name":"Paso Acahual",
    "gn:population":71,
    "gn:timezone":"America/Mexico_City",
    "iso:country":"MX",
    "wof:name":"Paso Acahual",
    "wof:placetype":"locality",
    "wof:population":71
},
  "geometry": {"coordinates":[-96.31722000000001,18.96167],"type":"Point"}
}