{
  "type": "Feature",
  "properties": {
    "gn:admin1_code":"2",
    "gn:admin2_code":"2",
    "gn:asciiname":"San Jorge",
    "gn:country_code":"MX",
    "gn:dem":9,
    "gn:feature_class":"P",
    "gn:feature_code":"PPL",
    "gn:name":"San Jorge",
    "gn:population":13,
    "gn:timezone":"America/Tijuana",
    "iso:country":"MX",
    "wof:name":"San Jorge",
    "wof:placetype":"locality",
    "wof:population":13
},
  "geometry": {"coordinates":[-115.16667,32.21972],"type":"Point"}
}