{
  "type": "Feature",
  "properties": {
    "gn:admin1_code":"16",
    "gn:admin2_code":"38",
    "gn:asciiname":"Los Llanos",
    "gn:country_code":"MX",
    "gn:dem":357,
    "gn:feature_class":"P",
    "gn:feature_code":"PPL",
    "gn:name":"Los Llanos",
    "gn:population":30,
    "gn:timezone":"America/Mexico_City",
    "iso:country":"MX",
    "wof:name":"Los Llanos",
    "wof:placetype":"locality",
    "wof:population":30
},
  "geometry": {"coordinates":[-100.90667000000001,18.67444],"type":"Point"}
}