{
  "type": "Feature",
  "properties": {
    "gn:admin1_code":"6.0",
    "gn:admin2_code":"12.0",
    "gn:asciiname":"Gueerachic",
    "gn:country_code":"MX",
    "gn:dem":2255,
    "gn:feature_class":"P",
    "gn:feature_code":"PPL",
    "gn:name":"G\u00fcer\u00e1chic",
    "gn:population":0,
    "gn:timezone":"America/Chihuahua",
    "iso:country":"MX",
    "name:und_x_variant":[
        "Huerachic",
        "G\u00fcer\u00e1chic"
    ],
    "wof:name":"Gueerachic",
    "wof:placetype":"locality"
},
  "geometry": {"coordinates":[-106.95,27.68333],"type":"Point"}
}