{
  "type": "Feature",
  "properties": {
    "gn:admin1_code":"24.0",
    "gn:asciiname":"Los Banquitos",
    "gn:country_code":"MX",
    "gn:dem":1316,
    "gn:feature_class":"P",
    "gn:feature_code":"PPL",
    "gn:name":"Los Banquitos",
    "gn:population":0,
    "gn:timezone":"America/Mexico_City",
    "iso:country":"MX",
    "name:spa_x_preferred":[
        "Los Banquitos"
    ],
    "wof:name":"Los Banquitos",
    "wof:placetype":"locality"
},
  "geometry": {"coordinates":[-99.90488999999999,21.57493],"type":"Point"}
}