{
  "type": "Feature",
  "properties": {
    "gn:admin1_code":"19",
    "gn:admin2_code":"22.0",
    "gn:asciiname":"La Brancha",
    "gn:country_code":"MX",
    "gn:dem":287,
    "gn:feature_class":"P",
    "gn:feature_code":"PPL",
    "gn:name":"La Brancha",
    "gn:population":0,
    "gn:timezone":"America/Monterrey",
    "iso:country":"MX",
    "name:spa_x_preferred":[
        "La Brancha"
    ],
    "wof:name":"La Brancha",
    "wof:placetype":"locality"
},
  "geometry": {"coordinates":[-99.49836999999999,25.14506],"type":"Point"}
}