{
  "type": "Feature",
  "properties": {
    "gn:admin1_code":"11",
    "gn:admin2_code":"37.0",
    "gn:asciiname":"San Jose de Gracia",
    "gn:country_code":"MX",
    "gn:dem":1761,
    "gn:feature_class":"P",
    "gn:feature_code":"PPL",
    "gn:name":"San Jos\u00e9 de Gracia",
    "gn:population":981,
    "gn:timezone":"America/Mexico_City",
    "iso:country":"MX",
    "name:und_x_variant":[
        "San Jos\u00e9 de Gracia"
    ],
    "wof:name":"San Jose de Gracia",
    "wof:placetype":"locality",
    "wof:population":981
},
  "geometry": {"coordinates":[-101.44694,20.89833],"type":"Point"}
}