{
  "type": "Feature",
  "properties": {
    "gn:admin1_code":"23.0",
    "gn:admin2_code":"4.0",
    "gn:asciiname":"La Ceiba",
    "gn:country_code":"MX",
    "gn:dem":29,
    "gn:feature_class":"P",
    "gn:feature_code":"PPL",
    "gn:name":"La Ceiba",
    "gn:population":156,
    "gn:timezone":"America/Cancun",
    "iso:country":"MX",
    "name:spa_x_preferred":[
        "La Ceiba"
    ],
    "wof:name":"La Ceiba",
    "wof:placetype":"locality",
    "wof:population":156
},
  "geometry": {"coordinates":[-88.50139,18.79222],"type":"Point"}
}