{
  "type": "Feature",
  "properties": {
    "gn:admin1_code":"24",
    "gn:admin2_code":"31.0",
    "gn:asciiname":"Paso de Botello",
    "gn:country_code":"MX",
    "gn:dem":460,
    "gn:feature_class":"P",
    "gn:feature_code":"PPL",
    "gn:name":"Paso de Botello",
    "gn:population":199,
    "gn:timezone":"America/Mexico_City",
    "iso:country":"MX",
    "wof:name":"Paso de Botello",
    "wof:placetype":"locality",
    "wof:population":199
},
  "geometry": {"coordinates":[-99.48472,21.43778],"type":"Point"}
}