{
  "type": "Feature",
  "properties": {
    "gn:admin1_code":"26.0",
    "gn:admin2_code":"29.0",
    "gn:asciiname":"El Campamento",
    "gn:country_code":"MX",
    "gn:dem":230,
    "gn:feature_class":"P",
    "gn:feature_code":"PPL",
    "gn:name":"El Campamento",
    "gn:population":0,
    "gn:timezone":"America/Hermosillo",
    "iso:country":"MX",
    "name:spa_x_preferred":[
        "El Campamento"
    ],
    "wof:name":"El Campamento",
    "wof:placetype":"locality"
},
  "geometry": {"coordinates":[-110.39834,28.43023],"type":"Point"}
}