{
  "type": "Feature",
  "properties": {
    "gn:admin1_code":"7",
    "gn:admin2_code":"20.0",
    "gn:asciiname":"San Jose de La Palma",
    "gn:country_code":"MX",
    "gn:dem":643,
    "gn:feature_class":"P",
    "gn:feature_code":"PPL",
    "gn:name":"San Jos\u00e9 de La Palma",
    "gn:population":0,
    "gn:timezone":"America/Monterrey",
    "iso:country":"MX",
    "name:und_x_variant":[
        "Rancho San Jos\u00e9 de La Palma",
        "San Jos\u00e9 de La Palma"
    ],
    "wof:name":"San Jose de La Palma",
    "wof:placetype":"locality"
},
  "geometry": {"coordinates":[-101.78608,27.92207],"type":"Point"}
}