{
  "type": "Feature",
  "properties": {
    "gn:admin1_code":"10.0",
    "gn:admin2_code":"3.0",
    "gn:asciiname":"Las Planillas",
    "gn:country_code":"MX",
    "gn:dem":2235,
    "gn:feature_class":"P",
    "gn:feature_code":"PPL",
    "gn:name":"Las Planillas",
    "gn:population":0,
    "gn:timezone":"America/Monterrey",
    "iso:country":"MX",
    "name:spa_x_preferred":[
        "Las Planillas"
    ],
    "wof:name":"Las Planillas",
    "wof:placetype":"locality"
},
  "geometry": {"coordinates":[-104.87591,25.13383],"type":"Point"}
}