{
  "type": "Feature",
  "properties": {
    "gn:admin1_code":"26",
    "gn:admin2_code":"52.0",
    "gn:asciiname":"Santo Domingo",
    "gn:country_code":"MX",
    "gn:dem":395,
    "gn:feature_class":"P",
    "gn:feature_code":"PPL",
    "gn:name":"Santo Domingo",
    "gn:population":0,
    "gn:timezone":"America/Hermosillo",
    "iso:country":"MX",
    "name:spa_x_preferred":[
        "Santo Domingo"
    ],
    "wof:name":"Santo Domingo",
    "wof:placetype":"locality"
},
  "geometry": {"coordinates":[-109.2364,29.37491],"type":"Point"}
}