{
  "type": "Feature",
  "properties": {
    "gn:admin1_code":"12",
    "gn:admin2_code":"36.0",
    "gn:asciiname":"La Victoria",
    "gn:country_code":"MX",
    "gn:dem":404,
    "gn:feature_class":"P",
    "gn:feature_code":"PPL",
    "gn:name":"La Victoria",
    "gn:population":460,
    "gn:timezone":"America/Mexico_City",
    "iso:country":"MX",
    "wof:name":"La Victoria",
    "wof:placetype":"locality",
    "wof:population":460
},
  "geometry": {"coordinates":[-98.49694,16.76],"type":"Point"}
}