{
  "type": "Feature",
  "properties": {
    "gn:admin1_code":"14",
    "gn:admin2_code":"25.0",
    "gn:asciiname":"Rancho la Azucena",
    "gn:country_code":"MX",
    "gn:dem":1736,
    "gn:feature_class":"P",
    "gn:feature_code":"PPL",
    "gn:name":"Rancho la Azucena",
    "gn:population":0,
    "gn:timezone":"America/Mexico_City",
    "iso:country":"MX",
    "name:spa_x_preferred":[
        "Rancho la Azucena"
    ],
    "wof:name":"Rancho la Azucena",
    "wof:placetype":"locality"
},
  "geometry": {"coordinates":[-103.27469000000001,21.98964],"type":"Point"}
}