{
  "type": "Feature",
  "properties": {
    "gn:admin1_code":"5",
    "gn:admin2_code":"117",
    "gn:asciiname":"El Capricho",
    "gn:country_code":"MX",
    "gn:dem":955,
    "gn:feature_class":"P",
    "gn:feature_code":"PPL",
    "gn:name":"El Capricho",
    "gn:population":12,
    "gn:timezone":"America/Mexico_City",
    "iso:country":"MX",
    "wof:name":"El Capricho",
    "wof:placetype":"locality",
    "wof:population":12
},
  "geometry": {"coordinates":[-92.61528,15.65056],"type":"Point"}
}