{
  "type": "Feature",
  "properties": {
    "gn:admin1_code":"12",
    "gn:admin2_code":"27",
    "gn:asciiname":"El Veladero",
    "gn:country_code":"MX",
    "gn:dem":599,
    "gn:feature_class":"P",
    "gn:feature_code":"PPL",
    "gn:name":"El Veladero",
    "gn:population":9,
    "gn:timezone":"America/Mexico_City",
    "iso:country":"MX",
    "wof:name":"El Veladero",
    "wof:placetype":"locality",
    "wof:population":9
},
  "geometry": {"coordinates":[-100.58256,18.84813],"type":"Point"}
}