{
  "type": "Feature",
  "properties": {
    "gn:admin1_code":"28",
    "gn:admin2_code":"42.0",
    "gn:asciiname":"Santa Fe",
    "gn:country_code":"MX",
    "gn:dem":317,
    "gn:feature_class":"P",
    "gn:feature_code":"PPL",
    "gn:name":"Santa Fe",
    "gn:population":8,
    "gn:timezone":"America/Monterrey",
    "iso:country":"MX",
    "wof:name":"Santa Fe",
    "wof:placetype":"locality",
    "wof:population":8
},
  "geometry": {"coordinates":[-99.30194,24.64778],"type":"Point"}
}