{
  "type": "Feature",
  "properties": {
    "gn:admin1_code":"19",
    "gn:admin2_code":"17.0",
    "gn:asciiname":"Rancho Los Alamos",
    "gn:country_code":"MX",
    "gn:dem":1965,
    "gn:feature_class":"P",
    "gn:feature_code":"PPL",
    "gn:name":"Rancho Los Alamos",
    "gn:population":0,
    "gn:timezone":"America/Monterrey",
    "iso:country":"MX",
    "wof:name":"Rancho Los Alamos",
    "wof:placetype":"locality"
},
  "geometry": {"coordinates":[-100.16667,24.93333],"type":"Point"}
}