{
  "type": "Feature",
  "properties": {
    "gn:admin1_code":"21",
    "gn:admin2_code":"197",
    "gn:asciiname":"Chicopanal",
    "gn:country_code":"MX",
    "gn:dem":984,
    "gn:feature_class":"P",
    "gn:feature_code":"PPL",
    "gn:name":"Chicopanal",
    "gn:population":10,
    "gn:timezone":"America/Mexico_City",
    "iso:country":"MX",
    "wof:name":"Chicopanal",
    "wof:placetype":"locality",
    "wof:population":10
},
  "geometry": {"coordinates":[-97.92389,20.29444],"type":"Point"}
}