{
  "type": "Feature",
  "properties": {
    "gn:admin1_code":"32.0",
    "gn:asciiname":"La Chamela",
    "gn:country_code":"MX",
    "gn:dem":2033,
    "gn:feature_class":"P",
    "gn:feature_code":"PPL",
    "gn:name":"La Chamela",
    "gn:population":0,
    "gn:timezone":"America/Mexico_City",
    "iso:country":"MX",
    "name:spa_x_preferred":[
        "La Chamela"
    ],
    "wof:name":"La Chamela",
    "wof:placetype":"locality"
},
  "geometry": {"coordinates":[-102.81288000000001,21.50226],"type":"Point"}
}