{
  "type": "Feature",
  "properties": {
    "gn:admin1_code":"27",
    "gn:admin2_code":"11.0",
    "gn:asciiname":"Zapotal 2da. Seccion",
    "gn:country_code":"MX",
    "gn:dem":9,
    "gn:feature_class":"P",
    "gn:feature_code":"PPL",
    "gn:name":"Zapotal 2da. Secci\u00f3n",
    "gn:population":349,
    "gn:timezone":"America/Mexico_City",
    "iso:country":"MX",
    "name:und_x_variant":[
        "Zapotal 2da. Secci\u00f3n"
    ],
    "wof:name":"Zapotal 2da. Seccion",
    "wof:placetype":"locality",
    "wof:population":349
},
  "geometry": {"coordinates":[-92.14556,17.98056],"type":"Point"}
}