{
  "type": "Feature",
  "properties": {
    "gn:admin1_code":"23",
    "gn:admin2_code":"2.0",
    "gn:asciiname":"Hazil",
    "gn:country_code":"MX",
    "gn:dem":30,
    "gn:feature_class":"P",
    "gn:feature_code":"PPL",
    "gn:name":"Hazil",
    "gn:population":0,
    "gn:timezone":"America/Cancun",
    "iso:country":"MX",
    "name:spa_x_preferred":[
        "Hazil"
    ],
    "wof:name":"Hazil",
    "wof:placetype":"locality"
},
  "geometry": {"coordinates":[-88.33498,19.63376],"type":"Point"}
}