{
  "type": "Feature",
  "properties": {
    "gn:admin1_code":"20",
    "gn:admin2_code":"137",
    "gn:asciiname":"Rio Ocote",
    "gn:country_code":"MX",
    "gn:dem":1153,
    "gn:feature_class":"P",
    "gn:feature_code":"PPL",
    "gn:name":"R\u00edo Ocote",
    "gn:population":49,
    "gn:timezone":"America/Mexico_City",
    "iso:country":"MX",
    "name:und_x_variant":[
        "R\u00edo Ocote"
    ],
    "wof:name":"Rio Ocote",
    "wof:placetype":"locality",
    "wof:population":49
},
  "geometry": {"coordinates":[-97.37582999999999,16.90722],"type":"Point"}
}