{
  "type": "Feature",
  "properties": {
    "gn:admin1_code":"30",
    "gn:admin2_code":"126.0",
    "gn:asciiname":"Puente Jula",
    "gn:country_code":"MX",
    "gn:dem":22,
    "gn:feature_class":"P",
    "gn:feature_code":"PPL",
    "gn:name":"Puente Jula",
    "gn:population":0,
    "gn:timezone":"America/Mexico_City",
    "iso:country":"MX",
    "name:spa_x_preferred":[
        "Puente Jula"
    ],
    "name:und_x_variant":[
        "Puente Tula"
    ],
    "wof:name":"Puente Jula",
    "wof:placetype":"locality"
},
  "geometry": {"coordinates":[-96.34828,19.20018],"type":"Point"}
}