{
  "type": "Feature",
  "properties": {
    "gn:admin1_code":"32",
    "gn:admin2_code":"36",
    "gn:asciiname":"Villa Sacramento",
    "gn:country_code":"MX",
    "gn:dem":2095,
    "gn:feature_class":"P",
    "gn:feature_code":"PPL",
    "gn:name":"Villa Sacramento",
    "gn:population":10,
    "gn:timezone":"America/Mexico_City",
    "iso:country":"MX",
    "wof:name":"Villa Sacramento",
    "wof:placetype":"locality",
    "wof:population":10
},
  "geometry": {"coordinates":[-102.22611000000001,22.60861],"type":"Point"}
}