{
  "type": "Feature",
  "properties": {
    "gn:admin1_code":"20",
    "gn:admin2_code":"141.0",
    "gn:asciiname":"San Francisco del Mar",
    "gn:country_code":"MX",
    "gn:dem":13,
    "gn:feature_class":"P",
    "gn:feature_code":"PPL",
    "gn:name":"San Francisco del Mar",
    "gn:population":0,
    "gn:timezone":"America/Mexico_City",
    "iso:country":"MX",
    "name:spa_x_preferred":[
        "San Francisco del Mar"
    ],
    "wof:name":"San Francisco del Mar",
    "wof:placetype":"locality"
},
  "geometry": {"coordinates":[-94.51528999999999,16.33987],"type":"Point"}
}