{
  "type": "Feature",
  "properties": {
    "gn:admin1_code":"14",
    "gn:admin2_code":"71",
    "gn:asciiname":"Los Mezquites",
    "gn:country_code":"MX",
    "gn:dem":904,
    "gn:feature_class":"P",
    "gn:feature_code":"PPL",
    "gn:name":"Los Mezquites",
    "gn:population":21,
    "gn:timezone":"America/Mexico_City",
    "iso:country":"MX",
    "wof:name":"Los Mezquites",
    "wof:placetype":"locality",
    "wof:population":21
},
  "geometry": {"coordinates":[-103.43722,21.10278],"type":"Point"}
}