{
  "type": "Feature",
  "properties": {
    "gn:admin1_code":"5",
    "gn:admin2_code":"34.0",
    "gn:asciiname":"Villa de Guadalupe",
    "gn:country_code":"MX",
    "gn:dem":713,
    "gn:feature_class":"P",
    "gn:feature_code":"PPL",
    "gn:name":"Villa de Guadalupe",
    "gn:population":163,
    "gn:timezone":"America/Mexico_City",
    "iso:country":"MX",
    "wof:name":"Villa de Guadalupe",
    "wof:placetype":"locality",
    "wof:population":163
},
  "geometry": {"coordinates":[-92.17444,15.87278],"type":"Point"}
}