{
  "type": "Feature",
  "properties": {
    "gn:admin1_code":"4",
    "gn:admin2_code":"3.0",
    "gn:asciiname":"La Carmita (La Texana)",
    "gn:country_code":"MX",
    "gn:dem":3,
    "gn:feature_class":"P",
    "gn:feature_code":"PPL",
    "gn:name":"La Carmita (La Texana)",
    "gn:population":5,
    "gn:timezone":"America/Merida",
    "iso:country":"MX",
    "wof:name":"La Carmita (La Texana)",
    "wof:placetype":"locality",
    "wof:population":5
},
  "geometry": {"coordinates":[-92.34556000000001,18.63],"type":"Point"}
}