{
  "type": "Feature",
  "properties": {
    "gn:admin1_code":"7.0",
    "gn:admin2_code":"30.0",
    "gn:asciiname":"La Hedionda Chica",
    "gn:cc2":"MX",
    "gn:country_code":"MX",
    "gn:dem":1613,
    "gn:feature_class":"P",
    "gn:feature_code":"PPL",
    "gn:name":"La Hedionda Chica",
    "gn:population":0,
    "gn:timezone":"America/Monterrey",
    "iso:country":"MX",
    "name:und_x_variant":[
        "Hedionda",
        "La Hedionda Chica"
    ],
    "wof:name":"La Hedionda Chica",
    "wof:placetype":"locality"
},
  "geometry": {"coordinates":[-101.23333,25.45],"type":"Point"}
}