{
  "type": "Feature",
  "properties": {
    "gn:admin1_code":"20",
    "gn:admin2_code":"94.0",
    "gn:asciiname":"La Joya",
    "gn:country_code":"MX",
    "gn:dem":2232,
    "gn:feature_class":"P",
    "gn:feature_code":"PPL",
    "gn:name":"La Joya",
    "gn:population":121,
    "gn:timezone":"America/Mexico_City",
    "iso:country":"MX",
    "wof:name":"La Joya",
    "wof:placetype":"locality",
    "wof:population":121
},
  "geometry": {"coordinates":[-97.06694,17.26611],"type":"Point"}
}