{
  "type": "Feature",
  "properties": {
    "gn:admin1_code":"30",
    "gn:admin2_code":"61.0",
    "gn:asciiname":"Los Constituyentes II",
    "gn:country_code":"MX",
    "gn:dem":138,
    "gn:feature_class":"P",
    "gn:feature_code":"PPL",
    "gn:name":"Los Constituyentes II",
    "gn:population":381,
    "gn:timezone":"America/Mexico_City",
    "iso:country":"MX",
    "wof:name":"Los Constituyentes II",
    "wof:placetype":"locality",
    "wof:population":381
},
  "geometry": {"coordinates":[-93.7775,17.30722],"type":"Point"}
}