{
  "type": "Feature",
  "properties": {
    "gn:admin1_code":"2.0",
    "gn:admin2_code":"3.0",
    "gn:asciiname":"La Paloma",
    "gn:country_code":"MX",
    "gn:dem":533,
    "gn:feature_class":"P",
    "gn:feature_code":"PPL",
    "gn:name":"La Paloma",
    "gn:population":9,
    "gn:timezone":"America/Tijuana",
    "iso:country":"MX",
    "name:spa_x_preferred":[
        "La Paloma"
    ],
    "name:und_x_variant":[
        "Las Palomas"
    ],
    "wof:name":"La Paloma",
    "wof:placetype":"locality",
    "wof:population":9
},
  "geometry": {"coordinates":[-116.66916999999999,32.56333],"type":"Point"}
}