{
  "type": "Feature",
  "properties": {
    "gn:admin1_code":"7",
    "gn:admin2_code":"4.0",
    "gn:asciiname":"Los Magueyes",
    "gn:country_code":"MX",
    "gn:dem":1762,
    "gn:feature_class":"P",
    "gn:feature_code":"PPL",
    "gn:name":"Los Magueyes",
    "gn:population":0,
    "gn:timezone":"America/Monterrey",
    "iso:country":"MX",
    "name:spa_x_preferred":[
        "Los Magueyes"
    ],
    "wof:name":"Los Magueyes",
    "wof:placetype":"locality"
},
  "geometry": {"coordinates":[-100.2753,25.28977],"type":"Point"}
}