{
  "type": "Feature",
  "properties": {
    "gn:admin1_code":"16.0",
    "gn:admin2_code":"92.0",
    "gn:asciiname":"El Rincon de Chapin",
    "gn:country_code":"MX",
    "gn:dem":553,
    "gn:feature_class":"P",
    "gn:feature_code":"PPL",
    "gn:name":"El Rinc\u00f3n de Chap\u00edn",
    "gn:population":0,
    "gn:timezone":"America/Mexico_City",
    "iso:country":"MX",
    "name:spa_x_preferred":[
        "El Rinc\u00f3n de Chap\u00edn"
    ],
    "wof:name":"El Rincon de Chapin",
    "wof:placetype":"locality"
},
  "geometry": {"coordinates":[-100.6079,19.04535],"type":"Point"}
}