{
  "type": "Feature",
  "properties": {
    "gn:admin1_code":"28",
    "gn:admin2_code":"16.0",
    "gn:asciiname":"Galindo",
    "gn:country_code":"MX",
    "gn:dem":1503,
    "gn:feature_class":"P",
    "gn:feature_code":"PPL",
    "gn:name":"Galindo",
    "gn:population":0,
    "gn:timezone":"America/Monterrey",
    "iso:country":"MX",
    "name:spa_x_preferred":[
        "Galindo"
    ],
    "wof:name":"Galindo",
    "wof:placetype":"locality"
},
  "geometry": {"coordinates":[-99.4572,23.97361],"type":"Point"}
}