{
  "type": "Feature",
  "properties": {
    "gn:admin1_code":"28",
    "gn:admin2_code":"16.0",
    "gn:asciiname":"Galindo",
    "gn:country_code":"MX",
    "gn:dem":1503,
    "gn:feature_class":"P",
    "gn:feature_code":"PPL",
    "gn:name":"Galindo",
    "gn:population":0,
    "gn:timezone":"America/Monterrey",
    "iso:country":"MX",
    "name:ceb_x_preferred":[
        "Galindo"
    ],
    "name:deu_x_preferred":[
        "Galindo"
    ],
    "name:ita_x_preferred":[
        "Galindo"
    ],
    "name:jpn_x_preferred":[
        "\u30ac\u30ea\u30f3\u30c9"
    ],
    "name:spa_x_preferred":[
        "Galindo"
    ],
    "name:srp_x_preferred":[
        "\u0413\u0430\u043b\u0438\u043d\u0434\u043e"
    ],
    "name:swe_x_preferred":[
        "Galindo"
    ],
    "wof:name":"Galindo",
    "wof:placetype":"locality"
},
  "geometry": {"coordinates":[-99.4572,23.97361],"type":"Point"}
}