{
  "type": "Feature",
  "properties": {
    "gn:admin1_code":"6",
    "gn:admin2_code":"29",
    "gn:asciiname":"Mesa del Barro (Barrio Viejo de Abajo)",
    "gn:country_code":"MX",
    "gn:dem":2625,
    "gn:feature_class":"P",
    "gn:feature_code":"PPL",
    "gn:name":"Mesa del Barro (Barrio Viejo de Abajo)",
    "gn:population":24,
    "gn:timezone":"America/Chihuahua",
    "iso:country":"MX",
    "wof:name":"Mesa del Barro (Barrio Viejo de Abajo)",
    "wof:placetype":"locality",
    "wof:population":24
},
  "geometry": {"coordinates":[-106.66513,26.2694],"type":"Point"}
}