{
  "type": "Feature",
  "properties": {
    "gn:admin1_code":"7",
    "gn:admin2_code":"7.0",
    "gn:asciiname":"Rancho San Vicente",
    "gn:country_code":"MX",
    "gn:dem":713,
    "gn:feature_class":"P",
    "gn:feature_code":"PPL",
    "gn:name":"Rancho San Vicente",
    "gn:population":0,
    "gn:timezone":"America/Monterrey",
    "iso:country":"MX",
    "wof:name":"Rancho San Vicente",
    "wof:placetype":"locality"
},
  "geometry": {"coordinates":[-101.86667,26.95],"type":"Point"}
}