{
  "type": "Feature",
  "properties": {
    "gn:admin1_code":"18",
    "gn:admin2_code":"5.0",
    "gn:asciiname":"El Ciruelo",
    "gn:country_code":"MX",
    "gn:dem":625,
    "gn:feature_class":"P",
    "gn:feature_code":"PPL",
    "gn:name":"El Ciruelo",
    "gn:population":5,
    "gn:timezone":"America/Mazatlan",
    "iso:country":"MX",
    "name:ita_x_preferred":[
        "El Ciruelo"
    ],
    "name:spa_x_preferred":[
        "El Ciruelo"
    ],
    "name:zho_x_preferred":[
        "\u57c3\u723e\u897f\u9b6f\u57c3\u6d1b"
    ],
    "wof:name":"El Ciruelo",
    "wof:placetype":"locality",
    "wof:population":5
},
  "geometry": {"coordinates":[-105.22083000000001,22.74667],"type":"Point"}
}