{
  "type": "Feature",
  "properties": {
    "gn:admin1_code":"7.0",
    "gn:admin2_code":"23.0",
    "gn:asciiname":"La Encantada",
    "gn:country_code":"MX",
    "gn:dem":1267,
    "gn:feature_class":"P",
    "gn:feature_code":"PPL",
    "gn:name":"La Encantada",
    "gn:population":0,
    "gn:timezone":"America/Monterrey",
    "iso:country":"MX",
    "name:spa_x_preferred":[
        "La Encantada"
    ],
    "wof:name":"La Encantada",
    "wof:placetype":"locality"
},
  "geometry": {"coordinates":[-102.68356,28.14008],"type":"Point"}
}