{
  "type": "Feature",
  "properties": {
    "gn:admin1_code":"10",
    "gn:admin2_code":"26.0",
    "gn:asciiname":"Union Modelo",
    "gn:country_code":"MX",
    "gn:dem":2327,
    "gn:feature_class":"P",
    "gn:feature_code":"PPL",
    "gn:name":"Uni\u00f3n Modelo",
    "gn:population":0,
    "gn:timezone":"America/Monterrey",
    "iso:country":"MX",
    "name:spa_x_preferred":[
        "Uni\u00f3n Modelo"
    ],
    "wof:name":"Union Modelo",
    "wof:placetype":"locality"
},
  "geometry": {"coordinates":[-105.53943,24.54753],"type":"Point"}
}