{
  "type": "Feature",
  "properties": {
    "gn:admin1_code":"7",
    "gn:admin2_code":"36.0",
    "gn:asciiname":"Juan Antonio del Sur (Sector Gilita Ocho)",
    "gn:country_code":"MX",
    "gn:dem":1160,
    "gn:feature_class":"P",
    "gn:feature_code":"PPL",
    "gn:name":"Juan Antonio del Sur (Sector Gilita Ocho)",
    "gn:population":56,
    "gn:timezone":"America/Monterrey",
    "iso:country":"MX",
    "wof:name":"Juan Antonio del Sur (Sector Gilita Ocho)",
    "wof:placetype":"locality",
    "wof:population":56
},
  "geometry": {"coordinates":[-103.18172,25.28222],"type":"Point"}
}