{
  "type": "Feature",
  "properties": {
    "gn:admin1_code":"5",
    "gn:admin2_code":"107.0",
    "gn:asciiname":"La Puerta",
    "gn:country_code":"MX",
    "gn:dem":634,
    "gn:feature_class":"P",
    "gn:feature_code":"PPL",
    "gn:name":"La Puerta",
    "gn:population":0,
    "gn:timezone":"America/Mexico_City",
    "iso:country":"MX",
    "name:ceb_x_preferred":[
        "La Puerta"
    ],
    "name:deu_x_preferred":[
        "La Puerta"
    ],
    "name:fra_x_preferred":[
        "La Puerta"
    ],
    "name:ita_x_preferred":[
        "La Puerta"
    ],
    "name:por_x_preferred":[
        "La Puerta"
    ],
    "name:spa_x_preferred":[
        "La Puerta"
    ],
    "name:swe_x_preferred":[
        "La Puerta"
    ],
    "name:zho_x_preferred":[
        "\u62c9\u666e\u57c3\u723e\u5854"
    ],
    "wof:name":"La Puerta",
    "wof:placetype":"locality"
},
  "geometry": {"coordinates":[-93.20761,16.0643],"type":"Point"}
}