{
  "type": "Feature",
  "properties": {
    "gn:admin1_code":"5.0",
    "gn:asciiname":"San Jose Guadalupe",
    "gn:country_code":"MX",
    "gn:dem":968,
    "gn:feature_class":"P",
    "gn:feature_code":"PPL",
    "gn:name":"San Jos\u00e9 Guadalupe",
    "gn:population":0,
    "gn:timezone":"America/Mexico_City",
    "iso:country":"MX",
    "name:spa_x_preferred":[
        "San Jos\u00e9 Guadalupe"
    ],
    "wof:name":"San Jose Guadalupe",
    "wof:placetype":"locality"
},
  "geometry": {"coordinates":[-92.13,16.93202],"type":"Point"}
}