{
  "type": "Feature",
  "properties": {
    "gn:admin1_code":"31",
    "gn:admin2_code":"96.0",
    "gn:asciiname":"Pasteje",
    "gn:country_code":"MX",
    "gn:dem":16,
    "gn:feature_class":"P",
    "gn:feature_code":"PPL",
    "gn:name":"Pastej\u00e9",
    "gn:population":0,
    "gn:timezone":"America/Merida",
    "iso:country":"MX",
    "name:spa_x_preferred":[
        "Pastej\u00e9"
    ],
    "wof:name":"Pasteje",
    "wof:placetype":"locality"
},
  "geometry": {"coordinates":[-87.93191999999998,21.25178],"type":"Point"}
}