{
  "type": "Feature",
  "properties": {
    "iso:country":"MX",
    "name:cat_x_preferred":[
        "Provid\u00e8ncia"
    ],
    "name:ceb_x_preferred":[
        "Providencia"
    ],
    "name:deu_x_preferred":[
        "Providencia"
    ],
    "name:fra_x_preferred":[
        "Providencia"
    ],
    "name:ita_x_preferred":[
        "Providencia"
    ],
    "name:kor_x_preferred":[
        "\ud504\ub85c\ube44\ub374\uc2dc\uc544"
    ],
    "name:nld_x_preferred":[
        "Providencia"
    ],
    "name:pol_x_preferred":[
        "Providencia"
    ],
    "name:por_x_preferred":[
        "Provid\u00eancia"
    ],
    "name:rus_x_preferred":[
        "\u041f\u0440\u043e\u0432\u0438\u0434\u0435\u043d\u0441\u0438\u044f"
    ],
    "name:sco_x_preferred":[
        "Providencia"
    ],
    "name:spa_x_preferred":[
        "Providencia"
    ],
    "name:swe_x_preferred":[
        "Providencia"
    ],
    "name:zho_x_preferred":[
        "\u666e\u7f85\u7dad\u767b\u897f\u4e9e"
    ],
    "qs_pg:aaroncc":"MX",
    "qs_pg:name":"Providencia",
    "qs_pg:name_adm0":"M\u00e9xico",
    "qs_pg:name_adm1":"Mexico",
    "qs_pg:photos":3,
    "qs_pg:photos_1k":1,
    "qs_pg:photos_9k":1,
    "qs_pg:photos_9r":1,
    "qs_pg:photos_all":3,
    "qs_pg:photos_sr":1,
    "qs_pg:pop_sr":0,
    "qs_pg:qs_pg_placetype":"neighbourhood",
    "qs_pg:qs_pg_placetype_gp":"Suburb",
    "qs_pg:woe_adm0":23424900,
    "woe:adm0_id":23424900,
    "woe:name_adm0":"M\u00e9xico",
    "woe:name_adm1":"Mexico",
    "woe:placetype":"Suburb",
    "wof:name":"Providencia",
    "wof:placetype":"neighbourhood"
},
  "geometry": {"coordinates":[-98.958778,19.303086],"type":"Point"}
}