{
  "type": "Feature",
  "properties": {
    "gn:admin1_code":"12.0",
    "gn:admin2_code":"57.0",
    "gn:asciiname":"Arroyo del Carrizal Uno",
    "gn:cc2":"MX",
    "gn:country_code":"MX",
    "gn:dem":304,
    "gn:feature_class":"P",
    "gn:feature_code":"PPL",
    "gn:name":"Arroyo del Carrizal Uno",
    "gn:population":9,
    "gn:timezone":"America/Mexico_City",
    "iso:country":"MX",
    "name:und_x_variant":[
        "El Carrizal",
        "Carrizal"
    ],
    "wof:name":"Arroyo del Carrizal Uno",
    "wof:placetype":"locality",
    "wof:population":9
},
  "geometry": {"coordinates":[-100.61113,17.42718],"type":"Point"}
}