{
  "type": "Feature",
  "properties": {
    "gn:admin1_code":"26",
    "gn:admin2_code":"69.0",
    "gn:asciiname":"Los Pinitos",
    "gn:country_code":"MX",
    "gn:dem":860,
    "gn:feature_class":"P",
    "gn:feature_code":"PPL",
    "gn:name":"Los Pinitos",
    "gn:population":0,
    "gn:timezone":"America/Hermosillo",
    "iso:country":"MX",
    "name:spa_x_preferred":[
        "Los Pinitos"
    ],
    "wof:name":"Los Pinitos",
    "wof:placetype":"locality"
},
  "geometry": {"coordinates":[-109.15072000000001,28.29447],"type":"Point"}
}