{
  "type": "Feature",
  "properties": {
    "gn:admin1_code":"30",
    "gn:admin2_code":"49.0",
    "gn:asciiname":"Sombrerete",
    "gn:country_code":"MX",
    "gn:dem":124,
    "gn:feature_class":"P",
    "gn:feature_code":"PPL",
    "gn:name":"Sombrerete",
    "gn:population":0,
    "gn:timezone":"America/Mexico_City",
    "iso:country":"MX",
    "name:spa_x_preferred":[
        "Sombrerete"
    ],
    "wof:name":"Sombrerete",
    "wof:placetype":"locality"
},
  "geometry": {"coordinates":[-96.44880000000001,18.86595],"type":"Point"}
}