{
  "type": "Feature",
  "properties": {
    "gn:admin1_code":"10",
    "gn:admin2_code":"5.0",
    "gn:asciiname":"Horacio Ruiz",
    "gn:country_code":"MX",
    "gn:dem":1866,
    "gn:feature_class":"P",
    "gn:feature_code":"PPL",
    "gn:name":"Horacio Ruiz",
    "gn:population":5,
    "gn:timezone":"America/Monterrey",
    "iso:country":"MX",
    "wof:name":"Horacio Ruiz",
    "wof:placetype":"locality",
    "wof:population":5
},
  "geometry": {"coordinates":[-104.56332999999999,24.17361],"type":"Point"}
}