{
  "type": "Feature",
  "properties": {
    "gn:admin1_code":"20",
    "gn:admin2_code":"41.0",
    "gn:asciiname":"Pena Campana",
    "gn:country_code":"MX",
    "gn:dem":1470,
    "gn:feature_class":"P",
    "gn:feature_code":"PPL",
    "gn:name":"Pe\u00f1a Campana",
    "gn:population":179,
    "gn:timezone":"America/Mexico_City",
    "iso:country":"MX",
    "name:und_x_variant":[
        "Pe\u00f1a Campana"
    ],
    "wof:name":"Pena Campana",
    "wof:placetype":"locality",
    "wof:population":179
},
  "geometry": {"coordinates":[-96.85917000000001,18.08806],"type":"Point"}
}