{
  "type": "Feature",
  "properties": {
    "gn:admin1_code":"30",
    "gn:admin2_code":"101.0",
    "gn:asciiname":"Villahermosa",
    "gn:country_code":"MX",
    "gn:dem":2658,
    "gn:feature_class":"P",
    "gn:feature_code":"PPL",
    "gn:name":"Villahermosa",
    "gn:population":199,
    "gn:timezone":"America/Mexico_City",
    "iso:country":"MX",
    "wof:name":"Villahermosa",
    "wof:placetype":"locality",
    "wof:population":199
},
  "geometry": {"coordinates":[-97.21889,18.93],"type":"Point"}
}