{
  "type": "Feature",
  "properties": {
    "gn:admin1_code":"30",
    "gn:admin2_code":"145.0",
    "gn:asciiname":"La Colmena",
    "gn:country_code":"MX",
    "gn:dem":53,
    "gn:feature_class":"P",
    "gn:feature_code":"PPL",
    "gn:name":"La Colmena",
    "gn:population":378,
    "gn:timezone":"America/Mexico_City",
    "iso:country":"MX",
    "name:ceb_x_preferred":[
        "La Colmena"
    ],
    "name:fra_x_preferred":[
        "La Colmena"
    ],
    "name:glg_x_preferred":[
        "La colmena"
    ],
    "name:nld_x_preferred":[
        "La colmena"
    ],
    "name:spa_x_preferred":[
        "La colmena"
    ],
    "name:swe_x_preferred":[
        "La Colmena"
    ],
    "wof:name":"La Colmena",
    "wof:placetype":"locality",
    "wof:population":378
},
  "geometry": {"coordinates":[-94.84222,17.99389],"type":"Point"}
}