{
  "type": "Feature",
  "properties": {
    "gn:admin1_code":"32",
    "gn:admin2_code":"33.0",
    "gn:asciiname":"Rancho el Dulce",
    "gn:country_code":"MX",
    "gn:dem":1198,
    "gn:feature_class":"P",
    "gn:feature_code":"PPL",
    "gn:name":"Rancho el Dulce",
    "gn:population":6,
    "gn:timezone":"America/Mexico_City",
    "iso:country":"MX",
    "wof:name":"Rancho el Dulce",
    "wof:placetype":"locality",
    "wof:population":6
},
  "geometry": {"coordinates":[-103.16139,21.27889],"type":"Point"}
}