{
  "type": "Feature",
  "properties": {
    "gn:admin1_code":"20",
    "gn:admin2_code":"286.0",
    "gn:asciiname":"Xinitioco",
    "gn:country_code":"MX",
    "gn:dem":2107,
    "gn:feature_class":"P",
    "gn:feature_code":"PPL",
    "gn:name":"Xinitioco",
    "gn:population":129,
    "gn:timezone":"America/Mexico_City",
    "iso:country":"MX",
    "wof:name":"Xinitioco",
    "wof:placetype":"locality",
    "wof:population":129
},
  "geometry": {"coordinates":[-97.98972000000001,17.415],"type":"Point"}
}