{
  "type": "Feature",
  "properties": {
    "gn:admin1_code":"13",
    "gn:admin2_code":"28.0",
    "gn:asciiname":"Hueynali",
    "gn:country_code":"MX",
    "gn:dem":239,
    "gn:feature_class":"P",
    "gn:feature_code":"PPL",
    "gn:name":"Hueynali",
    "gn:population":512,
    "gn:timezone":"America/Mexico_City",
    "iso:country":"MX",
    "wof:name":"Hueynali",
    "wof:placetype":"locality",
    "wof:population":512
},
  "geometry": {"coordinates":[-98.45611,21.14778],"type":"Point"}
}