{
  "type": "Feature",
  "properties": {
    "gn:admin1_code":"12.0",
    "gn:asciiname":"Doyo Kutu'ndii",
    "gn:country_code":"MX",
    "gn:dem":1106,
    "gn:feature_class":"P",
    "gn:feature_code":"PPL",
    "gn:name":"Doyo Kutu\u2019ndii",
    "gn:population":0,
    "gn:timezone":"America/Mexico_City",
    "iso:country":"MX",
    "name:spa_x_preferred":[
        "Doyo Kutu\u2019ndii"
    ],
    "wof:name":"Doyo Kutu'ndii",
    "wof:placetype":"locality"
},
  "geometry": {"coordinates":[-98.53953,17.02024],"type":"Point"}
}