{
  "type": "Feature",
  "properties": {
    "gn:admin1_code":"6.0",
    "gn:admin2_code":"17.0",
    "gn:asciiname":"Campo 16",
    "gn:country_code":"MX",
    "gn:dem":1982,
    "gn:feature_class":"P",
    "gn:feature_code":"PPL",
    "gn:name":"Campo 16",
    "gn:population":0,
    "gn:timezone":"America/Chihuahua",
    "iso:country":"MX",
    "wof:name":"Campo 16",
    "wof:placetype":"locality"
},
  "geometry": {"coordinates":[-106.87079,28.56021],"type":"Point"}
}