{
  "type": "Feature",
  "properties": {
    "gn:admin1_code":"26",
    "gn:admin2_code":"70.0",
    "gn:asciiname":"Miguel M. Pina",
    "gn:country_code":"MX",
    "gn:dem":382,
    "gn:feature_class":"P",
    "gn:feature_code":"PPL",
    "gn:name":"Miguel M. Pi\u00f1a",
    "gn:population":0,
    "gn:timezone":"America/Hermosillo",
    "iso:country":"MX",
    "wof:name":"Miguel M. Pina",
    "wof:placetype":"locality"
},
  "geometry": {"coordinates":[-112.90000000000001,31.66667],"type":"Point"}
}