{
  "type": "Feature",
  "properties": {
    "gn:admin1_code":"32",
    "gn:admin2_code":"44.0",
    "gn:asciiname":"Jaralillo",
    "gn:country_code":"MX",
    "gn:dem":1605,
    "gn:feature_class":"P",
    "gn:feature_code":"PPL",
    "gn:name":"Jaralillo",
    "gn:population":0,
    "gn:timezone":"America/Mexico_City",
    "iso:country":"MX",
    "wof:name":"Jaralillo",
    "wof:placetype":"locality"
},
  "geometry": {"coordinates":[-102.97812999999999,21.86455],"type":"Point"}
}