{
  "type": "Feature",
  "properties": {
    "gn:admin1_code":"3",
    "gn:admin2_code":"3",
    "gn:asciiname":"Corral Falso",
    "gn:country_code":"MX",
    "gn:dem":309,
    "gn:feature_class":"P",
    "gn:feature_code":"PPL",
    "gn:name":"Corral Falso",
    "gn:population":15,
    "gn:timezone":"America/Mazatlan",
    "iso:country":"MX",
    "name:ita_x_preferred":[
        "Corral Falso"
    ],
    "name:spa_x_preferred":[
        "Corral Falso"
    ],
    "name:zho_x_preferred":[
        "\u79d1\u62c9\u723e\u6cd5\u723e\u7d22"
    ],
    "wof:name":"Corral Falso",
    "wof:placetype":"locality",
    "wof:population":15
},
  "geometry": {"coordinates":[-110.85724999999999,24.8083],"type":"Point"}
}