{
  "type": "Feature",
  "properties": {
    "gn:admin1_code":"22",
    "gn:admin2_code":"11.0",
    "gn:asciiname":"Rancho el Momento",
    "gn:country_code":"MX",
    "gn:dem":1899,
    "gn:feature_class":"P",
    "gn:feature_code":"PPL",
    "gn:name":"Rancho el Momento",
    "gn:population":8,
    "gn:timezone":"America/Mexico_City",
    "iso:country":"MX",
    "wof:name":"Rancho el Momento",
    "wof:placetype":"locality",
    "wof:population":8
},
  "geometry": {"coordinates":[-100.21778,20.60222000000001],"type":"Point"}
}