{
  "type": "Feature",
  "properties": {
    "gn:admin1_code":"20",
    "gn:admin2_code":"205",
    "gn:asciiname":"Arroyo Yolan",
    "gn:country_code":"MX",
    "gn:dem":78,
    "gn:feature_class":"P",
    "gn:feature_code":"PPL",
    "gn:name":"Arroyo Yolan",
    "gn:population":35,
    "gn:timezone":"America/Mexico_City",
    "iso:country":"MX",
    "wof:name":"Arroyo Yolan",
    "wof:placetype":"locality",
    "wof:population":35
},
  "geometry": {"coordinates":[-95.57138999999999,17.53639],"type":"Point"}
}