{
  "type": "Feature",
  "properties": {
    "gn:admin1_code":"11",
    "gn:admin2_code":"20.0",
    "gn:asciiname":"Luis Hernandez",
    "gn:country_code":"MX",
    "gn:dem":1783,
    "gn:feature_class":"P",
    "gn:feature_code":"PPL",
    "gn:name":"Luis Hern\u00e1ndez",
    "gn:population":8,
    "gn:timezone":"America/Mexico_City",
    "iso:country":"MX",
    "name:und_x_variant":[
        "Luis Hern\u00e1ndez"
    ],
    "wof:name":"Luis Hernandez",
    "wof:placetype":"locality",
    "wof:population":8
},
  "geometry": {"coordinates":[-101.67778,21.01194],"type":"Point"}
}