{
  "type": "Feature",
  "properties": {
    "gn:admin1_code":"25.0",
    "gn:asciiname":"El Charco",
    "gn:country_code":"MX",
    "gn:dem":5,
    "gn:feature_class":"P",
    "gn:feature_code":"PPL",
    "gn:name":"El Charco",
    "gn:population":0,
    "gn:timezone":"America/Mazatlan",
    "iso:country":"MX",
    "name:spa_x_preferred":[
        "El Charco"
    ],
    "wof:name":"El Charco",
    "wof:placetype":"locality"
},
  "geometry": {"coordinates":[-105.94538,22.84678],"type":"Point"}
}