{
  "type": "Feature",
  "properties": {
    "gn:admin1_code":"27",
    "gn:admin2_code":"4.0",
    "gn:asciiname":"Veintiuno de Marzo",
    "gn:country_code":"MX",
    "gn:dem":10,
    "gn:feature_class":"P",
    "gn:feature_code":"PPL",
    "gn:name":"Veintiuno de Marzo",
    "gn:population":0,
    "gn:timezone":"America/Mexico_City",
    "iso:country":"MX",
    "name:spa_x_preferred":[
        "Veintiuno de Marzo"
    ],
    "wof:name":"Veintiuno de Marzo",
    "wof:placetype":"locality"
},
  "geometry": {"coordinates":[-93.04340999999999,18.01239],"type":"Point"}
}