{
  "type": "Feature",
  "properties": {
    "gn:admin1_code":"6",
    "gn:admin2_code":"31.0",
    "gn:asciiname":"Rio Verde",
    "gn:country_code":"MX",
    "gn:dem":2032,
    "gn:feature_class":"P",
    "gn:feature_code":"PPL",
    "gn:name":"R\u00edo Verde",
    "gn:population":164,
    "gn:timezone":"America/Chihuahua",
    "iso:country":"MX",
    "wof:name":"Rio Verde",
    "wof:placetype":"locality",
    "wof:population":164
},
  "geometry": {"coordinates":[-107.76194,28.38861],"type":"Point"}
}