{
  "type": "Feature",
  "properties": {
    "gn:admin1_code":"5",
    "gn:admin2_code":"3.0",
    "gn:asciiname":"Barra Zacapulco",
    "gn:cc2":"MX",
    "gn:country_code":"MX",
    "gn:dem":9,
    "gn:feature_class":"P",
    "gn:feature_code":"PPL",
    "gn:name":"Barra Zacapulco",
    "gn:population":385,
    "gn:timezone":"America/Mexico_City",
    "iso:country":"MX",
    "name:und_x_variant":[
        "Barra de Sacapulco",
        "Sacapulco",
        "Zacapulco"
    ],
    "wof:name":"Barra Zacapulco",
    "wof:placetype":"locality",
    "wof:population":385
},
  "geometry": {"coordinates":[-92.88306,15.195],"type":"Point"}
}