{
  "type": "Feature",
  "properties": {
    "gn:admin1_code":"6",
    "gn:admin2_code":"29.0",
    "gn:asciiname":"Uruachito",
    "gn:country_code":"MX",
    "gn:dem":1363,
    "gn:feature_class":"P",
    "gn:feature_code":"PPL",
    "gn:name":"Uruachito",
    "gn:population":0,
    "gn:timezone":"America/Chihuahua",
    "iso:country":"MX",
    "name:spa_x_preferred":[
        "Uruachito"
    ],
    "wof:name":"Uruachito",
    "wof:placetype":"locality"
},
  "geometry": {"coordinates":[-107.61335,26.31511],"type":"Point"}
}