{
  "type": "Feature",
  "properties": {
    "gn:admin1_code":"16.0",
    "gn:admin2_code":"12.0",
    "gn:asciiname":"La Pachicua",
    "gn:country_code":"MX",
    "gn:dem":791,
    "gn:feature_class":"P",
    "gn:feature_code":"PPL",
    "gn:name":"La Pachicua",
    "gn:population":0,
    "gn:timezone":"America/Mexico_City",
    "iso:country":"MX",
    "name:spa_x_preferred":[
        "La Pachicua"
    ],
    "wof:name":"La Pachicua",
    "wof:placetype":"locality"
},
  "geometry": {"coordinates":[-102.53461,19.25938],"type":"Point"}
}