{
  "type": "Feature",
  "properties": {
    "gn:admin1_code":"19.0",
    "gn:admin2_code":"22.0",
    "gn:asciiname":"El Aguila",
    "gn:country_code":"MX",
    "gn:dem":222,
    "gn:feature_class":"P",
    "gn:feature_code":"PPL",
    "gn:name":"El Aguila",
    "gn:population":0,
    "gn:timezone":"America/Monterrey",
    "iso:country":"MX",
    "name:spa_x_preferred":[
        "El Aguila"
    ],
    "wof:name":"El Aguila",
    "wof:placetype":"locality"
},
  "geometry": {"coordinates":[-99.33701000000001,25.31949],"type":"Point"}
}