{
  "type": "Feature",
  "properties": {
    "gn:admin1_code":"7.0",
    "gn:admin2_code":"7.0",
    "gn:asciiname":"Ejido El Venado",
    "gn:country_code":"MX",
    "gn:dem":706,
    "gn:feature_class":"P",
    "gn:feature_code":"PPL",
    "gn:name":"Ejido El Venado",
    "gn:population":0,
    "gn:timezone":"America/Monterrey",
    "iso:country":"MX",
    "wof:name":"Ejido El Venado",
    "wof:placetype":"locality"
},
  "geometry": {"coordinates":[-101.95377000000001,26.80704],"type":"Point"}
}