{
  "type": "Feature",
  "properties": {
    "gn:admin1_code":"14.0",
    "gn:admin2_code":"53.0",
    "gn:asciiname":"Castelongo",
    "gn:country_code":"MX",
    "gn:dem":1999,
    "gn:feature_class":"P",
    "gn:feature_code":"PPL",
    "gn:name":"Castelongo",
    "gn:population":0,
    "gn:timezone":"America/Mexico_City",
    "iso:country":"MX",
    "name:spa_x_preferred":[
        "Castelongo"
    ],
    "name:spa_x_variant":[
        "El Saucillo"
    ],
    "wof:name":"Castelongo",
    "wof:placetype":"locality"
},
  "geometry": {"coordinates":[-101.84072999999999,21.31829],"type":"Point"}
}