{
  "type": "Feature",
  "properties": {
    "gn:admin1_code":"28",
    "gn:admin2_code":"15.0",
    "gn:asciiname":"Los Sauces",
    "gn:country_code":"MX",
    "gn:dem":66,
    "gn:feature_class":"P",
    "gn:feature_code":"PPL",
    "gn:name":"Los Sauces",
    "gn:population":4,
    "gn:timezone":"America/Monterrey",
    "iso:country":"MX",
    "name:eus_x_preferred":[
        "Los Sauces"
    ],
    "name:fra_x_preferred":[
        "Los Sauces"
    ],
    "name:ita_x_preferred":[
        "Los Sauces"
    ],
    "name:kor_x_preferred":[
        "\ub85c\uc2a4\uc0ac\uc6b0\uc138\uc2a4"
    ],
    "name:nld_x_preferred":[
        "Los Sauces"
    ],
    "name:por_x_preferred":[
        "Los Sauces"
    ],
    "name:ron_x_preferred":[
        "Los Sauces"
    ],
    "name:rus_x_preferred":[
        "\u041b\u043e\u0441-\u0421\u0430\u0443\u0441\u0435\u0441"
    ],
    "name:spa_x_preferred":[
        "Los Sauces"
    ],
    "name:und_x_variant":[
        "Rancho Los Sauces",
        "Sauces"
    ],
    "name:zho_x_preferred":[
        "\u6d1b\u65af\u7d39\u585e\u65af"
    ],
    "wof:name":"Los Sauces",
    "wof:placetype":"locality",
    "wof:population":4
},
  "geometry": {"coordinates":[-98.71832999999999,26.09383],"type":"Point"}
}