{
  "type": "Feature",
  "properties": {
    "gn:admin1_code":"11.0",
    "gn:asciiname":"Casa Lopez",
    "gn:country_code":"MX",
    "gn:dem":1813,
    "gn:feature_class":"P",
    "gn:feature_code":"PPL",
    "gn:name":"Casa L\u00f3pez",
    "gn:population":0,
    "gn:timezone":"America/Mexico_City",
    "iso:country":"MX",
    "name:spa_x_preferred":[
        "Casa L\u00f3pez"
    ],
    "wof:name":"Casa Lopez",
    "wof:placetype":"locality"
},
  "geometry": {"coordinates":[-101.96328,20.68455],"type":"Point"}
}