{
  "type": "Feature",
  "properties": {
    "gn:admin1_code":"12",
    "gn:admin2_code":"2",
    "gn:asciiname":"Tezoquite (Tierra Prieta)",
    "gn:country_code":"MX",
    "gn:dem":1398,
    "gn:feature_class":"P",
    "gn:feature_code":"PPL",
    "gn:name":"Tezoquite (Tierra Prieta)",
    "gn:population":12,
    "gn:timezone":"America/Mexico_City",
    "iso:country":"MX",
    "wof:name":"Tezoquite (Tierra Prieta)",
    "wof:placetype":"locality",
    "wof:population":12
},
  "geometry": {"coordinates":[-99.05037,17.707],"type":"Point"}
}