{
  "type": "Feature",
  "properties": {
    "gn:admin1_code":"20",
    "gn:admin2_code":"12",
    "gn:asciiname":"Llano Frio",
    "gn:country_code":"MX",
    "gn:dem":450,
    "gn:feature_class":"P",
    "gn:feature_code":"PPL",
    "gn:name":"Llano Fr\u00edo",
    "gn:population":21,
    "gn:timezone":"America/Mexico_City",
    "iso:country":"MX",
    "name:und_x_variant":[
        "Llano Fr\u00edo"
    ],
    "wof:name":"Llano Frio",
    "wof:placetype":"locality",
    "wof:population":21
},
  "geometry": {"coordinates":[-96.56694,15.86528],"type":"Point"}
}