{
  "type": "Feature",
  "properties": {
    "gn:admin1_code":"5",
    "gn:admin2_code":"99.0",
    "gn:asciiname":"Belen Uno",
    "gn:country_code":"MX",
    "gn:dem":923,
    "gn:feature_class":"P",
    "gn:feature_code":"PPL",
    "gn:name":"Bel\u00e9n Uno",
    "gn:population":6,
    "gn:timezone":"America/Mexico_City",
    "iso:country":"MX",
    "name:und_x_variant":[
        "Bel\u00e9n Uno"
    ],
    "wof:name":"Belen Uno",
    "wof:placetype":"locality",
    "wof:population":6
},
  "geometry": {"coordinates":[-91.92917,15.97417],"type":"Point"}
}