{
  "type": "Feature",
  "properties": {
    "gn:admin1_code":"11.0",
    "gn:admin2_code":"19.0",
    "gn:asciiname":"San Jose de Pena",
    "gn:country_code":"MX",
    "gn:dem":2009,
    "gn:feature_class":"P",
    "gn:feature_code":"PPL",
    "gn:name":"San Jos\u00e9 de Pe\u00f1a",
    "gn:population":285,
    "gn:timezone":"America/Mexico_City",
    "iso:country":"MX",
    "name:spa_x_preferred":[
        "San Jos\u00e9 de Pe\u00f1a"
    ],
    "name:spa_x_variant":[
        "San Jos\u00e9 de la Pe\u00f1a"
    ],
    "wof:name":"San Jose de Pena",
    "wof:placetype":"locality",
    "wof:population":285
},
  "geometry": {"coordinates":[-100.64778,20.29083],"type":"Point"}
}