{
  "type": "Feature",
  "properties": {
    "gn:admin1_code":"16",
    "gn:admin2_code":"102.0",
    "gn:asciiname":"Predio Cerro Colorado (Rancho Sonado)",
    "gn:country_code":"MX",
    "gn:dem":1842,
    "gn:feature_class":"P",
    "gn:feature_code":"PPL",
    "gn:name":"Predio Cerro Colorado (Rancho So\u00f1ado)",
    "gn:population":8,
    "gn:timezone":"America/Mexico_City",
    "iso:country":"MX",
    "name:und_x_variant":[
        "Predio Cerro Colorado (Rancho So\u00f1ado)"
    ],
    "wof:name":"Predio Cerro Colorado (Rancho Sonado)",
    "wof:placetype":"locality",
    "wof:population":8
},
  "geometry": {"coordinates":[-101.98944,19.4525],"type":"Point"}
}