{
  "type": "Feature",
  "properties": {
    "gn:admin1_code":"31",
    "gn:admin2_code":"58.0",
    "gn:asciiname":"Papacal",
    "gn:country_code":"MX",
    "gn:dem":26,
    "gn:feature_class":"P",
    "gn:feature_code":"PPL",
    "gn:name":"Papacal",
    "gn:population":0,
    "gn:timezone":"America/Merida",
    "iso:country":"MX",
    "name:spa_x_preferred":[
        "Papacal"
    ],
    "wof:name":"Papacal",
    "wof:placetype":"locality"
},
  "geometry": {"coordinates":[-88.81668000000001,20.15384],"type":"Point"}
}