{
  "type": "Feature",
  "properties": {
    "gn:admin1_code":"13",
    "gn:admin2_code":"24",
    "gn:asciiname":"Barranca del Xuchil",
    "gn:country_code":"MX",
    "gn:dem":1584,
    "gn:feature_class":"P",
    "gn:feature_code":"PPL",
    "gn:name":"Barranca del X\u00fachil",
    "gn:population":11,
    "gn:timezone":"America/Mexico_City",
    "iso:country":"MX",
    "name:und_x_variant":[
        "Barranca del X\u00fachil"
    ],
    "wof:name":"Barranca del Xuchil",
    "wof:placetype":"locality",
    "wof:population":11
},
  "geometry": {"coordinates":[-98.51416999999999,20.28417],"type":"Point"}
}