{
  "type": "Feature",
  "properties": {
    "gn:admin1_code":"19.0",
    "gn:asciiname":"Rincon de San Antonio",
    "gn:country_code":"MX",
    "gn:dem":1960,
    "gn:feature_class":"P",
    "gn:feature_code":"PPL",
    "gn:name":"Rinc\u00f3n de San Antonio",
    "gn:population":0,
    "gn:timezone":"America/Monterrey",
    "iso:country":"MX",
    "name:spa_x_preferred":[
        "Rinc\u00f3n de San Antonio"
    ],
    "name:spa_x_variant":[
        "Rinc\u00f3n Santa Ana"
    ],
    "wof:name":"Rincon de San Antonio",
    "wof:placetype":"locality"
},
  "geometry": {"coordinates":[-99.99934,24.66247000000001],"type":"Point"}
}