{
  "type": "Feature",
  "properties": {
    "gn:admin1_code":"2",
    "gn:admin2_code":"1",
    "gn:asciiname":"Rancho Aguacaliente (Baja Country Club)",
    "gn:country_code":"MX",
    "gn:dem":46,
    "gn:feature_class":"P",
    "gn:feature_code":"PPL",
    "gn:name":"Rancho Aguacaliente (Baja Country Club)",
    "gn:population":27,
    "gn:timezone":"America/Tijuana",
    "iso:country":"MX",
    "wof:name":"Rancho Aguacaliente (Baja Country Club)",
    "wof:placetype":"locality",
    "wof:population":27
},
  "geometry": {"coordinates":[-116.52694,31.77028],"type":"Point"}
}