{
  "type": "Feature",
  "properties": {
    "gn:admin1_code":"7.0",
    "gn:admin2_code":"38.0",
    "gn:asciiname":"Las Urracas",
    "gn:country_code":"MX",
    "gn:dem":366,
    "gn:feature_class":"P",
    "gn:feature_code":"PPL",
    "gn:name":"Las Urracas",
    "gn:population":0,
    "gn:timezone":"America/Monterrey",
    "iso:country":"MX",
    "name:spa_x_preferred":[
        "Las Urracas"
    ],
    "wof:name":"Las Urracas",
    "wof:placetype":"locality"
},
  "geometry": {"coordinates":[-100.9331,28.49412],"type":"Point"}
}