{
  "type": "Feature",
  "properties": {
    "gn:admin1_code":"24",
    "gn:admin2_code":"11.0",
    "gn:asciiname":"Colonia la Penita",
    "gn:country_code":"MX",
    "gn:dem":1040,
    "gn:feature_class":"P",
    "gn:feature_code":"PPL",
    "gn:name":"Colonia la Pe\u00f1ita",
    "gn:population":204,
    "gn:timezone":"America/Mexico_City",
    "iso:country":"MX",
    "name:und_x_variant":[
        "Colonia la Pe\u00f1ita"
    ],
    "wof:name":"Colonia la Penita",
    "wof:placetype":"locality",
    "wof:population":204
},
  "geometry": {"coordinates":[-100.09778,21.92528],"type":"Point"}
}