{
  "type": "Feature",
  "properties": {
    "gn:admin1_code":"14.0",
    "gn:admin2_code":"33.0",
    "gn:asciiname":"El Tronconal",
    "gn:country_code":"MX",
    "gn:dem":1674,
    "gn:feature_class":"P",
    "gn:feature_code":"PPL",
    "gn:name":"El Tronconal",
    "gn:population":0,
    "gn:timezone":"America/Mexico_City",
    "iso:country":"MX",
    "name:spa_x_preferred":[
        "El Tronconal"
    ],
    "wof:name":"El Tronconal",
    "wof:placetype":"locality"
},
  "geometry": {"coordinates":[-102.15309999999999,20.40537],"type":"Point"}
}