{
  "type": "Feature",
  "properties": {
    "iso:country":"MX",
    "name:bre_x_preferred":[
        "San Rafael"
    ],
    "name:ceb_x_preferred":[
        "San Rafael"
    ],
    "name:ces_x_preferred":[
        "San Rafael"
    ],
    "name:deu_x_preferred":[
        "San Rafael"
    ],
    "name:fas_x_preferred":[
        "\u0633\u0627\u0646 \u0631\u0627\u0641\u0627\u0626\u0644"
    ],
    "name:fin_x_preferred":[
        "San Rafael"
    ],
    "name:fra_x_preferred":[
        "San Rafael"
    ],
    "name:hun_x_preferred":[
        "San Rafael"
    ],
    "name:hye_x_preferred":[
        "\u054d\u0561\u0576 \u054c\u0561\u0586\u0561\u0575\u0565\u056c"
    ],
    "name:ilo_x_preferred":[
        "San Rafael"
    ],
    "name:ita_x_preferred":[
        "San Rafael"
    ],
    "name:jpn_x_preferred":[
        "\u30b5\u30f3\u30fb\u30e9\u30d5\u30a1\u30a8\u30eb"
    ],
    "name:kor_x_preferred":[
        "\uc0b0 \ub77c\ud30c\uc5d8"
    ],
    "name:kor_x_variant":[
        "\uc0b0\ub77c\ud30c\uc5d8"
    ],
    "name:mlg_x_preferred":[
        "San Rafael"
    ],
    "name:nld_x_preferred":[
        "San Rafael"
    ],
    "name:pol_x_preferred":[
        "San Rafael"
    ],
    "name:por_x_preferred":[
        "San Rafael"
    ],
    "name:rus_x_preferred":[
        "\u0421\u0430\u043d-\u0420\u0430\u0444\u0430\u044d\u043b\u044c"
    ],
    "name:sco_x_preferred":[
        "San Rafael"
    ],
    "name:spa_x_preferred":[
        "San Rafael"
    ],
    "name:srp_x_preferred":[
        "\u0421\u0430\u043d \u0420\u0430\u0444\u0430\u0435\u043b"
    ],
    "name:swe_x_preferred":[
        "San Rafael"
    ],
    "name:tur_x_preferred":[
        "San Rafael"
    ],
    "name:ukr_x_preferred":[
        "\u0421\u0430\u043d-\u0420\u0430\u0444\u0430\u0435\u043b\u044c"
    ],
    "name:urd_x_preferred":[
        "\u0633\u0627\u0646 \u0631\u0627\u0641\u0627\u0626\u0644"
    ],
    "name:vie_x_preferred":[
        "San Rafael"
    ],
    "name:war_x_preferred":[
        "San Rafael"
    ],
    "qs:gn_adm0_cc":"MX",
    "qs:gn_fcode":"PPL",
    "qs:gn_local":4012408,
    "qs:gn_nam_loc":"Cuauhtemoc, Cuauht\u00e9moc, Colima, MX",
    "qs:gn_namadm1":"08",
    "qs:gn_name":"San Rafael",
    "qs:local_max":14,
    "qs:local_sum":14,
    "qs:localhoods":1,
    "qs:name":"San Rafael",
    "qs:name_adm0":"M\u00e9xico",
    "qs:name_adm1":"Colima",
    "qs:name_adm2":"Cuauhtemoc",
    "qs:name_local":"Cuauht\u00e9moc",
    "qs:photo_max":12,
    "qs:photo_sum":14,
    "qs:placetype":"Suburb",
    "qs:quad_count":3,
    "qs:woe_adm0":23424900,
    "qs:woe_adm1":2346271,
    "qs:woe_adm2":12599928,
    "qs:woe_lau":0,
    "qs:woe_local":117788,
    "qs:woe_ver":"7.10.0",
    "wof:lang":[
        "spa"
    ],
    "wof:name":"San Rafael",
    "wof:placetype":"neighbourhood"
},
  "geometry": {"coordinates":[-103.60225199999999,19.329658],"type":"Point"}
}