{
  "type": "Feature",
  "properties": {
    "iso:country":"MX",
    "name:spa_x_preferred":[
        "San Rafael"
    ],
    "name:unk_x_variant":[
        "San Rafael"
    ],
    "qs:gn_adm0_cc":"MX",
    "qs:gn_fcode":"PPL",
    "qs:gn_local":4012408,
    "qs:gn_nam_loc":"Cuauhtemoc, Cuauht\u00e9moc, Colima, MX",
    "qs:gn_namadm1":"08",
    "qs:gn_name":"San Rafael",
    "qs:local_max":14,
    "qs:local_sum":14,
    "qs:localhoods":1,
    "qs:name":"San Rafael",
    "qs:name_adm0":"M\u00e9xico",
    "qs:name_adm1":"Colima",
    "qs:name_adm2":"Cuauhtemoc",
    "qs:name_local":"Cuauht\u00e9moc",
    "qs:photo_max":12,
    "qs:photo_sum":14,
    "qs:placetype":"Suburb",
    "qs:quad_count":3,
    "qs:woe_adm0":23424900,
    "qs:woe_adm1":2346271,
    "qs:woe_adm2":12599928,
    "qs:woe_lau":0,
    "qs:woe_local":117788,
    "qs:woe_ver":"7.10.0",
    "wof:lang":[
        "spa"
    ],
    "wof:name":"San Rafael",
    "wof:placetype":"neighbourhood"
},
  "geometry": {"coordinates":[-103.60225199999999,19.329658],"type":"Point"}
}