{
  "type": "Feature",
  "properties": {
    "gn:admin1_code":"26",
    "gn:admin2_code":"47.0",
    "gn:asciiname":"Kan-Chun-Junga",
    "gn:country_code":"MX",
    "gn:dem":267,
    "gn:feature_class":"P",
    "gn:feature_code":"PPL",
    "gn:name":"Kan-Chun-Junga",
    "gn:population":0,
    "gn:timezone":"America/Hermosillo",
    "iso:country":"MX",
    "name:spa_x_preferred":[
        "Kan-Chun-Junga"
    ],
    "wof:name":"Kan-Chun-Junga",
    "wof:placetype":"locality"
},
  "geometry": {"coordinates":[-111.96223000000001,29.64459],"type":"Point"}
}