{
  "type": "Feature",
  "properties": {
    "gn:admin1_code":"16",
    "gn:admin2_code":"22.0",
    "gn:asciiname":"Triguillos",
    "gn:country_code":"MX",
    "gn:dem":2161,
    "gn:feature_class":"P",
    "gn:feature_code":"PPL",
    "gn:name":"Triguillos",
    "gn:population":345,
    "gn:timezone":"America/Mexico_City",
    "iso:country":"MX",
    "name:spa_x_preferred":[
        "Triguillos"
    ],
    "name:und_x_variant":[
        "Triguillo",
        "Los Triguillos"
    ],
    "wof:name":"Triguillos",
    "wof:placetype":"locality",
    "wof:population":345
},
  "geometry": {"coordinates":[-100.97874,19.64957],"type":"Point"}
}