{
  "type": "Feature",
  "properties": {
    "gn:admin1_code":"28",
    "gn:admin2_code":"39.0",
    "gn:asciiname":"Verdolaga",
    "gn:country_code":"MX",
    "gn:dem":1376,
    "gn:feature_class":"P",
    "gn:feature_code":"PPL",
    "gn:name":"Verdolaga",
    "gn:population":300,
    "gn:timezone":"America/Monterrey",
    "iso:country":"MX",
    "wof:name":"Verdolaga",
    "wof:placetype":"locality",
    "wof:population":300
},
  "geometry": {"coordinates":[-99.84833,23.215],"type":"Point"}
}