{
  "type": "Feature",
  "properties": {
    "gn:admin1_code":"6.0",
    "gn:admin2_code":"40.0",
    "gn:asciiname":"Hinojos",
    "gn:country_code":"MX",
    "gn:dem":2142,
    "gn:feature_class":"P",
    "gn:feature_code":"PPL",
    "gn:name":"Hinojos",
    "gn:population":0,
    "gn:timezone":"America/Chihuahua",
    "iso:country":"MX",
    "name:ara_x_preferred":[
        "\u0625\u0646\u0648\u062e\u0648\u0633"
    ],
    "name:ast_x_preferred":[
        "Hinojos"
    ],
    "name:cat_x_preferred":[
        "Hinojos"
    ],
    "name:ceb_x_preferred":[
        "Hinojos"
    ],
    "name:epo_x_preferred":[
        "Hinojos"
    ],
    "name:eus_x_preferred":[
        "Hinojos"
    ],
    "name:fra_x_preferred":[
        "Hinojos"
    ],
    "name:hat_x_preferred":[
        "Hinojos"
    ],
    "name:hun_x_preferred":[
        "Hinojos"
    ],
    "name:hye_x_preferred":[
        "\u053b\u0576\u0578\u056d\u0578\u057d"
    ],
    "name:hyw_x_preferred":[
        "\u053b\u0576\u0578\u0570\u0578\u057d"
    ],
    "name:ita_x_preferred":[
        "Hinojos"
    ],
    "name:kaz_x_preferred":[
        "\u0418\u043d\u043e\u0445\u043e\u0441"
    ],
    "name:msa_x_preferred":[
        "Hinojos"
    ],
    "name:nld_x_preferred":[
        "Hinojos"
    ],
    "name:oci_x_preferred":[
        "Hinojos"
    ],
    "name:pol_x_preferred":[
        "Hinojos"
    ],
    "name:por_x_preferred":[
        "Hinojos"
    ],
    "name:rus_x_preferred":[
        "\u0418\u043d\u043e\u0445\u043e\u0441"
    ],
    "name:spa_x_preferred":[
        "Hinojos"
    ],
    "name:swe_x_preferred":[
        "Hinojos"
    ],
    "name:tur_x_preferred":[
        "Hinojos"
    ],
    "name:ukr_x_preferred":[
        "\u0406\u043d\u043e\u0445\u043e\u0441"
    ],
    "name:uzb_x_preferred":[
        "Hinojos"
    ],
    "name:vie_x_preferred":[
        "Hinojos"
    ],
    "name:war_x_preferred":[
        "Hinojos"
    ],
    "name:zho_x_preferred":[
        "\u4f0a\u8bfa\u970d\u65af"
    ],
    "wof:name":"Hinojos",
    "wof:placetype":"locality"
},
  "geometry": {"coordinates":[-107.93979,29.36092],"type":"Point"}
}