{
  "type": "Feature",
  "properties": {
    "gn:admin1_code":"6.0",
    "gn:admin2_code":"40.0",
    "gn:asciiname":"Hinojos",
    "gn:country_code":"MX",
    "gn:dem":2142,
    "gn:feature_class":"P",
    "gn:feature_code":"PPL",
    "gn:name":"Hinojos",
    "gn:population":0,
    "gn:timezone":"America/Chihuahua",
    "iso:country":"MX",
    "name:spa_x_preferred":[
        "Hinojos"
    ],
    "wof:name":"Hinojos",
    "wof:placetype":"locality"
},
  "geometry": {"coordinates":[-107.93979,29.36092],"type":"Point"}
}