{
  "type": "Feature",
  "properties": {
    "gn:admin1_code":"17",
    "gn:admin2_code":"8",
    "gn:asciiname":"Fraccionamiento Club de Golf Paraiso",
    "gn:country_code":"MX",
    "gn:dem":1211,
    "gn:feature_class":"P",
    "gn:feature_code":"PPL",
    "gn:name":"Fraccionamiento Club de Golf Para\u00edso",
    "gn:population":17,
    "gn:timezone":"America/Mexico_City",
    "iso:country":"MX",
    "name:und_x_variant":[
        "Fraccionamiento Club de Golf Para\u00edso"
    ],
    "wof:name":"Fraccionamiento Club de Golf Paraiso",
    "wof:placetype":"locality",
    "wof:population":17
},
  "geometry": {"coordinates":[-99.20193999999999,18.83528],"type":"Point"}
}