{
  "type": "Feature",
  "properties": {
    "gn:admin1_code":"6.0",
    "gn:admin2_code":"29.0",
    "gn:asciiname":"Saucito de los Dominguez",
    "gn:country_code":"MX",
    "gn:dem":1105,
    "gn:feature_class":"P",
    "gn:feature_code":"PPL",
    "gn:name":"Saucito de los Dominguez",
    "gn:population":0,
    "gn:timezone":"America/Chihuahua",
    "iso:country":"MX",
    "name:spa_x_preferred":[
        "Saucito de los Dominguez"
    ],
    "wof:name":"Saucito de los Dominguez",
    "wof:placetype":"locality"
},
  "geometry": {"coordinates":[-107.34293,26.19087],"type":"Point"}
}