{
  "type": "Feature",
  "properties": {
    "gn:admin1_code":"13",
    "gn:admin2_code":"2.0",
    "gn:asciiname":"Montemar",
    "gn:country_code":"MX",
    "gn:dem":2170,
    "gn:feature_class":"P",
    "gn:feature_code":"PPL",
    "gn:name":"Montemar",
    "gn:population":340,
    "gn:timezone":"America/Mexico_City",
    "iso:country":"MX",
    "wof:name":"Montemar",
    "wof:placetype":"locality",
    "wof:population":340
},
  "geometry": {"coordinates":[-98.14028,20.14556],"type":"Point"}
}