{
  "type": "Feature",
  "properties": {
    "gn:admin1_code":"18.0",
    "gn:admin2_code":"20.0",
    "gn:asciiname":"El Ojo de Agua",
    "gn:country_code":"MX",
    "gn:dem":59,
    "gn:feature_class":"P",
    "gn:feature_code":"PPL",
    "gn:name":"El Ojo de Agua",
    "gn:population":0,
    "gn:timezone":"America/Bahia_Banderas",
    "iso:country":"MX",
    "name:spa_x_preferred":[
        "El Ojo de Agua"
    ],
    "wof:name":"El Ojo de Agua",
    "wof:placetype":"locality"
},
  "geometry": {"coordinates":[-105.45399999999999,20.76375],"type":"Point"}
}