{
  "type": "Feature",
  "properties": {
    "gn:admin1_code":"15",
    "gn:admin2_code":"39.0",
    "gn:asciiname":"El Patronato del Maguey (Santa Rosa)",
    "gn:country_code":"MX",
    "gn:dem":2254,
    "gn:feature_class":"P",
    "gn:feature_code":"PPL",
    "gn:name":"El Patronato del Maguey (Santa Rosa)",
    "gn:population":490,
    "gn:timezone":"America/Mexico_City",
    "iso:country":"MX",
    "wof:name":"El Patronato del Maguey (Santa Rosa)",
    "wof:placetype":"locality",
    "wof:population":490
},
  "geometry": {"coordinates":[-98.86884000000001,19.31041],"type":"Point"}
}