{
  "type": "Feature",
  "properties": {
    "gn:admin1_code":"21",
    "gn:admin2_code":"177.0",
    "gn:asciiname":"Jose Huerta (Seccion 17)",
    "gn:country_code":"MX",
    "gn:dem":1953,
    "gn:feature_class":"P",
    "gn:feature_code":"PPL",
    "gn:name":"Jos\u00e9 Huerta (Secci\u00f3n 17)",
    "gn:population":337,
    "gn:timezone":"America/Mexico_City",
    "iso:country":"MX",
    "name:und_x_variant":[
        "Jos\u00e9 Huerta (Secci\u00f3n 17)"
    ],
    "wof:name":"Jose Huerta (Seccion 17)",
    "wof:placetype":"locality",
    "wof:population":337
},
  "geometry": {"coordinates":[-97.67806,18.70306],"type":"Point"}
}