{
  "type": "Feature",
  "properties": {
    "gn:admin1_code":"20",
    "gn:admin2_code":"265.0",
    "gn:asciiname":"Las Piletas",
    "gn:country_code":"MX",
    "gn:dem":159,
    "gn:feature_class":"P",
    "gn:feature_code":"PPL",
    "gn:name":"Las Piletas",
    "gn:population":0,
    "gn:timezone":"America/Mexico_City",
    "iso:country":"MX",
    "wof:name":"Las Piletas",
    "wof:placetype":"locality"
},
  "geometry": {"coordinates":[-94.83333,16.63332999999999],"type":"Point"}
}