{
  "type": "Feature",
  "properties": {
    "gn:admin1_code":"29.0",
    "gn:admin2_code":"4.0",
    "gn:asciiname":"La Higuera",
    "gn:country_code":"MX",
    "gn:dem":2538,
    "gn:feature_class":"P",
    "gn:feature_code":"PPL",
    "gn:name":"La Higuera",
    "gn:population":0,
    "gn:timezone":"America/Mexico_City",
    "iso:country":"MX",
    "name:spa_x_preferred":[
        "La Higuera"
    ],
    "wof:name":"La Higuera",
    "wof:placetype":"locality"
},
  "geometry": {"coordinates":[-97.7912,19.37654],"type":"Point"}
}