{
  "type": "Feature",
  "properties": {
    "gn:admin1_code":"14",
    "gn:admin2_code":"106.0",
    "gn:asciiname":"Los Gonzalez",
    "gn:country_code":"MX",
    "gn:dem":786,
    "gn:feature_class":"P",
    "gn:feature_code":"PPL",
    "gn:name":"Los Gonz\u00e1lez",
    "gn:population":0,
    "gn:timezone":"America/Mexico_City",
    "iso:country":"MX",
    "name:spa_x_preferred":[
        "Los Gonz\u00e1lez"
    ],
    "wof:name":"Los Gonzalez",
    "wof:placetype":"locality"
},
  "geometry": {"coordinates":[-103.96902,19.73743],"type":"Point"}
}