{
  "type": "Feature",
  "properties": {
    "gn:admin1_code":"17",
    "gn:admin2_code":"14.0",
    "gn:asciiname":"Colonia Lomas del Calvario",
    "gn:country_code":"MX",
    "gn:dem":1029,
    "gn:feature_class":"P",
    "gn:feature_code":"PPL",
    "gn:name":"Colonia Lomas del Calvario",
    "gn:population":93,
    "gn:timezone":"America/Mexico_City",
    "iso:country":"MX",
    "wof:name":"Colonia Lomas del Calvario",
    "wof:placetype":"locality",
    "wof:population":93
},
  "geometry": {"coordinates":[-99.37194,18.72917],"type":"Point"}
}