{
  "type": "Feature",
  "properties": {
    "gn:admin1_code":"26",
    "gn:admin2_code":"30.0",
    "gn:asciiname":"El Chapulin",
    "gn:country_code":"MX",
    "gn:dem":61,
    "gn:feature_class":"P",
    "gn:feature_code":"PPL",
    "gn:name":"El Chapul\u00edn",
    "gn:population":0,
    "gn:timezone":"America/Hermosillo",
    "iso:country":"MX",
    "name:spa_x_preferred":[
        "El Chapul\u00edn"
    ],
    "wof:name":"El Chapulin",
    "wof:placetype":"locality"
},
  "geometry": {"coordinates":[-111.41249999999999,28.73972],"type":"Point"}
}