{
  "type": "Feature",
  "properties": {
    "gn:admin1_code":"10.0",
    "gn:admin2_code":"18.0",
    "gn:asciiname":"La Boquilla",
    "gn:country_code":"MX",
    "gn:dem":1530,
    "gn:feature_class":"P",
    "gn:feature_code":"PPL",
    "gn:name":"La Boquilla",
    "gn:population":0,
    "gn:timezone":"America/Monterrey",
    "iso:country":"MX",
    "name:spa_x_preferred":[
        "La Boquilla"
    ],
    "name:und_x_variant":[
        "Boquillas de Placer",
        "Boquilla",
        "Boquillas"
    ],
    "wof:name":"La Boquilla",
    "wof:placetype":"locality"
},
  "geometry": {"coordinates":[-105.16086,25.56026],"type":"Point"}
}