{
  "type": "Feature",
  "properties": {
    "gn:admin1_code":"21",
    "gn:admin2_code":"154.0",
    "gn:asciiname":"Barrio el Alto",
    "gn:country_code":"MX",
    "gn:dem":2119,
    "gn:feature_class":"P",
    "gn:feature_code":"PPL",
    "gn:name":"Barrio el Alto",
    "gn:population":85,
    "gn:timezone":"America/Mexico_City",
    "iso:country":"MX",
    "wof:name":"Barrio el Alto",
    "wof:placetype":"locality",
    "wof:population":85
},
  "geometry": {"coordinates":[-97.70106,18.85127],"type":"Point"}
}