{
  "type": "Feature",
  "properties": {
    "gn:admin1_code":"26",
    "gn:admin2_code":"61.0",
    "gn:asciiname":"El Mezquite",
    "gn:country_code":"MX",
    "gn:dem":388,
    "gn:feature_class":"P",
    "gn:feature_code":"PPL",
    "gn:name":"El Mezquite",
    "gn:population":0,
    "gn:timezone":"America/Hermosillo",
    "iso:country":"MX",
    "wof:name":"El Mezquite",
    "wof:placetype":"locality"
},
  "geometry": {"coordinates":[-109.72324999999999,28.8085],"type":"Point"}
}