{
  "type": "Feature",
  "properties": {
    "gn:admin1_code":"14",
    "gn:admin2_code":"73.0",
    "gn:asciiname":"Purisima",
    "gn:country_code":"MX",
    "gn:dem":1781,
    "gn:feature_class":"P",
    "gn:feature_code":"PPL",
    "gn:name":"Pur\u00edsima",
    "gn:population":171,
    "gn:timezone":"America/Mexico_City",
    "iso:country":"MX",
    "name:und_x_variant":[
        "Pur\u00edsima"
    ],
    "wof:name":"Purisima",
    "wof:placetype":"locality",
    "wof:population":171
},
  "geometry": {"coordinates":[-102.26833000000001,21.20833],"type":"Point"}
}