{
  "type": "Feature",
  "properties": {
    "gn:admin1_code":"16",
    "gn:admin2_code":"52.0",
    "gn:asciiname":"Los Llanos del Bejuco (El Bejuco)",
    "gn:country_code":"MX",
    "gn:dem":37,
    "gn:feature_class":"P",
    "gn:feature_code":"PPL",
    "gn:name":"Los Llanos del Bejuco (El Bejuco)",
    "gn:population":200,
    "gn:timezone":"America/Mexico_City",
    "iso:country":"MX",
    "wof:name":"Los Llanos del Bejuco (El Bejuco)",
    "wof:placetype":"locality",
    "wof:population":200
},
  "geometry": {"coordinates":[-102.51889,18.025],"type":"Point"}
}