{
  "type": "Feature",
  "properties": {
    "gn:admin1_code":"6.0",
    "gn:admin2_code":"15.0",
    "gn:asciiname":"La Cienega",
    "gn:country_code":"MX",
    "gn:dem":1252,
    "gn:feature_class":"P",
    "gn:feature_code":"PPL",
    "gn:name":"La Ci\u00e9nega",
    "gn:population":0,
    "gn:timezone":"America/Chihuahua",
    "iso:country":"MX",
    "name:ceb_x_preferred":[
        "La Cienega"
    ],
    "name:spa_x_preferred":[
        "La Ci\u00e9nega"
    ],
    "name:swe_x_preferred":[
        "La Cienega"
    ],
    "name:und_x_variant":[
        "Rancho La Ci\u00e9naga"
    ],
    "wof:name":"La Cienega",
    "wof:placetype":"locality"
},
  "geometry": {"coordinates":[-105.06366,29.40811],"type":"Point"}
}