{
  "type": "Feature",
  "properties": {
    "gn:admin1_code":"28.0",
    "gn:admin2_code":"19.0",
    "gn:asciiname":"La Casa de Teja",
    "gn:country_code":"MX",
    "gn:dem":667,
    "gn:feature_class":"P",
    "gn:feature_code":"PPL",
    "gn:name":"La Casa de Teja",
    "gn:population":0,
    "gn:timezone":"America/Monterrey",
    "iso:country":"MX",
    "name:spa_x_preferred":[
        "La Casa de Teja"
    ],
    "wof:name":"La Casa de Teja",
    "wof:placetype":"locality"
},
  "geometry": {"coordinates":[-98.45371,23.10229],"type":"Point"}
}