{
  "type": "Feature",
  "properties": {
    "gn:admin1_code":"12",
    "gn:admin2_code":"14",
    "gn:asciiname":"El Muelle",
    "gn:country_code":"MX",
    "gn:dem":8,
    "gn:feature_class":"P",
    "gn:feature_code":"PPL",
    "gn:name":"El Muelle",
    "gn:population":9,
    "gn:timezone":"America/Mexico_City",
    "iso:country":"MX",
    "wof:name":"El Muelle",
    "wof:placetype":"locality",
    "wof:population":9
},
  "geometry": {"coordinates":[-100.34471000000001,17.04176],"type":"Point"}
}