{
  "type": "Feature",
  "properties": {
    "gn:admin1_code":"24",
    "gn:admin2_code":"45.0",
    "gn:asciiname":"Polocote de Abajo (Polocotillo)",
    "gn:country_code":"MX",
    "gn:dem":1804,
    "gn:feature_class":"P",
    "gn:feature_code":"PPL",
    "gn:name":"Polocote de Abajo (Polocotillo)",
    "gn:population":71,
    "gn:timezone":"America/Mexico_City",
    "iso:country":"MX",
    "wof:name":"Polocote de Abajo (Polocotillo)",
    "wof:placetype":"locality",
    "wof:population":71
},
  "geometry": {"coordinates":[-101.08944,22.9575],"type":"Point"}
}