{
  "type": "Feature",
  "properties": {
    "gn:admin1_code":"15",
    "gn:admin2_code":"117.0",
    "gn:asciiname":"Velixtla",
    "gn:country_code":"MX",
    "gn:dem":1814,
    "gn:feature_class":"P",
    "gn:feature_code":"PPL",
    "gn:name":"Velixtla",
    "gn:population":82,
    "gn:timezone":"America/Mexico_City",
    "iso:country":"MX",
    "wof:name":"Velixtla",
    "wof:placetype":"locality",
    "wof:population":82
},
  "geometry": {"coordinates":[-99.85597,18.6222],"type":"Point"}
}