{
  "type": "Feature",
  "properties": {
    "gn:admin1_code":"5",
    "gn:admin2_code":"106.0",
    "gn:asciiname":"San Pedro Buenavista",
    "gn:country_code":"MX",
    "gn:dem":678,
    "gn:feature_class":"P",
    "gn:feature_code":"PPL",
    "gn:name":"San Pedro Buenavista",
    "gn:population":109,
    "gn:timezone":"America/Mexico_City",
    "iso:country":"MX",
    "wof:name":"San Pedro Buenavista",
    "wof:placetype":"locality",
    "wof:population":109
},
  "geometry": {"coordinates":[-92.46832999999999,16.31278],"type":"Point"}
}