{
  "type": "Feature",
  "properties": {
    "gn:admin1_code":"5",
    "gn:asciiname":"Los Corazones",
    "gn:country_code":"MX",
    "gn:dem":16,
    "gn:feature_class":"P",
    "gn:feature_code":"PPL",
    "gn:name":"Los Corazones",
    "gn:population":0,
    "gn:timezone":"America/Mexico_City",
    "iso:country":"MX",
    "name:spa_x_preferred":[
        "Los Corazones"
    ],
    "wof:name":"Los Corazones",
    "wof:placetype":"locality"
},
  "geometry": {"coordinates":[-94.07391,16.21026],"type":"Point"}
}