{
  "type": "Feature",
  "properties": {
    "gn:admin1_code":"5.0",
    "gn:admin2_code":"66.0",
    "gn:asciiname":"El Cafetal",
    "gn:country_code":"MX",
    "gn:dem":567,
    "gn:feature_class":"P",
    "gn:feature_code":"PPL",
    "gn:name":"El Cafetal",
    "gn:population":0,
    "gn:timezone":"America/Mexico_City",
    "iso:country":"MX",
    "name:spa_x_preferred":[
        "El Cafetal"
    ],
    "wof:name":"El Cafetal",
    "wof:placetype":"locality"
},
  "geometry": {"coordinates":[-92.45068999999999,17.04662],"type":"Point"}
}