{
  "type": "Feature",
  "properties": {
    "gn:admin1_code":"22.0",
    "gn:asciiname":"Puerto Torres",
    "gn:country_code":"MX",
    "gn:dem":3038,
    "gn:feature_class":"P",
    "gn:feature_code":"PPL",
    "gn:name":"Puerto Torres",
    "gn:population":0,
    "gn:timezone":"America/Mexico_City",
    "iso:country":"MX",
    "name:spa_x_preferred":[
        "Puerto Torres"
    ],
    "wof:name":"Puerto Torres",
    "wof:placetype":"locality"
},
  "geometry": {"coordinates":[-99.57204,20.78961],"type":"Point"}
}