{
  "type": "Feature",
  "properties": {
    "gn:admin1_code":"11.0",
    "gn:admin2_code":"22.0",
    "gn:asciiname":"Puerta del Monte del Conejo",
    "gn:country_code":"MX",
    "gn:dem":2204,
    "gn:feature_class":"P",
    "gn:feature_code":"PPL",
    "gn:name":"Puerta del Monte del Conejo",
    "gn:population":0,
    "gn:timezone":"America/Mexico_City",
    "iso:country":"MX",
    "name:spa_x_preferred":[
        "Puerta del Monte del Conejo"
    ],
    "wof:name":"Puerta del Monte del Conejo",
    "wof:placetype":"locality"
},
  "geometry": {"coordinates":[-101.48172,21.55428],"type":"Point"}
}