{
  "type": "Feature",
  "properties": {
    "gn:admin1_code":"7.0",
    "gn:admin2_code":"4.0",
    "gn:asciiname":"Ejido Chapultepec",
    "gn:country_code":"MX",
    "gn:dem":2220,
    "gn:feature_class":"P",
    "gn:feature_code":"PPL",
    "gn:name":"Ejido Chapultepec",
    "gn:population":0,
    "gn:timezone":"America/Monterrey",
    "iso:country":"MX",
    "wof:name":"Ejido Chapultepec",
    "wof:placetype":"locality"
},
  "geometry": {"coordinates":[-100.83333,25.23333],"type":"Point"}
}