{
  "type": "Feature",
  "properties": {
    "gn:admin1_code":"5",
    "gn:admin2_code":"89.0",
    "gn:asciiname":"Rincon del Bosque",
    "gn:country_code":"MX",
    "gn:dem":113,
    "gn:feature_class":"P",
    "gn:feature_code":"PPL",
    "gn:name":"Rinc\u00f3n del Bosque",
    "gn:population":301,
    "gn:timezone":"America/Mexico_City",
    "iso:country":"MX",
    "name:und_x_variant":[
        "Rinc\u00f3n del Bosque"
    ],
    "wof:name":"Rincon del Bosque",
    "wof:placetype":"locality",
    "wof:population":301
},
  "geometry": {"coordinates":[-92.27992,14.87225],"type":"Point"}
}