{
  "type": "Feature",
  "properties": {
    "gn:admin1_code":"20",
    "gn:admin2_code":"18.0",
    "gn:asciiname":"Santa Cruz Corunda",
    "gn:country_code":"MX",
    "gn:dem":2103,
    "gn:feature_class":"P",
    "gn:feature_code":"PPL",
    "gn:name":"Santa Cruz Corunda",
    "gn:population":0,
    "gn:timezone":"America/Mexico_City",
    "iso:country":"MX",
    "name:spa_x_preferred":[
        "Santa Cruz Corunda"
    ],
    "name:und_x_variant":[
        "Corunda"
    ],
    "wof:name":"Santa Cruz Corunda",
    "wof:placetype":"locality"
},
  "geometry": {"coordinates":[-97.4229,17.98446000000001],"type":"Point"}
}