{
  "type": "Feature",
  "properties": {
    "iso:country":"MX",
    "name:cat_x_preferred":[
        "Alameda"
    ],
    "name:ceb_x_preferred":[
        "Alameda"
    ],
    "name:deu_x_preferred":[
        "Alameda"
    ],
    "name:epo_x_preferred":[
        "Alameda"
    ],
    "name:fas_x_preferred":[
        "\u0622\u0644\u0627\u0645\u062f\u0627"
    ],
    "name:fra_x_preferred":[
        "Alameda"
    ],
    "name:glg_x_preferred":[
        "Alameda"
    ],
    "name:ita_x_preferred":[
        "Alameda"
    ],
    "name:jpn_x_preferred":[
        "\u30a2\u30e9\u30e1\u30c0"
    ],
    "name:kor_x_preferred":[
        "\uc568\ub7ec\ubbf8\ub2e4"
    ],
    "name:nld_x_preferred":[
        "Alameda"
    ],
    "name:pol_x_preferred":[
        "Alameda"
    ],
    "name:por_x_preferred":[
        "Alameda"
    ],
    "name:rus_x_preferred":[
        "\u0410\u043b\u0430\u043c\u0438\u0434\u0430"
    ],
    "name:spa_x_preferred":[
        "Alameda"
    ],
    "name:srp_x_preferred":[
        "\u0410\u043b\u0430\u043c\u0438\u0434\u0430"
    ],
    "name:swe_x_preferred":[
        "Alameda"
    ],
    "name:tur_x_preferred":[
        "Alameda"
    ],
    "name:ukr_x_preferred":[
        "\u0410\u043b\u0430\u043c\u0435\u0434\u0430"
    ],
    "qs_pg:aaroncc":"MX",
    "qs_pg:name":"Alameda",
    "qs_pg:name_adm0":"M\u00e9xico",
    "qs_pg:name_adm1":"Guanajuato",
    "qs_pg:photos":1,
    "qs_pg:photos_1k":1,
    "qs_pg:photos_9k":1,
    "qs_pg:photos_9r":1,
    "qs_pg:photos_all":1,
    "qs_pg:photos_sr":1,
    "qs_pg:pop_sr":0,
    "qs_pg:qs_pg_placetype":"neighbourhood",
    "qs_pg:qs_pg_placetype_gp":"Suburb",
    "qs_pg:woe_adm0":23424900,
    "woe:adm0_id":23424900,
    "woe:name_adm0":"M\u00e9xico",
    "woe:name_adm1":"Guanajuato",
    "woe:placetype":"Suburb",
    "wof:name":"Alameda",
    "wof:placetype":"neighbourhood"
},
  "geometry": {"coordinates":[-101.260385,21.018409],"type":"Point"}
}