{
  "type": "Feature",
  "properties": {
    "gn:admin1_code":"16",
    "gn:admin2_code":"26",
    "gn:asciiname":"Platanarillo",
    "gn:country_code":"MX",
    "gn:dem":448,
    "gn:feature_class":"P",
    "gn:feature_code":"PPL",
    "gn:name":"Platanarillo",
    "gn:population":21,
    "gn:timezone":"America/Mexico_City",
    "iso:country":"MX",
    "wof:name":"Platanarillo",
    "wof:placetype":"locality",
    "wof:population":21
},
  "geometry": {"coordinates":[-103.33056000000001,18.86306],"type":"Point"}
}