{
  "type": "Feature",
  "properties": {
    "gn:admin1_code":"6",
    "gn:admin2_code":"51.0",
    "gn:asciiname":"San Jose del Pinal",
    "gn:country_code":"MX",
    "gn:dem":1537,
    "gn:feature_class":"P",
    "gn:feature_code":"PPL",
    "gn:name":"San Jos\u00e9 del Pinal",
    "gn:population":0,
    "gn:timezone":"America/Chihuahua",
    "iso:country":"MX",
    "name:spa_x_preferred":[
        "San Jos\u00e9 del Pinal"
    ],
    "wof:name":"San Jose del Pinal",
    "wof:placetype":"locality"
},
  "geometry": {"coordinates":[-108.33041,28.01392],"type":"Point"}
}