{
  "type": "Feature",
  "properties": {
    "gn:admin1_code":"30",
    "gn:asciiname":"Ojo de Agua",
    "gn:country_code":"MX",
    "gn:dem":91,
    "gn:feature_class":"P",
    "gn:feature_code":"PPL",
    "gn:name":"Ojo de Agua",
    "gn:population":0,
    "gn:timezone":"America/Mexico_City",
    "iso:country":"MX",
    "name:spa_x_preferred":[
        "Ojo de Agua"
    ],
    "wof:name":"Ojo de Agua",
    "wof:placetype":"locality"
},
  "geometry": {"coordinates":[-96.48412999999999,18.44058],"type":"Point"}
}