{
  "type": "Feature",
  "properties": {
    "gn:admin1_code":"13",
    "gn:admin2_code":"18.0",
    "gn:asciiname":"Puerto del Amolar",
    "gn:country_code":"MX",
    "gn:dem":300,
    "gn:feature_class":"P",
    "gn:feature_code":"PPL",
    "gn:name":"Puerto del Amolar",
    "gn:population":32,
    "gn:timezone":"America/Mexico_City",
    "iso:country":"MX",
    "name:spa_x_preferred":[
        "El Amolar"
    ],
    "name:spa_x_variant":[
        "Puerto del Amolar"
    ],
    "wof:name":"Puerto del Amolar",
    "wof:placetype":"locality",
    "wof:population":32
},
  "geometry": {"coordinates":[-98.87873,21.11263],"type":"Point"}
}