{
  "type": "Feature",
  "properties": {
    "gn:admin1_code":"20.0",
    "gn:asciiname":"Loma Coyol",
    "gn:country_code":"MX",
    "gn:dem":638,
    "gn:feature_class":"P",
    "gn:feature_code":"PPL",
    "gn:name":"Loma Coyol",
    "gn:population":0,
    "gn:timezone":"America/Mexico_City",
    "iso:country":"MX",
    "name:spa_x_preferred":[
        "Loma Coyol"
    ],
    "wof:name":"Loma Coyol",
    "wof:placetype":"locality"
},
  "geometry": {"coordinates":[-96.59086000000001,17.85408],"type":"Point"}
}