{
  "type": "Feature",
  "properties": {
    "gn:admin1_code":"15.0",
    "gn:asciiname":"Colonia Aurora",
    "gn:country_code":"MX",
    "gn:dem":2862,
    "gn:feature_class":"P",
    "gn:feature_code":"PPL",
    "gn:name":"Colonia Aurora",
    "gn:population":0,
    "gn:timezone":"America/Mexico_City",
    "iso:country":"MX",
    "name:ceb_x_preferred":[
        "Colonia Aurora"
    ],
    "name:deu_x_preferred":[
        "Colonia Aurora"
    ],
    "name:por_x_preferred":[
        "Colonia Aurora"
    ],
    "name:spa_x_preferred":[
        "Colonia Aurora"
    ],
    "name:swe_x_preferred":[
        "Colonia Aurora"
    ],
    "wof:name":"Colonia Aurora",
    "wof:placetype":"locality"
},
  "geometry": {"coordinates":[-99.42317,19.55472],"type":"Point"}
}