{
  "type": "Feature",
  "properties": {
    "gn:admin1_code":"12",
    "gn:admin2_code":"41.0",
    "gn:asciiname":"Llano Pantanoso",
    "gn:country_code":"MX",
    "gn:dem":1471,
    "gn:feature_class":"P",
    "gn:feature_code":"PPL",
    "gn:name":"Llano Pantanoso",
    "gn:population":329,
    "gn:timezone":"America/Mexico_City",
    "iso:country":"MX",
    "wof:name":"Llano Pantanoso",
    "wof:placetype":"locality",
    "wof:population":329
},
  "geometry": {"coordinates":[-98.6884,17.2127],"type":"Point"}
}