{
  "type": "Feature",
  "properties": {
    "gn:admin1_code":"24",
    "gn:admin2_code":"12.0",
    "gn:asciiname":"Dhipak Mom",
    "gn:country_code":"MX",
    "gn:dem":276,
    "gn:feature_class":"P",
    "gn:feature_code":"PPL",
    "gn:name":"Dhipak Mom",
    "gn:population":6,
    "gn:timezone":"America/Mexico_City",
    "iso:country":"MX",
    "wof:name":"Dhipak Mom",
    "wof:placetype":"locality",
    "wof:population":6
},
  "geometry": {"coordinates":[-98.90667000000001,21.58806],"type":"Point"}
}