{
  "type": "Feature",
  "properties": {
    "gn:admin1_code":"12",
    "gn:admin2_code":"68.0",
    "gn:asciiname":"El Huicumo",
    "gn:country_code":"MX",
    "gn:dem":91,
    "gn:feature_class":"P",
    "gn:feature_code":"PPL",
    "gn:name":"El Huicumo",
    "gn:population":260,
    "gn:timezone":"America/Mexico_City",
    "iso:country":"MX",
    "wof:name":"El Huicumo",
    "wof:placetype":"locality",
    "wof:population":260
},
  "geometry": {"coordinates":[-102.1644,18.09215],"type":"Point"}
}