{
  "type": "Feature",
  "properties": {
    "gn:admin1_code":"6.0",
    "gn:admin2_code":"65.0",
    "gn:asciiname":"Huegorachi",
    "gn:country_code":"MX",
    "gn:dem":2052,
    "gn:feature_class":"P",
    "gn:feature_code":"PPL",
    "gn:name":"Huegorachi",
    "gn:population":0,
    "gn:timezone":"America/Chihuahua",
    "iso:country":"MX",
    "name:spa_x_preferred":[
        "Huegorachi"
    ],
    "wof:name":"Huegorachi",
    "wof:placetype":"locality"
},
  "geometry": {"coordinates":[-107.93419,27.51595],"type":"Point"}
}