{
  "type": "Feature",
  "properties": {
    "gn:admin1_code":"16.0",
    "gn:admin2_code":"15.0",
    "gn:asciiname":"La Granada de la Verdura",
    "gn:country_code":"MX",
    "gn:dem":1228,
    "gn:feature_class":"P",
    "gn:feature_code":"PPL",
    "gn:name":"La Granada de la Verdura",
    "gn:population":0,
    "gn:timezone":"America/Mexico_City",
    "iso:country":"MX",
    "name:spa_x_preferred":[
        "La Granada de la Verdura"
    ],
    "wof:name":"La Granada de la Verdura",
    "wof:placetype":"locality"
},
  "geometry": {"coordinates":[-103.15085999999999,18.49313],"type":"Point"}
}