{
  "type": "Feature",
  "properties": {
    "gn:admin1_code":"30.0",
    "gn:admin2_code":"121.0",
    "gn:asciiname":"El Sauce",
    "gn:country_code":"MX",
    "gn:dem":27,
    "gn:feature_class":"P",
    "gn:feature_code":"PPL",
    "gn:name":"El Sauce",
    "gn:population":2,
    "gn:timezone":"America/Mexico_City",
    "iso:country":"MX",
    "name:spa_x_preferred":[
        "El Sauce"
    ],
    "wof:name":"El Sauce",
    "wof:placetype":"locality",
    "wof:population":2
},
  "geometry": {"coordinates":[-97.83611000000001,21.53917],"type":"Point"}
}