{
  "type": "Feature",
  "properties": {
    "gn:admin1_code":"32",
    "gn:admin2_code":"56.0",
    "gn:asciiname":"Rancho San Juanito",
    "gn:country_code":"MX",
    "gn:dem":2252,
    "gn:feature_class":"P",
    "gn:feature_code":"PPL",
    "gn:name":"Rancho San Juanito",
    "gn:population":8,
    "gn:timezone":"America/Mexico_City",
    "iso:country":"MX",
    "wof:name":"Rancho San Juanito",
    "wof:placetype":"locality",
    "wof:population":8
},
  "geometry": {"coordinates":[-102.67278,22.70222],"type":"Point"}
}