{
  "type": "Feature",
  "properties": {
    "gn:admin1_code":"13",
    "gn:admin2_code":"49",
    "gn:asciiname":"Puerto Enebro",
    "gn:country_code":"MX",
    "gn:dem":623,
    "gn:feature_class":"P",
    "gn:feature_code":"PPL",
    "gn:name":"Puerto Enebro",
    "gn:population":36,
    "gn:timezone":"America/Mexico_City",
    "iso:country":"MX",
    "wof:name":"Puerto Enebro",
    "wof:placetype":"locality",
    "wof:population":36
},
  "geometry": {"coordinates":[-98.99276999999999,21.26072000000001],"type":"Point"}
}