{
  "type": "Feature",
  "properties": {
    "gn:admin1_code":"14",
    "gn:admin2_code":"44.0",
    "gn:asciiname":"La Playa (El Sobaco)",
    "gn:country_code":"MX",
    "gn:dem":1522,
    "gn:feature_class":"P",
    "gn:feature_code":"PPL",
    "gn:name":"La Playa (El Sobaco)",
    "gn:population":8,
    "gn:timezone":"America/Mexico_City",
    "iso:country":"MX",
    "wof:name":"La Playa (El Sobaco)",
    "wof:placetype":"locality",
    "wof:population":8
},
  "geometry": {"coordinates":[-103.17778,20.41944],"type":"Point"}
}