{
  "type": "Feature",
  "properties": {
    "gn:admin1_code":"6.0",
    "gn:admin2_code":"15.0",
    "gn:asciiname":"El Escondido",
    "gn:country_code":"MX",
    "gn:dem":1405,
    "gn:feature_class":"P",
    "gn:feature_code":"PPL",
    "gn:name":"El Escondido",
    "gn:population":4,
    "gn:timezone":"America/Chihuahua",
    "iso:country":"MX",
    "name:und_x_variant":[
        "Rancho El Escondido",
        "El Escondido"
    ],
    "wof:name":"El Escondido",
    "wof:placetype":"locality",
    "wof:population":4
},
  "geometry": {"coordinates":[-105.53643999999998,29.92054000000001],"type":"Point"}
}