{
  "type": "Feature",
  "properties": {
    "gn:admin1_code":"30",
    "gn:admin2_code":"3.0",
    "gn:asciiname":"Hermanos Nieves",
    "gn:country_code":"MX",
    "gn:dem":63,
    "gn:feature_class":"P",
    "gn:feature_code":"PPL",
    "gn:name":"Hermanos Nieves",
    "gn:population":5,
    "gn:timezone":"America/Mexico_City",
    "iso:country":"MX",
    "wof:name":"Hermanos Nieves",
    "wof:placetype":"locality",
    "wof:population":5
},
  "geometry": {"coordinates":[-95.12278000000001,18.07556],"type":"Point"}
}