{
  "type": "Feature",
  "properties": {
    "gn:admin1_code":"32",
    "gn:admin2_code":"14.0",
    "gn:asciiname":"Norias",
    "gn:country_code":"MX",
    "gn:dem":1809,
    "gn:feature_class":"P",
    "gn:feature_code":"PPL",
    "gn:name":"Norias",
    "gn:population":0,
    "gn:timezone":"America/Mexico_City",
    "iso:country":"MX",
    "name:spa_x_preferred":[
        "Norias"
    ],
    "name:und_x_variant":[
        "Noria",
        "La Noria"
    ],
    "wof:name":"Norias",
    "wof:placetype":"locality"
},
  "geometry": {"coordinates":[-102.6981,24.29689],"type":"Point"}
}