{
  "type": "Feature",
  "properties": {
    "gn:admin1_code":"2",
    "gn:admin2_code":"4.0",
    "gn:asciiname":"Antorcha Campesina",
    "gn:country_code":"MX",
    "gn:dem":153,
    "gn:feature_class":"P",
    "gn:feature_code":"PPL",
    "gn:name":"Antorcha Campesina",
    "gn:population":480,
    "gn:timezone":"America/Tijuana",
    "iso:country":"MX",
    "wof:name":"Antorcha Campesina",
    "wof:placetype":"locality",
    "wof:population":480
},
  "geometry": {"coordinates":[-117.08806,32.47528],"type":"Point"}
}