{
  "type": "Feature",
  "properties": {
    "gn:admin1_code":"2",
    "gn:admin2_code":"1.0",
    "gn:asciiname":"Los Frenos",
    "gn:country_code":"MX",
    "gn:dem":364,
    "gn:feature_class":"P",
    "gn:feature_code":"PPL",
    "gn:name":"Los Frenos",
    "gn:population":4,
    "gn:timezone":"America/Tijuana",
    "iso:country":"MX",
    "wof:name":"Los Frenos",
    "wof:placetype":"locality",
    "wof:population":4
},
  "geometry": {"coordinates":[-116.50778,31.91083],"type":"Point"}
}