{
  "type": "Feature",
  "properties": {
    "gn:admin1_code":"28.0",
    "gn:admin2_code":"22.0",
    "gn:asciiname":"Rincon El Toro",
    "gn:country_code":"MX",
    "gn:dem":10,
    "gn:feature_class":"P",
    "gn:feature_code":"PPL",
    "gn:name":"Rinc\u00f3n El Toro",
    "gn:population":0,
    "gn:timezone":"America/Matamoros",
    "iso:country":"MX",
    "name:spa_x_preferred":[
        "Rinc\u00f3n El Toro"
    ],
    "wof:name":"Rincon El Toro",
    "wof:placetype":"locality"
},
  "geometry": {"coordinates":[-97.67964000000001,25.51875],"type":"Point"}
}