{
  "type": "Feature",
  "properties": {
    "gn:admin1_code":"11",
    "gn:admin2_code":"4",
    "gn:asciiname":"La Via",
    "gn:country_code":"MX",
    "gn:dem":2051,
    "gn:feature_class":"P",
    "gn:feature_code":"PPL",
    "gn:name":"La V\u00eda",
    "gn:population":24,
    "gn:timezone":"America/Mexico_City",
    "iso:country":"MX",
    "name:und_x_variant":[
        "La V\u00eda"
    ],
    "wof:name":"La Via",
    "wof:placetype":"locality",
    "wof:population":24
},
  "geometry": {"coordinates":[-100.51889,20.35694],"type":"Point"}
}