{
  "type": "Feature",
  "properties": {
    "gn:admin1_code":"10",
    "gn:admin2_code":"2.0",
    "gn:asciiname":"La Yerbabuena",
    "gn:country_code":"MX",
    "gn:dem":1454,
    "gn:feature_class":"P",
    "gn:feature_code":"PPL",
    "gn:name":"La Yerbabuena",
    "gn:population":0,
    "gn:timezone":"America/Monterrey",
    "iso:country":"MX",
    "name:spa_x_preferred":[
        "La Yerbabuena"
    ],
    "name:und_x_variant":[
        "Yerbabuena"
    ],
    "wof:name":"La Yerbabuena",
    "wof:placetype":"locality"
},
  "geometry": {"coordinates":[-106.53424,25.11604],"type":"Point"}
}