{
  "type": "Feature",
  "properties": {
    "gn:admin1_code":"11",
    "gn:admin2_code":"1.0",
    "gn:asciiname":"Colonia Solidaridad (Colonia Morelos)",
    "gn:country_code":"MX",
    "gn:dem":1694,
    "gn:feature_class":"P",
    "gn:feature_code":"PPL",
    "gn:name":"Colonia Solidaridad (Colonia Morelos)",
    "gn:population":242,
    "gn:timezone":"America/Mexico_City",
    "iso:country":"MX",
    "wof:name":"Colonia Solidaridad (Colonia Morelos)",
    "wof:placetype":"locality",
    "wof:population":242
},
  "geometry": {"coordinates":[-101.55083,20.45],"type":"Point"}
}