{
  "type": "Feature",
  "properties": {
    "gn:admin1_code":"22",
    "gn:admin2_code":"4.0",
    "gn:asciiname":"San Juan de Enramadas",
    "gn:country_code":"MX",
    "gn:dem":2090,
    "gn:feature_class":"P",
    "gn:feature_code":"PPL",
    "gn:name":"San Juan de Enramadas",
    "gn:population":138,
    "gn:timezone":"America/Mexico_City",
    "iso:country":"MX",
    "wof:name":"San Juan de Enramadas",
    "wof:placetype":"locality",
    "wof:population":138
},
  "geometry": {"coordinates":[-99.51917,20.92389],"type":"Point"}
}