{
  "type": "Feature",
  "properties": {
    "gn:admin1_code":"10",
    "gn:admin2_code":"14",
    "gn:asciiname":"Los Sauces",
    "gn:country_code":"MX",
    "gn:dem":2387,
    "gn:feature_class":"P",
    "gn:feature_code":"PPL",
    "gn:name":"Los Sauces",
    "gn:population":29,
    "gn:timezone":"America/Monterrey",
    "iso:country":"MX",
    "wof:name":"Los Sauces",
    "wof:placetype":"locality",
    "wof:population":29
},
  "geometry": {"coordinates":[-104.66247,22.96836],"type":"Point"}
}