{
  "type": "Feature",
  "properties": {
    "gn:admin1_code":"6",
    "gn:admin2_code":"27.0",
    "gn:asciiname":"Chipora",
    "gn:country_code":"MX",
    "gn:dem":2232,
    "gn:feature_class":"P",
    "gn:feature_code":"PPL",
    "gn:name":"Chipora",
    "gn:population":12,
    "gn:timezone":"America/Chihuahua",
    "iso:country":"MX",
    "name:spa_x_preferred":[
        "Chipora"
    ],
    "wof:name":"Chipora",
    "wof:placetype":"locality",
    "wof:population":12
},
  "geometry": {"coordinates":[-107.41597,26.80669],"type":"Point"}
}