{
  "type": "Feature",
  "properties": {
    "gn:admin1_code":"12",
    "gn:admin2_code":"45.0",
    "gn:asciiname":"El Progreso (Chupandillo)",
    "gn:country_code":"MX",
    "gn:dem":1513,
    "gn:feature_class":"P",
    "gn:feature_code":"PPL",
    "gn:name":"El Progreso (Chupandillo)",
    "gn:population":70,
    "gn:timezone":"America/Mexico_City",
    "iso:country":"MX",
    "wof:name":"El Progreso (Chupandillo)",
    "wof:placetype":"locality",
    "wof:population":70
},
  "geometry": {"coordinates":[-98.71167,17.81022999999999],"type":"Point"}
}