{
  "type": "Feature",
  "properties": {
    "gn:admin1_code":"5",
    "gn:admin2_code":"59.0",
    "gn:asciiname":"Zaragoza",
    "gn:country_code":"MX",
    "gn:dem":1117,
    "gn:feature_class":"P",
    "gn:feature_code":"PPL",
    "gn:name":"Zaragoza",
    "gn:population":0,
    "gn:timezone":"America/Mexico_City",
    "iso:country":"MX",
    "name:spa_x_preferred":[
        "Zaragoza"
    ],
    "wof:name":"Zaragoza",
    "wof:placetype":"locality"
},
  "geometry": {"coordinates":[-91.64033000000001,17.00906],"type":"Point"}
}