{
  "type": "Feature",
  "properties": {
    "gn:admin1_code":"10",
    "gn:admin2_code":"5.0",
    "gn:asciiname":"Pradera las Gueeras",
    "gn:country_code":"MX",
    "gn:dem":1863,
    "gn:feature_class":"P",
    "gn:feature_code":"PPL",
    "gn:name":"Pradera las G\u00fceras",
    "gn:population":5,
    "gn:timezone":"America/Monterrey",
    "iso:country":"MX",
    "name:und_x_variant":[
        "Pradera las G\u00fceras"
    ],
    "wof:name":"Pradera las Gueeras",
    "wof:placetype":"locality",
    "wof:population":5
},
  "geometry": {"coordinates":[-104.58085,24.06502],"type":"Point"}
}