{
  "type": "Feature",
  "properties": {
    "gn:admin1_code":"30",
    "gn:admin2_code":"145.0",
    "gn:asciiname":"El Trapiche",
    "gn:country_code":"MX",
    "gn:dem":73,
    "gn:feature_class":"P",
    "gn:feature_code":"PPL",
    "gn:name":"El Trapiche",
    "gn:population":7,
    "gn:timezone":"America/Mexico_City",
    "iso:country":"MX",
    "wof:name":"El Trapiche",
    "wof:placetype":"locality",
    "wof:population":7
},
  "geometry": {"coordinates":[-94.88861,17.97306],"type":"Point"}
}