{
  "type": "Feature",
  "properties": {
    "gn:admin1_code":"14",
    "gn:admin2_code":"28.0",
    "gn:asciiname":"Suelos Duros",
    "gn:country_code":"MX",
    "gn:dem":1675,
    "gn:feature_class":"P",
    "gn:feature_code":"PPL",
    "gn:name":"Suelos Duros",
    "gn:population":0,
    "gn:timezone":"America/Mexico_City",
    "iso:country":"MX",
    "wof:name":"Suelos Duros",
    "wof:placetype":"locality"
},
  "geometry": {"coordinates":[-104.57584,20.17066],"type":"Point"}
}