{
  "type": "Feature",
  "properties": {
    "gn:admin1_code":"5",
    "gn:admin2_code":"107.0",
    "gn:asciiname":"Primero de Mayo",
    "gn:country_code":"MX",
    "gn:dem":567,
    "gn:feature_class":"P",
    "gn:feature_code":"PPL",
    "gn:name":"Primero de Mayo",
    "gn:population":0,
    "gn:timezone":"America/Mexico_City",
    "iso:country":"MX",
    "name:spa_x_preferred":[
        "Primero de Mayo"
    ],
    "wof:name":"Primero de Mayo",
    "wof:placetype":"locality"
},
  "geometry": {"coordinates":[-93.11551,16.15156],"type":"Point"}
}