{
  "type": "Feature",
  "properties": {
    "gn:admin1_code":"32.0",
    "gn:admin2_code":"14.0",
    "gn:asciiname":"Plan la Cienega",
    "gn:country_code":"MX",
    "gn:dem":1994,
    "gn:feature_class":"P",
    "gn:feature_code":"PPL",
    "gn:name":"Plan la Ci\u00e9nega",
    "gn:population":0,
    "gn:timezone":"America/Mexico_City",
    "iso:country":"MX",
    "name:spa_x_preferred":[
        "Plan la Ci\u00e9nega"
    ],
    "wof:name":"Plan la Cienega",
    "wof:placetype":"locality"
},
  "geometry": {"coordinates":[-103.06934,24.03901],"type":"Point"}
}