{
  "type": "Feature",
  "properties": {
    "gn:admin1_code":"13",
    "gn:admin2_code":"53",
    "gn:asciiname":"Camarones",
    "gn:country_code":"MX",
    "gn:dem":1261,
    "gn:feature_class":"P",
    "gn:feature_code":"PPL",
    "gn:name":"Camarones",
    "gn:population":11,
    "gn:timezone":"America/Mexico_City",
    "iso:country":"MX",
    "wof:name":"Camarones",
    "wof:placetype":"locality",
    "wof:population":11
},
  "geometry": {"coordinates":[-98.14679,20.44849],"type":"Point"}
}