{
  "type": "Feature",
  "properties": {
    "gn:admin1_code":"16",
    "gn:admin2_code":"15",
    "gn:asciiname":"La Sidra",
    "gn:country_code":"MX",
    "gn:dem":1515,
    "gn:feature_class":"P",
    "gn:feature_code":"PPL",
    "gn:name":"La Sidra",
    "gn:population":10,
    "gn:timezone":"America/Mexico_City",
    "iso:country":"MX",
    "name:ast_x_preferred":[
        "La Sidra"
    ],
    "name:glg_x_preferred":[
        "La Sidra"
    ],
    "wof:name":"La Sidra",
    "wof:placetype":"locality",
    "wof:population":10
},
  "geometry": {"coordinates":[-103.25306,18.80944],"type":"Point"}
}