{
  "type": "Feature",
  "properties": {
    "gn:admin1_code":"6.0",
    "gn:admin2_code":"30.0",
    "gn:asciiname":"Serachi",
    "gn:country_code":"MX",
    "gn:dem":1786,
    "gn:feature_class":"P",
    "gn:feature_code":"PPL",
    "gn:name":"Serachi",
    "gn:population":0,
    "gn:timezone":"America/Chihuahua",
    "iso:country":"MX",
    "name:spa_x_preferred":[
        "Serachi"
    ],
    "wof:name":"Serachi",
    "wof:placetype":"locality"
},
  "geometry": {"coordinates":[-108.16897,27.52995],"type":"Point"}
}