{
  "type": "Feature",
  "properties": {
    "gn:admin1_code":"30",
    "gn:admin2_code":"152.0",
    "gn:asciiname":"La Ceiba (Jicotes)",
    "gn:country_code":"MX",
    "gn:dem":8,
    "gn:feature_class":"P",
    "gn:feature_code":"PPL",
    "gn:name":"La Ceiba (Jicotes)",
    "gn:population":5,
    "gn:timezone":"America/Mexico_City",
    "iso:country":"MX",
    "wof:name":"La Ceiba (Jicotes)",
    "wof:placetype":"locality",
    "wof:population":5
},
  "geometry": {"coordinates":[-98.01056,21.98],"type":"Point"}
}