{
  "type": "Feature",
  "properties": {
    "gn:admin1_code":"20",
    "gn:admin2_code":"159",
    "gn:asciiname":"Rio Banco",
    "gn:country_code":"MX",
    "gn:dem":2148,
    "gn:feature_class":"P",
    "gn:feature_code":"PPL",
    "gn:name":"R\u00edo Banco",
    "gn:population":33,
    "gn:timezone":"America/Mexico_City",
    "iso:country":"MX",
    "name:und_x_variant":[
        "R\u00edo Banco"
    ],
    "wof:name":"Rio Banco",
    "wof:placetype":"locality",
    "wof:population":33
},
  "geometry": {"coordinates":[-96.91694,16.25361],"type":"Point"}
}