{
  "type": "Feature",
  "properties": {
    "gn:admin1_code":"16",
    "gn:admin2_code":"49.0",
    "gn:asciiname":"La Jagueiquera",
    "gn:country_code":"MX",
    "gn:dem":1550,
    "gn:feature_class":"P",
    "gn:feature_code":"PPL",
    "gn:name":"La Jag\u00fciquera",
    "gn:population":5,
    "gn:timezone":"America/Mexico_City",
    "iso:country":"MX",
    "name:und_x_variant":[
        "La Jag\u00fciquera"
    ],
    "wof:name":"La Jagueiquera",
    "wof:placetype":"locality",
    "wof:population":5
},
  "geometry": {"coordinates":[-101.31139,19.27556],"type":"Point"}
}