{
  "type": "Feature",
  "properties": {
    "gn:admin1_code":"26",
    "gn:admin2_code":"18.0",
    "gn:asciiname":"Zona de Granjas (Granjas Mica)",
    "gn:country_code":"MX",
    "gn:dem":62,
    "gn:feature_class":"P",
    "gn:feature_code":"PPL",
    "gn:name":"Zona de Granjas (Granjas Mica)",
    "gn:population":512,
    "gn:timezone":"America/Hermosillo",
    "iso:country":"MX",
    "wof:name":"Zona de Granjas (Granjas Mica)",
    "wof:placetype":"locality",
    "wof:population":512
},
  "geometry": {"coordinates":[-109.86333,27.52333],"type":"Point"}
}