{
  "type": "Feature",
  "properties": {
    "gn:admin1_code":"11.0",
    "gn:admin2_code":"15.0",
    "gn:asciiname":"Presa del Gogorron",
    "gn:country_code":"MX",
    "gn:dem":1971,
    "gn:feature_class":"P",
    "gn:feature_code":"PPL",
    "gn:name":"Presa del Gogorr\u00f3n",
    "gn:population":0,
    "gn:timezone":"America/Mexico_City",
    "iso:country":"MX",
    "name:spa_x_preferred":[
        "Presa del Gogorr\u00f3n"
    ],
    "wof:name":"Presa del Gogorron",
    "wof:placetype":"locality"
},
  "geometry": {"coordinates":[-101.29801999999999,21.00999],"type":"Point"}
}