{
  "type": "Feature",
  "properties": {
    "gn:admin1_code":"16.0",
    "gn:admin2_code":"8.0",
    "gn:asciiname":"Los Chochos",
    "gn:country_code":"MX",
    "gn:dem":868,
    "gn:feature_class":"P",
    "gn:feature_code":"PPL",
    "gn:name":"Los Chochos",
    "gn:population":0,
    "gn:timezone":"America/Mexico_City",
    "iso:country":"MX",
    "name:spa_x_preferred":[
        "Los Chochos"
    ],
    "wof:name":"Los Chochos",
    "wof:placetype":"locality"
},
  "geometry": {"coordinates":[-103.00167,18.31159],"type":"Point"}
}