{
  "type": "Feature",
  "properties": {
    "gn:admin1_code":"5.0",
    "gn:admin2_code":"19.0",
    "gn:asciiname":"Santa Rita",
    "gn:country_code":"MX",
    "gn:dem":2352,
    "gn:feature_class":"P",
    "gn:feature_code":"PPL",
    "gn:name":"Santa Rita",
    "gn:population":0,
    "gn:timezone":"America/Mexico_City",
    "iso:country":"MX",
    "name:spa_x_preferred":[
        "Santa Rita"
    ],
    "wof:name":"Santa Rita",
    "wof:placetype":"locality"
},
  "geometry": {"coordinates":[-92.26499,16.46094],"type":"Point"}
}