{
  "type": "Feature",
  "properties": {
    "gn:admin1_code":"26",
    "gn:admin2_code":"21.0",
    "gn:asciiname":"El Tileno",
    "gn:country_code":"MX",
    "gn:dem":470,
    "gn:feature_class":"P",
    "gn:feature_code":"PPL",
    "gn:name":"El Tile\u00f1o",
    "gn:population":0,
    "gn:timezone":"America/Hermosillo",
    "iso:country":"MX",
    "name:spa_x_preferred":[
        "El Tile\u00f1o"
    ],
    "wof:name":"El Tileno",
    "wof:placetype":"locality"
},
  "geometry": {"coordinates":[-110.22778,28.91222],"type":"Point"}
}