{
  "type": "Feature",
  "properties": {
    "gn:admin1_code":"14",
    "gn:admin2_code":"27.0",
    "gn:asciiname":"El Trompezon",
    "gn:country_code":"MX",
    "gn:dem":1222,
    "gn:feature_class":"P",
    "gn:feature_code":"PPL",
    "gn:name":"El Trompez\u00f3n",
    "gn:population":7,
    "gn:timezone":"America/Mexico_City",
    "iso:country":"MX",
    "name:und_x_variant":[
        "El Trompez\u00f3n"
    ],
    "wof:name":"El Trompezon",
    "wof:placetype":"locality",
    "wof:population":7
},
  "geometry": {"coordinates":[-104.15611,19.43667],"type":"Point"}
}