{
  "type": "Feature",
  "properties": {
    "gn:admin1_code":"20.0",
    "gn:asciiname":"Agua Fria",
    "gn:country_code":"MX",
    "gn:dem":3258,
    "gn:feature_class":"P",
    "gn:feature_code":"PPL",
    "gn:name":"Agua Fr\u00eda",
    "gn:population":0,
    "gn:timezone":"America/Mexico_City",
    "iso:country":"MX",
    "name:ceb_x_preferred":[
        "Agua Fria"
    ],
    "name:deu_x_preferred":[
        "Agua Fria"
    ],
    "name:spa_x_preferred":[
        "Agua Fr\u00eda"
    ],
    "name:swe_x_preferred":[
        "Agua Fria"
    ],
    "wof:name":"Agua Fria",
    "wof:placetype":"locality"
},
  "geometry": {"coordinates":[-96.24102000000001,16.1937],"type":"Point"}
}