{
  "type": "Feature",
  "properties": {
    "gn:admin1_code":"14",
    "gn:admin2_code":"73.0",
    "gn:asciiname":"El Gallo",
    "gn:country_code":"MX",
    "gn:dem":1829,
    "gn:feature_class":"P",
    "gn:feature_code":"PPL",
    "gn:name":"El Gallo",
    "gn:population":8,
    "gn:timezone":"America/Mexico_City",
    "iso:country":"MX",
    "wof:name":"El Gallo",
    "wof:placetype":"locality",
    "wof:population":8
},
  "geometry": {"coordinates":[-102.16028,21.20444],"type":"Point"}
}