{
  "type": "Feature",
  "properties": {
    "gn:admin1_code":"10",
    "gn:admin2_code":"27",
    "gn:asciiname":"El Floreno",
    "gn:country_code":"MX",
    "gn:dem":1750,
    "gn:feature_class":"P",
    "gn:feature_code":"PPL",
    "gn:name":"El Flore\u00f1o",
    "gn:population":35,
    "gn:timezone":"America/Mexico_City",
    "iso:country":"MX",
    "name:und_x_variant":[
        "El Flore\u00f1o"
    ],
    "wof:name":"El Floreno",
    "wof:placetype":"locality",
    "wof:population":35
},
  "geometry": {"coordinates":[-102.49272000000001,24.43716],"type":"Point"}
}