{
  "type": "Feature",
  "properties": {
    "gn:admin1_code":"30",
    "gn:admin2_code":"42.0",
    "gn:asciiname":"La Piedrilla",
    "gn:country_code":"MX",
    "gn:dem":370,
    "gn:feature_class":"P",
    "gn:feature_code":"PPL",
    "gn:name":"La Piedrilla",
    "gn:population":193,
    "gn:timezone":"America/Mexico_City",
    "iso:country":"MX",
    "wof:name":"La Piedrilla",
    "wof:placetype":"locality",
    "wof:population":193
},
  "geometry": {"coordinates":[-96.76861,19.92528],"type":"Point"}
}