{
  "type": "Feature",
  "properties": {
    "gn:admin1_code":"6",
    "gn:admin2_code":"26.0",
    "gn:asciiname":"Rancho Portillo (Valentin Gomez Farias)",
    "gn:cc2":"MX",
    "gn:country_code":"MX",
    "gn:dem":1686,
    "gn:feature_class":"P",
    "gn:feature_code":"PPL",
    "gn:name":"Rancho Portillo (Valent\u00edn G\u00f3mez Far\u00edas)",
    "gn:population":106,
    "gn:timezone":"America/Chihuahua",
    "iso:country":"MX",
    "name:und_x_variant":[
        "Los Portillos",
        "Portillo"
    ],
    "wof:name":"Rancho Portillo (Valentin Gomez Farias)",
    "wof:placetype":"locality",
    "wof:population":106
},
  "geometry": {"coordinates":[-106.59354,28.22686],"type":"Point"}
}