{
  "type": "Feature",
  "properties": {
    "gn:admin1_code":"19",
    "gn:admin2_code":"38.0",
    "gn:asciiname":"Piedra de Lumbre",
    "gn:country_code":"MX",
    "gn:dem":583,
    "gn:feature_class":"P",
    "gn:feature_code":"PPL",
    "gn:name":"Piedra de Lumbre",
    "gn:population":0,
    "gn:timezone":"America/Monterrey",
    "iso:country":"MX",
    "name:spa_x_preferred":[
        "Piedra de Lumbre"
    ],
    "name:und_x_variant":[
        "Rancho Piedras de Lumbre"
    ],
    "wof:name":"Piedra de Lumbre",
    "wof:placetype":"locality"
},
  "geometry": {"coordinates":[-99.93537000000001,25.08836],"type":"Point"}
}