{
  "type": "Feature",
  "properties": {
    "gn:admin1_code":"30",
    "gn:admin2_code":"126.0",
    "gn:asciiname":"El Juile",
    "gn:country_code":"MX",
    "gn:dem":22,
    "gn:feature_class":"P",
    "gn:feature_code":"PPL",
    "gn:name":"El Juile",
    "gn:population":61,
    "gn:timezone":"America/Mexico_City",
    "iso:country":"MX",
    "wof:name":"El Juile",
    "wof:placetype":"locality",
    "wof:population":61
},
  "geometry": {"coordinates":[-96.40361,19.32167],"type":"Point"}
}