{
  "type": "Feature",
  "properties": {
    "gn:admin1_code":"12",
    "gn:admin2_code":"28",
    "gn:asciiname":"El Paraiso de Tepila (El Paraiso)",
    "gn:country_code":"MX",
    "gn:dem":2038,
    "gn:feature_class":"P",
    "gn:feature_code":"PPL",
    "gn:name":"El Para\u00edso de Tepila (El Para\u00edso)",
    "gn:population":47,
    "gn:timezone":"America/Mexico_City",
    "iso:country":"MX",
    "name:und_x_variant":[
        "El Para\u00edso de Tepila (El Para\u00edso)"
    ],
    "wof:name":"El Paraiso de Tepila (El Paraiso)",
    "wof:placetype":"locality",
    "wof:population":47
},
  "geometry": {"coordinates":[-99.06589,17.48229],"type":"Point"}
}