{
  "type": "Feature",
  "properties": {
    "gn:admin1_code":"24",
    "gn:admin2_code":"23.0",
    "gn:asciiname":"El Quelitalillo",
    "gn:country_code":"MX",
    "gn:dem":1060,
    "gn:feature_class":"P",
    "gn:feature_code":"PPL",
    "gn:name":"El Quelitalillo",
    "gn:population":0,
    "gn:timezone":"America/Mexico_City",
    "iso:country":"MX",
    "name:spa_x_preferred":[
        "El Quelitalillo"
    ],
    "wof:name":"El Quelitalillo",
    "wof:placetype":"locality"
},
  "geometry": {"coordinates":[-99.67818,21.81917],"type":"Point"}
}