{
  "type": "Feature",
  "properties": {
    "gn:country":"MX",
    "gn:fcode":"PPL",
    "gn:population":0,
    "iso:country":"MX",
    "name:spa_x_preferred":[
        "Capulines"
    ],
    "qs_pg:aaroncc":"MX",
    "qs_pg:gn_country":"MX",
    "qs_pg:gn_fcode":"PPL",
    "qs_pg:gn_pop":0,
    "qs_pg:name":"Capulines",
    "qs_pg:name_adm0":"M\u00e9xico",
    "qs_pg:name_adm1":"San Luis Potosi",
    "qs_pg:photos":27,
    "qs_pg:photos_1k":5,
    "qs_pg:photos_9k":1,
    "qs_pg:photos_9r":2,
    "qs_pg:photos_all":27,
    "qs_pg:photos_sr":2,
    "qs_pg:pop_sr":0,
    "qs_pg:qs_pg_placetype":"locality",
    "qs_pg:qs_pg_placetype_gp":"Town",
    "qs_pg:woe_adm0":23424900,
    "woe:adm0_id":23424900,
    "woe:name_adm0":"M\u00e9xico",
    "woe:name_adm1":"San Luis Potosi",
    "woe:placetype":"Town",
    "wof:name":"Capulines",
    "wof:placetype":"locality"
},
  "geometry": {"coordinates":[-101.05197,22.17528],"type":"Point"}
}