{
  "type": "Feature",
  "properties": {
    "gn:admin1_code":"15.0",
    "gn:admin2_code":"7.0",
    "gn:asciiname":"Sabana Taborda Segunda Seccion",
    "gn:country_code":"MX",
    "gn:dem":2647,
    "gn:feature_class":"P",
    "gn:feature_code":"PPL",
    "gn:name":"S\u00e1bana Taborda Segunda Secci\u00f3n",
    "gn:population":0,
    "gn:timezone":"America/Mexico_City",
    "iso:country":"MX",
    "name:spa_x_preferred":[
        "S\u00e1bana Taborda Segunda Secci\u00f3n"
    ],
    "wof:name":"Sabana Taborda Segunda Seccion",
    "wof:placetype":"locality"
},
  "geometry": {"coordinates":[-100.02043999999999,19.30004],"type":"Point"}
}