{
  "type": "Feature",
  "properties": {
    "gn:admin1_code":"7",
    "gn:admin2_code":"3.0",
    "gn:asciiname":"Elizondo [Triturados]",
    "gn:country_code":"MX",
    "gn:dem":405,
    "gn:feature_class":"P",
    "gn:feature_code":"PPL",
    "gn:name":"Elizondo [Triturados]",
    "gn:population":7,
    "gn:timezone":"America/Monterrey",
    "iso:country":"MX",
    "wof:name":"Elizondo [Triturados]",
    "wof:placetype":"locality",
    "wof:population":7
},
  "geometry": {"coordinates":[-100.89815,28.31858],"type":"Point"}
}