{
  "type": "Feature",
  "properties": {
    "gn:admin1_code":"28.0",
    "gn:admin2_code":"19.0",
    "gn:asciiname":"Hermen Egildo Galeana",
    "gn:country_code":"MX",
    "gn:dem":299,
    "gn:feature_class":"P",
    "gn:feature_code":"PPL",
    "gn:name":"Hermen Egildo Galeana",
    "gn:population":0,
    "gn:timezone":"America/Monterrey",
    "iso:country":"MX",
    "name:spa_x_preferred":[
        "Hermen Egildo Galeana"
    ],
    "wof:name":"Hermen Egildo Galeana",
    "wof:placetype":"locality"
},
  "geometry": {"coordinates":[-99.10316,23.20728],"type":"Point"}
}