{
  "type": "Feature",
  "properties": {
    "gn:admin1_code":"5",
    "gn:admin2_code":"69.0",
    "gn:asciiname":"Santa Ines",
    "gn:country_code":"MX",
    "gn:dem":437,
    "gn:feature_class":"P",
    "gn:feature_code":"PPL",
    "gn:name":"Santa In\u00e9s",
    "gn:population":4,
    "gn:timezone":"America/Mexico_City",
    "iso:country":"MX",
    "name:und_x_variant":[
        "Santa In\u00e9s"
    ],
    "wof:name":"Santa Ines",
    "wof:placetype":"locality",
    "wof:population":4
},
  "geometry": {"coordinates":[-93.20972,15.82222],"type":"Point"}
}