{
  "type": "Feature",
  "properties": {
    "gn:admin1_code":"25",
    "gn:admin2_code":"3.0",
    "gn:asciiname":"Rico",
    "gn:country_code":"MX",
    "gn:dem":327,
    "gn:feature_class":"P",
    "gn:feature_code":"PPL",
    "gn:name":"Rico",
    "gn:population":0,
    "gn:timezone":"America/Mazatlan",
    "iso:country":"MX",
    "wof:name":"Rico",
    "wof:placetype":"locality"
},
  "geometry": {"coordinates":[-107.34166999999999,25.25],"type":"Point"}
}