{
  "type": "Feature",
  "properties": {
    "gn:admin1_code":"25",
    "gn:admin2_code":"3.0",
    "gn:asciiname":"Rico",
    "gn:country_code":"MX",
    "gn:dem":327,
    "gn:feature_class":"P",
    "gn:feature_code":"PPL",
    "gn:name":"Rico",
    "gn:population":0,
    "gn:timezone":"America/Mazatlan",
    "iso:country":"MX",
    "name:ceb_x_preferred":[
        "Rico"
    ],
    "name:deu_x_preferred":[
        "Rico"
    ],
    "name:fas_x_preferred":[
        "\u0631\u06cc\u06a9\u0648"
    ],
    "name:fin_x_preferred":[
        "Rico"
    ],
    "name:fra_x_preferred":[
        "Rico"
    ],
    "name:ita_x_preferred":[
        "Rico"
    ],
    "name:nld_x_preferred":[
        "Rico"
    ],
    "name:nor_x_preferred":[
        "Rico"
    ],
    "name:por_x_preferred":[
        "Rico"
    ],
    "name:swe_x_preferred":[
        "Rico"
    ],
    "wof:name":"Rico",
    "wof:placetype":"locality"
},
  "geometry": {"coordinates":[-107.34166999999999,25.25],"type":"Point"}
}