{
  "type": "Feature",
  "properties": {
    "gn:admin1_code":"6",
    "gn:admin2_code":"29",
    "gn:asciiname":"Carricitos",
    "gn:country_code":"MX",
    "gn:dem":1254,
    "gn:feature_class":"P",
    "gn:feature_code":"PPL",
    "gn:name":"Carricitos",
    "gn:population":17,
    "gn:timezone":"America/Mazatlan",
    "iso:country":"MX",
    "wof:name":"Carricitos",
    "wof:placetype":"locality",
    "wof:population":17
},
  "geometry": {"coordinates":[-107.54958999999999,26.15523],"type":"Point"}
}