{
  "type": "Feature",
  "properties": {
    "gn:admin1_code":"12",
    "gn:admin2_code":"10",
    "gn:asciiname":"Plan del Conejo",
    "gn:country_code":"MX",
    "gn:dem":1153,
    "gn:feature_class":"P",
    "gn:feature_code":"PPL",
    "gn:name":"Plan del Conejo",
    "gn:population":24,
    "gn:timezone":"America/Mexico_City",
    "iso:country":"MX",
    "wof:name":"Plan del Conejo",
    "wof:placetype":"locality",
    "wof:population":24
},
  "geometry": {"coordinates":[-98.9299,17.29657000000001],"type":"Point"}
}