{
  "type": "Feature",
  "properties": {
    "gn:admin1_code":"27.0",
    "gn:asciiname":"Cacao Primera Seccion",
    "gn:country_code":"MX",
    "gn:dem":27,
    "gn:feature_class":"P",
    "gn:feature_code":"PPL",
    "gn:name":"Cacao Primera Secci\u00f3n",
    "gn:population":0,
    "gn:timezone":"America/Mexico_City",
    "iso:country":"MX",
    "name:spa_x_preferred":[
        "Cacao Primera Secci\u00f3n"
    ],
    "wof:name":"Cacao Primera Seccion",
    "wof:placetype":"locality"
},
  "geometry": {"coordinates":[-91.57671999999999,17.65997],"type":"Point"}
}