{
  "type": "Feature",
  "properties": {
    "gn:admin1_code":"13",
    "gn:admin2_code":"40.0",
    "gn:asciiname":"Mesa del Huizache",
    "gn:country_code":"MX",
    "gn:dem":1496,
    "gn:feature_class":"P",
    "gn:feature_code":"PPL",
    "gn:name":"Mesa del Huizache",
    "gn:population":0,
    "gn:timezone":"America/Mexico_City",
    "iso:country":"MX",
    "name:spa_x_preferred":[
        "El Huizache"
    ],
    "name:spa_x_variant":[
        "Mesa del Huizache"
    ],
    "wof:name":"Mesa del Huizache",
    "wof:placetype":"locality"
},
  "geometry": {"coordinates":[-99.06269,21.00481],"type":"Point"}
}