{
  "type": "Feature",
  "properties": {
    "gn:admin1_code":"10",
    "gn:admin2_code":"23.0",
    "gn:asciiname":"Los Desmontes",
    "gn:country_code":"MX",
    "gn:dem":2055,
    "gn:feature_class":"P",
    "gn:feature_code":"PPL",
    "gn:name":"Los Desmontes",
    "gn:population":0,
    "gn:timezone":"America/Monterrey",
    "iso:country":"MX",
    "name:spa_x_preferred":[
        "Los Desmontes"
    ],
    "wof:name":"Los Desmontes",
    "wof:placetype":"locality"
},
  "geometry": {"coordinates":[-105.38934,23.19824],"type":"Point"}
}