{
  "type": "Feature",
  "properties": {
    "gn:admin1_code":"11",
    "gn:admin2_code":"27.0",
    "gn:asciiname":"San Jose de Mendoza",
    "gn:country_code":"MX",
    "gn:dem":1785,
    "gn:feature_class":"P",
    "gn:feature_code":"PPL",
    "gn:name":"San Jos\u00e9 de Mendoza",
    "gn:population":0,
    "gn:timezone":"America/Mexico_City",
    "iso:country":"MX",
    "name:spa_x_preferred":[
        "San Jos\u00e9 de Mendoza"
    ],
    "name:und_x_variant":[
        "R\u00edo Mendoza",
        "Mendoza"
    ],
    "wof:name":"San Jose de Mendoza",
    "wof:placetype":"locality"
},
  "geometry": {"coordinates":[-101.21353000000001,20.68965],"type":"Point"}
}