{
  "type": "Feature",
  "properties": {
    "gn:admin1_code":"28.0",
    "gn:admin2_code":"37.0",
    "gn:asciiname":"Las Azucenas",
    "gn:country_code":"MX",
    "gn:dem":337,
    "gn:feature_class":"P",
    "gn:feature_code":"PPL",
    "gn:name":"Las Azucenas",
    "gn:population":0,
    "gn:timezone":"America/Monterrey",
    "iso:country":"MX",
    "name:spa_x_preferred":[
        "Las Azucenas"
    ],
    "wof:name":"Las Azucenas",
    "wof:placetype":"locality"
},
  "geometry": {"coordinates":[-98.47306,23.71194],"type":"Point"}
}