{
  "type": "Feature",
  "properties": {
    "gn:admin1_code":"16",
    "gn:admin2_code":"8.0",
    "gn:asciiname":"Los Charcos",
    "gn:country_code":"MX",
    "gn:dem":1127,
    "gn:feature_class":"P",
    "gn:feature_code":"PPL",
    "gn:name":"Los Charcos",
    "gn:population":5,
    "gn:timezone":"America/Mexico_City",
    "iso:country":"MX",
    "wof:name":"Los Charcos",
    "wof:placetype":"locality",
    "wof:population":5
},
  "geometry": {"coordinates":[-103.1225,18.37639],"type":"Point"}
}