{
  "type": "Feature",
  "properties": {
    "gn:admin1_code":"30.0",
    "gn:admin2_code":"58.0",
    "gn:asciiname":"Tenexaco",
    "gn:country_code":"MX",
    "gn:dem":478,
    "gn:feature_class":"P",
    "gn:feature_code":"PPL",
    "gn:name":"Tenexaco",
    "gn:population":73,
    "gn:timezone":"America/Mexico_City",
    "iso:country":"MX",
    "name:spa_x_preferred":[
        "Tenexaco"
    ],
    "wof:name":"Tenexaco",
    "wof:placetype":"locality",
    "wof:population":73
},
  "geometry": {"coordinates":[-98.12139000000001,20.90333],"type":"Point"}
}