{
  "type": "Feature",
  "properties": {
    "gn:admin1_code":"3",
    "gn:admin2_code":"8",
    "gn:asciiname":"Playa Tortuga",
    "gn:country_code":"MX",
    "gn:dem":14,
    "gn:feature_class":"P",
    "gn:feature_code":"PPL",
    "gn:name":"Playa Tortuga",
    "gn:population":10,
    "gn:timezone":"America/Mazatlan",
    "iso:country":"MX",
    "wof:name":"Playa Tortuga",
    "wof:placetype":"locality",
    "wof:population":10
},
  "geometry": {"coordinates":[-109.53610999999999,23.10972000000001],"type":"Point"}
}