{
  "type": "Feature",
  "properties": {
    "gn:admin1_code":"30.0",
    "gn:admin2_code":"123.0",
    "gn:asciiname":"Tamboyoche y Topila",
    "gn:country_code":"MX",
    "gn:dem":6,
    "gn:feature_class":"P",
    "gn:feature_code":"PPL",
    "gn:name":"Tamboyoche y Topila",
    "gn:population":112,
    "gn:timezone":"America/Mexico_City",
    "iso:country":"MX",
    "name:spa_x_preferred":[
        "Tamboyoche y Topila"
    ],
    "wof:name":"Tamboyoche y Topila",
    "wof:placetype":"locality",
    "wof:population":112
},
  "geometry": {"coordinates":[-98.05278,22.05889],"type":"Point"}
}