{
  "type": "Feature",
  "properties": {
    "gn:admin1_code":"13",
    "gn:admin2_code":"46.0",
    "gn:asciiname":"Alfonso Cravioto",
    "gn:country_code":"MX",
    "gn:dem":150,
    "gn:feature_class":"P",
    "gn:feature_code":"PPL",
    "gn:name":"Alfonso Cravioto",
    "gn:population":0,
    "gn:timezone":"America/Mexico_City",
    "iso:country":"MX",
    "name:spa_x_preferred":[
        "Alfonso Cravioto"
    ],
    "wof:name":"Alfonso Cravioto",
    "wof:placetype":"locality"
},
  "geometry": {"coordinates":[-98.63227999999999,21.36434],"type":"Point"}
}