{
  "type": "Feature",
  "properties": {
    "gn:admin1_code":"19",
    "gn:admin2_code":"50.0",
    "gn:asciiname":"Los Cavazos",
    "gn:country_code":"MX",
    "gn:dem":212,
    "gn:feature_class":"P",
    "gn:feature_code":"PPL",
    "gn:name":"Los Cavazos",
    "gn:population":0,
    "gn:timezone":"America/Monterrey",
    "iso:country":"MX",
    "name:und_x_variant":[
        "Rancho Los Cavazos",
        "Los Cabazos",
        "Los Cavazos"
    ],
    "wof:name":"Los Cavazos",
    "wof:placetype":"locality"
},
  "geometry": {"coordinates":[-99.92636,26.57288],"type":"Point"}
}