{
  "type": "Feature",
  "properties": {
    "gn:admin1_code":"16",
    "gn:admin2_code":"28.0",
    "gn:asciiname":"Patzimaro del Rincon",
    "gn:country_code":"MX",
    "gn:dem":1807,
    "gn:feature_class":"P",
    "gn:feature_code":"PPL",
    "gn:name":"Patzimaro del Rinc\u00f3n",
    "gn:population":0,
    "gn:timezone":"America/Mexico_City",
    "iso:country":"MX",
    "wof:name":"Patzimaro del Rincon",
    "wof:placetype":"locality"
},
  "geometry": {"coordinates":[-102.12681000000001,20.14363],"type":"Point"}
}