{
  "type": "Feature",
  "properties": {
    "gn:admin1_code":"5",
    "gn:admin2_code":"89",
    "gn:asciiname":"Las Conchas",
    "gn:country_code":"MX",
    "gn:dem":14,
    "gn:feature_class":"P",
    "gn:feature_code":"PPL",
    "gn:name":"Las Conchas",
    "gn:population":9,
    "gn:timezone":"America/Mexico_City",
    "iso:country":"MX",
    "wof:name":"Las Conchas",
    "wof:placetype":"locality",
    "wof:population":9
},
  "geometry": {"coordinates":[-92.30306,14.65417],"type":"Point"}
}