{
  "type": "Feature",
  "properties": {
    "gn:admin1_code":"12",
    "gn:admin2_code":"58.0",
    "gn:asciiname":"Cerro Alto",
    "gn:country_code":"MX",
    "gn:dem":1492,
    "gn:feature_class":"P",
    "gn:feature_code":"PPL",
    "gn:name":"Cerro Alto",
    "gn:population":531,
    "gn:timezone":"America/Mexico_City",
    "iso:country":"MX",
    "name:ceb_x_preferred":[
        "Cerro Alto"
    ],
    "name:spa_x_preferred":[
        "Cerro Alto"
    ],
    "name:swe_x_preferred":[
        "Cerro Alto"
    ],
    "wof:name":"Cerro Alto",
    "wof:placetype":"locality",
    "wof:population":531
},
  "geometry": {"coordinates":[-99.95732,18.37744],"type":"Point"}
}