{
  "type": "Feature",
  "properties": {
    "gn:admin1_code":"10",
    "gn:admin2_code":"34.0",
    "gn:asciiname":"Mesa de los Becerros",
    "gn:country_code":"MX",
    "gn:dem":2344,
    "gn:feature_class":"P",
    "gn:feature_code":"PPL",
    "gn:name":"Mesa de los Becerros",
    "gn:population":57,
    "gn:timezone":"America/Monterrey",
    "iso:country":"MX",
    "wof:name":"Mesa de los Becerros",
    "wof:placetype":"locality",
    "wof:population":57
},
  "geometry": {"coordinates":[-106.91316,25.46025],"type":"Point"}
}