{
  "type": "Feature",
  "properties": {
    "gn:admin1_code":"6",
    "gn:admin2_code":"29",
    "gn:asciiname":"El Ojito",
    "gn:country_code":"MX",
    "gn:dem":2589,
    "gn:feature_class":"P",
    "gn:feature_code":"PPL",
    "gn:name":"El Ojito",
    "gn:population":16,
    "gn:timezone":"America/Chihuahua",
    "iso:country":"MX",
    "wof:name":"El Ojito",
    "wof:placetype":"locality",
    "wof:population":16
},
  "geometry": {"coordinates":[-106.63594999999999,25.93357],"type":"Point"}
}