{
  "type": "Feature",
  "properties": {
    "gn:admin1_code":"14",
    "gn:admin2_code":"78",
    "gn:asciiname":"Las Fuentes [Fraccionamiento]",
    "gn:country_code":"MX",
    "gn:dem":1875,
    "gn:feature_class":"P",
    "gn:feature_code":"PPL",
    "gn:name":"Las Fuentes [Fraccionamiento]",
    "gn:population":11,
    "gn:timezone":"America/Mexico_City",
    "iso:country":"MX",
    "wof:name":"Las Fuentes [Fraccionamiento]",
    "wof:placetype":"locality",
    "wof:population":11
},
  "geometry": {"coordinates":[-102.44611,21.02444],"type":"Point"}
}