{
  "type": "Feature",
  "properties": {
    "gn:admin1_code":"13",
    "gn:admin2_code":"32",
    "gn:asciiname":"El Cafetal",
    "gn:country_code":"MX",
    "gn:dem":140,
    "gn:feature_class":"P",
    "gn:feature_code":"PPL",
    "gn:name":"El Cafetal",
    "gn:population":15,
    "gn:timezone":"America/Mexico_City",
    "iso:country":"MX",
    "name:spa_x_preferred":[
        "El Cafetal"
    ],
    "wof:name":"El Cafetal",
    "wof:placetype":"locality",
    "wof:population":15
},
  "geometry": {"coordinates":[-98.52249999999999,21.16413],"type":"Point"}
}