{
  "type": "Feature",
  "properties": {
    "gn:admin1_code":"15",
    "gn:admin2_code":"64.0",
    "gn:asciiname":"Santa Rosa de Guadalupe",
    "gn:country_code":"MX",
    "gn:dem":2670,
    "gn:feature_class":"P",
    "gn:feature_code":"PPL",
    "gn:name":"Santa Rosa de Guadalupe",
    "gn:population":414,
    "gn:timezone":"America/Mexico_City",
    "iso:country":"MX",
    "wof:name":"Santa Rosa de Guadalupe",
    "wof:placetype":"locality",
    "wof:population":414
},
  "geometry": {"coordinates":[-100.0959,19.80026],"type":"Point"}
}