{
  "type": "Feature",
  "properties": {
    "gn:admin1_code":"1",
    "gn:admin2_code":"1.0",
    "gn:asciiname":"Granja Laura Angelica",
    "gn:country_code":"MX",
    "gn:dem":1857,
    "gn:feature_class":"P",
    "gn:feature_code":"PPL",
    "gn:name":"Granja Laura Ang\u00e9lica",
    "gn:population":4,
    "gn:timezone":"America/Mexico_City",
    "iso:country":"MX",
    "name:und_x_variant":[
        "Granja Laura Ang\u00e9lica"
    ],
    "wof:name":"Granja Laura Angelica",
    "wof:placetype":"locality",
    "wof:population":4
},
  "geometry": {"coordinates":[-102.34278,21.87528],"type":"Point"}
}