{
  "type": "Feature",
  "properties": {
    "gn:admin1_code":"17",
    "gn:admin2_code":"10",
    "gn:asciiname":"El Granadillo",
    "gn:country_code":"MX",
    "gn:dem":1497,
    "gn:feature_class":"P",
    "gn:feature_code":"PPL",
    "gn:name":"El Granadillo",
    "gn:population":10,
    "gn:timezone":"America/Mexico_City",
    "iso:country":"MX",
    "wof:name":"El Granadillo",
    "wof:placetype":"locality",
    "wof:population":10
},
  "geometry": {"coordinates":[-98.77943999999999,18.74056],"type":"Point"}
}