{
  "type": "Feature",
  "properties": {
    "gn:admin1_code":"20.0",
    "gn:admin2_code":"289.0",
    "gn:asciiname":"Agua del Higo",
    "gn:country_code":"MX",
    "gn:dem":1504,
    "gn:feature_class":"P",
    "gn:feature_code":"PPL",
    "gn:name":"Agua del Higo",
    "gn:population":0,
    "gn:timezone":"America/Mexico_City",
    "iso:country":"MX",
    "name:spa_x_preferred":[
        "Agua del Higo"
    ],
    "wof:name":"Agua del Higo",
    "wof:placetype":"locality"
},
  "geometry": {"coordinates":[-96.72608,16.459],"type":"Point"}
}