{
  "type": "Feature",
  "properties": {
    "gn:admin1_code":"28",
    "gn:admin2_code":"22",
    "gn:asciiname":"Guadalupe",
    "gn:country_code":"MX",
    "gn:dem":17,
    "gn:feature_class":"P",
    "gn:feature_code":"PPL",
    "gn:name":"Guadalupe",
    "gn:population":43,
    "gn:timezone":"America/Matamoros",
    "iso:country":"MX",
    "wof:name":"Guadalupe",
    "wof:placetype":"locality",
    "wof:population":43
},
  "geometry": {"coordinates":[-97.65971999999999,25.84833],"type":"Point"}
}