{
  "type": "Feature",
  "properties": {
    "gn:admin1_code":"13",
    "gn:asciiname":"San Jose Tena",
    "gn:country_code":"MX",
    "gn:dem":2293,
    "gn:feature_class":"P",
    "gn:feature_code":"PPL",
    "gn:name":"San Jos\u00e9 Te\u00f1a",
    "gn:population":0,
    "gn:timezone":"America/Mexico_City",
    "iso:country":"MX",
    "name:spa_x_preferred":[
        "San Jos\u00e9 Te\u00f1a"
    ],
    "wof:name":"San Jose Tena",
    "wof:placetype":"locality"
},
  "geometry": {"coordinates":[-99.13921999999999,20.00226],"type":"Point"}
}