{
  "type": "Feature",
  "properties": {
    "gn:admin1_code":"28",
    "gn:admin2_code":"22.0",
    "gn:asciiname":"Mezquital",
    "gn:country_code":"MX",
    "gn:dem":4,
    "gn:feature_class":"P",
    "gn:feature_code":"PPL",
    "gn:name":"Mezquital",
    "gn:population":0,
    "gn:timezone":"America/Matamoros",
    "iso:country":"MX",
    "name:spa_x_preferred":[
        "Mezquital"
    ],
    "name:und_x_variant":[
        "Rancho El Mezquital"
    ],
    "wof:name":"Mezquital",
    "wof:placetype":"locality"
},
  "geometry": {"coordinates":[-97.44320999999999,25.24225],"type":"Point"}
}