{
  "type": "Feature",
  "properties": {
    "gn:admin1_code":"16.0",
    "gn:admin2_code":"34.0",
    "gn:asciiname":"El Campamento",
    "gn:country_code":"MX",
    "gn:dem":1888,
    "gn:feature_class":"P",
    "gn:feature_code":"PPL",
    "gn:name":"El Campamento",
    "gn:population":0,
    "gn:timezone":"America/Mexico_City",
    "iso:country":"MX",
    "name:spa_x_preferred":[
        "El Campamento"
    ],
    "wof:name":"El Campamento",
    "wof:placetype":"locality"
},
  "geometry": {"coordinates":[-100.64060000000001,19.45965],"type":"Point"}
}