{
  "type": "Feature",
  "properties": {
    "gn:admin1_code":"14.0",
    "gn:asciiname":"Mesitas",
    "gn:country_code":"MX",
    "gn:dem":1791,
    "gn:feature_class":"P",
    "gn:feature_code":"PPL",
    "gn:name":"Mesitas",
    "gn:population":0,
    "gn:timezone":"America/Mexico_City",
    "iso:country":"MX",
    "name:spa_x_preferred":[
        "Mesitas"
    ],
    "name:spa_x_variant":[
        "Las Mesitas"
    ],
    "wof:name":"Mesitas",
    "wof:placetype":"locality"
},
  "geometry": {"coordinates":[-102.1704,21.19505],"type":"Point"}
}