{
  "type": "Feature",
  "properties": {
    "gn:admin1_code":"21",
    "gn:admin2_code":"142.0",
    "gn:asciiname":"Paso Puente de Santa Ana",
    "gn:country_code":"MX",
    "gn:dem":2420,
    "gn:feature_class":"P",
    "gn:feature_code":"PPL",
    "gn:name":"Paso Puente de Santa Ana",
    "gn:population":0,
    "gn:timezone":"America/Mexico_City",
    "iso:country":"MX",
    "name:spa_x_preferred":[
        "Paso Puente de Santa Ana"
    ],
    "wof:name":"Paso Puente de Santa Ana",
    "wof:placetype":"locality"
},
  "geometry": {"coordinates":[-97.60420000000001,19.06982],"type":"Point"}
}