{
  "type": "Feature",
  "properties": {
    "gn:admin1_code":"6",
    "gn:admin2_code":"9.0",
    "gn:asciiname":"La Mesa del Ojito",
    "gn:country_code":"MX",
    "gn:dem":2570,
    "gn:feature_class":"P",
    "gn:feature_code":"PPL",
    "gn:name":"La Mesa del Ojito",
    "gn:population":8,
    "gn:timezone":"America/Chihuahua",
    "iso:country":"MX",
    "wof:name":"La Mesa del Ojito",
    "wof:placetype":"locality",
    "wof:population":8
},
  "geometry": {"coordinates":[-107.32159,27.90575],"type":"Point"}
}