{
  "type": "Feature",
  "properties": {
    "gn:admin1_code":"5",
    "gn:admin2_code":"3.0",
    "gn:asciiname":"Embarcadero Rio Arriba",
    "gn:country_code":"MX",
    "gn:dem":7,
    "gn:feature_class":"P",
    "gn:feature_code":"PPL",
    "gn:name":"Embarcadero R\u00edo Arriba",
    "gn:population":79,
    "gn:timezone":"America/Mexico_City",
    "iso:country":"MX",
    "wof:name":"Embarcadero Rio Arriba",
    "wof:placetype":"locality",
    "wof:population":79
},
  "geometry": {"coordinates":[-92.7225,15.15139],"type":"Point"}
}