{
  "type": "Feature",
  "properties": {
    "gn:admin1_code":"18.0",
    "gn:admin2_code":"14.0",
    "gn:asciiname":"El Ermitano",
    "gn:country_code":"MX",
    "gn:dem":1276,
    "gn:feature_class":"P",
    "gn:feature_code":"PPL",
    "gn:name":"El Ermita\u00f1o",
    "gn:population":315,
    "gn:timezone":"America/Mazatlan",
    "iso:country":"MX",
    "name:spa_x_preferred":[
        "El Ermita\u00f1o"
    ],
    "wof:name":"El Ermitano",
    "wof:placetype":"locality",
    "wof:population":315
},
  "geometry": {"coordinates":[-104.74903999999999,21.32264],"type":"Point"}
}