{
  "type": "Feature",
  "properties": {
    "gn:admin1_code":"3",
    "gn:admin2_code":"1.0",
    "gn:asciiname":"El Guarismo",
    "gn:country_code":"MX",
    "gn:dem":200,
    "gn:feature_class":"P",
    "gn:feature_code":"PPL",
    "gn:name":"El Guarismo",
    "gn:population":0,
    "gn:timezone":"America/Mazatlan",
    "iso:country":"MX",
    "name:spa_x_preferred":[
        "El Guarismo"
    ],
    "wof:name":"El Guarismo",
    "wof:placetype":"locality"
},
  "geometry": {"coordinates":[-111.94571999999999,26.32551],"type":"Point"}
}