{
  "type": "Feature",
  "properties": {
    "gn:admin1_code":"10.0",
    "gn:admin2_code":"35.0",
    "gn:asciiname":"Cruz de Piedra",
    "gn:country_code":"MX",
    "gn:dem":2368,
    "gn:feature_class":"P",
    "gn:feature_code":"PPL",
    "gn:name":"Cruz de Piedra",
    "gn:population":0,
    "gn:timezone":"America/Monterrey",
    "iso:country":"MX",
    "wof:name":"Cruz de Piedra",
    "wof:placetype":"locality"
},
  "geometry": {"coordinates":[-106.24911000000002,25.698],"type":"Point"}
}