{
  "type": "Feature",
  "properties": {
    "gn:admin1_code":"30",
    "gn:admin2_code":"152.0",
    "gn:asciiname":"El Calabozo",
    "gn:country_code":"MX",
    "gn:dem":3,
    "gn:feature_class":"P",
    "gn:feature_code":"PPL",
    "gn:name":"El Calabozo",
    "gn:population":68,
    "gn:timezone":"America/Mexico_City",
    "iso:country":"MX",
    "wof:name":"El Calabozo",
    "wof:placetype":"locality",
    "wof:population":68
},
  "geometry": {"coordinates":[-97.78389,22.12944],"type":"Point"}
}