{
  "type": "Feature",
  "properties": {
    "gn:admin1_code":"14",
    "gn:admin2_code":"68.0",
    "gn:asciiname":"Las Vallas",
    "gn:country_code":"MX",
    "gn:dem":329,
    "gn:feature_class":"P",
    "gn:feature_code":"PPL",
    "gn:name":"Las Vallas",
    "gn:population":84,
    "gn:timezone":"America/Mexico_City",
    "iso:country":"MX",
    "wof:name":"Las Vallas",
    "wof:placetype":"locality",
    "wof:population":84
},
  "geometry": {"coordinates":[-104.56610999999999,19.64556],"type":"Point"}
}