{
  "type": "Feature",
  "properties": {
    "gn:admin1_code":"26.0",
    "gn:admin2_code":"68.0",
    "gn:asciiname":"David",
    "gn:country_code":"MX",
    "gn:dem":1012,
    "gn:feature_class":"P",
    "gn:feature_code":"PPL",
    "gn:name":"David",
    "gn:population":0,
    "gn:timezone":"America/Hermosillo",
    "iso:country":"MX",
    "wof:name":"David",
    "wof:placetype":"locality"
},
  "geometry": {"coordinates":[-109.90000000000001,29.31667],"type":"Point"}
}