{
  "type": "Feature",
  "properties": {
    "gn:admin1_code":"6",
    "gn:admin2_code":"62.0",
    "gn:asciiname":"Picacho de Abajo",
    "gn:country_code":"MX",
    "gn:dem":1347,
    "gn:feature_class":"P",
    "gn:feature_code":"PPL",
    "gn:name":"Picacho de Abajo",
    "gn:population":0,
    "gn:timezone":"America/Chihuahua",
    "iso:country":"MX",
    "name:spa_x_preferred":[
        "Picacho de Abajo"
    ],
    "wof:name":"Picacho de Abajo",
    "wof:placetype":"locality"
},
  "geometry": {"coordinates":[-105.3389,27.86854000000001],"type":"Point"}
}