{
  "type": "Feature",
  "properties": {
    "gn:admin1_code":"19.0",
    "gn:admin2_code":"11.0",
    "gn:asciiname":"El Manco",
    "gn:country_code":"MX",
    "gn:dem":300,
    "gn:feature_class":"P",
    "gn:feature_code":"PPL",
    "gn:name":"El Manco",
    "gn:population":0,
    "gn:timezone":"America/Monterrey",
    "iso:country":"MX",
    "name:spa_x_preferred":[
        "El Manco"
    ],
    "wof:name":"El Manco",
    "wof:placetype":"locality"
},
  "geometry": {"coordinates":[-99.62931,26.05617],"type":"Point"}
}