{
  "type": "Feature",
  "properties": {
    "gn:admin1_code":"5.0",
    "gn:admin2_code":"57.0",
    "gn:asciiname":"San Cristobalito",
    "gn:country_code":"MX",
    "gn:dem":991,
    "gn:feature_class":"P",
    "gn:feature_code":"PPL",
    "gn:name":"San Cristobalito",
    "gn:population":0,
    "gn:timezone":"America/Mexico_City",
    "iso:country":"MX",
    "name:spa_x_preferred":[
        "San Cristobalito"
    ],
    "wof:name":"San Cristobalito",
    "wof:placetype":"locality"
},
  "geometry": {"coordinates":[-92.40731,15.29606],"type":"Point"}
}