{
  "type": "Feature",
  "properties": {
    "gn:admin1_code":"16.0",
    "gn:admin2_code":"44.0",
    "gn:asciiname":"Copandaro (Copandaro del Cuatro)",
    "gn:country_code":"MX",
    "gn:dem":1991,
    "gn:feature_class":"P",
    "gn:feature_code":"PPL",
    "gn:name":"Cop\u00e1ndaro (Cop\u00e1ndaro del Cuatro)",
    "gn:population":1479,
    "gn:timezone":"America/Mexico_City",
    "iso:country":"MX",
    "name:und_x_variant":[
        "Cop\u00e1ndaro",
        "Cop\u00e1ndaro del Cuatro"
    ],
    "wof:name":"Copandaro (Copandaro del Cuatro)",
    "wof:placetype":"locality",
    "wof:population":1479
},
  "geometry": {"coordinates":[-101.65945000000001,19.90057],"type":"Point"}
}