{
  "type": "Feature",
  "properties": {
    "gn:admin1_code":"24",
    "gn:admin2_code":"3.0",
    "gn:asciiname":"Los Vidales",
    "gn:country_code":"MX",
    "gn:dem":859,
    "gn:feature_class":"P",
    "gn:feature_code":"PPL",
    "gn:name":"Los Vidales",
    "gn:population":57,
    "gn:timezone":"America/Mexico_City",
    "iso:country":"MX",
    "wof:name":"Los Vidales",
    "wof:placetype":"locality",
    "wof:population":57
},
  "geometry": {"coordinates":[-99.03389,21.51361],"type":"Point"}
}