{
  "type": "Feature",
  "properties": {
    "gn:admin1_code":"23",
    "gn:admin2_code":"4.0",
    "gn:asciiname":"Emiliano Zapata",
    "gn:country_code":"MX",
    "gn:dem":60,
    "gn:feature_class":"P",
    "gn:feature_code":"PPL",
    "gn:name":"Emiliano Zapata",
    "gn:population":0,
    "gn:timezone":"America/Cancun",
    "iso:country":"MX",
    "wof:name":"Emiliano Zapata",
    "wof:placetype":"locality"
},
  "geometry": {"coordinates":[-88.78333000000001,19.07917],"type":"Point"}
}