{
  "type": "Feature",
  "properties": {
    "gn:admin1_code":"6",
    "gn:admin2_code":"57",
    "gn:asciiname":"La Esperanza",
    "gn:country_code":"MX",
    "gn:dem":1779,
    "gn:feature_class":"P",
    "gn:feature_code":"PPL",
    "gn:name":"La Esperanza",
    "gn:population":43,
    "gn:timezone":"America/Chihuahua",
    "iso:country":"MX",
    "wof:name":"La Esperanza",
    "wof:placetype":"locality",
    "wof:population":43
},
  "geometry": {"coordinates":[-106.74159,28.04464],"type":"Point"}
}