{
  "type": "Feature",
  "properties": {
    "gn:admin1_code":"20",
    "gn:admin2_code":"124",
    "gn:asciiname":"Cruz Mojon",
    "gn:country_code":"MX",
    "gn:dem":28,
    "gn:feature_class":"P",
    "gn:feature_code":"PPL",
    "gn:name":"Cruz Moj\u00f3n",
    "gn:population":10,
    "gn:timezone":"America/Mexico_City",
    "iso:country":"MX",
    "name:und_x_variant":[
        "Cruz Moj\u00f3n"
    ],
    "wof:name":"Cruz Mojon",
    "wof:placetype":"locality",
    "wof:population":10
},
  "geometry": {"coordinates":[-95.185,16.30056],"type":"Point"}
}