{
  "type": "Feature",
  "properties": {
    "gn:admin1_code":"10",
    "gn:admin2_code":"5.0",
    "gn:asciiname":"Cienega de la Cebadilla",
    "gn:country_code":"MX",
    "gn:dem":2639,
    "gn:feature_class":"P",
    "gn:feature_code":"PPL",
    "gn:name":"Ci\u00e9nega de la Cebadilla",
    "gn:population":0,
    "gn:timezone":"America/Monterrey",
    "iso:country":"MX",
    "name:spa_x_preferred":[
        "Ci\u00e9nega de la Cebadilla"
    ],
    "wof:name":"Cienega de la Cebadilla",
    "wof:placetype":"locality"
},
  "geometry": {"coordinates":[-104.9494,23.62493],"type":"Point"}
}