{
  "type": "Feature",
  "properties": {
    "gn:admin1_code":"20",
    "gn:admin2_code":"309.0",
    "gn:asciiname":"Arroyo Murcielago",
    "gn:country_code":"MX",
    "gn:dem":96,
    "gn:feature_class":"P",
    "gn:feature_code":"PPL",
    "gn:name":"Arroyo Murci\u00e9lago",
    "gn:population":639,
    "gn:timezone":"America/Mexico_City",
    "iso:country":"MX",
    "name:und_x_variant":[
        "Arroyo Murci\u00e9lago"
    ],
    "wof:name":"Arroyo Murcielago",
    "wof:placetype":"locality",
    "wof:population":639
},
  "geometry": {"coordinates":[-96.5475,18.14611],"type":"Point"}
}