{
  "type": "Feature",
  "properties": {
    "gn:admin1_code":"6",
    "gn:admin2_code":"49.0",
    "gn:asciiname":"Paraje El Leon",
    "gn:country_code":"MX",
    "gn:dem":1910,
    "gn:feature_class":"P",
    "gn:feature_code":"PPL",
    "gn:name":"Paraje El Le\u00f3n",
    "gn:population":0,
    "gn:timezone":"America/Chihuahua",
    "iso:country":"MX",
    "name:spa_x_preferred":[
        "Paraje El Le\u00f3n"
    ],
    "wof:name":"Paraje El Leon",
    "wof:placetype":"locality"
},
  "geometry": {"coordinates":[-106.75003,27.61486],"type":"Point"}
}