{
  "type": "Feature",
  "properties": {
    "gn:admin1_code":"5",
    "gn:admin2_code":"11.0",
    "gn:asciiname":"Ojo de Agua",
    "gn:country_code":"MX",
    "gn:dem":2093,
    "gn:feature_class":"P",
    "gn:feature_code":"PPL",
    "gn:name":"Ojo de Agua",
    "gn:population":113,
    "gn:timezone":"America/Mexico_City",
    "iso:country":"MX",
    "wof:name":"Ojo de Agua",
    "wof:placetype":"locality",
    "wof:population":113
},
  "geometry": {"coordinates":[-92.29583,15.60278],"type":"Point"}
}