{
  "type": "Feature",
  "properties": {
    "gn:admin1_code":"5",
    "gn:admin2_code":"97.0",
    "gn:asciiname":"El Vergel",
    "gn:country_code":"MX",
    "gn:dem":22,
    "gn:feature_class":"P",
    "gn:feature_code":"PPL",
    "gn:name":"El Vergel",
    "gn:population":4,
    "gn:timezone":"America/Mexico_City",
    "iso:country":"MX",
    "wof:name":"El Vergel",
    "wof:placetype":"locality",
    "wof:population":4
},
  "geometry": {"coordinates":[-93.50611000000001,15.84528],"type":"Point"}
}