{
  "type": "Feature",
  "properties": {
    "gn:admin1_code":"24",
    "gn:admin2_code":"28",
    "gn:asciiname":"El Bosque (El Cascaron)",
    "gn:country_code":"MX",
    "gn:dem":1800,
    "gn:feature_class":"P",
    "gn:feature_code":"PPL",
    "gn:name":"El Bosque (El Cascar\u00f3n)",
    "gn:population":36,
    "gn:timezone":"America/Mexico_City",
    "iso:country":"MX",
    "name:und_x_variant":[
        "El Bosque (El Cascar\u00f3n)"
    ],
    "wof:name":"El Bosque (El Cascaron)",
    "wof:placetype":"locality",
    "wof:population":36
},
  "geometry": {"coordinates":[-101.07944000000001,22.47222],"type":"Point"}
}