{
  "type": "Feature",
  "properties": {
    "iso:country":"MX",
    "name:spa_x_preferred":[
        "Fovissste"
    ],
    "qs:gn_adm0_cc":"MX",
    "qs:gn_local":3996663,
    "qs:gn_nam_loc":"Manzanillo, Manzanillo, Colima, MX",
    "qs:gn_namadm1":"08",
    "qs:local_max":241,
    "qs:local_sum":1057,
    "qs:localhoods":11,
    "qs:name":"Fovissste",
    "qs:name_adm0":"M\u00e9xico",
    "qs:name_adm1":"Colima",
    "qs:name_adm2":"Manzanillo",
    "qs:name_local":"Manzanillo",
    "qs:photo_max":54,
    "qs:photo_sum":160,
    "qs:placetype":"Suburb",
    "qs:quad_count":8,
    "qs:woe_adm0":23424900,
    "qs:woe_adm1":2346271,
    "qs:woe_adm2":12599930,
    "qs:woe_lau":0,
    "qs:woe_local":132925,
    "qs:woe_ver":"7.10.0",
    "wof:lang":[
        "spa"
    ],
    "wof:name":"Fovissste",
    "wof:placetype":"neighbourhood"
},
  "geometry": {"coordinates":[-104.325819,19.09797],"type":"Point"}
}