{
  "type": "Feature",
  "properties": {
    "gn:admin1_code":"30",
    "gn:admin2_code":"38.0",
    "gn:asciiname":"Bella Esperanza",
    "gn:country_code":"MX",
    "gn:dem":1011,
    "gn:feature_class":"P",
    "gn:feature_code":"PPL",
    "gn:name":"Bella Esperanza",
    "gn:population":1618,
    "gn:timezone":"America/Mexico_City",
    "iso:country":"MX",
    "name:spa_x_preferred":[
        "Bella Esperanza"
    ],
    "wof:name":"Bella Esperanza",
    "wof:placetype":"locality",
    "wof:population":1618
},
  "geometry": {"coordinates":[-96.86648,19.43329],"type":"Point"}
}