{
  "type": "Feature",
  "properties": {
    "gn:admin1_code":"6.0",
    "gn:admin2_code":"1.0",
    "gn:asciiname":"Tijuana",
    "gn:country_code":"MX",
    "gn:dem":1389,
    "gn:feature_class":"P",
    "gn:feature_code":"PPL",
    "gn:name":"Tijuana",
    "gn:population":0,
    "gn:timezone":"America/Chihuahua",
    "iso:country":"MX",
    "name:spa_x_preferred":[
        "Tijuana"
    ],
    "name:spa_x_variant":[
        "Rancho Tijuana"
    ],
    "wof:name":"Tijuana",
    "wof:placetype":"locality"
},
  "geometry": {"coordinates":[-106.42366,30.17814000000001],"type":"Point"}
}