{
  "type": "Feature",
  "properties": {
    "gn:admin1_code":"16",
    "gn:admin2_code":"112.0",
    "gn:asciiname":"El Granjeno",
    "gn:country_code":"MX",
    "gn:dem":1871,
    "gn:feature_class":"P",
    "gn:feature_code":"PPL",
    "gn:name":"El Granjeno",
    "gn:population":200,
    "gn:timezone":"America/Mexico_City",
    "iso:country":"MX",
    "wof:name":"El Granjeno",
    "wof:placetype":"locality",
    "wof:population":200
},
  "geometry": {"coordinates":[-100.36360999999999,19.46611],"type":"Point"}
}