{
  "type": "Feature",
  "properties": {
    "gn:admin1_code":"26.0",
    "gn:admin2_code":"51.0",
    "gn:asciiname":"Cienega del Sauz",
    "gn:country_code":"MX",
    "gn:dem":1204,
    "gn:feature_class":"P",
    "gn:feature_code":"PPL",
    "gn:name":"Ci\u00e9nega del Sauz",
    "gn:population":0,
    "gn:timezone":"America/Chihuahua",
    "iso:country":"MX",
    "name:spa_x_preferred":[
        "Ci\u00e9nega del Sauz"
    ],
    "wof:name":"Cienega del Sauz",
    "wof:placetype":"locality"
},
  "geometry": {"coordinates":[-109.08691,28.13684000000001],"type":"Point"}
}