{
  "type": "Feature",
  "properties": {
    "gn:admin1_code":"14",
    "gn:admin2_code":"72",
    "gn:asciiname":"Canales",
    "gn:country_code":"MX",
    "gn:dem":1797,
    "gn:feature_class":"P",
    "gn:feature_code":"PPL",
    "gn:name":"Canales",
    "gn:population":25,
    "gn:timezone":"America/Mexico_City",
    "iso:country":"MX",
    "name:ara_x_preferred":[
        "\u0643\u0627\u0646\u0627\u0644\u064a\u0633"
    ],
    "name:cat_x_preferred":[
        "Canales"
    ],
    "name:eus_x_preferred":[
        "Canales"
    ],
    "name:fas_x_preferred":[
        "\u06a9\u0627\u0646\u0627\u0644\u0633"
    ],
    "name:fra_x_preferred":[
        "Canales"
    ],
    "name:hun_x_preferred":[
        "Canales"
    ],
    "name:ina_x_preferred":[
        "Canales"
    ],
    "name:ita_x_preferred":[
        "Canales"
    ],
    "name:kaz_x_preferred":[
        "\u041a\u0430\u043d\u0430\u043b\u0435\u0441"
    ],
    "name:mkd_x_preferred":[
        "\u041a\u0430\u043d\u0430\u043b\u0435\u0441"
    ],
    "name:msa_x_preferred":[
        "Canales"
    ],
    "name:nld_x_preferred":[
        "Canales"
    ],
    "name:oci_x_preferred":[
        "Canales"
    ],
    "name:pol_x_preferred":[
        "Canales"
    ],
    "name:por_x_preferred":[
        "Canales"
    ],
    "name:rus_x_preferred":[
        "\u041a\u0430\u043d\u0430\u043b\u0435\u0441"
    ],
    "name:spa_x_preferred":[
        "Canales"
    ],
    "name:ukr_x_preferred":[
        "\u041a\u0430\u043d\u0430\u043b\u0435\u0441"
    ],
    "name:uzb_x_preferred":[
        "Canales"
    ],
    "name:vie_x_preferred":[
        "Canales"
    ],
    "name:war_x_preferred":[
        "Canales"
    ],
    "name:zho_x_preferred":[
        "\u5361\u7eb3\u83b1\u65af"
    ],
    "wof:name":"Canales",
    "wof:placetype":"locality",
    "wof:population":25
},
  "geometry": {"coordinates":[-102.06667,20.89528],"type":"Point"}
}