{
  "type": "Feature",
  "properties": {
    "gn:admin1_code":"19",
    "gn:admin2_code":"42.0",
    "gn:asciiname":"El Palmarujo",
    "gn:country_code":"MX",
    "gn:dem":242,
    "gn:feature_class":"P",
    "gn:feature_code":"PPL",
    "gn:name":"El Palmarujo",
    "gn:population":1,
    "gn:timezone":"America/Monterrey",
    "iso:country":"MX",
    "wof:name":"El Palmarujo",
    "wof:placetype":"locality",
    "wof:population":1
},
  "geometry": {"coordinates":[-99.71001,25.55096],"type":"Point"}
}