{
  "type": "Feature",
  "properties": {
    "gn:admin1_code":"19",
    "gn:admin2_code":"17.0",
    "gn:asciiname":"El Alamar de Solis",
    "gn:country_code":"MX",
    "gn:dem":1710,
    "gn:feature_class":"P",
    "gn:feature_code":"PPL",
    "gn:name":"El Alamar de Sol\u00eds",
    "gn:population":0,
    "gn:timezone":"America/Monterrey",
    "iso:country":"MX",
    "name:spa_x_preferred":[
        "El Alamar de Sol\u00eds"
    ],
    "name:und_x_variant":[
        "Rancho Alamar de Solis"
    ],
    "wof:name":"El Alamar de Solis",
    "wof:placetype":"locality"
},
  "geometry": {"coordinates":[-99.90559,24.53138],"type":"Point"}
}