{
  "type": "Feature",
  "properties": {
    "gn:admin1_code":"26",
    "gn:admin2_code":"30.0",
    "gn:asciiname":"El Crucero (Cero Norte)",
    "gn:country_code":"MX",
    "gn:dem":67,
    "gn:feature_class":"P",
    "gn:feature_code":"PPL",
    "gn:name":"El Crucero (Cero Norte)",
    "gn:population":56,
    "gn:timezone":"America/Hermosillo",
    "iso:country":"MX",
    "wof:name":"El Crucero (Cero Norte)",
    "wof:placetype":"locality",
    "wof:population":56
},
  "geometry": {"coordinates":[-111.47889000000001,28.91361],"type":"Point"}
}