{
  "type": "Feature",
  "properties": {
    "gn:admin1_code":"20",
    "gn:admin2_code":"57",
    "gn:asciiname":"La Ceiba",
    "gn:country_code":"MX",
    "gn:dem":89,
    "gn:feature_class":"P",
    "gn:feature_code":"PPL",
    "gn:name":"La Ceiba",
    "gn:population":23,
    "gn:timezone":"America/Mexico_City",
    "iso:country":"MX",
    "wof:name":"La Ceiba",
    "wof:placetype":"locality",
    "wof:population":23
},
  "geometry": {"coordinates":[-94.95694,17.03972000000001],"type":"Point"}
}