{
  "type": "Feature",
  "properties": {
    "gn:admin1_code":"13",
    "gn:admin2_code":"59.0",
    "gn:asciiname":"La Cruz de Piedra",
    "gn:country_code":"MX",
    "gn:dem":1863,
    "gn:feature_class":"P",
    "gn:feature_code":"PPL",
    "gn:name":"La Cruz de Piedra",
    "gn:population":85,
    "gn:timezone":"America/Mexico_City",
    "iso:country":"MX",
    "wof:name":"La Cruz de Piedra",
    "wof:placetype":"locality",
    "wof:population":85
},
  "geometry": {"coordinates":[-99.74806,20.48361],"type":"Point"}
}