{
  "type": "Feature",
  "properties": {
    "gn:admin1_code":"27",
    "gn:admin2_code":"5.0",
    "gn:asciiname":"Arena 6ta. Seccion (La Bolsa)",
    "gn:country_code":"MX",
    "gn:dem":13,
    "gn:feature_class":"P",
    "gn:feature_code":"PPL",
    "gn:name":"Arena 6ta. Secci\u00f3n (La Bolsa)",
    "gn:population":1158,
    "gn:timezone":"America/Mexico_City",
    "iso:country":"MX",
    "name:und_x_variant":[
        "Arena 6ta. Secci\u00f3n (La Bolsa)"
    ],
    "wof:name":"Arena 6ta. Seccion (La Bolsa)",
    "wof:placetype":"locality",
    "wof:population":1158
},
  "geometry": {"coordinates":[-93.39539000000001,18.16218],"type":"Point"}
}