{
  "type": "Feature",
  "properties": {
    "gn:admin1_code":"22",
    "gn:admin2_code":"14.0",
    "gn:asciiname":"Cuitlahuac",
    "gn:country_code":"MX",
    "gn:dem":1843,
    "gn:feature_class":"P",
    "gn:feature_code":"PPL",
    "gn:name":"Cuitl\u00e1huac",
    "gn:population":366,
    "gn:timezone":"America/Mexico_City",
    "iso:country":"MX",
    "name:und_x_variant":[
        "Cuitl\u00e1huac"
    ],
    "wof:name":"Cuitlahuac",
    "wof:placetype":"locality",
    "wof:population":366
},
  "geometry": {"coordinates":[-100.42694,20.67111],"type":"Point"}
}