{
  "type": "Feature",
  "properties": {
    "gn:admin1_code":"14",
    "gn:admin2_code":"87",
    "gn:asciiname":"La Cuchilla",
    "gn:country_code":"MX",
    "gn:dem":1509,
    "gn:feature_class":"P",
    "gn:feature_code":"PPL",
    "gn:name":"La Cuchilla",
    "gn:population":15,
    "gn:timezone":"America/Mexico_City",
    "iso:country":"MX",
    "wof:name":"La Cuchilla",
    "wof:placetype":"locality",
    "wof:population":15
},
  "geometry": {"coordinates":[-103.27791000000001,19.19764],"type":"Point"}
}