{
  "type": "Feature",
  "properties": {
    "gn:admin1_code":"16",
    "gn:admin2_code":"92",
    "gn:asciiname":"Palmo Real",
    "gn:country_code":"MX",
    "gn:dem":1452,
    "gn:feature_class":"P",
    "gn:feature_code":"PPL",
    "gn:name":"Palmo Real",
    "gn:population":10,
    "gn:timezone":"America/Mexico_City",
    "iso:country":"MX",
    "wof:name":"Palmo Real",
    "wof:placetype":"locality",
    "wof:population":10
},
  "geometry": {"coordinates":[-100.92361,19.19639],"type":"Point"}
}