{
  "type": "Feature",
  "properties": {
    "gn:admin1_code":"20",
    "gn:admin2_code":"382",
    "gn:asciiname":"Yunuu",
    "gn:country_code":"MX",
    "gn:dem":1201,
    "gn:feature_class":"P",
    "gn:feature_code":"PPL",
    "gn:name":"Yu\u00f1uu",
    "gn:population":18,
    "gn:timezone":"America/Mexico_City",
    "iso:country":"MX",
    "name:und_x_variant":[
        "Yu\u00f1uu"
    ],
    "wof:name":"Yunuu",
    "wof:placetype":"locality",
    "wof:population":18
},
  "geometry": {"coordinates":[-97.4725,16.91278],"type":"Point"}
}