{
  "type": "Feature",
  "properties": {
    "gn:admin1_code":"32",
    "gn:admin2_code":"34",
    "gn:asciiname":"El Peine",
    "gn:country_code":"MX",
    "gn:dem":1830,
    "gn:feature_class":"P",
    "gn:feature_code":"PPL",
    "gn:name":"El Peine",
    "gn:population":33,
    "gn:timezone":"America/Mexico_City",
    "iso:country":"MX",
    "wof:name":"El Peine",
    "wof:placetype":"locality",
    "wof:population":33
},
  "geometry": {"coordinates":[-102.87555999999999,21.31083],"type":"Point"}
}