{
  "type": "Feature",
  "properties": {
    "gn:admin1_code":"30.0",
    "gn:admin2_code":"150.0",
    "gn:asciiname":"El Veinte",
    "gn:country_code":"MX",
    "gn:dem":13,
    "gn:feature_class":"P",
    "gn:feature_code":"PPL",
    "gn:name":"El Veinte",
    "gn:population":0,
    "gn:timezone":"America/Mexico_City",
    "iso:country":"MX",
    "name:spa_x_preferred":[
        "El Veinte"
    ],
    "wof:name":"El Veinte",
    "wof:placetype":"locality"
},
  "geometry": {"coordinates":[-97.60917000000001,21.48861],"type":"Point"}
}