{
  "type": "Feature",
  "properties": {
    "gn:admin1_code":"31",
    "gn:admin2_code":"16.0",
    "gn:asciiname":"Santa Juliana",
    "gn:country_code":"MX",
    "gn:dem":28,
    "gn:feature_class":"P",
    "gn:feature_code":"PPL",
    "gn:name":"Santa Juliana",
    "gn:population":0,
    "gn:timezone":"America/Merida",
    "iso:country":"MX",
    "name:bpy_x_preferred":[
        "\u09b8\u09be\u09a8\u09cd\u099f\u09be \u099c\u09c1\u09b2\u09bf\u09af\u09bc\u09be\u09a8\u09be"
    ],
    "name:ceb_x_preferred":[
        "Santa Juliana"
    ],
    "name:epo_x_preferred":[
        "Santa Juliana"
    ],
    "name:fra_x_preferred":[
        "Santa Juliana"
    ],
    "name:ita_x_preferred":[
        "Santa Juliana"
    ],
    "name:kat_x_preferred":[
        "\u10e1\u10d0\u10dc\u10e2\u10d0-\u10df\u10e3\u10da\u10d8\u10d0\u10dc\u10d0"
    ],
    "name:kaz_x_preferred":[
        "\u0421\u0430\u043d\u0442\u0430-\u0416\u0443\u043b\u0438\u0430\u043d\u0430"
    ],
    "name:mlg_x_preferred":[
        "Santa Juliana"
    ],
    "name:nld_x_preferred":[
        "Santa Juliana"
    ],
    "name:nor_x_preferred":[
        "Santa Juliana"
    ],
    "name:pol_x_preferred":[
        "Santa Juliana"
    ],
    "name:por_x_preferred":[
        "Santa Juliana"
    ],
    "name:ron_x_preferred":[
        "Santa Juliana"
    ],
    "name:rus_x_preferred":[
        "\u0421\u0430\u043d\u0442\u0430-\u0416\u0443\u043b\u0438\u0430\u043d\u0430"
    ],
    "name:spa_x_preferred":[
        "Santa Juliana"
    ],
    "name:vie_x_preferred":[
        "Santa Juliana"
    ],
    "name:vol_x_preferred":[
        "Santa Juliana"
    ],
    "name:war_x_preferred":[
        "Santa Juliana"
    ],
    "name:zho_x_preferred":[
        "\u5723\u8339\u5229\u4e9a\u5a1c"
    ],
    "wof:name":"Santa Juliana",
    "wof:placetype":"locality"
},
  "geometry": {"coordinates":[-88.98719,20.2303],"type":"Point"}
}