{
  "type": "Feature",
  "properties": {
    "gn:admin1_code":"31",
    "gn:admin2_code":"16.0",
    "gn:asciiname":"Santa Juliana",
    "gn:country_code":"MX",
    "gn:dem":28,
    "gn:feature_class":"P",
    "gn:feature_code":"PPL",
    "gn:name":"Santa Juliana",
    "gn:population":0,
    "gn:timezone":"America/Merida",
    "iso:country":"MX",
    "name:spa_x_preferred":[
        "Santa Juliana"
    ],
    "wof:name":"Santa Juliana",
    "wof:placetype":"locality"
},
  "geometry": {"coordinates":[-88.98719,20.2303],"type":"Point"}
}