{
  "type": "Feature",
  "properties": {
    "gn:admin1_code":"19",
    "gn:admin2_code":"50.0",
    "gn:asciiname":"Cuevecillas",
    "gn:country_code":"MX",
    "gn:dem":197,
    "gn:feature_class":"P",
    "gn:feature_code":"PPL",
    "gn:name":"Cuevecillas",
    "gn:population":0,
    "gn:timezone":"America/Monterrey",
    "iso:country":"MX",
    "wof:name":"Cuevecillas",
    "wof:placetype":"locality"
},
  "geometry": {"coordinates":[-99.88333,26.75],"type":"Point"}
}