{
  "type": "Feature",
  "properties": {
    "gn:gn_country":"MX",
    "gn:gn_fcode":"PPL",
    "gn:gn_pop":0,
    "iso:country":"MX",
    "name:bre_x_preferred":[
        "Los Lagos"
    ],
    "name:ceb_x_preferred":[
        "Los Lagos"
    ],
    "name:deu_x_preferred":[
        "Los Lagos"
    ],
    "name:hrv_x_preferred":[
        "Los Lagos"
    ],
    "name:ita_x_preferred":[
        "Los Lagos"
    ],
    "name:nld_x_preferred":[
        "Los Lagos"
    ],
    "name:rus_x_preferred":[
        "\u041b\u043e\u0441-\u041b\u0430\u0433\u043e\u0441"
    ],
    "name:sco_x_preferred":[
        "Los Lagos"
    ],
    "name:slk_x_preferred":[
        "Los Lagos"
    ],
    "name:spa_x_preferred":[
        "Los Llanos"
    ],
    "name:spa_x_variant":[
        "Los Lagos"
    ],
    "name:srp_x_preferred":[
        "\u041b\u043e\u0441 \u041b\u0430\u0433\u043e\u0441"
    ],
    "name:swe_x_preferred":[
        "Los Lagos"
    ],
    "qs_pg:aaroncc":"MX",
    "qs_pg:gn_country":"MX",
    "qs_pg:gn_fcode":"PPL",
    "qs_pg:gn_pop":0,
    "qs_pg:name":"Los Lagos",
    "qs_pg:name_adm0":"M\u00e9xico",
    "qs_pg:name_adm1":"Coahuila de Zaragoza",
    "qs_pg:photos":1,
    "qs_pg:photos_1k":1,
    "qs_pg:photos_9k":1,
    "qs_pg:photos_9r":1,
    "qs_pg:photos_all":1,
    "qs_pg:photos_sr":1,
    "qs_pg:pop_sr":0,
    "qs_pg:qs_pg_placetype":"neighbourhood",
    "qs_pg:qs_pg_placetype_gp":"Suburb",
    "qs_pg:woe_adm0":23424900,
    "woe:adm0_id":23424900,
    "woe:name_adm0":"M\u00e9xico",
    "woe:name_adm1":"Coahuila de Zaragoza",
    "woe:placetype":"Suburb",
    "wof:name":"Los Lagos",
    "wof:placetype":"neighbourhood"
},
  "geometry": {"coordinates":[-100.79952,25.30576],"type":"Point"}
}