{
  "type": "Feature",
  "properties": {
    "gn:country":"MX",
    "gn:fcode":"PPL",
    "gn:population":0,
    "iso:country":"MX",
    "name:ara_x_preferred":[
        "\u0644\u0648\u0633 \u0644\u0627\u063a\u0648\u0633"
    ],
    "name:ben_x_preferred":[
        "\u09b2\u09b8 \u09b2\u09be\u0997\u09cb\u09b8"
    ],
    "name:bre_x_preferred":[
        "Los Lagos"
    ],
    "name:ceb_x_preferred":[
        "Los Lagos"
    ],
    "name:deu_x_preferred":[
        "Los Lagos"
    ],
    "name:ell_x_preferred":[
        "\u039b\u03bf\u03c2 \u039b\u03ac\u03b3\u03bf\u03c2"
    ],
    "name:heb_x_preferred":[
        "\u05dc\u05d5\u05e1 \u05dc\u05d2\u05d5\u05e1"
    ],
    "name:hin_x_preferred":[
        "\u0932\u094b\u0938 \u0932\u093e\u0917\u094b\u0938"
    ],
    "name:hrv_x_preferred":[
        "Los Lagos"
    ],
    "name:hun_x_preferred":[
        "Los Lagos"
    ],
    "name:ind_x_preferred":[
        "Los Lagos"
    ],
    "name:ita_x_preferred":[
        "Los Lagos"
    ],
    "name:jpn_x_preferred":[
        "\u30ed\u30b9\u30e9\u30b4\u30b9"
    ],
    "name:nld_x_preferred":[
        "Los Lagos"
    ],
    "name:rus_x_preferred":[
        "\u041b\u043e\u0441-\u041b\u0430\u0433\u043e\u0441"
    ],
    "name:sco_x_preferred":[
        "Los Lagos"
    ],
    "name:slk_x_preferred":[
        "Los Lagos"
    ],
    "name:spa_x_preferred":[
        "Los Llanos"
    ],
    "name:spa_x_variant":[
        "Los Lagos"
    ],
    "name:srp_x_preferred":[
        "\u041b\u043e\u0441 \u041b\u0430\u0433\u043e\u0441"
    ],
    "name:swe_x_preferred":[
        "Los Lagos"
    ],
    "name:tur_x_preferred":[
        "Los Lagos"
    ],
    "name:ukr_x_preferred":[
        "\u041b\u043e\u0441-\u041b\u0430\u0433\u043e\u0441"
    ],
    "name:urd_x_preferred":[
        "\u0644\u0627\u0633 \u0644\u0627\u06af\u0648\u0633"
    ],
    "name:vie_x_preferred":[
        "Los Lagos"
    ],
    "qs_pg:aaroncc":"MX",
    "qs_pg:gn_country":"MX",
    "qs_pg:gn_fcode":"PPL",
    "qs_pg:gn_pop":0,
    "qs_pg:name":"Los Lagos",
    "qs_pg:name_adm0":"M\u00e9xico",
    "qs_pg:name_adm1":"Coahuila de Zaragoza",
    "qs_pg:photos":1,
    "qs_pg:photos_1k":1,
    "qs_pg:photos_9k":1,
    "qs_pg:photos_9r":1,
    "qs_pg:photos_all":1,
    "qs_pg:photos_sr":1,
    "qs_pg:pop_sr":0,
    "qs_pg:qs_pg_placetype":"neighbourhood",
    "qs_pg:qs_pg_placetype_gp":"Suburb",
    "qs_pg:woe_adm0":23424900,
    "woe:adm0_id":23424900,
    "woe:name_adm0":"M\u00e9xico",
    "woe:name_adm1":"Coahuila de Zaragoza",
    "woe:placetype":"Suburb",
    "wof:name":"Los Lagos",
    "wof:placetype":"neighbourhood"
},
  "geometry": {"coordinates":[-100.79952,25.30576],"type":"Point"}
}