{
  "type": "Feature",
  "properties": {
    "gn:admin1_code":"31",
    "gn:admin2_code":"16",
    "gn:asciiname":"Xno-Huayab",
    "gn:country_code":"MX",
    "gn:dem":35,
    "gn:feature_class":"P",
    "gn:feature_code":"PPL",
    "gn:name":"Xno-Huayab",
    "gn:population":38,
    "gn:timezone":"America/Merida",
    "iso:country":"MX",
    "wof:name":"Xno-Huayab",
    "wof:placetype":"locality",
    "wof:population":38
},
  "geometry": {"coordinates":[-88.98917,20.18667],"type":"Point"}
}