{
  "type": "Feature",
  "properties": {
    "gn:admin1_code":"6",
    "gn:admin2_code":"27.0",
    "gn:asciiname":"Rosanachi",
    "gn:country_code":"MX",
    "gn:dem":2219,
    "gn:feature_class":"P",
    "gn:feature_code":"PPL",
    "gn:name":"Rosanachi",
    "gn:population":7,
    "gn:timezone":"America/Chihuahua",
    "iso:country":"MX",
    "wof:name":"Rosanachi",
    "wof:placetype":"locality",
    "wof:population":7
},
  "geometry": {"coordinates":[-107.23157999999999,27.5802],"type":"Point"}
}