{
  "type": "Feature",
  "properties": {
    "gn:admin1_code":"6",
    "gn:admin2_code":"66",
    "gn:asciiname":"Bacabochi",
    "gn:country_code":"MX",
    "gn:dem":1789,
    "gn:feature_class":"P",
    "gn:feature_code":"PPL",
    "gn:name":"Bacabochi",
    "gn:population":11,
    "gn:timezone":"America/Chihuahua",
    "iso:country":"MX",
    "wof:name":"Bacabochi",
    "wof:placetype":"locality",
    "wof:population":11
},
  "geometry": {"coordinates":[-108.18438,27.75325],"type":"Point"}
}