{
  "type": "Feature",
  "properties": {
    "gn:admin1_code":"4",
    "gn:admin2_code":"11.0",
    "gn:asciiname":"Las Tres Estrellas",
    "gn:country_code":"MX",
    "gn:dem":114,
    "gn:feature_class":"P",
    "gn:feature_code":"PPL",
    "gn:name":"Las Tres Estrellas",
    "gn:population":8,
    "gn:timezone":"America/Merida",
    "iso:country":"MX",
    "wof:name":"Las Tres Estrellas",
    "wof:placetype":"locality",
    "wof:population":8
},
  "geometry": {"coordinates":[-90.37944,17.94639],"type":"Point"}
}