{
  "type": "Feature",
  "properties": {
    "gn:admin1_code":"27",
    "gn:admin2_code":"4.0",
    "gn:asciiname":"Jolochero 2da. Seccion",
    "gn:country_code":"MX",
    "gn:dem":4,
    "gn:feature_class":"P",
    "gn:feature_code":"PPL",
    "gn:name":"Jolochero 2da. Secci\u00f3n",
    "gn:population":1303,
    "gn:timezone":"America/Mexico_City",
    "iso:country":"MX",
    "name:und_x_variant":[
        "Jolochero 2da. Secci\u00f3n"
    ],
    "wof:name":"Jolochero 2da. Seccion",
    "wof:placetype":"locality",
    "wof:population":1303
},
  "geometry": {"coordinates":[-92.79833000000001,18.12],"type":"Point"}
}