{
  "type": "Feature",
  "properties": {
    "gn:admin1_code":"11",
    "gn:admin2_code":"39.0",
    "gn:asciiname":"El Cerrito (FOVISSSTE)",
    "gn:country_code":"MX",
    "gn:dem":1797,
    "gn:feature_class":"P",
    "gn:feature_code":"PPL",
    "gn:name":"El Cerrito (FOVISSSTE)",
    "gn:population":470,
    "gn:timezone":"America/Mexico_City",
    "iso:country":"MX",
    "wof:name":"El Cerrito (FOVISSSTE)",
    "wof:placetype":"locality",
    "wof:population":470
},
  "geometry": {"coordinates":[-100.74666999999999,20.29222],"type":"Point"}
}