{
  "type": "Feature",
  "properties": {
    "gn:admin1_code":"2",
    "gn:admin2_code":"2.0",
    "gn:asciiname":"Rancho Castillo",
    "gn:country_code":"MX",
    "gn:dem":14,
    "gn:feature_class":"P",
    "gn:feature_code":"PPL",
    "gn:name":"Rancho Castillo",
    "gn:population":5,
    "gn:timezone":"America/Tijuana",
    "iso:country":"MX",
    "wof:name":"Rancho Castillo",
    "wof:placetype":"locality",
    "wof:population":5
},
  "geometry": {"coordinates":[-115.16916999999999,32.6175],"type":"Point"}
}