{
  "type": "Feature",
  "properties": {
    "gn:admin1_code":"32",
    "gn:admin2_code":"57.0",
    "gn:asciiname":"La Puerta de Hierro",
    "gn:country_code":"MX",
    "gn:dem":2107,
    "gn:feature_class":"P",
    "gn:feature_code":"PPL",
    "gn:name":"La Puerta de Hierro",
    "gn:population":0,
    "gn:timezone":"America/Mexico_City",
    "iso:country":"MX",
    "name:spa_x_preferred":[
        "La Puerta de Hierro"
    ],
    "wof:name":"La Puerta de Hierro",
    "wof:placetype":"locality"
},
  "geometry": {"coordinates":[-102.30488,22.69236],"type":"Point"}
}