{
  "type": "Feature",
  "properties": {
    "gn:admin1_code":"10.0",
    "gn:admin2_code":"18.0",
    "gn:asciiname":"Cofradia",
    "gn:cc2":"MX",
    "gn:country_code":"MX",
    "gn:dem":1688,
    "gn:feature_class":"P",
    "gn:feature_code":"PPL",
    "gn:name":"Cofrad\u00eda",
    "gn:population":0,
    "gn:timezone":"America/Monterrey",
    "iso:country":"MX",
    "name:und_x_variant":[
        "La Cofrad\u00eda",
        "Cofrad\u00eda"
    ],
    "wof:name":"Cofradia",
    "wof:placetype":"locality"
},
  "geometry": {"coordinates":[-105.41667,25.86667000000001],"type":"Point"}
}