{
  "type": "Feature",
  "properties": {
    "gn:admin1_code":"5",
    "gn:admin2_code":"32.0",
    "gn:asciiname":"Jorge Robledo Lopez",
    "gn:country_code":"MX",
    "gn:dem":173,
    "gn:feature_class":"P",
    "gn:feature_code":"PPL",
    "gn:name":"Jorge Robledo L\u00f3pez",
    "gn:population":5,
    "gn:timezone":"America/Mexico_City",
    "iso:country":"MX",
    "name:und_x_variant":[
        "Jorge Robledo L\u00f3pez"
    ],
    "wof:name":"Jorge Robledo Lopez",
    "wof:placetype":"locality",
    "wof:population":5
},
  "geometry": {"coordinates":[-92.62806,15.31972],"type":"Point"}
}