{
  "type": "Feature",
  "properties": {
    "gn:admin1_code":"24",
    "gn:admin2_code":"39",
    "gn:asciiname":"La Cruz Chica",
    "gn:country_code":"MX",
    "gn:dem":149,
    "gn:feature_class":"P",
    "gn:feature_code":"PPL",
    "gn:name":"La Cruz Chica",
    "gn:population":14,
    "gn:timezone":"America/Mexico_City",
    "iso:country":"MX",
    "wof:name":"La Cruz Chica",
    "wof:placetype":"locality",
    "wof:population":14
},
  "geometry": {"coordinates":[-98.84028000000001,21.57556],"type":"Point"}
}