{
  "type": "Feature",
  "properties": {
    "gn:admin1_code":"20",
    "gn:admin2_code":"135",
    "gn:asciiname":"Rancho el Conejo",
    "gn:country_code":"MX",
    "gn:dem":1682,
    "gn:feature_class":"P",
    "gn:feature_code":"PPL",
    "gn:name":"Rancho el Conejo",
    "gn:population":42,
    "gn:timezone":"America/Mexico_City",
    "iso:country":"MX",
    "wof:name":"Rancho el Conejo",
    "wof:placetype":"locality",
    "wof:population":42
},
  "geometry": {"coordinates":[-96.86861,17.0925],"type":"Point"}
}