{
  "type": "Feature",
  "properties": {
    "gn:admin1_code":"18.0",
    "gn:admin2_code":"10.0",
    "gn:asciiname":"La Pinta",
    "gn:country_code":"MX",
    "gn:dem":12,
    "gn:feature_class":"P",
    "gn:feature_code":"PPL",
    "gn:name":"La Pinta",
    "gn:population":0,
    "gn:timezone":"America/Mazatlan",
    "iso:country":"MX",
    "name:spa_x_preferred":[
        "La Pinta"
    ],
    "wof:name":"La Pinta",
    "wof:placetype":"locality"
},
  "geometry": {"coordinates":[-105.267,21.99318],"type":"Point"}
}