{
  "type": "Feature",
  "properties": {
    "gn:admin1_code":"26.0",
    "gn:admin2_code":"42.0",
    "gn:asciiname":"Campo Bojorquez",
    "gn:country_code":"MX",
    "gn:dem":28,
    "gn:feature_class":"P",
    "gn:feature_code":"PPL",
    "gn:name":"Campo Boj\u00f3rquez",
    "gn:population":0,
    "gn:timezone":"America/Hermosillo",
    "iso:country":"MX",
    "name:spa_x_preferred":[
        "Campo Boj\u00f3rquez"
    ],
    "wof:name":"Campo Bojorquez",
    "wof:placetype":"locality"
},
  "geometry": {"coordinates":[-109.47874,26.92238],"type":"Point"}
}