{
  "type": "Feature",
  "properties": {
    "gn:admin1_code":"24",
    "gn:admin2_code":"15",
    "gn:asciiname":"El Entronque",
    "gn:country_code":"MX",
    "gn:dem":2034,
    "gn:feature_class":"P",
    "gn:feature_code":"PPL",
    "gn:name":"El Entronque",
    "gn:population":30,
    "gn:timezone":"America/Mexico_City",
    "iso:country":"MX",
    "wof:name":"El Entronque",
    "wof:placetype":"locality",
    "wof:population":30
},
  "geometry": {"coordinates":[-100.98333,23.21778],"type":"Point"}
}