{
  "type": "Feature",
  "properties": {
    "gn:admin1_code":"22",
    "gn:admin2_code":"2.0",
    "gn:asciiname":"Maguey Blanco",
    "gn:country_code":"MX",
    "gn:dem":1283,
    "gn:feature_class":"P",
    "gn:feature_code":"PPL",
    "gn:name":"Maguey Blanco",
    "gn:population":0,
    "gn:timezone":"America/Mexico_City",
    "iso:country":"MX",
    "name:spa_x_preferred":[
        "Maguey Blanco"
    ],
    "wof:name":"Maguey Blanco",
    "wof:placetype":"locality"
},
  "geometry": {"coordinates":[-99.60082,21.26822],"type":"Point"}
}