{
  "type": "Feature",
  "properties": {
    "gn:admin1_code":"10.0",
    "gn:admin2_code":"3.0",
    "gn:asciiname":"Coneto de Indios",
    "gn:country_code":"MX",
    "gn:dem":2079,
    "gn:feature_class":"P",
    "gn:feature_code":"PPL",
    "gn:name":"Coneto de Indios",
    "gn:population":0,
    "gn:timezone":"America/Monterrey",
    "iso:country":"MX",
    "name:spa_x_preferred":[
        "Coneto de Indios"
    ],
    "wof:name":"Coneto de Indios",
    "wof:placetype":"locality"
},
  "geometry": {"coordinates":[-104.8219,25.04506],"type":"Point"}
}