{
  "type": "Feature",
  "properties": {
    "gn:admin1_code":"20.0",
    "gn:asciiname":"Agua Palmera",
    "gn:country_code":"MX",
    "gn:dem":1893,
    "gn:feature_class":"P",
    "gn:feature_code":"PPL",
    "gn:name":"Agua Palmera",
    "gn:population":0,
    "gn:timezone":"America/Mexico_City",
    "iso:country":"MX",
    "name:spa_x_preferred":[
        "Agua Palmera"
    ],
    "wof:name":"Agua Palmera",
    "wof:placetype":"locality"
},
  "geometry": {"coordinates":[-96.79398999999999,18.14451],"type":"Point"}
}