{
  "type": "Feature",
  "properties": {
    "gn:admin1_code":"21",
    "gn:admin2_code":"194.0",
    "gn:asciiname":"Salsipuedes",
    "gn:country_code":"MX",
    "gn:dem":415,
    "gn:feature_class":"P",
    "gn:feature_code":"PPL",
    "gn:name":"Salsipuedes",
    "gn:population":8,
    "gn:timezone":"America/Mexico_City",
    "iso:country":"MX",
    "name:ceb_x_preferred":[
        "Salsipuedes"
    ],
    "name:spa_x_preferred":[
        "Salsipuedes"
    ],
    "name:swe_x_preferred":[
        "Salsipuedes"
    ],
    "wof:name":"Salsipuedes",
    "wof:placetype":"locality",
    "wof:population":8
},
  "geometry": {"coordinates":[-97.76174,20.51823],"type":"Point"}
}