{
  "type": "Feature",
  "properties": {
    "gn:admin1_code":"16.0",
    "gn:admin2_code":"6.0",
    "gn:asciiname":"Matamoros",
    "gn:country_code":"MX",
    "gn:dem":307,
    "gn:feature_class":"P",
    "gn:feature_code":"PPL",
    "gn:name":"Matamoros",
    "gn:population":0,
    "gn:timezone":"America/Mexico_City",
    "iso:country":"MX",
    "name:spa_x_preferred":[
        "Matamoros"
    ],
    "wof:name":"Matamoros",
    "wof:placetype":"locality"
},
  "geometry": {"coordinates":[-102.37683,19.11678],"type":"Point"}
}