{
  "type": "Feature",
  "properties": {
    "gn:admin1_code":"10",
    "gn:admin2_code":"14.0",
    "gn:asciiname":"Tepetates",
    "gn:country_code":"MX",
    "gn:dem":1399,
    "gn:feature_class":"P",
    "gn:feature_code":"PPL",
    "gn:name":"Tepetates",
    "gn:population":0,
    "gn:timezone":"America/Monterrey",
    "iso:country":"MX",
    "name:spa_x_preferred":[
        "Tepetates"
    ],
    "wof:name":"Tepetates",
    "wof:placetype":"locality"
},
  "geometry": {"coordinates":[-104.85799,22.8167],"type":"Point"}
}