{
  "type": "Feature",
  "properties": {
    "gn:admin1_code":"28.0",
    "gn:admin2_code":"43.0",
    "gn:asciiname":"El Mirador",
    "gn:country_code":"MX",
    "gn:dem":113,
    "gn:feature_class":"P",
    "gn:feature_code":"PPL",
    "gn:name":"El Mirador",
    "gn:population":0,
    "gn:timezone":"America/Monterrey",
    "iso:country":"MX",
    "name:spa_x_preferred":[
        "El Mirador"
    ],
    "wof:name":"El Mirador",
    "wof:placetype":"locality"
},
  "geometry": {"coordinates":[-98.98067,23.01477],"type":"Point"}
}