{
  "type": "Feature",
  "properties": {
    "gn:admin1_code":"30.0",
    "gn:asciiname":"Puente de la Llorona",
    "gn:country_code":"MX",
    "gn:dem":30,
    "gn:feature_class":"P",
    "gn:feature_code":"PPL",
    "gn:name":"Puente de la Llorona",
    "gn:population":0,
    "gn:timezone":"America/Mexico_City",
    "iso:country":"MX",
    "name:spa_x_preferred":[
        "Puente de la Llorona"
    ],
    "wof:name":"Puente de la Llorona",
    "wof:placetype":"locality"
},
  "geometry": {"coordinates":[-94.50756,17.79128],"type":"Point"}
}