{
  "type": "Feature",
  "properties": {
    "gn:admin1_code":"7.0",
    "gn:admin2_code":"14.0",
    "gn:asciiname":"Los Bigotones",
    "gn:country_code":"MX",
    "gn:dem":286,
    "gn:feature_class":"P",
    "gn:feature_code":"PPL",
    "gn:name":"Los Bigotones",
    "gn:population":0,
    "gn:timezone":"America/Monterrey",
    "iso:country":"MX",
    "name:und_x_variant":[
        "Bigotes"
    ],
    "wof:name":"Los Bigotones",
    "wof:placetype":"locality"
},
  "geometry": {"coordinates":[-100.81795,29.08819],"type":"Point"}
}