{
  "type": "Feature",
  "properties": {
    "iso:country":"MX",
    "name:spa_x_preferred":[
        "Tequila Centro"
    ],
    "qs:gn_adm0_cc":"MX",
    "qs:gn_local":3981885,
    "qs:gn_nam_loc":"tequila",
    "qs:gn_namadm1":"14",
    "qs:local_max":467,
    "qs:local_sum":1328,
    "qs:localhoods":4,
    "qs:name":"Tequila Centro",
    "qs:name_adm0":"M\u00e9xico",
    "qs:name_adm1":"Jalisco",
    "qs:name_adm2":"Tequila",
    "qs:name_local":"Tequila",
    "qs:photo_max":174,
    "qs:photo_sum":467,
    "qs:placetype":"Suburb",
    "qs:quad_count":7,
    "qs:woe_adm0":23424900,
    "qs:woe_adm1":2346277,
    "qs:woe_adm2":12600288,
    "qs:woe_lau":0,
    "qs:woe_local":149029,
    "qs:woe_ver":"7.10.0",
    "wof:lang":[
        "spa"
    ],
    "wof:name":"Tequila Centro",
    "wof:placetype":"neighbourhood"
},
  "geometry": {"coordinates":[-103.839212,20.882798],"type":"Point"}
}