{
  "type": "Feature",
  "properties": {
    "gn:admin1_code":"6",
    "gn:admin2_code":"1.0",
    "gn:asciiname":"Santa Elisa",
    "gn:country_code":"MX",
    "gn:dem":1222,
    "gn:feature_class":"P",
    "gn:feature_code":"PPL",
    "gn:name":"Santa Elisa",
    "gn:population":5,
    "gn:timezone":"America/Chihuahua",
    "iso:country":"MX",
    "wof:name":"Santa Elisa",
    "wof:placetype":"locality",
    "wof:population":5
},
  "geometry": {"coordinates":[-106.55052999999999,30.4207],"type":"Point"}
}