{
  "type": "Feature",
  "properties": {
    "gn:admin1_code":"16",
    "gn:admin2_code":"19.0",
    "gn:asciiname":"El Fresnito",
    "gn:country_code":"MX",
    "gn:dem":1907,
    "gn:feature_class":"P",
    "gn:feature_code":"PPL",
    "gn:name":"El Fresnito",
    "gn:population":53,
    "gn:timezone":"America/Mexico_City",
    "iso:country":"MX",
    "wof:name":"El Fresnito",
    "wof:placetype":"locality",
    "wof:population":53
},
  "geometry": {"coordinates":[-102.69889000000001,19.70917],"type":"Point"}
}