{
  "type": "Feature",
  "properties": {
    "gn:admin1_code":"8",
    "gn:admin2_code":"7.0",
    "gn:asciiname":"Colomitos",
    "gn:country_code":"MX",
    "gn:dem":304,
    "gn:feature_class":"P",
    "gn:feature_code":"PPL",
    "gn:name":"Colomitos",
    "gn:population":5,
    "gn:timezone":"America/Mexico_City",
    "iso:country":"MX",
    "wof:name":"Colomitos",
    "wof:placetype":"locality",
    "wof:population":5
},
  "geometry": {"coordinates":[-104.38444,19.22861],"type":"Point"}
}