{
  "type": "Feature",
  "properties": {
    "gn:admin1_code":"11",
    "gn:admin2_code":"34.0",
    "gn:asciiname":"Pena Colorada",
    "gn:country_code":"MX",
    "gn:dem":1601,
    "gn:feature_class":"P",
    "gn:feature_code":"PPL",
    "gn:name":"Pe\u00f1a Colorada",
    "gn:population":124,
    "gn:timezone":"America/Mexico_City",
    "iso:country":"MX",
    "name:und_x_variant":[
        "Pe\u00f1a Colorada"
    ],
    "wof:name":"Pena Colorada",
    "wof:placetype":"locality",
    "wof:population":124
},
  "geometry": {"coordinates":[-100.07472,21.15194],"type":"Point"}
}