{
  "type": "Feature",
  "properties": {
    "gn:admin1_code":"28",
    "gn:admin2_code":"33.0",
    "gn:asciiname":"Brecha 116 entre Kilometro 109 y 110",
    "gn:country_code":"MX",
    "gn:dem":28,
    "gn:feature_class":"P",
    "gn:feature_code":"PPL",
    "gn:name":"Brecha 116 entre Kil\u00f3metro 109 y 110",
    "gn:population":8,
    "gn:timezone":"America/Monterrey",
    "iso:country":"MX",
    "name:und_x_variant":[
        "Brecha 116 entre Kil\u00f3metro 109 y 110"
    ],
    "wof:name":"Brecha 116 entre Kilometro 109 y 110",
    "wof:placetype":"locality",
    "wof:population":8
},
  "geometry": {"coordinates":[-98.04833000000001,25.66083],"type":"Point"}
}