{
  "type": "Feature",
  "properties": {
    "gn:admin1_code":"25",
    "gn:asciiname":"La Canita",
    "gn:country_code":"MX",
    "gn:dem":617,
    "gn:feature_class":"P",
    "gn:feature_code":"PPL",
    "gn:name":"La Ca\u00f1ita",
    "gn:population":0,
    "gn:timezone":"America/Mazatlan",
    "iso:country":"MX",
    "name:spa_x_preferred":[
        "La Ca\u00f1ita"
    ],
    "wof:name":"La Canita",
    "wof:placetype":"locality"
},
  "geometry": {"coordinates":[-107.85898,26.30866],"type":"Point"}
}