{
  "type": "Feature",
  "properties": {
    "gn:admin1_code":"30",
    "gn:admin2_code":"170.0",
    "gn:asciiname":"Chila de Enriquez",
    "gn:country_code":"MX",
    "gn:dem":1236,
    "gn:feature_class":"P",
    "gn:feature_code":"PPL",
    "gn:name":"Chila de Enr\u00edquez",
    "gn:population":250,
    "gn:timezone":"America/Mexico_City",
    "iso:country":"MX",
    "name:und_x_variant":[
        "Chila de Enr\u00edquez"
    ],
    "wof:name":"Chila de Enriquez",
    "wof:placetype":"locality",
    "wof:population":250
},
  "geometry": {"coordinates":[-98.3425,20.57583],"type":"Point"}
}