{
  "type": "Feature",
  "properties": {
    "gn:admin1_code":"4",
    "gn:admin2_code":"6.0",
    "gn:asciiname":"El Temporal Cinco",
    "gn:country_code":"MX",
    "gn:dem":135,
    "gn:feature_class":"P",
    "gn:feature_code":"PPL",
    "gn:name":"El Temporal Cinco",
    "gn:population":224,
    "gn:timezone":"America/Merida",
    "iso:country":"MX",
    "wof:name":"El Temporal Cinco",
    "wof:placetype":"locality",
    "wof:population":224
},
  "geometry": {"coordinates":[-89.74472,19.53194],"type":"Point"}
}