{
  "type": "Feature",
  "properties": {
    "gn:admin1_code":"5",
    "gn:admin2_code":"20",
    "gn:asciiname":"El Cairo",
    "gn:country_code":"MX",
    "gn:dem":664,
    "gn:feature_class":"P",
    "gn:feature_code":"PPL",
    "gn:name":"El Cairo",
    "gn:population":18,
    "gn:timezone":"America/Mexico_City",
    "iso:country":"MX",
    "wof:name":"El Cairo",
    "wof:placetype":"locality",
    "wof:population":18
},
  "geometry": {"coordinates":[-92.81167000000001,15.91778],"type":"Point"}
}