{
  "type": "Feature",
  "properties": {
    "gn:country":"MX",
    "gn:fcode":"PPL",
    "gn:population":12278,
    "iso:country":"MX",
    "name:und_x_variant":[
        "Soledad de Doblado"
    ],
    "qs_pg:aaroncc":"MX",
    "qs_pg:gn_country":"MX",
    "qs_pg:gn_fcode":"PPL",
    "qs_pg:gn_pop":12278,
    "qs_pg:name":"Soledad de Doblado Centro",
    "qs_pg:name_adm0":"M\u00e9xico",
    "qs_pg:name_adm1":"Veracruz-Llave",
    "qs_pg:photos":1,
    "qs_pg:photos_1k":1,
    "qs_pg:photos_9k":1,
    "qs_pg:photos_9r":1,
    "qs_pg:photos_all":1,
    "qs_pg:photos_sr":1,
    "qs_pg:pop_sr":6,
    "qs_pg:qs_pg_placetype":"neighbourhood",
    "qs_pg:qs_pg_placetype_gp":"Suburb",
    "qs_pg:woe_adm0":23424900,
    "woe:adm0_id":23424900,
    "woe:name_adm0":"M\u00e9xico",
    "woe:name_adm1":"Veracruz-Llave",
    "woe:placetype":"Suburb",
    "wof:name":"Soledad de Doblado Centro",
    "wof:placetype":"neighbourhood",
    "wof:population":12278
},
  "geometry": {"coordinates":[-96.42113999999999,19.04582],"type":"Point"}
}