{
  "type": "Feature",
  "properties": {
    "gn:admin1_code":"7",
    "gn:admin2_code":"35.0",
    "gn:asciiname":"El Cedrito",
    "gn:country_code":"MX",
    "gn:dem":1127,
    "gn:feature_class":"P",
    "gn:feature_code":"PPL",
    "gn:name":"El Cedrito",
    "gn:population":0,
    "gn:timezone":"America/Monterrey",
    "iso:country":"MX",
    "name:spa_x_preferred":[
        "El Cedrito"
    ],
    "wof:name":"El Cedrito",
    "wof:placetype":"locality"
},
  "geometry": {"coordinates":[-103.39418000000001,25.58729],"type":"Point"}
}