{
  "type": "Feature",
  "properties": {
    "gn:admin1_code":"10",
    "gn:admin2_code":"15.0",
    "gn:asciiname":"Antonio Martinez P.",
    "gn:country_code":"MX",
    "gn:dem":1276,
    "gn:feature_class":"P",
    "gn:feature_code":"PPL",
    "gn:name":"Antonio Mart\u00ednez P.",
    "gn:population":7,
    "gn:timezone":"America/Monterrey",
    "iso:country":"MX",
    "name:und_x_variant":[
        "Antonio Mart\u00ednez P."
    ],
    "wof:name":"Antonio Martinez P.",
    "wof:placetype":"locality",
    "wof:population":7
},
  "geometry": {"coordinates":[-104.10921999999999,25.22],"type":"Point"}
}