{
  "type": "Feature",
  "properties": {
    "gn:admin1_code":"11.0",
    "gn:asciiname":"Las Cabanas de la Presa",
    "gn:country_code":"MX",
    "gn:dem":1855,
    "gn:feature_class":"P",
    "gn:feature_code":"PPL",
    "gn:name":"Las Caba\u00f1as de la Presa",
    "gn:population":0,
    "gn:timezone":"America/Mexico_City",
    "iso:country":"MX",
    "name:spa_x_preferred":[
        "Las Caba\u00f1as de la Presa"
    ],
    "wof:name":"Las Cabanas de la Presa",
    "wof:placetype":"locality"
},
  "geometry": {"coordinates":[-101.27041,20.8882],"type":"Point"}
}