{
  "type": "Feature",
  "properties": {
    "gn:admin1_code":"5",
    "gn:admin2_code":"47",
    "gn:asciiname":"Campanario San Rafael",
    "gn:country_code":"MX",
    "gn:dem":1683,
    "gn:feature_class":"P",
    "gn:feature_code":"PPL",
    "gn:name":"Campanario San Rafael",
    "gn:population":46,
    "gn:timezone":"America/Mexico_City",
    "iso:country":"MX",
    "wof:name":"Campanario San Rafael",
    "wof:placetype":"locality",
    "wof:population":46
},
  "geometry": {"coordinates":[-92.88833,17.14583],"type":"Point"}
}