{
  "type": "Feature",
  "properties": {
    "gn:admin1_code":"14",
    "gn:admin2_code":"53",
    "gn:asciiname":"Melo",
    "gn:country_code":"MX",
    "gn:dem":2063,
    "gn:feature_class":"P",
    "gn:feature_code":"PPL",
    "gn:name":"Melo",
    "gn:population":32,
    "gn:timezone":"America/Mexico_City",
    "iso:country":"MX",
    "wof:name":"Melo",
    "wof:placetype":"locality",
    "wof:population":32
},
  "geometry": {"coordinates":[-101.93722,21.50472],"type":"Point"}
}