{
  "type": "Feature",
  "properties": {
    "gn:admin1_code":"7",
    "gn:admin2_code":"30.0",
    "gn:asciiname":"Los Carteros",
    "gn:country_code":"MX",
    "gn:dem":1630,
    "gn:feature_class":"P",
    "gn:feature_code":"PPL",
    "gn:name":"Los Carteros",
    "gn:population":0,
    "gn:timezone":"America/Monterrey",
    "iso:country":"MX",
    "name:spa_x_preferred":[
        "Los Carteros"
    ],
    "wof:name":"Los Carteros",
    "wof:placetype":"locality"
},
  "geometry": {"coordinates":[-100.95348,25.41167],"type":"Point"}
}