{
  "type": "Feature",
  "properties": {
    "iso:country":"MX",
    "name:ceb_x_preferred":[
        "La Loma"
    ],
    "name:deu_x_preferred":[
        "La Loma"
    ],
    "name:spa_x_preferred":[
        "La Loma"
    ],
    "name:srp_x_preferred":[
        "\u041b\u0430 \u041b\u043e\u043c\u0430"
    ],
    "name:swe_x_preferred":[
        "La Loma"
    ],
    "name:und_x_variant":[
        "Loma"
    ],
    "qs:gn_adm0_cc":"MX",
    "qs:gn_fcode":"PPL",
    "qs:gn_local":4005539,
    "qs:gn_nam_loc":"Guadalajara, Guadalajara, Jalisco, MX",
    "qs:gn_namadm1":"14",
    "qs:gn_name":"La Loma",
    "qs:local_max":6158,
    "qs:local_sum":19156,
    "qs:localhoods":41,
    "qs:name":"La Loma",
    "qs:name_adm0":"M\u00e9xico",
    "qs:name_adm1":"Jalisco",
    "qs:name_adm2":"Guadalajara",
    "qs:name_local":"Guadalajara",
    "qs:photo_max":24,
    "qs:photo_sum":24,
    "qs:placetype":"Suburb",
    "qs:quad_count":1,
    "qs:woe_adm0":23424900,
    "qs:woe_adm1":2346277,
    "qs:woe_adm2":12600236,
    "qs:woe_lau":0,
    "qs:woe_local":124162,
    "qs:woe_ver":"7.10.0",
    "wof:lang":[
        "spa"
    ],
    "wof:name":"La Loma",
    "wof:placetype":"neighbourhood"
},
  "geometry": {"coordinates":[-103.31268300000001,20.650776],"type":"Point"}
}