{
  "type": "Feature",
  "properties": {
    "gn:admin1_code":"6.0",
    "gn:admin2_code":"27.0",
    "gn:asciiname":"Paraje El Madrono",
    "gn:country_code":"MX",
    "gn:dem":2350,
    "gn:feature_class":"P",
    "gn:feature_code":"PPL",
    "gn:name":"Paraje El Madro\u00f1o",
    "gn:population":0,
    "gn:timezone":"America/Chihuahua",
    "iso:country":"MX",
    "name:spa_x_preferred":[
        "Paraje El Madro\u00f1o"
    ],
    "name:und_x_variant":[
        "Rancho El Madro\u00f1o"
    ],
    "wof:name":"Paraje El Madrono",
    "wof:placetype":"locality"
},
  "geometry": {"coordinates":[-106.9333,27.07875],"type":"Point"}
}