{
  "type": "Feature",
  "properties": {
    "gn:admin1_code":"7.0",
    "gn:admin2_code":"6.0",
    "gn:asciiname":"San Vicente (El Coyote)",
    "gn:country_code":"MX",
    "gn:dem":896,
    "gn:feature_class":"P",
    "gn:feature_code":"PPL",
    "gn:name":"San Vicente (El Coyote)",
    "gn:population":3,
    "gn:timezone":"America/Monterrey",
    "iso:country":"MX",
    "name:spa_x_preferred":[
        "El Coyote"
    ],
    "wof:name":"San Vicente (El Coyote)",
    "wof:placetype":"locality",
    "wof:population":3
},
  "geometry": {"coordinates":[-101.32641,26.67003],"type":"Point"}
}