{
  "type": "Feature",
  "properties": {
    "gn:admin1_code":"5",
    "gn:admin2_code":"46.0",
    "gn:asciiname":"Mazatan",
    "gn:country_code":"MX",
    "gn:dem":541,
    "gn:feature_class":"P",
    "gn:feature_code":"PPL",
    "gn:name":"Mazat\u00e1n",
    "gn:population":4,
    "gn:timezone":"America/Mexico_City",
    "iso:country":"MX",
    "name:und_x_variant":[
        "Mazat\u00e1n"
    ],
    "wof:name":"Mazatan",
    "wof:placetype":"locality",
    "wof:population":4
},
  "geometry": {"coordinates":[-93.65722,16.69806],"type":"Point"}
}