{
  "type": "Feature",
  "properties": {
    "gn:admin1_code":"26.0",
    "gn:admin2_code":"5.0",
    "gn:asciiname":"El Jimachi",
    "gn:country_code":"MX",
    "gn:dem":483,
    "gn:feature_class":"P",
    "gn:feature_code":"PPL",
    "gn:name":"El Jimachi",
    "gn:population":0,
    "gn:timezone":"America/Hermosillo",
    "iso:country":"MX",
    "name:spa_x_preferred":[
        "El Jimachi"
    ],
    "wof:name":"El Jimachi",
    "wof:placetype":"locality"
},
  "geometry": {"coordinates":[-109.176,28.96398],"type":"Point"}
}