{
  "type": "Feature",
  "properties": {
    "gn:admin1_code":"6",
    "gn:admin2_code":"32.0",
    "gn:asciiname":"Animas de Abajo",
    "gn:country_code":"MX",
    "gn:dem":1676,
    "gn:feature_class":"P",
    "gn:feature_code":"PPL",
    "gn:name":"\u00c1nimas de Abajo",
    "gn:population":0,
    "gn:timezone":"America/Chihuahua",
    "iso:country":"MX",
    "name:spa_x_preferred":[
        "\u00c1nimas de Abajo"
    ],
    "name:spa_x_variant":[
        "Las \u00c1nimas de Abajo"
    ],
    "name:und_x_variant":[
        "Rancho Las Animas"
    ],
    "wof:name":"Animas de Abajo",
    "wof:placetype":"locality"
},
  "geometry": {"coordinates":[-105.63737,26.98743],"type":"Point"}
}