{
  "type": "Feature",
  "properties": {
    "gn:admin1_code":"6.0",
    "gn:admin2_code":"29.0",
    "gn:asciiname":"La Colorada",
    "gn:country_code":"MX",
    "gn:dem":2578,
    "gn:feature_class":"P",
    "gn:feature_code":"PPL",
    "gn:name":"La Colorada",
    "gn:population":0,
    "gn:timezone":"America/Chihuahua",
    "iso:country":"MX",
    "name:ceb_x_preferred":[
        "La Colorada"
    ],
    "name:deu_x_preferred":[
        "La Colorada"
    ],
    "name:ita_x_preferred":[
        "La Colorada"
    ],
    "name:spa_x_preferred":[
        "La Colorada"
    ],
    "name:swe_x_preferred":[
        "La Colorada"
    ],
    "wof:name":"La Colorada",
    "wof:placetype":"locality"
},
  "geometry": {"coordinates":[-106.59002,26.28199],"type":"Point"}
}