{
  "type": "Feature",
  "properties": {
    "gn:admin1_code":"12.0",
    "gn:asciiname":"Kilometro Treinta y Nueve",
    "gn:country_code":"MX",
    "gn:dem":411,
    "gn:feature_class":"P",
    "gn:feature_code":"PPL",
    "gn:name":"Kil\u00f3metro Treinta y Nueve",
    "gn:population":0,
    "gn:timezone":"America/Mexico_City",
    "iso:country":"MX",
    "name:spa_x_preferred":[
        "Kil\u00f3metro Treinta y Nueve"
    ],
    "wof:name":"Kilometro Treinta y Nueve",
    "wof:placetype":"locality"
},
  "geometry": {"coordinates":[-99.77914,17.04342999999999],"type":"Point"}
}