{
  "type": "Feature",
  "properties": {
    "gn:admin1_code":"28.0",
    "gn:admin2_code":"7.0",
    "gn:asciiname":"Los Ebanitos",
    "gn:country_code":"MX",
    "gn:dem":88,
    "gn:feature_class":"P",
    "gn:feature_code":"PPL",
    "gn:name":"Los Ebanitos",
    "gn:population":0,
    "gn:timezone":"America/Monterrey",
    "iso:country":"MX",
    "name:spa_x_preferred":[
        "Los Ebanitos"
    ],
    "wof:name":"Los Ebanitos",
    "wof:placetype":"locality"
},
  "geometry": {"coordinates":[-98.98157999999999,26.11796],"type":"Point"}
}