{
  "type": "Feature",
  "properties": {
    "gn:admin1_code":"16",
    "gn:admin2_code":"10",
    "gn:asciiname":"Cobano de Aguacola",
    "gn:country_code":"MX",
    "gn:dem":532,
    "gn:feature_class":"P",
    "gn:feature_code":"PPL",
    "gn:name":"C\u00f3bano de Aguacola",
    "gn:population":34,
    "gn:timezone":"America/Mexico_City",
    "iso:country":"MX",
    "name:und_x_variant":[
        "C\u00f3bano de Aguacola"
    ],
    "wof:name":"Cobano de Aguacola",
    "wof:placetype":"locality",
    "wof:population":34
},
  "geometry": {"coordinates":[-102.07361,18.36139],"type":"Point"}
}