{
  "type": "Feature",
  "properties": {
    "iso:country":"MX",
    "name:cat_x_preferred":[
        "Agua Dulce"
    ],
    "name:ceb_x_preferred":[
        "Agua Dulce"
    ],
    "name:deu_x_preferred":[
        "Agua Dulce"
    ],
    "name:fra_x_preferred":[
        "Agua Dulce"
    ],
    "name:ita_x_preferred":[
        "Agua Dulce"
    ],
    "name:nld_x_preferred":[
        "Agua Dulce"
    ],
    "name:pol_x_preferred":[
        "Agua Dulce"
    ],
    "name:por_x_preferred":[
        "Agua Dulce"
    ],
    "name:rus_x_preferred":[
        "\u0410\u0433\u0443\u0430-\u0414\u0443\u043b\u044c\u0441\u0435"
    ],
    "name:swe_x_preferred":[
        "Agua Dulce"
    ],
    "name:ukr_x_preferred":[
        "\u0410\u0433\u0432\u0430-\u0414\u0443\u043b\u044c\u0441\u0435"
    ],
    "name:vie_x_preferred":[
        "Agua Dulce"
    ],
    "name:vol_x_preferred":[
        "Agua Dulce"
    ],
    "qs_pg:aaroncc":"MX",
    "qs_pg:name":"Agua Dulce",
    "qs_pg:name_adm0":"M\u00e9xico",
    "qs_pg:name_adm1":"Puebla",
    "qs_pg:photos":16,
    "qs_pg:photos_1k":3,
    "qs_pg:photos_9k":1,
    "qs_pg:photos_9r":1,
    "qs_pg:photos_all":16,
    "qs_pg:photos_sr":1,
    "qs_pg:pop_sr":0,
    "qs_pg:qs_pg_placetype":"neighbourhood",
    "qs_pg:qs_pg_placetype_gp":"Suburb",
    "qs_pg:woe_adm0":23424900,
    "woe:adm0_id":23424900,
    "woe:name_adm0":"M\u00e9xico",
    "woe:name_adm1":"Puebla",
    "woe:placetype":"Suburb",
    "wof:name":"Agua Dulce",
    "wof:placetype":"neighbourhood"
},
  "geometry": {"coordinates":[-97.59979199999999,20.075602],"type":"Point"}
}