{
  "type": "Feature",
  "properties": {
    "gn:admin1_code":"20",
    "gn:admin2_code":"265.0",
    "gn:asciiname":"Palo Colorado",
    "gn:country_code":"MX",
    "gn:dem":296,
    "gn:feature_class":"P",
    "gn:feature_code":"PPL",
    "gn:name":"Palo Colorado",
    "gn:population":263,
    "gn:timezone":"America/Mexico_City",
    "iso:country":"MX",
    "wof:name":"Palo Colorado",
    "wof:placetype":"locality",
    "wof:population":263
},
  "geometry": {"coordinates":[-94.70111,16.66417],"type":"Point"}
}