{
  "type": "Feature",
  "properties": {
    "gn:admin1_code":"30.0",
    "gn:admin2_code":"207.0",
    "gn:asciiname":"Nuevo Leon",
    "gn:country_code":"MX",
    "gn:dem":35,
    "gn:feature_class":"P",
    "gn:feature_code":"PPL",
    "gn:name":"Nuevo Le\u00f3n",
    "gn:population":0,
    "gn:timezone":"America/Mexico_City",
    "iso:country":"MX",
    "name:spa_x_preferred":[
        "Nuevo Le\u00f3n"
    ],
    "wof:name":"Nuevo Leon",
    "wof:placetype":"locality"
},
  "geometry": {"coordinates":[-96.17872,18.35245],"type":"Point"}
}