{
  "type": "Feature",
  "properties": {
    "gn:admin1_code":"30",
    "gn:admin2_code":"8",
    "gn:asciiname":"La Cascada",
    "gn:country_code":"MX",
    "gn:dem":2037,
    "gn:feature_class":"P",
    "gn:feature_code":"PPL",
    "gn:name":"La Cascada",
    "gn:population":28,
    "gn:timezone":"America/Mexico_City",
    "iso:country":"MX",
    "wof:name":"La Cascada",
    "wof:placetype":"locality",
    "wof:population":28
},
  "geometry": {"coordinates":[-97.11333,19.10278],"type":"Point"}
}