{
  "type": "Feature",
  "properties": {
    "gn:admin1_code":"12",
    "gn:admin2_code":"2",
    "gn:asciiname":"Totolzintla",
    "gn:country_code":"MX",
    "gn:dem":1191,
    "gn:feature_class":"P",
    "gn:feature_code":"PPL",
    "gn:name":"Totolzintla",
    "gn:population":50,
    "gn:timezone":"America/Mexico_City",
    "iso:country":"MX",
    "wof:name":"Totolzintla",
    "wof:placetype":"locality",
    "wof:population":50
},
  "geometry": {"coordinates":[-99.02077,17.77148],"type":"Point"}
}