{
  "type": "Feature",
  "properties": {
    "gn:admin1_code":"10.0",
    "gn:admin2_code":"35.0",
    "gn:asciiname":"La Mesa Redondeada",
    "gn:country_code":"MX",
    "gn:dem":2605,
    "gn:feature_class":"P",
    "gn:feature_code":"PPL",
    "gn:name":"La Mesa Redondeada",
    "gn:population":0,
    "gn:timezone":"America/Monterrey",
    "iso:country":"MX",
    "name:spa_x_preferred":[
        "La Mesa Redondeada"
    ],
    "wof:name":"La Mesa Redondeada",
    "wof:placetype":"locality"
},
  "geometry": {"coordinates":[-106.28185000000001,25.53279],"type":"Point"}
}