{
  "type": "Feature",
  "properties": {
    "gn:admin1_code":"16",
    "gn:admin2_code":"51",
    "gn:asciiname":"Izote",
    "gn:country_code":"MX",
    "gn:dem":1992,
    "gn:feature_class":"P",
    "gn:feature_code":"PPL",
    "gn:name":"Izote",
    "gn:population":36,
    "gn:timezone":"America/Mexico_City",
    "iso:country":"MX",
    "wof:name":"Izote",
    "wof:placetype":"locality",
    "wof:population":36
},
  "geometry": {"coordinates":[-103.01694000000001,20.12056],"type":"Point"}
}