{
  "type": "Feature",
  "properties": {
    "gn:admin1_code":"6.0",
    "gn:admin2_code":"18.0",
    "gn:asciiname":"El Tascate",
    "gn:country_code":"MX",
    "gn:dem":2143,
    "gn:feature_class":"P",
    "gn:feature_code":"PPL",
    "gn:name":"El T\u00e1scate",
    "gn:population":67,
    "gn:timezone":"America/Chihuahua",
    "iso:country":"MX",
    "wof:name":"El Tascate",
    "wof:placetype":"locality",
    "wof:population":67
},
  "geometry": {"coordinates":[-106.947,28.09881],"type":"Point"}
}