{
  "type": "Feature",
  "properties": {
    "gn:admin1_code":"6.0",
    "gn:asciiname":"Tortuguillas",
    "gn:country_code":"MX",
    "gn:dem":1877,
    "gn:feature_class":"P",
    "gn:feature_code":"PPL",
    "gn:name":"Tortuguillas",
    "gn:population":0,
    "gn:timezone":"America/Chihuahua",
    "iso:country":"MX",
    "name:spa_x_preferred":[
        "Tortuguillas"
    ],
    "wof:name":"Tortuguillas",
    "wof:placetype":"locality"
},
  "geometry": {"coordinates":[-105.95672,26.96076],"type":"Point"}
}