{
  "type": "Feature",
  "properties": {
    "gn:admin1_code":"16",
    "gn:admin2_code":"71.0",
    "gn:asciiname":"El Fresno de Guadalupe",
    "gn:country_code":"MX",
    "gn:dem":2003,
    "gn:feature_class":"P",
    "gn:feature_code":"PPL",
    "gn:name":"El Fresno de Guadalupe",
    "gn:population":53,
    "gn:timezone":"America/Mexico_City",
    "iso:country":"MX",
    "wof:name":"El Fresno de Guadalupe",
    "wof:placetype":"locality",
    "wof:population":53
},
  "geometry": {"coordinates":[-101.45694,20.08639],"type":"Point"}
}