{
  "type": "Feature",
  "properties": {
    "gn:admin1_code":"14",
    "gn:admin2_code":"61",
    "gn:asciiname":"Los Olotes",
    "gn:country_code":"MX",
    "gn:dem":1847,
    "gn:feature_class":"P",
    "gn:feature_code":"PPL",
    "gn:name":"Los Olotes",
    "gn:population":33,
    "gn:timezone":"America/Mexico_City",
    "iso:country":"MX",
    "wof:name":"Los Olotes",
    "wof:placetype":"locality",
    "wof:population":33
},
  "geometry": {"coordinates":[-104.12444000000001,22.08083],"type":"Point"}
}