{
  "type": "Feature",
  "properties": {
    "gn:admin1_code":"3.0",
    "gn:admin2_code":"2.0",
    "gn:asciiname":"Acueducto Pacifico Norte",
    "gn:country_code":"MX",
    "gn:dem":34,
    "gn:feature_class":"P",
    "gn:feature_code":"PPL",
    "gn:name":"Acueducto Pacifico Norte",
    "gn:population":0,
    "gn:timezone":"America/Mazatlan",
    "iso:country":"MX",
    "name:spa_x_preferred":[
        "Acueducto Pacifico Norte"
    ],
    "wof:name":"Acueducto Pacifico Norte",
    "wof:placetype":"locality"
},
  "geometry": {"coordinates":[-113.72709999999999,27.51111],"type":"Point"}
}