{
  "type": "Feature",
  "properties": {
    "gn:admin1_code":"15",
    "gn:admin2_code":"40.0",
    "gn:asciiname":"San Alejo",
    "gn:country_code":"MX",
    "gn:dem":1851,
    "gn:feature_class":"P",
    "gn:feature_code":"PPL",
    "gn:name":"San Alejo",
    "gn:population":0,
    "gn:timezone":"America/Mexico_City",
    "iso:country":"MX",
    "name:spa_x_preferred":[
        "San Alejo"
    ],
    "wof:name":"San Alejo",
    "wof:placetype":"locality"
},
  "geometry": {"coordinates":[-99.72922,18.83857],"type":"Point"}
}