{
  "type": "Feature",
  "properties": {
    "gn:admin1_code":"30",
    "gn:admin2_code":"90.0",
    "gn:asciiname":"El Pinonal",
    "gn:country_code":"MX",
    "gn:dem":34,
    "gn:feature_class":"P",
    "gn:feature_code":"PPL",
    "gn:name":"El Pi\u00f1onal",
    "gn:population":384,
    "gn:timezone":"America/Mexico_City",
    "iso:country":"MX",
    "name:und_x_variant":[
        "El Pi\u00f1onal"
    ],
    "wof:name":"El Pinonal",
    "wof:placetype":"locality",
    "wof:population":384
},
  "geometry": {"coordinates":[-96.29806000000001,19.0175],"type":"Point"}
}