{
  "type": "Feature",
  "properties": {
    "gn:admin1_code":"2.0",
    "gn:admin2_code":"1.0",
    "gn:asciiname":"Navarro",
    "gn:country_code":"MX",
    "gn:dem":737,
    "gn:feature_class":"P",
    "gn:feature_code":"PPL",
    "gn:name":"Navarro",
    "gn:population":0,
    "gn:timezone":"America/Tijuana",
    "iso:country":"MX",
    "name:arg_x_preferred":[
        "Navarro"
    ],
    "name:ast_x_preferred":[
        "Navarro"
    ],
    "name:cat_x_preferred":[
        "Navarro"
    ],
    "name:ceb_x_preferred":[
        "Navarro"
    ],
    "name:ces_x_preferred":[
        "Navarro"
    ],
    "name:deu_x_preferred":[
        "Navarro"
    ],
    "name:fin_x_preferred":[
        "Navarro"
    ],
    "name:fra_x_preferred":[
        "Navarro"
    ],
    "name:heb_x_preferred":[
        "\u05e0\u05d1\u05d0\u05e8\u05d5"
    ],
    "name:ita_x_preferred":[
        "Navarro"
    ],
    "name:jpn_x_preferred":[
        "\u30ca\u30d0\u30fc\u30ed"
    ],
    "name:nds_x_preferred":[
        "Navarro"
    ],
    "name:nld_x_preferred":[
        "Navarro"
    ],
    "name:pol_x_preferred":[
        "Navarro"
    ],
    "name:por_x_preferred":[
        "Navarro"
    ],
    "name:rus_x_preferred":[
        "\u041d\u0430\u0432\u0430\u0440\u0440\u043e"
    ],
    "name:spa_x_preferred":[
        "Navarro"
    ],
    "name:srp_x_preferred":[
        "\u041d\u0430\u0432\u0430\u0440\u043e"
    ],
    "name:swe_x_preferred":[
        "Navarro"
    ],
    "name:tur_x_preferred":[
        "Navarro"
    ],
    "wof:name":"Navarro",
    "wof:placetype":"locality"
},
  "geometry": {"coordinates":[-116.20917,31.87889],"type":"Point"}
}