{
  "type": "Feature",
  "properties": {
    "gn:admin1_code":"24",
    "gn:admin2_code":"25.0",
    "gn:asciiname":"Juan Guerrero",
    "gn:country_code":"MX",
    "gn:dem":2091,
    "gn:feature_class":"P",
    "gn:feature_code":"PPL",
    "gn:name":"Juan Guerrero",
    "gn:population":9,
    "gn:timezone":"America/Mexico_City",
    "iso:country":"MX",
    "name:ara_x_preferred":[
        "\u062d\u0632\u0642\u064a\u0627\u0644 \u063a\u064a\u0631\u064a\u0631\u0648"
    ],
    "name:spa_x_preferred":[
        "Juan Guerrero"
    ],
    "wof:name":"Juan Guerrero",
    "wof:placetype":"locality",
    "wof:population":9
},
  "geometry": {"coordinates":[-101.73721999999999,22.58528],"type":"Point"}
}