{
  "type": "Feature",
  "properties": {
    "gn:admin1_code":"28.0",
    "gn:admin2_code":"27.0",
    "gn:asciiname":"El Perro",
    "gn:country_code":"MX",
    "gn:dem":144,
    "gn:feature_class":"P",
    "gn:feature_code":"PPL",
    "gn:name":"El Perro",
    "gn:population":0,
    "gn:timezone":"America/Matamoros",
    "iso:country":"MX",
    "name:spa_x_preferred":[
        "El Perro"
    ],
    "wof:name":"El Perro",
    "wof:placetype":"locality"
},
  "geometry": {"coordinates":[-99.68013000000001,27.31637000000001],"type":"Point"}
}