{
  "type": "Feature",
  "properties": {
    "gn:admin1_code":"18",
    "gn:admin2_code":"9",
    "gn:asciiname":"Las Guitarras",
    "gn:country_code":"MX",
    "gn:dem":627,
    "gn:feature_class":"P",
    "gn:feature_code":"PPL",
    "gn:name":"Las Guitarras",
    "gn:population":30,
    "gn:timezone":"America/Mazatlan",
    "iso:country":"MX",
    "wof:name":"Las Guitarras",
    "wof:placetype":"locality",
    "wof:population":30
},
  "geometry": {"coordinates":[-104.85361,22.56583],"type":"Point"}
}