{
  "type": "Feature",
  "properties": {
    "gn:admin1_code":"16.0",
    "gn:admin2_code":"20.0",
    "gn:asciiname":"Mariano Escobedo",
    "gn:country_code":"MX",
    "gn:dem":1857,
    "gn:feature_class":"P",
    "gn:feature_code":"PPL",
    "gn:name":"Mariano Escobedo",
    "gn:population":0,
    "gn:timezone":"America/Mexico_City",
    "iso:country":"MX",
    "name:ara_x_preferred":[
        "\u0645\u0627\u0631\u064a\u0627\u0646\u0648 \u0623\u0633\u0643\u0648\u0628\u0627\u062f\u0648"
    ],
    "name:bre_x_preferred":[
        "Mariano Escobedo"
    ],
    "name:jpn_x_preferred":[
        "\u30de\u30ea\u30a2\u30fc\u30ce\u30fb\u30a8\u30b9\u30b3\u30da\u30c9"
    ],
    "name:nld_x_preferred":[
        "Mariano Escobedo"
    ],
    "name:spa_x_preferred":[
        "Mariano Escobedo"
    ],
    "name:spa_x_variant":[
        "San Lorenzo"
    ],
    "name:swe_x_preferred":[
        "Mariano Escobedo"
    ],
    "name:vie_x_preferred":[
        "Mariano Escobedo"
    ],
    "wof:name":"Mariano Escobedo",
    "wof:placetype":"locality"
},
  "geometry": {"coordinates":[-101.06206,19.96481],"type":"Point"}
}