{
  "type": "Feature",
  "properties": {
    "gn:admin1_code":"16.0",
    "gn:admin2_code":"20.0",
    "gn:asciiname":"Mariano Escobedo",
    "gn:country_code":"MX",
    "gn:dem":1857,
    "gn:feature_class":"P",
    "gn:feature_code":"PPL",
    "gn:name":"Mariano Escobedo",
    "gn:population":0,
    "gn:timezone":"America/Mexico_City",
    "iso:country":"MX",
    "name:spa_x_preferred":[
        "Mariano Escobedo"
    ],
    "name:spa_x_variant":[
        "San Lorenzo"
    ],
    "wof:name":"Mariano Escobedo",
    "wof:placetype":"locality"
},
  "geometry": {"coordinates":[-101.06206,19.96481],"type":"Point"}
}