{
  "type": "Feature",
  "properties": {
    "gn:admin1_code":"16",
    "gn:admin2_code":"57",
    "gn:asciiname":"El Paso del Pinzan",
    "gn:country_code":"MX",
    "gn:dem":614,
    "gn:feature_class":"P",
    "gn:feature_code":"PPL",
    "gn:name":"El Paso del Pinz\u00e1n",
    "gn:population":10,
    "gn:timezone":"America/Mexico_City",
    "iso:country":"MX",
    "name:und_x_variant":[
        "El Paso del Pinz\u00e1n"
    ],
    "wof:name":"El Paso del Pinzan",
    "wof:placetype":"locality",
    "wof:population":10
},
  "geometry": {"coordinates":[-101.19,19.04528],"type":"Point"}
}