{
  "type": "Feature",
  "properties": {
    "gn:admin1_code":"6",
    "gn:admin2_code":"52.0",
    "gn:asciiname":"Adame",
    "gn:country_code":"MX",
    "gn:dem":787,
    "gn:feature_class":"P",
    "gn:feature_code":"PPL",
    "gn:name":"Adame",
    "gn:population":5,
    "gn:timezone":"America/Ojinaga",
    "iso:country":"MX",
    "name:spa_x_preferred":[
        "Adame"
    ],
    "wof:name":"Adame",
    "wof:placetype":"locality",
    "wof:population":5
},
  "geometry": {"coordinates":[-104.42631,29.57185],"type":"Point"}
}