{
  "type": "Feature",
  "properties": {
    "gn:admin1_code":"31",
    "gn:admin2_code":"85.0",
    "gn:asciiname":"Sahcaba",
    "gn:country_code":"MX",
    "gn:dem":23,
    "gn:feature_class":"P",
    "gn:feature_code":"PPL",
    "gn:name":"Sahcaba",
    "gn:population":0,
    "gn:timezone":"America/Merida",
    "iso:country":"MX",
    "name:spa_x_preferred":[
        "Sahcaba"
    ],
    "wof:name":"Sahcaba",
    "wof:placetype":"locality"
},
  "geometry": {"coordinates":[-88.12831,20.81354],"type":"Point"}
}