{
  "type": "Feature",
  "properties": {
    "gn:admin1_code":"5.0",
    "gn:admin2_code":"77.0",
    "gn:asciiname":"Chivalito Segunda Seccion",
    "gn:country_code":"MX",
    "gn:dem":237,
    "gn:feature_class":"P",
    "gn:feature_code":"PPL",
    "gn:name":"Chivalito Segunda Secci\u00f3n",
    "gn:population":0,
    "gn:timezone":"America/Mexico_City",
    "iso:country":"MX",
    "name:spa_x_preferred":[
        "Chivalito Segunda Secci\u00f3n"
    ],
    "wof:name":"Chivalito Segunda Seccion",
    "wof:placetype":"locality"
},
  "geometry": {"coordinates":[-92.42352,17.57371],"type":"Point"}
}