{
  "type": "Feature",
  "properties": {
    "gn:admin1_code":"24",
    "gn:admin2_code":"50",
    "gn:asciiname":"La Candelaria",
    "gn:country_code":"MX",
    "gn:dem":1952,
    "gn:feature_class":"P",
    "gn:feature_code":"PPL",
    "gn:name":"La Candelaria",
    "gn:population":33,
    "gn:timezone":"America/Mexico_City",
    "iso:country":"MX",
    "wof:name":"La Candelaria",
    "wof:placetype":"locality",
    "wof:population":33
},
  "geometry": {"coordinates":[-101.10306,21.83667],"type":"Point"}
}