{
  "type": "Feature",
  "properties": {
    "gn:admin1_code":"6.0",
    "gn:admin2_code":"12.0",
    "gn:asciiname":"Cordones de San Juan",
    "gn:country_code":"MX",
    "gn:dem":2111,
    "gn:feature_class":"P",
    "gn:feature_code":"PPL",
    "gn:name":"Cordones de San Juan",
    "gn:population":0,
    "gn:timezone":"America/Chihuahua",
    "iso:country":"MX",
    "name:spa_x_preferred":[
        "Cordones de San Juan"
    ],
    "wof:name":"Cordones de San Juan",
    "wof:placetype":"locality"
},
  "geometry": {"coordinates":[-107.12595,27.67195],"type":"Point"}
}