{
  "type": "Feature",
  "properties": {
    "gn:admin1_code":"26",
    "gn:admin2_code":"3.0",
    "gn:asciiname":"Jurinabo",
    "gn:country_code":"MX",
    "gn:dem":433,
    "gn:feature_class":"P",
    "gn:feature_code":"PPL",
    "gn:name":"Jurinabo",
    "gn:population":0,
    "gn:timezone":"America/Hermosillo",
    "iso:country":"MX",
    "name:spa_x_preferred":[
        "Jurinabo"
    ],
    "wof:name":"Jurinabo",
    "wof:placetype":"locality"
},
  "geometry": {"coordinates":[-108.77267000000001,27.26077],"type":"Point"}
}