{
  "type": "Feature",
  "properties": {
    "gn:admin1_code":"14.0",
    "gn:admin2_code":"113.0",
    "gn:asciiname":"El Jilote",
    "gn:country_code":"MX",
    "gn:dem":991,
    "gn:feature_class":"P",
    "gn:feature_code":"PPL",
    "gn:name":"El Jilote",
    "gn:population":0,
    "gn:timezone":"America/Mexico_City",
    "iso:country":"MX",
    "name:spa_x_preferred":[
        "El Jilote"
    ],
    "wof:name":"El Jilote",
    "wof:placetype":"locality"
},
  "geometry": {"coordinates":[-103.93171,19.77269],"type":"Point"}
}