{
  "type": "Feature",
  "properties": {
    "gn:admin1_code":"6",
    "gn:admin2_code":"40.0",
    "gn:asciiname":"El Campo Seis",
    "gn:country_code":"MX",
    "gn:dem":2176,
    "gn:feature_class":"P",
    "gn:feature_code":"PPL",
    "gn:name":"El Campo Seis",
    "gn:population":0,
    "gn:timezone":"America/Chihuahua",
    "iso:country":"MX",
    "name:spa_x_preferred":[
        "El Campo Seis"
    ],
    "name:und_x_variant":[
        "Rancho El Seis"
    ],
    "wof:name":"El Campo Seis",
    "wof:placetype":"locality"
},
  "geometry": {"coordinates":[-108.37024,29.08297],"type":"Point"}
}