{
  "type": "Feature",
  "properties": {
    "gn:admin1_code":"25",
    "gn:admin2_code":"6.0",
    "gn:asciiname":"Las Tapias",
    "gn:country_code":"MX",
    "gn:dem":188,
    "gn:feature_class":"P",
    "gn:feature_code":"PPL",
    "gn:name":"Las Tapias",
    "gn:population":0,
    "gn:timezone":"America/Mazatlan",
    "iso:country":"MX",
    "name:spa_x_preferred":[
        "Las Tapias"
    ],
    "name:und_x_variant":[
        "Tapias de Arriba"
    ],
    "wof:name":"Las Tapias",
    "wof:placetype":"locality"
},
  "geometry": {"coordinates":[-107.15608,24.65029],"type":"Point"}
}