{
  "type": "Feature",
  "properties": {
    "gn:admin1_code":"4.0",
    "gn:asciiname":"La Herradura",
    "gn:country_code":"MX",
    "gn:dem":7,
    "gn:feature_class":"P",
    "gn:feature_code":"PPL",
    "gn:name":"La Herradura",
    "gn:population":0,
    "gn:timezone":"America/Merida",
    "iso:country":"MX",
    "name:spa_x_preferred":[
        "La Herradura"
    ],
    "wof:name":"La Herradura",
    "wof:placetype":"locality"
},
  "geometry": {"coordinates":[-91.27549999999999,18.32618],"type":"Point"}
}