{
  "type": "Feature",
  "properties": {
    "gn:admin1_code":"6",
    "gn:admin2_code":"4.0",
    "gn:asciiname":"La Noria",
    "gn:country_code":"MX",
    "gn:dem":1206,
    "gn:feature_class":"P",
    "gn:feature_code":"PPL",
    "gn:name":"La Noria",
    "gn:population":0,
    "gn:timezone":"America/Chihuahua",
    "iso:country":"MX",
    "name:und_x_variant":[
        "Rancho de la Noria",
        "La Noria"
    ],
    "wof:name":"La Noria",
    "wof:placetype":"locality"
},
  "geometry": {"coordinates":[-105.7287,28.52988],"type":"Point"}
}