{
  "type": "Feature",
  "properties": {
    "gn:admin1_code":"31",
    "gn:admin2_code":"91.0",
    "gn:asciiname":"Xluch",
    "gn:country_code":"MX",
    "gn:dem":32,
    "gn:feature_class":"P",
    "gn:feature_code":"PPL",
    "gn:name":"Xluch",
    "gn:population":0,
    "gn:timezone":"America/Merida",
    "iso:country":"MX",
    "name:spa_x_preferred":[
        "Xluch"
    ],
    "wof:name":"Xluch",
    "wof:placetype":"locality"
},
  "geometry": {"coordinates":[-88.36696999999999,20.78519],"type":"Point"}
}