{
  "type": "Feature",
  "properties": {
    "gn:admin1_code":"13",
    "gn:admin2_code":"59.0",
    "gn:asciiname":"Pared Blanca",
    "gn:country_code":"MX",
    "gn:dem":1894,
    "gn:feature_class":"P",
    "gn:feature_code":"PPL",
    "gn:name":"Pared Blanca",
    "gn:population":0,
    "gn:timezone":"America/Mexico_City",
    "iso:country":"MX",
    "name:spa_x_preferred":[
        "Pared Blanca"
    ],
    "wof:name":"Pared Blanca",
    "wof:placetype":"locality"
},
  "geometry": {"coordinates":[-99.52244,20.57311],"type":"Point"}
}