{
  "type": "Feature",
  "properties": {
    "gn:admin1_code":"5",
    "gn:admin2_code":"109.0",
    "gn:asciiname":"La Ventana",
    "gn:country_code":"MX",
    "gn:dem":1827,
    "gn:feature_class":"P",
    "gn:feature_code":"PPL",
    "gn:name":"La Ventana",
    "gn:population":341,
    "gn:timezone":"America/Mexico_City",
    "iso:country":"MX",
    "name:urd_x_preferred":[
        "\u0644\u0627 \u0648\u06cc\u0646\u0679\u0627\u0646\u0627"
    ],
    "wof:name":"La Ventana",
    "wof:placetype":"locality",
    "wof:population":341
},
  "geometry": {"coordinates":[-92.37415,17.15437],"type":"Point"}
}