{
  "type": "Feature",
  "properties": {
    "gn:admin1_code":"15",
    "gn:admin2_code":"86.0",
    "gn:asciiname":"Paredones",
    "gn:country_code":"MX",
    "gn:dem":2937,
    "gn:feature_class":"P",
    "gn:feature_code":"PPL",
    "gn:name":"Paredones",
    "gn:population":0,
    "gn:timezone":"America/Mexico_City",
    "iso:country":"MX",
    "name:spa_x_preferred":[
        "Paredones"
    ],
    "wof:name":"Paredones",
    "wof:placetype":"locality"
},
  "geometry": {"coordinates":[-99.88612999999999,19.02811],"type":"Point"}
}