{
  "type": "Feature",
  "properties": {
    "gn:admin1_code":"6",
    "gn:admin2_code":"5.0",
    "gn:asciiname":"Amaya",
    "gn:country_code":"MX",
    "gn:dem":1291,
    "gn:feature_class":"P",
    "gn:feature_code":"PPL",
    "gn:name":"Amaya",
    "gn:population":0,
    "gn:timezone":"America/Chihuahua",
    "iso:country":"MX",
    "name:cat_x_preferred":[
        "Amaya"
    ],
    "name:ceb_x_preferred":[
        "Amaya"
    ],
    "name:ces_x_preferred":[
        "Amaya"
    ],
    "name:deu_x_preferred":[
        "Amaya"
    ],
    "name:eus_x_preferred":[
        "Amaya"
    ],
    "name:fra_x_preferred":[
        "Amaya"
    ],
    "name:glg_x_preferred":[
        "Amaya"
    ],
    "name:ita_x_preferred":[
        "Amaya"
    ],
    "name:por_x_preferred":[
        "Amaya"
    ],
    "name:spa_x_preferred":[
        "Los Amaya"
    ],
    "name:spa_x_variant":[
        "Amaya"
    ],
    "name:swe_x_preferred":[
        "Amaya"
    ],
    "wof:name":"Amaya",
    "wof:placetype":"locality"
},
  "geometry": {"coordinates":[-107.94999,31.1618],"type":"Point"}
}