{
  "type": "Feature",
  "properties": {
    "gn:admin1_code":"6",
    "gn:admin2_code":"7.0",
    "gn:asciiname":"Las Jaquimas",
    "gn:country_code":"MX",
    "gn:dem":2379,
    "gn:feature_class":"P",
    "gn:feature_code":"PPL",
    "gn:name":"Las J\u00e1quimas",
    "gn:population":0,
    "gn:timezone":"America/Chihuahua",
    "iso:country":"MX",
    "name:spa_x_preferred":[
        "Las J\u00e1quimas"
    ],
    "wof:name":"Las Jaquimas",
    "wof:placetype":"locality"
},
  "geometry": {"coordinates":[-106.74946,26.84729],"type":"Point"}
}