{
  "type": "Feature",
  "properties": {
    "gn:admin1_code":"6",
    "gn:admin2_code":"53.0",
    "gn:asciiname":"Presidio Viejo",
    "gn:country_code":"MX",
    "gn:dem":1129,
    "gn:feature_class":"P",
    "gn:feature_code":"PPL",
    "gn:name":"Presidio Viejo",
    "gn:population":0,
    "gn:timezone":"America/Chihuahua",
    "iso:country":"MX",
    "wof:name":"Presidio Viejo",
    "wof:placetype":"locality"
},
  "geometry": {"coordinates":[-105.88333,31.21667],"type":"Point"}
}