{
  "type": "Feature",
  "properties": {
    "gn:admin1_code":"24.0",
    "gn:admin2_code":"16.0",
    "gn:asciiname":"Las Coloradas",
    "gn:country_code":"MX",
    "gn:dem":21,
    "gn:feature_class":"P",
    "gn:feature_code":"PPL",
    "gn:name":"Las Coloradas",
    "gn:population":15,
    "gn:timezone":"America/Mexico_City",
    "iso:country":"MX",
    "name:ceb_x_preferred":[
        "Las Coloradas"
    ],
    "name:spa_x_preferred":[
        "Las Coloradas"
    ],
    "name:swe_x_preferred":[
        "Las Coloradas"
    ],
    "wof:name":"Las Coloradas",
    "wof:placetype":"locality",
    "wof:population":15
},
  "geometry": {"coordinates":[-98.48718,22.16094],"type":"Point"}
}