{
  "type": "Feature",
  "properties": {
    "gn:admin1_code":"30.0",
    "gn:admin2_code":"155.0",
    "gn:asciiname":"Palos Azules",
    "gn:country_code":"MX",
    "gn:dem":88,
    "gn:feature_class":"P",
    "gn:feature_code":"PPL",
    "gn:name":"Palos Azules",
    "gn:population":5,
    "gn:timezone":"America/Mexico_City",
    "iso:country":"MX",
    "name:spa_x_preferred":[
        "Palos Azules"
    ],
    "wof:name":"Palos Azules",
    "wof:placetype":"locality",
    "wof:population":5
},
  "geometry": {"coordinates":[-98.11691999999999,21.38135],"type":"Point"}
}