{
  "type": "Feature",
  "properties": {
    "gn:admin1_code":"12",
    "gn:admin2_code":"16.0",
    "gn:asciiname":"Valle Nuevo",
    "gn:country_code":"MX",
    "gn:dem":453,
    "gn:feature_class":"P",
    "gn:feature_code":"PPL",
    "gn:name":"Valle Nuevo",
    "gn:population":0,
    "gn:timezone":"America/Mexico_City",
    "iso:country":"MX",
    "name:spa_x_preferred":[
        "Valle Nuevo"
    ],
    "wof:name":"Valle Nuevo",
    "wof:placetype":"locality"
},
  "geometry": {"coordinates":[-101.56743,18.13695],"type":"Point"}
}