{
  "type": "Feature",
  "properties": {
    "gn:admin1_code":"7",
    "gn:admin2_code":"10.0",
    "gn:asciiname":"Jesus Mendoza",
    "gn:country_code":"MX",
    "gn:dem":524,
    "gn:feature_class":"P",
    "gn:feature_code":"PPL",
    "gn:name":"Jes\u00fas Mendoza",
    "gn:population":4,
    "gn:timezone":"America/Monterrey",
    "iso:country":"MX",
    "name:und_x_variant":[
        "Jes\u00fas Mendoza"
    ],
    "wof:name":"Jesus Mendoza",
    "wof:placetype":"locality",
    "wof:population":4
},
  "geometry": {"coordinates":[-101.49346,27.00727],"type":"Point"}
}