{
  "type": "Feature",
  "properties": {
    "gn:admin1_code":"12.0",
    "gn:admin2_code":"27.0",
    "gn:asciiname":"La Contrayerba",
    "gn:country_code":"MX",
    "gn:dem":638,
    "gn:feature_class":"P",
    "gn:feature_code":"PPL",
    "gn:name":"La Contrayerba",
    "gn:population":0,
    "gn:timezone":"America/Mexico_City",
    "iso:country":"MX",
    "name:spa_x_preferred":[
        "La Contrayerba"
    ],
    "wof:name":"La Contrayerba",
    "wof:placetype":"locality"
},
  "geometry": {"coordinates":[-100.53075,18.71147],"type":"Point"}
}