{
  "type": "Feature",
  "properties": {
    "gn:admin1_code":"12.0",
    "gn:admin2_code":"7.0",
    "gn:asciiname":"Tuiatengo",
    "gn:country_code":"MX",
    "gn:dem":423,
    "gn:feature_class":"P",
    "gn:feature_code":"PPL",
    "gn:name":"Tuiatengo",
    "gn:population":0,
    "gn:timezone":"America/Mexico_City",
    "iso:country":"MX",
    "wof:name":"Tuiatengo",
    "wof:placetype":"locality"
},
  "geometry": {"coordinates":[-100.28333000000001,18.26667],"type":"Point"}
}