{
  "type": "Feature",
  "properties": {
    "gn:admin1_code":"28.0",
    "gn:admin2_code":"39.0",
    "gn:asciiname":"Tierra Negra",
    "gn:country_code":"MX",
    "gn:dem":1278,
    "gn:feature_class":"P",
    "gn:feature_code":"PPL",
    "gn:name":"Tierra Negra",
    "gn:population":0,
    "gn:timezone":"America/Monterrey",
    "iso:country":"MX",
    "name:spa_x_preferred":[
        "Tierra Negra"
    ],
    "wof:name":"Tierra Negra",
    "wof:placetype":"locality"
},
  "geometry": {"coordinates":[-99.63121,22.97778],"type":"Point"}
}