{
  "type": "Feature",
  "properties": {
    "gn:admin1_code":"5",
    "gn:admin2_code":"66",
    "gn:asciiname":"Nuevo San Carlos",
    "gn:country_code":"MX",
    "gn:dem":1340,
    "gn:feature_class":"P",
    "gn:feature_code":"PPL",
    "gn:name":"Nuevo San Carlos",
    "gn:population":25,
    "gn:timezone":"America/Mexico_City",
    "iso:country":"MX",
    "wof:name":"Nuevo San Carlos",
    "wof:placetype":"locality",
    "wof:population":25
},
  "geometry": {"coordinates":[-92.4525,17.10528],"type":"Point"}
}