{
  "type": "Feature",
  "properties": {
    "gn:admin1_code":"26",
    "gn:admin2_code":"9.0",
    "gn:asciiname":"Babatochi",
    "gn:country_code":"MX",
    "gn:dem":892,
    "gn:feature_class":"P",
    "gn:feature_code":"PPL",
    "gn:name":"Babatochi",
    "gn:population":0,
    "gn:timezone":"America/Hermosillo",
    "iso:country":"MX",
    "name:spa_x_preferred":[
        "Babatochi"
    ],
    "wof:name":"Babatochi",
    "wof:placetype":"locality"
},
  "geometry": {"coordinates":[-109.31547999999999,28.6978],"type":"Point"}
}