{
  "type": "Feature",
  "properties": {
    "gn:admin1_code":"25",
    "gn:admin2_code":"17.0",
    "gn:asciiname":"Texcalama de Arriba",
    "gn:country_code":"MX",
    "gn:dem":252,
    "gn:feature_class":"P",
    "gn:feature_code":"PPL",
    "gn:name":"Texcalama de Arriba",
    "gn:population":0,
    "gn:timezone":"America/Mazatlan",
    "iso:country":"MX",
    "name:und_x_variant":[
        "La Tescalama",
        "Texcalama de Arriba"
    ],
    "wof:name":"Texcalama de Arriba",
    "wof:placetype":"locality"
},
  "geometry": {"coordinates":[-107.99970999999999,25.7181],"type":"Point"}
}