{
  "type": "Feature",
  "properties": {
    "gn:admin1_code":"20",
    "gn:admin2_code":"490.0",
    "gn:asciiname":"Pelixtitlan",
    "gn:country_code":"MX",
    "gn:dem":2080,
    "gn:feature_class":"P",
    "gn:feature_code":"PPL",
    "gn:name":"Pelixtitlan",
    "gn:population":376,
    "gn:timezone":"America/Mexico_City",
    "iso:country":"MX",
    "wof:name":"Pelixtitlan",
    "wof:placetype":"locality",
    "wof:population":376
},
  "geometry": {"coordinates":[-96.99222,18.22167],"type":"Point"}
}