{
  "type": "Feature",
  "properties": {
    "gn:admin1_code":"13",
    "gn:admin2_code":"15.0",
    "gn:asciiname":"Cieneguilla",
    "gn:country_code":"MX",
    "gn:dem":2078,
    "gn:feature_class":"P",
    "gn:feature_code":"PPL",
    "gn:name":"Cieneguilla",
    "gn:population":0,
    "gn:timezone":"America/Mexico_City",
    "iso:country":"MX",
    "wof:name":"Cieneguilla",
    "wof:placetype":"locality"
},
  "geometry": {"coordinates":[-99.03547,20.7163],"type":"Point"}
}