{
  "type": "Feature",
  "properties": {
    "gn:admin1_code":"6",
    "gn:admin2_code":"27.0",
    "gn:asciiname":"Bajio de las Mujeres",
    "gn:country_code":"MX",
    "gn:dem":2436,
    "gn:feature_class":"P",
    "gn:feature_code":"PPL",
    "gn:name":"Baj\u00edo de las Mujeres",
    "gn:population":0,
    "gn:timezone":"America/Chihuahua",
    "iso:country":"MX",
    "name:spa_x_preferred":[
        "Baj\u00edo de las Mujeres"
    ],
    "wof:name":"Bajio de las Mujeres",
    "wof:placetype":"locality"
},
  "geometry": {"coordinates":[-107.17424,26.85393],"type":"Point"}
}