{
  "type": "Feature",
  "properties": {
    "gn:admin1_code":"6.0",
    "gn:asciiname":"La Quinta",
    "gn:country_code":"MX",
    "gn:dem":1573,
    "gn:feature_class":"P",
    "gn:feature_code":"PPL",
    "gn:name":"La Quinta",
    "gn:population":0,
    "gn:timezone":"America/Chihuahua",
    "iso:country":"MX",
    "name:spa_x_preferred":[
        "La Quinta"
    ],
    "wof:name":"La Quinta",
    "wof:placetype":"locality"
},
  "geometry": {"coordinates":[-106.27374,29.02602000000001],"type":"Point"}
}