{
  "type": "Feature",
  "properties": {
    "gn:admin1_code":"10",
    "gn:admin2_code":"34",
    "gn:asciiname":"Los Platanos",
    "gn:country_code":"MX",
    "gn:dem":489,
    "gn:feature_class":"P",
    "gn:feature_code":"PPL",
    "gn:name":"Los Pl\u00e1tanos",
    "gn:population":35,
    "gn:timezone":"America/Monterrey",
    "iso:country":"MX",
    "name:und_x_variant":[
        "Los Pl\u00e1tanos"
    ],
    "wof:name":"Los Platanos",
    "wof:placetype":"locality",
    "wof:population":35
},
  "geometry": {"coordinates":[-106.56950999999999,24.70193],"type":"Point"}
}