{
  "type": "Feature",
  "properties": {
    "gn:admin1_code":"20",
    "gn:admin2_code":"397",
    "gn:asciiname":"Yososana",
    "gn:country_code":"MX",
    "gn:dem":1966,
    "gn:feature_class":"P",
    "gn:feature_code":"PPL",
    "gn:name":"Yososana",
    "gn:population":36,
    "gn:timezone":"America/Mexico_City",
    "iso:country":"MX",
    "wof:name":"Yososana",
    "wof:placetype":"locality",
    "wof:population":36
},
  "geometry": {"coordinates":[-97.74472,17.21833],"type":"Point"}
}