{
  "type": "Feature",
  "properties": {
    "gn:admin1_code":"11.0",
    "gn:admin2_code":"15.0",
    "gn:asciiname":"Las Adjuntas de Magdalenas",
    "gn:country_code":"MX",
    "gn:dem":1909,
    "gn:feature_class":"P",
    "gn:feature_code":"PPL",
    "gn:name":"Las Adjuntas de Magdalenas",
    "gn:population":5,
    "gn:timezone":"America/Mexico_City",
    "iso:country":"MX",
    "wof:name":"Las Adjuntas de Magdalenas",
    "wof:placetype":"locality",
    "wof:population":5
},
  "geometry": {"coordinates":[-101.39167,21.06806],"type":"Point"}
}