{
  "type": "Feature",
  "properties": {
    "gn:admin1_code":"16",
    "gn:admin2_code":"92.0",
    "gn:asciiname":"El Rincon del Indio",
    "gn:country_code":"MX",
    "gn:dem":481,
    "gn:feature_class":"P",
    "gn:feature_code":"PPL",
    "gn:name":"El Rinc\u00f3n del Indio",
    "gn:population":0,
    "gn:timezone":"America/Mexico_City",
    "iso:country":"MX",
    "name:spa_x_preferred":[
        "El Rinc\u00f3n del Indio"
    ],
    "wof:name":"El Rincon del Indio",
    "wof:placetype":"locality"
},
  "geometry": {"coordinates":[-100.85281999999999,19.01875],"type":"Point"}
}