{
  "type": "Feature",
  "properties": {
    "gn:admin1_code":"25",
    "gn:asciiname":"Mina de Oro",
    "gn:country_code":"MX",
    "gn:dem":1062,
    "gn:feature_class":"P",
    "gn:feature_code":"PPL",
    "gn:name":"Mina de Oro",
    "gn:population":0,
    "gn:timezone":"America/Mazatlan",
    "iso:country":"MX",
    "name:spa_x_preferred":[
        "Mina de Oro"
    ],
    "wof:name":"Mina de Oro",
    "wof:placetype":"locality"
},
  "geometry": {"coordinates":[-107.53968,26.13765],"type":"Point"}
}