{
  "type": "Feature",
  "properties": {
    "gn:admin1_code":"28",
    "gn:admin2_code":"10.0",
    "gn:asciiname":"San Felipe",
    "gn:country_code":"MX",
    "gn:dem":136,
    "gn:feature_class":"P",
    "gn:feature_code":"PPL",
    "gn:name":"San Felipe",
    "gn:population":1,
    "gn:timezone":"America/Monterrey",
    "iso:country":"MX",
    "name:spa_x_preferred":[
        "San Felipe"
    ],
    "name:und_x_variant":[
        "Rancho San Felipe"
    ],
    "wof:name":"San Felipe",
    "wof:placetype":"locality",
    "wof:population":1
},
  "geometry": {"coordinates":[-98.3409,24.50502],"type":"Point"}
}