{
  "type": "Feature",
  "properties": {
    "gn:admin1_code":"5.0",
    "gn:asciiname":"El Vergel la Rinconada",
    "gn:country_code":"MX",
    "gn:dem":1951,
    "gn:feature_class":"P",
    "gn:feature_code":"PPL",
    "gn:name":"El Vergel la Rinconada",
    "gn:population":0,
    "gn:timezone":"America/Mexico_City",
    "iso:country":"MX",
    "name:spa_x_preferred":[
        "El Vergel la Rinconada"
    ],
    "wof:name":"El Vergel la Rinconada",
    "wof:placetype":"locality"
},
  "geometry": {"coordinates":[-92.28703,15.60673],"type":"Point"}
}