{
  "type": "Feature",
  "properties": {
    "gn:admin1_code":"7.0",
    "gn:admin2_code":"27.0",
    "gn:asciiname":"Higo",
    "gn:country_code":"MX",
    "gn:dem":1112,
    "gn:feature_class":"P",
    "gn:feature_code":"PPL",
    "gn:name":"Higo",
    "gn:population":0,
    "gn:timezone":"America/Monterrey",
    "iso:country":"MX",
    "name:spa_x_preferred":[
        "Higo"
    ],
    "name:und_x_variant":[
        "Ejido Higo"
    ],
    "wof:name":"Higo",
    "wof:placetype":"locality"
},
  "geometry": {"coordinates":[-101.00326,25.69476],"type":"Point"}
}