{
  "type": "Feature",
  "properties": {
    "gn:admin1_code":"5",
    "gn:admin2_code":"59.0",
    "gn:asciiname":"Agua Escondida",
    "gn:country_code":"MX",
    "gn:dem":858,
    "gn:feature_class":"P",
    "gn:feature_code":"PPL",
    "gn:name":"Agua Escondida",
    "gn:population":0,
    "gn:timezone":"America/Mexico_City",
    "iso:country":"MX",
    "name:spa_x_preferred":[
        "Agua Escondida"
    ],
    "wof:name":"Agua Escondida",
    "wof:placetype":"locality"
},
  "geometry": {"coordinates":[-91.4943,16.62036],"type":"Point"}
}