{
  "type": "Feature",
  "properties": {
    "gn:admin1_code":"11.0",
    "gn:admin2_code":"19.0",
    "gn:asciiname":"Lagunilla de Agustinos",
    "gn:country_code":"MX",
    "gn:dem":2485,
    "gn:feature_class":"P",
    "gn:feature_code":"PPL",
    "gn:name":"Lagunilla de Agustinos",
    "gn:population":0,
    "gn:timezone":"America/Mexico_City",
    "iso:country":"MX",
    "name:spa_x_preferred":[
        "Lagunilla de Agustinos"
    ],
    "name:spa_x_variant":[
        "Lagunilla"
    ],
    "wof:name":"Lagunilla de Agustinos",
    "wof:placetype":"locality"
},
  "geometry": {"coordinates":[-100.6071,20.20288],"type":"Point"}
}