{
  "type": "Feature",
  "properties": {
    "gn:admin1_code":"26.0",
    "gn:admin2_code":"44.0",
    "gn:asciiname":"Los Arbolillos",
    "gn:country_code":"MX",
    "gn:dem":637,
    "gn:feature_class":"P",
    "gn:feature_code":"PPL",
    "gn:name":"Los Arbolillos",
    "gn:population":0,
    "gn:timezone":"America/Hermosillo",
    "iso:country":"MX",
    "name:spa_x_preferred":[
        "Los Arbolillos"
    ],
    "wof:name":"Los Arbolillos",
    "wof:placetype":"locality"
},
  "geometry": {"coordinates":[-109.43677,28.49091],"type":"Point"}
}