{
  "type": "Feature",
  "properties": {
    "gn:admin1_code":"32.0",
    "gn:admin2_code":"26.0",
    "gn:asciiname":"Tanque el Alamo",
    "gn:country_code":"MX",
    "gn:dem":2067,
    "gn:feature_class":"P",
    "gn:feature_code":"PPL",
    "gn:name":"Tanque el Alamo",
    "gn:population":0,
    "gn:timezone":"America/Mexico_City",
    "iso:country":"MX",
    "name:spa_x_preferred":[
        "Tanque el Alamo"
    ],
    "wof:name":"Tanque el Alamo",
    "wof:placetype":"locality"
},
  "geometry": {"coordinates":[-101.59603,24.5473],"type":"Point"}
}