{
  "type": "Feature",
  "properties": {
    "gn:admin1_code":"26",
    "gn:admin2_code":"17",
    "gn:asciiname":"Heroe de Nacozari",
    "gn:country_code":"MX",
    "gn:dem":157,
    "gn:feature_class":"P",
    "gn:feature_code":"PPL",
    "gn:name":"H\u00e9roe de Nacozari",
    "gn:population":30,
    "gn:timezone":"America/Hermosillo",
    "iso:country":"MX",
    "name:und_x_variant":[
        "H\u00e9roe de Nacozari"
    ],
    "wof:name":"Heroe de Nacozari",
    "wof:placetype":"locality",
    "wof:population":30
},
  "geometry": {"coordinates":[-112.55806,30.8125],"type":"Point"}
}