{
  "type": "Feature",
  "properties": {
    "gn:admin1_code":"25",
    "gn:admin2_code":"17.0",
    "gn:asciiname":"Buraguee",
    "gn:country_code":"MX",
    "gn:dem":150,
    "gn:feature_class":"P",
    "gn:feature_code":"PPL",
    "gn:name":"Burag\u00fce",
    "gn:population":99,
    "gn:timezone":"America/Mazatlan",
    "iso:country":"MX",
    "name:und_x_variant":[
        "Burag\u00fce"
    ],
    "wof:name":"Buraguee",
    "wof:placetype":"locality",
    "wof:population":99
},
  "geometry": {"coordinates":[-107.96653999999999,25.82422],"type":"Point"}
}