{
  "type": "Feature",
  "properties": {
    "gn:admin1_code":"6.0",
    "gn:admin2_code":"36.0",
    "gn:asciiname":"El Berrendo",
    "gn:country_code":"MX",
    "gn:dem":1457,
    "gn:feature_class":"P",
    "gn:feature_code":"PPL",
    "gn:name":"El Berrendo",
    "gn:population":0,
    "gn:timezone":"America/Chihuahua",
    "iso:country":"MX",
    "name:und_x_variant":[
        "Hacienda El Berrendo",
        "Berrendo",
        "El Berrendo"
    ],
    "wof:name":"El Berrendo",
    "wof:placetype":"locality"
},
  "geometry": {"coordinates":[-104.64689,27.33542000000001],"type":"Point"}
}