{
  "type": "Feature",
  "properties": {
    "gn:admin1_code":"25",
    "gn:admin2_code":"18.0",
    "gn:asciiname":"Rio Viejo",
    "gn:country_code":"MX",
    "gn:dem":19,
    "gn:feature_class":"P",
    "gn:feature_code":"PPL",
    "gn:name":"R\u00edo Viejo",
    "gn:population":491,
    "gn:timezone":"America/Mazatlan",
    "iso:country":"MX",
    "name:und_x_variant":[
        "R\u00edo Viejo"
    ],
    "wof:name":"Rio Viejo",
    "wof:placetype":"locality",
    "wof:population":491
},
  "geometry": {"coordinates":[-107.67833,24.77944],"type":"Point"}
}