{
  "type": "Feature",
  "properties": {
    "gn:admin1_code":"30.0",
    "gn:admin2_code":"123.0",
    "gn:asciiname":"Panotlan",
    "gn:country_code":"MX",
    "gn:dem":24,
    "gn:feature_class":"P",
    "gn:feature_code":"PPL",
    "gn:name":"Panotl\u00e1n",
    "gn:population":0,
    "gn:timezone":"America/Mexico_City",
    "iso:country":"MX",
    "name:spa_x_preferred":[
        "Panotl\u00e1n"
    ],
    "wof:name":"Panotlan",
    "wof:placetype":"locality"
},
  "geometry": {"coordinates":[-98.55513999999999,21.95705],"type":"Point"}
}