{
  "type": "Feature",
  "properties": {
    "gn:admin1_code":"26",
    "gn:admin2_code":"30",
    "gn:asciiname":"Agricola Oremor (Santa Patricia)",
    "gn:country_code":"MX",
    "gn:dem":83,
    "gn:feature_class":"P",
    "gn:feature_code":"PPL",
    "gn:name":"Agr\u00edcola Oremor (Santa Patricia)",
    "gn:population":14,
    "gn:timezone":"America/Hermosillo",
    "iso:country":"MX",
    "name:und_x_variant":[
        "Agr\u00edcola Oremor (Santa Patricia)"
    ],
    "wof:name":"Agricola Oremor (Santa Patricia)",
    "wof:placetype":"locality",
    "wof:population":14
},
  "geometry": {"coordinates":[-111.6925,29.17722],"type":"Point"}
}