{
  "type": "Feature",
  "properties": {
    "gn:admin1_code":"2",
    "gn:admin2_code":"2",
    "gn:asciiname":"Familia Vargas (Ejido Tabasco)",
    "gn:country_code":"MX",
    "gn:dem":23,
    "gn:feature_class":"P",
    "gn:feature_code":"PPL",
    "gn:name":"Familia Vargas (Ejido Tabasco)",
    "gn:population":14,
    "gn:timezone":"America/Tijuana",
    "iso:country":"MX",
    "wof:name":"Familia Vargas (Ejido Tabasco)",
    "wof:placetype":"locality",
    "wof:population":14
},
  "geometry": {"coordinates":[-114.88417,32.55972],"type":"Point"}
}