{
  "type": "Feature",
  "properties": {
    "gn:admin1_code":"14",
    "gn:admin2_code":"87.0",
    "gn:asciiname":"El Riito",
    "gn:country_code":"MX",
    "gn:dem":1286,
    "gn:feature_class":"P",
    "gn:feature_code":"PPL",
    "gn:name":"El Ri\u00edto",
    "gn:population":6,
    "gn:timezone":"America/Mexico_City",
    "iso:country":"MX",
    "name:und_x_variant":[
        "El Ri\u00edto"
    ],
    "wof:name":"El Riito",
    "wof:placetype":"locality",
    "wof:population":6
},
  "geometry": {"coordinates":[-103.21389000000001,19.40833],"type":"Point"}
}