{
  "type": "Feature",
  "properties": {
    "gn:admin1_code":"13",
    "gn:asciiname":"San Mateo Actipan",
    "gn:country_code":"MX",
    "gn:dem":2560,
    "gn:feature_class":"P",
    "gn:feature_code":"PPL",
    "gn:name":"San Mateo Actipan",
    "gn:population":0,
    "gn:timezone":"America/Mexico_City",
    "iso:country":"MX",
    "name:spa_x_preferred":[
        "San Mateo Actipac"
    ],
    "name:und_x_variant":[
        "Actipan",
        "San Mateo Actipan"
    ],
    "wof:name":"San Mateo Actipan",
    "wof:placetype":"locality"
},
  "geometry": {"coordinates":[-98.59684,19.61032],"type":"Point"}
}