{
  "type": "Feature",
  "properties": {
    "gn:admin1_code":"5",
    "gn:admin2_code":"4.0",
    "gn:asciiname":"Luis Espinoza",
    "gn:country_code":"MX",
    "gn:dem":812,
    "gn:feature_class":"P",
    "gn:feature_code":"PPL",
    "gn:name":"Luis Espinoza",
    "gn:population":0,
    "gn:timezone":"America/Mexico_City",
    "iso:country":"MX",
    "name:spa_x_preferred":[
        "Luis Espinoza"
    ],
    "name:und_x_variant":[
        "Luis Espinosa"
    ],
    "wof:name":"Luis Espinoza",
    "wof:placetype":"locality"
},
  "geometry": {"coordinates":[-91.62219,16.58814],"type":"Point"}
}