{
  "type": "Feature",
  "properties": {
    "gn:admin1_code":"2.0",
    "gn:admin2_code":"1.0",
    "gn:asciiname":"San Esteban",
    "gn:country_code":"MX",
    "gn:dem":1045,
    "gn:feature_class":"P",
    "gn:feature_code":"PPL",
    "gn:name":"San Esteban",
    "gn:population":0,
    "gn:timezone":"America/Tijuana",
    "iso:country":"MX",
    "name:spa_x_preferred":[
        "San Esteban"
    ],
    "wof:name":"San Esteban",
    "wof:placetype":"locality"
},
  "geometry": {"coordinates":[-116.05028,31.83111],"type":"Point"}
}