{
  "type": "Feature",
  "properties": {
    "gn:admin1_code":"16",
    "gn:admin2_code":"85",
    "gn:asciiname":"Las Canas",
    "gn:country_code":"MX",
    "gn:dem":2335,
    "gn:feature_class":"P",
    "gn:feature_code":"PPL",
    "gn:name":"Las Ca\u00f1as",
    "gn:population":15,
    "gn:timezone":"America/Mexico_City",
    "iso:country":"MX",
    "name:und_x_variant":[
        "Las Ca\u00f1as"
    ],
    "wof:name":"Las Canas",
    "wof:placetype":"locality",
    "wof:population":15
},
  "geometry": {"coordinates":[-102.38139,19.79],"type":"Point"}
}