{
  "type": "Feature",
  "properties": {
    "gn:admin1_code":"28.0",
    "gn:admin2_code":"3.0",
    "gn:asciiname":"Santa Amalia",
    "gn:country_code":"MX",
    "gn:dem":21,
    "gn:feature_class":"P",
    "gn:feature_code":"PPL",
    "gn:name":"Santa Amalia",
    "gn:population":0,
    "gn:timezone":"America/Monterrey",
    "iso:country":"MX",
    "name:spa_x_preferred":[
        "Santa Amalia"
    ],
    "wof:name":"Santa Amalia",
    "wof:placetype":"locality"
},
  "geometry": {"coordinates":[-98.30361000000001,22.51333],"type":"Point"}
}