{
  "type": "Feature",
  "properties": {
    "gn:admin1_code":"12",
    "gn:admin2_code":"22",
    "gn:asciiname":"El Cuirindalito",
    "gn:country_code":"MX",
    "gn:dem":924,
    "gn:feature_class":"P",
    "gn:feature_code":"PPL",
    "gn:name":"El Cuirindalito",
    "gn:population":49,
    "gn:timezone":"America/Mexico_City",
    "iso:country":"MX",
    "wof:name":"El Cuirindalito",
    "wof:placetype":"locality",
    "wof:population":49
},
  "geometry": {"coordinates":[-101.04966,18.04023],"type":"Point"}
}