{
  "type": "Feature",
  "properties": {
    "gn:admin1_code":"6",
    "gn:admin2_code":"9.0",
    "gn:asciiname":"Gururabo",
    "gn:country_code":"MX",
    "gn:dem":2420,
    "gn:feature_class":"P",
    "gn:feature_code":"PPL",
    "gn:name":"Gur\u00farabo",
    "gn:population":0,
    "gn:timezone":"America/Chihuahua",
    "iso:country":"MX",
    "name:spa_x_preferred":[
        "Gur\u00farabo"
    ],
    "wof:name":"Gururabo",
    "wof:placetype":"locality"
},
  "geometry": {"coordinates":[-107.55826,27.68958],"type":"Point"}
}