{
  "type": "Feature",
  "properties": {
    "gn:admin1_code":"5",
    "gn:admin2_code":"78.0",
    "gn:asciiname":"Nuevo Corral Che'N el Angel",
    "gn:country_code":"MX",
    "gn:dem":2343,
    "gn:feature_class":"P",
    "gn:feature_code":"PPL",
    "gn:name":"Nuevo Corral Che'N el \u00c1ngel",
    "gn:population":225,
    "gn:timezone":"America/Mexico_City",
    "iso:country":"MX",
    "name:und_x_variant":[
        "Nuevo Corral Che'N el \u00c1ngel"
    ],
    "wof:name":"Nuevo Corral Che'N el Angel",
    "wof:placetype":"locality",
    "wof:population":225
},
  "geometry": {"coordinates":[-92.54889,16.69778],"type":"Point"}
}