{
  "type": "Feature",
  "properties": {
    "gn:admin1_code":"26",
    "gn:admin2_code":"30.0",
    "gn:asciiname":"La Mision",
    "gn:country_code":"MX",
    "gn:dem":48,
    "gn:feature_class":"P",
    "gn:feature_code":"PPL",
    "gn:name":"La Misi\u00f3n",
    "gn:population":21,
    "gn:timezone":"America/Hermosillo",
    "iso:country":"MX",
    "name:spa_x_preferred":[
        "La Misi\u00f3n"
    ],
    "wof:name":"La Mision",
    "wof:placetype":"locality",
    "wof:population":21
},
  "geometry": {"coordinates":[-111.57944000000001,28.85306],"type":"Point"}
}