{
  "type": "Feature",
  "properties": {
    "gn:admin1_code":"14.0",
    "gn:admin2_code":"116.0",
    "gn:asciiname":"Los Lares",
    "gn:country_code":"MX",
    "gn:dem":1962,
    "gn:feature_class":"P",
    "gn:feature_code":"PPL",
    "gn:name":"Los Lares",
    "gn:population":0,
    "gn:timezone":"America/Mexico_City",
    "iso:country":"MX",
    "name:spa_x_preferred":[
        "Los Lares"
    ],
    "wof:name":"Los Lares",
    "wof:placetype":"locality"
},
  "geometry": {"coordinates":[-102.64158999999999,21.62068],"type":"Point"}
}