{
  "type": "Feature",
  "properties": {
    "gn:admin1_code":"18",
    "gn:admin2_code":"3.0",
    "gn:asciiname":"Jocuixtle",
    "gn:country_code":"MX",
    "gn:dem":764,
    "gn:feature_class":"P",
    "gn:feature_code":"PPL",
    "gn:name":"Jocuixtle",
    "gn:population":6,
    "gn:timezone":"America/Mexico_City",
    "iso:country":"MX",
    "wof:name":"Jocuixtle",
    "wof:placetype":"locality",
    "wof:population":6
},
  "geometry": {"coordinates":[-104.38722,20.76972],"type":"Point"}
}