{
  "type": "Feature",
  "properties": {
    "gn:admin1_code":"14",
    "gn:admin2_code":"61.0",
    "gn:asciiname":"Las Penitas",
    "gn:country_code":"MX",
    "gn:dem":2792,
    "gn:feature_class":"P",
    "gn:feature_code":"PPL",
    "gn:name":"Las Pe\u00f1itas",
    "gn:population":7,
    "gn:timezone":"America/Mexico_City",
    "iso:country":"MX",
    "name:und_x_variant":[
        "Las Pe\u00f1itas"
    ],
    "wof:name":"Las Penitas",
    "wof:placetype":"locality",
    "wof:population":7
},
  "geometry": {"coordinates":[-103.875,22.10583],"type":"Point"}
}