{
  "type": "Feature",
  "properties": {
    "gn:admin1_code":"24",
    "gn:admin2_code":"54.0",
    "gn:asciiname":"Joya del Durazno",
    "gn:country_code":"MX",
    "gn:dem":1162,
    "gn:feature_class":"P",
    "gn:feature_code":"PPL",
    "gn:name":"Joya del Durazno",
    "gn:population":64,
    "gn:timezone":"America/Mexico_City",
    "iso:country":"MX",
    "wof:name":"Joya del Durazno",
    "wof:placetype":"locality",
    "wof:population":64
},
  "geometry": {"coordinates":[-99.0625,21.35583],"type":"Point"}
}