{
  "type": "Feature",
  "properties": {
    "gn:admin1_code":"20",
    "gn:admin2_code":"208.0",
    "gn:asciiname":"Las Huertas",
    "gn:country_code":"MX",
    "gn:dem":1990,
    "gn:feature_class":"P",
    "gn:feature_code":"PPL",
    "gn:name":"Las Huertas",
    "gn:population":61,
    "gn:timezone":"America/Mexico_City",
    "iso:country":"MX",
    "wof:name":"Las Huertas",
    "wof:placetype":"locality",
    "wof:population":61
},
  "geometry": {"coordinates":[-97.86028,17.32139],"type":"Point"}
}