{
  "type": "Feature",
  "properties": {
    "gn:admin1_code":"28",
    "gn:admin2_code":"22.0",
    "gn:asciiname":"Feliciano (Miguel Villarreal Garza)",
    "gn:country_code":"MX",
    "gn:dem":12,
    "gn:feature_class":"P",
    "gn:feature_code":"PPL",
    "gn:name":"Feliciano (Miguel Villarreal Garza)",
    "gn:population":7,
    "gn:timezone":"America/Matamoros",
    "iso:country":"MX",
    "wof:name":"Feliciano (Miguel Villarreal Garza)",
    "wof:placetype":"locality",
    "wof:population":7
},
  "geometry": {"coordinates":[-97.63388999999999,25.79194],"type":"Point"}
}