{
  "type": "Feature",
  "properties": {
    "gn:admin1_code":"5.0",
    "gn:admin2_code":"23.0",
    "gn:asciiname":"Batojtic",
    "gn:country_code":"MX",
    "gn:dem":2321,
    "gn:feature_class":"P",
    "gn:feature_code":"PPL",
    "gn:name":"Batojtic",
    "gn:population":0,
    "gn:timezone":"America/Mexico_City",
    "iso:country":"MX",
    "name:spa_x_preferred":[
        "Batojtic"
    ],
    "wof:name":"Batojtic",
    "wof:placetype":"locality"
},
  "geometry": {"coordinates":[-92.61077,16.84307],"type":"Point"}
}