{
  "type": "Feature",
  "properties": {
    "gn:admin1_code":"5",
    "gn:admin2_code":"15.0",
    "gn:asciiname":"Bellavista",
    "gn:country_code":"MX",
    "gn:dem":1158,
    "gn:feature_class":"P",
    "gn:feature_code":"PPL",
    "gn:name":"Bellavista",
    "gn:population":525,
    "gn:timezone":"America/Mexico_City",
    "iso:country":"MX",
    "wof:name":"Bellavista",
    "wof:placetype":"locality",
    "wof:population":525
},
  "geometry": {"coordinates":[-92.14944,15.07611],"type":"Point"}
}