{
  "type": "Feature",
  "properties": {
    "gn:admin1_code":"11",
    "gn:admin2_code":"3.0",
    "gn:asciiname":"San Miguelito Dos",
    "gn:country_code":"MX",
    "gn:dem":1865,
    "gn:feature_class":"P",
    "gn:feature_code":"PPL",
    "gn:name":"San Miguelito Dos",
    "gn:population":311,
    "gn:timezone":"America/Mexico_City",
    "iso:country":"MX",
    "wof:name":"San Miguelito Dos",
    "wof:placetype":"locality",
    "wof:population":311
},
  "geometry": {"coordinates":[-100.80110999999999,21.00167],"type":"Point"}
}