{
  "type": "Feature",
  "properties": {
    "gn:admin1_code":"21.0",
    "gn:admin2_code":"114.0",
    "gn:asciiname":"Potreros del Sur",
    "gn:country_code":"MX",
    "gn:dem":2111,
    "gn:feature_class":"P",
    "gn:feature_code":"PPL",
    "gn:name":"Potreros del Sur",
    "gn:population":0,
    "gn:timezone":"America/Mexico_City",
    "iso:country":"MX",
    "name:spa_x_preferred":[
        "Potreros del Sur"
    ],
    "wof:name":"Potreros del Sur",
    "wof:placetype":"locality"
},
  "geometry": {"coordinates":[-98.22955,18.97479],"type":"Point"}
}