{
  "type": "Feature",
  "properties": {
    "gn:admin1_code":"5.0",
    "gn:admin2_code":"59.0",
    "gn:asciiname":"Marachi",
    "gn:country_code":"MX",
    "gn:dem":105,
    "gn:feature_class":"P",
    "gn:feature_code":"PPL",
    "gn:name":"Marach\u00ed",
    "gn:population":0,
    "gn:timezone":"America/Mexico_City",
    "iso:country":"MX",
    "name:spa_x_preferred":[
        "Macachi"
    ],
    "name:spa_x_variant":[
        "Marach\u00ed"
    ],
    "wof:name":"Marachi",
    "wof:placetype":"locality"
},
  "geometry": {"coordinates":[-90.92435999999999,16.82139],"type":"Point"}
}