{
  "type": "Feature",
  "properties": {
    "gn:admin1_code":"5",
    "gn:admin2_code":"106",
    "gn:asciiname":"San Juanito",
    "gn:country_code":"MX",
    "gn:dem":739,
    "gn:feature_class":"P",
    "gn:feature_code":"PPL",
    "gn:name":"San Juanito",
    "gn:population":19,
    "gn:timezone":"America/Mexico_City",
    "iso:country":"MX",
    "name:ceb_x_preferred":[
        "San Juanito"
    ],
    "name:deu_x_preferred":[
        "San Juanito"
    ],
    "name:msa_x_preferred":[
        "San Juanito"
    ],
    "name:spa_x_preferred":[
        "San Juanito"
    ],
    "name:swe_x_preferred":[
        "San Juanito"
    ],
    "name:tgl_x_preferred":[
        "San Juanito"
    ],
    "name:vie_x_preferred":[
        "San Juanito"
    ],
    "wof:name":"San Juanito",
    "wof:placetype":"locality",
    "wof:population":19
},
  "geometry": {"coordinates":[-92.53944,16.34111],"type":"Point"}
}