{
  "type": "Feature",
  "properties": {
    "gn:admin1_code":"11.0",
    "gn:admin2_code":"14.0",
    "gn:asciiname":"Colegiales",
    "gn:country_code":"MX",
    "gn:dem":2008,
    "gn:feature_class":"P",
    "gn:feature_code":"PPL",
    "gn:name":"Colegiales",
    "gn:population":0,
    "gn:timezone":"America/Mexico_City",
    "iso:country":"MX",
    "name:ceb_x_preferred":[
        "Colegiales"
    ],
    "name:deu_x_preferred":[
        "Colegiales"
    ],
    "name:fra_x_preferred":[
        "Colegiales"
    ],
    "name:ita_x_preferred":[
        "Colegiales"
    ],
    "name:jpn_x_preferred":[
        "\u30b3\u30ec\u30d2\u30a2\u30ec\u30b9"
    ],
    "name:lat_x_preferred":[
        "Colegiales"
    ],
    "name:lit_x_preferred":[
        "Kolechjalesas"
    ],
    "name:mlg_x_preferred":[
        "Colegiales"
    ],
    "name:nld_x_preferred":[
        "Colegiales"
    ],
    "name:por_x_preferred":[
        "Colegiales"
    ],
    "name:spa_x_preferred":[
        "Colegiales"
    ],
    "name:swe_x_preferred":[
        "Colegiales"
    ],
    "wof:name":"Colegiales",
    "wof:placetype":"locality"
},
  "geometry": {"coordinates":[-100.7128,21.24095],"type":"Point"}
}