{
  "type": "Feature",
  "properties": {
    "gn:admin1_code":"14.0",
    "gn:admin2_code":"68.0",
    "gn:asciiname":"Espinos de Carreon",
    "gn:cc2":"MX",
    "gn:country_code":"MX",
    "gn:dem":1129,
    "gn:feature_class":"P",
    "gn:feature_code":"PPL",
    "gn:name":"Espinos de Carre\u00f3n",
    "gn:population":0,
    "gn:timezone":"America/Mexico_City",
    "iso:country":"MX",
    "name:und_x_variant":[
        "Espinos",
        "Espinos de Carre\u00f3n"
    ],
    "wof:name":"Espinos de Carreon",
    "wof:placetype":"locality"
},
  "geometry": {"coordinates":[-104.56667,19.86667000000001],"type":"Point"}
}