{
  "type": "Feature",
  "properties": {
    "gn:admin1_code":"9",
    "gn:admin2_code":"13",
    "gn:asciiname":"Tixculco",
    "gn:country_code":"MX",
    "gn:dem":2410,
    "gn:feature_class":"P",
    "gn:feature_code":"PPL",
    "gn:name":"Tixculco",
    "gn:population":13,
    "gn:timezone":"America/Mexico_City",
    "iso:country":"MX",
    "wof:name":"Tixculco",
    "wof:placetype":"locality",
    "wof:population":13
},
  "geometry": {"coordinates":[-99.05417,19.22194],"type":"Point"}
}