{
  "type": "Feature",
  "properties": {
    "gn:admin1_code":"26.0",
    "gn:asciiname":"Los Torunos",
    "gn:country_code":"MX",
    "gn:dem":524,
    "gn:feature_class":"P",
    "gn:feature_code":"PPL",
    "gn:name":"Los Torunos",
    "gn:population":0,
    "gn:timezone":"America/Hermosillo",
    "iso:country":"MX",
    "name:spa_x_preferred":[
        "Los Torunos"
    ],
    "wof:name":"Los Torunos",
    "wof:placetype":"locality"
},
  "geometry": {"coordinates":[-109.44819,27.87104],"type":"Point"}
}