{
  "type": "Feature",
  "properties": {
    "gn:admin1_code":"21",
    "gn:admin2_code":"158",
    "gn:asciiname":"El Frijolillo",
    "gn:country_code":"MX",
    "gn:dem":280,
    "gn:feature_class":"P",
    "gn:feature_code":"PPL",
    "gn:name":"El Frijolillo",
    "gn:population":11,
    "gn:timezone":"America/Mexico_City",
    "iso:country":"MX",
    "wof:name":"El Frijolillo",
    "wof:placetype":"locality",
    "wof:population":11
},
  "geometry": {"coordinates":[-97.39722999999999,20.16306],"type":"Point"}
}