{
  "type": "Feature",
  "properties": {
    "gn:admin1_code":"28.0",
    "gn:admin2_code":"16.0",
    "gn:asciiname":"Marroquin",
    "gn:country_code":"MX",
    "gn:dem":283,
    "gn:feature_class":"P",
    "gn:feature_code":"PPL",
    "gn:name":"Marroqu\u00edn",
    "gn:population":0,
    "gn:timezone":"America/Monterrey",
    "iso:country":"MX",
    "name:spa_x_preferred":[
        "Marroqu\u00edn"
    ],
    "wof:name":"Marroquin",
    "wof:placetype":"locality"
},
  "geometry": {"coordinates":[-99.31652,24.03806],"type":"Point"}
}