{
  "type": "Feature",
  "properties": {
    "gn:admin1_code":"10",
    "gn:admin2_code":"13.0",
    "gn:asciiname":"Rancho Blanco",
    "gn:country_code":"MX",
    "gn:dem":1166,
    "gn:feature_class":"P",
    "gn:feature_code":"PPL",
    "gn:name":"Rancho Blanco",
    "gn:population":0,
    "gn:timezone":"America/Monterrey",
    "iso:country":"MX",
    "name:spa_x_preferred":[
        "Rancho Blanco"
    ],
    "wof:name":"Rancho Blanco",
    "wof:placetype":"locality"
},
  "geometry": {"coordinates":[-104.05779,26.41446],"type":"Point"}
}