{
  "type": "Feature",
  "properties": {
    "gn:admin1_code":"2",
    "gn:admin2_code":"1.0",
    "gn:asciiname":"Las Cruces",
    "gn:country_code":"MX",
    "gn:dem":291,
    "gn:feature_class":"P",
    "gn:feature_code":"PPL",
    "gn:name":"Las Cruces",
    "gn:population":0,
    "gn:timezone":"America/Tijuana",
    "iso:country":"MX",
    "name:spa_x_preferred":[
        "Las Cruces"
    ],
    "name:und_x_variant":[
        "Rancho Mesa las Cruces"
    ],
    "wof:name":"Las Cruces",
    "wof:placetype":"locality"
},
  "geometry": {"coordinates":[-116.37313,31.40797],"type":"Point"}
}