{
  "type": "Feature",
  "properties": {
    "gn:admin1_code":"11",
    "gn:admin2_code":"8",
    "gn:asciiname":"Rancho Nuevo del Venado",
    "gn:country_code":"MX",
    "gn:dem":1908,
    "gn:feature_class":"P",
    "gn:feature_code":"PPL",
    "gn:name":"Rancho Nuevo del Venado",
    "gn:population":34,
    "gn:timezone":"America/Mexico_City",
    "iso:country":"MX",
    "wof:name":"Rancho Nuevo del Venado",
    "wof:placetype":"locality",
    "wof:population":34
},
  "geometry": {"coordinates":[-101.98556000000001,20.66278],"type":"Point"}
}