{
  "type": "Feature",
  "properties": {
    "gn:admin1_code":"28",
    "gn:admin2_code":"22.0",
    "gn:asciiname":"Graneros, Semillas y Forrajes",
    "gn:country_code":"MX",
    "gn:dem":13,
    "gn:feature_class":"P",
    "gn:feature_code":"PPL",
    "gn:name":"Graneros, Semillas y Forrajes",
    "gn:population":6,
    "gn:timezone":"America/Matamoros",
    "iso:country":"MX",
    "wof:name":"Graneros, Semillas y Forrajes",
    "wof:placetype":"locality",
    "wof:population":6
},
  "geometry": {"coordinates":[-97.63889,25.85167],"type":"Point"}
}