{
  "type": "Feature",
  "properties": {
    "gn:admin1_code":"7",
    "gn:admin2_code":"9",
    "gn:asciiname":"Lazarin Gonzalez",
    "gn:country_code":"MX",
    "gn:dem":1111,
    "gn:feature_class":"P",
    "gn:feature_code":"PPL",
    "gn:name":"Lazar\u00edn Gonz\u00e1lez",
    "gn:population":29,
    "gn:timezone":"America/Monterrey",
    "iso:country":"MX",
    "name:und_x_variant":[
        "Lazar\u00edn Gonz\u00e1lez"
    ],
    "wof:name":"Lazarin Gonzalez",
    "wof:placetype":"locality",
    "wof:population":29
},
  "geometry": {"coordinates":[-103.24401,25.76073],"type":"Point"}
}