{
  "type": "Feature",
  "properties": {
    "gn:admin1_code":"16",
    "gn:admin2_code":"47.0",
    "gn:asciiname":"Las Anonas",
    "gn:country_code":"MX",
    "gn:dem":1587,
    "gn:feature_class":"P",
    "gn:feature_code":"PPL",
    "gn:name":"Las Anonas",
    "gn:population":550,
    "gn:timezone":"America/Mexico_City",
    "iso:country":"MX",
    "wof:name":"Las Anonas",
    "wof:placetype":"locality",
    "wof:population":550
},
  "geometry": {"coordinates":[-100.50528,19.48556],"type":"Point"}
}