{
  "type": "Feature",
  "properties": {
    "gn:admin1_code":"23",
    "gn:admin2_code":"2.0",
    "gn:asciiname":"Xcopoil",
    "gn:country_code":"MX",
    "gn:dem":31,
    "gn:feature_class":"P",
    "gn:feature_code":"PPL",
    "gn:name":"Xcopoil",
    "gn:population":0,
    "gn:timezone":"America/Cancun",
    "iso:country":"MX",
    "name:spa_x_preferred":[
        "Xcopoil"
    ],
    "wof:name":"Xcopoil",
    "wof:placetype":"locality"
},
  "geometry": {"coordinates":[-88.39596,20.11816],"type":"Point"}
}