{
  "type": "Feature",
  "properties": {
    "gn:admin1_code":"14",
    "gn:admin2_code":"111.0",
    "gn:asciiname":"El Cerro de Ramblas",
    "gn:country_code":"MX",
    "gn:dem":1975,
    "gn:feature_class":"P",
    "gn:feature_code":"PPL",
    "gn:name":"El Cerro de Ramblas",
    "gn:population":6,
    "gn:timezone":"America/Mexico_City",
    "iso:country":"MX",
    "wof:name":"El Cerro de Ramblas",
    "wof:placetype":"locality",
    "wof:population":6
},
  "geometry": {"coordinates":[-102.66139,21.02111],"type":"Point"}
}