{
  "type": "Feature",
  "properties": {
    "gn:admin1_code":"26.0",
    "gn:asciiname":"Tepeguaje",
    "gn:country_code":"MX",
    "gn:dem":451,
    "gn:feature_class":"P",
    "gn:feature_code":"PPL",
    "gn:name":"Tepeguaje",
    "gn:population":0,
    "gn:timezone":"America/Hermosillo",
    "iso:country":"MX",
    "name:spa_x_preferred":[
        "Tepeguaje"
    ],
    "wof:name":"Tepeguaje",
    "wof:placetype":"locality"
},
  "geometry": {"coordinates":[-109.39803999999999,27.85626],"type":"Point"}
}