{
  "type": "Feature",
  "properties": {
    "gn:admin1_code":"30",
    "gn:admin2_code":"174.0",
    "gn:asciiname":"Amapa (El Pochote)",
    "gn:country_code":"MX",
    "gn:dem":87,
    "gn:feature_class":"P",
    "gn:feature_code":"PPL",
    "gn:name":"Amapa (El Pochote)",
    "gn:population":6,
    "gn:timezone":"America/Mexico_City",
    "iso:country":"MX",
    "wof:name":"Amapa (El Pochote)",
    "wof:placetype":"locality",
    "wof:population":6
},
  "geometry": {"coordinates":[-96.41861,18.51806],"type":"Point"}
}