{
  "type": "Feature",
  "properties": {
    "gn:admin1_code":"10",
    "gn:admin2_code":"14",
    "gn:asciiname":"El Encino",
    "gn:country_code":"MX",
    "gn:dem":2018,
    "gn:feature_class":"P",
    "gn:feature_code":"PPL",
    "gn:name":"El Encino",
    "gn:population":11,
    "gn:timezone":"America/Monterrey",
    "iso:country":"MX",
    "wof:name":"El Encino",
    "wof:placetype":"locality",
    "wof:population":11
},
  "geometry": {"coordinates":[-104.42135,22.90864],"type":"Point"}
}