{
  "type": "Feature",
  "properties": {
    "gn:admin1_code":"11.0",
    "gn:admin2_code":"30.0",
    "gn:asciiname":"San Jose de la Pena",
    "gn:country_code":"MX",
    "gn:dem":2197,
    "gn:feature_class":"P",
    "gn:feature_code":"PPL",
    "gn:name":"San Jos\u00e9 de la Pe\u00f1a",
    "gn:population":0,
    "gn:timezone":"America/Mexico_City",
    "iso:country":"MX",
    "name:spa_x_preferred":[
        "San Jos\u00e9 de la Pe\u00f1a"
    ],
    "name:und_x_variant":[
        "Pe\u00f1a San Jos\u00e9"
    ],
    "wof:name":"San Jose de la Pena",
    "wof:placetype":"locality"
},
  "geometry": {"coordinates":[-101.27484,21.44888],"type":"Point"}
}