{
  "type": "Feature",
  "properties": {
    "gn:admin1_code":"7.0",
    "gn:admin2_code":"20.0",
    "gn:asciiname":"El Nogalito",
    "gn:country_code":"MX",
    "gn:dem":572,
    "gn:feature_class":"P",
    "gn:feature_code":"PPL",
    "gn:name":"El Nogalito",
    "gn:population":0,
    "gn:timezone":"America/Monterrey",
    "iso:country":"MX",
    "name:spa_x_preferred":[
        "El Nogalito"
    ],
    "wof:name":"El Nogalito",
    "wof:placetype":"locality"
},
  "geometry": {"coordinates":[-101.46898,27.80343],"type":"Point"}
}