{
  "type": "Feature",
  "properties": {
    "gn:admin1_code":"5",
    "gn:admin2_code":"89.0",
    "gn:asciiname":"Vega de los Molinos",
    "gn:country_code":"MX",
    "gn:dem":1862,
    "gn:feature_class":"P",
    "gn:feature_code":"PPL",
    "gn:name":"Vega de los Molinos",
    "gn:population":165,
    "gn:timezone":"America/Mexico_City",
    "iso:country":"MX",
    "wof:name":"Vega de los Molinos",
    "wof:placetype":"locality",
    "wof:population":165
},
  "geometry": {"coordinates":[-92.20184999999999,15.21994],"type":"Point"}
}