{
  "type": "Feature",
  "properties": {
    "gn:admin1_code":"32",
    "gn:admin2_code":"21.0",
    "gn:asciiname":"La Mesa de los Cielos",
    "gn:country_code":"MX",
    "gn:dem":2214,
    "gn:feature_class":"P",
    "gn:feature_code":"PPL",
    "gn:name":"La Mesa de los Cielos",
    "gn:population":0,
    "gn:timezone":"America/Mexico_City",
    "iso:country":"MX",
    "name:spa_x_preferred":[
        "La Mesa de los Cielos"
    ],
    "wof:name":"La Mesa de los Cielos",
    "wof:placetype":"locality"
},
  "geometry": {"coordinates":[-103.81896999999999,23.25296],"type":"Point"}
}