{
  "type": "Feature",
  "properties": {
    "gn:admin1_code":"10",
    "gn:admin2_code":"14.0",
    "gn:asciiname":"Mesa de la Torrecilla",
    "gn:country_code":"MX",
    "gn:dem":2439,
    "gn:feature_class":"P",
    "gn:feature_code":"PPL",
    "gn:name":"Mesa de la Torrecilla",
    "gn:population":66,
    "gn:timezone":"America/Monterrey",
    "iso:country":"MX",
    "wof:name":"Mesa de la Torrecilla",
    "wof:placetype":"locality",
    "wof:population":66
},
  "geometry": {"coordinates":[-104.33278,22.455],"type":"Point"}
}