{
  "type": "Feature",
  "properties": {
    "gn:admin1_code":"5",
    "gn:admin2_code":"108.0",
    "gn:asciiname":"Nandalonda",
    "gn:country_code":"MX",
    "gn:dem":544,
    "gn:feature_class":"P",
    "gn:feature_code":"PPL",
    "gn:name":"Nandalonda",
    "gn:population":5,
    "gn:timezone":"America/Mexico_City",
    "iso:country":"MX",
    "wof:name":"Nandalonda",
    "wof:placetype":"locality",
    "wof:population":5
},
  "geometry": {"coordinates":[-93.22528,16.26361],"type":"Point"}
}