{
  "type": "Feature",
  "properties": {
    "gn:admin1_code":"13",
    "gn:admin2_code":"44.0",
    "gn:asciiname":"San Sebastian Tenochtitlan",
    "gn:country_code":"MX",
    "gn:dem":2247,
    "gn:feature_class":"P",
    "gn:feature_code":"PPL",
    "gn:name":"San Sebasti\u00e1n Tenochtitl\u00e1n",
    "gn:population":0,
    "gn:timezone":"America/Mexico_City",
    "iso:country":"MX",
    "name:spa_x_preferred":[
        "San Sebasti\u00e1n Tenochtitl\u00e1n"
    ],
    "name:und_x_variant":[
        "San Sebasti\u00e1n",
        "San Sebasti\u00e1n Tenoxtitl\u00e1n"
    ],
    "wof:name":"San Sebastian Tenochtitlan",
    "wof:placetype":"locality"
},
  "geometry": {"coordinates":[-99.68879,20.27988],"type":"Point"}
}