{
  "type": "Feature",
  "properties": {
    "gn:admin1_code":"14",
    "gn:admin2_code":"66.0",
    "gn:asciiname":"Tlachichilco del Carmen",
    "gn:country_code":"MX",
    "gn:dem":1539,
    "gn:feature_class":"P",
    "gn:feature_code":"PPL",
    "gn:name":"Tlachichilco del Carmen",
    "gn:population":437,
    "gn:timezone":"America/Mexico_City",
    "iso:country":"MX",
    "wof:name":"Tlachichilco del Carmen",
    "wof:placetype":"locality",
    "wof:population":437
},
  "geometry": {"coordinates":[-103.08889000000001,20.33361],"type":"Point"}
}