{
  "type": "Feature",
  "properties": {
    "gn:admin1_code":"21",
    "gn:admin2_code":"19.0",
    "gn:asciiname":"Techichila (El Jagueey)",
    "gn:country_code":"MX",
    "gn:dem":1882,
    "gn:feature_class":"P",
    "gn:feature_code":"PPL",
    "gn:name":"Techichila (El Jag\u00fcey)",
    "gn:population":9,
    "gn:timezone":"America/Mexico_City",
    "iso:country":"MX",
    "name:und_x_variant":[
        "Techichila (El Jag\u00fcey)"
    ],
    "wof:name":"Techichila (El Jagueey)",
    "wof:placetype":"locality",
    "wof:population":9
},
  "geometry": {"coordinates":[-98.38164,18.92654],"type":"Point"}
}