{
  "type": "Feature",
  "properties": {
    "gn:admin1_code":"6",
    "gn:admin2_code":"27.0",
    "gn:asciiname":"Paraje Chinamachi",
    "gn:country_code":"MX",
    "gn:dem":1203,
    "gn:feature_class":"P",
    "gn:feature_code":"PPL",
    "gn:name":"Paraje Chinamachi",
    "gn:population":0,
    "gn:timezone":"America/Chihuahua",
    "iso:country":"MX",
    "name:spa_x_preferred":[
        "Paraje Chinamachi"
    ],
    "wof:name":"Paraje Chinamachi",
    "wof:placetype":"locality"
},
  "geometry": {"coordinates":[-106.96454,26.65269],"type":"Point"}
}