{
  "type": "Feature",
  "properties": {
    "gn:admin1_code":"4",
    "gn:admin2_code":"11.0",
    "gn:asciiname":"El Pimiental Dos",
    "gn:country_code":"MX",
    "gn:dem":118,
    "gn:feature_class":"P",
    "gn:feature_code":"PPL",
    "gn:name":"El Pimiental Dos",
    "gn:population":260,
    "gn:timezone":"America/Merida",
    "iso:country":"MX",
    "wof:name":"El Pimiental Dos",
    "wof:placetype":"locality",
    "wof:population":260
},
  "geometry": {"coordinates":[-90.45889,18.48639],"type":"Point"}
}