{
  "type": "Feature",
  "properties": {
    "gn:admin1_code":"16",
    "gn:admin2_code":"99.0",
    "gn:asciiname":"La Colonia",
    "gn:country_code":"MX",
    "gn:dem":532,
    "gn:feature_class":"P",
    "gn:feature_code":"PPL",
    "gn:name":"La Colonia",
    "gn:population":250,
    "gn:timezone":"America/Mexico_City",
    "iso:country":"MX",
    "wof:name":"La Colonia",
    "wof:placetype":"locality",
    "wof:population":250
},
  "geometry": {"coordinates":[-100.66444,19.15889],"type":"Point"}
}