{
  "type": "Feature",
  "properties": {
    "gn:admin1_code":"16.0",
    "gn:admin2_code":"9.0",
    "gn:asciiname":"Buenavista del Sur",
    "gn:country_code":"MX",
    "gn:dem":1289,
    "gn:feature_class":"P",
    "gn:feature_code":"PPL",
    "gn:name":"Buenavista del Sur",
    "gn:population":0,
    "gn:timezone":"America/Mexico_City",
    "iso:country":"MX",
    "name:spa_x_preferred":[
        "Buenavista del Sur"
    ],
    "name:und_x_variant":[
        "Buena Vista"
    ],
    "wof:name":"Buenavista del Sur",
    "wof:placetype":"locality"
},
  "geometry": {"coordinates":[-101.76853,19.05664],"type":"Point"}
}