{
  "type": "Feature",
  "properties": {
    "gn:admin1_code":"19.0",
    "gn:admin2_code":"16.0",
    "gn:asciiname":"Kilometro Sesenta y Cuatro",
    "gn:country_code":"MX",
    "gn:dem":386,
    "gn:feature_class":"P",
    "gn:feature_code":"PPL",
    "gn:name":"Kil\u00f3metro Sesenta y Cuatro",
    "gn:population":0,
    "gn:timezone":"America/Monterrey",
    "iso:country":"MX",
    "name:spa_x_preferred":[
        "Kil\u00f3metro Sesenta y Cuatro"
    ],
    "wof:name":"Kilometro Sesenta y Cuatro",
    "wof:placetype":"locality"
},
  "geometry": {"coordinates":[-99.812,25.89106],"type":"Point"}
}