{
  "type": "Feature",
  "properties": {
    "gn:admin1_code":"27.0",
    "gn:admin2_code":"1.0",
    "gn:asciiname":"El Rosarito",
    "gn:country_code":"MX",
    "gn:dem":44,
    "gn:feature_class":"P",
    "gn:feature_code":"PPL",
    "gn:name":"El Rosarito",
    "gn:population":0,
    "gn:timezone":"America/Mexico_City",
    "iso:country":"MX",
    "name:spa_x_preferred":[
        "Rosarito"
    ],
    "name:spa_x_variant":[
        "El Rosarito"
    ],
    "wof:name":"El Rosarito",
    "wof:placetype":"locality"
},
  "geometry": {"coordinates":[-91.21205999999999,17.87373],"type":"Point"}
}