{
  "type": "Feature",
  "properties": {
    "gn:admin1_code":"21",
    "gn:admin2_code":"147",
    "gn:asciiname":"El Tecuane",
    "gn:country_code":"MX",
    "gn:dem":1823,
    "gn:feature_class":"P",
    "gn:feature_code":"PPL",
    "gn:name":"El Tecuane",
    "gn:population":40,
    "gn:timezone":"America/Mexico_City",
    "iso:country":"MX",
    "wof:name":"El Tecuane",
    "wof:placetype":"locality",
    "wof:population":40
},
  "geometry": {"coordinates":[-98.08553000000001,18.38407],"type":"Point"}
}