{
  "type": "Feature",
  "properties": {
    "gn:admin1_code":"26",
    "gn:admin2_code":"21.0",
    "gn:asciiname":"La Laguna Colorada",
    "gn:country_code":"MX",
    "gn:dem":521,
    "gn:feature_class":"P",
    "gn:feature_code":"PPL",
    "gn:name":"La Laguna Colorada",
    "gn:population":0,
    "gn:timezone":"America/Hermosillo",
    "iso:country":"MX",
    "name:spa_x_preferred":[
        "La Laguna Colorada"
    ],
    "wof:name":"La Laguna Colorada",
    "wof:placetype":"locality"
},
  "geometry": {"coordinates":[-110.01448000000001,28.75289],"type":"Point"}
}