{
  "type": "Feature",
  "properties": {
    "gn:admin1_code":"21",
    "gn:admin2_code":"10.0",
    "gn:asciiname":"Cruz Chichiltzi",
    "gn:country_code":"MX",
    "gn:dem":2554,
    "gn:feature_class":"P",
    "gn:feature_code":"PPL",
    "gn:name":"Cruz Chichiltzi",
    "gn:population":179,
    "gn:timezone":"America/Mexico_City",
    "iso:country":"MX",
    "wof:name":"Cruz Chichiltzi",
    "wof:placetype":"locality",
    "wof:population":179
},
  "geometry": {"coordinates":[-97.07015,18.3957],"type":"Point"}
}