{
  "type": "Feature",
  "properties": {
    "gn:admin1_code":"23",
    "gn:admin2_code":"4.0",
    "gn:asciiname":"Chunaba",
    "gn:cc2":"BZ",
    "gn:country_code":"MX",
    "gn:dem":13,
    "gn:feature_class":"P",
    "gn:feature_code":"PPL",
    "gn:name":"Chunaba",
    "gn:population":0,
    "gn:timezone":"America/Cancun",
    "iso:country":"MX",
    "name:und_x_variant":[
        "Chumaba"
    ],
    "wof:name":"Chunaba",
    "wof:placetype":"locality"
},
  "geometry": {"coordinates":[-88.77353000000002,18.01166],"type":"Point"}
}