{
  "type": "Feature",
  "properties": {
    "gn:admin1_code":"25",
    "gn:admin2_code":"4.0",
    "gn:asciiname":"Potrerillos",
    "gn:country_code":"MX",
    "gn:dem":1522,
    "gn:feature_class":"P",
    "gn:feature_code":"PPL",
    "gn:name":"Potrerillos",
    "gn:population":502,
    "gn:timezone":"America/Mazatlan",
    "iso:country":"MX",
    "name:ceb_x_preferred":[
        "Potrerillos"
    ],
    "name:deu_x_preferred":[
        "Potrerillos"
    ],
    "name:fra_x_preferred":[
        "Potrerillos"
    ],
    "name:ita_x_preferred":[
        "Potrerillos"
    ],
    "name:nld_x_preferred":[
        "Potrerillos"
    ],
    "name:pol_x_preferred":[
        "Potrerillos"
    ],
    "name:por_x_preferred":[
        "Potrerillos"
    ],
    "name:spa_x_preferred":[
        "Potrerillos"
    ],
    "name:swe_x_preferred":[
        "Potrerillos"
    ],
    "wof:name":"Potrerillos",
    "wof:placetype":"locality",
    "wof:population":502
},
  "geometry": {"coordinates":[-105.82805999999999,23.45333],"type":"Point"}
}