{
  "type": "Feature",
  "properties": {
    "gn:admin1_code":"8.0",
    "gn:admin2_code":"2.0",
    "gn:asciiname":"El Santo Nino",
    "gn:country_code":"MX",
    "gn:dem":610,
    "gn:feature_class":"P",
    "gn:feature_code":"PPL",
    "gn:name":"El Santo Ni\u00f1o",
    "gn:population":0,
    "gn:timezone":"America/Mexico_City",
    "iso:country":"MX",
    "name:spa_x_preferred":[
        "El Santo Ni\u00f1o"
    ],
    "wof:name":"El Santo Nino",
    "wof:placetype":"locality"
},
  "geometry": {"coordinates":[-103.5158,19.19754],"type":"Point"}
}