{
  "type": "Feature",
  "properties": {
    "gn:admin1_code":"11.0",
    "gn:admin2_code":"8.0",
    "gn:asciiname":"Las Coloradas",
    "gn:country_code":"MX",
    "gn:dem":1785,
    "gn:feature_class":"P",
    "gn:feature_code":"PPL",
    "gn:name":"Las Coloradas",
    "gn:population":181,
    "gn:timezone":"America/Mexico_City",
    "iso:country":"MX",
    "name:spa_x_preferred":[
        "Las Coloradas"
    ],
    "wof:name":"Las Coloradas",
    "wof:placetype":"locality",
    "wof:population":181
},
  "geometry": {"coordinates":[-101.72272,20.77581],"type":"Point"}
}