{
  "type": "Feature",
  "properties": {
    "gn:admin1_code":"12",
    "gn:admin2_code":"47",
    "gn:asciiname":"Llano de la Merced",
    "gn:country_code":"MX",
    "gn:dem":1628,
    "gn:feature_class":"P",
    "gn:feature_code":"PPL",
    "gn:name":"Llano de la Merced",
    "gn:population":47,
    "gn:timezone":"America/Mexico_City",
    "iso:country":"MX",
    "wof:name":"Llano de la Merced",
    "wof:placetype":"locality",
    "wof:population":47
},
  "geometry": {"coordinates":[-99.90088,18.49853],"type":"Point"}
}