{
  "type": "Feature",
  "properties": {
    "gn:admin1_code":"28.0",
    "gn:admin2_code":"35.0",
    "gn:asciiname":"El Chile",
    "gn:country_code":"MX",
    "gn:dem":-9999,
    "gn:feature_class":"P",
    "gn:feature_code":"PPL",
    "gn:name":"El Chile",
    "gn:population":0,
    "gn:timezone":"America/Monterrey",
    "iso:country":"MX",
    "name:spa_x_preferred":[
        "El Chile"
    ],
    "wof:name":"El Chile",
    "wof:placetype":"locality"
},
  "geometry": {"coordinates":[-97.58472999999999,24.94227],"type":"Point"}
}