{
  "type": "Feature",
  "properties": {
    "gn:admin1_code":"19",
    "gn:admin2_code":"38.0",
    "gn:asciiname":"La Carreta Quebrada",
    "gn:country_code":"MX",
    "gn:dem":530,
    "gn:feature_class":"P",
    "gn:feature_code":"PPL",
    "gn:name":"La Carreta Quebrada",
    "gn:population":0,
    "gn:timezone":"America/Monterrey",
    "iso:country":"MX",
    "name:spa_x_preferred":[
        "La Carreta Quebrada"
    ],
    "wof:name":"La Carreta Quebrada",
    "wof:placetype":"locality"
},
  "geometry": {"coordinates":[-99.94528,25.13562],"type":"Point"}
}