{
  "type": "Feature",
  "properties": {
    "gn:admin1_code":"6.0",
    "gn:admin2_code":"63.0",
    "gn:asciiname":"Cienega del Rincon",
    "gn:country_code":"MX",
    "gn:dem":1947,
    "gn:feature_class":"P",
    "gn:feature_code":"PPL",
    "gn:name":"Ci\u00e9nega del Rinc\u00f3n",
    "gn:population":0,
    "gn:timezone":"America/Chihuahua",
    "iso:country":"MX",
    "name:spa_x_preferred":[
        "Ci\u00e9nega del Rinc\u00f3n"
    ],
    "wof:name":"Cienega del Rincon",
    "wof:placetype":"locality"
},
  "geometry": {"coordinates":[-107.87371,29.09744],"type":"Point"}
}