{
  "type": "Feature",
  "properties": {
    "gn:admin1_code":"6",
    "gn:admin2_code":"52.0",
    "gn:asciiname":"San Antonio del Bravo",
    "gn:country_code":"MX",
    "gn:dem":846,
    "gn:feature_class":"P",
    "gn:feature_code":"PPL",
    "gn:name":"San Antonio del Bravo",
    "gn:population":0,
    "gn:timezone":"America/Ojinaga",
    "iso:country":"MX",
    "name:spa_x_preferred":[
        "San Antonio del Bravo"
    ],
    "name:und_x_variant":[
        "San Antonio el Bravo",
        "San Antonio",
        "San Antonio de Bravo"
    ],
    "wof:name":"San Antonio del Bravo",
    "wof:placetype":"locality"
},
  "geometry": {"coordinates":[-104.70255,30.13924],"type":"Point"}
}