{
  "type": "Feature",
  "properties": {
    "gn:admin1_code":"22",
    "gn:admin2_code":"5.0",
    "gn:asciiname":"Ailitos",
    "gn:country_code":"MX",
    "gn:dem":2510,
    "gn:feature_class":"P",
    "gn:feature_code":"PPL",
    "gn:name":"Ailitos",
    "gn:population":82,
    "gn:timezone":"America/Mexico_City",
    "iso:country":"MX",
    "wof:name":"Ailitos",
    "wof:placetype":"locality",
    "wof:population":82
},
  "geometry": {"coordinates":[-100.17417,20.89944],"type":"Point"}
}