{
  "type": "Feature",
  "properties": {
    "gn:admin1_code":"13",
    "gn:admin2_code":"77",
    "gn:asciiname":"Huitititla",
    "gn:country_code":"MX",
    "gn:dem":2317,
    "gn:feature_class":"P",
    "gn:feature_code":"PPL",
    "gn:name":"Huitititla",
    "gn:population":51,
    "gn:timezone":"America/Mexico_City",
    "iso:country":"MX",
    "wof:name":"Huitititla",
    "wof:placetype":"locality",
    "wof:population":51
},
  "geometry": {"coordinates":[-98.27985,20.11273],"type":"Point"}
}