{
  "type": "Feature",
  "properties": {
    "gn:admin1_code":"5.0",
    "gn:asciiname":"Santa Elizabeth",
    "gn:country_code":"MX",
    "gn:dem":41,
    "gn:feature_class":"P",
    "gn:feature_code":"PPL",
    "gn:name":"Santa Elizabeth",
    "gn:population":0,
    "gn:timezone":"America/Mexico_City",
    "iso:country":"MX",
    "name:spa_x_preferred":[
        "Santa Elizabeth"
    ],
    "wof:name":"Santa Elizabeth",
    "wof:placetype":"locality"
},
  "geometry": {"coordinates":[-93.36601,15.775],"type":"Point"}
}