{
  "type": "Feature",
  "properties": {
    "gn:admin1_code":"19",
    "gn:admin2_code":"9",
    "gn:asciiname":"El Milagro",
    "gn:country_code":"MX",
    "gn:dem":307,
    "gn:feature_class":"P",
    "gn:feature_code":"PPL",
    "gn:name":"El Milagro",
    "gn:population":11,
    "gn:timezone":"America/Monterrey",
    "iso:country":"MX",
    "wof:name":"El Milagro",
    "wof:placetype":"locality",
    "wof:population":11
},
  "geometry": {"coordinates":[-99.93197000000001,25.60228],"type":"Point"}
}