{
  "type": "Feature",
  "properties": {
    "gn:admin1_code":"16",
    "gn:admin2_code":"38.0",
    "gn:asciiname":"Las Caguingas",
    "gn:country_code":"MX",
    "gn:dem":374,
    "gn:feature_class":"P",
    "gn:feature_code":"PPL",
    "gn:name":"Las Caguingas",
    "gn:population":0,
    "gn:timezone":"America/Mexico_City",
    "iso:country":"MX",
    "name:spa_x_preferred":[
        "Las Caguingas"
    ],
    "wof:name":"Las Caguingas",
    "wof:placetype":"locality"
},
  "geometry": {"coordinates":[-100.86557999999999,18.66013],"type":"Point"}
}