{
  "type": "Feature",
  "properties": {
    "gn:admin1_code":"10",
    "gn:admin2_code":"24.0",
    "gn:asciiname":"La Sabaneta",
    "gn:country_code":"MX",
    "gn:dem":1580,
    "gn:feature_class":"P",
    "gn:feature_code":"PPL",
    "gn:name":"La Sabaneta",
    "gn:population":0,
    "gn:timezone":"America/Monterrey",
    "iso:country":"MX",
    "name:spa_x_preferred":[
        "La Sabaneta"
    ],
    "name:und_x_variant":[
        "Rancho La Sabaneta"
    ],
    "wof:name":"La Sabaneta",
    "wof:placetype":"locality"
},
  "geometry": {"coordinates":[-104.57259999999999,25.37152],"type":"Point"}
}