{
  "type": "Feature",
  "properties": {
    "gn:admin1_code":"11",
    "gn:admin2_code":"32.0",
    "gn:asciiname":"La Soledad",
    "gn:country_code":"MX",
    "gn:dem":2071,
    "gn:feature_class":"P",
    "gn:feature_code":"PPL",
    "gn:name":"La Soledad",
    "gn:population":146,
    "gn:timezone":"America/Mexico_City",
    "iso:country":"MX",
    "wof:name":"La Soledad",
    "wof:placetype":"locality",
    "wof:population":146
},
  "geometry": {"coordinates":[-100.50472000000001,21.05639],"type":"Point"}
}