{
  "type": "Feature",
  "properties": {
    "gn:admin1_code":"20",
    "gn:admin2_code":"559.0",
    "gn:asciiname":"San Felipe de Leon",
    "gn:country_code":"MX",
    "gn:dem":287,
    "gn:feature_class":"P",
    "gn:feature_code":"PPL",
    "gn:name":"San Felipe de Le\u00f3n",
    "gn:population":328,
    "gn:timezone":"America/Mexico_City",
    "iso:country":"MX",
    "name:und_x_variant":[
        "San Felipe de Le\u00f3n"
    ],
    "wof:name":"San Felipe de Leon",
    "wof:placetype":"locality",
    "wof:population":328
},
  "geometry": {"coordinates":[-96.37555999999999,17.75361000000001],"type":"Point"}
}