{
  "type": "Feature",
  "properties": {
    "gn:admin1_code":"22",
    "gn:admin2_code":"11.0",
    "gn:asciiname":"Rancho San Sebastian de Aparicio",
    "gn:country_code":"MX",
    "gn:dem":1901,
    "gn:feature_class":"P",
    "gn:feature_code":"PPL",
    "gn:name":"Rancho San Sebasti\u00e1n de Aparicio",
    "gn:population":8,
    "gn:timezone":"America/Mexico_City",
    "iso:country":"MX",
    "name:und_x_variant":[
        "Rancho San Sebasti\u00e1n de Aparicio"
    ],
    "wof:name":"Rancho San Sebastian de Aparicio",
    "wof:placetype":"locality",
    "wof:population":8
},
  "geometry": {"coordinates":[-100.23333,20.60361],"type":"Point"}
}