{
  "type": "Feature",
  "properties": {
    "gn:admin1_code":"11",
    "gn:admin2_code":"43.0",
    "gn:asciiname":"El Jabonero",
    "gn:country_code":"MX",
    "gn:dem":2001,
    "gn:feature_class":"P",
    "gn:feature_code":"PPL",
    "gn:name":"El Jabonero",
    "gn:population":7,
    "gn:timezone":"America/Mexico_City",
    "iso:country":"MX",
    "wof:name":"El Jabonero",
    "wof:placetype":"locality",
    "wof:population":7
},
  "geometry": {"coordinates":[-100.25778,21.29333],"type":"Point"}
}