{
  "type": "Feature",
  "properties": {
    "gn:admin1_code":"1",
    "gn:admin2_code":"2",
    "gn:asciiname":"Santa Rita",
    "gn:country_code":"MX",
    "gn:dem":2083,
    "gn:feature_class":"P",
    "gn:feature_code":"PPL",
    "gn:name":"Santa Rita",
    "gn:population":43,
    "gn:timezone":"America/Mexico_City",
    "iso:country":"MX",
    "wof:name":"Santa Rita",
    "wof:placetype":"locality",
    "wof:population":43
},
  "geometry": {"coordinates":[-101.88361,22.035],"type":"Point"}
}