{
  "type": "Feature",
  "properties": {
    "gn:admin1_code":"31",
    "gn:admin2_code":"50.0",
    "gn:asciiname":"Oncan",
    "gn:country_code":"MX",
    "gn:dem":13,
    "gn:feature_class":"P",
    "gn:feature_code":"PPL",
    "gn:name":"Oncan",
    "gn:population":0,
    "gn:timezone":"America/Merida",
    "iso:country":"MX",
    "name:spa_x_preferred":[
        "Oncan"
    ],
    "wof:name":"Oncan",
    "wof:placetype":"locality"
},
  "geometry": {"coordinates":[-89.48392,20.96352000000001],"type":"Point"}
}