{
  "type": "Feature",
  "properties": {
    "gn:admin1_code":"5",
    "gn:admin2_code":"59",
    "gn:asciiname":"Villa los Pinos",
    "gn:country_code":"MX",
    "gn:dem":634,
    "gn:feature_class":"P",
    "gn:feature_code":"PPL",
    "gn:name":"Villa los Pinos",
    "gn:population":51,
    "gn:timezone":"America/Mexico_City",
    "iso:country":"MX",
    "wof:name":"Villa los Pinos",
    "wof:placetype":"locality",
    "wof:population":51
},
  "geometry": {"coordinates":[-91.74527999999999,16.89167],"type":"Point"}
}