{
  "type": "Feature",
  "properties": {
    "gn:admin1_code":"6",
    "gn:admin2_code":"9.0",
    "gn:asciiname":"El Corte",
    "gn:country_code":"MX",
    "gn:dem":2425,
    "gn:feature_class":"P",
    "gn:feature_code":"PPL",
    "gn:name":"El Corte",
    "gn:population":5,
    "gn:timezone":"America/Chihuahua",
    "iso:country":"MX",
    "wof:name":"El Corte",
    "wof:placetype":"locality",
    "wof:population":5
},
  "geometry": {"coordinates":[-107.42993,27.89603],"type":"Point"}
}