{
  "type": "Feature",
  "properties": {
    "gn:admin1_code":"25",
    "gn:admin2_code":"13.0",
    "gn:asciiname":"La Esmeralda",
    "gn:country_code":"MX",
    "gn:dem":37,
    "gn:feature_class":"P",
    "gn:feature_code":"PPL",
    "gn:name":"La Esmeralda",
    "gn:population":0,
    "gn:timezone":"America/Mazatlan",
    "iso:country":"MX",
    "name:spa_x_preferred":[
        "La Esmeralda"
    ],
    "wof:name":"La Esmeralda",
    "wof:placetype":"locality"
},
  "geometry": {"coordinates":[-107.69871999999999,25.0279],"type":"Point"}
}