{
  "type": "Feature",
  "properties": {
    "iso:country":"MX",
    "qs_pg:aaroncc":"MX",
    "qs_pg:name":"Francisco Zarco",
    "qs_pg:name_adm0":"M\u00e9xico",
    "qs_pg:name_adm1":"Durango",
    "qs_pg:photos":35,
    "qs_pg:photos_1k":7,
    "qs_pg:photos_9k":1,
    "qs_pg:photos_9r":2,
    "qs_pg:photos_all":35,
    "qs_pg:photos_sr":2,
    "qs_pg:pop_sr":0,
    "qs_pg:qs_pg_placetype":"neighbourhood",
    "qs_pg:qs_pg_placetype_gp":"Suburb",
    "qs_pg:woe_adm0":23424900,
    "woe:adm0_id":23424900,
    "woe:name_adm0":"M\u00e9xico",
    "woe:name_adm1":"Durango",
    "woe:placetype":"Suburb",
    "wof:name":"Francisco Zarco",
    "wof:placetype":"neighbourhood"
},
  "geometry": {"coordinates":[-103.491017,25.574653],"type":"Point"}
}