{
  "type": "Feature",
  "properties": {
    "gn:admin1_code":"6",
    "gn:admin2_code":"30",
    "gn:asciiname":"La Sidra",
    "gn:country_code":"MX",
    "gn:dem":826,
    "gn:feature_class":"P",
    "gn:feature_code":"PPL",
    "gn:name":"La Sidra",
    "gn:population":28,
    "gn:timezone":"America/Chihuahua",
    "iso:country":"MX",
    "name:ast_x_preferred":[
        "La Sidra"
    ],
    "name:glg_x_preferred":[
        "La Sidra"
    ],
    "wof:name":"La Sidra",
    "wof:placetype":"locality",
    "wof:population":28
},
  "geometry": {"coordinates":[-108.33632,27.48131],"type":"Point"}
}