{
  "type": "Feature",
  "properties": {
    "gn:admin1_code":"26",
    "gn:admin2_code":"17.0",
    "gn:asciiname":"La Almita",
    "gn:country_code":"MX",
    "gn:dem":176,
    "gn:feature_class":"P",
    "gn:feature_code":"PPL",
    "gn:name":"La Almita",
    "gn:population":644,
    "gn:timezone":"America/Hermosillo",
    "iso:country":"MX",
    "wof:name":"La Almita",
    "wof:placetype":"locality",
    "wof:population":644
},
  "geometry": {"coordinates":[-112.43333,30.70694],"type":"Point"}
}