{
  "type": "Feature",
  "properties": {
    "gn:admin1_code":"31",
    "gn:admin2_code":"102.0",
    "gn:asciiname":"Kaan Ac",
    "gn:country_code":"MX",
    "gn:dem":25,
    "gn:feature_class":"P",
    "gn:feature_code":"PPL",
    "gn:name":"Kaan Ac",
    "gn:population":8,
    "gn:timezone":"America/Merida",
    "iso:country":"MX",
    "wof:name":"Kaan Ac",
    "wof:placetype":"locality",
    "wof:population":8
},
  "geometry": {"coordinates":[-88.19806,20.72806],"type":"Point"}
}