{
  "type": "Feature",
  "properties": {
    "gn:admin1_code":"12.0",
    "gn:admin2_code":"27.0",
    "gn:asciiname":"La Papaya",
    "gn:country_code":"MX",
    "gn:dem":397,
    "gn:feature_class":"P",
    "gn:feature_code":"PPL",
    "gn:name":"La Papaya",
    "gn:population":8,
    "gn:timezone":"America/Mexico_City",
    "iso:country":"MX",
    "name:spa_x_preferred":[
        "La Papaya"
    ],
    "wof:name":"La Papaya",
    "wof:placetype":"locality",
    "wof:population":8
},
  "geometry": {"coordinates":[-100.51519999999999,18.55701],"type":"Point"}
}