{
  "type": "Feature",
  "properties": {
    "gn:admin1_code":"15",
    "gn:admin2_code":"106.0",
    "gn:asciiname":"San Mateo Oxtotitlan",
    "gn:country_code":"MX",
    "gn:dem":2718,
    "gn:feature_class":"P",
    "gn:feature_code":"PPL",
    "gn:name":"San Mateo Oxtotitl\u00e1n",
    "gn:population":0,
    "gn:timezone":"America/Mexico_City",
    "iso:country":"MX",
    "name:spa_x_preferred":[
        "San Mateo Oxtotitl\u00e1n"
    ],
    "wof:name":"San Mateo Oxtotitlan",
    "wof:placetype":"locality"
},
  "geometry": {"coordinates":[-99.69315,19.30175],"type":"Point"}
}