{
  "type": "Feature",
  "properties": {
    "gn:admin1_code":"15",
    "gn:admin2_code":"102.0",
    "gn:asciiname":"Barrio de Ocampo",
    "gn:country_code":"MX",
    "gn:dem":2671,
    "gn:feature_class":"P",
    "gn:feature_code":"PPL",
    "gn:name":"Barrio de Ocampo",
    "gn:population":511,
    "gn:timezone":"America/Mexico_City",
    "iso:country":"MX",
    "wof:name":"Barrio de Ocampo",
    "wof:placetype":"locality",
    "wof:population":511
},
  "geometry": {"coordinates":[-99.75389,19.87611],"type":"Point"}
}