{
  "type": "Feature",
  "properties": {
    "gn:admin1_code":"11",
    "gn:admin2_code":"30",
    "gn:asciiname":"El Rodadillo",
    "gn:country_code":"MX",
    "gn:dem":2684,
    "gn:feature_class":"P",
    "gn:feature_code":"PPL",
    "gn:name":"El Rodadillo",
    "gn:population":14,
    "gn:timezone":"America/Mexico_City",
    "iso:country":"MX",
    "wof:name":"El Rodadillo",
    "wof:placetype":"locality",
    "wof:population":14
},
  "geometry": {"coordinates":[-101.63972,21.33972],"type":"Point"}
}