{
  "type": "Feature",
  "properties": {
    "gn:admin1_code":"7",
    "gn:admin2_code":"13.0",
    "gn:asciiname":"Los Borregos",
    "gn:country_code":"MX",
    "gn:dem":203,
    "gn:feature_class":"P",
    "gn:feature_code":"PPL",
    "gn:name":"Los Borregos",
    "gn:population":12,
    "gn:timezone":"America/Monterrey",
    "iso:country":"MX",
    "name:spa_x_preferred":[
        "Los Borregos"
    ],
    "name:und_x_variant":[
        "Rancho Borregos"
    ],
    "wof:name":"Los Borregos",
    "wof:placetype":"locality",
    "wof:population":12
},
  "geometry": {"coordinates":[-99.98578000000001,27.9126],"type":"Point"}
}