{
  "type": "Feature",
  "properties": {
    "gn:admin1_code":"31",
    "gn:admin2_code":"56.0",
    "gn:asciiname":"Xul",
    "gn:country_code":"MX",
    "gn:dem":95,
    "gn:feature_class":"P",
    "gn:feature_code":"PPL",
    "gn:name":"Xul",
    "gn:population":1110,
    "gn:timezone":"America/Merida",
    "iso:country":"MX",
    "wof:name":"Xul",
    "wof:placetype":"locality",
    "wof:population":1110
},
  "geometry": {"coordinates":[-89.45999999999999,20.10222000000001],"type":"Point"}
}