{
  "type": "Feature",
  "properties": {
    "gn:admin1_code":"14.0",
    "gn:admin2_code":"69.0",
    "gn:asciiname":"El Coruco",
    "gn:country_code":"MX",
    "gn:dem":2499,
    "gn:feature_class":"P",
    "gn:feature_code":"PPL",
    "gn:name":"El Coruco",
    "gn:population":0,
    "gn:timezone":"America/Mexico_City",
    "iso:country":"MX",
    "name:spa_x_preferred":[
        "El Coruco"
    ],
    "wof:name":"El Coruco",
    "wof:placetype":"locality"
},
  "geometry": {"coordinates":[-102.95261000000001,19.86804],"type":"Point"}
}