{
  "type": "Feature",
  "properties": {
    "gn:admin1_code":"20.0",
    "gn:asciiname":"El Aguacatillo",
    "gn:country_code":"MX",
    "gn:dem":235,
    "gn:feature_class":"P",
    "gn:feature_code":"PPL",
    "gn:name":"El Aguacatillo",
    "gn:population":0,
    "gn:timezone":"America/Mexico_City",
    "iso:country":"MX",
    "name:spa_x_preferred":[
        "El Aguacatillo"
    ],
    "wof:name":"El Aguacatillo",
    "wof:placetype":"locality"
},
  "geometry": {"coordinates":[-98.11125,16.44237],"type":"Point"}
}