{
  "type": "Feature",
  "properties": {
    "gn:admin1_code":"5",
    "gn:admin2_code":"99.0",
    "gn:asciiname":"El Nuevo Progreso",
    "gn:country_code":"MX",
    "gn:dem":1525,
    "gn:feature_class":"P",
    "gn:feature_code":"PPL",
    "gn:name":"El Nuevo Progreso",
    "gn:population":63,
    "gn:timezone":"America/Mexico_City",
    "iso:country":"MX",
    "wof:name":"El Nuevo Progreso",
    "wof:placetype":"locality",
    "wof:population":63
},
  "geometry": {"coordinates":[-91.97187,16.16239],"type":"Point"}
}