{
  "type": "Feature",
  "properties": {
    "gn:admin1_code":"5.0",
    "gn:admin2_code":"39.0",
    "gn:asciiname":"Las Nubes",
    "gn:country_code":"MX",
    "gn:dem":712,
    "gn:feature_class":"P",
    "gn:feature_code":"PPL",
    "gn:name":"Las Nubes",
    "gn:population":0,
    "gn:timezone":"America/Mexico_City",
    "iso:country":"MX",
    "name:spa_x_preferred":[
        "Las Nubes"
    ],
    "wof:name":"Las Nubes",
    "wof:placetype":"locality"
},
  "geometry": {"coordinates":[-92.71742999999999,17.30602],"type":"Point"}
}