{
  "type": "Feature",
  "properties": {
    "gn:admin1_code":"16.0",
    "gn:admin2_code":"9.0",
    "gn:asciiname":"La Cebadilla Chica",
    "gn:country_code":"MX",
    "gn:dem":1430,
    "gn:feature_class":"P",
    "gn:feature_code":"PPL",
    "gn:name":"La Cebadilla Chica",
    "gn:population":0,
    "gn:timezone":"America/Mexico_City",
    "iso:country":"MX",
    "name:spa_x_preferred":[
        "La Cebadilla Chica"
    ],
    "wof:name":"La Cebadilla Chica",
    "wof:placetype":"locality"
},
  "geometry": {"coordinates":[-101.7803,19.1198],"type":"Point"}
}