{
  "type": "Feature",
  "properties": {
    "gn:admin1_code":"10",
    "gn:admin2_code":"13.0",
    "gn:asciiname":"California",
    "gn:country_code":"MX",
    "gn:dem":1190,
    "gn:feature_class":"P",
    "gn:feature_code":"PPL",
    "gn:name":"California",
    "gn:population":0,
    "gn:timezone":"America/Monterrey",
    "iso:country":"MX",
    "name:spa_x_preferred":[
        "California"
    ],
    "wof:name":"California",
    "wof:placetype":"locality"
},
  "geometry": {"coordinates":[-104.15237,26.52705],"type":"Point"}
}