{
  "type": "Feature",
  "properties": {
    "gn:admin1_code":"21",
    "gn:admin2_code":"64.0",
    "gn:asciiname":"El Mangal",
    "gn:country_code":"MX",
    "gn:dem":91,
    "gn:feature_class":"P",
    "gn:feature_code":"PPL",
    "gn:name":"El Mangal",
    "gn:population":7,
    "gn:timezone":"America/Mexico_City",
    "iso:country":"MX",
    "name:spa_x_preferred":[
        "El Mangal"
    ],
    "wof:name":"El Mangal",
    "wof:placetype":"locality",
    "wof:population":7
},
  "geometry": {"coordinates":[-97.86944,20.81372],"type":"Point"}
}