{
  "type": "Feature",
  "properties": {
    "gn:admin1_code":"26.0",
    "gn:admin2_code":"69.0",
    "gn:asciiname":"Los Jabalines",
    "gn:country_code":"MX",
    "gn:dem":1732,
    "gn:feature_class":"P",
    "gn:feature_code":"PPL",
    "gn:name":"Los Jabalines",
    "gn:population":0,
    "gn:timezone":"America/Chihuahua",
    "iso:country":"MX",
    "name:spa_x_preferred":[
        "Los Jabalines"
    ],
    "wof:name":"Los Jabalines",
    "wof:placetype":"locality"
},
  "geometry": {"coordinates":[-108.82284,28.27422],"type":"Point"}
}