{
  "type": "Feature",
  "properties": {
    "gn:admin1_code":"10",
    "gn:admin2_code":"16.0",
    "gn:asciiname":"Flecha Rota",
    "gn:country_code":"MX",
    "gn:dem":1888,
    "gn:feature_class":"P",
    "gn:feature_code":"PPL",
    "gn:name":"Flecha Rota",
    "gn:population":0,
    "gn:timezone":"America/Monterrey",
    "iso:country":"MX",
    "name:spa_x_preferred":[
        "Flecha Rota"
    ],
    "wof:name":"Flecha Rota",
    "wof:placetype":"locality"
},
  "geometry": {"coordinates":[-104.06876,23.78604],"type":"Point"}
}