{
  "type": "Feature",
  "properties": {
    "gn:admin1_code":"25",
    "gn:admin2_code":"6.0",
    "gn:asciiname":"La Noria",
    "gn:country_code":"MX",
    "gn:dem":84,
    "gn:feature_class":"P",
    "gn:feature_code":"PPL",
    "gn:name":"La Noria",
    "gn:population":0,
    "gn:timezone":"America/Mazatlan",
    "iso:country":"MX",
    "name:spa_x_preferred":[
        "La Noria"
    ],
    "wof:name":"La Noria",
    "wof:placetype":"locality"
},
  "geometry": {"coordinates":[-107.26334,24.80514],"type":"Point"}
}