{
  "type": "Feature",
  "properties": {
    "gn:admin1_code":"14",
    "gn:admin2_code":"19",
    "gn:asciiname":"Mezquitic",
    "gn:country_code":"MX",
    "gn:dem":912,
    "gn:feature_class":"P",
    "gn:feature_code":"PPL",
    "gn:name":"Mezquitic",
    "gn:population":24,
    "gn:timezone":"America/Mexico_City",
    "iso:country":"MX",
    "wof:name":"Mezquitic",
    "wof:placetype":"locality",
    "wof:population":24
},
  "geometry": {"coordinates":[-103.77278,21.87917],"type":"Point"}
}