{
  "type": "Feature",
  "properties": {
    "gn:admin1_code":"14",
    "gn:admin2_code":"19",
    "gn:asciiname":"Mezquitic",
    "gn:country_code":"MX",
    "gn:dem":912,
    "gn:feature_class":"P",
    "gn:feature_code":"PPL",
    "gn:name":"Mezquitic",
    "gn:population":24,
    "gn:timezone":"America/Mexico_City",
    "iso:country":"MX",
    "name:ceb_x_preferred":[
        "Mezquitic"
    ],
    "name:epo_x_preferred":[
        "Mezquitic"
    ],
    "name:eus_x_preferred":[
        "Mezquitic"
    ],
    "name:fra_x_preferred":[
        "Mezquitic"
    ],
    "name:ita_x_preferred":[
        "Mezquitic"
    ],
    "name:por_x_preferred":[
        "Mezquitic"
    ],
    "name:sco_x_preferred":[
        "Mezquitic"
    ],
    "name:spa_x_preferred":[
        "Mezquitic"
    ],
    "name:srp_x_preferred":[
        "\u041e\u043f\u0448\u0442\u0438\u043d\u0430 \u041c\u0435\u0441\u043a\u0438\u0442\u0438\u043a"
    ],
    "name:swe_x_preferred":[
        "Mezquitic"
    ],
    "name:vie_x_preferred":[
        "Mezquitic"
    ],
    "wof:name":"Mezquitic",
    "wof:placetype":"locality",
    "wof:population":24
},
  "geometry": {"coordinates":[-103.77278,21.87917],"type":"Point"}
}