{
  "type": "Feature",
  "properties": {
    "gn:admin1_code":"14",
    "gn:admin2_code":"19.0",
    "gn:asciiname":"La Taberna",
    "gn:country_code":"MX",
    "gn:dem":2050,
    "gn:feature_class":"P",
    "gn:feature_code":"PPL",
    "gn:name":"La Taberna",
    "gn:population":0,
    "gn:timezone":"America/Mexico_City",
    "iso:country":"MX",
    "name:spa_x_preferred":[
        "La Taberna"
    ],
    "wof:name":"La Taberna",
    "wof:placetype":"locality"
},
  "geometry": {"coordinates":[-103.93398000000001,21.85479],"type":"Point"}
}