{
  "type": "Feature",
  "properties": {
    "gn:admin1_code":"23.0",
    "gn:asciiname":"Don Chabelo",
    "gn:country_code":"MX",
    "gn:dem":55,
    "gn:feature_class":"P",
    "gn:feature_code":"PPL",
    "gn:name":"Don Chabelo",
    "gn:population":0,
    "gn:timezone":"America/Cancun",
    "iso:country":"MX",
    "name:spa_x_preferred":[
        "Don Chabelo"
    ],
    "wof:name":"Don Chabelo",
    "wof:placetype":"locality"
},
  "geometry": {"coordinates":[-88.70568,18.61244],"type":"Point"}
}