{
  "type": "Feature",
  "properties": {
    "gn:admin1_code":"15",
    "gn:admin2_code":"89",
    "gn:asciiname":"Tres Platos",
    "gn:country_code":"MX",
    "gn:dem":2377,
    "gn:feature_class":"P",
    "gn:feature_code":"PPL",
    "gn:name":"Tres Platos",
    "gn:population":19,
    "gn:timezone":"America/Mexico_City",
    "iso:country":"MX",
    "wof:name":"Tres Platos",
    "wof:placetype":"locality",
    "wof:population":19
},
  "geometry": {"coordinates":[-98.8546,19.16172000000001],"type":"Point"}
}