{
  "type": "Feature",
  "properties": {
    "gn:admin1_code":"6",
    "gn:admin2_code":"42.0",
    "gn:asciiname":"Tribuna",
    "gn:country_code":"MX",
    "gn:dem":1520,
    "gn:feature_class":"P",
    "gn:feature_code":"PPL",
    "gn:name":"Tribuna",
    "gn:population":0,
    "gn:timezone":"America/Chihuahua",
    "iso:country":"MX",
    "name:hye_x_preferred":[
        "\u054d\u0578\u0581\u056b\u0561\u056c\u056b\u057d\u057f\u056b\u0579\u0565\u057d\u056f\u0561\u0575\u0561 \u056b\u0576\u0564\u0578\u0582\u057d\u057f\u0580\u056b\u0561"
    ],
    "name:rus_x_preferred":[
        "\u0421\u043e\u0446\u0438\u0430\u043b\u0438\u0441\u0442\u0438\u0447\u0435\u0441\u043a\u0430\u044f \u0438\u043d\u0434\u0443\u0441\u0442\u0440\u0438\u044f"
    ],
    "name:spa_x_preferred":[
        "Tribuna"
    ],
    "wof:name":"Tribuna",
    "wof:placetype":"locality"
},
  "geometry": {"coordinates":[-104.10868000000001,28.72579],"type":"Point"}
}