{
  "type": "Feature",
  "properties": {
    "gn:admin1_code":"26",
    "gn:asciiname":"Las Canadas",
    "gn:country_code":"MX",
    "gn:dem":186,
    "gn:feature_class":"P",
    "gn:feature_code":"PPL",
    "gn:name":"Las Ca\u00f1adas",
    "gn:population":0,
    "gn:timezone":"America/Mazatlan",
    "iso:country":"MX",
    "name:und_x_variant":[
        "Ca\u00f1adas",
        "Las Ca\u00f1adas"
    ],
    "wof:name":"Las Canadas",
    "wof:placetype":"locality"
},
  "geometry": {"coordinates":[-108.64643999999998,26.61102],"type":"Point"}
}