{
  "type": "Feature",
  "properties": {
    "gn:admin1_code":"32.0",
    "gn:admin2_code":"38.0",
    "gn:asciiname":"Botica",
    "gn:country_code":"MX",
    "gn:dem":2249,
    "gn:feature_class":"P",
    "gn:feature_code":"PPL",
    "gn:name":"Botica",
    "gn:population":0,
    "gn:timezone":"America/Mexico_City",
    "iso:country":"MX",
    "wof:name":"Botica",
    "wof:placetype":"locality"
},
  "geometry": {"coordinates":[-101.46666999999999,21.93333],"type":"Point"}
}