{
  "type": "Feature",
  "properties": {
    "gn:admin1_code":"30",
    "gn:admin2_code":"39.0",
    "gn:asciiname":"Los Electricistas",
    "gn:country_code":"MX",
    "gn:dem":7,
    "gn:feature_class":"P",
    "gn:feature_code":"PPL",
    "gn:name":"Los Electricistas",
    "gn:population":0,
    "gn:timezone":"America/Mexico_City",
    "iso:country":"MX",
    "name:spa_x_preferred":[
        "Los Electricistas"
    ],
    "wof:name":"Los Electricistas",
    "wof:placetype":"locality"
},
  "geometry": {"coordinates":[-94.45535,18.10912],"type":"Point"}
}