{
  "type": "Feature",
  "properties": {
    "gn:admin1_code":"14.0",
    "gn:admin2_code":"108.0",
    "gn:asciiname":"Miahuatlancillo",
    "gn:country_code":"MX",
    "gn:dem":825,
    "gn:feature_class":"P",
    "gn:feature_code":"PPL",
    "gn:name":"Miahuatlancillo",
    "gn:population":0,
    "gn:timezone":"America/Mexico_City",
    "iso:country":"MX",
    "name:spa_x_preferred":[
        "Miahuatlancillo"
    ],
    "wof:name":"Miahuatlancillo",
    "wof:placetype":"locality"
},
  "geometry": {"coordinates":[-103.40052,19.35565],"type":"Point"}
}