{
  "type": "Feature",
  "properties": {
    "gn:admin1_code":"15",
    "gn:admin2_code":"55.0",
    "gn:asciiname":"Colonia Mazachulco",
    "gn:country_code":"MX",
    "gn:dem":2614,
    "gn:feature_class":"P",
    "gn:feature_code":"PPL",
    "gn:name":"Colonia Mazachulco",
    "gn:population":421,
    "gn:timezone":"America/Mexico_City",
    "iso:country":"MX",
    "wof:name":"Colonia Mazachulco",
    "wof:placetype":"locality",
    "wof:population":421
},
  "geometry": {"coordinates":[-99.58866,19.20513],"type":"Point"}
}