{
  "type": "Feature",
  "properties": {
    "gn:admin1_code":"30",
    "gn:admin2_code":"204.0",
    "gn:asciiname":"Miguel Aleman Valdez",
    "gn:country_code":"MX",
    "gn:dem":54,
    "gn:feature_class":"P",
    "gn:feature_code":"PPL",
    "gn:name":"Miguel Alem\u00e1n Valdez",
    "gn:population":0,
    "gn:timezone":"America/Mexico_City",
    "iso:country":"MX",
    "name:spa_x_preferred":[
        "Miguel Alem\u00e1n Valdez"
    ],
    "wof:name":"Miguel Aleman Valdez",
    "wof:placetype":"locality"
},
  "geometry": {"coordinates":[-94.17291,18.06413],"type":"Point"}
}