{
  "type": "Feature",
  "properties": {
    "gn:admin1_code":"6",
    "gn:admin2_code":"27.0",
    "gn:asciiname":"El Manzano",
    "gn:country_code":"MX",
    "gn:dem":2218,
    "gn:feature_class":"P",
    "gn:feature_code":"PPL",
    "gn:name":"El Manzano",
    "gn:population":20,
    "gn:timezone":"America/Chihuahua",
    "iso:country":"MX",
    "name:spa_x_preferred":[
        "El Manzano"
    ],
    "wof:name":"El Manzano",
    "wof:placetype":"locality",
    "wof:population":20
},
  "geometry": {"coordinates":[-107.22268,27.17993],"type":"Point"}
}