{
  "type": "Feature",
  "properties": {
    "gn:admin1_code":"30",
    "gn:admin2_code":"75.0",
    "gn:asciiname":"Palma de Coco",
    "gn:country_code":"MX",
    "gn:dem":12,
    "gn:feature_class":"P",
    "gn:feature_code":"PPL",
    "gn:name":"Palma de Coco",
    "gn:population":210,
    "gn:timezone":"America/Mexico_City",
    "iso:country":"MX",
    "wof:name":"Palma de Coco",
    "wof:placetype":"locality",
    "wof:population":210
},
  "geometry": {"coordinates":[-95.94889000000001,18.67778],"type":"Point"}
}