{
  "type": "Feature",
  "properties": {
    "gn:admin1_code":"11",
    "gn:admin2_code":"1",
    "gn:asciiname":"Soledad de Vargas",
    "gn:country_code":"MX",
    "gn:dem":1699,
    "gn:feature_class":"P",
    "gn:feature_code":"PPL",
    "gn:name":"Soledad de Vargas",
    "gn:population":34,
    "gn:timezone":"America/Mexico_City",
    "iso:country":"MX",
    "wof:name":"Soledad de Vargas",
    "wof:placetype":"locality",
    "wof:population":34
},
  "geometry": {"coordinates":[-101.59083,20.395],"type":"Point"}
}