{
  "type": "Feature",
  "properties": {
    "gn:admin1_code":"16",
    "gn:admin2_code":"34",
    "gn:asciiname":"Cerro del Macho",
    "gn:country_code":"MX",
    "gn:dem":2735,
    "gn:feature_class":"P",
    "gn:feature_code":"PPL",
    "gn:name":"Cerro del Macho",
    "gn:population":34,
    "gn:timezone":"America/Mexico_City",
    "iso:country":"MX",
    "wof:name":"Cerro del Macho",
    "wof:placetype":"locality",
    "wof:population":34
},
  "geometry": {"coordinates":[-100.64194000000001,19.55444],"type":"Point"}
}