{
  "type": "Feature",
  "properties": {
    "gn:admin1_code":"13",
    "gn:admin2_code":"57.0",
    "gn:asciiname":"Pedernales",
    "gn:country_code":"MX",
    "gn:dem":2605,
    "gn:feature_class":"P",
    "gn:feature_code":"PPL",
    "gn:name":"Pedernales",
    "gn:population":0,
    "gn:timezone":"America/Mexico_City",
    "iso:country":"MX",
    "name:ben_x_preferred":[
        "\u09aa\u09c7\u09a6\u09c7\u09b0\u09a8\u09be\u09b2\u09c7\u09b8"
    ],
    "name:ceb_x_preferred":[
        "Pedernales"
    ],
    "name:deu_x_preferred":[
        "Pedernales"
    ],
    "name:ell_x_preferred":[
        "\u03a0\u03b5\u03bd\u03c4\u03b5\u03c1\u03bd\u03ac\u03bb\u03b5\u03c2"
    ],
    "name:fra_x_preferred":[
        "Pedernales"
    ],
    "name:heb_x_preferred":[
        "\u05e4\u05d3\u05e8\u05e0\u05d0\u05dc\u05e1"
    ],
    "name:hun_x_preferred":[
        "Pedernales"
    ],
    "name:ind_x_preferred":[
        "Pedernales"
    ],
    "name:ita_x_preferred":[
        "Pedernales"
    ],
    "name:nld_x_preferred":[
        "Pedernales"
    ],
    "name:pol_x_preferred":[
        "Pedernales"
    ],
    "name:por_x_preferred":[
        "Pedernales"
    ],
    "name:rus_x_preferred":[
        "\u041f\u0435\u0434\u0435\u0440\u043d\u0430\u043b\u0435\u0441"
    ],
    "name:spa_x_preferred":[
        "Pedernales"
    ],
    "name:srp_x_preferred":[
        "\u041f\u0435\u0434\u0435\u0440\u043d\u0430\u043b\u0435\u0441"
    ],
    "name:swe_x_preferred":[
        "Pedernales"
    ],
    "name:tur_x_preferred":[
        "Pedernales"
    ],
    "name:ukr_x_preferred":[
        "\u041f\u0435\u0434\u0435\u0440\u043d\u0430\u043b\u0435\u0441"
    ],
    "name:vie_x_preferred":[
        "Pedernales"
    ],
    "wof:name":"Pedernales",
    "wof:placetype":"locality"
},
  "geometry": {"coordinates":[-98.53707,19.98533],"type":"Point"}
}