{
  "type": "Feature",
  "properties": {
    "gn:admin1_code":"14.0",
    "gn:admin2_code":"27.0",
    "gn:asciiname":"Tejones",
    "gn:country_code":"MX",
    "gn:dem":476,
    "gn:feature_class":"P",
    "gn:feature_code":"PPL",
    "gn:name":"Tejones",
    "gn:population":0,
    "gn:timezone":"America/Mexico_City",
    "iso:country":"MX",
    "name:spa_x_preferred":[
        "Tejones"
    ],
    "wof:name":"Tejones",
    "wof:placetype":"locality"
},
  "geometry": {"coordinates":[-104.28858,19.38123],"type":"Point"}
}