{
  "type": "Feature",
  "properties": {
    "gn:admin1_code":"12",
    "gn:admin2_code":"2.0",
    "gn:asciiname":"Alpuyecancingo de las Montanas",
    "gn:country_code":"MX",
    "gn:dem":1483,
    "gn:feature_class":"P",
    "gn:feature_code":"PPL",
    "gn:name":"Alpuyecancingo de las Monta\u00f1as",
    "gn:population":1838,
    "gn:timezone":"America/Mexico_City",
    "iso:country":"MX",
    "name:und_x_variant":[
        "Alpuyecancingo de las Monta\u00f1as"
    ],
    "wof:name":"Alpuyecancingo de las Montanas",
    "wof:placetype":"locality",
    "wof:population":1838
},
  "geometry": {"coordinates":[-98.85194,17.67083],"type":"Point"}
}