{
  "type": "Feature",
  "properties": {
    "gn:admin1_code":"5",
    "gn:admin2_code":"20",
    "gn:asciiname":"Ocotlan",
    "gn:country_code":"MX",
    "gn:dem":636,
    "gn:feature_class":"P",
    "gn:feature_code":"PPL",
    "gn:name":"Ocotl\u00e1n",
    "gn:population":28,
    "gn:timezone":"America/Mexico_City",
    "iso:country":"MX",
    "name:spa_x_preferred":[
        "Ocotl\u00e1n"
    ],
    "name:und_x_variant":[
        "Ocotl\u00e1n"
    ],
    "wof:name":"Ocotlan",
    "wof:placetype":"locality",
    "wof:population":28
},
  "geometry": {"coordinates":[-92.92749999999999,15.94417],"type":"Point"}
}