{
  "type": "Feature",
  "properties": {
    "gn:admin1_code":"14",
    "gn:admin2_code":"6.0",
    "gn:asciiname":"Las Raices",
    "gn:country_code":"MX",
    "gn:dem":1117,
    "gn:feature_class":"P",
    "gn:feature_code":"PPL",
    "gn:name":"Las Ra\u00edces",
    "gn:population":123,
    "gn:timezone":"America/Mexico_City",
    "iso:country":"MX",
    "name:spa_x_preferred":[
        "Las Ra\u00edces"
    ],
    "wof:name":"Las Raices",
    "wof:placetype":"locality",
    "wof:population":123
},
  "geometry": {"coordinates":[-104.21809,20.6077],"type":"Point"}
}