{
  "type": "Feature",
  "properties": {
    "gn:admin1_code":"11.0",
    "gn:admin2_code":"20.0",
    "gn:asciiname":"Ladrillera",
    "gn:country_code":"MX",
    "gn:dem":1864,
    "gn:feature_class":"P",
    "gn:feature_code":"PPL",
    "gn:name":"Ladrillera",
    "gn:population":0,
    "gn:timezone":"America/Mexico_City",
    "iso:country":"MX",
    "name:spa_x_preferred":[
        "Ladrillera"
    ],
    "wof:name":"Ladrillera",
    "wof:placetype":"locality"
},
  "geometry": {"coordinates":[-101.55032,21.08948],"type":"Point"}
}