{
  "type": "Feature",
  "properties": {
    "gn:admin1_code":"12",
    "gn:admin2_code":"48",
    "gn:asciiname":"Los Enanos (Esmir)",
    "gn:country_code":"MX",
    "gn:dem":1240,
    "gn:feature_class":"P",
    "gn:feature_code":"PPL",
    "gn:name":"Los Enanos (Esmir)",
    "gn:population":34,
    "gn:timezone":"America/Mexico_City",
    "iso:country":"MX",
    "wof:name":"Los Enanos (Esmir)",
    "wof:placetype":"locality",
    "wof:population":34
},
  "geometry": {"coordinates":[-101.12779,17.55744],"type":"Point"}
}