{
  "type": "Feature",
  "properties": {
    "gn:admin1_code":"10",
    "gn:admin2_code":"14",
    "gn:asciiname":"Ceja de los Encinos",
    "gn:country_code":"MX",
    "gn:dem":2096,
    "gn:feature_class":"P",
    "gn:feature_code":"PPL",
    "gn:name":"Ceja de los Encinos",
    "gn:population":10,
    "gn:timezone":"America/Monterrey",
    "iso:country":"MX",
    "wof:name":"Ceja de los Encinos",
    "wof:placetype":"locality",
    "wof:population":10
},
  "geometry": {"coordinates":[-104.42301999999999,22.9192],"type":"Point"}
}