{
  "type": "Feature",
  "properties": {
    "gn:admin1_code":"20",
    "gn:admin2_code":"198.0",
    "gn:asciiname":"Yese",
    "gn:country_code":"MX",
    "gn:dem":92,
    "gn:feature_class":"P",
    "gn:feature_code":"PPL",
    "gn:name":"Yes\u00e9",
    "gn:population":0,
    "gn:timezone":"America/Mexico_City",
    "iso:country":"MX",
    "wof:name":"Yese",
    "wof:placetype":"locality"
},
  "geometry": {"coordinates":[-95.01667,17.03333],"type":"Point"}
}