{
  "type": "Feature",
  "properties": {
    "gn:admin1_code":"28",
    "gn:admin2_code":"34.0",
    "gn:asciiname":"Benito Juarez",
    "gn:country_code":"MX",
    "gn:dem":222,
    "gn:feature_class":"P",
    "gn:feature_code":"PPL",
    "gn:name":"Benito Ju\u00e1rez",
    "gn:population":0,
    "gn:timezone":"America/Monterrey",
    "iso:country":"MX",
    "name:spa_x_preferred":[
        "Benito Ju\u00e1rez"
    ],
    "name:spa_x_variant":[
        "La Coma"
    ],
    "wof:name":"Benito Juarez",
    "wof:placetype":"locality"
},
  "geometry": {"coordinates":[-98.92897000000001,24.30821],"type":"Point"}
}