{
  "type": "Feature",
  "properties": {
    "gn:admin1_code":"10",
    "gn:admin2_code":"34.0",
    "gn:asciiname":"El Cordon",
    "gn:country_code":"MX",
    "gn:dem":1635,
    "gn:feature_class":"P",
    "gn:feature_code":"PPL",
    "gn:name":"El Cord\u00f3n",
    "gn:population":4,
    "gn:timezone":"America/Monterrey",
    "iso:country":"MX",
    "name:und_x_variant":[
        "El Cord\u00f3n"
    ],
    "wof:name":"El Cordon",
    "wof:placetype":"locality",
    "wof:population":4
},
  "geometry": {"coordinates":[-107.07261,25.54191],"type":"Point"}
}