{
  "type": "Feature",
  "properties": {
    "gn:admin1_code":"11",
    "gn:admin2_code":"33.0",
    "gn:asciiname":"San Pedro de la Esperanza (Los Rangeles)",
    "gn:country_code":"MX",
    "gn:dem":1986,
    "gn:feature_class":"P",
    "gn:feature_code":"PPL",
    "gn:name":"San Pedro de la Esperanza (Los Rangeles)",
    "gn:population":54,
    "gn:timezone":"America/Mexico_City",
    "iso:country":"MX",
    "wof:name":"San Pedro de la Esperanza (Los Rangeles)",
    "wof:placetype":"locality",
    "wof:population":54
},
  "geometry": {"coordinates":[-100.40639,21.37528],"type":"Point"}
}