{
  "type": "Feature",
  "properties": {
    "gn:admin1_code":"24.0",
    "gn:admin2_code":"32.0",
    "gn:asciiname":"La Betonica",
    "gn:country_code":"MX",
    "gn:dem":2411,
    "gn:feature_class":"P",
    "gn:feature_code":"PPL",
    "gn:name":"La Bet\u00f3nica",
    "gn:population":0,
    "gn:timezone":"America/Mexico_City",
    "iso:country":"MX",
    "name:spa_x_preferred":[
        "La Bet\u00f3nica"
    ],
    "wof:name":"La Betonica",
    "wof:placetype":"locality"
},
  "geometry": {"coordinates":[-100.42158999999999,21.77354],"type":"Point"}
}