{
  "type": "Feature",
  "properties": {
    "gn:admin1_code":"30",
    "gn:admin2_code":"168.0",
    "gn:asciiname":"Atempa",
    "gn:country_code":"MX",
    "gn:dem":1210,
    "gn:feature_class":"P",
    "gn:feature_code":"PPL",
    "gn:name":"Atempa",
    "gn:population":0,
    "gn:timezone":"America/Mexico_City",
    "iso:country":"MX",
    "name:spa_x_preferred":[
        "Atempa"
    ],
    "wof:name":"Atempa",
    "wof:placetype":"locality"
},
  "geometry": {"coordinates":[-97.00508000000001,18.7031],"type":"Point"}
}