{
  "type": "Feature",
  "properties": {
    "gn:admin1_code":"4",
    "gn:admin2_code":"11.0",
    "gn:asciiname":"Miguel de la Madrid (El Panuelo)",
    "gn:country_code":"MX",
    "gn:dem":100,
    "gn:feature_class":"P",
    "gn:feature_code":"PPL",
    "gn:name":"Miguel de la Madrid (El Pa\u00f1uelo)",
    "gn:population":667,
    "gn:timezone":"America/Merida",
    "iso:country":"MX",
    "name:und_x_variant":[
        "Miguel de la Madrid (El Pa\u00f1uelo)"
    ],
    "wof:name":"Miguel de la Madrid (El Panuelo)",
    "wof:placetype":"locality",
    "wof:population":667
},
  "geometry": {"coordinates":[-90.40778,17.99417],"type":"Point"}
}