{
  "type": "Feature",
  "properties": {
    "gn:admin1_code":"28.0",
    "gn:admin2_code":"3.0",
    "gn:asciiname":"Los Platanos",
    "gn:country_code":"MX",
    "gn:dem":56,
    "gn:feature_class":"P",
    "gn:feature_code":"PPL",
    "gn:name":"Los Pl\u00e1tanos",
    "gn:population":6,
    "gn:timezone":"America/Monterrey",
    "iso:country":"MX",
    "name:spa_x_preferred":[
        "Los Pl\u00e1tanos"
    ],
    "wof:name":"Los Platanos",
    "wof:placetype":"locality",
    "wof:population":6
},
  "geometry": {"coordinates":[-98.22519,22.62751],"type":"Point"}
}