{
  "type": "Feature",
  "properties": {
    "gn:admin1_code":"26.0",
    "gn:admin2_code":"36.0",
    "gn:asciiname":"Villa Fontana",
    "gn:country_code":"MX",
    "gn:dem":714,
    "gn:feature_class":"P",
    "gn:feature_code":"PPL",
    "gn:name":"Villa Fontana",
    "gn:population":0,
    "gn:timezone":"America/Hermosillo",
    "iso:country":"MX",
    "name:spa_x_preferred":[
        "Villa Fontana"
    ],
    "wof:name":"Villa Fontana",
    "wof:placetype":"locality"
},
  "geometry": {"coordinates":[-111.14577,30.65484],"type":"Point"}
}