{
  "type": "Feature",
  "properties": {
    "gn:admin1_code":"10.0",
    "gn:admin2_code":"32.0",
    "gn:asciiname":"Las Mesitas",
    "gn:country_code":"MX",
    "gn:dem":1051,
    "gn:feature_class":"P",
    "gn:feature_code":"PPL",
    "gn:name":"Las Mesitas",
    "gn:population":0,
    "gn:timezone":"America/Monterrey",
    "iso:country":"MX",
    "name:spa_x_preferred":[
        "Las Mesitas"
    ],
    "wof:name":"Las Mesitas",
    "wof:placetype":"locality"
},
  "geometry": {"coordinates":[-106.18281,24.89133],"type":"Point"}
}