{
  "type": "Feature",
  "properties": {
    "gn:admin1_code":"6",
    "gn:admin2_code":"11.0",
    "gn:asciiname":"El Refugio",
    "gn:country_code":"MX",
    "gn:dem":1354,
    "gn:feature_class":"P",
    "gn:feature_code":"PPL",
    "gn:name":"El Refugio",
    "gn:population":4,
    "gn:timezone":"America/Chihuahua",
    "iso:country":"MX",
    "name:ceb_x_preferred":[
        "El Refugio"
    ],
    "name:deu_x_preferred":[
        "El Refugio"
    ],
    "name:ita_x_preferred":[
        "El Refugio"
    ],
    "name:nld_x_preferred":[
        "El Refugio"
    ],
    "name:por_x_preferred":[
        "El Refugio"
    ],
    "name:spa_x_preferred":[
        "El refugio"
    ],
    "name:swe_x_preferred":[
        "El Refugio"
    ],
    "wof:name":"El Refugio",
    "wof:placetype":"locality",
    "wof:population":4
},
  "geometry": {"coordinates":[-105.15694999999999,27.40754],"type":"Point"}
}