{
  "type": "Feature",
  "properties": {
    "gn:admin1_code":"23",
    "gn:admin2_code":"2.0",
    "gn:asciiname":"Trapich",
    "gn:country_code":"MX",
    "gn:dem":18,
    "gn:feature_class":"P",
    "gn:feature_code":"PPL",
    "gn:name":"Trapich",
    "gn:population":197,
    "gn:timezone":"America/Cancun",
    "iso:country":"MX",
    "wof:name":"Trapich",
    "wof:placetype":"locality",
    "wof:population":197
},
  "geometry": {"coordinates":[-88.13861,20.01361],"type":"Point"}
}