{
  "type": "Feature",
  "properties": {
    "gn:admin1_code":"30.0",
    "gn:asciiname":"Labra",
    "gn:country_code":"MX",
    "gn:dem":31,
    "gn:feature_class":"P",
    "gn:feature_code":"PPL",
    "gn:name":"Labra",
    "gn:population":0,
    "gn:timezone":"America/Mexico_City",
    "iso:country":"MX",
    "name:ceb_x_preferred":[
        "Labra"
    ],
    "name:spa_x_preferred":[
        "Labra"
    ],
    "name:srp_x_preferred":[
        "\u041b\u0430\u0431\u0440\u0430"
    ],
    "name:swe_x_preferred":[
        "Labra"
    ],
    "wof:name":"Labra",
    "wof:placetype":"locality"
},
  "geometry": {"coordinates":[-95.74464,17.92016],"type":"Point"}
}