{
  "type": "Feature",
  "properties": {
    "gn:admin1_code":"14.0",
    "gn:admin2_code":"68.0",
    "gn:asciiname":"Ixtan",
    "gn:country_code":"MX",
    "gn:dem":628,
    "gn:feature_class":"P",
    "gn:feature_code":"PPL",
    "gn:name":"Ixt\u00e1n",
    "gn:population":0,
    "gn:timezone":"America/Mexico_City",
    "iso:country":"MX",
    "name:spa_x_preferred":[
        "Ixt\u00e1n"
    ],
    "wof:name":"Ixtan",
    "wof:placetype":"locality"
},
  "geometry": {"coordinates":[-104.59968000000001,19.78037],"type":"Point"}
}