{
  "type": "Feature",
  "properties": {
    "gn:admin1_code":"16",
    "gn:admin2_code":"13",
    "gn:asciiname":"Los Lampaces (Lampazos)",
    "gn:country_code":"MX",
    "gn:dem":711,
    "gn:feature_class":"P",
    "gn:feature_code":"PPL",
    "gn:name":"Los Lampaces (Lampazos)",
    "gn:population":11,
    "gn:timezone":"America/Mexico_City",
    "iso:country":"MX",
    "wof:name":"Los Lampaces (Lampazos)",
    "wof:placetype":"locality",
    "wof:population":11
},
  "geometry": {"coordinates":[-100.91583,19.02778],"type":"Point"}
}