{
  "type": "Feature",
  "properties": {
    "gn:admin1_code":"15.0",
    "gn:asciiname":"Ururuta",
    "gn:country_code":"MX",
    "gn:dem":1937,
    "gn:feature_class":"P",
    "gn:feature_code":"PPL",
    "gn:name":"Ururuta",
    "gn:population":0,
    "gn:timezone":"America/Mexico_City",
    "iso:country":"MX",
    "name:spa_x_preferred":[
        "Ururuta"
    ],
    "wof:name":"Ururuta",
    "wof:placetype":"locality"
},
  "geometry": {"coordinates":[-101.60733999999999,20.04464],"type":"Point"}
}