{
  "type": "Feature",
  "properties": {
    "gn:admin1_code":"6",
    "gn:admin2_code":"62.0",
    "gn:asciiname":"Loma Chica",
    "gn:country_code":"MX",
    "gn:dem":1183,
    "gn:feature_class":"P",
    "gn:feature_code":"PPL",
    "gn:name":"Loma Chica",
    "gn:population":653,
    "gn:timezone":"America/Chihuahua",
    "iso:country":"MX",
    "wof:name":"Loma Chica",
    "wof:placetype":"locality",
    "wof:population":653
},
  "geometry": {"coordinates":[-105.34305999999999,28.11583],"type":"Point"}
}