{
  "type": "Feature",
  "properties": {
    "gn:admin1_code":"30",
    "gn:admin2_code":"181.0",
    "gn:asciiname":"Mata Cabestro (La Vibora)",
    "gn:country_code":"MX",
    "gn:dem":36,
    "gn:feature_class":"P",
    "gn:feature_code":"PPL",
    "gn:name":"Mata Cabestro (La V\u00edbora)",
    "gn:population":548,
    "gn:timezone":"America/Mexico_City",
    "iso:country":"MX",
    "name:und_x_variant":[
        "Mata Cabestro (La V\u00edbora)"
    ],
    "wof:name":"Mata Cabestro (La Vibora)",
    "wof:placetype":"locality",
    "wof:population":548
},
  "geometry": {"coordinates":[-96.06917,18.91417],"type":"Point"}
}