{
  "type": "Feature",
  "properties": {
    "gn:admin1_code":"25",
    "gn:admin2_code":"6.0",
    "gn:asciiname":"Junta de Bagrecitos",
    "gn:country_code":"MX",
    "gn:dem":272,
    "gn:feature_class":"P",
    "gn:feature_code":"PPL",
    "gn:name":"Junta de Bagrecitos",
    "gn:population":146,
    "gn:timezone":"America/Mazatlan",
    "iso:country":"MX",
    "wof:name":"Junta de Bagrecitos",
    "wof:placetype":"locality",
    "wof:population":146
},
  "geometry": {"coordinates":[-107.21774000000001,25.06297],"type":"Point"}
}