{
  "type": "Feature",
  "properties": {
    "gn:admin1_code":"24",
    "gn:admin2_code":"23.0",
    "gn:asciiname":"San Patricio",
    "gn:country_code":"MX",
    "gn:dem":1163,
    "gn:feature_class":"P",
    "gn:feature_code":"PPL",
    "gn:name":"San Patricio",
    "gn:population":113,
    "gn:timezone":"America/Mexico_City",
    "iso:country":"MX",
    "name:ceb_x_preferred":[
        "San Patricio"
    ],
    "name:deu_x_preferred":[
        "San Patricio"
    ],
    "name:ita_x_preferred":[
        "San Patricio"
    ],
    "name:pol_x_preferred":[
        "San Patricio"
    ],
    "name:por_x_preferred":[
        "San Patricio"
    ],
    "name:spa_x_preferred":[
        "San Patricio"
    ],
    "name:srp_x_preferred":[
        "\u0421\u0430\u043d \u041f\u0430\u0442\u0440\u0438\u0448\u0438\u043e"
    ],
    "name:swe_x_preferred":[
        "San Patricio"
    ],
    "wof:name":"San Patricio",
    "wof:placetype":"locality",
    "wof:population":113
},
  "geometry": {"coordinates":[-99.64306000000001,21.94278],"type":"Point"}
}