{
  "type": "Feature",
  "properties": {
    "gn:admin1_code":"24",
    "gn:admin2_code":"23.0",
    "gn:asciiname":"San Patricio",
    "gn:country_code":"MX",
    "gn:dem":1163,
    "gn:feature_class":"P",
    "gn:feature_code":"PPL",
    "gn:name":"San Patricio",
    "gn:population":113,
    "gn:timezone":"America/Mexico_City",
    "iso:country":"MX",
    "wof:name":"San Patricio",
    "wof:placetype":"locality",
    "wof:population":113
},
  "geometry": {"coordinates":[-99.64306000000001,21.94278],"type":"Point"}
}