{
  "type": "Feature",
  "properties": {
    "gn:admin1_code":"19.0",
    "gn:admin2_code":"13.0",
    "gn:asciiname":"Las Auras",
    "gn:country_code":"MX",
    "gn:dem":175,
    "gn:feature_class":"P",
    "gn:feature_code":"PPL",
    "gn:name":"Las Auras",
    "gn:population":0,
    "gn:timezone":"America/Monterrey",
    "iso:country":"MX",
    "name:spa_x_preferred":[
        "Las Auras"
    ],
    "wof:name":"Las Auras",
    "wof:placetype":"locality"
},
  "geometry": {"coordinates":[-99.08105999999999,25.63992],"type":"Point"}
}