{
  "type": "Feature",
  "properties": {
    "gn:admin1_code":"20",
    "gn:admin2_code":"318",
    "gn:asciiname":"Arroyo Tepehuaje",
    "gn:country_code":"MX",
    "gn:dem":526,
    "gn:feature_class":"P",
    "gn:feature_code":"PPL",
    "gn:name":"Arroyo Tepehuaje",
    "gn:population":24,
    "gn:timezone":"America/Mexico_City",
    "iso:country":"MX",
    "wof:name":"Arroyo Tepehuaje",
    "wof:placetype":"locality",
    "wof:population":24
},
  "geometry": {"coordinates":[-96.93416999999999,15.98],"type":"Point"}
}