{
  "type": "Feature",
  "properties": {
    "gn:admin1_code":"30",
    "gn:admin2_code":"132",
    "gn:asciiname":"Virjan",
    "gn:country_code":"MX",
    "gn:dem":2389,
    "gn:feature_class":"P",
    "gn:feature_code":"PPL",
    "gn:name":"Virj\u00e1n",
    "gn:population":42,
    "gn:timezone":"America/Mexico_City",
    "iso:country":"MX",
    "name:und_x_variant":[
        "Virj\u00e1n"
    ],
    "wof:name":"Virjan",
    "wof:placetype":"locality",
    "wof:population":42
},
  "geometry": {"coordinates":[-97.06167000000001,19.62833],"type":"Point"}
}