{
  "type": "Feature",
  "properties": {
    "gn:admin1_code":"7",
    "gn:admin2_code":"38.0",
    "gn:asciiname":"Paso del Tio Pio",
    "gn:country_code":"MX",
    "gn:dem":357,
    "gn:feature_class":"P",
    "gn:feature_code":"PPL",
    "gn:name":"Paso del T\u00edo P\u00edo",
    "gn:population":548,
    "gn:timezone":"America/Monterrey",
    "iso:country":"MX",
    "wof:name":"Paso del Tio Pio",
    "wof:placetype":"locality",
    "wof:population":548
},
  "geometry": {"coordinates":[-100.90331,28.47865],"type":"Point"}
}