{
  "type": "Feature",
  "properties": {
    "iso:country":"MX",
    "name:spa_x_preferred":[
        "San Sebastian"
    ],
    "qs:gn_adm0_cc":"MX",
    "qs:gn_fcode":"PPL",
    "qs:gn_local":3985606,
    "qs:gn_nam_loc":"San Luis Potosi, San Luis Potosi, San Luis Potos\u00ed, MX",
    "qs:gn_namadm1":"24",
    "qs:gn_name":"San Sebastian",
    "qs:local_max":1936,
    "qs:local_sum":4960,
    "qs:localhoods":18,
    "qs:name":"San Sebastian",
    "qs:name_adm0":"M\u00e9xico",
    "qs:name_adm1":"San Luis Potosi",
    "qs:name_adm2":"San Luis Potosi",
    "qs:name_local":"San Luis Potos\u00ed",
    "qs:photo_max":47,
    "qs:photo_sum":269,
    "qs:placetype":"Suburb",
    "qs:quad_count":12,
    "qs:woe_adm0":23424900,
    "qs:woe_adm1":2346287,
    "qs:woe_adm2":12601498,
    "qs:woe_lau":0,
    "qs:woe_local":144265,
    "qs:woe_ver":"7.10.0",
    "wof:lang":[
        "spa"
    ],
    "wof:name":"San Sebastian",
    "wof:placetype":"neighbourhood"
},
  "geometry": {"coordinates":[-100.974817,22.146138],"type":"Point"}
}