{
  "type": "Feature",
  "properties": {
    "iso:country":"MX",
    "name:ast_x_preferred":[
        "Rick Trevino"
    ],
    "name:cat_x_preferred":[
        "Rick Trevino"
    ],
    "name:dan_x_preferred":[
        "Rick Trevino"
    ],
    "name:deu_x_preferred":[
        "Rick Trevino"
    ],
    "name:eng_x_preferred":[
        "Rick Trevino"
    ],
    "name:fra_x_preferred":[
        "Rick Trevino"
    ],
    "name:ita_x_preferred":[
        "Rick Trevino"
    ],
    "name:nld_x_preferred":[
        "Rick Trevino"
    ],
    "name:nno_x_preferred":[
        "Rick Trevino"
    ],
    "name:nob_x_preferred":[
        "Rick Trevino"
    ],
    "name:slv_x_preferred":[
        "Rick Trevino"
    ],
    "name:spa_x_colloquial":[
        "Ricardo Trevino"
    ],
    "name:spa_x_preferred":[
        "Ricardo Trevi\u00f1o"
    ],
    "name:spa_x_variant":[
        "Rick Trevino"
    ],
    "name:sqi_x_preferred":[
        "Rick Trevino"
    ],
    "name:swe_x_preferred":[
        "Rick Trevino"
    ],
    "qs:gn_adm0_cc":"MX",
    "qs:gn_local":3532592,
    "qs:gn_nam_loc":"Atlixco, Atlixco, Puebla, MX",
    "qs:gn_namadm1":"21",
    "qs:local_max":890,
    "qs:local_sum":1042,
    "qs:localhoods":2,
    "qs:name":"Ricardo Trevi\u00f1o",
    "qs:name_adm0":"M\u00e9xico",
    "qs:name_adm1":"Puebla",
    "qs:name_adm2":"Atlixco",
    "qs:name_local":"Atlixco",
    "qs:photo_max":598,
    "qs:photo_sum":890,
    "qs:placetype":"Suburb",
    "qs:quad_count":7,
    "qs:woe_adm0":23424900,
    "qs:woe_adm1":2346284,
    "qs:woe_adm2":12601245,
    "qs:woe_lau":0,
    "qs:woe_local":112652,
    "qs:woe_ver":"7.10.0",
    "wd:wordcount":1246,
    "wof:lang":[
        "spa"
    ],
    "wof:name":"Ricardo Trevi\u00f1o",
    "wof:placetype":"neighbourhood"
},
  "geometry": {"coordinates":[-98.434759,18.910279],"type":"Point"}
}