{
  "type": "Feature",
  "properties": {
    "gn:admin1_code":"12",
    "gn:admin2_code":"69.0",
    "gn:asciiname":"Quiahuitlatzala",
    "gn:country_code":"MX",
    "gn:dem":2130,
    "gn:feature_class":"P",
    "gn:feature_code":"PPL",
    "gn:name":"Quiahuitlatzala",
    "gn:population":0,
    "gn:timezone":"America/Mexico_City",
    "iso:country":"MX",
    "name:spa_x_preferred":[
        "Quiahuitlatzala"
    ],
    "name:und_x_variant":[
        "Quiahuitlazala",
        "Quihuitlatzala"
    ],
    "wof:name":"Quiahuitlatzala",
    "wof:placetype":"locality"
},
  "geometry": {"coordinates":[-98.60144,17.34136],"type":"Point"}
}