{
  "type": "Feature",
  "properties": {
    "gn:admin1_code":"14.0",
    "gn:admin2_code":"90.0",
    "gn:asciiname":"Higueras",
    "gn:country_code":"MX",
    "gn:dem":1185,
    "gn:feature_class":"P",
    "gn:feature_code":"PPL",
    "gn:name":"Higueras",
    "gn:population":0,
    "gn:timezone":"America/Mexico_City",
    "iso:country":"MX",
    "name:ara_x_preferred":[
        "\u0647\u064a\u062c\u0648\u064a\u0631\u0627\u0633"
    ],
    "name:arg_x_preferred":[
        "Figueras"
    ],
    "name:cat_x_preferred":[
        "Figueres"
    ],
    "name:ceb_x_preferred":[
        "Higueras"
    ],
    "name:eus_x_preferred":[
        "Higueras"
    ],
    "name:fra_x_preferred":[
        "Higueras"
    ],
    "name:hun_x_preferred":[
        "Higueras"
    ],
    "name:hye_x_preferred":[
        "\u053b\u0563\u0565\u0580\u0561\u057d"
    ],
    "name:ita_x_preferred":[
        "Higueras"
    ],
    "name:msa_x_preferred":[
        "Higueras"
    ],
    "name:nld_x_preferred":[
        "Higueras"
    ],
    "name:oci_x_preferred":[
        "Higueras"
    ],
    "name:pol_x_preferred":[
        "Higueras"
    ],
    "name:por_x_preferred":[
        "Higueras"
    ],
    "name:rus_x_preferred":[
        "\u0418\u0433\u0435\u0440\u0430\u0441"
    ],
    "name:spa_x_preferred":[
        "Higueras"
    ],
    "name:swe_x_preferred":[
        "Higueras"
    ],
    "name:ukr_x_preferred":[
        "\u0406\u0433\u0435\u0440\u0430\u0441"
    ],
    "name:uzb_x_preferred":[
        "Higueras"
    ],
    "name:war_x_preferred":[
        "Higueras"
    ],
    "name:zho_x_preferred":[
        "\u4f0a\u683c\u62c9\u65af"
    ],
    "wof:name":"Higueras",
    "wof:placetype":"locality"
},
  "geometry": {"coordinates":[-104.10406,20.00624],"type":"Point"}
}