{
  "type": "Feature",
  "properties": {
    "gn:admin1_code":"14.0",
    "gn:admin2_code":"90.0",
    "gn:asciiname":"Higueras",
    "gn:country_code":"MX",
    "gn:dem":1185,
    "gn:feature_class":"P",
    "gn:feature_code":"PPL",
    "gn:name":"Higueras",
    "gn:population":0,
    "gn:timezone":"America/Mexico_City",
    "iso:country":"MX",
    "name:spa_x_preferred":[
        "Higueras"
    ],
    "wof:name":"Higueras",
    "wof:placetype":"locality"
},
  "geometry": {"coordinates":[-104.10406,20.00624],"type":"Point"}
}