{
  "type": "Feature",
  "properties": {
    "gn:admin1_code":"23.0",
    "gn:admin2_code":"4.0",
    "gn:asciiname":"Villa Guacamaya",
    "gn:country_code":"MX",
    "gn:dem":0,
    "gn:feature_class":"P",
    "gn:feature_code":"PPL",
    "gn:name":"Villa Guacamaya",
    "gn:population":0,
    "gn:timezone":"America/Cancun",
    "iso:country":"MX",
    "name:spa_x_preferred":[
        "Villa Guacamaya"
    ],
    "wof:name":"Villa Guacamaya",
    "wof:placetype":"locality"
},
  "geometry": {"coordinates":[-87.80835999999999,18.34611],"type":"Point"}
}