{
  "type": "Feature",
  "properties": {
    "gn:admin1_code":"28",
    "gn:admin2_code":"10.0",
    "gn:asciiname":"Esperanza de los Perez",
    "gn:cc2":"MX",
    "gn:country_code":"MX",
    "gn:dem":414,
    "gn:feature_class":"P",
    "gn:feature_code":"PPL",
    "gn:name":"Esperanza de los P\u00e9rez",
    "gn:population":0,
    "gn:timezone":"America/Monterrey",
    "iso:country":"MX",
    "name:und_x_variant":[
        "Esperanza",
        "Esperanza de los P\u00e9rez"
    ],
    "wof:name":"Esperanza de los Perez",
    "wof:placetype":"locality"
},
  "geometry": {"coordinates":[-98.58333,24.66667],"type":"Point"}
}