{
  "type": "Feature",
  "properties": {
    "gn:admin1_code":"27.0",
    "gn:admin2_code":"1.0",
    "gn:asciiname":"El Tamarindo",
    "gn:country_code":"MX",
    "gn:dem":33,
    "gn:feature_class":"P",
    "gn:feature_code":"PPL",
    "gn:name":"El Tamarindo",
    "gn:population":0,
    "gn:timezone":"America/Mexico_City",
    "iso:country":"MX",
    "name:spa_x_preferred":[
        "El Tamarindo"
    ],
    "wof:name":"El Tamarindo",
    "wof:placetype":"locality"
},
  "geometry": {"coordinates":[-91.17017,17.78026000000001],"type":"Point"}
}