{
  "type": "Feature",
  "properties": {
    "gn:admin1_code":"30",
    "gn:admin2_code":"21.0",
    "gn:asciiname":"Manzanillo",
    "gn:country_code":"MX",
    "gn:dem":842,
    "gn:feature_class":"P",
    "gn:feature_code":"PPL",
    "gn:name":"Manzanillo",
    "gn:population":303,
    "gn:timezone":"America/Mexico_City",
    "iso:country":"MX",
    "name:bre_x_preferred":[
        "Manzanillo"
    ],
    "name:ceb_x_preferred":[
        "Manzanillo"
    ],
    "name:deu_x_preferred":[
        "Manzanillo"
    ],
    "name:epo_x_preferred":[
        "Manzanillo"
    ],
    "name:fra_x_preferred":[
        "Manzanillo"
    ],
    "name:glg_x_preferred":[
        "Manzanillo"
    ],
    "name:heb_x_preferred":[
        "\u05de\u05e0\u05e1\u05e0\u05d9\u05d5"
    ],
    "name:ita_x_preferred":[
        "Manzanillo"
    ],
    "name:kor_x_preferred":[
        "\ub9cc\uc0ac\ub2c8\uc694"
    ],
    "name:lit_x_preferred":[
        "Mansaniljas"
    ],
    "name:nld_x_preferred":[
        "Manzanillo"
    ],
    "name:oci_x_preferred":[
        "Manzanillo"
    ],
    "name:pol_x_preferred":[
        "Manzanillo"
    ],
    "name:rus_x_preferred":[
        "\u041c\u0430\u043d\u0441\u0430\u043d\u0438\u043b\u044c\u043e"
    ],
    "name:spa_x_preferred":[
        "Manzanillo"
    ],
    "name:swe_x_preferred":[
        "Manzanillo"
    ],
    "name:ukr_x_preferred":[
        "\u041c\u0430\u043d\u0441\u0430\u043d\u0456\u043b\u044c\u0439\u043e"
    ],
    "wof:name":"Manzanillo",
    "wof:placetype":"locality",
    "wof:population":303
},
  "geometry": {"coordinates":[-96.83222000000001,18.95194],"type":"Point"}
}