{
  "type": "Feature",
  "properties": {
    "gn:admin1_code":"10.0",
    "gn:admin2_code":"20.0",
    "gn:asciiname":"San Martin de Gamon",
    "gn:country_code":"MX",
    "gn:dem":2088,
    "gn:feature_class":"P",
    "gn:feature_code":"PPL",
    "gn:name":"San Martin de Gam\u00f3n",
    "gn:population":0,
    "gn:timezone":"America/Monterrey",
    "iso:country":"MX",
    "name:spa_x_preferred":[
        "San Martin de Gam\u00f3n"
    ],
    "name:und_x_variant":[
        "Rancho Gam\u00f3n",
        "Gam\u00f3n"
    ],
    "wof:name":"San Martin de Gamon",
    "wof:placetype":"locality"
},
  "geometry": {"coordinates":[-104.34008,24.60674],"type":"Point"}
}