{
  "type": "Feature",
  "properties": {
    "gn:admin1_code":"11",
    "gn:admin2_code":"29",
    "gn:asciiname":"Ejido Tepozan y Salitrillo (El Potrero)",
    "gn:country_code":"MX",
    "gn:dem":2038,
    "gn:feature_class":"P",
    "gn:feature_code":"PPL",
    "gn:name":"Ejido Tepoz\u00e1n y Salitrillo (El Potrero)",
    "gn:population":36,
    "gn:timezone":"America/Mexico_City",
    "iso:country":"MX",
    "name:und_x_variant":[
        "Ejido Tepoz\u00e1n y Salitrillo (El Potrero)"
    ],
    "wof:name":"Ejido Tepozan y Salitrillo (El Potrero)",
    "wof:placetype":"locality",
    "wof:population":36
},
  "geometry": {"coordinates":[-100.81332999999999,21.42833],"type":"Point"}
}