{
  "type": "Feature",
  "properties": {
    "gn:admin1_code":"14.0",
    "gn:admin2_code":"49.0",
    "gn:asciiname":"La Periquera",
    "gn:country_code":"MX",
    "gn:dem":732,
    "gn:feature_class":"P",
    "gn:feature_code":"PPL",
    "gn:name":"La Periquera",
    "gn:population":0,
    "gn:timezone":"America/Mexico_City",
    "iso:country":"MX",
    "name:spa_x_preferred":[
        "La Periquera"
    ],
    "wof:name":"La Periquera",
    "wof:placetype":"locality"
},
  "geometry": {"coordinates":[-102.95511,19.42528],"type":"Point"}
}