{
  "type": "Feature",
  "properties": {
    "gn:admin1_code":"7.0",
    "gn:admin2_code":"38.0",
    "gn:asciiname":"La Fragua",
    "gn:country_code":"MX",
    "gn:dem":599,
    "gn:feature_class":"P",
    "gn:feature_code":"PPL",
    "gn:name":"La Fragua",
    "gn:population":0,
    "gn:timezone":"America/Monterrey",
    "iso:country":"MX",
    "name:spa_x_preferred":[
        "La Fragua"
    ],
    "wof:name":"La Fragua",
    "wof:placetype":"locality"
},
  "geometry": {"coordinates":[-101.43329,29.00866],"type":"Point"}
}