{
  "type": "Feature",
  "properties": {
    "gn:admin1_code":"26",
    "gn:admin2_code":"65.0",
    "gn:asciiname":"Represo de los Franceses",
    "gn:country_code":"MX",
    "gn:dem":835,
    "gn:feature_class":"P",
    "gn:feature_code":"PPL",
    "gn:name":"Represo de los Franceses",
    "gn:population":2,
    "gn:timezone":"America/Hermosillo",
    "iso:country":"MX",
    "name:und_x_variant":[
        "Rancho El Represo",
        "Represo"
    ],
    "wof:name":"Represo de los Franceses",
    "wof:placetype":"locality",
    "wof:population":2
},
  "geometry": {"coordinates":[-111.64185999999999,31.18344],"type":"Point"}
}