{
  "type": "Feature",
  "properties": {
    "gn:admin1_code":"14.0",
    "gn:asciiname":"Salgado",
    "gn:country_code":"MX",
    "gn:dem":1841,
    "gn:feature_class":"P",
    "gn:feature_code":"PPL",
    "gn:name":"Salgado",
    "gn:population":0,
    "gn:timezone":"America/Mexico_City",
    "iso:country":"MX",
    "name:spa_x_preferred":[
        "Salgado"
    ],
    "wof:name":"Salgado",
    "wof:placetype":"locality"
},
  "geometry": {"coordinates":[-102.05349,20.87098],"type":"Point"}
}