{
  "type": "Feature",
  "properties": {
    "gn:admin1_code":"24",
    "gn:admin2_code":"38.0",
    "gn:asciiname":"El Sacrificio",
    "gn:country_code":"MX",
    "gn:dem":119,
    "gn:feature_class":"P",
    "gn:feature_code":"PPL",
    "gn:name":"El Sacrificio",
    "gn:population":5,
    "gn:timezone":"America/Mexico_City",
    "iso:country":"MX",
    "wof:name":"El Sacrificio",
    "wof:placetype":"locality",
    "wof:population":5
},
  "geometry": {"coordinates":[-98.70694,21.42972],"type":"Point"}
}