{
  "type": "Feature",
  "properties": {
    "gn:admin1_code":"5",
    "gn:admin2_code":"108",
    "gn:asciiname":"San Antolin",
    "gn:country_code":"MX",
    "gn:dem":598,
    "gn:feature_class":"P",
    "gn:feature_code":"PPL",
    "gn:name":"San Antol\u00edn",
    "gn:population":23,
    "gn:timezone":"America/Mexico_City",
    "iso:country":"MX",
    "name:und_x_variant":[
        "San Antol\u00edn"
    ],
    "wof:name":"San Antolin",
    "wof:placetype":"locality",
    "wof:population":23
},
  "geometry": {"coordinates":[-93.35722,16.425],"type":"Point"}
}