{
  "type": "Feature",
  "properties": {
    "gn:admin1_code":"30",
    "gn:admin2_code":"4.0",
    "gn:asciiname":"Paso de la Milpa",
    "gn:country_code":"MX",
    "gn:dem":226,
    "gn:feature_class":"P",
    "gn:feature_code":"PPL",
    "gn:name":"Paso de la Milpa",
    "gn:population":710,
    "gn:timezone":"America/Mexico_City",
    "iso:country":"MX",
    "name:spa_x_preferred":[
        "Paso de la Milpa"
    ],
    "wof:name":"Paso de la Milpa",
    "wof:placetype":"locality",
    "wof:population":710
},
  "geometry": {"coordinates":[-96.61297,19.42739],"type":"Point"}
}