{
  "type": "Feature",
  "properties": {
    "gn:admin1_code":"20",
    "gn:admin2_code":"554.0",
    "gn:asciiname":"San Jose Chinantequilla",
    "gn:country_code":"MX",
    "gn:dem":1169,
    "gn:feature_class":"P",
    "gn:feature_code":"PPL",
    "gn:name":"San Jose Chinantequilla",
    "gn:population":0,
    "gn:timezone":"America/Mexico_City",
    "iso:country":"MX",
    "wof:name":"San Jose Chinantequilla",
    "wof:placetype":"locality"
},
  "geometry": {"coordinates":[-95.99028,17.30778],"type":"Point"}
}