{
  "type": "Feature",
  "properties": {
    "gn:admin1_code":"30.0",
    "gn:admin2_code":"33.0",
    "gn:asciiname":"El Zapote",
    "gn:country_code":"MX",
    "gn:dem":59,
    "gn:feature_class":"P",
    "gn:feature_code":"PPL",
    "gn:name":"El Zapote",
    "gn:population":68,
    "gn:timezone":"America/Mexico_City",
    "iso:country":"MX",
    "name:spa_x_preferred":[
        "El Zapote"
    ],
    "wof:name":"El Zapote",
    "wof:placetype":"locality",
    "wof:population":68
},
  "geometry": {"coordinates":[-97.34361,20.65778],"type":"Point"}
}