{
  "type": "Feature",
  "properties": {
    "gn:admin1_code":"6",
    "gn:admin2_code":"3.0",
    "gn:asciiname":"San Juan de Allende",
    "gn:country_code":"MX",
    "gn:dem":1546,
    "gn:feature_class":"P",
    "gn:feature_code":"PPL",
    "gn:name":"San Juan de Allende",
    "gn:population":0,
    "gn:timezone":"America/Chihuahua",
    "iso:country":"MX",
    "name:und_x_variant":[
        "San Juan",
        "San Juan de Allende"
    ],
    "wof:name":"San Juan de Allende",
    "wof:placetype":"locality"
},
  "geometry": {"coordinates":[-105.28358,27.00592],"type":"Point"}
}