{
  "type": "Feature",
  "properties": {
    "gn:admin1_code":"19.0",
    "gn:admin2_code":"37.0",
    "gn:asciiname":"La Presa de los Fresnos",
    "gn:country_code":"MX",
    "gn:dem":612,
    "gn:feature_class":"P",
    "gn:feature_code":"PPL",
    "gn:name":"La Presa de los Fresnos",
    "gn:population":0,
    "gn:timezone":"America/Monterrey",
    "iso:country":"MX",
    "name:spa_x_preferred":[
        "La Presa de los Fresnos"
    ],
    "wof:name":"La Presa de los Fresnos",
    "wof:placetype":"locality"
},
  "geometry": {"coordinates":[-100.60055,26.39298],"type":"Point"}
}