{
  "type": "Feature",
  "properties": {
    "gn:admin1_code":"5",
    "gn:admin2_code":"34.0",
    "gn:asciiname":"Nuevo San Juan Carrizal",
    "gn:country_code":"MX",
    "gn:dem":703,
    "gn:feature_class":"P",
    "gn:feature_code":"PPL",
    "gn:name":"Nuevo San Juan Carrizal",
    "gn:population":148,
    "gn:timezone":"America/Mexico_City",
    "iso:country":"MX",
    "wof:name":"Nuevo San Juan Carrizal",
    "wof:placetype":"locality",
    "wof:population":148
},
  "geometry": {"coordinates":[-92.12889,15.80278],"type":"Point"}
}