{
  "type": "Feature",
  "properties": {
    "gn:admin1_code":"30",
    "gn:admin2_code":"178.0",
    "gn:asciiname":"Seis de Enero",
    "gn:country_code":"MX",
    "gn:dem":5,
    "gn:feature_class":"P",
    "gn:feature_code":"PPL",
    "gn:name":"Seis de Enero",
    "gn:population":93,
    "gn:timezone":"America/Mexico_City",
    "iso:country":"MX",
    "wof:name":"Seis de Enero",
    "wof:placetype":"locality",
    "wof:population":93
},
  "geometry": {"coordinates":[-95.58360999999999,18.51639],"type":"Point"}
}