{
  "type": "Feature",
  "properties": {
    "gn:admin1_code":"6",
    "gn:admin2_code":"16.0",
    "gn:asciiname":"Rancho las Galeras de Chavez",
    "gn:country_code":"MX",
    "gn:dem":1205,
    "gn:feature_class":"P",
    "gn:feature_code":"PPL",
    "gn:name":"Rancho las Galeras de Ch\u00e1vez",
    "gn:population":4,
    "gn:timezone":"America/Chihuahua",
    "iso:country":"MX",
    "name:und_x_variant":[
        "Rancho las Galeras de Ch\u00e1vez"
    ],
    "wof:name":"Rancho las Galeras de Chavez",
    "wof:placetype":"locality",
    "wof:population":4
},
  "geometry": {"coordinates":[-105.17516999999999,27.87244],"type":"Point"}
}