{
  "type": "Feature",
  "properties": {
    "gn:admin1_code":"16.0",
    "gn:admin2_code":"26.0",
    "gn:asciiname":"Paso de Potrerillos",
    "gn:country_code":"MX",
    "gn:dem":146,
    "gn:feature_class":"P",
    "gn:feature_code":"PPL",
    "gn:name":"Paso de Potrerillos",
    "gn:population":0,
    "gn:timezone":"America/Mexico_City",
    "iso:country":"MX",
    "name:spa_x_preferred":[
        "Paso de Potrerillos"
    ],
    "wof:name":"Paso de Potrerillos",
    "wof:placetype":"locality"
},
  "geometry": {"coordinates":[-103.50335,18.95122000000001],"type":"Point"}
}