{
  "type": "Feature",
  "properties": {
    "gn:admin1_code":"28",
    "gn:admin2_code":"39.0",
    "gn:asciiname":"La Joya del Berrendo",
    "gn:country_code":"MX",
    "gn:dem":1557,
    "gn:feature_class":"P",
    "gn:feature_code":"PPL",
    "gn:name":"La Joya del Berrendo",
    "gn:population":0,
    "gn:timezone":"America/Mexico_City",
    "iso:country":"MX",
    "name:spa_x_preferred":[
        "La Joya del Berrendo"
    ],
    "wof:name":"La Joya del Berrendo",
    "wof:placetype":"locality"
},
  "geometry": {"coordinates":[-100.00051000000001,23.0472],"type":"Point"}
}