{
  "type": "Feature",
  "properties": {
    "gn:admin1_code":"5",
    "gn:admin2_code":"32.0",
    "gn:asciiname":"Belisario Dominguez",
    "gn:country_code":"MX",
    "gn:dem":1511,
    "gn:feature_class":"P",
    "gn:feature_code":"PPL",
    "gn:name":"Belisario Dom\u00ednguez",
    "gn:population":185,
    "gn:timezone":"America/Mexico_City",
    "iso:country":"MX",
    "name:und_x_variant":[
        "Belisario Dom\u00ednguez"
    ],
    "wof:name":"Belisario Dominguez",
    "wof:placetype":"locality",
    "wof:population":185
},
  "geometry": {"coordinates":[-92.52388999999999,15.39833],"type":"Point"}
}