{
  "type": "Feature",
  "properties": {
    "gn:admin1_code":"14",
    "gn:admin2_code":"100.0",
    "gn:asciiname":"Teocinte (Teocintle)",
    "gn:country_code":"MX",
    "gn:dem":76,
    "gn:feature_class":"P",
    "gn:feature_code":"PPL",
    "gn:name":"Teocinte (Teocintle)",
    "gn:population":194,
    "gn:timezone":"America/Mexico_City",
    "iso:country":"MX",
    "wof:name":"Teocinte (Teocintle)",
    "wof:placetype":"locality",
    "wof:population":194
},
  "geometry": {"coordinates":[-105.19389,19.91611],"type":"Point"}
}