{
  "type": "Feature",
  "properties": {
    "gn:admin1_code":"22.0",
    "gn:admin2_code":"16.0",
    "gn:asciiname":"Dolores Cuadrilla de Enmedio",
    "gn:country_code":"MX",
    "gn:dem":2106,
    "gn:feature_class":"P",
    "gn:feature_code":"PPL",
    "gn:name":"Dolores Cuadrilla de Enmedio",
    "gn:population":0,
    "gn:timezone":"America/Mexico_City",
    "iso:country":"MX",
    "name:spa_x_preferred":[
        "Dolores Cuadrilla de Enmedio"
    ],
    "wof:name":"Dolores Cuadrilla de Enmedio",
    "wof:placetype":"locality"
},
  "geometry": {"coordinates":[-100.07966999999999,20.35257],"type":"Point"}
}