{
  "type": "Feature",
  "properties": {
    "gn:admin1_code":"19",
    "gn:admin2_code":"43.0",
    "gn:asciiname":"Los Pavorreales (La Hacienda)",
    "gn:country_code":"MX",
    "gn:dem":1043,
    "gn:feature_class":"P",
    "gn:feature_code":"PPL",
    "gn:name":"Los Pavorreales (La Hacienda)",
    "gn:population":8,
    "gn:timezone":"America/Monterrey",
    "iso:country":"MX",
    "wof:name":"Los Pavorreales (La Hacienda)",
    "wof:placetype":"locality",
    "wof:population":8
},
  "geometry": {"coordinates":[-100.14167,25.11562],"type":"Point"}
}