{
  "type": "Feature",
  "properties": {
    "gn:admin1_code":"10",
    "gn:admin2_code":"23.0",
    "gn:asciiname":"La Muralla",
    "gn:country_code":"MX",
    "gn:dem":2300,
    "gn:feature_class":"P",
    "gn:feature_code":"PPL",
    "gn:name":"La Muralla",
    "gn:population":0,
    "gn:timezone":"America/Monterrey",
    "iso:country":"MX",
    "name:spa_x_preferred":[
        "La Muralla"
    ],
    "wof:name":"La Muralla",
    "wof:placetype":"locality"
},
  "geometry": {"coordinates":[-105.61973999999999,23.67219],"type":"Point"}
}