{
  "type": "Feature",
  "properties": {
    "gn:admin1_code":"32",
    "gn:admin2_code":"9.0",
    "gn:asciiname":"Las Pilitas",
    "gn:country_code":"MX",
    "gn:dem":2168,
    "gn:feature_class":"P",
    "gn:feature_code":"PPL",
    "gn:name":"Las Pilitas",
    "gn:population":0,
    "gn:timezone":"America/Mexico_City",
    "iso:country":"MX",
    "name:spa_x_preferred":[
        "Las Pilitas"
    ],
    "name:spa_x_variant":[
        "Las Pilas"
    ],
    "wof:name":"Las Pilitas",
    "wof:placetype":"locality"
},
  "geometry": {"coordinates":[-103.97014,23.46921],"type":"Point"}
}