{
  "type": "Feature",
  "properties": {
    "gn:admin1_code":"31",
    "gn:admin2_code":"91.0",
    "gn:asciiname":"San Francisco Grande",
    "gn:country_code":"MX",
    "gn:dem":27,
    "gn:feature_class":"P",
    "gn:feature_code":"PPL",
    "gn:name":"San Francisco Grande",
    "gn:population":0,
    "gn:timezone":"America/Merida",
    "iso:country":"MX",
    "name:spa_x_preferred":[
        "San Francisco Grande"
    ],
    "name:spa_x_variant":[
        "San Francisco"
    ],
    "wof:name":"San Francisco Grande",
    "wof:placetype":"locality"
},
  "geometry": {"coordinates":[-88.47345,20.70071],"type":"Point"}
}