{
  "type": "Feature",
  "properties": {
    "gn:admin1_code":"30.0",
    "gn:admin2_code":"124.0",
    "gn:asciiname":"Vicente Guerrero",
    "gn:country_code":"MX",
    "gn:dem":145,
    "gn:feature_class":"P",
    "gn:feature_code":"PPL",
    "gn:name":"Vicente Guerrero",
    "gn:population":251,
    "gn:timezone":"America/Mexico_City",
    "iso:country":"MX",
    "name:spa_x_preferred":[
        "Vicente Guerrero"
    ],
    "wof:name":"Vicente Guerrero",
    "wof:placetype":"locality",
    "wof:population":251
},
  "geometry": {"coordinates":[-97.28944,20.43806],"type":"Point"}
}