{
  "type": "Feature",
  "properties": {
    "gn:admin1_code":"28.0",
    "gn:admin2_code":"2.0",
    "gn:asciiname":"El Boderoso",
    "gn:country_code":"MX",
    "gn:dem":197,
    "gn:feature_class":"P",
    "gn:feature_code":"PPL",
    "gn:name":"El Boderoso",
    "gn:population":1,
    "gn:timezone":"America/Monterrey",
    "iso:country":"MX",
    "name:spa_x_preferred":[
        "El Boderoso"
    ],
    "wof:name":"El Boderoso",
    "wof:placetype":"locality",
    "wof:population":1
},
  "geometry": {"coordinates":[-98.11499999999999,23.26417],"type":"Point"}
}