{
  "type": "Feature",
  "properties": {
    "gn:admin1_code":"5",
    "gn:admin2_code":"108",
    "gn:asciiname":"El Recuerdo",
    "gn:country_code":"MX",
    "gn:dem":674,
    "gn:feature_class":"P",
    "gn:feature_code":"PPL",
    "gn:name":"El Recuerdo",
    "gn:population":11,
    "gn:timezone":"America/Mexico_City",
    "iso:country":"MX",
    "wof:name":"El Recuerdo",
    "wof:placetype":"locality",
    "wof:population":11
},
  "geometry": {"coordinates":[-93.48611,16.35694],"type":"Point"}
}