{
  "type": "Feature",
  "properties": {
    "gn:admin1_code":"28.0",
    "gn:admin2_code":"37.0",
    "gn:asciiname":"El Amanecer",
    "gn:country_code":"MX",
    "gn:dem":43,
    "gn:feature_class":"P",
    "gn:feature_code":"PPL",
    "gn:name":"El Amanecer",
    "gn:population":6,
    "gn:timezone":"America/Monterrey",
    "iso:country":"MX",
    "name:spa_x_preferred":[
        "El Amanecer"
    ],
    "wof:name":"El Amanecer",
    "wof:placetype":"locality",
    "wof:population":6
},
  "geometry": {"coordinates":[-98.03959999999999,23.65576],"type":"Point"}
}