{
  "type": "Feature",
  "properties": {
    "gn:admin1_code":"14",
    "gn:admin2_code":"73",
    "gn:asciiname":"Los Tepetates",
    "gn:country_code":"MX",
    "gn:dem":1886,
    "gn:feature_class":"P",
    "gn:feature_code":"PPL",
    "gn:name":"Los Tepetates",
    "gn:population":11,
    "gn:timezone":"America/Mexico_City",
    "iso:country":"MX",
    "wof:name":"Los Tepetates",
    "wof:placetype":"locality",
    "wof:population":11
},
  "geometry": {"coordinates":[-102.21167,21.25472],"type":"Point"}
}