{
  "type": "Feature",
  "properties": {
    "gn:admin1_code":"5",
    "gn:admin2_code":"89",
    "gn:asciiname":"El Circulo",
    "gn:country_code":"MX",
    "gn:dem":45,
    "gn:feature_class":"P",
    "gn:feature_code":"PPL",
    "gn:name":"El C\u00edrculo",
    "gn:population":12,
    "gn:timezone":"America/Mexico_City",
    "iso:country":"MX",
    "name:und_x_variant":[
        "El C\u00edrculo"
    ],
    "wof:name":"El Circulo",
    "wof:placetype":"locality",
    "wof:population":12
},
  "geometry": {"coordinates":[-92.37,14.93083],"type":"Point"}
}