{
  "type": "Feature",
  "properties": {
    "gn:admin1_code":"15",
    "gn:admin2_code":"60",
    "gn:asciiname":"La Cantera",
    "gn:country_code":"MX",
    "gn:dem":2578,
    "gn:feature_class":"P",
    "gn:feature_code":"PPL",
    "gn:name":"La Cantera",
    "gn:population":30,
    "gn:timezone":"America/Mexico_City",
    "iso:country":"MX",
    "wof:name":"La Cantera",
    "wof:placetype":"locality",
    "wof:population":30
},
  "geometry": {"coordinates":[-99.40064,19.58735],"type":"Point"}
}