{
  "type": "Feature",
  "properties": {
    "gn:admin1_code":"10",
    "gn:admin2_code":"23.0",
    "gn:asciiname":"Los Guayabos",
    "gn:country_code":"MX",
    "gn:dem":1343,
    "gn:feature_class":"P",
    "gn:feature_code":"PPL",
    "gn:name":"Los Guayabos",
    "gn:population":142,
    "gn:timezone":"America/Monterrey",
    "iso:country":"MX",
    "wof:name":"Los Guayabos",
    "wof:placetype":"locality",
    "wof:population":142
},
  "geometry": {"coordinates":[-105.54445,23.45057000000001],"type":"Point"}
}