{
  "type": "Feature",
  "properties": {
    "gn:admin1_code":"26",
    "gn:admin2_code":"69.0",
    "gn:asciiname":"El Cusi",
    "gn:country_code":"MX",
    "gn:dem":1408,
    "gn:feature_class":"P",
    "gn:feature_code":"PPL",
    "gn:name":"El Cusi",
    "gn:population":0,
    "gn:timezone":"America/Hermosillo",
    "iso:country":"MX",
    "name:spa_x_preferred":[
        "El Cusi"
    ],
    "wof:name":"El Cusi",
    "wof:placetype":"locality"
},
  "geometry": {"coordinates":[-109.25887,28.50636],"type":"Point"}
}