{
  "type": "Feature",
  "properties": {
    "gn:admin1_code":"11",
    "gn:admin2_code":"23.0",
    "gn:asciiname":"La Yesca",
    "gn:country_code":"MX",
    "gn:dem":1999,
    "gn:feature_class":"P",
    "gn:feature_code":"PPL",
    "gn:name":"La Yesca",
    "gn:population":8,
    "gn:timezone":"America/Mexico_City",
    "iso:country":"MX",
    "name:ceb_x_preferred":[
        "La Yesca"
    ],
    "name:epo_x_preferred":[
        "La Yesca"
    ],
    "name:eus_x_preferred":[
        "La Yesca"
    ],
    "name:ita_x_preferred":[
        "La Yesca"
    ],
    "name:por_x_preferred":[
        "La Yesca"
    ],
    "name:rus_x_preferred":[
        "\u041b\u0430-\u0415\u0441\u043a\u0430"
    ],
    "name:sco_x_preferred":[
        "La Yesca"
    ],
    "name:spa_x_preferred":[
        "La Yesca"
    ],
    "name:srp_x_preferred":[
        "\u041e\u043f\u0448\u0442\u0438\u043d\u0430 \u041b\u0430 \u0408\u0435\u0441\u043a\u0430"
    ],
    "name:swe_x_preferred":[
        "La Yesca"
    ],
    "name:vie_x_preferred":[
        "La Yesca"
    ],
    "wof:name":"La Yesca",
    "wof:placetype":"locality",
    "wof:population":8
},
  "geometry": {"coordinates":[-101.80583,20.42667],"type":"Point"}
}