{
  "type": "Feature",
  "properties": {
    "gn:admin1_code":"13",
    "gn:admin2_code":"34.0",
    "gn:asciiname":"Mecapala",
    "gn:country_code":"MX",
    "gn:dem":1119,
    "gn:feature_class":"P",
    "gn:feature_code":"PPL",
    "gn:name":"Mecapala",
    "gn:population":8,
    "gn:timezone":"America/Mexico_City",
    "iso:country":"MX",
    "wof:name":"Mecapala",
    "wof:placetype":"locality",
    "wof:population":8
},
  "geometry": {"coordinates":[-98.73175000000001,20.97108],"type":"Point"}
}