{
  "type": "Feature",
  "properties": {
    "gn:admin1_code":"28",
    "gn:admin2_code":"31.0",
    "gn:asciiname":"Loma Larga",
    "gn:country_code":"MX",
    "gn:dem":1504,
    "gn:feature_class":"P",
    "gn:feature_code":"PPL",
    "gn:name":"Loma Larga",
    "gn:population":0,
    "gn:timezone":"America/Monterrey",
    "iso:country":"MX",
    "wof:name":"Loma Larga",
    "wof:placetype":"locality"
},
  "geometry": {"coordinates":[-99.56667,23.21667],"type":"Point"}
}