{
  "type": "Feature",
  "properties": {
    "gn:admin1_code":"20",
    "gn:admin2_code":"57.0",
    "gn:asciiname":"Rancho la Aurora (Desviacion Suchilapan)",
    "gn:country_code":"MX",
    "gn:dem":60,
    "gn:feature_class":"P",
    "gn:feature_code":"PPL",
    "gn:name":"Rancho la Aurora (Desviaci\u00f3n Suchilapan)",
    "gn:population":9,
    "gn:timezone":"America/Mexico_City",
    "iso:country":"MX",
    "name:und_x_variant":[
        "Rancho la Aurora (Desviaci\u00f3n Suchilapan)"
    ],
    "wof:name":"Rancho la Aurora (Desviacion Suchilapan)",
    "wof:placetype":"locality",
    "wof:population":9
},
  "geometry": {"coordinates":[-95.05333,17.36167],"type":"Point"}
}