{
  "type": "Feature",
  "properties": {
    "gn:admin1_code":"27",
    "gn:admin2_code":"6.0",
    "gn:asciiname":"Huimango Segunda Seccion",
    "gn:country_code":"MX",
    "gn:dem":15,
    "gn:feature_class":"P",
    "gn:feature_code":"PPL",
    "gn:name":"Huimango Segunda Secci\u00f3n",
    "gn:population":0,
    "gn:timezone":"America/Mexico_City",
    "iso:country":"MX",
    "name:spa_x_preferred":[
        "Huimango Segunda Secci\u00f3n"
    ],
    "name:spa_x_variant":[
        "La Mona"
    ],
    "wof:name":"Huimango Segunda Seccion",
    "wof:placetype":"locality"
},
  "geometry": {"coordinates":[-93.20934,18.15551],"type":"Point"}
}