{
  "type": "Feature",
  "properties": {
    "gn:admin1_code":"24",
    "gn:admin2_code":"33.0",
    "gn:asciiname":"San Dionisio",
    "gn:country_code":"MX",
    "gn:dem":1986,
    "gn:feature_class":"P",
    "gn:feature_code":"PPL",
    "gn:name":"San Dionisio",
    "gn:population":0,
    "gn:timezone":"America/Mexico_City",
    "iso:country":"MX",
    "name:ceb_x_preferred":[
        "San Dionisio"
    ],
    "name:fra_x_preferred":[
        "San Dionisio"
    ],
    "name:nld_x_preferred":[
        "San Dionisio"
    ],
    "name:por_x_preferred":[
        "San Dionisio"
    ],
    "name:spa_x_preferred":[
        "San Dionisio"
    ],
    "name:srp_x_preferred":[
        "\u0421\u0430\u043d \u0414\u0438\u043e\u043d\u0438\u0441\u0438\u043e"
    ],
    "name:swe_x_preferred":[
        "San Dionisio"
    ],
    "wof:name":"San Dionisio",
    "wof:placetype":"locality"
},
  "geometry": {"coordinates":[-101.97938000000001,23.23229],"type":"Point"}
}