{
  "type": "Feature",
  "properties": {
    "gn:admin1_code":"4",
    "gn:admin2_code":"6.0",
    "gn:asciiname":"La Parcela",
    "gn:country_code":"MX",
    "gn:dem":62,
    "gn:feature_class":"P",
    "gn:feature_code":"PPL",
    "gn:name":"La Parcela",
    "gn:population":0,
    "gn:timezone":"America/Merida",
    "iso:country":"MX",
    "name:spa_x_preferred":[
        "La Parcela"
    ],
    "wof:name":"La Parcela",
    "wof:placetype":"locality"
},
  "geometry": {"coordinates":[-89.83351,19.77165],"type":"Point"}
}