{
  "type": "Feature",
  "properties": {
    "gn:admin1_code":"13",
    "gn:admin2_code":"40",
    "gn:asciiname":"El Mexe Grande",
    "gn:country_code":"MX",
    "gn:dem":1393,
    "gn:feature_class":"P",
    "gn:feature_code":"PPL",
    "gn:name":"El Mexe Grande",
    "gn:population":19,
    "gn:timezone":"America/Mexico_City",
    "iso:country":"MX",
    "wof:name":"El Mexe Grande",
    "wof:placetype":"locality",
    "wof:population":19
},
  "geometry": {"coordinates":[-99.03753,21.04661],"type":"Point"}
}