{
  "type": "Feature",
  "properties": {
    "gn:admin1_code":"30.0",
    "gn:asciiname":"La Pepe",
    "gn:country_code":"MX",
    "gn:dem":12,
    "gn:feature_class":"P",
    "gn:feature_code":"PPL",
    "gn:name":"La Pepe",
    "gn:population":0,
    "gn:timezone":"America/Mexico_City",
    "iso:country":"MX",
    "name:spa_x_preferred":[
        "La Pepe"
    ],
    "wof:name":"La Pepe",
    "wof:placetype":"locality"
},
  "geometry": {"coordinates":[-96.62669,20.02028],"type":"Point"}
}