{
  "type": "Feature",
  "properties": {
    "gn:admin1_code":"6",
    "gn:admin2_code":"65.0",
    "gn:asciiname":"Mezcalerita",
    "gn:cc2":"MX",
    "gn:country_code":"MX",
    "gn:dem":760,
    "gn:feature_class":"P",
    "gn:feature_code":"PPL",
    "gn:name":"Mezcalerita",
    "gn:population":7,
    "gn:timezone":"America/Chihuahua",
    "iso:country":"MX",
    "name:und_x_variant":[
        "Mescalera Chica",
        "Mezcalera Chica"
    ],
    "wof:name":"Mezcalerita",
    "wof:placetype":"locality",
    "wof:population":7
},
  "geometry": {"coordinates":[-107.90685999999999,27.25104],"type":"Point"}
}