{
  "type": "Feature",
  "properties": {
    "gn:admin1_code":"26",
    "gn:admin2_code":"29.0",
    "gn:asciiname":"Colonia Luis Donaldo Colosio",
    "gn:country_code":"MX",
    "gn:dem":24,
    "gn:feature_class":"P",
    "gn:feature_code":"PPL",
    "gn:name":"Colonia Luis Donaldo Colosio",
    "gn:population":0,
    "gn:timezone":"America/Hermosillo",
    "iso:country":"MX",
    "name:spa_x_preferred":[
        "Colonia Luis Donaldo Colosio"
    ],
    "wof:name":"Colonia Luis Donaldo Colosio",
    "wof:placetype":"locality"
},
  "geometry": {"coordinates":[-110.92822,27.94601],"type":"Point"}
}