{
  "type": "Feature",
  "properties": {
    "gn:admin1_code":"17",
    "gn:asciiname":"Los Encinos",
    "gn:country_code":"MX",
    "gn:dem":2370,
    "gn:feature_class":"P",
    "gn:feature_code":"PPL",
    "gn:name":"Los Encinos",
    "gn:population":0,
    "gn:timezone":"America/Mexico_City",
    "iso:country":"MX",
    "name:spa_x_preferred":[
        "Los Encinos"
    ],
    "wof:name":"Los Encinos",
    "wof:placetype":"locality"
},
  "geometry": {"coordinates":[-99.52204,20.08488],"type":"Point"}
}