{
  "type": "Feature",
  "properties": {
    "gn:admin1_code":"14.0",
    "gn:admin2_code":"58.0",
    "gn:asciiname":"La Brea",
    "gn:country_code":"MX",
    "gn:dem":1100,
    "gn:feature_class":"P",
    "gn:feature_code":"PPL",
    "gn:name":"La Brea",
    "gn:population":0,
    "gn:timezone":"America/Mexico_City",
    "iso:country":"MX",
    "name:ceb_x_preferred":[
        "La Brea"
    ],
    "name:fin_x_preferred":[
        "La Brea"
    ],
    "name:spa_x_preferred":[
        "La Brea"
    ],
    "name:srp_x_preferred":[
        "\u041b\u0430 \u0411\u0440\u0435\u0430"
    ],
    "name:swe_x_preferred":[
        "La Brea"
    ],
    "wof:name":"La Brea",
    "wof:placetype":"locality"
},
  "geometry": {"coordinates":[-104.93132,20.6943],"type":"Point"}
}