{
  "type": "Feature",
  "properties": {
    "gn:admin1_code":"26",
    "gn:admin2_code":"33.0",
    "gn:asciiname":"El Ranchito (Yujumary)",
    "gn:country_code":"MX",
    "gn:dem":65,
    "gn:feature_class":"P",
    "gn:feature_code":"PPL",
    "gn:name":"El Ranchito (Yujumary)",
    "gn:population":5,
    "gn:timezone":"America/Hermosillo",
    "iso:country":"MX",
    "wof:name":"El Ranchito (Yujumary)",
    "wof:placetype":"locality",
    "wof:population":5
},
  "geometry": {"coordinates":[-109.13583,26.57833],"type":"Point"}
}