{
  "type": "Feature",
  "properties": {
    "gn:admin1_code":"14",
    "gn:admin2_code":"120",
    "gn:asciiname":"Cedral (La Escoba)",
    "gn:country_code":"MX",
    "gn:dem":1584,
    "gn:feature_class":"P",
    "gn:feature_code":"PPL",
    "gn:name":"Cedral (La Escoba)",
    "gn:population":11,
    "gn:timezone":"America/Mexico_City",
    "iso:country":"MX",
    "wof:name":"Cedral (La Escoba)",
    "wof:placetype":"locality",
    "wof:population":11
},
  "geometry": {"coordinates":[-103.43917,20.79861],"type":"Point"}
}