{
  "type": "Feature",
  "properties": {
    "gn:admin1_code":"30",
    "gn:admin2_code":"178.0",
    "gn:asciiname":"El Nacaste",
    "gn:country_code":"MX",
    "gn:dem":3,
    "gn:feature_class":"P",
    "gn:feature_code":"PPL",
    "gn:name":"El Nacaste",
    "gn:population":137,
    "gn:timezone":"America/Mexico_City",
    "iso:country":"MX",
    "wof:name":"El Nacaste",
    "wof:placetype":"locality",
    "wof:population":137
},
  "geometry": {"coordinates":[-95.75861,18.54194],"type":"Point"}
}