{
  "type": "Feature",
  "properties": {
    "gn:admin1_code":"5",
    "gn:admin2_code":"89.0",
    "gn:asciiname":"Hamburgo",
    "gn:country_code":"MX",
    "gn:dem":1175,
    "gn:feature_class":"P",
    "gn:feature_code":"PPL",
    "gn:name":"Hamburgo",
    "gn:population":0,
    "gn:timezone":"America/Mexico_City",
    "iso:country":"MX",
    "wof:name":"Hamburgo",
    "wof:placetype":"locality"
},
  "geometry": {"coordinates":[-92.32548,15.1726],"type":"Point"}
}