{
  "type": "Feature",
  "properties": {
    "gn:admin1_code":"13",
    "gn:asciiname":"Teacalco",
    "gn:country_code":"MX",
    "gn:dem":2438,
    "gn:feature_class":"P",
    "gn:feature_code":"PPL",
    "gn:name":"Teacalco",
    "gn:population":0,
    "gn:timezone":"America/Mexico_City",
    "iso:country":"MX",
    "name:spa_x_preferred":[
        "San Juan Teacalco"
    ],
    "name:und_x_variant":[
        "San Juan",
        "San Juan Bautista Teacalco"
    ],
    "wof:name":"Teacalco",
    "wof:placetype":"locality"
},
  "geometry": {"coordinates":[-98.85209,19.80561],"type":"Point"}
}