{
  "type": "Feature",
  "properties": {
    "gn:admin1_code":"11",
    "gn:admin2_code":"4.0",
    "gn:asciiname":"Colonia 18 de Diciembre",
    "gn:country_code":"MX",
    "gn:dem":1842,
    "gn:feature_class":"P",
    "gn:feature_code":"PPL",
    "gn:name":"Colonia 18 de Diciembre",
    "gn:population":135,
    "gn:timezone":"America/Mexico_City",
    "iso:country":"MX",
    "wof:name":"Colonia 18 de Diciembre",
    "wof:placetype":"locality",
    "wof:population":135
},
  "geometry": {"coordinates":[-100.64028,20.46472],"type":"Point"}
}