{
  "type": "Feature",
  "properties": {
    "gn:admin1_code":"11.0",
    "gn:admin2_code":"3.0",
    "gn:asciiname":"La Fraccion",
    "gn:country_code":"MX",
    "gn:dem":1889,
    "gn:feature_class":"P",
    "gn:feature_code":"PPL",
    "gn:name":"La Fracci\u00f3n",
    "gn:population":0,
    "gn:timezone":"America/Mexico_City",
    "iso:country":"MX",
    "wof:name":"La Fraccion",
    "wof:placetype":"locality"
},
  "geometry": {"coordinates":[-100.76389,20.92167],"type":"Point"}
}