{
  "type": "Feature",
  "properties": {
    "gn:admin1_code":"14",
    "gn:admin2_code":"76.0",
    "gn:asciiname":"El Zopilote",
    "gn:country_code":"MX",
    "gn:dem":1061,
    "gn:feature_class":"P",
    "gn:feature_code":"PPL",
    "gn:name":"El Zopilote",
    "gn:population":6,
    "gn:timezone":"America/Mexico_City",
    "iso:country":"MX",
    "wof:name":"El Zopilote",
    "wof:placetype":"locality",
    "wof:population":6
},
  "geometry": {"coordinates":[-103.84444000000001,21.72111],"type":"Point"}
}