{
  "type": "Feature",
  "properties": {
    "gn:admin1_code":"10.0",
    "gn:admin2_code":"9.0",
    "gn:asciiname":"Arroyo de Lajas",
    "gn:country_code":"MX",
    "gn:dem":2681,
    "gn:feature_class":"P",
    "gn:feature_code":"PPL",
    "gn:name":"Arroyo de Lajas",
    "gn:population":0,
    "gn:timezone":"America/Monterrey",
    "iso:country":"MX",
    "name:spa_x_preferred":[
        "Arroyo de Lajas"
    ],
    "wof:name":"Arroyo de Lajas",
    "wof:placetype":"locality"
},
  "geometry": {"coordinates":[-106.29665,25.94238],"type":"Point"}
}