{
  "type": "Feature",
  "properties": {
    "gn:admin1_code":"32",
    "gn:admin2_code":"51.0",
    "gn:asciiname":"Las Amapolas",
    "gn:country_code":"MX",
    "gn:dem":1999,
    "gn:feature_class":"P",
    "gn:feature_code":"PPL",
    "gn:name":"Las Amapolas",
    "gn:population":0,
    "gn:timezone":"America/Mexico_City",
    "iso:country":"MX",
    "name:spa_x_preferred":[
        "Las Amapolas"
    ],
    "wof:name":"Las Amapolas",
    "wof:placetype":"locality"
},
  "geometry": {"coordinates":[-102.37591,23.1398],"type":"Point"}
}