{
  "type": "Feature",
  "properties": {
    "gn:admin1_code":"5",
    "gn:admin2_code":"97.0",
    "gn:asciiname":"El Encanto (Estacion los Patos)",
    "gn:country_code":"MX",
    "gn:dem":41,
    "gn:feature_class":"P",
    "gn:feature_code":"PPL",
    "gn:name":"El Encanto (Estaci\u00f3n los Patos)",
    "gn:population":6,
    "gn:timezone":"America/Mexico_City",
    "iso:country":"MX",
    "name:und_x_variant":[
        "El Encanto (Estaci\u00f3n los Patos)"
    ],
    "wof:name":"El Encanto (Estacion los Patos)",
    "wof:placetype":"locality",
    "wof:population":6
},
  "geometry": {"coordinates":[-93.44,15.82833],"type":"Point"}
}