{
  "type": "Feature",
  "properties": {
    "gn:admin1_code":"10.0",
    "gn:admin2_code":"39.0",
    "gn:asciiname":"Los Alisos",
    "gn:country_code":"MX",
    "gn:dem":1981,
    "gn:feature_class":"P",
    "gn:feature_code":"PPL",
    "gn:name":"Los Alisos",
    "gn:population":0,
    "gn:timezone":"America/Monterrey",
    "iso:country":"MX",
    "name:spa_x_preferred":[
        "Los Alisos"
    ],
    "name:und_x_variant":[
        "Alisos"
    ],
    "wof:name":"Los Alisos",
    "wof:placetype":"locality"
},
  "geometry": {"coordinates":[-105.01536000000002,24.86248],"type":"Point"}
}