{
  "type": "Feature",
  "properties": {
    "gn:admin1_code":"30.0",
    "gn:admin2_code":"142.0",
    "gn:asciiname":"Medio Camino",
    "gn:country_code":"MX",
    "gn:dem":81,
    "gn:feature_class":"P",
    "gn:feature_code":"PPL",
    "gn:name":"Medio Camino",
    "gn:population":0,
    "gn:timezone":"America/Mexico_City",
    "iso:country":"MX",
    "name:spa_x_preferred":[
        "Medio Camino"
    ],
    "wof:name":"Medio Camino",
    "wof:placetype":"locality"
},
  "geometry": {"coordinates":[-95.16342,17.66567000000001],"type":"Point"}
}