{
  "type": "Feature",
  "properties": {
    "gn:admin1_code":"5",
    "gn:admin2_code":"92.0",
    "gn:asciiname":"Jesus Abadia Gutierrez",
    "gn:country_code":"MX",
    "gn:dem":293,
    "gn:feature_class":"P",
    "gn:feature_code":"PPL",
    "gn:name":"Jes\u00fas Abad\u00eda Guti\u00e9rrez",
    "gn:population":5,
    "gn:timezone":"America/Mexico_City",
    "iso:country":"MX",
    "name:und_x_variant":[
        "Jes\u00fas Abad\u00eda Guti\u00e9rrez"
    ],
    "wof:name":"Jesus Abadia Gutierrez",
    "wof:placetype":"locality",
    "wof:population":5
},
  "geometry": {"coordinates":[-93.58972,17.17722],"type":"Point"}
}