{
  "type": "Feature",
  "properties": {
    "gn:admin1_code":"28",
    "gn:admin2_code":"22.0",
    "gn:asciiname":"Los Cuates",
    "gn:cc2":"MX",
    "gn:country_code":"MX",
    "gn:dem":12,
    "gn:feature_class":"P",
    "gn:feature_code":"PPL",
    "gn:name":"Los Cuates",
    "gn:population":26,
    "gn:timezone":"America/Matamoros",
    "iso:country":"MX",
    "name:und_x_variant":[
        "Cuates",
        "Cuates Capote"
    ],
    "wof:name":"Los Cuates",
    "wof:placetype":"locality",
    "wof:population":26
},
  "geometry": {"coordinates":[-97.6875,25.9625],"type":"Point"}
}