{
  "type": "Feature",
  "properties": {
    "gn:admin1_code":"20.0",
    "gn:admin2_code":"277.0",
    "gn:asciiname":"El Chamizo",
    "gn:country_code":"MX",
    "gn:dem":2456,
    "gn:feature_class":"P",
    "gn:feature_code":"PPL",
    "gn:name":"El Chamizo",
    "gn:population":0,
    "gn:timezone":"America/Mexico_City",
    "iso:country":"MX",
    "name:spa_x_preferred":[
        "El Chamizo"
    ],
    "wof:name":"El Chamizo",
    "wof:placetype":"locality"
},
  "geometry": {"coordinates":[-97.19542,16.68422],"type":"Point"}
}