{
  "type": "Feature",
  "properties": {
    "gn:admin1_code":"30",
    "gn:admin2_code":"61.0",
    "gn:asciiname":"El Chichon",
    "gn:country_code":"MX",
    "gn:dem":27,
    "gn:feature_class":"P",
    "gn:feature_code":"PPL",
    "gn:name":"El Chich\u00f3n",
    "gn:population":0,
    "gn:timezone":"America/Mexico_City",
    "iso:country":"MX",
    "name:spa_x_preferred":[
        "El Chich\u00f3n"
    ],
    "wof:name":"El Chichon",
    "wof:placetype":"locality"
},
  "geometry": {"coordinates":[-94.13369,17.72863],"type":"Point"}
}