{
  "type": "Feature",
  "properties": {
    "gn:admin1_code":"13",
    "gn:admin2_code":"6.0",
    "gn:asciiname":"Santa Maria la Palma",
    "gn:country_code":"MX",
    "gn:dem":2012,
    "gn:feature_class":"P",
    "gn:feature_code":"PPL",
    "gn:name":"Santa Mar\u00eda la Palma",
    "gn:population":0,
    "gn:timezone":"America/Mexico_City",
    "iso:country":"MX",
    "name:und_x_variant":[
        "Santa Maria",
        "Santa Mar\u00eda la Palma"
    ],
    "wof:name":"Santa Maria la Palma",
    "wof:placetype":"locality"
},
  "geometry": {"coordinates":[-99.38764999999999,20.37012],"type":"Point"}
}