{
  "type": "Feature",
  "properties": {
    "gn:admin1_code":"30",
    "gn:admin2_code":"172.0",
    "gn:asciiname":"San Miguel (El Gallego)",
    "gn:country_code":"MX",
    "gn:dem":28,
    "gn:feature_class":"P",
    "gn:feature_code":"PPL",
    "gn:name":"San Miguel (El Gallego)",
    "gn:population":5,
    "gn:timezone":"America/Mexico_City",
    "iso:country":"MX",
    "wof:name":"San Miguel (El Gallego)",
    "wof:placetype":"locality",
    "wof:population":5
},
  "geometry": {"coordinates":[-94.74889,17.86694],"type":"Point"}
}