{
  "type": "Feature",
  "properties": {
    "gn:admin1_code":"5",
    "gn:admin2_code":"59.0",
    "gn:asciiname":"El Monte",
    "gn:country_code":"MX",
    "gn:dem":514,
    "gn:feature_class":"P",
    "gn:feature_code":"PPL",
    "gn:name":"El Monte",
    "gn:population":8,
    "gn:timezone":"America/Mexico_City",
    "iso:country":"MX",
    "wof:name":"El Monte",
    "wof:placetype":"locality",
    "wof:population":8
},
  "geometry": {"coordinates":[-91.66556,16.81028],"type":"Point"}
}