{
  "type": "Feature",
  "properties": {
    "gn:admin1_code":"5",
    "gn:admin2_code":"59.0",
    "gn:asciiname":"El Monte",
    "gn:country_code":"MX",
    "gn:dem":514,
    "gn:feature_class":"P",
    "gn:feature_code":"PPL",
    "gn:name":"El Monte",
    "gn:population":8,
    "gn:timezone":"America/Mexico_City",
    "iso:country":"MX",
    "name:ceb_x_preferred":[
        "El Monte"
    ],
    "name:deu_x_preferred":[
        "El Monte"
    ],
    "name:fra_x_preferred":[
        "El Monte"
    ],
    "name:ita_x_preferred":[
        "El Monte"
    ],
    "name:nld_x_preferred":[
        "El Monte"
    ],
    "name:por_x_preferred":[
        "El Monte"
    ],
    "name:rus_x_preferred":[
        "\u042d\u043b\u044c-\u041c\u043e\u043d\u0442\u0435"
    ],
    "name:srp_x_preferred":[
        "\u0415\u043b \u041c\u043e\u043d\u0442\u0435"
    ],
    "name:swe_x_preferred":[
        "El Monte"
    ],
    "wof:name":"El Monte",
    "wof:placetype":"locality",
    "wof:population":8
},
  "geometry": {"coordinates":[-91.66556,16.81028],"type":"Point"}
}