{
  "type": "Feature",
  "properties": {
    "gn:admin1_code":"5",
    "gn:admin2_code":"17.0",
    "gn:asciiname":"San Jesus",
    "gn:country_code":"MX",
    "gn:dem":600,
    "gn:feature_class":"P",
    "gn:feature_code":"PPL",
    "gn:name":"San Jes\u00fas",
    "gn:population":4,
    "gn:timezone":"America/Mexico_City",
    "iso:country":"MX",
    "name:und_x_variant":[
        "San Jes\u00fas"
    ],
    "wof:name":"San Jesus",
    "wof:placetype":"locality",
    "wof:population":4
},
  "geometry": {"coordinates":[-93.81778,16.79111],"type":"Point"}
}