{
  "type": "Feature",
  "properties": {
    "gn:admin1_code":"6",
    "gn:admin2_code":"9",
    "gn:asciiname":"Raperos",
    "gn:country_code":"MX",
    "gn:dem":2332,
    "gn:feature_class":"P",
    "gn:feature_code":"PPL",
    "gn:name":"Raperos",
    "gn:population":28,
    "gn:timezone":"America/Chihuahua",
    "iso:country":"MX",
    "wof:name":"Raperos",
    "wof:placetype":"locality",
    "wof:population":28
},
  "geometry": {"coordinates":[-107.72355,27.89769],"type":"Point"}
}