{
  "type": "Feature",
  "properties": {
    "gn:admin1_code":"25",
    "gn:admin2_code":"14.0",
    "gn:asciiname":"Tebaira",
    "gn:country_code":"MX",
    "gn:dem":256,
    "gn:feature_class":"P",
    "gn:feature_code":"PPL",
    "gn:name":"Tebaira",
    "gn:population":143,
    "gn:timezone":"America/Mazatlan",
    "iso:country":"MX",
    "wof:name":"Tebaira",
    "wof:placetype":"locality",
    "wof:population":143
},
  "geometry": {"coordinates":[-105.5224,22.98895],"type":"Point"}
}