{
  "type": "Feature",
  "properties": {
    "gn:admin1_code":"30",
    "gn:admin2_code":"174.0",
    "gn:asciiname":"Galvan Caracas",
    "gn:country_code":"MX",
    "gn:dem":113,
    "gn:feature_class":"P",
    "gn:feature_code":"PPL",
    "gn:name":"Galv\u00e1n Caracas",
    "gn:population":269,
    "gn:timezone":"America/Mexico_City",
    "iso:country":"MX",
    "name:und_x_variant":[
        "Galv\u00e1n Caracas"
    ],
    "wof:name":"Galvan Caracas",
    "wof:placetype":"locality",
    "wof:population":269
},
  "geometry": {"coordinates":[-96.45,18.64861],"type":"Point"}
}