{
  "type": "Feature",
  "properties": {
    "gn:admin1_code":"30",
    "gn:admin2_code":"201",
    "gn:asciiname":"Dos Caminos",
    "gn:country_code":"MX",
    "gn:dem":1093,
    "gn:feature_class":"P",
    "gn:feature_code":"PPL",
    "gn:name":"Dos Caminos",
    "gn:population":33,
    "gn:timezone":"America/Mexico_City",
    "iso:country":"MX",
    "wof:name":"Dos Caminos",
    "wof:placetype":"locality",
    "wof:population":33
},
  "geometry": {"coordinates":[-96.94944,18.72278],"type":"Point"}
}