{
  "type": "Feature",
  "properties": {
    "gn:admin1_code":"30",
    "gn:admin2_code":"4.0",
    "gn:asciiname":"Cansa Burro",
    "gn:country_code":"MX",
    "gn:dem":13,
    "gn:feature_class":"P",
    "gn:feature_code":"PPL",
    "gn:name":"Cansa Burro",
    "gn:population":0,
    "gn:timezone":"America/Mexico_City",
    "iso:country":"MX",
    "name:spa_x_preferred":[
        "Cansa Burro"
    ],
    "wof:name":"Cansa Burro",
    "wof:placetype":"locality"
},
  "geometry": {"coordinates":[-96.37772,19.5518],"type":"Point"}
}