{
  "type": "Feature",
  "properties": {
    "gn:admin1_code":"10",
    "gn:admin2_code":"23.0",
    "gn:asciiname":"El Pozole",
    "gn:country_code":"MX",
    "gn:dem":1190,
    "gn:feature_class":"P",
    "gn:feature_code":"PPL",
    "gn:name":"El Pozole",
    "gn:population":0,
    "gn:timezone":"America/Monterrey",
    "iso:country":"MX",
    "name:spa_x_preferred":[
        "El Pozole"
    ],
    "wof:name":"El Pozole",
    "wof:placetype":"locality"
},
  "geometry": {"coordinates":[-105.58307000000001,23.39445],"type":"Point"}
}