{
  "type": "Feature",
  "properties": {
    "gn:admin1_code":"28",
    "gn:admin2_code":"3.0",
    "gn:asciiname":"La Arboleda (La Fortuna)",
    "gn:country_code":"MX",
    "gn:dem":32,
    "gn:feature_class":"P",
    "gn:feature_code":"PPL",
    "gn:name":"La Arboleda (La Fortuna)",
    "gn:population":5,
    "gn:timezone":"America/Monterrey",
    "iso:country":"MX",
    "wof:name":"La Arboleda (La Fortuna)",
    "wof:placetype":"locality",
    "wof:population":5
},
  "geometry": {"coordinates":[-97.95111,22.52917],"type":"Point"}
}