{
  "type": "Feature",
  "properties": {
    "gn:admin1_code":"28.0",
    "gn:admin2_code":"8.0",
    "gn:asciiname":"Campo Numero Uno",
    "gn:country_code":"MX",
    "gn:dem":179,
    "gn:feature_class":"P",
    "gn:feature_code":"PPL",
    "gn:name":"Campo N\u00famero Uno",
    "gn:population":0,
    "gn:timezone":"America/Monterrey",
    "iso:country":"MX",
    "name:spa_x_preferred":[
        "Campo N\u00famero Uno"
    ],
    "name:spa_x_variant":[
        "Campo Alto"
    ],
    "wof:name":"Campo Numero Uno",
    "wof:placetype":"locality"
},
  "geometry": {"coordinates":[-98.77131,23.53682],"type":"Point"}
}