{
  "type": "Feature",
  "properties": {
    "gn:admin1_code":"29",
    "gn:admin2_code":"15.0",
    "gn:asciiname":"San Juan Nepopualco",
    "gn:country_code":"MX",
    "gn:dem":2527,
    "gn:feature_class":"P",
    "gn:feature_code":"PPL",
    "gn:name":"San Juan Nepopualco",
    "gn:population":0,
    "gn:timezone":"America/Mexico_City",
    "iso:country":"MX",
    "name:und_x_variant":[
        "Nepopualco"
    ],
    "wof:name":"San Juan Nepopualco",
    "wof:placetype":"locality"
},
  "geometry": {"coordinates":[-98.34385,19.36741],"type":"Point"}
}