{
  "type": "Feature",
  "properties": {
    "gn:admin1_code":"6",
    "gn:admin2_code":"27.0",
    "gn:asciiname":"Paraje Huiyorare",
    "gn:country_code":"MX",
    "gn:dem":2324,
    "gn:feature_class":"P",
    "gn:feature_code":"PPL",
    "gn:name":"Paraje Huiy\u00f3rare",
    "gn:population":0,
    "gn:timezone":"America/Chihuahua",
    "iso:country":"MX",
    "name:spa_x_preferred":[
        "Paraje Huiy\u00f3rare"
    ],
    "wof:name":"Paraje Huiyorare",
    "wof:placetype":"locality"
},
  "geometry": {"coordinates":[-107.33798,27.17102],"type":"Point"}
}