{
  "type": "Feature",
  "properties": {
    "gn:admin1_code":"1",
    "gn:admin2_code":"1",
    "gn:asciiname":"El Molino",
    "gn:country_code":"MX",
    "gn:dem":1968,
    "gn:feature_class":"P",
    "gn:feature_code":"PPL",
    "gn:name":"El Molino",
    "gn:population":31,
    "gn:timezone":"America/Mexico_City",
    "iso:country":"MX",
    "wof:name":"El Molino",
    "wof:placetype":"locality",
    "wof:population":31
},
  "geometry": {"coordinates":[-102.23528,21.79556],"type":"Point"}
}