{
  "type": "Feature",
  "properties": {
    "gn:admin1_code":"19",
    "gn:admin2_code":"39",
    "gn:asciiname":"Canadas del Sur",
    "gn:country_code":"MX",
    "gn:dem":730,
    "gn:feature_class":"P",
    "gn:feature_code":"PPL",
    "gn:name":"Ca\u00f1adas del Sur",
    "gn:population":11,
    "gn:timezone":"America/Monterrey",
    "iso:country":"MX",
    "name:und_x_variant":[
        "Ca\u00f1adas del Sur"
    ],
    "wof:name":"Canadas del Sur",
    "wof:placetype":"locality",
    "wof:population":11
},
  "geometry": {"coordinates":[-100.28586,25.59533],"type":"Point"}
}