{
  "type": "Feature",
  "properties": {
    "gn:admin1_code":"17",
    "gn:admin2_code":"2.0",
    "gn:asciiname":"Campo Tlacotlaco",
    "gn:country_code":"MX",
    "gn:dem":1679,
    "gn:feature_class":"P",
    "gn:feature_code":"PPL",
    "gn:name":"Campo Tlacotlaco",
    "gn:population":60,
    "gn:timezone":"America/Mexico_City",
    "iso:country":"MX",
    "wof:name":"Campo Tlacotlaco",
    "wof:placetype":"locality",
    "wof:population":60
},
  "geometry": {"coordinates":[-98.89496,18.94536],"type":"Point"}
}