{
  "type": "Feature",
  "properties": {
    "gn:admin1_code":"21",
    "gn:admin2_code":"53",
    "gn:asciiname":"Toltempan",
    "gn:country_code":"MX",
    "gn:dem":2284,
    "gn:feature_class":"P",
    "gn:feature_code":"PPL",
    "gn:name":"Toltempan",
    "gn:population":25,
    "gn:timezone":"America/Mexico_City",
    "iso:country":"MX",
    "wof:name":"Toltempan",
    "wof:placetype":"locality",
    "wof:population":25
},
  "geometry": {"coordinates":[-98.04268999999999,19.8419],"type":"Point"}
}