{
  "type": "Feature",
  "properties": {
    "gn:admin1_code":"30",
    "gn:admin2_code":"123.0",
    "gn:asciiname":"Herradura Leyva",
    "gn:country_code":"MX",
    "gn:dem":14,
    "gn:feature_class":"P",
    "gn:feature_code":"PPL",
    "gn:name":"Herradura Leyva",
    "gn:population":75,
    "gn:timezone":"America/Mexico_City",
    "iso:country":"MX",
    "wof:name":"Herradura Leyva",
    "wof:placetype":"locality",
    "wof:population":75
},
  "geometry": {"coordinates":[-98.12111,21.975],"type":"Point"}
}