{
  "type": "Feature",
  "properties": {
    "gn:admin1_code":"15.0",
    "gn:admin2_code":"99.0",
    "gn:asciiname":"Atlapulco",
    "gn:country_code":"MX",
    "gn:dem":3055,
    "gn:feature_class":"P",
    "gn:feature_code":"PPL",
    "gn:name":"Atlapulco",
    "gn:population":0,
    "gn:timezone":"America/Mexico_City",
    "iso:country":"MX",
    "name:spa_x_preferred":[
        "Atlapulco"
    ],
    "wof:name":"Atlapulco",
    "wof:placetype":"locality"
},
  "geometry": {"coordinates":[-98.76257,19.43854],"type":"Point"}
}