{
  "type": "Feature",
  "properties": {
    "gn:admin1_code":"3",
    "gn:admin2_code":"1.0",
    "gn:asciiname":"Colonia Agricola Revolucion Mexicana",
    "gn:country_code":"MX",
    "gn:dem":60,
    "gn:feature_class":"P",
    "gn:feature_code":"PPL",
    "gn:name":"Colonia Agr\u00edcola Revoluci\u00f3n Mexicana",
    "gn:population":4,
    "gn:timezone":"America/Mazatlan",
    "iso:country":"MX",
    "name:und_x_variant":[
        "Colonia Agr\u00edcola Revoluci\u00f3n Mexicana"
    ],
    "wof:name":"Colonia Agricola Revolucion Mexicana",
    "wof:placetype":"locality",
    "wof:population":4
},
  "geometry": {"coordinates":[-111.61991999999999,25.00928],"type":"Point"}
}