{
  "type": "Feature",
  "properties": {
    "gn:admin1_code":"16",
    "gn:admin2_code":"85.0",
    "gn:asciiname":"Colonia la Lomita",
    "gn:country_code":"MX",
    "gn:dem":1610,
    "gn:feature_class":"P",
    "gn:feature_code":"PPL",
    "gn:name":"Colonia la Lomita",
    "gn:population":314,
    "gn:timezone":"America/Mexico_City",
    "iso:country":"MX",
    "wof:name":"Colonia la Lomita",
    "wof:placetype":"locality",
    "wof:population":314
},
  "geometry": {"coordinates":[-102.25,19.93556],"type":"Point"}
}