{
  "type": "Feature",
  "properties": {
    "gn:admin1_code":"28.0",
    "gn:admin2_code":"40.0",
    "gn:asciiname":"Urbano de la Rosa",
    "gn:country_code":"MX",
    "gn:dem":21,
    "gn:feature_class":"P",
    "gn:feature_code":"PPL",
    "gn:name":"Urbano de la Rosa",
    "gn:population":0,
    "gn:timezone":"America/Monterrey",
    "iso:country":"MX",
    "name:spa_x_preferred":[
        "Urbano de la Rosa"
    ],
    "name:und_x_variant":[
        "Urban de la Rosa"
    ],
    "wof:name":"Urbano de la Rosa",
    "wof:placetype":"locality"
},
  "geometry": {"coordinates":[-97.84488,25.79301],"type":"Point"}
}