{
  "type": "Feature",
  "properties": {
    "gn:admin1_code":"32",
    "gn:admin2_code":"17.0",
    "gn:asciiname":"Bajio San Joaquin",
    "gn:country_code":"MX",
    "gn:dem":2181,
    "gn:feature_class":"P",
    "gn:feature_code":"PPL",
    "gn:name":"Baj\u00edo San Joaqu\u00edn",
    "gn:population":5,
    "gn:timezone":"America/Mexico_City",
    "iso:country":"MX",
    "name:und_x_variant":[
        "Baj\u00edo San Joaqu\u00edn"
    ],
    "wof:name":"Bajio San Joaquin",
    "wof:placetype":"locality",
    "wof:population":5
},
  "geometry": {"coordinates":[-102.44806,22.76111],"type":"Point"}
}