{
  "type": "Feature",
  "properties": {
    "gn:admin1_code":"24",
    "gn:admin2_code":"21.0",
    "gn:asciiname":"San Marcos Carmona",
    "gn:country_code":"MX",
    "gn:dem":1949,
    "gn:feature_class":"P",
    "gn:feature_code":"PPL",
    "gn:name":"San Marcos Carmona",
    "gn:population":0,
    "gn:timezone":"America/Mexico_City",
    "iso:country":"MX",
    "name:spa_x_preferred":[
        "San Marcos Carmona"
    ],
    "wof:name":"San Marcos Carmona",
    "wof:placetype":"locality"
},
  "geometry": {"coordinates":[-101.05195999999999,22.192],"type":"Point"}
}