{
  "type": "Feature",
  "properties": {
    "gn:admin1_code":"5",
    "gn:admin2_code":"32",
    "gn:asciiname":"Penjamo",
    "gn:country_code":"MX",
    "gn:dem":66,
    "gn:feature_class":"P",
    "gn:feature_code":"PPL",
    "gn:name":"P\u00e9njamo",
    "gn:population":13,
    "gn:timezone":"America/Mexico_City",
    "iso:country":"MX",
    "name:und_x_variant":[
        "P\u00e9njamo"
    ],
    "wof:name":"Penjamo",
    "wof:placetype":"locality",
    "wof:population":13
},
  "geometry": {"coordinates":[-92.62833000000001,15.25611],"type":"Point"}
}