{
  "type": "Feature",
  "properties": {
    "gn:admin1_code":"16.0",
    "gn:admin2_code":"1.0",
    "gn:asciiname":"Agua Chiquita",
    "gn:country_code":"MX",
    "gn:dem":2937,
    "gn:feature_class":"P",
    "gn:feature_code":"PPL",
    "gn:name":"Agua Chiquita",
    "gn:population":0,
    "gn:timezone":"America/Mexico_City",
    "iso:country":"MX",
    "name:spa_x_preferred":[
        "Agua Chiquita"
    ],
    "wof:name":"Agua Chiquita",
    "wof:placetype":"locality"
},
  "geometry": {"coordinates":[-101.40864000000001,19.43083],"type":"Point"}
}