{
  "type": "Feature",
  "properties": {
    "gn:admin1_code":"5",
    "gn:admin2_code":"108",
    "gn:asciiname":"El Eden",
    "gn:country_code":"MX",
    "gn:dem":654,
    "gn:feature_class":"P",
    "gn:feature_code":"PPL",
    "gn:name":"El Ed\u00e9n",
    "gn:population":17,
    "gn:timezone":"America/Mexico_City",
    "iso:country":"MX",
    "name:und_x_variant":[
        "El Ed\u00e9n"
    ],
    "wof:name":"El Eden",
    "wof:placetype":"locality",
    "wof:population":17
},
  "geometry": {"coordinates":[-93.45722000000001,16.37167],"type":"Point"}
}