{
  "type": "Feature",
  "properties": {
    "gn:admin1_code":"16",
    "gn:admin2_code":"8",
    "gn:asciiname":"La Iluminaria",
    "gn:country_code":"MX",
    "gn:dem":758,
    "gn:feature_class":"P",
    "gn:feature_code":"PPL",
    "gn:name":"La Iluminaria",
    "gn:population":10,
    "gn:timezone":"America/Mexico_City",
    "iso:country":"MX",
    "wof:name":"La Iluminaria",
    "wof:placetype":"locality",
    "wof:population":10
},
  "geometry": {"coordinates":[-102.83499999999999,18.27278],"type":"Point"}
}