{
  "type": "Feature",
  "properties": {
    "gn:admin1_code":"6",
    "gn:admin2_code":"8.0",
    "gn:asciiname":"Rancheria Rocahuachi",
    "gn:country_code":"MX",
    "gn:dem":1987,
    "gn:feature_class":"P",
    "gn:feature_code":"PPL",
    "gn:name":"Rancher\u00eda Rocahuachi",
    "gn:population":0,
    "gn:timezone":"America/Chihuahua",
    "iso:country":"MX",
    "name:spa_x_preferred":[
        "Rancher\u00eda Rocahuachi"
    ],
    "wof:name":"Rancheria Rocahuachi",
    "wof:placetype":"locality"
},
  "geometry": {"coordinates":[-107.53097,27.07072],"type":"Point"}
}