{
  "type": "Feature",
  "properties": {
    "gn:admin1_code":"15",
    "gn:admin2_code":"102.0",
    "gn:asciiname":"Primera Manzana del Pueblo de Rincon de Bucio",
    "gn:country_code":"MX",
    "gn:dem":2638,
    "gn:feature_class":"P",
    "gn:feature_code":"PPL",
    "gn:name":"Primera Manzana del Pueblo de Rinc\u00f3n de Bucio",
    "gn:population":816,
    "gn:timezone":"America/Mexico_City",
    "iso:country":"MX",
    "wof:name":"Primera Manzana del Pueblo de Rincon de Bucio",
    "wof:placetype":"locality",
    "wof:population":816
},
  "geometry": {"coordinates":[-99.68889,19.87583],"type":"Point"}
}