{
  "type": "Feature",
  "properties": {
    "gn:admin1_code":"5",
    "gn:admin2_code":"4",
    "gn:asciiname":"Santa Lucia",
    "gn:country_code":"MX",
    "gn:dem":1231,
    "gn:feature_class":"P",
    "gn:feature_code":"PPL",
    "gn:name":"Santa Lucia",
    "gn:population":34,
    "gn:timezone":"America/Mexico_City",
    "iso:country":"MX",
    "wof:name":"Santa Lucia",
    "wof:placetype":"locality",
    "wof:population":34
},
  "geometry": {"coordinates":[-92.10861,16.73639],"type":"Point"}
}