{
  "type": "Feature",
  "properties": {
    "gn:admin1_code":"6",
    "gn:admin2_code":"19.0",
    "gn:asciiname":"Don Reyes",
    "gn:country_code":"MX",
    "gn:dem":1782,
    "gn:feature_class":"P",
    "gn:feature_code":"PPL",
    "gn:name":"Don Reyes",
    "gn:population":0,
    "gn:timezone":"America/Chihuahua",
    "iso:country":"MX",
    "name:spa_x_preferred":[
        "Don Reyes"
    ],
    "wof:name":"Don Reyes",
    "wof:placetype":"locality"
},
  "geometry": {"coordinates":[-106.38564,28.93654],"type":"Point"}
}