{
  "type": "Feature",
  "properties": {
    "gn:admin1_code":"14",
    "gn:admin2_code":"38",
    "gn:asciiname":"La Coronilla",
    "gn:country_code":"MX",
    "gn:dem":913,
    "gn:feature_class":"P",
    "gn:feature_code":"PPL",
    "gn:name":"La Coronilla",
    "gn:population":14,
    "gn:timezone":"America/Mexico_City",
    "iso:country":"MX",
    "name:cat_x_preferred":[
        "La Coronilla"
    ],
    "name:ceb_x_preferred":[
        "La Coronilla"
    ],
    "name:deu_x_preferred":[
        "La Coronilla"
    ],
    "name:fra_x_preferred":[
        "La Coronilla"
    ],
    "name:hye_x_preferred":[
        "\u053c\u0561 \u053f\u0578\u0580\u0578\u0576\u056b\u056c\u056b\u0561"
    ],
    "name:nor_x_preferred":[
        "La Coronilla"
    ],
    "name:por_x_preferred":[
        "La Coronilla"
    ],
    "name:rus_x_preferred":[
        "\u041b\u0430-\u041a\u043e\u0440\u043e\u043d\u0438\u043b\u044c\u044f"
    ],
    "name:spa_x_preferred":[
        "La Coronilla"
    ],
    "name:urd_x_preferred":[
        "\u0644\u0627 \u06a9\u0648\u0631\u0648\u0646\u06cc\u0644\u0627"
    ],
    "wof:name":"La Coronilla",
    "wof:placetype":"locality",
    "wof:population":14
},
  "geometry": {"coordinates":[-104.48333,20.80444],"type":"Point"}
}