{
  "type": "Feature",
  "properties": {
    "gn:admin1_code":"14",
    "gn:admin2_code":"38",
    "gn:asciiname":"La Coronilla",
    "gn:country_code":"MX",
    "gn:dem":913,
    "gn:feature_class":"P",
    "gn:feature_code":"PPL",
    "gn:name":"La Coronilla",
    "gn:population":14,
    "gn:timezone":"America/Mexico_City",
    "iso:country":"MX",
    "wof:name":"La Coronilla",
    "wof:placetype":"locality",
    "wof:population":14
},
  "geometry": {"coordinates":[-104.48333,20.80444],"type":"Point"}
}