{
  "type": "Feature",
  "properties": {
    "gn:admin1_code":"10",
    "gn:admin2_code":"23.0",
    "gn:asciiname":"Bajio Hondo",
    "gn:country_code":"MX",
    "gn:dem":2463,
    "gn:feature_class":"P",
    "gn:feature_code":"PPL",
    "gn:name":"Baj\u00edo Hondo",
    "gn:population":0,
    "gn:timezone":"America/Monterrey",
    "iso:country":"MX",
    "name:spa_x_preferred":[
        "Baj\u00edo Hondo"
    ],
    "wof:name":"Bajio Hondo",
    "wof:placetype":"locality"
},
  "geometry": {"coordinates":[-105.34667,23.64105],"type":"Point"}
}