{
  "type": "Feature",
  "properties": {
    "gn:admin1_code":"21",
    "gn:admin2_code":"199",
    "gn:asciiname":"Ejido San Jose",
    "gn:country_code":"MX",
    "gn:dem":2893,
    "gn:feature_class":"P",
    "gn:feature_code":"PPL",
    "gn:name":"Ejido San Jos\u00e9",
    "gn:population":49,
    "gn:timezone":"America/Mexico_City",
    "iso:country":"MX",
    "name:und_x_variant":[
        "Ejido San Jos\u00e9"
    ],
    "wof:name":"Ejido San Jose",
    "wof:placetype":"locality",
    "wof:population":49
},
  "geometry": {"coordinates":[-97.37076999999999,19.67566],"type":"Point"}
}