{
  "type": "Feature",
  "properties": {
    "gn:admin1_code":"27",
    "gn:admin2_code":"11.0",
    "gn:asciiname":"Boca de Amatitan",
    "gn:country_code":"MX",
    "gn:dem":6,
    "gn:feature_class":"P",
    "gn:feature_code":"PPL",
    "gn:name":"Boca de Amatit\u00e1n",
    "gn:population":90,
    "gn:timezone":"America/Mexico_City",
    "iso:country":"MX",
    "name:und_x_variant":[
        "Boca de Amatit\u00e1n"
    ],
    "wof:name":"Boca de Amatitan",
    "wof:placetype":"locality",
    "wof:population":90
},
  "geometry": {"coordinates":[-92.09417000000001,18.09028],"type":"Point"}
}