{
  "type": "Feature",
  "properties": {
    "gn:admin1_code":"30",
    "gn:admin2_code":"89.0",
    "gn:asciiname":"El Mariscal",
    "gn:cc2":"MX",
    "gn:country_code":"MX",
    "gn:dem":7,
    "gn:feature_class":"P",
    "gn:feature_code":"PPL",
    "gn:name":"El Mariscal",
    "gn:population":2,
    "gn:timezone":"America/Mexico_City",
    "iso:country":"MX",
    "name:und_x_variant":[
        "Plan Marisal",
        "Plan Mariscal"
    ],
    "wof:name":"El Mariscal",
    "wof:placetype":"locality",
    "wof:population":2
},
  "geometry": {"coordinates":[-94.66,17.86222],"type":"Point"}
}