{
  "type": "Feature",
  "properties": {
    "gn:admin1_code":"30",
    "gn:admin2_code":"121.0",
    "gn:asciiname":"Dolor de Cabeza",
    "gn:country_code":"MX",
    "gn:dem":82,
    "gn:feature_class":"P",
    "gn:feature_code":"PPL",
    "gn:name":"Dolor de Cabeza",
    "gn:population":5,
    "gn:timezone":"America/Mexico_City",
    "iso:country":"MX",
    "wof:name":"Dolor de Cabeza",
    "wof:placetype":"locality",
    "wof:population":5
},
  "geometry": {"coordinates":[-97.92583,21.64139],"type":"Point"}
}