{
  "type": "Feature",
  "properties": {
    "gn:admin1_code":"30",
    "gn:admin2_code":"82",
    "gn:asciiname":"Rancho Daniela",
    "gn:country_code":"MX",
    "gn:dem":41,
    "gn:feature_class":"P",
    "gn:feature_code":"PPL",
    "gn:name":"Rancho Daniela",
    "gn:population":18,
    "gn:timezone":"America/Mexico_City",
    "iso:country":"MX",
    "wof:name":"Rancho Daniela",
    "wof:placetype":"locality",
    "wof:population":18
},
  "geometry": {"coordinates":[-94.33028,18.05417000000001],"type":"Point"}
}