{
  "type": "Feature",
  "properties": {
    "gn:admin1_code":"24",
    "gn:admin2_code":"32",
    "gn:asciiname":"El Sauz",
    "gn:country_code":"MX",
    "gn:dem":1890,
    "gn:feature_class":"P",
    "gn:feature_code":"PPL",
    "gn:name":"El Sauz",
    "gn:population":46,
    "gn:timezone":"America/Mexico_City",
    "iso:country":"MX",
    "wof:name":"El Sauz",
    "wof:placetype":"locality",
    "wof:population":46
},
  "geometry": {"coordinates":[-100.64333000000001,21.85583],"type":"Point"}
}