{
  "type": "Feature",
  "properties": {
    "gn:gn_country":"MX",
    "gn:gn_fcode":"PPL",
    "gn:gn_pop":0,
    "iso:country":"MX",
    "name:unk_x_variant":[
        "Cantera"
    ],
    "qs_pg:aaroncc":"MX",
    "qs_pg:gn_country":"MX",
    "qs_pg:gn_fcode":"PPL",
    "qs_pg:gn_pop":0,
    "qs_pg:name":"La Cantera",
    "qs_pg:name_adm0":"M\u00e9xico",
    "qs_pg:name_adm1":"Nayarit",
    "qs_pg:photos_9r":0,
    "qs_pg:photos_sr":0,
    "qs_pg:pop_sr":0,
    "qs_pg:qs_pg_placetype":"locality",
    "qs_pg:qs_pg_placetype_gp":"Town",
    "qs_pg:woe_adm0":23424900,
    "woe:adm0_id":23424900,
    "woe:name_adm0":"M\u00e9xico",
    "woe:name_adm1":"Nayarit",
    "woe:placetype":"Town",
    "wof:name":"La Cantera",
    "wof:placetype":"locality"
},
  "geometry": {"coordinates":[-104.82192999999999,21.50238],"type":"Point"}
}