{
  "type": "Feature",
  "properties": {
    "gn:admin1_code":"30",
    "gn:admin2_code":"204.0",
    "gn:asciiname":"Ejido el Burro",
    "gn:country_code":"MX",
    "gn:dem":38,
    "gn:feature_class":"P",
    "gn:feature_code":"PPL",
    "gn:name":"Ejido el Burro",
    "gn:population":0,
    "gn:timezone":"America/Mexico_City",
    "iso:country":"MX",
    "name:spa_x_preferred":[
        "Ejido el Burro"
    ],
    "name:und_x_variant":[
        "El Burro"
    ],
    "wof:name":"Ejido el Burro",
    "wof:placetype":"locality"
},
  "geometry": {"coordinates":[-94.22183,18.11171],"type":"Point"}
}