{
  "type": "Feature",
  "properties": {
    "gn:admin1_code":"7.0",
    "gn:admin2_code":"13.0",
    "gn:asciiname":"El Doce",
    "gn:country_code":"MX",
    "gn:dem":182,
    "gn:feature_class":"P",
    "gn:feature_code":"PPL",
    "gn:name":"El Doce",
    "gn:population":0,
    "gn:timezone":"America/Monterrey",
    "iso:country":"MX",
    "name:spa_x_preferred":[
        "El Doce"
    ],
    "wof:name":"El Doce",
    "wof:placetype":"locality"
},
  "geometry": {"coordinates":[-99.99796000000001,27.94733],"type":"Point"}
}