{
  "type": "Feature",
  "properties": {
    "iso:country":"MX",
    "name:spa_x_preferred":[
        "Lomas de Valenciana"
    ],
    "name:unk_x_variant":[
        "Valenciana",
        "Lomas de Valenciana"
    ],
    "qs:gn_adm0_cc":"MX",
    "qs:gn_fcode":"PPL",
    "qs:gn_local":4005270,
    "qs:gn_nam_loc":"Guanajuato, Guanajuato, Guanajuato, MX",
    "qs:gn_namadm1":"11",
    "qs:gn_name":"La Valenciana",
    "qs:local_max":2949,
    "qs:local_sum":12132,
    "qs:localhoods":16,
    "qs:name":"Lomas de Valenciana",
    "qs:name_adm0":"M\u00e9xico",
    "qs:name_adm1":"Guanajuato",
    "qs:name_adm2":"Guanajuato",
    "qs:name_local":"Guanajuato",
    "qs:photo_max":8,
    "qs:photo_sum":12,
    "qs:placetype":"Suburb",
    "qs:quad_count":4,
    "qs:woe_adm0":23424900,
    "qs:woe_adm1":2346274,
    "qs:woe_adm2":12600003,
    "qs:woe_lau":0,
    "qs:woe_local":124432,
    "qs:woe_ver":"7.10.0",
    "wof:lang":[
        "spa"
    ],
    "wof:name":"Lomas de Valenciana",
    "wof:placetype":"neighbourhood"
},
  "geometry": {"coordinates":[-101.259517,21.03516],"type":"Point"}
}