{
  "type": "Feature",
  "properties": {
    "gn:admin1_code":"6.0",
    "gn:admin2_code":"66.0",
    "gn:asciiname":"El Puerto de Jicamorachi",
    "gn:country_code":"MX",
    "gn:dem":1641,
    "gn:feature_class":"P",
    "gn:feature_code":"PPL",
    "gn:name":"El Puerto de Jicam\u00f3rachi",
    "gn:population":0,
    "gn:timezone":"America/Chihuahua",
    "iso:country":"MX",
    "name:spa_x_preferred":[
        "El Puerto de Jicam\u00f3rachi"
    ],
    "wof:name":"El Puerto de Jicamorachi",
    "wof:placetype":"locality"
},
  "geometry": {"coordinates":[-108.33123000000001,27.91845],"type":"Point"}
}