{
  "type": "Feature",
  "properties": {
    "gn:admin1_code":"14.0",
    "gn:asciiname":"Casas Coloradas",
    "gn:country_code":"MX",
    "gn:dem":1802,
    "gn:feature_class":"P",
    "gn:feature_code":"PPL",
    "gn:name":"Casas Coloradas",
    "gn:population":0,
    "gn:timezone":"America/Mexico_City",
    "iso:country":"MX",
    "name:spa_x_preferred":[
        "Casas Coloradas"
    ],
    "wof:name":"Casas Coloradas",
    "wof:placetype":"locality"
},
  "geometry": {"coordinates":[-102.17467000000001,21.17926],"type":"Point"}
}