{
  "type": "Feature",
  "properties": {
    "gn:admin1_code":"14",
    "gn:admin2_code":"125.0",
    "gn:asciiname":"Sacamecate",
    "gn:country_code":"MX",
    "gn:dem":2061,
    "gn:feature_class":"P",
    "gn:feature_code":"PPL",
    "gn:name":"Sacamecate",
    "gn:population":375,
    "gn:timezone":"America/Mexico_City",
    "iso:country":"MX",
    "wof:name":"Sacamecate",
    "wof:placetype":"locality",
    "wof:population":375
},
  "geometry": {"coordinates":[-102.48611,20.74194],"type":"Point"}
}