{
  "type": "Feature",
  "properties": {
    "gn:admin1_code":"5",
    "gn:admin2_code":"52.0",
    "gn:asciiname":"Santa Rita Invernadero",
    "gn:country_code":"MX",
    "gn:dem":342,
    "gn:feature_class":"P",
    "gn:feature_code":"PPL",
    "gn:name":"Santa Rita Invernadero",
    "gn:population":747,
    "gn:timezone":"America/Mexico_City",
    "iso:country":"MX",
    "wof:name":"Santa Rita Invernadero",
    "wof:placetype":"locality",
    "wof:population":747
},
  "geometry": {"coordinates":[-91.52778000000001,16.41361],"type":"Point"}
}