{
  "type": "Feature",
  "properties": {
    "gn:admin1_code":"5",
    "gn:admin2_code":"41.0",
    "gn:asciiname":"San Antonio Chiquinivaltic",
    "gn:country_code":"MX",
    "gn:dem":1501,
    "gn:feature_class":"P",
    "gn:feature_code":"PPL",
    "gn:name":"San Antonio Chiquinivaltic",
    "gn:population":550,
    "gn:timezone":"America/Mexico_City",
    "iso:country":"MX",
    "wof:name":"San Antonio Chiquinivaltic",
    "wof:placetype":"locality",
    "wof:population":550
},
  "geometry": {"coordinates":[-91.92361,16.24028],"type":"Point"}
}