{
  "type": "Feature",
  "properties": {
    "gn:admin1_code":"19.0",
    "gn:admin2_code":"14.0",
    "gn:asciiname":"El Tanquillo",
    "gn:country_code":"MX",
    "gn:dem":1717,
    "gn:feature_class":"P",
    "gn:feature_code":"PPL",
    "gn:name":"El Tanquillo",
    "gn:population":0,
    "gn:timezone":"America/Monterrey",
    "iso:country":"MX",
    "name:spa_x_preferred":[
        "El Tanquillo"
    ],
    "wof:name":"El Tanquillo",
    "wof:placetype":"locality"
},
  "geometry": {"coordinates":[-100.5672,24.29589],"type":"Point"}
}