{
  "type": "Feature",
  "properties": {
    "gn:admin1_code":"5",
    "gn:admin2_code":"96.0",
    "gn:asciiname":"La Cumbre y Cuesta",
    "gn:country_code":"MX",
    "gn:dem":727,
    "gn:feature_class":"P",
    "gn:feature_code":"PPL",
    "gn:name":"La Cumbre y Cuesta",
    "gn:population":246,
    "gn:timezone":"America/Mexico_City",
    "iso:country":"MX",
    "wof:name":"La Cumbre y Cuesta",
    "wof:placetype":"locality",
    "wof:population":246
},
  "geometry": {"coordinates":[-92.55194,17.31806],"type":"Point"}
}