{
  "type": "Feature",
  "properties": {
    "gn:admin1_code":"20",
    "gn:admin2_code":"72.0",
    "gn:asciiname":"Rancho de los Vasquez",
    "gn:country_code":"MX",
    "gn:dem":1525,
    "gn:feature_class":"P",
    "gn:feature_code":"PPL",
    "gn:name":"Rancho de los V\u00e1squez",
    "gn:population":249,
    "gn:timezone":"America/Mexico_City",
    "iso:country":"MX",
    "name:spa_x_preferred":[
        "V\u00e1squez"
    ],
    "wof:name":"Rancho de los Vasquez",
    "wof:placetype":"locality",
    "wof:population":249
},
  "geometry": {"coordinates":[-96.69123999999999,16.72472999999999],"type":"Point"}
}