{
  "type": "Feature",
  "properties": {
    "gn:admin1_code":"6.0",
    "gn:admin2_code":"61.0",
    "gn:asciiname":"El Carreton",
    "gn:country_code":"MX",
    "gn:dem":1572,
    "gn:feature_class":"P",
    "gn:feature_code":"PPL",
    "gn:name":"El Carret\u00f3n",
    "gn:population":0,
    "gn:timezone":"America/Chihuahua",
    "iso:country":"MX",
    "name:spa_x_preferred":[
        "El Carret\u00f3n"
    ],
    "wof:name":"El Carreton",
    "wof:placetype":"locality"
},
  "geometry": {"coordinates":[-105.93431,27.73556],"type":"Point"}
}