{
  "type": "Feature",
  "properties": {
    "gn:admin1_code":"25.0",
    "gn:asciiname":"La Receda",
    "gn:country_code":"MX",
    "gn:dem":10,
    "gn:feature_class":"P",
    "gn:feature_code":"PPL",
    "gn:name":"La Receda",
    "gn:population":0,
    "gn:timezone":"America/Mazatlan",
    "iso:country":"MX",
    "name:spa_x_preferred":[
        "La Receda"
    ],
    "wof:name":"La Receda",
    "wof:placetype":"locality"
},
  "geometry": {"coordinates":[-105.95815,22.9064],"type":"Point"}
}