{
  "type": "Feature",
  "properties": {
    "gn:admin1_code":"6",
    "gn:admin2_code":"27.0",
    "gn:asciiname":"Tucheachi",
    "gn:country_code":"MX",
    "gn:dem":2117,
    "gn:feature_class":"P",
    "gn:feature_code":"PPL",
    "gn:name":"Tucheachi",
    "gn:population":0,
    "gn:timezone":"America/Chihuahua",
    "iso:country":"MX",
    "name:spa_x_preferred":[
        "Tucheachi"
    ],
    "wof:name":"Tucheachi",
    "wof:placetype":"locality"
},
  "geometry": {"coordinates":[-107.12085,27.30702],"type":"Point"}
}