{
  "type": "Feature",
  "properties": {
    "gn:admin1_code":"21",
    "gn:admin2_code":"164.0",
    "gn:asciiname":"Vincente Guerrero",
    "gn:country_code":"MX",
    "gn:dem":2299,
    "gn:feature_class":"P",
    "gn:feature_code":"PPL",
    "gn:name":"Vincente Guerrero",
    "gn:population":0,
    "gn:timezone":"America/Mexico_City",
    "iso:country":"MX",
    "name:spa_x_preferred":[
        "Vincente Guerrero"
    ],
    "name:und_x_variant":[
        "Vicente Guerrero"
    ],
    "wof:name":"Vincente Guerrero",
    "wof:placetype":"locality"
},
  "geometry": {"coordinates":[-97.81719,19.05865],"type":"Point"}
}