{
  "type": "Feature",
  "properties": {
    "gn:admin1_code":"5",
    "gn:admin2_code":"112.0",
    "gn:asciiname":"Tzunjok",
    "gn:country_code":"MX",
    "gn:dem":1226,
    "gn:feature_class":"P",
    "gn:feature_code":"PPL",
    "gn:name":"Tzunjok",
    "gn:population":549,
    "gn:timezone":"America/Mexico_City",
    "iso:country":"MX",
    "wof:name":"Tzunjok",
    "wof:placetype":"locality",
    "wof:population":549
},
  "geometry": {"coordinates":[-92.3866,16.94756],"type":"Point"}
}