{
  "type": "Feature",
  "properties": {
    "gn:admin1_code":"24",
    "gn:admin2_code":"32.0",
    "gn:asciiname":"El Guaricho",
    "gn:country_code":"MX",
    "gn:dem":1989,
    "gn:feature_class":"P",
    "gn:feature_code":"PPL",
    "gn:name":"El Guaricho",
    "gn:population":59,
    "gn:timezone":"America/Mexico_City",
    "iso:country":"MX",
    "wof:name":"El Guaricho",
    "wof:placetype":"locality",
    "wof:population":59
},
  "geometry": {"coordinates":[-100.30361000000001,21.86444],"type":"Point"}
}