{
  "type": "Feature",
  "properties": {
    "gn:admin1_code":"6",
    "gn:admin2_code":"36.0",
    "gn:asciiname":"Gallineros",
    "gn:country_code":"MX",
    "gn:dem":1225,
    "gn:feature_class":"P",
    "gn:feature_code":"PPL",
    "gn:name":"Gallineros",
    "gn:population":0,
    "gn:timezone":"America/Chihuahua",
    "iso:country":"MX",
    "name:spa_x_preferred":[
        "Gallineros"
    ],
    "wof:name":"Gallineros",
    "wof:placetype":"locality"
},
  "geometry": {"coordinates":[-104.17346999999999,26.89982],"type":"Point"}
}