{
  "type": "Feature",
  "properties": {
    "gn:admin1_code":"15",
    "gn:admin2_code":"14.0",
    "gn:asciiname":"San Pedro del Rosal",
    "gn:country_code":"MX",
    "gn:dem":2567,
    "gn:feature_class":"P",
    "gn:feature_code":"PPL",
    "gn:name":"San Pedro del Rosal",
    "gn:population":0,
    "gn:timezone":"America/Mexico_City",
    "iso:country":"MX",
    "name:und_x_variant":[
        "San Pedro"
    ],
    "wof:name":"San Pedro del Rosal",
    "wof:placetype":"locality"
},
  "geometry": {"coordinates":[-99.81269,19.77774],"type":"Point"}
}