{
  "type": "Feature",
  "properties": {
    "gn:admin1_code":"14.0",
    "gn:admin2_code":"85.0",
    "gn:asciiname":"Las Latillas",
    "gn:country_code":"MX",
    "gn:dem":1205,
    "gn:feature_class":"P",
    "gn:feature_code":"PPL",
    "gn:name":"Las Latillas",
    "gn:population":0,
    "gn:timezone":"America/Mexico_City",
    "iso:country":"MX",
    "name:spa_x_preferred":[
        "Las Latillas"
    ],
    "wof:name":"Las Latillas",
    "wof:placetype":"locality"
},
  "geometry": {"coordinates":[-103.26261,19.70073],"type":"Point"}
}