{
  "type": "Feature",
  "properties": {
    "gn:admin1_code":"30",
    "gn:admin2_code":"125.0",
    "gn:asciiname":"San Antonio",
    "gn:country_code":"MX",
    "gn:dem":264,
    "gn:feature_class":"P",
    "gn:feature_code":"PPL",
    "gn:name":"San Antonio",
    "gn:population":92,
    "gn:timezone":"America/Mexico_City",
    "iso:country":"MX",
    "wof:name":"San Antonio",
    "wof:placetype":"locality",
    "wof:population":92
},
  "geometry": {"coordinates":[-96.56610999999999,18.95444],"type":"Point"}
}