{
  "type": "Feature",
  "properties": {
    "gn:admin1_code":"23",
    "gn:admin2_code":"4.0",
    "gn:asciiname":"La Flor",
    "gn:country_code":"MX",
    "gn:dem":27,
    "gn:feature_class":"P",
    "gn:feature_code":"PPL",
    "gn:name":"La Flor",
    "gn:population":6,
    "gn:timezone":"America/Cancun",
    "iso:country":"MX",
    "name:fra_x_preferred":[
        "La flor"
    ],
    "wof:name":"La Flor",
    "wof:placetype":"locality",
    "wof:population":6
},
  "geometry": {"coordinates":[-88.46819000000001,18.54085],"type":"Point"}
}