{
  "type": "Feature",
  "properties": {
    "gn:admin1_code":"23",
    "gn:admin2_code":"4.0",
    "gn:asciiname":"Esteban Baca Calderon",
    "gn:country_code":"MX",
    "gn:dem":64,
    "gn:feature_class":"P",
    "gn:feature_code":"PPL",
    "gn:name":"Esteban Baca Calder\u00f3n",
    "gn:population":222,
    "gn:timezone":"America/Cancun",
    "iso:country":"MX",
    "wof:name":"Esteban Baca Calderon",
    "wof:placetype":"locality",
    "wof:population":222
},
  "geometry": {"coordinates":[-88.82249,18.00962],"type":"Point"}
}