{
  "type": "Feature",
  "properties": {
    "gn:admin1_code":"30.0",
    "gn:admin2_code":"124.0",
    "gn:asciiname":"Arroyo Verde",
    "gn:country_code":"MX",
    "gn:dem":24,
    "gn:feature_class":"P",
    "gn:feature_code":"PPL",
    "gn:name":"Arroyo Verde",
    "gn:population":262,
    "gn:timezone":"America/Mexico_City",
    "iso:country":"MX",
    "name:spa_x_preferred":[
        "Arroyo Verde"
    ],
    "wof:name":"Arroyo Verde",
    "wof:placetype":"locality",
    "wof:population":262
},
  "geometry": {"coordinates":[-97.22011000000001,20.59569],"type":"Point"}
}