{
  "type": "Feature",
  "properties": {
    "gn:admin1_code":"12.0",
    "gn:asciiname":"El Oro Verde",
    "gn:country_code":"MX",
    "gn:dem":632,
    "gn:feature_class":"P",
    "gn:feature_code":"PPL",
    "gn:name":"El Oro Verde",
    "gn:population":0,
    "gn:timezone":"America/Mexico_City",
    "iso:country":"MX",
    "name:spa_x_preferred":[
        "El Oro Verde"
    ],
    "wof:name":"El Oro Verde",
    "wof:placetype":"locality"
},
  "geometry": {"coordinates":[-98.45735999999999,16.76365],"type":"Point"}
}