{
  "type": "Feature",
  "properties": {
    "gn:admin1_code":"16",
    "gn:admin2_code":"92.0",
    "gn:asciiname":"Puerto el Capulin",
    "gn:country_code":"MX",
    "gn:dem":1191,
    "gn:feature_class":"P",
    "gn:feature_code":"PPL",
    "gn:name":"Puerto el Capul\u00edn",
    "gn:population":0,
    "gn:timezone":"America/Mexico_City",
    "iso:country":"MX",
    "name:spa_x_preferred":[
        "Puerto el Capul\u00edn"
    ],
    "wof:name":"Puerto el Capulin",
    "wof:placetype":"locality"
},
  "geometry": {"coordinates":[-101.02332,19.18244],"type":"Point"}
}