{
  "type": "Feature",
  "properties": {
    "gn:admin1_code":"5.0",
    "gn:admin2_code":"83.0",
    "gn:asciiname":"El Cedral",
    "gn:country_code":"MX",
    "gn:dem":538,
    "gn:feature_class":"P",
    "gn:feature_code":"PPL",
    "gn:name":"El Cedral",
    "gn:population":0,
    "gn:timezone":"America/Mexico_City",
    "iso:country":"MX",
    "name:spa_x_preferred":[
        "El Cedral"
    ],
    "wof:name":"El Cedral",
    "wof:placetype":"locality"
},
  "geometry": {"coordinates":[-92.2201,15.93194],"type":"Point"}
}