{
  "type": "Feature",
  "properties": {
    "gn:admin1_code":"32",
    "gn:admin2_code":"39.0",
    "gn:asciiname":"Pastelera",
    "gn:country_code":"MX",
    "gn:dem":1914,
    "gn:feature_class":"P",
    "gn:feature_code":"PPL",
    "gn:name":"Pastelera",
    "gn:population":0,
    "gn:timezone":"America/Mexico_City",
    "iso:country":"MX",
    "name:und_x_variant":[
        "Hacienda Pastelera",
        "Pastelera"
    ],
    "wof:name":"Pastelera",
    "wof:placetype":"locality"
},
  "geometry": {"coordinates":[-103.09699999999999,23.7442],"type":"Point"}
}