{
  "type": "Feature",
  "properties": {
    "gn:admin1_code":"16",
    "gn:admin2_code":"10.0",
    "gn:asciiname":"Las Pajitas",
    "gn:country_code":"MX",
    "gn:dem":891,
    "gn:feature_class":"P",
    "gn:feature_code":"PPL",
    "gn:name":"Las Pajitas",
    "gn:population":0,
    "gn:timezone":"America/Mexico_City",
    "iso:country":"MX",
    "wof:name":"Las Pajitas",
    "wof:placetype":"locality"
},
  "geometry": {"coordinates":[-102.31667,18.33333],"type":"Point"}
}