{
  "type": "Feature",
  "properties": {
    "gn:admin1_code":"7",
    "gn:admin2_code":"2",
    "gn:asciiname":"La Espiga",
    "gn:country_code":"MX",
    "gn:dem":302,
    "gn:feature_class":"P",
    "gn:feature_code":"PPL",
    "gn:name":"La Espiga",
    "gn:population":14,
    "gn:timezone":"America/Matamoros",
    "iso:country":"MX",
    "wof:name":"La Espiga",
    "wof:placetype":"locality",
    "wof:population":14
},
  "geometry": {"coordinates":[-100.90787,29.26051],"type":"Point"}
}