{
  "type": "Feature",
  "properties": {
    "gn:admin1_code":"14",
    "gn:admin2_code":"61",
    "gn:asciiname":"Rancho los Encinos",
    "gn:country_code":"MX",
    "gn:dem":1904,
    "gn:feature_class":"P",
    "gn:feature_code":"PPL",
    "gn:name":"Rancho los Encinos",
    "gn:population":26,
    "gn:timezone":"America/Mexico_City",
    "iso:country":"MX",
    "wof:name":"Rancho los Encinos",
    "wof:placetype":"locality",
    "wof:population":26
},
  "geometry": {"coordinates":[-104.10639,22.20694],"type":"Point"}
}