{
  "type": "Feature",
  "properties": {
    "gn:admin1_code":"16",
    "gn:admin2_code":"81",
    "gn:asciiname":"La Colmena",
    "gn:country_code":"MX",
    "gn:dem":917,
    "gn:feature_class":"P",
    "gn:feature_code":"PPL",
    "gn:name":"La Colmena",
    "gn:population":21,
    "gn:timezone":"America/Mexico_City",
    "iso:country":"MX",
    "name:ceb_x_preferred":[
        "La Colmena"
    ],
    "name:fra_x_preferred":[
        "La Colmena"
    ],
    "name:glg_x_preferred":[
        "La colmena"
    ],
    "name:nld_x_preferred":[
        "La colmena"
    ],
    "name:spa_x_preferred":[
        "La colmena"
    ],
    "name:swe_x_preferred":[
        "La Colmena"
    ],
    "wof:name":"La Colmena",
    "wof:placetype":"locality",
    "wof:population":21
},
  "geometry": {"coordinates":[-100.43917,19.11833],"type":"Point"}
}