{
  "type": "Feature",
  "properties": {
    "gn:admin1_code":"11",
    "gn:admin2_code":"18.0",
    "gn:asciiname":"La Rana",
    "gn:cc2":"MX",
    "gn:country_code":"MX",
    "gn:dem":1731,
    "gn:feature_class":"P",
    "gn:feature_code":"PPL",
    "gn:name":"La Rana",
    "gn:population":4,
    "gn:timezone":"America/Mexico_City",
    "iso:country":"MX",
    "name:und_x_variant":[
        "Zanja",
        "San Isidro",
        "La Zanja"
    ],
    "wof:name":"La Rana",
    "wof:placetype":"locality",
    "wof:population":4
},
  "geometry": {"coordinates":[-101.03806,20.31806],"type":"Point"}
}