{
  "type": "Feature",
  "properties": {
    "gn:admin1_code":"10",
    "gn:asciiname":"Rancho El Compas",
    "gn:country_code":"MX",
    "gn:dem":1119,
    "gn:feature_class":"P",
    "gn:feature_code":"PPL",
    "gn:name":"Rancho El Comp\u00e1s",
    "gn:population":0,
    "gn:timezone":"America/Monterrey",
    "iso:country":"MX",
    "wof:name":"Rancho El Compas",
    "wof:placetype":"locality"
},
  "geometry": {"coordinates":[-103.36667,25.66667],"type":"Point"}
}