{
  "type": "Feature",
  "properties": {
    "gn:admin1_code":"19",
    "gn:admin2_code":"22.0",
    "gn:asciiname":"San Rafael del Llano",
    "gn:country_code":"MX",
    "gn:dem":344,
    "gn:feature_class":"P",
    "gn:feature_code":"PPL",
    "gn:name":"San Rafael del Llano",
    "gn:population":0,
    "gn:timezone":"America/Monterrey",
    "iso:country":"MX",
    "name:spa_x_preferred":[
        "San Rafael del Llano"
    ],
    "name:spa_x_variant":[
        "Macu\u00f1a"
    ],
    "wof:name":"San Rafael del Llano",
    "wof:placetype":"locality"
},
  "geometry": {"coordinates":[-99.71972,25.2186],"type":"Point"}
}