{
  "type": "Feature",
  "properties": {
    "gn:admin1_code":"28",
    "gn:admin2_code":"22",
    "gn:asciiname":"Las Delicias",
    "gn:country_code":"MX",
    "gn:dem":14,
    "gn:feature_class":"P",
    "gn:feature_code":"PPL",
    "gn:name":"Las Delicias",
    "gn:population":12,
    "gn:timezone":"America/Matamoros",
    "iso:country":"MX",
    "wof:name":"Las Delicias",
    "wof:placetype":"locality",
    "wof:population":12
},
  "geometry": {"coordinates":[-97.71832999999999,25.96694],"type":"Point"}
}