{
  "type": "Feature",
  "properties": {
    "gn:admin1_code":"32",
    "gn:admin2_code":"31.0",
    "gn:asciiname":"San Ignacio",
    "gn:country_code":"MX",
    "gn:dem":1835,
    "gn:feature_class":"P",
    "gn:feature_code":"PPL",
    "gn:name":"San Ignacio",
    "gn:population":6,
    "gn:timezone":"America/Mexico_City",
    "iso:country":"MX",
    "wof:name":"San Ignacio",
    "wof:placetype":"locality",
    "wof:population":6
},
  "geometry": {"coordinates":[-103.54917,22.54417],"type":"Point"}
}