{
  "type": "Feature",
  "properties": {
    "gn:admin1_code":"14",
    "gn:admin2_code":"93",
    "gn:asciiname":"Agua Escondida",
    "gn:country_code":"MX",
    "gn:dem":1843,
    "gn:feature_class":"P",
    "gn:feature_code":"PPL",
    "gn:name":"Agua Escondida",
    "gn:population":16,
    "gn:timezone":"America/Mexico_City",
    "iso:country":"MX",
    "wof:name":"Agua Escondida",
    "wof:placetype":"locality",
    "wof:population":16
},
  "geometry": {"coordinates":[-102.76694000000001,20.63417],"type":"Point"}
}