{
  "type": "Feature",
  "properties": {
    "gn:admin1_code":"16",
    "gn:admin2_code":"52.0",
    "gn:asciiname":"Barranca Verde",
    "gn:country_code":"MX",
    "gn:dem":149,
    "gn:feature_class":"P",
    "gn:feature_code":"PPL",
    "gn:name":"Barranca Verde",
    "gn:population":0,
    "gn:timezone":"America/Mexico_City",
    "iso:country":"MX",
    "name:spa_x_preferred":[
        "Barranca Verde"
    ],
    "wof:name":"Barranca Verde",
    "wof:placetype":"locality"
},
  "geometry": {"coordinates":[-102.30898999999999,18.16885],"type":"Point"}
}