{
  "type": "Feature",
  "properties": {
    "gn:admin1_code":"4",
    "gn:admin2_code":"11.0",
    "gn:asciiname":"Vuelta del Pital",
    "gn:country_code":"MX",
    "gn:dem":19,
    "gn:feature_class":"P",
    "gn:feature_code":"PPL",
    "gn:name":"Vuelta del Pital",
    "gn:population":0,
    "gn:timezone":"America/Merida",
    "iso:country":"MX",
    "name:spa_x_preferred":[
        "Vuelta del Pital"
    ],
    "wof:name":"Vuelta del Pital",
    "wof:placetype":"locality"
},
  "geometry": {"coordinates":[-91.21822,18.16964],"type":"Point"}
}