{
  "type": "Feature",
  "properties": {
    "gn:admin1_code":"6",
    "gn:admin2_code":"27",
    "gn:asciiname":"Mesa del Aguaje",
    "gn:country_code":"MX",
    "gn:dem":2400,
    "gn:feature_class":"P",
    "gn:feature_code":"PPL",
    "gn:name":"Mesa del Aguaje",
    "gn:population":17,
    "gn:timezone":"America/Chihuahua",
    "iso:country":"MX",
    "wof:name":"Mesa del Aguaje",
    "wof:placetype":"locality",
    "wof:population":17
},
  "geometry": {"coordinates":[-107.01600000000001,26.98327],"type":"Point"}
}