{
  "type": "Feature",
  "properties": {
    "gn:admin1_code":"5",
    "gn:admin2_code":"76.0",
    "gn:asciiname":"Juan Gonzalez Esponda",
    "gn:country_code":"MX",
    "gn:dem":301,
    "gn:feature_class":"P",
    "gn:feature_code":"PPL",
    "gn:name":"Juan Gonz\u00e1lez Esponda",
    "gn:population":66,
    "gn:timezone":"America/Mexico_City",
    "iso:country":"MX",
    "name:und_x_variant":[
        "Juan Gonz\u00e1lez Esponda"
    ],
    "wof:name":"Juan Gonzalez Esponda",
    "wof:placetype":"locality",
    "wof:population":66
},
  "geometry": {"coordinates":[-92.55056,17.2775],"type":"Point"}
}