{
  "type": "Feature",
  "properties": {
    "gn:admin1_code":"32",
    "gn:admin2_code":"42.0",
    "gn:asciiname":"Miguel Chiquito",
    "gn:country_code":"MX",
    "gn:dem":2374,
    "gn:feature_class":"P",
    "gn:feature_code":"PPL",
    "gn:name":"Miguel Chiquito",
    "gn:population":0,
    "gn:timezone":"America/Mexico_City",
    "iso:country":"MX",
    "name:spa_x_preferred":[
        "Miguel Chiquito"
    ],
    "wof:name":"Miguel Chiquito",
    "wof:placetype":"locality"
},
  "geometry": {"coordinates":[-103.42216999999999,23.71031],"type":"Point"}
}