{
  "type": "Feature",
  "properties": {
    "gn:admin1_code":"10.0",
    "gn:admin2_code":"5.0",
    "gn:asciiname":"Empinos",
    "gn:country_code":"MX",
    "gn:dem":2209,
    "gn:feature_class":"P",
    "gn:feature_code":"PPL",
    "gn:name":"Empinos",
    "gn:population":0,
    "gn:timezone":"America/Monterrey",
    "iso:country":"MX",
    "wof:name":"Empinos",
    "wof:placetype":"locality"
},
  "geometry": {"coordinates":[-104.66667,23.83333],"type":"Point"}
}