{
  "type": "Feature",
  "properties": {
    "gn:admin1_code":"2",
    "gn:admin2_code":"4.0",
    "gn:asciiname":"Rancho Gonzalez",
    "gn:country_code":"MX",
    "gn:dem":266,
    "gn:feature_class":"P",
    "gn:feature_code":"PPL",
    "gn:name":"Rancho Gonz\u00e1lez",
    "gn:population":5,
    "gn:timezone":"America/Tijuana",
    "iso:country":"MX",
    "name:und_x_variant":[
        "Rancho Gonz\u00e1lez"
    ],
    "wof:name":"Rancho Gonzalez",
    "wof:placetype":"locality",
    "wof:population":5
},
  "geometry": {"coordinates":[-117.00472000000001,32.45611],"type":"Point"}
}