{
  "type": "Feature",
  "properties": {
    "gn:admin1_code":"30",
    "gn:admin2_code":"70.0",
    "gn:asciiname":"Taxcocuayo",
    "gn:country_code":"MX",
    "gn:dem":12,
    "gn:feature_class":"P",
    "gn:feature_code":"PPL",
    "gn:name":"Taxcocuayo",
    "gn:population":56,
    "gn:timezone":"America/Mexico_City",
    "iso:country":"MX",
    "wof:name":"Taxcocuayo",
    "wof:placetype":"locality",
    "wof:population":56
},
  "geometry": {"coordinates":[-94.66611,17.73528],"type":"Point"}
}