{
  "type": "Feature",
  "properties": {
    "gn:admin1_code":"19",
    "gn:admin2_code":"34",
    "gn:asciiname":"San Angel",
    "gn:country_code":"MX",
    "gn:dem":400,
    "gn:feature_class":"P",
    "gn:feature_code":"PPL",
    "gn:name":"San \u00c1ngel",
    "gn:population":12,
    "gn:timezone":"America/Monterrey",
    "iso:country":"MX",
    "name:und_x_variant":[
        "San \u00c1ngel"
    ],
    "wof:name":"San Angel",
    "wof:placetype":"locality",
    "wof:population":12
},
  "geometry": {"coordinates":[-100.01389,25.86028],"type":"Point"}
}