{
  "type": "Feature",
  "properties": {
    "gn:admin1_code":"2",
    "gn:admin2_code":"2",
    "gn:asciiname":"Santa Veronica (Colonia Silva)",
    "gn:country_code":"MX",
    "gn:dem":18,
    "gn:feature_class":"P",
    "gn:feature_code":"PPL",
    "gn:name":"Santa Ver\u00f3nica (Colonia Silva)",
    "gn:population":14,
    "gn:timezone":"America/Tijuana",
    "iso:country":"MX",
    "name:und_x_variant":[
        "Santa Ver\u00f3nica (Colonia Silva)"
    ],
    "wof:name":"Santa Veronica (Colonia Silva)",
    "wof:placetype":"locality",
    "wof:population":14
},
  "geometry": {"coordinates":[-115.065,32.40056],"type":"Point"}
}