{
  "type": "Feature",
  "properties": {
    "gn:admin1_code":"10",
    "gn:admin2_code":"7.0",
    "gn:asciiname":"El Vuelo del Aguila",
    "gn:country_code":"MX",
    "gn:dem":1120,
    "gn:feature_class":"P",
    "gn:feature_code":"PPL",
    "gn:name":"El Vuelo del \u00c1guila",
    "gn:population":4,
    "gn:timezone":"America/Monterrey",
    "iso:country":"MX",
    "name:und_x_variant":[
        "El Vuelo del \u00c1guila"
    ],
    "wof:name":"El Vuelo del Aguila",
    "wof:placetype":"locality",
    "wof:population":4
},
  "geometry": {"coordinates":[-103.43868000000001,25.68278],"type":"Point"}
}