{
  "type": "Feature",
  "properties": {
    "gn:admin1_code":"7.0",
    "gn:admin2_code":"15.0",
    "gn:asciiname":"Los Ahogaditos",
    "gn:country_code":"MX",
    "gn:dem":269,
    "gn:feature_class":"P",
    "gn:feature_code":"PPL",
    "gn:name":"Los Ahogaditos",
    "gn:population":0,
    "gn:timezone":"America/Monterrey",
    "iso:country":"MX",
    "name:spa_x_preferred":[
        "Los Ahogaditos"
    ],
    "wof:name":"Los Ahogaditos",
    "wof:placetype":"locality"
},
  "geometry": {"coordinates":[-100.72286,27.56666],"type":"Point"}
}