{
  "type": "Feature",
  "properties": {
    "gn:admin1_code":"31.0",
    "gn:asciiname":"El Nino de Atocha",
    "gn:country_code":"MX",
    "gn:dem":20,
    "gn:feature_class":"P",
    "gn:feature_code":"PPL",
    "gn:name":"El Ni\u00f1o de Atocha",
    "gn:population":0,
    "gn:timezone":"America/Merida",
    "iso:country":"MX",
    "name:spa_x_preferred":[
        "El Ni\u00f1o de Atocha"
    ],
    "wof:name":"El Nino de Atocha",
    "wof:placetype":"locality"
},
  "geometry": {"coordinates":[-88.28666,21.15053],"type":"Point"}
}