{
  "type": "Feature",
  "properties": {
    "gn:admin1_code":"7.0",
    "gn:admin2_code":"28.0",
    "gn:asciiname":"Elote",
    "gn:cc2":"MX",
    "gn:country_code":"MX",
    "gn:dem":390,
    "gn:feature_class":"P",
    "gn:feature_code":"PPL",
    "gn:name":"Elote",
    "gn:population":0,
    "gn:timezone":"America/Monterrey",
    "iso:country":"MX",
    "name:grn_x_preferred":[
        "Avatiky"
    ],
    "name:lat_x_preferred":[
        "Elote"
    ],
    "name:spa_x_preferred":[
        "Elote"
    ],
    "name:und_x_variant":[
        "Helotes",
        "Elote"
    ],
    "wof:name":"Elote",
    "wof:placetype":"locality"
},
  "geometry": {"coordinates":[-101.16667,28.03333],"type":"Point"}
}