{
  "type": "Feature",
  "properties": {
    "gn:admin1_code":"1",
    "gn:admin2_code":"5.0",
    "gn:asciiname":"Villas de Guadalupe (La Malobra)",
    "gn:country_code":"MX",
    "gn:dem":1880,
    "gn:feature_class":"P",
    "gn:feature_code":"PPL",
    "gn:name":"Villas de Guadalupe (La Malobra)",
    "gn:population":495,
    "gn:timezone":"America/Mexico_City",
    "iso:country":"MX",
    "wof:name":"Villas de Guadalupe (La Malobra)",
    "wof:placetype":"locality",
    "wof:population":495
},
  "geometry": {"coordinates":[-102.32194,22.01667],"type":"Point"}
}