{
  "type": "Feature",
  "properties": {
    "gn:admin1_code":"30",
    "gn:admin2_code":"77.0",
    "gn:asciiname":"Jose Antonio Pitol",
    "gn:country_code":"MX",
    "gn:dem":87,
    "gn:feature_class":"P",
    "gn:feature_code":"PPL",
    "gn:name":"Jos\u00e9 Antonio Pitol",
    "gn:population":6,
    "gn:timezone":"America/Mexico_City",
    "iso:country":"MX",
    "name:und_x_variant":[
        "Jos\u00e9 Antonio Pitol"
    ],
    "wof:name":"Jose Antonio Pitol",
    "wof:placetype":"locality",
    "wof:population":6
},
  "geometry": {"coordinates":[-95.65083,17.93778],"type":"Point"}
}