{
  "type": "Feature",
  "properties": {
    "gn:admin1_code":"4.0",
    "gn:asciiname":"Bun y las Guillerminas",
    "gn:country_code":"MX",
    "gn:dem":28,
    "gn:feature_class":"P",
    "gn:feature_code":"PPL",
    "gn:name":"Bun y las Guillerminas",
    "gn:population":0,
    "gn:timezone":"America/Merida",
    "iso:country":"MX",
    "name:spa_x_preferred":[
        "Bun y las Guillerminas"
    ],
    "name:spa_x_variant":[
        "Las Guillerminas"
    ],
    "wof:name":"Bun y las Guillerminas",
    "wof:placetype":"locality"
},
  "geometry": {"coordinates":[-91.35996,18.1348],"type":"Point"}
}