{
  "type": "Feature",
  "properties": {
    "gn:admin1_code":"6",
    "gn:admin2_code":"21.0",
    "gn:asciiname":"La Fe",
    "gn:country_code":"MX",
    "gn:dem":1192,
    "gn:feature_class":"P",
    "gn:feature_code":"PPL",
    "gn:name":"La Fe",
    "gn:population":6,
    "gn:timezone":"America/Chihuahua",
    "iso:country":"MX",
    "wof:name":"La Fe",
    "wof:placetype":"locality",
    "wof:population":6
},
  "geometry": {"coordinates":[-105.3638,28.13487000000001],"type":"Point"}
}