{
  "type": "Feature",
  "properties": {
    "gn:admin1_code":"5",
    "gn:admin2_code":"54.0",
    "gn:asciiname":"Los Claveles",
    "gn:country_code":"MX",
    "gn:dem":10,
    "gn:feature_class":"P",
    "gn:feature_code":"PPL",
    "gn:name":"Los Claveles",
    "gn:population":7,
    "gn:timezone":"America/Mexico_City",
    "iso:country":"MX",
    "wof:name":"Los Claveles",
    "wof:placetype":"locality",
    "wof:population":7
},
  "geometry": {"coordinates":[-92.50944,14.89083],"type":"Point"}
}