{
  "type": "Feature",
  "properties": {
    "gn:admin1_code":"6",
    "gn:admin2_code":"35.0",
    "gn:asciiname":"San Pedro de Ojitos",
    "gn:country_code":"MX",
    "gn:dem":1557,
    "gn:feature_class":"P",
    "gn:feature_code":"PPL",
    "gn:name":"San Pedro de Ojitos",
    "gn:population":0,
    "gn:timezone":"America/Chihuahua",
    "iso:country":"MX",
    "name:spa_x_preferred":[
        "San Pedro de Ojitos"
    ],
    "name:und_x_variant":[
        "Hacienda San Pedro",
        "San Pedro"
    ],
    "wof:name":"San Pedro de Ojitos",
    "wof:placetype":"locality"
},
  "geometry": {"coordinates":[-108.54313999999999,30.6992],"type":"Point"}
}