{
  "type": "Feature",
  "properties": {
    "gn:admin1_code":"31",
    "gn:admin2_code":"29.0",
    "gn:asciiname":"Tres Reyes",
    "gn:country_code":"MX",
    "gn:dem":4,
    "gn:feature_class":"P",
    "gn:feature_code":"PPL",
    "gn:name":"Tres Reyes",
    "gn:population":0,
    "gn:timezone":"America/Merida",
    "iso:country":"MX",
    "name:spa_x_preferred":[
        "Tres Reyes"
    ],
    "wof:name":"Tres Reyes",
    "wof:placetype":"locality"
},
  "geometry": {"coordinates":[-88.73345,21.35843],"type":"Point"}
}