{
  "type": "Feature",
  "properties": {
    "gn:admin1_code":"24.0",
    "gn:asciiname":"La Carcacha",
    "gn:country_code":"MX",
    "gn:dem":987,
    "gn:feature_class":"P",
    "gn:feature_code":"PPL",
    "gn:name":"La Carcacha",
    "gn:population":0,
    "gn:timezone":"America/Mexico_City",
    "iso:country":"MX",
    "name:por_x_preferred":[
        "La Caracha"
    ],
    "name:spa_x_preferred":[
        "La Carcacha"
    ],
    "wof:name":"La Carcacha",
    "wof:placetype":"locality"
},
  "geometry": {"coordinates":[-99.95173,21.92776],"type":"Point"}
}