{
  "type": "Feature",
  "properties": {
    "gn:admin1_code":"16",
    "gn:admin2_code":"20.0",
    "gn:asciiname":"Epifanio C. Perez (San Miguel)",
    "gn:country_code":"MX",
    "gn:dem":1840,
    "gn:feature_class":"P",
    "gn:feature_code":"PPL",
    "gn:name":"Epifanio C. P\u00e9rez (San Miguel)",
    "gn:population":253,
    "gn:timezone":"America/Mexico_City",
    "iso:country":"MX",
    "name:und_x_variant":[
        "Epifanio C. P\u00e9rez (San Miguel)"
    ],
    "wof:name":"Epifanio C. Perez (San Miguel)",
    "wof:placetype":"locality",
    "wof:population":253
},
  "geometry": {"coordinates":[-101.15194,19.99028],"type":"Point"}
}