{
  "type": "Feature",
  "properties": {
    "gn:admin1_code":"15",
    "gn:admin2_code":"3.0",
    "gn:asciiname":"Gunyo Oriente",
    "gn:country_code":"MX",
    "gn:dem":2461,
    "gn:feature_class":"P",
    "gn:feature_code":"PPL",
    "gn:name":"Gunyo Oriente",
    "gn:population":602,
    "gn:timezone":"America/Mexico_City",
    "iso:country":"MX",
    "wof:name":"Gunyo Oriente",
    "wof:placetype":"locality",
    "wof:population":602
},
  "geometry": {"coordinates":[-99.81528,20.1175],"type":"Point"}
}