{
  "type": "Feature",
  "properties": {
    "gn:admin1_code":"2",
    "gn:admin2_code":"2",
    "gn:asciiname":"Familia Solorio (Colonia Chausse)",
    "gn:country_code":"MX",
    "gn:dem":19,
    "gn:feature_class":"P",
    "gn:feature_code":"PPL",
    "gn:name":"Familia Solorio (Colonia Chauss\u00e9)",
    "gn:population":26,
    "gn:timezone":"America/Tijuana",
    "iso:country":"MX",
    "name:und_x_variant":[
        "Familia Solorio (Colonia Chauss\u00e9)"
    ],
    "wof:name":"Familia Solorio (Colonia Chausse)",
    "wof:placetype":"locality",
    "wof:population":26
},
  "geometry": {"coordinates":[-115.02417,32.29528],"type":"Point"}
}