{
  "type": "Feature",
  "properties": {
    "gn:admin1_code":"6",
    "gn:admin2_code":"49.0",
    "gn:asciiname":"Arroyo Blanco",
    "gn:country_code":"MX",
    "gn:dem":1878,
    "gn:feature_class":"P",
    "gn:feature_code":"PPL",
    "gn:name":"Arroyo Blanco",
    "gn:population":4,
    "gn:timezone":"America/Chihuahua",
    "iso:country":"MX",
    "wof:name":"Arroyo Blanco",
    "wof:placetype":"locality",
    "wof:population":4
},
  "geometry": {"coordinates":[-106.79241,27.24242000000001],"type":"Point"}
}