{
  "type": "Feature",
  "properties": {
    "gn:admin1_code":"15",
    "gn:admin2_code":"51.0",
    "gn:asciiname":"Barranca Grande",
    "gn:country_code":"MX",
    "gn:dem":2709,
    "gn:feature_class":"P",
    "gn:feature_code":"PPL",
    "gn:name":"Barranca Grande",
    "gn:population":904,
    "gn:timezone":"America/Mexico_City",
    "iso:country":"MX",
    "wof:name":"Barranca Grande",
    "wof:placetype":"locality",
    "wof:population":904
},
  "geometry": {"coordinates":[-99.47611000000001,19.38528],"type":"Point"}
}