{
  "type": "Feature",
  "properties": {
    "gn:admin1_code":"1.0",
    "gn:admin2_code":"9.0",
    "gn:asciiname":"Los Amapolas",
    "gn:country_code":"MX",
    "gn:dem":2172,
    "gn:feature_class":"P",
    "gn:feature_code":"PPL",
    "gn:name":"Los Amapolas",
    "gn:population":0,
    "gn:timezone":"America/Mexico_City",
    "iso:country":"MX",
    "wof:name":"Los Amapolas",
    "wof:placetype":"locality"
},
  "geometry": {"coordinates":[-102.14167,22.175],"type":"Point"}
}