{
  "type": "Feature",
  "properties": {
    "gn:admin1_code":"14.0",
    "gn:asciiname":"El Ocotillo",
    "gn:country_code":"MX",
    "gn:dem":511,
    "gn:feature_class":"P",
    "gn:feature_code":"PPL",
    "gn:name":"El Ocotillo",
    "gn:population":0,
    "gn:timezone":"America/Mexico_City",
    "iso:country":"MX",
    "name:spa_x_preferred":[
        "El Ocotillo"
    ],
    "wof:name":"El Ocotillo",
    "wof:placetype":"locality"
},
  "geometry": {"coordinates":[-103.31469,18.94981],"type":"Point"}
}