{
  "type": "Feature",
  "properties": {
    "gn:admin1_code":"5",
    "gn:admin2_code":"109",
    "gn:asciiname":"San Fidencio Wayaquil",
    "gn:country_code":"MX",
    "gn:dem":980,
    "gn:feature_class":"P",
    "gn:feature_code":"PPL",
    "gn:name":"San Fidencio Wayaquil",
    "gn:population":23,
    "gn:timezone":"America/Mexico_City",
    "iso:country":"MX",
    "wof:name":"San Fidencio Wayaquil",
    "wof:placetype":"locality",
    "wof:population":23
},
  "geometry": {"coordinates":[-92.29684,17.21762],"type":"Point"}
}