{
  "type": "Feature",
  "properties": {
    "gn:admin1_code":"16.0",
    "gn:admin2_code":"34.0",
    "gn:asciiname":"Los Metates",
    "gn:country_code":"MX",
    "gn:dem":2436,
    "gn:feature_class":"P",
    "gn:feature_code":"PPL",
    "gn:name":"Los Metates",
    "gn:population":0,
    "gn:timezone":"America/Mexico_City",
    "iso:country":"MX",
    "name:spa_x_preferred":[
        "Los Metates"
    ],
    "wof:name":"Los Metates",
    "wof:placetype":"locality"
},
  "geometry": {"coordinates":[-100.72705000000001,19.5285],"type":"Point"}
}