{
  "type": "Feature",
  "properties": {
    "gn:admin1_code":"11",
    "gn:admin2_code":"12.0",
    "gn:asciiname":"Colonia Linda Vista",
    "gn:country_code":"MX",
    "gn:dem":1762,
    "gn:feature_class":"P",
    "gn:feature_code":"PPL",
    "gn:name":"Colonia Linda Vista",
    "gn:population":425,
    "gn:timezone":"America/Mexico_City",
    "iso:country":"MX",
    "wof:name":"Colonia Linda Vista",
    "wof:placetype":"locality",
    "wof:population":425
},
  "geometry": {"coordinates":[-101.68805999999999,20.61278],"type":"Point"}
}