{
  "type": "Feature",
  "properties": {
    "gn:admin1_code":"16.0",
    "gn:admin2_code":"53.0",
    "gn:asciiname":"Ichaqueo",
    "gn:country_code":"MX",
    "gn:dem":2462,
    "gn:feature_class":"P",
    "gn:feature_code":"PPL",
    "gn:name":"Ichaqueo",
    "gn:population":0,
    "gn:timezone":"America/Mexico_City",
    "iso:country":"MX",
    "name:spa_x_preferred":[
        "Ichaqueo"
    ],
    "wof:name":"Ichaqueo",
    "wof:placetype":"locality"
},
  "geometry": {"coordinates":[-101.13983,19.57303],"type":"Point"}
}