{
  "type": "Feature",
  "properties": {
    "gn:admin1_code":"25.0",
    "gn:admin2_code":"17.0",
    "gn:asciiname":"El Carrizo",
    "gn:country_code":"MX",
    "gn:dem":1164,
    "gn:feature_class":"P",
    "gn:feature_code":"PPL",
    "gn:name":"El Carrizo",
    "gn:population":0,
    "gn:timezone":"America/Mazatlan",
    "iso:country":"MX",
    "name:spa_x_preferred":[
        "El Carrizo"
    ],
    "wof:name":"El Carrizo",
    "wof:placetype":"locality"
},
  "geometry": {"coordinates":[-107.67187,25.91299],"type":"Point"}
}