{
  "type": "Feature",
  "properties": {
    "gn:admin1_code":"20",
    "gn:admin2_code":"498.0",
    "gn:asciiname":"La Soledad",
    "gn:country_code":"MX",
    "gn:dem":66,
    "gn:feature_class":"P",
    "gn:feature_code":"PPL",
    "gn:name":"La Soledad",
    "gn:population":5,
    "gn:timezone":"America/Mexico_City",
    "iso:country":"MX",
    "wof:name":"La Soledad",
    "wof:placetype":"locality",
    "wof:population":5
},
  "geometry": {"coordinates":[-95.5425,17.55583],"type":"Point"}
}