{
  "type": "Feature",
  "properties": {
    "gn:admin1_code":"25.0",
    "gn:asciiname":"Buenos Aires",
    "gn:country_code":"MX",
    "gn:dem":688,
    "gn:feature_class":"P",
    "gn:feature_code":"PPL",
    "gn:name":"Buenos Aires",
    "gn:population":0,
    "gn:timezone":"America/Mazatlan",
    "iso:country":"MX",
    "name:spa_x_preferred":[
        "Buenos Aires"
    ],
    "wof:name":"Buenos Aires",
    "wof:placetype":"locality"
},
  "geometry": {"coordinates":[-105.72874,22.93484],"type":"Point"}
}