{
  "type": "Feature",
  "properties": {
    "gn:admin1_code":"12",
    "gn:admin2_code":"76",
    "gn:asciiname":"Coxcomatepec",
    "gn:country_code":"MX",
    "gn:dem":1555,
    "gn:feature_class":"P",
    "gn:feature_code":"PPL",
    "gn:name":"Coxcomatepec",
    "gn:population":18,
    "gn:timezone":"America/Mexico_City",
    "iso:country":"MX",
    "wof:name":"Coxcomatepec",
    "wof:placetype":"locality",
    "wof:population":18
},
  "geometry": {"coordinates":[-99.04549,17.18883],"type":"Point"}
}