{
  "type": "Feature",
  "properties": {
    "gn:admin1_code":"6",
    "gn:admin2_code":"46.0",
    "gn:asciiname":"Santa Isabel",
    "gn:country_code":"MX",
    "gn:dem":425,
    "gn:feature_class":"P",
    "gn:feature_code":"PPL",
    "gn:name":"Santa Isabel",
    "gn:population":0,
    "gn:timezone":"America/Chihuahua",
    "iso:country":"MX",
    "name:cat_x_preferred":[
        "Santa Isabel"
    ],
    "name:ceb_x_preferred":[
        "Santa Isabel"
    ],
    "name:deu_x_preferred":[
        "Santa Isabel"
    ],
    "name:epo_x_preferred":[
        "Santa Isabel"
    ],
    "name:est_x_preferred":[
        "Santa Isabel"
    ],
    "name:fra_x_preferred":[
        "Santa Isabel"
    ],
    "name:glg_x_preferred":[
        "Santa Isabel"
    ],
    "name:ita_x_preferred":[
        "Santa Isabel"
    ],
    "name:lit_x_preferred":[
        "Santa Isabel\u0117"
    ],
    "name:mlg_x_preferred":[
        "Santa Isabel"
    ],
    "name:nld_x_preferred":[
        "Santa Isabel"
    ],
    "name:nor_x_preferred":[
        "Santa Isabel"
    ],
    "name:pol_x_preferred":[
        "Santa Isabel"
    ],
    "name:por_x_preferred":[
        "Santa Isabel"
    ],
    "name:rus_x_preferred":[
        "\u0421\u0430\u043d\u0442\u0430-\u0418\u0441\u0430\u0431\u0435\u043b\u044c"
    ],
    "name:sco_x_preferred":[
        "Santa Isabel"
    ],
    "name:slk_x_preferred":[
        "Santa Isabel"
    ],
    "name:spa_x_preferred":[
        "Santa Isabel"
    ],
    "name:srp_x_preferred":[
        "\u0421\u0430\u043d\u0442\u0430 \u0418\u0441\u0430\u0431\u0435\u043b"
    ],
    "name:swe_x_preferred":[
        "Santa Isabel"
    ],
    "name:ukr_x_preferred":[
        "\u0421\u0430\u043d\u0442\u0430-\u0406\u0437\u0430\u0431\u0435\u043b"
    ],
    "name:vol_x_preferred":[
        "Santa Isabel"
    ],
    "name:war_x_preferred":[
        "Santa Isabel"
    ],
    "wof:name":"Santa Isabel",
    "wof:placetype":"locality"
},
  "geometry": {"coordinates":[-107.73220000000001,26.78822000000001],"type":"Point"}
}