{
  "type": "Feature",
  "properties": {
    "gn:admin1_code":"4.0",
    "gn:asciiname":"San Bernabe",
    "gn:country_code":"MX",
    "gn:dem":-4,
    "gn:feature_class":"P",
    "gn:feature_code":"PPL",
    "gn:name":"San Bernab\u00e9",
    "gn:population":0,
    "gn:timezone":"America/Merida",
    "iso:country":"MX",
    "name:spa_x_preferred":[
        "San Bernab\u00e9"
    ],
    "wof:name":"San Bernabe",
    "wof:placetype":"locality"
},
  "geometry": {"coordinates":[-91.04089999999999,19.04768],"type":"Point"}
}