{
  "type": "Feature",
  "properties": {
    "gn:admin1_code":"12",
    "gn:admin2_code":"22",
    "gn:asciiname":"El Trueno",
    "gn:country_code":"MX",
    "gn:dem":1211,
    "gn:feature_class":"P",
    "gn:feature_code":"PPL",
    "gn:name":"El Trueno",
    "gn:population":21,
    "gn:timezone":"America/Mexico_City",
    "iso:country":"MX",
    "wof:name":"El Trueno",
    "wof:placetype":"locality",
    "wof:population":21
},
  "geometry": {"coordinates":[-101.26747,18.08423],"type":"Point"}
}