{
  "type": "Feature",
  "properties": {
    "gn:admin1_code":"32",
    "gn:admin2_code":"42.0",
    "gn:asciiname":"Rancho Tres Marias",
    "gn:country_code":"MX",
    "gn:dem":2231,
    "gn:feature_class":"P",
    "gn:feature_code":"PPL",
    "gn:name":"Rancho Tres Mar\u00edas",
    "gn:population":8,
    "gn:timezone":"America/Mexico_City",
    "iso:country":"MX",
    "name:und_x_variant":[
        "Rancho Tres Mar\u00edas"
    ],
    "wof:name":"Rancho Tres Marias",
    "wof:placetype":"locality",
    "wof:population":8
},
  "geometry": {"coordinates":[-103.46194,23.94694],"type":"Point"}
}