{
  "type": "Feature",
  "properties": {
    "gn:admin1_code":"19.0",
    "gn:admin2_code":"14.0",
    "gn:asciiname":"Albarcones",
    "gn:country_code":"MX",
    "gn:dem":1800,
    "gn:feature_class":"P",
    "gn:feature_code":"PPL",
    "gn:name":"Albarcones",
    "gn:population":0,
    "gn:timezone":"America/Monterrey",
    "iso:country":"MX",
    "name:und_x_variant":[
        "Albercones",
        "Albarcones"
    ],
    "wof:name":"Albarcones",
    "wof:placetype":"locality"
},
  "geometry": {"coordinates":[-100.21989000000001,23.70176],"type":"Point"}
}