{
  "type": "Feature",
  "properties": {
    "gn:admin1_code":"30.0",
    "gn:asciiname":"Puente Don Diego",
    "gn:country_code":"MX",
    "gn:dem":12,
    "gn:feature_class":"P",
    "gn:feature_code":"PPL",
    "gn:name":"Puente Don Diego",
    "gn:population":0,
    "gn:timezone":"America/Mexico_City",
    "iso:country":"MX",
    "name:spa_x_preferred":[
        "Puente Don Diego"
    ],
    "wof:name":"Puente Don Diego",
    "wof:placetype":"locality"
},
  "geometry": {"coordinates":[-97.46863999999999,20.86285],"type":"Point"}
}