{
  "type": "Feature",
  "properties": {
    "gn:admin1_code":"20",
    "gn:admin2_code":"71",
    "gn:asciiname":"El Manantial",
    "gn:country_code":"MX",
    "gn:dem":342,
    "gn:feature_class":"P",
    "gn:feature_code":"PPL",
    "gn:name":"El Manantial",
    "gn:population":18,
    "gn:timezone":"America/Mexico_City",
    "iso:country":"MX",
    "wof:name":"El Manantial",
    "wof:placetype":"locality",
    "wof:population":18
},
  "geometry": {"coordinates":[-96.37694,15.87444],"type":"Point"}
}