{
  "type": "Feature",
  "properties": {
    "gn:admin1_code":"5",
    "gn:admin2_code":"106",
    "gn:asciiname":"Las Brisas Dos",
    "gn:country_code":"MX",
    "gn:dem":533,
    "gn:feature_class":"P",
    "gn:feature_code":"PPL",
    "gn:name":"Las Brisas Dos",
    "gn:population":9,
    "gn:timezone":"America/Mexico_City",
    "iso:country":"MX",
    "wof:name":"Las Brisas Dos",
    "wof:placetype":"locality",
    "wof:population":9
},
  "geometry": {"coordinates":[-92.78055999999999,16.26527999999999],"type":"Point"}
}