{
  "type": "Feature",
  "properties": {
    "gn:admin1_code":"6.0",
    "gn:admin2_code":"5.0",
    "gn:asciiname":"Diaz",
    "gn:country_code":"MX",
    "gn:dem":1297,
    "gn:feature_class":"P",
    "gn:feature_code":"PPL",
    "gn:name":"D\u00edaz",
    "gn:population":1,
    "gn:timezone":"America/Chihuahua",
    "iso:country":"MX",
    "name:spa_x_preferred":[
        "D\u00edaz"
    ],
    "name:und_x_variant":[
        "Colonia D\u00edaz"
    ],
    "wof:name":"Diaz",
    "wof:placetype":"locality",
    "wof:population":1
},
  "geometry": {"coordinates":[-108.0026,31.14772],"type":"Point"}
}