{
  "type": "Feature",
  "properties": {
    "gn:admin1_code":"24",
    "gn:admin2_code":"29.0",
    "gn:asciiname":"Poza Rica",
    "gn:country_code":"MX",
    "gn:dem":109,
    "gn:feature_class":"P",
    "gn:feature_code":"PPL",
    "gn:name":"Poza Rica",
    "gn:population":8,
    "gn:timezone":"America/Mexico_City",
    "iso:country":"MX",
    "wof:name":"Poza Rica",
    "wof:placetype":"locality",
    "wof:population":8
},
  "geometry": {"coordinates":[-98.65611,21.47278],"type":"Point"}
}