{
  "type": "Feature",
  "properties": {
    "gn:admin1_code":"20",
    "gn:admin2_code":"557.0",
    "gn:asciiname":"Colonia Santo Domingo (23 de Enero)",
    "gn:country_code":"MX",
    "gn:dem":14,
    "gn:feature_class":"P",
    "gn:feature_code":"PPL",
    "gn:name":"Colonia Santo Domingo (23 de Enero)",
    "gn:population":25,
    "gn:timezone":"America/Mexico_City",
    "iso:country":"MX",
    "wof:name":"Colonia Santo Domingo (23 de Enero)",
    "wof:placetype":"locality",
    "wof:population":25
},
  "geometry": {"coordinates":[-94.82444,16.47917],"type":"Point"}
}