{
  "type": "Feature",
  "properties": {
    "gn:admin1_code":"20",
    "gn:admin2_code":"43.0",
    "gn:asciiname":"Santa Maria del Mar",
    "gn:country_code":"MX",
    "gn:dem":6,
    "gn:feature_class":"P",
    "gn:feature_code":"PPL",
    "gn:name":"Santa Mar\u00eda del Mar",
    "gn:population":0,
    "gn:timezone":"America/Mexico_City",
    "iso:country":"MX",
    "name:spa_x_preferred":[
        "Santa Mar\u00eda del Mar"
    ],
    "wof:name":"Santa Maria del Mar",
    "wof:placetype":"locality"
},
  "geometry": {"coordinates":[-94.85639,16.22238],"type":"Point"}
}