{
  "type": "Feature",
  "properties": {
    "gn:admin1_code":"11",
    "gn:admin2_code":"15",
    "gn:asciiname":"El Encinal",
    "gn:country_code":"MX",
    "gn:dem":2393,
    "gn:feature_class":"P",
    "gn:feature_code":"PPL",
    "gn:name":"El Encinal",
    "gn:population":39,
    "gn:timezone":"America/Mexico_City",
    "iso:country":"MX",
    "wof:name":"El Encinal",
    "wof:placetype":"locality",
    "wof:population":39
},
  "geometry": {"coordinates":[-101.30722,21.12944],"type":"Point"}
}