{
  "type": "Feature",
  "properties": {
    "gn:admin1_code":"13",
    "gn:admin2_code":"54.0",
    "gn:asciiname":"El Mezquital",
    "gn:country_code":"MX",
    "gn:dem":1942,
    "gn:feature_class":"P",
    "gn:feature_code":"PPL",
    "gn:name":"El Mezquital",
    "gn:population":449,
    "gn:timezone":"America/Mexico_City",
    "iso:country":"MX",
    "wof:name":"El Mezquital",
    "wof:placetype":"locality",
    "wof:population":449
},
  "geometry": {"coordinates":[-99.14055999999999,20.38722000000001],"type":"Point"}
}