{
  "type": "Feature",
  "properties": {
    "gn:admin1_code":"5",
    "gn:admin2_code":"34.0",
    "gn:asciiname":"Javier Guillermo C.",
    "gn:country_code":"MX",
    "gn:dem":667,
    "gn:feature_class":"P",
    "gn:feature_code":"PPL",
    "gn:name":"Javier Guillermo C.",
    "gn:population":70,
    "gn:timezone":"America/Mexico_City",
    "iso:country":"MX",
    "wof:name":"Javier Guillermo C.",
    "wof:placetype":"locality",
    "wof:population":70
},
  "geometry": {"coordinates":[-92.13778000000001,15.64389],"type":"Point"}
}