{
  "type": "Feature",
  "properties": {
    "gn:admin1_code":"15",
    "gn:admin2_code":"112.0",
    "gn:asciiname":"Llano de Zacapexco",
    "gn:country_code":"MX",
    "gn:dem":2689,
    "gn:feature_class":"P",
    "gn:feature_code":"PPL",
    "gn:name":"Llano de Zacapexco",
    "gn:population":0,
    "gn:timezone":"America/Mexico_City",
    "iso:country":"MX",
    "name:spa_x_preferred":[
        "Llano de Zacapexco"
    ],
    "wof:name":"Llano de Zacapexco",
    "wof:placetype":"locality"
},
  "geometry": {"coordinates":[-99.48506999999999,19.70405],"type":"Point"}
}