{
  "type": "Feature",
  "properties": {
    "gn:admin1_code":"6",
    "gn:admin2_code":"30.0",
    "gn:asciiname":"Magueche",
    "gn:country_code":"MX",
    "gn:dem":2122,
    "gn:feature_class":"P",
    "gn:feature_code":"PPL",
    "gn:name":"Magueche",
    "gn:population":0,
    "gn:timezone":"America/Chihuahua",
    "iso:country":"MX",
    "name:spa_x_preferred":[
        "Magueche"
    ],
    "name:spa_x_variant":[
        "Bach\u00e1muchi"
    ],
    "wof:name":"Magueche",
    "wof:placetype":"locality"
},
  "geometry": {"coordinates":[-108.21942,27.6581],"type":"Point"}
}