{
  "type": "Feature",
  "properties": {
    "gn:admin1_code":"5",
    "gn:admin2_code":"16",
    "gn:asciiname":"Santa Clara Palastun",
    "gn:country_code":"MX",
    "gn:dem":30,
    "gn:feature_class":"P",
    "gn:feature_code":"PPL",
    "gn:name":"Santa Clara Palast\u00fan",
    "gn:population":11,
    "gn:timezone":"America/Mexico_City",
    "iso:country":"MX",
    "name:und_x_variant":[
        "Santa Clara Palast\u00fan"
    ],
    "wof:name":"Santa Clara Palastun",
    "wof:placetype":"locality",
    "wof:population":11
},
  "geometry": {"coordinates":[-92.02388999999999,17.63917],"type":"Point"}
}