{
  "type": "Feature",
  "properties": {
    "gn:admin1_code":"16",
    "gn:admin2_code":"10.0",
    "gn:asciiname":"Cuachalatal",
    "gn:country_code":"MX",
    "gn:dem":534,
    "gn:feature_class":"P",
    "gn:feature_code":"PPL",
    "gn:name":"Cuachalatal",
    "gn:population":7,
    "gn:timezone":"America/Mexico_City",
    "iso:country":"MX",
    "wof:name":"Cuachalatal",
    "wof:placetype":"locality",
    "wof:population":7
},
  "geometry": {"coordinates":[-102.15389,18.36667000000001],"type":"Point"}
}