{
  "type": "Feature",
  "properties": {
    "gn:admin1_code":"5.0",
    "gn:admin2_code":"6.0",
    "gn:asciiname":"Nueva Rosario",
    "gn:country_code":"MX",
    "gn:dem":1544,
    "gn:feature_class":"P",
    "gn:feature_code":"PPL",
    "gn:name":"Nueva Rosario",
    "gn:population":0,
    "gn:timezone":"America/Mexico_City",
    "iso:country":"MX",
    "name:spa_x_preferred":[
        "Nueva Rosario"
    ],
    "wof:name":"Nueva Rosario",
    "wof:placetype":"locality"
},
  "geometry": {"coordinates":[-92.08839999999999,15.51591],"type":"Point"}
}