{
  "type": "Feature",
  "properties": {
    "gn:admin1_code":"5.0",
    "gn:asciiname":"Arroyo Dulce",
    "gn:country_code":"MX",
    "gn:dem":667,
    "gn:feature_class":"P",
    "gn:feature_code":"PPL",
    "gn:name":"Arroyo Dulce",
    "gn:population":0,
    "gn:timezone":"America/Mexico_City",
    "iso:country":"MX",
    "name:spa_x_preferred":[
        "Arroyo Dulce"
    ],
    "wof:name":"Arroyo Dulce",
    "wof:placetype":"locality"
},
  "geometry": {"coordinates":[-92.71502,15.82803],"type":"Point"}
}