{
  "type": "Feature",
  "properties": {
    "gn:admin1_code":"2",
    "gn:admin2_code":"1.0",
    "gn:asciiname":"La Lupita",
    "gn:country_code":"MX",
    "gn:dem":778,
    "gn:feature_class":"P",
    "gn:feature_code":"PPL",
    "gn:name":"La Lupita",
    "gn:population":0,
    "gn:timezone":"America/Tijuana",
    "iso:country":"MX",
    "name:spa_x_preferred":[
        "La Lupita"
    ],
    "wof:name":"La Lupita",
    "wof:placetype":"locality"
},
  "geometry": {"coordinates":[-115.69096,31.36085],"type":"Point"}
}