{
  "type": "Feature",
  "properties": {
    "gn:admin1_code":"11",
    "gn:admin2_code":"30",
    "gn:asciiname":"Los Rangeles",
    "gn:country_code":"MX",
    "gn:dem":2228,
    "gn:feature_class":"P",
    "gn:feature_code":"PPL",
    "gn:name":"Los Rangeles",
    "gn:population":16,
    "gn:timezone":"America/Mexico_City",
    "iso:country":"MX",
    "wof:name":"Los Rangeles",
    "wof:placetype":"locality",
    "wof:population":16
},
  "geometry": {"coordinates":[-101.425,21.24056],"type":"Point"}
}