{
  "type": "Feature",
  "properties": {
    "gn:admin1_code":"20",
    "gn:admin2_code":"307.0",
    "gn:asciiname":"Mazcalco",
    "gn:country_code":"MX",
    "gn:dem":4,
    "gn:feature_class":"P",
    "gn:feature_code":"PPL",
    "gn:name":"Mazcalco",
    "gn:population":0,
    "gn:timezone":"America/Mexico_City",
    "iso:country":"MX",
    "name:spa_x_preferred":[
        "Mazcalco"
    ],
    "wof:name":"Mazcalco",
    "wof:placetype":"locality"
},
  "geometry": {"coordinates":[-95.87347,15.87133],"type":"Point"}
}