{
  "type": "Feature",
  "properties": {
    "gn:admin1_code":"24",
    "gn:admin2_code":"36",
    "gn:asciiname":"Meliton Solis",
    "gn:country_code":"MX",
    "gn:dem":315,
    "gn:feature_class":"P",
    "gn:feature_code":"PPL",
    "gn:name":"Melit\u00f3n Sol\u00eds",
    "gn:population":13,
    "gn:timezone":"America/Mexico_City",
    "iso:country":"MX",
    "name:und_x_variant":[
        "Melit\u00f3n Sol\u00eds"
    ],
    "wof:name":"Meliton Solis",
    "wof:placetype":"locality",
    "wof:population":13
},
  "geometry": {"coordinates":[-99.28082999999999,21.73139],"type":"Point"}
}