{
  "type": "Feature",
  "properties": {
    "gn:admin1_code":"16",
    "gn:admin2_code":"55",
    "gn:asciiname":"La Limonera",
    "gn:country_code":"MX",
    "gn:dem":357,
    "gn:feature_class":"P",
    "gn:feature_code":"PPL",
    "gn:name":"La Limonera",
    "gn:population":28,
    "gn:timezone":"America/Mexico_City",
    "iso:country":"MX",
    "wof:name":"La Limonera",
    "wof:placetype":"locality",
    "wof:population":28
},
  "geometry": {"coordinates":[-102.08944,18.99167000000001],"type":"Point"}
}