{
  "type": "Feature",
  "properties": {
    "gn:admin1_code":"32",
    "gn:admin2_code":"46.0",
    "gn:asciiname":"Capulin de las Salinas",
    "gn:country_code":"MX",
    "gn:dem":1941,
    "gn:feature_class":"P",
    "gn:feature_code":"PPL",
    "gn:name":"Capul\u00edn de las Salinas",
    "gn:population":0,
    "gn:timezone":"America/Mexico_City",
    "iso:country":"MX",
    "name:spa_x_preferred":[
        "Capul\u00edn de las Salinas"
    ],
    "wof:name":"Capulin de las Salinas",
    "wof:placetype":"locality"
},
  "geometry": {"coordinates":[-103.0637,22.40005],"type":"Point"}
}