{
  "type": "Feature",
  "properties": {
    "gn:admin1_code":"3.0",
    "gn:asciiname":"San Refugio de la Presa",
    "gn:country_code":"MX",
    "gn:dem":132,
    "gn:feature_class":"P",
    "gn:feature_code":"PPL",
    "gn:name":"San Refugio de la Presa",
    "gn:population":0,
    "gn:timezone":"America/Mazatlan",
    "iso:country":"MX",
    "name:spa_x_preferred":[
        "San Refugio de la Presa"
    ],
    "wof:name":"San Refugio de la Presa",
    "wof:placetype":"locality"
},
  "geometry": {"coordinates":[-111.33843,24.96117000000001],"type":"Point"}
}