{
  "type": "Feature",
  "properties": {
    "gn:admin1_code":"5.0",
    "gn:asciiname":"Cuajilote Uno",
    "gn:country_code":"MX",
    "gn:dem":689,
    "gn:feature_class":"P",
    "gn:feature_code":"PPL",
    "gn:name":"Cuajilote Uno",
    "gn:population":0,
    "gn:timezone":"America/Mexico_City",
    "iso:country":"MX",
    "name:spa_x_preferred":[
        "Cuajilote Uno"
    ],
    "wof:name":"Cuajilote Uno",
    "wof:placetype":"locality"
},
  "geometry": {"coordinates":[-92.15101,16.06399],"type":"Point"}
}