{
  "type": "Feature",
  "properties": {
    "gn:admin1_code":"10",
    "gn:admin2_code":"5.0",
    "gn:asciiname":"Los Rayones",
    "gn:country_code":"MX",
    "gn:dem":2418,
    "gn:feature_class":"P",
    "gn:feature_code":"PPL",
    "gn:name":"Los Rayones",
    "gn:population":0,
    "gn:timezone":"America/Monterrey",
    "iso:country":"MX",
    "wof:name":"Los Rayones",
    "wof:placetype":"locality"
},
  "geometry": {"coordinates":[-104.96874,24.19266],"type":"Point"}
}