{
  "type": "Feature",
  "properties": {
    "gn:admin1_code":"27",
    "gn:admin2_code":"12.0",
    "gn:asciiname":"Allende Alto Primera Seccion",
    "gn:country_code":"MX",
    "gn:dem":14,
    "gn:feature_class":"P",
    "gn:feature_code":"PPL",
    "gn:name":"Allende Alto Primera Secci\u00f3n",
    "gn:population":0,
    "gn:timezone":"America/Mexico_City",
    "iso:country":"MX",
    "name:spa_x_preferred":[
        "Allende El Alto"
    ],
    "name:spa_x_variant":[
        "Allende Alto Primera Secci\u00f3n",
        "Ant\u00f3n",
        "Primera Secci\u00f3n",
        "Allende el Alto"
    ],
    "wof:name":"Allende Alto Primera Seccion",
    "wof:placetype":"locality"
},
  "geometry": {"coordinates":[-92.43153,17.7426],"type":"Point"}
}