{
  "type": "Feature",
  "properties": {
    "gn:admin1_code":"18",
    "gn:admin2_code":"1.0",
    "gn:asciiname":"Rancho de los Sicari",
    "gn:country_code":"MX",
    "gn:dem":17,
    "gn:feature_class":"P",
    "gn:feature_code":"PPL",
    "gn:name":"Rancho de los Sicari",
    "gn:population":7,
    "gn:timezone":"America/Mazatlan",
    "iso:country":"MX",
    "wof:name":"Rancho de los Sicari",
    "wof:placetype":"locality",
    "wof:population":7
},
  "geometry": {"coordinates":[-105.44056,22.46083],"type":"Point"}
}