{
  "type": "Feature",
  "properties": {
    "gn:admin1_code":"30",
    "gn:admin2_code":"116.0",
    "gn:asciiname":"Sante Fe",
    "gn:country_code":"MX",
    "gn:dem":87,
    "gn:feature_class":"P",
    "gn:feature_code":"PPL",
    "gn:name":"Sante Fe",
    "gn:population":0,
    "gn:timezone":"America/Mexico_City",
    "iso:country":"MX",
    "name:spa_x_preferred":[
        "Sante Fe"
    ],
    "name:und_x_variant":[
        "Santa F\u00e9"
    ],
    "wof:name":"Sante Fe",
    "wof:placetype":"locality"
},
  "geometry": {"coordinates":[-94.87289,17.92248],"type":"Point"}
}