{
  "type": "Feature",
  "properties": {
    "gn:admin1_code":"22",
    "gn:admin2_code":"1.0",
    "gn:asciiname":"Barrio la Joya",
    "gn:country_code":"MX",
    "gn:dem":2666,
    "gn:feature_class":"P",
    "gn:feature_code":"PPL",
    "gn:name":"Barrio la Joya",
    "gn:population":162,
    "gn:timezone":"America/Mexico_City",
    "iso:country":"MX",
    "wof:name":"Barrio la Joya",
    "wof:placetype":"locality",
    "wof:population":162
},
  "geometry": {"coordinates":[-100.17583,20.16472000000001],"type":"Point"}
}