{
  "type": "Feature",
  "properties": {
    "gn:admin1_code":"21",
    "gn:admin2_code":"53.0",
    "gn:asciiname":"Buenos Aires (Presa San Francisco)",
    "gn:country_code":"MX",
    "gn:dem":2348,
    "gn:feature_class":"P",
    "gn:feature_code":"PPL",
    "gn:name":"Buenos Aires (Presa San Francisco)",
    "gn:population":339,
    "gn:timezone":"America/Mexico_City",
    "iso:country":"MX",
    "wof:name":"Buenos Aires (Presa San Francisco)",
    "wof:placetype":"locality",
    "wof:population":339
},
  "geometry": {"coordinates":[-98.0675,19.78528],"type":"Point"}
}