{
  "type": "Feature",
  "properties": {
    "gn:admin1_code":"28",
    "gn:admin2_code":"4.0",
    "gn:asciiname":"Comeje",
    "gn:country_code":"MX",
    "gn:dem":167,
    "gn:feature_class":"P",
    "gn:feature_code":"PPL",
    "gn:name":"Comeje",
    "gn:population":0,
    "gn:timezone":"America/Monterrey",
    "iso:country":"MX",
    "wof:name":"Comeje",
    "wof:placetype":"locality"
},
  "geometry": {"coordinates":[-99.16667,22.71667],"type":"Point"}
}