{
  "type": "Feature",
  "properties": {
    "gn:admin1_code":"19.0",
    "gn:asciiname":"Carmelo",
    "gn:country_code":"MX",
    "gn:dem":446,
    "gn:feature_class":"P",
    "gn:feature_code":"PPL",
    "gn:name":"Carmelo",
    "gn:population":0,
    "gn:timezone":"America/Monterrey",
    "iso:country":"MX",
    "name:spa_x_preferred":[
        "Carmelo"
    ],
    "wof:name":"Carmelo",
    "wof:placetype":"locality"
},
  "geometry": {"coordinates":[-100.30446000000001,25.95712],"type":"Point"}
}