{
  "type": "Feature",
  "properties": {
    "gn:admin1_code":"4",
    "gn:admin2_code":"2.0",
    "gn:asciiname":"Yashanal",
    "gn:country_code":"MX",
    "gn:dem":54,
    "gn:feature_class":"P",
    "gn:feature_code":"PPL",
    "gn:name":"Yashanal",
    "gn:population":0,
    "gn:timezone":"America/Merida",
    "iso:country":"MX",
    "name:spa_x_preferred":[
        "Yaxanal"
    ],
    "name:spa_x_variant":[
        "Yashanal"
    ],
    "wof:name":"Yashanal",
    "wof:placetype":"locality"
},
  "geometry": {"coordinates":[-90.50551,19.72575],"type":"Point"}
}