{
  "type": "Feature",
  "properties": {
    "gn:admin1_code":"20",
    "gn:admin2_code":"446",
    "gn:asciiname":"Cabacaya",
    "gn:country_code":"MX",
    "gn:dem":2201,
    "gn:feature_class":"P",
    "gn:feature_code":"PPL",
    "gn:name":"Cabacaya",
    "gn:population":50,
    "gn:timezone":"America/Mexico_City",
    "iso:country":"MX",
    "wof:name":"Cabacaya",
    "wof:placetype":"locality",
    "wof:population":50
},
  "geometry": {"coordinates":[-97.77694,17.03028],"type":"Point"}
}