{
  "type": "Feature",
  "properties": {
    "gn:admin1_code":"18.0",
    "gn:admin2_code":"14.0",
    "gn:asciiname":"Gabriel Lopez",
    "gn:country_code":"MX",
    "gn:dem":1321,
    "gn:feature_class":"P",
    "gn:feature_code":"PPL",
    "gn:name":"Gabriel L\u00f3pez",
    "gn:population":0,
    "gn:timezone":"America/Mazatlan",
    "iso:country":"MX",
    "wof:name":"Gabriel Lopez",
    "wof:placetype":"locality"
},
  "geometry": {"coordinates":[-104.53251,21.29365],"type":"Point"}
}