{
  "type": "Feature",
  "properties": {
    "gn:admin1_code":"30",
    "gn:admin2_code":"156",
    "gn:asciiname":"El Palacio",
    "gn:country_code":"MX",
    "gn:dem":1572,
    "gn:feature_class":"P",
    "gn:feature_code":"PPL",
    "gn:name":"El Palacio",
    "gn:population":16,
    "gn:timezone":"America/Mexico_City",
    "iso:country":"MX",
    "wof:name":"El Palacio",
    "wof:placetype":"locality",
    "wof:population":16
},
  "geometry": {"coordinates":[-97.09332999999999,19.69639],"type":"Point"}
}