{
  "type": "Feature",
  "properties": {
    "gn:admin1_code":"27",
    "gn:admin2_code":"8",
    "gn:asciiname":"Salvador Neme Castillo",
    "gn:country_code":"MX",
    "gn:dem":18,
    "gn:feature_class":"P",
    "gn:feature_code":"PPL",
    "gn:name":"Salvador Neme Castillo",
    "gn:population":40,
    "gn:timezone":"America/Mexico_City",
    "iso:country":"MX",
    "wof:name":"Salvador Neme Castillo",
    "wof:placetype":"locality",
    "wof:population":40
},
  "geometry": {"coordinates":[-93.62582999999999,17.90361],"type":"Point"}
}