{
  "type": "Feature",
  "properties": {
    "gn:admin1_code":"26.0",
    "gn:admin2_code":"30.0",
    "gn:asciiname":"Aranjuez",
    "gn:country_code":"MX",
    "gn:dem":54,
    "gn:feature_class":"P",
    "gn:feature_code":"PPL",
    "gn:name":"Aranjuez",
    "gn:population":0,
    "gn:timezone":"America/Hermosillo",
    "iso:country":"MX",
    "name:spa_x_preferred":[
        "Aranjuez"
    ],
    "wof:name":"Aranjuez",
    "wof:placetype":"locality"
},
  "geometry": {"coordinates":[-111.51881000000002,28.8198],"type":"Point"}
}