{
  "type": "Feature",
  "properties": {
    "gn:admin1_code":"13",
    "gn:admin2_code":"81.0",
    "gn:asciiname":"Barrio Panotlan",
    "gn:country_code":"MX",
    "gn:dem":1889,
    "gn:feature_class":"P",
    "gn:feature_code":"PPL",
    "gn:name":"Barrio Panotl\u00e1n",
    "gn:population":5,
    "gn:timezone":"America/Mexico_City",
    "iso:country":"MX",
    "name:und_x_variant":[
        "Barrio Panotl\u00e1n"
    ],
    "wof:name":"Barrio Panotlan",
    "wof:placetype":"locality",
    "wof:population":5
},
  "geometry": {"coordinates":[-98.66011,20.63317],"type":"Point"}
}