{
  "type": "Feature",
  "properties": {
    "gn:admin1_code":"20",
    "gn:admin2_code":"57.0",
    "gn:asciiname":"Siete Hermanos",
    "gn:country_code":"MX",
    "gn:dem":67,
    "gn:feature_class":"P",
    "gn:feature_code":"PPL",
    "gn:name":"Siete Hermanos",
    "gn:population":5,
    "gn:timezone":"America/Mexico_City",
    "iso:country":"MX",
    "wof:name":"Siete Hermanos",
    "wof:placetype":"locality",
    "wof:population":5
},
  "geometry": {"coordinates":[-95.02667,17.26778],"type":"Point"}
}