{
  "type": "Feature",
  "properties": {
    "gn:admin1_code":"14",
    "gn:admin2_code":"8",
    "gn:asciiname":"El Carrizal (Carrizal de Abajo)",
    "gn:country_code":"MX",
    "gn:dem":1997,
    "gn:feature_class":"P",
    "gn:feature_code":"PPL",
    "gn:name":"El Carrizal (Carrizal de Abajo)",
    "gn:population":31,
    "gn:timezone":"America/Mexico_City",
    "iso:country":"MX",
    "wof:name":"El Carrizal (Carrizal de Abajo)",
    "wof:placetype":"locality",
    "wof:population":31
},
  "geometry": {"coordinates":[-102.39361,20.67889],"type":"Point"}
}