{
  "type": "Feature",
  "properties": {
    "gn:admin1_code":"15.0",
    "gn:admin2_code":"105.0",
    "gn:asciiname":"La Lagunilla",
    "gn:country_code":"MX",
    "gn:dem":703,
    "gn:feature_class":"P",
    "gn:feature_code":"PPL",
    "gn:name":"La Lagunilla",
    "gn:population":0,
    "gn:timezone":"America/Mexico_City",
    "iso:country":"MX",
    "name:spa_x_preferred":[
        "La Lagunilla"
    ],
    "name:und_x_variant":[
        "Laguna Lagunilla"
    ],
    "wof:name":"La Lagunilla",
    "wof:placetype":"locality"
},
  "geometry": {"coordinates":[-100.35722,18.53492],"type":"Point"}
}