{
  "type": "Feature",
  "properties": {
    "gn:admin1_code":"20",
    "gn:admin2_code":"413.0",
    "gn:asciiname":"San Francisco Limoncito",
    "gn:country_code":"MX",
    "gn:dem":201,
    "gn:feature_class":"P",
    "gn:feature_code":"PPL",
    "gn:name":"San Francisco Limoncito",
    "gn:population":114,
    "gn:timezone":"America/Mexico_City",
    "iso:country":"MX",
    "wof:name":"San Francisco Limoncito",
    "wof:placetype":"locality",
    "wof:population":114
},
  "geometry": {"coordinates":[-96.23860999999999,15.82278],"type":"Point"}
}