{
  "type": "Feature",
  "properties": {
    "gn:admin1_code":"21",
    "gn:admin2_code":"50.0",
    "gn:asciiname":"Bella Union",
    "gn:country_code":"MX",
    "gn:dem":2015,
    "gn:feature_class":"P",
    "gn:feature_code":"PPL",
    "gn:name":"Bella Uni\u00f3n",
    "gn:population":0,
    "gn:timezone":"America/Mexico_City",
    "iso:country":"MX",
    "name:spa_x_preferred":[
        "Bella Uni\u00f3n"
    ],
    "wof:name":"Bella Union",
    "wof:placetype":"locality"
},
  "geometry": {"coordinates":[-97.10281999999999,19.185],"type":"Point"}
}