{
  "type": "Feature",
  "properties": {
    "gn:admin1_code":"27",
    "gn:admin2_code":"6.0",
    "gn:asciiname":"Pino Suarez Segunda Seccion",
    "gn:country_code":"MX",
    "gn:dem":13,
    "gn:feature_class":"P",
    "gn:feature_code":"PPL",
    "gn:name":"Pino Su\u00e1rez Segunda Secci\u00f3n",
    "gn:population":0,
    "gn:timezone":"America/Mexico_City",
    "iso:country":"MX",
    "name:spa_x_preferred":[
        "Pino Su\u00e1rez Segunda Secci\u00f3n"
    ],
    "wof:name":"Pino Suarez Segunda Seccion",
    "wof:placetype":"locality"
},
  "geometry": {"coordinates":[-93.28955999999999,18.15042],"type":"Point"}
}