{
  "type": "Feature",
  "properties": {
    "gn:admin1_code":"20",
    "gn:admin2_code":"431",
    "gn:asciiname":"El Recibimiento",
    "gn:country_code":"MX",
    "gn:dem":635,
    "gn:feature_class":"P",
    "gn:feature_code":"PPL",
    "gn:name":"El Recibimiento",
    "gn:population":16,
    "gn:timezone":"America/Mexico_City",
    "iso:country":"MX",
    "wof:name":"El Recibimiento",
    "wof:placetype":"locality",
    "wof:population":16
},
  "geometry": {"coordinates":[-97.02417,17.96027999999999],"type":"Point"}
}