{
  "type": "Feature",
  "properties": {
    "gn:admin1_code":"7",
    "gn:admin2_code":"17.0",
    "gn:asciiname":"Rancho de Afuera",
    "gn:country_code":"MX",
    "gn:dem":1121,
    "gn:feature_class":"P",
    "gn:feature_code":"PPL",
    "gn:name":"Rancho de Afuera",
    "gn:population":0,
    "gn:timezone":"America/Monterrey",
    "iso:country":"MX",
    "name:spa_x_preferred":[
        "Rancho de Afuera"
    ],
    "wof:name":"Rancho de Afuera",
    "wof:placetype":"locality"
},
  "geometry": {"coordinates":[-103.35883,25.62603],"type":"Point"}
}