{
  "type": "Feature",
  "properties": {
    "gn:admin1_code":"20",
    "gn:admin2_code":"5.0",
    "gn:asciiname":"Canal Treinta y Tres",
    "gn:country_code":"MX",
    "gn:dem":39,
    "gn:feature_class":"P",
    "gn:feature_code":"PPL",
    "gn:name":"Canal Treinta y Tres",
    "gn:population":71,
    "gn:timezone":"America/Mexico_City",
    "iso:country":"MX",
    "wof:name":"Canal Treinta y Tres",
    "wof:placetype":"locality",
    "wof:population":71
},
  "geometry": {"coordinates":[-95.06694,16.49806],"type":"Point"}
}