{
  "type": "Feature",
  "properties": {
    "gn:admin1_code":"12",
    "gn:admin2_code":"76.0",
    "gn:asciiname":"Piedra Tuza",
    "gn:country_code":"MX",
    "gn:dem":1556,
    "gn:feature_class":"P",
    "gn:feature_code":"PPL",
    "gn:name":"Piedra Tuza",
    "gn:population":124,
    "gn:timezone":"America/Mexico_City",
    "iso:country":"MX",
    "wof:name":"Piedra Tuza",
    "wof:placetype":"locality",
    "wof:population":124
},
  "geometry": {"coordinates":[-98.90373,17.31146],"type":"Point"}
}