{
  "type": "Feature",
  "properties": {
    "gn:admin1_code":"25.0",
    "gn:asciiname":"Bebelamo",
    "gn:country_code":"MX",
    "gn:dem":6,
    "gn:feature_class":"P",
    "gn:feature_code":"PPL",
    "gn:name":"Bebelamo",
    "gn:population":0,
    "gn:timezone":"America/Mazatlan",
    "iso:country":"MX",
    "name:spa_x_preferred":[
        "Bebelamo"
    ],
    "wof:name":"Bebelamo",
    "wof:placetype":"locality"
},
  "geometry": {"coordinates":[-105.99093000000001,22.85328],"type":"Point"}
}