{
  "type": "Feature",
  "properties": {
    "gn:admin1_code":"5.0",
    "gn:asciiname":"Las Naranjas",
    "gn:country_code":"MX",
    "gn:dem":779,
    "gn:feature_class":"P",
    "gn:feature_code":"PPL",
    "gn:name":"Las Naranjas",
    "gn:population":0,
    "gn:timezone":"America/Mexico_City",
    "iso:country":"MX",
    "name:spa_x_preferred":[
        "Las Naranjas"
    ],
    "wof:name":"Las Naranjas",
    "wof:placetype":"locality"
},
  "geometry": {"coordinates":[-92.97702,15.82204],"type":"Point"}
}