{
  "type": "Feature",
  "properties": {
    "gn:admin1_code":"16.0",
    "gn:admin2_code":"9.0",
    "gn:asciiname":"El Potrero de Pablo Cuin",
    "gn:country_code":"MX",
    "gn:dem":2051,
    "gn:feature_class":"P",
    "gn:feature_code":"PPL",
    "gn:name":"El Potrero de Pablo Cu\u00edn",
    "gn:population":0,
    "gn:timezone":"America/Mexico_City",
    "iso:country":"MX",
    "name:spa_x_preferred":[
        "El Potrero de Pablo Cu\u00edn"
    ],
    "wof:name":"El Potrero de Pablo Cuin",
    "wof:placetype":"locality"
},
  "geometry": {"coordinates":[-101.67713999999999,19.21222],"type":"Point"}
}