{
  "type": "Feature",
  "properties": {
    "gn:admin1_code":"24",
    "gn:admin2_code":"13.0",
    "gn:asciiname":"Fraccionamiento Mision de San Miguel",
    "gn:country_code":"MX",
    "gn:dem":72,
    "gn:feature_class":"P",
    "gn:feature_code":"PPL",
    "gn:name":"Fraccionamiento Misi\u00f3n de San Miguel",
    "gn:population":227,
    "gn:timezone":"America/Mexico_City",
    "iso:country":"MX",
    "name:und_x_variant":[
        "Fraccionamiento Misi\u00f3n de San Miguel"
    ],
    "wof:name":"Fraccionamiento Mision de San Miguel",
    "wof:placetype":"locality",
    "wof:population":227
},
  "geometry": {"coordinates":[-99.02361000000001,21.96306],"type":"Point"}
}