{
  "type": "Feature",
  "properties": {
    "gn:admin1_code":"6",
    "gn:admin2_code":"12.0",
    "gn:asciiname":"Bacuseachi",
    "gn:country_code":"MX",
    "gn:dem":2098,
    "gn:feature_class":"P",
    "gn:feature_code":"PPL",
    "gn:name":"Bacuseachi",
    "gn:population":0,
    "gn:timezone":"America/Chihuahua",
    "iso:country":"MX",
    "wof:name":"Bacuseachi",
    "wof:placetype":"locality"
},
  "geometry": {"coordinates":[-106.94886,27.43486],"type":"Point"}
}