{
  "type": "Feature",
  "properties": {
    "gn:admin1_code":"16.0",
    "gn:admin2_code":"8.0",
    "gn:asciiname":"El Zapote",
    "gn:country_code":"MX",
    "gn:dem":257,
    "gn:feature_class":"P",
    "gn:feature_code":"PPL",
    "gn:name":"El Zapote",
    "gn:population":0,
    "gn:timezone":"America/Mexico_City",
    "iso:country":"MX",
    "name:spa_x_preferred":[
        "El Zapote"
    ],
    "wof:name":"El Zapote",
    "wof:placetype":"locality"
},
  "geometry": {"coordinates":[-103.60926000000001,18.61449],"type":"Point"}
}