{
  "type": "Feature",
  "properties": {
    "gn:admin1_code":"11",
    "gn:admin2_code":"19.0",
    "gn:asciiname":"San Isidro",
    "gn:cc2":"MX",
    "gn:country_code":"MX",
    "gn:dem":2136,
    "gn:feature_class":"P",
    "gn:feature_code":"PPL",
    "gn:name":"San Isidro",
    "gn:population":5,
    "gn:timezone":"America/Mexico_City",
    "iso:country":"MX",
    "name:und_x_variant":[
        "San Isidro de la Corregidora"
    ],
    "wof:name":"San Isidro",
    "wof:placetype":"locality",
    "wof:population":5
},
  "geometry": {"coordinates":[-100.44028,20.38528],"type":"Point"}
}