{
  "type": "Feature",
  "properties": {
    "gn:admin1_code":"6.0",
    "gn:admin2_code":"40.0",
    "gn:asciiname":"La Torre",
    "gn:country_code":"MX",
    "gn:dem":2395,
    "gn:feature_class":"P",
    "gn:feature_code":"PPL",
    "gn:name":"La Torre",
    "gn:population":0,
    "gn:timezone":"America/Chihuahua",
    "iso:country":"MX",
    "name:spa_x_preferred":[
        "La Torre"
    ],
    "wof:name":"La Torre",
    "wof:placetype":"locality"
},
  "geometry": {"coordinates":[-108.41896,29.12599],"type":"Point"}
}