{
  "type": "Feature",
  "properties": {
    "gn:admin1_code":"6",
    "gn:admin2_code":"1.0",
    "gn:asciiname":"San Lorencito",
    "gn:country_code":"MX",
    "gn:dem":1590,
    "gn:feature_class":"P",
    "gn:feature_code":"PPL",
    "gn:name":"San Lorencito",
    "gn:population":184,
    "gn:timezone":"America/Chihuahua",
    "iso:country":"MX",
    "wof:name":"San Lorencito",
    "wof:placetype":"locality",
    "wof:population":184
},
  "geometry": {"coordinates":[-106.39028,29.90472],"type":"Point"}
}