{
  "type": "Feature",
  "properties": {
    "gn:admin1_code":"5",
    "gn:admin2_code":"75.0",
    "gn:asciiname":"El Cipres",
    "gn:country_code":"MX",
    "gn:dem":1305,
    "gn:feature_class":"P",
    "gn:feature_code":"PPL",
    "gn:name":"El Cipr\u00e9s",
    "gn:population":216,
    "gn:timezone":"America/Mexico_City",
    "iso:country":"MX",
    "name:und_x_variant":[
        "El Cipr\u00e9s"
    ],
    "wof:name":"El Cipres",
    "wof:placetype":"locality",
    "wof:population":216
},
  "geometry": {"coordinates":[-92.33472,16.31167],"type":"Point"}
}