{
  "type": "Feature",
  "properties": {
    "gn:admin1_code":"7.0",
    "gn:admin2_code":"9.0",
    "gn:asciiname":"Ejido Cantabro",
    "gn:country_code":"MX",
    "gn:dem":1101,
    "gn:feature_class":"P",
    "gn:feature_code":"PPL",
    "gn:name":"Ejido Cantabro",
    "gn:population":0,
    "gn:timezone":"America/Monterrey",
    "iso:country":"MX",
    "wof:name":"Ejido Cantabro",
    "wof:placetype":"locality"
},
  "geometry": {"coordinates":[-103.20085,25.92722],"type":"Point"}
}