{
  "type": "Feature",
  "properties": {
    "gn:admin1_code":"32",
    "gn:admin2_code":"48.0",
    "gn:asciiname":"Fraccionamiento COPROVI Bellavista",
    "gn:country_code":"MX",
    "gn:dem":1709,
    "gn:feature_class":"P",
    "gn:feature_code":"PPL",
    "gn:name":"Fraccionamiento COPROVI Bellavista",
    "gn:population":292,
    "gn:timezone":"America/Mexico_City",
    "iso:country":"MX",
    "wof:name":"Fraccionamiento COPROVI Bellavista",
    "wof:placetype":"locality",
    "wof:population":292
},
  "geometry": {"coordinates":[-103.30139,21.75278],"type":"Point"}
}