{
  "type": "Feature",
  "properties": {
    "gn:admin1_code":"26",
    "gn:admin2_code":"18.0",
    "gn:asciiname":"Campo Cocorit",
    "gn:country_code":"MX",
    "gn:dem":28,
    "gn:feature_class":"P",
    "gn:feature_code":"PPL",
    "gn:name":"Campo Cocorit",
    "gn:population":0,
    "gn:timezone":"America/Hermosillo",
    "iso:country":"MX",
    "name:spa_x_preferred":[
        "Campo Cocorit"
    ],
    "wof:name":"Campo Cocorit",
    "wof:placetype":"locality"
},
  "geometry": {"coordinates":[-109.9907,27.57827],"type":"Point"}
}