{
  "type": "Feature",
  "properties": {
    "gn:admin1_code":"21",
    "gn:admin2_code":"21",
    "gn:asciiname":"Barrio de los Reyes",
    "gn:country_code":"MX",
    "gn:dem":1165,
    "gn:feature_class":"P",
    "gn:feature_code":"PPL",
    "gn:name":"Barrio de los Reyes",
    "gn:population":36,
    "gn:timezone":"America/Mexico_City",
    "iso:country":"MX",
    "wof:name":"Barrio de los Reyes",
    "wof:placetype":"locality",
    "wof:population":36
},
  "geometry": {"coordinates":[-98.55027,18.54073],"type":"Point"}
}