{
  "type": "Feature",
  "properties": {
    "gn:admin1_code":"3",
    "gn:admin2_code":"3",
    "gn:asciiname":"El Setentaidos",
    "gn:country_code":"MX",
    "gn:dem":13,
    "gn:feature_class":"P",
    "gn:feature_code":"PPL",
    "gn:name":"El Setentaid\u00f3s",
    "gn:population":13,
    "gn:timezone":"America/Mazatlan",
    "iso:country":"MX",
    "name:und_x_variant":[
        "El Setentaid\u00f3s"
    ],
    "wof:name":"El Setentaidos",
    "wof:placetype":"locality",
    "wof:population":13
},
  "geometry": {"coordinates":[-110.15271,23.26981],"type":"Point"}
}