{
  "type": "Feature",
  "properties": {
    "gn:admin1_code":"20",
    "gn:admin2_code":"306",
    "gn:asciiname":"Tierra Colorada",
    "gn:country_code":"MX",
    "gn:dem":1566,
    "gn:feature_class":"P",
    "gn:feature_code":"PPL",
    "gn:name":"Tierra Colorada",
    "gn:population":13,
    "gn:timezone":"America/Mexico_City",
    "iso:country":"MX",
    "wof:name":"Tierra Colorada",
    "wof:placetype":"locality",
    "wof:population":13
},
  "geometry": {"coordinates":[-96.45193999999999,16.01889],"type":"Point"}
}