{
  "type": "Feature",
  "properties": {
    "gn:admin1_code":"5",
    "gn:admin2_code":"64.0",
    "gn:asciiname":"Tzajalococh",
    "gn:country_code":"MX",
    "gn:dem":1657,
    "gn:feature_class":"P",
    "gn:feature_code":"PPL",
    "gn:name":"Tzajalococh",
    "gn:population":134,
    "gn:timezone":"America/Mexico_City",
    "iso:country":"MX",
    "wof:name":"Tzajalococh",
    "wof:placetype":"locality",
    "wof:population":134
},
  "geometry": {"coordinates":[-92.32889,16.86194],"type":"Point"}
}