{
  "type": "Feature",
  "properties": {
    "gn:admin1_code":"10",
    "gn:admin2_code":"23",
    "gn:asciiname":"Paso de Piedra",
    "gn:country_code":"MX",
    "gn:dem":2295,
    "gn:feature_class":"P",
    "gn:feature_code":"PPL",
    "gn:name":"Paso de Piedra",
    "gn:population":33,
    "gn:timezone":"America/Monterrey",
    "iso:country":"MX",
    "wof:name":"Paso de Piedra",
    "wof:placetype":"locality",
    "wof:population":33
},
  "geometry": {"coordinates":[-105.64055999999999,23.60362000000001],"type":"Point"}
}