{
  "type": "Feature",
  "properties": {
    "gn:admin1_code":"24",
    "gn:admin2_code":"2.0",
    "gn:asciiname":"San Antonio de las Tortugas",
    "gn:country_code":"MX",
    "gn:dem":1434,
    "gn:feature_class":"P",
    "gn:feature_code":"PPL",
    "gn:name":"San Antonio de las Tortugas",
    "gn:population":0,
    "gn:timezone":"America/Mexico_City",
    "iso:country":"MX",
    "name:spa_x_preferred":[
        "San Antonio de las Tortugas"
    ],
    "name:und_x_variant":[
        "Tortugas",
        "Rinc\u00f3n",
        "Rinc\u00f3n Tortugas"
    ],
    "wof:name":"San Antonio de las Tortugas",
    "wof:placetype":"locality"
},
  "geometry": {"coordinates":[-99.58244000000001,22.1812],"type":"Point"}
}