{
  "type": "Feature",
  "properties": {
    "gn:admin1_code":"26",
    "gn:admin2_code":"68.0",
    "gn:asciiname":"La Esmeralda",
    "gn:country_code":"MX",
    "gn:dem":584,
    "gn:feature_class":"P",
    "gn:feature_code":"PPL",
    "gn:name":"La Esmeralda",
    "gn:population":0,
    "gn:timezone":"America/Hermosillo",
    "iso:country":"MX",
    "name:ceb_x_preferred":[
        "La Esmeralda"
    ],
    "name:deu_x_preferred":[
        "La Esmeralda"
    ],
    "name:ita_x_preferred":[
        "La Esmeralda"
    ],
    "name:sco_x_preferred":[
        "La Esmeralda"
    ],
    "name:spa_x_preferred":[
        "La Esmeralda"
    ],
    "name:srp_x_preferred":[
        "\u041b\u0430 \u0415\u0441\u043c\u0435\u0440\u0430\u043b\u0434\u0430"
    ],
    "name:swe_x_preferred":[
        "La Esmeralda"
    ],
    "wof:name":"La Esmeralda",
    "wof:placetype":"locality"
},
  "geometry": {"coordinates":[-110.06444999999999,28.90547],"type":"Point"}
}