{
  "type": "Feature",
  "properties": {
    "gn:admin1_code":"24",
    "gn:admin2_code":"43",
    "gn:asciiname":"San Rafael",
    "gn:country_code":"MX",
    "gn:dem":1870,
    "gn:feature_class":"P",
    "gn:feature_code":"PPL",
    "gn:name":"San Rafael",
    "gn:population":11,
    "gn:timezone":"America/Mexico_City",
    "iso:country":"MX",
    "wof:name":"San Rafael",
    "wof:placetype":"locality",
    "wof:population":11
},
  "geometry": {"coordinates":[-100.52861,21.59861],"type":"Point"}
}