{
  "type": "Feature",
  "properties": {
    "gn:admin1_code":"32",
    "gn:admin2_code":"20.0",
    "gn:asciiname":"Mesa de Mercado",
    "gn:country_code":"MX",
    "gn:dem":2545,
    "gn:feature_class":"P",
    "gn:feature_code":"PPL",
    "gn:name":"Mesa de Mercado",
    "gn:population":0,
    "gn:timezone":"America/Mexico_City",
    "iso:country":"MX",
    "name:spa_x_preferred":[
        "Mesa de Mercado"
    ],
    "wof:name":"Mesa de Mercado",
    "wof:placetype":"locality"
},
  "geometry": {"coordinates":[-103.18603,22.72395],"type":"Point"}
}