{
  "type": "Feature",
  "properties": {
    "gn:admin1_code":"14.0",
    "gn:admin2_code":"121.0",
    "gn:asciiname":"La Parotita",
    "gn:country_code":"MX",
    "gn:dem":1234,
    "gn:feature_class":"P",
    "gn:feature_code":"PPL",
    "gn:name":"La Parotita",
    "gn:population":0,
    "gn:timezone":"America/Mexico_City",
    "iso:country":"MX",
    "name:spa_x_preferred":[
        "La Parotita"
    ],
    "wof:name":"La Parotita",
    "wof:placetype":"locality"
},
  "geometry": {"coordinates":[-103.23436,19.52061],"type":"Point"}
}