{
  "type": "Feature",
  "properties": {
    "gn:admin1_code":"30",
    "gn:admin2_code":"152.0",
    "gn:asciiname":"El Ojital",
    "gn:country_code":"MX",
    "gn:dem":34,
    "gn:feature_class":"P",
    "gn:feature_code":"PPL",
    "gn:name":"El Ojital",
    "gn:population":9,
    "gn:timezone":"America/Mexico_City",
    "iso:country":"MX",
    "wof:name":"El Ojital",
    "wof:placetype":"locality",
    "wof:population":9
},
  "geometry": {"coordinates":[-97.98972000000001,22.05222],"type":"Point"}
}