{
  "type": "Feature",
  "properties": {
    "gn:admin1_code":"24",
    "gn:admin2_code":"15",
    "gn:asciiname":"San Francisco de Asis del Campo Real",
    "gn:country_code":"MX",
    "gn:dem":2127,
    "gn:feature_class":"P",
    "gn:feature_code":"PPL",
    "gn:name":"San Francisco de As\u00eds del Campo Real",
    "gn:population":46,
    "gn:timezone":"America/Mexico_City",
    "iso:country":"MX",
    "name:und_x_variant":[
        "San Francisco de As\u00eds del Campo Real"
    ],
    "wof:name":"San Francisco de Asis del Campo Real",
    "wof:placetype":"locality",
    "wof:population":46
},
  "geometry": {"coordinates":[-101.06972,23.18972],"type":"Point"}
}