{
  "type": "Feature",
  "properties": {
    "gn:admin1_code":"20",
    "gn:admin2_code":"89.0",
    "gn:asciiname":"San Antonio de Leon",
    "gn:country_code":"MX",
    "gn:dem":1707,
    "gn:feature_class":"P",
    "gn:feature_code":"PPL",
    "gn:name":"San Antonio de Le\u00f3n",
    "gn:population":573,
    "gn:timezone":"America/Mexico_City",
    "iso:country":"MX",
    "name:und_x_variant":[
        "San Antonio de Le\u00f3n"
    ],
    "wof:name":"San Antonio de Leon",
    "wof:placetype":"locality",
    "wof:population":573
},
  "geometry": {"coordinates":[-97.73457000000001,17.69659],"type":"Point"}
}