{
  "type": "Feature",
  "properties": {
    "gn:admin1_code":"4",
    "gn:admin2_code":"11.0",
    "gn:asciiname":"El Faisan",
    "gn:country_code":"MX",
    "gn:dem":67,
    "gn:feature_class":"P",
    "gn:feature_code":"PPL",
    "gn:name":"El Fais\u00e1n",
    "gn:population":5,
    "gn:timezone":"America/Merida",
    "iso:country":"MX",
    "name:und_x_variant":[
        "El Fais\u00e1n"
    ],
    "wof:name":"El Faisan",
    "wof:placetype":"locality",
    "wof:population":5
},
  "geometry": {"coordinates":[-91.00306,17.96861],"type":"Point"}
}