{
  "type": "Feature",
  "properties": {
    "gn:admin1_code":"25",
    "gn:admin2_code":"7.0",
    "gn:asciiname":"Los Arenales",
    "gn:country_code":"MX",
    "gn:dem":152,
    "gn:feature_class":"P",
    "gn:feature_code":"PPL",
    "gn:name":"Los Arenales",
    "gn:population":10,
    "gn:timezone":"America/Hermosillo",
    "iso:country":"MX",
    "name:spa_x_preferred":[
        "Los Arenales"
    ],
    "wof:name":"Los Arenales",
    "wof:placetype":"locality",
    "wof:population":10
},
  "geometry": {"coordinates":[-108.50241,26.80882],"type":"Point"}
}