{
  "type": "Feature",
  "properties": {
    "gn:admin1_code":"14.0",
    "gn:asciiname":"Castellano",
    "gn:country_code":"MX",
    "gn:dem":380,
    "gn:feature_class":"P",
    "gn:feature_code":"PPL",
    "gn:name":"Castellano",
    "gn:population":0,
    "gn:timezone":"America/Mazatlan",
    "iso:country":"MX",
    "name:und_x_variant":[
        "Castellana",
        "Castellano"
    ],
    "wof:name":"Castellano",
    "wof:placetype":"locality"
},
  "geometry": {"coordinates":[-104.23833,21.19198],"type":"Point"}
}