{
  "type": "Feature",
  "properties": {
    "gn:admin1_code":"14.0",
    "gn:asciiname":"Castellano",
    "gn:country_code":"MX",
    "gn:dem":380,
    "gn:feature_class":"P",
    "gn:feature_code":"PPL",
    "gn:name":"Castellano",
    "gn:population":0,
    "gn:timezone":"America/Mazatlan",
    "iso:country":"MX",
    "name:ceb_x_preferred":[
        "Castellano"
    ],
    "name:deu_x_preferred":[
        "Castellano"
    ],
    "name:fra_x_preferred":[
        "Castellano"
    ],
    "name:ita_x_preferred":[
        "Castellano"
    ],
    "name:nld_x_preferred":[
        "Castellano"
    ],
    "name:pol_x_preferred":[
        "Castellano"
    ],
    "name:rus_x_preferred":[
        "\u041a\u0430\u0441\u0442\u0435\u043b\u043b\u0430\u043d\u043e"
    ],
    "name:spa_x_preferred":[
        "Castellano"
    ],
    "name:srp_x_preferred":[
        "Kastelano"
    ],
    "name:swe_x_preferred":[
        "Castellano"
    ],
    "name:und_x_variant":[
        "Castellana"
    ],
    "wof:name":"Castellano",
    "wof:placetype":"locality"
},
  "geometry": {"coordinates":[-104.23833,21.19198],"type":"Point"}
}