{
  "type": "Feature",
  "properties": {
    "gn:admin1_code":"16",
    "gn:admin2_code":"9.0",
    "gn:asciiname":"Tipitarillo",
    "gn:country_code":"MX",
    "gn:dem":1258,
    "gn:feature_class":"P",
    "gn:feature_code":"PPL",
    "gn:name":"Tipitarillo",
    "gn:population":486,
    "gn:timezone":"America/Mexico_City",
    "iso:country":"MX",
    "wof:name":"Tipitarillo",
    "wof:placetype":"locality",
    "wof:population":486
},
  "geometry": {"coordinates":[-101.8175,19.29389],"type":"Point"}
}