{
  "type": "Feature",
  "properties": {
    "gn:admin1_code":"10",
    "gn:admin2_code":"19.0",
    "gn:asciiname":"San Jose de la Cruz",
    "gn:country_code":"MX",
    "gn:dem":2425,
    "gn:feature_class":"P",
    "gn:feature_code":"PPL",
    "gn:name":"San Jos\u00e9 de la Cruz",
    "gn:population":129,
    "gn:timezone":"America/Monterrey",
    "iso:country":"MX",
    "name:und_x_variant":[
        "San Jos\u00e9 de la Cruz"
    ],
    "wof:name":"San Jose de la Cruz",
    "wof:placetype":"locality",
    "wof:population":129
},
  "geometry": {"coordinates":[-105.63972,24.74667],"type":"Point"}
}