{
  "type": "Feature",
  "properties": {
    "gn:admin1_code":"11",
    "gn:admin2_code":"23",
    "gn:asciiname":"Refugio de Medina",
    "gn:country_code":"MX",
    "gn:dem":1695,
    "gn:feature_class":"P",
    "gn:feature_code":"PPL",
    "gn:name":"Refugio de Medina",
    "gn:population":27,
    "gn:timezone":"America/Mexico_City",
    "iso:country":"MX",
    "wof:name":"Refugio de Medina",
    "wof:placetype":"locality",
    "wof:population":27
},
  "geometry": {"coordinates":[-101.86556,20.34806],"type":"Point"}
}