{
  "type": "Feature",
  "properties": {
    "gn:admin1_code":"6.0",
    "gn:admin2_code":"31.0",
    "gn:asciiname":"La Cienega del Gato",
    "gn:country_code":"MX",
    "gn:dem":2251,
    "gn:feature_class":"P",
    "gn:feature_code":"PPL",
    "gn:name":"La Ci\u00e9nega del Gato",
    "gn:population":0,
    "gn:timezone":"America/Chihuahua",
    "iso:country":"MX",
    "name:spa_x_preferred":[
        "La Ci\u00e9nega del Gato"
    ],
    "wof:name":"La Cienega del Gato",
    "wof:placetype":"locality"
},
  "geometry": {"coordinates":[-107.57906,28.39201],"type":"Point"}
}