{
  "type": "Feature",
  "properties": {
    "gn:admin1_code":"15",
    "gn:admin2_code":"51",
    "gn:asciiname":"La Pedrera",
    "gn:country_code":"MX",
    "gn:dem":3024,
    "gn:feature_class":"P",
    "gn:feature_code":"PPL",
    "gn:name":"La Pedrera",
    "gn:population":14,
    "gn:timezone":"America/Mexico_City",
    "iso:country":"MX",
    "wof:name":"La Pedrera",
    "wof:placetype":"locality",
    "wof:population":14
},
  "geometry": {"coordinates":[-99.40091,19.31827],"type":"Point"}
}