{
  "type": "Feature",
  "properties": {
    "gn:admin1_code":"26",
    "gn:admin2_code":"10.0",
    "gn:asciiname":"Agua Fria",
    "gn:country_code":"MX",
    "gn:dem":1727,
    "gn:feature_class":"P",
    "gn:feature_code":"PPL",
    "gn:name":"Agua Fr\u00eda",
    "gn:population":68,
    "gn:timezone":"America/Hermosillo",
    "iso:country":"MX",
    "name:ceb_x_preferred":[
        "Agua Fria"
    ],
    "name:deu_x_preferred":[
        "Agua Fria"
    ],
    "name:swe_x_preferred":[
        "Agua Fria"
    ],
    "name:und_x_variant":[
        "Agua Fr\u00eda"
    ],
    "wof:name":"Agua Fria",
    "wof:placetype":"locality",
    "wof:population":68
},
  "geometry": {"coordinates":[-108.67778,30.13667],"type":"Point"}
}