{
  "type": "Feature",
  "properties": {
    "gn:admin1_code":"2",
    "gn:admin2_code":"4",
    "gn:asciiname":"El Indio",
    "gn:country_code":"MX",
    "gn:dem":143,
    "gn:feature_class":"P",
    "gn:feature_code":"PPL",
    "gn:name":"El Indio",
    "gn:population":11,
    "gn:timezone":"America/Tijuana",
    "iso:country":"MX",
    "wof:name":"El Indio",
    "wof:placetype":"locality",
    "wof:population":11
},
  "geometry": {"coordinates":[-116.88083,32.43056],"type":"Point"}
}