{
  "type": "Feature",
  "properties": {
    "gn:admin1_code":"21",
    "gn:admin2_code":"114.0",
    "gn:asciiname":"Tepitzin",
    "gn:country_code":"MX",
    "gn:dem":2512,
    "gn:feature_class":"P",
    "gn:feature_code":"PPL",
    "gn:name":"Tepitzin",
    "gn:population":5,
    "gn:timezone":"America/Mexico_City",
    "iso:country":"MX",
    "wof:name":"Tepitzin",
    "wof:placetype":"locality",
    "wof:population":5
},
  "geometry": {"coordinates":[-98.06357,19.11486],"type":"Point"}
}