{
  "type": "Feature",
  "properties": {
    "gn:admin1_code":"10",
    "gn:admin2_code":"34",
    "gn:asciiname":"La India",
    "gn:country_code":"MX",
    "gn:dem":2305,
    "gn:feature_class":"P",
    "gn:feature_code":"PPL",
    "gn:name":"La India",
    "gn:population":23,
    "gn:timezone":"America/Monterrey",
    "iso:country":"MX",
    "name:bre_x_preferred":[
        "La India"
    ],
    "name:bul_x_preferred":[
        "\u041b\u0430 \u0418\u043d\u0434\u0438\u044f"
    ],
    "name:deu_x_preferred":[
        "La India"
    ],
    "name:fra_x_preferred":[
        "La India"
    ],
    "name:ita_x_preferred":[
        "La India"
    ],
    "name:nld_x_preferred":[
        "La India"
    ],
    "name:rus_x_preferred":[
        "La India"
    ],
    "name:spa_x_preferred":[
        "La India"
    ],
    "wof:name":"La India",
    "wof:placetype":"locality",
    "wof:population":23
},
  "geometry": {"coordinates":[-106.73205,25.50663],"type":"Point"}
}