{
  "type": "Feature",
  "properties": {
    "gn:admin1_code":"30",
    "gn:admin2_code":"158.0",
    "gn:asciiname":"Ricardo Flores Magon",
    "gn:country_code":"MX",
    "gn:dem":7,
    "gn:feature_class":"P",
    "gn:feature_code":"PPL",
    "gn:name":"Ricardo Flores Mag\u00f3n",
    "gn:population":955,
    "gn:timezone":"America/Mexico_City",
    "iso:country":"MX",
    "name:spa_x_preferred":[
        "Ricardo Flores Mag\u00f3n"
    ],
    "wof:name":"Ricardo Flores Magon",
    "wof:placetype":"locality",
    "wof:population":955
},
  "geometry": {"coordinates":[-96.9045,20.35888],"type":"Point"}
}