{
  "type": "Feature",
  "properties": {
    "gn:admin1_code":"19",
    "gn:admin2_code":"42.0",
    "gn:asciiname":"La Bandera",
    "gn:country_code":"MX",
    "gn:dem":249,
    "gn:feature_class":"P",
    "gn:feature_code":"PPL",
    "gn:name":"La Bandera",
    "gn:population":0,
    "gn:timezone":"America/Monterrey",
    "iso:country":"MX",
    "name:ceb_x_preferred":[
        "La Bandera"
    ],
    "name:fra_x_preferred":[
        "La Bandera"
    ],
    "name:spa_x_preferred":[
        "La Bandera"
    ],
    "name:srp_x_preferred":[
        "\u041b\u0430 \u0411\u0430\u043d\u0434\u0435\u0440\u0430"
    ],
    "name:swe_x_preferred":[
        "La Bandera"
    ],
    "wof:name":"La Bandera",
    "wof:placetype":"locality"
},
  "geometry": {"coordinates":[-99.70224,25.47967],"type":"Point"}
}