{
  "type": "Feature",
  "properties": {
    "gn:admin1_code":"25",
    "gn:admin2_code":"13.0",
    "gn:asciiname":"Palos Verdes",
    "gn:cc2":"MX",
    "gn:country_code":"MX",
    "gn:dem":60,
    "gn:feature_class":"P",
    "gn:feature_code":"PPL",
    "gn:name":"Palos Verdes",
    "gn:population":0,
    "gn:timezone":"America/Mazatlan",
    "iso:country":"MX",
    "name:und_x_variant":[
        "Patos Verdes",
        "Palos Verdes"
    ],
    "wof:name":"Palos Verdes",
    "wof:placetype":"locality"
},
  "geometry": {"coordinates":[-107.63333,25.01667],"type":"Point"}
}