{
  "type": "Feature",
  "properties": {
    "gn:admin1_code":"25",
    "gn:admin2_code":"16.0",
    "gn:asciiname":"La Morada",
    "gn:country_code":"MX",
    "gn:dem":154,
    "gn:feature_class":"P",
    "gn:feature_code":"PPL",
    "gn:name":"La Morada",
    "gn:population":0,
    "gn:timezone":"America/Mazatlan",
    "iso:country":"MX",
    "name:spa_x_preferred":[
        "La Morada"
    ],
    "wof:name":"La Morada",
    "wof:placetype":"locality"
},
  "geometry": {"coordinates":[-106.61002999999999,23.68488],"type":"Point"}
}