{
  "type": "Feature",
  "properties": {
    "gn:admin1_code":"30",
    "gn:admin2_code":"49",
    "gn:asciiname":"Paso Manco",
    "gn:country_code":"MX",
    "gn:dem":118,
    "gn:feature_class":"P",
    "gn:feature_code":"PPL",
    "gn:name":"Paso Manco",
    "gn:population":16,
    "gn:timezone":"America/Mexico_City",
    "iso:country":"MX",
    "wof:name":"Paso Manco",
    "wof:placetype":"locality",
    "wof:population":16
},
  "geometry": {"coordinates":[-96.45166999999999,18.78194],"type":"Point"}
}