{
  "type": "Feature",
  "properties": {
    "gn:admin1_code":"25",
    "gn:admin2_code":"12.0",
    "gn:asciiname":"El Papayo",
    "gn:country_code":"MX",
    "gn:dem":17,
    "gn:feature_class":"P",
    "gn:feature_code":"PPL",
    "gn:name":"El Papayo",
    "gn:population":0,
    "gn:timezone":"America/Mazatlan",
    "iso:country":"MX",
    "name:spa_x_preferred":[
        "El Papayo"
    ],
    "wof:name":"El Papayo",
    "wof:placetype":"locality"
},
  "geometry": {"coordinates":[-106.58507,23.51783],"type":"Point"}
}