{
  "type": "Feature",
  "properties": {
    "gn:admin1_code":"16.0",
    "gn:admin2_code":"82.0",
    "gn:asciiname":"Tinipicuchi",
    "gn:country_code":"MX",
    "gn:dem":2570,
    "gn:feature_class":"P",
    "gn:feature_code":"PPL",
    "gn:name":"Tinipicuchi",
    "gn:population":0,
    "gn:timezone":"America/Mexico_City",
    "iso:country":"MX",
    "name:spa_x_preferred":[
        "Tinipicuchi"
    ],
    "wof:name":"Tinipicuchi",
    "wof:placetype":"locality"
},
  "geometry": {"coordinates":[-101.44447,19.37323],"type":"Point"}
}