{
  "type": "Feature",
  "properties": {
    "gn:admin1_code":"30",
    "gn:admin2_code":"98.0",
    "gn:asciiname":"Tepetzingo",
    "gn:country_code":"MX",
    "gn:dem":1439,
    "gn:feature_class":"P",
    "gn:feature_code":"PPL",
    "gn:name":"Tepetzingo",
    "gn:population":400,
    "gn:timezone":"America/Mexico_City",
    "iso:country":"MX",
    "wof:name":"Tepetzingo",
    "wof:placetype":"locality",
    "wof:population":400
},
  "geometry": {"coordinates":[-97.04194,18.76083],"type":"Point"}
}