{
  "type": "Feature",
  "properties": {
    "gn:admin1_code":"6.0",
    "gn:admin2_code":"20.0",
    "gn:asciiname":"Mesa de Guasachi",
    "gn:country_code":"MX",
    "gn:dem":2291,
    "gn:feature_class":"P",
    "gn:feature_code":"PPL",
    "gn:name":"Mesa de Guasachi",
    "gn:population":0,
    "gn:timezone":"America/Chihuahua",
    "iso:country":"MX",
    "name:spa_x_preferred":[
        "Mesa de Guasachi"
    ],
    "wof:name":"Mesa de Guasachi",
    "wof:placetype":"locality"
},
  "geometry": {"coordinates":[-108.30193,27.673],"type":"Point"}
}