{
  "type": "Feature",
  "properties": {
    "gn:admin1_code":"16",
    "gn:admin2_code":"92.0",
    "gn:asciiname":"El Tamarindo",
    "gn:country_code":"MX",
    "gn:dem":720,
    "gn:feature_class":"P",
    "gn:feature_code":"PPL",
    "gn:name":"El Tamarindo",
    "gn:population":0,
    "gn:timezone":"America/Mexico_City",
    "iso:country":"MX",
    "name:spa_x_preferred":[
        "El Tamarindo"
    ],
    "wof:name":"El Tamarindo",
    "wof:placetype":"locality"
},
  "geometry": {"coordinates":[-100.94298000000001,19.1252],"type":"Point"}
}