{
  "type": "Feature",
  "properties": {
    "gn:admin1_code":"30",
    "gn:admin2_code":"40",
    "gn:asciiname":"Ejido Coatzintla",
    "gn:country_code":"MX",
    "gn:dem":129,
    "gn:feature_class":"P",
    "gn:feature_code":"PPL",
    "gn:name":"Ejido Coatzintla",
    "gn:population":15,
    "gn:timezone":"America/Mexico_City",
    "iso:country":"MX",
    "wof:name":"Ejido Coatzintla",
    "wof:placetype":"locality",
    "wof:population":15
},
  "geometry": {"coordinates":[-97.53222,20.46028],"type":"Point"}
}