{
  "type": "Feature",
  "properties": {
    "gn:admin1_code":"5",
    "gn:admin2_code":"109",
    "gn:asciiname":"Loma Linda",
    "gn:country_code":"MX",
    "gn:dem":811,
    "gn:feature_class":"P",
    "gn:feature_code":"PPL",
    "gn:name":"Loma Linda",
    "gn:population":51,
    "gn:timezone":"America/Mexico_City",
    "iso:country":"MX",
    "wof:name":"Loma Linda",
    "wof:placetype":"locality",
    "wof:population":51
},
  "geometry": {"coordinates":[-92.35778000000001,17.18889],"type":"Point"}
}