{
  "type": "Feature",
  "properties": {
    "gn:admin1_code":"10",
    "gn:admin2_code":"34.0",
    "gn:asciiname":"Vainoral",
    "gn:country_code":"MX",
    "gn:dem":381,
    "gn:feature_class":"P",
    "gn:feature_code":"PPL",
    "gn:name":"Vainoral",
    "gn:population":0,
    "gn:timezone":"America/Monterrey",
    "iso:country":"MX",
    "name:spa_x_preferred":[
        "Vainoral"
    ],
    "wof:name":"Vainoral",
    "wof:placetype":"locality"
},
  "geometry": {"coordinates":[-106.97528,25.083],"type":"Point"}
}