{
  "type": "Feature",
  "properties": {
    "gn:admin1_code":"24",
    "gn:admin2_code":"54.0",
    "gn:asciiname":"Cafetales",
    "gn:country_code":"MX",
    "gn:dem":416,
    "gn:feature_class":"P",
    "gn:feature_code":"PPL",
    "gn:name":"Cafetales",
    "gn:population":360,
    "gn:timezone":"America/Mexico_City",
    "iso:country":"MX",
    "wof:name":"Cafetales",
    "wof:placetype":"locality",
    "wof:population":360
},
  "geometry": {"coordinates":[-98.94944,21.33556],"type":"Point"}
}