{
  "type": "Feature",
  "properties": {
    "gn:admin1_code":"21",
    "gn:admin2_code":"140",
    "gn:asciiname":"Ocotitla",
    "gn:country_code":"MX",
    "gn:dem":2177,
    "gn:feature_class":"P",
    "gn:feature_code":"PPL",
    "gn:name":"Ocotitla",
    "gn:population":52,
    "gn:timezone":"America/Mexico_City",
    "iso:country":"MX",
    "wof:name":"Ocotitla",
    "wof:placetype":"locality",
    "wof:population":52
},
  "geometry": {"coordinates":[-98.38427,19.04587],"type":"Point"}
}