{
  "type": "Feature",
  "properties": {
    "gn:admin1_code":"24",
    "gn:admin2_code":"30.0",
    "gn:asciiname":"Las Cieneguitas",
    "gn:country_code":"MX",
    "gn:dem":1919,
    "gn:feature_class":"P",
    "gn:feature_code":"PPL",
    "gn:name":"Las Cieneguitas",
    "gn:population":8,
    "gn:timezone":"America/Mexico_City",
    "iso:country":"MX",
    "wof:name":"Las Cieneguitas",
    "wof:placetype":"locality",
    "wof:population":8
},
  "geometry": {"coordinates":[-100.54416999999999,22.00639],"type":"Point"}
}