{
  "type": "Feature",
  "properties": {
    "gn:admin1_code":"11.0",
    "gn:admin2_code":"33.0",
    "gn:asciiname":"San Javier",
    "gn:country_code":"MX",
    "gn:dem":1994,
    "gn:feature_class":"P",
    "gn:feature_code":"PPL",
    "gn:name":"San Javier",
    "gn:population":0,
    "gn:timezone":"America/Mexico_City",
    "iso:country":"MX",
    "name:ceb_x_preferred":[
        "San Javier"
    ],
    "name:deu_x_preferred":[
        "San Javier"
    ],
    "name:fra_x_preferred":[
        "San Javier"
    ],
    "name:ita_x_preferred":[
        "San Javier"
    ],
    "name:mlg_x_preferred":[
        "San Javier"
    ],
    "name:nld_x_preferred":[
        "San Javier"
    ],
    "name:pol_x_preferred":[
        "San Javier"
    ],
    "name:por_x_preferred":[
        "San Javier"
    ],
    "name:ron_x_preferred":[
        "San Javier"
    ],
    "name:rus_x_preferred":[
        "\u0421\u0430\u043d-\u0425\u0430\u0432\u044c\u0435\u0440"
    ],
    "name:sco_x_preferred":[
        "San Javier"
    ],
    "name:spa_x_preferred":[
        "San Javier"
    ],
    "name:spa_x_variant":[
        "San Cristobal"
    ],
    "name:swe_x_preferred":[
        "San Javier"
    ],
    "wof:name":"San Javier",
    "wof:placetype":"locality"
},
  "geometry": {"coordinates":[-100.64963,21.16015],"type":"Point"}
}