{
  "type": "Feature",
  "properties": {
    "gn:admin1_code":"26.0",
    "gn:admin2_code":"68.0",
    "gn:asciiname":"Adivino",
    "gn:country_code":"MX",
    "gn:dem":594,
    "gn:feature_class":"P",
    "gn:feature_code":"PPL",
    "gn:name":"Adivino",
    "gn:population":0,
    "gn:timezone":"America/Hermosillo",
    "iso:country":"MX",
    "name:und_x_variant":[
        "Rancho Adivino",
        "Adivino"
    ],
    "wof:name":"Adivino",
    "wof:placetype":"locality"
},
  "geometry": {"coordinates":[-110.03977999999999,28.97708],"type":"Point"}
}