{
  "type": "Feature",
  "properties": {
    "gn:admin1_code":"13",
    "gn:admin2_code":"79",
    "gn:asciiname":"Chinameca",
    "gn:country_code":"MX",
    "gn:dem":1202,
    "gn:feature_class":"P",
    "gn:feature_code":"PPL",
    "gn:name":"Chinameca",
    "gn:population":30,
    "gn:timezone":"America/Mexico_City",
    "iso:country":"MX",
    "name:ceb_x_preferred":[
        "Chinameca"
    ],
    "name:deu_x_preferred":[
        "Chinameca"
    ],
    "name:nld_x_preferred":[
        "Chinameca"
    ],
    "name:por_x_preferred":[
        "Chinameca"
    ],
    "name:spa_x_preferred":[
        "Chinameca"
    ],
    "name:swe_x_preferred":[
        "Chinameca"
    ],
    "wof:name":"Chinameca",
    "wof:placetype":"locality",
    "wof:population":30
},
  "geometry": {"coordinates":[-98.65271,20.75982],"type":"Point"}
}