{
  "type": "Feature",
  "properties": {
    "gn:admin1_code":"6",
    "gn:admin2_code":"13.0",
    "gn:asciiname":"Jaime",
    "gn:country_code":"MX",
    "gn:dem":2356,
    "gn:feature_class":"P",
    "gn:feature_code":"PPL",
    "gn:name":"Jaime",
    "gn:population":0,
    "gn:timezone":"America/Chihuahua",
    "iso:country":"MX",
    "name:deu_x_preferred":[
        "Jaime"
    ],
    "name:ita_x_preferred":[
        "Jaime"
    ],
    "name:jpn_x_preferred":[
        "\u30cf\u30a4\u30e1"
    ],
    "name:por_x_preferred":[
        "Jaime"
    ],
    "name:spa_x_preferred":[
        "Jaime"
    ],
    "name:ukr_x_preferred":[
        "\u0425\u0430\u0439\u043c\u0435"
    ],
    "wof:name":"Jaime",
    "wof:placetype":"locality"
},
  "geometry": {"coordinates":[-108.22156,29.92027],"type":"Point"}
}