{
  "type": "Feature",
  "properties": {
    "gn:admin1_code":"6",
    "gn:admin2_code":"13.0",
    "gn:asciiname":"Jaime",
    "gn:country_code":"MX",
    "gn:dem":2356,
    "gn:feature_class":"P",
    "gn:feature_code":"PPL",
    "gn:name":"Jaime",
    "gn:population":0,
    "gn:timezone":"America/Chihuahua",
    "iso:country":"MX",
    "name:spa_x_preferred":[
        "Jaime"
    ],
    "wof:name":"Jaime",
    "wof:placetype":"locality"
},
  "geometry": {"coordinates":[-108.22156,29.92027],"type":"Point"}
}