{
  "type": "Feature",
  "properties": {
    "gn:admin1_code":"10",
    "gn:admin2_code":"14",
    "gn:asciiname":"Las Botijas",
    "gn:country_code":"MX",
    "gn:dem":2090,
    "gn:feature_class":"P",
    "gn:feature_code":"PPL",
    "gn:name":"Las Botijas",
    "gn:population":42,
    "gn:timezone":"America/Monterrey",
    "iso:country":"MX",
    "wof:name":"Las Botijas",
    "wof:placetype":"locality",
    "wof:population":42
},
  "geometry": {"coordinates":[-104.79913000000001,22.77031],"type":"Point"}
}