{
  "type": "Feature",
  "properties": {
    "gn:admin1_code":"16",
    "gn:admin2_code":"15",
    "gn:asciiname":"La Parrilla",
    "gn:country_code":"MX",
    "gn:dem":1165,
    "gn:feature_class":"P",
    "gn:feature_code":"PPL",
    "gn:name":"La Parrilla",
    "gn:population":26,
    "gn:timezone":"America/Mexico_City",
    "iso:country":"MX",
    "name:arg_x_preferred":[
        "La Parrilla"
    ],
    "name:ast_x_preferred":[
        "La Parrilla"
    ],
    "name:cat_x_preferred":[
        "La Parrilla"
    ],
    "name:ceb_x_preferred":[
        "La Parrilla"
    ],
    "name:eus_x_preferred":[
        "La Parrilla"
    ],
    "name:fas_x_preferred":[
        "\u0644\u0627 \u067e\u0627\u0631\u06cc\u06cc\u0627"
    ],
    "name:fra_x_preferred":[
        "La Parrilla"
    ],
    "name:hun_x_preferred":[
        "La Parrilla"
    ],
    "name:hye_x_preferred":[
        "\u053c\u0561 \u054a\u0561\u057c\u056b\u056c\u0575\u0561"
    ],
    "name:ina_x_preferred":[
        "La Parrilla"
    ],
    "name:ita_x_preferred":[
        "La Parrilla"
    ],
    "name:msa_x_preferred":[
        "La Parrilla"
    ],
    "name:nld_x_preferred":[
        "La Parrilla"
    ],
    "name:oci_x_preferred":[
        "La Parrilla"
    ],
    "name:pol_x_preferred":[
        "La Parrilla"
    ],
    "name:por_x_preferred":[
        "La Parrilla"
    ],
    "name:rus_x_preferred":[
        "\u041b\u0430-\u041f\u0430\u0440\u0440\u0438\u043b\u044c\u044f"
    ],
    "name:spa_x_preferred":[
        "La Parrilla"
    ],
    "name:swe_x_preferred":[
        "La Parrilla"
    ],
    "name:ukr_x_preferred":[
        "\u041b\u0430-\u041f\u0430\u0440\u0440\u0456\u043b\u044c\u044f"
    ],
    "name:vie_x_preferred":[
        "La Parrilla"
    ],
    "name:war_x_preferred":[
        "La Parrilla"
    ],
    "name:zho_x_preferred":[
        "\u62c9\u5e15\u91cc\u5229\u4e9a"
    ],
    "wof:name":"La Parrilla",
    "wof:placetype":"locality",
    "wof:population":26
},
  "geometry": {"coordinates":[-103.1075,18.78306],"type":"Point"}
}