{
  "type": "Feature",
  "properties": {
    "gn:admin1_code":"16",
    "gn:admin2_code":"15",
    "gn:asciiname":"La Parrilla",
    "gn:country_code":"MX",
    "gn:dem":1165,
    "gn:feature_class":"P",
    "gn:feature_code":"PPL",
    "gn:name":"La Parrilla",
    "gn:population":26,
    "gn:timezone":"America/Mexico_City",
    "iso:country":"MX",
    "wof:name":"La Parrilla",
    "wof:placetype":"locality",
    "wof:population":26
},
  "geometry": {"coordinates":[-103.1075,18.78306],"type":"Point"}
}