{
  "type": "Feature",
  "properties": {
    "gn:admin1_code":"5",
    "gn:admin2_code":"97.0",
    "gn:asciiname":"El Otate",
    "gn:country_code":"MX",
    "gn:dem":6,
    "gn:feature_class":"P",
    "gn:feature_code":"PPL",
    "gn:name":"El Otate",
    "gn:population":0,
    "gn:timezone":"America/Mexico_City",
    "iso:country":"MX",
    "name:spa_x_preferred":[
        "El Otate"
    ],
    "name:und_x_variant":[
        "Otates"
    ],
    "wof:name":"El Otate",
    "wof:placetype":"locality"
},
  "geometry": {"coordinates":[-93.51787,15.75277],"type":"Point"}
}