{
  "type": "Feature",
  "properties": {
    "gn:admin1_code":"12",
    "gn:admin2_code":"27",
    "gn:asciiname":"Las Latas",
    "gn:country_code":"MX",
    "gn:dem":481,
    "gn:feature_class":"P",
    "gn:feature_code":"PPL",
    "gn:name":"Las Latas",
    "gn:population":15,
    "gn:timezone":"America/Mexico_City",
    "iso:country":"MX",
    "wof:name":"Las Latas",
    "wof:placetype":"locality",
    "wof:population":15
},
  "geometry": {"coordinates":[-100.47132999999999,18.75676],"type":"Point"}
}