{
  "type": "Feature",
  "properties": {
    "gn:admin1_code":"20.0",
    "gn:admin2_code":"12.0",
    "gn:asciiname":"Santa Maria Tepexilpana",
    "gn:country_code":"MX",
    "gn:dem":812,
    "gn:feature_class":"P",
    "gn:feature_code":"PPL",
    "gn:name":"Santa Mar\u00eda Tepexilpana",
    "gn:population":0,
    "gn:timezone":"America/Mexico_City",
    "iso:country":"MX",
    "name:spa_x_preferred":[
        "Santa Mar\u00eda Tepexilpana"
    ],
    "wof:name":"Santa Maria Tepexilpana",
    "wof:placetype":"locality"
},
  "geometry": {"coordinates":[-96.52469000000001,15.90338],"type":"Point"}
}