{
  "type": "Feature",
  "properties": {
    "gn:admin1_code":"12",
    "gn:admin2_code":"55.0",
    "gn:asciiname":"El Ejido (Ejido Guerrero)",
    "gn:country_code":"MX",
    "gn:dem":1327,
    "gn:feature_class":"P",
    "gn:feature_code":"PPL",
    "gn:name":"El Ejido (Ejido Guerrero)",
    "gn:population":701,
    "gn:timezone":"America/Mexico_City",
    "iso:country":"MX",
    "wof:name":"El Ejido (Ejido Guerrero)",
    "wof:placetype":"locality",
    "wof:population":701
},
  "geometry": {"coordinates":[-99.60361,18.50361],"type":"Point"}
}