{
  "type": "Feature",
  "properties": {
    "gn:admin1_code":"19",
    "gn:admin2_code":"6.0",
    "gn:asciiname":"Artemio Trevino",
    "gn:country_code":"MX",
    "gn:dem":401,
    "gn:feature_class":"P",
    "gn:feature_code":"PPL",
    "gn:name":"Artemio Trevi\u00f1o",
    "gn:population":1756,
    "gn:timezone":"America/Monterrey",
    "iso:country":"MX",
    "name:und_x_variant":[
        "Artemio Trevi\u00f1o"
    ],
    "wof:name":"Artemio Trevino",
    "wof:placetype":"locality",
    "wof:population":1756
},
  "geometry": {"coordinates":[-100.14278,25.83528],"type":"Point"}
}