{
  "type": "Feature",
  "properties": {
    "gn:admin1_code":"16.0",
    "gn:admin2_code":"95.0",
    "gn:asciiname":"Las Agrillas",
    "gn:country_code":"MX",
    "gn:dem":1172,
    "gn:feature_class":"P",
    "gn:feature_code":"PPL",
    "gn:name":"Las Agrillas",
    "gn:population":0,
    "gn:timezone":"America/Mexico_City",
    "iso:country":"MX",
    "name:spa_x_preferred":[
        "Las Agrillas"
    ],
    "wof:name":"Las Agrillas",
    "wof:placetype":"locality"
},
  "geometry": {"coordinates":[-102.60366,19.59838],"type":"Point"}
}