{
  "type": "Feature",
  "properties": {
    "gn:admin1_code":"32",
    "gn:admin2_code":"26.0",
    "gn:asciiname":"La Piedad",
    "gn:country_code":"MX",
    "gn:dem":1767,
    "gn:feature_class":"P",
    "gn:feature_code":"PPL",
    "gn:name":"La Piedad",
    "gn:population":0,
    "gn:timezone":"America/Mexico_City",
    "iso:country":"MX",
    "name:spa_x_preferred":[
        "La Piedad"
    ],
    "wof:name":"La Piedad",
    "wof:placetype":"locality"
},
  "geometry": {"coordinates":[-102.2392,24.5626],"type":"Point"}
}