{
  "type": "Feature",
  "properties": {
    "gn:admin1_code":"26",
    "gn:admin2_code":"39.0",
    "gn:asciiname":"Mina de Oro",
    "gn:country_code":"MX",
    "gn:dem":1534,
    "gn:feature_class":"P",
    "gn:feature_code":"PPL",
    "gn:name":"Mina de Oro",
    "gn:population":0,
    "gn:timezone":"America/Hermosillo",
    "iso:country":"MX",
    "name:spa_x_preferred":[
        "Mina de Oro"
    ],
    "name:und_x_variant":[
        "Rancho Mina Oro",
        "Mina Oro"
    ],
    "wof:name":"Mina de Oro",
    "wof:placetype":"locality"
},
  "geometry": {"coordinates":[-109.92305,31.25366],"type":"Point"}
}