{
  "type": "Feature",
  "properties": {
    "gn:admin1_code":"7",
    "gn:admin2_code":"4.0",
    "gn:asciiname":"El Carmen (Las Vigas)",
    "gn:country_code":"MX",
    "gn:dem":2273,
    "gn:feature_class":"P",
    "gn:feature_code":"PPL",
    "gn:name":"El Carmen (Las Vigas)",
    "gn:population":29,
    "gn:timezone":"America/Monterrey",
    "iso:country":"MX",
    "wof:name":"El Carmen (Las Vigas)",
    "wof:placetype":"locality",
    "wof:population":29
},
  "geometry": {"coordinates":[-100.62335,25.48535],"type":"Point"}
}