{
  "type": "Feature",
  "properties": {
    "gn:admin1_code":"19",
    "gn:admin2_code":"38.0",
    "gn:asciiname":"Las Canas",
    "gn:country_code":"MX",
    "gn:dem":442,
    "gn:feature_class":"P",
    "gn:feature_code":"PPL",
    "gn:name":"Las Ca\u00f1as",
    "gn:population":0,
    "gn:timezone":"America/Monterrey",
    "iso:country":"MX",
    "name:spa_x_preferred":[
        "Las Ca\u00f1as"
    ],
    "wof:name":"Las Canas",
    "wof:placetype":"locality"
},
  "geometry": {"coordinates":[-99.91652000000001,25.24152],"type":"Point"}
}