{
  "type": "Feature",
  "properties": {
    "gn:admin1_code":"14",
    "gn:admin2_code":"46",
    "gn:asciiname":"Santa Elena",
    "gn:country_code":"MX",
    "gn:dem":1791,
    "gn:feature_class":"P",
    "gn:feature_code":"PPL",
    "gn:name":"Santa Elena",
    "gn:population":21,
    "gn:timezone":"America/Mexico_City",
    "iso:country":"MX",
    "wof:name":"Santa Elena",
    "wof:placetype":"locality",
    "wof:population":21
},
  "geometry": {"coordinates":[-102.48083,21.31861],"type":"Point"}
}