{
  "type": "Feature",
  "properties": {
    "gn:admin1_code":"15",
    "gn:admin2_code":"123.0",
    "gn:asciiname":"Alborejo (Puerto Alborejo)",
    "gn:country_code":"MX",
    "gn:dem":1204,
    "gn:feature_class":"P",
    "gn:feature_code":"PPL",
    "gn:name":"Alborejo (Puerto Alborejo)",
    "gn:population":174,
    "gn:timezone":"America/Mexico_City",
    "iso:country":"MX",
    "wof:name":"Alborejo (Puerto Alborejo)",
    "wof:placetype":"locality",
    "wof:population":174
},
  "geometry": {"coordinates":[-100.29452000000001,18.99896],"type":"Point"}
}