{
  "type": "Feature",
  "properties": {
    "gn:admin1_code":"20",
    "gn:admin2_code":"73.0",
    "gn:asciiname":"Paraje Perez",
    "gn:country_code":"MX",
    "gn:dem":1055,
    "gn:feature_class":"P",
    "gn:feature_code":"PPL",
    "gn:name":"Paraje P\u00e9rez",
    "gn:population":0,
    "gn:timezone":"America/Mexico_City",
    "iso:country":"MX",
    "name:spa_x_preferred":[
        "Paraje P\u00e9rez"
    ],
    "wof:name":"Paraje Perez",
    "wof:placetype":"locality"
},
  "geometry": {"coordinates":[-97.88399,17.10079],"type":"Point"}
}