{
  "type": "Feature",
  "properties": {
    "gn:admin1_code":"11.0",
    "gn:admin2_code":"25.0",
    "gn:asciiname":"Los Girasoles",
    "gn:country_code":"MX",
    "gn:dem":1786,
    "gn:feature_class":"P",
    "gn:feature_code":"PPL",
    "gn:name":"Los Girasoles",
    "gn:population":0,
    "gn:timezone":"America/Mexico_City",
    "iso:country":"MX",
    "name:spa_x_preferred":[
        "Los Girasoles"
    ],
    "wof:name":"Los Girasoles",
    "wof:placetype":"locality"
},
  "geometry": {"coordinates":[-101.88287,21.04779],"type":"Point"}
}