{
  "type": "Feature",
  "properties": {
    "gn:admin1_code":"20",
    "gn:admin2_code":"403.0",
    "gn:asciiname":"Paraje Loma de Lucero",
    "gn:country_code":"MX",
    "gn:dem":1532,
    "gn:feature_class":"P",
    "gn:feature_code":"PPL",
    "gn:name":"Paraje Loma de Lucero",
    "gn:population":75,
    "gn:timezone":"America/Mexico_City",
    "iso:country":"MX",
    "wof:name":"Paraje Loma de Lucero",
    "wof:placetype":"locality",
    "wof:population":75
},
  "geometry": {"coordinates":[-96.70611,16.97611],"type":"Point"}
}