{
  "type": "Feature",
  "properties": {
    "gn:admin1_code":"28",
    "gn:admin2_code":"34.0",
    "gn:asciiname":"Nuevo Prado (San Juanito)",
    "gn:country_code":"MX",
    "gn:dem":363,
    "gn:feature_class":"P",
    "gn:feature_code":"PPL",
    "gn:name":"Nuevo Prado (San Juanito)",
    "gn:population":68,
    "gn:timezone":"America/Monterrey",
    "iso:country":"MX",
    "wof:name":"Nuevo Prado (San Juanito)",
    "wof:placetype":"locality",
    "wof:population":68
},
  "geometry": {"coordinates":[-99.06583000000001,24.46222],"type":"Point"}
}