{
  "type": "Feature",
  "properties": {
    "gn:admin1_code":"14",
    "gn:admin2_code":"15.0",
    "gn:asciiname":"Cruz de Palo (Las Palmas)",
    "gn:country_code":"MX",
    "gn:dem":884,
    "gn:feature_class":"P",
    "gn:feature_code":"PPL",
    "gn:name":"Cruz de Palo (Las Palmas)",
    "gn:population":6,
    "gn:timezone":"America/Mexico_City",
    "iso:country":"MX",
    "wof:name":"Cruz de Palo (Las Palmas)",
    "wof:placetype":"locality",
    "wof:population":6
},
  "geometry": {"coordinates":[-104.28528,19.77139],"type":"Point"}
}