{
  "type": "Feature",
  "properties": {
    "gn:admin1_code":"20",
    "gn:admin2_code":"2.0",
    "gn:asciiname":"La Martinica",
    "gn:country_code":"MX",
    "gn:dem":129,
    "gn:feature_class":"P",
    "gn:feature_code":"PPL",
    "gn:name":"La Martinica",
    "gn:population":0,
    "gn:timezone":"America/Mexico_City",
    "iso:country":"MX",
    "name:spa_x_preferred":[
        "La Martinica"
    ],
    "wof:name":"La Martinica",
    "wof:placetype":"locality"
},
  "geometry": {"coordinates":[-96.55427,18.5169],"type":"Point"}
}