{
  "type": "Feature",
  "properties": {
    "gn:admin1_code":"32.0",
    "gn:admin2_code":"10.0",
    "gn:asciiname":"Yerbanis",
    "gn:country_code":"MX",
    "gn:dem":2077,
    "gn:feature_class":"P",
    "gn:feature_code":"PPL",
    "gn:name":"Yerbanis",
    "gn:population":0,
    "gn:timezone":"America/Mexico_City",
    "iso:country":"MX",
    "name:und_x_variant":[
        "El Yerban\u00eds"
    ],
    "wof:name":"Yerbanis",
    "wof:placetype":"locality"
},
  "geometry": {"coordinates":[-102.70993,23.12523],"type":"Point"}
}