{
  "type": "Feature",
  "properties": {
    "gn:admin1_code":"14",
    "gn:admin2_code":"106.0",
    "gn:asciiname":"Temazcal",
    "gn:country_code":"MX",
    "gn:dem":1040,
    "gn:feature_class":"P",
    "gn:feature_code":"PPL",
    "gn:name":"Temazcal",
    "gn:population":0,
    "gn:timezone":"America/Mexico_City",
    "iso:country":"MX",
    "name:deu_x_preferred":[
        "Temazcal"
    ],
    "name:fin_x_preferred":[
        "Temascal"
    ],
    "name:fra_x_preferred":[
        "Temazcal"
    ],
    "name:hun_x_preferred":[
        "Temazcal"
    ],
    "name:ita_x_preferred":[
        "Temazcal"
    ],
    "name:jpn_x_preferred":[
        "\u30c6\u30de\u30b9\u30ab\u30eb"
    ],
    "name:nah_x_preferred":[
        "Temazcalli"
    ],
    "name:nld_x_preferred":[
        "Temazcal"
    ],
    "name:nor_x_preferred":[
        "Temazcal"
    ],
    "name:por_x_preferred":[
        "Temazcal"
    ],
    "name:spa_x_preferred":[
        "Temazcal"
    ],
    "name:swe_x_preferred":[
        "Temascal"
    ],
    "wof:name":"Temazcal",
    "wof:placetype":"locality"
},
  "geometry": {"coordinates":[-104.10456000000001,19.73271],"type":"Point"}
}