{
  "type": "Feature",
  "properties": {
    "gn:admin1_code":"14",
    "gn:admin2_code":"106.0",
    "gn:asciiname":"Temazcal",
    "gn:country_code":"MX",
    "gn:dem":1040,
    "gn:feature_class":"P",
    "gn:feature_code":"PPL",
    "gn:name":"Temazcal",
    "gn:population":0,
    "gn:timezone":"America/Mexico_City",
    "iso:country":"MX",
    "wof:name":"Temazcal",
    "wof:placetype":"locality"
},
  "geometry": {"coordinates":[-104.10456000000001,19.73271],"type":"Point"}
}