{
  "type": "Feature",
  "properties": {
    "gn:admin1_code":"7",
    "gn:admin2_code":"11.0",
    "gn:asciiname":"La Noria",
    "gn:country_code":"MX",
    "gn:dem":1695,
    "gn:feature_class":"P",
    "gn:feature_code":"PPL",
    "gn:name":"La Noria",
    "gn:population":11,
    "gn:timezone":"America/Monterrey",
    "iso:country":"MX",
    "wof:name":"La Noria",
    "wof:placetype":"locality",
    "wof:population":11
},
  "geometry": {"coordinates":[-101.3892,25.29864],"type":"Point"}
}