{
  "type": "Feature",
  "properties": {
    "gn:admin1_code":"32",
    "gn:admin2_code":"20.0",
    "gn:asciiname":"Morelos (El Nino Jesus)",
    "gn:country_code":"MX",
    "gn:dem":2009,
    "gn:feature_class":"P",
    "gn:feature_code":"PPL",
    "gn:name":"Morelos (El Ni\u00f1o Jes\u00fas)",
    "gn:population":87,
    "gn:timezone":"America/Mexico_City",
    "iso:country":"MX",
    "name:und_x_variant":[
        "Morelos (El Ni\u00f1o Jes\u00fas)"
    ],
    "wof:name":"Morelos (El Nino Jesus)",
    "wof:placetype":"locality",
    "wof:population":87
},
  "geometry": {"coordinates":[-102.99889,22.55778],"type":"Point"}
}