{
  "type": "Feature",
  "properties": {
    "gn:admin1_code":"30",
    "gn:admin2_code":"44.0",
    "gn:asciiname":"La Lagunilla",
    "gn:country_code":"MX",
    "gn:dem":1149,
    "gn:feature_class":"P",
    "gn:feature_code":"PPL",
    "gn:name":"La Lagunilla",
    "gn:population":455,
    "gn:timezone":"America/Mexico_City",
    "iso:country":"MX",
    "wof:name":"La Lagunilla",
    "wof:placetype":"locality",
    "wof:population":455
},
  "geometry": {"coordinates":[-96.94389,18.96306],"type":"Point"}
}