{
  "type": "Feature",
  "properties": {
    "gn:admin1_code":"12",
    "gn:admin2_code":"81.0",
    "gn:asciiname":"El Aserradero",
    "gn:country_code":"MX",
    "gn:dem":926,
    "gn:feature_class":"P",
    "gn:feature_code":"PPL",
    "gn:name":"El Aserradero",
    "gn:population":561,
    "gn:timezone":"America/Mexico_City",
    "iso:country":"MX",
    "wof:name":"El Aserradero",
    "wof:placetype":"locality",
    "wof:population":561
},
  "geometry": {"coordinates":[-98.66806,17.00667],"type":"Point"}
}