{
  "type": "Feature",
  "properties": {
    "gn:admin1_code":"12",
    "gn:admin2_code":"43.0",
    "gn:asciiname":"El Coyul",
    "gn:country_code":"MX",
    "gn:dem":935,
    "gn:feature_class":"P",
    "gn:feature_code":"PPL",
    "gn:name":"El Coyul",
    "gn:population":988,
    "gn:timezone":"America/Mexico_City",
    "iso:country":"MX",
    "wof:name":"El Coyul",
    "wof:placetype":"locality",
    "wof:population":988
},
  "geometry": {"coordinates":[-98.25278,17.05833],"type":"Point"}
}