{
  "type": "Feature",
  "properties": {
    "gn:admin1_code":"5",
    "gn:admin2_code":"52.0",
    "gn:asciiname":"Plan Rio Azul",
    "gn:country_code":"MX",
    "gn:dem":372,
    "gn:feature_class":"P",
    "gn:feature_code":"PPL",
    "gn:name":"Plan R\u00edo Azul",
    "gn:population":348,
    "gn:timezone":"America/Mexico_City",
    "iso:country":"MX",
    "name:und_x_variant":[
        "Plan R\u00edo Azul"
    ],
    "wof:name":"Plan Rio Azul",
    "wof:placetype":"locality",
    "wof:population":348
},
  "geometry": {"coordinates":[-91.34028000000001,16.08333],"type":"Point"}
}