{
  "type": "Feature",
  "properties": {
    "gn:admin1_code":"7",
    "gn:admin2_code":"33",
    "gn:asciiname":"El Pinto",
    "gn:country_code":"MX",
    "gn:dem":890,
    "gn:feature_class":"P",
    "gn:feature_code":"PPL",
    "gn:name":"El Pinto",
    "gn:population":16,
    "gn:timezone":"America/Monterrey",
    "iso:country":"MX",
    "wof:name":"El Pinto",
    "wof:placetype":"locality",
    "wof:population":16
},
  "geometry": {"coordinates":[-102.79898,26.24305],"type":"Point"}
}