{
  "type": "Feature",
  "properties": {
    "gn:admin1_code":"14.0",
    "gn:admin2_code":"61.0",
    "gn:asciiname":"El Tabaco",
    "gn:country_code":"MX",
    "gn:dem":2072,
    "gn:feature_class":"P",
    "gn:feature_code":"PPL",
    "gn:name":"El Tabaco",
    "gn:population":0,
    "gn:timezone":"America/Mexico_City",
    "iso:country":"MX",
    "name:spa_x_preferred":[
        "El Tabaco"
    ],
    "wof:name":"El Tabaco",
    "wof:placetype":"locality"
},
  "geometry": {"coordinates":[-104.00396000000001,22.13097],"type":"Point"}
}