{
  "type": "Feature",
  "properties": {
    "gn:admin1_code":"27",
    "gn:admin2_code":"6.0",
    "gn:asciiname":"Hormiguero",
    "gn:country_code":"MX",
    "gn:dem":10,
    "gn:feature_class":"P",
    "gn:feature_code":"PPL",
    "gn:name":"Hormiguero",
    "gn:population":0,
    "gn:timezone":"America/Mexico_City",
    "iso:country":"MX",
    "name:ceb_x_preferred":[
        "Hormiguero"
    ],
    "name:hun_x_preferred":[
        "Hormiguero"
    ],
    "name:spa_x_preferred":[
        "Hormiguero"
    ],
    "name:swe_x_preferred":[
        "Hormiguero"
    ],
    "wof:name":"Hormiguero",
    "wof:placetype":"locality"
},
  "geometry": {"coordinates":[-93.08333,18.03333],"type":"Point"}
}