{
  "type": "Feature",
  "properties": {
    "gn:admin1_code":"16",
    "gn:admin2_code":"38.0",
    "gn:asciiname":"El Limon de los Garcia",
    "gn:country_code":"MX",
    "gn:dem":221,
    "gn:feature_class":"P",
    "gn:feature_code":"PPL",
    "gn:name":"El Lim\u00f3n de los Garc\u00eda",
    "gn:population":81,
    "gn:timezone":"America/Mexico_City",
    "iso:country":"MX",
    "name:und_x_variant":[
        "El Lim\u00f3n de los Garc\u00eda"
    ],
    "wof:name":"El Limon de los Garcia",
    "wof:placetype":"locality",
    "wof:population":81
},
  "geometry": {"coordinates":[-100.91500000000001,18.47944],"type":"Point"}
}