{
  "type": "Feature",
  "properties": {
    "gn:admin1_code":"1",
    "gn:admin2_code":"2",
    "gn:asciiname":"Sector de Produccion el Chamizal",
    "gn:country_code":"MX",
    "gn:dem":2043,
    "gn:feature_class":"P",
    "gn:feature_code":"PPL",
    "gn:name":"Sector de Producci\u00f3n el Chamizal",
    "gn:population":11,
    "gn:timezone":"America/Mexico_City",
    "iso:country":"MX",
    "name:und_x_variant":[
        "Sector de Producci\u00f3n el Chamizal"
    ],
    "wof:name":"Sector de Produccion el Chamizal",
    "wof:placetype":"locality",
    "wof:population":11
},
  "geometry": {"coordinates":[-102.05583,22.29111],"type":"Point"}
}