{
  "type": "Feature",
  "properties": {
    "gn:admin1_code":"2",
    "gn:admin2_code":"4.0",
    "gn:asciiname":"San Isidro",
    "gn:country_code":"MX",
    "gn:dem":186,
    "gn:feature_class":"P",
    "gn:feature_code":"PPL",
    "gn:name":"San Isidro",
    "gn:population":7,
    "gn:timezone":"America/Tijuana",
    "iso:country":"MX",
    "name:spa_x_preferred":[
        "San Isidro"
    ],
    "name:und_x_variant":[
        "Rancho San Isidro Ajolojol"
    ],
    "wof:name":"San Isidro",
    "wof:placetype":"locality",
    "wof:population":7
},
  "geometry": {"coordinates":[-116.78928000000001,32.54037],"type":"Point"}
}