{
  "type": "Feature",
  "properties": {
    "gn:admin1_code":"32",
    "gn:admin2_code":"49.0",
    "gn:asciiname":"Chiltepec",
    "gn:country_code":"MX",
    "gn:dem":1091,
    "gn:feature_class":"P",
    "gn:feature_code":"PPL",
    "gn:name":"Chiltepec",
    "gn:population":0,
    "gn:timezone":"America/Mexico_City",
    "iso:country":"MX",
    "name:spa_x_preferred":[
        "Chiltepec"
    ],
    "name:und_x_variant":[
        "Palo Hueco"
    ],
    "wof:name":"Chiltepec",
    "wof:placetype":"locality"
},
  "geometry": {"coordinates":[-104.05789,22.71643],"type":"Point"}
}