{
  "type": "Feature",
  "properties": {
    "gn:admin1_code":"11.0",
    "gn:admin2_code":"14.0",
    "gn:asciiname":"Ex-Hacienda la California",
    "gn:country_code":"MX",
    "gn:dem":1992,
    "gn:feature_class":"P",
    "gn:feature_code":"PPL",
    "gn:name":"Ex-Hacienda la California",
    "gn:population":0,
    "gn:timezone":"America/Mexico_City",
    "iso:country":"MX",
    "name:spa_x_preferred":[
        "Ex-Hacienda la California"
    ],
    "wof:name":"Ex-Hacienda la California",
    "wof:placetype":"locality"
},
  "geometry": {"coordinates":[-100.83221,21.2827],"type":"Point"}
}