{
  "type": "Feature",
  "properties": {
    "gn:admin1_code":"15.0",
    "gn:admin2_code":"114.0",
    "gn:asciiname":"El Atole",
    "gn:country_code":"MX",
    "gn:dem":2755,
    "gn:feature_class":"P",
    "gn:feature_code":"PPL",
    "gn:name":"El Atole",
    "gn:population":0,
    "gn:timezone":"America/Mexico_City",
    "iso:country":"MX",
    "name:spa_x_preferred":[
        "El Atole"
    ],
    "wof:name":"El Atole",
    "wof:placetype":"locality"
},
  "geometry": {"coordinates":[-100.12354999999999,19.52041],"type":"Point"}
}