{
  "type": "Feature",
  "properties": {
    "gn:admin1_code":"28.0",
    "gn:admin2_code":"21.0",
    "gn:asciiname":"La Servilleta",
    "gn:country_code":"MX",
    "gn:dem":98,
    "gn:feature_class":"P",
    "gn:feature_code":"PPL",
    "gn:name":"La Servilleta",
    "gn:population":6,
    "gn:timezone":"America/Monterrey",
    "iso:country":"MX",
    "name:spa_x_preferred":[
        "La Servilleta"
    ],
    "wof:name":"La Servilleta",
    "wof:placetype":"locality",
    "wof:population":6
},
  "geometry": {"coordinates":[-99.11987999999999,22.85232],"type":"Point"}
}