{
  "type": "Feature",
  "properties": {
    "gn:admin1_code":"32",
    "gn:admin2_code":"29.0",
    "gn:asciiname":"Jose Maria Morelos",
    "gn:country_code":"MX",
    "gn:dem":2323,
    "gn:feature_class":"P",
    "gn:feature_code":"PPL",
    "gn:name":"Jos\u00e9 Mar\u00eda Morelos",
    "gn:population":0,
    "gn:timezone":"America/Mexico_City",
    "iso:country":"MX",
    "name:spa_x_preferred":[
        "Jos\u00e9 Mar\u00eda Morelos"
    ],
    "name:spa_x_variant":[
        "El Venadito"
    ],
    "wof:name":"Jose Maria Morelos",
    "wof:placetype":"locality"
},
  "geometry": {"coordinates":[-103.6962,24.03028],"type":"Point"}
}