{
  "type": "Feature",
  "properties": {
    "gn:admin1_code":"30",
    "gn:admin2_code":"3",
    "gn:asciiname":"Manuel de Jesus Prieto",
    "gn:country_code":"MX",
    "gn:dem":182,
    "gn:feature_class":"P",
    "gn:feature_code":"PPL",
    "gn:name":"Manuel de Jes\u00fas Prieto",
    "gn:population":18,
    "gn:timezone":"America/Mexico_City",
    "iso:country":"MX",
    "name:und_x_variant":[
        "Manuel de Jes\u00fas Prieto"
    ],
    "wof:name":"Manuel de Jesus Prieto",
    "wof:placetype":"locality",
    "wof:population":18
},
  "geometry": {"coordinates":[-94.995,18.05333],"type":"Point"}
}