{
  "type": "Feature",
  "properties": {
    "gn:admin1_code":"10.0",
    "gn:admin2_code":"9.0",
    "gn:asciiname":"Zape Chico",
    "gn:country_code":"MX",
    "gn:dem":1958,
    "gn:feature_class":"P",
    "gn:feature_code":"PPL",
    "gn:name":"Zape Chico",
    "gn:population":0,
    "gn:timezone":"America/Monterrey",
    "iso:country":"MX",
    "name:und_x_variant":[
        "El Zape Chico"
    ],
    "wof:name":"Zape Chico",
    "wof:placetype":"locality"
},
  "geometry": {"coordinates":[-105.7921,25.81283],"type":"Point"}
}