{
  "type": "Feature",
  "properties": {
    "gn:admin1_code":"26",
    "gn:admin2_code":"33.0",
    "gn:asciiname":"La Pitahaya",
    "gn:country_code":"MX",
    "gn:dem":10,
    "gn:feature_class":"P",
    "gn:feature_code":"PPL",
    "gn:name":"La Pitahaya",
    "gn:population":0,
    "gn:timezone":"America/Hermosillo",
    "iso:country":"MX",
    "name:spa_x_preferred":[
        "La Pitahaya"
    ],
    "name:und_x_variant":[
        "Rancho Pitahaya"
    ],
    "wof:name":"La Pitahaya",
    "wof:placetype":"locality"
},
  "geometry": {"coordinates":[-109.5461,26.82327],"type":"Point"}
}