{
  "type": "Feature",
  "properties": {
    "gn:admin1_code":"32",
    "gn:admin2_code":"14.0",
    "gn:asciiname":"Los Santos Ninos",
    "gn:country_code":"MX",
    "gn:dem":1830,
    "gn:feature_class":"P",
    "gn:feature_code":"PPL",
    "gn:name":"Los Santos Ni\u00f1os",
    "gn:population":6,
    "gn:timezone":"America/Mexico_City",
    "iso:country":"MX",
    "name:und_x_variant":[
        "Los Santos Ni\u00f1os"
    ],
    "wof:name":"Los Santos Ninos",
    "wof:placetype":"locality",
    "wof:population":6
},
  "geometry": {"coordinates":[-102.7975,24.23833],"type":"Point"}
}