{
  "type": "Feature",
  "properties": {
    "gn:admin1_code":"26.0",
    "gn:admin2_code":"69.0",
    "gn:asciiname":"Carricitos",
    "gn:country_code":"MX",
    "gn:dem":734,
    "gn:feature_class":"P",
    "gn:feature_code":"PPL",
    "gn:name":"Carricitos",
    "gn:population":0,
    "gn:timezone":"America/Hermosillo",
    "iso:country":"MX",
    "name:spa_x_preferred":[
        "Carricitos"
    ],
    "wof:name":"Carricitos",
    "wof:placetype":"locality"
},
  "geometry": {"coordinates":[-109.23497,28.46895],"type":"Point"}
}