{
  "type": "Feature",
  "properties": {
    "gn:admin1_code":"22",
    "gn:admin2_code":"18",
    "gn:asciiname":"El Mezquite",
    "gn:country_code":"MX",
    "gn:dem":1573,
    "gn:feature_class":"P",
    "gn:feature_code":"PPL",
    "gn:name":"El Mezquite",
    "gn:population":43,
    "gn:timezone":"America/Mexico_City",
    "iso:country":"MX",
    "wof:name":"El Mezquite",
    "wof:placetype":"locality",
    "wof:population":43
},
  "geometry": {"coordinates":[-99.935,20.90583],"type":"Point"}
}