{
  "type": "Feature",
  "properties": {
    "gn:admin1_code":"30",
    "gn:admin2_code":"77",
    "gn:asciiname":"Angel Rodriguez",
    "gn:country_code":"MX",
    "gn:dem":33,
    "gn:feature_class":"P",
    "gn:feature_code":"PPL",
    "gn:name":"\u00c1ngel Rodr\u00edguez",
    "gn:population":10,
    "gn:timezone":"America/Mexico_City",
    "iso:country":"MX",
    "name:und_x_variant":[
        "\u00c1ngel Rodr\u00edguez"
    ],
    "wof:name":"Angel Rodriguez",
    "wof:placetype":"locality",
    "wof:population":10
},
  "geometry": {"coordinates":[-95.56722000000001,18.01861],"type":"Point"}
}