{
  "type": "Feature",
  "properties": {
    "gn:admin1_code":"16",
    "gn:admin2_code":"44",
    "gn:asciiname":"La Jabonera",
    "gn:country_code":"MX",
    "gn:dem":1937,
    "gn:feature_class":"P",
    "gn:feature_code":"PPL",
    "gn:name":"La Jabonera",
    "gn:population":12,
    "gn:timezone":"America/Mexico_City",
    "iso:country":"MX",
    "wof:name":"La Jabonera",
    "wof:placetype":"locality",
    "wof:population":12
},
  "geometry": {"coordinates":[-101.76667,19.92917000000001],"type":"Point"}
}