{
  "type": "Feature",
  "properties": {
    "gn:admin1_code":"24",
    "gn:admin2_code":"38.0",
    "gn:asciiname":"El Huexco",
    "gn:country_code":"MX",
    "gn:dem":121,
    "gn:feature_class":"P",
    "gn:feature_code":"PPL",
    "gn:name":"El Huexco",
    "gn:population":0,
    "gn:timezone":"America/Mexico_City",
    "iso:country":"MX",
    "name:spa_x_preferred":[
        "El Huexco"
    ],
    "name:und_x_variant":[
        "Huaxuco",
        "Huexco"
    ],
    "wof:name":"El Huexco",
    "wof:placetype":"locality"
},
  "geometry": {"coordinates":[-98.7535,21.34075],"type":"Point"}
}