{
  "type": "Feature",
  "properties": {
    "gn:admin1_code":"5",
    "gn:admin2_code":"61.0",
    "gn:asciiname":"Jose Maria Morelos y Pavon",
    "gn:country_code":"MX",
    "gn:dem":751,
    "gn:feature_class":"P",
    "gn:feature_code":"PPL",
    "gn:name":"Jos\u00e9 Mar\u00eda Morelos y Pav\u00f3n",
    "gn:population":341,
    "gn:timezone":"America/Mexico_City",
    "iso:country":"MX",
    "name:und_x_variant":[
        "Jos\u00e9 Mar\u00eda Morelos y Pav\u00f3n"
    ],
    "wof:name":"Jose Maria Morelos y Pavon",
    "wof:placetype":"locality",
    "wof:population":341
},
  "geometry": {"coordinates":[-93.53639,17.08194],"type":"Point"}
}