{
  "type": "Feature",
  "properties": {
    "gn:admin1_code":"22.0",
    "gn:asciiname":"Militar",
    "gn:country_code":"MX",
    "gn:dem":1899,
    "gn:feature_class":"P",
    "gn:feature_code":"PPL",
    "gn:name":"Militar",
    "gn:population":0,
    "gn:timezone":"America/Mexico_City",
    "iso:country":"MX",
    "name:spa_x_preferred":[
        "Militar"
    ],
    "wof:name":"Militar",
    "wof:placetype":"locality"
},
  "geometry": {"coordinates":[-99.99236000000001,20.46549],"type":"Point"}
}