{
  "type": "Feature",
  "properties": {
    "gn:admin1_code":"14.0",
    "gn:admin2_code":"20.0",
    "gn:asciiname":"Malubaco",
    "gn:country_code":"MX",
    "gn:dem":616,
    "gn:feature_class":"P",
    "gn:feature_code":"PPL",
    "gn:name":"Malubaco",
    "gn:population":0,
    "gn:timezone":"America/Mexico_City",
    "iso:country":"MX",
    "name:spa_x_preferred":[
        "Malubaco"
    ],
    "wof:name":"Malubaco",
    "wof:placetype":"locality"
},
  "geometry": {"coordinates":[-105.45899,20.43806],"type":"Point"}
}