{
  "type": "Feature",
  "properties": {
    "gn:admin1_code":"24",
    "gn:admin2_code":"21.0",
    "gn:asciiname":"Los Jimenez",
    "gn:country_code":"MX",
    "gn:dem":1931,
    "gn:feature_class":"P",
    "gn:feature_code":"PPL",
    "gn:name":"Los Jim\u00e9nez",
    "gn:population":158,
    "gn:timezone":"America/Mexico_City",
    "iso:country":"MX",
    "name:und_x_variant":[
        "Los Jim\u00e9nez"
    ],
    "wof:name":"Los Jimenez",
    "wof:placetype":"locality",
    "wof:population":158
},
  "geometry": {"coordinates":[-101.1725,22.30667],"type":"Point"}
}