{
  "type": "Feature",
  "properties": {
    "gn:admin1_code":"13",
    "gn:admin2_code":"44.0",
    "gn:asciiname":"Humini",
    "gn:country_code":"MX",
    "gn:dem":2383,
    "gn:feature_class":"P",
    "gn:feature_code":"PPL",
    "gn:name":"Humini",
    "gn:population":242,
    "gn:timezone":"America/Mexico_City",
    "iso:country":"MX",
    "name:spa_x_preferred":[
        "Humin\u00ed"
    ],
    "wof:name":"Humini",
    "wof:placetype":"locality",
    "wof:population":242
},
  "geometry": {"coordinates":[-99.71194,20.22333],"type":"Point"}
}