{
  "type": "Feature",
  "properties": {
    "gn:admin1_code":"30",
    "gn:admin2_code":"160.0",
    "gn:asciiname":"Bruno Reyes",
    "gn:country_code":"MX",
    "gn:dem":49,
    "gn:feature_class":"P",
    "gn:feature_code":"PPL",
    "gn:name":"Bruno Reyes",
    "gn:population":5,
    "gn:timezone":"America/Mexico_City",
    "iso:country":"MX",
    "wof:name":"Bruno Reyes",
    "wof:placetype":"locality",
    "wof:population":5
},
  "geometry": {"coordinates":[-97.68028,21.01444],"type":"Point"}
}