{
  "type": "Feature",
  "properties": {
    "gn:admin1_code":"18",
    "gn:admin2_code":"9.0",
    "gn:asciiname":"Los Cajones",
    "gn:country_code":"MX",
    "gn:dem":167,
    "gn:feature_class":"P",
    "gn:feature_code":"PPL",
    "gn:name":"Los Cajones",
    "gn:population":65,
    "gn:timezone":"America/Mazatlan",
    "iso:country":"MX",
    "wof:name":"Los Cajones",
    "wof:placetype":"locality",
    "wof:population":65
},
  "geometry": {"coordinates":[-104.81056,21.83972],"type":"Point"}
}