{
  "type": "Feature",
  "properties": {
    "gn:admin1_code":"13",
    "gn:admin2_code":"17.0",
    "gn:asciiname":"Tlaunilolpan de Zaragoza",
    "gn:country_code":"MX",
    "gn:dem":2268,
    "gn:feature_class":"P",
    "gn:feature_code":"PPL",
    "gn:name":"Tlaunilolpan de Zaragoza",
    "gn:population":0,
    "gn:timezone":"America/Mexico_City",
    "iso:country":"MX",
    "name:spa_x_preferred":[
        "Tlaunilolpan de Zaragoza"
    ],
    "wof:name":"Tlaunilolpan de Zaragoza",
    "wof:placetype":"locality"
},
  "geometry": {"coordinates":[-99.46951,20.25988],"type":"Point"}
}