{
  "type": "Feature",
  "properties": {
    "gn:admin1_code":"30",
    "gn:admin2_code":"161.0",
    "gn:asciiname":"La Montana",
    "gn:country_code":"MX",
    "gn:dem":125,
    "gn:feature_class":"P",
    "gn:feature_code":"PPL",
    "gn:name":"La Monta\u00f1a",
    "gn:population":5,
    "gn:timezone":"America/Mexico_City",
    "iso:country":"MX",
    "name:und_x_variant":[
        "La Monta\u00f1a"
    ],
    "wof:name":"La Montana",
    "wof:placetype":"locality",
    "wof:population":5
},
  "geometry": {"coordinates":[-98.46056,21.46],"type":"Point"}
}