{
  "type": "Feature",
  "properties": {
    "gn:admin1_code":"6",
    "gn:admin2_code":"20",
    "gn:asciiname":"Los Jovinos",
    "gn:country_code":"MX",
    "gn:dem":430,
    "gn:feature_class":"P",
    "gn:feature_code":"PPL",
    "gn:name":"Los Jovinos",
    "gn:population":12,
    "gn:timezone":"America/Chihuahua",
    "iso:country":"MX",
    "wof:name":"Los Jovinos",
    "wof:placetype":"locality",
    "wof:population":12
},
  "geometry": {"coordinates":[-108.50132000000001,27.3502],"type":"Point"}
}