{
  "type": "Feature",
  "properties": {
    "gn:admin1_code":"7",
    "gn:admin2_code":"30.0",
    "gn:asciiname":"Presa de Guadalupe",
    "gn:country_code":"MX",
    "gn:dem":1724,
    "gn:feature_class":"P",
    "gn:feature_code":"PPL",
    "gn:name":"Presa de Guadalupe",
    "gn:population":40,
    "gn:timezone":"America/Monterrey",
    "iso:country":"MX",
    "name:spa_x_preferred":[
        "Presa de Guadalupe"
    ],
    "wof:name":"Presa de Guadalupe",
    "wof:placetype":"locality",
    "wof:population":40
},
  "geometry": {"coordinates":[-101.46201000000001,24.77603],"type":"Point"}
}