{
  "type": "Feature",
  "properties": {
    "gn:admin1_code":"5",
    "gn:admin2_code":"5.0",
    "gn:asciiname":"El Naranjo 2da. Seccion",
    "gn:country_code":"MX",
    "gn:dem":605,
    "gn:feature_class":"P",
    "gn:feature_code":"PPL",
    "gn:name":"El Naranjo 2da. Secci\u00f3n",
    "gn:population":295,
    "gn:timezone":"America/Mexico_City",
    "iso:country":"MX",
    "name:und_x_variant":[
        "El Naranjo 2da. Secci\u00f3n"
    ],
    "wof:name":"El Naranjo 2da. Seccion",
    "wof:placetype":"locality",
    "wof:population":295
},
  "geometry": {"coordinates":[-92.79722,17.38528],"type":"Point"}
}