{
  "type": "Feature",
  "properties": {
    "gn:admin1_code":"27",
    "gn:admin2_code":"11.0",
    "gn:asciiname":"San Benigno",
    "gn:country_code":"MX",
    "gn:dem":5,
    "gn:feature_class":"P",
    "gn:feature_code":"PPL",
    "gn:name":"San Benigno",
    "gn:population":0,
    "gn:timezone":"America/Mexico_City",
    "iso:country":"MX",
    "name:spa_x_preferred":[
        "Canul"
    ],
    "name:spa_x_variant":[
        "San Benigno"
    ],
    "wof:name":"San Benigno",
    "wof:placetype":"locality"
},
  "geometry": {"coordinates":[-92.16072,17.99369],"type":"Point"}
}