{
  "type": "Feature",
  "properties": {
    "gn:admin1_code":"17",
    "gn:asciiname":"Cerrito del Panal",
    "gn:country_code":"MX",
    "gn:dem":2715,
    "gn:feature_class":"P",
    "gn:feature_code":"PPL",
    "gn:name":"Cerrito del Panal",
    "gn:population":0,
    "gn:timezone":"America/Mexico_City",
    "iso:country":"MX",
    "name:spa_x_preferred":[
        "Cerrito del Panal"
    ],
    "wof:name":"Cerrito del Panal",
    "wof:placetype":"locality"
},
  "geometry": {"coordinates":[-99.61190000000001,19.49899],"type":"Point"}
}