{
  "type": "Feature",
  "properties": {
    "gn:admin1_code":"5",
    "gn:admin2_code":"31.0",
    "gn:asciiname":"Jolzacjum",
    "gn:country_code":"MX",
    "gn:dem":849,
    "gn:feature_class":"P",
    "gn:feature_code":"PPL",
    "gn:name":"Jolzacjum",
    "gn:population":0,
    "gn:timezone":"America/Mexico_City",
    "iso:country":"MX",
    "wof:name":"Jolzacjum",
    "wof:placetype":"locality"
},
  "geometry": {"coordinates":[-91.94028,17.12917],"type":"Point"}
}