{
  "type": "Feature",
  "properties": {
    "gn:admin1_code":"14.0",
    "gn:admin2_code":"64.0",
    "gn:asciiname":"El Bochorno",
    "gn:country_code":"MX",
    "gn:dem":2231,
    "gn:feature_class":"P",
    "gn:feature_code":"PPL",
    "gn:name":"El Bochorno",
    "gn:population":0,
    "gn:timezone":"America/Mexico_City",
    "iso:country":"MX",
    "name:spa_x_preferred":[
        "El Bochorno"
    ],
    "wof:name":"El Bochorno",
    "wof:placetype":"locality"
},
  "geometry": {"coordinates":[-101.64745000000001,21.61211],"type":"Point"}
}