{
  "type": "Feature",
  "properties": {
    "gn:admin1_code":"26",
    "gn:admin2_code":"64",
    "gn:asciiname":"Ejido la Playa",
    "gn:country_code":"MX",
    "gn:dem":485,
    "gn:feature_class":"P",
    "gn:feature_code":"PPL",
    "gn:name":"Ejido la Playa",
    "gn:population":52,
    "gn:timezone":"America/Hermosillo",
    "iso:country":"MX",
    "wof:name":"Ejido la Playa",
    "wof:placetype":"locality",
    "wof:population":52
},
  "geometry": {"coordinates":[-111.56222,30.46694],"type":"Point"}
}