{
  "type": "Feature",
  "properties": {
    "gn:admin1_code":"28.0",
    "gn:admin2_code":"2.0",
    "gn:asciiname":"Los Planes",
    "gn:country_code":"MX",
    "gn:dem":15,
    "gn:feature_class":"P",
    "gn:feature_code":"PPL",
    "gn:name":"Los Planes",
    "gn:population":2,
    "gn:timezone":"America/Monterrey",
    "iso:country":"MX",
    "name:spa_x_preferred":[
        "Los Planes"
    ],
    "wof:name":"Los Planes",
    "wof:placetype":"locality",
    "wof:population":2
},
  "geometry": {"coordinates":[-97.91472,22.66694],"type":"Point"}
}