{
  "type": "Feature",
  "properties": {
    "gn:admin1_code":"6.0",
    "gn:admin2_code":"48.0",
    "gn:asciiname":"Huerta Vazquena",
    "gn:country_code":"MX",
    "gn:dem":1872,
    "gn:feature_class":"P",
    "gn:feature_code":"PPL",
    "gn:name":"Huerta Vazque\u00f1a",
    "gn:population":0,
    "gn:timezone":"America/Chihuahua",
    "iso:country":"MX",
    "name:spa_x_preferred":[
        "Huerta Vazque\u00f1a"
    ],
    "name:spa_x_variant":[
        "La Vazque\u00f1a"
    ],
    "wof:name":"Huerta Vazquena",
    "wof:placetype":"locality"
},
  "geometry": {"coordinates":[-107.38800000000001,29.14602],"type":"Point"}
}