{
  "type": "Feature",
  "properties": {
    "gn:admin1_code":"31",
    "gn:admin2_code":"93.0",
    "gn:asciiname":"Lunhu",
    "gn:country_code":"MX",
    "gn:dem":10,
    "gn:feature_class":"P",
    "gn:feature_code":"PPL",
    "gn:name":"Lunhu",
    "gn:population":0,
    "gn:timezone":"America/Merida",
    "iso:country":"MX",
    "name:spa_x_preferred":[
        "Lunhu"
    ],
    "wof:name":"Lunhu",
    "wof:placetype":"locality"
},
  "geometry": {"coordinates":[-89.35401,20.97711],"type":"Point"}
}