{
  "type": "Feature",
  "properties": {
    "gn:admin1_code":"15",
    "gn:admin2_code":"8.0",
    "gn:asciiname":"Gueijas Blancas",
    "gn:country_code":"MX",
    "gn:dem":1275,
    "gn:feature_class":"P",
    "gn:feature_code":"PPL",
    "gn:name":"G\u00fcijas Blancas",
    "gn:population":168,
    "gn:timezone":"America/Mexico_City",
    "iso:country":"MX",
    "name:und_x_variant":[
        "G\u00fcijas Blancas"
    ],
    "wof:name":"Gueijas Blancas",
    "wof:placetype":"locality",
    "wof:population":168
},
  "geometry": {"coordinates":[-100.21550000000001,18.7344],"type":"Point"}
}