{
  "type": "Feature",
  "properties": {
    "gn:admin1_code":"30.0",
    "gn:admin2_code":"161.0",
    "gn:asciiname":"Santa Aurelia",
    "gn:country_code":"MX",
    "gn:dem":76,
    "gn:feature_class":"P",
    "gn:feature_code":"PPL",
    "gn:name":"Santa Aurelia",
    "gn:population":4,
    "gn:timezone":"America/Mexico_City",
    "iso:country":"MX",
    "name:spa_x_preferred":[
        "Santa Aurelia"
    ],
    "wof:name":"Santa Aurelia",
    "wof:placetype":"locality",
    "wof:population":4
},
  "geometry": {"coordinates":[-98.25722,21.60778],"type":"Point"}
}