{
  "type": "Feature",
  "properties": {
    "gn:admin1_code":"30",
    "gn:admin2_code":"22.0",
    "gn:asciiname":"Revolucion",
    "gn:country_code":"MX",
    "gn:dem":1290,
    "gn:feature_class":"P",
    "gn:feature_code":"PPL",
    "gn:name":"Revoluci\u00f3n",
    "gn:population":756,
    "gn:timezone":"America/Mexico_City",
    "iso:country":"MX",
    "name:und_x_variant":[
        "Revoluci\u00f3n"
    ],
    "wof:name":"Revolucion",
    "wof:placetype":"locality",
    "wof:population":756
},
  "geometry": {"coordinates":[-97.09139,18.88778],"type":"Point"}
}