{
  "type": "Feature",
  "properties": {
    "gn:admin1_code":"4",
    "gn:admin2_code":"10.0",
    "gn:asciiname":"Guillermo Prieto",
    "gn:country_code":"MX",
    "gn:dem":247,
    "gn:feature_class":"P",
    "gn:feature_code":"PPL",
    "gn:name":"Guillermo Prieto",
    "gn:population":0,
    "gn:timezone":"America/Cancun",
    "iso:country":"MX",
    "name:spa_x_preferred":[
        "Guillermo Prieto"
    ],
    "wof:name":"Guillermo Prieto",
    "wof:placetype":"locality"
},
  "geometry": {"coordinates":[-89.34413000000001,18.17795],"type":"Point"}
}