{
  "type": "Feature",
  "properties": {
    "gn:admin1_code":"19",
    "gn:admin2_code":"33.0",
    "gn:asciiname":"El Popote",
    "gn:country_code":"MX",
    "gn:dem":291,
    "gn:feature_class":"P",
    "gn:feature_code":"PPL",
    "gn:name":"El Popote",
    "gn:population":0,
    "gn:timezone":"America/Monterrey",
    "iso:country":"MX",
    "name:spa_x_preferred":[
        "El Poblado"
    ],
    "name:und_x_variant":[
        "Ejido El Popote",
        "El Popote"
    ],
    "wof:name":"El Popote",
    "wof:placetype":"locality"
},
  "geometry": {"coordinates":[-99.44446000000001,24.88818],"type":"Point"}
}