{
  "type": "Feature",
  "properties": {
    "gn:admin1_code":"10",
    "gn:admin2_code":"37.0",
    "gn:asciiname":"Metatitos",
    "gn:country_code":"MX",
    "gn:dem":1173,
    "gn:feature_class":"P",
    "gn:feature_code":"PPL",
    "gn:name":"Metatitos",
    "gn:population":0,
    "gn:timezone":"America/Monterrey",
    "iso:country":"MX",
    "wof:name":"Metatitos",
    "wof:placetype":"locality"
},
  "geometry": {"coordinates":[-106.58333,25.35],"type":"Point"}
}