{
  "type": "Feature",
  "properties": {
    "gn:admin1_code":"6.0",
    "gn:admin2_code":"46.0",
    "gn:asciiname":"El Frijolar",
    "gn:country_code":"MX",
    "gn:dem":1107,
    "gn:feature_class":"P",
    "gn:feature_code":"PPL",
    "gn:name":"El Frijolar",
    "gn:population":0,
    "gn:timezone":"America/Mazatlan",
    "iso:country":"MX",
    "name:spa_x_preferred":[
        "El Frijolar"
    ],
    "wof:name":"El Frijolar",
    "wof:placetype":"locality"
},
  "geometry": {"coordinates":[-107.90806000000001,26.49474],"type":"Point"}
}