{
  "type": "Feature",
  "properties": {
    "gn:admin1_code":"29",
    "gn:admin2_code":"3.0",
    "gn:asciiname":"San Antonio Tepetzala",
    "gn:country_code":"MX",
    "gn:dem":2626,
    "gn:feature_class":"P",
    "gn:feature_code":"PPL",
    "gn:name":"San Antonio Tepetzal\u00e1",
    "gn:population":0,
    "gn:timezone":"America/Mexico_City",
    "iso:country":"MX",
    "name:spa_x_preferred":[
        "San Antonio Tepetzal\u00e1"
    ],
    "wof:name":"San Antonio Tepetzala",
    "wof:placetype":"locality"
},
  "geometry": {"coordinates":[-98.11347000000001,19.53194],"type":"Point"}
}