{
  "type": "Feature",
  "properties": {
    "gn:admin1_code":"11",
    "gn:admin2_code":"8",
    "gn:asciiname":"El Palmito",
    "gn:country_code":"MX",
    "gn:dem":1964,
    "gn:feature_class":"P",
    "gn:feature_code":"PPL",
    "gn:name":"El Palmito",
    "gn:population":15,
    "gn:timezone":"America/Mexico_City",
    "iso:country":"MX",
    "wof:name":"El Palmito",
    "wof:placetype":"locality",
    "wof:population":15
},
  "geometry": {"coordinates":[-101.89389,20.60944],"type":"Point"}
}