{
  "type": "Feature",
  "properties": {
    "gn:admin1_code":"5.0",
    "gn:admin2_code":"97.0",
    "gn:asciiname":"Cimarron",
    "gn:country_code":"MX",
    "gn:dem":786,
    "gn:feature_class":"P",
    "gn:feature_code":"PPL",
    "gn:name":"Cimarr\u00f3n",
    "gn:population":0,
    "gn:timezone":"America/Mexico_City",
    "iso:country":"MX",
    "name:spa_x_preferred":[
        "Cimarr\u00f3n"
    ],
    "wof:name":"Cimarron",
    "wof:placetype":"locality"
},
  "geometry": {"coordinates":[-93.58414,16.01292999999999],"type":"Point"}
}