{
  "type": "Feature",
  "properties": {
    "gn:admin1_code":"5.0",
    "gn:admin2_code":"97.0",
    "gn:asciiname":"Cimarron",
    "gn:country_code":"MX",
    "gn:dem":786,
    "gn:feature_class":"P",
    "gn:feature_code":"PPL",
    "gn:name":"Cimarr\u00f3n",
    "gn:population":0,
    "gn:timezone":"America/Mexico_City",
    "iso:country":"MX",
    "name:cat_x_preferred":[
        "Cimarron"
    ],
    "name:ceb_x_preferred":[
        "Cimarron"
    ],
    "name:ces_x_preferred":[
        "Cimarron"
    ],
    "name:dan_x_preferred":[
        "Cimarron"
    ],
    "name:deu_x_preferred":[
        "Cimarron"
    ],
    "name:fin_x_preferred":[
        "Cimarron"
    ],
    "name:fra_x_preferred":[
        "Cimarron"
    ],
    "name:hrv_x_preferred":[
        "Cimarron"
    ],
    "name:ita_x_preferred":[
        "Cimarron"
    ],
    "name:jpn_x_preferred":[
        "\u30b7\u30de\u30ed\u30f3"
    ],
    "name:kor_x_preferred":[
        "\uc2dc\ub9c8\ub860"
    ],
    "name:nds_x_preferred":[
        "Cimarron"
    ],
    "name:nld_x_preferred":[
        "Cimarron"
    ],
    "name:pol_x_preferred":[
        "Cimarron"
    ],
    "name:por_x_preferred":[
        "Cimarron"
    ],
    "name:rus_x_preferred":[
        "\u0421\u0438\u043c\u0430\u0440\u0440\u043e\u043d"
    ],
    "name:spa_x_preferred":[
        "Cimarr\u00f3n"
    ],
    "name:srp_x_preferred":[
        "\u0421\u0438\u043c\u0430\u0440\u043e\u043d"
    ],
    "name:swe_x_preferred":[
        "Cimarron"
    ],
    "name:ukr_x_preferred":[
        "\u0426\u0438\u043c\u0430\u0440\u0440\u043e\u043d"
    ],
    "name:vol_x_preferred":[
        "Cimarron"
    ],
    "wof:name":"Cimarron",
    "wof:placetype":"locality"
},
  "geometry": {"coordinates":[-93.58414,16.01292999999999],"type":"Point"}
}