{
  "type": "Feature",
  "properties": {
    "gn:admin1_code":"25",
    "gn:admin2_code":"18",
    "gn:asciiname":"Los Alamitos",
    "gn:country_code":"MX",
    "gn:dem":7,
    "gn:feature_class":"P",
    "gn:feature_code":"PPL",
    "gn:name":"Los Alamitos",
    "gn:population":35,
    "gn:timezone":"America/Mazatlan",
    "iso:country":"MX",
    "name:ceb_x_preferred":[
        "Los Alamitos"
    ],
    "name:srp_x_preferred":[
        "\u041b\u043e\u0441 \u0410\u043b\u0430\u043c\u0438\u0442\u043e\u0441"
    ],
    "name:swe_x_preferred":[
        "Los Alamitos"
    ],
    "wof:name":"Los Alamitos",
    "wof:placetype":"locality",
    "wof:population":35
},
  "geometry": {"coordinates":[-107.54694000000001,24.57194],"type":"Point"}
}