{
  "type": "Feature",
  "properties": {
    "gn:admin1_code":"30",
    "gn:admin2_code":"143.0",
    "gn:asciiname":"Lomas de Alonso Lazaro (El Burro)",
    "gn:country_code":"MX",
    "gn:dem":9,
    "gn:feature_class":"P",
    "gn:feature_code":"PPL",
    "gn:name":"Lomas de Alonso L\u00e1zaro (El Burro)",
    "gn:population":135,
    "gn:timezone":"America/Mexico_City",
    "iso:country":"MX",
    "name:und_x_variant":[
        "Lomas de Alonso L\u00e1zaro (El Burro)"
    ],
    "wof:name":"Lomas de Alonso Lazaro (El Burro)",
    "wof:placetype":"locality",
    "wof:population":135
},
  "geometry": {"coordinates":[-95.49611,18.40722],"type":"Point"}
}