{
  "type": "Feature",
  "properties": {
    "gn:admin1_code":"26",
    "gn:admin2_code":"42.0",
    "gn:asciiname":"Campo Pilinque",
    "gn:country_code":"MX",
    "gn:dem":16,
    "gn:feature_class":"P",
    "gn:feature_code":"PPL",
    "gn:name":"Campo Pilinque",
    "gn:population":0,
    "gn:timezone":"America/Hermosillo",
    "iso:country":"MX",
    "name:spa_x_preferred":[
        "Campo Pilinque"
    ],
    "wof:name":"Campo Pilinque",
    "wof:placetype":"locality"
},
  "geometry": {"coordinates":[-109.58038999999999,26.84913],"type":"Point"}
}