{
  "type": "Feature",
  "properties": {
    "gn:admin1_code":"30.0",
    "gn:asciiname":"Los Framboyanes",
    "gn:country_code":"MX",
    "gn:dem":86,
    "gn:feature_class":"P",
    "gn:feature_code":"PPL",
    "gn:name":"Los Framboyanes",
    "gn:population":0,
    "gn:timezone":"America/Mexico_City",
    "iso:country":"MX",
    "name:spa_x_preferred":[
        "Los Framboyanes"
    ],
    "wof:name":"Los Framboyanes",
    "wof:placetype":"locality"
},
  "geometry": {"coordinates":[-95.76708000000001,17.94586],"type":"Point"}
}