{
  "type": "Feature",
  "properties": {
    "gn:admin1_code":"6",
    "gn:admin2_code":"14.0",
    "gn:asciiname":"Emiliano Zapata",
    "gn:country_code":"MX",
    "gn:dem":1473,
    "gn:feature_class":"P",
    "gn:feature_code":"PPL",
    "gn:name":"Emiliano Zapata",
    "gn:population":164,
    "gn:timezone":"America/Chihuahua",
    "iso:country":"MX",
    "name:und_x_variant":[
        "Ejido Emiliano Zapata",
        "Ya\u00f1iz",
        "Zapata"
    ],
    "wof:name":"Emiliano Zapata",
    "wof:placetype":"locality",
    "wof:population":164
},
  "geometry": {"coordinates":[-105.13056,26.87528],"type":"Point"}
}