{
  "type": "Feature",
  "properties": {
    "iso:country":"MX",
    "name:fas_x_preferred":[
        "\u0633\u0627\u0646 \u06a9\u0631\u06cc\u0633\u062a\u0648\u0628\u0627\u0644"
    ],
    "name:heb_x_preferred":[
        "\u05d0\u05d9\u05d9 \u05e1\u05df \u05db\u05e8\u05d9\u05e1\u05d8\u05d5\u05d1\u05dc"
    ],
    "name:hun_x_preferred":[
        "San Cristobal"
    ],
    "qs_pg:aaroncc":"MX",
    "qs_pg:name":"San Cristobal",
    "qs_pg:name_adm0":"M\u00e9xico",
    "qs_pg:name_adm1":"Morelos",
    "qs_pg:photos":1,
    "qs_pg:photos_1k":1,
    "qs_pg:photos_9k":1,
    "qs_pg:photos_9r":1,
    "qs_pg:photos_all":1,
    "qs_pg:photos_sr":1,
    "qs_pg:pop_sr":0,
    "qs_pg:qs_pg_placetype":"neighbourhood",
    "qs_pg:qs_pg_placetype_gp":"Suburb",
    "qs_pg:woe_adm0":23424900,
    "woe:adm0_id":23424900,
    "woe:name_adm0":"M\u00e9xico",
    "woe:name_adm1":"Morelos",
    "woe:placetype":"Suburb",
    "wof:name":"San Cristobal",
    "wof:placetype":"neighbourhood"
},
  "geometry": {"coordinates":[-99.23487799999999,18.92214],"type":"Point"}
}