{
  "type": "Feature",
  "properties": {
    "gn:admin1_code":"13",
    "gn:admin2_code":"44.0",
    "gn:asciiname":"Los Caballos",
    "gn:country_code":"MX",
    "gn:dem":2406,
    "gn:feature_class":"P",
    "gn:feature_code":"PPL",
    "gn:name":"Los Caballos",
    "gn:population":5,
    "gn:timezone":"America/Mexico_City",
    "iso:country":"MX",
    "wof:name":"Los Caballos",
    "wof:placetype":"locality",
    "wof:population":5
},
  "geometry": {"coordinates":[-99.59990000000001,20.19259],"type":"Point"}
}