{
  "type": "Feature",
  "properties": {
    "gn:admin1_code":"5",
    "gn:admin2_code":"89.0",
    "gn:asciiname":"El Porvenir",
    "gn:country_code":"MX",
    "gn:dem":343,
    "gn:feature_class":"P",
    "gn:feature_code":"PPL",
    "gn:name":"El Porvenir",
    "gn:population":489,
    "gn:timezone":"America/Mexico_City",
    "iso:country":"MX",
    "wof:name":"El Porvenir",
    "wof:placetype":"locality",
    "wof:population":489
},
  "geometry": {"coordinates":[-92.29277999999999,14.99694],"type":"Point"}
}