{
  "type": "Feature",
  "properties": {
    "gn:admin1_code":"6.0",
    "gn:admin2_code":"20.0",
    "gn:asciiname":"Agua del Venado",
    "gn:country_code":"MX",
    "gn:dem":1013,
    "gn:feature_class":"P",
    "gn:feature_code":"PPL",
    "gn:name":"Agua del Venado",
    "gn:population":0,
    "gn:timezone":"America/Chihuahua",
    "iso:country":"MX",
    "name:spa_x_preferred":[
        "Agua del Venado"
    ],
    "wof:name":"Agua del Venado",
    "wof:placetype":"locality"
},
  "geometry": {"coordinates":[-108.50700000000001,27.07495],"type":"Point"}
}