{
  "type": "Feature",
  "properties": {
    "gn:admin1_code":"26",
    "gn:admin2_code":"3.0",
    "gn:asciiname":"San Miguel",
    "gn:country_code":"MX",
    "gn:dem":656,
    "gn:feature_class":"P",
    "gn:feature_code":"PPL",
    "gn:name":"San Miguel",
    "gn:population":9,
    "gn:timezone":"America/Hermosillo",
    "iso:country":"MX",
    "wof:name":"San Miguel",
    "wof:placetype":"locality",
    "wof:population":9
},
  "geometry": {"coordinates":[-108.56889,26.98722],"type":"Point"}
}