{
  "type": "Feature",
  "properties": {
    "gn:admin1_code":"22",
    "gn:admin2_code":"16.0",
    "gn:asciiname":"Buenavista Palma de Romero",
    "gn:country_code":"MX",
    "gn:dem":2162,
    "gn:feature_class":"P",
    "gn:feature_code":"PPL",
    "gn:name":"Buenavista Palma de Romero",
    "gn:population":497,
    "gn:timezone":"America/Mexico_City",
    "iso:country":"MX",
    "wof:name":"Buenavista Palma de Romero",
    "wof:placetype":"locality",
    "wof:population":497
},
  "geometry": {"coordinates":[-99.95056,20.3375],"type":"Point"}
}