{
  "type": "Feature",
  "properties": {
    "gn:admin1_code":"5",
    "gn:admin2_code":"83.0",
    "gn:asciiname":"Santa Evangelina",
    "gn:country_code":"MX",
    "gn:dem":606,
    "gn:feature_class":"P",
    "gn:feature_code":"PPL",
    "gn:name":"Santa Evangelina",
    "gn:population":4,
    "gn:timezone":"America/Mexico_City",
    "iso:country":"MX",
    "wof:name":"Santa Evangelina",
    "wof:placetype":"locality",
    "wof:population":4
},
  "geometry": {"coordinates":[-92.42028000000001,16.18667],"type":"Point"}
}