{
  "type": "Feature",
  "properties": {
    "gn:admin1_code":"30",
    "gn:admin2_code":"130",
    "gn:asciiname":"Rancho Villegas",
    "gn:country_code":"MX",
    "gn:dem":119,
    "gn:feature_class":"P",
    "gn:feature_code":"PPL",
    "gn:name":"Rancho Villegas",
    "gn:population":18,
    "gn:timezone":"America/Mexico_City",
    "iso:country":"MX",
    "wof:name":"Rancho Villegas",
    "wof:placetype":"locality",
    "wof:population":18
},
  "geometry": {"coordinates":[-95.59972,17.71138999999999],"type":"Point"}
}