{
  "type": "Feature",
  "properties": {
    "gn:admin1_code":"10",
    "gn:admin2_code":"23",
    "gn:asciiname":"El Ojo de Agua",
    "gn:country_code":"MX",
    "gn:dem":959,
    "gn:feature_class":"P",
    "gn:feature_code":"PPL",
    "gn:name":"El Ojo de Agua",
    "gn:population":16,
    "gn:timezone":"America/Monterrey",
    "iso:country":"MX",
    "wof:name":"El Ojo de Agua",
    "wof:placetype":"locality",
    "wof:population":16
},
  "geometry": {"coordinates":[-105.33435,23.28187],"type":"Point"}
}