{
  "type": "Feature",
  "properties": {
    "gn:admin1_code":"11",
    "gn:admin2_code":"33",
    "gn:asciiname":"El Rescoldo (Jalapa)",
    "gn:country_code":"MX",
    "gn:dem":1998,
    "gn:feature_class":"P",
    "gn:feature_code":"PPL",
    "gn:name":"El Rescoldo (Jalapa)",
    "gn:population":20,
    "gn:timezone":"America/Mexico_City",
    "iso:country":"MX",
    "wof:name":"El Rescoldo (Jalapa)",
    "wof:placetype":"locality",
    "wof:population":20
},
  "geometry": {"coordinates":[-100.38500000000001,21.37222],"type":"Point"}
}