{
  "type": "Feature",
  "properties": {
    "gn:admin1_code":"32",
    "gn:admin2_code":"51.0",
    "gn:asciiname":"Lara Pacheco Uno (El Tejaban)",
    "gn:country_code":"MX",
    "gn:dem":2009,
    "gn:feature_class":"P",
    "gn:feature_code":"PPL",
    "gn:name":"Lara Pacheco Uno (El Tejab\u00e1n)",
    "gn:population":9,
    "gn:timezone":"America/Mexico_City",
    "iso:country":"MX",
    "name:und_x_variant":[
        "Lara Pacheco Uno (El Tejab\u00e1n)"
    ],
    "wof:name":"Lara Pacheco Uno (El Tejaban)",
    "wof:placetype":"locality",
    "wof:population":9
},
  "geometry": {"coordinates":[-102.43556,23.20806],"type":"Point"}
}