{
  "type": "Feature",
  "properties": {
    "gn:admin1_code":"10.0",
    "gn:admin2_code":"14.0",
    "gn:asciiname":"La Boquilla",
    "gn:country_code":"MX",
    "gn:dem":1519,
    "gn:feature_class":"P",
    "gn:feature_code":"PPL",
    "gn:name":"La Boquilla",
    "gn:population":0,
    "gn:timezone":"America/Monterrey",
    "iso:country":"MX",
    "name:spa_x_preferred":[
        "La Boquilla"
    ],
    "wof:name":"La Boquilla",
    "wof:placetype":"locality"
},
  "geometry": {"coordinates":[-104.39601,22.46497],"type":"Point"}
}