{
  "type": "Feature",
  "properties": {
    "gn:admin1_code":"21",
    "gn:asciiname":"Platanozapan",
    "gn:country_code":"MX",
    "gn:dem":840,
    "gn:feature_class":"P",
    "gn:feature_code":"PPL",
    "gn:name":"Platanozapan",
    "gn:population":0,
    "gn:timezone":"America/Mexico_City",
    "iso:country":"MX",
    "name:spa_x_preferred":[
        "Platanozapan"
    ],
    "name:und_x_variant":[
        "Platanozapa"
    ],
    "wof:name":"Platanozapan",
    "wof:placetype":"locality"
},
  "geometry": {"coordinates":[-97.2555,19.94314],"type":"Point"}
}