{
  "type": "Feature",
  "properties": {
    "gn:admin1_code":"4",
    "gn:admin2_code":"3",
    "gn:asciiname":"El Sacrificio",
    "gn:country_code":"MX",
    "gn:dem":26,
    "gn:feature_class":"P",
    "gn:feature_code":"PPL",
    "gn:name":"El Sacrificio",
    "gn:population":11,
    "gn:timezone":"America/Merida",
    "iso:country":"MX",
    "wof:name":"El Sacrificio",
    "wof:placetype":"locality",
    "wof:population":11
},
  "geometry": {"coordinates":[-91.20528,18.24139],"type":"Point"}
}