{
  "type": "Feature",
  "properties": {
    "gn:admin1_code":"5",
    "gn:admin2_code":"69.0",
    "gn:asciiname":"Morelia (Solo Dios)",
    "gn:country_code":"MX",
    "gn:dem":13,
    "gn:feature_class":"P",
    "gn:feature_code":"PPL",
    "gn:name":"Morelia (Solo Dios)",
    "gn:population":8,
    "gn:timezone":"America/Mexico_City",
    "iso:country":"MX",
    "wof:name":"Morelia (Solo Dios)",
    "wof:placetype":"locality",
    "wof:population":8
},
  "geometry": {"coordinates":[-93.44389,15.70472],"type":"Point"}
}