{
  "type": "Feature",
  "properties": {
    "gn:admin1_code":"24",
    "gn:admin2_code":"24.0",
    "gn:asciiname":"El Obrajero",
    "gn:country_code":"MX",
    "gn:dem":984,
    "gn:feature_class":"P",
    "gn:feature_code":"PPL",
    "gn:name":"El Obrajero",
    "gn:population":74,
    "gn:timezone":"America/Mexico_City",
    "iso:country":"MX",
    "wof:name":"El Obrajero",
    "wof:placetype":"locality",
    "wof:population":74
},
  "geometry": {"coordinates":[-99.90833000000001,21.83694],"type":"Point"}
}