{
  "type": "Feature",
  "properties": {
    "gn:admin1_code":"6",
    "gn:admin2_code":"65.0",
    "gn:asciiname":"Riquibitare",
    "gn:country_code":"MX",
    "gn:dem":2193,
    "gn:feature_class":"P",
    "gn:feature_code":"PPL",
    "gn:name":"Riquib\u00edtare",
    "gn:population":0,
    "gn:timezone":"America/Chihuahua",
    "iso:country":"MX",
    "name:spa_x_preferred":[
        "Riquib\u00edtare"
    ],
    "wof:name":"Riquibitare",
    "wof:placetype":"locality"
},
  "geometry": {"coordinates":[-107.99033,27.39724],"type":"Point"}
}