{
  "type": "Feature",
  "properties": {
    "gn:admin1_code":"5.0",
    "gn:admin2_code":"8.0",
    "gn:asciiname":"El Corchal",
    "gn:country_code":"MX",
    "gn:dem":1011,
    "gn:feature_class":"P",
    "gn:feature_code":"PPL",
    "gn:name":"El Corchal",
    "gn:population":0,
    "gn:timezone":"America/Mexico_City",
    "iso:country":"MX",
    "name:spa_x_preferred":[
        "El Corchal"
    ],
    "wof:name":"El Corchal",
    "wof:placetype":"locality"
},
  "geometry": {"coordinates":[-92.76997,15.768],"type":"Point"}
}