{
  "type": "Feature",
  "properties": {
    "gn:admin1_code":"14",
    "gn:admin2_code":"33.0",
    "gn:asciiname":"Quirino (La Sierrita)",
    "gn:country_code":"MX",
    "gn:dem":1740,
    "gn:feature_class":"P",
    "gn:feature_code":"PPL",
    "gn:name":"Quirino (La Sierrita)",
    "gn:population":277,
    "gn:timezone":"America/Mexico_City",
    "iso:country":"MX",
    "wof:name":"Quirino (La Sierrita)",
    "wof:placetype":"locality",
    "wof:population":277
},
  "geometry": {"coordinates":[-102.22278,20.46806],"type":"Point"}
}