{
  "type": "Feature",
  "properties": {
    "gn:admin1_code":"26",
    "gn:admin2_code":"60.0",
    "gn:asciiname":"La Garita de la Ladrillera",
    "gn:country_code":"MX",
    "gn:dem":1083,
    "gn:feature_class":"P",
    "gn:feature_code":"PPL",
    "gn:name":"La Garita de la Ladrillera",
    "gn:population":0,
    "gn:timezone":"America/Hermosillo",
    "iso:country":"MX",
    "wof:name":"La Garita de la Ladrillera",
    "wof:placetype":"locality"
},
  "geometry": {"coordinates":[-111.55,31.46667],"type":"Point"}
}