{
  "type": "Feature",
  "properties": {
    "gn:admin1_code":"19.0",
    "gn:asciiname":"El Quince",
    "gn:country_code":"MX",
    "gn:dem":477,
    "gn:feature_class":"P",
    "gn:feature_code":"PPL",
    "gn:name":"El Quince",
    "gn:population":0,
    "gn:timezone":"America/Monterrey",
    "iso:country":"MX",
    "name:spa_x_preferred":[
        "El Quince"
    ],
    "wof:name":"El Quince",
    "wof:placetype":"locality"
},
  "geometry": {"coordinates":[-100.27872000000001,25.78372],"type":"Point"}
}