{
  "type": "Feature",
  "properties": {
    "gn:admin1_code":"16",
    "gn:admin2_code":"49.0",
    "gn:asciiname":"Las Carboneras",
    "gn:country_code":"MX",
    "gn:dem":1654,
    "gn:feature_class":"P",
    "gn:feature_code":"PPL",
    "gn:name":"Las Carboneras",
    "gn:population":0,
    "gn:timezone":"America/Mexico_City",
    "iso:country":"MX",
    "name:spa_x_preferred":[
        "Las Carboneras"
    ],
    "wof:name":"Las Carboneras",
    "wof:placetype":"locality"
},
  "geometry": {"coordinates":[-101.05397000000001,19.32925],"type":"Point"}
}