{
  "type": "Feature",
  "properties": {
    "gn:admin1_code":"30",
    "gn:admin2_code":"189.0",
    "gn:asciiname":"Ceiba Rica",
    "gn:country_code":"MX",
    "gn:dem":32,
    "gn:feature_class":"P",
    "gn:feature_code":"PPL",
    "gn:name":"Ceiba Rica",
    "gn:population":633,
    "gn:timezone":"America/Mexico_City",
    "iso:country":"MX",
    "wof:name":"Ceiba Rica",
    "wof:placetype":"locality",
    "wof:population":633
},
  "geometry": {"coordinates":[-97.4375,20.89],"type":"Point"}
}