{
  "type": "Feature",
  "properties": {
    "gn:admin1_code":"14",
    "gn:admin2_code":"73",
    "gn:asciiname":"Canada de Perez",
    "gn:country_code":"MX",
    "gn:dem":1781,
    "gn:feature_class":"P",
    "gn:feature_code":"PPL",
    "gn:name":"Ca\u00f1ada de P\u00e9rez",
    "gn:population":10,
    "gn:timezone":"America/Mexico_City",
    "iso:country":"MX",
    "name:und_x_variant":[
        "Ca\u00f1ada de P\u00e9rez"
    ],
    "wof:name":"Canada de Perez",
    "wof:placetype":"locality",
    "wof:population":10
},
  "geometry": {"coordinates":[-102.34999999999999,21.20083],"type":"Point"}
}