{
  "type": "Feature",
  "properties": {
    "gn:admin1_code":"6",
    "gn:admin2_code":"29.0",
    "gn:asciiname":"La Palmita",
    "gn:country_code":"MX",
    "gn:dem":2127,
    "gn:feature_class":"P",
    "gn:feature_code":"PPL",
    "gn:name":"La Palmita",
    "gn:population":0,
    "gn:timezone":"America/Chihuahua",
    "iso:country":"MX",
    "name:spa_x_preferred":[
        "La Palmita"
    ],
    "wof:name":"La Palmita",
    "wof:placetype":"locality"
},
  "geometry": {"coordinates":[-106.86266000000001,26.24007000000001],"type":"Point"}
}