{
  "type": "Feature",
  "properties": {
    "gn:admin1_code":"25",
    "gn:admin2_code":"10",
    "gn:asciiname":"Lo de Mayo (Alamo Caido)",
    "gn:country_code":"MX",
    "gn:dem":77,
    "gn:feature_class":"P",
    "gn:feature_code":"PPL",
    "gn:name":"Lo de Mayo (\u00c1lamo Ca\u00eddo)",
    "gn:population":51,
    "gn:timezone":"America/Mazatlan",
    "iso:country":"MX",
    "name:und_x_variant":[
        "Lo de Mayo (\u00c1lamo Ca\u00eddo)"
    ],
    "wof:name":"Lo de Mayo (Alamo Caido)",
    "wof:placetype":"locality",
    "wof:population":51
},
  "geometry": {"coordinates":[-108.71323,26.42105],"type":"Point"}
}