{
  "type": "Feature",
  "properties": {
    "gn:admin1_code":"32",
    "gn:admin2_code":"5.0",
    "gn:asciiname":"San Carlos (Rancho de Elias Garcia)",
    "gn:country_code":"MX",
    "gn:dem":2162,
    "gn:feature_class":"P",
    "gn:feature_code":"PPL",
    "gn:name":"San Carlos (Rancho de El\u00edas Garc\u00eda)",
    "gn:population":8,
    "gn:timezone":"America/Mexico_City",
    "iso:country":"MX",
    "name:und_x_variant":[
        "San Carlos (Rancho de El\u00edas Garc\u00eda)"
    ],
    "wof:name":"San Carlos (Rancho de Elias Garcia)",
    "wof:placetype":"locality",
    "wof:population":8
},
  "geometry": {"coordinates":[-102.63222,22.96833],"type":"Point"}
}