{
  "type": "Feature",
  "properties": {
    "gn:admin1_code":"2.0",
    "gn:admin2_code":"2.0",
    "gn:asciiname":"Rancho Fierro",
    "gn:country_code":"MX",
    "gn:dem":31,
    "gn:feature_class":"P",
    "gn:feature_code":"PPL",
    "gn:name":"Rancho Fierro",
    "gn:population":11,
    "gn:timezone":"America/Tijuana",
    "iso:country":"MX",
    "name:spa_x_preferred":[
        "Fierro"
    ],
    "wof:name":"Rancho Fierro",
    "wof:placetype":"locality",
    "wof:population":11
},
  "geometry": {"coordinates":[-114.80777999999999,32.64667],"type":"Point"}
}