{
  "type": "Feature",
  "properties": {
    "gn:admin1_code":"12.0",
    "gn:admin2_code":"64.0",
    "gn:asciiname":"Chucumpun",
    "gn:country_code":"MX",
    "gn:dem":337,
    "gn:feature_class":"P",
    "gn:feature_code":"PPL",
    "gn:name":"Chucump\u00fan",
    "gn:population":0,
    "gn:timezone":"America/Mexico_City",
    "iso:country":"MX",
    "name:spa_x_preferred":[
        "Chucump\u00fan"
    ],
    "name:und_x_variant":[
        "Chucump\u00f3n"
    ],
    "wof:name":"Chucumpun",
    "wof:placetype":"locality"
},
  "geometry": {"coordinates":[-100.53158999999999,18.40828],"type":"Point"}
}