{
  "type": "Feature",
  "properties": {
    "gn:admin1_code":"31",
    "gn:admin2_code":"38.0",
    "gn:asciiname":"Xcun-ac",
    "gn:country_code":"MX",
    "gn:dem":5,
    "gn:feature_class":"P",
    "gn:feature_code":"PPL",
    "gn:name":"Xcun-ac",
    "gn:population":0,
    "gn:timezone":"America/Merida",
    "iso:country":"MX",
    "name:spa_x_preferred":[
        "Xcun-ac"
    ],
    "name:und_x_variant":[
        "Xcumac"
    ],
    "wof:name":"Xcun-ac",
    "wof:placetype":"locality"
},
  "geometry": {"coordinates":[-89.86492,21.04453],"type":"Point"}
}