{
  "type": "Feature",
  "properties": {
    "gn:admin1_code":"19",
    "gn:admin2_code":"50.0",
    "gn:asciiname":"El Jabali",
    "gn:country_code":"MX",
    "gn:dem":218,
    "gn:feature_class":"P",
    "gn:feature_code":"PPL",
    "gn:name":"El Jabal\u00ed",
    "gn:population":0,
    "gn:timezone":"America/Monterrey",
    "iso:country":"MX",
    "name:spa_x_preferred":[
        "El Jabal\u00ed"
    ],
    "wof:name":"El Jabali",
    "wof:placetype":"locality"
},
  "geometry": {"coordinates":[-99.88632,26.50448],"type":"Point"}
}