{
  "type": "Feature",
  "properties": {
    "gn:admin1_code":"5.0",
    "gn:asciiname":"El Jardin",
    "gn:country_code":"MX",
    "gn:dem":22,
    "gn:feature_class":"P",
    "gn:feature_code":"PPL",
    "gn:name":"El Jard\u00edn",
    "gn:population":0,
    "gn:timezone":"America/Mexico_City",
    "iso:country":"MX",
    "name:spa_x_preferred":[
        "El Jard\u00edn"
    ],
    "name:spa_x_variant":[
        "Casa El Jard\u00edn"
    ],
    "wof:name":"El Jardin",
    "wof:placetype":"locality"
},
  "geometry": {"coordinates":[-92.54423,15.10182],"type":"Point"}
}