{
  "type": "Feature",
  "properties": {
    "gn:admin1_code":"26",
    "gn:admin2_code":"30.0",
    "gn:asciiname":"San Javier",
    "gn:country_code":"MX",
    "gn:dem":16,
    "gn:feature_class":"P",
    "gn:feature_code":"PPL",
    "gn:name":"San Javier",
    "gn:population":0,
    "gn:timezone":"America/Hermosillo",
    "iso:country":"MX",
    "name:spa_x_preferred":[
        "San Javier"
    ],
    "name:und_x_variant":[
        "Rancho San Javi\u00e9r"
    ],
    "wof:name":"San Javier",
    "wof:placetype":"locality"
},
  "geometry": {"coordinates":[-111.94371,29.13026],"type":"Point"}
}