{
  "type": "Feature",
  "properties": {
    "gn:admin1_code":"19",
    "gn:admin2_code":"9.0",
    "gn:asciiname":"Don Gregorio",
    "gn:country_code":"MX",
    "gn:dem":324,
    "gn:feature_class":"P",
    "gn:feature_code":"PPL",
    "gn:name":"Don Gregorio",
    "gn:population":9,
    "gn:timezone":"America/Monterrey",
    "iso:country":"MX",
    "name:fra_x_preferred":[
        "Don Gregorio"
    ],
    "name:srp_x_preferred":[
        "\u0414\u043e\u043d \u0413\u0440\u0435\u0433\u043e\u0440\u0438\u043e"
    ],
    "wof:name":"Don Gregorio",
    "wof:placetype":"locality",
    "wof:population":9
},
  "geometry": {"coordinates":[-99.9975,25.56639],"type":"Point"}
}