{
  "type": "Feature",
  "properties": {
    "gn:admin1_code":"24",
    "gn:admin2_code":"53.0",
    "gn:asciiname":"Cuatecoyo",
    "gn:country_code":"MX",
    "gn:dem":91,
    "gn:feature_class":"P",
    "gn:feature_code":"PPL",
    "gn:name":"Cuatecoyo",
    "gn:population":213,
    "gn:timezone":"America/Mexico_City",
    "iso:country":"MX",
    "wof:name":"Cuatecoyo",
    "wof:placetype":"locality",
    "wof:population":213
},
  "geometry": {"coordinates":[-98.86861,21.46639],"type":"Point"}
}