{
  "type": "Feature",
  "properties": {
    "gn:admin1_code":"5",
    "gn:admin2_code":"59",
    "gn:asciiname":"Santa Rosa de Lima",
    "gn:country_code":"MX",
    "gn:dem":849,
    "gn:feature_class":"P",
    "gn:feature_code":"PPL",
    "gn:name":"Santa Rosa de Lima",
    "gn:population":25,
    "gn:timezone":"America/Mexico_City",
    "iso:country":"MX",
    "name:srp_x_preferred":[
        "\u0421\u0430\u043d\u0442\u0430 \u0420\u043e\u0441\u0430 \u0434\u0435 \u041b\u0438\u043c\u0430"
    ],
    "wof:name":"Santa Rosa de Lima",
    "wof:placetype":"locality",
    "wof:population":25
},
  "geometry": {"coordinates":[-91.825,16.99139],"type":"Point"}
}