{
  "type": "Feature",
  "properties": {
    "gn:admin1_code":"6",
    "gn:admin2_code":"29.0",
    "gn:asciiname":"San Francisco de la Joya",
    "gn:country_code":"MX",
    "gn:dem":2253,
    "gn:feature_class":"P",
    "gn:feature_code":"PPL",
    "gn:name":"San Francisco de la Joya",
    "gn:population":0,
    "gn:timezone":"America/Chihuahua",
    "iso:country":"MX",
    "name:spa_x_preferred":[
        "San Francisco de la Joya"
    ],
    "wof:name":"San Francisco de la Joya",
    "wof:placetype":"locality"
},
  "geometry": {"coordinates":[-106.87287000000001,25.98997],"type":"Point"}
}