{
  "type": "Feature",
  "properties": {
    "gn:admin1_code":"16.0",
    "gn:admin2_code":"101.0",
    "gn:asciiname":"Piedras de Lumbre",
    "gn:country_code":"MX",
    "gn:dem":1899,
    "gn:feature_class":"P",
    "gn:feature_code":"PPL",
    "gn:name":"Piedras de Lumbre",
    "gn:population":0,
    "gn:timezone":"America/Mexico_City",
    "iso:country":"MX",
    "name:spa_x_preferred":[
        "Piedras de Lumbre"
    ],
    "wof:name":"Piedras de Lumbre",
    "wof:placetype":"locality"
},
  "geometry": {"coordinates":[-101.09951,19.55161],"type":"Point"}
}