{
  "type": "Feature",
  "properties": {
    "gn:admin1_code":"9",
    "gn:admin2_code":"9",
    "gn:asciiname":"Teshutla",
    "gn:country_code":"MX",
    "gn:dem":2663,
    "gn:feature_class":"P",
    "gn:feature_code":"PPL",
    "gn:name":"Teshutla",
    "gn:population":14,
    "gn:timezone":"America/Mexico_City",
    "iso:country":"MX",
    "wof:name":"Teshutla",
    "wof:placetype":"locality",
    "wof:population":14
},
  "geometry": {"coordinates":[-98.98902,19.16547000000001],"type":"Point"}
}