{
  "type": "Feature",
  "properties": {
    "gn:admin1_code":"5",
    "gn:admin2_code":"37.0",
    "gn:asciiname":"Canton Florida",
    "gn:country_code":"MX",
    "gn:dem":283,
    "gn:feature_class":"P",
    "gn:feature_code":"PPL",
    "gn:name":"Cant\u00f3n Florida",
    "gn:population":115,
    "gn:timezone":"America/Mexico_City",
    "iso:country":"MX",
    "name:und_x_variant":[
        "Cant\u00f3n Florida"
    ],
    "wof:name":"Canton Florida",
    "wof:placetype":"locality",
    "wof:population":115
},
  "geometry": {"coordinates":[-92.34721999999999,15.06611],"type":"Point"}
}