{
  "type": "Feature",
  "properties": {
    "gn:admin1_code":"14",
    "gn:admin2_code":"50.0",
    "gn:asciiname":"San Cristobal Zapotitlan",
    "gn:country_code":"MX",
    "gn:dem":1538,
    "gn:feature_class":"P",
    "gn:feature_code":"PPL",
    "gn:name":"San Crist\u00f3bal Zapotitl\u00e1n",
    "gn:population":0,
    "gn:timezone":"America/Mexico_City",
    "iso:country":"MX",
    "name:und_x_variant":[
        "San Crist\u00f3bal",
        "San Crist\u00f3bal Zapot",
        "San Crist\u00f3bal Zapotitl\u00e1n"
    ],
    "wof:name":"San Cristobal Zapotitlan",
    "wof:placetype":"locality"
},
  "geometry": {"coordinates":[-103.36969000000001,20.22453],"type":"Point"}
}