{
  "type": "Feature",
  "properties": {
    "gn:admin1_code":"26",
    "gn:admin2_code":"42.0",
    "gn:asciiname":"Graciano Sanchez (Yorigibe)",
    "gn:country_code":"MX",
    "gn:dem":105,
    "gn:feature_class":"P",
    "gn:feature_code":"PPL",
    "gn:name":"Graciano S\u00e1nchez (Yorigibe)",
    "gn:population":5,
    "gn:timezone":"America/Hermosillo",
    "iso:country":"MX",
    "name:und_x_variant":[
        "Graciano S\u00e1nchez (Yorigibe)"
    ],
    "wof:name":"Graciano Sanchez (Yorigibe)",
    "wof:placetype":"locality",
    "wof:population":5
},
  "geometry": {"coordinates":[-109.30389,27.30056],"type":"Point"}
}