{
  "type": "Feature",
  "properties": {
    "iso:country":"MX",
    "name:spa_x_preferred":[
        "La Martinica"
    ],
    "qs:gn_adm0_cc":"MX",
    "qs:gn_local":3998655,
    "qs:gn_nam_loc":"Leon Guanajuato, Le\u00f3n, MX",
    "qs:gn_namadm1":"11",
    "qs:local_max":907,
    "qs:local_sum":2423,
    "qs:localhoods":13,
    "qs:name":"La Martinica",
    "qs:name_adm0":"M\u00e9xico",
    "qs:name_adm1":"Guanajuato",
    "qs:name_adm2":"Leon",
    "qs:name_local":"Le\u00f3n",
    "qs:photo_max":107,
    "qs:photo_sum":173,
    "qs:placetype":"Suburb",
    "qs:quad_count":10,
    "qs:woe_adm0":23424900,
    "qs:woe_adm1":2346274,
    "qs:woe_adm2":12600008,
    "qs:woe_lau":0,
    "qs:woe_local":131068,
    "qs:woe_ver":"7.10.0",
    "wof:lang":[
        "spa"
    ],
    "wof:name":"La Martinica",
    "wof:placetype":"neighbourhood"
},
  "geometry": {"coordinates":[-101.660155,21.115028],"type":"Point"}
}