{
  "type": "Feature",
  "properties": {
    "gn:admin1_code":"10.0",
    "gn:admin2_code":"14.0",
    "gn:asciiname":"Pino Caido",
    "gn:country_code":"MX",
    "gn:dem":2039,
    "gn:feature_class":"P",
    "gn:feature_code":"PPL",
    "gn:name":"Pino Caido",
    "gn:population":0,
    "gn:timezone":"America/Monterrey",
    "iso:country":"MX",
    "name:spa_x_preferred":[
        "Pino Caido"
    ],
    "wof:name":"Pino Caido",
    "wof:placetype":"locality"
},
  "geometry": {"coordinates":[-104.64664,22.8997],"type":"Point"}
}