{
  "type": "Feature",
  "properties": {
    "gn:admin1_code":"10",
    "gn:admin2_code":"4.0",
    "gn:asciiname":"Montecillos de Arriba",
    "gn:country_code":"MX",
    "gn:dem":1796,
    "gn:feature_class":"P",
    "gn:feature_code":"PPL",
    "gn:name":"Montecillos de Arriba",
    "gn:population":0,
    "gn:timezone":"America/Monterrey",
    "iso:country":"MX",
    "name:spa_x_preferred":[
        "Montecillos de Arriba"
    ],
    "wof:name":"Montecillos de Arriba",
    "wof:placetype":"locality"
},
  "geometry": {"coordinates":[-103.744,24.78619],"type":"Point"}
}