{
  "type": "Feature",
  "properties": {
    "gn:admin1_code":"18.0",
    "gn:admin2_code":"19.0",
    "gn:asciiname":"Puerto Blanco",
    "gn:country_code":"MX",
    "gn:dem":2268,
    "gn:feature_class":"P",
    "gn:feature_code":"PPL",
    "gn:name":"Puerto Blanco",
    "gn:population":0,
    "gn:timezone":"America/Mazatlan",
    "iso:country":"MX",
    "name:spa_x_preferred":[
        "Puerto Blanco"
    ],
    "name:spa_x_variant":[
        "El Manzamillas"
    ],
    "wof:name":"Puerto Blanco",
    "wof:placetype":"locality"
},
  "geometry": {"coordinates":[-104.04397,21.38326],"type":"Point"}
}