{
  "type": "Feature",
  "properties": {
    "gn:admin1_code":"27",
    "gn:admin2_code":"12.0",
    "gn:asciiname":"San Joaquin",
    "gn:country_code":"MX",
    "gn:dem":-1,
    "gn:feature_class":"P",
    "gn:feature_code":"PPL",
    "gn:name":"San Joaqu\u00edn",
    "gn:population":0,
    "gn:timezone":"America/Mexico_City",
    "iso:country":"MX",
    "wof:name":"San Joaquin",
    "wof:placetype":"locality"
},
  "geometry": {"coordinates":[-92.38333,18.01667],"type":"Point"}
}