{
  "type": "Feature",
  "properties": {
    "gn:admin1_code":"27",
    "gn:admin2_code":"12.0",
    "gn:asciiname":"Limbano Blandin",
    "gn:country_code":"MX",
    "gn:dem":27,
    "gn:feature_class":"P",
    "gn:feature_code":"PPL",
    "gn:name":"L\u00edmbano Bland\u00edn",
    "gn:population":0,
    "gn:timezone":"America/Mexico_City",
    "iso:country":"MX",
    "name:spa_x_preferred":[
        "Limbano Blandin"
    ],
    "name:spa_x_variant":[
        "L\u00edmbano Bland\u00edn",
        "Primera Secci\u00f3n"
    ],
    "wof:name":"Limbano Blandin",
    "wof:placetype":"locality"
},
  "geometry": {"coordinates":[-92.40997,17.7569],"type":"Point"}
}