{
  "type": "Feature",
  "properties": {
    "gn:admin1_code":"30",
    "gn:admin2_code":"173.0",
    "gn:asciiname":"Altamira",
    "gn:country_code":"MX",
    "gn:dem":132,
    "gn:feature_class":"P",
    "gn:feature_code":"PPL",
    "gn:name":"Altamira",
    "gn:population":60,
    "gn:timezone":"America/Mexico_City",
    "iso:country":"MX",
    "name:bel_x_preferred":[
        "\u0410\u043b\u044c\u0442\u0430\u043c\u0456\u0440\u0430"
    ],
    "name:ceb_x_preferred":[
        "Altamira"
    ],
    "name:dan_x_preferred":[
        "Altamira"
    ],
    "name:deu_x_preferred":[
        "Altamira"
    ],
    "name:epo_x_preferred":[
        "Altamira"
    ],
    "name:est_x_preferred":[
        "Altamira"
    ],
    "name:eus_x_preferred":[
        "Altamira"
    ],
    "name:fra_x_preferred":[
        "Altamira"
    ],
    "name:glg_x_preferred":[
        "Altamira"
    ],
    "name:hye_x_preferred":[
        "\u0531\u056c\u057f\u0561\u0574\u056b\u0580\u0561"
    ],
    "name:ita_x_preferred":[
        "Altamira"
    ],
    "name:jpn_x_preferred":[
        "\u30a2\u30eb\u30bf\u30df\u30e9"
    ],
    "name:kor_x_preferred":[
        "\uc54c\ud0c0\ubbf8\ub77c"
    ],
    "name:lit_x_preferred":[
        "Altamira"
    ],
    "name:mlg_x_preferred":[
        "Altamira"
    ],
    "name:nds_x_preferred":[
        "Altamira"
    ],
    "name:nld_x_preferred":[
        "Altamira"
    ],
    "name:nor_x_preferred":[
        "Altamira"
    ],
    "name:pol_x_preferred":[
        "Altamira"
    ],
    "name:por_x_preferred":[
        "Altamira"
    ],
    "name:ron_x_preferred":[
        "Altamira"
    ],
    "name:rus_x_preferred":[
        "\u0410\u043b\u044c\u0442\u0430\u043c\u0438\u0440\u0430"
    ],
    "name:sco_x_preferred":[
        "Altamira"
    ],
    "name:slk_x_preferred":[
        "Altamira"
    ],
    "name:spa_x_preferred":[
        "Altamira"
    ],
    "name:srp_x_preferred":[
        "\u0410\u043b\u0442\u0430\u043c\u0438\u0440\u0430"
    ],
    "name:swe_x_preferred":[
        "Altamira"
    ],
    "name:ukr_x_preferred":[
        "\u0410\u043b\u044c\u0442\u0430\u043c\u0456\u0440\u0430"
    ],
    "wof:name":"Altamira",
    "wof:placetype":"locality",
    "wof:population":60
},
  "geometry": {"coordinates":[-96.77028,18.5275],"type":"Point"}
}