{
  "type": "Feature",
  "properties": {
    "gn:admin1_code":"22",
    "gn:admin2_code":"16.0",
    "gn:asciiname":"San Gil",
    "gn:country_code":"MX",
    "gn:dem":1905,
    "gn:feature_class":"P",
    "gn:feature_code":"PPL",
    "gn:name":"San Gil",
    "gn:population":474,
    "gn:timezone":"America/Mexico_City",
    "iso:country":"MX",
    "wof:name":"San Gil",
    "wof:placetype":"locality",
    "wof:population":474
},
  "geometry": {"coordinates":[-100.06917,20.44306],"type":"Point"}
}