{
  "type": "Feature",
  "properties": {
    "gn:admin1_code":"22",
    "gn:admin2_code":"16.0",
    "gn:asciiname":"San Gil",
    "gn:country_code":"MX",
    "gn:dem":1905,
    "gn:feature_class":"P",
    "gn:feature_code":"PPL",
    "gn:name":"San Gil",
    "gn:population":474,
    "gn:timezone":"America/Mexico_City",
    "iso:country":"MX",
    "name:deu_x_preferred":[
        "San Gil"
    ],
    "name:fas_x_preferred":[
        "\u0633\u0627\u0646 \u062e\u06cc\u0644"
    ],
    "name:fra_x_preferred":[
        "San Gil"
    ],
    "name:glg_x_preferred":[
        "San Gil"
    ],
    "name:ita_x_preferred":[
        "San Gil"
    ],
    "name:kat_x_preferred":[
        "\u10e1\u10d0\u10dc-\u10ee\u10d8\u10da\u10d8"
    ],
    "name:lit_x_preferred":[
        "San Chilis"
    ],
    "name:msa_x_preferred":[
        "San Gil"
    ],
    "name:nld_x_preferred":[
        "San Gil"
    ],
    "name:spa_x_preferred":[
        "San Gil"
    ],
    "name:tgl_x_preferred":[
        "San Gil"
    ],
    "name:vie_x_preferred":[
        "San Gil"
    ],
    "name:war_x_preferred":[
        "San Gil"
    ],
    "name:zho_x_preferred":[
        "\u8056\u5e0c\u723e"
    ],
    "wof:name":"San Gil",
    "wof:placetype":"locality",
    "wof:population":474
},
  "geometry": {"coordinates":[-100.06917,20.44306],"type":"Point"}
}