{
  "type": "Feature",
  "properties": {
    "gn:admin1_code":"23",
    "gn:admin2_code":"8.0",
    "gn:asciiname":"San Manuelito",
    "gn:country_code":"MX",
    "gn:dem":9,
    "gn:feature_class":"P",
    "gn:feature_code":"PPL",
    "gn:name":"San Manuelito",
    "gn:population":0,
    "gn:timezone":"America/Cancun",
    "iso:country":"MX",
    "name:spa_x_preferred":[
        "San Manuelito"
    ],
    "name:und_x_variant":[
        "San Miguelito"
    ],
    "wof:name":"San Manuelito",
    "wof:placetype":"locality"
},
  "geometry": {"coordinates":[-87.01791,20.71144],"type":"Point"}
}