{
  "type": "Feature",
  "properties": {
    "gn:admin1_code":"32",
    "gn:admin2_code":"56.0",
    "gn:asciiname":"Cerro Santa Clara",
    "gn:country_code":"MX",
    "gn:dem":2527,
    "gn:feature_class":"P",
    "gn:feature_code":"PPL",
    "gn:name":"Cerro Santa Clara",
    "gn:population":5,
    "gn:timezone":"America/Mexico_City",
    "iso:country":"MX",
    "wof:name":"Cerro Santa Clara",
    "wof:placetype":"locality",
    "wof:population":5
},
  "geometry": {"coordinates":[-102.56833,22.78917],"type":"Point"}
}