{
  "type": "Feature",
  "properties": {
    "gn:admin1_code":"6",
    "gn:admin2_code":"46.0",
    "gn:asciiname":"Molinares",
    "gn:country_code":"MX",
    "gn:dem":810,
    "gn:feature_class":"P",
    "gn:feature_code":"PPL",
    "gn:name":"Molinares",
    "gn:population":6,
    "gn:timezone":"America/Chihuahua",
    "iso:country":"MX",
    "wof:name":"Molinares",
    "wof:placetype":"locality",
    "wof:population":6
},
  "geometry": {"coordinates":[-107.62572,26.68938],"type":"Point"}
}