{
  "type": "Feature",
  "properties": {
    "iso:country":"MX",
    "name:spa_x_preferred":[
        "Lomas Del Rio"
    ],
    "name:und_x_variant":[
        "Malpilca"
    ],
    "qs:gn_adm0_cc":"MX",
    "qs:gn_fcode":"PPL",
    "qs:gn_local":3521168,
    "qs:gn_nam_loc":"Poza Rica de Hidalgo, Veracruz-Llave, MX",
    "qs:gn_namadm1":"30",
    "qs:gn_name":"Lomas de Carrillo",
    "qs:local_max":44,
    "qs:local_sum":94,
    "qs:localhoods":3,
    "qs:name":"Lomas Del Rio",
    "qs:name_adm0":"M\u00e9xico",
    "qs:name_adm1":"Veracruz-Llave",
    "qs:name_adm2":"Poza Rica de Hidalgo",
    "qs:name_local":"Poza Rica de Hidalgo",
    "qs:photo_max":8,
    "qs:photo_sum":25,
    "qs:placetype":"Suburb",
    "qs:quad_count":6,
    "qs:woe_adm0":23424900,
    "qs:woe_adm1":2346293,
    "qs:woe_adm2":12601853,
    "qs:woe_lau":0,
    "qs:woe_local":137337,
    "qs:woe_ver":"7.10.0",
    "wof:lang":[
        "spa"
    ],
    "wof:name":"Lomas Del Rio",
    "wof:placetype":"neighbourhood"
},
  "geometry": {"coordinates":[-97.450818,20.546086],"type":"Point"}
}