{
  "type": "Feature",
  "properties": {
    "gn:admin1_code":"11",
    "gn:admin2_code":"19.0",
    "gn:asciiname":"Pilas de la Salitrera",
    "gn:country_code":"MX",
    "gn:dem":2111,
    "gn:feature_class":"P",
    "gn:feature_code":"PPL",
    "gn:name":"Pilas de la Salitrera",
    "gn:population":0,
    "gn:timezone":"America/Mexico_City",
    "iso:country":"MX",
    "name:spa_x_preferred":[
        "Pilas de la Salitrera"
    ],
    "name:und_x_variant":[
        "Pilas del Sa\u00faz",
        "Pilas",
        "Las Pilas de la Salitrera"
    ],
    "wof:name":"Pilas de la Salitrera",
    "wof:placetype":"locality"
},
  "geometry": {"coordinates":[-100.58947999999999,20.17695],"type":"Point"}
}