{
  "type": "Feature",
  "properties": {
    "gn:admin1_code":"16",
    "gn:admin2_code":"12.0",
    "gn:asciiname":"Pinzandaro",
    "gn:country_code":"MX",
    "gn:dem":259,
    "gn:feature_class":"P",
    "gn:feature_code":"PPL",
    "gn:name":"Pinz\u00e1ndaro",
    "gn:population":0,
    "gn:timezone":"America/Mexico_City",
    "iso:country":"MX",
    "name:spa_x_preferred":[
        "Pinz\u00e1ndaro"
    ],
    "wof:name":"Pinzandaro",
    "wof:placetype":"locality"
},
  "geometry": {"coordinates":[-102.54082,19.10928],"type":"Point"}
}