{
  "type": "Feature",
  "properties": {
    "gn:admin1_code":"15.0",
    "gn:asciiname":"Las Calabazas",
    "gn:country_code":"MX",
    "gn:dem":14,
    "gn:feature_class":"P",
    "gn:feature_code":"PPL",
    "gn:name":"Las Calabazas",
    "gn:population":0,
    "gn:timezone":"America/Mexico_City",
    "iso:country":"MX",
    "name:spa_x_preferred":[
        "Las Calabazas"
    ],
    "wof:name":"Las Calabazas",
    "wof:placetype":"locality"
},
  "geometry": {"coordinates":[-102.4152,18.00096],"type":"Point"}
}