{
  "type": "Feature",
  "properties": {
    "gn:admin1_code":"14",
    "gn:admin2_code":"69",
    "gn:asciiname":"Panales",
    "gn:country_code":"MX",
    "gn:dem":1394,
    "gn:feature_class":"P",
    "gn:feature_code":"PPL",
    "gn:name":"Panales",
    "gn:population":25,
    "gn:timezone":"America/Mexico_City",
    "iso:country":"MX",
    "wof:name":"Panales",
    "wof:placetype":"locality",
    "wof:population":25
},
  "geometry": {"coordinates":[-102.84056,19.72944],"type":"Point"}
}