{
  "type": "Feature",
  "properties": {
    "gn:admin1_code":"6.0",
    "gn:admin2_code":"54.0",
    "gn:asciiname":"Dos Alamos",
    "gn:country_code":"MX",
    "gn:dem":2067,
    "gn:feature_class":"P",
    "gn:feature_code":"PPL",
    "gn:name":"Dos Alamos",
    "gn:population":0,
    "gn:timezone":"America/Chihuahua",
    "iso:country":"MX",
    "name:spa_x_preferred":[
        "Dos Alamos"
    ],
    "wof:name":"Dos Alamos",
    "wof:placetype":"locality"
},
  "geometry": {"coordinates":[-106.84788,28.81064000000001],"type":"Point"}
}