{
  "type": "Feature",
  "properties": {
    "gn:admin1_code":"30",
    "gn:admin2_code":"61.0",
    "gn:asciiname":"Jose Valencia Ayala",
    "gn:country_code":"MX",
    "gn:dem":27,
    "gn:feature_class":"P",
    "gn:feature_code":"PPL",
    "gn:name":"Jos\u00e9 Valencia Ayala",
    "gn:population":7,
    "gn:timezone":"America/Mexico_City",
    "iso:country":"MX",
    "name:und_x_variant":[
        "Jos\u00e9 Valencia Ayala"
    ],
    "wof:name":"Jose Valencia Ayala",
    "wof:placetype":"locality",
    "wof:population":7
},
  "geometry": {"coordinates":[-93.99861,17.64472],"type":"Point"}
}