{
  "type": "Feature",
  "properties": {
    "gn:admin1_code":"12",
    "gn:admin2_code":"52.0",
    "gn:asciiname":"Pajarito Chiquito",
    "gn:country_code":"MX",
    "gn:dem":938,
    "gn:feature_class":"P",
    "gn:feature_code":"PPL",
    "gn:name":"Pajarito Chiquito",
    "gn:population":82,
    "gn:timezone":"America/Mexico_City",
    "iso:country":"MX",
    "wof:name":"Pajarito Chiquito",
    "wof:placetype":"locality",
    "wof:population":82
},
  "geometry": {"coordinates":[-98.6489,16.94036],"type":"Point"}
}