{
  "type": "Feature",
  "properties": {
    "gn:admin1_code":"20",
    "gn:admin2_code":"171.0",
    "gn:asciiname":"Cerro Trueno",
    "gn:country_code":"MX",
    "gn:dem":992,
    "gn:feature_class":"P",
    "gn:feature_code":"PPL",
    "gn:name":"Cerro Trueno",
    "gn:population":161,
    "gn:timezone":"America/Mexico_City",
    "iso:country":"MX",
    "wof:name":"Cerro Trueno",
    "wof:placetype":"locality",
    "wof:population":161
},
  "geometry": {"coordinates":[-96.73860999999999,18.20972],"type":"Point"}
}