{
  "type": "Feature",
  "properties": {
    "gn:admin1_code":"32.0",
    "gn:admin2_code":"49.0",
    "gn:asciiname":"Potrero del Cerrito",
    "gn:country_code":"MX",
    "gn:dem":2338,
    "gn:feature_class":"P",
    "gn:feature_code":"PPL",
    "gn:name":"Potrero del Cerrito",
    "gn:population":0,
    "gn:timezone":"America/Mexico_City",
    "iso:country":"MX",
    "name:spa_x_preferred":[
        "Potrero del Cerrito"
    ],
    "wof:name":"Potrero del Cerrito",
    "wof:placetype":"locality"
},
  "geometry": {"coordinates":[-103.26439000000001,22.8442],"type":"Point"}
}