{
  "type": "Feature",
  "properties": {
    "gn:admin1_code":"2",
    "gn:admin2_code":"2.0",
    "gn:asciiname":"Sesvania",
    "gn:country_code":"MX",
    "gn:dem":8,
    "gn:feature_class":"P",
    "gn:feature_code":"PPL",
    "gn:name":"Sesvania",
    "gn:population":42,
    "gn:timezone":"America/Tijuana",
    "iso:country":"MX",
    "wof:name":"Sesvania",
    "wof:placetype":"locality",
    "wof:population":42
},
  "geometry": {"coordinates":[-115.30110999999999,32.56722],"type":"Point"}
}