{
  "type": "Feature",
  "properties": {
    "gn:admin1_code":"10",
    "gn:admin2_code":"24.0",
    "gn:asciiname":"Playas",
    "gn:country_code":"MX",
    "gn:dem":1879,
    "gn:feature_class":"P",
    "gn:feature_code":"PPL",
    "gn:name":"Playas",
    "gn:population":0,
    "gn:timezone":"America/Monterrey",
    "iso:country":"MX",
    "wof:name":"Playas",
    "wof:placetype":"locality"
},
  "geometry": {"coordinates":[-104.41667,25.28333],"type":"Point"}
}