{
  "type": "Feature",
  "properties": {
    "gn:admin1_code":"12",
    "gn:admin2_code":"29.0",
    "gn:asciiname":"Tepechicotlan",
    "gn:country_code":"MX",
    "gn:dem":1042,
    "gn:feature_class":"P",
    "gn:feature_code":"PPL",
    "gn:name":"Tepechicotl\u00e1n",
    "gn:population":1480,
    "gn:timezone":"America/Mexico_City",
    "iso:country":"MX",
    "name:und_x_variant":[
        "Tepechicotl\u00e1n"
    ],
    "wof:name":"Tepechicotlan",
    "wof:placetype":"locality",
    "wof:population":1480
},
  "geometry": {"coordinates":[-99.41549000000001,17.48317],"type":"Point"}
}