{
  "type": "Feature",
  "properties": {
    "gn:admin1_code":"26",
    "gn:admin2_code":"18.0",
    "gn:asciiname":"Puente de Picos",
    "gn:country_code":"MX",
    "gn:dem":46,
    "gn:feature_class":"P",
    "gn:feature_code":"PPL",
    "gn:name":"Puente de Picos",
    "gn:population":281,
    "gn:timezone":"America/Hermosillo",
    "iso:country":"MX",
    "name:spa_x_preferred":[
        "Puente de Picos"
    ],
    "wof:name":"Puente de Picos",
    "wof:placetype":"locality",
    "wof:population":281
},
  "geometry": {"coordinates":[-109.92482,27.54351],"type":"Point"}
}