{
  "type": "Feature",
  "properties": {
    "gn:admin1_code":"12",
    "gn:admin2_code":"73.0",
    "gn:asciiname":"El Horcon Solo",
    "gn:country_code":"MX",
    "gn:dem":445,
    "gn:feature_class":"P",
    "gn:feature_code":"PPL",
    "gn:name":"El Horc\u00f3n Solo",
    "gn:population":0,
    "gn:timezone":"America/Mexico_City",
    "iso:country":"MX",
    "name:spa_x_preferred":[
        "El Horc\u00f3n Solo"
    ],
    "wof:name":"El Horcon Solo",
    "wof:placetype":"locality"
},
  "geometry": {"coordinates":[-101.32456999999999,18.40303],"type":"Point"}
}