{
  "type": "Feature",
  "properties": {
    "gn:admin1_code":"6",
    "gn:admin2_code":"15.0",
    "gn:asciiname":"Los Ibarra",
    "gn:country_code":"MX",
    "gn:dem":1263,
    "gn:feature_class":"P",
    "gn:feature_code":"PPL",
    "gn:name":"Los Ibarra",
    "gn:population":0,
    "gn:timezone":"America/Chihuahua",
    "iso:country":"MX",
    "wof:name":"Los Ibarra",
    "wof:placetype":"locality"
},
  "geometry": {"coordinates":[-105.05,29.43333],"type":"Point"}
}