{
  "type": "Feature",
  "properties": {
    "gn:admin1_code":"6",
    "gn:admin2_code":"36.0",
    "gn:asciiname":"El Predio",
    "gn:country_code":"MX",
    "gn:dem":1374,
    "gn:feature_class":"P",
    "gn:feature_code":"PPL",
    "gn:name":"El Predio",
    "gn:population":89,
    "gn:timezone":"America/Chihuahua",
    "iso:country":"MX",
    "wof:name":"El Predio",
    "wof:placetype":"locality",
    "wof:population":89
},
  "geometry": {"coordinates":[-104.92931000000002,27.1894],"type":"Point"}
}