{
  "type": "Feature",
  "properties": {
    "gn:admin1_code":"6",
    "gn:admin2_code":"49.0",
    "gn:asciiname":"Paraje las Minas",
    "gn:country_code":"MX",
    "gn:dem":2119,
    "gn:feature_class":"P",
    "gn:feature_code":"PPL",
    "gn:name":"Paraje las Minas",
    "gn:population":0,
    "gn:timezone":"America/Chihuahua",
    "iso:country":"MX",
    "name:spa_x_preferred":[
        "Paraje Las Minas"
    ],
    "wof:name":"Paraje las Minas",
    "wof:placetype":"locality"
},
  "geometry": {"coordinates":[-106.68441,27.24076],"type":"Point"}
}