{
  "type": "Feature",
  "properties": {
    "gn:admin1_code":"11",
    "gn:admin2_code":"3.0",
    "gn:asciiname":"La Mesa",
    "gn:country_code":"MX",
    "gn:dem":1873,
    "gn:feature_class":"P",
    "gn:feature_code":"PPL",
    "gn:name":"La Mesa",
    "gn:population":6,
    "gn:timezone":"America/Mexico_City",
    "iso:country":"MX",
    "name:ceb_x_preferred":[
        "La Mesa"
    ],
    "name:deu_x_preferred":[
        "La Mesa"
    ],
    "name:fra_x_preferred":[
        "La Mesa"
    ],
    "name:ita_x_preferred":[
        "La Mesa"
    ],
    "name:nld_x_preferred":[
        "La Mesa"
    ],
    "name:pol_x_preferred":[
        "La Mesa"
    ],
    "name:por_x_preferred":[
        "La Mesa"
    ],
    "name:sco_x_preferred":[
        "La Mesa"
    ],
    "name:spa_x_preferred":[
        "La Mesa"
    ],
    "name:srp_x_preferred":[
        "\u041b\u0430 \u041c\u0435\u0441\u0430"
    ],
    "name:swe_x_preferred":[
        "La Mesa"
    ],
    "name:vie_x_preferred":[
        "La Mesa"
    ],
    "wof:name":"La Mesa",
    "wof:placetype":"locality",
    "wof:population":6
},
  "geometry": {"coordinates":[-100.86417,20.96833],"type":"Point"}
}