{
  "type": "Feature",
  "properties": {
    "gn:admin1_code":"11",
    "gn:admin2_code":"3.0",
    "gn:asciiname":"La Mesa",
    "gn:country_code":"MX",
    "gn:dem":1873,
    "gn:feature_class":"P",
    "gn:feature_code":"PPL",
    "gn:name":"La Mesa",
    "gn:population":6,
    "gn:timezone":"America/Mexico_City",
    "iso:country":"MX",
    "wof:name":"La Mesa",
    "wof:placetype":"locality",
    "wof:population":6
},
  "geometry": {"coordinates":[-100.86417,20.96833],"type":"Point"}
}