{
  "type": "Feature",
  "properties": {
    "gn:admin1_code":"26",
    "gn:admin2_code":"71.0",
    "gn:asciiname":"Miguel Hidalgo",
    "gn:country_code":"MX",
    "gn:dem":12,
    "gn:feature_class":"P",
    "gn:feature_code":"PPL",
    "gn:name":"Miguel Hidalgo",
    "gn:population":0,
    "gn:timezone":"America/Hermosillo",
    "iso:country":"MX",
    "name:spa_x_preferred":[
        "Miguel Hidalgo"
    ],
    "name:spa_x_variant":[
        "El Mo\u00f1o"
    ],
    "wof:name":"Miguel Hidalgo",
    "wof:placetype":"locality"
},
  "geometry": {"coordinates":[-109.8925,27.10722],"type":"Point"}
}