{
  "type": "Feature",
  "properties": {
    "gn:admin1_code":"7",
    "gn:admin2_code":"15.0",
    "gn:asciiname":"El Lobo",
    "gn:country_code":"MX",
    "gn:dem":284,
    "gn:feature_class":"P",
    "gn:feature_code":"PPL",
    "gn:name":"El Lobo",
    "gn:population":0,
    "gn:timezone":"America/Monterrey",
    "iso:country":"MX",
    "name:spa_x_preferred":[
        "El Lobo"
    ],
    "name:und_x_variant":[
        "Rancho El Lobo"
    ],
    "wof:name":"El Lobo",
    "wof:placetype":"locality"
},
  "geometry": {"coordinates":[-100.83037,27.47322],"type":"Point"}
}