{
  "type": "Feature",
  "properties": {
    "gn:admin1_code":"28.0",
    "gn:admin2_code":"21.0",
    "gn:asciiname":"Ampliacion las Palmas",
    "gn:country_code":"MX",
    "gn:dem":69,
    "gn:feature_class":"P",
    "gn:feature_code":"PPL",
    "gn:name":"Ampliaci\u00f3n las Palmas",
    "gn:population":77,
    "gn:timezone":"America/Monterrey",
    "iso:country":"MX",
    "name:spa_x_preferred":[
        "Ampliaci\u00f3n las Palmas"
    ],
    "wof:name":"Ampliacion las Palmas",
    "wof:placetype":"locality",
    "wof:population":77
},
  "geometry": {"coordinates":[-99.02139,22.78917],"type":"Point"}
}