{
  "type": "Feature",
  "properties": {
    "gn:admin1_code":"24",
    "gn:admin2_code":"18.0",
    "gn:asciiname":"Alaquich",
    "gn:country_code":"MX",
    "gn:dem":275,
    "gn:feature_class":"P",
    "gn:feature_code":"PPL",
    "gn:name":"Alaquich",
    "gn:population":227,
    "gn:timezone":"America/Mexico_City",
    "iso:country":"MX",
    "wof:name":"Alaquich",
    "wof:placetype":"locality",
    "wof:population":227
},
  "geometry": {"coordinates":[-99.01889,21.54528],"type":"Point"}
}