{
  "type": "Feature",
  "properties": {
    "gn:gn_country":"MX",
    "gn:gn_fcode":"PPL",
    "gn:gn_pop":8591,
    "gn:population":8591,
    "iso:country":"MX",
    "name:spa_x_preferred":[
        "Morelos"
    ],
    "name:unk_x_variant":[
        "Ant\u00fanez"
    ],
    "qs_pg:aaroncc":"MX",
    "qs_pg:gn_country":"MX",
    "qs_pg:gn_fcode":"PPL",
    "qs_pg:gn_pop":8591,
    "qs_pg:name":"Antunes",
    "qs_pg:photos_9r":0,
    "qs_pg:photos_sr":0,
    "qs_pg:pop_sr":5,
    "qs_pg:qs_pg_placetype":"locality",
    "wof:name":"Antunes",
    "wof:placetype":"locality",
    "wof:population":8591
},
  "geometry": {"coordinates":[-102.20488,19.01477],"type":"Point"}
}