{
  "type": "Feature",
  "properties": {
    "gn:admin1_code":"24",
    "gn:admin2_code":"39.0",
    "gn:asciiname":"Zacazonapan",
    "gn:country_code":"MX",
    "gn:dem":128,
    "gn:feature_class":"P",
    "gn:feature_code":"PPL",
    "gn:name":"Zacazonapan",
    "gn:population":6,
    "gn:timezone":"America/Mexico_City",
    "iso:country":"MX",
    "name:cat_x_preferred":[
        "Zacazonapan"
    ],
    "name:ceb_x_preferred":[
        "Zacazonapan"
    ],
    "name:epo_x_preferred":[
        "Zacazonapan"
    ],
    "name:eus_x_preferred":[
        "Zacazonapan"
    ],
    "name:fra_x_preferred":[
        "Zacazonapan"
    ],
    "name:ita_x_preferred":[
        "Zacazonapan"
    ],
    "name:lad_x_preferred":[
        "Zacazonapan"
    ],
    "name:nor_x_preferred":[
        "Zacazonapan"
    ],
    "name:por_x_preferred":[
        "Zacazonapan"
    ],
    "name:sco_x_preferred":[
        "Zacazonapan"
    ],
    "name:srp_x_preferred":[
        "\u041e\u043f\u0448\u0442\u0438\u043d\u0430 \u0417\u0430\u043a\u0430\u0437\u043e\u043d\u0430\u043f\u0430\u043d"
    ],
    "name:swe_x_preferred":[
        "Zacazonapan"
    ],
    "name:urd_x_preferred":[
        "\u0632\u06a9\u0632\u0648\u0646\u0627\u067e\u0627\u0646"
    ],
    "name:vie_x_preferred":[
        "Zacazonapan"
    ],
    "wof:name":"Zacazonapan",
    "wof:placetype":"locality",
    "wof:population":6
},
  "geometry": {"coordinates":[-98.78667,21.6025],"type":"Point"}
}