{
  "type": "Feature",
  "properties": {
    "gn:admin1_code":"8",
    "gn:admin2_code":"4.0",
    "gn:asciiname":"El Palapo",
    "gn:country_code":"MX",
    "gn:dem":282,
    "gn:feature_class":"P",
    "gn:feature_code":"PPL",
    "gn:name":"El Palapo",
    "gn:population":5,
    "gn:timezone":"America/Mexico_City",
    "iso:country":"MX",
    "wof:name":"El Palapo",
    "wof:placetype":"locality",
    "wof:population":5
},
  "geometry": {"coordinates":[-103.91500000000001,19.19972000000001],"type":"Point"}
}