{
  "type": "Feature",
  "properties": {
    "gn:admin1_code":"16",
    "gn:admin2_code":"97.0",
    "gn:asciiname":"Las Parotas",
    "gn:country_code":"MX",
    "gn:dem":586,
    "gn:feature_class":"P",
    "gn:feature_code":"PPL",
    "gn:name":"Las Parotas",
    "gn:population":0,
    "gn:timezone":"America/Mexico_City",
    "iso:country":"MX",
    "name:spa_x_preferred":[
        "Las Parotas"
    ],
    "wof:name":"Las Parotas",
    "wof:placetype":"locality"
},
  "geometry": {"coordinates":[-101.36920000000001,18.8607],"type":"Point"}
}