{
  "type": "Feature",
  "properties": {
    "gn:admin1_code":"30",
    "gn:admin2_code":"149.0",
    "gn:asciiname":"Saltillo",
    "gn:country_code":"MX",
    "gn:dem":200,
    "gn:feature_class":"P",
    "gn:feature_code":"PPL",
    "gn:name":"Saltillo",
    "gn:population":0,
    "gn:timezone":"America/Mexico_City",
    "iso:country":"MX",
    "name:spa_x_preferred":[
        "Saltillo"
    ],
    "name:und_x_variant":[
        "Mirador Saltillo"
    ],
    "wof:name":"Saltillo",
    "wof:placetype":"locality"
},
  "geometry": {"coordinates":[-94.85325,18.15893],"type":"Point"}
}