{
  "type": "Feature",
  "properties": {
    "gn:admin1_code":"11.0",
    "gn:admin2_code":"7.0",
    "gn:asciiname":"La Cano",
    "gn:country_code":"MX",
    "gn:dem":1755,
    "gn:feature_class":"P",
    "gn:feature_code":"PPL",
    "gn:name":"La Cano",
    "gn:population":0,
    "gn:timezone":"America/Mexico_City",
    "iso:country":"MX",
    "name:spa_x_preferred":[
        "La Cano"
    ],
    "wof:name":"La Cano",
    "wof:placetype":"locality"
},
  "geometry": {"coordinates":[-100.78261000000001,20.53014],"type":"Point"}
}