{
  "type": "Feature",
  "properties": {
    "gn:admin1_code":"24",
    "gn:admin2_code":"13",
    "gn:asciiname":"Colonia Rodriguez",
    "gn:country_code":"MX",
    "gn:dem":103,
    "gn:feature_class":"P",
    "gn:feature_code":"PPL",
    "gn:name":"Colonia Rodr\u00edguez",
    "gn:population":40,
    "gn:timezone":"America/Mexico_City",
    "iso:country":"MX",
    "name:und_x_variant":[
        "Colonia Rodr\u00edguez"
    ],
    "wof:name":"Colonia Rodriguez",
    "wof:placetype":"locality",
    "wof:population":40
},
  "geometry": {"coordinates":[-98.96889,21.965],"type":"Point"}
}