{
  "type": "Feature",
  "properties": {
    "gn:admin1_code":"18.0",
    "gn:admin2_code":"9.0",
    "gn:asciiname":"El Cascabel",
    "gn:country_code":"MX",
    "gn:dem":412,
    "gn:feature_class":"P",
    "gn:feature_code":"PPL",
    "gn:name":"El Cascabel",
    "gn:population":0,
    "gn:timezone":"America/Mazatlan",
    "iso:country":"MX",
    "name:spa_x_preferred":[
        "El Cascabel"
    ],
    "wof:name":"El Cascabel",
    "wof:placetype":"locality"
},
  "geometry": {"coordinates":[-104.53842,22.19239],"type":"Point"}
}