{
  "type": "Feature",
  "properties": {
    "gn:admin1_code":"5.0",
    "gn:admin2_code":"44.0",
    "gn:asciiname":"Llano Alto",
    "gn:country_code":"MX",
    "gn:dem":1155,
    "gn:feature_class":"P",
    "gn:feature_code":"PPL",
    "gn:name":"Llano Alto",
    "gn:population":0,
    "gn:timezone":"America/Mexico_City",
    "iso:country":"MX",
    "name:spa_x_preferred":[
        "El Llano"
    ],
    "name:spa_x_variant":[
        "Llano Alto"
    ],
    "wof:name":"Llano Alto",
    "wof:placetype":"locality"
},
  "geometry": {"coordinates":[-92.87925,16.81355],"type":"Point"}
}