{
  "type": "Feature",
  "properties": {
    "gn:admin1_code":"7.0",
    "gn:admin2_code":"14.0",
    "gn:asciiname":"Enramada",
    "gn:cc2":"MX",
    "gn:country_code":"MX",
    "gn:dem":339,
    "gn:feature_class":"P",
    "gn:feature_code":"PPL",
    "gn:name":"Enramada",
    "gn:population":0,
    "gn:timezone":"America/Monterrey",
    "iso:country":"MX",
    "name:und_x_variant":[
        "Enrramada",
        "Enramada"
    ],
    "wof:name":"Enramada",
    "wof:placetype":"locality"
},
  "geometry": {"coordinates":[-100.91667,28.91667],"type":"Point"}
}