{
  "type": "Feature",
  "properties": {
    "gn:admin1_code":"20",
    "gn:admin2_code":"498.0",
    "gn:asciiname":"San Juan Jaltepec",
    "gn:country_code":"MX",
    "gn:dem":361,
    "gn:feature_class":"P",
    "gn:feature_code":"PPL",
    "gn:name":"San Juan Jaltepec",
    "gn:population":0,
    "gn:timezone":"America/Mexico_City",
    "iso:country":"MX",
    "name:und_x_variant":[
        "Jaltepec",
        "San Juan",
        "San Juan Jaltepec"
    ],
    "wof:name":"San Juan Jaltepec",
    "wof:placetype":"locality"
},
  "geometry": {"coordinates":[-95.66262999999999,17.35264],"type":"Point"}
}