{
  "type": "Feature",
  "properties": {
    "gn:admin1_code":"5",
    "gn:admin2_code":"32.0",
    "gn:asciiname":"Maria Jose",
    "gn:country_code":"MX",
    "gn:dem":53,
    "gn:feature_class":"P",
    "gn:feature_code":"PPL",
    "gn:name":"Mar\u00eda Jos\u00e9",
    "gn:population":6,
    "gn:timezone":"America/Mexico_City",
    "iso:country":"MX",
    "name:und_x_variant":[
        "Mar\u00eda Jos\u00e9"
    ],
    "wof:name":"Maria Jose",
    "wof:placetype":"locality",
    "wof:population":6
},
  "geometry": {"coordinates":[-92.66667,15.30528],"type":"Point"}
}