{
  "type": "Feature",
  "properties": {
    "gn:admin1_code":"19",
    "gn:admin2_code":"22.0",
    "gn:asciiname":"Santa Engracia",
    "gn:country_code":"MX",
    "gn:dem":226,
    "gn:feature_class":"P",
    "gn:feature_code":"PPL",
    "gn:name":"Santa Engracia",
    "gn:population":0,
    "gn:timezone":"America/Monterrey",
    "iso:country":"MX",
    "name:und_x_variant":[
        "Hacienda Santa Engracia",
        "Santa Engracia"
    ],
    "wof:name":"Santa Engracia",
    "wof:placetype":"locality"
},
  "geometry": {"coordinates":[-99.55898999999999,25.41337],"type":"Point"}
}