{
  "type": "Feature",
  "properties": {
    "gn:admin1_code":"11.0",
    "gn:asciiname":"Tanques del Mezquitillo",
    "gn:country_code":"MX",
    "gn:dem":1779,
    "gn:feature_class":"P",
    "gn:feature_code":"PPL",
    "gn:name":"Tanques del Mezquitillo",
    "gn:population":0,
    "gn:timezone":"America/Mexico_City",
    "iso:country":"MX",
    "name:spa_x_preferred":[
        "Tanques del Mezquitillo"
    ],
    "name:spa_x_variant":[
        "Los Tanques"
    ],
    "wof:name":"Tanques del Mezquitillo",
    "wof:placetype":"locality"
},
  "geometry": {"coordinates":[-101.81219,20.95208],"type":"Point"}
}