{
  "type": "Feature",
  "properties": {
    "gn:admin1_code":"6.0",
    "gn:admin2_code":"14.0",
    "gn:asciiname":"Laguna la Estacada",
    "gn:country_code":"MX",
    "gn:dem":1537,
    "gn:feature_class":"P",
    "gn:feature_code":"PPL",
    "gn:name":"Laguna la Estacada",
    "gn:population":2,
    "gn:timezone":"America/Chihuahua",
    "iso:country":"MX",
    "name:spa_x_preferred":[
        "Laguna la Estacada"
    ],
    "wof:name":"Laguna la Estacada",
    "wof:placetype":"locality",
    "wof:population":2
},
  "geometry": {"coordinates":[-104.80880000000001,26.55664],"type":"Point"}
}