{
  "type": "Feature",
  "properties": {
    "gn:admin1_code":"9",
    "gn:admin2_code":"4.0",
    "gn:asciiname":"Rancho Santa Laura",
    "gn:country_code":"MX",
    "gn:dem":2782,
    "gn:feature_class":"P",
    "gn:feature_code":"PPL",
    "gn:name":"Rancho Santa Laura",
    "gn:population":61,
    "gn:timezone":"America/Mexico_City",
    "iso:country":"MX",
    "wof:name":"Rancho Santa Laura",
    "wof:placetype":"locality",
    "wof:population":61
},
  "geometry": {"coordinates":[-99.32056,19.34306],"type":"Point"}
}