{
  "type": "Feature",
  "properties": {
    "gn:admin1_code":"12.0",
    "gn:admin2_code":"6.0",
    "gn:asciiname":"Las Trincheras",
    "gn:country_code":"MX",
    "gn:dem":761,
    "gn:feature_class":"P",
    "gn:feature_code":"PPL",
    "gn:name":"Las Trincheras",
    "gn:population":0,
    "gn:timezone":"America/Mexico_City",
    "iso:country":"MX",
    "name:spa_x_preferred":[
        "Las Trincheras"
    ],
    "wof:name":"Las Trincheras",
    "wof:placetype":"locality"
},
  "geometry": {"coordinates":[-100.08177000000001,18.01906],"type":"Point"}
}