{
  "type": "Feature",
  "properties": {
    "gn:admin1_code":"30",
    "gn:admin2_code":"72.0",
    "gn:asciiname":"El Crucero de Jacales",
    "gn:country_code":"MX",
    "gn:dem":2573,
    "gn:feature_class":"P",
    "gn:feature_code":"PPL",
    "gn:name":"El Crucero de Jacales",
    "gn:population":0,
    "gn:timezone":"America/Mexico_City",
    "iso:country":"MX",
    "name:spa_x_preferred":[
        "El Crucero de Jacales"
    ],
    "name:und_x_variant":[
        "Jacales",
        "Los Jacales"
    ],
    "wof:name":"El Crucero de Jacales",
    "wof:placetype":"locality"
},
  "geometry": {"coordinates":[-98.45735999999999,20.41584],"type":"Point"}
}