{
  "type": "Feature",
  "properties": {
    "gn:admin1_code":"16.0",
    "gn:admin2_code":"15.0",
    "gn:asciiname":"Los Fernandez",
    "gn:country_code":"MX",
    "gn:dem":1966,
    "gn:feature_class":"P",
    "gn:feature_code":"PPL",
    "gn:name":"Los Fern\u00e1ndez",
    "gn:population":0,
    "gn:timezone":"America/Mexico_City",
    "iso:country":"MX",
    "name:spa_x_preferred":[
        "Los Fern\u00e1ndez"
    ],
    "wof:name":"Los Fernandez",
    "wof:placetype":"locality"
},
  "geometry": {"coordinates":[-103.04541999999999,18.85763],"type":"Point"}
}