{
  "type": "Feature",
  "properties": {
    "gn:admin1_code":"16.0",
    "gn:admin2_code":"19.0",
    "gn:asciiname":"El Tajo",
    "gn:country_code":"MX",
    "gn:dem":1375,
    "gn:feature_class":"P",
    "gn:feature_code":"PPL",
    "gn:name":"El Tajo",
    "gn:population":0,
    "gn:timezone":"America/Mexico_City",
    "iso:country":"MX",
    "wof:name":"El Tajo",
    "wof:placetype":"locality"
},
  "geometry": {"coordinates":[-102.78214,19.68378],"type":"Point"}
}