{
  "type": "Feature",
  "properties": {
    "gn:admin1_code":"26",
    "gn:admin2_code":"40.0",
    "gn:asciiname":"Las Cieneguita",
    "gn:country_code":"MX",
    "gn:dem":907,
    "gn:feature_class":"P",
    "gn:feature_code":"PPL",
    "gn:name":"Las Cieneguita",
    "gn:population":0,
    "gn:timezone":"America/Hermosillo",
    "iso:country":"MX",
    "name:spa_x_preferred":[
        "Las Cieneguita"
    ],
    "wof:name":"Las Cieneguita",
    "wof:placetype":"locality"
},
  "geometry": {"coordinates":[-108.8275,29.61254000000001],"type":"Point"}
}