{
  "type": "Feature",
  "properties": {
    "gn:admin1_code":"14.0",
    "gn:admin2_code":"85.0",
    "gn:asciiname":"La Tacuachera",
    "gn:country_code":"MX",
    "gn:dem":1552,
    "gn:feature_class":"P",
    "gn:feature_code":"PPL",
    "gn:name":"La Tacuachera",
    "gn:population":0,
    "gn:timezone":"America/Mexico_City",
    "iso:country":"MX",
    "name:spa_x_preferred":[
        "La Tacuachera"
    ],
    "wof:name":"La Tacuachera",
    "wof:placetype":"locality"
},
  "geometry": {"coordinates":[-103.19234,19.47002],"type":"Point"}
}