{
  "type": "Feature",
  "properties": {
    "gn:admin1_code":"14",
    "gn:admin2_code":"65",
    "gn:asciiname":"El Platanar",
    "gn:country_code":"MX",
    "gn:dem":351,
    "gn:feature_class":"P",
    "gn:feature_code":"PPL",
    "gn:name":"El Platanar",
    "gn:population":51,
    "gn:timezone":"America/Mexico_City",
    "iso:country":"MX",
    "wof:name":"El Platanar",
    "wof:placetype":"locality",
    "wof:population":51
},
  "geometry": {"coordinates":[-103.49444,19.05611],"type":"Point"}
}