{
  "type": "Feature",
  "properties": {
    "gn:admin1_code":"13",
    "gn:admin2_code":"78.0",
    "gn:asciiname":"Tecopia",
    "gn:country_code":"MX",
    "gn:dem":361,
    "gn:feature_class":"P",
    "gn:feature_code":"PPL",
    "gn:name":"Tecopia",
    "gn:population":0,
    "gn:timezone":"America/Mexico_City",
    "iso:country":"MX",
    "name:spa_x_preferred":[
        "Tecopia"
    ],
    "wof:name":"Tecopia",
    "wof:placetype":"locality"
},
  "geometry": {"coordinates":[-98.2932,20.88851],"type":"Point"}
}