{
  "type": "Feature",
  "properties": {
    "gn:admin1_code":"24",
    "gn:admin2_code":"53.0",
    "gn:asciiname":"Cuayo Cerro",
    "gn:country_code":"MX",
    "gn:dem":451,
    "gn:feature_class":"P",
    "gn:feature_code":"PPL",
    "gn:name":"Cuayo Cerro",
    "gn:population":449,
    "gn:timezone":"America/Mexico_City",
    "iso:country":"MX",
    "wof:name":"Cuayo Cerro",
    "wof:placetype":"locality",
    "wof:population":449
},
  "geometry": {"coordinates":[-98.91777999999999,21.46361],"type":"Point"}
}