{
  "type": "Feature",
  "properties": {
    "gn:admin1_code":"12.0",
    "gn:admin2_code":"21.0",
    "gn:asciiname":"El Aguacate",
    "gn:country_code":"MX",
    "gn:dem":400,
    "gn:feature_class":"P",
    "gn:feature_code":"PPL",
    "gn:name":"El Aguacate",
    "gn:population":0,
    "gn:timezone":"America/Mexico_City",
    "iso:country":"MX",
    "name:spa_x_preferred":[
        "El Aguacate"
    ],
    "wof:name":"El Aguacate",
    "wof:placetype":"locality"
},
  "geometry": {"coordinates":[-100.18744,17.08675],"type":"Point"}
}