{
  "type": "Feature",
  "properties": {
    "gn:admin1_code":"11",
    "gn:admin2_code":"20",
    "gn:asciiname":"La Joya (Cerro Gigante)",
    "gn:country_code":"MX",
    "gn:dem":2501,
    "gn:feature_class":"P",
    "gn:feature_code":"PPL",
    "gn:name":"La Joya (Cerro Gigante)",
    "gn:population":41,
    "gn:timezone":"America/Mexico_City",
    "iso:country":"MX",
    "wof:name":"La Joya (Cerro Gigante)",
    "wof:placetype":"locality",
    "wof:population":41
},
  "geometry": {"coordinates":[-101.56194000000001,21.19639],"type":"Point"}
}