{
  "type": "Feature",
  "properties": {
    "gn:admin1_code":"11.0",
    "gn:admin2_code":"23.0",
    "gn:asciiname":"El Rodero",
    "gn:country_code":"MX",
    "gn:dem":1700,
    "gn:feature_class":"P",
    "gn:feature_code":"PPL",
    "gn:name":"El Rodero",
    "gn:population":0,
    "gn:timezone":"America/Mexico_City",
    "iso:country":"MX",
    "name:spa_x_preferred":[
        "El Rodero"
    ],
    "name:spa_x_variant":[
        "El Rodeo"
    ],
    "wof:name":"El Rodero",
    "wof:placetype":"locality"
},
  "geometry": {"coordinates":[-101.62744000000001,20.48392],"type":"Point"}
}