{
  "type": "Feature",
  "properties": {
    "gn:admin1_code":"13",
    "gn:admin2_code":"2.0",
    "gn:asciiname":"Parada 170",
    "gn:country_code":"MX",
    "gn:dem":2165,
    "gn:feature_class":"P",
    "gn:feature_code":"PPL",
    "gn:name":"Parada 170",
    "gn:population":59,
    "gn:timezone":"America/Mexico_City",
    "iso:country":"MX",
    "wof:name":"Parada 170",
    "wof:placetype":"locality",
    "wof:population":59
},
  "geometry": {"coordinates":[-98.17206,20.14096],"type":"Point"}
}