{
  "type": "Feature",
  "properties": {
    "gn:admin1_code":"4",
    "gn:admin2_code":"5.0",
    "gn:asciiname":"San Isidro Benaox",
    "gn:country_code":"MX",
    "gn:dem":13,
    "gn:feature_class":"P",
    "gn:feature_code":"PPL",
    "gn:name":"San Isidro Benaox",
    "gn:population":5,
    "gn:timezone":"America/Merida",
    "iso:country":"MX",
    "wof:name":"San Isidro Benaox",
    "wof:placetype":"locality",
    "wof:population":5
},
  "geometry": {"coordinates":[-90.15472,20.15778],"type":"Point"}
}