{
  "type": "Feature",
  "properties": {
    "gn:admin1_code":"5",
    "gn:admin2_code":"97.0",
    "gn:asciiname":"El Naranjo",
    "gn:cc2":"MX",
    "gn:country_code":"MX",
    "gn:dem":8,
    "gn:feature_class":"P",
    "gn:feature_code":"PPL",
    "gn:name":"El Naranjo",
    "gn:population":348,
    "gn:timezone":"America/Mexico_City",
    "iso:country":"MX",
    "name:und_x_variant":[
        "Naranjo",
        "El Naranjo"
    ],
    "wof:name":"El Naranjo",
    "wof:placetype":"locality",
    "wof:population":348
},
  "geometry": {"coordinates":[-93.80249999999999,15.99083],"type":"Point"}
}