{
  "type": "Feature",
  "properties": {
    "gn:admin1_code":"23",
    "gn:admin2_code":"3.0",
    "gn:asciiname":"Cayo Cahum",
    "gn:country_code":"MX",
    "gn:dem":0,
    "gn:feature_class":"P",
    "gn:feature_code":"PPL",
    "gn:name":"Cayo Cahum",
    "gn:population":6,
    "gn:timezone":"America/Cancun",
    "iso:country":"MX",
    "wof:name":"Cayo Cahum",
    "wof:placetype":"locality",
    "wof:population":6
},
  "geometry": {"coordinates":[-86.98867,21.56],"type":"Point"}
}