{
  "type": "Feature",
  "properties": {
    "gn:admin1_code":"30.0",
    "gn:admin2_code":"121.0",
    "gn:asciiname":"Santa Magdalena",
    "gn:country_code":"MX",
    "gn:dem":71,
    "gn:feature_class":"P",
    "gn:feature_code":"PPL",
    "gn:name":"Santa Magdalena",
    "gn:population":0,
    "gn:timezone":"America/Mexico_City",
    "iso:country":"MX",
    "name:spa_x_preferred":[
        "Santa Magdalena"
    ],
    "wof:name":"Santa Magdalena",
    "wof:placetype":"locality"
},
  "geometry": {"coordinates":[-97.91243,21.60811],"type":"Point"}
}