{
  "type": "Feature",
  "properties": {
    "gn:admin1_code":"16",
    "gn:admin2_code":"31.0",
    "gn:asciiname":"Cerrito Colorado",
    "gn:country_code":"MX",
    "gn:dem":2478,
    "gn:feature_class":"P",
    "gn:feature_code":"PPL",
    "gn:name":"Cerrito Colorado",
    "gn:population":75,
    "gn:timezone":"America/Mexico_City",
    "iso:country":"MX",
    "wof:name":"Cerrito Colorado",
    "wof:placetype":"locality",
    "wof:population":75
},
  "geometry": {"coordinates":[-100.26027999999999,20.12694],"type":"Point"}
}