{
  "type": "Feature",
  "properties": {
    "gn:admin1_code":"1",
    "gn:admin2_code":"10.0",
    "gn:asciiname":"Tampiquito",
    "gn:country_code":"MX",
    "gn:dem":2025,
    "gn:feature_class":"P",
    "gn:feature_code":"PPL",
    "gn:name":"Tampiquito",
    "gn:population":5,
    "gn:timezone":"America/Mexico_City",
    "iso:country":"MX",
    "wof:name":"Tampiquito",
    "wof:placetype":"locality",
    "wof:population":5
},
  "geometry": {"coordinates":[-102.08194,21.86139],"type":"Point"}
}