{
  "type": "Feature",
  "properties": {
    "gn:admin1_code":"20",
    "gn:admin2_code":"469",
    "gn:asciiname":"Loma de Mango",
    "gn:country_code":"MX",
    "gn:dem":1227,
    "gn:feature_class":"P",
    "gn:feature_code":"PPL",
    "gn:name":"Loma de Mango",
    "gn:population":20,
    "gn:timezone":"America/Mexico_City",
    "iso:country":"MX",
    "wof:name":"Loma de Mango",
    "wof:placetype":"locality",
    "wof:population":20
},
  "geometry": {"coordinates":[-98.04306,17.06889],"type":"Point"}
}