{
  "type": "Feature",
  "properties": {
    "gn:admin1_code":"17",
    "gn:admin2_code":"2.0",
    "gn:asciiname":"Las Minas",
    "gn:country_code":"MX",
    "gn:dem":1450,
    "gn:feature_class":"P",
    "gn:feature_code":"PPL",
    "gn:name":"Las Minas",
    "gn:population":837,
    "gn:timezone":"America/Mexico_City",
    "iso:country":"MX",
    "wof:name":"Las Minas",
    "wof:placetype":"locality",
    "wof:population":837
},
  "geometry": {"coordinates":[-98.93185,18.89178],"type":"Point"}
}