{
  "type": "Feature",
  "properties": {
    "gn:admin1_code":"25",
    "gn:admin2_code":"13.0",
    "gn:asciiname":"Ramon Felix",
    "gn:country_code":"MX",
    "gn:dem":70,
    "gn:feature_class":"P",
    "gn:feature_code":"PPL",
    "gn:name":"Ram\u00f3n F\u00e9lix",
    "gn:population":7,
    "gn:timezone":"America/Mazatlan",
    "iso:country":"MX",
    "name:und_x_variant":[
        "Ram\u00f3n F\u00e9lix"
    ],
    "wof:name":"Ramon Felix",
    "wof:placetype":"locality",
    "wof:population":7
},
  "geometry": {"coordinates":[-107.86861,25.11655],"type":"Point"}
}