{
  "type": "Feature",
  "properties": {
    "gn:admin1_code":"19.0",
    "gn:admin2_code":"33.0",
    "gn:asciiname":"Ampliacion los Hoyos",
    "gn:country_code":"MX",
    "gn:dem":353,
    "gn:feature_class":"P",
    "gn:feature_code":"PPL",
    "gn:name":"Ampliaci\u00f3n los Hoyos",
    "gn:population":0,
    "gn:timezone":"America/Monterrey",
    "iso:country":"MX",
    "name:spa_x_preferred":[
        "Milagro"
    ],
    "name:spa_x_variant":[
        "Ampliaci\u00f3n los Hoyos"
    ],
    "wof:name":"Ampliacion los Hoyos",
    "wof:placetype":"locality"
},
  "geometry": {"coordinates":[-99.53633000000001,24.7242],"type":"Point"}
}