{
  "type": "Feature",
  "properties": {
    "gn:admin1_code":"4.0",
    "gn:admin2_code":"7.0",
    "gn:asciiname":"Rio Palizada",
    "gn:country_code":"MX",
    "gn:dem":4,
    "gn:feature_class":"P",
    "gn:feature_code":"PPL",
    "gn:name":"R\u00edo Palizada",
    "gn:population":0,
    "gn:timezone":"America/Merida",
    "iso:country":"MX",
    "name:spa_x_preferred":[
        "R\u00edo Palizada"
    ],
    "wof:name":"Rio Palizada",
    "wof:placetype":"locality"
},
  "geometry": {"coordinates":[-92.01799,18.26512],"type":"Point"}
}