{
  "type": "Feature",
  "properties": {
    "gn:admin1_code":"6",
    "gn:admin2_code":"63.0",
    "gn:asciiname":"Rosahuachic",
    "gn:cc2":"MX",
    "gn:country_code":"MX",
    "gn:dem":2422,
    "gn:feature_class":"P",
    "gn:feature_code":"PPL",
    "gn:name":"Rosahuachic",
    "gn:population":0,
    "gn:timezone":"America/Chihuahua",
    "iso:country":"MX",
    "name:und_x_variant":[
        "Rosaguachic",
        "Rosahuachic"
    ],
    "wof:name":"Rosahuachic",
    "wof:placetype":"locality"
},
  "geometry": {"coordinates":[-107.96666999999999,28.45],"type":"Point"}
}