{
  "type": "Feature",
  "properties": {
    "gn:admin1_code":"16",
    "gn:admin2_code":"15",
    "gn:asciiname":"El Sauz",
    "gn:country_code":"MX",
    "gn:dem":1406,
    "gn:feature_class":"P",
    "gn:feature_code":"PPL",
    "gn:name":"El Sauz",
    "gn:population":38,
    "gn:timezone":"America/Mexico_City",
    "iso:country":"MX",
    "wof:name":"El Sauz",
    "wof:placetype":"locality",
    "wof:population":38
},
  "geometry": {"coordinates":[-102.94167,18.54111],"type":"Point"}
}