{
  "type": "Feature",
  "properties": {
    "gn:admin1_code":"3",
    "gn:admin2_code":"2.0",
    "gn:asciiname":"La Cachora",
    "gn:country_code":"MX",
    "gn:dem":453,
    "gn:feature_class":"P",
    "gn:feature_code":"PPL",
    "gn:name":"La Cachora",
    "gn:population":4,
    "gn:timezone":"America/Mazatlan",
    "iso:country":"MX",
    "wof:name":"La Cachora",
    "wof:placetype":"locality",
    "wof:population":4
},
  "geometry": {"coordinates":[-112.44183,27.13476],"type":"Point"}
}