{
  "type": "Feature",
  "properties": {
    "gn:admin1_code":"5",
    "gn:admin2_code":"113.0",
    "gn:asciiname":"Revolucion Fiu",
    "gn:country_code":"MX",
    "gn:dem":2128,
    "gn:feature_class":"P",
    "gn:feature_code":"PPL",
    "gn:name":"Revoluci\u00f3n Fiu",
    "gn:population":406,
    "gn:timezone":"America/Mexico_City",
    "iso:country":"MX",
    "name:und_x_variant":[
        "Revoluci\u00f3n Fiu"
    ],
    "wof:name":"Revolucion Fiu",
    "wof:placetype":"locality",
    "wof:population":406
},
  "geometry": {"coordinates":[-92.67639,16.89833],"type":"Point"}
}