{
  "type": "Feature",
  "properties": {
    "gn:admin1_code":"24",
    "gn:admin2_code":"21.0",
    "gn:asciiname":"Colonia Emiliano Zapata (El Chamizal)",
    "gn:country_code":"MX",
    "gn:dem":1797,
    "gn:feature_class":"P",
    "gn:feature_code":"PPL",
    "gn:name":"Colonia Emiliano Zapata (El Chamizal)",
    "gn:population":576,
    "gn:timezone":"America/Mexico_City",
    "iso:country":"MX",
    "wof:name":"Colonia Emiliano Zapata (El Chamizal)",
    "wof:placetype":"locality",
    "wof:population":576
},
  "geometry": {"coordinates":[-101.10722,22.40194],"type":"Point"}
}