{
  "type": "Feature",
  "properties": {
    "gn:admin1_code":"7",
    "gn:admin2_code":"34.0",
    "gn:asciiname":"San Isidro de Marquez (El Caracol)",
    "gn:country_code":"MX",
    "gn:dem":1483,
    "gn:feature_class":"P",
    "gn:feature_code":"PPL",
    "gn:name":"San Isidro de M\u00e1rquez (El Caracol)",
    "gn:population":2,
    "gn:timezone":"America/Monterrey",
    "iso:country":"MX",
    "wof:name":"San Isidro de Marquez (El Caracol)",
    "wof:placetype":"locality",
    "wof:population":2
},
  "geometry": {"coordinates":[-103.59614999999999,27.7594],"type":"Point"}
}