{
  "type": "Feature",
  "properties": {
    "gn:admin1_code":"5",
    "gn:admin2_code":"76.0",
    "gn:asciiname":"Villaflores",
    "gn:country_code":"MX",
    "gn:dem":421,
    "gn:feature_class":"P",
    "gn:feature_code":"PPL",
    "gn:name":"Villaflores",
    "gn:population":270,
    "gn:timezone":"America/Mexico_City",
    "iso:country":"MX",
    "wof:name":"Villaflores",
    "wof:placetype":"locality",
    "wof:population":270
},
  "geometry": {"coordinates":[-92.5925,17.30056],"type":"Point"}
}