{
  "type": "Feature",
  "properties": {
    "gn:admin1_code":"10",
    "gn:admin2_code":"26.0",
    "gn:asciiname":"Temporal",
    "gn:country_code":"MX",
    "gn:dem":2553,
    "gn:feature_class":"P",
    "gn:feature_code":"PPL",
    "gn:name":"Temporal",
    "gn:population":0,
    "gn:timezone":"America/Monterrey",
    "iso:country":"MX",
    "name:ceb_x_preferred":[
        "Temporal"
    ],
    "name:deu_x_preferred":[
        "Temporal"
    ],
    "name:fas_x_preferred":[
        "\u06af\u06cc\u062c\u06af\u0627\u0647\u06cc"
    ],
    "name:fra_x_preferred":[
        "Temporal"
    ],
    "name:glg_x_preferred":[
        "Temporal"
    ],
    "name:ita_x_preferred":[
        "Temporale"
    ],
    "name:pan_x_preferred":[
        "\u0a1f\u0a48\u0a02\u0a2a\u0a30\u0a32"
    ],
    "name:por_x_preferred":[
        "Temporal"
    ],
    "name:spa_x_preferred":[
        "Temporal"
    ],
    "name:swe_x_preferred":[
        "Temporal"
    ],
    "name:urd_x_preferred":[
        "Temporal"
    ],
    "wof:name":"Temporal",
    "wof:placetype":"locality"
},
  "geometry": {"coordinates":[-105.92348,24.48278],"type":"Point"}
}