{
  "type": "Feature",
  "properties": {
    "gn:admin1_code":"6",
    "gn:admin2_code":"40.0",
    "gn:asciiname":"Rancho de Mora",
    "gn:country_code":"MX",
    "gn:dem":1320,
    "gn:feature_class":"P",
    "gn:feature_code":"PPL",
    "gn:name":"Rancho de Mora",
    "gn:population":4,
    "gn:timezone":"America/Chihuahua",
    "iso:country":"MX",
    "wof:name":"Rancho de Mora",
    "wof:placetype":"locality",
    "wof:population":4
},
  "geometry": {"coordinates":[-108.45903,28.98471],"type":"Point"}
}