{
  "type": "Feature",
  "properties": {
    "gn:admin1_code":"12.0",
    "gn:admin2_code":"12.0",
    "gn:asciiname":"Coxcatlan San Pedro",
    "gn:country_code":"MX",
    "gn:dem":723,
    "gn:feature_class":"P",
    "gn:feature_code":"PPL",
    "gn:name":"Coxcatl\u00e1n San Pedro",
    "gn:population":0,
    "gn:timezone":"America/Mexico_City",
    "iso:country":"MX",
    "name:spa_x_preferred":[
        "Coxcatl\u00e1n San Pedro"
    ],
    "wof:name":"Coxcatlan San Pedro",
    "wof:placetype":"locality"
},
  "geometry": {"coordinates":[-99.03698,16.9125],"type":"Point"}
}