{
  "type": "Feature",
  "properties": {
    "gn:admin1_code":"22",
    "gn:admin2_code":"4",
    "gn:asciiname":"Puerto Verde",
    "gn:country_code":"MX",
    "gn:dem":2507,
    "gn:feature_class":"P",
    "gn:feature_code":"PPL",
    "gn:name":"Puerto Verde",
    "gn:population":24,
    "gn:timezone":"America/Mexico_City",
    "iso:country":"MX",
    "wof:name":"Puerto Verde",
    "wof:placetype":"locality",
    "wof:population":24
},
  "geometry": {"coordinates":[-99.56972,20.88028],"type":"Point"}
}