{
  "type": "Feature",
  "properties": {
    "gn:admin1_code":"12.0",
    "gn:asciiname":"Tecolutla",
    "gn:country_code":"MX",
    "gn:dem":1162,
    "gn:feature_class":"P",
    "gn:feature_code":"PPL",
    "gn:name":"Tecolutla",
    "gn:population":0,
    "gn:timezone":"America/Mexico_City",
    "iso:country":"MX",
    "name:spa_x_preferred":[
        "Tecolutla"
    ],
    "wof:name":"Tecolutla",
    "wof:placetype":"locality"
},
  "geometry": {"coordinates":[-98.43797000000001,18.00724],"type":"Point"}
}