{
  "type": "Feature",
  "properties": {
    "gn:admin1_code":"10",
    "gn:admin2_code":"37",
    "gn:asciiname":"Arroyo de la Galancita",
    "gn:country_code":"MX",
    "gn:dem":952,
    "gn:feature_class":"P",
    "gn:feature_code":"PPL",
    "gn:name":"Arroyo de la Galancita",
    "gn:population":9,
    "gn:timezone":"America/Monterrey",
    "iso:country":"MX",
    "wof:name":"Arroyo de la Galancita",
    "wof:placetype":"locality",
    "wof:population":9
},
  "geometry": {"coordinates":[-106.7662,25.16775],"type":"Point"}
}