{
  "type": "Feature",
  "properties": {
    "gn:admin1_code":"9",
    "gn:admin2_code":"9",
    "gn:asciiname":"Tetzumpa",
    "gn:country_code":"MX",
    "gn:dem":2893,
    "gn:feature_class":"P",
    "gn:feature_code":"PPL",
    "gn:name":"Tetzumpa",
    "gn:population":14,
    "gn:timezone":"America/Mexico_City",
    "iso:country":"MX",
    "wof:name":"Tetzumpa",
    "wof:placetype":"locality",
    "wof:population":14
},
  "geometry": {"coordinates":[-99.07096,19.16797],"type":"Point"}
}