{
  "type": "Feature",
  "properties": {
    "gn:admin1_code":"10",
    "gn:admin2_code":"35.0",
    "gn:asciiname":"El Bajio del Terrero",
    "gn:country_code":"MX",
    "gn:dem":1840,
    "gn:feature_class":"P",
    "gn:feature_code":"PPL",
    "gn:name":"El Baj\u00edo del Terrero",
    "gn:population":6,
    "gn:timezone":"America/Monterrey",
    "iso:country":"MX",
    "name:und_x_variant":[
        "El Baj\u00edo del Terrero"
    ],
    "wof:name":"El Bajio del Terrero",
    "wof:placetype":"locality",
    "wof:population":6
},
  "geometry": {"coordinates":[-105.81925,25.35248],"type":"Point"}
}