{
  "type": "Feature",
  "properties": {
    "gn:admin1_code":"6.0",
    "gn:admin2_code":"27.0",
    "gn:asciiname":"Rorogachi",
    "gn:country_code":"MX",
    "gn:dem":2270,
    "gn:feature_class":"P",
    "gn:feature_code":"PPL",
    "gn:name":"Rorogachi",
    "gn:population":0,
    "gn:timezone":"America/Chihuahua",
    "iso:country":"MX",
    "name:spa_x_preferred":[
        "Rorogachi"
    ],
    "wof:name":"Rorogachi",
    "wof:placetype":"locality"
},
  "geometry": {"coordinates":[-107.10167,27.19025],"type":"Point"}
}