{
  "type": "Feature",
  "properties": {
    "gn:admin1_code":"28",
    "gn:admin2_code":"3",
    "gn:asciiname":"Llano Grande (Coyol)",
    "gn:country_code":"MX",
    "gn:dem":5,
    "gn:feature_class":"P",
    "gn:feature_code":"PPL",
    "gn:name":"Llano Grande (Coyol)",
    "gn:population":41,
    "gn:timezone":"America/Monterrey",
    "iso:country":"MX",
    "wof:name":"Llano Grande (Coyol)",
    "wof:placetype":"locality",
    "wof:population":41
},
  "geometry": {"coordinates":[-98.11306,22.39556],"type":"Point"}
}