{
  "type": "Feature",
  "properties": {
    "gn:admin1_code":"2",
    "gn:admin2_code":"2",
    "gn:asciiname":"Valle Verde (Colonia Colorado Numero Uno) [Granjas]",
    "gn:country_code":"MX",
    "gn:dem":4,
    "gn:feature_class":"P",
    "gn:feature_code":"PPL",
    "gn:name":"Valle Verde (Colonia Colorado N\u00famero Uno) [Granjas]",
    "gn:population":24,
    "gn:timezone":"America/Tijuana",
    "iso:country":"MX",
    "name:und_x_variant":[
        "Valle Verde (Colonia Colorado N\u00famero Uno) [Granjas]"
    ],
    "wof:name":"Valle Verde (Colonia Colorado Numero Uno) [Granjas]",
    "wof:placetype":"locality",
    "wof:population":24
},
  "geometry": {"coordinates":[-115.44110999999999,32.565],"type":"Point"}
}