{
  "type": "Feature",
  "properties": {
    "gn:admin1_code":"11",
    "gn:admin2_code":"37",
    "gn:asciiname":"Loma del Plan de los Sauces",
    "gn:country_code":"MX",
    "gn:dem":1803,
    "gn:feature_class":"P",
    "gn:feature_code":"PPL",
    "gn:name":"Loma del Plan de los Sauces",
    "gn:population":44,
    "gn:timezone":"America/Mexico_City",
    "iso:country":"MX",
    "wof:name":"Loma del Plan de los Sauces",
    "wof:placetype":"locality",
    "wof:population":44
},
  "geometry": {"coordinates":[-101.51528,20.98806],"type":"Point"}
}