{
  "type": "Feature",
  "properties": {
    "gn:admin1_code":"32",
    "gn:admin2_code":"55.0",
    "gn:asciiname":"Juana Antonia",
    "gn:country_code":"MX",
    "gn:dem":1830,
    "gn:feature_class":"P",
    "gn:feature_code":"PPL",
    "gn:name":"Juana Antonia",
    "gn:population":7,
    "gn:timezone":"America/Mexico_City",
    "iso:country":"MX",
    "wof:name":"Juana Antonia",
    "wof:placetype":"locality",
    "wof:population":7
},
  "geometry": {"coordinates":[-102.81917,22.01528],"type":"Point"}
}