{
  "type": "Feature",
  "properties": {
    "gn:admin1_code":"5",
    "gn:admin2_code":"19",
    "gn:asciiname":"Buenavista el Ocote",
    "gn:country_code":"MX",
    "gn:dem":2287,
    "gn:feature_class":"P",
    "gn:feature_code":"PPL",
    "gn:name":"Buenavista el Ocote",
    "gn:population":19,
    "gn:timezone":"America/Mexico_City",
    "iso:country":"MX",
    "wof:name":"Buenavista el Ocote",
    "wof:placetype":"locality",
    "wof:population":19
},
  "geometry": {"coordinates":[-92.26611,16.35861],"type":"Point"}
}