{
  "type": "Feature",
  "properties": {
    "gn:admin1_code":"5",
    "gn:admin2_code":"31.0",
    "gn:asciiname":"Tzasibiltic",
    "gn:country_code":"MX",
    "gn:dem":1113,
    "gn:feature_class":"P",
    "gn:feature_code":"PPL",
    "gn:name":"Tzasibiltic",
    "gn:population":545,
    "gn:timezone":"America/Mexico_City",
    "iso:country":"MX",
    "wof:name":"Tzasibiltic",
    "wof:placetype":"locality",
    "wof:population":545
},
  "geometry": {"coordinates":[-92.28888999999999,17.1475],"type":"Point"}
}