{
  "type": "Feature",
  "properties": {
    "gn:admin1_code":"6.0",
    "gn:asciiname":"El Taconazo",
    "gn:country_code":"MX",
    "gn:dem":1216,
    "gn:feature_class":"P",
    "gn:feature_code":"PPL",
    "gn:name":"El Taconazo",
    "gn:population":0,
    "gn:timezone":"America/Chihuahua",
    "iso:country":"MX",
    "name:spa_x_preferred":[
        "El Taconazo"
    ],
    "wof:name":"El Taconazo",
    "wof:placetype":"locality"
},
  "geometry": {"coordinates":[-105.49982,28.06861],"type":"Point"}
}