{
  "type": "Feature",
  "properties": {
    "gn:admin1_code":"14.0",
    "gn:admin2_code":"35.0",
    "gn:asciiname":"El Riego",
    "gn:country_code":"MX",
    "gn:dem":1812,
    "gn:feature_class":"P",
    "gn:feature_code":"PPL",
    "gn:name":"El Riego",
    "gn:population":0,
    "gn:timezone":"America/Mexico_City",
    "iso:country":"MX",
    "name:spa_x_preferred":[
        "El Riego"
    ],
    "wof:name":"El Riego",
    "wof:placetype":"locality"
},
  "geometry": {"coordinates":[-102.32518,21.48589],"type":"Point"}
}