{
  "type": "Feature",
  "properties": {
    "gn:admin1_code":"10.0",
    "gn:admin2_code":"39.0",
    "gn:asciiname":"El Tanque",
    "gn:country_code":"MX",
    "gn:dem":2007,
    "gn:feature_class":"P",
    "gn:feature_code":"PPL",
    "gn:name":"El Tanque",
    "gn:population":0,
    "gn:timezone":"America/Monterrey",
    "iso:country":"MX",
    "name:spa_x_preferred":[
        "El Tanque"
    ],
    "wof:name":"El Tanque",
    "wof:placetype":"locality"
},
  "geometry": {"coordinates":[-105.07501000000001,24.8568],"type":"Point"}
}