{
  "type": "Feature",
  "properties": {
    "gn:admin1_code":"13",
    "gn:admin2_code":"37.0",
    "gn:asciiname":"La Paila Anahuac",
    "gn:country_code":"MX",
    "gn:dem":1292,
    "gn:feature_class":"P",
    "gn:feature_code":"PPL",
    "gn:name":"La Paila An\u00e1huac",
    "gn:population":0,
    "gn:timezone":"America/Mexico_City",
    "iso:country":"MX",
    "name:und_x_variant":[
        "La Paila An\u00e1huac",
        "La Paela",
        "La Paila"
    ],
    "wof:name":"La Paila Anahuac",
    "wof:placetype":"locality"
},
  "geometry": {"coordinates":[-98.71975999999999,20.52991],"type":"Point"}
}