{
  "type": "Feature",
  "properties": {
    "gn:admin1_code":"16",
    "gn:admin2_code":"49",
    "gn:asciiname":"Los Limoncitos",
    "gn:country_code":"MX",
    "gn:dem":1392,
    "gn:feature_class":"P",
    "gn:feature_code":"PPL",
    "gn:name":"Los Limoncitos",
    "gn:population":14,
    "gn:timezone":"America/Mexico_City",
    "iso:country":"MX",
    "wof:name":"Los Limoncitos",
    "wof:placetype":"locality",
    "wof:population":14
},
  "geometry": {"coordinates":[-101.17639,19.38861],"type":"Point"}
}