{
  "type": "Feature",
  "properties": {
    "gn:admin1_code":"14",
    "gn:admin2_code":"93.0",
    "gn:asciiname":"Mazatitlan",
    "gn:country_code":"MX",
    "gn:dem":1986,
    "gn:feature_class":"P",
    "gn:feature_code":"PPL",
    "gn:name":"Mazatitl\u00e1n",
    "gn:population":173,
    "gn:timezone":"America/Mexico_City",
    "iso:country":"MX",
    "name:und_x_variant":[
        "Mazatitl\u00e1n"
    ],
    "wof:name":"Mazatitlan",
    "wof:placetype":"locality",
    "wof:population":173
},
  "geometry": {"coordinates":[-102.75611000000001,20.94],"type":"Point"}
}