{
  "type": "Feature",
  "properties": {
    "gn:admin1_code":"26",
    "gn:admin2_code":"26.0",
    "gn:asciiname":"Macochin",
    "gn:country_code":"MX",
    "gn:dem":27,
    "gn:feature_class":"P",
    "gn:feature_code":"PPL",
    "gn:name":"Macoch\u00edn",
    "gn:population":487,
    "gn:timezone":"America/Hermosillo",
    "iso:country":"MX",
    "name:und_x_variant":[
        "Macoch\u00edn"
    ],
    "wof:name":"Macochin",
    "wof:placetype":"locality",
    "wof:population":487
},
  "geometry": {"coordinates":[-109.55628,27.03728],"type":"Point"}
}