{
  "type": "Feature",
  "properties": {
    "gn:admin1_code":"27.0",
    "gn:asciiname":"Huacta y Tequila Segunda Seccion",
    "gn:country_code":"MX",
    "gn:dem":38,
    "gn:feature_class":"P",
    "gn:feature_code":"PPL",
    "gn:name":"Huacta y Tequila Segunda Secci\u00f3n",
    "gn:population":0,
    "gn:timezone":"America/Mexico_City",
    "iso:country":"MX",
    "name:spa_x_preferred":[
        "Huacta y Tequila Segunda Secci\u00f3n"
    ],
    "name:spa_x_variant":[
        "El Rosario"
    ],
    "wof:name":"Huacta y Tequila Segunda Seccion",
    "wof:placetype":"locality"
},
  "geometry": {"coordinates":[-92.72490000000001,17.90503],"type":"Point"}
}