{
  "type": "Feature",
  "properties": {
    "gn:admin1_code":"11.0",
    "gn:admin2_code":"39.0",
    "gn:asciiname":"El Beato",
    "gn:country_code":"MX",
    "gn:dem":2120,
    "gn:feature_class":"P",
    "gn:feature_code":"PPL",
    "gn:name":"El Beato",
    "gn:population":28,
    "gn:timezone":"America/Mexico_City",
    "iso:country":"MX",
    "wof:name":"El Beato",
    "wof:placetype":"locality",
    "wof:population":28
},
  "geometry": {"coordinates":[-100.72167,20.39111],"type":"Point"}
}