{
  "type": "Feature",
  "properties": {
    "gn:admin1_code":"14",
    "gn:admin2_code":"53.0",
    "gn:asciiname":"El Mesoncito",
    "gn:country_code":"MX",
    "gn:dem":1919,
    "gn:feature_class":"P",
    "gn:feature_code":"PPL",
    "gn:name":"El Mesoncito",
    "gn:population":277,
    "gn:timezone":"America/Mexico_City",
    "iso:country":"MX",
    "wof:name":"El Mesoncito",
    "wof:placetype":"locality",
    "wof:population":277
},
  "geometry": {"coordinates":[-101.85250000000001,21.41583],"type":"Point"}
}