{
  "type": "Feature",
  "properties": {
    "gn:admin1_code":"18",
    "gn:admin2_code":"9",
    "gn:asciiname":"La Nanchilera",
    "gn:country_code":"MX",
    "gn:dem":926,
    "gn:feature_class":"P",
    "gn:feature_code":"PPL",
    "gn:name":"La Nanchilera",
    "gn:population":13,
    "gn:timezone":"America/Mazatlan",
    "iso:country":"MX",
    "wof:name":"La Nanchilera",
    "wof:placetype":"locality",
    "wof:population":13
},
  "geometry": {"coordinates":[-104.41417,22.23611],"type":"Point"}
}