{
  "type": "Feature",
  "properties": {
    "iso:country":"MX",
    "name:ind_x_preferred":[
        "Stasiun Pino Su\u00e1rez"
    ],
    "name:nor_x_preferred":[
        "Pino Su\u00e1rez metrostasjon"
    ],
    "name:por_x_preferred":[
        "Esta\u00e7\u00e3o Pino Su\u00e1rez"
    ],
    "name:spa_x_preferred":[
        "Pino Suarez",
        "Pino Su\u00e1rez"
    ],
    "name:spa_x_variant":[
        "Jos\u00e9 Mar\u00eda Pino Su\u00e1rez"
    ],
    "qs:gn_adm0_cc":"MX",
    "qs:gn_local":3514783,
    "qs:gn_nam_loc":"Veracruz Llave, Veracruz, Veracruz, MX",
    "qs:gn_namadm1":"30",
    "qs:local_max":2107,
    "qs:local_sum":5032,
    "qs:localhoods":12,
    "qs:name":"Pino Suarez",
    "qs:name_adm0":"M\u00e9xico",
    "qs:name_adm1":"Veracruz-Llave",
    "qs:name_adm2":"Veracruz",
    "qs:name_local":"Veracruz",
    "qs:photo_max":2,
    "qs:photo_sum":10,
    "qs:placetype":"Suburb",
    "qs:quad_count":6,
    "qs:woe_adm0":23424900,
    "qs:woe_adm1":2346293,
    "qs:woe_adm2":12601913,
    "qs:woe_lau":0,
    "qs:woe_local":150695,
    "qs:woe_ver":"7.10.0",
    "wof:lang":[
        "spa"
    ],
    "wof:name":"Pino Suarez",
    "wof:placetype":"neighbourhood"
},
  "geometry": {"coordinates":[-96.142838,19.18568],"type":"Point"}
}