{
  "type": "Feature",
  "properties": {
    "gn:admin1_code":"6",
    "gn:admin2_code":"29.0",
    "gn:asciiname":"Mesa del Caballo",
    "gn:country_code":"MX",
    "gn:dem":2496,
    "gn:feature_class":"P",
    "gn:feature_code":"PPL",
    "gn:name":"Mesa del Caballo",
    "gn:population":6,
    "gn:timezone":"America/Chihuahua",
    "iso:country":"MX",
    "wof:name":"Mesa del Caballo",
    "wof:placetype":"locality",
    "wof:population":6
},
  "geometry": {"coordinates":[-106.66567999999999,26.06218],"type":"Point"}
}