{
  "type": "Feature",
  "properties": {
    "gn:admin1_code":"30",
    "gn:admin2_code":"175.0",
    "gn:asciiname":"Sector Cinco",
    "gn:country_code":"MX",
    "gn:dem":63,
    "gn:feature_class":"P",
    "gn:feature_code":"PPL",
    "gn:name":"Sector Cinco",
    "gn:population":59,
    "gn:timezone":"America/Mexico_City",
    "iso:country":"MX",
    "wof:name":"Sector Cinco",
    "wof:placetype":"locality",
    "wof:population":59
},
  "geometry": {"coordinates":[-97.4975,20.55278],"type":"Point"}
}