{
  "type": "Feature",
  "properties": {
    "gn:admin1_code":"19.0",
    "gn:asciiname":"El Puerto Chico",
    "gn:country_code":"MX",
    "gn:dem":688,
    "gn:feature_class":"P",
    "gn:feature_code":"PPL",
    "gn:name":"El Puerto Chico",
    "gn:population":0,
    "gn:timezone":"America/Monterrey",
    "iso:country":"MX",
    "name:spa_x_preferred":[
        "El Puerto Chico"
    ],
    "wof:name":"El Puerto Chico",
    "wof:placetype":"locality"
},
  "geometry": {"coordinates":[-99.66929,24.49205],"type":"Point"}
}