{
  "type": "Feature",
  "properties": {
    "gn:admin1_code":"6.0",
    "gn:admin2_code":"38.0",
    "gn:asciiname":"Las Liebres",
    "gn:country_code":"MX",
    "gn:dem":1410,
    "gn:feature_class":"P",
    "gn:feature_code":"PPL",
    "gn:name":"Las Liebres",
    "gn:population":0,
    "gn:timezone":"America/Chihuahua",
    "iso:country":"MX",
    "name:spa_x_preferred":[
        "Las Liebres"
    ],
    "name:und_x_variant":[
        "Liebres",
        "Baj\u00edo de las Liebres"
    ],
    "wof:name":"Las Liebres",
    "wof:placetype":"locality"
},
  "geometry": {"coordinates":[-104.73957,28.50185],"type":"Point"}
}