{
  "type": "Feature",
  "properties": {
    "gn:admin1_code":"16",
    "gn:admin2_code":"101",
    "gn:asciiname":"La Fragua (La Fraguita)",
    "gn:country_code":"MX",
    "gn:dem":1907,
    "gn:feature_class":"P",
    "gn:feature_code":"PPL",
    "gn:name":"La Fragua (La Fraguita)",
    "gn:population":20,
    "gn:timezone":"America/Mexico_City",
    "iso:country":"MX",
    "wof:name":"La Fragua (La Fraguita)",
    "wof:placetype":"locality",
    "wof:population":20
},
  "geometry": {"coordinates":[-101.05444,19.45806],"type":"Point"}
}