{
  "type": "Feature",
  "properties": {
    "gn:admin1_code":"11",
    "gn:admin2_code":"30.0",
    "gn:asciiname":"Arroyo del Pino",
    "gn:country_code":"MX",
    "gn:dem":2087,
    "gn:feature_class":"P",
    "gn:feature_code":"PPL",
    "gn:name":"Arroyo del Pino",
    "gn:population":5,
    "gn:timezone":"America/Mexico_City",
    "iso:country":"MX",
    "wof:name":"Arroyo del Pino",
    "wof:placetype":"locality",
    "wof:population":5
},
  "geometry": {"coordinates":[-101.13861,21.2975],"type":"Point"}
}