{
  "type": "Feature",
  "properties": {
    "gn:admin1_code":"11",
    "gn:admin2_code":"17",
    "gn:asciiname":"San Ignacio (El Cuatro)",
    "gn:country_code":"MX",
    "gn:dem":1707,
    "gn:feature_class":"P",
    "gn:feature_code":"PPL",
    "gn:name":"San Ignacio (El Cuatro)",
    "gn:population":20,
    "gn:timezone":"America/Mexico_City",
    "iso:country":"MX",
    "wof:name":"San Ignacio (El Cuatro)",
    "wof:placetype":"locality",
    "wof:population":20
},
  "geometry": {"coordinates":[-101.495,20.56333],"type":"Point"}
}