{
  "type": "Feature",
  "properties": {
    "gn:admin1_code":"28",
    "gn:admin2_code":"13",
    "gn:asciiname":"La Guayalca",
    "gn:country_code":"MX",
    "gn:dem":213,
    "gn:feature_class":"P",
    "gn:feature_code":"PPL",
    "gn:name":"La Guayalca",
    "gn:population":10,
    "gn:timezone":"America/Monterrey",
    "iso:country":"MX",
    "wof:name":"La Guayalca",
    "wof:placetype":"locality",
    "wof:population":10
},
  "geometry": {"coordinates":[-99.03306000000001,23.78333],"type":"Point"}
}