{
  "type": "Feature",
  "properties": {
    "gn:admin1_code":"10",
    "gn:admin2_code":"34.0",
    "gn:asciiname":"El Perote",
    "gn:country_code":"MX",
    "gn:dem":1021,
    "gn:feature_class":"P",
    "gn:feature_code":"PPL",
    "gn:name":"El Perote",
    "gn:population":7,
    "gn:timezone":"America/Monterrey",
    "iso:country":"MX",
    "wof:name":"El Perote",
    "wof:placetype":"locality",
    "wof:population":7
},
  "geometry": {"coordinates":[-107.07899999999999,25.51274],"type":"Point"}
}