{
  "type": "Feature",
  "properties": {
    "gn:admin1_code":"32",
    "gn:admin2_code":"34.0",
    "gn:asciiname":"El Tescalame",
    "gn:country_code":"MX",
    "gn:dem":1949,
    "gn:feature_class":"P",
    "gn:feature_code":"PPL",
    "gn:name":"El Tescalame",
    "gn:population":0,
    "gn:timezone":"America/Mexico_City",
    "iso:country":"MX",
    "wof:name":"El Tescalame",
    "wof:placetype":"locality"
},
  "geometry": {"coordinates":[-102.82528000000001,21.40306],"type":"Point"}
}