{
  "type": "Feature",
  "properties": {
    "gn:admin1_code":"25",
    "gn:admin2_code":"17.0",
    "gn:asciiname":"Palma Vieja",
    "gn:country_code":"MX",
    "gn:dem":157,
    "gn:feature_class":"P",
    "gn:feature_code":"PPL",
    "gn:name":"Palma Vieja",
    "gn:population":0,
    "gn:timezone":"America/Mazatlan",
    "iso:country":"MX",
    "wof:name":"Palma Vieja",
    "wof:placetype":"locality"
},
  "geometry": {"coordinates":[-108.08333,25.81667],"type":"Point"}
}