{
  "type": "Feature",
  "properties": {
    "gn:admin1_code":"27",
    "gn:admin2_code":"5.0",
    "gn:asciiname":"Zapotal",
    "gn:country_code":"MX",
    "gn:dem":12,
    "gn:feature_class":"P",
    "gn:feature_code":"PPL",
    "gn:name":"Zapotal",
    "gn:population":0,
    "gn:timezone":"America/Mexico_City",
    "iso:country":"MX",
    "name:spa_x_preferred":[
        "Zaporal Segunda Secci\u00f3n"
    ],
    "name:spa_x_variant":[
        "Zapotal",
        "Segunda Secci\u00f3n"
    ],
    "wof:name":"Zapotal",
    "wof:placetype":"locality"
},
  "geometry": {"coordinates":[-93.26103999999999,18.3133],"type":"Point"}
}