{
  "type": "Feature",
  "properties": {
    "gn:admin1_code":"26",
    "gn:admin2_code":"29.0",
    "gn:asciiname":"Sahuaral",
    "gn:country_code":"MX",
    "gn:dem":20,
    "gn:feature_class":"P",
    "gn:feature_code":"PPL",
    "gn:name":"Sahuaral",
    "gn:population":0,
    "gn:timezone":"America/Hermosillo",
    "iso:country":"MX",
    "name:spa_x_preferred":[
        "Sahuaral"
    ],
    "wof:name":"Sahuaral",
    "wof:placetype":"locality"
},
  "geometry": {"coordinates":[-110.17515,27.57465],"type":"Point"}
}