{
  "type": "Feature",
  "properties": {
    "gn:admin1_code":"5",
    "gn:admin2_code":"87.0",
    "gn:asciiname":"Emiliano Zapata",
    "gn:country_code":"MX",
    "gn:dem":14,
    "gn:feature_class":"P",
    "gn:feature_code":"PPL",
    "gn:name":"Emiliano Zapata",
    "gn:population":205,
    "gn:timezone":"America/Mexico_City",
    "iso:country":"MX",
    "wof:name":"Emiliano Zapata",
    "wof:placetype":"locality",
    "wof:population":205
},
  "geometry": {"coordinates":[-92.25417,14.625],"type":"Point"}
}