{
  "type": "Feature",
  "properties": {
    "gn:admin1_code":"13",
    "gn:admin2_code":"73.0",
    "gn:asciiname":"Copaltitla",
    "gn:country_code":"MX",
    "gn:dem":431,
    "gn:feature_class":"P",
    "gn:feature_code":"PPL",
    "gn:name":"Copaltitla",
    "gn:population":67,
    "gn:timezone":"America/Mexico_City",
    "iso:country":"MX",
    "wof:name":"Copaltitla",
    "wof:placetype":"locality",
    "wof:population":67
},
  "geometry": {"coordinates":[-98.55374999999999,21.04279],"type":"Point"}
}