{
  "type": "Feature",
  "properties": {
    "gn:admin1_code":"16",
    "gn:admin2_code":"8",
    "gn:asciiname":"La Coyulera",
    "gn:country_code":"MX",
    "gn:dem":347,
    "gn:feature_class":"P",
    "gn:feature_code":"PPL",
    "gn:name":"La Coyulera",
    "gn:population":30,
    "gn:timezone":"America/Mexico_City",
    "iso:country":"MX",
    "wof:name":"La Coyulera",
    "wof:placetype":"locality",
    "wof:population":30
},
  "geometry": {"coordinates":[-103.34639,18.37972],"type":"Point"}
}