{
  "type": "Feature",
  "properties": {
    "gn:admin1_code":"13",
    "gn:admin2_code":"34.0",
    "gn:asciiname":"Contepec",
    "gn:country_code":"MX",
    "gn:dem":1524,
    "gn:feature_class":"P",
    "gn:feature_code":"PPL",
    "gn:name":"Contepec",
    "gn:population":174,
    "gn:timezone":"America/Mexico_City",
    "iso:country":"MX",
    "wof:name":"Contepec",
    "wof:placetype":"locality",
    "wof:population":174
},
  "geometry": {"coordinates":[-98.6825,20.8775],"type":"Point"}
}