{
  "type": "Feature",
  "properties": {
    "gn:admin1_code":"14",
    "gn:admin2_code":"118",
    "gn:asciiname":"Rancho los Ruvalcaba",
    "gn:country_code":"MX",
    "gn:dem":1778,
    "gn:feature_class":"P",
    "gn:feature_code":"PPL",
    "gn:name":"Rancho los Ruvalcaba",
    "gn:population":30,
    "gn:timezone":"America/Mexico_City",
    "iso:country":"MX",
    "wof:name":"Rancho los Ruvalcaba",
    "wof:placetype":"locality",
    "wof:population":30
},
  "geometry": {"coordinates":[-102.88361,21.23194],"type":"Point"}
}