{
  "type": "Feature",
  "properties": {
    "gn:admin1_code":"6.0",
    "gn:admin2_code":"2.0",
    "gn:asciiname":"Rancho El Refugio",
    "gn:country_code":"MX",
    "gn:dem":1314,
    "gn:feature_class":"P",
    "gn:feature_code":"PPL",
    "gn:name":"Rancho El Refugio",
    "gn:population":0,
    "gn:timezone":"America/Chihuahua",
    "iso:country":"MX",
    "name:und_x_variant":[
        "El Refugio"
    ],
    "wof:name":"Rancho El Refugio",
    "wof:placetype":"locality"
},
  "geometry": {"coordinates":[-105.8008,29.63466],"type":"Point"}
}