{
  "type": "Feature",
  "properties": {
    "gn:admin1_code":"21",
    "gn:admin2_code":"64.0",
    "gn:asciiname":"Plan de Arroyo",
    "gn:country_code":"MX",
    "gn:dem":118,
    "gn:feature_class":"P",
    "gn:feature_code":"PPL",
    "gn:name":"Plan de Arroyo",
    "gn:population":425,
    "gn:timezone":"America/Mexico_City",
    "iso:country":"MX",
    "name:spa_x_preferred":[
        "Plan de Arroyo"
    ],
    "wof:name":"Plan de Arroyo",
    "wof:placetype":"locality",
    "wof:population":425
},
  "geometry": {"coordinates":[-97.78333000000001,20.79722000000001],"type":"Point"}
}