{
  "type": "Feature",
  "properties": {
    "gn:admin1_code":"6",
    "gn:admin2_code":"8",
    "gn:asciiname":"Casas Coloradas",
    "gn:country_code":"MX",
    "gn:dem":595,
    "gn:feature_class":"P",
    "gn:feature_code":"PPL",
    "gn:name":"Casas Coloradas",
    "gn:population":19,
    "gn:timezone":"America/Chihuahua",
    "iso:country":"MX",
    "wof:name":"Casas Coloradas",
    "wof:placetype":"locality",
    "wof:population":19
},
  "geometry": {"coordinates":[-107.72157,27.06021],"type":"Point"}
}