{
  "type": "Feature",
  "properties": {
    "gn:admin1_code":"5.0",
    "gn:admin2_code":"106.0",
    "gn:asciiname":"San Martin",
    "gn:country_code":"MX",
    "gn:dem":591,
    "gn:feature_class":"P",
    "gn:feature_code":"PPL",
    "gn:name":"San Mart\u00edn",
    "gn:population":0,
    "gn:timezone":"America/Mexico_City",
    "iso:country":"MX",
    "name:spa_x_preferred":[
        "San Mart\u00edn"
    ],
    "wof:name":"San Martin",
    "wof:placetype":"locality"
},
  "geometry": {"coordinates":[-92.48894,16.24304],"type":"Point"}
}