{
  "type": "Feature",
  "properties": {
    "gn:admin1_code":"6.0",
    "gn:admin2_code":"28.0",
    "gn:asciiname":"Ejido Emilio Carranza",
    "gn:country_code":"MX",
    "gn:dem":904,
    "gn:feature_class":"P",
    "gn:feature_code":"PPL",
    "gn:name":"Ejido Emilio Carranza",
    "gn:population":0,
    "gn:timezone":"America/Chihuahua",
    "iso:country":"MX",
    "wof:name":"Ejido Emilio Carranza",
    "wof:placetype":"locality"
},
  "geometry": {"coordinates":[-104.91667,30.58333],"type":"Point"}
}