{
  "type": "Feature",
  "properties": {
    "gn:admin1_code":"30",
    "gn:admin2_code":"123.0",
    "gn:asciiname":"Palmas Reales",
    "gn:country_code":"MX",
    "gn:dem":15,
    "gn:feature_class":"P",
    "gn:feature_code":"PPL",
    "gn:name":"Palmas Reales",
    "gn:population":0,
    "gn:timezone":"America/Mexico_City",
    "iso:country":"MX",
    "name:spa_x_preferred":[
        "Palmas Reales"
    ],
    "wof:name":"Palmas Reales",
    "wof:placetype":"locality"
},
  "geometry": {"coordinates":[-98.27639000000001,22.07055],"type":"Point"}
}