{
  "type": "Feature",
  "properties": {
    "gn:admin1_code":"32",
    "gn:admin2_code":"14.0",
    "gn:asciiname":"La Pajarera",
    "gn:country_code":"MX",
    "gn:dem":1919,
    "gn:feature_class":"P",
    "gn:feature_code":"PPL",
    "gn:name":"La Pajarera",
    "gn:population":0,
    "gn:timezone":"America/Mexico_City",
    "iso:country":"MX",
    "name:spa_x_preferred":[
        "La Pajarera"
    ],
    "wof:name":"La Pajarera",
    "wof:placetype":"locality"
},
  "geometry": {"coordinates":[-103.02597,24.15812],"type":"Point"}
}