{
  "type": "Feature",
  "properties": {
    "gn:admin1_code":"11.0",
    "gn:admin2_code":"44.0",
    "gn:asciiname":"Huisachal",
    "gn:country_code":"MX",
    "gn:dem":1745,
    "gn:feature_class":"P",
    "gn:feature_code":"PPL",
    "gn:name":"Huisachal",
    "gn:population":0,
    "gn:timezone":"America/Mexico_City",
    "iso:country":"MX",
    "name:spa_x_preferred":[
        "Huisachal"
    ],
    "wof:name":"Huisachal",
    "wof:placetype":"locality"
},
  "geometry": {"coordinates":[-100.90934,20.53481],"type":"Point"}
}