{
  "type": "Feature",
  "properties": {
    "gn:admin1_code":"18.0",
    "gn:admin2_code":"19.0",
    "gn:asciiname":"Tepizuaque",
    "gn:country_code":"MX",
    "gn:dem":1376,
    "gn:feature_class":"P",
    "gn:feature_code":"PPL",
    "gn:name":"Tepizuaque",
    "gn:population":0,
    "gn:timezone":"America/Mazatlan",
    "iso:country":"MX",
    "name:spa_x_preferred":[
        "Tepizuaque"
    ],
    "wof:name":"Tepizuaque",
    "wof:placetype":"locality"
},
  "geometry": {"coordinates":[-104.01141,21.36654],"type":"Point"}
}