{
  "type": "Feature",
  "properties": {
    "gn:admin1_code":"19",
    "gn:admin2_code":"31.0",
    "gn:asciiname":"Montebello",
    "gn:country_code":"MX",
    "gn:dem":481,
    "gn:feature_class":"P",
    "gn:feature_code":"PPL",
    "gn:name":"Montebello",
    "gn:population":396,
    "gn:timezone":"America/Monterrey",
    "iso:country":"MX",
    "wof:name":"Montebello",
    "wof:placetype":"locality",
    "wof:population":396
},
  "geometry": {"coordinates":[-100.16,25.61694],"type":"Point"}
}