{
  "type": "Feature",
  "properties": {
    "gn:admin1_code":"14",
    "gn:admin2_code":"51.0",
    "gn:asciiname":"Casa de Teja",
    "gn:country_code":"MX",
    "gn:dem":1525,
    "gn:feature_class":"P",
    "gn:feature_code":"PPL",
    "gn:name":"Casa de Teja",
    "gn:population":320,
    "gn:timezone":"America/Mexico_City",
    "iso:country":"MX",
    "wof:name":"Casa de Teja",
    "wof:placetype":"locality",
    "wof:population":320
},
  "geometry": {"coordinates":[-103.13583,20.45639],"type":"Point"}
}