{
  "type": "Feature",
  "properties": {
    "gn:admin1_code":"30.0",
    "gn:admin2_code":"144.0",
    "gn:asciiname":"El Tamarindo",
    "gn:country_code":"MX",
    "gn:dem":65,
    "gn:feature_class":"P",
    "gn:feature_code":"PPL",
    "gn:name":"El Tamarindo",
    "gn:population":0,
    "gn:timezone":"America/Mexico_City",
    "iso:country":"MX",
    "name:spa_x_preferred":[
        "El Tamarindo"
    ],
    "wof:name":"El Tamarindo",
    "wof:placetype":"locality"
},
  "geometry": {"coordinates":[-94.98896999999999,17.84582],"type":"Point"}
}