{
  "type": "Feature",
  "properties": {
    "gn:admin1_code":"6",
    "gn:admin2_code":"41.0",
    "gn:asciiname":"Juveachi",
    "gn:country_code":"MX",
    "gn:dem":2280,
    "gn:feature_class":"P",
    "gn:feature_code":"PPL",
    "gn:name":"Juv\u00e9achi",
    "gn:population":0,
    "gn:timezone":"America/Chihuahua",
    "iso:country":"MX",
    "name:spa_x_preferred":[
        "Juv\u00e9achi"
    ],
    "wof:name":"Juveachi",
    "wof:placetype":"locality"
},
  "geometry": {"coordinates":[-107.86445000000001,27.82198],"type":"Point"}
}