{
  "type": "Feature",
  "properties": {
    "gn:admin1_code":"1",
    "gn:admin2_code":"2",
    "gn:asciiname":"Las Amapolas [Rancho]",
    "gn:country_code":"MX",
    "gn:dem":2050,
    "gn:feature_class":"P",
    "gn:feature_code":"PPL",
    "gn:name":"Las Amapolas [Rancho]",
    "gn:population":18,
    "gn:timezone":"America/Mexico_City",
    "iso:country":"MX",
    "wof:name":"Las Amapolas [Rancho]",
    "wof:placetype":"locality",
    "wof:population":18
},
  "geometry": {"coordinates":[-102.14667,22.08583],"type":"Point"}
}