{
  "type": "Feature",
  "properties": {
    "gn:admin1_code":"21",
    "gn:admin2_code":"64.0",
    "gn:asciiname":"Palma Real de Afuera",
    "gn:cc2":"MX",
    "gn:country_code":"MX",
    "gn:dem":111,
    "gn:feature_class":"P",
    "gn:feature_code":"PPL",
    "gn:name":"Palma Real de Afuera",
    "gn:population":0,
    "gn:timezone":"America/Mexico_City",
    "iso:country":"MX",
    "name:und_x_variant":[
        "Palma Real",
        "Palma Real de Afuera"
    ],
    "wof:name":"Palma Real de Afuera",
    "wof:placetype":"locality"
},
  "geometry": {"coordinates":[-97.76667,20.81667],"type":"Point"}
}