{
  "type": "Feature",
  "properties": {
    "gn:admin1_code":"10",
    "gn:admin2_code":"24.0",
    "gn:asciiname":"Francisco Marquez",
    "gn:country_code":"MX",
    "gn:dem":1316,
    "gn:feature_class":"P",
    "gn:feature_code":"PPL",
    "gn:name":"Francisco M\u00e1rquez",
    "gn:population":74,
    "gn:timezone":"America/Monterrey",
    "iso:country":"MX",
    "name:und_x_variant":[
        "Francisco M\u00e1rquez"
    ],
    "wof:name":"Francisco Marquez",
    "wof:placetype":"locality",
    "wof:population":74
},
  "geometry": {"coordinates":[-104.48739999999999,25.13365],"type":"Point"}
}