{
  "type": "Feature",
  "properties": {
    "gn:admin1_code":"10",
    "gn:admin2_code":"14.0",
    "gn:asciiname":"Santiago Teneraca",
    "gn:country_code":"MX",
    "gn:dem":1116,
    "gn:feature_class":"P",
    "gn:feature_code":"PPL",
    "gn:name":"Santiago Teneraca",
    "gn:population":269,
    "gn:timezone":"America/Monterrey",
    "iso:country":"MX",
    "wof:name":"Santiago Teneraca",
    "wof:placetype":"locality",
    "wof:population":269
},
  "geometry": {"coordinates":[-104.75664,23.08197],"type":"Point"}
}