{
  "type": "Feature",
  "properties": {
    "gn:admin1_code":"5",
    "gn:admin2_code":"34",
    "gn:asciiname":"Ampliacion Colon",
    "gn:country_code":"MX",
    "gn:dem":606,
    "gn:feature_class":"P",
    "gn:feature_code":"PPL",
    "gn:name":"Ampliaci\u00f3n Col\u00f3n",
    "gn:population":14,
    "gn:timezone":"America/Mexico_City",
    "iso:country":"MX",
    "name:und_x_variant":[
        "Ampliaci\u00f3n Col\u00f3n"
    ],
    "wof:name":"Ampliacion Colon",
    "wof:placetype":"locality",
    "wof:population":14
},
  "geometry": {"coordinates":[-91.96167,15.79833],"type":"Point"}
}