{
  "type": "Feature",
  "properties": {
    "gn:admin1_code":"5.0",
    "gn:admin2_code":"10.0",
    "gn:asciiname":"Banderas",
    "gn:country_code":"MX",
    "gn:dem":2699,
    "gn:feature_class":"P",
    "gn:feature_code":"PPL",
    "gn:name":"Banderas",
    "gn:population":0,
    "gn:timezone":"America/Mexico_City",
    "iso:country":"MX",
    "name:ceb_x_preferred":[
        "Banderas"
    ],
    "name:deu_x_preferred":[
        "Banderas"
    ],
    "name:eus_x_preferred":[
        "Banderas"
    ],
    "name:fra_x_preferred":[
        "Banderas"
    ],
    "name:ita_x_preferred":[
        "Banderas"
    ],
    "name:nld_x_preferred":[
        "Banderas"
    ],
    "name:pol_x_preferred":[
        "Banderas"
    ],
    "name:por_x_preferred":[
        "Banderas"
    ],
    "name:spa_x_preferred":[
        "Banderas"
    ],
    "name:srp_x_preferred":[
        "\u0411\u0430\u043d\u0434\u0435\u0440\u0430\u0441"
    ],
    "name:swe_x_preferred":[
        "Banderas"
    ],
    "wof:name":"Banderas",
    "wof:placetype":"locality"
},
  "geometry": {"coordinates":[-92.18447,15.47063],"type":"Point"}
}