{
  "type": "Feature",
  "properties": {
    "gn:admin1_code":"12.0",
    "gn:admin2_code":"53.0",
    "gn:asciiname":"Loma de los Morales",
    "gn:country_code":"MX",
    "gn:dem":28,
    "gn:feature_class":"P",
    "gn:feature_code":"PPL",
    "gn:name":"Loma de los Morales",
    "gn:population":0,
    "gn:timezone":"America/Mexico_City",
    "iso:country":"MX",
    "name:spa_x_preferred":[
        "Loma de los Morales"
    ],
    "wof:name":"Loma de los Morales",
    "wof:placetype":"locality"
},
  "geometry": {"coordinates":[-99.20327,16.75633],"type":"Point"}
}