{
  "type": "Feature",
  "properties": {
    "gn:admin1_code":"24",
    "gn:admin2_code":"38.0",
    "gn:asciiname":"Espejo (Leobardo Sanchez)",
    "gn:country_code":"MX",
    "gn:dem":126,
    "gn:feature_class":"P",
    "gn:feature_code":"PPL",
    "gn:name":"Espejo (Leobardo S\u00e1nchez)",
    "gn:population":6,
    "gn:timezone":"America/Mexico_City",
    "iso:country":"MX",
    "name:und_x_variant":[
        "Espejo (Leobardo S\u00e1nchez)"
    ],
    "wof:name":"Espejo (Leobardo Sanchez)",
    "wof:placetype":"locality",
    "wof:population":6
},
  "geometry": {"coordinates":[-98.70972,21.42583],"type":"Point"}
}