{
  "type": "Feature",
  "properties": {
    "gn:admin1_code":"16",
    "gn:admin2_code":"9.0",
    "gn:asciiname":"San Jose de Chuen",
    "gn:country_code":"MX",
    "gn:dem":1804,
    "gn:feature_class":"P",
    "gn:feature_code":"PPL",
    "gn:name":"San Jos\u00e9 de Chu\u00e9n",
    "gn:population":634,
    "gn:timezone":"America/Mexico_City",
    "iso:country":"MX",
    "name:und_x_variant":[
        "San Jos\u00e9 de Chu\u00e9n"
    ],
    "wof:name":"San Jose de Chuen",
    "wof:placetype":"locality",
    "wof:population":634
},
  "geometry": {"coordinates":[-101.76000000000001,19.275],"type":"Point"}
}