{
  "type": "Feature",
  "properties": {
    "gn:admin1_code":"11.0",
    "gn:admin2_code":"30.0",
    "gn:asciiname":"Pozo de San Juan",
    "gn:country_code":"MX",
    "gn:dem":1875,
    "gn:feature_class":"P",
    "gn:feature_code":"PPL",
    "gn:name":"Pozo de San Juan",
    "gn:population":0,
    "gn:timezone":"America/Mexico_City",
    "iso:country":"MX",
    "name:spa_x_preferred":[
        "Pozo de San Juan"
    ],
    "wof:name":"Pozo de San Juan",
    "wof:placetype":"locality"
},
  "geometry": {"coordinates":[-101.01907,21.60595],"type":"Point"}
}