{
  "type": "Feature",
  "properties": {
    "gn:admin1_code":"30.0",
    "gn:admin2_code":"63.0",
    "gn:asciiname":"Cruz Manantial",
    "gn:country_code":"MX",
    "gn:dem":108,
    "gn:feature_class":"P",
    "gn:feature_code":"PPL",
    "gn:name":"Cruz Manantial",
    "gn:population":600,
    "gn:timezone":"America/Mexico_City",
    "iso:country":"MX",
    "name:spa_x_preferred":[
        "Cruz Manantial"
    ],
    "wof:name":"Cruz Manantial",
    "wof:placetype":"locality",
    "wof:population":600
},
  "geometry": {"coordinates":[-97.97444,21.325],"type":"Point"}
}