{
  "type": "Feature",
  "properties": {
    "gn:admin1_code":"7",
    "gn:admin2_code":"31.0",
    "gn:asciiname":"Sauceda",
    "gn:country_code":"MX",
    "gn:dem":738,
    "gn:feature_class":"P",
    "gn:feature_code":"PPL",
    "gn:name":"Sauceda",
    "gn:population":0,
    "gn:timezone":"America/Monterrey",
    "iso:country":"MX",
    "wof:name":"Sauceda",
    "wof:placetype":"locality"
},
  "geometry": {"coordinates":[-101.55,27.51667],"type":"Point"}
}