{
  "type": "Feature",
  "properties": {
    "gn:admin1_code":"1",
    "gn:admin2_code":"1.0",
    "gn:asciiname":"El Ausente (La Tigra)",
    "gn:country_code":"MX",
    "gn:dem":1875,
    "gn:feature_class":"P",
    "gn:feature_code":"PPL",
    "gn:name":"El Ausente (La Tigra)",
    "gn:population":5,
    "gn:timezone":"America/Mexico_City",
    "iso:country":"MX",
    "wof:name":"El Ausente (La Tigra)",
    "wof:placetype":"locality",
    "wof:population":5
},
  "geometry": {"coordinates":[-102.36389,21.89389],"type":"Point"}
}