{
  "type": "Feature",
  "properties": {
    "gn:admin1_code":"32",
    "gn:admin2_code":"23.0",
    "gn:asciiname":"Amotochil",
    "gn:country_code":"MX",
    "gn:dem":1365,
    "gn:feature_class":"P",
    "gn:feature_code":"PPL",
    "gn:name":"Amot\u00f3chil",
    "gn:population":0,
    "gn:timezone":"America/Mexico_City",
    "iso:country":"MX",
    "wof:name":"Amotochil",
    "wof:placetype":"locality"
},
  "geometry": {"coordinates":[-103.07746,21.40093],"type":"Point"}
}