{
  "type": "Feature",
  "properties": {
    "gn:admin1_code":"5",
    "gn:admin2_code":"76.0",
    "gn:asciiname":"Cristobal Colon",
    "gn:country_code":"MX",
    "gn:dem":511,
    "gn:feature_class":"P",
    "gn:feature_code":"PPL",
    "gn:name":"Crist\u00f3bal Col\u00f3n",
    "gn:population":1000,
    "gn:timezone":"America/Mexico_City",
    "iso:country":"MX",
    "name:ceb_x_preferred":[
        "Crist\u00f3bal Col\u00f3n"
    ],
    "name:fin_x_preferred":[
        "Crist\u00f3bal Col\u00f3n"
    ],
    "name:ita_x_preferred":[
        "Crist\u00f3bal Col\u00f3n"
    ],
    "name:pol_x_preferred":[
        "Crist\u00f3bal Col\u00f3n"
    ],
    "name:spa_x_preferred":[
        "Crist\u00f3bal Col\u00f3n"
    ],
    "name:swe_x_preferred":[
        "Crist\u00f3bal Col\u00f3n"
    ],
    "name:und_x_variant":[
        "Crist\u00f3bal Col\u00f3n"
    ],
    "wof:name":"Cristobal Colon",
    "wof:placetype":"locality",
    "wof:population":1000
},
  "geometry": {"coordinates":[-92.65582999999999,17.35389],"type":"Point"}
}