{
  "type": "Feature",
  "properties": {
    "gn:admin1_code":"24",
    "gn:admin2_code":"55.0",
    "gn:asciiname":"Emiliano Zapata (El Tepozan)",
    "gn:country_code":"MX",
    "gn:dem":2022,
    "gn:feature_class":"P",
    "gn:feature_code":"PPL",
    "gn:name":"Emiliano Zapata (El Tepoz\u00e1n)",
    "gn:population":181,
    "gn:timezone":"America/Mexico_City",
    "iso:country":"MX",
    "name:und_x_variant":[
        "Emiliano Zapata (El Tepoz\u00e1n)"
    ],
    "wof:name":"Emiliano Zapata (El Tepozan)",
    "wof:placetype":"locality",
    "wof:population":181
},
  "geometry": {"coordinates":[-100.72750000000001,22.08306],"type":"Point"}
}