{
  "type": "Feature",
  "properties": {
    "gn:admin1_code":"27.0",
    "gn:admin2_code":"16.0",
    "gn:asciiname":"La Argentina",
    "gn:country_code":"MX",
    "gn:dem":74,
    "gn:feature_class":"P",
    "gn:feature_code":"PPL",
    "gn:name":"La Argentina",
    "gn:population":0,
    "gn:timezone":"America/Mexico_City",
    "iso:country":"MX",
    "name:spa_x_preferred":[
        "La Argentina"
    ],
    "name:spa_x_variant":[
        "Javier Mina",
        "Primera Secci\u00f3n"
    ],
    "wof:name":"La Argentina",
    "wof:placetype":"locality"
},
  "geometry": {"coordinates":[-92.89467,17.54714],"type":"Point"}
}