{
  "type": "Feature",
  "properties": {
    "gn:admin1_code":"18.0",
    "gn:admin2_code":"17.0",
    "gn:asciiname":"Colonia San Jose",
    "gn:country_code":"MX",
    "gn:dem":930,
    "gn:feature_class":"P",
    "gn:feature_code":"PPL",
    "gn:name":"Colonia San Jos\u00e9",
    "gn:population":0,
    "gn:timezone":"America/Mazatlan",
    "iso:country":"MX",
    "name:spa_x_preferred":[
        "Colonia San Jos\u00e9"
    ],
    "wof:name":"Colonia San Jose",
    "wof:placetype":"locality"
},
  "geometry": {"coordinates":[-104.82455,21.46026],"type":"Point"}
}