{
  "type": "Feature",
  "properties": {
    "gn:admin1_code":"5",
    "gn:admin2_code":"77.0",
    "gn:asciiname":"Santa Lucia 2da. Seccion",
    "gn:country_code":"MX",
    "gn:dem":445,
    "gn:feature_class":"P",
    "gn:feature_code":"PPL",
    "gn:name":"Santa Luc\u00eda 2da. Secci\u00f3n",
    "gn:population":496,
    "gn:timezone":"America/Mexico_City",
    "iso:country":"MX",
    "name:und_x_variant":[
        "Santa Luc\u00eda 2da. Secci\u00f3n"
    ],
    "wof:name":"Santa Lucia 2da. Seccion",
    "wof:placetype":"locality",
    "wof:population":496
},
  "geometry": {"coordinates":[-92.44668,17.5512],"type":"Point"}
}