{
  "type": "Feature",
  "properties": {
    "gn:admin1_code":"7.0",
    "gn:admin2_code":"17.0",
    "gn:asciiname":"Benavides",
    "gn:country_code":"MX",
    "gn:dem":1112,
    "gn:feature_class":"P",
    "gn:feature_code":"PPL",
    "gn:name":"Benavides",
    "gn:population":0,
    "gn:timezone":"America/Monterrey",
    "iso:country":"MX",
    "name:spa_x_preferred":[
        "Benavides"
    ],
    "wof:name":"Benavides",
    "wof:placetype":"locality"
},
  "geometry": {"coordinates":[-103.17082000000001,25.50694],"type":"Point"}
}