{
  "type": "Feature",
  "properties": {
    "gn:admin1_code":"19",
    "gn:admin2_code":"32.0",
    "gn:asciiname":"Las Norias",
    "gn:country_code":"MX",
    "gn:dem":299,
    "gn:feature_class":"P",
    "gn:feature_code":"PPL",
    "gn:name":"Las Norias",
    "gn:population":0,
    "gn:timezone":"America/Monterrey",
    "iso:country":"MX",
    "name:spa_x_preferred":[
        "Las Norias"
    ],
    "wof:name":"Las Norias",
    "wof:placetype":"locality"
},
  "geometry": {"coordinates":[-100.35366,27.03025],"type":"Point"}
}