{
  "type": "Feature",
  "properties": {
    "gn:admin1_code":"6.0",
    "gn:admin2_code":"52.0",
    "gn:asciiname":"El Divisadero",
    "gn:country_code":"MX",
    "gn:dem":790,
    "gn:feature_class":"P",
    "gn:feature_code":"PPL",
    "gn:name":"El Divisadero",
    "gn:population":0,
    "gn:timezone":"America/Ojinaga",
    "iso:country":"MX",
    "name:ceb_x_preferred":[
        "El Divisadero"
    ],
    "name:deu_x_preferred":[
        "El Divisadero"
    ],
    "name:ita_x_preferred":[
        "El Divisadero"
    ],
    "name:por_x_preferred":[
        "El Divisadero"
    ],
    "name:spa_x_preferred":[
        "El Divisadero"
    ],
    "name:und_x_variant":[
        "Divisadero"
    ],
    "name:zho_x_preferred":[
        "\u57c3\u723e\u8fea\u7dad\u85a9\u5fb7\u7f85"
    ],
    "wof:name":"El Divisadero",
    "wof:placetype":"locality"
},
  "geometry": {"coordinates":[-104.4525,29.5422],"type":"Point"}
}