{
  "type": "Feature",
  "properties": {
    "gn:admin1_code":"14",
    "gn:admin2_code":"49.0",
    "gn:asciiname":"Playa Colorada",
    "gn:country_code":"MX",
    "gn:dem":707,
    "gn:feature_class":"P",
    "gn:feature_code":"PPL",
    "gn:name":"Playa Colorada",
    "gn:population":73,
    "gn:timezone":"America/Mexico_City",
    "iso:country":"MX",
    "wof:name":"Playa Colorada",
    "wof:placetype":"locality",
    "wof:population":73
},
  "geometry": {"coordinates":[-102.62889,19.44056],"type":"Point"}
}