{
  "type": "Feature",
  "properties": {
    "gn:admin1_code":"20.0",
    "gn:asciiname":"La Escalera",
    "gn:country_code":"MX",
    "gn:dem":652,
    "gn:feature_class":"P",
    "gn:feature_code":"PPL",
    "gn:name":"La Escalera",
    "gn:population":0,
    "gn:timezone":"America/Mexico_City",
    "iso:country":"MX",
    "name:spa_x_preferred":[
        "La Escalera"
    ],
    "wof:name":"La Escalera",
    "wof:placetype":"locality"
},
  "geometry": {"coordinates":[-96.57384,17.96812000000001],"type":"Point"}
}