{
  "type": "Feature",
  "properties": {
    "gn:country":"MX",
    "gn:fcode":"PPL",
    "gn:population":0,
    "iso:country":"MX",
    "name:bre_x_preferred":[
        "Sabina"
    ],
    "name:bul_x_preferred":[
        "\u0421\u0430\u0431\u0438\u043d\u0430"
    ],
    "name:cat_x_preferred":[
        "Sabina"
    ],
    "name:ceb_x_preferred":[
        "Sabina"
    ],
    "name:dan_x_preferred":[
        "Sabina"
    ],
    "name:deu_x_preferred":[
        "Sabina"
    ],
    "name:est_x_preferred":[
        "Sabina"
    ],
    "name:fin_x_preferred":[
        "Sabina"
    ],
    "name:fra_x_preferred":[
        "Sabina"
    ],
    "name:glg_x_preferred":[
        "Sabina"
    ],
    "name:hin_x_preferred":[
        "\u0938\u092c\u0940\u0928\u093e"
    ],
    "name:ita_x_preferred":[
        "Sabina"
    ],
    "name:jpn_x_preferred":[
        "\u30b5\u30d3\u30fc\u30ca"
    ],
    "name:kor_x_preferred":[
        "\uc0ac\ube44\ub098"
    ],
    "name:nld_x_preferred":[
        "Sabina"
    ],
    "name:nor_x_preferred":[
        "Sabina"
    ],
    "name:pol_x_preferred":[
        "Sabina"
    ],
    "name:por_x_preferred":[
        "Sabina"
    ],
    "name:rus_x_preferred":[
        "\u0421\u0430\u0431\u0438\u043d\u0430"
    ],
    "name:slk_x_preferred":[
        "Sabina"
    ],
    "name:spa_x_preferred":[
        "Sabina"
    ],
    "name:srp_x_preferred":[
        "\u0421\u0430\u0431\u0438\u043d\u0430"
    ],
    "name:swe_x_preferred":[
        "Sabina"
    ],
    "name:ukr_x_preferred":[
        "\u0421\u0430\u0431\u0456\u043d\u0430"
    ],
    "qs_pg:aaroncc":"MX",
    "qs_pg:gn_country":"MX",
    "qs_pg:gn_fcode":"PPL",
    "qs_pg:gn_pop":0,
    "qs_pg:name":"Sabina",
    "qs_pg:name_adm0":"M\u00e9xico",
    "qs_pg:name_adm1":"Tabasco",
    "qs_pg:photos":2,
    "qs_pg:photos_1k":1,
    "qs_pg:photos_9k":1,
    "qs_pg:photos_9r":1,
    "qs_pg:photos_all":2,
    "qs_pg:photos_sr":1,
    "qs_pg:pop_sr":0,
    "qs_pg:qs_pg_placetype":"neighbourhood",
    "qs_pg:qs_pg_placetype_gp":"Suburb",
    "qs_pg:woe_adm0":23424900,
    "woe:adm0_id":23424900,
    "woe:name_adm0":"M\u00e9xico",
    "woe:name_adm1":"Tabasco",
    "woe:placetype":"Suburb",
    "wof:name":"Sabina",
    "wof:placetype":"neighbourhood"
},
  "geometry": {"coordinates":[-92.95068000000001,17.95858],"type":"Point"}
}