{
  "type": "Feature",
  "properties": {
    "iso:country":"MX",
    "name:spa_x_preferred":[
        "Zona Centro"
    ],
    "qs:gn_adm0_cc":"MX",
    "qs:gn_local":3514026,
    "qs:gn_nam_loc":"zinacantan",
    "qs:gn_namadm1":"05",
    "qs:local_max":307,
    "qs:local_sum":307,
    "qs:localhoods":1,
    "qs:name":"Zona Centro",
    "qs:name_adm0":"M\u00e9xico",
    "qs:name_adm1":"Chiapas",
    "qs:name_adm2":"Zinacantan",
    "qs:name_local":"Zinacant\u00e1n",
    "qs:photo_max":118,
    "qs:photo_sum":307,
    "qs:placetype":"Suburb",
    "qs:quad_count":11,
    "qs:woe_adm0":23424900,
    "qs:woe_adm1":2346268,
    "qs:woe_adm2":12599818,
    "qs:woe_lau":0,
    "qs:woe_local":151742,
    "qs:woe_ver":"7.10.0",
    "wof:lang":[
        "spa"
    ],
    "wof:name":"Zona Centro",
    "wof:placetype":"neighbourhood"
},
  "geometry": {"coordinates":[-92.721597,16.760244],"type":"Point"}
}