{
  "type": "Feature",
  "properties": {
    "gn:admin1_code":"16",
    "gn:admin2_code":"101.0",
    "gn:asciiname":"Joya la Encinera",
    "gn:country_code":"MX",
    "gn:dem":1635,
    "gn:feature_class":"P",
    "gn:feature_code":"PPL",
    "gn:name":"Joya la Encinera",
    "gn:population":0,
    "gn:timezone":"America/Mexico_City",
    "iso:country":"MX",
    "name:spa_x_preferred":[
        "Joya la Encinera"
    ],
    "wof:name":"Joya la Encinera",
    "wof:placetype":"locality"
},
  "geometry": {"coordinates":[-100.78328999999999,19.3345],"type":"Point"}
}