{
  "type": "Feature",
  "properties": {
    "gn:admin1_code":"25",
    "gn:admin2_code":"17.0",
    "gn:asciiname":"Campo Tres Carolinas",
    "gn:country_code":"MX",
    "gn:dem":64,
    "gn:feature_class":"P",
    "gn:feature_code":"PPL",
    "gn:name":"Campo Tres Carolinas",
    "gn:population":7,
    "gn:timezone":"America/Mazatlan",
    "iso:country":"MX",
    "wof:name":"Campo Tres Carolinas",
    "wof:placetype":"locality",
    "wof:population":7
},
  "geometry": {"coordinates":[-108.33056999999999,25.84364],"type":"Point"}
}