{
  "type": "Feature",
  "properties": {
    "gn:admin1_code":"24",
    "gn:admin2_code":"26.0",
    "gn:asciiname":"Tocoy",
    "gn:country_code":"MX",
    "gn:dem":260,
    "gn:feature_class":"P",
    "gn:feature_code":"PPL",
    "gn:name":"Tocoy",
    "gn:population":1061,
    "gn:timezone":"America/Mexico_City",
    "iso:country":"MX",
    "wof:name":"Tocoy",
    "wof:placetype":"locality",
    "wof:population":1061
},
  "geometry": {"coordinates":[-98.87083,21.63861],"type":"Point"}
}