{
  "type": "Feature",
  "properties": {
    "gn:admin1_code":"11",
    "gn:admin2_code":"3.0",
    "gn:asciiname":"San Miguel Viejo",
    "gn:country_code":"MX",
    "gn:dem":1860,
    "gn:feature_class":"P",
    "gn:feature_code":"PPL",
    "gn:name":"San Miguel Viejo",
    "gn:population":669,
    "gn:timezone":"America/Mexico_City",
    "iso:country":"MX",
    "wof:name":"San Miguel Viejo",
    "wof:placetype":"locality",
    "wof:population":669
},
  "geometry": {"coordinates":[-100.78028,20.90806],"type":"Point"}
}