{
  "type": "Feature",
  "properties": {
    "gn:admin1_code":"19",
    "gn:admin2_code":"22.0",
    "gn:asciiname":"El Encadenado",
    "gn:country_code":"MX",
    "gn:dem":208,
    "gn:feature_class":"P",
    "gn:feature_code":"PPL",
    "gn:name":"El Encadenado",
    "gn:population":0,
    "gn:timezone":"America/Monterrey",
    "iso:country":"MX",
    "name:und_x_variant":[
        "Encadenado",
        "El Encadenado"
    ],
    "wof:name":"El Encadenado",
    "wof:placetype":"locality"
},
  "geometry": {"coordinates":[-99.52079999999999,25.44662000000001],"type":"Point"}
}