{
  "type": "Feature",
  "properties": {
    "gn:admin1_code":"6",
    "gn:admin2_code":"30",
    "gn:asciiname":"Los Remedios",
    "gn:country_code":"MX",
    "gn:dem":1572,
    "gn:feature_class":"P",
    "gn:feature_code":"PPL",
    "gn:name":"Los Remedios",
    "gn:population":12,
    "gn:timezone":"America/Chihuahua",
    "iso:country":"MX",
    "wof:name":"Los Remedios",
    "wof:placetype":"locality",
    "wof:population":12
},
  "geometry": {"coordinates":[-108.30213999999999,27.28214],"type":"Point"}
}