{
  "type": "Feature",
  "properties": {
    "gn:admin1_code":"19",
    "gn:admin2_code":"22.0",
    "gn:asciiname":"El Charco",
    "gn:country_code":"MX",
    "gn:dem":357,
    "gn:feature_class":"P",
    "gn:feature_code":"PPL",
    "gn:name":"El Charco",
    "gn:population":0,
    "gn:timezone":"America/Monterrey",
    "iso:country":"MX",
    "name:deu_x_preferred":[
        "El Charco"
    ],
    "name:fas_x_preferred":[
        "\u0627\u0644 \u0686\u0627\u0631\u06a9\u0648"
    ],
    "name:fra_x_preferred":[
        "El Charco"
    ],
    "name:ita_x_preferred":[
        "El Charco"
    ],
    "name:kat_x_preferred":[
        "\u10d4\u10da-\u10e9\u10d0\u10e0\u10d9\u10dd"
    ],
    "name:msa_x_preferred":[
        "El Charco"
    ],
    "name:nld_x_preferred":[
        "El Charco"
    ],
    "name:por_x_preferred":[
        "El Charco"
    ],
    "name:sco_x_preferred":[
        "El Charco"
    ],
    "name:spa_x_preferred":[
        "El Charco"
    ],
    "name:tgl_x_preferred":[
        "El Charco"
    ],
    "name:vie_x_preferred":[
        "El Charco"
    ],
    "name:war_x_preferred":[
        "El Charco"
    ],
    "name:zho_x_preferred":[
        "\u57c3\u723e\u67e5\u723e\u79d1"
    ],
    "wof:name":"El Charco",
    "wof:placetype":"locality"
},
  "geometry": {"coordinates":[-99.59833,25.13035],"type":"Point"}
}