{
  "type": "Feature",
  "properties": {
    "gn:admin1_code":"25",
    "gn:admin2_code":"11.0",
    "gn:asciiname":"Cuesta de Arriba",
    "gn:country_code":"MX",
    "gn:dem":15,
    "gn:feature_class":"P",
    "gn:feature_code":"PPL",
    "gn:name":"Cuesta de Arriba",
    "gn:population":419,
    "gn:timezone":"America/Mazatlan",
    "iso:country":"MX",
    "wof:name":"Cuesta de Arriba",
    "wof:placetype":"locality",
    "wof:population":419
},
  "geometry": {"coordinates":[-108.44556,25.46611],"type":"Point"}
}