{
  "type": "Feature",
  "properties": {
    "gn:admin1_code":"3.0",
    "gn:admin2_code":"1.0",
    "gn:asciiname":"San Jose de la Noria",
    "gn:country_code":"MX",
    "gn:dem":367,
    "gn:feature_class":"P",
    "gn:feature_code":"PPL",
    "gn:name":"San Jos\u00e9 de la Noria",
    "gn:population":38,
    "gn:timezone":"America/Mazatlan",
    "iso:country":"MX",
    "name:spa_x_preferred":[
        "San Jos\u00e9 de la Noria"
    ],
    "wof:name":"San Jose de la Noria",
    "wof:placetype":"locality",
    "wof:population":38
},
  "geometry": {"coordinates":[-111.11426000000002,25.40539],"type":"Point"}
}