{
  "type": "Feature",
  "properties": {
    "gn:admin1_code":"16",
    "gn:admin2_code":"97.0",
    "gn:asciiname":"El Cobano",
    "gn:country_code":"MX",
    "gn:dem":941,
    "gn:feature_class":"P",
    "gn:feature_code":"PPL",
    "gn:name":"El Cobano",
    "gn:population":0,
    "gn:timezone":"America/Mexico_City",
    "iso:country":"MX",
    "name:spa_x_preferred":[
        "El Cobano"
    ],
    "wof:name":"El Cobano",
    "wof:placetype":"locality"
},
  "geometry": {"coordinates":[-101.41424000000001,18.80004],"type":"Point"}
}