{
  "type": "Feature",
  "properties": {
    "gn:admin1_code":"26.0",
    "gn:admin2_code":"64.0",
    "gn:asciiname":"El Boludo",
    "gn:country_code":"MX",
    "gn:dem":564,
    "gn:feature_class":"P",
    "gn:feature_code":"PPL",
    "gn:name":"El Boludo",
    "gn:population":0,
    "gn:timezone":"America/Hermosillo",
    "iso:country":"MX",
    "name:spa_x_preferred":[
        "El Boludo"
    ],
    "wof:name":"El Boludo",
    "wof:placetype":"locality"
},
  "geometry": {"coordinates":[-111.75694,30.33075],"type":"Point"}
}