{
  "type": "Feature",
  "properties": {
    "gn:admin1_code":"25.0",
    "gn:admin2_code":"16.0",
    "gn:asciiname":"El Destierro",
    "gn:country_code":"MX",
    "gn:dem":282,
    "gn:feature_class":"P",
    "gn:feature_code":"PPL",
    "gn:name":"El Destierro",
    "gn:population":0,
    "gn:timezone":"America/Mazatlan",
    "iso:country":"MX",
    "name:spa_x_preferred":[
        "El Destierro"
    ],
    "name:und_x_variant":[
        "Destierro"
    ],
    "wof:name":"El Destierro",
    "wof:placetype":"locality"
},
  "geometry": {"coordinates":[-106.43377,23.87742],"type":"Point"}
}