{
  "type": "Feature",
  "properties": {
    "gn:admin1_code":"30",
    "gn:admin2_code":"33.0",
    "gn:asciiname":"La Rosita",
    "gn:country_code":"MX",
    "gn:dem":58,
    "gn:feature_class":"P",
    "gn:feature_code":"PPL",
    "gn:name":"La Rosita",
    "gn:population":8,
    "gn:timezone":"America/Mexico_City",
    "iso:country":"MX",
    "wof:name":"La Rosita",
    "wof:placetype":"locality",
    "wof:population":8
},
  "geometry": {"coordinates":[-97.25639,20.74917],"type":"Point"}
}