{
  "type": "Feature",
  "properties": {
    "gn:admin1_code":"12",
    "gn:admin2_code":"68.0",
    "gn:asciiname":"Surcua",
    "gn:country_code":"MX",
    "gn:dem":18,
    "gn:feature_class":"P",
    "gn:feature_code":"PPL",
    "gn:name":"Surc\u00faa",
    "gn:population":0,
    "gn:timezone":"America/Mexico_City",
    "iso:country":"MX",
    "name:spa_x_preferred":[
        "Surc\u00faa"
    ],
    "name:und_x_variant":[
        "Sorcua"
    ],
    "wof:name":"Surcua",
    "wof:placetype":"locality"
},
  "geometry": {"coordinates":[-102.08096999999999,18.00799],"type":"Point"}
}