{
  "type": "Feature",
  "properties": {
    "gn:admin1_code":"24",
    "gn:admin2_code":"36.0",
    "gn:asciiname":"El Naranjo",
    "gn:country_code":"MX",
    "gn:dem":261,
    "gn:feature_class":"P",
    "gn:feature_code":"PPL",
    "gn:name":"El Naranjo",
    "gn:population":0,
    "gn:timezone":"America/Mexico_City",
    "iso:country":"MX",
    "name:spa_x_preferred":[
        "El Naranjo"
    ],
    "name:spa_x_variant":[
        "Naranjos"
    ],
    "wof:name":"El Naranjo",
    "wof:placetype":"locality"
},
  "geometry": {"coordinates":[-99.24324,21.68927],"type":"Point"}
}