{
  "type": "Feature",
  "properties": {
    "gn:admin1_code":"30",
    "gn:admin2_code":"181.0",
    "gn:asciiname":"El Moralillo",
    "gn:country_code":"MX",
    "gn:dem":24,
    "gn:feature_class":"P",
    "gn:feature_code":"PPL",
    "gn:name":"El Moralillo",
    "gn:population":212,
    "gn:timezone":"America/Mexico_City",
    "iso:country":"MX",
    "wof:name":"El Moralillo",
    "wof:placetype":"locality",
    "wof:population":212
},
  "geometry": {"coordinates":[-96.11944,18.71889],"type":"Point"}
}