{
  "type": "Feature",
  "properties": {
    "gn:admin1_code":"15.0",
    "gn:admin2_code":"105.0",
    "gn:asciiname":"Corral de Piedra",
    "gn:country_code":"MX",
    "gn:dem":1005,
    "gn:feature_class":"P",
    "gn:feature_code":"PPL",
    "gn:name":"Corral de Piedra",
    "gn:population":268,
    "gn:timezone":"America/Mexico_City",
    "iso:country":"MX",
    "name:spa_x_preferred":[
        "Corral de Piedra"
    ],
    "wof:name":"Corral de Piedra",
    "wof:placetype":"locality",
    "wof:population":268
},
  "geometry": {"coordinates":[-100.24732,18.57525],"type":"Point"}
}