{
  "type": "Feature",
  "properties": {
    "gn:admin1_code":"30",
    "gn:admin2_code":"139.0",
    "gn:asciiname":"El Caleton",
    "gn:cc2":"MX",
    "gn:country_code":"MX",
    "gn:dem":5,
    "gn:feature_class":"P",
    "gn:feature_code":"PPL",
    "gn:name":"El Calet\u00f3n",
    "gn:population":0,
    "gn:timezone":"America/Mexico_City",
    "iso:country":"MX",
    "name:und_x_variant":[
        "El Coleton",
        "El Calet\u00f3n"
    ],
    "wof:name":"El Caleton",
    "wof:placetype":"locality"
},
  "geometry": {"coordinates":[-95.55,18.55],"type":"Point"}
}