{
  "type": "Feature",
  "properties": {
    "gn:admin1_code":"14",
    "gn:admin2_code":"56",
    "gn:asciiname":"Mesa de Mendoza",
    "gn:country_code":"MX",
    "gn:dem":1321,
    "gn:feature_class":"P",
    "gn:feature_code":"PPL",
    "gn:name":"Mesa de Mendoza",
    "gn:population":13,
    "gn:timezone":"America/Mexico_City",
    "iso:country":"MX",
    "wof:name":"Mesa de Mendoza",
    "wof:placetype":"locality",
    "wof:population":13
},
  "geometry": {"coordinates":[-102.74833,19.59417],"type":"Point"}
}