{
  "type": "Feature",
  "properties": {
    "gn:admin1_code":"26",
    "gn:admin2_code":"70.0",
    "gn:asciiname":"Bladimiro Leon",
    "gn:country_code":"MX",
    "gn:dem":461,
    "gn:feature_class":"P",
    "gn:feature_code":"PPL",
    "gn:name":"Bladimiro Le\u00f3n",
    "gn:population":6,
    "gn:timezone":"America/Hermosillo",
    "iso:country":"MX",
    "name:und_x_variant":[
        "Bladimiro Le\u00f3n"
    ],
    "wof:name":"Bladimiro Leon",
    "wof:placetype":"locality",
    "wof:population":6
},
  "geometry": {"coordinates":[-112.64833,31.75167],"type":"Point"}
}