{
  "type": "Feature",
  "properties": {
    "gn:admin1_code":"11",
    "gn:admin2_code":"25.0",
    "gn:asciiname":"Canada de Soto",
    "gn:country_code":"MX",
    "gn:dem":1825,
    "gn:feature_class":"P",
    "gn:feature_code":"PPL",
    "gn:name":"Ca\u00f1ada de Soto",
    "gn:population":746,
    "gn:timezone":"America/Mexico_City",
    "iso:country":"MX",
    "name:und_x_variant":[
        "Ca\u00f1ada de Soto"
    ],
    "wof:name":"Canada de Soto",
    "wof:placetype":"locality",
    "wof:population":746
},
  "geometry": {"coordinates":[-101.81639,21.06111],"type":"Point"}
}