{
  "type": "Feature",
  "properties": {
    "gn:admin1_code":"20",
    "gn:admin2_code":"272",
    "gn:asciiname":"Colonia Aeropuerto",
    "gn:country_code":"MX",
    "gn:dem":778,
    "gn:feature_class":"P",
    "gn:feature_code":"PPL",
    "gn:name":"Colonia Aeropuerto",
    "gn:population":22,
    "gn:timezone":"America/Mexico_City",
    "iso:country":"MX",
    "wof:name":"Colonia Aeropuerto",
    "wof:placetype":"locality",
    "wof:population":22
},
  "geometry": {"coordinates":[-97.38500000000001,16.25639],"type":"Point"}
}