{
  "type": "Feature",
  "properties": {
    "gn:admin1_code":"6.0",
    "gn:admin2_code":"40.0",
    "gn:asciiname":"Tres Piedras",
    "gn:country_code":"MX",
    "gn:dem":1387,
    "gn:feature_class":"P",
    "gn:feature_code":"PPL",
    "gn:name":"Tres Piedras",
    "gn:population":0,
    "gn:timezone":"America/Chihuahua",
    "iso:country":"MX",
    "name:spa_x_preferred":[
        "Tres Piedras"
    ],
    "wof:name":"Tres Piedras",
    "wof:placetype":"locality"
},
  "geometry": {"coordinates":[-108.45202,28.942],"type":"Point"}
}