{
  "type": "Feature",
  "properties": {
    "gn:admin1_code":"28",
    "gn:admin2_code":"39.0",
    "gn:asciiname":"Alvaro Obregon",
    "gn:country_code":"MX",
    "gn:dem":1379,
    "gn:feature_class":"P",
    "gn:feature_code":"PPL",
    "gn:name":"\u00c1lvaro Obreg\u00f3n",
    "gn:population":0,
    "gn:timezone":"America/Monterrey",
    "iso:country":"MX",
    "name:und_x_variant":[
        "\u00c1lvaro Obreg\u00f3n",
        "Alvaro Obreg\u00f3n"
    ],
    "wof:name":"Alvaro Obregon",
    "wof:placetype":"locality"
},
  "geometry": {"coordinates":[-99.69398,23.17406],"type":"Point"}
}