{
  "type": "Feature",
  "properties": {
    "gn:admin1_code":"6",
    "gn:admin2_code":"29",
    "gn:asciiname":"El Chihuite",
    "gn:country_code":"MX",
    "gn:dem":2595,
    "gn:feature_class":"P",
    "gn:feature_code":"PPL",
    "gn:name":"El Chihuite",
    "gn:population":23,
    "gn:timezone":"America/Chihuahua",
    "iso:country":"MX",
    "wof:name":"El Chihuite",
    "wof:placetype":"locality",
    "wof:population":23
},
  "geometry": {"coordinates":[-106.93623999999998,26.03718],"type":"Point"}
}