{
  "type": "Feature",
  "properties": {
    "gn:admin1_code":"16",
    "gn:admin2_code":"57.0",
    "gn:asciiname":"Puerto el Toro",
    "gn:country_code":"MX",
    "gn:dem":920,
    "gn:feature_class":"P",
    "gn:feature_code":"PPL",
    "gn:name":"Puerto el Toro",
    "gn:population":0,
    "gn:timezone":"America/Mexico_City",
    "iso:country":"MX",
    "name:spa_x_preferred":[
        "Puerto el Toro"
    ],
    "wof:name":"Puerto el Toro",
    "wof:placetype":"locality"
},
  "geometry": {"coordinates":[-101.12048,19.09973],"type":"Point"}
}