{
  "type": "Feature",
  "properties": {
    "gn:admin1_code":"13",
    "gn:admin2_code":"8.0",
    "gn:asciiname":"San Joaquin",
    "gn:country_code":"MX",
    "gn:dem":2468,
    "gn:feature_class":"P",
    "gn:feature_code":"PPL",
    "gn:name":"San Joaqu\u00edn",
    "gn:population":7,
    "gn:timezone":"America/Mexico_City",
    "iso:country":"MX",
    "name:ceb_x_preferred":[
        "San Joaquin"
    ],
    "name:deu_x_preferred":[
        "San Joaquin"
    ],
    "name:fra_x_preferred":[
        "San Joaquin"
    ],
    "name:ita_x_preferred":[
        "San Joaquin"
    ],
    "name:nds_x_preferred":[
        "San Joaquin"
    ],
    "name:nld_x_preferred":[
        "San Joaquin"
    ],
    "name:pol_x_preferred":[
        "San Joaquin"
    ],
    "name:por_x_preferred":[
        "San Joaquin"
    ],
    "name:swe_x_preferred":[
        "San Joaquin"
    ],
    "name:und_x_variant":[
        "San Joaqu\u00edn"
    ],
    "name:war_x_preferred":[
        "San Joaquin"
    ],
    "wof:name":"San Joaquin",
    "wof:placetype":"locality",
    "wof:population":7
},
  "geometry": {"coordinates":[-98.47028,19.72306],"type":"Point"}
}