{
  "type": "Feature",
  "properties": {
    "gn:admin1_code":"6",
    "gn:admin2_code":"13.0",
    "gn:asciiname":"La Nina",
    "gn:country_code":"MX",
    "gn:dem":1418,
    "gn:feature_class":"P",
    "gn:feature_code":"PPL",
    "gn:name":"La Ni\u00f1a",
    "gn:population":4,
    "gn:timezone":"America/Chihuahua",
    "iso:country":"MX",
    "name:und_x_variant":[
        "La Ni\u00f1a"
    ],
    "wof:name":"La Nina",
    "wof:placetype":"locality",
    "wof:population":4
},
  "geometry": {"coordinates":[-107.98972999999999,30.54096],"type":"Point"}
}