{
  "type": "Feature",
  "properties": {
    "gn:admin1_code":"2",
    "gn:admin2_code":"3.0",
    "gn:asciiname":"El Plateado",
    "gn:country_code":"MX",
    "gn:dem":277,
    "gn:feature_class":"P",
    "gn:feature_code":"PPL",
    "gn:name":"El Plateado",
    "gn:population":6,
    "gn:timezone":"America/Tijuana",
    "iso:country":"MX",
    "wof:name":"El Plateado",
    "wof:placetype":"locality",
    "wof:population":6
},
  "geometry": {"coordinates":[-116.61528,32.37694],"type":"Point"}
}