{
  "type": "Feature",
  "properties": {
    "gn:admin1_code":"16",
    "gn:admin2_code":"19.0",
    "gn:asciiname":"Los Cachos",
    "gn:country_code":"MX",
    "gn:dem":1613,
    "gn:feature_class":"P",
    "gn:feature_code":"PPL",
    "gn:name":"Los Cachos",
    "gn:population":0,
    "gn:timezone":"America/Mexico_City",
    "iso:country":"MX",
    "wof:name":"Los Cachos",
    "wof:placetype":"locality"
},
  "geometry": {"coordinates":[-102.59999999999999,19.75],"type":"Point"}
}