{
  "type": "Feature",
  "properties": {
    "gn:admin1_code":"5.0",
    "gn:admin2_code":"75.0",
    "gn:asciiname":"Candelaria el Pozo",
    "gn:country_code":"MX",
    "gn:dem":2242,
    "gn:feature_class":"P",
    "gn:feature_code":"PPL",
    "gn:name":"Candelaria el Pozo",
    "gn:population":0,
    "gn:timezone":"America/Mexico_City",
    "iso:country":"MX",
    "name:spa_x_preferred":[
        "Candelaria el Pozo"
    ],
    "wof:name":"Candelaria el Pozo",
    "wof:placetype":"locality"
},
  "geometry": {"coordinates":[-92.32888,16.42915],"type":"Point"}
}