{
  "type": "Feature",
  "properties": {
    "gn:admin1_code":"16",
    "gn:admin2_code":"92.0",
    "gn:asciiname":"Palo Quemado",
    "gn:country_code":"MX",
    "gn:dem":477,
    "gn:feature_class":"P",
    "gn:feature_code":"PPL",
    "gn:name":"Palo Quemado",
    "gn:population":0,
    "gn:timezone":"America/Mexico_City",
    "iso:country":"MX",
    "name:spa_x_preferred":[
        "Palo Quemado"
    ],
    "wof:name":"Palo Quemado",
    "wof:placetype":"locality"
},
  "geometry": {"coordinates":[-100.83438,18.89652],"type":"Point"}
}