{
  "type": "Feature",
  "properties": {
    "gn:admin1_code":"20",
    "gn:admin2_code":"498.0",
    "gn:asciiname":"La Milpa",
    "gn:country_code":"MX",
    "gn:dem":96,
    "gn:feature_class":"P",
    "gn:feature_code":"PPL",
    "gn:name":"La Milpa",
    "gn:population":6,
    "gn:timezone":"America/Mexico_City",
    "iso:country":"MX",
    "wof:name":"La Milpa",
    "wof:placetype":"locality",
    "wof:population":6
},
  "geometry": {"coordinates":[-95.46666999999999,17.4725],"type":"Point"}
}