{
  "type": "Feature",
  "properties": {
    "gn:admin1_code":"30.0",
    "gn:admin2_code":"155.0",
    "gn:asciiname":"Chote Arriba",
    "gn:country_code":"MX",
    "gn:dem":98,
    "gn:feature_class":"P",
    "gn:feature_code":"PPL",
    "gn:name":"Chote Arriba",
    "gn:population":29,
    "gn:timezone":"America/Mexico_City",
    "iso:country":"MX",
    "name:spa_x_preferred":[
        "Chote Arriba"
    ],
    "wof:name":"Chote Arriba",
    "wof:placetype":"locality",
    "wof:population":29
},
  "geometry": {"coordinates":[-98.16167,21.485],"type":"Point"}
}