{
  "type": "Feature",
  "properties": {
    "gn:admin1_code":"6",
    "gn:admin2_code":"38.0",
    "gn:asciiname":"El Apache",
    "gn:country_code":"MX",
    "gn:dem":1344,
    "gn:feature_class":"P",
    "gn:feature_code":"PPL",
    "gn:name":"El Apache",
    "gn:population":0,
    "gn:timezone":"America/Chihuahua",
    "iso:country":"MX",
    "wof:name":"El Apache",
    "wof:placetype":"locality"
},
  "geometry": {"coordinates":[-105.14324000000001,28.50988],"type":"Point"}
}