{
  "type": "Feature",
  "properties": {
    "gn:admin1_code":"30",
    "gn:admin2_code":"79",
    "gn:asciiname":"Marintla",
    "gn:country_code":"MX",
    "gn:dem":1589,
    "gn:feature_class":"P",
    "gn:feature_code":"PPL",
    "gn:name":"Marintla",
    "gn:population":19,
    "gn:timezone":"America/Mexico_City",
    "iso:country":"MX",
    "wof:name":"Marintla",
    "wof:placetype":"locality",
    "wof:population":19
},
  "geometry": {"coordinates":[-97.07138999999999,19.37444],"type":"Point"}
}