{
  "type": "Feature",
  "properties": {
    "gn:admin1_code":"7",
    "gn:admin2_code":"13.0",
    "gn:asciiname":"Puerto de Agua Verde",
    "gn:country_code":"MX",
    "gn:dem":220,
    "gn:feature_class":"P",
    "gn:feature_code":"PPL",
    "gn:name":"Puerto de Agua Verde",
    "gn:population":0,
    "gn:timezone":"America/Monterrey",
    "iso:country":"MX",
    "name:spa_x_preferred":[
        "Puerto de Agua Verde"
    ],
    "name:und_x_variant":[
        "Rancho Puerto de Agua Verde"
    ],
    "wof:name":"Puerto de Agua Verde",
    "wof:placetype":"locality"
},
  "geometry": {"coordinates":[-100.21736,27.79609],"type":"Point"}
}