{
  "type": "Feature",
  "properties": {
    "gn:admin1_code":"29",
    "gn:admin2_code":"8",
    "gn:asciiname":"San Rafael Tepatlaxco (Union y Progreso)",
    "gn:country_code":"MX",
    "gn:dem":2583,
    "gn:feature_class":"P",
    "gn:feature_code":"PPL",
    "gn:name":"San Rafael Tepatlaxco (Uni\u00f3n y Progreso)",
    "gn:population":29,
    "gn:timezone":"America/Mexico_City",
    "iso:country":"MX",
    "name:und_x_variant":[
        "San Rafael Tepatlaxco (Uni\u00f3n y Progreso)"
    ],
    "wof:name":"San Rafael Tepatlaxco (Union y Progreso)",
    "wof:placetype":"locality",
    "wof:population":29
},
  "geometry": {"coordinates":[-97.85303999999999,19.37894],"type":"Point"}
}