{
  "type": "Feature",
  "properties": {
    "gn:admin1_code":"6",
    "gn:admin2_code":"27",
    "gn:asciiname":"Gueillamachi",
    "gn:country_code":"MX",
    "gn:dem":2351,
    "gn:feature_class":"P",
    "gn:feature_code":"PPL",
    "gn:name":"G\u00fcillamachi",
    "gn:population":15,
    "gn:timezone":"America/Chihuahua",
    "iso:country":"MX",
    "name:und_x_variant":[
        "G\u00fcillamachi"
    ],
    "wof:name":"Gueillamachi",
    "wof:placetype":"locality",
    "wof:population":15
},
  "geometry": {"coordinates":[-107.69714,27.43076],"type":"Point"}
}