{
  "type": "Feature",
  "properties": {
    "gn:admin1_code":"12.0",
    "gn:admin2_code":"22.0",
    "gn:asciiname":"Rincon de la Palma",
    "gn:country_code":"MX",
    "gn:dem":1231,
    "gn:feature_class":"P",
    "gn:feature_code":"PPL",
    "gn:name":"Rinc\u00f3n de la Palma",
    "gn:population":0,
    "gn:timezone":"America/Mexico_City",
    "iso:country":"MX",
    "name:spa_x_preferred":[
        "Rinc\u00f3n de la Palma"
    ],
    "wof:name":"Rincon de la Palma",
    "wof:placetype":"locality"
},
  "geometry": {"coordinates":[-100.83608,18.0181],"type":"Point"}
}