{
  "type": "Feature",
  "properties": {
    "gn:admin1_code":"19.0",
    "gn:asciiname":"San Nicolas de los Garza",
    "gn:country_code":"MX",
    "gn:dem":464,
    "gn:feature_class":"P",
    "gn:feature_code":"PPL",
    "gn:name":"San Nicol\u00e1s de los Garza",
    "gn:population":0,
    "gn:timezone":"America/Monterrey",
    "iso:country":"MX",
    "name:spa_x_preferred":[
        "San Nicol\u00e1s de los Garza"
    ],
    "name:spa_x_variant":[
        "San Nicol\u00e1s"
    ],
    "wof:name":"San Nicolas de los Garza",
    "wof:placetype":"locality"
},
  "geometry": {"coordinates":[-100.27744,25.87536],"type":"Point"}
}