{
  "type": "Feature",
  "properties": {
    "gn:admin1_code":"6",
    "gn:admin2_code":"55.0",
    "gn:asciiname":"Rancho la Manzana",
    "gn:country_code":"MX",
    "gn:dem":1177,
    "gn:feature_class":"P",
    "gn:feature_code":"PPL",
    "gn:name":"Rancho la Manzana",
    "gn:population":5,
    "gn:timezone":"America/Chihuahua",
    "iso:country":"MX",
    "wof:name":"Rancho la Manzana",
    "wof:placetype":"locality",
    "wof:population":5
},
  "geometry": {"coordinates":[-105.54713,28.17687],"type":"Point"}
}