{
  "type": "Feature",
  "properties": {
    "gn:admin1_code":"26",
    "gn:admin2_code":"29.0",
    "gn:asciiname":"El Pescado",
    "gn:country_code":"MX",
    "gn:dem":3,
    "gn:feature_class":"P",
    "gn:feature_code":"PPL",
    "gn:name":"El Pescado",
    "gn:population":43,
    "gn:timezone":"America/Hermosillo",
    "iso:country":"MX",
    "wof:name":"El Pescado",
    "wof:placetype":"locality",
    "wof:population":43
},
  "geometry": {"coordinates":[-110.38831,27.69193],"type":"Point"}
}