{
  "type": "Feature",
  "properties": {
    "gn:admin1_code":"10",
    "gn:admin2_code":"29.0",
    "gn:asciiname":"Encinillas de Arriba",
    "gn:country_code":"MX",
    "gn:dem":1838,
    "gn:feature_class":"P",
    "gn:feature_code":"PPL",
    "gn:name":"Encinillas de Arriba",
    "gn:population":0,
    "gn:timezone":"America/Monterrey",
    "iso:country":"MX",
    "name:spa_x_preferred":[
        "Encinillas de Arriba"
    ],
    "name:und_x_variant":[
        "Encillas de Arriba"
    ],
    "wof:name":"Encinillas de Arriba",
    "wof:placetype":"locality"
},
  "geometry": {"coordinates":[-104.38424000000001,25.29712],"type":"Point"}
}