{
  "type": "Feature",
  "properties": {
    "gn:admin1_code":"30.0",
    "gn:admin2_code":"189.0",
    "gn:asciiname":"Cuatro Cienegas",
    "gn:country_code":"MX",
    "gn:dem":7,
    "gn:feature_class":"P",
    "gn:feature_code":"PPL",
    "gn:name":"Cuatro Ci\u00e9negas",
    "gn:population":13,
    "gn:timezone":"America/Mexico_City",
    "iso:country":"MX",
    "name:spa_x_preferred":[
        "Cuatro Ci\u00e9negas"
    ],
    "wof:name":"Cuatro Cienegas",
    "wof:placetype":"locality",
    "wof:population":13
},
  "geometry": {"coordinates":[-97.28806,20.90889],"type":"Point"}
}