{
  "type": "Feature",
  "properties": {
    "gn:admin1_code":"30",
    "gn:admin2_code":"68.0",
    "gn:asciiname":"Paso Timon",
    "gn:country_code":"MX",
    "gn:dem":949,
    "gn:feature_class":"P",
    "gn:feature_code":"PPL",
    "gn:name":"Paso Tim\u00f3n",
    "gn:population":67,
    "gn:timezone":"America/Mexico_City",
    "iso:country":"MX",
    "name:und_x_variant":[
        "Paso Tim\u00f3n"
    ],
    "wof:name":"Paso Timon",
    "wof:placetype":"locality",
    "wof:population":67
},
  "geometry": {"coordinates":[-96.99028,18.88306],"type":"Point"}
}