{
  "type": "Feature",
  "properties": {
    "gn:admin1_code":"14",
    "gn:admin2_code":"63",
    "gn:asciiname":"Entronque Ocotlan",
    "gn:country_code":"MX",
    "gn:dem":1671,
    "gn:feature_class":"P",
    "gn:feature_code":"PPL",
    "gn:name":"Entronque Ocotl\u00e1n",
    "gn:population":19,
    "gn:timezone":"America/Mexico_City",
    "iso:country":"MX",
    "name:und_x_variant":[
        "Entronque Ocotl\u00e1n"
    ],
    "wof:name":"Entronque Ocotlan",
    "wof:placetype":"locality",
    "wof:population":19
},
  "geometry": {"coordinates":[-102.74778000000001,20.40583],"type":"Point"}
}