{
  "type": "Feature",
  "properties": {
    "gn:admin1_code":"5",
    "gn:admin2_code":"69.0",
    "gn:asciiname":"Plan de Ayala",
    "gn:country_code":"MX",
    "gn:dem":381,
    "gn:feature_class":"P",
    "gn:feature_code":"PPL",
    "gn:name":"Plan de Ayala",
    "gn:population":0,
    "gn:timezone":"America/Mexico_City",
    "iso:country":"MX",
    "name:spa_x_preferred":[
        "Plan de Ayala"
    ],
    "wof:name":"Plan de Ayala",
    "wof:placetype":"locality"
},
  "geometry": {"coordinates":[-93.03707,15.65998],"type":"Point"}
}