{
  "type": "Feature",
  "properties": {
    "gn:admin1_code":"20",
    "gn:admin2_code":"466.0",
    "gn:asciiname":"El Tetlate",
    "gn:country_code":"MX",
    "gn:dem":818,
    "gn:feature_class":"P",
    "gn:feature_code":"PPL",
    "gn:name":"El Tetlate",
    "gn:population":75,
    "gn:timezone":"America/Mexico_City",
    "iso:country":"MX",
    "wof:name":"El Tetlate",
    "wof:placetype":"locality",
    "wof:population":75
},
  "geometry": {"coordinates":[-97.70111,16.615],"type":"Point"}
}