{
  "type": "Feature",
  "properties": {
    "gn:admin1_code":"30",
    "gn:admin2_code":"66.0",
    "gn:asciiname":"Cinco de Octubre",
    "gn:country_code":"MX",
    "gn:dem":83,
    "gn:feature_class":"P",
    "gn:feature_code":"PPL",
    "gn:name":"Cinco de Octubre",
    "gn:population":220,
    "gn:timezone":"America/Mexico_City",
    "iso:country":"MX",
    "wof:name":"Cinco de Octubre",
    "wof:placetype":"locality",
    "wof:population":220
},
  "geometry": {"coordinates":[-97.52388999999999,20.27167],"type":"Point"}
}