{
  "type": "Feature",
  "properties": {
    "gn:admin1_code":"30",
    "gn:admin2_code":"89.0",
    "gn:asciiname":"La Escollera",
    "gn:country_code":"MX",
    "gn:dem":32,
    "gn:feature_class":"P",
    "gn:feature_code":"PPL",
    "gn:name":"La Escollera",
    "gn:population":9,
    "gn:timezone":"America/Mexico_City",
    "iso:country":"MX",
    "wof:name":"La Escollera",
    "wof:placetype":"locality",
    "wof:population":9
},
  "geometry": {"coordinates":[-94.71389000000001,17.91972],"type":"Point"}
}