{
  "type": "Feature",
  "properties": {
    "gn:admin1_code":"30.0",
    "gn:admin2_code":"161.0",
    "gn:asciiname":"Buenavista Uno",
    "gn:country_code":"MX",
    "gn:dem":87,
    "gn:feature_class":"P",
    "gn:feature_code":"PPL",
    "gn:name":"Buenavista Uno",
    "gn:population":2,
    "gn:timezone":"America/Mexico_City",
    "iso:country":"MX",
    "name:spa_x_preferred":[
        "Buenavista Uno"
    ],
    "wof:name":"Buenavista Uno",
    "wof:placetype":"locality",
    "wof:population":2
},
  "geometry": {"coordinates":[-98.18222,21.62083],"type":"Point"}
}