{
  "type": "Feature",
  "properties": {
    "gn:admin1_code":"20",
    "gn:admin2_code":"171.0",
    "gn:asciiname":"Agua Cuchara",
    "gn:country_code":"MX",
    "gn:dem":867,
    "gn:feature_class":"P",
    "gn:feature_code":"PPL",
    "gn:name":"Agua Cuchara",
    "gn:population":75,
    "gn:timezone":"America/Mexico_City",
    "iso:country":"MX",
    "wof:name":"Agua Cuchara",
    "wof:placetype":"locality",
    "wof:population":75
},
  "geometry": {"coordinates":[-96.705,18.15222],"type":"Point"}
}