{
  "type": "Feature",
  "properties": {
    "gn:admin1_code":"6",
    "gn:admin2_code":"65.0",
    "gn:asciiname":"Lluva de Oro",
    "gn:country_code":"MX",
    "gn:dem":588,
    "gn:feature_class":"P",
    "gn:feature_code":"PPL",
    "gn:name":"Lluva de Oro",
    "gn:population":0,
    "gn:timezone":"America/Mazatlan",
    "iso:country":"MX",
    "wof:name":"Lluva de Oro",
    "wof:placetype":"locality"
},
  "geometry": {"coordinates":[-108.09999999999999,26.91667],"type":"Point"}
}