{
  "type": "Feature",
  "properties": {
    "gn:admin1_code":"21.0",
    "gn:asciiname":"Temoapa",
    "gn:country_code":"MX",
    "gn:dem":1727,
    "gn:feature_class":"P",
    "gn:feature_code":"PPL",
    "gn:name":"Temoapa",
    "gn:population":0,
    "gn:timezone":"America/Mexico_City",
    "iso:country":"MX",
    "name:spa_x_preferred":[
        "Temoapa"
    ],
    "wof:name":"Temoapa",
    "wof:placetype":"locality"
},
  "geometry": {"coordinates":[-97.86311000000001,18.35473],"type":"Point"}
}