{
  "type": "Feature",
  "properties": {
    "gn:admin1_code":"18",
    "gn:admin2_code":"9.0",
    "gn:asciiname":"Huiscoyotl",
    "gn:country_code":"MX",
    "gn:dem":1572,
    "gn:feature_class":"P",
    "gn:feature_code":"PPL",
    "gn:name":"Huisc\u00f3yotl",
    "gn:population":5,
    "gn:timezone":"America/Mazatlan",
    "iso:country":"MX",
    "name:und_x_variant":[
        "Huisc\u00f3yotl"
    ],
    "wof:name":"Huiscoyotl",
    "wof:placetype":"locality",
    "wof:population":5
},
  "geometry": {"coordinates":[-104.72360999999999,22.11917],"type":"Point"}
}