{
  "type": "Feature",
  "properties": {
    "gn:admin1_code":"6",
    "gn:admin2_code":"47.0",
    "gn:asciiname":"Los Lobos",
    "gn:country_code":"MX",
    "gn:dem":1020,
    "gn:feature_class":"P",
    "gn:feature_code":"PPL",
    "gn:name":"Los Lobos",
    "gn:population":1,
    "gn:timezone":"America/Chihuahua",
    "iso:country":"MX",
    "name:spa_x_preferred":[
        "Los Lobos"
    ],
    "wof:name":"Los Lobos",
    "wof:placetype":"locality",
    "wof:population":1
},
  "geometry": {"coordinates":[-108.60004000000001,28.02472],"type":"Point"}
}