{
  "type": "Feature",
  "properties": {
    "gn:admin1_code":"21",
    "gn:admin2_code":"150.0",
    "gn:asciiname":"Colonia Agricola Hidalgo",
    "gn:country_code":"MX",
    "gn:dem":1641,
    "gn:feature_class":"P",
    "gn:feature_code":"PPL",
    "gn:name":"Colonia Agr\u00edcola Hidalgo",
    "gn:population":159,
    "gn:timezone":"America/Mexico_City",
    "iso:country":"MX",
    "name:und_x_variant":[
        "Colonia Agr\u00edcola Hidalgo"
    ],
    "wof:name":"Colonia Agricola Hidalgo",
    "wof:placetype":"locality",
    "wof:population":159
},
  "geometry": {"coordinates":[-98.19243,18.76792],"type":"Point"}
}