{
  "type": "Feature",
  "properties": {
    "gn:admin1_code":"11",
    "gn:admin2_code":"17.0",
    "gn:asciiname":"La Pila de los Hernandez",
    "gn:country_code":"MX",
    "gn:dem":1743,
    "gn:feature_class":"P",
    "gn:feature_code":"PPL",
    "gn:name":"La Pila de los Hern\u00e1ndez",
    "gn:population":90,
    "gn:timezone":"America/Mexico_City",
    "iso:country":"MX",
    "name:und_x_variant":[
        "La Pila de los Hern\u00e1ndez"
    ],
    "wof:name":"La Pila de los Hernandez",
    "wof:placetype":"locality",
    "wof:population":90
},
  "geometry": {"coordinates":[-101.50221999999999,20.74833],"type":"Point"}
}