{
  "type": "Feature",
  "properties": {
    "gn:admin1_code":"14",
    "gn:admin2_code":"17.0",
    "gn:asciiname":"Rancho las Aguilas",
    "gn:country_code":"MX",
    "gn:dem":1523,
    "gn:feature_class":"P",
    "gn:feature_code":"PPL",
    "gn:name":"Rancho las \u00c1guilas",
    "gn:population":5,
    "gn:timezone":"America/Mexico_City",
    "iso:country":"MX",
    "name:und_x_variant":[
        "Rancho las \u00c1guilas"
    ],
    "wof:name":"Rancho las Aguilas",
    "wof:placetype":"locality",
    "wof:population":5
},
  "geometry": {"coordinates":[-104.27722,20.17194],"type":"Point"}
}