{
  "type": "Feature",
  "properties": {
    "gn:admin1_code":"15",
    "gn:admin2_code":"8",
    "gn:asciiname":"El Jejen",
    "gn:country_code":"MX",
    "gn:dem":733,
    "gn:feature_class":"P",
    "gn:feature_code":"PPL",
    "gn:name":"El Jej\u00e9n",
    "gn:population":19,
    "gn:timezone":"America/Mexico_City",
    "iso:country":"MX",
    "name:und_x_variant":[
        "El Jej\u00e9n"
    ],
    "wof:name":"El Jejen",
    "wof:placetype":"locality",
    "wof:population":19
},
  "geometry": {"coordinates":[-100.29756,18.79112000000001],"type":"Point"}
}