{
  "type": "Feature",
  "properties": {
    "gn:admin1_code":"5.0",
    "gn:admin2_code":"62.0",
    "gn:asciiname":"Catedral Abajo Primera Seccion",
    "gn:country_code":"MX",
    "gn:dem":204,
    "gn:feature_class":"P",
    "gn:feature_code":"PPL",
    "gn:name":"Catedral Abajo Primera Secci\u00f3n",
    "gn:population":0,
    "gn:timezone":"America/Mexico_City",
    "iso:country":"MX",
    "name:spa_x_preferred":[
        "Catedral Abajo Primera Secci\u00f3n"
    ],
    "wof:name":"Catedral Abajo Primera Seccion",
    "wof:placetype":"locality"
},
  "geometry": {"coordinates":[-93.33790999999999,17.42375],"type":"Point"}
}