{
  "type": "Feature",
  "properties": {
    "gn:admin1_code":"26",
    "gn:asciiname":"Los Ajos",
    "gn:country_code":"MX",
    "gn:dem":1462,
    "gn:feature_class":"P",
    "gn:feature_code":"PPL",
    "gn:name":"Los Ajos",
    "gn:population":0,
    "gn:timezone":"America/Hermosillo",
    "iso:country":"MX",
    "wof:name":"Los Ajos",
    "wof:placetype":"locality"
},
  "geometry": {"coordinates":[-108.65000000000001,28.28333],"type":"Point"}
}