{
  "type": "Feature",
  "properties": {
    "gn:admin1_code":"32.0",
    "gn:admin2_code":"49.0",
    "gn:asciiname":"Pinos Altos",
    "gn:country_code":"MX",
    "gn:dem":2124,
    "gn:feature_class":"P",
    "gn:feature_code":"PPL",
    "gn:name":"Pinos Altos",
    "gn:population":0,
    "gn:timezone":"America/Mexico_City",
    "iso:country":"MX",
    "name:spa_x_preferred":[
        "Pinos Altos"
    ],
    "wof:name":"Pinos Altos",
    "wof:placetype":"locality"
},
  "geometry": {"coordinates":[-103.88731,22.77801],"type":"Point"}
}