{
  "type": "Feature",
  "properties": {
    "gn:admin1_code":"16",
    "gn:admin2_code":"69.0",
    "gn:asciiname":"La Escoba",
    "gn:country_code":"MX",
    "gn:dem":1663,
    "gn:feature_class":"P",
    "gn:feature_code":"PPL",
    "gn:name":"La Escoba",
    "gn:population":0,
    "gn:timezone":"America/Mexico_City",
    "iso:country":"MX",
    "name:spa_x_preferred":[
        "La Escoba"
    ],
    "name:und_x_variant":[
        "Las Escobas"
    ],
    "wof:name":"La Escoba",
    "wof:placetype":"locality"
},
  "geometry": {"coordinates":[-102.15298,20.36625],"type":"Point"}
}