{
  "type": "Feature",
  "properties": {
    "gn:admin1_code":"5",
    "gn:admin2_code":"99.0",
    "gn:asciiname":"San Lucas",
    "gn:country_code":"MX",
    "gn:dem":902,
    "gn:feature_class":"P",
    "gn:feature_code":"PPL",
    "gn:name":"San Lucas",
    "gn:population":0,
    "gn:timezone":"America/Mexico_City",
    "iso:country":"MX",
    "name:spa_x_preferred":[
        "San Lucas"
    ],
    "wof:name":"San Lucas",
    "wof:placetype":"locality"
},
  "geometry": {"coordinates":[-91.88684000000001,15.99258],"type":"Point"}
}