{
  "type": "Feature",
  "properties": {
    "gn:admin1_code":"6",
    "gn:admin2_code":"18.0",
    "gn:asciiname":"Cienega de Castillo",
    "gn:country_code":"MX",
    "gn:dem":1919,
    "gn:feature_class":"P",
    "gn:feature_code":"PPL",
    "gn:name":"Ci\u00e9nega de Castillo",
    "gn:population":0,
    "gn:timezone":"America/Chihuahua",
    "iso:country":"MX",
    "name:und_x_variant":[
        "Ci\u00e9naga de Castillos",
        "Ci\u00e9nega",
        "Ci\u00e9nega de Castillo"
    ],
    "wof:name":"Cienega de Castillo",
    "wof:placetype":"locality"
},
  "geometry": {"coordinates":[-106.71666999999999,28.36667000000001],"type":"Point"}
}