{
  "type": "Feature",
  "properties": {
    "gn:admin1_code":"12",
    "gn:admin2_code":"73",
    "gn:asciiname":"El Coco",
    "gn:country_code":"MX",
    "gn:dem":214,
    "gn:feature_class":"P",
    "gn:feature_code":"PPL",
    "gn:name":"El Coco",
    "gn:population":38,
    "gn:timezone":"America/Mexico_City",
    "iso:country":"MX",
    "wof:name":"El Coco",
    "wof:placetype":"locality",
    "wof:population":38
},
  "geometry": {"coordinates":[-100.9871,18.45618],"type":"Point"}
}