{
  "type": "Feature",
  "properties": {
    "gn:admin1_code":"19",
    "gn:admin2_code":"16.0",
    "gn:asciiname":"Garcia",
    "gn:country_code":"MX",
    "gn:dem":367,
    "gn:feature_class":"P",
    "gn:feature_code":"PPL",
    "gn:name":"Garc\u00eda",
    "gn:population":6,
    "gn:timezone":"America/Monterrey",
    "iso:country":"MX",
    "name:und_x_variant":[
        "Garc\u00eda"
    ],
    "wof:name":"Garcia",
    "wof:placetype":"locality",
    "wof:population":6
},
  "geometry": {"coordinates":[-99.78279999999999,25.87756],"type":"Point"}
}