{
  "type": "Feature",
  "properties": {
    "gn:admin1_code":"21",
    "gn:admin2_code":"50.0",
    "gn:asciiname":"Xochimilco",
    "gn:country_code":"MX",
    "gn:dem":1655,
    "gn:feature_class":"P",
    "gn:feature_code":"PPL",
    "gn:name":"Xochimilco",
    "gn:population":219,
    "gn:timezone":"America/Mexico_City",
    "iso:country":"MX",
    "wof:name":"Xochimilco",
    "wof:placetype":"locality",
    "wof:population":219
},
  "geometry": {"coordinates":[-97.04188000000001,19.23233],"type":"Point"}
}