{
  "type": "Feature",
  "properties": {
    "gn:admin1_code":"21",
    "gn:admin2_code":"110.0",
    "gn:asciiname":"Bellavista de Victoria (San Jose Bellavista)",
    "gn:country_code":"MX",
    "gn:dem":2239,
    "gn:feature_class":"P",
    "gn:feature_code":"PPL",
    "gn:name":"Bellavista de Victoria (San Jos\u00e9 Bellavista)",
    "gn:population":2492,
    "gn:timezone":"America/Mexico_City",
    "iso:country":"MX",
    "name:und_x_variant":[
        "Bellavista de Victoria (San Jos\u00e9 Bellavista)"
    ],
    "wof:name":"Bellavista de Victoria (San Jose Bellavista)",
    "wof:placetype":"locality",
    "wof:population":2492
},
  "geometry": {"coordinates":[-97.54389,18.87639],"type":"Point"}
}