{
  "type": "Feature",
  "properties": {
    "gn:admin1_code":"19.0",
    "gn:admin2_code":"5.0",
    "gn:asciiname":"Regantes Numero Diecinueve",
    "gn:country_code":"MX",
    "gn:dem":218,
    "gn:feature_class":"P",
    "gn:feature_code":"PPL",
    "gn:name":"Regantes N\u00famero Diecinueve",
    "gn:population":2,
    "gn:timezone":"America/Matamoros",
    "iso:country":"MX",
    "name:spa_x_preferred":[
        "Regantes N\u00famero Diecinueve"
    ],
    "name:und_x_variant":[
        "Regantes Diecinueve"
    ],
    "wof:name":"Regantes Numero Diecinueve",
    "wof:placetype":"locality",
    "wof:population":2
},
  "geometry": {"coordinates":[-100.34367,27.31752],"type":"Point"}
}