{
  "type": "Feature",
  "properties": {
    "gn:admin1_code":"19",
    "gn:admin2_code":"7.0",
    "gn:asciiname":"La Angostura",
    "gn:country_code":"MX",
    "gn:dem":2100,
    "gn:feature_class":"P",
    "gn:feature_code":"PPL",
    "gn:name":"La Angostura",
    "gn:population":0,
    "gn:timezone":"America/Monterrey",
    "iso:country":"MX",
    "name:ceb_x_preferred":[
        "La Angostura"
    ],
    "name:deu_x_preferred":[
        "La Angostura"
    ],
    "name:spa_x_preferred":[
        "La Angostura"
    ],
    "name:srp_x_preferred":[
        "\u041b\u0430 \u0410\u043d\u0433\u043e\u0441\u0442\u0443\u0440\u0430"
    ],
    "name:swe_x_preferred":[
        "La Angostura"
    ],
    "name:und_x_variant":[
        "Rancho La Angostura",
        "Angostura"
    ],
    "wof:name":"La Angostura",
    "wof:placetype":"locality"
},
  "geometry": {"coordinates":[-99.88436,24.41855],"type":"Point"}
}