{
  "type": "Feature",
  "properties": {
    "gn:admin1_code":"30",
    "gn:admin2_code":"72.0",
    "gn:asciiname":"Huayacoco",
    "gn:country_code":"MX",
    "gn:dem":2158,
    "gn:feature_class":"P",
    "gn:feature_code":"PPL",
    "gn:name":"Huayacoco",
    "gn:population":0,
    "gn:timezone":"America/Mexico_City",
    "iso:country":"MX",
    "wof:name":"Huayacoco",
    "wof:placetype":"locality"
},
  "geometry": {"coordinates":[-98.48333,20.53333],"type":"Point"}
}