{
  "type": "Feature",
  "properties": {
    "gn:admin1_code":"19",
    "gn:admin2_code":"13.0",
    "gn:asciiname":"El Purgatorio",
    "gn:country_code":"MX",
    "gn:dem":142,
    "gn:feature_class":"P",
    "gn:feature_code":"PPL",
    "gn:name":"El Purgatorio",
    "gn:population":6,
    "gn:timezone":"America/Monterrey",
    "iso:country":"MX",
    "wof:name":"El Purgatorio",
    "wof:placetype":"locality",
    "wof:population":6
},
  "geometry": {"coordinates":[-98.47999,25.41453],"type":"Point"}
}