{
  "type": "Feature",
  "properties": {
    "gn:admin1_code":"5",
    "gn:admin2_code":"44",
    "gn:asciiname":"Nuevo Monterrey",
    "gn:country_code":"MX",
    "gn:dem":1251,
    "gn:feature_class":"P",
    "gn:feature_code":"PPL",
    "gn:name":"Nuevo Monterrey",
    "gn:population":44,
    "gn:timezone":"America/Mexico_City",
    "iso:country":"MX",
    "wof:name":"Nuevo Monterrey",
    "wof:placetype":"locality",
    "wof:population":44
},
  "geometry": {"coordinates":[-92.96666999999999,16.80722],"type":"Point"}
}