{
  "type": "Feature",
  "properties": {
    "gn:admin1_code":"20",
    "gn:admin2_code":"73.0",
    "gn:asciiname":"El Cangrejo",
    "gn:country_code":"MX",
    "gn:dem":814,
    "gn:feature_class":"P",
    "gn:feature_code":"PPL",
    "gn:name":"El Cangrejo",
    "gn:population":65,
    "gn:timezone":"America/Mexico_City",
    "iso:country":"MX",
    "wof:name":"El Cangrejo",
    "wof:placetype":"locality",
    "wof:population":65
},
  "geometry": {"coordinates":[-97.87889,16.97972],"type":"Point"}
}