{
  "type": "Feature",
  "properties": {
    "gn:admin1_code":"20",
    "gn:admin2_code":"64.0",
    "gn:asciiname":"Soledad Agua Blanca",
    "gn:country_code":"MX",
    "gn:dem":1241,
    "gn:feature_class":"P",
    "gn:feature_code":"PPL",
    "gn:name":"Soledad Agua Blanca",
    "gn:population":0,
    "gn:timezone":"America/Mexico_City",
    "iso:country":"MX",
    "name:spa_x_preferred":[
        "Soledad Agua Blanca"
    ],
    "name:und_x_variant":[
        "Agua Blanca"
    ],
    "wof:name":"Soledad Agua Blanca",
    "wof:placetype":"locality"
},
  "geometry": {"coordinates":[-95.74159,16.65676],"type":"Point"}
}