{
  "type": "Feature",
  "properties": {
    "gn:admin1_code":"28",
    "gn:admin2_code":"2.0",
    "gn:asciiname":"Zanapam",
    "gn:country_code":"MX",
    "gn:dem":194,
    "gn:feature_class":"P",
    "gn:feature_code":"PPL",
    "gn:name":"Zanapam",
    "gn:population":0,
    "gn:timezone":"America/Monterrey",
    "iso:country":"MX",
    "name:und_x_variant":[
        "Zanapan"
    ],
    "wof:name":"Zanapam",
    "wof:placetype":"locality"
},
  "geometry": {"coordinates":[-98.05309,23.03083],"type":"Point"}
}