{
  "type": "Feature",
  "properties": {
    "gn:admin1_code":"6",
    "gn:admin2_code":"46",
    "gn:asciiname":"El Salto",
    "gn:country_code":"MX",
    "gn:dem":983,
    "gn:feature_class":"P",
    "gn:feature_code":"PPL",
    "gn:name":"El Salto",
    "gn:population":18,
    "gn:timezone":"America/Chihuahua",
    "iso:country":"MX",
    "wof:name":"El Salto",
    "wof:placetype":"locality",
    "wof:population":18
},
  "geometry": {"coordinates":[-107.73406,26.67744],"type":"Point"}
}