{
  "type": "Feature",
  "properties": {
    "gn:admin1_code":"6",
    "gn:admin2_code":"46",
    "gn:asciiname":"El Salto",
    "gn:country_code":"MX",
    "gn:dem":983,
    "gn:feature_class":"P",
    "gn:feature_code":"PPL",
    "gn:name":"El Salto",
    "gn:population":18,
    "gn:timezone":"America/Chihuahua",
    "iso:country":"MX",
    "name:ceb_x_preferred":[
        "El Salto"
    ],
    "name:deu_x_preferred":[
        "El Salto"
    ],
    "name:epo_x_preferred":[
        "El Salto"
    ],
    "name:ita_x_preferred":[
        "El Salto"
    ],
    "name:spa_x_preferred":[
        "El Salto"
    ],
    "name:srp_x_preferred":[
        "\u0415\u043b \u0421\u0430\u043b\u0442\u043e"
    ],
    "name:swe_x_preferred":[
        "El Salto"
    ],
    "name:vie_x_preferred":[
        "El Salto"
    ],
    "wof:name":"El Salto",
    "wof:placetype":"locality",
    "wof:population":18
},
  "geometry": {"coordinates":[-107.73406,26.67744],"type":"Point"}
}