{
  "type": "Feature",
  "properties": {
    "gn:admin1_code":"5.0",
    "gn:asciiname":"Sonora Brasilar",
    "gn:country_code":"MX",
    "gn:dem":678,
    "gn:feature_class":"P",
    "gn:feature_code":"PPL",
    "gn:name":"Sonora Brasilar",
    "gn:population":0,
    "gn:timezone":"America/Mexico_City",
    "iso:country":"MX",
    "name:spa_x_preferred":[
        "Sonora Brasilar"
    ],
    "wof:name":"Sonora Brasilar",
    "wof:placetype":"locality"
},
  "geometry": {"coordinates":[-92.45197,16.30198],"type":"Point"}
}