{
  "type": "Feature",
  "properties": {
    "gn:admin1_code":"14",
    "gn:admin2_code":"97.0",
    "gn:asciiname":"Potrero Grande",
    "gn:country_code":"MX",
    "gn:dem":1565,
    "gn:feature_class":"P",
    "gn:feature_code":"PPL",
    "gn:name":"Potrero Grande",
    "gn:population":9,
    "gn:timezone":"America/Mexico_City",
    "iso:country":"MX",
    "name:ceb_x_preferred":[
        "Potrero Grande"
    ],
    "wof:name":"Potrero Grande",
    "wof:placetype":"locality",
    "wof:population":9
},
  "geometry": {"coordinates":[-103.28444,20.44111],"type":"Point"}
}