{
  "type": "Feature",
  "properties": {
    "gn:admin1_code":"5.0",
    "gn:admin2_code":"87.0",
    "gn:asciiname":"Los Problemas",
    "gn:country_code":"MX",
    "gn:dem":15,
    "gn:feature_class":"P",
    "gn:feature_code":"PPL",
    "gn:name":"Los Problemas",
    "gn:population":0,
    "gn:timezone":"America/Mexico_City",
    "iso:country":"MX",
    "name:spa_x_preferred":[
        "Los Problemas"
    ],
    "wof:name":"Los Problemas",
    "wof:placetype":"locality"
},
  "geometry": {"coordinates":[-92.20492,14.60551],"type":"Point"}
}