{
  "type": "Feature",
  "properties": {
    "gn:admin1_code":"6.0",
    "gn:admin2_code":"15.0",
    "gn:asciiname":"San Jose Numero Uno",
    "gn:country_code":"MX",
    "gn:dem":978,
    "gn:feature_class":"P",
    "gn:feature_code":"PPL",
    "gn:name":"San Jos\u00e9 N\u00famero Uno",
    "gn:population":0,
    "gn:timezone":"America/Chihuahua",
    "iso:country":"MX",
    "name:spa_x_preferred":[
        "San Jos\u00e9 N\u00famero Uno"
    ],
    "wof:name":"San Jose Numero Uno",
    "wof:placetype":"locality"
},
  "geometry": {"coordinates":[-104.79931000000001,29.47231],"type":"Point"}
}