{
  "type": "Feature",
  "properties": {
    "gn:admin1_code":"32",
    "gn:admin2_code":"49.0",
    "gn:asciiname":"Cancun",
    "gn:country_code":"MX",
    "gn:dem":1987,
    "gn:feature_class":"P",
    "gn:feature_code":"PPL",
    "gn:name":"Canc\u00fan",
    "gn:population":7,
    "gn:timezone":"America/Mexico_City",
    "iso:country":"MX",
    "name:und_x_variant":[
        "Canc\u00fan"
    ],
    "wof:name":"Cancun",
    "wof:placetype":"locality",
    "wof:population":7
},
  "geometry": {"coordinates":[-103.85472,22.43361],"type":"Point"}
}