{
  "type": "Feature",
  "properties": {
    "gn:admin1_code":"12",
    "gn:admin2_code":"48",
    "gn:asciiname":"Chiverillos",
    "gn:country_code":"MX",
    "gn:dem":433,
    "gn:feature_class":"P",
    "gn:feature_code":"PPL",
    "gn:name":"Chiverillos",
    "gn:population":23,
    "gn:timezone":"America/Mexico_City",
    "iso:country":"MX",
    "wof:name":"Chiverillos",
    "wof:placetype":"locality",
    "wof:population":23
},
  "geometry": {"coordinates":[-101.01612,17.53939],"type":"Point"}
}