{
  "type": "Feature",
  "properties": {
    "gn:admin1_code":"6",
    "gn:admin2_code":"51.0",
    "gn:asciiname":"Las Calaveras",
    "gn:cc2":"MX",
    "gn:country_code":"MX",
    "gn:dem":2510,
    "gn:feature_class":"P",
    "gn:feature_code":"PPL",
    "gn:name":"Las Calaveras",
    "gn:population":0,
    "gn:timezone":"America/Chihuahua",
    "iso:country":"MX",
    "name:und_x_variant":[
        "Calaveras",
        "Las Calaveras de Arriba",
        "Las Calaveras"
    ],
    "wof:name":"Las Calaveras",
    "wof:placetype":"locality"
},
  "geometry": {"coordinates":[-107.88333,28.06667],"type":"Point"}
}