{
  "type": "Feature",
  "properties": {
    "gn:admin1_code":"10.0",
    "gn:admin2_code":"22.0",
    "gn:asciiname":"Ojo Zarco",
    "gn:country_code":"MX",
    "gn:dem":2109,
    "gn:feature_class":"P",
    "gn:feature_code":"PPL",
    "gn:name":"Ojo Zarco",
    "gn:population":0,
    "gn:timezone":"America/Monterrey",
    "iso:country":"MX",
    "name:spa_x_preferred":[
        "Ojo Zarco"
    ],
    "wof:name":"Ojo Zarco",
    "wof:placetype":"locality"
},
  "geometry": {"coordinates":[-104.01492,24.12222],"type":"Point"}
}