{
  "type": "Feature",
  "properties": {
    "gn:admin1_code":"31",
    "gn:admin2_code":"52.0",
    "gn:asciiname":"Las Codornices",
    "gn:country_code":"MX",
    "gn:dem":12,
    "gn:feature_class":"P",
    "gn:feature_code":"PPL",
    "gn:name":"Las Codornices",
    "gn:population":7,
    "gn:timezone":"America/Merida",
    "iso:country":"MX",
    "wof:name":"Las Codornices",
    "wof:placetype":"locality",
    "wof:population":7
},
  "geometry": {"coordinates":[-89.29472,21.11028],"type":"Point"}
}