{
  "type": "Feature",
  "properties": {
    "gn:admin1_code":"6",
    "gn:admin2_code":"27.0",
    "gn:asciiname":"Chuachi",
    "gn:country_code":"MX",
    "gn:dem":2194,
    "gn:feature_class":"P",
    "gn:feature_code":"PPL",
    "gn:name":"Chuachi",
    "gn:population":14,
    "gn:timezone":"America/Chihuahua",
    "iso:country":"MX",
    "name:spa_x_preferred":[
        "Chuachi"
    ],
    "wof:name":"Chuachi",
    "wof:placetype":"locality",
    "wof:population":14
},
  "geometry": {"coordinates":[-107.08462,27.11549],"type":"Point"}
}