{
  "type": "Feature",
  "properties": {
    "gn:admin1_code":"5",
    "gn:admin2_code":"104.0",
    "gn:asciiname":"San Miguel Modin",
    "gn:country_code":"MX",
    "gn:dem":1307,
    "gn:feature_class":"P",
    "gn:feature_code":"PPL",
    "gn:name":"San Miguel Mod\u00edn",
    "gn:population":7,
    "gn:timezone":"America/Mexico_City",
    "iso:country":"MX",
    "name:und_x_variant":[
        "San Miguel Mod\u00edn"
    ],
    "wof:name":"San Miguel Modin",
    "wof:placetype":"locality",
    "wof:population":7
},
  "geometry": {"coordinates":[-92.2175,16.20277999999999],"type":"Point"}
}