{
  "type": "Feature",
  "properties": {
    "gn:admin1_code":"18",
    "gn:admin2_code":"16.0",
    "gn:asciiname":"Nunca Tranquilo",
    "gn:country_code":"MX",
    "gn:dem":4,
    "gn:feature_class":"P",
    "gn:feature_code":"PPL",
    "gn:name":"Nunca Tranquilo",
    "gn:population":0,
    "gn:timezone":"America/Mazatlan",
    "iso:country":"MX",
    "name:spa_x_preferred":[
        "Nunca Tranquilo"
    ],
    "wof:name":"Nunca Tranquilo",
    "wof:placetype":"locality"
},
  "geometry": {"coordinates":[-105.66834,22.32208],"type":"Point"}
}