{
  "type": "Feature",
  "properties": {
    "gn:admin1_code":"26.0",
    "gn:admin2_code":"13.0",
    "gn:asciiname":"Juan Lopez",
    "gn:country_code":"MX",
    "gn:dem":781,
    "gn:feature_class":"P",
    "gn:feature_code":"PPL",
    "gn:name":"Juan L\u00f3pez",
    "gn:population":0,
    "gn:timezone":"America/Hermosillo",
    "iso:country":"MX",
    "wof:name":"Juan Lopez",
    "wof:placetype":"locality"
},
  "geometry": {"coordinates":[-110.16667,30.03333],"type":"Point"}
}