{
  "type": "Feature",
  "properties": {
    "gn:admin1_code":"17.0",
    "gn:asciiname":"Garcia",
    "gn:country_code":"MX",
    "gn:dem":1152,
    "gn:feature_class":"P",
    "gn:feature_code":"PPL",
    "gn:name":"Garc\u00eda",
    "gn:population":0,
    "gn:timezone":"America/Mexico_City",
    "iso:country":"MX",
    "name:spa_x_preferred":[
        "Garc\u00eda"
    ],
    "wof:name":"Garcia",
    "wof:placetype":"locality"
},
  "geometry": {"coordinates":[-98.76873999999999,18.59697],"type":"Point"}
}