{
  "type": "Feature",
  "properties": {
    "gn:admin1_code":"15",
    "gn:admin2_code":"118.0",
    "gn:asciiname":"El Capon (Puerta del Llano)",
    "gn:country_code":"MX",
    "gn:dem":2713,
    "gn:feature_class":"P",
    "gn:feature_code":"PPL",
    "gn:name":"El Cap\u00f3n (Puerta del Llano)",
    "gn:population":158,
    "gn:timezone":"America/Mexico_City",
    "iso:country":"MX",
    "name:und_x_variant":[
        "El Cap\u00f3n (Puerta del Llano)"
    ],
    "wof:name":"El Capon (Puerta del Llano)",
    "wof:placetype":"locality",
    "wof:population":158
},
  "geometry": {"coordinates":[-99.74639000000001,19.31556],"type":"Point"}
}