{
  "type": "Feature",
  "properties": {
    "gn:admin1_code":"24",
    "gn:admin2_code":"39",
    "gn:asciiname":"Primer Subida",
    "gn:country_code":"MX",
    "gn:dem":116,
    "gn:feature_class":"P",
    "gn:feature_code":"PPL",
    "gn:name":"Primer Subida",
    "gn:population":15,
    "gn:timezone":"America/Mexico_City",
    "iso:country":"MX",
    "wof:name":"Primer Subida",
    "wof:placetype":"locality",
    "wof:population":15
},
  "geometry": {"coordinates":[-98.81917,21.56861],"type":"Point"}
}