{
  "type": "Feature",
  "properties": {
    "gn:admin1_code":"13",
    "gn:admin2_code":"16.0",
    "gn:asciiname":"Caballo Rucio",
    "gn:country_code":"MX",
    "gn:dem":2662,
    "gn:feature_class":"P",
    "gn:feature_code":"PPL",
    "gn:name":"Caballo Rucio",
    "gn:population":8,
    "gn:timezone":"America/Mexico_City",
    "iso:country":"MX",
    "wof:name":"Caballo Rucio",
    "wof:placetype":"locality",
    "wof:population":8
},
  "geometry": {"coordinates":[-98.16722,19.97556],"type":"Point"}
}