{
  "type": "Feature",
  "properties": {
    "gn:admin1_code":"2",
    "gn:admin2_code":"1",
    "gn:asciiname":"El Barril (La Roca) [Centro de Rehabilitacion]",
    "gn:country_code":"MX",
    "gn:dem":760,
    "gn:feature_class":"P",
    "gn:feature_code":"PPL",
    "gn:name":"El Barril (La Roca) [Centro de Rehabilitaci\u00f3n]",
    "gn:population":30,
    "gn:timezone":"America/Tijuana",
    "iso:country":"MX",
    "name:und_x_variant":[
        "El Barril (La Roca) [Centro de Rehabilitaci\u00f3n]"
    ],
    "wof:name":"El Barril (La Roca) [Centro de Rehabilitacion]",
    "wof:placetype":"locality",
    "wof:population":30
},
  "geometry": {"coordinates":[-116.37472,31.91806],"type":"Point"}
}