{
  "type": "Feature",
  "properties": {
    "gn:admin1_code":"11",
    "gn:admin2_code":"11.0",
    "gn:asciiname":"Palmira",
    "gn:country_code":"MX",
    "gn:dem":1746,
    "gn:feature_class":"P",
    "gn:feature_code":"PPL",
    "gn:name":"Palmira",
    "gn:population":5,
    "gn:timezone":"America/Mexico_City",
    "iso:country":"MX",
    "wof:name":"Palmira",
    "wof:placetype":"locality",
    "wof:population":5
},
  "geometry": {"coordinates":[-100.91056,20.51333],"type":"Point"}
}