{
  "type": "Feature",
  "properties": {
    "gn:admin1_code":"4.0",
    "gn:admin2_code":"3.0",
    "gn:asciiname":"San Gabriel",
    "gn:country_code":"MX",
    "gn:dem":8,
    "gn:feature_class":"P",
    "gn:feature_code":"PPL",
    "gn:name":"San Gabriel",
    "gn:population":0,
    "gn:timezone":"America/Merida",
    "iso:country":"MX",
    "name:spa_x_preferred":[
        "San Gabriel"
    ],
    "wof:name":"San Gabriel",
    "wof:placetype":"locality"
},
  "geometry": {"coordinates":[-90.98528,18.83972],"type":"Point"}
}