{
  "type": "Feature",
  "properties": {
    "gn:admin1_code":"21",
    "gn:admin2_code":"113.0",
    "gn:asciiname":"Cristo Rey",
    "gn:country_code":"MX",
    "gn:dem":1160,
    "gn:feature_class":"P",
    "gn:feature_code":"PPL",
    "gn:name":"Cristo Rey",
    "gn:population":81,
    "gn:timezone":"America/Mexico_City",
    "iso:country":"MX",
    "wof:name":"Cristo Rey",
    "wof:placetype":"locality",
    "wof:population":81
},
  "geometry": {"coordinates":[-98.25942999999999,18.19298],"type":"Point"}
}