{
  "type": "Feature",
  "properties": {
    "gn:admin1_code":"2.0",
    "gn:admin2_code":"1.0",
    "gn:asciiname":"La Cremeria",
    "gn:country_code":"MX",
    "gn:dem":673,
    "gn:feature_class":"P",
    "gn:feature_code":"PPL",
    "gn:name":"La Cremer\u00eda",
    "gn:population":0,
    "gn:timezone":"America/Tijuana",
    "iso:country":"MX",
    "name:spa_x_preferred":[
        "La Cremer\u00eda"
    ],
    "wof:name":"La Cremeria",
    "wof:placetype":"locality"
},
  "geometry": {"coordinates":[-116.29998999999999,31.98451],"type":"Point"}
}