{
  "type": "Feature",
  "properties": {
    "gn:admin1_code":"26",
    "gn:admin2_code":"30",
    "gn:asciiname":"Dos Triangulos",
    "gn:country_code":"MX",
    "gn:dem":61,
    "gn:feature_class":"P",
    "gn:feature_code":"PPL",
    "gn:name":"Dos Tri\u00e1ngulos",
    "gn:population":18,
    "gn:timezone":"America/Hermosillo",
    "iso:country":"MX",
    "name:und_x_variant":[
        "Dos Tri\u00e1ngulos"
    ],
    "wof:name":"Dos Triangulos",
    "wof:placetype":"locality",
    "wof:population":18
},
  "geometry": {"coordinates":[-111.38806,28.69833],"type":"Point"}
}