{
  "type": "Feature",
  "properties": {
    "gn:admin1_code":"2",
    "gn:admin2_code":"1.0",
    "gn:asciiname":"El Dorado",
    "gn:country_code":"MX",
    "gn:dem":782,
    "gn:feature_class":"P",
    "gn:feature_code":"PPL",
    "gn:name":"El Dorado",
    "gn:population":0,
    "gn:timezone":"America/Tijuana",
    "iso:country":"MX",
    "name:spa_x_preferred":[
        "El Dorado"
    ],
    "wof:name":"El Dorado",
    "wof:placetype":"locality"
},
  "geometry": {"coordinates":[-115.69481,31.33996],"type":"Point"}
}