{
  "type": "Feature",
  "properties": {
    "gn:admin1_code":"24",
    "gn:admin2_code":"27.0",
    "gn:asciiname":"La Morita",
    "gn:country_code":"MX",
    "gn:dem":948,
    "gn:feature_class":"P",
    "gn:feature_code":"PPL",
    "gn:name":"La Morita",
    "gn:population":8,
    "gn:timezone":"America/Mexico_City",
    "iso:country":"MX",
    "wof:name":"La Morita",
    "wof:placetype":"locality",
    "wof:population":8
},
  "geometry": {"coordinates":[-99.83278,21.62806],"type":"Point"}
}