{
  "type": "Feature",
  "properties": {
    "gn:admin1_code":"14",
    "gn:admin2_code":"64.0",
    "gn:asciiname":"Papas de Arriba",
    "gn:country_code":"MX",
    "gn:dem":2281,
    "gn:feature_class":"P",
    "gn:feature_code":"PPL",
    "gn:name":"Papas de Arriba",
    "gn:population":0,
    "gn:timezone":"America/Mexico_City",
    "iso:country":"MX",
    "name:spa_x_preferred":[
        "Papas de Arriba"
    ],
    "wof:name":"Papas de Arriba",
    "wof:placetype":"locality"
},
  "geometry": {"coordinates":[-101.65335,21.72695],"type":"Point"}
}