{
  "type": "Feature",
  "properties": {
    "gn:admin1_code":"3",
    "gn:admin2_code":"1.0",
    "gn:asciiname":"Norte Lote 6",
    "gn:country_code":"MX",
    "gn:dem":52,
    "gn:feature_class":"P",
    "gn:feature_code":"PPL",
    "gn:name":"Norte Lote 6",
    "gn:population":4,
    "gn:timezone":"America/Mazatlan",
    "iso:country":"MX",
    "wof:name":"Norte Lote 6",
    "wof:placetype":"locality",
    "wof:population":4
},
  "geometry": {"coordinates":[-111.65953,25.13846],"type":"Point"}
}