{
  "type": "Feature",
  "properties": {
    "gn:admin1_code":"20.0",
    "gn:admin2_code":"474.0",
    "gn:asciiname":"El Ciruelito",
    "gn:country_code":"MX",
    "gn:dem":73,
    "gn:feature_class":"P",
    "gn:feature_code":"PPL",
    "gn:name":"El Ciruelito",
    "gn:population":0,
    "gn:timezone":"America/Mexico_City",
    "iso:country":"MX",
    "name:spa_x_preferred":[
        "El Ciruelito"
    ],
    "wof:name":"El Ciruelito",
    "wof:placetype":"locality"
},
  "geometry": {"coordinates":[-98.29731,16.55257000000001],"type":"Point"}
}