{
  "type": "Feature",
  "properties": {
    "gn:admin1_code":"28",
    "gn:admin2_code":"37.0",
    "gn:asciiname":"El Coronel",
    "gn:country_code":"MX",
    "gn:dem":79,
    "gn:feature_class":"P",
    "gn:feature_code":"PPL",
    "gn:name":"El Coronel",
    "gn:population":1,
    "gn:timezone":"America/Monterrey",
    "iso:country":"MX",
    "name:und_x_variant":[
        "Coronel",
        "El Coronel"
    ],
    "wof:name":"El Coronel",
    "wof:placetype":"locality",
    "wof:population":1
},
  "geometry": {"coordinates":[-98.20853,23.62253],"type":"Point"}
}