{
  "type": "Feature",
  "properties": {
    "gn:admin1_code":"23",
    "gn:admin2_code":"4",
    "gn:asciiname":"El Milagro del Siglo",
    "gn:country_code":"MX",
    "gn:dem":11,
    "gn:feature_class":"P",
    "gn:feature_code":"PPL",
    "gn:name":"El Milagro del Siglo",
    "gn:population":12,
    "gn:timezone":"America/Cancun",
    "iso:country":"MX",
    "wof:name":"El Milagro del Siglo",
    "wof:placetype":"locality",
    "wof:population":12
},
  "geometry": {"coordinates":[-88.26721999999999,18.63444],"type":"Point"}
}