{
  "type": "Feature",
  "properties": {
    "gn:admin1_code":"17",
    "gn:admin2_code":"12.0",
    "gn:asciiname":"Colonia el Paraiso (Colonia Vicente Guerrero)",
    "gn:country_code":"MX",
    "gn:dem":964,
    "gn:feature_class":"P",
    "gn:feature_code":"PPL",
    "gn:name":"Colonia el Para\u00edso (Colonia Vicente Guerrero)",
    "gn:population":113,
    "gn:timezone":"America/Mexico_City",
    "iso:country":"MX",
    "name:und_x_variant":[
        "Colonia el Para\u00edso (Colonia Vicente Guerrero)"
    ],
    "wof:name":"Colonia el Paraiso (Colonia Vicente Guerrero)",
    "wof:placetype":"locality",
    "wof:population":113
},
  "geometry": {"coordinates":[-99.21972,18.62944],"type":"Point"}
}