{
  "type": "Feature",
  "properties": {
    "gn:admin1_code":"6",
    "gn:admin2_code":"65.0",
    "gn:asciiname":"Selerabo",
    "gn:country_code":"MX",
    "gn:dem":2133,
    "gn:feature_class":"P",
    "gn:feature_code":"PPL",
    "gn:name":"Selerabo",
    "gn:population":6,
    "gn:timezone":"America/Chihuahua",
    "iso:country":"MX",
    "wof:name":"Selerabo",
    "wof:placetype":"locality",
    "wof:population":6
},
  "geometry": {"coordinates":[-107.88992,27.4302],"type":"Point"}
}