{
  "type": "Feature",
  "properties": {
    "gn:admin1_code":"26.0",
    "gn:admin2_code":"38.0",
    "gn:asciiname":"La Milpa de Barrio",
    "gn:country_code":"MX",
    "gn:dem":756,
    "gn:feature_class":"P",
    "gn:feature_code":"PPL",
    "gn:name":"La Milpa de Barrio",
    "gn:population":0,
    "gn:timezone":"America/Hermosillo",
    "iso:country":"MX",
    "name:spa_x_preferred":[
        "La Milpa de Barrio"
    ],
    "wof:name":"La Milpa de Barrio",
    "wof:placetype":"locality"
},
  "geometry": {"coordinates":[-109.70098,29.65699],"type":"Point"}
}