{
  "type": "Feature",
  "properties": {
    "gn:admin1_code":"7",
    "gn:admin2_code":"33.0",
    "gn:asciiname":"Vega Larga",
    "gn:country_code":"MX",
    "gn:dem":1106,
    "gn:feature_class":"P",
    "gn:feature_code":"PPL",
    "gn:name":"Vega Larga",
    "gn:population":523,
    "gn:timezone":"America/Monterrey",
    "iso:country":"MX",
    "wof:name":"Vega Larga",
    "wof:placetype":"locality",
    "wof:population":523
},
  "geometry": {"coordinates":[-103.20001000000001,25.88279],"type":"Point"}
}