{
  "type": "Feature",
  "properties": {
    "gn:admin1_code":"14",
    "gn:admin2_code":"94.0",
    "gn:asciiname":"El Zapote",
    "gn:country_code":"MX",
    "gn:dem":1639,
    "gn:feature_class":"P",
    "gn:feature_code":"PPL",
    "gn:name":"El Zapote",
    "gn:population":118,
    "gn:timezone":"America/Mexico_City",
    "iso:country":"MX",
    "wof:name":"El Zapote",
    "wof:placetype":"locality",
    "wof:population":118
},
  "geometry": {"coordinates":[-103.80167,21.19806],"type":"Point"}
}