{
  "type": "Feature",
  "properties": {
    "gn:admin1_code":"32.0",
    "gn:admin2_code":"14.0",
    "gn:asciiname":"San Antonio de los Pobres",
    "gn:country_code":"MX",
    "gn:dem":1852,
    "gn:feature_class":"P",
    "gn:feature_code":"PPL",
    "gn:name":"San Antonio de los Pobres",
    "gn:population":0,
    "gn:timezone":"America/Mexico_City",
    "iso:country":"MX",
    "name:spa_x_preferred":[
        "San Antonio de los Pobres"
    ],
    "wof:name":"San Antonio de los Pobres",
    "wof:placetype":"locality"
},
  "geometry": {"coordinates":[-102.36006999999999,24.12996],"type":"Point"}
}