{
  "type": "Feature",
  "properties": {
    "gn:admin1_code":"5",
    "gn:admin2_code":"31.0",
    "gn:asciiname":"Mojon Tzuy",
    "gn:country_code":"MX",
    "gn:dem":1247,
    "gn:feature_class":"P",
    "gn:feature_code":"PPL",
    "gn:name":"Moj\u00f3n Tzuy",
    "gn:population":60,
    "gn:timezone":"America/Mexico_City",
    "iso:country":"MX",
    "name:und_x_variant":[
        "Moj\u00f3n Tzuy"
    ],
    "wof:name":"Mojon Tzuy",
    "wof:placetype":"locality",
    "wof:population":60
},
  "geometry": {"coordinates":[-92.29056,17.03611],"type":"Point"}
}