{
  "type": "Feature",
  "properties": {
    "gn:admin1_code":"24",
    "gn:admin2_code":"31",
    "gn:asciiname":"Joya de Palma Real",
    "gn:country_code":"MX",
    "gn:dem":301,
    "gn:feature_class":"P",
    "gn:feature_code":"PPL",
    "gn:name":"Joya de Palma Real",
    "gn:population":20,
    "gn:timezone":"America/Mexico_City",
    "iso:country":"MX",
    "wof:name":"Joya de Palma Real",
    "wof:placetype":"locality",
    "wof:population":20
},
  "geometry": {"coordinates":[-99.32417,21.63333],"type":"Point"}
}