{
  "type": "Feature",
  "properties": {
    "gn:admin1_code":"14.0",
    "gn:admin2_code":"108.0",
    "gn:asciiname":"Barranca Verde",
    "gn:country_code":"MX",
    "gn:dem":1100,
    "gn:feature_class":"P",
    "gn:feature_code":"PPL",
    "gn:name":"Barranca Verde",
    "gn:population":0,
    "gn:timezone":"America/Mexico_City",
    "iso:country":"MX",
    "name:spa_x_preferred":[
        "Barranca Verde"
    ],
    "wof:name":"Barranca Verde",
    "wof:placetype":"locality"
},
  "geometry": {"coordinates":[-103.38218999999999,19.48211],"type":"Point"}
}