{
  "type": "Feature",
  "properties": {
    "gn:admin1_code":"16",
    "gn:admin2_code":"53",
    "gn:asciiname":"Curimeo",
    "gn:country_code":"MX",
    "gn:dem":2405,
    "gn:feature_class":"P",
    "gn:feature_code":"PPL",
    "gn:name":"Curimeo",
    "gn:population":20,
    "gn:timezone":"America/Mexico_City",
    "iso:country":"MX",
    "wof:name":"Curimeo",
    "wof:placetype":"locality",
    "wof:population":20
},
  "geometry": {"coordinates":[-101.18444,19.54833],"type":"Point"}
}