{
  "type": "Feature",
  "properties": {
    "gn:admin1_code":"5",
    "gn:admin2_code":"117.0",
    "gn:asciiname":"Rancho Bonito",
    "gn:country_code":"MX",
    "gn:dem":1219,
    "gn:feature_class":"P",
    "gn:feature_code":"PPL",
    "gn:name":"Rancho Bonito",
    "gn:population":6,
    "gn:timezone":"America/Mexico_City",
    "iso:country":"MX",
    "wof:name":"Rancho Bonito",
    "wof:placetype":"locality",
    "wof:population":6
},
  "geometry": {"coordinates":[-92.58472,15.73],"type":"Point"}
}