{
  "type": "Feature",
  "properties": {
    "gn:admin1_code":"26",
    "gn:admin2_code":"13.0",
    "gn:asciiname":"Los Vallecitos",
    "gn:country_code":"MX",
    "gn:dem":685,
    "gn:feature_class":"P",
    "gn:feature_code":"PPL",
    "gn:name":"Los Vallecitos",
    "gn:population":0,
    "gn:timezone":"America/Hermosillo",
    "iso:country":"MX",
    "name:spa_x_preferred":[
        "Los Vallecitos"
    ],
    "wof:name":"Los Vallecitos",
    "wof:placetype":"locality"
},
  "geometry": {"coordinates":[-110.22086000000002,30.06041],"type":"Point"}
}