{
  "type": "Feature",
  "properties": {
    "gn:admin1_code":"25",
    "gn:admin2_code":"7.0",
    "gn:asciiname":"Huirocoba de los Molinos",
    "gn:country_code":"MX",
    "gn:dem":317,
    "gn:feature_class":"P",
    "gn:feature_code":"PPL",
    "gn:name":"Huirocoba de los Molinos",
    "gn:population":0,
    "gn:timezone":"America/Mazatlan",
    "iso:country":"MX",
    "name:spa_x_preferred":[
        "Huirocoba de los Molinos"
    ],
    "name:und_x_variant":[
        "Molinos",
        "Los Molinos"
    ],
    "wof:name":"Huirocoba de los Molinos",
    "wof:placetype":"locality"
},
  "geometry": {"coordinates":[-108.27500999999999,26.97805],"type":"Point"}
}