{
  "type": "Feature",
  "properties": {
    "gn:admin1_code":"1",
    "gn:admin2_code":"6",
    "gn:asciiname":"La Arboleda (Miguel Reyes Gomez)",
    "gn:country_code":"MX",
    "gn:dem":1899,
    "gn:feature_class":"P",
    "gn:feature_code":"PPL",
    "gn:name":"La Arboleda (Miguel Reyes G\u00f3mez)",
    "gn:population":12,
    "gn:timezone":"America/Mexico_City",
    "iso:country":"MX",
    "name:und_x_variant":[
        "La Arboleda (Miguel Reyes G\u00f3mez)"
    ],
    "wof:name":"La Arboleda (Miguel Reyes Gomez)",
    "wof:placetype":"locality",
    "wof:population":12
},
  "geometry": {"coordinates":[-102.2775,22.12028],"type":"Point"}
}