{
  "type": "Feature",
  "properties": {
    "gn:admin1_code":"26",
    "gn:admin2_code":"30.0",
    "gn:asciiname":"El Molinito",
    "gn:country_code":"MX",
    "gn:dem":252,
    "gn:feature_class":"P",
    "gn:feature_code":"PPL",
    "gn:name":"El Molinito",
    "gn:population":6,
    "gn:timezone":"America/Hermosillo",
    "iso:country":"MX",
    "wof:name":"El Molinito",
    "wof:placetype":"locality",
    "wof:population":6
},
  "geometry": {"coordinates":[-110.89041,29.14867000000001],"type":"Point"}
}