{
  "type": "Feature",
  "properties": {
    "gn:admin1_code":"12.0",
    "gn:admin2_code":"21.0",
    "gn:asciiname":"La Colonia del Rio",
    "gn:country_code":"MX",
    "gn:dem":214,
    "gn:feature_class":"P",
    "gn:feature_code":"PPL",
    "gn:name":"La Colonia del R\u00edo",
    "gn:population":0,
    "gn:timezone":"America/Mexico_City",
    "iso:country":"MX",
    "name:spa_x_preferred":[
        "La Colonia del R\u00edo"
    ],
    "name:und_x_variant":[
        "La Colonia de R\u00edo"
    ],
    "wof:name":"La Colonia del Rio",
    "wof:placetype":"locality"
},
  "geometry": {"coordinates":[-100.15654000000001,17.18419],"type":"Point"}
}