{
  "type": "Feature",
  "properties": {
    "gn:admin1_code":"15",
    "gn:admin2_code":"56.0",
    "gn:asciiname":"Loma de Buenavista",
    "gn:country_code":"MX",
    "gn:dem":2729,
    "gn:feature_class":"P",
    "gn:feature_code":"PPL",
    "gn:name":"Loma de Buenavista",
    "gn:population":794,
    "gn:timezone":"America/Mexico_City",
    "iso:country":"MX",
    "wof:name":"Loma de Buenavista",
    "wof:placetype":"locality",
    "wof:population":794
},
  "geometry": {"coordinates":[-99.61278,19.63694],"type":"Point"}
}