{
  "type": "Feature",
  "properties": {
    "gn:admin1_code":"12",
    "gn:admin2_code":"55.0",
    "gn:asciiname":"Zapoapa",
    "gn:country_code":"MX",
    "gn:dem":1401,
    "gn:feature_class":"P",
    "gn:feature_code":"PPL",
    "gn:name":"Zapoapa",
    "gn:population":380,
    "gn:timezone":"America/Mexico_City",
    "iso:country":"MX",
    "wof:name":"Zapoapa",
    "wof:placetype":"locality",
    "wof:population":380
},
  "geometry": {"coordinates":[-99.66295,18.43568],"type":"Point"}
}