{
  "type": "Feature",
  "properties": {
    "gn:admin1_code":"30",
    "gn:admin2_code":"102",
    "gn:asciiname":"Los Tres Arbolitos",
    "gn:country_code":"MX",
    "gn:dem":91,
    "gn:feature_class":"P",
    "gn:feature_code":"PPL",
    "gn:name":"Los Tres Arbolitos",
    "gn:population":12,
    "gn:timezone":"America/Mexico_City",
    "iso:country":"MX",
    "wof:name":"Los Tres Arbolitos",
    "wof:placetype":"locality",
    "wof:population":12
},
  "geometry": {"coordinates":[-97.05472,20.10944],"type":"Point"}
}