{
  "type": "Feature",
  "properties": {
    "gn:admin1_code":"26.0",
    "gn:admin2_code":"11.0",
    "gn:asciiname":"El Cumaro",
    "gn:country_code":"MX",
    "gn:dem":1095,
    "gn:feature_class":"P",
    "gn:feature_code":"PPL",
    "gn:name":"El C\u00famaro",
    "gn:population":0,
    "gn:timezone":"America/Hermosillo",
    "iso:country":"MX",
    "name:spa_x_preferred":[
        "El C\u00famaro"
    ],
    "name:und_x_variant":[
        "C\u00famaio",
        "La Vinata"
    ],
    "wof:name":"El Cumaro",
    "wof:placetype":"locality"
},
  "geometry": {"coordinates":[-109.98335,30.69106],"type":"Point"}
}