{
  "type": "Feature",
  "properties": {
    "gn:admin1_code":"32.0",
    "gn:admin2_code":"46.0",
    "gn:asciiname":"Puerta del Llano",
    "gn:country_code":"MX",
    "gn:dem":1947,
    "gn:feature_class":"P",
    "gn:feature_code":"PPL",
    "gn:name":"Puerta del Llano",
    "gn:population":0,
    "gn:timezone":"America/Mexico_City",
    "iso:country":"MX",
    "name:spa_x_preferred":[
        "Puerta del Llano"
    ],
    "wof:name":"Puerta del Llano",
    "wof:placetype":"locality"
},
  "geometry": {"coordinates":[-103.05500000000001,22.45997],"type":"Point"}
}