{
  "type": "Feature",
  "properties": {
    "gn:admin1_code":"7",
    "gn:admin2_code":"10.0",
    "gn:asciiname":"Ejido El Fresnillo",
    "gn:country_code":"MX",
    "gn:dem":599,
    "gn:feature_class":"P",
    "gn:feature_code":"PPL",
    "gn:name":"Ejido El Fresnillo",
    "gn:population":0,
    "gn:timezone":"America/Monterrey",
    "iso:country":"MX",
    "name:spa_x_preferred":[
        "Ejido El Fresnillo"
    ],
    "name:und_x_variant":[
        "Fresnillo",
        "Rancho El Fresnillo"
    ],
    "wof:name":"Ejido El Fresnillo",
    "wof:placetype":"locality"
},
  "geometry": {"coordinates":[-101.50583,26.91494],"type":"Point"}
}