{
  "type": "Feature",
  "properties": {
    "gn:admin1_code":"6.0",
    "gn:admin2_code":"15.0",
    "gn:asciiname":"Cerro Chino",
    "gn:country_code":"MX",
    "gn:dem":1167,
    "gn:feature_class":"P",
    "gn:feature_code":"PPL",
    "gn:name":"Cerro Chino",
    "gn:population":0,
    "gn:timezone":"America/Chihuahua",
    "iso:country":"MX",
    "name:spa_x_preferred":[
        "Cerro Chino"
    ],
    "name:und_x_variant":[
        "Los Tajos"
    ],
    "wof:name":"Cerro Chino",
    "wof:placetype":"locality"
},
  "geometry": {"coordinates":[-105.023,29.63187000000001],"type":"Point"}
}