{
  "type": "Feature",
  "properties": {
    "gn:admin1_code":"6.0",
    "gn:admin2_code":"31.0",
    "gn:asciiname":"Corralitos",
    "gn:cc2":"MX",
    "gn:country_code":"MX",
    "gn:dem":2120,
    "gn:feature_class":"P",
    "gn:feature_code":"PPL",
    "gn:name":"Corralitos",
    "gn:population":3,
    "gn:timezone":"America/Chihuahua",
    "iso:country":"MX",
    "name:und_x_variant":[
        "Rancho Corralitos",
        "Corralillos",
        "Corralitos"
    ],
    "wof:name":"Corralitos",
    "wof:placetype":"locality",
    "wof:population":3
},
  "geometry": {"coordinates":[-107.58052000000001,28.51805],"type":"Point"}
}