{
  "type": "Feature",
  "properties": {
    "gn:admin1_code":"15",
    "gn:admin2_code":"50",
    "gn:asciiname":"Mario Sanchez R.",
    "gn:country_code":"MX",
    "gn:dem":2490,
    "gn:feature_class":"P",
    "gn:feature_code":"PPL",
    "gn:name":"Mario S\u00e1nchez R.",
    "gn:population":22,
    "gn:timezone":"America/Mexico_City",
    "iso:country":"MX",
    "name:und_x_variant":[
        "Mario S\u00e1nchez R."
    ],
    "wof:name":"Mario Sanchez R.",
    "wof:placetype":"locality",
    "wof:population":22
},
  "geometry": {"coordinates":[-98.83805,19.07514],"type":"Point"}
}