{
  "type": "Feature",
  "properties": {
    "gn:admin1_code":"5",
    "gn:admin2_code":"21.0",
    "gn:asciiname":"El Desengano",
    "gn:country_code":"MX",
    "gn:dem":669,
    "gn:feature_class":"P",
    "gn:feature_code":"PPL",
    "gn:name":"El Desenga\u00f1o",
    "gn:population":5,
    "gn:timezone":"America/Mexico_City",
    "iso:country":"MX",
    "name:und_x_variant":[
        "El Desenga\u00f1o"
    ],
    "wof:name":"El Desengano",
    "wof:placetype":"locality",
    "wof:population":5
},
  "geometry": {"coordinates":[-93.23944,17.09444],"type":"Point"}
}