{
  "type": "Feature",
  "properties": {
    "gn:admin1_code":"5.0",
    "gn:asciiname":"Argelia",
    "gn:country_code":"MX",
    "gn:dem":1390,
    "gn:feature_class":"P",
    "gn:feature_code":"PPL",
    "gn:name":"Argelia",
    "gn:population":0,
    "gn:timezone":"America/Mexico_City",
    "iso:country":"MX",
    "name:ceb_x_preferred":[
        "Argelia"
    ],
    "name:deu_x_preferred":[
        "Argelia"
    ],
    "name:fra_x_preferred":[
        "Argelia"
    ],
    "name:ita_x_preferred":[
        "Argelia"
    ],
    "name:nld_x_preferred":[
        "Argelia"
    ],
    "name:por_x_preferred":[
        "Arg\u00e9lia"
    ],
    "name:sco_x_preferred":[
        "Argelia"
    ],
    "name:spa_x_preferred":[
        "Argelia"
    ],
    "name:swe_x_preferred":[
        "Argelia"
    ],
    "name:vie_x_preferred":[
        "Argelia"
    ],
    "name:war_x_preferred":[
        "Argelia"
    ],
    "wof:name":"Argelia",
    "wof:placetype":"locality"
},
  "geometry": {"coordinates":[-92.5789,15.7475],"type":"Point"}
}