{
  "type": "Feature",
  "properties": {
    "gn:admin1_code":"27",
    "gn:admin2_code":"6.0",
    "gn:asciiname":"Monterrey",
    "gn:country_code":"MX",
    "gn:dem":18,
    "gn:feature_class":"P",
    "gn:feature_code":"PPL",
    "gn:name":"Monterrey",
    "gn:population":0,
    "gn:timezone":"America/Mexico_City",
    "iso:country":"MX",
    "name:spa_x_preferred":[
        "Monterrey"
    ],
    "wof:name":"Monterrey",
    "wof:placetype":"locality"
},
  "geometry": {"coordinates":[-93.28642000000001,18.17059],"type":"Point"}
}