{
  "type": "Feature",
  "properties": {
    "gn:admin1_code":"28.0",
    "gn:admin2_code":"3.0",
    "gn:asciiname":"Vicente Guerrero",
    "gn:country_code":"MX",
    "gn:dem":81,
    "gn:feature_class":"P",
    "gn:feature_code":"PPL",
    "gn:name":"Vicente Guerrero",
    "gn:population":32,
    "gn:timezone":"America/Monterrey",
    "iso:country":"MX",
    "name:spa_x_preferred":[
        "Vicente Guerrero"
    ],
    "wof:name":"Vicente Guerrero",
    "wof:placetype":"locality",
    "wof:population":32
},
  "geometry": {"coordinates":[-98.14694,22.71444],"type":"Point"}
}