{
  "type": "Feature",
  "properties": {
    "gn:admin1_code":"10",
    "gn:admin2_code":"10.0",
    "gn:asciiname":"Rancho Las Gueeras",
    "gn:country_code":"MX",
    "gn:dem":2010,
    "gn:feature_class":"P",
    "gn:feature_code":"PPL",
    "gn:name":"Rancho Las G\u00fceras",
    "gn:population":0,
    "gn:timezone":"America/Monterrey",
    "iso:country":"MX",
    "wof:name":"Rancho Las Gueeras",
    "wof:placetype":"locality"
},
  "geometry": {"coordinates":[-104.81667,25.73333],"type":"Point"}
}