{
  "type": "Feature",
  "properties": {
    "gn:admin1_code":"30",
    "gn:admin2_code":"45.0",
    "gn:asciiname":"Panaloya",
    "gn:country_code":"MX",
    "gn:dem":11,
    "gn:feature_class":"P",
    "gn:feature_code":"PPL",
    "gn:name":"Panaloya",
    "gn:population":0,
    "gn:timezone":"America/Mexico_City",
    "iso:country":"MX",
    "name:und_x_variant":[
        "Panololla"
    ],
    "wof:name":"Panaloya",
    "wof:placetype":"locality"
},
  "geometry": {"coordinates":[-95.99117,18.38856],"type":"Point"}
}