{
  "type": "Feature",
  "properties": {
    "gn:admin1_code":"11.0",
    "gn:admin2_code":"7.0",
    "gn:asciiname":"El Pozo de Morales",
    "gn:country_code":"MX",
    "gn:dem":1765,
    "gn:feature_class":"P",
    "gn:feature_code":"PPL",
    "gn:name":"El Pozo de Morales",
    "gn:population":0,
    "gn:timezone":"America/Mexico_City",
    "iso:country":"MX",
    "name:spa_x_preferred":[
        "El Pozo de Morales"
    ],
    "wof:name":"El Pozo de Morales",
    "wof:placetype":"locality"
},
  "geometry": {"coordinates":[-100.71953000000001,20.58004],"type":"Point"}
}