{
  "type": "Feature",
  "properties": {
    "gn:admin1_code":"23.0",
    "gn:asciiname":"X-Kalatzonot",
    "gn:country_code":"MX",
    "gn:dem":32,
    "gn:feature_class":"P",
    "gn:feature_code":"PPL",
    "gn:name":"X-Kalatzonot",
    "gn:population":0,
    "gn:timezone":"America/Cancun",
    "iso:country":"MX",
    "name:spa_x_preferred":[
        "X-Kalatzonot"
    ],
    "wof:name":"X-Kalatzonot",
    "wof:placetype":"locality"
},
  "geometry": {"coordinates":[-88.22570999999998,20.17723],"type":"Point"}
}