{
  "type": "Feature",
  "properties": {
    "gn:admin1_code":"6",
    "gn:admin2_code":"9.0",
    "gn:asciiname":"Gusarochi",
    "gn:country_code":"MX",
    "gn:dem":2207,
    "gn:feature_class":"P",
    "gn:feature_code":"PPL",
    "gn:name":"Gusarochi",
    "gn:population":7,
    "gn:timezone":"America/Chihuahua",
    "iso:country":"MX",
    "wof:name":"Gusarochi",
    "wof:placetype":"locality",
    "wof:population":7
},
  "geometry": {"coordinates":[-107.84771000000001,27.69519],"type":"Point"}
}