{
  "type": "Feature",
  "properties": {
    "gn:admin1_code":"7.0",
    "gn:admin2_code":"2.0",
    "gn:asciiname":"El Encino",
    "gn:country_code":"MX",
    "gn:dem":411,
    "gn:feature_class":"P",
    "gn:feature_code":"PPL",
    "gn:name":"El Encino",
    "gn:population":0,
    "gn:timezone":"America/Matamoros",
    "iso:country":"MX",
    "name:spa_x_preferred":[
        "El Encino"
    ],
    "wof:name":"El Encino",
    "wof:placetype":"locality"
},
  "geometry": {"coordinates":[-101.40107999999999,29.72423],"type":"Point"}
}