{
  "type": "Feature",
  "properties": {
    "gn:admin1_code":"13",
    "gn:admin2_code":"55.0",
    "gn:asciiname":"El Aguila",
    "gn:country_code":"MX",
    "gn:dem":2121,
    "gn:feature_class":"P",
    "gn:feature_code":"PPL",
    "gn:name":"El \u00c1guila",
    "gn:population":0,
    "gn:timezone":"America/Mexico_City",
    "iso:country":"MX",
    "name:fas_x_preferred":[
        "\u0627\u0644\u06af\u0648\u0626\u0644\u0627"
    ],
    "name:fra_x_preferred":[
        "El Aguila"
    ],
    "name:ita_x_preferred":[
        "Aguila"
    ],
    "name:spa_x_preferred":[
        "El \u00c1guila"
    ],
    "wof:name":"El Aguila",
    "wof:placetype":"locality"
},
  "geometry": {"coordinates":[-98.9845,20.44307],"type":"Point"}
}