{
  "type": "Feature",
  "properties": {
    "gn:admin1_code":"6",
    "gn:admin2_code":"29",
    "gn:asciiname":"El Chihuite",
    "gn:country_code":"MX",
    "gn:dem":2179,
    "gn:feature_class":"P",
    "gn:feature_code":"PPL",
    "gn:name":"El Chihuite",
    "gn:population":21,
    "gn:timezone":"America/Chihuahua",
    "iso:country":"MX",
    "wof:name":"El Chihuite",
    "wof:placetype":"locality",
    "wof:population":21
},
  "geometry": {"coordinates":[-106.99902,26.12968],"type":"Point"}
}