{
  "type": "Feature",
  "properties": {
    "gn:admin1_code":"20",
    "gn:admin2_code":"437",
    "gn:asciiname":"Salinas",
    "gn:country_code":"MX",
    "gn:dem":1848,
    "gn:feature_class":"P",
    "gn:feature_code":"PPL",
    "gn:name":"Salinas",
    "gn:population":36,
    "gn:timezone":"America/Mexico_City",
    "iso:country":"MX",
    "wof:name":"Salinas",
    "wof:placetype":"locality",
    "wof:population":36
},
  "geometry": {"coordinates":[-96.09472,17.07028],"type":"Point"}
}