{
  "type": "Feature",
  "properties": {
    "gn:admin1_code":"11",
    "gn:admin2_code":"43",
    "gn:asciiname":"Pena Blanca",
    "gn:country_code":"MX",
    "gn:dem":1651,
    "gn:feature_class":"P",
    "gn:feature_code":"PPL",
    "gn:name":"Pe\u00f1a Blanca",
    "gn:population":9,
    "gn:timezone":"America/Mexico_City",
    "iso:country":"MX",
    "name:und_x_variant":[
        "Pe\u00f1a Blanca"
    ],
    "wof:name":"Pena Blanca",
    "wof:placetype":"locality",
    "wof:population":9
},
  "geometry": {"coordinates":[-100.30194,21.36639],"type":"Point"}
}