{
  "type": "Feature",
  "properties": {
    "gn:admin1_code":"30",
    "gn:admin2_code":"9.0",
    "gn:asciiname":"Jacales",
    "gn:country_code":"MX",
    "gn:dem":1177,
    "gn:feature_class":"P",
    "gn:feature_code":"PPL",
    "gn:name":"Jacales",
    "gn:population":222,
    "gn:timezone":"America/Mexico_City",
    "iso:country":"MX",
    "wof:name":"Jacales",
    "wof:placetype":"locality",
    "wof:population":222
},
  "geometry": {"coordinates":[-96.6925,19.66139],"type":"Point"}
}