{
  "type": "Feature",
  "properties": {
    "gn:admin1_code":"5",
    "gn:admin2_code":"59",
    "gn:asciiname":"Candelaria",
    "gn:country_code":"MX",
    "gn:dem":648,
    "gn:feature_class":"P",
    "gn:feature_code":"PPL",
    "gn:name":"Candelaria",
    "gn:population":27,
    "gn:timezone":"America/Mexico_City",
    "iso:country":"MX",
    "wof:name":"Candelaria",
    "wof:placetype":"locality",
    "wof:population":27
},
  "geometry": {"coordinates":[-91.80194,16.94694],"type":"Point"}
}