{
  "type": "Feature",
  "properties": {
    "gn:admin1_code":"25",
    "gn:admin2_code":"10.0",
    "gn:asciiname":"Granja Desarrollo",
    "gn:country_code":"MX",
    "gn:dem":43,
    "gn:feature_class":"P",
    "gn:feature_code":"PPL",
    "gn:name":"Granja Desarrollo",
    "gn:population":6,
    "gn:timezone":"America/Mazatlan",
    "iso:country":"MX",
    "wof:name":"Granja Desarrollo",
    "wof:placetype":"locality",
    "wof:population":6
},
  "geometry": {"coordinates":[-108.72682,26.16333],"type":"Point"}
}