{
  "type": "Feature",
  "properties": {
    "gn:admin1_code":"32",
    "gn:admin2_code":"14.0",
    "gn:asciiname":"San Agustin El Viejo",
    "gn:country_code":"MX",
    "gn:dem":1779,
    "gn:feature_class":"P",
    "gn:feature_code":"PPL",
    "gn:name":"San Agustin El Viejo",
    "gn:population":0,
    "gn:timezone":"America/Mexico_City",
    "iso:country":"MX",
    "name:spa_x_preferred":[
        "San Agustin El Viejo"
    ],
    "name:und_x_variant":[
        "Rancho San Agust\u00edn El Viejo"
    ],
    "wof:name":"San Agustin El Viejo",
    "wof:placetype":"locality"
},
  "geometry": {"coordinates":[-102.89127000000001,24.05994],"type":"Point"}
}