{
  "type": "Feature",
  "properties": {
    "gn:admin1_code":"32.0",
    "gn:asciiname":"Las Charcas",
    "gn:country_code":"MX",
    "gn:dem":1785,
    "gn:feature_class":"P",
    "gn:feature_code":"PPL",
    "gn:name":"Las Charcas",
    "gn:population":0,
    "gn:timezone":"America/Mexico_City",
    "iso:country":"MX",
    "name:spa_x_preferred":[
        "Las Charcas"
    ],
    "wof:name":"Las Charcas",
    "wof:placetype":"locality"
},
  "geometry": {"coordinates":[-103.67337999999999,21.25745],"type":"Point"}
}