{
  "type": "Feature",
  "properties": {
    "gn:admin1_code":"19",
    "gn:admin2_code":"49.0",
    "gn:asciiname":"El Barranco",
    "gn:country_code":"MX",
    "gn:dem":1927,
    "gn:feature_class":"P",
    "gn:feature_code":"PPL",
    "gn:name":"El Barranco",
    "gn:population":7,
    "gn:timezone":"America/Monterrey",
    "iso:country":"MX",
    "name:spa_x_preferred":[
        "El Barranco"
    ],
    "wof:name":"El Barranco",
    "wof:placetype":"locality",
    "wof:population":7
},
  "geometry": {"coordinates":[-100.37196,25.35978],"type":"Point"}
}