{
  "type": "Feature",
  "properties": {
    "gn:admin1_code":"6",
    "gn:admin2_code":"45.0",
    "gn:asciiname":"Palo Blanco",
    "gn:country_code":"MX",
    "gn:dem":1140,
    "gn:feature_class":"P",
    "gn:feature_code":"PPL",
    "gn:name":"Palo Blanco",
    "gn:population":1,
    "gn:timezone":"America/Chihuahua",
    "iso:country":"MX",
    "wof:name":"Palo Blanco",
    "wof:placetype":"locality",
    "wof:population":1
},
  "geometry": {"coordinates":[-105.35713,28.30159],"type":"Point"}
}