{
  "type": "Feature",
  "properties": {
    "gn:admin1_code":"5",
    "gn:asciiname":"Quetzalcoatl Primera Seccion",
    "gn:country_code":"MX",
    "gn:dem":143,
    "gn:feature_class":"P",
    "gn:feature_code":"PPL",
    "gn:name":"Quetzalc\u00f3atl Primera Secci\u00f3n",
    "gn:population":0,
    "gn:timezone":"America/Mexico_City",
    "iso:country":"MX",
    "name:spa_x_preferred":[
        "Quetzalc\u00f3atl Primera Secci\u00f3n"
    ],
    "name:spa_x_variant":[
        "Quetzalcoatl"
    ],
    "wof:name":"Quetzalcoatl Primera Seccion",
    "wof:placetype":"locality"
},
  "geometry": {"coordinates":[-90.45525000000001,16.14889],"type":"Point"}
}