{
  "type": "Feature",
  "properties": {
    "gn:admin1_code":"20",
    "gn:admin2_code":"57.0",
    "gn:asciiname":"Lazaro Cardenas",
    "gn:country_code":"MX",
    "gn:dem":213,
    "gn:feature_class":"P",
    "gn:feature_code":"PPL",
    "gn:name":"L\u00e1zaro C\u00e1rdenas",
    "gn:population":0,
    "gn:timezone":"America/Mexico_City",
    "iso:country":"MX",
    "name:spa_x_preferred":[
        "L\u00e1zaro C\u00e1rdenas"
    ],
    "wof:name":"Lazaro Cardenas",
    "wof:placetype":"locality"
},
  "geometry": {"coordinates":[-95.14525999999999,17.20016],"type":"Point"}
}