{
  "type": "Feature",
  "properties": {
    "gn:admin1_code":"25",
    "gn:admin2_code":"13.0",
    "gn:asciiname":"Ranchito de los Gaxiola",
    "gn:country_code":"MX",
    "gn:dem":81,
    "gn:feature_class":"P",
    "gn:feature_code":"PPL",
    "gn:name":"Ranchito de los Gaxiola",
    "gn:population":117,
    "gn:timezone":"America/Mazatlan",
    "iso:country":"MX",
    "wof:name":"Ranchito de los Gaxiola",
    "wof:placetype":"locality",
    "wof:population":117
},
  "geometry": {"coordinates":[-107.94138999999998,25.49611],"type":"Point"}
}