{
  "type": "Feature",
  "properties": {
    "gn:admin1_code":"6.0",
    "gn:admin2_code":"16.0",
    "gn:asciiname":"Arroyo Hondo",
    "gn:country_code":"MX",
    "gn:dem":1208,
    "gn:feature_class":"P",
    "gn:feature_code":"PPL",
    "gn:name":"Arroyo Hondo",
    "gn:population":0,
    "gn:timezone":"America/Chihuahua",
    "iso:country":"MX",
    "name:ceb_x_preferred":[
        "Arroyo Hondo"
    ],
    "name:spa_x_preferred":[
        "Arroyo Hondo"
    ],
    "name:swe_x_preferred":[
        "Arroyo Hondo"
    ],
    "wof:name":"Arroyo Hondo",
    "wof:placetype":"locality"
},
  "geometry": {"coordinates":[-105.16656,27.82133],"type":"Point"}
}