{
  "type": "Feature",
  "properties": {
    "gn:admin1_code":"2",
    "gn:admin2_code":"4.0",
    "gn:asciiname":"Pilitas",
    "gn:country_code":"MX",
    "gn:dem":394,
    "gn:feature_class":"P",
    "gn:feature_code":"PPL",
    "gn:name":"Pilitas",
    "gn:population":0,
    "gn:timezone":"America/Tijuana",
    "iso:country":"MX",
    "wof:name":"Pilitas",
    "wof:placetype":"locality"
},
  "geometry": {"coordinates":[-116.68333,32.35],"type":"Point"}
}