{
  "type": "Feature",
  "properties": {
    "gn:admin1_code":"14.0",
    "gn:asciiname":"Rosa de Castilla",
    "gn:country_code":"MX",
    "gn:dem":2207,
    "gn:feature_class":"P",
    "gn:feature_code":"PPL",
    "gn:name":"Rosa de Castilla",
    "gn:population":0,
    "gn:timezone":"America/Mexico_City",
    "iso:country":"MX",
    "name:spa_x_preferred":[
        "Rosa de Castilla"
    ],
    "wof:name":"Rosa de Castilla",
    "wof:placetype":"locality"
},
  "geometry": {"coordinates":[-102.30816,20.90585],"type":"Point"}
}