{
  "type": "Feature",
  "properties": {
    "gn:admin1_code":"16",
    "gn:admin2_code":"81.0",
    "gn:asciiname":"La Loma (Los Hoyos)",
    "gn:country_code":"MX",
    "gn:dem":1656,
    "gn:feature_class":"P",
    "gn:feature_code":"PPL",
    "gn:name":"La Loma (Los Hoyos)",
    "gn:population":172,
    "gn:timezone":"America/Mexico_City",
    "iso:country":"MX",
    "wof:name":"La Loma (Los Hoyos)",
    "wof:placetype":"locality",
    "wof:population":172
},
  "geometry": {"coordinates":[-100.37194,19.23417],"type":"Point"}
}