{
  "type": "Feature",
  "properties": {
    "gn:admin1_code":"10",
    "gn:admin2_code":"34",
    "gn:asciiname":"Las Mesitas",
    "gn:country_code":"MX",
    "gn:dem":2144,
    "gn:feature_class":"P",
    "gn:feature_code":"PPL",
    "gn:name":"Las Mesitas",
    "gn:population":17,
    "gn:timezone":"America/Monterrey",
    "iso:country":"MX",
    "wof:name":"Las Mesitas",
    "wof:placetype":"locality",
    "wof:population":17
},
  "geometry": {"coordinates":[-106.88816,25.43858],"type":"Point"}
}