{
  "type": "Feature",
  "properties": {
    "gn:admin1_code":"12",
    "gn:admin2_code":"73.0",
    "gn:asciiname":"Ciricicuaro",
    "gn:country_code":"MX",
    "gn:dem":174,
    "gn:feature_class":"P",
    "gn:feature_code":"PPL",
    "gn:name":"Ciric\u00edcuaro",
    "gn:population":0,
    "gn:timezone":"America/Mexico_City",
    "iso:country":"MX",
    "name:spa_x_preferred":[
        "Ciric\u00edcuaro"
    ],
    "name:und_x_variant":[
        "Ziritz\u00edcuaro"
    ],
    "wof:name":"Ciricicuaro",
    "wof:placetype":"locality"
},
  "geometry": {"coordinates":[-101.41459999999999,18.49129],"type":"Point"}
}