{
  "type": "Feature",
  "properties": {
    "gn:admin1_code":"16",
    "gn:admin2_code":"59.0",
    "gn:asciiname":"Las Trojas (Las Trojes)",
    "gn:country_code":"MX",
    "gn:dem":1161,
    "gn:feature_class":"P",
    "gn:feature_code":"PPL",
    "gn:name":"Las Trojas (Las Trojes)",
    "gn:population":136,
    "gn:timezone":"America/Mexico_City",
    "iso:country":"MX",
    "wof:name":"Las Trojas (Las Trojes)",
    "wof:placetype":"locality",
    "wof:population":136
},
  "geometry": {"coordinates":[-101.82722,19.09556],"type":"Point"}
}