{
  "type": "Feature",
  "properties": {
    "gn:admin1_code":"28.0",
    "gn:admin2_code":"19.0",
    "gn:asciiname":"Los Marranos",
    "gn:country_code":"MX",
    "gn:dem":219,
    "gn:feature_class":"P",
    "gn:feature_code":"PPL",
    "gn:name":"Los Marranos",
    "gn:population":0,
    "gn:timezone":"America/Monterrey",
    "iso:country":"MX",
    "name:spa_x_preferred":[
        "Los Marranos"
    ],
    "wof:name":"Los Marranos",
    "wof:placetype":"locality"
},
  "geometry": {"coordinates":[-98.96402999999999,23.17083],"type":"Point"}
}