{
  "type": "Feature",
  "properties": {
    "gn:admin1_code":"10",
    "gn:admin2_code":"14.0",
    "gn:asciiname":"Rodeo",
    "gn:country_code":"MX",
    "gn:dem":1811,
    "gn:feature_class":"P",
    "gn:feature_code":"PPL",
    "gn:name":"Rodeo",
    "gn:population":0,
    "gn:timezone":"America/Monterrey",
    "iso:country":"MX",
    "name:spa_x_preferred":[
        "Rodeo"
    ],
    "wof:name":"Rodeo",
    "wof:placetype":"locality"
},
  "geometry": {"coordinates":[-104.72152,22.84062],"type":"Point"}
}