{
  "type": "Feature",
  "properties": {
    "gn:admin1_code":"14",
    "gn:admin2_code":"97",
    "gn:asciiname":"Potrero los Amadores",
    "gn:country_code":"MX",
    "gn:dem":1563,
    "gn:feature_class":"P",
    "gn:feature_code":"PPL",
    "gn:name":"Potrero los Amadores",
    "gn:population":36,
    "gn:timezone":"America/Mexico_City",
    "iso:country":"MX",
    "wof:name":"Potrero los Amadores",
    "wof:placetype":"locality",
    "wof:population":36
},
  "geometry": {"coordinates":[-103.42139,20.54833],"type":"Point"}
}