{
  "type": "Feature",
  "properties": {
    "gn:admin1_code":"6",
    "gn:admin2_code":"66.0",
    "gn:asciiname":"La Estacion",
    "gn:cc2":"MX",
    "gn:country_code":"MX",
    "gn:dem":1900,
    "gn:feature_class":"P",
    "gn:feature_code":"PPL",
    "gn:name":"La Estaci\u00f3n",
    "gn:population":23,
    "gn:timezone":"America/Chihuahua",
    "iso:country":"MX",
    "name:und_x_variant":[
        "Rancho Tentaci\u00f3n",
        "Tentaci\u00f3n"
    ],
    "wof:name":"La Estacion",
    "wof:placetype":"locality",
    "wof:population":23
},
  "geometry": {"coordinates":[-108.27355,27.7613],"type":"Point"}
}