{
  "type": "Feature",
  "properties": {
    "gn:admin1_code":"14.0",
    "gn:admin2_code":"28.0",
    "gn:asciiname":"Chilacayote",
    "gn:country_code":"MX",
    "gn:dem":2158,
    "gn:feature_class":"P",
    "gn:feature_code":"PPL",
    "gn:name":"Chilacayote",
    "gn:population":306,
    "gn:timezone":"America/Mexico_City",
    "iso:country":"MX",
    "wof:name":"Chilacayote",
    "wof:placetype":"locality",
    "wof:population":306
},
  "geometry": {"coordinates":[-104.64861000000001,20.13861],"type":"Point"}
}