{
  "type": "Feature",
  "properties": {
    "gn:admin1_code":"21.0",
    "gn:admin2_code":"119.0",
    "gn:asciiname":"San Jose Buenavista",
    "gn:country_code":"MX",
    "gn:dem":2118,
    "gn:feature_class":"P",
    "gn:feature_code":"PPL",
    "gn:name":"San Jos\u00e9 Buenavista",
    "gn:population":0,
    "gn:timezone":"America/Mexico_City",
    "iso:country":"MX",
    "name:spa_x_preferred":[
        "San Jos\u00e9 Buenavista"
    ],
    "name:spa_x_variant":[
        "Buena Vista"
    ],
    "wof:name":"San Jose Buenavista",
    "wof:placetype":"locality"
},
  "geometry": {"coordinates":[-98.26325,19.00431],"type":"Point"}
}