{
  "type": "Feature",
  "properties": {
    "gn:admin1_code":"29",
    "gn:admin2_code":"34.0",
    "gn:asciiname":"Ejido Jose Maria Morelos Buenavista",
    "gn:country_code":"MX",
    "gn:dem":2592,
    "gn:feature_class":"P",
    "gn:feature_code":"PPL",
    "gn:name":"Ejido Jos\u00e9 Mar\u00eda Morelos Buenavista",
    "gn:population":5,
    "gn:timezone":"America/Mexico_City",
    "iso:country":"MX",
    "wof:name":"Ejido Jose Maria Morelos Buenavista",
    "wof:placetype":"locality",
    "wof:population":5
},
  "geometry": {"coordinates":[-98.26519999999999,19.57522],"type":"Point"}
}