{
  "type": "Feature",
  "properties": {
    "gn:admin1_code":"30",
    "gn:admin2_code":"131.0",
    "gn:asciiname":"Tres Flechas",
    "gn:country_code":"MX",
    "gn:dem":172,
    "gn:feature_class":"P",
    "gn:feature_code":"PPL",
    "gn:name":"Tres Flechas",
    "gn:population":107,
    "gn:timezone":"America/Mexico_City",
    "iso:country":"MX",
    "wof:name":"Tres Flechas",
    "wof:placetype":"locality",
    "wof:population":107
},
  "geometry": {"coordinates":[-97.41167,20.49278],"type":"Point"}
}