{
  "type": "Feature",
  "properties": {
    "gn:admin1_code":"6",
    "gn:admin2_code":"41.0",
    "gn:asciiname":"Rojabo",
    "gn:country_code":"MX",
    "gn:dem":1932,
    "gn:feature_class":"P",
    "gn:feature_code":"PPL",
    "gn:name":"Rojab\u00f3",
    "gn:population":0,
    "gn:timezone":"America/Chihuahua",
    "iso:country":"MX",
    "name:spa_x_preferred":[
        "Rojab\u00f3"
    ],
    "wof:name":"Rojabo",
    "wof:placetype":"locality"
},
  "geometry": {"coordinates":[-107.96250999999999,27.69406],"type":"Point"}
}