{
  "type": "Feature",
  "properties": {
    "gn:admin1_code":"10",
    "gn:admin2_code":"9.0",
    "gn:asciiname":"La Pitarrilla",
    "gn:country_code":"MX",
    "gn:dem":2267,
    "gn:feature_class":"P",
    "gn:feature_code":"PPL",
    "gn:name":"La Pitarrilla",
    "gn:population":9,
    "gn:timezone":"America/Monterrey",
    "iso:country":"MX",
    "wof:name":"La Pitarrilla",
    "wof:placetype":"locality",
    "wof:population":9
},
  "geometry": {"coordinates":[-105.97955,25.75636],"type":"Point"}
}