{
  "type": "Feature",
  "properties": {
    "gn:admin1_code":"31",
    "gn:admin2_code":"36.0",
    "gn:asciiname":"San Isidro Ochil",
    "gn:country_code":"MX",
    "gn:dem":19,
    "gn:feature_class":"P",
    "gn:feature_code":"PPL",
    "gn:name":"San Isidro Ochil",
    "gn:population":0,
    "gn:timezone":"America/Merida",
    "iso:country":"MX",
    "name:und_x_variant":[
        "Ochil"
    ],
    "wof:name":"San Isidro Ochil",
    "wof:placetype":"locality"
},
  "geometry": {"coordinates":[-89.34249,20.63678],"type":"Point"}
}