{
  "type": "Feature",
  "properties": {
    "gn:admin1_code":"30",
    "gn:admin2_code":"143",
    "gn:asciiname":"Guasimal",
    "gn:country_code":"MX",
    "gn:dem":18,
    "gn:feature_class":"P",
    "gn:feature_code":"PPL",
    "gn:name":"Guasimal",
    "gn:population":31,
    "gn:timezone":"America/Mexico_City",
    "iso:country":"MX",
    "name:ceb_x_preferred":[
        "Guasimal"
    ],
    "name:deu_x_preferred":[
        "Guasimal"
    ],
    "name:hat_x_preferred":[
        "Guasimal"
    ],
    "name:nld_x_preferred":[
        "Guasimal"
    ],
    "wof:name":"Guasimal",
    "wof:placetype":"locality",
    "wof:population":31
},
  "geometry": {"coordinates":[-95.47111,18.26306],"type":"Point"}
}