{
  "type": "Feature",
  "properties": {
    "gn:admin1_code":"5.0",
    "gn:asciiname":"Nuevo Poblado Naranja Seca",
    "gn:country_code":"MX",
    "gn:dem":2101,
    "gn:feature_class":"P",
    "gn:feature_code":"PPL",
    "gn:name":"Nuevo Poblado Naranja Seca",
    "gn:population":0,
    "gn:timezone":"America/Mexico_City",
    "iso:country":"MX",
    "name:spa_x_preferred":[
        "Nuevo Poblado Naranja Seca"
    ],
    "wof:name":"Nuevo Poblado Naranja Seca",
    "wof:placetype":"locality"
},
  "geometry": {"coordinates":[-92.4003,16.81077],"type":"Point"}
}