{
  "type": "Feature",
  "properties": {
    "gn:country":"MX",
    "gn:fcode":"PPL",
    "gn:population":8959,
    "iso:country":"MX",
    "name:und_x_variant":[
        "Queser\u00eda"
    ],
    "qs_pg:aaroncc":"MX",
    "qs_pg:gn_country":"MX",
    "qs_pg:gn_fcode":"PPL",
    "qs_pg:gn_pop":8959,
    "qs_pg:name":"La Queser\u00eda",
    "qs_pg:name_adm0":"M\u00e9xico",
    "qs_pg:name_adm1":"Colima",
    "qs_pg:photos_9k":1,
    "qs_pg:photos_9r":1,
    "qs_pg:photos_all":3,
    "qs_pg:photos_sr":0,
    "qs_pg:pop_sr":5,
    "qs_pg:qs_pg_placetype":"locality",
    "qs_pg:qs_pg_placetype_gp":"Town",
    "qs_pg:woe_adm0":23424900,
    "woe:adm0_id":23424900,
    "woe:name_adm0":"M\u00e9xico",
    "woe:name_adm1":"Colima",
    "woe:placetype":"Town",
    "wof:name":"La Queser\u00eda",
    "wof:placetype":"locality",
    "wof:population":8959
},
  "geometry": {"coordinates":[-103.57243,19.38609],"type":"Point"}
}