{
  "type": "Feature",
  "properties": {
    "gn:admin1_code":"32.0",
    "gn:admin2_code":"6.0",
    "gn:asciiname":"Boquilla de Abajo",
    "gn:country_code":"MX",
    "gn:dem":2118,
    "gn:feature_class":"P",
    "gn:feature_code":"PPL",
    "gn:name":"Boquilla de Abajo",
    "gn:population":0,
    "gn:timezone":"America/Mexico_City",
    "iso:country":"MX",
    "name:spa_x_preferred":[
        "Boquilla de Abajo"
    ],
    "wof:name":"Boquilla de Abajo",
    "wof:placetype":"locality"
},
  "geometry": {"coordinates":[-102.86396000000001,23.55488],"type":"Point"}
}