{
  "type": "Feature",
  "properties": {
    "gn:admin1_code":"28",
    "gn:admin2_code":"8.0",
    "gn:asciiname":"Santa Maria de los Nogales",
    "gn:country_code":"MX",
    "gn:dem":914,
    "gn:feature_class":"P",
    "gn:feature_code":"PPL",
    "gn:name":"Santa Mar\u00eda de los Nogales",
    "gn:population":0,
    "gn:timezone":"America/Monterrey",
    "iso:country":"MX",
    "name:und_x_variant":[
        "Santa Mar\u00eda del Nogalar",
        "Santa Maria",
        "Santa Mar\u00eda de los Nogales"
    ],
    "wof:name":"Santa Maria de los Nogales",
    "wof:placetype":"locality"
},
  "geometry": {"coordinates":[-98.35924,23.20945],"type":"Point"}
}