{
  "type": "Feature",
  "properties": {
    "gn:admin1_code":"13",
    "gn:admin2_code":"62.0",
    "gn:asciiname":"Almolo",
    "gn:country_code":"MX",
    "gn:dem":541,
    "gn:feature_class":"P",
    "gn:feature_code":"PPL",
    "gn:name":"Almolo",
    "gn:population":0,
    "gn:timezone":"America/Mexico_City",
    "iso:country":"MX",
    "name:und_x_variant":[
        "San Isidro"
    ],
    "wof:name":"Almolo",
    "wof:placetype":"locality"
},
  "geometry": {"coordinates":[-98.86548000000001,21.06671],"type":"Point"}
}