{
  "type": "Feature",
  "properties": {
    "gn:admin1_code":"10",
    "gn:admin2_code":"32.0",
    "gn:asciiname":"La Canada de San Miguel",
    "gn:country_code":"MX",
    "gn:dem":2492,
    "gn:feature_class":"P",
    "gn:feature_code":"PPL",
    "gn:name":"La Ca\u00f1ada de San Miguel",
    "gn:population":60,
    "gn:timezone":"America/Monterrey",
    "iso:country":"MX",
    "name:und_x_variant":[
        "La Ca\u00f1ada de San Miguel"
    ],
    "wof:name":"La Canada de San Miguel",
    "wof:placetype":"locality",
    "wof:population":60
},
  "geometry": {"coordinates":[-106.12147,25.07887],"type":"Point"}
}