{
  "type": "Feature",
  "properties": {
    "gn:admin1_code":"21",
    "gn:admin2_code":"45.0",
    "gn:asciiname":"San Pedro Temamatla",
    "gn:country_code":"MX",
    "gn:dem":2419,
    "gn:feature_class":"P",
    "gn:feature_code":"PPL",
    "gn:name":"San Pedro Temamatla",
    "gn:population":1252,
    "gn:timezone":"America/Mexico_City",
    "iso:country":"MX",
    "name:spa_x_preferred":[
        "San Pedro Temamatla"
    ],
    "wof:name":"San Pedro Temamatla",
    "wof:placetype":"locality",
    "wof:population":1252
},
  "geometry": {"coordinates":[-97.51197999999999,18.92553],"type":"Point"}
}