{
  "type": "Feature",
  "properties": {
    "gn:admin1_code":"6",
    "gn:admin2_code":"20",
    "gn:asciiname":"Pinos Altos",
    "gn:country_code":"MX",
    "gn:dem":1106,
    "gn:feature_class":"P",
    "gn:feature_code":"PPL",
    "gn:name":"Pinos Altos",
    "gn:population":25,
    "gn:timezone":"America/Chihuahua",
    "iso:country":"MX",
    "wof:name":"Pinos Altos",
    "wof:placetype":"locality",
    "wof:population":25
},
  "geometry": {"coordinates":[-108.33799,27.61825],"type":"Point"}
}