{
  "type": "Feature",
  "properties": {
    "gn:admin1_code":"6",
    "gn:admin2_code":"65",
    "gn:asciiname":"Puerto los Pillados",
    "gn:country_code":"MX",
    "gn:dem":1175,
    "gn:feature_class":"P",
    "gn:feature_code":"PPL",
    "gn:name":"Puerto los Pillados",
    "gn:population":10,
    "gn:timezone":"America/Chihuahua",
    "iso:country":"MX",
    "wof:name":"Puerto los Pillados",
    "wof:placetype":"locality",
    "wof:population":10
},
  "geometry": {"coordinates":[-108.18519000000001,27.02632],"type":"Point"}
}