{
  "type": "Feature",
  "properties": {
    "gn:admin1_code":"24",
    "gn:admin2_code":"34.0",
    "gn:asciiname":"El Sasub",
    "gn:country_code":"MX",
    "gn:dem":42,
    "gn:feature_class":"P",
    "gn:feature_code":"PPL",
    "gn:name":"El Sasub",
    "gn:population":530,
    "gn:timezone":"America/Mexico_City",
    "iso:country":"MX",
    "name:und_x_variant":[
        "Sasub",
        "Sasu",
        "Sasua",
        "El Sasub"
    ],
    "wof:name":"El Sasub",
    "wof:placetype":"locality",
    "wof:population":530
},
  "geometry": {"coordinates":[-98.53945,21.73984],"type":"Point"}
}