{
  "type": "Feature",
  "properties": {
    "gn:admin1_code":"6.0",
    "gn:admin2_code":"22.0",
    "gn:asciiname":"Fernando de Arriba",
    "gn:country_code":"MX",
    "gn:dem":1727,
    "gn:feature_class":"P",
    "gn:feature_code":"PPL",
    "gn:name":"Fernando de Arriba",
    "gn:population":0,
    "gn:timezone":"America/Chihuahua",
    "iso:country":"MX",
    "name:und_x_variant":[
        "San Fernando Arriba",
        "San Fernando de Arriba",
        "Fernando de Arriba"
    ],
    "wof:name":"Fernando de Arriba",
    "wof:placetype":"locality"
},
  "geometry": {"coordinates":[-106.49784,28.01866],"type":"Point"}
}