{
  "type": "Feature",
  "properties": {
    "gn:admin1_code":"10",
    "gn:admin2_code":"4.0",
    "gn:asciiname":"Galeno",
    "gn:country_code":"MX",
    "gn:dem":2018,
    "gn:feature_class":"P",
    "gn:feature_code":"PPL",
    "gn:name":"Galeno",
    "gn:population":0,
    "gn:timezone":"America/Monterrey",
    "iso:country":"MX",
    "name:ita_x_preferred":[
        "Galeno"
    ],
    "name:spa_x_preferred":[
        "Galeno"
    ],
    "name:tgk_x_preferred":[
        "\u0413\u0430\u043b\u0435\u043d\u043e"
    ],
    "name:vie_x_preferred":[
        "Galeno"
    ],
    "wof:name":"Galeno",
    "wof:placetype":"locality"
},
  "geometry": {"coordinates":[-103.62163,24.70694],"type":"Point"}
}