{
  "type": "Feature",
  "properties": {
    "gn:admin1_code":"6",
    "gn:admin2_code":"29.0",
    "gn:asciiname":"Mesa de la Tableta",
    "gn:country_code":"MX",
    "gn:dem":2026,
    "gn:feature_class":"P",
    "gn:feature_code":"PPL",
    "gn:name":"Mesa de la Tableta",
    "gn:population":0,
    "gn:timezone":"America/Chihuahua",
    "iso:country":"MX",
    "name:spa_x_preferred":[
        "Mesa de la Tableta"
    ],
    "wof:name":"Mesa de la Tableta",
    "wof:placetype":"locality"
},
  "geometry": {"coordinates":[-107.55449,26.37731],"type":"Point"}
}