{
  "type": "Feature",
  "properties": {
    "gn:admin1_code":"5",
    "gn:admin2_code":"46",
    "gn:asciiname":"Los Vera",
    "gn:country_code":"MX",
    "gn:dem":703,
    "gn:feature_class":"P",
    "gn:feature_code":"PPL",
    "gn:name":"Los Vera",
    "gn:population":19,
    "gn:timezone":"America/Mexico_City",
    "iso:country":"MX",
    "wof:name":"Los Vera",
    "wof:placetype":"locality",
    "wof:population":19
},
  "geometry": {"coordinates":[-93.62306,16.76444],"type":"Point"}
}