{
  "type": "Feature",
  "properties": {
    "gn:admin1_code":"14",
    "gn:admin2_code":"86",
    "gn:asciiname":"Tapalpa [Country Club]",
    "gn:country_code":"MX",
    "gn:dem":2025,
    "gn:feature_class":"P",
    "gn:feature_code":"PPL",
    "gn:name":"Tapalpa [Country Club]",
    "gn:population":41,
    "gn:timezone":"America/Mexico_City",
    "iso:country":"MX",
    "wof:name":"Tapalpa [Country Club]",
    "wof:placetype":"locality",
    "wof:population":41
},
  "geometry": {"coordinates":[-103.80083,19.91389],"type":"Point"}
}