{
  "type": "Feature",
  "properties": {
    "gn:admin1_code":"25",
    "gn:admin2_code":"3.0",
    "gn:asciiname":"Surutato",
    "gn:country_code":"MX",
    "gn:dem":1446,
    "gn:feature_class":"P",
    "gn:feature_code":"PPL",
    "gn:name":"Surutato",
    "gn:population":0,
    "gn:timezone":"America/Mazatlan",
    "iso:country":"MX",
    "name:spa_x_preferred":[
        "Surutato"
    ],
    "wof:name":"Surutato",
    "wof:placetype":"locality"
},
  "geometry": {"coordinates":[-107.56055000000001,25.80618],"type":"Point"}
}