{
  "type": "Feature",
  "properties": {
    "gn:admin1_code":"3",
    "gn:admin2_code":"3",
    "gn:asciiname":"La Posta",
    "gn:country_code":"MX",
    "gn:dem":327,
    "gn:feature_class":"P",
    "gn:feature_code":"PPL",
    "gn:name":"La Posta",
    "gn:population":13,
    "gn:timezone":"America/Mazatlan",
    "iso:country":"MX",
    "wof:name":"La Posta",
    "wof:placetype":"locality",
    "wof:population":13
},
  "geometry": {"coordinates":[-110.0461,23.83492],"type":"Point"}
}