{
  "type": "Feature",
  "properties": {
    "iso:country":"MX",
    "name:spa_x_preferred":[
        "Tehuacan Centro"
    ],
    "qs:gn_adm0_cc":"MX",
    "qs:gn_local":3516109,
    "qs:gn_nam_loc":"Tehuacan, Tehuac\u00e1n, Puebla, MX",
    "qs:gn_namadm1":"21",
    "qs:local_max":234,
    "qs:local_sum":234,
    "qs:localhoods":1,
    "qs:name":"Tehuacan Centro",
    "qs:name_adm0":"M\u00e9xico",
    "qs:name_adm1":"Puebla",
    "qs:name_adm2":"Tehuacan",
    "qs:name_local":"Tehuac\u00e1n",
    "qs:photo_max":183,
    "qs:photo_sum":234,
    "qs:placetype":"Suburb",
    "qs:quad_count":5,
    "qs:woe_adm0":23424900,
    "qs:woe_adm1":2346284,
    "qs:woe_adm2":12601382,
    "qs:woe_lau":0,
    "qs:woe_local":148574,
    "qs:woe_ver":"7.10.0",
    "wof:lang":[
        "spa"
    ],
    "wof:name":"Tehuacan Centro",
    "wof:placetype":"neighbourhood"
},
  "geometry": {"coordinates":[-97.39286,18.462965],"type":"Point"}
}