{
  "type": "Feature",
  "properties": {
    "gn:admin1_code":"14",
    "gn:admin2_code":"124.0",
    "gn:asciiname":"El Durazno",
    "gn:country_code":"MX",
    "gn:dem":1847,
    "gn:feature_class":"P",
    "gn:feature_code":"PPL",
    "gn:name":"El Durazno",
    "gn:population":88,
    "gn:timezone":"America/Mexico_City",
    "iso:country":"MX",
    "name:ceb_x_preferred":[
        "El Durazno"
    ],
    "name:swe_x_preferred":[
        "El Durazno"
    ],
    "wof:name":"El Durazno",
    "wof:placetype":"locality",
    "wof:population":88
},
  "geometry": {"coordinates":[-103.00139,20.58833],"type":"Point"}
}