{
  "type": "Feature",
  "properties": {
    "gn:admin1_code":"14.0",
    "gn:admin2_code":"94.0",
    "gn:asciiname":"San Antonio del Potrero",
    "gn:country_code":"MX",
    "gn:dem":888,
    "gn:feature_class":"P",
    "gn:feature_code":"PPL",
    "gn:name":"San Antonio del Potrero",
    "gn:population":0,
    "gn:timezone":"America/Mexico_City",
    "iso:country":"MX",
    "name:spa_x_preferred":[
        "San Antonio del Potrero"
    ],
    "name:spa_x_variant":[
        "Potrero de San Antonio"
    ],
    "wof:name":"San Antonio del Potrero",
    "wof:placetype":"locality"
},
  "geometry": {"coordinates":[-103.80540999999999,20.90921],"type":"Point"}
}