{
  "type": "Feature",
  "properties": {
    "gn:admin1_code":"30",
    "gn:admin2_code":"61.0",
    "gn:asciiname":"Felipe Angeles",
    "gn:country_code":"MX",
    "gn:dem":217,
    "gn:feature_class":"P",
    "gn:feature_code":"PPL",
    "gn:name":"Felipe \u00c1ngeles",
    "gn:population":837,
    "gn:timezone":"America/Mexico_City",
    "iso:country":"MX",
    "name:und_x_variant":[
        "Felipe \u00c1ngeles"
    ],
    "wof:name":"Felipe Angeles",
    "wof:placetype":"locality",
    "wof:population":837
},
  "geometry": {"coordinates":[-93.83917,17.31028],"type":"Point"}
}