{
  "type": "Feature",
  "properties": {
    "gn:admin1_code":"30",
    "gn:admin2_code":"23.0",
    "gn:asciiname":"San Pedro Altepepan",
    "gn:country_code":"MX",
    "gn:dem":757,
    "gn:feature_class":"P",
    "gn:feature_code":"PPL",
    "gn:name":"San Pedro Altepepan",
    "gn:population":327,
    "gn:timezone":"America/Mexico_City",
    "iso:country":"MX",
    "wof:name":"San Pedro Altepepan",
    "wof:placetype":"locality",
    "wof:population":327
},
  "geometry": {"coordinates":[-97.03785000000001,19.89596],"type":"Point"}
}