{
  "type": "Feature",
  "properties": {
    "gn:admin1_code":"30.0",
    "gn:admin2_code":"109.0",
    "gn:asciiname":"Poza del Tigre",
    "gn:country_code":"MX",
    "gn:dem":80,
    "gn:feature_class":"P",
    "gn:feature_code":"PPL",
    "gn:name":"Poza del Tigre",
    "gn:population":151,
    "gn:timezone":"America/Mexico_City",
    "iso:country":"MX",
    "name:spa_x_preferred":[
        "Poza del Tigre"
    ],
    "name:spa_x_variant":[
        "Rancho Alegre"
    ],
    "wof:name":"Poza del Tigre",
    "wof:placetype":"locality",
    "wof:population":151
},
  "geometry": {"coordinates":[-96.89749999999999,20.04861],"type":"Point"}
}