{
  "type": "Feature",
  "properties": {
    "gn:admin1_code":"16",
    "gn:admin2_code":"53.0",
    "gn:asciiname":"La Maiza",
    "gn:country_code":"MX",
    "gn:dem":2163,
    "gn:feature_class":"P",
    "gn:feature_code":"PPL",
    "gn:name":"La Maiza",
    "gn:population":214,
    "gn:timezone":"America/Mexico_City",
    "iso:country":"MX",
    "wof:name":"La Maiza",
    "wof:placetype":"locality",
    "wof:population":214
},
  "geometry": {"coordinates":[-101.38639000000001,19.50361],"type":"Point"}
}