{
  "type": "Feature",
  "properties": {
    "gn:admin1_code":"4",
    "gn:admin2_code":"2.0",
    "gn:asciiname":"La Esperanza",
    "gn:country_code":"MX",
    "gn:dem":14,
    "gn:feature_class":"P",
    "gn:feature_code":"PPL",
    "gn:name":"La Esperanza",
    "gn:population":5,
    "gn:timezone":"America/Merida",
    "iso:country":"MX",
    "wof:name":"La Esperanza",
    "wof:placetype":"locality",
    "wof:population":5
},
  "geometry": {"coordinates":[-90.5125,19.75583],"type":"Point"}
}