{
  "type": "Feature",
  "properties": {
    "gn:admin1_code":"12",
    "gn:admin2_code":"75.0",
    "gn:asciiname":"Tepehuaje",
    "gn:country_code":"MX",
    "gn:dem":1279,
    "gn:feature_class":"P",
    "gn:feature_code":"PPL",
    "gn:name":"Tepehuaje",
    "gn:population":210,
    "gn:timezone":"America/Mexico_City",
    "iso:country":"MX",
    "wof:name":"Tepehuaje",
    "wof:placetype":"locality",
    "wof:population":210
},
  "geometry": {"coordinates":[-99.76472,17.9075],"type":"Point"}
}