{
  "type": "Feature",
  "properties": {
    "gn:admin1_code":"6",
    "gn:admin2_code":"7.0",
    "gn:asciiname":"Rancho de Bejarano",
    "gn:country_code":"MX",
    "gn:dem":2698,
    "gn:feature_class":"P",
    "gn:feature_code":"PPL",
    "gn:name":"Rancho de Bejarano",
    "gn:population":8,
    "gn:timezone":"America/Chihuahua",
    "iso:country":"MX",
    "wof:name":"Rancho de Bejarano",
    "wof:placetype":"locality",
    "wof:population":8
},
  "geometry": {"coordinates":[-106.45926,26.41802],"type":"Point"}
}