{
  "type": "Feature",
  "properties": {
    "gn:admin1_code":"6",
    "gn:admin2_code":"29",
    "gn:asciiname":"La Cumbre",
    "gn:country_code":"MX",
    "gn:dem":2541,
    "gn:feature_class":"P",
    "gn:feature_code":"PPL",
    "gn:name":"La Cumbre",
    "gn:population":27,
    "gn:timezone":"America/Chihuahua",
    "iso:country":"MX",
    "name:ceb_x_preferred":[
        "La Cumbre"
    ],
    "name:deu_x_preferred":[
        "La Cumbre"
    ],
    "name:eus_x_preferred":[
        "La Cumbre"
    ],
    "name:fra_x_preferred":[
        "La Cumbre"
    ],
    "name:ita_x_preferred":[
        "La Cumbre"
    ],
    "name:msa_x_preferred":[
        "La Cumbre"
    ],
    "name:nld_x_preferred":[
        "La Cumbre"
    ],
    "name:pol_x_preferred":[
        "La Cumbre"
    ],
    "name:spa_x_preferred":[
        "La Cumbre"
    ],
    "name:swe_x_preferred":[
        "La Cumbre"
    ],
    "name:vie_x_preferred":[
        "La Cumbre"
    ],
    "name:war_x_preferred":[
        "La Cumbre"
    ],
    "wof:name":"La Cumbre",
    "wof:placetype":"locality",
    "wof:population":27
},
  "geometry": {"coordinates":[-106.66928,25.79746],"type":"Point"}
}