{
  "type": "Feature",
  "properties": {
    "gn:admin1_code":"6",
    "gn:admin2_code":"29",
    "gn:asciiname":"La Cumbre",
    "gn:country_code":"MX",
    "gn:dem":2541,
    "gn:feature_class":"P",
    "gn:feature_code":"PPL",
    "gn:name":"La Cumbre",
    "gn:population":27,
    "gn:timezone":"America/Chihuahua",
    "iso:country":"MX",
    "wof:name":"La Cumbre",
    "wof:placetype":"locality",
    "wof:population":27
},
  "geometry": {"coordinates":[-106.66928,25.79746],"type":"Point"}
}