{
  "type": "Feature",
  "properties": {
    "gn:admin1_code":"12.0",
    "gn:admin2_code":"48.0",
    "gn:asciiname":"Puerto de las Flores",
    "gn:country_code":"MX",
    "gn:dem":757,
    "gn:feature_class":"P",
    "gn:feature_code":"PPL",
    "gn:name":"Puerto de las Flores",
    "gn:population":0,
    "gn:timezone":"America/Mexico_City",
    "iso:country":"MX",
    "name:spa_x_preferred":[
        "Puerto de las Flores"
    ],
    "wof:name":"Puerto de las Flores",
    "wof:placetype":"locality"
},
  "geometry": {"coordinates":[-101.10431,17.59586000000001],"type":"Point"}
}