{
  "type": "Feature",
  "properties": {
    "gn:admin1_code":"7.0",
    "gn:admin2_code":"12.0",
    "gn:asciiname":"La Zorra",
    "gn:country_code":"MX",
    "gn:dem":222,
    "gn:feature_class":"P",
    "gn:feature_code":"PPL",
    "gn:name":"La Zorra",
    "gn:population":0,
    "gn:timezone":"America/Monterrey",
    "iso:country":"MX",
    "name:spa_x_preferred":[
        "La Zorra"
    ],
    "wof:name":"La Zorra",
    "wof:placetype":"locality"
},
  "geometry": {"coordinates":[-100.19868,28.0336],"type":"Point"}
}