{
  "type": "Feature",
  "properties": {
    "gn:admin1_code":"10",
    "gn:admin2_code":"17.0",
    "gn:asciiname":"Victorio",
    "gn:country_code":"MX",
    "gn:dem":1812,
    "gn:feature_class":"P",
    "gn:feature_code":"PPL",
    "gn:name":"Victorio",
    "gn:population":0,
    "gn:timezone":"America/Monterrey",
    "iso:country":"MX",
    "name:spa_x_preferred":[
        "Victorio"
    ],
    "wof:name":"Victorio",
    "wof:placetype":"locality"
},
  "geometry": {"coordinates":[-105.41737000000001,26.44853],"type":"Point"}
}