{
  "type": "Feature",
  "properties": {
    "gn:admin1_code":"13.0",
    "gn:admin2_code":"27.0",
    "gn:asciiname":"Dos Caminos",
    "gn:country_code":"MX",
    "gn:dem":872,
    "gn:feature_class":"P",
    "gn:feature_code":"PPL",
    "gn:name":"Dos Caminos",
    "gn:population":0,
    "gn:timezone":"America/Mexico_City",
    "iso:country":"MX",
    "name:spa_x_preferred":[
        "Dos Caminos"
    ],
    "wof:name":"Dos Caminos",
    "wof:placetype":"locality"
},
  "geometry": {"coordinates":[-98.08161,20.42509],"type":"Point"}
}