{
  "type": "Feature",
  "properties": {
    "gn:admin1_code":"12",
    "gn:admin2_code":"27.0",
    "gn:asciiname":"Linda Vista",
    "gn:country_code":"MX",
    "gn:dem":375,
    "gn:feature_class":"P",
    "gn:feature_code":"PPL",
    "gn:name":"Linda Vista",
    "gn:population":7,
    "gn:timezone":"America/Mexico_City",
    "iso:country":"MX",
    "wof:name":"Linda Vista",
    "wof:placetype":"locality",
    "wof:population":7
},
  "geometry": {"coordinates":[-100.7088,18.80196],"type":"Point"}
}