{
  "type": "Feature",
  "properties": {
    "gn:admin1_code":"18",
    "gn:admin2_code":"17.0",
    "gn:asciiname":"La Calerita",
    "gn:country_code":"MX",
    "gn:dem":879,
    "gn:feature_class":"P",
    "gn:feature_code":"PPL",
    "gn:name":"La Calerita",
    "gn:population":0,
    "gn:timezone":"America/Mazatlan",
    "iso:country":"MX",
    "name:spa_x_preferred":[
        "La Calerita"
    ],
    "wof:name":"La Calerita",
    "wof:placetype":"locality"
},
  "geometry": {"coordinates":[-104.76201,21.61475],"type":"Point"}
}