{
  "type": "Feature",
  "properties": {
    "gn:admin1_code":"6",
    "gn:admin2_code":"29.0",
    "gn:asciiname":"Rancho de Mares",
    "gn:country_code":"MX",
    "gn:dem":2275,
    "gn:feature_class":"P",
    "gn:feature_code":"PPL",
    "gn:name":"Rancho de Mares",
    "gn:population":200,
    "gn:timezone":"America/Chihuahua",
    "iso:country":"MX",
    "wof:name":"Rancho de Mares",
    "wof:placetype":"locality",
    "wof:population":200
},
  "geometry": {"coordinates":[-107.05292,26.23051],"type":"Point"}
}