{
  "type": "Feature",
  "properties": {
    "gn:admin1_code":"20",
    "gn:admin2_code":"548.0",
    "gn:asciiname":"Ahijadero",
    "gn:cc2":"MX",
    "gn:country_code":"MX",
    "gn:dem":2170,
    "gn:feature_class":"P",
    "gn:feature_code":"PPL",
    "gn:name":"Ahijadero",
    "gn:population":0,
    "gn:timezone":"America/Mexico_City",
    "iso:country":"MX",
    "name:und_x_variant":[
        "Hijadero",
        "Ahijadero"
    ],
    "wof:name":"Ahijadero",
    "wof:placetype":"locality"
},
  "geometry": {"coordinates":[-97.34999999999999,17.96667],"type":"Point"}
}