{
  "type": "Feature",
  "properties": {
    "gn:admin1_code":"14",
    "gn:admin2_code":"33",
    "gn:asciiname":"El Nacimiento",
    "gn:country_code":"MX",
    "gn:dem":1626,
    "gn:feature_class":"P",
    "gn:feature_code":"PPL",
    "gn:name":"El Nacimiento",
    "gn:population":26,
    "gn:timezone":"America/Mexico_City",
    "iso:country":"MX",
    "wof:name":"El Nacimiento",
    "wof:placetype":"locality",
    "wof:population":26
},
  "geometry": {"coordinates":[-102.16306,20.38722000000001],"type":"Point"}
}