{
  "type": "Feature",
  "properties": {
    "gn:admin1_code":"5.0",
    "gn:admin2_code":"106.0",
    "gn:asciiname":"Pajalton",
    "gn:country_code":"MX",
    "gn:dem":769,
    "gn:feature_class":"P",
    "gn:feature_code":"PPL",
    "gn:name":"Pajalt\u00f3n",
    "gn:population":0,
    "gn:timezone":"America/Mexico_City",
    "iso:country":"MX",
    "name:spa_x_preferred":[
        "Pajaltan"
    ],
    "name:spa_x_variant":[
        "Pajalt\u00f3n"
    ],
    "wof:name":"Pajalton",
    "wof:placetype":"locality"
},
  "geometry": {"coordinates":[-92.74397999999999,16.36007],"type":"Point"}
}