{
  "type": "Feature",
  "properties": {
    "gn:admin1_code":"15",
    "gn:admin2_code":"124.0",
    "gn:asciiname":"La Chispa",
    "gn:country_code":"MX",
    "gn:dem":2747,
    "gn:feature_class":"P",
    "gn:feature_code":"PPL",
    "gn:name":"La Chispa",
    "gn:population":572,
    "gn:timezone":"America/Mexico_City",
    "iso:country":"MX",
    "wof:name":"La Chispa",
    "wof:placetype":"locality",
    "wof:population":572
},
  "geometry": {"coordinates":[-100.14167,19.5575],"type":"Point"}
}