{
  "type": "Feature",
  "properties": {
    "gn:admin1_code":"5",
    "gn:admin2_code":"46.0",
    "gn:asciiname":"El Brillante",
    "gn:country_code":"MX",
    "gn:dem":562,
    "gn:feature_class":"P",
    "gn:feature_code":"PPL",
    "gn:name":"El Brillante",
    "gn:population":6,
    "gn:timezone":"America/Mexico_City",
    "iso:country":"MX",
    "wof:name":"El Brillante",
    "wof:placetype":"locality",
    "wof:population":6
},
  "geometry": {"coordinates":[-93.66556,16.59333],"type":"Point"}
}