{
  "type": "Feature",
  "properties": {
    "gn:admin1_code":"21",
    "gn:admin2_code":"10.0",
    "gn:asciiname":"Tequexco",
    "gn:country_code":"MX",
    "gn:dem":1265,
    "gn:feature_class":"P",
    "gn:feature_code":"PPL",
    "gn:name":"Tequexco",
    "gn:population":118,
    "gn:timezone":"America/Mexico_City",
    "iso:country":"MX",
    "wof:name":"Tequexco",
    "wof:placetype":"locality",
    "wof:population":118
},
  "geometry": {"coordinates":[-97.28617,18.39073],"type":"Point"}
}