{
  "type": "Feature",
  "properties": {
    "gn:admin1_code":"30",
    "gn:admin2_code":"49",
    "gn:asciiname":"Loma Alta",
    "gn:country_code":"MX",
    "gn:dem":85,
    "gn:feature_class":"P",
    "gn:feature_code":"PPL",
    "gn:name":"Loma Alta",
    "gn:population":36,
    "gn:timezone":"America/Mexico_City",
    "iso:country":"MX",
    "wof:name":"Loma Alta",
    "wof:placetype":"locality",
    "wof:population":36
},
  "geometry": {"coordinates":[-96.35722,18.80389],"type":"Point"}
}