{
  "type": "Feature",
  "properties": {
    "gn:admin1_code":"32.0",
    "gn:admin2_code":"8.0",
    "gn:asciiname":"El Chan",
    "gn:country_code":"MX",
    "gn:dem":2308,
    "gn:feature_class":"P",
    "gn:feature_code":"PPL",
    "gn:name":"El Chan",
    "gn:population":0,
    "gn:timezone":"America/Mexico_City",
    "iso:country":"MX",
    "name:spa_x_preferred":[
        "El Chan"
    ],
    "wof:name":"El Chan",
    "wof:placetype":"locality"
},
  "geometry": {"coordinates":[-102.47620999999999,22.34624],"type":"Point"}
}