{
  "type": "Feature",
  "properties": {
    "gn:admin1_code":"5",
    "gn:admin2_code":"30.0",
    "gn:asciiname":"Chaschahual",
    "gn:country_code":"MX",
    "gn:dem":615,
    "gn:feature_class":"P",
    "gn:feature_code":"PPL",
    "gn:name":"Chaschahual",
    "gn:population":89,
    "gn:timezone":"America/Mexico_City",
    "iso:country":"MX",
    "wof:name":"Chaschahual",
    "wof:placetype":"locality",
    "wof:population":89
},
  "geometry": {"coordinates":[-92.28055999999999,15.755],"type":"Point"}
}