{
  "type": "Feature",
  "properties": {
    "gn:admin1_code":"6.0",
    "gn:admin2_code":"27.0",
    "gn:asciiname":"Rohuichi",
    "gn:country_code":"MX",
    "gn:dem":2297,
    "gn:feature_class":"P",
    "gn:feature_code":"PPL",
    "gn:name":"Rohuichi",
    "gn:population":0,
    "gn:timezone":"America/Chihuahua",
    "iso:country":"MX",
    "name:spa_x_preferred":[
        "Rohuichi"
    ],
    "wof:name":"Rohuichi",
    "wof:placetype":"locality"
},
  "geometry": {"coordinates":[-107.69549000000001,27.41789],"type":"Point"}
}