{
  "type": "Feature",
  "properties": {
    "gn:admin1_code":"16.0",
    "gn:admin2_code":"55.0",
    "gn:asciiname":"El Capiri",
    "gn:country_code":"MX",
    "gn:dem":380,
    "gn:feature_class":"P",
    "gn:feature_code":"PPL",
    "gn:name":"El Capiri",
    "gn:population":0,
    "gn:timezone":"America/Mexico_City",
    "iso:country":"MX",
    "name:spa_x_preferred":[
        "El Capiri"
    ],
    "wof:name":"El Capiri",
    "wof:placetype":"locality"
},
  "geometry": {"coordinates":[-102.12161999999999,19.00521],"type":"Point"}
}