{
  "type": "Feature",
  "properties": {
    "gn:admin1_code":"21",
    "gn:admin2_code":"43.0",
    "gn:asciiname":"Las Hamacas",
    "gn:country_code":"MX",
    "gn:dem":278,
    "gn:feature_class":"P",
    "gn:feature_code":"PPL",
    "gn:name":"Las Hamacas",
    "gn:population":245,
    "gn:timezone":"America/Mexico_City",
    "iso:country":"MX",
    "wof:name":"Las Hamacas",
    "wof:placetype":"locality",
    "wof:population":245
},
  "geometry": {"coordinates":[-97.44965999999999,20.03625],"type":"Point"}
}