{
  "type": "Feature",
  "properties": {
    "gn:admin1_code":"19.0",
    "gn:asciiname":"Los Tuceros",
    "gn:country_code":"MX",
    "gn:dem":913,
    "gn:feature_class":"P",
    "gn:feature_code":"PPL",
    "gn:name":"Los Tuceros",
    "gn:population":0,
    "gn:timezone":"America/Monterrey",
    "iso:country":"MX",
    "name:spa_x_preferred":[
        "Los Tuceros"
    ],
    "wof:name":"Los Tuceros",
    "wof:placetype":"locality"
},
  "geometry": {"coordinates":[-100.07746,24.99873],"type":"Point"}
}