{
  "type": "Feature",
  "properties": {
    "gn:admin1_code":"20",
    "gn:admin2_code":"171.0",
    "gn:asciiname":"Teocuatlan",
    "gn:country_code":"MX",
    "gn:dem":1119,
    "gn:feature_class":"P",
    "gn:feature_code":"PPL",
    "gn:name":"Teocuatl\u00e1n",
    "gn:population":271,
    "gn:timezone":"America/Mexico_City",
    "iso:country":"MX",
    "name:und_x_variant":[
        "Teocuatl\u00e1n"
    ],
    "wof:name":"Teocuatlan",
    "wof:placetype":"locality",
    "wof:population":271
},
  "geometry": {"coordinates":[-96.64472000000001,18.16139],"type":"Point"}
}