{
  "type": "Feature",
  "properties": {
    "gn:admin1_code":"9",
    "gn:admin2_code":"9",
    "gn:asciiname":"Tlalcospa (Nacatulatlaco)",
    "gn:country_code":"MX",
    "gn:dem":2674,
    "gn:feature_class":"P",
    "gn:feature_code":"PPL",
    "gn:name":"Tlalcospa (Nacatulatlaco)",
    "gn:population":30,
    "gn:timezone":"America/Mexico_City",
    "iso:country":"MX",
    "wof:name":"Tlalcospa (Nacatulatlaco)",
    "wof:placetype":"locality",
    "wof:population":30
},
  "geometry": {"coordinates":[-98.99117,19.16689],"type":"Point"}
}