{
  "type": "Feature",
  "properties": {
    "gn:admin1_code":"18",
    "gn:admin2_code":"20",
    "gn:asciiname":"Colonia las Iguanas",
    "gn:country_code":"MX",
    "gn:dem":43,
    "gn:feature_class":"P",
    "gn:feature_code":"PPL",
    "gn:name":"Colonia las Iguanas",
    "gn:population":45,
    "gn:timezone":"America/Bahia_Banderas",
    "iso:country":"MX",
    "wof:name":"Colonia las Iguanas",
    "wof:placetype":"locality",
    "wof:population":45
},
  "geometry": {"coordinates":[-105.24028,20.7975],"type":"Point"}
}