{
  "type": "Feature",
  "properties": {
    "gn:admin1_code":"1.0",
    "gn:admin2_code":"3.0",
    "gn:asciiname":"El Tepozan",
    "gn:country_code":"MX",
    "gn:dem":1781,
    "gn:feature_class":"P",
    "gn:feature_code":"PPL",
    "gn:name":"El Tepoz\u00e1n",
    "gn:population":0,
    "gn:timezone":"America/Mexico_City",
    "iso:country":"MX",
    "wof:name":"El Tepozan",
    "wof:placetype":"locality"
},
  "geometry": {"coordinates":[-102.75006999999999,21.94039],"type":"Point"}
}