{
  "type": "Feature",
  "properties": {
    "gn:admin1_code":"20",
    "gn:admin2_code":"278",
    "gn:asciiname":"Islas Santa Julia",
    "gn:country_code":"MX",
    "gn:dem":89,
    "gn:feature_class":"P",
    "gn:feature_code":"PPL",
    "gn:name":"Islas Santa Julia",
    "gn:population":22,
    "gn:timezone":"America/Mexico_City",
    "iso:country":"MX",
    "wof:name":"Islas Santa Julia",
    "wof:placetype":"locality",
    "wof:population":22
},
  "geometry": {"coordinates":[-96.55444,18.28778],"type":"Point"}
}