{
  "type": "Feature",
  "properties": {
    "gn:admin1_code":"19",
    "gn:admin2_code":"38.0",
    "gn:asciiname":"El Olmito",
    "gn:country_code":"MX",
    "gn:dem":348,
    "gn:feature_class":"P",
    "gn:feature_code":"PPL",
    "gn:name":"El Olmito",
    "gn:population":23,
    "gn:timezone":"America/Monterrey",
    "iso:country":"MX",
    "name:spa_x_preferred":[
        "El Olmito"
    ],
    "wof:name":"El Olmito",
    "wof:placetype":"locality",
    "wof:population":23
},
  "geometry": {"coordinates":[-99.80911999999999,25.27032],"type":"Point"}
}