{
  "type": "Feature",
  "properties": {
    "gn:admin1_code":"10",
    "gn:admin2_code":"14.0",
    "gn:asciiname":"La Noria",
    "gn:country_code":"MX",
    "gn:dem":1953,
    "gn:feature_class":"P",
    "gn:feature_code":"PPL",
    "gn:name":"La Noria",
    "gn:population":5,
    "gn:timezone":"America/Monterrey",
    "iso:country":"MX",
    "wof:name":"La Noria",
    "wof:placetype":"locality",
    "wof:population":5
},
  "geometry": {"coordinates":[-104.60135,22.76781],"type":"Point"}
}