{
  "type": "Feature",
  "properties": {
    "gn:admin1_code":"6",
    "gn:admin2_code":"65",
    "gn:asciiname":"La Canoa",
    "gn:country_code":"MX",
    "gn:dem":2122,
    "gn:feature_class":"P",
    "gn:feature_code":"PPL",
    "gn:name":"La Canoa",
    "gn:population":11,
    "gn:timezone":"America/Chihuahua",
    "iso:country":"MX",
    "wof:name":"La Canoa",
    "wof:placetype":"locality",
    "wof:population":11
},
  "geometry": {"coordinates":[-107.95491,27.11104000000001],"type":"Point"}
}