{
  "type": "Feature",
  "properties": {
    "gn:admin1_code":"5",
    "gn:admin2_code":"9",
    "gn:asciiname":"Bola de Oro",
    "gn:country_code":"MX",
    "gn:dem":39,
    "gn:feature_class":"P",
    "gn:feature_code":"PPL",
    "gn:name":"Bola de Oro",
    "gn:population":48,
    "gn:timezone":"America/Mexico_City",
    "iso:country":"MX",
    "wof:name":"Bola de Oro",
    "wof:placetype":"locality",
    "wof:population":48
},
  "geometry": {"coordinates":[-93.98389,16.23389],"type":"Point"}
}