{
  "type": "Feature",
  "properties": {
    "gn:admin1_code":"6.0",
    "gn:admin2_code":"7.0",
    "gn:asciiname":"El Chiguitoso",
    "gn:country_code":"MX",
    "gn:dem":2627,
    "gn:feature_class":"P",
    "gn:feature_code":"PPL",
    "gn:name":"El Chiguitoso",
    "gn:population":0,
    "gn:timezone":"America/Monterrey",
    "iso:country":"MX",
    "name:spa_x_preferred":[
        "El Chiguitoso"
    ],
    "wof:name":"El Chiguitoso",
    "wof:placetype":"locality"
},
  "geometry": {"coordinates":[-106.38701,26.31199],"type":"Point"}
}