{
  "type": "Feature",
  "properties": {
    "gn:admin1_code":"20",
    "gn:admin2_code":"2.0",
    "gn:asciiname":"San Eduardo",
    "gn:country_code":"MX",
    "gn:dem":138,
    "gn:feature_class":"P",
    "gn:feature_code":"PPL",
    "gn:name":"San Eduardo",
    "gn:population":0,
    "gn:timezone":"America/Mexico_City",
    "iso:country":"MX",
    "name:spa_x_preferred":[
        "San Eduardo"
    ],
    "wof:name":"San Eduardo",
    "wof:placetype":"locality"
},
  "geometry": {"coordinates":[-96.51943,18.56698],"type":"Point"}
}