{
  "type": "Feature",
  "properties": {
    "gn:admin1_code":"14.0",
    "gn:admin2_code":"69.0",
    "gn:asciiname":"El Chucharo",
    "gn:country_code":"MX",
    "gn:dem":2206,
    "gn:feature_class":"P",
    "gn:feature_code":"PPL",
    "gn:name":"El Chucharo",
    "gn:population":0,
    "gn:timezone":"America/Mexico_City",
    "iso:country":"MX",
    "name:spa_x_preferred":[
        "El Chucharo"
    ],
    "name:spa_x_variant":[
        "El Aserradero"
    ],
    "wof:name":"El Chucharo",
    "wof:placetype":"locality"
},
  "geometry": {"coordinates":[-102.92941999999999,19.72986],"type":"Point"}
}