{
  "type": "Feature",
  "properties": {
    "gn:admin1_code":"10.0",
    "gn:admin2_code":"6.0",
    "gn:asciiname":"Ricardo Flores Magon",
    "gn:country_code":"MX",
    "gn:dem":1460,
    "gn:feature_class":"P",
    "gn:feature_code":"PPL",
    "gn:name":"Ricardo Flores Mag\u00f3n",
    "gn:population":215,
    "gn:timezone":"America/Monterrey",
    "iso:country":"MX",
    "wof:name":"Ricardo Flores Magon",
    "wof:placetype":"locality",
    "wof:population":215
},
  "geometry": {"coordinates":[-103.18809,24.75358],"type":"Point"}
}