{
  "type": "Feature",
  "properties": {
    "gn:admin1_code":"21.0",
    "gn:asciiname":"Tehuiscomulco",
    "gn:country_code":"MX",
    "gn:dem":976,
    "gn:feature_class":"P",
    "gn:feature_code":"PPL",
    "gn:name":"Tehuiscomulco",
    "gn:population":0,
    "gn:timezone":"America/Mexico_City",
    "iso:country":"MX",
    "name:spa_x_preferred":[
        "Tehuiscomulco"
    ],
    "wof:name":"Tehuiscomulco",
    "wof:placetype":"locality"
},
  "geometry": {"coordinates":[-98.69132999999999,18.39183],"type":"Point"}
}