{
  "type": "Feature",
  "properties": {
    "gn:admin1_code":"30.0",
    "gn:admin2_code":"181.0",
    "gn:asciiname":"Canal Veintinueve",
    "gn:country_code":"MX",
    "gn:dem":36,
    "gn:feature_class":"P",
    "gn:feature_code":"PPL",
    "gn:name":"Canal Veintinueve",
    "gn:population":0,
    "gn:timezone":"America/Mexico_City",
    "iso:country":"MX",
    "name:spa_x_preferred":[
        "Canal Veintinueve"
    ],
    "wof:name":"Canal Veintinueve",
    "wof:placetype":"locality"
},
  "geometry": {"coordinates":[-96.21401,18.74494],"type":"Point"}
}