{
  "type": "Feature",
  "properties": {
    "gn:admin1_code":"15",
    "gn:admin2_code":"113.0",
    "gn:asciiname":"San Pedro Buenos Aires",
    "gn:country_code":"MX",
    "gn:dem":2439,
    "gn:feature_class":"P",
    "gn:feature_code":"PPL",
    "gn:name":"San Pedro Buenos Aires",
    "gn:population":0,
    "gn:timezone":"America/Mexico_City",
    "iso:country":"MX",
    "name:spa_x_preferred":[
        "San Pedro Buenos Aires"
    ],
    "wof:name":"San Pedro Buenos Aires",
    "wof:placetype":"locality"
},
  "geometry": {"coordinates":[-99.71021,18.92692000000001],"type":"Point"}
}