{
  "type": "Feature",
  "properties": {
    "gn:admin1_code":"26",
    "gn:admin2_code":"30.0",
    "gn:asciiname":"Puerto Arturo",
    "gn:country_code":"MX",
    "gn:dem":11,
    "gn:feature_class":"P",
    "gn:feature_code":"PPL",
    "gn:name":"Puerto Arturo",
    "gn:population":106,
    "gn:timezone":"America/Hermosillo",
    "iso:country":"MX",
    "wof:name":"Puerto Arturo",
    "wof:placetype":"locality",
    "wof:population":106
},
  "geometry": {"coordinates":[-111.41974999999999,28.42919],"type":"Point"}
}