{
  "type": "Feature",
  "properties": {
    "gn:admin1_code":"11",
    "gn:admin2_code":"7",
    "gn:asciiname":"Almanza",
    "gn:country_code":"MX",
    "gn:dem":2077,
    "gn:feature_class":"P",
    "gn:feature_code":"PPL",
    "gn:name":"Almanza",
    "gn:population":25,
    "gn:timezone":"America/Mexico_City",
    "iso:country":"MX",
    "name:arg_x_preferred":[
        "Almanza"
    ],
    "name:ast_x_preferred":[
        "Almanza"
    ],
    "name:azb_x_preferred":[
        "\u0627\u0644\u0645\u0646\u0632\u0627"
    ],
    "name:cat_x_preferred":[
        "Almanza"
    ],
    "name:ceb_x_preferred":[
        "Almanza"
    ],
    "name:eus_x_preferred":[
        "Almanza"
    ],
    "name:fas_x_preferred":[
        "\u0627\u0644\u0645\u0646\u0632\u0627"
    ],
    "name:fra_x_preferred":[
        "Almanza"
    ],
    "name:glg_x_preferred":[
        "Almanza"
    ],
    "name:haw_x_preferred":[
        "Almanza"
    ],
    "name:hun_x_preferred":[
        "Almanza"
    ],
    "name:ido_x_preferred":[
        "Almanza"
    ],
    "name:ina_x_preferred":[
        "Almanza"
    ],
    "name:ita_x_preferred":[
        "Almanza"
    ],
    "name:msa_x_preferred":[
        "Almanza"
    ],
    "name:oci_x_preferred":[
        "Almanza"
    ],
    "name:pol_x_preferred":[
        "Almanza"
    ],
    "name:por_x_preferred":[
        "Almanza"
    ],
    "name:rus_x_preferred":[
        "\u0410\u043b\u044c\u043c\u0430\u043d\u0441\u0430"
    ],
    "name:spa_x_preferred":[
        "Almanza"
    ],
    "name:swe_x_preferred":[
        "Almanza"
    ],
    "name:tpi_x_preferred":[
        "Almanza"
    ],
    "name:ukr_x_preferred":[
        "\u0410\u043b\u044c\u043c\u0430\u043d\u0441\u0430"
    ],
    "name:vie_x_preferred":[
        "Almanza"
    ],
    "name:zho_x_preferred":[
        "\u963f\u5c14\u66fc\u8428"
    ],
    "wof:name":"Almanza",
    "wof:placetype":"locality",
    "wof:population":25
},
  "geometry": {"coordinates":[-100.75278,20.38444],"type":"Point"}
}