{
  "type": "Feature",
  "properties": {
    "gn:admin1_code":"19",
    "gn:admin2_code":"5",
    "gn:asciiname":"Lazaro Cardenas",
    "gn:country_code":"MX",
    "gn:dem":205,
    "gn:feature_class":"P",
    "gn:feature_code":"PPL",
    "gn:name":"L\u00e1zaro C\u00e1rdenas",
    "gn:population":50,
    "gn:timezone":"America/Matamoros",
    "iso:country":"MX",
    "name:und_x_variant":[
        "L\u00e1zaro C\u00e1rdenas"
    ],
    "wof:name":"Lazaro Cardenas",
    "wof:placetype":"locality",
    "wof:population":50
},
  "geometry": {"coordinates":[-100.11228,27.24447],"type":"Point"}
}