{
  "type": "Feature",
  "properties": {
    "gn:admin1_code":"25",
    "gn:admin2_code":"7.0",
    "gn:asciiname":"La Guasa",
    "gn:country_code":"MX",
    "gn:dem":229,
    "gn:feature_class":"P",
    "gn:feature_code":"PPL",
    "gn:name":"La Guasa",
    "gn:population":0,
    "gn:timezone":"America/Mazatlan",
    "iso:country":"MX",
    "name:spa_x_preferred":[
        "La Guasa"
    ],
    "name:und_x_variant":[
        "Rancho La Guasa"
    ],
    "wof:name":"La Guasa",
    "wof:placetype":"locality"
},
  "geometry": {"coordinates":[-108.38866000000002,27.0008],"type":"Point"}
}