{
  "type": "Feature",
  "properties": {
    "gn:admin1_code":"30",
    "gn:admin2_code":"108.0",
    "gn:asciiname":"Julian Soto Cruz (Los Monos)",
    "gn:country_code":"MX",
    "gn:dem":6,
    "gn:feature_class":"P",
    "gn:feature_code":"PPL",
    "gn:name":"Juli\u00e1n Soto Cruz (Los Monos)",
    "gn:population":8,
    "gn:timezone":"America/Mexico_City",
    "iso:country":"MX",
    "name:und_x_variant":[
        "Juli\u00e1n Soto Cruz (Los Monos)"
    ],
    "wof:name":"Julian Soto Cruz (Los Monos)",
    "wof:placetype":"locality",
    "wof:population":8
},
  "geometry": {"coordinates":[-94.41361000000001,17.82389],"type":"Point"}
}