{
  "type": "Feature",
  "properties": {
    "gn:admin1_code":"19.0",
    "gn:asciiname":"Bocanegra",
    "gn:country_code":"MX",
    "gn:dem":1879,
    "gn:feature_class":"P",
    "gn:feature_code":"PPL",
    "gn:name":"Bocanegra",
    "gn:population":0,
    "gn:timezone":"America/Monterrey",
    "iso:country":"MX",
    "name:spa_x_preferred":[
        "Bocanegra"
    ],
    "wof:name":"Bocanegra",
    "wof:placetype":"locality"
},
  "geometry": {"coordinates":[-100.33007000000001,24.81213],"type":"Point"}
}