{
  "type": "Feature",
  "properties": {
    "gn:admin1_code":"25",
    "gn:admin2_code":"6.0",
    "gn:asciiname":"La Vainilla",
    "gn:country_code":"MX",
    "gn:dem":126,
    "gn:feature_class":"P",
    "gn:feature_code":"PPL",
    "gn:name":"La Vainilla",
    "gn:population":0,
    "gn:timezone":"America/Mazatlan",
    "iso:country":"MX",
    "name:und_x_variant":[
        "Vainilla"
    ],
    "wof:name":"La Vainilla",
    "wof:placetype":"locality"
},
  "geometry": {"coordinates":[-107.33880000000001,25.04452],"type":"Point"}
}