{
  "type": "Feature",
  "properties": {
    "gn:admin1_code":"5",
    "gn:admin2_code":"102",
    "gn:asciiname":"San Jose la Victoria",
    "gn:country_code":"MX",
    "gn:dem":488,
    "gn:feature_class":"P",
    "gn:feature_code":"PPL",
    "gn:name":"San Jos\u00e9 la Victoria",
    "gn:population":43,
    "gn:timezone":"America/Mexico_City",
    "iso:country":"MX",
    "name:und_x_variant":[
        "San Jos\u00e9 la Victoria"
    ],
    "wof:name":"San Jose la Victoria",
    "wof:placetype":"locality",
    "wof:population":43
},
  "geometry": {"coordinates":[-92.15416999999999,14.98639],"type":"Point"}
}