{
  "type": "Feature",
  "properties": {
    "gn:admin1_code":"16",
    "gn:admin2_code":"99",
    "gn:asciiname":"Palo Verde",
    "gn:country_code":"MX",
    "gn:dem":721,
    "gn:feature_class":"P",
    "gn:feature_code":"PPL",
    "gn:name":"Palo Verde",
    "gn:population":12,
    "gn:timezone":"America/Mexico_City",
    "iso:country":"MX",
    "name:ceb_x_preferred":[
        "Palo Verde"
    ],
    "name:deu_x_preferred":[
        "Palo Verde"
    ],
    "name:fra_x_preferred":[
        "Palo Verde"
    ],
    "name:spa_x_preferred":[
        "Palo Verde"
    ],
    "name:srp_x_preferred":[
        "\u041f\u0430\u043b\u043e \u0412\u0435\u0440\u0434\u0435"
    ],
    "name:swe_x_preferred":[
        "Palo Verde"
    ],
    "wof:name":"Palo Verde",
    "wof:placetype":"locality",
    "wof:population":12
},
  "geometry": {"coordinates":[-100.50306,19.13611],"type":"Point"}
}