{
  "type": "Feature",
  "properties": {
    "gn:admin1_code":"28.0",
    "gn:admin2_code":"18.0",
    "gn:asciiname":"El Chapotal",
    "gn:country_code":"MX",
    "gn:dem":283,
    "gn:feature_class":"P",
    "gn:feature_code":"PPL",
    "gn:name":"El Chapotal",
    "gn:population":0,
    "gn:timezone":"America/Monterrey",
    "iso:country":"MX",
    "name:spa_x_preferred":[
        "El Chapotal"
    ],
    "wof:name":"El Chapotal",
    "wof:placetype":"locality"
},
  "geometry": {"coordinates":[-98.63503,24.40136],"type":"Point"}
}