{
  "type": "Feature",
  "properties": {
    "gn:admin1_code":"6",
    "gn:admin2_code":"65",
    "gn:asciiname":"Yanapuchi",
    "gn:country_code":"MX",
    "gn:dem":2114,
    "gn:feature_class":"P",
    "gn:feature_code":"PPL",
    "gn:name":"Yanapuchi",
    "gn:population":10,
    "gn:timezone":"America/Chihuahua",
    "iso:country":"MX",
    "wof:name":"Yanapuchi",
    "wof:placetype":"locality",
    "wof:population":10
},
  "geometry": {"coordinates":[-108.02632,27.5952],"type":"Point"}
}