{
  "type": "Feature",
  "properties": {
    "gn:admin1_code":"24",
    "gn:admin2_code":"11.0",
    "gn:asciiname":"La Banda",
    "gn:country_code":"MX",
    "gn:dem":1090,
    "gn:feature_class":"P",
    "gn:feature_code":"PPL",
    "gn:name":"La Banda",
    "gn:population":9,
    "gn:timezone":"America/Mexico_City",
    "iso:country":"MX",
    "wof:name":"La Banda",
    "wof:placetype":"locality",
    "wof:population":9
},
  "geometry": {"coordinates":[-100.29861,22.075],"type":"Point"}
}