{
  "type": "Feature",
  "properties": {
    "gn:admin1_code":"14.0",
    "gn:admin2_code":"61.0",
    "gn:asciiname":"Ciudad Juarez",
    "gn:country_code":"MX",
    "gn:dem":1745,
    "gn:feature_class":"P",
    "gn:feature_code":"PPL",
    "gn:name":"Ciudad Ju\u00e1rez",
    "gn:population":0,
    "gn:timezone":"America/Mexico_City",
    "iso:country":"MX",
    "name:spa_x_preferred":[
        "Ciudad Ju\u00e1rez"
    ],
    "wof:name":"Ciudad Juarez",
    "wof:placetype":"locality"
},
  "geometry": {"coordinates":[-104.18103000000001,22.316],"type":"Point"}
}