{
  "type": "Feature",
  "properties": {
    "gn:admin1_code":"6",
    "gn:admin2_code":"17.0",
    "gn:asciiname":"La Nueva Union",
    "gn:country_code":"MX",
    "gn:dem":2191,
    "gn:feature_class":"P",
    "gn:feature_code":"PPL",
    "gn:name":"La Nueva Uni\u00f3n",
    "gn:population":11,
    "gn:timezone":"America/Chihuahua",
    "iso:country":"MX",
    "wof:name":"La Nueva Union",
    "wof:placetype":"locality",
    "wof:population":11
},
  "geometry": {"coordinates":[-107.01488000000001,28.41366],"type":"Point"}
}