{
  "type": "Feature",
  "properties": {
    "gn:admin1_code":"6",
    "gn:admin2_code":"46.0",
    "gn:asciiname":"Rancheria Buenavista",
    "gn:country_code":"MX",
    "gn:dem":1937,
    "gn:feature_class":"P",
    "gn:feature_code":"PPL",
    "gn:name":"Rancher\u00eda Buenavista",
    "gn:population":0,
    "gn:timezone":"America/Chihuahua",
    "iso:country":"MX",
    "name:spa_x_preferred":[
        "Rancher\u00eda Buenavista"
    ],
    "wof:name":"Rancheria Buenavista",
    "wof:placetype":"locality"
},
  "geometry": {"coordinates":[-107.77403,26.69962],"type":"Point"}
}