{
  "type": "Feature",
  "properties": {
    "gn:admin1_code":"16",
    "gn:admin2_code":"57",
    "gn:asciiname":"Las Calabazas",
    "gn:country_code":"MX",
    "gn:dem":912,
    "gn:feature_class":"P",
    "gn:feature_code":"PPL",
    "gn:name":"Las Calabazas",
    "gn:population":26,
    "gn:timezone":"America/Mexico_City",
    "iso:country":"MX",
    "wof:name":"Las Calabazas",
    "wof:placetype":"locality",
    "wof:population":26
},
  "geometry": {"coordinates":[-101.31111,19.12028],"type":"Point"}
}