{
  "type": "Feature",
  "properties": {
    "gn:admin1_code":"14",
    "gn:admin2_code":"48.0",
    "gn:asciiname":"El Amarradero",
    "gn:country_code":"MX",
    "gn:dem":2022,
    "gn:feature_class":"P",
    "gn:feature_code":"PPL",
    "gn:name":"El Amarradero",
    "gn:population":107,
    "gn:timezone":"America/Mexico_City",
    "iso:country":"MX",
    "wof:name":"El Amarradero",
    "wof:placetype":"locality",
    "wof:population":107
},
  "geometry": {"coordinates":[-102.01278000000001,20.65306],"type":"Point"}
}