{
  "type": "Feature",
  "properties": {
    "gn:admin1_code":"6",
    "gn:admin2_code":"31",
    "gn:asciiname":"Arroyo el Venado",
    "gn:country_code":"MX",
    "gn:dem":2586,
    "gn:feature_class":"P",
    "gn:feature_code":"PPL",
    "gn:name":"Arroyo el Venado",
    "gn:population":9,
    "gn:timezone":"America/Chihuahua",
    "iso:country":"MX",
    "wof:name":"Arroyo el Venado",
    "wof:placetype":"locality",
    "wof:population":9
},
  "geometry": {"coordinates":[-107.67523,28.1653],"type":"Point"}
}