{
  "type": "Feature",
  "properties": {
    "gn:admin1_code":"23.0",
    "gn:asciiname":"Tzucum",
    "gn:country_code":"MX",
    "gn:dem":19,
    "gn:feature_class":"P",
    "gn:feature_code":"PPL",
    "gn:name":"Tzucum",
    "gn:population":0,
    "gn:timezone":"America/Cancun",
    "iso:country":"MX",
    "name:spa_x_preferred":[
        "Tzucum"
    ],
    "wof:name":"Tzucum",
    "wof:placetype":"locality"
},
  "geometry": {"coordinates":[-88.1315,19.76831],"type":"Point"}
}