{
  "type": "Feature",
  "properties": {
    "gn:admin1_code":"20",
    "gn:admin2_code":"278.0",
    "gn:asciiname":"Benito Juarez II (San Martin)",
    "gn:country_code":"MX",
    "gn:dem":120,
    "gn:feature_class":"P",
    "gn:feature_code":"PPL",
    "gn:name":"Benito Ju\u00e1rez II (San Mart\u00edn)",
    "gn:population":1553,
    "gn:timezone":"America/Mexico_City",
    "iso:country":"MX",
    "name:und_x_variant":[
        "Benito Ju\u00e1rez II (San Mart\u00edn)"
    ],
    "wof:name":"Benito Juarez II (San Martin)",
    "wof:placetype":"locality",
    "wof:population":1553
},
  "geometry": {"coordinates":[-96.46138999999999,18.14056],"type":"Point"}
}