{
  "type": "Feature",
  "properties": {
    "gn:admin1_code":"19",
    "gn:admin2_code":"14.0",
    "gn:asciiname":"Santa Teresa y San Jeronimo",
    "gn:country_code":"MX",
    "gn:dem":1812,
    "gn:feature_class":"P",
    "gn:feature_code":"PPL",
    "gn:name":"Santa Teresa y San Jer\u00f3nimo",
    "gn:population":0,
    "gn:timezone":"America/Monterrey",
    "iso:country":"MX",
    "name:spa_x_preferred":[
        "Santa Teresa y San Jer\u00f3nimo"
    ],
    "name:und_x_variant":[
        "Santa Teresa"
    ],
    "wof:name":"Santa Teresa y San Jeronimo",
    "wof:placetype":"locality"
},
  "geometry": {"coordinates":[-100.4269,23.80672],"type":"Point"}
}