{
  "type": "Feature",
  "properties": {
    "gn:admin1_code":"10.0",
    "gn:admin2_code":"4.0",
    "gn:asciiname":"Ramon Corona",
    "gn:country_code":"MX",
    "gn:dem":2130,
    "gn:feature_class":"P",
    "gn:feature_code":"PPL",
    "gn:name":"Ram\u00f3n Corona",
    "gn:population":1870,
    "gn:timezone":"America/Monterrey",
    "iso:country":"MX",
    "wof:name":"Ramon Corona",
    "wof:placetype":"locality",
    "wof:population":1870
},
  "geometry": {"coordinates":[-103.63028,24.18611],"type":"Point"}
}