{
  "type": "Feature",
  "properties": {
    "gn:admin1_code":"15.0",
    "gn:asciiname":"Estacion los Lirios",
    "gn:country_code":"MX",
    "gn:dem":2151,
    "gn:feature_class":"P",
    "gn:feature_code":"PPL",
    "gn:name":"Estaci\u00f3n los Lirios",
    "gn:population":0,
    "gn:timezone":"America/Mexico_City",
    "iso:country":"MX",
    "name:spa_x_preferred":[
        "Estaci\u00f3n los Lirios"
    ],
    "wof:name":"Estacion los Lirios",
    "wof:placetype":"locality"
},
  "geometry": {"coordinates":[-100.26685999999999,19.92551],"type":"Point"}
}