{
  "type": "Feature",
  "properties": {
    "gn:admin1_code":"32",
    "gn:admin2_code":"10.0",
    "gn:asciiname":"Rancho Colorado",
    "gn:country_code":"MX",
    "gn:dem":2203,
    "gn:feature_class":"P",
    "gn:feature_code":"PPL",
    "gn:name":"Rancho Colorado",
    "gn:population":0,
    "gn:timezone":"America/Mexico_City",
    "iso:country":"MX",
    "name:spa_x_preferred":[
        "Rancho Colorado"
    ],
    "wof:name":"Rancho Colorado",
    "wof:placetype":"locality"
},
  "geometry": {"coordinates":[-103.17225999999999,23.2362],"type":"Point"}
}