{
  "type": "Feature",
  "properties": {
    "gn:admin1_code":"12.0",
    "gn:asciiname":"Rancho Santiago Castro",
    "gn:country_code":"MX",
    "gn:dem":1316,
    "gn:feature_class":"P",
    "gn:feature_code":"PPL",
    "gn:name":"Rancho Santiago Castro",
    "gn:population":0,
    "gn:timezone":"America/Mexico_City",
    "iso:country":"MX",
    "name:spa_x_preferred":[
        "Rancho Santiago Castro"
    ],
    "name:spa_x_variant":[
        "Agua Escondida"
    ],
    "wof:name":"Rancho Santiago Castro",
    "wof:placetype":"locality"
},
  "geometry": {"coordinates":[-98.54386,17.60156],"type":"Point"}
}