{
  "type": "Feature",
  "properties": {
    "gn:admin1_code":"5",
    "gn:admin2_code":"17.0",
    "gn:asciiname":"Cuba",
    "gn:country_code":"MX",
    "gn:dem":560,
    "gn:feature_class":"P",
    "gn:feature_code":"PPL",
    "gn:name":"Cuba",
    "gn:population":5,
    "gn:timezone":"America/Mexico_City",
    "iso:country":"MX",
    "wof:name":"Cuba",
    "wof:placetype":"locality",
    "wof:population":5
},
  "geometry": {"coordinates":[-93.72499999999999,16.66806],"type":"Point"}
}