{
  "type": "Feature",
  "properties": {
    "iso:country":"MX",
    "name:spa_x_preferred":[
        "El Fortin"
    ],
    "name:spa_x_variant":[
        "El Fort\u00edn"
    ],
    "qs:gn_adm0_cc":"MX",
    "qs:gn_fcode":"PPL",
    "qs:gn_local":3979770,
    "qs:gn_nam_loc":"Zapopan, Zapopan, Jalisco, MX",
    "qs:gn_namadm1":"16",
    "qs:gn_name":"El Fort\u00edn",
    "qs:local_max":794,
    "qs:local_sum":4209,
    "qs:localhoods":25,
    "qs:name":"El Fortin",
    "qs:name_adm0":"M\u00e9xico",
    "qs:name_adm1":"Jalisco",
    "qs:name_adm2":"Zapopan",
    "qs:name_local":"Zapopan",
    "qs:photo_max":3,
    "qs:photo_sum":7,
    "qs:placetype":"Suburb",
    "qs:quad_count":4,
    "qs:woe_adm0":23424900,
    "qs:woe_adm1":2346277,
    "qs:woe_adm2":12600313,
    "qs:woe_lau":0,
    "qs:woe_local":151582,
    "qs:woe_ver":"7.10.0",
    "wof:lang":[
        "spa"
    ],
    "wof:name":"El Fortin",
    "wof:placetype":"neighbourhood"
},
  "geometry": {"coordinates":[-103.491603,20.615525],"type":"Point"}
}