{
  "type": "Feature",
  "properties": {
    "gn:admin1_code":"11",
    "gn:admin2_code":"33",
    "gn:asciiname":"La Jarrilla",
    "gn:country_code":"MX",
    "gn:dem":2135,
    "gn:feature_class":"P",
    "gn:feature_code":"PPL",
    "gn:name":"La Jarrilla",
    "gn:population":43,
    "gn:timezone":"America/Mexico_City",
    "iso:country":"MX",
    "wof:name":"La Jarrilla",
    "wof:placetype":"locality",
    "wof:population":43
},
  "geometry": {"coordinates":[-100.54472,21.41972],"type":"Point"}
}