{
  "type": "Feature",
  "properties": {
    "gn:admin1_code":"25",
    "gn:admin2_code":"3.0",
    "gn:asciiname":"Milpillas",
    "gn:country_code":"MX",
    "gn:dem":576,
    "gn:feature_class":"P",
    "gn:feature_code":"PPL",
    "gn:name":"Milpillas",
    "gn:population":0,
    "gn:timezone":"America/Mazatlan",
    "iso:country":"MX",
    "name:spa_x_preferred":[
        "Milpillas"
    ],
    "wof:name":"Milpillas",
    "wof:placetype":"locality"
},
  "geometry": {"coordinates":[-107.54653,25.67738],"type":"Point"}
}