{
  "type": "Feature",
  "properties": {
    "gn:admin1_code":"30.0",
    "gn:admin2_code":"91.0",
    "gn:asciiname":"Tecolotlan",
    "gn:country_code":"MX",
    "gn:dem":26,
    "gn:feature_class":"P",
    "gn:feature_code":"PPL",
    "gn:name":"Tecolotl\u00e1n",
    "gn:population":0,
    "gn:timezone":"America/Mexico_City",
    "iso:country":"MX",
    "name:spa_x_preferred":[
        "Tecolotl\u00e1n"
    ],
    "wof:name":"Tecolotlan",
    "wof:placetype":"locality"
},
  "geometry": {"coordinates":[-94.97932,17.40491],"type":"Point"}
}