{
  "type": "Feature",
  "properties": {
    "gn:admin1_code":"30",
    "gn:admin2_code":"31.0",
    "gn:asciiname":"Mata Domingo",
    "gn:country_code":"MX",
    "gn:dem":261,
    "gn:feature_class":"P",
    "gn:feature_code":"PPL",
    "gn:name":"Mata Domingo",
    "gn:population":0,
    "gn:timezone":"America/Mexico_City",
    "iso:country":"MX",
    "wof:name":"Mata Domingo",
    "wof:placetype":"locality"
},
  "geometry": {"coordinates":[-96.60275,18.87503],"type":"Point"}
}