{
  "type": "Feature",
  "properties": {
    "gn:admin1_code":"26",
    "gn:admin2_code":"66.0",
    "gn:asciiname":"Rancho Grande",
    "gn:country_code":"MX",
    "gn:dem":365,
    "gn:feature_class":"P",
    "gn:feature_code":"PPL",
    "gn:name":"Rancho Grande",
    "gn:population":0,
    "gn:timezone":"America/Hermosillo",
    "iso:country":"MX",
    "name:spa_x_preferred":[
        "Rancho Grande"
    ],
    "wof:name":"Rancho Grande",
    "wof:placetype":"locality"
},
  "geometry": {"coordinates":[-110.52028,29.11278],"type":"Point"}
}