{
  "type": "Feature",
  "properties": {
    "gn:admin1_code":"5",
    "gn:admin2_code":"11",
    "gn:asciiname":"La Mesilla",
    "gn:country_code":"MX",
    "gn:dem":2060,
    "gn:feature_class":"P",
    "gn:feature_code":"PPL",
    "gn:name":"La Mesilla",
    "gn:population":52,
    "gn:timezone":"America/Mexico_City",
    "iso:country":"MX",
    "name:urd_x_preferred":[
        "\u0644\u0627 \u0645\u06cc\u0633\u06cc\u0644\u0627"
    ],
    "wof:name":"La Mesilla",
    "wof:placetype":"locality",
    "wof:population":52
},
  "geometry": {"coordinates":[-92.27500000000001,15.58444],"type":"Point"}
}