{
  "type": "Feature",
  "properties": {
    "gn:admin1_code":"14",
    "gn:admin2_code":"67.0",
    "gn:asciiname":"Los Carrizos",
    "gn:country_code":"MX",
    "gn:dem":29,
    "gn:feature_class":"P",
    "gn:feature_code":"PPL",
    "gn:name":"Los Carrizos",
    "gn:population":0,
    "gn:timezone":"America/Mexico_City",
    "iso:country":"MX",
    "name:spa_x_preferred":[
        "Los Carrizos"
    ],
    "wof:name":"Los Carrizos",
    "wof:placetype":"locality"
},
  "geometry": {"coordinates":[-105.25019,20.56921],"type":"Point"}
}