{
  "type": "Feature",
  "properties": {
    "gn:admin1_code":"11",
    "gn:admin2_code":"7",
    "gn:asciiname":"Granja el Monte [Fabrica de Muelles]",
    "gn:country_code":"MX",
    "gn:dem":1750,
    "gn:feature_class":"P",
    "gn:feature_code":"PPL",
    "gn:name":"Granja el Monte [F\u00e1brica de Muelles]",
    "gn:population":10,
    "gn:timezone":"America/Mexico_City",
    "iso:country":"MX",
    "name:und_x_variant":[
        "Granja el Monte [F\u00e1brica de Muelles]"
    ],
    "wof:name":"Granja el Monte [Fabrica de Muelles]",
    "wof:placetype":"locality",
    "wof:population":10
},
  "geometry": {"coordinates":[-100.8425,20.50111],"type":"Point"}
}