{
  "type": "Feature",
  "properties": {
    "gn:admin1_code":"26",
    "gn:admin2_code":"19.0",
    "gn:asciiname":"El Miller",
    "gn:country_code":"MX",
    "gn:dem":1318,
    "gn:feature_class":"P",
    "gn:feature_code":"PPL",
    "gn:name":"El Miller",
    "gn:population":0,
    "gn:timezone":"America/Hermosillo",
    "iso:country":"MX",
    "name:und_x_variant":[
        "Rancho El Miller",
        "El Miller"
    ],
    "wof:name":"El Miller",
    "wof:placetype":"locality"
},
  "geometry": {"coordinates":[-110.1033,30.88267],"type":"Point"}
}