{
  "type": "Feature",
  "properties": {
    "gn:admin1_code":"11",
    "gn:admin2_code":"34.0",
    "gn:asciiname":"El Zapote (El Miche)",
    "gn:country_code":"MX",
    "gn:dem":1612,
    "gn:feature_class":"P",
    "gn:feature_code":"PPL",
    "gn:name":"El Zapote (El Miche)",
    "gn:population":63,
    "gn:timezone":"America/Mexico_City",
    "iso:country":"MX",
    "wof:name":"El Zapote (El Miche)",
    "wof:placetype":"locality",
    "wof:population":63
},
  "geometry": {"coordinates":[-100.09999999999999,21.16583],"type":"Point"}
}