{
  "type": "Feature",
  "properties": {
    "gn:admin1_code":"14",
    "gn:admin2_code":"68.0",
    "gn:asciiname":"Las Chinas",
    "gn:country_code":"MX",
    "gn:dem":455,
    "gn:feature_class":"P",
    "gn:feature_code":"PPL",
    "gn:name":"Las Chinas",
    "gn:population":0,
    "gn:timezone":"America/Mexico_City",
    "iso:country":"MX",
    "name:spa_x_preferred":[
        "Las Chinas"
    ],
    "wof:name":"Las Chinas",
    "wof:placetype":"locality"
},
  "geometry": {"coordinates":[-104.69422,19.76812],"type":"Point"}
}