{
  "type": "Feature",
  "properties": {
    "gn:admin1_code":"16.0",
    "gn:admin2_code":"6.0",
    "gn:asciiname":"El Refugio",
    "gn:country_code":"MX",
    "gn:dem":254,
    "gn:feature_class":"P",
    "gn:feature_code":"PPL",
    "gn:name":"El Refugio",
    "gn:population":0,
    "gn:timezone":"America/Mexico_City",
    "iso:country":"MX",
    "name:spa_x_preferred":[
        "El Refugio"
    ],
    "wof:name":"El Refugio",
    "wof:placetype":"locality"
},
  "geometry": {"coordinates":[-102.44468000000001,19.08851],"type":"Point"}
}