{
  "type": "Feature",
  "properties": {
    "gn:admin1_code":"7",
    "gn:admin2_code":"27.0",
    "gn:asciiname":"San Pablo",
    "gn:country_code":"MX",
    "gn:dem":960,
    "gn:feature_class":"P",
    "gn:feature_code":"PPL",
    "gn:name":"San Pablo",
    "gn:population":1,
    "gn:timezone":"America/Monterrey",
    "iso:country":"MX",
    "name:spa_x_preferred":[
        "San Pablo"
    ],
    "wof:name":"San Pablo",
    "wof:placetype":"locality",
    "wof:population":1
},
  "geometry": {"coordinates":[-101.08616000000001,25.79892000000001],"type":"Point"}
}