{
  "type": "Feature",
  "properties": {
    "gn:admin1_code":"5",
    "gn:admin2_code":"12.0",
    "gn:asciiname":"El Chicozapote",
    "gn:country_code":"MX",
    "gn:dem":563,
    "gn:feature_class":"P",
    "gn:feature_code":"PPL",
    "gn:name":"El Chicozapote",
    "gn:population":0,
    "gn:timezone":"America/Mexico_City",
    "iso:country":"MX",
    "name:spa_x_preferred":[
        "El Chicozapote"
    ],
    "wof:name":"El Chicozapote",
    "wof:placetype":"locality"
},
  "geometry": {"coordinates":[-93.37654999999999,16.97214],"type":"Point"}
}