{
  "type": "Feature",
  "properties": {
    "gn:admin1_code":"6.0",
    "gn:admin2_code":"49.0",
    "gn:asciiname":"Humariza",
    "gn:country_code":"MX",
    "gn:dem":1753,
    "gn:feature_class":"P",
    "gn:feature_code":"PPL",
    "gn:name":"Humariza",
    "gn:population":323,
    "gn:timezone":"America/Chihuahua",
    "iso:country":"MX",
    "wof:name":"Humariza",
    "wof:placetype":"locality",
    "wof:population":323
},
  "geometry": {"coordinates":[-106.76778,27.26167],"type":"Point"}
}