{
  "type": "Feature",
  "properties": {
    "gn:admin1_code":"6.0",
    "gn:admin2_code":"11.0",
    "gn:asciiname":"El Aguaje",
    "gn:country_code":"MX",
    "gn:dem":1307,
    "gn:feature_class":"P",
    "gn:feature_code":"PPL",
    "gn:name":"El Aguaje",
    "gn:population":0,
    "gn:timezone":"America/Chihuahua",
    "iso:country":"MX",
    "name:spa_x_preferred":[
        "El Aguaje"
    ],
    "wof:name":"El Aguaje",
    "wof:placetype":"locality"
},
  "geometry": {"coordinates":[-104.02254000000001,27.96484],"type":"Point"}
}