{
  "type": "Feature",
  "properties": {
    "gn:admin1_code":"17",
    "gn:admin2_code":"15.0",
    "gn:asciiname":"Colonia Vista Hermosa",
    "gn:country_code":"MX",
    "gn:dem":1019,
    "gn:feature_class":"P",
    "gn:feature_code":"PPL",
    "gn:name":"Colonia Vista Hermosa",
    "gn:population":504,
    "gn:timezone":"America/Mexico_City",
    "iso:country":"MX",
    "wof:name":"Colonia Vista Hermosa",
    "wof:placetype":"locality",
    "wof:population":504
},
  "geometry": {"coordinates":[-99.35361,18.75722],"type":"Point"}
}