{
  "type": "Feature",
  "properties": {
    "gn:gn_country":"MX",
    "gn:gn_fcode":"PPL",
    "gn:gn_pop":0,
    "iso:country":"MX",
    "name:bpy_x_preferred":[
        "\u0995\u09be\u09b0\u09be\u0995\u09cb\u09b2"
    ],
    "name:ceb_x_preferred":[
        "Caracol"
    ],
    "name:deu_x_preferred":[
        "Caracol"
    ],
    "name:epo_x_preferred":[
        "Caracol"
    ],
    "name:fra_x_preferred":[
        "Caracol"
    ],
    "name:glg_x_preferred":[
        "El Caracol"
    ],
    "name:hrv_x_preferred":[
        "Caracol"
    ],
    "name:ind_x_preferred":[
        "Caracol"
    ],
    "name:ita_x_preferred":[
        "El Caracol"
    ],
    "name:jpn_x_preferred":[
        "\u30ab\u30e9\u30b3\u30eb"
    ],
    "name:lit_x_preferred":[
        "Karakolis"
    ],
    "name:mkd_x_preferred":[
        "\u041a\u0430\u0440\u0430\u043a\u043e\u043b"
    ],
    "name:nld_x_preferred":[
        "Caracol"
    ],
    "name:nor_x_preferred":[
        "Caracol"
    ],
    "name:pol_x_preferred":[
        "Caracol"
    ],
    "name:por_x_preferred":[
        "El Caracol"
    ],
    "name:rus_x_preferred":[
        "\u041a\u0430\u0440\u0430\u043a\u043e\u043b\u044c"
    ],
    "name:spa_x_preferred":[
        "El Caracol"
    ],
    "name:swa_x_preferred":[
        "Caracol"
    ],
    "name:swe_x_preferred":[
        "Caracol"
    ],
    "name:ukr_x_preferred":[
        "\u041a\u0430\u0440\u0430\u043a\u043e\u043b\u044c"
    ],
    "name:zho_x_preferred":[
        "\u5361\u62c9\u79d1\u5c14"
    ],
    "qs_pg:aaroncc":"MX",
    "qs_pg:gn_country":"MX",
    "qs_pg:gn_fcode":"PPL",
    "qs_pg:gn_pop":0,
    "qs_pg:name":"Caracol",
    "qs_pg:name_adm0":"M\u00e9xico",
    "qs_pg:name_adm1":"Nuevo Leon",
    "qs_pg:photos":127,
    "qs_pg:photos_1k":26,
    "qs_pg:photos_9k":1,
    "qs_pg:photos_9r":3,
    "qs_pg:photos_all":127,
    "qs_pg:photos_sr":3,
    "qs_pg:pop_sr":0,
    "qs_pg:qs_pg_placetype":"neighbourhood",
    "qs_pg:qs_pg_placetype_gp":"Suburb",
    "qs_pg:woe_adm0":23424900,
    "woe:adm0_id":23424900,
    "woe:name_adm0":"M\u00e9xico",
    "woe:name_adm1":"Nuevo Leon",
    "woe:placetype":"Suburb",
    "wof:name":"Caracol",
    "wof:placetype":"neighbourhood"
},
  "geometry": {"coordinates":[-100.06667,25.21667],"type":"Point"}
}