{
  "type": "Feature",
  "properties": {
    "gn:admin1_code":"2",
    "gn:admin2_code":"3",
    "gn:asciiname":"Rancho Vejar",
    "gn:country_code":"MX",
    "gn:dem":279,
    "gn:feature_class":"P",
    "gn:feature_code":"PPL",
    "gn:name":"Rancho V\u00e9jar",
    "gn:population":27,
    "gn:timezone":"America/Tijuana",
    "iso:country":"MX",
    "name:und_x_variant":[
        "Rancho V\u00e9jar"
    ],
    "wof:name":"Rancho Vejar",
    "wof:placetype":"locality",
    "wof:population":27
},
  "geometry": {"coordinates":[-116.60639,32.37333],"type":"Point"}
}