{
  "type": "Feature",
  "properties": {
    "gn:admin1_code":"12",
    "gn:admin2_code":"1.0",
    "gn:asciiname":"La Testaruda",
    "gn:country_code":"MX",
    "gn:dem":28,
    "gn:feature_class":"P",
    "gn:feature_code":"PPL",
    "gn:name":"La Testaruda",
    "gn:population":261,
    "gn:timezone":"America/Mexico_City",
    "iso:country":"MX",
    "wof:name":"La Testaruda",
    "wof:placetype":"locality",
    "wof:population":261
},
  "geometry": {"coordinates":[-99.78471999999999,16.88889],"type":"Point"}
}