{
  "type": "Feature",
  "properties": {
    "gn:admin1_code":"11.0",
    "gn:admin2_code":"30.0",
    "gn:asciiname":"Las Pilas del Sur",
    "gn:country_code":"MX",
    "gn:dem":2175,
    "gn:feature_class":"P",
    "gn:feature_code":"PPL",
    "gn:name":"Las Pilas del Sur",
    "gn:population":0,
    "gn:timezone":"America/Mexico_City",
    "iso:country":"MX",
    "name:spa_x_preferred":[
        "Las Pilas del Sur"
    ],
    "name:spa_x_variant":[
        "Las Pilas Sur"
    ],
    "wof:name":"Las Pilas del Sur",
    "wof:placetype":"locality"
},
  "geometry": {"coordinates":[-101.28292999999999,21.3713],"type":"Point"}
}