{
  "type": "Feature",
  "properties": {
    "gn:admin1_code":"21",
    "gn:admin2_code":"71.0",
    "gn:asciiname":"Los Capulines",
    "gn:country_code":"MX",
    "gn:dem":1544,
    "gn:feature_class":"P",
    "gn:feature_code":"PPL",
    "gn:name":"Los Capulines",
    "gn:population":121,
    "gn:timezone":"America/Mexico_City",
    "iso:country":"MX",
    "wof:name":"Los Capulines",
    "wof:placetype":"locality",
    "wof:population":121
},
  "geometry": {"coordinates":[-98.03221000000001,20.16106],"type":"Point"}
}