{
  "type": "Feature",
  "properties": {
    "gn:admin1_code":"10",
    "gn:admin2_code":"6.0",
    "gn:asciiname":"San Antonio de Zaragoza",
    "gn:country_code":"MX",
    "gn:dem":1246,
    "gn:feature_class":"P",
    "gn:feature_code":"PPL",
    "gn:name":"San Antonio de Zaragoza",
    "gn:population":0,
    "gn:timezone":"America/Monterrey",
    "iso:country":"MX",
    "name:spa_x_preferred":[
        "San Antonio de Zaragoza"
    ],
    "name:und_x_variant":[
        "San Antonio"
    ],
    "wof:name":"San Antonio de Zaragoza",
    "wof:placetype":"locality"
},
  "geometry": {"coordinates":[-103.4152,25.18359],"type":"Point"}
}