{
  "type": "Feature",
  "properties": {
    "gn:admin1_code":"32",
    "gn:admin2_code":"7",
    "gn:asciiname":"Majada San Isidro",
    "gn:country_code":"MX",
    "gn:dem":1779,
    "gn:feature_class":"P",
    "gn:feature_code":"PPL",
    "gn:name":"Majada San Isidro",
    "gn:population":40,
    "gn:timezone":"America/Mexico_City",
    "iso:country":"MX",
    "wof:name":"Majada San Isidro",
    "wof:placetype":"locality",
    "wof:population":40
},
  "geometry": {"coordinates":[-101.30777999999999,24.40389],"type":"Point"}
}