{
  "type": "Feature",
  "properties": {
    "gn:admin1_code":"6",
    "gn:admin2_code":"40.0",
    "gn:asciiname":"Las Pomas",
    "gn:country_code":"MX",
    "gn:dem":2098,
    "gn:feature_class":"P",
    "gn:feature_code":"PPL",
    "gn:name":"Las Pomas",
    "gn:population":0,
    "gn:timezone":"America/Chihuahua",
    "iso:country":"MX",
    "name:spa_x_preferred":[
        "Las Pomas"
    ],
    "name:und_x_variant":[
        "Rancho Arroyo Las Pomas"
    ],
    "wof:name":"Las Pomas",
    "wof:placetype":"locality"
},
  "geometry": {"coordinates":[-108.2342,29.65621],"type":"Point"}
}