{
  "type": "Feature",
  "properties": {
    "gn:admin1_code":"25.0",
    "gn:asciiname":"La Piedrera",
    "gn:country_code":"MX",
    "gn:dem":15,
    "gn:feature_class":"P",
    "gn:feature_code":"PPL",
    "gn:name":"La Piedrera",
    "gn:population":0,
    "gn:timezone":"America/Mazatlan",
    "iso:country":"MX",
    "name:spa_x_preferred":[
        "La Piedrera"
    ],
    "wof:name":"La Piedrera",
    "wof:placetype":"locality"
},
  "geometry": {"coordinates":[-108.87094,25.78076],"type":"Point"}
}