{
  "type": "Feature",
  "properties": {
    "gn:admin1_code":"22",
    "gn:admin2_code":"2.0",
    "gn:asciiname":"Carrizal de Adjuntas",
    "gn:country_code":"MX",
    "gn:dem":1402,
    "gn:feature_class":"P",
    "gn:feature_code":"PPL",
    "gn:name":"Carrizal de Adjuntas",
    "gn:population":88,
    "gn:timezone":"America/Mexico_City",
    "iso:country":"MX",
    "wof:name":"Carrizal de Adjuntas",
    "wof:placetype":"locality",
    "wof:population":88
},
  "geometry": {"coordinates":[-99.55833,21.22861],"type":"Point"}
}