{
  "type": "Feature",
  "properties": {
    "gn:admin1_code":"21",
    "gn:admin2_code":"185.0",
    "gn:asciiname":"Colonia las Palmas",
    "gn:country_code":"MX",
    "gn:dem":1408,
    "gn:feature_class":"P",
    "gn:feature_code":"PPL",
    "gn:name":"Colonia las Palmas",
    "gn:population":618,
    "gn:timezone":"America/Mexico_City",
    "iso:country":"MX",
    "wof:name":"Colonia las Palmas",
    "wof:placetype":"locality",
    "wof:population":618
},
  "geometry": {"coordinates":[-98.55,18.69639],"type":"Point"}
}