{
  "type": "Feature",
  "properties": {
    "gn:admin1_code":"11",
    "gn:admin2_code":"36",
    "gn:asciiname":"Francisco Villa",
    "gn:country_code":"MX",
    "gn:dem":1740,
    "gn:feature_class":"P",
    "gn:feature_code":"PPL",
    "gn:name":"Francisco Villa",
    "gn:population":32,
    "gn:timezone":"America/Mexico_City",
    "iso:country":"MX",
    "wof:name":"Francisco Villa",
    "wof:placetype":"locality",
    "wof:population":32
},
  "geometry": {"coordinates":[-100.99722,20.18111],"type":"Point"}
}