{
  "type": "Feature",
  "properties": {
    "gn:admin1_code":"7",
    "gn:admin2_code":"20.0",
    "gn:asciiname":"Rancho El Rincon",
    "gn:country_code":"MX",
    "gn:dem":432,
    "gn:feature_class":"P",
    "gn:feature_code":"PPL",
    "gn:name":"Rancho El Rinc\u00f3n",
    "gn:population":0,
    "gn:timezone":"America/Monterrey",
    "iso:country":"MX",
    "wof:name":"Rancho El Rincon",
    "wof:placetype":"locality"
},
  "geometry": {"coordinates":[-101.51667,27.95],"type":"Point"}
}