{
  "type": "Feature",
  "properties": {
    "gn:admin1_code":"14",
    "gn:admin2_code":"42",
    "gn:asciiname":"Los Llanos",
    "gn:country_code":"MX",
    "gn:dem":1852,
    "gn:feature_class":"P",
    "gn:feature_code":"PPL",
    "gn:name":"Los Llanos",
    "gn:population":42,
    "gn:timezone":"America/Mexico_City",
    "iso:country":"MX",
    "wof:name":"Los Llanos",
    "wof:placetype":"locality",
    "wof:population":42
},
  "geometry": {"coordinates":[-103.90416999999999,22.40889],"type":"Point"}
}