{
  "type": "Feature",
  "properties": {
    "gn:admin1_code":"20",
    "gn:admin2_code":"407",
    "gn:asciiname":"Los Cimientos",
    "gn:country_code":"MX",
    "gn:dem":912,
    "gn:feature_class":"P",
    "gn:feature_code":"PPL",
    "gn:name":"Los Cimientos",
    "gn:population":17,
    "gn:timezone":"America/Mexico_City",
    "iso:country":"MX",
    "wof:name":"Los Cimientos",
    "wof:placetype":"locality",
    "wof:population":17
},
  "geometry": {"coordinates":[-94.09889,16.83639],"type":"Point"}
}