{
  "type": "Feature",
  "properties": {
    "gn:admin1_code":"30",
    "gn:admin2_code":"36.0",
    "gn:asciiname":"La Ventana",
    "gn:country_code":"MX",
    "gn:dem":2269,
    "gn:feature_class":"P",
    "gn:feature_code":"PPL",
    "gn:name":"La Ventana",
    "gn:population":153,
    "gn:timezone":"America/Mexico_City",
    "iso:country":"MX",
    "wof:name":"La Ventana",
    "wof:placetype":"locality",
    "wof:population":153
},
  "geometry": {"coordinates":[-96.96167,19.71167],"type":"Point"}
}