{
  "type": "Feature",
  "properties": {
    "gn:admin1_code":"24",
    "gn:admin2_code":"6.0",
    "gn:asciiname":"Rancho Nebtashi",
    "gn:country_code":"MX",
    "gn:dem":1893,
    "gn:feature_class":"P",
    "gn:feature_code":"PPL",
    "gn:name":"Rancho Nebtashi",
    "gn:population":0,
    "gn:timezone":"America/Mexico_City",
    "iso:country":"MX",
    "name:spa_x_preferred":[
        "Rancho Nebtashi"
    ],
    "name:spa_x_variant":[
        "Tigre Azul"
    ],
    "wof:name":"Rancho Nebtashi",
    "wof:placetype":"locality"
},
  "geometry": {"coordinates":[-101.09014999999999,23.5577],"type":"Point"}
}