{
  "type": "Feature",
  "properties": {
    "gn:admin1_code":"17",
    "gn:admin2_code":"29.0",
    "gn:asciiname":"Campo Ixtonclal",
    "gn:country_code":"MX",
    "gn:dem":1247,
    "gn:feature_class":"P",
    "gn:feature_code":"PPL",
    "gn:name":"Campo Ixtonclal",
    "gn:population":125,
    "gn:timezone":"America/Mexico_City",
    "iso:country":"MX",
    "wof:name":"Campo Ixtonclal",
    "wof:placetype":"locality",
    "wof:population":125
},
  "geometry": {"coordinates":[-99.07701,18.898],"type":"Point"}
}