{
  "type": "Feature",
  "properties": {
    "gn:admin1_code":"5.0",
    "gn:admin2_code":"31.0",
    "gn:asciiname":"Jol Diamante",
    "gn:country_code":"MX",
    "gn:dem":677,
    "gn:feature_class":"P",
    "gn:feature_code":"PPL",
    "gn:name":"Jol Diamante",
    "gn:population":0,
    "gn:timezone":"America/Mexico_City",
    "iso:country":"MX",
    "name:spa_x_preferred":[
        "Jol Diamante"
    ],
    "wof:name":"Jol Diamante",
    "wof:placetype":"locality"
},
  "geometry": {"coordinates":[-91.75924999999999,17.12927],"type":"Point"}
}