{
  "type": "Feature",
  "properties": {
    "gn:admin1_code":"23",
    "gn:admin2_code":"4",
    "gn:asciiname":"Aaron Merino [Colonia]",
    "gn:country_code":"MX",
    "gn:dem":19,
    "gn:feature_class":"P",
    "gn:feature_code":"PPL",
    "gn:name":"Aar\u00f3n Merino [Colonia]",
    "gn:population":46,
    "gn:timezone":"America/Cancun",
    "iso:country":"MX",
    "name:und_x_variant":[
        "Aar\u00f3n Merino [Colonia]"
    ],
    "wof:name":"Aaron Merino [Colonia]",
    "wof:placetype":"locality",
    "wof:population":46
},
  "geometry": {"coordinates":[-88.38861,18.70611],"type":"Point"}
}