{
  "type": "Feature",
  "properties": {
    "gn:admin1_code":"6",
    "gn:admin2_code":"20.0",
    "gn:asciiname":"Guiciego",
    "gn:country_code":"MX",
    "gn:dem":1679,
    "gn:feature_class":"P",
    "gn:feature_code":"PPL",
    "gn:name":"Guiciego",
    "gn:population":0,
    "gn:timezone":"America/Chihuahua",
    "iso:country":"MX",
    "name:spa_x_preferred":[
        "Guiciego"
    ],
    "wof:name":"Guiciego",
    "wof:placetype":"locality"
},
  "geometry": {"coordinates":[-108.64828,27.68168],"type":"Point"}
}