{
  "type": "Feature",
  "properties": {
    "gn:admin1_code":"32",
    "gn:admin2_code":"36.0",
    "gn:asciiname":"Rancho la Gripa (El Gringo)",
    "gn:country_code":"MX",
    "gn:dem":2100,
    "gn:feature_class":"P",
    "gn:feature_code":"PPL",
    "gn:name":"Rancho la Gripa (El Gringo)",
    "gn:population":5,
    "gn:timezone":"America/Mexico_City",
    "iso:country":"MX",
    "wof:name":"Rancho la Gripa (El Gringo)",
    "wof:placetype":"locality",
    "wof:population":5
},
  "geometry": {"coordinates":[-102.23027999999999,22.63972],"type":"Point"}
}