{
  "type": "Feature",
  "properties": {
    "gn:admin1_code":"19",
    "gn:admin2_code":"7.0",
    "gn:asciiname":"San Ignacio de Torres",
    "gn:cc2":"MX",
    "gn:country_code":"MX",
    "gn:dem":2305,
    "gn:feature_class":"P",
    "gn:feature_code":"PPL",
    "gn:name":"San Ignacio de Torres",
    "gn:population":0,
    "gn:timezone":"America/Monterrey",
    "iso:country":"MX",
    "name:und_x_variant":[
        "San Ignacio",
        "San Ignacio de Torres"
    ],
    "wof:name":"San Ignacio de Torres",
    "wof:placetype":"locality"
},
  "geometry": {"coordinates":[-99.96666999999999,24.06667],"type":"Point"}
}