{
  "type": "Feature",
  "properties": {
    "gn:admin1_code":"25",
    "gn:admin2_code":"3.0",
    "gn:asciiname":"La Huerta",
    "gn:country_code":"MX",
    "gn:dem":310,
    "gn:feature_class":"P",
    "gn:feature_code":"PPL",
    "gn:name":"La Huerta",
    "gn:population":0,
    "gn:timezone":"America/Mazatlan",
    "iso:country":"MX",
    "name:spa_x_preferred":[
        "La Huerta de Arriba"
    ],
    "name:spa_x_variant":[
        "La Huerta"
    ],
    "wof:name":"La Huerta",
    "wof:placetype":"locality"
},
  "geometry": {"coordinates":[-107.6177,25.49897],"type":"Point"}
}