{
  "type": "Feature",
  "properties": {
    "gn:admin1_code":"20",
    "gn:admin2_code":"235.0",
    "gn:asciiname":"Lachiguizo",
    "gn:country_code":"MX",
    "gn:dem":1403,
    "gn:feature_class":"P",
    "gn:feature_code":"PPL",
    "gn:name":"Lachiguizo",
    "gn:population":102,
    "gn:timezone":"America/Mexico_City",
    "iso:country":"MX",
    "wof:name":"Lachiguizo",
    "wof:placetype":"locality",
    "wof:population":102
},
  "geometry": {"coordinates":[-96.52992999999999,16.42942],"type":"Point"}
}