{
  "type": "Feature",
  "properties": {
    "gn:admin1_code":"28",
    "gn:admin2_code":"29.0",
    "gn:asciiname":"Rancho Nuevo (Lee Taylor)",
    "gn:country_code":"MX",
    "gn:dem":150,
    "gn:feature_class":"P",
    "gn:feature_code":"PPL",
    "gn:name":"Rancho Nuevo (Lee Taylor)",
    "gn:population":1,
    "gn:timezone":"America/Monterrey",
    "iso:country":"MX",
    "wof:name":"Rancho Nuevo (Lee Taylor)",
    "wof:placetype":"locality",
    "wof:population":1
},
  "geometry": {"coordinates":[-99.19361000000001,22.87722],"type":"Point"}
}