{
  "type": "Feature",
  "properties": {
    "gn:admin1_code":"17",
    "gn:admin2_code":"9.0",
    "gn:asciiname":"Maria del Socorro",
    "gn:country_code":"MX",
    "gn:dem":2771,
    "gn:feature_class":"P",
    "gn:feature_code":"PPL",
    "gn:name":"Mar\u00eda del Socorro",
    "gn:population":0,
    "gn:timezone":"America/Mexico_City",
    "iso:country":"MX",
    "name:spa_x_preferred":[
        "Mar\u00eda del Socorro"
    ],
    "wof:name":"Maria del Socorro",
    "wof:placetype":"locality"
},
  "geometry": {"coordinates":[-99.26539,19.04981],"type":"Point"}
}