{
  "type": "Feature",
  "properties": {
    "gn:admin1_code":"26",
    "gn:admin2_code":"29.0",
    "gn:asciiname":"El Cautivo",
    "gn:country_code":"MX",
    "gn:dem":87,
    "gn:feature_class":"P",
    "gn:feature_code":"PPL",
    "gn:name":"El Cautivo",
    "gn:population":0,
    "gn:timezone":"America/Hermosillo",
    "iso:country":"MX",
    "name:spa_x_preferred":[
        "El Cautivo"
    ],
    "name:und_x_variant":[
        "Rancho El Cautivo"
    ],
    "wof:name":"El Cautivo",
    "wof:placetype":"locality"
},
  "geometry": {"coordinates":[-110.7097,28.22548],"type":"Point"}
}