{
  "type": "Feature",
  "properties": {
    "gn:admin1_code":"10",
    "gn:admin2_code":"14.0",
    "gn:asciiname":"Bajio de Milpillas (Tierra Sonando)",
    "gn:country_code":"MX",
    "gn:dem":2026,
    "gn:feature_class":"P",
    "gn:feature_code":"PPL",
    "gn:name":"Baj\u00edo de Milpillas (Tierra Sonando)",
    "gn:population":226,
    "gn:timezone":"America/Monterrey",
    "iso:country":"MX",
    "name:und_x_variant":[
        "Baj\u00edo de Milpillas (Tierra Sonando)"
    ],
    "wof:name":"Bajio de Milpillas (Tierra Sonando)",
    "wof:placetype":"locality",
    "wof:population":226
},
  "geometry": {"coordinates":[-104.6275,22.99583],"type":"Point"}
}