{
  "type": "Feature",
  "properties": {
    "gn:admin1_code":"14",
    "gn:admin2_code":"93.0",
    "gn:asciiname":"Lavadero",
    "gn:country_code":"MX",
    "gn:dem":2005,
    "gn:feature_class":"P",
    "gn:feature_code":"PPL",
    "gn:name":"Lavadero",
    "gn:population":0,
    "gn:timezone":"America/Mexico_City",
    "iso:country":"MX",
    "name:spa_x_preferred":[
        "Lavadero"
    ],
    "wof:name":"Lavadero",
    "wof:placetype":"locality"
},
  "geometry": {"coordinates":[-102.55732999999999,20.85046],"type":"Point"}
}