{
  "type": "Feature",
  "properties": {
    "gn:admin1_code":"7",
    "gn:admin2_code":"6.0",
    "gn:asciiname":"Tres Marias",
    "gn:country_code":"MX",
    "gn:dem":815,
    "gn:feature_class":"P",
    "gn:feature_code":"PPL",
    "gn:name":"Tres Mar\u00edas",
    "gn:population":0,
    "gn:timezone":"America/Monterrey",
    "iso:country":"MX",
    "wof:name":"Tres Marias",
    "wof:placetype":"locality"
},
  "geometry": {"coordinates":[-101.17547,26.49726],"type":"Point"}
}