{
  "type": "Feature",
  "properties": {
    "gn:admin1_code":"10.0",
    "gn:admin2_code":"14.0",
    "gn:asciiname":"Los Crucitos",
    "gn:country_code":"MX",
    "gn:dem":907,
    "gn:feature_class":"P",
    "gn:feature_code":"PPL",
    "gn:name":"Los Crucitos",
    "gn:population":0,
    "gn:timezone":"America/Mazatlan",
    "iso:country":"MX",
    "name:spa_x_preferred":[
        "Los Crucitos"
    ],
    "wof:name":"Los Crucitos",
    "wof:placetype":"locality"
},
  "geometry": {"coordinates":[-104.88697999999999,22.611],"type":"Point"}
}