{
  "type": "Feature",
  "properties": {
    "gn:admin1_code":"16",
    "gn:admin2_code":"9.0",
    "gn:asciiname":"La Campana",
    "gn:country_code":"MX",
    "gn:dem":1837,
    "gn:feature_class":"P",
    "gn:feature_code":"PPL",
    "gn:name":"La Campana",
    "gn:population":72,
    "gn:timezone":"America/Mexico_City",
    "iso:country":"MX",
    "wof:name":"La Campana",
    "wof:placetype":"locality",
    "wof:population":72
},
  "geometry": {"coordinates":[-101.66556,19.10222000000001],"type":"Point"}
}