{
  "type": "Feature",
  "properties": {
    "gn:admin1_code":"32",
    "gn:admin2_code":"55",
    "gn:asciiname":"Colonia Miguel Hidalgo (El Saucillo)",
    "gn:country_code":"MX",
    "gn:dem":2293,
    "gn:feature_class":"P",
    "gn:feature_code":"PPL",
    "gn:name":"Colonia Miguel Hidalgo (El Saucillo)",
    "gn:population":36,
    "gn:timezone":"America/Mexico_City",
    "iso:country":"MX",
    "wof:name":"Colonia Miguel Hidalgo (El Saucillo)",
    "wof:placetype":"locality",
    "wof:population":36
},
  "geometry": {"coordinates":[-103.06,22.06444],"type":"Point"}
}