{
  "type": "Feature",
  "properties": {
    "gn:admin1_code":"32",
    "gn:admin2_code":"42.0",
    "gn:asciiname":"San Juan de la Tapia",
    "gn:country_code":"MX",
    "gn:dem":2149,
    "gn:feature_class":"P",
    "gn:feature_code":"PPL",
    "gn:name":"San Juan de la Tapia",
    "gn:population":0,
    "gn:timezone":"America/Mexico_City",
    "iso:country":"MX",
    "name:und_x_variant":[
        "Juan Tapia",
        "San Juan Tapia",
        "San Juan de la Tapia"
    ],
    "wof:name":"San Juan de la Tapia",
    "wof:placetype":"locality"
},
  "geometry": {"coordinates":[-103.6923,23.49868],"type":"Point"}
}