{
  "type": "Feature",
  "properties": {
    "gn:admin1_code":"32.0",
    "gn:admin2_code":"18.0",
    "gn:asciiname":"Jesus Maria",
    "gn:country_code":"MX",
    "gn:dem":1799,
    "gn:feature_class":"P",
    "gn:feature_code":"PPL",
    "gn:name":"Jes\u00fas Mar\u00eda",
    "gn:population":0,
    "gn:timezone":"America/Mexico_City",
    "iso:country":"MX",
    "name:spa_x_preferred":[
        "Jes\u00fas Mar\u00eda"
    ],
    "wof:name":"Jesus Maria",
    "wof:placetype":"locality"
},
  "geometry": {"coordinates":[-103.06627,21.82751],"type":"Point"}
}