{
  "type": "Feature",
  "properties": {
    "gn:admin1_code":"6.0",
    "gn:admin2_code":"29.0",
    "gn:asciiname":"Rancho Colorado",
    "gn:country_code":"MX",
    "gn:dem":949,
    "gn:feature_class":"P",
    "gn:feature_code":"PPL",
    "gn:name":"Rancho Colorado",
    "gn:population":0,
    "gn:timezone":"America/Chihuahua",
    "iso:country":"MX",
    "name:spa_x_preferred":[
        "Rancho Colorado"
    ],
    "wof:name":"Rancho Colorado",
    "wof:placetype":"locality"
},
  "geometry": {"coordinates":[-107.16898999999999,26.53399000000001],"type":"Point"}
}