{
  "type": "Feature",
  "properties": {
    "gn:admin1_code":"7",
    "gn:admin2_code":"24.0",
    "gn:asciiname":"Lavaderos",
    "gn:country_code":"MX",
    "gn:dem":1537,
    "gn:feature_class":"P",
    "gn:feature_code":"PPL",
    "gn:name":"Lavaderos",
    "gn:population":0,
    "gn:timezone":"America/Monterrey",
    "iso:country":"MX",
    "name:und_x_variant":[
        "Tanque de Lavaderos"
    ],
    "wof:name":"Lavaderos",
    "wof:placetype":"locality"
},
  "geometry": {"coordinates":[-101.81102,25.03863],"type":"Point"}
}