{
  "type": "Feature",
  "properties": {
    "gn:admin1_code":"20",
    "gn:admin2_code":"125.0",
    "gn:asciiname":"Xavagnia",
    "gn:cc2":"MX",
    "gn:country_code":"MX",
    "gn:dem":1093,
    "gn:feature_class":"P",
    "gn:feature_code":"PPL",
    "gn:name":"Xavagnia",
    "gn:population":0,
    "gn:timezone":"America/Mexico_City",
    "iso:country":"MX",
    "name:und_x_variant":[
        "Xovaguia",
        "Xavagnia"
    ],
    "wof:name":"Xavagnia",
    "wof:placetype":"locality"
},
  "geometry": {"coordinates":[-95.78333000000001,16.81667],"type":"Point"}
}