{
  "type": "Feature",
  "properties": {
    "gn:admin1_code":"16.0",
    "gn:admin2_code":"2.0",
    "gn:asciiname":"El Fresnal",
    "gn:country_code":"MX",
    "gn:dem":1269,
    "gn:feature_class":"P",
    "gn:feature_code":"PPL",
    "gn:name":"El Fresnal",
    "gn:population":0,
    "gn:timezone":"America/Mexico_City",
    "iso:country":"MX",
    "name:spa_x_preferred":[
        "El Fresnal"
    ],
    "name:spa_x_variant":[
        "El Limoncito"
    ],
    "wof:name":"El Fresnal",
    "wof:placetype":"locality"
},
  "geometry": {"coordinates":[-102.81026,18.6834],"type":"Point"}
}