{
  "type": "Feature",
  "properties": {
    "gn:country":"MX",
    "gn:fcode":"PPL",
    "gn:population":0,
    "iso:country":"MX",
    "name:und_x_variant":[
        "Cuyo"
    ],
    "qs_pg:aaroncc":"MX",
    "qs_pg:gn_country":"MX",
    "qs_pg:gn_fcode":"PPL",
    "qs_pg:gn_pop":0,
    "qs_pg:name":"El Cuyo",
    "qs_pg:name_adm0":"M\u00e9xico",
    "qs_pg:name_adm1":"Yucatan",
    "qs_pg:photos":1046,
    "qs_pg:photos_1k":212,
    "qs_pg:photos_9k":5,
    "qs_pg:photos_9r":7,
    "qs_pg:photos_all":1046,
    "qs_pg:photos_sr":11,
    "qs_pg:pop_sr":0,
    "qs_pg:qs_pg_placetype":"locality",
    "qs_pg:qs_pg_placetype_gp":"Town",
    "qs_pg:woe_adm0":23424900,
    "woe:adm0_id":23424900,
    "woe:name_adm0":"M\u00e9xico",
    "woe:name_adm1":"Yucatan",
    "woe:placetype":"Town",
    "wof:name":"El Cuyo",
    "wof:placetype":"locality"
},
  "geometry": {"coordinates":[-87.67838999999999,21.51538],"type":"Point"}
}