{
  "type": "Feature",
  "properties": {
    "gn:admin1_code":"14.0",
    "gn:admin2_code":"90.0",
    "gn:asciiname":"La Bofetada",
    "gn:country_code":"MX",
    "gn:dem":1485,
    "gn:feature_class":"P",
    "gn:feature_code":"PPL",
    "gn:name":"La Bofetada",
    "gn:population":0,
    "gn:timezone":"America/Mexico_City",
    "iso:country":"MX",
    "name:spa_x_preferred":[
        "La Bofetada"
    ],
    "wof:name":"La Bofetada",
    "wof:placetype":"locality"
},
  "geometry": {"coordinates":[-104.1713,20.22508],"type":"Point"}
}