{
  "type": "Feature",
  "properties": {
    "gn:admin1_code":"14",
    "gn:admin2_code":"53.0",
    "gn:asciiname":"Tamara",
    "gn:country_code":"MX",
    "gn:dem":2302,
    "gn:feature_class":"P",
    "gn:feature_code":"PPL",
    "gn:name":"T\u00e1mara",
    "gn:population":0,
    "gn:timezone":"America/Mexico_City",
    "iso:country":"MX",
    "wof:name":"Tamara",
    "wof:placetype":"locality"
},
  "geometry": {"coordinates":[-101.91667,21.58333],"type":"Point"}
}