{
  "type": "Feature",
  "properties": {
    "gn:admin1_code":"11.0",
    "gn:admin2_code":"18.0",
    "gn:asciiname":"Hacienda de la Bolsa",
    "gn:country_code":"MX",
    "gn:dem":1748,
    "gn:feature_class":"P",
    "gn:feature_code":"PPL",
    "gn:name":"Hacienda de la Bolsa",
    "gn:population":0,
    "gn:timezone":"America/Mexico_City",
    "iso:country":"MX",
    "name:spa_x_preferred":[
        "Hacienda de la Bolsa"
    ],
    "name:spa_x_variant":[
        "La Bolsa"
    ],
    "wof:name":"Hacienda de la Bolsa",
    "wof:placetype":"locality"
},
  "geometry": {"coordinates":[-101.10424999999999,20.37524],"type":"Point"}
}