{
  "type": "Feature",
  "properties": {
    "gn:admin1_code":"18",
    "gn:admin2_code":"4.0",
    "gn:asciiname":"El Canal",
    "gn:country_code":"MX",
    "gn:dem":13,
    "gn:feature_class":"P",
    "gn:feature_code":"PPL",
    "gn:name":"El Canal",
    "gn:population":0,
    "gn:timezone":"America/Mazatlan",
    "iso:country":"MX",
    "name:spa_x_preferred":[
        "El Canal"
    ],
    "wof:name":"El Canal",
    "wof:placetype":"locality"
},
  "geometry": {"coordinates":[-105.16236000000001,21.22647000000001],"type":"Point"}
}