{
  "type": "Feature",
  "properties": {
    "gn:admin1_code":"14.0",
    "gn:admin2_code":"81.0",
    "gn:asciiname":"San Antonio de Cabreras",
    "gn:country_code":"MX",
    "gn:dem":1812,
    "gn:feature_class":"P",
    "gn:feature_code":"PPL",
    "gn:name":"San Antonio de Cabreras",
    "gn:population":0,
    "gn:timezone":"America/Mexico_City",
    "iso:country":"MX",
    "name:spa_x_preferred":[
        "San Antonio de Cabreras"
    ],
    "wof:name":"San Antonio de Cabreras",
    "wof:placetype":"locality"
},
  "geometry": {"coordinates":[-103.20801,22.15094],"type":"Point"}
}