{
  "type": "Feature",
  "properties": {
    "gn:admin1_code":"14.0",
    "gn:admin2_code":"18.0",
    "gn:asciiname":"La Lastima",
    "gn:country_code":"MX",
    "gn:dem":1581,
    "gn:feature_class":"P",
    "gn:feature_code":"PPL",
    "gn:name":"La L\u00e1stima",
    "gn:population":0,
    "gn:timezone":"America/Mexico_City",
    "iso:country":"MX",
    "name:spa_x_preferred":[
        "La L\u00e1stima"
    ],
    "wof:name":"La Lastima",
    "wof:placetype":"locality"
},
  "geometry": {"coordinates":[-102.51888,20.4272],"type":"Point"}
}