{
  "type": "Feature",
  "properties": {
    "gn:admin1_code":"10",
    "gn:admin2_code":"23.0",
    "gn:asciiname":"Los Charcos",
    "gn:country_code":"MX",
    "gn:dem":2731,
    "gn:feature_class":"P",
    "gn:feature_code":"PPL",
    "gn:name":"Los Charcos",
    "gn:population":5,
    "gn:timezone":"America/Monterrey",
    "iso:country":"MX",
    "wof:name":"Los Charcos",
    "wof:placetype":"locality",
    "wof:population":5
},
  "geometry": {"coordinates":[-105.53227,23.78872],"type":"Point"}
}