{
  "type": "Feature",
  "properties": {
    "gn:admin1_code":"21",
    "gn:admin2_code":"175.0",
    "gn:asciiname":"Ingeniero Cuauhtemoc Cardenas Segunda Seccion",
    "gn:country_code":"MX",
    "gn:dem":1970,
    "gn:feature_class":"P",
    "gn:feature_code":"PPL",
    "gn:name":"Ingeniero Cuauht\u00e9moc C\u00e1rdenas Segunda Secci\u00f3n",
    "gn:population":143,
    "gn:timezone":"America/Mexico_City",
    "iso:country":"MX",
    "name:und_x_variant":[
        "Ingeniero Cuauht\u00e9moc C\u00e1rdenas Segunda Secci\u00f3n"
    ],
    "wof:name":"Ingeniero Cuauhtemoc Cardenas Segunda Seccion",
    "wof:placetype":"locality",
    "wof:population":143
},
  "geometry": {"coordinates":[-98.4675,18.94056],"type":"Point"}
}