{
  "type": "Feature",
  "properties": {
    "gn:admin1_code":"12.0",
    "gn:admin2_code":"62.0",
    "gn:asciiname":"Yoloxochil",
    "gn:country_code":"MX",
    "gn:dem":842,
    "gn:feature_class":"P",
    "gn:feature_code":"PPL",
    "gn:name":"Yoloxochil",
    "gn:population":0,
    "gn:timezone":"America/Mexico_City",
    "iso:country":"MX",
    "name:spa_x_preferred":[
        "Yoloxochil"
    ],
    "wof:name":"Yoloxochil",
    "wof:placetype":"locality"
},
  "geometry": {"coordinates":[-98.22204000000001,17.00703],"type":"Point"}
}