{
  "type": "Feature",
  "properties": {
    "gn:admin1_code":"25",
    "gn:admin2_code":"6",
    "gn:asciiname":"Huerta la Marina",
    "gn:country_code":"MX",
    "gn:dem":28,
    "gn:feature_class":"P",
    "gn:feature_code":"PPL",
    "gn:name":"Huerta la Marina",
    "gn:population":14,
    "gn:timezone":"America/Mazatlan",
    "iso:country":"MX",
    "wof:name":"Huerta la Marina",
    "wof:placetype":"locality",
    "wof:population":14
},
  "geometry": {"coordinates":[-107.54074,24.77346],"type":"Point"}
}