{
  "type": "Feature",
  "properties": {
    "gn:admin1_code":"7",
    "gn:admin2_code":"23.0",
    "gn:asciiname":"La Presa de Maria Rebeca",
    "gn:country_code":"MX",
    "gn:dem":1215,
    "gn:feature_class":"P",
    "gn:feature_code":"PPL",
    "gn:name":"La Presa de Mar\u00eda Rebeca",
    "gn:population":0,
    "gn:timezone":"America/Monterrey",
    "iso:country":"MX",
    "name:spa_x_preferred":[
        "La Presa de Mar\u00eda Rebeca"
    ],
    "name:und_x_variant":[
        "Rancho La Presa de Mar\u00eda Rebeca",
        "La Presa Mar\u00eda Rebeca"
    ],
    "wof:name":"La Presa de Maria Rebeca",
    "wof:placetype":"locality"
},
  "geometry": {"coordinates":[-102.50955,27.94814],"type":"Point"}
}