{
  "type": "Feature",
  "properties": {
    "gn:admin1_code":"26",
    "gn:admin2_code":"30.0",
    "gn:asciiname":"Los Pozos",
    "gn:country_code":"MX",
    "gn:dem":409,
    "gn:feature_class":"P",
    "gn:feature_code":"PPL",
    "gn:name":"Los Pozos",
    "gn:population":0,
    "gn:timezone":"America/Hermosillo",
    "iso:country":"MX",
    "name:spa_x_preferred":[
        "Los Pozos"
    ],
    "wof:name":"Los Pozos",
    "wof:placetype":"locality"
},
  "geometry": {"coordinates":[-110.65142,29.36443],"type":"Point"}
}