{
  "type": "Feature",
  "properties": {
    "gn:admin1_code":"25",
    "gn:admin2_code":"10.0",
    "gn:asciiname":"Bachihui",
    "gn:country_code":"MX",
    "gn:dem":499,
    "gn:feature_class":"P",
    "gn:feature_code":"PPL",
    "gn:name":"Bachihui",
    "gn:population":0,
    "gn:timezone":"America/Mazatlan",
    "iso:country":"MX",
    "name:spa_x_preferred":[
        "Bachihui"
    ],
    "wof:name":"Bachihui",
    "wof:placetype":"locality"
},
  "geometry": {"coordinates":[-108.3419,26.46689000000001],"type":"Point"}
}