{
  "type": "Feature",
  "properties": {
    "gn:admin1_code":"5",
    "gn:admin2_code":"38.0",
    "gn:asciiname":"Doce de Octubre",
    "gn:country_code":"MX",
    "gn:dem":1762,
    "gn:feature_class":"P",
    "gn:feature_code":"PPL",
    "gn:name":"Doce de Octubre",
    "gn:population":84,
    "gn:timezone":"America/Mexico_City",
    "iso:country":"MX",
    "wof:name":"Doce de Octubre",
    "wof:placetype":"locality",
    "wof:population":84
},
  "geometry": {"coordinates":[-92.34444000000001,16.68778],"type":"Point"}
}