{
  "type": "Feature",
  "properties": {
    "gn:admin1_code":"30",
    "gn:admin2_code":"110.0",
    "gn:asciiname":"Ayahualulco",
    "gn:country_code":"MX",
    "gn:dem":1621,
    "gn:feature_class":"P",
    "gn:feature_code":"PPL",
    "gn:name":"Ayahualulco",
    "gn:population":421,
    "gn:timezone":"America/Mexico_City",
    "iso:country":"MX",
    "wof:name":"Ayahualulco",
    "wof:placetype":"locality",
    "wof:population":421
},
  "geometry": {"coordinates":[-97.015,18.60556],"type":"Point"}
}