{
  "type": "Feature",
  "properties": {
    "gn:admin1_code":"11.0",
    "gn:admin2_code":"33.0",
    "gn:asciiname":"Jalapa",
    "gn:country_code":"MX",
    "gn:dem":1960,
    "gn:feature_class":"P",
    "gn:feature_code":"PPL",
    "gn:name":"Jalapa",
    "gn:population":0,
    "gn:timezone":"America/Mexico_City",
    "iso:country":"MX",
    "name:ben_x_preferred":[
        "\u099c\u09be\u09b2\u09be\u09aa\u09be"
    ],
    "name:ell_x_preferred":[
        "\u03a7\u03b1\u03bb\u03ac\u03c0\u03b1"
    ],
    "name:heb_x_preferred":[
        "\u05d2'\u05dc\u05e4\u05d4"
    ],
    "name:hin_x_preferred":[
        "\u091c\u0932\u093e\u092a\u093e"
    ],
    "name:hun_x_preferred":[
        "Jalapa"
    ],
    "name:ind_x_preferred":[
        "Jalapa"
    ],
    "name:spa_x_preferred":[
        "Jalapa"
    ],
    "name:tur_x_preferred":[
        "Jalapa"
    ],
    "name:vie_x_preferred":[
        "Jalapa"
    ],
    "wof:name":"Jalapa",
    "wof:placetype":"locality"
},
  "geometry": {"coordinates":[-100.38127,21.3593],"type":"Point"}
}