{
  "type": "Feature",
  "properties": {
    "gn:admin1_code":"14",
    "gn:admin2_code":"8",
    "gn:asciiname":"El Puertecito",
    "gn:country_code":"MX",
    "gn:dem":2093,
    "gn:feature_class":"P",
    "gn:feature_code":"PPL",
    "gn:name":"El Puertecito",
    "gn:population":26,
    "gn:timezone":"America/Mexico_City",
    "iso:country":"MX",
    "wof:name":"El Puertecito",
    "wof:placetype":"locality",
    "wof:population":26
},
  "geometry": {"coordinates":[-102.29583,20.84917],"type":"Point"}
}