{
  "type": "Feature",
  "properties": {
    "gn:admin1_code":"6",
    "gn:admin2_code":"63.0",
    "gn:asciiname":"El Refugio",
    "gn:country_code":"MX",
    "gn:dem":1614,
    "gn:feature_class":"P",
    "gn:feature_code":"PPL",
    "gn:name":"El Refugio",
    "gn:population":0,
    "gn:timezone":"America/Chihuahua",
    "iso:country":"MX",
    "name:spa_x_preferred":[
        "El Refugio"
    ],
    "wof:name":"El Refugio",
    "wof:placetype":"locality"
},
  "geometry": {"coordinates":[-108.1337,28.80444],"type":"Point"}
}