{
  "type": "Feature",
  "properties": {
    "gn:admin1_code":"12",
    "gn:admin2_code":"41.0",
    "gn:asciiname":"Colonia Santa Anita",
    "gn:country_code":"MX",
    "gn:dem":2284,
    "gn:feature_class":"P",
    "gn:feature_code":"PPL",
    "gn:name":"Colonia Santa Anita",
    "gn:population":211,
    "gn:timezone":"America/Mexico_City",
    "iso:country":"MX",
    "wof:name":"Colonia Santa Anita",
    "wof:placetype":"locality",
    "wof:population":211
},
  "geometry": {"coordinates":[-98.63973,17.28964],"type":"Point"}
}