{
  "type": "Feature",
  "properties": {
    "gn:admin1_code":"30.0",
    "gn:admin2_code":"160.0",
    "gn:asciiname":"El Tepetate",
    "gn:country_code":"MX",
    "gn:dem":91,
    "gn:feature_class":"P",
    "gn:feature_code":"PPL",
    "gn:name":"El Tepetate",
    "gn:population":0,
    "gn:timezone":"America/Mexico_City",
    "iso:country":"MX",
    "name:spa_x_preferred":[
        "El Tepetate"
    ],
    "name:spa_x_variant":[
        "El Salto Nuevo"
    ],
    "wof:name":"El Tepetate",
    "wof:placetype":"locality"
},
  "geometry": {"coordinates":[-97.90571,21.02127],"type":"Point"}
}