{
  "type": "Feature",
  "properties": {
    "gn:admin1_code":"23.0",
    "gn:asciiname":"El Mostrenco",
    "gn:country_code":"MX",
    "gn:dem":88,
    "gn:feature_class":"P",
    "gn:feature_code":"PPL",
    "gn:name":"El Mostrenco",
    "gn:population":0,
    "gn:timezone":"America/Cancun",
    "iso:country":"MX",
    "name:spa_x_preferred":[
        "El Mostrenco"
    ],
    "wof:name":"El Mostrenco",
    "wof:placetype":"locality"
},
  "geometry": {"coordinates":[-88.91919,18.46428],"type":"Point"}
}