{
  "type": "Feature",
  "properties": {
    "gn:admin1_code":"24",
    "gn:admin2_code":"45.0",
    "gn:asciiname":"Rancho la Loma",
    "gn:country_code":"MX",
    "gn:dem":1820,
    "gn:feature_class":"P",
    "gn:feature_code":"PPL",
    "gn:name":"Rancho la Loma",
    "gn:population":6,
    "gn:timezone":"America/Mexico_City",
    "iso:country":"MX",
    "wof:name":"Rancho la Loma",
    "wof:placetype":"locality",
    "wof:population":6
},
  "geometry": {"coordinates":[-101.11306,22.93528],"type":"Point"}
}