{
  "type": "Feature",
  "properties": {
    "gn:admin1_code":"25",
    "gn:admin2_code":"1.0",
    "gn:asciiname":"Ninos Heroes de Chapultepec (Estacion Francisco)",
    "gn:country_code":"MX",
    "gn:dem":45,
    "gn:feature_class":"P",
    "gn:feature_code":"PPL",
    "gn:name":"Ni\u00f1os H\u00e9roes de Chapultepec (Estaci\u00f3n Francisco)",
    "gn:population":454,
    "gn:timezone":"America/Mazatlan",
    "iso:country":"MX",
    "name:und_x_variant":[
        "Ni\u00f1os H\u00e9roes de Chapultepec (Estaci\u00f3n Francisco)"
    ],
    "wof:name":"Ninos Heroes de Chapultepec (Estacion Francisco)",
    "wof:placetype":"locality",
    "wof:population":454
},
  "geometry": {"coordinates":[-108.94167,26.32861],"type":"Point"}
}