{
  "type": "Feature",
  "properties": {
    "gn:admin1_code":"30",
    "gn:admin2_code":"141.0",
    "gn:asciiname":"Apixtla",
    "gn:country_code":"MX",
    "gn:dem":69,
    "gn:feature_class":"P",
    "gn:feature_code":"PPL",
    "gn:name":"Apixtla",
    "gn:population":0,
    "gn:timezone":"America/Mexico_City",
    "iso:country":"MX",
    "name:spa_x_preferred":[
        "Apixtla"
    ],
    "wof:name":"Apixtla",
    "wof:placetype":"locality"
},
  "geometry": {"coordinates":[-95.29371,18.3159],"type":"Point"}
}