{
  "type": "Feature",
  "properties": {
    "gn:admin1_code":"6.0",
    "gn:admin2_code":"20.0",
    "gn:asciiname":"El Muerto",
    "gn:country_code":"MX",
    "gn:dem":1823,
    "gn:feature_class":"P",
    "gn:feature_code":"PPL",
    "gn:name":"El Muerto",
    "gn:population":0,
    "gn:timezone":"America/Chihuahua",
    "iso:country":"MX",
    "name:spa_x_preferred":[
        "El Muerto"
    ],
    "wof:name":"El Muerto",
    "wof:placetype":"locality"
},
  "geometry": {"coordinates":[-108.49099,27.72492],"type":"Point"}
}