{
  "type": "Feature",
  "properties": {
    "gn:admin1_code":"14",
    "gn:admin2_code":"72.0",
    "gn:asciiname":"San Sebastian",
    "gn:country_code":"MX",
    "gn:dem":2002,
    "gn:feature_class":"P",
    "gn:feature_code":"PPL",
    "gn:name":"San Sebasti\u00e1n",
    "gn:population":0,
    "gn:timezone":"America/Mexico_City",
    "iso:country":"MX",
    "name:spa_x_preferred":[
        "San Sebasti\u00e1n"
    ],
    "wof:name":"San Sebastian",
    "wof:placetype":"locality"
},
  "geometry": {"coordinates":[-102.19289999999999,20.8766],"type":"Point"}
}