{
  "type": "Feature",
  "properties": {
    "gn:admin1_code":"28",
    "gn:admin2_code":"34.0",
    "gn:asciiname":"La Yulisa",
    "gn:country_code":"MX",
    "gn:dem":253,
    "gn:feature_class":"P",
    "gn:feature_code":"PPL",
    "gn:name":"La Yulisa",
    "gn:population":5,
    "gn:timezone":"America/Monterrey",
    "iso:country":"MX",
    "wof:name":"La Yulisa",
    "wof:placetype":"locality",
    "wof:population":5
},
  "geometry": {"coordinates":[-99.0325,24.36111],"type":"Point"}
}