{
  "type": "Feature",
  "properties": {
    "gn:admin1_code":"7",
    "gn:admin2_code":"17.0",
    "gn:asciiname":"El Pacifico",
    "gn:country_code":"MX",
    "gn:dem":1133,
    "gn:feature_class":"P",
    "gn:feature_code":"PPL",
    "gn:name":"El Pac\u00edfico",
    "gn:population":447,
    "gn:timezone":"America/Monterrey",
    "iso:country":"MX",
    "name:und_x_variant":[
        "El Pac\u00edfico"
    ],
    "wof:name":"El Pacifico",
    "wof:placetype":"locality",
    "wof:population":447
},
  "geometry": {"coordinates":[-103.32832999999999,25.47083],"type":"Point"}
}