{
  "type": "Feature",
  "properties": {
    "gn:admin1_code":"4",
    "gn:admin2_code":"3.0",
    "gn:asciiname":"La Concordia",
    "gn:country_code":"MX",
    "gn:dem":-3,
    "gn:feature_class":"P",
    "gn:feature_code":"PPL",
    "gn:name":"La Concordia",
    "gn:population":5,
    "gn:timezone":"America/Merida",
    "iso:country":"MX",
    "name:ceb_x_preferred":[
        "La Concordia"
    ],
    "name:deu_x_preferred":[
        "La Concordia"
    ],
    "name:nld_x_preferred":[
        "La Concordia"
    ],
    "name:rus_x_preferred":[
        "\u041b\u0430-\u041a\u043e\u043d\u043a\u043e\u0440\u0434\u0438\u044f"
    ],
    "name:sco_x_preferred":[
        "La Concordia"
    ],
    "name:spa_x_preferred":[
        "La Concordia"
    ],
    "name:swe_x_preferred":[
        "La Concordia"
    ],
    "wof:name":"La Concordia",
    "wof:placetype":"locality",
    "wof:population":5
},
  "geometry": {"coordinates":[-91.71917000000001,18.34167],"type":"Point"}
}