{
  "type": "Feature",
  "properties": {
    "gn:admin1_code":"6",
    "gn:admin2_code":"45.0",
    "gn:asciiname":"Los Gavilanes",
    "gn:country_code":"MX",
    "gn:dem":1148,
    "gn:feature_class":"P",
    "gn:feature_code":"PPL",
    "gn:name":"Los Gavilanes",
    "gn:population":6,
    "gn:timezone":"America/Chihuahua",
    "iso:country":"MX",
    "wof:name":"Los Gavilanes",
    "wof:placetype":"locality",
    "wof:population":6
},
  "geometry": {"coordinates":[-105.51094000000001,28.26866],"type":"Point"}
}