{
  "type": "Feature",
  "properties": {
    "gn:admin1_code":"14",
    "gn:admin2_code":"104.0",
    "gn:asciiname":"El Tepante",
    "gn:country_code":"MX",
    "gn:dem":2000,
    "gn:feature_class":"P",
    "gn:feature_code":"PPL",
    "gn:name":"El Tepante",
    "gn:population":0,
    "gn:timezone":"America/Mexico_City",
    "iso:country":"MX",
    "name:spa_x_preferred":[
        "El Tepante"
    ],
    "wof:name":"El Tepante",
    "wof:placetype":"locality"
},
  "geometry": {"coordinates":[-103.52670999999999,21.88431],"type":"Point"}
}