{
  "type": "Feature",
  "properties": {
    "gn:admin1_code":"5",
    "gn:admin2_code":"89.0",
    "gn:asciiname":"Villa las Rosas",
    "gn:country_code":"MX",
    "gn:dem":67,
    "gn:feature_class":"P",
    "gn:feature_code":"PPL",
    "gn:name":"Villa las Rosas",
    "gn:population":335,
    "gn:timezone":"America/Mexico_City",
    "iso:country":"MX",
    "wof:name":"Villa las Rosas",
    "wof:placetype":"locality",
    "wof:population":335
},
  "geometry": {"coordinates":[-92.3155,14.83763],"type":"Point"}
}