{
  "type": "Feature",
  "properties": {
    "gn:admin1_code":"12.0",
    "gn:admin2_code":"76.0",
    "gn:asciiname":"Barranca Dulce",
    "gn:country_code":"MX",
    "gn:dem":2035,
    "gn:feature_class":"P",
    "gn:feature_code":"PPL",
    "gn:name":"Barranca Dulce",
    "gn:population":0,
    "gn:timezone":"America/Mexico_City",
    "iso:country":"MX",
    "name:spa_x_preferred":[
        "Barranca Dulce"
    ],
    "wof:name":"Barranca Dulce",
    "wof:placetype":"locality"
},
  "geometry": {"coordinates":[-98.87657,17.29056],"type":"Point"}
}