{
  "type": "Feature",
  "properties": {
    "gn:admin1_code":"12",
    "gn:admin2_code":"53.0",
    "gn:asciiname":"El Cerro Pesqueria",
    "gn:country_code":"MX",
    "gn:dem":7,
    "gn:feature_class":"P",
    "gn:feature_code":"PPL",
    "gn:name":"El Cerro Pesquer\u00eda",
    "gn:population":114,
    "gn:timezone":"America/Mexico_City",
    "iso:country":"MX",
    "name:und_x_variant":[
        "El Cerro Pesquer\u00eda"
    ],
    "wof:name":"El Cerro Pesqueria",
    "wof:placetype":"locality",
    "wof:population":114
},
  "geometry": {"coordinates":[-99.30886,16.69806],"type":"Point"}
}