{
  "type": "Feature",
  "properties": {
    "gn:admin1_code":"30",
    "gn:admin2_code":"83.0",
    "gn:asciiname":"Zapotempa",
    "gn:country_code":"MX",
    "gn:dem":105,
    "gn:feature_class":"P",
    "gn:feature_code":"PPL",
    "gn:name":"Zapotempa",
    "gn:population":0,
    "gn:timezone":"America/Mexico_City",
    "iso:country":"MX",
    "wof:name":"Zapotempa",
    "wof:placetype":"locality"
},
  "geometry": {"coordinates":[-97.95,20.78333],"type":"Point"}
}