{
  "type": "Feature",
  "properties": {
    "gn:admin1_code":"6",
    "gn:admin2_code":"65.0",
    "gn:asciiname":"Taborachi",
    "gn:country_code":"MX",
    "gn:dem":1975,
    "gn:feature_class":"P",
    "gn:feature_code":"PPL",
    "gn:name":"Taborachi",
    "gn:population":24,
    "gn:timezone":"America/Chihuahua",
    "iso:country":"MX",
    "name:spa_x_preferred":[
        "Taborachi"
    ],
    "wof:name":"Taborachi",
    "wof:placetype":"locality",
    "wof:population":24
},
  "geometry": {"coordinates":[-108.05798,27.51714],"type":"Point"}
}