{
  "type": "Feature",
  "properties": {
    "gn:admin1_code":"10",
    "gn:admin2_code":"7.0",
    "gn:asciiname":"La Magdalena (Fresnedo) [Granja]",
    "gn:country_code":"MX",
    "gn:dem":1113,
    "gn:feature_class":"P",
    "gn:feature_code":"PPL",
    "gn:name":"La Magdalena (Fresnedo) [Granja]",
    "gn:population":6,
    "gn:timezone":"America/Monterrey",
    "iso:country":"MX",
    "wof:name":"La Magdalena (Fresnedo) [Granja]",
    "wof:placetype":"locality",
    "wof:population":6
},
  "geometry": {"coordinates":[-103.55952000000001,25.74056],"type":"Point"}
}