{
  "type": "Feature",
  "properties": {
    "gn:admin1_code":"30.0",
    "gn:admin2_code":"121.0",
    "gn:asciiname":"El Horizonte",
    "gn:country_code":"MX",
    "gn:dem":55,
    "gn:feature_class":"P",
    "gn:feature_code":"PPL",
    "gn:name":"El Horizonte",
    "gn:population":0,
    "gn:timezone":"America/Mexico_City",
    "iso:country":"MX",
    "name:spa_x_preferred":[
        "El Horizonte"
    ],
    "wof:name":"El Horizonte",
    "wof:placetype":"locality"
},
  "geometry": {"coordinates":[-98.10056,21.67222000000001],"type":"Point"}
}