{
  "type": "Feature",
  "properties": {
    "gn:admin1_code":"17",
    "gn:admin2_code":"33.0",
    "gn:asciiname":"Popotlan (Barrio Santo Tomas)",
    "gn:country_code":"MX",
    "gn:dem":1582,
    "gn:feature_class":"P",
    "gn:feature_code":"PPL",
    "gn:name":"Popotl\u00e1n (Barrio Santo Tom\u00e1s)",
    "gn:population":869,
    "gn:timezone":"America/Mexico_City",
    "iso:country":"MX",
    "name:und_x_variant":[
        "Popotl\u00e1n (Barrio Santo Tom\u00e1s)"
    ],
    "wof:name":"Popotlan (Barrio Santo Tomas)",
    "wof:placetype":"locality",
    "wof:population":869
},
  "geometry": {"coordinates":[-98.76555999999999,18.76472],"type":"Point"}
}