{
  "type": "Feature",
  "properties": {
    "gn:admin1_code":"31",
    "gn:admin2_code":"50.0",
    "gn:asciiname":"Xcauaka",
    "gn:country_code":"MX",
    "gn:dem":11,
    "gn:feature_class":"P",
    "gn:feature_code":"PPL",
    "gn:name":"Xcauaka",
    "gn:population":2,
    "gn:timezone":"America/Merida",
    "iso:country":"MX",
    "wof:name":"Xcauaka",
    "wof:placetype":"locality",
    "wof:population":2
},
  "geometry": {"coordinates":[-89.60736999999997,20.86347],"type":"Point"}
}