{
  "type": "Feature",
  "properties": {
    "gn:admin1_code":"20",
    "gn:admin2_code":"86.0",
    "gn:asciiname":"Ndicayuco",
    "gn:country_code":"MX",
    "gn:dem":2190,
    "gn:feature_class":"P",
    "gn:feature_code":"PPL",
    "gn:name":"Ndicayuco",
    "gn:population":54,
    "gn:timezone":"America/Mexico_City",
    "iso:country":"MX",
    "wof:name":"Ndicayuco",
    "wof:placetype":"locality",
    "wof:population":54
},
  "geometry": {"coordinates":[-97.50278,17.20083],"type":"Point"}
}