{
  "type": "Feature",
  "properties": {
    "gn:admin1_code":"26",
    "gn:admin2_code":"21.0",
    "gn:asciiname":"Represito",
    "gn:country_code":"MX",
    "gn:dem":359,
    "gn:feature_class":"P",
    "gn:feature_code":"PPL",
    "gn:name":"Represito",
    "gn:population":0,
    "gn:timezone":"America/Hermosillo",
    "iso:country":"MX",
    "wof:name":"Represito",
    "wof:placetype":"locality"
},
  "geometry": {"coordinates":[-110.78333000000001,28.56667],"type":"Point"}
}