{
  "type": "Feature",
  "properties": {
    "gn:admin1_code":"25",
    "gn:admin2_code":"3.0",
    "gn:asciiname":"Alisitos",
    "gn:country_code":"MX",
    "gn:dem":1139,
    "gn:feature_class":"P",
    "gn:feature_code":"PPL",
    "gn:name":"Alisitos",
    "gn:population":69,
    "gn:timezone":"America/Mazatlan",
    "iso:country":"MX",
    "wof:name":"Alisitos",
    "wof:placetype":"locality",
    "wof:population":69
},
  "geometry": {"coordinates":[-107.11517000000001,25.67865],"type":"Point"}
}