{
  "type": "Feature",
  "properties": {
    "gn:admin1_code":"20",
    "gn:admin2_code":"125.0",
    "gn:asciiname":"Tecalatepec",
    "gn:cc2":"MX",
    "gn:country_code":"MX",
    "gn:dem":1474,
    "gn:feature_class":"P",
    "gn:feature_code":"PPL",
    "gn:name":"Tecalatepec",
    "gn:population":0,
    "gn:timezone":"America/Mexico_City",
    "iso:country":"MX",
    "name:und_x_variant":[
        "Tecolotepec",
        "Tecalatepec"
    ],
    "wof:name":"Tecalatepec",
    "wof:placetype":"locality"
},
  "geometry": {"coordinates":[-95.95,16.18333],"type":"Point"}
}