{
  "type": "Feature",
  "properties": {
    "gn:admin1_code":"28",
    "gn:admin2_code":"16.0",
    "gn:asciiname":"Los Magueyitos",
    "gn:country_code":"MX",
    "gn:dem":191,
    "gn:feature_class":"P",
    "gn:feature_code":"PPL",
    "gn:name":"Los Magueyitos",
    "gn:population":1,
    "gn:timezone":"America/Monterrey",
    "iso:country":"MX",
    "wof:name":"Los Magueyitos",
    "wof:placetype":"locality",
    "wof:population":1
},
  "geometry": {"coordinates":[-99.13442000000001,24.18407],"type":"Point"}
}