{
  "type": "Feature",
  "properties": {
    "gn:admin1_code":"2",
    "gn:admin2_code":"2.0",
    "gn:asciiname":"Don Manuel",
    "gn:country_code":"MX",
    "gn:dem":9,
    "gn:feature_class":"P",
    "gn:feature_code":"PPL",
    "gn:name":"Don Manuel",
    "gn:population":6,
    "gn:timezone":"America/Tijuana",
    "iso:country":"MX",
    "wof:name":"Don Manuel",
    "wof:placetype":"locality",
    "wof:population":6
},
  "geometry": {"coordinates":[-115.35805999999999,32.48972],"type":"Point"}
}