{
  "type": "Feature",
  "properties": {
    "gn:admin1_code":"12",
    "gn:admin2_code":"49.0",
    "gn:asciiname":"Ninguno",
    "gn:country_code":"MX",
    "gn:dem":1639,
    "gn:feature_class":"P",
    "gn:feature_code":"PPL",
    "gn:name":"Ninguno",
    "gn:population":118,
    "gn:timezone":"America/Mexico_City",
    "iso:country":"MX",
    "wof:name":"Ninguno",
    "wof:placetype":"locality",
    "wof:population":118
},
  "geometry": {"coordinates":[-99.68171,18.76199],"type":"Point"}
}