{
  "type": "Feature",
  "properties": {
    "gn:admin1_code":"2",
    "gn:admin2_code":"1",
    "gn:asciiname":"San Salvador",
    "gn:country_code":"MX",
    "gn:dem":101,
    "gn:feature_class":"P",
    "gn:feature_code":"PPL",
    "gn:name":"San Salvador",
    "gn:population":40,
    "gn:timezone":"America/Tijuana",
    "iso:country":"MX",
    "wof:name":"San Salvador",
    "wof:placetype":"locality",
    "wof:population":40
},
  "geometry": {"coordinates":[-116.5775,31.8125],"type":"Point"}
}