{
  "type": "Feature",
  "properties": {
    "gn:admin1_code":"7",
    "gn:admin2_code":"14.0",
    "gn:asciiname":"El Cedro",
    "gn:country_code":"MX",
    "gn:dem":417,
    "gn:feature_class":"P",
    "gn:feature_code":"PPL",
    "gn:name":"El Cedro",
    "gn:population":0,
    "gn:timezone":"America/Monterrey",
    "iso:country":"MX",
    "name:ceb_x_preferred":[
        "El Cedro"
    ],
    "name:fra_x_preferred":[
        "El Cedro"
    ],
    "name:ita_x_preferred":[
        "El Cedro"
    ],
    "name:spa_x_preferred":[
        "El Cedro"
    ],
    "name:swe_x_preferred":[
        "El Cedro"
    ],
    "name:und_x_variant":[
        "Rancho El Cedro"
    ],
    "wof:name":"El Cedro",
    "wof:placetype":"locality"
},
  "geometry": {"coordinates":[-101.06561000000001,28.84777],"type":"Point"}
}