{
  "type": "Feature",
  "properties": {
    "gn:admin1_code":"26.0",
    "gn:admin2_code":"36.0",
    "gn:asciiname":"La Agueita",
    "gn:country_code":"MX",
    "gn:dem":1048,
    "gn:feature_class":"P",
    "gn:feature_code":"PPL",
    "gn:name":"La Ag\u00fcita",
    "gn:population":0,
    "gn:timezone":"America/Hermosillo",
    "iso:country":"MX",
    "wof:name":"La Agueita",
    "wof:placetype":"locality"
},
  "geometry": {"coordinates":[-111.04801,30.90988],"type":"Point"}
}