{
  "type": "Feature",
  "properties": {
    "gn:admin1_code":"29",
    "gn:admin2_code":"43.0",
    "gn:asciiname":"Tlatelpa",
    "gn:country_code":"MX",
    "gn:dem":2504,
    "gn:feature_class":"P",
    "gn:feature_code":"PPL",
    "gn:name":"Tlatelpa",
    "gn:population":5,
    "gn:timezone":"America/Mexico_City",
    "iso:country":"MX",
    "wof:name":"Tlatelpa",
    "wof:placetype":"locality",
    "wof:population":5
},
  "geometry": {"coordinates":[-98.21347,19.39373],"type":"Point"}
}