{
  "type": "Feature",
  "properties": {
    "gn:admin1_code":"12",
    "gn:admin2_code":"48.0",
    "gn:asciiname":"Nuevo Mundo",
    "gn:country_code":"MX",
    "gn:dem":1164,
    "gn:feature_class":"P",
    "gn:feature_code":"PPL",
    "gn:name":"Nuevo Mundo",
    "gn:population":62,
    "gn:timezone":"America/Mexico_City",
    "iso:country":"MX",
    "name:ceb_x_preferred":[
        "Nuevo Mundo"
    ],
    "name:deu_x_preferred":[
        "Nuevo Mundo"
    ],
    "name:fra_x_preferred":[
        "Nuevo Mundo"
    ],
    "name:por_x_preferred":[
        "Novo Mundo"
    ],
    "name:spa_x_preferred":[
        "Nuevo Mundo"
    ],
    "name:swe_x_preferred":[
        "Nuevo Mundo"
    ],
    "wof:name":"Nuevo Mundo",
    "wof:placetype":"locality",
    "wof:population":62
},
  "geometry": {"coordinates":[-101.00449,17.70625],"type":"Point"}
}