{
  "type": "Feature",
  "properties": {
    "gn:admin1_code":"20",
    "gn:admin2_code":"50.0",
    "gn:asciiname":"San Juan del Rio",
    "gn:country_code":"MX",
    "gn:dem":2010,
    "gn:feature_class":"P",
    "gn:feature_code":"PPL",
    "gn:name":"San Juan del R\u00edo",
    "gn:population":200,
    "gn:timezone":"America/Mexico_City",
    "iso:country":"MX",
    "name:und_x_variant":[
        "San Juan del R\u00edo"
    ],
    "wof:name":"San Juan del Rio",
    "wof:placetype":"locality",
    "wof:population":200
},
  "geometry": {"coordinates":[-97.535,17.2675],"type":"Point"}
}