{
  "type": "Feature",
  "properties": {
    "gn:admin1_code":"7",
    "gn:admin2_code":"17.0",
    "gn:asciiname":"La Fortuna",
    "gn:country_code":"MX",
    "gn:dem":1111,
    "gn:feature_class":"P",
    "gn:feature_code":"PPL",
    "gn:name":"La Fortuna",
    "gn:population":0,
    "gn:timezone":"America/Monterrey",
    "iso:country":"MX",
    "name:spa_x_preferred":[
        "La Fortuna"
    ],
    "wof:name":"La Fortuna",
    "wof:placetype":"locality"
},
  "geometry": {"coordinates":[-103.15909000000001,25.49139],"type":"Point"}
}