{
  "type": "Feature",
  "properties": {
    "gn:admin1_code":"20",
    "gn:admin2_code":"67.0",
    "gn:asciiname":"Paraje Caballetillo",
    "gn:country_code":"MX",
    "gn:dem":1644,
    "gn:feature_class":"P",
    "gn:feature_code":"PPL",
    "gn:name":"Paraje Caballetillo",
    "gn:population":85,
    "gn:timezone":"America/Mexico_City",
    "iso:country":"MX",
    "wof:name":"Paraje Caballetillo",
    "wof:placetype":"locality",
    "wof:population":85
},
  "geometry": {"coordinates":[-96.745,17.13111],"type":"Point"}
}