{
  "type": "Feature",
  "properties": {
    "gn:admin1_code":"16",
    "gn:admin2_code":"49",
    "gn:asciiname":"Los Planes de Etucuaro",
    "gn:country_code":"MX",
    "gn:dem":1746,
    "gn:feature_class":"P",
    "gn:feature_code":"PPL",
    "gn:name":"Los Planes de Et\u00facuaro",
    "gn:population":28,
    "gn:timezone":"America/Mexico_City",
    "iso:country":"MX",
    "name:und_x_variant":[
        "Los Planes de Et\u00facuaro"
    ],
    "wof:name":"Los Planes de Etucuaro",
    "wof:placetype":"locality",
    "wof:population":28
},
  "geometry": {"coordinates":[-101.14583,19.49444],"type":"Point"}
}