{
  "type": "Feature",
  "properties": {
    "gn:admin1_code":"2",
    "gn:admin2_code":"1.0",
    "gn:asciiname":"Parcela Diecinueve (Ejido Nacionalista)",
    "gn:country_code":"MX",
    "gn:dem":21,
    "gn:feature_class":"P",
    "gn:feature_code":"PPL",
    "gn:name":"Parcela Diecinueve (Ejido Nacionalista)",
    "gn:population":66,
    "gn:timezone":"America/Tijuana",
    "iso:country":"MX",
    "wof:name":"Parcela Diecinueve (Ejido Nacionalista)",
    "wof:placetype":"locality",
    "wof:population":66
},
  "geometry": {"coordinates":[-116.56528,31.7625],"type":"Point"}
}