{
  "type": "Feature",
  "properties": {
    "gn:admin1_code":"12",
    "gn:admin2_code":"76.0",
    "gn:asciiname":"Filo de San Marcos",
    "gn:country_code":"MX",
    "gn:dem":1989,
    "gn:feature_class":"P",
    "gn:feature_code":"PPL",
    "gn:name":"Filo de San Marcos",
    "gn:population":85,
    "gn:timezone":"America/Mexico_City",
    "iso:country":"MX",
    "wof:name":"Filo de San Marcos",
    "wof:placetype":"locality",
    "wof:population":85
},
  "geometry": {"coordinates":[-98.87175000000001,17.28926],"type":"Point"}
}