{
  "type": "Feature",
  "properties": {
    "gn:admin1_code":"26.0",
    "gn:admin2_code":"27.0",
    "gn:asciiname":"Bufalo",
    "gn:country_code":"MX",
    "gn:dem":1093,
    "gn:feature_class":"P",
    "gn:feature_code":"PPL",
    "gn:name":"B\u00fafalo",
    "gn:population":0,
    "gn:timezone":"America/Hermosillo",
    "iso:country":"MX",
    "name:ceb_x_preferred":[
        "Bufalo"
    ],
    "name:deu_x_preferred":[
        "Del Bufalo"
    ],
    "name:glg_x_preferred":[
        "B\u00fafalo"
    ],
    "name:ita_x_preferred":[
        "Bufalo"
    ],
    "name:spa_x_preferred":[
        "B\u00fafalo"
    ],
    "name:swe_x_preferred":[
        "Bufalo"
    ],
    "wof:name":"Bufalo",
    "wof:placetype":"locality"
},
  "geometry": {"coordinates":[-109.51367999999999,30.98297],"type":"Point"}
}