{
  "type": "Feature",
  "properties": {
    "gn:admin1_code":"21",
    "gn:admin2_code":"213.0",
    "gn:asciiname":"Cerro Azul",
    "gn:country_code":"MX",
    "gn:dem":469,
    "gn:feature_class":"P",
    "gn:feature_code":"PPL",
    "gn:name":"Cerro Azul",
    "gn:population":41,
    "gn:timezone":"America/Mexico_City",
    "iso:country":"MX",
    "name:spa_x_preferred":[
        "Cerro Azul"
    ],
    "wof:name":"Cerro Azul",
    "wof:placetype":"locality",
    "wof:population":41
},
  "geometry": {"coordinates":[-97.76308,20.32341],"type":"Point"}
}