{
  "type": "Feature",
  "properties": {
    "gn:admin1_code":"16",
    "gn:admin2_code":"88.0",
    "gn:asciiname":"Canada de los Sauces",
    "gn:country_code":"MX",
    "gn:dem":2022,
    "gn:feature_class":"P",
    "gn:feature_code":"PPL",
    "gn:name":"Ca\u00f1ada de los Sauces",
    "gn:population":813,
    "gn:timezone":"America/Mexico_City",
    "iso:country":"MX",
    "name:und_x_variant":[
        "Ca\u00f1ada de los Sauces"
    ],
    "wof:name":"Canada de los Sauces",
    "wof:placetype":"locality",
    "wof:population":813
},
  "geometry": {"coordinates":[-101.21583,19.83194],"type":"Point"}
}