{
  "type": "Feature",
  "properties": {
    "gn:admin1_code":"22",
    "gn:admin2_code":"16.0",
    "gn:asciiname":"Villas Fundadores [Fraccionamiento]",
    "gn:country_code":"MX",
    "gn:dem":2054,
    "gn:feature_class":"P",
    "gn:feature_code":"PPL",
    "gn:name":"Villas Fundadores [Fraccionamiento]",
    "gn:population":1956,
    "gn:timezone":"America/Mexico_City",
    "iso:country":"MX",
    "wof:name":"Villas Fundadores [Fraccionamiento]",
    "wof:placetype":"locality",
    "wof:population":1956
},
  "geometry": {"coordinates":[-99.90944,20.37778],"type":"Point"}
}