{
  "type": "Feature",
  "properties": {
    "gn:admin1_code":"26.0",
    "gn:asciiname":"El Trigo",
    "gn:country_code":"MX",
    "gn:dem":1476,
    "gn:feature_class":"P",
    "gn:feature_code":"PPL",
    "gn:name":"El Trigo",
    "gn:population":0,
    "gn:timezone":"America/Chihuahua",
    "iso:country":"MX",
    "name:spa_x_preferred":[
        "El Trigo"
    ],
    "wof:name":"El Trigo",
    "wof:placetype":"locality"
},
  "geometry": {"coordinates":[-108.66965999999999,27.57373],"type":"Point"}
}