{
  "type": "Feature",
  "properties": {
    "gn:admin1_code":"6",
    "gn:admin2_code":"29.0",
    "gn:asciiname":"Arroyo de Basilio",
    "gn:country_code":"MX",
    "gn:dem":2469,
    "gn:feature_class":"P",
    "gn:feature_code":"PPL",
    "gn:name":"Arroyo de Basilio",
    "gn:population":8,
    "gn:timezone":"America/Monterrey",
    "iso:country":"MX",
    "wof:name":"Arroyo de Basilio",
    "wof:placetype":"locality",
    "wof:population":8
},
  "geometry": {"coordinates":[-106.52345,25.95496],"type":"Point"}
}