{
  "type": "Feature",
  "properties": {
    "gn:admin1_code":"10.0",
    "gn:asciiname":"La Espinaloza",
    "gn:country_code":"MX",
    "gn:dem":1273,
    "gn:feature_class":"P",
    "gn:feature_code":"PPL",
    "gn:name":"La Espinaloza",
    "gn:population":0,
    "gn:timezone":"America/Mazatlan",
    "iso:country":"MX",
    "name:spa_x_preferred":[
        "La Espinaloza"
    ],
    "wof:name":"La Espinaloza",
    "wof:placetype":"locality"
},
  "geometry": {"coordinates":[-105.93396,24.068],"type":"Point"}
}