{
  "type": "Feature",
  "properties": {
    "gn:admin1_code":"16.0",
    "gn:admin2_code":"10.0",
    "gn:asciiname":"La Parotita de Zuniga",
    "gn:country_code":"MX",
    "gn:dem":596,
    "gn:feature_class":"P",
    "gn:feature_code":"PPL",
    "gn:name":"La Parotita de Zu\u00f1iga",
    "gn:population":0,
    "gn:timezone":"America/Mexico_City",
    "iso:country":"MX",
    "name:spa_x_preferred":[
        "La Parotita de Zu\u00f1iga"
    ],
    "wof:name":"La Parotita de Zuniga",
    "wof:placetype":"locality"
},
  "geometry": {"coordinates":[-102.09392,18.34391],"type":"Point"}
}