{
  "type": "Feature",
  "properties": {
    "gn:admin1_code":"14",
    "gn:admin2_code":"44",
    "gn:asciiname":"La Calerita (El Reniego)",
    "gn:country_code":"MX",
    "gn:dem":1548,
    "gn:feature_class":"P",
    "gn:feature_code":"PPL",
    "gn:name":"La Calerita (El Reniego)",
    "gn:population":51,
    "gn:timezone":"America/Mexico_City",
    "iso:country":"MX",
    "wof:name":"La Calerita (El Reniego)",
    "wof:placetype":"locality",
    "wof:population":51
},
  "geometry": {"coordinates":[-103.22556,20.41889],"type":"Point"}
}