{
  "type": "Feature",
  "properties": {
    "gn:admin1_code":"26",
    "gn:admin2_code":"42.0",
    "gn:asciiname":"Tres Hermanos",
    "gn:country_code":"MX",
    "gn:dem":76,
    "gn:feature_class":"P",
    "gn:feature_code":"PPL",
    "gn:name":"Tres Hermanos",
    "gn:population":0,
    "gn:timezone":"America/Hermosillo",
    "iso:country":"MX",
    "name:spa_x_preferred":[
        "Tres Hermanos"
    ],
    "wof:name":"Tres Hermanos",
    "wof:placetype":"locality"
},
  "geometry": {"coordinates":[-109.19614,27.19524],"type":"Point"}
}