{
  "type": "Feature",
  "properties": {
    "gn:admin1_code":"5",
    "gn:admin2_code":"59.0",
    "gn:asciiname":"Santa Rosa Dos",
    "gn:country_code":"MX",
    "gn:dem":813,
    "gn:feature_class":"P",
    "gn:feature_code":"PPL",
    "gn:name":"Santa Rosa Dos",
    "gn:population":324,
    "gn:timezone":"America/Mexico_City",
    "iso:country":"MX",
    "wof:name":"Santa Rosa Dos",
    "wof:placetype":"locality",
    "wof:population":324
},
  "geometry": {"coordinates":[-91.67749999999999,16.94917],"type":"Point"}
}