{
  "type": "Feature",
  "properties": {
    "gn:admin1_code":"30",
    "gn:admin2_code":"147.0",
    "gn:asciiname":"Capulines",
    "gn:country_code":"MX",
    "gn:dem":1385,
    "gn:feature_class":"P",
    "gn:feature_code":"PPL",
    "gn:name":"Capulines",
    "gn:population":398,
    "gn:timezone":"America/Mexico_City",
    "iso:country":"MX",
    "wof:name":"Capulines",
    "wof:placetype":"locality",
    "wof:population":398
},
  "geometry": {"coordinates":[-97.22278,18.75972],"type":"Point"}
}