{
  "type": "Feature",
  "properties": {
    "gn:admin1_code":"10",
    "gn:admin2_code":"37",
    "gn:asciiname":"Los Madriles",
    "gn:country_code":"MX",
    "gn:dem":1511,
    "gn:feature_class":"P",
    "gn:feature_code":"PPL",
    "gn:name":"Los Madriles",
    "gn:population":23,
    "gn:timezone":"America/Monterrey",
    "iso:country":"MX",
    "wof:name":"Los Madriles",
    "wof:placetype":"locality",
    "wof:population":23
},
  "geometry": {"coordinates":[-106.67676000000002,25.1947],"type":"Point"}
}