{
  "type": "Feature",
  "properties": {
    "gn:admin1_code":"23",
    "gn:admin2_code":"4.0",
    "gn:asciiname":"Teresa",
    "gn:country_code":"MX",
    "gn:dem":17,
    "gn:feature_class":"P",
    "gn:feature_code":"PPL",
    "gn:name":"Teresa",
    "gn:population":6,
    "gn:timezone":"America/Cancun",
    "iso:country":"MX",
    "name:ara_x_preferred":[
        "\u062a\u064a\u0631\u064a\u0632\u0627"
    ],
    "name:bre_x_preferred":[
        "Teresa"
    ],
    "name:fin_x_preferred":[
        "Teresa"
    ],
    "name:glg_x_preferred":[
        "Tareixa"
    ],
    "name:isl_x_preferred":[
        "Teresa"
    ],
    "name:ita_x_preferred":[
        "Teresa"
    ],
    "name:lat_x_preferred":[
        "Teresa"
    ],
    "name:nor_x_preferred":[
        "Teresa"
    ],
    "name:pol_x_preferred":[
        "Teresa"
    ],
    "name:spa_x_preferred":[
        "Teresa"
    ],
    "name:ukr_x_preferred":[
        "\u0422\u0435\u0440\u0435\u0437\u0430"
    ],
    "wof:name":"Teresa",
    "wof:placetype":"locality",
    "wof:population":6
},
  "geometry": {"coordinates":[-88.45227,18.51607000000001],"type":"Point"}
}