{
  "type": "Feature",
  "properties": {
    "gn:admin1_code":"30",
    "gn:admin2_code":"8.0",
    "gn:asciiname":"Mesa de Buenavista",
    "gn:country_code":"MX",
    "gn:dem":2643,
    "gn:feature_class":"P",
    "gn:feature_code":"PPL",
    "gn:name":"Mesa de Buenavista",
    "gn:population":248,
    "gn:timezone":"America/Mexico_City",
    "iso:country":"MX",
    "wof:name":"Mesa de Buenavista",
    "wof:placetype":"locality",
    "wof:population":248
},
  "geometry": {"coordinates":[-97.14556,19.11806],"type":"Point"}
}