{
  "type": "Feature",
  "properties": {
    "gn:admin1_code":"17",
    "gn:admin2_code":"16",
    "gn:asciiname":"Cerrito Colorado",
    "gn:country_code":"MX",
    "gn:dem":1848,
    "gn:feature_class":"P",
    "gn:feature_code":"PPL",
    "gn:name":"Cerrito Colorado",
    "gn:population":27,
    "gn:timezone":"America/Mexico_City",
    "iso:country":"MX",
    "wof:name":"Cerrito Colorado",
    "wof:placetype":"locality",
    "wof:population":27
},
  "geometry": {"coordinates":[-98.78028,18.85889],"type":"Point"}
}