{
  "type": "Feature",
  "properties": {
    "gn:admin1_code":"6",
    "gn:admin2_code":"65",
    "gn:asciiname":"El Buey",
    "gn:country_code":"MX",
    "gn:dem":927,
    "gn:feature_class":"P",
    "gn:feature_code":"PPL",
    "gn:name":"El Buey",
    "gn:population":39,
    "gn:timezone":"America/Chihuahua",
    "iso:country":"MX",
    "wof:name":"El Buey",
    "wof:placetype":"locality",
    "wof:population":39
},
  "geometry": {"coordinates":[-107.83018,27.10076],"type":"Point"}
}