{
  "type": "Feature",
  "properties": {
    "gn:admin1_code":"5",
    "gn:admin2_code":"23.0",
    "gn:asciiname":"Chicumtantic",
    "gn:country_code":"MX",
    "gn:dem":2278,
    "gn:feature_class":"P",
    "gn:feature_code":"PPL",
    "gn:name":"Chicumtantic",
    "gn:population":0,
    "gn:timezone":"America/Mexico_City",
    "iso:country":"MX",
    "name:spa_x_preferred":[
        "Chicumtantic"
    ],
    "name:spa_x_variant":[
        "Chichuntact"
    ],
    "wof:name":"Chicumtantic",
    "wof:placetype":"locality"
},
  "geometry": {"coordinates":[-92.60706999999999,16.86519],"type":"Point"}
}