{
  "type": "Feature",
  "properties": {
    "gn:admin1_code":"32.0",
    "gn:admin2_code":"51.0",
    "gn:asciiname":"La Campechana",
    "gn:country_code":"MX",
    "gn:dem":2000,
    "gn:feature_class":"P",
    "gn:feature_code":"PPL",
    "gn:name":"La Campechana",
    "gn:population":150,
    "gn:timezone":"America/Mexico_City",
    "iso:country":"MX",
    "wof:name":"La Campechana",
    "wof:placetype":"locality",
    "wof:population":150
},
  "geometry": {"coordinates":[-102.09914000000001,23.65087],"type":"Point"}
}