{
  "type": "Feature",
  "properties": {
    "gn:admin1_code":"11",
    "gn:admin2_code":"29",
    "gn:asciiname":"El Suspiro",
    "gn:country_code":"MX",
    "gn:dem":2005,
    "gn:feature_class":"P",
    "gn:feature_code":"PPL",
    "gn:name":"El Suspiro",
    "gn:population":15,
    "gn:timezone":"America/Mexico_City",
    "iso:country":"MX",
    "wof:name":"El Suspiro",
    "wof:placetype":"locality",
    "wof:population":15
},
  "geometry": {"coordinates":[-100.79443999999999,21.41889],"type":"Point"}
}