{
  "type": "Feature",
  "properties": {
    "gn:admin1_code":"14.0",
    "gn:admin2_code":"58.0",
    "gn:asciiname":"El Palmilloso",
    "gn:country_code":"MX",
    "gn:dem":588,
    "gn:feature_class":"P",
    "gn:feature_code":"PPL",
    "gn:name":"El Palmilloso",
    "gn:population":0,
    "gn:timezone":"America/Mexico_City",
    "iso:country":"MX",
    "name:spa_x_preferred":[
        "El Palmilloso"
    ],
    "wof:name":"El Palmilloso",
    "wof:placetype":"locality"
},
  "geometry": {"coordinates":[-105.10585,20.61202],"type":"Point"}
}