{
  "type": "Feature",
  "properties": {
    "gn:gn_country":"MX",
    "gn:gn_fcode":"PPL",
    "gn:gn_pop":8584,
    "gn:population":8584,
    "iso:country":"MX",
    "name:dut_x_preferred":[
        "Ciudad Insurgentes"
    ],
    "name:eng_x_preferred":[
        "Ciudad Insurgentes"
    ],
    "name:rus_x_preferred":[
        "\u0421\u044c\u044e\u0434\u0430\u0434-\u0418\u043d\u0441\u0443\u0440\u0445\u0435\u043d\u0442\u0435\u0441"
    ],
    "name:spa_x_preferred":[
        "Fernando de la Toba"
    ],
    "name:spa_x_variant":[
        "Ciudad Insurgentes",
        "La Toba"
    ],
    "name:unk_x_variant":[
        "Ejido Insurgentes"
    ],
    "qs_pg:aaroncc":"MX",
    "qs_pg:gn_country":"MX",
    "qs_pg:gn_fcode":"PPL",
    "qs_pg:gn_pop":8584,
    "qs_pg:name":"Villa Insurgentes",
    "qs_pg:photos_9r":0,
    "qs_pg:photos_sr":0,
    "qs_pg:pop_sr":5,
    "qs_pg:qs_pg_placetype":"locality",
    "wof:name":"Villa Insurgentes",
    "wof:placetype":"locality",
    "wof:population":8584
},
  "geometry": {"coordinates":[-111.77685,25.26029],"type":"Point"}
}