{
  "type": "Feature",
  "properties": {
    "gn:admin1_code":"5",
    "gn:admin2_code":"108.0",
    "gn:asciiname":"Guarizamey",
    "gn:country_code":"MX",
    "gn:dem":642,
    "gn:feature_class":"P",
    "gn:feature_code":"PPL",
    "gn:name":"Guarizamey",
    "gn:population":6,
    "gn:timezone":"America/Mexico_City",
    "iso:country":"MX",
    "wof:name":"Guarizamey",
    "wof:placetype":"locality",
    "wof:population":6
},
  "geometry": {"coordinates":[-93.34389,16.34111],"type":"Point"}
}