{
  "type": "Feature",
  "properties": {
    "gn:admin1_code":"13",
    "gn:admin2_code":"84.0",
    "gn:asciiname":"Vaquero",
    "gn:country_code":"MX",
    "gn:dem":2089,
    "gn:feature_class":"P",
    "gn:feature_code":"PPL",
    "gn:name":"Vaquero",
    "gn:population":0,
    "gn:timezone":"America/Mexico_City",
    "iso:country":"MX",
    "name:deu_x_preferred":[
        "Vaquero"
    ],
    "name:fin_x_preferred":[
        "Vaquero"
    ],
    "name:fra_x_preferred":[
        "Vaquero"
    ],
    "name:hun_x_preferred":[
        "Vaquero"
    ],
    "name:por_x_preferred":[
        "Vaqueiro"
    ],
    "name:scn_x_preferred":[
        "Vaccaru"
    ],
    "name:spa_x_preferred":[
        "Vaquero"
    ],
    "wof:name":"Vaquero",
    "wof:placetype":"locality"
},
  "geometry": {"coordinates":[-99.41667,20.83333],"type":"Point"}
}