{
  "type": "Feature",
  "properties": {
    "gn:admin1_code":"30",
    "gn:admin2_code":"189.0",
    "gn:asciiname":"Ejido Ciento Cuarenta",
    "gn:country_code":"MX",
    "gn:dem":31,
    "gn:feature_class":"P",
    "gn:feature_code":"PPL",
    "gn:name":"Ejido Ciento Cuarenta",
    "gn:population":9,
    "gn:timezone":"America/Mexico_City",
    "iso:country":"MX",
    "wof:name":"Ejido Ciento Cuarenta",
    "wof:placetype":"locality",
    "wof:population":9
},
  "geometry": {"coordinates":[-97.42471999999999,20.87056],"type":"Point"}
}