{
  "type": "Feature",
  "properties": {
    "gn:admin1_code":"10",
    "gn:admin2_code":"35",
    "gn:asciiname":"Las Brisas (Potrero de Abajo)",
    "gn:country_code":"MX",
    "gn:dem":2495,
    "gn:feature_class":"P",
    "gn:feature_code":"PPL",
    "gn:name":"Las Brisas (Potrero de Abajo)",
    "gn:population":27,
    "gn:timezone":"America/Monterrey",
    "iso:country":"MX",
    "wof:name":"Las Brisas (Potrero de Abajo)",
    "wof:placetype":"locality",
    "wof:population":27
},
  "geometry": {"coordinates":[-106.41294000000001,25.6832],"type":"Point"}
}