{
  "type": "Feature",
  "properties": {
    "gn:admin1_code":"12",
    "gn:admin2_code":"78",
    "gn:asciiname":"Xaha Yucundia",
    "gn:country_code":"MX",
    "gn:dem":2131,
    "gn:feature_class":"P",
    "gn:feature_code":"PPL",
    "gn:name":"Xaha Yucundia",
    "gn:population":12,
    "gn:timezone":"America/Mexico_City",
    "iso:country":"MX",
    "wof:name":"Xaha Yucundia",
    "wof:placetype":"locality",
    "wof:population":12
},
  "geometry": {"coordinates":[-98.47305,17.16916],"type":"Point"}
}