{
  "type": "Feature",
  "properties": {
    "gn:admin1_code":"1",
    "gn:admin2_code":"7",
    "gn:asciiname":"El Chapulin [Granja]",
    "gn:country_code":"MX",
    "gn:dem":1957,
    "gn:feature_class":"P",
    "gn:feature_code":"PPL",
    "gn:name":"El Chapul\u00edn [Granja]",
    "gn:population":12,
    "gn:timezone":"America/Mexico_City",
    "iso:country":"MX",
    "name:und_x_variant":[
        "El Chapul\u00edn [Granja]"
    ],
    "wof:name":"El Chapulin [Granja]",
    "wof:placetype":"locality",
    "wof:population":12
},
  "geometry": {"coordinates":[-102.32583,22.21194],"type":"Point"}
}