{
  "type": "Feature",
  "properties": {
    "gn:admin1_code":"14.0",
    "gn:admin2_code":"49.0",
    "gn:asciiname":"La Carreta",
    "gn:country_code":"MX",
    "gn:dem":673,
    "gn:feature_class":"P",
    "gn:feature_code":"PPL",
    "gn:name":"La Carreta",
    "gn:population":0,
    "gn:timezone":"America/Mexico_City",
    "iso:country":"MX",
    "name:spa_x_preferred":[
        "La Carreta"
    ],
    "wof:name":"La Carreta",
    "wof:placetype":"locality"
},
  "geometry": {"coordinates":[-102.97619,19.27117],"type":"Point"}
}