{
  "type": "Feature",
  "properties": {
    "gn:admin1_code":"24",
    "gn:admin2_code":"53.0",
    "gn:asciiname":"Chimalaco",
    "gn:country_code":"MX",
    "gn:dem":105,
    "gn:feature_class":"P",
    "gn:feature_code":"PPL",
    "gn:name":"Chimalaco",
    "gn:population":714,
    "gn:timezone":"America/Mexico_City",
    "iso:country":"MX",
    "wof:name":"Chimalaco",
    "wof:placetype":"locality",
    "wof:population":714
},
  "geometry": {"coordinates":[-98.93971999999999,21.46083],"type":"Point"}
}