{
  "type": "Feature",
  "properties": {
    "gn:admin1_code":"19.0",
    "gn:admin2_code":"17.0",
    "gn:asciiname":"El Barrial",
    "gn:cc2":"MX",
    "gn:country_code":"MX",
    "gn:dem":1705,
    "gn:feature_class":"P",
    "gn:feature_code":"PPL",
    "gn:name":"El Barrial",
    "gn:population":2,
    "gn:timezone":"America/Monterrey",
    "iso:country":"MX",
    "name:spa_x_preferred":[
        "El Barrial"
    ],
    "name:und_x_variant":[
        "Barreal",
        "El Barrial"
    ],
    "wof:name":"El Barrial",
    "wof:placetype":"locality",
    "wof:population":2
},
  "geometry": {"coordinates":[-100.00221000000001,24.77063],"type":"Point"}
}