{
  "type": "Feature",
  "properties": {
    "gn:admin1_code":"30",
    "gn:admin2_code":"91.0",
    "gn:asciiname":"El Tesoro",
    "gn:country_code":"MX",
    "gn:dem":81,
    "gn:feature_class":"P",
    "gn:feature_code":"PPL",
    "gn:name":"El Tesoro",
    "gn:population":163,
    "gn:timezone":"America/Mexico_City",
    "iso:country":"MX",
    "wof:name":"El Tesoro",
    "wof:placetype":"locality",
    "wof:population":163
},
  "geometry": {"coordinates":[-94.81444,17.295],"type":"Point"}
}