{
  "type": "Feature",
  "properties": {
    "gn:admin1_code":"2",
    "gn:admin2_code":"1.0",
    "gn:asciiname":"Malvar",
    "gn:country_code":"MX",
    "gn:dem":147,
    "gn:feature_class":"P",
    "gn:feature_code":"PPL",
    "gn:name":"Malvar",
    "gn:population":0,
    "gn:timezone":"America/Tijuana",
    "iso:country":"MX",
    "name:spa_x_preferred":[
        "Malvar"
    ],
    "wof:name":"Malvar",
    "wof:placetype":"locality"
},
  "geometry": {"coordinates":[-115.47436999999999,29.81635],"type":"Point"}
}