{
  "type": "Feature",
  "properties": {
    "gn:admin1_code":"5",
    "gn:admin2_code":"52",
    "gn:asciiname":"Anexo Azafran",
    "gn:country_code":"MX",
    "gn:dem":2137,
    "gn:feature_class":"P",
    "gn:feature_code":"PPL",
    "gn:name":"Anexo Azafr\u00e1n",
    "gn:population":29,
    "gn:timezone":"America/Mexico_City",
    "iso:country":"MX",
    "name:und_x_variant":[
        "Anexo Azafr\u00e1n"
    ],
    "wof:name":"Anexo Azafran",
    "wof:placetype":"locality",
    "wof:population":29
},
  "geometry": {"coordinates":[-91.9225,16.50667],"type":"Point"}
}