{
  "type": "Feature",
  "properties": {
    "gn:admin1_code":"3",
    "gn:admin2_code":"1.0",
    "gn:asciiname":"Las Lisas",
    "gn:country_code":"MX",
    "gn:dem":47,
    "gn:feature_class":"P",
    "gn:feature_code":"PPL",
    "gn:name":"Las Lisas",
    "gn:population":0,
    "gn:timezone":"America/Mazatlan",
    "iso:country":"MX",
    "name:spa_x_preferred":[
        "Las Lisas"
    ],
    "wof:name":"Las Lisas",
    "wof:placetype":"locality"
},
  "geometry": {"coordinates":[-112.22665000000001,26.18],"type":"Point"}
}