{
  "type": "Feature",
  "properties": {
    "gn:admin1_code":"21",
    "gn:asciiname":"Ingrid",
    "gn:country_code":"MX",
    "gn:dem":2805,
    "gn:feature_class":"P",
    "gn:feature_code":"PPL",
    "gn:name":"Ingrid",
    "gn:population":0,
    "gn:timezone":"America/Mexico_City",
    "iso:country":"MX",
    "name:ara_x_preferred":[
        "\u0625\u0646\u063a\u0631\u064a\u062f"
    ],
    "name:ceb_x_preferred":[
        "Ingrid"
    ],
    "name:est_x_preferred":[
        "Ingrid"
    ],
    "name:fra_x_preferred":[
        "Ingrid"
    ],
    "name:jpn_x_preferred":[
        "\u30a4\u30f3\u30b0\u30ea\u30c3\u30c9"
    ],
    "name:por_x_preferred":[
        "Ingrid"
    ],
    "name:rus_x_preferred":[
        "\u0418\u043d\u0433\u0440\u0438\u0434"
    ],
    "name:spa_x_preferred":[
        "Ingrid"
    ],
    "name:ukr_x_preferred":[
        "\u0406\u043d\u0433\u0440\u0456\u0434"
    ],
    "wof:name":"Ingrid",
    "wof:placetype":"locality"
},
  "geometry": {"coordinates":[-98.07875,19.6976],"type":"Point"}
}