{
  "type": "Feature",
  "properties": {
    "gn:admin1_code":"14",
    "gn:admin2_code":"19",
    "gn:asciiname":"Rancho el Saucito",
    "gn:country_code":"MX",
    "gn:dem":1753,
    "gn:feature_class":"P",
    "gn:feature_code":"PPL",
    "gn:name":"Rancho el Saucito",
    "gn:population":25,
    "gn:timezone":"America/Mexico_City",
    "iso:country":"MX",
    "wof:name":"Rancho el Saucito",
    "wof:placetype":"locality",
    "wof:population":25
},
  "geometry": {"coordinates":[-103.98444000000001,21.80528],"type":"Point"}
}