{
  "type": "Feature",
  "properties": {
    "gn:admin1_code":"7.0",
    "gn:admin2_code":"23.0",
    "gn:asciiname":"Claveinas",
    "gn:country_code":"MX",
    "gn:dem":1092,
    "gn:feature_class":"P",
    "gn:feature_code":"PPL",
    "gn:name":"Claveinas",
    "gn:population":0,
    "gn:timezone":"America/Monterrey",
    "iso:country":"MX",
    "name:spa_x_preferred":[
        "Claveinas"
    ],
    "wof:name":"Claveinas",
    "wof:placetype":"locality"
},
  "geometry": {"coordinates":[-103.0566,27.74247],"type":"Point"}
}