{
  "type": "Feature",
  "properties": {
    "gn:admin1_code":"14",
    "gn:admin2_code":"90.0",
    "gn:asciiname":"Portezuelo",
    "gn:cc2":"MX",
    "gn:country_code":"MX",
    "gn:dem":1435,
    "gn:feature_class":"P",
    "gn:feature_code":"PPL",
    "gn:name":"Portezuelo",
    "gn:population":0,
    "gn:timezone":"America/Mexico_City",
    "iso:country":"MX",
    "name:und_x_variant":[
        "El Portezuelo",
        "Portezuela",
        "Portezuelo"
    ],
    "wof:name":"Portezuelo",
    "wof:placetype":"locality"
},
  "geometry": {"coordinates":[-104.18333,20.15],"type":"Point"}
}