{
  "type": "Feature",
  "properties": {
    "gn:admin1_code":"14",
    "gn:admin2_code":"90.0",
    "gn:asciiname":"Portezuelo",
    "gn:cc2":"MX",
    "gn:country_code":"MX",
    "gn:dem":1435,
    "gn:feature_class":"P",
    "gn:feature_code":"PPL",
    "gn:name":"Portezuelo",
    "gn:population":0,
    "gn:timezone":"America/Mexico_City",
    "iso:country":"MX",
    "name:bre_x_preferred":[
        "Portezuelo"
    ],
    "name:ceb_x_preferred":[
        "Portezuelo"
    ],
    "name:deu_x_preferred":[
        "Portezuelo"
    ],
    "name:eus_x_preferred":[
        "Portezuelo"
    ],
    "name:fra_x_preferred":[
        "Portezuelo"
    ],
    "name:glg_x_preferred":[
        "Portezuelo"
    ],
    "name:ita_x_preferred":[
        "Portezuelo"
    ],
    "name:kor_x_preferred":[
        "\ud3ec\ub974\ud14c\uc218\uc5d8\ub85c"
    ],
    "name:nld_x_preferred":[
        "Portezuelo"
    ],
    "name:oci_x_preferred":[
        "Portezuelo"
    ],
    "name:por_x_preferred":[
        "Portezuelo"
    ],
    "name:ron_x_preferred":[
        "Portezuelo"
    ],
    "name:rus_x_preferred":[
        "\u041f\u043e\u0440\u0442\u0435\u0441\u0443\u044d\u043b\u043e"
    ],
    "name:spa_x_preferred":[
        "Portezuelo"
    ],
    "name:srp_x_preferred":[
        "\u041f\u043e\u0440\u0442\u0435\u0437\u0443\u0435\u043b\u043e"
    ],
    "name:swe_x_preferred":[
        "Portezuelo"
    ],
    "name:und_x_variant":[
        "El Portezuelo",
        "Portezuela"
    ],
    "wof:name":"Portezuelo",
    "wof:placetype":"locality"
},
  "geometry": {"coordinates":[-104.18333,20.15],"type":"Point"}
}