{
  "type": "Feature",
  "properties": {
    "gn:admin1_code":"32",
    "gn:admin2_code":"39.0",
    "gn:asciiname":"Manuel Fernandez",
    "gn:country_code":"MX",
    "gn:dem":1887,
    "gn:feature_class":"P",
    "gn:feature_code":"PPL",
    "gn:name":"Manuel Fern\u00e1ndez",
    "gn:population":6,
    "gn:timezone":"America/Mexico_City",
    "iso:country":"MX",
    "name:und_x_variant":[
        "Manuel Fern\u00e1ndez"
    ],
    "wof:name":"Manuel Fernandez",
    "wof:placetype":"locality",
    "wof:population":6
},
  "geometry": {"coordinates":[-103.045,23.81],"type":"Point"}
}