{
  "type": "Feature",
  "properties": {
    "gn:admin1_code":"5",
    "gn:admin2_code":"52.0",
    "gn:asciiname":"Gabino Vazquez San Sebastian",
    "gn:country_code":"MX",
    "gn:dem":1512,
    "gn:feature_class":"P",
    "gn:feature_code":"PPL",
    "gn:name":"Gabino V\u00e1zquez San Sebasti\u00e1n",
    "gn:population":760,
    "gn:timezone":"America/Mexico_City",
    "iso:country":"MX",
    "name:und_x_variant":[
        "Gabino V\u00e1zquez San Sebasti\u00e1n"
    ],
    "wof:name":"Gabino Vazquez San Sebastian",
    "wof:placetype":"locality",
    "wof:population":760
},
  "geometry": {"coordinates":[-91.93722,16.35056],"type":"Point"}
}