{
  "type": "Feature",
  "properties": {
    "gn:admin1_code":"7",
    "gn:admin2_code":"36.0",
    "gn:asciiname":"Las Calaveras",
    "gn:country_code":"MX",
    "gn:dem":1094,
    "gn:feature_class":"P",
    "gn:feature_code":"PPL",
    "gn:name":"Las Calaveras",
    "gn:population":0,
    "gn:timezone":"America/Monterrey",
    "iso:country":"MX",
    "name:spa_x_preferred":[
        "Las Calaveras"
    ],
    "wof:name":"Las Calaveras",
    "wof:placetype":"locality"
},
  "geometry": {"coordinates":[-102.92157,25.48048],"type":"Point"}
}