{
  "type": "Feature",
  "properties": {
    "gn:admin1_code":"30.0",
    "gn:asciiname":"La Chatilla",
    "gn:country_code":"MX",
    "gn:dem":68,
    "gn:feature_class":"P",
    "gn:feature_code":"PPL",
    "gn:name":"La Chatilla",
    "gn:population":0,
    "gn:timezone":"America/Mexico_City",
    "iso:country":"MX",
    "name:spa_x_preferred":[
        "La Chatilla"
    ],
    "wof:name":"La Chatilla",
    "wof:placetype":"locality"
},
  "geometry": {"coordinates":[-95.47689,17.9899],"type":"Point"}
}