{
  "type": "Feature",
  "properties": {
    "gn:admin1_code":"11",
    "gn:admin2_code":"23.0",
    "gn:asciiname":"Presa de Joya de Mulas",
    "gn:country_code":"MX",
    "gn:dem":1815,
    "gn:feature_class":"P",
    "gn:feature_code":"PPL",
    "gn:name":"Presa de Joya de Mulas",
    "gn:population":56,
    "gn:timezone":"America/Mexico_City",
    "iso:country":"MX",
    "wof:name":"Presa de Joya de Mulas",
    "wof:placetype":"locality",
    "wof:population":56
},
  "geometry": {"coordinates":[-101.91694,20.44722],"type":"Point"}
}