{
  "type": "Feature",
  "properties": {
    "gn:admin1_code":"24",
    "gn:admin2_code":"36.0",
    "gn:asciiname":"Huamuchil",
    "gn:country_code":"MX",
    "gn:dem":421,
    "gn:feature_class":"P",
    "gn:feature_code":"PPL",
    "gn:name":"Huam\u00fachil",
    "gn:population":185,
    "gn:timezone":"America/Mexico_City",
    "iso:country":"MX",
    "name:und_x_variant":[
        "Huam\u00fachil"
    ],
    "wof:name":"Huamuchil",
    "wof:placetype":"locality",
    "wof:population":185
},
  "geometry": {"coordinates":[-99.30361000000001,22.115],"type":"Point"}
}