{
  "type": "Feature",
  "properties": {
    "gn:admin1_code":"7",
    "gn:admin2_code":"14.0",
    "gn:asciiname":"Juana Santana Rosa",
    "gn:country_code":"MX",
    "gn:dem":311,
    "gn:feature_class":"P",
    "gn:feature_code":"PPL",
    "gn:name":"Juana Santana Rosa",
    "gn:population":0,
    "gn:timezone":"America/Monterrey",
    "iso:country":"MX",
    "name:spa_x_preferred":[
        "Juana Santana Rosa"
    ],
    "name:und_x_variant":[
        "Juana Santa Rosa"
    ],
    "wof:name":"Juana Santana Rosa",
    "wof:placetype":"locality"
},
  "geometry": {"coordinates":[-100.82268000000001,29.01911],"type":"Point"}
}