{
  "type": "Feature",
  "properties": {
    "gn:admin1_code":"30",
    "gn:admin2_code":"4.0",
    "gn:asciiname":"Zoyacuautla",
    "gn:country_code":"MX",
    "gn:dem":296,
    "gn:feature_class":"P",
    "gn:feature_code":"PPL",
    "gn:name":"Zoyacuautla",
    "gn:population":0,
    "gn:timezone":"America/Mexico_City",
    "iso:country":"MX",
    "name:und_x_variant":[
        "Sayocuautitla",
        "Soyacuautla",
        "Zoyacuautla"
    ],
    "wof:name":"Zoyacuautla",
    "wof:placetype":"locality"
},
  "geometry": {"coordinates":[-96.57738000000001,19.57652],"type":"Point"}
}