{
  "type": "Feature",
  "properties": {
    "gn:admin1_code":"6.0",
    "gn:admin2_code":"32.0",
    "gn:asciiname":"La Huerta",
    "gn:country_code":"MX",
    "gn:dem":1563,
    "gn:feature_class":"P",
    "gn:feature_code":"PPL",
    "gn:name":"La Huerta",
    "gn:population":0,
    "gn:timezone":"America/Chihuahua",
    "iso:country":"MX",
    "name:ceb_x_preferred":[
        "La Huerta"
    ],
    "name:spa_x_preferred":[
        "La Huerta"
    ],
    "name:swe_x_preferred":[
        "La Huerta"
    ],
    "name:und_x_variant":[
        "Huerta",
        "La Huerta"
    ],
    "wof:name":"La Huerta",
    "wof:placetype":"locality"
},
  "geometry": {"coordinates":[-105.92999,27.13524],"type":"Point"}
}