{
  "type": "Feature",
  "properties": {
    "gn:admin1_code":"12",
    "gn:admin2_code":"28",
    "gn:asciiname":"24 de Febrero",
    "gn:country_code":"MX",
    "gn:dem":1404,
    "gn:feature_class":"P",
    "gn:feature_code":"PPL",
    "gn:name":"24 de Febrero",
    "gn:population":35,
    "gn:timezone":"America/Mexico_City",
    "iso:country":"MX",
    "wof:name":"24 de Febrero",
    "wof:placetype":"locality",
    "wof:population":35
},
  "geometry": {"coordinates":[-99.15443999999999,17.59389],"type":"Point"}
}