{
  "type": "Feature",
  "properties": {
    "gn:admin1_code":"2.0",
    "gn:admin2_code":"3.0",
    "gn:asciiname":"El Cerrito Tanama",
    "gn:country_code":"MX",
    "gn:dem":672,
    "gn:feature_class":"P",
    "gn:feature_code":"PPL",
    "gn:name":"El Cerrito Tanam\u00e1",
    "gn:population":20,
    "gn:timezone":"America/Tijuana",
    "iso:country":"MX",
    "name:spa_x_preferred":[
        "Tanam\u00e1"
    ],
    "wof:name":"El Cerrito Tanama",
    "wof:placetype":"locality",
    "wof:population":20
},
  "geometry": {"coordinates":[-116.59611,32.50528],"type":"Point"}
}