{
  "type": "Feature",
  "properties": {
    "gn:admin1_code":"28.0",
    "gn:admin2_code":"42.0",
    "gn:asciiname":"Las Viejas",
    "gn:country_code":"MX",
    "gn:dem":303,
    "gn:feature_class":"P",
    "gn:feature_code":"PPL",
    "gn:name":"Las Viejas",
    "gn:population":0,
    "gn:timezone":"America/Monterrey",
    "iso:country":"MX",
    "name:spa_x_preferred":[
        "Las Viejas"
    ],
    "wof:name":"Las Viejas",
    "wof:placetype":"locality"
},
  "geometry": {"coordinates":[-99.31867,24.55752],"type":"Point"}
}