{
  "type": "Feature",
  "properties": {
    "gn:admin1_code":"25",
    "gn:admin2_code":"11.0",
    "gn:asciiname":"Ninguno [Campo Rufino Felix]",
    "gn:country_code":"MX",
    "gn:dem":19,
    "gn:feature_class":"P",
    "gn:feature_code":"PPL",
    "gn:name":"Ninguno [Campo Rufino Fel\u00edx]",
    "gn:population":7,
    "gn:timezone":"America/Mazatlan",
    "iso:country":"MX",
    "name:und_x_variant":[
        "Ninguno [Campo Rufino Fel\u00edx]"
    ],
    "wof:name":"Ninguno [Campo Rufino Felix]",
    "wof:placetype":"locality",
    "wof:population":7
},
  "geometry": {"coordinates":[-108.80886,25.76091],"type":"Point"}
}