{
  "type": "Feature",
  "properties": {
    "gn:admin1_code":"14.0",
    "gn:admin2_code":"86.0",
    "gn:asciiname":"Puerta de los Bueyes",
    "gn:country_code":"MX",
    "gn:dem":1653,
    "gn:feature_class":"P",
    "gn:feature_code":"PPL",
    "gn:name":"Puerta de los Bueyes",
    "gn:population":0,
    "gn:timezone":"America/Mexico_City",
    "iso:country":"MX",
    "name:spa_x_preferred":[
        "Puerta de los Bueyes"
    ],
    "wof:name":"Puerta de los Bueyes",
    "wof:placetype":"locality"
},
  "geometry": {"coordinates":[-103.86566999999999,19.96446],"type":"Point"}
}