{
  "type": "Feature",
  "properties": {
    "gn:admin1_code":"21",
    "gn:admin2_code":"58.0",
    "gn:asciiname":"Plan de los Organos",
    "gn:country_code":"MX",
    "gn:dem":2879,
    "gn:feature_class":"P",
    "gn:feature_code":"PPL",
    "gn:name":"Plan de los \u00d3rganos",
    "gn:population":2,
    "gn:timezone":"America/Mexico_City",
    "iso:country":"MX",
    "wof:name":"Plan de los Organos",
    "wof:placetype":"locality",
    "wof:population":2
},
  "geometry": {"coordinates":[-97.24048999999999,19.31735],"type":"Point"}
}