{
  "type": "Feature",
  "properties": {
    "gn:admin1_code":"12",
    "gn:admin2_code":"52.0",
    "gn:asciiname":"Renacimiento",
    "gn:country_code":"MX",
    "gn:dem":328,
    "gn:feature_class":"P",
    "gn:feature_code":"PPL",
    "gn:name":"Renacimiento",
    "gn:population":140,
    "gn:timezone":"America/Mexico_City",
    "iso:country":"MX",
    "wof:name":"Renacimiento",
    "wof:placetype":"locality",
    "wof:population":140
},
  "geometry": {"coordinates":[-98.72889000000001,16.86889],"type":"Point"}
}