{
  "type": "Feature",
  "properties": {
    "gn:admin1_code":"6.0",
    "gn:asciiname":"Sacramento",
    "gn:country_code":"MX",
    "gn:dem":1153,
    "gn:feature_class":"P",
    "gn:feature_code":"PPL",
    "gn:name":"Sacramento",
    "gn:population":0,
    "gn:timezone":"America/Chihuahua",
    "iso:country":"MX",
    "name:spa_x_preferred":[
        "Sacramento"
    ],
    "wof:name":"Sacramento",
    "wof:placetype":"locality"
},
  "geometry": {"coordinates":[-105.47905,28.23665],"type":"Point"}
}