{
  "type": "Feature",
  "properties": {
    "gn:admin1_code":"5",
    "gn:admin2_code":"12",
    "gn:asciiname":"Monte Bonito",
    "gn:country_code":"MX",
    "gn:dem":468,
    "gn:feature_class":"P",
    "gn:feature_code":"PPL",
    "gn:name":"Monte Bonito",
    "gn:population":9,
    "gn:timezone":"America/Mexico_City",
    "iso:country":"MX",
    "wof:name":"Monte Bonito",
    "wof:placetype":"locality",
    "wof:population":9
},
  "geometry": {"coordinates":[-93.36972,16.9375],"type":"Point"}
}