{
  "type": "Feature",
  "properties": {
    "gn:admin1_code":"30.0",
    "gn:admin2_code":"144.0",
    "gn:asciiname":"El Escondido",
    "gn:country_code":"MX",
    "gn:dem":60,
    "gn:feature_class":"P",
    "gn:feature_code":"PPL",
    "gn:name":"El Escondido",
    "gn:population":0,
    "gn:timezone":"America/Mexico_City",
    "iso:country":"MX",
    "name:spa_x_preferred":[
        "El Escondido"
    ],
    "wof:name":"El Escondido",
    "wof:placetype":"locality"
},
  "geometry": {"coordinates":[-94.92202,17.91047],"type":"Point"}
}