{
  "type": "Feature",
  "properties": {
    "gn:admin1_code":"5",
    "gn:admin2_code":"107",
    "gn:asciiname":"Las Nubes",
    "gn:country_code":"MX",
    "gn:dem":738,
    "gn:feature_class":"P",
    "gn:feature_code":"PPL",
    "gn:name":"Las Nubes",
    "gn:population":11,
    "gn:timezone":"America/Mexico_City",
    "iso:country":"MX",
    "wof:name":"Las Nubes",
    "wof:placetype":"locality",
    "wof:population":11
},
  "geometry": {"coordinates":[-93.04555999999999,16.23861],"type":"Point"}
}