{
  "type": "Feature",
  "properties": {
    "gn:admin1_code":"22",
    "gn:admin2_code":"4.0",
    "gn:asciiname":"Bonu",
    "gn:country_code":"MX",
    "gn:dem":2068,
    "gn:feature_class":"P",
    "gn:feature_code":"PPL",
    "gn:name":"Bo\u00f1\u00fa",
    "gn:population":0,
    "gn:timezone":"America/Mexico_City",
    "iso:country":"MX",
    "wof:name":"Bonu",
    "wof:placetype":"locality"
},
  "geometry": {"coordinates":[-99.73333,20.68333],"type":"Point"}
}