{
  "type": "Feature",
  "properties": {
    "gn:admin1_code":"30.0",
    "gn:admin2_code":"151.0",
    "gn:asciiname":"Paso Grande",
    "gn:country_code":"MX",
    "gn:dem":23,
    "gn:feature_class":"P",
    "gn:feature_code":"PPL",
    "gn:name":"Paso Grande",
    "gn:population":89,
    "gn:timezone":"America/Mexico_City",
    "iso:country":"MX",
    "name:ceb_x_preferred":[
        "Paso Grande"
    ],
    "name:spa_x_preferred":[
        "Paso Grande"
    ],
    "name:swe_x_preferred":[
        "Paso Grande"
    ],
    "wof:name":"Paso Grande",
    "wof:placetype":"locality",
    "wof:population":89
},
  "geometry": {"coordinates":[-97.50917,21.22694],"type":"Point"}
}