{
  "type": "Feature",
  "properties": {
    "gn:admin1_code":"5",
    "gn:admin2_code":"2",
    "gn:asciiname":"La Trinitaria",
    "gn:country_code":"MX",
    "gn:dem":510,
    "gn:feature_class":"P",
    "gn:feature_code":"PPL",
    "gn:name":"La Trinitaria",
    "gn:population":9,
    "gn:timezone":"America/Mexico_City",
    "iso:country":"MX",
    "wof:name":"La Trinitaria",
    "wof:placetype":"locality",
    "wof:population":9
},
  "geometry": {"coordinates":[-92.86389,16.49861],"type":"Point"}
}