{
  "type": "Feature",
  "properties": {
    "gn:admin1_code":"20",
    "gn:admin2_code":"324",
    "gn:asciiname":"Zacamalin",
    "gn:country_code":"MX",
    "gn:dem":32,
    "gn:feature_class":"P",
    "gn:feature_code":"PPL",
    "gn:name":"Zacamal\u00edn",
    "gn:population":50,
    "gn:timezone":"America/Mexico_City",
    "iso:country":"MX",
    "name:und_x_variant":[
        "Zacamal\u00edn"
    ],
    "wof:name":"Zacamalin",
    "wof:placetype":"locality",
    "wof:population":50
},
  "geometry": {"coordinates":[-96.39639,15.69972],"type":"Point"}
}