{
  "type": "Feature",
  "properties": {
    "gn:admin1_code":"32.0",
    "gn:admin2_code":"10.0",
    "gn:asciiname":"Cienega de Santa Cruz",
    "gn:country_code":"MX",
    "gn:dem":2094,
    "gn:feature_class":"P",
    "gn:feature_code":"PPL",
    "gn:name":"Ci\u00e9nega de Santa Cruz",
    "gn:population":0,
    "gn:timezone":"America/Mexico_City",
    "iso:country":"MX",
    "name:spa_x_preferred":[
        "Ci\u00e9nega de Santa Cruz"
    ],
    "wof:name":"Cienega de Santa Cruz",
    "wof:placetype":"locality"
},
  "geometry": {"coordinates":[-103.09401,23.16367],"type":"Point"}
}