{
  "type": "Feature",
  "properties": {
    "gn:admin1_code":"16",
    "gn:admin2_code":"8",
    "gn:asciiname":"Marialito",
    "gn:country_code":"MX",
    "gn:dem":458,
    "gn:feature_class":"P",
    "gn:feature_code":"PPL",
    "gn:name":"Marialito",
    "gn:population":13,
    "gn:timezone":"America/Mexico_City",
    "iso:country":"MX",
    "wof:name":"Marialito",
    "wof:placetype":"locality",
    "wof:population":13
},
  "geometry": {"coordinates":[-103.35944000000001,18.40389],"type":"Point"}
}