{
  "type": "Feature",
  "properties": {
    "gn:admin1_code":"1.0",
    "gn:admin2_code":"1.0",
    "gn:asciiname":"El Refugio de Penuelas",
    "gn:country_code":"MX",
    "gn:dem":1864,
    "gn:feature_class":"P",
    "gn:feature_code":"PPL",
    "gn:name":"El Refugio de Pe\u00f1uelas",
    "gn:population":0,
    "gn:timezone":"America/Mexico_City",
    "iso:country":"MX",
    "name:spa_x_preferred":[
        "El Refugio de Pe\u00f1uelas"
    ],
    "wof:name":"El Refugio de Penuelas",
    "wof:placetype":"locality"
},
  "geometry": {"coordinates":[-102.28941,21.71635],"type":"Point"}
}