{
  "type": "Feature",
  "properties": {
    "gn:admin1_code":"5",
    "gn:admin2_code":"65",
    "gn:asciiname":"El Milagro",
    "gn:country_code":"MX",
    "gn:dem":35,
    "gn:feature_class":"P",
    "gn:feature_code":"PPL",
    "gn:name":"El Milagro",
    "gn:population":12,
    "gn:timezone":"America/Mexico_City",
    "iso:country":"MX",
    "wof:name":"El Milagro",
    "wof:placetype":"locality",
    "wof:population":12
},
  "geometry": {"coordinates":[-91.86556,17.48082999999999],"type":"Point"}
}