{
  "type": "Feature",
  "properties": {
    "gn:admin1_code":"26",
    "gn:admin2_code":"2.0",
    "gn:asciiname":"Roberto Lopez (La Virgen)",
    "gn:country_code":"MX",
    "gn:dem":1298,
    "gn:feature_class":"P",
    "gn:feature_code":"PPL",
    "gn:name":"Roberto L\u00f3pez (La Virgen)",
    "gn:population":9,
    "gn:timezone":"America/Hermosillo",
    "iso:country":"MX",
    "name:und_x_variant":[
        "Roberto L\u00f3pez (La Virgen)"
    ],
    "wof:name":"Roberto Lopez (La Virgen)",
    "wof:placetype":"locality",
    "wof:population":9
},
  "geometry": {"coordinates":[-109.48667,31.29056],"type":"Point"}
}