{
  "type": "Feature",
  "properties": {
    "gn:admin1_code":"7",
    "gn:admin2_code":"36.0",
    "gn:asciiname":"Ejido Emiliano Zapata",
    "gn:country_code":"MX",
    "gn:dem":1101,
    "gn:feature_class":"P",
    "gn:feature_code":"PPL",
    "gn:name":"Ejido Emiliano Zapata",
    "gn:population":0,
    "gn:timezone":"America/Monterrey",
    "iso:country":"MX",
    "name:spa_x_preferred":[
        "Ejido Emiliano Zapata"
    ],
    "name:und_x_variant":[
        "Emiliano Zapata"
    ],
    "wof:name":"Ejido Emiliano Zapata",
    "wof:placetype":"locality"
},
  "geometry": {"coordinates":[-102.9438,25.48834],"type":"Point"}
}