{
  "type": "Feature",
  "properties": {
    "gn:admin1_code":"12.0",
    "gn:admin2_code":"10.0",
    "gn:asciiname":"Cojiletepec",
    "gn:country_code":"MX",
    "gn:dem":2318,
    "gn:feature_class":"P",
    "gn:feature_code":"PPL",
    "gn:name":"Cojiletepec",
    "gn:population":0,
    "gn:timezone":"America/Mexico_City",
    "iso:country":"MX",
    "name:spa_x_preferred":[
        "Cojiletepec"
    ],
    "wof:name":"Cojiletepec",
    "wof:placetype":"locality"
},
  "geometry": {"coordinates":[-98.85629,17.43548],"type":"Point"}
}