{
  "type": "Feature",
  "properties": {
    "gn:admin1_code":"11",
    "gn:admin2_code":"29.0",
    "gn:asciiname":"Noria de Catalan",
    "gn:country_code":"MX",
    "gn:dem":2007,
    "gn:feature_class":"P",
    "gn:feature_code":"PPL",
    "gn:name":"Noria de Catal\u00e1n",
    "gn:population":200,
    "gn:timezone":"America/Mexico_City",
    "iso:country":"MX",
    "name:und_x_variant":[
        "Noria de Catal\u00e1n"
    ],
    "wof:name":"Noria de Catalan",
    "wof:placetype":"locality",
    "wof:population":200
},
  "geometry": {"coordinates":[-100.72944,21.32528],"type":"Point"}
}