{
  "type": "Feature",
  "properties": {
    "gn:admin1_code":"6",
    "gn:admin2_code":"30.0",
    "gn:asciiname":"Aremuigana",
    "gn:country_code":"MX",
    "gn:dem":1276,
    "gn:feature_class":"P",
    "gn:feature_code":"PPL",
    "gn:name":"Aremuigana",
    "gn:population":0,
    "gn:timezone":"America/Chihuahua",
    "iso:country":"MX",
    "name:spa_x_preferred":[
        "Aremuigana"
    ],
    "wof:name":"Aremuigana",
    "wof:placetype":"locality"
},
  "geometry": {"coordinates":[-108.2167,27.40249],"type":"Point"}
}