{
  "type": "Feature",
  "properties": {
    "gn:admin1_code":"12",
    "gn:admin2_code":"49",
    "gn:asciiname":"Poza Larga (Puente Cristo)",
    "gn:country_code":"MX",
    "gn:dem":1620,
    "gn:feature_class":"P",
    "gn:feature_code":"PPL",
    "gn:name":"Poza Larga (Puente Cristo)",
    "gn:population":51,
    "gn:timezone":"America/Mexico_City",
    "iso:country":"MX",
    "wof:name":"Poza Larga (Puente Cristo)",
    "wof:placetype":"locality",
    "wof:population":51
},
  "geometry": {"coordinates":[-99.67194000000001,18.7569],"type":"Point"}
}