{
  "type": "Feature",
  "properties": {
    "gn:country":"MX",
    "gn:fcode":"PPLX",
    "gn:population":100000,
    "iso:country":"MX",
    "name:spa_x_preferred":[
        "Col. Lindavista"
    ],
    "name:spa_x_variant":[
        "Col Lindavista",
        "Lindavista"
    ],
    "qs_pg:aaroncc":"MX",
    "qs_pg:gn_country":"MX",
    "qs_pg:gn_fcode":"PPLX",
    "qs_pg:gn_pop":100000,
    "qs_pg:name":"Colonia Lindavista",
    "qs_pg:photos_9r":0,
    "qs_pg:photos_sr":0,
    "qs_pg:pop_sr":8,
    "qs_pg:qs_pg_placetype":"neighbourhood",
    "wof:name":"Colonia Lindavista",
    "wof:placetype":"neighbourhood",
    "wof:population":100000
},
  "geometry": {"coordinates":[-99.12475000000001,19.49156],"type":"Point"}
}