{
  "type": "Feature",
  "properties": {
    "gn:admin1_code":"14",
    "gn:admin2_code":"94.0",
    "gn:asciiname":"La Puerta de San Pedro (La Puerta de Enmedio)",
    "gn:country_code":"MX",
    "gn:dem":1171,
    "gn:feature_class":"P",
    "gn:feature_code":"PPL",
    "gn:name":"La Puerta de San Pedro (La Puerta de Enmedio)",
    "gn:population":167,
    "gn:timezone":"America/Mexico_City",
    "iso:country":"MX",
    "wof:name":"La Puerta de San Pedro (La Puerta de Enmedio)",
    "wof:placetype":"locality",
    "wof:population":167
},
  "geometry": {"coordinates":[-103.84389,20.92778],"type":"Point"}
}