{
  "type": "Feature",
  "properties": {
    "gn:admin1_code":"26.0",
    "gn:admin2_code":"20.0",
    "gn:asciiname":"El Cherokee",
    "gn:country_code":"MX",
    "gn:dem":500,
    "gn:feature_class":"P",
    "gn:feature_code":"PPL",
    "gn:name":"El Cherokee",
    "gn:population":0,
    "gn:timezone":"America/Hermosillo",
    "iso:country":"MX",
    "name:spa_x_preferred":[
        "El Cherokee"
    ],
    "wof:name":"El Cherokee",
    "wof:placetype":"locality"
},
  "geometry": {"coordinates":[-110.92689,29.73187],"type":"Point"}
}