{
  "type": "Feature",
  "properties": {
    "gn:admin1_code":"6",
    "gn:admin2_code":"5.0",
    "gn:asciiname":"Entronque (Ley Seis de Enero)",
    "gn:country_code":"MX",
    "gn:dem":1214,
    "gn:feature_class":"P",
    "gn:feature_code":"PPL",
    "gn:name":"Entronque (Ley Seis de Enero)",
    "gn:population":745,
    "gn:timezone":"America/Chihuahua",
    "iso:country":"MX",
    "wof:name":"Entronque (Ley Seis de Enero)",
    "wof:placetype":"locality",
    "wof:population":745
},
  "geometry": {"coordinates":[-107.60861,31.46833],"type":"Point"}
}