{
  "type": "Feature",
  "properties": {
    "gn:admin1_code":"12",
    "gn:admin2_code":"69.0",
    "gn:asciiname":"Xilotepec (Jilotepec Chiquito)",
    "gn:country_code":"MX",
    "gn:dem":1834,
    "gn:feature_class":"P",
    "gn:feature_code":"PPL",
    "gn:name":"Xilotepec (Jilotepec Chiquito)",
    "gn:population":890,
    "gn:timezone":"America/Mexico_City",
    "iso:country":"MX",
    "wof:name":"Xilotepec (Jilotepec Chiquito)",
    "wof:placetype":"locality",
    "wof:population":890
},
  "geometry": {"coordinates":[-98.55222000000001,17.40528],"type":"Point"}
}