{
  "type": "Feature",
  "properties": {
    "gn:admin1_code":"12",
    "gn:admin2_code":"7",
    "gn:asciiname":"La Parotita",
    "gn:country_code":"MX",
    "gn:dem":1489,
    "gn:feature_class":"P",
    "gn:feature_code":"PPL",
    "gn:name":"La Parotita",
    "gn:population":29,
    "gn:timezone":"America/Mexico_City",
    "iso:country":"MX",
    "wof:name":"La Parotita",
    "wof:placetype":"locality",
    "wof:population":29
},
  "geometry": {"coordinates":[-100.12859,18.21301],"type":"Point"}
}