{
  "type": "Feature",
  "properties": {
    "gn:admin1_code":"20",
    "gn:admin2_code":"439.0",
    "gn:asciiname":"Paso de las Garzas",
    "gn:country_code":"MX",
    "gn:dem":136,
    "gn:feature_class":"P",
    "gn:feature_code":"PPL",
    "gn:name":"Paso de las Garzas",
    "gn:population":0,
    "gn:timezone":"America/Mexico_City",
    "iso:country":"MX",
    "name:spa_x_preferred":[
        "Paso Las Garzas"
    ],
    "name:spa_x_variant":[
        "Paso de las Garzas"
    ],
    "wof:name":"Paso de las Garzas",
    "wof:placetype":"locality"
},
  "geometry": {"coordinates":[-96.72284999999999,15.79331],"type":"Point"}
}