{
  "type": "Feature",
  "properties": {
    "gn:admin1_code":"12.0",
    "gn:asciiname":"El Guaje",
    "gn:country_code":"MX",
    "gn:dem":1366,
    "gn:feature_class":"P",
    "gn:feature_code":"PPL",
    "gn:name":"El Guaje",
    "gn:population":0,
    "gn:timezone":"America/Mexico_City",
    "iso:country":"MX",
    "name:spa_x_preferred":[
        "El Guaje"
    ],
    "wof:name":"El Guaje",
    "wof:placetype":"locality"
},
  "geometry": {"coordinates":[-99.65982,17.62803],"type":"Point"}
}