{
  "type": "Feature",
  "properties": {
    "gn:admin1_code":"6.0",
    "gn:asciiname":"El Cincuenta",
    "gn:country_code":"MX",
    "gn:dem":1532,
    "gn:feature_class":"P",
    "gn:feature_code":"PPL",
    "gn:name":"El Cincuenta",
    "gn:population":0,
    "gn:timezone":"America/Chihuahua",
    "iso:country":"MX",
    "name:spa_x_preferred":[
        "El Cincuenta"
    ],
    "wof:name":"El Cincuenta",
    "wof:placetype":"locality"
},
  "geometry": {"coordinates":[-105.37846999999999,27.10027],"type":"Point"}
}