{
  "type": "Feature",
  "properties": {
    "gn:admin1_code":"25.0",
    "gn:asciiname":"Campo San Juan",
    "gn:country_code":"MX",
    "gn:dem":26,
    "gn:feature_class":"P",
    "gn:feature_code":"PPL",
    "gn:name":"Campo San Juan",
    "gn:population":0,
    "gn:timezone":"America/Mazatlan",
    "iso:country":"MX",
    "name:spa_x_preferred":[
        "Campo San Juan"
    ],
    "name:spa_x_variant":[
        "Kil\u00f3metro Veintiocho"
    ],
    "wof:name":"Campo San Juan",
    "wof:placetype":"locality"
},
  "geometry": {"coordinates":[-108.78545,25.88596],"type":"Point"}
}