{
  "type": "Feature",
  "properties": {
    "gn:admin1_code":"16.0",
    "gn:admin2_code":"29.0",
    "gn:asciiname":"Puerto el Varal",
    "gn:country_code":"MX",
    "gn:dem":786,
    "gn:feature_class":"P",
    "gn:feature_code":"PPL",
    "gn:name":"Puerto el Varal",
    "gn:population":0,
    "gn:timezone":"America/Mexico_City",
    "iso:country":"MX",
    "name:spa_x_preferred":[
        "Puerto el Varal"
    ],
    "name:und_x_variant":[
        "El Varal"
    ],
    "wof:name":"Puerto el Varal",
    "wof:placetype":"locality"
},
  "geometry": {"coordinates":[-101.52092,18.75331],"type":"Point"}
}