{
  "type": "Feature",
  "properties": {
    "gn:admin1_code":"6",
    "gn:admin2_code":"20.0",
    "gn:asciiname":"La Picurucha",
    "gn:country_code":"MX",
    "gn:dem":431,
    "gn:feature_class":"P",
    "gn:feature_code":"PPL",
    "gn:name":"La Picurucha",
    "gn:population":0,
    "gn:timezone":"America/Chihuahua",
    "iso:country":"MX",
    "name:spa_x_preferred":[
        "La Picurucha"
    ],
    "wof:name":"La Picurucha",
    "wof:placetype":"locality"
},
  "geometry": {"coordinates":[-108.50344,27.34081],"type":"Point"}
}