{
  "type": "Feature",
  "properties": {
    "gn:admin1_code":"16",
    "gn:admin2_code":"64",
    "gn:asciiname":"La Estacion de Antunez",
    "gn:country_code":"MX",
    "gn:dem":405,
    "gn:feature_class":"P",
    "gn:feature_code":"PPL",
    "gn:name":"La Estaci\u00f3n de Ant\u00fanez",
    "gn:population":10,
    "gn:timezone":"America/Mexico_City",
    "iso:country":"MX",
    "name:und_x_variant":[
        "La Estaci\u00f3n de Ant\u00fanez"
    ],
    "wof:name":"La Estacion de Antunez",
    "wof:placetype":"locality",
    "wof:population":10
},
  "geometry": {"coordinates":[-102.20193999999999,19.03917],"type":"Point"}
}