{
  "type": "Feature",
  "properties": {
    "gn:admin1_code":"30",
    "gn:admin2_code":"175.0",
    "gn:asciiname":"Los Arayoles (La India) [Granja]",
    "gn:country_code":"MX",
    "gn:dem":56,
    "gn:feature_class":"P",
    "gn:feature_code":"PPL",
    "gn:name":"Los Arayoles (La India) [Granja]",
    "gn:population":7,
    "gn:timezone":"America/Mexico_City",
    "iso:country":"MX",
    "wof:name":"Los Arayoles (La India) [Granja]",
    "wof:placetype":"locality",
    "wof:population":7
},
  "geometry": {"coordinates":[-97.49778000000001,20.55111],"type":"Point"}
}