{
  "type": "Feature",
  "properties": {
    "gn:admin1_code":"30.0",
    "gn:admin2_code":"161.0",
    "gn:asciiname":"El Ebanito",
    "gn:country_code":"MX",
    "gn:dem":107,
    "gn:feature_class":"P",
    "gn:feature_code":"PPL",
    "gn:name":"El Ebanito",
    "gn:population":27,
    "gn:timezone":"America/Mexico_City",
    "iso:country":"MX",
    "name:spa_x_preferred":[
        "El Ebanito"
    ],
    "wof:name":"El Ebanito",
    "wof:placetype":"locality",
    "wof:population":27
},
  "geometry": {"coordinates":[-98.27972,21.53528],"type":"Point"}
}