{
  "type": "Feature",
  "properties": {
    "gn:admin1_code":"14",
    "gn:admin2_code":"61.0",
    "gn:asciiname":"El Tepeguaje",
    "gn:country_code":"MX",
    "gn:dem":1602,
    "gn:feature_class":"P",
    "gn:feature_code":"PPL",
    "gn:name":"El Tepeguaje",
    "gn:population":0,
    "gn:timezone":"America/Mexico_City",
    "iso:country":"MX",
    "name:spa_x_preferred":[
        "El Tepeguaje"
    ],
    "wof:name":"El Tepeguaje",
    "wof:placetype":"locality"
},
  "geometry": {"coordinates":[-103.71419,22.50191],"type":"Point"}
}