{
  "type": "Feature",
  "properties": {
    "gn:admin1_code":"30",
    "gn:admin2_code":"3.0",
    "gn:asciiname":"Flumencio Caballero Rodriguez",
    "gn:country_code":"MX",
    "gn:dem":90,
    "gn:feature_class":"P",
    "gn:feature_code":"PPL",
    "gn:name":"Flumencio Caballero Rodr\u00edguez",
    "gn:population":7,
    "gn:timezone":"America/Mexico_City",
    "iso:country":"MX",
    "name:und_x_variant":[
        "Flumencio Caballero Rodr\u00edguez"
    ],
    "wof:name":"Flumencio Caballero Rodriguez",
    "wof:placetype":"locality",
    "wof:population":7
},
  "geometry": {"coordinates":[-95.03306000000001,17.985],"type":"Point"}
}