{
  "type": "Feature",
  "properties": {
    "gn:admin1_code":"11",
    "gn:admin2_code":"37.0",
    "gn:asciiname":"San Jose de las Cruces (Las Pulgas)",
    "gn:country_code":"MX",
    "gn:dem":1768,
    "gn:feature_class":"P",
    "gn:feature_code":"PPL",
    "gn:name":"San Jos\u00e9 de las Cruces (Las Pulgas)",
    "gn:population":236,
    "gn:timezone":"America/Mexico_City",
    "iso:country":"MX",
    "name:und_x_variant":[
        "San Jos\u00e9 de las Cruces (Las Pulgas)"
    ],
    "wof:name":"San Jose de las Cruces (Las Pulgas)",
    "wof:placetype":"locality",
    "wof:population":236
},
  "geometry": {"coordinates":[-101.36444,20.86472],"type":"Point"}
}