{
  "type": "Feature",
  "properties": {
    "gn:admin1_code":"30.0",
    "gn:admin2_code":"123.0",
    "gn:asciiname":"El Cid",
    "gn:country_code":"MX",
    "gn:dem":25,
    "gn:feature_class":"P",
    "gn:feature_code":"PPL",
    "gn:name":"El Cid",
    "gn:population":0,
    "gn:timezone":"America/Mexico_City",
    "iso:country":"MX",
    "name:ara_x_preferred":[
        "\u0625\u0644 \u0633\u064a\u062f"
    ],
    "name:azb_x_preferred":[
        "\u0627\u0644 \u0633\u06cc\u062f"
    ],
    "name:bar_x_preferred":[
        "El Cid"
    ],
    "name:bel_x_preferred":[
        "\u0421\u0456\u0434 \u041a\u0430\u043c\u043f\u0435\u0430\u0434\u043e\u0440"
    ],
    "name:ben_x_preferred":[
        "\u098f\u09b2 \u09b8\u09bf\u09a6"
    ],
    "name:bre_x_preferred":[
        "El Cid"
    ],
    "name:bul_x_preferred":[
        "\u0415\u043b \u0421\u0438\u0434"
    ],
    "name:ceb_x_preferred":[
        "El Cid"
    ],
    "name:ces_x_preferred":[
        "Cid"
    ],
    "name:cym_x_preferred":[
        "El Cid"
    ],
    "name:dan_x_preferred":[
        "El Cid"
    ],
    "name:deu_x_preferred":[
        "El Cid"
    ],
    "name:ell_x_preferred":[
        "\u0395\u03bb \u03a3\u03b9\u03bd\u03c4"
    ],
    "name:epo_x_preferred":[
        "Cido"
    ],
    "name:eus_x_preferred":[
        "Cid Campeador"
    ],
    "name:fas_x_preferred":[
        "\u0627\u0644 \u0633\u06cc\u062f"
    ],
    "name:fin_x_preferred":[
        "El Cid"
    ],
    "name:gle_x_preferred":[
        "El Cid"
    ],
    "name:hak_x_preferred":[
        "El Cid"
    ],
    "name:heb_x_preferred":[
        "\u05d0\u05dc \u05e1\u05d9\u05d3"
    ],
    "name:hye_x_preferred":[
        "\u0537\u056c \u054d\u056b\u0564"
    ],
    "name:ind_x_preferred":[
        "El Cid"
    ],
    "name:isl_x_preferred":[
        "El Cid"
    ],
    "name:ita_x_preferred":[
        "El Cid"
    ],
    "name:jpn_x_preferred":[
        "\u30a8\u30eb\u30fb\u30b7\u30c3\u30c9"
    ],
    "name:kat_x_preferred":[
        "\u10e1\u10d8\u10d3 \u10d9\u10d0\u10db\u10de\u10d4\u10d0\u10d3\u10dd\u10e0\u10d8"
    ],
    "name:kor_x_preferred":[
        "\ub85c\ub4dc\ub9ac\uace0 \ub514\uc544\uc2a4 \ub370 \ube44\ubc14\ub974"
    ],
    "name:lat_x_preferred":[
        "Rodericus Didaci"
    ],
    "name:mkd_x_preferred":[
        "\u0415\u043b \u0421\u0438\u0434"
    ],
    "name:nno_x_preferred":[
        "El Cid"
    ],
    "name:nor_x_preferred":[
        "El Cid"
    ],
    "name:pol_x_preferred":[
        "Cyd"
    ],
    "name:por_x_preferred":[
        "O Cid"
    ],
    "name:rus_x_preferred":[
        "\u0421\u0438\u0434 \u041a\u0430\u043c\u043f\u0435\u0430\u0434\u043e\u0440"
    ],
    "name:slk_x_preferred":[
        "El Cid Campeador"
    ],
    "name:slv_x_preferred":[
        "El Cid"
    ],
    "name:spa_x_preferred":[
        "El Cid"
    ],
    "name:srp_x_preferred":[
        "\u0420\u043e\u0434\u0440\u0438\u0433\u043e \u0414\u0438\u0458\u0430\u0437 \u0434\u0435 \u0412\u0438\u0432\u0430\u0440"
    ],
    "name:swe_x_preferred":[
        "El Cid"
    ],
    "name:tha_x_preferred":[
        "\u0e40\u0e2d\u0e25\u0e0b\u0e34\u0e14"
    ],
    "name:ukr_x_preferred":[
        "\u0421\u0456\u0434 \u041a\u0430\u043c\u043f\u0435\u0430\u0434\u043e\u0440"
    ],
    "name:urd_x_preferred":[
        "\u0627\u0644\u0633\u06cc\u062f"
    ],
    "name:vie_x_preferred":[
        "El Cid"
    ],
    "wof:name":"El Cid",
    "wof:placetype":"locality"
},
  "geometry": {"coordinates":[-98.52377,21.86483],"type":"Point"}
}