{
  "type": "Feature",
  "properties": {
    "gn:admin1_code":"30",
    "gn:admin2_code":"15.0",
    "gn:asciiname":"El Candelabro",
    "gn:country_code":"MX",
    "gn:dem":15,
    "gn:feature_class":"P",
    "gn:feature_code":"PPL",
    "gn:name":"El Candelabro",
    "gn:population":0,
    "gn:timezone":"America/Mexico_City",
    "iso:country":"MX",
    "name:spa_x_preferred":[
        "El Candelabro"
    ],
    "wof:name":"El Candelabro",
    "wof:placetype":"locality"
},
  "geometry": {"coordinates":[-95.47244999999999,18.55011],"type":"Point"}
}