{
  "type": "Feature",
  "properties": {
    "gn:admin1_code":"21",
    "gn:admin2_code":"194",
    "gn:asciiname":"Finca Rosita",
    "gn:country_code":"MX",
    "gn:dem":245,
    "gn:feature_class":"P",
    "gn:feature_code":"PPL",
    "gn:name":"Finca Rosita",
    "gn:population":26,
    "gn:timezone":"America/Mexico_City",
    "iso:country":"MX",
    "wof:name":"Finca Rosita",
    "wof:placetype":"locality",
    "wof:population":26
},
  "geometry": {"coordinates":[-97.58772999999999,20.49945],"type":"Point"}
}