{
  "type": "Feature",
  "properties": {
    "gn:admin1_code":"27",
    "gn:admin2_code":"12.0",
    "gn:asciiname":"Los Gurria",
    "gn:country_code":"MX",
    "gn:dem":10,
    "gn:feature_class":"P",
    "gn:feature_code":"PPL",
    "gn:name":"Los Gurr\u00eda",
    "gn:population":78,
    "gn:timezone":"America/Mexico_City",
    "iso:country":"MX",
    "name:und_x_variant":[
        "Los Gurr\u00eda"
    ],
    "wof:name":"Los Gurria",
    "wof:placetype":"locality",
    "wof:population":78
},
  "geometry": {"coordinates":[-92.64139,17.91028],"type":"Point"}
}