{
  "type": "Feature",
  "properties": {
    "gn:admin1_code":"10",
    "gn:admin2_code":"37",
    "gn:asciiname":"La Joya",
    "gn:country_code":"MX",
    "gn:dem":1780,
    "gn:feature_class":"P",
    "gn:feature_code":"PPL",
    "gn:name":"La Joya",
    "gn:population":38,
    "gn:timezone":"America/Monterrey",
    "iso:country":"MX",
    "wof:name":"La Joya",
    "wof:placetype":"locality",
    "wof:population":38
},
  "geometry": {"coordinates":[-106.54537000000001,25.30942000000001],"type":"Point"}
}