{
  "type": "Feature",
  "properties": {
    "gn:admin1_code":"11",
    "gn:admin2_code":"1",
    "gn:asciiname":"El Nido",
    "gn:country_code":"MX",
    "gn:dem":1702,
    "gn:feature_class":"P",
    "gn:feature_code":"PPL",
    "gn:name":"El Nido",
    "gn:population":16,
    "gn:timezone":"America/Mexico_City",
    "iso:country":"MX",
    "name:ceb_x_preferred":[
        "El Nido"
    ],
    "name:ita_x_preferred":[
        "El nido"
    ],
    "name:spa_x_preferred":[
        "El Nido"
    ],
    "name:srp_x_preferred":[
        "\u0415\u043b \u041d\u0438\u0434\u043e"
    ],
    "name:swe_x_preferred":[
        "El Nido"
    ],
    "wof:name":"El Nido",
    "wof:placetype":"locality",
    "wof:population":16
},
  "geometry": {"coordinates":[-101.40056,20.50278],"type":"Point"}
}