{
  "type": "Feature",
  "properties": {
    "gn:admin1_code":"5",
    "gn:admin2_code":"114.0",
    "gn:asciiname":"Benito Juarez",
    "gn:country_code":"MX",
    "gn:dem":140,
    "gn:feature_class":"P",
    "gn:feature_code":"PPL",
    "gn:name":"Benito Ju\u00e1rez",
    "gn:population":695,
    "gn:timezone":"America/Mexico_City",
    "iso:country":"MX",
    "wof:name":"Benito Juarez",
    "wof:placetype":"locality",
    "wof:population":695
},
  "geometry": {"coordinates":[-90.54277999999999,16.33583],"type":"Point"}
}