{
  "type": "Feature",
  "properties": {
    "gn:admin1_code":"14",
    "gn:admin2_code":"35.0",
    "gn:asciiname":"Chupadero y Anexos",
    "gn:country_code":"MX",
    "gn:dem":1933,
    "gn:feature_class":"P",
    "gn:feature_code":"PPL",
    "gn:name":"Chupadero y Anexos",
    "gn:population":5,
    "gn:timezone":"America/Mexico_City",
    "iso:country":"MX",
    "wof:name":"Chupadero y Anexos",
    "wof:placetype":"locality",
    "wof:population":5
},
  "geometry": {"coordinates":[-102.10389000000001,21.5325],"type":"Point"}
}