{
  "type": "Feature",
  "properties": {
    "gn:admin1_code":"6",
    "gn:admin2_code":"30.0",
    "gn:asciiname":"Mesa Colorada",
    "gn:country_code":"MX",
    "gn:dem":1687,
    "gn:feature_class":"P",
    "gn:feature_code":"PPL",
    "gn:name":"Mesa Colorada",
    "gn:population":8,
    "gn:timezone":"America/Chihuahua",
    "iso:country":"MX",
    "wof:name":"Mesa Colorada",
    "wof:placetype":"locality",
    "wof:population":8
},
  "geometry": {"coordinates":[-108.31327,27.56825],"type":"Point"}
}