{
  "type": "Feature",
  "properties": {
    "gn:admin1_code":"18.0",
    "gn:admin2_code":"4.0",
    "gn:asciiname":"Calexico",
    "gn:country_code":"MX",
    "gn:dem":797,
    "gn:feature_class":"P",
    "gn:feature_code":"PPL",
    "gn:name":"Cal\u00e9xico",
    "gn:population":14,
    "gn:timezone":"America/Mazatlan",
    "iso:country":"MX",
    "wof:name":"Calexico",
    "wof:placetype":"locality",
    "wof:population":14
},
  "geometry": {"coordinates":[-104.89608,21.13848],"type":"Point"}
}