{
  "type": "Feature",
  "properties": {
    "gn:admin1_code":"26",
    "gn:admin2_code":"47",
    "gn:asciiname":"La Casa Grande (La Inmaculada)",
    "gn:country_code":"MX",
    "gn:dem":684,
    "gn:feature_class":"P",
    "gn:feature_code":"PPL",
    "gn:name":"La Casa Grande (La Inmaculada)",
    "gn:population":10,
    "gn:timezone":"America/Hermosillo",
    "iso:country":"MX",
    "wof:name":"La Casa Grande (La Inmaculada)",
    "wof:placetype":"locality",
    "wof:population":10
},
  "geometry": {"coordinates":[-111.86861,29.95444],"type":"Point"}
}