{
  "type": "Feature",
  "properties": {
    "gn:admin1_code":"4",
    "gn:admin2_code":"3",
    "gn:asciiname":"Carlos V",
    "gn:country_code":"MX",
    "gn:dem":12,
    "gn:feature_class":"P",
    "gn:feature_code":"PPL",
    "gn:name":"Carlos V",
    "gn:population":10,
    "gn:timezone":"America/Merida",
    "iso:country":"MX",
    "wof:name":"Carlos V",
    "wof:placetype":"locality",
    "wof:population":10
},
  "geometry": {"coordinates":[-91.23721999999999,18.31722],"type":"Point"}
}