{
  "type": "Feature",
  "properties": {
    "gn:admin1_code":"24.0",
    "gn:admin2_code":"42.0",
    "gn:asciiname":"El Vergel",
    "gn:country_code":"MX",
    "gn:dem":52,
    "gn:feature_class":"P",
    "gn:feature_code":"PPL",
    "gn:name":"El Vergel",
    "gn:population":5,
    "gn:timezone":"America/Mexico_City",
    "iso:country":"MX",
    "name:spa_x_preferred":[
        "El Vergel"
    ],
    "wof:name":"El Vergel",
    "wof:placetype":"locality",
    "wof:population":5
},
  "geometry": {"coordinates":[-98.65227,21.58217],"type":"Point"}
}