{
  "type": "Feature",
  "properties": {
    "gn:admin1_code":"32",
    "gn:admin2_code":"49.0",
    "gn:asciiname":"Salsipuedes",
    "gn:country_code":"MX",
    "gn:dem":2035,
    "gn:feature_class":"P",
    "gn:feature_code":"PPL",
    "gn:name":"Salsipuedes",
    "gn:population":7,
    "gn:timezone":"America/Mexico_City",
    "iso:country":"MX",
    "name:ceb_x_preferred":[
        "Salsipuedes"
    ],
    "name:spa_x_preferred":[
        "Salsipuedes"
    ],
    "name:swe_x_preferred":[
        "Salsipuedes"
    ],
    "wof:name":"Salsipuedes",
    "wof:placetype":"locality",
    "wof:population":7
},
  "geometry": {"coordinates":[-103.50111,22.70944],"type":"Point"}
}