{
  "type": "Feature",
  "properties": {
    "gn:admin1_code":"7.0",
    "gn:admin2_code":"20.0",
    "gn:asciiname":"El Papalote",
    "gn:country_code":"MX",
    "gn:dem":424,
    "gn:feature_class":"P",
    "gn:feature_code":"PPL",
    "gn:name":"El Papalote",
    "gn:population":0,
    "gn:timezone":"America/Monterrey",
    "iso:country":"MX",
    "name:spa_x_preferred":[
        "El Papalote"
    ],
    "wof:name":"El Papalote",
    "wof:placetype":"locality"
},
  "geometry": {"coordinates":[-101.43891000000001,27.93294],"type":"Point"}
}