{
  "type": "Feature",
  "properties": {
    "gn:admin1_code":"23",
    "gn:admin2_code":"2.0",
    "gn:asciiname":"Villahermosa",
    "gn:country_code":"MX",
    "gn:dem":24,
    "gn:feature_class":"P",
    "gn:feature_code":"PPL",
    "gn:name":"Villahermosa",
    "gn:population":189,
    "gn:timezone":"America/Cancun",
    "iso:country":"MX",
    "wof:name":"Villahermosa",
    "wof:placetype":"locality",
    "wof:population":189
},
  "geometry": {"coordinates":[-88.07056,20.27972],"type":"Point"}
}