{
  "type": "Feature",
  "properties": {
    "gn:admin1_code":"16.0",
    "gn:admin2_code":"35.0",
    "gn:asciiname":"El Mayorazgo",
    "gn:country_code":"MX",
    "gn:dem":588,
    "gn:feature_class":"P",
    "gn:feature_code":"PPL",
    "gn:name":"El Mayorazgo",
    "gn:population":0,
    "gn:timezone":"America/Mexico_City",
    "iso:country":"MX",
    "name:spa_x_preferred":[
        "El Mayorazgo"
    ],
    "wof:name":"El Mayorazgo",
    "wof:placetype":"locality"
},
  "geometry": {"coordinates":[-101.88034,19.03459],"type":"Point"}
}