{
  "type": "Feature",
  "properties": {
    "gn:admin1_code":"24",
    "gn:admin2_code":"51.0",
    "gn:asciiname":"Valle de San Juan",
    "gn:country_code":"MX",
    "gn:dem":1582,
    "gn:feature_class":"P",
    "gn:feature_code":"PPL",
    "gn:name":"Valle de San Juan",
    "gn:population":0,
    "gn:timezone":"America/Mexico_City",
    "iso:country":"MX",
    "wof:name":"Valle de San Juan",
    "wof:placetype":"locality"
},
  "geometry": {"coordinates":[-100.57603,22.39819],"type":"Point"}
}