{
  "type": "Feature",
  "properties": {
    "gn:admin1_code":"21",
    "gn:admin2_code":"10.0",
    "gn:asciiname":"Mazatianquixco",
    "gn:country_code":"MX",
    "gn:dem":2478,
    "gn:feature_class":"P",
    "gn:feature_code":"PPL",
    "gn:name":"Mazatianquixco",
    "gn:population":607,
    "gn:timezone":"America/Mexico_City",
    "iso:country":"MX",
    "wof:name":"Mazatianquixco",
    "wof:placetype":"locality",
    "wof:population":607
},
  "geometry": {"coordinates":[-97.07861,18.43667],"type":"Point"}
}