{
  "type": "Feature",
  "properties": {
    "gn:admin1_code":"7",
    "gn:admin2_code":"38.0",
    "gn:asciiname":"El Capricho",
    "gn:country_code":"MX",
    "gn:dem":374,
    "gn:feature_class":"P",
    "gn:feature_code":"PPL",
    "gn:name":"El Capricho",
    "gn:population":4,
    "gn:timezone":"America/Monterrey",
    "iso:country":"MX",
    "name:cat_x_preferred":[
        "El Capricho"
    ],
    "name:ces_x_preferred":[
        "Casa El Capricho"
    ],
    "name:deu_x_preferred":[
        "Villa Quijano"
    ],
    "name:eus_x_preferred":[
        "El Capricho"
    ],
    "name:ita_x_preferred":[
        "Il Capriccio"
    ],
    "name:nld_x_preferred":[
        "El Capricho"
    ],
    "name:por_x_preferred":[
        "El Capricho"
    ],
    "name:rus_x_preferred":[
        "\u042d\u043b\u044c-\u041a\u0430\u043f\u0440\u0438\u0447\u0447\u043e"
    ],
    "name:spa_x_preferred":[
        "El Capricho"
    ],
    "wof:name":"El Capricho",
    "wof:placetype":"locality",
    "wof:population":4
},
  "geometry": {"coordinates":[-100.97342999999999,28.52302],"type":"Point"}
}