{
  "type": "Feature",
  "properties": {
    "gn:admin1_code":"11",
    "gn:admin2_code":"19.0",
    "gn:asciiname":"Salto de Pena",
    "gn:country_code":"MX",
    "gn:dem":2001,
    "gn:feature_class":"P",
    "gn:feature_code":"PPL",
    "gn:name":"Salto de Pe\u00f1a",
    "gn:population":964,
    "gn:timezone":"America/Mexico_City",
    "iso:country":"MX",
    "name:und_x_variant":[
        "Salto de Pe\u00f1a"
    ],
    "wof:name":"Salto de Pena",
    "wof:placetype":"locality",
    "wof:population":964
},
  "geometry": {"coordinates":[-100.61472000000001,20.3075],"type":"Point"}
}