{
  "type": "Feature",
  "properties": {
    "gn:admin1_code":"31.0",
    "gn:asciiname":"El Chivo",
    "gn:country_code":"MX",
    "gn:dem":22,
    "gn:feature_class":"P",
    "gn:feature_code":"PPL",
    "gn:name":"El Chivo",
    "gn:population":0,
    "gn:timezone":"America/Merida",
    "iso:country":"MX",
    "name:spa_x_preferred":[
        "El Chivo"
    ],
    "wof:name":"El Chivo",
    "wof:placetype":"locality"
},
  "geometry": {"coordinates":[-88.30393000000002,21.1683],"type":"Point"}
}