{
  "type": "Feature",
  "properties": {
    "gn:admin1_code":"15.0",
    "gn:admin2_code":"77.0",
    "gn:asciiname":"Los Berros Cuentla",
    "gn:country_code":"MX",
    "gn:dem":1766,
    "gn:feature_class":"P",
    "gn:feature_code":"PPL",
    "gn:name":"Los Berros Cuentla",
    "gn:population":0,
    "gn:timezone":"America/Mexico_City",
    "iso:country":"MX",
    "name:spa_x_preferred":[
        "Los Berros Cuentla"
    ],
    "wof:name":"Los Berros Cuentla",
    "wof:placetype":"locality"
},
  "geometry": {"coordinates":[-100.06216999999999,18.99884],"type":"Point"}
}