{
  "type": "Feature",
  "properties": {
    "gn:admin1_code":"12",
    "gn:admin2_code":"80.0",
    "gn:asciiname":"El Zapotito",
    "gn:country_code":"MX",
    "gn:dem":17,
    "gn:feature_class":"P",
    "gn:feature_code":"PPL",
    "gn:name":"El Zapotito",
    "gn:population":65,
    "gn:timezone":"America/Mexico_City",
    "iso:country":"MX",
    "wof:name":"El Zapotito",
    "wof:placetype":"locality",
    "wof:population":65
},
  "geometry": {"coordinates":[-98.68537999999999,16.53814],"type":"Point"}
}