{
  "type": "Feature",
  "properties": {
    "gn:admin1_code":"5",
    "gn:admin2_code":"88.0",
    "gn:asciiname":"El Cucayo 1ra. Seccion",
    "gn:country_code":"MX",
    "gn:dem":397,
    "gn:feature_class":"P",
    "gn:feature_code":"PPL",
    "gn:name":"El Cucayo 1ra. Secci\u00f3n",
    "gn:population":116,
    "gn:timezone":"America/Mexico_City",
    "iso:country":"MX",
    "wof:name":"El Cucayo 1ra. Seccion",
    "wof:placetype":"locality",
    "wof:population":116
},
  "geometry": {"coordinates":[-93.24944000000001,17.45167],"type":"Point"}
}