{
  "type": "Feature",
  "properties": {
    "gn:admin1_code":"6",
    "gn:admin2_code":"27.0",
    "gn:asciiname":"San Caralampio",
    "gn:country_code":"MX",
    "gn:dem":2355,
    "gn:feature_class":"P",
    "gn:feature_code":"PPL",
    "gn:name":"San Caralampio",
    "gn:population":0,
    "gn:timezone":"America/Chihuahua",
    "iso:country":"MX",
    "name:spa_x_preferred":[
        "San Caralampio"
    ],
    "name:und_x_variant":[
        "San Carampio"
    ],
    "wof:name":"San Caralampio",
    "wof:placetype":"locality"
},
  "geometry": {"coordinates":[-107.0124,26.9478],"type":"Point"}
}