{
  "type": "Feature",
  "properties": {
    "gn:admin1_code":"8",
    "gn:admin2_code":"9.0",
    "gn:asciiname":"Isidro Galvan",
    "gn:country_code":"MX",
    "gn:dem":24,
    "gn:feature_class":"P",
    "gn:feature_code":"PPL",
    "gn:name":"Isidro Galv\u00e1n",
    "gn:population":5,
    "gn:timezone":"America/Mexico_City",
    "iso:country":"MX",
    "name:und_x_variant":[
        "Isidro Galv\u00e1n"
    ],
    "wof:name":"Isidro Galvan",
    "wof:placetype":"locality",
    "wof:population":5
},
  "geometry": {"coordinates":[-103.92667,18.92972],"type":"Point"}
}