{
  "type": "Feature",
  "properties": {
    "gn:admin1_code":"10",
    "gn:admin2_code":"13.0",
    "gn:asciiname":"Las Virginias",
    "gn:country_code":"MX",
    "gn:dem":1162,
    "gn:feature_class":"P",
    "gn:feature_code":"PPL",
    "gn:name":"Las Virginias",
    "gn:population":0,
    "gn:timezone":"America/Monterrey",
    "iso:country":"MX",
    "name:spa_x_preferred":[
        "Las Virginias"
    ],
    "name:und_x_variant":[
        "Rancho Las Virgenes"
    ],
    "wof:name":"Las Virginias",
    "wof:placetype":"locality"
},
  "geometry": {"coordinates":[-103.94450000000001,26.26819],"type":"Point"}
}