{
  "type": "Feature",
  "properties": {
    "gn:admin1_code":"25",
    "gn:admin2_code":"17",
    "gn:asciiname":"Las Mesas",
    "gn:country_code":"MX",
    "gn:dem":704,
    "gn:feature_class":"P",
    "gn:feature_code":"PPL",
    "gn:name":"Las Mesas",
    "gn:population":18,
    "gn:timezone":"America/Mazatlan",
    "iso:country":"MX",
    "wof:name":"Las Mesas",
    "wof:placetype":"locality",
    "wof:population":18
},
  "geometry": {"coordinates":[-107.67486,26.08439],"type":"Point"}
}