{
  "type": "Feature",
  "properties": {
    "gn:admin1_code":"15",
    "gn:admin2_code":"50",
    "gn:asciiname":"La Gallera",
    "gn:country_code":"MX",
    "gn:dem":2499,
    "gn:feature_class":"P",
    "gn:feature_code":"PPL",
    "gn:name":"La Gallera",
    "gn:population":14,
    "gn:timezone":"America/Mexico_City",
    "iso:country":"MX",
    "wof:name":"La Gallera",
    "wof:placetype":"locality",
    "wof:population":14
},
  "geometry": {"coordinates":[-98.87756,19.12441],"type":"Point"}
}