{
  "type": "Feature",
  "properties": {
    "gn:admin1_code":"27.0",
    "gn:admin2_code":"16.0",
    "gn:asciiname":"Guadalupe Victoria",
    "gn:country_code":"MX",
    "gn:dem":66,
    "gn:feature_class":"P",
    "gn:feature_code":"PPL",
    "gn:name":"Guadalupe Victoria",
    "gn:population":0,
    "gn:timezone":"America/Mexico_City",
    "iso:country":"MX",
    "name:spa_x_preferred":[
        "Guadalupe Victoria"
    ],
    "wof:name":"Guadalupe Victoria",
    "wof:placetype":"locality"
},
  "geometry": {"coordinates":[-92.95869999999999,17.53892],"type":"Point"}
}