{
  "type": "Feature",
  "properties": {
    "gn:admin1_code":"14",
    "gn:admin2_code":"50.0",
    "gn:asciiname":"La Rosita",
    "gn:country_code":"MX",
    "gn:dem":1534,
    "gn:feature_class":"P",
    "gn:feature_code":"PPL",
    "gn:name":"La Rosita",
    "gn:population":5,
    "gn:timezone":"America/Mexico_City",
    "iso:country":"MX",
    "wof:name":"La Rosita",
    "wof:placetype":"locality",
    "wof:population":5
},
  "geometry": {"coordinates":[-103.42333000000001,20.23278],"type":"Point"}
}