{
  "type": "Feature",
  "properties": {
    "gn:admin1_code":"17",
    "gn:admin2_code":"4.0",
    "gn:asciiname":"Huitzililla",
    "gn:country_code":"MX",
    "gn:dem":1218,
    "gn:feature_class":"P",
    "gn:feature_code":"PPL",
    "gn:name":"Huitzililla",
    "gn:population":0,
    "gn:timezone":"America/Mexico_City",
    "iso:country":"MX",
    "name:spa_x_preferred":[
        "Huitzililla"
    ],
    "wof:name":"Huitzililla",
    "wof:placetype":"locality"
},
  "geometry": {"coordinates":[-98.89687000000001,18.69425],"type":"Point"}
}