{
  "type": "Feature",
  "properties": {
    "gn:admin1_code":"8",
    "gn:admin2_code":"9.0",
    "gn:asciiname":"El Rocio",
    "gn:country_code":"MX",
    "gn:dem":18,
    "gn:feature_class":"P",
    "gn:feature_code":"PPL",
    "gn:name":"El Roc\u00edo",
    "gn:population":7,
    "gn:timezone":"America/Mexico_City",
    "iso:country":"MX",
    "name:und_x_variant":[
        "El Roc\u00edo"
    ],
    "wof:name":"El Rocio",
    "wof:placetype":"locality",
    "wof:population":7
},
  "geometry": {"coordinates":[-103.72306,18.74222],"type":"Point"}
}