{
  "type": "Feature",
  "properties": {
    "gn:admin1_code":"12",
    "gn:admin2_code":"13.0",
    "gn:asciiname":"Quetzalapa",
    "gn:country_code":"MX",
    "gn:dem":430,
    "gn:feature_class":"P",
    "gn:feature_code":"PPL",
    "gn:name":"Quetzalapa",
    "gn:population":0,
    "gn:timezone":"America/Mexico_City",
    "iso:country":"MX",
    "name:spa_x_preferred":[
        "Quetzalapa"
    ],
    "wof:name":"Quetzalapa",
    "wof:placetype":"locality"
},
  "geometry": {"coordinates":[-98.50272,16.78551],"type":"Point"}
}