{
  "type": "Feature",
  "properties": {
    "gn:admin1_code":"11",
    "gn:admin2_code":"23.0",
    "gn:asciiname":"Santa Teresa de Morales Dos",
    "gn:country_code":"MX",
    "gn:dem":1697,
    "gn:feature_class":"P",
    "gn:feature_code":"PPL",
    "gn:name":"Santa Teresa de Morales Dos",
    "gn:population":123,
    "gn:timezone":"America/Mexico_City",
    "iso:country":"MX",
    "wof:name":"Santa Teresa de Morales Dos",
    "wof:placetype":"locality",
    "wof:population":123
},
  "geometry": {"coordinates":[-101.80139,20.31222],"type":"Point"}
}