{
  "type": "Feature",
  "properties": {
    "gn:admin1_code":"6",
    "gn:admin2_code":"2.0",
    "gn:asciiname":"Rubio",
    "gn:country_code":"MX",
    "gn:dem":1238,
    "gn:feature_class":"P",
    "gn:feature_code":"PPL",
    "gn:name":"Rubio",
    "gn:population":0,
    "gn:timezone":"America/Chihuahua",
    "iso:country":"MX",
    "name:cat_x_preferred":[
        "Rubio"
    ],
    "name:ceb_x_preferred":[
        "Rubio"
    ],
    "name:ces_x_preferred":[
        "Rubio"
    ],
    "name:deu_x_preferred":[
        "Rubio"
    ],
    "name:fas_x_preferred":[
        "\u0631\u0648\u0628\u06cc\u0648"
    ],
    "name:fra_x_preferred":[
        "Rubio"
    ],
    "name:glg_x_preferred":[
        "Rubio"
    ],
    "name:heb_x_preferred":[
        "\u05e8\u05d5\u05d1\u05d9\u05d5"
    ],
    "name:ita_x_preferred":[
        "Rubio"
    ],
    "name:jpn_x_preferred":[
        "\u30eb\u30d3\u30aa"
    ],
    "name:kaz_x_preferred":[
        "\u0420\u0443\u0431\u0438\u043e"
    ],
    "name:lav_x_preferred":[
        "Ruvio"
    ],
    "name:lit_x_preferred":[
        "Rubio"
    ],
    "name:pol_x_preferred":[
        "Rubio"
    ],
    "name:rus_x_preferred":[
        "\u0420\u0443\u0431\u0438\u043e"
    ],
    "name:swe_x_preferred":[
        "Rubio"
    ],
    "wof:name":"Rubio",
    "wof:placetype":"locality"
},
  "geometry": {"coordinates":[-105.83333,28.81667],"type":"Point"}
}