{
  "type": "Feature",
  "properties": {
    "gn:admin1_code":"6",
    "gn:admin2_code":"2.0",
    "gn:asciiname":"Rubio",
    "gn:country_code":"MX",
    "gn:dem":1238,
    "gn:feature_class":"P",
    "gn:feature_code":"PPL",
    "gn:name":"Rubio",
    "gn:population":0,
    "gn:timezone":"America/Chihuahua",
    "iso:country":"MX",
    "wof:name":"Rubio",
    "wof:placetype":"locality"
},
  "geometry": {"coordinates":[-105.83333,28.81667],"type":"Point"}
}