{
  "type": "Feature",
  "properties": {
    "gn:admin1_code":"32",
    "gn:admin2_code":"47.0",
    "gn:asciiname":"Estancia de Guadalupe",
    "gn:country_code":"MX",
    "gn:dem":1679,
    "gn:feature_class":"P",
    "gn:feature_code":"PPL",
    "gn:name":"Estancia de Guadalupe",
    "gn:population":0,
    "gn:timezone":"America/Mexico_City",
    "iso:country":"MX",
    "wof:name":"Estancia de Guadalupe",
    "wof:placetype":"locality"
},
  "geometry": {"coordinates":[-103.61351999999999,21.24073],"type":"Point"}
}