{
  "type": "Feature",
  "properties": {
    "gn:admin1_code":"5.0",
    "gn:admin2_code":"28.0",
    "gn:asciiname":"Nandalumi",
    "gn:country_code":"MX",
    "gn:dem":427,
    "gn:feature_class":"P",
    "gn:feature_code":"PPL",
    "gn:name":"Nandalumi",
    "gn:population":0,
    "gn:timezone":"America/Mexico_City",
    "iso:country":"MX",
    "name:spa_x_preferred":[
        "Nandalumi"
    ],
    "wof:name":"Nandalumi",
    "wof:placetype":"locality"
},
  "geometry": {"coordinates":[-92.73788999999999,16.52591],"type":"Point"}
}