{
  "type": "Feature",
  "properties": {
    "gn:admin1_code":"8.0",
    "gn:admin2_code":"6.0",
    "gn:asciiname":"El Rincon del Diablo",
    "gn:country_code":"MX",
    "gn:dem":28,
    "gn:feature_class":"P",
    "gn:feature_code":"PPL",
    "gn:name":"El Rinc\u00f3n del Diablo",
    "gn:population":0,
    "gn:timezone":"America/Mexico_City",
    "iso:country":"MX",
    "name:spa_x_preferred":[
        "El Rinc\u00f3n del Diablo"
    ],
    "name:und_x_variant":[
        "Rinc\u00f3n del Diablo"
    ],
    "wof:name":"El Rincon del Diablo",
    "wof:placetype":"locality"
},
  "geometry": {"coordinates":[-103.76658999999999,18.91563],"type":"Point"}
}