{
  "type": "Feature",
  "properties": {
    "gn:admin1_code":"30",
    "gn:admin2_code":"178.0",
    "gn:asciiname":"Barranca de Limon",
    "gn:country_code":"MX",
    "gn:dem":5,
    "gn:feature_class":"P",
    "gn:feature_code":"PPL",
    "gn:name":"Barranca de Lim\u00f3n",
    "gn:population":7,
    "gn:timezone":"America/Mexico_City",
    "iso:country":"MX",
    "name:spa_x_preferred":[
        "Barranca de Lim\u00f3n"
    ],
    "wof:name":"Barranca de Limon",
    "wof:placetype":"locality",
    "wof:population":7
},
  "geometry": {"coordinates":[-95.6503,18.55978],"type":"Point"}
}