{
  "type": "Feature",
  "properties": {
    "gn:admin1_code":"12",
    "gn:admin2_code":"8",
    "gn:asciiname":"Tlalalmulco",
    "gn:country_code":"MX",
    "gn:dem":627,
    "gn:feature_class":"P",
    "gn:feature_code":"PPL",
    "gn:name":"Tlalalmulco",
    "gn:population":10,
    "gn:timezone":"America/Mexico_City",
    "iso:country":"MX",
    "wof:name":"Tlalalmulco",
    "wof:placetype":"locality",
    "wof:population":10
},
  "geometry": {"coordinates":[-99.11096000000001,18.09608],"type":"Point"}
}