{
  "type": "Feature",
  "properties": {
    "gn:admin1_code":"5",
    "gn:admin2_code":"107",
    "gn:asciiname":"Agua Cristalina",
    "gn:country_code":"MX",
    "gn:dem":979,
    "gn:feature_class":"P",
    "gn:feature_code":"PPL",
    "gn:name":"Agua Cristalina",
    "gn:population":10,
    "gn:timezone":"America/Mexico_City",
    "iso:country":"MX",
    "wof:name":"Agua Cristalina",
    "wof:placetype":"locality",
    "wof:population":10
},
  "geometry": {"coordinates":[-93.38861,15.99222],"type":"Point"}
}