{
  "type": "Feature",
  "properties": {
    "gn:admin1_code":"14.0",
    "gn:admin2_code":"99.0",
    "gn:asciiname":"Llano Verde",
    "gn:country_code":"MX",
    "gn:dem":2016,
    "gn:feature_class":"P",
    "gn:feature_code":"PPL",
    "gn:name":"Llano Verde",
    "gn:population":0,
    "gn:timezone":"America/Mexico_City",
    "iso:country":"MX",
    "name:spa_x_preferred":[
        "Llano Verde"
    ],
    "wof:name":"Llano Verde",
    "wof:placetype":"locality"
},
  "geometry": {"coordinates":[-103.96853,19.53185],"type":"Point"}
}