{
  "type": "Feature",
  "properties": {
    "gn:admin1_code":"6.0",
    "gn:asciiname":"Rancho Sanchez",
    "gn:country_code":"MX",
    "gn:dem":1175,
    "gn:feature_class":"P",
    "gn:feature_code":"PPL",
    "gn:name":"Rancho S\u00e1nchez",
    "gn:population":0,
    "gn:timezone":"America/Chihuahua",
    "iso:country":"MX",
    "name:spa_x_preferred":[
        "Rancho S\u00e1nchez"
    ],
    "name:spa_x_variant":[
        "Santa Mar\u00eda"
    ],
    "wof:name":"Rancho Sanchez",
    "wof:placetype":"locality"
},
  "geometry": {"coordinates":[-105.56579000000001,28.40499],"type":"Point"}
}