{
  "type": "Feature",
  "properties": {
    "gn:admin1_code":"22",
    "gn:admin2_code":"18",
    "gn:asciiname":"Familia Dimas",
    "gn:country_code":"MX",
    "gn:dem":1566,
    "gn:feature_class":"P",
    "gn:feature_code":"PPL",
    "gn:name":"Familia Dimas",
    "gn:population":11,
    "gn:timezone":"America/Mexico_City",
    "iso:country":"MX",
    "wof:name":"Familia Dimas",
    "wof:placetype":"locality",
    "wof:population":11
},
  "geometry": {"coordinates":[-99.93306,20.91111],"type":"Point"}
}