{
  "type": "Feature",
  "properties": {
    "gn:admin1_code":"31",
    "gn:admin2_code":"50",
    "gn:asciiname":"El Jabin",
    "gn:country_code":"MX",
    "gn:dem":13,
    "gn:feature_class":"P",
    "gn:feature_code":"PPL",
    "gn:name":"El Jab\u00edn",
    "gn:population":17,
    "gn:timezone":"America/Merida",
    "iso:country":"MX",
    "name:und_x_variant":[
        "El Jab\u00edn"
    ],
    "wof:name":"El Jabin",
    "wof:placetype":"locality",
    "wof:population":17
},
  "geometry": {"coordinates":[-89.53889000000002,21.00833],"type":"Point"}
}