{
  "type": "Feature",
  "properties": {
    "gn:admin1_code":"26.0",
    "gn:admin2_code":"15.0",
    "gn:asciiname":"La Bacolla",
    "gn:country_code":"MX",
    "gn:dem":1004,
    "gn:feature_class":"P",
    "gn:feature_code":"PPL",
    "gn:name":"La Bacolla",
    "gn:population":0,
    "gn:timezone":"America/Hermosillo",
    "iso:country":"MX",
    "name:spa_x_preferred":[
        "La Bacolla"
    ],
    "wof:name":"La Bacolla",
    "wof:placetype":"locality"
},
  "geometry": {"coordinates":[-108.9117,30.43632],"type":"Point"}
}