{
  "type": "Feature",
  "properties": {
    "gn:admin1_code":"12",
    "gn:admin2_code":"69.0",
    "gn:asciiname":"Igualita",
    "gn:country_code":"MX",
    "gn:dem":1117,
    "gn:feature_class":"P",
    "gn:feature_code":"PPL",
    "gn:name":"Igualita",
    "gn:population":869,
    "gn:timezone":"America/Mexico_City",
    "iso:country":"MX",
    "wof:name":"Igualita",
    "wof:placetype":"locality",
    "wof:population":869
},
  "geometry": {"coordinates":[-98.51639,17.46027999999999],"type":"Point"}
}