{
  "type": "Feature",
  "properties": {
    "gn:admin1_code":"21",
    "gn:admin2_code":"208.0",
    "gn:asciiname":"San Bartolo",
    "gn:country_code":"MX",
    "gn:dem":2070,
    "gn:feature_class":"P",
    "gn:feature_code":"PPL",
    "gn:name":"San Bartolo",
    "gn:population":373,
    "gn:timezone":"America/Mexico_City",
    "iso:country":"MX",
    "wof:name":"San Bartolo",
    "wof:placetype":"locality",
    "wof:population":373
},
  "geometry": {"coordinates":[-97.96528000000001,19.9175],"type":"Point"}
}