{
  "type": "Feature",
  "properties": {
    "gn:admin1_code":"11",
    "gn:admin2_code":"12",
    "gn:asciiname":"La Sabina",
    "gn:country_code":"MX",
    "gn:dem":1884,
    "gn:feature_class":"P",
    "gn:feature_code":"PPL",
    "gn:name":"La Sabina",
    "gn:population":32,
    "gn:timezone":"America/Mexico_City",
    "iso:country":"MX",
    "wof:name":"La Sabina",
    "wof:placetype":"locality",
    "wof:population":32
},
  "geometry": {"coordinates":[-101.74083,20.66056],"type":"Point"}
}