{
  "type": "Feature",
  "properties": {
    "gn:admin1_code":"30",
    "gn:admin2_code":"58",
    "gn:asciiname":"La Tranca (Cuatzapotl)",
    "gn:country_code":"MX",
    "gn:dem":462,
    "gn:feature_class":"P",
    "gn:feature_code":"PPL",
    "gn:name":"La Tranca (Cuatzapotl)",
    "gn:population":24,
    "gn:timezone":"America/Mexico_City",
    "iso:country":"MX",
    "wof:name":"La Tranca (Cuatzapotl)",
    "wof:placetype":"locality",
    "wof:population":24
},
  "geometry": {"coordinates":[-98.11778,20.9025],"type":"Point"}
}