{
  "type": "Feature",
  "properties": {
    "gn:admin1_code":"28",
    "gn:admin2_code":"39",
    "gn:asciiname":"Adolfo Lopez Mateos",
    "gn:country_code":"MX",
    "gn:dem":1023,
    "gn:feature_class":"P",
    "gn:feature_code":"PPL",
    "gn:name":"Adolfo L\u00f3pez Mateos",
    "gn:population":20,
    "gn:timezone":"America/Monterrey",
    "iso:country":"MX",
    "name:und_x_variant":[
        "Adolfo L\u00f3pez Mateos"
    ],
    "wof:name":"Adolfo Lopez Mateos",
    "wof:placetype":"locality",
    "wof:population":20
},
  "geometry": {"coordinates":[-99.88472,22.75278],"type":"Point"}
}