{
  "type": "Feature",
  "properties": {
    "gn:admin1_code":"16",
    "gn:admin2_code":"93",
    "gn:asciiname":"Planillas",
    "gn:country_code":"MX",
    "gn:dem":2636,
    "gn:feature_class":"P",
    "gn:feature_code":"PPL",
    "gn:name":"Planillas",
    "gn:population":33,
    "gn:timezone":"America/Mexico_City",
    "iso:country":"MX",
    "wof:name":"Planillas",
    "wof:placetype":"locality",
    "wof:population":33
},
  "geometry": {"coordinates":[-100.20222,19.79278],"type":"Point"}
}