{
  "type": "Feature",
  "properties": {
    "gn:admin1_code":"27",
    "gn:admin2_code":"4.0",
    "gn:asciiname":"Medellin y Madero Tercera Seccion",
    "gn:country_code":"MX",
    "gn:dem":7,
    "gn:feature_class":"P",
    "gn:feature_code":"PPL",
    "gn:name":"Medell\u00edn y Madero Tercera Secci\u00f3n",
    "gn:population":0,
    "gn:timezone":"America/Mexico_City",
    "iso:country":"MX",
    "name:spa_x_preferred":[
        "Medell\u00edn y Madero Tercera Secci\u00f3n"
    ],
    "wof:name":"Medellin y Madero Tercera Seccion",
    "wof:placetype":"locality"
},
  "geometry": {"coordinates":[-92.84475999999999,18.10306],"type":"Point"}
}