{
  "type": "Feature",
  "properties": {
    "gn:admin1_code":"29",
    "gn:admin2_code":"21.0",
    "gn:asciiname":"Los Paredones",
    "gn:country_code":"MX",
    "gn:dem":2759,
    "gn:feature_class":"P",
    "gn:feature_code":"PPL",
    "gn:name":"Los Paredones",
    "gn:population":9,
    "gn:timezone":"America/Mexico_City",
    "iso:country":"MX",
    "wof:name":"Los Paredones",
    "wof:placetype":"locality",
    "wof:population":9
},
  "geometry": {"coordinates":[-98.54170000000001,19.50352],"type":"Point"}
}