{
  "type": "Feature",
  "properties": {
    "gn:admin1_code":"24",
    "gn:admin2_code":"34.0",
    "gn:asciiname":"Tasajeras",
    "gn:country_code":"MX",
    "gn:dem":47,
    "gn:feature_class":"P",
    "gn:feature_code":"PPL",
    "gn:name":"Tasajeras",
    "gn:population":240,
    "gn:timezone":"America/Mexico_City",
    "iso:country":"MX",
    "name:spa_x_preferred":[
        "Tasajeras"
    ],
    "wof:name":"Tasajeras",
    "wof:placetype":"locality",
    "wof:population":240
},
  "geometry": {"coordinates":[-98.63048999999999,21.77645],"type":"Point"}
}