{
  "type": "Feature",
  "properties": {
    "gn:admin1_code":"10",
    "gn:admin2_code":"5.0",
    "gn:asciiname":"Rancho Ramirez (Sagrado Corazon)",
    "gn:country_code":"MX",
    "gn:dem":1865,
    "gn:feature_class":"P",
    "gn:feature_code":"PPL",
    "gn:name":"Rancho Ram\u00edrez (Sagrado Coraz\u00f3n)",
    "gn:population":6,
    "gn:timezone":"America/Monterrey",
    "iso:country":"MX",
    "name:und_x_variant":[
        "Rancho Ram\u00edrez (Sagrado Coraz\u00f3n)"
    ],
    "wof:name":"Rancho Ramirez (Sagrado Corazon)",
    "wof:placetype":"locality",
    "wof:population":6
},
  "geometry": {"coordinates":[-104.57418,24.15751],"type":"Point"}
}