{
  "type": "Feature",
  "properties": {
    "gn:admin1_code":"30.0",
    "gn:asciiname":"El Girasol",
    "gn:country_code":"MX",
    "gn:dem":52,
    "gn:feature_class":"P",
    "gn:feature_code":"PPL",
    "gn:name":"El Girasol",
    "gn:population":0,
    "gn:timezone":"America/Mexico_City",
    "iso:country":"MX",
    "name:spa_x_preferred":[
        "El Girasol"
    ],
    "wof:name":"El Girasol",
    "wof:placetype":"locality"
},
  "geometry": {"coordinates":[-95.61814,17.94376],"type":"Point"}
}