{
  "type": "Feature",
  "properties": {
    "gn:admin1_code":"6",
    "gn:admin2_code":"65",
    "gn:asciiname":"Ocoyvo",
    "gn:country_code":"MX",
    "gn:dem":1898,
    "gn:feature_class":"P",
    "gn:feature_code":"PPL",
    "gn:name":"Ocoyvo",
    "gn:population":14,
    "gn:timezone":"America/Chihuahua",
    "iso:country":"MX",
    "wof:name":"Ocoyvo",
    "wof:placetype":"locality",
    "wof:population":14
},
  "geometry": {"coordinates":[-108.01242000000001,27.45798],"type":"Point"}
}