{
  "type": "Feature",
  "properties": {
    "gn:admin1_code":"19",
    "gn:admin2_code":"38.0",
    "gn:asciiname":"Los Juanes (Doctor Albino Contreras)",
    "gn:country_code":"MX",
    "gn:dem":358,
    "gn:feature_class":"P",
    "gn:feature_code":"PPL",
    "gn:name":"Los Juanes (Doctor Albino Contreras)",
    "gn:population":7,
    "gn:timezone":"America/Monterrey",
    "iso:country":"MX",
    "wof:name":"Los Juanes (Doctor Albino Contreras)",
    "wof:placetype":"locality",
    "wof:population":7
},
  "geometry": {"coordinates":[-99.89418000000001,25.26784],"type":"Point"}
}