{
  "type": "Feature",
  "properties": {
    "gn:admin1_code":"4",
    "gn:admin2_code":"3",
    "gn:asciiname":"La Flor",
    "gn:country_code":"MX",
    "gn:dem":2,
    "gn:feature_class":"P",
    "gn:feature_code":"PPL",
    "gn:name":"La Flor",
    "gn:population":11,
    "gn:timezone":"America/Merida",
    "iso:country":"MX",
    "name:fra_x_preferred":[
        "La flor"
    ],
    "wof:name":"La Flor",
    "wof:placetype":"locality",
    "wof:population":11
},
  "geometry": {"coordinates":[-92.31889,18.63139],"type":"Point"}
}