{
  "type": "Feature",
  "properties": {
    "gn:admin1_code":"13",
    "gn:admin2_code":"24",
    "gn:asciiname":"Bosque Real",
    "gn:country_code":"MX",
    "gn:dem":2162,
    "gn:feature_class":"P",
    "gn:feature_code":"PPL",
    "gn:name":"Bosque Real",
    "gn:population":18,
    "gn:timezone":"America/Mexico_City",
    "iso:country":"MX",
    "wof:name":"Bosque Real",
    "wof:placetype":"locality",
    "wof:population":18
},
  "geometry": {"coordinates":[-98.56021,20.18801],"type":"Point"}
}