{
  "type": "Feature",
  "properties": {
    "gn:admin1_code":"6.0",
    "gn:asciiname":"Quince de Mayo",
    "gn:country_code":"MX",
    "gn:dem":1199,
    "gn:feature_class":"P",
    "gn:feature_code":"PPL",
    "gn:name":"Quince de Mayo",
    "gn:population":0,
    "gn:timezone":"America/Chihuahua",
    "iso:country":"MX",
    "name:spa_x_preferred":[
        "Quince de Mayo"
    ],
    "wof:name":"Quince de Mayo",
    "wof:placetype":"locality"
},
  "geometry": {"coordinates":[-105.51388,28.10502],"type":"Point"}
}