{
  "type": "Feature",
  "properties": {
    "gn:admin1_code":"15.0",
    "gn:admin2_code":"89.0",
    "gn:asciiname":"Rancho Aculco",
    "gn:country_code":"MX",
    "gn:dem":2319,
    "gn:feature_class":"P",
    "gn:feature_code":"PPL",
    "gn:name":"Rancho Aculco",
    "gn:population":0,
    "gn:timezone":"America/Mexico_City",
    "iso:country":"MX",
    "name:spa_x_preferred":[
        "Rancho Aculco"
    ],
    "name:spa_x_variant":[
        "Aculco",
        "El Para\u00edso"
    ],
    "wof:name":"Rancho Aculco",
    "wof:placetype":"locality"
},
  "geometry": {"coordinates":[-98.87130999999999,19.17733],"type":"Point"}
}