{
  "type": "Feature",
  "properties": {
    "gn:admin1_code":"5",
    "gn:admin2_code":"31.0",
    "gn:asciiname":"Ba Axupja",
    "gn:country_code":"MX",
    "gn:dem":627,
    "gn:feature_class":"P",
    "gn:feature_code":"PPL",
    "gn:name":"Ba Axupja",
    "gn:population":173,
    "gn:timezone":"America/Mexico_City",
    "iso:country":"MX",
    "wof:name":"Ba Axupja",
    "wof:placetype":"locality",
    "wof:population":173
},
  "geometry": {"coordinates":[-91.98721999999999,17.20694],"type":"Point"}
}