{
  "type": "Feature",
  "properties": {
    "gn:admin1_code":"26",
    "gn:admin2_code":"58.0",
    "gn:asciiname":"La Cuatena",
    "gn:country_code":"MX",
    "gn:dem":672,
    "gn:feature_class":"P",
    "gn:feature_code":"PPL",
    "gn:name":"La Cuate\u00f1a",
    "gn:population":8,
    "gn:timezone":"America/Hermosillo",
    "iso:country":"MX",
    "name:und_x_variant":[
        "La Cuate\u00f1a"
    ],
    "wof:name":"La Cuatena",
    "wof:placetype":"locality",
    "wof:population":8
},
  "geometry": {"coordinates":[-111.14833,30.53639],"type":"Point"}
}