{
  "type": "Feature",
  "properties": {
    "gn:admin1_code":"22",
    "gn:admin2_code":"5.0",
    "gn:asciiname":"Familia Nicolas Barcenas",
    "gn:country_code":"MX",
    "gn:dem":1922,
    "gn:feature_class":"P",
    "gn:feature_code":"PPL",
    "gn:name":"Familia Nicol\u00e1s B\u00e1rcenas",
    "gn:population":6,
    "gn:timezone":"America/Mexico_City",
    "iso:country":"MX",
    "name:und_x_variant":[
        "Familia Nicol\u00e1s B\u00e1rcenas"
    ],
    "wof:name":"Familia Nicolas Barcenas",
    "wof:placetype":"locality",
    "wof:population":6
},
  "geometry": {"coordinates":[-100.10693999999999,20.6075],"type":"Point"}
}