{
  "type": "Feature",
  "properties": {
    "gn:admin1_code":"14",
    "gn:admin2_code":"94",
    "gn:asciiname":"El Colomo",
    "gn:country_code":"MX",
    "gn:dem":1181,
    "gn:feature_class":"P",
    "gn:feature_code":"PPL",
    "gn:name":"El Colomo",
    "gn:population":27,
    "gn:timezone":"America/Mexico_City",
    "iso:country":"MX",
    "wof:name":"El Colomo",
    "wof:placetype":"locality",
    "wof:population":27
},
  "geometry": {"coordinates":[-103.88194,20.95917],"type":"Point"}
}