{
  "type": "Feature",
  "properties": {
    "gn:admin1_code":"3.0",
    "gn:admin2_code":"1.0",
    "gn:asciiname":"Tinaja los Becerros",
    "gn:country_code":"MX",
    "gn:dem":388,
    "gn:feature_class":"P",
    "gn:feature_code":"PPL",
    "gn:name":"Tinaja los Becerros",
    "gn:population":0,
    "gn:timezone":"America/Mazatlan",
    "iso:country":"MX",
    "name:spa_x_preferred":[
        "Tinaja los Becerros"
    ],
    "wof:name":"Tinaja los Becerros",
    "wof:placetype":"locality"
},
  "geometry": {"coordinates":[-111.94606,26.28009],"type":"Point"}
}