{
  "type": "Feature",
  "properties": {
    "gn:admin1_code":"30",
    "gn:admin2_code":"58.0",
    "gn:asciiname":"Tocerca",
    "gn:country_code":"MX",
    "gn:dem":344,
    "gn:feature_class":"P",
    "gn:feature_code":"PPL",
    "gn:name":"Tocerca",
    "gn:population":0,
    "gn:timezone":"America/Mexico_City",
    "iso:country":"MX",
    "wof:name":"Tocerca",
    "wof:placetype":"locality"
},
  "geometry": {"coordinates":[-97.96666999999999,20.98333],"type":"Point"}
}