{
  "type": "Feature",
  "properties": {
    "gn:admin1_code":"12",
    "gn:admin2_code":"66.0",
    "gn:asciiname":"La Providencia",
    "gn:country_code":"MX",
    "gn:dem":1092,
    "gn:feature_class":"P",
    "gn:feature_code":"PPL",
    "gn:name":"La Providencia",
    "gn:population":363,
    "gn:timezone":"America/Mexico_City",
    "iso:country":"MX",
    "wof:name":"La Providencia",
    "wof:placetype":"locality",
    "wof:population":363
},
  "geometry": {"coordinates":[-98.60111000000001,17.54667],"type":"Point"}
}