{
  "type": "Feature",
  "properties": {
    "gn:admin1_code":"12",
    "gn:admin2_code":"79.0",
    "gn:asciiname":"Tepozcotlaloca",
    "gn:country_code":"MX",
    "gn:dem":1515,
    "gn:feature_class":"P",
    "gn:feature_code":"PPL",
    "gn:name":"Tepozcotlaloca",
    "gn:population":173,
    "gn:timezone":"America/Mexico_City",
    "iso:country":"MX",
    "wof:name":"Tepozcotlaloca",
    "wof:placetype":"locality",
    "wof:population":173
},
  "geometry": {"coordinates":[-99.01147,17.45845],"type":"Point"}
}