{
  "type": "Feature",
  "properties": {
    "gn:admin1_code":"12.0",
    "gn:admin2_code":"48.0",
    "gn:asciiname":"La Morena de Enmedio",
    "gn:country_code":"MX",
    "gn:dem":406,
    "gn:feature_class":"P",
    "gn:feature_code":"PPL",
    "gn:name":"La Morena de Enmedio",
    "gn:population":0,
    "gn:timezone":"America/Mexico_City",
    "iso:country":"MX",
    "name:spa_x_preferred":[
        "La Morena de Enmedio"
    ],
    "wof:name":"La Morena de Enmedio",
    "wof:placetype":"locality"
},
  "geometry": {"coordinates":[-101.17574999999999,17.7052],"type":"Point"}
}