{
  "type": "Feature",
  "properties": {
    "gn:admin1_code":"30",
    "gn:admin2_code":"197",
    "gn:asciiname":"El Vado",
    "gn:country_code":"MX",
    "gn:dem":229,
    "gn:feature_class":"P",
    "gn:feature_code":"PPL",
    "gn:name":"El Vado",
    "gn:population":28,
    "gn:timezone":"America/Mexico_City",
    "iso:country":"MX",
    "wof:name":"El Vado",
    "wof:placetype":"locality",
    "wof:population":28
},
  "geometry": {"coordinates":[-96.73139,19.90167000000001],"type":"Point"}
}