{
  "type": "Feature",
  "properties": {
    "gn:country":"MX",
    "gn:fcode":"PPL",
    "gn:population":0,
    "iso:country":"MX",
    "name:ceb_x_preferred":[
        "El Refugio"
    ],
    "name:deu_x_preferred":[
        "El Refugio"
    ],
    "name:ita_x_preferred":[
        "El Refugio"
    ],
    "name:nld_x_preferred":[
        "El Refugio"
    ],
    "name:por_x_preferred":[
        "El Refugio"
    ],
    "name:spa_x_preferred":[
        "El refugio"
    ],
    "name:swe_x_preferred":[
        "El Refugio"
    ],
    "qs_pg:aaroncc":"MX",
    "qs_pg:gn_country":"MX",
    "qs_pg:gn_fcode":"PPL",
    "qs_pg:gn_pop":0,
    "qs_pg:name":"El Refugio",
    "qs_pg:name_adm0":"M\u00e9xico",
    "qs_pg:name_adm1":"Chiapas",
    "qs_pg:photos":98,
    "qs_pg:photos_1k":20,
    "qs_pg:photos_9k":1,
    "qs_pg:photos_9r":3,
    "qs_pg:photos_all":98,
    "qs_pg:photos_sr":3,
    "qs_pg:pop_sr":0,
    "qs_pg:qs_pg_placetype":"neighbourhood",
    "qs_pg:qs_pg_placetype_gp":"Suburb",
    "qs_pg:woe_adm0":23424900,
    "woe:adm0_id":23424900,
    "woe:name_adm0":"M\u00e9xico",
    "woe:name_adm1":"Chiapas",
    "woe:placetype":"Suburb",
    "wof:name":"El Refugio",
    "wof:placetype":"neighbourhood"
},
  "geometry": {"coordinates":[-93.71666999999999,16.75],"type":"Point"}
}