{
  "type": "Feature",
  "properties": {
    "gn:admin1_code":"10.0",
    "gn:admin2_code":"1.0",
    "gn:asciiname":"La Nortena",
    "gn:country_code":"MX",
    "gn:dem":1928,
    "gn:feature_class":"P",
    "gn:feature_code":"PPL",
    "gn:name":"La Norte\u00f1a",
    "gn:population":0,
    "gn:timezone":"America/Monterrey",
    "iso:country":"MX",
    "name:spa_x_preferred":[
        "La Norte\u00f1a"
    ],
    "wof:name":"La Nortena",
    "wof:placetype":"locality"
},
  "geometry": {"coordinates":[-104.6979,24.47695],"type":"Point"}
}