{
  "type": "Feature",
  "properties": {
    "gn:admin1_code":"10.0",
    "gn:admin2_code":"5.0",
    "gn:asciiname":"Tucson",
    "gn:country_code":"MX",
    "gn:dem":1885,
    "gn:feature_class":"P",
    "gn:feature_code":"PPL",
    "gn:name":"Tucson",
    "gn:population":0,
    "gn:timezone":"America/Monterrey",
    "iso:country":"MX",
    "name:spa_x_preferred":[
        "Tucson"
    ],
    "wof:name":"Tucson",
    "wof:placetype":"locality"
},
  "geometry": {"coordinates":[-104.61078000000001,24.0732],"type":"Point"}
}