{
  "type": "Feature",
  "properties": {
    "gn:admin1_code":"21",
    "gn:admin2_code":"186.0",
    "gn:asciiname":"Mecayucan",
    "gn:country_code":"MX",
    "gn:dem":1714,
    "gn:feature_class":"P",
    "gn:feature_code":"PPL",
    "gn:name":"Mecayucan",
    "gn:population":103,
    "gn:timezone":"America/Mexico_City",
    "iso:country":"MX",
    "wof:name":"Mecayucan",
    "wof:placetype":"locality",
    "wof:population":103
},
  "geometry": {"coordinates":[-97.48772,19.87564],"type":"Point"}
}