{
  "type": "Feature",
  "properties": {
    "gn:admin1_code":"20",
    "gn:admin2_code":"59",
    "gn:asciiname":"El Gueche",
    "gn:country_code":"MX",
    "gn:dem":1685,
    "gn:feature_class":"P",
    "gn:feature_code":"PPL",
    "gn:name":"El Gueche",
    "gn:population":45,
    "gn:timezone":"America/Mexico_City",
    "iso:country":"MX",
    "wof:name":"El Gueche",
    "wof:placetype":"locality",
    "wof:population":45
},
  "geometry": {"coordinates":[-96.51889,16.29528],"type":"Point"}
}