{
  "type": "Feature",
  "properties": {
    "gn:admin1_code":"4",
    "gn:admin2_code":"11.0",
    "gn:asciiname":"Vicente Guerrero",
    "gn:country_code":"MX",
    "gn:dem":17,
    "gn:feature_class":"P",
    "gn:feature_code":"PPL",
    "gn:name":"Vicente Guerrero",
    "gn:population":374,
    "gn:timezone":"America/Merida",
    "iso:country":"MX",
    "wof:name":"Vicente Guerrero",
    "wof:placetype":"locality",
    "wof:population":374
},
  "geometry": {"coordinates":[-91.2325,18.18361],"type":"Point"}
}