{
  "type": "Feature",
  "properties": {
    "gn:admin1_code":"13",
    "gn:admin2_code":"42",
    "gn:asciiname":"Mina la 300 (Ixtapalapa)",
    "gn:country_code":"MX",
    "gn:dem":1084,
    "gn:feature_class":"P",
    "gn:feature_code":"PPL",
    "gn:name":"Mina la 300 (Ixtapalapa)",
    "gn:population":19,
    "gn:timezone":"America/Mexico_City",
    "iso:country":"MX",
    "wof:name":"Mina la 300 (Ixtapalapa)",
    "wof:placetype":"locality",
    "wof:population":19
},
  "geometry": {"coordinates":[-98.7627,20.96618],"type":"Point"}
}