{
  "type": "Feature",
  "properties": {
    "gn:admin1_code":"6",
    "gn:admin2_code":"1.0",
    "gn:asciiname":"San Luis (Noche Buena)",
    "gn:country_code":"MX",
    "gn:dem":1637,
    "gn:feature_class":"P",
    "gn:feature_code":"PPL",
    "gn:name":"San Luis (Noche Buena)",
    "gn:population":4,
    "gn:timezone":"America/Chihuahua",
    "iso:country":"MX",
    "wof:name":"San Luis (Noche Buena)",
    "wof:placetype":"locality",
    "wof:population":4
},
  "geometry": {"coordinates":[-106.35861,29.74861],"type":"Point"}
}