{
  "type": "Feature",
  "properties": {
    "gn:admin1_code":"2",
    "gn:admin2_code":"3.0",
    "gn:asciiname":"El Tapirito",
    "gn:country_code":"MX",
    "gn:dem":1323,
    "gn:feature_class":"P",
    "gn:feature_code":"PPL",
    "gn:name":"El Tapirito",
    "gn:population":0,
    "gn:timezone":"America/Tijuana",
    "iso:country":"MX",
    "name:spa_x_preferred":[
        "El Tapirito"
    ],
    "name:und_x_variant":[
        "Rancho Tapirito"
    ],
    "wof:name":"El Tapirito",
    "wof:placetype":"locality"
},
  "geometry": {"coordinates":[-116.14709000000001,32.33775],"type":"Point"}
}