{
  "type": "Feature",
  "properties": {
    "gn:admin1_code":"12",
    "gn:admin2_code":"72.0",
    "gn:asciiname":"Tres Lagunas",
    "gn:country_code":"MX",
    "gn:dem":1866,
    "gn:feature_class":"P",
    "gn:feature_code":"PPL",
    "gn:name":"Tres Lagunas",
    "gn:population":136,
    "gn:timezone":"America/Mexico_City",
    "iso:country":"MX",
    "name:por_x_preferred":[
        "Tres Lagunas"
    ],
    "name:spa_x_preferred":[
        "Tres Lagunas"
    ],
    "wof:name":"Tres Lagunas",
    "wof:placetype":"locality",
    "wof:population":136
},
  "geometry": {"coordinates":[-98.75194,17.42194],"type":"Point"}
}