{
  "type": "Feature",
  "properties": {
    "gn:admin1_code":"5",
    "gn:admin2_code":"8",
    "gn:asciiname":"El Potrero (El Arroyon)",
    "gn:country_code":"MX",
    "gn:dem":891,
    "gn:feature_class":"P",
    "gn:feature_code":"PPL",
    "gn:name":"El Potrero (El Arroy\u00f3n)",
    "gn:population":9,
    "gn:timezone":"America/Mexico_City",
    "iso:country":"MX",
    "name:und_x_variant":[
        "El Potrero (El Arroy\u00f3n)"
    ],
    "wof:name":"El Potrero (El Arroyon)",
    "wof:placetype":"locality",
    "wof:population":9
},
  "geometry": {"coordinates":[-92.755,15.77028],"type":"Point"}
}