{
  "type": "Feature",
  "properties": {
    "gn:admin1_code":"6.0",
    "gn:asciiname":"La Casita",
    "gn:country_code":"MX",
    "gn:dem":1502,
    "gn:feature_class":"P",
    "gn:feature_code":"PPL",
    "gn:name":"La Casita",
    "gn:population":0,
    "gn:timezone":"America/Chihuahua",
    "iso:country":"MX",
    "name:spa_x_preferred":[
        "La Casita"
    ],
    "wof:name":"La Casita",
    "wof:placetype":"locality"
},
  "geometry": {"coordinates":[-105.35578999999998,27.16374],"type":"Point"}
}