{
  "type": "Feature",
  "properties": {
    "gn:admin1_code":"10.0",
    "gn:admin2_code":"9.0",
    "gn:asciiname":"Bajio del Leon",
    "gn:country_code":"MX",
    "gn:dem":2658,
    "gn:feature_class":"P",
    "gn:feature_code":"PPL",
    "gn:name":"Bajio del Le\u00f3n",
    "gn:population":0,
    "gn:timezone":"America/Monterrey",
    "iso:country":"MX",
    "name:spa_x_preferred":[
        "Bajio del Le\u00f3n"
    ],
    "wof:name":"Bajio del Leon",
    "wof:placetype":"locality"
},
  "geometry": {"coordinates":[-106.19114,25.79522],"type":"Point"}
}