{
  "type": "Feature",
  "properties": {
    "gn:admin1_code":"6",
    "gn:admin2_code":"47.0",
    "gn:asciiname":"Milpillas",
    "gn:country_code":"MX",
    "gn:dem":1149,
    "gn:feature_class":"P",
    "gn:feature_code":"PPL",
    "gn:name":"Milpillas",
    "gn:population":0,
    "gn:timezone":"America/Chihuahua",
    "iso:country":"MX",
    "name:spa_x_preferred":[
        "Milpillas"
    ],
    "wof:name":"Milpillas",
    "wof:placetype":"locality"
},
  "geometry": {"coordinates":[-108.56829,28.10324],"type":"Point"}
}