{
  "type": "Feature",
  "properties": {
    "gn:admin1_code":"10.0",
    "gn:admin2_code":"1.0",
    "gn:asciiname":"Anahuac",
    "gn:country_code":"MX",
    "gn:dem":1937,
    "gn:feature_class":"P",
    "gn:feature_code":"PPL",
    "gn:name":"An\u00e1huac",
    "gn:population":0,
    "gn:timezone":"America/Monterrey",
    "iso:country":"MX",
    "name:ceb_x_preferred":[
        "Anahuac"
    ],
    "name:ita_x_preferred":[
        "Anahuac"
    ],
    "name:nld_x_preferred":[
        "Anahuac"
    ],
    "name:sco_x_preferred":[
        "Anahuac"
    ],
    "name:spa_x_preferred":[
        "An\u00e1huac"
    ],
    "name:swe_x_preferred":[
        "Anahuac"
    ],
    "name:und_x_variant":[
        "Palo Blanco",
        "Colonia An\u00f3huac"
    ],
    "wof:name":"Anahuac",
    "wof:placetype":"locality"
},
  "geometry": {"coordinates":[-104.6112,24.40963],"type":"Point"}
}