{
  "type": "Feature",
  "properties": {
    "gn:admin1_code":"30",
    "gn:admin2_code":"154.0",
    "gn:asciiname":"Cerro de Ayahuint",
    "gn:country_code":"MX",
    "gn:dem":147,
    "gn:feature_class":"P",
    "gn:feature_code":"PPL",
    "gn:name":"Cerro de Ayahuint",
    "gn:population":83,
    "gn:timezone":"America/Mexico_City",
    "iso:country":"MX",
    "wof:name":"Cerro de Ayahuint",
    "wof:placetype":"locality",
    "wof:population":83
},
  "geometry": {"coordinates":[-97.77972,21.43861],"type":"Point"}
}