{
  "type": "Feature",
  "properties": {
    "gn:admin1_code":"19.0",
    "gn:admin2_code":"13.0",
    "gn:asciiname":"Los Borregos",
    "gn:country_code":"MX",
    "gn:dem":157,
    "gn:feature_class":"P",
    "gn:feature_code":"PPL",
    "gn:name":"Los Borregos",
    "gn:population":0,
    "gn:timezone":"America/Monterrey",
    "iso:country":"MX",
    "name:spa_x_preferred":[
        "Los Borregos"
    ],
    "wof:name":"Los Borregos",
    "wof:placetype":"locality"
},
  "geometry": {"coordinates":[-99.31829,25.62898],"type":"Point"}
}