{
  "type": "Feature",
  "properties": {
    "gn:admin1_code":"25",
    "gn:admin2_code":"10.0",
    "gn:asciiname":"El Bordo",
    "gn:country_code":"MX",
    "gn:dem":44,
    "gn:feature_class":"P",
    "gn:feature_code":"PPL",
    "gn:name":"El Bordo",
    "gn:population":0,
    "gn:timezone":"America/Mazatlan",
    "iso:country":"MX",
    "name:ceb_x_preferred":[
        "El Bordo"
    ],
    "name:spa_x_preferred":[
        "El Bordo"
    ],
    "name:srp_x_preferred":[
        "\u0415\u043b \u0411\u043e\u0440\u0434\u043e"
    ],
    "name:swe_x_preferred":[
        "El Bordo"
    ],
    "wof:name":"El Bordo",
    "wof:placetype":"locality"
},
  "geometry": {"coordinates":[-108.9255,26.06233],"type":"Point"}
}