{
  "type": "Feature",
  "properties": {
    "gn:admin1_code":"8.0",
    "gn:admin2_code":"1.0",
    "gn:asciiname":"La Atravezada",
    "gn:country_code":"MX",
    "gn:dem":232,
    "gn:feature_class":"P",
    "gn:feature_code":"PPL",
    "gn:name":"La Atravezada",
    "gn:population":0,
    "gn:timezone":"America/Mexico_City",
    "iso:country":"MX",
    "name:spa_x_preferred":[
        "La Atravezada"
    ],
    "wof:name":"La Atravezada",
    "wof:placetype":"locality"
},
  "geometry": {"coordinates":[-104.0266,19.10526],"type":"Point"}
}