{
  "type": "Feature",
  "properties": {
    "gn:admin1_code":"6",
    "gn:admin2_code":"65",
    "gn:asciiname":"Sillochi",
    "gn:country_code":"MX",
    "gn:dem":2222,
    "gn:feature_class":"P",
    "gn:feature_code":"PPL",
    "gn:name":"Sillochi",
    "gn:population":30,
    "gn:timezone":"America/Chihuahua",
    "iso:country":"MX",
    "wof:name":"Sillochi",
    "wof:placetype":"locality",
    "wof:population":30
},
  "geometry": {"coordinates":[-107.71408999999998,27.47409],"type":"Point"}
}