{
  "type": "Feature",
  "properties": {
    "gn:admin1_code":"12",
    "gn:admin2_code":"22",
    "gn:asciiname":"Tierras Coloradas (Tierra Colorada)",
    "gn:country_code":"MX",
    "gn:dem":837,
    "gn:feature_class":"P",
    "gn:feature_code":"PPL",
    "gn:name":"Tierras Coloradas (Tierra Colorada)",
    "gn:population":34,
    "gn:timezone":"America/Mexico_City",
    "iso:country":"MX",
    "wof:name":"Tierras Coloradas (Tierra Colorada)",
    "wof:placetype":"locality",
    "wof:population":34
},
  "geometry": {"coordinates":[-101.03561999999999,18.03442],"type":"Point"}
}