{
  "type": "Feature",
  "properties": {
    "gn:admin1_code":"11",
    "gn:admin2_code":"23.0",
    "gn:asciiname":"Los Capulines de Aguirre",
    "gn:country_code":"MX",
    "gn:dem":1809,
    "gn:feature_class":"P",
    "gn:feature_code":"PPL",
    "gn:name":"Los Capulines de Aguirre",
    "gn:population":63,
    "gn:timezone":"America/Mexico_City",
    "iso:country":"MX",
    "wof:name":"Los Capulines de Aguirre",
    "wof:placetype":"locality",
    "wof:population":63
},
  "geometry": {"coordinates":[-102.01027999999999,20.47417],"type":"Point"}
}