{
  "type": "Feature",
  "properties": {
    "gn:admin1_code":"28",
    "gn:admin2_code":"32.0",
    "gn:asciiname":"Reynosa Diaz",
    "gn:country_code":"MX",
    "gn:dem":42,
    "gn:feature_class":"P",
    "gn:feature_code":"PPL",
    "gn:name":"Reynosa D\u00edaz",
    "gn:population":0,
    "gn:timezone":"America/Matamoros",
    "iso:country":"MX",
    "name:spa_x_preferred":[
        "Reynosa D\u00edaz"
    ],
    "name:und_x_variant":[
        "Reynosa Viejo",
        "Reynosa de D\u00edaz",
        "Reinosa D\u00edaz"
    ],
    "wof:name":"Reynosa Diaz",
    "wof:placetype":"locality"
},
  "geometry": {"coordinates":[-98.45587999999999,26.20433],"type":"Point"}
}