{
  "type": "Feature",
  "properties": {
    "gn:admin1_code":"25",
    "gn:admin2_code":"5.0",
    "gn:asciiname":"La Llama",
    "gn:country_code":"MX",
    "gn:dem":309,
    "gn:feature_class":"P",
    "gn:feature_code":"PPL",
    "gn:name":"La Llama",
    "gn:population":0,
    "gn:timezone":"America/Mazatlan",
    "iso:country":"MX",
    "name:ast_x_preferred":[
        "La Llama"
    ],
    "wof:name":"La Llama",
    "wof:placetype":"locality"
},
  "geometry": {"coordinates":[-106.81667,24.61667000000001],"type":"Point"}
}