{
  "type": "Feature",
  "properties": {
    "gn:admin1_code":"21",
    "gn:admin2_code":"12.0",
    "gn:asciiname":"San Miguel Tecuitlapa",
    "gn:country_code":"MX",
    "gn:dem":2430,
    "gn:feature_class":"P",
    "gn:feature_code":"PPL",
    "gn:name":"San Miguel Tecuitlapa",
    "gn:population":0,
    "gn:timezone":"America/Mexico_City",
    "iso:country":"MX",
    "name:und_x_variant":[
        "Tecuitlapa",
        "San Miguel Tecuitlapa"
    ],
    "wof:name":"San Miguel Tecuitlapa",
    "wof:placetype":"locality"
},
  "geometry": {"coordinates":[-97.54714,19.12118],"type":"Point"}
}