{
  "type": "Feature",
  "properties": {
    "gn:admin1_code":"6",
    "gn:admin2_code":"27",
    "gn:asciiname":"Olirare (Timichi)",
    "gn:country_code":"MX",
    "gn:dem":2117,
    "gn:feature_class":"P",
    "gn:feature_code":"PPL",
    "gn:name":"Olirare (Timichi)",
    "gn:population":9,
    "gn:timezone":"America/Chihuahua",
    "iso:country":"MX",
    "wof:name":"Olirare (Timichi)",
    "wof:placetype":"locality",
    "wof:population":9
},
  "geometry": {"coordinates":[-107.23739999999999,27.16493],"type":"Point"}
}