{
  "type": "Feature",
  "properties": {
    "gn:admin1_code":"21",
    "gn:admin2_code":"74.0",
    "gn:asciiname":"Valle de San Miguel",
    "gn:country_code":"MX",
    "gn:dem":2311,
    "gn:feature_class":"P",
    "gn:feature_code":"PPL",
    "gn:name":"Valle de San Miguel",
    "gn:population":461,
    "gn:timezone":"America/Mexico_City",
    "iso:country":"MX",
    "wof:name":"Valle de San Miguel",
    "wof:placetype":"locality",
    "wof:population":461
},
  "geometry": {"coordinates":[-98.41694,19.14056],"type":"Point"}
}