{
  "type": "Feature",
  "properties": {
    "gn:admin1_code":"16",
    "gn:admin2_code":"38.0",
    "gn:asciiname":"El Tural",
    "gn:country_code":"MX",
    "gn:dem":490,
    "gn:feature_class":"P",
    "gn:feature_code":"PPL",
    "gn:name":"El Tural",
    "gn:population":6,
    "gn:timezone":"America/Mexico_City",
    "iso:country":"MX",
    "wof:name":"El Tural",
    "wof:placetype":"locality",
    "wof:population":6
},
  "geometry": {"coordinates":[-101.13500000000001,18.79778],"type":"Point"}
}