{
  "type": "Feature",
  "properties": {
    "gn:admin1_code":"30.0",
    "gn:admin2_code":"123.0",
    "gn:asciiname":"La Bellota",
    "gn:country_code":"MX",
    "gn:dem":36,
    "gn:feature_class":"P",
    "gn:feature_code":"PPL",
    "gn:name":"La Bellota",
    "gn:population":0,
    "gn:timezone":"America/Mexico_City",
    "iso:country":"MX",
    "name:spa_x_preferred":[
        "La Bellota"
    ],
    "wof:name":"La Bellota",
    "wof:placetype":"locality"
},
  "geometry": {"coordinates":[-98.48175000000001,21.87462],"type":"Point"}
}