{
  "type": "Feature",
  "properties": {
    "gn:admin1_code":"30",
    "gn:admin2_code":"172.0",
    "gn:asciiname":"Buenavista (El Corpal)",
    "gn:country_code":"MX",
    "gn:dem":14,
    "gn:feature_class":"P",
    "gn:feature_code":"PPL",
    "gn:name":"Buenavista (El Corpal)",
    "gn:population":103,
    "gn:timezone":"America/Mexico_City",
    "iso:country":"MX",
    "wof:name":"Buenavista (El Corpal)",
    "wof:placetype":"locality",
    "wof:population":103
},
  "geometry": {"coordinates":[-94.78417,17.78639],"type":"Point"}
}