{
  "type": "Feature",
  "properties": {
    "gn:admin1_code":"4.0",
    "gn:asciiname":"San Carlos Segundo",
    "gn:country_code":"MX",
    "gn:dem":2,
    "gn:feature_class":"P",
    "gn:feature_code":"PPL",
    "gn:name":"San Carlos Segundo",
    "gn:population":0,
    "gn:timezone":"America/Merida",
    "iso:country":"MX",
    "name:spa_x_preferred":[
        "San Carlos Segundo"
    ],
    "wof:name":"San Carlos Segundo",
    "wof:placetype":"locality"
},
  "geometry": {"coordinates":[-91.73286,18.67974],"type":"Point"}
}