{
  "type": "Feature",
  "properties": {
    "gn:admin1_code":"21",
    "gn:admin2_code":"177",
    "gn:asciiname":"San Jose Valsequillo Seccion Tercera",
    "gn:country_code":"MX",
    "gn:dem":1939,
    "gn:feature_class":"P",
    "gn:feature_code":"PPL",
    "gn:name":"San Jos\u00e9 Valsequillo Secci\u00f3n Tercera",
    "gn:population":47,
    "gn:timezone":"America/Mexico_City",
    "iso:country":"MX",
    "name:und_x_variant":[
        "San Jos\u00e9 Valsequillo Secci\u00f3n Tercera"
    ],
    "wof:name":"San Jose Valsequillo Seccion Tercera",
    "wof:placetype":"locality",
    "wof:population":47
},
  "geometry": {"coordinates":[-97.62356,18.67239],"type":"Point"}
}