{
  "type": "Feature",
  "properties": {
    "gn:admin1_code":"18.0",
    "gn:admin2_code":"4.0",
    "gn:asciiname":"El Herradero",
    "gn:country_code":"MX",
    "gn:dem":992,
    "gn:feature_class":"P",
    "gn:feature_code":"PPL",
    "gn:name":"El Herradero",
    "gn:population":0,
    "gn:timezone":"America/Mazatlan",
    "iso:country":"MX",
    "wof:name":"El Herradero",
    "wof:placetype":"locality"
},
  "geometry": {"coordinates":[-104.99621,21.09147],"type":"Point"}
}