{
  "type": "Feature",
  "properties": {
    "gn:admin1_code":"14.0",
    "gn:admin2_code":"79.0",
    "gn:asciiname":"Cienaga de Mata",
    "gn:cc2":"MX",
    "gn:country_code":"MX",
    "gn:dem":1854,
    "gn:feature_class":"P",
    "gn:feature_code":"PPL",
    "gn:name":"Ci\u00e9naga de Mata",
    "gn:population":0,
    "gn:timezone":"America/Mexico_City",
    "iso:country":"MX",
    "name:und_x_variant":[
        "Ci\u00e9nega de Mota",
        "Ci\u00e9nega de Mata",
        "Ci\u00e9naga de Mata"
    ],
    "wof:name":"Cienaga de Mata",
    "wof:placetype":"locality"
},
  "geometry": {"coordinates":[-103.36667,19.81667],"type":"Point"}
}