{
  "type": "Feature",
  "properties": {
    "gn:admin1_code":"21",
    "gn:admin2_code":"53.0",
    "gn:asciiname":"Loma Alta",
    "gn:country_code":"MX",
    "gn:dem":2337,
    "gn:feature_class":"P",
    "gn:feature_code":"PPL",
    "gn:name":"Loma Alta",
    "gn:population":0,
    "gn:timezone":"America/Mexico_City",
    "iso:country":"MX",
    "name:spa_x_preferred":[
        "Loma Alta"
    ],
    "wof:name":"Loma Alta",
    "wof:placetype":"locality"
},
  "geometry": {"coordinates":[-98.02712,19.79716],"type":"Point"}
}