{
  "type": "Feature",
  "properties": {
    "gn:admin1_code":"15.0",
    "gn:admin2_code":"123.0",
    "gn:asciiname":"El Reparo de Nochititla",
    "gn:country_code":"MX",
    "gn:dem":1056,
    "gn:feature_class":"P",
    "gn:feature_code":"PPL",
    "gn:name":"El Reparo de Nochititla",
    "gn:population":0,
    "gn:timezone":"America/Mexico_City",
    "iso:country":"MX",
    "name:spa_x_preferred":[
        "El Reparo de Nochititla"
    ],
    "name:und_x_variant":[
        "El Reparo"
    ],
    "wof:name":"El Reparo de Nochititla",
    "wof:placetype":"locality"
},
  "geometry": {"coordinates":[-100.44490999999999,18.90967],"type":"Point"}
}