{
  "type": "Feature",
  "properties": {
    "gn:admin1_code":"29",
    "gn:admin2_code":"57.0",
    "gn:asciiname":"Pedro Piscil Teniza",
    "gn:country_code":"MX",
    "gn:dem":2204,
    "gn:feature_class":"P",
    "gn:feature_code":"PPL",
    "gn:name":"Pedro Piscil Teniza",
    "gn:population":5,
    "gn:timezone":"America/Mexico_City",
    "iso:country":"MX",
    "wof:name":"Pedro Piscil Teniza",
    "wof:placetype":"locality",
    "wof:population":5
},
  "geometry": {"coordinates":[-98.30884,19.24986],"type":"Point"}
}