{
  "type": "Feature",
  "properties": {
    "gn:admin1_code":"30",
    "gn:admin2_code":"149.0",
    "gn:asciiname":"San Antonio",
    "gn:country_code":"MX",
    "gn:dem":818,
    "gn:feature_class":"P",
    "gn:feature_code":"PPL",
    "gn:name":"San Antonio",
    "gn:population":423,
    "gn:timezone":"America/Mexico_City",
    "iso:country":"MX",
    "wof:name":"San Antonio",
    "wof:placetype":"locality",
    "wof:population":423
},
  "geometry": {"coordinates":[-94.95083,18.30639],"type":"Point"}
}