{
  "type": "Feature",
  "properties": {
    "gn:admin1_code":"15",
    "gn:admin2_code":"99.0",
    "gn:asciiname":"Xalapango",
    "gn:country_code":"MX",
    "gn:dem":2274,
    "gn:feature_class":"P",
    "gn:feature_code":"PPL",
    "gn:name":"Xalapango",
    "gn:population":457,
    "gn:timezone":"America/Mexico_City",
    "iso:country":"MX",
    "wof:name":"Xalapango",
    "wof:placetype":"locality",
    "wof:population":457
},
  "geometry": {"coordinates":[-98.84577,19.53791],"type":"Point"}
}