{
  "type": "Feature",
  "properties": {
    "gn:admin1_code":"19.0",
    "gn:asciiname":"El Almirante",
    "gn:country_code":"MX",
    "gn:dem":496,
    "gn:feature_class":"P",
    "gn:feature_code":"PPL",
    "gn:name":"El Almirante",
    "gn:population":0,
    "gn:timezone":"America/Monterrey",
    "iso:country":"MX",
    "name:spa_x_preferred":[
        "El Almirante"
    ],
    "wof:name":"El Almirante",
    "wof:placetype":"locality"
},
  "geometry": {"coordinates":[-100.32459,25.85569],"type":"Point"}
}