{
  "type": "Feature",
  "properties": {
    "gn:admin1_code":"7",
    "gn:admin2_code":"32.0",
    "gn:asciiname":"Las Islitas",
    "gn:country_code":"MX",
    "gn:dem":378,
    "gn:feature_class":"P",
    "gn:feature_code":"PPL",
    "gn:name":"Las Islitas",
    "gn:population":6,
    "gn:timezone":"America/Monterrey",
    "iso:country":"MX",
    "wof:name":"Las Islitas",
    "wof:placetype":"locality",
    "wof:population":6
},
  "geometry": {"coordinates":[-101.30565,27.9097],"type":"Point"}
}