{
  "type": "Feature",
  "properties": {
    "gn:admin1_code":"17",
    "gn:admin2_code":"16.0",
    "gn:asciiname":"Tlalmimilulpan",
    "gn:country_code":"MX",
    "gn:dem":2403,
    "gn:feature_class":"P",
    "gn:feature_code":"PPL",
    "gn:name":"Tlalmimilulpan",
    "gn:population":0,
    "gn:timezone":"America/Mexico_City",
    "iso:country":"MX",
    "name:spa_x_preferred":[
        "San Pedro"
    ],
    "name:und_x_variant":[
        "Tlalmimilupan",
        "Tlalmimilulpan"
    ],
    "wof:name":"Tlalmimilulpan",
    "wof:placetype":"locality"
},
  "geometry": {"coordinates":[-98.74061,18.91847000000001],"type":"Point"}
}