{
  "type": "Feature",
  "properties": {
    "gn:admin1_code":"6.0",
    "gn:admin2_code":"39.0",
    "gn:asciiname":"Paso del Macho",
    "gn:country_code":"MX",
    "gn:dem":1422,
    "gn:feature_class":"P",
    "gn:feature_code":"PPL",
    "gn:name":"Paso del Macho",
    "gn:population":0,
    "gn:timezone":"America/Chihuahua",
    "iso:country":"MX",
    "name:spa_x_preferred":[
        "Paso del Macho"
    ],
    "wof:name":"Paso del Macho",
    "wof:placetype":"locality"
},
  "geometry": {"coordinates":[-105.03565999999999,26.99758],"type":"Point"}
}