{
  "type": "Feature",
  "properties": {
    "gn:admin1_code":"6.0",
    "gn:admin2_code":"51.0",
    "gn:asciiname":"Chiqueritos",
    "gn:country_code":"MX",
    "gn:dem":1812,
    "gn:feature_class":"P",
    "gn:feature_code":"PPL",
    "gn:name":"Chiqueritos",
    "gn:population":0,
    "gn:timezone":"America/Chihuahua",
    "iso:country":"MX",
    "name:spa_x_preferred":[
        "Chiqueritos"
    ],
    "wof:name":"Chiqueritos",
    "wof:placetype":"locality"
},
  "geometry": {"coordinates":[-108.31502999999999,28.00461],"type":"Point"}
}