{
  "type": "Feature",
  "properties": {
    "gn:admin1_code":"11.0",
    "gn:admin2_code":"29.0",
    "gn:asciiname":"La Jaula",
    "gn:country_code":"MX",
    "gn:dem":2075,
    "gn:feature_class":"P",
    "gn:feature_code":"PPL",
    "gn:name":"La Jaula",
    "gn:population":0,
    "gn:timezone":"America/Mexico_City",
    "iso:country":"MX",
    "name:und_x_variant":[
        "Jaula",
        "La Jaula"
    ],
    "wof:name":"La Jaula",
    "wof:placetype":"locality"
},
  "geometry": {"coordinates":[-100.72318,21.52802],"type":"Point"}
}