{
  "type": "Feature",
  "properties": {
    "gn:admin1_code":"6.0",
    "gn:asciiname":"Kilometro Noventa y Uno",
    "gn:country_code":"MX",
    "gn:dem":1611,
    "gn:feature_class":"P",
    "gn:feature_code":"PPL",
    "gn:name":"Kil\u00f3metro Noventa y Uno",
    "gn:population":0,
    "gn:timezone":"America/Chihuahua",
    "iso:country":"MX",
    "name:spa_x_preferred":[
        "Kil\u00f3metro Noventa y Uno"
    ],
    "wof:name":"Kilometro Noventa y Uno",
    "wof:placetype":"locality"
},
  "geometry": {"coordinates":[-106.41101999999999,29.35409000000001],"type":"Point"}
}