{
  "type": "Feature",
  "properties": {
    "gn:admin1_code":"5",
    "gn:admin2_code":"107",
    "gn:asciiname":"El Alto Buenavista",
    "gn:country_code":"MX",
    "gn:dem":553,
    "gn:feature_class":"P",
    "gn:feature_code":"PPL",
    "gn:name":"El Alto Buenavista",
    "gn:population":36,
    "gn:timezone":"America/Mexico_City",
    "iso:country":"MX",
    "wof:name":"El Alto Buenavista",
    "wof:placetype":"locality",
    "wof:population":36
},
  "geometry": {"coordinates":[-92.93611,16.10278],"type":"Point"}
}