{
  "type": "Feature",
  "properties": {
    "iso:country":"MX",
    "name:spa_x_preferred":[
        "Barrio Ortigas"
    ],
    "qs:gn_local":0,
    "qs:local_max":184,
    "qs:local_sum":221,
    "qs:localhoods":2,
    "qs:name":"Barrio Ortigas",
    "qs:name_adm0":"M\u00e9xico",
    "qs:name_adm1":"Queretaro de Arteaga",
    "qs:name_adm2":"Jalpan de Serra",
    "qs:name_local":"Jalpan de Serra",
    "qs:photo_max":29,
    "qs:photo_sum":37,
    "qs:placetype":"Suburb",
    "qs:quad_count":4,
    "qs:woe_adm0":23424900,
    "qs:woe_adm1":2346285,
    "qs:woe_adm2":12601452,
    "qs:woe_lau":0,
    "qs:woe_local":55905809,
    "qs:woe_ver":"7.10.0",
    "wof:lang":[
        "spa"
    ],
    "wof:name":"Barrio Ortigas",
    "wof:placetype":"neighbourhood"
},
  "geometry": {"coordinates":[-99.47726400000001,21.200746],"type":"Point"}
}