{
  "type": "Feature",
  "properties": {
    "gn:admin1_code":"30",
    "gn:admin2_code":"24.0",
    "gn:asciiname":"Buena Vista",
    "gn:country_code":"MX",
    "gn:dem":671,
    "gn:feature_class":"P",
    "gn:feature_code":"PPL",
    "gn:name":"Buena Vista",
    "gn:population":299,
    "gn:timezone":"America/Mexico_City",
    "iso:country":"MX",
    "wof:name":"Buena Vista",
    "wof:placetype":"locality",
    "wof:population":299
},
  "geometry": {"coordinates":[-96.77249999999999,19.29944],"type":"Point"}
}