{
  "type": "Feature",
  "properties": {
    "gn:admin1_code":"19",
    "gn:admin2_code":"14",
    "gn:asciiname":"Parada Santa Rita",
    "gn:country_code":"MX",
    "gn:dem":1749,
    "gn:feature_class":"P",
    "gn:feature_code":"PPL",
    "gn:name":"Parada Santa Rita",
    "gn:population":18,
    "gn:timezone":"America/Monterrey",
    "iso:country":"MX",
    "wof:name":"Parada Santa Rita",
    "wof:placetype":"locality",
    "wof:population":18
},
  "geometry": {"coordinates":[-100.37663000000001,24.18924],"type":"Point"}
}