{
  "type": "Feature",
  "properties": {
    "gn:admin1_code":"6.0",
    "gn:admin2_code":"51.0",
    "gn:asciiname":"Palmarito de Sepayvo",
    "gn:country_code":"MX",
    "gn:dem":904,
    "gn:feature_class":"P",
    "gn:feature_code":"PPL",
    "gn:name":"Palmarito de Sepayvo",
    "gn:population":0,
    "gn:timezone":"America/Chihuahua",
    "iso:country":"MX",
    "name:spa_x_preferred":[
        "Palmarito de Sepayvo"
    ],
    "wof:name":"Palmarito de Sepayvo",
    "wof:placetype":"locality"
},
  "geometry": {"coordinates":[-108.46563,28.02803],"type":"Point"}
}