{
  "type": "Feature",
  "properties": {
    "gn:admin1_code":"6",
    "gn:admin2_code":"15.0",
    "gn:asciiname":"El Paradero",
    "gn:country_code":"MX",
    "gn:dem":1438,
    "gn:feature_class":"P",
    "gn:feature_code":"PPL",
    "gn:name":"El Paradero",
    "gn:population":0,
    "gn:timezone":"America/Chihuahua",
    "iso:country":"MX",
    "wof:name":"El Paradero",
    "wof:placetype":"locality"
},
  "geometry": {"coordinates":[-105.53333000000001,29.71667],"type":"Point"}
}