{
  "type": "Feature",
  "properties": {
    "gn:admin1_code":"7.0",
    "gn:admin2_code":"26.0",
    "gn:asciiname":"El Almu",
    "gn:country_code":"MX",
    "gn:dem":354,
    "gn:feature_class":"P",
    "gn:feature_code":"PPL",
    "gn:name":"El Almu",
    "gn:population":0,
    "gn:timezone":"America/Monterrey",
    "iso:country":"MX",
    "name:spa_x_preferred":[
        "El Almu"
    ],
    "wof:name":"El Almu",
    "wof:placetype":"locality"
},
  "geometry": {"coordinates":[-100.85126,27.24861],"type":"Point"}
}