{
  "type": "Feature",
  "properties": {
    "gn:admin1_code":"25.0",
    "gn:admin2_code":"10.0",
    "gn:asciiname":"El Callejon de la Cruz",
    "gn:country_code":"MX",
    "gn:dem":24,
    "gn:feature_class":"P",
    "gn:feature_code":"PPL",
    "gn:name":"El Callej\u00f3n de la Cruz",
    "gn:population":21,
    "gn:timezone":"America/Mazatlan",
    "iso:country":"MX",
    "wof:name":"El Callejon de la Cruz",
    "wof:placetype":"locality",
    "wof:population":21
},
  "geometry": {"coordinates":[-108.88727,25.97212],"type":"Point"}
}