{
  "type": "Feature",
  "properties": {
    "gn:admin1_code":"11",
    "gn:admin2_code":"19.0",
    "gn:asciiname":"Santa Teresa del Fresno",
    "gn:country_code":"MX",
    "gn:dem":2340,
    "gn:feature_class":"P",
    "gn:feature_code":"PPL",
    "gn:name":"Santa Teresa del Fresno",
    "gn:population":182,
    "gn:timezone":"America/Mexico_City",
    "iso:country":"MX",
    "wof:name":"Santa Teresa del Fresno",
    "wof:placetype":"locality",
    "wof:population":182
},
  "geometry": {"coordinates":[-100.44667,20.30667],"type":"Point"}
}