{
  "type": "Feature",
  "properties": {
    "gn:admin1_code":"10",
    "gn:admin2_code":"13.0",
    "gn:asciiname":"Cuatro Milpas",
    "gn:country_code":"MX",
    "gn:dem":1363,
    "gn:feature_class":"P",
    "gn:feature_code":"PPL",
    "gn:name":"Cuatro Milpas",
    "gn:population":0,
    "gn:timezone":"America/Chihuahua",
    "iso:country":"MX",
    "name:spa_x_preferred":[
        "Cuatro Milpas"
    ],
    "name:spa_x_variant":[
        "La Pur\u00edsma"
    ],
    "wof:name":"Cuatro Milpas",
    "wof:placetype":"locality"
},
  "geometry": {"coordinates":[-104.47425,26.48812],"type":"Point"}
}