{
  "type": "Feature",
  "properties": {
    "gn:admin1_code":"14.0",
    "gn:admin2_code":"116.0",
    "gn:asciiname":"Cueva de Santa Ana",
    "gn:country_code":"MX",
    "gn:dem":1933,
    "gn:feature_class":"P",
    "gn:feature_code":"PPL",
    "gn:name":"Cueva de Santa Ana",
    "gn:population":0,
    "gn:timezone":"America/Mexico_City",
    "iso:country":"MX",
    "name:spa_x_preferred":[
        "Cueva de Santa Ana"
    ],
    "name:spa_x_variant":[
        "Cueva de Santana"
    ],
    "wof:name":"Cueva de Santa Ana",
    "wof:placetype":"locality"
},
  "geometry": {"coordinates":[-102.61691,21.67398],"type":"Point"}
}