{
  "type": "Feature",
  "properties": {
    "gn:admin1_code":"7",
    "gn:admin2_code":"2.0",
    "gn:asciiname":"Patricia Guerrero (El Castillo)",
    "gn:country_code":"MX",
    "gn:dem":293,
    "gn:feature_class":"P",
    "gn:feature_code":"PPL",
    "gn:name":"Patricia Guerrero (El Castillo)",
    "gn:population":5,
    "gn:timezone":"America/Matamoros",
    "iso:country":"MX",
    "wof:name":"Patricia Guerrero (El Castillo)",
    "wof:placetype":"locality",
    "wof:population":5
},
  "geometry": {"coordinates":[-100.89064999999999,29.24467000000001],"type":"Point"}
}