{
  "type": "Feature",
  "properties": {
    "gn:admin1_code":"7.0",
    "gn:asciiname":"El Zorrillo",
    "gn:country_code":"MX",
    "gn:dem":678,
    "gn:feature_class":"P",
    "gn:feature_code":"PPL",
    "gn:name":"El Zorrillo",
    "gn:population":0,
    "gn:timezone":"America/Monterrey",
    "iso:country":"MX",
    "name:spa_x_preferred":[
        "El Zorrillo"
    ],
    "name:spa_x_variant":[
        "Zorrillo",
        "Rancho Nuevo"
    ],
    "wof:name":"El Zorrillo",
    "wof:placetype":"locality"
},
  "geometry": {"coordinates":[-101.04170000000001,26.77886],"type":"Point"}
}