{
  "type": "Feature",
  "properties": {
    "iso:country":"MX",
    "name:spa_x_preferred":[
        "Pedreras de la Enramada"
    ],
    "qs:gn_adm0_cc":"MX",
    "qs:gn_local":4018390,
    "qs:gn_nam_loc":"Apodaca, Apodaca, Nuevo Leon, MX",
    "qs:gn_namadm1":"19",
    "qs:local_max":88,
    "qs:local_sum":157,
    "qs:localhoods":5,
    "qs:name":"Pedreras de la Enramada",
    "qs:name_adm0":"M\u00e9xico",
    "qs:name_adm1":"Nuevo Leon",
    "qs:name_adm2":"Apodaca",
    "qs:name_local":"Apodaca",
    "qs:photo_max":2,
    "qs:photo_sum":2,
    "qs:placetype":"Suburb",
    "qs:quad_count":1,
    "qs:woe_adm0":23424900,
    "qs:woe_adm1":2346282,
    "qs:woe_adm2":12600610,
    "qs:woe_lau":0,
    "qs:woe_local":112266,
    "qs:woe_ver":"7.10.0",
    "wof:lang":[
        "spa"
    ],
    "wof:name":"Pedreras de la Enramada",
    "wof:placetype":"neighbourhood"
},
  "geometry": {"coordinates":[-100.25299099999999,25.76774],"type":"Point"}
}