{
  "type": "Feature",
  "properties": {
    "gn:admin1_code":"28",
    "gn:admin2_code":"40.0",
    "gn:asciiname":"Salvador de Leon",
    "gn:country_code":"MX",
    "gn:dem":18,
    "gn:feature_class":"P",
    "gn:feature_code":"PPL",
    "gn:name":"Salvador de Le\u00f3n",
    "gn:population":5,
    "gn:timezone":"America/Monterrey",
    "iso:country":"MX",
    "name:und_x_variant":[
        "Salvador de Le\u00f3n"
    ],
    "wof:name":"Salvador de Leon",
    "wof:placetype":"locality",
    "wof:population":5
},
  "geometry": {"coordinates":[-97.77110999999999,25.83056],"type":"Point"}
}