{
  "type": "Feature",
  "properties": {
    "gn:admin1_code":"19.0",
    "gn:admin2_code":"24.0",
    "gn:asciiname":"El Barro de Abajo",
    "gn:country_code":"MX",
    "gn:dem":1974,
    "gn:feature_class":"P",
    "gn:feature_code":"PPL",
    "gn:name":"El Barro de Abajo",
    "gn:population":0,
    "gn:timezone":"America/Monterrey",
    "iso:country":"MX",
    "name:spa_x_preferred":[
        "El Barro de Abajo"
    ],
    "name:spa_x_variant":[
        "Santa Martha de Abajo"
    ],
    "wof:name":"El Barro de Abajo",
    "wof:placetype":"locality"
},
  "geometry": {"coordinates":[-99.63074,23.85561],"type":"Point"}
}