{
  "type": "Feature",
  "properties": {
    "gn:admin1_code":"3",
    "gn:admin2_code":"2.0",
    "gn:asciiname":"Las Matancitas",
    "gn:country_code":"MX",
    "gn:dem":564,
    "gn:feature_class":"P",
    "gn:feature_code":"PPL",
    "gn:name":"Las Matancitas",
    "gn:population":6,
    "gn:timezone":"America/Mazatlan",
    "iso:country":"MX",
    "wof:name":"Las Matancitas",
    "wof:placetype":"locality",
    "wof:population":6
},
  "geometry": {"coordinates":[-112.60718,26.97105],"type":"Point"}
}