{
  "type": "Feature",
  "properties": {
    "gn:admin1_code":"6",
    "gn:admin2_code":"5.0",
    "gn:asciiname":"Rancho el Tagle",
    "gn:country_code":"MX",
    "gn:dem":1217,
    "gn:feature_class":"P",
    "gn:feature_code":"PPL",
    "gn:name":"Rancho el Tagle",
    "gn:population":5,
    "gn:timezone":"America/Chihuahua",
    "iso:country":"MX",
    "wof:name":"Rancho el Tagle",
    "wof:placetype":"locality",
    "wof:population":5
},
  "geometry": {"coordinates":[-107.58141000000001,31.47733],"type":"Point"}
}