{
  "type": "Feature",
  "properties": {
    "gn:admin1_code":"10.0",
    "gn:admin2_code":"34.0",
    "gn:asciiname":"Atascaderitos",
    "gn:country_code":"MX",
    "gn:dem":2443,
    "gn:feature_class":"P",
    "gn:feature_code":"PPL",
    "gn:name":"Atascaderitos",
    "gn:population":0,
    "gn:timezone":"America/Monterrey",
    "iso:country":"MX",
    "name:spa_x_preferred":[
        "Atascaderitos"
    ],
    "wof:name":"Atascaderitos",
    "wof:placetype":"locality"
},
  "geometry": {"coordinates":[-106.94414,25.44204],"type":"Point"}
}