{
  "type": "Feature",
  "properties": {
    "gn:admin1_code":"20.0",
    "gn:asciiname":"Piedra Parada",
    "gn:country_code":"MX",
    "gn:dem":23,
    "gn:feature_class":"P",
    "gn:feature_code":"PPL",
    "gn:name":"Piedra Parada",
    "gn:population":0,
    "gn:timezone":"America/Mexico_City",
    "iso:country":"MX",
    "name:spa_x_preferred":[
        "Piedra Parada"
    ],
    "wof:name":"Piedra Parada",
    "wof:placetype":"locality"
},
  "geometry": {"coordinates":[-98.30186999999999,16.31188],"type":"Point"}
}