{
  "type": "Feature",
  "properties": {
    "gn:admin1_code":"16",
    "gn:admin2_code":"97.0",
    "gn:asciiname":"Arumbarapio",
    "gn:country_code":"MX",
    "gn:dem":715,
    "gn:feature_class":"P",
    "gn:feature_code":"PPL",
    "gn:name":"Arumbarapio",
    "gn:population":0,
    "gn:timezone":"America/Mexico_City",
    "iso:country":"MX",
    "name:spa_x_preferred":[
        "Arumbarapio"
    ],
    "wof:name":"Arumbarapio",
    "wof:placetype":"locality"
},
  "geometry": {"coordinates":[-101.32489,19.00781],"type":"Point"}
}