{
  "type": "Feature",
  "properties": {
    "gn:admin1_code":"5",
    "gn:admin2_code":"57.0",
    "gn:asciiname":"Tierra Santa",
    "gn:country_code":"MX",
    "gn:dem":652,
    "gn:feature_class":"P",
    "gn:feature_code":"PPL",
    "gn:name":"Tierra Santa",
    "gn:population":5,
    "gn:timezone":"America/Mexico_City",
    "iso:country":"MX",
    "name:ceb_x_preferred":[
        "Tierra Santa"
    ],
    "name:spa_x_preferred":[
        "Tierra Santa"
    ],
    "name:swe_x_preferred":[
        "Tierra Santa"
    ],
    "wof:name":"Tierra Santa",
    "wof:placetype":"locality",
    "wof:population":5
},
  "geometry": {"coordinates":[-92.39333000000001,15.26111],"type":"Point"}
}