{
  "type": "Feature",
  "properties": {
    "gn:admin1_code":"14",
    "gn:admin2_code":"84.0",
    "gn:asciiname":"Maromero",
    "gn:country_code":"MX",
    "gn:dem":1433,
    "gn:feature_class":"P",
    "gn:feature_code":"PPL",
    "gn:name":"Maromero",
    "gn:population":0,
    "gn:timezone":"America/Mexico_City",
    "iso:country":"MX",
    "wof:name":"Maromero",
    "wof:placetype":"locality"
},
  "geometry": {"coordinates":[-105.06667,20.43333],"type":"Point"}
}