{
  "type": "Feature",
  "properties": {
    "gn:admin1_code":"30",
    "gn:admin2_code":"196.0",
    "gn:asciiname":"San Francisco de las Mesillas",
    "gn:country_code":"MX",
    "gn:dem":482,
    "gn:feature_class":"P",
    "gn:feature_code":"PPL",
    "gn:name":"San Francisco de las Mesillas",
    "gn:population":590,
    "gn:timezone":"America/Mexico_City",
    "iso:country":"MX",
    "wof:name":"San Francisco de las Mesillas",
    "wof:placetype":"locality",
    "wof:population":590
},
  "geometry": {"coordinates":[-96.77639000000001,18.83],"type":"Point"}
}