{
  "type": "Feature",
  "properties": {
    "gn:admin1_code":"9",
    "gn:admin2_code":"9.0",
    "gn:asciiname":"Tlatepexco",
    "gn:country_code":"MX",
    "gn:dem":2625,
    "gn:feature_class":"P",
    "gn:feature_code":"PPL",
    "gn:name":"Tlatepexco",
    "gn:population":117,
    "gn:timezone":"America/Mexico_City",
    "iso:country":"MX",
    "wof:name":"Tlatepexco",
    "wof:placetype":"locality",
    "wof:population":117
},
  "geometry": {"coordinates":[-99.07763,19.19547],"type":"Point"}
}