{
  "type": "Feature",
  "properties": {
    "gn:admin1_code":"11.0",
    "gn:asciiname":"Pozo de la Luz Numero Uno",
    "gn:country_code":"MX",
    "gn:dem":2033,
    "gn:feature_class":"P",
    "gn:feature_code":"PPL",
    "gn:name":"Pozo de la Luz N\u00famero Uno",
    "gn:population":0,
    "gn:timezone":"America/Mexico_City",
    "iso:country":"MX",
    "name:spa_x_preferred":[
        "Pozo de la Luz N\u00famero Uno"
    ],
    "wof:name":"Pozo de la Luz Numero Uno",
    "wof:placetype":"locality"
},
  "geometry": {"coordinates":[-100.70688,20.89913],"type":"Point"}
}