{
  "type": "Feature",
  "properties": {
    "gn:admin1_code":"6.0",
    "gn:admin2_code":"1.0",
    "gn:asciiname":"Las Carboneras",
    "gn:country_code":"MX",
    "gn:dem":1190,
    "gn:feature_class":"P",
    "gn:feature_code":"PPL",
    "gn:name":"Las Carboneras",
    "gn:population":0,
    "gn:timezone":"America/Chihuahua",
    "iso:country":"MX",
    "name:und_x_variant":[
        "Rancho La Carbonera",
        "Las Carboneras"
    ],
    "wof:name":"Las Carboneras",
    "wof:placetype":"locality"
},
  "geometry": {"coordinates":[-106.63573999999998,30.71027],"type":"Point"}
}