{
  "type": "Feature",
  "properties": {
    "gn:admin1_code":"3",
    "gn:admin2_code":"8.0",
    "gn:asciiname":"Los Algodones",
    "gn:country_code":"MX",
    "gn:dem":204,
    "gn:feature_class":"P",
    "gn:feature_code":"PPL",
    "gn:name":"Los Algodones",
    "gn:population":7,
    "gn:timezone":"America/Mazatlan",
    "iso:country":"MX",
    "wof:name":"Los Algodones",
    "wof:placetype":"locality",
    "wof:population":7
},
  "geometry": {"coordinates":[-109.64064,23.21999],"type":"Point"}
}