{
  "type": "Feature",
  "properties": {
    "gn:admin1_code":"15",
    "gn:admin2_code":"5.0",
    "gn:asciiname":"Santiaguito",
    "gn:country_code":"MX",
    "gn:dem":2606,
    "gn:feature_class":"P",
    "gn:feature_code":"PPL",
    "gn:name":"Santiaguito",
    "gn:population":989,
    "gn:timezone":"America/Mexico_City",
    "iso:country":"MX",
    "wof:name":"Santiaguito",
    "wof:placetype":"locality",
    "wof:population":989
},
  "geometry": {"coordinates":[-99.83083000000001,19.40417],"type":"Point"}
}