{
  "type": "Feature",
  "properties": {
    "gn:admin1_code":"20",
    "gn:admin2_code":"287.0",
    "gn:asciiname":"El Coatillo",
    "gn:country_code":"MX",
    "gn:dem":2135,
    "gn:feature_class":"P",
    "gn:feature_code":"PPL",
    "gn:name":"El Coatillo",
    "gn:population":0,
    "gn:timezone":"America/Mexico_City",
    "iso:country":"MX",
    "name:spa_x_preferred":[
        "Coatillo"
    ],
    "name:spa_x_variant":[
        "El Castillo",
        "El Coatillo"
    ],
    "wof:name":"El Coatillo",
    "wof:placetype":"locality"
},
  "geometry": {"coordinates":[-97.40987,17.74984],"type":"Point"}
}