{
  "type": "Feature",
  "properties": {
    "gn:admin1_code":"19",
    "gn:admin2_code":"38.0",
    "gn:asciiname":"Los Vaqueros",
    "gn:country_code":"MX",
    "gn:dem":430,
    "gn:feature_class":"P",
    "gn:feature_code":"PPL",
    "gn:name":"Los Vaqueros",
    "gn:population":0,
    "gn:timezone":"America/Monterrey",
    "iso:country":"MX",
    "name:hun_x_preferred":[
        "Los vaqueros"
    ],
    "name:spa_x_preferred":[
        "Los Vaqueros"
    ],
    "name:spa_x_variant":[
        "Los vaqueros"
    ],
    "wof:name":"Los Vaqueros",
    "wof:placetype":"locality"
},
  "geometry": {"coordinates":[-99.90421000000001,25.20168],"type":"Point"}
}