{
  "type": "Feature",
  "properties": {
    "gn:admin1_code":"6",
    "gn:admin2_code":"27.0",
    "gn:asciiname":"Romichi",
    "gn:country_code":"MX",
    "gn:dem":2209,
    "gn:feature_class":"P",
    "gn:feature_code":"PPL",
    "gn:name":"Romichi",
    "gn:population":14,
    "gn:timezone":"America/Chihuahua",
    "iso:country":"MX",
    "name:spa_x_preferred":[
        "Romichi"
    ],
    "wof:name":"Romichi",
    "wof:placetype":"locality",
    "wof:population":14
},
  "geometry": {"coordinates":[-107.4091,26.82324],"type":"Point"}
}