{
  "type": "Feature",
  "properties": {
    "gn:admin1_code":"21",
    "gn:admin2_code":"27",
    "gn:asciiname":"Ixtlahualuca",
    "gn:country_code":"MX",
    "gn:dem":2123,
    "gn:feature_class":"P",
    "gn:feature_code":"PPL",
    "gn:name":"Ixtlahualuca",
    "gn:population":18,
    "gn:timezone":"America/Mexico_City",
    "iso:country":"MX",
    "wof:name":"Ixtlahualuca",
    "wof:placetype":"locality",
    "wof:population":18
},
  "geometry": {"coordinates":[-97.51967,18.13131],"type":"Point"}
}