{
  "type": "Feature",
  "properties": {
    "gn:admin1_code":"6.0",
    "gn:admin2_code":"41.0",
    "gn:asciiname":"Urisicuchi",
    "gn:country_code":"MX",
    "gn:dem":2127,
    "gn:feature_class":"P",
    "gn:feature_code":"PPL",
    "gn:name":"Urisicuchi",
    "gn:population":0,
    "gn:timezone":"America/Chihuahua",
    "iso:country":"MX",
    "name:spa_x_preferred":[
        "Urisicuchi"
    ],
    "wof:name":"Urisicuchi",
    "wof:placetype":"locality"
},
  "geometry": {"coordinates":[-108.05001,27.71096],"type":"Point"}
}