{
  "type": "Feature",
  "properties": {
    "gn:admin1_code":"24",
    "gn:admin2_code":"32.0",
    "gn:asciiname":"Paso de las Higueras",
    "gn:country_code":"MX",
    "gn:dem":1606,
    "gn:feature_class":"P",
    "gn:feature_code":"PPL",
    "gn:name":"Paso de las Higueras",
    "gn:population":0,
    "gn:timezone":"America/Mexico_City",
    "iso:country":"MX",
    "name:spa_x_preferred":[
        "Paso de las Higueras"
    ],
    "name:und_x_variant":[
        "Paso de Higueras",
        "Paso Higueras"
    ],
    "wof:name":"Paso de las Higueras",
    "wof:placetype":"locality"
},
  "geometry": {"coordinates":[-100.5428,21.76689],"type":"Point"}
}