{
  "type": "Feature",
  "properties": {
    "gn:admin1_code":"21",
    "gn:admin2_code":"71",
    "gn:asciiname":"La Palpa",
    "gn:country_code":"MX",
    "gn:dem":1512,
    "gn:feature_class":"P",
    "gn:feature_code":"PPL",
    "gn:name":"La Palpa",
    "gn:population":37,
    "gn:timezone":"America/Mexico_City",
    "iso:country":"MX",
    "wof:name":"La Palpa",
    "wof:placetype":"locality",
    "wof:population":37
},
  "geometry": {"coordinates":[-98.05361000000001,20.18222],"type":"Point"}
}