{
  "type": "Feature",
  "properties": {
    "gn:admin1_code":"5",
    "gn:admin2_code":"65.0",
    "gn:asciiname":"Muzquiz",
    "gn:country_code":"MX",
    "gn:dem":8,
    "gn:feature_class":"P",
    "gn:feature_code":"PPL",
    "gn:name":"Muzquiz",
    "gn:population":4,
    "gn:timezone":"America/Mexico_City",
    "iso:country":"MX",
    "wof:name":"Muzquiz",
    "wof:placetype":"locality",
    "wof:population":4
},
  "geometry": {"coordinates":[-91.82917,17.77306],"type":"Point"}
}