{
  "type": "Feature",
  "properties": {
    "gn:admin1_code":"5",
    "gn:admin2_code":"108.0",
    "gn:asciiname":"Nueva York",
    "gn:cc2":"MX",
    "gn:country_code":"MX",
    "gn:dem":569,
    "gn:feature_class":"P",
    "gn:feature_code":"PPL",
    "gn:name":"Nueva York",
    "gn:population":0,
    "gn:timezone":"America/Mexico_City",
    "iso:country":"MX",
    "name:und_x_variant":[
        "New York",
        "Nueva York"
    ],
    "wof:name":"Nueva York",
    "wof:placetype":"locality"
},
  "geometry": {"coordinates":[-93.23333,16.26667],"type":"Point"}
}