{
  "type": "Feature",
  "properties": {
    "gn:admin1_code":"30",
    "gn:admin2_code":"84.0",
    "gn:asciiname":"La Miel",
    "gn:country_code":"MX",
    "gn:dem":5,
    "gn:feature_class":"P",
    "gn:feature_code":"PPL",
    "gn:name":"La Miel",
    "gn:population":0,
    "gn:timezone":"America/Mexico_City",
    "iso:country":"MX",
    "name:ita_x_preferred":[
        "La Miel"
    ],
    "name:spa_x_preferred":[
        "La Miel"
    ],
    "name:zho_x_preferred":[
        "\u62c9\u7c73\u57c3\u723e"
    ],
    "wof:name":"La Miel",
    "wof:placetype":"locality"
},
  "geometry": {"coordinates":[-95.97382,18.45262],"type":"Point"}
}