{
  "type": "Feature",
  "properties": {
    "gn:admin1_code":"3",
    "gn:admin2_code":"2",
    "gn:asciiname":"El Rebaje Uno",
    "gn:country_code":"MX",
    "gn:dem":17,
    "gn:feature_class":"P",
    "gn:feature_code":"PPL",
    "gn:name":"El Rebaje Uno",
    "gn:population":49,
    "gn:timezone":"America/Mazatlan",
    "iso:country":"MX",
    "wof:name":"El Rebaje Uno",
    "wof:placetype":"locality",
    "wof:population":49
},
  "geometry": {"coordinates":[-111.9907,26.87803],"type":"Point"}
}