{
  "type": "Feature",
  "properties": {
    "gn:admin1_code":"7.0",
    "gn:admin2_code":"9.0",
    "gn:asciiname":"Ejido Coradonga",
    "gn:country_code":"MX",
    "gn:dem":1102,
    "gn:feature_class":"P",
    "gn:feature_code":"PPL",
    "gn:name":"Ejido Coradonga",
    "gn:population":0,
    "gn:timezone":"America/Monterrey",
    "iso:country":"MX",
    "wof:name":"Ejido Coradonga",
    "wof:placetype":"locality"
},
  "geometry": {"coordinates":[-103.23333,25.91667],"type":"Point"}
}