{
  "type": "Feature",
  "properties": {
    "gn:admin1_code":"14.0",
    "gn:admin2_code":"11.0",
    "gn:asciiname":"Camotitos",
    "gn:country_code":"MX",
    "gn:dem":2002,
    "gn:feature_class":"P",
    "gn:feature_code":"PPL",
    "gn:name":"Camotitos",
    "gn:population":0,
    "gn:timezone":"America/Mexico_City",
    "iso:country":"MX",
    "name:spa_x_preferred":[
        "Camotitos"
    ],
    "wof:name":"Camotitos",
    "wof:placetype":"locality"
},
  "geometry": {"coordinates":[-104.38688,20.2714],"type":"Point"}
}