{
  "type": "Feature",
  "properties": {
    "gn:admin1_code":"20.0",
    "gn:asciiname":"Colombia",
    "gn:country_code":"MX",
    "gn:dem":1327,
    "gn:feature_class":"P",
    "gn:feature_code":"PPL",
    "gn:name":"Colombia",
    "gn:population":0,
    "gn:timezone":"America/Mexico_City",
    "iso:country":"MX",
    "name:spa_x_preferred":[
        "Colombia"
    ],
    "wof:name":"Colombia",
    "wof:placetype":"locality"
},
  "geometry": {"coordinates":[-96.28946000000001,16.02141],"type":"Point"}
}