{
  "type": "Feature",
  "properties": {
    "gn:admin1_code":"14",
    "gn:admin2_code":"120.0",
    "gn:asciiname":"El Lazo (Ex-Hacienda del Lazo)",
    "gn:country_code":"MX",
    "gn:dem":1011,
    "gn:feature_class":"P",
    "gn:feature_code":"PPL",
    "gn:name":"El Lazo (Ex-Hacienda del Lazo)",
    "gn:population":228,
    "gn:timezone":"America/Mexico_City",
    "iso:country":"MX",
    "wof:name":"El Lazo (Ex-Hacienda del Lazo)",
    "wof:placetype":"locality",
    "wof:population":228
},
  "geometry": {"coordinates":[-103.32805999999999,20.79639],"type":"Point"}
}