{
  "type": "Feature",
  "properties": {
    "gn:admin1_code":"6",
    "gn:admin2_code":"3",
    "gn:asciiname":"El Verano",
    "gn:country_code":"MX",
    "gn:dem":1533,
    "gn:feature_class":"P",
    "gn:feature_code":"PPL",
    "gn:name":"El Verano",
    "gn:population":11,
    "gn:timezone":"America/Chihuahua",
    "iso:country":"MX",
    "wof:name":"El Verano",
    "wof:placetype":"locality",
    "wof:population":11
},
  "geometry": {"coordinates":[-105.38598,27.07884],"type":"Point"}
}