{
  "type": "Feature",
  "properties": {
    "gn:admin1_code":"26",
    "gn:admin2_code":"29.0",
    "gn:asciiname":"Baugo (Guasimas)",
    "gn:country_code":"MX",
    "gn:dem":11,
    "gn:feature_class":"P",
    "gn:feature_code":"PPL",
    "gn:name":"Baugo (Gu\u00e1simas)",
    "gn:population":285,
    "gn:timezone":"America/Hermosillo",
    "iso:country":"MX",
    "name:und_x_variant":[
        "Baugo (Gu\u00e1simas)"
    ],
    "wof:name":"Baugo (Guasimas)",
    "wof:placetype":"locality",
    "wof:population":285
},
  "geometry": {"coordinates":[-110.57333,27.91444000000001],"type":"Point"}
}