{
  "type": "Feature",
  "properties": {
    "gn:admin1_code":"30",
    "gn:admin2_code":"11.0",
    "gn:asciiname":"El Coyol",
    "gn:country_code":"MX",
    "gn:dem":8,
    "gn:feature_class":"P",
    "gn:feature_code":"PPL",
    "gn:name":"El Coyol",
    "gn:population":0,
    "gn:timezone":"America/Mexico_City",
    "iso:country":"MX",
    "name:spa_x_preferred":[
        "El Coyol"
    ],
    "wof:name":"El Coyol",
    "wof:placetype":"locality"
},
  "geometry": {"coordinates":[-95.88039000000001,18.79854],"type":"Point"}
}