{
  "type": "Feature",
  "properties": {
    "gn:admin1_code":"30.0",
    "gn:admin2_code":"157.0",
    "gn:asciiname":"Cerro Grande",
    "gn:country_code":"MX",
    "gn:dem":110,
    "gn:feature_class":"P",
    "gn:feature_code":"PPL",
    "gn:name":"Cerro Grande",
    "gn:population":0,
    "gn:timezone":"America/Mexico_City",
    "iso:country":"MX",
    "name:spa_x_preferred":[
        "Cerro Grande"
    ],
    "wof:name":"Cerro Grande",
    "wof:placetype":"locality"
},
  "geometry": {"coordinates":[-97.60398000000001,20.73781],"type":"Point"}
}