{
  "type": "Feature",
  "properties": {
    "gn:admin1_code":"6",
    "gn:admin2_code":"27.0",
    "gn:asciiname":"La Joya de los Ramos",
    "gn:country_code":"MX",
    "gn:dem":2464,
    "gn:feature_class":"P",
    "gn:feature_code":"PPL",
    "gn:name":"La Joya de los Ramos",
    "gn:population":0,
    "gn:timezone":"America/Chihuahua",
    "iso:country":"MX",
    "name:spa_x_preferred":[
        "La Joya de los Ramos"
    ],
    "name:spa_x_variant":[
        "Las Marijuntas"
    ],
    "wof:name":"La Joya de los Ramos",
    "wof:placetype":"locality"
},
  "geometry": {"coordinates":[-107.20362,26.83537],"type":"Point"}
}