{
  "type": "Feature",
  "properties": {
    "gn:admin1_code":"6.0",
    "gn:admin2_code":"29.0",
    "gn:asciiname":"El Arbolito",
    "gn:country_code":"MX",
    "gn:dem":2197,
    "gn:feature_class":"P",
    "gn:feature_code":"PPL",
    "gn:name":"El Arbolito",
    "gn:population":0,
    "gn:timezone":"America/Chihuahua",
    "iso:country":"MX",
    "name:und_x_variant":[
        "Arbolito",
        "El Arbolito"
    ],
    "wof:name":"El Arbolito",
    "wof:placetype":"locality"
},
  "geometry": {"coordinates":[-106.79746000000002,25.81631],"type":"Point"}
}