{
  "type": "Feature",
  "properties": {
    "gn:admin1_code":"1",
    "gn:admin2_code":"1",
    "gn:asciiname":"El Cardon",
    "gn:country_code":"MX",
    "gn:dem":1987,
    "gn:feature_class":"P",
    "gn:feature_code":"PPL",
    "gn:name":"El Card\u00f3n",
    "gn:population":37,
    "gn:timezone":"America/Mexico_City",
    "iso:country":"MX",
    "name:und_x_variant":[
        "El Card\u00f3n"
    ],
    "wof:name":"El Cardon",
    "wof:placetype":"locality",
    "wof:population":37
},
  "geometry": {"coordinates":[-102.20389,21.77722],"type":"Point"}
}