{
  "type": "Feature",
  "properties": {
    "gn:admin1_code":"32",
    "gn:admin2_code":"26.0",
    "gn:asciiname":"Ignacio Allende (San Angel)",
    "gn:country_code":"MX",
    "gn:dem":1928,
    "gn:feature_class":"P",
    "gn:feature_code":"PPL",
    "gn:name":"Ignacio Allende (San \u00c1ngel)",
    "gn:population":85,
    "gn:timezone":"America/Mexico_City",
    "iso:country":"MX",
    "name:und_x_variant":[
        "Ignacio Allende (San \u00c1ngel)"
    ],
    "wof:name":"Ignacio Allende (San Angel)",
    "wof:placetype":"locality",
    "wof:population":85
},
  "geometry": {"coordinates":[-101.95444000000001,24.285],"type":"Point"}
}