{
  "type": "Feature",
  "properties": {
    "gn:admin1_code":"22",
    "gn:admin2_code":"2.0",
    "gn:asciiname":"Puerto de los Chinos",
    "gn:country_code":"MX",
    "gn:dem":2929,
    "gn:feature_class":"P",
    "gn:feature_code":"PPL",
    "gn:name":"Puerto de los Chinos",
    "gn:population":5,
    "gn:timezone":"America/Mexico_City",
    "iso:country":"MX",
    "wof:name":"Puerto de los Chinos",
    "wof:placetype":"locality",
    "wof:population":5
},
  "geometry": {"coordinates":[-99.69528,21.14306],"type":"Point"}
}