{
  "type": "Feature",
  "properties": {
    "gn:admin1_code":"5",
    "gn:admin2_code":"108",
    "gn:asciiname":"Union Villaflores",
    "gn:country_code":"MX",
    "gn:dem":583,
    "gn:feature_class":"P",
    "gn:feature_code":"PPL",
    "gn:name":"Uni\u00f3n Villaflores",
    "gn:population":18,
    "gn:timezone":"America/Mexico_City",
    "iso:country":"MX",
    "name:und_x_variant":[
        "Uni\u00f3n Villaflores"
    ],
    "wof:name":"Union Villaflores",
    "wof:placetype":"locality",
    "wof:population":18
},
  "geometry": {"coordinates":[-93.25278,16.28667],"type":"Point"}
}