{
  "type": "Feature",
  "properties": {
    "gn:admin1_code":"5",
    "gn:admin2_code":"69.0",
    "gn:asciiname":"El Prado",
    "gn:country_code":"MX",
    "gn:dem":10,
    "gn:feature_class":"P",
    "gn:feature_code":"PPL",
    "gn:name":"El Prado",
    "gn:population":0,
    "gn:timezone":"America/Mexico_City",
    "iso:country":"MX",
    "name:ceb_x_preferred":[
        "El Prado"
    ],
    "name:spa_x_preferred":[
        "El Prado"
    ],
    "name:srp_x_preferred":[
        "\u0415\u043b \u041f\u0440\u0430\u0434\u043e"
    ],
    "name:swe_x_preferred":[
        "El Prado"
    ],
    "wof:name":"El Prado",
    "wof:placetype":"locality"
},
  "geometry": {"coordinates":[-93.39445000000001,15.76024],"type":"Point"}
}