{
  "type": "Feature",
  "properties": {
    "gn:admin1_code":"28.0",
    "gn:admin2_code":"19.0",
    "gn:asciiname":"Dos de Octubre",
    "gn:country_code":"MX",
    "gn:dem":177,
    "gn:feature_class":"P",
    "gn:feature_code":"PPL",
    "gn:name":"Dos de Octubre",
    "gn:population":129,
    "gn:timezone":"America/Monterrey",
    "iso:country":"MX",
    "name:spa_x_preferred":[
        "Dos de Octubre"
    ],
    "wof:name":"Dos de Octubre",
    "wof:placetype":"locality",
    "wof:population":129
},
  "geometry": {"coordinates":[-98.93138999999999,23.16722],"type":"Point"}
}