{
  "type": "Feature",
  "properties": {
    "gn:admin1_code":"5",
    "gn:admin2_code":"71",
    "gn:asciiname":"La Purisima",
    "gn:country_code":"MX",
    "gn:dem":10,
    "gn:feature_class":"P",
    "gn:feature_code":"PPL",
    "gn:name":"La Pur\u00edsima",
    "gn:population":10,
    "gn:timezone":"America/Mexico_City",
    "iso:country":"MX",
    "name:und_x_variant":[
        "La Pur\u00edsima"
    ],
    "wof:name":"La Purisima",
    "wof:placetype":"locality",
    "wof:population":10
},
  "geometry": {"coordinates":[-92.68528000000001,15.13719],"type":"Point"}
}