{
  "type": "Feature",
  "properties": {
    "gn:admin1_code":"14.0",
    "gn:admin2_code":"11.0",
    "gn:asciiname":"El Sobaco",
    "gn:country_code":"MX",
    "gn:dem":1417,
    "gn:feature_class":"P",
    "gn:feature_code":"PPL",
    "gn:name":"El Sobaco",
    "gn:population":0,
    "gn:timezone":"America/Mexico_City",
    "iso:country":"MX",
    "name:spa_x_preferred":[
        "El Sobaco"
    ],
    "wof:name":"El Sobaco",
    "wof:placetype":"locality"
},
  "geometry": {"coordinates":[-104.29142,20.24629],"type":"Point"}
}