{
  "type": "Feature",
  "properties": {
    "gn:admin1_code":"19.0",
    "gn:asciiname":"Cuatro de Diciembre",
    "gn:country_code":"MX",
    "gn:dem":455,
    "gn:feature_class":"P",
    "gn:feature_code":"PPL",
    "gn:name":"Cuatro de Diciembre",
    "gn:population":0,
    "gn:timezone":"America/Monterrey",
    "iso:country":"MX",
    "name:spa_x_preferred":[
        "Cuatro de Diciembre"
    ],
    "wof:name":"Cuatro de Diciembre",
    "wof:placetype":"locality"
},
  "geometry": {"coordinates":[-100.29755,25.93275],"type":"Point"}
}