{
  "type": "Feature",
  "properties": {
    "gn:admin1_code":"10",
    "gn:admin2_code":"14",
    "gn:asciiname":"Los Capulines",
    "gn:country_code":"MX",
    "gn:dem":2866,
    "gn:feature_class":"P",
    "gn:feature_code":"PPL",
    "gn:name":"Los Capulines",
    "gn:population":16,
    "gn:timezone":"America/Monterrey",
    "iso:country":"MX",
    "wof:name":"Los Capulines",
    "wof:placetype":"locality",
    "wof:population":16
},
  "geometry": {"coordinates":[-104.73111,23.28777],"type":"Point"}
}