{
  "type": "Feature",
  "properties": {
    "gn:admin1_code":"16.0",
    "gn:admin2_code":"98.0",
    "gn:asciiname":"Cerrito Colorado",
    "gn:country_code":"MX",
    "gn:dem":1766,
    "gn:feature_class":"P",
    "gn:feature_code":"PPL",
    "gn:name":"Cerrito Colorado",
    "gn:population":0,
    "gn:timezone":"America/Mexico_City",
    "iso:country":"MX",
    "name:spa_x_preferred":[
        "Cerrito Colorado"
    ],
    "wof:name":"Cerrito Colorado",
    "wof:placetype":"locality"
},
  "geometry": {"coordinates":[-100.50303,19.55174],"type":"Point"}
}