{
  "type": "Feature",
  "properties": {
    "gn:admin1_code":"17",
    "gn:admin2_code":"7.0",
    "gn:asciiname":"Loma del Cerrado",
    "gn:country_code":"MX",
    "gn:dem":1627,
    "gn:feature_class":"P",
    "gn:feature_code":"PPL",
    "gn:name":"Loma del Cerrado",
    "gn:population":7,
    "gn:timezone":"America/Mexico_City",
    "iso:country":"MX",
    "wof:name":"Loma del Cerrado",
    "wof:placetype":"locality",
    "wof:population":7
},
  "geometry": {"coordinates":[-99.26861,18.92194],"type":"Point"}
}