{
  "type": "Feature",
  "properties": {
    "gn:admin1_code":"5.0",
    "gn:asciiname":"La Panela",
    "gn:country_code":"MX",
    "gn:dem":1902,
    "gn:feature_class":"P",
    "gn:feature_code":"PPL",
    "gn:name":"La Panela",
    "gn:population":0,
    "gn:timezone":"America/Mexico_City",
    "iso:country":"MX",
    "name:spa_x_preferred":[
        "La Panela"
    ],
    "name:spa_x_variant":[
        "Cerro La Panela"
    ],
    "wof:name":"La Panela",
    "wof:placetype":"locality"
},
  "geometry": {"coordinates":[-93.23266,15.85485],"type":"Point"}
}