{
  "type": "Feature",
  "properties": {
    "gn:admin1_code":"2.0",
    "gn:asciiname":"Las Minitas",
    "gn:country_code":"MX",
    "gn:dem":691,
    "gn:feature_class":"P",
    "gn:feature_code":"PPL",
    "gn:name":"Las Minitas",
    "gn:population":0,
    "gn:timezone":"America/Tijuana",
    "iso:country":"MX",
    "name:spa_x_preferred":[
        "Las Minitas"
    ],
    "wof:name":"Las Minitas",
    "wof:placetype":"locality"
},
  "geometry": {"coordinates":[-116.38742999999999,31.91025],"type":"Point"}
}