{
  "type": "Feature",
  "properties": {
    "gn:admin1_code":"4",
    "gn:admin2_code":"3.0",
    "gn:asciiname":"Brasil",
    "gn:country_code":"MX",
    "gn:dem":10,
    "gn:feature_class":"P",
    "gn:feature_code":"PPL",
    "gn:name":"Brasil",
    "gn:population":8,
    "gn:timezone":"America/Merida",
    "iso:country":"MX",
    "wof:name":"Brasil",
    "wof:placetype":"locality",
    "wof:population":8
},
  "geometry": {"coordinates":[-91.12444000000001,18.48361],"type":"Point"}
}