{
  "type": "Feature",
  "properties": {
    "gn:admin1_code":"25",
    "gn:admin2_code":"1.0",
    "gn:asciiname":"Albergue Santa Rosa",
    "gn:country_code":"MX",
    "gn:dem":24,
    "gn:feature_class":"P",
    "gn:feature_code":"PPL",
    "gn:name":"Albergue Santa Rosa",
    "gn:population":78,
    "gn:timezone":"America/Mazatlan",
    "iso:country":"MX",
    "wof:name":"Albergue Santa Rosa",
    "wof:placetype":"locality",
    "wof:population":78
},
  "geometry": {"coordinates":[-108.90299,25.86731],"type":"Point"}
}