{
  "type": "Feature",
  "properties": {
    "gn:admin1_code":"32.0",
    "gn:admin2_code":"27.0",
    "gn:asciiname":"Cerros Altos",
    "gn:country_code":"MX",
    "gn:dem":2016,
    "gn:feature_class":"P",
    "gn:feature_code":"PPL",
    "gn:name":"Cerros Altos",
    "gn:population":0,
    "gn:timezone":"America/Mexico_City",
    "iso:country":"MX",
    "name:spa_x_preferred":[
        "Cerros Altos"
    ],
    "wof:name":"Cerros Altos",
    "wof:placetype":"locality"
},
  "geometry": {"coordinates":[-101.69114,24.77508],"type":"Point"}
}