{
  "type": "Feature",
  "properties": {
    "gn:admin1_code":"26",
    "gn:asciiname":"Los Veneros",
    "gn:country_code":"MX",
    "gn:dem":556,
    "gn:feature_class":"P",
    "gn:feature_code":"PPL",
    "gn:name":"Los Veneros",
    "gn:population":0,
    "gn:timezone":"America/Mazatlan",
    "iso:country":"MX",
    "name:und_x_variant":[
        "Veneros",
        "Los Veneros"
    ],
    "wof:name":"Los Veneros",
    "wof:placetype":"locality"
},
  "geometry": {"coordinates":[-106.48138,24.08038],"type":"Point"}
}