{
  "type": "Feature",
  "properties": {
    "gn:admin1_code":"10",
    "gn:admin2_code":"34.0",
    "gn:asciiname":"Huisolista",
    "gn:country_code":"MX",
    "gn:dem":277,
    "gn:feature_class":"P",
    "gn:feature_code":"PPL",
    "gn:name":"Huisolista",
    "gn:population":0,
    "gn:timezone":"America/Monterrey",
    "iso:country":"MX",
    "name:spa_x_preferred":[
        "Huisolista"
    ],
    "name:und_x_variant":[
        "Huisolsta"
    ],
    "wof:name":"Huisolista",
    "wof:placetype":"locality"
},
  "geometry": {"coordinates":[-107.01835,24.98912],"type":"Point"}
}