{
  "type": "Feature",
  "properties": {
    "gn:admin1_code":"7",
    "gn:admin2_code":"28.0",
    "gn:asciiname":"Guadalupe Victoria",
    "gn:country_code":"MX",
    "gn:dem":325,
    "gn:feature_class":"P",
    "gn:feature_code":"PPL",
    "gn:name":"Guadalupe Victoria",
    "gn:population":0,
    "gn:timezone":"America/Monterrey",
    "iso:country":"MX",
    "name:und_x_variant":[
        "Ejido Guadalupe Victoria",
        "Guadalupe Victoria",
        "Pueblo Nuevo"
    ],
    "wof:name":"Guadalupe Victoria",
    "wof:placetype":"locality"
},
  "geometry": {"coordinates":[-101.01824999999999,27.77292000000001],"type":"Point"}
}