{
  "type": "Feature",
  "properties": {
    "gn:admin1_code":"30",
    "gn:admin2_code":"38.0",
    "gn:asciiname":"San Jacinto",
    "gn:country_code":"MX",
    "gn:dem":1234,
    "gn:feature_class":"P",
    "gn:feature_code":"PPL",
    "gn:name":"San Jacinto",
    "gn:population":199,
    "gn:timezone":"America/Mexico_City",
    "iso:country":"MX",
    "wof:name":"San Jacinto",
    "wof:placetype":"locality",
    "wof:population":199
},
  "geometry": {"coordinates":[-96.95111,19.48194],"type":"Point"}
}