{
  "type": "Feature",
  "properties": {
    "gn:admin1_code":"16",
    "gn:admin2_code":"97",
    "gn:asciiname":"Los Guajes del Capire",
    "gn:country_code":"MX",
    "gn:dem":445,
    "gn:feature_class":"P",
    "gn:feature_code":"PPL",
    "gn:name":"Los Guajes del Capire",
    "gn:population":27,
    "gn:timezone":"America/Mexico_City",
    "iso:country":"MX",
    "wof:name":"Los Guajes del Capire",
    "wof:placetype":"locality",
    "wof:population":27
},
  "geometry": {"coordinates":[-101.29139000000001,18.86944],"type":"Point"}
}