{
  "type": "Feature",
  "properties": {
    "gn:admin1_code":"11",
    "gn:admin2_code":"34",
    "gn:asciiname":"Charco del Muerto",
    "gn:country_code":"MX",
    "gn:dem":1625,
    "gn:feature_class":"P",
    "gn:feature_code":"PPL",
    "gn:name":"Charco del Muerto",
    "gn:population":29,
    "gn:timezone":"America/Mexico_City",
    "iso:country":"MX",
    "wof:name":"Charco del Muerto",
    "wof:placetype":"locality",
    "wof:population":29
},
  "geometry": {"coordinates":[-100.10138999999999,21.13083],"type":"Point"}
}