{
  "type": "Feature",
  "properties": {
    "gn:admin1_code":"3",
    "gn:admin2_code":"3",
    "gn:asciiname":"La Palmilla",
    "gn:country_code":"MX",
    "gn:dem":271,
    "gn:feature_class":"P",
    "gn:feature_code":"PPL",
    "gn:name":"La Palmilla",
    "gn:population":9,
    "gn:timezone":"America/Mazatlan",
    "iso:country":"MX",
    "wof:name":"La Palmilla",
    "wof:placetype":"locality",
    "wof:population":9
},
  "geometry": {"coordinates":[-110.19915,24.10674],"type":"Point"}
}