{
  "type": "Feature",
  "properties": {
    "gn:admin1_code":"22",
    "gn:admin2_code":"3.0",
    "gn:asciiname":"La Maroma",
    "gn:country_code":"MX",
    "gn:dem":534,
    "gn:feature_class":"P",
    "gn:feature_code":"PPL",
    "gn:name":"La Maroma",
    "gn:population":68,
    "gn:timezone":"America/Mexico_City",
    "iso:country":"MX",
    "name:spa_x_preferred":[
        "La Maroma"
    ],
    "wof:name":"La Maroma",
    "wof:placetype":"locality",
    "wof:population":68
},
  "geometry": {"coordinates":[-99.60541000000001,21.41796],"type":"Point"}
}