{
  "type": "Feature",
  "properties": {
    "gn:admin1_code":"16.0",
    "gn:admin2_code":"91.0",
    "gn:asciiname":"Guascaro de Mujica",
    "gn:country_code":"MX",
    "gn:dem":1721,
    "gn:feature_class":"P",
    "gn:feature_code":"PPL",
    "gn:name":"Gu\u00e1scaro de Mujica",
    "gn:population":0,
    "gn:timezone":"America/Mexico_City",
    "iso:country":"MX",
    "name:spa_x_preferred":[
        "Gu\u00e1scaro de Mujica"
    ],
    "name:und_x_variant":[
        "Gu\u00e1scaro",
        "Gu\u00e1scuaro",
        "Gu\u00e1scaro Alto"
    ],
    "wof:name":"Guascaro de Mujica",
    "wof:placetype":"locality"
},
  "geometry": {"coordinates":[-102.52067,19.79784],"type":"Point"}
}