{
  "type": "Feature",
  "properties": {
    "gn:admin1_code":"6",
    "gn:admin2_code":"65.0",
    "gn:asciiname":"Hogue",
    "gn:country_code":"MX",
    "gn:dem":2073,
    "gn:feature_class":"P",
    "gn:feature_code":"PPL",
    "gn:name":"Hogu\u00e9",
    "gn:population":0,
    "gn:timezone":"America/Chihuahua",
    "iso:country":"MX",
    "name:spa_x_preferred":[
        "Hogu\u00e9"
    ],
    "wof:name":"Hogue",
    "wof:placetype":"locality"
},
  "geometry": {"coordinates":[-107.75391999999999,27.4062],"type":"Point"}
}