{
  "type": "Feature",
  "properties": {
    "gn:admin1_code":"22",
    "gn:admin2_code":"7",
    "gn:asciiname":"El Paraiso",
    "gn:country_code":"MX",
    "gn:dem":1999,
    "gn:feature_class":"P",
    "gn:feature_code":"PPL",
    "gn:name":"El Paraiso",
    "gn:population":19,
    "gn:timezone":"America/Mexico_City",
    "iso:country":"MX",
    "wof:name":"El Paraiso",
    "wof:placetype":"locality",
    "wof:population":19
},
  "geometry": {"coordinates":[-99.88361,20.68611],"type":"Point"}
}