{
  "type": "Feature",
  "properties": {
    "gn:admin1_code":"19",
    "gn:admin2_code":"30",
    "gn:asciiname":"Lampazos",
    "gn:country_code":"MX",
    "gn:dem":931,
    "gn:feature_class":"P",
    "gn:feature_code":"PPL",
    "gn:name":"Lampazos",
    "gn:population":37,
    "gn:timezone":"America/Monterrey",
    "iso:country":"MX",
    "wof:name":"Lampazos",
    "wof:placetype":"locality",
    "wof:population":37
},
  "geometry": {"coordinates":[-99.81442,24.60091],"type":"Point"}
}