{
  "type": "Feature",
  "properties": {
    "gn:admin1_code":"5",
    "gn:admin2_code":"70.0",
    "gn:asciiname":"Las Maravillas Uno",
    "gn:country_code":"MX",
    "gn:dem":2358,
    "gn:feature_class":"P",
    "gn:feature_code":"PPL",
    "gn:name":"Las Maravillas Uno",
    "gn:population":191,
    "gn:timezone":"America/Mexico_City",
    "iso:country":"MX",
    "wof:name":"Las Maravillas Uno",
    "wof:placetype":"locality",
    "wof:population":191
},
  "geometry": {"coordinates":[-92.32056,15.42028],"type":"Point"}
}