{
  "type": "Feature",
  "properties": {
    "gn:admin1_code":"14.0",
    "gn:admin2_code":"17.0",
    "gn:asciiname":"Buckingham",
    "gn:country_code":"MX",
    "gn:dem":1230,
    "gn:feature_class":"P",
    "gn:feature_code":"PPL",
    "gn:name":"B\u00fackingham",
    "gn:population":0,
    "gn:timezone":"America/Mexico_City",
    "iso:country":"MX",
    "wof:name":"Buckingham",
    "wof:placetype":"locality"
},
  "geometry": {"coordinates":[-104.39032,20.01677],"type":"Point"}
}