{
  "type": "Feature",
  "properties": {
    "gn:admin1_code":"14.0",
    "gn:admin2_code":"17.0",
    "gn:asciiname":"Buckingham",
    "gn:country_code":"MX",
    "gn:dem":1230,
    "gn:feature_class":"P",
    "gn:feature_code":"PPL",
    "gn:name":"B\u00fackingham",
    "gn:population":0,
    "gn:timezone":"America/Mexico_City",
    "iso:country":"MX",
    "name:ara_x_preferred":[
        "\u0628\u0627\u0643\u0646\u063a\u0647\u0627\u0645"
    ],
    "name:azb_x_preferred":[
        "\u0628\u0627\u06a9\u06cc\u0646\u0642\u0647\u0627\u0645"
    ],
    "name:bar_x_preferred":[
        "Buckingham"
    ],
    "name:cat_x_preferred":[
        "Buckingham"
    ],
    "name:cym_x_preferred":[
        "Buckingham"
    ],
    "name:dan_x_preferred":[
        "Buckingham"
    ],
    "name:deu_x_preferred":[
        "Buckingham"
    ],
    "name:fas_x_preferred":[
        "\u0628\u0627\u06a9\u06cc\u0646\u06af\u0647\u0627\u0645"
    ],
    "name:fra_x_preferred":[
        "Buckingham"
    ],
    "name:gle_x_preferred":[
        "Buckingham"
    ],
    "name:glg_x_preferred":[
        "Buckingham"
    ],
    "name:ita_x_preferred":[
        "Buckingham"
    ],
    "name:lat_x_preferred":[
        "Buckinghamia"
    ],
    "name:nld_x_preferred":[
        "Buckingham"
    ],
    "name:nno_x_preferred":[
        "Buckingham"
    ],
    "name:nor_x_preferred":[
        "Buckingham"
    ],
    "name:pol_x_preferred":[
        "Buckingham"
    ],
    "name:por_x_preferred":[
        "Buckingham"
    ],
    "name:ron_x_preferred":[
        "Buckingham"
    ],
    "name:rus_x_preferred":[
        "\u0411\u0430\u043a\u0438\u043d\u0433\u0435\u043c"
    ],
    "name:spa_x_preferred":[
        "Buckingham"
    ],
    "name:swe_x_preferred":[
        "Buckingham"
    ],
    "name:urd_x_preferred":[
        "\u0628\u06a9\u0646\u06af\u06be\u0645"
    ],
    "name:vie_x_preferred":[
        "Buckingham"
    ],
    "name:vol_x_preferred":[
        "Buckingham"
    ],
    "name:zho_x_preferred":[
        "\u767d\u91d1\u6f22"
    ],
    "wof:name":"Buckingham",
    "wof:placetype":"locality"
},
  "geometry": {"coordinates":[-104.39032,20.01677],"type":"Point"}
}