{
  "type": "Feature",
  "properties": {
    "gn:admin1_code":"16.0",
    "gn:admin2_code":"6.0",
    "gn:asciiname":"Maria Teresa",
    "gn:country_code":"MX",
    "gn:dem":224,
    "gn:feature_class":"P",
    "gn:feature_code":"PPL",
    "gn:name":"Mar\u00eda Teresa",
    "gn:population":0,
    "gn:timezone":"America/Mexico_City",
    "iso:country":"MX",
    "name:spa_x_preferred":[
        "Mar\u00eda Teresa"
    ],
    "wof:name":"Maria Teresa",
    "wof:placetype":"locality"
},
  "geometry": {"coordinates":[-102.47103,19.01363],"type":"Point"}
}