{
  "type": "Feature",
  "properties": {
    "gn:admin1_code":"23.0",
    "gn:asciiname":"Antares",
    "gn:country_code":"MX",
    "gn:dem":11,
    "gn:feature_class":"P",
    "gn:feature_code":"PPL",
    "gn:name":"Antares",
    "gn:population":0,
    "gn:timezone":"America/Cancun",
    "iso:country":"MX",
    "name:spa_x_preferred":[
        "Antares"
    ],
    "wof:name":"Antares",
    "wof:placetype":"locality"
},
  "geometry": {"coordinates":[-87.10533000000002,20.64053],"type":"Point"}
}