{
  "type": "Feature",
  "properties": {
    "gn:admin1_code":"16",
    "gn:admin2_code":"38",
    "gn:asciiname":"Tierras Blancas",
    "gn:country_code":"MX",
    "gn:dem":552,
    "gn:feature_class":"P",
    "gn:feature_code":"PPL",
    "gn:name":"Tierras Blancas",
    "gn:population":26,
    "gn:timezone":"America/Mexico_City",
    "iso:country":"MX",
    "wof:name":"Tierras Blancas",
    "wof:placetype":"locality",
    "wof:population":26
},
  "geometry": {"coordinates":[-100.95193999999999,18.76861],"type":"Point"}
}