{
  "type": "Feature",
  "properties": {
    "gn:admin1_code":"8",
    "gn:admin2_code":"6.0",
    "gn:asciiname":"Zinacamitlan (Los Chicos)",
    "gn:country_code":"MX",
    "gn:dem":118,
    "gn:feature_class":"P",
    "gn:feature_code":"PPL",
    "gn:name":"Zinacamitl\u00e1n (Los Chicos)",
    "gn:population":295,
    "gn:timezone":"America/Mexico_City",
    "iso:country":"MX",
    "name:und_x_variant":[
        "Cinacamitl\u00e1n",
        "Zinacamitl\u00e1n",
        "Zinacamit\u00e1n"
    ],
    "wof:name":"Zinacamitlan (Los Chicos)",
    "wof:placetype":"locality",
    "wof:population":295
},
  "geometry": {"coordinates":[-103.69601,18.97936],"type":"Point"}
}