{
  "type": "Feature",
  "properties": {
    "gn:admin1_code":"19",
    "gn:admin2_code":"5.0",
    "gn:asciiname":"Genaro Perez",
    "gn:country_code":"MX",
    "gn:dem":193,
    "gn:feature_class":"P",
    "gn:feature_code":"PPL",
    "gn:name":"Genaro P\u00e9rez",
    "gn:population":7,
    "gn:timezone":"America/Matamoros",
    "iso:country":"MX",
    "name:und_x_variant":[
        "Genaro P\u00e9rez"
    ],
    "wof:name":"Genaro Perez",
    "wof:placetype":"locality",
    "wof:population":7
},
  "geometry": {"coordinates":[-100.13561,27.21002],"type":"Point"}
}