{
  "type": "Feature",
  "properties": {
    "gn:admin1_code":"30",
    "gn:admin2_code":"126",
    "gn:asciiname":"Mata de Cana (Loma de Toche)",
    "gn:country_code":"MX",
    "gn:dem":31,
    "gn:feature_class":"P",
    "gn:feature_code":"PPL",
    "gn:name":"Mata de Ca\u00f1a (Loma de Toche)",
    "gn:population":41,
    "gn:timezone":"America/Mexico_City",
    "iso:country":"MX",
    "name:und_x_variant":[
        "Mata de Ca\u00f1a (Loma de Toche)"
    ],
    "wof:name":"Mata de Cana (Loma de Toche)",
    "wof:placetype":"locality",
    "wof:population":41
},
  "geometry": {"coordinates":[-96.37083,19.25417],"type":"Point"}
}