{
  "type": "Feature",
  "properties": {
    "gn:admin1_code":"6",
    "gn:admin2_code":"19",
    "gn:asciiname":"El Comienzo",
    "gn:country_code":"MX",
    "gn:dem":1587,
    "gn:feature_class":"P",
    "gn:feature_code":"PPL",
    "gn:name":"El Comienzo",
    "gn:population":10,
    "gn:timezone":"America/Chihuahua",
    "iso:country":"MX",
    "wof:name":"El Comienzo",
    "wof:placetype":"locality",
    "wof:population":10
},
  "geometry": {"coordinates":[-106.30745,29.00157],"type":"Point"}
}