{
  "type": "Feature",
  "properties": {
    "gn:admin1_code":"7.0",
    "gn:admin2_code":"20.0",
    "gn:asciiname":"El Consuelo",
    "gn:country_code":"MX",
    "gn:dem":504,
    "gn:feature_class":"P",
    "gn:feature_code":"PPL",
    "gn:name":"El Consuelo",
    "gn:population":0,
    "gn:timezone":"America/Monterrey",
    "iso:country":"MX",
    "name:und_x_variant":[
        "Rancho El Consuelo",
        "El Consuelo"
    ],
    "wof:name":"El Consuelo",
    "wof:placetype":"locality"
},
  "geometry": {"coordinates":[-101.54534,28.28106],"type":"Point"}
}