{
  "type": "Feature",
  "properties": {
    "gn:admin1_code":"6",
    "gn:admin2_code":"65",
    "gn:asciiname":"Huitosachi",
    "gn:country_code":"MX",
    "gn:dem":2198,
    "gn:feature_class":"P",
    "gn:feature_code":"PPL",
    "gn:name":"Huitosachi",
    "gn:population":48,
    "gn:timezone":"America/Chihuahua",
    "iso:country":"MX",
    "wof:name":"Huitosachi",
    "wof:placetype":"locality",
    "wof:population":48
},
  "geometry": {"coordinates":[-107.85492000000001,27.52686],"type":"Point"}
}