{
  "type": "Feature",
  "properties": {
    "gn:admin1_code":"30",
    "gn:admin2_code":"207.0",
    "gn:asciiname":"Benjamin Salomon",
    "gn:country_code":"MX",
    "gn:dem":17,
    "gn:feature_class":"P",
    "gn:feature_code":"PPL",
    "gn:name":"Benjam\u00edn Salom\u00f3n",
    "gn:population":7,
    "gn:timezone":"America/Mexico_City",
    "iso:country":"MX",
    "name:und_x_variant":[
        "Benjam\u00edn Salom\u00f3n"
    ],
    "wof:name":"Benjamin Salomon",
    "wof:placetype":"locality",
    "wof:population":7
},
  "geometry": {"coordinates":[-96.06722000000001,18.37889],"type":"Point"}
}