{
  "type": "Feature",
  "properties": {
    "gn:admin1_code":"15.0",
    "gn:admin2_code":"105.0",
    "gn:asciiname":"Corral de Vigas",
    "gn:country_code":"MX",
    "gn:dem":564,
    "gn:feature_class":"P",
    "gn:feature_code":"PPL",
    "gn:name":"Corral de Vigas",
    "gn:population":0,
    "gn:timezone":"America/Mexico_City",
    "iso:country":"MX",
    "name:spa_x_preferred":[
        "Corral de Vigas"
    ],
    "wof:name":"Corral de Vigas",
    "wof:placetype":"locality"
},
  "geometry": {"coordinates":[-100.4359,18.5655],"type":"Point"}
}