{
  "type": "Feature",
  "properties": {
    "gn:admin1_code":"14",
    "gn:admin2_code":"14.0",
    "gn:asciiname":"Poncitlan",
    "gn:country_code":"MX",
    "gn:dem":1352,
    "gn:feature_class":"P",
    "gn:feature_code":"PPL",
    "gn:name":"Poncitl\u00e1n",
    "gn:population":199,
    "gn:timezone":"America/Mexico_City",
    "iso:country":"MX",
    "wof:name":"Poncitlan",
    "wof:placetype":"locality",
    "wof:population":199
},
  "geometry": {"coordinates":[-103.48641000000001,20.05256],"type":"Point"}
}