{
  "type": "Feature",
  "properties": {
    "gn:admin1_code":"6",
    "gn:admin2_code":"1.0",
    "gn:asciiname":"Mundo Nuevo",
    "gn:country_code":"MX",
    "gn:dem":1419,
    "gn:feature_class":"P",
    "gn:feature_code":"PPL",
    "gn:name":"Mundo Nuevo",
    "gn:population":0,
    "gn:timezone":"America/Chihuahua",
    "iso:country":"MX",
    "wof:name":"Mundo Nuevo",
    "wof:placetype":"locality"
},
  "geometry": {"coordinates":[-106.19018,29.92099],"type":"Point"}
}