{
  "type": "Feature",
  "properties": {
    "gn:admin1_code":"20",
    "gn:admin2_code":"217.0",
    "gn:asciiname":"Canada Tierra Blanca",
    "gn:country_code":"MX",
    "gn:dem":2245,
    "gn:feature_class":"P",
    "gn:feature_code":"PPL",
    "gn:name":"Ca\u00f1ada Tierra Blanca",
    "gn:population":9,
    "gn:timezone":"America/Mexico_City",
    "iso:country":"MX",
    "name:und_x_variant":[
        "Ca\u00f1ada Tierra Blanca"
    ],
    "wof:name":"Canada Tierra Blanca",
    "wof:placetype":"locality",
    "wof:population":9
},
  "geometry": {"coordinates":[-97.11306,17.13944],"type":"Point"}
}