{
  "type": "Feature",
  "properties": {
    "gn:admin1_code":"30",
    "gn:admin2_code":"28.0",
    "gn:asciiname":"El Estero",
    "gn:country_code":"MX",
    "gn:dem":8,
    "gn:feature_class":"P",
    "gn:feature_code":"PPL",
    "gn:name":"El Estero",
    "gn:population":102,
    "gn:timezone":"America/Mexico_City",
    "iso:country":"MX",
    "wof:name":"El Estero",
    "wof:placetype":"locality",
    "wof:population":102
},
  "geometry": {"coordinates":[-96.10138999999999,19.09472],"type":"Point"}
}