{
  "type": "Feature",
  "properties": {
    "gn:admin1_code":"20",
    "gn:admin2_code":"566.0",
    "gn:asciiname":"Santa Cruz",
    "gn:country_code":"MX",
    "gn:dem":1516,
    "gn:feature_class":"P",
    "gn:feature_code":"PPL",
    "gn:name":"Santa Cruz",
    "gn:population":63,
    "gn:timezone":"America/Mexico_City",
    "iso:country":"MX",
    "wof:name":"Santa Cruz",
    "wof:placetype":"locality",
    "wof:population":63
},
  "geometry": {"coordinates":[-97.25028,16.87056],"type":"Point"}
}