{
  "type": "Feature",
  "properties": {
    "gn:admin1_code":"30",
    "gn:admin2_code":"5.0",
    "gn:asciiname":"El Talladero",
    "gn:country_code":"MX",
    "gn:dem":6,
    "gn:feature_class":"P",
    "gn:feature_code":"PPL",
    "gn:name":"El Talladero",
    "gn:population":214,
    "gn:timezone":"America/Mexico_City",
    "iso:country":"MX",
    "wof:name":"El Talladero",
    "wof:placetype":"locality",
    "wof:population":214
},
  "geometry": {"coordinates":[-95.80361000000001,18.55194],"type":"Point"}
}