{
  "type": "Feature",
  "properties": {
    "gn:admin1_code":"26",
    "gn:admin2_code":"15.0",
    "gn:asciiname":"El Fuste",
    "gn:country_code":"MX",
    "gn:dem":1525,
    "gn:feature_class":"P",
    "gn:feature_code":"PPL",
    "gn:name":"El Fuste",
    "gn:population":1,
    "gn:timezone":"America/Hermosillo",
    "iso:country":"MX",
    "name:und_x_variant":[
        "Rancho El Fuste",
        "El Fuste"
    ],
    "wof:name":"El Fuste",
    "wof:placetype":"locality",
    "wof:population":1
},
  "geometry": {"coordinates":[-108.86712,30.59382],"type":"Point"}
}