{
  "type": "Feature",
  "properties": {
    "gn:admin1_code":"7",
    "gn:admin2_code":"4.0",
    "gn:asciiname":"Kilometro Trece",
    "gn:country_code":"MX",
    "gn:dem":1630,
    "gn:feature_class":"P",
    "gn:feature_code":"PPL",
    "gn:name":"Kil\u00f3metro Trece",
    "gn:population":5,
    "gn:timezone":"America/Monterrey",
    "iso:country":"MX",
    "name:und_x_variant":[
        "Kil\u00f3metro Trece"
    ],
    "wof:name":"Kilometro Trece",
    "wof:placetype":"locality",
    "wof:population":5
},
  "geometry": {"coordinates":[-100.86864,25.44393],"type":"Point"}
}