{
  "type": "Feature",
  "properties": {
    "gn:admin1_code":"23",
    "gn:admin2_code":"4.0",
    "gn:asciiname":"El Potrillo",
    "gn:country_code":"MX",
    "gn:dem":3,
    "gn:feature_class":"P",
    "gn:feature_code":"PPL",
    "gn:name":"El Potrillo",
    "gn:population":8,
    "gn:timezone":"America/Cancun",
    "iso:country":"MX",
    "wof:name":"El Potrillo",
    "wof:placetype":"locality",
    "wof:population":8
},
  "geometry": {"coordinates":[-88.19954,18.82278],"type":"Point"}
}