{
  "type": "Feature",
  "properties": {
    "gn:admin1_code":"12",
    "gn:admin2_code":"7",
    "gn:asciiname":"La Laguna",
    "gn:country_code":"MX",
    "gn:dem":1031,
    "gn:feature_class":"P",
    "gn:feature_code":"PPL",
    "gn:name":"La Laguna",
    "gn:population":15,
    "gn:timezone":"America/Mexico_City",
    "iso:country":"MX",
    "wof:name":"La Laguna",
    "wof:placetype":"locality",
    "wof:population":15
},
  "geometry": {"coordinates":[-100.17744999999999,18.20441],"type":"Point"}
}