{
  "type": "Feature",
  "properties": {
    "gn:admin1_code":"20",
    "gn:admin2_code":"334",
    "gn:asciiname":"El Espinal",
    "gn:country_code":"MX",
    "gn:dem":15,
    "gn:feature_class":"P",
    "gn:feature_code":"PPL",
    "gn:name":"El Espinal",
    "gn:population":10,
    "gn:timezone":"America/Mexico_City",
    "iso:country":"MX",
    "name:cat_x_preferred":[
        "L'Espinal"
    ],
    "name:ceb_x_preferred":[
        "El Espinal"
    ],
    "name:ita_x_preferred":[
        "El Espinal"
    ],
    "name:spa_x_preferred":[
        "El Espinal"
    ],
    "name:srp_x_preferred":[
        "\u0415\u043b \u0415\u0441\u043f\u0438\u043d\u0430\u043b"
    ],
    "name:swe_x_preferred":[
        "El Espinal"
    ],
    "wof:name":"El Espinal",
    "wof:placetype":"locality",
    "wof:population":10
},
  "geometry": {"coordinates":[-97.58,16.03722],"type":"Point"}
}