{
  "type": "Feature",
  "properties": {
    "gn:admin1_code":"20",
    "gn:admin2_code":"171",
    "gn:asciiname":"Patio Viejo",
    "gn:country_code":"MX",
    "gn:dem":324,
    "gn:feature_class":"P",
    "gn:feature_code":"PPL",
    "gn:name":"Patio Viejo",
    "gn:population":38,
    "gn:timezone":"America/Mexico_City",
    "iso:country":"MX",
    "wof:name":"Patio Viejo",
    "wof:placetype":"locality",
    "wof:population":38
},
  "geometry": {"coordinates":[-96.66083,18.20889],"type":"Point"}
}