{
  "type": "Feature",
  "properties": {
    "gn:admin1_code":"25",
    "gn:admin2_code":"1.0",
    "gn:asciiname":"Caduchiu",
    "gn:country_code":"MX",
    "gn:dem":11,
    "gn:feature_class":"P",
    "gn:feature_code":"PPL",
    "gn:name":"Caduchiu",
    "gn:population":0,
    "gn:timezone":"America/Mazatlan",
    "iso:country":"MX",
    "name:spa_x_preferred":[
        "Caduchiu"
    ],
    "wof:name":"Caduchiu",
    "wof:placetype":"locality"
},
  "geometry": {"coordinates":[-109.11638000000001,25.90918],"type":"Point"}
}