{
  "type": "Feature",
  "properties": {
    "gn:admin1_code":"16",
    "gn:admin2_code":"50.0",
    "gn:asciiname":"San Isidrito",
    "gn:country_code":"MX",
    "gn:dem":2481,
    "gn:feature_class":"P",
    "gn:feature_code":"PPL",
    "gn:name":"San Isidrito",
    "gn:population":59,
    "gn:timezone":"America/Mexico_City",
    "iso:country":"MX",
    "wof:name":"San Isidrito",
    "wof:placetype":"locality",
    "wof:population":59
},
  "geometry": {"coordinates":[-100.36389,19.96194],"type":"Point"}
}