{
  "type": "Feature",
  "properties": {
    "gn:admin1_code":"5",
    "gn:admin2_code":"59.0",
    "gn:asciiname":"Noy Aquil",
    "gn:country_code":"MX",
    "gn:dem":1223,
    "gn:feature_class":"P",
    "gn:feature_code":"PPL",
    "gn:name":"Noy Aquil",
    "gn:population":77,
    "gn:timezone":"America/Mexico_City",
    "iso:country":"MX",
    "wof:name":"Noy Aquil",
    "wof:placetype":"locality",
    "wof:population":77
},
  "geometry": {"coordinates":[-92.24111000000001,16.855],"type":"Point"}
}