{
  "type": "Feature",
  "properties": {
    "gn:admin1_code":"28",
    "gn:admin2_code":"19",
    "gn:asciiname":"El Valle",
    "gn:country_code":"MX",
    "gn:dem":431,
    "gn:feature_class":"P",
    "gn:feature_code":"PPL",
    "gn:name":"El Valle",
    "gn:population":12,
    "gn:timezone":"America/Monterrey",
    "iso:country":"MX",
    "name:ast_x_preferred":[
        "El Valle"
    ],
    "name:ceb_x_preferred":[
        "El Valle"
    ],
    "name:deu_x_preferred":[
        "El Valle"
    ],
    "name:fra_x_preferred":[
        "El Valle"
    ],
    "name:jpn_x_preferred":[
        "\u30a8\u30eb\u30d0\u30b8\u30a7"
    ],
    "name:nld_x_preferred":[
        "El Valle"
    ],
    "name:spa_x_preferred":[
        "El Valle"
    ],
    "name:swe_x_preferred":[
        "El Valle"
    ],
    "wof:name":"El Valle",
    "wof:placetype":"locality",
    "wof:population":12
},
  "geometry": {"coordinates":[-99.03361,23.1975],"type":"Point"}
}