{
  "type": "Feature",
  "properties": {
    "gn:admin1_code":"16",
    "gn:admin2_code":"97",
    "gn:asciiname":"La Mesa del Jagueey",
    "gn:country_code":"MX",
    "gn:dem":839,
    "gn:feature_class":"P",
    "gn:feature_code":"PPL",
    "gn:name":"La Mesa del Jag\u00fcey",
    "gn:population":30,
    "gn:timezone":"America/Mexico_City",
    "iso:country":"MX",
    "name:und_x_variant":[
        "La Mesa del Jag\u00fcey"
    ],
    "wof:name":"La Mesa del Jagueey",
    "wof:placetype":"locality",
    "wof:population":30
},
  "geometry": {"coordinates":[-101.34889,19.05639],"type":"Point"}
}