{
  "type": "Feature",
  "properties": {
    "gn:admin1_code":"19",
    "gn:admin2_code":"16.0",
    "gn:asciiname":"La Canada (Fidel Garza)",
    "gn:country_code":"MX",
    "gn:dem":282,
    "gn:feature_class":"P",
    "gn:feature_code":"PPL",
    "gn:name":"La Ca\u00f1ada (Fidel Garza)",
    "gn:population":7,
    "gn:timezone":"America/Monterrey",
    "iso:country":"MX",
    "name:und_x_variant":[
        "La Ca\u00f1ada (Fidel Garza)"
    ],
    "wof:name":"La Canada (Fidel Garza)",
    "wof:placetype":"locality",
    "wof:population":7
},
  "geometry": {"coordinates":[-99.83835999999999,25.75867],"type":"Point"}
}