{
  "type": "Feature",
  "properties": {
    "gn:admin1_code":"26",
    "gn:admin2_code":"69.0",
    "gn:asciiname":"Los Huerigos",
    "gn:country_code":"MX",
    "gn:dem":658,
    "gn:feature_class":"P",
    "gn:feature_code":"PPL",
    "gn:name":"Los Hu\u00e9rigos",
    "gn:population":0,
    "gn:timezone":"America/Hermosillo",
    "iso:country":"MX",
    "name:spa_x_preferred":[
        "Los Hu\u00e9rigos"
    ],
    "wof:name":"Los Huerigos",
    "wof:placetype":"locality"
},
  "geometry": {"coordinates":[-109.20833,28.41861],"type":"Point"}
}