{
  "type": "Feature",
  "properties": {
    "gn:admin1_code":"5",
    "gn:admin2_code":"59.0",
    "gn:asciiname":"San Salvador",
    "gn:country_code":"MX",
    "gn:dem":752,
    "gn:feature_class":"P",
    "gn:feature_code":"PPL",
    "gn:name":"San Salvador",
    "gn:population":506,
    "gn:timezone":"America/Mexico_City",
    "iso:country":"MX",
    "wof:name":"San Salvador",
    "wof:placetype":"locality",
    "wof:population":506
},
  "geometry": {"coordinates":[-91.87667,16.97167],"type":"Point"}
}