{
  "type": "Feature",
  "properties": {
    "gn:admin1_code":"32",
    "gn:admin2_code":"9.0",
    "gn:asciiname":"Rancho Colorado",
    "gn:country_code":"MX",
    "gn:dem":2084,
    "gn:feature_class":"P",
    "gn:feature_code":"PPL",
    "gn:name":"Rancho Colorado",
    "gn:population":173,
    "gn:timezone":"America/Mexico_City",
    "iso:country":"MX",
    "wof:name":"Rancho Colorado",
    "wof:placetype":"locality",
    "wof:population":173
},
  "geometry": {"coordinates":[-103.92556,23.47944],"type":"Point"}
}