{
  "type": "Feature",
  "properties": {
    "gn:admin1_code":"26.0",
    "gn:admin2_code":"43.0",
    "gn:asciiname":"La Flor",
    "gn:country_code":"MX",
    "gn:dem":1133,
    "gn:feature_class":"P",
    "gn:feature_code":"PPL",
    "gn:name":"La Flor",
    "gn:population":0,
    "gn:timezone":"America/Hermosillo",
    "iso:country":"MX",
    "name:fra_x_preferred":[
        "La flor"
    ],
    "name:spa_x_preferred":[
        "La Flor"
    ],
    "wof:name":"La Flor",
    "wof:placetype":"locality"
},
  "geometry": {"coordinates":[-110.94808999999999,31.13985],"type":"Point"}
}