{
  "type": "Feature",
  "properties": {
    "gn:admin1_code":"10",
    "gn:admin2_code":"27.0",
    "gn:asciiname":"Vicente Guerrero (Siete Zacates)",
    "gn:country_code":"MX",
    "gn:dem":1710,
    "gn:feature_class":"P",
    "gn:feature_code":"PPL",
    "gn:name":"Vicente Guerrero (Siete Zacates)",
    "gn:population":218,
    "gn:timezone":"America/Monterrey",
    "iso:country":"MX",
    "wof:name":"Vicente Guerrero (Siete Zacates)",
    "wof:placetype":"locality",
    "wof:population":218
},
  "geometry": {"coordinates":[-102.62889,24.54],"type":"Point"}
}