{
  "type": "Feature",
  "properties": {
    "gn:admin1_code":"6",
    "gn:admin2_code":"55.0",
    "gn:asciiname":"Santa Rita de Casia (Ampliacion Cuarenta y Dos)",
    "gn:country_code":"MX",
    "gn:dem":1189,
    "gn:feature_class":"P",
    "gn:feature_code":"PPL",
    "gn:name":"Santa Rita de Casia (Ampliaci\u00f3n Cuarenta y Dos)",
    "gn:population":326,
    "gn:timezone":"America/Chihuahua",
    "iso:country":"MX",
    "name:und_x_variant":[
        "Santa Rita de Casia (Ampliaci\u00f3n Cuarenta y Dos)"
    ],
    "wof:name":"Santa Rita de Casia (Ampliacion Cuarenta y Dos)",
    "wof:placetype":"locality",
    "wof:population":326
},
  "geometry": {"coordinates":[-105.59944,28.45583],"type":"Point"}
}