{
  "type": "Feature",
  "properties": {
    "gn:admin1_code":"2",
    "gn:admin2_code":"2.0",
    "gn:asciiname":"Maldonado (Ejido Morelos) [Empaque]",
    "gn:country_code":"MX",
    "gn:dem":28,
    "gn:feature_class":"P",
    "gn:feature_code":"PPL",
    "gn:name":"Maldonado (Ejido Morelos) [Empaque]",
    "gn:population":7,
    "gn:timezone":"America/Tijuana",
    "iso:country":"MX",
    "wof:name":"Maldonado (Ejido Morelos) [Empaque]",
    "wof:placetype":"locality",
    "wof:population":7
},
  "geometry": {"coordinates":[-114.83944,32.63694],"type":"Point"}
}