{
  "type": "Feature",
  "properties": {
    "gn:admin1_code":"15.0",
    "gn:asciiname":"Ejido de San Pablo Huantepec",
    "gn:country_code":"MX",
    "gn:dem":2403,
    "gn:feature_class":"P",
    "gn:feature_code":"PPL",
    "gn:name":"Ejido de San Pablo Huantepec",
    "gn:population":0,
    "gn:timezone":"America/Mexico_City",
    "iso:country":"MX",
    "name:spa_x_preferred":[
        "Ejido de San Pablo Huantepec"
    ],
    "wof:name":"Ejido de San Pablo Huantepec",
    "wof:placetype":"locality"
},
  "geometry": {"coordinates":[-99.50651999999999,19.9994],"type":"Point"}
}