{
  "type": "Feature",
  "properties": {
    "gn:admin1_code":"28.0",
    "gn:admin2_code":"12.0",
    "gn:asciiname":"San Juan del Vado",
    "gn:country_code":"MX",
    "gn:dem":33,
    "gn:feature_class":"P",
    "gn:feature_code":"PPL",
    "gn:name":"San Juan del Vado",
    "gn:population":0,
    "gn:timezone":"America/Monterrey",
    "iso:country":"MX",
    "name:spa_x_preferred":[
        "San Juan del Vado"
    ],
    "wof:name":"San Juan del Vado",
    "wof:placetype":"locality"
},
  "geometry": {"coordinates":[-98.65926,22.6764],"type":"Point"}
}