{
  "type": "Feature",
  "properties": {
    "gn:admin1_code":"6",
    "gn:admin2_code":"29",
    "gn:asciiname":"La Mesa de los Meza",
    "gn:country_code":"MX",
    "gn:dem":2518,
    "gn:feature_class":"P",
    "gn:feature_code":"PPL",
    "gn:name":"La Mesa de los Meza",
    "gn:population":38,
    "gn:timezone":"America/Chihuahua",
    "iso:country":"MX",
    "wof:name":"La Mesa de los Meza",
    "wof:placetype":"locality",
    "wof:population":38
},
  "geometry": {"coordinates":[-106.93737,26.41217],"type":"Point"}
}