{
  "type": "Feature",
  "properties": {
    "gn:admin1_code":"26.0",
    "gn:admin2_code":"3.0",
    "gn:asciiname":"El Sauce",
    "gn:cc2":"MX",
    "gn:country_code":"MX",
    "gn:dem":301,
    "gn:feature_class":"P",
    "gn:feature_code":"PPL",
    "gn:name":"El Sauce",
    "gn:population":5,
    "gn:timezone":"America/Hermosillo",
    "iso:country":"MX",
    "name:und_x_variant":[
        "Sauz",
        "El Sauz"
    ],
    "wof:name":"El Sauce",
    "wof:placetype":"locality",
    "wof:population":5
},
  "geometry": {"coordinates":[-108.825,26.84583],"type":"Point"}
}