{
  "type": "Feature",
  "properties": {
    "gn:admin1_code":"13",
    "gn:admin2_code":"47.0",
    "gn:asciiname":"San Francisco",
    "gn:country_code":"MX",
    "gn:dem":1963,
    "gn:feature_class":"P",
    "gn:feature_code":"PPL",
    "gn:name":"San Francisco",
    "gn:population":254,
    "gn:timezone":"America/Mexico_City",
    "iso:country":"MX",
    "wof:name":"San Francisco",
    "wof:placetype":"locality",
    "wof:population":254
},
  "geometry": {"coordinates":[-99.35805999999999,20.97833],"type":"Point"}
}