{
  "type": "Feature",
  "properties": {
    "iso:country":"MX",
    "name:spa_x_preferred":[
        "Benito Juarez"
    ],
    "qs:gn_adm0_cc":"MX",
    "qs:gn_fcode":"PPLX",
    "qs:gn_local":3530589,
    "qs:gn_nam_loc":"Nezahualcoyotl, Ciudad Netzahualc\u00f3yotl, Mexico, MX",
    "qs:gn_namadm1":"09",
    "qs:gn_name":"Benito Ju\u00e1rez",
    "qs:local_max":88,
    "qs:local_sum":236,
    "qs:localhoods":6,
    "qs:name":"Benito Juarez",
    "qs:name_adm0":"M\u00e9xico",
    "qs:name_adm1":"Mexico",
    "qs:name_adm2":"Nezahualcoyotl",
    "qs:name_local":"Ciudad Netzahualc\u00f3yotl",
    "qs:photo_max":22,
    "qs:photo_sum":52,
    "qs:placetype":"Suburb",
    "qs:quad_count":15,
    "qs:woe_adm0":23424900,
    "qs:woe_adm1":2346278,
    "qs:woe_adm2":12600379,
    "qs:woe_lau":0,
    "qs:woe_local":116564,
    "qs:woe_ver":"7.10.0",
    "wof:lang":[
        "spa"
    ],
    "wof:name":"Benito Juarez",
    "wof:placetype":"neighbourhood"
},
  "geometry": {"coordinates":[-99.00551400000001,19.409911],"type":"Point"}
}