{
  "type": "Feature",
  "properties": {
    "gn:admin1_code":"28.0",
    "gn:admin2_code":"2.0",
    "gn:asciiname":"El Chijolito",
    "gn:country_code":"MX",
    "gn:dem":81,
    "gn:feature_class":"P",
    "gn:feature_code":"PPL",
    "gn:name":"El Chijolito",
    "gn:population":0,
    "gn:timezone":"America/Monterrey",
    "iso:country":"MX",
    "name:spa_x_preferred":[
        "El Chijolito"
    ],
    "wof:name":"El Chijolito",
    "wof:placetype":"locality"
},
  "geometry": {"coordinates":[-98.02943999999999,22.87972],"type":"Point"}
}