{
  "type": "Feature",
  "properties": {
    "gn:admin1_code":"12",
    "gn:admin2_code":"73",
    "gn:asciiname":"El Salitre",
    "gn:country_code":"MX",
    "gn:dem":819,
    "gn:feature_class":"P",
    "gn:feature_code":"PPL",
    "gn:name":"El Salitre",
    "gn:population":13,
    "gn:timezone":"America/Mexico_City",
    "iso:country":"MX",
    "wof:name":"El Salitre",
    "wof:placetype":"locality",
    "wof:population":13
},
  "geometry": {"coordinates":[-101.12249,18.18646],"type":"Point"}
}