{
  "type": "Feature",
  "properties": {
    "gn:admin1_code":"6.0",
    "gn:admin2_code":"54.0",
    "gn:asciiname":"Campo Sesenta y Cuatro A",
    "gn:country_code":"MX",
    "gn:dem":2169,
    "gn:feature_class":"P",
    "gn:feature_code":"PPL",
    "gn:name":"Campo Sesenta y Cuatro A",
    "gn:population":0,
    "gn:timezone":"America/Chihuahua",
    "iso:country":"MX",
    "name:und_x_variant":[
        "Campo Menonita N\u00famero 64 \u201dA\u201d",
        "Campo Sesenta y Cuatro A",
        "Campo 64 A"
    ],
    "wof:name":"Campo Sesenta y Cuatro A",
    "wof:placetype":"locality"
},
  "geometry": {"coordinates":[-106.70927,28.98178],"type":"Point"}
}