{
  "type": "Feature",
  "properties": {
    "gn:admin1_code":"21",
    "gn:admin2_code":"204.0",
    "gn:asciiname":"Teteltipan",
    "gn:country_code":"MX",
    "gn:dem":754,
    "gn:feature_class":"P",
    "gn:feature_code":"PPL",
    "gn:name":"Teteltipan",
    "gn:population":203,
    "gn:timezone":"America/Mexico_City",
    "iso:country":"MX",
    "wof:name":"Teteltipan",
    "wof:placetype":"locality",
    "wof:population":203
},
  "geometry": {"coordinates":[-97.42861000000001,19.95306],"type":"Point"}
}