{
  "type": "Feature",
  "properties": {
    "gn:admin1_code":"5",
    "gn:admin2_code":"17",
    "gn:asciiname":"El Cucurucho",
    "gn:country_code":"MX",
    "gn:dem":805,
    "gn:feature_class":"P",
    "gn:feature_code":"PPL",
    "gn:name":"El Cucurucho",
    "gn:population":12,
    "gn:timezone":"America/Mexico_City",
    "iso:country":"MX",
    "wof:name":"El Cucurucho",
    "wof:placetype":"locality",
    "wof:population":12
},
  "geometry": {"coordinates":[-93.72861,16.85639],"type":"Point"}
}