{
  "type": "Feature",
  "properties": {
    "gn:admin1_code":"27",
    "gn:admin2_code":"4.0",
    "gn:asciiname":"Aztlan 2da. Seccion (El Corcho)",
    "gn:country_code":"MX",
    "gn:dem":3,
    "gn:feature_class":"P",
    "gn:feature_code":"PPL",
    "gn:name":"Aztl\u00e1n 2da. Secci\u00f3n (El Corcho)",
    "gn:population":324,
    "gn:timezone":"America/Mexico_City",
    "iso:country":"MX",
    "name:und_x_variant":[
        "Aztl\u00e1n 2da. Secci\u00f3n (El Corcho)"
    ],
    "wof:name":"Aztlan 2da. Seccion (El Corcho)",
    "wof:placetype":"locality",
    "wof:population":324
},
  "geometry": {"coordinates":[-92.74639000000001,18.09472],"type":"Point"}
}