{
  "type": "Feature",
  "properties": {
    "gn:admin1_code":"14.0",
    "gn:admin2_code":"38.0",
    "gn:asciiname":"Sauces de Arriba",
    "gn:country_code":"MX",
    "gn:dem":1516,
    "gn:feature_class":"P",
    "gn:feature_code":"PPL",
    "gn:name":"Sauces de Arriba",
    "gn:population":0,
    "gn:timezone":"America/Mexico_City",
    "iso:country":"MX",
    "name:spa_x_preferred":[
        "Sauces de Arriba"
    ],
    "wof:name":"Sauces de Arriba",
    "wof:placetype":"locality"
},
  "geometry": {"coordinates":[-104.37147,20.65844],"type":"Point"}
}