{
  "type": "Feature",
  "properties": {
    "gn:admin1_code":"14.0",
    "gn:admin2_code":"38.0",
    "gn:asciiname":"Rancho Escondido",
    "gn:country_code":"MX",
    "gn:dem":1511,
    "gn:feature_class":"P",
    "gn:feature_code":"PPL",
    "gn:name":"Rancho Escondido",
    "gn:population":0,
    "gn:timezone":"America/Mexico_City",
    "iso:country":"MX",
    "name:spa_x_preferred":[
        "Rancho Escondido"
    ],
    "wof:name":"Rancho Escondido",
    "wof:placetype":"locality"
},
  "geometry": {"coordinates":[-104.36645,20.6474],"type":"Point"}
}