{
  "type": "Feature",
  "properties": {
    "gn:admin1_code":"26",
    "gn:admin2_code":"72.0",
    "gn:asciiname":"Los Huitivos",
    "gn:country_code":"MX",
    "gn:dem":3,
    "gn:feature_class":"P",
    "gn:feature_code":"PPL",
    "gn:name":"Los Hu\u00edtivos",
    "gn:population":0,
    "gn:timezone":"America/Hermosillo",
    "iso:country":"MX",
    "name:spa_x_preferred":[
        "Los Hu\u00edtivos"
    ],
    "wof:name":"Los Huitivos",
    "wof:placetype":"locality"
},
  "geometry": {"coordinates":[-110.30629999999999,27.22701],"type":"Point"}
}