{
  "type": "Feature",
  "properties": {
    "gn:admin1_code":"28.0",
    "gn:admin2_code":"42.0",
    "gn:asciiname":"Duenas",
    "gn:country_code":"MX",
    "gn:dem":474,
    "gn:feature_class":"P",
    "gn:feature_code":"PPL",
    "gn:name":"Due\u00f1as",
    "gn:population":9,
    "gn:timezone":"America/Monterrey",
    "iso:country":"MX",
    "name:spa_x_preferred":[
        "Due\u00f1as"
    ],
    "wof:name":"Duenas",
    "wof:placetype":"locality",
    "wof:population":9
},
  "geometry": {"coordinates":[-99.54555999999999,24.44833],"type":"Point"}
}