{
  "type": "Feature",
  "properties": {
    "gn:admin1_code":"3",
    "gn:admin2_code":"3",
    "gn:asciiname":"Ninguno [Almacen y Molino Forrajero]",
    "gn:country_code":"MX",
    "gn:dem":98,
    "gn:feature_class":"P",
    "gn:feature_code":"PPL",
    "gn:name":"Ninguno [Almac\u00e9n y Molino Forrajero]",
    "gn:population":9,
    "gn:timezone":"America/Mazatlan",
    "iso:country":"MX",
    "name:und_x_variant":[
        "Ninguno [Almac\u00e9n y Molino Forrajero]"
    ],
    "wof:name":"Ninguno [Almacen y Molino Forrajero]",
    "wof:placetype":"locality",
    "wof:population":9
},
  "geometry": {"coordinates":[-110.20842,23.48393],"type":"Point"}
}