{
  "type": "Feature",
  "properties": {
    "gn:admin1_code":"22.0",
    "gn:admin2_code":"1.0",
    "gn:asciiname":"El Batan",
    "gn:country_code":"MX",
    "gn:dem":2304,
    "gn:feature_class":"P",
    "gn:feature_code":"PPL",
    "gn:name":"El Bat\u00e1n",
    "gn:population":0,
    "gn:timezone":"America/Mexico_City",
    "iso:country":"MX",
    "name:spa_x_preferred":[
        "El Bat\u00e1n"
    ],
    "wof:name":"El Batan",
    "wof:placetype":"locality"
},
  "geometry": {"coordinates":[-100.18183999999999,20.3008],"type":"Point"}
}