{
  "type": "Feature",
  "properties": {
    "gn:admin1_code":"10",
    "gn:admin2_code":"7.0",
    "gn:asciiname":"El Garbanzo",
    "gn:country_code":"MX",
    "gn:dem":1117,
    "gn:feature_class":"P",
    "gn:feature_code":"PPL",
    "gn:name":"El Garbanzo",
    "gn:population":0,
    "gn:timezone":"America/Monterrey",
    "iso:country":"MX",
    "name:spa_x_preferred":[
        "El Garbanzo"
    ],
    "wof:name":"El Garbanzo",
    "wof:placetype":"locality"
},
  "geometry": {"coordinates":[-103.45672999999999,25.70043],"type":"Point"}
}