{
  "type": "Feature",
  "properties": {
    "gn:admin1_code":"6",
    "gn:admin2_code":"7.0",
    "gn:asciiname":"La Cebolla",
    "gn:country_code":"MX",
    "gn:dem":2549,
    "gn:feature_class":"P",
    "gn:feature_code":"PPL",
    "gn:name":"La Cebolla",
    "gn:population":164,
    "gn:timezone":"America/Chihuahua",
    "iso:country":"MX",
    "wof:name":"La Cebolla",
    "wof:placetype":"locality",
    "wof:population":164
},
  "geometry": {"coordinates":[-106.47056000000001,26.51528],"type":"Point"}
}