{
  "type": "Feature",
  "properties": {
    "gn:admin1_code":"5.0",
    "gn:admin2_code":"37.0",
    "gn:asciiname":"Estacion Huehuetan",
    "gn:country_code":"MX",
    "gn:dem":30,
    "gn:feature_class":"P",
    "gn:feature_code":"PPL",
    "gn:name":"Estaci\u00f3n Huehuet\u00e1n",
    "gn:population":0,
    "gn:timezone":"America/Mexico_City",
    "iso:country":"MX",
    "name:spa_x_preferred":[
        "Estaci\u00f3n Huehuet\u00e1n"
    ],
    "wof:name":"Estacion Huehuetan",
    "wof:placetype":"locality"
},
  "geometry": {"coordinates":[-92.40662,15.01091],"type":"Point"}
}