{
  "type": "Feature",
  "properties": {
    "gn:admin1_code":"15.0",
    "gn:admin2_code":"124.0",
    "gn:asciiname":"Santa Cruz del Tejocote",
    "gn:country_code":"MX",
    "gn:dem":2866,
    "gn:feature_class":"P",
    "gn:feature_code":"PPL",
    "gn:name":"Santa Cruz del Tejocote",
    "gn:population":0,
    "gn:timezone":"America/Mexico_City",
    "iso:country":"MX",
    "name:spa_x_preferred":[
        "Santa Cruz del Tejocote"
    ],
    "name:und_x_variant":[
        "Santa Cruz Tejocote"
    ],
    "wof:name":"Santa Cruz del Tejocote",
    "wof:placetype":"locality"
},
  "geometry": {"coordinates":[-100.17144999999999,19.68308],"type":"Point"}
}