{
  "type": "Feature",
  "properties": {
    "gn:admin1_code":"26.0",
    "gn:admin2_code":"14.0",
    "gn:asciiname":"Coruco",
    "gn:country_code":"MX",
    "gn:dem":579,
    "gn:feature_class":"P",
    "gn:feature_code":"PPL",
    "gn:name":"Coruco",
    "gn:population":0,
    "gn:timezone":"America/Hermosillo",
    "iso:country":"MX",
    "wof:name":"Coruco",
    "wof:placetype":"locality"
},
  "geometry": {"coordinates":[-110.11667,29.61667000000001],"type":"Point"}
}