{
  "type": "Feature",
  "properties": {
    "gn:admin1_code":"14",
    "gn:admin2_code":"27.0",
    "gn:asciiname":"Rincon de Almoloya",
    "gn:cc2":"MX",
    "gn:country_code":"MX",
    "gn:dem":1078,
    "gn:feature_class":"P",
    "gn:feature_code":"PPL",
    "gn:name":"Rinc\u00f3n de Almoloya",
    "gn:population":0,
    "gn:timezone":"America/Mexico_City",
    "iso:country":"MX",
    "name:und_x_variant":[
        "Rinc\u00f3n de Almoloyan",
        "Rinc\u00f3n de Almoloya"
    ],
    "wof:name":"Rincon de Almoloya",
    "wof:placetype":"locality"
},
  "geometry": {"coordinates":[-104.38333,19.33333],"type":"Point"}
}