{
  "type": "Feature",
  "properties": {
    "gn:admin1_code":"30",
    "gn:admin2_code":"94.0",
    "gn:asciiname":"Vicente Guerrero",
    "gn:country_code":"MX",
    "gn:dem":97,
    "gn:feature_class":"P",
    "gn:feature_code":"PPL",
    "gn:name":"Vicente Guerrero",
    "gn:population":134,
    "gn:timezone":"America/Mexico_City",
    "iso:country":"MX",
    "wof:name":"Vicente Guerrero",
    "wof:placetype":"locality",
    "wof:population":134
},
  "geometry": {"coordinates":[-95.31528,18.02278],"type":"Point"}
}