{
  "type": "Feature",
  "properties": {
    "gn:admin1_code":"24",
    "gn:admin2_code":"12.0",
    "gn:asciiname":"Tlajcutepec",
    "gn:country_code":"MX",
    "gn:dem":435,
    "gn:feature_class":"P",
    "gn:feature_code":"PPL",
    "gn:name":"Tlajcutepec",
    "gn:population":56,
    "gn:timezone":"America/Mexico_City",
    "iso:country":"MX",
    "wof:name":"Tlajcutepec",
    "wof:placetype":"locality",
    "wof:population":56
},
  "geometry": {"coordinates":[-98.92528,21.57278],"type":"Point"}
}