{
  "type": "Feature",
  "properties": {
    "gn:admin1_code":"10",
    "gn:admin2_code":"34",
    "gn:asciiname":"La Mesa Pinosa",
    "gn:country_code":"MX",
    "gn:dem":1082,
    "gn:feature_class":"P",
    "gn:feature_code":"PPL",
    "gn:name":"La Mesa Pinosa",
    "gn:population":24,
    "gn:timezone":"America/Monterrey",
    "iso:country":"MX",
    "wof:name":"La Mesa Pinosa",
    "wof:placetype":"locality",
    "wof:population":24
},
  "geometry": {"coordinates":[-107.09482,25.1558],"type":"Point"}
}