{
  "type": "Feature",
  "properties": {
    "gn:admin1_code":"5",
    "gn:admin2_code":"103.0",
    "gn:asciiname":"San Lucas Manacal",
    "gn:country_code":"MX",
    "gn:dem":610,
    "gn:feature_class":"P",
    "gn:feature_code":"PPL",
    "gn:name":"San Lucas Manacal",
    "gn:population":100,
    "gn:timezone":"America/Mexico_City",
    "iso:country":"MX",
    "wof:name":"San Lucas Manacal",
    "wof:placetype":"locality",
    "wof:population":100
},
  "geometry": {"coordinates":[-92.40056,15.22306],"type":"Point"}
}