{
  "type": "Feature",
  "properties": {
    "gn:admin1_code":"12",
    "gn:admin2_code":"25",
    "gn:asciiname":"Zacatecomate (El Puerto)",
    "gn:country_code":"MX",
    "gn:dem":125,
    "gn:feature_class":"P",
    "gn:feature_code":"PPL",
    "gn:name":"Zacatecomate (El Puerto)",
    "gn:population":18,
    "gn:timezone":"America/Mexico_City",
    "iso:country":"MX",
    "wof:name":"Zacatecomate (El Puerto)",
    "wof:placetype":"locality",
    "wof:population":18
},
  "geometry": {"coordinates":[-98.95135999999999,16.66473],"type":"Point"}
}