{
  "type": "Feature",
  "properties": {
    "gn:admin1_code":"5.0",
    "gn:asciiname":"Parcelas de Manacal",
    "gn:country_code":"MX",
    "gn:dem":744,
    "gn:feature_class":"P",
    "gn:feature_code":"PPL",
    "gn:name":"Parcelas de Manacal",
    "gn:population":0,
    "gn:timezone":"America/Mexico_City",
    "iso:country":"MX",
    "name:spa_x_preferred":[
        "Parcelas de Manacal"
    ],
    "wof:name":"Parcelas de Manacal",
    "wof:placetype":"locality"
},
  "geometry": {"coordinates":[-92.21031000000001,15.10252],"type":"Point"}
}