{
  "type": "Feature",
  "properties": {
    "gn:admin1_code":"20",
    "gn:admin2_code":"229.0",
    "gn:asciiname":"El Raton",
    "gn:country_code":"MX",
    "gn:dem":1400,
    "gn:feature_class":"P",
    "gn:feature_code":"PPL",
    "gn:name":"El Rat\u00f3n",
    "gn:population":9,
    "gn:timezone":"America/Mexico_City",
    "iso:country":"MX",
    "name:und_x_variant":[
        "El Rat\u00f3n"
    ],
    "wof:name":"El Raton",
    "wof:placetype":"locality",
    "wof:population":9
},
  "geometry": {"coordinates":[-97.19444,16.56194],"type":"Point"}
}