{
  "type": "Feature",
  "properties": {
    "gn:admin1_code":"6",
    "gn:admin2_code":"65",
    "gn:asciiname":"Los Potreros",
    "gn:country_code":"MX",
    "gn:dem":1043,
    "gn:feature_class":"P",
    "gn:feature_code":"PPL",
    "gn:name":"Los Potreros",
    "gn:population":21,
    "gn:timezone":"America/Chihuahua",
    "iso:country":"MX",
    "wof:name":"Los Potreros",
    "wof:placetype":"locality",
    "wof:population":21
},
  "geometry": {"coordinates":[-107.89908,27.13909],"type":"Point"}
}