{
  "type": "Feature",
  "properties": {
    "gn:admin1_code":"4",
    "gn:admin2_code":"3.0",
    "gn:asciiname":"Hawai",
    "gn:country_code":"MX",
    "gn:dem":3,
    "gn:feature_class":"P",
    "gn:feature_code":"PPL",
    "gn:name":"Hawai",
    "gn:population":4,
    "gn:timezone":"America/Merida",
    "iso:country":"MX",
    "name:bar_x_preferred":[
        "Hawai"
    ],
    "name:deu_x_preferred":[
        "Hawai"
    ],
    "name:glg_x_preferred":[
        "Hawai"
    ],
    "wof:name":"Hawai",
    "wof:placetype":"locality",
    "wof:population":4
},
  "geometry": {"coordinates":[-91.80249999999999,18.19639],"type":"Point"}
}