{
  "type": "Feature",
  "properties": {
    "gn:admin1_code":"26",
    "gn:admin2_code":"55.0",
    "gn:asciiname":"Consuelo Cruz",
    "gn:country_code":"MX",
    "gn:dem":15,
    "gn:feature_class":"P",
    "gn:feature_code":"PPL",
    "gn:name":"Consuelo Cruz",
    "gn:population":5,
    "gn:timezone":"America/Hermosillo",
    "iso:country":"MX",
    "wof:name":"Consuelo Cruz",
    "wof:placetype":"locality",
    "wof:population":5
},
  "geometry": {"coordinates":[-114.92889,32.26],"type":"Point"}
}