{
  "type": "Feature",
  "properties": {
    "gn:admin1_code":"7.0",
    "gn:admin2_code":"26.0",
    "gn:asciiname":"Casa Vieja",
    "gn:country_code":"MX",
    "gn:dem":460,
    "gn:feature_class":"P",
    "gn:feature_code":"PPL",
    "gn:name":"Casa Vieja",
    "gn:population":0,
    "gn:timezone":"America/Monterrey",
    "iso:country":"MX",
    "wof:name":"Casa Vieja",
    "wof:placetype":"locality"
},
  "geometry": {"coordinates":[-101.36667,27.63333],"type":"Point"}
}