{
  "type": "Feature",
  "properties": {
    "gn:admin1_code":"6",
    "gn:admin2_code":"66",
    "gn:asciiname":"Las Calabazas",
    "gn:country_code":"MX",
    "gn:dem":876,
    "gn:feature_class":"P",
    "gn:feature_code":"PPL",
    "gn:name":"Las Calabazas",
    "gn:population":13,
    "gn:timezone":"America/Chihuahua",
    "iso:country":"MX",
    "wof:name":"Las Calabazas",
    "wof:placetype":"locality",
    "wof:population":13
},
  "geometry": {"coordinates":[-108.73743,27.98533],"type":"Point"}
}