{
  "type": "Feature",
  "properties": {
    "gn:admin1_code":"4.0",
    "gn:asciiname":"El Cocoyol",
    "gn:country_code":"MX",
    "gn:dem":9,
    "gn:feature_class":"P",
    "gn:feature_code":"PPL",
    "gn:name":"El Cocoyol",
    "gn:population":0,
    "gn:timezone":"America/Mexico_City",
    "iso:country":"MX",
    "name:spa_x_preferred":[
        "El Cocoyol"
    ],
    "wof:name":"El Cocoyol",
    "wof:placetype":"locality"
},
  "geometry": {"coordinates":[-91.67746,17.93994],"type":"Point"}
}