{
  "type": "Feature",
  "properties": {
    "gn:admin1_code":"10",
    "gn:admin2_code":"18.0",
    "gn:asciiname":"Las Playas",
    "gn:country_code":"MX",
    "gn:dem":1881,
    "gn:feature_class":"P",
    "gn:feature_code":"PPL",
    "gn:name":"Las Playas",
    "gn:population":0,
    "gn:timezone":"America/Monterrey",
    "iso:country":"MX",
    "name:spa_x_preferred":[
        "Las Playas"
    ],
    "wof:name":"Las Playas",
    "wof:placetype":"locality"
},
  "geometry": {"coordinates":[-105.08101000000001,25.3137],"type":"Point"}
}