{
  "type": "Feature",
  "properties": {
    "gn:admin1_code":"15",
    "gn:admin2_code":"19.0",
    "gn:asciiname":"Agua Blanca",
    "gn:country_code":"MX",
    "gn:dem":2575,
    "gn:feature_class":"P",
    "gn:feature_code":"PPL",
    "gn:name":"Agua Blanca",
    "gn:population":1092,
    "gn:timezone":"America/Mexico_City",
    "iso:country":"MX",
    "name:bre_x_preferred":[
        "Agua Blanca"
    ],
    "name:ceb_x_preferred":[
        "Agua Blanca"
    ],
    "name:deu_x_preferred":[
        "Agua Blanca"
    ],
    "name:fra_x_preferred":[
        "Agua Blanca"
    ],
    "name:nld_x_preferred":[
        "Agua Blanca"
    ],
    "name:por_x_preferred":[
        "Agua Blanca"
    ],
    "name:sco_x_preferred":[
        "Agua Blanca"
    ],
    "name:spa_x_preferred":[
        "Agua Blanca"
    ],
    "name:swe_x_preferred":[
        "Agua Blanca"
    ],
    "wof:name":"Agua Blanca",
    "wof:placetype":"locality",
    "wof:population":1092
},
  "geometry": {"coordinates":[-99.47056000000001,19.22056],"type":"Point"}
}