{
  "type": "Feature",
  "properties": {
    "gn:admin1_code":"6",
    "gn:admin2_code":"47.0",
    "gn:asciiname":"Aripillachi",
    "gn:country_code":"MX",
    "gn:dem":579,
    "gn:feature_class":"P",
    "gn:feature_code":"PPL",
    "gn:name":"Aripillachi",
    "gn:population":2,
    "gn:timezone":"America/Chihuahua",
    "iso:country":"MX",
    "wof:name":"Aripillachi",
    "wof:placetype":"locality",
    "wof:population":2
},
  "geometry": {"coordinates":[-108.5194,28.03102],"type":"Point"}
}