{
  "type": "Feature",
  "properties": {
    "gn:admin1_code":"12",
    "gn:admin2_code":"57",
    "gn:asciiname":"Humedad",
    "gn:country_code":"MX",
    "gn:dem":361,
    "gn:feature_class":"P",
    "gn:feature_code":"PPL",
    "gn:name":"Humedad",
    "gn:population":34,
    "gn:timezone":"America/Mexico_City",
    "iso:country":"MX",
    "wof:name":"Humedad",
    "wof:placetype":"locality",
    "wof:population":34
},
  "geometry": {"coordinates":[-100.79789,17.38607],"type":"Point"}
}