{
  "type": "Feature",
  "properties": {
    "gn:admin1_code":"13",
    "gn:admin2_code":"62.0",
    "gn:asciiname":"La Fabrica Vieja",
    "gn:country_code":"MX",
    "gn:dem":341,
    "gn:feature_class":"P",
    "gn:feature_code":"PPL",
    "gn:name":"La F\u00e1brica Vieja",
    "gn:population":0,
    "gn:timezone":"America/Mexico_City",
    "iso:country":"MX",
    "name:spa_x_preferred":[
        "La F\u00e1brica Vieja"
    ],
    "name:spa_x_variant":[
        "\u00c1lamo"
    ],
    "wof:name":"La Fabrica Vieja",
    "wof:placetype":"locality"
},
  "geometry": {"coordinates":[-98.87662,21.08387],"type":"Point"}
}