{
  "type": "Feature",
  "properties": {
    "gn:admin1_code":"13",
    "gn:admin2_code":"63.0",
    "gn:asciiname":"Xaisnal",
    "gn:country_code":"MX",
    "gn:dem":2226,
    "gn:feature_class":"P",
    "gn:feature_code":"PPL",
    "gn:name":"Xaisnal",
    "gn:population":8,
    "gn:timezone":"America/Mexico_City",
    "iso:country":"MX",
    "wof:name":"Xaisnal",
    "wof:placetype":"locality",
    "wof:population":8
},
  "geometry": {"coordinates":[-99.37389,19.92333],"type":"Point"}
}