{
  "type": "Feature",
  "properties": {
    "gn:admin1_code":"25",
    "gn:admin2_code":"7.0",
    "gn:asciiname":"El Tepehuaje (Caballihuaza)",
    "gn:country_code":"MX",
    "gn:dem":164,
    "gn:feature_class":"P",
    "gn:feature_code":"PPL",
    "gn:name":"El Tepehuaje (Caballihuaza)",
    "gn:population":75,
    "gn:timezone":"America/Mazatlan",
    "iso:country":"MX",
    "wof:name":"El Tepehuaje (Caballihuaza)",
    "wof:placetype":"locality",
    "wof:population":75
},
  "geometry": {"coordinates":[-108.56471999999999,26.71333],"type":"Point"}
}