{
  "type": "Feature",
  "properties": {
    "gn:admin1_code":"26",
    "gn:admin2_code":"3.0",
    "gn:asciiname":"21 de Marzo Uno",
    "gn:country_code":"MX",
    "gn:dem":72,
    "gn:feature_class":"P",
    "gn:feature_code":"PPL",
    "gn:name":"21 de Marzo Uno",
    "gn:population":5,
    "gn:timezone":"America/Hermosillo",
    "iso:country":"MX",
    "wof:name":"21 de Marzo Uno",
    "wof:placetype":"locality",
    "wof:population":5
},
  "geometry": {"coordinates":[-109.05249999999999,26.49972],"type":"Point"}
}