{
  "type": "Feature",
  "properties": {
    "gn:admin1_code":"28.0",
    "gn:admin2_code":"27.0",
    "gn:asciiname":"Los Santos",
    "gn:country_code":"MX",
    "gn:dem":145,
    "gn:feature_class":"P",
    "gn:feature_code":"PPL",
    "gn:name":"Los Santos",
    "gn:population":0,
    "gn:timezone":"America/Matamoros",
    "iso:country":"MX",
    "name:spa_x_preferred":[
        "Los Santos"
    ],
    "wof:name":"Los Santos",
    "wof:placetype":"locality"
},
  "geometry": {"coordinates":[-99.63697000000001,27.48485],"type":"Point"}
}