{
  "type": "Feature",
  "properties": {
    "gn:admin1_code":"32",
    "gn:admin2_code":"54.0",
    "gn:asciiname":"Purisima del Rucio (El Rucio)",
    "gn:country_code":"MX",
    "gn:dem":2116,
    "gn:feature_class":"P",
    "gn:feature_code":"PPL",
    "gn:name":"Pur\u00edsima del Rucio (El Rucio)",
    "gn:population":470,
    "gn:timezone":"America/Mexico_City",
    "iso:country":"MX",
    "name:und_x_variant":[
        "Pur\u00edsima del Rucio (El Rucio)"
    ],
    "wof:name":"Purisima del Rucio (El Rucio)",
    "wof:placetype":"locality",
    "wof:population":470
},
  "geometry": {"coordinates":[-101.78778,22.43278],"type":"Point"}
}