{
  "type": "Feature",
  "properties": {
    "gn:admin1_code":"16.0",
    "gn:asciiname":"Puerta de Barajas",
    "gn:country_code":"MX",
    "gn:dem":1524,
    "gn:feature_class":"P",
    "gn:feature_code":"PPL",
    "gn:name":"Puerta de Barajas",
    "gn:population":0,
    "gn:timezone":"America/Mexico_City",
    "iso:country":"MX",
    "name:spa_x_preferred":[
        "Puerta de Barajas"
    ],
    "name:spa_x_variant":[
        "La Puerta de Barajas"
    ],
    "wof:name":"Puerta de Barajas",
    "wof:placetype":"locality"
},
  "geometry": {"coordinates":[-102.59093,20.23354],"type":"Point"}
}