{
  "type": "Feature",
  "properties": {
    "gn:admin1_code":"4.0",
    "gn:admin2_code":"3.0",
    "gn:asciiname":"La Chiquis",
    "gn:country_code":"MX",
    "gn:dem":13,
    "gn:feature_class":"P",
    "gn:feature_code":"PPL",
    "gn:name":"La Chiquis",
    "gn:population":0,
    "gn:timezone":"America/Merida",
    "iso:country":"MX",
    "name:spa_x_preferred":[
        "La Chiquis"
    ],
    "wof:name":"La Chiquis",
    "wof:placetype":"locality"
},
  "geometry": {"coordinates":[-91.11118999999999,18.4975],"type":"Point"}
}