{
  "type": "Feature",
  "properties": {
    "gn:admin1_code":"16.0",
    "gn:admin2_code":"16.0",
    "gn:asciiname":"Cortijo Viejo",
    "gn:country_code":"MX",
    "gn:dem":1997,
    "gn:feature_class":"P",
    "gn:feature_code":"PPL",
    "gn:name":"Cortijo Viejo",
    "gn:population":0,
    "gn:timezone":"America/Mexico_City",
    "iso:country":"MX",
    "name:spa_x_preferred":[
        "Cortijo Viejo"
    ],
    "wof:name":"Cortijo Viejo",
    "wof:placetype":"locality"
},
  "geometry": {"coordinates":[-101.69347,19.79875],"type":"Point"}
}