{
  "type": "Feature",
  "properties": {
    "gn:admin1_code":"11",
    "gn:admin2_code":"11.0",
    "gn:asciiname":"Los Pioneros [Invernadero Casa Verde]",
    "gn:country_code":"MX",
    "gn:dem":1742,
    "gn:feature_class":"P",
    "gn:feature_code":"PPL",
    "gn:name":"Los Pioneros [Invernadero Casa Verde]",
    "gn:population":8,
    "gn:timezone":"America/Mexico_City",
    "iso:country":"MX",
    "wof:name":"Los Pioneros [Invernadero Casa Verde]",
    "wof:placetype":"locality",
    "wof:population":8
},
  "geometry": {"coordinates":[-100.92083,20.505],"type":"Point"}
}