{
  "type": "Feature",
  "properties": {
    "gn:admin1_code":"20",
    "gn:admin2_code":"453.0",
    "gn:asciiname":"La Colorada",
    "gn:country_code":"MX",
    "gn:dem":10,
    "gn:feature_class":"P",
    "gn:feature_code":"PPL",
    "gn:name":"La Colorada",
    "gn:population":0,
    "gn:timezone":"America/Mexico_City",
    "iso:country":"MX",
    "name:spa_x_preferred":[
        "La Colorada"
    ],
    "wof:name":"La Colorada",
    "wof:placetype":"locality"
},
  "geometry": {"coordinates":[-95.58031,15.95166],"type":"Point"}
}