{
  "type": "Feature",
  "properties": {
    "gn:admin1_code":"26.0",
    "gn:admin2_code":"69.0",
    "gn:asciiname":"El Tumiqui",
    "gn:country_code":"MX",
    "gn:dem":1491,
    "gn:feature_class":"P",
    "gn:feature_code":"PPL",
    "gn:name":"El Tumiqui",
    "gn:population":0,
    "gn:timezone":"America/Hermosillo",
    "iso:country":"MX",
    "name:spa_x_preferred":[
        "El Tumiqui"
    ],
    "wof:name":"El Tumiqui",
    "wof:placetype":"locality"
},
  "geometry": {"coordinates":[-108.85205999999999,28.41892],"type":"Point"}
}