{
  "type": "Feature",
  "properties": {
    "gn:admin1_code":"11",
    "gn:admin2_code":"27",
    "gn:asciiname":"Santa Cecilia (Familia Lozano Vargas)",
    "gn:country_code":"MX",
    "gn:dem":1717,
    "gn:feature_class":"P",
    "gn:feature_code":"PPL",
    "gn:name":"Santa Cecilia (Familia Lozano Vargas)",
    "gn:population":9,
    "gn:timezone":"America/Mexico_City",
    "iso:country":"MX",
    "wof:name":"Santa Cecilia (Familia Lozano Vargas)",
    "wof:placetype":"locality",
    "wof:population":9
},
  "geometry": {"coordinates":[-101.26528,20.56167],"type":"Point"}
}