{
  "type": "Feature",
  "properties": {
    "gn:admin1_code":"16",
    "gn:admin2_code":"4.0",
    "gn:asciiname":"Guadalupe Sur",
    "gn:country_code":"MX",
    "gn:dem":1746,
    "gn:feature_class":"P",
    "gn:feature_code":"PPL",
    "gn:name":"Guadalupe Sur",
    "gn:population":177,
    "gn:timezone":"America/Mexico_City",
    "iso:country":"MX",
    "wof:name":"Guadalupe Sur",
    "wof:placetype":"locality",
    "wof:population":177
},
  "geometry": {"coordinates":[-101.78583,20.11],"type":"Point"}
}