{
  "type": "Feature",
  "properties": {
    "gn:admin1_code":"6",
    "gn:admin2_code":"65.0",
    "gn:asciiname":"Mahiochic",
    "gn:country_code":"MX",
    "gn:dem":1883,
    "gn:feature_class":"P",
    "gn:feature_code":"PPL",
    "gn:name":"Mahiochic",
    "gn:population":0,
    "gn:timezone":"America/Chihuahua",
    "iso:country":"MX",
    "name:spa_x_preferred":[
        "Mahiochic"
    ],
    "wof:name":"Mahiochic",
    "wof:placetype":"locality"
},
  "geometry": {"coordinates":[-108.08401000000001,27.45787],"type":"Point"}
}