{
  "type": "Feature",
  "properties": {
    "gn:admin1_code":"13",
    "gn:admin2_code":"1.0",
    "gn:asciiname":"Veintiocho de Mayo",
    "gn:country_code":"MX",
    "gn:dem":2134,
    "gn:feature_class":"P",
    "gn:feature_code":"PPL",
    "gn:name":"Veintiocho de Mayo",
    "gn:population":0,
    "gn:timezone":"America/Mexico_City",
    "iso:country":"MX",
    "name:spa_x_preferred":[
        "Veintiocho de Mayo"
    ],
    "name:spa_x_variant":[
        "Santa Rosa"
    ],
    "wof:name":"Veintiocho de Mayo",
    "wof:placetype":"locality"
},
  "geometry": {"coordinates":[-98.38804,20.17074],"type":"Point"}
}