{
  "type": "Feature",
  "properties": {
    "gn:admin1_code":"7",
    "gn:admin2_code":"11.0",
    "gn:asciiname":"El Corralero",
    "gn:country_code":"MX",
    "gn:dem":1396,
    "gn:feature_class":"P",
    "gn:feature_code":"PPL",
    "gn:name":"El Corralero",
    "gn:population":8,
    "gn:timezone":"America/Monterrey",
    "iso:country":"MX",
    "wof:name":"El Corralero",
    "wof:placetype":"locality",
    "wof:population":8
},
  "geometry": {"coordinates":[-101.55455000000001,25.43263],"type":"Point"}
}