{
  "type": "Feature",
  "properties": {
    "gn:admin1_code":"5",
    "gn:admin2_code":"59.0",
    "gn:asciiname":"Miguel Hidalgo y Costilla",
    "gn:country_code":"MX",
    "gn:dem":213,
    "gn:feature_class":"P",
    "gn:feature_code":"PPL",
    "gn:name":"Miguel Hidalgo y Costilla",
    "gn:population":0,
    "gn:timezone":"America/Mexico_City",
    "iso:country":"MX",
    "name:rus_x_preferred":[
        "\u0418\u0434\u0430\u043b\u044c\u0433\u043e"
    ],
    "name:und_x_variant":[
        "Hidalgo"
    ],
    "wof:name":"Miguel Hidalgo y Costilla",
    "wof:placetype":"locality"
},
  "geometry": {"coordinates":[-91.29422,16.32215],"type":"Point"}
}