{
  "type": "Feature",
  "properties": {
    "gn:admin1_code":"14",
    "gn:admin2_code":"1",
    "gn:asciiname":"El Ranero",
    "gn:country_code":"MX",
    "gn:dem":1711,
    "gn:feature_class":"P",
    "gn:feature_code":"PPL",
    "gn:name":"El Ranero",
    "gn:population":27,
    "gn:timezone":"America/Mexico_City",
    "iso:country":"MX",
    "wof:name":"El Ranero",
    "wof:placetype":"locality",
    "wof:population":27
},
  "geometry": {"coordinates":[-102.90194,20.80056],"type":"Point"}
}