{
  "type": "Feature",
  "properties": {
    "gn:admin1_code":"16",
    "gn:admin2_code":"92.0",
    "gn:asciiname":"La Torrecilla",
    "gn:country_code":"MX",
    "gn:dem":1095,
    "gn:feature_class":"P",
    "gn:feature_code":"PPL",
    "gn:name":"La Torrecilla",
    "gn:population":72,
    "gn:timezone":"America/Mexico_City",
    "iso:country":"MX",
    "wof:name":"La Torrecilla",
    "wof:placetype":"locality",
    "wof:population":72
},
  "geometry": {"coordinates":[-101.01389,19.15861],"type":"Point"}
}