{
  "type": "Feature",
  "properties": {
    "gn:admin1_code":"27",
    "gn:admin2_code":"8.0",
    "gn:asciiname":"Francisco Martinez Gaytan",
    "gn:country_code":"MX",
    "gn:dem":33,
    "gn:feature_class":"P",
    "gn:feature_code":"PPL",
    "gn:name":"Francisco Mart\u00ednez Gayt\u00e1n",
    "gn:population":777,
    "gn:timezone":"America/Mexico_City",
    "iso:country":"MX",
    "name:spa_x_preferred":[
        "Francisco Mart\u00ednez Gayt\u00e1n"
    ],
    "wof:name":"Francisco Martinez Gaytan",
    "wof:placetype":"locality",
    "wof:population":777
},
  "geometry": {"coordinates":[-93.8125,17.76972],"type":"Point"}
}