{
  "type": "Feature",
  "properties": {
    "gn:admin1_code":"10",
    "gn:admin2_code":"23.0",
    "gn:asciiname":"La Crucita",
    "gn:country_code":"MX",
    "gn:dem":1954,
    "gn:feature_class":"P",
    "gn:feature_code":"PPL",
    "gn:name":"La Crucita",
    "gn:population":0,
    "gn:timezone":"America/Monterrey",
    "iso:country":"MX",
    "name:spa_x_preferred":[
        "La Crucita"
    ],
    "wof:name":"La Crucita",
    "wof:placetype":"locality"
},
  "geometry": {"coordinates":[-105.42618,23.29421],"type":"Point"}
}