{
  "type": "Feature",
  "properties": {
    "gn:admin1_code":"30.0",
    "gn:admin2_code":"121.0",
    "gn:asciiname":"Frambollan",
    "gn:country_code":"MX",
    "gn:dem":48,
    "gn:feature_class":"P",
    "gn:feature_code":"PPL",
    "gn:name":"Framboll\u00e1n",
    "gn:population":0,
    "gn:timezone":"America/Mexico_City",
    "iso:country":"MX",
    "name:spa_x_preferred":[
        "Framboll\u00e1n"
    ],
    "wof:name":"Frambollan",
    "wof:placetype":"locality"
},
  "geometry": {"coordinates":[-97.89454000000001,21.49924],"type":"Point"}
}