{
  "type": "Feature",
  "properties": {
    "gn:admin1_code":"19.0",
    "gn:admin2_code":"11.0",
    "gn:asciiname":"Los Vela",
    "gn:country_code":"MX",
    "gn:dem":298,
    "gn:feature_class":"P",
    "gn:feature_code":"PPL",
    "gn:name":"Los Vela",
    "gn:population":0,
    "gn:timezone":"America/Monterrey",
    "iso:country":"MX",
    "name:spa_x_preferred":[
        "Los Vela"
    ],
    "wof:name":"Los Vela",
    "wof:placetype":"locality"
},
  "geometry": {"coordinates":[-99.64324999999999,26.14945],"type":"Point"}
}