{
  "type": "Feature",
  "properties": {
    "gn:admin1_code":"14",
    "gn:admin2_code":"33.0",
    "gn:asciiname":"La Sabinilla (Sabinillas)",
    "gn:country_code":"MX",
    "gn:dem":1755,
    "gn:feature_class":"P",
    "gn:feature_code":"PPL",
    "gn:name":"La Sabinilla (Sabinillas)",
    "gn:population":83,
    "gn:timezone":"America/Mexico_City",
    "iso:country":"MX",
    "wof:name":"La Sabinilla (Sabinillas)",
    "wof:placetype":"locality",
    "wof:population":83
},
  "geometry": {"coordinates":[-102.20222,20.50583],"type":"Point"}
}