{
  "type": "Feature",
  "properties": {
    "gn:admin1_code":"19.0",
    "gn:asciiname":"Palo Agujerado",
    "gn:country_code":"MX",
    "gn:dem":957,
    "gn:feature_class":"P",
    "gn:feature_code":"PPL",
    "gn:name":"Palo Agujerado",
    "gn:population":0,
    "gn:timezone":"America/Monterrey",
    "iso:country":"MX",
    "name:spa_x_preferred":[
        "Palo Agujerado"
    ],
    "wof:name":"Palo Agujerado",
    "wof:placetype":"locality"
},
  "geometry": {"coordinates":[-99.745,24.155],"type":"Point"}
}