{
  "type": "Feature",
  "properties": {
    "gn:admin1_code":"21",
    "gn:admin2_code":"93.0",
    "gn:asciiname":"Cuauhtemoc",
    "gn:country_code":"MX",
    "gn:dem":2716,
    "gn:feature_class":"P",
    "gn:feature_code":"PPL",
    "gn:name":"Cuauht\u00e9moc",
    "gn:population":1382,
    "gn:timezone":"America/Mexico_City",
    "iso:country":"MX",
    "name:und_x_variant":[
        "Cuauht\u00e9moc"
    ],
    "wof:name":"Cuauhtemoc",
    "wof:placetype":"locality",
    "wof:population":1382
},
  "geometry": {"coordinates":[-97.33833,19.22306],"type":"Point"}
}