{
  "type": "Feature",
  "properties": {
    "gn:admin1_code":"15",
    "gn:admin2_code":"9.0",
    "gn:asciiname":"El Arenal",
    "gn:country_code":"MX",
    "gn:dem":2478,
    "gn:feature_class":"P",
    "gn:feature_code":"PPL",
    "gn:name":"El Arenal",
    "gn:population":59,
    "gn:timezone":"America/Mexico_City",
    "iso:country":"MX",
    "wof:name":"El Arenal",
    "wof:placetype":"locality",
    "wof:population":59
},
  "geometry": {"coordinates":[-98.77838,19.1086],"type":"Point"}
}