{
  "type": "Feature",
  "properties": {
    "gn:admin1_code":"6.0",
    "gn:admin2_code":"15.0",
    "gn:asciiname":"Dos Anillos",
    "gn:country_code":"MX",
    "gn:dem":1504,
    "gn:feature_class":"P",
    "gn:feature_code":"PPL",
    "gn:name":"Dos Anillos",
    "gn:population":0,
    "gn:timezone":"America/Chihuahua",
    "iso:country":"MX",
    "name:spa_x_preferred":[
        "Dos Anillos"
    ],
    "wof:name":"Dos Anillos",
    "wof:placetype":"locality"
},
  "geometry": {"coordinates":[-105.28295,29.44941],"type":"Point"}
}