{
  "type": "Feature",
  "properties": {
    "gn:admin1_code":"16",
    "gn:admin2_code":"61.0",
    "gn:asciiname":"Manzana del Tejocote",
    "gn:country_code":"MX",
    "gn:dem":2487,
    "gn:feature_class":"P",
    "gn:feature_code":"PPL",
    "gn:name":"Manzana del Tejocote",
    "gn:population":325,
    "gn:timezone":"America/Mexico_City",
    "iso:country":"MX",
    "wof:name":"Manzana del Tejocote",
    "wof:placetype":"locality",
    "wof:population":325
},
  "geometry": {"coordinates":[-100.39694,19.61139],"type":"Point"}
}