{
  "type": "Feature",
  "properties": {
    "gn:admin1_code":"16",
    "gn:admin2_code":"97.0",
    "gn:asciiname":"El Reparito",
    "gn:country_code":"MX",
    "gn:dem":719,
    "gn:feature_class":"P",
    "gn:feature_code":"PPL",
    "gn:name":"El Reparito",
    "gn:population":0,
    "gn:timezone":"America/Mexico_City",
    "iso:country":"MX",
    "name:spa_x_preferred":[
        "El Reparito"
    ],
    "wof:name":"El Reparito",
    "wof:placetype":"locality"
},
  "geometry": {"coordinates":[-101.40559,18.82801],"type":"Point"}
}