{
  "type": "Feature",
  "properties": {
    "gn:admin1_code":"7",
    "gn:asciiname":"Los Amparos",
    "gn:country_code":"MX",
    "gn:dem":1095,
    "gn:feature_class":"P",
    "gn:feature_code":"PPL",
    "gn:name":"Los Amparos",
    "gn:population":0,
    "gn:timezone":"America/Monterrey",
    "iso:country":"MX",
    "name:spa_x_preferred":[
        "Los Amparos"
    ],
    "wof:name":"Los Amparos",
    "wof:placetype":"locality"
},
  "geometry": {"coordinates":[-103.42403,25.98091],"type":"Point"}
}