{
  "type": "Feature",
  "properties": {
    "gn:admin1_code":"15",
    "gn:admin2_code":"120.0",
    "gn:asciiname":"Granjas Praderas (Santa Rita)",
    "gn:country_code":"MX",
    "gn:dem":2277,
    "gn:feature_class":"P",
    "gn:feature_code":"PPL",
    "gn:name":"Granjas Praderas (Santa Rita)",
    "gn:population":7,
    "gn:timezone":"America/Mexico_City",
    "iso:country":"MX",
    "wof:name":"Granjas Praderas (Santa Rita)",
    "wof:placetype":"locality",
    "wof:population":7
},
  "geometry": {"coordinates":[-99.05441,19.83402],"type":"Point"}
}