{
  "type": "Feature",
  "properties": {
    "gn:admin1_code":"18",
    "gn:admin2_code":"15.0",
    "gn:asciiname":"Rancho de los Lozano",
    "gn:country_code":"MX",
    "gn:dem":10,
    "gn:feature_class":"P",
    "gn:feature_code":"PPL",
    "gn:name":"Rancho de los Lozano",
    "gn:population":7,
    "gn:timezone":"America/Mazatlan",
    "iso:country":"MX",
    "wof:name":"Rancho de los Lozano",
    "wof:placetype":"locality",
    "wof:population":7
},
  "geometry": {"coordinates":[-105.22750000000001,21.75667],"type":"Point"}
}