{
  "type": "Feature",
  "properties": {
    "gn:admin1_code":"4",
    "gn:admin2_code":"9.0",
    "gn:asciiname":"Moch-Cohuo",
    "gn:country_code":"MX",
    "gn:dem":58,
    "gn:feature_class":"P",
    "gn:feature_code":"PPL",
    "gn:name":"Moch-Cohuo",
    "gn:population":5,
    "gn:timezone":"America/Merida",
    "iso:country":"MX",
    "wof:name":"Moch-Cohuo",
    "wof:placetype":"locality",
    "wof:population":5
},
  "geometry": {"coordinates":[-90.73972000000001,18.79861],"type":"Point"}
}