{
  "type": "Feature",
  "properties": {
    "gn:admin1_code":"21",
    "gn:admin2_code":"17.0",
    "gn:asciiname":"Cala Norte",
    "gn:country_code":"MX",
    "gn:dem":1970,
    "gn:feature_class":"P",
    "gn:feature_code":"PPL",
    "gn:name":"Cala Norte",
    "gn:population":1357,
    "gn:timezone":"America/Mexico_City",
    "iso:country":"MX",
    "wof:name":"Cala Norte",
    "wof:placetype":"locality",
    "wof:population":1357
},
  "geometry": {"coordinates":[-97.42306000000001,19.84778],"type":"Point"}
}