{
  "type": "Feature",
  "properties": {
    "gn:admin1_code":"30.0",
    "gn:admin2_code":"205.0",
    "gn:asciiname":"El Encanto",
    "gn:country_code":"MX",
    "gn:dem":35,
    "gn:feature_class":"P",
    "gn:feature_code":"PPL",
    "gn:name":"El Encanto",
    "gn:population":4,
    "gn:timezone":"America/Mexico_City",
    "iso:country":"MX",
    "name:cat_x_preferred":[
        "El Encanto"
    ],
    "name:ceb_x_preferred":[
        "El Encanto"
    ],
    "name:fra_x_preferred":[
        "El Encanto"
    ],
    "name:heb_x_preferred":[
        "\u05d0\u05dc \u05d0\u05e0\u05e7\u05e0\u05d8\u05d5"
    ],
    "name:ilo_x_preferred":[
        "El Encanto"
    ],
    "name:ita_x_preferred":[
        "El Encanto"
    ],
    "name:msa_x_preferred":[
        "El Encanto"
    ],
    "name:nld_x_preferred":[
        "El Encanto"
    ],
    "name:por_x_preferred":[
        "El Encanto"
    ],
    "name:rus_x_preferred":[
        "\u042d\u043b\u044c-\u042d\u043d\u043a\u0430\u043d\u0442\u043e"
    ],
    "name:spa_x_preferred":[
        "El Encanto"
    ],
    "name:swe_x_preferred":[
        "El Encanto"
    ],
    "name:tgl_x_preferred":[
        "El Encanto"
    ],
    "name:vie_x_preferred":[
        "El Encanto"
    ],
    "name:war_x_preferred":[
        "El Encanto"
    ],
    "name:zho_x_preferred":[
        "\u57c3\u723e\u6069\u574e\u6258"
    ],
    "wof:name":"El Encanto",
    "wof:placetype":"locality",
    "wof:population":4
},
  "geometry": {"coordinates":[-98.42139,21.67222000000001],"type":"Point"}
}