{
  "type": "Feature",
  "properties": {
    "gn:admin1_code":"30.0",
    "gn:admin2_code":"205.0",
    "gn:asciiname":"El Encanto",
    "gn:country_code":"MX",
    "gn:dem":35,
    "gn:feature_class":"P",
    "gn:feature_code":"PPL",
    "gn:name":"El Encanto",
    "gn:population":4,
    "gn:timezone":"America/Mexico_City",
    "iso:country":"MX",
    "name:spa_x_preferred":[
        "El Encanto"
    ],
    "wof:name":"El Encanto",
    "wof:placetype":"locality",
    "wof:population":4
},
  "geometry": {"coordinates":[-98.42139,21.67222000000001],"type":"Point"}
}