{
  "type": "Feature",
  "properties": {
    "gn:admin1_code":"10",
    "gn:admin2_code":"32.0",
    "gn:asciiname":"Los Altares",
    "gn:country_code":"MX",
    "gn:dem":2485,
    "gn:feature_class":"P",
    "gn:feature_code":"PPL",
    "gn:name":"Los Altares",
    "gn:population":155,
    "gn:timezone":"America/Monterrey",
    "iso:country":"MX",
    "wof:name":"Los Altares",
    "wof:placetype":"locality",
    "wof:population":155
},
  "geometry": {"coordinates":[-105.89610999999999,24.99889],"type":"Point"}
}