{
  "type": "Feature",
  "properties": {
    "gn:admin1_code":"32",
    "gn:admin2_code":"57.0",
    "gn:asciiname":"Familias Reyes",
    "gn:country_code":"MX",
    "gn:dem":2225,
    "gn:feature_class":"P",
    "gn:feature_code":"PPL",
    "gn:name":"Familias Reyes",
    "gn:population":5,
    "gn:timezone":"America/Mexico_City",
    "iso:country":"MX",
    "wof:name":"Familias Reyes",
    "wof:placetype":"locality",
    "wof:population":5
},
  "geometry": {"coordinates":[-102.38444,22.73333],"type":"Point"}
}