{
  "type": "Feature",
  "properties": {
    "gn:admin1_code":"1.0",
    "gn:admin2_code":"1.0",
    "gn:asciiname":"La Haciendita",
    "gn:country_code":"MX",
    "gn:dem":1768,
    "gn:feature_class":"P",
    "gn:feature_code":"PPL",
    "gn:name":"La Haciendita",
    "gn:population":0,
    "gn:timezone":"America/Mexico_City",
    "iso:country":"MX",
    "name:spa_x_preferred":[
        "La Haciendita"
    ],
    "name:und_x_variant":[
        "La Hacienda"
    ],
    "wof:name":"La Haciendita",
    "wof:placetype":"locality"
},
  "geometry": {"coordinates":[-102.45152,21.6858],"type":"Point"}
}