{
  "type": "Feature",
  "properties": {
    "gn:admin1_code":"7",
    "gn:admin2_code":"2.0",
    "gn:asciiname":"Manga del Oso",
    "gn:country_code":"MX",
    "gn:dem":522,
    "gn:feature_class":"P",
    "gn:feature_code":"PPL",
    "gn:name":"Manga del Oso",
    "gn:population":0,
    "gn:timezone":"America/Matamoros",
    "iso:country":"MX",
    "name:spa_x_preferred":[
        "Manga del Oso"
    ],
    "name:und_x_variant":[
        "Manga el Oso"
    ],
    "wof:name":"Manga del Oso",
    "wof:placetype":"locality"
},
  "geometry": {"coordinates":[-102.20229999999999,29.76216],"type":"Point"}
}