{
  "type": "Feature",
  "properties": {
    "gn:admin1_code":"5.0",
    "gn:admin2_code":"17.0",
    "gn:asciiname":"La Piedad",
    "gn:country_code":"MX",
    "gn:dem":549,
    "gn:feature_class":"P",
    "gn:feature_code":"PPL",
    "gn:name":"La Piedad",
    "gn:population":0,
    "gn:timezone":"America/Mexico_City",
    "iso:country":"MX",
    "name:spa_x_preferred":[
        "La Piedad"
    ],
    "wof:name":"La Piedad",
    "wof:placetype":"locality"
},
  "geometry": {"coordinates":[-93.70359999999999,16.67667],"type":"Point"}
}