{
  "type": "Feature",
  "properties": {
    "gn:admin1_code":"6.0",
    "gn:admin2_code":"14.0",
    "gn:asciiname":"Siete Hermanos",
    "gn:country_code":"MX",
    "gn:dem":1497,
    "gn:feature_class":"P",
    "gn:feature_code":"PPL",
    "gn:name":"Siete Hermanos",
    "gn:population":0,
    "gn:timezone":"America/Chihuahua",
    "iso:country":"MX",
    "name:spa_x_preferred":[
        "Siete Hermanos"
    ],
    "wof:name":"Siete Hermanos",
    "wof:placetype":"locality"
},
  "geometry": {"coordinates":[-105.13303999999999,26.78115],"type":"Point"}
}