{
  "type": "Feature",
  "properties": {
    "gn:admin1_code":"24.0",
    "gn:asciiname":"Chiquihuitillo",
    "gn:country_code":"MX",
    "gn:dem":2118,
    "gn:feature_class":"P",
    "gn:feature_code":"PPL",
    "gn:name":"Chiquihuitillo",
    "gn:population":0,
    "gn:timezone":"America/Mexico_City",
    "iso:country":"MX",
    "wof:name":"Chiquihuitillo",
    "wof:placetype":"locality"
},
  "geometry": {"coordinates":[-101.33333,22.53333],"type":"Point"}
}