{
  "type": "Feature",
  "properties": {
    "gn:admin1_code":"14",
    "gn:admin2_code":"45",
    "gn:asciiname":"La Manga",
    "gn:country_code":"MX",
    "gn:dem":1619,
    "gn:feature_class":"P",
    "gn:feature_code":"PPL",
    "gn:name":"La Manga",
    "gn:population":17,
    "gn:timezone":"America/Mexico_City",
    "iso:country":"MX",
    "name:aze_x_preferred":[
        "La-Manqa dili"
    ],
    "name:ceb_x_preferred":[
        "Manga del Mar Menor"
    ],
    "name:dan_x_preferred":[
        "La Manga"
    ],
    "name:fra_x_preferred":[
        "La Manga"
    ],
    "name:jpn_x_preferred":[
        "\u30e9\u30fb\u30de\u30f3\u30ac"
    ],
    "name:nno_x_preferred":[
        "La Manga"
    ],
    "name:nor_x_preferred":[
        "La Manga"
    ],
    "name:pol_x_preferred":[
        "La Manga"
    ],
    "name:rus_x_preferred":[
        "\u041b\u0430-\u041c\u0430\u043d\u0433\u0430"
    ],
    "name:swe_x_preferred":[
        "La Manga"
    ],
    "name:ukr_x_preferred":[
        "\u041b\u0430-\u041c\u0430\u043d\u0433\u0430"
    ],
    "wof:name":"La Manga",
    "wof:placetype":"locality",
    "wof:population":17
},
  "geometry": {"coordinates":[-103.15000000000001,20.79306],"type":"Point"}
}