{
  "type": "Feature",
  "properties": {
    "gn:admin1_code":"31",
    "gn:admin2_code":"58.0",
    "gn:asciiname":"X-Cobiacal",
    "gn:country_code":"MX",
    "gn:dem":47,
    "gn:feature_class":"P",
    "gn:feature_code":"PPL",
    "gn:name":"X-Cobiacal",
    "gn:population":0,
    "gn:timezone":"America/Cancun",
    "iso:country":"MX",
    "name:spa_x_preferred":[
        "X-Cobiacal"
    ],
    "wof:name":"X-Cobiacal",
    "wof:placetype":"locality"
},
  "geometry": {"coordinates":[-88.98206,19.83829],"type":"Point"}
}