{
  "type": "Feature",
  "properties": {
    "gn:admin1_code":"30",
    "gn:admin2_code":"11",
    "gn:asciiname":"San Antonio Flota",
    "gn:country_code":"MX",
    "gn:dem":2,
    "gn:feature_class":"P",
    "gn:feature_code":"PPL",
    "gn:name":"San Antonio Flota",
    "gn:population":15,
    "gn:timezone":"America/Mexico_City",
    "iso:country":"MX",
    "wof:name":"San Antonio Flota",
    "wof:placetype":"locality",
    "wof:population":15
},
  "geometry": {"coordinates":[-95.7675,18.64861],"type":"Point"}
}