{
  "type": "Feature",
  "properties": {
    "gn:admin1_code":"15",
    "gn:admin2_code":"99.0",
    "gn:asciiname":"Moreda",
    "gn:country_code":"MX",
    "gn:dem":2250,
    "gn:feature_class":"P",
    "gn:feature_code":"PPL",
    "gn:name":"Moreda",
    "gn:population":0,
    "gn:timezone":"America/Mexico_City",
    "iso:country":"MX",
    "name:bre_x_preferred":[
        "Moreda"
    ],
    "name:eus_x_preferred":[
        "Moreda"
    ],
    "name:glg_x_preferred":[
        "Moreda"
    ],
    "name:spa_x_preferred":[
        "Moreda"
    ],
    "wof:name":"Moreda",
    "wof:placetype":"locality"
},
  "geometry": {"coordinates":[-98.90414,19.52967],"type":"Point"}
}