{
  "type": "Feature",
  "properties": {
    "gn:admin1_code":"7.0",
    "gn:admin2_code":"3.0",
    "gn:asciiname":"La Mota",
    "gn:country_code":"MX",
    "gn:dem":393,
    "gn:feature_class":"P",
    "gn:feature_code":"PPL",
    "gn:name":"La Mota",
    "gn:population":0,
    "gn:timezone":"America/Monterrey",
    "iso:country":"MX",
    "name:spa_x_preferred":[
        "La Mota"
    ],
    "wof:name":"La Mota",
    "wof:placetype":"locality"
},
  "geometry": {"coordinates":[-100.87571,28.32874],"type":"Point"}
}