{
  "type": "Feature",
  "properties": {
    "gn:admin1_code":"16",
    "gn:admin2_code":"50.0",
    "gn:asciiname":"El Botin",
    "gn:country_code":"MX",
    "gn:dem":2391,
    "gn:feature_class":"P",
    "gn:feature_code":"PPL",
    "gn:name":"El Bot\u00edn",
    "gn:population":59,
    "gn:timezone":"America/Mexico_City",
    "iso:country":"MX",
    "name:und_x_variant":[
        "El Bot\u00edn"
    ],
    "wof:name":"El Botin",
    "wof:placetype":"locality",
    "wof:population":59
},
  "geometry": {"coordinates":[-100.31806,19.98278],"type":"Point"}
}