{
  "type": "Feature",
  "properties": {
    "gn:admin1_code":"27",
    "gn:admin2_code":"11.0",
    "gn:asciiname":"Cirilo y Narvaez",
    "gn:country_code":"MX",
    "gn:dem":10,
    "gn:feature_class":"P",
    "gn:feature_code":"PPL",
    "gn:name":"Cirilo y Narv\u00e1ez",
    "gn:population":0,
    "gn:timezone":"America/Mexico_City",
    "iso:country":"MX",
    "name:spa_x_preferred":[
        "Cirilo y Narv\u00e1ez"
    ],
    "wof:name":"Cirilo y Narvaez",
    "wof:placetype":"locality"
},
  "geometry": {"coordinates":[-92.26401,18.12086],"type":"Point"}
}