{
  "type": "Feature",
  "properties": {
    "gn:admin1_code":"5",
    "gn:admin2_code":"51",
    "gn:asciiname":"Punta del Llano (El Pajon)",
    "gn:country_code":"MX",
    "gn:dem":12,
    "gn:feature_class":"P",
    "gn:feature_code":"PPL",
    "gn:name":"Punta del Llano (El Paj\u00f3n)",
    "gn:population":24,
    "gn:timezone":"America/Mexico_City",
    "iso:country":"MX",
    "name:und_x_variant":[
        "Punta del Llano (El Paj\u00f3n)"
    ],
    "wof:name":"Punta del Llano (El Pajon)",
    "wof:placetype":"locality",
    "wof:population":24
},
  "geometry": {"coordinates":[-93.09860999999999,15.39917],"type":"Point"}
}