{
  "type": "Feature",
  "properties": {
    "gn:admin1_code":"10",
    "gn:admin2_code":"4.0",
    "gn:asciiname":"Los Barriales",
    "gn:country_code":"MX",
    "gn:dem":2111,
    "gn:feature_class":"P",
    "gn:feature_code":"PPL",
    "gn:name":"Los Barriales",
    "gn:population":8,
    "gn:timezone":"America/Monterrey",
    "iso:country":"MX",
    "wof:name":"Los Barriales",
    "wof:placetype":"locality",
    "wof:population":8
},
  "geometry": {"coordinates":[-103.75423000000001,24.39039],"type":"Point"}
}