{
  "type": "Feature",
  "properties": {
    "gn:admin1_code":"27",
    "gn:admin2_code":"11.0",
    "gn:asciiname":"El Chinal",
    "gn:country_code":"MX",
    "gn:dem":5,
    "gn:feature_class":"P",
    "gn:feature_code":"PPL",
    "gn:name":"El Chinal",
    "gn:population":0,
    "gn:timezone":"America/Mexico_City",
    "iso:country":"MX",
    "name:spa_x_preferred":[
        "El Chinal"
    ],
    "wof:name":"El Chinal",
    "wof:placetype":"locality"
},
  "geometry": {"coordinates":[-92.08333,17.96667],"type":"Point"}
}