{
  "type": "Feature",
  "properties": {
    "gn:admin1_code":"16",
    "gn:admin2_code":"89.0",
    "gn:asciiname":"Pinolapa",
    "gn:country_code":"MX",
    "gn:dem":546,
    "gn:feature_class":"P",
    "gn:feature_code":"PPL",
    "gn:name":"Pinolapa",
    "gn:population":79,
    "gn:timezone":"America/Mexico_City",
    "iso:country":"MX",
    "wof:name":"Pinolapa",
    "wof:placetype":"locality",
    "wof:population":79
},
  "geometry": {"coordinates":[-103.01083,19.01944],"type":"Point"}
}