{
  "type": "Feature",
  "properties": {
    "gn:admin1_code":"20",
    "gn:admin2_code":"13.0",
    "gn:asciiname":"Paraje Rio Seco (Rancho Guichicovi)",
    "gn:country_code":"MX",
    "gn:dem":1508,
    "gn:feature_class":"P",
    "gn:feature_code":"PPL",
    "gn:name":"Paraje R\u00edo Seco (Rancho Guichicovi)",
    "gn:population":6,
    "gn:timezone":"America/Mexico_City",
    "iso:country":"MX",
    "name:und_x_variant":[
        "Paraje R\u00edo Seco (Rancho Guichicovi)"
    ],
    "wof:name":"Paraje Rio Seco (Rancho Guichicovi)",
    "wof:placetype":"locality",
    "wof:population":6
},
  "geometry": {"coordinates":[-96.77861,16.88611],"type":"Point"}
}