{
  "type": "Feature",
  "properties": {
    "gn:admin1_code":"24",
    "gn:admin2_code":"34.0",
    "gn:asciiname":"Potreros el Sabino",
    "gn:country_code":"MX",
    "gn:dem":41,
    "gn:feature_class":"P",
    "gn:feature_code":"PPL",
    "gn:name":"Potreros el Sabino",
    "gn:population":3,
    "gn:timezone":"America/Mexico_City",
    "iso:country":"MX",
    "wof:name":"Potreros el Sabino",
    "wof:placetype":"locality",
    "wof:population":3
},
  "geometry": {"coordinates":[-98.51262,21.75091],"type":"Point"}
}