{
  "type": "Feature",
  "properties": {
    "gn:admin1_code":"25",
    "gn:admin2_code":"5.0",
    "gn:asciiname":"Las Mesas",
    "gn:country_code":"MX",
    "gn:dem":339,
    "gn:feature_class":"P",
    "gn:feature_code":"PPL",
    "gn:name":"Las Mesas",
    "gn:population":0,
    "gn:timezone":"America/Mazatlan",
    "iso:country":"MX",
    "name:ara_x_preferred":[
        "\u0644\u0627\u0633 \u0645\u064a\u0633\u0627\u0633"
    ],
    "name:arg_x_preferred":[
        "Las Mesas"
    ],
    "name:ast_x_preferred":[
        "Las Mesas"
    ],
    "name:cat_x_preferred":[
        "Las Mesas"
    ],
    "name:ceb_x_preferred":[
        "Las Mesas"
    ],
    "name:epo_x_preferred":[
        "Las Mesas"
    ],
    "name:eus_x_preferred":[
        "Las Mesas"
    ],
    "name:fra_x_preferred":[
        "Las Mesas"
    ],
    "name:hun_x_preferred":[
        "Las Mesas"
    ],
    "name:ita_x_preferred":[
        "Las Mesas"
    ],
    "name:kaz_x_preferred":[
        "\u041b\u0430\u0441-\u041c\u0435\u0441\u0430\u0441"
    ],
    "name:msa_x_preferred":[
        "Las Mesas"
    ],
    "name:nld_x_preferred":[
        "Las Mesas"
    ],
    "name:oci_x_preferred":[
        "Las Mesas"
    ],
    "name:pol_x_preferred":[
        "Las Mesas"
    ],
    "name:rus_x_preferred":[
        "\u041b\u0430\u0441-\u041c\u0435\u0441\u0430\u0441"
    ],
    "name:sco_x_preferred":[
        "Las Mesas"
    ],
    "name:spa_x_preferred":[
        "Las Mesas"
    ],
    "name:ukr_x_preferred":[
        "\u041b\u0430\u0441-\u041c\u0435\u0441\u0430\u0441"
    ],
    "name:vie_x_preferred":[
        "Las Mesas"
    ],
    "name:war_x_preferred":[
        "Las Mesas"
    ],
    "name:zho_x_preferred":[
        "\u62c9\u65af\u6885\u8428\u65af"
    ],
    "wof:name":"Las Mesas",
    "wof:placetype":"locality"
},
  "geometry": {"coordinates":[-106.73956,24.26459],"type":"Point"}
}