{
  "type": "Feature",
  "properties": {
    "gn:admin1_code":"29",
    "gn:admin2_code":"55.0",
    "gn:asciiname":"Tlaxcantitla",
    "gn:country_code":"MX",
    "gn:dem":2566,
    "gn:feature_class":"P",
    "gn:feature_code":"PPL",
    "gn:name":"Tlaxcantitla",
    "gn:population":29,
    "gn:timezone":"America/Mexico_City",
    "iso:country":"MX",
    "name:spa_x_preferred":[
        "Tlaxcantitla"
    ],
    "wof:name":"Tlaxcantitla",
    "wof:placetype":"locality",
    "wof:population":29
},
  "geometry": {"coordinates":[-98.24881999999999,19.4673],"type":"Point"}
}