{
  "type": "Feature",
  "properties": {
    "gn:admin1_code":"16.0",
    "gn:admin2_code":"2.0",
    "gn:asciiname":"El Pie de la Cuesta",
    "gn:country_code":"MX",
    "gn:dem":999,
    "gn:feature_class":"P",
    "gn:feature_code":"PPL",
    "gn:name":"El Pie de la Cuesta",
    "gn:population":0,
    "gn:timezone":"America/Mexico_City",
    "iso:country":"MX",
    "name:spa_x_preferred":[
        "El Pie de la Cuesta"
    ],
    "wof:name":"El Pie de la Cuesta",
    "wof:placetype":"locality"
},
  "geometry": {"coordinates":[-102.80800000000001,18.74388],"type":"Point"}
}