{
  "type": "Feature",
  "properties": {
    "gn:admin1_code":"6",
    "gn:admin2_code":"18.0",
    "gn:asciiname":"Rancho Masichin",
    "gn:country_code":"MX",
    "gn:dem":2121,
    "gn:feature_class":"P",
    "gn:feature_code":"PPL",
    "gn:name":"Rancho Masich\u00edn",
    "gn:population":5,
    "gn:timezone":"America/Chihuahua",
    "iso:country":"MX",
    "name:und_x_variant":[
        "Rancho Masich\u00edn"
    ],
    "wof:name":"Rancho Masichin",
    "wof:placetype":"locality",
    "wof:population":5
},
  "geometry": {"coordinates":[-107.02726,28.20426],"type":"Point"}
}