{
  "type": "Feature",
  "properties": {
    "gn:admin1_code":"5",
    "gn:admin2_code":"18",
    "gn:asciiname":"Vistahermosa",
    "gn:country_code":"MX",
    "gn:dem":1695,
    "gn:feature_class":"P",
    "gn:feature_code":"PPL",
    "gn:name":"Vistahermosa",
    "gn:population":31,
    "gn:timezone":"America/Mexico_City",
    "iso:country":"MX",
    "wof:name":"Vistahermosa",
    "wof:placetype":"locality",
    "wof:population":31
},
  "geometry": {"coordinates":[-93.14861000000001,17.14278],"type":"Point"}
}