{
  "type": "Feature",
  "properties": {
    "gn:admin1_code":"2.0",
    "gn:admin2_code":"1.0",
    "gn:asciiname":"Valle Lindo",
    "gn:country_code":"MX",
    "gn:dem":187,
    "gn:feature_class":"P",
    "gn:feature_code":"PPL",
    "gn:name":"Valle Lindo",
    "gn:population":0,
    "gn:timezone":"America/Tijuana",
    "iso:country":"MX",
    "name:spa_x_preferred":[
        "Valle Lindo"
    ],
    "wof:name":"Valle Lindo",
    "wof:placetype":"locality"
},
  "geometry": {"coordinates":[-116.46878999999998,31.71183],"type":"Point"}
}