{
  "type": "Feature",
  "properties": {
    "gn:admin1_code":"5",
    "gn:admin2_code":"99.0",
    "gn:asciiname":"El Pedernal",
    "gn:country_code":"MX",
    "gn:dem":1093,
    "gn:feature_class":"P",
    "gn:feature_code":"PPL",
    "gn:name":"El Pedernal",
    "gn:population":0,
    "gn:timezone":"America/Mexico_City",
    "iso:country":"MX",
    "name:spa_x_preferred":[
        "El Pedernal"
    ],
    "wof:name":"El Pedernal",
    "wof:placetype":"locality"
},
  "geometry": {"coordinates":[-91.78435,16.00072],"type":"Point"}
}