{
  "type": "Feature",
  "properties": {
    "gn:admin1_code":"26",
    "gn:admin2_code":"45.0",
    "gn:asciiname":"Santa Gertrudis",
    "gn:country_code":"MX",
    "gn:dem":862,
    "gn:feature_class":"P",
    "gn:feature_code":"PPL",
    "gn:name":"Santa Gertrudis",
    "gn:population":0,
    "gn:timezone":"America/Hermosillo",
    "iso:country":"MX",
    "name:cat_x_preferred":[
        "Santa Gertrudis"
    ],
    "name:ceb_x_preferred":[
        "Santa Gertrudis"
    ],
    "name:deu_x_preferred":[
        "Santa Gertrudis"
    ],
    "name:sco_x_preferred":[
        "Santa Gertrudis"
    ],
    "name:spa_x_preferred":[
        "Santa Gertrudis"
    ],
    "name:swe_x_preferred":[
        "Santa Gertrudis"
    ],
    "name:und_x_variant":[
        "Rancho Santa Gertrudis",
        "Santa Gertrudis"
    ],
    "wof:name":"Santa Gertrudis",
    "wof:placetype":"locality"
},
  "geometry": {"coordinates":[-110.83234,30.04191],"type":"Point"}
}