{
  "type": "Feature",
  "properties": {
    "gn:admin1_code":"6",
    "gn:admin2_code":"35.0",
    "gn:asciiname":"Punta de Agua",
    "gn:country_code":"MX",
    "gn:dem":1458,
    "gn:feature_class":"P",
    "gn:feature_code":"PPL",
    "gn:name":"Punta de Agua",
    "gn:population":6,
    "gn:timezone":"America/Chihuahua",
    "iso:country":"MX",
    "wof:name":"Punta de Agua",
    "wof:placetype":"locality",
    "wof:population":6
},
  "geometry": {"coordinates":[-108.40042,30.74827],"type":"Point"}
}