{
  "type": "Feature",
  "properties": {
    "gn:admin1_code":"6",
    "gn:admin2_code":"65.0",
    "gn:asciiname":"La Yerba Buena",
    "gn:country_code":"MX",
    "gn:dem":1639,
    "gn:feature_class":"P",
    "gn:feature_code":"PPL",
    "gn:name":"La Yerba Buena",
    "gn:population":7,
    "gn:timezone":"America/Chihuahua",
    "iso:country":"MX",
    "wof:name":"La Yerba Buena",
    "wof:placetype":"locality",
    "wof:population":7
},
  "geometry": {"coordinates":[-107.99352,27.06965],"type":"Point"}
}