{
  "type": "Feature",
  "properties": {
    "gn:admin1_code":"14",
    "gn:admin2_code":"45.0",
    "gn:asciiname":"Canada de los Lobos (Las Margaritas)",
    "gn:country_code":"MX",
    "gn:dem":1832,
    "gn:feature_class":"P",
    "gn:feature_code":"PPL",
    "gn:name":"Ca\u00f1ada de los Lobos (Las Margaritas)",
    "gn:population":5,
    "gn:timezone":"America/Mexico_City",
    "iso:country":"MX",
    "name:und_x_variant":[
        "Ca\u00f1ada de los Lobos (Las Margaritas)"
    ],
    "wof:name":"Canada de los Lobos (Las Margaritas)",
    "wof:placetype":"locality",
    "wof:population":5
},
  "geometry": {"coordinates":[-103.23778,20.91972],"type":"Point"}
}