{
  "type": "Feature",
  "properties": {
    "gn:admin1_code":"4",
    "gn:admin2_code":"9.0",
    "gn:asciiname":"Inspeccion",
    "gn:country_code":"MX",
    "gn:dem":71,
    "gn:feature_class":"P",
    "gn:feature_code":"PPL",
    "gn:name":"Inspecci\u00f3n",
    "gn:population":0,
    "gn:timezone":"America/Merida",
    "iso:country":"MX",
    "wof:name":"Inspeccion",
    "wof:placetype":"locality"
},
  "geometry": {"coordinates":[-90.91667,18.28333],"type":"Point"}
}