{
  "type": "Feature",
  "properties": {
    "gn:admin1_code":"11",
    "gn:admin2_code":"14.0",
    "gn:asciiname":"Los Quiotes",
    "gn:country_code":"MX",
    "gn:dem":2045,
    "gn:feature_class":"P",
    "gn:feature_code":"PPL",
    "gn:name":"Los Quiotes",
    "gn:population":0,
    "gn:timezone":"America/Mexico_City",
    "iso:country":"MX",
    "name:spa_x_preferred":[
        "Los Quiotes"
    ],
    "wof:name":"Los Quiotes",
    "wof:placetype":"locality"
},
  "geometry": {"coordinates":[-101.07107999999999,21.16931],"type":"Point"}
}