{
  "type": "Feature",
  "properties": {
    "gn:admin1_code":"13",
    "gn:asciiname":"Tejocotes",
    "gn:country_code":"MX",
    "gn:dem":2298,
    "gn:feature_class":"P",
    "gn:feature_code":"PPL",
    "gn:name":"Tejocotes",
    "gn:population":0,
    "gn:timezone":"America/Mexico_City",
    "iso:country":"MX",
    "name:spa_x_preferred":[
        "Tejocotes"
    ],
    "wof:name":"Tejocotes",
    "wof:placetype":"locality"
},
  "geometry": {"coordinates":[-98.53422,20.50378],"type":"Point"}
}