{
  "type": "Feature",
  "properties": {
    "gn:admin1_code":"24",
    "gn:admin2_code":"56.0",
    "gn:asciiname":"Capillas (La Capilla)",
    "gn:country_code":"MX",
    "gn:dem":1616,
    "gn:feature_class":"P",
    "gn:feature_code":"PPL",
    "gn:name":"Capillas (La Capilla)",
    "gn:population":5,
    "gn:timezone":"America/Mexico_City",
    "iso:country":"MX",
    "wof:name":"Capillas (La Capilla)",
    "wof:placetype":"locality",
    "wof:population":5
},
  "geometry": {"coordinates":[-100.91361000000001,22.68694],"type":"Point"}
}