{
  "type": "Feature",
  "properties": {
    "gn:admin1_code":"25",
    "gn:admin2_code":"9.0",
    "gn:asciiname":"La Campana Numero Dos (El Pochote)",
    "gn:country_code":"MX",
    "gn:dem":15,
    "gn:feature_class":"P",
    "gn:feature_code":"PPL",
    "gn:name":"La Campana N\u00famero Dos (El Pochote)",
    "gn:population":267,
    "gn:timezone":"America/Mazatlan",
    "iso:country":"MX",
    "wof:name":"La Campana Numero Dos (El Pochote)",
    "wof:placetype":"locality",
    "wof:population":267
},
  "geometry": {"coordinates":[-105.59778,22.71972],"type":"Point"}
}