{
  "type": "Feature",
  "properties": {
    "gn:admin1_code":"5.0",
    "gn:admin2_code":"13.0",
    "gn:asciiname":"Nio",
    "gn:country_code":"MX",
    "gn:dem":1269,
    "gn:feature_class":"P",
    "gn:feature_code":"PPL",
    "gn:name":"N\u00edo",
    "gn:population":0,
    "gn:timezone":"America/Mexico_City",
    "iso:country":"MX",
    "name:spa_x_preferred":[
        "N\u00edo"
    ],
    "wof:name":"Nio",
    "wof:placetype":"locality"
},
  "geometry": {"coordinates":[-92.94284,17.00457999999999],"type":"Point"}
}