{
  "type": "Feature",
  "properties": {
    "gn:admin1_code":"30",
    "gn:admin2_code":"32.0",
    "gn:asciiname":"Antonio Zetina",
    "gn:country_code":"MX",
    "gn:dem":149,
    "gn:feature_class":"P",
    "gn:feature_code":"PPL",
    "gn:name":"Antonio Zetina",
    "gn:population":7,
    "gn:timezone":"America/Mexico_City",
    "iso:country":"MX",
    "wof:name":"Antonio Zetina",
    "wof:placetype":"locality",
    "wof:population":7
},
  "geometry": {"coordinates":[-95.0625,18.52861],"type":"Point"}
}