{
  "type": "Feature",
  "properties": {
    "gn:admin1_code":"6",
    "gn:admin2_code":"47.0",
    "gn:asciiname":"Cienega Prieta",
    "gn:country_code":"MX",
    "gn:dem":1041,
    "gn:feature_class":"P",
    "gn:feature_code":"PPL",
    "gn:name":"Ci\u00e9nega Prieta",
    "gn:population":0,
    "gn:timezone":"America/Chihuahua",
    "iso:country":"MX",
    "name:spa_x_preferred":[
        "Ci\u00e9nega Prieta"
    ],
    "wof:name":"Cienega Prieta",
    "wof:placetype":"locality"
},
  "geometry": {"coordinates":[-108.78112,28.10289],"type":"Point"}
}