{
  "type": "Feature",
  "properties": {
    "gn:admin1_code":"25",
    "gn:admin2_code":"3.0",
    "gn:asciiname":"Paso del Huejote",
    "gn:country_code":"MX",
    "gn:dem":214,
    "gn:feature_class":"P",
    "gn:feature_code":"PPL",
    "gn:name":"Paso del Huejote",
    "gn:population":65,
    "gn:timezone":"America/Mazatlan",
    "iso:country":"MX",
    "wof:name":"Paso del Huejote",
    "wof:placetype":"locality",
    "wof:population":65
},
  "geometry": {"coordinates":[-107.48092,25.21928],"type":"Point"}
}