{
  "type": "Feature",
  "properties": {
    "gn:admin1_code":"4",
    "gn:admin2_code":"7.0",
    "gn:asciiname":"Ribera Alta",
    "gn:country_code":"MX",
    "gn:dem":3,
    "gn:feature_class":"P",
    "gn:feature_code":"PPL",
    "gn:name":"Ribera Alta",
    "gn:population":0,
    "gn:timezone":"America/Merida",
    "iso:country":"MX",
    "name:deu_x_preferred":[
        "Ribera Alta"
    ],
    "name:eus_x_preferred":[
        "Ribera Alta"
    ],
    "name:fra_x_preferred":[
        "Ribera Alta"
    ],
    "name:nld_x_preferred":[
        "Ribera Alta"
    ],
    "name:pol_x_preferred":[
        "Ribera Alta"
    ],
    "name:por_x_preferred":[
        "Ribera Alta"
    ],
    "name:rus_x_preferred":[
        "\u0420\u0438\u0431\u0435\u0440\u0430-\u0410\u043b\u044c\u0442\u0430"
    ],
    "name:spa_x_preferred":[
        "Ribera Alta"
    ],
    "wof:name":"Ribera Alta",
    "wof:placetype":"locality"
},
  "geometry": {"coordinates":[-92.10833,18.23333],"type":"Point"}
}