{
  "type": "Feature",
  "properties": {
    "gn:admin1_code":"14",
    "gn:admin2_code":"44.0",
    "gn:asciiname":"Las Alazanas",
    "gn:country_code":"MX",
    "gn:dem":1530,
    "gn:feature_class":"P",
    "gn:feature_code":"PPL",
    "gn:name":"Las Alazanas",
    "gn:population":8,
    "gn:timezone":"America/Mexico_City",
    "iso:country":"MX",
    "wof:name":"Las Alazanas",
    "wof:placetype":"locality",
    "wof:population":8
},
  "geometry": {"coordinates":[-103.21611,20.43722],"type":"Point"}
}