{
  "type": "Feature",
  "properties": {
    "gn:admin1_code":"30",
    "gn:admin2_code":"69.0",
    "gn:asciiname":"Carrillo Puerto",
    "gn:country_code":"MX",
    "gn:dem":32,
    "gn:feature_class":"P",
    "gn:feature_code":"PPL",
    "gn:name":"Carrillo Puerto",
    "gn:population":0,
    "gn:timezone":"America/Mexico_City",
    "iso:country":"MX",
    "name:und_x_variant":[
        "Santa Rosa"
    ],
    "wof:name":"Carrillo Puerto",
    "wof:placetype":"locality"
},
  "geometry": {"coordinates":[-97.17899,20.4189],"type":"Point"}
}