{
  "type": "Feature",
  "properties": {
    "gn:admin1_code":"20",
    "gn:admin2_code":"366.0",
    "gn:asciiname":"La Primavera",
    "gn:country_code":"MX",
    "gn:dem":486,
    "gn:feature_class":"P",
    "gn:feature_code":"PPL",
    "gn:name":"La Primavera",
    "gn:population":0,
    "gn:timezone":"America/Mexico_City",
    "iso:country":"MX",
    "name:spa_x_preferred":[
        "La Tollana"
    ],
    "name:spa_x_variant":[
        "La Primavera"
    ],
    "name:und_x_variant":[
        "La Tellona"
    ],
    "wof:name":"La Primavera",
    "wof:placetype":"locality"
},
  "geometry": {"coordinates":[-96.71709,16.0227],"type":"Point"}
}