{
  "type": "Feature",
  "properties": {
    "gn:admin1_code":"26.0",
    "gn:admin2_code":"56.0",
    "gn:asciiname":"San Roberto",
    "gn:country_code":"MX",
    "gn:dem":394,
    "gn:feature_class":"P",
    "gn:feature_code":"PPL",
    "gn:name":"San Roberto",
    "gn:population":0,
    "gn:timezone":"America/Hermosillo",
    "iso:country":"MX",
    "name:spa_x_preferred":[
        "San Roberto"
    ],
    "wof:name":"San Roberto",
    "wof:placetype":"locality"
},
  "geometry": {"coordinates":[-110.94302,29.35194000000001],"type":"Point"}
}