{
  "type": "Feature",
  "properties": {
    "gn:admin1_code":"19.0",
    "gn:admin2_code":"44.0",
    "gn:asciiname":"San Luis",
    "gn:country_code":"MX",
    "gn:dem":262,
    "gn:feature_class":"P",
    "gn:feature_code":"PPL",
    "gn:name":"San Luis",
    "gn:population":0,
    "gn:timezone":"America/Monterrey",
    "iso:country":"MX",
    "name:spa_x_preferred":[
        "San Luis"
    ],
    "wof:name":"San Luis",
    "wof:placetype":"locality"
},
  "geometry": {"coordinates":[-100.05355,26.57316],"type":"Point"}
}