{
  "type": "Feature",
  "properties": {
    "gn:admin1_code":"20",
    "gn:admin2_code":"124",
    "gn:asciiname":"Pedro Aquino Lopez",
    "gn:country_code":"MX",
    "gn:dem":26,
    "gn:feature_class":"P",
    "gn:feature_code":"PPL",
    "gn:name":"Pedro Aquino L\u00f3pez",
    "gn:population":11,
    "gn:timezone":"America/Mexico_City",
    "iso:country":"MX",
    "name:und_x_variant":[
        "Pedro Aquino L\u00f3pez"
    ],
    "wof:name":"Pedro Aquino Lopez",
    "wof:placetype":"locality",
    "wof:population":11
},
  "geometry": {"coordinates":[-95.185,16.29528],"type":"Point"}
}