{
  "type": "Feature",
  "properties": {
    "gn:admin1_code":"11",
    "gn:admin2_code":"40.0",
    "gn:asciiname":"Fraccion del Cano",
    "gn:country_code":"MX",
    "gn:dem":1857,
    "gn:feature_class":"P",
    "gn:feature_code":"PPL",
    "gn:name":"Fracci\u00f3n del Cano",
    "gn:population":480,
    "gn:timezone":"America/Mexico_City",
    "iso:country":"MX",
    "name:und_x_variant":[
        "Fracci\u00f3n del Cano"
    ],
    "wof:name":"Fraccion del Cano",
    "wof:placetype":"locality",
    "wof:population":480
},
  "geometry": {"coordinates":[-100.22694,21.06333],"type":"Point"}
}