{
  "type": "Feature",
  "properties": {
    "gn:admin1_code":"32.0",
    "gn:admin2_code":"10.0",
    "gn:asciiname":"La Division",
    "gn:country_code":"MX",
    "gn:dem":2056,
    "gn:feature_class":"P",
    "gn:feature_code":"PPL",
    "gn:name":"La Divisi\u00f3n",
    "gn:population":0,
    "gn:timezone":"America/Mexico_City",
    "iso:country":"MX",
    "name:spa_x_preferred":[
        "La Divisi\u00f3n"
    ],
    "wof:name":"La Division",
    "wof:placetype":"locality"
},
  "geometry": {"coordinates":[-103.01793000000001,23.38131],"type":"Point"}
}