{
  "type": "Feature",
  "properties": {
    "gn:admin1_code":"6.0",
    "gn:admin2_code":"8.0",
    "gn:asciiname":"Guasimas",
    "gn:country_code":"MX",
    "gn:dem":909,
    "gn:feature_class":"P",
    "gn:feature_code":"PPL",
    "gn:name":"Gu\u00e1simas",
    "gn:population":0,
    "gn:timezone":"America/Chihuahua",
    "iso:country":"MX",
    "name:spa_x_preferred":[
        "Gu\u00e1simas"
    ],
    "wof:name":"Guasimas",
    "wof:placetype":"locality"
},
  "geometry": {"coordinates":[-107.78279999999999,26.87307],"type":"Point"}
}