{
  "type": "Feature",
  "properties": {
    "gn:admin1_code":"32.0",
    "gn:admin2_code":"29.0",
    "gn:asciiname":"Pozo Gamboa",
    "gn:country_code":"MX",
    "gn:dem":2091,
    "gn:feature_class":"P",
    "gn:feature_code":"PPL",
    "gn:name":"Pozo Gamboa",
    "gn:population":0,
    "gn:timezone":"America/Mexico_City",
    "iso:country":"MX",
    "name:spa_x_preferred":[
        "Pozo Gamboa"
    ],
    "wof:name":"Pozo Gamboa",
    "wof:placetype":"locality"
},
  "geometry": {"coordinates":[-103.31905999999999,24.03168],"type":"Point"}
}