{
  "type": "Feature",
  "properties": {
    "gn:admin1_code":"3",
    "gn:admin2_code":"1.0",
    "gn:asciiname":"San Luisito",
    "gn:country_code":"MX",
    "gn:dem":138,
    "gn:feature_class":"P",
    "gn:feature_code":"PPL",
    "gn:name":"San Luisito",
    "gn:population":0,
    "gn:timezone":"America/Mazatlan",
    "iso:country":"MX",
    "name:spa_x_preferred":[
        "San Luisito"
    ],
    "name:spa_x_variant":[
        "La Colorina"
    ],
    "wof:name":"San Luisito",
    "wof:placetype":"locality"
},
  "geometry": {"coordinates":[-111.3267,24.93677000000001],"type":"Point"}
}