{
  "type": "Feature",
  "properties": {
    "gn:admin1_code":"30",
    "gn:admin2_code":"23.0",
    "gn:asciiname":"Tierra Nueva",
    "gn:country_code":"MX",
    "gn:dem":637,
    "gn:feature_class":"P",
    "gn:feature_code":"PPL",
    "gn:name":"Tierra Nueva",
    "gn:population":0,
    "gn:timezone":"America/Mexico_City",
    "iso:country":"MX",
    "name:ceb_x_preferred":[
        "Tierra Nueva"
    ],
    "name:spa_x_preferred":[
        "Tierra Nueva"
    ],
    "name:swe_x_preferred":[
        "Tierra Nueva"
    ],
    "wof:name":"Tierra Nueva",
    "wof:placetype":"locality"
},
  "geometry": {"coordinates":[-97.01644,19.93925],"type":"Point"}
}