{
  "type": "Feature",
  "properties": {
    "gn:admin1_code":"21",
    "gn:admin2_code":"94.0",
    "gn:asciiname":"Atlapaleca",
    "gn:country_code":"MX",
    "gn:dem":2358,
    "gn:feature_class":"P",
    "gn:feature_code":"PPL",
    "gn:name":"Atlapaleca",
    "gn:population":6,
    "gn:timezone":"America/Mexico_City",
    "iso:country":"MX",
    "wof:name":"Atlapaleca",
    "wof:placetype":"locality",
    "wof:population":6
},
  "geometry": {"coordinates":[-97.57744,19.45622],"type":"Point"}
}