{
  "type": "Feature",
  "properties": {
    "gn:admin1_code":"18",
    "gn:admin2_code":"7",
    "gn:asciiname":"Familia Rodriguez Ruvalcaba",
    "gn:country_code":"MX",
    "gn:dem":1058,
    "gn:feature_class":"P",
    "gn:feature_code":"PPL",
    "gn:name":"Familia Rodr\u00edguez Ruvalcaba",
    "gn:population":26,
    "gn:timezone":"America/Mazatlan",
    "iso:country":"MX",
    "name:und_x_variant":[
        "Familia Rodr\u00edguez Ruvalcaba"
    ],
    "wof:name":"Familia Rodriguez Ruvalcaba",
    "wof:placetype":"locality",
    "wof:population":26
},
  "geometry": {"coordinates":[-104.43611,21.09472],"type":"Point"}
}