{
  "type": "Feature",
  "properties": {
    "gn:admin1_code":"12",
    "gn:admin2_code":"53.0",
    "gn:asciiname":"El Medano",
    "gn:country_code":"MX",
    "gn:dem":9,
    "gn:feature_class":"P",
    "gn:feature_code":"PPL",
    "gn:name":"El M\u00e9dano",
    "gn:population":0,
    "gn:timezone":"America/Mexico_City",
    "iso:country":"MX",
    "name:spa_x_preferred":[
        "El M\u00e9dano"
    ],
    "wof:name":"El Medano",
    "wof:placetype":"locality"
},
  "geometry": {"coordinates":[-99.32129999999999,16.6604],"type":"Point"}
}