{
  "type": "Feature",
  "properties": {
    "gn:admin1_code":"20",
    "gn:admin2_code":"232.0",
    "gn:asciiname":"El Platanal",
    "gn:country_code":"MX",
    "gn:dem":164,
    "gn:feature_class":"P",
    "gn:feature_code":"PPL",
    "gn:name":"El Platanal",
    "gn:population":0,
    "gn:timezone":"America/Mexico_City",
    "iso:country":"MX",
    "name:spa_x_preferred":[
        "Platanal"
    ],
    "name:spa_x_variant":[
        "El Platanal"
    ],
    "wof:name":"El Platanal",
    "wof:placetype":"locality"
},
  "geometry": {"coordinates":[-96.43728,18.00327],"type":"Point"}
}