{
  "type": "Feature",
  "properties": {
    "gn:admin1_code":"20",
    "gn:admin2_code":"468.0",
    "gn:asciiname":"San Alfredo",
    "gn:country_code":"MX",
    "gn:dem":74,
    "gn:feature_class":"P",
    "gn:feature_code":"PPL",
    "gn:name":"San Alfredo",
    "gn:population":164,
    "gn:timezone":"America/Mexico_City",
    "iso:country":"MX",
    "name:eus_x_preferred":[
        "San Alfredo"
    ],
    "name:por_x_preferred":[
        "San Alfredo"
    ],
    "name:spa_x_preferred":[
        "San Alfredo"
    ],
    "wof:name":"San Alfredo",
    "wof:placetype":"locality",
    "wof:population":164
},
  "geometry": {"coordinates":[-95.88556,17.67027999999999],"type":"Point"}
}