{
  "type": "Feature",
  "properties": {
    "gn:admin1_code":"14",
    "gn:admin2_code":"35.0",
    "gn:asciiname":"Arandas",
    "gn:country_code":"MX",
    "gn:dem":1898,
    "gn:feature_class":"P",
    "gn:feature_code":"PPL",
    "gn:name":"Arandas",
    "gn:population":97,
    "gn:timezone":"America/Mexico_City",
    "iso:country":"MX",
    "wof:name":"Arandas",
    "wof:placetype":"locality",
    "wof:population":97
},
  "geometry": {"coordinates":[-102.26889,21.64139],"type":"Point"}
}