{
  "type": "Feature",
  "properties": {
    "gn:admin1_code":"25",
    "gn:admin2_code":"11.0",
    "gn:asciiname":"Colonia Paul",
    "gn:country_code":"MX",
    "gn:dem":13,
    "gn:feature_class":"P",
    "gn:feature_code":"PPL",
    "gn:name":"Colonia Paul",
    "gn:population":78,
    "gn:timezone":"America/Mazatlan",
    "iso:country":"MX",
    "wof:name":"Colonia Paul",
    "wof:placetype":"locality",
    "wof:population":78
},
  "geometry": {"coordinates":[-108.30143,25.48708],"type":"Point"}
}