{
  "type": "Feature",
  "properties": {
    "gn:admin1_code":"12",
    "gn:admin2_code":"61.0",
    "gn:asciiname":"Zoquiapa",
    "gn:country_code":"MX",
    "gn:dem":1881,
    "gn:feature_class":"P",
    "gn:feature_code":"PPL",
    "gn:name":"Zoquiapa",
    "gn:population":1390,
    "gn:timezone":"America/Mexico_City",
    "iso:country":"MX",
    "wof:name":"Zoquiapa",
    "wof:placetype":"locality",
    "wof:population":1390
},
  "geometry": {"coordinates":[-99.27694,17.54472],"type":"Point"}
}