{
  "type": "Feature",
  "properties": {
    "gn:admin1_code":"25.0",
    "gn:admin2_code":"17.0",
    "gn:asciiname":"Las Palominas",
    "gn:country_code":"MX",
    "gn:dem":411,
    "gn:feature_class":"P",
    "gn:feature_code":"PPL",
    "gn:name":"Las Palominas",
    "gn:population":0,
    "gn:timezone":"America/Mazatlan",
    "iso:country":"MX",
    "name:spa_x_preferred":[
        "Las Palominas"
    ],
    "wof:name":"Las Palominas",
    "wof:placetype":"locality"
},
  "geometry": {"coordinates":[-108.19593,26.22599],"type":"Point"}
}