{
  "type": "Feature",
  "properties": {
    "gn:admin1_code":"14",
    "gn:admin2_code":"35",
    "gn:asciiname":"El Cortijo y las Cavas",
    "gn:country_code":"MX",
    "gn:dem":1836,
    "gn:feature_class":"P",
    "gn:feature_code":"PPL",
    "gn:name":"El Cortijo y las Cavas",
    "gn:population":12,
    "gn:timezone":"America/Mexico_City",
    "iso:country":"MX",
    "wof:name":"El Cortijo y las Cavas",
    "wof:placetype":"locality",
    "wof:population":12
},
  "geometry": {"coordinates":[-102.34944,21.58833],"type":"Point"}
}