{
  "type": "Feature",
  "properties": {
    "gn:admin1_code":"32.0",
    "gn:admin2_code":"8.0",
    "gn:asciiname":"Encinillas",
    "gn:country_code":"MX",
    "gn:dem":2106,
    "gn:feature_class":"P",
    "gn:feature_code":"PPL",
    "gn:name":"Encinillas",
    "gn:population":2,
    "gn:timezone":"America/Mexico_City",
    "iso:country":"MX",
    "name:ast_x_preferred":[
        "Encinillas"
    ],
    "name:cat_x_preferred":[
        "Encinillas"
    ],
    "name:eus_x_preferred":[
        "Encinillas"
    ],
    "name:fra_x_preferred":[
        "Encinillas"
    ],
    "name:hun_x_preferred":[
        "Encinillas"
    ],
    "name:ina_x_preferred":[
        "Encinillas"
    ],
    "name:ita_x_preferred":[
        "Encinillas"
    ],
    "name:msa_x_preferred":[
        "Encinillas"
    ],
    "name:nld_x_preferred":[
        "Encinillas"
    ],
    "name:oci_x_preferred":[
        "Encinillas"
    ],
    "name:pol_x_preferred":[
        "Encinillas"
    ],
    "name:por_x_preferred":[
        "Encinillas"
    ],
    "name:rus_x_preferred":[
        "\u042d\u043d\u0441\u0438\u043d\u0438\u043b\u044c\u044f\u0441"
    ],
    "name:spa_x_preferred":[
        "Encinillas"
    ],
    "name:ukr_x_preferred":[
        "\u0415\u043d\u0441\u0456\u043d\u0456\u043b\u044c\u044f\u0441"
    ],
    "name:vie_x_preferred":[
        "Encinillas"
    ],
    "name:war_x_preferred":[
        "Encinillas"
    ],
    "name:zho_x_preferred":[
        "\u6069\u897f\u5c3c\u5229\u4e9a\u65af"
    ],
    "wof:name":"Encinillas",
    "wof:placetype":"locality",
    "wof:population":2
},
  "geometry": {"coordinates":[-102.34305999999999,22.53583],"type":"Point"}
}