{
  "type": "Feature",
  "properties": {
    "gn:admin1_code":"31",
    "gn:admin2_code":"19.0",
    "gn:asciiname":"Yoactun",
    "gn:country_code":"MX",
    "gn:dem":23,
    "gn:feature_class":"P",
    "gn:feature_code":"PPL",
    "gn:name":"Yoactun",
    "gn:population":0,
    "gn:timezone":"America/Merida",
    "iso:country":"MX",
    "wof:name":"Yoactun",
    "wof:placetype":"locality"
},
  "geometry": {"coordinates":[-87.75,20.7375],"type":"Point"}
}