{
  "type": "Feature",
  "properties": {
    "gn:admin1_code":"7.0",
    "gn:admin2_code":"27.0",
    "gn:asciiname":"El Carmen",
    "gn:country_code":"MX",
    "gn:dem":1308,
    "gn:feature_class":"P",
    "gn:feature_code":"PPL",
    "gn:name":"El Carmen",
    "gn:population":0,
    "gn:timezone":"America/Monterrey",
    "iso:country":"MX",
    "name:spa_x_preferred":[
        "El Carmen"
    ],
    "name:spa_x_variant":[
        "Las Galeras"
    ],
    "name:und_x_variant":[
        "Granja El Carmen"
    ],
    "wof:name":"El Carmen",
    "wof:placetype":"locality"
},
  "geometry": {"coordinates":[-101.0873,25.60185],"type":"Point"}
}