{
  "type": "Feature",
  "properties": {
    "gn:admin1_code":"17.0",
    "gn:asciiname":"Las Cabanas",
    "gn:country_code":"MX",
    "gn:dem":3139,
    "gn:feature_class":"P",
    "gn:feature_code":"PPL",
    "gn:name":"Las Caba\u00f1as",
    "gn:population":0,
    "gn:timezone":"America/Mexico_City",
    "iso:country":"MX",
    "name:spa_x_preferred":[
        "Las Caba\u00f1as"
    ],
    "wof:name":"Las Cabanas",
    "wof:placetype":"locality"
},
  "geometry": {"coordinates":[-99.36561,19.43227000000001],"type":"Point"}
}