{
  "type": "Feature",
  "properties": {
    "gn:admin1_code":"31",
    "gn:admin2_code":"19",
    "gn:asciiname":"Rancho Bonito",
    "gn:country_code":"MX",
    "gn:dem":22,
    "gn:feature_class":"P",
    "gn:feature_code":"PPL",
    "gn:name":"Rancho Bonito",
    "gn:population":15,
    "gn:timezone":"America/Merida",
    "iso:country":"MX",
    "wof:name":"Rancho Bonito",
    "wof:placetype":"locality",
    "wof:population":15
},
  "geometry": {"coordinates":[-87.88028,20.76778],"type":"Point"}
}