{
  "type": "Feature",
  "properties": {
    "gn:admin1_code":"5",
    "gn:admin2_code":"89.0",
    "gn:asciiname":"El Manacal",
    "gn:country_code":"MX",
    "gn:dem":1031,
    "gn:feature_class":"P",
    "gn:feature_code":"PPL",
    "gn:name":"El Manacal",
    "gn:population":0,
    "gn:timezone":"America/Mexico_City",
    "iso:country":"MX",
    "name:und_x_variant":[
        "Manacal"
    ],
    "wof:name":"El Manacal",
    "wof:placetype":"locality"
},
  "geometry": {"coordinates":[-92.21792000000001,15.10298],"type":"Point"}
}