{
  "type": "Feature",
  "properties": {
    "gn:admin1_code":"6",
    "gn:admin2_code":"9.0",
    "gn:asciiname":"El Alamillo",
    "gn:country_code":"MX",
    "gn:dem":2418,
    "gn:feature_class":"P",
    "gn:feature_code":"PPL",
    "gn:name":"El Alamillo",
    "gn:population":8,
    "gn:timezone":"America/Chihuahua",
    "iso:country":"MX",
    "wof:name":"El Alamillo",
    "wof:placetype":"locality",
    "wof:population":8
},
  "geometry": {"coordinates":[-107.69938,27.93019],"type":"Point"}
}