{
  "type": "Feature",
  "properties": {
    "gn:admin1_code":"6.0",
    "gn:admin2_code":"29.0",
    "gn:asciiname":"El Molino",
    "gn:country_code":"MX",
    "gn:dem":2496,
    "gn:feature_class":"P",
    "gn:feature_code":"PPL",
    "gn:name":"El Molino",
    "gn:population":0,
    "gn:timezone":"America/Monterrey",
    "iso:country":"MX",
    "name:spa_x_preferred":[
        "El Molino"
    ],
    "name:und_x_variant":[
        "Rancho El Molino"
    ],
    "wof:name":"El Molino",
    "wof:placetype":"locality"
},
  "geometry": {"coordinates":[-106.47836,26.00848],"type":"Point"}
}