{
  "type": "Feature",
  "properties": {
    "gn:admin1_code":"6",
    "gn:admin2_code":"45",
    "gn:asciiname":"Granja la Nortena",
    "gn:country_code":"MX",
    "gn:dem":1151,
    "gn:feature_class":"P",
    "gn:feature_code":"PPL",
    "gn:name":"Granja la Norte\u00f1a",
    "gn:population":14,
    "gn:timezone":"America/Chihuahua",
    "iso:country":"MX",
    "name:und_x_variant":[
        "Granja la Norte\u00f1a"
    ],
    "wof:name":"Granja la Nortena",
    "wof:placetype":"locality",
    "wof:population":14
},
  "geometry": {"coordinates":[-105.50864,28.25457],"type":"Point"}
}