{
  "type": "Feature",
  "properties": {
    "gn:admin1_code":"3.0",
    "gn:admin2_code":"3.0",
    "gn:asciiname":"San Fermin",
    "gn:country_code":"MX",
    "gn:dem":346,
    "gn:feature_class":"P",
    "gn:feature_code":"PPL",
    "gn:name":"San Ferm\u00edn",
    "gn:population":0,
    "gn:timezone":"America/Mazatlan",
    "iso:country":"MX",
    "name:spa_x_preferred":[
        "San Ferm\u00edn"
    ],
    "name:spa_x_variant":[
        "La Cuesta"
    ],
    "wof:name":"San Fermin",
    "wof:placetype":"locality"
},
  "geometry": {"coordinates":[-110.0625,24.01152],"type":"Point"}
}