{
  "type": "Feature",
  "properties": {
    "gn:admin1_code":"18.0",
    "gn:asciiname":"Palmillas",
    "gn:country_code":"MX",
    "gn:dem":632,
    "gn:feature_class":"P",
    "gn:feature_code":"PPL",
    "gn:name":"Palmillas",
    "gn:population":0,
    "gn:timezone":"America/Mazatlan",
    "iso:country":"MX",
    "name:spa_x_preferred":[
        "Palmillas"
    ],
    "wof:name":"Palmillas",
    "wof:placetype":"locality"
},
  "geometry": {"coordinates":[-104.38383,21.50334],"type":"Point"}
}