{
  "type": "Feature",
  "properties": {
    "gn:admin1_code":"11.0",
    "gn:asciiname":"El Pajarito",
    "gn:country_code":"MX",
    "gn:dem":2013,
    "gn:feature_class":"P",
    "gn:feature_code":"PPL",
    "gn:name":"El Pajarito",
    "gn:population":0,
    "gn:timezone":"America/Mexico_City",
    "iso:country":"MX",
    "name:spa_x_preferred":[
        "El Pajarito"
    ],
    "wof:name":"El Pajarito",
    "wof:placetype":"locality"
},
  "geometry": {"coordinates":[-101.8231,20.44853],"type":"Point"}
}