{
  "type": "Feature",
  "properties": {
    "gn:admin1_code":"13",
    "gn:admin2_code":"28.0",
    "gn:asciiname":"Oxale",
    "gn:country_code":"MX",
    "gn:dem":114,
    "gn:feature_class":"P",
    "gn:feature_code":"PPL",
    "gn:name":"Oxale",
    "gn:population":0,
    "gn:timezone":"America/Mexico_City",
    "iso:country":"MX",
    "name:spa_x_preferred":[
        "Axole"
    ],
    "name:spa_x_variant":[
        "Oxale"
    ],
    "wof:name":"Oxale",
    "wof:placetype":"locality"
},
  "geometry": {"coordinates":[-98.31703,21.09129],"type":"Point"}
}