{
  "type": "Feature",
  "properties": {
    "gn:admin1_code":"11",
    "gn:admin2_code":"23.0",
    "gn:asciiname":"Puerta de Gomez Chica",
    "gn:country_code":"MX",
    "gn:dem":1748,
    "gn:feature_class":"P",
    "gn:feature_code":"PPL",
    "gn:name":"Puerta de G\u00f3mez Chica",
    "gn:population":57,
    "gn:timezone":"America/Mexico_City",
    "iso:country":"MX",
    "name:und_x_variant":[
        "Puerta de G\u00f3mez Chica"
    ],
    "wof:name":"Puerta de Gomez Chica",
    "wof:placetype":"locality",
    "wof:population":57
},
  "geometry": {"coordinates":[-101.73778,20.39],"type":"Point"}
}