{
  "type": "Feature",
  "properties": {
    "gn:admin1_code":"25",
    "gn:admin2_code":"6.0",
    "gn:asciiname":"Monte Verde de Villa (El Verde)",
    "gn:country_code":"MX",
    "gn:dem":167,
    "gn:feature_class":"P",
    "gn:feature_code":"PPL",
    "gn:name":"Monte Verde de Villa (El Verde)",
    "gn:population":340,
    "gn:timezone":"America/Mazatlan",
    "iso:country":"MX",
    "wof:name":"Monte Verde de Villa (El Verde)",
    "wof:placetype":"locality",
    "wof:population":340
},
  "geometry": {"coordinates":[-107.11472000000001,24.60583],"type":"Point"}
}