{
  "type": "Feature",
  "properties": {
    "gn:admin1_code":"10",
    "gn:admin2_code":"32.0",
    "gn:asciiname":"El Naranjito",
    "gn:country_code":"MX",
    "gn:dem":688,
    "gn:feature_class":"P",
    "gn:feature_code":"PPL",
    "gn:name":"El Naranjito",
    "gn:population":0,
    "gn:timezone":"America/Monterrey",
    "iso:country":"MX",
    "name:spa_x_preferred":[
        "El Naranjito"
    ],
    "name:und_x_variant":[
        "Naranjito"
    ],
    "wof:name":"El Naranjito",
    "wof:placetype":"locality"
},
  "geometry": {"coordinates":[-106.40572,24.88414],"type":"Point"}
}