{
  "type": "Feature",
  "properties": {
    "gn:admin1_code":"1.0",
    "gn:admin2_code":"7.0",
    "gn:asciiname":"El Ajiladero",
    "gn:country_code":"MX",
    "gn:dem":2082,
    "gn:feature_class":"P",
    "gn:feature_code":"PPL",
    "gn:name":"El Ajiladero",
    "gn:population":56,
    "gn:timezone":"America/Mexico_City",
    "iso:country":"MX",
    "wof:name":"El Ajiladero",
    "wof:placetype":"locality",
    "wof:population":56
},
  "geometry": {"coordinates":[-102.36139,22.29056],"type":"Point"}
}