{
  "type": "Feature",
  "properties": {
    "gn:admin1_code":"14",
    "gn:admin2_code":"8.0",
    "gn:asciiname":"Los Aviones",
    "gn:country_code":"MX",
    "gn:dem":2046,
    "gn:feature_class":"P",
    "gn:feature_code":"PPL",
    "gn:name":"Los Aviones",
    "gn:population":5,
    "gn:timezone":"America/Mexico_City",
    "iso:country":"MX",
    "wof:name":"Los Aviones",
    "wof:placetype":"locality",
    "wof:population":5
},
  "geometry": {"coordinates":[-102.3425,20.67333],"type":"Point"}
}