{
  "type": "Feature",
  "properties": {
    "gn:admin1_code":"27",
    "gn:admin2_code":"12.0",
    "gn:asciiname":"El Congo",
    "gn:country_code":"MX",
    "gn:dem":22,
    "gn:feature_class":"P",
    "gn:feature_code":"PPL",
    "gn:name":"El Congo",
    "gn:population":0,
    "gn:timezone":"America/Mexico_City",
    "iso:country":"MX",
    "name:ceb_x_preferred":[
        "El Congo"
    ],
    "name:ita_x_preferred":[
        "El Congo"
    ],
    "name:por_x_preferred":[
        "El Congo"
    ],
    "name:spa_x_preferred":[
        "El Congo"
    ],
    "name:zho_x_preferred":[
        "\u57c3\u723e\u5b54\u6208"
    ],
    "wof:name":"El Congo",
    "wof:placetype":"locality"
},
  "geometry": {"coordinates":[-92.43886999999999,17.82522],"type":"Point"}
}