{
  "type": "Feature",
  "properties": {
    "gn:admin1_code":"16",
    "gn:admin2_code":"97.0",
    "gn:asciiname":"El Platano",
    "gn:country_code":"MX",
    "gn:dem":869,
    "gn:feature_class":"P",
    "gn:feature_code":"PPL",
    "gn:name":"El Pl\u00e1tano",
    "gn:population":0,
    "gn:timezone":"America/Mexico_City",
    "iso:country":"MX",
    "name:spa_x_preferred":[
        "El Pl\u00e1tano"
    ],
    "wof:name":"El Platano",
    "wof:placetype":"locality"
},
  "geometry": {"coordinates":[-101.41115000000001,18.80902],"type":"Point"}
}