{
  "type": "Feature",
  "properties": {
    "gn:admin1_code":"30",
    "gn:admin2_code":"148",
    "gn:asciiname":"Mata Bruja",
    "gn:country_code":"MX",
    "gn:dem":141,
    "gn:feature_class":"P",
    "gn:feature_code":"PPL",
    "gn:name":"Mata Bruja",
    "gn:population":31,
    "gn:timezone":"America/Mexico_City",
    "iso:country":"MX",
    "wof:name":"Mata Bruja",
    "wof:placetype":"locality",
    "wof:population":31
},
  "geometry": {"coordinates":[-96.45694,18.9975],"type":"Point"}
}