{
  "type": "Feature",
  "properties": {
    "gn:admin1_code":"19",
    "gn:admin2_code":"30.0",
    "gn:asciiname":"La Colorada",
    "gn:country_code":"MX",
    "gn:dem":1691,
    "gn:feature_class":"P",
    "gn:feature_code":"PPL",
    "gn:name":"La Colorada",
    "gn:population":0,
    "gn:timezone":"America/Monterrey",
    "iso:country":"MX",
    "name:ceb_x_preferred":[
        "La Colorada"
    ],
    "name:deu_x_preferred":[
        "La Colorada"
    ],
    "name:ita_x_preferred":[
        "La Colorada"
    ],
    "name:spa_x_preferred":[
        "La Colorada"
    ],
    "name:swe_x_preferred":[
        "La Colorada"
    ],
    "wof:name":"La Colorada",
    "wof:placetype":"locality"
},
  "geometry": {"coordinates":[-99.94064,24.7512],"type":"Point"}
}