{
  "type": "Feature",
  "properties": {
    "gn:admin1_code":"21",
    "gn:admin2_code":"36.0",
    "gn:asciiname":"Ahuatla",
    "gn:country_code":"MX",
    "gn:dem":2021,
    "gn:feature_class":"P",
    "gn:feature_code":"PPL",
    "gn:name":"Ahuatla",
    "gn:population":490,
    "gn:timezone":"America/Mexico_City",
    "iso:country":"MX",
    "wof:name":"Ahuatla",
    "wof:placetype":"locality",
    "wof:population":490
},
  "geometry": {"coordinates":[-96.98148999999999,18.29198],"type":"Point"}
}