{
  "type": "Feature",
  "properties": {
    "gn:admin1_code":"30",
    "gn:admin2_code":"147.0",
    "gn:asciiname":"Huixtitla",
    "gn:country_code":"MX",
    "gn:dem":1955,
    "gn:feature_class":"P",
    "gn:feature_code":"PPL",
    "gn:name":"Huixtitla",
    "gn:population":0,
    "gn:timezone":"America/Mexico_City",
    "iso:country":"MX",
    "name:spa_x_preferred":[
        "Los Horcones"
    ],
    "name:spa_x_variant":[
        "Huitztitla",
        "Huixtitla"
    ],
    "wof:name":"Huixtitla",
    "wof:placetype":"locality"
},
  "geometry": {"coordinates":[-97.19327,18.75037],"type":"Point"}
}