{
  "type": "Feature",
  "properties": {
    "gn:admin1_code":"24",
    "gn:admin2_code":"25.0",
    "gn:asciiname":"El Palomar",
    "gn:country_code":"MX",
    "gn:dem":2128,
    "gn:feature_class":"P",
    "gn:feature_code":"PPL",
    "gn:name":"El Palomar",
    "gn:population":9,
    "gn:timezone":"America/Mexico_City",
    "iso:country":"MX",
    "wof:name":"El Palomar",
    "wof:placetype":"locality",
    "wof:population":9
},
  "geometry": {"coordinates":[-101.71083,22.57778],"type":"Point"}
}