{
  "type": "Feature",
  "properties": {
    "gn:admin1_code":"28.0",
    "gn:admin2_code":"3.0",
    "gn:asciiname":"Monte Verde",
    "gn:country_code":"MX",
    "gn:dem":61,
    "gn:feature_class":"P",
    "gn:feature_code":"PPL",
    "gn:name":"Monte Verde",
    "gn:population":0,
    "gn:timezone":"America/Monterrey",
    "iso:country":"MX",
    "name:spa_x_preferred":[
        "Monte Verde"
    ],
    "wof:name":"Monte Verde",
    "wof:placetype":"locality"
},
  "geometry": {"coordinates":[-98.11159000000001,22.70794],"type":"Point"}
}