{
  "type": "Feature",
  "properties": {
    "gn:admin1_code":"25",
    "gn:admin2_code":"7.0",
    "gn:asciiname":"Techobampo de los Paredes",
    "gn:country_code":"MX",
    "gn:dem":395,
    "gn:feature_class":"P",
    "gn:feature_code":"PPL",
    "gn:name":"Techobampo de los Paredes",
    "gn:population":0,
    "gn:timezone":"America/Mazatlan",
    "iso:country":"MX",
    "name:spa_x_preferred":[
        "Techobampo de los Paredes"
    ],
    "name:spa_x_variant":[
        "El Cedrito"
    ],
    "wof:name":"Techobampo de los Paredes",
    "wof:placetype":"locality"
},
  "geometry": {"coordinates":[-108.31592000000001,26.84892],"type":"Point"}
}