{
  "type": "Feature",
  "properties": {
    "gn:admin1_code":"28",
    "gn:admin2_code":"42.0",
    "gn:asciiname":"El Progreso",
    "gn:country_code":"MX",
    "gn:dem":312,
    "gn:feature_class":"P",
    "gn:feature_code":"PPL",
    "gn:name":"El Progreso",
    "gn:population":0,
    "gn:timezone":"America/Monterrey",
    "iso:country":"MX",
    "name:spa_x_preferred":[
        "El Progreso"
    ],
    "wof:name":"El Progreso",
    "wof:placetype":"locality"
},
  "geometry": {"coordinates":[-99.40224000000001,24.40483],"type":"Point"}
}