{
  "type": "Feature",
  "properties": {
    "gn:admin1_code":"16.0",
    "gn:admin2_code":"92.0",
    "gn:asciiname":"La Calzada",
    "gn:country_code":"MX",
    "gn:dem":811,
    "gn:feature_class":"P",
    "gn:feature_code":"PPL",
    "gn:name":"La Calzada",
    "gn:population":0,
    "gn:timezone":"America/Mexico_City",
    "iso:country":"MX",
    "name:spa_x_preferred":[
        "La Calzada"
    ],
    "wof:name":"La Calzada",
    "wof:placetype":"locality"
},
  "geometry": {"coordinates":[-100.53807999999999,19.023],"type":"Point"}
}