{
  "type": "Feature",
  "properties": {
    "gn:admin1_code":"5",
    "gn:admin2_code":"109",
    "gn:asciiname":"Limbano Utrilla",
    "gn:country_code":"MX",
    "gn:dem":893,
    "gn:feature_class":"P",
    "gn:feature_code":"PPL",
    "gn:name":"L\u00edmbano Utrilla",
    "gn:population":18,
    "gn:timezone":"America/Mexico_City",
    "iso:country":"MX",
    "name:und_x_variant":[
        "L\u00edmbano Utrilla"
    ],
    "wof:name":"Limbano Utrilla",
    "wof:placetype":"locality",
    "wof:population":18
},
  "geometry": {"coordinates":[-92.33722,17.18889],"type":"Point"}
}