{
  "type": "Feature",
  "properties": {
    "gn:admin1_code":"32",
    "gn:admin2_code":"34.0",
    "gn:asciiname":"La Canteria",
    "gn:country_code":"MX",
    "gn:dem":1911,
    "gn:feature_class":"P",
    "gn:feature_code":"PPL",
    "gn:name":"La Canter\u00eda",
    "gn:population":8,
    "gn:timezone":"America/Mexico_City",
    "iso:country":"MX",
    "name:und_x_variant":[
        "La Canter\u00eda"
    ],
    "wof:name":"La Canteria",
    "wof:placetype":"locality",
    "wof:population":8
},
  "geometry": {"coordinates":[-102.72083000000001,21.44389],"type":"Point"}
}