{
  "type": "Feature",
  "properties": {
    "gn:admin1_code":"31",
    "gn:admin2_code":"32.0",
    "gn:asciiname":"Lahchen",
    "gn:country_code":"MX",
    "gn:dem":23,
    "gn:feature_class":"P",
    "gn:feature_code":"PPL",
    "gn:name":"Lahch\u00e9n",
    "gn:population":0,
    "gn:timezone":"America/Merida",
    "iso:country":"MX",
    "name:spa_x_preferred":[
        "Lahch\u00e9n"
    ],
    "name:spa_x_variant":[
        "Labchen"
    ],
    "name:und_x_variant":[
        "Labch\u00e9n"
    ],
    "wof:name":"Lahchen",
    "wof:placetype":"locality"
},
  "geometry": {"coordinates":[-88.32095,21.00536],"type":"Point"}
}