{
  "type": "Feature",
  "properties": {
    "gn:admin1_code":"4.0",
    "gn:admin2_code":"9.0",
    "gn:asciiname":"El Zacatecano",
    "gn:country_code":"MX",
    "gn:dem":50,
    "gn:feature_class":"P",
    "gn:feature_code":"PPL",
    "gn:name":"El Zacatecano",
    "gn:population":0,
    "gn:timezone":"America/Merida",
    "iso:country":"MX",
    "name:spa_x_preferred":[
        "El Mirador"
    ],
    "name:spa_x_variant":[
        "El Zacatecano"
    ],
    "wof:name":"El Zacatecano",
    "wof:placetype":"locality"
},
  "geometry": {"coordinates":[-91.00403,18.43729],"type":"Point"}
}