{
  "type": "Feature",
  "properties": {
    "gn:admin1_code":"5",
    "gn:admin2_code":"12.0",
    "gn:asciiname":"Santa Ines",
    "gn:country_code":"MX",
    "gn:dem":900,
    "gn:feature_class":"P",
    "gn:feature_code":"PPL",
    "gn:name":"Santa In\u00e9s",
    "gn:population":0,
    "gn:timezone":"America/Mexico_City",
    "iso:country":"MX",
    "name:spa_x_preferred":[
        "Santa In\u00e9s"
    ],
    "wof:name":"Santa Ines",
    "wof:placetype":"locality"
},
  "geometry": {"coordinates":[-93.27346,16.76451],"type":"Point"}
}