{
  "type": "Feature",
  "properties": {
    "gn:admin1_code":"16.0",
    "gn:admin2_code":"28.0",
    "gn:asciiname":"El Fuerte",
    "gn:country_code":"MX",
    "gn:dem":1789,
    "gn:feature_class":"P",
    "gn:feature_code":"PPL",
    "gn:name":"El Fuerte",
    "gn:population":0,
    "gn:timezone":"America/Mexico_City",
    "iso:country":"MX",
    "wof:name":"El Fuerte",
    "wof:placetype":"locality"
},
  "geometry": {"coordinates":[-102.10993999999999,20.14563],"type":"Point"}
}