{
  "type": "Feature",
  "properties": {
    "gn:admin1_code":"32",
    "gn:admin2_code":"6.0",
    "gn:asciiname":"El Vivero",
    "gn:country_code":"MX",
    "gn:dem":2009,
    "gn:feature_class":"P",
    "gn:feature_code":"PPL",
    "gn:name":"El Vivero",
    "gn:population":0,
    "gn:timezone":"America/Mexico_City",
    "iso:country":"MX",
    "name:spa_x_preferred":[
        "El Vivero"
    ],
    "wof:name":"El Vivero",
    "wof:placetype":"locality"
},
  "geometry": {"coordinates":[-102.72297,23.61325],"type":"Point"}
}