{
  "type": "Feature",
  "properties": {
    "gn:admin1_code":"6",
    "gn:admin2_code":"46.0",
    "gn:asciiname":"La Palmita",
    "gn:country_code":"MX",
    "gn:dem":1530,
    "gn:feature_class":"P",
    "gn:feature_code":"PPL",
    "gn:name":"La Palmita",
    "gn:population":5,
    "gn:timezone":"America/Chihuahua",
    "iso:country":"MX",
    "wof:name":"La Palmita",
    "wof:placetype":"locality",
    "wof:population":5
},
  "geometry": {"coordinates":[-107.77043999999999,26.67105],"type":"Point"}
}