{
  "type": "Feature",
  "properties": {
    "gn:admin1_code":"5",
    "gn:admin2_code":"30",
    "gn:asciiname":"Veracruz",
    "gn:country_code":"MX",
    "gn:dem":604,
    "gn:feature_class":"P",
    "gn:feature_code":"PPL",
    "gn:name":"Veracruz",
    "gn:population":32,
    "gn:timezone":"America/Mexico_City",
    "iso:country":"MX",
    "wof:name":"Veracruz",
    "wof:placetype":"locality",
    "wof:population":32
},
  "geometry": {"coordinates":[-92.32666999999999,15.73194],"type":"Point"}
}