{
  "type": "Feature",
  "properties": {
    "gn:admin1_code":"10.0",
    "gn:admin2_code":"13.0",
    "gn:asciiname":"Las Magdalenas",
    "gn:country_code":"MX",
    "gn:dem":1188,
    "gn:feature_class":"P",
    "gn:feature_code":"PPL",
    "gn:name":"Las Magdalenas",
    "gn:population":0,
    "gn:timezone":"America/Monterrey",
    "iso:country":"MX",
    "name:spa_x_preferred":[
        "Las Magdalenas"
    ],
    "wof:name":"Las Magdalenas",
    "wof:placetype":"locality"
},
  "geometry": {"coordinates":[-104.202,26.59597],"type":"Point"}
}