{
  "type": "Feature",
  "properties": {
    "gn:admin1_code":"30",
    "gn:admin2_code":"90.0",
    "gn:asciiname":"El Tropel",
    "gn:country_code":"MX",
    "gn:dem":21,
    "gn:feature_class":"P",
    "gn:feature_code":"PPL",
    "gn:name":"El Tropel",
    "gn:population":8,
    "gn:timezone":"America/Mexico_City",
    "iso:country":"MX",
    "wof:name":"El Tropel",
    "wof:placetype":"locality",
    "wof:population":8
},
  "geometry": {"coordinates":[-96.23417000000001,19.04722000000001],"type":"Point"}
}