{
  "type": "Feature",
  "properties": {
    "gn:admin1_code":"7",
    "gn:admin2_code":"28.0",
    "gn:asciiname":"Riva Palacio",
    "gn:country_code":"MX",
    "gn:dem":396,
    "gn:feature_class":"P",
    "gn:feature_code":"PPL",
    "gn:name":"Riva Palacio",
    "gn:population":0,
    "gn:timezone":"America/Monterrey",
    "iso:country":"MX",
    "name:ceb_x_preferred":[
        "Riva Palacio"
    ],
    "name:deu_x_preferred":[
        "Riva Palacio"
    ],
    "name:rus_x_preferred":[
        "\u0420\u0438\u0432\u0430-\u041f\u0430\u043b\u0430\u0441\u0438\u043e"
    ],
    "name:spa_x_preferred":[
        "Riva Palacio"
    ],
    "name:swe_x_preferred":[
        "Riva Palacio"
    ],
    "wof:name":"Riva Palacio",
    "wof:placetype":"locality"
},
  "geometry": {"coordinates":[-101.00149999999999,27.92677],"type":"Point"}
}