{
  "type": "Feature",
  "properties": {
    "gn:admin1_code":"13",
    "gn:admin2_code":"12.0",
    "gn:asciiname":"Rincon Xathe",
    "gn:country_code":"MX",
    "gn:dem":2023,
    "gn:feature_class":"P",
    "gn:feature_code":"PPL",
    "gn:name":"Rinc\u00f3n Xath\u00e9",
    "gn:population":0,
    "gn:timezone":"America/Mexico_City",
    "iso:country":"MX",
    "name:spa_x_preferred":[
        "Rinc\u00f3n Xath\u00e9"
    ],
    "wof:name":"Rincon Xathe",
    "wof:placetype":"locality"
},
  "geometry": {"coordinates":[-98.76327000000001,20.41789],"type":"Point"}
}