{
  "type": "Feature",
  "properties": {
    "gn:admin1_code":"14",
    "gn:admin2_code":"124.0",
    "gn:asciiname":"San Isidro (El Trompillo)",
    "gn:country_code":"MX",
    "gn:dem":1580,
    "gn:feature_class":"P",
    "gn:feature_code":"PPL",
    "gn:name":"San Isidro (El Trompillo)",
    "gn:population":65,
    "gn:timezone":"America/Mexico_City",
    "iso:country":"MX",
    "wof:name":"San Isidro (El Trompillo)",
    "wof:placetype":"locality",
    "wof:population":65
},
  "geometry": {"coordinates":[-103.17083,20.7075],"type":"Point"}
}