{
  "type": "Feature",
  "properties": {
    "gn:admin1_code":"5.0",
    "gn:asciiname":"Crucero Zaragoza",
    "gn:country_code":"MX",
    "gn:dem":19,
    "gn:feature_class":"P",
    "gn:feature_code":"PPL",
    "gn:name":"Crucero Zaragoza",
    "gn:population":0,
    "gn:timezone":"America/Mexico_City",
    "iso:country":"MX",
    "name:spa_x_preferred":[
        "Crucero Zaragoza"
    ],
    "wof:name":"Crucero Zaragoza",
    "wof:placetype":"locality"
},
  "geometry": {"coordinates":[-91.98314000000001,17.72142999999999],"type":"Point"}
}