{
  "type": "Feature",
  "properties": {
    "gn:admin1_code":"14.0",
    "gn:admin2_code":"35.0",
    "gn:asciiname":"La Puerta del Cuervo",
    "gn:country_code":"MX",
    "gn:dem":1770,
    "gn:feature_class":"P",
    "gn:feature_code":"PPL",
    "gn:name":"La Puerta del Cuervo",
    "gn:population":0,
    "gn:timezone":"America/Mexico_City",
    "iso:country":"MX",
    "name:spa_x_preferred":[
        "La Puerta del Cuervo"
    ],
    "wof:name":"La Puerta del Cuervo",
    "wof:placetype":"locality"
},
  "geometry": {"coordinates":[-102.30670000000001,21.51741],"type":"Point"}
}