{
  "type": "Feature",
  "properties": {
    "gn:admin1_code":"21",
    "gn:admin2_code":"208.0",
    "gn:asciiname":"Xoxonacatla",
    "gn:country_code":"MX",
    "gn:dem":2009,
    "gn:feature_class":"P",
    "gn:feature_code":"PPL",
    "gn:name":"Xoxonacatla",
    "gn:population":2007,
    "gn:timezone":"America/Mexico_City",
    "iso:country":"MX",
    "wof:name":"Xoxonacatla",
    "wof:placetype":"locality",
    "wof:population":2007
},
  "geometry": {"coordinates":[-97.94056,20.0075],"type":"Point"}
}