{
  "type": "Feature",
  "properties": {
    "gn:admin1_code":"14.0",
    "gn:admin2_code":"110.0",
    "gn:asciiname":"El Novillero",
    "gn:country_code":"MX",
    "gn:dem":1345,
    "gn:feature_class":"P",
    "gn:feature_code":"PPL",
    "gn:name":"El Novillero",
    "gn:population":0,
    "gn:timezone":"America/Mexico_City",
    "iso:country":"MX",
    "name:spa_x_preferred":[
        "El Novillero"
    ],
    "wof:name":"El Novillero",
    "wof:placetype":"locality"
},
  "geometry": {"coordinates":[-104.28865,19.96028],"type":"Point"}
}