{
  "type": "Feature",
  "properties": {
    "gn:admin1_code":"4",
    "gn:admin2_code":"3.0",
    "gn:asciiname":"Fernando Foglio Miramontes",
    "gn:country_code":"MX",
    "gn:dem":1,
    "gn:feature_class":"P",
    "gn:feature_code":"PPL",
    "gn:name":"Fernando Foglio Miramontes",
    "gn:population":96,
    "gn:timezone":"America/Merida",
    "iso:country":"MX",
    "wof:name":"Fernando Foglio Miramontes",
    "wof:placetype":"locality",
    "wof:population":96
},
  "geometry": {"coordinates":[-91.61167,18.32306],"type":"Point"}
}