{
  "type": "Feature",
  "properties": {
    "gn:admin1_code":"14.0",
    "gn:admin2_code":"54.0",
    "gn:asciiname":"Mateo Guzman",
    "gn:country_code":"MX",
    "gn:dem":836,
    "gn:feature_class":"P",
    "gn:feature_code":"PPL",
    "gn:name":"Mateo Guzm\u00e1n",
    "gn:population":0,
    "gn:timezone":"America/Mexico_City",
    "iso:country":"MX",
    "name:spa_x_preferred":[
        "Mateo Guzm\u00e1n"
    ],
    "name:spa_x_variant":[
        "La Amolera"
    ],
    "wof:name":"Mateo Guzman",
    "wof:placetype":"locality"
},
  "geometry": {"coordinates":[-104.12936999999999,19.81826],"type":"Point"}
}