{
  "type": "Feature",
  "properties": {
    "gn:admin1_code":"5",
    "gn:admin2_code":"59.0",
    "gn:asciiname":"Carmen Tajaltic",
    "gn:country_code":"MX",
    "gn:dem":767,
    "gn:feature_class":"P",
    "gn:feature_code":"PPL",
    "gn:name":"Carmen Tajaltic",
    "gn:population":116,
    "gn:timezone":"America/Mexico_City",
    "iso:country":"MX",
    "wof:name":"Carmen Tajaltic",
    "wof:placetype":"locality",
    "wof:population":116
},
  "geometry": {"coordinates":[-91.82611,16.96778],"type":"Point"}
}