{
  "type": "Feature",
  "properties": {
    "gn:admin1_code":"30",
    "gn:admin2_code":"182",
    "gn:asciiname":"El Timbre",
    "gn:country_code":"MX",
    "gn:dem":1482,
    "gn:feature_class":"P",
    "gn:feature_code":"PPL",
    "gn:name":"El Timbre",
    "gn:population":12,
    "gn:timezone":"America/Mexico_City",
    "iso:country":"MX",
    "wof:name":"El Timbre",
    "wof:placetype":"locality",
    "wof:population":12
},
  "geometry": {"coordinates":[-96.98333,19.5125],"type":"Point"}
}