{
  "type": "Feature",
  "properties": {
    "gn:admin1_code":"28.0",
    "gn:admin2_code":"41.0",
    "gn:asciiname":"Dieciocho de Marzo",
    "gn:country_code":"MX",
    "gn:dem":220,
    "gn:feature_class":"P",
    "gn:feature_code":"PPL",
    "gn:name":"Dieciocho de Marzo",
    "gn:population":73,
    "gn:timezone":"America/Monterrey",
    "iso:country":"MX",
    "name:spa_x_preferred":[
        "Dieciocho de Marzo"
    ],
    "wof:name":"Dieciocho de Marzo",
    "wof:placetype":"locality",
    "wof:population":73
},
  "geometry": {"coordinates":[-99.03833,23.77278],"type":"Point"}
}