{
  "type": "Feature",
  "properties": {
    "gn:admin1_code":"30",
    "gn:admin2_code":"158.0",
    "gn:asciiname":"Juan Arambulo Hernandez",
    "gn:country_code":"MX",
    "gn:dem":6,
    "gn:feature_class":"P",
    "gn:feature_code":"PPL",
    "gn:name":"Juan Arambulo Hern\u00e1ndez",
    "gn:population":7,
    "gn:timezone":"America/Mexico_City",
    "iso:country":"MX",
    "name:und_x_variant":[
        "Juan Arambulo Hern\u00e1ndez"
    ],
    "wof:name":"Juan Arambulo Hernandez",
    "wof:placetype":"locality",
    "wof:population":7
},
  "geometry": {"coordinates":[-96.96693999999999,20.43028],"type":"Point"}
}