{
  "type": "Feature",
  "properties": {
    "gn:admin1_code":"7",
    "gn:admin2_code":"31.0",
    "gn:asciiname":"El Colorado",
    "gn:country_code":"MX",
    "gn:dem":1125,
    "gn:feature_class":"P",
    "gn:feature_code":"PPL",
    "gn:name":"El Colorado",
    "gn:population":0,
    "gn:timezone":"America/Monterrey",
    "iso:country":"MX",
    "name:deu_x_preferred":[
        "El Colorado"
    ],
    "name:fra_x_preferred":[
        "El Colorado"
    ],
    "name:nld_x_preferred":[
        "El Colorado"
    ],
    "name:pol_x_preferred":[
        "El Colorado"
    ],
    "name:por_x_preferred":[
        "El Colorado"
    ],
    "name:spa_x_preferred":[
        "El Colorado"
    ],
    "name:und_x_variant":[
        "Sierra Colorada",
        "Hacienda Sierra Colorada"
    ],
    "wof:name":"El Colorado",
    "wof:placetype":"locality"
},
  "geometry": {"coordinates":[-102.19538,28.10769],"type":"Point"}
}