{
  "type": "Feature",
  "properties": {
    "gn:admin1_code":"16",
    "gn:admin2_code":"9",
    "gn:asciiname":"La Bodega (Las Mesas)",
    "gn:country_code":"MX",
    "gn:dem":1937,
    "gn:feature_class":"P",
    "gn:feature_code":"PPL",
    "gn:name":"La Bodega (Las Mesas)",
    "gn:population":14,
    "gn:timezone":"America/Mexico_City",
    "iso:country":"MX",
    "wof:name":"La Bodega (Las Mesas)",
    "wof:placetype":"locality",
    "wof:population":14
},
  "geometry": {"coordinates":[-101.74361,19.27722],"type":"Point"}
}