{
  "type": "Feature",
  "properties": {
    "gn:admin1_code":"14",
    "gn:admin2_code":"53",
    "gn:asciiname":"Santa Emilia",
    "gn:country_code":"MX",
    "gn:dem":1866,
    "gn:feature_class":"P",
    "gn:feature_code":"PPL",
    "gn:name":"Santa Emilia",
    "gn:population":11,
    "gn:timezone":"America/Mexico_City",
    "iso:country":"MX",
    "wof:name":"Santa Emilia",
    "wof:placetype":"locality",
    "wof:population":11
},
  "geometry": {"coordinates":[-101.96917000000001,21.30611],"type":"Point"}
}