{
  "type": "Feature",
  "properties": {
    "gn:admin1_code":"24",
    "gn:admin2_code":"57.0",
    "gn:asciiname":"Texquitote Primero",
    "gn:country_code":"MX",
    "gn:dem":259,
    "gn:feature_class":"P",
    "gn:feature_code":"PPL",
    "gn:name":"Texquitote Primero",
    "gn:population":772,
    "gn:timezone":"America/Mexico_City",
    "iso:country":"MX",
    "wof:name":"Texquitote Primero",
    "wof:placetype":"locality",
    "wof:population":772
},
  "geometry": {"coordinates":[-98.80110999999999,21.29778],"type":"Point"}
}