{
  "type": "Feature",
  "properties": {
    "gn:admin1_code":"32",
    "gn:admin2_code":"20.0",
    "gn:asciiname":"Rancho de los Rios",
    "gn:country_code":"MX",
    "gn:dem":2030,
    "gn:feature_class":"P",
    "gn:feature_code":"PPL",
    "gn:name":"Rancho de los R\u00edos",
    "gn:population":0,
    "gn:timezone":"America/Mexico_City",
    "iso:country":"MX",
    "wof:name":"Rancho de los Rios",
    "wof:placetype":"locality"
},
  "geometry": {"coordinates":[-102.97535999999999,22.57669],"type":"Point"}
}