{
  "type": "Feature",
  "properties": {
    "gn:admin1_code":"15.0",
    "gn:asciiname":"El Colector",
    "gn:country_code":"MX",
    "gn:dem":2582,
    "gn:feature_class":"P",
    "gn:feature_code":"PPL",
    "gn:name":"El Colector",
    "gn:population":0,
    "gn:timezone":"America/Mexico_City",
    "iso:country":"MX",
    "name:spa_x_preferred":[
        "El Colector"
    ],
    "wof:name":"El Colector",
    "wof:placetype":"locality"
},
  "geometry": {"coordinates":[-99.64913,19.56703],"type":"Point"}
}