{
  "type": "Feature",
  "properties": {
    "gn:admin1_code":"15",
    "gn:admin2_code":"9.0",
    "gn:asciiname":"Tenexcaltitla",
    "gn:country_code":"MX",
    "gn:dem":2531,
    "gn:feature_class":"P",
    "gn:feature_code":"PPL",
    "gn:name":"Tenexcaltitla",
    "gn:population":5,
    "gn:timezone":"America/Mexico_City",
    "iso:country":"MX",
    "wof:name":"Tenexcaltitla",
    "wof:placetype":"locality",
    "wof:population":5
},
  "geometry": {"coordinates":[-98.79589,19.07954],"type":"Point"}
}