{
  "type": "Feature",
  "properties": {
    "gn:admin1_code":"30.0",
    "gn:admin2_code":"60.0",
    "gn:asciiname":"El Corpo",
    "gn:country_code":"MX",
    "gn:dem":28,
    "gn:feature_class":"P",
    "gn:feature_code":"PPL",
    "gn:name":"El Corpo",
    "gn:population":0,
    "gn:timezone":"America/Mexico_City",
    "iso:country":"MX",
    "name:spa_x_preferred":[
        "El Corpo"
    ],
    "name:spa_x_variant":[
        "San Jos\u00e9"
    ],
    "wof:name":"El Corpo",
    "wof:placetype":"locality"
},
  "geometry": {"coordinates":[-97.65751,21.41034],"type":"Point"}
}