{
  "type": "Feature",
  "properties": {
    "gn:admin1_code":"5",
    "gn:admin2_code":"7",
    "gn:asciiname":"Guadalupe Porvenir",
    "gn:country_code":"MX",
    "gn:dem":2357,
    "gn:feature_class":"P",
    "gn:feature_code":"PPL",
    "gn:name":"Guadalupe Porvenir",
    "gn:population":45,
    "gn:timezone":"America/Mexico_City",
    "iso:country":"MX",
    "wof:name":"Guadalupe Porvenir",
    "wof:placetype":"locality",
    "wof:population":45
},
  "geometry": {"coordinates":[-92.32583,16.47667],"type":"Point"}
}