{
  "type": "Feature",
  "properties": {
    "gn:admin1_code":"20",
    "gn:admin2_code":"44.0",
    "gn:asciiname":"Guadalupe Cristo",
    "gn:country_code":"MX",
    "gn:dem":39,
    "gn:feature_class":"P",
    "gn:feature_code":"PPL",
    "gn:name":"Guadalupe Cristo",
    "gn:population":5,
    "gn:timezone":"America/Mexico_City",
    "iso:country":"MX",
    "wof:name":"Guadalupe Cristo",
    "wof:placetype":"locality",
    "wof:population":5
},
  "geometry": {"coordinates":[-95.83556,18.07722],"type":"Point"}
}