{
  "type": "Feature",
  "properties": {
    "gn:admin1_code":"30.0",
    "gn:asciiname":"La Panga",
    "gn:country_code":"MX",
    "gn:dem":38,
    "gn:feature_class":"P",
    "gn:feature_code":"PPL",
    "gn:name":"La Panga",
    "gn:population":0,
    "gn:timezone":"America/Mexico_City",
    "iso:country":"MX",
    "name:spa_x_preferred":[
        "La Panga"
    ],
    "name:spa_x_variant":[
        "Panga"
    ],
    "wof:name":"La Panga",
    "wof:placetype":"locality"
},
  "geometry": {"coordinates":[-95.76499,17.86899],"type":"Point"}
}