{
  "type": "Feature",
  "properties": {
    "gn:admin1_code":"5",
    "gn:admin2_code":"52.0",
    "gn:asciiname":"Rosario Santiago",
    "gn:country_code":"MX",
    "gn:dem":2048,
    "gn:feature_class":"P",
    "gn:feature_code":"PPL",
    "gn:name":"Rosario Santiago",
    "gn:population":54,
    "gn:timezone":"America/Mexico_City",
    "iso:country":"MX",
    "wof:name":"Rosario Santiago",
    "wof:placetype":"locality",
    "wof:population":54
},
  "geometry": {"coordinates":[-91.93048,16.5203],"type":"Point"}
}