{
  "type": "Feature",
  "properties": {
    "gn:admin1_code":"5",
    "gn:admin2_code":"89.0",
    "gn:asciiname":"Janitzio",
    "gn:country_code":"MX",
    "gn:dem":37,
    "gn:feature_class":"P",
    "gn:feature_code":"PPL",
    "gn:name":"Janitzio",
    "gn:population":5,
    "gn:timezone":"America/Mexico_City",
    "iso:country":"MX",
    "name:eus_x_preferred":[
        "Janitzio"
    ],
    "name:hun_x_preferred":[
        "Janitzio"
    ],
    "name:nld_x_preferred":[
        "Janitzio"
    ],
    "name:nor_x_preferred":[
        "Janitzio"
    ],
    "name:rus_x_preferred":[
        "\u0425\u0430\u043d\u0438\u0446\u0438\u043e"
    ],
    "name:spa_x_preferred":[
        "Janitzio"
    ],
    "name:tha_x_preferred":[
        "\u0e40\u0e01\u0e32\u0e30\u0e06\u0e32\u0e19\u0e34\u0e15\u0e0b\u0e34\u0e42\u0e2d"
    ],
    "name:ukr_x_preferred":[
        "\u0425\u0430\u043d\u0456\u0446\u0456\u043e"
    ],
    "wof:name":"Janitzio",
    "wof:placetype":"locality",
    "wof:population":5
},
  "geometry": {"coordinates":[-92.35805999999999,14.83083],"type":"Point"}
}