{
  "type": "Feature",
  "properties": {
    "gn:admin1_code":"32",
    "gn:admin2_code":"17.0",
    "gn:asciiname":"Colonia Osiris",
    "gn:country_code":"MX",
    "gn:dem":2187,
    "gn:feature_class":"P",
    "gn:feature_code":"PPL",
    "gn:name":"Colonia Osiris",
    "gn:population":220,
    "gn:timezone":"America/Mexico_City",
    "iso:country":"MX",
    "wof:name":"Colonia Osiris",
    "wof:placetype":"locality",
    "wof:population":220
},
  "geometry": {"coordinates":[-102.45444000000001,22.765],"type":"Point"}
}