{
  "type": "Feature",
  "properties": {
    "gn:admin1_code":"27",
    "gn:admin2_code":"6.0",
    "gn:asciiname":"La Piedra 2da. Seccion (La Candelaria)",
    "gn:country_code":"MX",
    "gn:dem":19,
    "gn:feature_class":"P",
    "gn:feature_code":"PPL",
    "gn:name":"La Piedra 2da. Secci\u00f3n (La Candelaria)",
    "gn:population":352,
    "gn:timezone":"America/Mexico_City",
    "iso:country":"MX",
    "name:und_x_variant":[
        "La Piedra 2da. Secci\u00f3n (La Candelaria)"
    ],
    "wof:name":"La Piedra 2da. Seccion (La Candelaria)",
    "wof:placetype":"locality",
    "wof:population":352
},
  "geometry": {"coordinates":[-93.19944,18.11639],"type":"Point"}
}