{
  "type": "Feature",
  "properties": {
    "gn:admin1_code":"21",
    "gn:admin2_code":"76.0",
    "gn:asciiname":"Paxta",
    "gn:country_code":"MX",
    "gn:dem":400,
    "gn:feature_class":"P",
    "gn:feature_code":"PPL",
    "gn:name":"Paxta",
    "gn:population":0,
    "gn:timezone":"America/Mexico_City",
    "iso:country":"MX",
    "name:und_x_variant":[
        "Puxtla",
        "Paxta"
    ],
    "wof:name":"Paxta",
    "wof:placetype":"locality"
},
  "geometry": {"coordinates":[-97.2289,20.01285],"type":"Point"}
}