{
  "type": "Feature",
  "properties": {
    "gn:admin1_code":"32",
    "gn:admin2_code":"54",
    "gn:asciiname":"Los Saucitos",
    "gn:country_code":"MX",
    "gn:dem":2115,
    "gn:feature_class":"P",
    "gn:feature_code":"PPL",
    "gn:name":"Los Saucitos",
    "gn:population":31,
    "gn:timezone":"America/Mexico_City",
    "iso:country":"MX",
    "wof:name":"Los Saucitos",
    "wof:placetype":"locality",
    "wof:population":31
},
  "geometry": {"coordinates":[-101.77,22.36778],"type":"Point"}
}