{
  "type": "Feature",
  "properties": {
    "gn:admin1_code":"11",
    "gn:admin2_code":"15.0",
    "gn:asciiname":"Zangarro (Zangarro Nuevo)",
    "gn:country_code":"MX",
    "gn:dem":1878,
    "gn:feature_class":"P",
    "gn:feature_code":"PPL",
    "gn:name":"Zangarro (Zangarro Nuevo)",
    "gn:population":1360,
    "gn:timezone":"America/Mexico_City",
    "iso:country":"MX",
    "wof:name":"Zangarro (Zangarro Nuevo)",
    "wof:placetype":"locality",
    "wof:population":1360
},
  "geometry": {"coordinates":[-101.27278,20.85806],"type":"Point"}
}