{
  "type": "Feature",
  "properties": {
    "gn:admin1_code":"6",
    "gn:admin2_code":"62.0",
    "gn:asciiname":"Rancho Los Pozos",
    "gn:country_code":"MX",
    "gn:dem":1312,
    "gn:feature_class":"P",
    "gn:feature_code":"PPL",
    "gn:name":"Rancho Los Pozos",
    "gn:population":0,
    "gn:timezone":"America/Chihuahua",
    "iso:country":"MX",
    "wof:name":"Rancho Los Pozos",
    "wof:placetype":"locality"
},
  "geometry": {"coordinates":[-105.39527,27.91682],"type":"Point"}
}