{
  "type": "Feature",
  "properties": {
    "gn:admin1_code":"12",
    "gn:admin2_code":"72",
    "gn:asciiname":"Rancho Pollo",
    "gn:country_code":"MX",
    "gn:dem":1573,
    "gn:feature_class":"P",
    "gn:feature_code":"PPL",
    "gn:name":"Rancho Pollo",
    "gn:population":49,
    "gn:timezone":"America/Mexico_City",
    "iso:country":"MX",
    "wof:name":"Rancho Pollo",
    "wof:placetype":"locality",
    "wof:population":49
},
  "geometry": {"coordinates":[-98.88472,17.18833],"type":"Point"}
}