{
  "type": "Feature",
  "properties": {
    "gn:admin1_code":"14.0",
    "gn:admin2_code":"49.0",
    "gn:asciiname":"Canollitas",
    "gn:country_code":"MX",
    "gn:dem":1001,
    "gn:feature_class":"P",
    "gn:feature_code":"PPL",
    "gn:name":"Canollitas",
    "gn:population":0,
    "gn:timezone":"America/Mexico_City",
    "iso:country":"MX",
    "name:spa_x_preferred":[
        "Canollitas"
    ],
    "wof:name":"Canollitas",
    "wof:placetype":"locality"
},
  "geometry": {"coordinates":[-102.56964000000001,19.47372],"type":"Point"}
}