{
  "type": "Feature",
  "properties": {
    "gn:admin1_code":"28.0",
    "gn:admin2_code":"35.0",
    "gn:asciiname":"Las Puertas",
    "gn:country_code":"MX",
    "gn:dem":46,
    "gn:feature_class":"P",
    "gn:feature_code":"PPL",
    "gn:name":"Las Puertas",
    "gn:population":0,
    "gn:timezone":"America/Monterrey",
    "iso:country":"MX",
    "name:spa_x_preferred":[
        "Las Puertas"
    ],
    "wof:name":"Las Puertas",
    "wof:placetype":"locality"
},
  "geometry": {"coordinates":[-98.24463,24.90608],"type":"Point"}
}