{
  "type": "Feature",
  "properties": {
    "gn:admin1_code":"31",
    "gn:admin2_code":"42.0",
    "gn:asciiname":"Tahdzibichen",
    "gn:country_code":"MX",
    "gn:dem":17,
    "gn:feature_class":"P",
    "gn:feature_code":"PPL",
    "gn:name":"Tahdzibichen",
    "gn:population":0,
    "gn:timezone":"America/Merida",
    "iso:country":"MX",
    "name:spa_x_preferred":[
        "Tahdzibichen"
    ],
    "wof:name":"Tahdzibichen",
    "wof:placetype":"locality"
},
  "geometry": {"coordinates":[-89.0125,20.73266],"type":"Point"}
}