{
  "type": "Feature",
  "properties": {
    "gn:admin1_code":"18.0",
    "gn:asciiname":"Las Islitas",
    "gn:country_code":"MX",
    "gn:dem":9,
    "gn:feature_class":"P",
    "gn:feature_code":"PPL",
    "gn:name":"Las Islitas",
    "gn:population":0,
    "gn:timezone":"America/Mazatlan",
    "iso:country":"MX",
    "name:spa_x_preferred":[
        "Las Islitas"
    ],
    "wof:name":"Las Islitas",
    "wof:placetype":"locality"
},
  "geometry": {"coordinates":[-105.24777,21.51483],"type":"Point"}
}