{
  "type": "Feature",
  "properties": {
    "gn:admin1_code":"14",
    "gn:admin2_code":"29.0",
    "gn:asciiname":"Teponahuasco",
    "gn:country_code":"MX",
    "gn:dem":1799,
    "gn:feature_class":"P",
    "gn:feature_code":"PPL",
    "gn:name":"Teponahuasco",
    "gn:population":0,
    "gn:timezone":"America/Mexico_City",
    "iso:country":"MX",
    "wof:name":"Teponahuasco",
    "wof:placetype":"locality"
},
  "geometry": {"coordinates":[-103.03944,20.9091],"type":"Point"}
}