{
  "type": "Feature",
  "properties": {
    "gn:admin1_code":"6",
    "gn:admin2_code":"29.0",
    "gn:asciiname":"Rosas Azules",
    "gn:country_code":"MX",
    "gn:dem":2633,
    "gn:feature_class":"P",
    "gn:feature_code":"PPL",
    "gn:name":"Rosas Azules",
    "gn:population":0,
    "gn:timezone":"America/Chihuahua",
    "iso:country":"MX",
    "name:spa_x_preferred":[
        "Rosas Azules"
    ],
    "wof:name":"Rosas Azules",
    "wof:placetype":"locality"
},
  "geometry": {"coordinates":[-106.90933,26.07191],"type":"Point"}
}