{
  "type": "Feature",
  "properties": {
    "gn:admin1_code":"6",
    "gn:admin2_code":"65.0",
    "gn:asciiname":"Otonachi",
    "gn:country_code":"MX",
    "gn:dem":1886,
    "gn:feature_class":"P",
    "gn:feature_code":"PPL",
    "gn:name":"Otonachi",
    "gn:population":5,
    "gn:timezone":"America/Chihuahua",
    "iso:country":"MX",
    "wof:name":"Otonachi",
    "wof:placetype":"locality",
    "wof:population":5
},
  "geometry": {"coordinates":[-108.03270000000001,27.46548],"type":"Point"}
}