{
  "type": "Feature",
  "properties": {
    "gn:admin1_code":"2",
    "gn:admin2_code":"5.0",
    "gn:asciiname":"Santa Isabel del Mar",
    "gn:country_code":"MX",
    "gn:dem":179,
    "gn:feature_class":"P",
    "gn:feature_code":"PPL",
    "gn:name":"Santa Isabel del Mar",
    "gn:population":5,
    "gn:timezone":"America/Tijuana",
    "iso:country":"MX",
    "wof:name":"Santa Isabel del Mar",
    "wof:placetype":"locality",
    "wof:population":5
},
  "geometry": {"coordinates":[-116.98944,32.28944],"type":"Point"}
}