{
  "type": "Feature",
  "properties": {
    "gn:admin1_code":"17",
    "gn:admin2_code":"28",
    "gn:asciiname":"Fraccionamiento Cumbres del Campestre",
    "gn:country_code":"MX",
    "gn:dem":1131,
    "gn:feature_class":"P",
    "gn:feature_code":"PPL",
    "gn:name":"Fraccionamiento Cumbres del Campestre",
    "gn:population":13,
    "gn:timezone":"America/Mexico_City",
    "iso:country":"MX",
    "wof:name":"Fraccionamiento Cumbres del Campestre",
    "wof:placetype":"locality",
    "wof:population":13
},
  "geometry": {"coordinates":[-99.19355,18.73545],"type":"Point"}
}