{
  "type": "Feature",
  "properties": {
    "gn:admin1_code":"7",
    "gn:admin2_code":"33.0",
    "gn:asciiname":"Diez de Mayo (El Chorizo)",
    "gn:country_code":"MX",
    "gn:dem":1109,
    "gn:feature_class":"P",
    "gn:feature_code":"PPL",
    "gn:name":"Diez de Mayo (El Chorizo)",
    "gn:population":99,
    "gn:timezone":"America/Monterrey",
    "iso:country":"MX",
    "wof:name":"Diez de Mayo (El Chorizo)",
    "wof:placetype":"locality",
    "wof:population":99
},
  "geometry": {"coordinates":[-103.18583,25.80083],"type":"Point"}
}