{
  "type": "Feature",
  "properties": {
    "gn:admin1_code":"28",
    "gn:admin2_code":"33.0",
    "gn:asciiname":"San Valentin",
    "gn:country_code":"MX",
    "gn:dem":18,
    "gn:feature_class":"P",
    "gn:feature_code":"PPL",
    "gn:name":"San Valent\u00edn",
    "gn:population":5,
    "gn:timezone":"America/Monterrey",
    "iso:country":"MX",
    "name:und_x_variant":[
        "San Valent\u00edn"
    ],
    "wof:name":"San Valentin",
    "wof:placetype":"locality",
    "wof:population":5
},
  "geometry": {"coordinates":[-97.95860999999999,25.49556],"type":"Point"}
}