{
  "type": "Feature",
  "properties": {
    "gn:admin1_code":"5",
    "gn:admin2_code":"31.0",
    "gn:asciiname":"Saquil-Ulub",
    "gn:country_code":"MX",
    "gn:dem":486,
    "gn:feature_class":"P",
    "gn:feature_code":"PPL",
    "gn:name":"Saquil-Ulub",
    "gn:population":149,
    "gn:timezone":"America/Mexico_City",
    "iso:country":"MX",
    "wof:name":"Saquil-Ulub",
    "wof:placetype":"locality",
    "wof:population":149
},
  "geometry": {"coordinates":[-92.09417000000001,17.23667],"type":"Point"}
}