{
  "type": "Feature",
  "properties": {
    "gn:admin1_code":"15",
    "gn:admin2_code":"80.0",
    "gn:asciiname":"Coquillo",
    "gn:country_code":"MX",
    "gn:dem":1217,
    "gn:feature_class":"P",
    "gn:feature_code":"PPL",
    "gn:name":"Coquillo",
    "gn:population":306,
    "gn:timezone":"America/Mexico_City",
    "iso:country":"MX",
    "wof:name":"Coquillo",
    "wof:placetype":"locality",
    "wof:population":306
},
  "geometry": {"coordinates":[-99.96056,18.69556],"type":"Point"}
}