{
  "type": "Feature",
  "properties": {
    "gn:admin1_code":"26",
    "gn:admin2_code":"68.0",
    "gn:asciiname":"El Tanque",
    "gn:country_code":"MX",
    "gn:dem":671,
    "gn:feature_class":"P",
    "gn:feature_code":"PPL",
    "gn:name":"El Tanque",
    "gn:population":1,
    "gn:timezone":"America/Hermosillo",
    "iso:country":"MX",
    "name:spa_x_preferred":[
        "El Tanque"
    ],
    "wof:name":"El Tanque",
    "wof:placetype":"locality",
    "wof:population":1
},
  "geometry": {"coordinates":[-110.01443999999999,29.07639],"type":"Point"}
}