{
  "type": "Feature",
  "properties": {
    "gn:admin1_code":"27",
    "gn:admin2_code":"14.0",
    "gn:asciiname":"Monte Adentro",
    "gn:country_code":"MX",
    "gn:dem":17,
    "gn:feature_class":"P",
    "gn:feature_code":"PPL",
    "gn:name":"Monte Adentro",
    "gn:population":0,
    "gn:timezone":"America/Mexico_City",
    "iso:country":"MX",
    "name:spa_x_preferred":[
        "Monte Adentro"
    ],
    "wof:name":"Monte Adentro",
    "wof:placetype":"locality"
},
  "geometry": {"coordinates":[-93.2123,18.36194],"type":"Point"}
}