{
  "type": "Feature",
  "properties": {
    "gn:admin1_code":"12",
    "gn:admin2_code":"51.0",
    "gn:asciiname":"Juxtlahuaca",
    "gn:country_code":"MX",
    "gn:dem":865,
    "gn:feature_class":"P",
    "gn:feature_code":"PPL",
    "gn:name":"Juxtlahuaca",
    "gn:population":908,
    "gn:timezone":"America/Mexico_City",
    "iso:country":"MX",
    "name:hun_x_preferred":[
        "Juxtlahuaca-barlang"
    ],
    "name:ita_x_preferred":[
        "Juxtlahuaca"
    ],
    "name:jpn_x_preferred":[
        "\u30d5\u30b9\u30c8\u30e9\u30ef\u30ab\u6d1e\u7a9f"
    ],
    "name:kat_x_preferred":[
        "\u10ee\u10e3\u10e8\u10e2\u10da\u10d0\u10e3\u10d0\u10d9\u10d0"
    ],
    "name:pol_x_preferred":[
        "Juxtlahuaca"
    ],
    "wof:name":"Juxtlahuaca",
    "wof:placetype":"locality",
    "wof:population":908
},
  "geometry": {"coordinates":[-99.14639,17.42917000000001],"type":"Point"}
}