{
  "type": "Feature",
  "properties": {
    "gn:admin1_code":"12",
    "gn:admin2_code":"27.0",
    "gn:asciiname":"La Huerta Vieja",
    "gn:country_code":"MX",
    "gn:dem":1141,
    "gn:feature_class":"P",
    "gn:feature_code":"PPL",
    "gn:name":"La Huerta Vieja",
    "gn:population":0,
    "gn:timezone":"America/Mexico_City",
    "iso:country":"MX",
    "name:spa_x_preferred":[
        "La Huerta Vieja"
    ],
    "wof:name":"La Huerta Vieja",
    "wof:placetype":"locality"
},
  "geometry": {"coordinates":[-100.77634,18.79825],"type":"Point"}
}