{
  "type": "Feature",
  "properties": {
    "gn:admin1_code":"10.0",
    "gn:admin2_code":"13.0",
    "gn:asciiname":"Margaritos",
    "gn:country_code":"MX",
    "gn:dem":1114,
    "gn:feature_class":"P",
    "gn:feature_code":"PPL",
    "gn:name":"Margaritos",
    "gn:population":0,
    "gn:timezone":"America/Monterrey",
    "iso:country":"MX",
    "name:spa_x_preferred":[
        "Margaritos"
    ],
    "wof:name":"Margaritos",
    "wof:placetype":"locality"
},
  "geometry": {"coordinates":[-103.60637,25.89901],"type":"Point"}
}