{
  "type": "Feature",
  "properties": {
    "gn:admin1_code":"14",
    "gn:admin2_code":"104.0",
    "gn:asciiname":"El Pedernal",
    "gn:country_code":"MX",
    "gn:dem":1786,
    "gn:feature_class":"P",
    "gn:feature_code":"PPL",
    "gn:name":"El Pedernal",
    "gn:population":0,
    "gn:timezone":"America/Mexico_City",
    "iso:country":"MX",
    "name:spa_x_preferred":[
        "El Pedernal"
    ],
    "wof:name":"El Pedernal",
    "wof:placetype":"locality"
},
  "geometry": {"coordinates":[-103.48842,22.07147],"type":"Point"}
}