{
  "type": "Feature",
  "properties": {
    "gn:admin1_code":"12",
    "gn:admin2_code":"63.0",
    "gn:asciiname":"Potoicha",
    "gn:country_code":"MX",
    "gn:dem":1175,
    "gn:feature_class":"P",
    "gn:feature_code":"PPL",
    "gn:name":"Potoicha",
    "gn:population":0,
    "gn:timezone":"America/Mexico_City",
    "iso:country":"MX",
    "wof:name":"Potoicha",
    "wof:placetype":"locality"
},
  "geometry": {"coordinates":[-98.78333000000001,17.18333],"type":"Point"}
}