{
  "type": "Feature",
  "properties": {
    "gn:admin1_code":"7.0",
    "gn:admin2_code":"28.0",
    "gn:asciiname":"Los Santos",
    "gn:country_code":"MX",
    "gn:dem":320,
    "gn:feature_class":"P",
    "gn:feature_code":"PPL",
    "gn:name":"Los Santos",
    "gn:population":0,
    "gn:timezone":"America/Monterrey",
    "iso:country":"MX",
    "name:cat_x_preferred":[
        "Los Santos"
    ],
    "name:ceb_x_preferred":[
        "Los Santos"
    ],
    "name:deu_x_preferred":[
        "Los Santos"
    ],
    "name:fra_x_preferred":[
        "Los Santos"
    ],
    "name:heb_x_preferred":[
        "\u05dc\u05d5\u05e9\u05e7\u05d4 \u05d3\u05d5\u05dc\u05d9\u05e0\u05d4"
    ],
    "name:hun_x_preferred":[
        "Los Santos"
    ],
    "name:ita_x_preferred":[
        "Los Santos"
    ],
    "name:kor_x_preferred":[
        "\ub85c\uc2a4\uc0b0\ud1a0\uc2a4"
    ],
    "name:lit_x_preferred":[
        "Los Santos"
    ],
    "name:nld_x_preferred":[
        "Los Santos"
    ],
    "name:oci_x_preferred":[
        "Los Santos"
    ],
    "name:pol_x_preferred":[
        "Los Santos"
    ],
    "name:por_x_preferred":[
        "Los Santos"
    ],
    "name:rus_x_preferred":[
        "\u041b\u043e\u0441-\u0421\u0430\u043d\u0442\u043e\u0441"
    ],
    "name:sco_x_preferred":[
        "Los Santos"
    ],
    "name:spa_x_preferred":[
        "Los Santos"
    ],
    "name:srp_x_preferred":[
        "\u041b\u043e\u0441 \u0421\u0430\u043d\u0442\u043e\u0441"
    ],
    "name:swe_x_preferred":[
        "Los Santos"
    ],
    "name:tur_x_preferred":[
        "Los Santos"
    ],
    "name:zho_x_preferred":[
        "\u6d1b\u8056\u90fd"
    ],
    "wof:name":"Los Santos",
    "wof:placetype":"locality"
},
  "geometry": {"coordinates":[-101.0098,27.73639],"type":"Point"}
}