{
  "type": "Feature",
  "properties": {
    "gn:admin1_code":"5",
    "gn:admin2_code":"107.0",
    "gn:asciiname":"El Faro",
    "gn:country_code":"MX",
    "gn:dem":602,
    "gn:feature_class":"P",
    "gn:feature_code":"PPL",
    "gn:name":"El Faro",
    "gn:population":7,
    "gn:timezone":"America/Mexico_City",
    "iso:country":"MX",
    "name:ceb_x_preferred":[
        "El Faro"
    ],
    "name:srp_x_preferred":[
        "\u0415\u043b \u0424\u0430\u0440\u043e"
    ],
    "name:swe_x_preferred":[
        "El Faro"
    ],
    "wof:name":"El Faro",
    "wof:placetype":"locality",
    "wof:population":7
},
  "geometry": {"coordinates":[-93.18138999999999,16.15361],"type":"Point"}
}