{
  "type": "Feature",
  "properties": {
    "gn:admin1_code":"5",
    "gn:admin2_code":"32",
    "gn:asciiname":"Fraccion el Joval",
    "gn:country_code":"MX",
    "gn:dem":109,
    "gn:feature_class":"P",
    "gn:feature_code":"PPL",
    "gn:name":"Fracci\u00f3n el Joval",
    "gn:population":19,
    "gn:timezone":"America/Mexico_City",
    "iso:country":"MX",
    "name:und_x_variant":[
        "Fracci\u00f3n el Joval"
    ],
    "wof:name":"Fraccion el Joval",
    "wof:placetype":"locality",
    "wof:population":19
},
  "geometry": {"coordinates":[-92.65139000000001,15.30889],"type":"Point"}
}