{
  "type": "Feature",
  "properties": {
    "gn:admin1_code":"18.0",
    "gn:admin2_code":"1.0",
    "gn:asciiname":"La Lagunita",
    "gn:country_code":"MX",
    "gn:dem":53,
    "gn:feature_class":"P",
    "gn:feature_code":"PPL",
    "gn:name":"La Lagunita",
    "gn:population":125,
    "gn:timezone":"America/Mazatlan",
    "iso:country":"MX",
    "wof:name":"La Lagunita",
    "wof:placetype":"locality",
    "wof:population":125
},
  "geometry": {"coordinates":[-105.30533,22.54921],"type":"Point"}
}