{
  "type": "Feature",
  "properties": {
    "gn:admin1_code":"16",
    "gn:admin2_code":"53",
    "gn:asciiname":"Fraccionamiento la Purisima",
    "gn:country_code":"MX",
    "gn:dem":1905,
    "gn:feature_class":"P",
    "gn:feature_code":"PPL",
    "gn:name":"Fraccionamiento la Pur\u00edsima",
    "gn:population":23,
    "gn:timezone":"America/Mexico_City",
    "iso:country":"MX",
    "name:und_x_variant":[
        "Fraccionamiento la Pur\u00edsima"
    ],
    "wof:name":"Fraccionamiento la Purisima",
    "wof:placetype":"locality",
    "wof:population":23
},
  "geometry": {"coordinates":[-101.11639,19.75111],"type":"Point"}
}