{
  "type": "Feature",
  "properties": {
    "gn:admin1_code":"5",
    "gn:admin2_code":"89.0",
    "gn:asciiname":"El Encanto",
    "gn:country_code":"MX",
    "gn:dem":8,
    "gn:feature_class":"P",
    "gn:feature_code":"PPL",
    "gn:name":"El Encanto",
    "gn:population":1726,
    "gn:timezone":"America/Mexico_City",
    "iso:country":"MX",
    "wof:name":"El Encanto",
    "wof:placetype":"locality",
    "wof:population":1726
},
  "geometry": {"coordinates":[-92.41028,14.73083],"type":"Point"}
}