{
  "type": "Feature",
  "properties": {
    "gn:admin1_code":"22",
    "gn:admin2_code":"3.0",
    "gn:asciiname":"Limoncito",
    "gn:country_code":"MX",
    "gn:dem":935,
    "gn:feature_class":"P",
    "gn:feature_code":"PPL",
    "gn:name":"Limoncito",
    "gn:population":0,
    "gn:timezone":"America/Mexico_City",
    "iso:country":"MX",
    "name:ceb_x_preferred":[
        "Limoncito"
    ],
    "name:deu_x_preferred":[
        "Limoncito"
    ],
    "name:zho_x_preferred":[
        "\u5229\u8499\u897f\u6258"
    ],
    "wof:name":"Limoncito",
    "wof:placetype":"locality"
},
  "geometry": {"coordinates":[-99.65000000000001,21.35],"type":"Point"}
}