{
  "type": "Feature",
  "properties": {
    "gn:admin1_code":"31",
    "gn:admin2_code":"101.0",
    "gn:asciiname":"La Guadalupana",
    "gn:country_code":"MX",
    "gn:dem":8,
    "gn:feature_class":"P",
    "gn:feature_code":"PPL",
    "gn:name":"La Guadalupana",
    "gn:population":7,
    "gn:timezone":"America/Merida",
    "iso:country":"MX",
    "wof:name":"La Guadalupana",
    "wof:placetype":"locality",
    "wof:population":7
},
  "geometry": {"coordinates":[-89.72194,20.87833],"type":"Point"}
}