{
  "type": "Feature",
  "properties": {
    "gn:admin1_code":"14",
    "gn:admin2_code":"68.0",
    "gn:asciiname":"El Coyul",
    "gn:country_code":"MX",
    "gn:dem":645,
    "gn:feature_class":"P",
    "gn:feature_code":"PPL",
    "gn:name":"El Coyul",
    "gn:population":6,
    "gn:timezone":"America/Mexico_City",
    "iso:country":"MX",
    "wof:name":"El Coyul",
    "wof:placetype":"locality",
    "wof:population":6
},
  "geometry": {"coordinates":[-104.84972,19.75417],"type":"Point"}
}