{
  "type": "Feature",
  "properties": {
    "gn:admin1_code":"5.0",
    "gn:asciiname":"Eden del Carmen",
    "gn:country_code":"MX",
    "gn:dem":1208,
    "gn:feature_class":"P",
    "gn:feature_code":"PPL",
    "gn:name":"Ed\u00e9n del Carmen",
    "gn:population":0,
    "gn:timezone":"America/Mexico_City",
    "iso:country":"MX",
    "name:spa_x_preferred":[
        "Ed\u00e9n del Carmen"
    ],
    "wof:name":"Eden del Carmen",
    "wof:placetype":"locality"
},
  "geometry": {"coordinates":[-92.11472999999999,16.77653],"type":"Point"}
}