{
  "type": "Feature",
  "properties": {
    "gn:admin1_code":"6",
    "gn:admin2_code":"31.0",
    "gn:asciiname":"Rancho la Union (La Alondra)",
    "gn:country_code":"MX",
    "gn:dem":1993,
    "gn:feature_class":"P",
    "gn:feature_code":"PPL",
    "gn:name":"Rancho la Uni\u00f3n (La Alondra)",
    "gn:population":5,
    "gn:timezone":"America/Chihuahua",
    "iso:country":"MX",
    "name:und_x_variant":[
        "Rancho la Uni\u00f3n (La Alondra)"
    ],
    "wof:name":"Rancho la Union (La Alondra)",
    "wof:placetype":"locality",
    "wof:population":5
},
  "geometry": {"coordinates":[-107.49024,28.58527],"type":"Point"}
}