{
  "type": "Feature",
  "properties": {
    "gn:admin1_code":"15",
    "gn:admin2_code":"112.0",
    "gn:asciiname":"San Salvador de la Laguna",
    "gn:country_code":"MX",
    "gn:dem":2423,
    "gn:feature_class":"P",
    "gn:feature_code":"PPL",
    "gn:name":"San Salvador de la Laguna",
    "gn:population":0,
    "gn:timezone":"America/Mexico_City",
    "iso:country":"MX",
    "name:spa_x_preferred":[
        "San Salvador de la Laguna"
    ],
    "wof:name":"San Salvador de la Laguna",
    "wof:placetype":"locality"
},
  "geometry": {"coordinates":[-99.45843000000001,19.79428],"type":"Point"}
}