{
  "type": "Feature",
  "properties": {
    "gn:admin1_code":"28.0",
    "gn:admin2_code":"3.0",
    "gn:asciiname":"San Javier",
    "gn:country_code":"MX",
    "gn:dem":38,
    "gn:feature_class":"P",
    "gn:feature_code":"PPL",
    "gn:name":"San Javier",
    "gn:population":0,
    "gn:timezone":"America/Monterrey",
    "iso:country":"MX",
    "name:spa_x_preferred":[
        "San Javier"
    ],
    "name:spa_x_variant":[
        "Tl\u00e1loc"
    ],
    "wof:name":"San Javier",
    "wof:placetype":"locality"
},
  "geometry": {"coordinates":[-98.29324,22.56128],"type":"Point"}
}