{
  "type": "Feature",
  "properties": {
    "gn:admin1_code":"20",
    "gn:admin2_code":"364.0",
    "gn:asciiname":"El CERESO",
    "gn:country_code":"MX",
    "gn:dem":1420,
    "gn:feature_class":"P",
    "gn:feature_code":"PPL",
    "gn:name":"El CERESO",
    "gn:population":358,
    "gn:timezone":"America/Mexico_City",
    "iso:country":"MX",
    "wof:name":"El CERESO",
    "wof:placetype":"locality",
    "wof:population":358
},
  "geometry": {"coordinates":[-97.28639,16.24028],"type":"Point"}
}