{
  "type": "Feature",
  "properties": {
    "gn:admin1_code":"30.0",
    "gn:admin2_code":"124.0",
    "gn:asciiname":"El Suspiro",
    "gn:country_code":"MX",
    "gn:dem":38,
    "gn:feature_class":"P",
    "gn:feature_code":"PPL",
    "gn:name":"El Suspiro",
    "gn:population":3,
    "gn:timezone":"America/Mexico_City",
    "iso:country":"MX",
    "name:spa_x_preferred":[
        "El Suspiro"
    ],
    "wof:name":"El Suspiro",
    "wof:placetype":"locality",
    "wof:population":3
},
  "geometry": {"coordinates":[-97.25583,20.39944],"type":"Point"}
}