{
  "type": "Feature",
  "properties": {
    "gn:admin1_code":"22",
    "gn:admin2_code":"4.0",
    "gn:asciiname":"El Soyatal",
    "gn:country_code":"MX",
    "gn:dem":2601,
    "gn:feature_class":"P",
    "gn:feature_code":"PPL",
    "gn:name":"El Soyatal",
    "gn:population":0,
    "gn:timezone":"America/Mexico_City",
    "iso:country":"MX",
    "name:spa_x_preferred":[
        "El Soyatal"
    ],
    "name:und_x_variant":[
        "Soyatal"
    ],
    "wof:name":"El Soyatal",
    "wof:placetype":"locality"
},
  "geometry": {"coordinates":[-99.65616,20.78251],"type":"Point"}
}