{
  "type": "Feature",
  "properties": {
    "gn:admin1_code":"16",
    "gn:admin2_code":"57",
    "gn:asciiname":"La Limoncilla",
    "gn:country_code":"MX",
    "gn:dem":1304,
    "gn:feature_class":"P",
    "gn:feature_code":"PPL",
    "gn:name":"La Limoncilla",
    "gn:population":26,
    "gn:timezone":"America/Mexico_City",
    "iso:country":"MX",
    "wof:name":"La Limoncilla",
    "wof:placetype":"locality",
    "wof:population":26
},
  "geometry": {"coordinates":[-101.28361,19.18417],"type":"Point"}
}