{
  "type": "Feature",
  "properties": {
    "gn:admin1_code":"28.0",
    "gn:admin2_code":"42.0",
    "gn:asciiname":"El Tambor",
    "gn:country_code":"MX",
    "gn:dem":341,
    "gn:feature_class":"P",
    "gn:feature_code":"PPL",
    "gn:name":"El Tambor",
    "gn:population":0,
    "gn:timezone":"America/Monterrey",
    "iso:country":"MX",
    "name:spa_x_preferred":[
        "El Tambor"
    ],
    "wof:name":"El Tambor",
    "wof:placetype":"locality"
},
  "geometry": {"coordinates":[-99.43694000000001,24.45528],"type":"Point"}
}