{
  "type": "Feature",
  "properties": {
    "gn:admin1_code":"28",
    "gn:admin2_code":"40.0",
    "gn:asciiname":"Magueyes (Martin Benavides)",
    "gn:country_code":"MX",
    "gn:dem":18,
    "gn:feature_class":"P",
    "gn:feature_code":"PPL",
    "gn:name":"Magueyes (Mart\u00edn Benavides)",
    "gn:population":5,
    "gn:timezone":"America/Monterrey",
    "iso:country":"MX",
    "name:und_x_variant":[
        "Magueyes (Mart\u00edn Benavides)"
    ],
    "wof:name":"Magueyes (Martin Benavides)",
    "wof:placetype":"locality",
    "wof:population":5
},
  "geometry": {"coordinates":[-97.80110999999999,25.71278],"type":"Point"}
}