{
  "type": "Feature",
  "properties": {
    "gn:admin1_code":"5",
    "gn:admin2_code":"89.0",
    "gn:asciiname":"Mi Lupita",
    "gn:country_code":"MX",
    "gn:dem":54,
    "gn:feature_class":"P",
    "gn:feature_code":"PPL",
    "gn:name":"Mi Lupita",
    "gn:population":4,
    "gn:timezone":"America/Mexico_City",
    "iso:country":"MX",
    "wof:name":"Mi Lupita",
    "wof:placetype":"locality",
    "wof:population":4
},
  "geometry": {"coordinates":[-92.35917000000001,14.92361],"type":"Point"}
}