{
  "type": "Feature",
  "properties": {
    "gn:admin1_code":"11",
    "gn:admin2_code":"33.0",
    "gn:asciiname":"Santa Brigida",
    "gn:country_code":"MX",
    "gn:dem":2164,
    "gn:feature_class":"P",
    "gn:feature_code":"PPL",
    "gn:name":"Santa Br\u00edgida",
    "gn:population":23,
    "gn:timezone":"America/Mexico_City",
    "iso:country":"MX",
    "wof:name":"Santa Brigida",
    "wof:placetype":"locality",
    "wof:population":23
},
  "geometry": {"coordinates":[-100.46417,21.23028],"type":"Point"}
}