{
  "type": "Feature",
  "properties": {
    "gn:admin1_code":"11",
    "gn:admin2_code":"33.0",
    "gn:asciiname":"Santa Brigida",
    "gn:country_code":"MX",
    "gn:dem":2164,
    "gn:feature_class":"P",
    "gn:feature_code":"PPL",
    "gn:name":"Santa Br\u00edgida",
    "gn:population":23,
    "gn:timezone":"America/Mexico_City",
    "iso:country":"MX",
    "name:bel_x_preferred":[
        "\u0421\u0430\u043d\u0442\u0430-\u0411\u0440\u044b\u0434\u0436\u044b\u0434\u0430"
    ],
    "name:ceb_x_preferred":[
        "Santa Brigida"
    ],
    "name:ces_x_preferred":[
        "Santa Brigida"
    ],
    "name:deu_x_preferred":[
        "Santa Brigida"
    ],
    "name:eus_x_preferred":[
        "Santa Brigida"
    ],
    "name:fra_x_preferred":[
        "Santa Brigida"
    ],
    "name:heb_x_preferred":[
        "\u05d1\u05e8\u05d9\u05d2\u05d9\u05d8\u05d4 \u05d4\u05e7\u05d3\u05d5\u05e9\u05d4"
    ],
    "name:hun_x_preferred":[
        "Santa Brigida"
    ],
    "name:ita_x_preferred":[
        "Santa Brigida"
    ],
    "name:msa_x_preferred":[
        "Santa Br\u00edgida"
    ],
    "name:nld_x_preferred":[
        "Santa Brigida"
    ],
    "name:pol_x_preferred":[
        "Santa Brigida"
    ],
    "name:por_x_preferred":[
        "Santa Br\u00edgida"
    ],
    "name:spa_x_preferred":[
        "Santa Br\u00edgida"
    ],
    "name:srp_x_preferred":[
        "Santa Bri\u0111ida"
    ],
    "name:swe_x_preferred":[
        "Santa Brigida"
    ],
    "name:vie_x_preferred":[
        "Santa Br\u00edgida"
    ],
    "name:war_x_preferred":[
        "Santa Br\u00edgida"
    ],
    "wof:name":"Santa Brigida",
    "wof:placetype":"locality",
    "wof:population":23
},
  "geometry": {"coordinates":[-100.46417,21.23028],"type":"Point"}
}