{
  "type": "Feature",
  "properties": {
    "gn:admin1_code":"14",
    "gn:admin2_code":"105.0",
    "gn:asciiname":"Union de Guadalupe",
    "gn:country_code":"MX",
    "gn:dem":1590,
    "gn:feature_class":"P",
    "gn:feature_code":"PPL",
    "gn:name":"Uni\u00f3n de Guadalupe",
    "gn:population":0,
    "gn:timezone":"America/Mexico_City",
    "iso:country":"MX",
    "wof:name":"Union de Guadalupe",
    "wof:placetype":"locality"
},
  "geometry": {"coordinates":[-102.70090999999999,20.57148],"type":"Point"}
}