{
  "type": "Feature",
  "properties": {
    "gn:admin1_code":"13",
    "gn:admin2_code":"81.0",
    "gn:asciiname":"Colonia 11 de Abril (El Deposito Viejo)",
    "gn:country_code":"MX",
    "gn:dem":2058,
    "gn:feature_class":"P",
    "gn:feature_code":"PPL",
    "gn:name":"Colonia 11 de Abril (El Dep\u00f3sito Viejo)",
    "gn:population":122,
    "gn:timezone":"America/Mexico_City",
    "iso:country":"MX",
    "name:und_x_variant":[
        "Colonia 11 de Abril (El Dep\u00f3sito Viejo)"
    ],
    "wof:name":"Colonia 11 de Abril (El Deposito Viejo)",
    "wof:placetype":"locality",
    "wof:population":122
},
  "geometry": {"coordinates":[-98.66972,20.65052],"type":"Point"}
}