{
  "type": "Feature",
  "properties": {
    "gn:admin1_code":"2",
    "gn:admin2_code":"4.0",
    "gn:asciiname":"El Florido",
    "gn:country_code":"MX",
    "gn:dem":167,
    "gn:feature_class":"P",
    "gn:feature_code":"PPL",
    "gn:name":"El Florido",
    "gn:population":0,
    "gn:timezone":"America/Tijuana",
    "iso:country":"MX",
    "wof:name":"El Florido",
    "wof:placetype":"locality"
},
  "geometry": {"coordinates":[-116.79736,32.46628],"type":"Point"}
}