{
  "type": "Feature",
  "properties": {
    "gn:admin1_code":"25",
    "gn:admin2_code":"11.0",
    "gn:asciiname":"Campo Guasadeli",
    "gn:country_code":"MX",
    "gn:dem":21,
    "gn:feature_class":"P",
    "gn:feature_code":"PPL",
    "gn:name":"Campo Guasadeli",
    "gn:population":0,
    "gn:timezone":"America/Mazatlan",
    "iso:country":"MX",
    "name:spa_x_preferred":[
        "Guasadeli"
    ],
    "name:spa_x_variant":[
        "Campo Guasadeli"
    ],
    "wof:name":"Campo Guasadeli",
    "wof:placetype":"locality"
},
  "geometry": {"coordinates":[-108.66858999999999,25.68117],"type":"Point"}
}