{
  "type": "Feature",
  "properties": {
    "gn:admin1_code":"30",
    "gn:admin2_code":"117.0",
    "gn:asciiname":"El Callejon",
    "gn:country_code":"MX",
    "gn:dem":371,
    "gn:feature_class":"P",
    "gn:feature_code":"PPL",
    "gn:name":"El Callej\u00f3n",
    "gn:population":289,
    "gn:timezone":"America/Mexico_City",
    "iso:country":"MX",
    "name:und_x_variant":[
        "El Callej\u00f3n"
    ],
    "wof:name":"El Callejon",
    "wof:placetype":"locality",
    "wof:population":289
},
  "geometry": {"coordinates":[-96.75444,18.73778],"type":"Point"}
}