{
  "type": "Feature",
  "properties": {
    "gn:admin1_code":"14.0",
    "gn:admin2_code":"86.0",
    "gn:asciiname":"Los Manzano",
    "gn:country_code":"MX",
    "gn:dem":2217,
    "gn:feature_class":"P",
    "gn:feature_code":"PPL",
    "gn:name":"Los Manzano",
    "gn:population":0,
    "gn:timezone":"America/Mexico_City",
    "iso:country":"MX",
    "name:spa_x_preferred":[
        "Los Manzano"
    ],
    "wof:name":"Los Manzano",
    "wof:placetype":"locality"
},
  "geometry": {"coordinates":[-103.71335000000001,19.91294],"type":"Point"}
}