{
  "type": "Feature",
  "properties": {
    "gn:admin1_code":"10",
    "gn:admin2_code":"23",
    "gn:asciiname":"El Coscomate",
    "gn:country_code":"MX",
    "gn:dem":2046,
    "gn:feature_class":"P",
    "gn:feature_code":"PPL",
    "gn:name":"El Coscomate",
    "gn:population":9,
    "gn:timezone":"America/Monterrey",
    "iso:country":"MX",
    "wof:name":"El Coscomate",
    "wof:placetype":"locality",
    "wof:population":9
},
  "geometry": {"coordinates":[-105.38164999999999,23.39341],"type":"Point"}
}