{
  "type": "Feature",
  "properties": {
    "gn:admin1_code":"24",
    "gn:admin2_code":"37.0",
    "gn:asciiname":"Cuatzontitla",
    "gn:country_code":"MX",
    "gn:dem":153,
    "gn:feature_class":"P",
    "gn:feature_code":"PPL",
    "gn:name":"Cuatzontitla",
    "gn:population":256,
    "gn:timezone":"America/Mexico_City",
    "iso:country":"MX",
    "wof:name":"Cuatzontitla",
    "wof:placetype":"locality",
    "wof:population":256
},
  "geometry": {"coordinates":[-98.78471999999999,21.22222],"type":"Point"}
}