{
  "type": "Feature",
  "properties": {
    "gn:admin1_code":"30",
    "gn:admin2_code":"141",
    "gn:asciiname":"Caleria Alta",
    "gn:country_code":"MX",
    "gn:dem":710,
    "gn:feature_class":"P",
    "gn:feature_code":"PPL",
    "gn:name":"Caler\u00eda Alta",
    "gn:population":10,
    "gn:timezone":"America/Mexico_City",
    "iso:country":"MX",
    "name:und_x_variant":[
        "Caler\u00eda Alta"
    ],
    "wof:name":"Caleria Alta",
    "wof:placetype":"locality",
    "wof:population":10
},
  "geometry": {"coordinates":[-95.15944,18.48528],"type":"Point"}
}