{
  "type": "Feature",
  "properties": {
    "gn:admin1_code":"16",
    "gn:admin2_code":"38.0",
    "gn:asciiname":"Zacualpan",
    "gn:country_code":"MX",
    "gn:dem":247,
    "gn:feature_class":"P",
    "gn:feature_code":"PPL",
    "gn:name":"Zacualpan",
    "gn:population":59,
    "gn:timezone":"America/Mexico_City",
    "iso:country":"MX",
    "wof:name":"Zacualpan",
    "wof:placetype":"locality",
    "wof:population":59
},
  "geometry": {"coordinates":[-100.86667,18.54028],"type":"Point"}
}