{
  "type": "Feature",
  "properties": {
    "gn:admin1_code":"2",
    "gn:admin2_code":"2.0",
    "gn:asciiname":"Colonia Borquez Norte (La Canaleta)",
    "gn:country_code":"MX",
    "gn:dem":17,
    "gn:feature_class":"P",
    "gn:feature_code":"PPL",
    "gn:name":"Colonia B\u00f3rquez Norte (La Canaleta)",
    "gn:population":155,
    "gn:timezone":"America/Tijuana",
    "iso:country":"MX",
    "name:und_x_variant":[
        "Colonia B\u00f3rquez Norte (La Canaleta)"
    ],
    "wof:name":"Colonia Borquez Norte (La Canaleta)",
    "wof:placetype":"locality",
    "wof:population":155
},
  "geometry": {"coordinates":[-115.01944,32.63111],"type":"Point"}
}