{
  "type": "Feature",
  "properties": {
    "gn:admin1_code":"3",
    "gn:admin2_code":"1.0",
    "gn:asciiname":"Carambuche",
    "gn:country_code":"MX",
    "gn:dem":136,
    "gn:feature_class":"P",
    "gn:feature_code":"PPL",
    "gn:name":"Carambuche",
    "gn:population":140,
    "gn:timezone":"America/Mazatlan",
    "iso:country":"MX",
    "wof:name":"Carambuche",
    "wof:placetype":"locality",
    "wof:population":140
},
  "geometry": {"coordinates":[-112.01752999999999,26.2162],"type":"Point"}
}