{
  "type": "Feature",
  "properties": {
    "gn:admin1_code":"6",
    "gn:admin2_code":"32.0",
    "gn:asciiname":"San Jeronimo de Abajo",
    "gn:country_code":"MX",
    "gn:dem":1596,
    "gn:feature_class":"P",
    "gn:feature_code":"PPL",
    "gn:name":"San Jer\u00f3nimo de Abajo",
    "gn:population":0,
    "gn:timezone":"America/Chihuahua",
    "iso:country":"MX",
    "name:spa_x_preferred":[
        "San Jer\u00f3nimo de Abajo"
    ],
    "name:und_x_variant":[
        "Rancho San Jer\u00f3nimo",
        "San Ger\u00f3nimo",
        "San Jer\u00f3nimo"
    ],
    "wof:name":"San Jeronimo de Abajo",
    "wof:placetype":"locality"
},
  "geometry": {"coordinates":[-105.59887999999999,27.14346],"type":"Point"}
}