{
  "type": "Feature",
  "properties": {
    "gn:admin1_code":"30",
    "gn:admin2_code":"64",
    "gn:asciiname":"Las Letras",
    "gn:country_code":"MX",
    "gn:dem":223,
    "gn:feature_class":"P",
    "gn:feature_code":"PPL",
    "gn:name":"Las Letras",
    "gn:population":27,
    "gn:timezone":"America/Mexico_City",
    "iso:country":"MX",
    "wof:name":"Las Letras",
    "wof:placetype":"locality",
    "wof:population":27
},
  "geometry": {"coordinates":[-97.59889,20.20139],"type":"Point"}
}