{
  "type": "Feature",
  "properties": {
    "gn:admin1_code":"26.0",
    "gn:admin2_code":"69.0",
    "gn:asciiname":"Puerto del Sotolar",
    "gn:country_code":"MX",
    "gn:dem":1714,
    "gn:feature_class":"P",
    "gn:feature_code":"PPL",
    "gn:name":"Puerto del Sotolar",
    "gn:population":0,
    "gn:timezone":"America/Hermosillo",
    "iso:country":"MX",
    "name:spa_x_preferred":[
        "Puerto del Sotolar"
    ],
    "wof:name":"Puerto del Sotolar",
    "wof:placetype":"locality"
},
  "geometry": {"coordinates":[-108.88056,28.38464],"type":"Point"}
}