{
  "type": "Feature",
  "properties": {
    "gn:admin1_code":"21",
    "gn:admin2_code":"53.0",
    "gn:asciiname":"Temascales",
    "gn:country_code":"MX",
    "gn:dem":2569,
    "gn:feature_class":"P",
    "gn:feature_code":"PPL",
    "gn:name":"Temascales",
    "gn:population":0,
    "gn:timezone":"America/Mexico_City",
    "iso:country":"MX",
    "name:spa_x_preferred":[
        "Temascales"
    ],
    "wof:name":"Temascales",
    "wof:placetype":"locality"
},
  "geometry": {"coordinates":[-98.18042,19.80449],"type":"Point"}
}