{
  "type": "Feature",
  "properties": {
    "gn:country":"MX",
    "gn:fcode":"PPL",
    "gn:population":0,
    "iso:country":"MX",
    "name:bre_x_preferred":[
        "Santa Catarina"
    ],
    "name:cat_x_preferred":[
        "Santa Catarina"
    ],
    "name:ceb_x_preferred":[
        "Santa Catarina"
    ],
    "name:deu_x_preferred":[
        "Santa Catarina"
    ],
    "name:epo_x_preferred":[
        "Sankta Katarino"
    ],
    "name:fin_x_preferred":[
        "Santa Catarina"
    ],
    "name:fra_x_preferred":[
        "Santa Catarina"
    ],
    "name:glg_x_preferred":[
        "Santa Catarina"
    ],
    "name:hrv_x_preferred":[
        "Santa Catarina"
    ],
    "name:hun_x_preferred":[
        "Santa Catarina"
    ],
    "name:ita_x_preferred":[
        "Santa Catarina"
    ],
    "name:jpn_x_preferred":[
        "\u30b5\u30f3\u30bf\u30ab\u30bf\u30ea\u30ca"
    ],
    "name:kor_x_preferred":[
        "\uc0b0\ud0c0\uce74\ud0c0\ub9ac\ub098"
    ],
    "name:nld_x_preferred":[
        "Santa Catarina"
    ],
    "name:nor_x_preferred":[
        "Santa Catarina"
    ],
    "name:pol_x_preferred":[
        "Santa Catarina"
    ],
    "name:por_x_preferred":[
        "Santa Catarina"
    ],
    "name:rus_x_preferred":[
        "\u0421\u0430\u043d\u0442\u0430-\u041a\u0430\u0442\u0430\u0440\u0438\u043d\u0430"
    ],
    "name:scn_x_preferred":[
        "Santa Catarina"
    ],
    "name:sco_x_preferred":[
        "Santa Catarina"
    ],
    "name:spa_x_preferred":[
        "Santa Catarina"
    ],
    "name:srp_x_preferred":[
        "\u0421\u0430\u043d\u0442\u0430 \u041a\u0430\u0442\u0430\u0440\u0438\u043d\u0430"
    ],
    "name:swe_x_preferred":[
        "Santa Catarina"
    ],
    "name:tur_x_preferred":[
        "Santa Catarina"
    ],
    "name:ukr_x_preferred":[
        "\u0421\u0430\u043d\u0442\u0430-\u041a\u0430\u0442\u0430\u0440\u0456\u043d\u0430"
    ],
    "qs_pg:aaroncc":"MX",
    "qs_pg:gn_country":"MX",
    "qs_pg:gn_fcode":"PPL",
    "qs_pg:gn_pop":0,
    "qs_pg:name":"Santa Catarina",
    "qs_pg:name_adm0":"M\u00e9xico",
    "qs_pg:name_adm1":"Puebla",
    "qs_pg:photos":26,
    "qs_pg:photos_1k":5,
    "qs_pg:photos_9k":1,
    "qs_pg:photos_9r":2,
    "qs_pg:photos_all":26,
    "qs_pg:photos_sr":2,
    "qs_pg:pop_sr":0,
    "qs_pg:qs_pg_placetype":"neighbourhood",
    "qs_pg:qs_pg_placetype_gp":"Suburb",
    "qs_pg:woe_adm0":23424900,
    "woe:adm0_id":23424900,
    "woe:name_adm0":"M\u00e9xico",
    "woe:name_adm1":"Puebla",
    "woe:placetype":"Suburb",
    "wof:name":"Santa Catarina",
    "wof:placetype":"neighbourhood"
},
  "geometry": {"coordinates":[-98.17718000000001,20.24417],"type":"Point"}
}