{
  "type": "Feature",
  "properties": {
    "gn:admin1_code":"27.0",
    "gn:admin2_code":"17.0",
    "gn:asciiname":"Benito Juarez Segunda Seccion",
    "gn:country_code":"MX",
    "gn:dem":49,
    "gn:feature_class":"P",
    "gn:feature_code":"PPL",
    "gn:name":"Benito Ju\u00e1rez Segunda Secci\u00f3n",
    "gn:population":0,
    "gn:timezone":"America/Mexico_City",
    "iso:country":"MX",
    "name:spa_x_preferred":[
        "Benito Ju\u00e1rez Segunda Secci\u00f3n"
    ],
    "wof:name":"Benito Juarez Segunda Seccion",
    "wof:placetype":"locality"
},
  "geometry": {"coordinates":[-91.23090999999999,17.4231],"type":"Point"}
}