{
  "type": "Feature",
  "properties": {
    "gn:admin1_code":"16",
    "gn:admin2_code":"35.0",
    "gn:asciiname":"Cuimbo",
    "gn:country_code":"MX",
    "gn:dem":571,
    "gn:feature_class":"P",
    "gn:feature_code":"PPL",
    "gn:name":"Cuimbo",
    "gn:population":297,
    "gn:timezone":"America/Mexico_City",
    "iso:country":"MX",
    "wof:name":"Cuimbo",
    "wof:placetype":"locality",
    "wof:population":297
},
  "geometry": {"coordinates":[-101.66417,18.86306],"type":"Point"}
}