{
  "type": "Feature",
  "properties": {
    "gn:admin1_code":"32",
    "gn:admin2_code":"33.0",
    "gn:asciiname":"El Alacran",
    "gn:country_code":"MX",
    "gn:dem":1550,
    "gn:feature_class":"P",
    "gn:feature_code":"PPL",
    "gn:name":"El Alacr\u00e1n",
    "gn:population":65,
    "gn:timezone":"America/Mexico_City",
    "iso:country":"MX",
    "name:und_x_variant":[
        "El Alacr\u00e1n"
    ],
    "wof:name":"El Alacran",
    "wof:placetype":"locality",
    "wof:population":65
},
  "geometry": {"coordinates":[-103.13111000000001,21.1075],"type":"Point"}
}