{
  "type": "Feature",
  "properties": {
    "gn:admin1_code":"14",
    "gn:admin2_code":"56",
    "gn:asciiname":"El Volcancillo",
    "gn:country_code":"MX",
    "gn:dem":908,
    "gn:feature_class":"P",
    "gn:feature_code":"PPL",
    "gn:name":"El Volcancillo",
    "gn:population":10,
    "gn:timezone":"America/Mexico_City",
    "iso:country":"MX",
    "wof:name":"El Volcancillo",
    "wof:placetype":"locality",
    "wof:population":10
},
  "geometry": {"coordinates":[-102.745,19.55667],"type":"Point"}
}