{
  "type": "Feature",
  "properties": {
    "gn:admin1_code":"16",
    "gn:admin2_code":"49.0",
    "gn:asciiname":"Ojos de Agua",
    "gn:country_code":"MX",
    "gn:dem":1819,
    "gn:feature_class":"P",
    "gn:feature_code":"PPL",
    "gn:name":"Ojos de Agua",
    "gn:population":0,
    "gn:timezone":"America/Mexico_City",
    "iso:country":"MX",
    "name:spa_x_preferred":[
        "Ojos de Agua"
    ],
    "name:zho_x_preferred":[
        "\u5967\u970d\u65af\u5fb7\u963f\u74dc"
    ],
    "wof:name":"Ojos de Agua",
    "wof:placetype":"locality"
},
  "geometry": {"coordinates":[-101.05465,19.3457],"type":"Point"}
}