{
  "type": "Feature",
  "properties": {
    "gn:admin1_code":"24.0",
    "gn:admin2_code":"40.0",
    "gn:asciiname":"Maracaibo",
    "gn:country_code":"MX",
    "gn:dem":24,
    "gn:feature_class":"P",
    "gn:feature_code":"PPL",
    "gn:name":"Maracaibo",
    "gn:population":0,
    "gn:timezone":"America/Mexico_City",
    "iso:country":"MX",
    "name:spa_x_preferred":[
        "Maracaibo"
    ],
    "wof:name":"Maracaibo",
    "wof:placetype":"locality"
},
  "geometry": {"coordinates":[-98.53936,22.13534],"type":"Point"}
}