{
  "type": "Feature",
  "properties": {
    "gn:admin1_code":"5",
    "gn:admin2_code":"77.0",
    "gn:asciiname":"Cacateel",
    "gn:country_code":"MX",
    "gn:dem":380,
    "gn:feature_class":"P",
    "gn:feature_code":"PPL",
    "gn:name":"Cacateel",
    "gn:population":112,
    "gn:timezone":"America/Mexico_City",
    "iso:country":"MX",
    "wof:name":"Cacateel",
    "wof:placetype":"locality",
    "wof:population":112
},
  "geometry": {"coordinates":[-91.93056,17.22361],"type":"Point"}
}