{
  "type": "Feature",
  "properties": {
    "gn:admin1_code":"12",
    "gn:admin2_code":"78.0",
    "gn:asciiname":"Rancho de Guadalupe (Barranca Pobre)",
    "gn:country_code":"MX",
    "gn:dem":2154,
    "gn:feature_class":"P",
    "gn:feature_code":"PPL",
    "gn:name":"Rancho de Guadalupe (Barranca Pobre)",
    "gn:population":117,
    "gn:timezone":"America/Mexico_City",
    "iso:country":"MX",
    "wof:name":"Rancho de Guadalupe (Barranca Pobre)",
    "wof:placetype":"locality",
    "wof:population":117
},
  "geometry": {"coordinates":[-98.3961,17.155],"type":"Point"}
}