{
  "type": "Feature",
  "properties": {
    "gn:admin1_code":"11.0",
    "gn:admin2_code":"30.0",
    "gn:asciiname":"San Jose de los Barcos",
    "gn:country_code":"MX",
    "gn:dem":2061,
    "gn:feature_class":"P",
    "gn:feature_code":"PPL",
    "gn:name":"San Jos\u00e9 de los Barcos",
    "gn:population":0,
    "gn:timezone":"America/Mexico_City",
    "iso:country":"MX",
    "name:spa_x_preferred":[
        "San Jos\u00e9 de los Barcos"
    ],
    "wof:name":"San Jose de los Barcos",
    "wof:placetype":"locality"
},
  "geometry": {"coordinates":[-101.24884,21.30877000000001],"type":"Point"}
}