{
  "type": "Feature",
  "properties": {
    "gn:admin1_code":"6",
    "gn:admin2_code":"41.0",
    "gn:asciiname":"Sojaguachi",
    "gn:country_code":"MX",
    "gn:dem":1925,
    "gn:feature_class":"P",
    "gn:feature_code":"PPL",
    "gn:name":"Soj\u00e1guachi",
    "gn:population":0,
    "gn:timezone":"America/Chihuahua",
    "iso:country":"MX",
    "name:spa_x_preferred":[
        "Soj\u00e1guachi"
    ],
    "wof:name":"Sojaguachi",
    "wof:placetype":"locality"
},
  "geometry": {"coordinates":[-107.96947,27.76999],"type":"Point"}
}