{
  "type": "Feature",
  "properties": {
    "gn:admin1_code":"22",
    "gn:admin2_code":"14",
    "gn:asciiname":"Anahuac",
    "gn:country_code":"MX",
    "gn:dem":1806,
    "gn:feature_class":"P",
    "gn:feature_code":"PPL",
    "gn:name":"An\u00e1huac",
    "gn:population":26,
    "gn:timezone":"America/Mexico_City",
    "iso:country":"MX",
    "name:ceb_x_preferred":[
        "Anahuac"
    ],
    "name:ita_x_preferred":[
        "Anahuac"
    ],
    "name:nld_x_preferred":[
        "Anahuac"
    ],
    "name:sco_x_preferred":[
        "Anahuac"
    ],
    "name:swe_x_preferred":[
        "Anahuac"
    ],
    "name:und_x_variant":[
        "An\u00e1huac"
    ],
    "wof:name":"Anahuac",
    "wof:placetype":"locality",
    "wof:population":26
},
  "geometry": {"coordinates":[-100.42028000000001,20.57556],"type":"Point"}
}