{
  "type": "Feature",
  "properties": {
    "gn:admin1_code":"20",
    "gn:admin2_code":"401.0",
    "gn:asciiname":"Totolapam",
    "gn:country_code":"MX",
    "gn:dem":41,
    "gn:feature_class":"P",
    "gn:feature_code":"PPL",
    "gn:name":"Totolapam",
    "gn:population":0,
    "gn:timezone":"America/Mexico_City",
    "iso:country":"MX",
    "name:spa_x_preferred":[
        "Totolapam"
    ],
    "name:und_x_variant":[
        "Totolapa"
    ],
    "wof:name":"Totolapam",
    "wof:placetype":"locality"
},
  "geometry": {"coordinates":[-97.00391999999999,15.86673],"type":"Point"}
}