{
  "type": "Feature",
  "properties": {
    "gn:admin1_code":"5",
    "gn:admin2_code":"30.0",
    "gn:asciiname":"San Francisco las Palmas",
    "gn:country_code":"MX",
    "gn:dem":652,
    "gn:feature_class":"P",
    "gn:feature_code":"PPL",
    "gn:name":"San Francisco las Palmas",
    "gn:population":236,
    "gn:timezone":"America/Mexico_City",
    "iso:country":"MX",
    "wof:name":"San Francisco las Palmas",
    "wof:placetype":"locality",
    "wof:population":236
},
  "geometry": {"coordinates":[-92.44444,15.75056],"type":"Point"}
}