{
  "type": "Feature",
  "properties": {
    "gn:admin1_code":"5",
    "gn:admin2_code":"32.0",
    "gn:asciiname":"San Juan Panama",
    "gn:country_code":"MX",
    "gn:dem":1690,
    "gn:feature_class":"P",
    "gn:feature_code":"PPL",
    "gn:name":"San Juan Panam\u00e1",
    "gn:population":0,
    "gn:timezone":"America/Mexico_City",
    "iso:country":"MX",
    "name:spa_x_preferred":[
        "San Juan Panam\u00e1"
    ],
    "name:und_x_variant":[
        "San Juan Panana"
    ],
    "wof:name":"San Juan Panama",
    "wof:placetype":"locality"
},
  "geometry": {"coordinates":[-92.50319,15.41287],"type":"Point"}
}