{
  "type": "Feature",
  "properties": {
    "gn:admin1_code":"26",
    "gn:admin2_code":"18.0",
    "gn:asciiname":"Ontagota",
    "gn:country_code":"MX",
    "gn:dem":25,
    "gn:feature_class":"P",
    "gn:feature_code":"PPL",
    "gn:name":"Ontagota",
    "gn:population":0,
    "gn:timezone":"America/Hermosillo",
    "iso:country":"MX",
    "name:und_x_variant":[
        "Onlagota",
        "Ontagota"
    ],
    "wof:name":"Ontagota",
    "wof:placetype":"locality"
},
  "geometry": {"coordinates":[-110.05592,27.45548],"type":"Point"}
}