{
  "type": "Feature",
  "properties": {
    "gn:admin1_code":"20",
    "gn:admin2_code":"321.0",
    "gn:asciiname":"Yosocuno",
    "gn:country_code":"MX",
    "gn:dem":2246,
    "gn:feature_class":"P",
    "gn:feature_code":"PPL",
    "gn:name":"Yosocuno",
    "gn:population":243,
    "gn:timezone":"America/Mexico_City",
    "iso:country":"MX",
    "wof:name":"Yosocuno",
    "wof:placetype":"locality",
    "wof:population":243
},
  "geometry": {"coordinates":[-97.58360999999999,17.84722],"type":"Point"}
}