{
  "type": "Feature",
  "properties": {
    "gn:admin1_code":"30.0",
    "gn:admin2_code":"134.0",
    "gn:asciiname":"Guayabalito",
    "gn:country_code":"MX",
    "gn:dem":63,
    "gn:feature_class":"P",
    "gn:feature_code":"PPL",
    "gn:name":"Guayabalito",
    "gn:population":0,
    "gn:timezone":"America/Mexico_City",
    "iso:country":"MX",
    "name:spa_x_preferred":[
        "Guayabalito"
    ],
    "wof:name":"Guayabalito",
    "wof:placetype":"locality"
},
  "geometry": {"coordinates":[-96.43097,19.33897],"type":"Point"}
}