{
  "type": "Feature",
  "properties": {
    "gn:admin1_code":"6",
    "gn:admin2_code":"61.0",
    "gn:asciiname":"San Antonio de los Chacon",
    "gn:cc2":"MX",
    "gn:country_code":"MX",
    "gn:dem":1449,
    "gn:feature_class":"P",
    "gn:feature_code":"PPL",
    "gn:name":"San Antonio de los Chac\u00f3n",
    "gn:population":124,
    "gn:timezone":"America/Chihuahua",
    "iso:country":"MX",
    "name:und_x_variant":[
        "San Antonio",
        "San Antonio de Chacones"
    ],
    "wof:name":"San Antonio de los Chacon",
    "wof:placetype":"locality",
    "wof:population":124
},
  "geometry": {"coordinates":[-106.20806,28.03944000000001],"type":"Point"}
}