{
  "type": "Feature",
  "properties": {
    "gn:admin1_code":"11",
    "gn:admin2_code":"20.0",
    "gn:asciiname":"San Antonio de Padua",
    "gn:country_code":"MX",
    "gn:dem":1979,
    "gn:feature_class":"P",
    "gn:feature_code":"PPL",
    "gn:name":"San Antonio de Padua",
    "gn:population":151,
    "gn:timezone":"America/Mexico_City",
    "iso:country":"MX",
    "name:ara_x_preferred":[
        "\u0633\u0627\u0646 \u0627\u0646\u0637\u0648\u0646\u064a\u0648 \u062f\u064a \u0628\u0627\u062f\u0648\u0627"
    ],
    "name:azb_x_preferred":[
        "\u0633\u0627\u0646 \u0622\u0646\u062a\u0648\u0646\u06cc\u0648 \u062f\u0647 \u067e\u0627\u062f\u0648\u0627"
    ],
    "name:fas_x_preferred":[
        "\u0633\u0627\u0646 \u0622\u0646\u062a\u0648\u0646\u06cc\u0648 \u062f\u0647 \u067e\u0627\u062f\u0648\u0627"
    ],
    "wof:name":"San Antonio de Padua",
    "wof:placetype":"locality",
    "wof:population":151
},
  "geometry": {"coordinates":[-101.71693999999999,21.26028],"type":"Point"}
}