{
  "type": "Feature",
  "properties": {
    "gn:admin1_code":"7.0",
    "gn:admin2_code":"2.0",
    "gn:asciiname":"Chupadero del Caballo",
    "gn:country_code":"MX",
    "gn:dem":634,
    "gn:feature_class":"P",
    "gn:feature_code":"PPL",
    "gn:name":"Chupadero del Caballo",
    "gn:population":2,
    "gn:timezone":"America/Matamoros",
    "iso:country":"MX",
    "name:spa_x_preferred":[
        "Chupadero del Caballo"
    ],
    "name:und_x_variant":[
        "Rancho Chupadero del Caballo"
    ],
    "wof:name":"Chupadero del Caballo",
    "wof:placetype":"locality",
    "wof:population":2
},
  "geometry": {"coordinates":[-101.81097,29.38858],"type":"Point"}
}