{
  "type": "Feature",
  "properties": {
    "gn:admin1_code":"11",
    "gn:admin2_code":"4",
    "gn:asciiname":"San Rafael de los Pinas",
    "gn:country_code":"MX",
    "gn:dem":2096,
    "gn:feature_class":"P",
    "gn:feature_code":"PPL",
    "gn:name":"San Rafael de los Pi\u00f1as",
    "gn:population":31,
    "gn:timezone":"America/Mexico_City",
    "iso:country":"MX",
    "name:und_x_variant":[
        "San Rafael de los Pi\u00f1as"
    ],
    "wof:name":"San Rafael de los Pinas",
    "wof:placetype":"locality",
    "wof:population":31
},
  "geometry": {"coordinates":[-100.51333,20.34278],"type":"Point"}
}