{
  "type": "Feature",
  "properties": {
    "gn:admin1_code":"4",
    "gn:admin2_code":"4.0",
    "gn:asciiname":"Lopez Portillo Numero Dos",
    "gn:country_code":"MX",
    "gn:dem":21,
    "gn:feature_class":"P",
    "gn:feature_code":"PPL",
    "gn:name":"L\u00f3pez Portillo N\u00famero Dos",
    "gn:population":0,
    "gn:timezone":"America/Merida",
    "iso:country":"MX",
    "name:spa_x_preferred":[
        "Jos\u00e9 L\u00f3pez Portillo"
    ],
    "name:spa_x_variant":[
        "L\u00f3pez Portillo N\u00famero Dos",
        "L\u00f3pez Portillo N\u00famero 2"
    ],
    "name:und_x_variant":[
        "Nilun",
        "Nilum"
    ],
    "wof:name":"Lopez Portillo Numero Dos",
    "wof:placetype":"locality"
},
  "geometry": {"coordinates":[-90.2546,19.23698],"type":"Point"}
}