{
  "type": "Feature",
  "properties": {
    "gn:admin1_code":"6.0",
    "gn:asciiname":"El Tinaco",
    "gn:country_code":"MX",
    "gn:dem":1299,
    "gn:feature_class":"P",
    "gn:feature_code":"PPL",
    "gn:name":"El Tinaco",
    "gn:population":0,
    "gn:timezone":"America/Chihuahua",
    "iso:country":"MX",
    "name:spa_x_preferred":[
        "El Tinaco"
    ],
    "wof:name":"El Tinaco",
    "wof:placetype":"locality"
},
  "geometry": {"coordinates":[-107.97645,31.09412],"type":"Point"}
}