{
  "type": "Feature",
  "properties": {
    "gn:admin1_code":"6",
    "gn:admin2_code":"35.0",
    "gn:asciiname":"San Francisco",
    "gn:country_code":"MX",
    "gn:dem":1509,
    "gn:feature_class":"P",
    "gn:feature_code":"PPL",
    "gn:name":"San Francisco",
    "gn:population":0,
    "gn:timezone":"America/Chihuahua",
    "iso:country":"MX",
    "name:und_x_variant":[
        "Hacienda San Francisco",
        "San Francisco",
        "Ojo de San Francisco"
    ],
    "wof:name":"San Francisco",
    "wof:placetype":"locality"
},
  "geometry": {"coordinates":[-108.65072000000001,31.23672],"type":"Point"}
}