{
  "type": "Feature",
  "properties": {
    "gn:admin1_code":"6",
    "gn:admin2_code":"2.0",
    "gn:asciiname":"Las Florenas Uno",
    "gn:country_code":"MX",
    "gn:dem":1261,
    "gn:feature_class":"P",
    "gn:feature_code":"PPL",
    "gn:name":"Las Flore\u00f1as Uno",
    "gn:population":4,
    "gn:timezone":"America/Chihuahua",
    "iso:country":"MX",
    "name:und_x_variant":[
        "Las Flore\u00f1as Uno"
    ],
    "wof:name":"Las Florenas Uno",
    "wof:placetype":"locality",
    "wof:population":4
},
  "geometry": {"coordinates":[-105.89111,28.83194],"type":"Point"}
}