{
  "type": "Feature",
  "properties": {
    "gn:admin1_code":"24",
    "gn:admin2_code":"38.0",
    "gn:asciiname":"Doctor Salvador Nava Martinez (Nuevo Santa Rita)",
    "gn:country_code":"MX",
    "gn:dem":167,
    "gn:feature_class":"P",
    "gn:feature_code":"PPL",
    "gn:name":"Doctor Salvador Nava Mart\u00ednez (Nuevo Santa Rita)",
    "gn:population":100,
    "gn:timezone":"America/Mexico_City",
    "iso:country":"MX",
    "name:und_x_variant":[
        "Doctor Salvador Nava Mart\u00ednez (Nuevo Santa Rita)"
    ],
    "wof:name":"Doctor Salvador Nava Martinez (Nuevo Santa Rita)",
    "wof:placetype":"locality",
    "wof:population":100
},
  "geometry": {"coordinates":[-98.69861,21.42167],"type":"Point"}
}