{
  "type": "Feature",
  "properties": {
    "gn:admin1_code":"4",
    "gn:admin2_code":"4.0",
    "gn:asciiname":"Xaxe",
    "gn:cc2":"MX",
    "gn:country_code":"MX",
    "gn:dem":18,
    "gn:feature_class":"P",
    "gn:feature_code":"PPL",
    "gn:name":"Xax\u00e9",
    "gn:population":0,
    "gn:timezone":"America/Merida",
    "iso:country":"MX",
    "name:und_x_variant":[
        "Yax\u00e1",
        "Xax\u00e9"
    ],
    "wof:name":"Xaxe",
    "wof:placetype":"locality"
},
  "geometry": {"coordinates":[-90.53333000000001,19.61667000000001],"type":"Point"}
}