{
  "type": "Feature",
  "properties": {
    "gn:admin1_code":"20",
    "gn:admin2_code":"397.0",
    "gn:asciiname":"Cruz Llorada",
    "gn:country_code":"MX",
    "gn:dem":2111,
    "gn:feature_class":"P",
    "gn:feature_code":"PPL",
    "gn:name":"Cruz Llorada",
    "gn:population":435,
    "gn:timezone":"America/Mexico_City",
    "iso:country":"MX",
    "wof:name":"Cruz Llorada",
    "wof:placetype":"locality",
    "wof:population":435
},
  "geometry": {"coordinates":[-97.66777999999999,17.29028],"type":"Point"}
}