{
  "type": "Feature",
  "properties": {
    "gn:admin1_code":"20",
    "gn:admin2_code":"388.0",
    "gn:asciiname":"Barrio Lluu",
    "gn:country_code":"MX",
    "gn:dem":2282,
    "gn:feature_class":"P",
    "gn:feature_code":"PPL",
    "gn:name":"Barrio Lluu",
    "gn:population":124,
    "gn:timezone":"America/Mexico_City",
    "iso:country":"MX",
    "wof:name":"Barrio Lluu",
    "wof:placetype":"locality",
    "wof:population":124
},
  "geometry": {"coordinates":[-96.85722,16.92222000000001],"type":"Point"}
}