{
  "type": "Feature",
  "properties": {
    "gn:admin1_code":"5.0",
    "gn:admin2_code":"99.0",
    "gn:asciiname":"Tanjob",
    "gn:country_code":"MX",
    "gn:dem":1461,
    "gn:feature_class":"P",
    "gn:feature_code":"PPL",
    "gn:name":"Tanjob",
    "gn:population":0,
    "gn:timezone":"America/Mexico_City",
    "iso:country":"MX",
    "name:spa_x_preferred":[
        "Tanjob"
    ],
    "wof:name":"Tanjob",
    "wof:placetype":"locality"
},
  "geometry": {"coordinates":[-91.80598999999999,16.08455],"type":"Point"}
}