{
  "type": "Feature",
  "properties": {
    "gn:admin1_code":"5",
    "gn:admin2_code":"40.0",
    "gn:asciiname":"Canton las Morenas",
    "gn:country_code":"MX",
    "gn:dem":17,
    "gn:feature_class":"P",
    "gn:feature_code":"PPL",
    "gn:name":"Cant\u00f3n las Morenas",
    "gn:population":280,
    "gn:timezone":"America/Mexico_City",
    "iso:country":"MX",
    "name:und_x_variant":[
        "Cant\u00f3n las Morenas"
    ],
    "wof:name":"Canton las Morenas",
    "wof:placetype":"locality",
    "wof:population":280
},
  "geometry": {"coordinates":[-92.58917,15.11361],"type":"Point"}
}