{
  "type": "Feature",
  "properties": {
    "gn:admin1_code":"11",
    "gn:admin2_code":"8",
    "gn:asciiname":"La Escondida",
    "gn:country_code":"MX",
    "gn:dem":1729,
    "gn:feature_class":"P",
    "gn:feature_code":"PPL",
    "gn:name":"La Escondida",
    "gn:population":21,
    "gn:timezone":"America/Mexico_City",
    "iso:country":"MX",
    "wof:name":"La Escondida",
    "wof:placetype":"locality",
    "wof:population":21
},
  "geometry": {"coordinates":[-101.88916999999999,20.80111],"type":"Point"}
}