{
  "type": "Feature",
  "properties": {
    "gn:admin1_code":"16",
    "gn:admin2_code":"3.0",
    "gn:asciiname":"La Presa",
    "gn:country_code":"MX",
    "gn:dem":1840,
    "gn:feature_class":"P",
    "gn:feature_code":"PPL",
    "gn:name":"La Presa",
    "gn:population":759,
    "gn:timezone":"America/Mexico_City",
    "iso:country":"MX",
    "wof:name":"La Presa",
    "wof:placetype":"locality",
    "wof:population":759
},
  "geometry": {"coordinates":[-101.03749999999999,19.90083],"type":"Point"}
}