{
  "type": "Feature",
  "properties": {
    "gn:admin1_code":"6",
    "gn:admin2_code":"65.0",
    "gn:asciiname":"Erisiochi",
    "gn:country_code":"MX",
    "gn:dem":1868,
    "gn:feature_class":"P",
    "gn:feature_code":"PPL",
    "gn:name":"Erisiochi",
    "gn:population":0,
    "gn:timezone":"America/Chihuahua",
    "iso:country":"MX",
    "name:spa_x_preferred":[
        "Erisiochi"
    ],
    "wof:name":"Erisiochi",
    "wof:placetype":"locality"
},
  "geometry": {"coordinates":[-108.07662999999999,27.23536],"type":"Point"}
}