{
  "type": "Feature",
  "properties": {
    "gn:admin1_code":"20",
    "gn:admin2_code":"210",
    "gn:asciiname":"Pie de Mogote",
    "gn:country_code":"MX",
    "gn:dem":2145,
    "gn:feature_class":"P",
    "gn:feature_code":"PPL",
    "gn:name":"Pie de Mogote",
    "gn:population":29,
    "gn:timezone":"America/Mexico_City",
    "iso:country":"MX",
    "wof:name":"Pie de Mogote",
    "wof:placetype":"locality",
    "wof:population":29
},
  "geometry": {"coordinates":[-97.70528,17.39306],"type":"Point"}
}