{
  "type": "Feature",
  "properties": {
    "gn:admin1_code":"6",
    "gn:admin2_code":"65.0",
    "gn:asciiname":"El Aguaje",
    "gn:country_code":"MX",
    "gn:dem":1546,
    "gn:feature_class":"P",
    "gn:feature_code":"PPL",
    "gn:name":"El Aguaje",
    "gn:population":7,
    "gn:timezone":"America/Chihuahua",
    "iso:country":"MX",
    "wof:name":"El Aguaje",
    "wof:placetype":"locality",
    "wof:population":7
},
  "geometry": {"coordinates":[-108.13658,27.13881],"type":"Point"}
}