{
  "type": "Feature",
  "properties": {
    "gn:admin1_code":"6",
    "gn:admin2_code":"17.0",
    "gn:asciiname":"La Selya",
    "gn:country_code":"MX",
    "gn:dem":1967,
    "gn:feature_class":"P",
    "gn:feature_code":"PPL",
    "gn:name":"La Selya",
    "gn:population":0,
    "gn:timezone":"America/Chihuahua",
    "iso:country":"MX",
    "wof:name":"La Selya",
    "wof:placetype":"locality"
},
  "geometry": {"coordinates":[-106.71666999999999,28.56667],"type":"Point"}
}