{
  "type": "Feature",
  "properties": {
    "gn:admin1_code":"30",
    "gn:admin2_code":"84.0",
    "gn:asciiname":"Majapa (Mata Lagarto)",
    "gn:country_code":"MX",
    "gn:dem":8,
    "gn:feature_class":"P",
    "gn:feature_code":"PPL",
    "gn:name":"Majapa (Mata Lagarto)",
    "gn:population":66,
    "gn:timezone":"America/Mexico_City",
    "iso:country":"MX",
    "wof:name":"Majapa (Mata Lagarto)",
    "wof:placetype":"locality",
    "wof:population":66
},
  "geometry": {"coordinates":[-95.89028,18.44056],"type":"Point"}
}