{
  "type": "Feature",
  "properties": {
    "gn:admin1_code":"8",
    "gn:admin2_code":"4.0",
    "gn:asciiname":"El Charro Uno",
    "gn:country_code":"MX",
    "gn:dem":332,
    "gn:feature_class":"P",
    "gn:feature_code":"PPL",
    "gn:name":"El Charro Uno",
    "gn:population":6,
    "gn:timezone":"America/Mexico_City",
    "iso:country":"MX",
    "wof:name":"El Charro Uno",
    "wof:placetype":"locality",
    "wof:population":6
},
  "geometry": {"coordinates":[-103.82138999999999,19.2075],"type":"Point"}
}