{
  "type": "Feature",
  "properties": {
    "gn:admin1_code":"6.0",
    "gn:admin2_code":"45.0",
    "gn:asciiname":"Lomas del Consuelo",
    "gn:country_code":"MX",
    "gn:dem":1143,
    "gn:feature_class":"P",
    "gn:feature_code":"PPL",
    "gn:name":"Lomas del Consuelo",
    "gn:population":0,
    "gn:timezone":"America/Chihuahua",
    "iso:country":"MX",
    "name:und_x_variant":[
        "Consuelo",
        "El Consuelo",
        "Lomas del Consuelo"
    ],
    "wof:name":"Lomas del Consuelo",
    "wof:placetype":"locality"
},
  "geometry": {"coordinates":[-105.46375999999999,28.31502],"type":"Point"}
}