{
  "type": "Feature",
  "properties": {
    "gn:admin1_code":"15",
    "gn:asciiname":"Polvorones",
    "gn:country_code":"MX",
    "gn:dem":2500,
    "gn:feature_class":"P",
    "gn:feature_code":"PPL",
    "gn:name":"Polvorones",
    "gn:population":0,
    "gn:timezone":"America/Mexico_City",
    "iso:country":"MX",
    "name:spa_x_preferred":[
        "Polvorones"
    ],
    "wof:name":"Polvorones",
    "wof:placetype":"locality"
},
  "geometry": {"coordinates":[-98.78534999999999,19.54407],"type":"Point"}
}