{
  "type": "Feature",
  "properties": {
    "gn:admin1_code":"7.0",
    "gn:admin2_code":"3.0",
    "gn:asciiname":"Moncivais",
    "gn:country_code":"MX",
    "gn:dem":448,
    "gn:feature_class":"P",
    "gn:feature_code":"PPL",
    "gn:name":"Monciv\u00e1is",
    "gn:population":0,
    "gn:timezone":"America/Monterrey",
    "iso:country":"MX",
    "name:spa_x_preferred":[
        "Monciv\u00e1is"
    ],
    "wof:name":"Moncivais",
    "wof:placetype":"locality"
},
  "geometry": {"coordinates":[-100.90778,28.24067],"type":"Point"}
}