{
  "type": "Feature",
  "properties": {
    "gn:admin1_code":"19.0",
    "gn:asciiname":"Villarreal",
    "gn:country_code":"MX",
    "gn:dem":670,
    "gn:feature_class":"P",
    "gn:feature_code":"PPL",
    "gn:name":"Villarreal",
    "gn:population":0,
    "gn:timezone":"America/Monterrey",
    "iso:country":"MX",
    "name:spa_x_preferred":[
        "Villarreal"
    ],
    "wof:name":"Villarreal",
    "wof:placetype":"locality"
},
  "geometry": {"coordinates":[-100.51796,25.79723],"type":"Point"}
}