{
  "type": "Feature",
  "properties": {
    "gn:admin1_code":"18.0",
    "gn:admin2_code":"11.0",
    "gn:asciiname":"Los Fortines",
    "gn:country_code":"MX",
    "gn:dem":1206,
    "gn:feature_class":"P",
    "gn:feature_code":"PPL",
    "gn:name":"Los Fortines",
    "gn:population":0,
    "gn:timezone":"America/Mazatlan",
    "iso:country":"MX",
    "name:spa_x_preferred":[
        "Los Fortines"
    ],
    "wof:name":"Los Fortines",
    "wof:placetype":"locality"
},
  "geometry": {"coordinates":[-104.87905000000001,22.11379],"type":"Point"}
}