{
  "type": "Feature",
  "properties": {
    "gn:admin1_code":"6",
    "gn:admin2_code":"66.0",
    "gn:asciiname":"Las Estrellas",
    "gn:country_code":"MX",
    "gn:dem":2545,
    "gn:feature_class":"P",
    "gn:feature_code":"PPL",
    "gn:name":"Las Estrellas",
    "gn:population":0,
    "gn:timezone":"America/Chihuahua",
    "iso:country":"MX",
    "name:ara_x_preferred":[
        "\u0642\u0646\u0627\u0629 \u0627\u0644\u0646\u062c\u0648\u0645"
    ],
    "name:ast_x_preferred":[
        "Las Estrellas"
    ],
    "name:bul_x_preferred":[
        "\u041b\u0430\u0441 \u0435\u0441\u0442\u0440\u0435\u044f\u0441"
    ],
    "name:deu_x_preferred":[
        "Las Estrellas"
    ],
    "name:fra_x_preferred":[
        "Las Estrellas"
    ],
    "name:ita_x_preferred":[
        "Las Estrellas"
    ],
    "name:jpn_x_preferred":[
        "\u30e9\u30b9\u30fb\u30a8\u30b9\u30c8\u30ec\u30fc\u30b8\u30e3\u30b9"
    ],
    "name:kor_x_preferred":[
        "\ub77c\uc2a4 \uc5d0\uc2a4\ud2b8\ub808\uc57c\uc2a4"
    ],
    "name:pol_x_preferred":[
        "Las Estrellas"
    ],
    "name:por_x_preferred":[
        "Las Estrellas"
    ],
    "name:rus_x_preferred":[
        "Las Estrellas"
    ],
    "name:spa_x_preferred":[
        "Las Estrellas"
    ],
    "name:swe_x_preferred":[
        "Las Estrellas"
    ],
    "name:tgl_x_preferred":[
        "Las Estrellas"
    ],
    "wof:name":"Las Estrellas",
    "wof:placetype":"locality"
},
  "geometry": {"coordinates":[-108.15062,27.73587],"type":"Point"}
}