{
  "type": "Feature",
  "properties": {
    "gn:admin1_code":"6",
    "gn:admin2_code":"61.0",
    "gn:asciiname":"La Carreta",
    "gn:country_code":"MX",
    "gn:dem":1388,
    "gn:feature_class":"P",
    "gn:feature_code":"PPL",
    "gn:name":"La Carreta",
    "gn:population":6,
    "gn:timezone":"America/Chihuahua",
    "iso:country":"MX",
    "wof:name":"La Carreta",
    "wof:placetype":"locality",
    "wof:population":6
},
  "geometry": {"coordinates":[-106.14082999999999,27.96806],"type":"Point"}
}