{
  "type": "Feature",
  "properties": {
    "gn:admin1_code":"2.0",
    "gn:admin2_code":"4.0",
    "gn:asciiname":"Lopez",
    "gn:country_code":"MX",
    "gn:dem":247,
    "gn:feature_class":"P",
    "gn:feature_code":"PPL",
    "gn:name":"L\u00f3pez",
    "gn:population":0,
    "gn:timezone":"America/Tijuana",
    "iso:country":"MX",
    "name:spa_x_preferred":[
        "L\u00f3pez"
    ],
    "wof:name":"Lopez",
    "wof:placetype":"locality"
},
  "geometry": {"coordinates":[-116.75076,32.53072],"type":"Point"}
}