{
  "type": "Feature",
  "properties": {
    "gn:admin1_code":"10.0",
    "gn:admin2_code":"4.0",
    "gn:asciiname":"San Diego de Arriba",
    "gn:country_code":"MX",
    "gn:dem":1302,
    "gn:feature_class":"P",
    "gn:feature_code":"PPL",
    "gn:name":"San Diego de Arriba",
    "gn:population":0,
    "gn:timezone":"America/Monterrey",
    "iso:country":"MX",
    "name:spa_x_preferred":[
        "San Diego de Arriba"
    ],
    "wof:name":"San Diego de Arriba",
    "wof:placetype":"locality"
},
  "geometry": {"coordinates":[-103.60993000000001,25.19288],"type":"Point"}
}