{
  "type": "Feature",
  "properties": {
    "gn:admin1_code":"13",
    "gn:admin2_code":"2.0",
    "gn:asciiname":"Coyametepec",
    "gn:country_code":"MX",
    "gn:dem":2338,
    "gn:feature_class":"P",
    "gn:feature_code":"PPL",
    "gn:name":"Coyametepec",
    "gn:population":666,
    "gn:timezone":"America/Mexico_City",
    "iso:country":"MX",
    "wof:name":"Coyametepec",
    "wof:placetype":"locality",
    "wof:population":666
},
  "geometry": {"coordinates":[-98.19667,20.11528],"type":"Point"}
}