{
  "type": "Feature",
  "properties": {
    "gn:admin1_code":"6.0",
    "gn:admin2_code":"7.0",
    "gn:asciiname":"Cerro Blanco",
    "gn:country_code":"MX",
    "gn:dem":2347,
    "gn:feature_class":"P",
    "gn:feature_code":"PPL",
    "gn:name":"Cerro Blanco",
    "gn:population":0,
    "gn:timezone":"America/Chihuahua",
    "iso:country":"MX",
    "name:spa_x_preferred":[
        "Cerro Blanco"
    ],
    "name:und_x_variant":[
        "Rancho Cerro Blanco"
    ],
    "wof:name":"Cerro Blanco",
    "wof:placetype":"locality"
},
  "geometry": {"coordinates":[-106.7854,26.91253],"type":"Point"}
}