{
  "type": "Feature",
  "properties": {
    "gn:admin1_code":"5.0",
    "gn:asciiname":"El Sabino",
    "gn:country_code":"MX",
    "gn:dem":990,
    "gn:feature_class":"P",
    "gn:feature_code":"PPL",
    "gn:name":"El Sabino",
    "gn:population":0,
    "gn:timezone":"America/Mexico_City",
    "iso:country":"MX",
    "name:spa_x_preferred":[
        "El Sabino"
    ],
    "wof:name":"El Sabino",
    "wof:placetype":"locality"
},
  "geometry": {"coordinates":[-93.41750999999999,16.58484],"type":"Point"}
}