{
  "type": "Feature",
  "properties": {
    "gn:admin1_code":"19",
    "gn:admin2_code":"17.0",
    "gn:asciiname":"El Veinte",
    "gn:country_code":"MX",
    "gn:dem":1880,
    "gn:feature_class":"P",
    "gn:feature_code":"PPL",
    "gn:name":"El Veinte",
    "gn:population":0,
    "gn:timezone":"America/Monterrey",
    "iso:country":"MX",
    "name:spa_x_preferred":[
        "El Veinte"
    ],
    "wof:name":"El Veinte",
    "wof:placetype":"locality"
},
  "geometry": {"coordinates":[-100.67627,25.0093],"type":"Point"}
}