{
  "type": "Feature",
  "properties": {
    "gn:admin1_code":"28",
    "gn:admin2_code":"41.0",
    "gn:asciiname":"La Penita",
    "gn:country_code":"MX",
    "gn:dem":267,
    "gn:feature_class":"P",
    "gn:feature_code":"PPL",
    "gn:name":"La Pe\u00f1ita",
    "gn:population":0,
    "gn:timezone":"America/Monterrey",
    "iso:country":"MX",
    "name:und_x_variant":[
        "Pe\u00f1itas",
        "La Pe\u00f1ita"
    ],
    "wof:name":"La Penita",
    "wof:placetype":"locality"
},
  "geometry": {"coordinates":[-99.25547,23.94364],"type":"Point"}
}