{
  "type": "Feature",
  "properties": {
    "gn:admin1_code":"7.0",
    "gn:admin2_code":"28.0",
    "gn:asciiname":"Los Frentones",
    "gn:country_code":"MX",
    "gn:dem":350,
    "gn:feature_class":"P",
    "gn:feature_code":"PPL",
    "gn:name":"Los Frentones",
    "gn:population":0,
    "gn:timezone":"America/Monterrey",
    "iso:country":"MX",
    "name:ceb_x_preferred":[
        "Los Frentones"
    ],
    "name:ita_x_preferred":[
        "Los Frentones"
    ],
    "name:por_x_preferred":[
        "Los Frentones"
    ],
    "name:spa_x_preferred":[
        "Los Frentones"
    ],
    "name:swe_x_preferred":[
        "Los Frentones"
    ],
    "wof:name":"Los Frentones",
    "wof:placetype":"locality"
},
  "geometry": {"coordinates":[-101.08194,27.8813],"type":"Point"}
}