{
  "type": "Feature",
  "properties": {
    "gn:admin1_code":"15",
    "gn:admin2_code":"118.0",
    "gn:asciiname":"Colonia Praztitlan (Colonia de los Ingenieros)",
    "gn:country_code":"MX",
    "gn:dem":2712,
    "gn:feature_class":"P",
    "gn:feature_code":"PPL",
    "gn:name":"Colonia Praztitl\u00e1n (Colonia de los Ingenieros)",
    "gn:population":253,
    "gn:timezone":"America/Mexico_City",
    "iso:country":"MX",
    "name:und_x_variant":[
        "Colonia Praztitl\u00e1n (Colonia de los Ingenieros)"
    ],
    "wof:name":"Colonia Praztitlan (Colonia de los Ingenieros)",
    "wof:placetype":"locality",
    "wof:population":253
},
  "geometry": {"coordinates":[-99.74411000000001,19.31723],"type":"Point"}
}