{
  "type": "Feature",
  "properties": {
    "gn:admin1_code":"20",
    "gn:admin2_code":"327",
    "gn:asciiname":"Barrio Galeana",
    "gn:country_code":"MX",
    "gn:dem":58,
    "gn:feature_class":"P",
    "gn:feature_code":"PPL",
    "gn:name":"Barrio Galeana",
    "gn:population":13,
    "gn:timezone":"America/Mexico_City",
    "iso:country":"MX",
    "wof:name":"Barrio Galeana",
    "wof:placetype":"locality",
    "wof:population":13
},
  "geometry": {"coordinates":[-94.20361,16.3625],"type":"Point"}
}