{
  "type": "Feature",
  "properties": {
    "gn:admin1_code":"24",
    "gn:admin2_code":"41.0",
    "gn:asciiname":"Monec",
    "gn:country_code":"MX",
    "gn:dem":56,
    "gn:feature_class":"P",
    "gn:feature_code":"PPL",
    "gn:name":"Monec",
    "gn:population":0,
    "gn:timezone":"America/Mexico_City",
    "iso:country":"MX",
    "name:spa_x_preferred":[
        "Monec"
    ],
    "wof:name":"Monec",
    "wof:placetype":"locality"
},
  "geometry": {"coordinates":[-98.86986,21.70944],"type":"Point"}
}