{
  "type": "Feature",
  "properties": {
    "gn:admin1_code":"7.0",
    "gn:admin2_code":"31.0",
    "gn:asciiname":"Agua de Agueero",
    "gn:country_code":"MX",
    "gn:dem":497,
    "gn:feature_class":"P",
    "gn:feature_code":"PPL",
    "gn:name":"Agua de Ag\u00fcero",
    "gn:population":0,
    "gn:timezone":"America/Monterrey",
    "iso:country":"MX",
    "name:und_x_variant":[
        "Agua de Agriero",
        "Agua de Ag\u00fcero"
    ],
    "wof:name":"Agua de Agueero",
    "wof:placetype":"locality"
},
  "geometry": {"coordinates":[-101.55,27.25],"type":"Point"}
}