{
  "type": "Feature",
  "properties": {
    "gn:admin1_code":"26.0",
    "gn:asciiname":"Los Chinitos",
    "gn:country_code":"MX",
    "gn:dem":420,
    "gn:feature_class":"P",
    "gn:feature_code":"PPL",
    "gn:name":"Los Chinitos",
    "gn:population":0,
    "gn:timezone":"America/Hermosillo",
    "iso:country":"MX",
    "name:spa_x_preferred":[
        "Los Chinitos"
    ],
    "wof:name":"Los Chinitos",
    "wof:placetype":"locality"
},
  "geometry": {"coordinates":[-109.55134,27.82177],"type":"Point"}
}