{
  "type": "Feature",
  "properties": {
    "gn:admin1_code":"13",
    "gn:admin2_code":"14.0",
    "gn:asciiname":"Tecueyaca",
    "gn:country_code":"MX",
    "gn:dem":1389,
    "gn:feature_class":"P",
    "gn:feature_code":"PPL",
    "gn:name":"Tecueyaca",
    "gn:population":376,
    "gn:timezone":"America/Mexico_City",
    "iso:country":"MX",
    "name:spa_x_preferred":[
        "Tecueyaca"
    ],
    "wof:name":"Tecueyaca",
    "wof:placetype":"locality",
    "wof:population":376
},
  "geometry": {"coordinates":[-98.61299,20.92741],"type":"Point"}
}