{
  "type": "Feature",
  "properties": {
    "gn:admin1_code":"20",
    "gn:admin2_code":"403.0",
    "gn:asciiname":"Fraccionamiento Proyecto 2000",
    "gn:country_code":"MX",
    "gn:dem":1519,
    "gn:feature_class":"P",
    "gn:feature_code":"PPL",
    "gn:name":"Fraccionamiento Proyecto 2000",
    "gn:population":92,
    "gn:timezone":"America/Mexico_City",
    "iso:country":"MX",
    "wof:name":"Fraccionamiento Proyecto 2000",
    "wof:placetype":"locality",
    "wof:population":92
},
  "geometry": {"coordinates":[-96.70972,16.98082999999999],"type":"Point"}
}