{
  "type": "Feature",
  "properties": {
    "gn:admin1_code":"12",
    "gn:admin2_code":"31.0",
    "gn:asciiname":"Las Ceibitas",
    "gn:country_code":"MX",
    "gn:dem":1391,
    "gn:feature_class":"P",
    "gn:feature_code":"PPL",
    "gn:name":"Las Ceibitas",
    "gn:population":113,
    "gn:timezone":"America/Mexico_City",
    "iso:country":"MX",
    "wof:name":"Las Ceibitas",
    "wof:placetype":"locality",
    "wof:population":113
},
  "geometry": {"coordinates":[-100.08289000000001,18.40078],"type":"Point"}
}