{
  "type": "Feature",
  "properties": {
    "gn:admin1_code":"14",
    "gn:admin2_code":"74",
    "gn:asciiname":"Pacheco",
    "gn:country_code":"MX",
    "gn:dem":1977,
    "gn:feature_class":"P",
    "gn:feature_code":"PPL",
    "gn:name":"Pacheco",
    "gn:population":10,
    "gn:timezone":"America/Mexico_City",
    "iso:country":"MX",
    "wof:name":"Pacheco",
    "wof:placetype":"locality",
    "wof:population":10
},
  "geometry": {"coordinates":[-102.16583,21.08667],"type":"Point"}
}