{
  "type": "Feature",
  "properties": {
    "gn:admin1_code":"16",
    "gn:admin2_code":"34.0",
    "gn:asciiname":"Terrero Obscuro",
    "gn:country_code":"MX",
    "gn:dem":2191,
    "gn:feature_class":"P",
    "gn:feature_code":"PPL",
    "gn:name":"Terrero Obscuro",
    "gn:population":0,
    "gn:timezone":"America/Mexico_City",
    "iso:country":"MX",
    "name:spa_x_preferred":[
        "Terrero Obscuro"
    ],
    "wof:name":"Terrero Obscuro",
    "wof:placetype":"locality"
},
  "geometry": {"coordinates":[-100.72516,19.44675],"type":"Point"}
}