{
  "type": "Feature",
  "properties": {
    "gn:admin1_code":"7",
    "gn:admin2_code":"23.0",
    "gn:asciiname":"Puerto Arturo",
    "gn:country_code":"MX",
    "gn:dem":1189,
    "gn:feature_class":"P",
    "gn:feature_code":"PPL",
    "gn:name":"Puerto Arturo",
    "gn:population":0,
    "gn:timezone":"America/Monterrey",
    "iso:country":"MX",
    "name:spa_x_preferred":[
        "Puerto Arturo"
    ],
    "name:spa_x_variant":[
        "El Caballo"
    ],
    "name:und_x_variant":[
        "Rancho El Caballo"
    ],
    "wof:name":"Puerto Arturo",
    "wof:placetype":"locality"
},
  "geometry": {"coordinates":[-103.06010000000001,27.56851],"type":"Point"}
}