{
  "type": "Feature",
  "properties": {
    "gn:admin1_code":"15",
    "gn:admin2_code":"118.0",
    "gn:asciiname":"Colonia la Virgen",
    "gn:country_code":"MX",
    "gn:dem":2714,
    "gn:feature_class":"P",
    "gn:feature_code":"PPL",
    "gn:name":"Colonia la Virgen",
    "gn:population":562,
    "gn:timezone":"America/Mexico_City",
    "iso:country":"MX",
    "wof:name":"Colonia la Virgen",
    "wof:placetype":"locality",
    "wof:population":562
},
  "geometry": {"coordinates":[-99.72611000000001,19.30361],"type":"Point"}
}