{
  "type": "Feature",
  "properties": {
    "gn:admin1_code":"5.0",
    "gn:asciiname":"San Marcos",
    "gn:country_code":"MX",
    "gn:dem":689,
    "gn:feature_class":"P",
    "gn:feature_code":"PPL",
    "gn:name":"San Marcos",
    "gn:population":0,
    "gn:timezone":"America/Mexico_City",
    "iso:country":"MX",
    "name:spa_x_preferred":[
        "San Marcos"
    ],
    "wof:name":"San Marcos",
    "wof:placetype":"locality"
},
  "geometry": {"coordinates":[-92.10505000000001,16.01406],"type":"Point"}
}