{
  "type": "Feature",
  "properties": {
    "gn:admin1_code":"12.0",
    "gn:asciiname":"Laguna Grande",
    "gn:country_code":"MX",
    "gn:dem":1821,
    "gn:feature_class":"P",
    "gn:feature_code":"PPL",
    "gn:name":"Laguna Grande",
    "gn:population":0,
    "gn:timezone":"America/Mexico_City",
    "iso:country":"MX",
    "name:spa_x_preferred":[
        "Laguna Grande"
    ],
    "wof:name":"Laguna Grande",
    "wof:placetype":"locality"
},
  "geometry": {"coordinates":[-100.45657,18.85191],"type":"Point"}
}