{
  "type": "Feature",
  "properties": {
    "iso:country":"MX",
    "name:ara_x_preferred":[
        "\u0633\u0627\u0646\u062a\u0627 \u0633\u064a\u0633\u064a\u0644\u064a\u0627"
    ],
    "name:arg_x_preferred":[
        "Santa Cecilia"
    ],
    "name:azb_x_preferred":[
        "\u0633\u0627\u0646\u062a\u0627 \u0633\u0633\u06cc\u0644\u06cc\u0627"
    ],
    "name:cat_x_preferred":[
        "Santa Cecilia"
    ],
    "name:epo_x_preferred":[
        "Santa Cecilia"
    ],
    "name:eus_x_preferred":[
        "Santa Cecilia"
    ],
    "name:fas_x_preferred":[
        "\u0633\u0627\u0646\u062a\u0627 \u0633\u0633\u06cc\u0644\u06cc\u0627"
    ],
    "name:fra_x_preferred":[
        "Santa Cecilia"
    ],
    "name:glg_x_preferred":[
        "Santa Cecilia"
    ],
    "name:haw_x_preferred":[
        "Santa Cecilia"
    ],
    "name:hun_x_preferred":[
        "Santa Cecilia"
    ],
    "name:ina_x_preferred":[
        "Santa Cecilia"
    ],
    "name:ita_x_preferred":[
        "Santa Cecilia"
    ],
    "name:msa_x_preferred":[
        "Santa Cecilia"
    ],
    "name:nld_x_preferred":[
        "Santa Cecilia"
    ],
    "name:oci_x_preferred":[
        "Santa Cecilia"
    ],
    "name:pol_x_preferred":[
        "Santa Cecilia"
    ],
    "name:por_x_preferred":[
        "Santa Cecilia"
    ],
    "name:rus_x_preferred":[
        "\u0421\u0430\u043d\u0442\u0430-\u0421\u0435\u0441\u0438\u043b\u0438\u044f"
    ],
    "name:spa_x_preferred":[
        "Santa Cecilia"
    ],
    "name:ukr_x_preferred":[
        "\u0421\u0430\u043d\u0442\u0430-\u0421\u0435\u0441\u0456\u043b\u0456\u044f"
    ],
    "name:vie_x_preferred":[
        "Santa Cecilia"
    ],
    "name:war_x_preferred":[
        "Santa Cecilia"
    ],
    "name:zho_x_preferred":[
        "\u5723\u585e\u897f\u5229\u4e9a"
    ],
    "qs_pg:aaroncc":"MX",
    "qs_pg:name":"Santa Cecilia",
    "qs_pg:name_adm0":"M\u00e9xico",
    "qs_pg:name_adm1":"Chiapas",
    "qs_pg:photos":1,
    "qs_pg:photos_1k":1,
    "qs_pg:photos_9k":1,
    "qs_pg:photos_9r":1,
    "qs_pg:photos_all":1,
    "qs_pg:photos_sr":1,
    "qs_pg:pop_sr":0,
    "qs_pg:qs_pg_placetype":"neighbourhood",
    "qs_pg:qs_pg_placetype_gp":"Suburb",
    "qs_pg:woe_adm0":23424900,
    "woe:adm0_id":23424900,
    "woe:name_adm0":"M\u00e9xico",
    "woe:name_adm1":"Chiapas",
    "woe:placetype":"Suburb",
    "wof:name":"Santa Cecilia",
    "wof:placetype":"neighbourhood"
},
  "geometry": {"coordinates":[-92.641525,16.7372405],"type":"Point"}
}