{
  "type": "Feature",
  "properties": {
    "gn:admin1_code":"20",
    "gn:admin2_code":"324.0",
    "gn:asciiname":"La Cienega III",
    "gn:country_code":"MX",
    "gn:dem":142,
    "gn:feature_class":"P",
    "gn:feature_code":"PPL",
    "gn:name":"La Ci\u00e9nega III",
    "gn:population":88,
    "gn:timezone":"America/Mexico_City",
    "iso:country":"MX",
    "name:und_x_variant":[
        "La Ci\u00e9nega III"
    ],
    "wof:name":"La Cienega III",
    "wof:placetype":"locality",
    "wof:population":88
},
  "geometry": {"coordinates":[-96.48917,15.68222],"type":"Point"}
}