{
  "type": "Feature",
  "properties": {
    "gn:admin1_code":"25",
    "gn:admin2_code":"13.0",
    "gn:asciiname":"Santa Rosario",
    "gn:country_code":"MX",
    "gn:dem":69,
    "gn:feature_class":"P",
    "gn:feature_code":"PPL",
    "gn:name":"Santa Rosario",
    "gn:population":0,
    "gn:timezone":"America/Mazatlan",
    "iso:country":"MX",
    "name:spa_x_preferred":[
        "Santa Rosario"
    ],
    "name:spa_x_variant":[
        "Campo Fortino"
    ],
    "wof:name":"Santa Rosario",
    "wof:placetype":"locality"
},
  "geometry": {"coordinates":[-107.70112,25.12694],"type":"Point"}
}