{
  "type": "Feature",
  "properties": {
    "gn:admin1_code":"5.0",
    "gn:admin2_code":"59.0",
    "gn:asciiname":"Patate Viejo",
    "gn:country_code":"MX",
    "gn:dem":1235,
    "gn:feature_class":"P",
    "gn:feature_code":"PPL",
    "gn:name":"Patat\u00e9 Viejo",
    "gn:population":0,
    "gn:timezone":"America/Mexico_City",
    "iso:country":"MX",
    "name:spa_x_preferred":[
        "Patat\u00e9 Viejo"
    ],
    "wof:name":"Patate Viejo",
    "wof:placetype":"locality"
},
  "geometry": {"coordinates":[-91.88191,16.77637],"type":"Point"}
}