{
  "type": "Feature",
  "properties": {
    "gn:admin1_code":"30",
    "gn:admin2_code":"43.0",
    "gn:asciiname":"La Malin",
    "gn:country_code":"MX",
    "gn:dem":726,
    "gn:feature_class":"P",
    "gn:feature_code":"PPL",
    "gn:name":"La Mal\u00edn",
    "gn:population":114,
    "gn:timezone":"America/Mexico_City",
    "iso:country":"MX",
    "name:und_x_variant":[
        "La Mal\u00edn"
    ],
    "wof:name":"La Malin",
    "wof:placetype":"locality",
    "wof:population":114
},
  "geometry": {"coordinates":[-96.78610999999999,19.12444],"type":"Point"}
}