{
  "type": "Feature",
  "properties": {
    "gn:admin1_code":"5",
    "gn:admin2_code":"52.0",
    "gn:asciiname":"Plan de Santo Tomas",
    "gn:country_code":"MX",
    "gn:dem":848,
    "gn:feature_class":"P",
    "gn:feature_code":"PPL",
    "gn:name":"Plan de Santo Tom\u00e1s",
    "gn:population":598,
    "gn:timezone":"America/Mexico_City",
    "iso:country":"MX",
    "name:und_x_variant":[
        "Plan de Santo Tom\u00e1s"
    ],
    "wof:name":"Plan de Santo Tomas",
    "wof:placetype":"locality",
    "wof:population":598
},
  "geometry": {"coordinates":[-91.58278,16.41333],"type":"Point"}
}