{
  "type": "Feature",
  "properties": {
    "gn:admin1_code":"10.0",
    "gn:admin2_code":"35.0",
    "gn:asciiname":"Nuevo Lajitas",
    "gn:country_code":"MX",
    "gn:dem":2509,
    "gn:feature_class":"P",
    "gn:feature_code":"PPL",
    "gn:name":"Nuevo Lajitas",
    "gn:population":0,
    "gn:timezone":"America/Monterrey",
    "iso:country":"MX",
    "name:spa_x_preferred":[
        "Nuevo Lajitas"
    ],
    "wof:name":"Nuevo Lajitas",
    "wof:placetype":"locality"
},
  "geometry": {"coordinates":[-106.34744000000001,25.45743],"type":"Point"}
}