{
  "type": "Feature",
  "properties": {
    "gn:admin1_code":"11.0",
    "gn:asciiname":"Ejido de Aldama",
    "gn:country_code":"MX",
    "gn:dem":1772,
    "gn:feature_class":"P",
    "gn:feature_code":"PPL",
    "gn:name":"Ejido de Aldama",
    "gn:population":0,
    "gn:timezone":"America/Mexico_City",
    "iso:country":"MX",
    "name:spa_x_preferred":[
        "Ejido de Aldama"
    ],
    "wof:name":"Ejido de Aldama",
    "wof:placetype":"locality"
},
  "geometry": {"coordinates":[-101.32504,20.83055],"type":"Point"}
}