{
  "type": "Feature",
  "properties": {
    "gn:admin1_code":"10",
    "gn:admin2_code":"19",
    "gn:asciiname":"El Nopal",
    "gn:country_code":"MX",
    "gn:dem":1031,
    "gn:feature_class":"P",
    "gn:feature_code":"PPL",
    "gn:name":"El Nopal",
    "gn:population":41,
    "gn:timezone":"America/Monterrey",
    "iso:country":"MX",
    "wof:name":"El Nopal",
    "wof:placetype":"locality",
    "wof:population":41
},
  "geometry": {"coordinates":[-106.04673,24.69971],"type":"Point"}
}