{
  "type": "Feature",
  "properties": {
    "gn:admin1_code":"28.0",
    "gn:admin2_code":"28.0",
    "gn:asciiname":"El Balcon",
    "gn:country_code":"MX",
    "gn:dem":258,
    "gn:feature_class":"P",
    "gn:feature_code":"PPL",
    "gn:name":"El Balcon",
    "gn:population":0,
    "gn:timezone":"America/Monterrey",
    "iso:country":"MX",
    "name:spa_x_preferred":[
        "El Balcon"
    ],
    "wof:name":"El Balcon",
    "wof:placetype":"locality"
},
  "geometry": {"coordinates":[-99.20019000000001,22.52337],"type":"Point"}
}