{
  "type": "Feature",
  "properties": {
    "gn:admin1_code":"14.0",
    "gn:asciiname":"Corral Blanco",
    "gn:country_code":"MX",
    "gn:dem":1842,
    "gn:feature_class":"P",
    "gn:feature_code":"PPL",
    "gn:name":"Corral Blanco",
    "gn:population":0,
    "gn:timezone":"America/Mexico_City",
    "iso:country":"MX",
    "name:spa_x_preferred":[
        "Corral Blanco"
    ],
    "wof:name":"Corral Blanco",
    "wof:placetype":"locality"
},
  "geometry": {"coordinates":[-102.09447,20.86862],"type":"Point"}
}