{
  "type": "Feature",
  "properties": {
    "gn:admin1_code":"11",
    "gn:admin2_code":"27.0",
    "gn:asciiname":"Salvador Vidal",
    "gn:country_code":"MX",
    "gn:dem":1751,
    "gn:feature_class":"P",
    "gn:feature_code":"PPL",
    "gn:name":"Salvador Vidal",
    "gn:population":8,
    "gn:timezone":"America/Mexico_City",
    "iso:country":"MX",
    "wof:name":"Salvador Vidal",
    "wof:placetype":"locality",
    "wof:population":8
},
  "geometry": {"coordinates":[-101.22194,20.53889],"type":"Point"}
}