{
  "type": "Feature",
  "properties": {
    "gn:admin1_code":"20",
    "gn:admin2_code":"40.0",
    "gn:asciiname":"Santa Catarina Buenavista",
    "gn:country_code":"MX",
    "gn:dem":1229,
    "gn:feature_class":"P",
    "gn:feature_code":"PPL",
    "gn:name":"Santa Catarina Buenavista",
    "gn:population":705,
    "gn:timezone":"America/Mexico_City",
    "iso:country":"MX",
    "wof:name":"Santa Catarina Buenavista",
    "wof:placetype":"locality",
    "wof:population":705
},
  "geometry": {"coordinates":[-96.80417,18.07667],"type":"Point"}
}