{
  "type": "Feature",
  "properties": {
    "gn:admin1_code":"10",
    "gn:admin2_code":"11.0",
    "gn:asciiname":"El Oso",
    "gn:country_code":"MX",
    "gn:dem":1931,
    "gn:feature_class":"P",
    "gn:feature_code":"PPL",
    "gn:name":"El Oso",
    "gn:population":0,
    "gn:timezone":"America/Monterrey",
    "iso:country":"MX",
    "name:spa_x_preferred":[
        "El Oso"
    ],
    "wof:name":"El Oso",
    "wof:placetype":"locality"
},
  "geometry": {"coordinates":[-105.14676,26.00908],"type":"Point"}
}