{
  "type": "Feature",
  "properties": {
    "gn:admin1_code":"13",
    "gn:admin2_code":"17.0",
    "gn:asciiname":"Toxthe",
    "gn:country_code":"MX",
    "gn:dem":2285,
    "gn:feature_class":"P",
    "gn:feature_code":"PPL",
    "gn:name":"Toxthe",
    "gn:population":0,
    "gn:timezone":"America/Mexico_City",
    "iso:country":"MX",
    "name:spa_x_preferred":[
        "Toxth\u00e9"
    ],
    "name:spa_x_variant":[
        "Toxthe"
    ],
    "wof:name":"Toxthe",
    "wof:placetype":"locality"
},
  "geometry": {"coordinates":[-99.45738,20.29816],"type":"Point"}
}