{
  "type": "Feature",
  "properties": {
    "gn:admin1_code":"20",
    "gn:admin2_code":"397.0",
    "gn:asciiname":"Los Blancos",
    "gn:country_code":"MX",
    "gn:dem":2175,
    "gn:feature_class":"P",
    "gn:feature_code":"PPL",
    "gn:name":"Los Blancos",
    "gn:population":76,
    "gn:timezone":"America/Mexico_City",
    "iso:country":"MX",
    "wof:name":"Los Blancos",
    "wof:placetype":"locality",
    "wof:population":76
},
  "geometry": {"coordinates":[-97.64111,17.30083],"type":"Point"}
}