{
  "type": "Feature",
  "properties": {
    "gn:admin1_code":"20",
    "gn:admin2_code":"515.0",
    "gn:asciiname":"Tecuani",
    "gn:country_code":"MX",
    "gn:dem":502,
    "gn:feature_class":"P",
    "gn:feature_code":"PPL",
    "gn:name":"Tecuani",
    "gn:population":0,
    "gn:timezone":"America/Mexico_City",
    "iso:country":"MX",
    "wof:name":"Tecuani",
    "wof:placetype":"locality"
},
  "geometry": {"coordinates":[-95.36667,16.23333],"type":"Point"}
}