{
  "type": "Feature",
  "properties": {
    "gn:admin1_code":"6.0",
    "gn:admin2_code":"15.0",
    "gn:asciiname":"El Viejito",
    "gn:country_code":"MX",
    "gn:dem":1478,
    "gn:feature_class":"P",
    "gn:feature_code":"PPL",
    "gn:name":"El Viejito",
    "gn:population":0,
    "gn:timezone":"America/Chihuahua",
    "iso:country":"MX",
    "name:spa_x_preferred":[
        "El Viejito"
    ],
    "wof:name":"El Viejito",
    "wof:placetype":"locality"
},
  "geometry": {"coordinates":[-105.31780000000001,29.36568],"type":"Point"}
}