{
  "type": "Feature",
  "properties": {
    "gn:admin1_code":"20",
    "gn:admin2_code":"185.0",
    "gn:asciiname":"Alto de las Mesas",
    "gn:country_code":"MX",
    "gn:dem":262,
    "gn:feature_class":"P",
    "gn:feature_code":"PPL",
    "gn:name":"Alto de las Mesas",
    "gn:population":0,
    "gn:timezone":"America/Mexico_City",
    "iso:country":"MX",
    "name:spa_x_preferred":[
        "Alto de las Mesas"
    ],
    "wof:name":"Alto de las Mesas",
    "wof:placetype":"locality"
},
  "geometry": {"coordinates":[-98.16498,16.57542],"type":"Point"}
}