{
  "type": "Feature",
  "properties": {
    "gn:admin1_code":"14",
    "gn:admin2_code":"125",
    "gn:asciiname":"El Bimbalete",
    "gn:country_code":"MX",
    "gn:dem":2074,
    "gn:feature_class":"P",
    "gn:feature_code":"PPL",
    "gn:name":"El Bimbalete",
    "gn:population":13,
    "gn:timezone":"America/Mexico_City",
    "iso:country":"MX",
    "wof:name":"El Bimbalete",
    "wof:placetype":"locality",
    "wof:population":13
},
  "geometry": {"coordinates":[-102.50221999999999,20.76528],"type":"Point"}
}