{
  "type": "Feature",
  "properties": {
    "gn:admin1_code":"14.0",
    "gn:admin2_code":"109.0",
    "gn:asciiname":"Las Negritas",
    "gn:country_code":"MX",
    "gn:dem":1902,
    "gn:feature_class":"P",
    "gn:feature_code":"PPL",
    "gn:name":"Las Negritas",
    "gn:population":0,
    "gn:timezone":"America/Mexico_City",
    "iso:country":"MX",
    "name:spa_x_preferred":[
        "Las Negritas"
    ],
    "wof:name":"Las Negritas",
    "wof:placetype":"locality"
},
  "geometry": {"coordinates":[-101.99903999999999,21.07383],"type":"Point"}
}