{
  "type": "Feature",
  "properties": {
    "gn:admin1_code":"10",
    "gn:admin2_code":"32.0",
    "gn:asciiname":"El Puertecito",
    "gn:country_code":"MX",
    "gn:dem":1523,
    "gn:feature_class":"P",
    "gn:feature_code":"PPL",
    "gn:name":"El Puertecito",
    "gn:population":6,
    "gn:timezone":"America/Monterrey",
    "iso:country":"MX",
    "wof:name":"El Puertecito",
    "wof:placetype":"locality",
    "wof:population":6
},
  "geometry": {"coordinates":[-106.20131000000001,24.96719],"type":"Point"}
}