{
  "type": "Feature",
  "properties": {
    "gn:admin1_code":"14",
    "gn:admin2_code":"8",
    "gn:asciiname":"Huertas Viejas",
    "gn:country_code":"MX",
    "gn:dem":1910,
    "gn:feature_class":"P",
    "gn:feature_code":"PPL",
    "gn:name":"Huertas Viejas",
    "gn:population":24,
    "gn:timezone":"America/Mexico_City",
    "iso:country":"MX",
    "wof:name":"Huertas Viejas",
    "wof:placetype":"locality",
    "wof:population":24
},
  "geometry": {"coordinates":[-102.13916999999999,20.84667],"type":"Point"}
}