{
  "type": "Feature",
  "properties": {
    "gn:admin1_code":"26.0",
    "gn:admin2_code":"65.0",
    "gn:asciiname":"Buenavista",
    "gn:country_code":"MX",
    "gn:dem":737,
    "gn:feature_class":"P",
    "gn:feature_code":"PPL",
    "gn:name":"Buenavista",
    "gn:population":0,
    "gn:timezone":"America/Hermosillo",
    "iso:country":"MX",
    "wof:name":"Buenavista",
    "wof:placetype":"locality"
},
  "geometry": {"coordinates":[-111.34397,30.9265],"type":"Point"}
}