{
  "type": "Feature",
  "properties": {
    "gn:admin1_code":"15",
    "gn:admin2_code":"24.0",
    "gn:asciiname":"Rancho Canta Ranas",
    "gn:country_code":"MX",
    "gn:dem":2248,
    "gn:feature_class":"P",
    "gn:feature_code":"PPL",
    "gn:name":"Rancho Canta Ranas",
    "gn:population":78,
    "gn:timezone":"America/Mexico_City",
    "iso:country":"MX",
    "wof:name":"Rancho Canta Ranas",
    "wof:placetype":"locality",
    "wof:population":78
},
  "geometry": {"coordinates":[-99.14999,19.73648],"type":"Point"}
}