{
  "type": "Feature",
  "properties": {
    "gn:admin1_code":"7",
    "gn:admin2_code":"30.0",
    "gn:asciiname":"El Porvenir",
    "gn:country_code":"MX",
    "gn:dem":1756,
    "gn:feature_class":"P",
    "gn:feature_code":"PPL",
    "gn:name":"El Porvenir",
    "gn:population":3,
    "gn:timezone":"America/Monterrey",
    "iso:country":"MX",
    "name:spa_x_preferred":[
        "El Porvenir"
    ],
    "wof:name":"El Porvenir",
    "wof:placetype":"locality",
    "wof:population":3
},
  "geometry": {"coordinates":[-101.27531,25.29476],"type":"Point"}
}