{
  "type": "Feature",
  "properties": {
    "gn:admin1_code":"6",
    "gn:admin2_code":"27.0",
    "gn:asciiname":"Los Charcos",
    "gn:country_code":"MX",
    "gn:dem":2295,
    "gn:feature_class":"P",
    "gn:feature_code":"PPL",
    "gn:name":"Los Charcos",
    "gn:population":0,
    "gn:timezone":"America/Chihuahua",
    "iso:country":"MX",
    "name:spa_x_preferred":[
        "Los Charcos"
    ],
    "wof:name":"Los Charcos",
    "wof:placetype":"locality"
},
  "geometry": {"coordinates":[-107.0369,27.19521],"type":"Point"}
}