{
  "type": "Feature",
  "properties": {
    "gn:admin1_code":"3.0",
    "gn:admin2_code":"2.0",
    "gn:asciiname":"Guillermo Prieto",
    "gn:country_code":"MX",
    "gn:dem":150,
    "gn:feature_class":"P",
    "gn:feature_code":"PPL",
    "gn:name":"Guillermo Prieto",
    "gn:population":5,
    "gn:timezone":"America/Mazatlan",
    "iso:country":"MX",
    "name:pol_x_preferred":[
        "Guillermo Prieto"
    ],
    "name:spa_x_preferred":[
        "Guillermo Prieto Pradillo"
    ],
    "name:srp_x_preferred":[
        "\u0413\u0438\u0459\u0435\u0440\u043c\u043e \u041f\u0440\u0438\u0458\u0435\u0442\u043e"
    ],
    "wof:name":"Guillermo Prieto",
    "wof:placetype":"locality",
    "wof:population":5
},
  "geometry": {"coordinates":[-113.29861,27.84222],"type":"Point"}
}