{
  "type": "Feature",
  "properties": {
    "gn:admin1_code":"3.0",
    "gn:admin2_code":"2.0",
    "gn:asciiname":"Guillermo Prieto",
    "gn:country_code":"MX",
    "gn:dem":150,
    "gn:feature_class":"P",
    "gn:feature_code":"PPL",
    "gn:name":"Guillermo Prieto",
    "gn:population":5,
    "gn:timezone":"America/Mazatlan",
    "iso:country":"MX",
    "wof:name":"Guillermo Prieto",
    "wof:placetype":"locality",
    "wof:population":5
},
  "geometry": {"coordinates":[-113.29861,27.84222],"type":"Point"}
}