{
  "type": "Feature",
  "properties": {
    "gn:admin1_code":"5",
    "gn:admin2_code":"57.0",
    "gn:asciiname":"Libertad Calera",
    "gn:country_code":"MX",
    "gn:dem":2123,
    "gn:feature_class":"P",
    "gn:feature_code":"PPL",
    "gn:name":"Libertad Calera",
    "gn:population":0,
    "gn:timezone":"America/Mexico_City",
    "iso:country":"MX",
    "name:spa_x_preferred":[
        "Libertad Calera"
    ],
    "wof:name":"Libertad Calera",
    "wof:placetype":"locality"
},
  "geometry": {"coordinates":[-92.34186,15.25418],"type":"Point"}
}