{
  "type": "Feature",
  "properties": {
    "gn:admin1_code":"28",
    "gn:admin2_code":"22.0",
    "gn:asciiname":"Mexico Agrario",
    "gn:country_code":"MX",
    "gn:dem":16,
    "gn:feature_class":"P",
    "gn:feature_code":"PPL",
    "gn:name":"M\u00e9xico Agrario",
    "gn:population":0,
    "gn:timezone":"America/Matamoros",
    "iso:country":"MX",
    "name:spa_x_preferred":[
        "M\u00e9xico Agrario"
    ],
    "wof:name":"Mexico Agrario",
    "wof:placetype":"locality"
},
  "geometry": {"coordinates":[-97.46813,25.85927],"type":"Point"}
}