{
  "type": "Feature",
  "properties": {
    "gn:admin1_code":"3.0",
    "gn:admin2_code":"1.0",
    "gn:asciiname":"Ramaditas",
    "gn:country_code":"MX",
    "gn:dem":31,
    "gn:feature_class":"P",
    "gn:feature_code":"PPL",
    "gn:name":"Ramaditas",
    "gn:population":176,
    "gn:timezone":"America/Mazatlan",
    "iso:country":"MX",
    "wof:name":"Ramaditas",
    "wof:placetype":"locality",
    "wof:population":176
},
  "geometry": {"coordinates":[-111.95556000000001,25.12139],"type":"Point"}
}