{
  "type": "Feature",
  "properties": {
    "gn:admin1_code":"12",
    "gn:admin2_code":"35.0",
    "gn:asciiname":"Los Guajes (La Canada)",
    "gn:country_code":"MX",
    "gn:dem":739,
    "gn:feature_class":"P",
    "gn:feature_code":"PPL",
    "gn:name":"Los Guajes (La Ca\u00f1ada)",
    "gn:population":6,
    "gn:timezone":"America/Mexico_City",
    "iso:country":"MX",
    "name:und_x_variant":[
        "Los Guajes (La Ca\u00f1ada)"
    ],
    "wof:name":"Los Guajes (La Canada)",
    "wof:placetype":"locality",
    "wof:population":6
},
  "geometry": {"coordinates":[-99.58277,18.34729],"type":"Point"}
}