{
  "type": "Feature",
  "properties": {
    "gn:admin1_code":"24",
    "gn:admin2_code":"37.0",
    "gn:asciiname":"Xinitli",
    "gn:country_code":"MX",
    "gn:dem":769,
    "gn:feature_class":"P",
    "gn:feature_code":"PPL",
    "gn:name":"Xinitli",
    "gn:population":0,
    "gn:timezone":"America/Mexico_City",
    "iso:country":"MX",
    "name:spa_x_preferred":[
        "Xinitli"
    ],
    "wof:name":"Xinitli",
    "wof:placetype":"locality"
},
  "geometry": {"coordinates":[-98.86127999999999,21.29407],"type":"Point"}
}