{
  "type": "Feature",
  "properties": {
    "gn:admin1_code":"10",
    "gn:admin2_code":"14.0",
    "gn:asciiname":"San Juan del Mezquital",
    "gn:country_code":"MX",
    "gn:dem":1889,
    "gn:feature_class":"P",
    "gn:feature_code":"PPL",
    "gn:name":"San Juan del Mezquital",
    "gn:population":0,
    "gn:timezone":"America/Monterrey",
    "iso:country":"MX",
    "name:spa_x_preferred":[
        "San Juan del Mezquital"
    ],
    "name:spa_x_variant":[
        "San Juan"
    ],
    "wof:name":"San Juan del Mezquital",
    "wof:placetype":"locality"
},
  "geometry": {"coordinates":[-104.4727,23.48051],"type":"Point"}
}