{
  "type": "Feature",
  "properties": {
    "gn:admin1_code":"16.0",
    "gn:admin2_code":"26.0",
    "gn:asciiname":"Puerto Chorohuira",
    "gn:country_code":"MX",
    "gn:dem":1170,
    "gn:feature_class":"P",
    "gn:feature_code":"PPL",
    "gn:name":"Puerto Chorohuira",
    "gn:population":0,
    "gn:timezone":"America/Mexico_City",
    "iso:country":"MX",
    "name:spa_x_preferred":[
        "Puerto Chorohuira"
    ],
    "wof:name":"Puerto Chorohuira",
    "wof:placetype":"locality"
},
  "geometry": {"coordinates":[-103.45474,18.7274],"type":"Point"}
}