{
  "type": "Feature",
  "properties": {
    "gn:admin1_code":"12",
    "gn:admin2_code":"7",
    "gn:asciiname":"Tlanilpa el Nuevo",
    "gn:country_code":"MX",
    "gn:dem":623,
    "gn:feature_class":"P",
    "gn:feature_code":"PPL",
    "gn:name":"Tlanilpa el Nuevo",
    "gn:population":18,
    "gn:timezone":"America/Mexico_City",
    "iso:country":"MX",
    "wof:name":"Tlanilpa el Nuevo",
    "wof:placetype":"locality",
    "wof:population":18
},
  "geometry": {"coordinates":[-100.15531,18.33983],"type":"Point"}
}