{
  "type": "Feature",
  "properties": {
    "gn:admin1_code":"32.0",
    "gn:admin2_code":"25.0",
    "gn:asciiname":"Vinedos el Milagro",
    "gn:country_code":"MX",
    "gn:dem":2021,
    "gn:feature_class":"P",
    "gn:feature_code":"PPL",
    "gn:name":"Vi\u00f1edos el Milagro",
    "gn:population":0,
    "gn:timezone":"America/Mexico_City",
    "iso:country":"MX",
    "name:spa_x_preferred":[
        "Vi\u00f1edos el Milagro"
    ],
    "wof:name":"Vinedos el Milagro",
    "wof:placetype":"locality"
},
  "geometry": {"coordinates":[-102.25694,22.50943],"type":"Point"}
}