{
  "type": "Feature",
  "properties": {
    "gn:admin1_code":"7",
    "gn:admin2_code":"28.0",
    "gn:asciiname":"Agua Prieta",
    "gn:country_code":"MX",
    "gn:dem":340,
    "gn:feature_class":"P",
    "gn:feature_code":"PPL",
    "gn:name":"Agua Prieta",
    "gn:population":6,
    "gn:timezone":"America/Monterrey",
    "iso:country":"MX",
    "name:cat_x_preferred":[
        "Agua Prieta"
    ],
    "name:ces_x_preferred":[
        "Agua Prieta"
    ],
    "name:deu_x_preferred":[
        "Agua Prieta"
    ],
    "name:fra_x_preferred":[
        "Agua Prieta"
    ],
    "name:ita_x_preferred":[
        "Agua Prieta"
    ],
    "name:nld_x_preferred":[
        "Agua Prieta"
    ],
    "name:pol_x_preferred":[
        "Agua Prieta"
    ],
    "name:ron_x_preferred":[
        "Agua Prieta"
    ],
    "name:rus_x_preferred":[
        "\u0410\u0433\u0443\u0430-\u041f\u0440\u0438\u0435\u0442\u0430"
    ],
    "name:spa_x_preferred":[
        "Agua Prieta"
    ],
    "name:srp_x_preferred":[
        "\u0410\u0433\u0432\u0430 \u041f\u0440\u0438\u0458\u0435\u0442\u0430"
    ],
    "wof:name":"Agua Prieta",
    "wof:placetype":"locality",
    "wof:population":6
},
  "geometry": {"coordinates":[-101.10592,27.82888],"type":"Point"}
}