{
  "type": "Feature",
  "properties": {
    "gn:admin1_code":"6",
    "gn:admin2_code":"9.0",
    "gn:asciiname":"Bahuinocachi",
    "gn:country_code":"MX",
    "gn:dem":2503,
    "gn:feature_class":"P",
    "gn:feature_code":"PPL",
    "gn:name":"Bahuinocachi",
    "gn:population":252,
    "gn:timezone":"America/Chihuahua",
    "iso:country":"MX",
    "wof:name":"Bahuinocachi",
    "wof:placetype":"locality",
    "wof:population":252
},
  "geometry": {"coordinates":[-107.3625,27.90944],"type":"Point"}
}