{
  "type": "Feature",
  "properties": {
    "gn:admin1_code":"26",
    "gn:admin2_code":"15.0",
    "gn:asciiname":"El Membrillo",
    "gn:country_code":"MX",
    "gn:dem":961,
    "gn:feature_class":"P",
    "gn:feature_code":"PPL",
    "gn:name":"El Membrillo",
    "gn:population":0,
    "gn:timezone":"America/Hermosillo",
    "iso:country":"MX",
    "name:spa_x_preferred":[
        "El Membrillo"
    ],
    "name:und_x_variant":[
        "Rancho El Membrillo"
    ],
    "wof:name":"El Membrillo",
    "wof:placetype":"locality"
},
  "geometry": {"coordinates":[-108.94334000000001,30.56893],"type":"Point"}
}