{
  "type": "Feature",
  "properties": {
    "gn:admin1_code":"5",
    "gn:admin2_code":"69.0",
    "gn:asciiname":"San Antonio Manacal",
    "gn:country_code":"MX",
    "gn:dem":423,
    "gn:feature_class":"P",
    "gn:feature_code":"PPL",
    "gn:name":"San Antonio Manacal",
    "gn:population":5,
    "gn:timezone":"America/Mexico_City",
    "iso:country":"MX",
    "wof:name":"San Antonio Manacal",
    "wof:placetype":"locality",
    "wof:population":5
},
  "geometry": {"coordinates":[-93.07805999999999,15.63556],"type":"Point"}
}