{
  "type": "Feature",
  "properties": {
    "gn:admin1_code":"23.0",
    "gn:asciiname":"San Jose de la Torre",
    "gn:country_code":"MX",
    "gn:dem":9,
    "gn:feature_class":"P",
    "gn:feature_code":"PPL",
    "gn:name":"San Jos\u00e9 de la Torre",
    "gn:population":0,
    "gn:timezone":"America/Cancun",
    "iso:country":"MX",
    "name:spa_x_preferred":[
        "San Jos\u00e9 de la Torre"
    ],
    "wof:name":"San Jose de la Torre",
    "wof:placetype":"locality"
},
  "geometry": {"coordinates":[-88.26474,18.63782],"type":"Point"}
}