{
  "type": "Feature",
  "properties": {
    "gn:admin1_code":"24",
    "gn:admin2_code":"13.0",
    "gn:asciiname":"Nuevo Tambolon",
    "gn:country_code":"MX",
    "gn:dem":54,
    "gn:feature_class":"P",
    "gn:feature_code":"PPL",
    "gn:name":"Nuevo Tambol\u00f3n",
    "gn:population":160,
    "gn:timezone":"America/Mexico_City",
    "iso:country":"MX",
    "name:und_x_variant":[
        "Nuevo Tambol\u00f3n"
    ],
    "wof:name":"Nuevo Tambolon",
    "wof:placetype":"locality",
    "wof:population":160
},
  "geometry": {"coordinates":[-98.96278,21.82056],"type":"Point"}
}