{
  "type": "Feature",
  "properties": {
    "gn:admin1_code":"30",
    "gn:admin2_code":"102.0",
    "gn:asciiname":"Finca la Imperial",
    "gn:country_code":"MX",
    "gn:dem":38,
    "gn:feature_class":"P",
    "gn:feature_code":"PPL",
    "gn:name":"Finca la Imperial",
    "gn:population":8,
    "gn:timezone":"America/Mexico_City",
    "iso:country":"MX",
    "wof:name":"Finca la Imperial",
    "wof:placetype":"locality",
    "wof:population":8
},
  "geometry": {"coordinates":[-97.04277999999999,20.25028],"type":"Point"}
}