{
  "type": "Feature",
  "properties": {
    "gn:admin1_code":"32",
    "gn:admin2_code":"1.0",
    "gn:asciiname":"Las Chivas",
    "gn:country_code":"MX",
    "gn:dem":1520,
    "gn:feature_class":"P",
    "gn:feature_code":"PPL",
    "gn:name":"Las Chivas",
    "gn:population":6,
    "gn:timezone":"America/Mexico_City",
    "iso:country":"MX",
    "wof:name":"Las Chivas",
    "wof:placetype":"locality",
    "wof:population":6
},
  "geometry": {"coordinates":[-103.0125,21.45389],"type":"Point"}
}