{
  "type": "Feature",
  "properties": {
    "gn:admin1_code":"30",
    "gn:admin2_code":"125",
    "gn:asciiname":"Las Higueras",
    "gn:country_code":"MX",
    "gn:dem":408,
    "gn:feature_class":"P",
    "gn:feature_code":"PPL",
    "gn:name":"Las Higueras",
    "gn:population":18,
    "gn:timezone":"America/Mexico_City",
    "iso:country":"MX",
    "wof:name":"Las Higueras",
    "wof:placetype":"locality",
    "wof:population":18
},
  "geometry": {"coordinates":[-96.67278,18.96111],"type":"Point"}
}