{
  "type": "Feature",
  "properties": {
    "gn:admin1_code":"20.0",
    "gn:asciiname":"Tecoanapan",
    "gn:country_code":"MX",
    "gn:dem":1958,
    "gn:feature_class":"P",
    "gn:feature_code":"PPL",
    "gn:name":"Tecoanapan",
    "gn:population":0,
    "gn:timezone":"America/Mexico_City",
    "iso:country":"MX",
    "name:spa_x_preferred":[
        "Tecoanapan"
    ],
    "wof:name":"Tecoanapan",
    "wof:placetype":"locality"
},
  "geometry": {"coordinates":[-96.96433,18.16406],"type":"Point"}
}