{
  "type": "Feature",
  "properties": {
    "gn:admin1_code":"21",
    "gn:admin2_code":"154.0",
    "gn:asciiname":"Colonia Cuauhtemoc",
    "gn:country_code":"MX",
    "gn:dem":1987,
    "gn:feature_class":"P",
    "gn:feature_code":"PPL",
    "gn:name":"Colonia Cuauht\u00e9moc",
    "gn:population":281,
    "gn:timezone":"America/Mexico_City",
    "iso:country":"MX",
    "name:und_x_variant":[
        "Colonia Cuauht\u00e9moc"
    ],
    "wof:name":"Colonia Cuauhtemoc",
    "wof:placetype":"locality",
    "wof:population":281
},
  "geometry": {"coordinates":[-97.74194,18.83194],"type":"Point"}
}