{
  "type": "Feature",
  "properties": {
    "gn:admin1_code":"16.0",
    "gn:admin2_code":"96.0",
    "gn:asciiname":"El Nuevo Agostadero",
    "gn:country_code":"MX",
    "gn:dem":552,
    "gn:feature_class":"P",
    "gn:feature_code":"PPL",
    "gn:name":"El Nuevo Agostadero",
    "gn:population":0,
    "gn:timezone":"America/Mexico_City",
    "iso:country":"MX",
    "name:spa_x_preferred":[
        "El Nuevo Agostadero"
    ],
    "wof:name":"El Nuevo Agostadero",
    "wof:placetype":"locality"
},
  "geometry": {"coordinates":[-102.36736000000001,18.63491],"type":"Point"}
}