{
  "type": "Feature",
  "properties": {
    "gn:admin1_code":"16.0",
    "gn:admin2_code":"10.0",
    "gn:asciiname":"Las Charanditas",
    "gn:country_code":"MX",
    "gn:dem":716,
    "gn:feature_class":"P",
    "gn:feature_code":"PPL",
    "gn:name":"Las Charanditas",
    "gn:population":0,
    "gn:timezone":"America/Mexico_City",
    "iso:country":"MX",
    "name:spa_x_preferred":[
        "Las Charanditas"
    ],
    "wof:name":"Las Charanditas",
    "wof:placetype":"locality"
},
  "geometry": {"coordinates":[-102.26593,18.38598],"type":"Point"}
}