{
  "type": "Feature",
  "properties": {
    "gn:admin1_code":"28",
    "gn:admin2_code":"41.0",
    "gn:asciiname":"Hacienda el Olmo",
    "gn:country_code":"MX",
    "gn:dem":310,
    "gn:feature_class":"P",
    "gn:feature_code":"PPL",
    "gn:name":"Hacienda el Olmo",
    "gn:population":6,
    "gn:timezone":"America/Monterrey",
    "iso:country":"MX",
    "wof:name":"Hacienda el Olmo",
    "wof:placetype":"locality",
    "wof:population":6
},
  "geometry": {"coordinates":[-99.09944,23.70389],"type":"Point"}
}