{
  "type": "Feature",
  "properties": {
    "gn:admin1_code":"10",
    "gn:admin2_code":"14.0",
    "gn:asciiname":"La Joyita",
    "gn:country_code":"MX",
    "gn:dem":1449,
    "gn:feature_class":"P",
    "gn:feature_code":"PPL",
    "gn:name":"La Joyita",
    "gn:population":4,
    "gn:timezone":"America/Monterrey",
    "iso:country":"MX",
    "wof:name":"La Joyita",
    "wof:placetype":"locality",
    "wof:population":4
},
  "geometry": {"coordinates":[-104.4469,22.7417],"type":"Point"}
}