{
  "type": "Feature",
  "properties": {
    "gn:admin1_code":"30",
    "gn:admin2_code":"15",
    "gn:asciiname":"Los Tablones",
    "gn:country_code":"MX",
    "gn:dem":80,
    "gn:feature_class":"P",
    "gn:feature_code":"PPL",
    "gn:name":"Los Tablones",
    "gn:population":17,
    "gn:timezone":"America/Mexico_City",
    "iso:country":"MX",
    "wof:name":"Los Tablones",
    "wof:placetype":"locality",
    "wof:population":17
},
  "geometry": {"coordinates":[-95.37694,18.56306],"type":"Point"}
}