{
  "type": "Feature",
  "properties": {
    "gn:admin1_code":"22",
    "gn:admin2_code":"18.0",
    "gn:asciiname":"Barrio de Garcia",
    "gn:country_code":"MX",
    "gn:dem":1652,
    "gn:feature_class":"P",
    "gn:feature_code":"PPL",
    "gn:name":"Barrio de Garc\u00eda",
    "gn:population":733,
    "gn:timezone":"America/Mexico_City",
    "iso:country":"MX",
    "name:und_x_variant":[
        "Barrio de Garc\u00eda"
    ],
    "wof:name":"Barrio de Garcia",
    "wof:placetype":"locality",
    "wof:population":733
},
  "geometry": {"coordinates":[-99.96861,20.86889],"type":"Point"}
}