{
  "type": "Feature",
  "properties": {
    "gn:admin1_code":"16.0",
    "gn:admin2_code":"79.0",
    "gn:asciiname":"Turiran",
    "gn:country_code":"MX",
    "gn:dem":2415,
    "gn:feature_class":"P",
    "gn:feature_code":"PPL",
    "gn:name":"Turir\u00e1n",
    "gn:population":0,
    "gn:timezone":"America/Mexico_City",
    "iso:country":"MX",
    "name:spa_x_preferred":[
        "Turir\u00e1n"
    ],
    "name:und_x_variant":[
        "Turi\u00e1n"
    ],
    "wof:name":"Turiran",
    "wof:placetype":"locality"
},
  "geometry": {"coordinates":[-101.59977000000001,19.35471],"type":"Point"}
}