{
  "type": "Feature",
  "properties": {
    "gn:admin1_code":"10",
    "gn:admin2_code":"14.0",
    "gn:asciiname":"Siete Hermanos (El Frio)",
    "gn:country_code":"MX",
    "gn:dem":1988,
    "gn:feature_class":"P",
    "gn:feature_code":"PPL",
    "gn:name":"Siete Hermanos (El Fr\u00edo)",
    "gn:population":4,
    "gn:timezone":"America/Monterrey",
    "iso:country":"MX",
    "name:und_x_variant":[
        "Siete Hermanos (El Fr\u00edo)"
    ],
    "wof:name":"Siete Hermanos (El Frio)",
    "wof:placetype":"locality",
    "wof:population":4
},
  "geometry": {"coordinates":[-104.46277000000001,23.63974],"type":"Point"}
}