{
  "type": "Feature",
  "properties": {
    "gn:admin1_code":"16.0",
    "gn:admin2_code":"19.0",
    "gn:asciiname":"Los Cicuares",
    "gn:country_code":"MX",
    "gn:dem":1652,
    "gn:feature_class":"P",
    "gn:feature_code":"PPL",
    "gn:name":"Los Cicuares",
    "gn:population":0,
    "gn:timezone":"America/Mexico_City",
    "iso:country":"MX",
    "name:spa_x_preferred":[
        "Los Cicuares"
    ],
    "wof:name":"Los Cicuares",
    "wof:placetype":"locality"
},
  "geometry": {"coordinates":[-102.78091000000001,19.72693],"type":"Point"}
}