{
  "type": "Feature",
  "properties": {
    "gn:admin1_code":"14.0",
    "gn:admin2_code":"38.0",
    "gn:asciiname":"El Llano Grande",
    "gn:country_code":"MX",
    "gn:dem":1437,
    "gn:feature_class":"P",
    "gn:feature_code":"PPL",
    "gn:name":"El Llano Grande",
    "gn:population":0,
    "gn:timezone":"America/Mexico_City",
    "iso:country":"MX",
    "wof:name":"El Llano Grande",
    "wof:placetype":"locality"
},
  "geometry": {"coordinates":[-104.51667,20.76667],"type":"Point"}
}