{
  "type": "Feature",
  "properties": {
    "gn:admin1_code":"30.0",
    "gn:admin2_code":"161.0",
    "gn:asciiname":"Rancho el Sergio",
    "gn:country_code":"MX",
    "gn:dem":78,
    "gn:feature_class":"P",
    "gn:feature_code":"PPL",
    "gn:name":"Rancho el Sergio",
    "gn:population":0,
    "gn:timezone":"America/Mexico_City",
    "iso:country":"MX",
    "name:spa_x_preferred":[
        "Rancho el Sergio"
    ],
    "wof:name":"Rancho el Sergio",
    "wof:placetype":"locality"
},
  "geometry": {"coordinates":[-98.30622,21.67661],"type":"Point"}
}