{
  "type": "Feature",
  "properties": {
    "gn:admin1_code":"23",
    "gn:admin2_code":"2.0",
    "gn:asciiname":"Kopchen",
    "gn:country_code":"MX",
    "gn:dem":30,
    "gn:feature_class":"P",
    "gn:feature_code":"PPL",
    "gn:name":"Kopchen",
    "gn:population":0,
    "gn:timezone":"America/Cancun",
    "iso:country":"MX",
    "name:und_x_variant":[
        "Kopchhen",
        "Kopchen"
    ],
    "wof:name":"Kopchen",
    "wof:placetype":"locality"
},
  "geometry": {"coordinates":[-88.15170999999999,19.33257],"type":"Point"}
}