{
  "type": "Feature",
  "properties": {
    "gn:admin1_code":"30",
    "gn:admin2_code":"121.0",
    "gn:asciiname":"Romerillos (Isla Juan A. Ramirez)",
    "gn:country_code":"MX",
    "gn:dem":14,
    "gn:feature_class":"P",
    "gn:feature_code":"PPL",
    "gn:name":"Romerillos (Isla Juan A. Ram\u00edrez)",
    "gn:population":55,
    "gn:timezone":"America/Mexico_City",
    "iso:country":"MX",
    "name:und_x_variant":[
        "Romerillos (Isla Juan A. Ram\u00edrez)"
    ],
    "wof:name":"Romerillos (Isla Juan A. Ramirez)",
    "wof:placetype":"locality",
    "wof:population":55
},
  "geometry": {"coordinates":[-97.67694,21.79583],"type":"Point"}
}