{
  "type": "Feature",
  "properties": {
    "gn:admin1_code":"15",
    "gn:admin2_code":"3.0",
    "gn:asciiname":"La Concepcion Ejido",
    "gn:country_code":"MX",
    "gn:dem":2404,
    "gn:feature_class":"P",
    "gn:feature_code":"PPL",
    "gn:name":"La Concepci\u00f3n Ejido",
    "gn:population":560,
    "gn:timezone":"America/Mexico_City",
    "iso:country":"MX",
    "name:und_x_variant":[
        "La Concepci\u00f3n Ejido"
    ],
    "wof:name":"La Concepcion Ejido",
    "wof:placetype":"locality",
    "wof:population":560
},
  "geometry": {"coordinates":[-99.87306,20.13306],"type":"Point"}
}