{
  "type": "Feature",
  "properties": {
    "gn:admin1_code":"3.0",
    "gn:admin2_code":"3.0",
    "gn:asciiname":"Las Vinoramitas",
    "gn:country_code":"MX",
    "gn:dem":196,
    "gn:feature_class":"P",
    "gn:feature_code":"PPL",
    "gn:name":"Las Vinoramitas",
    "gn:population":0,
    "gn:timezone":"America/Mazatlan",
    "iso:country":"MX",
    "name:spa_x_preferred":[
        "Las Vinoramitas"
    ],
    "wof:name":"Las Vinoramitas",
    "wof:placetype":"locality"
},
  "geometry": {"coordinates":[-110.03494000000001,23.25655],"type":"Point"}
}