{
  "type": "Feature",
  "properties": {
    "gn:admin1_code":"26",
    "gn:admin2_code":"3.0",
    "gn:asciiname":"Jamochiusa",
    "gn:country_code":"MX",
    "gn:dem":277,
    "gn:feature_class":"P",
    "gn:feature_code":"PPL",
    "gn:name":"Jamochiusa",
    "gn:population":0,
    "gn:timezone":"America/Hermosillo",
    "iso:country":"MX",
    "name:spa_x_preferred":[
        "Jamochiusa"
    ],
    "wof:name":"Jamochiusa",
    "wof:placetype":"locality"
},
  "geometry": {"coordinates":[-108.80468,26.80051],"type":"Point"}
}