{
  "type": "Feature",
  "properties": {
    "gn:admin1_code":"5",
    "gn:admin2_code":"89.0",
    "gn:asciiname":"Toquian Grande",
    "gn:country_code":"MX",
    "gn:dem":1945,
    "gn:feature_class":"P",
    "gn:feature_code":"PPL",
    "gn:name":"Toqui\u00e1n Grande",
    "gn:population":0,
    "gn:timezone":"America/Mexico_City",
    "iso:country":"MX",
    "name:spa_x_preferred":[
        "Toquian Grande"
    ],
    "name:und_x_variant":[
        "Toqui\u00e1n Grande"
    ],
    "wof:name":"Toquian Grande",
    "wof:placetype":"locality"
},
  "geometry": {"coordinates":[-92.20362,15.20175],"type":"Point"}
}