{
  "type": "Feature",
  "properties": {
    "gn:admin1_code":"28.0",
    "gn:admin2_code":"13.0",
    "gn:asciiname":"Talismanes",
    "gn:country_code":"MX",
    "gn:dem":168,
    "gn:feature_class":"P",
    "gn:feature_code":"PPL",
    "gn:name":"Talismanes",
    "gn:population":9,
    "gn:timezone":"America/Monterrey",
    "iso:country":"MX",
    "name:spa_x_preferred":[
        "Talismanes"
    ],
    "wof:name":"Talismanes",
    "wof:placetype":"locality",
    "wof:population":9
},
  "geometry": {"coordinates":[-98.81861000000001,23.71611],"type":"Point"}
}