{
  "type": "Feature",
  "properties": {
    "gn:admin1_code":"26.0",
    "gn:admin2_code":"36.0",
    "gn:asciiname":"El Cuadro",
    "gn:country_code":"MX",
    "gn:dem":726,
    "gn:feature_class":"P",
    "gn:feature_code":"PPL",
    "gn:name":"El Cuadro",
    "gn:population":0,
    "gn:timezone":"America/Hermosillo",
    "iso:country":"MX",
    "name:spa_x_preferred":[
        "El Cuadro"
    ],
    "wof:name":"El Cuadro",
    "wof:placetype":"locality"
},
  "geometry": {"coordinates":[-111.05108,30.60769],"type":"Point"}
}