{
  "type": "Feature",
  "properties": {
    "gn:admin1_code":"30",
    "gn:admin2_code":"137.0",
    "gn:asciiname":"Zoquiapan",
    "gn:country_code":"MX",
    "gn:dem":2339,
    "gn:feature_class":"P",
    "gn:feature_code":"PPL",
    "gn:name":"Zoquiapan",
    "gn:population":326,
    "gn:timezone":"America/Mexico_City",
    "iso:country":"MX",
    "wof:name":"Zoquiapan",
    "wof:placetype":"locality",
    "wof:population":326
},
  "geometry": {"coordinates":[-97.06444,18.64944],"type":"Point"}
}