{
  "type": "Feature",
  "properties": {
    "gn:admin1_code":"30",
    "gn:admin2_code":"137.0",
    "gn:asciiname":"Zoquiapan",
    "gn:country_code":"MX",
    "gn:dem":2339,
    "gn:feature_class":"P",
    "gn:feature_code":"PPL",
    "gn:name":"Zoquiapan",
    "gn:population":326,
    "gn:timezone":"America/Mexico_City",
    "iso:country":"MX",
    "name:ceb_x_preferred":[
        "Zoquiapan"
    ],
    "name:epo_x_preferred":[
        "Zoquiapan"
    ],
    "name:eus_x_preferred":[
        "Zoquiapan"
    ],
    "name:rus_x_preferred":[
        "\u0421\u043e\u043a\u044c\u044f\u043f\u0430\u043d"
    ],
    "name:spa_x_preferred":[
        "Zoquiapan"
    ],
    "name:srp_x_preferred":[
        "\u041e\u043f\u0448\u0442\u0438\u043d\u0430 \u0417\u043e\u043a\u0438\u0458\u0430\u043f\u0430\u043d"
    ],
    "name:swe_x_preferred":[
        "Zoquiapan"
    ],
    "name:vie_x_preferred":[
        "Zoquiapan"
    ],
    "wof:name":"Zoquiapan",
    "wof:placetype":"locality",
    "wof:population":326
},
  "geometry": {"coordinates":[-97.06444,18.64944],"type":"Point"}
}