{
  "type": "Feature",
  "properties": {
    "gn:admin1_code":"24.0",
    "gn:admin2_code":"40.0",
    "gn:asciiname":"El Naranjal",
    "gn:country_code":"MX",
    "gn:dem":36,
    "gn:feature_class":"P",
    "gn:feature_code":"PPL",
    "gn:name":"El Naranjal",
    "gn:population":0,
    "gn:timezone":"America/Mexico_City",
    "iso:country":"MX",
    "name:spa_x_preferred":[
        "El Naranjal"
    ],
    "wof:name":"El Naranjal",
    "wof:placetype":"locality"
},
  "geometry": {"coordinates":[-98.60151999999999,22.12361],"type":"Point"}
}