{
  "type": "Feature",
  "properties": {
    "gn:admin1_code":"15",
    "gn:admin2_code":"124.0",
    "gn:asciiname":"Colonia Emiliano Zapata",
    "gn:country_code":"MX",
    "gn:dem":2822,
    "gn:feature_class":"P",
    "gn:feature_code":"PPL",
    "gn:name":"Colonia Emiliano Zapata",
    "gn:population":178,
    "gn:timezone":"America/Mexico_City",
    "iso:country":"MX",
    "wof:name":"Colonia Emiliano Zapata",
    "wof:placetype":"locality",
    "wof:population":178
},
  "geometry": {"coordinates":[-100.10056,19.74944],"type":"Point"}
}