{
  "type": "Feature",
  "properties": {
    "gn:admin1_code":"6.0",
    "gn:admin2_code":"32.0",
    "gn:asciiname":"Cueva Blanca",
    "gn:country_code":"MX",
    "gn:dem":1653,
    "gn:feature_class":"P",
    "gn:feature_code":"PPL",
    "gn:name":"Cueva Blanca",
    "gn:population":0,
    "gn:timezone":"America/Chihuahua",
    "iso:country":"MX",
    "name:spa_x_preferred":[
        "Cueva Blanca"
    ],
    "name:und_x_variant":[
        "Rancho Cueva Blanca"
    ],
    "wof:name":"Cueva Blanca",
    "wof:placetype":"locality"
},
  "geometry": {"coordinates":[-105.72987999999999,27.24014],"type":"Point"}
}