{
  "type": "Feature",
  "properties": {
    "gn:admin1_code":"30.0",
    "gn:admin2_code":"155.0",
    "gn:asciiname":"Tazajera Santa Clara",
    "gn:country_code":"MX",
    "gn:dem":302,
    "gn:feature_class":"P",
    "gn:feature_code":"PPL",
    "gn:name":"Tazajera Santa Clara",
    "gn:population":13,
    "gn:timezone":"America/Mexico_City",
    "iso:country":"MX",
    "name:spa_x_preferred":[
        "Tazajera Santa Clara"
    ],
    "wof:name":"Tazajera Santa Clara",
    "wof:placetype":"locality",
    "wof:population":13
},
  "geometry": {"coordinates":[-98.10417,21.25083],"type":"Point"}
}