{
  "type": "Feature",
  "properties": {
    "gn:admin1_code":"24",
    "gn:admin2_code":"24",
    "gn:asciiname":"Palo Alto",
    "gn:country_code":"MX",
    "gn:dem":1065,
    "gn:feature_class":"P",
    "gn:feature_code":"PPL",
    "gn:name":"Palo Alto",
    "gn:population":45,
    "gn:timezone":"America/Mexico_City",
    "iso:country":"MX",
    "wof:name":"Palo Alto",
    "wof:placetype":"locality",
    "wof:population":45
},
  "geometry": {"coordinates":[-100.08417,21.86528],"type":"Point"}
}