{
  "type": "Feature",
  "properties": {
    "gn:admin1_code":"22",
    "gn:admin2_code":"7.0",
    "gn:asciiname":"Las Adelitas",
    "gn:country_code":"MX",
    "gn:dem":2019,
    "gn:feature_class":"P",
    "gn:feature_code":"PPL",
    "gn:name":"Las Adelitas",
    "gn:population":0,
    "gn:timezone":"America/Mexico_City",
    "iso:country":"MX",
    "name:spa_x_preferred":[
        "Las Adelitas"
    ],
    "name:spa_x_variant":[
        "San Jos\u00e9 de los Trejo"
    ],
    "name:und_x_variant":[
        "San Jos\u00e9 de las Trojes"
    ],
    "wof:name":"Las Adelitas",
    "wof:placetype":"locality"
},
  "geometry": {"coordinates":[-99.8442,20.5897],"type":"Point"}
}