{
  "type": "Feature",
  "properties": {
    "gn:admin1_code":"30",
    "gn:admin2_code":"21",
    "gn:asciiname":"La Cuchilla",
    "gn:country_code":"MX",
    "gn:dem":904,
    "gn:feature_class":"P",
    "gn:feature_code":"PPL",
    "gn:name":"La Cuchilla",
    "gn:population":13,
    "gn:timezone":"America/Mexico_City",
    "iso:country":"MX",
    "wof:name":"La Cuchilla",
    "wof:placetype":"locality",
    "wof:population":13
},
  "geometry": {"coordinates":[-96.82111,18.945],"type":"Point"}
}