{
  "type": "Feature",
  "properties": {
    "gn:admin1_code":"11",
    "gn:admin2_code":"17",
    "gn:asciiname":"La Casa de Polo",
    "gn:country_code":"MX",
    "gn:dem":1741,
    "gn:feature_class":"P",
    "gn:feature_code":"PPL",
    "gn:name":"La Casa de Polo",
    "gn:population":16,
    "gn:timezone":"America/Mexico_City",
    "iso:country":"MX",
    "wof:name":"La Casa de Polo",
    "wof:placetype":"locality",
    "wof:population":16
},
  "geometry": {"coordinates":[-101.39472000000001,20.75083],"type":"Point"}
}