{
  "type": "Feature",
  "properties": {
    "gn:admin1_code":"6",
    "gn:admin2_code":"8",
    "gn:asciiname":"La Gavilana",
    "gn:country_code":"MX",
    "gn:dem":2071,
    "gn:feature_class":"P",
    "gn:feature_code":"PPL",
    "gn:name":"La Gavilana",
    "gn:population":16,
    "gn:timezone":"America/Chihuahua",
    "iso:country":"MX",
    "wof:name":"La Gavilana",
    "wof:placetype":"locality",
    "wof:population":16
},
  "geometry": {"coordinates":[-107.6863,27.19493],"type":"Point"}
}