{
  "type": "Feature",
  "properties": {
    "gn:admin1_code":"24",
    "gn:admin2_code":"1.0",
    "gn:asciiname":"El Temazcal",
    "gn:country_code":"MX",
    "gn:dem":2005,
    "gn:feature_class":"P",
    "gn:feature_code":"PPL",
    "gn:name":"El Temazcal",
    "gn:population":186,
    "gn:timezone":"America/Mexico_City",
    "iso:country":"MX",
    "wof:name":"El Temazcal",
    "wof:placetype":"locality",
    "wof:population":186
},
  "geometry": {"coordinates":[-101.20860999999999,22.46639],"type":"Point"}
}