{
  "type": "Feature",
  "properties": {
    "gn:admin1_code":"5",
    "gn:admin2_code":"69.0",
    "gn:asciiname":"Nueva Coapa (Estacion Echegaray)",
    "gn:country_code":"MX",
    "gn:dem":22,
    "gn:feature_class":"P",
    "gn:feature_code":"PPL",
    "gn:name":"Nueva Coapa (Estaci\u00f3n Echegaray)",
    "gn:population":636,
    "gn:timezone":"America/Mexico_City",
    "iso:country":"MX",
    "wof:name":"Nueva Coapa (Estacion Echegaray)",
    "wof:placetype":"locality",
    "wof:population":636
},
  "geometry": {"coordinates":[-93.16611,15.625],"type":"Point"}
}