{
  "type": "Feature",
  "properties": {
    "gn:admin1_code":"26",
    "gn:admin2_code":"39.0",
    "gn:asciiname":"Ojo de Piedra",
    "gn:country_code":"MX",
    "gn:dem":1523,
    "gn:feature_class":"P",
    "gn:feature_code":"PPL",
    "gn:name":"Ojo de Piedra",
    "gn:population":0,
    "gn:timezone":"America/Hermosillo",
    "iso:country":"MX",
    "name:spa_x_preferred":[
        "Ojo de Piedra"
    ],
    "name:und_x_variant":[
        "Rancho El Ojo de Piedra"
    ],
    "wof:name":"Ojo de Piedra",
    "wof:placetype":"locality"
},
  "geometry": {"coordinates":[-109.96807,31.15885],"type":"Point"}
}