{
  "type": "Feature",
  "properties": {
    "gn:admin1_code":"12",
    "gn:admin2_code":"54.0",
    "gn:asciiname":"La Canada",
    "gn:country_code":"MX",
    "gn:dem":1359,
    "gn:feature_class":"P",
    "gn:feature_code":"PPL",
    "gn:name":"La Ca\u00f1ada",
    "gn:population":59,
    "gn:timezone":"America/Mexico_City",
    "iso:country":"MX",
    "name:und_x_variant":[
        "La Ca\u00f1ada"
    ],
    "wof:name":"La Canada",
    "wof:placetype":"locality",
    "wof:population":59
},
  "geometry": {"coordinates":[-100.25928,17.89642000000001],"type":"Point"}
}