{
  "type": "Feature",
  "properties": {
    "gn:admin1_code":"5",
    "gn:admin2_code":"51.0",
    "gn:asciiname":"8 de Septiembre",
    "gn:country_code":"MX",
    "gn:dem":100,
    "gn:feature_class":"P",
    "gn:feature_code":"PPL",
    "gn:name":"8 de Septiembre",
    "gn:population":89,
    "gn:timezone":"America/Mexico_City",
    "iso:country":"MX",
    "wof:name":"8 de Septiembre",
    "wof:placetype":"locality",
    "wof:population":89
},
  "geometry": {"coordinates":[-92.89514,15.4674],"type":"Point"}
}