{
  "type": "Feature",
  "properties": {
    "gn:admin1_code":"14",
    "gn:admin2_code":"91.0",
    "gn:asciiname":"Teocaltitan",
    "gn:country_code":"MX",
    "gn:dem":1669,
    "gn:feature_class":"P",
    "gn:feature_code":"PPL",
    "gn:name":"Teocaltit\u00e1n",
    "gn:population":0,
    "gn:timezone":"America/Mexico_City",
    "iso:country":"MX",
    "wof:name":"Teocaltitan",
    "wof:placetype":"locality"
},
  "geometry": {"coordinates":[-102.63216,21.28972000000001],"type":"Point"}
}