{
  "type": "Feature",
  "properties": {
    "gn:admin1_code":"14",
    "gn:admin2_code":"49.0",
    "gn:asciiname":"El Pajal",
    "gn:country_code":"MX",
    "gn:dem":1445,
    "gn:feature_class":"P",
    "gn:feature_code":"PPL",
    "gn:name":"El Pajal",
    "gn:population":58,
    "gn:timezone":"America/Mexico_City",
    "iso:country":"MX",
    "wof:name":"El Pajal",
    "wof:placetype":"locality",
    "wof:population":58
},
  "geometry": {"coordinates":[-103.11444,19.34889],"type":"Point"}
}