{
  "type": "Feature",
  "properties": {
    "gn:admin1_code":"20",
    "gn:admin2_code":"234.0",
    "gn:asciiname":"Agua de Nino",
    "gn:country_code":"MX",
    "gn:dem":1642,
    "gn:feature_class":"P",
    "gn:feature_code":"PPL",
    "gn:name":"Agua de Ni\u00f1o",
    "gn:population":0,
    "gn:timezone":"America/Mexico_City",
    "iso:country":"MX",
    "name:spa_x_preferred":[
        "Agua de Ni\u00f1o"
    ],
    "wof:name":"Agua de Nino",
    "wof:placetype":"locality"
},
  "geometry": {"coordinates":[-96.88023,18.10578],"type":"Point"}
}