{
  "type": "Feature",
  "properties": {
    "gn:admin1_code":"29",
    "gn:admin2_code":"43.0",
    "gn:asciiname":"San Jose Tepoxtla",
    "gn:country_code":"MX",
    "gn:dem":2411,
    "gn:feature_class":"P",
    "gn:feature_code":"PPL",
    "gn:name":"San Jos\u00e9 Tepoxtla",
    "gn:population":638,
    "gn:timezone":"America/Mexico_City",
    "iso:country":"MX",
    "name:und_x_variant":[
        "San Jos\u00e9 Tepoxtla"
    ],
    "wof:name":"San Jose Tepoxtla",
    "wof:placetype":"locality",
    "wof:population":638
},
  "geometry": {"coordinates":[-98.15694000000001,19.38167],"type":"Point"}
}