{
  "type": "Feature",
  "properties": {
    "gn:admin1_code":"11",
    "gn:admin2_code":"32.0",
    "gn:asciiname":"Fatima",
    "gn:country_code":"MX",
    "gn:dem":2129,
    "gn:feature_class":"P",
    "gn:feature_code":"PPL",
    "gn:name":"F\u00e1tima",
    "gn:population":223,
    "gn:timezone":"America/Mexico_City",
    "iso:country":"MX",
    "name:und_x_variant":[
        "F\u00e1tima"
    ],
    "wof:name":"Fatima",
    "wof:placetype":"locality",
    "wof:population":223
},
  "geometry": {"coordinates":[-100.29861,21.07639],"type":"Point"}
}