{
  "type": "Feature",
  "properties": {
    "gn:admin1_code":"28.0",
    "gn:admin2_code":"29.0",
    "gn:asciiname":"El Jagueey",
    "gn:country_code":"MX",
    "gn:dem":141,
    "gn:feature_class":"P",
    "gn:feature_code":"PPL",
    "gn:name":"El Jag\u00fcey",
    "gn:population":0,
    "gn:timezone":"America/Monterrey",
    "iso:country":"MX",
    "name:spa_x_preferred":[
        "El Jag\u00fcey"
    ],
    "wof:name":"El Jagueey",
    "wof:placetype":"locality"
},
  "geometry": {"coordinates":[-99.14667,22.76611],"type":"Point"}
}