{
  "type": "Feature",
  "properties": {
    "gn:admin1_code":"27",
    "gn:admin2_code":"4.0",
    "gn:asciiname":"Dieciseis de Septiembre",
    "gn:country_code":"MX",
    "gn:dem":9,
    "gn:feature_class":"P",
    "gn:feature_code":"PPL",
    "gn:name":"Diecis\u00e9is de Septiembre",
    "gn:population":335,
    "gn:timezone":"America/Mexico_City",
    "iso:country":"MX",
    "name:und_x_variant":[
        "Diecis\u00e9is de Septiembre"
    ],
    "wof:name":"Dieciseis de Septiembre",
    "wof:placetype":"locality",
    "wof:population":335
},
  "geometry": {"coordinates":[-93.03888999999999,18.01027999999999],"type":"Point"}
}