{
  "type": "Feature",
  "properties": {
    "gn:admin1_code":"25",
    "gn:admin2_code":"18.0",
    "gn:asciiname":"El Portugues (El Campito)",
    "gn:country_code":"MX",
    "gn:dem":7,
    "gn:feature_class":"P",
    "gn:feature_code":"PPL",
    "gn:name":"El Portugu\u00e9s (El Campito)",
    "gn:population":305,
    "gn:timezone":"America/Mazatlan",
    "iso:country":"MX",
    "wof:name":"El Portugues (El Campito)",
    "wof:placetype":"locality",
    "wof:population":305
},
  "geometry": {"coordinates":[-107.82793999999998,24.75146],"type":"Point"}
}