{
  "type": "Feature",
  "properties": {
    "gn:admin1_code":"4",
    "gn:admin2_code":"3.0",
    "gn:asciiname":"La Lagartera",
    "gn:country_code":"MX",
    "gn:dem":6,
    "gn:feature_class":"P",
    "gn:feature_code":"PPL",
    "gn:name":"La Lagartera",
    "gn:population":0,
    "gn:timezone":"America/Merida",
    "iso:country":"MX",
    "name:spa_x_preferred":[
        "La Lagartera"
    ],
    "wof:name":"La Lagartera",
    "wof:placetype":"locality"
},
  "geometry": {"coordinates":[-91.65694999999999,18.71912],"type":"Point"}
}