{
  "type": "Feature",
  "properties": {
    "gn:admin1_code":"31",
    "gn:admin2_code":"67.0",
    "gn:asciiname":"Talao",
    "gn:country_code":"MX",
    "gn:dem":12,
    "gn:feature_class":"P",
    "gn:feature_code":"PPL",
    "gn:name":"Talao",
    "gn:population":0,
    "gn:timezone":"America/Merida",
    "iso:country":"MX",
    "name:spa_x_preferred":[
        "Talao"
    ],
    "wof:name":"Talao",
    "wof:placetype":"locality"
},
  "geometry": {"coordinates":[-89.39924999999999,20.82589],"type":"Point"}
}