{
  "type": "Feature",
  "properties": {
    "gn:admin1_code":"13",
    "gn:admin2_code":"50.0",
    "gn:asciiname":"Colonia el Moreno",
    "gn:country_code":"MX",
    "gn:dem":2026,
    "gn:feature_class":"P",
    "gn:feature_code":"PPL",
    "gn:name":"Colonia el Moreno",
    "gn:population":0,
    "gn:timezone":"America/Mexico_City",
    "iso:country":"MX",
    "name:spa_x_preferred":[
        "Colonia el Moreno"
    ],
    "wof:name":"Colonia el Moreno",
    "wof:placetype":"locality"
},
  "geometry": {"coordinates":[-99.17471999999999,20.30204],"type":"Point"}
}