{
  "type": "Feature",
  "properties": {
    "gn:admin1_code":"25",
    "gn:admin2_code":"6",
    "gn:asciiname":"La Bascula (Crucero de Costa Rica)",
    "gn:country_code":"MX",
    "gn:dem":80,
    "gn:feature_class":"P",
    "gn:feature_code":"PPL",
    "gn:name":"La B\u00e1scula (Crucero de Costa Rica)",
    "gn:population":30,
    "gn:timezone":"America/Mazatlan",
    "iso:country":"MX",
    "name:und_x_variant":[
        "La B\u00e1scula (Crucero de Costa Rica)"
    ],
    "wof:name":"La Bascula (Crucero de Costa Rica)",
    "wof:placetype":"locality",
    "wof:population":30
},
  "geometry": {"coordinates":[-107.27153,24.63628],"type":"Point"}
}