{
  "type": "Feature",
  "properties": {
    "gn:admin1_code":"12",
    "gn:admin2_code":"1.0",
    "gn:asciiname":"La Carbonera",
    "gn:country_code":"MX",
    "gn:dem":1038,
    "gn:feature_class":"P",
    "gn:feature_code":"PPL",
    "gn:name":"La Carbonera",
    "gn:population":56,
    "gn:timezone":"America/Mexico_City",
    "iso:country":"MX",
    "wof:name":"La Carbonera",
    "wof:placetype":"locality",
    "wof:population":56
},
  "geometry": {"coordinates":[-99.84177,17.15281],"type":"Point"}
}