{
  "type": "Feature",
  "properties": {
    "gn:admin1_code":"15.0",
    "gn:asciiname":"Puente del Jaral",
    "gn:country_code":"MX",
    "gn:dem":1605,
    "gn:feature_class":"P",
    "gn:feature_code":"PPL",
    "gn:name":"Puente del Jaral",
    "gn:population":0,
    "gn:timezone":"America/Mexico_City",
    "iso:country":"MX",
    "name:spa_x_preferred":[
        "Puente del Jaral"
    ],
    "wof:name":"Puente del Jaral",
    "wof:placetype":"locality"
},
  "geometry": {"coordinates":[-102.62726000000001,19.8199],"type":"Point"}
}