{
  "type": "Feature",
  "properties": {
    "iso:country":"MX",
    "name:dut_x_preferred":[
        "Guam\u00fachil"
    ],
    "name:eng_x_preferred":[
        "Guam\u00fachil"
    ],
    "name:fre_x_preferred":[
        "Guam\u00fachil"
    ],
    "name:ger_x_preferred":[
        "Guam\u00fachil"
    ],
    "name:hun_x_preferred":[
        "Guam\u00fachil"
    ],
    "name:ita_x_preferred":[
        "Guam\u00fachil"
    ],
    "name:jpn_x_preferred":[
        "\u30b0\u30a2\u30e0\u30c1\u30eb"
    ],
    "name:pol_x_preferred":[
        "Guam\u00fachil"
    ],
    "name:rus_x_preferred":[
        "\u0413\u0443\u0430\u043c\u0443\u0447\u0438\u043b\u044c"
    ],
    "name:spa_x_preferred":[
        "Guam\u00fachil"
    ],
    "name:vie_x_preferred":[
        "Guam\u00fachil"
    ],
    "ne:ADM0CAP":0.0,
    "ne:ADM0NAME":"Mexico",
    "ne:ADM0_A3":"MEX",
    "ne:ADM1NAME":"Sinaloa",
    "ne:ADMIN1_COD":25,
    "ne:CAPALT":0,
    "ne:CHANGED":0,
    "ne:CHECKME":0,
    "ne:COMPARE":0,
    "ne:DIFFASCII":0,
    "ne:ELEVATION":0.0,
    "ne:FEATURECLA":"Populated place",
    "ne:FEATURE_CL":"P",
    "ne:FEATURE_CO":"PPL",
    "ne:GEONAMEID":4005297,
    "ne:GEONAMESNO":"Geonames ascii name + lat.d + long.d matching.",
    "ne:GN_ASCII":"Guamuchil",
    "ne:GN_POP":59276,
    "ne:GTOPO30":47.0,
    "ne:ISO_A2":"MX",
    "ne:LABELRANK":2,
    "ne:LATITUDE":25.470369,
    "ne:LONGITUDE":-108.090002,
    "ne:LS_MATCH":1,
    "ne:LS_NAME":"Guamuchil",
    "ne:MAX_AREAKM":22.0,
    "ne:MAX_AREAMI":8.0,
    "ne:MAX_BBXMAX":-108.05,
    "ne:MAX_BBXMIN":-108.108333,
    "ne:MAX_BBYMAX":25.483333,
    "ne:MAX_BBYMIN":25.433333,
    "ne:MAX_NATSCA":20.0,
    "ne:MAX_PERKM":23.0,
    "ne:MAX_PERMI":14.0,
    "ne:MAX_POP10":62695,
    "ne:MAX_POP20":62695,
    "ne:MAX_POP300":0,
    "ne:MAX_POP310":0,
    "ne:MAX_POP50":0,
    "ne:MEAN_BBXC":-108.079167,
    "ne:MEAN_BBYC":25.459821,
    "ne:MEGACITY":0,
    "ne:MIN_AREAKM":22.0,
    "ne:MIN_AREAMI":8.0,
    "ne:MIN_BBXMAX":-108.05,
    "ne:MIN_BBXMIN":-108.108333,
    "ne:MIN_BBYMAX":25.483333,
    "ne:MIN_BBYMIN":25.433333,
    "ne:MIN_PERKM":23.0,
    "ne:MIN_PERMI":14.0,
    "ne:NAME":"Guamuchil",
    "ne:NAMEASCII":"Guamuchil",
    "ne:NAMEDIFF":0,
    "ne:NATSCALE":20,
    "ne:POP1950":0,
    "ne:POP1955":0,
    "ne:POP1960":0,
    "ne:POP1965":0,
    "ne:POP1970":0,
    "ne:POP1975":0,
    "ne:POP1980":0,
    "ne:POP1985":0,
    "ne:POP1990":0,
    "ne:POP1995":0,
    "ne:POP2000":0,
    "ne:POP2005":0,
    "ne:POP2010":0,
    "ne:POP2015":0,
    "ne:POP2020":0,
    "ne:POP2025":0,
    "ne:POP2050":0,
    "ne:POP_MAX":62695,
    "ne:POP_MIN":59276,
    "ne:POP_OTHER":62695,
    "ne:RANK_MAX":8,
    "ne:RANK_MIN":8,
    "ne:SCALERANK":7,
    "ne:SOV0NAME":"Mexico",
    "ne:SOV_A3":"MEX",
    "ne:TIMEZONE":"America/Mazatlan",
    "ne:UN_FID":0,
    "ne:UN_LAT":0.0,
    "ne:UN_LONG":0.0,
    "ne:WORLDCITY":0,
    "ne:min_zoom":6.7,
    "wof:name":"Guamuchil",
    "wof:placetype":"locality"
},
  "geometry": {"coordinates":[-108.0900020770423,25.47036907856887],"type":"Point"}
}