{
  "type": "Feature",
  "properties": {
    "gn:admin1_code":"30",
    "gn:admin2_code":"3",
    "gn:asciiname":"Solosuchil",
    "gn:country_code":"MX",
    "gn:dem":69,
    "gn:feature_class":"P",
    "gn:feature_code":"PPL",
    "gn:name":"Solos\u00fachil",
    "gn:population":17,
    "gn:timezone":"America/Mexico_City",
    "iso:country":"MX",
    "name:und_x_variant":[
        "Solos\u00fachil"
    ],
    "wof:name":"Solosuchil",
    "wof:placetype":"locality",
    "wof:population":17
},
  "geometry": {"coordinates":[-94.93111,17.96917000000001],"type":"Point"}
}