{
  "type": "Feature",
  "properties": {
    "gn:admin1_code":"27",
    "gn:admin2_code":"8.0",
    "gn:asciiname":"Paso de la Mina 1ra. Seccion",
    "gn:country_code":"MX",
    "gn:dem":15,
    "gn:feature_class":"P",
    "gn:feature_code":"PPL",
    "gn:name":"Paso de la Mina 1ra. Secci\u00f3n",
    "gn:population":930,
    "gn:timezone":"America/Mexico_City",
    "iso:country":"MX",
    "name:spa_x_preferred":[
        "Paso de la Mina Primera Secci\u00f3n"
    ],
    "wof:name":"Paso de la Mina 1ra. Seccion",
    "wof:placetype":"locality",
    "wof:population":930
},
  "geometry": {"coordinates":[-93.73611,17.91972],"type":"Point"}
}