{
  "type": "Feature",
  "properties": {
    "gn:admin1_code":"16.0",
    "gn:asciiname":"Santa Martha",
    "gn:country_code":"MX",
    "gn:dem":1530,
    "gn:feature_class":"P",
    "gn:feature_code":"PPL",
    "gn:name":"Santa Martha",
    "gn:population":0,
    "gn:timezone":"America/Mexico_City",
    "iso:country":"MX",
    "name:spa_x_preferred":[
        "Santa Martha"
    ],
    "name:spa_x_variant":[
        "El Meyado"
    ],
    "wof:name":"Santa Martha",
    "wof:placetype":"locality"
},
  "geometry": {"coordinates":[-102.44893,20.18256],"type":"Point"}
}