{
  "type": "Feature",
  "properties": {
    "gn:admin1_code":"25",
    "gn:admin2_code":"7.0",
    "gn:asciiname":"Rincon de Agua Caliente Grande",
    "gn:country_code":"MX",
    "gn:dem":230,
    "gn:feature_class":"P",
    "gn:feature_code":"PPL",
    "gn:name":"Rinc\u00f3n de Agua Caliente Grande",
    "gn:population":257,
    "gn:timezone":"America/Mazatlan",
    "iso:country":"MX",
    "name:und_x_variant":[
        "Rinc\u00f3n de Agua Caliente Grande"
    ],
    "wof:name":"Rincon de Agua Caliente Grande",
    "wof:placetype":"locality",
    "wof:population":257
},
  "geometry": {"coordinates":[-108.37917,26.51917000000001],"type":"Point"}
}