{
  "type": "Feature",
  "properties": {
    "gn:admin1_code":"26",
    "gn:admin2_code":"30.0",
    "gn:asciiname":"Sahuaripa Numero Tres",
    "gn:country_code":"MX",
    "gn:dem":59,
    "gn:feature_class":"P",
    "gn:feature_code":"PPL",
    "gn:name":"Sahuaripa N\u00famero Tres",
    "gn:population":0,
    "gn:timezone":"America/Hermosillo",
    "iso:country":"MX",
    "name:und_x_variant":[
        "Sahuaripa Campo N\u00famero 3",
        "Sahuaripa N\u00famero Tres",
        "Sahuaripa N\u00famero 3"
    ],
    "wof:name":"Sahuaripa Numero Tres",
    "wof:placetype":"locality"
},
  "geometry": {"coordinates":[-111.70716000000002,29.12369],"type":"Point"}
}