{
  "type": "Feature",
  "properties": {
    "gn:admin1_code":"30",
    "gn:admin2_code":"150",
    "gn:asciiname":"El Rey (San Ramon)",
    "gn:country_code":"MX",
    "gn:dem":7,
    "gn:feature_class":"P",
    "gn:feature_code":"PPL",
    "gn:name":"El Rey (San Ram\u00f3n)",
    "gn:population":12,
    "gn:timezone":"America/Mexico_City",
    "iso:country":"MX",
    "name:und_x_variant":[
        "El Rey (San Ram\u00f3n)"
    ],
    "wof:name":"El Rey (San Ramon)",
    "wof:placetype":"locality",
    "wof:population":12
},
  "geometry": {"coordinates":[-97.65361,21.60139],"type":"Point"}
}