{
  "type": "Feature",
  "properties": {
    "gn:admin1_code":"14",
    "gn:admin2_code":"64.0",
    "gn:asciiname":"Hierba de Matancillas",
    "gn:country_code":"MX",
    "gn:dem":2180,
    "gn:feature_class":"P",
    "gn:feature_code":"PPL",
    "gn:name":"Hierba de Matancillas",
    "gn:population":799,
    "gn:timezone":"America/Mexico_City",
    "iso:country":"MX",
    "wof:name":"Hierba de Matancillas",
    "wof:placetype":"locality",
    "wof:population":799
},
  "geometry": {"coordinates":[-101.67333000000001,21.86528],"type":"Point"}
}