{
  "type": "Feature",
  "properties": {
    "gn:admin1_code":"13",
    "gn:admin2_code":"26.0",
    "gn:asciiname":"Huilotitla II",
    "gn:country_code":"MX",
    "gn:dem":312,
    "gn:feature_class":"P",
    "gn:feature_code":"PPL",
    "gn:name":"Huilotitla II",
    "gn:population":103,
    "gn:timezone":"America/Mexico_City",
    "iso:country":"MX",
    "wof:name":"Huilotitla II",
    "wof:placetype":"locality",
    "wof:population":103
},
  "geometry": {"coordinates":[-98.49832000000001,21.05575],"type":"Point"}
}