{
  "type": "Feature",
  "properties": {
    "gn:admin1_code":"26",
    "gn:admin2_code":"47.0",
    "gn:asciiname":"El Saguarito",
    "gn:country_code":"MX",
    "gn:dem":12,
    "gn:feature_class":"P",
    "gn:feature_code":"PPL",
    "gn:name":"El Saguarito",
    "gn:population":0,
    "gn:timezone":"America/Hermosillo",
    "iso:country":"MX",
    "name:spa_x_preferred":[
        "El Saguarito"
    ],
    "wof:name":"El Saguarito",
    "wof:placetype":"locality"
},
  "geometry": {"coordinates":[-112.64036000000002,29.81962],"type":"Point"}
}