{
  "type": "Feature",
  "properties": {
    "gn:admin1_code":"16.0",
    "gn:admin2_code":"63.0",
    "gn:asciiname":"Los Alvarados",
    "gn:country_code":"MX",
    "gn:dem":1773,
    "gn:feature_class":"P",
    "gn:feature_code":"PPL",
    "gn:name":"Los Alvarados",
    "gn:population":271,
    "gn:timezone":"America/Mexico_City",
    "iso:country":"MX",
    "name:spa_x_preferred":[
        "Los Alvarados"
    ],
    "name:und_x_variant":[
        "Los Alvarado"
    ],
    "wof:name":"Los Alvarados",
    "wof:placetype":"locality",
    "wof:population":271
},
  "geometry": {"coordinates":[-101.74986,20.03503],"type":"Point"}
}