{
  "type": "Feature",
  "properties": {
    "gn:admin1_code":"4",
    "gn:admin2_code":"4.0",
    "gn:asciiname":"Jose Maria Morelos y Pavon",
    "gn:country_code":"MX",
    "gn:dem":39,
    "gn:feature_class":"P",
    "gn:feature_code":"PPL",
    "gn:name":"Jos\u00e9 Mar\u00eda Morelos y Pav\u00f3n",
    "gn:population":678,
    "gn:timezone":"America/Merida",
    "iso:country":"MX",
    "wof:name":"Jose Maria Morelos y Pavon",
    "wof:placetype":"locality",
    "wof:population":678
},
  "geometry": {"coordinates":[-90.72221999999999,19.0925],"type":"Point"}
}