{
  "type": "Feature",
  "properties": {
    "gn:admin1_code":"15",
    "gn:admin2_code":"80.0",
    "gn:asciiname":"Puentecillas",
    "gn:country_code":"MX",
    "gn:dem":2321,
    "gn:feature_class":"P",
    "gn:feature_code":"PPL",
    "gn:name":"Puentecillas",
    "gn:population":0,
    "gn:timezone":"America/Mexico_City",
    "iso:country":"MX",
    "name:und_x_variant":[
        "Puntecillas",
        "Puentecillas"
    ],
    "wof:name":"Puentecillas",
    "wof:placetype":"locality"
},
  "geometry": {"coordinates":[-100.0502,18.74878],"type":"Point"}
}