{
  "type": "Feature",
  "properties": {
    "gn:admin1_code":"32.0",
    "gn:admin2_code":"1.0",
    "gn:asciiname":"La Jarilla",
    "gn:country_code":"MX",
    "gn:dem":2082,
    "gn:feature_class":"P",
    "gn:feature_code":"PPL",
    "gn:name":"La Jarilla",
    "gn:population":0,
    "gn:timezone":"America/Mexico_City",
    "iso:country":"MX",
    "name:spa_x_preferred":[
        "La Jarilla"
    ],
    "wof:name":"La Jarilla",
    "wof:placetype":"locality"
},
  "geometry": {"coordinates":[-102.96589,21.42165],"type":"Point"}
}