{
  "type": "Feature",
  "properties": {
    "gn:admin1_code":"5",
    "gn:admin2_code":"87.0",
    "gn:asciiname":"Tierra y Libertad",
    "gn:country_code":"MX",
    "gn:dem":16,
    "gn:feature_class":"P",
    "gn:feature_code":"PPL",
    "gn:name":"Tierra y Libertad",
    "gn:population":134,
    "gn:timezone":"America/Mexico_City",
    "iso:country":"MX",
    "wof:name":"Tierra y Libertad",
    "wof:placetype":"locality",
    "wof:population":134
},
  "geometry": {"coordinates":[-92.25306,14.67056],"type":"Point"}
}