{
  "type": "Feature",
  "properties": {
    "gn:admin1_code":"13",
    "gn:admin2_code":"35.0",
    "gn:asciiname":"Las Trojas",
    "gn:country_code":"MX",
    "gn:dem":2175,
    "gn:feature_class":"P",
    "gn:feature_code":"PPL",
    "gn:name":"Las Trojas",
    "gn:population":74,
    "gn:timezone":"America/Mexico_City",
    "iso:country":"MX",
    "wof:name":"Las Trojas",
    "wof:placetype":"locality",
    "wof:population":74
},
  "geometry": {"coordinates":[-98.35935000000001,20.28566],"type":"Point"}
}