{
  "type": "Feature",
  "properties": {
    "gn:admin1_code":"32",
    "gn:admin2_code":"38",
    "gn:asciiname":"La Panadera",
    "gn:country_code":"MX",
    "gn:dem":2302,
    "gn:feature_class":"P",
    "gn:feature_code":"PPL",
    "gn:name":"La Panadera",
    "gn:population":26,
    "gn:timezone":"America/Mexico_City",
    "iso:country":"MX",
    "wof:name":"La Panadera",
    "wof:placetype":"locality",
    "wof:population":26
},
  "geometry": {"coordinates":[-101.45583000000001,22.3725],"type":"Point"}
}