{
  "type": "Feature",
  "properties": {
    "gn:admin1_code":"31",
    "gn:admin2_code":"19.0",
    "gn:asciiname":"Chauao",
    "gn:cc2":"MX",
    "gn:country_code":"MX",
    "gn:dem":22,
    "gn:feature_class":"P",
    "gn:feature_code":"PPL",
    "gn:name":"Chauao",
    "gn:population":0,
    "gn:timezone":"America/Merida",
    "iso:country":"MX",
    "name:und_x_variant":[
        "Chauaco",
        "Chauao"
    ],
    "wof:name":"Chauao",
    "wof:placetype":"locality"
},
  "geometry": {"coordinates":[-87.75,20.76667],"type":"Point"}
}