{
  "type": "Feature",
  "properties": {
    "gn:admin1_code":"20",
    "gn:admin2_code":"278.0",
    "gn:asciiname":"Colonia Cosoltepec",
    "gn:country_code":"MX",
    "gn:dem":50,
    "gn:feature_class":"P",
    "gn:feature_code":"PPL",
    "gn:name":"Colonia Cosoltepec",
    "gn:population":312,
    "gn:timezone":"America/Mexico_City",
    "iso:country":"MX",
    "wof:name":"Colonia Cosoltepec",
    "wof:placetype":"locality",
    "wof:population":312
},
  "geometry": {"coordinates":[-96.36389,18.28139],"type":"Point"}
}