{
  "type": "Feature",
  "properties": {
    "gn:admin1_code":"21.0",
    "gn:admin2_code":"114.0",
    "gn:asciiname":"Seccion Sexta de San Miguel Canoa",
    "gn:country_code":"MX",
    "gn:dem":2482,
    "gn:feature_class":"P",
    "gn:feature_code":"PPL",
    "gn:name":"Secci\u00f3n Sexta de San Miguel Canoa",
    "gn:population":0,
    "gn:timezone":"America/Mexico_City",
    "iso:country":"MX",
    "name:spa_x_preferred":[
        "Secci\u00f3n Sexta de San Miguel Canoa"
    ],
    "wof:name":"Seccion Sexta de San Miguel Canoa",
    "wof:placetype":"locality"
},
  "geometry": {"coordinates":[-98.1165,19.13494],"type":"Point"}
}