{
  "type": "Feature",
  "properties": {
    "gn:admin1_code":"10",
    "gn:admin2_code":"14",
    "gn:asciiname":"Mesa de Duraznitos",
    "gn:country_code":"MX",
    "gn:dem":2108,
    "gn:feature_class":"P",
    "gn:feature_code":"PPL",
    "gn:name":"Mesa de Duraznitos",
    "gn:population":35,
    "gn:timezone":"America/Monterrey",
    "iso:country":"MX",
    "wof:name":"Mesa de Duraznitos",
    "wof:placetype":"locality",
    "wof:population":35
},
  "geometry": {"coordinates":[-104.63969,22.94809],"type":"Point"}
}