{
  "type": "Feature",
  "properties": {
    "gn:admin1_code":"26.0",
    "gn:admin2_code":"44.0",
    "gn:asciiname":"Agua del Buey",
    "gn:country_code":"MX",
    "gn:dem":694,
    "gn:feature_class":"P",
    "gn:feature_code":"PPL",
    "gn:name":"Agua del Buey",
    "gn:population":0,
    "gn:timezone":"America/Hermosillo",
    "iso:country":"MX",
    "name:spa_x_preferred":[
        "Agua del Buey"
    ],
    "wof:name":"Agua del Buey",
    "wof:placetype":"locality"
},
  "geometry": {"coordinates":[-109.459,28.51297000000001],"type":"Point"}
}