{
  "type": "Feature",
  "properties": {
    "gn:admin1_code":"25",
    "gn:admin2_code":"3.0",
    "gn:asciiname":"Los Cuates",
    "gn:cc2":"MX",
    "gn:country_code":"MX",
    "gn:dem":1364,
    "gn:feature_class":"P",
    "gn:feature_code":"PPL",
    "gn:name":"Los Cuates",
    "gn:population":11,
    "gn:timezone":"America/Chihuahua",
    "iso:country":"MX",
    "name:und_x_variant":[
        "San Jos\u00e9 Ladesma",
        "Cuates",
        "Los Cuates"
    ],
    "wof:name":"Los Cuates",
    "wof:placetype":"locality",
    "wof:population":11
},
  "geometry": {"coordinates":[-107.13937,25.78342],"type":"Point"}
}