{
  "type": "Feature",
  "properties": {
    "gn:admin1_code":"30",
    "gn:admin2_code":"141",
    "gn:asciiname":"Los Puchetas",
    "gn:country_code":"MX",
    "gn:dem":368,
    "gn:feature_class":"P",
    "gn:feature_code":"PPL",
    "gn:name":"Los Puchetas",
    "gn:population":53,
    "gn:timezone":"America/Mexico_City",
    "iso:country":"MX",
    "wof:name":"Los Puchetas",
    "wof:placetype":"locality",
    "wof:population":53
},
  "geometry": {"coordinates":[-95.17333000000001,18.34361],"type":"Point"}
}