{
  "type": "Feature",
  "properties": {
    "gn:admin1_code":"25",
    "gn:admin2_code":"18.0",
    "gn:asciiname":"La Reforma",
    "gn:country_code":"MX",
    "gn:dem":17,
    "gn:feature_class":"P",
    "gn:feature_code":"PPL",
    "gn:name":"La Reforma",
    "gn:population":5,
    "gn:timezone":"America/Mazatlan",
    "iso:country":"MX",
    "name:cym_x_preferred":[
        "La Reforma"
    ],
    "name:nld_x_preferred":[
        "Reforma"
    ],
    "name:por_x_preferred":[
        "La Reforma"
    ],
    "wof:name":"La Reforma",
    "wof:placetype":"locality",
    "wof:population":5
},
  "geometry": {"coordinates":[-107.64743,24.80404],"type":"Point"}
}