{
  "type": "Feature",
  "properties": {
    "gn:admin1_code":"4.0",
    "gn:admin2_code":"11.0",
    "gn:asciiname":"El Paisa",
    "gn:country_code":"MX",
    "gn:dem":53,
    "gn:feature_class":"P",
    "gn:feature_code":"PPL",
    "gn:name":"El Paisa",
    "gn:population":0,
    "gn:timezone":"America/Merida",
    "iso:country":"MX",
    "name:spa_x_preferred":[
        "El Paisa"
    ],
    "wof:name":"El Paisa",
    "wof:placetype":"locality"
},
  "geometry": {"coordinates":[-90.86879,17.8656],"type":"Point"}
}