{
  "type": "Feature",
  "properties": {
    "gn:admin1_code":"30",
    "gn:admin2_code":"43.0",
    "gn:asciiname":"Tiolinga",
    "gn:country_code":"MX",
    "gn:dem":655,
    "gn:feature_class":"P",
    "gn:feature_code":"PPL",
    "gn:name":"Tiolinga",
    "gn:population":0,
    "gn:timezone":"America/Mexico_City",
    "iso:country":"MX",
    "name:spa_x_preferred":[
        "Tiolinga"
    ],
    "wof:name":"Tiolinga",
    "wof:placetype":"locality"
},
  "geometry": {"coordinates":[-96.74393999999999,19.15923],"type":"Point"}
}