{
  "type": "Feature",
  "properties": {
    "gn:admin1_code":"14",
    "gn:admin2_code":"87",
    "gn:asciiname":"La Pedregosa",
    "gn:country_code":"MX",
    "gn:dem":1235,
    "gn:feature_class":"P",
    "gn:feature_code":"PPL",
    "gn:name":"La Pedregosa",
    "gn:population":14,
    "gn:timezone":"America/Mexico_City",
    "iso:country":"MX",
    "wof:name":"La Pedregosa",
    "wof:placetype":"locality",
    "wof:population":14
},
  "geometry": {"coordinates":[-103.19861,19.39778],"type":"Point"}
}