{
  "type": "Feature",
  "properties": {
    "gn:admin1_code":"30",
    "gn:admin2_code":"174.0",
    "gn:asciiname":"El Chismoso",
    "gn:country_code":"MX",
    "gn:dem":22,
    "gn:feature_class":"P",
    "gn:feature_code":"PPL",
    "gn:name":"El Chismoso",
    "gn:population":63,
    "gn:timezone":"America/Mexico_City",
    "iso:country":"MX",
    "wof:name":"El Chismoso",
    "wof:placetype":"locality",
    "wof:population":63
},
  "geometry": {"coordinates":[-96.13388999999999,18.55972],"type":"Point"}
}