{
  "type": "Feature",
  "properties": {
    "gn:admin1_code":"10.0",
    "gn:admin2_code":"14.0",
    "gn:asciiname":"Yerbabuena",
    "gn:country_code":"MX",
    "gn:dem":963,
    "gn:feature_class":"P",
    "gn:feature_code":"PPL",
    "gn:name":"Yerbabuena",
    "gn:population":0,
    "gn:timezone":"America/Monterrey",
    "iso:country":"MX",
    "name:spa_x_preferred":[
        "Yerbabuena"
    ],
    "wof:name":"Yerbabuena",
    "wof:placetype":"locality"
},
  "geometry": {"coordinates":[-104.57147000000001,22.47236],"type":"Point"}
}