{
  "type": "Feature",
  "properties": {
    "gn:admin1_code":"14.0",
    "gn:admin2_code":"21.0",
    "gn:asciiname":"Coacoyul",
    "gn:country_code":"MX",
    "gn:dem":300,
    "gn:feature_class":"P",
    "gn:feature_code":"PPL",
    "gn:name":"Coacoyul",
    "gn:population":0,
    "gn:timezone":"America/Mexico_City",
    "iso:country":"MX",
    "name:spa_x_preferred":[
        "Coacoyul"
    ],
    "wof:name":"Coacoyul",
    "wof:placetype":"locality"
},
  "geometry": {"coordinates":[-104.54385000000001,19.59315],"type":"Point"}
}