{
  "type": "Feature",
  "properties": {
    "gn:admin1_code":"12.0",
    "gn:admin2_code":"16.0",
    "gn:asciiname":"Abejones",
    "gn:country_code":"MX",
    "gn:dem":374,
    "gn:feature_class":"P",
    "gn:feature_code":"PPL",
    "gn:name":"Abejones",
    "gn:population":0,
    "gn:timezone":"America/Mexico_City",
    "iso:country":"MX",
    "name:epo_x_preferred":[
        "Abejones"
    ],
    "name:eus_x_preferred":[
        "Abejones"
    ],
    "name:fas_x_preferred":[
        "\u0627\u0628\u062c\u0648\u0646\u0633"
    ],
    "name:fra_x_preferred":[
        "Abejones"
    ],
    "name:ita_x_preferred":[
        "Abejones"
    ],
    "name:rus_x_preferred":[
        "\u0410\u0431\u0435\u0445\u043e\u043d\u0435\u0441"
    ],
    "name:sco_x_preferred":[
        "Abejones"
    ],
    "name:srp_x_preferred":[
        "\u041e\u043f\u0448\u0442\u0438\u043d\u0430 \u0410\u0431\u0435\u0445\u043e\u043d\u0435\u0441"
    ],
    "name:vie_x_preferred":[
        "Abejones"
    ],
    "wof:name":"Abejones",
    "wof:placetype":"locality"
},
  "geometry": {"coordinates":[-101.56667,18.06667],"type":"Point"}
}