{
  "type": "Feature",
  "properties": {
    "gn:admin1_code":"26.0",
    "gn:admin2_code":"35.0",
    "gn:asciiname":"Los Perez",
    "gn:country_code":"MX",
    "gn:dem":1021,
    "gn:feature_class":"P",
    "gn:feature_code":"PPL",
    "gn:name":"Los P\u00e9rez",
    "gn:population":0,
    "gn:timezone":"America/Hermosillo",
    "iso:country":"MX",
    "name:spa_x_preferred":[
        "Los P\u00e9rez"
    ],
    "name:und_x_variant":[
        "Los Charrasqueados"
    ],
    "wof:name":"Los Perez",
    "wof:placetype":"locality"
},
  "geometry": {"coordinates":[-110.77752,30.84647],"type":"Point"}
}