{
  "type": "Feature",
  "properties": {
    "gn:admin1_code":"10.0",
    "gn:admin2_code":"9.0",
    "gn:asciiname":"La Medalla",
    "gn:country_code":"MX",
    "gn:dem":2678,
    "gn:feature_class":"P",
    "gn:feature_code":"PPL",
    "gn:name":"La Medalla",
    "gn:population":0,
    "gn:timezone":"America/Monterrey",
    "iso:country":"MX",
    "name:spa_x_preferred":[
        "La Medalla"
    ],
    "wof:name":"La Medalla",
    "wof:placetype":"locality"
},
  "geometry": {"coordinates":[-106.2124,26.0356],"type":"Point"}
}