{
  "type": "Feature",
  "properties": {
    "gn:admin1_code":"26",
    "gn:admin2_code":"45.0",
    "gn:asciiname":"El Alivio",
    "gn:country_code":"MX",
    "gn:dem":783,
    "gn:feature_class":"P",
    "gn:feature_code":"PPL",
    "gn:name":"El Alivio",
    "gn:population":0,
    "gn:timezone":"America/Hermosillo",
    "iso:country":"MX",
    "name:spa_x_preferred":[
        "El Alivio"
    ],
    "wof:name":"El Alivio",
    "wof:placetype":"locality"
},
  "geometry": {"coordinates":[-110.69503,30.1834],"type":"Point"}
}