{
  "type": "Feature",
  "properties": {
    "gn:admin1_code":"11",
    "gn:admin2_code":"30",
    "gn:asciiname":"Tanque de San Ignacio",
    "gn:country_code":"MX",
    "gn:dem":2096,
    "gn:feature_class":"P",
    "gn:feature_code":"PPL",
    "gn:name":"Tanque de San Ignacio",
    "gn:population":12,
    "gn:timezone":"America/Mexico_City",
    "iso:country":"MX",
    "wof:name":"Tanque de San Ignacio",
    "wof:placetype":"locality",
    "wof:population":12
},
  "geometry": {"coordinates":[-101.24583,21.37417],"type":"Point"}
}