{
  "type": "Feature",
  "properties": {
    "gn:admin1_code":"7.0",
    "gn:asciiname":"San Pedro del Sauz",
    "gn:country_code":"MX",
    "gn:dem":586,
    "gn:feature_class":"P",
    "gn:feature_code":"PPL",
    "gn:name":"San Pedro del Sauz",
    "gn:population":0,
    "gn:timezone":"America/Monterrey",
    "iso:country":"MX",
    "name:spa_x_preferred":[
        "San Pedro del Sauz"
    ],
    "name:spa_x_variant":[
        "Los Pinos"
    ],
    "wof:name":"San Pedro del Sauz",
    "wof:placetype":"locality"
},
  "geometry": {"coordinates":[-101.33011,26.93782],"type":"Point"}
}