{
  "type": "Feature",
  "properties": {
    "gn:admin1_code":"28.0",
    "gn:admin2_code":"24.0",
    "gn:asciiname":"Abra el Ebanito",
    "gn:country_code":"MX",
    "gn:dem":113,
    "gn:feature_class":"P",
    "gn:feature_code":"PPL",
    "gn:name":"Abra el Ebanito",
    "gn:population":0,
    "gn:timezone":"America/Monterrey",
    "iso:country":"MX",
    "name:spa_x_preferred":[
        "Abra el Ebanito"
    ],
    "wof:name":"Abra el Ebanito",
    "wof:placetype":"locality"
},
  "geometry": {"coordinates":[-99.20533,26.495],"type":"Point"}
}