{
  "type": "Feature",
  "properties": {
    "gn:admin1_code":"30",
    "gn:admin2_code":"100.0",
    "gn:asciiname":"Dos Bocas",
    "gn:country_code":"MX",
    "gn:dem":37,
    "gn:feature_class":"P",
    "gn:feature_code":"PPL",
    "gn:name":"Dos Bocas",
    "gn:population":0,
    "gn:timezone":"America/Mexico_City",
    "iso:country":"MX",
    "name:spa_x_preferred":[
        "Dos Bocas"
    ],
    "wof:name":"Dos Bocas",
    "wof:placetype":"locality"
},
  "geometry": {"coordinates":[-96.31676,19.00157],"type":"Point"}
}