{
  "type": "Feature",
  "properties": {
    "gn:admin1_code":"25",
    "gn:admin2_code":"10.0",
    "gn:asciiname":"Bacamocha",
    "gn:country_code":"MX",
    "gn:dem":102,
    "gn:feature_class":"P",
    "gn:feature_code":"PPL",
    "gn:name":"Bacamocha",
    "gn:population":0,
    "gn:timezone":"America/Mazatlan",
    "iso:country":"MX",
    "name:spa_x_preferred":[
        "Bacamocha"
    ],
    "wof:name":"Bacamocha",
    "wof:placetype":"locality"
},
  "geometry": {"coordinates":[-108.66067,26.2788],"type":"Point"}
}