{
  "type": "Feature",
  "properties": {
    "iso:country":"MX",
    "name:cat_x_preferred":[
        "Ap\u00f3stol Santiago"
    ],
    "name:por_x_preferred":[
        "Ap\u00f3stol Santiago"
    ],
    "name:spa_x_preferred":[
        "Santiago Apostol Centro"
    ],
    "qs:gn_adm0_cc":"MX",
    "qs:gn_local":3801625,
    "qs:gn_nam_loc":"Santiago Apostol, Santiago Apostol, Oaxaca, MX",
    "qs:gn_namadm1":"20",
    "qs:local_max":8,
    "qs:local_sum":8,
    "qs:localhoods":1,
    "qs:name":"Santiago Apostol Centro",
    "qs:name_adm0":"M\u00e9xico",
    "qs:name_adm1":"Oaxaca",
    "qs:name_adm2":"Santiago Apostol",
    "qs:name_local":"Santiago Apostol",
    "qs:photo_max":4,
    "qs:photo_sum":8,
    "qs:placetype":"Suburb",
    "qs:quad_count":4,
    "qs:woe_adm0":23424900,
    "qs:woe_adm1":2346283,
    "qs:woe_adm2":12601113,
    "qs:woe_lau":0,
    "qs:woe_local":26797961,
    "qs:woe_ver":"7.10.0",
    "wof:lang":[
        "spa"
    ],
    "wof:name":"Santiago Apostol Centro",
    "wof:placetype":"neighbourhood"
},
  "geometry": {"coordinates":[-96.72294599999999,16.803884],"type":"Point"}
}