{
  "type": "Feature",
  "properties": {
    "gn:admin1_code":"6",
    "gn:admin2_code":"48.0",
    "gn:asciiname":"Santa Gertrudis de Abajo",
    "gn:country_code":"MX",
    "gn:dem":1952,
    "gn:feature_class":"P",
    "gn:feature_code":"PPL",
    "gn:name":"Santa Gertrudis de Abajo",
    "gn:population":29,
    "gn:timezone":"America/Chihuahua",
    "iso:country":"MX",
    "name:spa_x_preferred":[
        "Santa Gertrudis de Abajo"
    ],
    "wof:name":"Santa Gertrudis de Abajo",
    "wof:placetype":"locality",
    "wof:population":29
},
  "geometry": {"coordinates":[-107.26251999999999,29.16514],"type":"Point"}
}