{
  "type": "Feature",
  "properties": {
    "gn:admin1_code":"31",
    "gn:admin2_code":"6.0",
    "gn:asciiname":"X-Bec",
    "gn:country_code":"MX",
    "gn:dem":6,
    "gn:feature_class":"P",
    "gn:feature_code":"PPL",
    "gn:name":"X-Bec",
    "gn:population":462,
    "gn:timezone":"America/Merida",
    "iso:country":"MX",
    "wof:name":"X-Bec",
    "wof:placetype":"locality",
    "wof:population":462
},
  "geometry": {"coordinates":[-88.82472,21.24833],"type":"Point"}
}