{
  "type": "Feature",
  "properties": {
    "gn:admin1_code":"15",
    "gn:admin2_code":"52.0",
    "gn:asciiname":"El Platanar",
    "gn:country_code":"MX",
    "gn:dem":1268,
    "gn:feature_class":"P",
    "gn:feature_code":"PPL",
    "gn:name":"El Platanar",
    "gn:population":0,
    "gn:timezone":"America/Mexico_City",
    "iso:country":"MX",
    "name:spa_x_preferred":[
        "El Platanar"
    ],
    "name:und_x_variant":[
        "Platanar"
    ],
    "wof:name":"El Platanar",
    "wof:placetype":"locality"
},
  "geometry": {"coordinates":[-99.45707,18.8302],"type":"Point"}
}