{
  "type": "Feature",
  "properties": {
    "gn:admin1_code":"6",
    "gn:admin2_code":"8.0",
    "gn:asciiname":"Rancheria Pitorreal",
    "gn:country_code":"MX",
    "gn:dem":2411,
    "gn:feature_class":"P",
    "gn:feature_code":"PPL",
    "gn:name":"Rancher\u00eda Pitorreal",
    "gn:population":0,
    "gn:timezone":"America/Chihuahua",
    "iso:country":"MX",
    "name:spa_x_preferred":[
        "Rancher\u00eda Pitorreal"
    ],
    "wof:name":"Rancheria Pitorreal",
    "wof:placetype":"locality"
},
  "geometry": {"coordinates":[-107.56706,26.92568],"type":"Point"}
}