{
  "type": "Feature",
  "properties": {
    "gn:admin1_code":"12",
    "gn:admin2_code":"12",
    "gn:asciiname":"Zacatula",
    "gn:country_code":"MX",
    "gn:dem":200,
    "gn:feature_class":"P",
    "gn:feature_code":"PPL",
    "gn:name":"Zacatula",
    "gn:population":26,
    "gn:timezone":"America/Mexico_City",
    "iso:country":"MX",
    "wof:name":"Zacatula",
    "wof:placetype":"locality",
    "wof:population":26
},
  "geometry": {"coordinates":[-99.09005999999999,16.77912],"type":"Point"}
}