{
  "type": "Feature",
  "properties": {
    "gn:admin1_code":"12",
    "gn:admin2_code":"48.0",
    "gn:asciiname":"Carrizo",
    "gn:country_code":"MX",
    "gn:dem":364,
    "gn:feature_class":"P",
    "gn:feature_code":"PPL",
    "gn:name":"Carrizo",
    "gn:population":0,
    "gn:timezone":"America/Mexico_City",
    "iso:country":"MX",
    "name:ceb_x_preferred":[
        "Carrizo"
    ],
    "name:deu_x_preferred":[
        "Carrizo"
    ],
    "name:glg_x_preferred":[
        "Carrizo"
    ],
    "name:ita_x_preferred":[
        "Carrizo"
    ],
    "name:jpn_x_preferred":[
        "\u30ab\u30ea\u30fc\u30bd"
    ],
    "name:nld_x_preferred":[
        "Carrizo"
    ],
    "name:por_x_preferred":[
        "Carrizo"
    ],
    "name:spa_x_preferred":[
        "Carrizo"
    ],
    "name:swe_x_preferred":[
        "Carrizo"
    ],
    "wof:name":"Carrizo",
    "wof:placetype":"locality"
},
  "geometry": {"coordinates":[-101.09738,17.45038],"type":"Point"}
}