{
  "type": "Feature",
  "properties": {
    "gn:admin1_code":"5",
    "gn:admin2_code":"12.0",
    "gn:asciiname":"El Corralito",
    "gn:country_code":"MX",
    "gn:dem":851,
    "gn:feature_class":"P",
    "gn:feature_code":"PPL",
    "gn:name":"El Corralito",
    "gn:population":5,
    "gn:timezone":"America/Mexico_City",
    "iso:country":"MX",
    "wof:name":"El Corralito",
    "wof:placetype":"locality",
    "wof:population":5
},
  "geometry": {"coordinates":[-93.24972,16.80111],"type":"Point"}
}