{
  "type": "Feature",
  "properties": {
    "gn:admin1_code":"31",
    "gn:admin2_code":"18.0",
    "gn:asciiname":"Canalun",
    "gn:country_code":"MX",
    "gn:dem":20,
    "gn:feature_class":"P",
    "gn:feature_code":"PPL",
    "gn:name":"Canal\u00fan",
    "gn:population":0,
    "gn:timezone":"America/Merida",
    "iso:country":"MX",
    "wof:name":"Canalun",
    "wof:placetype":"locality"
},
  "geometry": {"coordinates":[-89.48333000000002,20.48333],"type":"Point"}
}