{
  "type": "Feature",
  "properties": {
    "gn:admin1_code":"19",
    "gn:admin2_code":"33.0",
    "gn:asciiname":"La Pamona",
    "gn:country_code":"MX",
    "gn:dem":193,
    "gn:feature_class":"P",
    "gn:feature_code":"PPL",
    "gn:name":"La Pamona",
    "gn:population":0,
    "gn:timezone":"America/Monterrey",
    "iso:country":"MX",
    "name:spa_x_preferred":[
        "La Pamona"
    ],
    "wof:name":"La Pamona",
    "wof:placetype":"locality"
},
  "geometry": {"coordinates":[-99.20526,24.99904],"type":"Point"}
}