{
  "type": "Feature",
  "properties": {
    "gn:admin1_code":"27",
    "gn:admin2_code":"8.0",
    "gn:asciiname":"Bellas Artes",
    "gn:country_code":"MX",
    "gn:dem":22,
    "gn:feature_class":"P",
    "gn:feature_code":"PPL",
    "gn:name":"Bellas Artes",
    "gn:population":0,
    "gn:timezone":"America/Mexico_City",
    "iso:country":"MX",
    "name:fra_x_preferred":[
        "Bellas Artes"
    ],
    "name:ita_x_preferred":[
        "Bellas Artes"
    ],
    "name:spa_x_preferred":[
        "Bellas Artes"
    ],
    "name:spa_x_variant":[
        "Bellas artes"
    ],
    "wof:name":"Bellas Artes",
    "wof:placetype":"locality"
},
  "geometry": {"coordinates":[-93.73048,17.63628],"type":"Point"}
}