{
  "type": "Feature",
  "properties": {
    "gn:admin1_code":"32.0",
    "gn:asciiname":"Rancho Tomas",
    "gn:country_code":"MX",
    "gn:dem":1973,
    "gn:feature_class":"P",
    "gn:feature_code":"PPL",
    "gn:name":"Rancho Tom\u00e1s",
    "gn:population":0,
    "gn:timezone":"America/Mexico_City",
    "iso:country":"MX",
    "name:spa_x_preferred":[
        "Rancho Tom\u00e1s"
    ],
    "name:spa_x_variant":[
        "El Cerro de las Piedras Negras"
    ],
    "wof:name":"Rancho Tomas",
    "wof:placetype":"locality"
},
  "geometry": {"coordinates":[-103.88225,22.33074],"type":"Point"}
}