{
  "type": "Feature",
  "properties": {
    "gn:admin1_code":"14",
    "gn:admin2_code":"61",
    "gn:asciiname":"Los Pinabetes",
    "gn:country_code":"MX",
    "gn:dem":2279,
    "gn:feature_class":"P",
    "gn:feature_code":"PPL",
    "gn:name":"Los Pinabetes",
    "gn:population":12,
    "gn:timezone":"America/Mexico_City",
    "iso:country":"MX",
    "wof:name":"Los Pinabetes",
    "wof:placetype":"locality",
    "wof:population":12
},
  "geometry": {"coordinates":[-104.02500000000001,22.30528],"type":"Point"}
}