{
  "type": "Feature",
  "properties": {
    "gn:admin1_code":"26",
    "gn:admin2_code":"18.0",
    "gn:asciiname":"Bahia",
    "gn:country_code":"MX",
    "gn:dem":33,
    "gn:feature_class":"P",
    "gn:feature_code":"PPL",
    "gn:name":"Bah\u00eda",
    "gn:population":0,
    "gn:timezone":"America/Hermosillo",
    "iso:country":"MX",
    "name:spa_x_preferred":[
        "Bah\u00eda"
    ],
    "wof:name":"Bahia",
    "wof:placetype":"locality"
},
  "geometry": {"coordinates":[-109.96268000000001,27.60592],"type":"Point"}
}