{
  "type": "Feature",
  "properties": {
    "gn:admin1_code":"20",
    "gn:admin2_code":"492.0",
    "gn:asciiname":"Buenavista",
    "gn:country_code":"MX",
    "gn:dem":2388,
    "gn:feature_class":"P",
    "gn:feature_code":"PPL",
    "gn:name":"Buenavista",
    "gn:population":117,
    "gn:timezone":"America/Mexico_City",
    "iso:country":"MX",
    "wof:name":"Buenavista",
    "wof:placetype":"locality",
    "wof:population":117
},
  "geometry": {"coordinates":[-97.34111,17.31333],"type":"Point"}
}