{
  "type": "Feature",
  "properties": {
    "gn:admin1_code":"25",
    "gn:admin2_code":"12.0",
    "gn:asciiname":"Las Tatemas de Abajo",
    "gn:country_code":"MX",
    "gn:dem":168,
    "gn:feature_class":"P",
    "gn:feature_code":"PPL",
    "gn:name":"Las Tatemas de Abajo",
    "gn:population":0,
    "gn:timezone":"America/Mazatlan",
    "iso:country":"MX",
    "name:spa_x_preferred":[
        "Las Tatemas de Abajo"
    ],
    "wof:name":"Las Tatemas de Abajo",
    "wof:placetype":"locality"
},
  "geometry": {"coordinates":[-106.25115,23.55612],"type":"Point"}
}