{
  "type": "Feature",
  "properties": {
    "gn:admin1_code":"23",
    "gn:admin2_code":"4",
    "gn:asciiname":"La Divina Esperanza",
    "gn:country_code":"MX",
    "gn:dem":8,
    "gn:feature_class":"P",
    "gn:feature_code":"PPL",
    "gn:name":"La Divina Esperanza",
    "gn:population":16,
    "gn:timezone":"America/Cancun",
    "iso:country":"MX",
    "wof:name":"La Divina Esperanza",
    "wof:placetype":"locality",
    "wof:population":16
},
  "geometry": {"coordinates":[-87.72278,18.71611],"type":"Point"}
}