{
  "type": "Feature",
  "properties": {
    "gn:admin1_code":"5",
    "gn:admin2_code":"3.0",
    "gn:asciiname":"La Lupe",
    "gn:country_code":"MX",
    "gn:dem":1,
    "gn:feature_class":"P",
    "gn:feature_code":"PPL",
    "gn:name":"La Lupe",
    "gn:population":144,
    "gn:timezone":"America/Merida",
    "iso:country":"MX",
    "name:azb_x_preferred":[
        "\u0644\u0648\u067e\u0647"
    ],
    "name:bre_x_preferred":[
        "La Lupe"
    ],
    "name:cat_x_preferred":[
        "La Lupe"
    ],
    "name:deu_x_preferred":[
        "La Lupe"
    ],
    "name:epo_x_preferred":[
        "La Lupe"
    ],
    "name:fas_x_preferred":[
        "\u0644\u0648\u067e\u0647"
    ],
    "name:fra_x_preferred":[
        "La Lupe"
    ],
    "name:jpn_x_preferred":[
        "\u30e9\u30fb\u30eb\u30fc\u30da"
    ],
    "name:rus_x_preferred":[
        "\u041b\u0430 \u041b\u0443\u043f\u0435"
    ],
    "name:spa_x_preferred":[
        "La Lupe"
    ],
    "name:srp_x_preferred":[
        "\u041b\u0430 \u041b\u0443\u043f\u0435"
    ],
    "wof:name":"La Lupe",
    "wof:placetype":"locality",
    "wof:population":144
},
  "geometry": {"coordinates":[-92.87056,15.17528],"type":"Point"}
}