{
  "type": "Feature",
  "properties": {
    "gn:admin1_code":"32",
    "gn:admin2_code":"38.0",
    "gn:asciiname":"Los Rodriguez",
    "gn:country_code":"MX",
    "gn:dem":1998,
    "gn:feature_class":"P",
    "gn:feature_code":"PPL",
    "gn:name":"Los Rodr\u00edguez",
    "gn:population":8,
    "gn:timezone":"America/Mexico_City",
    "iso:country":"MX",
    "name:und_x_variant":[
        "Los Rodr\u00edguez"
    ],
    "wof:name":"Los Rodriguez",
    "wof:placetype":"locality",
    "wof:population":8
},
  "geometry": {"coordinates":[-101.43778,22.63278],"type":"Point"}
}