{
  "type": "Feature",
  "properties": {
    "gn:admin1_code":"24",
    "gn:admin2_code":"22.0",
    "gn:asciiname":"Tapado",
    "gn:country_code":"MX",
    "gn:dem":1943,
    "gn:feature_class":"P",
    "gn:feature_code":"PPL",
    "gn:name":"Tapado",
    "gn:population":0,
    "gn:timezone":"America/Mexico_City",
    "iso:country":"MX",
    "wof:name":"Tapado",
    "wof:placetype":"locality"
},
  "geometry": {"coordinates":[-101.43848,22.79174],"type":"Point"}
}