{
  "type": "Feature",
  "properties": {
    "gn:admin1_code":"21.0",
    "gn:admin2_code":"153.0",
    "gn:asciiname":"Tzocuilac",
    "gn:country_code":"MX",
    "gn:dem":2144,
    "gn:feature_class":"P",
    "gn:feature_code":"PPL",
    "gn:name":"Tzocuilac",
    "gn:population":0,
    "gn:timezone":"America/Mexico_City",
    "iso:country":"MX",
    "name:spa_x_preferred":[
        "Tzocuilac"
    ],
    "wof:name":"Tzocuilac",
    "wof:placetype":"locality"
},
  "geometry": {"coordinates":[-97.99178999999999,18.89885],"type":"Point"}
}