{
  "type": "Feature",
  "properties": {
    "gn:admin1_code":"31",
    "gn:admin2_code":"11.0",
    "gn:asciiname":"Santa Cruz Xixin",
    "gn:country_code":"MX",
    "gn:dem":5,
    "gn:feature_class":"P",
    "gn:feature_code":"PPL",
    "gn:name":"Santa Cruz Xixin",
    "gn:population":0,
    "gn:timezone":"America/Merida",
    "iso:country":"MX",
    "wof:name":"Santa Cruz Xixin",
    "wof:placetype":"locality"
},
  "geometry": {"coordinates":[-90.35863999999999,20.9592],"type":"Point"}
}