{
  "type": "Feature",
  "properties": {
    "gn:admin1_code":"25.0",
    "gn:admin2_code":"6.0",
    "gn:asciiname":"Capulito",
    "gn:country_code":"MX",
    "gn:dem":100,
    "gn:feature_class":"P",
    "gn:feature_code":"PPL",
    "gn:name":"Capulito",
    "gn:population":0,
    "gn:timezone":"America/Mazatlan",
    "iso:country":"MX",
    "name:spa_x_preferred":[
        "Capulito"
    ],
    "name:und_x_variant":[
        "El Capulito"
    ],
    "wof:name":"Capulito",
    "wof:placetype":"locality"
},
  "geometry": {"coordinates":[-107.23860000000001,24.65483],"type":"Point"}
}