{
  "type": "Feature",
  "properties": {
    "gn:admin1_code":"20",
    "gn:admin2_code":"310.0",
    "gn:asciiname":"Jardines del Tepeyac",
    "gn:country_code":"MX",
    "gn:dem":1680,
    "gn:feature_class":"P",
    "gn:feature_code":"PPL",
    "gn:name":"Jardines del Tepeyac",
    "gn:population":103,
    "gn:timezone":"America/Mexico_City",
    "iso:country":"MX",
    "wof:name":"Jardines del Tepeyac",
    "wof:placetype":"locality",
    "wof:population":103
},
  "geometry": {"coordinates":[-96.8275,17.04833],"type":"Point"}
}