{
  "type": "Feature",
  "properties": {
    "gn:admin1_code":"14",
    "gn:admin2_code":"59",
    "gn:asciiname":"Palos Gordos",
    "gn:country_code":"MX",
    "gn:dem":2113,
    "gn:feature_class":"P",
    "gn:feature_code":"PPL",
    "gn:name":"Palos Gordos",
    "gn:population":16,
    "gn:timezone":"America/Mexico_City",
    "iso:country":"MX",
    "wof:name":"Palos Gordos",
    "wof:placetype":"locality",
    "wof:population":16
},
  "geometry": {"coordinates":[-103.06667,19.92778],"type":"Point"}
}