{
  "type": "Feature",
  "properties": {
    "gn:admin1_code":"24",
    "gn:admin2_code":"31.0",
    "gn:asciiname":"El Coco",
    "gn:country_code":"MX",
    "gn:dem":461,
    "gn:feature_class":"P",
    "gn:feature_code":"PPL",
    "gn:name":"El Coco",
    "gn:population":414,
    "gn:timezone":"America/Mexico_City",
    "iso:country":"MX",
    "wof:name":"El Coco",
    "wof:placetype":"locality",
    "wof:population":414
},
  "geometry": {"coordinates":[-99.39111,21.62694],"type":"Point"}
}