{
  "type": "Feature",
  "properties": {
    "gn:admin1_code":"24",
    "gn:admin2_code":"29",
    "gn:asciiname":"Tahuache Uno",
    "gn:country_code":"MX",
    "gn:dem":99,
    "gn:feature_class":"P",
    "gn:feature_code":"PPL",
    "gn:name":"Tahuache Uno",
    "gn:population":14,
    "gn:timezone":"America/Mexico_City",
    "iso:country":"MX",
    "wof:name":"Tahuache Uno",
    "wof:placetype":"locality",
    "wof:population":14
},
  "geometry": {"coordinates":[-98.66528,21.45306],"type":"Point"}
}