{
  "type": "Feature",
  "properties": {
    "gn:admin1_code":"30.0",
    "gn:admin2_code":"121.0",
    "gn:asciiname":"El Cometa",
    "gn:country_code":"MX",
    "gn:dem":90,
    "gn:feature_class":"P",
    "gn:feature_code":"PPL",
    "gn:name":"El Cometa",
    "gn:population":2,
    "gn:timezone":"America/Mexico_City",
    "iso:country":"MX",
    "name:spa_x_preferred":[
        "El Cometa"
    ],
    "wof:name":"El Cometa",
    "wof:placetype":"locality",
    "wof:population":2
},
  "geometry": {"coordinates":[-97.96583,21.47583],"type":"Point"}
}