{
  "type": "Feature",
  "properties": {
    "gn:admin1_code":"6",
    "gn:admin2_code":"63",
    "gn:asciiname":"El Arbolito",
    "gn:country_code":"MX",
    "gn:dem":1673,
    "gn:feature_class":"P",
    "gn:feature_code":"PPL",
    "gn:name":"El Arbolito",
    "gn:population":20,
    "gn:timezone":"America/Chihuahua",
    "iso:country":"MX",
    "wof:name":"El Arbolito",
    "wof:placetype":"locality",
    "wof:population":20
},
  "geometry": {"coordinates":[-108.40913999999999,28.641],"type":"Point"}
}