{
  "type": "Feature",
  "properties": {
    "gn:admin1_code":"10.0",
    "gn:asciiname":"El Cuadro",
    "gn:country_code":"MX",
    "gn:dem":2420,
    "gn:feature_class":"P",
    "gn:feature_code":"PPL",
    "gn:name":"El Cuadro",
    "gn:population":0,
    "gn:timezone":"America/Monterrey",
    "iso:country":"MX",
    "name:spa_x_preferred":[
        "El Cuadro"
    ],
    "wof:name":"El Cuadro",
    "wof:placetype":"locality"
},
  "geometry": {"coordinates":[-106.05268,24.43859],"type":"Point"}
}