{
  "type": "Feature",
  "properties": {
    "gn:admin1_code":"6",
    "gn:admin2_code":"25.0",
    "gn:asciiname":"Pablo Amaya",
    "gn:country_code":"MX",
    "gn:dem":2150,
    "gn:feature_class":"P",
    "gn:feature_code":"PPL",
    "gn:name":"Pablo Amaya",
    "gn:population":0,
    "gn:timezone":"America/Chihuahua",
    "iso:country":"MX",
    "name:spa_x_preferred":[
        "Pablo Amaya"
    ],
    "name:spa_x_variant":[
        "La Martha"
    ],
    "wof:name":"Pablo Amaya",
    "wof:placetype":"locality"
},
  "geometry": {"coordinates":[-107.831,29.4789],"type":"Point"}
}