{
  "type": "Feature",
  "properties": {
    "gn:admin1_code":"32",
    "gn:admin2_code":"29.0",
    "gn:asciiname":"Pozo de Loreto Dos",
    "gn:country_code":"MX",
    "gn:dem":2082,
    "gn:feature_class":"P",
    "gn:feature_code":"PPL",
    "gn:name":"Pozo de Loreto Dos",
    "gn:population":0,
    "gn:timezone":"America/Mexico_City",
    "iso:country":"MX",
    "name:spa_x_preferred":[
        "Pozo de Loreto Dos"
    ],
    "wof:name":"Pozo de Loreto Dos",
    "wof:placetype":"locality"
},
  "geometry": {"coordinates":[-103.31276,23.99236],"type":"Point"}
}