{
  "type": "Feature",
  "properties": {
    "gn:admin1_code":"30",
    "gn:admin2_code":"70",
    "gn:asciiname":"El Chocolin",
    "gn:country_code":"MX",
    "gn:dem":51,
    "gn:feature_class":"P",
    "gn:feature_code":"PPL",
    "gn:name":"El Chocol\u00edn",
    "gn:population":15,
    "gn:timezone":"America/Mexico_City",
    "iso:country":"MX",
    "name:und_x_variant":[
        "El Chocol\u00edn"
    ],
    "wof:name":"El Chocolin",
    "wof:placetype":"locality",
    "wof:population":15
},
  "geometry": {"coordinates":[-94.65278000000001,17.46056],"type":"Point"}
}