{
  "type": "Feature",
  "properties": {
    "gn:admin1_code":"26",
    "gn:admin2_code":"43",
    "gn:asciiname":"Guadalupe (Jimenez)",
    "gn:country_code":"MX",
    "gn:dem":1227,
    "gn:feature_class":"P",
    "gn:feature_code":"PPL",
    "gn:name":"Guadalupe (Jim\u00e9nez)",
    "gn:population":16,
    "gn:timezone":"America/Hermosillo",
    "iso:country":"MX",
    "name:und_x_variant":[
        "Guadalupe (Jim\u00e9nez)"
    ],
    "wof:name":"Guadalupe (Jimenez)",
    "wof:placetype":"locality",
    "wof:population":16
},
  "geometry": {"coordinates":[-110.97306,31.21111],"type":"Point"}
}