{
  "type": "Feature",
  "properties": {
    "gn:admin1_code":"24.0",
    "gn:admin2_code":"40.0",
    "gn:asciiname":"El Caballito",
    "gn:country_code":"MX",
    "gn:dem":74,
    "gn:feature_class":"P",
    "gn:feature_code":"PPL",
    "gn:name":"El Caballito",
    "gn:population":0,
    "gn:timezone":"America/Mexico_City",
    "iso:country":"MX",
    "name:spa_x_preferred":[
        "El Caballito"
    ],
    "wof:name":"El Caballito",
    "wof:placetype":"locality"
},
  "geometry": {"coordinates":[-98.73215,21.82215],"type":"Point"}
}