{
  "type": "Feature",
  "properties": {
    "gn:admin1_code":"30",
    "gn:admin2_code":"105.0",
    "gn:asciiname":"Guillermina Morales",
    "gn:country_code":"MX",
    "gn:dem":36,
    "gn:feature_class":"P",
    "gn:feature_code":"PPL",
    "gn:name":"Guillermina Morales",
    "gn:population":8,
    "gn:timezone":"America/Mexico_City",
    "iso:country":"MX",
    "wof:name":"Guillermina Morales",
    "wof:placetype":"locality",
    "wof:population":8
},
  "geometry": {"coordinates":[-96.11888999999999,18.98778],"type":"Point"}
}