{
  "type": "Feature",
  "properties": {
    "gn:admin1_code":"32",
    "gn:admin2_code":"56.0",
    "gn:asciiname":"San Antonio de los Negros (Los Negros)",
    "gn:country_code":"MX",
    "gn:dem":2259,
    "gn:feature_class":"P",
    "gn:feature_code":"PPL",
    "gn:name":"San Antonio de los Negros (Los Negros)",
    "gn:population":87,
    "gn:timezone":"America/Mexico_City",
    "iso:country":"MX",
    "wof:name":"San Antonio de los Negros (Los Negros)",
    "wof:placetype":"locality",
    "wof:population":87
},
  "geometry": {"coordinates":[-102.76667,22.7375],"type":"Point"}
}