{
  "type": "Feature",
  "properties": {
    "gn:admin1_code":"6.0",
    "gn:admin2_code":"12.0",
    "gn:asciiname":"Cerritos Blancos",
    "gn:country_code":"MX",
    "gn:dem":1903,
    "gn:feature_class":"P",
    "gn:feature_code":"PPL",
    "gn:name":"Cerritos Blancos",
    "gn:population":0,
    "gn:timezone":"America/Chihuahua",
    "iso:country":"MX",
    "name:spa_x_preferred":[
        "Cerritos Blancos"
    ],
    "wof:name":"Cerritos Blancos",
    "wof:placetype":"locality"
},
  "geometry": {"coordinates":[-106.69304,27.6389],"type":"Point"}
}