{
  "type": "Feature",
  "properties": {
    "gn:admin1_code":"25",
    "gn:admin2_code":"14.0",
    "gn:asciiname":"Palmarito",
    "gn:country_code":"MX",
    "gn:dem":181,
    "gn:feature_class":"P",
    "gn:feature_code":"PPL",
    "gn:name":"Palmarito",
    "gn:population":84,
    "gn:timezone":"America/Mazatlan",
    "iso:country":"MX",
    "name:spa_x_preferred":[
        "Palmarito"
    ],
    "wof:name":"Palmarito",
    "wof:placetype":"locality",
    "wof:population":84
},
  "geometry": {"coordinates":[-105.64724,23.03861],"type":"Point"}
}