{
  "type": "Feature",
  "properties": {
    "gn:admin1_code":"14",
    "gn:admin2_code":"22.0",
    "gn:asciiname":"Cadillac Ranch",
    "gn:country_code":"MX",
    "gn:dem":8,
    "gn:feature_class":"P",
    "gn:feature_code":"PPL",
    "gn:name":"Cadillac Ranch",
    "gn:population":7,
    "gn:timezone":"America/Mexico_City",
    "iso:country":"MX",
    "wof:name":"Cadillac Ranch",
    "wof:placetype":"locality",
    "wof:population":7
},
  "geometry": {"coordinates":[-104.68472,19.21833],"type":"Point"}
}