{
  "type": "Feature",
  "properties": {
    "gn:admin1_code":"6",
    "gn:admin2_code":"27.0",
    "gn:asciiname":"Rosanachi",
    "gn:country_code":"MX",
    "gn:dem":2163,
    "gn:feature_class":"P",
    "gn:feature_code":"PPL",
    "gn:name":"Ros\u00e1nachi",
    "gn:population":0,
    "gn:timezone":"America/Chihuahua",
    "iso:country":"MX",
    "name:spa_x_preferred":[
        "Ros\u00e1nachi"
    ],
    "wof:name":"Rosanachi",
    "wof:placetype":"locality"
},
  "geometry": {"coordinates":[-107.31598,27.23242],"type":"Point"}
}