{
  "type": "Feature",
  "properties": {
    "gn:admin1_code":"6",
    "gn:admin2_code":"11.0",
    "gn:asciiname":"San Jorge",
    "gn:country_code":"MX",
    "gn:dem":1323,
    "gn:feature_class":"P",
    "gn:feature_code":"PPL",
    "gn:name":"San Jorge",
    "gn:population":0,
    "gn:timezone":"America/Chihuahua",
    "iso:country":"MX",
    "wof:name":"San Jorge",
    "wof:placetype":"locality"
},
  "geometry": {"coordinates":[-104.90000000000001,27.45],"type":"Point"}
}