{
  "type": "Feature",
  "properties": {
    "gn:admin1_code":"10",
    "gn:admin2_code":"12.0",
    "gn:asciiname":"Lucrecia Martinez",
    "gn:country_code":"MX",
    "gn:dem":1133,
    "gn:feature_class":"P",
    "gn:feature_code":"PPL",
    "gn:name":"Lucrecia Mart\u00ednez",
    "gn:population":6,
    "gn:timezone":"America/Monterrey",
    "iso:country":"MX",
    "name:und_x_variant":[
        "Lucrecia Mart\u00ednez"
    ],
    "wof:name":"Lucrecia Martinez",
    "wof:placetype":"locality",
    "wof:population":6
},
  "geometry": {"coordinates":[-103.50367,25.52278],"type":"Point"}
}