{
  "type": "Feature",
  "properties": {
    "gn:admin1_code":"4",
    "gn:admin2_code":"3.0",
    "gn:asciiname":"El Mango",
    "gn:country_code":"MX",
    "gn:dem":2,
    "gn:feature_class":"P",
    "gn:feature_code":"PPL",
    "gn:name":"El Mango",
    "gn:population":14,
    "gn:timezone":"America/Merida",
    "iso:country":"MX",
    "wof:name":"El Mango",
    "wof:placetype":"locality",
    "wof:population":14
},
  "geometry": {"coordinates":[-91.20917,18.48944],"type":"Point"}
}