{
  "type": "Feature",
  "properties": {
    "gn:admin1_code":"13",
    "gn:asciiname":"Tenango",
    "gn:country_code":"MX",
    "gn:dem":362,
    "gn:feature_class":"P",
    "gn:feature_code":"PPL",
    "gn:name":"Tenango",
    "gn:population":0,
    "gn:timezone":"America/Mexico_City",
    "iso:country":"MX",
    "name:ceb_x_preferred":[
        "Tenango"
    ],
    "name:deu_x_preferred":[
        "Tenango"
    ],
    "name:sco_x_preferred":[
        "Tenango"
    ],
    "name:spa_x_preferred":[
        "Tenango"
    ],
    "name:srp_x_preferred":[
        "\u0422\u0435\u043d\u0430\u043d\u0433\u043e"
    ],
    "name:swe_x_preferred":[
        "Tenango"
    ],
    "wof:name":"Tenango",
    "wof:placetype":"locality"
},
  "geometry": {"coordinates":[-98.69722,21.16389],"type":"Point"}
}