{
  "type": "Feature",
  "properties": {
    "gn:admin1_code":"24",
    "gn:admin2_code":"1.0",
    "gn:asciiname":"El Salitre",
    "gn:country_code":"MX",
    "gn:dem":1829,
    "gn:feature_class":"P",
    "gn:feature_code":"PPL",
    "gn:name":"El Salitre",
    "gn:population":194,
    "gn:timezone":"America/Mexico_City",
    "iso:country":"MX",
    "wof:name":"El Salitre",
    "wof:placetype":"locality",
    "wof:population":194
},
  "geometry": {"coordinates":[-101.14194000000001,22.42111],"type":"Point"}
}