{
  "type": "Feature",
  "properties": {
    "gn:admin1_code":"5",
    "gn:admin2_code":"22.0",
    "gn:asciiname":"Kanech",
    "gn:country_code":"MX",
    "gn:dem":1758,
    "gn:feature_class":"P",
    "gn:feature_code":"PPL",
    "gn:name":"Kanech",
    "gn:population":0,
    "gn:timezone":"America/Mexico_City",
    "iso:country":"MX",
    "name:spa_x_preferred":[
        "Canech"
    ],
    "name:spa_x_variant":[
        "Kanech"
    ],
    "wof:name":"Kanech",
    "wof:placetype":"locality"
},
  "geometry": {"coordinates":[-92.58832,16.98436],"type":"Point"}
}