{
  "type": "Feature",
  "properties": {
    "gn:admin1_code":"18",
    "gn:admin2_code":"5",
    "gn:asciiname":"Los Tobos",
    "gn:country_code":"MX",
    "gn:dem":1139,
    "gn:feature_class":"P",
    "gn:feature_code":"PPL",
    "gn:name":"Los Tobos",
    "gn:population":32,
    "gn:timezone":"America/Mazatlan",
    "iso:country":"MX",
    "wof:name":"Los Tobos",
    "wof:placetype":"locality",
    "wof:population":32
},
  "geometry": {"coordinates":[-105.20833,22.84],"type":"Point"}
}