{
  "type": "Feature",
  "properties": {
    "gn:admin1_code":"19",
    "gn:admin2_code":"7.0",
    "gn:asciiname":"Puerto Carretas",
    "gn:country_code":"MX",
    "gn:dem":1839,
    "gn:feature_class":"P",
    "gn:feature_code":"PPL",
    "gn:name":"Puerto Carretas",
    "gn:population":109,
    "gn:timezone":"America/Monterrey",
    "iso:country":"MX",
    "wof:name":"Puerto Carretas",
    "wof:placetype":"locality",
    "wof:population":109
},
  "geometry": {"coordinates":[-99.95801,24.05091],"type":"Point"}
}