{
  "type": "Feature",
  "properties": {
    "gn:admin1_code":"30",
    "gn:admin2_code":"161.0",
    "gn:asciiname":"Higinio Sanchez Arrieta (Maguey II)",
    "gn:country_code":"MX",
    "gn:dem":107,
    "gn:feature_class":"P",
    "gn:feature_code":"PPL",
    "gn:name":"Higinio S\u00e1nchez Arrieta (Maguey II)",
    "gn:population":5,
    "gn:timezone":"America/Mexico_City",
    "iso:country":"MX",
    "name:und_x_variant":[
        "Higinio S\u00e1nchez Arrieta (Maguey II)"
    ],
    "wof:name":"Higinio Sanchez Arrieta (Maguey II)",
    "wof:placetype":"locality",
    "wof:population":5
},
  "geometry": {"coordinates":[-98.25778,21.65083],"type":"Point"}
}