{
  "type": "Feature",
  "properties": {
    "gn:admin1_code":"26.0",
    "gn:admin2_code":"63.0",
    "gn:asciiname":"El Opotalito",
    "gn:country_code":"MX",
    "gn:dem":964,
    "gn:feature_class":"P",
    "gn:feature_code":"PPL",
    "gn:name":"El Opotalito",
    "gn:population":0,
    "gn:timezone":"America/Hermosillo",
    "iso:country":"MX",
    "name:spa_x_preferred":[
        "El Opotalito"
    ],
    "wof:name":"El Opotalito",
    "wof:placetype":"locality"
},
  "geometry": {"coordinates":[-109.70699,29.52689],"type":"Point"}
}