{
  "type": "Feature",
  "properties": {
    "gn:admin1_code":"18.0",
    "gn:asciiname":"Saldana",
    "gn:country_code":"MX",
    "gn:dem":1104,
    "gn:feature_class":"P",
    "gn:feature_code":"PPL",
    "gn:name":"Salda\u00f1a",
    "gn:population":0,
    "gn:timezone":"America/Mexico_City",
    "iso:country":"MX",
    "name:spa_x_preferred":[
        "Salda\u00f1a"
    ],
    "wof:name":"Saldana",
    "wof:placetype":"locality"
},
  "geometry": {"coordinates":[-104.29513,20.65464],"type":"Point"}
}