{
  "type": "Feature",
  "properties": {
    "gn:admin1_code":"21",
    "gn:admin2_code":"59.0",
    "gn:asciiname":"Huaxocotepec",
    "gn:country_code":"MX",
    "gn:dem":1139,
    "gn:feature_class":"P",
    "gn:feature_code":"PPL",
    "gn:name":"Huaxocotepec",
    "gn:population":9,
    "gn:timezone":"America/Mexico_City",
    "iso:country":"MX",
    "wof:name":"Huaxocotepec",
    "wof:placetype":"locality",
    "wof:population":9
},
  "geometry": {"coordinates":[-98.24637,18.21687],"type":"Point"}
}