{
  "type": "Feature",
  "properties": {
    "gn:admin1_code":"28",
    "gn:admin2_code":"43.0",
    "gn:asciiname":"Los Dos Amigos",
    "gn:country_code":"MX",
    "gn:dem":67,
    "gn:feature_class":"P",
    "gn:feature_code":"PPL",
    "gn:name":"Los Dos Amigos",
    "gn:population":5,
    "gn:timezone":"America/Monterrey",
    "iso:country":"MX",
    "wof:name":"Los Dos Amigos",
    "wof:placetype":"locality",
    "wof:population":5
},
  "geometry": {"coordinates":[-98.96028,22.85889],"type":"Point"}
}