{
  "type": "Feature",
  "properties": {
    "gn:admin1_code":"30",
    "gn:admin2_code":"61",
    "gn:asciiname":"El Roble",
    "gn:country_code":"MX",
    "gn:dem":40,
    "gn:feature_class":"P",
    "gn:feature_code":"PPL",
    "gn:name":"El Roble",
    "gn:population":16,
    "gn:timezone":"America/Mexico_City",
    "iso:country":"MX",
    "name:ceb_x_preferred":[
        "El Roble"
    ],
    "name:fra_x_preferred":[
        "El Roble"
    ],
    "name:ita_x_preferred":[
        "El Roble"
    ],
    "name:nld_x_preferred":[
        "El Roble"
    ],
    "name:srp_x_preferred":[
        "\u0415\u043b \u0420\u043e\u0431\u043b\u0435"
    ],
    "name:swe_x_preferred":[
        "El Roble"
    ],
    "wof:name":"El Roble",
    "wof:placetype":"locality",
    "wof:population":16
},
  "geometry": {"coordinates":[-94.10361,17.72917],"type":"Point"}
}