{
  "type": "Feature",
  "properties": {
    "gn:admin1_code":"24",
    "gn:admin2_code":"41.0",
    "gn:asciiname":"Paixtzan",
    "gn:country_code":"MX",
    "gn:dem":249,
    "gn:feature_class":"P",
    "gn:feature_code":"PPL",
    "gn:name":"Paixtz\u00e1n",
    "gn:population":392,
    "gn:timezone":"America/Mexico_City",
    "iso:country":"MX",
    "name:und_x_variant":[
        "Paixtz\u00e1n"
    ],
    "wof:name":"Paixtzan",
    "wof:placetype":"locality",
    "wof:population":392
},
  "geometry": {"coordinates":[-98.92361,21.6575],"type":"Point"}
}