{
  "type": "Feature",
  "properties": {
    "gn:admin1_code":"6",
    "gn:admin2_code":"48.0",
    "gn:asciiname":"Rancho Saymi",
    "gn:country_code":"MX",
    "gn:dem":1892,
    "gn:feature_class":"P",
    "gn:feature_code":"PPL",
    "gn:name":"Rancho Saymi",
    "gn:population":6,
    "gn:timezone":"America/Chihuahua",
    "iso:country":"MX",
    "wof:name":"Rancho Saymi",
    "wof:placetype":"locality",
    "wof:population":6
},
  "geometry": {"coordinates":[-107.46306,28.98667],"type":"Point"}
}