{
  "type": "Feature",
  "properties": {
    "gn:admin1_code":"21",
    "gn:admin2_code":"64.0",
    "gn:asciiname":"Media Luna",
    "gn:country_code":"MX",
    "gn:dem":141,
    "gn:feature_class":"P",
    "gn:feature_code":"PPL",
    "gn:name":"Media Luna",
    "gn:population":9,
    "gn:timezone":"America/Mexico_City",
    "iso:country":"MX",
    "name:ina_x_preferred":[
        "Media Luna"
    ],
    "name:por_x_preferred":[
        "Media Luna"
    ],
    "name:spa_x_preferred":[
        "Media Luna"
    ],
    "wof:name":"Media Luna",
    "wof:placetype":"locality",
    "wof:population":9
},
  "geometry": {"coordinates":[-97.72295,20.59551],"type":"Point"}
}