{
  "type": "Feature",
  "properties": {
    "gn:admin1_code":"6.0",
    "gn:admin2_code":"65.0",
    "gn:asciiname":"Onoconapuchi",
    "gn:country_code":"MX",
    "gn:dem":1407,
    "gn:feature_class":"P",
    "gn:feature_code":"PPL",
    "gn:name":"Onoconapuchi",
    "gn:population":0,
    "gn:timezone":"America/Chihuahua",
    "iso:country":"MX",
    "name:spa_x_preferred":[
        "Onoconapuchi"
    ],
    "wof:name":"Onoconapuchi",
    "wof:placetype":"locality"
},
  "geometry": {"coordinates":[-107.85701,27.34800000000001],"type":"Point"}
}