{
  "type": "Feature",
  "properties": {
    "gn:admin1_code":"18",
    "gn:admin2_code":"11",
    "gn:asciiname":"La Encinera",
    "gn:country_code":"MX",
    "gn:dem":202,
    "gn:feature_class":"P",
    "gn:feature_code":"PPL",
    "gn:name":"La Encinera",
    "gn:population":30,
    "gn:timezone":"America/Mazatlan",
    "iso:country":"MX",
    "wof:name":"La Encinera",
    "wof:placetype":"locality",
    "wof:population":30
},
  "geometry": {"coordinates":[-104.92917,22.03056],"type":"Point"}
}