{
  "type": "Feature",
  "properties": {
    "gn:admin1_code":"21",
    "gn:admin2_code":"145.0",
    "gn:asciiname":"El Carpintero",
    "gn:country_code":"MX",
    "gn:dem":1107,
    "gn:feature_class":"P",
    "gn:feature_code":"PPL",
    "gn:name":"El Carpintero",
    "gn:population":169,
    "gn:timezone":"America/Mexico_City",
    "iso:country":"MX",
    "wof:name":"El Carpintero",
    "wof:placetype":"locality",
    "wof:population":169
},
  "geometry": {"coordinates":[-96.87687,18.26131],"type":"Point"}
}