{
  "type": "Feature",
  "properties": {
    "gn:admin1_code":"20",
    "gn:admin2_code":"461",
    "gn:asciiname":"Rancho el Varejonal",
    "gn:country_code":"MX",
    "gn:dem":1785,
    "gn:feature_class":"P",
    "gn:feature_code":"PPL",
    "gn:name":"Rancho el Varejonal",
    "gn:population":10,
    "gn:timezone":"America/Mexico_City",
    "iso:country":"MX",
    "wof:name":"Rancho el Varejonal",
    "wof:placetype":"locality",
    "wof:population":10
},
  "geometry": {"coordinates":[-98.07666999999999,17.44222],"type":"Point"}
}