{
  "type": "Feature",
  "properties": {
    "gn:admin1_code":"25",
    "gn:admin2_code":"7.0",
    "gn:asciiname":"San Juanito",
    "gn:country_code":"MX",
    "gn:dem":157,
    "gn:feature_class":"P",
    "gn:feature_code":"PPL",
    "gn:name":"San Juanito",
    "gn:population":6,
    "gn:timezone":"America/Mazatlan",
    "iso:country":"MX",
    "wof:name":"San Juanito",
    "wof:placetype":"locality",
    "wof:population":6
},
  "geometry": {"coordinates":[-108.48536,26.64099],"type":"Point"}
}