{
  "type": "Feature",
  "properties": {
    "gn:admin1_code":"13",
    "gn:admin2_code":"46.0",
    "gn:asciiname":"Palma Sola",
    "gn:country_code":"MX",
    "gn:dem":191,
    "gn:feature_class":"P",
    "gn:feature_code":"PPL",
    "gn:name":"Palma Sola",
    "gn:population":247,
    "gn:timezone":"America/Mexico_City",
    "iso:country":"MX",
    "wof:name":"Palma Sola",
    "wof:placetype":"locality",
    "wof:population":247
},
  "geometry": {"coordinates":[-98.64082999999999,21.34528],"type":"Point"}
}