{
  "type": "Feature",
  "properties": {
    "gn:admin1_code":"5",
    "gn:admin2_code":"38.0",
    "gn:asciiname":"Adolfo Lopez Mateos",
    "gn:country_code":"MX",
    "gn:dem":2160,
    "gn:feature_class":"P",
    "gn:feature_code":"PPL",
    "gn:name":"Adolfo L\u00f3pez Mateos",
    "gn:population":0,
    "gn:timezone":"America/Mexico_City",
    "iso:country":"MX",
    "name:spa_x_preferred":[
        "Adolfo L\u00f3pez Mateos"
    ],
    "name:spa_x_variant":[
        "L\u00f3pez Mateos"
    ],
    "wof:name":"Adolfo Lopez Mateos",
    "wof:placetype":"locality"
},
  "geometry": {"coordinates":[-92.41435,16.75119],"type":"Point"}
}