{
  "type": "Feature",
  "properties": {
    "gn:admin1_code":"3",
    "gn:admin2_code":"1.0",
    "gn:asciiname":"San Jose de los Arce",
    "gn:cc2":"MX",
    "gn:country_code":"MX",
    "gn:dem":542,
    "gn:feature_class":"P",
    "gn:feature_code":"PPL",
    "gn:name":"San Jos\u00e9 de los Arce",
    "gn:population":0,
    "gn:timezone":"America/Mazatlan",
    "iso:country":"MX",
    "name:und_x_variant":[
        "San Jos\u00e9",
        "San Jos\u00e9 de los Arce"
    ],
    "wof:name":"San Jose de los Arce",
    "wof:placetype":"locality"
},
  "geometry": {"coordinates":[-112.15000000000001,26.38333],"type":"Point"}
}