{
  "type": "Feature",
  "properties": {
    "gn:admin1_code":"13",
    "gn:admin2_code":"4.0",
    "gn:asciiname":"El Palizar",
    "gn:country_code":"MX",
    "gn:dem":2218,
    "gn:feature_class":"P",
    "gn:feature_code":"PPL",
    "gn:name":"El Palizar",
    "gn:population":252,
    "gn:timezone":"America/Mexico_City",
    "iso:country":"MX",
    "wof:name":"El Palizar",
    "wof:placetype":"locality",
    "wof:population":252
},
  "geometry": {"coordinates":[-98.38861,20.37444],"type":"Point"}
}