{
  "type": "Feature",
  "properties": {
    "gn:admin1_code":"19.0",
    "gn:admin2_code":"32.0",
    "gn:asciiname":"El Brasil",
    "gn:country_code":"MX",
    "gn:dem":346,
    "gn:feature_class":"P",
    "gn:feature_code":"PPL",
    "gn:name":"El Brasil",
    "gn:population":0,
    "gn:timezone":"America/Monterrey",
    "iso:country":"MX",
    "name:spa_x_preferred":[
        "El Brasil"
    ],
    "wof:name":"El Brasil",
    "wof:placetype":"locality"
},
  "geometry": {"coordinates":[-100.50705000000001,26.93521],"type":"Point"}
}