{
  "type": "Feature",
  "properties": {
    "gn:admin1_code":"5",
    "gn:admin2_code":"20.0",
    "gn:asciiname":"Michoacan",
    "gn:country_code":"MX",
    "gn:dem":663,
    "gn:feature_class":"P",
    "gn:feature_code":"PPL",
    "gn:name":"Michoac\u00e1n",
    "gn:population":4,
    "gn:timezone":"America/Mexico_City",
    "iso:country":"MX",
    "name:und_x_variant":[
        "Michoac\u00e1n"
    ],
    "wof:name":"Michoacan",
    "wof:placetype":"locality",
    "wof:population":4
},
  "geometry": {"coordinates":[-92.97444,15.9325],"type":"Point"}
}