{
  "type": "Feature",
  "properties": {
    "gn:admin1_code":"16.0",
    "gn:admin2_code":"99.0",
    "gn:asciiname":"La Minita",
    "gn:country_code":"MX",
    "gn:dem":784,
    "gn:feature_class":"P",
    "gn:feature_code":"PPL",
    "gn:name":"La Minita",
    "gn:population":0,
    "gn:timezone":"America/Mexico_City",
    "iso:country":"MX",
    "name:spa_x_preferred":[
        "La Minita"
    ],
    "name:spa_x_variant":[
        "El Salitrillo"
    ],
    "wof:name":"La Minita",
    "wof:placetype":"locality"
},
  "geometry": {"coordinates":[-100.59554,19.32736],"type":"Point"}
}