{
  "type": "Feature",
  "properties": {
    "gn:admin1_code":"17",
    "gn:admin2_code":"29.0",
    "gn:asciiname":"Ampliacion Lomas del Real",
    "gn:country_code":"MX",
    "gn:dem":1318,
    "gn:feature_class":"P",
    "gn:feature_code":"PPL",
    "gn:name":"Ampliaci\u00f3n Lomas del Real",
    "gn:population":59,
    "gn:timezone":"America/Mexico_City",
    "iso:country":"MX",
    "name:und_x_variant":[
        "Ampliaci\u00f3n Lomas del Real"
    ],
    "wof:name":"Ampliacion Lomas del Real",
    "wof:placetype":"locality",
    "wof:population":59
},
  "geometry": {"coordinates":[-99.05833,18.86139],"type":"Point"}
}