{
  "type": "Feature",
  "properties": {
    "gn:admin1_code":"12.0",
    "gn:admin2_code":"34.0",
    "gn:asciiname":"El Chautle",
    "gn:country_code":"MX",
    "gn:dem":1142,
    "gn:feature_class":"P",
    "gn:feature_code":"PPL",
    "gn:name":"El Chautle",
    "gn:population":0,
    "gn:timezone":"America/Mexico_City",
    "iso:country":"MX",
    "name:spa_x_preferred":[
        "El Chautle"
    ],
    "wof:name":"El Chautle",
    "wof:placetype":"locality"
},
  "geometry": {"coordinates":[-99.25099,18.19161],"type":"Point"}
}