{
  "type": "Feature",
  "properties": {
    "gn:admin1_code":"4",
    "gn:admin2_code":"3.0",
    "gn:asciiname":"El Castillo",
    "gn:country_code":"MX",
    "gn:dem":-3,
    "gn:feature_class":"P",
    "gn:feature_code":"PPL",
    "gn:name":"El Castillo",
    "gn:population":5,
    "gn:timezone":"America/Merida",
    "iso:country":"MX",
    "wof:name":"El Castillo",
    "wof:placetype":"locality",
    "wof:population":5
},
  "geometry": {"coordinates":[-91.79361,18.19194],"type":"Point"}
}