{
  "type": "Feature",
  "properties": {
    "gn:admin1_code":"30",
    "gn:admin2_code":"184.0",
    "gn:asciiname":"Apoxquila (Los Pinos)",
    "gn:country_code":"MX",
    "gn:dem":2597,
    "gn:feature_class":"P",
    "gn:feature_code":"PPL",
    "gn:name":"Apoxquila (Los Pinos)",
    "gn:population":148,
    "gn:timezone":"America/Mexico_City",
    "iso:country":"MX",
    "wof:name":"Apoxquila (Los Pinos)",
    "wof:placetype":"locality",
    "wof:population":148
},
  "geometry": {"coordinates":[-97.12222,18.58028],"type":"Point"}
}