{
  "type": "Feature",
  "properties": {
    "gn:admin1_code":"7.0",
    "gn:admin2_code":"4.0",
    "gn:asciiname":"El Astillero",
    "gn:country_code":"MX",
    "gn:dem":2106,
    "gn:feature_class":"P",
    "gn:feature_code":"PPL",
    "gn:name":"El Astillero",
    "gn:population":0,
    "gn:timezone":"America/Monterrey",
    "iso:country":"MX",
    "name:und_x_variant":[
        "Astillero",
        "El Astillero"
    ],
    "wof:name":"El Astillero",
    "wof:placetype":"locality"
},
  "geometry": {"coordinates":[-100.68079,25.46115],"type":"Point"}
}