{
  "type": "Feature",
  "properties": {
    "gn:admin1_code":"22",
    "gn:admin2_code":"7.0",
    "gn:asciiname":"Rancho el Gallo Giro",
    "gn:country_code":"MX",
    "gn:dem":2009,
    "gn:feature_class":"P",
    "gn:feature_code":"PPL",
    "gn:name":"Rancho el Gallo Giro",
    "gn:population":7,
    "gn:timezone":"America/Mexico_City",
    "iso:country":"MX",
    "wof:name":"Rancho el Gallo Giro",
    "wof:placetype":"locality",
    "wof:population":7
},
  "geometry": {"coordinates":[-99.86750000000001,20.69528],"type":"Point"}
}