{
  "type": "Feature",
  "properties": {
    "gn:admin1_code":"11.0",
    "gn:admin2_code":"37.0",
    "gn:asciiname":"Loza de Barrera",
    "gn:country_code":"MX",
    "gn:dem":1785,
    "gn:feature_class":"P",
    "gn:feature_code":"PPL",
    "gn:name":"Loza de Barrera",
    "gn:population":0,
    "gn:timezone":"America/Mexico_City",
    "iso:country":"MX",
    "name:spa_x_preferred":[
        "Loza de Barrera"
    ],
    "wof:name":"Loza de Barrera",
    "wof:placetype":"locality"
},
  "geometry": {"coordinates":[-101.52972,20.98461],"type":"Point"}
}