{
  "type": "Feature",
  "properties": {
    "gn:admin1_code":"27",
    "gn:admin2_code":"5.0",
    "gn:asciiname":"Uspi",
    "gn:country_code":"MX",
    "gn:dem":8,
    "gn:feature_class":"P",
    "gn:feature_code":"PPL",
    "gn:name":"Usp\u00ed",
    "gn:population":708,
    "gn:timezone":"America/Mexico_City",
    "iso:country":"MX",
    "name:und_x_variant":[
        "Usp\u00ed"
    ],
    "wof:name":"Uspi",
    "wof:placetype":"locality",
    "wof:population":708
},
  "geometry": {"coordinates":[-93.12361,18.24972],"type":"Point"}
}