{
  "type": "Feature",
  "properties": {
    "gn:admin1_code":"16.0",
    "gn:admin2_code":"52.0",
    "gn:asciiname":"El Infiernillo",
    "gn:country_code":"MX",
    "gn:dem":67,
    "gn:feature_class":"P",
    "gn:feature_code":"PPL",
    "gn:name":"El Infiernillo",
    "gn:population":0,
    "gn:timezone":"America/Mexico_City",
    "iso:country":"MX",
    "name:spa_x_preferred":[
        "El Infiernillo"
    ],
    "name:und_x_variant":[
        "Infiernillo"
    ],
    "wof:name":"El Infiernillo",
    "wof:placetype":"locality"
},
  "geometry": {"coordinates":[-102.16687,18.14519],"type":"Point"}
}