{
  "type": "Feature",
  "properties": {
    "gn:admin1_code":"32.0",
    "gn:admin2_code":"17.0",
    "gn:asciiname":"Coyote",
    "gn:country_code":"MX",
    "gn:dem":2344,
    "gn:feature_class":"P",
    "gn:feature_code":"PPL",
    "gn:name":"Coyote",
    "gn:population":0,
    "gn:timezone":"America/Mexico_City",
    "iso:country":"MX",
    "wof:name":"Coyote",
    "wof:placetype":"locality"
},
  "geometry": {"coordinates":[-102.53333000000001,22.56667],"type":"Point"}
}