{
  "type": "Feature",
  "properties": {
    "gn:admin1_code":"7.0",
    "gn:admin2_code":"20.0",
    "gn:asciiname":"Las Moras",
    "gn:country_code":"MX",
    "gn:dem":1317,
    "gn:feature_class":"P",
    "gn:feature_code":"PPL",
    "gn:name":"Las Moras",
    "gn:population":0,
    "gn:timezone":"America/Monterrey",
    "iso:country":"MX",
    "name:spa_x_preferred":[
        "Las Moras"
    ],
    "wof:name":"Las Moras",
    "wof:placetype":"locality"
},
  "geometry": {"coordinates":[-102.45614999999999,28.78886],"type":"Point"}
}