{
  "type": "Feature",
  "properties": {
    "gn:admin1_code":"30.0",
    "gn:admin2_code":"155.0",
    "gn:asciiname":"Ixtle Blanco",
    "gn:country_code":"MX",
    "gn:dem":172,
    "gn:feature_class":"P",
    "gn:feature_code":"PPL",
    "gn:name":"Ixtle Blanco",
    "gn:population":388,
    "gn:timezone":"America/Mexico_City",
    "iso:country":"MX",
    "name:spa_x_preferred":[
        "Ixtle Blanco"
    ],
    "wof:name":"Ixtle Blanco",
    "wof:placetype":"locality",
    "wof:population":388
},
  "geometry": {"coordinates":[-98.27083,21.325],"type":"Point"}
}