{
  "type": "Feature",
  "properties": {
    "gn:admin1_code":"7",
    "gn:admin2_code":"36.0",
    "gn:asciiname":"Tejaban de la Rosita",
    "gn:country_code":"MX",
    "gn:dem":1170,
    "gn:feature_class":"P",
    "gn:feature_code":"PPL",
    "gn:name":"Tejab\u00e1n de la Rosita",
    "gn:population":576,
    "gn:timezone":"America/Monterrey",
    "iso:country":"MX",
    "name:und_x_variant":[
        "Tejab\u00e1n de la Rosita"
    ],
    "wof:name":"Tejaban de la Rosita",
    "wof:placetype":"locality",
    "wof:population":576
},
  "geometry": {"coordinates":[-103.20305999999999,25.27667000000001],"type":"Point"}
}