{
  "type": "Feature",
  "properties": {
    "gn:admin1_code":"26.0",
    "gn:admin2_code":"30.0",
    "gn:asciiname":"El Parian",
    "gn:cc2":"MX",
    "gn:country_code":"MX",
    "gn:dem":232,
    "gn:feature_class":"P",
    "gn:feature_code":"PPL",
    "gn:name":"El Pari\u00e1n",
    "gn:population":0,
    "gn:timezone":"America/Hermosillo",
    "iso:country":"MX",
    "name:und_x_variant":[
        "Pari\u00e1n",
        "El Pari\u00e1n"
    ],
    "wof:name":"El Parian",
    "wof:placetype":"locality"
},
  "geometry": {"coordinates":[-111.26667,29.21667],"type":"Point"}
}