{
  "type": "Feature",
  "properties": {
    "gn:admin1_code":"28",
    "gn:admin2_code":"20.0",
    "gn:asciiname":"Las Puentes",
    "gn:country_code":"MX",
    "gn:dem":390,
    "gn:feature_class":"P",
    "gn:feature_code":"PPL",
    "gn:name":"Las Puentes",
    "gn:population":0,
    "gn:timezone":"America/Monterrey",
    "iso:country":"MX",
    "name:spa_x_preferred":[
        "Las Fuentes"
    ],
    "name:spa_x_variant":[
        "Las Puentes"
    ],
    "name:und_x_variant":[
        "Los Puentes"
    ],
    "wof:name":"Las Puentes",
    "wof:placetype":"locality"
},
  "geometry": {"coordinates":[-99.52321000000001,24.55943],"type":"Point"}
}