{
  "type": "Feature",
  "properties": {
    "gn:admin1_code":"13.0",
    "gn:asciiname":"La Codorniz",
    "gn:country_code":"MX",
    "gn:dem":1867,
    "gn:feature_class":"P",
    "gn:feature_code":"PPL",
    "gn:name":"La Codorniz",
    "gn:population":0,
    "gn:timezone":"America/Mexico_City",
    "iso:country":"MX",
    "name:spa_x_preferred":[
        "La Codorniz"
    ],
    "wof:name":"La Codorniz",
    "wof:placetype":"locality"
},
  "geometry": {"coordinates":[-99.74832000000001,20.49037],"type":"Point"}
}