{
  "type": "Feature",
  "properties": {
    "gn:admin1_code":"4",
    "gn:admin2_code":"4.0",
    "gn:asciiname":"San Dimas",
    "gn:country_code":"MX",
    "gn:dem":12,
    "gn:feature_class":"P",
    "gn:feature_code":"PPL",
    "gn:name":"San Dimas",
    "gn:population":0,
    "gn:timezone":"America/Merida",
    "iso:country":"MX",
    "name:ceb_x_preferred":[
        "San Dimas"
    ],
    "name:deu_x_preferred":[
        "San Dimas"
    ],
    "name:hun_x_preferred":[
        "San Dimas"
    ],
    "name:ita_x_preferred":[
        "San Dimas"
    ],
    "name:pol_x_preferred":[
        "San Dimas"
    ],
    "name:por_x_preferred":[
        "San Dimas"
    ],
    "name:sco_x_preferred":[
        "San Dimas"
    ],
    "name:srp_x_preferred":[
        "\u0421\u0430\u043d \u0414\u0438\u043c\u0430\u0441"
    ],
    "name:swe_x_preferred":[
        "San Dimas"
    ],
    "wof:name":"San Dimas",
    "wof:placetype":"locality"
},
  "geometry": {"coordinates":[-90.41667,19.31667],"type":"Point"}
}