{
  "type": "Feature",
  "properties": {
    "gn:admin1_code":"16.0",
    "gn:asciiname":"Epunguio el Viejo",
    "gn:country_code":"MX",
    "gn:dem":2391,
    "gn:feature_class":"P",
    "gn:feature_code":"PPL",
    "gn:name":"Epunguio el Viejo",
    "gn:population":0,
    "gn:timezone":"America/Mexico_City",
    "iso:country":"MX",
    "name:spa_x_preferred":[
        "Epunguio el Viejo"
    ],
    "wof:name":"Epunguio el Viejo",
    "wof:placetype":"locality"
},
  "geometry": {"coordinates":[-100.40783,19.71279],"type":"Point"}
}