{
  "type": "Feature",
  "properties": {
    "gn:admin1_code":"21",
    "gn:admin2_code":"27.0",
    "gn:asciiname":"Los Membrillos",
    "gn:country_code":"MX",
    "gn:dem":1993,
    "gn:feature_class":"P",
    "gn:feature_code":"PPL",
    "gn:name":"Los Membrillos",
    "gn:population":53,
    "gn:timezone":"America/Mexico_City",
    "iso:country":"MX",
    "wof:name":"Los Membrillos",
    "wof:placetype":"locality",
    "wof:population":53
},
  "geometry": {"coordinates":[-97.51134,18.16187],"type":"Point"}
}