{
  "type": "Feature",
  "properties": {
    "gn:admin1_code":"23",
    "gn:admin2_code":"9",
    "gn:asciiname":"El Pequeno Paraiso",
    "gn:country_code":"MX",
    "gn:dem":20,
    "gn:feature_class":"P",
    "gn:feature_code":"PPL",
    "gn:name":"El Peque\u00f1o Para\u00edso",
    "gn:population":10,
    "gn:timezone":"America/Cancun",
    "iso:country":"MX",
    "name:und_x_variant":[
        "El Peque\u00f1o Para\u00edso"
    ],
    "wof:name":"El Pequeno Paraiso",
    "wof:placetype":"locality",
    "wof:population":10
},
  "geometry": {"coordinates":[-87.5261,20.3028],"type":"Point"}
}