{
  "type": "Feature",
  "properties": {
    "gn:admin1_code":"18",
    "gn:admin2_code":"9.0",
    "gn:asciiname":"La Tristeza",
    "gn:country_code":"MX",
    "gn:dem":1866,
    "gn:feature_class":"P",
    "gn:feature_code":"PPL",
    "gn:name":"La Tristeza",
    "gn:population":7,
    "gn:timezone":"America/Mexico_City",
    "iso:country":"MX",
    "wof:name":"La Tristeza",
    "wof:placetype":"locality",
    "wof:population":7
},
  "geometry": {"coordinates":[-104.30222000000001,22.29722000000001],"type":"Point"}
}