{
  "type": "Feature",
  "properties": {
    "gn:admin1_code":"22",
    "gn:admin2_code":"2",
    "gn:asciiname":"El Pilon",
    "gn:country_code":"MX",
    "gn:dem":1077,
    "gn:feature_class":"P",
    "gn:feature_code":"PPL",
    "gn:name":"El Pil\u00f3n",
    "gn:population":26,
    "gn:timezone":"America/Mexico_City",
    "iso:country":"MX",
    "name:und_x_variant":[
        "El Pil\u00f3n"
    ],
    "wof:name":"El Pilon",
    "wof:placetype":"locality",
    "wof:population":26
},
  "geometry": {"coordinates":[-99.60861,21.28306],"type":"Point"}
}