{
  "type": "Feature",
  "properties": {
    "gn:admin1_code":"27",
    "gn:admin2_code":"11.0",
    "gn:asciiname":"Isla Helva de Guadalupe",
    "gn:country_code":"MX",
    "gn:dem":6,
    "gn:feature_class":"P",
    "gn:feature_code":"PPL",
    "gn:name":"Isla Helva de Guadalupe",
    "gn:population":0,
    "gn:timezone":"America/Mexico_City",
    "iso:country":"MX",
    "name:spa_x_preferred":[
        "Selva de Guadalupe"
    ],
    "name:spa_x_variant":[
        "Isla Helva de Guadalupe"
    ],
    "wof:name":"Isla Helva de Guadalupe",
    "wof:placetype":"locality"
},
  "geometry": {"coordinates":[-91.9361,17.86722],"type":"Point"}
}