{
  "type": "Feature",
  "properties": {
    "gn:admin1_code":"31",
    "gn:admin2_code":"19.0",
    "gn:asciiname":"Cholul",
    "gn:country_code":"MX",
    "gn:dem":24,
    "gn:feature_class":"P",
    "gn:feature_code":"PPL",
    "gn:name":"Cholul",
    "gn:population":0,
    "gn:timezone":"America/Merida",
    "iso:country":"MX",
    "name:spa_x_preferred":[
        "Cholul"
    ],
    "name:und_x_variant":[
        "Chuluco",
        "Chuluc"
    ],
    "wof:name":"Cholul",
    "wof:placetype":"locality"
},
  "geometry": {"coordinates":[-87.79446999999998,20.77446],"type":"Point"}
}