{
  "type": "Feature",
  "properties": {
    "gn:admin1_code":"25",
    "gn:admin2_code":"7",
    "gn:asciiname":"Puerto del Reparo",
    "gn:country_code":"MX",
    "gn:dem":786,
    "gn:feature_class":"P",
    "gn:feature_code":"PPL",
    "gn:name":"Puerto del Reparo",
    "gn:population":20,
    "gn:timezone":"America/Mazatlan",
    "iso:country":"MX",
    "wof:name":"Puerto del Reparo",
    "wof:placetype":"locality",
    "wof:population":20
},
  "geometry": {"coordinates":[-108.06498000000001,26.46132],"type":"Point"}
}