{
  "type": "Feature",
  "properties": {
    "gn:admin1_code":"13",
    "gn:admin2_code":"29.0",
    "gn:asciiname":"Rancho Taxanhgo",
    "gn:country_code":"MX",
    "gn:dem":2146,
    "gn:feature_class":"P",
    "gn:feature_code":"PPL",
    "gn:name":"Rancho Taxanhgo",
    "gn:population":0,
    "gn:timezone":"America/Mexico_City",
    "iso:country":"MX",
    "name:spa_x_preferred":[
        "Rancho Taxanhgo"
    ],
    "wof:name":"Rancho Taxanhgo",
    "wof:placetype":"locality"
},
  "geometry": {"coordinates":[-99.60666999999999,20.3966],"type":"Point"}
}