{
  "type": "Feature",
  "properties": {
    "gn:admin1_code":"26.0",
    "gn:admin2_code":"62.0",
    "gn:asciiname":"Los Baules",
    "gn:country_code":"MX",
    "gn:dem":412,
    "gn:feature_class":"P",
    "gn:feature_code":"PPL",
    "gn:name":"Los Ba\u00fales",
    "gn:population":0,
    "gn:timezone":"America/Hermosillo",
    "iso:country":"MX",
    "name:spa_x_preferred":[
        "Los Ba\u00fales"
    ],
    "wof:name":"Los Baules",
    "wof:placetype":"locality"
},
  "geometry": {"coordinates":[-109.7811,28.4768],"type":"Point"}
}