{
  "type": "Feature",
  "properties": {
    "gn:admin1_code":"6.0",
    "gn:admin2_code":"15.0",
    "gn:asciiname":"La Granja",
    "gn:country_code":"MX",
    "gn:dem":1619,
    "gn:feature_class":"P",
    "gn:feature_code":"PPL",
    "gn:name":"La Granja",
    "gn:population":0,
    "gn:timezone":"America/Chihuahua",
    "iso:country":"MX",
    "name:und_x_variant":[
        "Rancho La Granja",
        "La Granja"
    ],
    "wof:name":"La Granja",
    "wof:placetype":"locality"
},
  "geometry": {"coordinates":[-105.21607,29.80711],"type":"Point"}
}