{
  "type": "Feature",
  "properties": {
    "gn:admin1_code":"28",
    "gn:admin2_code":"4.0",
    "gn:asciiname":"Tranquitas",
    "gn:country_code":"MX",
    "gn:dem":145,
    "gn:feature_class":"P",
    "gn:feature_code":"PPL",
    "gn:name":"Tranquitas",
    "gn:population":0,
    "gn:timezone":"America/Monterrey",
    "iso:country":"MX",
    "name:spa_x_preferred":[
        "Tranquitas"
    ],
    "wof:name":"Tranquitas",
    "wof:placetype":"locality"
},
  "geometry": {"coordinates":[-99.10398000000001,22.71947],"type":"Point"}
}