{
  "type": "Feature",
  "properties": {
    "gn:admin1_code":"7",
    "gn:admin2_code":"5.0",
    "gn:asciiname":"Valladares",
    "gn:country_code":"MX",
    "gn:dem":384,
    "gn:feature_class":"P",
    "gn:feature_code":"PPL",
    "gn:name":"Valladares",
    "gn:population":0,
    "gn:timezone":"America/Monterrey",
    "iso:country":"MX",
    "name:spa_x_preferred":[
        "Valladares"
    ],
    "wof:name":"Valladares",
    "wof:placetype":"locality"
},
  "geometry": {"coordinates":[-100.60064,26.87553],"type":"Point"}
}