{
  "type": "Feature",
  "properties": {
    "gn:admin1_code":"16.0",
    "gn:admin2_code":"10.0",
    "gn:asciiname":"El Puertecito",
    "gn:country_code":"MX",
    "gn:dem":470,
    "gn:feature_class":"P",
    "gn:feature_code":"PPL",
    "gn:name":"El Puertecito",
    "gn:population":0,
    "gn:timezone":"America/Mexico_City",
    "iso:country":"MX",
    "name:spa_x_preferred":[
        "El Puertecito"
    ],
    "name:spa_x_variant":[
        "La Quebradora"
    ],
    "wof:name":"El Puertecito",
    "wof:placetype":"locality"
},
  "geometry": {"coordinates":[-102.06852000000001,18.47642],"type":"Point"}
}