{
  "type": "Feature",
  "properties": {
    "gn:admin1_code":"11",
    "gn:admin2_code":"19.0",
    "gn:asciiname":"El Cerrito (Las Palmas)",
    "gn:country_code":"MX",
    "gn:dem":1965,
    "gn:feature_class":"P",
    "gn:feature_code":"PPL",
    "gn:name":"El Cerrito (Las Palmas)",
    "gn:population":65,
    "gn:timezone":"America/Mexico_City",
    "iso:country":"MX",
    "wof:name":"El Cerrito (Las Palmas)",
    "wof:placetype":"locality",
    "wof:population":65
},
  "geometry": {"coordinates":[-100.51278000000001,20.16556],"type":"Point"}
}