{
  "type": "Feature",
  "properties": {
    "gn:admin1_code":"0.0",
    "gn:asciiname":"Las Amarillas",
    "gn:country_code":"MX",
    "gn:dem":2205,
    "gn:feature_class":"P",
    "gn:feature_code":"PPL",
    "gn:name":"Las Amarillas",
    "gn:population":0,
    "gn:timezone":"America/Mexico_City",
    "iso:country":"MX",
    "name:spa_x_preferred":[
        "Las Amarillas"
    ],
    "wof:name":"Las Amarillas",
    "wof:placetype":"locality"
},
  "geometry": {"coordinates":[-101.38661,22.2655],"type":"Point"}
}