{
  "type": "Feature",
  "properties": {
    "gn:admin1_code":"32",
    "gn:admin2_code":"38.0",
    "gn:asciiname":"El Terrero",
    "gn:country_code":"MX",
    "gn:dem":2272,
    "gn:feature_class":"P",
    "gn:feature_code":"PPL",
    "gn:name":"El Terrero",
    "gn:population":62,
    "gn:timezone":"America/Mexico_City",
    "iso:country":"MX",
    "wof:name":"El Terrero",
    "wof:placetype":"locality",
    "wof:population":62
},
  "geometry": {"coordinates":[-101.59583000000001,22.39722],"type":"Point"}
}