{
  "type": "Feature",
  "properties": {
    "gn:admin1_code":"5.0",
    "gn:asciiname":"Los Organos",
    "gn:country_code":"MX",
    "gn:dem":540,
    "gn:feature_class":"P",
    "gn:feature_code":"PPL",
    "gn:name":"Los \u00d3rganos",
    "gn:population":0,
    "gn:timezone":"America/Mexico_City",
    "iso:country":"MX",
    "name:spa_x_preferred":[
        "Los \u00d3rganos"
    ],
    "wof:name":"Los Organos",
    "wof:placetype":"locality"
},
  "geometry": {"coordinates":[-93.64541,16.60093],"type":"Point"}
}