{
  "type": "Feature",
  "properties": {
    "gn:admin1_code":"20",
    "gn:admin2_code":"18.0",
    "gn:asciiname":"El Enebro",
    "gn:country_code":"MX",
    "gn:dem":2051,
    "gn:feature_class":"P",
    "gn:feature_code":"PPL",
    "gn:name":"El Enebro",
    "gn:population":0,
    "gn:timezone":"America/Mexico_City",
    "iso:country":"MX",
    "name:spa_x_preferred":[
        "Enebro"
    ],
    "name:spa_x_variant":[
        "El Enebro"
    ],
    "wof:name":"El Enebro",
    "wof:placetype":"locality"
},
  "geometry": {"coordinates":[-97.43066,17.99662],"type":"Point"}
}