{
  "type": "Feature",
  "properties": {
    "gn:admin1_code":"20",
    "gn:admin2_code":"16.0",
    "gn:asciiname":"Rio Alumbrado",
    "gn:country_code":"MX",
    "gn:dem":1225,
    "gn:feature_class":"P",
    "gn:feature_code":"PPL",
    "gn:name":"R\u00edo Alumbrado",
    "gn:population":220,
    "gn:timezone":"America/Mexico_City",
    "iso:country":"MX",
    "name:spa_x_preferred":[
        "R\u00edo Alumbrado"
    ],
    "wof:name":"Rio Alumbrado",
    "wof:placetype":"locality",
    "wof:population":220
},
  "geometry": {"coordinates":[-98.19889000000001,17.19472],"type":"Point"}
}