{
  "type": "Feature",
  "properties": {
    "gn:admin1_code":"14",
    "gn:admin2_code":"61",
    "gn:asciiname":"La Guacamaya",
    "gn:country_code":"MX",
    "gn:dem":2267,
    "gn:feature_class":"P",
    "gn:feature_code":"PPL",
    "gn:name":"La Guacamaya",
    "gn:population":19,
    "gn:timezone":"America/Mexico_City",
    "iso:country":"MX",
    "wof:name":"La Guacamaya",
    "wof:placetype":"locality",
    "wof:population":19
},
  "geometry": {"coordinates":[-103.9325,22.09861],"type":"Point"}
}