{
  "type": "Feature",
  "properties": {
    "gn:admin1_code":"14",
    "gn:admin2_code":"19",
    "gn:asciiname":"La Roblera",
    "gn:country_code":"MX",
    "gn:dem":1415,
    "gn:feature_class":"P",
    "gn:feature_code":"PPL",
    "gn:name":"La Roblera",
    "gn:population":34,
    "gn:timezone":"America/Mexico_City",
    "iso:country":"MX",
    "wof:name":"La Roblera",
    "wof:placetype":"locality",
    "wof:population":34
},
  "geometry": {"coordinates":[-103.96111000000001,21.8275],"type":"Point"}
}