{
  "type": "Feature",
  "properties": {
    "gn:admin1_code":"30",
    "gn:admin2_code":"177.0",
    "gn:asciiname":"Potrero de Garcia",
    "gn:country_code":"MX",
    "gn:dem":2103,
    "gn:feature_class":"P",
    "gn:feature_code":"PPL",
    "gn:name":"Potrero de Garc\u00eda",
    "gn:population":151,
    "gn:timezone":"America/Mexico_City",
    "iso:country":"MX",
    "wof:name":"Potrero de Garcia",
    "wof:placetype":"locality",
    "wof:population":151
},
  "geometry": {"coordinates":[-97.02778000000001,19.63222],"type":"Point"}
}