{
  "type": "Feature",
  "properties": {
    "gn:admin1_code":"19.0",
    "gn:asciiname":"Los Robalos",
    "gn:country_code":"MX",
    "gn:dem":429,
    "gn:feature_class":"P",
    "gn:feature_code":"PPL",
    "gn:name":"Los Robalos",
    "gn:population":0,
    "gn:timezone":"America/Monterrey",
    "iso:country":"MX",
    "name:spa_x_preferred":[
        "Los Robalos"
    ],
    "wof:name":"Los Robalos",
    "wof:placetype":"locality"
},
  "geometry": {"coordinates":[-100.12486,25.97714],"type":"Point"}
}