{
  "type": "Feature",
  "properties": {
    "gn:admin1_code":"8.0",
    "gn:admin2_code":"4.0",
    "gn:asciiname":"El Huzilacate",
    "gn:country_code":"MX",
    "gn:dem":306,
    "gn:feature_class":"P",
    "gn:feature_code":"PPL",
    "gn:name":"El Huzilacate",
    "gn:population":0,
    "gn:timezone":"America/Mexico_City",
    "iso:country":"MX",
    "name:spa_x_preferred":[
        "El Huzilacate"
    ],
    "name:und_x_variant":[
        "El Huizalacate"
    ],
    "wof:name":"El Huzilacate",
    "wof:placetype":"locality"
},
  "geometry": {"coordinates":[-103.8154,19.17532000000001],"type":"Point"}
}