{
  "type": "Feature",
  "properties": {
    "gn:admin1_code":"19",
    "gn:admin2_code":"9.0",
    "gn:asciiname":"Los Sabinos",
    "gn:country_code":"MX",
    "gn:dem":254,
    "gn:feature_class":"P",
    "gn:feature_code":"PPL",
    "gn:name":"Los Sabinos",
    "gn:population":0,
    "gn:timezone":"America/Monterrey",
    "iso:country":"MX",
    "wof:name":"Los Sabinos",
    "wof:placetype":"locality"
},
  "geometry": {"coordinates":[-99.77734,25.50345],"type":"Point"}
}