{
  "type": "Feature",
  "properties": {
    "gn:admin1_code":"10",
    "gn:admin2_code":"15.0",
    "gn:asciiname":"La Campana",
    "gn:country_code":"MX",
    "gn:dem":1466,
    "gn:feature_class":"P",
    "gn:feature_code":"PPL",
    "gn:name":"La Campana",
    "gn:population":0,
    "gn:timezone":"America/Monterrey",
    "iso:country":"MX",
    "name:spa_x_preferred":[
        "La Campana"
    ],
    "wof:name":"La Campana",
    "wof:placetype":"locality"
},
  "geometry": {"coordinates":[-104.14267,25.43218],"type":"Point"}
}