{
  "type": "Feature",
  "properties": {
    "gn:admin1_code":"20.0",
    "gn:admin2_code":"324.0",
    "gn:asciiname":"Camaronal",
    "gn:country_code":"MX",
    "gn:dem":404,
    "gn:feature_class":"P",
    "gn:feature_code":"PPL",
    "gn:name":"Camaronal",
    "gn:population":0,
    "gn:timezone":"America/Mexico_City",
    "iso:country":"MX",
    "name:spa_x_preferred":[
        "Camaronal"
    ],
    "wof:name":"Camaronal",
    "wof:placetype":"locality"
},
  "geometry": {"coordinates":[-96.49987,15.81962],"type":"Point"}
}