{
  "type": "Feature",
  "properties": {
    "iso:country":"MX",
    "name:spa_x_preferred":[
        "Zacatlan Centro"
    ],
    "qs:gn_adm0_cc":"MX",
    "qs:gn_local":3514148,
    "qs:gn_nam_loc":"Zacatlan, Zacatl\u00e1n, Puebla, MX",
    "qs:gn_namadm1":"21",
    "qs:local_max":75,
    "qs:local_sum":75,
    "qs:localhoods":1,
    "qs:name":"Zacatlan Centro",
    "qs:name_adm0":"M\u00e9xico",
    "qs:name_adm1":"Puebla",
    "qs:name_adm2":"Zacatlan",
    "qs:name_local":"Zacatl\u00e1n",
    "qs:photo_max":48,
    "qs:photo_sum":75,
    "qs:placetype":"Suburb",
    "qs:quad_count":6,
    "qs:woe_adm0":23424900,
    "qs:woe_adm1":2346284,
    "qs:woe_adm2":12601434,
    "qs:woe_lau":0,
    "qs:woe_local":151514,
    "qs:woe_ver":"7.10.0",
    "wof:lang":[
        "spa"
    ],
    "wof:name":"Zacatlan Centro",
    "wof:placetype":"neighbourhood"
},
  "geometry": {"coordinates":[-97.960729,19.933522],"type":"Point"}
}