{
  "type": "Feature",
  "properties": {
    "gn:admin1_code":"31",
    "gn:admin2_code":"62.0",
    "gn:asciiname":"San Antonio Sodzil",
    "gn:country_code":"MX",
    "gn:dem":17,
    "gn:feature_class":"P",
    "gn:feature_code":"PPL",
    "gn:name":"San Antonio Sodzil",
    "gn:population":0,
    "gn:timezone":"America/Merida",
    "iso:country":"MX",
    "name:und_x_variant":[
        "Sodzil",
        "San Antonio Sodzil",
        "San Antonio Zodil"
    ],
    "wof:name":"San Antonio Sodzil",
    "wof:placetype":"locality"
},
  "geometry": {"coordinates":[-89.60595000000001,20.53844],"type":"Point"}
}