{
  "type": "Feature",
  "properties": {
    "gn:admin1_code":"12",
    "gn:admin2_code":"28",
    "gn:asciiname":"Puente Carrizal (Atexca)",
    "gn:country_code":"MX",
    "gn:dem":1417,
    "gn:feature_class":"P",
    "gn:feature_code":"PPL",
    "gn:name":"Puente Carrizal (Atexca)",
    "gn:population":27,
    "gn:timezone":"America/Mexico_City",
    "iso:country":"MX",
    "wof:name":"Puente Carrizal (Atexca)",
    "wof:placetype":"locality",
    "wof:population":27
},
  "geometry": {"coordinates":[-99.13687,17.55537],"type":"Point"}
}