{
  "type": "Feature",
  "properties": {
    "gn:admin1_code":"17",
    "gn:admin2_code":"21.0",
    "gn:asciiname":"Llano Viejo",
    "gn:country_code":"MX",
    "gn:dem":989,
    "gn:feature_class":"P",
    "gn:feature_code":"PPL",
    "gn:name":"Llano Viejo",
    "gn:population":8,
    "gn:timezone":"America/Mexico_City",
    "iso:country":"MX",
    "wof:name":"Llano Viejo",
    "wof:placetype":"locality",
    "wof:population":8
},
  "geometry": {"coordinates":[-99.39472000000001,18.73889],"type":"Point"}
}