{
  "type": "Feature",
  "properties": {
    "gn:admin1_code":"21",
    "gn:admin2_code":"4.0",
    "gn:asciiname":"La Fe (Los Sandoval)",
    "gn:country_code":"MX",
    "gn:dem":2099,
    "gn:feature_class":"P",
    "gn:feature_code":"PPL",
    "gn:name":"La Fe (Los Sandoval)",
    "gn:population":7,
    "gn:timezone":"America/Mexico_City",
    "iso:country":"MX",
    "wof:name":"La Fe (Los Sandoval)",
    "wof:placetype":"locality",
    "wof:population":7
},
  "geometry": {"coordinates":[-97.76300999999999,18.9582],"type":"Point"}
}