{
  "type": "Feature",
  "properties": {
    "gn:admin1_code":"24",
    "gn:admin2_code":"28.0",
    "gn:asciiname":"El Blanco",
    "gn:country_code":"MX",
    "gn:dem":1718,
    "gn:feature_class":"P",
    "gn:feature_code":"PPL",
    "gn:name":"El Blanco",
    "gn:population":101,
    "gn:timezone":"America/Mexico_City",
    "iso:country":"MX",
    "wof:name":"El Blanco",
    "wof:placetype":"locality",
    "wof:population":101
},
  "geometry": {"coordinates":[-101.03222,22.625],"type":"Point"}
}