{
  "type": "Feature",
  "properties": {
    "gn:admin1_code":"10",
    "gn:admin2_code":"15.0",
    "gn:asciiname":"Rodeo",
    "gn:country_code":"MX",
    "gn:dem":1610,
    "gn:feature_class":"P",
    "gn:feature_code":"PPL",
    "gn:name":"Rodeo",
    "gn:population":0,
    "gn:timezone":"America/Monterrey",
    "iso:country":"MX",
    "wof:name":"Rodeo",
    "wof:placetype":"locality"
},
  "geometry": {"coordinates":[-104.06667,25.18333],"type":"Point"}
}