{
  "type": "Feature",
  "properties": {
    "gn:admin1_code":"5",
    "gn:admin2_code":"111",
    "gn:asciiname":"El Prospero",
    "gn:country_code":"MX",
    "gn:dem":1620,
    "gn:feature_class":"P",
    "gn:feature_code":"PPL",
    "gn:name":"El Pr\u00f3spero",
    "gn:population":17,
    "gn:timezone":"America/Mexico_City",
    "iso:country":"MX",
    "name:und_x_variant":[
        "El Pr\u00f3spero"
    ],
    "wof:name":"El Prospero",
    "wof:placetype":"locality",
    "wof:population":17
},
  "geometry": {"coordinates":[-92.78610999999999,16.77556],"type":"Point"}
}