{
  "type": "Feature",
  "properties": {
    "gn:admin1_code":"14.0",
    "gn:admin2_code":"12.0",
    "gn:asciiname":"La Poma",
    "gn:country_code":"MX",
    "gn:dem":1426,
    "gn:feature_class":"P",
    "gn:feature_code":"PPL",
    "gn:name":"La Poma",
    "gn:population":0,
    "gn:timezone":"America/Mexico_City",
    "iso:country":"MX",
    "name:ceb_x_preferred":[
        "La Poma"
    ],
    "name:fra_x_preferred":[
        "La Poma"
    ],
    "name:por_x_preferred":[
        "La Poma"
    ],
    "name:spa_x_preferred":[
        "La Poma"
    ],
    "name:swe_x_preferred":[
        "La Poma"
    ],
    "name:urd_x_preferred":[
        "\u0644\u0627 \u067e\u0648\u0645\u0627"
    ],
    "name:zho_x_preferred":[
        "\u62c9\u6ce2\u99ac"
    ],
    "wof:name":"La Poma",
    "wof:placetype":"locality"
},
  "geometry": {"coordinates":[-104.49442999999999,20.47537],"type":"Point"}
}