{
  "type": "Feature",
  "properties": {
    "gn:admin1_code":"6",
    "gn:admin2_code":"49.0",
    "gn:asciiname":"Paraje La Cueva",
    "gn:country_code":"MX",
    "gn:dem":1782,
    "gn:feature_class":"P",
    "gn:feature_code":"PPL",
    "gn:name":"Paraje La Cueva",
    "gn:population":0,
    "gn:timezone":"America/Chihuahua",
    "iso:country":"MX",
    "name:spa_x_preferred":[
        "Paraje La Cueva"
    ],
    "wof:name":"Paraje La Cueva",
    "wof:placetype":"locality"
},
  "geometry": {"coordinates":[-106.7646,27.22642],"type":"Point"}
}