{
  "type": "Feature",
  "properties": {
    "gn:admin1_code":"30",
    "gn:admin2_code":"126.0",
    "gn:asciiname":"Palmaritos",
    "gn:country_code":"MX",
    "gn:dem":53,
    "gn:feature_class":"P",
    "gn:feature_code":"PPL",
    "gn:name":"Palmaritos",
    "gn:population":898,
    "gn:timezone":"America/Mexico_City",
    "iso:country":"MX",
    "wof:name":"Palmaritos",
    "wof:placetype":"locality",
    "wof:population":898
},
  "geometry": {"coordinates":[-96.41058,19.22069],"type":"Point"}
}