{
  "type": "Feature",
  "properties": {
    "gn:admin1_code":"27",
    "gn:admin2_code":"10.0",
    "gn:asciiname":"El Coquito",
    "gn:country_code":"MX",
    "gn:dem":5,
    "gn:feature_class":"P",
    "gn:feature_code":"PPL",
    "gn:name":"El Coquito",
    "gn:population":0,
    "gn:timezone":"America/Mexico_City",
    "iso:country":"MX",
    "name:spa_x_preferred":[
        "El Coquito"
    ],
    "wof:name":"El Coquito",
    "wof:placetype":"locality"
},
  "geometry": {"coordinates":[-93.06932999999999,18.32156],"type":"Point"}
}