{
  "type": "Feature",
  "properties": {
    "gn:admin1_code":"6",
    "gn:admin2_code":"51.0",
    "gn:asciiname":"La Cascarita",
    "gn:country_code":"MX",
    "gn:dem":2312,
    "gn:feature_class":"P",
    "gn:feature_code":"PPL",
    "gn:name":"La Cascarita",
    "gn:population":0,
    "gn:timezone":"America/Chihuahua",
    "iso:country":"MX",
    "name:spa_x_preferred":[
        "La Cascarita"
    ],
    "wof:name":"La Cascarita",
    "wof:placetype":"locality"
},
  "geometry": {"coordinates":[-108.11790999999999,28.13169000000001],"type":"Point"}
}