{
  "type": "Feature",
  "properties": {
    "gn:admin1_code":"28",
    "gn:admin2_code":"42",
    "gn:asciiname":"San Antonio",
    "gn:country_code":"MX",
    "gn:dem":321,
    "gn:feature_class":"P",
    "gn:feature_code":"PPL",
    "gn:name":"San Antonio",
    "gn:population":13,
    "gn:timezone":"America/Monterrey",
    "iso:country":"MX",
    "wof:name":"San Antonio",
    "wof:placetype":"locality",
    "wof:population":13
},
  "geometry": {"coordinates":[-99.38861,24.50889],"type":"Point"}
}