{
  "type": "Feature",
  "properties": {
    "gn:admin1_code":"31",
    "gn:admin2_code":"85.0",
    "gn:asciiname":"Dzalbay",
    "gn:country_code":"MX",
    "gn:dem":19,
    "gn:feature_class":"P",
    "gn:feature_code":"PPL",
    "gn:name":"Dzalbay",
    "gn:population":0,
    "gn:timezone":"America/Merida",
    "iso:country":"MX",
    "name:spa_x_preferred":[
        "Dzalbay"
    ],
    "wof:name":"Dzalbay",
    "wof:placetype":"locality"
},
  "geometry": {"coordinates":[-88.0527,20.83461],"type":"Point"}
}