{
  "type": "Feature",
  "properties": {
    "gn:admin1_code":"5",
    "gn:admin2_code":"77.0",
    "gn:asciiname":"Cristobal Colon (Miguel Hidalgo)",
    "gn:country_code":"MX",
    "gn:dem":75,
    "gn:feature_class":"P",
    "gn:feature_code":"PPL",
    "gn:name":"Cristobal Col\u00f3n (Miguel Hidalgo)",
    "gn:population":53,
    "gn:timezone":"America/Mexico_City",
    "iso:country":"MX",
    "name:und_x_variant":[
        "Cristobal Col\u00f3n (Miguel Hidalgo)"
    ],
    "wof:name":"Cristobal Colon (Miguel Hidalgo)",
    "wof:placetype":"locality",
    "wof:population":53
},
  "geometry": {"coordinates":[-92.12833000000001,17.3225],"type":"Point"}
}