{
  "type": "Feature",
  "properties": {
    "gn:admin1_code":"16",
    "gn:admin2_code":"89.0",
    "gn:asciiname":"Los Guerrero",
    "gn:country_code":"MX",
    "gn:dem":341,
    "gn:feature_class":"P",
    "gn:feature_code":"PPL",
    "gn:name":"Los Guerrero",
    "gn:population":6,
    "gn:timezone":"America/Mexico_City",
    "iso:country":"MX",
    "wof:name":"Los Guerrero",
    "wof:placetype":"locality",
    "wof:population":6
},
  "geometry": {"coordinates":[-102.83139,19.12944],"type":"Point"}
}