{
  "type": "Feature",
  "properties": {
    "gn:admin1_code":"30",
    "gn:admin2_code":"160.0",
    "gn:asciiname":"Colonia Unidad Socialista",
    "gn:country_code":"MX",
    "gn:dem":32,
    "gn:feature_class":"P",
    "gn:feature_code":"PPL",
    "gn:name":"Colonia Unidad Socialista",
    "gn:population":0,
    "gn:timezone":"America/Mexico_City",
    "iso:country":"MX",
    "name:spa_x_preferred":[
        "Colonia Unidad Socialista"
    ],
    "wof:name":"Colonia Unidad Socialista",
    "wof:placetype":"locality"
},
  "geometry": {"coordinates":[-97.69851,20.89671],"type":"Point"}
}