{
  "type": "Feature",
  "properties": {
    "gn:admin1_code":"2",
    "gn:admin2_code":"1.0",
    "gn:asciiname":"Veintisiete de Enero",
    "gn:country_code":"MX",
    "gn:dem":16,
    "gn:feature_class":"P",
    "gn:feature_code":"PPL",
    "gn:name":"Veintisiete de Enero",
    "gn:population":0,
    "gn:timezone":"America/Tijuana",
    "iso:country":"MX",
    "name:spa_x_preferred":[
        "Veintisiete de Enero"
    ],
    "wof:name":"Veintisiete de Enero",
    "wof:placetype":"locality"
},
  "geometry": {"coordinates":[-116.31646000000001,31.07475],"type":"Point"}
}