{
  "type": "Feature",
  "properties": {
    "gn:admin1_code":"25",
    "gn:admin2_code":"17.0",
    "gn:asciiname":"Cuitabon",
    "gn:country_code":"MX",
    "gn:dem":102,
    "gn:feature_class":"P",
    "gn:feature_code":"PPL",
    "gn:name":"Cuitab\u00f3n",
    "gn:population":0,
    "gn:timezone":"America/Mazatlan",
    "iso:country":"MX",
    "name:spa_x_preferred":[
        "Cuitab\u00f3n"
    ],
    "wof:name":"Cuitabon",
    "wof:placetype":"locality"
},
  "geometry": {"coordinates":[-108.19759000000001,25.90955],"type":"Point"}
}