{
  "type": "Feature",
  "properties": {
    "gn:admin1_code":"15",
    "gn:admin2_code":"80.0",
    "gn:asciiname":"La Union",
    "gn:country_code":"MX",
    "gn:dem":1861,
    "gn:feature_class":"P",
    "gn:feature_code":"PPL",
    "gn:name":"La Uni\u00f3n",
    "gn:population":0,
    "gn:timezone":"America/Mexico_City",
    "iso:country":"MX",
    "name:spa_x_preferred":[
        "La Uni\u00f3n"
    ],
    "wof:name":"La Union",
    "wof:placetype":"locality"
},
  "geometry": {"coordinates":[-99.98631,18.84575],"type":"Point"}
}