{
  "type": "Feature",
  "properties": {
    "gn:admin1_code":"25.0",
    "gn:admin2_code":"11.0",
    "gn:asciiname":"El Chino",
    "gn:country_code":"MX",
    "gn:dem":17,
    "gn:feature_class":"P",
    "gn:feature_code":"PPL",
    "gn:name":"El Chino",
    "gn:population":0,
    "gn:timezone":"America/Mazatlan",
    "iso:country":"MX",
    "name:spa_x_preferred":[
        "El Chino"
    ],
    "name:spa_x_variant":[
        "Los L\u00f3pez"
    ],
    "wof:name":"El Chino",
    "wof:placetype":"locality"
},
  "geometry": {"coordinates":[-108.42733,25.50075],"type":"Point"}
}