{
  "type": "Feature",
  "properties": {
    "gn:admin1_code":"6.0",
    "gn:admin2_code":"40.0",
    "gn:asciiname":"Arroyo Bonito",
    "gn:country_code":"MX",
    "gn:dem":1215,
    "gn:feature_class":"P",
    "gn:feature_code":"PPL",
    "gn:name":"Arroyo Bonito",
    "gn:population":0,
    "gn:timezone":"America/Chihuahua",
    "iso:country":"MX",
    "name:spa_x_preferred":[
        "Arroyo Bonito"
    ],
    "wof:name":"Arroyo Bonito",
    "wof:placetype":"locality"
},
  "geometry": {"coordinates":[-108.46626000000001,28.92814000000001],"type":"Point"}
}