{
  "type": "Feature",
  "properties": {
    "gn:admin1_code":"13",
    "gn:admin2_code":"26.0",
    "gn:asciiname":"Tlatzonco",
    "gn:country_code":"MX",
    "gn:dem":315,
    "gn:feature_class":"P",
    "gn:feature_code":"PPL",
    "gn:name":"Tlatzonco",
    "gn:population":0,
    "gn:timezone":"America/Mexico_City",
    "iso:country":"MX",
    "name:und_x_variant":[
        "Tlalzonco",
        "Tlaltzongo",
        "Tlaltzonco"
    ],
    "wof:name":"Tlatzonco",
    "wof:placetype":"locality"
},
  "geometry": {"coordinates":[-98.47089,20.96461],"type":"Point"}
}