{
  "type": "Feature",
  "properties": {
    "gn:admin1_code":"6",
    "gn:admin2_code":"36",
    "gn:asciiname":"Los Compadres",
    "gn:country_code":"MX",
    "gn:dem":1330,
    "gn:feature_class":"P",
    "gn:feature_code":"PPL",
    "gn:name":"Los Compadres",
    "gn:population":20,
    "gn:timezone":"America/Chihuahua",
    "iso:country":"MX",
    "wof:name":"Los Compadres",
    "wof:placetype":"locality",
    "wof:population":20
},
  "geometry": {"coordinates":[-104.88339999999999,27.27641],"type":"Point"}
}