{
  "type": "Feature",
  "properties": {
    "gn:admin1_code":"13",
    "gn:admin2_code":"58.0",
    "gn:asciiname":"Huisache",
    "gn:country_code":"MX",
    "gn:dem":1924,
    "gn:feature_class":"P",
    "gn:feature_code":"PPL",
    "gn:name":"Huisache",
    "gn:population":0,
    "gn:timezone":"America/Mexico_City",
    "iso:country":"MX",
    "name:spa_x_preferred":[
        "Huizache"
    ],
    "name:spa_x_variant":[
        "Huisache"
    ],
    "wof:name":"Huisache",
    "wof:placetype":"locality"
},
  "geometry": {"coordinates":[-99.40658999999999,20.5255],"type":"Point"}
}