{
  "type": "Feature",
  "properties": {
    "gn:admin1_code":"4",
    "gn:admin2_code":"3.0",
    "gn:asciiname":"La Carmelita",
    "gn:country_code":"MX",
    "gn:dem":4,
    "gn:feature_class":"P",
    "gn:feature_code":"PPL",
    "gn:name":"La Carmelita",
    "gn:population":0,
    "gn:timezone":"America/Merida",
    "iso:country":"MX",
    "name:spa_x_preferred":[
        "La Carmelita"
    ],
    "wof:name":"La Carmelita",
    "wof:placetype":"locality"
},
  "geometry": {"coordinates":[-91.27054,18.21581],"type":"Point"}
}