{
  "type": "Feature",
  "properties": {
    "gn:admin1_code":"5",
    "gn:admin2_code":"52.0",
    "gn:asciiname":"San Francisco el Naranjo",
    "gn:country_code":"MX",
    "gn:dem":978,
    "gn:feature_class":"P",
    "gn:feature_code":"PPL",
    "gn:name":"San Francisco el Naranjo",
    "gn:population":392,
    "gn:timezone":"America/Mexico_City",
    "iso:country":"MX",
    "wof:name":"San Francisco el Naranjo",
    "wof:placetype":"locality",
    "wof:population":392
},
  "geometry": {"coordinates":[-91.60333,16.41278],"type":"Point"}
}