{
  "type": "Feature",
  "properties": {
    "gn:admin1_code":"28",
    "gn:admin2_code":"34.0",
    "gn:asciiname":"Rincon Murillo (Rancho Viejo)",
    "gn:country_code":"MX",
    "gn:dem":749,
    "gn:feature_class":"P",
    "gn:feature_code":"PPL",
    "gn:name":"Rinc\u00f3n Murillo (Rancho Viejo)",
    "gn:population":148,
    "gn:timezone":"America/Monterrey",
    "iso:country":"MX",
    "wof:name":"Rincon Murillo (Rancho Viejo)",
    "wof:placetype":"locality",
    "wof:population":148
},
  "geometry": {"coordinates":[-99.05313,24.52888],"type":"Point"}
}