{
  "type": "Feature",
  "properties": {
    "gn:admin1_code":"27",
    "gn:admin2_code":"1.0",
    "gn:asciiname":"Ponzona",
    "gn:country_code":"MX",
    "gn:dem":44,
    "gn:feature_class":"P",
    "gn:feature_code":"PPL",
    "gn:name":"Ponzo\u00f1a",
    "gn:population":0,
    "gn:timezone":"America/Mexico_City",
    "iso:country":"MX",
    "name:spa_x_preferred":[
        "Ponzo\u00f1a"
    ],
    "wof:name":"Ponzona",
    "wof:placetype":"locality"
},
  "geometry": {"coordinates":[-91.32109,17.90954],"type":"Point"}
}