{
  "type": "Feature",
  "properties": {
    "gn:admin1_code":"5.0",
    "gn:admin2_code":"52.0",
    "gn:asciiname":"San Antonio Villaflores",
    "gn:country_code":"MX",
    "gn:dem":1054,
    "gn:feature_class":"P",
    "gn:feature_code":"PPL",
    "gn:name":"San Antonio Villaflores",
    "gn:population":0,
    "gn:timezone":"America/Mexico_City",
    "iso:country":"MX",
    "name:spa_x_preferred":[
        "Villa Flores"
    ],
    "name:spa_x_variant":[
        "San Antonio Villaflores"
    ],
    "wof:name":"San Antonio Villaflores",
    "wof:placetype":"locality"
},
  "geometry": {"coordinates":[-91.61636,16.23249],"type":"Point"}
}