{
  "type": "Feature",
  "properties": {
    "gn:admin1_code":"20",
    "gn:admin2_code":"348.0",
    "gn:asciiname":"San Mateo Tunuchi",
    "gn:country_code":"MX",
    "gn:dem":2178,
    "gn:feature_class":"P",
    "gn:feature_code":"PPL",
    "gn:name":"San Mateo Tunuchi",
    "gn:population":0,
    "gn:timezone":"America/Mexico_City",
    "iso:country":"MX",
    "name:spa_x_preferred":[
        "San Mateo Tunuchi"
    ],
    "wof:name":"San Mateo Tunuchi",
    "wof:placetype":"locality"
},
  "geometry": {"coordinates":[-98.08377,17.3986],"type":"Point"}
}