{
  "type": "Feature",
  "properties": {
    "gn:admin1_code":"6",
    "gn:admin2_code":"27.0",
    "gn:asciiname":"Riquirachi",
    "gn:country_code":"MX",
    "gn:dem":1801,
    "gn:feature_class":"P",
    "gn:feature_code":"PPL",
    "gn:name":"Riqu\u00edrachi",
    "gn:population":0,
    "gn:timezone":"America/Chihuahua",
    "iso:country":"MX",
    "name:spa_x_preferred":[
        "Riqu\u00edrachi"
    ],
    "wof:name":"Riquirachi",
    "wof:placetype":"locality"
},
  "geometry": {"coordinates":[-107.46132,27.38182],"type":"Point"}
}