{
  "type": "Feature",
  "properties": {
    "gn:admin1_code":"12",
    "gn:admin2_code":"43.0",
    "gn:asciiname":"Los Llanos",
    "gn:country_code":"MX",
    "gn:dem":2130,
    "gn:feature_class":"P",
    "gn:feature_code":"PPL",
    "gn:name":"Los Llanos",
    "gn:population":0,
    "gn:timezone":"America/Mexico_City",
    "iso:country":"MX",
    "name:spa_x_preferred":[
        "Los Llanos"
    ],
    "name:spa_x_variant":[
        "Yoso Tia\u00f1u\u2019u"
    ],
    "name:und_x_variant":[
        "Yozo Tyanu"
    ],
    "wof:name":"Los Llanos",
    "wof:placetype":"locality"
},
  "geometry": {"coordinates":[-98.35636,17.19744],"type":"Point"}
}