{
  "type": "Feature",
  "properties": {
    "gn:admin1_code":"12",
    "gn:admin2_code":"54.0",
    "gn:asciiname":"Gama (Puerto de Gama)",
    "gn:country_code":"MX",
    "gn:dem":1821,
    "gn:feature_class":"P",
    "gn:feature_code":"PPL",
    "gn:name":"Gama (Puerto de Gama)",
    "gn:population":8,
    "gn:timezone":"America/Mexico_City",
    "iso:country":"MX",
    "wof:name":"Gama (Puerto de Gama)",
    "wof:placetype":"locality",
    "wof:population":8
},
  "geometry": {"coordinates":[-100.26067,17.92671],"type":"Point"}
}