{
  "type": "Feature",
  "properties": {
    "gn:admin1_code":"30.0",
    "gn:admin2_code":"161.0",
    "gn:asciiname":"La Noria",
    "gn:country_code":"MX",
    "gn:dem":97,
    "gn:feature_class":"P",
    "gn:feature_code":"PPL",
    "gn:name":"La Noria",
    "gn:population":3,
    "gn:timezone":"America/Mexico_City",
    "iso:country":"MX",
    "name:spa_x_preferred":[
        "La Noria"
    ],
    "wof:name":"La Noria",
    "wof:placetype":"locality",
    "wof:population":3
},
  "geometry": {"coordinates":[-98.35306,21.52528],"type":"Point"}
}