{
  "type": "Feature",
  "properties": {
    "gn:admin1_code":"16.0",
    "gn:admin2_code":"2.0",
    "gn:asciiname":"El Ancon",
    "gn:country_code":"MX",
    "gn:dem":254,
    "gn:feature_class":"P",
    "gn:feature_code":"PPL",
    "gn:name":"El Anc\u00f3n",
    "gn:population":0,
    "gn:timezone":"America/Mexico_City",
    "iso:country":"MX",
    "name:spa_x_preferred":[
        "El Anc\u00f3n"
    ],
    "wof:name":"El Ancon",
    "wof:placetype":"locality"
},
  "geometry": {"coordinates":[-102.65085000000001,19.04515],"type":"Point"}
}