{
  "type": "Feature",
  "properties": {
    "gn:admin1_code":"24",
    "gn:admin2_code":"22.0",
    "gn:asciiname":"Las Pilitas",
    "gn:country_code":"MX",
    "gn:dem":1915,
    "gn:feature_class":"P",
    "gn:feature_code":"PPL",
    "gn:name":"Las Pilitas",
    "gn:population":82,
    "gn:timezone":"America/Mexico_City",
    "iso:country":"MX",
    "wof:name":"Las Pilitas",
    "wof:placetype":"locality",
    "wof:population":82
},
  "geometry": {"coordinates":[-101.13889,22.60667],"type":"Point"}
}