{
  "type": "Feature",
  "properties": {
    "gn:admin1_code":"11.0",
    "gn:admin2_code":"23.0",
    "gn:asciiname":"El Guayabito",
    "gn:cc2":"MX",
    "gn:country_code":"MX",
    "gn:dem":1693,
    "gn:feature_class":"P",
    "gn:feature_code":"PPL",
    "gn:name":"El Guayabito",
    "gn:population":0,
    "gn:timezone":"America/Mexico_City",
    "iso:country":"MX",
    "name:und_x_variant":[
        "Guayabito",
        "El Guayabo",
        "El Guayabito"
    ],
    "wof:name":"El Guayabito",
    "wof:placetype":"locality"
},
  "geometry": {"coordinates":[-101.9725,20.37861],"type":"Point"}
}