{
  "type": "Feature",
  "properties": {
    "gn:admin1_code":"5",
    "gn:admin2_code":"75.0",
    "gn:asciiname":"Ixtapilla",
    "gn:country_code":"MX",
    "gn:dem":1071,
    "gn:feature_class":"P",
    "gn:feature_code":"PPL",
    "gn:name":"Ixtapilla",
    "gn:population":0,
    "gn:timezone":"America/Mexico_City",
    "iso:country":"MX",
    "name:spa_x_preferred":[
        "Ixtapilla"
    ],
    "wof:name":"Ixtapilla",
    "wof:placetype":"locality"
},
  "geometry": {"coordinates":[-92.43062,16.36365],"type":"Point"}
}