{
  "type": "Feature",
  "properties": {
    "gn:admin1_code":"18",
    "gn:admin2_code":"20",
    "gn:asciiname":"Bandera de Reyes",
    "gn:country_code":"MX",
    "gn:dem":47,
    "gn:feature_class":"P",
    "gn:feature_code":"PPL",
    "gn:name":"Bandera de Reyes",
    "gn:population":14,
    "gn:timezone":"America/Bahia_Banderas",
    "iso:country":"MX",
    "wof:name":"Bandera de Reyes",
    "wof:placetype":"locality",
    "wof:population":14
},
  "geometry": {"coordinates":[-105.39278,20.89722],"type":"Point"}
}