{
  "type": "Feature",
  "properties": {
    "gn:admin1_code":"26",
    "gn:admin2_code":"20.0",
    "gn:asciiname":"Zanjon",
    "gn:country_code":"MX",
    "gn:dem":424,
    "gn:feature_class":"P",
    "gn:feature_code":"PPL",
    "gn:name":"Zanj\u00f3n",
    "gn:population":69,
    "gn:timezone":"America/Hermosillo",
    "iso:country":"MX",
    "name:und_x_variant":[
        "Zanj\u00f3n"
    ],
    "wof:name":"Zanjon",
    "wof:placetype":"locality",
    "wof:population":69
},
  "geometry": {"coordinates":[-110.93472,29.59083],"type":"Point"}
}