{
  "type": "Feature",
  "properties": {
    "gn:admin1_code":"17",
    "gn:admin2_code":"29",
    "gn:asciiname":"Campo San Nicolas",
    "gn:country_code":"MX",
    "gn:dem":1150,
    "gn:feature_class":"P",
    "gn:feature_code":"PPL",
    "gn:name":"Campo San Nicol\u00e1s",
    "gn:population":14,
    "gn:timezone":"America/Mexico_City",
    "iso:country":"MX",
    "name:und_x_variant":[
        "Campo San Nicol\u00e1s"
    ],
    "wof:name":"Campo San Nicolas",
    "wof:placetype":"locality",
    "wof:population":14
},
  "geometry": {"coordinates":[-99.08417,18.84306],"type":"Point"}
}