{
  "type": "Feature",
  "properties": {
    "gn:admin1_code":"11.0",
    "gn:admin2_code":"1.0",
    "gn:asciiname":"Soledad de Camacho",
    "gn:country_code":"MX",
    "gn:dem":1697,
    "gn:feature_class":"P",
    "gn:feature_code":"PPL",
    "gn:name":"Soledad de Camacho",
    "gn:population":0,
    "gn:timezone":"America/Mexico_City",
    "iso:country":"MX",
    "name:spa_x_preferred":[
        "Soledad de Camacho"
    ],
    "wof:name":"Soledad de Camacho",
    "wof:placetype":"locality"
},
  "geometry": {"coordinates":[-101.59484,20.39732],"type":"Point"}
}