{
  "type": "Feature",
  "properties": {
    "gn:admin1_code":"21",
    "gn:admin2_code":"217.0",
    "gn:asciiname":"Cuapnepantla",
    "gn:country_code":"MX",
    "gn:dem":2331,
    "gn:feature_class":"P",
    "gn:feature_code":"PPL",
    "gn:name":"Cuapnepantla",
    "gn:population":179,
    "gn:timezone":"America/Mexico_City",
    "iso:country":"MX",
    "wof:name":"Cuapnepantla",
    "wof:placetype":"locality",
    "wof:population":179
},
  "geometry": {"coordinates":[-97.04921,18.32391],"type":"Point"}
}