{
  "type": "Feature",
  "properties": {
    "gn:admin1_code":"6",
    "gn:admin2_code":"27.0",
    "gn:asciiname":"Rechanachi",
    "gn:country_code":"MX",
    "gn:dem":2284,
    "gn:feature_class":"P",
    "gn:feature_code":"PPL",
    "gn:name":"Rechanachi",
    "gn:population":5,
    "gn:timezone":"America/Chihuahua",
    "iso:country":"MX",
    "wof:name":"Rechanachi",
    "wof:placetype":"locality",
    "wof:population":5
},
  "geometry": {"coordinates":[-107.03295,27.01688],"type":"Point"}
}