{
  "type": "Feature",
  "properties": {
    "gn:admin1_code":"11.0",
    "gn:admin2_code":"23.0",
    "gn:asciiname":"Tierras Negras",
    "gn:country_code":"MX",
    "gn:dem":2224,
    "gn:feature_class":"P",
    "gn:feature_code":"PPL",
    "gn:name":"Tierras Negras",
    "gn:population":0,
    "gn:timezone":"America/Mexico_City",
    "iso:country":"MX",
    "name:spa_x_preferred":[
        "Tierras Negras"
    ],
    "wof:name":"Tierras Negras",
    "wof:placetype":"locality"
},
  "geometry": {"coordinates":[-101.74307,20.49483],"type":"Point"}
}