{
  "type": "Feature",
  "properties": {
    "gn:admin1_code":"30",
    "gn:admin2_code":"202.0",
    "gn:asciiname":"Santiago Ateno",
    "gn:country_code":"MX",
    "gn:dem":552,
    "gn:feature_class":"P",
    "gn:feature_code":"PPL",
    "gn:name":"Santiago Ateno",
    "gn:population":111,
    "gn:timezone":"America/Mexico_City",
    "iso:country":"MX",
    "wof:name":"Santiago Ateno",
    "wof:placetype":"locality",
    "wof:population":111
},
  "geometry": {"coordinates":[-98.35917000000001,20.75444],"type":"Point"}
}