{
  "type": "Feature",
  "properties": {
    "gn:admin1_code":"30",
    "gn:admin2_code":"207.0",
    "gn:asciiname":"Coapilla de Colorado",
    "gn:country_code":"MX",
    "gn:dem":36,
    "gn:feature_class":"P",
    "gn:feature_code":"PPL",
    "gn:name":"Coapilla de Colorado",
    "gn:population":9,
    "gn:timezone":"America/Mexico_City",
    "iso:country":"MX",
    "wof:name":"Coapilla de Colorado",
    "wof:placetype":"locality",
    "wof:population":9
},
  "geometry": {"coordinates":[-96.2225,18.27889],"type":"Point"}
}