{
  "type": "Feature",
  "properties": {
    "gn:admin1_code":"5",
    "gn:admin2_code":"119.0",
    "gn:asciiname":"Magdalenas",
    "gn:cc2":"MX",
    "gn:country_code":"MX",
    "gn:dem":1752,
    "gn:feature_class":"P",
    "gn:feature_code":"PPL",
    "gn:name":"Magdalenas",
    "gn:population":0,
    "gn:timezone":"America/Mexico_City",
    "iso:country":"MX",
    "name:und_x_variant":[
        "Magdalena",
        "Magdalenas"
    ],
    "wof:name":"Magdalenas",
    "wof:placetype":"locality"
},
  "geometry": {"coordinates":[-92.71666999999999,16.93333],"type":"Point"}
}