{
  "type": "Feature",
  "properties": {
    "gn:admin1_code":"6",
    "gn:admin2_code":"9",
    "gn:asciiname":"Sayahuachi",
    "gn:country_code":"MX",
    "gn:dem":2287,
    "gn:feature_class":"P",
    "gn:feature_code":"PPL",
    "gn:name":"Sayahuachi",
    "gn:population":13,
    "gn:timezone":"America/Chihuahua",
    "iso:country":"MX",
    "wof:name":"Sayahuachi",
    "wof:placetype":"locality",
    "wof:population":13
},
  "geometry": {"coordinates":[-107.31909,27.80297],"type":"Point"}
}