{
  "type": "Feature",
  "properties": {
    "gn:admin1_code":"25",
    "gn:admin2_code":"16.0",
    "gn:asciiname":"Potrerillo de Piaxtla",
    "gn:country_code":"MX",
    "gn:dem":64,
    "gn:feature_class":"P",
    "gn:feature_code":"PPL",
    "gn:name":"Potrerillo de Piaxtla",
    "gn:population":0,
    "gn:timezone":"America/Mazatlan",
    "iso:country":"MX",
    "name:spa_x_preferred":[
        "Potrerillo de Piaxtla"
    ],
    "wof:name":"Potrerillo de Piaxtla",
    "wof:placetype":"locality"
},
  "geometry": {"coordinates":[-106.6164,23.87658],"type":"Point"}
}