{
  "type": "Feature",
  "properties": {
    "gn:admin1_code":"13",
    "gn:admin2_code":"35.0",
    "gn:asciiname":"El Casco",
    "gn:country_code":"MX",
    "gn:dem":2309,
    "gn:feature_class":"P",
    "gn:feature_code":"PPL",
    "gn:name":"El Casco",
    "gn:population":272,
    "gn:timezone":"America/Mexico_City",
    "iso:country":"MX",
    "wof:name":"El Casco",
    "wof:placetype":"locality",
    "wof:population":272
},
  "geometry": {"coordinates":[-98.33528,20.31583],"type":"Point"}
}