{
  "type": "Feature",
  "properties": {
    "gn:admin1_code":"5.0",
    "gn:asciiname":"Sierra La Cojolita",
    "gn:country_code":"MX",
    "gn:dem":659,
    "gn:feature_class":"P",
    "gn:feature_code":"PPL",
    "gn:name":"Sierra La Cojolita",
    "gn:population":0,
    "gn:timezone":"America/Mexico_City",
    "iso:country":"MX",
    "name:spa_x_preferred":[
        "Sierra La Cojolita"
    ],
    "wof:name":"Sierra La Cojolita",
    "wof:placetype":"locality"
},
  "geometry": {"coordinates":[-91.0361,16.71965],"type":"Point"}
}