{
  "type": "Feature",
  "properties": {
    "gn:admin1_code":"5",
    "gn:admin2_code":"83.0",
    "gn:asciiname":"Adolfo Ruiz Cortinez (Ojo de Agua)",
    "gn:country_code":"MX",
    "gn:dem":915,
    "gn:feature_class":"P",
    "gn:feature_code":"PPL",
    "gn:name":"Adolfo Ruiz Cort\u00ednez (Ojo de Agua)",
    "gn:population":58,
    "gn:timezone":"America/Mexico_City",
    "iso:country":"MX",
    "name:und_x_variant":[
        "Adolfo Ruiz Cort\u00ednez (Ojo de Agua)"
    ],
    "wof:name":"Adolfo Ruiz Cortinez (Ojo de Agua)",
    "wof:placetype":"locality",
    "wof:population":58
},
  "geometry": {"coordinates":[-92.35389000000001,16.25889],"type":"Point"}
}