{
  "type": "Feature",
  "properties": {
    "gn:admin1_code":"6.0",
    "gn:asciiname":"La Sandia",
    "gn:country_code":"MX",
    "gn:dem":1207,
    "gn:feature_class":"P",
    "gn:feature_code":"PPL",
    "gn:name":"La Sand\u00eda",
    "gn:population":0,
    "gn:timezone":"America/Chihuahua",
    "iso:country":"MX",
    "name:spa_x_preferred":[
        "La Sand\u00eda"
    ],
    "wof:name":"La Sandia",
    "wof:placetype":"locality"
},
  "geometry": {"coordinates":[-105.38168,28.09689],"type":"Point"}
}