{
  "type": "Feature",
  "properties": {
    "gn:admin1_code":"28",
    "gn:admin2_code":"34.0",
    "gn:asciiname":"Praxedis Balboa",
    "gn:country_code":"MX",
    "gn:dem":211,
    "gn:feature_class":"P",
    "gn:feature_code":"PPL",
    "gn:name":"Praxedis Balboa",
    "gn:population":0,
    "gn:timezone":"America/Monterrey",
    "iso:country":"MX",
    "name:spa_x_preferred":[
        "Praxedis Balboa"
    ],
    "wof:name":"Praxedis Balboa",
    "wof:placetype":"locality"
},
  "geometry": {"coordinates":[-99.14794999999999,24.34172],"type":"Point"}
}