{
  "type": "Feature",
  "properties": {
    "gn:admin1_code":"28",
    "gn:admin2_code":"32.0",
    "gn:asciiname":"La Guarida",
    "gn:country_code":"MX",
    "gn:dem":73,
    "gn:feature_class":"P",
    "gn:feature_code":"PPL",
    "gn:name":"La Guarida",
    "gn:population":0,
    "gn:timezone":"America/Matamoros",
    "iso:country":"MX",
    "name:spa_x_preferred":[
        "La Guarida"
    ],
    "name:und_x_variant":[
        "La Guardia"
    ],
    "wof:name":"La Guarida",
    "wof:placetype":"locality"
},
  "geometry": {"coordinates":[-98.38597,26.04944],"type":"Point"}
}