{
  "type": "Feature",
  "properties": {
    "gn:admin1_code":"20",
    "gn:admin2_code":"12.0",
    "gn:asciiname":"La Galerita",
    "gn:country_code":"MX",
    "gn:dem":398,
    "gn:feature_class":"P",
    "gn:feature_code":"PPL",
    "gn:name":"La Galerita",
    "gn:population":53,
    "gn:timezone":"America/Mexico_City",
    "iso:country":"MX",
    "wof:name":"La Galerita",
    "wof:placetype":"locality",
    "wof:population":53
},
  "geometry": {"coordinates":[-96.49306,15.91944],"type":"Point"}
}