{
  "type": "Feature",
  "properties": {
    "gn:admin1_code":"16.0",
    "gn:admin2_code":"32.0",
    "gn:asciiname":"San Miguel Nocutzepo",
    "gn:country_code":"MX",
    "gn:dem":2050,
    "gn:feature_class":"P",
    "gn:feature_code":"PPL",
    "gn:name":"San Miguel Nocutzepo",
    "gn:population":939,
    "gn:timezone":"America/Mexico_City",
    "iso:country":"MX",
    "wof:name":"San Miguel Nocutzepo",
    "wof:placetype":"locality",
    "wof:population":939
},
  "geometry": {"coordinates":[-101.69861,19.53],"type":"Point"}
}