{
  "type": "Feature",
  "properties": {
    "gn:admin1_code":"18",
    "gn:admin2_code":"9.0",
    "gn:asciiname":"El Pinito",
    "gn:country_code":"MX",
    "gn:dem":1047,
    "gn:feature_class":"P",
    "gn:feature_code":"PPL",
    "gn:name":"El Pinito",
    "gn:population":6,
    "gn:timezone":"America/Mazatlan",
    "iso:country":"MX",
    "wof:name":"El Pinito",
    "wof:placetype":"locality",
    "wof:population":6
},
  "geometry": {"coordinates":[-104.78833,22.11528],"type":"Point"}
}