{
  "type": "Feature",
  "properties": {
    "gn:admin1_code":"26",
    "gn:admin2_code":"55.0",
    "gn:asciiname":"Los Tornero",
    "gn:country_code":"MX",
    "gn:dem":15,
    "gn:feature_class":"P",
    "gn:feature_code":"PPL",
    "gn:name":"Los Tornero",
    "gn:population":98,
    "gn:timezone":"America/Hermosillo",
    "iso:country":"MX",
    "wof:name":"Los Tornero",
    "wof:placetype":"locality",
    "wof:population":98
},
  "geometry": {"coordinates":[-114.93722,32.22389],"type":"Point"}
}