{
  "type": "Feature",
  "properties": {
    "gn:admin1_code":"11.0",
    "gn:admin2_code":"30.0",
    "gn:asciiname":"El Establo",
    "gn:country_code":"MX",
    "gn:dem":2299,
    "gn:feature_class":"P",
    "gn:feature_code":"PPL",
    "gn:name":"El Establo",
    "gn:population":0,
    "gn:timezone":"America/Mexico_City",
    "iso:country":"MX",
    "name:spa_x_preferred":[
        "El Establo"
    ],
    "wof:name":"El Establo",
    "wof:placetype":"locality"
},
  "geometry": {"coordinates":[-101.25632,21.7258],"type":"Point"}
}