{
  "type": "Feature",
  "properties": {
    "gn:admin1_code":"30.0",
    "gn:admin2_code":"155.0",
    "gn:asciiname":"Ejido Emiliano Zapata",
    "gn:country_code":"MX",
    "gn:dem":104,
    "gn:feature_class":"P",
    "gn:feature_code":"PPL",
    "gn:name":"Ejido Emiliano Zapata",
    "gn:population":118,
    "gn:timezone":"America/Mexico_City",
    "iso:country":"MX",
    "name:spa_x_preferred":[
        "Ejido Emiliano Zapata"
    ],
    "wof:name":"Ejido Emiliano Zapata",
    "wof:placetype":"locality",
    "wof:population":118
},
  "geometry": {"coordinates":[-98.30278,21.35722],"type":"Point"}
}