{
  "type": "Feature",
  "properties": {
    "gn:admin1_code":"15.0",
    "gn:asciiname":"La Higuera del Padre",
    "gn:country_code":"MX",
    "gn:dem":58,
    "gn:feature_class":"P",
    "gn:feature_code":"PPL",
    "gn:name":"La Higuera del Padre",
    "gn:population":0,
    "gn:timezone":"America/Mexico_City",
    "iso:country":"MX",
    "name:spa_x_preferred":[
        "La Higuera del Padre"
    ],
    "wof:name":"La Higuera del Padre",
    "wof:placetype":"locality"
},
  "geometry": {"coordinates":[-102.44670000000001,18.08207],"type":"Point"}
}