{
  "type": "Feature",
  "properties": {
    "gn:admin1_code":"18.0",
    "gn:admin2_code":"9.0",
    "gn:asciiname":"El Colomo",
    "gn:country_code":"MX",
    "gn:dem":821,
    "gn:feature_class":"P",
    "gn:feature_code":"PPL",
    "gn:name":"El Colomo",
    "gn:population":0,
    "gn:timezone":"America/Mazatlan",
    "iso:country":"MX",
    "name:spa_x_preferred":[
        "El Colomo"
    ],
    "wof:name":"El Colomo",
    "wof:placetype":"locality"
},
  "geometry": {"coordinates":[-104.51352,22.1688],"type":"Point"}
}