{
  "type": "Feature",
  "properties": {
    "gn:admin1_code":"28",
    "gn:admin2_code":"8.0",
    "gn:asciiname":"El Caiman",
    "gn:country_code":"MX",
    "gn:dem":341,
    "gn:feature_class":"P",
    "gn:feature_code":"PPL",
    "gn:name":"El Caim\u00e1n",
    "gn:population":0,
    "gn:timezone":"America/Monterrey",
    "iso:country":"MX",
    "name:spa_x_preferred":[
        "El Caim\u00e1n"
    ],
    "wof:name":"El Caiman",
    "wof:placetype":"locality"
},
  "geometry": {"coordinates":[-99.01573999999999,23.55709],"type":"Point"}
}