{
  "type": "Feature",
  "properties": {
    "gn:admin1_code":"5",
    "gn:admin2_code":"19",
    "gn:asciiname":"La Sombra",
    "gn:country_code":"MX",
    "gn:dem":2312,
    "gn:feature_class":"P",
    "gn:feature_code":"PPL",
    "gn:name":"La Sombra",
    "gn:population":31,
    "gn:timezone":"America/Mexico_City",
    "iso:country":"MX",
    "wof:name":"La Sombra",
    "wof:placetype":"locality",
    "wof:population":31
},
  "geometry": {"coordinates":[-92.27556,16.47639],"type":"Point"}
}