{
  "type": "Feature",
  "properties": {
    "gn:admin1_code":"20",
    "gn:admin2_code":"478.0",
    "gn:asciiname":"San Juan Tonaltepec",
    "gn:country_code":"MX",
    "gn:dem":1823,
    "gn:feature_class":"P",
    "gn:feature_code":"PPL",
    "gn:name":"San Juan Tonaltepec",
    "gn:population":0,
    "gn:timezone":"America/Mexico_City",
    "iso:country":"MX",
    "name:und_x_variant":[
        "Tonaltepec",
        "San Juan Tonaltepec"
    ],
    "wof:name":"San Juan Tonaltepec",
    "wof:placetype":"locality"
},
  "geometry": {"coordinates":[-96.95686000000001,17.57161],"type":"Point"}
}