{
  "type": "Feature",
  "properties": {
    "gn:admin1_code":"14",
    "gn:admin2_code":"78.0",
    "gn:asciiname":"Ninguno [Crucero San Miguel-San Julian Kilometro Siete]",
    "gn:country_code":"MX",
    "gn:dem":1988,
    "gn:feature_class":"P",
    "gn:feature_code":"PPL",
    "gn:name":"Ninguno [Crucero San Miguel-San Juli\u00e1n Kil\u00f3metro Siete]",
    "gn:population":8,
    "gn:timezone":"America/Mexico_City",
    "iso:country":"MX",
    "name:und_x_variant":[
        "Ninguno [Crucero San Miguel-San Juli\u00e1n Kil\u00f3metro Siete]"
    ],
    "wof:name":"Ninguno [Crucero San Miguel-San Julian Kilometro Siete]",
    "wof:placetype":"locality",
    "wof:population":8
},
  "geometry": {"coordinates":[-102.32444,21.01417],"type":"Point"}
}