{
  "type": "Feature",
  "properties": {
    "gn:admin1_code":"28",
    "gn:admin2_code":"20.0",
    "gn:asciiname":"Los Mimbres",
    "gn:cc2":"MX",
    "gn:country_code":"MX",
    "gn:dem":397,
    "gn:feature_class":"P",
    "gn:feature_code":"PPL",
    "gn:name":"Los Mimbres",
    "gn:population":0,
    "gn:timezone":"America/Monterrey",
    "iso:country":"MX",
    "name:und_x_variant":[
        "Mimbres",
        "Los Mimbres"
    ],
    "wof:name":"Los Mimbres",
    "wof:placetype":"locality"
},
  "geometry": {"coordinates":[-99.53333000000001,24.56667],"type":"Point"}
}