{
  "type": "Feature",
  "properties": {
    "gn:admin1_code":"6",
    "gn:admin2_code":"8",
    "gn:asciiname":"La Noria",
    "gn:country_code":"MX",
    "gn:dem":629,
    "gn:feature_class":"P",
    "gn:feature_code":"PPL",
    "gn:name":"La Noria",
    "gn:population":30,
    "gn:timezone":"America/Chihuahua",
    "iso:country":"MX",
    "wof:name":"La Noria",
    "wof:placetype":"locality",
    "wof:population":30
},
  "geometry": {"coordinates":[-107.7474,27.02243],"type":"Point"}
}