{
  "type": "Feature",
  "properties": {
    "gn:admin1_code":"28.0",
    "gn:admin2_code":"37.0",
    "gn:asciiname":"La Vuelta",
    "gn:country_code":"MX",
    "gn:dem":146,
    "gn:feature_class":"P",
    "gn:feature_code":"PPL",
    "gn:name":"La Vuelta",
    "gn:population":0,
    "gn:timezone":"America/Monterrey",
    "iso:country":"MX",
    "name:spa_x_preferred":[
        "La Vuelta"
    ],
    "wof:name":"La Vuelta",
    "wof:placetype":"locality"
},
  "geometry": {"coordinates":[-98.17639,23.43639],"type":"Point"}
}