{
  "type": "Feature",
  "properties": {
    "gn:admin1_code":"6",
    "gn:admin2_code":"29.0",
    "gn:asciiname":"Pericos",
    "gn:country_code":"MX",
    "gn:dem":2205,
    "gn:feature_class":"P",
    "gn:feature_code":"PPL",
    "gn:name":"Pericos",
    "gn:population":0,
    "gn:timezone":"America/Chihuahua",
    "iso:country":"MX",
    "name:spa_x_preferred":[
        "Pericos"
    ],
    "wof:name":"Pericos",
    "wof:placetype":"locality"
},
  "geometry": {"coordinates":[-107.39874,26.49192],"type":"Point"}
}