{
  "type": "Feature",
  "properties": {
    "gn:admin1_code":"24",
    "gn:admin2_code":"13.0",
    "gn:asciiname":"Flor de Maria",
    "gn:country_code":"MX",
    "gn:dem":213,
    "gn:feature_class":"P",
    "gn:feature_code":"PPL",
    "gn:name":"Flor de Mar\u00eda",
    "gn:population":0,
    "gn:timezone":"America/Mexico_City",
    "iso:country":"MX",
    "name:spa_x_preferred":[
        "Flor de Mar\u00eda"
    ],
    "wof:name":"Flor de Maria",
    "wof:placetype":"locality"
},
  "geometry": {"coordinates":[-99.03852000000001,22.30702],"type":"Point"}
}