{
  "type": "Feature",
  "properties": {
    "gn:admin1_code":"26.0",
    "gn:admin2_code":"43.0",
    "gn:asciiname":"Maytorena",
    "gn:country_code":"MX",
    "gn:dem":1096,
    "gn:feature_class":"P",
    "gn:feature_code":"PPL",
    "gn:name":"Maytorena",
    "gn:population":0,
    "gn:timezone":"America/Hermosillo",
    "iso:country":"MX",
    "name:spa_x_preferred":[
        "Maytorena"
    ],
    "wof:name":"Maytorena",
    "wof:placetype":"locality"
},
  "geometry": {"coordinates":[-110.9132,31.09701],"type":"Point"}
}