{
  "type": "Feature",
  "properties": {
    "gn:admin1_code":"6.0",
    "gn:admin2_code":"66.0",
    "gn:asciiname":"Tesos",
    "gn:country_code":"MX",
    "gn:dem":440,
    "gn:feature_class":"P",
    "gn:feature_code":"PPL",
    "gn:name":"Tesos",
    "gn:population":0,
    "gn:timezone":"America/Chihuahua",
    "iso:country":"MX",
    "name:spa_x_preferred":[
        "Tesos"
    ],
    "wof:name":"Tesos",
    "wof:placetype":"locality"
},
  "geometry": {"coordinates":[-108.82926999999999,27.89891],"type":"Point"}
}