{
  "type": "Feature",
  "properties": {
    "gn:admin1_code":"16",
    "gn:admin2_code":"99",
    "gn:asciiname":"El Molinito",
    "gn:country_code":"MX",
    "gn:dem":1265,
    "gn:feature_class":"P",
    "gn:feature_code":"PPL",
    "gn:name":"El Molinito",
    "gn:population":51,
    "gn:timezone":"America/Mexico_City",
    "iso:country":"MX",
    "wof:name":"El Molinito",
    "wof:placetype":"locality",
    "wof:population":51
},
  "geometry": {"coordinates":[-100.62361,19.36139],"type":"Point"}
}