{
  "type": "Feature",
  "properties": {
    "gn:admin1_code":"26",
    "gn:asciiname":"Caramechic",
    "gn:country_code":"MX",
    "gn:dem":320,
    "gn:feature_class":"P",
    "gn:feature_code":"PPL",
    "gn:name":"Caramechic",
    "gn:population":0,
    "gn:timezone":"America/Chihuahua",
    "iso:country":"MX",
    "name:spa_x_preferred":[
        "Caramechic"
    ],
    "name:und_x_variant":[
        "Caramochic"
    ],
    "wof:name":"Caramechic",
    "wof:placetype":"locality"
},
  "geometry": {"coordinates":[-108.86060000000001,27.77945],"type":"Point"}
}