{
  "type": "Feature",
  "properties": {
    "gn:admin1_code":"12",
    "gn:admin2_code":"22",
    "gn:asciiname":"Nueva Italia",
    "gn:country_code":"MX",
    "gn:dem":1372,
    "gn:feature_class":"P",
    "gn:feature_code":"PPL",
    "gn:name":"Nueva Italia",
    "gn:population":10,
    "gn:timezone":"America/Mexico_City",
    "iso:country":"MX",
    "name:ceb_x_preferred":[
        "Nueva Italia"
    ],
    "name:sco_x_preferred":[
        "Nueva Italia"
    ],
    "name:srp_x_preferred":[
        "\u041d\u0443\u0435\u0432\u0430 \u0418\u0442\u0430\u043b\u0438\u0458\u0430"
    ],
    "name:swe_x_preferred":[
        "Nueva Italia"
    ],
    "wof:name":"Nueva Italia",
    "wof:placetype":"locality",
    "wof:population":10
},
  "geometry": {"coordinates":[-101.02460000000001,18.11616],"type":"Point"}
}