{
  "type": "Feature",
  "properties": {
    "gn:admin1_code":"12",
    "gn:admin2_code":"22",
    "gn:asciiname":"Nueva Italia",
    "gn:country_code":"MX",
    "gn:dem":1372,
    "gn:feature_class":"P",
    "gn:feature_code":"PPL",
    "gn:name":"Nueva Italia",
    "gn:population":10,
    "gn:timezone":"America/Mexico_City",
    "iso:country":"MX",
    "wof:name":"Nueva Italia",
    "wof:placetype":"locality",
    "wof:population":10
},
  "geometry": {"coordinates":[-101.02460000000001,18.11616],"type":"Point"}
}