{
  "type": "Feature",
  "properties": {
    "gn:admin1_code":"26",
    "gn:admin2_code":"51.0",
    "gn:asciiname":"El Baltazar",
    "gn:country_code":"MX",
    "gn:dem":529,
    "gn:feature_class":"P",
    "gn:feature_code":"PPL",
    "gn:name":"El Baltazar",
    "gn:population":0,
    "gn:timezone":"America/Hermosillo",
    "iso:country":"MX",
    "name:spa_x_preferred":[
        "El Baltazar"
    ],
    "wof:name":"El Baltazar",
    "wof:placetype":"locality"
},
  "geometry": {"coordinates":[-109.42812000000001,27.96006],"type":"Point"}
}