{
  "type": "Feature",
  "properties": {
    "gn:admin1_code":"18.0",
    "gn:admin2_code":"4.0",
    "gn:asciiname":"El Piojillo",
    "gn:country_code":"MX",
    "gn:dem":43,
    "gn:feature_class":"P",
    "gn:feature_code":"PPL",
    "gn:name":"El Piojillo",
    "gn:population":0,
    "gn:timezone":"America/Mazatlan",
    "iso:country":"MX",
    "name:spa_x_preferred":[
        "El Piojillo"
    ],
    "wof:name":"El Piojillo",
    "wof:placetype":"locality"
},
  "geometry": {"coordinates":[-105.1551,21.13235],"type":"Point"}
}