{
  "type": "Feature",
  "properties": {
    "gn:admin1_code":"19.0",
    "gn:asciiname":"Las Raices de Abajo",
    "gn:country_code":"MX",
    "gn:dem":402,
    "gn:feature_class":"P",
    "gn:feature_code":"PPL",
    "gn:name":"Las Ra\u00edces de Abajo",
    "gn:population":0,
    "gn:timezone":"America/Monterrey",
    "iso:country":"MX",
    "name:spa_x_preferred":[
        "Las Ra\u00edces de Abajo"
    ],
    "wof:name":"Las Raices de Abajo",
    "wof:placetype":"locality"
},
  "geometry": {"coordinates":[-99.64503999999999,24.84004],"type":"Point"}
}