{
  "type": "Feature",
  "properties": {
    "gn:admin1_code":"16.0",
    "gn:admin2_code":"10.0",
    "gn:asciiname":"El Pataco",
    "gn:country_code":"MX",
    "gn:dem":939,
    "gn:feature_class":"P",
    "gn:feature_code":"PPL",
    "gn:name":"El Pataco",
    "gn:population":0,
    "gn:timezone":"America/Mexico_City",
    "iso:country":"MX",
    "name:spa_x_preferred":[
        "El Pataco"
    ],
    "wof:name":"El Pataco",
    "wof:placetype":"locality"
},
  "geometry": {"coordinates":[-102.37641000000001,18.32753],"type":"Point"}
}