{
  "type": "Feature",
  "properties": {
    "gn:admin1_code":"20.0",
    "gn:asciiname":"Cerro los Cuates",
    "gn:country_code":"MX",
    "gn:dem":1535,
    "gn:feature_class":"P",
    "gn:feature_code":"PPL",
    "gn:name":"Cerro los Cuates",
    "gn:population":0,
    "gn:timezone":"America/Mexico_City",
    "iso:country":"MX",
    "name:spa_x_preferred":[
        "Cerro los Cuates"
    ],
    "wof:name":"Cerro los Cuates",
    "wof:placetype":"locality"
},
  "geometry": {"coordinates":[-98.42797,17.69939],"type":"Point"}
}