{
  "type": "Feature",
  "properties": {
    "gn:admin1_code":"3",
    "gn:admin2_code":"1.0",
    "gn:asciiname":"Los Clavelitos",
    "gn:country_code":"MX",
    "gn:dem":418,
    "gn:feature_class":"P",
    "gn:feature_code":"PPL",
    "gn:name":"Los Clavelitos",
    "gn:population":0,
    "gn:timezone":"America/Mazatlan",
    "iso:country":"MX",
    "name:spa_x_preferred":[
        "Los Clavelitos"
    ],
    "wof:name":"Los Clavelitos",
    "wof:placetype":"locality"
},
  "geometry": {"coordinates":[-111.99807,26.49977],"type":"Point"}
}