{
  "type": "Feature",
  "properties": {
    "gn:admin1_code":"15",
    "gn:admin2_code":"87.0",
    "gn:asciiname":"Llano de la Y",
    "gn:country_code":"MX",
    "gn:dem":2580,
    "gn:feature_class":"P",
    "gn:feature_code":"PPL",
    "gn:name":"Llano de la Y",
    "gn:population":2554,
    "gn:timezone":"America/Mexico_City",
    "iso:country":"MX",
    "wof:name":"Llano de la Y",
    "wof:placetype":"locality",
    "wof:population":2554
},
  "geometry": {"coordinates":[-99.61639,19.40278],"type":"Point"}
}