{
  "type": "Feature",
  "properties": {
    "gn:admin1_code":"26",
    "gn:admin2_code":"69.0",
    "gn:asciiname":"Terreros",
    "gn:country_code":"MX",
    "gn:dem":1576,
    "gn:feature_class":"P",
    "gn:feature_code":"PPL",
    "gn:name":"Terreros",
    "gn:population":0,
    "gn:timezone":"America/Hermosillo",
    "iso:country":"MX",
    "name:spa_x_preferred":[
        "Terreros"
    ],
    "wof:name":"Terreros",
    "wof:placetype":"locality"
},
  "geometry": {"coordinates":[-108.63739,28.39288],"type":"Point"}
}