{
  "type": "Feature",
  "properties": {
    "gn:admin1_code":"12.0",
    "gn:asciiname":"Arroyo Olor",
    "gn:country_code":"MX",
    "gn:dem":967,
    "gn:feature_class":"P",
    "gn:feature_code":"PPL",
    "gn:name":"Arroyo Olor",
    "gn:population":0,
    "gn:timezone":"America/Mexico_City",
    "iso:country":"MX",
    "name:spa_x_preferred":[
        "Arroyo Olor"
    ],
    "name:spa_x_variant":[
        "Tierra Olor",
        "Itia Xa\u2019an"
    ],
    "wof:name":"Arroyo Olor",
    "wof:placetype":"locality"
},
  "geometry": {"coordinates":[-98.36069999999999,16.97306],"type":"Point"}
}