{
  "type": "Feature",
  "properties": {
    "gn:admin1_code":"19.0",
    "gn:admin2_code":"14.0",
    "gn:asciiname":"Estanque Nuevo",
    "gn:country_code":"MX",
    "gn:dem":1728,
    "gn:feature_class":"P",
    "gn:feature_code":"PPL",
    "gn:name":"Estanque Nuevo",
    "gn:population":0,
    "gn:timezone":"America/Monterrey",
    "iso:country":"MX",
    "name:spa_x_preferred":[
        "Estanque Nuevo"
    ],
    "wof:name":"Estanque Nuevo",
    "wof:placetype":"locality"
},
  "geometry": {"coordinates":[-100.24961999999999,24.10685],"type":"Point"}
}