{
  "type": "Feature",
  "properties": {
    "gn:admin1_code":"26.0",
    "gn:admin2_code":"27.0",
    "gn:asciiname":"Tecoripa",
    "gn:country_code":"MX",
    "gn:dem":1475,
    "gn:feature_class":"P",
    "gn:feature_code":"PPL",
    "gn:name":"Tecoripa",
    "gn:population":0,
    "gn:timezone":"America/Hermosillo",
    "iso:country":"MX",
    "name:spa_x_preferred":[
        "Tecoripa"
    ],
    "name:und_x_variant":[
        "Rancho El Tecoripa"
    ],
    "wof:name":"Tecoripa",
    "wof:placetype":"locality"
},
  "geometry": {"coordinates":[-109.84529000000001,31.01959],"type":"Point"}
}