{
  "type": "Feature",
  "properties": {
    "gn:admin1_code":"30",
    "gn:admin2_code":"184.0",
    "gn:asciiname":"Ichcualco (Las Canoas)",
    "gn:country_code":"MX",
    "gn:dem":2563,
    "gn:feature_class":"P",
    "gn:feature_code":"PPL",
    "gn:name":"Ichcualco (Las Canoas)",
    "gn:population":63,
    "gn:timezone":"America/Mexico_City",
    "iso:country":"MX",
    "wof:name":"Ichcualco (Las Canoas)",
    "wof:placetype":"locality",
    "wof:population":63
},
  "geometry": {"coordinates":[-97.13583,18.60806],"type":"Point"}
}