{
  "type": "Feature",
  "properties": {
    "gn:admin1_code":"30",
    "gn:admin2_code":"45.0",
    "gn:asciiname":"Camino a Cerro de Torres",
    "gn:country_code":"MX",
    "gn:dem":10,
    "gn:feature_class":"P",
    "gn:feature_code":"PPL",
    "gn:name":"Camino a Cerro de Torres",
    "gn:population":71,
    "gn:timezone":"America/Mexico_City",
    "iso:country":"MX",
    "wof:name":"Camino a Cerro de Torres",
    "wof:placetype":"locality",
    "wof:population":71
},
  "geometry": {"coordinates":[-95.78278,18.36222],"type":"Point"}
}