{
  "type": "Feature",
  "properties": {
    "gn:admin1_code":"2.0",
    "gn:admin2_code":"1.0",
    "gn:asciiname":"Las Playitas",
    "gn:country_code":"MX",
    "gn:dem":14,
    "gn:feature_class":"P",
    "gn:feature_code":"PPL",
    "gn:name":"Las Playitas",
    "gn:population":0,
    "gn:timezone":"America/Tijuana",
    "iso:country":"MX",
    "name:spa_x_preferred":[
        "Las Playitas"
    ],
    "wof:name":"Las Playitas",
    "wof:placetype":"locality"
},
  "geometry": {"coordinates":[-113.97441999999999,28.01418],"type":"Point"}
}