{
  "type": "Feature",
  "properties": {
    "gn:admin1_code":"13",
    "gn:admin2_code":"54.0",
    "gn:asciiname":"El Puerto Lazaro Cardenas",
    "gn:country_code":"MX",
    "gn:dem":2041,
    "gn:feature_class":"P",
    "gn:feature_code":"PPL",
    "gn:name":"El Puerto L\u00e1zaro C\u00e1rdenas",
    "gn:population":994,
    "gn:timezone":"America/Mexico_City",
    "iso:country":"MX",
    "name:und_x_variant":[
        "El Puerto L\u00e1zaro C\u00e1rdenas"
    ],
    "wof:name":"El Puerto Lazaro Cardenas",
    "wof:placetype":"locality",
    "wof:population":994
},
  "geometry": {"coordinates":[-99.02083,20.22056],"type":"Point"}
}