{
  "type": "Feature",
  "properties": {
    "gn:admin1_code":"10",
    "gn:admin2_code":"34",
    "gn:asciiname":"La Cruz",
    "gn:country_code":"MX",
    "gn:dem":565,
    "gn:feature_class":"P",
    "gn:feature_code":"PPL",
    "gn:name":"La Cruz",
    "gn:population":44,
    "gn:timezone":"America/Monterrey",
    "iso:country":"MX",
    "wof:name":"La Cruz",
    "wof:placetype":"locality",
    "wof:population":44
},
  "geometry": {"coordinates":[-106.50368,24.64943],"type":"Point"}
}