{
  "type": "Feature",
  "properties": {
    "gn:admin1_code":"16.0",
    "gn:admin2_code":"21.0",
    "gn:asciiname":"Charapan",
    "gn:country_code":"MX",
    "gn:dem":2366,
    "gn:feature_class":"P",
    "gn:feature_code":"PPL",
    "gn:name":"Charap\u00e1n",
    "gn:population":0,
    "gn:timezone":"America/Mexico_City",
    "iso:country":"MX",
    "name:epo_x_preferred":[
        "Charapan"
    ],
    "name:eus_x_preferred":[
        "Charapan"
    ],
    "name:ita_x_preferred":[
        "Charapan"
    ],
    "name:spa_x_preferred":[
        "Charapan"
    ],
    "name:srp_x_preferred":[
        "\u0427\u0430\u0440\u0430\u043f\u0430\u043d"
    ],
    "name:und_x_variant":[
        "Charap\u00e1n"
    ],
    "name:vie_x_preferred":[
        "Charapan"
    ],
    "wof:name":"Charapan",
    "wof:placetype":"locality"
},
  "geometry": {"coordinates":[-102.25,19.65],"type":"Point"}
}