{
  "type": "Feature",
  "properties": {
    "gn:admin1_code":"20",
    "gn:admin2_code":"265",
    "gn:asciiname":"Cerro Baul",
    "gn:country_code":"MX",
    "gn:dem":1135,
    "gn:feature_class":"P",
    "gn:feature_code":"PPL",
    "gn:name":"Cerro Ba\u00fal",
    "gn:population":12,
    "gn:timezone":"America/Mexico_City",
    "iso:country":"MX",
    "name:und_x_variant":[
        "Cerro Ba\u00fal"
    ],
    "wof:name":"Cerro Baul",
    "wof:placetype":"locality",
    "wof:population":12
},
  "geometry": {"coordinates":[-94.19750000000001,16.60694],"type":"Point"}
}