{
  "type": "Feature",
  "properties": {
    "gn:admin1_code":"19.0",
    "gn:admin2_code":"15.0",
    "gn:asciiname":"Retamitas",
    "gn:country_code":"MX",
    "gn:dem":88,
    "gn:feature_class":"P",
    "gn:feature_code":"PPL",
    "gn:name":"Retamitas",
    "gn:population":0,
    "gn:timezone":"America/Monterrey",
    "iso:country":"MX",
    "name:spa_x_preferred":[
        "Retamitas"
    ],
    "wof:name":"Retamitas",
    "wof:placetype":"locality"
},
  "geometry": {"coordinates":[-99.06704000000001,26.03494],"type":"Point"}
}