{
  "type": "Feature",
  "properties": {
    "gn:admin1_code":"24",
    "gn:admin2_code":"24",
    "gn:asciiname":"Joya de Caballos (Joya de Jesus)",
    "gn:country_code":"MX",
    "gn:dem":1467,
    "gn:feature_class":"P",
    "gn:feature_code":"PPL",
    "gn:name":"Joya de Caballos (Joya de Jes\u00fas)",
    "gn:population":15,
    "gn:timezone":"America/Mexico_City",
    "iso:country":"MX",
    "name:und_x_variant":[
        "Joya de Caballos (Joya de Jes\u00fas)"
    ],
    "wof:name":"Joya de Caballos (Joya de Jesus)",
    "wof:placetype":"locality",
    "wof:population":15
},
  "geometry": {"coordinates":[-99.94694,21.655],"type":"Point"}
}