{
  "type": "Feature",
  "properties": {
    "gn:admin1_code":"16",
    "gn:admin2_code":"38",
    "gn:asciiname":"Hornos del Palmar",
    "gn:country_code":"MX",
    "gn:dem":451,
    "gn:feature_class":"P",
    "gn:feature_code":"PPL",
    "gn:name":"Hornos del Palmar",
    "gn:population":13,
    "gn:timezone":"America/Mexico_City",
    "iso:country":"MX",
    "wof:name":"Hornos del Palmar",
    "wof:placetype":"locality",
    "wof:population":13
},
  "geometry": {"coordinates":[-101.19611,18.63222],"type":"Point"}
}