{
  "type": "Feature",
  "properties": {
    "gn:admin1_code":"28.0",
    "gn:admin2_code":"12.0",
    "gn:asciiname":"Torreon de Canas",
    "gn:country_code":"MX",
    "gn:dem":56,
    "gn:feature_class":"P",
    "gn:feature_code":"PPL",
    "gn:name":"Torre\u00f3n de Ca\u00f1as",
    "gn:population":0,
    "gn:timezone":"America/Monterrey",
    "iso:country":"MX",
    "name:spa_x_preferred":[
        "Torre\u00f3n de Ca\u00f1as"
    ],
    "wof:name":"Torreon de Canas",
    "wof:placetype":"locality"
},
  "geometry": {"coordinates":[-98.80179,22.65572],"type":"Point"}
}