{
  "type": "Feature",
  "properties": {
    "gn:admin1_code":"31",
    "gn:admin2_code":"80.0",
    "gn:asciiname":"Dolores Aceeh",
    "gn:country_code":"MX",
    "gn:dem":20,
    "gn:feature_class":"P",
    "gn:feature_code":"PPL",
    "gn:name":"Dolores Aceeh",
    "gn:population":0,
    "gn:timezone":"America/Merida",
    "iso:country":"MX",
    "name:spa_x_preferred":[
        "Dolores Aceeh"
    ],
    "wof:name":"Dolores Aceeh",
    "wof:placetype":"locality"
},
  "geometry": {"coordinates":[-89.28878,20.5521],"type":"Point"}
}