{
  "type": "Feature",
  "properties": {
    "gn:admin1_code":"28",
    "gn:admin2_code":"7.0",
    "gn:asciiname":"Nuevo Camargo",
    "gn:country_code":"MX",
    "gn:dem":60,
    "gn:feature_class":"P",
    "gn:feature_code":"PPL",
    "gn:name":"Nuevo Camargo",
    "gn:population":0,
    "gn:timezone":"America/Monterrey",
    "iso:country":"MX",
    "name:spa_x_preferred":[
        "Nuevo Camargo"
    ],
    "name:und_x_variant":[
        "Villa Nueva"
    ],
    "wof:name":"Nuevo Camargo",
    "wof:placetype":"locality"
},
  "geometry": {"coordinates":[-98.84421,26.29086],"type":"Point"}
}