{
  "type": "Feature",
  "properties": {
    "gn:admin1_code":"30.0",
    "gn:admin2_code":"60.0",
    "gn:asciiname":"Don Margaro",
    "gn:country_code":"MX",
    "gn:dem":54,
    "gn:feature_class":"P",
    "gn:feature_code":"PPL",
    "gn:name":"Don M\u00e1rgaro",
    "gn:population":0,
    "gn:timezone":"America/Mexico_City",
    "iso:country":"MX",
    "name:spa_x_preferred":[
        "Don M\u00e1rgaro"
    ],
    "wof:name":"Don Margaro",
    "wof:placetype":"locality"
},
  "geometry": {"coordinates":[-97.63366000000001,21.34704],"type":"Point"}
}