{
  "type": "Feature",
  "properties": {
    "gn:admin1_code":"5",
    "gn:admin2_code":"109.0",
    "gn:asciiname":"Rosario Saclumil",
    "gn:country_code":"MX",
    "gn:dem":832,
    "gn:feature_class":"P",
    "gn:feature_code":"PPL",
    "gn:name":"Rosario Saclumil",
    "gn:population":225,
    "gn:timezone":"America/Mexico_City",
    "iso:country":"MX",
    "wof:name":"Rosario Saclumil",
    "wof:placetype":"locality",
    "wof:population":225
},
  "geometry": {"coordinates":[-92.34332999999999,17.19417],"type":"Point"}
}