{
  "type": "Feature",
  "properties": {
    "gn:admin1_code":"14",
    "gn:asciiname":"Zapote",
    "gn:country_code":"MX",
    "gn:dem":1743,
    "gn:feature_class":"P",
    "gn:feature_code":"PPL",
    "gn:name":"Zapote",
    "gn:population":0,
    "gn:timezone":"America/Mexico_City",
    "iso:country":"MX",
    "wof:name":"Zapote",
    "wof:placetype":"locality"
},
  "geometry": {"coordinates":[-98.86667,20.41667],"type":"Point"}
}