{
  "type": "Feature",
  "properties": {
    "gn:admin1_code":"10",
    "gn:admin2_code":"32",
    "gn:asciiname":"Boca del Potrero",
    "gn:country_code":"MX",
    "gn:dem":2233,
    "gn:feature_class":"P",
    "gn:feature_code":"PPL",
    "gn:name":"Boca del Potrero",
    "gn:population":14,
    "gn:timezone":"America/Monterrey",
    "iso:country":"MX",
    "wof:name":"Boca del Potrero",
    "wof:placetype":"locality",
    "wof:population":14
},
  "geometry": {"coordinates":[-105.57340000000001,24.64828],"type":"Point"}
}