{
  "type": "Feature",
  "properties": {
    "gn:admin1_code":"26.0",
    "gn:asciiname":"Buyobampo",
    "gn:country_code":"MX",
    "gn:dem":162,
    "gn:feature_class":"P",
    "gn:feature_code":"PPL",
    "gn:name":"Buyobampo",
    "gn:population":0,
    "gn:timezone":"America/Mazatlan",
    "iso:country":"MX",
    "name:spa_x_preferred":[
        "Buyobampo"
    ],
    "wof:name":"Buyobampo",
    "wof:placetype":"locality"
},
  "geometry": {"coordinates":[-108.6147,26.62953],"type":"Point"}
}