{
  "type": "Feature",
  "properties": {
    "gn:admin1_code":"23",
    "gn:admin2_code":"7.0",
    "gn:asciiname":"Bravo Monte",
    "gn:country_code":"MX",
    "gn:dem":19,
    "gn:feature_class":"P",
    "gn:feature_code":"PPL",
    "gn:name":"Bravo Monte",
    "gn:population":0,
    "gn:timezone":"America/Cancun",
    "iso:country":"MX",
    "wof:name":"Bravo Monte",
    "wof:placetype":"locality"
},
  "geometry": {"coordinates":[-87.375,21.31667],"type":"Point"}
}