{
  "type": "Feature",
  "properties": {
    "gn:admin1_code":"21",
    "gn:admin2_code":"145.0",
    "gn:asciiname":"Xalatiopa",
    "gn:country_code":"MX",
    "gn:dem":807,
    "gn:feature_class":"P",
    "gn:feature_code":"PPL",
    "gn:name":"Xalatiopa",
    "gn:population":187,
    "gn:timezone":"America/Mexico_City",
    "iso:country":"MX",
    "wof:name":"Xalatiopa",
    "wof:placetype":"locality",
    "wof:population":187
},
  "geometry": {"coordinates":[-96.85603,18.24982],"type":"Point"}
}