{
  "type": "Feature",
  "properties": {
    "gn:admin1_code":"11.0",
    "gn:admin2_code":"3.0",
    "gn:asciiname":"Cerritos",
    "gn:country_code":"MX",
    "gn:dem":2075,
    "gn:feature_class":"P",
    "gn:feature_code":"PPL",
    "gn:name":"Cerritos",
    "gn:population":0,
    "gn:timezone":"America/Mexico_City",
    "iso:country":"MX",
    "name:und_x_variant":[
        "Los Cerritos",
        "Cerritos"
    ],
    "wof:name":"Cerritos",
    "wof:placetype":"locality"
},
  "geometry": {"coordinates":[-100.5988,20.88552],"type":"Point"}
}