{
  "type": "Feature",
  "properties": {
    "gn:admin1_code":"11",
    "gn:admin2_code":"9",
    "gn:asciiname":"Leonides Rico Presa (Predio la Cajita)",
    "gn:country_code":"MX",
    "gn:dem":1814,
    "gn:feature_class":"P",
    "gn:feature_code":"PPL",
    "gn:name":"Le\u00f3nides Rico Presa (Predio la Cajita)",
    "gn:population":15,
    "gn:timezone":"America/Mexico_City",
    "iso:country":"MX",
    "name:und_x_variant":[
        "Le\u00f3nides Rico Presa (Predio la Cajita)"
    ],
    "wof:name":"Leonides Rico Presa (Predio la Cajita)",
    "wof:placetype":"locality",
    "wof:population":15
},
  "geometry": {"coordinates":[-100.82250000000001,20.70806],"type":"Point"}
}