{
  "type": "Feature",
  "properties": {
    "gn:admin1_code":"6",
    "gn:admin2_code":"10.0",
    "gn:asciiname":"Las Tortugas",
    "gn:country_code":"MX",
    "gn:dem":1275,
    "gn:feature_class":"P",
    "gn:feature_code":"PPL",
    "gn:name":"Las Tortugas",
    "gn:population":0,
    "gn:timezone":"America/Chihuahua",
    "iso:country":"MX",
    "name:spa_x_preferred":[
        "Las Tortugas"
    ],
    "name:und_x_variant":[
        "Rancho Las Tortugas"
    ],
    "wof:name":"Las Tortugas",
    "wof:placetype":"locality"
},
  "geometry": {"coordinates":[-107.32852,30.55482],"type":"Point"}
}