{
  "type": "Feature",
  "properties": {
    "gn:admin1_code":"20",
    "gn:admin2_code":"184.0",
    "gn:asciiname":"El Peal",
    "gn:country_code":"MX",
    "gn:dem":27,
    "gn:feature_class":"P",
    "gn:feature_code":"PPL",
    "gn:name":"El Peal",
    "gn:population":7,
    "gn:timezone":"America/Mexico_City",
    "iso:country":"MX",
    "wof:name":"El Peal",
    "wof:placetype":"locality",
    "wof:population":7
},
  "geometry": {"coordinates":[-96.02972,18.00556],"type":"Point"}
}