{
  "type": "Feature",
  "properties": {
    "gn:admin1_code":"31",
    "gn:admin2_code":"67.0",
    "gn:asciiname":"Sahcatzin",
    "gn:country_code":"MX",
    "gn:dem":16,
    "gn:feature_class":"P",
    "gn:feature_code":"PPL",
    "gn:name":"Sahcatz\u00edn",
    "gn:population":0,
    "gn:timezone":"America/Merida",
    "iso:country":"MX",
    "wof:name":"Sahcatzin",
    "wof:placetype":"locality"
},
  "geometry": {"coordinates":[-89.38333,20.79583],"type":"Point"}
}