{
  "type": "Feature",
  "properties": {
    "gn:admin1_code":"30.0",
    "gn:admin2_code":"121.0",
    "gn:asciiname":"El Retono",
    "gn:country_code":"MX",
    "gn:dem":30,
    "gn:feature_class":"P",
    "gn:feature_code":"PPL",
    "gn:name":"El Reto\u00f1o",
    "gn:population":0,
    "gn:timezone":"America/Mexico_City",
    "iso:country":"MX",
    "name:spa_x_preferred":[
        "El Reto\u00f1o"
    ],
    "wof:name":"El Retono",
    "wof:placetype":"locality"
},
  "geometry": {"coordinates":[-98.0266,21.92468],"type":"Point"}
}