{
  "type": "Feature",
  "properties": {
    "gn:admin1_code":"5",
    "gn:admin2_code":"57",
    "gn:asciiname":"Concepcion Tocanaque",
    "gn:country_code":"MX",
    "gn:dem":2465,
    "gn:feature_class":"P",
    "gn:feature_code":"PPL",
    "gn:name":"Concepci\u00f3n Tocanaque",
    "gn:population":15,
    "gn:timezone":"America/Mexico_City",
    "iso:country":"MX",
    "name:und_x_variant":[
        "Concepci\u00f3n Tocanaque"
    ],
    "wof:name":"Concepcion Tocanaque",
    "wof:placetype":"locality",
    "wof:population":15
},
  "geometry": {"coordinates":[-92.23611,15.29417],"type":"Point"}
}