{
  "type": "Feature",
  "properties": {
    "gn:admin1_code":"12",
    "gn:admin2_code":"10.0",
    "gn:asciiname":"Cerro Liro (Gabino Martinez Sanchez)",
    "gn:country_code":"MX",
    "gn:dem":1609,
    "gn:feature_class":"P",
    "gn:feature_code":"PPL",
    "gn:name":"Cerro Liro (Gabino Mart\u00ednez S\u00e1nchez)",
    "gn:population":8,
    "gn:timezone":"America/Mexico_City",
    "iso:country":"MX",
    "name:und_x_variant":[
        "Cerro Liro (Gabino Mart\u00ednez S\u00e1nchez)"
    ],
    "wof:name":"Cerro Liro (Gabino Martinez Sanchez)",
    "wof:placetype":"locality",
    "wof:population":8
},
  "geometry": {"coordinates":[-98.89416,17.36917],"type":"Point"}
}