{
  "type": "Feature",
  "properties": {
    "gn:admin1_code":"31",
    "gn:admin2_code":"35.0",
    "gn:asciiname":"Peten-Xi",
    "gn:country_code":"MX",
    "gn:dem":17,
    "gn:feature_class":"P",
    "gn:feature_code":"PPL",
    "gn:name":"Peten-Xi",
    "gn:population":0,
    "gn:timezone":"America/Merida",
    "iso:country":"MX",
    "name:spa_x_preferred":[
        "Peten-Xi"
    ],
    "name:spa_x_variant":[
        "Petenchi"
    ],
    "wof:name":"Peten-Xi",
    "wof:placetype":"locality"
},
  "geometry": {"coordinates":[-89.17448,20.8791],"type":"Point"}
}