{
  "type": "Feature",
  "properties": {
    "gn:admin1_code":"26",
    "gn:admin2_code":"30.0",
    "gn:asciiname":"El Represo del Padre",
    "gn:country_code":"MX",
    "gn:dem":144,
    "gn:feature_class":"P",
    "gn:feature_code":"PPL",
    "gn:name":"El Represo del Padre",
    "gn:population":0,
    "gn:timezone":"America/Hermosillo",
    "iso:country":"MX",
    "name:spa_x_preferred":[
        "El Represo del Padre"
    ],
    "name:spa_x_variant":[
        "Rancho El Padre"
    ],
    "wof:name":"El Represo del Padre",
    "wof:placetype":"locality"
},
  "geometry": {"coordinates":[-111.12073999999998,28.93094],"type":"Point"}
}