{
  "type": "Feature",
  "properties": {
    "gn:admin1_code":"14",
    "gn:admin2_code":"122",
    "gn:asciiname":"Tlajomulco",
    "gn:country_code":"MX",
    "gn:dem":1444,
    "gn:feature_class":"P",
    "gn:feature_code":"PPL",
    "gn:name":"Tlajomulco",
    "gn:population":13,
    "gn:timezone":"America/Mexico_City",
    "iso:country":"MX",
    "wof:name":"Tlajomulco",
    "wof:placetype":"locality",
    "wof:population":13
},
  "geometry": {"coordinates":[-103.71306,19.47694],"type":"Point"}
}