{
  "type": "Feature",
  "properties": {
    "gn:admin1_code":"14",
    "gn:admin2_code":"68",
    "gn:asciiname":"El Platanar",
    "gn:country_code":"MX",
    "gn:dem":875,
    "gn:feature_class":"P",
    "gn:feature_code":"PPL",
    "gn:name":"El Platanar",
    "gn:population":44,
    "gn:timezone":"America/Mexico_City",
    "iso:country":"MX",
    "wof:name":"El Platanar",
    "wof:placetype":"locality",
    "wof:population":44
},
  "geometry": {"coordinates":[-104.67806,20.03306],"type":"Point"}
}