{
  "type": "Feature",
  "properties": {
    "gn:admin1_code":"7",
    "gn:admin2_code":"33.0",
    "gn:asciiname":"Patrocinio",
    "gn:country_code":"MX",
    "gn:dem":1100,
    "gn:feature_class":"P",
    "gn:feature_code":"PPL",
    "gn:name":"Patrocinio",
    "gn:population":328,
    "gn:timezone":"America/Monterrey",
    "iso:country":"MX",
    "wof:name":"Patrocinio",
    "wof:placetype":"locality",
    "wof:population":328
},
  "geometry": {"coordinates":[-102.95694,25.78417],"type":"Point"}
}