{
  "type": "Feature",
  "properties": {
    "gn:admin1_code":"25",
    "gn:admin2_code":"8.0",
    "gn:asciiname":"Campo las Carolinas",
    "gn:country_code":"MX",
    "gn:dem":23,
    "gn:feature_class":"P",
    "gn:feature_code":"PPL",
    "gn:name":"Campo las Carolinas",
    "gn:population":65,
    "gn:timezone":"America/Mazatlan",
    "iso:country":"MX",
    "wof:name":"Campo las Carolinas",
    "wof:placetype":"locality",
    "wof:population":65
},
  "geometry": {"coordinates":[-106.94944,23.99056],"type":"Point"}
}