{
  "type": "Feature",
  "properties": {
    "gn:admin1_code":"25",
    "gn:admin2_code":"18.0",
    "gn:asciiname":"Las Aguamitas",
    "gn:country_code":"MX",
    "gn:dem":6,
    "gn:feature_class":"P",
    "gn:feature_code":"PPL",
    "gn:name":"Las Aguamitas",
    "gn:population":1629,
    "gn:timezone":"America/Mazatlan",
    "iso:country":"MX",
    "wof:name":"Las Aguamitas",
    "wof:placetype":"locality",
    "wof:population":1629
},
  "geometry": {"coordinates":[-107.80056,24.57556],"type":"Point"}
}