{
  "type": "Feature",
  "properties": {
    "gn:admin1_code":"14",
    "gn:admin2_code":"87",
    "gn:asciiname":"Paso de Medio (La Cuchilla)",
    "gn:country_code":"MX",
    "gn:dem":1351,
    "gn:feature_class":"P",
    "gn:feature_code":"PPL",
    "gn:name":"Paso de Medio (La Cuchilla)",
    "gn:population":24,
    "gn:timezone":"America/Mexico_City",
    "iso:country":"MX",
    "wof:name":"Paso de Medio (La Cuchilla)",
    "wof:placetype":"locality",
    "wof:population":24
},
  "geometry": {"coordinates":[-103.0925,19.18833],"type":"Point"}
}