{
  "type": "Feature",
  "properties": {
    "gn:admin1_code":"15.0",
    "gn:admin2_code":"85.0",
    "gn:asciiname":"Agostadero",
    "gn:country_code":"MX",
    "gn:dem":2375,
    "gn:feature_class":"P",
    "gn:feature_code":"PPL",
    "gn:name":"Agostadero",
    "gn:population":0,
    "gn:timezone":"America/Mexico_City",
    "iso:country":"MX",
    "wof:name":"Agostadero",
    "wof:placetype":"locality"
},
  "geometry": {"coordinates":[-100.01667,19.9875],"type":"Point"}
}