{
  "type": "Feature",
  "properties": {
    "gn:admin1_code":"30",
    "gn:admin2_code":"20.0",
    "gn:asciiname":"Ticonca",
    "gn:country_code":"MX",
    "gn:dem":2377,
    "gn:feature_class":"P",
    "gn:feature_code":"PPL",
    "gn:name":"Ticonca",
    "gn:population":239,
    "gn:timezone":"America/Mexico_City",
    "iso:country":"MX",
    "wof:name":"Ticonca",
    "wof:placetype":"locality",
    "wof:population":239
},
  "geometry": {"coordinates":[-97.12306,18.69667],"type":"Point"}
}