{
  "type": "Feature",
  "properties": {
    "gn:admin1_code":"28",
    "gn:admin2_code":"16.0",
    "gn:asciiname":"Santa Fe",
    "gn:country_code":"MX",
    "gn:dem":297,
    "gn:feature_class":"P",
    "gn:feature_code":"PPL",
    "gn:name":"Santa Fe",
    "gn:population":0,
    "gn:timezone":"America/Monterrey",
    "iso:country":"MX",
    "name:spa_x_preferred":[
        "Santa Fe"
    ],
    "name:und_x_variant":[
        "Santa F\u00e9"
    ],
    "wof:name":"Santa Fe",
    "wof:placetype":"locality"
},
  "geometry": {"coordinates":[-99.39772000000001,24.15206],"type":"Point"}
}