{
  "type": "Feature",
  "properties": {
    "gn:admin1_code":"6.0",
    "gn:asciiname":"El Paraje",
    "gn:country_code":"MX",
    "gn:dem":1305,
    "gn:feature_class":"P",
    "gn:feature_code":"PPL",
    "gn:name":"El Paraje",
    "gn:population":0,
    "gn:timezone":"America/Chihuahua",
    "iso:country":"MX",
    "name:spa_x_preferred":[
        "El Paraje"
    ],
    "wof:name":"El Paraje",
    "wof:placetype":"locality"
},
  "geometry": {"coordinates":[-107.94756,31.00804],"type":"Point"}
}