{
  "type": "Feature",
  "properties": {
    "gn:admin1_code":"16.0",
    "gn:admin2_code":"38.0",
    "gn:asciiname":"J. David Taitu",
    "gn:country_code":"MX",
    "gn:dem":205,
    "gn:feature_class":"P",
    "gn:feature_code":"PPL",
    "gn:name":"J. David Taitu",
    "gn:population":0,
    "gn:timezone":"America/Mexico_City",
    "iso:country":"MX",
    "wof:name":"J. David Taitu",
    "wof:placetype":"locality"
},
  "geometry": {"coordinates":[-101.08333,18.51667],"type":"Point"}
}