{
  "type": "Feature",
  "properties": {
    "gn:admin1_code":"6",
    "gn:admin2_code":"66",
    "gn:asciiname":"Celayna",
    "gn:country_code":"MX",
    "gn:dem":1661,
    "gn:feature_class":"P",
    "gn:feature_code":"PPL",
    "gn:name":"Celayna",
    "gn:population":12,
    "gn:timezone":"America/Chihuahua",
    "iso:country":"MX",
    "wof:name":"Celayna",
    "wof:placetype":"locality",
    "wof:population":12
},
  "geometry": {"coordinates":[-108.30132999999999,27.90019],"type":"Point"}
}