{
  "type": "Feature",
  "properties": {
    "gn:admin1_code":"7",
    "gn:admin2_code":"4",
    "gn:asciiname":"Los Ranchitos",
    "gn:country_code":"MX",
    "gn:dem":2074,
    "gn:feature_class":"P",
    "gn:feature_code":"PPL",
    "gn:name":"Los Ranchitos",
    "gn:population":25,
    "gn:timezone":"America/Monterrey",
    "iso:country":"MX",
    "wof:name":"Los Ranchitos",
    "wof:placetype":"locality",
    "wof:population":25
},
  "geometry": {"coordinates":[-100.66585000000001,25.33394],"type":"Point"}
}