{
  "type": "Feature",
  "properties": {
    "gn:admin1_code":"1",
    "gn:admin2_code":"5.0",
    "gn:asciiname":"San Mateo",
    "gn:country_code":"MX",
    "gn:dem":1911,
    "gn:feature_class":"P",
    "gn:feature_code":"PPL",
    "gn:name":"San Mateo",
    "gn:population":7,
    "gn:timezone":"America/Mexico_City",
    "iso:country":"MX",
    "wof:name":"San Mateo",
    "wof:placetype":"locality",
    "wof:population":7
},
  "geometry": {"coordinates":[-102.36360999999999,21.92611],"type":"Point"}
}