{
  "type": "Feature",
  "properties": {
    "iso:country":"MX",
    "name:arg_x_preferred":[
        "Centro"
    ],
    "name:cat_x_preferred":[
        "Centro"
    ],
    "name:ceb_x_preferred":[
        "Centro"
    ],
    "name:ces_x_preferred":[
        "Centro"
    ],
    "name:deu_x_preferred":[
        "Centro"
    ],
    "name:ell_x_preferred":[
        "\u039a\u03ad\u03bd\u03c4\u03c1\u03bf"
    ],
    "name:epo_x_preferred":[
        "Centro"
    ],
    "name:eus_x_preferred":[
        "Centro"
    ],
    "name:fra_x_preferred":[
        "Centro"
    ],
    "name:glg_x_preferred":[
        "Centro"
    ],
    "name:ido_x_preferred":[
        "Centro"
    ],
    "name:ita_x_preferred":[
        "Centro"
    ],
    "name:jpn_x_preferred":[
        "\u30bb\u30f3\u30c8\u30ed"
    ],
    "name:kor_x_preferred":[
        "\uc13c\ud2b8\ub85c"
    ],
    "name:nld_x_preferred":[
        "Centro"
    ],
    "name:pol_x_preferred":[
        "Centro"
    ],
    "name:por_x_preferred":[
        "Centro"
    ],
    "name:rus_x_preferred":[
        "\u0421\u0435\u043d\u0442\u0440\u043e"
    ],
    "name:sco_x_preferred":[
        "Centro"
    ],
    "name:slk_x_preferred":[
        "Centro"
    ],
    "name:spa_x_preferred":[
        "Centro"
    ],
    "name:srp_x_preferred":[
        "Centro"
    ],
    "name:swe_x_preferred":[
        "Centro"
    ],
    "name:vie_x_preferred":[
        "Centro"
    ],
    "qs:gn_adm0_cc":"MX",
    "qs:gn_local":3530103,
    "qs:gn_nam_loc":"san miguel de cozumel",
    "qs:gn_namadm1":"23",
    "qs:local_max":3537,
    "qs:local_sum":9431,
    "qs:localhoods":6,
    "qs:name":"Centro",
    "qs:name_adm0":"M\u00e9xico",
    "qs:name_adm1":"Quintana Roo",
    "qs:name_adm2":"Cozumel",
    "qs:name_local":"San Miguel de Cozumel",
    "qs:photo_max":778,
    "qs:photo_sum":3537,
    "qs:placetype":"Suburb",
    "qs:quad_count":44,
    "qs:woe_adm0":23424900,
    "qs:woe_adm1":2346286,
    "qs:woe_adm2":12601463,
    "qs:woe_lau":0,
    "qs:woe_local":144625,
    "qs:woe_ver":"7.10.0",
    "wof:lang":[
        "spa"
    ],
    "wof:name":"Centro",
    "wof:placetype":"neighbourhood"
},
  "geometry": {"coordinates":[-86.951003,20.507551],"type":"Point"}
}