{
  "type": "Feature",
  "properties": {
    "iso:country":"MX",
    "name:spa_x_preferred":[
        "Centro"
    ],
    "name:unk_x_variant":[
        "Centro"
    ],
    "qs:gn_adm0_cc":"MX",
    "qs:gn_local":3530103,
    "qs:gn_nam_loc":"san miguel de cozumel",
    "qs:gn_namadm1":"23",
    "qs:local_max":3537,
    "qs:local_sum":9431,
    "qs:localhoods":6,
    "qs:name":"Centro",
    "qs:name_adm0":"M\u00e9xico",
    "qs:name_adm1":"Quintana Roo",
    "qs:name_adm2":"Cozumel",
    "qs:name_local":"San Miguel de Cozumel",
    "qs:photo_max":778,
    "qs:photo_sum":3537,
    "qs:placetype":"Suburb",
    "qs:quad_count":44,
    "qs:woe_adm0":23424900,
    "qs:woe_adm1":2346286,
    "qs:woe_adm2":12601463,
    "qs:woe_lau":0,
    "qs:woe_local":144625,
    "qs:woe_ver":"7.10.0",
    "wof:lang":[
        "spa"
    ],
    "wof:name":"Centro",
    "wof:placetype":"neighbourhood"
},
  "geometry": {"coordinates":[-86.951003,20.507551],"type":"Point"}
}