{
  "type": "Feature",
  "properties": {
    "gn:admin1_code":"14",
    "gn:admin2_code":"93.0",
    "gn:asciiname":"Callejon Colorado",
    "gn:country_code":"MX",
    "gn:dem":1992,
    "gn:feature_class":"P",
    "gn:feature_code":"PPL",
    "gn:name":"Callej\u00f3n Colorado",
    "gn:population":8,
    "gn:timezone":"America/Mexico_City",
    "iso:country":"MX",
    "name:und_x_variant":[
        "Callej\u00f3n Colorado"
    ],
    "wof:name":"Callejon Colorado",
    "wof:placetype":"locality",
    "wof:population":8
},
  "geometry": {"coordinates":[-102.63527999999999,20.8625],"type":"Point"}
}