{
  "type": "Feature",
  "properties": {
    "gn:admin1_code":"20",
    "gn:admin2_code":"184",
    "gn:asciiname":"La Montana",
    "gn:country_code":"MX",
    "gn:dem":111,
    "gn:feature_class":"P",
    "gn:feature_code":"PPL",
    "gn:name":"La Monta\u00f1a",
    "gn:population":51,
    "gn:timezone":"America/Mexico_City",
    "iso:country":"MX",
    "name:und_x_variant":[
        "La Monta\u00f1a"
    ],
    "wof:name":"La Montana",
    "wof:placetype":"locality",
    "wof:population":51
},
  "geometry": {"coordinates":[-95.90667000000001,17.84083],"type":"Point"}
}