{
  "type": "Feature",
  "properties": {
    "gn:admin1_code":"5.0",
    "gn:admin2_code":"71.0",
    "gn:asciiname":"Monte Flor Abajo",
    "gn:country_code":"MX",
    "gn:dem":377,
    "gn:feature_class":"P",
    "gn:feature_code":"PPL",
    "gn:name":"Monte Flor Abajo",
    "gn:population":0,
    "gn:timezone":"America/Mexico_City",
    "iso:country":"MX",
    "name:spa_x_preferred":[
        "Monte Flor Abajo"
    ],
    "wof:name":"Monte Flor Abajo",
    "wof:placetype":"locality"
},
  "geometry": {"coordinates":[-92.58722,15.31118],"type":"Point"}
}