{
  "type": "Feature",
  "properties": {
    "gn:admin1_code":"5",
    "gn:admin2_code":"100.0",
    "gn:asciiname":"Flor de Cafe",
    "gn:country_code":"MX",
    "gn:dem":551,
    "gn:feature_class":"P",
    "gn:feature_code":"PPL",
    "gn:name":"Flor de Caf\u00e9",
    "gn:population":251,
    "gn:timezone":"America/Mexico_City",
    "iso:country":"MX",
    "name:und_x_variant":[
        "Flor de Caf\u00e9"
    ],
    "wof:name":"Flor de Cafe",
    "wof:placetype":"locality",
    "wof:population":251
},
  "geometry": {"coordinates":[-92.26833000000001,17.32777999999999],"type":"Point"}
}