{
  "type": "Feature",
  "properties": {
    "gn:admin1_code":"12",
    "gn:admin2_code":"32.0",
    "gn:asciiname":"Tetela del Rio",
    "gn:country_code":"MX",
    "gn:dem":371,
    "gn:feature_class":"P",
    "gn:feature_code":"PPL",
    "gn:name":"Tetela del R\u00edo",
    "gn:population":0,
    "gn:timezone":"America/Mexico_City",
    "iso:country":"MX",
    "name:spa_x_preferred":[
        "Tetela del R\u00edo"
    ],
    "wof:name":"Tetela del Rio",
    "wof:placetype":"locality"
},
  "geometry": {"coordinates":[-100.07857,17.98125],"type":"Point"}
}