{
  "type": "Feature",
  "properties": {
    "gn:admin1_code":"28.0",
    "gn:admin2_code":"32.0",
    "gn:asciiname":"El Sinai",
    "gn:country_code":"MX",
    "gn:dem":39,
    "gn:feature_class":"P",
    "gn:feature_code":"PPL",
    "gn:name":"El Sina\u00ed",
    "gn:population":0,
    "gn:timezone":"America/Matamoros",
    "iso:country":"MX",
    "name:spa_x_preferred":[
        "El Sina\u00ed"
    ],
    "name:und_x_variant":[
        "Sina\u00ed"
    ],
    "wof:name":"El Sinai",
    "wof:placetype":"locality"
},
  "geometry": {"coordinates":[-98.39485999999999,26.16261],"type":"Point"}
}