{
  "type": "Feature",
  "properties": {
    "gn:admin1_code":"6.0",
    "gn:admin2_code":"36.0",
    "gn:asciiname":"Asunsolo",
    "gn:country_code":"MX",
    "gn:dem":1297,
    "gn:feature_class":"P",
    "gn:feature_code":"PPL",
    "gn:name":"As\u00fansolo",
    "gn:population":0,
    "gn:timezone":"America/Chihuahua",
    "iso:country":"MX",
    "name:spa_x_preferred":[
        "As\u00fansolo"
    ],
    "name:und_x_variant":[
        "As\u00fansulo"
    ],
    "wof:name":"Asunsolo",
    "wof:placetype":"locality"
},
  "geometry": {"coordinates":[-104.41054,26.80162],"type":"Point"}
}