{
  "type": "Feature",
  "properties": {
    "gn:admin1_code":"7",
    "gn:admin2_code":"14.0",
    "gn:asciiname":"Emiliano Zapata (Santa Elena)",
    "gn:country_code":"MX",
    "gn:dem":320,
    "gn:feature_class":"P",
    "gn:feature_code":"PPL",
    "gn:name":"Emiliano Zapata (Santa Elena)",
    "gn:population":140,
    "gn:timezone":"America/Monterrey",
    "iso:country":"MX",
    "wof:name":"Emiliano Zapata (Santa Elena)",
    "wof:placetype":"locality",
    "wof:population":140
},
  "geometry": {"coordinates":[-100.85945,29.02218],"type":"Point"}
}