{
  "type": "Feature",
  "properties": {
    "gn:admin1_code":"6",
    "gn:admin2_code":"27.0",
    "gn:asciiname":"Samuchichi",
    "gn:country_code":"MX",
    "gn:dem":2201,
    "gn:feature_class":"P",
    "gn:feature_code":"PPL",
    "gn:name":"Samuchichi",
    "gn:population":0,
    "gn:timezone":"America/Chihuahua",
    "iso:country":"MX",
    "name:spa_x_preferred":[
        "Samuchichi"
    ],
    "wof:name":"Samuchichi",
    "wof:placetype":"locality"
},
  "geometry": {"coordinates":[-107.10216,27.2593],"type":"Point"}
}