{
  "type": "Feature",
  "properties": {
    "gn:admin1_code":"26",
    "gn:admin2_code":"30.0",
    "gn:asciiname":"San Luis",
    "gn:country_code":"MX",
    "gn:dem":204,
    "gn:feature_class":"P",
    "gn:feature_code":"PPL",
    "gn:name":"San Luis",
    "gn:population":8,
    "gn:timezone":"America/Hermosillo",
    "iso:country":"MX",
    "name:spa_x_preferred":[
        "San Luis"
    ],
    "name:spa_x_variant":[
        "Rancho San Luis"
    ],
    "wof:name":"San Luis",
    "wof:placetype":"locality",
    "wof:population":8
},
  "geometry": {"coordinates":[-110.97814,28.73395],"type":"Point"}
}