{
  "type": "Feature",
  "properties": {
    "gn:admin1_code":"32",
    "gn:admin2_code":"20.0",
    "gn:asciiname":"Santa Clara (Colonia Alvaro Obregon)",
    "gn:country_code":"MX",
    "gn:dem":2101,
    "gn:feature_class":"P",
    "gn:feature_code":"PPL",
    "gn:name":"Santa Clara (Colonia \u00c1lvaro Obreg\u00f3n)",
    "gn:population":72,
    "gn:timezone":"America/Mexico_City",
    "iso:country":"MX",
    "name:und_x_variant":[
        "Santa Clara (Colonia \u00c1lvaro Obreg\u00f3n)"
    ],
    "wof:name":"Santa Clara (Colonia Alvaro Obregon)",
    "wof:placetype":"locality",
    "wof:population":72
},
  "geometry": {"coordinates":[-102.87027999999999,22.65611],"type":"Point"}
}