{
  "type": "Feature",
  "properties": {
    "gn:admin1_code":"30.0",
    "gn:admin2_code":"155.0",
    "gn:asciiname":"Sombrerillo",
    "gn:country_code":"MX",
    "gn:dem":125,
    "gn:feature_class":"P",
    "gn:feature_code":"PPL",
    "gn:name":"Sombrerillo",
    "gn:population":266,
    "gn:timezone":"America/Mexico_City",
    "iso:country":"MX",
    "name:spa_x_preferred":[
        "Sombrerillo"
    ],
    "wof:name":"Sombrerillo",
    "wof:placetype":"locality",
    "wof:population":266
},
  "geometry": {"coordinates":[-98.26472,21.30944],"type":"Point"}
}