{
  "type": "Feature",
  "properties": {
    "gn:admin1_code":"26",
    "gn:admin2_code":"55.0",
    "gn:asciiname":"La Mora",
    "gn:country_code":"MX",
    "gn:dem":27,
    "gn:feature_class":"P",
    "gn:feature_code":"PPL",
    "gn:name":"La Mora",
    "gn:population":5,
    "gn:timezone":"America/Hermosillo",
    "iso:country":"MX",
    "wof:name":"La Mora",
    "wof:placetype":"locality",
    "wof:population":5
},
  "geometry": {"coordinates":[-114.8075,32.48417],"type":"Point"}
}