{
  "type": "Feature",
  "properties": {
    "gn:admin1_code":"5",
    "gn:admin2_code":"76",
    "gn:asciiname":"Anexo Berriozabal",
    "gn:country_code":"MX",
    "gn:dem":393,
    "gn:feature_class":"P",
    "gn:feature_code":"PPL",
    "gn:name":"Anexo Berrioz\u00e1bal",
    "gn:population":23,
    "gn:timezone":"America/Mexico_City",
    "iso:country":"MX",
    "name:und_x_variant":[
        "Anexo Berrioz\u00e1bal"
    ],
    "wof:name":"Anexo Berriozabal",
    "wof:placetype":"locality",
    "wof:population":23
},
  "geometry": {"coordinates":[-92.58556,17.29806],"type":"Point"}
}