{
  "type": "Feature",
  "properties": {
    "gn:admin1_code":"16",
    "gn:admin2_code":"9",
    "gn:asciiname":"El Timbinal",
    "gn:country_code":"MX",
    "gn:dem":2067,
    "gn:feature_class":"P",
    "gn:feature_code":"PPL",
    "gn:name":"El Timbinal",
    "gn:population":17,
    "gn:timezone":"America/Mexico_City",
    "iso:country":"MX",
    "wof:name":"El Timbinal",
    "wof:placetype":"locality",
    "wof:population":17
},
  "geometry": {"coordinates":[-101.72667,19.25972],"type":"Point"}
}