{
  "type": "Feature",
  "properties": {
    "gn:admin1_code":"25.0",
    "gn:admin2_code":"6.0",
    "gn:asciiname":"La Lajita",
    "gn:country_code":"MX",
    "gn:dem":255,
    "gn:feature_class":"P",
    "gn:feature_code":"PPL",
    "gn:name":"La Lajita",
    "gn:population":0,
    "gn:timezone":"America/Mazatlan",
    "iso:country":"MX",
    "name:spa_x_preferred":[
        "La Lajita"
    ],
    "name:und_x_variant":[
        "Rancho La Lajita"
    ],
    "wof:name":"La Lajita",
    "wof:placetype":"locality"
},
  "geometry": {"coordinates":[-107.27705,25.11413],"type":"Point"}
}