{
  "type": "Feature",
  "properties": {
    "gn:admin1_code":"25",
    "gn:admin2_code":"3.0",
    "gn:asciiname":"San Juanico",
    "gn:country_code":"MX",
    "gn:dem":318,
    "gn:feature_class":"P",
    "gn:feature_code":"PPL",
    "gn:name":"San Juanico",
    "gn:population":0,
    "gn:timezone":"America/Mazatlan",
    "iso:country":"MX",
    "name:spa_x_preferred":[
        "San Juanico"
    ],
    "wof:name":"San Juanico",
    "wof:placetype":"locality"
},
  "geometry": {"coordinates":[-107.52615,25.46925],"type":"Point"}
}