{
  "type": "Feature",
  "properties": {
    "gn:admin1_code":"12.0",
    "gn:admin2_code":"57.0",
    "gn:asciiname":"La Martha",
    "gn:country_code":"MX",
    "gn:dem":500,
    "gn:feature_class":"P",
    "gn:feature_code":"PPL",
    "gn:name":"La Martha",
    "gn:population":0,
    "gn:timezone":"America/Mexico_City",
    "iso:country":"MX",
    "name:spa_x_preferred":[
        "La Martha"
    ],
    "wof:name":"La Martha",
    "wof:placetype":"locality"
},
  "geometry": {"coordinates":[-100.72481999999999,17.30079],"type":"Point"}
}