{
  "type": "Feature",
  "properties": {
    "gn:admin1_code":"14",
    "gn:admin2_code":"86.0",
    "gn:asciiname":"Tlacuache",
    "gn:country_code":"MX",
    "gn:dem":1801,
    "gn:feature_class":"P",
    "gn:feature_code":"PPL",
    "gn:name":"Tlacuache",
    "gn:population":0,
    "gn:timezone":"America/Mexico_City",
    "iso:country":"MX",
    "wof:name":"Tlacuache",
    "wof:placetype":"locality"
},
  "geometry": {"coordinates":[-103.84999999999999,19.95],"type":"Point"}
}