{
  "type": "Feature",
  "properties": {
    "gn:admin1_code":"27",
    "gn:admin2_code":"4.0",
    "gn:asciiname":"Acachapan y Colmena Primera Seccion",
    "gn:country_code":"MX",
    "gn:dem":6,
    "gn:feature_class":"P",
    "gn:feature_code":"PPL",
    "gn:name":"Acachapan y Colmena Primera Secci\u00f3n",
    "gn:population":0,
    "gn:timezone":"America/Mexico_City",
    "iso:country":"MX",
    "name:spa_x_preferred":[
        "Acachapan y Colmena Primera Secci\u00f3n"
    ],
    "name:spa_x_variant":[
        "Acachapan"
    ],
    "wof:name":"Acachapan y Colmena Primera Seccion",
    "wof:placetype":"locality"
},
  "geometry": {"coordinates":[-92.8784,18.00902],"type":"Point"}
}