{
  "type": "Feature",
  "properties": {
    "gn:admin1_code":"6",
    "gn:admin2_code":"45.0",
    "gn:asciiname":"Rancho Santo Nino",
    "gn:country_code":"MX",
    "gn:dem":1132,
    "gn:feature_class":"P",
    "gn:feature_code":"PPL",
    "gn:name":"Rancho Santo Ni\u00f1o",
    "gn:population":5,
    "gn:timezone":"America/Chihuahua",
    "iso:country":"MX",
    "name:und_x_variant":[
        "Rancho Santo Ni\u00f1o"
    ],
    "wof:name":"Rancho Santo Nino",
    "wof:placetype":"locality",
    "wof:population":5
},
  "geometry": {"coordinates":[-105.46644999999999,28.34033],"type":"Point"}
}