{
  "type": "Feature",
  "properties": {
    "gn:admin1_code":"13.0",
    "gn:admin2_code":"28.0",
    "gn:asciiname":"Temaxcaltitla",
    "gn:country_code":"MX",
    "gn:dem":375,
    "gn:feature_class":"P",
    "gn:feature_code":"PPL",
    "gn:name":"Temaxcaltitla",
    "gn:population":229,
    "gn:timezone":"America/Mexico_City",
    "iso:country":"MX",
    "name:spa_x_preferred":[
        "Temaxcaltitla"
    ],
    "wof:name":"Temaxcaltitla",
    "wof:placetype":"locality",
    "wof:population":229
},
  "geometry": {"coordinates":[-98.51389,21.11111],"type":"Point"}
}