{
  "type": "Feature",
  "properties": {
    "gn:admin1_code":"20",
    "gn:admin2_code":"327.0",
    "gn:asciiname":"Murcielago",
    "gn:country_code":"MX",
    "gn:dem":59,
    "gn:feature_class":"P",
    "gn:feature_code":"PPL",
    "gn:name":"Murci\u00e9lago",
    "gn:population":0,
    "gn:timezone":"America/Mexico_City",
    "iso:country":"MX",
    "wof:name":"Murcielago",
    "wof:placetype":"locality"
},
  "geometry": {"coordinates":[-94.16667,16.31667],"type":"Point"}
}