{
  "type": "Feature",
  "properties": {
    "gn:admin1_code":"11",
    "gn:admin2_code":"14.0",
    "gn:asciiname":"La Laborcilla de Arriba",
    "gn:country_code":"MX",
    "gn:dem":2097,
    "gn:feature_class":"P",
    "gn:feature_code":"PPL",
    "gn:name":"La Laborcilla de Arriba",
    "gn:population":99,
    "gn:timezone":"America/Mexico_City",
    "iso:country":"MX",
    "wof:name":"La Laborcilla de Arriba",
    "wof:placetype":"locality",
    "wof:population":99
},
  "geometry": {"coordinates":[-101.10083,21.19278],"type":"Point"}
}