{
  "type": "Feature",
  "properties": {
    "gn:admin1_code":"28",
    "gn:admin2_code":"43.0",
    "gn:asciiname":"Ampliacion Beatriz Anaya",
    "gn:country_code":"MX",
    "gn:dem":90,
    "gn:feature_class":"P",
    "gn:feature_code":"PPL",
    "gn:name":"Ampliaci\u00f3n Beatriz Anaya",
    "gn:population":9,
    "gn:timezone":"America/Monterrey",
    "iso:country":"MX",
    "name:und_x_variant":[
        "Ampliaci\u00f3n Beatriz Anaya"
    ],
    "wof:name":"Ampliacion Beatriz Anaya",
    "wof:placetype":"locality",
    "wof:population":9
},
  "geometry": {"coordinates":[-98.95444000000001,22.98806],"type":"Point"}
}