{
  "type": "Feature",
  "properties": {
    "gn:admin1_code":"16",
    "gn:admin2_code":"57.0",
    "gn:asciiname":"Apicho",
    "gn:country_code":"MX",
    "gn:dem":685,
    "gn:feature_class":"P",
    "gn:feature_code":"PPL",
    "gn:name":"Apicho",
    "gn:population":0,
    "gn:timezone":"America/Mexico_City",
    "iso:country":"MX",
    "name:spa_x_preferred":[
        "Apicho"
    ],
    "wof:name":"Apicho",
    "wof:placetype":"locality"
},
  "geometry": {"coordinates":[-101.21073,19.04506],"type":"Point"}
}