{
  "type": "Feature",
  "properties": {
    "gn:admin1_code":"6",
    "gn:admin2_code":"45",
    "gn:asciiname":"El Ranchito",
    "gn:country_code":"MX",
    "gn:dem":1126,
    "gn:feature_class":"P",
    "gn:feature_code":"PPL",
    "gn:name":"El Ranchito",
    "gn:population":39,
    "gn:timezone":"America/Chihuahua",
    "iso:country":"MX",
    "wof:name":"El Ranchito",
    "wof:placetype":"locality",
    "wof:population":39
},
  "geometry": {"coordinates":[-105.40713999999998,28.33909],"type":"Point"}
}