{
  "type": "Feature",
  "properties": {
    "gn:admin1_code":"30",
    "gn:admin2_code":"21",
    "gn:asciiname":"Nogales",
    "gn:country_code":"MX",
    "gn:dem":940,
    "gn:feature_class":"P",
    "gn:feature_code":"PPL",
    "gn:name":"Nogales",
    "gn:population":50,
    "gn:timezone":"America/Mexico_City",
    "iso:country":"MX",
    "wof:name":"Nogales",
    "wof:placetype":"locality",
    "wof:population":50
},
  "geometry": {"coordinates":[-96.83333,18.95972],"type":"Point"}
}