{
  "type": "Feature",
  "properties": {
    "gn:admin1_code":"4.0",
    "gn:admin2_code":"3.0",
    "gn:asciiname":"La Salada",
    "gn:country_code":"MX",
    "gn:dem":-2,
    "gn:feature_class":"P",
    "gn:feature_code":"PPL",
    "gn:name":"La Salada",
    "gn:population":0,
    "gn:timezone":"America/Merida",
    "iso:country":"MX",
    "name:spa_x_preferred":[
        "La Salada"
    ],
    "wof:name":"La Salada",
    "wof:placetype":"locality"
},
  "geometry": {"coordinates":[-91.06305999999999,18.93508],"type":"Point"}
}