{
  "type": "Feature",
  "properties": {
    "gn:admin1_code":"12.0",
    "gn:admin2_code":"38.0",
    "gn:asciiname":"Carboneras",
    "gn:country_code":"MX",
    "gn:dem":1422,
    "gn:feature_class":"P",
    "gn:feature_code":"PPL",
    "gn:name":"Carboneras",
    "gn:population":0,
    "gn:timezone":"America/Mexico_City",
    "iso:country":"MX",
    "wof:name":"Carboneras",
    "wof:placetype":"locality"
},
  "geometry": {"coordinates":[-101.30741,18.04397],"type":"Point"}
}