{
  "type": "Feature",
  "properties": {
    "gn:admin1_code":"26.0",
    "gn:admin2_code":"66.0",
    "gn:asciiname":"Las Burras",
    "gn:country_code":"MX",
    "gn:dem":561,
    "gn:feature_class":"P",
    "gn:feature_code":"PPL",
    "gn:name":"Las Burras",
    "gn:population":0,
    "gn:timezone":"America/Hermosillo",
    "iso:country":"MX",
    "name:spa_x_preferred":[
        "Las Burras"
    ],
    "wof:name":"Las Burras",
    "wof:placetype":"locality"
},
  "geometry": {"coordinates":[-110.26687,29.28263],"type":"Point"}
}