{
  "type": "Feature",
  "properties": {
    "gn:admin1_code":"6",
    "gn:admin2_code":"9",
    "gn:asciiname":"Napuchis",
    "gn:country_code":"MX",
    "gn:dem":2388,
    "gn:feature_class":"P",
    "gn:feature_code":"PPL",
    "gn:name":"Napuchis",
    "gn:population":26,
    "gn:timezone":"America/Chihuahua",
    "iso:country":"MX",
    "wof:name":"Napuchis",
    "wof:placetype":"locality",
    "wof:population":26
},
  "geometry": {"coordinates":[-107.56965,27.68992],"type":"Point"}
}