{
  "type": "Feature",
  "properties": {
    "gn:admin1_code":"5",
    "gn:admin2_code":"26.0",
    "gn:asciiname":"Carmelita Atzam",
    "gn:country_code":"MX",
    "gn:dem":1582,
    "gn:feature_class":"P",
    "gn:feature_code":"PPL",
    "gn:name":"Carmelita Atzam",
    "gn:population":77,
    "gn:timezone":"America/Mexico_City",
    "iso:country":"MX",
    "wof:name":"Carmelita Atzam",
    "wof:placetype":"locality",
    "wof:population":77
},
  "geometry": {"coordinates":[-92.62917,16.88194],"type":"Point"}
}