{
  "type": "Feature",
  "properties": {
    "gn:admin1_code":"16",
    "gn:admin2_code":"8",
    "gn:asciiname":"El Garrote",
    "gn:country_code":"MX",
    "gn:dem":553,
    "gn:feature_class":"P",
    "gn:feature_code":"PPL",
    "gn:name":"El Garrote",
    "gn:population":16,
    "gn:timezone":"America/Mexico_City",
    "iso:country":"MX",
    "wof:name":"El Garrote",
    "wof:placetype":"locality",
    "wof:population":16
},
  "geometry": {"coordinates":[-103.40694000000001,18.5325],"type":"Point"}
}