{
  "type": "Feature",
  "properties": {
    "gn:admin1_code":"5",
    "gn:admin2_code":"19.0",
    "gn:asciiname":"La Floresta",
    "gn:country_code":"MX",
    "gn:dem":2177,
    "gn:feature_class":"P",
    "gn:feature_code":"PPL",
    "gn:name":"La Floresta",
    "gn:population":0,
    "gn:timezone":"America/Mexico_City",
    "iso:country":"MX",
    "name:spa_x_preferred":[
        "La Floresta"
    ],
    "wof:name":"La Floresta",
    "wof:placetype":"locality"
},
  "geometry": {"coordinates":[-92.31251,16.50915],"type":"Point"}
}