{
  "type": "Feature",
  "properties": {
    "gn:admin1_code":"25",
    "gn:admin2_code":"6",
    "gn:asciiname":"Campo Silvia",
    "gn:country_code":"MX",
    "gn:dem":14,
    "gn:feature_class":"P",
    "gn:feature_code":"PPL",
    "gn:name":"Campo Silvia",
    "gn:population":22,
    "gn:timezone":"America/Mazatlan",
    "iso:country":"MX",
    "wof:name":"Campo Silvia",
    "wof:placetype":"locality",
    "wof:population":22
},
  "geometry": {"coordinates":[-107.47595,24.65079],"type":"Point"}
}