{
  "type": "Feature",
  "properties": {
    "gn:admin1_code":"4.0",
    "gn:asciiname":"La Lucha",
    "gn:country_code":"MX",
    "gn:dem":16,
    "gn:feature_class":"P",
    "gn:feature_code":"PPL",
    "gn:name":"La Lucha",
    "gn:population":0,
    "gn:timezone":"America/Merida",
    "iso:country":"MX",
    "name:spa_x_preferred":[
        "La Lucha"
    ],
    "wof:name":"La Lucha",
    "wof:placetype":"locality"
},
  "geometry": {"coordinates":[-91.36557000000001,18.08803],"type":"Point"}
}