{
  "type": "Feature",
  "properties": {
    "gn:admin1_code":"2",
    "gn:admin2_code":"3",
    "gn:asciiname":"Los Perez",
    "gn:country_code":"MX",
    "gn:dem":1298,
    "gn:feature_class":"P",
    "gn:feature_code":"PPL",
    "gn:name":"Los P\u00e9rez",
    "gn:population":10,
    "gn:timezone":"America/Tijuana",
    "iso:country":"MX",
    "name:und_x_variant":[
        "Los P\u00e9rez"
    ],
    "wof:name":"Los Perez",
    "wof:placetype":"locality",
    "wof:population":10
},
  "geometry": {"coordinates":[-116.16194,32.45833],"type":"Point"}
}