{
  "type": "Feature",
  "properties": {
    "gn:admin1_code":"30.0",
    "gn:admin2_code":"114.0",
    "gn:asciiname":"Chamalote",
    "gn:country_code":"MX",
    "gn:dem":23,
    "gn:feature_class":"P",
    "gn:feature_code":"PPL",
    "gn:name":"Chamalote",
    "gn:population":1,
    "gn:timezone":"America/Mexico_City",
    "iso:country":"MX",
    "name:spa_x_preferred":[
        "Chamalote"
    ],
    "wof:name":"Chamalote",
    "wof:placetype":"locality",
    "wof:population":1
},
  "geometry": {"coordinates":[-96.81361,20.12917],"type":"Point"}
}