{
  "type": "Feature",
  "properties": {
    "gn:admin1_code":"5",
    "gn:admin2_code":"6.0",
    "gn:asciiname":"Miguel Hidalgo",
    "gn:country_code":"MX",
    "gn:dem":1503,
    "gn:feature_class":"P",
    "gn:feature_code":"PPL",
    "gn:name":"Miguel Hidalgo",
    "gn:population":767,
    "gn:timezone":"America/Mexico_City",
    "iso:country":"MX",
    "wof:name":"Miguel Hidalgo",
    "wof:placetype":"locality",
    "wof:population":767
},
  "geometry": {"coordinates":[-92.09657,15.51353],"type":"Point"}
}