{
  "type": "Feature",
  "properties": {
    "gn:admin1_code":"14.0",
    "gn:admin2_code":"94.0",
    "gn:asciiname":"Choloaca",
    "gn:country_code":"MX",
    "gn:dem":1302,
    "gn:feature_class":"P",
    "gn:feature_code":"PPL",
    "gn:name":"Choloaca",
    "gn:population":0,
    "gn:timezone":"America/Mexico_City",
    "iso:country":"MX",
    "name:spa_x_preferred":[
        "Choloaca"
    ],
    "wof:name":"Choloaca",
    "wof:placetype":"locality"
},
  "geometry": {"coordinates":[-103.8443,20.86233],"type":"Point"}
}