{
  "type": "Feature",
  "properties": {
    "gn:admin1_code":"26.0",
    "gn:admin2_code":"21.0",
    "gn:asciiname":"La Citacota",
    "gn:country_code":"MX",
    "gn:dem":413,
    "gn:feature_class":"P",
    "gn:feature_code":"PPL",
    "gn:name":"La Citacota",
    "gn:population":0,
    "gn:timezone":"America/Hermosillo",
    "iso:country":"MX",
    "name:spa_x_preferred":[
        "La Citacota"
    ],
    "name:und_x_variant":[
        "Rancho La Citacota",
        "Citacota"
    ],
    "wof:name":"La Citacota",
    "wof:placetype":"locality"
},
  "geometry": {"coordinates":[-110.2979,28.82783],"type":"Point"}
}