{
  "type": "Feature",
  "properties": {
    "gn:admin1_code":"3",
    "gn:admin2_code":"1.0",
    "gn:asciiname":"Galeana Lote 15",
    "gn:country_code":"MX",
    "gn:dem":53,
    "gn:feature_class":"P",
    "gn:feature_code":"PPL",
    "gn:name":"Galeana Lote 15",
    "gn:population":8,
    "gn:timezone":"America/Mazatlan",
    "iso:country":"MX",
    "wof:name":"Galeana Lote 15",
    "wof:placetype":"locality",
    "wof:population":8
},
  "geometry": {"coordinates":[-111.69712,25.36343],"type":"Point"}
}