{
  "type": "Feature",
  "properties": {
    "gn:admin1_code":"26",
    "gn:admin2_code":"30.0",
    "gn:asciiname":"Bebelama",
    "gn:country_code":"MX",
    "gn:dem":168,
    "gn:feature_class":"P",
    "gn:feature_code":"PPL",
    "gn:name":"Bebelama",
    "gn:population":0,
    "gn:timezone":"America/Hermosillo",
    "iso:country":"MX",
    "name:spa_x_preferred":[
        "Bebelama"
    ],
    "name:und_x_variant":[
        "Rancho La Bebelama"
    ],
    "wof:name":"Bebelama",
    "wof:placetype":"locality"
},
  "geometry": {"coordinates":[-111.06489000000001,29.0162],"type":"Point"}
}