{
  "type": "Feature",
  "properties": {
    "gn:admin1_code":"30.0",
    "gn:admin2_code":"133.0",
    "gn:asciiname":"El Ojital",
    "gn:country_code":"MX",
    "gn:dem":6,
    "gn:feature_class":"P",
    "gn:feature_code":"PPL",
    "gn:name":"El Ojital",
    "gn:population":63,
    "gn:timezone":"America/Mexico_City",
    "iso:country":"MX",
    "name:spa_x_preferred":[
        "El Ojital"
    ],
    "wof:name":"El Ojital",
    "wof:placetype":"locality",
    "wof:population":63
},
  "geometry": {"coordinates":[-98.04940999999999,22.14112],"type":"Point"}
}