{
  "type": "Feature",
  "properties": {
    "gn:admin1_code":"32",
    "gn:admin2_code":"33.0",
    "gn:asciiname":"Las Codornices",
    "gn:country_code":"MX",
    "gn:dem":1539,
    "gn:feature_class":"P",
    "gn:feature_code":"PPL",
    "gn:name":"Las Codornices",
    "gn:population":9,
    "gn:timezone":"America/Mexico_City",
    "iso:country":"MX",
    "wof:name":"Las Codornices",
    "wof:placetype":"locality",
    "wof:population":9
},
  "geometry": {"coordinates":[-103.13889,21.09083],"type":"Point"}
}