{
  "type": "Feature",
  "properties": {
    "gn:admin1_code":"27",
    "gn:admin2_code":"3.0",
    "gn:asciiname":"El Faisan",
    "gn:country_code":"MX",
    "gn:dem":2,
    "gn:feature_class":"P",
    "gn:feature_code":"PPL",
    "gn:name":"El Fais\u00e1n",
    "gn:population":0,
    "gn:timezone":"America/Mexico_City",
    "iso:country":"MX",
    "name:spa_x_preferred":[
        "El Fais\u00e1n"
    ],
    "wof:name":"El Faisan",
    "wof:placetype":"locality"
},
  "geometry": {"coordinates":[-92.72248999999999,18.53734],"type":"Point"}
}