{
  "type": "Feature",
  "properties": {
    "gn:admin1_code":"16",
    "gn:admin2_code":"34.0",
    "gn:asciiname":"La Guacamaya",
    "gn:country_code":"MX",
    "gn:dem":2510,
    "gn:feature_class":"P",
    "gn:feature_code":"PPL",
    "gn:name":"La Guacamaya",
    "gn:population":0,
    "gn:timezone":"America/Mexico_City",
    "iso:country":"MX",
    "name:spa_x_preferred":[
        "La Guacamaya"
    ],
    "wof:name":"La Guacamaya",
    "wof:placetype":"locality"
},
  "geometry": {"coordinates":[-100.71203,19.48594],"type":"Point"}
}