{
  "type": "Feature",
  "properties": {
    "gn:admin1_code":"14.0",
    "gn:admin2_code":"17.0",
    "gn:asciiname":"El Colomito",
    "gn:country_code":"MX",
    "gn:dem":1390,
    "gn:feature_class":"P",
    "gn:feature_code":"PPL",
    "gn:name":"El Colomito",
    "gn:population":0,
    "gn:timezone":"America/Mexico_City",
    "iso:country":"MX",
    "name:spa_x_preferred":[
        "El Colomito"
    ],
    "wof:name":"El Colomito",
    "wof:placetype":"locality"
},
  "geometry": {"coordinates":[-104.39377,19.99382],"type":"Point"}
}