{
  "type": "Feature",
  "properties": {
    "gn:admin1_code":"17",
    "gn:admin2_code":"15.0",
    "gn:asciiname":"El Amate Amarillo",
    "gn:country_code":"MX",
    "gn:dem":1122,
    "gn:feature_class":"P",
    "gn:feature_code":"PPL",
    "gn:name":"El Amate Amarillo",
    "gn:population":6,
    "gn:timezone":"America/Mexico_City",
    "iso:country":"MX",
    "wof:name":"El Amate Amarillo",
    "wof:placetype":"locality",
    "wof:population":6
},
  "geometry": {"coordinates":[-99.30833,18.79056],"type":"Point"}
}