{
  "type": "Feature",
  "properties": {
    "gn:admin1_code":"5",
    "gn:admin2_code":"31",
    "gn:asciiname":"Nueva Esperanza",
    "gn:country_code":"MX",
    "gn:dem":1285,
    "gn:feature_class":"P",
    "gn:feature_code":"PPL",
    "gn:name":"Nueva Esperanza",
    "gn:population":32,
    "gn:timezone":"America/Mexico_City",
    "iso:country":"MX",
    "wof:name":"Nueva Esperanza",
    "wof:placetype":"locality",
    "wof:population":32
},
  "geometry": {"coordinates":[-92.0175,17.07222],"type":"Point"}
}