{
  "type": "Feature",
  "properties": {
    "gn:admin1_code":"24",
    "gn:admin2_code":"12",
    "gn:asciiname":"Acuapichco",
    "gn:country_code":"MX",
    "gn:dem":470,
    "gn:feature_class":"P",
    "gn:feature_code":"PPL",
    "gn:name":"Acuapichco",
    "gn:population":50,
    "gn:timezone":"America/Mexico_City",
    "iso:country":"MX",
    "wof:name":"Acuapichco",
    "wof:placetype":"locality",
    "wof:population":50
},
  "geometry": {"coordinates":[-98.94194,21.56611],"type":"Point"}
}