{
  "type": "Feature",
  "properties": {
    "gn:admin1_code":"6.0",
    "gn:admin2_code":"8.0",
    "gn:asciiname":"Regeibo",
    "gn:country_code":"MX",
    "gn:dem":1405,
    "gn:feature_class":"P",
    "gn:feature_code":"PPL",
    "gn:name":"Regeibo",
    "gn:population":0,
    "gn:timezone":"America/Chihuahua",
    "iso:country":"MX",
    "name:spa_x_preferred":[
        "Regeibo"
    ],
    "wof:name":"Regeibo",
    "wof:placetype":"locality"
},
  "geometry": {"coordinates":[-107.54897,27.1269],"type":"Point"}
}