{
  "type": "Feature",
  "properties": {
    "gn:admin1_code":"30",
    "gn:admin2_code":"160.0",
    "gn:asciiname":"Palma Real",
    "gn:country_code":"MX",
    "gn:dem":102,
    "gn:feature_class":"P",
    "gn:feature_code":"PPL",
    "gn:name":"Palma Real",
    "gn:population":6,
    "gn:timezone":"America/Mexico_City",
    "iso:country":"MX",
    "wof:name":"Palma Real",
    "wof:placetype":"locality",
    "wof:population":6
},
  "geometry": {"coordinates":[-97.69028,21.06583],"type":"Point"}
}