{
  "type": "Feature",
  "properties": {
    "gn:admin1_code":"18.0",
    "gn:admin2_code":"17.0",
    "gn:asciiname":"Puente Quebrado",
    "gn:country_code":"MX",
    "gn:dem":919,
    "gn:feature_class":"P",
    "gn:feature_code":"PPL",
    "gn:name":"Puente Quebrado",
    "gn:population":0,
    "gn:timezone":"America/Mazatlan",
    "iso:country":"MX",
    "name:spa_x_preferred":[
        "Puente Quebrado"
    ],
    "wof:name":"Puente Quebrado",
    "wof:placetype":"locality"
},
  "geometry": {"coordinates":[-104.87494,21.49851],"type":"Point"}
}