{
  "type": "Feature",
  "properties": {
    "gn:admin1_code":"5",
    "gn:admin2_code":"87.0",
    "gn:asciiname":"El Silencio",
    "gn:country_code":"MX",
    "gn:dem":18,
    "gn:feature_class":"P",
    "gn:feature_code":"PPL",
    "gn:name":"El Silencio",
    "gn:population":0,
    "gn:timezone":"America/Mexico_City",
    "iso:country":"MX",
    "name:ceb_x_preferred":[
        "El Silencio"
    ],
    "name:spa_x_preferred":[
        "El Silencio"
    ],
    "name:swe_x_preferred":[
        "El Silencio"
    ],
    "name:und_x_variant":[
        "Silencio",
        "El Silencio"
    ],
    "wof:name":"El Silencio",
    "wof:placetype":"locality"
},
  "geometry": {"coordinates":[-92.23081000000001,14.67239],"type":"Point"}
}