{
  "type": "Feature",
  "properties": {
    "gn:admin1_code":"20",
    "gn:admin2_code":"52.0",
    "gn:asciiname":"Corral de Ganado",
    "gn:country_code":"MX",
    "gn:dem":486,
    "gn:feature_class":"P",
    "gn:feature_code":"PPL",
    "gn:name":"Corral de Ganado",
    "gn:population":0,
    "gn:timezone":"America/Mexico_City",
    "iso:country":"MX",
    "wof:name":"Corral de Ganado",
    "wof:placetype":"locality"
},
  "geometry": {"coordinates":[-95.75,16.35],"type":"Point"}
}