{
  "type": "Feature",
  "properties": {
    "gn:admin1_code":"5",
    "gn:admin2_code":"52.0",
    "gn:asciiname":"Bello Paisaje",
    "gn:country_code":"MX",
    "gn:dem":1520,
    "gn:feature_class":"P",
    "gn:feature_code":"PPL",
    "gn:name":"Bello Paisaje",
    "gn:population":98,
    "gn:timezone":"America/Mexico_City",
    "iso:country":"MX",
    "wof:name":"Bello Paisaje",
    "wof:placetype":"locality",
    "wof:population":98
},
  "geometry": {"coordinates":[-91.96444,16.37139],"type":"Point"}
}