{
  "type": "Feature",
  "properties": {
    "gn:admin1_code":"30",
    "gn:admin2_code":"23.0",
    "gn:asciiname":"La Noria (Arrieral)",
    "gn:cc2":"MX",
    "gn:country_code":"MX",
    "gn:dem":499,
    "gn:feature_class":"P",
    "gn:feature_code":"PPL",
    "gn:name":"La Noria (Arrieral)",
    "gn:population":207,
    "gn:timezone":"America/Mexico_City",
    "iso:country":"MX",
    "name:und_x_variant":[
        "Noria",
        "La Noria"
    ],
    "wof:name":"La Noria (Arrieral)",
    "wof:placetype":"locality",
    "wof:population":207
},
  "geometry": {"coordinates":[-97.09332999999999,19.91972],"type":"Point"}
}