{
  "type": "Feature",
  "properties": {
    "gn:admin1_code":"32",
    "gn:admin2_code":"31",
    "gn:asciiname":"Las Cruces",
    "gn:country_code":"MX",
    "gn:dem":2181,
    "gn:feature_class":"P",
    "gn:feature_code":"PPL",
    "gn:name":"Las Cruces",
    "gn:population":21,
    "gn:timezone":"America/Mexico_City",
    "iso:country":"MX",
    "name:ast_x_preferred":[
        "Las Cruces"
    ],
    "name:bre_x_preferred":[
        "Cruces"
    ],
    "name:ceb_x_preferred":[
        "Las Cruces"
    ],
    "name:fra_x_preferred":[
        "Las Cruces"
    ],
    "name:ita_x_preferred":[
        "Las Cruces"
    ],
    "name:sco_x_preferred":[
        "Las Cruces"
    ],
    "name:spa_x_preferred":[
        "Cruces"
    ],
    "name:swe_x_preferred":[
        "Las Cruces"
    ],
    "wof:name":"Las Cruces",
    "wof:placetype":"locality",
    "wof:population":21
},
  "geometry": {"coordinates":[-103.55861,22.46833],"type":"Point"}
}