{
  "type": "Feature",
  "properties": {
    "gn:admin1_code":"20",
    "gn:admin2_code":"210.0",
    "gn:asciiname":"Vistahermosa",
    "gn:country_code":"MX",
    "gn:dem":2249,
    "gn:feature_class":"P",
    "gn:feature_code":"PPL",
    "gn:name":"Vistahermosa",
    "gn:population":82,
    "gn:timezone":"America/Mexico_City",
    "iso:country":"MX",
    "wof:name":"Vistahermosa",
    "wof:placetype":"locality",
    "wof:population":82
},
  "geometry": {"coordinates":[-97.79667000000001,17.46833],"type":"Point"}
}