{
  "type": "Feature",
  "properties": {
    "gn:admin1_code":"28",
    "gn:admin2_code":"32.0",
    "gn:asciiname":"Las Anacuas",
    "gn:country_code":"MX",
    "gn:dem":65,
    "gn:feature_class":"P",
    "gn:feature_code":"PPL",
    "gn:name":"Las Anacuas",
    "gn:population":189,
    "gn:timezone":"America/Matamoros",
    "iso:country":"MX",
    "wof:name":"Las Anacuas",
    "wof:placetype":"locality",
    "wof:population":189
},
  "geometry": {"coordinates":[-98.30861,25.9975],"type":"Point"}
}