{
  "type": "Feature",
  "properties": {
    "gn:admin1_code":"16",
    "gn:admin2_code":"83",
    "gn:asciiname":"Huerta la Soledad",
    "gn:country_code":"MX",
    "gn:dem":1919,
    "gn:feature_class":"P",
    "gn:feature_code":"PPL",
    "gn:name":"Huerta la Soledad",
    "gn:population":17,
    "gn:timezone":"America/Mexico_City",
    "iso:country":"MX",
    "wof:name":"Huerta la Soledad",
    "wof:placetype":"locality",
    "wof:population":17
},
  "geometry": {"coordinates":[-102.27056,19.26972],"type":"Point"}
}