{
  "type": "Feature",
  "properties": {
    "gn:admin1_code":"18",
    "gn:admin2_code":"6",
    "gn:asciiname":"Coyulita",
    "gn:country_code":"MX",
    "gn:dem":1207,
    "gn:feature_class":"P",
    "gn:feature_code":"PPL",
    "gn:name":"Coyulita",
    "gn:population":12,
    "gn:timezone":"America/Mazatlan",
    "iso:country":"MX",
    "wof:name":"Coyulita",
    "wof:placetype":"locality",
    "wof:population":12
},
  "geometry": {"coordinates":[-104.29000000000001,21.10806],"type":"Point"}
}