{
  "type": "Feature",
  "properties": {
    "gn:admin1_code":"30",
    "gn:admin2_code":"123.0",
    "gn:asciiname":"Chijoles",
    "gn:country_code":"MX",
    "gn:dem":7,
    "gn:feature_class":"P",
    "gn:feature_code":"PPL",
    "gn:name":"Chijoles",
    "gn:population":60,
    "gn:timezone":"America/Mexico_City",
    "iso:country":"MX",
    "wof:name":"Chijoles",
    "wof:placetype":"locality",
    "wof:population":60
},
  "geometry": {"coordinates":[-98.24056,21.9925],"type":"Point"}
}