{
  "type": "Feature",
  "properties": {
    "gn:admin1_code":"10",
    "gn:admin2_code":"37.0",
    "gn:asciiname":"Valle de Topia",
    "gn:country_code":"MX",
    "gn:dem":1557,
    "gn:feature_class":"P",
    "gn:feature_code":"PPL",
    "gn:name":"Valle de Top\u00eda",
    "gn:population":444,
    "gn:timezone":"America/Monterrey",
    "iso:country":"MX",
    "name:spa_x_preferred":[
        "Valle de Top\u00eda"
    ],
    "wof:name":"Valle de Topia",
    "wof:placetype":"locality",
    "wof:population":444
},
  "geometry": {"coordinates":[-106.42113999999999,25.24307],"type":"Point"}
}