{
  "type": "Feature",
  "properties": {
    "gn:admin1_code":"26.0",
    "gn:admin2_code":"43.0",
    "gn:asciiname":"Barraza",
    "gn:country_code":"MX",
    "gn:dem":1091,
    "gn:feature_class":"P",
    "gn:feature_code":"PPL",
    "gn:name":"Barraza",
    "gn:population":0,
    "gn:timezone":"America/Hermosillo",
    "iso:country":"MX",
    "name:deu_x_preferred":[
        "Barraza"
    ],
    "name:rus_x_preferred":[
        "\u0411\u0430\u0440\u0440\u0430\u0441\u0430"
    ],
    "name:spa_x_preferred":[
        "Barraza"
    ],
    "wof:name":"Barraza",
    "wof:placetype":"locality"
},
  "geometry": {"coordinates":[-110.90854,31.0893],"type":"Point"}
}