{
  "type": "Feature",
  "properties": {
    "gn:admin1_code":"12",
    "gn:admin2_code":"11.0",
    "gn:asciiname":"Huerta de Juan Hernandez",
    "gn:country_code":"MX",
    "gn:dem":31,
    "gn:feature_class":"P",
    "gn:feature_code":"PPL",
    "gn:name":"Huerta de Juan Hern\u00e1ndez",
    "gn:population":7,
    "gn:timezone":"America/Mexico_City",
    "iso:country":"MX",
    "name:und_x_variant":[
        "Huerta de Juan Hern\u00e1ndez"
    ],
    "wof:name":"Huerta de Juan Hernandez",
    "wof:placetype":"locality",
    "wof:population":7
},
  "geometry": {"coordinates":[-100.45650000000001,17.19156],"type":"Point"}
}