{
  "type": "Feature",
  "properties": {
    "gn:admin1_code":"30",
    "gn:admin2_code":"149.0",
    "gn:asciiname":"Cuilonia Viejo",
    "gn:country_code":"MX",
    "gn:dem":380,
    "gn:feature_class":"P",
    "gn:feature_code":"PPL",
    "gn:name":"Cuilonia Viejo",
    "gn:population":0,
    "gn:timezone":"America/Mexico_City",
    "iso:country":"MX",
    "name:spa_x_preferred":[
        "Cuilonia Viejo"
    ],
    "name:und_x_variant":[
        "Cuiliona",
        "Cuilonia"
    ],
    "wof:name":"Cuilonia Viejo",
    "wof:placetype":"locality"
},
  "geometry": {"coordinates":[-94.93908999999999,18.18533],"type":"Point"}
}