{
  "type": "Feature",
  "properties": {
    "gn:admin1_code":"27",
    "gn:admin2_code":"1.0",
    "gn:asciiname":"Las Carmelitas",
    "gn:country_code":"MX",
    "gn:dem":21,
    "gn:feature_class":"P",
    "gn:feature_code":"PPL",
    "gn:name":"Las Carmelitas",
    "gn:population":0,
    "gn:timezone":"America/Mexico_City",
    "iso:country":"MX",
    "name:spa_x_preferred":[
        "Las Carmelitas"
    ],
    "wof:name":"Las Carmelitas",
    "wof:placetype":"locality"
},
  "geometry": {"coordinates":[-91.52500000000001,17.98333],"type":"Point"}
}