{
  "type": "Feature",
  "properties": {
    "gn:admin1_code":"15",
    "gn:admin2_code":"83",
    "gn:asciiname":"Barrio Tepetitlan",
    "gn:country_code":"MX",
    "gn:dem":2281,
    "gn:feature_class":"P",
    "gn:feature_code":"PPL",
    "gn:name":"Barrio Tepetitl\u00e1n",
    "gn:population":26,
    "gn:timezone":"America/Mexico_City",
    "iso:country":"MX",
    "name:und_x_variant":[
        "Barrio Tepetitl\u00e1n"
    ],
    "wof:name":"Barrio Tepetitlan",
    "wof:placetype":"locality",
    "wof:population":26
},
  "geometry": {"coordinates":[-98.86447,19.19936],"type":"Point"}
}