{
  "type": "Feature",
  "properties": {
    "gn:admin1_code":"21.0",
    "gn:asciiname":"Temetla",
    "gn:country_code":"MX",
    "gn:dem":1205,
    "gn:feature_class":"P",
    "gn:feature_code":"PPL",
    "gn:name":"Temetla",
    "gn:population":0,
    "gn:timezone":"America/Mexico_City",
    "iso:country":"MX",
    "name:spa_x_preferred":[
        "Temetla"
    ],
    "wof:name":"Temetla",
    "wof:placetype":"locality"
},
  "geometry": {"coordinates":[-98.83696,18.42498],"type":"Point"}
}