{
  "type": "Feature",
  "properties": {
    "gn:admin1_code":"12",
    "gn:admin2_code":"78.0",
    "gn:asciiname":"San Miguel Amoltepec Nuevo",
    "gn:country_code":"MX",
    "gn:dem":2464,
    "gn:elevation":"2480.0",
    "gn:feature_class":"P",
    "gn:feature_code":"PPL",
    "gn:name":"San Miguel Amoltepec Nuevo",
    "gn:population":0,
    "gn:timezone":"America/Mexico_City",
    "iso:country":"MX",
    "wof:name":"San Miguel Amoltepec Nuevo",
    "wof:placetype":"locality"
},
  "geometry": {"coordinates":[-98.49194,17.20306],"type":"Point"}
}