{
  "type": "Feature",
  "properties": {
    "gn:admin1_code":"14.0",
    "gn:admin2_code":"8.0",
    "gn:asciiname":"El Cabrito",
    "gn:country_code":"MX",
    "gn:dem":2159,
    "gn:feature_class":"P",
    "gn:feature_code":"PPL",
    "gn:name":"El Cabrito",
    "gn:population":0,
    "gn:timezone":"America/Mexico_City",
    "iso:country":"MX",
    "name:und_x_variant":[
        "Cabrito",
        "El Cabrito"
    ],
    "wof:name":"El Cabrito",
    "wof:placetype":"locality"
},
  "geometry": {"coordinates":[-102.27285000000001,20.69555],"type":"Point"}
}