{
  "type": "Feature",
  "properties": {
    "gn:admin1_code":"32",
    "gn:admin2_code":"36.0",
    "gn:asciiname":"San Blas Copudas",
    "gn:country_code":"MX",
    "gn:dem":2102,
    "gn:feature_class":"P",
    "gn:feature_code":"PPL",
    "gn:name":"San Blas Copudas",
    "gn:population":0,
    "gn:timezone":"America/Mexico_City",
    "iso:country":"MX",
    "name:und_x_variant":[
        "Las Copudas",
        "Las Coqudas",
        "Las Cojudas"
    ],
    "wof:name":"San Blas Copudas",
    "wof:placetype":"locality"
},
  "geometry": {"coordinates":[-102.14952,22.55529],"type":"Point"}
}