{
  "type": "Feature",
  "properties": {
    "gn:admin1_code":"30",
    "gn:admin2_code":"130.0",
    "gn:asciiname":"Agua Fria Nazareno",
    "gn:country_code":"MX",
    "gn:dem":108,
    "gn:feature_class":"P",
    "gn:feature_code":"PPL",
    "gn:name":"Agua Fr\u00eda Nazareno",
    "gn:population":102,
    "gn:timezone":"America/Mexico_City",
    "iso:country":"MX",
    "name:und_x_variant":[
        "Agua Fr\u00eda Nazareno"
    ],
    "wof:name":"Agua Fria Nazareno",
    "wof:placetype":"locality",
    "wof:population":102
},
  "geometry": {"coordinates":[-95.49806,17.63139],"type":"Point"}
}