{
  "type": "Feature",
  "properties": {
    "gn:admin1_code":"30",
    "gn:admin2_code":"174.0",
    "gn:asciiname":"Rincon de Iguanas (El Iguanero)",
    "gn:country_code":"MX",
    "gn:dem":26,
    "gn:feature_class":"P",
    "gn:feature_code":"PPL",
    "gn:name":"Rinc\u00f3n de Iguanas (El Iguanero)",
    "gn:population":7,
    "gn:timezone":"America/Mexico_City",
    "iso:country":"MX",
    "name:und_x_variant":[
        "Rinc\u00f3n de Iguanas (El Iguanero)"
    ],
    "wof:name":"Rincon de Iguanas (El Iguanero)",
    "wof:placetype":"locality",
    "wof:population":7
},
  "geometry": {"coordinates":[-96.12889,18.495],"type":"Point"}
}