{
  "type": "Feature",
  "properties": {
    "gn:admin1_code":"30",
    "gn:admin2_code":"160",
    "gn:asciiname":"El Volador",
    "gn:country_code":"MX",
    "gn:dem":34,
    "gn:feature_class":"P",
    "gn:feature_code":"PPL",
    "gn:name":"El Volador",
    "gn:population":10,
    "gn:timezone":"America/Mexico_City",
    "iso:country":"MX",
    "wof:name":"El Volador",
    "wof:placetype":"locality",
    "wof:population":10
},
  "geometry": {"coordinates":[-97.54111,20.84139],"type":"Point"}
}