{
  "type": "Feature",
  "properties": {
    "gn:admin1_code":"6",
    "gn:asciiname":"San Ignacio Sotelo",
    "gn:country_code":"MX",
    "gn:dem":2953,
    "gn:feature_class":"P",
    "gn:feature_code":"PPL",
    "gn:name":"San Ignacio Sotelo",
    "gn:population":0,
    "gn:timezone":"America/Monterrey",
    "iso:country":"MX",
    "wof:name":"San Ignacio Sotelo",
    "wof:placetype":"locality"
},
  "geometry": {"coordinates":[-106.09999999999999,26.03333],"type":"Point"}
}