{
  "type": "Feature",
  "properties": {
    "gn:admin1_code":"30",
    "gn:admin2_code":"121.0",
    "gn:asciiname":"Rancho Nuevo (Santa Dalia)",
    "gn:country_code":"MX",
    "gn:dem":79,
    "gn:feature_class":"P",
    "gn:feature_code":"PPL",
    "gn:name":"Rancho Nuevo (Santa Dalia)",
    "gn:population":8,
    "gn:timezone":"America/Mexico_City",
    "iso:country":"MX",
    "wof:name":"Rancho Nuevo (Santa Dalia)",
    "wof:placetype":"locality",
    "wof:population":8
},
  "geometry": {"coordinates":[-97.95139,21.68056],"type":"Point"}
}