{
  "type": "Feature",
  "properties": {
    "gn:admin1_code":"32",
    "gn:admin2_code":"58.0",
    "gn:asciiname":"El Guitarrero",
    "gn:country_code":"MX",
    "gn:dem":2341,
    "gn:feature_class":"P",
    "gn:feature_code":"PPL",
    "gn:name":"El Guitarrero",
    "gn:population":0,
    "gn:timezone":"America/Mexico_City",
    "iso:country":"MX",
    "name:spa_x_preferred":[
        "El Guitarrero"
    ],
    "wof:name":"El Guitarrero",
    "wof:placetype":"locality"
},
  "geometry": {"coordinates":[-103.22632,21.54131],"type":"Point"}
}