{
  "type": "Feature",
  "properties": {
    "gn:admin1_code":"19",
    "gn:admin2_code":"38.0",
    "gn:asciiname":"Los Pinos",
    "gn:country_code":"MX",
    "gn:dem":420,
    "gn:feature_class":"P",
    "gn:feature_code":"PPL",
    "gn:name":"Los Pinos",
    "gn:population":0,
    "gn:timezone":"America/Monterrey",
    "iso:country":"MX",
    "name:fra_x_preferred":[
        "Los Pinos"
    ],
    "name:heb_x_preferred":[
        "\u05dc\u05d5\u05e1 \u05e4\u05d9\u05e0\u05d5\u05e1"
    ],
    "name:ita_x_preferred":[
        "Los Pinos"
    ],
    "name:msa_x_preferred":[
        "Los Pinos"
    ],
    "name:nld_x_preferred":[
        "Los Pinos"
    ],
    "name:nor_x_preferred":[
        "Los Pinos"
    ],
    "name:por_x_preferred":[
        "Los Pinos"
    ],
    "name:rus_x_preferred":[
        "\u041b\u043e\u0441 \u041f\u0438\u043d\u043e\u0441"
    ],
    "name:spa_x_preferred":[
        "Los Pinos"
    ],
    "name:swe_x_preferred":[
        "Los Pinos"
    ],
    "wof:name":"Los Pinos",
    "wof:placetype":"locality"
},
  "geometry": {"coordinates":[-99.85194,25.21609],"type":"Point"}
}