{
  "type": "Feature",
  "properties": {
    "gn:admin1_code":"3",
    "gn:admin2_code":"1.0",
    "gn:asciiname":"El Liberato",
    "gn:country_code":"MX",
    "gn:dem":323,
    "gn:feature_class":"P",
    "gn:feature_code":"PPL",
    "gn:name":"El Liberato",
    "gn:population":0,
    "gn:timezone":"America/Mazatlan",
    "iso:country":"MX",
    "name:spa_x_preferred":[
        "El Liberato"
    ],
    "wof:name":"El Liberato",
    "wof:placetype":"locality"
},
  "geometry": {"coordinates":[-111.90366000000002,26.28573],"type":"Point"}
}