{
  "type": "Feature",
  "properties": {
    "gn:admin1_code":"26",
    "gn:admin2_code":"19.0",
    "gn:asciiname":"El Cinco",
    "gn:country_code":"MX",
    "gn:dem":1656,
    "gn:feature_class":"P",
    "gn:feature_code":"PPL",
    "gn:name":"El Cinco",
    "gn:population":0,
    "gn:timezone":"America/Hermosillo",
    "iso:country":"MX",
    "name:und_x_variant":[
        "Divisaderos",
        "El Cinco"
    ],
    "wof:name":"El Cinco",
    "wof:placetype":"locality"
},
  "geometry": {"coordinates":[-109.96793999999998,31.04745],"type":"Point"}
}