{
  "type": "Feature",
  "properties": {
    "gn:admin1_code":"28.0",
    "gn:admin2_code":"13.0",
    "gn:asciiname":"San Felipe",
    "gn:country_code":"MX",
    "gn:dem":215,
    "gn:feature_class":"P",
    "gn:feature_code":"PPL",
    "gn:name":"San Felipe",
    "gn:population":2,
    "gn:timezone":"America/Monterrey",
    "iso:country":"MX",
    "name:spa_x_preferred":[
        "San Felipe"
    ],
    "wof:name":"San Felipe",
    "wof:placetype":"locality",
    "wof:population":2
},
  "geometry": {"coordinates":[-99.09222,23.8575],"type":"Point"}
}