{
  "type": "Feature",
  "properties": {
    "gn:admin1_code":"14.0",
    "gn:admin2_code":"49.0",
    "gn:asciiname":"Puerto el Viejo",
    "gn:country_code":"MX",
    "gn:dem":1045,
    "gn:feature_class":"P",
    "gn:feature_code":"PPL",
    "gn:name":"Puerto el Viejo",
    "gn:population":0,
    "gn:timezone":"America/Mexico_City",
    "iso:country":"MX",
    "name:spa_x_preferred":[
        "Puerto el Viejo"
    ],
    "wof:name":"Puerto el Viejo",
    "wof:placetype":"locality"
},
  "geometry": {"coordinates":[-102.98103999999999,19.46591],"type":"Point"}
}