{
  "type": "Feature",
  "properties": {
    "gn:admin1_code":"4",
    "gn:admin2_code":"3.0",
    "gn:asciiname":"Amira (San Martin)",
    "gn:country_code":"MX",
    "gn:dem":7,
    "gn:feature_class":"P",
    "gn:feature_code":"PPL",
    "gn:name":"Amira (San Mart\u00edn)",
    "gn:population":6,
    "gn:timezone":"America/Merida",
    "iso:country":"MX",
    "name:und_x_variant":[
        "Amira (San Mart\u00edn)"
    ],
    "wof:name":"Amira (San Martin)",
    "wof:placetype":"locality",
    "wof:population":6
},
  "geometry": {"coordinates":[-91.69638999999999,17.985],"type":"Point"}
}