{
  "type": "Feature",
  "properties": {
    "gn:admin1_code":"25",
    "gn:admin2_code":"5.0",
    "gn:asciiname":"El Mulato",
    "gn:country_code":"MX",
    "gn:dem":352,
    "gn:feature_class":"P",
    "gn:feature_code":"PPL",
    "gn:name":"El Mulato",
    "gn:population":0,
    "gn:timezone":"America/Mazatlan",
    "iso:country":"MX",
    "name:spa_x_preferred":[
        "El Mulato"
    ],
    "wof:name":"El Mulato",
    "wof:placetype":"locality"
},
  "geometry": {"coordinates":[-107.00212999999999,24.6327],"type":"Point"}
}