{
  "type": "Feature",
  "properties": {
    "gn:admin1_code":"14",
    "gn:admin2_code":"97.0",
    "gn:asciiname":"Villas de la Hacienda [Fraccionamiento]",
    "gn:country_code":"MX",
    "gn:dem":1536,
    "gn:feature_class":"P",
    "gn:feature_code":"PPL",
    "gn:name":"Villas de la Hacienda [Fraccionamiento]",
    "gn:population":11078,
    "gn:timezone":"America/Mexico_City",
    "iso:country":"MX",
    "wof:name":"Villas de la Hacienda [Fraccionamiento]",
    "wof:placetype":"locality",
    "wof:population":11078
},
  "geometry": {"coordinates":[-103.38278,20.53111],"type":"Point"}
}