{
  "type": "Feature",
  "properties": {
    "gn:admin1_code":"13",
    "gn:admin2_code":"76.0",
    "gn:asciiname":"Xonthe",
    "gn:country_code":"MX",
    "gn:dem":2110,
    "gn:feature_class":"P",
    "gn:feature_code":"PPL",
    "gn:name":"Xonthe",
    "gn:population":122,
    "gn:timezone":"America/Mexico_City",
    "iso:country":"MX",
    "wof:name":"Xonthe",
    "wof:placetype":"locality",
    "wof:population":122
},
  "geometry": {"coordinates":[-99.40028,20.04917],"type":"Point"}
}