{
  "type": "Feature",
  "properties": {
    "gn:admin1_code":"18.0",
    "gn:admin2_code":"1.0",
    "gn:asciiname":"El Carrizal",
    "gn:country_code":"MX",
    "gn:dem":1725,
    "gn:feature_class":"P",
    "gn:feature_code":"PPL",
    "gn:name":"El Carrizal",
    "gn:population":105,
    "gn:timezone":"America/Mazatlan",
    "iso:country":"MX",
    "wof:name":"El Carrizal",
    "wof:placetype":"locality",
    "wof:population":105
},
  "geometry": {"coordinates":[-105.08638999999999,22.60472],"type":"Point"}
}