{
  "type": "Feature",
  "properties": {
    "gn:admin1_code":"16.0",
    "gn:admin2_code":"10.0",
    "gn:asciiname":"El Chacualatal",
    "gn:country_code":"MX",
    "gn:dem":539,
    "gn:feature_class":"P",
    "gn:feature_code":"PPL",
    "gn:name":"El Chacualatal",
    "gn:population":0,
    "gn:timezone":"America/Mexico_City",
    "iso:country":"MX",
    "name:spa_x_preferred":[
        "El Chacualatal"
    ],
    "wof:name":"El Chacualatal",
    "wof:placetype":"locality"
},
  "geometry": {"coordinates":[-102.15389,18.3683],"type":"Point"}
}