{
  "type": "Feature",
  "properties": {
    "gn:admin1_code":"30",
    "gn:admin2_code":"21.0",
    "gn:asciiname":"El Rosario",
    "gn:country_code":"MX",
    "gn:dem":462,
    "gn:feature_class":"P",
    "gn:feature_code":"PPL",
    "gn:name":"El Rosario",
    "gn:population":5,
    "gn:timezone":"America/Mexico_City",
    "iso:country":"MX",
    "wof:name":"El Rosario",
    "wof:placetype":"locality",
    "wof:population":5
},
  "geometry": {"coordinates":[-96.77667,18.94833],"type":"Point"}
}