{
  "type": "Feature",
  "properties": {
    "gn:admin1_code":"5.0",
    "gn:asciiname":"San Antonio los Mares",
    "gn:country_code":"MX",
    "gn:dem":7,
    "gn:feature_class":"P",
    "gn:feature_code":"PPL",
    "gn:name":"San Antonio los Mares",
    "gn:population":0,
    "gn:timezone":"America/Mexico_City",
    "iso:country":"MX",
    "name:spa_x_preferred":[
        "San Antonio los Mares"
    ],
    "wof:name":"San Antonio los Mares",
    "wof:placetype":"locality"
},
  "geometry": {"coordinates":[-93.72711,15.9007],"type":"Point"}
}