{
  "type": "Feature",
  "properties": {
    "gn:admin1_code":"21",
    "gn:admin2_code":"53.0",
    "gn:asciiname":"San Miguel Pedernales",
    "gn:country_code":"MX",
    "gn:dem":2808,
    "gn:feature_class":"P",
    "gn:feature_code":"PPL",
    "gn:name":"San Miguel Pedernales",
    "gn:population":133,
    "gn:timezone":"America/Mexico_City",
    "iso:country":"MX",
    "wof:name":"San Miguel Pedernales",
    "wof:placetype":"locality",
    "wof:population":133
},
  "geometry": {"coordinates":[-98.17095,19.95759],"type":"Point"}
}