{
  "type": "Feature",
  "properties": {
    "gn:admin1_code":"11",
    "gn:admin2_code":"13.0",
    "gn:asciiname":"Las Flores",
    "gn:cc2":"MX",
    "gn:country_code":"MX",
    "gn:dem":2069,
    "gn:feature_class":"P",
    "gn:feature_code":"PPL",
    "gn:name":"Las Flores",
    "gn:population":394,
    "gn:timezone":"America/Mexico_City",
    "iso:country":"MX",
    "name:und_x_variant":[
        "Dolores",
        "Los Dolores"
    ],
    "wof:name":"Las Flores",
    "wof:placetype":"locality",
    "wof:population":394
},
  "geometry": {"coordinates":[-100.44750000000001,21.13222],"type":"Point"}
}