{
  "type": "Feature",
  "properties": {
    "gn:admin1_code":"25",
    "gn:admin2_code":"11.0",
    "gn:asciiname":"Los Ebanos",
    "gn:country_code":"MX",
    "gn:dem":12,
    "gn:feature_class":"P",
    "gn:feature_code":"PPL",
    "gn:name":"Los Ebanos",
    "gn:population":0,
    "gn:timezone":"America/Mazatlan",
    "iso:country":"MX",
    "name:spa_x_preferred":[
        "Los Ebanos"
    ],
    "wof:name":"Los Ebanos",
    "wof:placetype":"locality"
},
  "geometry": {"coordinates":[-108.50824,25.5409],"type":"Point"}
}