{
  "type": "Feature",
  "properties": {
    "gn:admin1_code":"22",
    "gn:admin2_code":"13",
    "gn:asciiname":"Corral Viejo",
    "gn:country_code":"MX",
    "gn:dem":1750,
    "gn:feature_class":"P",
    "gn:feature_code":"PPL",
    "gn:name":"Corral Viejo",
    "gn:population":37,
    "gn:timezone":"America/Mexico_City",
    "iso:country":"MX",
    "wof:name":"Corral Viejo",
    "wof:placetype":"locality",
    "wof:population":37
},
  "geometry": {"coordinates":[-99.85222,21.14417000000001],"type":"Point"}
}