{
  "type": "Feature",
  "properties": {
    "gn:admin1_code":"30",
    "gn:admin2_code":"108.0",
    "gn:asciiname":"Nuevo Carrizal",
    "gn:country_code":"MX",
    "gn:dem":17,
    "gn:feature_class":"P",
    "gn:feature_code":"PPL",
    "gn:name":"Nuevo Carrizal",
    "gn:population":0,
    "gn:timezone":"America/Mexico_City",
    "iso:country":"MX",
    "name:spa_x_preferred":[
        "Nuevo Carrizal"
    ],
    "wof:name":"Nuevo Carrizal",
    "wof:placetype":"locality"
},
  "geometry": {"coordinates":[-94.56846,18.05525],"type":"Point"}
}