{
  "type": "Feature",
  "properties": {
    "gn:admin1_code":"14",
    "gn:admin2_code":"71.0",
    "gn:asciiname":"Corral Falso",
    "gn:country_code":"MX",
    "gn:dem":1171,
    "gn:feature_class":"P",
    "gn:feature_code":"PPL",
    "gn:name":"Corral Falso",
    "gn:population":7,
    "gn:timezone":"America/Mexico_City",
    "iso:country":"MX",
    "name:ita_x_preferred":[
        "Corral Falso"
    ],
    "name:spa_x_preferred":[
        "Corral Falso"
    ],
    "name:zho_x_preferred":[
        "\u79d1\u62c9\u723e\u6cd5\u723e\u7d22"
    ],
    "wof:name":"Corral Falso",
    "wof:placetype":"locality",
    "wof:population":7
},
  "geometry": {"coordinates":[-103.48806,21.06528],"type":"Point"}
}