{
  "type": "Feature",
  "properties": {
    "gn:admin1_code":"12",
    "gn:admin2_code":"2.0",
    "gn:asciiname":"Tlalxocotitlan",
    "gn:country_code":"MX",
    "gn:dem":1635,
    "gn:feature_class":"P",
    "gn:feature_code":"PPL",
    "gn:name":"Tlalxocotitl\u00e1n",
    "gn:population":176,
    "gn:timezone":"America/Mexico_City",
    "iso:country":"MX",
    "name:und_x_variant":[
        "Tlalxocotitl\u00e1n"
    ],
    "wof:name":"Tlalxocotitlan",
    "wof:placetype":"locality",
    "wof:population":176
},
  "geometry": {"coordinates":[-98.79816,17.72087999999999],"type":"Point"}
}