{
  "type": "Feature",
  "properties": {
    "gn:admin1_code":"16",
    "gn:admin2_code":"101",
    "gn:asciiname":"Los Timones",
    "gn:country_code":"MX",
    "gn:dem":1046,
    "gn:feature_class":"P",
    "gn:feature_code":"PPL",
    "gn:name":"Los Timones",
    "gn:population":13,
    "gn:timezone":"America/Mexico_City",
    "iso:country":"MX",
    "wof:name":"Los Timones",
    "wof:placetype":"locality",
    "wof:population":13
},
  "geometry": {"coordinates":[-100.96444,19.5075],"type":"Point"}
}