{
  "type": "Feature",
  "properties": {
    "gn:admin1_code":"28",
    "gn:asciiname":"Huisachitos",
    "gn:cc2":"MX",
    "gn:country_code":"MX",
    "gn:dem":80,
    "gn:feature_class":"P",
    "gn:feature_code":"PPL",
    "gn:name":"Huisachitos",
    "gn:population":0,
    "gn:timezone":"America/Monterrey",
    "iso:country":"MX",
    "name:und_x_variant":[
        "Huizachitos",
        "Huisachitos"
    ],
    "wof:name":"Huisachitos",
    "wof:placetype":"locality"
},
  "geometry": {"coordinates":[-99.31667,26.86667000000001],"type":"Point"}
}