{
  "type": "Feature",
  "properties": {
    "gn:admin1_code":"5.0",
    "gn:admin2_code":"107.0",
    "gn:asciiname":"Las Carretas",
    "gn:country_code":"MX",
    "gn:dem":878,
    "gn:feature_class":"P",
    "gn:feature_code":"PPL",
    "gn:name":"Las Carretas",
    "gn:population":0,
    "gn:timezone":"America/Mexico_City",
    "iso:country":"MX",
    "name:spa_x_preferred":[
        "Las Carretas"
    ],
    "wof:name":"Las Carretas",
    "wof:placetype":"locality"
},
  "geometry": {"coordinates":[-93.32491,15.93609],"type":"Point"}
}