{
  "type": "Feature",
  "properties": {
    "gn:admin1_code":"12",
    "gn:admin2_code":"45.0",
    "gn:asciiname":"Tecolapa",
    "gn:country_code":"MX",
    "gn:dem":994,
    "gn:feature_class":"P",
    "gn:feature_code":"PPL",
    "gn:name":"Tecolapa",
    "gn:population":0,
    "gn:timezone":"America/Mexico_City",
    "iso:country":"MX",
    "name:spa_x_preferred":[
        "Tecolapa"
    ],
    "wof:name":"Tecolapa",
    "wof:placetype":"locality"
},
  "geometry": {"coordinates":[-98.76425999999999,17.97443999999999],"type":"Point"}
}