{
  "type": "Feature",
  "properties": {
    "gn:admin1_code":"1",
    "gn:admin2_code":"3.0",
    "gn:asciiname":"Miguel Hidalgo (El Huarache)",
    "gn:country_code":"MX",
    "gn:dem":2189,
    "gn:feature_class":"P",
    "gn:feature_code":"PPL",
    "gn:name":"Miguel Hidalgo (El Huarache)",
    "gn:population":8,
    "gn:timezone":"America/Mexico_City",
    "iso:country":"MX",
    "wof:name":"Miguel Hidalgo (El Huarache)",
    "wof:placetype":"locality",
    "wof:population":8
},
  "geometry": {"coordinates":[-102.79443999999999,21.9025],"type":"Point"}
}