{
  "type": "Feature",
  "properties": {
    "gn:admin1_code":"14",
    "gn:admin2_code":"58.0",
    "gn:asciiname":"Tranquillas",
    "gn:country_code":"MX",
    "gn:dem":1551,
    "gn:feature_class":"P",
    "gn:feature_code":"PPL",
    "gn:name":"Tranquillas",
    "gn:population":0,
    "gn:timezone":"America/Mexico_City",
    "iso:country":"MX",
    "name:spa_x_preferred":[
        "Tranquillas"
    ],
    "wof:name":"Tranquillas",
    "wof:placetype":"locality"
},
  "geometry": {"coordinates":[-104.77419999999999,20.69952],"type":"Point"}
}