{
  "type": "Feature",
  "properties": {
    "gn:admin1_code":"5",
    "gn:admin2_code":"57",
    "gn:asciiname":"Regalo de Dios",
    "gn:country_code":"MX",
    "gn:dem":732,
    "gn:feature_class":"P",
    "gn:feature_code":"PPL",
    "gn:name":"Regalo de Dios",
    "gn:population":9,
    "gn:timezone":"America/Mexico_City",
    "iso:country":"MX",
    "wof:name":"Regalo de Dios",
    "wof:placetype":"locality",
    "wof:population":9
},
  "geometry": {"coordinates":[-92.39028,15.30139],"type":"Point"}
}