{
  "type": "Feature",
  "properties": {
    "gn:admin1_code":"20",
    "gn:admin2_code":"94",
    "gn:asciiname":"Loma Manzanal",
    "gn:country_code":"MX",
    "gn:dem":2114,
    "gn:feature_class":"P",
    "gn:feature_code":"PPL",
    "gn:name":"Loma Manzanal",
    "gn:population":41,
    "gn:timezone":"America/Mexico_City",
    "iso:country":"MX",
    "wof:name":"Loma Manzanal",
    "wof:placetype":"locality",
    "wof:population":41
},
  "geometry": {"coordinates":[-97.04333,17.21361],"type":"Point"}
}