{
  "type": "Feature",
  "properties": {
    "gn:admin1_code":"26",
    "gn:admin2_code":"10.0",
    "gn:asciiname":"Cienega de Horcones",
    "gn:country_code":"MX",
    "gn:dem":2122,
    "gn:feature_class":"P",
    "gn:feature_code":"PPL",
    "gn:name":"Ci\u00e9nega de Horcones",
    "gn:population":95,
    "gn:timezone":"America/Hermosillo",
    "iso:country":"MX",
    "name:und_x_variant":[
        "Ci\u00e9nega de Horcones"
    ],
    "wof:name":"Cienega de Horcones",
    "wof:placetype":"locality",
    "wof:population":95
},
  "geometry": {"coordinates":[-108.61811000000002,30.19777],"type":"Point"}
}