{
  "type": "Feature",
  "properties": {
    "gn:admin1_code":"12",
    "gn:admin2_code":"38.0",
    "gn:asciiname":"Las Ollas",
    "gn:country_code":"MX",
    "gn:dem":119,
    "gn:feature_class":"P",
    "gn:feature_code":"PPL",
    "gn:name":"Las Ollas",
    "gn:population":0,
    "gn:timezone":"America/Mexico_City",
    "iso:country":"MX",
    "name:spa_x_preferred":[
        "Las Ollas"
    ],
    "wof:name":"Las Ollas",
    "wof:placetype":"locality"
},
  "geometry": {"coordinates":[-101.52401,17.76468],"type":"Point"}
}