{
  "type": "Feature",
  "properties": {
    "gn:admin1_code":"5",
    "gn:admin2_code":"19.0",
    "gn:asciiname":"Guadalupe Chichima",
    "gn:country_code":"MX",
    "gn:dem":1595,
    "gn:feature_class":"P",
    "gn:feature_code":"PPL",
    "gn:name":"Guadalupe Chichima",
    "gn:population":0,
    "gn:timezone":"America/Mexico_City",
    "iso:country":"MX",
    "wof:name":"Guadalupe Chichima",
    "wof:placetype":"locality"
},
  "geometry": {"coordinates":[-92.12222,16.20833],"type":"Point"}
}