{
  "type": "Feature",
  "properties": {
    "gn:admin1_code":"13",
    "gn:admin2_code":"71.0",
    "gn:asciiname":"Lindavista",
    "gn:country_code":"MX",
    "gn:dem":2138,
    "gn:feature_class":"P",
    "gn:feature_code":"PPL",
    "gn:name":"Lindavista",
    "gn:population":63,
    "gn:timezone":"America/Mexico_City",
    "iso:country":"MX",
    "name:fra_x_preferred":[
        "Lindavista"
    ],
    "name:nor_x_preferred":[
        "Lindavista"
    ],
    "name:spa_x_preferred":[
        "Lindavista"
    ],
    "wof:name":"Lindavista",
    "wof:placetype":"locality",
    "wof:population":63
},
  "geometry": {"coordinates":[-98.94656999999999,20.91726],"type":"Point"}
}