{
  "type": "Feature",
  "properties": {
    "gn:admin1_code":"15.0",
    "gn:asciiname":"El Granjenal",
    "gn:country_code":"MX",
    "gn:dem":1944,
    "gn:feature_class":"P",
    "gn:feature_code":"PPL",
    "gn:name":"El Granjenal",
    "gn:population":0,
    "gn:timezone":"America/Mexico_City",
    "iso:country":"MX",
    "name:spa_x_preferred":[
        "El Granjenal"
    ],
    "wof:name":"El Granjenal",
    "wof:placetype":"locality"
},
  "geometry": {"coordinates":[-101.66501,20.01646],"type":"Point"}
}