{
  "type": "Feature",
  "properties": {
    "gn:admin1_code":"25",
    "gn:admin2_code":"1.0",
    "gn:asciiname":"Campo Meaker",
    "gn:country_code":"MX",
    "gn:dem":10,
    "gn:feature_class":"P",
    "gn:feature_code":"PPL",
    "gn:name":"Campo Meaker",
    "gn:population":8,
    "gn:timezone":"America/Mazatlan",
    "iso:country":"MX",
    "wof:name":"Campo Meaker",
    "wof:placetype":"locality",
    "wof:population":8
},
  "geometry": {"coordinates":[-109.05182000000001,25.79439],"type":"Point"}
}