{
  "type": "Feature",
  "properties": {
    "gn:admin1_code":"30",
    "gn:admin2_code":"142",
    "gn:asciiname":"La Hacienda Solcuautla",
    "gn:country_code":"MX",
    "gn:dem":47,
    "gn:feature_class":"P",
    "gn:feature_code":"PPL",
    "gn:name":"La Hacienda Solcuautla",
    "gn:population":11,
    "gn:timezone":"America/Mexico_City",
    "iso:country":"MX",
    "wof:name":"La Hacienda Solcuautla",
    "wof:placetype":"locality",
    "wof:population":11
},
  "geometry": {"coordinates":[-95.18167,17.87082999999999],"type":"Point"}
}