{
  "type": "Feature",
  "properties": {
    "gn:admin1_code":"5",
    "gn:admin2_code":"14",
    "gn:asciiname":"Nueva Ucrania",
    "gn:country_code":"MX",
    "gn:dem":1143,
    "gn:feature_class":"P",
    "gn:feature_code":"PPL",
    "gn:name":"Nueva Ucrania",
    "gn:population":51,
    "gn:timezone":"America/Mexico_City",
    "iso:country":"MX",
    "wof:name":"Nueva Ucrania",
    "wof:placetype":"locality",
    "wof:population":51
},
  "geometry": {"coordinates":[-92.73417000000001,17.04944],"type":"Point"}
}