{
  "type": "Feature",
  "properties": {
    "gn:admin1_code":"26.0",
    "gn:admin2_code":"52.0",
    "gn:asciiname":"El Hechadero",
    "gn:country_code":"MX",
    "gn:dem":1406,
    "gn:feature_class":"P",
    "gn:feature_code":"PPL",
    "gn:name":"El Hechadero",
    "gn:population":0,
    "gn:timezone":"America/Hermosillo",
    "iso:country":"MX",
    "name:spa_x_preferred":[
        "El Hechadero"
    ],
    "wof:name":"El Hechadero",
    "wof:placetype":"locality"
},
  "geometry": {"coordinates":[-108.94795999999999,28.63498],"type":"Point"}
}