{
  "type": "Feature",
  "properties": {
    "gn:admin1_code":"16",
    "gn:admin2_code":"112.0",
    "gn:asciiname":"La Mojonera",
    "gn:country_code":"MX",
    "gn:dem":2112,
    "gn:feature_class":"P",
    "gn:feature_code":"PPL",
    "gn:name":"La Mojonera",
    "gn:population":221,
    "gn:timezone":"America/Mexico_City",
    "iso:country":"MX",
    "wof:name":"La Mojonera",
    "wof:placetype":"locality",
    "wof:population":221
},
  "geometry": {"coordinates":[-100.32333,19.43222],"type":"Point"}
}