{
  "type": "Feature",
  "properties": {
    "gn:admin1_code":"3.0",
    "gn:admin2_code":"1.0",
    "gn:asciiname":"Ley Federal de Aguas Numero Cuatro",
    "gn:country_code":"MX",
    "gn:dem":81,
    "gn:feature_class":"P",
    "gn:feature_code":"PPL",
    "gn:name":"Ley Federal de Aguas N\u00famero Cuatro",
    "gn:population":0,
    "gn:timezone":"America/Mazatlan",
    "iso:country":"MX",
    "name:spa_x_preferred":[
        "Ley Federal de Aguas N\u00famero Cuatro"
    ],
    "wof:name":"Ley Federal de Aguas Numero Cuatro",
    "wof:placetype":"locality"
},
  "geometry": {"coordinates":[-111.56161000000002,25.20313],"type":"Point"}
}