{
  "type": "Feature",
  "properties": {
    "gn:admin1_code":"4",
    "gn:admin2_code":"9.0",
    "gn:asciiname":"Yozuch",
    "gn:country_code":"MX",
    "gn:dem":56,
    "gn:feature_class":"P",
    "gn:feature_code":"PPL",
    "gn:name":"Yozuch",
    "gn:population":0,
    "gn:timezone":"America/Merida",
    "iso:country":"MX",
    "name:spa_x_preferred":[
        "Yozuch"
    ],
    "name:und_x_variant":[
        "Voz\u00fachil"
    ],
    "wof:name":"Yozuch",
    "wof:placetype":"locality"
},
  "geometry": {"coordinates":[-90.31236,18.53229],"type":"Point"}
}