{
  "type": "Feature",
  "properties": {
    "gn:admin1_code":"30",
    "gn:admin2_code":"182.0",
    "gn:asciiname":"El Tabachin",
    "gn:country_code":"MX",
    "gn:dem":1547,
    "gn:feature_class":"P",
    "gn:feature_code":"PPL",
    "gn:name":"El Tabach\u00edn",
    "gn:population":0,
    "gn:timezone":"America/Mexico_City",
    "iso:country":"MX",
    "name:spa_x_preferred":[
        "El Tabach\u00edn"
    ],
    "wof:name":"El Tabachin",
    "wof:placetype":"locality"
},
  "geometry": {"coordinates":[-96.96362999999999,19.56502],"type":"Point"}
}