{
  "type": "Feature",
  "properties": {
    "gn:admin1_code":"10.0",
    "gn:admin2_code":"35.0",
    "gn:asciiname":"Los Desechos",
    "gn:country_code":"MX",
    "gn:dem":2455,
    "gn:feature_class":"P",
    "gn:feature_code":"PPL",
    "gn:name":"Los Desechos",
    "gn:population":0,
    "gn:timezone":"America/Monterrey",
    "iso:country":"MX",
    "name:spa_x_preferred":[
        "Los Desechos"
    ],
    "name:und_x_variant":[
        "Desechos",
        "Los Dechos"
    ],
    "wof:name":"Los Desechos",
    "wof:placetype":"locality"
},
  "geometry": {"coordinates":[-106.29631999999999,25.60041],"type":"Point"}
}