{
  "type": "Feature",
  "properties": {
    "gn:admin1_code":"6",
    "gn:admin2_code":"64.0",
    "gn:asciiname":"Los Encinos",
    "gn:country_code":"MX",
    "gn:dem":1702,
    "gn:feature_class":"P",
    "gn:feature_code":"PPL",
    "gn:name":"Los Encinos",
    "gn:population":6,
    "gn:timezone":"America/Chihuahua",
    "iso:country":"MX",
    "wof:name":"Los Encinos",
    "wof:placetype":"locality",
    "wof:population":6
},
  "geometry": {"coordinates":[-106.40796,27.12706],"type":"Point"}
}