{
  "type": "Feature",
  "properties": {
    "gn:admin1_code":"25",
    "gn:admin2_code":"16.0",
    "gn:asciiname":"El Pujido",
    "gn:country_code":"MX",
    "gn:dem":58,
    "gn:feature_class":"P",
    "gn:feature_code":"PPL",
    "gn:name":"El Pujido",
    "gn:population":56,
    "gn:timezone":"America/Mazatlan",
    "iso:country":"MX",
    "wof:name":"El Pujido",
    "wof:placetype":"locality",
    "wof:population":56
},
  "geometry": {"coordinates":[-106.61937,23.88297],"type":"Point"}
}