{
  "type": "Feature",
  "properties": {
    "gn:admin1_code":"20",
    "gn:admin2_code":"435.0",
    "gn:asciiname":"Orilla del Mar",
    "gn:country_code":"MX",
    "gn:dem":1475,
    "gn:feature_class":"P",
    "gn:feature_code":"PPL",
    "gn:name":"Orilla del Mar",
    "gn:population":202,
    "gn:timezone":"America/Mexico_City",
    "iso:country":"MX",
    "wof:name":"Orilla del Mar",
    "wof:placetype":"locality",
    "wof:population":202
},
  "geometry": {"coordinates":[-95.95972,16.985],"type":"Point"}
}