{
  "type": "Feature",
  "properties": {
    "gn:admin1_code":"30",
    "gn:admin2_code":"82.0",
    "gn:asciiname":"Retorno el Diablo",
    "gn:country_code":"MX",
    "gn:dem":6,
    "gn:feature_class":"P",
    "gn:feature_code":"PPL",
    "gn:name":"Retorno el Diablo",
    "gn:population":6,
    "gn:timezone":"America/Mexico_City",
    "iso:country":"MX",
    "wof:name":"Retorno el Diablo",
    "wof:placetype":"locality",
    "wof:population":6
},
  "geometry": {"coordinates":[-94.45694,18.035],"type":"Point"}
}