{
  "type": "Feature",
  "properties": {
    "gn:admin1_code":"16.0",
    "gn:admin2_code":"34.0",
    "gn:asciiname":"Las Pitahayas",
    "gn:country_code":"MX",
    "gn:dem":2338,
    "gn:feature_class":"P",
    "gn:feature_code":"PPL",
    "gn:name":"Las Pitahayas",
    "gn:population":0,
    "gn:timezone":"America/Mexico_City",
    "iso:country":"MX",
    "name:spa_x_preferred":[
        "Las Pitahayas"
    ],
    "wof:name":"Las Pitahayas",
    "wof:placetype":"locality"
},
  "geometry": {"coordinates":[-100.73211000000001,19.55738],"type":"Point"}
}