{
  "type": "Feature",
  "properties": {
    "gn:admin1_code":"12",
    "gn:admin2_code":"73.0",
    "gn:asciiname":"Las Paracatas",
    "gn:country_code":"MX",
    "gn:dem":272,
    "gn:feature_class":"P",
    "gn:feature_code":"PPL",
    "gn:name":"Las Par\u00e1catas",
    "gn:population":0,
    "gn:timezone":"America/Mexico_City",
    "iso:country":"MX",
    "name:spa_x_preferred":[
        "Las Par\u00e1catas"
    ],
    "wof:name":"Las Paracatas",
    "wof:placetype":"locality"
},
  "geometry": {"coordinates":[-101.12533000000001,18.45576],"type":"Point"}
}