{
  "type": "Feature",
  "properties": {
    "gn:admin1_code":"14.0",
    "gn:admin2_code":"49.0",
    "gn:asciiname":"Los Tepeguajes",
    "gn:country_code":"MX",
    "gn:dem":795,
    "gn:feature_class":"P",
    "gn:feature_code":"PPL",
    "gn:name":"Los Tepeguajes",
    "gn:population":0,
    "gn:timezone":"America/Mexico_City",
    "iso:country":"MX",
    "name:spa_x_preferred":[
        "Los Tepeguajes"
    ],
    "wof:name":"Los Tepeguajes",
    "wof:placetype":"locality"
},
  "geometry": {"coordinates":[-103.02697000000001,19.38254],"type":"Point"}
}