{
  "type": "Feature",
  "properties": {
    "gn:admin1_code":"12.0",
    "gn:admin2_code":"32.0",
    "gn:asciiname":"Ixcateopan",
    "gn:country_code":"MX",
    "gn:dem":2352,
    "gn:feature_class":"P",
    "gn:feature_code":"PPL",
    "gn:name":"Ixcateopan",
    "gn:population":0,
    "gn:timezone":"America/Mexico_City",
    "iso:country":"MX",
    "name:spa_x_preferred":[
        "Ixcateopan"
    ],
    "wof:name":"Ixcateopan",
    "wof:placetype":"locality"
},
  "geometry": {"coordinates":[-100.01085,17.54045],"type":"Point"}
}