{
  "type": "Feature",
  "properties": {
    "gn:admin1_code":"6.0",
    "gn:admin2_code":"11.0",
    "gn:asciiname":"Alta Vista",
    "gn:country_code":"MX",
    "gn:dem":1232,
    "gn:feature_class":"P",
    "gn:feature_code":"PPL",
    "gn:name":"Alta Vista",
    "gn:population":0,
    "gn:timezone":"America/Chihuahua",
    "iso:country":"MX",
    "wof:name":"Alta Vista",
    "wof:placetype":"locality"
},
  "geometry": {"coordinates":[-105.19785,27.71794],"type":"Point"}
}