{
  "type": "Feature",
  "properties": {
    "gn:admin1_code":"27",
    "gn:admin2_code":"8.0",
    "gn:asciiname":"Los Manantiales",
    "gn:country_code":"MX",
    "gn:dem":25,
    "gn:feature_class":"P",
    "gn:feature_code":"PPL",
    "gn:name":"Los Manantiales",
    "gn:population":0,
    "gn:timezone":"America/Mexico_City",
    "iso:country":"MX",
    "name:spa_x_preferred":[
        "Los Manantiales"
    ],
    "wof:name":"Los Manantiales",
    "wof:placetype":"locality"
},
  "geometry": {"coordinates":[-93.7375,17.7875],"type":"Point"}
}