{
  "type": "Feature",
  "properties": {
    "gn:admin1_code":"22",
    "gn:admin2_code":"13.0",
    "gn:asciiname":"El Atoron",
    "gn:country_code":"MX",
    "gn:dem":1448,
    "gn:feature_class":"P",
    "gn:feature_code":"PPL",
    "gn:name":"El Ator\u00f3n",
    "gn:population":142,
    "gn:timezone":"America/Mexico_City",
    "iso:country":"MX",
    "name:und_x_variant":[
        "El Ator\u00f3n"
    ],
    "wof:name":"El Atoron",
    "wof:placetype":"locality",
    "wof:population":142
},
  "geometry": {"coordinates":[-99.69417,21.05722],"type":"Point"}
}