{
  "type": "Feature",
  "properties": {
    "gn:admin1_code":"1",
    "gn:admin2_code":"10.0",
    "gn:asciiname":"Parcela Escuela Secundaria Tecnica Numero 4",
    "gn:country_code":"MX",
    "gn:dem":2014,
    "gn:feature_class":"P",
    "gn:feature_code":"PPL",
    "gn:name":"Parcela Escuela Secundaria T\u00e9cnica N\u00famero 4",
    "gn:population":4,
    "gn:timezone":"America/Mexico_City",
    "iso:country":"MX",
    "name:und_x_variant":[
        "Parcela Escuela Secundaria T\u00e9cnica N\u00famero 4"
    ],
    "wof:name":"Parcela Escuela Secundaria Tecnica Numero 4",
    "wof:placetype":"locality",
    "wof:population":4
},
  "geometry": {"coordinates":[-101.97278,21.91861],"type":"Point"}
}