{
  "type": "Feature",
  "properties": {
    "gn:admin1_code":"24",
    "gn:admin2_code":"15.0",
    "gn:asciiname":"Santa Ana de Zaragoza",
    "gn:country_code":"MX",
    "gn:dem":1872,
    "gn:feature_class":"P",
    "gn:feature_code":"PPL",
    "gn:name":"Santa Ana de Zaragoza",
    "gn:population":0,
    "gn:timezone":"America/Mexico_City",
    "iso:country":"MX",
    "name:spa_x_preferred":[
        "Santa Ana de Zaragoza"
    ],
    "name:und_x_variant":[
        "Santa Ana"
    ],
    "wof:name":"Santa Ana de Zaragoza",
    "wof:placetype":"locality"
},
  "geometry": {"coordinates":[-101.01984,23.06688],"type":"Point"}
}