{
  "type": "Feature",
  "properties": {
    "gn:admin1_code":"24",
    "gn:admin2_code":"54",
    "gn:asciiname":"Pozo Tapado",
    "gn:country_code":"MX",
    "gn:dem":1353,
    "gn:feature_class":"P",
    "gn:feature_code":"PPL",
    "gn:name":"Pozo Tapado",
    "gn:population":23,
    "gn:timezone":"America/Mexico_City",
    "iso:country":"MX",
    "wof:name":"Pozo Tapado",
    "wof:placetype":"locality",
    "wof:population":23
},
  "geometry": {"coordinates":[-99.08722,21.33194],"type":"Point"}
}