{
  "type": "Feature",
  "properties": {
    "gn:admin1_code":"16",
    "gn:admin2_code":"34",
    "gn:asciiname":"Las Espinas de la Union",
    "gn:country_code":"MX",
    "gn:dem":2526,
    "gn:feature_class":"P",
    "gn:feature_code":"PPL",
    "gn:name":"Las Espinas de la Uni\u00f3n",
    "gn:population":49,
    "gn:timezone":"America/Mexico_City",
    "iso:country":"MX",
    "name:und_x_variant":[
        "Las Espinas de la Uni\u00f3n"
    ],
    "wof:name":"Las Espinas de la Union",
    "wof:placetype":"locality",
    "wof:population":49
},
  "geometry": {"coordinates":[-100.65833000000001,19.62056],"type":"Point"}
}