{
  "type": "Feature",
  "properties": {
    "gn:admin1_code":"6.0",
    "gn:admin2_code":"1.0",
    "gn:asciiname":"El Carrizal",
    "gn:country_code":"MX",
    "gn:dem":1225,
    "gn:feature_class":"P",
    "gn:feature_code":"PPL",
    "gn:name":"El Carrizal",
    "gn:population":0,
    "gn:timezone":"America/Chihuahua",
    "iso:country":"MX",
    "name:spa_x_preferred":[
        "El Carrizal"
    ],
    "wof:name":"El Carrizal",
    "wof:placetype":"locality"
},
  "geometry": {"coordinates":[-106.65336000000001,30.56112000000001],"type":"Point"}
}