{
  "type": "Feature",
  "properties": {
    "gn:admin1_code":"26.0",
    "gn:admin2_code":"25.0",
    "gn:asciiname":"Pozo Cincuenta y Uno",
    "gn:country_code":"MX",
    "gn:dem":63,
    "gn:feature_class":"P",
    "gn:feature_code":"PPL",
    "gn:name":"Pozo Cincuenta y Uno",
    "gn:population":0,
    "gn:timezone":"America/Hermosillo",
    "iso:country":"MX",
    "name:spa_x_preferred":[
        "Pozo Cincuenta y Uno"
    ],
    "wof:name":"Pozo Cincuenta y Uno",
    "wof:placetype":"locality"
},
  "geometry": {"coordinates":[-110.66073,28.12722],"type":"Point"}
}