{
  "type": "Feature",
  "properties": {
    "gn:admin1_code":"21",
    "gn:admin2_code":"3",
    "gn:asciiname":"Piedra Blanca",
    "gn:country_code":"MX",
    "gn:dem":1217,
    "gn:feature_class":"P",
    "gn:feature_code":"PPL",
    "gn:name":"Piedra Blanca",
    "gn:population":40,
    "gn:timezone":"America/Mexico_City",
    "iso:country":"MX",
    "wof:name":"Piedra Blanca",
    "wof:placetype":"locality",
    "wof:population":40
},
  "geometry": {"coordinates":[-98.03691000000001,18.10021],"type":"Point"}
}