{
  "type": "Feature",
  "properties": {
    "gn:admin1_code":"5",
    "gn:admin2_code":"52.0",
    "gn:asciiname":"Matias Castellanos",
    "gn:country_code":"MX",
    "gn:dem":1213,
    "gn:feature_class":"P",
    "gn:feature_code":"PPL",
    "gn:name":"Mat\u00edas Castellanos",
    "gn:population":275,
    "gn:timezone":"America/Mexico_City",
    "iso:country":"MX",
    "name:und_x_variant":[
        "Mat\u00edas Castellanos"
    ],
    "wof:name":"Matias Castellanos",
    "wof:placetype":"locality",
    "wof:population":275
},
  "geometry": {"coordinates":[-91.77972,16.34083],"type":"Point"}
}