{
  "type": "Feature",
  "properties": {
    "gn:admin1_code":"26.0",
    "gn:admin2_code":"54.0",
    "gn:asciiname":"Aguaje del Monte",
    "gn:country_code":"MX",
    "gn:dem":536,
    "gn:feature_class":"P",
    "gn:feature_code":"PPL",
    "gn:name":"Aguaje del Monte",
    "gn:population":0,
    "gn:timezone":"America/Hermosillo",
    "iso:country":"MX",
    "name:und_x_variant":[
        "Rancho Aguaje del Monte",
        "Aguaje Monte",
        "Aguaje del Monte"
    ],
    "wof:name":"Aguaje del Monte",
    "wof:placetype":"locality"
},
  "geometry": {"coordinates":[-109.82089999999999,28.71895],"type":"Point"}
}