{
  "type": "Feature",
  "properties": {
    "gn:admin1_code":"9",
    "gn:admin2_code":"11",
    "gn:asciiname":"Santa Catarina [Lienzo Charro]",
    "gn:country_code":"MX",
    "gn:dem":2243,
    "gn:feature_class":"P",
    "gn:feature_code":"PPL",
    "gn:name":"Santa Catarina [Lienzo Charro]",
    "gn:population":16,
    "gn:timezone":"America/Mexico_City",
    "iso:country":"MX",
    "wof:name":"Santa Catarina [Lienzo Charro]",
    "wof:placetype":"locality",
    "wof:population":16
},
  "geometry": {"coordinates":[-98.96972,19.30472],"type":"Point"}
}