{
  "type": "Feature",
  "properties": {
    "gn:admin1_code":"18.0",
    "gn:admin2_code":"19.0",
    "gn:asciiname":"La Tizatera",
    "gn:country_code":"MX",
    "gn:dem":1392,
    "gn:feature_class":"P",
    "gn:feature_code":"PPL",
    "gn:name":"La Tizatera",
    "gn:population":0,
    "gn:timezone":"America/Mazatlan",
    "iso:country":"MX",
    "name:spa_x_preferred":[
        "La Tizatera"
    ],
    "wof:name":"La Tizatera",
    "wof:placetype":"locality"
},
  "geometry": {"coordinates":[-104.13663,21.34327],"type":"Point"}
}