{
  "type": "Feature",
  "properties": {
    "gn:admin1_code":"24",
    "gn:admin2_code":"34.0",
    "gn:asciiname":"El Pando",
    "gn:country_code":"MX",
    "gn:dem":28,
    "gn:feature_class":"P",
    "gn:feature_code":"PPL",
    "gn:name":"El Pando",
    "gn:population":0,
    "gn:timezone":"America/Mexico_City",
    "iso:country":"MX",
    "wof:name":"El Pando",
    "wof:placetype":"locality"
},
  "geometry": {"coordinates":[-98.56667,21.86667000000001],"type":"Point"}
}