{
  "type": "Feature",
  "properties": {
    "gn:admin1_code":"16.0",
    "gn:admin2_code":"89.0",
    "gn:asciiname":"Corralitos",
    "gn:country_code":"MX",
    "gn:dem":489,
    "gn:feature_class":"P",
    "gn:feature_code":"PPL",
    "gn:name":"Corralitos",
    "gn:population":0,
    "gn:timezone":"America/Mexico_City",
    "iso:country":"MX",
    "name:spa_x_preferred":[
        "Corralitos"
    ],
    "wof:name":"Corralitos",
    "wof:placetype":"locality"
},
  "geometry": {"coordinates":[-102.92788,19.02794],"type":"Point"}
}