{
  "type": "Feature",
  "properties": {
    "gn:admin1_code":"30.0",
    "gn:admin2_code":"181.0",
    "gn:asciiname":"El Alacran",
    "gn:country_code":"MX",
    "gn:dem":17,
    "gn:feature_class":"P",
    "gn:feature_code":"PPL",
    "gn:name":"El Alacr\u00e1n",
    "gn:population":0,
    "gn:timezone":"America/Mexico_City",
    "iso:country":"MX",
    "name:spa_x_preferred":[
        "El Alacr\u00e1n"
    ],
    "wof:name":"El Alacran",
    "wof:placetype":"locality"
},
  "geometry": {"coordinates":[-96.11169,18.65831],"type":"Point"}
}