{
  "type": "Feature",
  "properties": {
    "gn:admin1_code":"32",
    "gn:admin2_code":"40.0",
    "gn:asciiname":"El Sauz",
    "gn:country_code":"MX",
    "gn:dem":2117,
    "gn:feature_class":"P",
    "gn:feature_code":"PPL",
    "gn:name":"El Sauz",
    "gn:population":0,
    "gn:timezone":"America/Mexico_City",
    "iso:country":"MX",
    "name:spa_x_preferred":[
        "El Sauz"
    ],
    "wof:name":"El Sauz",
    "wof:placetype":"locality"
},
  "geometry": {"coordinates":[-103.21872,23.54913],"type":"Point"}
}