{
  "type": "Feature",
  "properties": {
    "gn:admin1_code":"15",
    "gn:admin2_code":"39.0",
    "gn:asciiname":"Ejidos de Xalpa (Camino de los Alcanfores)",
    "gn:country_code":"MX",
    "gn:dem":2297,
    "gn:feature_class":"P",
    "gn:feature_code":"PPL",
    "gn:name":"Ejidos de Xalpa (Camino de los Alcanfores)",
    "gn:population":69,
    "gn:timezone":"America/Mexico_City",
    "iso:country":"MX",
    "wof:name":"Ejidos de Xalpa (Camino de los Alcanfores)",
    "wof:placetype":"locality",
    "wof:population":69
},
  "geometry": {"coordinates":[-98.85178999999999,19.33723],"type":"Point"}
}