{
  "type": "Feature",
  "properties": {
    "gn:admin1_code":"21",
    "gn:admin2_code":"208.0",
    "gn:asciiname":"Popotohuilco",
    "gn:country_code":"MX",
    "gn:dem":2275,
    "gn:feature_class":"P",
    "gn:feature_code":"PPL",
    "gn:name":"Popotohuilco",
    "gn:population":126,
    "gn:timezone":"America/Mexico_City",
    "iso:country":"MX",
    "wof:name":"Popotohuilco",
    "wof:placetype":"locality",
    "wof:population":126
},
  "geometry": {"coordinates":[-97.9166,19.86369],"type":"Point"}
}