{
  "type": "Feature",
  "properties": {
    "gn:admin1_code":"12",
    "gn:admin2_code":"29",
    "gn:asciiname":"El Chapopote",
    "gn:country_code":"MX",
    "gn:dem":687,
    "gn:feature_class":"P",
    "gn:feature_code":"PPL",
    "gn:name":"El Chapopote",
    "gn:population":17,
    "gn:timezone":"America/Mexico_City",
    "iso:country":"MX",
    "wof:name":"El Chapopote",
    "wof:placetype":"locality",
    "wof:population":17
},
  "geometry": {"coordinates":[-99.52321999999999,17.2319],"type":"Point"}
}