{
  "type": "Feature",
  "properties": {
    "gn:admin1_code":"1",
    "gn:admin2_code":"9.0",
    "gn:asciiname":"Santa Catalina [Rancho]",
    "gn:country_code":"MX",
    "gn:dem":1911,
    "gn:feature_class":"P",
    "gn:feature_code":"PPL",
    "gn:name":"Santa Catalina [Rancho]",
    "gn:population":7,
    "gn:timezone":"America/Mexico_City",
    "iso:country":"MX",
    "wof:name":"Santa Catalina [Rancho]",
    "wof:placetype":"locality",
    "wof:population":7
},
  "geometry": {"coordinates":[-102.26528,22.19028],"type":"Point"}
}