{
  "type": "Feature",
  "properties": {
    "gn:admin1_code":"19.0",
    "gn:admin2_code":"20.0",
    "gn:asciiname":"El Oscurito",
    "gn:country_code":"MX",
    "gn:dem":146,
    "gn:feature_class":"P",
    "gn:feature_code":"PPL",
    "gn:name":"El Oscurito",
    "gn:population":0,
    "gn:timezone":"America/Monterrey",
    "iso:country":"MX",
    "name:spa_x_preferred":[
        "El Oscurito"
    ],
    "wof:name":"El Oscurito",
    "wof:placetype":"locality"
},
  "geometry": {"coordinates":[-99.09090999999999,25.72621],"type":"Point"}
}