{
  "type": "Feature",
  "properties": {
    "gn:admin1_code":"16",
    "gn:admin2_code":"6",
    "gn:asciiname":"Santa Rosa",
    "gn:country_code":"MX",
    "gn:dem":273,
    "gn:feature_class":"P",
    "gn:feature_code":"PPL",
    "gn:name":"Santa Rosa",
    "gn:population":31,
    "gn:timezone":"America/Mexico_City",
    "iso:country":"MX",
    "wof:name":"Santa Rosa",
    "wof:placetype":"locality",
    "wof:population":31
},
  "geometry": {"coordinates":[-102.50917,19.13389],"type":"Point"}
}