{
  "type": "Feature",
  "properties": {
    "gn:admin1_code":"30",
    "gn:admin2_code":"124.0",
    "gn:asciiname":"Heladio Garcia Vazquez",
    "gn:country_code":"MX",
    "gn:dem":85,
    "gn:feature_class":"P",
    "gn:feature_code":"PPL",
    "gn:name":"Heladio Garc\u00eda V\u00e1zquez",
    "gn:population":264,
    "gn:timezone":"America/Mexico_City",
    "iso:country":"MX",
    "name:und_x_variant":[
        "Heladio Garc\u00eda V\u00e1zquez"
    ],
    "wof:name":"Heladio Garcia Vazquez",
    "wof:placetype":"locality",
    "wof:population":264
},
  "geometry": {"coordinates":[-97.15861,20.48806],"type":"Point"}
}