{
  "type": "Feature",
  "properties": {
    "gn:admin1_code":"11",
    "gn:admin2_code":"35.0",
    "gn:asciiname":"Mesas de Almanza",
    "gn:country_code":"MX",
    "gn:dem":2167,
    "gn:feature_class":"P",
    "gn:feature_code":"PPL",
    "gn:name":"Mesas de Almanza",
    "gn:population":66,
    "gn:timezone":"America/Mexico_City",
    "iso:country":"MX",
    "wof:name":"Mesas de Almanza",
    "wof:placetype":"locality",
    "wof:population":66
},
  "geometry": {"coordinates":[-101.06083,20.7775],"type":"Point"}
}