{
  "type": "Feature",
  "properties": {
    "gn:admin1_code":"16.0",
    "gn:admin2_code":"8.0",
    "gn:asciiname":"Hizote",
    "gn:country_code":"MX",
    "gn:dem":550,
    "gn:feature_class":"P",
    "gn:feature_code":"PPL",
    "gn:name":"Hizote",
    "gn:population":0,
    "gn:timezone":"America/Mexico_City",
    "iso:country":"MX",
    "wof:name":"Hizote",
    "wof:placetype":"locality"
},
  "geometry": {"coordinates":[-102.94558000000001,18.33104],"type":"Point"}
}