{
  "type": "Feature",
  "properties": {
    "gn:admin1_code":"16.0",
    "gn:admin2_code":"15.0",
    "gn:asciiname":"La Majada",
    "gn:country_code":"MX",
    "gn:dem":1589,
    "gn:feature_class":"P",
    "gn:feature_code":"PPL",
    "gn:name":"La Majada",
    "gn:population":0,
    "gn:timezone":"America/Mexico_City",
    "iso:country":"MX",
    "name:spa_x_preferred":[
        "La Majada"
    ],
    "wof:name":"La Majada",
    "wof:placetype":"locality"
},
  "geometry": {"coordinates":[-102.89722999999999,18.41072],"type":"Point"}
}