{
  "type": "Feature",
  "properties": {
    "gn:admin1_code":"14",
    "gn:admin2_code":"53",
    "gn:asciiname":"Las Cajas",
    "gn:country_code":"MX",
    "gn:dem":1840,
    "gn:feature_class":"P",
    "gn:feature_code":"PPL",
    "gn:name":"Las Cajas",
    "gn:population":11,
    "gn:timezone":"America/Mexico_City",
    "iso:country":"MX",
    "wof:name":"Las Cajas",
    "wof:placetype":"locality",
    "wof:population":11
},
  "geometry": {"coordinates":[-102.08389,21.23472000000001],"type":"Point"}
}