{
  "type": "Feature",
  "properties": {
    "gn:admin1_code":"29",
    "gn:admin2_code":"25.0",
    "gn:asciiname":"Ex-Hacienda Guadalupe Xaltelulco",
    "gn:country_code":"MX",
    "gn:dem":2480,
    "gn:feature_class":"P",
    "gn:feature_code":"PPL",
    "gn:name":"Ex-Hacienda Guadalupe Xaltelulco",
    "gn:population":14,
    "gn:timezone":"America/Mexico_City",
    "iso:country":"MX",
    "wof:name":"Ex-Hacienda Guadalupe Xaltelulco",
    "wof:placetype":"locality",
    "wof:population":14
},
  "geometry": {"coordinates":[-98.14107,19.17513],"type":"Point"}
}