{
  "type": "Feature",
  "properties": {
    "gn:admin1_code":"23",
    "gn:admin2_code":"8",
    "gn:asciiname":"Puerto Chile",
    "gn:country_code":"MX",
    "gn:dem":6,
    "gn:feature_class":"P",
    "gn:feature_code":"PPL",
    "gn:name":"Puerto Chile",
    "gn:population":12,
    "gn:timezone":"America/Cancun",
    "iso:country":"MX",
    "wof:name":"Puerto Chile",
    "wof:placetype":"locality",
    "wof:population":12
},
  "geometry": {"coordinates":[-87.26666999999998,20.47167],"type":"Point"}
}