{
  "type": "Feature",
  "properties": {
    "gn:admin1_code":"18",
    "gn:admin2_code":"16.0",
    "gn:asciiname":"Loma de los Changos",
    "gn:country_code":"MX",
    "gn:dem":13,
    "gn:feature_class":"P",
    "gn:feature_code":"PPL",
    "gn:name":"Loma de los Changos",
    "gn:population":0,
    "gn:timezone":"America/Mazatlan",
    "iso:country":"MX",
    "name:spa_x_preferred":[
        "Loma de los Changos"
    ],
    "wof:name":"Loma de los Changos",
    "wof:placetype":"locality"
},
  "geometry": {"coordinates":[-105.41849999999999,22.34813],"type":"Point"}
}