{
  "type": "Feature",
  "properties": {
    "gn:admin1_code":"6",
    "gn:admin2_code":"7.0",
    "gn:asciiname":"Arroyo de Chabela",
    "gn:country_code":"MX",
    "gn:dem":2559,
    "gn:feature_class":"P",
    "gn:feature_code":"PPL",
    "gn:name":"Arroyo de Chabela",
    "gn:population":8,
    "gn:timezone":"America/Chihuahua",
    "iso:country":"MX",
    "wof:name":"Arroyo de Chabela",
    "wof:placetype":"locality",
    "wof:population":8
},
  "geometry": {"coordinates":[-106.56999999999999,26.43319],"type":"Point"}
}