{
  "type": "Feature",
  "properties": {
    "gn:admin1_code":"5",
    "gn:admin2_code":"30.0",
    "gn:asciiname":"El Cairo",
    "gn:country_code":"MX",
    "gn:dem":658,
    "gn:feature_class":"P",
    "gn:feature_code":"PPL",
    "gn:name":"El Cairo",
    "gn:population":6,
    "gn:timezone":"America/Mexico_City",
    "iso:country":"MX",
    "wof:name":"El Cairo",
    "wof:placetype":"locality",
    "wof:population":6
},
  "geometry": {"coordinates":[-92.32056,15.84139],"type":"Point"}
}