{
  "type": "Feature",
  "properties": {
    "gn:admin1_code":"7",
    "gn:admin2_code":"27.0",
    "gn:asciiname":"Quitanillo",
    "gn:country_code":"MX",
    "gn:dem":1486,
    "gn:feature_class":"P",
    "gn:feature_code":"PPL",
    "gn:name":"Quitanillo",
    "gn:population":0,
    "gn:timezone":"America/Monterrey",
    "iso:country":"MX",
    "name:spa_x_preferred":[
        "Quitanillo"
    ],
    "wof:name":"Quitanillo",
    "wof:placetype":"locality"
},
  "geometry": {"coordinates":[-101.04519000000001,25.54685],"type":"Point"}
}