{
  "type": "Feature",
  "properties": {
    "gn:admin1_code":"30",
    "gn:admin2_code":"159.0",
    "gn:asciiname":"Tonalapa",
    "gn:country_code":"MX",
    "gn:dem":2120,
    "gn:feature_class":"P",
    "gn:feature_code":"PPL",
    "gn:name":"Tonalapa",
    "gn:population":222,
    "gn:timezone":"America/Mexico_City",
    "iso:country":"MX",
    "wof:name":"Tonalapa",
    "wof:placetype":"locality",
    "wof:population":222
},
  "geometry": {"coordinates":[-97.06833,18.47417],"type":"Point"}
}