{
  "type": "Feature",
  "properties": {
    "gn:admin1_code":"13",
    "gn:admin2_code":"49",
    "gn:asciiname":"El Pemuche",
    "gn:country_code":"MX",
    "gn:dem":931,
    "gn:feature_class":"P",
    "gn:feature_code":"PPL",
    "gn:name":"El Pemuche",
    "gn:population":38,
    "gn:timezone":"America/Mexico_City",
    "iso:country":"MX",
    "wof:name":"El Pemuche",
    "wof:placetype":"locality",
    "wof:population":38
},
  "geometry": {"coordinates":[-99.0462,21.26982000000001],"type":"Point"}
}