{
  "type": "Feature",
  "properties": {
    "gn:admin1_code":"21",
    "gn:admin2_code":"180.0",
    "gn:asciiname":"Apapacaxco",
    "gn:country_code":"MX",
    "gn:dem":2553,
    "gn:feature_class":"P",
    "gn:feature_code":"PPL",
    "gn:name":"Apapacaxco",
    "gn:population":0,
    "gn:timezone":"America/Mexico_City",
    "iso:country":"MX",
    "name:spa_x_preferred":[
        "Apapacaxco"
    ],
    "wof:name":"Apapacaxco",
    "wof:placetype":"locality"
},
  "geometry": {"coordinates":[-98.56084,19.33921],"type":"Point"}
}