{
  "type": "Feature",
  "properties": {
    "gn:admin1_code":"7",
    "gn:admin2_code":"38.0",
    "gn:asciiname":"Silverio Dominguez Hernandez",
    "gn:country_code":"MX",
    "gn:dem":378,
    "gn:feature_class":"P",
    "gn:feature_code":"PPL",
    "gn:name":"Silverio Dom\u00ednguez Hern\u00e1ndez",
    "gn:population":8,
    "gn:timezone":"America/Monterrey",
    "iso:country":"MX",
    "name:und_x_variant":[
        "Silverio Dom\u00ednguez Hern\u00e1ndez"
    ],
    "wof:name":"Silverio Dominguez Hernandez",
    "wof:placetype":"locality",
    "wof:population":8
},
  "geometry": {"coordinates":[-100.93953,28.44165],"type":"Point"}
}