{
  "type": "Feature",
  "properties": {
    "gn:admin1_code":"12",
    "gn:admin2_code":"3.0",
    "gn:asciiname":"Los Horcones",
    "gn:country_code":"MX",
    "gn:dem":2402,
    "gn:feature_class":"P",
    "gn:feature_code":"PPL",
    "gn:name":"Los Horcones",
    "gn:population":59,
    "gn:timezone":"America/Mexico_City",
    "iso:country":"MX",
    "name:fra_x_preferred":[
        "Los Horcones"
    ],
    "name:por_x_preferred":[
        "Los horcones"
    ],
    "wof:name":"Los Horcones",
    "wof:placetype":"locality",
    "wof:population":59
},
  "geometry": {"coordinates":[-100.64379,17.72132000000001],"type":"Point"}
}