{
  "type": "Feature",
  "properties": {
    "gn:admin1_code":"12.0",
    "gn:admin2_code":"11.0",
    "gn:asciiname":"El Corral",
    "gn:country_code":"MX",
    "gn:dem":854,
    "gn:feature_class":"P",
    "gn:feature_code":"PPL",
    "gn:name":"El Corral",
    "gn:population":0,
    "gn:timezone":"America/Mexico_City",
    "iso:country":"MX",
    "name:spa_x_preferred":[
        "El Corral"
    ],
    "name:spa_x_variant":[
        "El Puerto"
    ],
    "wof:name":"El Corral",
    "wof:placetype":"locality"
},
  "geometry": {"coordinates":[-100.24189,17.39538],"type":"Point"}
}