{
  "type": "Feature",
  "properties": {
    "gn:admin1_code":"20.0",
    "gn:admin2_code":"291.0",
    "gn:asciiname":"Arroyo Moral",
    "gn:country_code":"MX",
    "gn:dem":1814,
    "gn:feature_class":"P",
    "gn:feature_code":"PPL",
    "gn:name":"Arroyo Moral",
    "gn:population":0,
    "gn:timezone":"America/Mexico_City",
    "iso:country":"MX",
    "name:spa_x_preferred":[
        "Arroyo Moral"
    ],
    "wof:name":"Arroyo Moral",
    "wof:placetype":"locality"
},
  "geometry": {"coordinates":[-96.779,16.15305],"type":"Point"}
}