{
  "type": "Feature",
  "properties": {
    "gn:admin1_code":"6",
    "gn:admin2_code":"65",
    "gn:asciiname":"Las Sabanillas",
    "gn:country_code":"MX",
    "gn:dem":1605,
    "gn:feature_class":"P",
    "gn:feature_code":"PPL",
    "gn:name":"Las Sabanillas",
    "gn:population":9,
    "gn:timezone":"America/Chihuahua",
    "iso:country":"MX",
    "wof:name":"Las Sabanillas",
    "wof:placetype":"locality",
    "wof:population":9
},
  "geometry": {"coordinates":[-108.08880000000001,27.03632],"type":"Point"}
}