{
  "type": "Feature",
  "properties": {
    "gn:admin1_code":"16",
    "gn:admin2_code":"8",
    "gn:asciiname":"Los Cabezos",
    "gn:country_code":"MX",
    "gn:dem":1011,
    "gn:feature_class":"P",
    "gn:feature_code":"PPL",
    "gn:name":"Los Cabezos",
    "gn:population":10,
    "gn:timezone":"America/Mexico_City",
    "iso:country":"MX",
    "wof:name":"Los Cabezos",
    "wof:placetype":"locality",
    "wof:population":10
},
  "geometry": {"coordinates":[-103.18556,18.37667],"type":"Point"}
}