{
  "type": "Feature",
  "properties": {
    "gn:admin1_code":"26",
    "gn:admin2_code":"30.0",
    "gn:asciiname":"Santa Amalia",
    "gn:country_code":"MX",
    "gn:dem":183,
    "gn:feature_class":"P",
    "gn:feature_code":"PPL",
    "gn:name":"Santa Amalia",
    "gn:population":0,
    "gn:timezone":"America/Hermosillo",
    "iso:country":"MX",
    "wof:name":"Santa Amalia",
    "wof:placetype":"locality"
},
  "geometry": {"coordinates":[-111.88943999999999,29.43194],"type":"Point"}
}