{
  "type": "Feature",
  "properties": {
    "gn:admin1_code":"6",
    "gn:admin2_code":"36.0",
    "gn:asciiname":"La Chavinda",
    "gn:country_code":"MX",
    "gn:dem":1340,
    "gn:feature_class":"P",
    "gn:feature_code":"PPL",
    "gn:name":"La Chavinda",
    "gn:population":0,
    "gn:timezone":"America/Chihuahua",
    "iso:country":"MX",
    "name:spa_x_preferred":[
        "La Chavinda"
    ],
    "wof:name":"La Chavinda",
    "wof:placetype":"locality"
},
  "geometry": {"coordinates":[-104.25797,27.54147],"type":"Point"}
}