{
  "type": "Feature",
  "properties": {
    "gn:admin1_code":"20",
    "gn:admin2_code":"73.0",
    "gn:asciiname":"San Marcos Mesoncito",
    "gn:country_code":"MX",
    "gn:dem":1208,
    "gn:feature_class":"P",
    "gn:feature_code":"PPL",
    "gn:name":"San Marcos Mesoncito",
    "gn:population":180,
    "gn:timezone":"America/Mexico_City",
    "iso:country":"MX",
    "wof:name":"San Marcos Mesoncito",
    "wof:placetype":"locality",
    "wof:population":180
},
  "geometry": {"coordinates":[-97.85167,17.09803],"type":"Point"}
}