{
  "type": "Feature",
  "properties": {
    "gn:admin1_code":"31",
    "gn:admin2_code":"28.0",
    "gn:asciiname":"Xlabon Subin",
    "gn:country_code":"MX",
    "gn:dem":4,
    "gn:feature_class":"P",
    "gn:feature_code":"PPL",
    "gn:name":"Xlabon Subin",
    "gn:population":0,
    "gn:timezone":"America/Merida",
    "iso:country":"MX",
    "name:spa_x_preferred":[
        "Xlabon Subin"
    ],
    "name:spa_x_variant":[
        "Xlabonsubin"
    ],
    "wof:name":"Xlabon Subin",
    "wof:placetype":"locality"
},
  "geometry": {"coordinates":[-88.65824000000001,21.36013],"type":"Point"}
}