{
  "type": "Feature",
  "properties": {
    "gn:admin1_code":"14",
    "gn:admin2_code":"120.0",
    "gn:asciiname":"San Antonio",
    "gn:country_code":"MX",
    "gn:dem":1347,
    "gn:feature_class":"P",
    "gn:feature_code":"PPL",
    "gn:name":"San Antonio",
    "gn:population":5,
    "gn:timezone":"America/Mexico_City",
    "iso:country":"MX",
    "wof:name":"San Antonio",
    "wof:placetype":"locality",
    "wof:population":5
},
  "geometry": {"coordinates":[-103.58944,20.84389],"type":"Point"}
}