{
  "type": "Feature",
  "properties": {
    "gn:admin1_code":"19.0",
    "gn:admin2_code":"49.0",
    "gn:asciiname":"El Gueical",
    "gn:country_code":"MX",
    "gn:dem":698,
    "gn:feature_class":"P",
    "gn:feature_code":"PPL",
    "gn:name":"El G\u00fcical",
    "gn:population":0,
    "gn:timezone":"America/Monterrey",
    "iso:country":"MX",
    "name:spa_x_preferred":[
        "El G\u00fcical"
    ],
    "wof:name":"El Gueical",
    "wof:placetype":"locality"
},
  "geometry": {"coordinates":[-100.21961,25.45817000000001],"type":"Point"}
}