{
  "type": "Feature",
  "properties": {
    "gn:admin1_code":"10",
    "gn:admin2_code":"5.0",
    "gn:asciiname":"Las Tinajas",
    "gn:country_code":"MX",
    "gn:dem":2381,
    "gn:feature_class":"P",
    "gn:feature_code":"PPL",
    "gn:name":"Las Tinajas",
    "gn:population":0,
    "gn:timezone":"America/Monterrey",
    "iso:country":"MX",
    "name:spa_x_preferred":[
        "Las Tinajas"
    ],
    "wof:name":"Las Tinajas",
    "wof:placetype":"locality"
},
  "geometry": {"coordinates":[-105.38307,23.92835],"type":"Point"}
}