{
  "type": "Feature",
  "properties": {
    "gn:admin1_code":"22",
    "gn:admin2_code":"17.0",
    "gn:asciiname":"Santillan",
    "gn:country_code":"MX",
    "gn:dem":1922,
    "gn:feature_class":"P",
    "gn:feature_code":"PPL",
    "gn:name":"Santill\u00e1n",
    "gn:population":0,
    "gn:timezone":"America/Mexico_City",
    "iso:country":"MX",
    "name:spa_x_preferred":[
        "Santill\u00e1n"
    ],
    "wof:name":"Santillan",
    "wof:placetype":"locality"
},
  "geometry": {"coordinates":[-99.93951,20.60073],"type":"Point"}
}