{
  "type": "Feature",
  "properties": {
    "gn:admin1_code":"13",
    "gn:admin2_code":"28.0",
    "gn:asciiname":"Oxtomal",
    "gn:country_code":"MX",
    "gn:dem":227,
    "gn:feature_class":"P",
    "gn:feature_code":"PPL",
    "gn:name":"Oxtomal",
    "gn:population":0,
    "gn:timezone":"America/Mexico_City",
    "iso:country":"MX",
    "name:spa_x_preferred":[
        "Oxtomal"
    ],
    "wof:name":"Oxtomal",
    "wof:placetype":"locality"
},
  "geometry": {"coordinates":[-98.46268000000001,21.12466],"type":"Point"}
}