{
  "type": "Feature",
  "properties": {
    "gn:admin1_code":"28",
    "gn:admin2_code":"34.0",
    "gn:asciiname":"El Sauz",
    "gn:country_code":"MX",
    "gn:dem":335,
    "gn:feature_class":"P",
    "gn:feature_code":"PPL",
    "gn:name":"El Sauz",
    "gn:population":0,
    "gn:timezone":"America/Monterrey",
    "iso:country":"MX",
    "name:spa_x_preferred":[
        "El Sauz"
    ],
    "name:und_x_variant":[
        "Sauz"
    ],
    "wof:name":"El Sauz",
    "wof:placetype":"locality"
},
  "geometry": {"coordinates":[-98.77037,24.37502000000001],"type":"Point"}
}