{
  "type": "Feature",
  "properties": {
    "gn:admin1_code":"7",
    "gn:admin2_code":"23.0",
    "gn:asciiname":"El Bandido",
    "gn:country_code":"MX",
    "gn:dem":1213,
    "gn:feature_class":"P",
    "gn:feature_code":"PPL",
    "gn:name":"El Bandido",
    "gn:population":0,
    "gn:timezone":"America/Monterrey",
    "iso:country":"MX",
    "name:spa_x_preferred":[
        "El Bandido"
    ],
    "wof:name":"El Bandido",
    "wof:placetype":"locality"
},
  "geometry": {"coordinates":[-102.73385,27.31259],"type":"Point"}
}