{
  "type": "Feature",
  "properties": {
    "gn:admin1_code":"11",
    "gn:admin2_code":"14",
    "gn:asciiname":"La Colorada (El Tablon del Colorado)",
    "gn:country_code":"MX",
    "gn:dem":1958,
    "gn:feature_class":"P",
    "gn:feature_code":"PPL",
    "gn:name":"La Colorada (El Tabl\u00f3n del Colorado)",
    "gn:population":9,
    "gn:timezone":"America/Mexico_City",
    "iso:country":"MX",
    "name:und_x_variant":[
        "La Colorada (El Tabl\u00f3n del Colorado)"
    ],
    "wof:name":"La Colorada (El Tablon del Colorado)",
    "wof:placetype":"locality",
    "wof:population":9
},
  "geometry": {"coordinates":[-100.80889000000001,21.16444],"type":"Point"}
}