{
  "type": "Feature",
  "properties": {
    "gn:admin1_code":"30",
    "gn:admin2_code":"59",
    "gn:asciiname":"Valerio",
    "gn:country_code":"MX",
    "gn:dem":29,
    "gn:feature_class":"P",
    "gn:feature_code":"PPL",
    "gn:name":"Valerio",
    "gn:population":24,
    "gn:timezone":"America/Mexico_City",
    "iso:country":"MX",
    "name:deu_x_preferred":[
        "Valerio"
    ],
    "name:ita_x_preferred":[
        "Valerio"
    ],
    "name:rus_x_preferred":[
        "\u0412\u0430\u043b\u0435\u0440\u0438\u043e"
    ],
    "name:spa_x_preferred":[
        "Valerio"
    ],
    "name:srp_x_preferred":[
        "Valerio"
    ],
    "wof:name":"Valerio",
    "wof:placetype":"locality",
    "wof:population":24
},
  "geometry": {"coordinates":[-94.72056000000001,18.08139],"type":"Point"}
}