{
  "type": "Feature",
  "properties": {
    "gn:admin1_code":"25.0",
    "gn:admin2_code":"13.0",
    "gn:asciiname":"El Carrizo",
    "gn:country_code":"MX",
    "gn:dem":71,
    "gn:feature_class":"P",
    "gn:feature_code":"PPL",
    "gn:name":"El Carrizo",
    "gn:population":153,
    "gn:timezone":"America/Mazatlan",
    "iso:country":"MX",
    "wof:name":"El Carrizo",
    "wof:placetype":"locality",
    "wof:population":153
},
  "geometry": {"coordinates":[-107.64794999999999,25.09937],"type":"Point"}
}