{
  "type": "Feature",
  "properties": {
    "gn:admin1_code":"28",
    "gn:admin2_code":"34.0",
    "gn:asciiname":"Camacho Viejo",
    "gn:country_code":"MX",
    "gn:dem":174,
    "gn:feature_class":"P",
    "gn:feature_code":"PPL",
    "gn:name":"Camacho Viejo",
    "gn:population":0,
    "gn:timezone":"America/Monterrey",
    "iso:country":"MX",
    "name:und_x_variant":[
        "Ejido Camacho Viejo",
        "Camacho Viejo"
    ],
    "wof:name":"Camacho Viejo",
    "wof:placetype":"locality"
},
  "geometry": {"coordinates":[-98.98869000000001,24.18866],"type":"Point"}
}