{
  "type": "Feature",
  "properties": {
    "gn:admin1_code":"28.0",
    "gn:admin2_code":"24.0",
    "gn:asciiname":"Aduana",
    "gn:country_code":"MX",
    "gn:dem":101,
    "gn:feature_class":"P",
    "gn:feature_code":"PPL",
    "gn:name":"Aduana",
    "gn:population":0,
    "gn:timezone":"America/Monterrey",
    "iso:country":"MX",
    "name:spa_x_preferred":[
        "Aduana"
    ],
    "wof:name":"Aduana",
    "wof:placetype":"locality"
},
  "geometry": {"coordinates":[-99.20099,26.5614],"type":"Point"}
}