{
  "type": "Feature",
  "properties": {
    "gn:admin1_code":"14",
    "gn:admin2_code":"49.0",
    "gn:asciiname":"El Soyatal",
    "gn:country_code":"MX",
    "gn:dem":1202,
    "gn:feature_class":"P",
    "gn:feature_code":"PPL",
    "gn:name":"El Soyatal",
    "gn:population":82,
    "gn:timezone":"America/Mexico_City",
    "iso:country":"MX",
    "wof:name":"El Soyatal",
    "wof:placetype":"locality",
    "wof:population":82
},
  "geometry": {"coordinates":[-103.11694,19.27667000000001],"type":"Point"}
}