{
  "type": "Feature",
  "properties": {
    "gn:admin1_code":"16",
    "gn:admin2_code":"9.0",
    "gn:asciiname":"El Valle (Valle Nuevo)",
    "gn:country_code":"MX",
    "gn:dem":1457,
    "gn:feature_class":"P",
    "gn:feature_code":"PPL",
    "gn:name":"El Valle (Valle Nuevo)",
    "gn:population":107,
    "gn:timezone":"America/Mexico_City",
    "iso:country":"MX",
    "wof:name":"El Valle (Valle Nuevo)",
    "wof:placetype":"locality",
    "wof:population":107
},
  "geometry": {"coordinates":[-101.7475,19.16917],"type":"Point"}
}