{
  "type": "Feature",
  "properties": {
    "gn:admin1_code":"5.0",
    "gn:asciiname":"El Escondido",
    "gn:country_code":"MX",
    "gn:dem":1070,
    "gn:feature_class":"P",
    "gn:feature_code":"PPL",
    "gn:name":"El Escondido",
    "gn:population":0,
    "gn:timezone":"America/Mexico_City",
    "iso:country":"MX",
    "name:spa_x_preferred":[
        "El Escondido"
    ],
    "wof:name":"El Escondido",
    "wof:placetype":"locality"
},
  "geometry": {"coordinates":[-92.932,15.77807],"type":"Point"}
}