{
  "type": "Feature",
  "properties": {
    "gn:admin1_code":"4",
    "gn:admin2_code":"7.0",
    "gn:asciiname":"Puerto Arturo",
    "gn:country_code":"MX",
    "gn:dem":3,
    "gn:feature_class":"P",
    "gn:feature_code":"PPL",
    "gn:name":"Puerto Arturo",
    "gn:population":127,
    "gn:timezone":"America/Merida",
    "iso:country":"MX",
    "wof:name":"Puerto Arturo",
    "wof:placetype":"locality",
    "wof:population":127
},
  "geometry": {"coordinates":[-91.86444,18.35611],"type":"Point"}
}