{
  "type": "Feature",
  "properties": {
    "gn:admin1_code":"21",
    "gn:admin2_code":"210.0",
    "gn:asciiname":"Nanacatlan",
    "gn:country_code":"MX",
    "gn:dem":926,
    "gn:feature_class":"P",
    "gn:feature_code":"PPL",
    "gn:name":"Nanacatl\u00e1n",
    "gn:population":0,
    "gn:timezone":"America/Mexico_City",
    "iso:country":"MX",
    "name:spa_x_preferred":[
        "Nanacatl\u00e1n"
    ],
    "wof:name":"Nanacatlan",
    "wof:placetype":"locality"
},
  "geometry": {"coordinates":[-97.67583999999999,20.00366],"type":"Point"}
}