{
  "type": "Feature",
  "properties": {
    "gn:admin1_code":"31",
    "gn:admin2_code":"6.0",
    "gn:asciiname":"San Marcos",
    "gn:country_code":"MX",
    "gn:dem":7,
    "gn:feature_class":"P",
    "gn:feature_code":"PPL",
    "gn:name":"San Marcos",
    "gn:population":5,
    "gn:timezone":"America/Merida",
    "iso:country":"MX",
    "wof:name":"San Marcos",
    "wof:placetype":"locality",
    "wof:population":5
},
  "geometry": {"coordinates":[-88.53806,21.23889],"type":"Point"}
}