{
  "type": "Feature",
  "properties": {
    "gn:admin1_code":"2",
    "gn:admin2_code":"1.0",
    "gn:asciiname":"Las Flores Nuevas",
    "gn:country_code":"MX",
    "gn:dem":721,
    "gn:feature_class":"P",
    "gn:feature_code":"PPL",
    "gn:name":"Las Flores Nuevas",
    "gn:population":0,
    "gn:timezone":"America/Tijuana",
    "iso:country":"MX",
    "name:spa_x_preferred":[
        "Las Flores Nuevas"
    ],
    "name:und_x_variant":[
        "Las Flores"
    ],
    "wof:name":"Las Flores Nuevas",
    "wof:placetype":"locality"
},
  "geometry": {"coordinates":[-116.21059,31.94009],"type":"Point"}
}