{
  "type": "Feature",
  "properties": {
    "gn:admin1_code":"20",
    "gn:admin2_code":"439",
    "gn:asciiname":"Arroyo la Puerta",
    "gn:country_code":"MX",
    "gn:dem":79,
    "gn:feature_class":"P",
    "gn:feature_code":"PPL",
    "gn:name":"Arroyo la Puerta",
    "gn:population":49,
    "gn:timezone":"America/Mexico_City",
    "iso:country":"MX",
    "wof:name":"Arroyo la Puerta",
    "wof:placetype":"locality",
    "wof:population":49
},
  "geometry": {"coordinates":[-96.71222,15.76333],"type":"Point"}
}