{
  "type": "Feature",
  "properties": {
    "gn:admin1_code":"16",
    "gn:admin2_code":"64.0",
    "gn:asciiname":"Puerta Chica (Barrio Seco)",
    "gn:country_code":"MX",
    "gn:dem":849,
    "gn:feature_class":"P",
    "gn:feature_code":"PPL",
    "gn:name":"Puerta Chica (Barrio Seco)",
    "gn:population":272,
    "gn:timezone":"America/Mexico_City",
    "iso:country":"MX",
    "wof:name":"Puerta Chica (Barrio Seco)",
    "wof:placetype":"locality",
    "wof:population":272
},
  "geometry": {"coordinates":[-102.2075,19.19139],"type":"Point"}
}