{
  "type": "Feature",
  "properties": {
    "gn:country":"MX",
    "gn:fcode":"PPL",
    "gn:population":4145,
    "iso:country":"MX",
    "name:spa_x_preferred":[
        "Tener\u00eda del Santuario"
    ],
    "name:spa_x_variant":[
        "Tener\u00eda"
    ],
    "qs_pg:aaroncc":"MX",
    "qs_pg:gn_country":"MX",
    "qs_pg:gn_fcode":"PPL",
    "qs_pg:gn_pop":4145,
    "qs_pg:name":"Tenerias",
    "qs_pg:name_adm0":"M\u00e9xico",
    "qs_pg:name_adm1":"Michoacan de Ocampo",
    "qs_pg:photos_9r":0,
    "qs_pg:photos_sr":0,
    "qs_pg:pop_sr":4,
    "qs_pg:qs_pg_placetype":"neighbourhood",
    "qs_pg:qs_pg_placetype_gp":"Suburb",
    "qs_pg:woe_adm0":23424900,
    "woe:adm0_id":23424900,
    "woe:name_adm0":"M\u00e9xico",
    "woe:name_adm1":"Michoacan de Ocampo",
    "woe:placetype":"Suburb",
    "wof:name":"Tenerias",
    "wof:placetype":"neighbourhood",
    "wof:population":4145
},
  "geometry": {"coordinates":[-100.79789,20.59956],"type":"Point"}
}