{
  "type": "Feature",
  "properties": {
    "gn:admin1_code":"15",
    "gn:admin2_code":"59.0",
    "gn:asciiname":"Ejido Xaltocan",
    "gn:country_code":"MX",
    "gn:dem":2245,
    "gn:feature_class":"P",
    "gn:feature_code":"PPL",
    "gn:name":"Ejido Xaltocan",
    "gn:population":0,
    "gn:timezone":"America/Mexico_City",
    "iso:country":"MX",
    "wof:name":"Ejido Xaltocan",
    "wof:placetype":"locality"
},
  "geometry": {"coordinates":[-99.04416999999999,19.71167],"type":"Point"}
}