{
  "type": "Feature",
  "properties": {
    "gn:admin1_code":"14.0",
    "gn:admin2_code":"65.0",
    "gn:asciiname":"Las Higueras",
    "gn:country_code":"MX",
    "gn:dem":846,
    "gn:feature_class":"P",
    "gn:feature_code":"PPL",
    "gn:name":"Las Higueras",
    "gn:population":0,
    "gn:timezone":"America/Mexico_City",
    "iso:country":"MX",
    "name:spa_x_preferred":[
        "Las Higueras"
    ],
    "wof:name":"Las Higueras",
    "wof:placetype":"locality"
},
  "geometry": {"coordinates":[-103.33847,19.26954],"type":"Point"}
}