{
  "type": "Feature",
  "properties": {
    "gn:admin1_code":"29",
    "gn:admin2_code":"40.0",
    "gn:asciiname":"La Retama",
    "gn:country_code":"MX",
    "gn:dem":2616,
    "gn:feature_class":"P",
    "gn:feature_code":"PPL",
    "gn:name":"La Retama",
    "gn:population":0,
    "gn:timezone":"America/Mexico_City",
    "iso:country":"MX",
    "name:spa_x_preferred":[
        "La Retama"
    ],
    "name:und_x_variant":[
        "La Reforma"
    ],
    "wof:name":"La Retama",
    "wof:placetype":"locality"
},
  "geometry": {"coordinates":[-98.25757,19.45331],"type":"Point"}
}