{
  "type": "Feature",
  "properties": {
    "gn:admin1_code":"6",
    "gn:admin2_code":"31.0",
    "gn:asciiname":"Minaca",
    "gn:country_code":"MX",
    "gn:dem":2110,
    "gn:feature_class":"P",
    "gn:feature_code":"PPL",
    "gn:name":"Mi\u00f1aca",
    "gn:population":353,
    "gn:timezone":"America/Chihuahua",
    "iso:country":"MX",
    "wof:name":"Minaca",
    "wof:placetype":"locality",
    "wof:population":353
},
  "geometry": {"coordinates":[-107.42583,28.44861],"type":"Point"}
}