{
  "type": "Feature",
  "properties": {
    "gn:admin1_code":"21.0",
    "gn:admin2_code":"172.0",
    "gn:asciiname":"Pichonco",
    "gn:country_code":"MX",
    "gn:dem":2514,
    "gn:feature_class":"P",
    "gn:feature_code":"PPL",
    "gn:name":"Pichonco",
    "gn:population":0,
    "gn:timezone":"America/Mexico_City",
    "iso:country":"MX",
    "name:spa_x_preferred":[
        "Pichonco"
    ],
    "wof:name":"Pichonco",
    "wof:placetype":"locality"
},
  "geometry": {"coordinates":[-97.74102999999999,19.77699],"type":"Point"}
}