{
  "type": "Feature",
  "properties": {
    "gn:admin1_code":"24.0",
    "gn:admin2_code":"17.0",
    "gn:asciiname":"Puerto las Matianas",
    "gn:country_code":"MX",
    "gn:dem":1682,
    "gn:feature_class":"P",
    "gn:feature_code":"PPL",
    "gn:name":"Puerto las Matianas",
    "gn:population":0,
    "gn:timezone":"America/Mexico_City",
    "iso:country":"MX",
    "name:spa_x_preferred":[
        "Puerto las Matianas"
    ],
    "wof:name":"Puerto las Matianas",
    "wof:placetype":"locality"
},
  "geometry": {"coordinates":[-100.28234,22.74179],"type":"Point"}
}