{
  "type": "Feature",
  "properties": {
    "gn:admin1_code":"21.0",
    "gn:asciiname":"La Fortuna",
    "gn:country_code":"MX",
    "gn:dem":2232,
    "gn:feature_class":"P",
    "gn:feature_code":"PPL",
    "gn:name":"La Fortuna",
    "gn:population":0,
    "gn:timezone":"America/Mexico_City",
    "iso:country":"MX",
    "name:spa_x_preferred":[
        "La Fortuna"
    ],
    "wof:name":"La Fortuna",
    "wof:placetype":"locality"
},
  "geometry": {"coordinates":[-98.36835000000001,19.17816],"type":"Point"}
}