{
  "type": "Feature",
  "properties": {
    "gn:admin1_code":"5",
    "gn:admin2_code":"108",
    "gn:asciiname":"Jaltipan",
    "gn:country_code":"MX",
    "gn:dem":650,
    "gn:feature_class":"P",
    "gn:feature_code":"PPL",
    "gn:name":"J\u00e1ltipan",
    "gn:population":9,
    "gn:timezone":"America/Mexico_City",
    "iso:country":"MX",
    "name:und_x_variant":[
        "J\u00e1ltipan"
    ],
    "wof:name":"Jaltipan",
    "wof:placetype":"locality",
    "wof:population":9
},
  "geometry": {"coordinates":[-93.40056,16.37944],"type":"Point"}
}