{
  "type": "Feature",
  "properties": {
    "gn:admin1_code":"5",
    "gn:admin2_code":"108",
    "gn:asciiname":"Jaltipan",
    "gn:country_code":"MX",
    "gn:dem":650,
    "gn:feature_class":"P",
    "gn:feature_code":"PPL",
    "gn:name":"J\u00e1ltipan",
    "gn:population":9,
    "gn:timezone":"America/Mexico_City",
    "iso:country":"MX",
    "name:ara_x_preferred":[
        "\u062c\u0627\u0644\u062a\u064a\u0628\u0627\u0646"
    ],
    "name:ben_x_preferred":[
        "\u099c\u09be\u09b2\u09a4\u09bf\u09aa\u09be\u09a8"
    ],
    "name:deu_x_preferred":[
        "J\u00e1ltipan"
    ],
    "name:ell_x_preferred":[
        "\u03a7\u03b1\u03bb\u03c4\u03b9\u03c0\u03ac\u03bd"
    ],
    "name:fas_x_preferred":[
        "\u062c\u0627\u062a\u06cc\u067e\u0627\u0646"
    ],
    "name:heb_x_preferred":[
        "\u05d2'\u05dc\u05d8\u05d9\u05e4\u05df"
    ],
    "name:hin_x_preferred":[
        "\u0939\u093e\u0932\u094d\u0924\u093f\u092a\u0928"
    ],
    "name:hun_x_preferred":[
        "Jaltipan"
    ],
    "name:ind_x_preferred":[
        "Jaltipan"
    ],
    "name:ita_x_preferred":[
        "J\u00e1ltipan"
    ],
    "name:jpn_x_preferred":[
        "\u30cf\u30eb\u30c6\u30a3\u30d1\u30f3"
    ],
    "name:kor_x_preferred":[
        "\uc798\ud2f0\ud310"
    ],
    "name:por_x_preferred":[
        "J\u00e1ltipan"
    ],
    "name:swe_x_preferred":[
        "J\u00e1ltipan"
    ],
    "name:tur_x_preferred":[
        "Jaltipan"
    ],
    "name:ukr_x_preferred":[
        "\u0425\u0430\u043b\u0442\u0456\u043f\u0430\u043d"
    ],
    "name:und_x_variant":[
        "J\u00e1ltipan"
    ],
    "name:urd_x_preferred":[
        "\u062c\u0644\u062a\u06cc\u067e\u0627\u0646"
    ],
    "name:vie_x_preferred":[
        "Jaltipan"
    ],
    "name:zho_cn_x_preferred":[
        "\u8d3e\u5c14\u8482\u6f58"
    ],
    "name:zho_tw_x_preferred":[
        "\u8cc8\u723e\u8482\u6f58"
    ],
    "wof:name":"Jaltipan",
    "wof:placetype":"locality",
    "wof:population":9
},
  "geometry": {"coordinates":[-93.40056,16.37944],"type":"Point"}
}