{
  "type": "Feature",
  "properties": {
    "gn:admin1_code":"19.0",
    "gn:asciiname":"La Engorda",
    "gn:country_code":"MX",
    "gn:dem":575,
    "gn:feature_class":"P",
    "gn:feature_code":"PPL",
    "gn:name":"La Engorda",
    "gn:population":0,
    "gn:timezone":"America/Monterrey",
    "iso:country":"MX",
    "name:spa_x_preferred":[
        "La Engorda"
    ],
    "wof:name":"La Engorda",
    "wof:placetype":"locality"
},
  "geometry": {"coordinates":[-100.51016,26.00014],"type":"Point"}
}