{
  "type": "Feature",
  "properties": {
    "gn:admin1_code":"11.0",
    "gn:admin2_code":"27.0",
    "gn:asciiname":"El Cuatro de Altamira",
    "gn:country_code":"MX",
    "gn:dem":1719,
    "gn:feature_class":"P",
    "gn:feature_code":"PPL",
    "gn:name":"El Cuatro de Altamira",
    "gn:population":0,
    "gn:timezone":"America/Mexico_City",
    "iso:country":"MX",
    "name:spa_x_preferred":[
        "Colonia Cuatro de Altamira"
    ],
    "name:und_x_variant":[
        "El Cuatro",
        "El Cuatro de Altamira"
    ],
    "wof:name":"El Cuatro de Altamira",
    "wof:placetype":"locality"
},
  "geometry": {"coordinates":[-101.16598,20.48541],"type":"Point"}
}