{
  "type": "Feature",
  "properties": {
    "gn:admin1_code":"12",
    "gn:admin2_code":"73.0",
    "gn:asciiname":"Cuernavaca",
    "gn:country_code":"MX",
    "gn:dem":765,
    "gn:feature_class":"P",
    "gn:feature_code":"PPL",
    "gn:name":"Cuernavaca",
    "gn:population":0,
    "gn:timezone":"America/Mexico_City",
    "iso:country":"MX",
    "name:spa_x_preferred":[
        "Cuernavaca"
    ],
    "wof:name":"Cuernavaca",
    "wof:placetype":"locality"
},
  "geometry": {"coordinates":[-101.32792000000001,18.28225],"type":"Point"}
}