{
  "type": "Feature",
  "properties": {
    "gn:admin1_code":"16",
    "gn:admin2_code":"82.0",
    "gn:asciiname":"Canicuaro",
    "gn:country_code":"MX",
    "gn:dem":1526,
    "gn:feature_class":"P",
    "gn:feature_code":"PPL",
    "gn:name":"Can\u00edcuaro",
    "gn:population":641,
    "gn:timezone":"America/Mexico_City",
    "iso:country":"MX",
    "name:und_x_variant":[
        "Can\u00edcuaro"
    ],
    "wof:name":"Canicuaro",
    "wof:placetype":"locality",
    "wof:population":641
},
  "geometry": {"coordinates":[-101.43583,19.23194],"type":"Point"}
}