{
  "type": "Feature",
  "properties": {
    "gn:admin1_code":"5",
    "gn:admin2_code":"97",
    "gn:asciiname":"San Francisco Potrerillo",
    "gn:country_code":"MX",
    "gn:dem":130,
    "gn:feature_class":"P",
    "gn:feature_code":"PPL",
    "gn:name":"San Francisco Potrerillo",
    "gn:population":20,
    "gn:timezone":"America/Mexico_City",
    "iso:country":"MX",
    "wof:name":"San Francisco Potrerillo",
    "wof:placetype":"locality",
    "wof:population":20
},
  "geometry": {"coordinates":[-93.61221999999999,15.96],"type":"Point"}
}