{
  "type": "Feature",
  "properties": {
    "gn:admin1_code":"25",
    "gn:admin2_code":"7.0",
    "gn:asciiname":"El Retan",
    "gn:country_code":"MX",
    "gn:dem":638,
    "gn:feature_class":"P",
    "gn:feature_code":"PPL",
    "gn:name":"El Ret\u00e1n",
    "gn:population":0,
    "gn:timezone":"America/Mazatlan",
    "iso:country":"MX",
    "name:spa_x_preferred":[
        "El Ret\u00e1n"
    ],
    "wof:name":"El Retan",
    "wof:placetype":"locality"
},
  "geometry": {"coordinates":[-108.22754,26.61061],"type":"Point"}
}