{
  "type": "Feature",
  "properties": {
    "gn:admin1_code":"26.0",
    "gn:admin2_code":"2.0",
    "gn:asciiname":"La Sota",
    "gn:country_code":"MX",
    "gn:dem":1218,
    "gn:feature_class":"P",
    "gn:feature_code":"PPL",
    "gn:name":"La Sota",
    "gn:population":0,
    "gn:timezone":"America/Hermosillo",
    "iso:country":"MX",
    "name:spa_x_preferred":[
        "La Sota"
    ],
    "wof:name":"La Sota",
    "wof:placetype":"locality"
},
  "geometry": {"coordinates":[-109.37434,31.03147],"type":"Point"}
}