{
  "type": "Feature",
  "properties": {
    "gn:admin1_code":"20",
    "gn:admin2_code":"327",
    "gn:asciiname":"Ro-Be-Ca",
    "gn:country_code":"MX",
    "gn:dem":13,
    "gn:feature_class":"P",
    "gn:feature_code":"PPL",
    "gn:name":"Ro-Be-Ca",
    "gn:population":13,
    "gn:timezone":"America/Mexico_City",
    "iso:country":"MX",
    "wof:name":"Ro-Be-Ca",
    "wof:placetype":"locality",
    "wof:population":13
},
  "geometry": {"coordinates":[-94.10028,16.25667],"type":"Point"}
}