{
  "type": "Feature",
  "properties": {
    "gn:admin1_code":"10.0",
    "gn:admin2_code":"34.0",
    "gn:asciiname":"La Balanza",
    "gn:country_code":"MX",
    "gn:dem":2351,
    "gn:feature_class":"P",
    "gn:feature_code":"PPL",
    "gn:name":"La Balanza",
    "gn:population":0,
    "gn:timezone":"America/Monterrey",
    "iso:country":"MX",
    "name:spa_x_preferred":[
        "La Balanza"
    ],
    "wof:name":"La Balanza",
    "wof:placetype":"locality"
},
  "geometry": {"coordinates":[-106.75317,25.48811],"type":"Point"}
}