{
  "type": "Feature",
  "properties": {
    "gn:admin1_code":"16",
    "gn:admin2_code":"50.0",
    "gn:asciiname":"Las Mesas",
    "gn:country_code":"MX",
    "gn:dem":2483,
    "gn:feature_class":"P",
    "gn:feature_code":"PPL",
    "gn:name":"Las Mesas",
    "gn:population":234,
    "gn:timezone":"America/Mexico_City",
    "iso:country":"MX",
    "wof:name":"Las Mesas",
    "wof:placetype":"locality",
    "wof:population":234
},
  "geometry": {"coordinates":[-100.28778,19.84611],"type":"Point"}
}