{
  "type": "Feature",
  "properties": {
    "gn:admin1_code":"5",
    "gn:admin2_code":"17",
    "gn:asciiname":"Rancho Alegre",
    "gn:country_code":"MX",
    "gn:dem":887,
    "gn:feature_class":"P",
    "gn:feature_code":"PPL",
    "gn:name":"Rancho Alegre",
    "gn:population":10,
    "gn:timezone":"America/Mexico_City",
    "iso:country":"MX",
    "wof:name":"Rancho Alegre",
    "wof:placetype":"locality",
    "wof:population":10
},
  "geometry": {"coordinates":[-93.93889,16.38332999999999],"type":"Point"}
}