{
  "type": "Feature",
  "properties": {
    "gn:admin1_code":"28",
    "gn:admin2_code":"12.0",
    "gn:asciiname":"San Antonio Nogalar",
    "gn:country_code":"MX",
    "gn:dem":348,
    "gn:feature_class":"P",
    "gn:feature_code":"PPL",
    "gn:name":"San Antonio Nogalar",
    "gn:population":124,
    "gn:timezone":"America/Monterrey",
    "iso:country":"MX",
    "name:spa_x_preferred":[
        "San Antonio Nogalar"
    ],
    "wof:name":"San Antonio Nogalar",
    "wof:placetype":"locality",
    "wof:population":124
},
  "geometry": {"coordinates":[-98.40926,23.05959],"type":"Point"}
}