{
  "type": "Feature",
  "properties": {
    "gn:admin1_code":"26.0",
    "gn:admin2_code":"9.0",
    "gn:asciiname":"La Salvia",
    "gn:country_code":"MX",
    "gn:dem":953,
    "gn:feature_class":"P",
    "gn:feature_code":"PPL",
    "gn:name":"La Salvia",
    "gn:population":0,
    "gn:timezone":"America/Hermosillo",
    "iso:country":"MX",
    "name:spa_x_preferred":[
        "La Salvia"
    ],
    "wof:name":"La Salvia",
    "wof:placetype":"locality"
},
  "geometry": {"coordinates":[-109.32935000000001,28.73116],"type":"Point"}
}