{
  "type": "Feature",
  "properties": {
    "gn:admin1_code":"9",
    "gn:admin2_code":"9",
    "gn:asciiname":"Camino Tigustitla",
    "gn:country_code":"MX",
    "gn:dem":2732,
    "gn:feature_class":"P",
    "gn:feature_code":"PPL",
    "gn:name":"Camino Tigustitla",
    "gn:population":50,
    "gn:timezone":"America/Mexico_City",
    "iso:country":"MX",
    "wof:name":"Camino Tigustitla",
    "wof:placetype":"locality",
    "wof:population":50
},
  "geometry": {"coordinates":[-99.03818,19.17019],"type":"Point"}
}