{
  "type": "Feature",
  "properties": {
    "gn:admin1_code":"6",
    "gn:admin2_code":"37.0",
    "gn:asciiname":"Samalayuca",
    "gn:country_code":"MX",
    "gn:dem":1265,
    "gn:feature_class":"P",
    "gn:feature_code":"PPL",
    "gn:name":"Samalayuca",
    "gn:population":0,
    "gn:timezone":"America/Ojinaga",
    "iso:country":"MX",
    "name:und_x_variant":[
        "Estacion Samalayuca",
        "Samalayuca"
    ],
    "wof:name":"Samalayuca",
    "wof:placetype":"locality"
},
  "geometry": {"coordinates":[-106.47981,31.34242],"type":"Point"}
}