{
  "type": "Feature",
  "properties": {
    "gn:admin1_code":"19.0",
    "gn:admin2_code":"40.0",
    "gn:asciiname":"Cuatro Hermanas",
    "gn:country_code":"MX",
    "gn:dem":151,
    "gn:feature_class":"P",
    "gn:feature_code":"PPL",
    "gn:name":"Cuatro Hermanas",
    "gn:population":0,
    "gn:timezone":"America/Monterrey",
    "iso:country":"MX",
    "name:spa_x_preferred":[
        "Cuatro Hermanas"
    ],
    "wof:name":"Cuatro Hermanas",
    "wof:placetype":"locality"
},
  "geometry": {"coordinates":[-99.4879,26.51891],"type":"Point"}
}