{
  "type": "Feature",
  "properties": {
    "gn:admin1_code":"6",
    "gn:admin2_code":"7",
    "gn:asciiname":"La Joya del Rio Verde",
    "gn:country_code":"MX",
    "gn:dem":2446,
    "gn:feature_class":"P",
    "gn:feature_code":"PPL",
    "gn:name":"La Joya del R\u00edo Verde",
    "gn:population":23,
    "gn:timezone":"America/Chihuahua",
    "iso:country":"MX",
    "name:und_x_variant":[
        "La Joya del R\u00edo Verde"
    ],
    "wof:name":"La Joya del Rio Verde",
    "wof:placetype":"locality",
    "wof:population":23
},
  "geometry": {"coordinates":[-106.48182,26.28253],"type":"Point"}
}