{
  "type": "Feature",
  "properties": {
    "gn:admin1_code":"21",
    "gn:admin2_code":"114.0",
    "gn:asciiname":"Bosques de Amalucan Segunda Seccion",
    "gn:country_code":"MX",
    "gn:dem":2270,
    "gn:feature_class":"P",
    "gn:feature_code":"PPL",
    "gn:name":"Bosques de Amalucan Segunda Secci\u00f3n",
    "gn:population":66,
    "gn:timezone":"America/Mexico_City",
    "iso:country":"MX",
    "name:und_x_variant":[
        "Bosques de Amalucan Segunda Secci\u00f3n"
    ],
    "wof:name":"Bosques de Amalucan Segunda Seccion",
    "wof:placetype":"locality",
    "wof:population":66
},
  "geometry": {"coordinates":[-98.11111,19.05889],"type":"Point"}
}