{
  "type": "Feature",
  "properties": {
    "gn:admin1_code":"6.0",
    "gn:admin2_code":"5.0",
    "gn:asciiname":"Cerros Prietos",
    "gn:country_code":"MX",
    "gn:dem":1316,
    "gn:feature_class":"P",
    "gn:feature_code":"PPL",
    "gn:name":"Cerros Prietos",
    "gn:population":0,
    "gn:timezone":"America/Chihuahua",
    "iso:country":"MX",
    "name:spa_x_preferred":[
        "Cerros Prietos"
    ],
    "name:und_x_variant":[
        "Las Pe\u00f1itas"
    ],
    "wof:name":"Cerros Prietos",
    "wof:placetype":"locality"
},
  "geometry": {"coordinates":[-107.4479,30.78778],"type":"Point"}
}