{
  "type": "Feature",
  "properties": {
    "gn:admin1_code":"4",
    "gn:admin2_code":"4.0",
    "gn:asciiname":"Aquiles Serdan (Chuina)",
    "gn:country_code":"MX",
    "gn:dem":18,
    "gn:feature_class":"P",
    "gn:feature_code":"PPL",
    "gn:name":"Aquiles Serd\u00e1n (Chuin\u00e1)",
    "gn:population":896,
    "gn:timezone":"America/Merida",
    "iso:country":"MX",
    "wof:name":"Aquiles Serdan (Chuina)",
    "wof:placetype":"locality",
    "wof:population":896
},
  "geometry": {"coordinates":[-90.71389000000001,18.96389],"type":"Point"}
}