{
  "type": "Feature",
  "properties": {
    "gn:admin1_code":"9",
    "gn:admin2_code":"9",
    "gn:asciiname":"Panuca (Kilometro 27.5)",
    "gn:country_code":"MX",
    "gn:dem":2733,
    "gn:feature_class":"P",
    "gn:feature_code":"PPL",
    "gn:name":"Panuca (Kil\u00f3metro 27.5)",
    "gn:population":23,
    "gn:timezone":"America/Mexico_City",
    "iso:country":"MX",
    "name:und_x_variant":[
        "Panuca (Kil\u00f3metro 27.5)"
    ],
    "wof:name":"Panuca (Kilometro 27.5)",
    "wof:placetype":"locality",
    "wof:population":23
},
  "geometry": {"coordinates":[-98.99346,19.16436],"type":"Point"}
}