{
  "type": "Feature",
  "properties": {
    "gn:admin1_code":"30",
    "gn:admin2_code":"181.0",
    "gn:asciiname":"Los Peladeros",
    "gn:country_code":"MX",
    "gn:dem":73,
    "gn:feature_class":"P",
    "gn:feature_code":"PPL",
    "gn:name":"Los Peladeros",
    "gn:population":9,
    "gn:timezone":"America/Mexico_City",
    "iso:country":"MX",
    "wof:name":"Los Peladeros",
    "wof:placetype":"locality",
    "wof:population":9
},
  "geometry": {"coordinates":[-96.34417000000001,18.7475],"type":"Point"}
}