{
  "type": "Feature",
  "properties": {
    "gn:admin1_code":"32",
    "gn:admin2_code":"39.0",
    "gn:asciiname":"Rancho el Canon (Los Torres)",
    "gn:country_code":"MX",
    "gn:dem":1946,
    "gn:feature_class":"P",
    "gn:feature_code":"PPL",
    "gn:name":"Rancho el Ca\u00f1\u00f3n (Los Torres)",
    "gn:population":90,
    "gn:timezone":"America/Mexico_City",
    "iso:country":"MX",
    "name:und_x_variant":[
        "Rancho el Ca\u00f1\u00f3n (Los Torres)"
    ],
    "wof:name":"Rancho el Canon (Los Torres)",
    "wof:placetype":"locality",
    "wof:population":90
},
  "geometry": {"coordinates":[-103.13417,23.76389],"type":"Point"}
}