{
  "type": "Feature",
  "properties": {
    "gn:admin1_code":"8.0",
    "gn:admin2_code":"9.0",
    "gn:asciiname":"Cajitlan",
    "gn:country_code":"MX",
    "gn:dem":63,
    "gn:feature_class":"P",
    "gn:feature_code":"PPL",
    "gn:name":"Cajitl\u00e1n",
    "gn:population":0,
    "gn:timezone":"America/Mexico_City",
    "iso:country":"MX",
    "wof:name":"Cajitlan",
    "wof:placetype":"locality"
},
  "geometry": {"coordinates":[-103.88333,18.96667],"type":"Point"}
}