{
  "type": "Feature",
  "properties": {
    "gn:admin1_code":"28.0",
    "gn:admin2_code":"8.0",
    "gn:asciiname":"La Canada",
    "gn:country_code":"MX",
    "gn:dem":254,
    "gn:feature_class":"P",
    "gn:feature_code":"PPL",
    "gn:name":"La Ca\u00f1ada",
    "gn:population":0,
    "gn:timezone":"America/Monterrey",
    "iso:country":"MX",
    "name:spa_x_preferred":[
        "La Ca\u00f1ada"
    ],
    "wof:name":"La Canada",
    "wof:placetype":"locality"
},
  "geometry": {"coordinates":[-98.62389,23.61333],"type":"Point"}
}