{
  "type": "Feature",
  "properties": {
    "gn:admin1_code":"30",
    "gn:admin2_code":"102.0",
    "gn:asciiname":"El Canon",
    "gn:country_code":"MX",
    "gn:dem":62,
    "gn:feature_class":"P",
    "gn:feature_code":"PPL",
    "gn:name":"El Ca\u00f1\u00f3n",
    "gn:population":0,
    "gn:timezone":"America/Mexico_City",
    "iso:country":"MX",
    "wof:name":"El Canon",
    "wof:placetype":"locality"
},
  "geometry": {"coordinates":[-97.02222,20.09028],"type":"Point"}
}