{
  "type": "Feature",
  "properties": {
    "gn:admin1_code":"5",
    "gn:admin2_code":"12.0",
    "gn:asciiname":"La Primavera",
    "gn:country_code":"MX",
    "gn:dem":755,
    "gn:feature_class":"P",
    "gn:feature_code":"PPL",
    "gn:name":"La Primavera",
    "gn:population":5,
    "gn:timezone":"America/Mexico_City",
    "iso:country":"MX",
    "wof:name":"La Primavera",
    "wof:placetype":"locality",
    "wof:population":5
},
  "geometry": {"coordinates":[-93.33056000000001,16.93194],"type":"Point"}
}