{
  "type": "Feature",
  "properties": {
    "gn:admin1_code":"25.0",
    "gn:admin2_code":"18.0",
    "gn:asciiname":"Los Angeles Dos",
    "gn:country_code":"MX",
    "gn:dem":5,
    "gn:feature_class":"P",
    "gn:feature_code":"PPL",
    "gn:name":"Los Angeles Dos",
    "gn:population":0,
    "gn:timezone":"America/Mazatlan",
    "iso:country":"MX",
    "name:spa_x_preferred":[
        "Los Angeles Dos"
    ],
    "wof:name":"Los Angeles Dos",
    "wof:placetype":"locality"
},
  "geometry": {"coordinates":[-107.89128999999998,24.82151],"type":"Point"}
}