{
  "type": "Feature",
  "properties": {
    "gn:admin1_code":"10",
    "gn:admin2_code":"16.0",
    "gn:asciiname":"Francisco Villa (San Isidro)",
    "gn:country_code":"MX",
    "gn:dem":1813,
    "gn:feature_class":"P",
    "gn:feature_code":"PPL",
    "gn:name":"Francisco Villa (San Isidro)",
    "gn:population":218,
    "gn:timezone":"America/Monterrey",
    "iso:country":"MX",
    "wof:name":"Francisco Villa (San Isidro)",
    "wof:placetype":"locality",
    "wof:population":218
},
  "geometry": {"coordinates":[-104.26167,23.94667],"type":"Point"}
}