{
  "type": "Feature",
  "properties": {
    "gn:admin1_code":"21",
    "gn:admin2_code":"94.0",
    "gn:asciiname":"Teoloyucan",
    "gn:country_code":"MX",
    "gn:dem":2351,
    "gn:feature_class":"P",
    "gn:feature_code":"PPL",
    "gn:name":"Teoloyucan",
    "gn:population":0,
    "gn:timezone":"America/Mexico_City",
    "iso:country":"MX",
    "name:cat_x_preferred":[
        "Teoloyucan"
    ],
    "name:ceb_x_preferred":[
        "Teoloyucan"
    ],
    "name:deu_x_preferred":[
        "Municipio Teoloyucan"
    ],
    "name:epo_x_preferred":[
        "Teoloyucan"
    ],
    "name:eus_x_preferred":[
        "Teoloyucan"
    ],
    "name:fra_x_preferred":[
        "Teoloyucan"
    ],
    "name:ita_x_preferred":[
        "Teoloyucan"
    ],
    "name:lad_x_preferred":[
        "Teoloyucan"
    ],
    "name:nld_x_preferred":[
        "Teoloyucan"
    ],
    "name:por_x_preferred":[
        "Teoloyucan"
    ],
    "name:rus_x_preferred":[
        "\u0422\u0435\u043e\u043b\u043e\u044e\u043a\u0430\u043d"
    ],
    "name:srp_x_preferred":[
        "\u041e\u043f\u0448\u0442\u0438\u043d\u0430 \u0422\u0435\u043e\u043b\u043e\u0458\u0443\u043a\u0430\u043d"
    ],
    "name:swe_x_preferred":[
        "Teoloyucan"
    ],
    "name:und_x_variant":[
        "Teoloyuca"
    ],
    "name:vie_x_preferred":[
        "Teoloyuc\u00e1n"
    ],
    "wof:name":"Teoloyucan",
    "wof:placetype":"locality"
},
  "geometry": {"coordinates":[-97.61614,19.43093],"type":"Point"}
}