{
  "type": "Feature",
  "properties": {
    "gn:admin1_code":"21",
    "gn:admin2_code":"94.0",
    "gn:asciiname":"Teoloyucan",
    "gn:country_code":"MX",
    "gn:dem":2351,
    "gn:feature_class":"P",
    "gn:feature_code":"PPL",
    "gn:name":"Teoloyucan",
    "gn:population":0,
    "gn:timezone":"America/Mexico_City",
    "iso:country":"MX",
    "name:und_x_variant":[
        "Teoloyuca"
    ],
    "wof:name":"Teoloyucan",
    "wof:placetype":"locality"
},
  "geometry": {"coordinates":[-97.61614,19.43093],"type":"Point"}
}