{
  "type": "Feature",
  "properties": {
    "gn:admin1_code":"16",
    "gn:admin2_code":"82.0",
    "gn:asciiname":"La Mesa Alta",
    "gn:country_code":"MX",
    "gn:dem":2387,
    "gn:feature_class":"P",
    "gn:feature_code":"PPL",
    "gn:name":"La Mesa Alta",
    "gn:population":66,
    "gn:timezone":"America/Mexico_City",
    "iso:country":"MX",
    "wof:name":"La Mesa Alta",
    "wof:placetype":"locality",
    "wof:population":66
},
  "geometry": {"coordinates":[-101.45056,19.34389],"type":"Point"}
}