{
  "type": "Feature",
  "properties": {
    "gn:admin1_code":"10",
    "gn:admin2_code":"5.0",
    "gn:asciiname":"La Puerta de los Lobos",
    "gn:country_code":"MX",
    "gn:dem":2686,
    "gn:feature_class":"P",
    "gn:feature_code":"PPL",
    "gn:name":"La Puerta de los Lobos",
    "gn:population":0,
    "gn:timezone":"America/Monterrey",
    "iso:country":"MX",
    "name:spa_x_preferred":[
        "La Puerta de los Lobos"
    ],
    "wof:name":"La Puerta de los Lobos",
    "wof:placetype":"locality"
},
  "geometry": {"coordinates":[-104.91858999999999,23.63212],"type":"Point"}
}