{
  "type": "Feature",
  "properties": {
    "gn:admin1_code":"6.0",
    "gn:admin2_code":"20.0",
    "gn:asciiname":"Desechos",
    "gn:country_code":"MX",
    "gn:dem":653,
    "gn:feature_class":"P",
    "gn:feature_code":"PPL",
    "gn:name":"Desechos",
    "gn:population":0,
    "gn:timezone":"America/Chihuahua",
    "iso:country":"MX",
    "name:spa_x_preferred":[
        "Desechos"
    ],
    "wof:name":"Desechos",
    "wof:placetype":"locality"
},
  "geometry": {"coordinates":[-108.56083999999998,27.54415],"type":"Point"}
}