{
  "type": "Feature",
  "properties": {
    "gn:admin1_code":"26.0",
    "gn:admin2_code":"19.0",
    "gn:asciiname":"Joya Norte",
    "gn:country_code":"MX",
    "gn:dem":1515,
    "gn:feature_class":"P",
    "gn:feature_code":"PPL",
    "gn:name":"Joya Norte",
    "gn:population":0,
    "gn:timezone":"America/Hermosillo",
    "iso:country":"MX",
    "name:spa_x_preferred":[
        "Joya Norte"
    ],
    "wof:name":"Joya Norte",
    "wof:placetype":"locality"
},
  "geometry": {"coordinates":[-109.97501,31.13864],"type":"Point"}
}