{
  "type": "Feature",
  "properties": {
    "gn:admin1_code":"19.0",
    "gn:admin2_code":"40.0",
    "gn:asciiname":"Case Nava",
    "gn:country_code":"MX",
    "gn:dem":122,
    "gn:feature_class":"P",
    "gn:feature_code":"PPL",
    "gn:name":"Case Nava",
    "gn:population":0,
    "gn:timezone":"America/Monterrey",
    "iso:country":"MX",
    "name:spa_x_preferred":[
        "Case Nava"
    ],
    "wof:name":"Case Nava",
    "wof:placetype":"locality"
},
  "geometry": {"coordinates":[-99.64142,26.88441],"type":"Point"}
}