{
  "type": "Feature",
  "properties": {
    "gn:admin1_code":"12",
    "gn:admin2_code":"22.0",
    "gn:asciiname":"Pancira",
    "gn:country_code":"MX",
    "gn:dem":286,
    "gn:feature_class":"P",
    "gn:feature_code":"PPL",
    "gn:name":"Pancira",
    "gn:population":279,
    "gn:timezone":"America/Mexico_City",
    "iso:country":"MX",
    "wof:name":"Pancira",
    "wof:placetype":"locality",
    "wof:population":279
},
  "geometry": {"coordinates":[-100.73721999999999,18.26806],"type":"Point"}
}