{
  "type": "Feature",
  "properties": {
    "gn:admin1_code":"26.0",
    "gn:admin2_code":"55.0",
    "gn:asciiname":"La Escondida",
    "gn:country_code":"MX",
    "gn:dem":18,
    "gn:feature_class":"P",
    "gn:feature_code":"PPL",
    "gn:name":"La Escondida",
    "gn:population":37,
    "gn:timezone":"America/Hermosillo",
    "iso:country":"MX",
    "name:spa_x_preferred":[
        "La Escondida"
    ],
    "wof:name":"La Escondida",
    "wof:placetype":"locality",
    "wof:population":37
},
  "geometry": {"coordinates":[-114.93889,32.33194],"type":"Point"}
}