{
  "type": "Feature",
  "properties": {
    "gn:admin1_code":"23",
    "gn:admin2_code":"2.0",
    "gn:asciiname":"Xlata",
    "gn:country_code":"MX",
    "gn:dem":32,
    "gn:feature_class":"P",
    "gn:feature_code":"PPL",
    "gn:name":"Xlata",
    "gn:population":0,
    "gn:timezone":"America/Cancun",
    "iso:country":"MX",
    "name:spa_x_preferred":[
        "Xlata"
    ],
    "name:und_x_variant":[
        "X-Lata"
    ],
    "wof:name":"Xlata",
    "wof:placetype":"locality"
},
  "geometry": {"coordinates":[-88.31164,20.15618],"type":"Point"}
}