{
  "type": "Feature",
  "properties": {
    "gn:admin1_code":"26.0",
    "gn:admin2_code":"10.0",
    "gn:asciiname":"Jaquiverachi",
    "gn:country_code":"MX",
    "gn:dem":1324,
    "gn:feature_class":"P",
    "gn:feature_code":"PPL",
    "gn:name":"Jaquiverachi",
    "gn:population":0,
    "gn:timezone":"America/Hermosillo",
    "iso:country":"MX",
    "name:und_x_variant":[
        "Rancho Jaquiv\u00e9rachi",
        "Jaquiverachi"
    ],
    "wof:name":"Jaquiverachi",
    "wof:placetype":"locality"
},
  "geometry": {"coordinates":[-108.78537,30.25279],"type":"Point"}
}