{
  "type": "Feature",
  "properties": {
    "gn:admin1_code":"28.0",
    "gn:admin2_code":"3.0",
    "gn:asciiname":"Rancho Grande",
    "gn:country_code":"MX",
    "gn:dem":51,
    "gn:feature_class":"P",
    "gn:feature_code":"PPL",
    "gn:name":"Rancho Grande",
    "gn:population":1,
    "gn:timezone":"America/Monterrey",
    "iso:country":"MX",
    "name:fra_x_preferred":[
        "Rancho Grande"
    ],
    "name:ita_x_preferred":[
        "Rancho Grande"
    ],
    "name:spa_x_preferred":[
        "Rancho Grande"
    ],
    "name:swe_x_preferred":[
        "Rancho Grande"
    ],
    "name:urd_x_preferred":[
        "\u0631\u0627\u0646\u0686\u0648 \u06af\u0631\u0627\u0646\u062f\u06d2"
    ],
    "name:vie_x_preferred":[
        "Rancho Grande"
    ],
    "name:zho_x_preferred":[
        "\u862d\u55ac\u683c\u862d\u5fb7"
    ],
    "wof:name":"Rancho Grande",
    "wof:placetype":"locality",
    "wof:population":1
},
  "geometry": {"coordinates":[-98.06480000000001,22.5289],"type":"Point"}
}