{
  "type": "Feature",
  "properties": {
    "iso:country":"MX",
    "name:deu_x_preferred":[
        "Vallarta"
    ],
    "name:fra_x_preferred":[
        "Vallarta"
    ],
    "name:spa_x_preferred":[
        "Vallarta"
    ],
    "qs:gn_adm0_cc":"MX",
    "qs:gn_local":3996069,
    "qs:local_max":355,
    "qs:local_sum":1530,
    "qs:localhoods":20,
    "qs:name":"Vallarta",
    "qs:name_adm0":"M\u00e9xico",
    "qs:name_adm1":"Baja California",
    "qs:name_adm2":"Mexicali",
    "qs:name_local":"Mexicali",
    "qs:photo_max":8,
    "qs:photo_sum":8,
    "qs:placetype":"Suburb",
    "qs:quad_count":1,
    "qs:woe_adm0":23424900,
    "qs:woe_adm1":2346265,
    "qs:woe_adm2":12599692,
    "qs:woe_lau":0,
    "qs:woe_local":133475,
    "qs:woe_ver":"7.10.0",
    "qs_pg:name":"Vallarta",
    "qs_pg:name_adm0":"M\u00e9xico",
    "qs_pg:name_adm1":"Baja California",
    "qs_pg:photos":9,
    "qs_pg:photos_1k":2,
    "qs_pg:photos_9k":1,
    "qs_pg:photos_9r":1,
    "qs_pg:photos_all":9,
    "qs_pg:photos_sr":1,
    "qs_pg:pop_sr":0,
    "qs_pg:qs_pg_placetype":"neighbourhood",
    "qs_pg:qs_pg_placetype_gp":"Suburb",
    "qs_pg:woe_adm0":23424900,
    "wd:wordcount":43,
    "woe:adm0_id":23424900,
    "woe:name_adm0":"M\u00e9xico",
    "woe:name_adm1":"Baja California",
    "woe:placetype":"Suburb",
    "wof:lang":[
        "spa"
    ],
    "wof:name":"Vallarta",
    "wof:placetype":"neighbourhood"
},
  "geometry": {"coordinates":[-115.43609600000001,32.641689],"type":"Point"}
}