{
  "type": "Feature",
  "properties": {
    "gn:admin1_code":"20",
    "gn:admin2_code":"318.0",
    "gn:asciiname":"San Andres Copala",
    "gn:country_code":"MX",
    "gn:dem":335,
    "gn:feature_class":"P",
    "gn:feature_code":"PPL",
    "gn:name":"San Andr\u00e9s Copala",
    "gn:population":840,
    "gn:timezone":"America/Mexico_City",
    "iso:country":"MX",
    "name:spa_x_preferred":[
        "Copala"
    ],
    "name:spa_x_variant":[
        "San Andr\u00e9s Copala"
    ],
    "wof:name":"San Andres Copala",
    "wof:placetype":"locality",
    "wof:population":840
},
  "geometry": {"coordinates":[-97.14469,15.99886],"type":"Point"}
}