{
  "type": "Feature",
  "properties": {
    "gn:admin1_code":"14",
    "gn:admin2_code":"73",
    "gn:asciiname":"El Duarte",
    "gn:country_code":"MX",
    "gn:dem":1855,
    "gn:feature_class":"P",
    "gn:feature_code":"PPL",
    "gn:name":"El Duarte",
    "gn:population":48,
    "gn:timezone":"America/Mexico_City",
    "iso:country":"MX",
    "wof:name":"El Duarte",
    "wof:placetype":"locality",
    "wof:population":48
},
  "geometry": {"coordinates":[-102.33806,21.19333],"type":"Point"}
}