{
  "type": "Feature",
  "properties": {
    "gn:admin1_code":"7",
    "gn:admin2_code":"20.0",
    "gn:asciiname":"Jose Alejandro Saucedo (La Victoria)",
    "gn:country_code":"MX",
    "gn:dem":464,
    "gn:feature_class":"P",
    "gn:feature_code":"PPL",
    "gn:name":"Jos\u00e9 Alejandro Saucedo (La Victoria)",
    "gn:population":5,
    "gn:timezone":"America/Monterrey",
    "iso:country":"MX",
    "name:und_x_variant":[
        "Jos\u00e9 Alejandro Saucedo (La Victoria)"
    ],
    "wof:name":"Jose Alejandro Saucedo (La Victoria)",
    "wof:placetype":"locality",
    "wof:population":5
},
  "geometry": {"coordinates":[-101.45009,27.85943],"type":"Point"}
}