{
  "type": "Feature",
  "properties": {
    "gn:admin1_code":"26",
    "gn:admin2_code":"66.0",
    "gn:asciiname":"Teopari",
    "gn:country_code":"MX",
    "gn:dem":669,
    "gn:feature_class":"P",
    "gn:feature_code":"PPL",
    "gn:name":"Te\u00f3pari",
    "gn:population":0,
    "gn:timezone":"America/Hermosillo",
    "iso:country":"MX",
    "name:spa_x_preferred":[
        "Te\u00f3pari"
    ],
    "name:und_x_variant":[
        "Rancho Teopari",
        "Teopari",
        "Teopare"
    ],
    "wof:name":"Teopari",
    "wof:placetype":"locality"
},
  "geometry": {"coordinates":[-110.0826,29.23692],"type":"Point"}
}