{
  "type": "Feature",
  "properties": {
    "gn:admin1_code":"28.0",
    "gn:admin2_code":"37.0",
    "gn:asciiname":"Mayoral",
    "gn:country_code":"MX",
    "gn:dem":182,
    "gn:feature_class":"P",
    "gn:feature_code":"PPL",
    "gn:name":"Mayoral",
    "gn:population":0,
    "gn:timezone":"America/Monterrey",
    "iso:country":"MX",
    "name:fra_x_preferred":[
        "Mayoral"
    ],
    "name:spa_x_preferred":[
        "Mayoral"
    ],
    "wof:name":"Mayoral",
    "wof:placetype":"locality"
},
  "geometry": {"coordinates":[-98.40488000000001,23.79781],"type":"Point"}
}