{
  "type": "Feature",
  "properties": {
    "gn:admin1_code":"32",
    "gn:admin2_code":"10.0",
    "gn:asciiname":"Colonia Benito Juarez",
    "gn:country_code":"MX",
    "gn:dem":2085,
    "gn:feature_class":"P",
    "gn:feature_code":"PPL",
    "gn:name":"Colonia Benito Ju\u00e1rez",
    "gn:population":263,
    "gn:timezone":"America/Mexico_City",
    "iso:country":"MX",
    "name:und_x_variant":[
        "Colonia Benito Ju\u00e1rez"
    ],
    "wof:name":"Colonia Benito Juarez",
    "wof:placetype":"locality",
    "wof:population":263
},
  "geometry": {"coordinates":[-102.63222,23.11556],"type":"Point"}
}