{
  "type": "Feature",
  "properties": {
    "gn:admin1_code":"11",
    "gn:admin2_code":"22.0",
    "gn:asciiname":"Maria Eugenia",
    "gn:country_code":"MX",
    "gn:dem":2285,
    "gn:feature_class":"P",
    "gn:feature_code":"PPL",
    "gn:name":"Mar\u00eda Eugenia",
    "gn:population":7,
    "gn:timezone":"America/Mexico_City",
    "iso:country":"MX",
    "name:und_x_variant":[
        "Mar\u00eda Eugenia"
    ],
    "wof:name":"Maria Eugenia",
    "wof:placetype":"locality",
    "wof:population":7
},
  "geometry": {"coordinates":[-101.52361000000001,21.72639],"type":"Point"}
}