{
  "type": "Feature",
  "properties": {
    "gn:admin1_code":"5",
    "gn:admin2_code":"45.0",
    "gn:asciiname":"Las Nieves",
    "gn:country_code":"MX",
    "gn:dem":338,
    "gn:feature_class":"P",
    "gn:feature_code":"PPL",
    "gn:name":"Las Nieves",
    "gn:population":0,
    "gn:timezone":"America/Mexico_City",
    "iso:country":"MX",
    "name:ceb_x_preferred":[
        "Las Nieves"
    ],
    "name:deu_x_preferred":[
        "Las Nieves"
    ],
    "name:ita_x_preferred":[
        "Las Nieves"
    ],
    "name:nld_x_preferred":[
        "Las Nieves"
    ],
    "name:spa_x_preferred":[
        "Las Nieves"
    ],
    "name:swe_x_preferred":[
        "Las Nieves"
    ],
    "wof:name":"Las Nieves",
    "wof:placetype":"locality"
},
  "geometry": {"coordinates":[-92.93498,17.49758],"type":"Point"}
}