{
  "type": "Feature",
  "properties": {
    "gn:admin1_code":"16",
    "gn:admin2_code":"96.0",
    "gn:asciiname":"El Rincon de la Huerta",
    "gn:country_code":"MX",
    "gn:dem":782,
    "gn:feature_class":"P",
    "gn:feature_code":"PPL",
    "gn:name":"El Rinc\u00f3n de la Huerta",
    "gn:population":5,
    "gn:timezone":"America/Mexico_City",
    "iso:country":"MX",
    "name:und_x_variant":[
        "El Rinc\u00f3n de la Huerta"
    ],
    "wof:name":"El Rincon de la Huerta",
    "wof:placetype":"locality",
    "wof:population":5
},
  "geometry": {"coordinates":[-102.35778000000001,18.41528],"type":"Point"}
}