{
  "type": "Feature",
  "properties": {
    "gn:admin1_code":"8.0",
    "gn:admin2_code":"7.0",
    "gn:asciiname":"Jaguey",
    "gn:country_code":"MX",
    "gn:dem":24,
    "gn:feature_class":"P",
    "gn:feature_code":"PPL",
    "gn:name":"Jaguey",
    "gn:population":0,
    "gn:timezone":"America/Mexico_City",
    "iso:country":"MX",
    "wof:name":"Jaguey",
    "wof:placetype":"locality"
},
  "geometry": {"coordinates":[-104.54722,19.23333],"type":"Point"}
}