{
  "type": "Feature",
  "properties": {
    "gn:admin1_code":"5.0",
    "gn:admin2_code":"107.0",
    "gn:asciiname":"El Roblar Espeso",
    "gn:country_code":"MX",
    "gn:dem":694,
    "gn:feature_class":"P",
    "gn:feature_code":"PPL",
    "gn:name":"El Roblar Espeso",
    "gn:population":0,
    "gn:timezone":"America/Mexico_City",
    "iso:country":"MX",
    "name:spa_x_preferred":[
        "El Roblar Espeso"
    ],
    "wof:name":"El Roblar Espeso",
    "wof:placetype":"locality"
},
  "geometry": {"coordinates":[-93.13314,16.24324],"type":"Point"}
}