{
  "type": "Feature",
  "properties": {
    "gn:admin1_code":"12",
    "gn:admin2_code":"35",
    "gn:asciiname":"Huerta Carrion",
    "gn:country_code":"MX",
    "gn:dem":768,
    "gn:feature_class":"P",
    "gn:feature_code":"PPL",
    "gn:name":"Huerta Carri\u00f3n",
    "gn:population":22,
    "gn:timezone":"America/Mexico_City",
    "iso:country":"MX",
    "name:und_x_variant":[
        "Huerta Carri\u00f3n"
    ],
    "wof:name":"Huerta Carrion",
    "wof:placetype":"locality",
    "wof:population":22
},
  "geometry": {"coordinates":[-99.5104,18.33847],"type":"Point"}
}