{
  "type": "Feature",
  "properties": {
    "gn:admin1_code":"27",
    "gn:admin2_code":"17.0",
    "gn:asciiname":"La Estancia",
    "gn:country_code":"MX",
    "gn:dem":155,
    "gn:feature_class":"P",
    "gn:feature_code":"PPL",
    "gn:name":"La Estancia",
    "gn:population":218,
    "gn:timezone":"America/Mexico_City",
    "iso:country":"MX",
    "wof:name":"La Estancia",
    "wof:placetype":"locality",
    "wof:population":218
},
  "geometry": {"coordinates":[-91.21355,17.28339],"type":"Point"}
}