{
  "type": "Feature",
  "properties": {
    "gn:admin1_code":"25",
    "gn:admin2_code":"3.0",
    "gn:asciiname":"Campo El Carrizalejo",
    "gn:country_code":"MX",
    "gn:dem":225,
    "gn:feature_class":"P",
    "gn:feature_code":"PPL",
    "gn:name":"Campo El Carrizalejo",
    "gn:population":0,
    "gn:timezone":"America/Mazatlan",
    "iso:country":"MX",
    "name:spa_x_preferred":[
        "Campo El Carrizalejo"
    ],
    "name:und_x_variant":[
        "El Carrizalejo"
    ],
    "wof:name":"Campo El Carrizalejo",
    "wof:placetype":"locality"
},
  "geometry": {"coordinates":[-107.49896,25.32105],"type":"Point"}
}