{
  "type": "Feature",
  "properties": {
    "gn:admin1_code":"11",
    "gn:admin2_code":"27",
    "gn:asciiname":"Armando Prieto Rodriguez (El Sapo)",
    "gn:country_code":"MX",
    "gn:dem":1718,
    "gn:feature_class":"P",
    "gn:feature_code":"PPL",
    "gn:name":"Armando Prieto Rodr\u00edguez (El Sapo)",
    "gn:population":30,
    "gn:timezone":"America/Mexico_City",
    "iso:country":"MX",
    "name:und_x_variant":[
        "Armando Prieto Rodr\u00edguez (El Sapo)"
    ],
    "wof:name":"Armando Prieto Rodriguez (El Sapo)",
    "wof:placetype":"locality",
    "wof:population":30
},
  "geometry": {"coordinates":[-101.12222,20.58528],"type":"Point"}
}