{
  "type": "Feature",
  "properties": {
    "gn:admin1_code":"24",
    "gn:admin2_code":"29.0",
    "gn:asciiname":"El Descanso",
    "gn:country_code":"MX",
    "gn:dem":97,
    "gn:feature_class":"P",
    "gn:feature_code":"PPL",
    "gn:name":"El Descanso",
    "gn:population":0,
    "gn:timezone":"America/Mexico_City",
    "iso:country":"MX",
    "name:spa_x_preferred":[
        "El Descanso"
    ],
    "wof:name":"El Descanso",
    "wof:placetype":"locality"
},
  "geometry": {"coordinates":[-98.66034999999999,21.48792000000001],"type":"Point"}
}