{
  "type": "Feature",
  "properties": {
    "gn:admin1_code":"23",
    "gn:admin2_code":"7.0",
    "gn:asciiname":"El Pocito",
    "gn:country_code":"MX",
    "gn:dem":18,
    "gn:feature_class":"P",
    "gn:feature_code":"PPL",
    "gn:name":"El Pocito",
    "gn:population":159,
    "gn:timezone":"America/Cancun",
    "iso:country":"MX",
    "wof:name":"El Pocito",
    "wof:placetype":"locality",
    "wof:population":159
},
  "geometry": {"coordinates":[-87.48283000000001,20.89001],"type":"Point"}
}