{
  "type": "Feature",
  "properties": {
    "gn:admin1_code":"15",
    "gn:admin2_code":"117",
    "gn:asciiname":"Rancho Santa Lucia",
    "gn:country_code":"MX",
    "gn:dem":1621,
    "gn:feature_class":"P",
    "gn:feature_code":"PPL",
    "gn:name":"Rancho Santa Luc\u00eda",
    "gn:population":27,
    "gn:timezone":"America/Mexico_City",
    "iso:country":"MX",
    "name:und_x_variant":[
        "Rancho Santa Luc\u00eda"
    ],
    "wof:name":"Rancho Santa Lucia",
    "wof:placetype":"locality",
    "wof:population":27
},
  "geometry": {"coordinates":[-99.74337,18.72657],"type":"Point"}
}