{
  "type": "Feature",
  "properties": {
    "gn:admin1_code":"26.0",
    "gn:admin2_code":"5.0",
    "gn:asciiname":"Balbanera",
    "gn:country_code":"MX",
    "gn:dem":1279,
    "gn:feature_class":"P",
    "gn:feature_code":"PPL",
    "gn:name":"Balbanera",
    "gn:population":0,
    "gn:timezone":"America/Hermosillo",
    "iso:country":"MX",
    "wof:name":"Balbanera",
    "wof:placetype":"locality"
},
  "geometry": {"coordinates":[-108.86667,28.83333],"type":"Point"}
}