{
  "type": "Feature",
  "properties": {
    "gn:admin1_code":"6",
    "gn:admin2_code":"36.0",
    "gn:asciiname":"La Palma",
    "gn:country_code":"MX",
    "gn:dem":1394,
    "gn:feature_class":"P",
    "gn:feature_code":"PPL",
    "gn:name":"La Palma",
    "gn:population":6,
    "gn:timezone":"America/Chihuahua",
    "iso:country":"MX",
    "wof:name":"La Palma",
    "wof:placetype":"locality",
    "wof:population":6
},
  "geometry": {"coordinates":[-104.93556,27.07472000000001],"type":"Point"}
}