{
  "type": "Feature",
  "properties": {
    "gn:admin1_code":"20.0",
    "gn:admin2_code":"498.0",
    "gn:asciiname":"El Vergel",
    "gn:country_code":"MX",
    "gn:dem":70,
    "gn:feature_class":"P",
    "gn:feature_code":"PPL",
    "gn:name":"El Vergel",
    "gn:population":0,
    "gn:timezone":"America/Mexico_City",
    "iso:country":"MX",
    "name:spa_x_preferred":[
        "El Vergel"
    ],
    "wof:name":"El Vergel",
    "wof:placetype":"locality"
},
  "geometry": {"coordinates":[-95.35035999999999,17.50945],"type":"Point"}
}