{
  "type": "Feature",
  "properties": {
    "gn:admin1_code":"24",
    "gn:admin2_code":"36.0",
    "gn:asciiname":"Quinta Karel",
    "gn:country_code":"MX",
    "gn:dem":375,
    "gn:feature_class":"P",
    "gn:feature_code":"PPL",
    "gn:name":"Quinta Karel",
    "gn:population":9,
    "gn:timezone":"America/Mexico_City",
    "iso:country":"MX",
    "wof:name":"Quinta Karel",
    "wof:placetype":"locality",
    "wof:population":9
},
  "geometry": {"coordinates":[-99.39694,21.945],"type":"Point"}
}