{
  "type": "Feature",
  "properties": {
    "gn:admin1_code":"14.0",
    "gn:admin2_code":"87.0",
    "gn:asciiname":"El Montoso",
    "gn:country_code":"MX",
    "gn:dem":1686,
    "gn:feature_class":"P",
    "gn:feature_code":"PPL",
    "gn:name":"El Montoso",
    "gn:population":0,
    "gn:timezone":"America/Mexico_City",
    "iso:country":"MX",
    "name:spa_x_preferred":[
        "El Montoso"
    ],
    "wof:name":"El Montoso",
    "wof:placetype":"locality"
},
  "geometry": {"coordinates":[-103.22999,19.30359],"type":"Point"}
}