{
  "type": "Feature",
  "properties": {
    "gn:admin1_code":"26",
    "gn:admin2_code":"12.0",
    "gn:asciiname":"Algodones",
    "gn:country_code":"MX",
    "gn:dem":232,
    "gn:feature_class":"P",
    "gn:feature_code":"PPL",
    "gn:name":"Algodones",
    "gn:population":2,
    "gn:timezone":"America/Hermosillo",
    "iso:country":"MX",
    "name:spa_x_preferred":[
        "Algodones"
    ],
    "wof:name":"Algodones",
    "wof:placetype":"locality",
    "wof:population":2
},
  "geometry": {"coordinates":[-110.11448,27.92209],"type":"Point"}
}