{
  "type": "Feature",
  "properties": {
    "gn:admin1_code":"21.0",
    "gn:asciiname":"Cantil Alto",
    "gn:country_code":"MX",
    "gn:dem":1834,
    "gn:feature_class":"P",
    "gn:feature_code":"PPL",
    "gn:name":"Cantil Alto",
    "gn:population":0,
    "gn:timezone":"America/Mexico_City",
    "iso:country":"MX",
    "name:spa_x_preferred":[
        "Cantil Alto"
    ],
    "wof:name":"Cantil Alto",
    "wof:placetype":"locality"
},
  "geometry": {"coordinates":[-97.99807,18.33823],"type":"Point"}
}