{
  "type": "Feature",
  "properties": {
    "gn:admin1_code":"4.0",
    "gn:admin2_code":"3.0",
    "gn:asciiname":"Los Tulipanes",
    "gn:country_code":"MX",
    "gn:dem":6,
    "gn:feature_class":"P",
    "gn:feature_code":"PPL",
    "gn:name":"Los Tulipanes",
    "gn:population":0,
    "gn:timezone":"America/Merida",
    "iso:country":"MX",
    "name:spa_x_preferred":[
        "Los Tulipanes"
    ],
    "name:spa_x_variant":[
        "La Ilusi\u00f3n"
    ],
    "wof:name":"Los Tulipanes",
    "wof:placetype":"locality"
},
  "geometry": {"coordinates":[-91.6003,18.14872],"type":"Point"}
}