{
  "type": "Feature",
  "properties": {
    "gn:admin1_code":"10.0",
    "gn:admin2_code":"26.0",
    "gn:asciiname":"El Pastor",
    "gn:country_code":"MX",
    "gn:dem":1150,
    "gn:feature_class":"P",
    "gn:feature_code":"PPL",
    "gn:name":"El Pastor",
    "gn:population":0,
    "gn:timezone":"America/Monterrey",
    "iso:country":"MX",
    "name:spa_x_preferred":[
        "El Pastor"
    ],
    "wof:name":"El Pastor",
    "wof:placetype":"locality"
},
  "geometry": {"coordinates":[-105.85132,24.55771],"type":"Point"}
}