{
  "type": "Feature",
  "properties": {
    "gn:admin1_code":"30",
    "gn:admin2_code":"159.0",
    "gn:asciiname":"Cimarrontla",
    "gn:country_code":"MX",
    "gn:dem":1915,
    "gn:feature_class":"P",
    "gn:feature_code":"PPL",
    "gn:name":"Cimarrontla",
    "gn:population":242,
    "gn:timezone":"America/Mexico_City",
    "iso:country":"MX",
    "wof:name":"Cimarrontla",
    "wof:placetype":"locality",
    "wof:population":242
},
  "geometry": {"coordinates":[-97.07167,18.55556],"type":"Point"}
}