{
  "type": "Feature",
  "properties": {
    "gn:admin1_code":"5",
    "gn:asciiname":"Frontera",
    "gn:country_code":"MX",
    "gn:dem":72,
    "gn:feature_class":"P",
    "gn:feature_code":"PPL",
    "gn:name":"Frontera",
    "gn:population":0,
    "gn:timezone":"America/Mexico_City",
    "iso:country":"MX",
    "name:spa_x_preferred":[
        "Frontera"
    ],
    "wof:name":"Frontera",
    "wof:placetype":"locality"
},
  "geometry": {"coordinates":[-94.07719,16.32201],"type":"Point"}
}