{
  "type": "Feature",
  "properties": {
    "gn:admin1_code":"5",
    "gn:asciiname":"Frontera",
    "gn:country_code":"MX",
    "gn:dem":72,
    "gn:feature_class":"P",
    "gn:feature_code":"PPL",
    "gn:name":"Frontera",
    "gn:population":0,
    "gn:timezone":"America/Mexico_City",
    "iso:country":"MX",
    "name:ara_x_preferred":[
        "\u0641\u0648\u0631\u064a\u0646\u062a\u0631\u0627"
    ],
    "name:ben_x_preferred":[
        "\u09ab\u09cd\u09b0\u09a8\u09cd\u09a4\u09c7\u09b0\u09be"
    ],
    "name:bre_x_preferred":[
        "Frontera"
    ],
    "name:ceb_x_preferred":[
        "Frontera"
    ],
    "name:deu_x_preferred":[
        "Frontera"
    ],
    "name:ell_x_preferred":[
        "\u03a6\u03c1\u03bf\u03bd\u03c4\u03ad\u03c1\u03b1"
    ],
    "name:fas_x_preferred":[
        "\u0641\u0631\u0648\u0646\u062a\u0631\u0627"
    ],
    "name:fin_x_preferred":[
        "Frontera"
    ],
    "name:fra_x_preferred":[
        "Frontera"
    ],
    "name:heb_x_preferred":[
        "\u05e4\u05e8\u05d5\u05e0\u05d8\u05e8\u05d4"
    ],
    "name:hin_x_preferred":[
        "\u092b\u093c\u094d\u0930\u0902\u091f\u0947\u0930\u093e"
    ],
    "name:hun_x_preferred":[
        "Frontera"
    ],
    "name:ind_x_preferred":[
        "Frontera"
    ],
    "name:ita_x_preferred":[
        "Frontera"
    ],
    "name:jpn_x_preferred":[
        "\u30d5\u30ed\u30f3\u30c6\u30e9"
    ],
    "name:kor_x_preferred":[
        "\ud504\ub860\ud14c\ub77c"
    ],
    "name:nld_x_preferred":[
        "Frontera"
    ],
    "name:por_x_preferred":[
        "Frontera"
    ],
    "name:rus_x_preferred":[
        "\u0424\u0440\u043e\u043d\u0442\u0435\u0440\u0430"
    ],
    "name:spa_x_preferred":[
        "Frontera"
    ],
    "name:srp_x_preferred":[
        "\u0424\u0440\u043e\u043d\u0442\u0435\u0440\u0430"
    ],
    "name:swe_x_preferred":[
        "Frontera"
    ],
    "name:tur_x_preferred":[
        "Frontera"
    ],
    "name:ukr_x_preferred":[
        "\u0424\u0440\u043e\u043d\u0442\u0435\u0440\u0430"
    ],
    "name:urd_x_preferred":[
        "\u0641\u0631\u0646\u0679\u06cc\u0631\u0627"
    ],
    "name:vie_x_preferred":[
        "Frontera"
    ],
    "name:zho_cn_x_preferred":[
        "\u5f17\u9f99\u7279\u62c9"
    ],
    "name:zho_tw_x_preferred":[
        "\u5f17\u9f8d\u7279\u62c9"
    ],
    "wof:name":"Frontera",
    "wof:placetype":"locality"
},
  "geometry": {"coordinates":[-94.07719,16.32201],"type":"Point"}
}