{
  "type": "Feature",
  "properties": {
    "gn:admin1_code":"4.0",
    "gn:asciiname":"Los Manguitos",
    "gn:country_code":"MX",
    "gn:dem":2,
    "gn:feature_class":"P",
    "gn:feature_code":"PPL",
    "gn:name":"Los Manguitos",
    "gn:population":0,
    "gn:timezone":"America/Merida",
    "iso:country":"MX",
    "name:spa_x_preferred":[
        "Los Manguitos"
    ],
    "wof:name":"Los Manguitos",
    "wof:placetype":"locality"
},
  "geometry": {"coordinates":[-91.50754000000001,18.23111],"type":"Point"}
}