{
  "type": "Feature",
  "properties": {
    "gn:admin1_code":"20",
    "gn:admin2_code":"378.0",
    "gn:asciiname":"Rio Culebra (El Tlacuache)",
    "gn:country_code":"MX",
    "gn:dem":1715,
    "gn:feature_class":"P",
    "gn:feature_code":"PPL",
    "gn:name":"R\u00edo Culebra (El Tlacuache)",
    "gn:population":60,
    "gn:timezone":"America/Mexico_City",
    "iso:country":"MX",
    "name:und_x_variant":[
        "R\u00edo Culebra (El Tlacuache)"
    ],
    "wof:name":"Rio Culebra (El Tlacuache)",
    "wof:placetype":"locality",
    "wof:population":60
},
  "geometry": {"coordinates":[-96.91667,16.79139],"type":"Point"}
}