{
  "type": "Feature",
  "properties": {
    "gn:admin1_code":"30",
    "gn:admin2_code":"47.0",
    "gn:asciiname":"Tlamapa",
    "gn:country_code":"MX",
    "gn:dem":1644,
    "gn:feature_class":"P",
    "gn:feature_code":"PPL",
    "gn:name":"Tlamapa",
    "gn:population":82,
    "gn:timezone":"America/Mexico_City",
    "iso:country":"MX",
    "wof:name":"Tlamapa",
    "wof:placetype":"locality",
    "wof:population":82
},
  "geometry": {"coordinates":[-97.0625,19.08111],"type":"Point"}
}