{
  "type": "Feature",
  "properties": {
    "gn:admin1_code":"5.0",
    "gn:admin2_code":"61.0",
    "gn:asciiname":"Las Piedronas",
    "gn:country_code":"MX",
    "gn:dem":469,
    "gn:feature_class":"P",
    "gn:feature_code":"PPL",
    "gn:name":"Las Piedronas",
    "gn:population":0,
    "gn:timezone":"America/Mexico_City",
    "iso:country":"MX",
    "name:spa_x_preferred":[
        "Las Piedronas"
    ],
    "wof:name":"Las Piedronas",
    "wof:placetype":"locality"
},
  "geometry": {"coordinates":[-93.43832,16.96183],"type":"Point"}
}