{
  "type": "Feature",
  "properties": {
    "gn:admin1_code":"14",
    "gn:admin2_code":"68.0",
    "gn:asciiname":"El Tecuane",
    "gn:country_code":"MX",
    "gn:dem":415,
    "gn:feature_class":"P",
    "gn:feature_code":"PPL",
    "gn:name":"El Tecuane",
    "gn:population":7,
    "gn:timezone":"America/Mexico_City",
    "iso:country":"MX",
    "wof:name":"El Tecuane",
    "wof:placetype":"locality",
    "wof:population":7
},
  "geometry": {"coordinates":[-104.81583000000001,19.66694],"type":"Point"}
}