{
  "type": "Feature",
  "properties": {
    "gn:admin1_code":"30",
    "gn:admin2_code":"134.0",
    "gn:asciiname":"Chichicaxtle",
    "gn:country_code":"MX",
    "gn:dem":125,
    "gn:feature_class":"P",
    "gn:feature_code":"PPL",
    "gn:name":"Chichicaxtle",
    "gn:population":1910,
    "gn:timezone":"America/Mexico_City",
    "iso:country":"MX",
    "wof:name":"Chichicaxtle",
    "wof:placetype":"locality",
    "wof:population":1910
},
  "geometry": {"coordinates":[-96.46861,19.34306],"type":"Point"}
}