{
  "type": "Feature",
  "properties": {
    "gn:admin1_code":"19",
    "gn:admin2_code":"4.0",
    "gn:asciiname":"Lomas los Cavazos",
    "gn:country_code":"MX",
    "gn:dem":443,
    "gn:feature_class":"P",
    "gn:feature_code":"PPL",
    "gn:name":"Lomas los Cavazos",
    "gn:population":0,
    "gn:timezone":"America/Monterrey",
    "iso:country":"MX",
    "name:spa_x_preferred":[
        "Lomas los Cavazos"
    ],
    "wof:name":"Lomas los Cavazos",
    "wof:placetype":"locality"
},
  "geometry": {"coordinates":[-100.03315000000001,25.34105],"type":"Point"}
}