{
  "type": "Feature",
  "properties": {
    "gn:admin1_code":"9.0",
    "gn:asciiname":"Tercer Dinamo",
    "gn:country_code":"MX",
    "gn:dem":2808,
    "gn:feature_class":"P",
    "gn:feature_code":"PPL",
    "gn:name":"Tercer Dinamo",
    "gn:population":0,
    "gn:timezone":"America/Mexico_City",
    "iso:country":"MX",
    "name:spa_x_preferred":[
        "Tercer Dinamo"
    ],
    "wof:name":"Tercer Dinamo",
    "wof:placetype":"locality"
},
  "geometry": {"coordinates":[-99.274,19.28178],"type":"Point"}
}