{
  "type": "Feature",
  "properties": {
    "gn:admin1_code":"14",
    "gn:admin2_code":"104.0",
    "gn:asciiname":"Rancho de Conchas",
    "gn:country_code":"MX",
    "gn:dem":2040,
    "gn:feature_class":"P",
    "gn:feature_code":"PPL",
    "gn:name":"Rancho de Conchas",
    "gn:population":0,
    "gn:timezone":"America/Mexico_City",
    "iso:country":"MX",
    "name:spa_x_preferred":[
        "Rancho de Conchas"
    ],
    "wof:name":"Rancho de Conchas",
    "wof:placetype":"locality"
},
  "geometry": {"coordinates":[-103.45336,21.89331],"type":"Point"}
}