{
  "type": "Feature",
  "properties": {
    "gn:admin1_code":"6",
    "gn:admin2_code":"37.0",
    "gn:asciiname":"Desierto",
    "gn:country_code":"MX",
    "gn:dem":1248,
    "gn:feature_class":"P",
    "gn:feature_code":"PPL",
    "gn:name":"Desierto",
    "gn:population":0,
    "gn:timezone":"America/Ojinaga",
    "iso:country":"MX",
    "name:ara_x_preferred":[
        "\u0635\u062d\u0631\u0627\u0621"
    ],
    "name:ell_x_preferred":[
        "Desierto"
    ],
    "name:fra_x_preferred":[
        "Desierto"
    ],
    "name:ind_x_preferred":[
        "Desierto"
    ],
    "name:ita_x_preferred":[
        "Desierto"
    ],
    "name:por_x_preferred":[
        "Desierto"
    ],
    "name:spa_x_preferred":[
        "Desierto"
    ],
    "wof:name":"Desierto",
    "wof:placetype":"locality"
},
  "geometry": {"coordinates":[-106.43333,31.48333],"type":"Point"}
}