{
  "type": "Feature",
  "properties": {
    "gn:admin1_code":"18",
    "gn:admin2_code":"19",
    "gn:asciiname":"Los Llanitos",
    "gn:country_code":"MX",
    "gn:dem":1050,
    "gn:feature_class":"P",
    "gn:feature_code":"PPL",
    "gn:name":"Los Llanitos",
    "gn:population":10,
    "gn:timezone":"America/Mazatlan",
    "iso:country":"MX",
    "name:ita_x_preferred":[
        "Los Llanitos"
    ],
    "name:spa_x_preferred":[
        "Los Llanitos"
    ],
    "name:zho_x_preferred":[
        "\u6d1b\u65af\u5229\u4e9e\u5c3c\u6258\u65af"
    ],
    "wof:name":"Los Llanitos",
    "wof:placetype":"locality",
    "wof:population":10
},
  "geometry": {"coordinates":[-104.375,21.40528],"type":"Point"}
}