{
  "type": "Feature",
  "properties": {
    "gn:admin1_code":"28.0",
    "gn:admin2_code":"37.0",
    "gn:asciiname":"Don Nicho",
    "gn:country_code":"MX",
    "gn:dem":74,
    "gn:feature_class":"P",
    "gn:feature_code":"PPL",
    "gn:name":"Don Nicho",
    "gn:population":2,
    "gn:timezone":"America/Monterrey",
    "iso:country":"MX",
    "name:spa_x_preferred":[
        "Don Nicho"
    ],
    "wof:name":"Don Nicho",
    "wof:placetype":"locality",
    "wof:population":2
},
  "geometry": {"coordinates":[-98.00917,23.48444],"type":"Point"}
}