{
  "type": "Feature",
  "properties": {
    "gn:admin1_code":"15",
    "gn:admin2_code":"1.0",
    "gn:asciiname":"Barrios Dos",
    "gn:country_code":"MX",
    "gn:dem":2511,
    "gn:feature_class":"P",
    "gn:feature_code":"PPL",
    "gn:name":"Barrios Dos",
    "gn:population":0,
    "gn:timezone":"America/Mexico_City",
    "iso:country":"MX",
    "wof:name":"Barrios Dos",
    "wof:placetype":"locality"
},
  "geometry": {"coordinates":[-99.89972,19.93361],"type":"Point"}
}