{
  "type": "Feature",
  "properties": {
    "gn:admin1_code":"26.0",
    "gn:admin2_code":"52.0",
    "gn:asciiname":"El Sobaco",
    "gn:country_code":"MX",
    "gn:dem":502,
    "gn:feature_class":"P",
    "gn:feature_code":"PPL",
    "gn:name":"El Sobaco",
    "gn:population":0,
    "gn:timezone":"America/Hermosillo",
    "iso:country":"MX",
    "name:spa_x_preferred":[
        "El Sobaco"
    ],
    "wof:name":"El Sobaco",
    "wof:placetype":"locality"
},
  "geometry": {"coordinates":[-109.21796999999999,29.12082],"type":"Point"}
}