{
  "type": "Feature",
  "properties": {
    "gn:admin1_code":"6",
    "gn:admin2_code":"65.0",
    "gn:asciiname":"Basascuchi",
    "gn:country_code":"MX",
    "gn:dem":855,
    "gn:feature_class":"P",
    "gn:feature_code":"PPL",
    "gn:name":"Bas\u00e1scuchi",
    "gn:population":0,
    "gn:timezone":"America/Chihuahua",
    "iso:country":"MX",
    "name:spa_x_preferred":[
        "Bas\u00e1scuchi"
    ],
    "wof:name":"Basascuchi",
    "wof:placetype":"locality"
},
  "geometry": {"coordinates":[-107.83723000000001,27.41827],"type":"Point"}
}