{
  "type": "Feature",
  "properties": {
    "gn:admin1_code":"5.0",
    "gn:asciiname":"Veinte de Mayo",
    "gn:country_code":"MX",
    "gn:dem":702,
    "gn:feature_class":"P",
    "gn:feature_code":"PPL",
    "gn:name":"Veinte de Mayo",
    "gn:population":0,
    "gn:timezone":"America/Mexico_City",
    "iso:country":"MX",
    "name:spa_x_preferred":[
        "Veinte de Mayo"
    ],
    "wof:name":"Veinte de Mayo",
    "wof:placetype":"locality"
},
  "geometry": {"coordinates":[-91.97213000000001,15.70035],"type":"Point"}
}