{
  "type": "Feature",
  "properties": {
    "gn:admin1_code":"12",
    "gn:admin2_code":"18",
    "gn:asciiname":"Mata de Mangle",
    "gn:country_code":"MX",
    "gn:dem":6,
    "gn:feature_class":"P",
    "gn:feature_code":"PPL",
    "gn:name":"Mata de Mangle",
    "gn:population":17,
    "gn:timezone":"America/Mazatlan",
    "iso:country":"MX",
    "wof:name":"Mata de Mangle",
    "wof:placetype":"locality",
    "wof:population":17
},
  "geometry": {"coordinates":[-99.01273999999999,16.57419],"type":"Point"}
}