{
  "type": "Feature",
  "properties": {
    "gn:admin1_code":"25",
    "gn:admin2_code":"10.0",
    "gn:asciiname":"La Curva",
    "gn:country_code":"MX",
    "gn:dem":53,
    "gn:feature_class":"P",
    "gn:feature_code":"PPL",
    "gn:name":"La Curva",
    "gn:population":236,
    "gn:timezone":"America/Mazatlan",
    "iso:country":"MX",
    "wof:name":"La Curva",
    "wof:placetype":"locality",
    "wof:population":236
},
  "geometry": {"coordinates":[-108.76944,26.2725],"type":"Point"}
}