{
  "type": "Feature",
  "properties": {
    "gn:admin1_code":"6.0",
    "gn:admin2_code":"61.0",
    "gn:asciiname":"El Altamar",
    "gn:country_code":"MX",
    "gn:dem":1626,
    "gn:feature_class":"P",
    "gn:feature_code":"PPL",
    "gn:name":"El Altamar",
    "gn:population":0,
    "gn:timezone":"America/Chihuahua",
    "iso:country":"MX",
    "name:spa_x_preferred":[
        "El Altamar"
    ],
    "wof:name":"El Altamar",
    "wof:placetype":"locality"
},
  "geometry": {"coordinates":[-105.94653999999998,27.70933],"type":"Point"}
}