{
  "type": "Feature",
  "properties": {
    "gn:admin1_code":"30",
    "gn:admin2_code":"11.0",
    "gn:asciiname":"La Mojarra",
    "gn:country_code":"MX",
    "gn:dem":9,
    "gn:feature_class":"P",
    "gn:feature_code":"PPL",
    "gn:name":"La Mojarra",
    "gn:population":0,
    "gn:timezone":"America/Mexico_City",
    "iso:country":"MX",
    "name:deu_x_preferred":[
        "La Mojarra"
    ],
    "name:fra_x_preferred":[
        "La Mojarra"
    ],
    "name:ita_x_preferred":[
        "La Mojarra"
    ],
    "name:jpn_x_preferred":[
        "\u30e9\u30fb\u30e2\u30cf\u30fc\u30e9"
    ],
    "name:por_x_preferred":[
        "La Mojarra"
    ],
    "name:rus_x_preferred":[
        "\u041b\u0430-\u041c\u043e\u0445\u0430\u0440\u0440\u0430"
    ],
    "name:spa_x_preferred":[
        "La Mojarra"
    ],
    "wof:name":"La Mojarra",
    "wof:placetype":"locality"
},
  "geometry": {"coordinates":[-95.79573000000001,18.62234],"type":"Point"}
}