{
  "type": "Feature",
  "properties": {
    "gn:admin1_code":"19.0",
    "gn:asciiname":"El Puerto del Aguaje",
    "gn:country_code":"MX",
    "gn:dem":1360,
    "gn:feature_class":"P",
    "gn:feature_code":"PPL",
    "gn:name":"El Puerto del Aguaje",
    "gn:population":0,
    "gn:timezone":"America/Monterrey",
    "iso:country":"MX",
    "name:spa_x_preferred":[
        "El Puerto del Aguaje"
    ],
    "wof:name":"El Puerto del Aguaje",
    "wof:placetype":"locality"
},
  "geometry": {"coordinates":[-100.07463,24.91412],"type":"Point"}
}