{
  "type": "Feature",
  "properties": {
    "gn:admin1_code":"10",
    "gn:admin2_code":"34.0",
    "gn:asciiname":"Los Burros",
    "gn:country_code":"MX",
    "gn:dem":473,
    "gn:feature_class":"P",
    "gn:feature_code":"PPL",
    "gn:name":"Los Burros",
    "gn:population":4,
    "gn:timezone":"America/Monterrey",
    "iso:country":"MX",
    "wof:name":"Los Burros",
    "wof:placetype":"locality",
    "wof:population":4
},
  "geometry": {"coordinates":[-107.0826,25.23025],"type":"Point"}
}