{
  "type": "Feature",
  "properties": {
    "gn:admin1_code":"19",
    "gn:admin2_code":"42.0",
    "gn:asciiname":"Altamira (Capadero)",
    "gn:country_code":"MX",
    "gn:dem":219,
    "gn:feature_class":"P",
    "gn:feature_code":"PPL",
    "gn:name":"Altamira (Capadero)",
    "gn:population":270,
    "gn:timezone":"America/Monterrey",
    "iso:country":"MX",
    "wof:name":"Altamira (Capadero)",
    "wof:placetype":"locality",
    "wof:population":270
},
  "geometry": {"coordinates":[-99.6194,25.68909],"type":"Point"}
}