{
  "type": "Feature",
  "properties": {
    "gn:admin1_code":"32.0",
    "gn:admin2_code":"22.0",
    "gn:asciiname":"Tanque Colorado",
    "gn:country_code":"MX",
    "gn:dem":2172,
    "gn:feature_class":"P",
    "gn:feature_code":"PPL",
    "gn:name":"Tanque Colorado",
    "gn:population":0,
    "gn:timezone":"America/Mexico_City",
    "iso:country":"MX",
    "name:spa_x_preferred":[
        "Tanque Colorado"
    ],
    "wof:name":"Tanque Colorado",
    "wof:placetype":"locality"
},
  "geometry": {"coordinates":[-103.27437999999999,24.11217000000001],"type":"Point"}
}