{
  "type": "Feature",
  "properties": {
    "gn:admin1_code":"31",
    "gn:admin2_code":"102.0",
    "gn:asciiname":"Nohcankam",
    "gn:country_code":"MX",
    "gn:dem":27,
    "gn:feature_class":"P",
    "gn:feature_code":"PPL",
    "gn:name":"Nohcankam",
    "gn:population":0,
    "gn:timezone":"America/Merida",
    "iso:country":"MX",
    "name:spa_x_preferred":[
        "Nohcankam"
    ],
    "wof:name":"Nohcankam",
    "wof:placetype":"locality"
},
  "geometry": {"coordinates":[-88.14275000000001,20.58068],"type":"Point"}
}