{
  "type": "Feature",
  "properties": {
    "gn:admin1_code":"6",
    "gn:admin2_code":"11.0",
    "gn:asciiname":"El Berrendito",
    "gn:country_code":"MX",
    "gn:dem":1255,
    "gn:feature_class":"P",
    "gn:feature_code":"PPL",
    "gn:name":"El Berrendito",
    "gn:population":4,
    "gn:timezone":"America/Chihuahua",
    "iso:country":"MX",
    "wof:name":"El Berrendito",
    "wof:placetype":"locality",
    "wof:population":4
},
  "geometry": {"coordinates":[-105.15128,27.65078],"type":"Point"}
}