{
  "type": "Feature",
  "properties": {
    "gn:admin1_code":"21",
    "gn:admin2_code":"89.0",
    "gn:asciiname":"Izquimpan",
    "gn:country_code":"MX",
    "gn:dem":428,
    "gn:feature_class":"P",
    "gn:feature_code":"PPL",
    "gn:name":"Izquimpan",
    "gn:population":83,
    "gn:timezone":"America/Mexico_City",
    "iso:country":"MX",
    "wof:name":"Izquimpan",
    "wof:placetype":"locality",
    "wof:population":83
},
  "geometry": {"coordinates":[-97.66773999999999,20.14951],"type":"Point"}
}