{
  "type": "Feature",
  "properties": {
    "gn:admin1_code":"4",
    "gn:admin2_code":"11",
    "gn:asciiname":"Nuevo Capricho",
    "gn:country_code":"MX",
    "gn:dem":58,
    "gn:feature_class":"P",
    "gn:feature_code":"PPL",
    "gn:name":"Nuevo Capricho",
    "gn:population":19,
    "gn:timezone":"America/Merida",
    "iso:country":"MX",
    "wof:name":"Nuevo Capricho",
    "wof:placetype":"locality",
    "wof:population":19
},
  "geometry": {"coordinates":[-90.50221999999999,18.10222000000001],"type":"Point"}
}