{
  "type": "Feature",
  "properties": {
    "gn:admin1_code":"7",
    "gn:admin2_code":"11",
    "gn:asciiname":"Crucero de Jalpa (Tramo Ancho)",
    "gn:country_code":"MX",
    "gn:dem":1207,
    "gn:feature_class":"P",
    "gn:feature_code":"PPL",
    "gn:name":"Crucero de Jalpa (Tramo Ancho)",
    "gn:population":12,
    "gn:timezone":"America/Monterrey",
    "iso:country":"MX",
    "wof:name":"Crucero de Jalpa (Tramo Ancho)",
    "wof:placetype":"locality",
    "wof:population":12
},
  "geometry": {"coordinates":[-101.78783,25.66252],"type":"Point"}
}