{
  "type": "Feature",
  "properties": {
    "gn:admin1_code":"30",
    "gn:admin2_code":"173",
    "gn:asciiname":"Pozo Blanco (El Retiro)",
    "gn:country_code":"MX",
    "gn:dem":355,
    "gn:feature_class":"P",
    "gn:feature_code":"PPL",
    "gn:name":"Pozo Blanco (El Retiro)",
    "gn:population":21,
    "gn:timezone":"America/Mexico_City",
    "iso:country":"MX",
    "wof:name":"Pozo Blanco (El Retiro)",
    "wof:placetype":"locality",
    "wof:population":21
},
  "geometry": {"coordinates":[-96.77778000000001,18.69333],"type":"Point"}
}