{
  "type": "Feature",
  "properties": {
    "gn:admin1_code":"30",
    "gn:admin2_code":"4.0",
    "gn:asciiname":"La Luz",
    "gn:country_code":"MX",
    "gn:dem":59,
    "gn:feature_class":"P",
    "gn:feature_code":"PPL",
    "gn:name":"La Luz",
    "gn:population":222,
    "gn:timezone":"America/Mexico_City",
    "iso:country":"MX",
    "wof:name":"La Luz",
    "wof:placetype":"locality",
    "wof:population":222
},
  "geometry": {"coordinates":[-96.46167,19.68528],"type":"Point"}
}