{
  "type": "Feature",
  "properties": {
    "gn:admin1_code":"16",
    "gn:admin2_code":"32.0",
    "gn:asciiname":"La Flor de la Esperanza",
    "gn:country_code":"MX",
    "gn:dem":2051,
    "gn:feature_class":"P",
    "gn:feature_code":"PPL",
    "gn:name":"La Flor de la Esperanza",
    "gn:population":106,
    "gn:timezone":"America/Mexico_City",
    "iso:country":"MX",
    "wof:name":"La Flor de la Esperanza",
    "wof:placetype":"locality",
    "wof:population":106
},
  "geometry": {"coordinates":[-101.71278,19.59528],"type":"Point"}
}