{
  "type": "Feature",
  "properties": {
    "gn:admin1_code":"30",
    "gn:admin2_code":"32",
    "gn:asciiname":"Ejido Amayaga",
    "gn:country_code":"MX",
    "gn:dem":390,
    "gn:feature_class":"P",
    "gn:feature_code":"PPL",
    "gn:name":"Ejido Amayaga",
    "gn:population":35,
    "gn:timezone":"America/Mexico_City",
    "iso:country":"MX",
    "wof:name":"Ejido Amayaga",
    "wof:placetype":"locality",
    "wof:population":35
},
  "geometry": {"coordinates":[-95.03972,18.43667],"type":"Point"}
}