{
  "type": "Feature",
  "properties": {
    "gn:admin1_code":"30.0",
    "gn:admin2_code":"160.0",
    "gn:asciiname":"Los Cuates",
    "gn:country_code":"MX",
    "gn:dem":76,
    "gn:feature_class":"P",
    "gn:feature_code":"PPL",
    "gn:name":"Los Cuates",
    "gn:population":4,
    "gn:timezone":"America/Mexico_City",
    "iso:country":"MX",
    "name:spa_x_preferred":[
        "Los Cuates"
    ],
    "wof:name":"Los Cuates",
    "wof:placetype":"locality",
    "wof:population":4
},
  "geometry": {"coordinates":[-97.73721999999999,21.03333],"type":"Point"}
}