{
  "type": "Feature",
  "properties": {
    "gn:admin1_code":"26.0",
    "gn:admin2_code":"44.0",
    "gn:asciiname":"La Pila",
    "gn:country_code":"MX",
    "gn:dem":162,
    "gn:feature_class":"P",
    "gn:feature_code":"PPL",
    "gn:name":"La Pila",
    "gn:population":0,
    "gn:timezone":"America/Hermosillo",
    "iso:country":"MX",
    "name:spa_x_preferred":[
        "La Pila"
    ],
    "wof:name":"La Pila",
    "wof:placetype":"locality"
},
  "geometry": {"coordinates":[-109.53084,28.46986],"type":"Point"}
}