{
  "type": "Feature",
  "properties": {
    "gn:admin1_code":"25",
    "gn:admin2_code":"3",
    "gn:asciiname":"Alisitos",
    "gn:country_code":"MX",
    "gn:dem":1526,
    "gn:feature_class":"P",
    "gn:feature_code":"PPL",
    "gn:name":"Alisitos",
    "gn:population":14,
    "gn:timezone":"America/Chihuahua",
    "iso:country":"MX",
    "wof:name":"Alisitos",
    "wof:placetype":"locality",
    "wof:population":14
},
  "geometry": {"coordinates":[-107.29397,25.94824],"type":"Point"}
}