{
  "type": "Feature",
  "properties": {
    "gn:admin1_code":"31",
    "gn:admin2_code":"52.0",
    "gn:asciiname":"San Pedro Chacabal",
    "gn:country_code":"MX",
    "gn:dem":14,
    "gn:feature_class":"P",
    "gn:feature_code":"PPL",
    "gn:name":"San Pedro Chacabal",
    "gn:population":0,
    "gn:timezone":"America/Merida",
    "iso:country":"MX",
    "name:und_x_variant":[
        "Chacabal",
        "San Pedro Chakabal"
    ],
    "wof:name":"San Pedro Chacabal",
    "wof:placetype":"locality"
},
  "geometry": {"coordinates":[-89.19308000000002,21.13491],"type":"Point"}
}