{
  "type": "Feature",
  "properties": {
    "gn:admin1_code":"12",
    "gn:admin2_code":"29",
    "gn:asciiname":"Tecolotlicha",
    "gn:country_code":"MX",
    "gn:dem":1241,
    "gn:feature_class":"P",
    "gn:feature_code":"PPL",
    "gn:name":"Tecolotlicha",
    "gn:population":16,
    "gn:timezone":"America/Mexico_City",
    "iso:country":"MX",
    "wof:name":"Tecolotlicha",
    "wof:placetype":"locality",
    "wof:population":16
},
  "geometry": {"coordinates":[-99.47666,17.4879],"type":"Point"}
}