{
  "type": "Feature",
  "properties": {
    "gn:admin1_code":"14",
    "gn:admin2_code":"57",
    "gn:asciiname":"El Aguacate (La Sabanilla)",
    "gn:country_code":"MX",
    "gn:dem":1956,
    "gn:feature_class":"P",
    "gn:feature_code":"PPL",
    "gn:name":"El Aguacate (La Sabanilla)",
    "gn:population":46,
    "gn:timezone":"America/Mexico_City",
    "iso:country":"MX",
    "wof:name":"El Aguacate (La Sabanilla)",
    "wof:placetype":"locality",
    "wof:population":46
},
  "geometry": {"coordinates":[-103.06083,20.04694],"type":"Point"}
}