{
  "type": "Feature",
  "properties": {
    "gn:admin1_code":"20",
    "gn:admin2_code":"95.0",
    "gn:asciiname":"Cerro Santiago",
    "gn:country_code":"MX",
    "gn:dem":2421,
    "gn:feature_class":"P",
    "gn:feature_code":"PPL",
    "gn:name":"Cerro Santiago",
    "gn:population":184,
    "gn:timezone":"America/Mexico_City",
    "iso:country":"MX",
    "name:fas_x_preferred":[
        "\u0633\u0631\u0648 \u0633\u0627\u0646\u062a\u06cc\u0627\u06af\u0648"
    ],
    "name:fra_x_preferred":[
        "Cerro Santiago"
    ],
    "name:nld_x_preferred":[
        "Cerro Santiago"
    ],
    "name:slk_x_preferred":[
        "Cerro Santiago"
    ],
    "wof:name":"Cerro Santiago",
    "wof:placetype":"locality",
    "wof:population":184
},
  "geometry": {"coordinates":[-96.57666999999999,16.19167],"type":"Point"}
}