{
  "type": "Feature",
  "properties": {
    "gn:admin1_code":"5",
    "gn:admin2_code":"65",
    "gn:asciiname":"El Recuerdo",
    "gn:country_code":"MX",
    "gn:dem":61,
    "gn:feature_class":"P",
    "gn:feature_code":"PPL",
    "gn:name":"El Recuerdo",
    "gn:population":34,
    "gn:timezone":"America/Mexico_City",
    "iso:country":"MX",
    "wof:name":"El Recuerdo",
    "wof:placetype":"locality",
    "wof:population":34
},
  "geometry": {"coordinates":[-91.93722,17.62167],"type":"Point"}
}