{
  "type": "Feature",
  "properties": {
    "gn:admin1_code":"26.0",
    "gn:admin2_code":"17.0",
    "gn:asciiname":"Agricola San Fernando",
    "gn:country_code":"MX",
    "gn:dem":268,
    "gn:feature_class":"P",
    "gn:feature_code":"PPL",
    "gn:name":"Agr\u00edcola San Fernando",
    "gn:population":0,
    "gn:timezone":"America/Hermosillo",
    "iso:country":"MX",
    "name:spa_x_preferred":[
        "Agr\u00edcola San Fernando"
    ],
    "wof:name":"Agricola San Fernando",
    "wof:placetype":"locality"
},
  "geometry": {"coordinates":[-112.17465,30.64478],"type":"Point"}
}