{
  "type": "Feature",
  "properties": {
    "gn:admin1_code":"14.0",
    "gn:admin2_code":"33.0",
    "gn:asciiname":"San Hipolito",
    "gn:country_code":"MX",
    "gn:dem":1856,
    "gn:feature_class":"P",
    "gn:feature_code":"PPL",
    "gn:name":"San Hip\u00f3lito",
    "gn:population":0,
    "gn:timezone":"America/Mexico_City",
    "iso:country":"MX",
    "name:und_x_variant":[
        "Altamira",
        "San Hip\u00f3lito"
    ],
    "wof:name":"San Hipolito",
    "wof:placetype":"locality"
},
  "geometry": {"coordinates":[-102.08468999999999,20.48091],"type":"Point"}
}