{
  "type": "Feature",
  "properties": {
    "gn:admin1_code":"16",
    "gn:admin2_code":"87.0",
    "gn:asciiname":"Mesa de Cazarez",
    "gn:country_code":"MX",
    "gn:dem":1559,
    "gn:feature_class":"P",
    "gn:feature_code":"PPL",
    "gn:name":"Mesa de C\u00e1zarez",
    "gn:population":456,
    "gn:timezone":"America/Mexico_City",
    "iso:country":"MX",
    "name:und_x_variant":[
        "Mesa de C\u00e1zarez"
    ],
    "wof:name":"Mesa de Cazarez",
    "wof:placetype":"locality",
    "wof:population":456
},
  "geometry": {"coordinates":[-101.85389000000001,19.3775],"type":"Point"}
}