{
  "type": "Feature",
  "properties": {
    "gn:admin1_code":"30",
    "gn:admin2_code":"72.0",
    "gn:asciiname":"Dejiguei",
    "gn:country_code":"MX",
    "gn:dem":1804,
    "gn:feature_class":"P",
    "gn:feature_code":"PPL",
    "gn:name":"Dejig\u00fc\u00ed",
    "gn:population":5,
    "gn:timezone":"America/Mexico_City",
    "iso:country":"MX",
    "wof:name":"Dejiguei",
    "wof:placetype":"locality",
    "wof:population":5
},
  "geometry": {"coordinates":[-98.45083,20.54249],"type":"Point"}
}