{
  "type": "Feature",
  "properties": {
    "gn:admin1_code":"27",
    "gn:admin2_code":"7.0",
    "gn:asciiname":"Montebello",
    "gn:country_code":"MX",
    "gn:dem":58,
    "gn:feature_class":"P",
    "gn:feature_code":"PPL",
    "gn:name":"Montebello",
    "gn:population":7,
    "gn:timezone":"America/Mexico_City",
    "iso:country":"MX",
    "wof:name":"Montebello",
    "wof:placetype":"locality",
    "wof:population":7
},
  "geometry": {"coordinates":[-91.64194000000001,17.70944],"type":"Point"}
}