{
  "type": "Feature",
  "properties": {
    "gn:admin1_code":"6",
    "gn:admin2_code":"32.0",
    "gn:asciiname":"La Pila",
    "gn:country_code":"MX",
    "gn:dem":1670,
    "gn:feature_class":"P",
    "gn:feature_code":"PPL",
    "gn:name":"La Pila",
    "gn:population":0,
    "gn:timezone":"America/Chihuahua",
    "iso:country":"MX",
    "name:ceb_x_preferred":[
        "La Pila"
    ],
    "name:ita_x_preferred":[
        "La Pila"
    ],
    "name:spa_x_preferred":[
        "La Pila"
    ],
    "name:srp_x_preferred":[
        "\u041b\u0430 \u041f\u0438\u043b\u0430"
    ],
    "wof:name":"La Pila",
    "wof:placetype":"locality"
},
  "geometry": {"coordinates":[-105.74209999999999,27.21161],"type":"Point"}
}