{
  "type": "Feature",
  "properties": {
    "gn:admin1_code":"31.0",
    "gn:asciiname":"San Ignacio",
    "gn:country_code":"MX",
    "gn:dem":27,
    "gn:feature_class":"P",
    "gn:feature_code":"PPL",
    "gn:name":"San Ignacio",
    "gn:population":0,
    "gn:timezone":"America/Merida",
    "iso:country":"MX",
    "name:spa_x_preferred":[
        "San Ignacio"
    ],
    "wof:name":"San Ignacio",
    "wof:placetype":"locality"
},
  "geometry": {"coordinates":[-88.21261,21.09207],"type":"Point"}
}