{
  "type": "Feature",
  "properties": {
    "gn:admin1_code":"11",
    "gn:admin2_code":"37.0",
    "gn:asciiname":"Granja Ana Teresa (Noria de Chencho)",
    "gn:country_code":"MX",
    "gn:dem":1745,
    "gn:feature_class":"P",
    "gn:feature_code":"PPL",
    "gn:name":"Granja Ana Teresa (Noria de Chencho)",
    "gn:population":5,
    "gn:timezone":"America/Mexico_City",
    "iso:country":"MX",
    "wof:name":"Granja Ana Teresa (Noria de Chencho)",
    "wof:placetype":"locality",
    "wof:population":5
},
  "geometry": {"coordinates":[-101.4825,20.85722],"type":"Point"}
}