{
  "type": "Feature",
  "properties": {
    "gn:admin1_code":"26.0",
    "gn:admin2_code":"66.0",
    "gn:asciiname":"El Bamuri",
    "gn:country_code":"MX",
    "gn:dem":406,
    "gn:feature_class":"P",
    "gn:feature_code":"PPL",
    "gn:name":"El Bamuri",
    "gn:population":0,
    "gn:timezone":"America/Hermosillo",
    "iso:country":"MX",
    "name:spa_x_preferred":[
        "El Bamuri"
    ],
    "wof:name":"El Bamuri",
    "wof:placetype":"locality"
},
  "geometry": {"coordinates":[-110.41005,29.36305],"type":"Point"}
}