{
  "type": "Feature",
  "properties": {
    "gn:admin1_code":"31",
    "gn:admin2_code":"102.0",
    "gn:asciiname":"Champo",
    "gn:country_code":"MX",
    "gn:dem":30,
    "gn:feature_class":"P",
    "gn:feature_code":"PPL",
    "gn:name":"Champ\u00f3",
    "gn:population":0,
    "gn:timezone":"America/Merida",
    "iso:country":"MX",
    "name:spa_x_preferred":[
        "Champ\u00f3"
    ],
    "wof:name":"Champo",
    "wof:placetype":"locality"
},
  "geometry": {"coordinates":[-88.04623000000002,20.49199],"type":"Point"}
}