{
  "type": "Feature",
  "properties": {
    "gn:admin1_code":"20",
    "gn:admin2_code":"12.0",
    "gn:asciiname":"San Agustin",
    "gn:country_code":"MX",
    "gn:dem":288,
    "gn:feature_class":"P",
    "gn:feature_code":"PPL",
    "gn:name":"San Agust\u00edn",
    "gn:population":0,
    "gn:timezone":"America/Mexico_City",
    "iso:country":"MX",
    "name:spa_x_preferred":[
        "San Agust\u00edn"
    ],
    "name:und_x_variant":[
        "R\u00edo Culebra"
    ],
    "wof:name":"San Agustin",
    "wof:placetype":"locality"
},
  "geometry": {"coordinates":[-96.5048,15.83271],"type":"Point"}
}