{
  "type": "Feature",
  "properties": {
    "gn:admin1_code":"26",
    "gn:admin2_code":"42.0",
    "gn:asciiname":"Huerta Aguilera",
    "gn:country_code":"MX",
    "gn:dem":37,
    "gn:feature_class":"P",
    "gn:feature_code":"PPL",
    "gn:name":"Huerta Aguilera",
    "gn:population":8,
    "gn:timezone":"America/Hermosillo",
    "iso:country":"MX",
    "wof:name":"Huerta Aguilera",
    "wof:placetype":"locality",
    "wof:population":8
},
  "geometry": {"coordinates":[-109.45166999999999,27.10778],"type":"Point"}
}