{
  "type": "Feature",
  "properties": {
    "gn:admin1_code":"14",
    "gn:admin2_code":"118",
    "gn:asciiname":"Los Guayabitos (Los Cerritos)",
    "gn:country_code":"MX",
    "gn:dem":1830,
    "gn:feature_class":"P",
    "gn:feature_code":"PPL",
    "gn:name":"Los Guayabitos (Los Cerritos)",
    "gn:population":18,
    "gn:timezone":"America/Mexico_City",
    "iso:country":"MX",
    "wof:name":"Los Guayabitos (Los Cerritos)",
    "wof:placetype":"locality",
    "wof:population":18
},
  "geometry": {"coordinates":[-102.88500000000001,21.16778],"type":"Point"}
}