{
  "type": "Feature",
  "properties": {
    "gn:admin1_code":"13",
    "gn:admin2_code":"62.0",
    "gn:asciiname":"Acoxcatlan",
    "gn:country_code":"MX",
    "gn:dem":1137,
    "gn:feature_class":"P",
    "gn:feature_code":"PPL",
    "gn:name":"Acoxcatl\u00e1n",
    "gn:population":0,
    "gn:timezone":"America/Mexico_City",
    "iso:country":"MX",
    "name:spa_x_preferred":[
        "Acoxcatl\u00e1n"
    ],
    "wof:name":"Acoxcatlan",
    "wof:placetype":"locality"
},
  "geometry": {"coordinates":[-98.77793,20.97343],"type":"Point"}
}