{
  "type": "Feature",
  "properties": {
    "gn:admin1_code":"16",
    "gn:admin2_code":"10",
    "gn:asciiname":"Coacuyulito",
    "gn:country_code":"MX",
    "gn:dem":654,
    "gn:feature_class":"P",
    "gn:feature_code":"PPL",
    "gn:name":"Coacuyulito",
    "gn:population":23,
    "gn:timezone":"America/Mexico_City",
    "iso:country":"MX",
    "wof:name":"Coacuyulito",
    "wof:placetype":"locality",
    "wof:population":23
},
  "geometry": {"coordinates":[-102.16361000000001,18.37389],"type":"Point"}
}