{
  "type": "Feature",
  "properties": {
    "gn:admin1_code":"27.0",
    "gn:asciiname":"Santo Domingo Segunda Seccion",
    "gn:country_code":"MX",
    "gn:dem":19,
    "gn:feature_class":"P",
    "gn:feature_code":"PPL",
    "gn:name":"Santo Domingo Segunda Secci\u00f3n",
    "gn:population":0,
    "gn:timezone":"America/Mexico_City",
    "iso:country":"MX",
    "name:spa_x_preferred":[
        "Santo Domingo Segunda Secci\u00f3n"
    ],
    "wof:name":"Santo Domingo Segunda Seccion",
    "wof:placetype":"locality"
},
  "geometry": {"coordinates":[-92.74164,17.87572999999999],"type":"Point"}
}