{
  "type": "Feature",
  "properties": {
    "gn:admin1_code":"31",
    "gn:admin2_code":"53.0",
    "gn:asciiname":"Xocchel",
    "gn:country_code":"MX",
    "gn:dem":43,
    "gn:feature_class":"P",
    "gn:feature_code":"PPL",
    "gn:name":"Xocchel",
    "gn:population":6,
    "gn:timezone":"America/Merida",
    "iso:country":"MX",
    "wof:name":"Xocchel",
    "wof:placetype":"locality",
    "wof:population":6
},
  "geometry": {"coordinates":[-89.77944000000002,20.40556],"type":"Point"}
}