{
  "type": "Feature",
  "properties": {
    "gn:admin1_code":"16.0",
    "gn:admin2_code":"12.0",
    "gn:asciiname":"Los Mojos",
    "gn:country_code":"MX",
    "gn:dem":231,
    "gn:feature_class":"P",
    "gn:feature_code":"PPL",
    "gn:name":"Los Mojos",
    "gn:population":0,
    "gn:timezone":"America/Mexico_City",
    "iso:country":"MX",
    "name:spa_x_preferred":[
        "Los Mojos"
    ],
    "wof:name":"Los Mojos",
    "wof:placetype":"locality"
},
  "geometry": {"coordinates":[-102.53767999999999,19.01565],"type":"Point"}
}