{
  "type": "Feature",
  "properties": {
    "gn:admin1_code":"20.0",
    "gn:admin2_code":"73.0",
    "gn:asciiname":"San Isidro Palizada",
    "gn:country_code":"MX",
    "gn:dem":739,
    "gn:feature_class":"P",
    "gn:feature_code":"PPL",
    "gn:name":"San Isidro Palizada",
    "gn:population":0,
    "gn:timezone":"America/Mexico_City",
    "iso:country":"MX",
    "name:spa_x_preferred":[
        "San Isidro Palizada"
    ],
    "wof:name":"San Isidro Palizada",
    "wof:placetype":"locality"
},
  "geometry": {"coordinates":[-97.92196,16.99246],"type":"Point"}
}