{
  "type": "Feature",
  "properties": {
    "gn:admin1_code":"14.0",
    "gn:admin2_code":"87.0",
    "gn:asciiname":"Corona",
    "gn:country_code":"MX",
    "gn:dem":1205,
    "gn:feature_class":"P",
    "gn:feature_code":"PPL",
    "gn:name":"Corona",
    "gn:population":0,
    "gn:timezone":"America/Mexico_City",
    "iso:country":"MX",
    "name:spa_x_preferred":[
        "Corona"
    ],
    "wof:name":"Corona",
    "wof:placetype":"locality"
},
  "geometry": {"coordinates":[-103.29085000000001,19.44475],"type":"Point"}
}