{
  "type": "Feature",
  "properties": {
    "gn:admin1_code":"16",
    "gn:admin2_code":"2.0",
    "gn:asciiname":"El Moro",
    "gn:country_code":"MX",
    "gn:dem":929,
    "gn:feature_class":"P",
    "gn:feature_code":"PPL",
    "gn:name":"El Moro",
    "gn:population":7,
    "gn:timezone":"America/Mexico_City",
    "iso:country":"MX",
    "wof:name":"El Moro",
    "wof:placetype":"locality",
    "wof:population":7
},
  "geometry": {"coordinates":[-102.76139000000001,18.71417000000001],"type":"Point"}
}