{
  "type": "Feature",
  "properties": {
    "gn:admin1_code":"28.0",
    "gn:admin2_code":"12.0",
    "gn:asciiname":"Los Colorados",
    "gn:country_code":"MX",
    "gn:dem":62,
    "gn:feature_class":"P",
    "gn:feature_code":"PPL",
    "gn:name":"Los Colorados",
    "gn:population":2,
    "gn:timezone":"America/Monterrey",
    "iso:country":"MX",
    "name:spa_x_preferred":[
        "Los Colorados"
    ],
    "wof:name":"Los Colorados",
    "wof:placetype":"locality",
    "wof:population":2
},
  "geometry": {"coordinates":[-98.32111,22.70333],"type":"Point"}
}