{
  "type": "Feature",
  "properties": {
    "gn:admin1_code":"5",
    "gn:admin2_code":"59.0",
    "gn:asciiname":"Ojo de Agua Cristalina",
    "gn:country_code":"MX",
    "gn:dem":425,
    "gn:feature_class":"P",
    "gn:feature_code":"PPL",
    "gn:name":"Ojo de Agua Cristalina",
    "gn:population":4,
    "gn:timezone":"America/Mexico_City",
    "iso:country":"MX",
    "wof:name":"Ojo de Agua Cristalina",
    "wof:placetype":"locality",
    "wof:population":4
},
  "geometry": {"coordinates":[-91.29167,16.91417],"type":"Point"}
}