{
  "type": "Feature",
  "properties": {
    "gn:admin1_code":"24.0",
    "gn:admin2_code":"28.0",
    "gn:asciiname":"Labor de San Diego",
    "gn:cc2":"MX",
    "gn:country_code":"MX",
    "gn:dem":1845,
    "gn:feature_class":"P",
    "gn:feature_code":"PPL",
    "gn:name":"Labor de San Diego",
    "gn:population":0,
    "gn:timezone":"America/Mexico_City",
    "iso:country":"MX",
    "name:und_x_variant":[
        "Labor",
        "Labor de San Diego"
    ],
    "wof:name":"Labor de San Diego",
    "wof:placetype":"locality"
},
  "geometry": {"coordinates":[-100.93333,22.36667000000001],"type":"Point"}
}