{
  "type": "Feature",
  "properties": {
    "gn:admin1_code":"15",
    "gn:admin2_code":"53.0",
    "gn:asciiname":"Rancho el Banadero",
    "gn:country_code":"MX",
    "gn:dem":2256,
    "gn:feature_class":"P",
    "gn:feature_code":"PPL",
    "gn:name":"Rancho el Ba\u00f1adero",
    "gn:population":8,
    "gn:timezone":"America/Mexico_City",
    "iso:country":"MX",
    "name:und_x_variant":[
        "Rancho el Ba\u00f1adero"
    ],
    "wof:name":"Rancho el Banadero",
    "wof:placetype":"locality",
    "wof:population":8
},
  "geometry": {"coordinates":[-99.15631,19.70018],"type":"Point"}
}