{
  "type": "Feature",
  "properties": {
    "gn:admin1_code":"20",
    "gn:admin2_code":"143.0",
    "gn:asciiname":"Los Nanches",
    "gn:country_code":"MX",
    "gn:dem":11,
    "gn:feature_class":"P",
    "gn:feature_code":"PPL",
    "gn:name":"Los Nanches",
    "gn:population":0,
    "gn:timezone":"America/Mexico_City",
    "iso:country":"MX",
    "wof:name":"Los Nanches",
    "wof:placetype":"locality"
},
  "geometry": {"coordinates":[-94.55,16.38332999999999],"type":"Point"}
}