{
  "type": "Feature",
  "properties": {
    "gn:admin1_code":"26",
    "gn:admin2_code":"43.0",
    "gn:asciiname":"Mascarena",
    "gn:country_code":"MX",
    "gn:dem":1152,
    "gn:feature_class":"P",
    "gn:feature_code":"PPL",
    "gn:name":"Mascare\u00f1a",
    "gn:population":0,
    "gn:timezone":"America/Hermosillo",
    "iso:country":"MX",
    "name:spa_x_preferred":[
        "Mascare\u00f1a"
    ],
    "name:spa_x_variant":[
        "Mascare\u00f1as"
    ],
    "wof:name":"Mascarena",
    "wof:placetype":"locality"
},
  "geometry": {"coordinates":[-110.83693999999998,31.31025],"type":"Point"}
}