{
  "type": "Feature",
  "properties": {
    "gn:admin1_code":"14",
    "gn:admin2_code":"110.0",
    "gn:asciiname":"Santa Fe",
    "gn:country_code":"MX",
    "gn:dem":1321,
    "gn:feature_class":"P",
    "gn:feature_code":"PPL",
    "gn:name":"Santa Fe",
    "gn:population":189,
    "gn:timezone":"America/Mexico_City",
    "iso:country":"MX",
    "name:spa_x_preferred":[
        "Santa Fe"
    ],
    "wof:name":"Santa Fe",
    "wof:placetype":"locality",
    "wof:population":189
},
  "geometry": {"coordinates":[-104.28436000000001,20.00878],"type":"Point"}
}