{
  "type": "Feature",
  "properties": {
    "gn:admin1_code":"11.0",
    "gn:asciiname":"Monte del Sitio",
    "gn:country_code":"MX",
    "gn:dem":1725,
    "gn:feature_class":"P",
    "gn:feature_code":"PPL",
    "gn:name":"Monte del Sitio",
    "gn:population":0,
    "gn:timezone":"America/Mexico_City",
    "iso:country":"MX",
    "name:spa_x_preferred":[
        "Monte del Sitio"
    ],
    "wof:name":"Monte del Sitio",
    "wof:placetype":"locality"
},
  "geometry": {"coordinates":[-101.8998,20.77063],"type":"Point"}
}