{
  "type": "Feature",
  "properties": {
    "gn:admin1_code":"5",
    "gn:admin2_code":"107.0",
    "gn:asciiname":"Palestina",
    "gn:country_code":"MX",
    "gn:dem":684,
    "gn:feature_class":"P",
    "gn:feature_code":"PPL",
    "gn:name":"Palestina",
    "gn:population":5,
    "gn:timezone":"America/Mexico_City",
    "iso:country":"MX",
    "name:bre_x_preferred":[
        "Palestina"
    ],
    "name:cat_x_preferred":[
        "Palestina"
    ],
    "name:ceb_x_preferred":[
        "Palestina"
    ],
    "name:ces_x_preferred":[
        "Palestina"
    ],
    "name:deu_x_preferred":[
        "Palestina"
    ],
    "name:est_x_preferred":[
        "Palestina"
    ],
    "name:fra_x_preferred":[
        "Palestina"
    ],
    "name:heb_x_preferred":[
        "\u05e4\u05dc\u05e9\u05ea\u05d9\u05e0\u05d4"
    ],
    "name:ilo_x_preferred":[
        "Palestina"
    ],
    "name:ind_x_preferred":[
        "Palestina"
    ],
    "name:ita_x_preferred":[
        "Palestina"
    ],
    "name:kat_x_preferred":[
        "\u10de\u10d0\u10da\u10d4\u10e1\u10e2\u10d8\u10dc\u10d0"
    ],
    "name:lav_x_preferred":[
        "Palest\u012bna"
    ],
    "name:lim_x_preferred":[
        "Palestina"
    ],
    "name:lit_x_preferred":[
        "Palestina"
    ],
    "name:ltz_x_preferred":[
        "Palestina"
    ],
    "name:min_x_preferred":[
        "Palestina"
    ],
    "name:nld_x_preferred":[
        "Palestina"
    ],
    "name:nor_x_preferred":[
        "Palestina"
    ],
    "name:oci_x_preferred":[
        "Palestina"
    ],
    "name:pol_x_preferred":[
        "Palestina"
    ],
    "name:por_x_preferred":[
        "Palestina"
    ],
    "name:rus_x_preferred":[
        "\u041f\u0430\u043b\u0435\u0441\u0442\u0438\u043d\u0430"
    ],
    "name:sco_x_preferred":[
        "Palestina"
    ],
    "name:slk_x_preferred":[
        "Palestina"
    ],
    "name:spa_x_preferred":[
        "Palestina"
    ],
    "name:srp_x_preferred":[
        "\u041f\u0430\u043b\u0435\u0441\u0442\u0438\u043d\u0430"
    ],
    "name:sun_x_preferred":[
        "Pal\u00e9stina"
    ],
    "name:swe_x_preferred":[
        "Palestina"
    ],
    "name:ukr_x_preferred":[
        "\u041f\u0430\u043b\u0435\u0441\u0442\u0438\u043d\u0430"
    ],
    "name:vie_x_preferred":[
        "Palestina"
    ],
    "name:vol_x_preferred":[
        "Palestina"
    ],
    "name:war_x_preferred":[
        "Palestina"
    ],
    "name:zho_x_preferred":[
        "\u5e15\u840a\u65af\u8482\u7d0d"
    ],
    "wof:name":"Palestina",
    "wof:placetype":"locality",
    "wof:population":5
},
  "geometry": {"coordinates":[-93.19750000000001,16.05139],"type":"Point"}
}