{
  "type": "Feature",
  "properties": {
    "gn:admin1_code":"10",
    "gn:admin2_code":"23.0",
    "gn:asciiname":"Arroyo de la Puerta",
    "gn:country_code":"MX",
    "gn:dem":1726,
    "gn:feature_class":"P",
    "gn:feature_code":"PPL",
    "gn:name":"Arroyo de la Puerta",
    "gn:population":0,
    "gn:timezone":"America/Monterrey",
    "iso:country":"MX",
    "name:spa_x_preferred":[
        "Arroyo de la Puerta"
    ],
    "wof:name":"Arroyo de la Puerta",
    "wof:placetype":"locality"
},
  "geometry": {"coordinates":[-105.60199,23.83344],"type":"Point"}
}