{
  "type": "Feature",
  "properties": {
    "gn:admin1_code":"6",
    "gn:admin2_code":"27.0",
    "gn:asciiname":"Tobosachi",
    "gn:country_code":"MX",
    "gn:dem":2385,
    "gn:feature_class":"P",
    "gn:feature_code":"PPL",
    "gn:name":"Tobosachi",
    "gn:population":6,
    "gn:timezone":"America/Chihuahua",
    "iso:country":"MX",
    "wof:name":"Tobosachi",
    "wof:placetype":"locality",
    "wof:population":6
},
  "geometry": {"coordinates":[-107.26129,27.0866],"type":"Point"}
}