{
  "type": "Feature",
  "properties": {
    "gn:admin1_code":"5",
    "gn:admin2_code":"46.0",
    "gn:asciiname":"La Asuncion",
    "gn:country_code":"MX",
    "gn:dem":573,
    "gn:feature_class":"P",
    "gn:feature_code":"PPL",
    "gn:name":"La Asunci\u00f3n",
    "gn:population":0,
    "gn:timezone":"America/Mexico_City",
    "iso:country":"MX",
    "wof:name":"La Asuncion",
    "wof:placetype":"locality"
},
  "geometry": {"coordinates":[-93.68333,16.48333],"type":"Point"}
}