{
  "type": "Feature",
  "properties": {
    "gn:admin1_code":"16.0",
    "gn:admin2_code":"92.0",
    "gn:asciiname":"Huahuasco",
    "gn:country_code":"MX",
    "gn:dem":439,
    "gn:feature_class":"P",
    "gn:feature_code":"PPL",
    "gn:name":"Huahuasco",
    "gn:population":0,
    "gn:timezone":"America/Mexico_City",
    "iso:country":"MX",
    "name:spa_x_preferred":[
        "Huahuasco"
    ],
    "wof:name":"Huahuasco",
    "wof:placetype":"locality"
},
  "geometry": {"coordinates":[-100.59295,18.91709],"type":"Point"}
}