{
  "type": "Feature",
  "properties": {
    "gn:admin1_code":"19.0",
    "gn:admin2_code":"13.0",
    "gn:asciiname":"Dos Arbolitos",
    "gn:country_code":"MX",
    "gn:dem":145,
    "gn:feature_class":"P",
    "gn:feature_code":"PPL",
    "gn:name":"Dos Arbolitos",
    "gn:population":0,
    "gn:timezone":"America/Monterrey",
    "iso:country":"MX",
    "name:spa_x_preferred":[
        "Dos Arbolitos"
    ],
    "wof:name":"Dos Arbolitos",
    "wof:placetype":"locality"
},
  "geometry": {"coordinates":[-99.21194,25.73442],"type":"Point"}
}