{
  "type": "Feature",
  "properties": {
    "gn:admin1_code":"5",
    "gn:admin2_code":"65.0",
    "gn:asciiname":"El Manguito",
    "gn:country_code":"MX",
    "gn:dem":30,
    "gn:feature_class":"P",
    "gn:feature_code":"PPL",
    "gn:name":"El Manguito",
    "gn:population":6,
    "gn:timezone":"America/Mexico_City",
    "iso:country":"MX",
    "wof:name":"El Manguito",
    "wof:placetype":"locality",
    "wof:population":6
},
  "geometry": {"coordinates":[-92.26528,17.68611],"type":"Point"}
}