{
  "type": "Feature",
  "properties": {
    "gn:admin1_code":"11.0",
    "gn:admin2_code":"42.0",
    "gn:asciiname":"Chicamito",
    "gn:country_code":"MX",
    "gn:dem":2070,
    "gn:feature_class":"P",
    "gn:feature_code":"PPL",
    "gn:name":"Chicamito",
    "gn:population":226,
    "gn:timezone":"America/Mexico_City",
    "iso:country":"MX",
    "name:spa_x_preferred":[
        "Chicamito"
    ],
    "wof:name":"Chicamito",
    "wof:placetype":"locality",
    "wof:population":226
},
  "geometry": {"coordinates":[-101.21407000000001,20.31722],"type":"Point"}
}