{
  "type": "Feature",
  "properties": {
    "gn:admin1_code":"5",
    "gn:admin2_code":"117.0",
    "gn:asciiname":"Puerto Rico",
    "gn:country_code":"MX",
    "gn:dem":1240,
    "gn:feature_class":"P",
    "gn:feature_code":"PPL",
    "gn:name":"Puerto Rico",
    "gn:population":322,
    "gn:timezone":"America/Mexico_City",
    "iso:country":"MX",
    "name:spa_x_preferred":[
        "Puerto Rico"
    ],
    "wof:name":"Puerto Rico",
    "wof:placetype":"locality",
    "wof:population":322
},
  "geometry": {"coordinates":[-92.71213,15.66469],"type":"Point"}
}