{
  "type": "Feature",
  "properties": {
    "gn:admin1_code":"14.0",
    "gn:asciiname":"La Cumbrita",
    "gn:country_code":"MX",
    "gn:dem":1243,
    "gn:feature_class":"P",
    "gn:feature_code":"PPL",
    "gn:name":"La Cumbrita",
    "gn:population":0,
    "gn:timezone":"America/Mexico_City",
    "iso:country":"MX",
    "name:spa_x_preferred":[
        "La Cumbrita"
    ],
    "wof:name":"La Cumbrita",
    "wof:placetype":"locality"
},
  "geometry": {"coordinates":[-103.84063999999999,21.47688],"type":"Point"}
}