{
  "type": "Feature",
  "properties": {
    "gn:admin1_code":"11.0",
    "gn:asciiname":"Los Barriles",
    "gn:country_code":"MX",
    "gn:dem":2096,
    "gn:feature_class":"P",
    "gn:feature_code":"PPL",
    "gn:name":"Los Barriles",
    "gn:population":0,
    "gn:timezone":"America/Mexico_City",
    "iso:country":"MX",
    "name:spa_x_preferred":[
        "Los Barriles"
    ],
    "wof:name":"Los Barriles",
    "wof:placetype":"locality"
},
  "geometry": {"coordinates":[-100.51564999999999,20.28543],"type":"Point"}
}