{
  "type": "Feature",
  "properties": {
    "gn:admin1_code":"13",
    "gn:asciiname":"La Encantada",
    "gn:country_code":"MX",
    "gn:dem":77,
    "gn:feature_class":"P",
    "gn:feature_code":"PPL",
    "gn:name":"La Encantada",
    "gn:population":0,
    "gn:timezone":"America/Mexico_City",
    "iso:country":"MX",
    "name:spa_x_preferred":[
        "La Encantada"
    ],
    "wof:name":"La Encantada",
    "wof:placetype":"locality"
},
  "geometry": {"coordinates":[-98.51217,21.3865],"type":"Point"}
}