{
  "type": "Feature",
  "properties": {
    "gn:admin1_code":"19.0",
    "gn:admin2_code":"49.0",
    "gn:asciiname":"El Trece",
    "gn:country_code":"MX",
    "gn:dem":385,
    "gn:feature_class":"P",
    "gn:feature_code":"PPL",
    "gn:name":"El Trece",
    "gn:population":0,
    "gn:timezone":"America/Monterrey",
    "iso:country":"MX",
    "name:spa_x_preferred":[
        "El Trece"
    ],
    "wof:name":"El Trece",
    "wof:placetype":"locality"
},
  "geometry": {"coordinates":[-100.05656999999999,25.46096],"type":"Point"}
}