{
  "type": "Feature",
  "properties": {
    "gn:admin1_code":"16",
    "gn:admin2_code":"101",
    "gn:asciiname":"La Calavera",
    "gn:country_code":"MX",
    "gn:dem":1253,
    "gn:feature_class":"P",
    "gn:feature_code":"PPL",
    "gn:name":"La Calavera",
    "gn:population":20,
    "gn:timezone":"America/Mexico_City",
    "iso:country":"MX",
    "wof:name":"La Calavera",
    "wof:placetype":"locality",
    "wof:population":20
},
  "geometry": {"coordinates":[-100.90917,19.53056],"type":"Point"}
}