{
  "type": "Feature",
  "properties": {
    "gn:admin1_code":"20",
    "gn:admin2_code":"28.0",
    "gn:asciiname":"San Juan Coatecas Bajas",
    "gn:country_code":"MX",
    "gn:dem":1482,
    "gn:feature_class":"P",
    "gn:feature_code":"PPL",
    "gn:name":"San Juan Coatecas Bajas",
    "gn:population":0,
    "gn:timezone":"America/Mexico_City",
    "iso:country":"MX",
    "name:und_x_variant":[
        "Coatecas",
        "San Juan Coatecas Bajas",
        "Coatequitas"
    ],
    "wof:name":"San Juan Coatecas Bajas",
    "wof:placetype":"locality"
},
  "geometry": {"coordinates":[-96.71052,16.5483],"type":"Point"}
}