{
  "type": "Feature",
  "properties": {
    "gn:admin1_code":"16",
    "gn:admin2_code":"61",
    "gn:asciiname":"Hernandez (El Paso)",
    "gn:country_code":"MX",
    "gn:dem":2278,
    "gn:feature_class":"P",
    "gn:feature_code":"PPL",
    "gn:name":"Hern\u00e1ndez (El Paso)",
    "gn:population":29,
    "gn:timezone":"America/Mexico_City",
    "iso:country":"MX",
    "name:und_x_variant":[
        "Hern\u00e1ndez (El Paso)"
    ],
    "wof:name":"Hernandez (El Paso)",
    "wof:placetype":"locality",
    "wof:population":29
},
  "geometry": {"coordinates":[-100.35693999999999,19.56139],"type":"Point"}
}