{
  "type": "Feature",
  "properties": {
    "gn:admin1_code":"32",
    "gn:admin2_code":"42.0",
    "gn:asciiname":"Milpillas",
    "gn:country_code":"MX",
    "gn:dem":2113,
    "gn:feature_class":"P",
    "gn:feature_code":"PPL",
    "gn:name":"Milpillas",
    "gn:population":91,
    "gn:timezone":"America/Mexico_City",
    "iso:country":"MX",
    "wof:name":"Milpillas",
    "wof:placetype":"locality",
    "wof:population":91
},
  "geometry": {"coordinates":[-103.80361000000001,23.96222],"type":"Point"}
}