{
  "type": "Feature",
  "properties": {
    "gn:admin1_code":"31",
    "gn:admin2_code":"96.0",
    "gn:asciiname":"X-Uenkal [Rancho]",
    "gn:country_code":"MX",
    "gn:dem":22,
    "gn:feature_class":"P",
    "gn:feature_code":"PPL",
    "gn:name":"X-Uenkal [Rancho]",
    "gn:population":8,
    "gn:timezone":"America/Merida",
    "iso:country":"MX",
    "wof:name":"X-Uenkal [Rancho]",
    "wof:placetype":"locality",
    "wof:population":8
},
  "geometry": {"coordinates":[-88.18444000000002,21.12556],"type":"Point"}
}