{
  "type": "Feature",
  "properties": {
    "gn:admin1_code":"3.0",
    "gn:admin2_code":"2.0",
    "gn:asciiname":"Paredones",
    "gn:country_code":"MX",
    "gn:dem":128,
    "gn:feature_class":"P",
    "gn:feature_code":"PPL",
    "gn:name":"Paredones",
    "gn:population":0,
    "gn:timezone":"America/Mazatlan",
    "iso:country":"MX",
    "name:spa_x_preferred":[
        "Paredones"
    ],
    "wof:name":"Paredones",
    "wof:placetype":"locality"
},
  "geometry": {"coordinates":[-112.90817,27.29807000000001],"type":"Point"}
}