{
  "type": "Feature",
  "properties": {
    "gn:admin1_code":"26",
    "gn:admin2_code":"45.0",
    "gn:asciiname":"Santa Margarita",
    "gn:country_code":"MX",
    "gn:dem":699,
    "gn:feature_class":"P",
    "gn:feature_code":"PPL",
    "gn:name":"Santa Margarita",
    "gn:population":0,
    "gn:timezone":"America/Hermosillo",
    "iso:country":"MX",
    "name:spa_x_preferred":[
        "Santa Margarita"
    ],
    "name:spa_x_variant":[
        "La Trampa"
    ],
    "wof:name":"Santa Margarita",
    "wof:placetype":"locality"
},
  "geometry": {"coordinates":[-110.66565,30.01963],"type":"Point"}
}