{
  "type": "Feature",
  "properties": {
    "gn:admin1_code":"26",
    "gn:admin2_code":"45.0",
    "gn:asciiname":"Santa Margarita",
    "gn:country_code":"MX",
    "gn:dem":699,
    "gn:feature_class":"P",
    "gn:feature_code":"PPL",
    "gn:name":"Santa Margarita",
    "gn:population":0,
    "gn:timezone":"America/Hermosillo",
    "iso:country":"MX",
    "name:bre_x_preferred":[
        "Santa Margarita"
    ],
    "name:ceb_x_preferred":[
        "Santa Margarita"
    ],
    "name:deu_x_preferred":[
        "Santa Margarita"
    ],
    "name:fin_x_preferred":[
        "Santa Margarita"
    ],
    "name:fra_x_preferred":[
        "Santa Margarita"
    ],
    "name:ita_x_preferred":[
        "Santa Margarita"
    ],
    "name:por_x_preferred":[
        "Santa Margarita"
    ],
    "name:scn_x_preferred":[
        "Santa Margarita"
    ],
    "name:spa_x_preferred":[
        "Santa Margarita"
    ],
    "name:spa_x_variant":[
        "La Trampa"
    ],
    "name:srp_x_preferred":[
        "\u0421\u0430\u043d\u0442\u0430 \u041c\u0430\u0440\u0433\u0430\u0440\u0438\u0442\u0430"
    ],
    "name:swe_x_preferred":[
        "Santa Margarita"
    ],
    "name:war_x_preferred":[
        "Santa Margarita"
    ],
    "wof:name":"Santa Margarita",
    "wof:placetype":"locality"
},
  "geometry": {"coordinates":[-110.66565,30.01963],"type":"Point"}
}