{
  "type": "Feature",
  "properties": {
    "gn:admin1_code":"5",
    "gn:admin2_code":"61.0",
    "gn:asciiname":"Quinta Lupita",
    "gn:country_code":"MX",
    "gn:dem":1073,
    "gn:feature_class":"P",
    "gn:feature_code":"PPL",
    "gn:name":"Quinta Lupita",
    "gn:population":7,
    "gn:timezone":"America/Mexico_City",
    "iso:country":"MX",
    "wof:name":"Quinta Lupita",
    "wof:placetype":"locality",
    "wof:population":7
},
  "geometry": {"coordinates":[-93.33167,16.74694],"type":"Point"}
}