{
  "type": "Feature",
  "properties": {
    "gn:admin1_code":"30.0",
    "gn:admin2_code":"155.0",
    "gn:asciiname":"El Calvario",
    "gn:country_code":"MX",
    "gn:dem":93,
    "gn:feature_class":"P",
    "gn:feature_code":"PPL",
    "gn:name":"El Calvario",
    "gn:population":3,
    "gn:timezone":"America/Mexico_City",
    "iso:country":"MX",
    "name:spa_x_preferred":[
        "El Calvario"
    ],
    "wof:name":"El Calvario",
    "wof:placetype":"locality",
    "wof:population":3
},
  "geometry": {"coordinates":[-98.12639,21.50833],"type":"Point"}
}