{
  "type": "Feature",
  "properties": {
    "gn:admin1_code":"30.0",
    "gn:admin2_code":"155.0",
    "gn:asciiname":"El Calvario",
    "gn:country_code":"MX",
    "gn:dem":93,
    "gn:feature_class":"P",
    "gn:feature_code":"PPL",
    "gn:name":"El Calvario",
    "gn:population":3,
    "gn:timezone":"America/Mexico_City",
    "iso:country":"MX",
    "name:ceb_x_preferred":[
        "El Calvario"
    ],
    "name:fra_x_preferred":[
        "El Calvario"
    ],
    "name:ita_x_preferred":[
        "El Calvario"
    ],
    "name:kat_x_preferred":[
        "\u10d4\u10da-\u10d9\u10d0\u10da\u10d5\u10d0\u10e0\u10d8\u10dd"
    ],
    "name:msa_x_preferred":[
        "El Calvario"
    ],
    "name:nld_x_preferred":[
        "El Calvario"
    ],
    "name:por_x_preferred":[
        "El Calvario"
    ],
    "name:spa_x_preferred":[
        "El Calvario"
    ],
    "name:swe_x_preferred":[
        "El Calvario"
    ],
    "name:tgl_x_preferred":[
        "El Calvario"
    ],
    "name:vie_x_preferred":[
        "El Calvario"
    ],
    "name:war_x_preferred":[
        "El Calvario"
    ],
    "name:zho_x_preferred":[
        "\u57c3\u723e\u5361\u723e\u74e6\u91cc\u5967"
    ],
    "wof:name":"El Calvario",
    "wof:placetype":"locality",
    "wof:population":3
},
  "geometry": {"coordinates":[-98.12639,21.50833],"type":"Point"}
}