{
  "type": "Feature",
  "properties": {
    "gn:admin1_code":"7",
    "gn:admin2_code":"27.0",
    "gn:asciiname":"San Jose de Monteverde",
    "gn:country_code":"MX",
    "gn:dem":996,
    "gn:feature_class":"P",
    "gn:feature_code":"PPL",
    "gn:name":"San Jos\u00e9 de Monteverde",
    "gn:population":0,
    "gn:timezone":"America/Monterrey",
    "iso:country":"MX",
    "name:spa_x_preferred":[
        "San Jos\u00e9 de Monteverde"
    ],
    "wof:name":"San Jose de Monteverde",
    "wof:placetype":"locality"
},
  "geometry": {"coordinates":[-101.11799999999999,25.76829],"type":"Point"}
}