{
  "type": "Feature",
  "properties": {
    "gn:admin1_code":"28",
    "gn:admin2_code":"6.0",
    "gn:asciiname":"Magdaleno Aguilar",
    "gn:country_code":"MX",
    "gn:dem":1585,
    "gn:feature_class":"P",
    "gn:feature_code":"PPL",
    "gn:name":"Magdaleno Agu\u00edlar",
    "gn:population":0,
    "gn:timezone":"America/Monterrey",
    "iso:country":"MX",
    "name:spa_x_preferred":[
        "Magdaleno Agu\u00edlar"
    ],
    "name:und_x_variant":[
        "San Vicente"
    ],
    "wof:name":"Magdaleno Aguilar",
    "wof:placetype":"locality"
},
  "geometry": {"coordinates":[-99.87004,23.28114],"type":"Point"}
}