{
  "type": "Feature",
  "properties": {
    "gn:admin1_code":"6",
    "gn:admin2_code":"7",
    "gn:asciiname":"La Hierbabuena",
    "gn:country_code":"MX",
    "gn:dem":2769,
    "gn:feature_class":"P",
    "gn:feature_code":"PPL",
    "gn:name":"La Hierbabuena",
    "gn:population":38,
    "gn:timezone":"America/Chihuahua",
    "iso:country":"MX",
    "wof:name":"La Hierbabuena",
    "wof:placetype":"locality",
    "wof:population":38
},
  "geometry": {"coordinates":[-106.69123,26.48599],"type":"Point"}
}