{
  "type": "Feature",
  "properties": {
    "gn:admin1_code":"6.0",
    "gn:admin2_code":"17.0",
    "gn:asciiname":"Chorachic",
    "gn:country_code":"MX",
    "gn:dem":2132,
    "gn:feature_class":"P",
    "gn:feature_code":"PPL",
    "gn:name":"Chor\u00e1chic",
    "gn:population":0,
    "gn:timezone":"America/Chihuahua",
    "iso:country":"MX",
    "wof:name":"Chorachic",
    "wof:placetype":"locality"
},
  "geometry": {"coordinates":[-106.93333,28.35],"type":"Point"}
}