{
  "type": "Feature",
  "properties": {
    "gn:admin1_code":"6.0",
    "gn:asciiname":"El Olvido",
    "gn:country_code":"MX",
    "gn:dem":1581,
    "gn:feature_class":"P",
    "gn:feature_code":"PPL",
    "gn:name":"El Olvido",
    "gn:population":0,
    "gn:timezone":"America/Chihuahua",
    "iso:country":"MX",
    "name:spa_x_preferred":[
        "El Olvido"
    ],
    "wof:name":"El Olvido",
    "wof:placetype":"locality"
},
  "geometry": {"coordinates":[-106.29951,29.0227],"type":"Point"}
}