{
  "type": "Feature",
  "properties": {
    "gn:admin1_code":"6",
    "gn:admin2_code":"29",
    "gn:asciiname":"El Terrerito",
    "gn:country_code":"MX",
    "gn:dem":999,
    "gn:feature_class":"P",
    "gn:feature_code":"PPL",
    "gn:name":"El Terrerito",
    "gn:population":23,
    "gn:timezone":"America/Chihuahua",
    "iso:country":"MX",
    "wof:name":"El Terrerito",
    "wof:placetype":"locality",
    "wof:population":23
},
  "geometry": {"coordinates":[-107.21707000000001,25.8719],"type":"Point"}
}