{
  "type": "Feature",
  "properties": {
    "gn:admin1_code":"6",
    "gn:admin2_code":"8",
    "gn:asciiname":"El Triguito",
    "gn:country_code":"MX",
    "gn:dem":1448,
    "gn:feature_class":"P",
    "gn:feature_code":"PPL",
    "gn:name":"El Triguito",
    "gn:population":10,
    "gn:timezone":"America/Chihuahua",
    "iso:country":"MX",
    "wof:name":"El Triguito",
    "wof:placetype":"locality",
    "wof:population":10
},
  "geometry": {"coordinates":[-107.77018,27.11076],"type":"Point"}
}