{
  "type": "Feature",
  "properties": {
    "gn:admin1_code":"5",
    "gn:admin2_code":"61",
    "gn:asciiname":"Yucatan",
    "gn:country_code":"MX",
    "gn:dem":941,
    "gn:feature_class":"P",
    "gn:feature_code":"PPL",
    "gn:name":"Yucat\u00e1n",
    "gn:population":9,
    "gn:timezone":"America/Mexico_City",
    "iso:country":"MX",
    "name:und_x_variant":[
        "Yucat\u00e1n"
    ],
    "wof:name":"Yucatan",
    "wof:placetype":"locality",
    "wof:population":9
},
  "geometry": {"coordinates":[-93.31833,16.70583],"type":"Point"}
}