{
  "type": "Feature",
  "properties": {
    "gn:admin1_code":"31",
    "gn:admin2_code":"4.0",
    "gn:asciiname":"Tixkunchell",
    "gn:country_code":"MX",
    "gn:dem":10,
    "gn:feature_class":"P",
    "gn:feature_code":"PPL",
    "gn:name":"Tixkunchell",
    "gn:population":0,
    "gn:timezone":"America/Merida",
    "iso:country":"MX",
    "name:spa_x_preferred":[
        "Tixkunchell"
    ],
    "name:und_x_variant":[
        "Tixcuncheil",
        "Tixkuncheil"
    ],
    "wof:name":"Tixkunchell",
    "wof:placetype":"locality"
},
  "geometry": {"coordinates":[-89.3977,21.07988],"type":"Point"}
}