{
  "type": "Feature",
  "properties": {
    "gn:admin1_code":"13",
    "gn:admin2_code":"57",
    "gn:asciiname":"La Reforma (San Isidro)",
    "gn:country_code":"MX",
    "gn:dem":2603,
    "gn:feature_class":"P",
    "gn:feature_code":"PPL",
    "gn:name":"La Reforma (San Isidro)",
    "gn:population":31,
    "gn:timezone":"America/Mexico_City",
    "iso:country":"MX",
    "wof:name":"La Reforma (San Isidro)",
    "wof:placetype":"locality",
    "wof:population":31
},
  "geometry": {"coordinates":[-98.52835,19.97463],"type":"Point"}
}