{
  "type": "Feature",
  "properties": {
    "gn:admin1_code":"16",
    "gn:admin2_code":"8",
    "gn:asciiname":"Playa de la Mula",
    "gn:country_code":"MX",
    "gn:dem":598,
    "gn:feature_class":"P",
    "gn:feature_code":"PPL",
    "gn:name":"Playa de la Mula",
    "gn:population":25,
    "gn:timezone":"America/Mexico_City",
    "iso:country":"MX",
    "wof:name":"Playa de la Mula",
    "wof:placetype":"locality",
    "wof:population":25
},
  "geometry": {"coordinates":[-103.02916999999999,18.29778],"type":"Point"}
}