{
  "type": "Feature",
  "properties": {
    "gn:admin1_code":"27.0",
    "gn:asciiname":"El Faisan",
    "gn:country_code":"MX",
    "gn:dem":4,
    "gn:feature_class":"P",
    "gn:feature_code":"PPL",
    "gn:name":"El Fais\u00e1n",
    "gn:population":0,
    "gn:timezone":"America/Mexico_City",
    "iso:country":"MX",
    "name:spa_x_preferred":[
        "Fais\u00e1n"
    ],
    "name:spa_x_variant":[
        "El Fais\u00e1n"
    ],
    "wof:name":"El Faisan",
    "wof:placetype":"locality"
},
  "geometry": {"coordinates":[-91.60968,18.021],"type":"Point"}
}