{
  "type": "Feature",
  "properties": {
    "gn:admin1_code":"27",
    "gn:admin2_code":"4.0",
    "gn:asciiname":"Coronel Traconis 2da. Seccion (El Zapote)",
    "gn:country_code":"MX",
    "gn:dem":8,
    "gn:feature_class":"P",
    "gn:feature_code":"PPL",
    "gn:name":"Coronel Traconis 2da. Secci\u00f3n (El Zapote)",
    "gn:population":170,
    "gn:timezone":"America/Mexico_City",
    "iso:country":"MX",
    "name:spa_x_preferred":[
        "Coronel Traconis"
    ],
    "wof:name":"Coronel Traconis 2da. Seccion (El Zapote)",
    "wof:placetype":"locality",
    "wof:population":170
},
  "geometry": {"coordinates":[-92.83194,17.94777999999999],"type":"Point"}
}