{
  "type": "Feature",
  "properties": {
    "gn:admin1_code":"19",
    "gn:admin2_code":"13.0",
    "gn:asciiname":"Dulces Nombres",
    "gn:country_code":"MX",
    "gn:dem":181,
    "gn:feature_class":"P",
    "gn:feature_code":"PPL",
    "gn:name":"Dulces Nombres",
    "gn:population":0,
    "gn:timezone":"America/Monterrey",
    "iso:country":"MX",
    "name:spa_x_preferred":[
        "Dulces Nombres"
    ],
    "wof:name":"Dulces Nombres",
    "wof:placetype":"locality"
},
  "geometry": {"coordinates":[-99.17639,25.56507],"type":"Point"}
}