{
  "type": "Feature",
  "properties": {
    "gn:admin1_code":"16",
    "gn:admin2_code":"69",
    "gn:asciiname":"La R [Granja]",
    "gn:country_code":"MX",
    "gn:dem":1736,
    "gn:feature_class":"P",
    "gn:feature_code":"PPL",
    "gn:name":"La R [Granja]",
    "gn:population":15,
    "gn:timezone":"America/Mexico_City",
    "iso:country":"MX",
    "wof:name":"La R [Granja]",
    "wof:placetype":"locality",
    "wof:population":15
},
  "geometry": {"coordinates":[-101.98528,20.29083],"type":"Point"}
}