{
  "type": "Feature",
  "properties": {
    "gn:admin1_code":"6",
    "gn:admin2_code":"33.0",
    "gn:asciiname":"El Arco",
    "gn:country_code":"MX",
    "gn:dem":1670,
    "gn:feature_class":"P",
    "gn:feature_code":"PPL",
    "gn:name":"El Arco",
    "gn:population":0,
    "gn:timezone":"America/Chihuahua",
    "iso:country":"MX",
    "name:ceb_x_preferred":[
        "El Arco"
    ],
    "name:spa_x_preferred":[
        "El Arco"
    ],
    "name:swe_x_preferred":[
        "El Arco"
    ],
    "wof:name":"El Arco",
    "wof:placetype":"locality"
},
  "geometry": {"coordinates":[-106.16154,27.05016],"type":"Point"}
}