{
  "type": "Feature",
  "properties": {
    "gn:country":"MX",
    "gn:fcode":"PPL",
    "gn:population":0,
    "iso:country":"MX",
    "name:ceb_x_preferred":[
        "Pueblo Nuevo"
    ],
    "name:deu_x_preferred":[
        "Pueblo Nuevo"
    ],
    "name:epo_x_preferred":[
        "Pueblo Nuevo"
    ],
    "name:fra_x_preferred":[
        "Pueblo Nuevo"
    ],
    "name:ita_x_preferred":[
        "Pueblo Nuevo"
    ],
    "name:nds_x_preferred":[
        "Pueblo Nuevo"
    ],
    "name:nld_x_preferred":[
        "Pueblo Nuevo"
    ],
    "name:pol_x_preferred":[
        "Pueblo Nuevo"
    ],
    "name:por_x_preferred":[
        "Pueblo Nuevo"
    ],
    "name:rus_x_preferred":[
        "\u041f\u0443\u044d\u0431\u043b\u043e-\u041d\u0443\u044d\u0432\u043e"
    ],
    "name:sco_x_preferred":[
        "Pueblo Nuevo"
    ],
    "name:spa_x_preferred":[
        "Pueblo Nuevo"
    ],
    "name:srp_x_preferred":[
        "\u041f\u0443\u0435\u0431\u043b\u043e \u041d\u0443\u0435\u0432\u043e"
    ],
    "name:swe_x_preferred":[
        "Pueblo Nuevo"
    ],
    "name:vie_x_preferred":[
        "Pueblo Nuevo"
    ],
    "qs_pg:aaroncc":"MX",
    "qs_pg:gn_country":"MX",
    "qs_pg:gn_fcode":"PPL",
    "qs_pg:gn_pop":0,
    "qs_pg:name":"Pueblo Nuevo",
    "qs_pg:name_adm0":"M\u00e9xico",
    "qs_pg:name_adm1":"Hidalgo",
    "qs_pg:photos":3,
    "qs_pg:photos_1k":1,
    "qs_pg:photos_9k":1,
    "qs_pg:photos_9r":1,
    "qs_pg:photos_all":3,
    "qs_pg:photos_sr":1,
    "qs_pg:pop_sr":0,
    "qs_pg:qs_pg_placetype":"neighbourhood",
    "qs_pg:qs_pg_placetype_gp":"Suburb",
    "qs_pg:woe_adm0":23424900,
    "woe:adm0_id":23424900,
    "woe:name_adm0":"M\u00e9xico",
    "woe:name_adm1":"Hidalgo",
    "woe:placetype":"Suburb",
    "wof:name":"Pueblo Nuevo",
    "wof:placetype":"neighbourhood"
},
  "geometry": {"coordinates":[-98.69027,20.17281],"type":"Point"}
}