{
  "type": "Feature",
  "properties": {
    "gn:admin1_code":"30",
    "gn:admin2_code":"169.0",
    "gn:asciiname":"Sidaria",
    "gn:country_code":"MX",
    "gn:dem":18,
    "gn:feature_class":"P",
    "gn:feature_code":"PPL",
    "gn:name":"Sidaria",
    "gn:population":0,
    "gn:timezone":"America/Mexico_City",
    "iso:country":"MX",
    "name:spa_x_preferred":[
        "Sidaria"
    ],
    "wof:name":"Sidaria",
    "wof:placetype":"locality"
},
  "geometry": {"coordinates":[-95.67973000000001,18.11709],"type":"Point"}
}