{
  "type": "Feature",
  "properties": {
    "gn:admin1_code":"14",
    "gn:admin2_code":"35",
    "gn:asciiname":"El Arca",
    "gn:country_code":"MX",
    "gn:dem":1983,
    "gn:feature_class":"P",
    "gn:feature_code":"PPL",
    "gn:name":"El Arca",
    "gn:population":16,
    "gn:timezone":"America/Mexico_City",
    "iso:country":"MX",
    "wof:name":"El Arca",
    "wof:placetype":"locality",
    "wof:population":16
},
  "geometry": {"coordinates":[-102.09611,21.73889],"type":"Point"}
}