{
  "type": "Feature",
  "properties": {
    "gn:admin1_code":"19.0",
    "gn:asciiname":"El Pirul",
    "gn:country_code":"MX",
    "gn:dem":340,
    "gn:feature_class":"P",
    "gn:feature_code":"PPL",
    "gn:name":"El Pirul",
    "gn:population":0,
    "gn:timezone":"America/Monterrey",
    "iso:country":"MX",
    "name:spa_x_preferred":[
        "El Pirul"
    ],
    "wof:name":"El Pirul",
    "wof:placetype":"locality"
},
  "geometry": {"coordinates":[-100.06373000000001,25.78416],"type":"Point"}
}