{
  "type": "Feature",
  "properties": {
    "gn:admin1_code":"21",
    "gn:admin2_code":"107.0",
    "gn:asciiname":"Santa Catarina",
    "gn:country_code":"MX",
    "gn:dem":409,
    "gn:feature_class":"P",
    "gn:feature_code":"PPL",
    "gn:name":"Santa Catarina",
    "gn:population":855,
    "gn:timezone":"America/Mexico_City",
    "iso:country":"MX",
    "wof:name":"Santa Catarina",
    "wof:placetype":"locality",
    "wof:population":855
},
  "geometry": {"coordinates":[-97.65525,20.14403],"type":"Point"}
}