{
  "type": "Feature",
  "properties": {
    "gn:admin1_code":"6",
    "gn:admin2_code":"46",
    "gn:asciiname":"El Rio",
    "gn:country_code":"MX",
    "gn:dem":788,
    "gn:feature_class":"P",
    "gn:feature_code":"PPL",
    "gn:name":"El R\u00edo",
    "gn:population":22,
    "gn:timezone":"America/Mazatlan",
    "iso:country":"MX",
    "name:und_x_variant":[
        "El R\u00edo"
    ],
    "wof:name":"El Rio",
    "wof:placetype":"locality",
    "wof:population":22
},
  "geometry": {"coordinates":[-107.94405,26.47022],"type":"Point"}
}