{
  "type": "Feature",
  "properties": {
    "gn:admin1_code":"16",
    "gn:admin2_code":"54.0",
    "gn:asciiname":"La Salud",
    "gn:country_code":"MX",
    "gn:dem":2247,
    "gn:feature_class":"P",
    "gn:feature_code":"PPL",
    "gn:name":"La Salud",
    "gn:population":228,
    "gn:timezone":"America/Mexico_City",
    "iso:country":"MX",
    "wof:name":"La Salud",
    "wof:placetype":"locality",
    "wof:population":228
},
  "geometry": {"coordinates":[-101.34193999999999,20.01611],"type":"Point"}
}