{
  "type": "Feature",
  "properties": {
    "gn:admin1_code":"19",
    "gn:admin2_code":"22.0",
    "gn:asciiname":"Barreales",
    "gn:country_code":"MX",
    "gn:dem":186,
    "gn:feature_class":"P",
    "gn:feature_code":"PPL",
    "gn:name":"Barreales",
    "gn:population":0,
    "gn:timezone":"America/Monterrey",
    "iso:country":"MX",
    "name:sco_x_preferred":[
        "Barreales"
    ],
    "name:spa_x_preferred":[
        "Barreales"
    ],
    "name:und_x_variant":[
        "Los Barreales",
        "Los Barriales"
    ],
    "wof:name":"Barreales",
    "wof:placetype":"locality"
},
  "geometry": {"coordinates":[-99.19074999999999,25.24409],"type":"Point"}
}