{
  "type": "Feature",
  "properties": {
    "gn:admin1_code":"23",
    "gn:admin2_code":"4.0",
    "gn:asciiname":"Canaan",
    "gn:country_code":"MX",
    "gn:dem":45,
    "gn:feature_class":"P",
    "gn:feature_code":"PPL",
    "gn:name":"Cana\u00e1n",
    "gn:population":0,
    "gn:timezone":"America/Cancun",
    "iso:country":"MX",
    "name:spa_x_preferred":[
        "Cana\u00e1n"
    ],
    "name:spa_x_variant":[
        "Canaan"
    ],
    "wof:name":"Canaan",
    "wof:placetype":"locality"
},
  "geometry": {"coordinates":[-88.83111,19.15077],"type":"Point"}
}