{
  "type": "Feature",
  "properties": {
    "gn:admin1_code":"30",
    "gn:admin2_code":"167.0",
    "gn:asciiname":"Copaltitla",
    "gn:country_code":"MX",
    "gn:dem":322,
    "gn:feature_class":"P",
    "gn:feature_code":"PPL",
    "gn:name":"Copaltitla",
    "gn:population":0,
    "gn:timezone":"America/Mexico_City",
    "iso:country":"MX",
    "name:und_x_variant":[
        "Copaltilla",
        "Copaltitla"
    ],
    "wof:name":"Copaltitla",
    "wof:placetype":"locality"
},
  "geometry": {"coordinates":[-97.87433,21.18481],"type":"Point"}
}