{
  "type": "Feature",
  "properties": {
    "gn:admin1_code":"10.0",
    "gn:admin2_code":"32.0",
    "gn:asciiname":"Cerro Nevado",
    "gn:country_code":"MX",
    "gn:dem":3093,
    "gn:feature_class":"P",
    "gn:feature_code":"PPL",
    "gn:name":"Cerro Nevado",
    "gn:population":0,
    "gn:timezone":"America/Monterrey",
    "iso:country":"MX",
    "name:spa_x_preferred":[
        "Cerro Nevado"
    ],
    "wof:name":"Cerro Nevado",
    "wof:placetype":"locality"
},
  "geometry": {"coordinates":[-106.07885,25.05367],"type":"Point"}
}