{
  "type": "Feature",
  "properties": {
    "gn:admin1_code":"26",
    "gn:admin2_code":"3.0",
    "gn:asciiname":"Munihuasa",
    "gn:country_code":"MX",
    "gn:dem":482,
    "gn:feature_class":"P",
    "gn:feature_code":"PPL",
    "gn:name":"Munihuasa",
    "gn:population":189,
    "gn:timezone":"America/Hermosillo",
    "iso:country":"MX",
    "wof:name":"Munihuasa",
    "wof:placetype":"locality",
    "wof:population":189
},
  "geometry": {"coordinates":[-108.80138999999998,27.14472],"type":"Point"}
}