{
  "type": "Feature",
  "properties": {
    "gn:admin1_code":"16",
    "gn:admin2_code":"29.0",
    "gn:asciiname":"Cuiripan",
    "gn:country_code":"MX",
    "gn:dem":1014,
    "gn:feature_class":"P",
    "gn:feature_code":"PPL",
    "gn:name":"Cuiripan",
    "gn:population":96,
    "gn:timezone":"America/Mexico_City",
    "iso:country":"MX",
    "wof:name":"Cuiripan",
    "wof:placetype":"locality",
    "wof:population":96
},
  "geometry": {"coordinates":[-101.47278,18.58083],"type":"Point"}
}