{
  "type": "Feature",
  "properties": {
    "gn:admin1_code":"6",
    "gn:admin2_code":"3.0",
    "gn:asciiname":"Plan de Ayala",
    "gn:country_code":"MX",
    "gn:dem":1386,
    "gn:feature_class":"P",
    "gn:feature_code":"PPL",
    "gn:name":"Plan de Ayala",
    "gn:population":0,
    "gn:timezone":"America/Chihuahua",
    "iso:country":"MX",
    "name:und_x_variant":[
        "Ejido Plan de Ayala",
        "Plan de Ayala"
    ],
    "wof:name":"Plan de Ayala",
    "wof:placetype":"locality"
},
  "geometry": {"coordinates":[-105.19126,27.31304],"type":"Point"}
}