{
  "type": "Feature",
  "properties": {
    "gn:admin1_code":"2",
    "gn:admin2_code":"3",
    "gn:asciiname":"El Cachoral",
    "gn:country_code":"MX",
    "gn:dem":962,
    "gn:feature_class":"P",
    "gn:feature_code":"PPL",
    "gn:name":"El Cachoral",
    "gn:population":12,
    "gn:timezone":"America/Tijuana",
    "iso:country":"MX",
    "wof:name":"El Cachoral",
    "wof:placetype":"locality",
    "wof:population":12
},
  "geometry": {"coordinates":[-116.36111,32.52056],"type":"Point"}
}