{
  "type": "Feature",
  "properties": {
    "gn:admin1_code":"30",
    "gn:admin2_code":"184.0",
    "gn:asciiname":"Ocotitla",
    "gn:country_code":"MX",
    "gn:dem":2391,
    "gn:feature_class":"P",
    "gn:feature_code":"PPL",
    "gn:name":"Ocotitla",
    "gn:population":128,
    "gn:timezone":"America/Mexico_City",
    "iso:country":"MX",
    "wof:name":"Ocotitla",
    "wof:placetype":"locality",
    "wof:population":128
},
  "geometry": {"coordinates":[-97.11944,18.59056],"type":"Point"}
}