{
  "type": "Feature",
  "properties": {
    "gn:admin1_code":"24",
    "gn:admin2_code":"46",
    "gn:asciiname":"Cono San Carlos",
    "gn:country_code":"MX",
    "gn:dem":2108,
    "gn:feature_class":"P",
    "gn:feature_code":"PPL",
    "gn:name":"Cono San Carlos",
    "gn:population":17,
    "gn:timezone":"America/Mexico_City",
    "iso:country":"MX",
    "wof:name":"Cono San Carlos",
    "wof:placetype":"locality",
    "wof:population":17
},
  "geometry": {"coordinates":[-101.33667,22.00833],"type":"Point"}
}