{
  "type": "Feature",
  "properties": {
    "gn:admin1_code":"11.0",
    "gn:admin2_code":"14.0",
    "gn:asciiname":"Ojo de Agua de Trancas",
    "gn:country_code":"MX",
    "gn:dem":2017,
    "gn:feature_class":"P",
    "gn:feature_code":"PPL",
    "gn:name":"Ojo de Agua de Trancas",
    "gn:population":0,
    "gn:timezone":"America/Mexico_City",
    "iso:country":"MX",
    "name:spa_x_preferred":[
        "Ojo de Agua de Trancas"
    ],
    "name:spa_x_variant":[
        "El Penal de Trancas"
    ],
    "wof:name":"Ojo de Agua de Trancas",
    "wof:placetype":"locality"
},
  "geometry": {"coordinates":[-100.9894,21.25447],"type":"Point"}
}