{
  "type": "Feature",
  "properties": {
    "gn:admin1_code":"4",
    "gn:admin2_code":"4.0",
    "gn:asciiname":"La Parcela",
    "gn:country_code":"MX",
    "gn:dem":30,
    "gn:feature_class":"P",
    "gn:feature_code":"PPL",
    "gn:name":"La Parcela",
    "gn:population":4,
    "gn:timezone":"America/Merida",
    "iso:country":"MX",
    "wof:name":"La Parcela",
    "wof:placetype":"locality",
    "wof:population":4
},
  "geometry": {"coordinates":[-90.59332999999999,18.94389],"type":"Point"}
}