{
  "type": "Feature",
  "properties": {
    "gn:admin1_code":"28",
    "gn:admin2_code":"22.0",
    "gn:asciiname":"La Jarita",
    "gn:country_code":"MX",
    "gn:dem":17,
    "gn:feature_class":"P",
    "gn:feature_code":"PPL",
    "gn:name":"La Jarita",
    "gn:population":0,
    "gn:timezone":"America/Matamoros",
    "iso:country":"MX",
    "name:und_x_variant":[
        "Jarita",
        "La Jarita"
    ],
    "wof:name":"La Jarita",
    "wof:placetype":"locality"
},
  "geometry": {"coordinates":[-97.68425999999999,25.66628],"type":"Point"}
}