{
  "type": "Feature",
  "properties": {
    "gn:admin1_code":"2",
    "gn:admin2_code":"3.0",
    "gn:asciiname":"Rosa de Castilla",
    "gn:country_code":"MX",
    "gn:dem":763,
    "gn:feature_class":"P",
    "gn:feature_code":"PPL",
    "gn:name":"Rosa de Castilla",
    "gn:population":0,
    "gn:timezone":"America/Tijuana",
    "iso:country":"MX",
    "name:spa_x_preferred":[
        "Rosa de Castilla"
    ],
    "name:und_x_variant":[
        "Rancho Rosa de Castilla"
    ],
    "wof:name":"Rosa de Castilla",
    "wof:placetype":"locality"
},
  "geometry": {"coordinates":[-116.48868,32.56729],"type":"Point"}
}