{
  "type": "Feature",
  "properties": {
    "gn:admin1_code":"5",
    "gn:admin2_code":"12",
    "gn:asciiname":"Quinta Emita",
    "gn:country_code":"MX",
    "gn:dem":850,
    "gn:feature_class":"P",
    "gn:feature_code":"PPL",
    "gn:name":"Quinta Emita",
    "gn:population":12,
    "gn:timezone":"America/Mexico_City",
    "iso:country":"MX",
    "wof:name":"Quinta Emita",
    "wof:placetype":"locality",
    "wof:population":12
},
  "geometry": {"coordinates":[-93.23444000000001,16.79332999999999],"type":"Point"}
}