{
  "type": "Feature",
  "properties": {
    "gn:admin1_code":"32",
    "gn:admin2_code":"19.0",
    "gn:asciiname":"La Media Luna",
    "gn:country_code":"MX",
    "gn:dem":1656,
    "gn:feature_class":"P",
    "gn:feature_code":"PPL",
    "gn:name":"La Media Luna",
    "gn:population":18,
    "gn:timezone":"America/Mexico_City",
    "iso:country":"MX",
    "wof:name":"La Media Luna",
    "wof:placetype":"locality",
    "wof:population":18
},
  "geometry": {"coordinates":[-102.83722,21.69444],"type":"Point"}
}