{
  "type": "Feature",
  "properties": {
    "gn:admin1_code":"14",
    "gn:admin2_code":"56.0",
    "gn:asciiname":"La Vibora",
    "gn:country_code":"MX",
    "gn:dem":613,
    "gn:feature_class":"P",
    "gn:feature_code":"PPL",
    "gn:name":"La V\u00edbora",
    "gn:population":6,
    "gn:timezone":"America/Mexico_City",
    "iso:country":"MX",
    "name:deu_x_preferred":[
        "La Vibora"
    ],
    "name:fra_x_preferred":[
        "La Vibora"
    ],
    "name:nld_x_preferred":[
        "La Vibora"
    ],
    "name:und_x_variant":[
        "La V\u00edbora"
    ],
    "wof:name":"La Vibora",
    "wof:placetype":"locality",
    "wof:population":6
},
  "geometry": {"coordinates":[-102.78417,19.52694],"type":"Point"}
}