{
  "type": "Feature",
  "properties": {
    "gn:admin1_code":"24.0",
    "gn:admin2_code":"40.0",
    "gn:asciiname":"Nuevo Progreso",
    "gn:country_code":"MX",
    "gn:dem":32,
    "gn:feature_class":"P",
    "gn:feature_code":"PPL",
    "gn:name":"Nuevo Progreso",
    "gn:population":0,
    "gn:timezone":"America/Mexico_City",
    "iso:country":"MX",
    "name:spa_x_preferred":[
        "Nuevo Progreso"
    ],
    "wof:name":"Nuevo Progreso",
    "wof:placetype":"locality"
},
  "geometry": {"coordinates":[-98.50736999999999,22.14898],"type":"Point"}
}