{
  "type": "Feature",
  "properties": {
    "gn:admin1_code":"24.0",
    "gn:admin2_code":"40.0",
    "gn:asciiname":"Nuevo Progreso",
    "gn:country_code":"MX",
    "gn:dem":32,
    "gn:feature_class":"P",
    "gn:feature_code":"PPL",
    "gn:name":"Nuevo Progreso",
    "gn:population":0,
    "gn:timezone":"America/Mexico_City",
    "iso:country":"MX",
    "name:ceb_x_preferred":[
        "Nuevo Progreso"
    ],
    "name:deu_x_preferred":[
        "Nuevo Progreso"
    ],
    "name:nld_x_preferred":[
        "Nuevo Progreso"
    ],
    "name:rus_x_preferred":[
        "\u041d\u0443\u044d\u0432\u043e-\u041f\u0440\u043e\u0433\u0440\u0435\u0441\u043e"
    ],
    "name:spa_x_preferred":[
        "Nuevo Progreso"
    ],
    "name:srp_x_preferred":[
        "\u041d\u0443\u0435\u0432\u043e \u041f\u0440\u043e\u0433\u0440\u0435\u0441\u043e"
    ],
    "name:swe_x_preferred":[
        "Nuevo Progreso"
    ],
    "wof:name":"Nuevo Progreso",
    "wof:placetype":"locality"
},
  "geometry": {"coordinates":[-98.50736999999999,22.14898],"type":"Point"}
}