{
  "type": "Feature",
  "properties": {
    "gn:admin1_code":"12",
    "gn:admin2_code":"79.0",
    "gn:asciiname":"Apozonalco",
    "gn:country_code":"MX",
    "gn:dem":1763,
    "gn:feature_class":"P",
    "gn:feature_code":"PPL",
    "gn:name":"Apozonalco",
    "gn:population":478,
    "gn:timezone":"America/Mexico_City",
    "iso:country":"MX",
    "wof:name":"Apozonalco",
    "wof:placetype":"locality",
    "wof:population":478
},
  "geometry": {"coordinates":[-98.99250000000001,17.46778],"type":"Point"}
}