{
  "type": "Feature",
  "properties": {
    "gn:admin1_code":"14.0",
    "gn:admin2_code":"35.0",
    "gn:asciiname":"Los Sauces Chicos",
    "gn:country_code":"MX",
    "gn:dem":1889,
    "gn:feature_class":"P",
    "gn:feature_code":"PPL",
    "gn:name":"Los Sauces Chicos",
    "gn:population":0,
    "gn:timezone":"America/Mexico_City",
    "iso:country":"MX",
    "name:spa_x_preferred":[
        "Los Sauces Chicos"
    ],
    "wof:name":"Los Sauces Chicos",
    "wof:placetype":"locality"
},
  "geometry": {"coordinates":[-102.13534,21.59727],"type":"Point"}
}