{
  "type": "Feature",
  "properties": {
    "gn:admin1_code":"19",
    "gn:admin2_code":"49.0",
    "gn:asciiname":"San Jose de las Boquillas",
    "gn:country_code":"MX",
    "gn:dem":1940,
    "gn:feature_class":"P",
    "gn:feature_code":"PPL",
    "gn:name":"San Jos\u00e9 de las Boquillas",
    "gn:population":65,
    "gn:timezone":"America/Monterrey",
    "iso:country":"MX",
    "name:spa_x_preferred":[
        "San Jos\u00e9 de las Boquillas"
    ],
    "wof:name":"San Jose de las Boquillas",
    "wof:placetype":"locality",
    "wof:population":65
},
  "geometry": {"coordinates":[-100.40492,25.36445],"type":"Point"}
}