{
  "type": "Feature",
  "properties": {
    "gn:admin1_code":"5.0",
    "gn:admin2_code":"51.0",
    "gn:asciiname":"California",
    "gn:country_code":"MX",
    "gn:dem":13,
    "gn:feature_class":"P",
    "gn:feature_code":"PPL",
    "gn:name":"California",
    "gn:population":0,
    "gn:timezone":"America/Mexico_City",
    "iso:country":"MX",
    "name:spa_x_preferred":[
        "Las Delicias"
    ],
    "name:spa_x_variant":[
        "California"
    ],
    "wof:name":"California",
    "wof:placetype":"locality"
},
  "geometry": {"coordinates":[-93.02706999999999,15.36226],"type":"Point"}
}