{
  "type": "Feature",
  "properties": {
    "gn:admin1_code":"22",
    "gn:admin2_code":"3.0",
    "gn:asciiname":"La Minita",
    "gn:cc2":"MX",
    "gn:country_code":"MX",
    "gn:dem":705,
    "gn:feature_class":"P",
    "gn:feature_code":"PPL",
    "gn:name":"La Minita",
    "gn:population":0,
    "gn:timezone":"America/Mexico_City",
    "iso:country":"MX",
    "name:und_x_variant":[
        "Minita",
        "La Minita"
    ],
    "wof:name":"La Minita",
    "wof:placetype":"locality"
},
  "geometry": {"coordinates":[-99.61667,21.45],"type":"Point"}
}