{
  "type": "Feature",
  "properties": {
    "gn:admin1_code":"26.0",
    "gn:admin2_code":"17.0",
    "gn:asciiname":"Ejido Salomon Kiwis",
    "gn:country_code":"MX",
    "gn:dem":226,
    "gn:feature_class":"P",
    "gn:feature_code":"PPL",
    "gn:name":"Ejido Salom\u00f3n Kiwis",
    "gn:population":0,
    "gn:timezone":"America/Hermosillo",
    "iso:country":"MX",
    "name:spa_x_preferred":[
        "Ejido Salom\u00f3n Kiwis"
    ],
    "wof:name":"Ejido Salomon Kiwis",
    "wof:placetype":"locality"
},
  "geometry": {"coordinates":[-112.25573,30.57938],"type":"Point"}
}