{
  "type": "Feature",
  "properties": {
    "gn:admin1_code":"4",
    "gn:admin2_code":"7.0",
    "gn:asciiname":"Dolores",
    "gn:country_code":"MX",
    "gn:dem":-5,
    "gn:feature_class":"P",
    "gn:feature_code":"PPL",
    "gn:name":"Dolores",
    "gn:population":0,
    "gn:timezone":"America/Merida",
    "iso:country":"MX",
    "name:aze_x_preferred":[
        "Dolores"
    ],
    "name:bre_x_preferred":[
        "Dolores"
    ],
    "name:ceb_x_preferred":[
        "Dolores"
    ],
    "name:deu_x_preferred":[
        "Dolores"
    ],
    "name:est_x_preferred":[
        "Dolores"
    ],
    "name:fra_x_preferred":[
        "Dolores"
    ],
    "name:hun_x_preferred":[
        "Dolores"
    ],
    "name:ilo_x_preferred":[
        "Dolores"
    ],
    "name:ita_x_preferred":[
        "Dolores"
    ],
    "name:jpn_x_preferred":[
        "\u30c9\u30ed\u30ec\u30b9"
    ],
    "name:nds_x_preferred":[
        "Dolores"
    ],
    "name:nld_x_preferred":[
        "Dolores"
    ],
    "name:pol_x_preferred":[
        "Dolores"
    ],
    "name:por_x_preferred":[
        "Dolores"
    ],
    "name:rus_x_preferred":[
        "\u0414\u043e\u043b\u043e\u0440\u0435\u0441"
    ],
    "name:spa_x_preferred":[
        "Dolores"
    ],
    "name:srp_x_preferred":[
        "\u0414\u043e\u043b\u043e\u0440\u0435\u0441"
    ],
    "name:swe_x_preferred":[
        "Dolores"
    ],
    "name:tur_x_preferred":[
        "Dolores"
    ],
    "name:ukr_x_preferred":[
        "\u0414\u043e\u043b\u043e\u0440\u0435\u0441"
    ],
    "name:vie_x_preferred":[
        "Dolores"
    ],
    "name:war_x_preferred":[
        "Dolores"
    ],
    "wof:name":"Dolores",
    "wof:placetype":"locality"
},
  "geometry": {"coordinates":[-91.83137000000001,18.25106],"type":"Point"}
}