{
  "type": "Feature",
  "properties": {
    "gn:admin1_code":"32",
    "gn:admin2_code":"52.0",
    "gn:asciiname":"Emiliano Zapata (Arrebiatadas)",
    "gn:country_code":"MX",
    "gn:dem":2186,
    "gn:feature_class":"P",
    "gn:feature_code":"PPL",
    "gn:name":"Emiliano Zapata (Arrebiatadas)",
    "gn:population":142,
    "gn:timezone":"America/Mexico_City",
    "iso:country":"MX",
    "wof:name":"Emiliano Zapata (Arrebiatadas)",
    "wof:placetype":"locality",
    "wof:population":142
},
  "geometry": {"coordinates":[-101.88806,22.14806],"type":"Point"}
}