{
  "type": "Feature",
  "properties": {
    "gn:admin1_code":"21.0",
    "gn:asciiname":"El Epazote",
    "gn:country_code":"MX",
    "gn:dem":1492,
    "gn:feature_class":"P",
    "gn:feature_code":"PPL",
    "gn:name":"El Epazote",
    "gn:population":0,
    "gn:timezone":"America/Mexico_City",
    "iso:country":"MX",
    "name:spa_x_preferred":[
        "El Epazote"
    ],
    "wof:name":"El Epazote",
    "wof:placetype":"locality"
},
  "geometry": {"coordinates":[-98.14,18.309],"type":"Point"}
}