{
  "type": "Feature",
  "properties": {
    "gn:admin1_code":"5",
    "gn:admin2_code":"61.0",
    "gn:asciiname":"El Recreo",
    "gn:country_code":"MX",
    "gn:dem":770,
    "gn:feature_class":"P",
    "gn:feature_code":"PPL",
    "gn:name":"El Recreo",
    "gn:population":6,
    "gn:timezone":"America/Mexico_City",
    "iso:country":"MX",
    "wof:name":"El Recreo",
    "wof:placetype":"locality",
    "wof:population":6
},
  "geometry": {"coordinates":[-93.46417,16.54889],"type":"Point"}
}