{
  "type": "Feature",
  "properties": {
    "gn:admin1_code":"7",
    "gn:admin2_code":"37.0",
    "gn:asciiname":"Las Galeras",
    "gn:country_code":"MX",
    "gn:dem":347,
    "gn:feature_class":"P",
    "gn:feature_code":"PPL",
    "gn:name":"Las Galeras",
    "gn:population":0,
    "gn:timezone":"America/Monterrey",
    "iso:country":"MX",
    "name:spa_x_preferred":[
        "Las Galeras"
    ],
    "name:spa_x_variant":[
        "Galeras"
    ],
    "wof:name":"Las Galeras",
    "wof:placetype":"locality"
},
  "geometry": {"coordinates":[-100.77446999999999,28.34725],"type":"Point"}
}