{
  "type": "Feature",
  "properties": {
    "gn:admin1_code":"20",
    "gn:admin2_code":"279.0",
    "gn:asciiname":"La Luz del Sol",
    "gn:country_code":"MX",
    "gn:dem":2368,
    "gn:feature_class":"P",
    "gn:feature_code":"PPL",
    "gn:name":"La Luz del Sol",
    "gn:population":65,
    "gn:timezone":"America/Mexico_City",
    "iso:country":"MX",
    "wof:name":"La Luz del Sol",
    "wof:placetype":"locality",
    "wof:population":65
},
  "geometry": {"coordinates":[-96.46056,16.07777999999999],"type":"Point"}
}