{
  "type": "Feature",
  "properties": {
    "gn:admin1_code":"30.0",
    "gn:admin2_code":"207.0",
    "gn:asciiname":"El Pinito",
    "gn:country_code":"MX",
    "gn:dem":28,
    "gn:feature_class":"P",
    "gn:feature_code":"PPL",
    "gn:name":"El Pinito",
    "gn:population":0,
    "gn:timezone":"America/Mexico_City",
    "iso:country":"MX",
    "name:spa_x_preferred":[
        "El Pinito"
    ],
    "wof:name":"El Pinito",
    "wof:placetype":"locality"
},
  "geometry": {"coordinates":[-96.25385,18.27817000000001],"type":"Point"}
}