{
  "type": "Feature",
  "properties": {
    "gn:admin1_code":"14.0",
    "gn:admin2_code":"87.0",
    "gn:asciiname":"La Mojada",
    "gn:country_code":"MX",
    "gn:dem":765,
    "gn:feature_class":"P",
    "gn:feature_code":"PPL",
    "gn:name":"La Mojada",
    "gn:population":0,
    "gn:timezone":"America/Mexico_City",
    "iso:country":"MX",
    "name:spa_x_preferred":[
        "La Mojada"
    ],
    "name:und_x_variant":[
        "La Majada"
    ],
    "wof:name":"La Mojada",
    "wof:placetype":"locality"
},
  "geometry": {"coordinates":[-103.18262,19.03858],"type":"Point"}
}