{
  "type": "Feature",
  "properties": {
    "gn:admin1_code":"7.0",
    "gn:admin2_code":"31.0",
    "gn:asciiname":"La Loba",
    "gn:country_code":"MX",
    "gn:dem":1170,
    "gn:feature_class":"P",
    "gn:feature_code":"PPL",
    "gn:name":"La Loba",
    "gn:population":0,
    "gn:timezone":"America/Monterrey",
    "iso:country":"MX",
    "name:spa_x_preferred":[
        "La Loba"
    ],
    "wof:name":"La Loba",
    "wof:placetype":"locality"
},
  "geometry": {"coordinates":[-102.02598999999999,27.91963],"type":"Point"}
}