{
  "type": "Feature",
  "properties": {
    "gn:admin1_code":"6.0",
    "gn:admin2_code":"62.0",
    "gn:asciiname":"Kilometro Cincuenta y Nueve",
    "gn:country_code":"MX",
    "gn:dem":1217,
    "gn:feature_class":"P",
    "gn:feature_code":"PPL",
    "gn:name":"Kil\u00f3metro Cincuenta y Nueve",
    "gn:population":301,
    "gn:timezone":"America/Chihuahua",
    "iso:country":"MX",
    "wof:name":"Kilometro Cincuenta y Nueve",
    "wof:placetype":"locality",
    "wof:population":301
},
  "geometry": {"coordinates":[-105.35457,28.07022000000001],"type":"Point"}
}