{
  "type": "Feature",
  "properties": {
    "gn:admin1_code":"15",
    "gn:admin2_code":"41",
    "gn:asciiname":"Sabanilla",
    "gn:country_code":"MX",
    "gn:dem":1945,
    "gn:feature_class":"P",
    "gn:feature_code":"PPL",
    "gn:name":"Sabanilla",
    "gn:population":46,
    "gn:timezone":"America/Mexico_City",
    "iso:country":"MX",
    "name:ceb_x_preferred":[
        "Sabanilla"
    ],
    "name:deu_x_preferred":[
        "Municipio Sabanilla"
    ],
    "name:epo_x_preferred":[
        "Sabanilla"
    ],
    "name:eus_x_preferred":[
        "Sabanilla"
    ],
    "name:fra_x_preferred":[
        "Sabanilla"
    ],
    "name:por_x_preferred":[
        "Sabanilla"
    ],
    "name:rus_x_preferred":[
        "\u0421\u0430\u0431\u0430\u043d\u0438\u043b\u044c\u044f"
    ],
    "name:sco_x_preferred":[
        "Sabanilla"
    ],
    "name:spa_x_preferred":[
        "Sabanilla"
    ],
    "name:srp_x_preferred":[
        "\u041e\u043f\u0448\u0442\u0438\u043d\u0430 \u0421\u0430\u0431\u0430\u043d\u0438\u0459\u0430"
    ],
    "name:swe_x_preferred":[
        "Sabanilla"
    ],
    "name:urd_x_preferred":[
        "\u0633\u0628\u0646\u0644\u06c1"
    ],
    "name:vie_x_preferred":[
        "Sabanilla"
    ],
    "wof:name":"Sabanilla",
    "wof:placetype":"locality",
    "wof:population":46
},
  "geometry": {"coordinates":[-100.28507,19.27435],"type":"Point"}
}