{
  "type": "Feature",
  "properties": {
    "gn:admin1_code":"26.0",
    "gn:asciiname":"La Pitahayita",
    "gn:country_code":"MX",
    "gn:dem":449,
    "gn:feature_class":"P",
    "gn:feature_code":"PPL",
    "gn:name":"La Pitahayita",
    "gn:population":0,
    "gn:timezone":"America/Hermosillo",
    "iso:country":"MX",
    "name:spa_x_preferred":[
        "La Pitahayita"
    ],
    "wof:name":"La Pitahayita",
    "wof:placetype":"locality"
},
  "geometry": {"coordinates":[-109.39476000000001,27.86429],"type":"Point"}
}