{
  "type": "Feature",
  "properties": {
    "gn:admin1_code":"32.0",
    "gn:admin2_code":"16.0",
    "gn:asciiname":"Vinedos Santa Ana",
    "gn:country_code":"MX",
    "gn:dem":2064,
    "gn:feature_class":"P",
    "gn:feature_code":"PPL",
    "gn:name":"Vi\u00f1edos Santa Ana",
    "gn:population":0,
    "gn:timezone":"America/Mexico_City",
    "iso:country":"MX",
    "name:spa_x_preferred":[
        "Vi\u00f1edos Santa Ana"
    ],
    "wof:name":"Vinedos Santa Ana",
    "wof:placetype":"locality"
},
  "geometry": {"coordinates":[-102.07041,22.68946],"type":"Point"}
}