{
  "type": "Feature",
  "properties": {
    "gn:admin1_code":"30",
    "gn:admin2_code":"54.0",
    "gn:asciiname":"Loma del Carmen",
    "gn:country_code":"MX",
    "gn:dem":40,
    "gn:feature_class":"P",
    "gn:feature_code":"PPL",
    "gn:name":"Loma del Carmen",
    "gn:population":4,
    "gn:timezone":"America/Mexico_City",
    "iso:country":"MX",
    "wof:name":"Loma del Carmen",
    "wof:placetype":"locality",
    "wof:population":4
},
  "geometry": {"coordinates":[-95.80500000000001,18.21778],"type":"Point"}
}