{
  "type": "Feature",
  "properties": {
    "gn:admin1_code":"18.0",
    "gn:admin2_code":"12.0",
    "gn:asciiname":"El Tepeyac",
    "gn:country_code":"MX",
    "gn:dem":126,
    "gn:feature_class":"P",
    "gn:feature_code":"PPL",
    "gn:name":"El Tepeyac",
    "gn:population":0,
    "gn:timezone":"America/Mazatlan",
    "iso:country":"MX",
    "name:und_x_variant":[
        "Cofradia",
        "El Tepeyac"
    ],
    "wof:name":"El Tepeyac",
    "wof:placetype":"locality"
},
  "geometry": {"coordinates":[-105.14400000000001,21.59503],"type":"Point"}
}