{
  "type": "Feature",
  "properties": {
    "gn:admin1_code":"26",
    "gn:admin2_code":"3.0",
    "gn:asciiname":"Los Capomos",
    "gn:country_code":"MX",
    "gn:dem":178,
    "gn:feature_class":"P",
    "gn:feature_code":"PPL",
    "gn:name":"Los Capomos",
    "gn:population":8,
    "gn:timezone":"America/Hermosillo",
    "iso:country":"MX",
    "name:und_x_variant":[
        "Rancho Los Capomos",
        "Capomos",
        "Los Capomos"
    ],
    "wof:name":"Los Capomos",
    "wof:placetype":"locality",
    "wof:population":8
},
  "geometry": {"coordinates":[-109.04984,26.73965],"type":"Point"}
}