{
  "type": "Feature",
  "properties": {
    "iso:country":"MX",
    "qs_pg:aaroncc":"MX",
    "qs_pg:name":"Rinconada San Jose",
    "qs_pg:name_adm0":"M\u00e9xico",
    "qs_pg:name_adm1":"Queretaro de Arteaga",
    "qs_pg:photos":22,
    "qs_pg:photos_1k":4,
    "qs_pg:photos_9k":1,
    "qs_pg:photos_9r":1,
    "qs_pg:photos_all":22,
    "qs_pg:photos_sr":1,
    "qs_pg:pop_sr":0,
    "qs_pg:qs_pg_placetype":"neighbourhood",
    "qs_pg:qs_pg_placetype_gp":"Suburb",
    "qs_pg:woe_adm0":23424900,
    "woe:adm0_id":23424900,
    "woe:name_adm0":"M\u00e9xico",
    "woe:name_adm1":"Queretaro de Arteaga",
    "woe:placetype":"Suburb",
    "wof:name":"Rinconada San Jose",
    "wof:placetype":"neighbourhood"
},
  "geometry": {"coordinates":[-100.40057049999999,20.6176545],"type":"Point"}
}