{
  "type": "Feature",
  "properties": {
    "gn:admin1_code":"11",
    "gn:admin2_code":"8",
    "gn:asciiname":"La Luz de Cortez",
    "gn:country_code":"MX",
    "gn:dem":1747,
    "gn:feature_class":"P",
    "gn:feature_code":"PPL",
    "gn:name":"La Luz de Cortez",
    "gn:population":34,
    "gn:timezone":"America/Mexico_City",
    "iso:country":"MX",
    "wof:name":"La Luz de Cortez",
    "wof:placetype":"locality",
    "wof:population":34
},
  "geometry": {"coordinates":[-101.79555999999999,20.72889],"type":"Point"}
}