{
  "type": "Feature",
  "properties": {
    "gn:admin1_code":"16",
    "gn:admin2_code":"34.0",
    "gn:asciiname":"El Chiquihuite",
    "gn:country_code":"MX",
    "gn:dem":2525,
    "gn:feature_class":"P",
    "gn:feature_code":"PPL",
    "gn:name":"El Chiquihuite",
    "gn:population":9,
    "gn:timezone":"America/Mexico_City",
    "iso:country":"MX",
    "wof:name":"El Chiquihuite",
    "wof:placetype":"locality",
    "wof:population":9
},
  "geometry": {"coordinates":[-100.65306,19.60639],"type":"Point"}
}