{
  "type": "Feature",
  "properties": {
    "gn:admin1_code":"16",
    "gn:admin2_code":"52.0",
    "gn:asciiname":"Baden de Nexpa",
    "gn:country_code":"MX",
    "gn:dem":16,
    "gn:feature_class":"P",
    "gn:feature_code":"PPL",
    "gn:name":"Baden de Nexpa",
    "gn:population":0,
    "gn:timezone":"America/Mexico_City",
    "iso:country":"MX",
    "name:spa_x_preferred":[
        "Baden de Nexpa"
    ],
    "wof:name":"Baden de Nexpa",
    "wof:placetype":"locality"
},
  "geometry": {"coordinates":[-102.78163000000001,18.09127],"type":"Point"}
}