{
  "type": "Feature",
  "properties": {
    "gn:admin1_code":"28",
    "gn:admin2_code":"43.0",
    "gn:asciiname":"Melchor Ocampo",
    "gn:country_code":"MX",
    "gn:dem":82,
    "gn:feature_class":"P",
    "gn:feature_code":"PPL",
    "gn:name":"Melchor Ocampo",
    "gn:population":0,
    "gn:timezone":"America/Monterrey",
    "iso:country":"MX",
    "name:deu_x_preferred":[
        "Melchor Ocampo"
    ],
    "name:epo_x_preferred":[
        "Melchor Ocampo"
    ],
    "name:fra_x_preferred":[
        "Melchor Ocampo"
    ],
    "name:ita_x_preferred":[
        "Melchor Ocampo"
    ],
    "name:nld_x_preferred":[
        "Melchor Ocampo"
    ],
    "name:pol_x_preferred":[
        "Melchor Ocampo"
    ],
    "name:por_x_preferred":[
        "Melchor Ocampo"
    ],
    "name:que_x_preferred":[
        "Melchor Ocampo"
    ],
    "name:rus_x_preferred":[
        "\u041e\u043a\u0430\u043c\u043f\u043e"
    ],
    "name:spa_x_preferred":[
        "Melchor Ocampo"
    ],
    "wof:name":"Melchor Ocampo",
    "wof:placetype":"locality"
},
  "geometry": {"coordinates":[-98.99903,22.92757000000001],"type":"Point"}
}