{
  "type": "Feature",
  "properties": {
    "gn:admin1_code":"5",
    "gn:admin2_code":"109.0",
    "gn:asciiname":"Pucilton Uno",
    "gn:country_code":"MX",
    "gn:dem":874,
    "gn:feature_class":"P",
    "gn:feature_code":"PPL",
    "gn:name":"Pucilt\u00f3n Uno",
    "gn:population":193,
    "gn:timezone":"America/Mexico_City",
    "iso:country":"MX",
    "name:und_x_variant":[
        "Pucilt\u00f3n Uno"
    ],
    "wof:name":"Pucilton Uno",
    "wof:placetype":"locality",
    "wof:population":193
},
  "geometry": {"coordinates":[-92.34166999999999,17.19889],"type":"Point"}
}