{
  "type": "Feature",
  "properties": {
    "gn:admin1_code":"17",
    "gn:asciiname":"San Sebastian",
    "gn:country_code":"MX",
    "gn:dem":2261,
    "gn:feature_class":"P",
    "gn:feature_code":"PPL",
    "gn:name":"San Sebasti\u00e1n",
    "gn:population":0,
    "gn:timezone":"America/Mexico_City",
    "iso:country":"MX",
    "name:spa_x_preferred":[
        "San Sebasti\u00e1n"
    ],
    "wof:name":"San Sebastian",
    "wof:placetype":"locality"
},
  "geometry": {"coordinates":[-99.0556,19.78431],"type":"Point"}
}