{
  "type": "Feature",
  "properties": {
    "gn:admin1_code":"20",
    "gn:admin2_code":"170.0",
    "gn:asciiname":"Lachivigoza",
    "gn:country_code":"MX",
    "gn:dem":1657,
    "gn:feature_class":"P",
    "gn:feature_code":"PPL",
    "gn:name":"Lachivigoza",
    "gn:population":0,
    "gn:timezone":"America/Mexico_City",
    "iso:country":"MX",
    "name:und_x_variant":[
        "Lonchivigosa",
        "Lachivigosa",
        "Lachivigoza"
    ],
    "wof:name":"Lachivigoza",
    "wof:placetype":"locality"
},
  "geometry": {"coordinates":[-96.31965,16.41464],"type":"Point"}
}