{
  "type": "Feature",
  "properties": {
    "gn:admin1_code":"5",
    "gn:admin2_code":"46.0",
    "gn:asciiname":"Las Carolinas",
    "gn:country_code":"MX",
    "gn:dem":558,
    "gn:feature_class":"P",
    "gn:feature_code":"PPL",
    "gn:name":"Las Carolinas",
    "gn:population":7,
    "gn:timezone":"America/Mexico_City",
    "iso:country":"MX",
    "wof:name":"Las Carolinas",
    "wof:placetype":"locality",
    "wof:population":7
},
  "geometry": {"coordinates":[-93.56332999999999,16.5975],"type":"Point"}
}