{
  "type": "Feature",
  "properties": {
    "gn:admin1_code":"5",
    "gn:admin2_code":"59.0",
    "gn:asciiname":"Nueva Libertad",
    "gn:country_code":"MX",
    "gn:dem":246,
    "gn:feature_class":"P",
    "gn:feature_code":"PPL",
    "gn:name":"Nueva Libertad",
    "gn:population":0,
    "gn:timezone":"America/Mexico_City",
    "iso:country":"MX",
    "name:spa_x_preferred":[
        "Nueva Libertad"
    ],
    "wof:name":"Nueva Libertad",
    "wof:placetype":"locality"
},
  "geometry": {"coordinates":[-91.30598000000001,17.10081],"type":"Point"}
}