{
  "type": "Feature",
  "properties": {
    "gn:admin1_code":"11",
    "gn:admin2_code":"23.0",
    "gn:asciiname":"Huerta Grande (Sauz de Mendez)",
    "gn:country_code":"MX",
    "gn:dem":1835,
    "gn:feature_class":"P",
    "gn:feature_code":"PPL",
    "gn:name":"Huerta Grande (Sauz de M\u00e9ndez)",
    "gn:population":102,
    "gn:timezone":"America/Mexico_City",
    "iso:country":"MX",
    "name:und_x_variant":[
        "Huerta Grande (Sauz de M\u00e9ndez)"
    ],
    "wof:name":"Huerta Grande (Sauz de Mendez)",
    "wof:placetype":"locality",
    "wof:population":102
},
  "geometry": {"coordinates":[-101.89806,20.47611],"type":"Point"}
}