{
  "type": "Feature",
  "properties": {
    "gn:admin1_code":"6",
    "gn:admin2_code":"31.0",
    "gn:asciiname":"Rancho Carpio",
    "gn:country_code":"MX",
    "gn:dem":2004,
    "gn:feature_class":"P",
    "gn:feature_code":"PPL",
    "gn:name":"Rancho Carpio",
    "gn:population":194,
    "gn:timezone":"America/Chihuahua",
    "iso:country":"MX",
    "wof:name":"Rancho Carpio",
    "wof:placetype":"locality",
    "wof:population":194
},
  "geometry": {"coordinates":[-107.49806,28.57083],"type":"Point"}
}