{
  "type": "Feature",
  "properties": {
    "gn:admin1_code":"12.0",
    "gn:asciiname":"Cinco Mangos",
    "gn:country_code":"MX",
    "gn:dem":1116,
    "gn:feature_class":"P",
    "gn:feature_code":"PPL",
    "gn:name":"Cinco Mangos",
    "gn:population":0,
    "gn:timezone":"America/Mexico_City",
    "iso:country":"MX",
    "name:spa_x_preferred":[
        "Cinco Mangos"
    ],
    "wof:name":"Cinco Mangos",
    "wof:placetype":"locality"
},
  "geometry": {"coordinates":[-98.61951000000001,17.53002],"type":"Point"}
}