{
  "type": "Feature",
  "properties": {
    "gn:admin1_code":"12.0",
    "gn:admin2_code":"24.0",
    "gn:asciiname":"Tezoquia",
    "gn:country_code":"MX",
    "gn:dem":1583,
    "gn:feature_class":"P",
    "gn:feature_code":"PPL",
    "gn:name":"Tezoquia",
    "gn:population":0,
    "gn:timezone":"America/Mexico_City",
    "iso:country":"MX",
    "name:spa_x_preferred":[
        "Tezoquia"
    ],
    "wof:name":"Tezoquia",
    "wof:placetype":"locality"
},
  "geometry": {"coordinates":[-98.60677,17.76705],"type":"Point"}
}