{
  "type": "Feature",
  "properties": {
    "gn:admin1_code":"24",
    "gn:admin2_code":"20",
    "gn:asciiname":"Los Torres",
    "gn:country_code":"MX",
    "gn:dem":1608,
    "gn:feature_class":"P",
    "gn:feature_code":"PPL",
    "gn:name":"Los Torres",
    "gn:population":40,
    "gn:timezone":"America/Mexico_City",
    "iso:country":"MX",
    "wof:name":"Los Torres",
    "wof:placetype":"locality",
    "wof:population":40
},
  "geometry": {"coordinates":[-100.65694000000001,23.62833],"type":"Point"}
}