{
  "type": "Feature",
  "properties": {
    "gn:admin1_code":"30",
    "gn:admin2_code":"137.0",
    "gn:asciiname":"Tlanestla",
    "gn:country_code":"MX",
    "gn:dem":1725,
    "gn:feature_class":"P",
    "gn:feature_code":"PPL",
    "gn:name":"Tlanestla",
    "gn:population":92,
    "gn:timezone":"America/Mexico_City",
    "iso:country":"MX",
    "wof:name":"Tlanestla",
    "wof:placetype":"locality",
    "wof:population":92
},
  "geometry": {"coordinates":[-97.02972,18.67139],"type":"Point"}
}