{
  "type": "Feature",
  "properties": {
    "gn:admin1_code":"19.0",
    "gn:asciiname":"San Jose Lote Cuarenta",
    "gn:country_code":"MX",
    "gn:dem":584,
    "gn:feature_class":"P",
    "gn:feature_code":"PPL",
    "gn:name":"San Jos\u00e9 Lote Cuarenta",
    "gn:population":0,
    "gn:timezone":"America/Monterrey",
    "iso:country":"MX",
    "name:spa_x_preferred":[
        "San Jos\u00e9 Lote Cuarenta"
    ],
    "wof:name":"San Jose Lote Cuarenta",
    "wof:placetype":"locality"
},
  "geometry": {"coordinates":[-100.43537000000001,25.79704],"type":"Point"}
}