{
  "type": "Feature",
  "properties": {
    "gn:admin1_code":"7.0",
    "gn:admin2_code":"4.0",
    "gn:asciiname":"Escobedo",
    "gn:country_code":"MX",
    "gn:dem":2109,
    "gn:feature_class":"P",
    "gn:feature_code":"PPL",
    "gn:name":"Escobedo",
    "gn:population":0,
    "gn:timezone":"America/Monterrey",
    "iso:country":"MX",
    "name:ceb_x_preferred":[
        "Escobedo"
    ],
    "name:deu_x_preferred":[
        "Escobedo"
    ],
    "name:spa_x_preferred":[
        "Escobedo"
    ],
    "name:swe_x_preferred":[
        "Escobedo"
    ],
    "name:vie_x_preferred":[
        "Escobedo"
    ],
    "wof:name":"Escobedo",
    "wof:placetype":"locality"
},
  "geometry": {"coordinates":[-100.6711,25.34661],"type":"Point"}
}