{
  "type": "Feature",
  "properties": {
    "gn:admin1_code":"5.0",
    "gn:admin2_code":"94.0",
    "gn:asciiname":"Las Coquetas Rojas",
    "gn:country_code":"MX",
    "gn:dem":1826,
    "gn:feature_class":"P",
    "gn:feature_code":"PPL",
    "gn:name":"Las Coquetas Rojas",
    "gn:population":0,
    "gn:timezone":"America/Mexico_City",
    "iso:country":"MX",
    "name:spa_x_preferred":[
        "Las Coquetas Rojas"
    ],
    "wof:name":"Las Coquetas Rojas",
    "wof:placetype":"locality"
},
  "geometry": {"coordinates":[-92.50100999999999,16.56799],"type":"Point"}
}