{
  "type": "Feature",
  "properties": {
    "gn:admin1_code":"16",
    "gn:admin2_code":"80.0",
    "gn:asciiname":"La Lagunita",
    "gn:country_code":"MX",
    "gn:dem":2694,
    "gn:feature_class":"P",
    "gn:feature_code":"PPL",
    "gn:name":"La Lagunita",
    "gn:population":96,
    "gn:timezone":"America/Mexico_City",
    "iso:country":"MX",
    "wof:name":"La Lagunita",
    "wof:placetype":"locality",
    "wof:population":96
},
  "geometry": {"coordinates":[-100.2975,19.73611],"type":"Point"}
}