{
  "type": "Feature",
  "properties": {
    "gn:admin1_code":"13",
    "gn:admin2_code":"28.0",
    "gn:asciiname":"Tilcalco",
    "gn:country_code":"MX",
    "gn:dem":408,
    "gn:feature_class":"P",
    "gn:feature_code":"PPL",
    "gn:name":"Tilcalco",
    "gn:population":72,
    "gn:timezone":"America/Mexico_City",
    "iso:country":"MX",
    "wof:name":"Tilcalco",
    "wof:placetype":"locality",
    "wof:population":72
},
  "geometry": {"coordinates":[-98.50960000000001,21.07577],"type":"Point"}
}