{
  "type": "Feature",
  "properties": {
    "gn:admin1_code":"6",
    "gn:admin2_code":"54.0",
    "gn:asciiname":"Campo Ochenta y Cuatro",
    "gn:country_code":"MX",
    "gn:dem":2175,
    "gn:feature_class":"P",
    "gn:feature_code":"PPL",
    "gn:name":"Campo Ochenta y Cuatro",
    "gn:population":0,
    "gn:timezone":"America/Chihuahua",
    "iso:country":"MX",
    "name:spa_x_preferred":[
        "Campo Ochenta y Cuatro"
    ],
    "wof:name":"Campo Ochenta y Cuatro",
    "wof:placetype":"locality"
},
  "geometry": {"coordinates":[-106.68168,29.24387],"type":"Point"}
}