{
  "type": "Feature",
  "properties": {
    "gn:admin1_code":"5",
    "gn:admin2_code":"108",
    "gn:asciiname":"Los Alamos",
    "gn:country_code":"MX",
    "gn:dem":661,
    "gn:feature_class":"P",
    "gn:feature_code":"PPL",
    "gn:name":"Los \u00c1lamos",
    "gn:population":9,
    "gn:timezone":"America/Mexico_City",
    "iso:country":"MX",
    "name:und_x_variant":[
        "Los \u00c1lamos"
    ],
    "wof:name":"Los Alamos",
    "wof:placetype":"locality",
    "wof:population":9
},
  "geometry": {"coordinates":[-93.41194,16.17056],"type":"Point"}
}