{
  "type": "Feature",
  "properties": {
    "gn:admin1_code":"16",
    "gn:admin2_code":"58",
    "gn:asciiname":"El Durazno",
    "gn:country_code":"MX",
    "gn:dem":2234,
    "gn:feature_class":"P",
    "gn:feature_code":"PPL",
    "gn:name":"El Durazno",
    "gn:population":39,
    "gn:timezone":"America/Mexico_City",
    "iso:country":"MX",
    "wof:name":"El Durazno",
    "wof:placetype":"locality",
    "wof:population":39
},
  "geometry": {"coordinates":[-102.23472,19.37833],"type":"Point"}
}