{
  "type": "Feature",
  "properties": {
    "gn:admin1_code":"28.0",
    "gn:admin2_code":"5.0",
    "gn:asciiname":"La Jarita",
    "gn:country_code":"MX",
    "gn:dem":152,
    "gn:feature_class":"P",
    "gn:feature_code":"PPL",
    "gn:name":"La Jarita",
    "gn:population":22,
    "gn:timezone":"America/Monterrey",
    "iso:country":"MX",
    "name:spa_x_preferred":[
        "La Jarita"
    ],
    "wof:name":"La Jarita",
    "wof:placetype":"locality",
    "wof:population":22
},
  "geometry": {"coordinates":[-98.52083,24.90083],"type":"Point"}
}