{
  "type": "Feature",
  "properties": {
    "gn:admin1_code":"26",
    "gn:admin2_code":"38.0",
    "gn:asciiname":"Paredones de Viruto",
    "gn:country_code":"MX",
    "gn:dem":593,
    "gn:feature_class":"P",
    "gn:feature_code":"PPL",
    "gn:name":"Paredones de Viruto",
    "gn:population":0,
    "gn:timezone":"America/Hermosillo",
    "iso:country":"MX",
    "name:spa_x_preferred":[
        "Paredones de Viruto"
    ],
    "wof:name":"Paredones de Viruto",
    "wof:placetype":"locality"
},
  "geometry": {"coordinates":[-109.6769,29.72654],"type":"Point"}
}