{
  "type": "Feature",
  "properties": {
    "gn:admin1_code":"23.0",
    "gn:admin2_code":"4.0",
    "gn:asciiname":"Bacalar Dos",
    "gn:country_code":"MX",
    "gn:dem":19,
    "gn:feature_class":"P",
    "gn:feature_code":"PPL",
    "gn:name":"Bacalar Dos",
    "gn:population":3,
    "gn:timezone":"America/Cancun",
    "iso:country":"MX",
    "name:spa_x_preferred":[
        "Bacalar Dos"
    ],
    "wof:name":"Bacalar Dos",
    "wof:placetype":"locality",
    "wof:population":3
},
  "geometry": {"coordinates":[-88.54833000000001,18.75778],"type":"Point"}
}