{
  "type": "Feature",
  "properties": {
    "gn:admin1_code":"30",
    "gn:admin2_code":"58.0",
    "gn:asciiname":"Las Puentes",
    "gn:country_code":"MX",
    "gn:dem":136,
    "gn:feature_class":"P",
    "gn:feature_code":"PPL",
    "gn:name":"Las Puentes",
    "gn:population":0,
    "gn:timezone":"America/Mexico_City",
    "iso:country":"MX",
    "name:und_x_variant":[
        "La Puente",
        "Las Fuentes"
    ],
    "wof:name":"Las Puentes",
    "wof:placetype":"locality"
},
  "geometry": {"coordinates":[-97.99988999999999,21.04882000000001],"type":"Point"}
}