{
  "type": "Feature",
  "properties": {
    "gn:admin1_code":"20",
    "gn:admin2_code":"29.0",
    "gn:asciiname":"Barrio Moctezuma",
    "gn:country_code":"MX",
    "gn:dem":1427,
    "gn:feature_class":"P",
    "gn:feature_code":"PPL",
    "gn:name":"Barrio Moctezuma",
    "gn:population":68,
    "gn:timezone":"America/Mexico_City",
    "iso:country":"MX",
    "wof:name":"Barrio Moctezuma",
    "wof:placetype":"locality",
    "wof:population":68
},
  "geometry": {"coordinates":[-96.87111,18.17972],"type":"Point"}
}