{
  "type": "Feature",
  "properties": {
    "gn:admin1_code":"25.0",
    "gn:admin2_code":"14.0",
    "gn:asciiname":"Castaneda",
    "gn:country_code":"MX",
    "gn:dem":41,
    "gn:feature_class":"P",
    "gn:feature_code":"PPL",
    "gn:name":"Casta\u00f1eda",
    "gn:population":0,
    "gn:timezone":"America/Mazatlan",
    "iso:country":"MX",
    "wof:name":"Castaneda",
    "wof:placetype":"locality"
},
  "geometry": {"coordinates":[-105.83333,23.01667],"type":"Point"}
}