{
  "type": "Feature",
  "properties": {
    "gn:admin1_code":"30",
    "gn:admin2_code":"124.0",
    "gn:asciiname":"San Manuel",
    "gn:country_code":"MX",
    "gn:dem":179,
    "gn:feature_class":"P",
    "gn:feature_code":"PPL",
    "gn:name":"San Manuel",
    "gn:population":124,
    "gn:timezone":"America/Mexico_City",
    "iso:country":"MX",
    "name:ceb_x_preferred":[
        "San Manuel"
    ],
    "name:deu_x_preferred":[
        "San Manuel"
    ],
    "name:fra_x_preferred":[
        "San Manuel"
    ],
    "name:ilo_x_preferred":[
        "San Manuel"
    ],
    "name:ita_x_preferred":[
        "San Manuel"
    ],
    "name:nld_x_preferred":[
        "San Manuel"
    ],
    "name:por_x_preferred":[
        "San Manuel"
    ],
    "name:spa_x_preferred":[
        "San Manuel"
    ],
    "name:srp_x_preferred":[
        "\u0421\u0430\u043d \u041c\u0430\u043d\u0443\u0435\u043b"
    ],
    "name:swe_x_preferred":[
        "San Manuel"
    ],
    "name:war_x_preferred":[
        "San Manuel"
    ],
    "wof:name":"San Manuel",
    "wof:placetype":"locality",
    "wof:population":124
},
  "geometry": {"coordinates":[-97.19861,20.21333],"type":"Point"}
}