{
  "type": "Feature",
  "properties": {
    "gn:admin1_code":"6",
    "gn:admin2_code":"11.0",
    "gn:asciiname":"Los Alamos de Arrieta",
    "gn:country_code":"MX",
    "gn:dem":1536,
    "gn:feature_class":"P",
    "gn:feature_code":"PPL",
    "gn:name":"Los \u00c1lamos de Arrieta",
    "gn:population":0,
    "gn:timezone":"America/Chihuahua",
    "iso:country":"MX",
    "name:spa_x_preferred":[
        "Los \u00c1lamos de Arrieta"
    ],
    "name:und_x_variant":[
        "Los \u00c1lamos"
    ],
    "wof:name":"Los Alamos de Arrieta",
    "wof:placetype":"locality"
},
  "geometry": {"coordinates":[-104.14941,28.66421],"type":"Point"}
}