{
  "type": "Feature",
  "properties": {
    "gn:admin1_code":"21",
    "gn:admin2_code":"54.0",
    "gn:asciiname":"Unidad los Cables",
    "gn:country_code":"MX",
    "gn:dem":2195,
    "gn:feature_class":"P",
    "gn:feature_code":"PPL",
    "gn:name":"Unidad los Cables",
    "gn:population":251,
    "gn:timezone":"America/Mexico_City",
    "iso:country":"MX",
    "wof:name":"Unidad los Cables",
    "wof:placetype":"locality",
    "wof:population":251
},
  "geometry": {"coordinates":[-97.41861,19.80083],"type":"Point"}
}