{
  "type": "Feature",
  "properties": {
    "gn:admin1_code":"6",
    "gn:admin2_code":"54.0",
    "gn:asciiname":"Canon de San Miguel (Canon del Diablo)",
    "gn:country_code":"MX",
    "gn:dem":1788,
    "gn:feature_class":"P",
    "gn:feature_code":"PPL",
    "gn:name":"Ca\u00f1\u00f3n de San Miguel (Ca\u00f1\u00f3n del Diablo)",
    "gn:population":8,
    "gn:timezone":"America/Chihuahua",
    "iso:country":"MX",
    "name:und_x_variant":[
        "Ca\u00f1\u00f3n de San Miguel (Ca\u00f1\u00f3n del Diablo)"
    ],
    "wof:name":"Canon de San Miguel (Canon del Diablo)",
    "wof:placetype":"locality",
    "wof:population":8
},
  "geometry": {"coordinates":[-106.47494,28.52213],"type":"Point"}
}