{
  "type": "Feature",
  "properties": {
    "gn:admin1_code":"20.0",
    "gn:admin2_code":"263.0",
    "gn:asciiname":"El Madrono",
    "gn:country_code":"MX",
    "gn:dem":2020,
    "gn:feature_class":"P",
    "gn:feature_code":"PPL",
    "gn:name":"El Madro\u00f1o",
    "gn:population":0,
    "gn:timezone":"America/Mexico_City",
    "iso:country":"MX",
    "name:spa_x_preferred":[
        "El Madro\u00f1o"
    ],
    "wof:name":"El Madrono",
    "wof:placetype":"locality"
},
  "geometry": {"coordinates":[-96.68008,16.17069],"type":"Point"}
}