{
  "type": "Feature",
  "properties": {
    "gn:admin1_code":"30.0",
    "gn:admin2_code":"150.0",
    "gn:asciiname":"El Ojital",
    "gn:country_code":"MX",
    "gn:dem":96,
    "gn:feature_class":"P",
    "gn:feature_code":"PPL",
    "gn:name":"El Ojital",
    "gn:population":0,
    "gn:timezone":"America/Mexico_City",
    "iso:country":"MX",
    "name:spa_x_preferred":[
        "El Ojital"
    ],
    "wof:name":"El Ojital",
    "wof:placetype":"locality"
},
  "geometry": {"coordinates":[-97.7482,21.43638],"type":"Point"}
}