{
  "type": "Feature",
  "properties": {
    "gn:admin1_code":"14",
    "gn:admin2_code":"19",
    "gn:asciiname":"Las Penas",
    "gn:country_code":"MX",
    "gn:dem":1607,
    "gn:feature_class":"P",
    "gn:feature_code":"PPL",
    "gn:name":"Las Pe\u00f1as",
    "gn:population":11,
    "gn:timezone":"America/Mexico_City",
    "iso:country":"MX",
    "name:und_x_variant":[
        "Las Pe\u00f1as"
    ],
    "wof:name":"Las Penas",
    "wof:placetype":"locality",
    "wof:population":11
},
  "geometry": {"coordinates":[-103.97472,21.90194],"type":"Point"}
}