{
  "type": "Feature",
  "properties": {
    "gn:admin1_code":"14",
    "gn:admin2_code":"84.0",
    "gn:asciiname":"Trementina",
    "gn:country_code":"MX",
    "gn:dem":1691,
    "gn:feature_class":"P",
    "gn:feature_code":"PPL",
    "gn:name":"Trementina",
    "gn:population":6,
    "gn:timezone":"America/Mexico_City",
    "iso:country":"MX",
    "wof:name":"Trementina",
    "wof:placetype":"locality",
    "wof:population":6
},
  "geometry": {"coordinates":[-104.94693999999998,20.30667],"type":"Point"}
}