{
  "type": "Feature",
  "properties": {
    "gn:admin1_code":"4",
    "gn:admin2_code":"11.0",
    "gn:asciiname":"El Charro",
    "gn:country_code":"MX",
    "gn:dem":54,
    "gn:feature_class":"P",
    "gn:feature_code":"PPL",
    "gn:name":"El Charro",
    "gn:population":3,
    "gn:timezone":"America/Merida",
    "iso:country":"MX",
    "wof:name":"El Charro",
    "wof:placetype":"locality",
    "wof:population":3
},
  "geometry": {"coordinates":[-91.105,18.31667],"type":"Point"}
}