{
  "type": "Feature",
  "properties": {
    "gn:admin1_code":"2.0",
    "gn:admin2_code":"1.0",
    "gn:asciiname":"Arce (Ejido Nacionalista)",
    "gn:country_code":"MX",
    "gn:dem":5,
    "gn:feature_class":"P",
    "gn:feature_code":"PPL",
    "gn:name":"Arce (Ejido Nacionalista)",
    "gn:population":34,
    "gn:timezone":"America/Tijuana",
    "iso:country":"MX",
    "name:spa_x_preferred":[
        "Arce"
    ],
    "wof:name":"Arce (Ejido Nacionalista)",
    "wof:placetype":"locality",
    "wof:population":34
},
  "geometry": {"coordinates":[-116.59332999999999,31.74389],"type":"Point"}
}