{
  "type": "Feature",
  "properties": {
    "gn:admin1_code":"15",
    "gn:admin2_code":"60.0",
    "gn:asciiname":"La Concepcion (El Escobal)",
    "gn:country_code":"MX",
    "gn:dem":2638,
    "gn:feature_class":"P",
    "gn:feature_code":"PPL",
    "gn:name":"La Concepci\u00f3n (El Escobal)",
    "gn:population":442,
    "gn:timezone":"America/Mexico_City",
    "iso:country":"MX",
    "name:und_x_variant":[
        "La Concepci\u00f3n (El Escobal)"
    ],
    "wof:name":"La Concepcion (El Escobal)",
    "wof:placetype":"locality",
    "wof:population":442
},
  "geometry": {"coordinates":[-99.39112,19.6447],"type":"Point"}
}