{
  "type": "Feature",
  "properties": {
    "gn:admin1_code":"10.0",
    "gn:admin2_code":"12.0",
    "gn:asciiname":"Las Vegas",
    "gn:country_code":"MX",
    "gn:dem":1166,
    "gn:feature_class":"P",
    "gn:feature_code":"PPL",
    "gn:name":"Las Vegas",
    "gn:population":0,
    "gn:timezone":"America/Monterrey",
    "iso:country":"MX",
    "name:spa_x_preferred":[
        "Las Vegas"
    ],
    "wof:name":"Las Vegas",
    "wof:placetype":"locality"
},
  "geometry": {"coordinates":[-103.73088,25.45678],"type":"Point"}
}