{
  "type": "Feature",
  "properties": {
    "gn:admin1_code":"28",
    "gn:admin2_code":"22.0",
    "gn:asciiname":"El Paso de la Pita",
    "gn:country_code":"MX",
    "gn:dem":6,
    "gn:feature_class":"P",
    "gn:feature_code":"PPL",
    "gn:name":"El Paso de la Pita",
    "gn:population":0,
    "gn:timezone":"America/Matamoros",
    "iso:country":"MX",
    "name:und_x_variant":[
        "Rancho Paso de La Pita"
    ],
    "wof:name":"El Paso de la Pita",
    "wof:placetype":"locality"
},
  "geometry": {"coordinates":[-97.36696999999999,25.74093],"type":"Point"}
}