{
  "type": "Feature",
  "properties": {
    "gn:admin1_code":"6",
    "gn:admin2_code":"19",
    "gn:asciiname":"La Piedra",
    "gn:country_code":"MX",
    "gn:dem":1507,
    "gn:feature_class":"P",
    "gn:feature_code":"PPL",
    "gn:name":"La Piedra",
    "gn:population":31,
    "gn:timezone":"America/Chihuahua",
    "iso:country":"MX",
    "wof:name":"La Piedra",
    "wof:placetype":"locality",
    "wof:population":31
},
  "geometry": {"coordinates":[-106.20547999999999,28.17131],"type":"Point"}
}