{
  "type": "Feature",
  "properties": {
    "gn:admin1_code":"7",
    "gn:admin2_code":"4.0",
    "gn:asciiname":"La Terraza",
    "gn:country_code":"MX",
    "gn:dem":2122,
    "gn:feature_class":"P",
    "gn:feature_code":"PPL",
    "gn:name":"La Terraza",
    "gn:population":4,
    "gn:timezone":"America/Monterrey",
    "iso:country":"MX",
    "wof:name":"La Terraza",
    "wof:placetype":"locality",
    "wof:population":4
},
  "geometry": {"coordinates":[-100.67086,25.46226],"type":"Point"}
}