{
  "type": "Feature",
  "properties": {
    "gn:admin1_code":"6",
    "gn:admin2_code":"66.0",
    "gn:asciiname":"El Baquiachivo",
    "gn:country_code":"MX",
    "gn:dem":1838,
    "gn:feature_class":"P",
    "gn:feature_code":"PPL",
    "gn:name":"El Baquiachivo",
    "gn:population":0,
    "gn:timezone":"America/Chihuahua",
    "iso:country":"MX",
    "name:spa_x_preferred":[
        "El Baquiachivo"
    ],
    "wof:name":"El Baquiachivo",
    "wof:placetype":"locality"
},
  "geometry": {"coordinates":[-108.37694,27.74788],"type":"Point"}
}