{
  "type": "Feature",
  "properties": {
    "gn:admin1_code":"15",
    "gn:admin2_code":"93.0",
    "gn:asciiname":"San Jose Bellavista",
    "gn:country_code":"MX",
    "gn:dem":2507,
    "gn:feature_class":"P",
    "gn:feature_code":"PPL",
    "gn:name":"San Jos\u00e9 Bellavista",
    "gn:population":0,
    "gn:timezone":"America/Mexico_City",
    "iso:country":"MX",
    "name:spa_x_preferred":[
        "San Jos\u00e9 Bellavista"
    ],
    "wof:name":"San Jose Bellavista",
    "wof:placetype":"locality"
},
  "geometry": {"coordinates":[-98.78855,19.53757],"type":"Point"}
}