{
  "type": "Feature",
  "properties": {
    "gn:admin1_code":"26",
    "gn:admin2_code":"66.0",
    "gn:asciiname":"Mateboca",
    "gn:country_code":"MX",
    "gn:dem":442,
    "gn:feature_class":"P",
    "gn:feature_code":"PPL",
    "gn:name":"Mateboca",
    "gn:population":0,
    "gn:timezone":"America/Hermosillo",
    "iso:country":"MX",
    "name:und_x_variant":[
        "Matehoca",
        "Mateboca"
    ],
    "wof:name":"Mateboca",
    "wof:placetype":"locality"
},
  "geometry": {"coordinates":[-110.22691,29.46746],"type":"Point"}
}