{
  "type": "Feature",
  "properties": {
    "gn:admin1_code":"20",
    "gn:admin2_code":"294.0",
    "gn:asciiname":"Joyas de Rio Blanco",
    "gn:country_code":"MX",
    "gn:dem":2082,
    "gn:feature_class":"P",
    "gn:feature_code":"PPL",
    "gn:name":"Joyas de R\u00edo Blanco",
    "gn:population":0,
    "gn:timezone":"America/Mexico_City",
    "iso:country":"MX",
    "name:spa_x_preferred":[
        "Joyas de R\u00edo Blanco"
    ],
    "wof:name":"Joyas de Rio Blanco",
    "wof:placetype":"locality"
},
  "geometry": {"coordinates":[-96.84658,17.36466],"type":"Point"}
}