{
  "type": "Feature",
  "properties": {
    "gn:admin1_code":"17",
    "gn:admin2_code":"7.0",
    "gn:asciiname":"Colonia San Miguel Apatlaco",
    "gn:country_code":"MX",
    "gn:dem":2091,
    "gn:feature_class":"P",
    "gn:feature_code":"PPL",
    "gn:name":"Colonia San Miguel Apatlaco",
    "gn:population":54,
    "gn:timezone":"America/Mexico_City",
    "iso:country":"MX",
    "wof:name":"Colonia San Miguel Apatlaco",
    "wof:placetype":"locality",
    "wof:population":54
},
  "geometry": {"coordinates":[-99.26278000000001,18.99306],"type":"Point"}
}