{
  "type": "Feature",
  "properties": {
    "gn:admin1_code":"21",
    "gn:admin2_code":"126",
    "gn:asciiname":"Alhualazintla",
    "gn:country_code":"MX",
    "gn:dem":2221,
    "gn:feature_class":"P",
    "gn:feature_code":"PPL",
    "gn:name":"Alhualazintla",
    "gn:population":12,
    "gn:timezone":"America/Mexico_City",
    "iso:country":"MX",
    "wof:name":"Alhualazintla",
    "wof:placetype":"locality",
    "wof:population":12
},
  "geometry": {"coordinates":[-98.41861,19.06056],"type":"Point"}
}