{
  "type": "Feature",
  "properties": {
    "gn:admin1_code":"26",
    "gn:admin2_code":"17.0",
    "gn:asciiname":"Los Juncos",
    "gn:country_code":"MX",
    "gn:dem":664,
    "gn:feature_class":"P",
    "gn:feature_code":"PPL",
    "gn:name":"Los Juncos",
    "gn:population":0,
    "gn:timezone":"America/Hermosillo",
    "iso:country":"MX",
    "name:und_x_variant":[
        "Rancho Los Juncos",
        "Los Juncos"
    ],
    "wof:name":"Los Juncos",
    "wof:placetype":"locality"
},
  "geometry": {"coordinates":[-112.35809,31.3092],"type":"Point"}
}