{
  "type": "Feature",
  "properties": {
    "gn:admin1_code":"21",
    "gn:admin2_code":"156",
    "gn:asciiname":"Portezuelo Tongo",
    "gn:country_code":"MX",
    "gn:dem":2523,
    "gn:feature_class":"P",
    "gn:feature_code":"PPL",
    "gn:name":"Portezuelo Tongo",
    "gn:population":18,
    "gn:timezone":"America/Mexico_City",
    "iso:country":"MX",
    "wof:name":"Portezuelo Tongo",
    "wof:placetype":"locality",
    "wof:population":18
},
  "geometry": {"coordinates":[-97.57995,18.41046],"type":"Point"}
}