{
  "type": "Feature",
  "properties": {
    "gn:admin1_code":"6",
    "gn:admin2_code":"32.0",
    "gn:asciiname":"San Jose",
    "gn:country_code":"MX",
    "gn:dem":1670,
    "gn:feature_class":"P",
    "gn:feature_code":"PPL",
    "gn:name":"San Jos\u00e9",
    "gn:population":2,
    "gn:timezone":"America/Chihuahua",
    "iso:country":"MX",
    "wof:name":"San Jose",
    "wof:placetype":"locality",
    "wof:population":2
},
  "geometry": {"coordinates":[-105.63468,26.97571],"type":"Point"}
}