{
  "type": "Feature",
  "properties": {
    "gn:admin1_code":"1.0",
    "gn:admin2_code":"10.0",
    "gn:asciiname":"Crucero Ojo de Agua de Crucitas",
    "gn:country_code":"MX",
    "gn:dem":2020,
    "gn:feature_class":"P",
    "gn:feature_code":"PPL",
    "gn:name":"Crucero Ojo de Agua de Crucitas",
    "gn:population":0,
    "gn:timezone":"America/Mexico_City",
    "iso:country":"MX",
    "name:spa_x_preferred":[
        "Crucero Ojo de Agua de Crucitas"
    ],
    "name:spa_x_variant":[
        "El Crucero"
    ],
    "wof:name":"Crucero Ojo de Agua de Crucitas",
    "wof:placetype":"locality"
},
  "geometry": {"coordinates":[-101.97461,21.93375],"type":"Point"}
}