{
  "type": "Feature",
  "properties": {
    "gn:admin1_code":"26",
    "gn:admin2_code":"33.0",
    "gn:asciiname":"Buiyarumo",
    "gn:country_code":"MX",
    "gn:dem":9,
    "gn:feature_class":"P",
    "gn:feature_code":"PPL",
    "gn:name":"Buiyarumo",
    "gn:population":267,
    "gn:timezone":"America/Hermosillo",
    "iso:country":"MX",
    "name:spa_x_preferred":[
        "Buiyarumo"
    ],
    "wof:name":"Buiyarumo",
    "wof:placetype":"locality",
    "wof:population":267
},
  "geometry": {"coordinates":[-109.69638999999999,26.83698],"type":"Point"}
}