{
  "type": "Feature",
  "properties": {
    "gn:admin1_code":"11.0",
    "gn:admin2_code":"26.0",
    "gn:asciiname":"Tuna Agria",
    "gn:country_code":"MX",
    "gn:dem":1777,
    "gn:feature_class":"P",
    "gn:feature_code":"PPL",
    "gn:name":"Tuna Agria",
    "gn:population":0,
    "gn:timezone":"America/Mexico_City",
    "iso:country":"MX",
    "name:spa_x_preferred":[
        "Tuna Agria"
    ],
    "name:spa_x_variant":[
        "La Tuna Agria"
    ],
    "wof:name":"Tuna Agria",
    "wof:placetype":"locality"
},
  "geometry": {"coordinates":[-101.68038,20.84595],"type":"Point"}
}