{
  "type": "Feature",
  "properties": {
    "gn:admin1_code":"32",
    "gn:admin2_code":"54.0",
    "gn:asciiname":"San Antonio de la Cruz",
    "gn:country_code":"MX",
    "gn:dem":2115,
    "gn:feature_class":"P",
    "gn:feature_code":"PPL",
    "gn:name":"San Antonio de la Cruz",
    "gn:population":103,
    "gn:timezone":"America/Mexico_City",
    "iso:country":"MX",
    "name:ita_x_preferred":[
        "San Antonio La Cruz"
    ],
    "wof:name":"San Antonio de la Cruz",
    "wof:placetype":"locality",
    "wof:population":103
},
  "geometry": {"coordinates":[-101.76222,22.48194],"type":"Point"}
}