{
  "type": "Feature",
  "properties": {
    "gn:admin1_code":"20",
    "gn:admin2_code":"413",
    "gn:asciiname":"Xuchil el Alto",
    "gn:country_code":"MX",
    "gn:dem":312,
    "gn:feature_class":"P",
    "gn:feature_code":"PPL",
    "gn:name":"X\u00fachil el Alto",
    "gn:population":18,
    "gn:timezone":"America/Mexico_City",
    "iso:country":"MX",
    "name:und_x_variant":[
        "X\u00fachil el Alto"
    ],
    "wof:name":"Xuchil el Alto",
    "wof:placetype":"locality",
    "wof:population":18
},
  "geometry": {"coordinates":[-96.23,15.86],"type":"Point"}
}