{
  "type": "Feature",
  "properties": {
    "gn:admin1_code":"11.0",
    "gn:admin2_code":"2.0",
    "gn:asciiname":"San Luis de los Agustinos",
    "gn:country_code":"MX",
    "gn:dem":2247,
    "gn:feature_class":"P",
    "gn:feature_code":"PPL",
    "gn:name":"San Luis de los Agustinos",
    "gn:population":0,
    "gn:timezone":"America/Mexico_City",
    "iso:country":"MX",
    "name:spa_x_preferred":[
        "San Luis de los Agustinos"
    ],
    "name:und_x_variant":[
        "San Luis"
    ],
    "wof:name":"San Luis de los Agustinos",
    "wof:placetype":"locality"
},
  "geometry": {"coordinates":[-100.69162,20.19342],"type":"Point"}
}