{
  "type": "Feature",
  "properties": {
    "gn:admin1_code":"1",
    "gn:admin2_code":"7",
    "gn:asciiname":"La Higuera [Rancho]",
    "gn:country_code":"MX",
    "gn:dem":1918,
    "gn:feature_class":"P",
    "gn:feature_code":"PPL",
    "gn:name":"La Higuera [Rancho]",
    "gn:population":12,
    "gn:timezone":"America/Mexico_City",
    "iso:country":"MX",
    "wof:name":"La Higuera [Rancho]",
    "wof:placetype":"locality",
    "wof:population":12
},
  "geometry": {"coordinates":[-102.30389,22.16194],"type":"Point"}
}