{
  "type": "Feature",
  "properties": {
    "gn:admin1_code":"32",
    "gn:admin2_code":"31.0",
    "gn:asciiname":"San Antonito",
    "gn:country_code":"MX",
    "gn:dem":2266,
    "gn:feature_class":"P",
    "gn:feature_code":"PPL",
    "gn:name":"San Anto\u00f1ito",
    "gn:population":0,
    "gn:timezone":"America/Mexico_City",
    "iso:country":"MX",
    "name:spa_x_preferred":[
        "San Anto\u00f1ito"
    ],
    "wof:name":"San Antonito",
    "wof:placetype":"locality"
},
  "geometry": {"coordinates":[-103.56098,22.35048],"type":"Point"}
}