{
  "type": "Feature",
  "properties": {
    "gn:admin1_code":"2",
    "gn:admin2_code":"1.0",
    "gn:asciiname":"La Nopalera (El Huatamote)",
    "gn:country_code":"MX",
    "gn:dem":181,
    "gn:feature_class":"P",
    "gn:feature_code":"PPL",
    "gn:name":"La Nopalera (El Huatamote)",
    "gn:population":4,
    "gn:timezone":"America/Tijuana",
    "iso:country":"MX",
    "wof:name":"La Nopalera (El Huatamote)",
    "wof:placetype":"locality",
    "wof:population":4
},
  "geometry": {"coordinates":[-116.46639,31.71222],"type":"Point"}
}