{
  "type": "Feature",
  "properties": {
    "gn:admin1_code":"16",
    "gn:admin2_code":"10.0",
    "gn:asciiname":"La Hierbabuena",
    "gn:country_code":"MX",
    "gn:dem":564,
    "gn:feature_class":"P",
    "gn:feature_code":"PPL",
    "gn:name":"La Hierbabuena",
    "gn:population":0,
    "gn:timezone":"America/Mexico_City",
    "iso:country":"MX",
    "name:spa_x_preferred":[
        "La Hierbabuena"
    ],
    "wof:name":"La Hierbabuena",
    "wof:placetype":"locality"
},
  "geometry": {"coordinates":[-102.70878,18.23516],"type":"Point"}
}