{
  "type": "Feature",
  "properties": {
    "gn:admin1_code":"31",
    "gn:admin2_code":"58.0",
    "gn:asciiname":"Yaxcopil",
    "gn:country_code":"MX",
    "gn:dem":42,
    "gn:feature_class":"P",
    "gn:feature_code":"PPL",
    "gn:name":"Yaxcopil",
    "gn:population":0,
    "gn:timezone":"America/Merida",
    "iso:country":"MX",
    "wof:name":"Yaxcopil",
    "wof:placetype":"locality"
},
  "geometry": {"coordinates":[-88.91667,20.0625],"type":"Point"}
}