{
  "type": "Feature",
  "properties": {
    "gn:admin1_code":"12",
    "gn:admin2_code":"56.0",
    "gn:asciiname":"El Tejoruco (Tejoruco)",
    "gn:country_code":"MX",
    "gn:dem":449,
    "gn:feature_class":"P",
    "gn:feature_code":"PPL",
    "gn:name":"El Tejoruco (Tejoruco)",
    "gn:population":389,
    "gn:timezone":"America/Mexico_City",
    "iso:country":"MX",
    "wof:name":"El Tejoruco (Tejoruco)",
    "wof:placetype":"locality",
    "wof:population":389
},
  "geometry": {"coordinates":[-99.24139,16.93611],"type":"Point"}
}