{
  "type": "Feature",
  "properties": {
    "gn:admin1_code":"16",
    "gn:admin2_code":"38.0",
    "gn:asciiname":"Buena Vista",
    "gn:country_code":"MX",
    "gn:dem":320,
    "gn:feature_class":"P",
    "gn:feature_code":"PPL",
    "gn:name":"Buena Vista",
    "gn:population":64,
    "gn:timezone":"America/Mexico_City",
    "iso:country":"MX",
    "wof:name":"Buena Vista",
    "wof:placetype":"locality",
    "wof:population":64
},
  "geometry": {"coordinates":[-100.94110999999999,18.58667],"type":"Point"}
}