{
  "type": "Feature",
  "properties": {
    "gn:admin1_code":"6",
    "gn:admin2_code":"65.0",
    "gn:asciiname":"Tejabanes",
    "gn:country_code":"MX",
    "gn:dem":1838,
    "gn:feature_class":"P",
    "gn:feature_code":"PPL",
    "gn:name":"Tejabanes",
    "gn:population":2,
    "gn:timezone":"America/Chihuahua",
    "iso:country":"MX",
    "name:spa_x_preferred":[
        "Tejabanes"
    ],
    "wof:name":"Tejabanes",
    "wof:placetype":"locality",
    "wof:population":2
},
  "geometry": {"coordinates":[-108.095,27.04085],"type":"Point"}
}