{
  "type": "Feature",
  "properties": {
    "gn:admin1_code":"19.0",
    "gn:asciiname":"Las Cuarenta",
    "gn:country_code":"MX",
    "gn:dem":469,
    "gn:feature_class":"P",
    "gn:feature_code":"PPL",
    "gn:name":"Las Cuarenta",
    "gn:population":0,
    "gn:timezone":"America/Monterrey",
    "iso:country":"MX",
    "name:spa_x_preferred":[
        "Las Cuarenta"
    ],
    "wof:name":"Las Cuarenta",
    "wof:placetype":"locality"
},
  "geometry": {"coordinates":[-100.334,25.91298],"type":"Point"}
}