{
  "type": "Feature",
  "properties": {
    "gn:admin1_code":"8",
    "gn:admin2_code":"9.0",
    "gn:asciiname":"La Ceiba [Vivero]",
    "gn:country_code":"MX",
    "gn:dem":71,
    "gn:feature_class":"P",
    "gn:feature_code":"PPL",
    "gn:name":"La Ceiba [Vivero]",
    "gn:population":5,
    "gn:timezone":"America/Mexico_City",
    "iso:country":"MX",
    "wof:name":"La Ceiba [Vivero]",
    "wof:placetype":"locality",
    "wof:population":5
},
  "geometry": {"coordinates":[-103.88889,18.99194],"type":"Point"}
}