{
  "type": "Feature",
  "properties": {
    "gn:admin1_code":"32",
    "gn:admin2_code":"50.0",
    "gn:asciiname":"El Llano de las Virgenes",
    "gn:country_code":"MX",
    "gn:dem":2514,
    "gn:feature_class":"P",
    "gn:feature_code":"PPL",
    "gn:name":"El Llano de las V\u00edrgenes",
    "gn:population":331,
    "gn:timezone":"America/Mexico_City",
    "iso:country":"MX",
    "name:und_x_variant":[
        "El Llano de las V\u00edrgenes"
    ],
    "wof:name":"El Llano de las Virgenes",
    "wof:placetype":"locality",
    "wof:population":331
},
  "geometry": {"coordinates":[-102.55564,22.84307],"type":"Point"}
}