{
  "type": "Feature",
  "properties": {
    "gn:admin1_code":"14",
    "gn:admin2_code":"109.0",
    "gn:asciiname":"San Jose del Caliche (El Caliche)",
    "gn:country_code":"MX",
    "gn:dem":1812,
    "gn:feature_class":"P",
    "gn:feature_code":"PPL",
    "gn:name":"San Jos\u00e9 del Caliche (El Caliche)",
    "gn:population":1138,
    "gn:timezone":"America/Mexico_City",
    "iso:country":"MX",
    "name:und_x_variant":[
        "San Jos\u00e9 del Caliche (El Caliche)"
    ],
    "wof:name":"San Jose del Caliche (El Caliche)",
    "wof:placetype":"locality",
    "wof:population":1138
},
  "geometry": {"coordinates":[-101.93000000000001,21.12528],"type":"Point"}
}