{
  "type": "Feature",
  "properties": {
    "gn:admin1_code":"11",
    "gn:admin2_code":"25.0",
    "gn:asciiname":"Vallao de Villalobos",
    "gn:country_code":"MX",
    "gn:dem":1756,
    "gn:feature_class":"P",
    "gn:feature_code":"PPL",
    "gn:name":"Vallao de Villalobos",
    "gn:population":8,
    "gn:timezone":"America/Mexico_City",
    "iso:country":"MX",
    "wof:name":"Vallao de Villalobos",
    "wof:placetype":"locality",
    "wof:population":8
},
  "geometry": {"coordinates":[-101.88139,21.00972],"type":"Point"}
}