{
  "type": "Feature",
  "properties": {
    "gn:admin1_code":"6",
    "gn:admin2_code":"42.0",
    "gn:asciiname":"Palomas Numero Dos",
    "gn:country_code":"MX",
    "gn:dem":1540,
    "gn:feature_class":"P",
    "gn:feature_code":"PPL",
    "gn:name":"Palomas N\u00famero Dos",
    "gn:population":0,
    "gn:timezone":"America/Chihuahua",
    "iso:country":"MX",
    "name:spa_x_preferred":[
        "Palomas N\u00famero Dos"
    ],
    "name:und_x_variant":[
        "Palomas"
    ],
    "wof:name":"Palomas Numero Dos",
    "wof:placetype":"locality"
},
  "geometry": {"coordinates":[-103.68770000000001,28.76917000000001],"type":"Point"}
}