{
  "type": "Feature",
  "properties": {
    "gn:admin1_code":"5",
    "gn:admin2_code":"17",
    "gn:asciiname":"Miramar (El Tempisque)",
    "gn:country_code":"MX",
    "gn:dem":650,
    "gn:feature_class":"P",
    "gn:feature_code":"PPL",
    "gn:name":"Miramar (El Tempisque)",
    "gn:population":19,
    "gn:timezone":"America/Mexico_City",
    "iso:country":"MX",
    "wof:name":"Miramar (El Tempisque)",
    "wof:placetype":"locality",
    "wof:population":19
},
  "geometry": {"coordinates":[-93.94861,16.54111],"type":"Point"}
}