{
  "type": "Feature",
  "properties": {
    "gn:admin1_code":"30.0",
    "gn:asciiname":"Los Piales",
    "gn:country_code":"MX",
    "gn:dem":45,
    "gn:feature_class":"P",
    "gn:feature_code":"PPL",
    "gn:name":"Los Piales",
    "gn:population":0,
    "gn:timezone":"America/Mexico_City",
    "iso:country":"MX",
    "name:spa_x_preferred":[
        "Los Piales"
    ],
    "wof:name":"Los Piales",
    "wof:placetype":"locality"
},
  "geometry": {"coordinates":[-97.98522,21.85926],"type":"Point"}
}