{
  "type": "Feature",
  "properties": {
    "gn:admin1_code":"12",
    "gn:admin2_code":"66.0",
    "gn:asciiname":"Atlamajalcingo del Rio",
    "gn:country_code":"MX",
    "gn:dem":1150,
    "gn:feature_class":"P",
    "gn:feature_code":"PPL",
    "gn:name":"Atlamajalcingo del R\u00edo",
    "gn:population":1228,
    "gn:timezone":"America/Mexico_City",
    "iso:country":"MX",
    "name:und_x_variant":[
        "Atlamajalcingo del R\u00edo"
    ],
    "wof:name":"Atlamajalcingo del Rio",
    "wof:placetype":"locality",
    "wof:population":1228
},
  "geometry": {"coordinates":[-98.65555999999999,17.52667000000001],"type":"Point"}
}