{
  "type": "Feature",
  "properties": {
    "gn:admin1_code":"2",
    "gn:admin2_code":"3.0",
    "gn:asciiname":"Maclovio Herrera (Colonia Aviacion)",
    "gn:country_code":"MX",
    "gn:dem":608,
    "gn:feature_class":"P",
    "gn:feature_code":"PPL",
    "gn:name":"Maclovio Herrera (Colonia Aviaci\u00f3n)",
    "gn:population":1219,
    "gn:timezone":"America/Tijuana",
    "iso:country":"MX",
    "name:und_x_variant":[
        "Maclovio Herrera (Colonia Aviaci\u00f3n)"
    ],
    "wof:name":"Maclovio Herrera (Colonia Aviacion)",
    "wof:placetype":"locality",
    "wof:population":1219
},
  "geometry": {"coordinates":[-116.63611000000002,32.54194],"type":"Point"}
}