{
  "type": "Feature",
  "properties": {
    "gn:admin1_code":"14",
    "gn:admin2_code":"77",
    "gn:asciiname":"La Puerta Blanca",
    "gn:country_code":"MX",
    "gn:dem":1263,
    "gn:feature_class":"P",
    "gn:feature_code":"PPL",
    "gn:name":"La Puerta Blanca",
    "gn:population":16,
    "gn:timezone":"America/Mexico_City",
    "iso:country":"MX",
    "wof:name":"La Puerta Blanca",
    "wof:placetype":"locality",
    "wof:population":16
},
  "geometry": {"coordinates":[-103.85778000000001,20.49917],"type":"Point"}
}