{
  "type": "Feature",
  "properties": {
    "gn:admin1_code":"10",
    "gn:admin2_code":"39.0",
    "gn:asciiname":"La Cienega de la Casa",
    "gn:country_code":"MX",
    "gn:dem":2452,
    "gn:feature_class":"P",
    "gn:feature_code":"PPL",
    "gn:name":"La Ci\u00e9nega de la Casa",
    "gn:population":0,
    "gn:timezone":"America/Monterrey",
    "iso:country":"MX",
    "name:spa_x_preferred":[
        "La Ci\u00e9nega de la Casa"
    ],
    "wof:name":"La Cienega de la Casa",
    "wof:placetype":"locality"
},
  "geometry": {"coordinates":[-105.03908,24.6389],"type":"Point"}
}