{
  "type": "Feature",
  "properties": {
    "gn:admin1_code":"16",
    "gn:admin2_code":"52",
    "gn:asciiname":"Las Calabacillas",
    "gn:country_code":"MX",
    "gn:dem":104,
    "gn:feature_class":"P",
    "gn:feature_code":"PPL",
    "gn:name":"Las Calabacillas",
    "gn:population":19,
    "gn:timezone":"America/Mexico_City",
    "iso:country":"MX",
    "wof:name":"Las Calabacillas",
    "wof:placetype":"locality",
    "wof:population":19
},
  "geometry": {"coordinates":[-102.62667,18.11389],"type":"Point"}
}