{
  "type": "Feature",
  "properties": {
    "gn:admin1_code":"20.0",
    "gn:admin2_code":"131.0",
    "gn:asciiname":"Loech",
    "gn:country_code":"MX",
    "gn:dem":1626,
    "gn:feature_class":"P",
    "gn:feature_code":"PPL",
    "gn:name":"Loech",
    "gn:population":0,
    "gn:timezone":"America/Mexico_City",
    "iso:country":"MX",
    "name:spa_x_preferred":[
        "Loech"
    ],
    "wof:name":"Loech",
    "wof:placetype":"locality"
},
  "geometry": {"coordinates":[-96.3246,16.74921],"type":"Point"}
}