{
  "type": "Feature",
  "properties": {
    "gn:admin1_code":"14",
    "gn:admin2_code":"67.0",
    "gn:asciiname":"La Playa Grande",
    "gn:country_code":"MX",
    "gn:dem":41,
    "gn:feature_class":"P",
    "gn:feature_code":"PPL",
    "gn:name":"La Playa Grande",
    "gn:population":0,
    "gn:timezone":"America/Mexico_City",
    "iso:country":"MX",
    "name:spa_x_preferred":[
        "La Playa Grande"
    ],
    "wof:name":"La Playa Grande",
    "wof:placetype":"locality"
},
  "geometry": {"coordinates":[-105.18987,20.64997],"type":"Point"}
}