{
  "type": "Feature",
  "properties": {
    "gn:admin1_code":"4",
    "gn:admin2_code":"4.0",
    "gn:asciiname":"Ceyba Cabecera",
    "gn:country_code":"MX",
    "gn:dem":3,
    "gn:feature_class":"P",
    "gn:feature_code":"PPL",
    "gn:name":"Ceyba Cabecera",
    "gn:population":0,
    "gn:timezone":"America/Merida",
    "iso:country":"MX",
    "name:spa_x_preferred":[
        "Ceyba Cabecera"
    ],
    "name:und_x_variant":[
        "Seiba Cabecera",
        "Seybacabecera"
    ],
    "wof:name":"Ceyba Cabecera",
    "wof:placetype":"locality"
},
  "geometry": {"coordinates":[-90.57002,19.60317],"type":"Point"}
}