{
  "type": "Feature",
  "properties": {
    "gn:admin1_code":"32",
    "gn:admin2_code":"53.0",
    "gn:asciiname":"San Leonardo",
    "gn:country_code":"MX",
    "gn:dem":2145,
    "gn:feature_class":"P",
    "gn:feature_code":"PPL",
    "gn:name":"San Leonardo",
    "gn:population":57,
    "gn:timezone":"America/Mexico_City",
    "iso:country":"MX",
    "name:ceb_x_preferred":[
        "San Leonardo"
    ],
    "name:deu_x_preferred":[
        "San Leonardo"
    ],
    "name:epo_x_preferred":[
        "San Leonardo"
    ],
    "name:fra_x_preferred":[
        "San Leonardo"
    ],
    "name:hun_x_preferred":[
        "San Leonardo"
    ],
    "name:ita_x_preferred":[
        "San Leonardo"
    ],
    "name:nld_x_preferred":[
        "San Leonardo"
    ],
    "name:spa_x_preferred":[
        "San Leonardo"
    ],
    "name:srp_x_preferred":[
        "\u0421\u0430\u043d \u041b\u0435\u043e\u043d\u0430\u0440\u0434\u043e"
    ],
    "name:swe_x_preferred":[
        "San Leonardo"
    ],
    "name:war_x_preferred":[
        "San Leonardo"
    ],
    "wof:name":"San Leonardo",
    "wof:placetype":"locality",
    "wof:population":57
},
  "geometry": {"coordinates":[-101.83806,22.51],"type":"Point"}
}