{
  "type": "Feature",
  "properties": {
    "gn:admin1_code":"32",
    "gn:admin2_code":"53.0",
    "gn:asciiname":"San Leonardo",
    "gn:country_code":"MX",
    "gn:dem":2145,
    "gn:feature_class":"P",
    "gn:feature_code":"PPL",
    "gn:name":"San Leonardo",
    "gn:population":57,
    "gn:timezone":"America/Mexico_City",
    "iso:country":"MX",
    "wof:name":"San Leonardo",
    "wof:placetype":"locality",
    "wof:population":57
},
  "geometry": {"coordinates":[-101.83806,22.51],"type":"Point"}
}