{
  "type": "Feature",
  "properties": {
    "gn:admin1_code":"19.0",
    "gn:asciiname":"El Barro",
    "gn:country_code":"MX",
    "gn:dem":1892,
    "gn:feature_class":"P",
    "gn:feature_code":"PPL",
    "gn:name":"El Barro",
    "gn:population":0,
    "gn:timezone":"America/Monterrey",
    "iso:country":"MX",
    "name:spa_x_preferred":[
        "El Barro"
    ],
    "wof:name":"El Barro",
    "wof:placetype":"locality"
},
  "geometry": {"coordinates":[-99.79295,23.94652],"type":"Point"}
}