{
  "type": "Feature",
  "properties": {
    "gn:admin1_code":"5",
    "gn:admin2_code":"17.0",
    "gn:asciiname":"Piedra Azul",
    "gn:country_code":"MX",
    "gn:dem":569,
    "gn:feature_class":"P",
    "gn:feature_code":"PPL",
    "gn:name":"Piedra Azul",
    "gn:population":4,
    "gn:timezone":"America/Mexico_City",
    "iso:country":"MX",
    "wof:name":"Piedra Azul",
    "wof:placetype":"locality",
    "wof:population":4
},
  "geometry": {"coordinates":[-93.83444,16.82028],"type":"Point"}
}