{
  "type": "Feature",
  "properties": {
    "gn:admin1_code":"16",
    "gn:admin2_code":"101",
    "gn:asciiname":"La Codorniz",
    "gn:country_code":"MX",
    "gn:dem":1905,
    "gn:feature_class":"P",
    "gn:feature_code":"PPL",
    "gn:name":"La Codorniz",
    "gn:population":15,
    "gn:timezone":"America/Mexico_City",
    "iso:country":"MX",
    "wof:name":"La Codorniz",
    "wof:placetype":"locality",
    "wof:population":15
},
  "geometry": {"coordinates":[-101.03082999999999,19.51917000000001],"type":"Point"}
}