{
  "type": "Feature",
  "properties": {
    "gn:admin1_code":"6.0",
    "gn:admin2_code":"34.0",
    "gn:asciiname":"Modelo",
    "gn:country_code":"MX",
    "gn:dem":2143,
    "gn:feature_class":"P",
    "gn:feature_code":"PPL",
    "gn:name":"Modelo",
    "gn:population":0,
    "gn:timezone":"America/Chihuahua",
    "iso:country":"MX",
    "name:ceb_x_preferred":[
        "Modelo"
    ],
    "name:deu_x_preferred":[
        "Modelo"
    ],
    "name:epo_x_preferred":[
        "Modelo"
    ],
    "name:eus_x_preferred":[
        "Modelo"
    ],
    "name:fra_x_preferred":[
        "Modelo"
    ],
    "name:glg_x_preferred":[
        "Modelo"
    ],
    "name:nld_x_preferred":[
        "Modelo"
    ],
    "name:por_x_preferred":[
        "Modelo"
    ],
    "name:spa_x_preferred":[
        "Modelo"
    ],
    "name:srp_x_preferred":[
        "\u041c\u043e\u0434\u0435\u043b\u043e"
    ],
    "name:swe_x_preferred":[
        "Modelo"
    ],
    "name:und_x_variant":[
        "Ejido Modelo"
    ],
    "wof:name":"Modelo",
    "wof:placetype":"locality"
},
  "geometry": {"coordinates":[-107.82658000000001,29.84767],"type":"Point"}
}