{
  "type": "Feature",
  "properties": {
    "gn:admin1_code":"6.0",
    "gn:admin2_code":"34.0",
    "gn:asciiname":"Modelo",
    "gn:country_code":"MX",
    "gn:dem":2143,
    "gn:feature_class":"P",
    "gn:feature_code":"PPL",
    "gn:name":"Modelo",
    "gn:population":0,
    "gn:timezone":"America/Chihuahua",
    "iso:country":"MX",
    "name:spa_x_preferred":[
        "Modelo"
    ],
    "name:und_x_variant":[
        "Ejido Modelo"
    ],
    "wof:name":"Modelo",
    "wof:placetype":"locality"
},
  "geometry": {"coordinates":[-107.82658000000001,29.84767],"type":"Point"}
}