{
  "type": "Feature",
  "properties": {
    "gn:admin1_code":"19.0",
    "gn:admin2_code":"11.0",
    "gn:asciiname":"El Ochenta y Seis",
    "gn:country_code":"MX",
    "gn:dem":322,
    "gn:feature_class":"P",
    "gn:feature_code":"PPL",
    "gn:name":"El Ochenta y Seis",
    "gn:population":0,
    "gn:timezone":"America/Monterrey",
    "iso:country":"MX",
    "name:spa_x_preferred":[
        "El Ochenta y Seis"
    ],
    "wof:name":"El Ochenta y Seis",
    "wof:placetype":"locality"
},
  "geometry": {"coordinates":[-99.66063,26.01241],"type":"Point"}
}