{
  "type": "Feature",
  "properties": {
    "gn:admin1_code":"16",
    "gn:admin2_code":"97.0",
    "gn:asciiname":"Puquio",
    "gn:country_code":"MX",
    "gn:dem":423,
    "gn:feature_class":"P",
    "gn:feature_code":"PPL",
    "gn:name":"Puqu\u00edo",
    "gn:population":0,
    "gn:timezone":"America/Mexico_City",
    "iso:country":"MX",
    "name:ara_x_preferred":[
        "\u0628\u0648\u0643\u0648\u064a\u0648"
    ],
    "name:aym_x_preferred":[
        "Pukyu"
    ],
    "name:ceb_x_preferred":[
        "Puquio"
    ],
    "name:fra_x_preferred":[
        "Puquio"
    ],
    "name:ita_x_preferred":[
        "Puquio"
    ],
    "name:lit_x_preferred":[
        "Pukijas"
    ],
    "name:pol_x_preferred":[
        "Puquio"
    ],
    "name:que_x_preferred":[
        "Pukyu llaqta"
    ],
    "name:spa_x_preferred":[
        "Puqu\u00edo"
    ],
    "name:spa_x_variant":[
        "Puquio"
    ],
    "name:war_x_preferred":[
        "Puquio"
    ],
    "name:zho_x_preferred":[
        "\u666e\u57fa\u5967"
    ],
    "wof:name":"Puquio",
    "wof:placetype":"locality"
},
  "geometry": {"coordinates":[-101.24946,18.87418],"type":"Point"}
}