{
  "type": "Feature",
  "properties": {
    "gn:admin1_code":"16",
    "gn:admin2_code":"97.0",
    "gn:asciiname":"Puquio",
    "gn:country_code":"MX",
    "gn:dem":423,
    "gn:feature_class":"P",
    "gn:feature_code":"PPL",
    "gn:name":"Puqu\u00edo",
    "gn:population":0,
    "gn:timezone":"America/Mexico_City",
    "iso:country":"MX",
    "name:spa_x_preferred":[
        "Puqu\u00edo"
    ],
    "wof:name":"Puquio",
    "wof:placetype":"locality"
},
  "geometry": {"coordinates":[-101.24946,18.87418],"type":"Point"}
}