{
  "type": "Feature",
  "properties": {
    "gn:admin1_code":"14",
    "gn:admin2_code":"114.0",
    "gn:asciiname":"La Piedra Grande",
    "gn:country_code":"MX",
    "gn:dem":1356,
    "gn:feature_class":"P",
    "gn:feature_code":"PPL",
    "gn:name":"La Piedra Grande",
    "gn:population":6,
    "gn:timezone":"America/Mexico_City",
    "iso:country":"MX",
    "wof:name":"La Piedra Grande",
    "wof:placetype":"locality",
    "wof:population":6
},
  "geometry": {"coordinates":[-103.67667,20.43333],"type":"Point"}
}