{
  "type": "Feature",
  "properties": {
    "gn:admin1_code":"6",
    "gn:admin2_code":"19.0",
    "gn:asciiname":"Las Norias",
    "gn:country_code":"MX",
    "gn:dem":1505,
    "gn:feature_class":"P",
    "gn:feature_code":"PPL",
    "gn:name":"Las Norias",
    "gn:population":0,
    "gn:timezone":"America/Chihuahua",
    "iso:country":"MX",
    "name:und_x_variant":[
        "Rancho Las Norias",
        "Las Norias"
    ],
    "wof:name":"Las Norias",
    "wof:placetype":"locality"
},
  "geometry": {"coordinates":[-106.03828,28.58025],"type":"Point"}
}