{
  "type": "Feature",
  "properties": {
    "gn:admin1_code":"26",
    "gn:admin2_code":"33.0",
    "gn:asciiname":"Buiduores",
    "gn:country_code":"MX",
    "gn:dem":6,
    "gn:feature_class":"P",
    "gn:feature_code":"PPL",
    "gn:name":"Buiduores",
    "gn:population":0,
    "gn:timezone":"America/Hermosillo",
    "iso:country":"MX",
    "name:spa_x_preferred":[
        "Buiduores"
    ],
    "name:und_x_variant":[
        "Los Buivores"
    ],
    "wof:name":"Buiduores",
    "wof:placetype":"locality"
},
  "geometry": {"coordinates":[-109.71369,26.76079],"type":"Point"}
}