{
  "type": "Feature",
  "properties": {
    "gn:admin1_code":"5",
    "gn:admin2_code":"61",
    "gn:asciiname":"Carlos Velasquez Reyes",
    "gn:country_code":"MX",
    "gn:dem":1075,
    "gn:feature_class":"P",
    "gn:feature_code":"PPL",
    "gn:name":"Carlos Vel\u00e1squez Reyes",
    "gn:population":10,
    "gn:timezone":"America/Mexico_City",
    "iso:country":"MX",
    "name:und_x_variant":[
        "Carlos Vel\u00e1squez Reyes"
    ],
    "wof:name":"Carlos Velasquez Reyes",
    "wof:placetype":"locality",
    "wof:population":10
},
  "geometry": {"coordinates":[-93.31610999999999,16.76944],"type":"Point"}
}