{
  "type": "Feature",
  "properties": {
    "gn:admin1_code":"16",
    "gn:admin2_code":"111.0",
    "gn:asciiname":"Chupacato",
    "gn:country_code":"MX",
    "gn:dem":1324,
    "gn:feature_class":"P",
    "gn:feature_code":"PPL",
    "gn:name":"Chupacato",
    "gn:population":57,
    "gn:timezone":"America/Mexico_City",
    "iso:country":"MX",
    "wof:name":"Chupacato",
    "wof:placetype":"locality",
    "wof:population":57
},
  "geometry": {"coordinates":[-101.90667000000001,19.40472],"type":"Point"}
}