{
  "type": "Feature",
  "properties": {
    "gn:admin1_code":"14",
    "gn:admin2_code":"122.0",
    "gn:asciiname":"San Isidro",
    "gn:country_code":"MX",
    "gn:dem":1010,
    "gn:feature_class":"P",
    "gn:feature_code":"PPL",
    "gn:name":"San Isidro",
    "gn:population":63,
    "gn:timezone":"America/Mexico_City",
    "iso:country":"MX",
    "wof:name":"San Isidro",
    "wof:placetype":"locality",
    "wof:population":63
},
  "geometry": {"coordinates":[-103.80472,19.50333],"type":"Point"}
}