{
  "type": "Feature",
  "properties": {
    "gn:admin1_code":"28",
    "gn:admin2_code":"16.0",
    "gn:asciiname":"Carretas",
    "gn:country_code":"MX",
    "gn:dem":384,
    "gn:feature_class":"P",
    "gn:feature_code":"PPL",
    "gn:name":"Carretas",
    "gn:population":0,
    "gn:timezone":"America/Monterrey",
    "iso:country":"MX",
    "name:und_x_variant":[
        "Carreras",
        "Carretas"
    ],
    "wof:name":"Carretas",
    "wof:placetype":"locality"
},
  "geometry": {"coordinates":[-99.51875,24.22300000000001],"type":"Point"}
}