{
  "type": "Feature",
  "properties": {
    "gn:admin1_code":"31",
    "gn:admin2_code":"78.0",
    "gn:asciiname":"Montecristo",
    "gn:country_code":"MX",
    "gn:dem":9,
    "gn:feature_class":"P",
    "gn:feature_code":"PPL",
    "gn:name":"Montecristo",
    "gn:population":6,
    "gn:timezone":"America/Merida",
    "iso:country":"MX",
    "wof:name":"Montecristo",
    "wof:placetype":"locality",
    "wof:population":6
},
  "geometry": {"coordinates":[-89.13889,21.03611],"type":"Point"}
}