{
  "type": "Feature",
  "properties": {
    "gn:admin1_code":"31",
    "gn:admin2_code":"78.0",
    "gn:asciiname":"Montecristo",
    "gn:country_code":"MX",
    "gn:dem":9,
    "gn:feature_class":"P",
    "gn:feature_code":"PPL",
    "gn:name":"Montecristo",
    "gn:population":6,
    "gn:timezone":"America/Merida",
    "iso:country":"MX",
    "name:bel_x_preferred":[
        "\u041c\u0430\u043d\u0442\u044d\u043a\u0440\u044b\u0441\u0442\u0430"
    ],
    "name:cat_x_preferred":[
        "Montecristo"
    ],
    "name:ces_x_preferred":[
        "Montecristo"
    ],
    "name:dan_x_preferred":[
        "Montecristo"
    ],
    "name:deu_x_preferred":[
        "Montecristo"
    ],
    "name:ell_x_preferred":[
        "\u039c\u03bf\u03bd\u03c4\u03b5\u03ba\u03c1\u03af\u03c3\u03c4\u03bf"
    ],
    "name:epo_x_preferred":[
        "Montecristo"
    ],
    "name:est_x_preferred":[
        "Montecristo saar"
    ],
    "name:eus_x_preferred":[
        "Montecristo"
    ],
    "name:fin_x_preferred":[
        "Montecristo"
    ],
    "name:fra_x_preferred":[
        "Montecristo"
    ],
    "name:heb_x_preferred":[
        "\u05de\u05d5\u05e0\u05d8\u05e7\u05e8\u05d9\u05e1\u05d8\u05d5"
    ],
    "name:hrv_x_preferred":[
        "Montecristo"
    ],
    "name:hun_x_preferred":[
        "Montecristo"
    ],
    "name:hye_x_preferred":[
        "\u0544\u0578\u0576\u057f\u0565\u0584\u0580\u056b\u057d\u057f\u0578"
    ],
    "name:ind_x_preferred":[
        "Montecristo"
    ],
    "name:jpn_x_preferred":[
        "\u30e2\u30f3\u30c6\u30af\u30ea\u30b9\u30c8\u5cf6"
    ],
    "name:kor_x_preferred":[
        "\ubaac\ud14c\ud06c\ub9ac\uc2a4\ud1a0\uc12c"
    ],
    "name:lat_x_preferred":[
        "Oglasa"
    ],
    "name:nld_x_preferred":[
        "Montecristo"
    ],
    "name:nno_x_preferred":[
        "Montecristo"
    ],
    "name:nor_x_preferred":[
        "Montecristo"
    ],
    "name:pol_x_preferred":[
        "Montecristo"
    ],
    "name:por_x_preferred":[
        "Montecristo"
    ],
    "name:rus_x_preferred":[
        "\u041c\u043e\u043d\u0442\u0435\u043a\u0440\u0438\u0441\u0442\u043e"
    ],
    "name:srp_x_preferred":[
        "\u041c\u043e\u043d\u0442\u0435\u043a\u0440\u0438\u0441\u0442\u043e"
    ],
    "name:tam_x_preferred":[
        "\u0bae\u0bca\u0ba9\u0bcd\u0b9f\u0bc7\u0b95\u0bbf\u0bb1\u0bbf\u0bb8\u0bcd\u0b9f\u0bcb"
    ],
    "name:ukr_x_preferred":[
        "\u041c\u043e\u043d\u0442\u0435\u043a\u0440\u0456\u0441\u0442\u043e"
    ],
    "name:vie_x_preferred":[
        "\u0110\u1ea3o Montecristo"
    ],
    "name:zho_x_preferred":[
        "\u57fa\u5ea6\u5c71"
    ],
    "wof:name":"Montecristo",
    "wof:placetype":"locality",
    "wof:population":6
},
  "geometry": {"coordinates":[-89.13889,21.03611],"type":"Point"}
}