{
  "type": "Feature",
  "properties": {
    "gn:admin1_code":"30",
    "gn:admin2_code":"83.0",
    "gn:asciiname":"Ayolia",
    "gn:country_code":"MX",
    "gn:dem":280,
    "gn:feature_class":"P",
    "gn:feature_code":"PPL",
    "gn:name":"Ayolia",
    "gn:population":704,
    "gn:timezone":"America/Mexico_City",
    "iso:country":"MX",
    "name:spa_x_preferred":[
        "Ayolia"
    ],
    "wof:name":"Ayolia",
    "wof:placetype":"locality",
    "wof:population":704
},
  "geometry": {"coordinates":[-97.99028,20.83139],"type":"Point"}
}