{
  "type": "Feature",
  "properties": {
    "gn:admin1_code":"5",
    "gn:admin2_code":"107.0",
    "gn:asciiname":"Nuevo Eden",
    "gn:country_code":"MX",
    "gn:dem":652,
    "gn:feature_class":"P",
    "gn:feature_code":"PPL",
    "gn:name":"Nuevo Ed\u00e9n",
    "gn:population":93,
    "gn:timezone":"America/Mexico_City",
    "iso:country":"MX",
    "name:und_x_variant":[
        "Nuevo Ed\u00e9n"
    ],
    "wof:name":"Nuevo Eden",
    "wof:placetype":"locality",
    "wof:population":93
},
  "geometry": {"coordinates":[-93.00944,16.01028],"type":"Point"}
}