{
  "type": "Feature",
  "properties": {
    "gn:admin1_code":"13",
    "gn:admin2_code":"46.0",
    "gn:asciiname":"Cuetzontla",
    "gn:country_code":"MX",
    "gn:dem":67,
    "gn:feature_class":"P",
    "gn:feature_code":"PPL",
    "gn:name":"Cuetzontla",
    "gn:population":0,
    "gn:timezone":"America/Mexico_City",
    "iso:country":"MX",
    "wof:name":"Cuetzontla",
    "wof:placetype":"locality"
},
  "geometry": {"coordinates":[-98.53333000000001,21.35],"type":"Point"}
}