{
  "type": "Feature",
  "properties": {
    "gn:admin1_code":"17.0",
    "gn:asciiname":"La Estrada",
    "gn:country_code":"MX",
    "gn:dem":1290,
    "gn:feature_class":"P",
    "gn:feature_code":"PPL",
    "gn:name":"La Estrada",
    "gn:population":0,
    "gn:timezone":"America/Mexico_City",
    "iso:country":"MX",
    "name:spa_x_preferred":[
        "La Estrada"
    ],
    "wof:name":"La Estrada",
    "wof:placetype":"locality"
},
  "geometry": {"coordinates":[-98.92726,18.74887],"type":"Point"}
}