{
  "type": "Feature",
  "properties": {
    "gn:admin1_code":"16",
    "gn:admin2_code":"52.0",
    "gn:asciiname":"Colonia Movimiento Urbano Popular",
    "gn:country_code":"MX",
    "gn:dem":54,
    "gn:feature_class":"P",
    "gn:feature_code":"PPL",
    "gn:name":"Colonia Movimiento Urbano Popular",
    "gn:population":350,
    "gn:timezone":"America/Mexico_City",
    "iso:country":"MX",
    "wof:name":"Colonia Movimiento Urbano Popular",
    "wof:placetype":"locality",
    "wof:population":350
},
  "geometry": {"coordinates":[-102.19917,18.035],"type":"Point"}
}