{
  "type": "Feature",
  "properties": {
    "gn:admin1_code":"28",
    "gn:admin2_code":"37.0",
    "gn:asciiname":"Isla los Federales",
    "gn:country_code":"MX",
    "gn:dem":2,
    "gn:feature_class":"P",
    "gn:feature_code":"PPL",
    "gn:name":"Isla los Federales",
    "gn:population":5,
    "gn:timezone":"America/Monterrey",
    "iso:country":"MX",
    "wof:name":"Isla los Federales",
    "wof:placetype":"locality",
    "wof:population":5
},
  "geometry": {"coordinates":[-97.75583,24.07917],"type":"Point"}
}