{
  "type": "Feature",
  "properties": {
    "gn:admin1_code":"26.0",
    "gn:admin2_code":"30.0",
    "gn:asciiname":"San Salvador",
    "gn:country_code":"MX",
    "gn:dem":34,
    "gn:feature_class":"P",
    "gn:feature_code":"PPL",
    "gn:name":"San Salvador",
    "gn:population":0,
    "gn:timezone":"America/Hermosillo",
    "iso:country":"MX",
    "name:spa_x_preferred":[
        "San Salvador"
    ],
    "wof:name":"San Salvador",
    "wof:placetype":"locality"
},
  "geometry": {"coordinates":[-111.24957999999999,28.31769],"type":"Point"}
}