{
  "type": "Feature",
  "properties": {
    "gn:admin1_code":"20",
    "gn:admin2_code":"324.0",
    "gn:asciiname":"Barra de Cuatunalco",
    "gn:country_code":"MX",
    "gn:dem":17,
    "gn:feature_class":"P",
    "gn:feature_code":"PPL",
    "gn:name":"Barra de Cuatunalco",
    "gn:population":177,
    "gn:timezone":"America/Mexico_City",
    "iso:country":"MX",
    "wof:name":"Barra de Cuatunalco",
    "wof:placetype":"locality",
    "wof:population":177
},
  "geometry": {"coordinates":[-96.33861,15.68806],"type":"Point"}
}