{
  "type": "Feature",
  "properties": {
    "gn:admin1_code":"18.0",
    "gn:admin2_code":"16.0",
    "gn:asciiname":"Tecualilla",
    "gn:country_code":"MX",
    "gn:dem":2,
    "gn:feature_class":"P",
    "gn:feature_code":"PPL",
    "gn:name":"Tecualilla",
    "gn:population":5,
    "gn:timezone":"America/Mazatlan",
    "iso:country":"MX",
    "wof:name":"Tecualilla",
    "wof:placetype":"locality",
    "wof:population":5
},
  "geometry": {"coordinates":[-105.64788,22.46415],"type":"Point"}
}