{
  "type": "Feature",
  "properties": {
    "gn:admin1_code":"14",
    "gn:admin2_code":"46.0",
    "gn:asciiname":"La Cofradia",
    "gn:country_code":"MX",
    "gn:dem":1776,
    "gn:feature_class":"P",
    "gn:feature_code":"PPL",
    "gn:name":"La Cofrad\u00eda",
    "gn:population":7,
    "gn:timezone":"America/Mexico_City",
    "iso:country":"MX",
    "name:und_x_variant":[
        "La Cofrad\u00eda"
    ],
    "wof:name":"La Cofradia",
    "wof:placetype":"locality",
    "wof:population":7
},
  "geometry": {"coordinates":[-102.49583,21.18667],"type":"Point"}
}