{
  "type": "Feature",
  "properties": {
    "gn:admin1_code":"6",
    "gn:admin2_code":"17",
    "gn:asciiname":"Rancho Madrid",
    "gn:country_code":"MX",
    "gn:dem":2026,
    "gn:feature_class":"P",
    "gn:feature_code":"PPL",
    "gn:name":"Rancho Madrid",
    "gn:population":9,
    "gn:timezone":"America/Chihuahua",
    "iso:country":"MX",
    "wof:name":"Rancho Madrid",
    "wof:placetype":"locality",
    "wof:population":9
},
  "geometry": {"coordinates":[-106.90967000000001,28.75712],"type":"Point"}
}