{
  "type": "Feature",
  "properties": {
    "gn:admin1_code":"13",
    "gn:admin2_code":"45.0",
    "gn:asciiname":"Manuel Teniente (El Llano)",
    "gn:country_code":"MX",
    "gn:dem":2547,
    "gn:feature_class":"P",
    "gn:feature_code":"PPL",
    "gn:name":"Manuel Teniente (El Llano)",
    "gn:population":175,
    "gn:timezone":"America/Mexico_City",
    "iso:country":"MX",
    "name:spa_x_preferred":[
        "Manuel"
    ],
    "wof:name":"Manuel Teniente (El Llano)",
    "wof:placetype":"locality",
    "wof:population":175
},
  "geometry": {"coordinates":[-98.62582999999999,20.18194],"type":"Point"}
}