{
  "type": "Feature",
  "properties": {
    "iso:country":"MX",
    "qs_pg:aaroncc":"MX",
    "qs_pg:name":"Fracc Villas Fortuna",
    "qs_pg:name_adm0":"M\u00e9xico",
    "qs_pg:name_adm1":"Mexico",
    "qs_pg:photos":30,
    "qs_pg:photos_1k":6,
    "qs_pg:photos_9k":1,
    "qs_pg:photos_9r":2,
    "qs_pg:photos_all":30,
    "qs_pg:photos_sr":2,
    "qs_pg:pop_sr":0,
    "qs_pg:qs_pg_placetype":"neighbourhood",
    "qs_pg:qs_pg_placetype_gp":"Suburb",
    "qs_pg:woe_adm0":23424900,
    "woe:adm0_id":23424900,
    "woe:name_adm0":"M\u00e9xico",
    "woe:name_adm1":"Mexico",
    "woe:placetype":"Suburb",
    "wof:name":"Fracc Villas Fortuna",
    "wof:placetype":"neighbourhood"
},
  "geometry": {"coordinates":[-99.22778599999999,19.604327],"type":"Point"}
}