{
  "type": "Feature",
  "properties": {
    "gn:admin1_code":"6",
    "gn:admin2_code":"17",
    "gn:asciiname":"Kilometro Nueve Carretera la Junta",
    "gn:country_code":"MX",
    "gn:dem":2128,
    "gn:feature_class":"P",
    "gn:feature_code":"PPL",
    "gn:name":"Kil\u00f3metro Nueve Carretera la Junta",
    "gn:population":28,
    "gn:timezone":"America/Chihuahua",
    "iso:country":"MX",
    "name:und_x_variant":[
        "Kil\u00f3metro Nueve Carretera la Junta"
    ],
    "wof:name":"Kilometro Nueve Carretera la Junta",
    "wof:placetype":"locality",
    "wof:population":28
},
  "geometry": {"coordinates":[-106.96438000000001,28.39463],"type":"Point"}
}