{
  "type": "Feature",
  "properties": {
    "gn:admin1_code":"10",
    "gn:admin2_code":"25.0",
    "gn:asciiname":"El Aguaje",
    "gn:country_code":"MX",
    "gn:dem":1872,
    "gn:feature_class":"P",
    "gn:feature_code":"PPL",
    "gn:name":"El Aguaje",
    "gn:population":57,
    "gn:timezone":"America/Monterrey",
    "iso:country":"MX",
    "wof:name":"El Aguaje",
    "wof:placetype":"locality",
    "wof:population":57
},
  "geometry": {"coordinates":[-105.72402,26.3933],"type":"Point"}
}