{
  "type": "Feature",
  "properties": {
    "gn:admin1_code":"16",
    "gn:admin2_code":"97.0",
    "gn:asciiname":"Chiquihuitero",
    "gn:country_code":"MX",
    "gn:dem":844,
    "gn:feature_class":"P",
    "gn:feature_code":"PPL",
    "gn:name":"Chiquihuitero",
    "gn:population":0,
    "gn:timezone":"America/Mexico_City",
    "iso:country":"MX",
    "name:spa_x_preferred":[
        "Chiquihuitero"
    ],
    "wof:name":"Chiquihuitero",
    "wof:placetype":"locality"
},
  "geometry": {"coordinates":[-101.50501,18.97866],"type":"Point"}
}