{
  "type": "Feature",
  "properties": {
    "gn:admin1_code":"5",
    "gn:admin2_code":"107.0",
    "gn:asciiname":"San Martin",
    "gn:country_code":"MX",
    "gn:dem":841,
    "gn:feature_class":"P",
    "gn:feature_code":"PPL",
    "gn:name":"San Mart\u00edn",
    "gn:population":4,
    "gn:timezone":"America/Mexico_City",
    "iso:country":"MX",
    "name:und_x_variant":[
        "San Mart\u00edn"
    ],
    "wof:name":"San Martin",
    "wof:placetype":"locality",
    "wof:population":4
},
  "geometry": {"coordinates":[-93.34222,16.04861],"type":"Point"}
}