{
  "type": "Feature",
  "properties": {
    "gn:admin1_code":"6.0",
    "gn:admin2_code":"34.0",
    "gn:asciiname":"El Leon",
    "gn:country_code":"MX",
    "gn:dem":2204,
    "gn:feature_class":"P",
    "gn:feature_code":"PPL",
    "gn:name":"El Le\u00f3n",
    "gn:population":0,
    "gn:timezone":"America/Chihuahua",
    "iso:country":"MX",
    "name:spa_x_preferred":[
        "El Le\u00f3n"
    ],
    "name:und_x_variant":[
        "Barrio El Leon"
    ],
    "wof:name":"El Leon",
    "wof:placetype":"locality"
},
  "geometry": {"coordinates":[-107.88188999999998,29.59149],"type":"Point"}
}