{
  "type": "Feature",
  "properties": {
    "gn:admin1_code":"12",
    "gn:admin2_code":"61.0",
    "gn:asciiname":"La Villita",
    "gn:country_code":"MX",
    "gn:dem":1027,
    "gn:feature_class":"P",
    "gn:feature_code":"PPL",
    "gn:name":"La Villita",
    "gn:population":219,
    "gn:timezone":"America/Mexico_City",
    "iso:country":"MX",
    "wof:name":"La Villita",
    "wof:placetype":"locality",
    "wof:population":219
},
  "geometry": {"coordinates":[-99.37344,17.47889],"type":"Point"}
}