{
  "type": "Feature",
  "properties": {
    "gn:admin1_code":"3",
    "gn:admin2_code":"1.0",
    "gn:asciiname":"Los Pajaros",
    "gn:country_code":"MX",
    "gn:dem":257,
    "gn:feature_class":"P",
    "gn:feature_code":"PPL",
    "gn:name":"Los P\u00e1jaros",
    "gn:population":0,
    "gn:timezone":"America/Mazatlan",
    "iso:country":"MX",
    "name:spa_x_preferred":[
        "Los P\u00e1jaros"
    ],
    "wof:name":"Los Pajaros",
    "wof:placetype":"locality"
},
  "geometry": {"coordinates":[-112.11726000000002,26.35007],"type":"Point"}
}