{
  "type": "Feature",
  "properties": {
    "gn:admin1_code":"24",
    "gn:admin2_code":"24.0",
    "gn:asciiname":"Las Vigas",
    "gn:country_code":"MX",
    "gn:dem":920,
    "gn:feature_class":"P",
    "gn:feature_code":"PPL",
    "gn:name":"Las Vigas",
    "gn:population":0,
    "gn:timezone":"America/Mexico_City",
    "iso:country":"MX",
    "name:spa_x_preferred":[
        "Las Vigas"
    ],
    "name:und_x_variant":[
        "Vigas"
    ],
    "wof:name":"Las Vigas",
    "wof:placetype":"locality"
},
  "geometry": {"coordinates":[-99.83929000000001,21.80485],"type":"Point"}
}