{
  "type": "Feature",
  "properties": {
    "gn:admin1_code":"25",
    "gn:admin2_code":"11.0",
    "gn:asciiname":"Choipa Numero Dos",
    "gn:country_code":"MX",
    "gn:dem":35,
    "gn:feature_class":"P",
    "gn:feature_code":"PPL",
    "gn:name":"Choipa N\u00famero Dos",
    "gn:population":0,
    "gn:timezone":"America/Mazatlan",
    "iso:country":"MX",
    "name:spa_x_preferred":[
        "Choipa N\u00famero Dos"
    ],
    "wof:name":"Choipa Numero Dos",
    "wof:placetype":"locality"
},
  "geometry": {"coordinates":[-108.29767,25.63734],"type":"Point"}
}