{
  "type": "Feature",
  "properties": {
    "gn:admin1_code":"6.0",
    "gn:admin2_code":"36.0",
    "gn:asciiname":"El Consuelo",
    "gn:cc2":"MX",
    "gn:country_code":"MX",
    "gn:dem":1379,
    "gn:feature_class":"P",
    "gn:feature_code":"PPL",
    "gn:name":"El Consuelo",
    "gn:population":0,
    "gn:timezone":"America/Chihuahua",
    "iso:country":"MX",
    "name:und_x_variant":[
        "Consuelo",
        "El Consuelo"
    ],
    "wof:name":"El Consuelo",
    "wof:placetype":"locality"
},
  "geometry": {"coordinates":[-104.93333,27.1325],"type":"Point"}
}