{
  "type": "Feature",
  "properties": {
    "gn:admin1_code":"6",
    "gn:admin2_code":"49.0",
    "gn:asciiname":"El Ermitano",
    "gn:country_code":"MX",
    "gn:dem":1549,
    "gn:feature_class":"P",
    "gn:feature_code":"PPL",
    "gn:name":"El Ermita\u00f1o",
    "gn:population":0,
    "gn:timezone":"America/Chihuahua",
    "iso:country":"MX",
    "name:spa_x_preferred":[
        "El Ermita\u00f1o"
    ],
    "wof:name":"El Ermitano",
    "wof:placetype":"locality"
},
  "geometry": {"coordinates":[-106.59066,27.52497],"type":"Point"}
}