{
  "type": "Feature",
  "properties": {
    "gn:admin1_code":"7",
    "gn:admin2_code":"12.0",
    "gn:asciiname":"Los Rodriguez",
    "gn:cc2":"MX",
    "gn:country_code":"MX",
    "gn:dem":262,
    "gn:feature_class":"P",
    "gn:feature_code":"PPL",
    "gn:name":"Los Rodr\u00edguez",
    "gn:population":0,
    "gn:timezone":"America/Monterrey",
    "iso:country":"MX",
    "name:und_x_variant":[
        "Rodriguez",
        "Los Rodr\u00edguez"
    ],
    "wof:name":"Los Rodriguez",
    "wof:placetype":"locality"
},
  "geometry": {"coordinates":[-100.46666999999999,28.35],"type":"Point"}
}