{
  "type": "Feature",
  "properties": {
    "gn:admin1_code":"26.0",
    "gn:admin2_code":"29.0",
    "gn:asciiname":"General Vicente Guerrero",
    "gn:country_code":"MX",
    "gn:dem":73,
    "gn:feature_class":"P",
    "gn:feature_code":"PPL",
    "gn:name":"General Vicente Guerrero",
    "gn:population":0,
    "gn:timezone":"America/Hermosillo",
    "iso:country":"MX",
    "name:spa_x_preferred":[
        "General Vicente Guerrero"
    ],
    "wof:name":"General Vicente Guerrero",
    "wof:placetype":"locality"
},
  "geometry": {"coordinates":[-110.51288,28.08406],"type":"Point"}
}