{
  "type": "Feature",
  "properties": {
    "gn:admin1_code":"25",
    "gn:admin2_code":"12.0",
    "gn:asciiname":"San Joaquin",
    "gn:country_code":"MX",
    "gn:dem":24,
    "gn:feature_class":"P",
    "gn:feature_code":"PPL",
    "gn:name":"San Joaqu\u00edn",
    "gn:population":0,
    "gn:timezone":"America/Mazatlan",
    "iso:country":"MX",
    "name:ceb_x_preferred":[
        "San Joaquin"
    ],
    "name:deu_x_preferred":[
        "San Joaquin"
    ],
    "name:fra_x_preferred":[
        "San Joaquin"
    ],
    "name:ita_x_preferred":[
        "San Joaquin"
    ],
    "name:nds_x_preferred":[
        "San Joaquin"
    ],
    "name:nld_x_preferred":[
        "San Joaquin"
    ],
    "name:pol_x_preferred":[
        "San Joaquin"
    ],
    "name:por_x_preferred":[
        "San Joaquin"
    ],
    "name:spa_x_preferred":[
        "San Joaqu\u00edn"
    ],
    "name:swe_x_preferred":[
        "San Joaquin"
    ],
    "name:war_x_preferred":[
        "San Joaquin"
    ],
    "wof:name":"San Joaquin",
    "wof:placetype":"locality"
},
  "geometry": {"coordinates":[-106.46384,23.35774],"type":"Point"}
}