{
  "type": "Feature",
  "properties": {
    "gn:admin1_code":"6",
    "gn:admin2_code":"41.0",
    "gn:asciiname":"El Arco",
    "gn:country_code":"MX",
    "gn:dem":1981,
    "gn:feature_class":"P",
    "gn:feature_code":"PPL",
    "gn:name":"El Arco",
    "gn:population":0,
    "gn:timezone":"America/Chihuahua",
    "iso:country":"MX",
    "name:spa_x_preferred":[
        "El Arco"
    ],
    "wof:name":"El Arco",
    "wof:placetype":"locality"
},
  "geometry": {"coordinates":[-107.99460000000001,27.90011],"type":"Point"}
}