{
  "type": "Feature",
  "properties": {
    "gn:admin1_code":"2",
    "gn:admin2_code":"4.0",
    "gn:asciiname":"Isla Coronado",
    "gn:country_code":"MX",
    "gn:dem":16,
    "gn:feature_class":"P",
    "gn:feature_code":"PPL",
    "gn:name":"Isla Coronado",
    "gn:population":4,
    "gn:timezone":"America/Tijuana",
    "iso:country":"MX",
    "wof:name":"Isla Coronado",
    "wof:placetype":"locality",
    "wof:population":4
},
  "geometry": {"coordinates":[-117.26000000000001,32.4175],"type":"Point"}
}