{
  "type": "Feature",
  "properties": {
    "gn:admin1_code":"4.0",
    "gn:admin2_code":"4.0",
    "gn:asciiname":"Cantemo",
    "gn:country_code":"MX",
    "gn:dem":31,
    "gn:feature_class":"P",
    "gn:feature_code":"PPL",
    "gn:name":"Cantemo",
    "gn:population":0,
    "gn:timezone":"America/Merida",
    "iso:country":"MX",
    "name:spa_x_preferred":[
        "Cantemo"
    ],
    "wof:name":"Cantemo",
    "wof:placetype":"locality"
},
  "geometry": {"coordinates":[-90.74632,18.81103],"type":"Point"}
}