{
  "type": "Feature",
  "properties": {
    "gn:admin1_code":"30",
    "gn:admin2_code":"175",
    "gn:asciiname":"Alfredo Reyes Juarez",
    "gn:country_code":"MX",
    "gn:dem":68,
    "gn:feature_class":"P",
    "gn:feature_code":"PPL",
    "gn:name":"Alfredo Reyes Ju\u00e1rez",
    "gn:population":20,
    "gn:timezone":"America/Mexico_City",
    "iso:country":"MX",
    "name:und_x_variant":[
        "Alfredo Reyes Ju\u00e1rez"
    ],
    "wof:name":"Alfredo Reyes Juarez",
    "wof:placetype":"locality",
    "wof:population":20
},
  "geometry": {"coordinates":[-97.51639,20.55139],"type":"Point"}
}