{
  "type": "Feature",
  "properties": {
    "gn:admin1_code":"14",
    "gn:admin2_code":"75",
    "gn:asciiname":"Las Cebollas",
    "gn:country_code":"MX",
    "gn:dem":1667,
    "gn:feature_class":"P",
    "gn:feature_code":"PPL",
    "gn:name":"Las Cebollas",
    "gn:population":30,
    "gn:timezone":"America/Mazatlan",
    "iso:country":"MX",
    "wof:name":"Las Cebollas",
    "wof:placetype":"locality",
    "wof:population":30
},
  "geometry": {"coordinates":[-104.30889000000001,20.79694],"type":"Point"}
}