{
  "type": "Feature",
  "properties": {
    "gn:admin1_code":"25",
    "gn:admin2_code":"17",
    "gn:asciiname":"Las Higueritas",
    "gn:country_code":"MX",
    "gn:dem":371,
    "gn:feature_class":"P",
    "gn:feature_code":"PPL",
    "gn:name":"Las Higueritas",
    "gn:population":19,
    "gn:timezone":"America/Mazatlan",
    "iso:country":"MX",
    "wof:name":"Las Higueritas",
    "wof:placetype":"locality",
    "wof:population":19
},
  "geometry": {"coordinates":[-107.88897,26.13627],"type":"Point"}
}