{
  "type": "Feature",
  "properties": {
    "gn:admin1_code":"26.0",
    "gn:admin2_code":"29.0",
    "gn:asciiname":"Guapari",
    "gn:country_code":"MX",
    "gn:dem":75,
    "gn:feature_class":"P",
    "gn:feature_code":"PPL",
    "gn:name":"Gu\u00e1pari",
    "gn:population":0,
    "gn:timezone":"America/Hermosillo",
    "iso:country":"MX",
    "name:spa_x_preferred":[
        "Gu\u00e1pari"
    ],
    "name:und_x_variant":[
        "Guapare"
    ],
    "wof:name":"Guapari",
    "wof:placetype":"locality"
},
  "geometry": {"coordinates":[-110.28192,27.75087000000001],"type":"Point"}
}