{
  "type": "Feature",
  "properties": {
    "gn:admin1_code":"6.0",
    "gn:asciiname":"El Papalote",
    "gn:country_code":"MX",
    "gn:dem":1741,
    "gn:feature_class":"P",
    "gn:feature_code":"PPL",
    "gn:name":"El Papalote",
    "gn:population":0,
    "gn:timezone":"America/Chihuahua",
    "iso:country":"MX",
    "name:spa_x_preferred":[
        "El Papalote"
    ],
    "name:spa_x_variant":[
        "Las Mercedes"
    ],
    "wof:name":"El Papalote",
    "wof:placetype":"locality"
},
  "geometry": {"coordinates":[-105.62245,26.7927],"type":"Point"}
}