{
  "type": "Feature",
  "properties": {
    "gn:admin1_code":"6.0",
    "gn:admin2_code":"19.0",
    "gn:asciiname":"La Cendradita",
    "gn:country_code":"MX",
    "gn:dem":1695,
    "gn:feature_class":"P",
    "gn:feature_code":"PPL",
    "gn:name":"La Cendradita",
    "gn:population":0,
    "gn:timezone":"America/Chihuahua",
    "iso:country":"MX",
    "name:spa_x_preferred":[
        "La Cendradita"
    ],
    "name:spa_x_variant":[
        "Colonia Hidalgo"
    ],
    "name:und_x_variant":[
        "Rancho La Cendrada",
        "La Cendrada"
    ],
    "wof:name":"La Cendradita",
    "wof:placetype":"locality"
},
  "geometry": {"coordinates":[-106.35135,28.93669],"type":"Point"}
}