{
  "type": "Feature",
  "properties": {
    "gn:admin1_code":"24",
    "gn:admin2_code":"41.0",
    "gn:asciiname":"Cebadilla",
    "gn:country_code":"MX",
    "gn:dem":77,
    "gn:feature_class":"P",
    "gn:feature_code":"PPL",
    "gn:name":"Cebadilla",
    "gn:population":0,
    "gn:timezone":"America/Mexico_City",
    "iso:country":"MX",
    "name:spa_x_preferred":[
        "Cebadilla"
    ],
    "wof:name":"Cebadilla",
    "wof:placetype":"locality"
},
  "geometry": {"coordinates":[-98.71724,21.66965],"type":"Point"}
}