{
  "type": "Feature",
  "properties": {
    "gn:admin1_code":"5",
    "gn:admin2_code":"61.0",
    "gn:asciiname":"Piedra Parada",
    "gn:country_code":"MX",
    "gn:dem":826,
    "gn:feature_class":"P",
    "gn:feature_code":"PPL",
    "gn:name":"Piedra Parada",
    "gn:population":501,
    "gn:timezone":"America/Mexico_City",
    "iso:country":"MX",
    "wof:name":"Piedra Parada",
    "wof:placetype":"locality",
    "wof:population":501
},
  "geometry": {"coordinates":[-93.43667000000001,16.82806],"type":"Point"}
}