{
  "type": "Feature",
  "properties": {
    "gn:admin1_code":"8.0",
    "gn:admin2_code":"6.0",
    "gn:asciiname":"Aquiles Serdan (Tamala)",
    "gn:country_code":"MX",
    "gn:dem":196,
    "gn:feature_class":"P",
    "gn:feature_code":"PPL",
    "gn:name":"Aquiles Serd\u00e1n (Tamala)",
    "gn:population":403,
    "gn:timezone":"America/Mexico_City",
    "iso:country":"MX",
    "wof:name":"Aquiles Serdan (Tamala)",
    "wof:placetype":"locality",
    "wof:population":403
},
  "geometry": {"coordinates":[-103.75713,19.00491],"type":"Point"}
}