{
  "type": "Feature",
  "properties": {
    "gn:admin1_code":"32",
    "gn:admin2_code":"42.0",
    "gn:asciiname":"Ojo de Agua la Batea",
    "gn:country_code":"MX",
    "gn:dem":2340,
    "gn:feature_class":"P",
    "gn:feature_code":"PPL",
    "gn:name":"Ojo de Agua la Batea",
    "gn:population":0,
    "gn:timezone":"America/Mexico_City",
    "iso:country":"MX",
    "name:spa_x_preferred":[
        "Ojo de Agua la Batea"
    ],
    "wof:name":"Ojo de Agua la Batea",
    "wof:placetype":"locality"
},
  "geometry": {"coordinates":[-103.6142,23.17893],"type":"Point"}
}