{
  "type": "Feature",
  "properties": {
    "gn:admin1_code":"11.0",
    "gn:admin2_code":"39.0",
    "gn:asciiname":"Huapango",
    "gn:country_code":"MX",
    "gn:dem":2161,
    "gn:feature_class":"P",
    "gn:feature_code":"PPL",
    "gn:name":"Huapango",
    "gn:population":0,
    "gn:timezone":"America/Mexico_City",
    "iso:country":"MX",
    "name:spa_x_preferred":[
        "Huapango"
    ],
    "wof:name":"Huapango",
    "wof:placetype":"locality"
},
  "geometry": {"coordinates":[-100.68433,20.36526],"type":"Point"}
}