{
  "type": "Feature",
  "properties": {
    "gn:admin1_code":"21",
    "gn:admin2_code":"19.0",
    "gn:asciiname":"San Jose Acatocha",
    "gn:country_code":"MX",
    "gn:dem":1873,
    "gn:feature_class":"P",
    "gn:feature_code":"PPL",
    "gn:name":"San Jos\u00e9 Acatocha",
    "gn:population":73,
    "gn:timezone":"America/Mexico_City",
    "iso:country":"MX",
    "name:und_x_variant":[
        "San Jos\u00e9 Acatocha"
    ],
    "wof:name":"San Jose Acatocha",
    "wof:placetype":"locality",
    "wof:population":73
},
  "geometry": {"coordinates":[-98.40331,18.91404],"type":"Point"}
}