{
  "type": "Feature",
  "properties": {
    "gn:admin1_code":"12.0",
    "gn:admin2_code":"27.0",
    "gn:asciiname":"Zirandanganguio",
    "gn:country_code":"MX",
    "gn:dem":299,
    "gn:feature_class":"P",
    "gn:feature_code":"PPL",
    "gn:name":"Zirandanganguio",
    "gn:population":0,
    "gn:timezone":"America/Mexico_City",
    "iso:country":"MX",
    "name:spa_x_preferred":[
        "Zirandanganguio"
    ],
    "name:und_x_variant":[
        "Ziranganguio"
    ],
    "wof:name":"Zirandanganguio",
    "wof:placetype":"locality"
},
  "geometry": {"coordinates":[-100.54589,18.47394],"type":"Point"}
}