{
  "type": "Feature",
  "properties": {
    "gn:admin1_code":"21.0",
    "gn:admin2_code":"114.0",
    "gn:asciiname":"Quince de Septiembre",
    "gn:country_code":"MX",
    "gn:dem":2302,
    "gn:feature_class":"P",
    "gn:feature_code":"PPL",
    "gn:name":"Quince de Septiembre",
    "gn:population":0,
    "gn:timezone":"America/Mexico_City",
    "iso:country":"MX",
    "name:spa_x_preferred":[
        "Quince de Septiembre"
    ],
    "wof:name":"Quince de Septiembre",
    "wof:placetype":"locality"
},
  "geometry": {"coordinates":[-98.12887000000001,19.08599],"type":"Point"}
}