{
  "type": "Feature",
  "properties": {
    "gn:admin1_code":"30.0",
    "gn:admin2_code":"155.0",
    "gn:asciiname":"Zapotal",
    "gn:country_code":"MX",
    "gn:dem":132,
    "gn:feature_class":"P",
    "gn:feature_code":"PPL",
    "gn:name":"Zapotal",
    "gn:population":140,
    "gn:timezone":"America/Mexico_City",
    "iso:country":"MX",
    "name:spa_x_preferred":[
        "Zapotal"
    ],
    "wof:name":"Zapotal",
    "wof:placetype":"locality",
    "wof:population":140
},
  "geometry": {"coordinates":[-98.28917,21.30972],"type":"Point"}
}