{
  "type": "Feature",
  "properties": {
    "gn:admin1_code":"13",
    "gn:admin2_code":"44.0",
    "gn:asciiname":"Cuaxithi",
    "gn:country_code":"MX",
    "gn:dem":2343,
    "gn:feature_class":"P",
    "gn:feature_code":"PPL",
    "gn:name":"Cuaxithi",
    "gn:population":397,
    "gn:timezone":"America/Mexico_City",
    "iso:country":"MX",
    "name:spa_x_preferred":[
        "Cuaxithi"
    ],
    "wof:name":"Cuaxithi",
    "wof:placetype":"locality",
    "wof:population":397
},
  "geometry": {"coordinates":[-99.76307,20.2216],"type":"Point"}
}