{
  "type": "Feature",
  "properties": {
    "gn:admin1_code":"16",
    "gn:admin2_code":"6.0",
    "gn:asciiname":"Villa Paraiso",
    "gn:country_code":"MX",
    "gn:dem":247,
    "gn:feature_class":"P",
    "gn:feature_code":"PPL",
    "gn:name":"Villa Para\u00edso",
    "gn:population":5,
    "gn:timezone":"America/Mexico_City",
    "iso:country":"MX",
    "name:und_x_variant":[
        "Villa Para\u00edso"
    ],
    "wof:name":"Villa Paraiso",
    "wof:placetype":"locality",
    "wof:population":5
},
  "geometry": {"coordinates":[-102.4975,19.09167],"type":"Point"}
}