{
  "type": "Feature",
  "properties": {
    "gn:admin1_code":"5",
    "gn:admin2_code":"12.0",
    "gn:asciiname":"Nuevo Montecristo",
    "gn:country_code":"MX",
    "gn:dem":352,
    "gn:feature_class":"P",
    "gn:feature_code":"PPL",
    "gn:name":"Nuevo Montecristo",
    "gn:population":252,
    "gn:timezone":"America/Mexico_City",
    "iso:country":"MX",
    "wof:name":"Nuevo Montecristo",
    "wof:placetype":"locality",
    "wof:population":252
},
  "geometry": {"coordinates":[-93.30638999999999,16.93611],"type":"Point"}
}