{
  "type": "Feature",
  "properties": {
    "gn:admin1_code":"12.0",
    "gn:admin2_code":"21.0",
    "gn:asciiname":"Cahuatitan",
    "gn:country_code":"MX",
    "gn:dem":14,
    "gn:feature_class":"P",
    "gn:feature_code":"PPL",
    "gn:name":"Cahuatit\u00e1n",
    "gn:population":0,
    "gn:timezone":"America/Mexico_City",
    "iso:country":"MX",
    "name:spa_x_preferred":[
        "Cahuatit\u00e1n"
    ],
    "wof:name":"Cahuatitan",
    "wof:placetype":"locality"
},
  "geometry": {"coordinates":[-100.12354999999999,16.99462],"type":"Point"}
}