{
  "type": "Feature",
  "properties": {
    "gn:admin1_code":"30",
    "gn:admin2_code":"61.0",
    "gn:asciiname":"Ingeniero Vela",
    "gn:country_code":"MX",
    "gn:dem":25,
    "gn:feature_class":"P",
    "gn:feature_code":"PPL",
    "gn:name":"Ingeniero Vela",
    "gn:population":6,
    "gn:timezone":"America/Mexico_City",
    "iso:country":"MX",
    "wof:name":"Ingeniero Vela",
    "wof:placetype":"locality",
    "wof:population":6
},
  "geometry": {"coordinates":[-94.17917,17.78361],"type":"Point"}
}