{
  "type": "Feature",
  "properties": {
    "gn:admin1_code":"15.0",
    "gn:asciiname":"San Martin Xico",
    "gn:country_code":"MX",
    "gn:dem":2233,
    "gn:feature_class":"P",
    "gn:feature_code":"PPL",
    "gn:name":"San Mart\u00edn Xico",
    "gn:population":0,
    "gn:timezone":"America/Mexico_City",
    "iso:country":"MX",
    "name:spa_x_preferred":[
        "San Mart\u00edn Xico"
    ],
    "wof:name":"San Martin Xico",
    "wof:placetype":"locality"
},
  "geometry": {"coordinates":[-98.93855000000001,19.25315],"type":"Point"}
}