{
  "type": "Feature",
  "properties": {
    "gn:admin1_code":"16.0",
    "gn:admin2_code":"52.0",
    "gn:asciiname":"La Manzanilla",
    "gn:country_code":"MX",
    "gn:dem":9,
    "gn:feature_class":"P",
    "gn:feature_code":"PPL",
    "gn:name":"La Manzanilla",
    "gn:population":0,
    "gn:timezone":"America/Mexico_City",
    "iso:country":"MX",
    "name:spa_x_preferred":[
        "La Manzanilla"
    ],
    "name:und_x_variant":[
        "La Manzanilla Uno"
    ],
    "wof:name":"La Manzanilla",
    "wof:placetype":"locality"
},
  "geometry": {"coordinates":[-102.69029,18.06276],"type":"Point"}
}