{
  "type": "Feature",
  "properties": {
    "gn:admin1_code":"12",
    "gn:admin2_code":"21.0",
    "gn:asciiname":"Las Tranquitas",
    "gn:country_code":"MX",
    "gn:dem":25,
    "gn:feature_class":"P",
    "gn:feature_code":"PPL",
    "gn:name":"Las Tranquitas",
    "gn:population":189,
    "gn:timezone":"America/Mexico_City",
    "iso:country":"MX",
    "wof:name":"Las Tranquitas",
    "wof:placetype":"locality",
    "wof:population":189
},
  "geometry": {"coordinates":[-100.17749999999999,17.00417],"type":"Point"}
}