{
  "type": "Feature",
  "properties": {
    "gn:admin1_code":"16",
    "gn:admin2_code":"105",
    "gn:asciiname":"Las Casitas",
    "gn:country_code":"MX",
    "gn:dem":1537,
    "gn:feature_class":"P",
    "gn:feature_code":"PPL",
    "gn:name":"Las Casitas",
    "gn:population":19,
    "gn:timezone":"America/Mexico_City",
    "iso:country":"MX",
    "wof:name":"Las Casitas",
    "wof:placetype":"locality",
    "wof:population":19
},
  "geometry": {"coordinates":[-102.42306000000001,20.31806],"type":"Point"}
}