{
  "type": "Feature",
  "properties": {
    "gn:admin1_code":"12.0",
    "gn:admin2_code":"57.0",
    "gn:asciiname":"El Zacatonalito",
    "gn:country_code":"MX",
    "gn:dem":521,
    "gn:feature_class":"P",
    "gn:feature_code":"PPL",
    "gn:name":"El Zacatonalito",
    "gn:population":0,
    "gn:timezone":"America/Mexico_City",
    "iso:country":"MX",
    "name:spa_x_preferred":[
        "El Zacatonalito"
    ],
    "wof:name":"El Zacatonalito",
    "wof:placetype":"locality"
},
  "geometry": {"coordinates":[-100.69289000000001,17.45721],"type":"Point"}
}