{
  "type": "Feature",
  "properties": {
    "gn:admin1_code":"27",
    "gn:admin2_code":"17.0",
    "gn:asciiname":"Tenosique 1ra. Seccion (El Mool)",
    "gn:country_code":"MX",
    "gn:dem":16,
    "gn:feature_class":"P",
    "gn:feature_code":"PPL",
    "gn:name":"Tenosique 1ra. Secci\u00f3n (El Mool)",
    "gn:population":123,
    "gn:timezone":"America/Mexico_City",
    "iso:country":"MX",
    "name:und_x_variant":[
        "Tenosique 1ra. Secci\u00f3n (El Mool)"
    ],
    "wof:name":"Tenosique 1ra. Seccion (El Mool)",
    "wof:placetype":"locality",
    "wof:population":123
},
  "geometry": {"coordinates":[-91.41278,17.51833],"type":"Point"}
}