{
  "type": "Feature",
  "properties": {
    "gn:admin1_code":"6.0",
    "gn:asciiname":"El Mirador",
    "gn:country_code":"MX",
    "gn:dem":1590,
    "gn:feature_class":"P",
    "gn:feature_code":"PPL",
    "gn:name":"El Mirador",
    "gn:population":0,
    "gn:timezone":"America/Chihuahua",
    "iso:country":"MX",
    "name:spa_x_preferred":[
        "El Mirador"
    ],
    "wof:name":"El Mirador",
    "wof:placetype":"locality"
},
  "geometry": {"coordinates":[-105.37806999999999,26.95025],"type":"Point"}
}