{
  "type": "Feature",
  "properties": {
    "gn:admin1_code":"6",
    "gn:admin2_code":"7.0",
    "gn:asciiname":"La Cienega",
    "gn:country_code":"MX",
    "gn:dem":2387,
    "gn:feature_class":"P",
    "gn:feature_code":"PPL",
    "gn:name":"La Ci\u00e9nega",
    "gn:population":6,
    "gn:timezone":"America/Chihuahua",
    "iso:country":"MX",
    "name:und_x_variant":[
        "La Ci\u00e9nega"
    ],
    "wof:name":"La Cienega",
    "wof:placetype":"locality",
    "wof:population":6
},
  "geometry": {"coordinates":[-106.67326,26.75215],"type":"Point"}
}