{
  "type": "Feature",
  "properties": {
    "gn:admin1_code":"24",
    "gn:admin2_code":"55.0",
    "gn:asciiname":"Cerro Gordo",
    "gn:country_code":"MX",
    "gn:dem":1862,
    "gn:feature_class":"P",
    "gn:feature_code":"PPL",
    "gn:name":"Cerro Gordo",
    "gn:population":2123,
    "gn:timezone":"America/Mexico_City",
    "iso:country":"MX",
    "name:arg_x_preferred":[
        "Cerro Gordo"
    ],
    "name:ceb_x_preferred":[
        "Cerro Gordo"
    ],
    "name:deu_x_preferred":[
        "Cerro Gordo"
    ],
    "name:fra_x_preferred":[
        "Cerro Gordo"
    ],
    "name:ita_x_preferred":[
        "Cerro Gordo"
    ],
    "name:nld_x_preferred":[
        "Cerro Gordo"
    ],
    "name:pol_x_preferred":[
        "Cerro Gordo"
    ],
    "name:por_x_preferred":[
        "Cerro Gordo"
    ],
    "name:rus_x_preferred":[
        "\u0421\u0435\u0440\u0440\u043e-\u0413\u043e\u0440\u0434\u043e"
    ],
    "name:spa_x_preferred":[
        "Cerro Gordo"
    ],
    "name:srp_x_preferred":[
        "\u0421\u0435\u0440\u043e \u0413\u043e\u0440\u0434\u043e"
    ],
    "name:swe_x_preferred":[
        "Cerro Gordo"
    ],
    "name:ukr_x_preferred":[
        "\u0421\u0435\u0440\u0440\u043e-\u0413\u043e\u0440\u0434\u043e"
    ],
    "name:vol_x_preferred":[
        "Cerro Gordo"
    ],
    "wof:name":"Cerro Gordo",
    "wof:placetype":"locality",
    "wof:population":2123
},
  "geometry": {"coordinates":[-100.80661000000001,21.97448],"type":"Point"}
}