{
  "type": "Feature",
  "properties": {
    "gn:admin1_code":"5.0",
    "gn:admin2_code":"30.0",
    "gn:asciiname":"Vista Hermosa",
    "gn:country_code":"MX",
    "gn:dem":668,
    "gn:feature_class":"P",
    "gn:feature_code":"PPL",
    "gn:name":"Vista Hermosa",
    "gn:population":0,
    "gn:timezone":"America/Mexico_City",
    "iso:country":"MX",
    "name:ceb_x_preferred":[
        "Vista Hermosa"
    ],
    "name:deu_x_preferred":[
        "Vista Hermosa"
    ],
    "name:spa_x_preferred":[
        "Vista Hermosa"
    ],
    "name:swe_x_preferred":[
        "Vista Hermosa"
    ],
    "name:vie_x_preferred":[
        "Vista Hermosa"
    ],
    "wof:name":"Vista Hermosa",
    "wof:placetype":"locality"
},
  "geometry": {"coordinates":[-92.32893,15.8552],"type":"Point"}
}