{
  "type": "Feature",
  "properties": {
    "gn:admin1_code":"31",
    "gn:admin2_code":"96.0",
    "gn:asciiname":"San Fermin",
    "gn:country_code":"MX",
    "gn:dem":13,
    "gn:feature_class":"P",
    "gn:feature_code":"PPL",
    "gn:name":"San Ferm\u00edn",
    "gn:population":5,
    "gn:timezone":"America/Merida",
    "iso:country":"MX",
    "name:und_x_variant":[
        "San Ferm\u00edn"
    ],
    "wof:name":"San Fermin",
    "wof:placetype":"locality",
    "wof:population":5
},
  "geometry": {"coordinates":[-87.68028000000002,21.23333],"type":"Point"}
}