{
  "type": "Feature",
  "properties": {
    "gn:admin1_code":"30",
    "gn:admin2_code":"129.0",
    "gn:asciiname":"Rancho Ahuehueyo",
    "gn:country_code":"MX",
    "gn:dem":54,
    "gn:feature_class":"P",
    "gn:feature_code":"PPL",
    "gn:name":"Rancho Ahuehueyo",
    "gn:population":0,
    "gn:timezone":"America/Mexico_City",
    "iso:country":"MX",
    "name:spa_x_preferred":[
        "Rancho Ahuehueyo"
    ],
    "wof:name":"Rancho Ahuehueyo",
    "wof:placetype":"locality"
},
  "geometry": {"coordinates":[-98.35525,21.28007],"type":"Point"}
}