{
  "type": "Feature",
  "properties": {
    "gn:admin1_code":"12",
    "gn:admin2_code":"20.0",
    "gn:asciiname":"Tehuiskojtla",
    "gn:country_code":"MX",
    "gn:dem":1755,
    "gn:feature_class":"P",
    "gn:feature_code":"PPL",
    "gn:name":"Tehuiskojtla",
    "gn:population":288,
    "gn:timezone":"America/Mexico_City",
    "iso:country":"MX",
    "wof:name":"Tehuiskojtla",
    "wof:placetype":"locality",
    "wof:population":288
},
  "geometry": {"coordinates":[-98.67757,17.45597],"type":"Point"}
}