{
  "type": "Feature",
  "properties": {
    "gn:admin1_code":"21",
    "gn:admin2_code":"192",
    "gn:asciiname":"El Cata",
    "gn:country_code":"MX",
    "gn:dem":494,
    "gn:feature_class":"P",
    "gn:feature_code":"PPL",
    "gn:name":"El Cata",
    "gn:population":21,
    "gn:timezone":"America/Mexico_City",
    "iso:country":"MX",
    "name:ita_x_preferred":[
        "El Cata"
    ],
    "name:pol_x_preferred":[
        "El Cata"
    ],
    "name:tur_x_preferred":[
        "El Cata"
    ],
    "wof:name":"El Cata",
    "wof:placetype":"locality",
    "wof:population":21
},
  "geometry": {"coordinates":[-97.56938,20.06747],"type":"Point"}
}