{
  "type": "Feature",
  "properties": {
    "gn:admin1_code":"32",
    "gn:admin2_code":"49.0",
    "gn:asciiname":"Santa Ana de Arriba",
    "gn:country_code":"MX",
    "gn:dem":1991,
    "gn:feature_class":"P",
    "gn:feature_code":"PPL",
    "gn:name":"Santa Ana de Arriba",
    "gn:population":0,
    "gn:timezone":"America/Mexico_City",
    "iso:country":"MX",
    "name:spa_x_preferred":[
        "Santa Ana de Arriba"
    ],
    "wof:name":"Santa Ana de Arriba",
    "wof:placetype":"locality"
},
  "geometry": {"coordinates":[-103.53916,22.65894],"type":"Point"}
}