{
  "type": "Feature",
  "properties": {
    "gn:admin1_code":"10",
    "gn:admin2_code":"25",
    "gn:asciiname":"Rancho de Sosa",
    "gn:country_code":"MX",
    "gn:dem":2115,
    "gn:feature_class":"P",
    "gn:feature_code":"PPL",
    "gn:name":"Rancho de Sosa",
    "gn:population":42,
    "gn:timezone":"America/Monterrey",
    "iso:country":"MX",
    "wof:name":"Rancho de Sosa",
    "wof:placetype":"locality",
    "wof:population":42
},
  "geometry": {"coordinates":[-105.81207000000001,26.26052],"type":"Point"}
}