{
  "type": "Feature",
  "properties": {
    "gn:admin1_code":"20",
    "gn:admin2_code":"498.0",
    "gn:asciiname":"Arroyo Limon",
    "gn:country_code":"MX",
    "gn:dem":131,
    "gn:feature_class":"P",
    "gn:feature_code":"PPL",
    "gn:name":"Arroyo Lim\u00f3n",
    "gn:population":0,
    "gn:timezone":"America/Mexico_City",
    "iso:country":"MX",
    "name:spa_x_preferred":[
        "Arroyo Lim\u00f3n"
    ],
    "wof:name":"Arroyo Limon",
    "wof:placetype":"locality"
},
  "geometry": {"coordinates":[-95.52422,17.47703],"type":"Point"}
}