{
  "type": "Feature",
  "properties": {
    "gn:admin1_code":"11.0",
    "gn:admin2_code":"31.0",
    "gn:asciiname":"Sauz de Armenta",
    "gn:country_code":"MX",
    "gn:dem":1819,
    "gn:feature_class":"P",
    "gn:feature_code":"PPL",
    "gn:name":"Sauz de Armenta",
    "gn:population":0,
    "gn:timezone":"America/Mexico_City",
    "iso:country":"MX",
    "name:spa_x_preferred":[
        "Sauz de Armenta"
    ],
    "name:spa_x_variant":[
        "El Sauz de Armenta"
    ],
    "name:und_x_variant":[
        "Sauz",
        "El Sauz"
    ],
    "wof:name":"Sauz de Armenta",
    "wof:placetype":"locality"
},
  "geometry": {"coordinates":[-101.7552,20.85065],"type":"Point"}
}