{
  "type": "Feature",
  "properties": {
    "gn:admin1_code":"14.0",
    "gn:asciiname":"Presa la Garza",
    "gn:country_code":"MX",
    "gn:dem":1819,
    "gn:feature_class":"P",
    "gn:feature_code":"PPL",
    "gn:name":"Presa la Garza",
    "gn:population":0,
    "gn:timezone":"America/Mexico_City",
    "iso:country":"MX",
    "name:spa_x_preferred":[
        "Presa la Garza"
    ],
    "wof:name":"Presa la Garza",
    "wof:placetype":"locality"
},
  "geometry": {"coordinates":[-102.0604,21.21402],"type":"Point"}
}