{
  "type": "Feature",
  "properties": {
    "gn:admin1_code":"11",
    "gn:admin2_code":"30.0",
    "gn:asciiname":"El Rodeo (El Rodeo del Lindero)",
    "gn:country_code":"MX",
    "gn:dem":2153,
    "gn:feature_class":"P",
    "gn:feature_code":"PPL",
    "gn:name":"El Rodeo (El Rodeo del Lindero)",
    "gn:population":57,
    "gn:timezone":"America/Mexico_City",
    "iso:country":"MX",
    "wof:name":"El Rodeo (El Rodeo del Lindero)",
    "wof:placetype":"locality",
    "wof:population":57
},
  "geometry": {"coordinates":[-101.30249999999999,21.25556],"type":"Point"}
}