{
  "type": "Feature",
  "properties": {
    "gn:admin1_code":"14",
    "gn:admin2_code":"5",
    "gn:asciiname":"Santa Rita (El Tecuane)",
    "gn:country_code":"MX",
    "gn:dem":1016,
    "gn:feature_class":"P",
    "gn:feature_code":"PPL",
    "gn:name":"Santa Rita (El Tecuane)",
    "gn:population":10,
    "gn:timezone":"America/Mexico_City",
    "iso:country":"MX",
    "wof:name":"Santa Rita (El Tecuane)",
    "wof:placetype":"locality",
    "wof:population":10
},
  "geometry": {"coordinates":[-103.71778,20.87444],"type":"Point"}
}