{
  "type": "Feature",
  "properties": {
    "gn:admin1_code":"28.0",
    "gn:admin2_code":"34.0",
    "gn:asciiname":"Tres Hermanas",
    "gn:country_code":"MX",
    "gn:dem":175,
    "gn:feature_class":"P",
    "gn:feature_code":"PPL",
    "gn:name":"Tres Hermanas",
    "gn:population":0,
    "gn:timezone":"America/Monterrey",
    "iso:country":"MX",
    "name:spa_x_preferred":[
        "Tres Hermanas"
    ],
    "wof:name":"Tres Hermanas",
    "wof:placetype":"locality"
},
  "geometry": {"coordinates":[-99.01716999999999,24.20785],"type":"Point"}
}