{
  "type": "Feature",
  "properties": {
    "gn:admin1_code":"26",
    "gn:admin2_code":"30.0",
    "gn:asciiname":"Los Pinitos",
    "gn:country_code":"MX",
    "gn:dem":270,
    "gn:feature_class":"P",
    "gn:feature_code":"PPL",
    "gn:name":"Los Pinitos",
    "gn:population":6,
    "gn:timezone":"America/Hermosillo",
    "iso:country":"MX",
    "wof:name":"Los Pinitos",
    "wof:placetype":"locality",
    "wof:population":6
},
  "geometry": {"coordinates":[-110.88648000000001,29.23224],"type":"Point"}
}