{
  "type": "Feature",
  "properties": {
    "gn:admin1_code":"13",
    "gn:admin2_code":"26.0",
    "gn:asciiname":"Ixtlahuac",
    "gn:country_code":"MX",
    "gn:dem":359,
    "gn:feature_class":"P",
    "gn:feature_code":"PPL",
    "gn:name":"Ixtlahuac",
    "gn:population":376,
    "gn:timezone":"America/Mexico_City",
    "iso:country":"MX",
    "name:spa_x_preferred":[
        "Ixtl\u00e1huac"
    ],
    "name:spa_x_variant":[
        "Ixtlahuac"
    ],
    "wof:name":"Ixtlahuac",
    "wof:placetype":"locality",
    "wof:population":376
},
  "geometry": {"coordinates":[-98.49156000000001,20.95758],"type":"Point"}
}