{
  "type": "Feature",
  "properties": {
    "gn:admin1_code":"14",
    "gn:admin2_code":"97.0",
    "gn:asciiname":"Muyutan",
    "gn:country_code":"MX",
    "gn:dem":1585,
    "gn:feature_class":"P",
    "gn:feature_code":"PPL",
    "gn:name":"Muyut\u00e1n",
    "gn:population":88,
    "gn:timezone":"America/Mexico_City",
    "iso:country":"MX",
    "name:und_x_variant":[
        "Muyut\u00e1n"
    ],
    "wof:name":"Muyutan",
    "wof:placetype":"locality",
    "wof:population":88
},
  "geometry": {"coordinates":[-103.4375,20.43694],"type":"Point"}
}