{
  "type": "Feature",
  "properties": {
    "gn:admin1_code":"6",
    "gn:admin2_code":"61.0",
    "gn:asciiname":"Los Ojitos",
    "gn:country_code":"MX",
    "gn:dem":1587,
    "gn:feature_class":"P",
    "gn:feature_code":"PPL",
    "gn:name":"Los Ojitos",
    "gn:population":0,
    "gn:timezone":"America/Chihuahua",
    "iso:country":"MX",
    "name:spa_x_preferred":[
        "Los Ojitos"
    ],
    "wof:name":"Los Ojitos",
    "wof:placetype":"locality"
},
  "geometry": {"coordinates":[-106.32809,27.46518],"type":"Point"}
}