{
  "type": "Feature",
  "properties": {
    "gn:admin1_code":"6.0",
    "gn:admin2_code":"19.0",
    "gn:asciiname":"Guadalupe",
    "gn:country_code":"MX",
    "gn:dem":1501,
    "gn:feature_class":"P",
    "gn:feature_code":"PPL",
    "gn:name":"Guadalupe",
    "gn:population":0,
    "gn:timezone":"America/Chihuahua",
    "iso:country":"MX",
    "wof:name":"Guadalupe",
    "wof:placetype":"locality"
},
  "geometry": {"coordinates":[-106.23281,28.2018],"type":"Point"}
}