{
  "type": "Feature",
  "properties": {
    "gn:admin1_code":"16",
    "gn:admin2_code":"47",
    "gn:asciiname":"La Cienega",
    "gn:country_code":"MX",
    "gn:dem":1845,
    "gn:feature_class":"P",
    "gn:feature_code":"PPL",
    "gn:name":"La Ci\u00e9nega",
    "gn:population":17,
    "gn:timezone":"America/Mexico_City",
    "iso:country":"MX",
    "name:und_x_variant":[
        "La Ci\u00e9nega"
    ],
    "wof:name":"La Cienega",
    "wof:placetype":"locality",
    "wof:population":17
},
  "geometry": {"coordinates":[-100.52110999999999,19.49694],"type":"Point"}
}