{
  "type": "Feature",
  "properties": {
    "gn:admin1_code":"26.0",
    "gn:admin2_code":"6.0",
    "gn:asciiname":"El Pescado",
    "gn:country_code":"MX",
    "gn:dem":991,
    "gn:feature_class":"P",
    "gn:feature_code":"PPL",
    "gn:name":"El Pescado",
    "gn:population":0,
    "gn:timezone":"America/Hermosillo",
    "iso:country":"MX",
    "name:spa_x_preferred":[
        "El Pescado"
    ],
    "name:und_x_variant":[
        "Rancho el Pescado"
    ],
    "wof:name":"El Pescado",
    "wof:placetype":"locality"
},
  "geometry": {"coordinates":[-110.17695999999999,30.53304],"type":"Point"}
}