{
  "type": "Feature",
  "properties": {
    "gn:admin1_code":"11",
    "gn:admin2_code":"15",
    "gn:asciiname":"Mineral de Garrapata",
    "gn:country_code":"MX",
    "gn:dem":2125,
    "gn:feature_class":"P",
    "gn:feature_code":"PPL",
    "gn:name":"Mineral de Garrapata",
    "gn:population":10,
    "gn:timezone":"America/Mexico_City",
    "iso:country":"MX",
    "wof:name":"Mineral de Garrapata",
    "wof:placetype":"locality",
    "wof:population":10
},
  "geometry": {"coordinates":[-101.24472,21.02722],"type":"Point"}
}