{
  "type": "Feature",
  "properties": {
    "gn:admin1_code":"11",
    "gn:admin2_code":"12",
    "gn:asciiname":"San Juan de los Lopez",
    "gn:country_code":"MX",
    "gn:dem":1725,
    "gn:feature_class":"P",
    "gn:feature_code":"PPL",
    "gn:name":"San Juan de los L\u00f3pez",
    "gn:population":9,
    "gn:timezone":"America/Mexico_City",
    "iso:country":"MX",
    "name:und_x_variant":[
        "San Juan de los L\u00f3pez"
    ],
    "wof:name":"San Juan de los Lopez",
    "wof:placetype":"locality",
    "wof:population":9
},
  "geometry": {"coordinates":[-101.67806,20.64278],"type":"Point"}
}