{
  "type": "Feature",
  "properties": {
    "gn:admin1_code":"24",
    "gn:admin2_code":"37.0",
    "gn:asciiname":"La Cichilla",
    "gn:country_code":"MX",
    "gn:dem":119,
    "gn:feature_class":"P",
    "gn:feature_code":"PPL",
    "gn:name":"La Cichilla",
    "gn:population":0,
    "gn:timezone":"America/Mexico_City",
    "iso:country":"MX",
    "name:spa_x_preferred":[
        "La Cichilla"
    ],
    "name:spa_x_variant":[
        "La Cuchilla"
    ],
    "wof:name":"La Cichilla",
    "wof:placetype":"locality"
},
  "geometry": {"coordinates":[-98.72445,21.28599],"type":"Point"}
}