{
  "type": "Feature",
  "properties": {
    "gn:admin1_code":"21",
    "gn:admin2_code":"54.0",
    "gn:asciiname":"Calicanto",
    "gn:country_code":"MX",
    "gn:dem":2252,
    "gn:feature_class":"P",
    "gn:feature_code":"PPL",
    "gn:name":"Calicanto",
    "gn:population":267,
    "gn:timezone":"America/Mexico_City",
    "iso:country":"MX",
    "wof:name":"Calicanto",
    "wof:placetype":"locality",
    "wof:population":267
},
  "geometry": {"coordinates":[-97.38556,19.78833],"type":"Point"}
}