{
  "type": "Feature",
  "properties": {
    "gn:admin1_code":"14",
    "gn:admin2_code":"12.0",
    "gn:asciiname":"Los Topetes",
    "gn:country_code":"MX",
    "gn:dem":1446,
    "gn:feature_class":"P",
    "gn:feature_code":"PPL",
    "gn:name":"Los Topetes",
    "gn:population":0,
    "gn:timezone":"America/Mexico_City",
    "iso:country":"MX",
    "name:spa_x_preferred":[
        "Los Topetes"
    ],
    "name:und_x_variant":[
        "Los Topete"
    ],
    "wof:name":"Los Topetes",
    "wof:placetype":"locality"
},
  "geometry": {"coordinates":[-104.479,20.39093],"type":"Point"}
}