{
  "type": "Feature",
  "properties": {
    "gn:admin1_code":"30.0",
    "gn:admin2_code":"155.0",
    "gn:asciiname":"Por Hacer",
    "gn:country_code":"MX",
    "gn:dem":102,
    "gn:feature_class":"P",
    "gn:feature_code":"PPL",
    "gn:name":"Por Hacer",
    "gn:population":17,
    "gn:timezone":"America/Mexico_City",
    "iso:country":"MX",
    "name:spa_x_preferred":[
        "Por Hacer"
    ],
    "wof:name":"Por Hacer",
    "wof:placetype":"locality",
    "wof:population":17
},
  "geometry": {"coordinates":[-98.15035,21.54846],"type":"Point"}
}