{
  "type": "Feature",
  "properties": {
    "gn:admin1_code":"27.0",
    "gn:admin2_code":"8.0",
    "gn:asciiname":"La Parra",
    "gn:country_code":"MX",
    "gn:dem":23,
    "gn:feature_class":"P",
    "gn:feature_code":"PPL",
    "gn:name":"La Parra",
    "gn:population":0,
    "gn:timezone":"America/Mexico_City",
    "iso:country":"MX",
    "name:spa_x_preferred":[
        "La Parra"
    ],
    "wof:name":"La Parra",
    "wof:placetype":"locality"
},
  "geometry": {"coordinates":[-93.72403,17.62673999999999],"type":"Point"}
}