{
  "type": "Feature",
  "properties": {
    "gn:admin1_code":"26",
    "gn:admin2_code":"30",
    "gn:asciiname":"Union de Credito Agricola de Hermosillo",
    "gn:country_code":"MX",
    "gn:dem":81,
    "gn:feature_class":"P",
    "gn:feature_code":"PPL",
    "gn:name":"Uni\u00f3n de Cr\u00e9dito Agr\u00edcola de Hermosillo",
    "gn:population":17,
    "gn:timezone":"America/Hermosillo",
    "iso:country":"MX",
    "name:und_x_variant":[
        "Uni\u00f3n de Cr\u00e9dito Agr\u00edcola de Hermosillo"
    ],
    "wof:name":"Union de Credito Agricola de Hermosillo",
    "wof:placetype":"locality",
    "wof:population":17
},
  "geometry": {"coordinates":[-111.39111,28.82306],"type":"Point"}
}