{
  "type": "Feature",
  "properties": {
    "gn:admin1_code":"7",
    "gn:admin2_code":"4.0",
    "gn:asciiname":"La Yerbabuena",
    "gn:country_code":"MX",
    "gn:dem":2193,
    "gn:feature_class":"P",
    "gn:feature_code":"PPL",
    "gn:name":"La Yerbabuena",
    "gn:population":8,
    "gn:timezone":"America/Monterrey",
    "iso:country":"MX",
    "name:spa_x_preferred":[
        "La Yerbabuena"
    ],
    "wof:name":"La Yerbabuena",
    "wof:placetype":"locality",
    "wof:population":8
},
  "geometry": {"coordinates":[-100.47308,25.40282],"type":"Point"}
}