{
  "type": "Feature",
  "properties": {
    "gn:admin1_code":"30",
    "gn:admin2_code":"201.0",
    "gn:asciiname":"Zapotitla",
    "gn:country_code":"MX",
    "gn:dem":1286,
    "gn:feature_class":"P",
    "gn:feature_code":"PPL",
    "gn:name":"Zapotitla",
    "gn:population":155,
    "gn:timezone":"America/Mexico_City",
    "iso:country":"MX",
    "wof:name":"Zapotitla",
    "wof:placetype":"locality",
    "wof:population":155
},
  "geometry": {"coordinates":[-96.96528000000001,18.54639],"type":"Point"}
}