{
  "type": "Feature",
  "properties": {
    "gn:admin1_code":"4",
    "gn:admin2_code":"3.0",
    "gn:asciiname":"Blanca Citlally",
    "gn:country_code":"MX",
    "gn:dem":1,
    "gn:feature_class":"P",
    "gn:feature_code":"PPL",
    "gn:name":"Blanca Citlally",
    "gn:population":5,
    "gn:timezone":"America/Merida",
    "iso:country":"MX",
    "wof:name":"Blanca Citlally",
    "wof:placetype":"locality",
    "wof:population":5
},
  "geometry": {"coordinates":[-91.21917000000001,18.49972],"type":"Point"}
}