{
  "type": "Feature",
  "properties": {
    "gn:admin1_code":"17",
    "gn:admin2_code":"16",
    "gn:asciiname":"Santa Monica",
    "gn:country_code":"MX",
    "gn:dem":1829,
    "gn:feature_class":"P",
    "gn:feature_code":"PPL",
    "gn:name":"Santa M\u00f3nica",
    "gn:population":38,
    "gn:timezone":"America/Mexico_City",
    "iso:country":"MX",
    "name:und_x_variant":[
        "Santa M\u00f3nica"
    ],
    "wof:name":"Santa Monica",
    "wof:placetype":"locality",
    "wof:population":38
},
  "geometry": {"coordinates":[-98.79028,18.88028],"type":"Point"}
}