{
  "type": "Feature",
  "properties": {
    "gn:admin1_code":"30.0",
    "gn:admin2_code":"109.0",
    "gn:asciiname":"San Jorge",
    "gn:country_code":"MX",
    "gn:dem":73,
    "gn:feature_class":"P",
    "gn:feature_code":"PPL",
    "gn:name":"San Jorge",
    "gn:population":0,
    "gn:timezone":"America/Mexico_City",
    "iso:country":"MX",
    "name:spa_x_preferred":[
        "San Jorge"
    ],
    "name:spa_x_variant":[
        "La Finca"
    ],
    "wof:name":"San Jorge",
    "wof:placetype":"locality"
},
  "geometry": {"coordinates":[-96.87672000000001,20.00877],"type":"Point"}
}