{
  "type": "Feature",
  "properties": {
    "gn:admin1_code":"23",
    "gn:admin2_code":"6.0",
    "gn:asciiname":"Monte Grande",
    "gn:country_code":"MX",
    "gn:dem":128,
    "gn:feature_class":"P",
    "gn:feature_code":"PPL",
    "gn:name":"Monte Grande",
    "gn:population":6,
    "gn:timezone":"America/Cancun",
    "iso:country":"MX",
    "wof:name":"Monte Grande",
    "wof:placetype":"locality",
    "wof:population":6
},
  "geometry": {"coordinates":[-88.84801999999998,19.50919],"type":"Point"}
}