{
  "type": "Feature",
  "properties": {
    "gn:admin1_code":"30",
    "gn:admin2_code":"10.0",
    "gn:asciiname":"Cerro Gordo",
    "gn:country_code":"MX",
    "gn:dem":1343,
    "gn:feature_class":"P",
    "gn:feature_code":"PPL",
    "gn:name":"Cerro Gordo",
    "gn:population":55,
    "gn:timezone":"America/Mexico_City",
    "iso:country":"MX",
    "wof:name":"Cerro Gordo",
    "wof:placetype":"locality",
    "wof:population":55
},
  "geometry": {"coordinates":[-96.99917000000001,19.80472],"type":"Point"}
}