{
  "type": "Feature",
  "properties": {
    "gn:admin1_code":"16",
    "gn:admin2_code":"101.0",
    "gn:asciiname":"La Soledad",
    "gn:country_code":"MX",
    "gn:dem":2025,
    "gn:feature_class":"P",
    "gn:feature_code":"PPL",
    "gn:name":"La Soledad",
    "gn:population":0,
    "gn:timezone":"America/Mexico_City",
    "iso:country":"MX",
    "name:spa_x_preferred":[
        "La Soledad"
    ],
    "wof:name":"La Soledad",
    "wof:placetype":"locality"
},
  "geometry": {"coordinates":[-101.00839000000001,19.44018],"type":"Point"}
}