{
  "type": "Feature",
  "properties": {
    "gn:admin1_code":"30.0",
    "gn:admin2_code":"121.0",
    "gn:asciiname":"San Raymundo",
    "gn:country_code":"MX",
    "gn:dem":46,
    "gn:feature_class":"P",
    "gn:feature_code":"PPL",
    "gn:name":"San Raymundo",
    "gn:population":19,
    "gn:timezone":"America/Mexico_City",
    "iso:country":"MX",
    "name:spa_x_preferred":[
        "San Raymundo"
    ],
    "wof:name":"San Raymundo",
    "wof:placetype":"locality",
    "wof:population":19
},
  "geometry": {"coordinates":[-97.84028000000001,21.58917000000001],"type":"Point"}
}