{
  "type": "Feature",
  "properties": {
    "gn:admin1_code":"13",
    "gn:admin2_code":"46.0",
    "gn:asciiname":"Tatacuatitla",
    "gn:country_code":"MX",
    "gn:dem":189,
    "gn:feature_class":"P",
    "gn:feature_code":"PPL",
    "gn:name":"Tatacuatitla",
    "gn:population":0,
    "gn:timezone":"America/Mexico_City",
    "iso:country":"MX",
    "name:spa_x_preferred":[
        "Tala Cuatro"
    ],
    "name:spa_x_variant":[
        "Tatacuatitla"
    ],
    "wof:name":"Tatacuatitla",
    "wof:placetype":"locality"
},
  "geometry": {"coordinates":[-98.56368000000001,21.16736],"type":"Point"}
}