{
  "type": "Feature",
  "properties": {
    "gn:admin1_code":"2.0",
    "gn:admin2_code":"1.0",
    "gn:asciiname":"Rancho de Dios",
    "gn:country_code":"MX",
    "gn:dem":6,
    "gn:feature_class":"P",
    "gn:feature_code":"PPL",
    "gn:name":"Rancho de Dios",
    "gn:population":35,
    "gn:timezone":"America/Tijuana",
    "iso:country":"MX",
    "name:spa_x_preferred":[
        "Rancho de Dios"
    ],
    "wof:name":"Rancho de Dios",
    "wof:placetype":"locality",
    "wof:population":35
},
  "geometry": {"coordinates":[-116.60333,31.72806],"type":"Point"}
}