{
  "type": "Feature",
  "properties": {
    "gn:admin1_code":"5",
    "gn:admin2_code":"30.0",
    "gn:asciiname":"Union Buenavista",
    "gn:country_code":"MX",
    "gn:dem":1788,
    "gn:feature_class":"P",
    "gn:feature_code":"PPL",
    "gn:name":"Uni\u00f3n Buenavista",
    "gn:population":0,
    "gn:timezone":"America/Mexico_City",
    "iso:country":"MX",
    "name:spa_x_preferred":[
        "Uni\u00f3n Buenavista"
    ],
    "wof:name":"Union Buenavista",
    "wof:placetype":"locality"
},
  "geometry": {"coordinates":[-92.54416999999999,15.79527],"type":"Point"}
}