{
  "type": "Feature",
  "properties": {
    "gn:admin1_code":"19.0",
    "gn:asciiname":"San Jose del Chupadero",
    "gn:country_code":"MX",
    "gn:dem":585,
    "gn:feature_class":"P",
    "gn:feature_code":"PPL",
    "gn:name":"San Jos\u00e9 del Chupadero",
    "gn:population":0,
    "gn:timezone":"America/Monterrey",
    "iso:country":"MX",
    "name:spa_x_preferred":[
        "San Jos\u00e9 del Chupadero"
    ],
    "wof:name":"San Jose del Chupadero",
    "wof:placetype":"locality"
},
  "geometry": {"coordinates":[-100.40222,25.96646],"type":"Point"}
}