{
  "type": "Feature",
  "properties": {
    "gn:admin1_code":"18.0",
    "gn:admin2_code":"17.0",
    "gn:asciiname":"Laguna Tepic",
    "gn:cc2":"MX",
    "gn:country_code":"MX",
    "gn:dem":924,
    "gn:feature_class":"P",
    "gn:feature_code":"PPL",
    "gn:name":"Laguna Tepic",
    "gn:population":0,
    "gn:timezone":"America/Mazatlan",
    "iso:country":"MX",
    "name:und_x_variant":[
        "Tepic",
        "Laguna",
        "Laguna Tepic"
    ],
    "wof:name":"Laguna Tepic",
    "wof:placetype":"locality"
},
  "geometry": {"coordinates":[-104.88333,21.51667],"type":"Point"}
}