{
  "type": "Feature",
  "properties": {
    "gn:admin1_code":"2.0",
    "gn:admin2_code":"2.0",
    "gn:asciiname":"El Chimi (Ejido Nuevo Leon)",
    "gn:country_code":"MX",
    "gn:dem":10,
    "gn:feature_class":"P",
    "gn:feature_code":"PPL",
    "gn:name":"El Chim\u00ed (Ejido Nuevo Le\u00f3n)",
    "gn:population":106,
    "gn:timezone":"America/Tijuana",
    "iso:country":"MX",
    "name:spa_x_preferred":[
        "El Chimi"
    ],
    "wof:name":"El Chimi (Ejido Nuevo Leon)",
    "wof:placetype":"locality",
    "wof:population":106
},
  "geometry": {"coordinates":[-115.18707999999999,32.37185],"type":"Point"}
}