{
  "type": "Feature",
  "properties": {
    "gn:admin1_code":"28.0",
    "gn:admin2_code":"21.0",
    "gn:asciiname":"Santa Viviana",
    "gn:country_code":"MX",
    "gn:dem":67,
    "gn:feature_class":"P",
    "gn:feature_code":"PPL",
    "gn:name":"Santa Viviana",
    "gn:population":6,
    "gn:timezone":"America/Monterrey",
    "iso:country":"MX",
    "name:spa_x_preferred":[
        "Santa Viviana"
    ],
    "wof:name":"Santa Viviana",
    "wof:placetype":"locality",
    "wof:population":6
},
  "geometry": {"coordinates":[-98.88611,22.69056],"type":"Point"}
}