{
  "type": "Feature",
  "properties": {
    "gn:admin1_code":"12.0",
    "gn:admin2_code":"48.0",
    "gn:asciiname":"El Regadito",
    "gn:country_code":"MX",
    "gn:dem":152,
    "gn:feature_class":"P",
    "gn:feature_code":"PPL",
    "gn:name":"El Regadito",
    "gn:population":0,
    "gn:timezone":"America/Mexico_City",
    "iso:country":"MX",
    "name:spa_x_preferred":[
        "El Regadito"
    ],
    "name:und_x_variant":[
        "Regaditos"
    ],
    "wof:name":"El Regadito",
    "wof:placetype":"locality"
},
  "geometry": {"coordinates":[-101.30356999999999,17.70622000000001],"type":"Point"}
}