{
  "type": "Feature",
  "properties": {
    "gn:admin1_code":"11",
    "gn:admin2_code":"3",
    "gn:asciiname":"Rancho Tonanes",
    "gn:country_code":"MX",
    "gn:dem":2038,
    "gn:feature_class":"P",
    "gn:feature_code":"PPL",
    "gn:name":"Rancho To\u00f1anes",
    "gn:population":28,
    "gn:timezone":"America/Mexico_City",
    "iso:country":"MX",
    "name:und_x_variant":[
        "Rancho To\u00f1anes"
    ],
    "wof:name":"Rancho Tonanes",
    "wof:placetype":"locality",
    "wof:population":28
},
  "geometry": {"coordinates":[-100.65333,20.91806],"type":"Point"}
}