{
  "type": "Feature",
  "properties": {
    "gn:admin1_code":"16",
    "gn:admin2_code":"8",
    "gn:asciiname":"San Mateo (Barranca San Mateo)",
    "gn:country_code":"MX",
    "gn:dem":155,
    "gn:feature_class":"P",
    "gn:feature_code":"PPL",
    "gn:name":"San Mateo (Barranca San Mateo)",
    "gn:population":29,
    "gn:timezone":"America/Mexico_City",
    "iso:country":"MX",
    "wof:name":"San Mateo (Barranca San Mateo)",
    "wof:placetype":"locality",
    "wof:population":29
},
  "geometry": {"coordinates":[-103.46693999999999,18.51694],"type":"Point"}
}