{
  "type": "Feature",
  "properties": {
    "gn:admin1_code":"19",
    "gn:admin2_code":"17.0",
    "gn:asciiname":"CONASUPO [Almacen Rural]",
    "gn:country_code":"MX",
    "gn:dem":1881,
    "gn:feature_class":"P",
    "gn:feature_code":"PPL",
    "gn:name":"CONASUPO [Almacen Rural]",
    "gn:population":6,
    "gn:timezone":"America/Monterrey",
    "iso:country":"MX",
    "wof:name":"CONASUPO [Almacen Rural]",
    "wof:placetype":"locality",
    "wof:population":6
},
  "geometry": {"coordinates":[-100.34472,24.82729],"type":"Point"}
}