{
  "type": "Feature",
  "properties": {
    "gn:admin1_code":"30.0",
    "gn:admin2_code":"83.0",
    "gn:asciiname":"El Ojite",
    "gn:country_code":"MX",
    "gn:dem":251,
    "gn:feature_class":"P",
    "gn:feature_code":"PPL",
    "gn:name":"El Ojite",
    "gn:population":0,
    "gn:timezone":"America/Mexico_City",
    "iso:country":"MX",
    "name:spa_x_preferred":[
        "El Ojite"
    ],
    "wof:name":"El Ojite",
    "wof:placetype":"locality"
},
  "geometry": {"coordinates":[-98.09423,20.64588],"type":"Point"}
}