{
  "type": "Feature",
  "properties": {
    "gn:admin1_code":"25",
    "gn:admin2_code":"17",
    "gn:asciiname":"San Rafael",
    "gn:country_code":"MX",
    "gn:dem":50,
    "gn:feature_class":"P",
    "gn:feature_code":"PPL",
    "gn:name":"San Rafael",
    "gn:population":48,
    "gn:timezone":"America/Mazatlan",
    "iso:country":"MX",
    "name:ara_x_preferred":[
        "\u0633\u0627\u0646 \u0631\u0627\u0641\u0627\u0626\u064a\u0644"
    ],
    "name:ben_x_preferred":[
        "\u09b8\u09be\u09a8 \u09b0\u09be\u09ab\u09be\u09df\u09c7\u09b2"
    ],
    "name:ell_x_preferred":[
        "\u03a3\u03b1\u03bd \u03a1\u03b1\u03c6\u03b1\u03ad\u03bb"
    ],
    "name:heb_x_preferred":[
        "\u05e1\u05df \u05e8\u05e4\u05d0\u05dc"
    ],
    "name:hin_x_preferred":[
        "\u0938\u0948\u0928 \u0930\u093e\u092b\u093c\u0947\u0932"
    ],
    "name:hun_x_preferred":[
        "San Rafael"
    ],
    "name:ind_x_preferred":[
        "San Rafael"
    ],
    "name:ita_x_preferred":[
        "San Rafael"
    ],
    "name:jpn_x_preferred":[
        "\u30b5\u30f3\u30e9\u30d5\u30a1\u30a8\u30eb"
    ],
    "name:kor_x_preferred":[
        "\uc0b0 \ub77c\ud30c\uc5d8"
    ],
    "name:por_x_preferred":[
        "San Rafael"
    ],
    "name:rus_x_preferred":[
        "\u0421\u0430\u043d-\u0420\u0430\u0444\u0430\u044d\u043b\u044c"
    ],
    "name:spa_x_preferred":[
        "San Rafael"
    ],
    "name:srp_x_preferred":[
        "\u0421\u0430\u043d \u0420\u0430\u0444\u0430\u0435\u043b"
    ],
    "name:tur_x_preferred":[
        "San Rafael"
    ],
    "name:ukr_x_preferred":[
        "\u0421\u0430\u043d-\u0420\u0430\u0444\u0430\u0435\u043b\u044c"
    ],
    "name:urd_x_preferred":[
        "\u0633\u0627\u0646 \u0631\u0627\u0641\u0627\u0626\u0644"
    ],
    "name:vie_x_preferred":[
        "San Rafael"
    ],
    "wof:name":"San Rafael",
    "wof:placetype":"locality",
    "wof:population":48
},
  "geometry": {"coordinates":[-108.6375,25.83722],"type":"Point"}
}