{
  "type": "Feature",
  "properties": {
    "gn:admin1_code":"30.0",
    "gn:admin2_code":"78.0",
    "gn:asciiname":"Tampatel",
    "gn:country_code":"MX",
    "gn:dem":133,
    "gn:feature_class":"P",
    "gn:feature_code":"PPL",
    "gn:name":"Tampatel",
    "gn:population":72,
    "gn:timezone":"America/Mexico_City",
    "iso:country":"MX",
    "name:spa_x_preferred":[
        "Tampatel"
    ],
    "wof:name":"Tampatel",
    "wof:placetype":"locality",
    "wof:population":72
},
  "geometry": {"coordinates":[-98.05916999999999,21.295],"type":"Point"}
}