{
  "type": "Feature",
  "properties": {
    "gn:admin1_code":"6",
    "gn:admin2_code":"7.0",
    "gn:asciiname":"Cueva Pinta",
    "gn:country_code":"MX",
    "gn:dem":1987,
    "gn:feature_class":"P",
    "gn:feature_code":"PPL",
    "gn:name":"Cueva Pinta",
    "gn:population":0,
    "gn:timezone":"America/Chihuahua",
    "iso:country":"MX",
    "name:spa_x_preferred":[
        "Cueva Pinta"
    ],
    "wof:name":"Cueva Pinta",
    "wof:placetype":"locality"
},
  "geometry": {"coordinates":[-106.79136,27.04973],"type":"Point"}
}