{
  "type": "Feature",
  "properties": {
    "gn:admin1_code":"20",
    "gn:admin2_code":"37.0",
    "gn:asciiname":"Las Mesas",
    "gn:country_code":"MX",
    "gn:dem":537,
    "gn:feature_class":"P",
    "gn:feature_code":"PPL",
    "gn:name":"Las Mesas",
    "gn:population":0,
    "gn:timezone":"America/Mexico_City",
    "iso:country":"MX",
    "name:spa_x_preferred":[
        "La Mesa"
    ],
    "name:spa_x_variant":[
        "Las Mesas"
    ],
    "wof:name":"Las Mesas",
    "wof:placetype":"locality"
},
  "geometry": {"coordinates":[-97.96003,16.87956],"type":"Point"}
}