{
  "type": "Feature",
  "properties": {
    "gn:admin1_code":"31",
    "gn:admin2_code":"19.0",
    "gn:asciiname":"Chulutan",
    "gn:country_code":"MX",
    "gn:dem":24,
    "gn:feature_class":"P",
    "gn:feature_code":"PPL",
    "gn:name":"Chulutan",
    "gn:population":0,
    "gn:timezone":"America/Merida",
    "iso:country":"MX",
    "name:spa_x_preferred":[
        "Chulutan"
    ],
    "wof:name":"Chulutan",
    "wof:placetype":"locality"
},
  "geometry": {"coordinates":[-87.96275,20.56781],"type":"Point"}
}