{
  "type": "Feature",
  "properties": {
    "gn:admin1_code":"28",
    "gn:admin2_code":"18.0",
    "gn:asciiname":"Rancho Marquesotes",
    "gn:country_code":"MX",
    "gn:dem":106,
    "gn:feature_class":"P",
    "gn:feature_code":"PPL",
    "gn:name":"Rancho Marquesotes",
    "gn:population":0,
    "gn:timezone":"America/Monterrey",
    "iso:country":"MX",
    "wof:name":"Rancho Marquesotes",
    "wof:placetype":"locality"
},
  "geometry": {"coordinates":[-98.58333,24.11667000000001],"type":"Point"}
}