{
  "type": "Feature",
  "properties": {
    "gn:admin1_code":"14",
    "gn:admin2_code":"53.0",
    "gn:asciiname":"Geovillas Laureles del Campanario",
    "gn:country_code":"MX",
    "gn:dem":1872,
    "gn:feature_class":"P",
    "gn:feature_code":"PPL",
    "gn:name":"Geovillas Laureles del Campanario",
    "gn:population":1755,
    "gn:timezone":"America/Mexico_City",
    "iso:country":"MX",
    "wof:name":"Geovillas Laureles del Campanario",
    "wof:placetype":"locality",
    "wof:population":1755
},
  "geometry": {"coordinates":[-101.92361,21.33056],"type":"Point"}
}