{
  "type": "Feature",
  "properties": {
    "gn:admin1_code":"19.0",
    "gn:admin2_code":"31.0",
    "gn:asciiname":"Ciudadela",
    "gn:country_code":"MX",
    "gn:dem":460,
    "gn:feature_class":"P",
    "gn:feature_code":"PPL",
    "gn:name":"Ciudadela",
    "gn:population":0,
    "gn:timezone":"America/Monterrey",
    "iso:country":"MX",
    "name:ceb_x_preferred":[
        "Ciudadela"
    ],
    "name:deu_x_preferred":[
        "Ciudadela"
    ],
    "name:fra_x_preferred":[
        "Ciudadela"
    ],
    "name:ita_x_preferred":[
        "Ciudadela"
    ],
    "name:por_x_preferred":[
        "Ciudadela"
    ],
    "name:sco_x_preferred":[
        "Ciudadela"
    ],
    "name:spa_x_preferred":[
        "Ciudadela"
    ],
    "name:swe_x_preferred":[
        "Ciudadela"
    ],
    "name:und_x_variant":[
        "La Ciudadela",
        "Ciudadela"
    ],
    "wof:name":"Ciudadela",
    "wof:placetype":"locality"
},
  "geometry": {"coordinates":[-100.12806999999999,25.56681],"type":"Point"}
}