{
  "type": "Feature",
  "properties": {
    "gn:admin1_code":"6.0",
    "gn:admin2_code":"41.0",
    "gn:asciiname":"La Galana",
    "gn:country_code":"MX",
    "gn:dem":2495,
    "gn:feature_class":"P",
    "gn:feature_code":"PPL",
    "gn:name":"La Galana",
    "gn:population":0,
    "gn:timezone":"America/Chihuahua",
    "iso:country":"MX",
    "name:spa_x_preferred":[
        "La Galana"
    ],
    "wof:name":"La Galana",
    "wof:placetype":"locality"
},
  "geometry": {"coordinates":[-107.91013999999998,27.93657],"type":"Point"}
}