{
  "type": "Feature",
  "properties": {
    "gn:admin1_code":"16",
    "gn:admin2_code":"24.0",
    "gn:asciiname":"Copuro",
    "gn:country_code":"MX",
    "gn:dem":2347,
    "gn:feature_class":"P",
    "gn:feature_code":"PPL",
    "gn:name":"Copuro",
    "gn:population":9,
    "gn:timezone":"America/Mexico_City",
    "iso:country":"MX",
    "wof:name":"Copuro",
    "wof:placetype":"locality",
    "wof:population":9
},
  "geometry": {"coordinates":[-101.96278,19.67556],"type":"Point"}
}