{
  "type": "Feature",
  "properties": {
    "gn:admin1_code":"28.0",
    "gn:admin2_code":"8.0",
    "gn:asciiname":"Mirasol",
    "gn:country_code":"MX",
    "gn:dem":192,
    "gn:feature_class":"P",
    "gn:feature_code":"PPL",
    "gn:name":"Mirasol",
    "gn:population":1,
    "gn:timezone":"America/Monterrey",
    "iso:country":"MX",
    "name:spa_x_preferred":[
        "Mirasol"
    ],
    "wof:name":"Mirasol",
    "wof:placetype":"locality",
    "wof:population":1
},
  "geometry": {"coordinates":[-98.80211,23.50148],"type":"Point"}
}