{
  "type": "Feature",
  "properties": {
    "gn:admin1_code":"18",
    "gn:admin2_code":"5",
    "gn:asciiname":"El Vallecito",
    "gn:country_code":"MX",
    "gn:dem":246,
    "gn:feature_class":"P",
    "gn:feature_code":"PPL",
    "gn:name":"El Vallecito",
    "gn:population":46,
    "gn:timezone":"America/Mazatlan",
    "iso:country":"MX",
    "wof:name":"El Vallecito",
    "wof:placetype":"locality",
    "wof:population":46
},
  "geometry": {"coordinates":[-105.50694,22.79694],"type":"Point"}
}