{
  "type": "Feature",
  "properties": {
    "gn:admin1_code":"11",
    "gn:admin2_code":"42.0",
    "gn:asciiname":"Pozo de Arostegui (Las Correas)",
    "gn:country_code":"MX",
    "gn:dem":1750,
    "gn:feature_class":"P",
    "gn:feature_code":"PPL",
    "gn:name":"Pozo de Ar\u00f3stegui (Las Correas)",
    "gn:population":883,
    "gn:timezone":"America/Mexico_City",
    "iso:country":"MX",
    "name:und_x_variant":[
        "Pozo de Ar\u00f3stegui (Las Correas)"
    ],
    "wof:name":"Pozo de Arostegui (Las Correas)",
    "wof:placetype":"locality",
    "wof:population":883
},
  "geometry": {"coordinates":[-101.14194000000001,20.355],"type":"Point"}
}