{
  "type": "Feature",
  "properties": {
    "gn:admin1_code":"12.0",
    "gn:admin2_code":"16.0",
    "gn:asciiname":"La Cuchilla de Enmedio",
    "gn:country_code":"MX",
    "gn:dem":385,
    "gn:feature_class":"P",
    "gn:feature_code":"PPL",
    "gn:name":"La Cuchilla de Enmedio",
    "gn:population":0,
    "gn:timezone":"America/Mexico_City",
    "iso:country":"MX",
    "name:spa_x_preferred":[
        "La Cuchilla de Enmedio"
    ],
    "wof:name":"La Cuchilla de Enmedio",
    "wof:placetype":"locality"
},
  "geometry": {"coordinates":[-101.55535999999999,18.05002],"type":"Point"}
}