{
  "type": "Feature",
  "properties": {
    "gn:admin1_code":"12.0",
    "gn:admin2_code":"2.0",
    "gn:asciiname":"Atlica",
    "gn:country_code":"MX",
    "gn:dem":1319,
    "gn:feature_class":"P",
    "gn:feature_code":"PPL",
    "gn:name":"Atlica",
    "gn:population":0,
    "gn:timezone":"America/Mexico_City",
    "iso:country":"MX",
    "name:spa_x_preferred":[
        "Atlica"
    ],
    "wof:name":"Atlica",
    "wof:placetype":"locality"
},
  "geometry": {"coordinates":[-98.91677,17.69214],"type":"Point"}
}