{
  "type": "Feature",
  "properties": {
    "gn:admin1_code":"30.0",
    "gn:admin2_code":"123.0",
    "gn:asciiname":"Las Gladiolas",
    "gn:country_code":"MX",
    "gn:dem":55,
    "gn:feature_class":"P",
    "gn:feature_code":"PPL",
    "gn:name":"Las Gladiolas",
    "gn:population":0,
    "gn:timezone":"America/Mexico_City",
    "iso:country":"MX",
    "name:spa_x_preferred":[
        "Las Gladiolas"
    ],
    "wof:name":"Las Gladiolas",
    "wof:placetype":"locality"
},
  "geometry": {"coordinates":[-98.29083,21.73611],"type":"Point"}
}