{
  "type": "Feature",
  "properties": {
    "gn:admin1_code":"20.0",
    "gn:admin2_code":"253.0",
    "gn:asciiname":"Cerro Leon Pinas",
    "gn:country_code":"MX",
    "gn:dem":1342,
    "gn:feature_class":"P",
    "gn:feature_code":"PPL",
    "gn:name":"Cerro Le\u00f3n Pi\u00f1as",
    "gn:population":0,
    "gn:timezone":"America/Mexico_City",
    "iso:country":"MX",
    "name:spa_x_preferred":[
        "Cerro Le\u00f3n Pi\u00f1as"
    ],
    "wof:name":"Cerro Leon Pinas",
    "wof:placetype":"locality"
},
  "geometry": {"coordinates":[-96.37732,15.97869],"type":"Point"}
}