{
  "type": "Feature",
  "properties": {
    "gn:admin1_code":"21",
    "gn:admin2_code":"25.0",
    "gn:asciiname":"Colonia Cuauhtemoc",
    "gn:country_code":"MX",
    "gn:dem":287,
    "gn:feature_class":"P",
    "gn:feature_code":"PPL",
    "gn:name":"Colonia Cuauht\u00e9moc",
    "gn:population":0,
    "gn:timezone":"America/Mexico_City",
    "iso:country":"MX",
    "name:spa_x_preferred":[
        "Colonia Cuauht\u00e9moc"
    ],
    "name:spa_x_variant":[
        "Tlacuilolostoc"
    ],
    "wof:name":"Colonia Cuauhtemoc",
    "wof:placetype":"locality"
},
  "geometry": {"coordinates":[-97.42846,20.06061],"type":"Point"}
}