{
  "type": "Feature",
  "properties": {
    "gn:admin1_code":"26",
    "gn:admin2_code":"20.0",
    "gn:asciiname":"Carbo",
    "gn:country_code":"MX",
    "gn:dem":468,
    "gn:feature_class":"P",
    "gn:feature_code":"PPLA2",
    "gn:name":"Carbo",
    "gn:population":0,
    "gn:timezone":"America/Hermosillo",
    "iso:country":"MX",
    "name:deu_x_preferred":[
        "Carbo"
    ],
    "name:nld_x_preferred":[
        "Carbo"
    ],
    "name:spa_x_preferred":[
        "Carbo"
    ],
    "wof:name":"Carbo",
    "wof:placetype":"locality"
},
  "geometry": {"coordinates":[-110.95619000000001,29.68306],"type":"Point"}
}