{
  "type": "Feature",
  "properties": {
    "gn:admin1_code":"5.0",
    "gn:admin2_code":"17.0",
    "gn:asciiname":"El Medallin",
    "gn:country_code":"MX",
    "gn:dem":1032,
    "gn:feature_class":"P",
    "gn:feature_code":"PPL",
    "gn:name":"El Medall\u00edn",
    "gn:population":0,
    "gn:timezone":"America/Mexico_City",
    "iso:country":"MX",
    "name:spa_x_preferred":[
        "El Medall\u00edn"
    ],
    "name:spa_x_variant":[
        "Unesco"
    ],
    "wof:name":"El Medallin",
    "wof:placetype":"locality"
},
  "geometry": {"coordinates":[-93.74222,16.83144],"type":"Point"}
}