{
  "type": "Feature",
  "properties": {
    "gn:admin1_code":"32",
    "gn:admin2_code":"20.0",
    "gn:asciiname":"Sarabia",
    "gn:country_code":"MX",
    "gn:dem":2352,
    "gn:feature_class":"P",
    "gn:feature_code":"PPL",
    "gn:name":"Sarabia",
    "gn:population":0,
    "gn:timezone":"America/Mexico_City",
    "iso:country":"MX",
    "name:spa_x_preferred":[
        "Sarabia"
    ],
    "wof:name":"Sarabia",
    "wof:placetype":"locality"
},
  "geometry": {"coordinates":[-103.18407999999999,22.86946],"type":"Point"}
}