{
  "type": "Feature",
  "properties": {
    "gn:admin1_code":"32",
    "gn:admin2_code":"20.0",
    "gn:asciiname":"Sarabia",
    "gn:country_code":"MX",
    "gn:dem":2352,
    "gn:feature_class":"P",
    "gn:feature_code":"PPL",
    "gn:name":"Sarabia",
    "gn:population":0,
    "gn:timezone":"America/Mexico_City",
    "iso:country":"MX",
    "name:ceb_x_preferred":[
        "Sarabia"
    ],
    "name:deu_x_preferred":[
        "Sarabia"
    ],
    "name:fra_x_preferred":[
        "Sarabia"
    ],
    "name:glg_x_preferred":[
        "Sarabia"
    ],
    "name:ita_x_preferred":[
        "Sarabia"
    ],
    "name:kor_x_preferred":[
        "\uc0ac\ub77c\ube44\uc544"
    ],
    "name:rus_x_preferred":[
        "\u0421\u0430\u0440\u0430\u0431\u0438\u0430"
    ],
    "name:spa_x_preferred":[
        "Sarabia"
    ],
    "name:swe_x_preferred":[
        "Sarabia"
    ],
    "wof:name":"Sarabia",
    "wof:placetype":"locality"
},
  "geometry": {"coordinates":[-103.18407999999999,22.86946],"type":"Point"}
}