{
  "type": "Feature",
  "properties": {
    "gn:admin1_code":"12",
    "gn:admin2_code":"55.0",
    "gn:asciiname":"El Aguacatito",
    "gn:country_code":"MX",
    "gn:dem":1892,
    "gn:feature_class":"P",
    "gn:feature_code":"PPL",
    "gn:name":"El Aguacatito",
    "gn:population":180,
    "gn:timezone":"America/Mexico_City",
    "iso:country":"MX",
    "wof:name":"El Aguacatito",
    "wof:placetype":"locality",
    "wof:population":180
},
  "geometry": {"coordinates":[-99.64415,18.55899],"type":"Point"}
}