{
  "type": "Feature",
  "properties": {
    "gn:admin1_code":"14.0",
    "gn:admin2_code":"67.0",
    "gn:asciiname":"Paso del Guayabo",
    "gn:country_code":"MX",
    "gn:dem":103,
    "gn:feature_class":"P",
    "gn:feature_code":"PPL",
    "gn:name":"Paso del Guayabo",
    "gn:population":0,
    "gn:timezone":"America/Mexico_City",
    "iso:country":"MX",
    "name:spa_x_preferred":[
        "Paso del Guayabo"
    ],
    "wof:name":"Paso del Guayabo",
    "wof:placetype":"locality"
},
  "geometry": {"coordinates":[-105.21198,20.58783],"type":"Point"}
}