{
  "type": "Feature",
  "properties": {
    "gn:admin1_code":"11",
    "gn:admin2_code":"46.0",
    "gn:asciiname":"El Canario",
    "gn:country_code":"MX",
    "gn:dem":1874,
    "gn:feature_class":"P",
    "gn:feature_code":"PPL",
    "gn:name":"El Canario",
    "gn:population":1157,
    "gn:timezone":"America/Mexico_City",
    "iso:country":"MX",
    "wof:name":"El Canario",
    "wof:placetype":"locality",
    "wof:population":1157
},
  "geometry": {"coordinates":[-101.33556,20.15694],"type":"Point"}
}