{
  "type": "Feature",
  "properties": {
    "gn:admin1_code":"12.0",
    "gn:admin2_code":"57.0",
    "gn:asciiname":"Los Canales",
    "gn:country_code":"MX",
    "gn:dem":241,
    "gn:feature_class":"P",
    "gn:feature_code":"PPL",
    "gn:name":"Los Ca\u00f1ales",
    "gn:population":0,
    "gn:timezone":"America/Mexico_City",
    "iso:country":"MX",
    "name:spa_x_preferred":[
        "Los Ca\u00f1ales"
    ],
    "wof:name":"Los Canales",
    "wof:placetype":"locality"
},
  "geometry": {"coordinates":[-100.52244,17.22321],"type":"Point"}
}