{
  "type": "Feature",
  "properties": {
    "gn:admin1_code":"6.0",
    "gn:admin2_code":"31.0",
    "gn:asciiname":"La Monche",
    "gn:country_code":"MX",
    "gn:dem":2121,
    "gn:feature_class":"P",
    "gn:feature_code":"PPL",
    "gn:name":"La Monche",
    "gn:population":0,
    "gn:timezone":"America/Chihuahua",
    "iso:country":"MX",
    "name:spa_x_preferred":[
        "La Monche"
    ],
    "wof:name":"La Monche",
    "wof:placetype":"locality"
},
  "geometry": {"coordinates":[-107.47692000000001,28.39642000000001],"type":"Point"}
}