{
  "type": "Feature",
  "properties": {
    "gn:admin1_code":"27",
    "gn:admin2_code":"8.0",
    "gn:asciiname":"Chicoacan (Ampliacion)",
    "gn:country_code":"MX",
    "gn:dem":45,
    "gn:feature_class":"P",
    "gn:feature_code":"PPL",
    "gn:name":"Chicoac\u00e1n (Ampliaci\u00f3n)",
    "gn:population":524,
    "gn:timezone":"America/Mexico_City",
    "iso:country":"MX",
    "name:spa_x_preferred":[
        "Chicoacan"
    ],
    "wof:name":"Chicoacan (Ampliacion)",
    "wof:placetype":"locality",
    "wof:population":524
},
  "geometry": {"coordinates":[-93.4525,17.75611],"type":"Point"}
}