{
  "type": "Feature",
  "properties": {
    "gn:admin1_code":"19",
    "gn:admin2_code":"7.0",
    "gn:asciiname":"Puerto Pinones",
    "gn:country_code":"MX",
    "gn:dem":2355,
    "gn:feature_class":"P",
    "gn:feature_code":"PPL",
    "gn:name":"Puerto Pi\u00f1ones",
    "gn:population":81,
    "gn:timezone":"America/Monterrey",
    "iso:country":"MX",
    "name:und_x_variant":[
        "Puerto Pi\u00f1ones"
    ],
    "wof:name":"Puerto Pinones",
    "wof:placetype":"locality",
    "wof:population":81
},
  "geometry": {"coordinates":[-100.01775000000001,24.45119],"type":"Point"}
}