{
  "type": "Feature",
  "properties": {
    "gn:admin1_code":"20",
    "gn:admin2_code":"130.0",
    "gn:asciiname":"Salinas Buenavista",
    "gn:country_code":"MX",
    "gn:dem":8,
    "gn:feature_class":"P",
    "gn:feature_code":"PPL",
    "gn:name":"Salinas Buenavista",
    "gn:population":0,
    "gn:timezone":"America/Mexico_City",
    "iso:country":"MX",
    "name:spa_x_preferred":[
        "Buenavista"
    ],
    "name:spa_x_variant":[
        "Salinas Buenavista"
    ],
    "wof:name":"Salinas Buenavista",
    "wof:placetype":"locality"
},
  "geometry": {"coordinates":[-94.8128,16.38052],"type":"Point"}
}