{
  "type": "Feature",
  "properties": {
    "gn:admin1_code":"31",
    "gn:admin2_code":"91.0",
    "gn:asciiname":"San Felipe Nuevo",
    "gn:country_code":"MX",
    "gn:dem":33,
    "gn:feature_class":"P",
    "gn:feature_code":"PPL",
    "gn:name":"San Felipe Nuevo",
    "gn:population":100,
    "gn:timezone":"America/Merida",
    "iso:country":"MX",
    "wof:name":"San Felipe Nuevo",
    "wof:placetype":"locality",
    "wof:population":100
},
  "geometry": {"coordinates":[-88.5625,20.68444],"type":"Point"}
}