{
  "type": "Feature",
  "properties": {
    "gn:admin1_code":"13",
    "gn:admin2_code":"28",
    "gn:asciiname":"Las Chacas",
    "gn:country_code":"MX",
    "gn:dem":165,
    "gn:feature_class":"P",
    "gn:feature_code":"PPL",
    "gn:name":"Las Chacas",
    "gn:population":33,
    "gn:timezone":"America/Mexico_City",
    "iso:country":"MX",
    "wof:name":"Las Chacas",
    "wof:placetype":"locality",
    "wof:population":33
},
  "geometry": {"coordinates":[-98.41934999999999,21.12652000000001],"type":"Point"}
}