{
  "type": "Feature",
  "properties": {
    "gn:admin1_code":"26",
    "gn:admin2_code":"12.0",
    "gn:asciiname":"Las Tortolas",
    "gn:country_code":"MX",
    "gn:dem":176,
    "gn:feature_class":"P",
    "gn:feature_code":"PPL",
    "gn:name":"Las T\u00f3rtolas",
    "gn:population":0,
    "gn:timezone":"America/Hermosillo",
    "iso:country":"MX",
    "name:spa_x_preferred":[
        "Las T\u00f3rtolas"
    ],
    "wof:name":"Las Tortolas",
    "wof:placetype":"locality"
},
  "geometry": {"coordinates":[-110.2131,27.81054],"type":"Point"}
}