{
  "type": "Feature",
  "properties": {
    "gn:admin1_code":"24",
    "gn:admin2_code":"6",
    "gn:asciiname":"El Pozo Viejo",
    "gn:country_code":"MX",
    "gn:dem":1789,
    "gn:feature_class":"P",
    "gn:feature_code":"PPL",
    "gn:name":"El Pozo Viejo",
    "gn:population":11,
    "gn:timezone":"America/Mexico_City",
    "iso:country":"MX",
    "wof:name":"El Pozo Viejo",
    "wof:placetype":"locality",
    "wof:population":11
},
  "geometry": {"coordinates":[-101.02916999999999,23.67],"type":"Point"}
}