{
  "type": "Feature",
  "properties": {
    "gn:admin1_code":"32",
    "gn:admin2_code":"51.0",
    "gn:asciiname":"Tierra y Libertad (San Blas)",
    "gn:country_code":"MX",
    "gn:dem":2031,
    "gn:feature_class":"P",
    "gn:feature_code":"PPL",
    "gn:name":"Tierra y Libertad (San Blas)",
    "gn:population":501,
    "gn:timezone":"America/Mexico_City",
    "iso:country":"MX",
    "wof:name":"Tierra y Libertad (San Blas)",
    "wof:placetype":"locality",
    "wof:population":501
},
  "geometry": {"coordinates":[-102.38889,23.45361],"type":"Point"}
}