{
  "type": "Feature",
  "properties": {
    "gn:admin1_code":"11.0",
    "gn:admin2_code":"3.0",
    "gn:asciiname":"Cinco Senores",
    "gn:country_code":"MX",
    "gn:dem":1904,
    "gn:feature_class":"P",
    "gn:feature_code":"PPL",
    "gn:name":"Cinco Se\u00f1ores",
    "gn:population":87,
    "gn:timezone":"America/Mexico_City",
    "iso:country":"MX",
    "wof:name":"Cinco Senores",
    "wof:placetype":"locality",
    "wof:population":87
},
  "geometry": {"coordinates":[-100.90833000000001,20.95694],"type":"Point"}
}