{
  "type": "Feature",
  "properties": {
    "gn:admin1_code":"17",
    "gn:admin2_code":"20.0",
    "gn:asciiname":"Colonia Obrera",
    "gn:country_code":"MX",
    "gn:dem":1290,
    "gn:feature_class":"P",
    "gn:feature_code":"PPL",
    "gn:name":"Colonia Obrera",
    "gn:population":1316,
    "gn:timezone":"America/Mexico_City",
    "iso:country":"MX",
    "wof:name":"Colonia Obrera",
    "wof:placetype":"locality",
    "wof:population":1316
},
  "geometry": {"coordinates":[-99.03888999999999,18.93167],"type":"Point"}
}