{
  "type": "Feature",
  "properties": {
    "gn:admin1_code":"18.0",
    "gn:admin2_code":"15.0",
    "gn:asciiname":"Dona Maria",
    "gn:country_code":"MX",
    "gn:dem":95,
    "gn:feature_class":"P",
    "gn:feature_code":"PPL",
    "gn:name":"Do\u00f1a Mar\u00eda",
    "gn:population":0,
    "gn:timezone":"America/Mazatlan",
    "iso:country":"MX",
    "wof:name":"Dona Maria",
    "wof:placetype":"locality"
},
  "geometry": {"coordinates":[-105.01667,21.83333],"type":"Point"}
}