{
  "type": "Feature",
  "properties": {
    "gn:admin1_code":"12",
    "gn:admin2_code":"78",
    "gn:asciiname":"Ahuezutla",
    "gn:country_code":"MX",
    "gn:dem":2046,
    "gn:feature_class":"P",
    "gn:feature_code":"PPL",
    "gn:name":"Ahuezutla",
    "gn:population":28,
    "gn:timezone":"America/Mexico_City",
    "iso:country":"MX",
    "wof:name":"Ahuezutla",
    "wof:placetype":"locality",
    "wof:population":28
},
  "geometry": {"coordinates":[-98.51443999999999,17.21194],"type":"Point"}
}