{
  "type": "Feature",
  "properties": {
    "gn:admin1_code":"5",
    "gn:admin2_code":"30.0",
    "gn:asciiname":"Rincon Pena Blanca",
    "gn:country_code":"MX",
    "gn:dem":664,
    "gn:feature_class":"P",
    "gn:feature_code":"PPL",
    "gn:name":"Rinc\u00f3n Pe\u00f1a Blanca",
    "gn:population":7,
    "gn:timezone":"America/Mexico_City",
    "iso:country":"MX",
    "name:und_x_variant":[
        "Rinc\u00f3n Pe\u00f1a Blanca"
    ],
    "wof:name":"Rincon Pena Blanca",
    "wof:placetype":"locality",
    "wof:population":7
},
  "geometry": {"coordinates":[-92.36611000000001,15.82056],"type":"Point"}
}