{
  "type": "Feature",
  "properties": {
    "gn:admin1_code":"11.0",
    "gn:admin2_code":"31.0",
    "gn:asciiname":"El Acebuche",
    "gn:country_code":"MX",
    "gn:dem":1791,
    "gn:feature_class":"P",
    "gn:feature_code":"PPL",
    "gn:name":"El Acebuche",
    "gn:population":0,
    "gn:timezone":"America/Mexico_City",
    "iso:country":"MX",
    "name:spa_x_preferred":[
        "El Acebuche"
    ],
    "wof:name":"El Acebuche",
    "wof:placetype":"locality"
},
  "geometry": {"coordinates":[-101.7354,20.9083],"type":"Point"}
}