{
  "type": "Feature",
  "properties": {
    "gn:admin1_code":"26",
    "gn:admin2_code":"26.0",
    "gn:asciiname":"Juchica",
    "gn:country_code":"MX",
    "gn:dem":19,
    "gn:feature_class":"P",
    "gn:feature_code":"PPL",
    "gn:name":"Juchica",
    "gn:population":108,
    "gn:timezone":"America/Hermosillo",
    "iso:country":"MX",
    "wof:name":"Juchica",
    "wof:placetype":"locality",
    "wof:population":108
},
  "geometry": {"coordinates":[-109.64583,27.08389],"type":"Point"}
}