{
  "type": "Feature",
  "properties": {
    "gn:admin1_code":"5.0",
    "gn:admin2_code":"20.0",
    "gn:asciiname":"El Laberinto",
    "gn:country_code":"MX",
    "gn:dem":530,
    "gn:feature_class":"P",
    "gn:feature_code":"PPL",
    "gn:name":"El Laberinto",
    "gn:population":0,
    "gn:timezone":"America/Mexico_City",
    "iso:country":"MX",
    "name:spa_x_preferred":[
        "El Laberinto"
    ],
    "wof:name":"El Laberinto",
    "wof:placetype":"locality"
},
  "geometry": {"coordinates":[-92.75714000000001,16.10664],"type":"Point"}
}