{
  "type": "Feature",
  "properties": {
    "gn:admin1_code":"16",
    "gn:admin2_code":"91.0",
    "gn:asciiname":"Tacatzcuaro",
    "gn:country_code":"MX",
    "gn:dem":1619,
    "gn:feature_class":"P",
    "gn:feature_code":"PPL",
    "gn:name":"Tac\u00e1tzcuaro",
    "gn:population":0,
    "gn:timezone":"America/Mexico_City",
    "iso:country":"MX",
    "name:spa_x_preferred":[
        "Tac\u00e1tzcuaro"
    ],
    "name:und_x_variant":[
        "Tacazcuaro"
    ],
    "wof:name":"Tacatzcuaro",
    "wof:placetype":"locality"
},
  "geometry": {"coordinates":[-102.54742,19.73009],"type":"Point"}
}