{
  "type": "Feature",
  "properties": {
    "gn:admin1_code":"14",
    "gn:admin2_code":"46",
    "gn:asciiname":"Apozolco",
    "gn:country_code":"MX",
    "gn:dem":1692,
    "gn:feature_class":"P",
    "gn:feature_code":"PPL",
    "gn:name":"Apozolco",
    "gn:population":51,
    "gn:timezone":"America/Mexico_City",
    "iso:country":"MX",
    "wof:name":"Apozolco",
    "wof:placetype":"locality",
    "wof:population":51
},
  "geometry": {"coordinates":[-102.52222,21.28806],"type":"Point"}
}