{
  "type": "Feature",
  "properties": {
    "gn:admin1_code":"30.0",
    "gn:admin2_code":"161.0",
    "gn:asciiname":"Raya Zapote",
    "gn:country_code":"MX",
    "gn:dem":43,
    "gn:feature_class":"P",
    "gn:feature_code":"PPL",
    "gn:name":"Raya Zapote",
    "gn:population":4,
    "gn:timezone":"America/Mexico_City",
    "iso:country":"MX",
    "name:spa_x_preferred":[
        "Raya Zapote"
    ],
    "wof:name":"Raya Zapote",
    "wof:placetype":"locality",
    "wof:population":4
},
  "geometry": {"coordinates":[-98.16357000000001,21.6672],"type":"Point"}
}