{
  "type": "Feature",
  "properties": {
    "gn:admin1_code":"5",
    "gn:admin2_code":"80",
    "gn:asciiname":"San Antonio Chico",
    "gn:country_code":"MX",
    "gn:dem":1405,
    "gn:feature_class":"P",
    "gn:feature_code":"PPL",
    "gn:name":"San Antonio Chico",
    "gn:population":36,
    "gn:timezone":"America/Mexico_City",
    "iso:country":"MX",
    "wof:name":"San Antonio Chico",
    "wof:placetype":"locality",
    "wof:population":36
},
  "geometry": {"coordinates":[-92.36917,15.67361],"type":"Point"}
}