{
  "type": "Feature",
  "properties": {
    "gn:admin1_code":"15",
    "gn:admin2_code":"14",
    "gn:asciiname":"La Loma Ejido Bombatevi (El Manto)",
    "gn:country_code":"MX",
    "gn:dem":2517,
    "gn:feature_class":"P",
    "gn:feature_code":"PPL",
    "gn:name":"La Loma Ejido Bombatevi (El Manto)",
    "gn:population":20,
    "gn:timezone":"America/Mexico_City",
    "iso:country":"MX",
    "wof:name":"La Loma Ejido Bombatevi (El Manto)",
    "wof:placetype":"locality",
    "wof:population":20
},
  "geometry": {"coordinates":[-99.91936,19.83997],"type":"Point"}
}