{
  "type": "Feature",
  "properties": {
    "gn:admin1_code":"29.0",
    "gn:admin2_code":"17.0",
    "gn:asciiname":"San Juan Ixhualco",
    "gn:country_code":"MX",
    "gn:dem":2350,
    "gn:feature_class":"P",
    "gn:feature_code":"PPL",
    "gn:name":"San Juan Ixhualco",
    "gn:population":0,
    "gn:timezone":"America/Mexico_City",
    "iso:country":"MX",
    "name:spa_x_preferred":[
        "San Juan"
    ],
    "name:spa_x_variant":[
        "San Juan Ixhualco"
    ],
    "wof:name":"San Juan Ixhualco",
    "wof:placetype":"locality"
},
  "geometry": {"coordinates":[-98.18380000000001,19.19586],"type":"Point"}
}