{
  "type": "Feature",
  "properties": {
    "gn:admin1_code":"32",
    "gn:admin2_code":"22.0",
    "gn:asciiname":"La India",
    "gn:country_code":"MX",
    "gn:dem":2096,
    "gn:feature_class":"P",
    "gn:feature_code":"PPL",
    "gn:name":"La India",
    "gn:population":0,
    "gn:timezone":"America/Mexico_City",
    "iso:country":"MX",
    "name:bre_x_preferred":[
        "La India"
    ],
    "name:bul_x_preferred":[
        "\u041b\u0430 \u0418\u043d\u0434\u0438\u044f"
    ],
    "name:deu_x_preferred":[
        "La India"
    ],
    "name:fra_x_preferred":[
        "La India"
    ],
    "name:ita_x_preferred":[
        "La India"
    ],
    "name:nld_x_preferred":[
        "La India"
    ],
    "name:rus_x_preferred":[
        "La India"
    ],
    "name:spa_x_preferred":[
        "La India"
    ],
    "wof:name":"La India",
    "wof:placetype":"locality"
},
  "geometry": {"coordinates":[-103.25821000000001,24.26488],"type":"Point"}
}