{
  "type": "Feature",
  "properties": {
    "gn:admin1_code":"30",
    "gn:admin2_code":"109.0",
    "gn:asciiname":"La Frontera",
    "gn:country_code":"MX",
    "gn:dem":17,
    "gn:feature_class":"P",
    "gn:feature_code":"PPL",
    "gn:name":"La Frontera",
    "gn:population":6,
    "gn:timezone":"America/Mexico_City",
    "iso:country":"MX",
    "wof:name":"La Frontera",
    "wof:placetype":"locality",
    "wof:population":6
},
  "geometry": {"coordinates":[-96.91167,20.13111],"type":"Point"}
}