{
  "type": "Feature",
  "properties": {
    "gn:admin1_code":"5.0",
    "gn:admin2_code":"3.0",
    "gn:asciiname":"Balun Canan",
    "gn:country_code":"MX",
    "gn:dem":4,
    "gn:feature_class":"P",
    "gn:feature_code":"PPL",
    "gn:name":"Bal\u00fan Can\u00e1n",
    "gn:population":0,
    "gn:timezone":"America/Mexico_City",
    "iso:country":"MX",
    "name:spa_x_preferred":[
        "Bal\u00fan Can\u00e1n"
    ],
    "wof:name":"Balun Canan",
    "wof:placetype":"locality"
},
  "geometry": {"coordinates":[-92.76966,15.21555],"type":"Point"}
}