{
  "type": "Feature",
  "properties": {
    "gn:admin1_code":"30",
    "gn:admin2_code":"102.0",
    "gn:asciiname":"Arroyo del Potrero",
    "gn:country_code":"MX",
    "gn:dem":88,
    "gn:feature_class":"P",
    "gn:feature_code":"PPL",
    "gn:name":"Arroyo del Potrero",
    "gn:population":0,
    "gn:timezone":"America/Mexico_City",
    "iso:country":"MX",
    "name:spa_x_preferred":[
        "Arroyo del Potrero"
    ],
    "wof:name":"Arroyo del Potrero",
    "wof:placetype":"locality"
},
  "geometry": {"coordinates":[-97.0652,20.14554],"type":"Point"}
}