{
  "type": "Feature",
  "properties": {
    "gn:admin1_code":"11.0",
    "gn:asciiname":"Huandarillo",
    "gn:country_code":"MX",
    "gn:dem":1683,
    "gn:feature_class":"P",
    "gn:feature_code":"PPL",
    "gn:name":"Huandarillo",
    "gn:population":0,
    "gn:timezone":"America/Mexico_City",
    "iso:country":"MX",
    "name:spa_x_preferred":[
        "Huandarillo"
    ],
    "name:und_x_variant":[
        "Guandarillo"
    ],
    "wof:name":"Huandarillo",
    "wof:placetype":"locality"
},
  "geometry": {"coordinates":[-101.87597,20.20481],"type":"Point"}
}