{
  "type": "Feature",
  "properties": {
    "gn:admin1_code":"14.0",
    "gn:asciiname":"La Guaracha",
    "gn:country_code":"MX",
    "gn:dem":1925,
    "gn:feature_class":"P",
    "gn:feature_code":"PPL",
    "gn:name":"La Guaracha",
    "gn:population":0,
    "gn:timezone":"America/Mexico_City",
    "iso:country":"MX",
    "name:spa_x_preferred":[
        "La Guaracha"
    ],
    "wof:name":"La Guaracha",
    "wof:placetype":"locality"
},
  "geometry": {"coordinates":[-101.98544,20.92546],"type":"Point"}
}