{
  "type": "Feature",
  "properties": {
    "gn:admin1_code":"28",
    "gn:admin2_code":"19.0",
    "gn:asciiname":"El Platanal",
    "gn:country_code":"MX",
    "gn:dem":452,
    "gn:feature_class":"P",
    "gn:feature_code":"PPL",
    "gn:name":"El Platanal",
    "gn:population":0,
    "gn:timezone":"America/Monterrey",
    "iso:country":"MX",
    "name:spa_x_preferred":[
        "El Platanal"
    ],
    "wof:name":"El Platanal",
    "wof:placetype":"locality"
},
  "geometry": {"coordinates":[-99.10651,23.41899],"type":"Point"}
}