{
  "type": "Feature",
  "properties": {
    "gn:admin1_code":"26",
    "gn:admin2_code":"30.0",
    "gn:asciiname":"Chapingo",
    "gn:country_code":"MX",
    "gn:dem":233,
    "gn:feature_class":"P",
    "gn:feature_code":"PPL",
    "gn:name":"Chapingo",
    "gn:population":0,
    "gn:timezone":"America/Hermosillo",
    "iso:country":"MX",
    "name:fra_x_preferred":[
        "Chapingo"
    ],
    "name:spa_x_preferred":[
        "Chapingo"
    ],
    "wof:name":"Chapingo",
    "wof:placetype":"locality"
},
  "geometry": {"coordinates":[-110.89773,29.11662],"type":"Point"}
}