{
  "type": "Feature",
  "properties": {
    "gn:admin1_code":"21.0",
    "gn:admin2_code":"19.0",
    "gn:asciiname":"El Zapatero",
    "gn:country_code":"MX",
    "gn:dem":1884,
    "gn:feature_class":"P",
    "gn:feature_code":"PPL",
    "gn:name":"El Zapatero",
    "gn:population":0,
    "gn:timezone":"America/Mexico_City",
    "iso:country":"MX",
    "name:spa_x_preferred":[
        "El Zapatero"
    ],
    "wof:name":"El Zapatero",
    "wof:placetype":"locality"
},
  "geometry": {"coordinates":[-98.41011,18.92786],"type":"Point"}
}