{
  "type": "Feature",
  "properties": {
    "gn:admin1_code":"31",
    "gn:admin2_code":"69.0",
    "gn:asciiname":"San Jeronimo",
    "gn:country_code":"MX",
    "gn:dem":22,
    "gn:feature_class":"P",
    "gn:feature_code":"PPL",
    "gn:name":"San Jer\u00f3nimo",
    "gn:population":0,
    "gn:timezone":"America/Merida",
    "iso:country":"MX",
    "name:spa_x_preferred":[
        "San Jer\u00f3nimo"
    ],
    "wof:name":"San Jeronimo",
    "wof:placetype":"locality"
},
  "geometry": {"coordinates":[-89.03927,20.53338],"type":"Point"}
}