{
  "type": "Feature",
  "properties": {
    "gn:admin1_code":"14.0",
    "gn:admin2_code":"68.0",
    "gn:asciiname":"Los Metatitos",
    "gn:country_code":"MX",
    "gn:dem":619,
    "gn:feature_class":"P",
    "gn:feature_code":"PPL",
    "gn:name":"Los Metatitos",
    "gn:population":0,
    "gn:timezone":"America/Mexico_City",
    "iso:country":"MX",
    "name:spa_x_preferred":[
        "Los Metatitos"
    ],
    "wof:name":"Los Metatitos",
    "wof:placetype":"locality"
},
  "geometry": {"coordinates":[-104.62065,19.7659],"type":"Point"}
}