{
  "type": "Feature",
  "properties": {
    "gn:admin1_code":"11",
    "gn:admin2_code":"35.0",
    "gn:asciiname":"Fraccionamiento las Maravillas",
    "gn:country_code":"MX",
    "gn:dem":1756,
    "gn:feature_class":"P",
    "gn:feature_code":"PPL",
    "gn:name":"Fraccionamiento las Maravillas",
    "gn:population":5,
    "gn:timezone":"America/Mexico_City",
    "iso:country":"MX",
    "wof:name":"Fraccionamiento las Maravillas",
    "wof:placetype":"locality",
    "wof:population":5
},
  "geometry": {"coordinates":[-100.89,20.59167],"type":"Point"}
}