{
  "type": "Feature",
  "properties": {
    "gn:admin1_code":"26",
    "gn:admin2_code":"3.0",
    "gn:asciiname":"El Tanque",
    "gn:country_code":"MX",
    "gn:dem":320,
    "gn:feature_class":"P",
    "gn:feature_code":"PPL",
    "gn:name":"El Tanque",
    "gn:population":0,
    "gn:timezone":"America/Hermosillo",
    "iso:country":"MX",
    "name:spa_x_preferred":[
        "El Tanque"
    ],
    "wof:name":"El Tanque",
    "wof:placetype":"locality"
},
  "geometry": {"coordinates":[-109.0883,26.97573],"type":"Point"}
}