{
  "type": "Feature",
  "properties": {
    "gn:admin1_code":"10",
    "gn:admin2_code":"37",
    "gn:asciiname":"La Junta de los Hernandez (La Junta)",
    "gn:country_code":"MX",
    "gn:dem":797,
    "gn:feature_class":"P",
    "gn:feature_code":"PPL",
    "gn:name":"La Junta de los Hern\u00e1ndez (La Junta)",
    "gn:population":11,
    "gn:timezone":"America/Monterrey",
    "iso:country":"MX",
    "name:und_x_variant":[
        "La Junta de los Hern\u00e1ndez (La Junta)"
    ],
    "wof:name":"La Junta de los Hernandez (La Junta)",
    "wof:placetype":"locality",
    "wof:population":11
},
  "geometry": {"coordinates":[-106.60536999999999,25.1597],"type":"Point"}
}