{
  "type": "Feature",
  "properties": {
    "gn:admin1_code":"8.0",
    "gn:admin2_code":"9.0",
    "gn:asciiname":"Yautepec",
    "gn:country_code":"MX",
    "gn:dem":14,
    "gn:feature_class":"P",
    "gn:feature_code":"PPL",
    "gn:name":"Yautepec",
    "gn:population":0,
    "gn:timezone":"America/Mexico_City",
    "iso:country":"MX",
    "name:ceb_x_preferred":[
        "Yautepec"
    ],
    "name:rus_x_preferred":[
        "\u042f\u0443\u0442\u0435\u043f\u0435\u043a"
    ],
    "name:sco_x_preferred":[
        "Yautepec"
    ],
    "name:spa_x_preferred":[
        "Yautepec"
    ],
    "name:swe_x_preferred":[
        "Yautepec"
    ],
    "wof:name":"Yautepec",
    "wof:placetype":"locality"
},
  "geometry": {"coordinates":[-103.86673,18.83076],"type":"Point"}
}