{
  "type": "Feature",
  "properties": {
    "gn:admin1_code":"32",
    "gn:admin2_code":"14.0",
    "gn:asciiname":"La Herradura",
    "gn:country_code":"MX",
    "gn:dem":1965,
    "gn:feature_class":"P",
    "gn:feature_code":"PPL",
    "gn:name":"La Herradura",
    "gn:population":0,
    "gn:timezone":"America/Mexico_City",
    "iso:country":"MX",
    "name:spa_x_preferred":[
        "La Herradura"
    ],
    "wof:name":"La Herradura",
    "wof:placetype":"locality"
},
  "geometry": {"coordinates":[-103.00794,24.0632],"type":"Point"}
}