{
  "type": "Feature",
  "properties": {
    "gn:admin1_code":"30",
    "gn:admin2_code":"197",
    "gn:asciiname":"La Esmeralda",
    "gn:country_code":"MX",
    "gn:dem":1238,
    "gn:feature_class":"P",
    "gn:feature_code":"PPL",
    "gn:name":"La Esmeralda",
    "gn:population":31,
    "gn:timezone":"America/Mexico_City",
    "iso:country":"MX",
    "wof:name":"La Esmeralda",
    "wof:placetype":"locality",
    "wof:population":31
},
  "geometry": {"coordinates":[-96.80472,19.83194],"type":"Point"}
}