{
  "type": "Feature",
  "properties": {
    "gn:admin1_code":"11.0",
    "gn:admin2_code":"45.0",
    "gn:asciiname":"La Lajita",
    "gn:country_code":"MX",
    "gn:dem":1618,
    "gn:feature_class":"P",
    "gn:feature_code":"PPL",
    "gn:name":"La Lajita",
    "gn:population":0,
    "gn:timezone":"America/Mexico_City",
    "iso:country":"MX",
    "name:spa_x_preferred":[
        "La Lajita"
    ],
    "wof:name":"La Lajita",
    "wof:placetype":"locality"
},
  "geometry": {"coordinates":[-100.11,21.38832],"type":"Point"}
}