{
  "type": "Feature",
  "properties": {
    "gn:admin1_code":"30.0",
    "gn:admin2_code":"123.0",
    "gn:asciiname":"Alto de Vega Cercada",
    "gn:country_code":"MX",
    "gn:dem":23,
    "gn:feature_class":"P",
    "gn:feature_code":"PPL",
    "gn:name":"Alto de Vega Cercada",
    "gn:population":157,
    "gn:timezone":"America/Mexico_City",
    "iso:country":"MX",
    "name:spa_x_preferred":[
        "Alto de Vega Cercada"
    ],
    "wof:name":"Alto de Vega Cercada",
    "wof:placetype":"locality",
    "wof:population":157
},
  "geometry": {"coordinates":[-98.32333,22.08167000000001],"type":"Point"}
}