{
  "type": "Feature",
  "properties": {
    "gn:admin1_code":"25",
    "gn:admin2_code":"3",
    "gn:asciiname":"Las Gueejas",
    "gn:country_code":"MX",
    "gn:dem":1018,
    "gn:feature_class":"P",
    "gn:feature_code":"PPL",
    "gn:name":"Las G\u00fcejas",
    "gn:population":13,
    "gn:timezone":"America/Mazatlan",
    "iso:country":"MX",
    "name:und_x_variant":[
        "Las G\u00fcejas"
    ],
    "wof:name":"Las Gueejas",
    "wof:placetype":"locality",
    "wof:population":13
},
  "geometry": {"coordinates":[-107.16762,25.76784],"type":"Point"}
}