{
  "type": "Feature",
  "properties": {
    "gn:admin1_code":"32",
    "gn:admin2_code":"14.0",
    "gn:asciiname":"Valenciana",
    "gn:country_code":"MX",
    "gn:dem":2115,
    "gn:feature_class":"P",
    "gn:feature_code":"PPL",
    "gn:name":"Valenciana",
    "gn:population":0,
    "gn:timezone":"America/Mexico_City",
    "iso:country":"MX",
    "name:ceb_x_preferred":[
        "Valenciana"
    ],
    "name:swe_x_preferred":[
        "Valenciana"
    ],
    "name:und_x_variant":[
        "Mina Valenciana"
    ],
    "wof:name":"Valenciana",
    "wof:placetype":"locality"
},
  "geometry": {"coordinates":[-103.19262000000001,24.16699],"type":"Point"}
}