{
  "type": "Feature",
  "properties": {
    "gn:admin1_code":"2",
    "gn:admin2_code":"1",
    "gn:asciiname":"Parcela Numero Cuatro (Rancho Carrillo)",
    "gn:country_code":"MX",
    "gn:dem":6,
    "gn:feature_class":"P",
    "gn:feature_code":"PPL",
    "gn:name":"Parcela N\u00famero Cuatro (Rancho Carrillo)",
    "gn:population":10,
    "gn:timezone":"America/Tijuana",
    "iso:country":"MX",
    "name:und_x_variant":[
        "Parcela N\u00famero Cuatro (Rancho Carrillo)"
    ],
    "wof:name":"Parcela Numero Cuatro (Rancho Carrillo)",
    "wof:placetype":"locality",
    "wof:population":10
},
  "geometry": {"coordinates":[-116.59389,31.76722],"type":"Point"}
}