{
  "type": "Feature",
  "properties": {
    "gn:admin1_code":"13.0",
    "gn:asciiname":"Paso del Membrillal",
    "gn:country_code":"MX",
    "gn:dem":872,
    "gn:feature_class":"P",
    "gn:feature_code":"PPL",
    "gn:name":"Paso del Membrillal",
    "gn:population":0,
    "gn:timezone":"America/Mexico_City",
    "iso:country":"MX",
    "name:spa_x_preferred":[
        "Paso del Membrillal"
    ],
    "wof:name":"Paso del Membrillal",
    "wof:placetype":"locality"
},
  "geometry": {"coordinates":[-99.39054,20.95462],"type":"Point"}
}