{
  "type": "Feature",
  "properties": {
    "gn:admin1_code":"22",
    "gn:admin2_code":"9.0",
    "gn:asciiname":"Jagueey (Jagueey Grande)",
    "gn:country_code":"MX",
    "gn:dem":1602,
    "gn:feature_class":"P",
    "gn:feature_code":"PPL",
    "gn:name":"Jag\u00fcey (Jag\u00fcey Grande)",
    "gn:population":116,
    "gn:timezone":"America/Mexico_City",
    "iso:country":"MX",
    "name:und_x_variant":[
        "Jag\u00fcey (Jag\u00fcey Grande)"
    ],
    "wof:name":"Jagueey (Jagueey Grande)",
    "wof:placetype":"locality",
    "wof:population":116
},
  "geometry": {"coordinates":[-99.46167,21.12417],"type":"Point"}
}