{
  "type": "Feature",
  "properties": {
    "gn:admin1_code":"16.0",
    "gn:admin2_code":"8.0",
    "gn:asciiname":"Cayaca",
    "gn:cc2":"MX",
    "gn:country_code":"MX",
    "gn:dem":455,
    "gn:feature_class":"P",
    "gn:feature_code":"PPL",
    "gn:name":"Cayaca",
    "gn:population":0,
    "gn:timezone":"America/Mexico_City",
    "iso:country":"MX",
    "name:und_x_variant":[
        "Cayacal",
        "Cayal",
        "Cayaca"
    ],
    "wof:name":"Cayaca",
    "wof:placetype":"locality"
},
  "geometry": {"coordinates":[-103.65000000000001,18.58333],"type":"Point"}
}