{
  "type": "Feature",
  "properties": {
    "gn:admin1_code":"12",
    "gn:admin2_code":"6.0",
    "gn:asciiname":"Petlacala",
    "gn:country_code":"MX",
    "gn:dem":1532,
    "gn:feature_class":"P",
    "gn:feature_code":"PPL",
    "gn:name":"Petlacala",
    "gn:population":0,
    "gn:timezone":"America/Mexico_City",
    "iso:country":"MX",
    "wof:name":"Petlacala",
    "wof:placetype":"locality"
},
  "geometry": {"coordinates":[-99.88494,18.18639],"type":"Point"}
}