{
  "type": "Feature",
  "properties": {
    "gn:admin1_code":"5",
    "gn:admin2_code":"108.0",
    "gn:asciiname":"La Ausencia",
    "gn:country_code":"MX",
    "gn:dem":629,
    "gn:feature_class":"P",
    "gn:feature_code":"PPL",
    "gn:name":"La Ausencia",
    "gn:population":6,
    "gn:timezone":"America/Mexico_City",
    "iso:country":"MX",
    "wof:name":"La Ausencia",
    "wof:placetype":"locality",
    "wof:population":6
},
  "geometry": {"coordinates":[-93.34833,16.40639],"type":"Point"}
}