{
  "type": "Feature",
  "properties": {
    "gn:admin1_code":"6",
    "gn:admin2_code":"27",
    "gn:asciiname":"Aborirare (Guarirare)",
    "gn:country_code":"MX",
    "gn:dem":2293,
    "gn:feature_class":"P",
    "gn:feature_code":"PPL",
    "gn:name":"Aborirare (Guarirare)",
    "gn:population":19,
    "gn:timezone":"America/Chihuahua",
    "iso:country":"MX",
    "wof:name":"Aborirare (Guarirare)",
    "wof:placetype":"locality",
    "wof:population":19
},
  "geometry": {"coordinates":[-107.37102,27.30715],"type":"Point"}
}