{
  "type": "Feature",
  "properties": {
    "gn:admin1_code":"30.0",
    "gn:admin2_code":"158.0",
    "gn:asciiname":"Cuatro Hermanos",
    "gn:country_code":"MX",
    "gn:dem":33,
    "gn:feature_class":"P",
    "gn:feature_code":"PPL",
    "gn:name":"Cuatro Hermanos",
    "gn:population":0,
    "gn:timezone":"America/Mexico_City",
    "iso:country":"MX",
    "name:spa_x_preferred":[
        "Cuatro Hermanos"
    ],
    "name:spa_x_variant":[
        "San Miguel"
    ],
    "wof:name":"Cuatro Hermanos",
    "wof:placetype":"locality"
},
  "geometry": {"coordinates":[-96.97579,20.37362000000001],"type":"Point"}
}