{
  "type": "Feature",
  "properties": {
    "gn:admin1_code":"30",
    "gn:admin2_code":"105.0",
    "gn:asciiname":"La Casa Amarilla",
    "gn:country_code":"MX",
    "gn:dem":19,
    "gn:feature_class":"P",
    "gn:feature_code":"PPL",
    "gn:name":"La Casa Amarilla",
    "gn:population":5,
    "gn:timezone":"America/Mexico_City",
    "iso:country":"MX",
    "wof:name":"La Casa Amarilla",
    "wof:placetype":"locality",
    "wof:population":5
},
  "geometry": {"coordinates":[-96.10444,18.99806],"type":"Point"}
}