{
  "type": "Feature",
  "properties": {
    "gn:admin1_code":"25",
    "gn:admin2_code":"14.0",
    "gn:asciiname":"El Calderon",
    "gn:country_code":"MX",
    "gn:dem":154,
    "gn:feature_class":"P",
    "gn:feature_code":"PPL",
    "gn:name":"El Calder\u00f3n",
    "gn:population":0,
    "gn:timezone":"America/Mazatlan",
    "iso:country":"MX",
    "name:spa_x_preferred":[
        "El Calder\u00f3n"
    ],
    "wof:name":"El Calderon",
    "wof:placetype":"locality"
},
  "geometry": {"coordinates":[-105.63043,23.11909],"type":"Point"}
}