{
  "type": "Feature",
  "properties": {
    "gn:admin1_code":"14",
    "gn:admin2_code":"100.0",
    "gn:asciiname":"Lechuguilla",
    "gn:country_code":"MX",
    "gn:dem":34,
    "gn:feature_class":"P",
    "gn:feature_code":"PPL",
    "gn:name":"Lechuguilla",
    "gn:population":0,
    "gn:timezone":"America/Mexico_City",
    "iso:country":"MX",
    "wof:name":"Lechuguilla",
    "wof:placetype":"locality"
},
  "geometry": {"coordinates":[-105.28333000000001,19.98333],"type":"Point"}
}