{
  "type": "Feature",
  "properties": {
    "gn:admin1_code":"13",
    "gn:admin2_code":"66.0",
    "gn:asciiname":"Acozac",
    "gn:country_code":"MX",
    "gn:dem":2609,
    "gn:feature_class":"P",
    "gn:feature_code":"PPL",
    "gn:name":"Acozac",
    "gn:population":94,
    "gn:timezone":"America/Mexico_City",
    "iso:country":"MX",
    "name:deu_x_preferred":[
        "Acozac"
    ],
    "name:mar_x_preferred":[
        "\u0905\u0915\u094b\u091d\u093e\u0915"
    ],
    "name:spa_x_preferred":[
        "Acozac"
    ],
    "wof:name":"Acozac",
    "wof:placetype":"locality",
    "wof:population":94
},
  "geometry": {"coordinates":[-98.75667,19.91861],"type":"Point"}
}