{
  "type": "Feature",
  "properties": {
    "gn:admin1_code":"5",
    "gn:admin2_code":"27",
    "gn:asciiname":"Paredon",
    "gn:country_code":"MX",
    "gn:dem":450,
    "gn:feature_class":"P",
    "gn:feature_code":"PPL",
    "gn:name":"Pared\u00f3n",
    "gn:population":17,
    "gn:timezone":"America/Mexico_City",
    "iso:country":"MX",
    "name:und_x_variant":[
        "Pared\u00f3n"
    ],
    "wof:name":"Paredon",
    "wof:placetype":"locality",
    "wof:population":17
},
  "geometry": {"coordinates":[-92.99167,16.49306],"type":"Point"}
}