{
  "type": "Feature",
  "properties": {
    "gn:admin1_code":"4",
    "gn:admin2_code":"3.0",
    "gn:asciiname":"El Milagro de Dios",
    "gn:country_code":"MX",
    "gn:dem":12,
    "gn:feature_class":"P",
    "gn:feature_code":"PPL",
    "gn:name":"El Milagro de Dios",
    "gn:population":4,
    "gn:timezone":"America/Merida",
    "iso:country":"MX",
    "wof:name":"El Milagro de Dios",
    "wof:placetype":"locality",
    "wof:population":4
},
  "geometry": {"coordinates":[-91.62,18.11083],"type":"Point"}
}