{
  "type": "Feature",
  "properties": {
    "gn:admin1_code":"26",
    "gn:admin2_code":"70.0",
    "gn:asciiname":"Los Toritos",
    "gn:country_code":"MX",
    "gn:dem":471,
    "gn:feature_class":"P",
    "gn:feature_code":"PPL",
    "gn:name":"Los Toritos",
    "gn:population":0,
    "gn:timezone":"America/Hermosillo",
    "iso:country":"MX",
    "wof:name":"Los Toritos",
    "wof:placetype":"locality"
},
  "geometry": {"coordinates":[-112.73318,31.58416],"type":"Point"}
}