{
  "type": "Feature",
  "properties": {
    "gn:admin1_code":"10",
    "gn:admin2_code":"14.0",
    "gn:asciiname":"Las Aguilillas (El Venado)",
    "gn:country_code":"MX",
    "gn:dem":2121,
    "gn:feature_class":"P",
    "gn:feature_code":"PPL",
    "gn:name":"Las Aguilillas (El Venado)",
    "gn:population":118,
    "gn:timezone":"America/Monterrey",
    "iso:country":"MX",
    "wof:name":"Las Aguilillas (El Venado)",
    "wof:placetype":"locality",
    "wof:population":118
},
  "geometry": {"coordinates":[-104.63941,22.92725],"type":"Point"}
}