{
  "type": "Feature",
  "properties": {
    "gn:admin1_code":"30",
    "gn:admin2_code":"72.0",
    "gn:asciiname":"Cruz de Ataque",
    "gn:country_code":"MX",
    "gn:dem":2569,
    "gn:feature_class":"P",
    "gn:feature_code":"PPL",
    "gn:name":"Cruz de Ataque",
    "gn:population":244,
    "gn:timezone":"America/Mexico_City",
    "iso:country":"MX",
    "wof:name":"Cruz de Ataque",
    "wof:placetype":"locality",
    "wof:population":244
},
  "geometry": {"coordinates":[-98.43889,20.43611],"type":"Point"}
}