{
  "type": "Feature",
  "properties": {
    "gn:admin1_code":"24",
    "gn:admin2_code":"15.0",
    "gn:asciiname":"Salitrillos",
    "gn:country_code":"MX",
    "gn:dem":2135,
    "gn:feature_class":"P",
    "gn:feature_code":"PPL",
    "gn:name":"Salitrillos",
    "gn:population":0,
    "gn:timezone":"America/Mexico_City",
    "iso:country":"MX",
    "name:spa_x_preferred":[
        "Salitrillos"
    ],
    "wof:name":"Salitrillos",
    "wof:placetype":"locality"
},
  "geometry": {"coordinates":[-101.30604,23.17853],"type":"Point"}
}