{
  "type": "Feature",
  "properties": {
    "gn:admin1_code":"10.0",
    "gn:admin2_code":"39.0",
    "gn:asciiname":"Campo de Rosas",
    "gn:country_code":"MX",
    "gn:dem":1966,
    "gn:feature_class":"P",
    "gn:feature_code":"PPL",
    "gn:name":"Campo de Rosas",
    "gn:population":0,
    "gn:timezone":"America/Monterrey",
    "iso:country":"MX",
    "name:spa_x_preferred":[
        "Campo de Rosas"
    ],
    "name:und_x_variant":[
        "Campo Rosas"
    ],
    "wof:name":"Campo de Rosas",
    "wof:placetype":"locality"
},
  "geometry": {"coordinates":[-105.00677,24.93114],"type":"Point"}
}