{
  "type": "Feature",
  "properties": {
    "gn:admin1_code":"11",
    "gn:admin2_code":"19.0",
    "gn:asciiname":"Tejocote de Puriantzicuaro",
    "gn:country_code":"MX",
    "gn:dem":1921,
    "gn:feature_class":"P",
    "gn:feature_code":"PPL",
    "gn:name":"Tejocote de Puriantz\u00edcuaro",
    "gn:population":73,
    "gn:timezone":"America/Mexico_City",
    "iso:country":"MX",
    "name:und_x_variant":[
        "Tejocote de Puriantz\u00edcuaro"
    ],
    "wof:name":"Tejocote de Puriantzicuaro",
    "wof:placetype":"locality",
    "wof:population":73
},
  "geometry": {"coordinates":[-100.55472,20.08556],"type":"Point"}
}