{
  "type": "Feature",
  "properties": {
    "gn:admin1_code":"20",
    "gn:admin2_code":"26.0",
    "gn:asciiname":"Allende",
    "gn:country_code":"MX",
    "gn:dem":2715,
    "gn:feature_class":"P",
    "gn:feature_code":"PPL",
    "gn:name":"Allende",
    "gn:population":212,
    "gn:timezone":"America/Mexico_City",
    "iso:country":"MX",
    "wof:name":"Allende",
    "wof:placetype":"locality",
    "wof:population":212
},
  "geometry": {"coordinates":[-97.53833,16.96944],"type":"Point"}
}