{
  "type": "Feature",
  "properties": {
    "gn:admin1_code":"24",
    "gn:admin2_code":"20.0",
    "gn:asciiname":"Las Escamillas",
    "gn:country_code":"MX",
    "gn:dem":1900,
    "gn:feature_class":"P",
    "gn:feature_code":"PPL",
    "gn:name":"Las Escamillas",
    "gn:population":0,
    "gn:timezone":"America/Mexico_City",
    "iso:country":"MX",
    "name:spa_x_preferred":[
        "Las Escamillas"
    ],
    "wof:name":"Las Escamillas",
    "wof:placetype":"locality"
},
  "geometry": {"coordinates":[-100.77146999999999,23.56766],"type":"Point"}
}