{
  "type": "Feature",
  "properties": {
    "gn:admin1_code":"12",
    "gn:admin2_code":"48.0",
    "gn:asciiname":"Los Cimientos (Los Cimientos de Esquivel)",
    "gn:country_code":"MX",
    "gn:dem":647,
    "gn:feature_class":"P",
    "gn:feature_code":"PPL",
    "gn:name":"Los Cimientos (Los Cimientos de Esquivel)",
    "gn:population":8,
    "gn:timezone":"America/Mexico_City",
    "iso:country":"MX",
    "wof:name":"Los Cimientos (Los Cimientos de Esquivel)",
    "wof:placetype":"locality",
    "wof:population":8
},
  "geometry": {"coordinates":[-101.24605,17.8067],"type":"Point"}
}