{
  "type": "Feature",
  "properties": {
    "gn:admin1_code":"10",
    "gn:admin2_code":"7",
    "gn:asciiname":"Chavez [Granja]",
    "gn:country_code":"MX",
    "gn:dem":1118,
    "gn:feature_class":"P",
    "gn:feature_code":"PPL",
    "gn:name":"Ch\u00e1vez [Granja]",
    "gn:population":38,
    "gn:timezone":"America/Monterrey",
    "iso:country":"MX",
    "name:und_x_variant":[
        "Ch\u00e1vez [Granja]"
    ],
    "wof:name":"Chavez [Granja]",
    "wof:placetype":"locality",
    "wof:population":38
},
  "geometry": {"coordinates":[-103.43617999999999,25.68084],"type":"Point"}
}