{
  "type": "Feature",
  "properties": {
    "gn:admin1_code":"5",
    "gn:admin2_code":"2",
    "gn:asciiname":"La Providencia",
    "gn:country_code":"MX",
    "gn:dem":457,
    "gn:feature_class":"P",
    "gn:feature_code":"PPL",
    "gn:name":"La Providencia",
    "gn:population":23,
    "gn:timezone":"America/Mexico_City",
    "iso:country":"MX",
    "wof:name":"La Providencia",
    "wof:placetype":"locality",
    "wof:population":23
},
  "geometry": {"coordinates":[-92.91556,16.56917],"type":"Point"}
}