{
  "type": "Feature",
  "properties": {
    "gn:admin1_code":"6",
    "gn:admin2_code":"27.0",
    "gn:asciiname":"Nacoybo",
    "gn:country_code":"MX",
    "gn:dem":542,
    "gn:feature_class":"P",
    "gn:feature_code":"PPL",
    "gn:name":"Nacoybo",
    "gn:population":0,
    "gn:timezone":"America/Chihuahua",
    "iso:country":"MX",
    "name:spa_x_preferred":[
        "Nacoybo"
    ],
    "wof:name":"Nacoybo",
    "wof:placetype":"locality"
},
  "geometry": {"coordinates":[-107.56941999999999,26.7759],"type":"Point"}
}