{
  "type": "Feature",
  "properties": {
    "gn:admin1_code":"19",
    "gn:admin2_code":"34",
    "gn:asciiname":"Leyvi",
    "gn:country_code":"MX",
    "gn:dem":430,
    "gn:feature_class":"P",
    "gn:feature_code":"PPL",
    "gn:name":"Leyvi",
    "gn:population":26,
    "gn:timezone":"America/Monterrey",
    "iso:country":"MX",
    "wof:name":"Leyvi",
    "wof:placetype":"locality",
    "wof:population":26
},
  "geometry": {"coordinates":[-100.00391999999999,25.897],"type":"Point"}
}