{
  "type": "Feature",
  "properties": {
    "gn:admin1_code":"30",
    "gn:admin2_code":"11",
    "gn:asciiname":"Paso de la Culata",
    "gn:country_code":"MX",
    "gn:dem":10,
    "gn:feature_class":"P",
    "gn:feature_code":"PPL",
    "gn:name":"Paso de la Culata",
    "gn:population":14,
    "gn:timezone":"America/Mexico_City",
    "iso:country":"MX",
    "wof:name":"Paso de la Culata",
    "wof:placetype":"locality",
    "wof:population":14
},
  "geometry": {"coordinates":[-95.94777999999999,18.87333],"type":"Point"}
}