{
  "type": "Feature",
  "properties": {
    "gn:admin1_code":"22",
    "gn:admin2_code":"13.0",
    "gn:asciiname":"Boquillas",
    "gn:country_code":"MX",
    "gn:dem":1661,
    "gn:feature_class":"P",
    "gn:feature_code":"PPL",
    "gn:name":"Boquillas",
    "gn:population":0,
    "gn:timezone":"America/Mexico_City",
    "iso:country":"MX",
    "name:ceb_x_preferred":[
        "Boquillas"
    ],
    "name:deu_x_preferred":[
        "Boquillas"
    ],
    "name:spa_x_preferred":[
        "Boquillas"
    ],
    "name:swe_x_preferred":[
        "Boquillas"
    ],
    "wof:name":"Boquillas",
    "wof:placetype":"locality"
},
  "geometry": {"coordinates":[-99.91431,21.11615],"type":"Point"}
}