{
  "type": "Feature",
  "properties": {
    "gn:admin1_code":"19",
    "gn:admin2_code":"9.0",
    "gn:asciiname":"Villa Vieja",
    "gn:country_code":"MX",
    "gn:dem":295,
    "gn:feature_class":"P",
    "gn:feature_code":"PPL",
    "gn:name":"Villa Vieja",
    "gn:population":90,
    "gn:timezone":"America/Monterrey",
    "iso:country":"MX",
    "wof:name":"Villa Vieja",
    "wof:placetype":"locality",
    "wof:population":90
},
  "geometry": {"coordinates":[-99.92752,25.53951],"type":"Point"}
}