{
  "type": "Feature",
  "properties": {
    "gn:admin1_code":"25",
    "gn:admin2_code":"1",
    "gn:asciiname":"El Rio",
    "gn:country_code":"MX",
    "gn:dem":16,
    "gn:feature_class":"P",
    "gn:feature_code":"PPL",
    "gn:name":"El R\u00edo",
    "gn:population":26,
    "gn:timezone":"America/Mazatlan",
    "iso:country":"MX",
    "name:und_x_variant":[
        "El R\u00edo"
    ],
    "wof:name":"El Rio",
    "wof:placetype":"locality",
    "wof:population":26
},
  "geometry": {"coordinates":[-109.15509,25.93507],"type":"Point"}
}