{
  "type": "Feature",
  "properties": {
    "gn:admin1_code":"14",
    "gn:admin2_code":"48.0",
    "gn:asciiname":"El Tesorito",
    "gn:country_code":"MX",
    "gn:dem":2165,
    "gn:feature_class":"P",
    "gn:feature_code":"PPL",
    "gn:name":"El Tesorito",
    "gn:population":9,
    "gn:timezone":"America/Mexico_City",
    "iso:country":"MX",
    "wof:name":"El Tesorito",
    "wof:placetype":"locality",
    "wof:population":9
},
  "geometry": {"coordinates":[-102.17167000000001,20.605],"type":"Point"}
}