{
  "type": "Feature",
  "properties": {
    "gn:admin1_code":"4.0",
    "gn:asciiname":"Dos Arbolitos",
    "gn:country_code":"MX",
    "gn:dem":46,
    "gn:feature_class":"P",
    "gn:feature_code":"PPL",
    "gn:name":"Dos Arbolitos",
    "gn:population":0,
    "gn:timezone":"America/Merida",
    "iso:country":"MX",
    "name:spa_x_preferred":[
        "Dos Arbolitos"
    ],
    "wof:name":"Dos Arbolitos",
    "wof:placetype":"locality"
},
  "geometry": {"coordinates":[-90.90803,18.57579],"type":"Point"}
}