{
  "type": "Feature",
  "properties": {
    "gn:admin1_code":"1",
    "gn:admin2_code":"11.0",
    "gn:asciiname":"Ninguno [Taller]",
    "gn:country_code":"MX",
    "gn:dem":1883,
    "gn:feature_class":"P",
    "gn:feature_code":"PPL",
    "gn:name":"Ninguno [Taller]",
    "gn:population":4,
    "gn:timezone":"America/Mexico_City",
    "iso:country":"MX",
    "wof:name":"Ninguno [Taller]",
    "wof:placetype":"locality",
    "wof:population":4
},
  "geometry": {"coordinates":[-102.28222,22.06639],"type":"Point"}
}