{
  "type": "Feature",
  "properties": {
    "gn:admin1_code":"10",
    "gn:admin2_code":"5.0",
    "gn:asciiname":"Arroyo de Patos",
    "gn:country_code":"MX",
    "gn:dem":2325,
    "gn:feature_class":"P",
    "gn:feature_code":"PPL",
    "gn:name":"Arroyo de Patos",
    "gn:population":0,
    "gn:timezone":"America/Monterrey",
    "iso:country":"MX",
    "name:spa_x_preferred":[
        "Arroyo de Patos"
    ],
    "wof:name":"Arroyo de Patos",
    "wof:placetype":"locality"
},
  "geometry": {"coordinates":[-105.24077,23.91804],"type":"Point"}
}