{
  "type": "Feature",
  "properties": {
    "gn:admin1_code":"6",
    "gn:admin2_code":"40.0",
    "gn:asciiname":"El Sapito",
    "gn:country_code":"MX",
    "gn:dem":2403,
    "gn:feature_class":"P",
    "gn:feature_code":"PPL",
    "gn:name":"El Sapito",
    "gn:population":0,
    "gn:timezone":"America/Chihuahua",
    "iso:country":"MX",
    "name:spa_x_preferred":[
        "El Sapito"
    ],
    "wof:name":"El Sapito",
    "wof:placetype":"locality"
},
  "geometry": {"coordinates":[-108.24767,29.79438],"type":"Point"}
}