{
  "type": "Feature",
  "properties": {
    "gn:admin1_code":"6.0",
    "gn:admin2_code":"30.0",
    "gn:asciiname":"Agua Escondida",
    "gn:country_code":"MX",
    "gn:dem":1458,
    "gn:feature_class":"P",
    "gn:feature_code":"PPL",
    "gn:name":"Agua Escondida",
    "gn:population":0,
    "gn:timezone":"America/Chihuahua",
    "iso:country":"MX",
    "name:spa_x_preferred":[
        "Agua Escondida"
    ],
    "wof:name":"Agua Escondida",
    "wof:placetype":"locality"
},
  "geometry": {"coordinates":[-108.28100000000001,27.28897000000001],"type":"Point"}
}