{
  "type": "Feature",
  "properties": {
    "gn:admin1_code":"12.0",
    "gn:admin2_code":"48.0",
    "gn:asciiname":"El Arenoso",
    "gn:country_code":"MX",
    "gn:dem":45,
    "gn:feature_class":"P",
    "gn:feature_code":"PPL",
    "gn:name":"El Arenoso",
    "gn:population":0,
    "gn:timezone":"America/Mexico_City",
    "iso:country":"MX",
    "name:und_x_variant":[
        "Arenoso",
        "El Arenoso"
    ],
    "wof:name":"El Arenoso",
    "wof:placetype":"locality"
},
  "geometry": {"coordinates":[-101.30001,17.57602],"type":"Point"}
}