{
  "type": "Feature",
  "properties": {
    "gn:admin1_code":"5",
    "gn:admin2_code":"59.0",
    "gn:asciiname":"Agua Dulce Tehuacan",
    "gn:country_code":"MX",
    "gn:dem":668,
    "gn:feature_class":"P",
    "gn:feature_code":"PPL",
    "gn:name":"Agua Dulce Tehuac\u00e1n",
    "gn:population":0,
    "gn:timezone":"America/Mexico_City",
    "iso:country":"MX",
    "name:spa_x_preferred":[
        "Agua Dulce Tehuac\u00e1n"
    ],
    "wof:name":"Agua Dulce Tehuacan",
    "wof:placetype":"locality"
},
  "geometry": {"coordinates":[-91.58347999999999,17.06756],"type":"Point"}
}