{
  "type": "Feature",
  "properties": {
    "iso:country":"MX",
    "name:spa_x_preferred":[
        "Nueva Santa Rosalia"
    ],
    "qs:gn_adm0_cc":"MX",
    "qs:gn_local":3983805,
    "qs:gn_nam_loc":"santa rosalia",
    "qs:gn_namadm1":"03",
    "qs:local_max":88,
    "qs:local_sum":114,
    "qs:localhoods":3,
    "qs:name":"Nueva Santa Rosalia",
    "qs:name_adm0":"M\u00e9xico",
    "qs:name_adm1":"Baja California Sur",
    "qs:name_adm2":"Mulege",
    "qs:name_local":"Santa Rosal\u00eda",
    "qs:photo_max":8,
    "qs:photo_sum":16,
    "qs:placetype":"Suburb",
    "qs:quad_count":4,
    "qs:woe_adm0":23424900,
    "qs:woe_adm1":2346266,
    "qs:woe_adm2":12599698,
    "qs:woe_lau":0,
    "qs:woe_local":146916,
    "qs:woe_ver":"7.10.0",
    "wof:lang":[
        "spa"
    ],
    "wof:name":"Nueva Santa Rosalia",
    "wof:placetype":"neighbourhood"
},
  "geometry": {"coordinates":[-112.255554,27.327245],"type":"Point"}
}