{
  "type": "Feature",
  "properties": {
    "gn:admin1_code":"6",
    "gn:admin2_code":"36.0",
    "gn:asciiname":"El Torito",
    "gn:country_code":"MX",
    "gn:dem":1250,
    "gn:feature_class":"P",
    "gn:feature_code":"PPL",
    "gn:name":"El Torito",
    "gn:population":0,
    "gn:timezone":"America/Chihuahua",
    "iso:country":"MX",
    "name:dan_x_preferred":[
        "El Torito"
    ],
    "name:pol_x_preferred":[
        "El Torito"
    ],
    "name:por_x_preferred":[
        "El Torito"
    ],
    "name:spa_x_preferred":[
        "El Torito"
    ],
    "wof:name":"El Torito",
    "wof:placetype":"locality"
},
  "geometry": {"coordinates":[-104.31776000000001,26.80614000000001],"type":"Point"}
}