{
  "type": "Feature",
  "properties": {
    "gn:admin1_code":"20",
    "gn:admin2_code":"535.0",
    "gn:asciiname":"Las Dos Cruces",
    "gn:country_code":"MX",
    "gn:dem":2075,
    "gn:feature_class":"P",
    "gn:feature_code":"PPL",
    "gn:name":"Las Dos Cruces",
    "gn:population":0,
    "gn:timezone":"America/Mexico_City",
    "iso:country":"MX",
    "name:spa_x_preferred":[
        "Las Dos Cruces"
    ],
    "wof:name":"Las Dos Cruces",
    "wof:placetype":"locality"
},
  "geometry": {"coordinates":[-96.99694,16.68306],"type":"Point"}
}