{
  "type": "Feature",
  "properties": {
    "gn:admin1_code":"26",
    "gn:admin2_code":"30.0",
    "gn:asciiname":"Tepeyac",
    "gn:country_code":"MX",
    "gn:dem":169,
    "gn:feature_class":"P",
    "gn:feature_code":"PPL",
    "gn:name":"Tepeyac",
    "gn:population":0,
    "gn:timezone":"America/Hermosillo",
    "iso:country":"MX",
    "name:ces_x_preferred":[
        "Tepeyac"
    ],
    "name:deu_x_preferred":[
        "Tepeyac"
    ],
    "name:epo_x_preferred":[
        "Tepejako"
    ],
    "name:eus_x_preferred":[
        "Tepeyac"
    ],
    "name:fra_x_preferred":[
        "Tepeyac"
    ],
    "name:hun_x_preferred":[
        "Tepeyac"
    ],
    "name:ita_x_preferred":[
        "Tepeyac"
    ],
    "name:nor_x_preferred":[
        "Tepeyac"
    ],
    "name:por_x_preferred":[
        "Tepeyac"
    ],
    "name:spa_x_preferred":[
        "Tepeyac"
    ],
    "name:swe_x_preferred":[
        "Tepeyac"
    ],
    "name:und_x_variant":[
        "Rancho El Tepevac"
    ],
    "wof:name":"Tepeyac",
    "wof:placetype":"locality"
},
  "geometry": {"coordinates":[-111.0869,29.0392],"type":"Point"}
}