{
  "type": "Feature",
  "properties": {
    "gn:admin1_code":"17.0",
    "gn:asciiname":"El Dique",
    "gn:country_code":"MX",
    "gn:dem":1078,
    "gn:feature_class":"P",
    "gn:feature_code":"PPL",
    "gn:name":"El Dique",
    "gn:population":0,
    "gn:timezone":"America/Mexico_City",
    "iso:country":"MX",
    "name:spa_x_preferred":[
        "El Dique"
    ],
    "wof:name":"El Dique",
    "wof:placetype":"locality"
},
  "geometry": {"coordinates":[-99.33002,18.76514],"type":"Point"}
}