{
  "type": "Feature",
  "properties": {
    "gn:admin1_code":"14",
    "gn:admin2_code":"93",
    "gn:asciiname":"El Madrono",
    "gn:country_code":"MX",
    "gn:dem":1955,
    "gn:feature_class":"P",
    "gn:feature_code":"PPL",
    "gn:name":"El Madro\u00f1o",
    "gn:population":19,
    "gn:timezone":"America/Mexico_City",
    "iso:country":"MX",
    "name:und_x_variant":[
        "El Madro\u00f1o"
    ],
    "wof:name":"El Madrono",
    "wof:placetype":"locality",
    "wof:population":19
},
  "geometry": {"coordinates":[-102.78944,20.89806],"type":"Point"}
}