{
  "type": "Feature",
  "properties": {
    "gn:admin1_code":"13",
    "gn:admin2_code":"80.0",
    "gn:asciiname":"Aguacatitla",
    "gn:country_code":"MX",
    "gn:dem":795,
    "gn:feature_class":"P",
    "gn:feature_code":"PPL",
    "gn:name":"Aguacatitla",
    "gn:population":521,
    "gn:timezone":"America/Mexico_City",
    "iso:country":"MX",
    "name:spa_x_preferred":[
        "Aguatitla"
    ],
    "wof:name":"Aguacatitla",
    "wof:placetype":"locality",
    "wof:population":521
},
  "geometry": {"coordinates":[-98.42822,20.86128],"type":"Point"}
}