{
  "type": "Feature",
  "properties": {
    "gn:admin1_code":"19.0",
    "gn:asciiname":"El Resplandor",
    "gn:country_code":"MX",
    "gn:dem":370,
    "gn:feature_class":"P",
    "gn:feature_code":"PPL",
    "gn:name":"El Resplandor",
    "gn:population":0,
    "gn:timezone":"America/Monterrey",
    "iso:country":"MX",
    "name:spa_x_preferred":[
        "El Resplandor"
    ],
    "wof:name":"El Resplandor",
    "wof:placetype":"locality"
},
  "geometry": {"coordinates":[-100.10948999999999,25.83872],"type":"Point"}
}