{
  "type": "Feature",
  "properties": {
    "gn:admin1_code":"18.0",
    "gn:admin2_code":"16.0",
    "gn:asciiname":"Crucero Los Mimbres",
    "gn:country_code":"MX",
    "gn:dem":33,
    "gn:feature_class":"P",
    "gn:feature_code":"PPL",
    "gn:name":"Crucero Los Mimbres",
    "gn:population":0,
    "gn:timezone":"America/Mazatlan",
    "iso:country":"MX",
    "wof:name":"Crucero Los Mimbres",
    "wof:placetype":"locality"
},
  "geometry": {"coordinates":[-105.30833,22.35],"type":"Point"}
}