{
  "type": "Feature",
  "properties": {
    "gn:admin1_code":"28",
    "gn:admin2_code":"8.0",
    "gn:asciiname":"Nuevo Abrevaderos",
    "gn:country_code":"MX",
    "gn:dem":163,
    "gn:feature_class":"P",
    "gn:feature_code":"PPL",
    "gn:name":"Nuevo Abrevaderos",
    "gn:population":0,
    "gn:timezone":"America/Monterrey",
    "iso:country":"MX",
    "name:spa_x_preferred":[
        "Nuevo Abrevaderos"
    ],
    "name:und_x_variant":[
        "El Abrevadero",
        "Abrevaderos",
        "Los Abrevaderos"
    ],
    "wof:name":"Nuevo Abrevaderos",
    "wof:placetype":"locality"
},
  "geometry": {"coordinates":[-98.75937,23.60941],"type":"Point"}
}