{
  "type": "Feature",
  "properties": {
    "gn:admin1_code":"16",
    "gn:admin2_code":"13",
    "gn:asciiname":"La Bejuquera",
    "gn:country_code":"MX",
    "gn:dem":808,
    "gn:feature_class":"P",
    "gn:feature_code":"PPL",
    "gn:name":"La Bejuquera",
    "gn:population":25,
    "gn:timezone":"America/Mexico_City",
    "iso:country":"MX",
    "wof:name":"La Bejuquera",
    "wof:placetype":"locality",
    "wof:population":25
},
  "geometry": {"coordinates":[-100.98361,19.05556],"type":"Point"}
}