{
  "type": "Feature",
  "properties": {
    "gn:admin1_code":"5",
    "gn:admin2_code":"108.0",
    "gn:asciiname":"El Eden",
    "gn:country_code":"MX",
    "gn:dem":666,
    "gn:feature_class":"P",
    "gn:feature_code":"PPL",
    "gn:name":"El Ed\u00e9n",
    "gn:population":4,
    "gn:timezone":"America/Mexico_City",
    "iso:country":"MX",
    "name:und_x_variant":[
        "El Ed\u00e9n"
    ],
    "wof:name":"El Eden",
    "wof:placetype":"locality",
    "wof:population":4
},
  "geometry": {"coordinates":[-93.33056000000001,16.35806],"type":"Point"}
}