{
  "type": "Feature",
  "properties": {
    "gn:admin1_code":"4",
    "gn:admin2_code":"4.0",
    "gn:asciiname":"Valle de Quetzalcoatl",
    "gn:country_code":"MX",
    "gn:dem":30,
    "gn:feature_class":"P",
    "gn:feature_code":"PPL",
    "gn:name":"Valle de Quetzalc\u00f3atl",
    "gn:population":161,
    "gn:timezone":"America/Merida",
    "iso:country":"MX",
    "name:und_x_variant":[
        "Valle de Quetzalc\u00f3atl"
    ],
    "wof:name":"Valle de Quetzalcoatl",
    "wof:placetype":"locality",
    "wof:population":161
},
  "geometry": {"coordinates":[-90.24111000000001,19.22556],"type":"Point"}
}