{
  "type": "Feature",
  "properties": {
    "gn:admin1_code":"30",
    "gn:admin2_code":"189.0",
    "gn:asciiname":"Molinos del Golfo",
    "gn:country_code":"MX",
    "gn:dem":21,
    "gn:feature_class":"P",
    "gn:feature_code":"PPL",
    "gn:name":"Molinos del Golfo",
    "gn:population":5,
    "gn:timezone":"America/Mexico_City",
    "iso:country":"MX",
    "wof:name":"Molinos del Golfo",
    "wof:placetype":"locality",
    "wof:population":5
},
  "geometry": {"coordinates":[-97.38249999999999,20.93222],"type":"Point"}
}