{
  "type": "Feature",
  "properties": {
    "gn:admin1_code":"11.0",
    "gn:admin2_code":"1.0",
    "gn:asciiname":"Boquillas",
    "gn:country_code":"MX",
    "gn:dem":1721,
    "gn:feature_class":"P",
    "gn:feature_code":"PPL",
    "gn:name":"Boquillas",
    "gn:population":0,
    "gn:timezone":"America/Mexico_City",
    "iso:country":"MX",
    "name:ceb_x_preferred":[
        "Boquillas"
    ],
    "name:deu_x_preferred":[
        "Boquillas"
    ],
    "name:swe_x_preferred":[
        "Boquillas"
    ],
    "name:und_x_variant":[
        "Boquilla",
        "Boquillas"
    ],
    "wof:name":"Boquillas",
    "wof:placetype":"locality"
},
  "geometry": {"coordinates":[-101.43333,20.41642],"type":"Point"}
}