{
  "type": "Feature",
  "properties": {
    "gn:admin1_code":"11",
    "gn:admin2_code":"14.0",
    "gn:asciiname":"La Quemadita",
    "gn:country_code":"MX",
    "gn:dem":1993,
    "gn:feature_class":"P",
    "gn:feature_code":"PPL",
    "gn:name":"La Quemadita",
    "gn:population":238,
    "gn:timezone":"America/Mexico_City",
    "iso:country":"MX",
    "wof:name":"La Quemadita",
    "wof:placetype":"locality",
    "wof:population":238
},
  "geometry": {"coordinates":[-100.88943999999999,21.2475],"type":"Point"}
}