{
  "type": "Feature",
  "properties": {
    "gn:admin1_code":"19.0",
    "gn:admin2_code":"50.0",
    "gn:asciiname":"Aquiles Serdan",
    "gn:country_code":"MX",
    "gn:dem":178,
    "gn:feature_class":"P",
    "gn:feature_code":"PPL",
    "gn:name":"Aquiles Serd\u00e1n",
    "gn:population":0,
    "gn:timezone":"America/Monterrey",
    "iso:country":"MX",
    "name:spa_x_preferred":[
        "Aquiles Serd\u00e1n"
    ],
    "name:und_x_variant":[
        "El Mate\u00f1o"
    ],
    "wof:name":"Aquiles Serdan",
    "wof:placetype":"locality"
},
  "geometry": {"coordinates":[-99.79819000000001,26.83323],"type":"Point"}
}