{
  "type": "Feature",
  "properties": {
    "gn:admin1_code":"30",
    "gn:admin2_code":"77",
    "gn:asciiname":"Lino Carvajal",
    "gn:country_code":"MX",
    "gn:dem":22,
    "gn:feature_class":"P",
    "gn:feature_code":"PPL",
    "gn:name":"Lino Carvajal",
    "gn:population":18,
    "gn:timezone":"America/Mexico_City",
    "iso:country":"MX",
    "wof:name":"Lino Carvajal",
    "wof:placetype":"locality",
    "wof:population":18
},
  "geometry": {"coordinates":[-95.48917,18.20806],"type":"Point"}
}