{
  "type": "Feature",
  "properties": {
    "gn:admin1_code":"21",
    "gn:admin2_code":"19.0",
    "gn:asciiname":"Texiquemetl (Los Olivares)",
    "gn:country_code":"MX",
    "gn:dem":1815,
    "gn:feature_class":"P",
    "gn:feature_code":"PPL",
    "gn:name":"Texiqu\u00e9metl (Los Olivares)",
    "gn:population":172,
    "gn:timezone":"America/Mexico_City",
    "iso:country":"MX",
    "name:und_x_variant":[
        "Texiqu\u00e9metl (Los Olivares)"
    ],
    "wof:name":"Texiquemetl (Los Olivares)",
    "wof:placetype":"locality",
    "wof:population":172
},
  "geometry": {"coordinates":[-98.39608,18.89765],"type":"Point"}
}