{
  "type": "Feature",
  "properties": {
    "gn:admin1_code":"5",
    "gn:admin2_code":"30",
    "gn:asciiname":"La Esperanza Cinco de Mayo",
    "gn:country_code":"MX",
    "gn:dem":623,
    "gn:feature_class":"P",
    "gn:feature_code":"PPL",
    "gn:name":"La Esperanza Cinco de Mayo",
    "gn:population":13,
    "gn:timezone":"America/Mexico_City",
    "iso:country":"MX",
    "wof:name":"La Esperanza Cinco de Mayo",
    "wof:placetype":"locality",
    "wof:population":13
},
  "geometry": {"coordinates":[-92.34083,15.80639],"type":"Point"}
}