{
  "type": "Feature",
  "properties": {
    "gn:admin1_code":"11.0",
    "gn:admin2_code":"43.0",
    "gn:asciiname":"Higueras",
    "gn:country_code":"MX",
    "gn:dem":1814,
    "gn:feature_class":"P",
    "gn:feature_code":"PPL",
    "gn:name":"Higueras",
    "gn:population":0,
    "gn:timezone":"America/Mexico_City",
    "iso:country":"MX",
    "name:spa_x_preferred":[
        "Higueras"
    ],
    "name:spa_x_variant":[
        "Ex-Hacienda de Higueras"
    ],
    "name:und_x_variant":[
        "Ca\u00f1ada de Higueras",
        "Las Higueras"
    ],
    "wof:name":"Higueras",
    "wof:placetype":"locality"
},
  "geometry": {"coordinates":[-100.17344,21.24379],"type":"Point"}
}