{
  "type": "Feature",
  "properties": {
    "gn:admin1_code":"28",
    "gn:admin2_code":"40.0",
    "gn:asciiname":"Doce de Octubre",
    "gn:country_code":"MX",
    "gn:dem":11,
    "gn:feature_class":"P",
    "gn:feature_code":"PPL",
    "gn:name":"Doce de Octubre",
    "gn:population":8,
    "gn:timezone":"America/Monterrey",
    "iso:country":"MX",
    "wof:name":"Doce de Octubre",
    "wof:placetype":"locality",
    "wof:population":8
},
  "geometry": {"coordinates":[-97.79528000000001,25.61972],"type":"Point"}
}