{
  "type": "Feature",
  "properties": {
    "gn:admin1_code":"21",
    "gn:admin2_code":"53",
    "gn:asciiname":"El Refugio",
    "gn:country_code":"MX",
    "gn:dem":2552,
    "gn:feature_class":"P",
    "gn:feature_code":"PPL",
    "gn:name":"El Refugio",
    "gn:population":30,
    "gn:timezone":"America/Mexico_City",
    "iso:country":"MX",
    "wof:name":"El Refugio",
    "wof:placetype":"locality",
    "wof:population":30
},
  "geometry": {"coordinates":[-98.17306000000001,19.80285],"type":"Point"}
}