{
  "type": "Feature",
  "properties": {
    "gn:admin1_code":"15",
    "gn:admin2_code":"120",
    "gn:asciiname":"La Zurda [Granja]",
    "gn:country_code":"MX",
    "gn:dem":2264,
    "gn:feature_class":"P",
    "gn:feature_code":"PPL",
    "gn:name":"La Zurda [Granja]",
    "gn:population":14,
    "gn:timezone":"America/Mexico_City",
    "iso:country":"MX",
    "wof:name":"La Zurda [Granja]",
    "wof:placetype":"locality",
    "wof:population":14
},
  "geometry": {"coordinates":[-99.05405,19.79487],"type":"Point"}
}