{
  "type": "Feature",
  "properties": {
    "gn:admin1_code":"15",
    "gn:admin2_code":"106.0",
    "gn:asciiname":"Barrio de Balbuena",
    "gn:country_code":"MX",
    "gn:dem":2580,
    "gn:feature_class":"P",
    "gn:feature_code":"PPL",
    "gn:name":"Barrio de Balbuena",
    "gn:population":461,
    "gn:timezone":"America/Mexico_City",
    "iso:country":"MX",
    "wof:name":"Barrio de Balbuena",
    "wof:placetype":"locality",
    "wof:population":461
},
  "geometry": {"coordinates":[-99.65111,19.43944],"type":"Point"}
}