{
  "type": "Feature",
  "properties": {
    "gn:admin1_code":"25",
    "gn:admin2_code":"17.0",
    "gn:asciiname":"Batamote",
    "gn:country_code":"MX",
    "gn:dem":158,
    "gn:feature_class":"P",
    "gn:feature_code":"PPL",
    "gn:name":"Batamote",
    "gn:population":0,
    "gn:timezone":"America/Mazatlan",
    "iso:country":"MX",
    "name:spa_x_preferred":[
        "Batamote"
    ],
    "wof:name":"Batamote",
    "wof:placetype":"locality"
},
  "geometry": {"coordinates":[-108.48339,26.04011],"type":"Point"}
}