{
  "type": "Feature",
  "properties": {
    "gn:admin1_code":"20",
    "gn:admin2_code":"71.0",
    "gn:asciiname":"La Junta",
    "gn:country_code":"MX",
    "gn:dem":393,
    "gn:feature_class":"P",
    "gn:feature_code":"PPL",
    "gn:name":"La Junta",
    "gn:population":7,
    "gn:timezone":"America/Mexico_City",
    "iso:country":"MX",
    "wof:name":"La Junta",
    "wof:placetype":"locality",
    "wof:population":7
},
  "geometry": {"coordinates":[-96.37917,15.88944],"type":"Point"}
}