{
  "type": "Feature",
  "properties": {
    "gn:admin1_code":"30",
    "gn:admin2_code":"58.0",
    "gn:asciiname":"Ejido de Tlanempa",
    "gn:country_code":"MX",
    "gn:dem":99,
    "gn:feature_class":"P",
    "gn:feature_code":"PPL",
    "gn:name":"Ejido de Tlanempa",
    "gn:population":204,
    "gn:timezone":"America/Mexico_City",
    "iso:country":"MX",
    "name:spa_x_preferred":[
        "Ejido de Tlanempa"
    ],
    "wof:name":"Ejido de Tlanempa",
    "wof:placetype":"locality",
    "wof:population":204
},
  "geometry": {"coordinates":[-97.94224,20.90371],"type":"Point"}
}