{
  "type": "Feature",
  "properties": {
    "gn:admin1_code":"3.0",
    "gn:admin2_code":"8.0",
    "gn:asciiname":"Las Manzanas",
    "gn:country_code":"MX",
    "gn:dem":181,
    "gn:feature_class":"P",
    "gn:feature_code":"PPL",
    "gn:name":"Las Manzanas",
    "gn:population":0,
    "gn:timezone":"America/Mazatlan",
    "iso:country":"MX",
    "name:spa_x_preferred":[
        "Las Manzanas"
    ],
    "wof:name":"Las Manzanas",
    "wof:placetype":"locality"
},
  "geometry": {"coordinates":[-109.50605,23.22922],"type":"Point"}
}