{
  "type": "Feature",
  "properties": {
    "gn:admin1_code":"2",
    "gn:admin2_code":"3",
    "gn:asciiname":"Familia Lona",
    "gn:country_code":"MX",
    "gn:dem":977,
    "gn:feature_class":"P",
    "gn:feature_code":"PPL",
    "gn:name":"Familia Lona",
    "gn:population":32,
    "gn:timezone":"America/Tijuana",
    "iso:country":"MX",
    "wof:name":"Familia Lona",
    "wof:placetype":"locality",
    "wof:population":32
},
  "geometry": {"coordinates":[-116.32167,32.52472],"type":"Point"}
}