{
  "type": "Feature",
  "properties": {
    "gn:admin1_code":"27",
    "gn:admin2_code":"15.0",
    "gn:asciiname":"Reforma (Madrigal 2da. Seccion)",
    "gn:country_code":"MX",
    "gn:dem":29,
    "gn:feature_class":"P",
    "gn:feature_code":"PPL",
    "gn:name":"Reforma (Madrigal 2da. Secci\u00f3n)",
    "gn:population":466,
    "gn:timezone":"America/Mexico_City",
    "iso:country":"MX",
    "name:und_x_variant":[
        "Reforma (Madrigal 2da. Secci\u00f3n)"
    ],
    "wof:name":"Reforma (Madrigal 2da. Seccion)",
    "wof:placetype":"locality",
    "wof:population":466
},
  "geometry": {"coordinates":[-92.80243,17.55711],"type":"Point"}
}