{
  "type": "Feature",
  "properties": {
    "gn:admin1_code":"4",
    "gn:admin2_code":"3.0",
    "gn:asciiname":"El Imposible",
    "gn:country_code":"MX",
    "gn:dem":-1,
    "gn:feature_class":"P",
    "gn:feature_code":"PPL",
    "gn:name":"El Imposible",
    "gn:population":0,
    "gn:timezone":"America/Merida",
    "iso:country":"MX",
    "name:spa_x_preferred":[
        "El Imposible"
    ],
    "name:und_x_variant":[
        "Imposible"
    ],
    "wof:name":"El Imposible",
    "wof:placetype":"locality"
},
  "geometry": {"coordinates":[-91.24720000000001,18.59574],"type":"Point"}
}