{
  "type": "Feature",
  "properties": {
    "gn:admin1_code":"14",
    "gn:admin2_code":"27.0",
    "gn:asciiname":"El Gavilan",
    "gn:country_code":"MX",
    "gn:dem":479,
    "gn:feature_class":"P",
    "gn:feature_code":"PPL",
    "gn:name":"El Gavil\u00e1n",
    "gn:population":6,
    "gn:timezone":"America/Mexico_City",
    "iso:country":"MX",
    "name:und_x_variant":[
        "El Gavil\u00e1n"
    ],
    "wof:name":"El Gavilan",
    "wof:placetype":"locality",
    "wof:population":6
},
  "geometry": {"coordinates":[-104.53972,19.37444],"type":"Point"}
}