{
  "type": "Feature",
  "properties": {
    "gn:admin1_code":"30",
    "gn:admin2_code":"10.0",
    "gn:asciiname":"Equimita",
    "gn:country_code":"MX",
    "gn:dem":981,
    "gn:feature_class":"P",
    "gn:feature_code":"PPL",
    "gn:name":"Equimita",
    "gn:population":137,
    "gn:timezone":"America/Mexico_City",
    "iso:country":"MX",
    "wof:name":"Equimita",
    "wof:placetype":"locality",
    "wof:population":137
},
  "geometry": {"coordinates":[-97.08139,19.76611],"type":"Point"}
}