{
  "type": "Feature",
  "properties": {
    "gn:admin1_code":"28",
    "gn:admin2_code":"37.0",
    "gn:asciiname":"San Enrique",
    "gn:country_code":"MX",
    "gn:dem":8,
    "gn:feature_class":"P",
    "gn:feature_code":"PPL",
    "gn:name":"San Enrique",
    "gn:population":0,
    "gn:timezone":"America/Monterrey",
    "iso:country":"MX",
    "name:spa_x_preferred":[
        "San Enrique"
    ],
    "wof:name":"San Enrique",
    "wof:placetype":"locality"
},
  "geometry": {"coordinates":[-97.88481,23.79765],"type":"Point"}
}