{
  "type": "Feature",
  "properties": {
    "gn:admin1_code":"14",
    "gn:admin2_code":"109",
    "gn:asciiname":"El Banco",
    "gn:country_code":"MX",
    "gn:dem":1799,
    "gn:feature_class":"P",
    "gn:feature_code":"PPL",
    "gn:name":"El Banco",
    "gn:population":22,
    "gn:timezone":"America/Mexico_City",
    "iso:country":"MX",
    "wof:name":"El Banco",
    "wof:placetype":"locality",
    "wof:population":22
},
  "geometry": {"coordinates":[-101.92194000000001,21.13278],"type":"Point"}
}