{
  "type": "Feature",
  "properties": {
    "gn:admin1_code":"26",
    "gn:admin2_code":"18.0",
    "gn:asciiname":"El Sombrerete",
    "gn:country_code":"MX",
    "gn:dem":179,
    "gn:feature_class":"P",
    "gn:feature_code":"PPL",
    "gn:name":"El Sombrerete",
    "gn:population":0,
    "gn:timezone":"America/Hermosillo",
    "iso:country":"MX",
    "name:spa_x_preferred":[
        "El Sombrerete"
    ],
    "wof:name":"El Sombrerete",
    "wof:placetype":"locality"
},
  "geometry": {"coordinates":[-109.97667,27.89861],"type":"Point"}
}