{
  "type": "Feature",
  "properties": {
    "gn:admin1_code":"28.0",
    "gn:admin2_code":"21.0",
    "gn:asciiname":"Los Gavilanes",
    "gn:country_code":"MX",
    "gn:dem":86,
    "gn:feature_class":"P",
    "gn:feature_code":"PPL",
    "gn:name":"Los Gavilanes",
    "gn:population":1,
    "gn:timezone":"America/Monterrey",
    "iso:country":"MX",
    "name:spa_x_preferred":[
        "Los Gavilanes"
    ],
    "wof:name":"Los Gavilanes",
    "wof:placetype":"locality",
    "wof:population":1
},
  "geometry": {"coordinates":[-99.04806000000001,22.76167],"type":"Point"}
}