{
  "type": "Feature",
  "properties": {
    "gn:admin1_code":"25.0",
    "gn:admin2_code":"1.0",
    "gn:asciiname":"Las Compuertas",
    "gn:country_code":"MX",
    "gn:dem":16,
    "gn:feature_class":"P",
    "gn:feature_code":"PPL",
    "gn:name":"Las Compuertas",
    "gn:population":0,
    "gn:timezone":"America/Mazatlan",
    "iso:country":"MX",
    "name:spa_x_preferred":[
        "Las Compuertas"
    ],
    "name:und_x_variant":[
        "Compuerta"
    ],
    "wof:name":"Las Compuertas",
    "wof:placetype":"locality"
},
  "geometry": {"coordinates":[-109.0198,25.84202],"type":"Point"}
}