{
  "type": "Feature",
  "properties": {
    "gn:admin1_code":"18.0",
    "gn:admin2_code":"1.0",
    "gn:asciiname":"La Paloma Nueva Reforma",
    "gn:country_code":"MX",
    "gn:dem":62,
    "gn:feature_class":"P",
    "gn:feature_code":"PPL",
    "gn:name":"La Paloma Nueva Reforma",
    "gn:population":107,
    "gn:timezone":"America/Mazatlan",
    "iso:country":"MX",
    "wof:name":"La Paloma Nueva Reforma",
    "wof:placetype":"locality",
    "wof:population":107
},
  "geometry": {"coordinates":[-105.23480000000001,22.31164],"type":"Point"}
}