{
  "type": "Feature",
  "properties": {
    "gn:admin1_code":"17",
    "gn:asciiname":"San Jose de las Presas",
    "gn:country_code":"MX",
    "gn:dem":2699,
    "gn:feature_class":"P",
    "gn:feature_code":"PPL",
    "gn:name":"San Jos\u00e9 de las Presas",
    "gn:population":0,
    "gn:timezone":"America/Mexico_City",
    "iso:country":"MX",
    "name:spa_x_preferred":[
        "San Jos\u00e9 de las Presas"
    ],
    "wof:name":"San Jose de las Presas",
    "wof:placetype":"locality"
},
  "geometry": {"coordinates":[-98.69971,19.6512],"type":"Point"}
}