{
  "type": "Feature",
  "properties": {
    "gn:admin1_code":"6.0",
    "gn:admin2_code":"66.0",
    "gn:asciiname":"San Jose de Caramechi",
    "gn:country_code":"MX",
    "gn:dem":362,
    "gn:feature_class":"P",
    "gn:feature_code":"PPL",
    "gn:name":"San Jos\u00e9 de Caramechi",
    "gn:population":0,
    "gn:timezone":"America/Chihuahua",
    "iso:country":"MX",
    "name:spa_x_preferred":[
        "San Jos\u00e9 de Caramechi"
    ],
    "wof:name":"San Jose de Caramechi",
    "wof:placetype":"locality"
},
  "geometry": {"coordinates":[-108.84094,27.81309000000001],"type":"Point"}
}