{
  "type": "Feature",
  "properties": {
    "gn:admin1_code":"27.0",
    "gn:asciiname":"San Juan de la Montana",
    "gn:country_code":"MX",
    "gn:dem":69,
    "gn:feature_class":"P",
    "gn:feature_code":"PPL",
    "gn:name":"San Juan de la Monta\u00f1a",
    "gn:population":0,
    "gn:timezone":"America/Mexico_City",
    "iso:country":"MX",
    "name:spa_x_preferred":[
        "San Juan de la Monta\u00f1a"
    ],
    "wof:name":"San Juan de la Montana",
    "wof:placetype":"locality"
},
  "geometry": {"coordinates":[-91.16598999999999,17.45001],"type":"Point"}
}