{
  "type": "Feature",
  "properties": {
    "gn:admin1_code":"15.0",
    "gn:asciiname":"La Pinuela",
    "gn:country_code":"MX",
    "gn:dem":2454,
    "gn:feature_class":"P",
    "gn:feature_code":"PPL",
    "gn:name":"La Pi\u00f1uela",
    "gn:population":0,
    "gn:timezone":"America/Mexico_City",
    "iso:country":"MX",
    "name:spa_x_preferred":[
        "La Pi\u00f1uela"
    ],
    "wof:name":"La Pinuela",
    "wof:placetype":"locality"
},
  "geometry": {"coordinates":[-98.818,19.30627],"type":"Point"}
}