{
  "type": "Feature",
  "properties": {
    "gn:admin1_code":"30.0",
    "gn:admin2_code":"161.0",
    "gn:asciiname":"Grano de Oro",
    "gn:country_code":"MX",
    "gn:dem":31,
    "gn:feature_class":"P",
    "gn:feature_code":"PPL",
    "gn:name":"Grano de Oro",
    "gn:population":3,
    "gn:timezone":"America/Mexico_City",
    "iso:country":"MX",
    "name:spa_x_preferred":[
        "Grano de Oro"
    ],
    "wof:name":"Grano de Oro",
    "wof:placetype":"locality",
    "wof:population":3
},
  "geometry": {"coordinates":[-98.43176,21.64924],"type":"Point"}
}