{
  "type": "Feature",
  "properties": {
    "gn:admin1_code":"16",
    "gn:admin2_code":"97.0",
    "gn:asciiname":"Tierras Flojas",
    "gn:country_code":"MX",
    "gn:dem":802,
    "gn:feature_class":"P",
    "gn:feature_code":"PPL",
    "gn:name":"Tierras Flojas",
    "gn:population":0,
    "gn:timezone":"America/Mexico_City",
    "iso:country":"MX",
    "name:spa_x_preferred":[
        "Tierras Flojas"
    ],
    "wof:name":"Tierras Flojas",
    "wof:placetype":"locality"
},
  "geometry": {"coordinates":[-101.40526,18.96106],"type":"Point"}
}