{
  "type": "Feature",
  "properties": {
    "gn:admin1_code":"15",
    "gn:admin2_code":"1",
    "gn:asciiname":"La Terquedad",
    "gn:country_code":"MX",
    "gn:dem":2664,
    "gn:feature_class":"P",
    "gn:feature_code":"PPL",
    "gn:name":"La Terquedad",
    "gn:population":11,
    "gn:timezone":"America/Mexico_City",
    "iso:country":"MX",
    "wof:name":"La Terquedad",
    "wof:placetype":"locality",
    "wof:population":11
},
  "geometry": {"coordinates":[-99.81603,20.03915],"type":"Point"}
}