{
  "type": "Feature",
  "properties": {
    "gn:admin1_code":"6",
    "gn:admin2_code":"8",
    "gn:asciiname":"Mezquital",
    "gn:country_code":"MX",
    "gn:dem":682,
    "gn:feature_class":"P",
    "gn:feature_code":"PPL",
    "gn:name":"Mezquital",
    "gn:population":9,
    "gn:timezone":"America/Chihuahua",
    "iso:country":"MX",
    "wof:name":"Mezquital",
    "wof:placetype":"locality",
    "wof:population":9
},
  "geometry": {"coordinates":[-107.73685,27.09965],"type":"Point"}
}