{
  "type": "Feature",
  "properties": {
    "gn:admin1_code":"13",
    "gn:admin2_code":"31.0",
    "gn:asciiname":"Los Hoyos",
    "gn:country_code":"MX",
    "gn:dem":1401,
    "gn:feature_class":"P",
    "gn:feature_code":"PPL",
    "gn:name":"Los Hoyos",
    "gn:population":0,
    "gn:timezone":"America/Mexico_City",
    "iso:country":"MX",
    "name:und_x_variant":[
        "Hoyos",
        "Los Hoyos"
    ],
    "wof:name":"Los Hoyos",
    "wof:placetype":"locality"
},
  "geometry": {"coordinates":[-99.22145999999999,20.98675],"type":"Point"}
}