{
  "type": "Feature",
  "properties": {
    "gn:admin1_code":"5",
    "gn:admin2_code":"38.0",
    "gn:asciiname":"San Jose el Porvenir",
    "gn:country_code":"MX",
    "gn:dem":2333,
    "gn:feature_class":"P",
    "gn:feature_code":"PPL",
    "gn:name":"San Jos\u00e9 el Porvenir",
    "gn:population":213,
    "gn:timezone":"America/Mexico_City",
    "iso:country":"MX",
    "name:und_x_variant":[
        "San Jos\u00e9 el Porvenir"
    ],
    "wof:name":"San Jose el Porvenir",
    "wof:placetype":"locality",
    "wof:population":213
},
  "geometry": {"coordinates":[-92.51111,16.70111],"type":"Point"}
}