{
  "type": "Feature",
  "properties": {
    "gn:admin1_code":"19.0",
    "gn:admin2_code":"40.0",
    "gn:asciiname":"San Jeronimo",
    "gn:country_code":"MX",
    "gn:dem":193,
    "gn:feature_class":"P",
    "gn:feature_code":"PPL",
    "gn:name":"San Jer\u00f3nimo",
    "gn:population":0,
    "gn:timezone":"America/Monterrey",
    "iso:country":"MX",
    "name:spa_x_preferred":[
        "San Jer\u00f3nimo"
    ],
    "wof:name":"San Jeronimo",
    "wof:placetype":"locality"
},
  "geometry": {"coordinates":[-99.70689,26.42573],"type":"Point"}
}