{
  "type": "Feature",
  "properties": {
    "iso:country":"MX",
    "qs_pg:aaroncc":"MX",
    "qs_pg:name":"Fracc Los Cedros",
    "qs_pg:name_adm0":"M\u00e9xico",
    "qs_pg:name_adm1":"Tabasco",
    "qs_pg:photos":146,
    "qs_pg:photos_1k":30,
    "qs_pg:photos_9k":1,
    "qs_pg:photos_9r":3,
    "qs_pg:photos_all":146,
    "qs_pg:photos_sr":3,
    "qs_pg:pop_sr":0,
    "qs_pg:qs_pg_placetype":"neighbourhood",
    "qs_pg:qs_pg_placetype_gp":"Suburb",
    "qs_pg:woe_adm0":23424900,
    "woe:adm0_id":23424900,
    "woe:name_adm0":"M\u00e9xico",
    "woe:name_adm1":"Tabasco",
    "woe:placetype":"Suburb",
    "wof:name":"Fracc Los Cedros",
    "wof:placetype":"neighbourhood"
},
  "geometry": {"coordinates":[-92.916702,17.983316],"type":"Point"}
}