{
  "type": "Feature",
  "properties": {
    "gn:admin1_code":"14",
    "gn:admin2_code":"49",
    "gn:asciiname":"Salatito Uno (Santa Ines)",
    "gn:country_code":"MX",
    "gn:dem":1105,
    "gn:feature_class":"P",
    "gn:feature_code":"PPL",
    "gn:name":"Salatito Uno (Santa In\u00e9s)",
    "gn:population":11,
    "gn:timezone":"America/Mexico_City",
    "iso:country":"MX",
    "name:und_x_variant":[
        "Salatito Uno (Santa In\u00e9s)"
    ],
    "wof:name":"Salatito Uno (Santa Ines)",
    "wof:placetype":"locality",
    "wof:population":11
},
  "geometry": {"coordinates":[-103.04778,19.31278],"type":"Point"}
}