{
  "type": "Feature",
  "properties": {
    "gn:admin1_code":"16.0",
    "gn:admin2_code":"10.0",
    "gn:asciiname":"El Pinzan",
    "gn:country_code":"MX",
    "gn:dem":756,
    "gn:feature_class":"P",
    "gn:feature_code":"PPL",
    "gn:name":"El Pinz\u00e1n",
    "gn:population":0,
    "gn:timezone":"America/Mexico_City",
    "iso:country":"MX",
    "name:spa_x_preferred":[
        "El Pinz\u00e1n"
    ],
    "name:spa_x_variant":[
        "Plan del Muleto"
    ],
    "wof:name":"El Pinzan",
    "wof:placetype":"locality"
},
  "geometry": {"coordinates":[-102.37926,18.31143],"type":"Point"}
}