{
  "type": "Feature",
  "properties": {
    "gn:admin1_code":"20",
    "gn:admin2_code":"232.0",
    "gn:asciiname":"Arroyo Achiote",
    "gn:country_code":"MX",
    "gn:dem":72,
    "gn:feature_class":"P",
    "gn:feature_code":"PPL",
    "gn:name":"Arroyo Achiote",
    "gn:population":0,
    "gn:timezone":"America/Mexico_City",
    "iso:country":"MX",
    "name:spa_x_preferred":[
        "Arroyo Achiote"
    ],
    "wof:name":"Arroyo Achiote",
    "wof:placetype":"locality"
},
  "geometry": {"coordinates":[-96.33326,18.08409],"type":"Point"}
}