{
  "type": "Feature",
  "properties": {
    "gn:admin1_code":"16",
    "gn:admin2_code":"92.0",
    "gn:asciiname":"El Pinzanito",
    "gn:country_code":"MX",
    "gn:dem":472,
    "gn:feature_class":"P",
    "gn:feature_code":"PPL",
    "gn:name":"El Pinzanito",
    "gn:population":0,
    "gn:timezone":"America/Mexico_City",
    "iso:country":"MX",
    "name:spa_x_preferred":[
        "El Pinzanito"
    ],
    "wof:name":"El Pinzanito",
    "wof:placetype":"locality"
},
  "geometry": {"coordinates":[-100.79786,18.88091],"type":"Point"}
}