{
  "type": "Feature",
  "properties": {
    "gn:admin1_code":"26.0",
    "gn:admin2_code":"41.0",
    "gn:asciiname":"Las Higueras",
    "gn:country_code":"MX",
    "gn:dem":1047,
    "gn:feature_class":"P",
    "gn:feature_code":"PPL",
    "gn:name":"Las Higueras",
    "gn:population":18,
    "gn:timezone":"America/Hermosillo",
    "iso:country":"MX",
    "name:spa_x_preferred":[
        "Las Higueras"
    ],
    "wof:name":"Las Higueras",
    "wof:placetype":"locality",
    "wof:population":18
},
  "geometry": {"coordinates":[-109.68889,30.31694],"type":"Point"}
}