{
  "type": "Feature",
  "properties": {
    "gn:admin1_code":"19",
    "gn:admin2_code":"35.0",
    "gn:asciiname":"Loma Blanca",
    "gn:country_code":"MX",
    "gn:dem":171,
    "gn:feature_class":"P",
    "gn:feature_code":"PPL",
    "gn:name":"Loma Blanca",
    "gn:population":0,
    "gn:timezone":"America/Monterrey",
    "iso:country":"MX",
    "name:hye_x_preferred":[
        "\u053c\u0578\u0574\u0561 \u0532\u056c\u0561\u0576\u056f\u0561"
    ],
    "name:rus_x_preferred":[
        "\u041b\u043e\u043c\u0430-\u0411\u043b\u0430\u043d\u043a\u0430"
    ],
    "name:spa_x_preferred":[
        "Loma Blanca"
    ],
    "name:und_x_variant":[
        "Rancho Loma Blanca"
    ],
    "wof:name":"Loma Blanca",
    "wof:placetype":"locality"
},
  "geometry": {"coordinates":[-99.46639999999999,26.04928],"type":"Point"}
}