{
  "type": "Feature",
  "properties": {
    "gn:admin1_code":"19",
    "gn:admin2_code":"35.0",
    "gn:asciiname":"Loma Blanca",
    "gn:country_code":"MX",
    "gn:dem":171,
    "gn:feature_class":"P",
    "gn:feature_code":"PPL",
    "gn:name":"Loma Blanca",
    "gn:population":0,
    "gn:timezone":"America/Monterrey",
    "iso:country":"MX",
    "name:spa_x_preferred":[
        "Loma Blanca"
    ],
    "name:und_x_variant":[
        "Rancho Loma Blanca"
    ],
    "wof:name":"Loma Blanca",
    "wof:placetype":"locality"
},
  "geometry": {"coordinates":[-99.46639999999999,26.04928],"type":"Point"}
}