{
  "type": "Feature",
  "properties": {
    "gn:admin1_code":"14",
    "gn:admin2_code":"115.0",
    "gn:asciiname":"Mesa de Capellania",
    "gn:country_code":"MX",
    "gn:dem":1905,
    "gn:feature_class":"P",
    "gn:feature_code":"PPL",
    "gn:name":"Mesa de Capellan\u00eda",
    "gn:population":0,
    "gn:timezone":"America/Mexico_City",
    "iso:country":"MX",
    "name:spa_x_preferred":[
        "Mesa de Capellan\u00eda"
    ],
    "wof:name":"Mesa de Capellania",
    "wof:placetype":"locality"
},
  "geometry": {"coordinates":[-103.54541999999999,21.99163],"type":"Point"}
}