{
  "type": "Feature",
  "properties": {
    "gn:admin1_code":"5.0",
    "gn:asciiname":"Las Isabeles",
    "gn:country_code":"MX",
    "gn:dem":600,
    "gn:feature_class":"P",
    "gn:feature_code":"PPL",
    "gn:name":"Las Isabeles",
    "gn:population":0,
    "gn:timezone":"America/Mexico_City",
    "iso:country":"MX",
    "name:spa_x_preferred":[
        "Las Isabeles"
    ],
    "wof:name":"Las Isabeles",
    "wof:placetype":"locality"
},
  "geometry": {"coordinates":[-91.98302,15.86504],"type":"Point"}
}