{
  "type": "Feature",
  "properties": {
    "gn:admin1_code":"5.0",
    "gn:asciiname":"La Bonanza",
    "gn:country_code":"MX",
    "gn:dem":14,
    "gn:feature_class":"P",
    "gn:feature_code":"PPL",
    "gn:name":"La Bonanza",
    "gn:population":0,
    "gn:timezone":"America/Mexico_City",
    "iso:country":"MX",
    "name:spa_x_preferred":[
        "La Bonanza"
    ],
    "wof:name":"La Bonanza",
    "wof:placetype":"locality"
},
  "geometry": {"coordinates":[-93.76779999999999,15.976],"type":"Point"}
}