{
  "type": "Feature",
  "properties": {
    "gn:admin1_code":"26.0",
    "gn:admin2_code":"46.0",
    "gn:asciiname":"La Sierrita",
    "gn:country_code":"MX",
    "gn:dem":465,
    "gn:feature_class":"P",
    "gn:feature_code":"PPL",
    "gn:name":"La Sierr\u00edta",
    "gn:population":0,
    "gn:timezone":"America/Hermosillo",
    "iso:country":"MX",
    "name:spa_x_preferred":[
        "La Sierr\u00edta"
    ],
    "wof:name":"La Sierrita",
    "wof:placetype":"locality"
},
  "geometry": {"coordinates":[-111.74988999999999,30.72723],"type":"Point"}
}