{
  "type": "Feature",
  "properties": {
    "gn:admin1_code":"2",
    "gn:admin2_code":"1.0",
    "gn:asciiname":"Valladares",
    "gn:country_code":"MX",
    "gn:dem":704,
    "gn:feature_class":"P",
    "gn:feature_code":"PPL",
    "gn:name":"Valladares",
    "gn:population":0,
    "gn:timezone":"America/Tijuana",
    "iso:country":"MX",
    "name:spa_x_preferred":[
        "Valladares"
    ],
    "wof:name":"Valladares",
    "wof:placetype":"locality"
},
  "geometry": {"coordinates":[-115.70395000000001,30.85947],"type":"Point"}
}