{
  "type": "Feature",
  "properties": {
    "gn:admin1_code":"30",
    "gn:admin2_code":"44.0",
    "gn:asciiname":"Agustin Millan",
    "gn:country_code":"MX",
    "gn:dem":824,
    "gn:feature_class":"P",
    "gn:feature_code":"PPL",
    "gn:name":"Agust\u00edn Mill\u00e1n",
    "gn:population":579,
    "gn:timezone":"America/Mexico_City",
    "iso:country":"MX",
    "name:und_x_variant":[
        "Agust\u00edn Mill\u00e1n"
    ],
    "wof:name":"Agustin Millan",
    "wof:placetype":"locality",
    "wof:population":579
},
  "geometry": {"coordinates":[-96.92010000000001,18.88586],"type":"Point"}
}