{
  "type": "Feature",
  "properties": {
    "gn:admin1_code":"2.0",
    "gn:admin2_code":"1.0",
    "gn:asciiname":"Las Higueras",
    "gn:country_code":"MX",
    "gn:dem":93,
    "gn:feature_class":"P",
    "gn:feature_code":"PPL",
    "gn:name":"Las Higueras",
    "gn:population":0,
    "gn:timezone":"America/Tijuana",
    "iso:country":"MX",
    "name:spa_x_preferred":[
        "Las Higueras"
    ],
    "wof:name":"Las Higueras",
    "wof:placetype":"locality"
},
  "geometry": {"coordinates":[-116.11982999999999,31.09061],"type":"Point"}
}