{
  "type": "Feature",
  "properties": {
    "gn:admin1_code":"14.0",
    "gn:admin2_code":"42.0",
    "gn:asciiname":"Mesa Alta",
    "gn:country_code":"MX",
    "gn:dem":2401,
    "gn:feature_class":"P",
    "gn:feature_code":"PPL",
    "gn:name":"Mesa Alta",
    "gn:population":0,
    "gn:timezone":"America/Mexico_City",
    "iso:country":"MX",
    "name:spa_x_preferred":[
        "Mesa Alta"
    ],
    "wof:name":"Mesa Alta",
    "wof:placetype":"locality"
},
  "geometry": {"coordinates":[-103.76804,22.71098],"type":"Point"}
}