{
  "type": "Feature",
  "properties": {
    "gn:admin1_code":"30.0",
    "gn:admin2_code":"189.0",
    "gn:asciiname":"La Tinaja",
    "gn:country_code":"MX",
    "gn:dem":61,
    "gn:feature_class":"P",
    "gn:feature_code":"PPL",
    "gn:name":"La Tinaja",
    "gn:population":0,
    "gn:timezone":"America/Mexico_City",
    "iso:country":"MX",
    "name:spa_x_preferred":[
        "La Tinaja"
    ],
    "wof:name":"La Tinaja",
    "wof:placetype":"locality"
},
  "geometry": {"coordinates":[-97.51786,21.00577],"type":"Point"}
}