{
  "type": "Feature",
  "properties": {
    "gn:admin1_code":"5",
    "gn:admin2_code":"107.0",
    "gn:asciiname":"Embarcadero de Jerico (El Siglo)",
    "gn:country_code":"MX",
    "gn:dem":525,
    "gn:feature_class":"P",
    "gn:feature_code":"PPL",
    "gn:name":"Embarcadero de Jeric\u00f3 (El Siglo)",
    "gn:population":685,
    "gn:timezone":"America/Mexico_City",
    "iso:country":"MX",
    "name:und_x_variant":[
        "Embarcadero de Jeric\u00f3 (El Siglo)"
    ],
    "wof:name":"Embarcadero de Jerico (El Siglo)",
    "wof:placetype":"locality",
    "wof:population":685
},
  "geometry": {"coordinates":[-92.93611,16.20056],"type":"Point"}
}