{
  "type": "Feature",
  "properties": {
    "gn:admin1_code":"30",
    "gn:admin2_code":"109.0",
    "gn:asciiname":"Arroyo Frio",
    "gn:country_code":"MX",
    "gn:dem":194,
    "gn:feature_class":"P",
    "gn:feature_code":"PPL",
    "gn:name":"Arroyo Fr\u00edo",
    "gn:population":586,
    "gn:timezone":"America/Mexico_City",
    "iso:country":"MX",
    "name:spa_x_preferred":[
        "Arroyo Fr\u00edo"
    ],
    "wof:name":"Arroyo Frio",
    "wof:placetype":"locality",
    "wof:population":586
},
  "geometry": {"coordinates":[-96.76524999999999,19.96427000000001],"type":"Point"}
}