{
  "type": "Feature",
  "properties": {
    "gn:admin1_code":"15",
    "gn:admin2_code":"8.0",
    "gn:asciiname":"El Aguacate (El Aguacate San Martin)",
    "gn:country_code":"MX",
    "gn:dem":997,
    "gn:feature_class":"P",
    "gn:feature_code":"PPL",
    "gn:name":"El Aguacate (El Aguacate San Mart\u00edn)",
    "gn:population":120,
    "gn:timezone":"America/Mexico_City",
    "iso:country":"MX",
    "name:und_x_variant":[
        "El Aguacate (El Aguacate San Mart\u00edn)"
    ],
    "wof:name":"El Aguacate (El Aguacate San Martin)",
    "wof:placetype":"locality",
    "wof:population":120
},
  "geometry": {"coordinates":[-100.24758,18.73327],"type":"Point"}
}