{
  "type": "Feature",
  "properties": {
    "gn:admin1_code":"30",
    "gn:admin2_code":"65.0",
    "gn:asciiname":"Paso Ladrillo",
    "gn:country_code":"MX",
    "gn:dem":1155,
    "gn:feature_class":"P",
    "gn:feature_code":"PPL",
    "gn:name":"Paso Ladrillo",
    "gn:population":0,
    "gn:timezone":"America/Mexico_City",
    "iso:country":"MX",
    "name:und_x_variant":[
        "Paso de Ladrillo"
    ],
    "wof:name":"Paso Ladrillo",
    "wof:placetype":"locality"
},
  "geometry": {"coordinates":[-96.85205999999999,19.48217],"type":"Point"}
}