{
  "type": "Feature",
  "properties": {
    "gn:admin1_code":"12",
    "gn:admin2_code":"32",
    "gn:asciiname":"El Tarasco",
    "gn:country_code":"MX",
    "gn:dem":1175,
    "gn:feature_class":"P",
    "gn:feature_code":"PPL",
    "gn:name":"El Tarasco",
    "gn:population":19,
    "gn:timezone":"America/Mexico_City",
    "iso:country":"MX",
    "wof:name":"El Tarasco",
    "wof:placetype":"locality",
    "wof:population":19
},
  "geometry": {"coordinates":[-99.99834,17.8963],"type":"Point"}
}