{
  "type": "Feature",
  "properties": {
    "gn:admin1_code":"16",
    "gn:admin2_code":"102.0",
    "gn:asciiname":"Meson de la Guerra",
    "gn:country_code":"MX",
    "gn:dem":1570,
    "gn:feature_class":"P",
    "gn:feature_code":"PPL",
    "gn:name":"Mes\u00f3n de la Guerra",
    "gn:population":5,
    "gn:timezone":"America/Mexico_City",
    "iso:country":"MX",
    "name:und_x_variant":[
        "Mes\u00f3n de la Guerra"
    ],
    "wof:name":"Meson de la Guerra",
    "wof:placetype":"locality",
    "wof:population":5
},
  "geometry": {"coordinates":[-102.02667,19.29278],"type":"Point"}
}