{
  "type": "Feature",
  "properties": {
    "gn:admin1_code":"1.0",
    "gn:admin2_code":"3.0",
    "gn:asciiname":"La Joja",
    "gn:country_code":"MX",
    "gn:dem":1925,
    "gn:feature_class":"P",
    "gn:feature_code":"PPL",
    "gn:name":"La Joja",
    "gn:population":0,
    "gn:timezone":"America/Mexico_City",
    "iso:country":"MX",
    "wof:name":"La Joja",
    "wof:placetype":"locality"
},
  "geometry": {"coordinates":[-102.78456,21.887],"type":"Point"}
}