{
  "type": "Feature",
  "properties": {
    "gn:admin1_code":"24",
    "gn:admin2_code":"28",
    "gn:asciiname":"Jesus Maria",
    "gn:country_code":"MX",
    "gn:dem":1737,
    "gn:feature_class":"P",
    "gn:feature_code":"PPL",
    "gn:name":"Jes\u00fas Mar\u00eda",
    "gn:population":15,
    "gn:timezone":"America/Mexico_City",
    "iso:country":"MX",
    "name:und_x_variant":[
        "Jes\u00fas Mar\u00eda"
    ],
    "wof:name":"Jesus Maria",
    "wof:placetype":"locality",
    "wof:population":15
},
  "geometry": {"coordinates":[-101.04806000000001,22.53583],"type":"Point"}
}