{
  "type": "Feature",
  "properties": {
    "gn:admin1_code":"6",
    "gn:admin2_code":"50.0",
    "gn:asciiname":"Pena Dorada",
    "gn:country_code":"MX",
    "gn:dem":1553,
    "gn:feature_class":"P",
    "gn:feature_code":"PPL",
    "gn:name":"Pe\u00f1a Dorada",
    "gn:population":0,
    "gn:timezone":"America/Chihuahua",
    "iso:country":"MX",
    "wof:name":"Pena Dorada",
    "wof:placetype":"locality"
},
  "geometry": {"coordinates":[-107.93333,30.25],"type":"Point"}
}