{
  "type": "Feature",
  "properties": {
    "gn:admin1_code":"10",
    "gn:admin2_code":"2.0",
    "gn:asciiname":"Casas Vigias",
    "gn:country_code":"MX",
    "gn:dem":1555,
    "gn:feature_class":"P",
    "gn:feature_code":"PPL",
    "gn:name":"Casas Vigias",
    "gn:population":0,
    "gn:timezone":"America/Monterrey",
    "iso:country":"MX",
    "name:spa_x_preferred":[
        "Casas Vigias"
    ],
    "wof:name":"Casas Vigias",
    "wof:placetype":"locality"
},
  "geometry": {"coordinates":[-106.52056,25.05911],"type":"Point"}
}