{
  "type": "Feature",
  "properties": {
    "gn:admin1_code":"15",
    "gn:admin2_code":"106.0",
    "gn:asciiname":"Ejido San Marcos Yachihuacaltepec",
    "gn:country_code":"MX",
    "gn:dem":2631,
    "gn:feature_class":"P",
    "gn:feature_code":"PPL",
    "gn:name":"Ejido San Marcos Yachihuacaltepec",
    "gn:population":847,
    "gn:timezone":"America/Mexico_City",
    "iso:country":"MX",
    "wof:name":"Ejido San Marcos Yachihuacaltepec",
    "wof:placetype":"locality",
    "wof:population":847
},
  "geometry": {"coordinates":[-99.71778,19.37778],"type":"Point"}
}