{
  "type": "Feature",
  "properties": {
    "gn:admin1_code":"6.0",
    "gn:admin2_code":"11.0",
    "gn:asciiname":"El Cuervo",
    "gn:country_code":"MX",
    "gn:dem":1313,
    "gn:feature_class":"P",
    "gn:feature_code":"PPL",
    "gn:name":"El Cuervo",
    "gn:population":0,
    "gn:timezone":"America/Chihuahua",
    "iso:country":"MX",
    "name:spa_x_preferred":[
        "El Cuervo"
    ],
    "wof:name":"El Cuervo",
    "wof:placetype":"locality"
},
  "geometry": {"coordinates":[-104.47486000000001,28.74908],"type":"Point"}
}