{
  "type": "Feature",
  "properties": {
    "gn:admin1_code":"5",
    "gn:admin2_code":"26.0",
    "gn:asciiname":"Miguel Utrilla (Los Chorros)",
    "gn:country_code":"MX",
    "gn:dem":1312,
    "gn:feature_class":"P",
    "gn:feature_code":"PPL",
    "gn:name":"Miguel Utrilla (Los Chorros)",
    "gn:population":1113,
    "gn:timezone":"America/Mexico_City",
    "iso:country":"MX",
    "wof:name":"Miguel Utrilla (Los Chorros)",
    "wof:placetype":"locality",
    "wof:population":1113
},
  "geometry": {"coordinates":[-92.47972,16.94278],"type":"Point"}
}