{
  "type": "Feature",
  "properties": {
    "gn:admin1_code":"32",
    "gn:admin2_code":"6.0",
    "gn:asciiname":"Rancho el Carmen",
    "gn:country_code":"MX",
    "gn:dem":2059,
    "gn:feature_class":"P",
    "gn:feature_code":"PPL",
    "gn:name":"Rancho el Carmen",
    "gn:population":7,
    "gn:timezone":"America/Mexico_City",
    "iso:country":"MX",
    "wof:name":"Rancho el Carmen",
    "wof:placetype":"locality",
    "wof:population":7
},
  "geometry": {"coordinates":[-102.625,23.56583],"type":"Point"}
}