{
  "type": "Feature",
  "properties": {
    "gn:admin1_code":"16",
    "gn:admin2_code":"49.0",
    "gn:asciiname":"La Cienega",
    "gn:country_code":"MX",
    "gn:dem":1971,
    "gn:feature_class":"P",
    "gn:feature_code":"PPL",
    "gn:name":"La Ci\u00e9nega",
    "gn:population":0,
    "gn:timezone":"America/Mexico_City",
    "iso:country":"MX",
    "name:spa_x_preferred":[
        "La Ci\u00e9nega"
    ],
    "wof:name":"La Cienega",
    "wof:placetype":"locality"
},
  "geometry": {"coordinates":[-101.05757,19.38473],"type":"Point"}
}