{
  "type": "Feature",
  "properties": {
    "gn:admin1_code":"19.0",
    "gn:admin2_code":"23.0",
    "gn:asciiname":"El Uno",
    "gn:country_code":"MX",
    "gn:dem":147,
    "gn:feature_class":"P",
    "gn:feature_code":"PPL",
    "gn:name":"El Uno",
    "gn:population":0,
    "gn:timezone":"America/Monterrey",
    "iso:country":"MX",
    "name:spa_x_preferred":[
        "El Uno"
    ],
    "wof:name":"El Uno",
    "wof:placetype":"locality"
},
  "geometry": {"coordinates":[-99.41522999999999,26.16106],"type":"Point"}
}