{
  "type": "Feature",
  "properties": {
    "gn:admin1_code":"32",
    "gn:admin2_code":"38",
    "gn:asciiname":"Noria de Arriba (J. Guadalupe Jimenez)",
    "gn:country_code":"MX",
    "gn:dem":2318,
    "gn:feature_class":"P",
    "gn:feature_code":"PPL",
    "gn:name":"Noria de Arriba (J. Guadalupe Jim\u00e9nez)",
    "gn:population":30,
    "gn:timezone":"America/Mexico_City",
    "iso:country":"MX",
    "name:und_x_variant":[
        "Noria de Arriba (J. Guadalupe Jim\u00e9nez)"
    ],
    "wof:name":"Noria de Arriba (J. Guadalupe Jimenez)",
    "wof:placetype":"locality",
    "wof:population":30
},
  "geometry": {"coordinates":[-101.58611000000001,22.26222000000001],"type":"Point"}
}