{
  "type": "Feature",
  "properties": {
    "gn:admin1_code":"16",
    "gn:admin2_code":"9",
    "gn:asciiname":"Agua Zarca de Oriente (El Cazo)",
    "gn:country_code":"MX",
    "gn:dem":1941,
    "gn:feature_class":"P",
    "gn:feature_code":"PPL",
    "gn:name":"Agua Zarca de Oriente (El Cazo)",
    "gn:population":34,
    "gn:timezone":"America/Mexico_City",
    "iso:country":"MX",
    "wof:name":"Agua Zarca de Oriente (El Cazo)",
    "wof:placetype":"locality",
    "wof:population":34
},
  "geometry": {"coordinates":[-101.68333,19.19139],"type":"Point"}
}