{
  "type": "Feature",
  "properties": {
    "gn:admin1_code":"30.0",
    "gn:admin2_code":"61.0",
    "gn:asciiname":"El Premio",
    "gn:country_code":"MX",
    "gn:dem":14,
    "gn:feature_class":"P",
    "gn:feature_code":"PPL",
    "gn:name":"El Premio",
    "gn:population":0,
    "gn:timezone":"America/Mexico_City",
    "iso:country":"MX",
    "name:spa_x_preferred":[
        "El Premio"
    ],
    "wof:name":"El Premio",
    "wof:placetype":"locality"
},
  "geometry": {"coordinates":[-93.93483999999999,17.7328],"type":"Point"}
}