{
  "type": "Feature",
  "properties": {
    "gn:admin1_code":"30",
    "gn:admin2_code":"11.0",
    "gn:asciiname":"Don Miguel",
    "gn:country_code":"MX",
    "gn:dem":13,
    "gn:feature_class":"P",
    "gn:feature_code":"PPL",
    "gn:name":"Don Miguel",
    "gn:population":8,
    "gn:timezone":"America/Mexico_City",
    "iso:country":"MX",
    "wof:name":"Don Miguel",
    "wof:placetype":"locality",
    "wof:population":8
},
  "geometry": {"coordinates":[-96.01416999999999,18.94361],"type":"Point"}
}