{
  "type": "Feature",
  "properties": {
    "gn:admin1_code":"6",
    "gn:admin2_code":"66.0",
    "gn:asciiname":"Mesa del Carrizo",
    "gn:country_code":"MX",
    "gn:dem":760,
    "gn:feature_class":"P",
    "gn:feature_code":"PPL",
    "gn:name":"Mesa del Carrizo",
    "gn:population":0,
    "gn:timezone":"America/Chihuahua",
    "iso:country":"MX",
    "name:spa_x_preferred":[
        "Mesa del Carrizo"
    ],
    "wof:name":"Mesa del Carrizo",
    "wof:placetype":"locality"
},
  "geometry": {"coordinates":[-108.81273,27.83074],"type":"Point"}
}