{
  "type": "Feature",
  "properties": {
    "gn:admin1_code":"32",
    "gn:asciiname":"Tajicaringa",
    "gn:cc2":"MX",
    "gn:country_code":"MX",
    "gn:dem":2728,
    "gn:feature_class":"P",
    "gn:feature_code":"PPL",
    "gn:name":"Tajicaringa",
    "gn:population":0,
    "gn:timezone":"America/Monterrey",
    "iso:country":"MX",
    "name:und_x_variant":[
        "Taxicoringa",
        "Tajicaringa"
    ],
    "wof:name":"Tajicaringa",
    "wof:placetype":"locality"
},
  "geometry": {"coordinates":[-104.73333,23.25],"type":"Point"}
}