{
  "type": "Feature",
  "properties": {
    "gn:admin1_code":"25.0",
    "gn:admin2_code":"2.0",
    "gn:asciiname":"Chinitos",
    "gn:country_code":"MX",
    "gn:dem":15,
    "gn:feature_class":"P",
    "gn:feature_code":"PPL",
    "gn:name":"Chinitos",
    "gn:population":0,
    "gn:timezone":"America/Mazatlan",
    "iso:country":"MX",
    "wof:name":"Chinitos",
    "wof:placetype":"locality"
},
  "geometry": {"coordinates":[-107.90000000000001,25.01667],"type":"Point"}
}