{
  "type": "Feature",
  "properties": {
    "gn:admin1_code":"2.0",
    "gn:admin2_code":"2.0",
    "gn:asciiname":"Colonia el Triangulo",
    "gn:country_code":"MX",
    "gn:dem":12,
    "gn:feature_class":"P",
    "gn:feature_code":"PPL",
    "gn:name":"Colonia el Tri\u00e1ngulo",
    "gn:population":33,
    "gn:timezone":"America/Tijuana",
    "iso:country":"MX",
    "name:spa_x_preferred":[
        "Tri\u00e1ngulo"
    ],
    "wof:name":"Colonia el Triangulo",
    "wof:placetype":"locality",
    "wof:population":33
},
  "geometry": {"coordinates":[-115.11111,32.26444],"type":"Point"}
}