{
  "type": "Feature",
  "properties": {
    "gn:admin1_code":"6",
    "gn:admin2_code":"12.0",
    "gn:asciiname":"Sahuachi",
    "gn:country_code":"MX",
    "gn:dem":1992,
    "gn:feature_class":"P",
    "gn:feature_code":"PPL",
    "gn:name":"Sahuachi",
    "gn:population":0,
    "gn:timezone":"America/Chihuahua",
    "iso:country":"MX",
    "name:spa_x_preferred":[
        "Sahuachi"
    ],
    "wof:name":"Sahuachi",
    "wof:placetype":"locality"
},
  "geometry": {"coordinates":[-106.89313,27.52973],"type":"Point"}
}