{
  "type": "Feature",
  "properties": {
    "gn:admin1_code":"30",
    "gn:admin2_code":"161.0",
    "gn:asciiname":"Santa Adela",
    "gn:country_code":"MX",
    "gn:dem":94,
    "gn:feature_class":"P",
    "gn:feature_code":"PPL",
    "gn:name":"Santa Adela",
    "gn:population":0,
    "gn:timezone":"America/Mexico_City",
    "iso:country":"MX",
    "name:spa_x_preferred":[
        "Santa Adela"
    ],
    "wof:name":"Santa Adela",
    "wof:placetype":"locality"
},
  "geometry": {"coordinates":[-98.34558,21.48092],"type":"Point"}
}