{
  "type": "Feature",
  "properties": {
    "gn:admin1_code":"20",
    "gn:asciiname":"Acatitlan",
    "gn:country_code":"MX",
    "gn:dem":2049,
    "gn:feature_class":"P",
    "gn:feature_code":"PPL",
    "gn:name":"Acatitl\u00e1n",
    "gn:population":0,
    "gn:timezone":"America/Mexico_City",
    "iso:country":"MX",
    "name:spa_x_preferred":[
        "Acatitl\u00e1n"
    ],
    "wof:name":"Acatitlan",
    "wof:placetype":"locality"
},
  "geometry": {"coordinates":[-97.55212,18.11624],"type":"Point"}
}