{
  "type": "Feature",
  "properties": {
    "gn:admin1_code":"15",
    "gn:admin2_code":"24.0",
    "gn:asciiname":"Machero",
    "gn:country_code":"MX",
    "gn:dem":2252,
    "gn:feature_class":"P",
    "gn:feature_code":"PPL",
    "gn:name":"Machero",
    "gn:population":385,
    "gn:timezone":"America/Mexico_City",
    "iso:country":"MX",
    "wof:name":"Machero",
    "wof:placetype":"locality",
    "wof:population":385
},
  "geometry": {"coordinates":[-99.16417,19.70889],"type":"Point"}
}