{
  "type": "Feature",
  "properties": {
    "gn:admin1_code":"27.0",
    "gn:asciiname":"Monte Largo Primera Seccion",
    "gn:country_code":"MX",
    "gn:dem":41,
    "gn:feature_class":"P",
    "gn:feature_code":"PPL",
    "gn:name":"Monte Largo Primera Secci\u00f3n",
    "gn:population":0,
    "gn:timezone":"America/Mexico_City",
    "iso:country":"MX",
    "name:spa_x_preferred":[
        "Monte Largo Primera Secci\u00f3n"
    ],
    "name:spa_x_variant":[
        "Monte Largo"
    ],
    "wof:name":"Monte Largo Primera Seccion",
    "wof:placetype":"locality"
},
  "geometry": {"coordinates":[-92.60724999999999,17.82897],"type":"Point"}
}