{
  "type": "Feature",
  "properties": {
    "gn:admin1_code":"20",
    "gn:admin2_code":"14.0",
    "gn:asciiname":"Cofradia",
    "gn:country_code":"MX",
    "gn:dem":144,
    "gn:feature_class":"P",
    "gn:feature_code":"PPL",
    "gn:name":"Cofrad\u00eda",
    "gn:population":0,
    "gn:timezone":"America/Mexico_City",
    "iso:country":"MX",
    "wof:name":"Cofradia",
    "wof:placetype":"locality"
},
  "geometry": {"coordinates":[-95.03333000000001,16.63332999999999],"type":"Point"}
}