{
  "type": "Feature",
  "properties": {
    "gn:admin1_code":"14",
    "gn:admin2_code":"68.0",
    "gn:asciiname":"Las Higuerillas",
    "gn:country_code":"MX",
    "gn:dem":305,
    "gn:feature_class":"P",
    "gn:feature_code":"PPL",
    "gn:name":"Las Higuerillas",
    "gn:population":9,
    "gn:timezone":"America/Mexico_City",
    "iso:country":"MX",
    "wof:name":"Las Higuerillas",
    "wof:placetype":"locality",
    "wof:population":9
},
  "geometry": {"coordinates":[-104.77139,19.63722000000001],"type":"Point"}
}