{
  "type": "Feature",
  "properties": {
    "gn:admin1_code":"10",
    "gn:admin2_code":"39.0",
    "gn:asciiname":"Pomas",
    "gn:country_code":"MX",
    "gn:dem":1985,
    "gn:feature_class":"P",
    "gn:feature_code":"PPL",
    "gn:name":"Pomas",
    "gn:population":0,
    "gn:timezone":"America/Monterrey",
    "iso:country":"MX",
    "name:cat_x_preferred":[
        "Pomars"
    ],
    "name:ceb_x_preferred":[
        "Pomas"
    ],
    "name:deu_x_preferred":[
        "Pomas"
    ],
    "name:eus_x_preferred":[
        "Pomas"
    ],
    "name:fra_x_preferred":[
        "Pomas"
    ],
    "name:hun_x_preferred":[
        "Pomas"
    ],
    "name:hye_x_preferred":[
        "\u054a\u0578\u0574\u0561"
    ],
    "name:ita_x_preferred":[
        "Pomas"
    ],
    "name:kaz_x_preferred":[
        "\u041f\u043e\u043c\u0430\u0441"
    ],
    "name:lat_x_preferred":[
        "Pomas"
    ],
    "name:lmo_x_preferred":[
        "Pomas"
    ],
    "name:mlg_x_preferred":[
        "Pomas"
    ],
    "name:msa_x_preferred":[
        "Pomas"
    ],
    "name:nld_x_preferred":[
        "Pomas"
    ],
    "name:oci_x_preferred":[
        "Pomars"
    ],
    "name:pms_x_preferred":[
        "Pomas"
    ],
    "name:pol_x_preferred":[
        "Pomas"
    ],
    "name:por_x_preferred":[
        "Pomas"
    ],
    "name:ron_x_preferred":[
        "Pomas"
    ],
    "name:rus_x_preferred":[
        "\u041f\u043e\u043c\u0430"
    ],
    "name:slk_x_preferred":[
        "Pomas"
    ],
    "name:spa_x_preferred":[
        "Pomas"
    ],
    "name:swe_x_preferred":[
        "Pomas"
    ],
    "name:ukr_x_preferred":[
        "\u041f\u043e\u043c\u0430\u0441"
    ],
    "name:vie_x_preferred":[
        "Pomas"
    ],
    "name:vol_x_preferred":[
        "Pomas"
    ],
    "name:war_x_preferred":[
        "Pomas"
    ],
    "wof:name":"Pomas",
    "wof:placetype":"locality"
},
  "geometry": {"coordinates":[-105.03917,25.00757],"type":"Point"}
}