{
  "type": "Feature",
  "properties": {
    "gn:admin1_code":"10",
    "gn:admin2_code":"39.0",
    "gn:asciiname":"Pomas",
    "gn:country_code":"MX",
    "gn:dem":1985,
    "gn:feature_class":"P",
    "gn:feature_code":"PPL",
    "gn:name":"Pomas",
    "gn:population":0,
    "gn:timezone":"America/Monterrey",
    "iso:country":"MX",
    "name:spa_x_preferred":[
        "Pomas"
    ],
    "wof:name":"Pomas",
    "wof:placetype":"locality"
},
  "geometry": {"coordinates":[-105.03917,25.00757],"type":"Point"}
}