{
  "type": "Feature",
  "properties": {
    "gn:admin1_code":"11",
    "gn:admin2_code":"14.0",
    "gn:asciiname":"Colonia las Palomas",
    "gn:country_code":"MX",
    "gn:dem":1933,
    "gn:feature_class":"P",
    "gn:feature_code":"PPL",
    "gn:name":"Colonia las Palomas",
    "gn:population":81,
    "gn:timezone":"America/Mexico_City",
    "iso:country":"MX",
    "wof:name":"Colonia las Palomas",
    "wof:placetype":"locality",
    "wof:population":81
},
  "geometry": {"coordinates":[-100.93167,21.14139],"type":"Point"}
}