{
  "type": "Feature",
  "properties": {
    "gn:admin1_code":"32",
    "gn:admin2_code":"7.0",
    "gn:asciiname":"El Charco (La Cigueena)",
    "gn:country_code":"MX",
    "gn:dem":1835,
    "gn:feature_class":"P",
    "gn:feature_code":"PPL",
    "gn:name":"El Charco (La Cig\u00fce\u00f1a)",
    "gn:population":89,
    "gn:timezone":"America/Mexico_City",
    "iso:country":"MX",
    "name:und_x_variant":[
        "El Charco (La Cig\u00fce\u00f1a)"
    ],
    "wof:name":"El Charco (La Cigueena)",
    "wof:placetype":"locality",
    "wof:population":89
},
  "geometry": {"coordinates":[-101.36944,24.41944],"type":"Point"}
}