{
  "type": "Feature",
  "properties": {
    "gn:admin1_code":"16",
    "gn:admin2_code":"102",
    "gn:asciiname":"La Esperanza (La Huerta)",
    "gn:country_code":"MX",
    "gn:dem":1400,
    "gn:feature_class":"P",
    "gn:feature_code":"PPL",
    "gn:name":"La Esperanza (La Huerta)",
    "gn:population":14,
    "gn:timezone":"America/Mexico_City",
    "iso:country":"MX",
    "wof:name":"La Esperanza (La Huerta)",
    "wof:placetype":"locality",
    "wof:population":14
},
  "geometry": {"coordinates":[-102.06389,19.29222],"type":"Point"}
}