{
  "type": "Feature",
  "properties": {
    "gn:admin1_code":"6",
    "gn:admin2_code":"9",
    "gn:asciiname":"Guatopiachi",
    "gn:country_code":"MX",
    "gn:dem":2266,
    "gn:feature_class":"P",
    "gn:feature_code":"PPL",
    "gn:name":"Guatopiachi",
    "gn:population":23,
    "gn:timezone":"America/Chihuahua",
    "iso:country":"MX",
    "wof:name":"Guatopiachi",
    "wof:placetype":"locality",
    "wof:population":23
},
  "geometry": {"coordinates":[-107.56826,27.83936],"type":"Point"}
}