{
  "type": "Feature",
  "properties": {
    "gn:admin1_code":"20",
    "gn:admin2_code":"232.0",
    "gn:asciiname":"Heladio Ramirez Lopez",
    "gn:country_code":"MX",
    "gn:dem":108,
    "gn:feature_class":"P",
    "gn:feature_code":"PPL",
    "gn:name":"Heladio Ram\u00edrez L\u00f3pez",
    "gn:population":153,
    "gn:timezone":"America/Mexico_City",
    "iso:country":"MX",
    "name:und_x_variant":[
        "Heladio Ram\u00edrez L\u00f3pez"
    ],
    "wof:name":"Heladio Ramirez Lopez",
    "wof:placetype":"locality",
    "wof:population":153
},
  "geometry": {"coordinates":[-96.36056000000001,17.97472],"type":"Point"}
}