{
  "type": "Feature",
  "properties": {
    "gn:admin1_code":"26",
    "gn:admin2_code":"55",
    "gn:asciiname":"Ninguno [Jose Luis Murillo]",
    "gn:country_code":"MX",
    "gn:dem":14,
    "gn:feature_class":"P",
    "gn:feature_code":"PPL",
    "gn:name":"Ninguno [Jos\u00e9 Luis Murillo]",
    "gn:population":22,
    "gn:timezone":"America/Hermosillo",
    "iso:country":"MX",
    "name:und_x_variant":[
        "Ninguno [Jos\u00e9 Luis Murillo]"
    ],
    "wof:name":"Ninguno [Jose Luis Murillo]",
    "wof:placetype":"locality",
    "wof:population":22
},
  "geometry": {"coordinates":[-114.91306000000002,32.20472],"type":"Point"}
}