{
  "type": "Feature",
  "properties": {
    "gn:admin1_code":"19.0",
    "gn:asciiname":"Las Cuatro Milpas",
    "gn:country_code":"MX",
    "gn:dem":576,
    "gn:feature_class":"P",
    "gn:feature_code":"PPL",
    "gn:name":"Las Cuatro Milpas",
    "gn:population":0,
    "gn:timezone":"America/Monterrey",
    "iso:country":"MX",
    "name:spa_x_preferred":[
        "Las Cuatro Milpas"
    ],
    "wof:name":"Las Cuatro Milpas",
    "wof:placetype":"locality"
},
  "geometry": {"coordinates":[-100.45842,25.99571],"type":"Point"}
}