{
  "type": "Feature",
  "properties": {
    "gn:admin1_code":"4.0",
    "gn:admin2_code":"11.0",
    "gn:asciiname":"Laguna del Toro",
    "gn:country_code":"MX",
    "gn:dem":40,
    "gn:feature_class":"P",
    "gn:feature_code":"PPL",
    "gn:name":"Laguna del Toro",
    "gn:population":0,
    "gn:timezone":"America/Merida",
    "iso:country":"MX",
    "name:spa_x_preferred":[
        "Laguna del Toro"
    ],
    "wof:name":"Laguna del Toro",
    "wof:placetype":"locality"
},
  "geometry": {"coordinates":[-90.76797000000001,17.83334],"type":"Point"}
}