{
  "type": "Feature",
  "properties": {
    "gn:admin1_code":"26",
    "gn:admin2_code":"3",
    "gn:asciiname":"San Rafael del Sabino (El Sabinito)",
    "gn:country_code":"MX",
    "gn:dem":343,
    "gn:feature_class":"P",
    "gn:feature_code":"PPL",
    "gn:name":"San Rafael del Sabino (El Sabinito)",
    "gn:population":12,
    "gn:timezone":"America/Hermosillo",
    "iso:country":"MX",
    "wof:name":"San Rafael del Sabino (El Sabinito)",
    "wof:placetype":"locality",
    "wof:population":12
},
  "geometry": {"coordinates":[-108.79056,27.3225],"type":"Point"}
}