{
  "type": "Feature",
  "properties": {
    "gn:admin1_code":"13",
    "gn:admin2_code":"53",
    "gn:asciiname":"El Mirador",
    "gn:country_code":"MX",
    "gn:dem":1895,
    "gn:feature_class":"P",
    "gn:feature_code":"PPL",
    "gn:name":"El Mirador",
    "gn:population":20,
    "gn:timezone":"America/Mexico_City",
    "iso:country":"MX",
    "wof:name":"El Mirador",
    "wof:placetype":"locality",
    "wof:population":20
},
  "geometry": {"coordinates":[-98.28060000000001,20.41742],"type":"Point"}
}