{
  "type": "Feature",
  "properties": {
    "gn:admin1_code":"14.0",
    "gn:admin2_code":"68.0",
    "gn:asciiname":"Las Pintadas",
    "gn:country_code":"MX",
    "gn:dem":753,
    "gn:feature_class":"P",
    "gn:feature_code":"PPL",
    "gn:name":"Las Pintadas",
    "gn:population":0,
    "gn:timezone":"America/Mexico_City",
    "iso:country":"MX",
    "name:spa_x_preferred":[
        "Las Pintadas"
    ],
    "wof:name":"Las Pintadas",
    "wof:placetype":"locality"
},
  "geometry": {"coordinates":[-104.71948999999999,19.83212],"type":"Point"}
}