{
  "type": "Feature",
  "properties": {
    "gn:admin1_code":"14",
    "gn:admin2_code":"46",
    "gn:asciiname":"Las Irlas",
    "gn:country_code":"MX",
    "gn:dem":1673,
    "gn:feature_class":"P",
    "gn:feature_code":"PPL",
    "gn:name":"Las Irlas",
    "gn:population":10,
    "gn:timezone":"America/Mexico_City",
    "iso:country":"MX",
    "wof:name":"Las Irlas",
    "wof:placetype":"locality",
    "wof:population":10
},
  "geometry": {"coordinates":[-102.61167,21.17389],"type":"Point"}
}