{
  "type": "Feature",
  "properties": {
    "gn:admin1_code":"31.0",
    "gn:asciiname":"Xceh",
    "gn:country_code":"MX",
    "gn:dem":20,
    "gn:feature_class":"P",
    "gn:feature_code":"PPL",
    "gn:name":"Xceh",
    "gn:population":0,
    "gn:timezone":"America/Merida",
    "iso:country":"MX",
    "name:spa_x_preferred":[
        "Xceh"
    ],
    "wof:name":"Xceh",
    "wof:placetype":"locality"
},
  "geometry": {"coordinates":[-88.15869000000001,21.07136],"type":"Point"}
}