{
  "type": "Feature",
  "properties": {
    "gn:admin1_code":"10",
    "gn:admin2_code":"5.0",
    "gn:asciiname":"San Lorenzo Calderon",
    "gn:country_code":"MX",
    "gn:dem":1882,
    "gn:feature_class":"P",
    "gn:feature_code":"PPL",
    "gn:name":"San Lorenzo Calder\u00f3n",
    "gn:population":0,
    "gn:timezone":"America/Monterrey",
    "iso:country":"MX",
    "name:spa_x_preferred":[
        "San Lorenzo Calder\u00f3n"
    ],
    "wof:name":"San Lorenzo Calderon",
    "wof:placetype":"locality"
},
  "geometry": {"coordinates":[-104.55862,23.92663],"type":"Point"}
}