{
  "type": "Feature",
  "properties": {
    "gn:admin1_code":"24",
    "gn:admin2_code":"20.0",
    "gn:asciiname":"El Herradero",
    "gn:country_code":"MX",
    "gn:dem":1681,
    "gn:feature_class":"P",
    "gn:feature_code":"PPL",
    "gn:name":"El Herradero",
    "gn:population":0,
    "gn:timezone":"America/Mexico_City",
    "iso:country":"MX",
    "name:spa_x_preferred":[
        "El Herradero"
    ],
    "wof:name":"El Herradero",
    "wof:placetype":"locality"
},
  "geometry": {"coordinates":[-100.68134000000001,23.63553],"type":"Point"}
}