{
  "type": "Feature",
  "properties": {
    "gn:admin1_code":"21",
    "gn:admin2_code":"53.0",
    "gn:asciiname":"Almeya Casa Blanca",
    "gn:country_code":"MX",
    "gn:dem":2313,
    "gn:feature_class":"P",
    "gn:feature_code":"PPL",
    "gn:name":"Almeya Casa Blanca",
    "gn:population":0,
    "gn:timezone":"America/Mexico_City",
    "iso:country":"MX",
    "name:spa_x_preferred":[
        "Almeya Casa Blanca"
    ],
    "name:und_x_variant":[
        "Almeya"
    ],
    "wof:name":"Almeya Casa Blanca",
    "wof:placetype":"locality"
},
  "geometry": {"coordinates":[-98.02097000000001,19.79974],"type":"Point"}
}