{
  "type": "Feature",
  "properties": {
    "gn:admin1_code":"5.0",
    "gn:admin2_code":"39.0",
    "gn:asciiname":"Cobadonga",
    "gn:country_code":"MX",
    "gn:dem":738,
    "gn:feature_class":"P",
    "gn:feature_code":"PPL",
    "gn:name":"Cobadonga",
    "gn:population":0,
    "gn:timezone":"America/Mexico_City",
    "iso:country":"MX",
    "name:spa_x_preferred":[
        "Cobadonga"
    ],
    "wof:name":"Cobadonga",
    "wof:placetype":"locality"
},
  "geometry": {"coordinates":[-92.63699,17.17278],"type":"Point"}
}