{
  "type": "Feature",
  "properties": {
    "gn:admin1_code":"5",
    "gn:admin2_code":"51",
    "gn:asciiname":"El Encuentro",
    "gn:country_code":"MX",
    "gn:dem":36,
    "gn:feature_class":"P",
    "gn:feature_code":"PPL",
    "gn:name":"El Encuentro",
    "gn:population":13,
    "gn:timezone":"America/Mexico_City",
    "iso:country":"MX",
    "name:ceb_x_preferred":[
        "El Encuentro"
    ],
    "name:swe_x_preferred":[
        "El Encuentro"
    ],
    "wof:name":"El Encuentro",
    "wof:placetype":"locality",
    "wof:population":13
},
  "geometry": {"coordinates":[-92.91722,15.42167],"type":"Point"}
}