{
  "type": "Feature",
  "properties": {
    "gn:admin1_code":"26",
    "gn:admin2_code":"21.0",
    "gn:asciiname":"La Estacada",
    "gn:country_code":"MX",
    "gn:dem":308,
    "gn:feature_class":"P",
    "gn:feature_code":"PPL",
    "gn:name":"La Estacada",
    "gn:population":1,
    "gn:timezone":"America/Hermosillo",
    "iso:country":"MX",
    "name:spa_x_preferred":[
        "La Estacada"
    ],
    "wof:name":"La Estacada",
    "wof:placetype":"locality",
    "wof:population":1
},
  "geometry": {"coordinates":[-110.30638999999999,28.60972000000001],"type":"Point"}
}