{
  "type": "Feature",
  "properties": {
    "gn:admin1_code":"15.0",
    "gn:admin2_code":"105.0",
    "gn:asciiname":"Cacahuananche",
    "gn:country_code":"MX",
    "gn:dem":504,
    "gn:feature_class":"P",
    "gn:feature_code":"PPL",
    "gn:name":"Cacahuananche",
    "gn:population":0,
    "gn:timezone":"America/Mexico_City",
    "iso:country":"MX",
    "name:spa_x_preferred":[
        "Cacahuananche"
    ],
    "name:spa_x_variant":[
        "La Palmita"
    ],
    "wof:name":"Cacahuananche",
    "wof:placetype":"locality"
},
  "geometry": {"coordinates":[-100.24511,18.43745],"type":"Point"}
}