{
  "type": "Feature",
  "properties": {
    "gn:admin1_code":"30",
    "gn:admin2_code":"211.0",
    "gn:asciiname":"El Jaral",
    "gn:country_code":"MX",
    "gn:dem":33,
    "gn:feature_class":"P",
    "gn:feature_code":"PPL",
    "gn:name":"El Jaral",
    "gn:population":5,
    "gn:timezone":"America/Mexico_City",
    "iso:country":"MX",
    "wof:name":"El Jaral",
    "wof:placetype":"locality",
    "wof:population":5
},
  "geometry": {"coordinates":[-96.93944,20.22361],"type":"Point"}
}