{
  "type": "Feature",
  "properties": {
    "gn:admin1_code":"25",
    "gn:admin2_code":"17.0",
    "gn:asciiname":"Sauz",
    "gn:country_code":"MX",
    "gn:dem":851,
    "gn:feature_class":"P",
    "gn:feature_code":"PPL",
    "gn:name":"Sauz",
    "gn:population":0,
    "gn:timezone":"America/Mazatlan",
    "iso:country":"MX",
    "name:spa_x_preferred":[
        "Sauz"
    ],
    "wof:name":"Sauz",
    "wof:placetype":"locality"
},
  "geometry": {"coordinates":[-107.57467,26.15691],"type":"Point"}
}