{
  "type": "Feature",
  "properties": {
    "gn:admin1_code":"20",
    "gn:admin2_code":"208.0",
    "gn:asciiname":"San Pedro Yososcua",
    "gn:country_code":"MX",
    "gn:dem":2111,
    "gn:feature_class":"P",
    "gn:feature_code":"PPL",
    "gn:name":"San Pedro Yososcu\u00e1",
    "gn:population":94,
    "gn:timezone":"America/Mexico_City",
    "iso:country":"MX",
    "name:mix_x_preferred":[
        "Yososkua"
    ],
    "name:und_x_variant":[
        "San Pedro Yososcu\u00e1"
    ],
    "wof:name":"San Pedro Yososcua",
    "wof:placetype":"locality",
    "wof:population":94
},
  "geometry": {"coordinates":[-97.81417,17.26028],"type":"Point"}
}