{
  "type": "Feature",
  "properties": {
    "gn:admin1_code":"5",
    "gn:admin2_code":"59.0",
    "gn:asciiname":"Yaxala",
    "gn:country_code":"MX",
    "gn:dem":697,
    "gn:feature_class":"P",
    "gn:feature_code":"PPL",
    "gn:name":"Yaxala",
    "gn:population":218,
    "gn:timezone":"America/Mexico_City",
    "iso:country":"MX",
    "wof:name":"Yaxala",
    "wof:placetype":"locality",
    "wof:population":218
},
  "geometry": {"coordinates":[-91.70278,16.89777999999999],"type":"Point"}
}