{
  "type": "Feature",
  "properties": {
    "gn:admin1_code":"10",
    "gn:admin2_code":"14",
    "gn:asciiname":"Los Perros",
    "gn:country_code":"MX",
    "gn:dem":1067,
    "gn:feature_class":"P",
    "gn:feature_code":"PPL",
    "gn:name":"Los Perros",
    "gn:population":21,
    "gn:timezone":"America/Monterrey",
    "iso:country":"MX",
    "wof:name":"Los Perros",
    "wof:placetype":"locality",
    "wof:population":21
},
  "geometry": {"coordinates":[-104.62121999999999,22.68118],"type":"Point"}
}