{
  "type": "Feature",
  "properties": {
    "gn:admin1_code":"5",
    "gn:admin2_code":"100.0",
    "gn:asciiname":"La Ilusion",
    "gn:country_code":"MX",
    "gn:dem":977,
    "gn:feature_class":"P",
    "gn:feature_code":"PPL",
    "gn:name":"La Ilusi\u00f3n",
    "gn:population":112,
    "gn:timezone":"America/Mexico_City",
    "iso:country":"MX",
    "name:und_x_variant":[
        "La Ilusi\u00f3n"
    ],
    "wof:name":"La Ilusion",
    "wof:placetype":"locality",
    "wof:population":112
},
  "geometry": {"coordinates":[-92.32889,17.24944],"type":"Point"}
}