{
  "type": "Feature",
  "properties": {
    "gn:admin1_code":"19",
    "gn:admin2_code":"22.0",
    "gn:asciiname":"La Piedra",
    "gn:country_code":"MX",
    "gn:dem":347,
    "gn:feature_class":"P",
    "gn:feature_code":"PPL",
    "gn:name":"La Piedra",
    "gn:population":0,
    "gn:timezone":"America/Monterrey",
    "iso:country":"MX",
    "name:spa_x_preferred":[
        "La Piedra"
    ],
    "wof:name":"La Piedra",
    "wof:placetype":"locality"
},
  "geometry": {"coordinates":[-99.77316999999999,25.2904],"type":"Point"}
}