{
  "type": "Feature",
  "properties": {
    "gn:admin1_code":"26",
    "gn:admin2_code":"8.0",
    "gn:asciiname":"Corachi",
    "gn:country_code":"MX",
    "gn:dem":729,
    "gn:feature_class":"P",
    "gn:feature_code":"PPL",
    "gn:name":"Corachi",
    "gn:population":0,
    "gn:timezone":"America/Hermosillo",
    "iso:country":"MX",
    "name:spa_x_preferred":[
        "Corachi"
    ],
    "wof:name":"Corachi",
    "wof:placetype":"locality"
},
  "geometry": {"coordinates":[-109.12224999999999,29.72643],"type":"Point"}
}