{
  "type": "Feature",
  "properties": {
    "gn:admin1_code":"14",
    "gn:admin2_code":"71",
    "gn:asciiname":"Huilotan",
    "gn:country_code":"MX",
    "gn:dem":1139,
    "gn:feature_class":"P",
    "gn:feature_code":"PPL",
    "gn:name":"Huilot\u00e1n",
    "gn:population":16,
    "gn:timezone":"America/Mexico_City",
    "iso:country":"MX",
    "name:und_x_variant":[
        "Huilot\u00e1n"
    ],
    "wof:name":"Huilotan",
    "wof:placetype":"locality",
    "wof:population":16
},
  "geometry": {"coordinates":[-103.39610999999999,20.95889],"type":"Point"}
}