{
  "type": "Feature",
  "properties": {
    "gn:admin1_code":"10.0",
    "gn:admin2_code":"4.0",
    "gn:asciiname":"Aguaje de Morteros",
    "gn:country_code":"MX",
    "gn:dem":1680,
    "gn:feature_class":"P",
    "gn:feature_code":"PPL",
    "gn:name":"Aguaje de Morteros",
    "gn:population":0,
    "gn:timezone":"America/Monterrey",
    "iso:country":"MX",
    "name:spa_x_preferred":[
        "Aguaje de Morteros"
    ],
    "wof:name":"Aguaje de Morteros",
    "wof:placetype":"locality"
},
  "geometry": {"coordinates":[-103.95199,24.92894],"type":"Point"}
}