{
  "type": "Feature",
  "properties": {
    "gn:admin1_code":"5",
    "gn:admin2_code":"49.0",
    "gn:asciiname":"K'Ante'El",
    "gn:country_code":"MX",
    "gn:dem":2032,
    "gn:feature_class":"P",
    "gn:feature_code":"PPL",
    "gn:name":"K'Ante'El",
    "gn:population":107,
    "gn:timezone":"America/Mexico_City",
    "iso:country":"MX",
    "wof:name":"K'Ante'El",
    "wof:placetype":"locality",
    "wof:population":107
},
  "geometry": {"coordinates":[-92.71138999999999,16.87194],"type":"Point"}
}