{
  "type": "Feature",
  "properties": {
    "gn:admin1_code":"21",
    "gn:admin2_code":"49.0",
    "gn:asciiname":"Axocopactla",
    "gn:country_code":"MX",
    "gn:dem":1945,
    "gn:feature_class":"P",
    "gn:feature_code":"PPL",
    "gn:name":"Axocopactla",
    "gn:population":130,
    "gn:timezone":"America/Mexico_City",
    "iso:country":"MX",
    "wof:name":"Axocopactla",
    "wof:placetype":"locality",
    "wof:population":130
},
  "geometry": {"coordinates":[-97.97756,20.06684],"type":"Point"}
}