{
  "type": "Feature",
  "properties": {
    "gn:admin1_code":"30",
    "gn:admin2_code":"61.0",
    "gn:asciiname":"Trinidad",
    "gn:cc2":"MX",
    "gn:country_code":"MX",
    "gn:dem":11,
    "gn:feature_class":"P",
    "gn:feature_code":"PPL",
    "gn:name":"Trinidad",
    "gn:population":0,
    "gn:timezone":"America/Mexico_City",
    "iso:country":"MX",
    "name:und_x_variant":[
        "La Trinidad",
        "Trinidad"
    ],
    "wof:name":"Trinidad",
    "wof:placetype":"locality"
},
  "geometry": {"coordinates":[-94.03333000000001,17.75],"type":"Point"}
}