{
  "type": "Feature",
  "properties": {
    "gn:admin1_code":"7",
    "gn:admin2_code":"33.0",
    "gn:asciiname":"Nueva Candelaria",
    "gn:country_code":"MX",
    "gn:dem":1100,
    "gn:feature_class":"P",
    "gn:feature_code":"PPL",
    "gn:name":"Nueva Candelaria",
    "gn:population":0,
    "gn:timezone":"America/Monterrey",
    "iso:country":"MX",
    "name:spa_x_preferred":[
        "Nueva Candelaria"
    ],
    "wof:name":"Nueva Candelaria",
    "wof:placetype":"locality"
},
  "geometry": {"coordinates":[-102.95864,25.72091],"type":"Point"}
}