{
  "type": "Feature",
  "properties": {
    "gn:admin1_code":"6",
    "gn:admin2_code":"4.0",
    "gn:asciiname":"Los Compadres",
    "gn:country_code":"MX",
    "gn:dem":1407,
    "gn:feature_class":"P",
    "gn:feature_code":"PPL",
    "gn:name":"Los Compadres",
    "gn:population":0,
    "gn:timezone":"America/Chihuahua",
    "iso:country":"MX",
    "name:bre_x_preferred":[
        "Los Compadres"
    ],
    "name:ell_x_preferred":[
        "Los Compadres"
    ],
    "name:epo_x_preferred":[
        "D\u00fao Los Compadres"
    ],
    "name:ita_x_preferred":[
        "Los Compadres"
    ],
    "name:spa_x_preferred":[
        "Los Compadres"
    ],
    "name:spa_x_variant":[
        "D\u00fao Los Compadres"
    ],
    "wof:name":"Los Compadres",
    "wof:placetype":"locality"
},
  "geometry": {"coordinates":[-105.83266,28.64583],"type":"Point"}
}