{
  "type": "Feature",
  "properties": {
    "gn:admin1_code":"24",
    "gn:admin2_code":"20",
    "gn:asciiname":"Rancho Santa Elena",
    "gn:country_code":"MX",
    "gn:dem":1336,
    "gn:feature_class":"P",
    "gn:feature_code":"PPL",
    "gn:name":"Rancho Santa Elena",
    "gn:population":26,
    "gn:timezone":"America/Mexico_City",
    "iso:country":"MX",
    "wof:name":"Rancho Santa Elena",
    "wof:placetype":"locality",
    "wof:population":26
},
  "geometry": {"coordinates":[-100.60556,23.28194],"type":"Point"}
}