{
  "type": "Feature",
  "properties": {
    "gn:admin1_code":"22",
    "gn:admin2_code":"18",
    "gn:asciiname":"El Pedregal",
    "gn:country_code":"MX",
    "gn:dem":1769,
    "gn:feature_class":"P",
    "gn:feature_code":"PPL",
    "gn:name":"El Pedregal",
    "gn:population":17,
    "gn:timezone":"America/Mexico_City",
    "iso:country":"MX",
    "wof:name":"El Pedregal",
    "wof:placetype":"locality",
    "wof:population":17
},
  "geometry": {"coordinates":[-99.98056,20.92889],"type":"Point"}
}