{
  "type": "Feature",
  "properties": {
    "gn:admin1_code":"10",
    "gn:admin2_code":"12.0",
    "gn:asciiname":"Las Lules [Granja]",
    "gn:country_code":"MX",
    "gn:dem":1157,
    "gn:feature_class":"P",
    "gn:feature_code":"PPL",
    "gn:name":"Las Lules [Granja]",
    "gn:population":6,
    "gn:timezone":"America/Monterrey",
    "iso:country":"MX",
    "wof:name":"Las Lules [Granja]",
    "wof:placetype":"locality",
    "wof:population":6
},
  "geometry": {"coordinates":[-103.66589999999999,25.47806],"type":"Point"}
}