{
  "type": "Feature",
  "properties": {
    "gn:admin1_code":"18.0",
    "gn:admin2_code":"7.0",
    "gn:asciiname":"El Zoquite",
    "gn:country_code":"MX",
    "gn:dem":1420,
    "gn:feature_class":"P",
    "gn:feature_code":"PPL",
    "gn:name":"El Zoquite",
    "gn:population":0,
    "gn:timezone":"America/Mazatlan",
    "iso:country":"MX",
    "name:spa_x_preferred":[
        "El Zoquite"
    ],
    "wof:name":"El Zoquite",
    "wof:placetype":"locality"
},
  "geometry": {"coordinates":[-104.50641,21.19499],"type":"Point"}
}