{
  "type": "Feature",
  "properties": {
    "gn:admin1_code":"21",
    "gn:admin2_code":"139.0",
    "gn:asciiname":"Nueva Rosita",
    "gn:country_code":"MX",
    "gn:dem":1284,
    "gn:feature_class":"P",
    "gn:feature_code":"PPL",
    "gn:name":"Nueva Rosita",
    "gn:population":60,
    "gn:timezone":"America/Mexico_City",
    "iso:country":"MX",
    "name:ita_x_preferred":[
        "Nueva Rosita"
    ],
    "name:nld_x_preferred":[
        "Nueva Rosita"
    ],
    "name:pol_x_preferred":[
        "Nueva Rosita"
    ],
    "name:rus_x_preferred":[
        "\u041d\u0443\u044d\u0432\u0430-\u0420\u043e\u0441\u0438\u0442\u0430"
    ],
    "name:sco_x_preferred":[
        "Nueva Rosita"
    ],
    "name:spa_x_preferred":[
        "Nueva Rosita"
    ],
    "name:srp_x_preferred":[
        "\u041d\u0443\u0435\u0432\u0430 \u0420\u043e\u0441\u0438\u0442\u0430"
    ],
    "wof:name":"Nueva Rosita",
    "wof:placetype":"locality",
    "wof:population":60
},
  "geometry": {"coordinates":[-98.16331,18.14798],"type":"Point"}
}