{
  "type": "Feature",
  "properties": {
    "gn:admin1_code":"15",
    "gn:admin2_code":"114.0",
    "gn:asciiname":"Campo Nuevo",
    "gn:country_code":"MX",
    "gn:dem":2707,
    "gn:feature_class":"P",
    "gn:feature_code":"PPL",
    "gn:name":"Campo Nuevo",
    "gn:population":205,
    "gn:timezone":"America/Mexico_City",
    "iso:country":"MX",
    "wof:name":"Campo Nuevo",
    "wof:placetype":"locality",
    "wof:population":205
},
  "geometry": {"coordinates":[-100.12389,19.49361],"type":"Point"}
}