{
  "type": "Feature",
  "properties": {
    "gn:admin1_code":"4.0",
    "gn:asciiname":"San Inocente",
    "gn:country_code":"MX",
    "gn:dem":-1,
    "gn:feature_class":"P",
    "gn:feature_code":"PPL",
    "gn:name":"San Inocente",
    "gn:population":0,
    "gn:timezone":"America/Merida",
    "iso:country":"MX",
    "name:spa_x_preferred":[
        "San Inocente"
    ],
    "wof:name":"San Inocente",
    "wof:placetype":"locality"
},
  "geometry": {"coordinates":[-91.54487,18.27644],"type":"Point"}
}