{
  "type": "Feature",
  "properties": {
    "gn:admin1_code":"31",
    "gn:admin2_code":"97.0",
    "gn:asciiname":"Onichen",
    "gn:country_code":"MX",
    "gn:dem":20,
    "gn:feature_class":"P",
    "gn:feature_code":"PPL",
    "gn:name":"Onich\u00e9n",
    "gn:population":93,
    "gn:timezone":"America/Merida",
    "iso:country":"MX",
    "wof:name":"Onichen",
    "wof:placetype":"locality",
    "wof:population":93
},
  "geometry": {"coordinates":[-88.84028000000001,20.83472],"type":"Point"}
}