{
  "type": "Feature",
  "properties": {
    "gn:admin1_code":"26",
    "gn:admin2_code":"13.0",
    "gn:asciiname":"El Cazo",
    "gn:country_code":"MX",
    "gn:dem":673,
    "gn:feature_class":"P",
    "gn:feature_code":"PPL",
    "gn:name":"El Cazo",
    "gn:population":5,
    "gn:timezone":"America/Hermosillo",
    "iso:country":"MX",
    "wof:name":"El Cazo",
    "wof:placetype":"locality",
    "wof:population":5
},
  "geometry": {"coordinates":[-110.21944000000001,30.02194],"type":"Point"}
}