{
  "type": "Feature",
  "properties": {
    "gn:admin1_code":"7",
    "gn:admin2_code":"33.0",
    "gn:asciiname":"Lagos de Moreno (Ampueros)",
    "gn:country_code":"MX",
    "gn:dem":1101,
    "gn:feature_class":"P",
    "gn:feature_code":"PPL",
    "gn:name":"Lagos de Moreno (Ampueros)",
    "gn:population":133,
    "gn:timezone":"America/Monterrey",
    "iso:country":"MX",
    "wof:name":"Lagos de Moreno (Ampueros)",
    "wof:placetype":"locality",
    "wof:population":133
},
  "geometry": {"coordinates":[-103.13694,25.91556],"type":"Point"}
}