{
  "type": "Feature",
  "properties": {
    "gn:admin1_code":"15",
    "gn:admin2_code":"1.0",
    "gn:asciiname":"Rincon de San Francisco Shaxni",
    "gn:country_code":"MX",
    "gn:dem":2945,
    "gn:feature_class":"P",
    "gn:feature_code":"PPL",
    "gn:name":"Rinc\u00f3n de San Francisco Shaxni",
    "gn:population":130,
    "gn:timezone":"America/Mexico_City",
    "iso:country":"MX",
    "name:und_x_variant":[
        "Rinc\u00f3n de San Francisco Shaxni"
    ],
    "wof:name":"Rincon de San Francisco Shaxni",
    "wof:placetype":"locality",
    "wof:population":130
},
  "geometry": {"coordinates":[-99.95999999999999,20.04],"type":"Point"}
}