{
  "type": "Feature",
  "properties": {
    "gn:admin1_code":"5",
    "gn:admin2_code":"99",
    "gn:asciiname":"Porvenir Campo Alegre",
    "gn:country_code":"MX",
    "gn:dem":798,
    "gn:feature_class":"P",
    "gn:feature_code":"PPL",
    "gn:name":"Porvenir Campo Alegre",
    "gn:population":50,
    "gn:timezone":"America/Mexico_City",
    "iso:country":"MX",
    "wof:name":"Porvenir Campo Alegre",
    "wof:placetype":"locality",
    "wof:population":50
},
  "geometry": {"coordinates":[-91.96389000000001,15.88472],"type":"Point"}
}