{
  "type": "Feature",
  "properties": {
    "gn:admin1_code":"27.0",
    "gn:admin2_code":"1.0",
    "gn:asciiname":"El Pangolar",
    "gn:country_code":"MX",
    "gn:dem":31,
    "gn:feature_class":"P",
    "gn:feature_code":"PPL",
    "gn:name":"El Pangolar",
    "gn:population":0,
    "gn:timezone":"America/Mexico_City",
    "iso:country":"MX",
    "name:spa_x_preferred":[
        "El Pangolar"
    ],
    "wof:name":"El Pangolar",
    "wof:placetype":"locality"
},
  "geometry": {"coordinates":[-91.23081000000001,17.75375],"type":"Point"}
}