{
  "type": "Feature",
  "properties": {
    "gn:admin1_code":"16",
    "gn:admin2_code":"34.0",
    "gn:asciiname":"Palomas (Cerro del Gallo)",
    "gn:country_code":"MX",
    "gn:dem":2271,
    "gn:feature_class":"P",
    "gn:feature_code":"PPL",
    "gn:name":"Palomas (Cerro del Gallo)",
    "gn:population":67,
    "gn:timezone":"America/Mexico_City",
    "iso:country":"MX",
    "wof:name":"Palomas (Cerro del Gallo)",
    "wof:placetype":"locality",
    "wof:population":67
},
  "geometry": {"coordinates":[-100.73721999999999,19.54583],"type":"Point"}
}