{
  "type": "Feature",
  "properties": {
    "gn:admin1_code":"32.0",
    "gn:admin2_code":"42.0",
    "gn:asciiname":"Jacales",
    "gn:country_code":"MX",
    "gn:dem":2270,
    "gn:feature_class":"P",
    "gn:feature_code":"PPL",
    "gn:name":"Jacales",
    "gn:population":0,
    "gn:timezone":"America/Mexico_City",
    "iso:country":"MX",
    "wof:name":"Jacales",
    "wof:placetype":"locality"
},
  "geometry": {"coordinates":[-103.48333,23.71667],"type":"Point"}
}