{
  "type": "Feature",
  "properties": {
    "gn:admin1_code":"16",
    "gn:admin2_code":"38.0",
    "gn:asciiname":"La Pareja",
    "gn:country_code":"MX",
    "gn:dem":515,
    "gn:feature_class":"P",
    "gn:feature_code":"PPL",
    "gn:name":"La Pareja",
    "gn:population":6,
    "gn:timezone":"America/Mexico_City",
    "iso:country":"MX",
    "wof:name":"La Pareja",
    "wof:placetype":"locality",
    "wof:population":6
},
  "geometry": {"coordinates":[-101.00583,18.68389],"type":"Point"}
}