{
  "type": "Feature",
  "properties": {
    "gn:admin1_code":"30",
    "gn:admin2_code":"77.0",
    "gn:asciiname":"Matilla de Cana",
    "gn:country_code":"MX",
    "gn:dem":50,
    "gn:feature_class":"P",
    "gn:feature_code":"PPL",
    "gn:name":"Matilla de Ca\u00f1a",
    "gn:population":8,
    "gn:timezone":"America/Mexico_City",
    "iso:country":"MX",
    "name:und_x_variant":[
        "Matilla de Ca\u00f1a"
    ],
    "wof:name":"Matilla de Cana",
    "wof:placetype":"locality",
    "wof:population":8
},
  "geometry": {"coordinates":[-95.53833,18.04361],"type":"Point"}
}