{
  "type": "Feature",
  "properties": {
    "gn:admin1_code":"14",
    "gn:admin2_code":"85",
    "gn:asciiname":"Rancho de Medina",
    "gn:country_code":"MX",
    "gn:dem":1163,
    "gn:feature_class":"P",
    "gn:feature_code":"PPL",
    "gn:name":"Rancho de Medina",
    "gn:population":19,
    "gn:timezone":"America/Mexico_City",
    "iso:country":"MX",
    "wof:name":"Rancho de Medina",
    "wof:placetype":"locality",
    "wof:population":19
},
  "geometry": {"coordinates":[-103.21889,19.67833],"type":"Point"}
}