{
  "type": "Feature",
  "properties": {
    "gn:admin1_code":"6.0",
    "gn:admin2_code":"56.0",
    "gn:asciiname":"El Duraznillo",
    "gn:country_code":"MX",
    "gn:dem":1502,
    "gn:feature_class":"P",
    "gn:feature_code":"PPL",
    "gn:name":"El Duraznillo",
    "gn:population":0,
    "gn:timezone":"America/Chihuahua",
    "iso:country":"MX",
    "name:spa_x_preferred":[
        "El Duraznillo"
    ],
    "wof:name":"El Duraznillo",
    "wof:placetype":"locality"
},
  "geometry": {"coordinates":[-106.33615,27.27667000000001],"type":"Point"}
}