{
  "type": "Feature",
  "properties": {
    "gn:admin1_code":"30",
    "gn:admin2_code":"172",
    "gn:asciiname":"El Progreso",
    "gn:country_code":"MX",
    "gn:dem":54,
    "gn:feature_class":"P",
    "gn:feature_code":"PPL",
    "gn:name":"El Progreso",
    "gn:population":12,
    "gn:timezone":"America/Mexico_City",
    "iso:country":"MX",
    "wof:name":"El Progreso",
    "wof:placetype":"locality",
    "wof:population":12
},
  "geometry": {"coordinates":[-94.8475,17.82943999999999],"type":"Point"}
}