{
  "type": "Feature",
  "properties": {
    "gn:admin1_code":"6",
    "gn:admin2_code":"62.0",
    "gn:asciiname":"Granja Maria Elena",
    "gn:country_code":"MX",
    "gn:dem":1212,
    "gn:feature_class":"P",
    "gn:feature_code":"PPL",
    "gn:name":"Granja Mar\u00eda Elena",
    "gn:population":4,
    "gn:timezone":"America/Chihuahua",
    "iso:country":"MX",
    "name:und_x_variant":[
        "Granja Mar\u00eda Elena"
    ],
    "wof:name":"Granja Maria Elena",
    "wof:placetype":"locality",
    "wof:population":4
},
  "geometry": {"coordinates":[-105.31796,28.02993],"type":"Point"}
}