{
  "type": "Feature",
  "properties": {
    "gn:admin1_code":"6",
    "gn:admin2_code":"66.0",
    "gn:asciiname":"Gosogachi",
    "gn:country_code":"MX",
    "gn:dem":1752,
    "gn:feature_class":"P",
    "gn:feature_code":"PPL",
    "gn:name":"Gosogachi",
    "gn:population":0,
    "gn:timezone":"America/Chihuahua",
    "iso:country":"MX",
    "name:und_x_variant":[
        "Gasogachic",
        "Gosogachic",
        "Gosogachi"
    ],
    "wof:name":"Gosogachi",
    "wof:placetype":"locality"
},
  "geometry": {"coordinates":[-108.32016000000002,27.84897],"type":"Point"}
}