{
  "type": "Feature",
  "properties": {
    "gn:admin1_code":"28",
    "gn:admin2_code":"32.0",
    "gn:asciiname":"Las Minitas",
    "gn:country_code":"MX",
    "gn:dem":34,
    "gn:feature_class":"P",
    "gn:feature_code":"PPL",
    "gn:name":"Las Minitas",
    "gn:population":7,
    "gn:timezone":"America/Matamoros",
    "iso:country":"MX",
    "wof:name":"Las Minitas",
    "wof:placetype":"locality",
    "wof:population":7
},
  "geometry": {"coordinates":[-98.22417,26.06528],"type":"Point"}
}