{
  "type": "Feature",
  "properties": {
    "gn:admin1_code":"14.0",
    "gn:admin2_code":"88.0",
    "gn:asciiname":"El Carcamo",
    "gn:country_code":"MX",
    "gn:dem":1180,
    "gn:feature_class":"P",
    "gn:feature_code":"PPL",
    "gn:name":"El C\u00e1rcamo",
    "gn:population":0,
    "gn:timezone":"America/Mexico_City",
    "iso:country":"MX",
    "name:spa_x_preferred":[
        "El C\u00e1rcamo"
    ],
    "name:spa_x_variant":[
        "El Pozo"
    ],
    "wof:name":"El Carcamo",
    "wof:placetype":"locality"
},
  "geometry": {"coordinates":[-104.01965,20.16134],"type":"Point"}
}