{
  "type": "Feature",
  "properties": {
    "gn:admin1_code":"26.0",
    "gn:admin2_code":"16.0",
    "gn:asciiname":"Los Venados",
    "gn:country_code":"MX",
    "gn:dem":929,
    "gn:feature_class":"P",
    "gn:feature_code":"PPL",
    "gn:name":"Los Venados",
    "gn:population":0,
    "gn:timezone":"America/Hermosillo",
    "iso:country":"MX",
    "name:spa_x_preferred":[
        "Los Venados"
    ],
    "name:spa_x_variant":[
        "El Cal\u00edchi"
    ],
    "wof:name":"Los Venados",
    "wof:placetype":"locality"
},
  "geometry": {"coordinates":[-111.34683,30.07379],"type":"Point"}
}