{
  "type": "Feature",
  "properties": {
    "gn:admin1_code":"2",
    "gn:admin2_code":"1.0",
    "gn:asciiname":"Rodeo Viejo",
    "gn:country_code":"MX",
    "gn:dem":716,
    "gn:feature_class":"P",
    "gn:feature_code":"PPL",
    "gn:name":"Rodeo Viejo",
    "gn:population":6,
    "gn:timezone":"America/Tijuana",
    "iso:country":"MX",
    "wof:name":"Rodeo Viejo",
    "wof:placetype":"locality",
    "wof:population":6
},
  "geometry": {"coordinates":[-116.23667,31.88194],"type":"Point"}
}