{
  "type": "Feature",
  "properties": {
    "gn:admin1_code":"30",
    "gn:admin2_code":"172.0",
    "gn:asciiname":"Amapa",
    "gn:country_code":"MX",
    "gn:dem":45,
    "gn:feature_class":"P",
    "gn:feature_code":"PPL",
    "gn:name":"Amapa",
    "gn:population":0,
    "gn:timezone":"America/Mexico_City",
    "iso:country":"MX",
    "name:ceb_x_preferred":[
        "Amapa"
    ],
    "name:sco_x_preferred":[
        "Amapa"
    ],
    "name:srp_x_preferred":[
        "\u0410\u043c\u0430\u043f\u0430"
    ],
    "name:swe_x_preferred":[
        "Amapa"
    ],
    "name:vie_x_preferred":[
        "Amapa"
    ],
    "wof:name":"Amapa",
    "wof:placetype":"locality"
},
  "geometry": {"coordinates":[-94.88333,17.85],"type":"Point"}
}