{
  "type": "Feature",
  "properties": {
    "gn:admin1_code":"32",
    "gn:admin2_code":"12.0",
    "gn:asciiname":"Presa de Maravillas",
    "gn:country_code":"MX",
    "gn:dem":2208,
    "gn:feature_class":"P",
    "gn:feature_code":"PPL",
    "gn:name":"Presa de Maravillas",
    "gn:population":0,
    "gn:timezone":"America/Mexico_City",
    "iso:country":"MX",
    "name:spa_x_preferred":[
        "Presa de Maravillas"
    ],
    "name:und_x_variant":[
        "Maravillas"
    ],
    "wof:name":"Presa de Maravillas",
    "wof:placetype":"locality"
},
  "geometry": {"coordinates":[-102.73885,22.58453],"type":"Point"}
}