{
  "type": "Feature",
  "properties": {
    "gn:admin1_code":"6.0",
    "gn:admin2_code":"1.0",
    "gn:asciiname":"Santa Monica",
    "gn:country_code":"MX",
    "gn:dem":1192,
    "gn:feature_class":"P",
    "gn:feature_code":"PPL",
    "gn:name":"Santa M\u00f3nica",
    "gn:population":0,
    "gn:timezone":"America/Chihuahua",
    "iso:country":"MX",
    "name:spa_x_preferred":[
        "Santa M\u00f3nica"
    ],
    "wof:name":"Santa Monica",
    "wof:placetype":"locality"
},
  "geometry": {"coordinates":[-106.51542999999999,30.65998],"type":"Point"}
}