{
  "type": "Feature",
  "properties": {
    "gn:admin1_code":"30",
    "gn:admin2_code":"148",
    "gn:asciiname":"Tres Higueras",
    "gn:country_code":"MX",
    "gn:dem":209,
    "gn:feature_class":"P",
    "gn:feature_code":"PPL",
    "gn:name":"Tres Higueras",
    "gn:population":17,
    "gn:timezone":"America/Mexico_City",
    "iso:country":"MX",
    "wof:name":"Tres Higueras",
    "wof:placetype":"locality",
    "wof:population":17
},
  "geometry": {"coordinates":[-96.50278,18.97611],"type":"Point"}
}