{
  "type": "Feature",
  "properties": {
    "gn:admin1_code":"15",
    "gn:admin2_code":"56.0",
    "gn:asciiname":"La Epifania",
    "gn:country_code":"MX",
    "gn:dem":2580,
    "gn:feature_class":"P",
    "gn:feature_code":"PPL",
    "gn:name":"La Epifania",
    "gn:population":0,
    "gn:timezone":"America/Mexico_City",
    "iso:country":"MX",
    "name:spa_x_preferred":[
        "Epifania"
    ],
    "name:spa_x_variant":[
        "La Epifania"
    ],
    "wof:name":"La Epifania",
    "wof:placetype":"locality"
},
  "geometry": {"coordinates":[-99.65940999999999,19.71629],"type":"Point"}
}