{
  "type": "Feature",
  "properties": {
    "gn:admin1_code":"10",
    "gn:admin2_code":"21.0",
    "gn:asciiname":"Magallanes",
    "gn:country_code":"MX",
    "gn:dem":1890,
    "gn:feature_class":"P",
    "gn:feature_code":"PPL",
    "gn:name":"Magallanes",
    "gn:population":0,
    "gn:timezone":"America/Monterrey",
    "iso:country":"MX",
    "name:spa_x_preferred":[
        "Magallanes"
    ],
    "wof:name":"Magallanes",
    "wof:placetype":"locality"
},
  "geometry": {"coordinates":[-104.00807,24.6667],"type":"Point"}
}