{
  "type": "Feature",
  "properties": {
    "gn:admin1_code":"25",
    "gn:admin2_code":"2.0",
    "gn:asciiname":"Santa Maria del Playon",
    "gn:country_code":"MX",
    "gn:dem":10,
    "gn:feature_class":"P",
    "gn:feature_code":"PPL",
    "gn:name":"Santa Mar\u00eda del Play\u00f3n",
    "gn:population":16,
    "gn:timezone":"America/Mazatlan",
    "iso:country":"MX",
    "name:spa_x_preferred":[
        "Santa Mar\u00eda del Play\u00f3n"
    ],
    "wof:name":"Santa Maria del Playon",
    "wof:placetype":"locality",
    "wof:population":16
},
  "geometry": {"coordinates":[-108.12541,25.146],"type":"Point"}
}