{
  "type": "Feature",
  "properties": {
    "gn:admin1_code":"5",
    "gn:admin2_code":"52.0",
    "gn:asciiname":"Piedra Huixtla",
    "gn:country_code":"MX",
    "gn:dem":1524,
    "gn:feature_class":"P",
    "gn:feature_code":"PPL",
    "gn:name":"Piedra Huixtla",
    "gn:population":299,
    "gn:timezone":"America/Mexico_City",
    "iso:country":"MX",
    "wof:name":"Piedra Huixtla",
    "wof:placetype":"locality",
    "wof:population":299
},
  "geometry": {"coordinates":[-92.01056,16.57777999999999],"type":"Point"}
}