{
  "type": "Feature",
  "properties": {
    "gn:admin1_code":"11.0",
    "gn:admin2_code":"46.0",
    "gn:asciiname":"Cerecuaro",
    "gn:country_code":"MX",
    "gn:dem":2314,
    "gn:feature_class":"P",
    "gn:feature_code":"PPL",
    "gn:name":"Cer\u00e9cuaro",
    "gn:population":0,
    "gn:timezone":"America/Mexico_City",
    "iso:country":"MX",
    "name:und_x_variant":[
        "Cir\u00e9cuaro",
        "Cer\u00e9cuaro"
    ],
    "wof:name":"Cerecuaro",
    "wof:placetype":"locality"
},
  "geometry": {"coordinates":[-101.3455,20.05036],"type":"Point"}
}