{
  "type": "Feature",
  "properties": {
    "gn:admin1_code":"5",
    "gn:admin2_code":"51.0",
    "gn:asciiname":"El Girasol",
    "gn:country_code":"MX",
    "gn:dem":22,
    "gn:feature_class":"P",
    "gn:feature_code":"PPL",
    "gn:name":"El Girasol",
    "gn:population":4,
    "gn:timezone":"America/Mexico_City",
    "iso:country":"MX",
    "wof:name":"El Girasol",
    "wof:placetype":"locality",
    "wof:population":4
},
  "geometry": {"coordinates":[-93.02222,15.45972],"type":"Point"}
}