{
  "type": "Feature",
  "properties": {
    "gn:admin1_code":"19.0",
    "gn:admin2_code":"20.0",
    "gn:asciiname":"El Cipros",
    "gn:country_code":"MX",
    "gn:dem":187,
    "gn:feature_class":"P",
    "gn:feature_code":"PPL",
    "gn:name":"El Cipr\u00f3s",
    "gn:population":0,
    "gn:timezone":"America/Monterrey",
    "iso:country":"MX",
    "name:spa_x_preferred":[
        "El Cipr\u00f3s"
    ],
    "wof:name":"El Cipros",
    "wof:placetype":"locality"
},
  "geometry": {"coordinates":[-98.79953,25.77913],"type":"Point"}
}