{
  "type": "Feature",
  "properties": {
    "gn:admin1_code":"20",
    "gn:admin2_code":"462.0",
    "gn:asciiname":"San Pedro Sochiapan",
    "gn:cc2":"MX",
    "gn:country_code":"MX",
    "gn:dem":1823,
    "gn:feature_class":"P",
    "gn:feature_code":"PPL",
    "gn:name":"San Pedro Sochiapan",
    "gn:population":0,
    "gn:timezone":"America/Mexico_City",
    "iso:country":"MX",
    "name:und_x_variant":[
        "Sochiapam",
        "San Pedro Sochiapan"
    ],
    "wof:name":"San Pedro Sochiapan",
    "wof:placetype":"locality"
},
  "geometry": {"coordinates":[-97.71666999999999,17.86667000000001],"type":"Point"}
}