{
  "type": "Feature",
  "properties": {
    "gn:admin1_code":"16",
    "gn:admin2_code":"38",
    "gn:asciiname":"Las Galeras",
    "gn:country_code":"MX",
    "gn:dem":180,
    "gn:feature_class":"P",
    "gn:feature_code":"PPL",
    "gn:name":"Las Galeras",
    "gn:population":35,
    "gn:timezone":"America/Mexico_City",
    "iso:country":"MX",
    "name:spa_x_preferred":[
        "Las Galeras"
    ],
    "wof:name":"Las Galeras",
    "wof:placetype":"locality",
    "wof:population":35
},
  "geometry": {"coordinates":[-101.30444,18.54111],"type":"Point"}
}