{
  "type": "Feature",
  "properties": {
    "gn:admin1_code":"2",
    "gn:admin2_code":"1.0",
    "gn:asciiname":"El Progreso",
    "gn:country_code":"MX",
    "gn:dem":495,
    "gn:feature_class":"P",
    "gn:feature_code":"PPL",
    "gn:name":"El Progreso",
    "gn:population":3,
    "gn:timezone":"America/Tijuana",
    "iso:country":"MX",
    "name:spa_x_preferred":[
        "El Progreso"
    ],
    "wof:name":"El Progreso",
    "wof:placetype":"locality",
    "wof:population":3
},
  "geometry": {"coordinates":[-115.20278,29.97694000000001],"type":"Point"}
}