{
  "type": "Feature",
  "properties": {
    "gn:admin1_code":"11",
    "gn:admin2_code":"23.0",
    "gn:asciiname":"Castillo de Villasenor",
    "gn:country_code":"MX",
    "gn:dem":1716,
    "gn:feature_class":"P",
    "gn:feature_code":"PPL",
    "gn:name":"Castillo de Villase\u00f1or",
    "gn:population":645,
    "gn:timezone":"America/Mexico_City",
    "iso:country":"MX",
    "name:und_x_variant":[
        "Castillo de Villase\u00f1or"
    ],
    "wof:name":"Castillo de Villasenor",
    "wof:placetype":"locality",
    "wof:population":645
},
  "geometry": {"coordinates":[-101.845,20.28167],"type":"Point"}
}