{
  "type": "Feature",
  "properties": {
    "gn:admin1_code":"10.0",
    "gn:admin2_code":"32.0",
    "gn:asciiname":"Atotonilco",
    "gn:country_code":"MX",
    "gn:dem":1685,
    "gn:feature_class":"P",
    "gn:feature_code":"PPL",
    "gn:name":"Atotonilco",
    "gn:population":282,
    "gn:timezone":"America/Monterrey",
    "iso:country":"MX",
    "wof:name":"Atotonilco",
    "wof:placetype":"locality",
    "wof:population":282
},
  "geometry": {"coordinates":[-105.44528,25.16472000000001],"type":"Point"}
}