{
  "type": "Feature",
  "properties": {
    "gn:admin1_code":"8",
    "gn:admin2_code":"2",
    "gn:asciiname":"Antonio Tejeda Olivera",
    "gn:country_code":"MX",
    "gn:dem":342,
    "gn:feature_class":"P",
    "gn:feature_code":"PPL",
    "gn:name":"Antonio Tejeda Olivera",
    "gn:population":11,
    "gn:timezone":"America/Mexico_City",
    "iso:country":"MX",
    "wof:name":"Antonio Tejeda Olivera",
    "wof:placetype":"locality",
    "wof:population":11
},
  "geometry": {"coordinates":[-103.77861,19.10889],"type":"Point"}
}