{
  "type": "Feature",
  "properties": {
    "gn:admin1_code":"7",
    "gn:admin2_code":"12.0",
    "gn:asciiname":"Bracitos",
    "gn:country_code":"MX",
    "gn:dem":285,
    "gn:feature_class":"P",
    "gn:feature_code":"PPL",
    "gn:name":"Bracitos",
    "gn:population":0,
    "gn:timezone":"America/Monterrey",
    "iso:country":"MX",
    "wof:name":"Bracitos",
    "wof:placetype":"locality"
},
  "geometry": {"coordinates":[-100.41643000000001,28.01384],"type":"Point"}
}