{
  "type": "Feature",
  "properties": {
    "gn:admin1_code":"10",
    "gn:admin2_code":"34.0",
    "gn:asciiname":"Boca de Arroyo del Zapote",
    "gn:country_code":"MX",
    "gn:dem":346,
    "gn:feature_class":"P",
    "gn:feature_code":"PPL",
    "gn:name":"Boca de Arroyo del Zapote",
    "gn:population":8,
    "gn:timezone":"America/Mazatlan",
    "iso:country":"MX",
    "wof:name":"Boca de Arroyo del Zapote",
    "wof:placetype":"locality",
    "wof:population":8
},
  "geometry": {"coordinates":[-107.15788000000001,25.32691],"type":"Point"}
}