{
  "type": "Feature",
  "properties": {
    "gn:admin1_code":"28",
    "gn:admin2_code":"34",
    "gn:asciiname":"San Juan",
    "gn:country_code":"MX",
    "gn:dem":354,
    "gn:feature_class":"P",
    "gn:feature_code":"PPL",
    "gn:name":"San Juan",
    "gn:population":13,
    "gn:timezone":"America/Monterrey",
    "iso:country":"MX",
    "wof:name":"San Juan",
    "wof:placetype":"locality",
    "wof:population":13
},
  "geometry": {"coordinates":[-99.13361,24.49167000000001],"type":"Point"}
}