{
  "type": "Feature",
  "properties": {
    "gn:admin1_code":"12",
    "gn:admin2_code":"54.0",
    "gn:asciiname":"Colonia del Pedregal",
    "gn:country_code":"MX",
    "gn:dem":305,
    "gn:feature_class":"P",
    "gn:feature_code":"PPL",
    "gn:name":"Colonia del Pedregal",
    "gn:population":187,
    "gn:timezone":"America/Mexico_City",
    "iso:country":"MX",
    "wof:name":"Colonia del Pedregal",
    "wof:placetype":"locality",
    "wof:population":187
},
  "geometry": {"coordinates":[-100.3978,18.17636],"type":"Point"}
}