{
  "type": "Feature",
  "properties": {
    "gn:admin1_code":"6",
    "gn:admin2_code":"65.0",
    "gn:asciiname":"Matanzas",
    "gn:country_code":"MX",
    "gn:dem":544,
    "gn:feature_class":"P",
    "gn:feature_code":"PPL",
    "gn:name":"Matanzas",
    "gn:population":26,
    "gn:timezone":"America/Mazatlan",
    "iso:country":"MX",
    "name:spa_x_preferred":[
        "Matanzas"
    ],
    "wof:name":"Matanzas",
    "wof:placetype":"locality",
    "wof:population":26
},
  "geometry": {"coordinates":[-108.17657,26.94299],"type":"Point"}
}