{
  "type": "Feature",
  "properties": {
    "gn:admin1_code":"6",
    "gn:admin2_code":"10.0",
    "gn:asciiname":"Loma Colorada",
    "gn:country_code":"MX",
    "gn:dem":1428,
    "gn:feature_class":"P",
    "gn:feature_code":"PPL",
    "gn:name":"Loma Colorada",
    "gn:population":0,
    "gn:timezone":"America/Chihuahua",
    "iso:country":"MX",
    "name:spa_x_preferred":[
        "Loma Colorada"
    ],
    "name:und_x_variant":[
        "Rancho Loma Colorada"
    ],
    "wof:name":"Loma Colorada",
    "wof:placetype":"locality"
},
  "geometry": {"coordinates":[-106.9722,29.99217],"type":"Point"}
}