{
  "type": "Feature",
  "properties": {
    "gn:admin1_code":"32",
    "gn:admin2_code":"39.0",
    "gn:asciiname":"Rancho San Miguel",
    "gn:country_code":"MX",
    "gn:dem":2065,
    "gn:feature_class":"P",
    "gn:feature_code":"PPL",
    "gn:name":"Rancho San Miguel",
    "gn:population":0,
    "gn:timezone":"America/Mexico_City",
    "iso:country":"MX",
    "name:spa_x_preferred":[
        "Rancho San Miguel"
    ],
    "wof:name":"Rancho San Miguel",
    "wof:placetype":"locality"
},
  "geometry": {"coordinates":[-103.30552,23.95784],"type":"Point"}
}