{
  "type": "Feature",
  "properties": {
    "gn:admin1_code":"27",
    "gn:admin2_code":"3.0",
    "gn:asciiname":"Carlos Rovirosa",
    "gn:country_code":"MX",
    "gn:dem":4,
    "gn:feature_class":"P",
    "gn:feature_code":"PPL",
    "gn:name":"Carlos Rovirosa",
    "gn:population":0,
    "gn:timezone":"America/Mexico_City",
    "iso:country":"MX",
    "name:spa_x_preferred":[
        "Carlos Rubirosa"
    ],
    "name:spa_x_variant":[
        "Carlos Rovirosa"
    ],
    "wof:name":"Carlos Rovirosa",
    "wof:placetype":"locality"
},
  "geometry": {"coordinates":[-92.64322,18.57088],"type":"Point"}
}