{
  "type": "Feature",
  "properties": {
    "gn:admin1_code":"10",
    "gn:admin2_code":"34",
    "gn:asciiname":"La Piedra",
    "gn:country_code":"MX",
    "gn:dem":453,
    "gn:feature_class":"P",
    "gn:feature_code":"PPL",
    "gn:name":"La Piedra",
    "gn:population":18,
    "gn:timezone":"America/Monterrey",
    "iso:country":"MX",
    "wof:name":"La Piedra",
    "wof:placetype":"locality",
    "wof:population":18
},
  "geometry": {"coordinates":[-106.60312999999999,24.71193],"type":"Point"}
}