{
  "type": "Feature",
  "properties": {
    "gn:admin1_code":"8",
    "gn:admin2_code":"7",
    "gn:asciiname":"La Pina",
    "gn:country_code":"MX",
    "gn:dem":283,
    "gn:feature_class":"P",
    "gn:feature_code":"PPL",
    "gn:name":"La Pi\u00f1a",
    "gn:population":12,
    "gn:timezone":"America/Mexico_City",
    "iso:country":"MX",
    "name:und_x_variant":[
        "La Pi\u00f1a"
    ],
    "wof:name":"La Pina",
    "wof:placetype":"locality",
    "wof:population":12
},
  "geometry": {"coordinates":[-104.33833,19.24972],"type":"Point"}
}