{
  "type": "Feature",
  "properties": {
    "gn:admin1_code":"11",
    "gn:admin2_code":"40.0",
    "gn:asciiname":"Cano de San Isidro",
    "gn:country_code":"MX",
    "gn:dem":1838,
    "gn:feature_class":"P",
    "gn:feature_code":"PPL",
    "gn:name":"Cano de San Isidro",
    "gn:population":968,
    "gn:timezone":"America/Mexico_City",
    "iso:country":"MX",
    "wof:name":"Cano de San Isidro",
    "wof:placetype":"locality",
    "wof:population":968
},
  "geometry": {"coordinates":[-100.2225,21.0725],"type":"Point"}
}