{
  "type": "Feature",
  "properties": {
    "gn:admin1_code":"16",
    "gn:admin2_code":"34.0",
    "gn:asciiname":"Noche Buena",
    "gn:country_code":"MX",
    "gn:dem":2317,
    "gn:feature_class":"P",
    "gn:feature_code":"PPL",
    "gn:name":"Noche Buena",
    "gn:population":0,
    "gn:timezone":"America/Mexico_City",
    "iso:country":"MX",
    "name:spa_x_preferred":[
        "Noche Buena"
    ],
    "wof:name":"Noche Buena",
    "wof:placetype":"locality"
},
  "geometry": {"coordinates":[-100.69531000000001,19.49383],"type":"Point"}
}