{
  "type": "Feature",
  "properties": {
    "gn:admin1_code":"30",
    "gn:admin2_code":"95",
    "gn:asciiname":"La Pagueita",
    "gn:country_code":"MX",
    "gn:dem":594,
    "gn:feature_class":"P",
    "gn:feature_code":"PPL",
    "gn:name":"La Pag\u00fcita",
    "gn:population":21,
    "gn:timezone":"America/Mexico_City",
    "iso:country":"MX",
    "name:und_x_variant":[
        "La Pag\u00fcita"
    ],
    "wof:name":"La Pagueita",
    "wof:placetype":"locality",
    "wof:population":21
},
  "geometry": {"coordinates":[-96.60306,19.81],"type":"Point"}
}