{
  "type": "Feature",
  "properties": {
    "gn:admin1_code":"25",
    "gn:admin2_code":"5",
    "gn:asciiname":"Picacho",
    "gn:country_code":"MX",
    "gn:dem":139,
    "gn:feature_class":"P",
    "gn:feature_code":"PPL",
    "gn:name":"Picacho",
    "gn:population":27,
    "gn:timezone":"America/Mazatlan",
    "iso:country":"MX",
    "name:ceb_x_preferred":[
        "Picacho"
    ],
    "name:deu_x_preferred":[
        "Picacho"
    ],
    "name:swe_x_preferred":[
        "Picacho"
    ],
    "wof:name":"Picacho",
    "wof:placetype":"locality",
    "wof:population":27
},
  "geometry": {"coordinates":[-107.03964000000001,24.46892],"type":"Point"}
}