{
  "type": "Feature",
  "properties": {
    "gn:admin1_code":"5",
    "gn:admin2_code":"81.0",
    "gn:asciiname":"San Antonio Rio Cacateal",
    "gn:country_code":"MX",
    "gn:dem":549,
    "gn:feature_class":"P",
    "gn:feature_code":"PPL",
    "gn:name":"San Antonio R\u00edo Cacateal",
    "gn:population":121,
    "gn:timezone":"America/Mexico_City",
    "iso:country":"MX",
    "name:und_x_variant":[
        "San Antonio R\u00edo Cacateal"
    ],
    "wof:name":"San Antonio Rio Cacateal",
    "wof:placetype":"locality",
    "wof:population":121
},
  "geometry": {"coordinates":[-92.76111,17.15917],"type":"Point"}
}