{
  "type": "Feature",
  "properties": {
    "gn:admin1_code":"16",
    "gn:admin2_code":"97",
    "gn:asciiname":"Las Piedras (Las Piedras de Santa Cruz)",
    "gn:country_code":"MX",
    "gn:dem":757,
    "gn:feature_class":"P",
    "gn:feature_code":"PPL",
    "gn:name":"Las Piedras (Las Piedras de Santa Cruz)",
    "gn:population":40,
    "gn:timezone":"America/Mexico_City",
    "iso:country":"MX",
    "wof:name":"Las Piedras (Las Piedras de Santa Cruz)",
    "wof:placetype":"locality",
    "wof:population":40
},
  "geometry": {"coordinates":[-101.34917,18.77389],"type":"Point"}
}