{
  "type": "Feature",
  "properties": {
    "gn:admin1_code":"28",
    "gn:admin2_code":"12.0",
    "gn:asciiname":"Las Aguilas del Bernal",
    "gn:country_code":"MX",
    "gn:dem":49,
    "gn:feature_class":"P",
    "gn:feature_code":"PPL",
    "gn:name":"Las \u00c1guilas del Bernal",
    "gn:population":0,
    "gn:timezone":"America/Monterrey",
    "iso:country":"MX",
    "name:spa_x_preferred":[
        "Las \u00c1guilas del Bernal"
    ],
    "wof:name":"Las Aguilas del Bernal",
    "wof:placetype":"locality"
},
  "geometry": {"coordinates":[-98.52397000000001,22.74305],"type":"Point"}
}