{
  "type": "Feature",
  "properties": {
    "gn:admin1_code":"10",
    "gn:admin2_code":"22.0",
    "gn:asciiname":"San Juan Bautista",
    "gn:country_code":"MX",
    "gn:dem":1863,
    "gn:feature_class":"P",
    "gn:feature_code":"PPL",
    "gn:name":"San Juan Bautista",
    "gn:population":0,
    "gn:timezone":"America/Monterrey",
    "iso:country":"MX",
    "wof:name":"San Juan Bautista",
    "wof:placetype":"locality"
},
  "geometry": {"coordinates":[-104.13333,23.91667],"type":"Point"}
}