{
  "type": "Feature",
  "properties": {
    "gn:admin1_code":"5",
    "gn:admin2_code":"46.0",
    "gn:asciiname":"La Florida",
    "gn:country_code":"MX",
    "gn:dem":763,
    "gn:feature_class":"P",
    "gn:feature_code":"PPL",
    "gn:name":"La Florida",
    "gn:population":4,
    "gn:timezone":"America/Mexico_City",
    "iso:country":"MX",
    "wof:name":"La Florida",
    "wof:placetype":"locality",
    "wof:population":4
},
  "geometry": {"coordinates":[-93.54889,16.45528],"type":"Point"}
}