{
  "type": "Feature",
  "properties": {
    "gn:admin1_code":"17",
    "gn:admin2_code":"25.0",
    "gn:asciiname":"Lorenzo Vazquez (Santa Cruz)",
    "gn:country_code":"MX",
    "gn:dem":896,
    "gn:feature_class":"P",
    "gn:feature_code":"PPL",
    "gn:name":"Lorenzo V\u00e1zquez (Santa Cruz)",
    "gn:population":785,
    "gn:timezone":"America/Mexico_City",
    "iso:country":"MX",
    "name:und_x_variant":[
        "Lorenzo V\u00e1zquez (Santa Cruz)"
    ],
    "wof:name":"Lorenzo Vazquez (Santa Cruz)",
    "wof:placetype":"locality",
    "wof:population":785
},
  "geometry": {"coordinates":[-99.07277999999999,18.57361],"type":"Point"}
}