{
  "type": "Feature",
  "properties": {
    "gn:admin1_code":"28",
    "gn:admin2_code":"34.0",
    "gn:asciiname":"Sinai",
    "gn:country_code":"MX",
    "gn:dem":312,
    "gn:feature_class":"P",
    "gn:feature_code":"PPL",
    "gn:name":"Sina\u00ed",
    "gn:population":9,
    "gn:timezone":"America/Monterrey",
    "iso:country":"MX",
    "name:und_x_variant":[
        "Sina\u00ed"
    ],
    "wof:name":"Sinai",
    "wof:placetype":"locality",
    "wof:population":9
},
  "geometry": {"coordinates":[-98.88333,24.41389],"type":"Point"}
}