{
  "type": "Feature",
  "properties": {
    "gn:admin1_code":"24",
    "gn:admin2_code":"8.0",
    "gn:asciiname":"Montanas",
    "gn:country_code":"MX",
    "gn:dem":1266,
    "gn:feature_class":"P",
    "gn:feature_code":"PPL",
    "gn:name":"Monta\u00f1as",
    "gn:population":0,
    "gn:timezone":"America/Mexico_City",
    "iso:country":"MX",
    "wof:name":"Montanas",
    "wof:placetype":"locality"
},
  "geometry": {"coordinates":[-100.37962,22.48253],"type":"Point"}
}