{
  "type": "Feature",
  "properties": {
    "gn:admin1_code":"14",
    "gn:admin2_code":"61.0",
    "gn:asciiname":"El Encinal",
    "gn:country_code":"MX",
    "gn:dem":1433,
    "gn:feature_class":"P",
    "gn:feature_code":"PPL",
    "gn:name":"El Encinal",
    "gn:population":7,
    "gn:timezone":"America/Mexico_City",
    "iso:country":"MX",
    "wof:name":"El Encinal",
    "wof:placetype":"locality",
    "wof:population":7
},
  "geometry": {"coordinates":[-104.06332999999999,22.08583],"type":"Point"}
}