{
  "type": "Feature",
  "properties": {
    "gn:admin1_code":"15.0",
    "gn:asciiname":"La Entrada del Colomo",
    "gn:country_code":"MX",
    "gn:dem":27,
    "gn:feature_class":"P",
    "gn:feature_code":"PPL",
    "gn:name":"La Entrada del Colomo",
    "gn:population":0,
    "gn:timezone":"America/Mexico_City",
    "iso:country":"MX",
    "name:spa_x_preferred":[
        "La Entrada del Colomo"
    ],
    "wof:name":"La Entrada del Colomo",
    "wof:placetype":"locality"
},
  "geometry": {"coordinates":[-102.40432,18.01737],"type":"Point"}
}