{
  "type": "Feature",
  "properties": {
    "gn:admin1_code":"16",
    "gn:admin2_code":"62.0",
    "gn:asciiname":"Fray Dominguez (Los Zapotes)",
    "gn:country_code":"MX",
    "gn:dem":1948,
    "gn:feature_class":"P",
    "gn:feature_code":"PPL",
    "gn:name":"Fray Dom\u00ednguez (Los Zapotes)",
    "gn:population":130,
    "gn:timezone":"America/Mexico_City",
    "iso:country":"MX",
    "name:und_x_variant":[
        "Fray Dom\u00ednguez (Los Zapotes)"
    ],
    "wof:name":"Fray Dominguez (Los Zapotes)",
    "wof:placetype":"locality",
    "wof:population":130
},
  "geometry": {"coordinates":[-102.56471999999999,20.10167],"type":"Point"}
}