{
  "type": "Feature",
  "properties": {
    "gn:admin1_code":"6.0",
    "gn:admin2_code":"1.0",
    "gn:asciiname":"El Consuelo",
    "gn:country_code":"MX",
    "gn:dem":1282,
    "gn:feature_class":"P",
    "gn:feature_code":"PPL",
    "gn:name":"El Consuelo",
    "gn:population":0,
    "gn:timezone":"America/Chihuahua",
    "iso:country":"MX",
    "name:spa_x_preferred":[
        "El Consuelo"
    ],
    "wof:name":"El Consuelo",
    "wof:placetype":"locality"
},
  "geometry": {"coordinates":[-106.78607,30.67247],"type":"Point"}
}