{
  "type": "Feature",
  "properties": {
    "gn:admin1_code":"6.0",
    "gn:admin2_code":"15.0",
    "gn:asciiname":"La Cruz",
    "gn:country_code":"MX",
    "gn:dem":1279,
    "gn:feature_class":"P",
    "gn:feature_code":"PPL",
    "gn:name":"La Cruz",
    "gn:population":0,
    "gn:timezone":"America/Chihuahua",
    "iso:country":"MX",
    "name:spa_x_preferred":[
        "La Cruz"
    ],
    "name:und_x_variant":[
        "Los Charcos"
    ],
    "wof:name":"La Cruz",
    "wof:placetype":"locality"
},
  "geometry": {"coordinates":[-105.15328,29.40931],"type":"Point"}
}