{
  "type": "Feature",
  "properties": {
    "gn:admin1_code":"26.0",
    "gn:admin2_code":"47.0",
    "gn:asciiname":"Dolores",
    "gn:country_code":"MX",
    "gn:dem":223,
    "gn:feature_class":"P",
    "gn:feature_code":"PPL",
    "gn:name":"Dolores",
    "gn:population":0,
    "gn:timezone":"America/Hermosillo",
    "iso:country":"MX",
    "name:spa_x_preferred":[
        "Dolores"
    ],
    "wof:name":"Dolores",
    "wof:placetype":"locality"
},
  "geometry": {"coordinates":[-111.99504,29.60792],"type":"Point"}
}