{
  "type": "Feature",
  "properties": {
    "gn:country":"MX",
    "gn:fcode":"PPL",
    "gn:population":0,
    "iso:country":"MX",
    "name:ceb_x_preferred":[
        "La Mesa"
    ],
    "name:deu_x_preferred":[
        "La Mesa"
    ],
    "name:fra_x_preferred":[
        "La Mesa"
    ],
    "name:ita_x_preferred":[
        "La Mesa"
    ],
    "name:nld_x_preferred":[
        "La Mesa"
    ],
    "name:pol_x_preferred":[
        "La Mesa"
    ],
    "name:por_x_preferred":[
        "La Mesa"
    ],
    "name:sco_x_preferred":[
        "La Mesa"
    ],
    "name:spa_x_preferred":[
        "La Mesa"
    ],
    "name:srp_x_preferred":[
        "\u041b\u0430 \u041c\u0435\u0441\u0430"
    ],
    "name:swe_x_preferred":[
        "La Mesa"
    ],
    "name:vie_x_preferred":[
        "La Mesa"
    ],
    "qs_pg:aaroncc":"MX",
    "qs_pg:gn_country":"MX",
    "qs_pg:gn_fcode":"PPL",
    "qs_pg:gn_pop":0,
    "qs_pg:name":"La Mesa",
    "qs_pg:name_adm0":"M\u00e9xico",
    "qs_pg:name_adm1":"Jalisco",
    "qs_pg:photos":9,
    "qs_pg:photos_1k":2,
    "qs_pg:photos_9k":1,
    "qs_pg:photos_9r":1,
    "qs_pg:photos_all":9,
    "qs_pg:photos_sr":1,
    "qs_pg:pop_sr":0,
    "qs_pg:qs_pg_placetype":"locality",
    "qs_pg:qs_pg_placetype_gp":"Town",
    "qs_pg:woe_adm0":23424900,
    "woe:adm0_id":23424900,
    "woe:name_adm0":"M\u00e9xico",
    "woe:name_adm1":"Jalisco",
    "woe:placetype":"Town",
    "wof:name":"La Mesa",
    "wof:placetype":"locality"
},
  "geometry": {"coordinates":[-104.82644999999999,20.39787],"type":"Point"}
}