{
  "type": "Feature",
  "properties": {
    "gn:admin1_code":"19.0",
    "gn:asciiname":"Las Normas",
    "gn:country_code":"MX",
    "gn:dem":458,
    "gn:feature_class":"P",
    "gn:feature_code":"PPL",
    "gn:name":"Las Normas",
    "gn:population":0,
    "gn:timezone":"America/Monterrey",
    "iso:country":"MX",
    "name:spa_x_preferred":[
        "Las Normas"
    ],
    "wof:name":"Las Normas",
    "wof:placetype":"locality"
},
  "geometry": {"coordinates":[-100.251,25.83223],"type":"Point"}
}