{
  "type": "Feature",
  "properties": {
    "gn:admin1_code":"25",
    "gn:admin2_code":"6",
    "gn:asciiname":"Rancho Dona Santos",
    "gn:country_code":"MX",
    "gn:dem":64,
    "gn:feature_class":"P",
    "gn:feature_code":"PPL",
    "gn:name":"Rancho Do\u00f1a Santos",
    "gn:population":10,
    "gn:timezone":"America/Mazatlan",
    "iso:country":"MX",
    "name:und_x_variant":[
        "Rancho Do\u00f1a Santos"
    ],
    "wof:name":"Rancho Dona Santos",
    "wof:placetype":"locality",
    "wof:population":10
},
  "geometry": {"coordinates":[-107.38029,24.74596],"type":"Point"}
}