{
  "type": "Feature",
  "properties": {
    "gn:admin1_code":"26",
    "gn:admin2_code":"42.0",
    "gn:asciiname":"Rancho del Padre (El Padre)",
    "gn:country_code":"MX",
    "gn:dem":36,
    "gn:feature_class":"P",
    "gn:feature_code":"PPL",
    "gn:name":"Rancho del Padre (El Padre)",
    "gn:population":342,
    "gn:timezone":"America/Hermosillo",
    "iso:country":"MX",
    "wof:name":"Rancho del Padre (El Padre)",
    "wof:placetype":"locality",
    "wof:population":342
},
  "geometry": {"coordinates":[-109.51528,27.11556],"type":"Point"}
}