{
  "type": "Feature",
  "properties": {
    "gn:admin1_code":"18.0",
    "gn:admin2_code":"19.0",
    "gn:asciiname":"Salatita",
    "gn:country_code":"MX",
    "gn:dem":744,
    "gn:feature_class":"P",
    "gn:feature_code":"PPL",
    "gn:name":"Salatita",
    "gn:population":0,
    "gn:timezone":"America/Mazatlan",
    "iso:country":"MX",
    "wof:name":"Salatita",
    "wof:placetype":"locality"
},
  "geometry": {"coordinates":[-104.32011,21.97704],"type":"Point"}
}