{
  "type": "Feature",
  "properties": {
    "gn:admin1_code":"13",
    "gn:admin2_code":"43.0",
    "gn:asciiname":"Jagueey",
    "gn:country_code":"MX",
    "gn:dem":2426,
    "gn:feature_class":"P",
    "gn:feature_code":"PPL",
    "gn:name":"Jag\u00fcey",
    "gn:population":0,
    "gn:timezone":"America/Mexico_City",
    "iso:country":"MX",
    "name:spa_x_preferred":[
        "Jaguey"
    ],
    "name:spa_x_variant":[
        "Jag\u00fcey"
    ],
    "wof:name":"Jagueey",
    "wof:placetype":"locality"
},
  "geometry": {"coordinates":[-99.22848999999999,20.79932],"type":"Point"}
}