{
  "type": "Feature",
  "properties": {
    "gn:admin1_code":"31",
    "gn:admin2_code":"3.0",
    "gn:asciiname":"San Victor",
    "gn:country_code":"MX",
    "gn:dem":33,
    "gn:feature_class":"P",
    "gn:feature_code":"PPL",
    "gn:name":"San V\u00edctor",
    "gn:population":8,
    "gn:timezone":"America/Merida",
    "iso:country":"MX",
    "name:und_x_variant":[
        "San V\u00edctor"
    ],
    "wof:name":"San Victor",
    "wof:placetype":"locality",
    "wof:population":8
},
  "geometry": {"coordinates":[-89.34,20.25194],"type":"Point"}
}