{
  "type": "Feature",
  "properties": {
    "gn:admin1_code":"32",
    "gn:admin2_code":"37.0",
    "gn:asciiname":"El Rey",
    "gn:country_code":"MX",
    "gn:dem":2002,
    "gn:feature_class":"P",
    "gn:feature_code":"PPL",
    "gn:name":"El Rey",
    "gn:population":64,
    "gn:timezone":"America/Mexico_City",
    "iso:country":"MX",
    "name:ceb_x_preferred":[
        "El Rey"
    ],
    "name:hun_x_preferred":[
        "El Rey"
    ],
    "name:spa_x_preferred":[
        "El Rey"
    ],
    "name:swe_x_preferred":[
        "El Rey"
    ],
    "wof:name":"El Rey",
    "wof:placetype":"locality",
    "wof:population":64
},
  "geometry": {"coordinates":[-102.30583,23.03167],"type":"Point"}
}