{
  "type": "Feature",
  "properties": {
    "gn:admin1_code":"6.0",
    "gn:admin2_code":"65.0",
    "gn:asciiname":"Los Pelillos",
    "gn:country_code":"MX",
    "gn:dem":1596,
    "gn:feature_class":"P",
    "gn:feature_code":"PPL",
    "gn:name":"Los Pelillos",
    "gn:population":0,
    "gn:timezone":"America/Chihuahua",
    "iso:country":"MX",
    "name:spa_x_preferred":[
        "Los Pelillos"
    ],
    "wof:name":"Los Pelillos",
    "wof:placetype":"locality"
},
  "geometry": {"coordinates":[-108.00999,27.10198],"type":"Point"}
}