{
  "type": "Feature",
  "properties": {
    "gn:admin1_code":"16",
    "gn:admin2_code":"26",
    "gn:asciiname":"Los Guayabos",
    "gn:country_code":"MX",
    "gn:dem":880,
    "gn:feature_class":"P",
    "gn:feature_code":"PPL",
    "gn:name":"Los Guayabos",
    "gn:population":10,
    "gn:timezone":"America/Mexico_City",
    "iso:country":"MX",
    "wof:name":"Los Guayabos",
    "wof:placetype":"locality",
    "wof:population":10
},
  "geometry": {"coordinates":[-103.3925,18.66778],"type":"Point"}
}