{
  "type": "Feature",
  "properties": {
    "gn:admin1_code":"14",
    "gn:admin2_code":"31",
    "gn:asciiname":"Acualaxco",
    "gn:country_code":"MX",
    "gn:dem":1979,
    "gn:feature_class":"P",
    "gn:feature_code":"PPL",
    "gn:name":"Acualaxco",
    "gn:population":17,
    "gn:timezone":"America/Mexico_City",
    "iso:country":"MX",
    "wof:name":"Acualaxco",
    "wof:placetype":"locality",
    "wof:population":17
},
  "geometry": {"coordinates":[-103.65028,21.6625],"type":"Point"}
}