{
  "type": "Feature",
  "properties": {
    "gn:admin1_code":"30",
    "gn:admin2_code":"89.0",
    "gn:asciiname":"La Ladrillera",
    "gn:country_code":"MX",
    "gn:dem":16,
    "gn:feature_class":"P",
    "gn:feature_code":"PPL",
    "gn:name":"La Ladrillera",
    "gn:population":26,
    "gn:timezone":"America/Mexico_City",
    "iso:country":"MX",
    "wof:name":"La Ladrillera",
    "wof:placetype":"locality",
    "wof:population":26
},
  "geometry": {"coordinates":[-94.71138999999999,17.86167],"type":"Point"}
}