{
  "type": "Feature",
  "properties": {
    "gn:admin1_code":"21.0",
    "gn:admin2_code":"140.0",
    "gn:asciiname":"San Sebastian Tepalcatepec",
    "gn:country_code":"MX",
    "gn:dem":2177,
    "gn:feature_class":"P",
    "gn:feature_code":"PPL",
    "gn:name":"San Sebast\u00edan Tepalcatepec",
    "gn:population":0,
    "gn:timezone":"America/Mexico_City",
    "iso:country":"MX",
    "name:spa_x_preferred":[
        "San Sebasti\u00e1n Tepalcatepec"
    ],
    "name:spa_x_variant":[
        "San Sebast\u00edan Tepalcatepec",
        "San Sebastian Tepalcatepec"
    ],
    "wof:name":"San Sebastian Tepalcatepec",
    "wof:placetype":"locality"
},
  "geometry": {"coordinates":[-98.33327,19.09216],"type":"Point"}
}