{
  "type": "Feature",
  "properties": {
    "gn:admin1_code":"30",
    "gn:admin2_code":"184",
    "gn:asciiname":"Cruzintitla (Ameyalco)",
    "gn:country_code":"MX",
    "gn:dem":2271,
    "gn:feature_class":"P",
    "gn:feature_code":"PPL",
    "gn:name":"Cruzintitla (Ameyalco)",
    "gn:population":34,
    "gn:timezone":"America/Mexico_City",
    "iso:country":"MX",
    "wof:name":"Cruzintitla (Ameyalco)",
    "wof:placetype":"locality",
    "wof:population":34
},
  "geometry": {"coordinates":[-97.12027999999999,18.60278],"type":"Point"}
}