{
  "type": "Feature",
  "properties": {
    "gn:admin1_code":"24",
    "gn:admin2_code":"50.0",
    "gn:asciiname":"Puerta de San Antonio",
    "gn:country_code":"MX",
    "gn:dem":1995,
    "gn:feature_class":"P",
    "gn:feature_code":"PPL",
    "gn:name":"Puerta de San Antonio",
    "gn:population":0,
    "gn:timezone":"America/Mexico_City",
    "iso:country":"MX",
    "name:spa_x_preferred":[
        "Puerta de San Antonio"
    ],
    "wof:name":"Puerta de San Antonio",
    "wof:placetype":"locality"
},
  "geometry": {"coordinates":[-100.85177,21.69758],"type":"Point"}
}