{
  "type": "Feature",
  "properties": {
    "gn:admin1_code":"12",
    "gn:admin2_code":"28.0",
    "gn:asciiname":"Lodo Grande",
    "gn:country_code":"MX",
    "gn:dem":1528,
    "gn:feature_class":"P",
    "gn:feature_code":"PPL",
    "gn:name":"Lodo Grande",
    "gn:population":1035,
    "gn:timezone":"America/Mexico_City",
    "iso:country":"MX",
    "wof:name":"Lodo Grande",
    "wof:placetype":"locality",
    "wof:population":1035
},
  "geometry": {"coordinates":[-99.21194,17.60972000000001],"type":"Point"}
}