{
  "type": "Feature",
  "properties": {
    "gn:admin1_code":"31",
    "gn:admin2_code":"96.0",
    "gn:asciiname":"Santa Candelaria",
    "gn:country_code":"MX",
    "gn:dem":11,
    "gn:feature_class":"P",
    "gn:feature_code":"PPL",
    "gn:name":"Santa Candelaria",
    "gn:population":8,
    "gn:timezone":"America/Merida",
    "iso:country":"MX",
    "wof:name":"Santa Candelaria",
    "wof:placetype":"locality",
    "wof:population":8
},
  "geometry": {"coordinates":[-88.05,21.2625],"type":"Point"}
}