{
  "type": "Feature",
  "properties": {
    "gn:admin1_code":"5",
    "gn:admin2_code":"99",
    "gn:asciiname":"San Martin el Recuerdo",
    "gn:country_code":"MX",
    "gn:dem":799,
    "gn:feature_class":"P",
    "gn:feature_code":"PPL",
    "gn:name":"San Mart\u00edn el Recuerdo",
    "gn:population":18,
    "gn:timezone":"America/Mexico_City",
    "iso:country":"MX",
    "name:und_x_variant":[
        "San Mart\u00edn el Recuerdo"
    ],
    "wof:name":"San Martin el Recuerdo",
    "wof:placetype":"locality",
    "wof:population":18
},
  "geometry": {"coordinates":[-91.96472,15.97056],"type":"Point"}
}