{
  "type": "Feature",
  "properties": {
    "gn:admin1_code":"30.0",
    "gn:admin2_code":"160.0",
    "gn:asciiname":"Cerro Verde",
    "gn:country_code":"MX",
    "gn:dem":109,
    "gn:feature_class":"P",
    "gn:feature_code":"PPL",
    "gn:name":"Cerro Verde",
    "gn:population":3,
    "gn:timezone":"America/Mexico_City",
    "iso:country":"MX",
    "name:spa_x_preferred":[
        "Cerro Verde"
    ],
    "wof:name":"Cerro Verde",
    "wof:placetype":"locality",
    "wof:population":3
},
  "geometry": {"coordinates":[-97.73778,21.12028],"type":"Point"}
}