{
  "type": "Feature",
  "properties": {
    "gn:admin1_code":"8",
    "gn:admin2_code":"3.0",
    "gn:asciiname":"San Martin de los Pinos",
    "gn:country_code":"MX",
    "gn:dem":949,
    "gn:feature_class":"P",
    "gn:feature_code":"PPL",
    "gn:name":"San Mart\u00edn de los Pinos",
    "gn:population":7,
    "gn:timezone":"America/Mexico_City",
    "iso:country":"MX",
    "name:und_x_variant":[
        "San Mart\u00edn de los Pinos"
    ],
    "wof:name":"San Martin de los Pinos",
    "wof:placetype":"locality",
    "wof:population":7
},
  "geometry": {"coordinates":[-103.72360999999999,19.36556],"type":"Point"}
}