{
  "type": "Feature",
  "properties": {
    "gn:admin1_code":"16.0",
    "gn:admin2_code":"53.0",
    "gn:asciiname":"Atecuaro",
    "gn:country_code":"MX",
    "gn:dem":2243,
    "gn:feature_class":"P",
    "gn:feature_code":"PPL",
    "gn:name":"At\u00e9cuaro",
    "gn:population":437,
    "gn:timezone":"America/Mexico_City",
    "iso:country":"MX",
    "name:spa_x_preferred":[
        "At\u00e9cuaro"
    ],
    "wof:name":"Atecuaro",
    "wof:placetype":"locality",
    "wof:population":437
},
  "geometry": {"coordinates":[-101.18906,19.58277],"type":"Point"}
}