{
  "type": "Feature",
  "properties": {
    "gn:admin1_code":"16.0",
    "gn:admin2_code":"100.0",
    "gn:asciiname":"Cucuchucho",
    "gn:country_code":"MX",
    "gn:dem":2060,
    "gn:feature_class":"P",
    "gn:feature_code":"PPL",
    "gn:name":"Cucuchucho",
    "gn:population":0,
    "gn:timezone":"America/Mexico_City",
    "iso:country":"MX",
    "name:spa_x_preferred":[
        "Cucuchucho"
    ],
    "name:spa_x_variant":[
        "San Pedro Cucuchucho"
    ],
    "wof:name":"Cucuchucho",
    "wof:placetype":"locality"
},
  "geometry": {"coordinates":[-101.63111000000001,19.58275],"type":"Point"}
}