{
  "type": "Feature",
  "properties": {
    "gn:admin1_code":"24.0",
    "gn:admin2_code":"43.0",
    "gn:asciiname":"Labor de Osolla",
    "gn:country_code":"MX",
    "gn:dem":1983,
    "gn:feature_class":"P",
    "gn:feature_code":"PPL",
    "gn:name":"Labor de Osolla",
    "gn:population":0,
    "gn:timezone":"America/Mexico_City",
    "iso:country":"MX",
    "name:spa_x_preferred":[
        "Labor de Osolla"
    ],
    "wof:name":"Labor de Osolla",
    "wof:placetype":"locality"
},
  "geometry": {"coordinates":[-100.56229,21.57575],"type":"Point"}
}