{
  "type": "Feature",
  "properties": {
    "gn:admin1_code":"14.0",
    "gn:admin2_code":"52.0",
    "gn:asciiname":"Mezcalera",
    "gn:country_code":"MX",
    "gn:dem":1292,
    "gn:feature_class":"P",
    "gn:feature_code":"PPL",
    "gn:name":"Mezcalera",
    "gn:population":0,
    "gn:timezone":"America/Mexico_City",
    "iso:country":"MX",
    "name:spa_x_preferred":[
        "Mezcalera"
    ],
    "wof:name":"Mezcalera",
    "wof:placetype":"locality"
},
  "geometry": {"coordinates":[-104.00568,20.05159],"type":"Point"}
}