{
  "type": "Feature",
  "properties": {
    "gn:admin1_code":"31",
    "gn:admin2_code":"58.0",
    "gn:asciiname":"Sahpacal",
    "gn:country_code":"MX",
    "gn:dem":33,
    "gn:feature_class":"P",
    "gn:feature_code":"PPL",
    "gn:name":"Sahpacal",
    "gn:population":0,
    "gn:timezone":"America/Merida",
    "iso:country":"MX",
    "name:spa_x_preferred":[
        "Sahpacal"
    ],
    "wof:name":"Sahpacal",
    "wof:placetype":"locality"
},
  "geometry": {"coordinates":[-88.72234,20.10533],"type":"Point"}
}