{
  "type": "Feature",
  "properties": {
    "gn:admin1_code":"5",
    "gn:admin2_code":"44",
    "gn:asciiname":"El Piedron",
    "gn:country_code":"MX",
    "gn:dem":1198,
    "gn:feature_class":"P",
    "gn:feature_code":"PPL",
    "gn:name":"El Piedr\u00f3n",
    "gn:population":19,
    "gn:timezone":"America/Mexico_City",
    "iso:country":"MX",
    "name:und_x_variant":[
        "El Piedr\u00f3n"
    ],
    "wof:name":"El Piedron",
    "wof:placetype":"locality",
    "wof:population":19
},
  "geometry": {"coordinates":[-92.87900999999999,16.79473],"type":"Point"}
}