{
  "type": "Feature",
  "properties": {
    "gn:admin1_code":"15",
    "gn:admin2_code":"52.0",
    "gn:asciiname":"San Simon el Alto",
    "gn:country_code":"MX",
    "gn:dem":2412,
    "gn:feature_class":"P",
    "gn:feature_code":"PPL",
    "gn:name":"San Sim\u00f3n el Alto",
    "gn:population":0,
    "gn:timezone":"America/Mexico_City",
    "iso:country":"MX",
    "name:spa_x_preferred":[
        "San Sim\u00f3n el Alto"
    ],
    "wof:name":"San Simon el Alto",
    "wof:placetype":"locality"
},
  "geometry": {"coordinates":[-99.50344,18.99653],"type":"Point"}
}