{
  "type": "Feature",
  "properties": {
    "gn:admin1_code":"5.0",
    "gn:asciiname":"Kukulkan",
    "gn:country_code":"MX",
    "gn:dem":58,
    "gn:feature_class":"P",
    "gn:feature_code":"PPL",
    "gn:name":"Kukulk\u00e1n",
    "gn:population":0,
    "gn:timezone":"America/Mexico_City",
    "iso:country":"MX",
    "name:bel_x_preferred":[
        "\u041a\u0443\u043a\u0443\u043b\u044c\u043a\u0430\u043d"
    ],
    "name:cat_x_preferred":[
        "Kukulkan"
    ],
    "name:deu_x_preferred":[
        "Kukulkan"
    ],
    "name:diq_x_preferred":[
        "Kukulkan"
    ],
    "name:epo_x_preferred":[
        "Kukulkano"
    ],
    "name:fas_x_preferred":[
        "\u06a9\u0648\u06a9\u0648\u0644\u06a9\u0627\u0646"
    ],
    "name:fra_x_preferred":[
        "Kukulkan"
    ],
    "name:ind_x_preferred":[
        "Kukulkan"
    ],
    "name:ita_x_preferred":[
        "Kukulk\u00e1n"
    ],
    "name:jpn_x_preferred":[
        "\u30af\u30af\u30eb\u30ab\u30f3"
    ],
    "name:kat_x_preferred":[
        "\u10d9\u10e3\u10d9\u10e3\u10da\u10d9\u10d0\u10dc\u10d8"
    ],
    "name:kor_x_preferred":[
        "\ucfe0\ucfe8\uce78"
    ],
    "name:lit_x_preferred":[
        "Kukulkanas"
    ],
    "name:nah_x_preferred":[
        "Kukulk\u00e1n"
    ],
    "name:nld_x_preferred":[
        "Kukulcan"
    ],
    "name:pol_x_preferred":[
        "Kukulkan"
    ],
    "name:por_x_preferred":[
        "Kukulc\u00e1n"
    ],
    "name:ron_x_preferred":[
        "Kukulkan"
    ],
    "name:rus_x_preferred":[
        "\u041a\u0443\u043a\u0443\u043b\u044c\u043a\u0430\u043d"
    ],
    "name:slv_x_preferred":[
        "Kukulkan"
    ],
    "name:spa_x_preferred":[
        "Kukulk\u00e1n"
    ],
    "name:swe_x_preferred":[
        "Kukulc\u00e1n"
    ],
    "name:zho_x_preferred":[
        "\u5eab\u5eab\u723e\u574e"
    ],
    "wof:name":"Kukulkan",
    "wof:placetype":"locality"
},
  "geometry": {"coordinates":[-91.98002,17.48904],"type":"Point"}
}