{
  "type": "Feature",
  "properties": {
    "gn:admin1_code":"15",
    "gn:admin2_code":"60.0",
    "gn:asciiname":"La Colmena",
    "gn:country_code":"MX",
    "gn:dem":2394,
    "gn:feature_class":"P",
    "gn:feature_code":"PPL",
    "gn:name":"La Colmena",
    "gn:population":0,
    "gn:timezone":"America/Mexico_City",
    "iso:country":"MX",
    "name:und_x_variant":[
        "Colmena",
        "La Colmena"
    ],
    "wof:name":"La Colmena",
    "wof:placetype":"locality"
},
  "geometry": {"coordinates":[-99.28212000000001,19.60354],"type":"Point"}
}