{
  "type": "Feature",
  "properties": {
    "gn:admin1_code":"5",
    "gn:admin2_code":"3",
    "gn:asciiname":"El Trebol",
    "gn:country_code":"MX",
    "gn:dem":38,
    "gn:feature_class":"P",
    "gn:feature_code":"PPL",
    "gn:name":"El Trebol",
    "gn:population":9,
    "gn:timezone":"America/Mexico_City",
    "iso:country":"MX",
    "wof:name":"El Trebol",
    "wof:placetype":"locality",
    "wof:population":9
},
  "geometry": {"coordinates":[-92.7975,15.38833],"type":"Point"}
}