{
  "type": "Feature",
  "properties": {
    "gn:admin1_code":"13",
    "gn:admin2_code":"52",
    "gn:asciiname":"Monte de Guadalupe",
    "gn:country_code":"MX",
    "gn:dem":2188,
    "gn:feature_class":"P",
    "gn:feature_code":"PPL",
    "gn:name":"Monte de Guadalupe",
    "gn:population":42,
    "gn:timezone":"America/Mexico_City",
    "iso:country":"MX",
    "wof:name":"Monte de Guadalupe",
    "wof:placetype":"locality",
    "wof:population":42
},
  "geometry": {"coordinates":[-98.97288,20.11055],"type":"Point"}
}