{
  "type": "Feature",
  "properties": {
    "gn:admin1_code":"28.0",
    "gn:admin2_code":"8.0",
    "gn:asciiname":"Subida de Palmas",
    "gn:country_code":"MX",
    "gn:dem":462,
    "gn:feature_class":"P",
    "gn:feature_code":"PPL",
    "gn:name":"Subida de Palmas",
    "gn:population":55,
    "gn:timezone":"America/Monterrey",
    "iso:country":"MX",
    "name:spa_x_preferred":[
        "Subida de Palmas"
    ],
    "wof:name":"Subida de Palmas",
    "wof:placetype":"locality",
    "wof:population":55
},
  "geometry": {"coordinates":[-98.55556,23.57972],"type":"Point"}
}