{
  "type": "Feature",
  "properties": {
    "gn:admin1_code":"30.0",
    "gn:admin2_code":"207.0",
    "gn:asciiname":"San Martin las Caobas",
    "gn:country_code":"MX",
    "gn:dem":44,
    "gn:feature_class":"P",
    "gn:feature_code":"PPL",
    "gn:name":"San Mart\u00edn las Caobas",
    "gn:population":0,
    "gn:timezone":"America/Mexico_City",
    "iso:country":"MX",
    "name:spa_x_preferred":[
        "San Mart\u00edn las Caobas"
    ],
    "name:spa_x_variant":[
        "El Sacrificio"
    ],
    "wof:name":"San Martin las Caobas",
    "wof:placetype":"locality"
},
  "geometry": {"coordinates":[-96.26887000000001,18.32239],"type":"Point"}
}