{
  "type": "Feature",
  "properties": {
    "gn:admin1_code":"21",
    "gn:admin2_code":"36.0",
    "gn:asciiname":"Ahuatepec",
    "gn:country_code":"MX",
    "gn:dem":2095,
    "gn:feature_class":"P",
    "gn:feature_code":"PPL",
    "gn:name":"Ahuatepec",
    "gn:population":0,
    "gn:timezone":"America/Mexico_City",
    "iso:country":"MX",
    "name:und_x_variant":[
        "Aguatepec",
        "Ahuatepec"
    ],
    "wof:name":"Ahuatepec",
    "wof:placetype":"locality"
},
  "geometry": {"coordinates":[-96.99926000000001,18.23302],"type":"Point"}
}