{
  "type": "Feature",
  "properties": {
    "gn:admin1_code":"17.0",
    "gn:asciiname":"El Platanar",
    "gn:country_code":"MX",
    "gn:dem":1059,
    "gn:feature_class":"P",
    "gn:feature_code":"PPL",
    "gn:name":"El Platanar",
    "gn:population":0,
    "gn:timezone":"America/Mexico_City",
    "iso:country":"MX",
    "name:spa_x_preferred":[
        "El Platanar"
    ],
    "name:spa_x_variant":[
        "Las Higuerillas"
    ],
    "wof:name":"El Platanar",
    "wof:placetype":"locality"
},
  "geometry": {"coordinates":[-99.10397,18.73891],"type":"Point"}
}