{
  "type": "Feature",
  "properties": {
    "gn:admin1_code":"10",
    "gn:admin2_code":"8.0",
    "gn:asciiname":"Juan Saldivar Avalos",
    "gn:country_code":"MX",
    "gn:dem":1994,
    "gn:feature_class":"P",
    "gn:feature_code":"PPL",
    "gn:name":"Juan Saldivar \u00c1valos",
    "gn:population":4,
    "gn:timezone":"America/Monterrey",
    "iso:country":"MX",
    "name:und_x_variant":[
        "Juan Saldivar \u00c1valos"
    ],
    "wof:name":"Juan Saldivar Avalos",
    "wof:placetype":"locality",
    "wof:population":4
},
  "geometry": {"coordinates":[-104.06778,24.46389],"type":"Point"}
}