{
  "type": "Feature",
  "properties": {
    "gn:admin1_code":"25.0",
    "gn:admin2_code":"16.0",
    "gn:asciiname":"Bordentita",
    "gn:country_code":"MX",
    "gn:dem":346,
    "gn:feature_class":"P",
    "gn:feature_code":"PPL",
    "gn:name":"Bordentita",
    "gn:population":0,
    "gn:timezone":"America/Mazatlan",
    "iso:country":"MX",
    "name:und_x_variant":[
        "Bordonlita",
        "Bordondita"
    ],
    "wof:name":"Bordentita",
    "wof:placetype":"locality"
},
  "geometry": {"coordinates":[-106.32331000000001,24.19017],"type":"Point"}
}