{
  "type": "Feature",
  "properties": {
    "gn:admin1_code":"30",
    "gn:admin2_code":"155.0",
    "gn:asciiname":"Condesa Chica",
    "gn:country_code":"MX",
    "gn:dem":86,
    "gn:feature_class":"P",
    "gn:feature_code":"PPL",
    "gn:name":"Condesa Chica",
    "gn:population":0,
    "gn:timezone":"America/Mexico_City",
    "iso:country":"MX",
    "name:spa_x_preferred":[
        "Condesa Chica"
    ],
    "name:und_x_variant":[
        "La Condesa"
    ],
    "wof:name":"Condesa Chica",
    "wof:placetype":"locality"
},
  "geometry": {"coordinates":[-98.21505999999999,21.20238],"type":"Point"}
}