{
  "type": "Feature",
  "properties": {
    "gn:admin1_code":"6",
    "gn:admin2_code":"2.0",
    "gn:asciiname":"Loma Larga",
    "gn:country_code":"MX",
    "gn:dem":1144,
    "gn:feature_class":"P",
    "gn:feature_code":"PPL",
    "gn:name":"Loma Larga",
    "gn:population":0,
    "gn:timezone":"America/Chihuahua",
    "iso:country":"MX",
    "name:und_x_variant":[
        "Rancho Loma Larga",
        "Loma Larga"
    ],
    "wof:name":"Loma Larga",
    "wof:placetype":"locality"
},
  "geometry": {"coordinates":[-105.56638999999998,28.85841],"type":"Point"}
}