{
  "type": "Feature",
  "properties": {
    "gn:admin1_code":"9",
    "gn:admin2_code":"13.0",
    "gn:asciiname":"Rancho el Cedro",
    "gn:country_code":"MX",
    "gn:dem":2596,
    "gn:feature_class":"P",
    "gn:feature_code":"PPL",
    "gn:name":"Rancho el Cedro",
    "gn:population":112,
    "gn:timezone":"America/Mexico_City",
    "iso:country":"MX",
    "wof:name":"Rancho el Cedro",
    "wof:placetype":"locality",
    "wof:population":112
},
  "geometry": {"coordinates":[-99.11083000000001,19.20222],"type":"Point"}
}