{
  "type": "Feature",
  "properties": {
    "gn:admin1_code":"5",
    "gn:admin2_code":"59",
    "gn:asciiname":"La Palma",
    "gn:country_code":"MX",
    "gn:dem":1092,
    "gn:feature_class":"P",
    "gn:feature_code":"PPL",
    "gn:name":"La Palma",
    "gn:population":51,
    "gn:timezone":"America/Mexico_City",
    "iso:country":"MX",
    "wof:name":"La Palma",
    "wof:placetype":"locality",
    "wof:population":51
},
  "geometry": {"coordinates":[-91.99028,16.93639],"type":"Point"}
}