{
  "type": "Feature",
  "properties": {
    "gn:admin1_code":"24",
    "gn:admin2_code":"21.0",
    "gn:asciiname":"Ojo Zarco",
    "gn:country_code":"MX",
    "gn:dem":2137,
    "gn:feature_class":"P",
    "gn:feature_code":"PPL",
    "gn:name":"Ojo Zarco",
    "gn:population":0,
    "gn:timezone":"America/Mexico_City",
    "iso:country":"MX",
    "wof:name":"Ojo Zarco",
    "wof:placetype":"locality"
},
  "geometry": {"coordinates":[-101.26079,22.28792],"type":"Point"}
}