{
  "type": "Feature",
  "properties": {
    "gn:admin1_code":"6",
    "gn:admin2_code":"67.0",
    "gn:asciiname":"Bartoleno",
    "gn:country_code":"MX",
    "gn:dem":1381,
    "gn:feature_class":"P",
    "gn:feature_code":"PPL",
    "gn:name":"Bartole\u00f1o",
    "gn:population":0,
    "gn:timezone":"America/Chihuahua",
    "iso:country":"MX",
    "name:spa_x_preferred":[
        "Bartole\u00f1o"
    ],
    "wof:name":"Bartoleno",
    "wof:placetype":"locality"
},
  "geometry": {"coordinates":[-106.03856,27.3574],"type":"Point"}
}