{
  "type": "Feature",
  "properties": {
    "gn:admin1_code":"32",
    "gn:admin2_code":"13.0",
    "gn:asciiname":"Estacada",
    "gn:country_code":"MX",
    "gn:dem":2116,
    "gn:feature_class":"P",
    "gn:feature_code":"PPL",
    "gn:name":"Estacada",
    "gn:population":0,
    "gn:timezone":"America/Mexico_City",
    "iso:country":"MX",
    "name:spa_x_preferred":[
        "Estacada"
    ],
    "wof:name":"Estacada",
    "wof:placetype":"locality"
},
  "geometry": {"coordinates":[-102.71005,23.03674],"type":"Point"}
}