{
  "type": "Feature",
  "properties": {
    "gn:admin1_code":"30",
    "gn:admin2_code":"187.0",
    "gn:asciiname":"Puentezuelos",
    "gn:country_code":"MX",
    "gn:dem":1982,
    "gn:feature_class":"P",
    "gn:feature_code":"PPL",
    "gn:name":"Puentezuelos",
    "gn:population":792,
    "gn:timezone":"America/Mexico_City",
    "iso:country":"MX",
    "wof:name":"Puentezuelos",
    "wof:placetype":"locality",
    "wof:population":792
},
  "geometry": {"coordinates":[-96.92694,19.71306],"type":"Point"}
}