{
  "type": "Feature",
  "properties": {
    "gn:admin1_code":"7.0",
    "gn:admin2_code":"14.0",
    "gn:asciiname":"Paso los Cristales",
    "gn:country_code":"MX",
    "gn:dem":327,
    "gn:feature_class":"P",
    "gn:feature_code":"PPL",
    "gn:name":"Paso los Cristales",
    "gn:population":0,
    "gn:timezone":"America/Monterrey",
    "iso:country":"MX",
    "name:spa_x_preferred":[
        "Paso los Cristales"
    ],
    "wof:name":"Paso los Cristales",
    "wof:placetype":"locality"
},
  "geometry": {"coordinates":[-100.98193000000001,29.08233],"type":"Point"}
}