{
  "type": "Feature",
  "properties": {
    "gn:admin1_code":"6.0",
    "gn:asciiname":"Los Sauces",
    "gn:country_code":"MX",
    "gn:dem":1299,
    "gn:feature_class":"P",
    "gn:feature_code":"PPL",
    "gn:name":"Los Sauces",
    "gn:population":0,
    "gn:timezone":"America/Chihuahua",
    "iso:country":"MX",
    "name:spa_x_preferred":[
        "Los Sauces"
    ],
    "wof:name":"Los Sauces",
    "wof:placetype":"locality"
},
  "geometry": {"coordinates":[-107.97763,31.12292],"type":"Point"}
}