{
  "type": "Feature",
  "properties": {
    "gn:admin1_code":"31",
    "gn:admin2_code":"79.0",
    "gn:asciiname":"Pocoboch",
    "gn:country_code":"MX",
    "gn:dem":123,
    "gn:feature_class":"P",
    "gn:feature_code":"PPL",
    "gn:name":"Pocoboch",
    "gn:population":0,
    "gn:timezone":"America/Merida",
    "iso:country":"MX",
    "name:spa_x_preferred":[
        "Pocoboch"
    ],
    "name:spa_x_variant":[
        "Popobosh"
    ],
    "wof:name":"Pocoboch",
    "wof:placetype":"locality"
},
  "geometry": {"coordinates":[-89.30759,19.90241],"type":"Point"}
}