{
  "type": "Feature",
  "properties": {
    "gn:admin1_code":"6",
    "gn:admin2_code":"58.0",
    "gn:asciiname":"Los Filtros",
    "gn:country_code":"MX",
    "gn:dem":1266,
    "gn:feature_class":"P",
    "gn:feature_code":"PPL",
    "gn:name":"Los Filtros",
    "gn:population":0,
    "gn:timezone":"America/Chihuahua",
    "iso:country":"MX",
    "name:spa_x_preferred":[
        "Los Filtros"
    ],
    "name:spa_x_variant":[
        "Las Palmas"
    ],
    "wof:name":"Los Filtros",
    "wof:placetype":"locality"
},
  "geometry": {"coordinates":[-105.42407,27.56999],"type":"Point"}
}