{
  "type": "Feature",
  "properties": {
    "gn:admin1_code":"6",
    "gn:admin2_code":"7.0",
    "gn:asciiname":"Mesa del Agua",
    "gn:country_code":"MX",
    "gn:dem":2660,
    "gn:feature_class":"P",
    "gn:feature_code":"PPL",
    "gn:name":"Mesa del Agua",
    "gn:population":0,
    "gn:timezone":"America/Monterrey",
    "iso:country":"MX",
    "name:spa_x_preferred":[
        "Mesa del Agua"
    ],
    "wof:name":"Mesa del Agua",
    "wof:placetype":"locality"
},
  "geometry": {"coordinates":[-106.35659,26.34286],"type":"Point"}
}