{
  "type": "Feature",
  "properties": {
    "gn:admin1_code":"16",
    "gn:admin2_code":"97.0",
    "gn:asciiname":"El Paracatal",
    "gn:country_code":"MX",
    "gn:dem":613,
    "gn:feature_class":"P",
    "gn:feature_code":"PPL",
    "gn:name":"El Paracatal",
    "gn:population":0,
    "gn:timezone":"America/Mexico_City",
    "iso:country":"MX",
    "name:spa_x_preferred":[
        "El Paracatal"
    ],
    "wof:name":"El Paracatal",
    "wof:placetype":"locality"
},
  "geometry": {"coordinates":[-101.38521,18.83985],"type":"Point"}
}