{
  "type": "Feature",
  "properties": {
    "gn:admin1_code":"25",
    "gn:admin2_code":"10",
    "gn:asciiname":"El Pantano",
    "gn:country_code":"MX",
    "gn:dem":211,
    "gn:feature_class":"P",
    "gn:feature_code":"PPL",
    "gn:name":"El Pantano",
    "gn:population":19,
    "gn:timezone":"America/Mazatlan",
    "iso:country":"MX",
    "name:ita_x_preferred":[
        "El Pantano"
    ],
    "name:spa_x_preferred":[
        "El Pantano"
    ],
    "name:zho_x_preferred":[
        "\u57c3\u5c14\u6f58\u5854\u8bfa"
    ],
    "wof:name":"El Pantano",
    "wof:placetype":"locality",
    "wof:population":19
},
  "geometry": {"coordinates":[-108.30920999999999,26.26535],"type":"Point"}
}