{
  "type": "Feature",
  "properties": {
    "gn:admin1_code":"26.0",
    "gn:admin2_code":"19.0",
    "gn:asciiname":"Cuitaca",
    "gn:country_code":"MX",
    "gn:dem":1328,
    "gn:feature_class":"P",
    "gn:feature_code":"PPL",
    "gn:name":"Cuitaca",
    "gn:population":0,
    "gn:timezone":"America/Hermosillo",
    "iso:country":"MX",
    "wof:name":"Cuitaca",
    "wof:placetype":"locality"
},
  "geometry": {"coordinates":[-110.46666999999999,30.96667],"type":"Point"}
}