{
  "type": "Feature",
  "properties": {
    "gn:admin1_code":"5.0",
    "gn:admin2_code":"65.0",
    "gn:asciiname":"Jabalineros",
    "gn:country_code":"MX",
    "gn:dem":32,
    "gn:feature_class":"P",
    "gn:feature_code":"PPL",
    "gn:name":"Jabalineros",
    "gn:population":0,
    "gn:timezone":"America/Mexico_City",
    "iso:country":"MX",
    "name:spa_x_preferred":[
        "El Jabalinero"
    ],
    "name:spa_x_variant":[
        "Jabalineros"
    ],
    "wof:name":"Jabalineros",
    "wof:placetype":"locality"
},
  "geometry": {"coordinates":[-91.78908,17.50217],"type":"Point"}
}