{
  "type": "Feature",
  "properties": {
    "gn:admin1_code":"16.0",
    "gn:admin2_code":"8.0",
    "gn:asciiname":"Maruata Viejo",
    "gn:country_code":"MX",
    "gn:dem":14,
    "gn:feature_class":"P",
    "gn:feature_code":"PPL",
    "gn:name":"Maruata Viejo",
    "gn:population":0,
    "gn:timezone":"America/Mexico_City",
    "iso:country":"MX",
    "name:spa_x_preferred":[
        "Maruata Viejo"
    ],
    "wof:name":"Maruata Viejo",
    "wof:placetype":"locality"
},
  "geometry": {"coordinates":[-103.37157999999999,18.28062000000001],"type":"Point"}
}