{
  "type": "Feature",
  "properties": {
    "gn:admin1_code":"6",
    "gn:admin2_code":"11.0",
    "gn:asciiname":"San Fernando",
    "gn:country_code":"MX",
    "gn:dem":1398,
    "gn:feature_class":"P",
    "gn:feature_code":"PPL",
    "gn:name":"San Fernando",
    "gn:population":3,
    "gn:timezone":"America/Chihuahua",
    "iso:country":"MX",
    "name:spa_x_preferred":[
        "San Fernando"
    ],
    "name:und_x_variant":[
        "Rancho San Fernando"
    ],
    "wof:name":"San Fernando",
    "wof:placetype":"locality",
    "wof:population":3
},
  "geometry": {"coordinates":[-104.6139,27.97186],"type":"Point"}
}