{
  "type": "Feature",
  "properties": {
    "gn:admin1_code":"19",
    "gn:admin2_code":"38.0",
    "gn:asciiname":"Ejido Cieneguillas",
    "gn:country_code":"MX",
    "gn:dem":391,
    "gn:feature_class":"P",
    "gn:feature_code":"PPL",
    "gn:name":"Ejido Cieneguillas",
    "gn:population":0,
    "gn:timezone":"America/Monterrey",
    "iso:country":"MX",
    "name:spa_x_preferred":[
        "Ejido Cieneguillas"
    ],
    "wof:name":"Ejido Cieneguillas",
    "wof:placetype":"locality"
},
  "geometry": {"coordinates":[-99.87494,25.24051],"type":"Point"}
}