{
  "type": "Feature",
  "properties": {
    "gn:admin1_code":"25",
    "gn:admin2_code":"16.0",
    "gn:asciiname":"Campanillas",
    "gn:country_code":"MX",
    "gn:dem":258,
    "gn:feature_class":"P",
    "gn:feature_code":"PPL",
    "gn:name":"Campanillas",
    "gn:population":68,
    "gn:timezone":"America/Mazatlan",
    "iso:country":"MX",
    "name:fra_x_preferred":[
        "Campanillas"
    ],
    "name:hat_x_preferred":[
        "Campanillas"
    ],
    "name:spa_x_preferred":[
        "Campanillas"
    ],
    "wof:name":"Campanillas",
    "wof:placetype":"locality",
    "wof:population":68
},
  "geometry": {"coordinates":[-106.45944,24.05944],"type":"Point"}
}