{
  "type": "Feature",
  "properties": {
    "gn:admin1_code":"5",
    "gn:admin2_code":"4",
    "gn:asciiname":"San Luis",
    "gn:country_code":"MX",
    "gn:dem":1222,
    "gn:feature_class":"P",
    "gn:feature_code":"PPL",
    "gn:name":"San Luis",
    "gn:population":20,
    "gn:timezone":"America/Mexico_City",
    "iso:country":"MX",
    "wof:name":"San Luis",
    "wof:placetype":"locality",
    "wof:population":20
},
  "geometry": {"coordinates":[-92.10778000000001,16.73556],"type":"Point"}
}