{
  "type": "Feature",
  "properties": {
    "gn:admin1_code":"15",
    "gn:admin2_code":"124.0",
    "gn:asciiname":"La Curva",
    "gn:country_code":"MX",
    "gn:dem":2752,
    "gn:feature_class":"P",
    "gn:feature_code":"PPL",
    "gn:name":"La Curva",
    "gn:population":255,
    "gn:timezone":"America/Mexico_City",
    "iso:country":"MX",
    "wof:name":"La Curva",
    "wof:placetype":"locality",
    "wof:population":255
},
  "geometry": {"coordinates":[-100.12694,19.52917],"type":"Point"}
}