{
  "type": "Feature",
  "properties": {
    "gn:admin1_code":"15",
    "gn:admin2_code":"25.0",
    "gn:asciiname":"San Juan y San Pedro Tezompa",
    "gn:country_code":"MX",
    "gn:dem":2251,
    "gn:feature_class":"P",
    "gn:feature_code":"PPL",
    "gn:name":"San Juan y San Pedro Tezompa",
    "gn:population":0,
    "gn:timezone":"America/Mexico_City",
    "iso:country":"MX",
    "name:spa_x_preferred":[
        "San Juan y San Pedro Tezompa"
    ],
    "name:spa_x_variant":[
        "San Juan Tezompa"
    ],
    "name:und_x_variant":[
        "Tezompa",
        "San Juan",
        "San Pedro Tezompa"
    ],
    "wof:name":"San Juan y San Pedro Tezompa",
    "wof:placetype":"locality"
},
  "geometry": {"coordinates":[-98.96073,19.2068],"type":"Point"}
}