{
  "type": "Feature",
  "properties": {
    "gn:admin1_code":"30",
    "gn:admin2_code":"116.0",
    "gn:asciiname":"El Campero",
    "gn:country_code":"MX",
    "gn:dem":80,
    "gn:feature_class":"P",
    "gn:feature_code":"PPL",
    "gn:name":"El Campero",
    "gn:population":9,
    "gn:timezone":"America/Mexico_City",
    "iso:country":"MX",
    "wof:name":"El Campero",
    "wof:placetype":"locality",
    "wof:population":9
},
  "geometry": {"coordinates":[-94.92417,17.92833],"type":"Point"}
}