{
  "type": "Feature",
  "properties": {
    "gn:admin1_code":"22",
    "gn:admin2_code":"7.0",
    "gn:asciiname":"Rancho Santa Cruz de Purisima",
    "gn:country_code":"MX",
    "gn:dem":1946,
    "gn:feature_class":"P",
    "gn:feature_code":"PPL",
    "gn:name":"Rancho Santa Cruz de Pur\u00edsima",
    "gn:population":7,
    "gn:timezone":"America/Mexico_City",
    "iso:country":"MX",
    "name:und_x_variant":[
        "Rancho Santa Cruz de Pur\u00edsima"
    ],
    "wof:name":"Rancho Santa Cruz de Purisima",
    "wof:placetype":"locality",
    "wof:population":7
},
  "geometry": {"coordinates":[-99.92194000000001,20.65361],"type":"Point"}
}