{
  "type": "Feature",
  "properties": {
    "gn:admin1_code":"14.0",
    "gn:asciiname":"El Santo Cristo",
    "gn:country_code":"MX",
    "gn:dem":2025,
    "gn:feature_class":"P",
    "gn:feature_code":"PPL",
    "gn:name":"El Santo Cristo",
    "gn:population":0,
    "gn:timezone":"America/Mexico_City",
    "iso:country":"MX",
    "name:spa_x_preferred":[
        "El Santo Cristo"
    ],
    "name:spa_x_variant":[
        "Santo Cristo"
    ],
    "wof:name":"El Santo Cristo",
    "wof:placetype":"locality"
},
  "geometry": {"coordinates":[-102.15273999999999,20.92032],"type":"Point"}
}