{
  "type": "Feature",
  "properties": {
    "gn:admin1_code":"6",
    "gn:admin2_code":"7.0",
    "gn:asciiname":"Mesa Blanca",
    "gn:country_code":"MX",
    "gn:dem":2505,
    "gn:feature_class":"P",
    "gn:feature_code":"PPL",
    "gn:name":"Mesa Blanca",
    "gn:population":91,
    "gn:timezone":"America/Chihuahua",
    "iso:country":"MX",
    "wof:name":"Mesa Blanca",
    "wof:placetype":"locality",
    "wof:population":91
},
  "geometry": {"coordinates":[-106.57228000000001,26.50713],"type":"Point"}
}