{
  "type": "Feature",
  "properties": {
    "gn:admin1_code":"12",
    "gn:admin2_code":"47",
    "gn:asciiname":"Agua Fria",
    "gn:country_code":"MX",
    "gn:dem":1415,
    "gn:feature_class":"P",
    "gn:feature_code":"PPL",
    "gn:name":"Agua Fr\u00eda",
    "gn:population":17,
    "gn:timezone":"America/Mexico_City",
    "iso:country":"MX",
    "name:ceb_x_preferred":[
        "Agua Fria"
    ],
    "name:deu_x_preferred":[
        "Agua Fria"
    ],
    "name:swe_x_preferred":[
        "Agua Fria"
    ],
    "name:und_x_variant":[
        "Agua Fr\u00eda"
    ],
    "wof:name":"Agua Fria",
    "wof:placetype":"locality",
    "wof:population":17
},
  "geometry": {"coordinates":[-99.86065000000001,18.56133],"type":"Point"}
}