{
  "type": "Feature",
  "properties": {
    "gn:admin1_code":"30",
    "gn:admin2_code":"117.0",
    "gn:asciiname":"Paso Real",
    "gn:country_code":"MX",
    "gn:dem":358,
    "gn:feature_class":"P",
    "gn:feature_code":"PPL",
    "gn:name":"Paso Real",
    "gn:population":438,
    "gn:timezone":"America/Mexico_City",
    "iso:country":"MX",
    "wof:name":"Paso Real",
    "wof:placetype":"locality",
    "wof:population":438
},
  "geometry": {"coordinates":[-96.72944,18.73556],"type":"Point"}
}