{
  "type": "Feature",
  "properties": {
    "gn:admin1_code":"11",
    "gn:admin2_code":"20",
    "gn:asciiname":"La Tambora",
    "gn:country_code":"MX",
    "gn:dem":2080,
    "gn:feature_class":"P",
    "gn:feature_code":"PPL",
    "gn:name":"La Tambora",
    "gn:population":20,
    "gn:timezone":"America/Mexico_City",
    "iso:country":"MX",
    "wof:name":"La Tambora",
    "wof:placetype":"locality",
    "wof:population":20
},
  "geometry": {"coordinates":[-101.72889000000001,21.21333],"type":"Point"}
}