{
  "type": "Feature",
  "properties": {
    "gn:admin1_code":"16",
    "gn:admin2_code":"26.0",
    "gn:asciiname":"El Sipimo",
    "gn:country_code":"MX",
    "gn:dem":672,
    "gn:feature_class":"P",
    "gn:feature_code":"PPL",
    "gn:name":"El S\u00edpimo",
    "gn:population":121,
    "gn:timezone":"America/Mexico_City",
    "iso:country":"MX",
    "name:und_x_variant":[
        "El S\u00edpimo"
    ],
    "wof:name":"El Sipimo",
    "wof:placetype":"locality",
    "wof:population":121
},
  "geometry": {"coordinates":[-103.44806,18.78528],"type":"Point"}
}