{
  "type": "Feature",
  "properties": {
    "gn:admin1_code":"11",
    "gn:admin2_code":"33",
    "gn:asciiname":"Paso de la Virgen",
    "gn:country_code":"MX",
    "gn:dem":1355,
    "gn:feature_class":"P",
    "gn:feature_code":"PPL",
    "gn:name":"Paso de la Virgen",
    "gn:population":20,
    "gn:timezone":"America/Mexico_City",
    "iso:country":"MX",
    "wof:name":"Paso de la Virgen",
    "wof:placetype":"locality",
    "wof:population":20
},
  "geometry": {"coordinates":[-100.30722,21.55944],"type":"Point"}
}