{
  "type": "Feature",
  "properties": {
    "gn:admin1_code":"30",
    "gn:admin2_code":"15.0",
    "gn:asciiname":"Laguna de Majahual",
    "gn:country_code":"MX",
    "gn:dem":184,
    "gn:feature_class":"P",
    "gn:feature_code":"PPL",
    "gn:name":"Laguna de Majahual",
    "gn:population":0,
    "gn:timezone":"America/Mexico_City",
    "iso:country":"MX",
    "name:spa_x_preferred":[
        "Laguna de Majahual"
    ],
    "name:und_x_variant":[
        "Majahual",
        "Majagual",
        "Laguna del Majahual"
    ],
    "wof:name":"Laguna de Majahual",
    "wof:placetype":"locality"
},
  "geometry": {"coordinates":[-95.29885,18.65896],"type":"Point"}
}