{
  "type": "Feature",
  "properties": {
    "gn:admin1_code":"5",
    "gn:admin2_code":"4.0",
    "gn:asciiname":"Agua Escondida la Florida",
    "gn:country_code":"MX",
    "gn:dem":361,
    "gn:feature_class":"P",
    "gn:feature_code":"PPL",
    "gn:name":"Agua Escondida la Florida",
    "gn:population":147,
    "gn:timezone":"America/Mexico_City",
    "iso:country":"MX",
    "wof:name":"Agua Escondida la Florida",
    "wof:placetype":"locality",
    "wof:population":147
},
  "geometry": {"coordinates":[-91.56389,16.58861],"type":"Point"}
}