{
  "type": "Feature",
  "properties": {
    "gn:admin1_code":"2",
    "gn:admin2_code":"1.0",
    "gn:asciiname":"Nuevo Centro de Poblacion Ejidal el Pipila",
    "gn:country_code":"MX",
    "gn:dem":140,
    "gn:feature_class":"P",
    "gn:feature_code":"PPL",
    "gn:name":"Nuevo Centro de Poblaci\u00f3n Ejidal el P\u00edpila",
    "gn:population":76,
    "gn:timezone":"America/Tijuana",
    "iso:country":"MX",
    "name:und_x_variant":[
        "Nuevo Centro de Poblaci\u00f3n Ejidal el P\u00edpila"
    ],
    "wof:name":"Nuevo Centro de Poblacion Ejidal el Pipila",
    "wof:placetype":"locality",
    "wof:population":76
},
  "geometry": {"coordinates":[-116.49472,31.695],"type":"Point"}
}