{
  "type": "Feature",
  "properties": {
    "gn:admin1_code":"14",
    "gn:admin2_code":"84.0",
    "gn:asciiname":"La Estancita",
    "gn:country_code":"MX",
    "gn:dem":1144,
    "gn:feature_class":"P",
    "gn:feature_code":"PPL",
    "gn:name":"La Estancita",
    "gn:population":6,
    "gn:timezone":"America/Mexico_City",
    "iso:country":"MX",
    "wof:name":"La Estancita",
    "wof:placetype":"locality",
    "wof:population":6
},
  "geometry": {"coordinates":[-104.84083,20.40056],"type":"Point"}
}