{
  "type": "Feature",
  "properties": {
    "gn:admin1_code":"25.0",
    "gn:admin2_code":"2.0",
    "gn:asciiname":"El Guamuchil",
    "gn:country_code":"MX",
    "gn:dem":1,
    "gn:feature_class":"P",
    "gn:feature_code":"PPL",
    "gn:name":"El Guam\u00fachil",
    "gn:population":0,
    "gn:timezone":"America/Mazatlan",
    "iso:country":"MX",
    "name:spa_x_preferred":[
        "El Guam\u00fachil"
    ],
    "wof:name":"El Guamuchil",
    "wof:placetype":"locality"
},
  "geometry": {"coordinates":[-108.09143,24.82407000000001],"type":"Point"}
}