{
  "type": "Feature",
  "properties": {
    "iso:country":"MX",
    "name:spa_x_preferred":[
        "Fracc Guadalupe"
    ],
    "qs:gn_adm0_cc":"MX",
    "qs:gn_local":3997479,
    "qs:gn_nam_loc":"los mochis",
    "qs:gn_namadm1":"25",
    "qs:local_max":29,
    "qs:local_sum":73,
    "qs:localhoods":6,
    "qs:name":"Fracc Guadalupe",
    "qs:name_adm0":"M\u00e9xico",
    "qs:name_adm1":"Sinaloa",
    "qs:name_adm2":"Ahome",
    "qs:name_local":"Los Mochis",
    "qs:photo_max":1,
    "qs:photo_sum":1,
    "qs:placetype":"Suburb",
    "qs:quad_count":1,
    "qs:woe_adm0":23424900,
    "qs:woe_adm1":2346288,
    "qs:woe_adm2":12601527,
    "qs:woe_lau":0,
    "qs:woe_local":132141,
    "qs:woe_ver":"7.10.0",
    "wof:lang":[
        "spa"
    ],
    "wof:name":"Fracc Guadalupe",
    "wof:placetype":"neighbourhood"
},
  "geometry": {"coordinates":[-109.01458700000001,25.777634],"type":"Point"}
}