{
  "type": "Feature",
  "properties": {
    "gn:admin1_code":"24.0",
    "gn:asciiname":"El Orito",
    "gn:country_code":"MX",
    "gn:dem":2151,
    "gn:feature_class":"P",
    "gn:feature_code":"PPL",
    "gn:name":"El Orito",
    "gn:population":0,
    "gn:timezone":"America/Mexico_City",
    "iso:country":"MX",
    "name:spa_x_preferred":[
        "El Orito"
    ],
    "wof:name":"El Orito",
    "wof:placetype":"locality"
},
  "geometry": {"coordinates":[-101.23175000000001,23.13647000000001],"type":"Point"}
}