{
  "type": "Feature",
  "properties": {
    "gn:admin1_code":"6.0",
    "gn:admin2_code":"52.0",
    "gn:asciiname":"La Sauceda",
    "gn:country_code":"MX",
    "gn:dem":1243,
    "gn:feature_class":"P",
    "gn:feature_code":"PPL",
    "gn:name":"La Sauceda",
    "gn:population":0,
    "gn:timezone":"America/Ojinaga",
    "iso:country":"MX",
    "name:und_x_variant":[
        "Rancho El Sauceda",
        "La Sauceda"
    ],
    "wof:name":"La Sauceda",
    "wof:placetype":"locality"
},
  "geometry": {"coordinates":[-104.40588,29.04473],"type":"Point"}
}