{
  "type": "Feature",
  "properties": {
    "gn:admin1_code":"17",
    "gn:admin2_code":"21.0",
    "gn:asciiname":"Colonia Francisco Sarabia",
    "gn:country_code":"MX",
    "gn:dem":987,
    "gn:feature_class":"P",
    "gn:feature_code":"PPL",
    "gn:name":"Colonia Francisco Sarabia",
    "gn:population":73,
    "gn:timezone":"America/Mexico_City",
    "iso:country":"MX",
    "wof:name":"Colonia Francisco Sarabia",
    "wof:placetype":"locality",
    "wof:population":73
},
  "geometry": {"coordinates":[-99.39528,18.72083],"type":"Point"}
}