{
  "type": "Feature",
  "properties": {
    "gn:admin1_code":"10",
    "gn:asciiname":"Paraje Los Pastores",
    "gn:country_code":"MX",
    "gn:dem":1770,
    "gn:feature_class":"P",
    "gn:feature_code":"PPL",
    "gn:name":"Paraje Los Pastores",
    "gn:population":0,
    "gn:timezone":"America/Chihuahua",
    "iso:country":"MX",
    "name:spa_x_preferred":[
        "Paraje Los Pastores"
    ],
    "wof:name":"Paraje Los Pastores",
    "wof:placetype":"locality"
},
  "geometry": {"coordinates":[-106.23721,26.60103],"type":"Point"}
}