{
  "type": "Feature",
  "properties": {
    "gn:admin1_code":"28.0",
    "gn:admin2_code":"13.0",
    "gn:asciiname":"El Chorro Tres",
    "gn:country_code":"MX",
    "gn:dem":179,
    "gn:feature_class":"P",
    "gn:feature_code":"PPL",
    "gn:name":"El Chorro Tres",
    "gn:population":3,
    "gn:timezone":"America/Monterrey",
    "iso:country":"MX",
    "name:spa_x_preferred":[
        "El Chorro Tres"
    ],
    "wof:name":"El Chorro Tres",
    "wof:placetype":"locality",
    "wof:population":3
},
  "geometry": {"coordinates":[-98.84444000000001,23.70167],"type":"Point"}
}