{
  "type": "Feature",
  "properties": {
    "gn:admin1_code":"10",
    "gn:admin2_code":"14",
    "gn:asciiname":"La China",
    "gn:country_code":"MX",
    "gn:dem":2756,
    "gn:feature_class":"P",
    "gn:feature_code":"PPL",
    "gn:name":"La China",
    "gn:population":21,
    "gn:timezone":"America/Monterrey",
    "iso:country":"MX",
    "wof:name":"La China",
    "wof:placetype":"locality",
    "wof:population":21
},
  "geometry": {"coordinates":[-104.69943000000001,23.34058],"type":"Point"}
}