{
  "type": "Feature",
  "properties": {
    "gn:admin1_code":"21.0",
    "gn:admin2_code":"22.0",
    "gn:asciiname":"El Arenal",
    "gn:country_code":"MX",
    "gn:dem":1841,
    "gn:feature_class":"P",
    "gn:feature_code":"PPL",
    "gn:name":"El Arenal",
    "gn:population":0,
    "gn:timezone":"America/Mexico_City",
    "iso:country":"MX",
    "name:spa_x_preferred":[
        "El Arenal"
    ],
    "wof:name":"El Arenal",
    "wof:placetype":"locality"
},
  "geometry": {"coordinates":[-98.52816,18.85605],"type":"Point"}
}