{
  "type": "Feature",
  "properties": {
    "gn:admin1_code":"20",
    "gn:admin2_code":"184.0",
    "gn:asciiname":"Santa Teresa (Boca de Coapa)",
    "gn:country_code":"MX",
    "gn:dem":23,
    "gn:feature_class":"P",
    "gn:feature_code":"PPL",
    "gn:name":"Santa Teresa (Boca de Coapa)",
    "gn:population":7,
    "gn:timezone":"America/Mexico_City",
    "iso:country":"MX",
    "wof:name":"Santa Teresa (Boca de Coapa)",
    "wof:placetype":"locality",
    "wof:population":7
},
  "geometry": {"coordinates":[-96.01278000000001,18.02361],"type":"Point"}
}