{
  "type": "Feature",
  "properties": {
    "gn:admin1_code":"5",
    "gn:admin2_code":"99.0",
    "gn:asciiname":"Alemania",
    "gn:country_code":"MX",
    "gn:dem":1541,
    "gn:feature_class":"P",
    "gn:feature_code":"PPL",
    "gn:name":"Alemania",
    "gn:population":7,
    "gn:timezone":"America/Mexico_City",
    "iso:country":"MX",
    "wof:name":"Alemania",
    "wof:placetype":"locality",
    "wof:population":7
},
  "geometry": {"coordinates":[-91.82361,16.11889],"type":"Point"}
}