{
  "type": "Feature",
  "properties": {
    "gn:admin1_code":"26.0",
    "gn:admin2_code":"30.0",
    "gn:asciiname":"Costa Rica",
    "gn:country_code":"MX",
    "gn:dem":50,
    "gn:feature_class":"P",
    "gn:feature_code":"PPL",
    "gn:name":"Costa Rica",
    "gn:population":0,
    "gn:timezone":"America/Hermosillo",
    "iso:country":"MX",
    "name:und_x_variant":[
        "Rancho La Costa",
        "San Francisco de Costa Rica",
        "Costa Rica"
    ],
    "wof:name":"Costa Rica",
    "wof:placetype":"locality"
},
  "geometry": {"coordinates":[-111.57210000000001,28.91922000000001],"type":"Point"}
}