{
  "type": "Feature",
  "properties": {
    "gn:admin1_code":"3.0",
    "gn:admin2_code":"3.0",
    "gn:asciiname":"El Bainoro",
    "gn:country_code":"MX",
    "gn:dem":611,
    "gn:feature_class":"P",
    "gn:feature_code":"PPL",
    "gn:name":"El Bainoro",
    "gn:population":0,
    "gn:timezone":"America/Mazatlan",
    "iso:country":"MX",
    "name:spa_x_preferred":[
        "El Bainoro"
    ],
    "wof:name":"El Bainoro",
    "wof:placetype":"locality"
},
  "geometry": {"coordinates":[-109.91248,23.7248],"type":"Point"}
}