{
  "type": "Feature",
  "properties": {
    "gn:admin1_code":"10",
    "gn:admin2_code":"3.0",
    "gn:asciiname":"El Indio",
    "gn:country_code":"MX",
    "gn:dem":2189,
    "gn:feature_class":"P",
    "gn:feature_code":"PPL",
    "gn:name":"El Indio",
    "gn:population":0,
    "gn:timezone":"America/Monterrey",
    "iso:country":"MX",
    "name:ceb_x_preferred":[
        "El Indio"
    ],
    "name:ita_x_preferred":[
        "El Indio"
    ],
    "name:spa_x_preferred":[
        "El Indio"
    ],
    "name:srp_x_preferred":[
        "\u0415\u043b \u0418\u043d\u0434\u0438\u043e"
    ],
    "name:swe_x_preferred":[
        "El Indio"
    ],
    "wof:name":"El Indio",
    "wof:placetype":"locality"
},
  "geometry": {"coordinates":[-104.94159000000001,25.14968],"type":"Point"}
}