{
  "type": "Feature",
  "properties": {
    "gn:admin1_code":"21",
    "gn:admin2_code":"172.0",
    "gn:asciiname":"Tilapa",
    "gn:country_code":"MX",
    "gn:dem":2049,
    "gn:feature_class":"P",
    "gn:feature_code":"PPL",
    "gn:name":"Tilapa",
    "gn:population":83,
    "gn:timezone":"America/Mexico_City",
    "iso:country":"MX",
    "name:ceb_x_preferred":[
        "Tilapa"
    ],
    "name:epo_x_preferred":[
        "Tilapa"
    ],
    "name:eus_x_preferred":[
        "Tilapa"
    ],
    "name:srp_x_preferred":[
        "\u041e\u043f\u0448\u0442\u0438\u043d\u0430 \u0422\u0438\u043b\u0430\u043f\u0430"
    ],
    "name:swe_x_preferred":[
        "Tilapa"
    ],
    "name:vie_x_preferred":[
        "Tilapa"
    ],
    "wof:name":"Tilapa",
    "wof:placetype":"locality",
    "wof:population":83
},
  "geometry": {"coordinates":[-97.82253,19.76523],"type":"Point"}
}