{
  "type": "Feature",
  "properties": {
    "gn:admin1_code":"21",
    "gn:admin2_code":"172.0",
    "gn:asciiname":"Tilapa",
    "gn:country_code":"MX",
    "gn:dem":2049,
    "gn:feature_class":"P",
    "gn:feature_code":"PPL",
    "gn:name":"Tilapa",
    "gn:population":83,
    "gn:timezone":"America/Mexico_City",
    "iso:country":"MX",
    "wof:name":"Tilapa",
    "wof:placetype":"locality",
    "wof:population":83
},
  "geometry": {"coordinates":[-97.82253,19.76523],"type":"Point"}
}