{
  "type": "Feature",
  "properties": {
    "gn:admin1_code":"5",
    "gn:admin2_code":"108.0",
    "gn:asciiname":"San Jose los Negros",
    "gn:cc2":"MX",
    "gn:country_code":"MX",
    "gn:dem":670,
    "gn:feature_class":"P",
    "gn:feature_code":"PPL",
    "gn:name":"San Jos\u00e9 los Negros",
    "gn:population":13,
    "gn:timezone":"America/Mexico_City",
    "iso:country":"MX",
    "name:und_x_variant":[
        "San Jos\u00e9",
        "San Jos\u00e9 de los Negros"
    ],
    "wof:name":"San Jose los Negros",
    "wof:placetype":"locality",
    "wof:population":13
},
  "geometry": {"coordinates":[-93.49028,16.39694],"type":"Point"}
}