{
  "type": "Feature",
  "properties": {
    "gn:admin1_code":"30",
    "gn:admin2_code":"202",
    "gn:asciiname":"Comescalco",
    "gn:country_code":"MX",
    "gn:dem":1100,
    "gn:feature_class":"P",
    "gn:feature_code":"PPL",
    "gn:name":"Comescalco",
    "gn:population":22,
    "gn:timezone":"America/Mexico_City",
    "iso:country":"MX",
    "wof:name":"Comescalco",
    "wof:placetype":"locality",
    "wof:population":22
},
  "geometry": {"coordinates":[-98.37194,20.72528],"type":"Point"}
}