{
  "type": "Feature",
  "properties": {
    "gn:admin1_code":"25.0",
    "gn:admin2_code":"2.0",
    "gn:asciiname":"Punta el Esteron",
    "gn:country_code":"MX",
    "gn:dem":5,
    "gn:feature_class":"P",
    "gn:feature_code":"PPL",
    "gn:name":"Punta el Ester\u00f3n",
    "gn:population":0,
    "gn:timezone":"America/Mazatlan",
    "iso:country":"MX",
    "name:spa_x_preferred":[
        "Punta el Ester\u00f3n"
    ],
    "wof:name":"Punta el Esteron",
    "wof:placetype":"locality"
},
  "geometry": {"coordinates":[-108.05504999999999,24.83836],"type":"Point"}
}