{
  "type": "Feature",
  "properties": {
    "gn:admin1_code":"13",
    "gn:admin2_code":"75.0",
    "gn:asciiname":"Huaquiluca",
    "gn:country_code":"MX",
    "gn:dem":2324,
    "gn:feature_class":"P",
    "gn:feature_code":"PPL",
    "gn:name":"Huaquiluca",
    "gn:population":0,
    "gn:timezone":"America/Mexico_City",
    "iso:country":"MX",
    "name:spa_x_preferred":[
        "Huaquiluca"
    ],
    "wof:name":"Huaquiluca",
    "wof:placetype":"locality"
},
  "geometry": {"coordinates":[-98.86621,19.90359],"type":"Point"}
}