{
  "type": "Feature",
  "properties": {
    "gn:admin1_code":"17",
    "gn:admin2_code":"4.0",
    "gn:asciiname":"Colonia las Arboledas",
    "gn:country_code":"MX",
    "gn:dem":1308,
    "gn:feature_class":"P",
    "gn:feature_code":"PPL",
    "gn:name":"Colonia las Arboledas",
    "gn:population":1409,
    "gn:timezone":"America/Mexico_City",
    "iso:country":"MX",
    "wof:name":"Colonia las Arboledas",
    "wof:placetype":"locality",
    "wof:population":1409
},
  "geometry": {"coordinates":[-98.93971999999999,18.78528],"type":"Point"}
}