{
  "type": "Feature",
  "properties": {
    "gn:admin1_code":"22",
    "gn:admin2_code":"4.0",
    "gn:asciiname":"La Lagunita",
    "gn:country_code":"MX",
    "gn:dem":2900,
    "gn:feature_class":"P",
    "gn:feature_code":"PPL",
    "gn:name":"La Lagunita",
    "gn:population":67,
    "gn:timezone":"America/Mexico_City",
    "iso:country":"MX",
    "wof:name":"La Lagunita",
    "wof:placetype":"locality",
    "wof:population":67
},
  "geometry": {"coordinates":[-99.58917,20.82889],"type":"Point"}
}