{
  "type": "Feature",
  "properties": {
    "gn:admin1_code":"25",
    "gn:admin2_code":"10.0",
    "gn:asciiname":"Los Manzanares",
    "gn:country_code":"MX",
    "gn:dem":24,
    "gn:feature_class":"P",
    "gn:feature_code":"PPL",
    "gn:name":"Los Manzanares",
    "gn:population":0,
    "gn:timezone":"America/Mazatlan",
    "iso:country":"MX",
    "name:spa_x_preferred":[
        "Los Manzanares"
    ],
    "wof:name":"Los Manzanares",
    "wof:placetype":"locality"
},
  "geometry": {"coordinates":[-108.96523999999999,26.11799],"type":"Point"}
}