{
  "type": "Feature",
  "properties": {
    "gn:admin1_code":"10",
    "gn:admin2_code":"13.0",
    "gn:asciiname":"La Jarita",
    "gn:country_code":"MX",
    "gn:dem":1399,
    "gn:feature_class":"P",
    "gn:feature_code":"PPL",
    "gn:name":"La Jarita",
    "gn:population":0,
    "gn:timezone":"America/Monterrey",
    "iso:country":"MX",
    "name:spa_x_preferred":[
        "La Jarita"
    ],
    "wof:name":"La Jarita",
    "wof:placetype":"locality"
},
  "geometry": {"coordinates":[-103.98714,25.83884],"type":"Point"}
}