{
  "type": "Feature",
  "properties": {
    "gn:admin1_code":"2.0",
    "gn:admin2_code":"3.0",
    "gn:asciiname":"El Barrilito",
    "gn:country_code":"MX",
    "gn:dem":483,
    "gn:feature_class":"P",
    "gn:feature_code":"PPL",
    "gn:name":"El Barrilito",
    "gn:population":0,
    "gn:timezone":"America/Tijuana",
    "iso:country":"MX",
    "name:spa_x_preferred":[
        "El Barrilito"
    ],
    "wof:name":"El Barrilito",
    "wof:placetype":"locality"
},
  "geometry": {"coordinates":[-116.66955,32.54885],"type":"Point"}
}