{
  "type": "Feature",
  "properties": {
    "gn:admin1_code":"22",
    "gn:admin2_code":"8",
    "gn:asciiname":"Rancho la Mora",
    "gn:country_code":"MX",
    "gn:dem":2154,
    "gn:feature_class":"P",
    "gn:feature_code":"PPL",
    "gn:name":"Rancho la Mora",
    "gn:population":29,
    "gn:timezone":"America/Mexico_City",
    "iso:country":"MX",
    "wof:name":"Rancho la Mora",
    "wof:placetype":"locality",
    "wof:population":29
},
  "geometry": {"coordinates":[-100.30806,20.42417],"type":"Point"}
}