{
  "type": "Feature",
  "properties": {
    "gn:admin1_code":"12",
    "gn:admin2_code":"38",
    "gn:asciiname":"Puerto de Casitas",
    "gn:country_code":"MX",
    "gn:dem":593,
    "gn:feature_class":"P",
    "gn:feature_code":"PPL",
    "gn:name":"Puerto de Casitas",
    "gn:population":12,
    "gn:timezone":"America/Mexico_City",
    "iso:country":"MX",
    "wof:name":"Puerto de Casitas",
    "wof:placetype":"locality",
    "wof:population":12
},
  "geometry": {"coordinates":[-101.39058,17.77665],"type":"Point"}
}