{
  "type": "Feature",
  "properties": {
    "gn:admin1_code":"26.0",
    "gn:admin2_code":"11.0",
    "gn:asciiname":"Los Jucaros",
    "gn:country_code":"MX",
    "gn:dem":1413,
    "gn:feature_class":"P",
    "gn:feature_code":"PPL",
    "gn:name":"Los J\u00facaros",
    "gn:population":0,
    "gn:timezone":"America/Hermosillo",
    "iso:country":"MX",
    "name:spa_x_preferred":[
        "Los J\u00facaros"
    ],
    "wof:name":"Los Jucaros",
    "wof:placetype":"locality"
},
  "geometry": {"coordinates":[-109.79861,30.52444],"type":"Point"}
}