{
  "type": "Feature",
  "properties": {
    "gn:admin1_code":"11",
    "gn:admin2_code":"33",
    "gn:asciiname":"Adjuntas de las Mesas",
    "gn:country_code":"MX",
    "gn:dem":2303,
    "gn:feature_class":"P",
    "gn:feature_code":"PPL",
    "gn:name":"Adjuntas de las Mesas",
    "gn:population":18,
    "gn:timezone":"America/Mexico_City",
    "iso:country":"MX",
    "wof:name":"Adjuntas de las Mesas",
    "wof:placetype":"locality",
    "wof:population":18
},
  "geometry": {"coordinates":[-100.44722,21.47722000000001],"type":"Point"}
}