{
  "type": "Feature",
  "properties": {
    "gn:admin1_code":"5.0",
    "gn:admin2_code":"76.0",
    "gn:asciiname":"Colonia Catarina",
    "gn:country_code":"MX",
    "gn:dem":577,
    "gn:feature_class":"P",
    "gn:feature_code":"PPL",
    "gn:name":"Colonia Catarina",
    "gn:population":0,
    "gn:timezone":"America/Mexico_City",
    "iso:country":"MX",
    "name:spa_x_preferred":[
        "Colonia Catarina"
    ],
    "wof:name":"Colonia Catarina",
    "wof:placetype":"locality"
},
  "geometry": {"coordinates":[-92.55694,17.26078],"type":"Point"}
}