{
  "type": "Feature",
  "properties": {
    "gn:admin1_code":"29",
    "gn:admin2_code":"9.0",
    "gn:asciiname":"San Miguel Buenavista",
    "gn:country_code":"MX",
    "gn:dem":2525,
    "gn:feature_class":"P",
    "gn:feature_code":"PPL",
    "gn:name":"San Miguel Buenavista",
    "gn:population":710,
    "gn:timezone":"America/Mexico_City",
    "iso:country":"MX",
    "wof:name":"San Miguel Buenavista",
    "wof:placetype":"locality",
    "wof:population":710
},
  "geometry": {"coordinates":[-98.07444,19.35444],"type":"Point"}
}