{
  "type": "Feature",
  "properties": {
    "gn:admin1_code":"6",
    "gn:admin2_code":"9",
    "gn:asciiname":"La Mesa",
    "gn:country_code":"MX",
    "gn:dem":2429,
    "gn:feature_class":"P",
    "gn:feature_code":"PPL",
    "gn:name":"La Mesa",
    "gn:population":14,
    "gn:timezone":"America/Chihuahua",
    "iso:country":"MX",
    "wof:name":"La Mesa",
    "wof:placetype":"locality",
    "wof:population":14
},
  "geometry": {"coordinates":[-107.60493,27.95519],"type":"Point"}
}