{
  "type": "Feature",
  "properties": {
    "gn:admin1_code":"20",
    "gn:admin2_code":"413.0",
    "gn:asciiname":"Barrio de la Soledad",
    "gn:country_code":"MX",
    "gn:dem":222,
    "gn:feature_class":"P",
    "gn:feature_code":"PPL",
    "gn:name":"Barrio de la Soledad",
    "gn:population":98,
    "gn:timezone":"America/Mexico_City",
    "iso:country":"MX",
    "wof:name":"Barrio de la Soledad",
    "wof:placetype":"locality",
    "wof:population":98
},
  "geometry": {"coordinates":[-96.32333,15.84],"type":"Point"}
}