{
  "type": "Feature",
  "properties": {
    "gn:admin1_code":"6",
    "gn:admin2_code":"63.0",
    "gn:asciiname":"Vinata",
    "gn:country_code":"MX",
    "gn:dem":1963,
    "gn:feature_class":"P",
    "gn:feature_code":"PPL",
    "gn:name":"Vinata",
    "gn:population":0,
    "gn:timezone":"America/Chihuahua",
    "iso:country":"MX",
    "wof:name":"Vinata",
    "wof:placetype":"locality"
},
  "geometry": {"coordinates":[-108.01667,28.76667],"type":"Point"}
}