{
  "type": "Feature",
  "properties": {
    "gn:admin1_code":"6",
    "gn:admin2_code":"63.0",
    "gn:asciiname":"Vinata",
    "gn:country_code":"MX",
    "gn:dem":1963,
    "gn:feature_class":"P",
    "gn:feature_code":"PPL",
    "gn:name":"Vinata",
    "gn:population":0,
    "gn:timezone":"America/Chihuahua",
    "iso:country":"MX",
    "name:deu_x_preferred":[
        "Vinata"
    ],
    "name:ita_x_preferred":[
        "Vinata"
    ],
    "name:jpn_x_preferred":[
        "\u30f4\u30a3\u30ca\u30bf\u30fc"
    ],
    "name:kan_x_preferred":[
        "\u0cb5\u0cbf\u0ca8\u0ca4\u0cc6"
    ],
    "name:mal_x_preferred":[
        "\u0d35\u0d3f\u0d28\u0d24"
    ],
    "name:mar_x_preferred":[
        "\u0935\u093f\u0928\u0924\u093e"
    ],
    "name:nno_x_preferred":[
        "Vinata"
    ],
    "name:pan_x_preferred":[
        "\u0a35\u0a3f\u0a28\u0a24\u0a3e"
    ],
    "name:tam_x_preferred":[
        "\u0bb5\u0bbf\u0ba9\u0ba4\u0bbe"
    ],
    "name:tel_x_preferred":[
        "\u0c35\u0c3f\u0c28\u0c24"
    ],
    "wof:name":"Vinata",
    "wof:placetype":"locality"
},
  "geometry": {"coordinates":[-108.01667,28.76667],"type":"Point"}
}