{
  "type": "Feature",
  "properties": {
    "gn:admin1_code":"5",
    "gn:admin2_code":"107.0",
    "gn:asciiname":"Argelia",
    "gn:country_code":"MX",
    "gn:dem":1419,
    "gn:feature_class":"P",
    "gn:feature_code":"PPL",
    "gn:name":"Argelia",
    "gn:population":7,
    "gn:timezone":"America/Mexico_City",
    "iso:country":"MX",
    "name:ceb_x_preferred":[
        "Argelia"
    ],
    "name:deu_x_preferred":[
        "Argelia"
    ],
    "name:fra_x_preferred":[
        "Argelia"
    ],
    "name:ita_x_preferred":[
        "Argelia"
    ],
    "name:nld_x_preferred":[
        "Argelia"
    ],
    "name:por_x_preferred":[
        "Arg\u00e9lia"
    ],
    "name:sco_x_preferred":[
        "Argelia"
    ],
    "name:spa_x_preferred":[
        "Argelia"
    ],
    "name:swe_x_preferred":[
        "Argelia"
    ],
    "name:vie_x_preferred":[
        "Argelia"
    ],
    "name:war_x_preferred":[
        "Argelia"
    ],
    "wof:name":"Argelia",
    "wof:placetype":"locality",
    "wof:population":7
},
  "geometry": {"coordinates":[-93.58222000000001,16.10639],"type":"Point"}
}