{
  "type": "Feature",
  "properties": {
    "gn:admin1_code":"20",
    "gn:admin2_code":"414.0",
    "gn:asciiname":"Tomiltepec",
    "gn:country_code":"MX",
    "gn:dem":490,
    "gn:feature_class":"P",
    "gn:feature_code":"PPL",
    "gn:name":"Tomiltepec",
    "gn:population":0,
    "gn:timezone":"America/Mexico_City",
    "iso:country":"MX",
    "wof:name":"Tomiltepec",
    "wof:placetype":"locality"
},
  "geometry": {"coordinates":[-97.86667,16.28333],"type":"Point"}
}