{
  "type": "Feature",
  "properties": {
    "gn:admin1_code":"12",
    "gn:admin2_code":"59.0",
    "gn:asciiname":"Tecuixiapan",
    "gn:country_code":"MX",
    "gn:dem":987,
    "gn:feature_class":"P",
    "gn:feature_code":"PPL",
    "gn:name":"Tecuixiapan",
    "gn:population":0,
    "gn:timezone":"America/Mexico_City",
    "iso:country":"MX",
    "wof:name":"Tecuixiapan",
    "wof:placetype":"locality"
},
  "geometry": {"coordinates":[-99.41667,18.01667],"type":"Point"}
}