{
  "type": "Feature",
  "properties": {
    "gn:admin1_code":"20",
    "gn:admin2_code":"385.0",
    "gn:asciiname":"Juquilita",
    "gn:country_code":"MX",
    "gn:dem":1630,
    "gn:feature_class":"P",
    "gn:feature_code":"PPL",
    "gn:name":"Juquilita",
    "gn:population":217,
    "gn:timezone":"America/Mexico_City",
    "iso:country":"MX",
    "wof:name":"Juquilita",
    "wof:placetype":"locality",
    "wof:population":217
},
  "geometry": {"coordinates":[-96.78417,17.04472],"type":"Point"}
}