{
  "type": "Feature",
  "properties": {
    "gn:admin1_code":"21",
    "gn:admin2_code":"175.0",
    "gn:asciiname":"San Baltazar Atlimeyaya",
    "gn:cc2":"MX",
    "gn:country_code":"MX",
    "gn:dem":2196,
    "gn:feature_class":"P",
    "gn:feature_code":"PPL",
    "gn:name":"San Baltazar Atlimeyaya",
    "gn:population":1104,
    "gn:timezone":"America/Mexico_City",
    "iso:country":"MX",
    "name:und_x_variant":[
        "Atlimayaya",
        "San Baltazar",
        "Atlimeyaya",
        "San Baltasar",
        "San Baltasar Atlimeyaya"
    ],
    "wof:name":"San Baltazar Atlimeyaya",
    "wof:placetype":"locality",
    "wof:population":1104
},
  "geometry": {"coordinates":[-98.48111,18.98694],"type":"Point"}
}