{
  "type": "Feature",
  "properties": {
    "gn:admin1_code":"6",
    "gn:admin2_code":"7",
    "gn:asciiname":"El Puerto (La Puerta)",
    "gn:country_code":"MX",
    "gn:dem":2703,
    "gn:feature_class":"P",
    "gn:feature_code":"PPL",
    "gn:name":"El Puerto (La Puerta)",
    "gn:population":24,
    "gn:timezone":"America/Chihuahua",
    "iso:country":"MX",
    "wof:name":"El Puerto (La Puerta)",
    "wof:placetype":"locality",
    "wof:population":24
},
  "geometry": {"coordinates":[-106.46952,26.46734],"type":"Point"}
}