{
  "type": "Feature",
  "properties": {
    "gn:admin1_code":"13",
    "gn:admin2_code":"14.0",
    "gn:asciiname":"Techichico",
    "gn:country_code":"MX",
    "gn:dem":787,
    "gn:feature_class":"P",
    "gn:feature_code":"PPL",
    "gn:name":"Techichico",
    "gn:population":408,
    "gn:timezone":"America/Mexico_City",
    "iso:country":"MX",
    "name:spa_x_preferred":[
        "Techichico"
    ],
    "wof:name":"Techichico",
    "wof:placetype":"locality",
    "wof:population":408
},
  "geometry": {"coordinates":[-98.51503,20.89733],"type":"Point"}
}