{
  "type": "Feature",
  "properties": {
    "gn:admin1_code":"12",
    "gn:admin2_code":"57",
    "gn:asciiname":"Lomas de San Isidro",
    "gn:country_code":"MX",
    "gn:dem":1801,
    "gn:feature_class":"P",
    "gn:feature_code":"PPL",
    "gn:name":"Lomas de San Isidro",
    "gn:population":15,
    "gn:timezone":"America/Mexico_City",
    "iso:country":"MX",
    "wof:name":"Lomas de San Isidro",
    "wof:placetype":"locality",
    "wof:population":15
},
  "geometry": {"coordinates":[-100.82558,17.66485],"type":"Point"}
}