{
  "type": "Feature",
  "properties": {
    "gn:admin1_code":"2",
    "gn:admin2_code":"2.0",
    "gn:asciiname":"Familia Solorio",
    "gn:country_code":"MX",
    "gn:dem":21,
    "gn:feature_class":"P",
    "gn:feature_code":"PPL",
    "gn:name":"Familia Solorio",
    "gn:population":5,
    "gn:timezone":"America/Tijuana",
    "iso:country":"MX",
    "wof:name":"Familia Solorio",
    "wof:placetype":"locality",
    "wof:population":5
},
  "geometry": {"coordinates":[-114.97638999999999,32.62694],"type":"Point"}
}