{
  "type": "Feature",
  "properties": {
    "gn:admin1_code":"11",
    "gn:admin2_code":"14.0",
    "gn:asciiname":"El Saucito",
    "gn:country_code":"MX",
    "gn:dem":1989,
    "gn:feature_class":"P",
    "gn:feature_code":"PPL",
    "gn:name":"El Saucito",
    "gn:population":8,
    "gn:timezone":"America/Mexico_City",
    "iso:country":"MX",
    "wof:name":"El Saucito",
    "wof:placetype":"locality",
    "wof:population":8
},
  "geometry": {"coordinates":[-100.83389,21.205],"type":"Point"}
}