{
  "type": "Feature",
  "properties": {
    "gn:admin1_code":"24",
    "gn:admin2_code":"51.0",
    "gn:asciiname":"Manga Quemada",
    "gn:country_code":"MX",
    "gn:dem":1572,
    "gn:feature_class":"P",
    "gn:feature_code":"PPL",
    "gn:name":"Manga Quemada",
    "gn:population":0,
    "gn:timezone":"America/Mexico_City",
    "iso:country":"MX",
    "wof:name":"Manga Quemada",
    "wof:placetype":"locality"
},
  "geometry": {"coordinates":[-100.66667,22.91667],"type":"Point"}
}