{
  "type": "Feature",
  "properties": {
    "gn:admin1_code":"30",
    "gn:admin2_code":"61.0",
    "gn:asciiname":"Arroyo Grande",
    "gn:country_code":"MX",
    "gn:dem":65,
    "gn:feature_class":"P",
    "gn:feature_code":"PPL",
    "gn:name":"Arroyo Grande",
    "gn:population":326,
    "gn:timezone":"America/Mexico_City",
    "iso:country":"MX",
    "wof:name":"Arroyo Grande",
    "wof:placetype":"locality",
    "wof:population":326
},
  "geometry": {"coordinates":[-93.78278,17.64583],"type":"Point"}
}