{
  "type": "Feature",
  "properties": {
    "gn:admin1_code":"26",
    "gn:asciiname":"Los Parajes",
    "gn:country_code":"MX",
    "gn:dem":125,
    "gn:feature_class":"P",
    "gn:feature_code":"PPL",
    "gn:name":"Los Parajes",
    "gn:population":0,
    "gn:timezone":"America/Mazatlan",
    "iso:country":"MX",
    "name:spa_x_preferred":[
        "Los Parajes"
    ],
    "wof:name":"Los Parajes",
    "wof:placetype":"locality"
},
  "geometry": {"coordinates":[-108.89879000000001,26.39749],"type":"Point"}
}