{
  "type": "Feature",
  "properties": {
    "gn:admin1_code":"5",
    "gn:admin2_code":"77.0",
    "gn:asciiname":"Recuerdo Ixtelja",
    "gn:country_code":"MX",
    "gn:dem":83,
    "gn:feature_class":"P",
    "gn:feature_code":"PPL",
    "gn:name":"Recuerdo Ixtelja",
    "gn:population":112,
    "gn:timezone":"America/Mexico_City",
    "iso:country":"MX",
    "wof:name":"Recuerdo Ixtelja",
    "wof:placetype":"locality",
    "wof:population":112
},
  "geometry": {"coordinates":[-92.18194,17.34167],"type":"Point"}
}