{
  "type": "Feature",
  "properties": {
    "gn:admin1_code":"8",
    "gn:admin2_code":"3.0",
    "gn:asciiname":"La Mameyera",
    "gn:country_code":"MX",
    "gn:dem":965,
    "gn:feature_class":"P",
    "gn:feature_code":"PPL",
    "gn:name":"La Mameyera",
    "gn:population":61,
    "gn:timezone":"America/Mexico_City",
    "iso:country":"MX",
    "wof:name":"La Mameyera",
    "wof:placetype":"locality",
    "wof:population":61
},
  "geometry": {"coordinates":[-103.71278,19.36139],"type":"Point"}
}