{
  "type": "Feature",
  "properties": {
    "gn:admin1_code":"11.0",
    "gn:admin2_code":"1.0",
    "gn:asciiname":"Coyoacan",
    "gn:country_code":"MX",
    "gn:dem":1700,
    "gn:feature_class":"P",
    "gn:feature_code":"PPL",
    "gn:name":"Coyoac\u00e1n",
    "gn:population":0,
    "gn:timezone":"America/Mexico_City",
    "iso:country":"MX",
    "name:spa_x_preferred":[
        "Coyoac\u00e1n"
    ],
    "name:spa_x_variant":[
        "El Alem\u00e1n"
    ],
    "wof:name":"Coyoacan",
    "wof:placetype":"locality"
},
  "geometry": {"coordinates":[-101.59021,20.39136],"type":"Point"}
}