{
  "type": "Feature",
  "properties": {
    "gn:admin1_code":"32",
    "gn:admin2_code":"10",
    "gn:asciiname":"Las Margaritas Uno (Hugo Valle)",
    "gn:country_code":"MX",
    "gn:dem":2067,
    "gn:feature_class":"P",
    "gn:feature_code":"PPL",
    "gn:name":"Las Margaritas Uno (Hugo Valle)",
    "gn:population":11,
    "gn:timezone":"America/Mexico_City",
    "iso:country":"MX",
    "wof:name":"Las Margaritas Uno (Hugo Valle)",
    "wof:placetype":"locality",
    "wof:population":11
},
  "geometry": {"coordinates":[-102.95667,23.3425],"type":"Point"}
}