{
  "type": "Feature",
  "properties": {
    "gn:admin1_code":"6",
    "gn:admin2_code":"29.0",
    "gn:asciiname":"Cienega de Silva",
    "gn:country_code":"MX",
    "gn:dem":1328,
    "gn:feature_class":"P",
    "gn:feature_code":"PPL",
    "gn:name":"Ci\u00e9nega de Silva",
    "gn:population":269,
    "gn:timezone":"America/Chihuahua",
    "iso:country":"MX",
    "name:und_x_variant":[
        "Ci\u00e9nega de Silva"
    ],
    "wof:name":"Cienega de Silva",
    "wof:placetype":"locality",
    "wof:population":269
},
  "geometry": {"coordinates":[-107.15361,25.85861],"type":"Point"}
}