{
  "type": "Feature",
  "properties": {
    "gn:admin1_code":"26",
    "gn:admin2_code":"2.0",
    "gn:asciiname":"El Trece",
    "gn:country_code":"MX",
    "gn:dem":1206,
    "gn:feature_class":"P",
    "gn:feature_code":"PPL",
    "gn:name":"El Trece",
    "gn:population":5,
    "gn:timezone":"America/Hermosillo",
    "iso:country":"MX",
    "wof:name":"El Trece",
    "wof:placetype":"locality",
    "wof:population":5
},
  "geometry": {"coordinates":[-109.58222000000001,31.21222],"type":"Point"}
}