{
  "type": "Feature",
  "properties": {
    "gn:admin1_code":"7",
    "gn:admin2_code":"11.0",
    "gn:asciiname":"El Saucillo",
    "gn:country_code":"MX",
    "gn:dem":1250,
    "gn:feature_class":"P",
    "gn:feature_code":"PPL",
    "gn:name":"El Saucillo",
    "gn:population":2,
    "gn:timezone":"America/Monterrey",
    "iso:country":"MX",
    "name:spa_x_preferred":[
        "El Saucillo"
    ],
    "wof:name":"El Saucillo",
    "wof:placetype":"locality",
    "wof:population":2
},
  "geometry": {"coordinates":[-101.36833,25.50782],"type":"Point"}
}