{
  "type": "Feature",
  "properties": {
    "gn:admin1_code":"18",
    "gn:admin2_code":"15.0",
    "gn:asciiname":"Valle Zaragoza",
    "gn:country_code":"MX",
    "gn:dem":18,
    "gn:feature_class":"P",
    "gn:feature_code":"PPL",
    "gn:name":"Valle Zaragoza",
    "gn:population":0,
    "gn:timezone":"America/Mazatlan",
    "iso:country":"MX",
    "name:spa_x_preferred":[
        "Valle Zaragoza"
    ],
    "wof:name":"Valle Zaragoza",
    "wof:placetype":"locality"
},
  "geometry": {"coordinates":[-105.1639,21.7941],"type":"Point"}
}