{
  "type": "Feature",
  "properties": {
    "gn:admin1_code":"30",
    "gn:admin2_code":"202",
    "gn:asciiname":"La Cuchilla",
    "gn:country_code":"MX",
    "gn:dem":906,
    "gn:feature_class":"P",
    "gn:feature_code":"PPL",
    "gn:name":"La Cuchilla",
    "gn:population":14,
    "gn:timezone":"America/Mexico_City",
    "iso:country":"MX",
    "wof:name":"La Cuchilla",
    "wof:placetype":"locality",
    "wof:population":14
},
  "geometry": {"coordinates":[-98.28917,20.68972],"type":"Point"}
}