{
  "type": "Feature",
  "properties": {
    "gn:admin1_code":"26",
    "gn:admin2_code":"50.0",
    "gn:asciiname":"San Ricardo (Buenos Aires)",
    "gn:country_code":"MX",
    "gn:dem":604,
    "gn:feature_class":"P",
    "gn:feature_code":"PPL",
    "gn:name":"San Ricardo (Buenos Aires)",
    "gn:population":7,
    "gn:timezone":"America/Hermosillo",
    "iso:country":"MX",
    "wof:name":"San Ricardo (Buenos Aires)",
    "wof:placetype":"locality",
    "wof:population":7
},
  "geometry": {"coordinates":[-110.58389,29.84528],"type":"Point"}
}