{
  "type": "Feature",
  "properties": {
    "gn:admin1_code":"6",
    "gn:asciiname":"Saucito",
    "gn:country_code":"MX",
    "gn:dem":1767,
    "gn:feature_class":"P",
    "gn:feature_code":"PPL",
    "gn:name":"Saucito",
    "gn:population":0,
    "gn:timezone":"America/Monterrey",
    "iso:country":"MX",
    "name:spa_x_preferred":[
        "Saucito"
    ],
    "wof:name":"Saucito",
    "wof:placetype":"locality"
},
  "geometry": {"coordinates":[-105.38467,26.46889],"type":"Point"}
}