{
  "type": "Feature",
  "properties": {
    "gn:admin1_code":"11",
    "gn:admin2_code":"35.0",
    "gn:asciiname":"Tejada",
    "gn:country_code":"MX",
    "gn:dem":1731,
    "gn:feature_class":"P",
    "gn:feature_code":"PPL",
    "gn:name":"Tejada",
    "gn:population":173,
    "gn:timezone":"America/Mexico_City",
    "iso:country":"MX",
    "name:ceb_x_preferred":[
        "Tejada"
    ],
    "name:deu_x_preferred":[
        "Tejada"
    ],
    "name:eus_x_preferred":[
        "Tejada"
    ],
    "name:fra_x_preferred":[
        "Tejada"
    ],
    "name:heb_x_preferred":[
        "\u05d8\u05d7\u05d3\u05d4"
    ],
    "name:rus_x_preferred":[
        "\u0422\u0435\u0445\u0430\u0434\u0430"
    ],
    "name:spa_x_preferred":[
        "Tejada"
    ],
    "name:swe_x_preferred":[
        "Tejada"
    ],
    "wof:name":"Tejada",
    "wof:placetype":"locality",
    "wof:population":173
},
  "geometry": {"coordinates":[-101.03610999999999,20.58528],"type":"Point"}
}