{
  "type": "Feature",
  "properties": {
    "gn:admin1_code":"16.0",
    "gn:admin2_code":"56.0",
    "gn:asciiname":"La Mojonera",
    "gn:country_code":"MX",
    "gn:dem":2635,
    "gn:feature_class":"P",
    "gn:feature_code":"PPL",
    "gn:name":"La Mojonera",
    "gn:population":0,
    "gn:timezone":"America/Mexico_City",
    "iso:country":"MX",
    "name:spa_x_preferred":[
        "La Mojonera"
    ],
    "wof:name":"La Mojonera",
    "wof:placetype":"locality"
},
  "geometry": {"coordinates":[-101.83343000000001,19.70366],"type":"Point"}
}