{
  "type": "Feature",
  "properties": {
    "gn:admin1_code":"24",
    "gn:admin2_code":"14.0",
    "gn:asciiname":"Amplicacion Calmecayo",
    "gn:country_code":"MX",
    "gn:dem":148,
    "gn:feature_class":"P",
    "gn:feature_code":"PPL",
    "gn:name":"Amplicaci\u00f3n Calmecayo",
    "gn:population":0,
    "gn:timezone":"America/Mexico_City",
    "iso:country":"MX",
    "name:spa_x_preferred":[
        "Amplicaci\u00f3n Calmecayo"
    ],
    "wof:name":"Amplicacion Calmecayo",
    "wof:placetype":"locality"
},
  "geometry": {"coordinates":[-98.87615,21.52682],"type":"Point"}
}