{
  "type": "Feature",
  "properties": {
    "gn:admin1_code":"30",
    "gn:admin2_code":"108.0",
    "gn:asciiname":"Los Cabritos",
    "gn:country_code":"MX",
    "gn:dem":14,
    "gn:feature_class":"P",
    "gn:feature_code":"PPL",
    "gn:name":"Los Cabritos",
    "gn:population":0,
    "gn:timezone":"America/Mexico_City",
    "iso:country":"MX",
    "name:und_x_variant":[
        "Cabritos",
        "Los Cabritos"
    ],
    "wof:name":"Los Cabritos",
    "wof:placetype":"locality"
},
  "geometry": {"coordinates":[-94.26081000000001,17.83552000000001],"type":"Point"}
}