{
  "type": "Feature",
  "properties": {
    "gn:admin1_code":"5",
    "gn:admin2_code":"51.0",
    "gn:asciiname":"El Castano",
    "gn:country_code":"MX",
    "gn:dem":15,
    "gn:feature_class":"P",
    "gn:feature_code":"PPL",
    "gn:name":"El Casta\u00f1o",
    "gn:population":75,
    "gn:timezone":"America/Mexico_City",
    "iso:country":"MX",
    "name:und_x_variant":[
        "El Casta\u00f1o"
    ],
    "wof:name":"El Castano",
    "wof:placetype":"locality",
    "wof:population":75
},
  "geometry": {"coordinates":[-92.96666999999999,15.29028],"type":"Point"}
}