{
  "type": "Feature",
  "properties": {
    "gn:admin1_code":"20",
    "gn:admin2_code":"2.0",
    "gn:asciiname":"El Nacimiento",
    "gn:country_code":"MX",
    "gn:dem":139,
    "gn:feature_class":"P",
    "gn:feature_code":"PPL",
    "gn:name":"El Nacimiento",
    "gn:population":53,
    "gn:timezone":"America/Mexico_City",
    "iso:country":"MX",
    "wof:name":"El Nacimiento",
    "wof:placetype":"locality",
    "wof:population":53
},
  "geometry": {"coordinates":[-96.62361,18.56194],"type":"Point"}
}