{
  "type": "Feature",
  "properties": {
    "gn:admin1_code":"21",
    "gn:admin2_code":"83",
    "gn:asciiname":"Corral de Piedra",
    "gn:country_code":"MX",
    "gn:dem":2561,
    "gn:feature_class":"P",
    "gn:feature_code":"PPL",
    "gn:name":"Corral de Piedra",
    "gn:population":40,
    "gn:timezone":"America/Mexico_City",
    "iso:country":"MX",
    "wof:name":"Corral de Piedra",
    "wof:placetype":"locality",
    "wof:population":40
},
  "geometry": {"coordinates":[-97.92579000000001,19.66759],"type":"Point"}
}