{
  "type": "Feature",
  "properties": {
    "gn:admin1_code":"15",
    "gn:admin2_code":"123",
    "gn:asciiname":"Mesa de los Espinos (Mesa de las Escobas)",
    "gn:country_code":"MX",
    "gn:dem":1281,
    "gn:feature_class":"P",
    "gn:feature_code":"PPL",
    "gn:name":"Mesa de los Espinos (Mesa de las Escobas)",
    "gn:population":36,
    "gn:timezone":"America/Mexico_City",
    "iso:country":"MX",
    "wof:name":"Mesa de los Espinos (Mesa de las Escobas)",
    "wof:placetype":"locality",
    "wof:population":36
},
  "geometry": {"coordinates":[-100.39060000000001,18.94655],"type":"Point"}
}