{
  "type": "Feature",
  "properties": {
    "gn:admin1_code":"19.0",
    "gn:admin2_code":"37.0",
    "gn:asciiname":"El Sauz",
    "gn:country_code":"MX",
    "gn:dem":583,
    "gn:feature_class":"P",
    "gn:feature_code":"PPL",
    "gn:name":"El Sauz",
    "gn:population":1,
    "gn:timezone":"America/Monterrey",
    "iso:country":"MX",
    "name:und_x_variant":[
        "Rancho El Sauz",
        "El Sauz"
    ],
    "wof:name":"El Sauz",
    "wof:placetype":"locality",
    "wof:population":1
},
  "geometry": {"coordinates":[-100.72913,26.43271],"type":"Point"}
}