{
  "type": "Feature",
  "properties": {
    "gn:admin1_code":"11.0",
    "gn:admin2_code":"26.0",
    "gn:asciiname":"Gavia de Rionda",
    "gn:country_code":"MX",
    "gn:dem":1777,
    "gn:feature_class":"P",
    "gn:feature_code":"PPL",
    "gn:name":"Gavia de Rionda",
    "gn:population":0,
    "gn:timezone":"America/Mexico_City",
    "iso:country":"MX",
    "name:spa_x_preferred":[
        "Gavia de Rionda"
    ],
    "wof:name":"Gavia de Rionda",
    "wof:placetype":"locality"
},
  "geometry": {"coordinates":[-101.61647000000001,20.83357],"type":"Point"}
}