{
  "type": "Feature",
  "properties": {
    "gn:admin1_code":"24",
    "gn:admin2_code":"49.0",
    "gn:asciiname":"La Arena",
    "gn:country_code":"MX",
    "gn:dem":2055,
    "gn:feature_class":"P",
    "gn:feature_code":"PPL",
    "gn:name":"La Arena",
    "gn:population":0,
    "gn:timezone":"America/Mexico_City",
    "iso:country":"MX",
    "name:und_x_variant":[
        "Los Escare\u00f1o",
        "La Arena"
    ],
    "wof:name":"La Arena",
    "wof:placetype":"locality"
},
  "geometry": {"coordinates":[-101.99484,23.05732],"type":"Point"}
}