{
  "type": "Feature",
  "properties": {
    "gn:admin1_code":"6",
    "gn:admin2_code":"20.0",
    "gn:asciiname":"Los Platanos",
    "gn:country_code":"MX",
    "gn:dem":878,
    "gn:feature_class":"P",
    "gn:feature_code":"PPL",
    "gn:name":"Los Pl\u00e1tanos",
    "gn:population":0,
    "gn:timezone":"America/Chihuahua",
    "iso:country":"MX",
    "name:spa_x_preferred":[
        "Los Pl\u00e1tanos"
    ],
    "wof:name":"Los Platanos",
    "wof:placetype":"locality"
},
  "geometry": {"coordinates":[-108.48990000000001,27.24093],"type":"Point"}
}