{
  "type": "Feature",
  "properties": {
    "gn:admin1_code":"13",
    "gn:admin2_code":"13.0",
    "gn:asciiname":"Zacamulpa",
    "gn:country_code":"MX",
    "gn:dem":2198,
    "gn:feature_class":"P",
    "gn:feature_code":"PPL",
    "gn:name":"Zacamulpa",
    "gn:population":1034,
    "gn:timezone":"America/Mexico_City",
    "iso:country":"MX",
    "wof:name":"Zacamulpa",
    "wof:placetype":"locality",
    "wof:population":1034
},
  "geometry": {"coordinates":[-99.25694,20.00583],"type":"Point"}
}