{
  "type": "Feature",
  "properties": {
    "gn:admin1_code":"24.0",
    "gn:admin2_code":"16.0",
    "gn:asciiname":"El Pitayo",
    "gn:country_code":"MX",
    "gn:dem":44,
    "gn:feature_class":"P",
    "gn:feature_code":"PPL",
    "gn:name":"El Pitayo",
    "gn:population":3,
    "gn:timezone":"America/Mexico_City",
    "iso:country":"MX",
    "name:spa_x_preferred":[
        "El Pitayo"
    ],
    "wof:name":"El Pitayo",
    "wof:placetype":"locality",
    "wof:population":3
},
  "geometry": {"coordinates":[-98.49741,22.25849],"type":"Point"}
}