{
  "type": "Feature",
  "properties": {
    "gn:admin1_code":"31",
    "gn:admin2_code":"40.0",
    "gn:asciiname":"Noptunchen",
    "gn:cc2":"MX",
    "gn:country_code":"MX",
    "gn:dem":12,
    "gn:feature_class":"P",
    "gn:feature_code":"PPL",
    "gn:name":"Noptunch\u00e9n",
    "gn:population":0,
    "gn:timezone":"America/Merida",
    "iso:country":"MX",
    "name:und_x_variant":[
        "Nuptunch\u00e9n",
        "Noptunch\u00e9n"
    ],
    "wof:name":"Noptunchen",
    "wof:placetype":"locality"
},
  "geometry": {"coordinates":[-88.96666999999999,20.98333],"type":"Point"}
}