{
  "type": "Feature",
  "properties": {
    "gn:admin1_code":"5",
    "gn:admin2_code":"59.0",
    "gn:asciiname":"Cuauhtemoc",
    "gn:country_code":"MX",
    "gn:dem":640,
    "gn:feature_class":"P",
    "gn:feature_code":"PPL",
    "gn:name":"Cuauht\u00e9moc",
    "gn:population":335,
    "gn:timezone":"America/Mexico_City",
    "iso:country":"MX",
    "name:und_x_variant":[
        "Cuauht\u00e9moc"
    ],
    "wof:name":"Cuauhtemoc",
    "wof:placetype":"locality",
    "wof:population":335
},
  "geometry": {"coordinates":[-91.69833,17.12389],"type":"Point"}
}