{
  "type": "Feature",
  "properties": {
    "gn:admin1_code":"25",
    "gn:admin2_code":"18.0",
    "gn:asciiname":"La Pipima",
    "gn:cc2":"MX",
    "gn:country_code":"MX",
    "gn:dem":10,
    "gn:feature_class":"P",
    "gn:feature_code":"PPL",
    "gn:name":"La Pipima",
    "gn:population":392,
    "gn:timezone":"America/Mazatlan",
    "iso:country":"MX",
    "name:und_x_variant":[
        "Pipima",
        "La P\u00edpima"
    ],
    "wof:name":"La Pipima",
    "wof:placetype":"locality",
    "wof:population":392
},
  "geometry": {"coordinates":[-107.68944,24.6975],"type":"Point"}
}