{
  "type": "Feature",
  "properties": {
    "gn:admin1_code":"20",
    "gn:admin2_code":"439.0",
    "gn:asciiname":"Rincon Bonito",
    "gn:country_code":"MX",
    "gn:dem":91,
    "gn:feature_class":"P",
    "gn:feature_code":"PPL",
    "gn:name":"Rinc\u00f3n Bonito",
    "gn:population":290,
    "gn:timezone":"America/Mexico_City",
    "iso:country":"MX",
    "name:und_x_variant":[
        "Rinc\u00f3n Bonito"
    ],
    "wof:name":"Rincon Bonito",
    "wof:placetype":"locality",
    "wof:population":290
},
  "geometry": {"coordinates":[-96.55500000000001,15.79083],"type":"Point"}
}