{
  "type": "Feature",
  "properties": {
    "gn:admin1_code":"30",
    "gn:admin2_code":"11.0",
    "gn:asciiname":"Pikilin",
    "gn:country_code":"MX",
    "gn:dem":22,
    "gn:feature_class":"P",
    "gn:feature_code":"PPL",
    "gn:name":"Pikil\u00edn",
    "gn:population":6,
    "gn:timezone":"America/Mexico_City",
    "iso:country":"MX",
    "name:und_x_variant":[
        "Pikil\u00edn"
    ],
    "wof:name":"Pikilin",
    "wof:placetype":"locality",
    "wof:population":6
},
  "geometry": {"coordinates":[-96.01083,19.05167],"type":"Point"}
}