{
  "type": "Feature",
  "properties": {
    "gn:admin1_code":"13",
    "gn:admin2_code":"84.0",
    "gn:asciiname":"Tathi",
    "gn:country_code":"MX",
    "gn:dem":1947,
    "gn:feature_class":"P",
    "gn:feature_code":"PPL",
    "gn:name":"Tathi",
    "gn:population":0,
    "gn:timezone":"America/Mexico_City",
    "iso:country":"MX",
    "name:spa_x_preferred":[
        "El Tathi"
    ],
    "name:spa_x_variant":[
        "Tathi"
    ],
    "wof:name":"Tathi",
    "wof:placetype":"locality"
},
  "geometry": {"coordinates":[-99.41128999999999,20.68039],"type":"Point"}
}