{
  "type": "Feature",
  "properties": {
    "gn:admin1_code":"14",
    "gn:admin2_code":"124",
    "gn:asciiname":"La Grulla",
    "gn:country_code":"MX",
    "gn:dem":1873,
    "gn:feature_class":"P",
    "gn:feature_code":"PPL",
    "gn:name":"La Grulla",
    "gn:population":45,
    "gn:timezone":"America/Mexico_City",
    "iso:country":"MX",
    "wof:name":"La Grulla",
    "wof:placetype":"locality",
    "wof:population":45
},
  "geometry": {"coordinates":[-102.89861000000001,20.56278],"type":"Point"}
}