{
  "type": "Feature",
  "properties": {
    "gn:admin1_code":"20",
    "gn:admin2_code":"278.0",
    "gn:asciiname":"Arroyo de Abajo",
    "gn:country_code":"MX",
    "gn:dem":68,
    "gn:feature_class":"P",
    "gn:feature_code":"PPL",
    "gn:name":"Arroyo de Abajo",
    "gn:population":0,
    "gn:timezone":"America/Mexico_City",
    "iso:country":"MX",
    "name:spa_x_preferred":[
        "Arroyo de Abajo"
    ],
    "wof:name":"Arroyo de Abajo",
    "wof:placetype":"locality"
},
  "geometry": {"coordinates":[-96.32666999999999,18.22139],"type":"Point"}
}