{
  "type": "Feature",
  "properties": {
    "gn:admin1_code":"20",
    "gn:admin2_code":"515.0",
    "gn:asciiname":"Mariano",
    "gn:country_code":"MX",
    "gn:dem":49,
    "gn:feature_class":"P",
    "gn:feature_code":"PPL",
    "gn:name":"Mariano",
    "gn:population":0,
    "gn:timezone":"America/Mexico_City",
    "iso:country":"MX",
    "name:deu_x_preferred":[
        "Mariano"
    ],
    "name:epo_x_preferred":[
        "Mariano"
    ],
    "name:ita_x_preferred":[
        "Mariano"
    ],
    "name:jpn_x_preferred":[
        "\u30de\u30ea\u30a2\u30fc\u30ce"
    ],
    "name:rus_x_preferred":[
        "\u041c\u0430\u0440\u0438\u0430\u043d\u043e"
    ],
    "name:spa_x_preferred":[
        "Mariano"
    ],
    "wof:name":"Mariano",
    "wof:placetype":"locality"
},
  "geometry": {"coordinates":[-95.23333,16.35],"type":"Point"}
}