{
  "type": "Feature",
  "properties": {
    "gn:admin1_code":"15",
    "gn:admin2_code":"86.0",
    "gn:asciiname":"Santanas",
    "gn:country_code":"MX",
    "gn:dem":2423,
    "gn:feature_class":"P",
    "gn:feature_code":"PPL",
    "gn:name":"Santanas",
    "gn:population":798,
    "gn:timezone":"America/Mexico_City",
    "iso:country":"MX",
    "wof:name":"Santanas",
    "wof:placetype":"locality",
    "wof:population":798
},
  "geometry": {"coordinates":[-99.94667,19.12111],"type":"Point"}
}