{
  "type": "Feature",
  "properties": {
    "gn:admin1_code":"16",
    "gn:admin2_code":"46.0",
    "gn:asciiname":"Orocutin de Serdan",
    "gn:country_code":"MX",
    "gn:dem":1245,
    "gn:feature_class":"P",
    "gn:feature_code":"PPL",
    "gn:name":"Orocut\u00edn de Serd\u00e1n",
    "gn:population":231,
    "gn:timezone":"America/Mexico_City",
    "iso:country":"MX",
    "name:und_x_variant":[
        "Orocut\u00edn de Serd\u00e1n"
    ],
    "wof:name":"Orocutin de Serdan",
    "wof:placetype":"locality",
    "wof:population":231
},
  "geometry": {"coordinates":[-100.47139,19.26528],"type":"Point"}
}