{
  "type": "Feature",
  "properties": {
    "gn:admin1_code":"25.0",
    "gn:admin2_code":"18.0",
    "gn:asciiname":"Ejido el Caimancito",
    "gn:country_code":"MX",
    "gn:dem":15,
    "gn:feature_class":"P",
    "gn:feature_code":"PPL",
    "gn:name":"Ejido el Caimancito",
    "gn:population":464,
    "gn:timezone":"America/Mazatlan",
    "iso:country":"MX",
    "wof:name":"Ejido el Caimancito",
    "wof:placetype":"locality",
    "wof:population":464
},
  "geometry": {"coordinates":[-107.70581,24.81364],"type":"Point"}
}