{
  "type": "Feature",
  "properties": {
    "gn:admin1_code":"6",
    "gn:admin2_code":"49",
    "gn:asciiname":"La Vinata",
    "gn:country_code":"MX",
    "gn:dem":1741,
    "gn:feature_class":"P",
    "gn:feature_code":"PPL",
    "gn:name":"La Vinata",
    "gn:population":24,
    "gn:timezone":"America/Chihuahua",
    "iso:country":"MX",
    "wof:name":"La Vinata",
    "wof:placetype":"locality",
    "wof:population":24
},
  "geometry": {"coordinates":[-106.77639000000001,27.26528],"type":"Point"}
}