{
  "type": "Feature",
  "properties": {
    "gn:admin1_code":"14",
    "gn:admin2_code":"31.0",
    "gn:asciiname":"Cocuasco",
    "gn:country_code":"MX",
    "gn:dem":1764,
    "gn:feature_class":"P",
    "gn:feature_code":"PPL",
    "gn:name":"Cocuasco",
    "gn:population":140,
    "gn:timezone":"America/Mexico_City",
    "iso:country":"MX",
    "wof:name":"Cocuasco",
    "wof:placetype":"locality",
    "wof:population":140
},
  "geometry": {"coordinates":[-103.64389,21.83444],"type":"Point"}
}