{
  "type": "Feature",
  "properties": {
    "gn:admin1_code":"21.0",
    "gn:admin2_code":"194.0",
    "gn:asciiname":"Salto Chico",
    "gn:country_code":"MX",
    "gn:dem":411,
    "gn:feature_class":"P",
    "gn:feature_code":"PPL",
    "gn:name":"Salto Chico",
    "gn:population":0,
    "gn:timezone":"America/Mexico_City",
    "iso:country":"MX",
    "name:spa_x_preferred":[
        "Salto Chico"
    ],
    "wof:name":"Salto Chico",
    "wof:placetype":"locality"
},
  "geometry": {"coordinates":[-97.75602000000001,20.50802],"type":"Point"}
}