{
  "type": "Feature",
  "properties": {
    "gn:admin1_code":"30",
    "gn:admin2_code":"23.0",
    "gn:asciiname":"Ejido Penas de Almanza",
    "gn:country_code":"MX",
    "gn:dem":511,
    "gn:feature_class":"P",
    "gn:feature_code":"PPL",
    "gn:name":"Ejido Pe\u00f1as de Almanza",
    "gn:population":0,
    "gn:timezone":"America/Mexico_City",
    "iso:country":"MX",
    "name:spa_x_preferred":[
        "Ejido Pe\u00f1as de Almanza"
    ],
    "wof:name":"Ejido Penas de Almanza",
    "wof:placetype":"locality"
},
  "geometry": {"coordinates":[-97.0256,19.94967],"type":"Point"}
}