{
  "type": "Feature",
  "properties": {
    "gn:admin1_code":"6.0",
    "gn:admin2_code":"54.0",
    "gn:asciiname":"Campo Cuarenta y Cinco",
    "gn:country_code":"MX",
    "gn:dem":2131,
    "gn:feature_class":"P",
    "gn:feature_code":"PPL",
    "gn:name":"Campo Cuarenta y Cinco",
    "gn:population":0,
    "gn:timezone":"America/Chihuahua",
    "iso:country":"MX",
    "name:spa_x_preferred":[
        "Campo Cuarenta y Cinco"
    ],
    "name:und_x_variant":[
        "Campo Menonita N\u00famero 45"
    ],
    "wof:name":"Campo Cuarenta y Cinco",
    "wof:placetype":"locality"
},
  "geometry": {"coordinates":[-106.82758,28.9111],"type":"Point"}
}