{
  "type": "Feature",
  "properties": {
    "gn:admin1_code":"29",
    "gn:admin2_code":"12.0",
    "gn:asciiname":"Los Alpinos",
    "gn:country_code":"MX",
    "gn:dem":2658,
    "gn:feature_class":"P",
    "gn:feature_code":"PPL",
    "gn:name":"Los Alpinos",
    "gn:population":0,
    "gn:timezone":"America/Mexico_City",
    "iso:country":"MX",
    "name:spa_x_preferred":[
        "Los Alpinos"
    ],
    "wof:name":"Los Alpinos",
    "wof:placetype":"locality"
},
  "geometry": {"coordinates":[-98.50293000000001,19.49142],"type":"Point"}
}