{
  "type": "Feature",
  "properties": {
    "gn:admin1_code":"24.0",
    "gn:admin2_code":"55.0",
    "gn:asciiname":"Ranchito de Juarez",
    "gn:country_code":"MX",
    "gn:dem":1972,
    "gn:feature_class":"P",
    "gn:feature_code":"PPL",
    "gn:name":"Ranchito de Ju\u00e1rez",
    "gn:population":0,
    "gn:timezone":"America/Mexico_City",
    "iso:country":"MX",
    "name:spa_x_preferred":[
        "Ranchito de Ju\u00e1rez"
    ],
    "name:und_x_variant":[
        "Ju\u00e1rez"
    ],
    "wof:name":"Ranchito de Juarez",
    "wof:placetype":"locality"
},
  "geometry": {"coordinates":[-100.60986,21.95754],"type":"Point"}
}