{
  "type": "Feature",
  "properties": {
    "gn:admin1_code":"7.0",
    "gn:admin2_code":"23.0",
    "gn:asciiname":"El Rayo",
    "gn:country_code":"MX",
    "gn:dem":1234,
    "gn:feature_class":"P",
    "gn:feature_code":"PPL",
    "gn:name":"El Rayo",
    "gn:population":0,
    "gn:timezone":"America/Monterrey",
    "iso:country":"MX",
    "name:spa_x_preferred":[
        "El Rayo"
    ],
    "name:und_x_variant":[
        "Rancho El Rayo"
    ],
    "wof:name":"El Rayo",
    "wof:placetype":"locality"
},
  "geometry": {"coordinates":[-102.89579999999999,27.95665],"type":"Point"}
}