{
  "type": "Feature",
  "properties": {
    "gn:admin1_code":"14.0",
    "gn:admin2_code":"115.0",
    "gn:asciiname":"La Ventana",
    "gn:country_code":"MX",
    "gn:dem":1424,
    "gn:feature_class":"P",
    "gn:feature_code":"PPL",
    "gn:name":"La Ventana",
    "gn:population":0,
    "gn:timezone":"America/Mexico_City",
    "iso:country":"MX",
    "name:spa_x_preferred":[
        "La Ventana"
    ],
    "name:urd_x_preferred":[
        "\u0644\u0627 \u0648\u06cc\u0646\u0679\u0627\u0646\u0627"
    ],
    "wof:name":"La Ventana",
    "wof:placetype":"locality"
},
  "geometry": {"coordinates":[-103.76102,22.03502000000001],"type":"Point"}
}