{
  "type": "Feature",
  "properties": {
    "gn:admin1_code":"14",
    "gn:admin2_code":"58.0",
    "gn:asciiname":"Rio de la Plata",
    "gn:country_code":"MX",
    "gn:dem":1224,
    "gn:feature_class":"P",
    "gn:feature_code":"PPL",
    "gn:name":"R\u00edo de la Plata",
    "gn:population":6,
    "gn:timezone":"America/Mexico_City",
    "iso:country":"MX",
    "name:spa_x_preferred":[
        "R\u00edo de la Plata"
    ],
    "wof:name":"Rio de la Plata",
    "wof:placetype":"locality",
    "wof:population":6
},
  "geometry": {"coordinates":[-104.8417,20.55519],"type":"Point"}
}