{
  "type": "Feature",
  "properties": {
    "gn:admin1_code":"10.0",
    "gn:admin2_code":"24.0",
    "gn:asciiname":"Los Amoles",
    "gn:country_code":"MX",
    "gn:dem":1318,
    "gn:feature_class":"P",
    "gn:feature_code":"PPL",
    "gn:name":"Los Amoles",
    "gn:population":271,
    "gn:timezone":"America/Monterrey",
    "iso:country":"MX",
    "name:und_x_variant":[
        "Amoles"
    ],
    "wof:name":"Los Amoles",
    "wof:placetype":"locality",
    "wof:population":271
},
  "geometry": {"coordinates":[-104.4469,25.13148],"type":"Point"}
}