{
  "type": "Feature",
  "properties": {
    "gn:admin1_code":"30.0",
    "gn:admin2_code":"60.0",
    "gn:asciiname":"Loma Alta",
    "gn:country_code":"MX",
    "gn:dem":51,
    "gn:feature_class":"P",
    "gn:feature_code":"PPL",
    "gn:name":"Loma Alta",
    "gn:population":2,
    "gn:timezone":"America/Mexico_City",
    "iso:country":"MX",
    "name:spa_x_preferred":[
        "Loma Alta"
    ],
    "wof:name":"Loma Alta",
    "wof:placetype":"locality",
    "wof:population":2
},
  "geometry": {"coordinates":[-97.60583,21.36194],"type":"Point"}
}