{
  "type": "Feature",
  "properties": {
    "gn:admin1_code":"19",
    "gn:admin2_code":"36.0",
    "gn:asciiname":"La Morena",
    "gn:country_code":"MX",
    "gn:dem":1844,
    "gn:feature_class":"P",
    "gn:feature_code":"PPL",
    "gn:name":"La More\u00f1a",
    "gn:population":0,
    "gn:timezone":"America/Monterrey",
    "iso:country":"MX",
    "name:und_x_variant":[
        "Tapona More\u00f1a",
        "La More\u00f1a"
    ],
    "wof:name":"La Morena",
    "wof:placetype":"locality"
},
  "geometry": {"coordinates":[-100.32077,23.36619],"type":"Point"}
}