{
  "type": "Feature",
  "properties": {
    "gn:admin1_code":"19",
    "gn:admin2_code":"5.0",
    "gn:asciiname":"Lupe Cavazos",
    "gn:country_code":"MX",
    "gn:dem":165,
    "gn:feature_class":"P",
    "gn:feature_code":"PPL",
    "gn:name":"Lupe Cavazos",
    "gn:population":5,
    "gn:timezone":"America/Matamoros",
    "iso:country":"MX",
    "wof:name":"Lupe Cavazos",
    "wof:placetype":"locality",
    "wof:population":5
},
  "geometry": {"coordinates":[-100.02394,27.0903],"type":"Point"}
}