{
  "type": "Feature",
  "properties": {
    "gn:admin1_code":"20",
    "gn:admin2_code":"217",
    "gn:asciiname":"Joya de Platanal",
    "gn:country_code":"MX",
    "gn:dem":2069,
    "gn:feature_class":"P",
    "gn:feature_code":"PPL",
    "gn:name":"Joya de Platanal",
    "gn:population":20,
    "gn:timezone":"America/Mexico_City",
    "iso:country":"MX",
    "wof:name":"Joya de Platanal",
    "wof:placetype":"locality",
    "wof:population":20
},
  "geometry": {"coordinates":[-97.1075,17.09583],"type":"Point"}
}