{
  "type": "Feature",
  "properties": {
    "gn:admin1_code":"11.0",
    "gn:admin2_code":"3.0",
    "gn:asciiname":"Canada de Garcia",
    "gn:country_code":"MX",
    "gn:dem":2048,
    "gn:feature_class":"P",
    "gn:feature_code":"PPL",
    "gn:name":"Ca\u00f1ada de Garc\u00eda",
    "gn:population":112,
    "gn:timezone":"America/Mexico_City",
    "iso:country":"MX",
    "wof:name":"Canada de Garcia",
    "wof:placetype":"locality",
    "wof:population":112
},
  "geometry": {"coordinates":[-100.98944,20.88139],"type":"Point"}
}