{
  "type": "Feature",
  "properties": {
    "gn:admin1_code":"26",
    "gn:admin2_code":"19.0",
    "gn:asciiname":"Penuelos",
    "gn:country_code":"MX",
    "gn:dem":1388,
    "gn:feature_class":"P",
    "gn:feature_code":"PPL",
    "gn:name":"Pe\u00f1uelos",
    "gn:population":0,
    "gn:timezone":"America/Hermosillo",
    "iso:country":"MX",
    "wof:name":"Penuelos",
    "wof:placetype":"locality"
},
  "geometry": {"coordinates":[-110.45,30.86667000000001],"type":"Point"}
}