{
  "type": "Feature",
  "properties": {
    "gn:admin1_code":"14",
    "gn:admin2_code":"54.0",
    "gn:asciiname":"Apulquito",
    "gn:country_code":"MX",
    "gn:dem":788,
    "gn:feature_class":"P",
    "gn:feature_code":"PPL",
    "gn:name":"Apulquito",
    "gn:population":6,
    "gn:timezone":"America/Mexico_City",
    "iso:country":"MX",
    "wof:name":"Apulquito",
    "wof:placetype":"locality",
    "wof:population":6
},
  "geometry": {"coordinates":[-104.07917,19.86861],"type":"Point"}
}