{
  "type": "Feature",
  "properties": {
    "gn:admin1_code":"5",
    "gn:admin2_code":"69.0",
    "gn:asciiname":"Aqui te Espero",
    "gn:country_code":"MX",
    "gn:dem":33,
    "gn:feature_class":"P",
    "gn:feature_code":"PPL",
    "gn:name":"Aqu\u00ed te Espero",
    "gn:population":5,
    "gn:timezone":"America/Mexico_City",
    "iso:country":"MX",
    "name:und_x_variant":[
        "Aqu\u00ed te Espero"
    ],
    "wof:name":"Aqui te Espero",
    "wof:placetype":"locality",
    "wof:population":5
},
  "geometry": {"coordinates":[-93.08583,15.60583],"type":"Point"}
}