{
  "type": "Feature",
  "properties": {
    "gn:admin1_code":"7",
    "gn:admin2_code":"4.0",
    "gn:asciiname":"Ojo de Mula",
    "gn:country_code":"MX",
    "gn:dem":2354,
    "gn:feature_class":"P",
    "gn:feature_code":"PPL",
    "gn:name":"Ojo de Mula",
    "gn:population":0,
    "gn:timezone":"America/Monterrey",
    "iso:country":"MX",
    "name:spa_x_preferred":[
        "Ojo de Mula"
    ],
    "wof:name":"Ojo de Mula",
    "wof:placetype":"locality"
},
  "geometry": {"coordinates":[-100.65364,25.42765],"type":"Point"}
}