{
  "type": "Feature",
  "properties": {
    "gn:admin1_code":"28.0",
    "gn:admin2_code":"42.0",
    "gn:asciiname":"La Independencia",
    "gn:country_code":"MX",
    "gn:dem":287,
    "gn:feature_class":"P",
    "gn:feature_code":"PPL",
    "gn:name":"La Independencia",
    "gn:population":0,
    "gn:timezone":"America/Monterrey",
    "iso:country":"MX",
    "name:spa_x_preferred":[
        "La Independencia"
    ],
    "wof:name":"La Independencia",
    "wof:placetype":"locality"
},
  "geometry": {"coordinates":[-99.28556,24.49806],"type":"Point"}
}