{
  "type": "Feature",
  "properties": {
    "gn:admin1_code":"32",
    "gn:admin2_code":"12.0",
    "gn:asciiname":"Paso de Mendez",
    "gn:country_code":"MX",
    "gn:dem":2237,
    "gn:feature_class":"P",
    "gn:feature_code":"PPL",
    "gn:name":"Paso de M\u00e9ndez",
    "gn:population":0,
    "gn:timezone":"America/Mexico_City",
    "iso:country":"MX",
    "name:spa_x_preferred":[
        "Paso de M\u00e9ndez"
    ],
    "wof:name":"Paso de Mendez",
    "wof:placetype":"locality"
},
  "geometry": {"coordinates":[-102.46956,22.51588],"type":"Point"}
}