{
  "type": "Feature",
  "properties": {
    "gn:admin1_code":"16",
    "gn:admin2_code":"12.0",
    "gn:asciiname":"El Tamarindo Uno",
    "gn:country_code":"MX",
    "gn:dem":385,
    "gn:feature_class":"P",
    "gn:feature_code":"PPL",
    "gn:name":"El Tamarindo Uno",
    "gn:population":5,
    "gn:timezone":"America/Mexico_City",
    "iso:country":"MX",
    "wof:name":"El Tamarindo Uno",
    "wof:placetype":"locality",
    "wof:population":5
},
  "geometry": {"coordinates":[-102.56667,19.17972],"type":"Point"}
}