{
  "type": "Feature",
  "properties": {
    "gn:admin1_code":"6",
    "gn:admin2_code":"27.0",
    "gn:asciiname":"El Manzano",
    "gn:country_code":"MX",
    "gn:dem":2254,
    "gn:feature_class":"P",
    "gn:feature_code":"PPL",
    "gn:name":"El Manzano",
    "gn:population":6,
    "gn:timezone":"America/Chihuahua",
    "iso:country":"MX",
    "wof:name":"El Manzano",
    "wof:placetype":"locality",
    "wof:population":6
},
  "geometry": {"coordinates":[-107.49488999999998,26.8391],"type":"Point"}
}