{
  "type": "Feature",
  "properties": {
    "gn:admin1_code":"6.0",
    "gn:admin2_code":"15.0",
    "gn:asciiname":"Coyamito",
    "gn:country_code":"MX",
    "gn:dem":1098,
    "gn:feature_class":"P",
    "gn:feature_code":"PPL",
    "gn:name":"Coyamito",
    "gn:population":0,
    "gn:timezone":"America/Chihuahua",
    "iso:country":"MX",
    "name:spa_x_preferred":[
        "Coyamito"
    ],
    "name:und_x_variant":[
        "El Coyamito"
    ],
    "wof:name":"Coyamito",
    "wof:placetype":"locality"
},
  "geometry": {"coordinates":[-105.02061999999999,29.52921],"type":"Point"}
}