{
  "type": "Feature",
  "properties": {
    "gn:admin1_code":"26",
    "gn:admin2_code":"72.0",
    "gn:asciiname":"Bateve Segundo (Dos de Marzo)",
    "gn:country_code":"MX",
    "gn:dem":7,
    "gn:feature_class":"P",
    "gn:feature_code":"PPL",
    "gn:name":"Bateve Segundo (Dos de Marzo)",
    "gn:population":7,
    "gn:timezone":"America/Hermosillo",
    "iso:country":"MX",
    "wof:name":"Bateve Segundo (Dos de Marzo)",
    "wof:placetype":"locality",
    "wof:population":7
},
  "geometry": {"coordinates":[-110.26194,27.25944],"type":"Point"}
}