{
  "type": "Feature",
  "properties": {
    "gn:admin1_code":"14",
    "gn:admin2_code":"109",
    "gn:asciiname":"Presa San Angel",
    "gn:country_code":"MX",
    "gn:dem":1824,
    "gn:feature_class":"P",
    "gn:feature_code":"PPL",
    "gn:name":"Presa San \u00c1ngel",
    "gn:population":13,
    "gn:timezone":"America/Mexico_City",
    "iso:country":"MX",
    "name:und_x_variant":[
        "Presa San \u00c1ngel"
    ],
    "wof:name":"Presa San Angel",
    "wof:placetype":"locality",
    "wof:population":13
},
  "geometry": {"coordinates":[-101.87667,21.19056],"type":"Point"}
}