{
  "type": "Feature",
  "properties": {
    "gn:admin1_code":"26",
    "gn:admin2_code":"18",
    "gn:asciiname":"Ojai",
    "gn:country_code":"MX",
    "gn:dem":22,
    "gn:feature_class":"P",
    "gn:feature_code":"PPL",
    "gn:name":"Ojai",
    "gn:population":15,
    "gn:timezone":"America/Hermosillo",
    "iso:country":"MX",
    "wof:name":"Ojai",
    "wof:placetype":"locality",
    "wof:population":15
},
  "geometry": {"coordinates":[-110.01555999999999,27.34028],"type":"Point"}
}