{
  "type": "Feature",
  "properties": {
    "gn:admin1_code":"26",
    "gn:admin2_code":"36",
    "gn:asciiname":"Nanenachi",
    "gn:country_code":"MX",
    "gn:dem":762,
    "gn:feature_class":"P",
    "gn:feature_code":"PPL",
    "gn:name":"Nanenachi",
    "gn:population":14,
    "gn:timezone":"America/Hermosillo",
    "iso:country":"MX",
    "wof:name":"Nanenachi",
    "wof:placetype":"locality",
    "wof:population":14
},
  "geometry": {"coordinates":[-111.14778,30.7275],"type":"Point"}
}