{
  "type": "Feature",
  "properties": {
    "gn:admin1_code":"13",
    "gn:admin2_code":"81.0",
    "gn:asciiname":"Tepeoco",
    "gn:country_code":"MX",
    "gn:dem":2036,
    "gn:feature_class":"P",
    "gn:feature_code":"PPL",
    "gn:name":"Tepeoco",
    "gn:population":0,
    "gn:timezone":"America/Mexico_City",
    "iso:country":"MX",
    "name:spa_x_preferred":[
        "Tepeoco"
    ],
    "wof:name":"Tepeoco",
    "wof:placetype":"locality"
},
  "geometry": {"coordinates":[-98.67207000000001,20.68621],"type":"Point"}
}