{
  "type": "Feature",
  "properties": {
    "gn:admin1_code":"26",
    "gn:admin2_code":"21.0",
    "gn:asciiname":"El Lapiz",
    "gn:country_code":"MX",
    "gn:dem":450,
    "gn:feature_class":"P",
    "gn:feature_code":"PPL",
    "gn:name":"El L\u00e1piz",
    "gn:population":0,
    "gn:timezone":"America/Hermosillo",
    "iso:country":"MX",
    "name:spa_x_preferred":[
        "El L\u00e1piz"
    ],
    "name:und_x_variant":[
        "Rancho L\u00e1piz Viejo",
        "L\u00e1piz",
        "L\u00e1piz Viejo"
    ],
    "wof:name":"El Lapiz",
    "wof:placetype":"locality"
},
  "geometry": {"coordinates":[-110.46521,28.64812],"type":"Point"}
}