{
  "type": "Feature",
  "properties": {
    "gn:admin1_code":"25",
    "gn:admin2_code":"5.0",
    "gn:asciiname":"Los Mimbres",
    "gn:country_code":"MX",
    "gn:dem":260,
    "gn:feature_class":"P",
    "gn:feature_code":"PPL",
    "gn:name":"Los Mimbres",
    "gn:population":19,
    "gn:timezone":"America/Mazatlan",
    "iso:country":"MX",
    "wof:name":"Los Mimbres",
    "wof:placetype":"locality",
    "wof:population":19
},
  "geometry": {"coordinates":[-106.95303,24.6365],"type":"Point"}
}