{
  "type": "Feature",
  "properties": {
    "gn:admin1_code":"3",
    "gn:admin2_code":"1.0",
    "gn:asciiname":"La Sabila",
    "gn:country_code":"MX",
    "gn:dem":129,
    "gn:feature_class":"P",
    "gn:feature_code":"PPL",
    "gn:name":"La S\u00e1bila",
    "gn:population":6,
    "gn:timezone":"America/Mazatlan",
    "iso:country":"MX",
    "name:und_x_variant":[
        "La S\u00e1bila"
    ],
    "wof:name":"La Sabila",
    "wof:placetype":"locality",
    "wof:population":6
},
  "geometry": {"coordinates":[-111.62836,25.58975],"type":"Point"}
}