{
  "type": "Feature",
  "properties": {
    "gn:admin1_code":"17",
    "gn:admin2_code":"4.0",
    "gn:asciiname":"Rancho el Panuelo",
    "gn:country_code":"MX",
    "gn:dem":1236,
    "gn:feature_class":"P",
    "gn:feature_code":"PPL",
    "gn:name":"Rancho el Pa\u00f1uelo",
    "gn:population":96,
    "gn:timezone":"America/Mexico_City",
    "iso:country":"MX",
    "name:und_x_variant":[
        "Rancho el Pa\u00f1uelo"
    ],
    "wof:name":"Rancho el Panuelo",
    "wof:placetype":"locality",
    "wof:population":96
},
  "geometry": {"coordinates":[-98.87944,18.69944],"type":"Point"}
}