{
  "type": "Feature",
  "properties": {
    "gn:admin1_code":"8.0",
    "gn:admin2_code":"1.0",
    "gn:asciiname":"Escaltitan",
    "gn:country_code":"MX",
    "gn:dem":93,
    "gn:feature_class":"P",
    "gn:feature_code":"PPL",
    "gn:name":"Escaltit\u00e1n",
    "gn:population":0,
    "gn:timezone":"America/Mexico_City",
    "iso:country":"MX",
    "name:spa_x_preferred":[
        "Escaltit\u00e1n"
    ],
    "wof:name":"Escaltitan",
    "wof:placetype":"locality"
},
  "geometry": {"coordinates":[-103.92009,19.02235],"type":"Point"}
}