{
  "type": "Feature",
  "properties": {
    "gn:admin1_code":"22",
    "gn:admin2_code":"18.0",
    "gn:asciiname":"Bermejo",
    "gn:country_code":"MX",
    "gn:dem":2343,
    "gn:feature_class":"P",
    "gn:feature_code":"PPL",
    "gn:name":"Bermejo",
    "gn:population":0,
    "gn:timezone":"America/Mexico_City",
    "iso:country":"MX",
    "name:spa_x_preferred":[
        "Bermejo"
    ],
    "wof:name":"Bermejo",
    "wof:placetype":"locality"
},
  "geometry": {"coordinates":[-99.99169000000001,20.97421],"type":"Point"}
}