{
  "type": "Feature",
  "properties": {
    "gn:admin1_code":"14",
    "gn:admin2_code":"38.0",
    "gn:asciiname":"Quililla",
    "gn:country_code":"MX",
    "gn:dem":1482,
    "gn:feature_class":"P",
    "gn:feature_code":"PPL",
    "gn:name":"Quililla",
    "gn:population":0,
    "gn:timezone":"America/Mexico_City",
    "iso:country":"MX",
    "wof:name":"Quililla",
    "wof:placetype":"locality"
},
  "geometry": {"coordinates":[-104.30566,20.49412],"type":"Point"}
}