{
  "type": "Feature",
  "properties": {
    "gn:admin1_code":"20",
    "gn:admin2_code":"467.0",
    "gn:asciiname":"San Jose Rio Verde (La Boquilla)",
    "gn:country_code":"MX",
    "gn:dem":25,
    "gn:feature_class":"P",
    "gn:feature_code":"PPL",
    "gn:name":"San Jos\u00e9 R\u00edo Verde (La Boquilla)",
    "gn:population":654,
    "gn:timezone":"America/Mexico_City",
    "iso:country":"MX",
    "name:spa_x_preferred":[
        "San Jos\u00e9 R\u00edo Verde"
    ],
    "wof:name":"San Jose Rio Verde (La Boquilla)",
    "wof:placetype":"locality",
    "wof:population":654
},
  "geometry": {"coordinates":[-97.75306,16.13667],"type":"Point"}
}