{
  "type": "Feature",
  "properties": {
    "gn:admin1_code":"10",
    "gn:admin2_code":"13.0",
    "gn:asciiname":"Ojuela",
    "gn:country_code":"MX",
    "gn:dem":1622,
    "gn:feature_class":"P",
    "gn:feature_code":"PPL",
    "gn:name":"Ojuela",
    "gn:population":0,
    "gn:timezone":"America/Monterrey",
    "iso:country":"MX",
    "name:jpn_x_preferred":[
        "\u30aa\u30cf\u30a8\u30e9\u9271\u5c71"
    ],
    "name:spa_x_preferred":[
        "Ojuela"
    ],
    "wof:name":"Ojuela",
    "wof:placetype":"locality"
},
  "geometry": {"coordinates":[-103.76667,25.76667],"type":"Point"}
}