{
  "type": "Feature",
  "properties": {
    "gn:admin1_code":"31",
    "gn:admin2_code":"19.0",
    "gn:asciiname":"Estrella",
    "gn:country_code":"MX",
    "gn:dem":20,
    "gn:feature_class":"P",
    "gn:feature_code":"PPL",
    "gn:name":"Estrella",
    "gn:population":72,
    "gn:timezone":"America/Merida",
    "iso:country":"MX",
    "wof:name":"Estrella",
    "wof:placetype":"locality",
    "wof:population":72
},
  "geometry": {"coordinates":[-87.7375,20.80694],"type":"Point"}
}