{
  "type": "Feature",
  "properties": {
    "gn:admin1_code":"10",
    "gn:admin2_code":"26",
    "gn:asciiname":"Las Cebollas",
    "gn:country_code":"MX",
    "gn:dem":2567,
    "gn:feature_class":"P",
    "gn:feature_code":"PPL",
    "gn:name":"Las Cebollas",
    "gn:population":39,
    "gn:timezone":"America/Monterrey",
    "iso:country":"MX",
    "wof:name":"Las Cebollas",
    "wof:placetype":"locality",
    "wof:population":39
},
  "geometry": {"coordinates":[-105.98144000000001,24.44222],"type":"Point"}
}