{
  "type": "Feature",
  "properties": {
    "gn:admin1_code":"5",
    "gn:admin2_code":"61.0",
    "gn:asciiname":"Samaria",
    "gn:country_code":"MX",
    "gn:dem":494,
    "gn:feature_class":"P",
    "gn:feature_code":"PPL",
    "gn:name":"Samaria",
    "gn:population":8,
    "gn:timezone":"America/Mexico_City",
    "iso:country":"MX",
    "wof:name":"Samaria",
    "wof:placetype":"locality",
    "wof:population":8
},
  "geometry": {"coordinates":[-93.46167,17.0125],"type":"Point"}
}