{
  "type": "Feature",
  "properties": {
    "gn:admin1_code":"10",
    "gn:admin2_code":"14.0",
    "gn:asciiname":"Combustita",
    "gn:country_code":"MX",
    "gn:dem":758,
    "gn:feature_class":"P",
    "gn:feature_code":"PPL",
    "gn:name":"Combustita",
    "gn:population":58,
    "gn:timezone":"America/Monterrey",
    "iso:country":"MX",
    "wof:name":"Combustita",
    "wof:placetype":"locality",
    "wof:population":58
},
  "geometry": {"coordinates":[-104.60745,22.66809],"type":"Point"}
}