{
  "type": "Feature",
  "properties": {
    "gn:admin1_code":"3",
    "gn:admin2_code":"3.0",
    "gn:asciiname":"Bola de Fuego",
    "gn:country_code":"MX",
    "gn:dem":27,
    "gn:feature_class":"P",
    "gn:feature_code":"PPL",
    "gn:name":"Bola de Fuego",
    "gn:population":4,
    "gn:timezone":"America/Mazatlan",
    "iso:country":"MX",
    "wof:name":"Bola de Fuego",
    "wof:placetype":"locality",
    "wof:population":4
},
  "geometry": {"coordinates":[-110.3922,24.05717000000001],"type":"Point"}
}