{
  "type": "Feature",
  "properties": {
    "gn:admin1_code":"30.0",
    "gn:admin2_code":"83.0",
    "gn:asciiname":"El Nopal",
    "gn:country_code":"MX",
    "gn:dem":168,
    "gn:feature_class":"P",
    "gn:feature_code":"PPL",
    "gn:name":"El Nopal",
    "gn:population":162,
    "gn:timezone":"America/Mexico_City",
    "iso:country":"MX",
    "name:spa_x_preferred":[
        "El Nopal"
    ],
    "wof:name":"El Nopal",
    "wof:placetype":"locality",
    "wof:population":162
},
  "geometry": {"coordinates":[-97.95389,20.7075],"type":"Point"}
}