{
  "type": "Feature",
  "properties": {
    "gn:admin1_code":"26.0",
    "gn:admin2_code":"11.0",
    "gn:asciiname":"Taguarucachi",
    "gn:country_code":"MX",
    "gn:dem":1067,
    "gn:feature_class":"P",
    "gn:feature_code":"PPL",
    "gn:name":"Taguarucachi",
    "gn:population":0,
    "gn:timezone":"America/Hermosillo",
    "iso:country":"MX",
    "name:spa_x_preferred":[
        "Taguarucachi"
    ],
    "wof:name":"Taguarucachi",
    "wof:placetype":"locality"
},
  "geometry": {"coordinates":[-109.9413,30.6451],"type":"Point"}
}