{
  "type": "Feature",
  "properties": {
    "gn:admin1_code":"12",
    "gn:admin2_code":"36.0",
    "gn:asciiname":"Acalmani",
    "gn:country_code":"MX",
    "gn:dem":349,
    "gn:feature_class":"P",
    "gn:feature_code":"PPL",
    "gn:name":"Acalmani",
    "gn:population":743,
    "gn:timezone":"America/Mexico_City",
    "iso:country":"MX",
    "name:ceb_x_preferred":[
        "Acalmani"
    ],
    "name:fas_x_preferred":[
        "\u0627\u06a9\u0627\u0644\u0645\u0627\u0646\u06cc"
    ],
    "name:sco_x_preferred":[
        "Acalmani"
    ],
    "name:srp_x_preferred":[
        "\u0410\u043a\u0430\u043b\u043c\u0430\u043d\u0438"
    ],
    "wof:name":"Acalmani",
    "wof:placetype":"locality",
    "wof:population":743
},
  "geometry": {"coordinates":[-98.50637999999999,16.81591],"type":"Point"}
}