{
  "type": "Feature",
  "properties": {
    "gn:admin1_code":"6",
    "gn:admin2_code":"51.0",
    "gn:asciiname":"La Guitarra",
    "gn:country_code":"MX",
    "gn:dem":2327,
    "gn:feature_class":"P",
    "gn:feature_code":"PPL",
    "gn:name":"La Guitarra",
    "gn:population":0,
    "gn:timezone":"America/Chihuahua",
    "iso:country":"MX",
    "name:spa_x_preferred":[
        "La Guitarra"
    ],
    "wof:name":"La Guitarra",
    "wof:placetype":"locality"
},
  "geometry": {"coordinates":[-108.16579,28.07202],"type":"Point"}
}