{
  "type": "Feature",
  "properties": {
    "gn:admin1_code":"6.0",
    "gn:admin2_code":"58.0",
    "gn:asciiname":"El Amparaleno",
    "gn:country_code":"MX",
    "gn:dem":1272,
    "gn:feature_class":"P",
    "gn:feature_code":"PPL",
    "gn:name":"El Amparale\u00f1o",
    "gn:population":0,
    "gn:timezone":"America/Chihuahua",
    "iso:country":"MX",
    "name:und_x_variant":[
        "El Lamparale\u00f1o",
        "El Amparale\u00f1o",
        "Amparene\u00f1o",
        "Ampare\u00f1o",
        "Amporone\u00f1o"
    ],
    "wof:name":"El Amparaleno",
    "wof:placetype":"locality"
},
  "geometry": {"coordinates":[-105.33333,27.58333],"type":"Point"}
}