{
  "type": "Feature",
  "properties": {
    "gn:admin1_code":"17",
    "gn:asciiname":"Coleapan",
    "gn:country_code":"MX",
    "gn:dem":2266,
    "gn:feature_class":"P",
    "gn:feature_code":"PPL",
    "gn:name":"Coleapan",
    "gn:population":0,
    "gn:timezone":"America/Mexico_City",
    "iso:country":"MX",
    "name:spa_x_preferred":[
        "Coleapan"
    ],
    "wof:name":"Coleapan",
    "wof:placetype":"locality"
},
  "geometry": {"coordinates":[-99.03209,19.80577000000001],"type":"Point"}
}