{
  "type": "Feature",
  "properties": {
    "gn:admin1_code":"12",
    "gn:admin2_code":"62",
    "gn:asciiname":"Barranca Seca (Rancho Jacinto Santiago)",
    "gn:country_code":"MX",
    "gn:dem":802,
    "gn:feature_class":"P",
    "gn:feature_code":"PPL",
    "gn:name":"Barranca Seca (Rancho Jacinto Santiago)",
    "gn:population":14,
    "gn:timezone":"America/Mexico_City",
    "iso:country":"MX",
    "wof:name":"Barranca Seca (Rancho Jacinto Santiago)",
    "wof:placetype":"locality",
    "wof:population":14
},
  "geometry": {"coordinates":[-98.20165,17.08584],"type":"Point"}
}