{
  "type": "Feature",
  "properties": {
    "gn:admin1_code":"32.0",
    "gn:asciiname":"Las Riveras",
    "gn:country_code":"MX",
    "gn:dem":2382,
    "gn:feature_class":"P",
    "gn:feature_code":"PPL",
    "gn:name":"Las Riveras",
    "gn:population":0,
    "gn:timezone":"America/Mexico_City",
    "iso:country":"MX",
    "name:spa_x_preferred":[
        "Las Riveras"
    ],
    "wof:name":"Las Riveras",
    "wof:placetype":"locality"
},
  "geometry": {"coordinates":[-101.58909,22.28869],"type":"Point"}
}