{
  "type": "Feature",
  "properties": {
    "gn:admin1_code":"6",
    "gn:admin2_code":"20.0",
    "gn:asciiname":"Mochagari",
    "gn:country_code":"MX",
    "gn:dem":901,
    "gn:feature_class":"P",
    "gn:feature_code":"PPL",
    "gn:name":"Mochagari",
    "gn:population":8,
    "gn:timezone":"America/Chihuahua",
    "iso:country":"MX",
    "wof:name":"Mochagari",
    "wof:placetype":"locality",
    "wof:population":8
},
  "geometry": {"coordinates":[-108.51415,27.58448],"type":"Point"}
}