{
  "type": "Feature",
  "properties": {
    "gn:admin1_code":"19.0",
    "gn:asciiname":"Los Potros",
    "gn:country_code":"MX",
    "gn:dem":793,
    "gn:feature_class":"P",
    "gn:feature_code":"PPL",
    "gn:name":"Los Potros",
    "gn:population":0,
    "gn:timezone":"America/Monterrey",
    "iso:country":"MX",
    "name:spa_x_preferred":[
        "Los Potros"
    ],
    "wof:name":"Los Potros",
    "wof:placetype":"locality"
},
  "geometry": {"coordinates":[-100.65182,25.83909],"type":"Point"}
}