{
  "type": "Feature",
  "properties": {
    "gn:admin1_code":"17",
    "gn:admin2_code":"9",
    "gn:asciiname":"Rancho mi Reyna",
    "gn:country_code":"MX",
    "gn:dem":2222,
    "gn:feature_class":"P",
    "gn:feature_code":"PPL",
    "gn:name":"Rancho mi Reyna",
    "gn:population":12,
    "gn:timezone":"America/Mexico_City",
    "iso:country":"MX",
    "wof:name":"Rancho mi Reyna",
    "wof:placetype":"locality",
    "wof:population":12
},
  "geometry": {"coordinates":[-99.25583,19.00556],"type":"Point"}
}