{
  "type": "Feature",
  "properties": {
    "gn:admin1_code":"32",
    "gn:asciiname":"Jaltomate",
    "gn:country_code":"MX",
    "gn:dem":2134,
    "gn:feature_class":"P",
    "gn:feature_code":"PPL",
    "gn:name":"Jaltomate",
    "gn:population":0,
    "gn:timezone":"America/Mexico_City",
    "iso:country":"MX",
    "wof:name":"Jaltomate",
    "wof:placetype":"locality"
},
  "geometry": {"coordinates":[-101.27500000000001,22.16667],"type":"Point"}
}