{
  "type": "Feature",
  "properties": {
    "gn:admin1_code":"5",
    "gn:admin2_code":"112.0",
    "gn:asciiname":"Cruzton",
    "gn:country_code":"MX",
    "gn:dem":1389,
    "gn:feature_class":"P",
    "gn:feature_code":"PPL",
    "gn:name":"Cruzt\u00f3n",
    "gn:population":868,
    "gn:timezone":"America/Mexico_City",
    "iso:country":"MX",
    "name:und_x_variant":[
        "Cruzt\u00f3n"
    ],
    "wof:name":"Cruzton",
    "wof:placetype":"locality",
    "wof:population":868
},
  "geometry": {"coordinates":[-92.43694000000001,16.94917],"type":"Point"}
}