{
  "type": "Feature",
  "properties": {
    "gn:admin1_code":"20",
    "gn:admin2_code":"277.0",
    "gn:asciiname":"La Loma de los Ingenieros",
    "gn:country_code":"MX",
    "gn:dem":1549,
    "gn:feature_class":"P",
    "gn:feature_code":"PPL",
    "gn:name":"La Loma de los Ingenieros",
    "gn:population":9,
    "gn:timezone":"America/Mexico_City",
    "iso:country":"MX",
    "wof:name":"La Loma de los Ingenieros",
    "wof:placetype":"locality",
    "wof:population":9
},
  "geometry": {"coordinates":[-96.90111,16.39333],"type":"Point"}
}