{
  "type": "Feature",
  "properties": {
    "gn:admin1_code":"2.0",
    "gn:admin2_code":"1.0",
    "gn:asciiname":"La Candelaria",
    "gn:cc2":"MX",
    "gn:country_code":"MX",
    "gn:dem":1163,
    "gn:feature_class":"P",
    "gn:feature_code":"PPL",
    "gn:name":"La Candelaria",
    "gn:population":0,
    "gn:timezone":"America/Tijuana",
    "iso:country":"MX",
    "name:ceb_x_preferred":[
        "La Candelaria"
    ],
    "name:deu_x_preferred":[
        "La Candelaria"
    ],
    "name:epo_x_preferred":[
        "La Candelaria"
    ],
    "name:fra_x_preferred":[
        "La Candelaria"
    ],
    "name:glg_x_preferred":[
        "La Candelaria"
    ],
    "name:ita_x_preferred":[
        "La Candelaria"
    ],
    "name:msa_x_preferred":[
        "La Candelaria"
    ],
    "name:nor_x_preferred":[
        "La Candelaria"
    ],
    "name:por_x_preferred":[
        "La Candelaria"
    ],
    "name:spa_x_preferred":[
        "La Candelaria"
    ],
    "name:und_x_variant":[
        "Candelaria",
        "La Candelaria"
    ],
    "wof:name":"La Candelaria",
    "wof:placetype":"locality"
},
  "geometry": {"coordinates":[-116.09999999999999,31.63333],"type":"Point"}
}