{
  "type": "Feature",
  "properties": {
    "gn:admin1_code":"12",
    "gn:admin2_code":"40.0",
    "gn:asciiname":"Polixtepec",
    "gn:country_code":"MX",
    "gn:dem":2050,
    "gn:feature_class":"P",
    "gn:feature_code":"PPL",
    "gn:name":"Polixtepec",
    "gn:population":409,
    "gn:timezone":"America/Mexico_City",
    "iso:country":"MX",
    "wof:name":"Polixtepec",
    "wof:placetype":"locality",
    "wof:population":409
},
  "geometry": {"coordinates":[-99.90278000000001,17.63694],"type":"Point"}
}