{
  "type": "Feature",
  "properties": {
    "gn:admin1_code":"2.0",
    "gn:admin2_code":"1.0",
    "gn:asciiname":"Agua Caliente",
    "gn:country_code":"MX",
    "gn:dem":1046,
    "gn:feature_class":"P",
    "gn:feature_code":"PPL",
    "gn:name":"Agua Caliente",
    "gn:population":0,
    "gn:timezone":"America/Tijuana",
    "iso:country":"MX",
    "name:bre_x_preferred":[
        "Agua Caliente"
    ],
    "name:ceb_x_preferred":[
        "Agua Caliente"
    ],
    "name:deu_x_preferred":[
        "Agua Caliente"
    ],
    "name:spa_x_preferred":[
        "Agua Caliente"
    ],
    "name:swe_x_preferred":[
        "Agua Caliente"
    ],
    "wof:name":"Agua Caliente",
    "wof:placetype":"locality"
},
  "geometry": {"coordinates":[-115.73333,31.56667],"type":"Point"}
}