{
  "type": "Feature",
  "properties": {
    "gn:admin1_code":"10",
    "gn:admin2_code":"26.0",
    "gn:asciiname":"Trigueros",
    "gn:country_code":"MX",
    "gn:dem":2432,
    "gn:feature_class":"P",
    "gn:feature_code":"PPL",
    "gn:name":"Trigueros",
    "gn:population":0,
    "gn:timezone":"America/Monterrey",
    "iso:country":"MX",
    "name:ceb_x_preferred":[
        "Trigueros"
    ],
    "name:deu_x_preferred":[
        "Trigueros"
    ],
    "name:swe_x_preferred":[
        "Trigueros"
    ],
    "name:und_x_variant":[
        "Trigueras"
    ],
    "wof:name":"Trigueros",
    "wof:placetype":"locality"
},
  "geometry": {"coordinates":[-105.69925000000001,24.40052],"type":"Point"}
}