{
  "type": "Feature",
  "properties": {
    "gn:admin1_code":"15",
    "gn:admin2_code":"105.0",
    "gn:asciiname":"El Limo",
    "gn:country_code":"MX",
    "gn:dem":844,
    "gn:feature_class":"P",
    "gn:feature_code":"PPL",
    "gn:name":"El Limo",
    "gn:population":179,
    "gn:timezone":"America/Mexico_City",
    "iso:country":"MX",
    "wof:name":"El Limo",
    "wof:placetype":"locality",
    "wof:population":179
},
  "geometry": {"coordinates":[-100.2996,18.62873],"type":"Point"}
}