{
  "type": "Feature",
  "properties": {
    "gn:admin1_code":"13",
    "gn:admin2_code":"14",
    "gn:asciiname":"Metlatepetl",
    "gn:country_code":"MX",
    "gn:dem":1067,
    "gn:feature_class":"P",
    "gn:feature_code":"PPL",
    "gn:name":"Metlat\u00e9petl",
    "gn:population":29,
    "gn:timezone":"America/Mexico_City",
    "iso:country":"MX",
    "name:und_x_variant":[
        "Metlat\u00e9petl"
    ],
    "wof:name":"Metlatepetl",
    "wof:placetype":"locality",
    "wof:population":29
},
  "geometry": {"coordinates":[-98.57231,20.91214],"type":"Point"}
}