{
  "type": "Feature",
  "properties": {
    "gn:admin1_code":"28",
    "gn:admin2_code":"22.0",
    "gn:asciiname":"El Huisachal",
    "gn:country_code":"MX",
    "gn:dem":9,
    "gn:feature_class":"P",
    "gn:feature_code":"PPL",
    "gn:name":"El Huisachal",
    "gn:population":112,
    "gn:timezone":"America/Matamoros",
    "iso:country":"MX",
    "name:spa_x_preferred":[
        "El Huisachal"
    ],
    "name:und_x_variant":[
        "El Huizachal"
    ],
    "wof:name":"El Huisachal",
    "wof:placetype":"locality",
    "wof:population":112
},
  "geometry": {"coordinates":[-97.29065,25.82358],"type":"Point"}
}