{
  "type": "Feature",
  "properties": {
    "gn:admin1_code":"24.0",
    "gn:admin2_code":"34.0",
    "gn:asciiname":"Rancho Cinco Estrellas",
    "gn:country_code":"MX",
    "gn:dem":42,
    "gn:feature_class":"P",
    "gn:feature_code":"PPL",
    "gn:name":"Rancho Cinco Estrellas",
    "gn:population":0,
    "gn:timezone":"America/Mexico_City",
    "iso:country":"MX",
    "name:spa_x_preferred":[
        "Rancho Cinco Estrellas"
    ],
    "wof:name":"Rancho Cinco Estrellas",
    "wof:placetype":"locality"
},
  "geometry": {"coordinates":[-98.62663000000001,21.67229],"type":"Point"}
}