{
  "type": "Feature",
  "properties": {
    "gn:admin1_code":"14",
    "gn:admin2_code":"89.0",
    "gn:asciiname":"San Miguel del Zapote",
    "gn:country_code":"MX",
    "gn:dem":1353,
    "gn:feature_class":"P",
    "gn:feature_code":"PPL",
    "gn:name":"San Miguel del Zapote",
    "gn:population":0,
    "gn:timezone":"America/Mexico_City",
    "iso:country":"MX",
    "wof:name":"San Miguel del Zapote",
    "wof:placetype":"locality"
},
  "geometry": {"coordinates":[-103.53346000000001,20.13176],"type":"Point"}
}