{
  "type": "Feature",
  "properties": {
    "gn:admin1_code":"10",
    "gn:asciiname":"Aguacaliente",
    "gn:country_code":"MX",
    "gn:dem":1255,
    "gn:feature_class":"P",
    "gn:feature_code":"PPL",
    "gn:name":"Aguacaliente",
    "gn:population":0,
    "gn:timezone":"America/Monterrey",
    "iso:country":"MX",
    "name:spa_x_preferred":[
        "Aguacaliente"
    ],
    "wof:name":"Aguacaliente",
    "wof:placetype":"locality"
},
  "geometry": {"coordinates":[-106.57447000000001,25.66008],"type":"Point"}
}