{
  "type": "Feature",
  "properties": {
    "gn:admin1_code":"19.0",
    "gn:asciiname":"Los Gonzalez",
    "gn:country_code":"MX",
    "gn:dem":489,
    "gn:feature_class":"P",
    "gn:feature_code":"PPL",
    "gn:name":"Los Gonz\u00e1lez",
    "gn:population":0,
    "gn:timezone":"America/Monterrey",
    "iso:country":"MX",
    "name:spa_x_preferred":[
        "Los Gonz\u00e1lez"
    ],
    "wof:name":"Los Gonzalez",
    "wof:placetype":"locality"
},
  "geometry": {"coordinates":[-100.37214,25.92853],"type":"Point"}
}