{
  "type": "Feature",
  "properties": {
    "gn:admin1_code":"5.0",
    "gn:admin2_code":"59.0",
    "gn:asciiname":"Reparosan",
    "gn:country_code":"MX",
    "gn:dem":973,
    "gn:feature_class":"P",
    "gn:feature_code":"PPL",
    "gn:name":"Reparosan",
    "gn:population":0,
    "gn:timezone":"America/Mexico_City",
    "iso:country":"MX",
    "name:spa_x_preferred":[
        "Reparosan"
    ],
    "wof:name":"Reparosan",
    "wof:placetype":"locality"
},
  "geometry": {"coordinates":[-91.93720999999999,16.92222000000001],"type":"Point"}
}