{
  "type": "Feature",
  "properties": {
    "gn:admin1_code":"10",
    "gn:admin2_code":"27.0",
    "gn:asciiname":"Quinta",
    "gn:country_code":"MX",
    "gn:dem":1676,
    "gn:feature_class":"P",
    "gn:feature_code":"PPL",
    "gn:name":"Quinta",
    "gn:population":0,
    "gn:timezone":"America/Monterrey",
    "iso:country":"MX",
    "name:ceb_x_preferred":[
        "Quinta"
    ],
    "name:ces_x_preferred":[
        "Kvinta"
    ],
    "name:deu_x_preferred":[
        "Quinta"
    ],
    "name:fra_x_preferred":[
        "Quinte"
    ],
    "name:glg_x_preferred":[
        "Quinta"
    ],
    "name:ita_x_preferred":[
        "Quinta"
    ],
    "name:por_x_preferred":[
        "Quinta"
    ],
    "name:rus_x_preferred":[
        "\u041a\u0438\u043d\u0442\u0430"
    ],
    "name:spa_x_preferred":[
        "Quinta"
    ],
    "name:srp_x_preferred":[
        "\u041a\u0432\u0438\u043d\u0442\u0430"
    ],
    "name:swe_x_preferred":[
        "Quinta"
    ],
    "wof:name":"Quinta",
    "wof:placetype":"locality"
},
  "geometry": {"coordinates":[-102.75,24.66667],"type":"Point"}
}