{
  "type": "Feature",
  "properties": {
    "gn:admin1_code":"19.0",
    "gn:admin2_code":"17.0",
    "gn:asciiname":"El Canelito",
    "gn:country_code":"MX",
    "gn:dem":1882,
    "gn:feature_class":"P",
    "gn:feature_code":"PPL",
    "gn:name":"El Canelito",
    "gn:population":0,
    "gn:timezone":"America/Monterrey",
    "iso:country":"MX",
    "name:spa_x_preferred":[
        "El Canelito"
    ],
    "wof:name":"El Canelito",
    "wof:placetype":"locality"
},
  "geometry": {"coordinates":[-100.71861,24.80278],"type":"Point"}
}