{
  "type": "Feature",
  "properties": {
    "gn:admin1_code":"14.0",
    "gn:admin2_code":"122.0",
    "gn:asciiname":"La Piedra del Sacrificio",
    "gn:country_code":"MX",
    "gn:dem":959,
    "gn:feature_class":"P",
    "gn:feature_code":"PPL",
    "gn:name":"La Piedra del Sacrific\u00edo",
    "gn:population":0,
    "gn:timezone":"America/Mexico_City",
    "iso:country":"MX",
    "name:spa_x_preferred":[
        "La Piedra del Sacrific\u00edo"
    ],
    "wof:name":"La Piedra del Sacrificio",
    "wof:placetype":"locality"
},
  "geometry": {"coordinates":[-103.80141999999999,19.47824],"type":"Point"}
}