{
  "type": "Feature",
  "properties": {
    "gn:admin1_code":"17",
    "gn:admin2_code":"31",
    "gn:asciiname":"Colonia Plan de Ayala",
    "gn:country_code":"MX",
    "gn:dem":925,
    "gn:feature_class":"P",
    "gn:feature_code":"PPL",
    "gn:name":"Colonia Plan de Ayala",
    "gn:population":20,
    "gn:timezone":"America/Mexico_City",
    "iso:country":"MX",
    "wof:name":"Colonia Plan de Ayala",
    "wof:placetype":"locality",
    "wof:population":20
},
  "geometry": {"coordinates":[-99.18416999999999,18.66111],"type":"Point"}
}