{
  "type": "Feature",
  "properties": {
    "gn:admin1_code":"17",
    "gn:admin2_code":"29.0",
    "gn:asciiname":"Colonia Santa Lucia (Ampliacion Itzamatitlan)",
    "gn:country_code":"MX",
    "gn:dem":1270,
    "gn:feature_class":"P",
    "gn:feature_code":"PPL",
    "gn:name":"Colonia Santa Luc\u00eda (Ampliaci\u00f3n Itzamatitl\u00e1n)",
    "gn:population":133,
    "gn:timezone":"America/Mexico_City",
    "iso:country":"MX",
    "name:und_x_variant":[
        "Colonia Santa Luc\u00eda (Ampliaci\u00f3n Itzamatitl\u00e1n)"
    ],
    "wof:name":"Colonia Santa Lucia (Ampliacion Itzamatitlan)",
    "wof:placetype":"locality",
    "wof:population":133
},
  "geometry": {"coordinates":[-99.01701,18.90882],"type":"Point"}
}