{
  "type": "Feature",
  "properties": {
    "gn:admin1_code":"26",
    "gn:admin2_code":"18",
    "gn:asciiname":"Alfonso Castro",
    "gn:country_code":"MX",
    "gn:dem":24,
    "gn:feature_class":"P",
    "gn:feature_code":"PPL",
    "gn:name":"Alfonso Castro",
    "gn:population":20,
    "gn:timezone":"America/Hermosillo",
    "iso:country":"MX",
    "wof:name":"Alfonso Castro",
    "wof:placetype":"locality",
    "wof:population":20
},
  "geometry": {"coordinates":[-110.01278000000001,27.39056],"type":"Point"}
}