{
  "type": "Feature",
  "properties": {
    "gn:admin1_code":"11",
    "gn:admin2_code":"18.0",
    "gn:asciiname":"Lomo de Toro",
    "gn:country_code":"MX",
    "gn:dem":1734,
    "gn:feature_class":"P",
    "gn:feature_code":"PPL",
    "gn:name":"Lomo de Toro",
    "gn:population":5,
    "gn:timezone":"America/Mexico_City",
    "iso:country":"MX",
    "wof:name":"Lomo de Toro",
    "wof:placetype":"locality",
    "wof:population":5
},
  "geometry": {"coordinates":[-101.02249999999999,20.285],"type":"Point"}
}