{
  "type": "Feature",
  "properties": {
    "gn:admin1_code":"7",
    "gn:admin2_code":"9.0",
    "gn:asciiname":"Finisterre",
    "gn:country_code":"MX",
    "gn:dem":1099,
    "gn:feature_class":"P",
    "gn:feature_code":"PPL",
    "gn:name":"Finisterre",
    "gn:population":0,
    "gn:timezone":"America/Monterrey",
    "iso:country":"MX",
    "name:arg_x_preferred":[
        "Finisterre"
    ],
    "name:ceb_x_preferred":[
        "Finisterre"
    ],
    "name:deu_x_preferred":[
        "Finisterre"
    ],
    "name:fra_x_preferred":[
        "Finisterre"
    ],
    "name:glg_x_preferred":[
        "Finisterre"
    ],
    "name:ita_x_preferred":[
        "Finisterre"
    ],
    "name:rus_x_preferred":[
        "\u0424\u0438\u043d\u0438\u0441\u0442\u0435\u0440\u0440\u0435"
    ],
    "name:spa_x_preferred":[
        "Finisterre"
    ],
    "name:swe_x_preferred":[
        "Finisterre"
    ],
    "wof:name":"Finisterre",
    "wof:placetype":"locality"
},
  "geometry": {"coordinates":[-103.21876,25.98635],"type":"Point"}
}