{
  "type": "Feature",
  "properties": {
    "gn:admin1_code":"5",
    "gn:admin2_code":"64.0",
    "gn:asciiname":"El Pozo",
    "gn:country_code":"MX",
    "gn:dem":1959,
    "gn:feature_class":"P",
    "gn:feature_code":"PPL",
    "gn:name":"El Pozo",
    "gn:population":135,
    "gn:timezone":"America/Mexico_City",
    "iso:country":"MX",
    "name:deu_x_preferred":[
        "El Pozo"
    ],
    "name:srp_x_preferred":[
        "\u0415\u043b \u041f\u043e\u0437\u043e"
    ],
    "wof:name":"El Pozo",
    "wof:placetype":"locality",
    "wof:population":135
},
  "geometry": {"coordinates":[-92.33944,16.80056],"type":"Point"}
}