{
  "type": "Feature",
  "properties": {
    "gn:admin1_code":"12",
    "gn:admin2_code":"22.0",
    "gn:asciiname":"Tierras Blancas",
    "gn:country_code":"MX",
    "gn:dem":1510,
    "gn:feature_class":"P",
    "gn:feature_code":"PPL",
    "gn:name":"Tierras Blancas",
    "gn:population":0,
    "gn:timezone":"America/Mexico_City",
    "iso:country":"MX",
    "name:spa_x_preferred":[
        "Tierras Blancas"
    ],
    "wof:name":"Tierras Blancas",
    "wof:placetype":"locality"
},
  "geometry": {"coordinates":[-101.2808,18.15743],"type":"Point"}
}