{
  "type": "Feature",
  "properties": {
    "gn:admin1_code":"17",
    "gn:admin2_code":"29.0",
    "gn:asciiname":"Rancho el Toro",
    "gn:country_code":"MX",
    "gn:dem":1287,
    "gn:feature_class":"P",
    "gn:feature_code":"PPL",
    "gn:name":"Rancho el Toro",
    "gn:population":8,
    "gn:timezone":"America/Mexico_City",
    "iso:country":"MX",
    "wof:name":"Rancho el Toro",
    "wof:placetype":"locality",
    "wof:population":8
},
  "geometry": {"coordinates":[-99.10278,18.86333],"type":"Point"}
}