{
  "type": "Feature",
  "properties": {
    "gn:admin1_code":"16.0",
    "gn:admin2_code":"8.0",
    "gn:asciiname":"El Tanimbre Grande",
    "gn:country_code":"MX",
    "gn:dem":159,
    "gn:feature_class":"P",
    "gn:feature_code":"PPL",
    "gn:name":"El Tanimbre Grande",
    "gn:population":0,
    "gn:timezone":"America/Mexico_City",
    "iso:country":"MX",
    "name:spa_x_preferred":[
        "El Tanimbre Grande"
    ],
    "wof:name":"El Tanimbre Grande",
    "wof:placetype":"locality"
},
  "geometry": {"coordinates":[-103.52840999999999,18.57791],"type":"Point"}
}