{
  "type": "Feature",
  "properties": {
    "gn:admin1_code":"30.0",
    "gn:admin2_code":"210.0",
    "gn:asciiname":"Rio Verde",
    "gn:country_code":"MX",
    "gn:dem":117,
    "gn:feature_class":"P",
    "gn:feature_code":"PPL",
    "gn:name":"R\u00edo Verde",
    "gn:population":0,
    "gn:timezone":"America/Mexico_City",
    "iso:country":"MX",
    "name:spa_x_preferred":[
        "R\u00edo Verde"
    ],
    "wof:name":"Rio Verde",
    "wof:placetype":"locality"
},
  "geometry": {"coordinates":[-94.15846000000001,17.27925],"type":"Point"}
}