{
  "type": "Feature",
  "properties": {
    "gn:admin1_code":"7",
    "gn:admin2_code":"17.0",
    "gn:asciiname":"Vicente Guerrero",
    "gn:country_code":"MX",
    "gn:dem":1124,
    "gn:feature_class":"P",
    "gn:feature_code":"PPL",
    "gn:name":"Vicente Guerrero",
    "gn:population":0,
    "gn:timezone":"America/Monterrey",
    "iso:country":"MX",
    "name:ara_x_preferred":[
        "\u0641\u064a\u0633\u0646\u062a\u064a \u063a\u064a\u0631\u064a\u0631\u0648"
    ],
    "name:ast_x_preferred":[
        "Vicente Guerrero"
    ],
    "name:aym_x_preferred":[
        "Vicente Guerrero"
    ],
    "name:bre_x_preferred":[
        "Vicente Guerrero"
    ],
    "name:cat_x_preferred":[
        "Vicente Guerrero"
    ],
    "name:deu_x_preferred":[
        "Vicente Guerrero"
    ],
    "name:fra_x_preferred":[
        "Vicente Guerrero"
    ],
    "name:hun_x_preferred":[
        "Vicente Guerrero"
    ],
    "name:ido_x_preferred":[
        "Vicente Guerrero"
    ],
    "name:ita_x_preferred":[
        "Vicente Guerrero"
    ],
    "name:jpn_x_preferred":[
        "\u30d3\u30bb\u30f3\u30c6\u30fb\u30b2\u30ec\u30ed"
    ],
    "name:kor_x_preferred":[
        "\ube44\uc13c\ud14c \uac8c\ub808\ub85c"
    ],
    "name:lat_x_preferred":[
        "Vincentius Guerrero"
    ],
    "name:mkd_x_preferred":[
        "\u0412\u0438\u043d\u0441\u0435\u043d\u0442\u0435 \u0413\u0435\u0440\u0435\u0440\u043e"
    ],
    "name:msa_x_preferred":[
        "Vicente Guerrero"
    ],
    "name:nld_x_preferred":[
        "Vicente Guerrero"
    ],
    "name:nno_x_preferred":[
        "Vicente Guerrero"
    ],
    "name:nor_x_preferred":[
        "Vicente Guerrero"
    ],
    "name:pol_x_preferred":[
        "Vicente Guerrero"
    ],
    "name:por_x_preferred":[
        "Vicente Guerrero"
    ],
    "name:que_x_preferred":[
        "Vicente Guerrero"
    ],
    "name:rus_x_preferred":[
        "\u0412\u0438\u043d\u0441\u0435\u043d\u0442\u0435-\u0413\u0435\u0440\u0440\u0435\u0440\u043e"
    ],
    "name:rus_x_variant":[
        "\u0413\u0435\u0440\u0440\u0435\u0440\u043e"
    ],
    "name:sco_x_preferred":[
        "Vicente Guerrero"
    ],
    "name:spa_x_preferred":[
        "Vicente Guerrero"
    ],
    "name:srp_x_preferred":[
        "\u0412\u0438\u0441\u0435\u043d\u0442\u0435 \u0413\u0435\u0440\u0435\u0440\u043e"
    ],
    "name:swe_x_preferred":[
        "Vicente Guerrero"
    ],
    "name:tur_x_preferred":[
        "Vicente Guerrero"
    ],
    "name:ukr_x_preferred":[
        "\u0412\u0456\u0441\u0435\u043d\u0442\u0435-\u0413\u0435\u0440\u0440\u0435\u0440\u043e"
    ],
    "name:urd_x_preferred":[
        "\u0648\u06cc\u0633\u06cc\u0646\u0679 \u06af\u0631\u06cc\u0631\u0648"
    ],
    "name:vie_x_preferred":[
        "Vicente Guerrero"
    ],
    "name:yor_x_preferred":[
        "Vicente Guerrero"
    ],
    "name:zho_cn_x_preferred":[
        "\u7ef4\u68ee\u7279\u683c\u96f7\u7f57"
    ],
    "name:zho_tw_x_preferred":[
        "\u7dad\u68ee\u7279\u00b7\u683c\u96f7\u7f85"
    ],
    "name:zho_x_preferred":[
        "\u6bd4\u68ee\u7279\u00b7\u683c\u96f7\u7f57"
    ],
    "wof:name":"Vicente Guerrero",
    "wof:placetype":"locality"
},
  "geometry": {"coordinates":[-103.29609000000001,25.49368],"type":"Point"}
}