{
  "type": "Feature",
  "properties": {
    "gn:admin1_code":"28",
    "gn:admin2_code":"22.0",
    "gn:asciiname":"Isla Puntilla Norte",
    "gn:country_code":"MX",
    "gn:dem":4,
    "gn:feature_class":"P",
    "gn:feature_code":"PPL",
    "gn:name":"Isla Puntilla Norte",
    "gn:population":101,
    "gn:timezone":"America/Matamoros",
    "iso:country":"MX",
    "wof:name":"Isla Puntilla Norte",
    "wof:placetype":"locality",
    "wof:population":101
},
  "geometry": {"coordinates":[-97.45111,25.24472],"type":"Point"}
}