{
  "type": "Feature",
  "properties": {
    "gn:admin1_code":"16.0",
    "gn:admin2_code":"58.0",
    "gn:asciiname":"Nuevo San Salvador Paracutin",
    "gn:country_code":"MX",
    "gn:dem":2778,
    "gn:feature_class":"P",
    "gn:feature_code":"PPL",
    "gn:name":"Nuevo San Salvador Paracut\u00edn",
    "gn:population":0,
    "gn:timezone":"America/Mexico_City",
    "iso:country":"MX",
    "name:spa_x_preferred":[
        "Nuevo San Salvador Paracut\u00edn"
    ],
    "name:spa_x_variant":[
        "La Escondida"
    ],
    "wof:name":"Nuevo San Salvador Paracutin",
    "wof:placetype":"locality"
},
  "geometry": {"coordinates":[-102.25679,19.45902],"type":"Point"}
}