{
  "type": "Feature",
  "properties": {
    "gn:admin1_code":"13",
    "gn:asciiname":"Agua Buena",
    "gn:country_code":"MX",
    "gn:dem":388,
    "gn:feature_class":"P",
    "gn:feature_code":"PPL",
    "gn:name":"Agua Buena",
    "gn:population":0,
    "gn:timezone":"America/Mexico_City",
    "iso:country":"MX",
    "name:spa_x_preferred":[
        "Agua Buena"
    ],
    "wof:name":"Agua Buena",
    "wof:placetype":"locality"
},
  "geometry": {"coordinates":[-98.95988,21.31327000000001],"type":"Point"}
}