{
  "type": "Feature",
  "properties": {
    "gn:admin1_code":"13",
    "gn:admin2_code":"11.0",
    "gn:asciiname":"Pochoica",
    "gn:country_code":"MX",
    "gn:dem":189,
    "gn:feature_class":"P",
    "gn:feature_code":"PPL",
    "gn:name":"Pocho\u00edca",
    "gn:population":60,
    "gn:timezone":"America/Mexico_City",
    "iso:country":"MX",
    "name:und_x_variant":[
        "Pocho\u00edca"
    ],
    "wof:name":"Pochoica",
    "wof:placetype":"locality",
    "wof:population":60
},
  "geometry": {"coordinates":[-98.37121999999999,21.03497],"type":"Point"}
}