{
  "type": "Feature",
  "properties": {
    "gn:admin1_code":"25",
    "gn:admin2_code":"6.0",
    "gn:asciiname":"El Chirimollo",
    "gn:country_code":"MX",
    "gn:dem":505,
    "gn:feature_class":"P",
    "gn:feature_code":"PPL",
    "gn:name":"El Chirimollo",
    "gn:population":6,
    "gn:timezone":"America/Monterrey",
    "iso:country":"MX",
    "wof:name":"El Chirimollo",
    "wof:placetype":"locality",
    "wof:population":6
},
  "geometry": {"coordinates":[-106.95119,24.85424],"type":"Point"}
}