{
  "type": "Feature",
  "properties": {
    "gn:admin1_code":"30.0",
    "gn:admin2_code":"157.0",
    "gn:asciiname":"El Mante",
    "gn:country_code":"MX",
    "gn:dem":95,
    "gn:feature_class":"P",
    "gn:feature_code":"PPL",
    "gn:name":"El Mante",
    "gn:population":488,
    "gn:timezone":"America/Mexico_City",
    "iso:country":"MX",
    "name:spa_x_preferred":[
        "El Mante"
    ],
    "wof:name":"El Mante",
    "wof:placetype":"locality",
    "wof:population":488
},
  "geometry": {"coordinates":[-97.70694,20.70611],"type":"Point"}
}