{
  "type": "Feature",
  "properties": {
    "gn:admin1_code":"12.0",
    "gn:admin2_code":"6.0",
    "gn:asciiname":"Valle Seco",
    "gn:country_code":"MX",
    "gn:dem":1345,
    "gn:feature_class":"P",
    "gn:feature_code":"PPL",
    "gn:name":"Valle Seco",
    "gn:population":0,
    "gn:timezone":"America/Mexico_City",
    "iso:country":"MX",
    "name:spa_x_preferred":[
        "Valle Seco"
    ],
    "wof:name":"Valle Seco",
    "wof:placetype":"locality"
},
  "geometry": {"coordinates":[-99.98582,18.05166],"type":"Point"}
}