{
  "type": "Feature",
  "properties": {
    "gn:admin1_code":"18",
    "gn:admin2_code":"9",
    "gn:asciiname":"Arroyo Barbon",
    "gn:country_code":"MX",
    "gn:dem":710,
    "gn:feature_class":"P",
    "gn:feature_code":"PPL",
    "gn:name":"Arroyo Barb\u00f3n",
    "gn:population":23,
    "gn:timezone":"America/Mazatlan",
    "iso:country":"MX",
    "name:und_x_variant":[
        "Arroyo Barb\u00f3n"
    ],
    "wof:name":"Arroyo Barbon",
    "wof:placetype":"locality",
    "wof:population":23
},
  "geometry": {"coordinates":[-104.65222,21.92889],"type":"Point"}
}