{
  "type": "Feature",
  "properties": {
    "gn:admin1_code":"30",
    "gn:admin2_code":"205.0",
    "gn:asciiname":"Ejido los Marcos",
    "gn:country_code":"MX",
    "gn:dem":75,
    "gn:feature_class":"P",
    "gn:feature_code":"PPL",
    "gn:name":"Ejido los Marcos",
    "gn:population":0,
    "gn:timezone":"America/Mexico_City",
    "iso:country":"MX",
    "name:und_x_variant":[
        "Los Marcos",
        "Alto el Ojite"
    ],
    "wof:name":"Ejido los Marcos",
    "wof:placetype":"locality"
},
  "geometry": {"coordinates":[-98.52515,21.65637000000001],"type":"Point"}
}