{
  "type": "Feature",
  "properties": {
    "gn:admin1_code":"21",
    "gn:admin2_code":"186.0",
    "gn:asciiname":"Jiliapa",
    "gn:country_code":"MX",
    "gn:dem":1791,
    "gn:feature_class":"P",
    "gn:feature_code":"PPL",
    "gn:name":"Jiliapa",
    "gn:population":0,
    "gn:timezone":"America/Mexico_City",
    "iso:country":"MX",
    "name:spa_x_preferred":[
        "Jiliapa"
    ],
    "wof:name":"Jiliapa",
    "wof:placetype":"locality"
},
  "geometry": {"coordinates":[-97.50375,19.87403],"type":"Point"}
}