{
  "type": "Feature",
  "properties": {
    "gn:admin1_code":"20",
    "gn:admin2_code":"105.0",
    "gn:asciiname":"Guadalupe de las Flores",
    "gn:country_code":"MX",
    "gn:dem":2173,
    "gn:feature_class":"P",
    "gn:feature_code":"PPL",
    "gn:name":"Guadalupe de las Flores",
    "gn:population":231,
    "gn:timezone":"America/Mexico_City",
    "iso:country":"MX",
    "wof:name":"Guadalupe de las Flores",
    "wof:placetype":"locality",
    "wof:population":231
},
  "geometry": {"coordinates":[-97.73833,17.53944],"type":"Point"}
}