{
  "type": "Feature",
  "properties": {
    "gn:admin1_code":"12",
    "gn:admin2_code":"1.0",
    "gn:asciiname":"Tres Palos",
    "gn:country_code":"MX",
    "gn:dem":13,
    "gn:feature_class":"P",
    "gn:feature_code":"PPL",
    "gn:name":"Tres Palos",
    "gn:population":0,
    "gn:timezone":"America/Mexico_City",
    "iso:country":"MX",
    "name:spa_x_preferred":[
        "Tres Palos"
    ],
    "wof:name":"Tres Palos",
    "wof:placetype":"locality"
},
  "geometry": {"coordinates":[-99.77813,16.82959],"type":"Point"}
}