{
  "type": "Feature",
  "properties": {
    "gn:admin1_code":"21.0",
    "gn:admin2_code":"66.0",
    "gn:asciiname":"San Rafael la Paz",
    "gn:country_code":"MX",
    "gn:dem":1094,
    "gn:feature_class":"P",
    "gn:feature_code":"PPL",
    "gn:name":"San Rafael la Paz",
    "gn:population":0,
    "gn:timezone":"America/Mexico_City",
    "iso:country":"MX",
    "name:spa_x_preferred":[
        "San Rafael la Paz"
    ],
    "wof:name":"San Rafael la Paz",
    "wof:placetype":"locality"
},
  "geometry": {"coordinates":[-98.12544,18.09679],"type":"Point"}
}