{
  "type": "Feature",
  "properties": {
    "gn:admin1_code":"10",
    "gn:admin2_code":"34.0",
    "gn:asciiname":"Mesa de Rafael",
    "gn:country_code":"MX",
    "gn:dem":2467,
    "gn:feature_class":"P",
    "gn:feature_code":"PPL",
    "gn:name":"Mesa de Rafael",
    "gn:population":0,
    "gn:timezone":"America/Monterrey",
    "iso:country":"MX",
    "name:spa_x_preferred":[
        "Mesa de Rafael"
    ],
    "name:und_x_variant":[
        "Mesa San Rafael"
    ],
    "wof:name":"Mesa de Rafael",
    "wof:placetype":"locality"
},
  "geometry": {"coordinates":[-106.75745000000001,25.48763],"type":"Point"}
}