{
  "type": "Feature",
  "properties": {
    "gn:admin1_code":"19.0",
    "gn:admin2_code":"27.0",
    "gn:asciiname":"Llanito Redondo",
    "gn:country_code":"MX",
    "gn:dem":143,
    "gn:feature_class":"P",
    "gn:feature_code":"PPL",
    "gn:name":"Llanito Redondo",
    "gn:population":0,
    "gn:timezone":"America/Monterrey",
    "iso:country":"MX",
    "name:spa_x_preferred":[
        "Llanito Redondo"
    ],
    "wof:name":"Llanito Redondo",
    "wof:placetype":"locality"
},
  "geometry": {"coordinates":[-99.32141,25.85301],"type":"Point"}
}