{
  "type": "Feature",
  "properties": {
    "gn:admin1_code":"15.0",
    "gn:admin2_code":"123.0",
    "gn:asciiname":"Arroyo Seco",
    "gn:country_code":"MX",
    "gn:dem":1152,
    "gn:feature_class":"P",
    "gn:feature_code":"PPL",
    "gn:name":"Arroyo Seco",
    "gn:population":0,
    "gn:timezone":"America/Mexico_City",
    "iso:country":"MX",
    "name:ceb_x_preferred":[
        "Arroyo Seco"
    ],
    "name:deu_x_preferred":[
        "Arroyo Seco"
    ],
    "name:fra_x_preferred":[
        "Arroyo Seco"
    ],
    "name:rus_x_preferred":[
        "\u0410\u0440\u0440\u043e\u0439\u043e-\u0421\u0435\u043a\u043e"
    ],
    "name:spa_x_preferred":[
        "Arroyo Seco"
    ],
    "name:swe_x_preferred":[
        "Arroyo Seco"
    ],
    "wof:name":"Arroyo Seco",
    "wof:placetype":"locality"
},
  "geometry": {"coordinates":[-100.25629000000001,18.93316],"type":"Point"}
}