{
  "type": "Feature",
  "properties": {
    "gn:admin1_code":"26",
    "gn:admin2_code":"21.0",
    "gn:asciiname":"El Pozo de la Pitahaya",
    "gn:country_code":"MX",
    "gn:dem":346,
    "gn:feature_class":"P",
    "gn:feature_code":"PPL",
    "gn:name":"El Pozo de la Pitahaya",
    "gn:population":0,
    "gn:timezone":"America/Hermosillo",
    "iso:country":"MX",
    "name:spa_x_preferred":[
        "El Pozo de la Pitahaya"
    ],
    "name:und_x_variant":[
        "Pitahaya",
        "Rancho El Pozo de la Pitahaya",
        "Pozo de la Pitahaya"
    ],
    "wof:name":"El Pozo de la Pitahaya",
    "wof:placetype":"locality"
},
  "geometry": {"coordinates":[-110.58859,28.70626],"type":"Point"}
}