{
  "type": "Feature",
  "properties": {
    "gn:admin1_code":"4.0",
    "gn:admin2_code":"3.0",
    "gn:asciiname":"Los Pasos",
    "gn:country_code":"MX",
    "gn:dem":18,
    "gn:feature_class":"P",
    "gn:feature_code":"PPL",
    "gn:name":"Los Pasos",
    "gn:population":0,
    "gn:timezone":"America/Merida",
    "iso:country":"MX",
    "name:spa_x_preferred":[
        "Los Pasos"
    ],
    "wof:name":"Los Pasos",
    "wof:placetype":"locality"
},
  "geometry": {"coordinates":[-90.99165000000001,18.71451],"type":"Point"}
}