{
  "type": "Feature",
  "properties": {
    "gn:admin1_code":"23",
    "gn:asciiname":"San Narciso",
    "gn:country_code":"MX",
    "gn:dem":48,
    "gn:feature_class":"P",
    "gn:feature_code":"PPL",
    "gn:name":"San Narciso",
    "gn:population":0,
    "gn:timezone":"America/Cancun",
    "iso:country":"MX",
    "name:spa_x_preferred":[
        "San Narciso"
    ],
    "wof:name":"San Narciso",
    "wof:placetype":"locality"
},
  "geometry": {"coordinates":[-89.05069,19.78208],"type":"Point"}
}