{
  "type": "Feature",
  "properties": {
    "gn:admin1_code":"15",
    "gn:admin2_code":"5.0",
    "gn:asciiname":"Loma de Guadalupe",
    "gn:country_code":"MX",
    "gn:dem":2822,
    "gn:feature_class":"P",
    "gn:feature_code":"PPL",
    "gn:name":"Loma de Guadalupe",
    "gn:population":640,
    "gn:timezone":"America/Mexico_City",
    "iso:country":"MX",
    "wof:name":"Loma de Guadalupe",
    "wof:placetype":"locality",
    "wof:population":640
},
  "geometry": {"coordinates":[-99.80194,19.29667],"type":"Point"}
}