{
  "type": "Feature",
  "properties": {
    "gn:admin1_code":"12",
    "gn:admin2_code":"43.0",
    "gn:asciiname":"Mini Nuhuma",
    "gn:country_code":"MX",
    "gn:dem":2086,
    "gn:feature_class":"P",
    "gn:feature_code":"PPL",
    "gn:name":"Mini Nuhuma",
    "gn:population":287,
    "gn:timezone":"America/Mexico_City",
    "iso:country":"MX",
    "wof:name":"Mini Nuhuma",
    "wof:placetype":"locality",
    "wof:population":287
},
  "geometry": {"coordinates":[-98.37193000000001,17.19666],"type":"Point"}
}