{
  "type": "Feature",
  "properties": {
    "gn:admin1_code":"23",
    "gn:admin2_code":"7.0",
    "gn:asciiname":"Unidad Ganadera Emiliano Zapata",
    "gn:country_code":"MX",
    "gn:dem":14,
    "gn:feature_class":"P",
    "gn:feature_code":"PPL",
    "gn:name":"Unidad Ganadera Emiliano Zapata",
    "gn:population":0,
    "gn:timezone":"America/Cancun",
    "iso:country":"MX",
    "wof:name":"Unidad Ganadera Emiliano Zapata",
    "wof:placetype":"locality"
},
  "geometry": {"coordinates":[-87.37917,21.225],"type":"Point"}
}