{
  "type": "Feature",
  "properties": {
    "gn:admin1_code":"6.0",
    "gn:asciiname":"El Sombrerete",
    "gn:country_code":"MX",
    "gn:dem":1211,
    "gn:feature_class":"P",
    "gn:feature_code":"PPL",
    "gn:name":"El Sombrerete",
    "gn:population":0,
    "gn:timezone":"America/Chihuahua",
    "iso:country":"MX",
    "name:spa_x_preferred":[
        "El Sombrerete"
    ],
    "name:spa_x_variant":[
        "Sombrete"
    ],
    "wof:name":"El Sombrerete",
    "wof:placetype":"locality"
},
  "geometry": {"coordinates":[-105.40792,28.16922000000001],"type":"Point"}
}