{
  "type": "Feature",
  "properties": {
    "gn:admin1_code":"26",
    "gn:admin2_code":"18.0",
    "gn:asciiname":"Palo Fierral",
    "gn:country_code":"MX",
    "gn:dem":104,
    "gn:feature_class":"P",
    "gn:feature_code":"PPL",
    "gn:name":"Palo Fierral",
    "gn:population":0,
    "gn:timezone":"America/Hermosillo",
    "iso:country":"MX",
    "name:spa_x_preferred":[
        "Palo Fierral"
    ],
    "wof:name":"Palo Fierral",
    "wof:placetype":"locality"
},
  "geometry": {"coordinates":[-109.81610999999999,27.60333],"type":"Point"}
}