{
  "type": "Feature",
  "properties": {
    "gn:admin1_code":"5",
    "gn:admin2_code":"56",
    "gn:asciiname":"Baamnaltic",
    "gn:country_code":"MX",
    "gn:dem":2123,
    "gn:feature_class":"P",
    "gn:feature_code":"PPL",
    "gn:name":"Baamnaltic",
    "gn:population":50,
    "gn:timezone":"America/Mexico_City",
    "iso:country":"MX",
    "wof:name":"Baamnaltic",
    "wof:placetype":"locality",
    "wof:population":50
},
  "geometry": {"coordinates":[-92.61583,16.87361],"type":"Point"}
}