{
  "type": "Feature",
  "properties": {
    "gn:admin1_code":"14.0",
    "gn:admin2_code":"85.0",
    "gn:asciiname":"Los Tabaquitos",
    "gn:country_code":"MX",
    "gn:dem":1335,
    "gn:feature_class":"P",
    "gn:feature_code":"PPL",
    "gn:name":"Los Tabaquitos",
    "gn:population":0,
    "gn:timezone":"America/Mexico_City",
    "iso:country":"MX",
    "name:spa_x_preferred":[
        "Los Tabaquitos"
    ],
    "wof:name":"Los Tabaquitos",
    "wof:placetype":"locality"
},
  "geometry": {"coordinates":[-103.16298999999999,19.48555],"type":"Point"}
}