{
  "type": "Feature",
  "properties": {
    "gn:admin1_code":"19.0",
    "gn:asciiname":"Palma Sola",
    "gn:country_code":"MX",
    "gn:dem":554,
    "gn:feature_class":"P",
    "gn:feature_code":"PPL",
    "gn:name":"Palma Sola",
    "gn:population":0,
    "gn:timezone":"America/Monterrey",
    "iso:country":"MX",
    "name:spa_x_preferred":[
        "Palma Sola"
    ],
    "wof:name":"Palma Sola",
    "wof:placetype":"locality"
},
  "geometry": {"coordinates":[-99.74979999999999,24.8336],"type":"Point"}
}