{
  "type": "Feature",
  "properties": {
    "gn:admin1_code":"21",
    "gn:admin2_code":"179.0",
    "gn:asciiname":"Albergue Alpino",
    "gn:country_code":"MX",
    "gn:dem":4211,
    "gn:feature_class":"P",
    "gn:feature_code":"PPL",
    "gn:name":"Albergue Alpino",
    "gn:population":0,
    "gn:timezone":"America/Mexico_City",
    "iso:country":"MX",
    "name:spa_x_preferred":[
        "Albergue Alpino"
    ],
    "wof:name":"Albergue Alpino",
    "wof:placetype":"locality"
},
  "geometry": {"coordinates":[-97.26927000000001,19.05831],"type":"Point"}
}