{
  "type": "Feature",
  "properties": {
    "gn:admin1_code":"6",
    "gn:admin2_code":"30.0",
    "gn:asciiname":"La Mesa el Toro",
    "gn:country_code":"MX",
    "gn:dem":1615,
    "gn:feature_class":"P",
    "gn:feature_code":"PPL",
    "gn:name":"La Mesa el Toro",
    "gn:population":0,
    "gn:timezone":"America/Chihuahua",
    "iso:country":"MX",
    "name:spa_x_preferred":[
        "La Mesa el Toro"
    ],
    "wof:name":"La Mesa el Toro",
    "wof:placetype":"locality"
},
  "geometry": {"coordinates":[-108.21902,27.37562],"type":"Point"}
}