{
  "type": "Feature",
  "properties": {
    "gn:admin1_code":"16.0",
    "gn:admin2_code":"99.0",
    "gn:asciiname":"El Infiernillo",
    "gn:country_code":"MX",
    "gn:dem":958,
    "gn:feature_class":"P",
    "gn:feature_code":"PPL",
    "gn:name":"El Infiernillo",
    "gn:population":0,
    "gn:timezone":"America/Mexico_City",
    "iso:country":"MX",
    "wof:name":"El Infiernillo",
    "wof:placetype":"locality"
},
  "geometry": {"coordinates":[-100.54722,19.05],"type":"Point"}
}