{
  "type": "Feature",
  "properties": {
    "gn:admin1_code":"7",
    "gn:admin2_code":"35.0",
    "gn:asciiname":"California",
    "gn:country_code":"MX",
    "gn:dem":1121,
    "gn:feature_class":"P",
    "gn:feature_code":"PPL",
    "gn:name":"California",
    "gn:population":0,
    "gn:timezone":"America/Monterrey",
    "iso:country":"MX",
    "name:spa_x_preferred":[
        "California"
    ],
    "wof:name":"California",
    "wof:placetype":"locality"
},
  "geometry": {"coordinates":[-103.39427000000001,25.53921],"type":"Point"}
}