{
  "type": "Feature",
  "properties": {
    "gn:admin1_code":"18.0",
    "gn:admin2_code":"10.0",
    "gn:asciiname":"Zapotillo",
    "gn:country_code":"MX",
    "gn:dem":45,
    "gn:feature_class":"P",
    "gn:feature_code":"PPL",
    "gn:name":"Zapotillo",
    "gn:population":0,
    "gn:timezone":"America/Mazatlan",
    "iso:country":"MX",
    "name:spa_x_preferred":[
        "Zapotillo"
    ],
    "name:und_x_variant":[
        "Zapotillos"
    ],
    "wof:name":"Zapotillo",
    "wof:placetype":"locality"
},
  "geometry": {"coordinates":[-105.1755,22.17039],"type":"Point"}
}