{
  "type": "Feature",
  "properties": {
    "gn:admin1_code":"30",
    "gn:admin2_code":"174",
    "gn:asciiname":"Paso Lagarto",
    "gn:country_code":"MX",
    "gn:dem":80,
    "gn:feature_class":"P",
    "gn:feature_code":"PPL",
    "gn:name":"Paso Lagarto",
    "gn:population":11,
    "gn:timezone":"America/Mexico_City",
    "iso:country":"MX",
    "wof:name":"Paso Lagarto",
    "wof:placetype":"locality",
    "wof:population":11
},
  "geometry": {"coordinates":[-96.39861000000001,18.57917],"type":"Point"}
}