{
  "type": "Feature",
  "properties": {
    "gn:admin1_code":"12",
    "gn:admin2_code":"79.0",
    "gn:asciiname":"Temixco",
    "gn:country_code":"MX",
    "gn:dem":1893,
    "gn:feature_class":"P",
    "gn:feature_code":"PPL",
    "gn:name":"Temixco",
    "gn:population":203,
    "gn:timezone":"America/Mexico_City",
    "iso:country":"MX",
    "name:cat_x_preferred":[
        "Temixco"
    ],
    "name:epo_x_preferred":[
        "Temixco"
    ],
    "name:fas_x_preferred":[
        "\u062a\u0645\u06cc\u06a9\u0633\u06a9\u0648"
    ],
    "name:fra_x_preferred":[
        "Temixco"
    ],
    "name:ita_x_preferred":[
        "Temixco"
    ],
    "name:jpn_x_preferred":[
        "\u30c6\u30df\u30b9\u30b3"
    ],
    "name:nld_x_preferred":[
        "Temixco"
    ],
    "name:pol_x_preferred":[
        "Temixco"
    ],
    "name:por_x_preferred":[
        "Temixco"
    ],
    "name:rus_x_preferred":[
        "\u0422\u0435\u043c\u0438\u0441\u043a\u043e"
    ],
    "name:sco_x_preferred":[
        "Temixco"
    ],
    "name:srp_x_preferred":[
        "\u0422\u0435\u043c\u0438\u0441\u043a\u043e"
    ],
    "name:swe_x_preferred":[
        "Temixco"
    ],
    "name:vie_x_preferred":[
        "Temixco"
    ],
    "name:zho_x_preferred":[
        "\u7279\u7c73\u65af\u79d1"
    ],
    "wof:name":"Temixco",
    "wof:placetype":"locality",
    "wof:population":203
},
  "geometry": {"coordinates":[-99.01648,17.47722000000001],"type":"Point"}
}