{
  "type": "Feature",
  "properties": {
    "gn:admin1_code":"32.0",
    "gn:admin2_code":"40.0",
    "gn:asciiname":"Ranchito Casa de Piedra",
    "gn:country_code":"MX",
    "gn:dem":2199,
    "gn:feature_class":"P",
    "gn:feature_code":"PPL",
    "gn:name":"Ranchito Casa de Piedra",
    "gn:population":0,
    "gn:timezone":"America/Mexico_City",
    "iso:country":"MX",
    "name:spa_x_preferred":[
        "Ranchito Casa de Piedra"
    ],
    "wof:name":"Ranchito Casa de Piedra",
    "wof:placetype":"locality"
},
  "geometry": {"coordinates":[-103.4204,23.57297],"type":"Point"}
}