{
  "type": "Feature",
  "properties": {
    "gn:admin1_code":"20",
    "gn:admin2_code":"483",
    "gn:asciiname":"Colonia del Sol",
    "gn:country_code":"MX",
    "gn:dem":1675,
    "gn:feature_class":"P",
    "gn:feature_code":"PPL",
    "gn:name":"Colonia del Sol",
    "gn:population":18,
    "gn:timezone":"America/Mexico_City",
    "iso:country":"MX",
    "wof:name":"Colonia del Sol",
    "wof:placetype":"locality",
    "wof:population":18
},
  "geometry": {"coordinates":[-96.86360999999999,17.23333],"type":"Point"}
}