{
  "type": "Feature",
  "properties": {
    "gn:admin1_code":"4",
    "gn:admin2_code":"3.0",
    "gn:asciiname":"La Esperanza de Dios Cuatro",
    "gn:country_code":"MX",
    "gn:dem":5,
    "gn:feature_class":"P",
    "gn:feature_code":"PPL",
    "gn:name":"La Esperanza de Dios Cuatro",
    "gn:population":7,
    "gn:timezone":"America/Merida",
    "iso:country":"MX",
    "wof:name":"La Esperanza de Dios Cuatro",
    "wof:placetype":"locality",
    "wof:population":7
},
  "geometry": {"coordinates":[-91.25528,18.21167],"type":"Point"}
}