{
  "type": "Feature",
  "properties": {
    "gn:admin1_code":"5",
    "gn:admin2_code":"97.0",
    "gn:asciiname":"Boca del Cielo",
    "gn:country_code":"MX",
    "gn:dem":5,
    "gn:feature_class":"P",
    "gn:feature_code":"PPL",
    "gn:name":"Boca del Cielo",
    "gn:population":0,
    "gn:timezone":"America/Mexico_City",
    "iso:country":"MX",
    "name:spa_x_preferred":[
        "Boca del Cielo"
    ],
    "wof:name":"Boca del Cielo",
    "wof:placetype":"locality"
},
  "geometry": {"coordinates":[-93.67547999999999,15.85559],"type":"Point"}
}