{
  "type": "Feature",
  "properties": {
    "gn:admin1_code":"30.0",
    "gn:admin2_code":"155.0",
    "gn:asciiname":"La Tinaja San Gabriel",
    "gn:country_code":"MX",
    "gn:dem":120,
    "gn:feature_class":"P",
    "gn:feature_code":"PPL",
    "gn:name":"La Tinaja San Gabriel",
    "gn:population":344,
    "gn:timezone":"America/Mexico_City",
    "iso:country":"MX",
    "name:spa_x_preferred":[
        "La Tinaja San Gabriel"
    ],
    "wof:name":"La Tinaja San Gabriel",
    "wof:placetype":"locality",
    "wof:population":344
},
  "geometry": {"coordinates":[-98.32583,21.35222000000001],"type":"Point"}
}