{
  "type": "Feature",
  "properties": {
    "gn:admin1_code":"20",
    "gn:admin2_code":"44.0",
    "gn:asciiname":"Roca de los Rios",
    "gn:country_code":"MX",
    "gn:dem":64,
    "gn:feature_class":"P",
    "gn:feature_code":"PPL",
    "gn:name":"Roca de los Rios",
    "gn:population":0,
    "gn:timezone":"America/Mexico_City",
    "iso:country":"MX",
    "wof:name":"Roca de los Rios",
    "wof:placetype":"locality"
},
  "geometry": {"coordinates":[-95.89472000000001,17.77277999999999],"type":"Point"}
}