{
  "type": "Feature",
  "properties": {
    "gn:admin1_code":"21",
    "gn:admin2_code":"83.0",
    "gn:asciiname":"Capolictic",
    "gn:country_code":"MX",
    "gn:dem":2702,
    "gn:feature_class":"P",
    "gn:feature_code":"PPL",
    "gn:name":"Capolictic",
    "gn:population":200,
    "gn:timezone":"America/Mexico_City",
    "iso:country":"MX",
    "wof:name":"Capolictic",
    "wof:placetype":"locality",
    "wof:population":200
},
  "geometry": {"coordinates":[-97.8492,19.59458],"type":"Point"}
}