{
  "type": "Feature",
  "properties": {
    "gn:admin1_code":"26",
    "gn:admin2_code":"68.0",
    "gn:asciiname":"El Horno",
    "gn:country_code":"MX",
    "gn:dem":800,
    "gn:feature_class":"P",
    "gn:feature_code":"PPL",
    "gn:name":"El Horno",
    "gn:population":0,
    "gn:timezone":"America/Hermosillo",
    "iso:country":"MX",
    "name:spa_x_preferred":[
        "El Horno"
    ],
    "wof:name":"El Horno",
    "wof:placetype":"locality"
},
  "geometry": {"coordinates":[-109.95028000000001,29.14778],"type":"Point"}
}