{
  "type": "Feature",
  "properties": {
    "gn:admin1_code":"28.0",
    "gn:admin2_code":"11.0",
    "gn:asciiname":"La Bocatoma",
    "gn:country_code":"MX",
    "gn:dem":106,
    "gn:feature_class":"P",
    "gn:feature_code":"PPL",
    "gn:name":"La Bocatoma",
    "gn:population":9,
    "gn:timezone":"America/Monterrey",
    "iso:country":"MX",
    "name:spa_x_preferred":[
        "La Bocatoma"
    ],
    "wof:name":"La Bocatoma",
    "wof:placetype":"locality",
    "wof:population":9
},
  "geometry": {"coordinates":[-99.14525999999999,22.98713],"type":"Point"}
}