{
  "type": "Feature",
  "properties": {
    "gn:admin1_code":"26",
    "gn:admin2_code":"30.0",
    "gn:asciiname":"Carmen Dolores",
    "gn:country_code":"MX",
    "gn:dem":45,
    "gn:feature_class":"P",
    "gn:feature_code":"PPL",
    "gn:name":"Carmen Dolores",
    "gn:population":36,
    "gn:timezone":"America/Hermosillo",
    "iso:country":"MX",
    "name:spa_x_preferred":[
        "Carmen Dolores"
    ],
    "wof:name":"Carmen Dolores",
    "wof:placetype":"locality",
    "wof:population":36
},
  "geometry": {"coordinates":[-111.47444,28.67556],"type":"Point"}
}