{
  "type": "Feature",
  "properties": {
    "gn:admin1_code":"30",
    "gn:admin2_code":"111.0",
    "gn:asciiname":"El Grullo",
    "gn:country_code":"MX",
    "gn:dem":56,
    "gn:feature_class":"P",
    "gn:feature_code":"PPL",
    "gn:name":"El Grullo",
    "gn:population":7,
    "gn:timezone":"America/Mexico_City",
    "iso:country":"MX",
    "wof:name":"El Grullo",
    "wof:placetype":"locality",
    "wof:population":7
},
  "geometry": {"coordinates":[-94.32971999999999,18.01583],"type":"Point"}
}