{
  "type": "Feature",
  "properties": {
    "gn:admin1_code":"30",
    "gn:admin2_code":"111.0",
    "gn:asciiname":"El Grullo",
    "gn:country_code":"MX",
    "gn:dem":56,
    "gn:feature_class":"P",
    "gn:feature_code":"PPL",
    "gn:name":"El Grullo",
    "gn:population":7,
    "gn:timezone":"America/Mexico_City",
    "iso:country":"MX",
    "name:ceb_x_preferred":[
        "El Grullo"
    ],
    "name:epo_x_preferred":[
        "El Grullo"
    ],
    "name:eus_x_preferred":[
        "El Grullo"
    ],
    "name:fra_x_preferred":[
        "El Grullo"
    ],
    "name:ita_x_preferred":[
        "El Grullo"
    ],
    "name:nor_x_preferred":[
        "El Grullo"
    ],
    "name:pol_x_preferred":[
        "El Grullo"
    ],
    "name:por_x_preferred":[
        "El Grullo"
    ],
    "name:spa_x_preferred":[
        "El Grullo"
    ],
    "name:srp_x_preferred":[
        "\u041e\u043f\u0448\u0442\u0438\u043d\u0430 \u0415\u043b \u0413\u0440\u0443\u0459\u043e"
    ],
    "name:swe_x_preferred":[
        "El Grullo"
    ],
    "name:vie_x_preferred":[
        "El Grullo"
    ],
    "wof:name":"El Grullo",
    "wof:placetype":"locality",
    "wof:population":7
},
  "geometry": {"coordinates":[-94.32971999999999,18.01583],"type":"Point"}
}