{
  "type": "Feature",
  "properties": {
    "gn:admin1_code":"20",
    "gn:admin2_code":"166.0",
    "gn:asciiname":"Arroyo Choapam",
    "gn:country_code":"MX",
    "gn:dem":53,
    "gn:feature_class":"P",
    "gn:feature_code":"PPL",
    "gn:name":"Arroyo Cho\u00e1pam",
    "gn:population":1576,
    "gn:timezone":"America/Mexico_City",
    "iso:country":"MX",
    "name:und_x_variant":[
        "Arroyo Cho\u00e1pam"
    ],
    "wof:name":"Arroyo Choapam",
    "wof:placetype":"locality",
    "wof:population":1576
},
  "geometry": {"coordinates":[-96.15722,17.97028],"type":"Point"}
}