{
  "type": "Feature",
  "properties": {
    "gn:admin1_code":"7.0",
    "gn:admin2_code":"18.0",
    "gn:asciiname":"Georgina",
    "gn:country_code":"MX",
    "gn:dem":517,
    "gn:feature_class":"P",
    "gn:feature_code":"PPL",
    "gn:name":"Georgina",
    "gn:population":0,
    "gn:timezone":"America/Monterrey",
    "iso:country":"MX",
    "name:bre_x_preferred":[
        "Georgina"
    ],
    "name:fra_x_preferred":[
        "Georgina"
    ],
    "name:ita_x_preferred":[
        "Georgina"
    ],
    "name:pol_x_preferred":[
        "Georgina"
    ],
    "name:spa_x_preferred":[
        "Georgina"
    ],
    "wof:name":"Georgina",
    "wof:placetype":"locality"
},
  "geometry": {"coordinates":[-101.37335,26.98526],"type":"Point"}
}