{
  "type": "Feature",
  "properties": {
    "gn:admin1_code":"20",
    "gn:admin2_code":"1.0",
    "gn:asciiname":"Pena Negra",
    "gn:country_code":"MX",
    "gn:dem":1662,
    "gn:feature_class":"P",
    "gn:feature_code":"PPL",
    "gn:name":"Pe\u00f1a Negra",
    "gn:population":0,
    "gn:timezone":"America/Mexico_City",
    "iso:country":"MX",
    "wof:name":"Pena Negra",
    "wof:placetype":"locality"
},
  "geometry": {"coordinates":[-96.63333,17.53333],"type":"Point"}
}