{
  "type": "Feature",
  "properties": {
    "gn:admin1_code":"28",
    "gn:admin2_code":"21.0",
    "gn:asciiname":"Doctor Emilio Martinez Manautou (La Hulera)",
    "gn:country_code":"MX",
    "gn:dem":68,
    "gn:feature_class":"P",
    "gn:feature_code":"PPL",
    "gn:name":"Doctor Emilio Mart\u00ednez Manautou (La Hulera)",
    "gn:population":5,
    "gn:timezone":"America/Monterrey",
    "iso:country":"MX",
    "name:und_x_variant":[
        "Doctor Emilio Mart\u00ednez Manautou (La Hulera)"
    ],
    "wof:name":"Doctor Emilio Martinez Manautou (La Hulera)",
    "wof:placetype":"locality",
    "wof:population":5
},
  "geometry": {"coordinates":[-98.80444,22.50806],"type":"Point"}
}