{
  "type": "Feature",
  "properties": {
    "gn:admin1_code":"20",
    "gn:admin2_code":"58.0",
    "gn:asciiname":"Platanillo",
    "gn:country_code":"MX",
    "gn:dem":1293,
    "gn:feature_class":"P",
    "gn:feature_code":"PPL",
    "gn:name":"Platanillo",
    "gn:population":322,
    "gn:timezone":"America/Mexico_City",
    "iso:country":"MX",
    "wof:name":"Platanillo",
    "wof:placetype":"locality",
    "wof:population":322
},
  "geometry": {"coordinates":[-96.91278,18.05389],"type":"Point"}
}