{
  "type": "Feature",
  "properties": {
    "gn:admin1_code":"14",
    "gn:admin2_code":"61.0",
    "gn:asciiname":"Taller de Tuapuri (Santa Cruz)",
    "gn:country_code":"MX",
    "gn:dem":2498,
    "gn:feature_class":"P",
    "gn:feature_code":"PPL",
    "gn:name":"Taller de Tuapuri (Santa Cruz)",
    "gn:population":7,
    "gn:timezone":"America/Mexico_City",
    "iso:country":"MX",
    "wof:name":"Taller de Tuapuri (Santa Cruz)",
    "wof:placetype":"locality",
    "wof:population":7
},
  "geometry": {"coordinates":[-103.91110999999999,22.215],"type":"Point"}
}