{
  "type": "Feature",
  "properties": {
    "gn:admin1_code":"16.0",
    "gn:admin2_code":"15.0",
    "gn:asciiname":"La Cebollita",
    "gn:country_code":"MX",
    "gn:dem":1051,
    "gn:feature_class":"P",
    "gn:feature_code":"PPL",
    "gn:name":"La Cebollita",
    "gn:population":0,
    "gn:timezone":"America/Mexico_City",
    "iso:country":"MX",
    "name:spa_x_preferred":[
        "La Cebollita"
    ],
    "wof:name":"La Cebollita",
    "wof:placetype":"locality"
},
  "geometry": {"coordinates":[-103.13711000000001,18.79066],"type":"Point"}
}