{
  "type": "Feature",
  "properties": {
    "gn:admin1_code":"20",
    "gn:admin2_code":"344.0",
    "gn:asciiname":"Santo Antonio Lalana",
    "gn:country_code":"MX",
    "gn:dem":1108,
    "gn:feature_class":"P",
    "gn:feature_code":"PPL",
    "gn:name":"Santo Antonio Lalana",
    "gn:population":0,
    "gn:timezone":"America/Mexico_City",
    "iso:country":"MX",
    "name:spa_x_preferred":[
        "Santo Antonio Lalana"
    ],
    "wof:name":"Santo Antonio Lalana",
    "wof:placetype":"locality"
},
  "geometry": {"coordinates":[-96.85917000000001,16.10611],"type":"Point"}
}