{
  "type": "Feature",
  "properties": {
    "gn:admin1_code":"12.0",
    "gn:admin2_code":"6.0",
    "gn:asciiname":"Alceseca",
    "gn:country_code":"MX",
    "gn:dem":1131,
    "gn:feature_class":"P",
    "gn:feature_code":"PPL",
    "gn:name":"Alceseca",
    "gn:population":0,
    "gn:timezone":"America/Mexico_City",
    "iso:country":"MX",
    "name:spa_x_preferred":[
        "Alceseca"
    ],
    "wof:name":"Alceseca",
    "wof:placetype":"locality"
},
  "geometry": {"coordinates":[-100.04967000000001,18.17611],"type":"Point"}
}