{
  "type": "Feature",
  "properties": {
    "gn:admin1_code":"12",
    "gn:admin2_code":"78",
    "gn:asciiname":"Barrio del Carmen",
    "gn:country_code":"MX",
    "gn:dem":1279,
    "gn:feature_class":"P",
    "gn:feature_code":"PPL",
    "gn:name":"Barrio del Carmen",
    "gn:population":46,
    "gn:timezone":"America/Mexico_City",
    "iso:country":"MX",
    "wof:name":"Barrio del Carmen",
    "wof:placetype":"locality",
    "wof:population":46
},
  "geometry": {"coordinates":[-98.3075,17.07111],"type":"Point"}
}