{
  "type": "Feature",
  "properties": {
    "gn:admin1_code":"25",
    "gn:admin2_code":"3.0",
    "gn:asciiname":"San Nicolas Sitio de Arriba",
    "gn:country_code":"MX",
    "gn:dem":331,
    "gn:feature_class":"P",
    "gn:feature_code":"PPL",
    "gn:name":"San Nicolas Sitio de Arriba",
    "gn:population":0,
    "gn:timezone":"America/Mazatlan",
    "iso:country":"MX",
    "name:spa_x_preferred":[
        "San Nicolas Sitio de Arriba"
    ],
    "name:und_x_variant":[
        "Sitio de Arriba"
    ],
    "wof:name":"San Nicolas Sitio de Arriba",
    "wof:placetype":"locality"
},
  "geometry": {"coordinates":[-107.64449999999999,25.48396],"type":"Point"}
}