{
  "type": "Feature",
  "properties": {
    "gn:admin1_code":"30",
    "gn:admin2_code":"23.0",
    "gn:asciiname":"Martinica",
    "gn:country_code":"MX",
    "gn:dem":1003,
    "gn:feature_class":"P",
    "gn:feature_code":"PPL",
    "gn:name":"Martinica",
    "gn:population":272,
    "gn:timezone":"America/Mexico_City",
    "iso:country":"MX",
    "wof:name":"Martinica",
    "wof:placetype":"locality",
    "wof:population":272
},
  "geometry": {"coordinates":[-97.08,19.86694],"type":"Point"}
}