{
  "type": "Feature",
  "properties": {
    "gn:admin1_code":"30",
    "gn:admin2_code":"210.0",
    "gn:asciiname":"Numero Uno",
    "gn:country_code":"MX",
    "gn:dem":107,
    "gn:feature_class":"P",
    "gn:feature_code":"PPL",
    "gn:name":"N\u00famero Uno",
    "gn:population":0,
    "gn:timezone":"America/Mexico_City",
    "iso:country":"MX",
    "name:spa_x_preferred":[
        "N\u00famero Uno"
    ],
    "name:spa_x_variant":[
        "Poblado Uno"
    ],
    "wof:name":"Numero Uno",
    "wof:placetype":"locality"
},
  "geometry": {"coordinates":[-94.724,17.21416],"type":"Point"}
}