{
  "type": "Feature",
  "properties": {
    "gn:admin1_code":"17",
    "gn:admin2_code":"11.0",
    "gn:asciiname":"Rancho Paraiso",
    "gn:country_code":"MX",
    "gn:dem":1343,
    "gn:feature_class":"P",
    "gn:feature_code":"PPL",
    "gn:name":"Rancho Para\u00edso",
    "gn:population":315,
    "gn:timezone":"America/Mexico_City",
    "iso:country":"MX",
    "name:und_x_variant":[
        "Rancho Para\u00edso"
    ],
    "wof:name":"Rancho Paraiso",
    "wof:placetype":"locality",
    "wof:population":315
},
  "geometry": {"coordinates":[-99.15312,18.86922],"type":"Point"}
}