{
  "type": "Feature",
  "properties": {
    "gn:admin1_code":"32.0",
    "gn:admin2_code":"7.0",
    "gn:asciiname":"La Casa Blanca",
    "gn:country_code":"MX",
    "gn:dem":1888,
    "gn:feature_class":"P",
    "gn:feature_code":"PPL",
    "gn:name":"La Casa Blanca",
    "gn:population":0,
    "gn:timezone":"America/Mexico_City",
    "iso:country":"MX",
    "name:spa_x_preferred":[
        "La Casa Blanca"
    ],
    "wof:name":"La Casa Blanca",
    "wof:placetype":"locality"
},
  "geometry": {"coordinates":[-101.37411,24.61298],"type":"Point"}
}