{
  "type": "Feature",
  "properties": {
    "gn:admin1_code":"10",
    "gn:admin2_code":"7.0",
    "gn:asciiname":"Isidro Morales",
    "gn:country_code":"MX",
    "gn:dem":1115,
    "gn:feature_class":"P",
    "gn:feature_code":"PPL",
    "gn:name":"Isidro Morales",
    "gn:population":4,
    "gn:timezone":"America/Monterrey",
    "iso:country":"MX",
    "wof:name":"Isidro Morales",
    "wof:placetype":"locality",
    "wof:population":4
},
  "geometry": {"coordinates":[-103.37257,25.70251],"type":"Point"}
}