{
  "type": "Feature",
  "properties": {
    "gn:admin1_code":"30.0",
    "gn:admin2_code":"205.0",
    "gn:asciiname":"El Estero",
    "gn:country_code":"MX",
    "gn:dem":30,
    "gn:feature_class":"P",
    "gn:feature_code":"PPL",
    "gn:name":"El Estero",
    "gn:population":21,
    "gn:timezone":"America/Mexico_City",
    "iso:country":"MX",
    "name:spa_x_preferred":[
        "El Estero"
    ],
    "wof:name":"El Estero",
    "wof:placetype":"locality",
    "wof:population":21
},
  "geometry": {"coordinates":[-98.53194000000001,21.69412],"type":"Point"}
}