{
  "type": "Feature",
  "properties": {
    "gn:admin1_code":"16",
    "gn:admin2_code":"89.0",
    "gn:asciiname":"Salatito",
    "gn:country_code":"MX",
    "gn:dem":883,
    "gn:feature_class":"P",
    "gn:feature_code":"PPL",
    "gn:name":"Salatito",
    "gn:population":0,
    "gn:timezone":"America/Mexico_City",
    "iso:country":"MX",
    "name:spa_x_preferred":[
        "Salatito"
    ],
    "wof:name":"Salatito",
    "wof:placetype":"locality"
},
  "geometry": {"coordinates":[-102.97069999999999,19.01526],"type":"Point"}
}