{
  "type": "Feature",
  "properties": {
    "gn:admin1_code":"4",
    "gn:admin2_code":"10.0",
    "gn:asciiname":"La Llamarada Dos",
    "gn:country_code":"MX",
    "gn:dem":194,
    "gn:feature_class":"P",
    "gn:feature_code":"PPL",
    "gn:name":"La Llamarada Dos",
    "gn:population":0,
    "gn:timezone":"America/Cancun",
    "iso:country":"MX",
    "name:spa_x_preferred":[
        "La Llamarada Dos"
    ],
    "wof:name":"La Llamarada Dos",
    "wof:placetype":"locality"
},
  "geometry": {"coordinates":[-89.19749,18.19105],"type":"Point"}
}