{
  "type": "Feature",
  "properties": {
    "gn:admin1_code":"25.0",
    "gn:asciiname":"El Pozole",
    "gn:country_code":"MX",
    "gn:dem":452,
    "gn:feature_class":"P",
    "gn:feature_code":"PPL",
    "gn:name":"El Pozole",
    "gn:population":0,
    "gn:timezone":"America/Mazatlan",
    "iso:country":"MX",
    "name:spa_x_preferred":[
        "El Pozole"
    ],
    "name:spa_x_variant":[
        "Pozole"
    ],
    "wof:name":"El Pozole",
    "wof:placetype":"locality"
},
  "geometry": {"coordinates":[-106.54550999999999,24.18086],"type":"Point"}
}