{
  "type": "Feature",
  "properties": {
    "gn:admin1_code":"24",
    "gn:admin2_code":"32",
    "gn:asciiname":"Juan Diego",
    "gn:country_code":"MX",
    "gn:dem":2038,
    "gn:feature_class":"P",
    "gn:feature_code":"PPL",
    "gn:name":"Juan Diego",
    "gn:population":14,
    "gn:timezone":"America/Mexico_City",
    "iso:country":"MX",
    "wof:name":"Juan Diego",
    "wof:placetype":"locality",
    "wof:population":14
},
  "geometry": {"coordinates":[-100.44638999999999,21.81306],"type":"Point"}
}