{
  "type": "Feature",
  "properties": {
    "gn:admin1_code":"24",
    "gn:admin2_code":"32",
    "gn:asciiname":"Juan Diego",
    "gn:country_code":"MX",
    "gn:dem":2038,
    "gn:feature_class":"P",
    "gn:feature_code":"PPL",
    "gn:name":"Juan Diego",
    "gn:population":14,
    "gn:timezone":"America/Mexico_City",
    "iso:country":"MX",
    "name:ara_x_preferred":[
        "\u062e\u0648\u0627\u0646 \u062f\u064a\u064a\u063a\u0648"
    ],
    "name:cat_x_preferred":[
        "Juan Diego Cuauhtlatoatzin"
    ],
    "name:ceb_x_preferred":[
        "Juan Diego Cuauhtlatoatzin"
    ],
    "name:ces_x_preferred":[
        "Juan Diego Cuauhtlatoatzin"
    ],
    "name:deu_x_preferred":[
        "Juan Diego"
    ],
    "name:epo_x_preferred":[
        "Johano Diego"
    ],
    "name:fra_x_preferred":[
        "Juan Diego Cuauhtlatoatzin"
    ],
    "name:hrv_x_preferred":[
        "Ivan Diego"
    ],
    "name:hun_x_preferred":[
        "Juan Diego"
    ],
    "name:ind_x_preferred":[
        "Juan Diego"
    ],
    "name:ita_x_preferred":[
        "Juan Diego Cuauhtlatoatzin"
    ],
    "name:lat_x_preferred":[
        "Ioannes Didacus"
    ],
    "name:nah_x_preferred":[
        "Juan Diego Cuauhtlahtoatzin"
    ],
    "name:nld_x_preferred":[
        "Juan Diego Cuauhtlatoatzin"
    ],
    "name:pol_x_preferred":[
        "Juan Diego"
    ],
    "name:por_x_preferred":[
        "Juan Diego Cuauhtlatoatzin"
    ],
    "name:rus_x_preferred":[
        "\u041a\u0443\u0430\u0443\u0445\u0442\u043b\u0430\u0442\u043e\u0430\u0442\u0446\u0438\u043d"
    ],
    "name:scn_x_preferred":[
        "Juan Diego Cuauhtlatoatzin"
    ],
    "name:spa_x_preferred":[
        "Juan Diego Cuauhtlatoatzin"
    ],
    "name:swa_x_preferred":[
        "Juan Diego"
    ],
    "name:swe_x_preferred":[
        "Juan Diego Cuauhtlatoatzin"
    ],
    "name:tgl_x_preferred":[
        "Juan Diego"
    ],
    "name:urd_x_preferred":[
        "\u062c\u0648\u0622\u0646 \u0688\u0627\u0626\u06af\u0648"
    ],
    "wof:name":"Juan Diego",
    "wof:placetype":"locality",
    "wof:population":14
},
  "geometry": {"coordinates":[-100.44638999999999,21.81306],"type":"Point"}
}