{
  "type": "Feature",
  "properties": {
    "gn:admin1_code":"5.0",
    "gn:asciiname":"Alta Luz",
    "gn:country_code":"MX",
    "gn:dem":65,
    "gn:feature_class":"P",
    "gn:feature_code":"PPL",
    "gn:name":"Alta Luz",
    "gn:population":0,
    "gn:timezone":"America/Mexico_City",
    "iso:country":"MX",
    "name:spa_x_preferred":[
        "Alta Luz"
    ],
    "wof:name":"Alta Luz",
    "wof:placetype":"locality"
},
  "geometry": {"coordinates":[-94.08691,16.32146],"type":"Point"}
}