{
  "type": "Feature",
  "properties": {
    "gn:admin1_code":"5",
    "gn:admin2_code":"77.0",
    "gn:asciiname":"Paso Naranjo 1ra. Seccion",
    "gn:country_code":"MX",
    "gn:dem":58,
    "gn:feature_class":"P",
    "gn:feature_code":"PPL",
    "gn:name":"Paso Naranjo 1ra. Secci\u00f3n",
    "gn:population":288,
    "gn:timezone":"America/Mexico_City",
    "iso:country":"MX",
    "name:und_x_variant":[
        "Paso Naranjo 1ra. Secci\u00f3n"
    ],
    "wof:name":"Paso Naranjo 1ra. Seccion",
    "wof:placetype":"locality",
    "wof:population":288
},
  "geometry": {"coordinates":[-92.28972,17.51389],"type":"Point"}
}