{
  "type": "Feature",
  "properties": {
    "gn:admin1_code":"10",
    "gn:admin2_code":"13.0",
    "gn:asciiname":"Rancho La Merceo",
    "gn:country_code":"MX",
    "gn:dem":1337,
    "gn:feature_class":"P",
    "gn:feature_code":"PPL",
    "gn:name":"Rancho La Merceo",
    "gn:population":0,
    "gn:timezone":"America/Monterrey",
    "iso:country":"MX",
    "wof:name":"Rancho La Merceo",
    "wof:placetype":"locality"
},
  "geometry": {"coordinates":[-104.38333,26.28333],"type":"Point"}
}