{
  "type": "Feature",
  "properties": {
    "gn:admin1_code":"28",
    "gn:admin2_code":"32.0",
    "gn:asciiname":"Rigo Garza",
    "gn:country_code":"MX",
    "gn:dem":41,
    "gn:feature_class":"P",
    "gn:feature_code":"PPL",
    "gn:name":"Rigo Garza",
    "gn:population":5,
    "gn:timezone":"America/Matamoros",
    "iso:country":"MX",
    "wof:name":"Rigo Garza",
    "wof:placetype":"locality",
    "wof:population":5
},
  "geometry": {"coordinates":[-98.44556,26.20139],"type":"Point"}
}