{
  "type": "Feature",
  "properties": {
    "gn:admin1_code":"6.0",
    "gn:asciiname":"La Ladrillera",
    "gn:country_code":"MX",
    "gn:dem":1985,
    "gn:feature_class":"P",
    "gn:feature_code":"PPL",
    "gn:name":"La Ladrillera",
    "gn:population":0,
    "gn:timezone":"America/Chihuahua",
    "iso:country":"MX",
    "name:spa_x_preferred":[
        "La Ladrillera"
    ],
    "wof:name":"La Ladrillera",
    "wof:placetype":"locality"
},
  "geometry": {"coordinates":[-105.84215,26.78932],"type":"Point"}
}