{
  "type": "Feature",
  "properties": {
    "gn:admin1_code":"20",
    "gn:admin2_code":"554.0",
    "gn:asciiname":"San Miguel Metepec",
    "gn:country_code":"MX",
    "gn:dem":2606,
    "gn:feature_class":"P",
    "gn:feature_code":"PPL",
    "gn:name":"San Miguel Metepec",
    "gn:population":0,
    "gn:timezone":"America/Mexico_City",
    "iso:country":"MX",
    "name:spa_x_preferred":[
        "Metepec"
    ],
    "name:spa_x_variant":[
        "San Miguel Metepec"
    ],
    "wof:name":"San Miguel Metepec",
    "wof:placetype":"locality"
},
  "geometry": {"coordinates":[-96.05869,17.21481],"type":"Point"}
}