{
  "type": "Feature",
  "properties": {
    "gn:admin1_code":"20",
    "gn:admin2_code":"537.0",
    "gn:asciiname":"Santiago Asuncion",
    "gn:country_code":"MX",
    "gn:dem":1935,
    "gn:feature_class":"P",
    "gn:feature_code":"PPL",
    "gn:name":"Santiago Asunci\u00f3n",
    "gn:population":256,
    "gn:timezone":"America/Mexico_City",
    "iso:country":"MX",
    "name:spa_x_preferred":[
        "Santiago Asunci\u00f3n"
    ],
    "wof:name":"Santiago Asuncion",
    "wof:placetype":"locality",
    "wof:population":256
},
  "geometry": {"coordinates":[-98.02972,17.51806],"type":"Point"}
}