{
  "type": "Feature",
  "properties": {
    "gn:admin1_code":"20",
    "gn:admin2_code":"439.0",
    "gn:asciiname":"Union del Palmar",
    "gn:country_code":"MX",
    "gn:dem":37,
    "gn:feature_class":"P",
    "gn:feature_code":"PPL",
    "gn:name":"Uni\u00f3n del Palmar",
    "gn:population":69,
    "gn:timezone":"America/Mexico_City",
    "iso:country":"MX",
    "name:und_x_variant":[
        "Uni\u00f3n del Palmar"
    ],
    "wof:name":"Union del Palmar",
    "wof:placetype":"locality",
    "wof:population":69
},
  "geometry": {"coordinates":[-96.62139000000001,15.72083],"type":"Point"}
}