{
  "type": "Feature",
  "properties": {
    "gn:admin1_code":"30",
    "gn:admin2_code":"207.0",
    "gn:asciiname":"Laguna de Colorado (Las Macayas)",
    "gn:country_code":"MX",
    "gn:dem":42,
    "gn:feature_class":"P",
    "gn:feature_code":"PPL",
    "gn:name":"Laguna de Colorado (Las Macayas)",
    "gn:population":6,
    "gn:timezone":"America/Mexico_City",
    "iso:country":"MX",
    "wof:name":"Laguna de Colorado (Las Macayas)",
    "wof:placetype":"locality",
    "wof:population":6
},
  "geometry": {"coordinates":[-96.18416999999999,18.30056],"type":"Point"}
}