{
  "type": "Feature",
  "properties": {
    "gn:admin1_code":"21",
    "gn:admin2_code":"155",
    "gn:asciiname":"Piedra Azul",
    "gn:country_code":"MX",
    "gn:dem":937,
    "gn:feature_class":"P",
    "gn:feature_code":"PPL",
    "gn:name":"Piedra Azul",
    "gn:population":14,
    "gn:timezone":"America/Mexico_City",
    "iso:country":"MX",
    "wof:name":"Piedra Azul",
    "wof:placetype":"locality",
    "wof:population":14
},
  "geometry": {"coordinates":[-98.31804,18.10548],"type":"Point"}
}