{
  "type": "Feature",
  "properties": {
    "gn:admin1_code":"26",
    "gn:admin2_code":"3.0",
    "gn:asciiname":"Rancho San Francisco",
    "gn:country_code":"MX",
    "gn:dem":100,
    "gn:feature_class":"P",
    "gn:feature_code":"PPL",
    "gn:name":"Rancho San Francisco",
    "gn:population":0,
    "gn:timezone":"America/Mazatlan",
    "iso:country":"MX",
    "name:fra_x_preferred":[
        "Rancho San Francisco"
    ],
    "wof:name":"Rancho San Francisco",
    "wof:placetype":"locality"
},
  "geometry": {"coordinates":[-108.96056000000002,26.47333],"type":"Point"}
}