{
  "type": "Feature",
  "properties": {
    "gn:admin1_code":"30",
    "gn:admin2_code":"207.0",
    "gn:asciiname":"Poblado Tres",
    "gn:country_code":"MX",
    "gn:dem":30,
    "gn:feature_class":"P",
    "gn:feature_code":"PPL",
    "gn:name":"Poblado Tres",
    "gn:population":0,
    "gn:timezone":"America/Mexico_City",
    "iso:country":"MX",
    "name:spa_x_preferred":[
        "Poblado Tres"
    ],
    "wof:name":"Poblado Tres",
    "wof:placetype":"locality"
},
  "geometry": {"coordinates":[-96.09114,18.28929],"type":"Point"}
}