{
  "type": "Feature",
  "properties": {
    "gn:admin1_code":"25",
    "gn:admin2_code":"14.0",
    "gn:asciiname":"El Tacon",
    "gn:country_code":"MX",
    "gn:dem":29,
    "gn:feature_class":"P",
    "gn:feature_code":"PPL",
    "gn:name":"El Tac\u00f3n",
    "gn:population":6,
    "gn:timezone":"America/Mazatlan",
    "iso:country":"MX",
    "name:und_x_variant":[
        "El Tac\u00f3n"
    ],
    "wof:name":"El Tacon",
    "wof:placetype":"locality",
    "wof:population":6
},
  "geometry": {"coordinates":[-105.91892,23.01503],"type":"Point"}
}