{
  "type": "Feature",
  "properties": {
    "gn:admin1_code":"12",
    "gn:admin2_code":"65",
    "gn:asciiname":"Guajolotitlan (Rio Salado)",
    "gn:country_code":"MX",
    "gn:dem":1162,
    "gn:feature_class":"P",
    "gn:feature_code":"PPL",
    "gn:name":"Guajolotitl\u00e1n (R\u00edo Salado)",
    "gn:population":18,
    "gn:timezone":"America/Mexico_City",
    "iso:country":"MX",
    "name:und_x_variant":[
        "Guajolotitl\u00e1n (R\u00edo Salado)"
    ],
    "wof:name":"Guajolotitlan (Rio Salado)",
    "wof:placetype":"locality",
    "wof:population":18
},
  "geometry": {"coordinates":[-98.38332,17.55552999999999],"type":"Point"}
}