{
  "type": "Feature",
  "properties": {
    "gn:admin1_code":"5",
    "gn:admin2_code":"49.0",
    "gn:asciiname":"Tres Puentes Uno",
    "gn:country_code":"MX",
    "gn:dem":1537,
    "gn:feature_class":"P",
    "gn:feature_code":"PPL",
    "gn:name":"Tres Puentes Uno",
    "gn:population":0,
    "gn:timezone":"America/Mexico_City",
    "iso:country":"MX",
    "name:spa_x_preferred":[
        "Tres Puentes"
    ],
    "name:spa_x_variant":[
        "Tres Puentes Uno"
    ],
    "wof:name":"Tres Puentes Uno",
    "wof:placetype":"locality"
},
  "geometry": {"coordinates":[-92.75651999999999,16.93856],"type":"Point"}
}