{
  "type": "Feature",
  "properties": {
    "gn:admin1_code":"14.0",
    "gn:asciiname":"Zermeno",
    "gn:country_code":"MX",
    "gn:dem":1965,
    "gn:feature_class":"P",
    "gn:feature_code":"PPL",
    "gn:name":"Zerme\u00f1o",
    "gn:population":0,
    "gn:timezone":"America/Mexico_City",
    "iso:country":"MX",
    "name:spa_x_preferred":[
        "Zerme\u00f1o"
    ],
    "wof:name":"Zermeno",
    "wof:placetype":"locality"
},
  "geometry": {"coordinates":[-102.11208999999999,21.22786],"type":"Point"}
}