{
  "type": "Feature",
  "properties": {
    "gn:admin1_code":"30",
    "gn:admin2_code":"192.0",
    "gn:asciiname":"Agua Santa",
    "gn:country_code":"MX",
    "gn:dem":336,
    "gn:feature_class":"P",
    "gn:feature_code":"PPL",
    "gn:name":"Agua Santa",
    "gn:population":9,
    "gn:timezone":"America/Mexico_City",
    "iso:country":"MX",
    "wof:name":"Agua Santa",
    "wof:placetype":"locality",
    "wof:population":9
},
  "geometry": {"coordinates":[-96.75306,19.98444],"type":"Point"}
}