{
  "type": "Feature",
  "properties": {
    "gn:admin1_code":"21.0",
    "gn:admin2_code":"136.0",
    "gn:asciiname":"El Milagro",
    "gn:country_code":"MX",
    "gn:dem":2192,
    "gn:feature_class":"P",
    "gn:feature_code":"PPLL",
    "gn:name":"El Milagro",
    "gn:population":0,
    "gn:timezone":"America/Mexico_City",
    "iso:country":"MX",
    "name:spa_x_preferred":[
        "El Milagro"
    ],
    "wof:name":"El Milagro",
    "wof:placetype":"locality"
},
  "geometry": {"coordinates":[-98.30184,19.17893],"type":"Point"}
}