{
  "type": "Feature",
  "properties": {
    "gn:admin1_code":"15",
    "gn:admin2_code":"113",
    "gn:asciiname":"Loma del Capulin",
    "gn:country_code":"MX",
    "gn:dem":2367,
    "gn:feature_class":"P",
    "gn:feature_code":"PPL",
    "gn:name":"Loma del Capul\u00edn",
    "gn:population":50,
    "gn:timezone":"America/Mexico_City",
    "iso:country":"MX",
    "name:und_x_variant":[
        "Loma del Capul\u00edn"
    ],
    "wof:name":"Loma del Capulin",
    "wof:placetype":"locality",
    "wof:population":50
},
  "geometry": {"coordinates":[-99.70004,18.97725],"type":"Point"}
}