{
  "type": "Feature",
  "properties": {
    "gn:admin1_code":"20",
    "gn:admin2_code":"297.0",
    "gn:asciiname":"Union y Progreso",
    "gn:country_code":"MX",
    "gn:dem":1520,
    "gn:feature_class":"P",
    "gn:feature_code":"PPL",
    "gn:name":"Uni\u00f3n y Progreso",
    "gn:population":56,
    "gn:timezone":"America/Mexico_City",
    "iso:country":"MX",
    "name:und_x_variant":[
        "Uni\u00f3n y Progreso"
    ],
    "wof:name":"Union y Progreso",
    "wof:placetype":"locality",
    "wof:population":56
},
  "geometry": {"coordinates":[-97.47111,16.95694],"type":"Point"}
}