{
  "type": "Feature",
  "properties": {
    "gn:admin1_code":"30",
    "gn:admin2_code":"200.0",
    "gn:asciiname":"Potrero (Potrerillo)",
    "gn:country_code":"MX",
    "gn:dem":835,
    "gn:feature_class":"P",
    "gn:feature_code":"PPL",
    "gn:name":"Potrero (Potrerillo)",
    "gn:population":390,
    "gn:timezone":"America/Mexico_City",
    "iso:country":"MX",
    "wof:name":"Potrero (Potrerillo)",
    "wof:placetype":"locality",
    "wof:population":390
},
  "geometry": {"coordinates":[-96.83222000000001,19.10861],"type":"Point"}
}