{
  "type": "Feature",
  "properties": {
    "gn:admin1_code":"16",
    "gn:admin2_code":"34.0",
    "gn:asciiname":"Agua del Pino",
    "gn:country_code":"MX",
    "gn:dem":2591,
    "gn:feature_class":"P",
    "gn:feature_code":"PPL",
    "gn:name":"Agua del Pino",
    "gn:population":95,
    "gn:timezone":"America/Mexico_City",
    "iso:country":"MX",
    "wof:name":"Agua del Pino",
    "wof:placetype":"locality",
    "wof:population":95
},
  "geometry": {"coordinates":[-100.54333,19.77611],"type":"Point"}
}