{
  "type": "Feature",
  "properties": {
    "gn:admin1_code":"5.0",
    "gn:asciiname":"El Borboton",
    "gn:country_code":"MX",
    "gn:dem":39,
    "gn:feature_class":"P",
    "gn:feature_code":"PPL",
    "gn:name":"El Borbot\u00f3n",
    "gn:population":0,
    "gn:timezone":"America/Mexico_City",
    "iso:country":"MX",
    "name:spa_x_preferred":[
        "El Borbot\u00f3n"
    ],
    "wof:name":"El Borboton",
    "wof:placetype":"locality"
},
  "geometry": {"coordinates":[-91.87595,17.71203],"type":"Point"}
}