{
  "type": "Feature",
  "properties": {
    "gn:admin1_code":"23",
    "gn:admin2_code":"2.0",
    "gn:asciiname":"Chumbalche",
    "gn:country_code":"MX",
    "gn:dem":29,
    "gn:feature_class":"P",
    "gn:feature_code":"PPL",
    "gn:name":"Chumbalch\u00e9",
    "gn:population":0,
    "gn:timezone":"America/Cancun",
    "iso:country":"MX",
    "name:und_x_variant":[
        "Chumbache",
        "Chumbalch\u00e9"
    ],
    "wof:name":"Chumbalche",
    "wof:placetype":"locality"
},
  "geometry": {"coordinates":[-88.2653,19.52916],"type":"Point"}
}