{
  "type": "Feature",
  "properties": {
    "gn:admin1_code":"13",
    "gn:admin2_code":"24.0",
    "gn:asciiname":"Tonteopa",
    "gn:country_code":"MX",
    "gn:dem":2079,
    "gn:feature_class":"P",
    "gn:feature_code":"PPL",
    "gn:name":"Tonteopa",
    "gn:population":108,
    "gn:timezone":"America/Mexico_City",
    "iso:country":"MX",
    "wof:name":"Tonteopa",
    "wof:placetype":"locality",
    "wof:population":108
},
  "geometry": {"coordinates":[-98.57106,20.21484],"type":"Point"}
}