{
  "type": "Feature",
  "properties": {
    "gn:admin1_code":"30",
    "gn:admin2_code":"116",
    "gn:asciiname":"Santa Elvia",
    "gn:country_code":"MX",
    "gn:dem":90,
    "gn:feature_class":"P",
    "gn:feature_code":"PPL",
    "gn:name":"Santa Elvia",
    "gn:population":13,
    "gn:timezone":"America/Mexico_City",
    "iso:country":"MX",
    "wof:name":"Santa Elvia",
    "wof:placetype":"locality",
    "wof:population":13
},
  "geometry": {"coordinates":[-94.87472,17.92333],"type":"Point"}
}