{
  "type": "Feature",
  "properties": {
    "gn:admin1_code":"12",
    "gn:admin2_code":"47.0",
    "gn:asciiname":"Rincon de Jumapa",
    "gn:country_code":"MX",
    "gn:dem":1546,
    "gn:feature_class":"P",
    "gn:feature_code":"PPL",
    "gn:name":"Rinc\u00f3n de Jumapa",
    "gn:population":142,
    "gn:timezone":"America/Mexico_City",
    "iso:country":"MX",
    "name:und_x_variant":[
        "Rinc\u00f3n de Jumapa"
    ],
    "wof:name":"Rincon de Jumapa",
    "wof:placetype":"locality",
    "wof:population":142
},
  "geometry": {"coordinates":[-99.95192,18.43752000000001],"type":"Point"}
}