{
  "type": "Feature",
  "properties": {
    "gn:admin1_code":"26",
    "gn:admin2_code":"10.0",
    "gn:asciiname":"San Jose de los Pozos",
    "gn:country_code":"MX",
    "gn:dem":2054,
    "gn:feature_class":"P",
    "gn:feature_code":"PPL",
    "gn:name":"San Jos\u00e9 de los Pozos",
    "gn:population":132,
    "gn:timezone":"America/Chihuahua",
    "iso:country":"MX",
    "wof:name":"San Jose de los Pozos",
    "wof:placetype":"locality",
    "wof:population":132
},
  "geometry": {"coordinates":[-108.55670000000001,30.27724000000001],"type":"Point"}
}