{
  "type": "Feature",
  "properties": {
    "gn:admin1_code":"12",
    "gn:admin2_code":"32.0",
    "gn:asciiname":"Reparo",
    "gn:country_code":"MX",
    "gn:dem":1496,
    "gn:feature_class":"P",
    "gn:feature_code":"PPL",
    "gn:name":"Reparo",
    "gn:population":0,
    "gn:timezone":"America/Mexico_City",
    "iso:country":"MX",
    "wof:name":"Reparo",
    "wof:placetype":"locality"
},
  "geometry": {"coordinates":[-99.88333,17.83333],"type":"Point"}
}