{
  "type": "Feature",
  "properties": {
    "gn:admin1_code":"26",
    "gn:admin2_code":"72.0",
    "gn:asciiname":"Tetabiate",
    "gn:country_code":"MX",
    "gn:dem":11,
    "gn:feature_class":"P",
    "gn:feature_code":"PPL",
    "gn:name":"Tetabiate",
    "gn:population":492,
    "gn:timezone":"America/Hermosillo",
    "iso:country":"MX",
    "wof:name":"Tetabiate",
    "wof:placetype":"locality",
    "wof:population":492
},
  "geometry": {"coordinates":[-110.32195,27.44593],"type":"Point"}
}