{
  "type": "Feature",
  "properties": {
    "gn:admin1_code":"14",
    "gn:admin2_code":"61",
    "gn:asciiname":"Los Zapatos",
    "gn:country_code":"MX",
    "gn:dem":1106,
    "gn:feature_class":"P",
    "gn:feature_code":"PPL",
    "gn:name":"Los Zapatos",
    "gn:population":27,
    "gn:timezone":"America/Mexico_City",
    "iso:country":"MX",
    "wof:name":"Los Zapatos",
    "wof:placetype":"locality",
    "wof:population":27
},
  "geometry": {"coordinates":[-104.26555999999999,22.1725],"type":"Point"}
}