{
  "type": "Feature",
  "properties": {
    "gn:admin1_code":"25.0",
    "gn:admin2_code":"7.0",
    "gn:asciiname":"Agua Caliente de Baca",
    "gn:country_code":"MX",
    "gn:dem":158,
    "gn:feature_class":"P",
    "gn:feature_code":"PPL",
    "gn:name":"Agua Caliente de Baca",
    "gn:population":0,
    "gn:timezone":"America/Mazatlan",
    "iso:country":"MX",
    "name:spa_x_preferred":[
        "Agua Caliente de Baca"
    ],
    "name:und_x_variant":[
        "Agua Caliente"
    ],
    "wof:name":"Agua Caliente de Baca",
    "wof:placetype":"locality"
},
  "geometry": {"coordinates":[-108.42685,26.80652000000001],"type":"Point"}
}