{
  "type": "Feature",
  "properties": {
    "gn:admin1_code":"16.0",
    "gn:admin2_code":"94.0",
    "gn:asciiname":"Jamanducuaro",
    "gn:country_code":"MX",
    "gn:dem":1859,
    "gn:feature_class":"P",
    "gn:feature_code":"PPL",
    "gn:name":"Jamanducuaro",
    "gn:population":0,
    "gn:timezone":"America/Mexico_City",
    "iso:country":"MX",
    "wof:name":"Jamanducuaro",
    "wof:placetype":"locality"
},
  "geometry": {"coordinates":[-102.04036000000001,20.02237],"type":"Point"}
}