{
  "type": "Feature",
  "properties": {
    "gn:admin1_code":"6",
    "gn:admin2_code":"45.0",
    "gn:asciiname":"Las Isabeles",
    "gn:country_code":"MX",
    "gn:dem":1159,
    "gn:feature_class":"P",
    "gn:feature_code":"PPL",
    "gn:name":"Las Isabeles",
    "gn:population":5,
    "gn:timezone":"America/Chihuahua",
    "iso:country":"MX",
    "wof:name":"Las Isabeles",
    "wof:placetype":"locality",
    "wof:population":5
},
  "geometry": {"coordinates":[-105.53574999999999,28.38298],"type":"Point"}
}