{
  "type": "Feature",
  "properties": {
    "gn:admin1_code":"16",
    "gn:admin2_code":"101.0",
    "gn:asciiname":"El Capulincito",
    "gn:country_code":"MX",
    "gn:dem":2031,
    "gn:feature_class":"P",
    "gn:feature_code":"PPL",
    "gn:name":"El Capulincito",
    "gn:population":0,
    "gn:timezone":"America/Mexico_City",
    "iso:country":"MX",
    "name:spa_x_preferred":[
        "El Capulincito"
    ],
    "wof:name":"El Capulincito",
    "wof:placetype":"locality"
},
  "geometry": {"coordinates":[-101.02255,19.42116],"type":"Point"}
}