{
  "type": "Feature",
  "properties": {
    "gn:admin1_code":"20",
    "gn:admin2_code":"125.0",
    "gn:asciiname":"San Miguel",
    "gn:country_code":"MX",
    "gn:dem":1149,
    "gn:feature_class":"P",
    "gn:feature_code":"PPL",
    "gn:name":"San Miguel",
    "gn:population":9,
    "gn:timezone":"America/Mexico_City",
    "iso:country":"MX",
    "wof:name":"San Miguel",
    "wof:placetype":"locality",
    "wof:population":9
},
  "geometry": {"coordinates":[-95.73639,16.84528],"type":"Point"}
}