{
  "type": "Feature",
  "properties": {
    "gn:admin1_code":"15",
    "gn:admin2_code":"87",
    "gn:asciiname":"Rancho Cordero",
    "gn:country_code":"MX",
    "gn:dem":2613,
    "gn:feature_class":"P",
    "gn:feature_code":"PPL",
    "gn:name":"Rancho Cordero",
    "gn:population":19,
    "gn:timezone":"America/Mexico_City",
    "iso:country":"MX",
    "wof:name":"Rancho Cordero",
    "wof:placetype":"locality",
    "wof:population":19
},
  "geometry": {"coordinates":[-99.60499,19.4664],"type":"Point"}
}