{
  "type": "Feature",
  "properties": {
    "gn:admin1_code":"30",
    "gn:admin2_code":"11.0",
    "gn:asciiname":"Isla de Tatayan",
    "gn:country_code":"MX",
    "gn:dem":4,
    "gn:feature_class":"P",
    "gn:feature_code":"PPL",
    "gn:name":"Isla de Tatay\u00e1n",
    "gn:population":5,
    "gn:timezone":"America/Mexico_City",
    "iso:country":"MX",
    "name:und_x_variant":[
        "Isla de Tatay\u00e1n"
    ],
    "wof:name":"Isla de Tatayan",
    "wof:placetype":"locality",
    "wof:population":5
},
  "geometry": {"coordinates":[-95.88249999999999,18.7075],"type":"Point"}
}