{
  "type": "Feature",
  "properties": {
    "gn:admin1_code":"25.0",
    "gn:admin2_code":"17.0",
    "gn:asciiname":"Gueera",
    "gn:cc2":"MX",
    "gn:country_code":"MX",
    "gn:dem":110,
    "gn:feature_class":"P",
    "gn:feature_code":"PPL",
    "gn:name":"G\u00fcera",
    "gn:population":148,
    "gn:timezone":"America/Mazatlan",
    "iso:country":"MX",
    "name:und_x_variant":[
        "Gueta",
        "G\u00fcera"
    ],
    "wof:name":"Gueera",
    "wof:placetype":"locality",
    "wof:population":148
},
  "geometry": {"coordinates":[-107.99527999999999,25.87944],"type":"Point"}
}