{
  "type": "Feature",
  "properties": {
    "gn:admin1_code":"30.0",
    "gn:admin2_code":"83.0",
    "gn:asciiname":"Piedra Grande la Sierra",
    "gn:country_code":"MX",
    "gn:dem":225,
    "gn:feature_class":"P",
    "gn:feature_code":"PPL",
    "gn:name":"Piedra Grande la Sierra",
    "gn:population":355,
    "gn:timezone":"America/Mexico_City",
    "iso:country":"MX",
    "name:spa_x_preferred":[
        "Piedra Grande la Sierra"
    ],
    "wof:name":"Piedra Grande la Sierra",
    "wof:placetype":"locality",
    "wof:population":355
},
  "geometry": {"coordinates":[-98.00333000000001,20.62417],"type":"Point"}
}