{
  "type": "Feature",
  "properties": {
    "gn:admin1_code":"6.0",
    "gn:admin2_code":"29.0",
    "gn:asciiname":"El Oyamel",
    "gn:country_code":"MX",
    "gn:dem":2672,
    "gn:feature_class":"P",
    "gn:feature_code":"PPL",
    "gn:name":"El Oyamel",
    "gn:population":0,
    "gn:timezone":"America/Chihuahua",
    "iso:country":"MX",
    "name:spa_x_preferred":[
        "El Oyamel"
    ],
    "wof:name":"El Oyamel",
    "wof:placetype":"locality"
},
  "geometry": {"coordinates":[-106.60693000000001,26.17786],"type":"Point"}
}