{
  "type": "Feature",
  "properties": {
    "gn:admin1_code":"2.0",
    "gn:admin2_code":"1.0",
    "gn:asciiname":"El Potrero",
    "gn:country_code":"MX",
    "gn:dem":11,
    "gn:feature_class":"P",
    "gn:feature_code":"PPL",
    "gn:name":"El Potrero",
    "gn:population":1,
    "gn:timezone":"America/Tijuana",
    "iso:country":"MX",
    "name:ceb_x_preferred":[
        "El Potrero"
    ],
    "name:ita_x_preferred":[
        "El Potrero"
    ],
    "name:spa_x_preferred":[
        "El Potrero"
    ],
    "name:srp_x_preferred":[
        "\u0415\u043b \u041f\u043e\u0442\u0440\u0435\u0440\u043e"
    ],
    "name:swe_x_preferred":[
        "El Potrero"
    ],
    "wof:name":"El Potrero",
    "wof:placetype":"locality",
    "wof:population":1
},
  "geometry": {"coordinates":[-115.98111000000002,30.60917],"type":"Point"}
}