{
  "type": "Feature",
  "properties": {
    "gn:admin1_code":"6.0",
    "gn:admin2_code":"29.0",
    "gn:asciiname":"Cienega de Santa Barbara",
    "gn:country_code":"MX",
    "gn:dem":2062,
    "gn:feature_class":"P",
    "gn:feature_code":"PPL",
    "gn:name":"Ci\u00e9nega de Santa B\u00e1rbara",
    "gn:population":0,
    "gn:timezone":"America/Chihuahua",
    "iso:country":"MX",
    "name:spa_x_preferred":[
        "Ci\u00e9nega de Santa B\u00e1rbara"
    ],
    "wof:name":"Cienega de Santa Barbara",
    "wof:placetype":"locality"
},
  "geometry": {"coordinates":[-106.78402,25.62196],"type":"Point"}
}