{
  "type": "Feature",
  "properties": {
    "gn:admin1_code":"11",
    "gn:admin2_code":"35",
    "gn:asciiname":"Numero Tres [Granja Avicola]",
    "gn:country_code":"MX",
    "gn:dem":1752,
    "gn:feature_class":"P",
    "gn:feature_code":"PPL",
    "gn:name":"N\u00famero Tres [Granja Av\u00edcola]",
    "gn:population":9,
    "gn:timezone":"America/Mexico_City",
    "iso:country":"MX",
    "name:und_x_variant":[
        "N\u00famero Tres [Granja Av\u00edcola]"
    ],
    "wof:name":"Numero Tres [Granja Avicola]",
    "wof:placetype":"locality",
    "wof:population":9
},
  "geometry": {"coordinates":[-100.88861,20.58833],"type":"Point"}
}