{
  "type": "Feature",
  "properties": {
    "gn:admin1_code":"22",
    "gn:admin2_code":"17.0",
    "gn:asciiname":"Familia Jimenez (Colonia Santa Fe)",
    "gn:country_code":"MX",
    "gn:dem":1906,
    "gn:feature_class":"P",
    "gn:feature_code":"PPL",
    "gn:name":"Familia Jim\u00e9nez (Colonia Santa Fe)",
    "gn:population":139,
    "gn:timezone":"America/Mexico_City",
    "iso:country":"MX",
    "name:und_x_variant":[
        "Familia Jim\u00e9nez (Colonia Santa Fe)"
    ],
    "wof:name":"Familia Jimenez (Colonia Santa Fe)",
    "wof:placetype":"locality",
    "wof:population":139
},
  "geometry": {"coordinates":[-99.89082999999999,20.50556],"type":"Point"}
}