{
  "type": "Feature",
  "properties": {
    "gn:admin1_code":"12",
    "gn:admin2_code":"19",
    "gn:asciiname":"Atlixtic",
    "gn:country_code":"MX",
    "gn:dem":562,
    "gn:feature_class":"P",
    "gn:feature_code":"PPL",
    "gn:name":"Atlixtic",
    "gn:population":23,
    "gn:timezone":"America/Mexico_City",
    "iso:country":"MX",
    "wof:name":"Atlixtic",
    "wof:placetype":"locality",
    "wof:population":23
},
  "geometry": {"coordinates":[-99.12499,17.88237],"type":"Point"}
}