{
  "type": "Feature",
  "properties": {
    "gn:admin1_code":"32.0",
    "gn:admin2_code":"42.0",
    "gn:asciiname":"La Loma de San Rafael",
    "gn:country_code":"MX",
    "gn:dem":2333,
    "gn:feature_class":"P",
    "gn:feature_code":"PPL",
    "gn:name":"La Loma de San Rafael",
    "gn:population":0,
    "gn:timezone":"America/Mexico_City",
    "iso:country":"MX",
    "name:spa_x_preferred":[
        "La Loma de San Rafael"
    ],
    "wof:name":"La Loma de San Rafael",
    "wof:placetype":"locality"
},
  "geometry": {"coordinates":[-103.44665999999999,23.74759],"type":"Point"}
}