{
  "type": "Feature",
  "properties": {
    "gn:admin1_code":"30",
    "gn:admin2_code":"148.0",
    "gn:asciiname":"Paso las Pintas",
    "gn:country_code":"MX",
    "gn:dem":69,
    "gn:feature_class":"P",
    "gn:feature_code":"PPL",
    "gn:name":"Paso las Pintas",
    "gn:population":262,
    "gn:timezone":"America/Mexico_City",
    "iso:country":"MX",
    "wof:name":"Paso las Pintas",
    "wof:placetype":"locality",
    "wof:population":262
},
  "geometry": {"coordinates":[-96.38806,19.05889],"type":"Point"}
}