{
  "type": "Feature",
  "properties": {
    "gn:admin1_code":"28",
    "gn:admin2_code":"42.0",
    "gn:asciiname":"Nicolas Flores",
    "gn:country_code":"MX",
    "gn:dem":361,
    "gn:feature_class":"P",
    "gn:feature_code":"PPL",
    "gn:name":"Nicol\u00e1s Flores",
    "gn:population":0,
    "gn:timezone":"America/Monterrey",
    "iso:country":"MX",
    "name:spa_x_preferred":[
        "Nicol\u00e1s Flores"
    ],
    "name:spa_x_variant":[
        "Barretas"
    ],
    "wof:name":"Nicolas Flores",
    "wof:placetype":"locality"
},
  "geometry": {"coordinates":[-99.47324,24.52718],"type":"Point"}
}