{
  "type": "Feature",
  "properties": {
    "gn:admin1_code":"12",
    "gn:admin2_code":"16.0",
    "gn:asciiname":"Las Juntas de Bustos (Las Juntas)",
    "gn:country_code":"MX",
    "gn:dem":183,
    "gn:feature_class":"P",
    "gn:feature_code":"PPL",
    "gn:name":"Las Juntas de Bustos (Las Juntas)",
    "gn:population":118,
    "gn:timezone":"America/Mexico_City",
    "iso:country":"MX",
    "wof:name":"Las Juntas de Bustos (Las Juntas)",
    "wof:placetype":"locality",
    "wof:population":118
},
  "geometry": {"coordinates":[-101.77222999999999,18.28101],"type":"Point"}
}