{
  "type": "Feature",
  "properties": {
    "gn:admin1_code":"6.0",
    "gn:admin2_code":"32.0",
    "gn:asciiname":"Juan Mateo",
    "gn:cc2":"MX",
    "gn:country_code":"MX",
    "gn:dem":1855,
    "gn:feature_class":"P",
    "gn:feature_code":"PPL",
    "gn:name":"Juan Mateo",
    "gn:population":0,
    "gn:timezone":"America/Chihuahua",
    "iso:country":"MX",
    "name:ara_x_preferred":[
        "\u062d\u0632\u0642\u064a\u0627\u0644 \u0645\u0627\u062a\u064a\u0648"
    ],
    "name:spa_x_preferred":[
        "Juan Mateo"
    ],
    "name:und_x_variant":[
        "Mateo",
        "Juan Mateo"
    ],
    "wof:name":"Juan Mateo",
    "wof:placetype":"locality"
},
  "geometry": {"coordinates":[-105.88333,27.01667],"type":"Point"}
}