{
  "type": "Feature",
  "properties": {
    "gn:admin1_code":"10",
    "gn:admin2_code":"14.0",
    "gn:asciiname":"Santa Monica",
    "gn:country_code":"MX",
    "gn:dem":1829,
    "gn:feature_class":"P",
    "gn:feature_code":"PPL",
    "gn:name":"Santa M\u00f3nica",
    "gn:population":0,
    "gn:timezone":"America/Monterrey",
    "iso:country":"MX",
    "name:spa_x_preferred":[
        "Santa M\u00f3nica"
    ],
    "wof:name":"Santa Monica",
    "wof:placetype":"locality"
},
  "geometry": {"coordinates":[-104.43818,23.7085],"type":"Point"}
}