{
  "type": "Feature",
  "properties": {
    "gn:admin1_code":"30",
    "gn:admin2_code":"48.0",
    "gn:asciiname":"La Nacional",
    "gn:country_code":"MX",
    "gn:dem":28,
    "gn:feature_class":"P",
    "gn:feature_code":"PPL",
    "gn:name":"La Nacional",
    "gn:population":9,
    "gn:timezone":"America/Mexico_City",
    "iso:country":"MX",
    "wof:name":"La Nacional",
    "wof:placetype":"locality",
    "wof:population":9
},
  "geometry": {"coordinates":[-94.57444,18.03222],"type":"Point"}
}