{
  "type": "Feature",
  "properties": {
    "gn:admin1_code":"10",
    "gn:admin2_code":"10.0",
    "gn:asciiname":"Valle Verde",
    "gn:country_code":"MX",
    "gn:dem":1949,
    "gn:feature_class":"P",
    "gn:feature_code":"PPL",
    "gn:name":"Valle Verde",
    "gn:population":0,
    "gn:timezone":"America/Monterrey",
    "iso:country":"MX",
    "name:spa_x_preferred":[
        "Valle Verde"
    ],
    "name:und_x_variant":[
        "La Mula"
    ],
    "wof:name":"Valle Verde",
    "wof:placetype":"locality"
},
  "geometry": {"coordinates":[-105.07423,26.06864],"type":"Point"}
}