{
  "type": "Feature",
  "properties": {
    "gn:admin1_code":"6",
    "gn:admin2_code":"9",
    "gn:asciiname":"Machoge",
    "gn:country_code":"MX",
    "gn:dem":2318,
    "gn:feature_class":"P",
    "gn:feature_code":"PPL",
    "gn:name":"Machoge",
    "gn:population":9,
    "gn:timezone":"America/Chihuahua",
    "iso:country":"MX",
    "wof:name":"Machoge",
    "wof:placetype":"locality",
    "wof:population":9
},
  "geometry": {"coordinates":[-107.7727,27.65047],"type":"Point"}
}