{
  "type": "Feature",
  "properties": {
    "gn:admin1_code":"24",
    "gn:admin2_code":"58.0",
    "gn:asciiname":"La Victoria",
    "gn:country_code":"MX",
    "gn:dem":270,
    "gn:feature_class":"P",
    "gn:feature_code":"PPL",
    "gn:name":"La Victoria",
    "gn:population":78,
    "gn:timezone":"America/Mexico_City",
    "iso:country":"MX",
    "wof:name":"La Victoria",
    "wof:placetype":"locality",
    "wof:population":78
},
  "geometry": {"coordinates":[-99.30083,22.46889],"type":"Point"}
}