{
  "type": "Feature",
  "properties": {
    "gn:admin1_code":"11",
    "gn:admin2_code":"30",
    "gn:asciiname":"Quinta Paola (Kilometro 26)",
    "gn:country_code":"MX",
    "gn:dem":2692,
    "gn:feature_class":"P",
    "gn:feature_code":"PPL",
    "gn:name":"Quinta Paola (Kil\u00f3metro 26)",
    "gn:population":9,
    "gn:timezone":"America/Mexico_City",
    "iso:country":"MX",
    "name:und_x_variant":[
        "Quinta Paola (Kil\u00f3metro 26)"
    ],
    "wof:name":"Quinta Paola (Kilometro 26)",
    "wof:placetype":"locality",
    "wof:population":9
},
  "geometry": {"coordinates":[-101.61694,21.33389],"type":"Point"}
}