{
  "type": "Feature",
  "properties": {
    "gn:admin1_code":"14",
    "gn:admin2_code":"118.0",
    "gn:asciiname":"Los Silos (Bellavista)",
    "gn:country_code":"MX",
    "gn:dem":1896,
    "gn:feature_class":"P",
    "gn:feature_code":"PPL",
    "gn:name":"Los Silos (Bellavista)",
    "gn:population":8,
    "gn:timezone":"America/Mexico_City",
    "iso:country":"MX",
    "wof:name":"Los Silos (Bellavista)",
    "wof:placetype":"locality",
    "wof:population":8
},
  "geometry": {"coordinates":[-102.87889,21.055],"type":"Point"}
}