{
  "type": "Feature",
  "properties": {
    "gn:admin1_code":"13",
    "gn:admin2_code":"76.0",
    "gn:asciiname":"El Ocote",
    "gn:cc2":"MX",
    "gn:country_code":"MX",
    "gn:dem":2075,
    "gn:feature_class":"P",
    "gn:feature_code":"PPL",
    "gn:name":"El Ocote",
    "gn:population":15,
    "gn:timezone":"America/Mexico_City",
    "iso:country":"MX",
    "name:und_x_variant":[
        "Ocote",
        "El Ocote",
        "El Ocotal"
    ],
    "wof:name":"El Ocote",
    "wof:placetype":"locality",
    "wof:population":15
},
  "geometry": {"coordinates":[-99.34944,20.01694],"type":"Point"}
}