{
  "type": "Feature",
  "properties": {
    "gn:admin1_code":"26.0",
    "gn:admin2_code":"18.0",
    "gn:asciiname":"Francisco Villa",
    "gn:country_code":"MX",
    "gn:dem":41,
    "gn:feature_class":"P",
    "gn:feature_code":"PPL",
    "gn:name":"Francisco Villa",
    "gn:population":0,
    "gn:timezone":"America/Hermosillo",
    "iso:country":"MX",
    "name:spa_x_preferred":[
        "Francisco Villa"
    ],
    "wof:name":"Francisco Villa",
    "wof:placetype":"locality"
},
  "geometry": {"coordinates":[-109.91108,27.35525],"type":"Point"}
}