{
  "type": "Feature",
  "properties": {
    "gn:admin1_code":"6",
    "gn:admin2_code":"7.0",
    "gn:asciiname":"El Embudo",
    "gn:country_code":"MX",
    "gn:dem":2664,
    "gn:feature_class":"P",
    "gn:feature_code":"PPL",
    "gn:name":"El Embudo",
    "gn:population":0,
    "gn:timezone":"America/Monterrey",
    "iso:country":"MX",
    "name:spa_x_preferred":[
        "El Embudo"
    ],
    "wof:name":"El Embudo",
    "wof:placetype":"locality"
},
  "geometry": {"coordinates":[-106.33765,26.33944],"type":"Point"}
}