{
  "type": "Feature",
  "properties": {
    "gn:admin1_code":"16.0",
    "gn:admin2_code":"66.0",
    "gn:asciiname":"Janitzio",
    "gn:country_code":"MX",
    "gn:dem":2100,
    "gn:feature_class":"P",
    "gn:feature_code":"PPL",
    "gn:name":"Janitzio",
    "gn:population":0,
    "gn:timezone":"America/Mexico_City",
    "iso:country":"MX",
    "name:und_x_variant":[
        "Isla de Janitzio"
    ],
    "wof:name":"Janitzio",
    "wof:placetype":"locality"
},
  "geometry": {"coordinates":[-101.65188999999999,19.57327],"type":"Point"}
}