{
  "type": "Feature",
  "properties": {
    "gn:gn_country":"MX",
    "gn:gn_fcode":"PPL",
    "gn:gn_pop":0,
    "gn:population":753,
    "iso:country":"MX",
    "name:spa_x_preferred":[
        "Francisco Villa"
    ],
    "name:unk_x_variant":[
        "Francisco Vitta"
    ],
    "qs_pg:aaroncc":"MX",
    "qs_pg:gn_country":"MX",
    "qs_pg:gn_fcode":"PPL",
    "qs_pg:gn_pop":0,
    "qs_pg:name":"Francisco Villa",
    "qs_pg:name_adm0":"M\u00e9xico",
    "qs_pg:name_adm1":"Aguascalientes",
    "qs_pg:photos":28,
    "qs_pg:photos_1k":6,
    "qs_pg:photos_9k":1,
    "qs_pg:photos_9r":2,
    "qs_pg:photos_all":28,
    "qs_pg:photos_sr":2,
    "qs_pg:pop_sr":0,
    "qs_pg:qs_pg_placetype":"neighbourhood",
    "qs_pg:qs_pg_placetype_gp":"Suburb",
    "qs_pg:woe_adm0":23424900,
    "woe:adm0_id":23424900,
    "woe:name_adm0":"M\u00e9xico",
    "woe:name_adm1":"Aguascalientes",
    "woe:placetype":"Suburb",
    "wof:name":"Francisco Villa",
    "wof:placetype":"neighbourhood",
    "wof:population":753
},
  "geometry": {"coordinates":[-101.96801000000001,22.08837],"type":"Point"}
}