{
  "type": "Feature",
  "properties": {
    "gn:admin1_code":"25",
    "gn:admin2_code":"6",
    "gn:asciiname":"Vitroflothier de Sinaloa (Industria Esperanza)",
    "gn:country_code":"MX",
    "gn:dem":22,
    "gn:feature_class":"P",
    "gn:feature_code":"PPL",
    "gn:name":"Vitroflothier de Sinaloa (Industria Esperanza)",
    "gn:population":17,
    "gn:timezone":"America/Mazatlan",
    "iso:country":"MX",
    "wof:name":"Vitroflothier de Sinaloa (Industria Esperanza)",
    "wof:placetype":"locality",
    "wof:population":17
},
  "geometry": {"coordinates":[-107.44249000000001,24.63614],"type":"Point"}
}