{
  "type": "Feature",
  "properties": {
    "gn:admin1_code":"12.0",
    "gn:admin2_code":"41.0",
    "gn:asciiname":"Tepehuaje",
    "gn:country_code":"MX",
    "gn:dem":2148,
    "gn:feature_class":"P",
    "gn:feature_code":"PPL",
    "gn:name":"Tepehuaje",
    "gn:population":0,
    "gn:timezone":"America/Mexico_City",
    "iso:country":"MX",
    "name:spa_x_preferred":[
        "Tepehuaje"
    ],
    "wof:name":"Tepehuaje",
    "wof:placetype":"locality"
},
  "geometry": {"coordinates":[-98.61078000000001,17.27995],"type":"Point"}
}