{
  "type": "Feature",
  "properties": {
    "gn:admin1_code":"5",
    "gn:admin2_code":"29.0",
    "gn:asciiname":"La Represa",
    "gn:country_code":"MX",
    "gn:dem":551,
    "gn:feature_class":"P",
    "gn:feature_code":"PPL",
    "gn:name":"La Represa",
    "gn:population":154,
    "gn:timezone":"America/Mexico_City",
    "iso:country":"MX",
    "name:ita_x_preferred":[
        "La Represa"
    ],
    "name:spa_x_preferred":[
        "La Represa"
    ],
    "name:zho_x_preferred":[
        "\u62c9\u96f7\u666e\u96f7\u85a9"
    ],
    "wof:name":"La Represa",
    "wof:placetype":"locality",
    "wof:population":154
},
  "geometry": {"coordinates":[-93.15555999999999,17.01472],"type":"Point"}
}