{
  "type": "Feature",
  "properties": {
    "gn:admin1_code":"16",
    "gn:admin2_code":"49.0",
    "gn:asciiname":"Corral Falso",
    "gn:country_code":"MX",
    "gn:dem":1687,
    "gn:feature_class":"P",
    "gn:feature_code":"PPL",
    "gn:name":"Corral Falso",
    "gn:population":0,
    "gn:timezone":"America/Mexico_City",
    "iso:country":"MX",
    "name:spa_x_preferred":[
        "Corral Falso"
    ],
    "wof:name":"Corral Falso",
    "wof:placetype":"locality"
},
  "geometry": {"coordinates":[-101.1549,19.43176],"type":"Point"}
}