{
  "type": "Feature",
  "properties": {
    "iso:country":"MX",
    "name:spa_x_preferred":[
        "Barrio de Guadalupe"
    ],
    "qs:gn_adm0_cc":"MX",
    "qs:gn_fcode":"PPL",
    "qs:gn_local":3516225,
    "qs:gn_nam_loc":"Taxco de Alarcon, Taxco de Alarc\u00f3n, Guerrero, MX",
    "qs:gn_namadm1":"15",
    "qs:gn_name":"Barrio de Guadalupe",
    "qs:local_max":734,
    "qs:local_sum":962,
    "qs:localhoods":2,
    "qs:name":"Barrio de Guadalupe",
    "qs:name_adm0":"M\u00e9xico",
    "qs:name_adm1":"Guerrero",
    "qs:name_adm2":"Taxco de Alarcon",
    "qs:name_local":"Taxco de Alarc\u00f3n",
    "qs:photo_max":120,
    "qs:photo_sum":228,
    "qs:placetype":"Suburb",
    "qs:quad_count":8,
    "qs:woe_adm0":23424900,
    "qs:woe_adm1":2346275,
    "qs:woe_adm2":12600091,
    "qs:woe_lau":0,
    "qs:woe_local":148381,
    "qs:woe_ver":"7.10.0",
    "wof:lang":[
        "spa"
    ],
    "wof:name":"Barrio de Guadalupe",
    "wof:placetype":"neighbourhood"
},
  "geometry": {"coordinates":[-99.607282,18.556412],"type":"Point"}
}