{
  "type": "Feature",
  "properties": {
    "gn:admin1_code":"7.0",
    "gn:admin2_code":"24.0",
    "gn:asciiname":"Ejido El Cinco",
    "gn:country_code":"MX",
    "gn:dem":2156,
    "gn:feature_class":"P",
    "gn:feature_code":"PPL",
    "gn:name":"Ejido El Cinco",
    "gn:population":0,
    "gn:timezone":"America/Monterrey",
    "iso:country":"MX",
    "wof:name":"Ejido El Cinco",
    "wof:placetype":"locality"
},
  "geometry": {"coordinates":[-101.63333,25.18333],"type":"Point"}
}