{
  "type": "Feature",
  "properties": {
    "gn:admin1_code":"16",
    "gn:admin2_code":"99.0",
    "gn:asciiname":"Joyas de Vigas",
    "gn:country_code":"MX",
    "gn:dem":2123,
    "gn:feature_class":"P",
    "gn:feature_code":"PPL",
    "gn:name":"Joyas de Vigas",
    "gn:population":75,
    "gn:timezone":"America/Mexico_City",
    "iso:country":"MX",
    "wof:name":"Joyas de Vigas",
    "wof:placetype":"locality",
    "wof:population":75
},
  "geometry": {"coordinates":[-100.62944,19.40056],"type":"Point"}
}