{
  "type": "Feature",
  "properties": {
    "gn:admin1_code":"32",
    "gn:admin2_code":"51.0",
    "gn:asciiname":"Arroyo El Durazno",
    "gn:country_code":"MX",
    "gn:dem":2088,
    "gn:feature_class":"P",
    "gn:feature_code":"PPL",
    "gn:name":"Arroyo El Durazno",
    "gn:population":0,
    "gn:timezone":"America/Mexico_City",
    "iso:country":"MX",
    "wof:name":"Arroyo El Durazno",
    "wof:placetype":"locality"
},
  "geometry": {"coordinates":[-101.71666999999999,23.68333],"type":"Point"}
}