{
  "type": "Feature",
  "properties": {
    "gn:admin1_code":"10",
    "gn:admin2_code":"5.0",
    "gn:asciiname":"Puerta de la Cantera",
    "gn:country_code":"MX",
    "gn:dem":1893,
    "gn:feature_class":"P",
    "gn:feature_code":"PPL",
    "gn:name":"Puerta de la Cantera",
    "gn:population":475,
    "gn:timezone":"America/Monterrey",
    "iso:country":"MX",
    "wof:name":"Puerta de la Cantera",
    "wof:placetype":"locality",
    "wof:population":475
},
  "geometry": {"coordinates":[-104.59389,23.90694],"type":"Point"}
}