{
  "type": "Feature",
  "properties": {
    "gn:admin1_code":"15.0",
    "gn:admin2_code":"80.0",
    "gn:asciiname":"Totolmanca",
    "gn:country_code":"MX",
    "gn:dem":1195,
    "gn:feature_class":"P",
    "gn:feature_code":"PPL",
    "gn:name":"Totolmanca",
    "gn:population":0,
    "gn:timezone":"America/Mexico_City",
    "iso:country":"MX",
    "name:spa_x_preferred":[
        "Totolmanca"
    ],
    "wof:name":"Totolmanca",
    "wof:placetype":"locality"
},
  "geometry": {"coordinates":[-100.0822,18.80657],"type":"Point"}
}