{
  "type": "Feature",
  "properties": {
    "gn:admin1_code":"14",
    "gn:admin2_code":"104.0",
    "gn:asciiname":"La Tuna Amarilla",
    "gn:country_code":"MX",
    "gn:dem":1677,
    "gn:feature_class":"P",
    "gn:feature_code":"PPL",
    "gn:name":"La Tuna Amarilla",
    "gn:population":0,
    "gn:timezone":"America/Mexico_City",
    "iso:country":"MX",
    "name:spa_x_preferred":[
        "La Tuna Amarilla"
    ],
    "wof:name":"La Tuna Amarilla",
    "wof:placetype":"locality"
},
  "geometry": {"coordinates":[-103.5128,22.0266],"type":"Point"}
}