{
  "type": "Feature",
  "properties": {
    "gn:admin1_code":"16",
    "gn:admin2_code":"92",
    "gn:asciiname":"Las Trojas",
    "gn:country_code":"MX",
    "gn:dem":1785,
    "gn:feature_class":"P",
    "gn:feature_code":"PPL",
    "gn:name":"Las Trojas",
    "gn:population":17,
    "gn:timezone":"America/Mexico_City",
    "iso:country":"MX",
    "wof:name":"Las Trojas",
    "wof:placetype":"locality",
    "wof:population":17
},
  "geometry": {"coordinates":[-100.97167,19.27417],"type":"Point"}
}