{
  "type": "Feature",
  "properties": {
    "gn:admin1_code":"23",
    "gn:admin2_code":"7",
    "gn:asciiname":"Yokdzonot",
    "gn:country_code":"MX",
    "gn:dem":5,
    "gn:feature_class":"P",
    "gn:feature_code":"PPL",
    "gn:name":"Yokdzonot",
    "gn:population":13,
    "gn:timezone":"America/Cancun",
    "iso:country":"MX",
    "wof:name":"Yokdzonot",
    "wof:placetype":"locality",
    "wof:population":13
},
  "geometry": {"coordinates":[-87.66444,20.66667],"type":"Point"}
}