{
  "type": "Feature",
  "properties": {
    "gn:admin1_code":"3.0",
    "gn:admin2_code":"3.0",
    "gn:asciiname":"La Divina Providencia",
    "gn:country_code":"MX",
    "gn:dem":181,
    "gn:feature_class":"P",
    "gn:feature_code":"PPL",
    "gn:name":"La Divina Providencia",
    "gn:population":0,
    "gn:timezone":"America/Mazatlan",
    "iso:country":"MX",
    "name:spa_x_preferred":[
        "La Divina Providencia"
    ],
    "wof:name":"La Divina Providencia",
    "wof:placetype":"locality"
},
  "geometry": {"coordinates":[-110.27011,24.01641],"type":"Point"}
}