{
  "type": "Feature",
  "properties": {
    "gn:admin1_code":"10",
    "gn:admin2_code":"14.0",
    "gn:asciiname":"Cuesta Blanca (Agueita Escondida)",
    "gn:country_code":"MX",
    "gn:dem":2680,
    "gn:feature_class":"P",
    "gn:feature_code":"PPL",
    "gn:name":"Cuesta Blanca (Ag\u00fcita Escondida)",
    "gn:population":79,
    "gn:timezone":"America/Monterrey",
    "iso:country":"MX",
    "name:und_x_variant":[
        "Cuesta Blanca (Ag\u00fcita Escondida)"
    ],
    "wof:name":"Cuesta Blanca (Agueita Escondida)",
    "wof:placetype":"locality",
    "wof:population":79
},
  "geometry": {"coordinates":[-104.34303,23.29003],"type":"Point"}
}