{
  "type": "Feature",
  "properties": {
    "gn:admin1_code":"20",
    "gn:admin2_code":"133",
    "gn:asciiname":"Totohi",
    "gn:country_code":"MX",
    "gn:dem":2863,
    "gn:feature_class":"P",
    "gn:feature_code":"PPL",
    "gn:name":"Totohi",
    "gn:population":35,
    "gn:timezone":"America/Mexico_City",
    "iso:country":"MX",
    "wof:name":"Totohi",
    "wof:placetype":"locality",
    "wof:population":35
},
  "geometry": {"coordinates":[-97.69139,17.09861],"type":"Point"}
}