{
  "type": "Feature",
  "properties": {
    "gn:admin1_code":"15.0",
    "gn:asciiname":"La Aguililla",
    "gn:country_code":"MX",
    "gn:dem":345,
    "gn:feature_class":"P",
    "gn:feature_code":"PPL",
    "gn:name":"La Aguililla",
    "gn:population":0,
    "gn:timezone":"America/Mexico_City",
    "iso:country":"MX",
    "name:spa_x_preferred":[
        "La Aguililla"
    ],
    "wof:name":"La Aguililla",
    "wof:placetype":"locality"
},
  "geometry": {"coordinates":[-102.37733,18.12451],"type":"Point"}
}