{
  "type": "Feature",
  "properties": {
    "gn:admin1_code":"12.0",
    "gn:admin2_code":"27.0",
    "gn:asciiname":"El Tigre",
    "gn:country_code":"MX",
    "gn:dem":622,
    "gn:feature_class":"P",
    "gn:feature_code":"PPL",
    "gn:name":"El Tigre",
    "gn:population":0,
    "gn:timezone":"America/Mexico_City",
    "iso:country":"MX",
    "name:spa_x_preferred":[
        "El Tigre"
    ],
    "wof:name":"El Tigre",
    "wof:placetype":"locality"
},
  "geometry": {"coordinates":[-100.54382,18.58444],"type":"Point"}
}