{
  "type": "Feature",
  "properties": {
    "gn:admin1_code":"14",
    "gn:admin2_code":"56.0",
    "gn:asciiname":"Abasolo (La Otra Casa)",
    "gn:country_code":"MX",
    "gn:dem":726,
    "gn:feature_class":"P",
    "gn:feature_code":"PPL",
    "gn:name":"Abasolo (La Otra Casa)",
    "gn:population":73,
    "gn:timezone":"America/Mexico_City",
    "iso:country":"MX",
    "wof:name":"Abasolo (La Otra Casa)",
    "wof:placetype":"locality",
    "wof:population":73
},
  "geometry": {"coordinates":[-102.82333,19.47389],"type":"Point"}
}