{
  "type": "Feature",
  "properties": {
    "gn:admin1_code":"11",
    "gn:admin2_code":"26",
    "gn:asciiname":"Granja San Hipolito (Don Eufemio)",
    "gn:country_code":"MX",
    "gn:dem":1750,
    "gn:feature_class":"P",
    "gn:feature_code":"PPL",
    "gn:name":"Granja San Hip\u00f3lito (Don Eufemio)",
    "gn:population":30,
    "gn:timezone":"America/Mexico_City",
    "iso:country":"MX",
    "name:und_x_variant":[
        "Granja San Hip\u00f3lito (Don Eufemio)"
    ],
    "wof:name":"Granja San Hipolito (Don Eufemio)",
    "wof:placetype":"locality",
    "wof:population":30
},
  "geometry": {"coordinates":[-101.50778,20.87833],"type":"Point"}
}