{
  "type": "Feature",
  "properties": {
    "gn:admin1_code":"10.0",
    "gn:admin2_code":"31.0",
    "gn:asciiname":"Las Curvas",
    "gn:country_code":"MX",
    "gn:dem":1815,
    "gn:feature_class":"P",
    "gn:feature_code":"PPL",
    "gn:name":"Las Curvas",
    "gn:population":0,
    "gn:timezone":"America/Monterrey",
    "iso:country":"MX",
    "name:spa_x_preferred":[
        "Las Curvas"
    ],
    "wof:name":"Las Curvas",
    "wof:placetype":"locality"
},
  "geometry": {"coordinates":[-103.36978999999999,24.47469],"type":"Point"}
}