{
  "type": "Feature",
  "properties": {
    "gn:admin1_code":"6.0",
    "gn:admin2_code":"30.0",
    "gn:asciiname":"Cordon de Chuihayvo",
    "gn:country_code":"MX",
    "gn:dem":2112,
    "gn:feature_class":"P",
    "gn:feature_code":"PPL",
    "gn:name":"Cord\u00f3n de Chuihayvo",
    "gn:population":0,
    "gn:timezone":"America/Chihuahua",
    "iso:country":"MX",
    "name:spa_x_preferred":[
        "Cord\u00f3n de Chuihayvo"
    ],
    "wof:name":"Cordon de Chuihayvo",
    "wof:placetype":"locality"
},
  "geometry": {"coordinates":[-108.10408,27.45168],"type":"Point"}
}