{
  "type": "Feature",
  "properties": {
    "gn:admin1_code":"5",
    "gn:admin2_code":"87.0",
    "gn:asciiname":"Lucio Cabana",
    "gn:country_code":"MX",
    "gn:dem":13,
    "gn:feature_class":"P",
    "gn:feature_code":"PPL",
    "gn:name":"Lucio Caba\u00f1a",
    "gn:population":138,
    "gn:timezone":"America/Mexico_City",
    "iso:country":"MX",
    "name:und_x_variant":[
        "Lucio Caba\u00f1a"
    ],
    "wof:name":"Lucio Cabana",
    "wof:placetype":"locality",
    "wof:population":138
},
  "geometry": {"coordinates":[-92.2475,14.66333],"type":"Point"}
}