{
  "type": "Feature",
  "properties": {
    "gn:admin1_code":"26",
    "gn:admin2_code":"40.0",
    "gn:asciiname":"Los Sauces",
    "gn:country_code":"MX",
    "gn:dem":981,
    "gn:feature_class":"P",
    "gn:feature_code":"PPL",
    "gn:name":"Los Sauces",
    "gn:population":0,
    "gn:timezone":"America/Hermosillo",
    "iso:country":"MX",
    "name:spa_x_preferred":[
        "Los Sauces"
    ],
    "wof:name":"Los Sauces",
    "wof:placetype":"locality"
},
  "geometry": {"coordinates":[-108.83714999999999,29.65751],"type":"Point"}
}