{
  "type": "Feature",
  "properties": {
    "iso:country":"MX",
    "name:ceb_x_preferred":[
        "El Calvario"
    ],
    "name:fra_x_preferred":[
        "El Calvario"
    ],
    "name:ita_x_preferred":[
        "El Calvario"
    ],
    "name:kat_x_preferred":[
        "\u10d4\u10da-\u10d9\u10d0\u10da\u10d5\u10d0\u10e0\u10d8\u10dd"
    ],
    "name:msa_x_preferred":[
        "El Calvario"
    ],
    "name:nld_x_preferred":[
        "El Calvario"
    ],
    "name:por_x_preferred":[
        "El Calvario"
    ],
    "name:spa_x_preferred":[
        "El Calvario"
    ],
    "name:swe_x_preferred":[
        "El Calvario"
    ],
    "name:tgl_x_preferred":[
        "El Calvario"
    ],
    "name:vie_x_preferred":[
        "El Calvario"
    ],
    "name:war_x_preferred":[
        "El Calvario"
    ],
    "name:zho_x_preferred":[
        "\u57c3\u723e\u5361\u723e\u74e6\u91cc\u5967"
    ],
    "qs:gn_adm0_cc":"MX",
    "qs:gn_local":3530150,
    "qs:gn_nam_loc":"coxcatlan",
    "qs:gn_namadm1":"21",
    "qs:local_max":51,
    "qs:local_sum":51,
    "qs:localhoods":1,
    "qs:name":"El Calvario",
    "qs:name_adm0":"M\u00e9xico",
    "qs:name_adm1":"Puebla",
    "qs:name_adm2":"Coxcatlan",
    "qs:name_local":"Coxcatl\u00e1n",
    "qs:photo_max":51,
    "qs:photo_sum":51,
    "qs:placetype":"Suburb",
    "qs:quad_count":1,
    "qs:woe_adm0":23424900,
    "qs:woe_adm1":2346284,
    "qs:woe_adm2":12601277,
    "qs:woe_lau":0,
    "qs:woe_local":117530,
    "qs:woe_ver":"7.10.0",
    "wof:lang":[
        "spa"
    ],
    "wof:name":"El Calvario",
    "wof:placetype":"neighbourhood"
},
  "geometry": {"coordinates":[-97.14798,18.267174],"type":"Point"}
}