{
  "type": "Feature",
  "properties": {
    "gn:admin1_code":"13",
    "gn:admin2_code":"60.0",
    "gn:asciiname":"San Jose del Valle",
    "gn:country_code":"MX",
    "gn:dem":1194,
    "gn:feature_class":"P",
    "gn:feature_code":"PPL",
    "gn:name":"San Jos\u00e9 del Valle",
    "gn:population":0,
    "gn:timezone":"America/Mexico_City",
    "iso:country":"MX",
    "name:spa_x_preferred":[
        "San Jos\u00e9 del Valle"
    ],
    "wof:name":"San Jose del Valle",
    "wof:placetype":"locality"
},
  "geometry": {"coordinates":[-98.13899000000001,20.38503],"type":"Point"}
}