{
  "type": "Feature",
  "properties": {
    "gn:admin1_code":"27.0",
    "gn:asciiname":"Rio Viejo Tercera Seccion",
    "gn:country_code":"MX",
    "gn:dem":14,
    "gn:feature_class":"P",
    "gn:feature_code":"PPL",
    "gn:name":"R\u00edo Viejo Tercera Secci\u00f3n",
    "gn:population":0,
    "gn:timezone":"America/Mexico_City",
    "iso:country":"MX",
    "name:spa_x_preferred":[
        "R\u00edo Viejo Tercera Secci\u00f3n"
    ],
    "name:spa_x_variant":[
        "R\u00edo Viejo",
        "Tercera Secci\u00f3n"
    ],
    "wof:name":"Rio Viejo Tercera Seccion",
    "wof:placetype":"locality"
},
  "geometry": {"coordinates":[-93.01477,17.9217],"type":"Point"}
}