{
  "type": "Feature",
  "properties": {
    "gn:admin1_code":"26",
    "gn:admin2_code":"30.0",
    "gn:asciiname":"El Diecinueve",
    "gn:country_code":"MX",
    "gn:dem":58,
    "gn:feature_class":"P",
    "gn:feature_code":"PPL",
    "gn:name":"El Diecinueve",
    "gn:population":0,
    "gn:timezone":"America/Hermosillo",
    "iso:country":"MX",
    "name:spa_x_preferred":[
        "El Diecinueve"
    ],
    "wof:name":"El Diecinueve",
    "wof:placetype":"locality"
},
  "geometry": {"coordinates":[-111.37103,28.69289],"type":"Point"}
}