{
  "type": "Feature",
  "properties": {
    "gn:admin1_code":"30",
    "gn:admin2_code":"130.0",
    "gn:asciiname":"El Ramie",
    "gn:country_code":"MX",
    "gn:dem":38,
    "gn:feature_class":"P",
    "gn:feature_code":"PPL",
    "gn:name":"El Ramie",
    "gn:population":269,
    "gn:timezone":"America/Mexico_City",
    "iso:country":"MX",
    "wof:name":"El Ramie",
    "wof:placetype":"locality",
    "wof:population":269
},
  "geometry": {"coordinates":[-95.72778,17.90306],"type":"Point"}
}