{
  "type": "Feature",
  "properties": {
    "gn:admin1_code":"13",
    "gn:admin2_code":"36.0",
    "gn:asciiname":"Loma la Pareja",
    "gn:country_code":"MX",
    "gn:dem":1860,
    "gn:feature_class":"P",
    "gn:feature_code":"PPL",
    "gn:name":"Loma la Pareja",
    "gn:population":53,
    "gn:timezone":"America/Mexico_City",
    "iso:country":"MX",
    "wof:name":"Loma la Pareja",
    "wof:placetype":"locality",
    "wof:population":53
},
  "geometry": {"coordinates":[-98.58963,20.4538],"type":"Point"}
}