{
  "type": "Feature",
  "properties": {
    "gn:admin1_code":"21",
    "gn:admin2_code":"217.0",
    "gn:asciiname":"Cacaloc",
    "gn:country_code":"MX",
    "gn:dem":2257,
    "gn:feature_class":"P",
    "gn:feature_code":"PPL",
    "gn:name":"Cacaloc",
    "gn:population":765,
    "gn:timezone":"America/Mexico_City",
    "iso:country":"MX",
    "wof:name":"Cacaloc",
    "wof:placetype":"locality",
    "wof:population":765
},
  "geometry": {"coordinates":[-97.09944,18.35306],"type":"Point"}
}