{
  "type": "Feature",
  "properties": {
    "gn:admin1_code":"30",
    "gn:admin2_code":"8.0",
    "gn:asciiname":"Teanquisco",
    "gn:country_code":"MX",
    "gn:dem":2245,
    "gn:feature_class":"P",
    "gn:feature_code":"PPL",
    "gn:name":"Teanquisco",
    "gn:population":223,
    "gn:timezone":"America/Mexico_City",
    "iso:country":"MX",
    "wof:name":"Teanquisco",
    "wof:placetype":"locality",
    "wof:population":223
},
  "geometry": {"coordinates":[-97.12417000000001,19.11083],"type":"Point"}
}