{
  "type": "Feature",
  "properties": {
    "gn:admin1_code":"10",
    "gn:admin2_code":"9.0",
    "gn:asciiname":"Cueva Prieta",
    "gn:country_code":"MX",
    "gn:dem":2825,
    "gn:feature_class":"P",
    "gn:feature_code":"PPL",
    "gn:name":"Cueva Prieta",
    "gn:population":0,
    "gn:timezone":"America/Monterrey",
    "iso:country":"MX",
    "name:spa_x_preferred":[
        "Cueva Prieta"
    ],
    "wof:name":"Cueva Prieta",
    "wof:placetype":"locality"
},
  "geometry": {"coordinates":[-106.35799,26.01044],"type":"Point"}
}