{
  "type": "Feature",
  "properties": {
    "gn:admin1_code":"7",
    "gn:admin2_code":"20.0",
    "gn:asciiname":"El Encino (Maria del Carmen Guerra de Jimenez)",
    "gn:country_code":"MX",
    "gn:dem":460,
    "gn:feature_class":"P",
    "gn:feature_code":"PPL",
    "gn:name":"El Encino (Mar\u00eda del Carmen Guerra de Jim\u00e9nez)",
    "gn:population":4,
    "gn:timezone":"America/Monterrey",
    "iso:country":"MX",
    "name:und_x_variant":[
        "El Encino (Mar\u00eda del Carmen Guerra de Jim\u00e9nez)"
    ],
    "wof:name":"El Encino (Maria del Carmen Guerra de Jimenez)",
    "wof:placetype":"locality",
    "wof:population":4
},
  "geometry": {"coordinates":[-101.54564999999999,27.90971],"type":"Point"}
}