{
  "type": "Feature",
  "properties": {
    "gn:admin1_code":"13",
    "gn:admin2_code":"53.0",
    "gn:asciiname":"La Cumbre de la Campana",
    "gn:country_code":"MX",
    "gn:dem":1032,
    "gn:feature_class":"P",
    "gn:feature_code":"PPL",
    "gn:name":"La Cumbre de la Campana",
    "gn:population":116,
    "gn:timezone":"America/Mexico_City",
    "iso:country":"MX",
    "wof:name":"La Cumbre de la Campana",
    "wof:placetype":"locality",
    "wof:population":116
},
  "geometry": {"coordinates":[-98.1925,20.40417],"type":"Point"}
}