{
  "type": "Feature",
  "properties": {
    "gn:admin1_code":"30.0",
    "gn:admin2_code":"124.0",
    "gn:asciiname":"Cerro de las Flores",
    "gn:country_code":"MX",
    "gn:dem":49,
    "gn:feature_class":"P",
    "gn:feature_code":"PPL",
    "gn:name":"Cerro de las Flores",
    "gn:population":232,
    "gn:timezone":"America/Mexico_City",
    "iso:country":"MX",
    "name:spa_x_preferred":[
        "Cerro de las Flores"
    ],
    "wof:name":"Cerro de las Flores",
    "wof:placetype":"locality",
    "wof:population":232
},
  "geometry": {"coordinates":[-97.2025,20.63944],"type":"Point"}
}