{
  "type": "Feature",
  "properties": {
    "gn:admin1_code":"11",
    "gn:admin2_code":"20.0",
    "gn:asciiname":"San Rafael de los Ramirez",
    "gn:country_code":"MX",
    "gn:dem":1798,
    "gn:feature_class":"P",
    "gn:feature_code":"PPL",
    "gn:name":"San Rafael de los Ram\u00edrez",
    "gn:population":96,
    "gn:timezone":"America/Mexico_City",
    "iso:country":"MX",
    "name:und_x_variant":[
        "San Rafael de los Ram\u00edrez"
    ],
    "wof:name":"San Rafael de los Ramirez",
    "wof:placetype":"locality",
    "wof:population":96
},
  "geometry": {"coordinates":[-101.58806,21.00417],"type":"Point"}
}