{
  "type": "Feature",
  "properties": {
    "gn:admin1_code":"6",
    "gn:admin2_code":"50.0",
    "gn:asciiname":"Ninguno",
    "gn:country_code":"MX",
    "gn:dem":1453,
    "gn:feature_class":"P",
    "gn:feature_code":"PPL",
    "gn:name":"Ninguno",
    "gn:population":151,
    "gn:timezone":"America/Chihuahua",
    "iso:country":"MX",
    "wof:name":"Ninguno",
    "wof:placetype":"locality",
    "wof:population":151
},
  "geometry": {"coordinates":[-107.86698,30.40361],"type":"Point"}
}