{
  "type": "Feature",
  "properties": {
    "gn:admin1_code":"18.0",
    "gn:admin2_code":"9.0",
    "gn:asciiname":"Tierra Blanca",
    "gn:country_code":"MX",
    "gn:dem":708,
    "gn:feature_class":"P",
    "gn:feature_code":"PPL",
    "gn:name":"Tierra Blanca",
    "gn:population":0,
    "gn:timezone":"America/Mazatlan",
    "iso:country":"MX",
    "wof:name":"Tierra Blanca",
    "wof:placetype":"locality"
},
  "geometry": {"coordinates":[-104.66144,21.921],"type":"Point"}
}