{
  "type": "Feature",
  "properties": {
    "gn:admin1_code":"25",
    "gn:admin2_code":"10",
    "gn:asciiname":"Guillermo Prieto",
    "gn:country_code":"MX",
    "gn:dem":66,
    "gn:feature_class":"P",
    "gn:feature_code":"PPL",
    "gn:name":"Guillermo Prieto",
    "gn:population":16,
    "gn:timezone":"America/Mazatlan",
    "iso:country":"MX",
    "wof:name":"Guillermo Prieto",
    "wof:placetype":"locality",
    "wof:population":16
},
  "geometry": {"coordinates":[-108.8991,26.08551],"type":"Point"}
}