{
  "type": "Feature",
  "properties": {
    "gn:admin1_code":"25",
    "gn:admin2_code":"10",
    "gn:asciiname":"Guillermo Prieto",
    "gn:country_code":"MX",
    "gn:dem":66,
    "gn:feature_class":"P",
    "gn:feature_code":"PPL",
    "gn:name":"Guillermo Prieto",
    "gn:population":16,
    "gn:timezone":"America/Mazatlan",
    "iso:country":"MX",
    "name:pol_x_preferred":[
        "Guillermo Prieto"
    ],
    "name:spa_x_preferred":[
        "Guillermo Prieto Pradillo"
    ],
    "name:srp_x_preferred":[
        "\u0413\u0438\u0459\u0435\u0440\u043c\u043e \u041f\u0440\u0438\u0458\u0435\u0442\u043e"
    ],
    "wof:name":"Guillermo Prieto",
    "wof:placetype":"locality",
    "wof:population":16
},
  "geometry": {"coordinates":[-108.8991,26.08551],"type":"Point"}
}