{
  "type": "Feature",
  "properties": {
    "gn:admin1_code":"16.0",
    "gn:admin2_code":"92.0",
    "gn:asciiname":"Agua Zarca",
    "gn:country_code":"MX",
    "gn:dem":586,
    "gn:feature_class":"P",
    "gn:feature_code":"PPL",
    "gn:name":"Agua Zarca",
    "gn:population":0,
    "gn:timezone":"America/Mexico_City",
    "iso:country":"MX",
    "name:spa_x_preferred":[
        "Agua Zarca"
    ],
    "wof:name":"Agua Zarca",
    "wof:placetype":"locality"
},
  "geometry": {"coordinates":[-100.65516,18.93444],"type":"Point"}
}