{
  "type": "Feature",
  "properties": {
    "gn:admin1_code":"10",
    "gn:admin2_code":"13.0",
    "gn:asciiname":"Pedernal",
    "gn:country_code":"MX",
    "gn:dem":1173,
    "gn:feature_class":"P",
    "gn:feature_code":"PPL",
    "gn:name":"Pedernal",
    "gn:population":0,
    "gn:timezone":"America/Monterrey",
    "iso:country":"MX",
    "name:und_x_variant":[
        "Pedernales",
        "Pedernal"
    ],
    "wof:name":"Pedernal",
    "wof:placetype":"locality"
},
  "geometry": {"coordinates":[-103.77714,25.99717],"type":"Point"}
}