{
  "type": "Feature",
  "properties": {
    "gn:admin1_code":"27.0",
    "gn:admin2_code":"1.0",
    "gn:asciiname":"El Destino",
    "gn:country_code":"MX",
    "gn:dem":47,
    "gn:feature_class":"P",
    "gn:feature_code":"PPL",
    "gn:name":"El Destino",
    "gn:population":0,
    "gn:timezone":"America/Mexico_City",
    "iso:country":"MX",
    "name:spa_x_preferred":[
        "El Destino"
    ],
    "wof:name":"El Destino",
    "wof:placetype":"locality"
},
  "geometry": {"coordinates":[-91.00505,17.81426],"type":"Point"}
}