{
  "type": "Feature",
  "properties": {
    "gn:admin1_code":"7.0",
    "gn:admin2_code":"16.0",
    "gn:asciiname":"Carranza",
    "gn:country_code":"MX",
    "gn:dem":686,
    "gn:feature_class":"P",
    "gn:feature_code":"PPL",
    "gn:name":"Carranza",
    "gn:population":0,
    "gn:timezone":"America/Monterrey",
    "iso:country":"MX",
    "name:ceb_x_preferred":[
        "Carranza"
    ],
    "name:deu_x_preferred":[
        "Carranza"
    ],
    "name:fra_x_preferred":[
        "Carranza"
    ],
    "name:ita_x_preferred":[
        "Carranza"
    ],
    "name:jpn_x_preferred":[
        "\u30ab\u30e9\u30f3\u30b5"
    ],
    "name:nds_x_preferred":[
        "Carranza"
    ],
    "name:nld_x_preferred":[
        "Carranza"
    ],
    "name:por_x_preferred":[
        "Carranza"
    ],
    "name:rus_x_preferred":[
        "\u041a\u0430\u0440\u0440\u0430\u043d\u0441\u0430"
    ],
    "name:spa_x_preferred":[
        "Carranza"
    ],
    "name:swe_x_preferred":[
        "Carranza"
    ],
    "wof:name":"Carranza",
    "wof:placetype":"locality"
},
  "geometry": {"coordinates":[-101.80691,27.07256],"type":"Point"}
}