{
  "type": "Feature",
  "properties": {
    "gn:admin1_code":"7.0",
    "gn:admin2_code":"16.0",
    "gn:asciiname":"Carranza",
    "gn:country_code":"MX",
    "gn:dem":686,
    "gn:feature_class":"P",
    "gn:feature_code":"PPL",
    "gn:name":"Carranza",
    "gn:population":0,
    "gn:timezone":"America/Monterrey",
    "iso:country":"MX",
    "name:spa_x_preferred":[
        "Carranza"
    ],
    "wof:name":"Carranza",
    "wof:placetype":"locality"
},
  "geometry": {"coordinates":[-101.80691,27.07256],"type":"Point"}
}