{
  "type": "Feature",
  "properties": {
    "gn:admin1_code":"6.0",
    "gn:admin2_code":"13.0",
    "gn:asciiname":"Arroyo Seco",
    "gn:cc2":"MX",
    "gn:country_code":"MX",
    "gn:dem":1483,
    "gn:feature_class":"P",
    "gn:feature_code":"PPL",
    "gn:name":"Arroyo Seco",
    "gn:population":0,
    "gn:timezone":"America/Chihuahua",
    "iso:country":"MX",
    "name:und_x_variant":[
        "Vado de Arroyo Seco",
        "Arroyo Seco"
    ],
    "wof:name":"Arroyo Seco",
    "wof:placetype":"locality"
},
  "geometry": {"coordinates":[-107.95,30.31667],"type":"Point"}
}