{
  "type": "Feature",
  "properties": {
    "gn:admin1_code":"32",
    "gn:admin2_code":"42.0",
    "gn:asciiname":"Lo de Mena",
    "gn:country_code":"MX",
    "gn:dem":2136,
    "gn:feature_class":"P",
    "gn:feature_code":"PPL",
    "gn:name":"Lo de Mena",
    "gn:population":260,
    "gn:timezone":"America/Mexico_City",
    "iso:country":"MX",
    "name:spa_x_preferred":[
        "Lo de Mena"
    ],
    "wof:name":"Lo de Mena",
    "wof:placetype":"locality",
    "wof:population":260
},
  "geometry": {"coordinates":[-103.66212,23.54706],"type":"Point"}
}