{
  "type": "Feature",
  "properties": {
    "gn:admin1_code":"14",
    "gn:admin2_code":"33.0",
    "gn:asciiname":"La Sanguijuela",
    "gn:country_code":"MX",
    "gn:dem":1819,
    "gn:feature_class":"P",
    "gn:feature_code":"PPL",
    "gn:name":"La Sanguijuela",
    "gn:population":146,
    "gn:timezone":"America/Mexico_City",
    "iso:country":"MX",
    "wof:name":"La Sanguijuela",
    "wof:placetype":"locality",
    "wof:population":146
},
  "geometry": {"coordinates":[-102.04416999999999,20.49222],"type":"Point"}
}