{
  "type": "Feature",
  "properties": {
    "gn:admin1_code":"26.0",
    "gn:asciiname":"El Oso",
    "gn:country_code":"MX",
    "gn:dem":1671,
    "gn:feature_class":"P",
    "gn:feature_code":"PPL",
    "gn:name":"El Oso",
    "gn:population":0,
    "gn:timezone":"America/Hermosillo",
    "iso:country":"MX",
    "name:spa_x_preferred":[
        "El Oso"
    ],
    "wof:name":"El Oso",
    "wof:placetype":"locality"
},
  "geometry": {"coordinates":[-108.69905,30.58929],"type":"Point"}
}