{
  "type": "Feature",
  "properties": {
    "gn:admin1_code":"27",
    "gn:admin2_code":"2.0",
    "gn:asciiname":"Encrucijada 4ta. Seccion B (La Lucha)",
    "gn:country_code":"MX",
    "gn:dem":4,
    "gn:feature_class":"P",
    "gn:feature_code":"PPL",
    "gn:name":"Encrucijada 4ta. Secci\u00f3n B (La Lucha)",
    "gn:population":544,
    "gn:timezone":"America/Mexico_City",
    "iso:country":"MX",
    "name:und_x_variant":[
        "Encrucijada 4ta. Secci\u00f3n B (La Lucha)"
    ],
    "wof:name":"Encrucijada 4ta. Seccion B (La Lucha)",
    "wof:placetype":"locality",
    "wof:population":544
},
  "geometry": {"coordinates":[-93.5425,18.21139],"type":"Point"}
}