{
  "type": "Feature",
  "properties": {
    "gn:admin1_code":"21",
    "gn:admin2_code":"74.0",
    "gn:asciiname":"San Diego Buenavista",
    "gn:country_code":"MX",
    "gn:dem":2548,
    "gn:feature_class":"P",
    "gn:feature_code":"PPL",
    "gn:name":"San Diego Buenavista",
    "gn:population":0,
    "gn:timezone":"America/Mexico_City",
    "iso:country":"MX",
    "name:spa_x_preferred":[
        "San Diego Buenavista"
    ],
    "name:und_x_variant":[
        "Buenavista"
    ],
    "wof:name":"San Diego Buenavista",
    "wof:placetype":"locality"
},
  "geometry": {"coordinates":[-98.48502000000001,19.12953],"type":"Point"}
}