{
  "type": "Feature",
  "properties": {
    "gn:admin1_code":"3",
    "gn:admin2_code":"1.0",
    "gn:asciiname":"Navojoa Uno Lote 7",
    "gn:country_code":"MX",
    "gn:dem":35,
    "gn:feature_class":"P",
    "gn:feature_code":"PPL",
    "gn:name":"Navojoa Uno Lote 7",
    "gn:population":4,
    "gn:timezone":"America/Mazatlan",
    "iso:country":"MX",
    "wof:name":"Navojoa Uno Lote 7",
    "wof:placetype":"locality",
    "wof:population":4
},
  "geometry": {"coordinates":[-111.81832,25.25851],"type":"Point"}
}