{
  "type": "Feature",
  "properties": {
    "gn:admin1_code":"6",
    "gn:admin2_code":"37.0",
    "gn:asciiname":"El Lobo",
    "gn:country_code":"MX",
    "gn:dem":1298,
    "gn:feature_class":"P",
    "gn:feature_code":"PPL",
    "gn:name":"El Lobo",
    "gn:population":4,
    "gn:timezone":"America/Ojinaga",
    "iso:country":"MX",
    "wof:name":"El Lobo",
    "wof:placetype":"locality",
    "wof:population":4
},
  "geometry": {"coordinates":[-106.50489,31.23111],"type":"Point"}
}