{
  "type": "Feature",
  "properties": {
    "gn:admin1_code":"25.0",
    "gn:asciiname":"El Apomo",
    "gn:country_code":"MX",
    "gn:dem":282,
    "gn:feature_class":"P",
    "gn:feature_code":"PPL",
    "gn:name":"El Apomo",
    "gn:population":0,
    "gn:timezone":"America/Mazatlan",
    "iso:country":"MX",
    "name:spa_x_preferred":[
        "El Apomo"
    ],
    "wof:name":"El Apomo",
    "wof:placetype":"locality"
},
  "geometry": {"coordinates":[-106.34498000000001,24.08298],"type":"Point"}
}