{
  "type": "Feature",
  "properties": {
    "gn:admin1_code":"12",
    "gn:admin2_code":"60.0",
    "gn:asciiname":"Coapango",
    "gn:country_code":"MX",
    "gn:dem":1334,
    "gn:feature_class":"P",
    "gn:feature_code":"PPL",
    "gn:name":"Coapango",
    "gn:population":0,
    "gn:timezone":"America/Mexico_City",
    "iso:country":"MX",
    "name:und_x_variant":[
        "Coapanco",
        "Coapango"
    ],
    "wof:name":"Coapango",
    "wof:placetype":"locality"
},
  "geometry": {"coordinates":[-99.55544999999999,18.63386],"type":"Point"}
}