{
  "type": "Feature",
  "properties": {
    "gn:admin1_code":"5",
    "gn:admin2_code":"57.0",
    "gn:asciiname":"El Area",
    "gn:country_code":"MX",
    "gn:dem":649,
    "gn:feature_class":"P",
    "gn:feature_code":"PPL",
    "gn:name":"El \u00c1rea",
    "gn:population":5,
    "gn:timezone":"America/Mexico_City",
    "iso:country":"MX",
    "name:und_x_variant":[
        "El \u00c1rea"
    ],
    "wof:name":"El Area",
    "wof:placetype":"locality",
    "wof:population":5
},
  "geometry": {"coordinates":[-92.47889000000001,15.33528],"type":"Point"}
}