{
  "type": "Feature",
  "properties": {
    "gn:admin1_code":"5",
    "gn:admin2_code":"19.0",
    "gn:asciiname":"Arturo Albores",
    "gn:country_code":"MX",
    "gn:dem":671,
    "gn:feature_class":"P",
    "gn:feature_code":"PPL",
    "gn:name":"Arturo Albores",
    "gn:population":139,
    "gn:timezone":"America/Mexico_City",
    "iso:country":"MX",
    "wof:name":"Arturo Albores",
    "wof:placetype":"locality",
    "wof:population":139
},
  "geometry": {"coordinates":[-92.19499999999999,16.09306],"type":"Point"}
}