{
  "type": "Feature",
  "properties": {
    "gn:admin1_code":"5",
    "gn:admin2_code":"17",
    "gn:asciiname":"Alaska",
    "gn:country_code":"MX",
    "gn:dem":686,
    "gn:feature_class":"P",
    "gn:feature_code":"PPL",
    "gn:name":"Alaska",
    "gn:population":12,
    "gn:timezone":"America/Mexico_City",
    "iso:country":"MX",
    "wof:name":"Alaska",
    "wof:placetype":"locality",
    "wof:population":12
},
  "geometry": {"coordinates":[-93.97306,16.55889],"type":"Point"}
}