{
  "type": "Feature",
  "properties": {
    "gn:admin1_code":"13",
    "gn:admin2_code":"81.0",
    "gn:asciiname":"Chapatla",
    "gn:country_code":"MX",
    "gn:dem":1884,
    "gn:feature_class":"P",
    "gn:feature_code":"PPL",
    "gn:name":"Chapatla",
    "gn:population":0,
    "gn:timezone":"America/Mexico_City",
    "iso:country":"MX",
    "name:spa_x_preferred":[
        "Chapatla"
    ],
    "wof:name":"Chapatla",
    "wof:placetype":"locality"
},
  "geometry": {"coordinates":[-98.68098000000001,20.68765],"type":"Point"}
}