{
  "type": "Feature",
  "properties": {
    "gn:admin1_code":"29",
    "gn:admin2_code":"31.0",
    "gn:asciiname":"Ocotitla",
    "gn:country_code":"MX",
    "gn:dem":2467,
    "gn:feature_class":"P",
    "gn:feature_code":"PPL",
    "gn:name":"Ocotitla",
    "gn:population":0,
    "gn:timezone":"America/Mexico_City",
    "iso:country":"MX",
    "name:und_x_variant":[
        "Tetla Tercera Secci\u00f3n"
    ],
    "wof:name":"Ocotitla",
    "wof:placetype":"locality"
},
  "geometry": {"coordinates":[-98.08879,19.45017],"type":"Point"}
}