{
  "type": "Feature",
  "properties": {
    "gn:admin1_code":"15",
    "gn:admin2_code":"113.0",
    "gn:asciiname":"Potrero del Moral",
    "gn:country_code":"MX",
    "gn:dem":2781,
    "gn:feature_class":"P",
    "gn:feature_code":"PPL",
    "gn:name":"Potrero del Moral",
    "gn:population":65,
    "gn:timezone":"America/Mexico_City",
    "iso:country":"MX",
    "wof:name":"Potrero del Moral",
    "wof:placetype":"locality",
    "wof:population":65
},
  "geometry": {"coordinates":[-99.67308,19.04459],"type":"Point"}
}