{
  "type": "Feature",
  "properties": {
    "gn:admin1_code":"20",
    "gn:admin2_code":"59",
    "gn:asciiname":"Fraccionamiento Nuevo Amanecer",
    "gn:country_code":"MX",
    "gn:dem":1636,
    "gn:feature_class":"P",
    "gn:feature_code":"PPL",
    "gn:name":"Fraccionamiento Nuevo Amanecer",
    "gn:population":38,
    "gn:timezone":"America/Mexico_City",
    "iso:country":"MX",
    "wof:name":"Fraccionamiento Nuevo Amanecer",
    "wof:placetype":"locality",
    "wof:population":38
},
  "geometry": {"coordinates":[-96.58139,16.30027999999999],"type":"Point"}
}