{
  "type": "Feature",
  "properties": {
    "gn:admin1_code":"26",
    "gn:admin2_code":"61.0",
    "gn:asciiname":"El Encino",
    "gn:country_code":"MX",
    "gn:dem":518,
    "gn:feature_class":"P",
    "gn:feature_code":"PPL",
    "gn:name":"El Encino",
    "gn:population":0,
    "gn:timezone":"America/Hermosillo",
    "iso:country":"MX",
    "name:spa_x_preferred":[
        "El Encino"
    ],
    "wof:name":"El Encino",
    "wof:placetype":"locality"
},
  "geometry": {"coordinates":[-109.38713,28.57822],"type":"Point"}
}