{
  "type": "Feature",
  "properties": {
    "gn:admin1_code":"16",
    "gn:admin2_code":"13.0",
    "gn:asciiname":"San Jose",
    "gn:country_code":"MX",
    "gn:dem":521,
    "gn:feature_class":"P",
    "gn:feature_code":"PPL",
    "gn:name":"San Jos\u00e9",
    "gn:population":5,
    "gn:timezone":"America/Mexico_City",
    "iso:country":"MX",
    "name:und_x_variant":[
        "San Jos\u00e9"
    ],
    "wof:name":"San Jose",
    "wof:placetype":"locality",
    "wof:population":5
},
  "geometry": {"coordinates":[-101.14333000000001,18.90778],"type":"Point"}
}