{
  "type": "Feature",
  "properties": {
    "iso:country":"MX",
    "name:spa_x_preferred":[
        "El Pueblito Del Revolcadero"
    ],
    "qs:gn_adm0_cc":"MX",
    "qs:gn_local":3533462,
    "qs:gn_nam_loc":"Acapulco de Juarez, Acapulco de Ju\u00e1rez, Guerrero, MX",
    "qs:gn_namadm1":"12",
    "qs:local_max":685,
    "qs:local_sum":4998,
    "qs:localhoods":23,
    "qs:name":"El Pueblito Del Revolcadero",
    "qs:name_adm0":"M\u00e9xico",
    "qs:name_adm1":"Guerrero",
    "qs:name_adm2":"Acapulco de Juarez",
    "qs:name_local":"Acapulco de Ju\u00e1rez",
    "qs:photo_max":69,
    "qs:photo_sum":198,
    "qs:placetype":"Suburb",
    "qs:quad_count":16,
    "qs:woe_adm0":23424900,
    "qs:woe_adm1":2346275,
    "qs:woe_adm2":12600035,
    "qs:woe_lau":0,
    "qs:woe_local":110978,
    "qs:woe_ver":"7.10.0",
    "wof:lang":[
        "spa"
    ],
    "wof:name":"El Pueblito Del Revolcadero",
    "wof:placetype":"neighbourhood"
},
  "geometry": {"coordinates":[-99.81509200000001,16.789641],"type":"Point"}
}