{
  "type": "Feature",
  "properties": {
    "gn:admin1_code":"6",
    "gn:admin2_code":"47.0",
    "gn:asciiname":"El Duraznito",
    "gn:country_code":"MX",
    "gn:dem":1114,
    "gn:feature_class":"P",
    "gn:feature_code":"PPL",
    "gn:name":"El Duraznito",
    "gn:population":0,
    "gn:timezone":"America/Chihuahua",
    "iso:country":"MX",
    "name:spa_x_preferred":[
        "El Duraznito"
    ],
    "wof:name":"El Duraznito",
    "wof:placetype":"locality"
},
  "geometry": {"coordinates":[-108.67230000000001,27.99623],"type":"Point"}
}