{
  "type": "Feature",
  "properties": {
    "gn:admin1_code":"14.0",
    "gn:admin2_code":"37.0",
    "gn:asciiname":"Rastro Municipal",
    "gn:country_code":"MX",
    "gn:dem":867,
    "gn:feature_class":"P",
    "gn:feature_code":"PPL",
    "gn:name":"Rastro Municipal",
    "gn:population":0,
    "gn:timezone":"America/Mexico_City",
    "iso:country":"MX",
    "name:spa_x_preferred":[
        "Rastro Municipal"
    ],
    "wof:name":"Rastro Municipal",
    "wof:placetype":"locality"
},
  "geometry": {"coordinates":[-104.20817,19.7918],"type":"Point"}
}