{
  "type": "Feature",
  "properties": {
    "gn:admin1_code":"30.0",
    "gn:admin2_code":"33.0",
    "gn:asciiname":"Santa Rosalia",
    "gn:country_code":"MX",
    "gn:dem":13,
    "gn:feature_class":"P",
    "gn:feature_code":"PPL",
    "gn:name":"Santa Rosal\u00eda",
    "gn:population":31,
    "gn:timezone":"America/Mexico_City",
    "iso:country":"MX",
    "name:spa_x_preferred":[
        "Santa Rosal\u00eda"
    ],
    "wof:name":"Santa Rosalia",
    "wof:placetype":"locality",
    "wof:population":31
},
  "geometry": {"coordinates":[-97.28167000000001,20.69528],"type":"Point"}
}