{
  "type": "Feature",
  "properties": {
    "gn:admin1_code":"5",
    "gn:admin2_code":"59",
    "gn:asciiname":"San Manuel",
    "gn:country_code":"MX",
    "gn:dem":563,
    "gn:feature_class":"P",
    "gn:feature_code":"PPL",
    "gn:name":"San Manuel",
    "gn:population":36,
    "gn:timezone":"America/Mexico_City",
    "iso:country":"MX",
    "wof:name":"San Manuel",
    "wof:placetype":"locality",
    "wof:population":36
},
  "geometry": {"coordinates":[-91.70556000000001,16.83361],"type":"Point"}
}