{
  "type": "Feature",
  "properties": {
    "gn:admin1_code":"29",
    "gn:admin2_code":"30.0",
    "gn:asciiname":"El Rosario",
    "gn:country_code":"MX",
    "gn:dem":3178,
    "gn:feature_class":"P",
    "gn:feature_code":"PPL",
    "gn:name":"El Rosario",
    "gn:population":0,
    "gn:timezone":"America/Mexico_City",
    "iso:country":"MX",
    "name:spa_x_preferred":[
        "El Rosario"
    ],
    "name:spa_x_variant":[
        "El Crucero"
    ],
    "wof:name":"El Rosario",
    "wof:placetype":"locality"
},
  "geometry": {"coordinates":[-97.883,19.52287],"type":"Point"}
}