{
  "type": "Feature",
  "properties": {
    "gn:admin1_code":"2.0",
    "gn:admin2_code":"5.0",
    "gn:asciiname":"Alfonso",
    "gn:country_code":"MX",
    "gn:dem":17,
    "gn:feature_class":"P",
    "gn:feature_code":"PPL",
    "gn:name":"Alfonso",
    "gn:population":0,
    "gn:timezone":"America/Tijuana",
    "iso:country":"MX",
    "name:spa_x_preferred":[
        "Alfonso"
    ],
    "wof:name":"Alfonso",
    "wof:placetype":"locality"
},
  "geometry": {"coordinates":[-117.04432,32.30837],"type":"Point"}
}