{
  "type": "Feature",
  "properties": {
    "gn:admin1_code":"25.0",
    "gn:admin2_code":"2.0",
    "gn:asciiname":"Alhuey",
    "gn:country_code":"MX",
    "gn:dem":29,
    "gn:feature_class":"P",
    "gn:feature_code":"PPL",
    "gn:name":"Alhuey",
    "gn:population":0,
    "gn:timezone":"America/Mazatlan",
    "iso:country":"MX",
    "name:und_x_variant":[
        "Alhuey de los Lugos",
        "Alhuey"
    ],
    "wof:name":"Alhuey",
    "wof:placetype":"locality"
},
  "geometry": {"coordinates":[-108.13025,25.37708],"type":"Point"}
}