{
  "type": "Feature",
  "properties": {
    "gn:admin1_code":"5.0",
    "gn:asciiname":"Santaella",
    "gn:country_code":"MX",
    "gn:dem":217,
    "gn:feature_class":"P",
    "gn:feature_code":"PPL",
    "gn:name":"Santaella",
    "gn:population":0,
    "gn:timezone":"America/Mexico_City",
    "iso:country":"MX",
    "name:ara_x_preferred":[
        "\u0633\u0627\u0646\u062a\u0627\u064a\u0644\u0627"
    ],
    "name:arg_x_preferred":[
        "Santaella"
    ],
    "name:bul_x_preferred":[
        "\u0421\u0430\u043d\u0442\u0430\u0435\u043b\u044f"
    ],
    "name:cat_x_preferred":[
        "Santaella"
    ],
    "name:ceb_x_preferred":[
        "Santaella"
    ],
    "name:epo_x_preferred":[
        "Santaella"
    ],
    "name:eus_x_preferred":[
        "Santaella"
    ],
    "name:fra_x_preferred":[
        "Santaella"
    ],
    "name:glg_x_preferred":[
        "Santaella"
    ],
    "name:hun_x_preferred":[
        "Santaella"
    ],
    "name:ina_x_preferred":[
        "Santaella"
    ],
    "name:ita_x_preferred":[
        "Santaella"
    ],
    "name:msa_x_preferred":[
        "Santaella"
    ],
    "name:nld_x_preferred":[
        "Santaella"
    ],
    "name:oci_x_preferred":[
        "Santaella"
    ],
    "name:pol_x_preferred":[
        "Santaella"
    ],
    "name:por_x_preferred":[
        "Santaella"
    ],
    "name:ron_x_preferred":[
        "Santaella"
    ],
    "name:rus_x_preferred":[
        "\u0421\u0430\u043d\u0442\u0430\u044d\u043b\u044c\u044f"
    ],
    "name:spa_x_preferred":[
        "Santaella"
    ],
    "name:swe_x_preferred":[
        "Santaella"
    ],
    "name:tur_x_preferred":[
        "Santaella"
    ],
    "name:ukr_x_preferred":[
        "\u0421\u0430\u043d\u0442\u0430\u0435\u043b\u044c\u044f"
    ],
    "name:uzb_x_preferred":[
        "Santaella"
    ],
    "name:vie_x_preferred":[
        "Santaella"
    ],
    "name:war_x_preferred":[
        "Santaella"
    ],
    "name:zho_x_preferred":[
        "\u6851\u6cf0\u5229\u4e9a"
    ],
    "wof:name":"Santaella",
    "wof:placetype":"locality"
},
  "geometry": {"coordinates":[-93.16406000000001,15.76499],"type":"Point"}
}