{
  "type": "Feature",
  "properties": {
    "gn:admin1_code":"16",
    "gn:admin2_code":"6.0",
    "gn:asciiname":"Los Puertecitos (Rincon de los Bueyes)",
    "gn:country_code":"MX",
    "gn:dem":378,
    "gn:feature_class":"P",
    "gn:feature_code":"PPL",
    "gn:name":"Los Puertecitos (Rinc\u00f3n de los Bueyes)",
    "gn:population":193,
    "gn:timezone":"America/Mexico_City",
    "iso:country":"MX",
    "name:und_x_variant":[
        "Los Puertecitos (Rinc\u00f3n de los Bueyes)"
    ],
    "wof:name":"Los Puertecitos (Rincon de los Bueyes)",
    "wof:placetype":"locality",
    "wof:population":193
},
  "geometry": {"coordinates":[-102.28833,19.07278],"type":"Point"}
}