{
  "type": "Feature",
  "properties": {
    "gn:admin1_code":"26",
    "gn:admin2_code":"25",
    "gn:asciiname":"Malichita",
    "gn:country_code":"MX",
    "gn:dem":61,
    "gn:feature_class":"P",
    "gn:feature_code":"PPL",
    "gn:name":"Malichita",
    "gn:population":16,
    "gn:timezone":"America/Hermosillo",
    "iso:country":"MX",
    "wof:name":"Malichita",
    "wof:placetype":"locality",
    "wof:population":16
},
  "geometry": {"coordinates":[-110.56305999999999,28.065],"type":"Point"}
}