{
  "type": "Feature",
  "properties": {
    "gn:admin1_code":"30.0",
    "gn:admin2_code":"158.0",
    "gn:asciiname":"Cinco Letras",
    "gn:country_code":"MX",
    "gn:dem":12,
    "gn:feature_class":"P",
    "gn:feature_code":"PPL",
    "gn:name":"Cinco Letras",
    "gn:population":0,
    "gn:timezone":"America/Mexico_City",
    "iso:country":"MX",
    "name:spa_x_preferred":[
        "Cinco Letras"
    ],
    "wof:name":"Cinco Letras",
    "wof:placetype":"locality"
},
  "geometry": {"coordinates":[-96.94917,20.37028],"type":"Point"}
}