{
  "type": "Feature",
  "properties": {
    "gn:admin1_code":"1.0",
    "gn:admin2_code":"2.0",
    "gn:asciiname":"El Chiquihuite",
    "gn:cc2":"MX",
    "gn:country_code":"MX",
    "gn:dem":2123,
    "gn:feature_class":"P",
    "gn:feature_code":"PPL",
    "gn:name":"El Chiquihuite",
    "gn:population":0,
    "gn:timezone":"America/Mexico_City",
    "iso:country":"MX",
    "name:und_x_variant":[
        "Chiquihuite",
        "El Chiquihuite"
    ],
    "wof:name":"El Chiquihuite",
    "wof:placetype":"locality"
},
  "geometry": {"coordinates":[-102.13333,22.13333],"type":"Point"}
}