{
  "type": "Feature",
  "properties": {
    "gn:admin1_code":"12.0",
    "gn:admin2_code":"71.0",
    "gn:asciiname":"Plan del Maguey",
    "gn:country_code":"MX",
    "gn:dem":298,
    "gn:feature_class":"P",
    "gn:feature_code":"PPL",
    "gn:name":"Plan del Maguey",
    "gn:population":0,
    "gn:timezone":"America/Mexico_City",
    "iso:country":"MX",
    "name:spa_x_preferred":[
        "Plan del Maguey"
    ],
    "wof:name":"Plan del Maguey",
    "wof:placetype":"locality"
},
  "geometry": {"coordinates":[-98.24370999999999,16.77542],"type":"Point"}
}