{
  "type": "Feature",
  "properties": {
    "gn:admin1_code":"21",
    "gn:admin2_code":"69.0",
    "gn:asciiname":"Tlapetlahuaya",
    "gn:country_code":"MX",
    "gn:dem":1526,
    "gn:feature_class":"P",
    "gn:feature_code":"PPL",
    "gn:name":"Tlapetlahuaya",
    "gn:population":601,
    "gn:timezone":"America/Mexico_City",
    "iso:country":"MX",
    "wof:name":"Tlapetlahuaya",
    "wof:placetype":"locality",
    "wof:population":601
},
  "geometry": {"coordinates":[-98.57138999999999,18.75528],"type":"Point"}
}