{
  "type": "Feature",
  "properties": {
    "gn:admin1_code":"32",
    "gn:admin2_code":"29.0",
    "gn:asciiname":"Tierra Generosa",
    "gn:country_code":"MX",
    "gn:dem":2126,
    "gn:feature_class":"P",
    "gn:feature_code":"PPL",
    "gn:name":"Tierra Generosa",
    "gn:population":0,
    "gn:timezone":"America/Mexico_City",
    "iso:country":"MX",
    "name:spa_x_preferred":[
        "Tierra Generosa"
    ],
    "wof:name":"Tierra Generosa",
    "wof:placetype":"locality"
},
  "geometry": {"coordinates":[-103.55524,24.15163],"type":"Point"}
}