{
  "type": "Feature",
  "properties": {
    "gn:admin1_code":"12",
    "gn:admin2_code":"35.0",
    "gn:asciiname":"Joya de Pantla",
    "gn:country_code":"MX",
    "gn:dem":883,
    "gn:feature_class":"P",
    "gn:feature_code":"PPL",
    "gn:name":"Joya de Pantla",
    "gn:population":0,
    "gn:timezone":"America/Mexico_City",
    "iso:country":"MX",
    "name:spa_x_preferred":[
        "Joya de Pantla"
    ],
    "wof:name":"Joya de Pantla",
    "wof:placetype":"locality"
},
  "geometry": {"coordinates":[-99.53301999999999,18.26345],"type":"Point"}
}