{
  "type": "Feature",
  "properties": {
    "gn:admin1_code":"10",
    "gn:admin2_code":"32.0",
    "gn:asciiname":"San Antonio de la Sierra",
    "gn:country_code":"MX",
    "gn:dem":2339,
    "gn:feature_class":"P",
    "gn:feature_code":"PPL",
    "gn:name":"San Antonio de la Sierra",
    "gn:population":43,
    "gn:timezone":"America/Monterrey",
    "iso:country":"MX",
    "wof:name":"San Antonio de la Sierra",
    "wof:placetype":"locality",
    "wof:population":43
},
  "geometry": {"coordinates":[-105.65089,24.86416],"type":"Point"}
}