{
  "type": "Feature",
  "properties": {
    "gn:admin1_code":"26",
    "gn:admin2_code":"18.0",
    "gn:asciiname":"Sitabaro",
    "gn:country_code":"MX",
    "gn:dem":59,
    "gn:feature_class":"P",
    "gn:feature_code":"PPL",
    "gn:name":"Sitabaro",
    "gn:population":0,
    "gn:timezone":"America/Hermosillo",
    "iso:country":"MX",
    "name:spa_x_preferred":[
        "Sitabaro"
    ],
    "wof:name":"Sitabaro",
    "wof:placetype":"locality"
},
  "geometry": {"coordinates":[-109.88525,27.54351],"type":"Point"}
}