{
  "type": "Feature",
  "properties": {
    "gn:admin1_code":"13",
    "gn:admin2_code":"71.0",
    "gn:asciiname":"San Andres Miraflores",
    "gn:country_code":"MX",
    "gn:dem":768,
    "gn:feature_class":"P",
    "gn:feature_code":"PPL",
    "gn:name":"San Andr\u00e9s Miraflores",
    "gn:population":0,
    "gn:timezone":"America/Mexico_City",
    "iso:country":"MX",
    "name:und_x_variant":[
        "San Andr\u00e9s",
        "San Andr\u00e9s Miraflores"
    ],
    "wof:name":"San Andres Miraflores",
    "wof:placetype":"locality"
},
  "geometry": {"coordinates":[-99.00165,20.80155],"type":"Point"}
}