{
  "type": "Feature",
  "properties": {
    "gn:admin1_code":"15",
    "gn:admin2_code":"7.0",
    "gn:asciiname":"Corral de Piedra",
    "gn:country_code":"MX",
    "gn:dem":2929,
    "gn:feature_class":"P",
    "gn:feature_code":"PPL",
    "gn:name":"Corral de Piedra",
    "gn:population":0,
    "gn:timezone":"America/Mexico_City",
    "iso:country":"MX",
    "name:spa_x_preferred":[
        "Corral de Piedra"
    ],
    "wof:name":"Corral de Piedra",
    "wof:placetype":"locality"
},
  "geometry": {"coordinates":[-99.97020999999999,19.21127000000001],"type":"Point"}
}