{
  "type": "Feature",
  "properties": {
    "gn:admin1_code":"32",
    "gn:admin2_code":"41.0",
    "gn:asciiname":"Paso de Agua Dulce",
    "gn:country_code":"MX",
    "gn:dem":2193,
    "gn:feature_class":"P",
    "gn:feature_code":"PPL",
    "gn:name":"Paso de Agua Dulce",
    "gn:population":8,
    "gn:timezone":"America/Mexico_City",
    "iso:country":"MX",
    "wof:name":"Paso de Agua Dulce",
    "wof:placetype":"locality",
    "wof:population":8
},
  "geometry": {"coordinates":[-100.99361,24.48833],"type":"Point"}
}