{
  "type": "Feature",
  "properties": {
    "gn:admin1_code":"28.0",
    "gn:admin2_code":"11.0",
    "gn:asciiname":"El Cielo",
    "gn:country_code":"MX",
    "gn:dem":1174,
    "gn:feature_class":"P",
    "gn:feature_code":"PPL",
    "gn:name":"El Cielo",
    "gn:population":0,
    "gn:timezone":"America/Monterrey",
    "iso:country":"MX",
    "name:spa_x_preferred":[
        "El Cielo"
    ],
    "wof:name":"El Cielo",
    "wof:placetype":"locality"
},
  "geometry": {"coordinates":[-99.19255,23.09976],"type":"Point"}
}