{
  "type": "Feature",
  "properties": {
    "gn:admin1_code":"30",
    "gn:admin2_code":"123.0",
    "gn:asciiname":"Ejido Tancoco",
    "gn:country_code":"MX",
    "gn:dem":35,
    "gn:feature_class":"P",
    "gn:feature_code":"PPL",
    "gn:name":"Ejido Tancoco",
    "gn:population":77,
    "gn:timezone":"America/Mexico_City",
    "iso:country":"MX",
    "wof:name":"Ejido Tancoco",
    "wof:placetype":"locality",
    "wof:population":77
},
  "geometry": {"coordinates":[-98.31028000000001,22.19167],"type":"Point"}
}