{
  "type": "Feature",
  "properties": {
    "gn:admin1_code":"4",
    "gn:admin2_code":"10.0",
    "gn:asciiname":"Felix",
    "gn:country_code":"MX",
    "gn:dem":250,
    "gn:feature_class":"P",
    "gn:feature_code":"PPL",
    "gn:name":"F\u00e9lix",
    "gn:population":4,
    "gn:timezone":"America/Cancun",
    "iso:country":"MX",
    "name:und_x_variant":[
        "F\u00e9lix"
    ],
    "wof:name":"Felix",
    "wof:placetype":"locality",
    "wof:population":4
},
  "geometry": {"coordinates":[-89.31305999999999,18.49694],"type":"Point"}
}