{
  "type": "Feature",
  "properties": {
    "gn:admin1_code":"4",
    "gn:admin2_code":"10.0",
    "gn:asciiname":"Felix",
    "gn:country_code":"MX",
    "gn:dem":250,
    "gn:feature_class":"P",
    "gn:feature_code":"PPL",
    "gn:name":"F\u00e9lix",
    "gn:population":4,
    "gn:timezone":"America/Cancun",
    "iso:country":"MX",
    "name:bre_x_preferred":[
        "Felix"
    ],
    "name:bul_x_preferred":[
        "\u0424\u0435\u043b\u0438\u043a\u0441"
    ],
    "name:cat_x_preferred":[
        "F\u00e8lix"
    ],
    "name:ceb_x_preferred":[
        "Felix"
    ],
    "name:ces_x_preferred":[
        "Felix"
    ],
    "name:deu_x_preferred":[
        "Felix"
    ],
    "name:ell_x_preferred":[
        "\u03a6\u03ae\u03bb\u03b9\u03be"
    ],
    "name:est_x_preferred":[
        "Felix"
    ],
    "name:heb_x_preferred":[
        "\u05e4\u05dc\u05d9\u05e7\u05e1"
    ],
    "name:ita_x_preferred":[
        "Felix"
    ],
    "name:jpn_x_preferred":[
        "\u30d5\u30a7\u30ea\u30af\u30b9"
    ],
    "name:kor_x_preferred":[
        "\ud3a0\ub9ad\uc2a4"
    ],
    "name:lav_x_preferred":[
        "F\u0113likss"
    ],
    "name:nld_x_preferred":[
        "Felix"
    ],
    "name:pol_x_preferred":[
        "Felix"
    ],
    "name:ron_x_preferred":[
        "Felix"
    ],
    "name:rus_x_preferred":[
        "\u0424\u0435\u043b\u0438\u043a\u0441"
    ],
    "name:swe_x_preferred":[
        "Felix"
    ],
    "name:tur_x_preferred":[
        "Felix"
    ],
    "name:ukr_x_preferred":[
        "\u0424\u0435\u043b\u0456\u043a\u0441"
    ],
    "name:und_x_variant":[
        "F\u00e9lix"
    ],
    "name:zho_x_preferred":[
        "Felix"
    ],
    "wof:name":"Felix",
    "wof:placetype":"locality",
    "wof:population":4
},
  "geometry": {"coordinates":[-89.31305999999999,18.49694],"type":"Point"}
}