{
  "type": "Feature",
  "properties": {
    "gn:admin1_code":"16",
    "gn:admin2_code":"97.0",
    "gn:asciiname":"Los Saucitos",
    "gn:country_code":"MX",
    "gn:dem":1613,
    "gn:feature_class":"P",
    "gn:feature_code":"PPL",
    "gn:name":"Los Saucitos",
    "gn:population":0,
    "gn:timezone":"America/Mexico_City",
    "iso:country":"MX",
    "name:spa_x_preferred":[
        "Los Saucitos"
    ],
    "wof:name":"Los Saucitos",
    "wof:placetype":"locality"
},
  "geometry": {"coordinates":[-101.52133000000001,19.03434],"type":"Point"}
}