{
  "type": "Feature",
  "properties": {
    "gn:admin1_code":"22.0",
    "gn:admin2_code":"5.0",
    "gn:asciiname":"Establos",
    "gn:country_code":"MX",
    "gn:dem":1909,
    "gn:feature_class":"P",
    "gn:feature_code":"PPL",
    "gn:name":"Establos",
    "gn:population":0,
    "gn:timezone":"America/Mexico_City",
    "iso:country":"MX",
    "wof:name":"Establos",
    "wof:placetype":"locality"
},
  "geometry": {"coordinates":[-100.14167,20.58056],"type":"Point"}
}