{
  "type": "Feature",
  "properties": {
    "gn:admin1_code":"30",
    "gn:admin2_code":"77.0",
    "gn:asciiname":"Dos Estrellas",
    "gn:country_code":"MX",
    "gn:dem":107,
    "gn:feature_class":"P",
    "gn:feature_code":"PPL",
    "gn:name":"Dos Estrellas",
    "gn:population":7,
    "gn:timezone":"America/Mexico_City",
    "iso:country":"MX",
    "wof:name":"Dos Estrellas",
    "wof:placetype":"locality",
    "wof:population":7
},
  "geometry": {"coordinates":[-95.57361,17.94693999999999],"type":"Point"}
}