{
  "type": "Feature",
  "properties": {
    "gn:admin1_code":"26.0",
    "gn:admin2_code":"52.0",
    "gn:asciiname":"Vinorama",
    "gn:country_code":"MX",
    "gn:dem":1189,
    "gn:feature_class":"P",
    "gn:feature_code":"PPL",
    "gn:name":"Vinorama",
    "gn:population":0,
    "gn:timezone":"America/Hermosillo",
    "iso:country":"MX",
    "name:spa_x_preferred":[
        "Vinorama"
    ],
    "wof:name":"Vinorama",
    "wof:placetype":"locality"
},
  "geometry": {"coordinates":[-108.80097000000001,29.01598],"type":"Point"}
}