{
  "type": "Feature",
  "properties": {
    "gn:admin1_code":"27",
    "gn:admin2_code":"12.0",
    "gn:asciiname":"Bonanza Primera Seccion",
    "gn:country_code":"MX",
    "gn:dem":33,
    "gn:feature_class":"P",
    "gn:feature_code":"PPL",
    "gn:name":"Bonanza Primera Secci\u00f3n",
    "gn:population":0,
    "gn:timezone":"America/Mexico_City",
    "iso:country":"MX",
    "name:spa_x_preferred":[
        "Bonanza Primera Secci\u00f3n"
    ],
    "wof:name":"Bonanza Primera Seccion",
    "wof:placetype":"locality"
},
  "geometry": {"coordinates":[-92.26872,17.70767],"type":"Point"}
}