{
  "type": "Feature",
  "properties": {
    "gn:admin1_code":"6.0",
    "gn:asciiname":"El Carmen Uno",
    "gn:country_code":"MX",
    "gn:dem":1173,
    "gn:feature_class":"P",
    "gn:feature_code":"PPL",
    "gn:name":"El Carmen Uno",
    "gn:population":0,
    "gn:timezone":"America/Chihuahua",
    "iso:country":"MX",
    "name:spa_x_preferred":[
        "El Carmen Uno"
    ],
    "name:spa_x_variant":[
        "El Carmen"
    ],
    "wof:name":"El Carmen Uno",
    "wof:placetype":"locality"
},
  "geometry": {"coordinates":[-105.3897,28.25434000000001],"type":"Point"}
}