{
  "type": "Feature",
  "properties": {
    "gn:admin1_code":"19",
    "gn:admin2_code":"14.0",
    "gn:asciiname":"Villa Seca",
    "gn:country_code":"MX",
    "gn:dem":1879,
    "gn:feature_class":"P",
    "gn:feature_code":"PPL",
    "gn:name":"Villa Seca",
    "gn:population":5,
    "gn:timezone":"America/Monterrey",
    "iso:country":"MX",
    "wof:name":"Villa Seca",
    "wof:placetype":"locality",
    "wof:population":5
},
  "geometry": {"coordinates":[-100.14521999999999,23.69953],"type":"Point"}
}