{
  "type": "Feature",
  "properties": {
    "gn:admin1_code":"30.0",
    "gn:admin2_code":"161.0",
    "gn:asciiname":"Alto las Pilas",
    "gn:country_code":"MX",
    "gn:dem":52,
    "gn:feature_class":"P",
    "gn:feature_code":"PPL",
    "gn:name":"Alto las Pilas",
    "gn:population":0,
    "gn:timezone":"America/Mexico_City",
    "iso:country":"MX",
    "name:spa_x_preferred":[
        "Alto las Pilas"
    ],
    "wof:name":"Alto las Pilas",
    "wof:placetype":"locality"
},
  "geometry": {"coordinates":[-98.60222,21.61528],"type":"Point"}
}