{
  "type": "Feature",
  "properties": {
    "gn:admin1_code":"12.0",
    "gn:admin2_code":"8.0",
    "gn:asciiname":"Tehuaucingo",
    "gn:country_code":"MX",
    "gn:dem":611,
    "gn:feature_class":"P",
    "gn:feature_code":"PPL",
    "gn:name":"Tehuaucingo",
    "gn:population":0,
    "gn:timezone":"America/Mexico_City",
    "iso:country":"MX",
    "name:spa_x_preferred":[
        "Tehuaucingo"
    ],
    "wof:name":"Tehuaucingo",
    "wof:placetype":"locality"
},
  "geometry": {"coordinates":[-99.12662,18.00535],"type":"Point"}
}