{
  "type": "Feature",
  "properties": {
    "gn:admin1_code":"28",
    "gn:admin2_code":"32",
    "gn:asciiname":"Baltazar Diaz Bazan Uno",
    "gn:country_code":"MX",
    "gn:dem":63,
    "gn:feature_class":"P",
    "gn:feature_code":"PPL",
    "gn:name":"Baltazar D\u00edaz Baz\u00e1n Uno",
    "gn:population":13,
    "gn:timezone":"America/Matamoros",
    "iso:country":"MX",
    "name:und_x_variant":[
        "Baltazar D\u00edaz Baz\u00e1n Uno"
    ],
    "wof:name":"Baltazar Diaz Bazan Uno",
    "wof:placetype":"locality",
    "wof:population":13
},
  "geometry": {"coordinates":[-98.25861,25.78028],"type":"Point"}
}