{
  "type": "Feature",
  "properties": {
    "gn:admin1_code":"2",
    "gn:admin2_code":"2.0",
    "gn:asciiname":"Familia Corona",
    "gn:country_code":"MX",
    "gn:dem":17,
    "gn:feature_class":"P",
    "gn:feature_code":"PPL",
    "gn:name":"Familia Corona",
    "gn:population":4,
    "gn:timezone":"America/Tijuana",
    "iso:country":"MX",
    "wof:name":"Familia Corona",
    "wof:placetype":"locality",
    "wof:population":4
},
  "geometry": {"coordinates":[-115.10861,32.44167],"type":"Point"}
}