{
  "type": "Feature",
  "properties": {
    "gn:admin1_code":"6.0",
    "gn:admin2_code":"63.0",
    "gn:asciiname":"Catorce",
    "gn:cc2":"MX",
    "gn:country_code":"MX",
    "gn:dem":1903,
    "gn:feature_class":"P",
    "gn:feature_code":"PPL",
    "gn:name":"Catorce",
    "gn:population":0,
    "gn:timezone":"America/Chihuahua",
    "iso:country":"MX",
    "name:und_x_variant":[
        "Rancho Catorce",
        "Catoreo",
        "Catorce"
    ],
    "wof:name":"Catorce",
    "wof:placetype":"locality"
},
  "geometry": {"coordinates":[-108.34999999999999,28.38333],"type":"Point"}
}