{
  "type": "Feature",
  "properties": {
    "gn:admin1_code":"6.0",
    "gn:admin2_code":"63.0",
    "gn:asciiname":"Catorce",
    "gn:cc2":"MX",
    "gn:country_code":"MX",
    "gn:dem":1903,
    "gn:feature_class":"P",
    "gn:feature_code":"PPL",
    "gn:name":"Catorce",
    "gn:population":0,
    "gn:timezone":"America/Chihuahua",
    "iso:country":"MX",
    "name:cat_x_preferred":[
        "Catorce"
    ],
    "name:ceb_x_preferred":[
        "Catorce"
    ],
    "name:epo_x_preferred":[
        "Catorce"
    ],
    "name:eus_x_preferred":[
        "Catorce"
    ],
    "name:ita_x_preferred":[
        "Catorce"
    ],
    "name:lad_x_preferred":[
        "Catorce"
    ],
    "name:por_x_preferred":[
        "Catorce"
    ],
    "name:rus_x_preferred":[
        "\u041a\u0430\u0442\u043e\u0440\u0441\u0435"
    ],
    "name:sco_x_preferred":[
        "Catorce"
    ],
    "name:spa_x_preferred":[
        "Catorce"
    ],
    "name:srp_x_preferred":[
        "\u041e\u043f\u0448\u0442\u0438\u043d\u0430 \u041a\u0430\u0442\u043e\u0440\u0441\u0435"
    ],
    "name:swe_x_preferred":[
        "Catorce"
    ],
    "name:und_x_variant":[
        "Rancho Catorce",
        "Catoreo",
        "Catorce"
    ],
    "name:vie_x_preferred":[
        "Catorce"
    ],
    "wof:name":"Catorce",
    "wof:placetype":"locality"
},
  "geometry": {"coordinates":[-108.34999999999999,28.38333],"type":"Point"}
}