{
  "type": "Feature",
  "properties": {
    "gn:admin1_code":"32",
    "gn:admin2_code":"49.0",
    "gn:asciiname":"La Boquilla de San Isidro",
    "gn:country_code":"MX",
    "gn:dem":2271,
    "gn:feature_class":"P",
    "gn:feature_code":"PPL",
    "gn:name":"La Boquilla de San Isidro",
    "gn:population":0,
    "gn:timezone":"America/Mexico_City",
    "iso:country":"MX",
    "name:spa_x_preferred":[
        "La Boquilla de San Isidro"
    ],
    "name:und_x_variant":[
        "La Boquilla"
    ],
    "wof:name":"La Boquilla de San Isidro",
    "wof:placetype":"locality"
},
  "geometry": {"coordinates":[-103.45849,23.07579],"type":"Point"}
}