{
  "type": "Feature",
  "properties": {
    "gn:admin1_code":"10",
    "gn:admin2_code":"23.0",
    "gn:asciiname":"La Ventana",
    "gn:country_code":"MX",
    "gn:dem":1931,
    "gn:feature_class":"P",
    "gn:feature_code":"PPL",
    "gn:name":"La Ventana",
    "gn:population":106,
    "gn:timezone":"America/Monterrey",
    "iso:country":"MX",
    "name:urd_x_preferred":[
        "\u0644\u0627 \u0648\u06cc\u0646\u0679\u0627\u0646\u0627"
    ],
    "wof:name":"La Ventana",
    "wof:placetype":"locality",
    "wof:population":106
},
  "geometry": {"coordinates":[-104.90639,23.16083],"type":"Point"}
}