{
  "type": "Feature",
  "properties": {
    "gn:admin1_code":"20",
    "gn:admin2_code":"397.0",
    "gn:asciiname":"San  Juan del Rio",
    "gn:country_code":"MX",
    "gn:dem":1993,
    "gn:feature_class":"P",
    "gn:feature_code":"PPL",
    "gn:name":"San  Juan del R\u00edo",
    "gn:population":98,
    "gn:timezone":"America/Mexico_City",
    "iso:country":"MX",
    "name:und_x_variant":[
        "San Juan del R\u00edo"
    ],
    "wof:name":"San Juan del Rio",
    "wof:placetype":"locality",
    "wof:population":98
},
  "geometry": {"coordinates":[-97.77222,17.17361],"type":"Point"}
}