{
  "type": "Feature",
  "properties": {
    "gn:admin1_code":"12",
    "gn:admin2_code":"9.0",
    "gn:asciiname":"Tierra Colorada",
    "gn:country_code":"MX",
    "gn:dem":2131,
    "gn:feature_class":"P",
    "gn:feature_code":"PPL",
    "gn:name":"Tierra Colorada",
    "gn:population":266,
    "gn:timezone":"America/Mexico_City",
    "iso:country":"MX",
    "name:deu_x_preferred":[
        "Tierra Colorada"
    ],
    "name:ita_x_preferred":[
        "Tierra Colorada"
    ],
    "name:rus_x_preferred":[
        "\u0422\u044c\u0435\u0440\u0440\u0430-\u041a\u043e\u043b\u043e\u0440\u0430\u0434\u0430"
    ],
    "name:spa_x_preferred":[
        "Tierra Colorada"
    ],
    "wof:name":"Tierra Colorada",
    "wof:placetype":"locality",
    "wof:population":266
},
  "geometry": {"coordinates":[-98.62582999999999,17.24833],"type":"Point"}
}