{
  "type": "Feature",
  "properties": {
    "gn:admin1_code":"12",
    "gn:admin2_code":"9.0",
    "gn:asciiname":"Tierra Colorada",
    "gn:country_code":"MX",
    "gn:dem":2131,
    "gn:feature_class":"P",
    "gn:feature_code":"PPL",
    "gn:name":"Tierra Colorada",
    "gn:population":266,
    "gn:timezone":"America/Mexico_City",
    "iso:country":"MX",
    "wof:name":"Tierra Colorada",
    "wof:placetype":"locality",
    "wof:population":266
},
  "geometry": {"coordinates":[-98.62582999999999,17.24833],"type":"Point"}
}