{
  "type": "Feature",
  "properties": {
    "gn:admin1_code":"32",
    "gn:admin2_code":"10.0",
    "gn:asciiname":"Los Gavilanes",
    "gn:country_code":"MX",
    "gn:dem":2066,
    "gn:feature_class":"P",
    "gn:feature_code":"PPL",
    "gn:name":"Los Gavilanes",
    "gn:population":0,
    "gn:timezone":"America/Mexico_City",
    "iso:country":"MX",
    "name:spa_x_preferred":[
        "Los Gavilanes"
    ],
    "wof:name":"Los Gavilanes",
    "wof:placetype":"locality"
},
  "geometry": {"coordinates":[-102.86741000000001,23.32993],"type":"Point"}
}