{
  "type": "Feature",
  "properties": {
    "gn:admin1_code":"15",
    "gn:admin2_code":"124.0",
    "gn:asciiname":"Santa Cruz del Rincon",
    "gn:country_code":"MX",
    "gn:dem":2731,
    "gn:feature_class":"P",
    "gn:feature_code":"PPL",
    "gn:name":"Santa Cruz del Rinc\u00f3n",
    "gn:population":671,
    "gn:timezone":"America/Mexico_City",
    "iso:country":"MX",
    "name:und_x_variant":[
        "Santa Cruz del Rinc\u00f3n"
    ],
    "wof:name":"Santa Cruz del Rincon",
    "wof:placetype":"locality",
    "wof:population":671
},
  "geometry": {"coordinates":[-100.11333,19.66722],"type":"Point"}
}