{
  "type": "Feature",
  "properties": {
    "gn:admin1_code":"22",
    "gn:asciiname":"El Zapote",
    "gn:country_code":"MX",
    "gn:dem":992,
    "gn:feature_class":"P",
    "gn:feature_code":"PPL",
    "gn:name":"El Zapote",
    "gn:population":0,
    "gn:timezone":"America/Mexico_City",
    "iso:country":"MX",
    "name:spa_x_preferred":[
        "El Zapote"
    ],
    "wof:name":"El Zapote",
    "wof:placetype":"locality"
},
  "geometry": {"coordinates":[-99.69516,21.5682],"type":"Point"}
}