{
  "type": "Feature",
  "properties": {
    "gn:admin1_code":"27",
    "gn:admin2_code":"8.0",
    "gn:asciiname":"Esperanza del Bajio",
    "gn:country_code":"MX",
    "gn:dem":41,
    "gn:feature_class":"P",
    "gn:feature_code":"PPL",
    "gn:name":"Esperanza del Baj\u00edo",
    "gn:population":150,
    "gn:timezone":"America/Mexico_City",
    "iso:country":"MX",
    "name:und_x_variant":[
        "Esperanza del Baj\u00edo"
    ],
    "wof:name":"Esperanza del Bajio",
    "wof:placetype":"locality",
    "wof:population":150
},
  "geometry": {"coordinates":[-93.70361,17.69693999999999],"type":"Point"}
}