{
  "type": "Feature",
  "properties": {
    "gn:admin1_code":"6",
    "gn:admin2_code":"67.0",
    "gn:asciiname":"El Mimbre",
    "gn:country_code":"MX",
    "gn:dem":1383,
    "gn:feature_class":"P",
    "gn:feature_code":"PPL",
    "gn:name":"El Mimbre",
    "gn:population":0,
    "gn:timezone":"America/Chihuahua",
    "iso:country":"MX",
    "name:spa_x_preferred":[
        "El Mimbre"
    ],
    "wof:name":"El Mimbre",
    "wof:placetype":"locality"
},
  "geometry": {"coordinates":[-106.00494,27.34936],"type":"Point"}
}