{
  "type": "Feature",
  "properties": {
    "gn:admin1_code":"32.0",
    "gn:asciiname":"Zapotillo",
    "gn:country_code":"MX",
    "gn:dem":1843,
    "gn:feature_class":"P",
    "gn:feature_code":"PPL",
    "gn:name":"Zapotillo",
    "gn:population":0,
    "gn:timezone":"America/Mexico_City",
    "iso:country":"MX",
    "name:ita_x_preferred":[
        "Zapotillo"
    ],
    "name:spa_x_preferred":[
        "Zapotillo"
    ],
    "name:zho_x_preferred":[
        "\u85a9\u6ce2\u8482\u7565"
    ],
    "wof:name":"Zapotillo",
    "wof:placetype":"locality"
},
  "geometry": {"coordinates":[-103.92276,22.33161],"type":"Point"}
}