{
  "type": "Feature",
  "properties": {
    "gn:admin1_code":"7",
    "gn:admin2_code":"3.0",
    "gn:asciiname":"La Muralla",
    "gn:cc2":"MX",
    "gn:country_code":"MX",
    "gn:dem":462,
    "gn:feature_class":"P",
    "gn:feature_code":"PPL",
    "gn:name":"La Muralla",
    "gn:population":0,
    "gn:timezone":"America/Monterrey",
    "iso:country":"MX",
    "name:und_x_variant":[
        "Muralla",
        "La Muralla"
    ],
    "wof:name":"La Muralla",
    "wof:placetype":"locality"
},
  "geometry": {"coordinates":[-100.93333,28.23333],"type":"Point"}
}