{
  "type": "Feature",
  "properties": {
    "gn:admin1_code":"22",
    "gn:admin2_code":"18.0",
    "gn:asciiname":"Las Crucitas",
    "gn:country_code":"MX",
    "gn:dem":1485,
    "gn:feature_class":"P",
    "gn:feature_code":"PPL",
    "gn:name":"Las Crucitas",
    "gn:population":0,
    "gn:timezone":"America/Mexico_City",
    "iso:country":"MX",
    "name:spa_x_preferred":[
        "Las Crucitas"
    ],
    "name:spa_x_variant":[
        "Crucitas"
    ],
    "wof:name":"Las Crucitas",
    "wof:placetype":"locality",
    "wof:population":57
},
  "geometry": {"coordinates":[-99.88903999999999,20.96951],"type":"Point"}
}