{
  "type": "Feature",
  "properties": {
    "gn:admin1_code":"5",
    "gn:admin2_code":"59.0",
    "gn:asciiname":"San Juan del Rio",
    "gn:country_code":"MX",
    "gn:dem":742,
    "gn:feature_class":"P",
    "gn:feature_code":"PPL",
    "gn:name":"San Juan del R\u00edo",
    "gn:population":53,
    "gn:timezone":"America/Mexico_City",
    "iso:country":"MX",
    "name:und_x_variant":[
        "San Juan del R\u00edo"
    ],
    "wof:name":"San Juan del Rio",
    "wof:placetype":"locality",
    "wof:population":53
},
  "geometry": {"coordinates":[-91.66583,16.91806],"type":"Point"}
}