{
  "type": "Feature",
  "properties": {
    "gn:admin1_code":"15.0",
    "gn:admin2_code":"1.0",
    "gn:asciiname":"Loma del Fresno",
    "gn:country_code":"MX",
    "gn:dem":2667,
    "gn:feature_class":"P",
    "gn:feature_code":"PPL",
    "gn:name":"Loma del Fresno",
    "gn:population":285,
    "gn:timezone":"America/Mexico_City",
    "iso:country":"MX",
    "wof:name":"Loma del Fresno",
    "wof:placetype":"locality",
    "wof:population":285
},
  "geometry": {"coordinates":[-100.00611000000001,20.02778],"type":"Point"}
}