{
  "type": "Feature",
  "properties": {
    "gn:admin1_code":"6",
    "gn:admin2_code":"27",
    "gn:asciiname":"Cordon de la Cumbre",
    "gn:country_code":"MX",
    "gn:dem":2408,
    "gn:feature_class":"P",
    "gn:feature_code":"PPL",
    "gn:name":"Cord\u00f3n de la Cumbre",
    "gn:population":12,
    "gn:timezone":"America/Chihuahua",
    "iso:country":"MX",
    "name:und_x_variant":[
        "Cord\u00f3n de la Cumbre"
    ],
    "wof:name":"Cordon de la Cumbre",
    "wof:placetype":"locality",
    "wof:population":12
},
  "geometry": {"coordinates":[-107.06895,26.72006],"type":"Point"}
}