{
  "type": "Feature",
  "properties": {
    "gn:admin1_code":"30",
    "gn:admin2_code":"23.0",
    "gn:asciiname":"El Campamento",
    "gn:country_code":"MX",
    "gn:dem":404,
    "gn:feature_class":"P",
    "gn:feature_code":"PPL",
    "gn:name":"El Campamento",
    "gn:population":940,
    "gn:timezone":"America/Mexico_City",
    "iso:country":"MX",
    "wof:name":"El Campamento",
    "wof:placetype":"locality",
    "wof:population":940
},
  "geometry": {"coordinates":[-97.16861,19.95028],"type":"Point"}
}