{
  "type": "Feature",
  "properties": {
    "gn:admin1_code":"1",
    "gn:admin2_code":"4",
    "gn:asciiname":"El Ciruelo",
    "gn:country_code":"MX",
    "gn:dem":1993,
    "gn:feature_class":"P",
    "gn:feature_code":"PPL",
    "gn:name":"El Ciruelo",
    "gn:population":37,
    "gn:timezone":"America/Mexico_City",
    "iso:country":"MX",
    "name:ita_x_preferred":[
        "El Ciruelo"
    ],
    "name:spa_x_preferred":[
        "El Ciruelo"
    ],
    "name:zho_x_preferred":[
        "\u57c3\u723e\u897f\u9b6f\u57c3\u6d1b"
    ],
    "wof:name":"El Ciruelo",
    "wof:placetype":"locality",
    "wof:population":37
},
  "geometry": {"coordinates":[-102.29971999999999,22.375],"type":"Point"}
}