{
  "type": "Feature",
  "properties": {
    "gn:admin1_code":"16.0",
    "gn:admin2_code":"14.0",
    "gn:asciiname":"Agua del Gallo",
    "gn:country_code":"MX",
    "gn:dem":241,
    "gn:feature_class":"P",
    "gn:feature_code":"PPL",
    "gn:name":"Agua del Gallo",
    "gn:population":0,
    "gn:timezone":"America/Mexico_City",
    "iso:country":"MX",
    "name:spa_x_preferred":[
        "Agua del Gallo"
    ],
    "wof:name":"Agua del Gallo",
    "wof:placetype":"locality"
},
  "geometry": {"coordinates":[-103.5573,18.73171],"type":"Point"}
}