{
  "type": "Feature",
  "properties": {
    "gn:admin1_code":"7",
    "gn:admin2_code":"36.0",
    "gn:asciiname":"Tierra Libertad",
    "gn:country_code":"MX",
    "gn:dem":1108,
    "gn:feature_class":"P",
    "gn:feature_code":"PPL",
    "gn:name":"Tierra Libertad",
    "gn:population":0,
    "gn:timezone":"America/Monterrey",
    "iso:country":"MX",
    "name:spa_x_preferred":[
        "Tierra Libertad"
    ],
    "name:und_x_variant":[
        "Tierra y Libertad"
    ],
    "wof:name":"Tierra Libertad",
    "wof:placetype":"locality"
},
  "geometry": {"coordinates":[-103.0928,25.40788],"type":"Point"}
}