{
  "type": "Feature",
  "properties": {
    "gn:admin1_code":"3",
    "gn:admin2_code":"2.0",
    "gn:asciiname":"El Aguajito de Bermudez",
    "gn:country_code":"MX",
    "gn:dem":596,
    "gn:feature_class":"P",
    "gn:feature_code":"PPL",
    "gn:name":"El Aguajito de Berm\u00fadez",
    "gn:population":4,
    "gn:timezone":"America/Mazatlan",
    "iso:country":"MX",
    "name:und_x_variant":[
        "El Aguajito de Berm\u00fadez"
    ],
    "wof:name":"El Aguajito de Bermudez",
    "wof:placetype":"locality",
    "wof:population":4
},
  "geometry": {"coordinates":[-112.94806,27.52479000000001],"type":"Point"}
}