{
  "type": "Feature",
  "properties": {
    "gn:admin1_code":"10.0",
    "gn:admin2_code":"25.0",
    "gn:asciiname":"Barrio",
    "gn:country_code":"MX",
    "gn:dem":1627,
    "gn:feature_class":"P",
    "gn:feature_code":"PPL",
    "gn:name":"Barrio",
    "gn:population":0,
    "gn:timezone":"America/Monterrey",
    "iso:country":"MX",
    "name:deu_x_preferred":[
        "Barrio"
    ],
    "name:hun_x_preferred":[
        "Barrio"
    ],
    "name:ilo_x_preferred":[
        "Barrio"
    ],
    "name:ind_x_preferred":[
        "Barrio"
    ],
    "name:ita_x_preferred":[
        "Barrio"
    ],
    "name:lat_x_preferred":[
        "Barrium"
    ],
    "name:scn_x_preferred":[
        "Barrio"
    ],
    "name:spa_x_preferred":[
        "Barrio"
    ],
    "name:swe_x_preferred":[
        "Barrio"
    ],
    "name:tur_x_preferred":[
        "Barrio"
    ],
    "wof:name":"Barrio",
    "wof:placetype":"locality"
},
  "geometry": {"coordinates":[-105.48333,25.98333],"type":"Point"}
}