{
  "type": "Feature",
  "properties": {
    "gn:admin1_code":"30",
    "gn:admin2_code":"142.0",
    "gn:asciiname":"Poblado los Arco Iris",
    "gn:country_code":"MX",
    "gn:dem":70,
    "gn:feature_class":"P",
    "gn:feature_code":"PPL",
    "gn:name":"Poblado los Arco Iris",
    "gn:population":209,
    "gn:timezone":"America/Mexico_City",
    "iso:country":"MX",
    "wof:name":"Poblado los Arco Iris",
    "wof:placetype":"locality",
    "wof:population":209
},
  "geometry": {"coordinates":[-95.4225,17.72861],"type":"Point"}
}