{
  "type": "Feature",
  "properties": {
    "gn:admin1_code":"14",
    "gn:admin2_code":"35.0",
    "gn:asciiname":"El Carmen",
    "gn:country_code":"MX",
    "gn:dem":1985,
    "gn:feature_class":"P",
    "gn:feature_code":"PPL",
    "gn:name":"El Carmen",
    "gn:population":180,
    "gn:timezone":"America/Mexico_City",
    "iso:country":"MX",
    "wof:name":"El Carmen",
    "wof:placetype":"locality",
    "wof:population":180
},
  "geometry": {"coordinates":[-101.99250000000001,21.70111],"type":"Point"}
}