{
  "type": "Feature",
  "properties": {
    "gn:admin1_code":"6.0",
    "gn:admin2_code":"27.0",
    "gn:asciiname":"Aguaje Escondido",
    "gn:country_code":"MX",
    "gn:dem":2093,
    "gn:feature_class":"P",
    "gn:feature_code":"PPL",
    "gn:name":"Aguaje Escondido",
    "gn:population":0,
    "gn:timezone":"America/Chihuahua",
    "iso:country":"MX",
    "name:spa_x_preferred":[
        "Aguaje Escondido"
    ],
    "wof:name":"Aguaje Escondido",
    "wof:placetype":"locality"
},
  "geometry": {"coordinates":[-106.88800999999999,26.75899],"type":"Point"}
}