{
  "type": "Feature",
  "properties": {
    "gn:admin1_code":"26",
    "gn:admin2_code":"30.0",
    "gn:asciiname":"Hector Ruiz",
    "gn:country_code":"MX",
    "gn:dem":294,
    "gn:feature_class":"P",
    "gn:feature_code":"PPL",
    "gn:name":"H\u00e9ctor Ruiz",
    "gn:population":6,
    "gn:timezone":"America/Hermosillo",
    "iso:country":"MX",
    "name:ara_x_preferred":[
        "\u0647\u0643\u062a\u0648\u0631 \u0631\u0648\u064a\u0632"
    ],
    "name:deu_x_preferred":[
        "H\u00e9ctor Ruiz"
    ],
    "name:por_x_preferred":[
        "H\u00e9ctor Ruiz"
    ],
    "wof:name":"Hector Ruiz",
    "wof:placetype":"locality",
    "wof:population":6
},
  "geometry": {"coordinates":[-110.87027999999999,29.29722000000001],"type":"Point"}
}