{
  "type": "Feature",
  "properties": {
    "gn:admin1_code":"10",
    "gn:admin2_code":"10.0",
    "gn:asciiname":"Roman Arreola",
    "gn:country_code":"MX",
    "gn:dem":1892,
    "gn:feature_class":"P",
    "gn:feature_code":"PPL",
    "gn:name":"Rom\u00e1n Arreola",
    "gn:population":0,
    "gn:timezone":"America/Monterrey",
    "iso:country":"MX",
    "name:spa_x_preferred":[
        "La Mimbrera"
    ],
    "name:und_x_variant":[
        "Rom\u00e1n Arreola",
        "Mimbrera"
    ],
    "wof:name":"Roman Arreola",
    "wof:placetype":"locality"
},
  "geometry": {"coordinates":[-105.03212000000001,26.08494],"type":"Point"}
}