{
  "type": "Feature",
  "properties": {
    "gn:admin1_code":"26",
    "gn:admin2_code":"37.0",
    "gn:asciiname":"La Pitahaya",
    "gn:country_code":"MX",
    "gn:dem":499,
    "gn:feature_class":"P",
    "gn:feature_code":"PPL",
    "gn:name":"La Pitahaya",
    "gn:population":2,
    "gn:timezone":"America/Hermosillo",
    "iso:country":"MX",
    "name:spa_x_preferred":[
        "La Pitahaya"
    ],
    "wof:name":"La Pitahaya",
    "wof:placetype":"locality",
    "wof:population":2
},
  "geometry": {"coordinates":[-110.17567,28.90419],"type":"Point"}
}