{
  "type": "Feature",
  "properties": {
    "gn:admin1_code":"6.0",
    "gn:admin2_code":"65.0",
    "gn:asciiname":"Chapote",
    "gn:country_code":"MX",
    "gn:dem":1826,
    "gn:feature_class":"P",
    "gn:feature_code":"PPL",
    "gn:name":"Chapote",
    "gn:population":0,
    "gn:timezone":"America/Chihuahua",
    "iso:country":"MX",
    "name:spa_x_preferred":[
        "Chapote"
    ],
    "wof:name":"Chapote",
    "wof:placetype":"locality"
},
  "geometry": {"coordinates":[-108.02094,27.35495],"type":"Point"}
}