{
  "type": "Feature",
  "properties": {
    "gn:admin1_code":"6",
    "gn:admin2_code":"58.0",
    "gn:asciiname":"La Coqueta",
    "gn:country_code":"MX",
    "gn:dem":1247,
    "gn:feature_class":"P",
    "gn:feature_code":"PPL",
    "gn:name":"La Coqueta",
    "gn:population":85,
    "gn:timezone":"America/Chihuahua",
    "iso:country":"MX",
    "name:spa_x_preferred":[
        "La Coqueta"
    ],
    "wof:name":"La Coqueta",
    "wof:placetype":"locality",
    "wof:population":85
},
  "geometry": {"coordinates":[-105.3519,27.59593],"type":"Point"}
}