{
  "type": "Feature",
  "properties": {
    "gn:admin1_code":"6.0",
    "gn:admin2_code":"23.0",
    "gn:asciiname":"Galera Parrena",
    "gn:country_code":"MX",
    "gn:dem":1443,
    "gn:feature_class":"P",
    "gn:feature_code":"PPL",
    "gn:name":"Galera Parre\u00f1a",
    "gn:population":0,
    "gn:timezone":"America/Chihuahua",
    "iso:country":"MX",
    "name:und_x_variant":[
        "Rancho Parre\u00f1o",
        "Galera Parre\u00f1a"
    ],
    "wof:name":"Galera Parrena",
    "wof:placetype":"locality"
},
  "geometry": {"coordinates":[-107.65378,30.07517],"type":"Point"}
}