{
  "type": "Feature",
  "properties": {
    "gn:admin1_code":"10.0",
    "gn:admin2_code":"39.0",
    "gn:asciiname":"Las Gemelas",
    "gn:country_code":"MX",
    "gn:dem":1997,
    "gn:feature_class":"P",
    "gn:feature_code":"PPL",
    "gn:name":"Las Gemelas",
    "gn:population":0,
    "gn:timezone":"America/Monterrey",
    "iso:country":"MX",
    "name:spa_x_preferred":[
        "Las Gemelas"
    ],
    "wof:name":"Las Gemelas",
    "wof:placetype":"locality"
},
  "geometry": {"coordinates":[-105.07971999999999,24.87331],"type":"Point"}
}