{
  "type": "Feature",
  "properties": {
    "gn:admin1_code":"30",
    "gn:admin2_code":"155.0",
    "gn:asciiname":"Rey de Oros",
    "gn:country_code":"MX",
    "gn:dem":105,
    "gn:feature_class":"P",
    "gn:feature_code":"PPL",
    "gn:name":"Rey de Oros",
    "gn:population":3,
    "gn:timezone":"America/Mexico_City",
    "iso:country":"MX",
    "name:und_x_variant":[
        "Rey de Ores",
        "Rey de Oros"
    ],
    "wof:name":"Rey de Oros",
    "wof:placetype":"locality",
    "wof:population":3
},
  "geometry": {"coordinates":[-98.14245,21.5498],"type":"Point"}
}