{
  "type": "Feature",
  "properties": {
    "gn:admin1_code":"26.0",
    "gn:admin2_code":"2.0",
    "gn:asciiname":"Tapila",
    "gn:country_code":"MX",
    "gn:dem":1428,
    "gn:feature_class":"P",
    "gn:feature_code":"PPL",
    "gn:name":"Tapila",
    "gn:population":0,
    "gn:timezone":"America/Hermosillo",
    "iso:country":"MX",
    "name:spa_x_preferred":[
        "Tapila"
    ],
    "name:und_x_variant":[
        "Rancho El T\u00e1pila"
    ],
    "wof:name":"Tapila",
    "wof:placetype":"locality"
},
  "geometry": {"coordinates":[-109.0127,31.18225],"type":"Point"}
}