{
  "type": "Feature",
  "properties": {
    "gn:admin1_code":"18",
    "gn:admin2_code":"19.0",
    "gn:asciiname":"La Pulga",
    "gn:country_code":"MX",
    "gn:dem":1030,
    "gn:feature_class":"P",
    "gn:feature_code":"PPL",
    "gn:name":"La Pulga",
    "gn:population":8,
    "gn:timezone":"America/Mexico_City",
    "iso:country":"MX",
    "wof:name":"La Pulga",
    "wof:placetype":"locality",
    "wof:population":8
},
  "geometry": {"coordinates":[-103.91249999999999,21.52944],"type":"Point"}
}