{
  "type": "Feature",
  "properties": {
    "gn:admin1_code":"32.0",
    "gn:admin2_code":"49.0",
    "gn:asciiname":"Las Caidas",
    "gn:country_code":"MX",
    "gn:dem":1905,
    "gn:feature_class":"P",
    "gn:feature_code":"PPL",
    "gn:name":"Las Caidas",
    "gn:population":0,
    "gn:timezone":"America/Mexico_City",
    "iso:country":"MX",
    "name:spa_x_preferred":[
        "Las Caidas"
    ],
    "wof:name":"Las Caidas",
    "wof:placetype":"locality"
},
  "geometry": {"coordinates":[-103.59687,22.73325],"type":"Point"}
}