{
  "type": "Feature",
  "properties": {
    "gn:admin1_code":"6",
    "gn:admin2_code":"29.0",
    "gn:asciiname":"El Sabinal",
    "gn:country_code":"MX",
    "gn:dem":2446,
    "gn:feature_class":"P",
    "gn:feature_code":"PPL",
    "gn:name":"El Sabinal",
    "gn:population":0,
    "gn:timezone":"America/Chihuahua",
    "iso:country":"MX",
    "name:spa_x_preferred":[
        "El Sabinal"
    ],
    "wof:name":"El Sabinal",
    "wof:placetype":"locality"
},
  "geometry": {"coordinates":[-107.39626,26.45293],"type":"Point"}
}