{
  "type": "Feature",
  "properties": {
    "gn:admin1_code":"12",
    "gn:admin2_code":"30.0",
    "gn:asciiname":"Huerta Grande",
    "gn:country_code":"MX",
    "gn:dem":23,
    "gn:feature_class":"P",
    "gn:feature_code":"PPL",
    "gn:name":"Huerta Grande",
    "gn:population":54,
    "gn:timezone":"America/Mexico_City",
    "iso:country":"MX",
    "wof:name":"Huerta Grande",
    "wof:placetype":"locality",
    "wof:population":54
},
  "geometry": {"coordinates":[-99.19302,16.7185],"type":"Point"}
}