{
  "type": "Feature",
  "properties": {
    "gn:admin1_code":"16",
    "gn:admin2_code":"102",
    "gn:asciiname":"Rincon de las Aguilas",
    "gn:country_code":"MX",
    "gn:dem":1757,
    "gn:feature_class":"P",
    "gn:feature_code":"PPL",
    "gn:name":"Rinc\u00f3n de las \u00c1guilas",
    "gn:population":43,
    "gn:timezone":"America/Mexico_City",
    "iso:country":"MX",
    "name:und_x_variant":[
        "Rinc\u00f3n de las \u00c1guilas"
    ],
    "wof:name":"Rincon de las Aguilas",
    "wof:placetype":"locality",
    "wof:population":43
},
  "geometry": {"coordinates":[-102.08861,19.43028],"type":"Point"}
}