{
  "type": "Feature",
  "properties": {
    "gn:admin1_code":"6",
    "gn:admin2_code":"67.0",
    "gn:asciiname":"Penjamo",
    "gn:country_code":"MX",
    "gn:dem":1316,
    "gn:feature_class":"P",
    "gn:feature_code":"PPL",
    "gn:name":"P\u00e9njamo",
    "gn:population":2,
    "gn:timezone":"America/Chihuahua",
    "iso:country":"MX",
    "name:spa_x_preferred":[
        "P\u00e9njamo"
    ],
    "wof:name":"Penjamo",
    "wof:placetype":"locality",
    "wof:population":2
},
  "geometry": {"coordinates":[-105.41123,27.47337000000001],"type":"Point"}
}