{
  "type": "Feature",
  "properties": {
    "gn:admin1_code":"6.0",
    "gn:admin2_code":"61.0",
    "gn:asciiname":"Carmona",
    "gn:country_code":"MX",
    "gn:dem":1540,
    "gn:feature_class":"P",
    "gn:feature_code":"PPL",
    "gn:name":"Carmona",
    "gn:population":10,
    "gn:timezone":"America/Chihuahua",
    "iso:country":"MX",
    "name:spa_x_preferred":[
        "Carmona"
    ],
    "wof:name":"Carmona",
    "wof:placetype":"locality",
    "wof:population":10
},
  "geometry": {"coordinates":[-105.91435,27.74938],"type":"Point"}
}