{
  "type": "Feature",
  "properties": {
    "gn:admin1_code":"6.0",
    "gn:admin2_code":"61.0",
    "gn:asciiname":"Carmona",
    "gn:country_code":"MX",
    "gn:dem":1540,
    "gn:feature_class":"P",
    "gn:feature_code":"PPL",
    "gn:name":"Carmona",
    "gn:population":10,
    "gn:timezone":"America/Chihuahua",
    "iso:country":"MX",
    "name:ceb_x_preferred":[
        "Carmona"
    ],
    "name:deu_x_preferred":[
        "Carmona"
    ],
    "name:fra_x_preferred":[
        "Carmona"
    ],
    "name:ita_x_preferred":[
        "Carmona"
    ],
    "name:jpn_x_preferred":[
        "\u30ab\u30eb\u30e2\u30ca"
    ],
    "name:nld_x_preferred":[
        "Carmona"
    ],
    "name:pol_x_preferred":[
        "Carmona"
    ],
    "name:por_x_preferred":[
        "Carmona"
    ],
    "name:rus_x_preferred":[
        "\u041a\u0430\u0440\u043c\u043e\u043d\u0430"
    ],
    "name:sco_x_preferred":[
        "Carmona"
    ],
    "name:spa_x_preferred":[
        "Carmona"
    ],
    "name:srp_x_preferred":[
        "\u041a\u0430\u0440\u043c\u043e\u043d\u0430"
    ],
    "name:swe_x_preferred":[
        "Carmona"
    ],
    "name:war_x_preferred":[
        "Carmona"
    ],
    "wof:name":"Carmona",
    "wof:placetype":"locality",
    "wof:population":10
},
  "geometry": {"coordinates":[-105.91435,27.74938],"type":"Point"}
}