{
  "type": "Feature",
  "properties": {
    "gn:admin1_code":"4",
    "gn:admin2_code":"8.0",
    "gn:asciiname":"San Eduardo",
    "gn:country_code":"MX",
    "gn:dem":6,
    "gn:feature_class":"P",
    "gn:feature_code":"PPL",
    "gn:name":"San Eduardo",
    "gn:population":0,
    "gn:timezone":"America/Merida",
    "iso:country":"MX",
    "name:spa_x_preferred":[
        "San Eduardo"
    ],
    "wof:name":"San Eduardo",
    "wof:placetype":"locality"
},
  "geometry": {"coordinates":[-90.26819999999999,20.00907],"type":"Point"}
}