{
  "type": "Feature",
  "properties": {
    "gn:admin1_code":"6",
    "gn:admin2_code":"41.0",
    "gn:asciiname":"Paraje Ochahuachi",
    "gn:country_code":"MX",
    "gn:dem":2127,
    "gn:feature_class":"P",
    "gn:feature_code":"PPL",
    "gn:name":"Paraje Och\u00e1huachi",
    "gn:population":0,
    "gn:timezone":"America/Chihuahua",
    "iso:country":"MX",
    "name:spa_x_preferred":[
        "Paraje Och\u00e1huachi"
    ],
    "wof:name":"Paraje Ochahuachi",
    "wof:placetype":"locality"
},
  "geometry": {"coordinates":[-107.86237,27.78674],"type":"Point"}
}