{
  "type": "Feature",
  "properties": {
    "gn:admin1_code":"25",
    "gn:admin2_code":"8.0",
    "gn:asciiname":"La Canita",
    "gn:country_code":"MX",
    "gn:dem":312,
    "gn:feature_class":"P",
    "gn:feature_code":"PPL",
    "gn:name":"La Ca\u00f1ita",
    "gn:population":5,
    "gn:timezone":"America/Mazatlan",
    "iso:country":"MX",
    "name:und_x_variant":[
        "La Ca\u00f1ita"
    ],
    "wof:name":"La Canita",
    "wof:placetype":"locality",
    "wof:population":5
},
  "geometry": {"coordinates":[-106.65372000000001,24.19078],"type":"Point"}
}