{
  "type": "Feature",
  "properties": {
    "gn:admin1_code":"30",
    "gn:admin2_code":"200.0",
    "gn:asciiname":"Rincon Patino",
    "gn:country_code":"MX",
    "gn:dem":271,
    "gn:feature_class":"P",
    "gn:feature_code":"PPL",
    "gn:name":"Rinc\u00f3n Pati\u00f1o",
    "gn:population":0,
    "gn:timezone":"America/Mexico_City",
    "iso:country":"MX",
    "name:spa_x_preferred":[
        "Rinc\u00f3n Pati\u00f1o"
    ],
    "wof:name":"Rincon Patino",
    "wof:placetype":"locality"
},
  "geometry": {"coordinates":[-96.57286999999999,19.05415],"type":"Point"}
}