{
  "type": "Feature",
  "properties": {
    "gn:admin1_code":"6",
    "gn:admin2_code":"65.0",
    "gn:asciiname":"La Mesa Tecomichi",
    "gn:country_code":"MX",
    "gn:dem":2033,
    "gn:feature_class":"P",
    "gn:feature_code":"PPL",
    "gn:name":"La Mesa Tecomichi",
    "gn:population":5,
    "gn:timezone":"America/Chihuahua",
    "iso:country":"MX",
    "wof:name":"La Mesa Tecomichi",
    "wof:placetype":"locality",
    "wof:population":5
},
  "geometry": {"coordinates":[-107.91656999999999,27.0891],"type":"Point"}
}