{
  "type": "Feature",
  "properties": {
    "gn:admin1_code":"20.0",
    "gn:admin2_code":"525.0",
    "gn:asciiname":"Reparo Lencho",
    "gn:country_code":"MX",
    "gn:dem":78,
    "gn:feature_class":"P",
    "gn:feature_code":"PPL",
    "gn:name":"Reparo Lencho",
    "gn:population":0,
    "gn:timezone":"America/Mexico_City",
    "iso:country":"MX",
    "name:spa_x_preferred":[
        "Reparo Lencho"
    ],
    "wof:name":"Reparo Lencho",
    "wof:placetype":"locality"
},
  "geometry": {"coordinates":[-94.39067,16.43407],"type":"Point"}
}