{
  "type": "Feature",
  "properties": {
    "gn:admin1_code":"16.0",
    "gn:admin2_code":"96.0",
    "gn:asciiname":"Jaltomate",
    "gn:country_code":"MX",
    "gn:dem":778,
    "gn:feature_class":"P",
    "gn:feature_code":"PPL",
    "gn:name":"Jaltomate",
    "gn:population":0,
    "gn:timezone":"America/Mexico_City",
    "iso:country":"MX",
    "name:spa_x_preferred":[
        "Jaltomate"
    ],
    "wof:name":"Jaltomate",
    "wof:placetype":"locality"
},
  "geometry": {"coordinates":[-102.39452,18.42375],"type":"Point"}
}