{
  "type": "Feature",
  "properties": {
    "gn:admin1_code":"30",
    "gn:admin2_code":"58.0",
    "gn:asciiname":"Tepetzintla",
    "gn:country_code":"MX",
    "gn:dem":403,
    "gn:feature_class":"P",
    "gn:feature_code":"PPL",
    "gn:name":"Tepetzintla",
    "gn:population":0,
    "gn:timezone":"America/Mexico_City",
    "iso:country":"MX",
    "name:ceb_x_preferred":[
        "Tepetzintla"
    ],
    "name:deu_x_preferred":[
        "Tepetzintla"
    ],
    "name:ita_x_preferred":[
        "Tepetzintla"
    ],
    "name:rus_x_preferred":[
        "\u0422\u0435\u043f\u0435\u0446\u0438\u043d\u0442\u043b\u0430"
    ],
    "name:spa_x_preferred":[
        "Tepetzintla"
    ],
    "name:swe_x_preferred":[
        "Tepetzintla"
    ],
    "name:und_x_variant":[
        "Tepelzintla"
    ],
    "wof:name":"Tepetzintla",
    "wof:placetype":"locality"
},
  "geometry": {"coordinates":[-98.14276,20.96677],"type":"Point"}
}