{
  "type": "Feature",
  "properties": {
    "gn:admin1_code":"30.0",
    "gn:admin2_code":"123.0",
    "gn:asciiname":"La Crema",
    "gn:country_code":"MX",
    "gn:dem":42,
    "gn:feature_class":"P",
    "gn:feature_code":"PPL",
    "gn:name":"La Crema",
    "gn:population":3,
    "gn:timezone":"America/Mexico_City",
    "iso:country":"MX",
    "name:spa_x_preferred":[
        "La Crema"
    ],
    "wof:name":"La Crema",
    "wof:placetype":"locality",
    "wof:population":3
},
  "geometry": {"coordinates":[-98.25221999999999,22.17667],"type":"Point"}
}