{
  "type": "Feature",
  "properties": {
    "gn:admin1_code":"20",
    "gn:admin2_code":"59.0",
    "gn:asciiname":"El Guayabo (San Isidro el Guayabo)",
    "gn:country_code":"MX",
    "gn:dem":1640,
    "gn:feature_class":"P",
    "gn:feature_code":"PPL",
    "gn:name":"El Guayabo (San Isidro el Guayabo)",
    "gn:population":342,
    "gn:timezone":"America/Mexico_City",
    "iso:country":"MX",
    "wof:name":"El Guayabo (San Isidro el Guayabo)",
    "wof:placetype":"locality",
    "wof:population":342
},
  "geometry": {"coordinates":[-96.61278,16.40694],"type":"Point"}
}