{
  "type": "Feature",
  "properties": {
    "gn:admin1_code":"26.0",
    "gn:admin2_code":"45.0",
    "gn:asciiname":"Las Granadas",
    "gn:country_code":"MX",
    "gn:dem":772,
    "gn:feature_class":"P",
    "gn:feature_code":"PPL",
    "gn:name":"Las Granadas",
    "gn:population":0,
    "gn:timezone":"America/Hermosillo",
    "iso:country":"MX",
    "name:spa_x_preferred":[
        "Las Granadas"
    ],
    "wof:name":"Las Granadas",
    "wof:placetype":"locality"
},
  "geometry": {"coordinates":[-110.68973,30.15672],"type":"Point"}
}