{
  "type": "Feature",
  "properties": {
    "gn:admin1_code":"6",
    "gn:admin2_code":"9.0",
    "gn:asciiname":"Tallarachi",
    "gn:country_code":"MX",
    "gn:dem":2215,
    "gn:feature_class":"P",
    "gn:feature_code":"PPL",
    "gn:name":"Tallarachi",
    "gn:population":151,
    "gn:timezone":"America/Chihuahua",
    "iso:country":"MX",
    "wof:name":"Tallarachi",
    "wof:placetype":"locality",
    "wof:population":151
},
  "geometry": {"coordinates":[-107.86493,27.67853],"type":"Point"}
}