{
  "type": "Feature",
  "properties": {
    "gn:admin1_code":"6",
    "gn:admin2_code":"12",
    "gn:asciiname":"Churugueichi",
    "gn:country_code":"MX",
    "gn:dem":1981,
    "gn:feature_class":"P",
    "gn:feature_code":"PPL",
    "gn:name":"Churug\u00fcichi",
    "gn:population":22,
    "gn:timezone":"America/Chihuahua",
    "iso:country":"MX",
    "name:und_x_variant":[
        "Churug\u00fcichi"
    ],
    "wof:name":"Churugueichi",
    "wof:placetype":"locality",
    "wof:population":22
},
  "geometry": {"coordinates":[-107.03881,27.67366],"type":"Point"}
}