{
  "type": "Feature",
  "properties": {
    "gn:admin1_code":"24",
    "gn:admin2_code":"57.0",
    "gn:asciiname":"Barrio Teopancahuatl",
    "gn:country_code":"MX",
    "gn:dem":472,
    "gn:feature_class":"P",
    "gn:feature_code":"PPL",
    "gn:name":"Barrio Teopancahuatl",
    "gn:population":265,
    "gn:timezone":"America/Mexico_City",
    "iso:country":"MX",
    "wof:name":"Barrio Teopancahuatl",
    "wof:placetype":"locality",
    "wof:population":265
},
  "geometry": {"coordinates":[-98.82194,21.29194],"type":"Point"}
}