{
  "type": "Feature",
  "properties": {
    "gn:admin1_code":"20",
    "gn:admin2_code":"570",
    "gn:asciiname":"Corral de Piedra",
    "gn:country_code":"MX",
    "gn:dem":1815,
    "gn:feature_class":"P",
    "gn:feature_code":"PPL",
    "gn:name":"Corral de Piedra",
    "gn:population":10,
    "gn:timezone":"America/Mexico_City",
    "iso:country":"MX",
    "wof:name":"Corral de Piedra",
    "wof:placetype":"locality",
    "wof:population":10
},
  "geometry": {"coordinates":[-97.15000000000001,16.83333],"type":"Point"}
}