{
  "type": "Feature",
  "properties": {
    "gn:admin1_code":"20.0",
    "gn:asciiname":"Cuatro Vientos",
    "gn:country_code":"MX",
    "gn:dem":2557,
    "gn:feature_class":"P",
    "gn:feature_code":"PPL",
    "gn:name":"Cuatro Vientos",
    "gn:population":0,
    "gn:timezone":"America/Mexico_City",
    "iso:country":"MX",
    "name:cat_x_preferred":[
        "Cuatro Vientos"
    ],
    "name:eus_x_preferred":[
        "Cuatro Vientos"
    ],
    "name:por_x_preferred":[
        "Cuatro Vientos"
    ],
    "name:spa_x_preferred":[
        "Cuatro Vientos"
    ],
    "name:spa_x_variant":[
        "Calle San Antonio Inuyu"
    ],
    "wof:name":"Cuatro Vientos",
    "wof:placetype":"locality"
},
  "geometry": {"coordinates":[-97.08219,17.59034],"type":"Point"}
}