{
  "type": "Feature",
  "properties": {
    "gn:admin1_code":"28.0",
    "gn:admin2_code":"12.0",
    "gn:asciiname":"El Tepeyac",
    "gn:country_code":"MX",
    "gn:dem":144,
    "gn:feature_class":"P",
    "gn:feature_code":"PPL",
    "gn:name":"El Tepeyac",
    "gn:population":0,
    "gn:timezone":"America/Monterrey",
    "iso:country":"MX",
    "name:spa_x_preferred":[
        "El Tepeyac"
    ],
    "wof:name":"El Tepeyac",
    "wof:placetype":"locality"
},
  "geometry": {"coordinates":[-98.46167,22.9125],"type":"Point"}
}