{
  "type": "Feature",
  "properties": {
    "gn:admin1_code":"1",
    "gn:admin2_code":"2.0",
    "gn:asciiname":"El Chinchin [Rancho]",
    "gn:country_code":"MX",
    "gn:dem":2005,
    "gn:feature_class":"P",
    "gn:feature_code":"PPL",
    "gn:name":"El Chinch\u00edn [Rancho]",
    "gn:population":6,
    "gn:timezone":"America/Mexico_City",
    "iso:country":"MX",
    "name:und_x_variant":[
        "El Chinch\u00edn [Rancho]"
    ],
    "wof:name":"El Chinchin [Rancho]",
    "wof:placetype":"locality",
    "wof:population":6
},
  "geometry": {"coordinates":[-102.02,22.06417],"type":"Point"}
}