{
  "type": "Feature",
  "properties": {
    "gn:admin1_code":"20",
    "gn:admin2_code":"348.0",
    "gn:asciiname":"Barrio Guadalupe",
    "gn:country_code":"MX",
    "gn:dem":2439,
    "gn:feature_class":"P",
    "gn:feature_code":"PPL",
    "gn:name":"Barrio Guadalupe",
    "gn:population":60,
    "gn:timezone":"America/Mexico_City",
    "iso:country":"MX",
    "wof:name":"Barrio Guadalupe",
    "wof:placetype":"locality",
    "wof:population":60
},
  "geometry": {"coordinates":[-98.14333000000001,17.30583],"type":"Point"}
}