{
  "type": "Feature",
  "properties": {
    "gn:admin1_code":"31",
    "gn:admin2_code":"79.0",
    "gn:asciiname":"San Luis Huechil",
    "gn:country_code":"MX",
    "gn:dem":144,
    "gn:feature_class":"P",
    "gn:feature_code":"PPL",
    "gn:name":"San Luis Huechil",
    "gn:population":0,
    "gn:timezone":"America/Merida",
    "iso:country":"MX",
    "name:spa_x_preferred":[
        "San Luis Huechil"
    ],
    "name:spa_x_variant":[
        "Huechil"
    ],
    "wof:name":"San Luis Huechil",
    "wof:placetype":"locality"
},
  "geometry": {"coordinates":[-89.28400999999999,19.92855],"type":"Point"}
}