{
  "type": "Feature",
  "properties": {
    "gn:admin1_code":"10",
    "gn:admin2_code":"1",
    "gn:asciiname":"Rancherias",
    "gn:country_code":"MX",
    "gn:dem":1953,
    "gn:feature_class":"P",
    "gn:feature_code":"PPL",
    "gn:name":"Rancher\u00edas",
    "gn:population":37,
    "gn:timezone":"America/Monterrey",
    "iso:country":"MX",
    "name:und_x_variant":[
        "Rancher\u00edas"
    ],
    "wof:name":"Rancherias",
    "wof:placetype":"locality",
    "wof:population":37
},
  "geometry": {"coordinates":[-104.58528,24.66333],"type":"Point"}
}