{
  "type": "Feature",
  "properties": {
    "gn:admin1_code":"6.0",
    "gn:admin2_code":"30.0",
    "gn:asciiname":"Los Nopalitos",
    "gn:country_code":"MX",
    "gn:dem":1181,
    "gn:feature_class":"P",
    "gn:feature_code":"PPL",
    "gn:name":"Los Nopalitos",
    "gn:population":0,
    "gn:timezone":"America/Chihuahua",
    "iso:country":"MX",
    "name:spa_x_preferred":[
        "Los Nopalitos"
    ],
    "wof:name":"Los Nopalitos",
    "wof:placetype":"locality"
},
  "geometry": {"coordinates":[-108.26521,27.15104],"type":"Point"}
}