{
  "type": "Feature",
  "properties": {
    "gn:admin1_code":"12",
    "gn:admin2_code":"43.0",
    "gn:asciiname":"Chimalapa",
    "gn:country_code":"MX",
    "gn:dem":414,
    "gn:feature_class":"P",
    "gn:feature_code":"PPL",
    "gn:name":"Chimalapa",
    "gn:population":733,
    "gn:timezone":"America/Mexico_City",
    "iso:country":"MX",
    "wof:name":"Chimalapa",
    "wof:placetype":"locality",
    "wof:population":733
},
  "geometry": {"coordinates":[-98.46250000000001,16.93111],"type":"Point"}
}