{
  "type": "Feature",
  "properties": {
    "gn:admin1_code":"8",
    "gn:admin2_code":"9.0",
    "gn:asciiname":"Los Retonos",
    "gn:country_code":"MX",
    "gn:dem":40,
    "gn:feature_class":"P",
    "gn:feature_code":"PPL",
    "gn:name":"Los Reto\u00f1os",
    "gn:population":5,
    "gn:timezone":"America/Mexico_City",
    "iso:country":"MX",
    "name:und_x_variant":[
        "Los Reto\u00f1os"
    ],
    "wof:name":"Los Retonos",
    "wof:placetype":"locality",
    "wof:population":5
},
  "geometry": {"coordinates":[-103.90667000000001,18.92472],"type":"Point"}
}