{
  "type": "Feature",
  "properties": {
    "gn:admin1_code":"30",
    "gn:admin2_code":"121.0",
    "gn:asciiname":"El Chintel",
    "gn:country_code":"MX",
    "gn:dem":102,
    "gn:feature_class":"P",
    "gn:feature_code":"PPL",
    "gn:name":"El Chintel",
    "gn:population":5,
    "gn:timezone":"America/Mexico_City",
    "iso:country":"MX",
    "wof:name":"El Chintel",
    "wof:placetype":"locality",
    "wof:population":5
},
  "geometry": {"coordinates":[-97.95139,21.41889],"type":"Point"}
}