{
  "type": "Feature",
  "properties": {
    "gn:admin1_code":"26",
    "gn:admin2_code":"18.0",
    "gn:asciiname":"Palos Quemados",
    "gn:country_code":"MX",
    "gn:dem":164,
    "gn:feature_class":"P",
    "gn:feature_code":"PPL",
    "gn:name":"Palos Quemados",
    "gn:population":0,
    "gn:timezone":"America/Hermosillo",
    "iso:country":"MX",
    "name:spa_x_preferred":[
        "Palos Quemados"
    ],
    "name:und_x_variant":[
        "Rancho Palos Quemados"
    ],
    "wof:name":"Palos Quemados",
    "wof:placetype":"locality"
},
  "geometry": {"coordinates":[-109.7003,28.11766],"type":"Point"}
}