{
  "type": "Feature",
  "properties": {
    "gn:admin1_code":"19.0",
    "gn:admin2_code":"20.0",
    "gn:asciiname":"San Jose de la Paz",
    "gn:country_code":"MX",
    "gn:dem":172,
    "gn:feature_class":"P",
    "gn:feature_code":"PPL",
    "gn:name":"San Jos\u00e9 de la Paz",
    "gn:population":0,
    "gn:timezone":"America/Monterrey",
    "iso:country":"MX",
    "name:spa_x_preferred":[
        "San Jos\u00e9 de la Paz"
    ],
    "wof:name":"San Jose de la Paz",
    "wof:placetype":"locality"
},
  "geometry": {"coordinates":[-98.81946000000001,25.66996],"type":"Point"}
}