{
  "type": "Feature",
  "properties": {
    "gn:admin1_code":"20",
    "gn:admin2_code":"265.0",
    "gn:asciiname":"Paso Lagarto",
    "gn:country_code":"MX",
    "gn:dem":68,
    "gn:feature_class":"P",
    "gn:feature_code":"PPL",
    "gn:name":"Paso Lagarto",
    "gn:population":0,
    "gn:timezone":"America/Mexico_City",
    "iso:country":"MX",
    "wof:name":"Paso Lagarto",
    "wof:placetype":"locality"
},
  "geometry": {"coordinates":[-94.76667,16.61667000000001],"type":"Point"}
}