{
  "type": "Feature",
  "properties": {
    "gn:admin1_code":"20",
    "gn:admin2_code":"313.0",
    "gn:asciiname":"Providencia",
    "gn:country_code":"MX",
    "gn:dem":1855,
    "gn:feature_class":"P",
    "gn:feature_code":"PPL",
    "gn:name":"Providencia",
    "gn:population":0,
    "gn:timezone":"America/Mexico_City",
    "iso:country":"MX",
    "wof:name":"Providencia",
    "wof:placetype":"locality"
},
  "geometry": {"coordinates":[-97.05,17.78333],"type":"Point"}
}