{
  "type": "Feature",
  "properties": {
    "gn:admin1_code":"7",
    "gn:admin2_code":"23.0",
    "gn:asciiname":"Rancho Santa Anita",
    "gn:country_code":"MX",
    "gn:dem":840,
    "gn:feature_class":"P",
    "gn:feature_code":"PPL",
    "gn:name":"Rancho Santa Anita",
    "gn:population":0,
    "gn:timezone":"America/Monterrey",
    "iso:country":"MX",
    "wof:name":"Rancho Santa Anita",
    "wof:placetype":"locality"
},
  "geometry": {"coordinates":[-102.83333,28.96667],"type":"Point"}
}