{
  "type": "Feature",
  "properties": {
    "gn:admin1_code":"20",
    "gn:admin2_code":"2",
    "gn:asciiname":"Sierra Mojarra",
    "gn:country_code":"MX",
    "gn:dem":129,
    "gn:feature_class":"P",
    "gn:feature_code":"PPL",
    "gn:name":"Sierra Mojarra",
    "gn:population":48,
    "gn:timezone":"America/Mexico_City",
    "iso:country":"MX",
    "wof:name":"Sierra Mojarra",
    "wof:placetype":"locality",
    "wof:population":48
},
  "geometry": {"coordinates":[-96.62306,18.54028],"type":"Point"}
}