{
  "type": "Feature",
  "properties": {
    "gn:admin1_code":"5",
    "gn:admin2_code":"61",
    "gn:asciiname":"Solo Dios",
    "gn:country_code":"MX",
    "gn:dem":800,
    "gn:feature_class":"P",
    "gn:feature_code":"PPL",
    "gn:name":"Solo Dios",
    "gn:population":47,
    "gn:timezone":"America/Mexico_City",
    "iso:country":"MX",
    "wof:name":"Solo Dios",
    "wof:placetype":"locality",
    "wof:population":47
},
  "geometry": {"coordinates":[-93.40306,16.88056],"type":"Point"}
}