{
  "type": "Feature",
  "properties": {
    "gn:admin1_code":"12",
    "gn:admin2_code":"26.0",
    "gn:asciiname":"Molonial",
    "gn:country_code":"MX",
    "gn:dem":1438,
    "gn:feature_class":"P",
    "gn:feature_code":"PPL",
    "gn:name":"Molonial",
    "gn:population":62,
    "gn:timezone":"America/Mexico_City",
    "iso:country":"MX",
    "wof:name":"Molonial",
    "wof:placetype":"locality",
    "wof:population":62
},
  "geometry": {"coordinates":[-99.89088,18.21744],"type":"Point"}
}