{
  "type": "Feature",
  "properties": {
    "gn:admin1_code":"15.0",
    "gn:admin2_code":"123.0",
    "gn:asciiname":"Paso del Agua Piedra Grande",
    "gn:country_code":"MX",
    "gn:dem":1200,
    "gn:feature_class":"P",
    "gn:feature_code":"PPL",
    "gn:name":"Paso del Agua Piedra Grande",
    "gn:population":0,
    "gn:timezone":"America/Mexico_City",
    "iso:country":"MX",
    "name:spa_x_preferred":[
        "Paso del Agua Piedra Grande"
    ],
    "wof:name":"Paso del Agua Piedra Grande",
    "wof:placetype":"locality"
},
  "geometry": {"coordinates":[-100.36163999999999,18.92841],"type":"Point"}
}