{
  "type": "Feature",
  "properties": {
    "gn:admin1_code":"8.0",
    "gn:admin2_code":"2.0",
    "gn:asciiname":"El Canario",
    "gn:country_code":"MX",
    "gn:dem":334,
    "gn:feature_class":"P",
    "gn:feature_code":"PPL",
    "gn:name":"El Canario",
    "gn:population":4,
    "gn:timezone":"America/Mexico_City",
    "iso:country":"MX",
    "wof:name":"El Canario",
    "wof:placetype":"locality",
    "wof:population":4
},
  "geometry": {"coordinates":[-103.76667,19.12917],"type":"Point"}
}