{
  "type": "Feature",
  "properties": {
    "gn:admin1_code":"25",
    "gn:admin2_code":"15.0",
    "gn:asciiname":"El Taballal",
    "gn:country_code":"MX",
    "gn:dem":71,
    "gn:feature_class":"P",
    "gn:feature_code":"PPL",
    "gn:name":"El Taballal",
    "gn:population":577,
    "gn:timezone":"America/Mazatlan",
    "iso:country":"MX",
    "wof:name":"El Taballal",
    "wof:placetype":"locality",
    "wof:population":577
},
  "geometry": {"coordinates":[-108.04306,25.4125],"type":"Point"}
}