{
  "type": "Feature",
  "properties": {
    "gn:country":"MX",
    "gn:fcode":"PPL",
    "gn:population":0,
    "iso:country":"MX",
    "name:bre_x_preferred":[
        "Aguas Blancas"
    ],
    "name:ceb_x_preferred":[
        "Aguas Blancas"
    ],
    "name:deu_x_preferred":[
        "Aguas Blancas"
    ],
    "name:ita_x_preferred":[
        "Aguas Blancas"
    ],
    "name:nld_x_preferred":[
        "Aguas Blancas"
    ],
    "name:spa_x_preferred":[
        "Aguas Blancas"
    ],
    "name:swe_x_preferred":[
        "Aguas Blancas"
    ],
    "qs_pg:aaroncc":"MX",
    "qs_pg:gn_country":"MX",
    "qs_pg:gn_fcode":"PPL",
    "qs_pg:gn_pop":0,
    "qs_pg:name":"Aguas Blancas",
    "qs_pg:name_adm0":"M\u00e9xico",
    "qs_pg:name_adm1":"Guerrero",
    "qs_pg:photos":1,
    "qs_pg:photos_1k":1,
    "qs_pg:photos_9k":1,
    "qs_pg:photos_9r":1,
    "qs_pg:photos_all":1,
    "qs_pg:photos_sr":1,
    "qs_pg:pop_sr":0,
    "qs_pg:qs_pg_placetype":"neighbourhood",
    "qs_pg:qs_pg_placetype_gp":"Suburb",
    "qs_pg:woe_adm0":23424900,
    "woe:adm0_id":23424900,
    "woe:name_adm0":"M\u00e9xico",
    "woe:name_adm1":"Guerrero",
    "woe:placetype":"Suburb",
    "wof:name":"Aguas Blancas",
    "wof:placetype":"neighbourhood"
},
  "geometry": {"coordinates":[-100.06297000000001,17.03654],"type":"Point"}
}