{
  "type": "Feature",
  "properties": {
    "gn:admin1_code":"4.0",
    "gn:asciiname":"El Zafiro",
    "gn:country_code":"MX",
    "gn:dem":13,
    "gn:feature_class":"P",
    "gn:feature_code":"PPL",
    "gn:name":"El Zafiro",
    "gn:population":0,
    "gn:timezone":"America/Merida",
    "iso:country":"MX",
    "name:spa_x_preferred":[
        "El Zafiro"
    ],
    "wof:name":"El Zafiro",
    "wof:placetype":"locality"
},
  "geometry": {"coordinates":[-91.05485,18.5431],"type":"Point"}
}