{
  "type": "Feature",
  "properties": {
    "gn:admin1_code":"5",
    "gn:admin2_code":"54",
    "gn:asciiname":"Oro Verde",
    "gn:country_code":"MX",
    "gn:dem":20,
    "gn:feature_class":"P",
    "gn:feature_code":"PPL",
    "gn:name":"Oro Verde",
    "gn:population":15,
    "gn:timezone":"America/Mexico_City",
    "iso:country":"MX",
    "name:ceb_x_preferred":[
        "Oro Verde"
    ],
    "name:nld_x_preferred":[
        "Oro Verde"
    ],
    "name:por_x_preferred":[
        "Oro Verde"
    ],
    "name:spa_x_preferred":[
        "Oro Verde"
    ],
    "name:swe_x_preferred":[
        "Oro Verde"
    ],
    "wof:name":"Oro Verde",
    "wof:placetype":"locality",
    "wof:population":15
},
  "geometry": {"coordinates":[-92.45389,14.91944],"type":"Point"}
}