{
  "type": "Feature",
  "properties": {
    "gn:admin1_code":"32",
    "gn:admin2_code":"1.0",
    "gn:asciiname":"La Tiricia",
    "gn:country_code":"MX",
    "gn:dem":1276,
    "gn:feature_class":"P",
    "gn:feature_code":"PPL",
    "gn:name":"La Tiricia",
    "gn:population":256,
    "gn:timezone":"America/Mexico_City",
    "iso:country":"MX",
    "wof:name":"La Tiricia",
    "wof:placetype":"locality",
    "wof:population":256
},
  "geometry": {"coordinates":[-103.09999999999999,21.43861],"type":"Point"}
}