{
  "type": "Feature",
  "properties": {
    "gn:admin1_code":"12",
    "gn:admin2_code":"62.0",
    "gn:asciiname":"El Limon Guadalupe",
    "gn:country_code":"MX",
    "gn:dem":772,
    "gn:feature_class":"P",
    "gn:feature_code":"PPL",
    "gn:name":"El Lim\u00f3n Guadalupe",
    "gn:population":618,
    "gn:timezone":"America/Mexico_City",
    "iso:country":"MX",
    "name:und_x_variant":[
        "El Lim\u00f3n Guadalupe"
    ],
    "wof:name":"El Limon Guadalupe",
    "wof:placetype":"locality",
    "wof:population":618
},
  "geometry": {"coordinates":[-98.23889,17.14194],"type":"Point"}
}