{
  "type": "Feature",
  "properties": {
    "gn:admin1_code":"20",
    "gn:admin2_code":"184.0",
    "gn:asciiname":"La Central",
    "gn:country_code":"MX",
    "gn:dem":45,
    "gn:feature_class":"P",
    "gn:feature_code":"PPL",
    "gn:name":"La Central",
    "gn:population":0,
    "gn:timezone":"America/Mexico_City",
    "iso:country":"MX",
    "name:spa_x_preferred":[
        "La Central"
    ],
    "wof:name":"La Central",
    "wof:placetype":"locality"
},
  "geometry": {"coordinates":[-96.15501,18.02741],"type":"Point"}
}