{
  "type": "Feature",
  "properties": {
    "gn:admin1_code":"32",
    "gn:admin2_code":"49",
    "gn:asciiname":"Garcitas",
    "gn:country_code":"MX",
    "gn:dem":1185,
    "gn:feature_class":"P",
    "gn:feature_code":"PPL",
    "gn:name":"Garcitas",
    "gn:population":11,
    "gn:timezone":"America/Mexico_City",
    "iso:country":"MX",
    "wof:name":"Garcitas",
    "wof:placetype":"locality",
    "wof:population":11
},
  "geometry": {"coordinates":[-104.13388999999999,22.91028],"type":"Point"}
}