{
  "type": "Feature",
  "properties": {
    "gn:admin1_code":"20",
    "gn:admin2_code":"177.0",
    "gn:asciiname":"San Jose del Chilar",
    "gn:country_code":"MX",
    "gn:dem":681,
    "gn:feature_class":"P",
    "gn:feature_code":"PPL",
    "gn:name":"San Jos\u00e9 del Chilar",
    "gn:population":0,
    "gn:timezone":"America/Mexico_City",
    "iso:country":"MX",
    "name:spa_x_preferred":[
        "San Jos\u00e9 del Chilar"
    ],
    "wof:name":"San Jose del Chilar",
    "wof:placetype":"locality"
},
  "geometry": {"coordinates":[-96.93715,17.71141],"type":"Point"}
}