{
  "type": "Feature",
  "properties": {
    "gn:admin1_code":"31",
    "gn:admin2_code":"12.0",
    "gn:asciiname":"Las Palomas",
    "gn:country_code":"MX",
    "gn:dem":17,
    "gn:feature_class":"P",
    "gn:feature_code":"PPL",
    "gn:name":"Las Palomas",
    "gn:population":8,
    "gn:timezone":"America/Merida",
    "iso:country":"MX",
    "wof:name":"Las Palomas",
    "wof:placetype":"locality",
    "wof:population":8
},
  "geometry": {"coordinates":[-88.55139,21.06528],"type":"Point"}
}