{
  "type": "Feature",
  "properties": {
    "gn:admin1_code":"7",
    "gn:admin2_code":"30.0",
    "gn:asciiname":"El Moral",
    "gn:country_code":"MX",
    "gn:dem":1697,
    "gn:feature_class":"P",
    "gn:feature_code":"PPL",
    "gn:name":"El Moral",
    "gn:population":78,
    "gn:timezone":"America/Monterrey",
    "iso:country":"MX",
    "wof:name":"El Moral",
    "wof:placetype":"locality",
    "wof:population":78
},
  "geometry": {"coordinates":[-101.28802,25.34897],"type":"Point"}
}