{
  "type": "Feature",
  "properties": {
    "gn:admin1_code":"13",
    "gn:admin2_code":"1.0",
    "gn:asciiname":"Lagunicatlan",
    "gn:country_code":"MX",
    "gn:dem":2457,
    "gn:feature_class":"P",
    "gn:feature_code":"PPL",
    "gn:name":"Lagunicatl\u00e1n",
    "gn:population":395,
    "gn:timezone":"America/Mexico_City",
    "iso:country":"MX",
    "name:spa_x_preferred":[
        "Lagunicatl\u00e1n"
    ],
    "wof:name":"Lagunicatlan",
    "wof:placetype":"locality",
    "wof:population":395
},
  "geometry": {"coordinates":[-98.47254,20.07922],"type":"Point"}
}