{
  "type": "Feature",
  "properties": {
    "gn:admin1_code":"24.0",
    "gn:admin2_code":"13.0",
    "gn:asciiname":"Crucero las Pitas",
    "gn:country_code":"MX",
    "gn:dem":256,
    "gn:feature_class":"P",
    "gn:feature_code":"PPL",
    "gn:name":"Crucero las Pitas",
    "gn:population":0,
    "gn:timezone":"America/Mexico_City",
    "iso:country":"MX",
    "name:spa_x_preferred":[
        "Crucero las Pitas"
    ],
    "wof:name":"Crucero las Pitas",
    "wof:placetype":"locality"
},
  "geometry": {"coordinates":[-99.05528,22.37135],"type":"Point"}
}