{
  "type": "Feature",
  "properties": {
    "gn:admin1_code":"11.0",
    "gn:admin2_code":"33.0",
    "gn:asciiname":"Vergel de Guadalupe",
    "gn:country_code":"MX",
    "gn:dem":2176,
    "gn:feature_class":"P",
    "gn:feature_code":"PPL",
    "gn:name":"Vergel de Guadalupe",
    "gn:population":0,
    "gn:timezone":"America/Mexico_City",
    "iso:country":"MX",
    "name:spa_x_preferred":[
        "Vergel de Guadalupe"
    ],
    "name:spa_x_variant":[
        "El Vergel de Guadalupe"
    ],
    "name:und_x_variant":[
        "Vergel",
        "El Verjel",
        "El Vergel"
    ],
    "wof:name":"Vergel de Guadalupe",
    "wof:placetype":"locality"
},
  "geometry": {"coordinates":[-100.66677,21.45073],"type":"Point"}
}