{
  "type": "Feature",
  "properties": {
    "gn:admin1_code":"5",
    "gn:admin2_code":"109.0",
    "gn:asciiname":"Fraccion la Union",
    "gn:country_code":"MX",
    "gn:dem":967,
    "gn:feature_class":"P",
    "gn:feature_code":"PPL",
    "gn:name":"Fracci\u00f3n la Uni\u00f3n",
    "gn:population":65,
    "gn:timezone":"America/Mexico_City",
    "iso:country":"MX",
    "name:und_x_variant":[
        "Fracci\u00f3n la Uni\u00f3n"
    ],
    "wof:name":"Fraccion la Union",
    "wof:placetype":"locality",
    "wof:population":65
},
  "geometry": {"coordinates":[-92.32472,17.19852],"type":"Point"}
}