{
  "type": "Feature",
  "properties": {
    "gn:admin1_code":"21",
    "gn:admin2_code":"10.0",
    "gn:asciiname":"Vista Hermosa Zayulapa",
    "gn:country_code":"MX",
    "gn:dem":2607,
    "gn:feature_class":"P",
    "gn:feature_code":"PPL",
    "gn:name":"Vista Hermosa Zayulapa",
    "gn:population":0,
    "gn:timezone":"America/Mexico_City",
    "iso:country":"MX",
    "name:spa_x_preferred":[
        "Vista Hermosa Zayulapa"
    ],
    "name:und_x_variant":[
        "Vista Hermosa Zayulapan"
    ],
    "wof:name":"Vista Hermosa Zayulapa",
    "wof:placetype":"locality"
},
  "geometry": {"coordinates":[-97.09828,18.4311],"type":"Point"}
}