{
  "type": "Feature",
  "properties": {
    "gn:admin1_code":"6",
    "gn:admin2_code":"11.0",
    "gn:asciiname":"Rancho Canon Obscuro",
    "gn:country_code":"MX",
    "gn:dem":1486,
    "gn:feature_class":"P",
    "gn:feature_code":"PPL",
    "gn:name":"Rancho Ca\u00f1\u00f3n Obscuro",
    "gn:population":6,
    "gn:timezone":"America/Chihuahua",
    "iso:country":"MX",
    "name:und_x_variant":[
        "Rancho Ca\u00f1\u00f3n Obscuro"
    ],
    "wof:name":"Rancho Canon Obscuro",
    "wof:placetype":"locality",
    "wof:population":6
},
  "geometry": {"coordinates":[-104.38433000000001,27.85578],"type":"Point"}
}