{
  "type": "Feature",
  "properties": {
    "gn:admin1_code":"14",
    "gn:admin2_code":"106",
    "gn:asciiname":"La Piedra",
    "gn:country_code":"MX",
    "gn:dem":769,
    "gn:feature_class":"P",
    "gn:feature_code":"PPL",
    "gn:name":"La Piedra",
    "gn:population":12,
    "gn:timezone":"America/Mexico_City",
    "iso:country":"MX",
    "wof:name":"La Piedra",
    "wof:placetype":"locality",
    "wof:population":12
},
  "geometry": {"coordinates":[-104.03667,19.62833],"type":"Point"}
}