{
  "type": "Feature",
  "properties": {
    "gn:admin1_code":"31",
    "gn:admin2_code":"19.0",
    "gn:asciiname":"Mizal",
    "gn:country_code":"MX",
    "gn:dem":22,
    "gn:feature_class":"P",
    "gn:feature_code":"PPL",
    "gn:name":"Mizal",
    "gn:population":0,
    "gn:timezone":"America/Cancun",
    "iso:country":"MX",
    "name:spa_x_preferred":[
        "Mizal"
    ],
    "wof:name":"Mizal",
    "wof:placetype":"locality"
},
  "geometry": {"coordinates":[-87.88649000000002,20.56183],"type":"Point"}
}