{
  "type": "Feature",
  "properties": {
    "gn:country":"MX",
    "gn:fcode":"PPL",
    "gn:population":4384,
    "iso:country":"MX",
    "name:und_x_variant":[
        "Ciudad Nueva Guerrero"
    ],
    "qs_pg:aaroncc":"MX",
    "qs_pg:gn_country":"MX",
    "qs_pg:gn_fcode":"PPL",
    "qs_pg:gn_pop":4384,
    "qs_pg:name":"Nueva Ciudad Guerrero Centro",
    "qs_pg:name_adm0":"M\u00e9xico",
    "qs_pg:name_adm1":"Tamaulipas",
    "qs_pg:photos_9r":0,
    "qs_pg:photos_sr":0,
    "qs_pg:pop_sr":4,
    "qs_pg:qs_pg_placetype":"neighbourhood",
    "qs_pg:qs_pg_placetype_gp":"Suburb",
    "qs_pg:woe_adm0":23424900,
    "woe:adm0_id":23424900,
    "woe:name_adm0":"M\u00e9xico",
    "woe:name_adm1":"Tamaulipas",
    "woe:placetype":"Suburb",
    "wof:name":"Nueva Ciudad Guerrero Centro",
    "wof:placetype":"neighbourhood",
    "wof:population":4384
},
  "geometry": {"coordinates":[-99.22801,26.56281],"type":"Point"}
}