{
  "type": "Feature",
  "properties": {
    "gn:admin1_code":"24",
    "gn:admin2_code":"46",
    "gn:asciiname":"El Pastor",
    "gn:country_code":"MX",
    "gn:dem":2168,
    "gn:feature_class":"P",
    "gn:feature_code":"PPL",
    "gn:name":"El Pastor",
    "gn:population":11,
    "gn:timezone":"America/Mexico_City",
    "iso:country":"MX",
    "wof:name":"El Pastor",
    "wof:placetype":"locality",
    "wof:population":11
},
  "geometry": {"coordinates":[-101.27333,21.9225],"type":"Point"}
}