{
  "type": "Feature",
  "properties": {
    "gn:admin1_code":"10",
    "gn:admin2_code":"26.0",
    "gn:asciiname":"La Tableta",
    "gn:country_code":"MX",
    "gn:dem":2845,
    "gn:feature_class":"P",
    "gn:feature_code":"PPL",
    "gn:name":"La Tableta",
    "gn:population":6,
    "gn:timezone":"America/Monterrey",
    "iso:country":"MX",
    "wof:name":"La Tableta",
    "wof:placetype":"locality",
    "wof:population":6
},
  "geometry": {"coordinates":[-105.76336000000001,24.10472],"type":"Point"}
}