{
  "type": "Feature",
  "properties": {
    "gn:admin1_code":"6",
    "gn:admin2_code":"9.0",
    "gn:asciiname":"Menerichi",
    "gn:country_code":"MX",
    "gn:dem":2413,
    "gn:feature_class":"P",
    "gn:feature_code":"PPL",
    "gn:name":"Menerichi",
    "gn:population":0,
    "gn:timezone":"America/Chihuahua",
    "iso:country":"MX",
    "name:spa_x_preferred":[
        "Rec\u00f3huata"
    ],
    "name:spa_x_variant":[
        "Menerichi"
    ],
    "wof:name":"Menerichi",
    "wof:placetype":"locality"
},
  "geometry": {"coordinates":[-107.71711999999999,27.72221],"type":"Point"}
}