{
  "type": "Feature",
  "properties": {
    "gn:admin1_code":"25",
    "gn:admin2_code":"17.0",
    "gn:asciiname":"Chimon",
    "gn:country_code":"MX",
    "gn:dem":1452,
    "gn:feature_class":"P",
    "gn:feature_code":"PPL",
    "gn:name":"Chim\u00f3n",
    "gn:population":0,
    "gn:timezone":"America/Mazatlan",
    "iso:country":"MX",
    "name:spa_x_preferred":[
        "Chim\u00f3n"
    ],
    "wof:name":"Chimon",
    "wof:placetype":"locality"
},
  "geometry": {"coordinates":[-107.85628,26.22236],"type":"Point"}
}