{
  "type": "Feature",
  "properties": {
    "gn:admin1_code":"18.0",
    "gn:admin2_code":"10.0",
    "gn:asciiname":"Lazaro Cardenas",
    "gn:country_code":"MX",
    "gn:dem":57,
    "gn:feature_class":"P",
    "gn:feature_code":"PPL",
    "gn:name":"L\u00e1zaro C\u00e1rdenas",
    "gn:population":24,
    "gn:timezone":"America/Mazatlan",
    "iso:country":"MX",
    "wof:name":"Lazaro Cardenas",
    "wof:placetype":"locality",
    "wof:population":24
},
  "geometry": {"coordinates":[-105.2531,22.20813],"type":"Point"}
}