{
  "type": "Feature",
  "properties": {
    "gn:admin1_code":"6.0",
    "gn:admin2_code":"29.0",
    "gn:asciiname":"Ojo del Buey",
    "gn:country_code":"MX",
    "gn:dem":2733,
    "gn:feature_class":"P",
    "gn:feature_code":"PPL",
    "gn:name":"Ojo del Buey",
    "gn:population":0,
    "gn:timezone":"America/Chihuahua",
    "iso:country":"MX",
    "name:spa_x_preferred":[
        "Ojo del Buey"
    ],
    "wof:name":"Ojo del Buey",
    "wof:placetype":"locality"
},
  "geometry": {"coordinates":[-107.01092,26.04977],"type":"Point"}
}