{
  "type": "Feature",
  "properties": {
    "gn:admin1_code":"32",
    "gn:admin2_code":"49.0",
    "gn:asciiname":"Colonia Progreso (La Cadena)",
    "gn:country_code":"MX",
    "gn:dem":2052,
    "gn:feature_class":"P",
    "gn:feature_code":"PPL",
    "gn:name":"Colonia Progreso (La Cadena)",
    "gn:population":94,
    "gn:timezone":"America/Mexico_City",
    "iso:country":"MX",
    "wof:name":"Colonia Progreso (La Cadena)",
    "wof:placetype":"locality",
    "wof:population":94
},
  "geometry": {"coordinates":[-103.47667,22.94806],"type":"Point"}
}