{
  "type": "Feature",
  "properties": {
    "gn:admin1_code":"10",
    "gn:admin2_code":"35.0",
    "gn:asciiname":"El Toro",
    "gn:country_code":"MX",
    "gn:dem":2445,
    "gn:feature_class":"P",
    "gn:feature_code":"PPL",
    "gn:name":"El Toro",
    "gn:population":7,
    "gn:timezone":"America/Monterrey",
    "iso:country":"MX",
    "wof:name":"El Toro",
    "wof:placetype":"locality",
    "wof:population":7
},
  "geometry": {"coordinates":[-106.06291,25.51266],"type":"Point"}
}