{
  "type": "Feature",
  "properties": {
    "gn:admin1_code":"6.0",
    "gn:admin2_code":"65.0",
    "gn:asciiname":"El Tejaban",
    "gn:country_code":"MX",
    "gn:dem":1311,
    "gn:feature_class":"P",
    "gn:feature_code":"PPL",
    "gn:name":"El Tejab\u00e1n",
    "gn:population":0,
    "gn:timezone":"America/Chihuahua",
    "iso:country":"MX",
    "name:spa_x_preferred":[
        "El Tejab\u00e1n"
    ],
    "wof:name":"El Tejaban",
    "wof:placetype":"locality"
},
  "geometry": {"coordinates":[-108.00964999999999,27.0965],"type":"Point"}
}