{
  "type": "Feature",
  "properties": {
    "gn:admin1_code":"22",
    "gn:admin2_code":"15.0",
    "gn:asciiname":"Puerto de la Garita",
    "gn:country_code":"MX",
    "gn:dem":838,
    "gn:feature_class":"P",
    "gn:feature_code":"PPL",
    "gn:name":"Puerto de la Garita",
    "gn:population":72,
    "gn:timezone":"America/Mexico_City",
    "iso:country":"MX",
    "wof:name":"Puerto de la Garita",
    "wof:placetype":"locality",
    "wof:population":72
},
  "geometry": {"coordinates":[-99.47417,21.04917],"type":"Point"}
}