{
  "type": "Feature",
  "properties": {
    "gn:admin1_code":"16",
    "gn:admin2_code":"88.0",
    "gn:asciiname":"Fraccionamiento la Cantera",
    "gn:country_code":"MX",
    "gn:dem":1906,
    "gn:feature_class":"P",
    "gn:feature_code":"PPL",
    "gn:name":"Fraccionamiento la Cantera",
    "gn:population":775,
    "gn:timezone":"America/Mexico_City",
    "iso:country":"MX",
    "wof:name":"Fraccionamiento la Cantera",
    "wof:placetype":"locality",
    "wof:population":775
},
  "geometry": {"coordinates":[-101.16194,19.76917000000001],"type":"Point"}
}