{
  "type": "Feature",
  "properties": {
    "gn:admin1_code":"30",
    "gn:admin2_code":"70.0",
    "gn:asciiname":"Anselmo Saavedra",
    "gn:country_code":"MX",
    "gn:dem":49,
    "gn:feature_class":"P",
    "gn:feature_code":"PPL",
    "gn:name":"Anselmo Saavedra",
    "gn:population":8,
    "gn:timezone":"America/Mexico_City",
    "iso:country":"MX",
    "wof:name":"Anselmo Saavedra",
    "wof:placetype":"locality",
    "wof:population":8
},
  "geometry": {"coordinates":[-94.55417,17.45972],"type":"Point"}
}