{
  "type": "Feature",
  "properties": {
    "gn:admin1_code":"19",
    "gn:admin2_code":"44",
    "gn:asciiname":"Los Morton",
    "gn:country_code":"MX",
    "gn:dem":289,
    "gn:feature_class":"P",
    "gn:feature_code":"PPL",
    "gn:name":"Los Morton",
    "gn:population":10,
    "gn:timezone":"America/Monterrey",
    "iso:country":"MX",
    "wof:name":"Los Morton",
    "wof:placetype":"locality",
    "wof:population":10
},
  "geometry": {"coordinates":[-100.13949,26.49226],"type":"Point"}
}