{
  "type": "Feature",
  "properties": {
    "gn:admin1_code":"30",
    "gn:admin2_code":"184",
    "gn:asciiname":"Rojaxtla",
    "gn:country_code":"MX",
    "gn:dem":2213,
    "gn:feature_class":"P",
    "gn:feature_code":"PPL",
    "gn:name":"Rojaxtla",
    "gn:population":32,
    "gn:timezone":"America/Mexico_City",
    "iso:country":"MX",
    "wof:name":"Rojaxtla",
    "wof:placetype":"locality",
    "wof:population":32
},
  "geometry": {"coordinates":[-97.11556,18.60528],"type":"Point"}
}