{
  "type": "Feature",
  "properties": {
    "gn:admin1_code":"11",
    "gn:admin2_code":"39.0",
    "gn:asciiname":"Puerto Ferrer",
    "gn:country_code":"MX",
    "gn:dem":1901,
    "gn:feature_class":"P",
    "gn:feature_code":"PPL",
    "gn:name":"Puerto Ferrer",
    "gn:population":0,
    "gn:timezone":"America/Mexico_City",
    "iso:country":"MX",
    "name:und_x_variant":[
        "Puerto de Ferrer"
    ],
    "wof:name":"Puerto Ferrer",
    "wof:placetype":"locality"
},
  "geometry": {"coordinates":[-100.73746,20.17848],"type":"Point"}
}