{
  "type": "Feature",
  "properties": {
    "gn:admin1_code":"26",
    "gn:admin2_code":"33.0",
    "gn:asciiname":"Pozo Dulce",
    "gn:country_code":"MX",
    "gn:dem":9,
    "gn:feature_class":"P",
    "gn:feature_code":"PPL",
    "gn:name":"Pozo Dulce",
    "gn:population":0,
    "gn:timezone":"America/Hermosillo",
    "iso:country":"MX",
    "name:spa_x_preferred":[
        "Pozo Dulce"
    ],
    "wof:name":"Pozo Dulce",
    "wof:placetype":"locality"
},
  "geometry": {"coordinates":[-109.7535,26.84506],"type":"Point"}
}