{
  "type": "Feature",
  "properties": {
    "gn:admin1_code":"5",
    "gn:admin2_code":"59.0",
    "gn:asciiname":"San Antonio el Cipres",
    "gn:country_code":"MX",
    "gn:dem":1387,
    "gn:feature_class":"P",
    "gn:feature_code":"PPL",
    "gn:name":"San Antonio el Cipr\u00e9s",
    "gn:population":8,
    "gn:timezone":"America/Mexico_City",
    "iso:country":"MX",
    "name:und_x_variant":[
        "San Antonio el Cipr\u00e9s"
    ],
    "wof:name":"San Antonio el Cipres",
    "wof:placetype":"locality",
    "wof:population":8
},
  "geometry": {"coordinates":[-92.21361,16.84417],"type":"Point"}
}