{
  "type": "Feature",
  "properties": {
    "gn:admin1_code":"26",
    "gn:admin2_code":"47.0",
    "gn:asciiname":"San Emeterio",
    "gn:country_code":"MX",
    "gn:dem":746,
    "gn:feature_class":"P",
    "gn:feature_code":"PPL",
    "gn:name":"San Emeterio",
    "gn:population":0,
    "gn:timezone":"America/Hermosillo",
    "iso:country":"MX",
    "name:spa_x_preferred":[
        "San Emeterio"
    ],
    "wof:name":"San Emeterio",
    "wof:placetype":"locality"
},
  "geometry": {"coordinates":[-111.52762,29.8659],"type":"Point"}
}