{
  "type": "Feature",
  "properties": {
    "gn:admin1_code":"31",
    "gn:admin2_code":"102",
    "gn:asciiname":"Santa Rosa",
    "gn:country_code":"MX",
    "gn:dem":27,
    "gn:feature_class":"P",
    "gn:feature_code":"PPL",
    "gn:name":"Santa Rosa",
    "gn:population":40,
    "gn:timezone":"America/Merida",
    "iso:country":"MX",
    "wof:name":"Santa Rosa",
    "wof:placetype":"locality",
    "wof:population":40
},
  "geometry": {"coordinates":[-88.09583000000001,20.49278],"type":"Point"}
}