{
  "type": "Feature",
  "properties": {
    "gn:admin1_code":"17",
    "gn:admin2_code":"24.0",
    "gn:asciiname":"Bonifacio Garcia",
    "gn:country_code":"MX",
    "gn:dem":970,
    "gn:feature_class":"P",
    "gn:feature_code":"PPL",
    "gn:name":"Bonifacio Garc\u00eda",
    "gn:population":0,
    "gn:timezone":"America/Mexico_City",
    "iso:country":"MX",
    "name:und_x_variant":[
        "Bonifacio Garc\u00eda",
        "Colonia Alejandra"
    ],
    "wof:name":"Bonifacio Garcia",
    "wof:placetype":"locality"
},
  "geometry": {"coordinates":[-99.12011,18.71786],"type":"Point"}
}