{
  "type": "Feature",
  "properties": {
    "gn:admin1_code":"12",
    "gn:admin2_code":"65",
    "gn:asciiname":"Barrio la Villa",
    "gn:country_code":"MX",
    "gn:dem":1190,
    "gn:feature_class":"P",
    "gn:feature_code":"PPL",
    "gn:name":"Barrio la Villa",
    "gn:population":17,
    "gn:timezone":"America/Mexico_City",
    "iso:country":"MX",
    "wof:name":"Barrio la Villa",
    "wof:placetype":"locality",
    "wof:population":17
},
  "geometry": {"coordinates":[-98.36295,17.58049],"type":"Point"}
}