{
  "type": "Feature",
  "properties": {
    "gn:admin1_code":"26",
    "gn:admin2_code":"30.0",
    "gn:asciiname":"La Tuna",
    "gn:country_code":"MX",
    "gn:dem":130,
    "gn:feature_class":"P",
    "gn:feature_code":"PPL",
    "gn:name":"La Tuna",
    "gn:population":0,
    "gn:timezone":"America/Hermosillo",
    "iso:country":"MX",
    "name:spa_x_preferred":[
        "La Tuna"
    ],
    "wof:name":"La Tuna",
    "wof:placetype":"locality"
},
  "geometry": {"coordinates":[-111.16162,28.91549],"type":"Point"}
}