{
  "type": "Feature",
  "properties": {
    "gn:admin1_code":"27",
    "gn:admin2_code":"7.0",
    "gn:asciiname":"Loma Bonita",
    "gn:country_code":"MX",
    "gn:dem":44,
    "gn:feature_class":"P",
    "gn:feature_code":"PPL",
    "gn:name":"Loma Bonita",
    "gn:population":5,
    "gn:timezone":"America/Mexico_City",
    "iso:country":"MX",
    "name:epo_x_preferred":[
        "Loma Bonita"
    ],
    "name:eus_x_preferred":[
        "Loma Bonita"
    ],
    "name:hun_x_preferred":[
        "Loma Bonita"
    ],
    "name:ita_x_preferred":[
        "Loma Bonita"
    ],
    "name:rus_x_preferred":[
        "\u041b\u043e\u043c\u0430-\u0411\u043e\u043d\u0438\u0442\u0430"
    ],
    "name:sco_x_preferred":[
        "Loma Bonita"
    ],
    "name:spa_x_preferred":[
        "Loma Bonita"
    ],
    "name:srp_x_preferred":[
        "\u041e\u043f\u0448\u0442\u0438\u043d\u0430 \u041b\u043e\u043c\u0430 \u0411\u043e\u043d\u0438\u0442\u0430"
    ],
    "name:vie_x_preferred":[
        "Loma Bonita"
    ],
    "wof:name":"Loma Bonita",
    "wof:placetype":"locality",
    "wof:population":5
},
  "geometry": {"coordinates":[-91.61667,17.57556],"type":"Point"}
}