{
  "type": "Feature",
  "properties": {
    "gn:admin1_code":"12",
    "gn:admin2_code":"28.0",
    "gn:asciiname":"Amiltepec",
    "gn:country_code":"MX",
    "gn:dem":2330,
    "gn:feature_class":"P",
    "gn:feature_code":"PPL",
    "gn:name":"Amiltepec",
    "gn:population":0,
    "gn:timezone":"America/Mexico_City",
    "iso:country":"MX",
    "name:spa_x_preferred":[
        "Amiltepec"
    ],
    "wof:name":"Amiltepec",
    "wof:placetype":"locality"
},
  "geometry": {"coordinates":[-98.90900999999999,17.48719],"type":"Point"}
}