{
  "type": "Feature",
  "properties": {
    "gn:admin1_code":"5",
    "gn:admin2_code":"23.0",
    "gn:asciiname":"Tilil Centro",
    "gn:country_code":"MX",
    "gn:dem":2459,
    "gn:feature_class":"P",
    "gn:feature_code":"PPL",
    "gn:name":"Tilil Centro",
    "gn:population":341,
    "gn:timezone":"America/Mexico_City",
    "iso:country":"MX",
    "wof:name":"Tilil Centro",
    "wof:placetype":"locality",
    "wof:population":341
},
  "geometry": {"coordinates":[-92.72917,16.8025],"type":"Point"}
}