{
  "type": "Feature",
  "properties": {
    "gn:admin1_code":"11",
    "gn:admin2_code":"20.0",
    "gn:asciiname":"Granja Aracely (Cristela)",
    "gn:country_code":"MX",
    "gn:dem":2041,
    "gn:feature_class":"P",
    "gn:feature_code":"PPL",
    "gn:name":"Granja Aracely (Cristela)",
    "gn:population":8,
    "gn:timezone":"America/Mexico_City",
    "iso:country":"MX",
    "wof:name":"Granja Aracely (Cristela)",
    "wof:placetype":"locality",
    "wof:population":8
},
  "geometry": {"coordinates":[-101.75082999999999,21.19583],"type":"Point"}
}