{
  "type": "Feature",
  "properties": {
    "gn:admin1_code":"30",
    "gn:admin2_code":"126.0",
    "gn:asciiname":"Mata Mateo",
    "gn:country_code":"MX",
    "gn:dem":184,
    "gn:feature_class":"P",
    "gn:feature_code":"PPL",
    "gn:name":"Mata Mateo",
    "gn:population":96,
    "gn:timezone":"America/Mexico_City",
    "iso:country":"MX",
    "wof:name":"Mata Mateo",
    "wof:placetype":"locality",
    "wof:population":96
},
  "geometry": {"coordinates":[-96.50167,19.27333],"type":"Point"}
}