{
  "type": "Feature",
  "properties": {
    "gn:admin1_code":"15",
    "gn:admin2_code":"34.0",
    "gn:asciiname":"San Marcos Tecomaxusco",
    "gn:cc2":"MX",
    "gn:country_code":"MX",
    "gn:dem":2472,
    "gn:feature_class":"P",
    "gn:feature_code":"PPL",
    "gn:name":"San Marcos Tecomaxusco",
    "gn:population":1022,
    "gn:timezone":"America/Mexico_City",
    "iso:country":"MX",
    "name:und_x_variant":[
        "Tecomaxuxco",
        "Tecomaxusco"
    ],
    "wof:name":"San Marcos Tecomaxusco",
    "wof:placetype":"locality",
    "wof:population":1022
},
  "geometry": {"coordinates":[-98.76035,18.98152],"type":"Point"}
}