{
  "type": "Feature",
  "properties": {
    "gn:admin1_code":"14",
    "gn:admin2_code":"8",
    "gn:asciiname":"El Ocote de Abajo",
    "gn:country_code":"MX",
    "gn:dem":1987,
    "gn:feature_class":"P",
    "gn:feature_code":"PPL",
    "gn:name":"El Ocote de Abajo",
    "gn:population":20,
    "gn:timezone":"America/Mexico_City",
    "iso:country":"MX",
    "wof:name":"El Ocote de Abajo",
    "wof:placetype":"locality",
    "wof:population":20
},
  "geometry": {"coordinates":[-102.36722,20.66889],"type":"Point"}
}