{
  "type": "Feature",
  "properties": {
    "gn:admin1_code":"5",
    "gn:admin2_code":"61.0",
    "gn:asciiname":"Flor de la Industria",
    "gn:country_code":"MX",
    "gn:dem":800,
    "gn:feature_class":"P",
    "gn:feature_code":"PPL",
    "gn:name":"Flor de la Industria",
    "gn:population":8,
    "gn:timezone":"America/Mexico_City",
    "iso:country":"MX",
    "wof:name":"Flor de la Industria",
    "wof:placetype":"locality",
    "wof:population":8
},
  "geometry": {"coordinates":[-93.44777999999999,16.56861],"type":"Point"}
}