{
  "type": "Feature",
  "properties": {
    "gn:admin1_code":"19",
    "gn:admin2_code":"13.0",
    "gn:asciiname":"Retama",
    "gn:country_code":"MX",
    "gn:dem":190,
    "gn:feature_class":"P",
    "gn:feature_code":"PPL",
    "gn:name":"Retama",
    "gn:population":0,
    "gn:timezone":"America/Monterrey",
    "iso:country":"MX",
    "name:ara_x_preferred":[
        "\u0631\u062a\u0645"
    ],
    "name:cat_x_preferred":[
        "Retama"
    ],
    "name:ceb_x_preferred":[
        "Retama"
    ],
    "name:fra_x_preferred":[
        "Retama"
    ],
    "name:heb_x_preferred":[
        "\u05e8\u05d5\u05ea\u05dd"
    ],
    "name:ind_x_preferred":[
        "Retama"
    ],
    "name:ita_x_preferred":[
        "Retama"
    ],
    "name:por_x_preferred":[
        "Retama"
    ],
    "name:spa_x_preferred":[
        "Retama"
    ],
    "name:swe_x_preferred":[
        "Retama"
    ],
    "name:und_x_variant":[
        "La Retama"
    ],
    "name:vie_x_preferred":[
        "Retama"
    ],
    "name:war_x_preferred":[
        "Retama"
    ],
    "wof:name":"Retama",
    "wof:placetype":"locality"
},
  "geometry": {"coordinates":[-99.14333000000001,25.49911],"type":"Point"}
}