{
  "type": "Feature",
  "properties": {
    "gn:admin1_code":"6.0",
    "gn:admin2_code":"20.0",
    "gn:asciiname":"El Zapote de Rascon",
    "gn:country_code":"MX",
    "gn:dem":1567,
    "gn:feature_class":"P",
    "gn:feature_code":"PPL",
    "gn:name":"El Zapote de Rasc\u00f3n",
    "gn:population":0,
    "gn:timezone":"America/Chihuahua",
    "iso:country":"MX",
    "name:spa_x_preferred":[
        "El Zapote de Rasc\u00f3n"
    ],
    "wof:name":"El Zapote de Rascon",
    "wof:placetype":"locality"
},
  "geometry": {"coordinates":[-108.49236999999999,27.68812],"type":"Point"}
}