{
  "type": "Feature",
  "properties": {
    "gn:admin1_code":"16.0",
    "gn:admin2_code":"92.0",
    "gn:asciiname":"Las Anonas",
    "gn:country_code":"MX",
    "gn:dem":614,
    "gn:feature_class":"P",
    "gn:feature_code":"PPL",
    "gn:name":"Las Anonas",
    "gn:population":0,
    "gn:timezone":"America/Mexico_City",
    "iso:country":"MX",
    "name:spa_x_preferred":[
        "Las Anonas"
    ],
    "wof:name":"Las Anonas",
    "wof:placetype":"locality"
},
  "geometry": {"coordinates":[-100.78055000000001,19.14853],"type":"Point"}
}