{
  "type": "Feature",
  "properties": {
    "gn:admin1_code":"5",
    "gn:admin2_code":"61",
    "gn:asciiname":"Las Cruces (Rincon Novillo)",
    "gn:country_code":"MX",
    "gn:dem":803,
    "gn:feature_class":"P",
    "gn:feature_code":"PPL",
    "gn:name":"Las Cruces (Rinc\u00f3n Novillo)",
    "gn:population":20,
    "gn:timezone":"America/Mexico_City",
    "iso:country":"MX",
    "name:und_x_variant":[
        "Las Cruces (Rinc\u00f3n Novillo)"
    ],
    "wof:name":"Las Cruces (Rincon Novillo)",
    "wof:placetype":"locality",
    "wof:population":20
},
  "geometry": {"coordinates":[-93.32138999999999,16.65194],"type":"Point"}
}