{
  "type": "Feature",
  "properties": {
    "gn:admin1_code":"6",
    "gn:admin2_code":"7.0",
    "gn:asciiname":"Valverde",
    "gn:country_code":"MX",
    "gn:dem":2370,
    "gn:feature_class":"P",
    "gn:feature_code":"PPL",
    "gn:name":"Valverde",
    "gn:population":0,
    "gn:timezone":"America/Chihuahua",
    "iso:country":"MX",
    "name:spa_x_preferred":[
        "Valverde"
    ],
    "wof:name":"Valverde",
    "wof:placetype":"locality"
},
  "geometry": {"coordinates":[-106.80069,26.90432],"type":"Point"}
}