{
  "type": "Feature",
  "properties": {
    "gn:admin1_code":"20",
    "gn:admin2_code":"336",
    "gn:asciiname":"Rancho Bobo",
    "gn:country_code":"MX",
    "gn:dem":876,
    "gn:feature_class":"P",
    "gn:feature_code":"PPL",
    "gn:name":"Rancho Bobo",
    "gn:population":47,
    "gn:timezone":"America/Mexico_City",
    "iso:country":"MX",
    "wof:name":"Rancho Bobo",
    "wof:placetype":"locality",
    "wof:population":47
},
  "geometry": {"coordinates":[-96.42639,17.63278],"type":"Point"}
}