{
  "type": "Feature",
  "properties": {
    "gn:admin1_code":"5.0",
    "gn:admin2_code":"52.0",
    "gn:asciiname":"Penasco",
    "gn:country_code":"MX",
    "gn:dem":1243,
    "gn:feature_class":"P",
    "gn:feature_code":"PPL",
    "gn:name":"Pe\u00f1asco",
    "gn:population":0,
    "gn:timezone":"America/Mexico_City",
    "iso:country":"MX",
    "name:spa_x_preferred":[
        "Pe\u00f1asco"
    ],
    "wof:name":"Penasco",
    "wof:placetype":"locality"
},
  "geometry": {"coordinates":[-91.70471000000001,16.34389],"type":"Point"}
}