{
  "type": "Feature",
  "properties": {
    "gn:admin1_code":"5.0",
    "gn:asciiname":"Juan de Dios",
    "gn:country_code":"MX",
    "gn:dem":237,
    "gn:feature_class":"P",
    "gn:feature_code":"PPL",
    "gn:name":"Juan de Dios",
    "gn:population":0,
    "gn:timezone":"America/Mexico_City",
    "iso:country":"MX",
    "name:spa_x_preferred":[
        "Juan de Dios"
    ],
    "wof:name":"Juan de Dios",
    "wof:placetype":"locality"
},
  "geometry": {"coordinates":[-93.17538,15.76904],"type":"Point"}
}