{
  "type": "Feature",
  "properties": {
    "gn:admin1_code":"11.0",
    "gn:admin2_code":"14.0",
    "gn:asciiname":"La Colorada",
    "gn:cc2":"MX",
    "gn:country_code":"MX",
    "gn:dem":1996,
    "gn:feature_class":"P",
    "gn:feature_code":"PPL",
    "gn:name":"La Colorada",
    "gn:population":664,
    "gn:timezone":"America/Mexico_City",
    "iso:country":"MX",
    "name:und_x_variant":[
        "Colorado",
        "Colorada",
        "El Colorada"
    ],
    "wof:name":"La Colorada",
    "wof:placetype":"locality",
    "wof:population":664
},
  "geometry": {"coordinates":[-100.85583,21.29556],"type":"Point"}
}