{
  "type": "Feature",
  "properties": {
    "gn:admin1_code":"10",
    "gn:admin2_code":"5.0",
    "gn:asciiname":"Primitivo Ochoa",
    "gn:country_code":"MX",
    "gn:dem":1860,
    "gn:feature_class":"P",
    "gn:feature_code":"PPL",
    "gn:name":"Primitivo Ochoa",
    "gn:population":8,
    "gn:timezone":"America/Monterrey",
    "iso:country":"MX",
    "wof:name":"Primitivo Ochoa",
    "wof:placetype":"locality",
    "wof:population":8
},
  "geometry": {"coordinates":[-104.56528,24.1075],"type":"Point"}
}