{
  "type": "Feature",
  "properties": {
    "gn:admin1_code":"30",
    "gn:admin2_code":"172.0",
    "gn:asciiname":"Villa Alta",
    "gn:country_code":"MX",
    "gn:dem":28,
    "gn:feature_class":"P",
    "gn:feature_code":"PPL",
    "gn:name":"Villa Alta",
    "gn:population":0,
    "gn:timezone":"America/Mexico_City",
    "iso:country":"MX",
    "name:spa_x_preferred":[
        "Villa Alta"
    ],
    "name:spa_x_variant":[
        "Villalta"
    ],
    "wof:name":"Villa Alta",
    "wof:placetype":"locality"
},
  "geometry": {"coordinates":[-94.75474,17.60014],"type":"Point"}
}