{
  "type": "Feature",
  "properties": {
    "gn:admin1_code":"30",
    "gn:admin2_code":"67.0",
    "gn:asciiname":"El Crucero",
    "gn:country_code":"MX",
    "gn:dem":737,
    "gn:feature_class":"P",
    "gn:feature_code":"PPL",
    "gn:name":"El Crucero",
    "gn:population":508,
    "gn:timezone":"America/Mexico_City",
    "iso:country":"MX",
    "wof:name":"El Crucero",
    "wof:placetype":"locality",
    "wof:population":508
},
  "geometry": {"coordinates":[-97.70139,20.21806],"type":"Point"}
}