{
  "type": "Feature",
  "properties": {
    "gn:admin1_code":"21",
    "gn:admin2_code":"154.0",
    "gn:asciiname":"Rancho el Laurel (El Laurel)",
    "gn:country_code":"MX",
    "gn:dem":2059,
    "gn:feature_class":"P",
    "gn:feature_code":"PPL",
    "gn:name":"Rancho el Laurel (El Laurel)",
    "gn:population":266,
    "gn:timezone":"America/Mexico_City",
    "iso:country":"MX",
    "wof:name":"Rancho el Laurel (El Laurel)",
    "wof:placetype":"locality",
    "wof:population":266
},
  "geometry": {"coordinates":[-97.71222,18.86167],"type":"Point"}
}