{
  "type": "Feature",
  "properties": {
    "gn:admin1_code":"20",
    "gn:admin2_code":"450",
    "gn:asciiname":"Llano Metate",
    "gn:country_code":"MX",
    "gn:dem":1273,
    "gn:feature_class":"P",
    "gn:feature_code":"PPL",
    "gn:name":"Llano Metate",
    "gn:population":34,
    "gn:timezone":"America/Mexico_City",
    "iso:country":"MX",
    "wof:name":"Llano Metate",
    "wof:placetype":"locality",
    "wof:population":34
},
  "geometry": {"coordinates":[-97.46528000000001,16.61056],"type":"Point"}
}