{
  "type": "Feature",
  "properties": {
    "gn:admin1_code":"30",
    "gn:admin2_code":"166.0",
    "gn:asciiname":"El Patio",
    "gn:country_code":"MX",
    "gn:dem":1519,
    "gn:feature_class":"P",
    "gn:feature_code":"PPL",
    "gn:name":"El Patio",
    "gn:population":0,
    "gn:timezone":"America/Mexico_City",
    "iso:country":"MX",
    "name:spa_x_preferred":[
        "El Patio"
    ],
    "wof:name":"El Patio",
    "wof:placetype":"locality"
},
  "geometry": {"coordinates":[-96.76962,19.67227],"type":"Point"}
}