{
  "type": "Feature",
  "properties": {
    "gn:admin1_code":"6.0",
    "gn:asciiname":"El Alto de los Lirios",
    "gn:country_code":"MX",
    "gn:dem":2934,
    "gn:feature_class":"P",
    "gn:feature_code":"PPL",
    "gn:name":"El Alto de los Lirios",
    "gn:population":0,
    "gn:timezone":"America/Monterrey",
    "iso:country":"MX",
    "name:spa_x_preferred":[
        "El Alto de los Lirios"
    ],
    "wof:name":"El Alto de los Lirios",
    "wof:placetype":"locality"
},
  "geometry": {"coordinates":[-106.38486,26.24189],"type":"Point"}
}