{
  "type": "Feature",
  "properties": {
    "gn:admin1_code":"26.0",
    "gn:admin2_code":"69.0",
    "gn:asciiname":"La Cebadilla",
    "gn:country_code":"MX",
    "gn:dem":1298,
    "gn:feature_class":"P",
    "gn:feature_code":"PPL",
    "gn:name":"La Cebadilla",
    "gn:population":0,
    "gn:timezone":"America/Hermosillo",
    "iso:country":"MX",
    "name:spa_x_preferred":[
        "La Cebadilla"
    ],
    "wof:name":"La Cebadilla",
    "wof:placetype":"locality"
},
  "geometry": {"coordinates":[-109.20699999999999,28.60298],"type":"Point"}
}