{
  "type": "Feature",
  "properties": {
    "gn:admin1_code":"4",
    "gn:admin2_code":"11",
    "gn:asciiname":"Laguna San Ramon I",
    "gn:country_code":"MX",
    "gn:dem":70,
    "gn:feature_class":"P",
    "gn:feature_code":"PPL",
    "gn:name":"Laguna San Ram\u00f3n I",
    "gn:population":11,
    "gn:timezone":"America/Merida",
    "iso:country":"MX",
    "name:und_x_variant":[
        "Laguna San Ram\u00f3n I"
    ],
    "wof:name":"Laguna San Ramon I",
    "wof:placetype":"locality",
    "wof:population":11
},
  "geometry": {"coordinates":[-90.62111,18.12083],"type":"Point"}
}