{
  "type": "Feature",
  "properties": {
    "gn:admin1_code":"32",
    "gn:admin2_code":"40.0",
    "gn:asciiname":"La Sementera",
    "gn:country_code":"MX",
    "gn:dem":2099,
    "gn:feature_class":"P",
    "gn:feature_code":"PPL",
    "gn:name":"La Sementera",
    "gn:population":0,
    "gn:timezone":"America/Mexico_City",
    "iso:country":"MX",
    "name:spa_x_preferred":[
        "La Sementera"
    ],
    "wof:name":"La Sementera",
    "wof:placetype":"locality"
},
  "geometry": {"coordinates":[-103.30398,23.61945],"type":"Point"}
}