{
  "type": "Feature",
  "properties": {
    "gn:admin1_code":"30",
    "gn:admin2_code":"11.0",
    "gn:asciiname":"El Moral",
    "gn:cc2":"MX",
    "gn:country_code":"MX",
    "gn:dem":7,
    "gn:feature_class":"P",
    "gn:feature_code":"PPL",
    "gn:name":"El Moral",
    "gn:population":0,
    "gn:timezone":"America/Mexico_City",
    "iso:country":"MX",
    "name:und_x_variant":[
        "Moral",
        "El Moral"
    ],
    "wof:name":"El Moral",
    "wof:placetype":"locality"
},
  "geometry": {"coordinates":[-95.91667,18.81667],"type":"Point"}
}