{
  "type": "Feature",
  "properties": {
    "gn:admin1_code":"16",
    "gn:admin2_code":"34.0",
    "gn:asciiname":"Pinitos",
    "gn:country_code":"MX",
    "gn:dem":2559,
    "gn:feature_class":"P",
    "gn:feature_code":"PPL",
    "gn:name":"Pinitos",
    "gn:population":0,
    "gn:timezone":"America/Mexico_City",
    "iso:country":"MX",
    "name:spa_x_preferred":[
        "Pinitos"
    ],
    "wof:name":"Pinitos",
    "wof:placetype":"locality"
},
  "geometry": {"coordinates":[-100.71391,19.49165],"type":"Point"}
}