{
  "type": "Feature",
  "properties": {
    "gn:admin1_code":"7",
    "gn:admin2_code":"4.0",
    "gn:asciiname":"Bella Union",
    "gn:country_code":"MX",
    "gn:dem":1747,
    "gn:feature_class":"P",
    "gn:feature_code":"PPL",
    "gn:name":"Bella Uni\u00f3n",
    "gn:population":0,
    "gn:timezone":"America/Monterrey",
    "iso:country":"MX",
    "name:ces_x_preferred":[
        "Bella Union"
    ],
    "name:deu_x_preferred":[
        "Bella Union"
    ],
    "name:fin_x_preferred":[
        "Bella Union"
    ],
    "name:fra_x_preferred":[
        "Bella Union"
    ],
    "name:glg_x_preferred":[
        "Bella Union"
    ],
    "name:ita_x_preferred":[
        "Bella Union Records"
    ],
    "name:jpn_x_preferred":[
        "\u30d9\u30e9\u30fb\u30e6\u30cb\u30aa\u30f3"
    ],
    "name:por_x_preferred":[
        "Bella Union"
    ],
    "name:spa_x_preferred":[
        "Bella Uni\u00f3n"
    ],
    "name:swe_x_preferred":[
        "Bella Union"
    ],
    "wof:name":"Bella Union",
    "wof:placetype":"locality"
},
  "geometry": {"coordinates":[-100.81676,25.43348],"type":"Point"}
}