{
  "type": "Feature",
  "properties": {
    "gn:admin1_code":"26.0",
    "gn:admin2_code":"30.0",
    "gn:asciiname":"Colonia el Abanico",
    "gn:country_code":"MX",
    "gn:dem":14,
    "gn:feature_class":"P",
    "gn:feature_code":"PPL",
    "gn:name":"Colonia el Abanico",
    "gn:population":0,
    "gn:timezone":"America/Hermosillo",
    "iso:country":"MX",
    "wof:name":"Colonia el Abanico",
    "wof:placetype":"locality"
},
  "geometry": {"coordinates":[-111.71666999999999,28.75],"type":"Point"}
}