{
  "type": "Feature",
  "properties": {
    "gn:admin1_code":"6",
    "gn:admin2_code":"1.0",
    "gn:asciiname":"La Sanguijuela",
    "gn:country_code":"MX",
    "gn:dem":1183,
    "gn:feature_class":"P",
    "gn:feature_code":"PPL",
    "gn:name":"La Sanguijuela",
    "gn:population":0,
    "gn:timezone":"America/Chihuahua",
    "iso:country":"MX",
    "name:spa_x_preferred":[
        "La Sanguijuela"
    ],
    "wof:name":"La Sanguijuela",
    "wof:placetype":"locality"
},
  "geometry": {"coordinates":[-107.01485,30.74192],"type":"Point"}
}