{
  "type": "Feature",
  "properties": {
    "gn:admin1_code":"6.0",
    "gn:admin2_code":"67.0",
    "gn:asciiname":"Angel Posada",
    "gn:country_code":"MX",
    "gn:dem":1345,
    "gn:feature_class":"P",
    "gn:feature_code":"PPL",
    "gn:name":"Angel Posada",
    "gn:population":0,
    "gn:timezone":"America/Chihuahua",
    "iso:country":"MX",
    "name:spa_x_preferred":[
        "Angel Posada"
    ],
    "wof:name":"Angel Posada",
    "wof:placetype":"locality"
},
  "geometry": {"coordinates":[-105.78395999999999,27.49945],"type":"Point"}
}