{
  "type": "Feature",
  "properties": {
    "gn:admin1_code":"28",
    "gn:admin2_code":"41.0",
    "gn:asciiname":"Quinta Hualala",
    "gn:country_code":"MX",
    "gn:dem":231,
    "gn:feature_class":"P",
    "gn:feature_code":"PPL",
    "gn:name":"Quinta Hualala",
    "gn:population":5,
    "gn:timezone":"America/Monterrey",
    "iso:country":"MX",
    "wof:name":"Quinta Hualala",
    "wof:placetype":"locality",
    "wof:population":5
},
  "geometry": {"coordinates":[-99.0825,23.81028],"type":"Point"}
}