{
  "type": "Feature",
  "properties": {
    "gn:admin1_code":"26.0",
    "gn:admin2_code":"35.0",
    "gn:asciiname":"El Bachatal",
    "gn:country_code":"MX",
    "gn:dem":843,
    "gn:feature_class":"P",
    "gn:feature_code":"PPL",
    "gn:name":"El Bachatal",
    "gn:population":0,
    "gn:timezone":"America/Hermosillo",
    "iso:country":"MX",
    "name:spa_x_preferred":[
        "El Bachatal"
    ],
    "wof:name":"El Bachatal",
    "wof:placetype":"locality"
},
  "geometry": {"coordinates":[-110.88521,30.79207],"type":"Point"}
}