{
  "type": "Feature",
  "properties": {
    "gn:admin1_code":"28",
    "gn:admin2_code":"5.0",
    "gn:asciiname":"Jaboncillos",
    "gn:country_code":"MX",
    "gn:dem":172,
    "gn:feature_class":"P",
    "gn:feature_code":"PPL",
    "gn:name":"Jaboncillos",
    "gn:population":0,
    "gn:timezone":"America/Monterrey",
    "iso:country":"MX",
    "name:spa_x_preferred":[
        "Jaboncillos"
    ],
    "wof:name":"Jaboncillos",
    "wof:placetype":"locality"
},
  "geometry": {"coordinates":[-98.57253,24.89999],"type":"Point"}
}