{
  "type": "Feature",
  "properties": {
    "gn:admin1_code":"28",
    "gn:admin2_code":"22.0",
    "gn:asciiname":"Doctor Jose Arredondo",
    "gn:country_code":"MX",
    "gn:dem":16,
    "gn:feature_class":"P",
    "gn:feature_code":"PPL",
    "gn:name":"Doctor Jos\u00e9 Arredondo",
    "gn:population":5,
    "gn:timezone":"America/Matamoros",
    "iso:country":"MX",
    "name:und_x_variant":[
        "Doctor Jos\u00e9 Arredondo"
    ],
    "wof:name":"Doctor Jose Arredondo",
    "wof:placetype":"locality",
    "wof:population":5
},
  "geometry": {"coordinates":[-97.58333,25.92861],"type":"Point"}
}