{
  "type": "Feature",
  "properties": {
    "gn:admin1_code":"25",
    "gn:admin2_code":"5.0",
    "gn:asciiname":"El Palmarito",
    "gn:country_code":"MX",
    "gn:dem":250,
    "gn:feature_class":"P",
    "gn:feature_code":"PPL",
    "gn:name":"El Palmarito",
    "gn:population":15,
    "gn:timezone":"America/Mazatlan",
    "iso:country":"MX",
    "wof:name":"El Palmarito",
    "wof:placetype":"locality",
    "wof:population":15
},
  "geometry": {"coordinates":[-106.92878,24.60151],"type":"Point"}
}