{
  "type": "Feature",
  "properties": {
    "gn:admin1_code":"20.0",
    "gn:asciiname":"Rio Viejo",
    "gn:country_code":"MX",
    "gn:dem":2098,
    "gn:feature_class":"P",
    "gn:feature_code":"PPL",
    "gn:name":"Rio Viejo",
    "gn:population":0,
    "gn:timezone":"America/Mexico_City",
    "iso:country":"MX",
    "name:spa_x_preferred":[
        "Rio Viejo"
    ],
    "wof:name":"Rio Viejo",
    "wof:placetype":"locality"
},
  "geometry": {"coordinates":[-97.27755000000001,17.5349],"type":"Point"}
}