{
  "type": "Feature",
  "properties": {
    "gn:admin1_code":"3.0",
    "gn:admin2_code":"1.0",
    "gn:asciiname":"San Miguel de Quepo",
    "gn:country_code":"MX",
    "gn:dem":187,
    "gn:feature_class":"P",
    "gn:feature_code":"PPL",
    "gn:name":"San Miguel de Quepo",
    "gn:population":0,
    "gn:timezone":"America/Mazatlan",
    "iso:country":"MX",
    "name:spa_x_preferred":[
        "San Miguel de Quepo"
    ],
    "wof:name":"San Miguel de Quepo",
    "wof:placetype":"locality"
},
  "geometry": {"coordinates":[-111.37954000000001,25.28913],"type":"Point"}
}