{
  "type": "Feature",
  "properties": {
    "gn:admin1_code":"12.0",
    "gn:admin2_code":"21.0",
    "gn:asciiname":"La Barra",
    "gn:country_code":"MX",
    "gn:dem":9,
    "gn:feature_class":"P",
    "gn:feature_code":"PPL",
    "gn:name":"La Barra",
    "gn:population":0,
    "gn:timezone":"America/Mexico_City",
    "iso:country":"MX",
    "name:spa_x_preferred":[
        "La Barra"
    ],
    "name:spa_x_variant":[
        "La Barra de Coyuca"
    ],
    "name:und_x_variant":[
        "Barro de Coyuca"
    ],
    "wof:name":"La Barra",
    "wof:placetype":"locality"
},
  "geometry": {"coordinates":[-100.10784,16.948],"type":"Point"}
}