{
  "type": "Feature",
  "properties": {
    "gn:admin1_code":"11.0",
    "gn:admin2_code":"30.0",
    "gn:asciiname":"Cerrito de San Francisco",
    "gn:country_code":"MX",
    "gn:dem":2168,
    "gn:feature_class":"P",
    "gn:feature_code":"PPL",
    "gn:name":"Cerrito de San Francisco",
    "gn:population":0,
    "gn:timezone":"America/Mexico_City",
    "iso:country":"MX",
    "name:spa_x_preferred":[
        "Cerrito de San Francisco"
    ],
    "name:spa_x_variant":[
        "El Cerrito"
    ],
    "wof:name":"Cerrito de San Francisco",
    "wof:placetype":"locality"
},
  "geometry": {"coordinates":[-101.23690999999999,21.51907000000001],"type":"Point"}
}