{
  "type": "Feature",
  "properties": {
    "gn:admin1_code":"19",
    "gn:admin2_code":"17.0",
    "gn:asciiname":"La Cuatro [Granja]",
    "gn:country_code":"MX",
    "gn:dem":1882,
    "gn:feature_class":"P",
    "gn:feature_code":"PPL",
    "gn:name":"La Cuatro [Granja]",
    "gn:population":8,
    "gn:timezone":"America/Monterrey",
    "iso:country":"MX",
    "wof:name":"La Cuatro [Granja]",
    "wof:placetype":"locality",
    "wof:population":8
},
  "geometry": {"coordinates":[-100.63028,24.99784],"type":"Point"}
}