{
  "type": "Feature",
  "properties": {
    "gn:admin1_code":"6",
    "gn:admin2_code":"29.0",
    "gn:asciiname":"Mesa de San Jose",
    "gn:country_code":"MX",
    "gn:dem":2305,
    "gn:feature_class":"P",
    "gn:feature_code":"PPL",
    "gn:name":"Mesa de San Jos\u00e9",
    "gn:population":0,
    "gn:timezone":"America/Chihuahua",
    "iso:country":"MX",
    "name:spa_x_preferred":[
        "Mesa de San Jos\u00e9"
    ],
    "name:und_x_variant":[
        "Rancho Mesa de San Jos\u00e9"
    ],
    "wof:name":"Mesa de San Jose",
    "wof:placetype":"locality"
},
  "geometry": {"coordinates":[-106.90246,25.96768],"type":"Point"}
}