{
  "type": "Feature",
  "properties": {
    "gn:admin1_code":"12",
    "gn:admin2_code":"57",
    "gn:asciiname":"Palo Dulce",
    "gn:country_code":"MX",
    "gn:dem":949,
    "gn:feature_class":"P",
    "gn:feature_code":"PPL",
    "gn:name":"Palo Dulce",
    "gn:population":31,
    "gn:timezone":"America/Mexico_City",
    "iso:country":"MX",
    "wof:name":"Palo Dulce",
    "wof:placetype":"locality",
    "wof:population":31
},
  "geometry": {"coordinates":[-100.70667,17.35694],"type":"Point"}
}