{
  "type": "Feature",
  "properties": {
    "gn:admin1_code":"28",
    "gn:admin2_code":"35",
    "gn:asciiname":"La Isla (Las Malvinas)",
    "gn:country_code":"MX",
    "gn:dem":7,
    "gn:feature_class":"P",
    "gn:feature_code":"PPL",
    "gn:name":"La Isla (Las Malvinas)",
    "gn:population":12,
    "gn:timezone":"America/Monterrey",
    "iso:country":"MX",
    "wof:name":"La Isla (Las Malvinas)",
    "wof:placetype":"locality",
    "wof:population":12
},
  "geometry": {"coordinates":[-97.78556,24.92528],"type":"Point"}
}