{
  "type": "Feature",
  "properties": {
    "gn:admin1_code":"7",
    "gn:admin2_code":"24.0",
    "gn:asciiname":"Trincheras",
    "gn:country_code":"MX",
    "gn:dem":1216,
    "gn:feature_class":"P",
    "gn:feature_code":"PPL",
    "gn:name":"Trincheras",
    "gn:population":0,
    "gn:timezone":"America/Monterrey",
    "iso:country":"MX",
    "name:spa_x_preferred":[
        "Trincheras"
    ],
    "wof:name":"Trincheras",
    "wof:placetype":"locality"
},
  "geometry": {"coordinates":[-101.98260000000001,25.60686],"type":"Point"}
}