{
  "type": "Feature",
  "properties": {
    "gn:admin1_code":"5",
    "gn:admin2_code":"8.0",
    "gn:asciiname":"Nueva Esperanza",
    "gn:country_code":"MX",
    "gn:dem":821,
    "gn:feature_class":"P",
    "gn:feature_code":"PPL",
    "gn:name":"Nueva Esperanza",
    "gn:population":100,
    "gn:timezone":"America/Mexico_City",
    "iso:country":"MX",
    "wof:name":"Nueva Esperanza",
    "wof:placetype":"locality",
    "wof:population":100
},
  "geometry": {"coordinates":[-92.56610999999999,15.68611],"type":"Point"}
}