{
  "type": "Feature",
  "properties": {
    "gn:admin1_code":"30",
    "gn:admin2_code":"124",
    "gn:asciiname":"Corpus Christy",
    "gn:country_code":"MX",
    "gn:dem":200,
    "gn:feature_class":"P",
    "gn:feature_code":"PPL",
    "gn:name":"Corpus Christy",
    "gn:population":27,
    "gn:timezone":"America/Mexico_City",
    "iso:country":"MX",
    "wof:name":"Corpus Christy",
    "wof:placetype":"locality",
    "wof:population":27
},
  "geometry": {"coordinates":[-97.34,20.43278],"type":"Point"}
}