{
  "type": "Feature",
  "properties": {
    "gn:admin1_code":"12",
    "gn:admin2_code":"41.0",
    "gn:asciiname":"Portezuelo (Crucero de Xochiatenco)",
    "gn:country_code":"MX",
    "gn:dem":2135,
    "gn:feature_class":"P",
    "gn:feature_code":"PPL",
    "gn:name":"Portezuelo (Crucero de Xochiatenco)",
    "gn:population":6,
    "gn:timezone":"America/Mexico_City",
    "iso:country":"MX",
    "wof:name":"Portezuelo (Crucero de Xochiatenco)",
    "wof:placetype":"locality",
    "wof:population":6
},
  "geometry": {"coordinates":[-98.69138,17.1575],"type":"Point"}
}