{
  "type": "Feature",
  "properties": {
    "gn:admin1_code":"27",
    "gn:admin2_code":"9.0",
    "gn:asciiname":"Candelaria",
    "gn:country_code":"MX",
    "gn:dem":18,
    "gn:feature_class":"P",
    "gn:feature_code":"PPL",
    "gn:name":"Candelaria",
    "gn:population":0,
    "gn:timezone":"America/Mexico_City",
    "iso:country":"MX",
    "name:spa_x_preferred":[
        "Candelaria"
    ],
    "name:spa_x_variant":[
        "La Candelaria"
    ],
    "wof:name":"Candelaria",
    "wof:placetype":"locality"
},
  "geometry": {"coordinates":[-92.81495,17.65651],"type":"Point"}
}