{
  "type": "Feature",
  "properties": {
    "gn:admin1_code":"17",
    "gn:admin2_code":"26",
    "gn:asciiname":"Rancho Teja",
    "gn:country_code":"MX",
    "gn:dem":1495,
    "gn:feature_class":"P",
    "gn:feature_code":"PPL",
    "gn:name":"Rancho Teja",
    "gn:population":14,
    "gn:timezone":"America/Mexico_City",
    "iso:country":"MX",
    "wof:name":"Rancho Teja",
    "wof:placetype":"locality",
    "wof:population":14
},
  "geometry": {"coordinates":[-98.95028000000001,18.93],"type":"Point"}
}