{
  "type": "Feature",
  "properties": {
    "gn:admin1_code":"26",
    "gn:admin2_code":"51.0",
    "gn:asciiname":"Campo el Sauz",
    "gn:country_code":"MX",
    "gn:dem":1463,
    "gn:feature_class":"P",
    "gn:feature_code":"PPL",
    "gn:name":"Campo el Sauz",
    "gn:population":0,
    "gn:timezone":"America/Chihuahua",
    "iso:country":"MX",
    "name:spa_x_preferred":[
        "Campo el Sauz"
    ],
    "wof:name":"Campo el Sauz",
    "wof:placetype":"locality"
},
  "geometry": {"coordinates":[-109.07666999999999,28.17917000000001],"type":"Point"}
}