{
  "type": "Feature",
  "properties": {
    "gn:admin1_code":"27",
    "gn:admin2_code":"9.0",
    "gn:asciiname":"Jahuacapa",
    "gn:country_code":"MX",
    "gn:dem":17,
    "gn:feature_class":"P",
    "gn:feature_code":"PPL",
    "gn:name":"Jahuacapa",
    "gn:population":0,
    "gn:timezone":"America/Mexico_City",
    "iso:country":"MX",
    "name:spa_x_preferred":[
        "Jahuacapa"
    ],
    "wof:name":"Jahuacapa",
    "wof:placetype":"locality"
},
  "geometry": {"coordinates":[-92.83271999999999,17.73935],"type":"Point"}
}