{
  "type": "Feature",
  "properties": {
    "gn:admin1_code":"24",
    "gn:admin2_code":"13.0",
    "gn:asciiname":"La Reforma",
    "gn:country_code":"MX",
    "gn:dem":39,
    "gn:feature_class":"P",
    "gn:feature_code":"PPL",
    "gn:name":"La Reforma",
    "gn:population":5,
    "gn:timezone":"America/Mexico_City",
    "iso:country":"MX",
    "wof:name":"La Reforma",
    "wof:placetype":"locality",
    "wof:population":5
},
  "geometry": {"coordinates":[-98.89361,21.84583],"type":"Point"}
}