{
  "type": "Feature",
  "properties": {
    "gn:admin1_code":"12",
    "gn:admin2_code":"28",
    "gn:asciiname":"Zapote Blanco (Los Zapotes)",
    "gn:country_code":"MX",
    "gn:dem":1406,
    "gn:feature_class":"P",
    "gn:feature_code":"PPL",
    "gn:name":"Zapote Blanco (Los Zapotes)",
    "gn:population":10,
    "gn:timezone":"America/Mexico_City",
    "iso:country":"MX",
    "wof:name":"Zapote Blanco (Los Zapotes)",
    "wof:placetype":"locality",
    "wof:population":10
},
  "geometry": {"coordinates":[-99.07955,17.45962],"type":"Point"}
}