{
  "type": "Feature",
  "properties": {
    "gn:admin1_code":"13",
    "gn:admin2_code":"7",
    "gn:asciiname":"El Recuerdo",
    "gn:country_code":"MX",
    "gn:dem":2534,
    "gn:feature_class":"P",
    "gn:feature_code":"PPL",
    "gn:name":"El Recuerdo",
    "gn:population":10,
    "gn:timezone":"America/Mexico_City",
    "iso:country":"MX",
    "wof:name":"El Recuerdo",
    "wof:placetype":"locality",
    "wof:population":10
},
  "geometry": {"coordinates":[-98.43532999999999,19.70777],"type":"Point"}
}