{
  "type": "Feature",
  "properties": {
    "gn:admin1_code":"20",
    "gn:admin2_code":"386.0",
    "gn:asciiname":"Los Mendez",
    "gn:country_code":"MX",
    "gn:dem":547,
    "gn:feature_class":"P",
    "gn:feature_code":"PPL",
    "gn:name":"Los M\u00e9ndez",
    "gn:population":86,
    "gn:timezone":"America/Mexico_City",
    "iso:country":"MX",
    "name:und_x_variant":[
        "Los M\u00e9ndez"
    ],
    "wof:name":"Los Mendez",
    "wof:placetype":"locality",
    "wof:population":86
},
  "geometry": {"coordinates":[-97.45583000000001,16.52944],"type":"Point"}
}