{
  "type": "Feature",
  "properties": {
    "gn:admin1_code":"14.0",
    "gn:admin2_code":"64.0",
    "gn:asciiname":"Las Arcinas",
    "gn:country_code":"MX",
    "gn:dem":2123,
    "gn:feature_class":"P",
    "gn:feature_code":"PPL",
    "gn:name":"Las Arcinas",
    "gn:population":0,
    "gn:timezone":"America/Mexico_City",
    "iso:country":"MX",
    "name:spa_x_preferred":[
        "Las Arcinas"
    ],
    "wof:name":"Las Arcinas",
    "wof:placetype":"locality"
},
  "geometry": {"coordinates":[-101.69654,21.91754],"type":"Point"}
}