{
  "type": "Feature",
  "properties": {
    "gn:admin1_code":"28",
    "gn:admin2_code":"3",
    "gn:asciiname":"Buenos Aires (Dolores del Angel Martinez)",
    "gn:country_code":"MX",
    "gn:dem":16,
    "gn:feature_class":"P",
    "gn:feature_code":"PPL",
    "gn:name":"Buenos Aires (Dolores del \u00c1ngel Mart\u00ednez)",
    "gn:population":10,
    "gn:timezone":"America/Monterrey",
    "iso:country":"MX",
    "name:und_x_variant":[
        "Buenos Aires (Dolores del \u00c1ngel Mart\u00ednez)"
    ],
    "wof:name":"Buenos Aires (Dolores del Angel Martinez)",
    "wof:placetype":"locality",
    "wof:population":10
},
  "geometry": {"coordinates":[-98.01472,22.44361],"type":"Point"}
}