{
  "type": "Feature",
  "properties": {
    "gn:admin1_code":"20",
    "gn:admin2_code":"64",
    "gn:asciiname":"Cuajinicuil",
    "gn:country_code":"MX",
    "gn:dem":935,
    "gn:feature_class":"P",
    "gn:feature_code":"PPL",
    "gn:name":"Cuajinicuil",
    "gn:population":35,
    "gn:timezone":"America/Mexico_City",
    "iso:country":"MX",
    "wof:name":"Cuajinicuil",
    "wof:placetype":"locality",
    "wof:population":35
},
  "geometry": {"coordinates":[-95.57889,16.8625],"type":"Point"}
}