{
  "type": "Feature",
  "properties": {
    "gn:admin1_code":"8.0",
    "gn:admin2_code":"5.0",
    "gn:asciiname":"La Cebada",
    "gn:country_code":"MX",
    "gn:dem":1595,
    "gn:feature_class":"P",
    "gn:feature_code":"PPL",
    "gn:name":"La Cebada",
    "gn:population":0,
    "gn:timezone":"America/Mexico_City",
    "iso:country":"MX",
    "name:spa_x_preferred":[
        "La Cebada"
    ],
    "wof:name":"La Cebada",
    "wof:placetype":"locality"
},
  "geometry": {"coordinates":[-103.62587000000001,19.41965],"type":"Point"}
}