{
  "type": "Feature",
  "properties": {
    "gn:admin1_code":"30",
    "gn:admin2_code":"150.0",
    "gn:asciiname":"El Mamey",
    "gn:country_code":"MX",
    "gn:dem":8,
    "gn:feature_class":"P",
    "gn:feature_code":"PPL",
    "gn:name":"El Mamey",
    "gn:population":0,
    "gn:timezone":"America/Mexico_City",
    "iso:country":"MX",
    "wof:name":"El Mamey",
    "wof:placetype":"locality"
},
  "geometry": {"coordinates":[-97.65694000000001,21.51667],"type":"Point"}
}