{
  "type": "Feature",
  "properties": {
    "gn:admin1_code":"4",
    "gn:admin2_code":"11.0",
    "gn:asciiname":"Monte Carmelo",
    "gn:country_code":"MX",
    "gn:dem":58,
    "gn:feature_class":"P",
    "gn:feature_code":"PPL",
    "gn:name":"Monte Carmelo",
    "gn:population":5,
    "gn:timezone":"America/Merida",
    "iso:country":"MX",
    "wof:name":"Monte Carmelo",
    "wof:placetype":"locality",
    "wof:population":5
},
  "geometry": {"coordinates":[-91.08444,18.25639],"type":"Point"}
}