{
  "type": "Feature",
  "properties": {
    "gn:admin1_code":"14",
    "gn:admin2_code":"58.0",
    "gn:asciiname":"La Palapa",
    "gn:country_code":"MX",
    "gn:dem":159,
    "gn:feature_class":"P",
    "gn:feature_code":"PPL",
    "gn:name":"La Palapa",
    "gn:population":75,
    "gn:timezone":"America/Mexico_City",
    "iso:country":"MX",
    "name:spa_x_preferred":[
        "La Palapa"
    ],
    "wof:name":"La Palapa",
    "wof:placetype":"locality",
    "wof:population":75
},
  "geometry": {"coordinates":[-105.09439999999999,20.68065],"type":"Point"}
}