{
  "type": "Feature",
  "properties": {
    "gn:admin1_code":"14",
    "gn:asciiname":"Tuxpan",
    "gn:country_code":"MX",
    "gn:dem":1277,
    "gn:feature_class":"P",
    "gn:feature_code":"PPL",
    "gn:name":"Tuxpan",
    "gn:population":0,
    "gn:timezone":"America/Mexico_City",
    "iso:country":"MX",
    "name:ara_x_preferred":[
        "\u062a\u0648\u0643\u0633\u0628\u0627\u0646"
    ],
    "name:ben_x_preferred":[
        "\u09a4\u09c1\u0995\u09cd\u09b8\u09be\u09aa\u09be\u09a8"
    ],
    "name:deu_x_preferred":[
        "Tuxpan"
    ],
    "name:ell_x_preferred":[
        "\u03a4\u03bf\u03cd\u03be\u03c0\u03b1\u03bd"
    ],
    "name:fas_x_preferred":[
        "\u062a\u0648\u06a9\u0633\u067e\u0627\u0646"
    ],
    "name:fra_x_preferred":[
        "Tuxpan"
    ],
    "name:heb_x_preferred":[
        "\u05d8\u05d5\u05e7\u05e1\u05e4\u05d0\u05df"
    ],
    "name:hin_x_preferred":[
        "\u091f\u0915\u094d\u0938\u092a\u0928"
    ],
    "name:hun_x_preferred":[
        "Tuxpan"
    ],
    "name:ind_x_preferred":[
        "Tuxpan"
    ],
    "name:jpn_x_preferred":[
        "\u30c8\u30a5\u30b9\u30d1\u30f3"
    ],
    "name:kor_x_preferred":[
        "\ud131\uc2a4\ud310"
    ],
    "name:nld_x_preferred":[
        "Tuxpan"
    ],
    "name:pol_x_preferred":[
        "Tuxpan"
    ],
    "name:por_x_preferred":[
        "Tuxpan"
    ],
    "name:tur_x_preferred":[
        "Tuxpan"
    ],
    "name:ukr_x_preferred":[
        "\u0422\u0443\u0441\u043f\u0430\u043d"
    ],
    "name:urd_x_preferred":[
        "\u0679\u06a9\u0633\u067e\u0627\u0646"
    ],
    "name:zho_cn_x_preferred":[
        "\u56fe\u65af\u6f58"
    ],
    "name:zho_tw_x_preferred":[
        "\u5716\u514b\u65af\u6f58"
    ],
    "wof:name":"Tuxpan",
    "wof:placetype":"locality"
},
  "geometry": {"coordinates":[-104.11667,21.61667],"type":"Point"}
}