{
  "type": "Feature",
  "properties": {
    "gn:admin1_code":"14",
    "gn:asciiname":"Tuxpan",
    "gn:country_code":"MX",
    "gn:dem":1277,
    "gn:feature_class":"P",
    "gn:feature_code":"PPL",
    "gn:name":"Tuxpan",
    "gn:population":0,
    "gn:timezone":"America/Mexico_City",
    "iso:country":"MX",
    "name:deu_x_preferred":[
        "Tuxpan"
    ],
    "name:fas_x_preferred":[
        "\u062a\u0648\u06a9\u0633\u067e\u0627\u0646"
    ],
    "name:fra_x_preferred":[
        "Tuxpan"
    ],
    "name:ind_x_preferred":[
        "Tuxpan"
    ],
    "name:nld_x_preferred":[
        "Tuxpan"
    ],
    "name:por_x_preferred":[
        "Tuxpan"
    ],
    "wof:name":"Tuxpan",
    "wof:placetype":"locality"
},
  "geometry": {"coordinates":[-104.11667,21.61667000000001],"type":"Point"}
}