{
  "type": "Feature",
  "properties": {
    "gn:admin1_code":"14",
    "gn:asciiname":"Tuxpan",
    "gn:country_code":"MX",
    "gn:dem":1277,
    "gn:feature_class":"P",
    "gn:feature_code":"PPL",
    "gn:name":"Tuxpan",
    "gn:population":0,
    "gn:timezone":"America/Mexico_City",
    "iso:country":"MX",
    "wof:name":"Tuxpan",
    "wof:placetype":"locality"
},
  "geometry": {"coordinates":[-104.11667,21.61667000000001],"type":"Point"}
}