{
  "type": "Feature",
  "properties": {
    "gn:admin1_code":"30",
    "gn:admin2_code":"208.0",
    "gn:asciiname":"Las Cruces (Cerro Partido)",
    "gn:country_code":"MX",
    "gn:dem":8,
    "gn:feature_class":"P",
    "gn:feature_code":"PPL",
    "gn:name":"Las Cruces (Cerro Partido)",
    "gn:population":7,
    "gn:timezone":"America/Mexico_City",
    "iso:country":"MX",
    "wof:name":"Las Cruces (Cerro Partido)",
    "wof:placetype":"locality",
    "wof:population":7
},
  "geometry": {"coordinates":[-95.77916999999999,18.40278],"type":"Point"}
}