{
  "type": "Feature",
  "properties": {
    "gn:admin1_code":"6.0",
    "gn:admin2_code":"52.0",
    "gn:asciiname":"El Mulato",
    "gn:country_code":"MX",
    "gn:dem":767,
    "gn:feature_class":"P",
    "gn:feature_code":"PPL",
    "gn:name":"El Mulato",
    "gn:population":16,
    "gn:timezone":"America/Ojinaga",
    "iso:country":"MX",
    "name:und_x_variant":[
        "Mulato",
        "El Mulato"
    ],
    "wof:name":"El Mulato",
    "wof:placetype":"locality",
    "wof:population":16
},
  "geometry": {"coordinates":[-104.16907,29.3954],"type":"Point"}
}