{
  "type": "Feature",
  "properties": {
    "gn:admin1_code":"11",
    "gn:admin2_code":"4",
    "gn:asciiname":"Santa Maria del Rosario (Victor Ledezma)",
    "gn:country_code":"MX",
    "gn:dem":1978,
    "gn:feature_class":"P",
    "gn:feature_code":"PPL",
    "gn:name":"Santa Mar\u00eda del Rosario (V\u00edctor Ledezma)",
    "gn:population":12,
    "gn:timezone":"America/Mexico_City",
    "iso:country":"MX",
    "name:und_x_variant":[
        "Santa Mar\u00eda del Rosario (V\u00edctor Ledezma)"
    ],
    "wof:name":"Santa Maria del Rosario (Victor Ledezma)",
    "wof:placetype":"locality",
    "wof:population":12
},
  "geometry": {"coordinates":[-100.56556,20.46056],"type":"Point"}
}