{
  "type": "Feature",
  "properties": {
    "gn:admin1_code":"6",
    "gn:admin2_code":"12",
    "gn:asciiname":"Recohuarore",
    "gn:country_code":"MX",
    "gn:dem":1968,
    "gn:feature_class":"P",
    "gn:feature_code":"PPL",
    "gn:name":"Recohu\u00e1rore",
    "gn:population":33,
    "gn:timezone":"America/Chihuahua",
    "iso:country":"MX",
    "name:und_x_variant":[
        "Recohu\u00e1rore"
    ],
    "wof:name":"Recohuarore",
    "wof:placetype":"locality",
    "wof:population":33
},
  "geometry": {"coordinates":[-107.25423000000001,27.60245],"type":"Point"}
}