{
  "type": "Feature",
  "properties": {
    "gn:admin1_code":"25",
    "gn:admin2_code":"18.0",
    "gn:asciiname":"La Galera",
    "gn:country_code":"MX",
    "gn:dem":11,
    "gn:feature_class":"P",
    "gn:feature_code":"PPL",
    "gn:name":"La Galera",
    "gn:population":138,
    "gn:timezone":"America/Mazatlan",
    "iso:country":"MX",
    "wof:name":"La Galera",
    "wof:placetype":"locality",
    "wof:population":138
},
  "geometry": {"coordinates":[-107.53917,24.60778],"type":"Point"}
}