{
  "type": "Feature",
  "properties": {
    "gn:admin1_code":"17",
    "gn:admin2_code":"22",
    "gn:asciiname":"Ahuazutlan",
    "gn:country_code":"MX",
    "gn:dem":2231,
    "gn:feature_class":"P",
    "gn:feature_code":"PPL",
    "gn:name":"Ahuazutl\u00e1n",
    "gn:population":14,
    "gn:timezone":"America/Mexico_City",
    "iso:country":"MX",
    "name:und_x_variant":[
        "Ahuazutl\u00e1n"
    ],
    "wof:name":"Ahuazutlan",
    "wof:placetype":"locality",
    "wof:population":14
},
  "geometry": {"coordinates":[-98.69972,18.86444],"type":"Point"}
}