{
  "type": "Feature",
  "properties": {
    "gn:admin1_code":"28.0",
    "gn:admin2_code":"12.0",
    "gn:asciiname":"Los Higuerones",
    "gn:country_code":"MX",
    "gn:dem":27,
    "gn:feature_class":"P",
    "gn:feature_code":"PPL",
    "gn:name":"Los Higuerones",
    "gn:population":0,
    "gn:timezone":"America/Monterrey",
    "iso:country":"MX",
    "name:spa_x_preferred":[
        "Los Higuerones"
    ],
    "wof:name":"Los Higuerones",
    "wof:placetype":"locality"
},
  "geometry": {"coordinates":[-98.5915,22.65428],"type":"Point"}
}