{
  "type": "Feature",
  "properties": {
    "gn:admin1_code":"21",
    "gn:admin2_code":"109.0",
    "gn:asciiname":"Ahuacatitla",
    "gn:country_code":"MX",
    "gn:dem":1223,
    "gn:feature_class":"P",
    "gn:feature_code":"PPL",
    "gn:name":"Ahuacatitla",
    "gn:population":211,
    "gn:timezone":"America/Mexico_City",
    "iso:country":"MX",
    "wof:name":"Ahuacatitla",
    "wof:placetype":"locality",
    "wof:population":211
},
  "geometry": {"coordinates":[-98.14096000000001,20.30812],"type":"Point"}
}