{
  "type": "Feature",
  "properties": {
    "gn:admin1_code":"5",
    "gn:admin2_code":"61.0",
    "gn:asciiname":"Cotitlan",
    "gn:country_code":"MX",
    "gn:dem":754,
    "gn:feature_class":"P",
    "gn:feature_code":"PPL",
    "gn:name":"Cotitl\u00e1n",
    "gn:population":4,
    "gn:timezone":"America/Mexico_City",
    "iso:country":"MX",
    "name:und_x_variant":[
        "Cotitl\u00e1n"
    ],
    "wof:name":"Cotitlan",
    "wof:placetype":"locality",
    "wof:population":4
},
  "geometry": {"coordinates":[-93.48806,16.52583],"type":"Point"}
}