{
  "type": "Feature",
  "properties": {
    "gn:admin1_code":"16",
    "gn:admin2_code":"81.0",
    "gn:asciiname":"El Bonete",
    "gn:country_code":"MX",
    "gn:dem":961,
    "gn:feature_class":"P",
    "gn:feature_code":"PPL",
    "gn:name":"El Bonete",
    "gn:population":60,
    "gn:timezone":"America/Mexico_City",
    "iso:country":"MX",
    "wof:name":"El Bonete",
    "wof:placetype":"locality",
    "wof:population":60
},
  "geometry": {"coordinates":[-100.46083,19.07583],"type":"Point"}
}