{
  "type": "Feature",
  "properties": {
    "gn:admin1_code":"3",
    "gn:admin2_code":"9.0",
    "gn:asciiname":"Isla Nuestra Senora del Carmen",
    "gn:country_code":"MX",
    "gn:dem":108,
    "gn:feature_class":"P",
    "gn:feature_code":"PPL",
    "gn:name":"Isla Nuestra Se\u00f1ora del Carmen",
    "gn:population":4,
    "gn:timezone":"America/Mazatlan",
    "iso:country":"MX",
    "name:und_x_variant":[
        "Isla Nuestra Se\u00f1ora del Carmen"
    ],
    "wof:name":"Isla Nuestra Senora del Carmen",
    "wof:placetype":"locality",
    "wof:population":4
},
  "geometry": {"coordinates":[-111.17983,25.92228],"type":"Point"}
}