{
  "type": "Feature",
  "properties": {
    "gn:admin1_code":"30",
    "gn:admin2_code":"197.0",
    "gn:asciiname":"Miramar",
    "gn:country_code":"MX",
    "gn:dem":993,
    "gn:feature_class":"P",
    "gn:feature_code":"PPL",
    "gn:name":"Miramar",
    "gn:population":88,
    "gn:timezone":"America/Mexico_City",
    "iso:country":"MX",
    "wof:name":"Miramar",
    "wof:placetype":"locality",
    "wof:population":88
},
  "geometry": {"coordinates":[-96.74527999999999,19.82417],"type":"Point"}
}