{
  "type": "Feature",
  "properties": {
    "gn:admin1_code":"6",
    "gn:admin2_code":"2.0",
    "gn:asciiname":"El Pelillo",
    "gn:country_code":"MX",
    "gn:dem":984,
    "gn:feature_class":"P",
    "gn:feature_code":"PPL",
    "gn:name":"El Pelillo",
    "gn:population":0,
    "gn:timezone":"America/Chihuahua",
    "iso:country":"MX",
    "name:und_x_variant":[
        "Rancho Pelillo",
        "El Pelillo"
    ],
    "wof:name":"El Pelillo",
    "wof:placetype":"locality"
},
  "geometry": {"coordinates":[-105.16396,29.04274],"type":"Point"}
}