{
  "type": "Feature",
  "properties": {
    "gn:admin1_code":"14",
    "gn:admin2_code":"94.0",
    "gn:asciiname":"El Tepetate",
    "gn:country_code":"MX",
    "gn:dem":1116,
    "gn:feature_class":"P",
    "gn:feature_code":"PPL",
    "gn:name":"El Tepetate",
    "gn:population":129,
    "gn:timezone":"America/Mexico_City",
    "iso:country":"MX",
    "wof:name":"El Tepetate",
    "wof:placetype":"locality",
    "wof:population":129
},
  "geometry": {"coordinates":[-103.77333,21.06472],"type":"Point"}
}