{
  "type": "Feature",
  "properties": {
    "gn:admin1_code":"12.0",
    "gn:admin2_code":"22.0",
    "gn:asciiname":"El Paraisito",
    "gn:country_code":"MX",
    "gn:dem":576,
    "gn:feature_class":"P",
    "gn:feature_code":"PPL",
    "gn:name":"El Paraisito",
    "gn:population":0,
    "gn:timezone":"America/Mexico_City",
    "iso:country":"MX",
    "name:spa_x_preferred":[
        "El Paraisito"
    ],
    "wof:name":"El Paraisito",
    "wof:placetype":"locality"
},
  "geometry": {"coordinates":[-100.92363,18.07098],"type":"Point"}
}