{
  "type": "Feature",
  "properties": {
    "gn:admin1_code":"16",
    "gn:admin2_code":"97",
    "gn:asciiname":"Las Gueilotas",
    "gn:country_code":"MX",
    "gn:dem":1293,
    "gn:feature_class":"P",
    "gn:feature_code":"PPL",
    "gn:name":"Las G\u00fcilotas",
    "gn:population":19,
    "gn:timezone":"America/Mexico_City",
    "iso:country":"MX",
    "name:und_x_variant":[
        "Las G\u00fcilotas"
    ],
    "wof:name":"Las Gueilotas",
    "wof:placetype":"locality",
    "wof:population":19
},
  "geometry": {"coordinates":[-101.53667,19.105],"type":"Point"}
}