{
  "type": "Feature",
  "properties": {
    "gn:admin1_code":"30.0",
    "gn:admin2_code":"141.0",
    "gn:asciiname":"Tepanca",
    "gn:country_code":"MX",
    "gn:dem":613,
    "gn:feature_class":"P",
    "gn:feature_code":"PPL",
    "gn:name":"Tepanca",
    "gn:population":0,
    "gn:timezone":"America/Mexico_City",
    "iso:country":"MX",
    "name:spa_x_preferred":[
        "Tepanca"
    ],
    "wof:name":"Tepanca",
    "wof:placetype":"locality"
},
  "geometry": {"coordinates":[-95.25827,18.58168],"type":"Point"}
}