{
  "type": "Feature",
  "properties": {
    "gn:admin1_code":"15",
    "gn:admin2_code":"50.0",
    "gn:asciiname":"Tlaxcantitla",
    "gn:country_code":"MX",
    "gn:dem":2719,
    "gn:feature_class":"P",
    "gn:feature_code":"PPL",
    "gn:name":"Tlaxcantitla",
    "gn:population":0,
    "gn:timezone":"America/Mexico_City",
    "iso:country":"MX",
    "wof:name":"Tlaxcantitla",
    "wof:placetype":"locality"
},
  "geometry": {"coordinates":[-98.90000000000001,19.06667],"type":"Point"}
}