{
  "type": "Feature",
  "properties": {
    "gn:admin1_code":"24",
    "gn:admin2_code":"26.0",
    "gn:asciiname":"Pozo Blanco III (Tanchahuil)",
    "gn:country_code":"MX",
    "gn:dem":203,
    "gn:feature_class":"P",
    "gn:feature_code":"PPL",
    "gn:name":"Pozo Blanco III (Tanchahuil)",
    "gn:population":72,
    "gn:timezone":"America/Mexico_City",
    "iso:country":"MX",
    "wof:name":"Pozo Blanco III (Tanchahuil)",
    "wof:placetype":"locality",
    "wof:population":72
},
  "geometry": {"coordinates":[-98.86861,21.57917],"type":"Point"}
}