{
  "type": "Feature",
  "properties": {
    "gn:admin1_code":"22.0",
    "gn:admin2_code":"14.0",
    "gn:asciiname":"La Estacada",
    "gn:country_code":"MX",
    "gn:dem":2049,
    "gn:feature_class":"P",
    "gn:feature_code":"PPL",
    "gn:name":"La Estacada",
    "gn:population":1972,
    "gn:timezone":"America/Mexico_City",
    "iso:country":"MX",
    "name:und_x_variant":[
        "Estacada",
        "La Estacada"
    ],
    "wof:name":"La Estacada",
    "wof:placetype":"locality",
    "wof:population":1972
},
  "geometry": {"coordinates":[-100.40763,20.82151],"type":"Point"}
}