{
  "type": "Feature",
  "properties": {
    "gn:admin1_code":"16",
    "gn:admin2_code":"101.0",
    "gn:asciiname":"La Muerta (San Rafael)",
    "gn:country_code":"MX",
    "gn:dem":768,
    "gn:feature_class":"P",
    "gn:feature_code":"PPL",
    "gn:name":"La Muerta (San Rafael)",
    "gn:population":7,
    "gn:timezone":"America/Mexico_City",
    "iso:country":"MX",
    "wof:name":"La Muerta (San Rafael)",
    "wof:placetype":"locality",
    "wof:population":7
},
  "geometry": {"coordinates":[-100.87611,19.35583],"type":"Point"}
}