{
  "type": "Feature",
  "properties": {
    "gn:admin1_code":"15.0",
    "gn:asciiname":"El Cayaco",
    "gn:country_code":"MX",
    "gn:dem":93,
    "gn:feature_class":"P",
    "gn:feature_code":"PPL",
    "gn:name":"El Cayaco",
    "gn:population":0,
    "gn:timezone":"America/Mexico_City",
    "iso:country":"MX",
    "name:spa_x_preferred":[
        "El Cayaco"
    ],
    "wof:name":"El Cayaco",
    "wof:placetype":"locality"
},
  "geometry": {"coordinates":[-102.54991,18.15809],"type":"Point"}
}