{
  "type": "Feature",
  "properties": {
    "gn:admin1_code":"6",
    "gn:admin2_code":"27",
    "gn:asciiname":"Boquirare",
    "gn:country_code":"MX",
    "gn:dem":1902,
    "gn:feature_class":"P",
    "gn:feature_code":"PPL",
    "gn:name":"Boquirare",
    "gn:population":14,
    "gn:timezone":"America/Chihuahua",
    "iso:country":"MX",
    "wof:name":"Boquirare",
    "wof:placetype":"locality",
    "wof:population":14
},
  "geometry": {"coordinates":[-107.49769000000001,27.45937],"type":"Point"}
}