{
  "type": "Feature",
  "properties": {
    "gn:admin1_code":"16.0",
    "gn:admin2_code":"47.0",
    "gn:asciiname":"La Parrita",
    "gn:country_code":"MX",
    "gn:dem":1612,
    "gn:feature_class":"P",
    "gn:feature_code":"PPL",
    "gn:name":"La Parrita",
    "gn:population":0,
    "gn:timezone":"America/Mexico_City",
    "iso:country":"MX",
    "name:spa_x_preferred":[
        "La Parrita"
    ],
    "wof:name":"La Parrita",
    "wof:placetype":"locality"
},
  "geometry": {"coordinates":[-100.53169,19.44953],"type":"Point"}
}