{
  "type": "Feature",
  "properties": {
    "gn:admin1_code":"30.0",
    "gn:admin2_code":"161.0",
    "gn:asciiname":"Cocales",
    "gn:country_code":"MX",
    "gn:dem":114,
    "gn:feature_class":"P",
    "gn:feature_code":"PPL",
    "gn:name":"Cocales",
    "gn:population":0,
    "gn:timezone":"America/Mexico_City",
    "iso:country":"MX",
    "name:spa_x_preferred":[
        "Cocales"
    ],
    "wof:name":"Cocales",
    "wof:placetype":"locality"
},
  "geometry": {"coordinates":[-98.54083,21.54667],"type":"Point"}
}