{
  "type": "Feature",
  "properties": {
    "gn:admin1_code":"10",
    "gn:admin2_code":"12.0",
    "gn:asciiname":"Monterrey",
    "gn:country_code":"MX",
    "gn:dem":1163,
    "gn:feature_class":"P",
    "gn:feature_code":"PPL",
    "gn:name":"Monterrey",
    "gn:population":0,
    "gn:timezone":"America/Monterrey",
    "iso:country":"MX",
    "wof:name":"Monterrey",
    "wof:placetype":"locality"
},
  "geometry": {"coordinates":[-103.62672999999999,25.4895],"type":"Point"}
}