{
  "type": "Feature",
  "properties": {
    "gn:admin1_code":"21",
    "gn:admin2_code":"212.0",
    "gn:asciiname":"Tenampulco",
    "gn:country_code":"MX",
    "gn:dem":1935,
    "gn:feature_class":"P",
    "gn:feature_code":"PPL",
    "gn:name":"Tenampulco",
    "gn:population":323,
    "gn:timezone":"America/Mexico_City",
    "iso:country":"MX",
    "name:ceb_x_preferred":[
        "Tenampulco"
    ],
    "name:epo_x_preferred":[
        "Tenampulco"
    ],
    "name:eus_x_preferred":[
        "Tenampulco"
    ],
    "name:rus_x_preferred":[
        "\u0422\u0435\u043d\u0430\u043c\u043f\u0443\u043b\u044c\u043a\u043e"
    ],
    "name:spa_x_preferred":[
        "Tenampulco"
    ],
    "name:srp_x_preferred":[
        "\u041e\u043f\u0448\u0442\u0438\u043d\u0430 \u0422\u0435\u043d\u0430\u043c\u043f\u0443\u043b\u043a\u043e"
    ],
    "name:swe_x_preferred":[
        "Tenampulco"
    ],
    "name:vie_x_preferred":[
        "Tenampulco"
    ],
    "wof:name":"Tenampulco",
    "wof:placetype":"locality",
    "wof:population":323
},
  "geometry": {"coordinates":[-97.69417,19.72611],"type":"Point"}
}