{
  "type": "Feature",
  "properties": {
    "gn:admin1_code":"21",
    "gn:admin2_code":"212.0",
    "gn:asciiname":"Tenampulco",
    "gn:country_code":"MX",
    "gn:dem":1935,
    "gn:feature_class":"P",
    "gn:feature_code":"PPL",
    "gn:name":"Tenampulco",
    "gn:population":323,
    "gn:timezone":"America/Mexico_City",
    "iso:country":"MX",
    "wof:name":"Tenampulco",
    "wof:placetype":"locality",
    "wof:population":323
},
  "geometry": {"coordinates":[-97.69417,19.72611],"type":"Point"}
}