{
  "type": "Feature",
  "properties": {
    "gn:admin1_code":"32.0",
    "gn:admin2_code":"29.0",
    "gn:asciiname":"San Julian",
    "gn:country_code":"MX",
    "gn:dem":2108,
    "gn:feature_class":"P",
    "gn:feature_code":"PPL",
    "gn:name":"San Juli\u00e1n",
    "gn:population":0,
    "gn:timezone":"America/Mexico_City",
    "iso:country":"MX",
    "name:spa_x_preferred":[
        "San Juli\u00e1n"
    ],
    "wof:name":"San Julian",
    "wof:placetype":"locality"
},
  "geometry": {"coordinates":[-103.36053,24.03771],"type":"Point"}
}