{
  "type": "Feature",
  "properties": {
    "gn:admin1_code":"20",
    "gn:admin2_code":"21.0",
    "gn:asciiname":"Rancho Tablas",
    "gn:country_code":"MX",
    "gn:dem":172,
    "gn:feature_class":"P",
    "gn:feature_code":"PPL",
    "gn:name":"Rancho Tablas",
    "gn:population":0,
    "gn:timezone":"America/Mexico_City",
    "iso:country":"MX",
    "name:spa_x_preferred":[
        "Rancho Tabla"
    ],
    "name:spa_x_variant":[
        "Rancho Tablas"
    ],
    "wof:name":"Rancho Tablas",
    "wof:placetype":"locality"
},
  "geometry": {"coordinates":[-96.65546999999999,18.5725],"type":"Point"}
}