{
  "type": "Feature",
  "properties": {
    "gn:admin1_code":"28.0",
    "gn:admin2_code":"37.0",
    "gn:asciiname":"Uresteno",
    "gn:country_code":"MX",
    "gn:dem":65,
    "gn:feature_class":"P",
    "gn:feature_code":"PPL",
    "gn:name":"Ureste\u00f1o",
    "gn:population":2,
    "gn:timezone":"America/Monterrey",
    "iso:country":"MX",
    "name:spa_x_preferred":[
        "Ureste\u00f1o"
    ],
    "wof:name":"Uresteno",
    "wof:placetype":"locality",
    "wof:population":2
},
  "geometry": {"coordinates":[-97.93138999999999,23.94583],"type":"Point"}
}