{
  "type": "Feature",
  "properties": {
    "gn:admin1_code":"24",
    "gn:admin2_code":"22.0",
    "gn:asciiname":"El Yaqui",
    "gn:country_code":"MX",
    "gn:dem":1672,
    "gn:feature_class":"P",
    "gn:feature_code":"PPL",
    "gn:name":"El Yaqui",
    "gn:population":7,
    "gn:timezone":"America/Mexico_City",
    "iso:country":"MX",
    "wof:name":"El Yaqui",
    "wof:placetype":"locality",
    "wof:population":7
},
  "geometry": {"coordinates":[-100.99889,22.70167],"type":"Point"}
}