{
  "type": "Feature",
  "properties": {
    "gn:admin1_code":"19",
    "gn:admin2_code":"33.0",
    "gn:asciiname":"Cuauhtemoc (La Ceja)",
    "gn:country_code":"MX",
    "gn:dem":233,
    "gn:feature_class":"P",
    "gn:feature_code":"PPL",
    "gn:name":"Cuauht\u00e9moc (La Ceja)",
    "gn:population":37,
    "gn:timezone":"America/Monterrey",
    "iso:country":"MX",
    "name:spa_x_preferred":[
        "Cuauht\u00e9moc"
    ],
    "wof:name":"Cuauhtemoc (La Ceja)",
    "wof:placetype":"locality",
    "wof:population":37
},
  "geometry": {"coordinates":[-99.28668999999999,25.03398],"type":"Point"}
}