{
  "type": "Feature",
  "properties": {
    "gn:admin1_code":"24.0",
    "gn:admin2_code":"29.0",
    "gn:asciiname":"Tanzocob",
    "gn:country_code":"MX",
    "gn:dem":67,
    "gn:feature_class":"P",
    "gn:feature_code":"PPL",
    "gn:name":"Tanzocob",
    "gn:population":0,
    "gn:timezone":"America/Mexico_City",
    "iso:country":"MX",
    "name:spa_x_preferred":[
        "Tanzocob"
    ],
    "wof:name":"Tanzocob",
    "wof:placetype":"locality"
},
  "geometry": {"coordinates":[-98.61039,21.50547000000001],"type":"Point"}
}