{
  "type": "Feature",
  "properties": {
    "gn:admin1_code":"10",
    "gn:admin2_code":"39.0",
    "gn:asciiname":"Campo Limpio",
    "gn:country_code":"MX",
    "gn:dem":1976,
    "gn:feature_class":"P",
    "gn:feature_code":"PPL",
    "gn:name":"Campo Limpio",
    "gn:population":74,
    "gn:timezone":"America/Monterrey",
    "iso:country":"MX",
    "wof:name":"Campo Limpio",
    "wof:placetype":"locality",
    "wof:population":74
},
  "geometry": {"coordinates":[-105.03977999999999,24.99138],"type":"Point"}
}