{
  "type": "Feature",
  "properties": {
    "gn:admin1_code":"6",
    "gn:admin2_code":"27.0",
    "gn:asciiname":"Bocoyna",
    "gn:country_code":"MX",
    "gn:dem":2342,
    "gn:feature_class":"P",
    "gn:feature_code":"PPL",
    "gn:name":"Bocoyna",
    "gn:population":0,
    "gn:timezone":"America/Chihuahua",
    "iso:country":"MX",
    "name:ceb_x_preferred":[
        "Bocoyna"
    ],
    "name:rus_x_preferred":[
        "\u0411\u043e\u043a\u043e\u0439\u043d\u0430"
    ],
    "name:sco_x_preferred":[
        "Bocoyna"
    ],
    "name:spa_x_preferred":[
        "Bocoyna"
    ],
    "wof:name":"Bocoyna",
    "wof:placetype":"locality"
},
  "geometry": {"coordinates":[-107.24665,27.09141],"type":"Point"}
}