{
  "type": "Feature",
  "properties": {
    "gn:admin1_code":"6.0",
    "gn:admin2_code":"63.0",
    "gn:asciiname":"Los Arbolitos",
    "gn:country_code":"MX",
    "gn:dem":2065,
    "gn:feature_class":"P",
    "gn:feature_code":"PPL",
    "gn:name":"Los Arbolitos",
    "gn:population":0,
    "gn:timezone":"America/Chihuahua",
    "iso:country":"MX",
    "name:spa_x_preferred":[
        "Los Arbolitos"
    ],
    "wof:name":"Los Arbolitos",
    "wof:placetype":"locality"
},
  "geometry": {"coordinates":[-108.15198999999998,28.51296],"type":"Point"}
}