{
  "type": "Feature",
  "properties": {
    "gn:admin1_code":"16",
    "gn:admin2_code":"3",
    "gn:asciiname":"Potrero Verde",
    "gn:country_code":"MX",
    "gn:dem":1843,
    "gn:feature_class":"P",
    "gn:feature_code":"PPL",
    "gn:name":"Potrero Verde",
    "gn:population":26,
    "gn:timezone":"America/Mexico_City",
    "iso:country":"MX",
    "wof:name":"Potrero Verde",
    "wof:placetype":"locality",
    "wof:population":26
},
  "geometry": {"coordinates":[-101.03139,19.8125],"type":"Point"}
}