{
  "type": "Feature",
  "properties": {
    "gn:admin1_code":"30",
    "gn:admin2_code":"23.0",
    "gn:asciiname":"Plan de las Animas",
    "gn:country_code":"MX",
    "gn:dem":1704,
    "gn:feature_class":"P",
    "gn:feature_code":"PPL",
    "gn:name":"Plan de las \u00c1nimas",
    "gn:population":95,
    "gn:timezone":"America/Mexico_City",
    "iso:country":"MX",
    "name:und_x_variant":[
        "Plan de las \u00c1nimas"
    ],
    "wof:name":"Plan de las Animas",
    "wof:placetype":"locality",
    "wof:population":95
},
  "geometry": {"coordinates":[-97.20889,19.79],"type":"Point"}
}