{
  "type": "Feature",
  "properties": {
    "gn:admin1_code":"15",
    "gn:admin2_code":"18.0",
    "gn:asciiname":"Residencial Rancho el Meson",
    "gn:country_code":"MX",
    "gn:dem":2607,
    "gn:feature_class":"P",
    "gn:feature_code":"PPL",
    "gn:name":"Residencial Rancho el Mes\u00f3n",
    "gn:population":139,
    "gn:timezone":"America/Mexico_City",
    "iso:country":"MX",
    "name:und_x_variant":[
        "Residencial Rancho el Mes\u00f3n"
    ],
    "wof:name":"Residencial Rancho el Meson",
    "wof:placetype":"locality",
    "wof:population":139
},
  "geometry": {"coordinates":[-99.58499999999999,19.18111],"type":"Point"}
}