{
  "type": "Feature",
  "properties": {
    "gn:admin1_code":"12",
    "gn:admin2_code":"22",
    "gn:asciiname":"Canas Viejas",
    "gn:country_code":"MX",
    "gn:dem":448,
    "gn:feature_class":"P",
    "gn:feature_code":"PPL",
    "gn:name":"Ca\u00f1as Viejas",
    "gn:population":26,
    "gn:timezone":"America/Mexico_City",
    "iso:country":"MX",
    "name:und_x_variant":[
        "Ca\u00f1as Viejas"
    ],
    "wof:name":"Canas Viejas",
    "wof:placetype":"locality",
    "wof:population":26
},
  "geometry": {"coordinates":[-100.9418,18.24087],"type":"Point"}
}