{
  "type": "Feature",
  "properties": {
    "gn:admin1_code":"6.0",
    "gn:admin2_code":"20.0",
    "gn:asciiname":"Mesa Colorada",
    "gn:country_code":"MX",
    "gn:dem":740,
    "gn:feature_class":"P",
    "gn:feature_code":"PPL",
    "gn:name":"Mesa Colorada",
    "gn:population":0,
    "gn:timezone":"America/Chihuahua",
    "iso:country":"MX",
    "name:spa_x_preferred":[
        "Mesa Colorada"
    ],
    "name:und_x_variant":[
        "Casa Colorada"
    ],
    "wof:name":"Mesa Colorada",
    "wof:placetype":"locality"
},
  "geometry": {"coordinates":[-108.58013,27.56388],"type":"Point"}
}