{
  "type": "Feature",
  "properties": {
    "gn:admin1_code":"10.0",
    "gn:admin2_code":"37.0",
    "gn:asciiname":"Divisadero de Galancita",
    "gn:country_code":"MX",
    "gn:dem":1348,
    "gn:feature_class":"P",
    "gn:feature_code":"PPL",
    "gn:name":"Divisadero de Galancita",
    "gn:population":0,
    "gn:timezone":"America/Monterrey",
    "iso:country":"MX",
    "name:spa_x_preferred":[
        "Divisadero de Galancita"
    ],
    "wof:name":"Divisadero de Galancita",
    "wof:placetype":"locality"
},
  "geometry": {"coordinates":[-106.75803999999999,25.14432],"type":"Point"}
}