{
  "type": "Feature",
  "properties": {
    "gn:admin1_code":"13",
    "gn:admin2_code":"10.0",
    "gn:asciiname":"San Onofre",
    "gn:country_code":"MX",
    "gn:dem":1044,
    "gn:feature_class":"P",
    "gn:feature_code":"PPL",
    "gn:name":"San Onofre",
    "gn:population":99,
    "gn:timezone":"America/Mexico_City",
    "iso:country":"MX",
    "name:spa_x_preferred":[
        "San Onofre"
    ],
    "wof:name":"San Onofre",
    "wof:placetype":"locality",
    "wof:population":99
},
  "geometry": {"coordinates":[-99.05415000000001,21.20909],"type":"Point"}
}