{
  "type": "Feature",
  "properties": {
    "gn:admin1_code":"6",
    "gn:admin2_code":"27",
    "gn:asciiname":"Napuchi",
    "gn:country_code":"MX",
    "gn:dem":2337,
    "gn:feature_class":"P",
    "gn:feature_code":"PPL",
    "gn:name":"Napuchi",
    "gn:population":15,
    "gn:timezone":"America/Chihuahua",
    "iso:country":"MX",
    "wof:name":"Napuchi",
    "wof:placetype":"locality",
    "wof:population":15
},
  "geometry": {"coordinates":[-107.08296,27.39243],"type":"Point"}
}