{
  "type": "Feature",
  "properties": {
    "gn:admin1_code":"4",
    "gn:admin2_code":"9.0",
    "gn:asciiname":"Guadalajara",
    "gn:country_code":"MX",
    "gn:dem":61,
    "gn:feature_class":"P",
    "gn:feature_code":"PPL",
    "gn:name":"Guadalajara",
    "gn:population":0,
    "gn:timezone":"America/Merida",
    "iso:country":"MX",
    "wof:name":"Guadalajara",
    "wof:placetype":"locality"
},
  "geometry": {"coordinates":[-90.99222,18.39293],"type":"Point"}
}