{
  "type": "Feature",
  "properties": {
    "gn:admin1_code":"28.0",
    "gn:admin2_code":"8.0",
    "gn:asciiname":"El Reparo",
    "gn:country_code":"MX",
    "gn:dem":166,
    "gn:feature_class":"P",
    "gn:feature_code":"PPL",
    "gn:name":"El Reparo",
    "gn:population":4,
    "gn:timezone":"America/Monterrey",
    "iso:country":"MX",
    "name:spa_x_preferred":[
        "El Reparo"
    ],
    "wof:name":"El Reparo",
    "wof:placetype":"locality",
    "wof:population":4
},
  "geometry": {"coordinates":[-98.78505,23.68411],"type":"Point"}
}