{
  "type": "Feature",
  "properties": {
    "gn:admin1_code":"14.0",
    "gn:asciiname":"Pedregal",
    "gn:country_code":"MX",
    "gn:dem":1957,
    "gn:feature_class":"P",
    "gn:feature_code":"PPL",
    "gn:name":"Pedregal",
    "gn:population":0,
    "gn:timezone":"America/Mexico_City",
    "iso:country":"MX",
    "name:spa_x_preferred":[
        "Pedregal"
    ],
    "name:spa_x_variant":[
        "El Pedregal"
    ],
    "wof:name":"Pedregal",
    "wof:placetype":"locality"
},
  "geometry": {"coordinates":[-102.01549,21.12941],"type":"Point"}
}