{
  "type": "Feature",
  "properties": {
    "gn:admin1_code":"24",
    "gn:admin2_code":"53.0",
    "gn:asciiname":"El Laurel",
    "gn:country_code":"MX",
    "gn:dem":118,
    "gn:feature_class":"P",
    "gn:feature_code":"PPL",
    "gn:name":"El Laurel",
    "gn:population":57,
    "gn:timezone":"America/Mexico_City",
    "iso:country":"MX",
    "wof:name":"El Laurel",
    "wof:placetype":"locality",
    "wof:population":57
},
  "geometry": {"coordinates":[-98.89667,21.43194],"type":"Point"}
}