{
  "type": "Feature",
  "properties": {
    "gn:admin1_code":"4.0",
    "gn:asciiname":"Santa Cristina",
    "gn:country_code":"MX",
    "gn:dem":149,
    "gn:feature_class":"P",
    "gn:feature_code":"PPL",
    "gn:name":"Santa Cristina",
    "gn:population":0,
    "gn:timezone":"America/Merida",
    "iso:country":"MX",
    "name:bre_x_preferred":[
        "Santa Cristina"
    ],
    "name:cat_x_preferred":[
        "Santa Cristina"
    ],
    "name:ceb_x_preferred":[
        "Santa Cristina"
    ],
    "name:deu_x_preferred":[
        "Santa Cristina"
    ],
    "name:glg_x_preferred":[
        "Santa Cristina"
    ],
    "name:ita_x_preferred":[
        "Santa Cristina"
    ],
    "name:pms_x_preferred":[
        "Santa Cristina"
    ],
    "name:por_x_preferred":[
        "Santa Cristina"
    ],
    "name:scn_x_preferred":[
        "Santa Cristina"
    ],
    "name:sco_x_preferred":[
        "Santa Cristina"
    ],
    "name:spa_x_preferred":[
        "Santa Cristina"
    ],
    "name:srp_x_preferred":[
        "Santa Kristina"
    ],
    "name:swe_x_preferred":[
        "Santa Cristina"
    ],
    "name:ukr_x_preferred":[
        "\u0421\u0432\u044f\u0442\u0430 \u0425\u0440\u0438\u0441\u0442\u0438\u043d\u0430"
    ],
    "wof:name":"Santa Cristina",
    "wof:placetype":"locality"
},
  "geometry": {"coordinates":[-89.95976999999998,18.54345],"type":"Point"}
}