{
  "type": "Feature",
  "properties": {
    "gn:admin1_code":"4.0",
    "gn:asciiname":"Santa Cristina",
    "gn:country_code":"MX",
    "gn:dem":149,
    "gn:feature_class":"P",
    "gn:feature_code":"PPL",
    "gn:name":"Santa Cristina",
    "gn:population":0,
    "gn:timezone":"America/Merida",
    "iso:country":"MX",
    "name:spa_x_preferred":[
        "Santa Cristina"
    ],
    "wof:name":"Santa Cristina",
    "wof:placetype":"locality"
},
  "geometry": {"coordinates":[-89.95976999999998,18.54345],"type":"Point"}
}