{
  "type": "Feature",
  "properties": {
    "gn:admin1_code":"29",
    "gn:admin2_code":"13",
    "gn:asciiname":"San Diego Meca",
    "gn:country_code":"MX",
    "gn:dem":2456,
    "gn:feature_class":"P",
    "gn:feature_code":"PPL",
    "gn:name":"San Diego Meca",
    "gn:population":11,
    "gn:timezone":"America/Mexico_City",
    "iso:country":"MX",
    "wof:name":"San Diego Meca",
    "wof:placetype":"locality",
    "wof:population":11
},
  "geometry": {"coordinates":[-97.86926,19.36884],"type":"Point"}
}