{
  "type": "Feature",
  "properties": {
    "gn:admin1_code":"27",
    "gn:admin2_code":"12.0",
    "gn:asciiname":"Encrucijada",
    "gn:country_code":"MX",
    "gn:dem":5,
    "gn:feature_class":"P",
    "gn:feature_code":"PPL",
    "gn:name":"Encrucijada",
    "gn:population":0,
    "gn:timezone":"America/Mexico_City",
    "iso:country":"MX",
    "name:spa_x_preferred":[
        "Encrucijada"
    ],
    "name:spa_x_variant":[
        "La Encrucijada"
    ],
    "wof:name":"Encrucijada",
    "wof:placetype":"locality"
},
  "geometry": {"coordinates":[-92.47954,17.92817],"type":"Point"}
}