{
  "type": "Feature",
  "properties": {
    "gn:admin1_code":"27",
    "gn:admin2_code":"12.0",
    "gn:asciiname":"Encrucijada",
    "gn:country_code":"MX",
    "gn:dem":5,
    "gn:feature_class":"P",
    "gn:feature_code":"PPL",
    "gn:name":"Encrucijada",
    "gn:population":0,
    "gn:timezone":"America/Mexico_City",
    "iso:country":"MX",
    "name:fra_x_preferred":[
        "Encrucijada"
    ],
    "name:ita_x_preferred":[
        "Encrucijada"
    ],
    "name:kat_x_preferred":[
        "\u10d4\u10dc\u10d9\u10e0\u10e3\u10e1\u10d8\u10ee\u10d0\u10d3\u10d0"
    ],
    "name:pol_x_preferred":[
        "Encrucijada"
    ],
    "name:por_x_preferred":[
        "Encrucijada"
    ],
    "name:sco_x_preferred":[
        "Encrucijada"
    ],
    "name:spa_x_preferred":[
        "Encrucijada"
    ],
    "name:spa_x_variant":[
        "La Encrucijada"
    ],
    "name:vie_x_preferred":[
        "Encrucijada"
    ],
    "name:zho_x_preferred":[
        "\u6069\u514b\u9b6f\u897f\u54c8\u9054"
    ],
    "wof:name":"Encrucijada",
    "wof:placetype":"locality"
},
  "geometry": {"coordinates":[-92.47954,17.92817],"type":"Point"}
}