{
  "type": "Feature",
  "properties": {
    "gn:admin1_code":"10",
    "gn:admin2_code":"13.0",
    "gn:asciiname":"San Lorenzo",
    "gn:country_code":"MX",
    "gn:dem":1177,
    "gn:feature_class":"P",
    "gn:feature_code":"PPL",
    "gn:name":"San Lorenzo",
    "gn:population":0,
    "gn:timezone":"America/Monterrey",
    "iso:country":"MX",
    "name:spa_x_preferred":[
        "San Lorenzo"
    ],
    "wof:name":"San Lorenzo",
    "wof:placetype":"locality"
},
  "geometry": {"coordinates":[-104.14194999999999,26.59492],"type":"Point"}
}