{
  "type": "Feature",
  "properties": {
    "gn:admin1_code":"23",
    "gn:admin2_code":"9.0",
    "gn:asciiname":"Houston",
    "gn:country_code":"MX",
    "gn:dem":7,
    "gn:feature_class":"P",
    "gn:feature_code":"PPL",
    "gn:name":"Houston",
    "gn:population":7,
    "gn:timezone":"America/Cancun",
    "iso:country":"MX",
    "wof:name":"Houston",
    "wof:placetype":"locality",
    "wof:population":7
},
  "geometry": {"coordinates":[-87.47469,20.09201],"type":"Point"}
}