{
  "type": "Feature",
  "properties": {
    "gn:admin1_code":"26",
    "gn:admin2_code":"50.0",
    "gn:asciiname":"La Casa Colorada",
    "gn:country_code":"MX",
    "gn:dem":525,
    "gn:feature_class":"P",
    "gn:feature_code":"PPL",
    "gn:name":"La Casa Colorada",
    "gn:population":0,
    "gn:timezone":"America/Hermosillo",
    "iso:country":"MX",
    "name:spa_x_preferred":[
        "La Casa Colorada"
    ],
    "wof:name":"La Casa Colorada",
    "wof:placetype":"locality"
},
  "geometry": {"coordinates":[-110.58083000000001,29.68611],"type":"Point"}
}