{
  "type": "Feature",
  "properties": {
    "gn:admin1_code":"3",
    "gn:admin2_code":"8.0",
    "gn:asciiname":"Guayparin",
    "gn:country_code":"MX",
    "gn:dem":431,
    "gn:feature_class":"P",
    "gn:feature_code":"PPL",
    "gn:name":"Guayparin",
    "gn:population":0,
    "gn:timezone":"America/Mazatlan",
    "iso:country":"MX",
    "name:spa_x_preferred":[
        "Guayparin"
    ],
    "wof:name":"Guayparin",
    "wof:placetype":"locality"
},
  "geometry": {"coordinates":[-109.84414,23.55005],"type":"Point"}
}