{
  "type": "Feature",
  "properties": {
    "gn:admin1_code":"20.0",
    "gn:admin2_code":"334.0",
    "gn:asciiname":"Las Tres Marias",
    "gn:country_code":"MX",
    "gn:dem":10,
    "gn:feature_class":"P",
    "gn:feature_code":"PPL",
    "gn:name":"Las Tres Mar\u00edas",
    "gn:population":0,
    "gn:timezone":"America/Mexico_City",
    "iso:country":"MX",
    "name:ceb_x_preferred":[
        "Las Tres Marias"
    ],
    "name:spa_x_preferred":[
        "Las Tres Mar\u00edas"
    ],
    "name:swe_x_preferred":[
        "Las Tres Marias"
    ],
    "wof:name":"Las Tres Marias",
    "wof:placetype":"locality"
},
  "geometry": {"coordinates":[-97.45602,15.97124],"type":"Point"}
}