{
  "type": "Feature",
  "properties": {
    "gn:admin1_code":"5",
    "gn:admin2_code":"44.0",
    "gn:asciiname":"Las Tejitas",
    "gn:country_code":"MX",
    "gn:dem":1129,
    "gn:feature_class":"P",
    "gn:feature_code":"PPL",
    "gn:name":"Las Tejitas",
    "gn:population":7,
    "gn:timezone":"America/Mexico_City",
    "iso:country":"MX",
    "wof:name":"Las Tejitas",
    "wof:placetype":"locality",
    "wof:population":7
},
  "geometry": {"coordinates":[-92.93306,16.77167],"type":"Point"}
}