{
  "type": "Feature",
  "properties": {
    "gn:admin1_code":"7.0",
    "gn:admin2_code":"36.0",
    "gn:asciiname":"Cinco Hermanos",
    "gn:country_code":"MX",
    "gn:dem":1177,
    "gn:feature_class":"P",
    "gn:feature_code":"PPL",
    "gn:name":"Cinco Hermanos",
    "gn:population":0,
    "gn:timezone":"America/Monterrey",
    "iso:country":"MX",
    "wof:name":"Cinco Hermanos",
    "wof:placetype":"locality"
},
  "geometry": {"coordinates":[-103.37466000000001,25.37852],"type":"Point"}
}