{
  "type": "Feature",
  "properties": {
    "gn:admin1_code":"5",
    "gn:admin2_code":"40.0",
    "gn:asciiname":"El Carmen",
    "gn:country_code":"MX",
    "gn:dem":10,
    "gn:feature_class":"P",
    "gn:feature_code":"PPL",
    "gn:name":"El Carmen",
    "gn:population":6,
    "gn:timezone":"America/Mexico_City",
    "iso:country":"MX",
    "wof:name":"El Carmen",
    "wof:placetype":"locality",
    "wof:population":6
},
  "geometry": {"coordinates":[-92.56389,15.07917],"type":"Point"}
}