{
  "type": "Feature",
  "properties": {
    "gn:admin1_code":"30",
    "gn:admin2_code":"152.0",
    "gn:asciiname":"Rancho Playas",
    "gn:country_code":"MX",
    "gn:dem":17,
    "gn:feature_class":"P",
    "gn:feature_code":"PPL",
    "gn:name":"Rancho Playas",
    "gn:population":6,
    "gn:timezone":"America/Mexico_City",
    "iso:country":"MX",
    "wof:name":"Rancho Playas",
    "wof:placetype":"locality",
    "wof:population":6
},
  "geometry": {"coordinates":[-97.77722,22.06972],"type":"Point"}
}