{
  "type": "Feature",
  "properties": {
    "gn:admin1_code":"10.0",
    "gn:admin2_code":"32.0",
    "gn:asciiname":"La Lagunita",
    "gn:country_code":"MX",
    "gn:dem":1833,
    "gn:feature_class":"P",
    "gn:feature_code":"PPL",
    "gn:name":"La Lagunita",
    "gn:population":0,
    "gn:timezone":"America/Monterrey",
    "iso:country":"MX",
    "name:und_x_variant":[
        "Lagunita",
        "La Lagunita"
    ],
    "wof:name":"La Lagunita",
    "wof:placetype":"locality"
},
  "geometry": {"coordinates":[-105.42995999999999,24.94324],"type":"Point"}
}