{
  "type": "Feature",
  "properties": {
    "gn:admin1_code":"6",
    "gn:admin2_code":"47",
    "gn:asciiname":"Coralillo",
    "gn:country_code":"MX",
    "gn:dem":1784,
    "gn:feature_class":"P",
    "gn:feature_code":"PPL",
    "gn:name":"Coralillo",
    "gn:population":12,
    "gn:timezone":"America/Chihuahua",
    "iso:country":"MX",
    "wof:name":"Coralillo",
    "wof:placetype":"locality",
    "wof:population":12
},
  "geometry": {"coordinates":[-108.66661999999999,28.01213],"type":"Point"}
}