{
  "type": "Feature",
  "properties": {
    "gn:admin1_code":"16.0",
    "gn:admin2_code":"38.0",
    "gn:asciiname":"Sanchiqueo",
    "gn:country_code":"MX",
    "gn:dem":523,
    "gn:feature_class":"P",
    "gn:feature_code":"PPL",
    "gn:name":"Sanchiqueo",
    "gn:population":122,
    "gn:timezone":"America/Mexico_City",
    "iso:country":"MX",
    "wof:name":"Sanchiqueo",
    "wof:placetype":"locality",
    "wof:population":122
},
  "geometry": {"coordinates":[-101.22806,18.72111],"type":"Point"}
}