{
  "type": "Feature",
  "properties": {
    "gn:admin1_code":"20",
    "gn:admin2_code":"12",
    "gn:asciiname":"El Venero",
    "gn:country_code":"MX",
    "gn:dem":540,
    "gn:feature_class":"P",
    "gn:feature_code":"PPL",
    "gn:name":"El Venero",
    "gn:population":12,
    "gn:timezone":"America/Mexico_City",
    "iso:country":"MX",
    "wof:name":"El Venero",
    "wof:placetype":"locality",
    "wof:population":12
},
  "geometry": {"coordinates":[-96.49611,15.93],"type":"Point"}
}