{
  "type": "Feature",
  "properties": {
    "gn:admin1_code":"14",
    "gn:admin2_code":"58",
    "gn:asciiname":"Santa Monica",
    "gn:country_code":"MX",
    "gn:dem":1229,
    "gn:feature_class":"P",
    "gn:feature_code":"PPL",
    "gn:name":"Santa M\u00f3nica",
    "gn:population":20,
    "gn:timezone":"America/Mexico_City",
    "iso:country":"MX",
    "name:und_x_variant":[
        "Santa M\u00f3nica"
    ],
    "wof:name":"Santa Monica",
    "wof:placetype":"locality",
    "wof:population":20
},
  "geometry": {"coordinates":[-104.82693999999999,20.56222],"type":"Point"}
}