{
  "type": "Feature",
  "properties": {
    "iso:country":"MX",
    "name:spa_x_preferred":[
        "San Miguel de Allende Centro"
    ],
    "name:spa_x_variant":[
        "San Miguel"
    ],
    "wof:lang":[
        "spa"
    ],
    "wof:name":"San Miguel de Allende Centro",
    "wof:placetype":"neighbourhood"
},
  "geometry": {"coordinates":[-100.74299600000001,20.913263],"type":"Point"}
}