{
  "type": "Feature",
  "properties": {
    "gn:admin1_code":"6.0",
    "gn:admin2_code":"30.0",
    "gn:asciiname":"Mesa del Rayo",
    "gn:country_code":"MX",
    "gn:dem":2378,
    "gn:feature_class":"P",
    "gn:feature_code":"PPL",
    "gn:name":"Mesa del Rayo",
    "gn:population":0,
    "gn:timezone":"America/Chihuahua",
    "iso:country":"MX",
    "name:spa_x_preferred":[
        "Mesa del Rayo"
    ],
    "wof:name":"Mesa del Rayo",
    "wof:placetype":"locality"
},
  "geometry": {"coordinates":[-108.253,27.63599],"type":"Point"}
}