{
  "type": "Feature",
  "properties": {
    "gn:admin1_code":"6",
    "gn:admin2_code":"40.0",
    "gn:asciiname":"El Caballo Bayo",
    "gn:country_code":"MX",
    "gn:dem":2333,
    "gn:feature_class":"P",
    "gn:feature_code":"PPL",
    "gn:name":"El Caballo Bayo",
    "gn:population":0,
    "gn:timezone":"America/Chihuahua",
    "iso:country":"MX",
    "name:spa_x_preferred":[
        "El Caballo Bayo"
    ],
    "wof:name":"El Caballo Bayo",
    "wof:placetype":"locality"
},
  "geometry": {"coordinates":[-108.32944999999999,29.82597],"type":"Point"}
}