{
  "type": "Feature",
  "properties": {
    "gn:admin1_code":"1",
    "gn:admin2_code":"9.0",
    "gn:asciiname":"Mexiquito",
    "gn:country_code":"MX",
    "gn:dem":2081,
    "gn:feature_class":"P",
    "gn:feature_code":"PPL",
    "gn:name":"Mexiquito",
    "gn:population":0,
    "gn:timezone":"America/Mexico_City",
    "iso:country":"MX",
    "wof:name":"Mexiquito",
    "wof:placetype":"locality"
},
  "geometry": {"coordinates":[-102.16667,22.15],"type":"Point"}
}