{
  "type": "Feature",
  "properties": {
    "gn:admin1_code":"11",
    "gn:admin2_code":"14.0",
    "gn:asciiname":"San Pedro (Palo Mocho)",
    "gn:country_code":"MX",
    "gn:dem":1995,
    "gn:feature_class":"P",
    "gn:feature_code":"PPL",
    "gn:name":"San Pedro (Palo Mocho)",
    "gn:population":388,
    "gn:timezone":"America/Mexico_City",
    "iso:country":"MX",
    "wof:name":"San Pedro (Palo Mocho)",
    "wof:placetype":"locality",
    "wof:population":388
},
  "geometry": {"coordinates":[-100.66639000000001,21.1175],"type":"Point"}
}