{
  "type": "Feature",
  "properties": {
    "gn:admin1_code":"6.0",
    "gn:admin2_code":"38.0",
    "gn:asciiname":"El Recuerdo",
    "gn:country_code":"MX",
    "gn:dem":1202,
    "gn:feature_class":"P",
    "gn:feature_code":"PPL",
    "gn:name":"El Recuerdo",
    "gn:population":0,
    "gn:timezone":"America/Chihuahua",
    "iso:country":"MX",
    "name:und_x_variant":[
        "Rancho el Recuerdo",
        "El Recuerdo"
    ],
    "wof:name":"El Recuerdo",
    "wof:placetype":"locality"
},
  "geometry": {"coordinates":[-105.21129999999999,28.7636],"type":"Point"}
}