{
  "type": "Feature",
  "properties": {
    "gn:admin1_code":"12",
    "gn:admin2_code":"81.0",
    "gn:asciiname":"Loma Baldia",
    "gn:country_code":"MX",
    "gn:dem":1498,
    "gn:feature_class":"P",
    "gn:feature_code":"PPL",
    "gn:name":"Loma Bald\u00eda",
    "gn:population":60,
    "gn:timezone":"America/Mexico_City",
    "iso:country":"MX",
    "name:und_x_variant":[
        "Loma Bald\u00eda"
    ],
    "wof:name":"Loma Baldia",
    "wof:placetype":"locality",
    "wof:population":60
},
  "geometry": {"coordinates":[-98.72356000000001,17.0671],"type":"Point"}
}