{
  "type": "Feature",
  "properties": {
    "gn:admin1_code":"6",
    "gn:admin2_code":"46.0",
    "gn:asciiname":"El Bordo",
    "gn:country_code":"MX",
    "gn:dem":1495,
    "gn:feature_class":"P",
    "gn:feature_code":"PPL",
    "gn:name":"El Bordo",
    "gn:population":148,
    "gn:timezone":"America/Mazatlan",
    "iso:country":"MX",
    "wof:name":"El Bordo",
    "wof:placetype":"locality",
    "wof:population":148
},
  "geometry": {"coordinates":[-107.90931999999999,26.31633],"type":"Point"}
}