{
  "type": "Feature",
  "properties": {
    "gn:admin1_code":"26",
    "gn:admin2_code":"66.0",
    "gn:asciiname":"La Encinena",
    "gn:country_code":"MX",
    "gn:dem":412,
    "gn:feature_class":"P",
    "gn:feature_code":"PPL",
    "gn:name":"La Encinena",
    "gn:population":0,
    "gn:timezone":"America/Hermosillo",
    "iso:country":"MX",
    "name:spa_x_preferred":[
        "La Encinena"
    ],
    "wof:name":"La Encinena",
    "wof:placetype":"locality"
},
  "geometry": {"coordinates":[-110.39400999999999,29.1345],"type":"Point"}
}