{
  "type": "Feature",
  "properties": {
    "gn:admin1_code":"2.0",
    "gn:admin2_code":"1.0",
    "gn:asciiname":"El Gato",
    "gn:country_code":"MX",
    "gn:dem":890,
    "gn:feature_class":"P",
    "gn:feature_code":"PPL",
    "gn:name":"El Gato",
    "gn:population":0,
    "gn:timezone":"America/Tijuana",
    "iso:country":"MX",
    "wof:name":"El Gato",
    "wof:placetype":"locality"
},
  "geometry": {"coordinates":[-114.65000000000001,29.61667000000001],"type":"Point"}
}