{
  "type": "Feature",
  "properties": {
    "gn:admin1_code":"26",
    "gn:admin2_code":"68.0",
    "gn:asciiname":"La Rastrita",
    "gn:country_code":"MX",
    "gn:dem":721,
    "gn:feature_class":"P",
    "gn:feature_code":"PPL",
    "gn:name":"La Rastrita",
    "gn:population":0,
    "gn:timezone":"America/Hermosillo",
    "iso:country":"MX",
    "name:spa_x_preferred":[
        "La Rastrita"
    ],
    "wof:name":"La Rastrita",
    "wof:placetype":"locality"
},
  "geometry": {"coordinates":[-109.95111,29.06417],"type":"Point"}
}