{
  "type": "Feature",
  "properties": {
    "gn:admin1_code":"7",
    "gn:admin2_code":"23.0",
    "gn:asciiname":"El Cimarron",
    "gn:country_code":"MX",
    "gn:dem":1263,
    "gn:feature_class":"P",
    "gn:feature_code":"PPL",
    "gn:name":"El Cimarr\u00f3n",
    "gn:population":0,
    "gn:timezone":"America/Monterrey",
    "iso:country":"MX",
    "name:spa_x_preferred":[
        "El Cimarr\u00f3n"
    ],
    "name:und_x_variant":[
        "Cimarr\u00f3n",
        "Agritos",
        "Rancho Agritos"
    ],
    "wof:name":"El Cimarron",
    "wof:placetype":"locality"
},
  "geometry": {"coordinates":[-102.84528,28.09648],"type":"Point"}
}