{
  "type": "Feature",
  "properties": {
    "gn:admin1_code":"31",
    "gn:admin2_code":"96.0",
    "gn:asciiname":"Comichen",
    "gn:country_code":"MX",
    "gn:dem":20,
    "gn:feature_class":"P",
    "gn:feature_code":"PPL",
    "gn:name":"Comich\u00e9n",
    "gn:population":0,
    "gn:timezone":"America/Merida",
    "iso:country":"MX",
    "name:spa_x_preferred":[
        "Comich\u00e9n"
    ],
    "wof:name":"Comichen",
    "wof:placetype":"locality"
},
  "geometry": {"coordinates":[-87.99484,21.12131],"type":"Point"}
}