{
  "type": "Feature",
  "properties": {
    "gn:admin1_code":"21",
    "gn:admin2_code":"177.0",
    "gn:asciiname":"Los Marias",
    "gn:country_code":"MX",
    "gn:dem":1992,
    "gn:feature_class":"P",
    "gn:feature_code":"PPL",
    "gn:name":"Los Mar\u00edas",
    "gn:population":651,
    "gn:timezone":"America/Mexico_City",
    "iso:country":"MX",
    "name:und_x_variant":[
        "Los Mar\u00edas"
    ],
    "wof:name":"Los Marias",
    "wof:placetype":"locality",
    "wof:population":651
},
  "geometry": {"coordinates":[-97.66249999999999,18.72139],"type":"Point"}
}