{
  "type": "Feature",
  "properties": {
    "gn:admin1_code":"18",
    "gn:admin2_code":"9",
    "gn:asciiname":"Las Tortugas",
    "gn:country_code":"MX",
    "gn:dem":2064,
    "gn:feature_class":"P",
    "gn:feature_code":"PPL",
    "gn:name":"Las Tortugas",
    "gn:population":18,
    "gn:timezone":"America/Mazatlan",
    "iso:country":"MX",
    "wof:name":"Las Tortugas",
    "wof:placetype":"locality",
    "wof:population":18
},
  "geometry": {"coordinates":[-104.73556000000001,22.51333],"type":"Point"}
}