{
  "type": "Feature",
  "properties": {
    "gn:admin1_code":"13",
    "gn:admin2_code":"37.0",
    "gn:asciiname":"Macuila",
    "gn:country_code":"MX",
    "gn:dem":1285,
    "gn:feature_class":"P",
    "gn:feature_code":"PPL",
    "gn:name":"Macuila",
    "gn:population":426,
    "gn:timezone":"America/Mexico_City",
    "iso:country":"MX",
    "wof:name":"Macuila",
    "wof:placetype":"locality",
    "wof:population":426
},
  "geometry": {"coordinates":[-98.80638999999999,20.6475],"type":"Point"}
}