{
  "type": "Feature",
  "properties": {
    "gn:admin1_code":"29",
    "gn:admin2_code":"12.0",
    "gn:asciiname":"Asilo de Ancianos San Judas Tadeo",
    "gn:country_code":"MX",
    "gn:dem":2535,
    "gn:feature_class":"P",
    "gn:feature_code":"PPL",
    "gn:name":"Asilo de Ancianos San Judas Tadeo",
    "gn:population":67,
    "gn:timezone":"America/Mexico_City",
    "iso:country":"MX",
    "wof:name":"Asilo de Ancianos San Judas Tadeo",
    "wof:placetype":"locality",
    "wof:population":67
},
  "geometry": {"coordinates":[-98.4085,19.43185],"type":"Point"}
}