{
  "type": "Feature",
  "properties": {
    "gn:admin1_code":"30",
    "gn:admin2_code":"144.0",
    "gn:asciiname":"El Suspiro",
    "gn:country_code":"MX",
    "gn:dem":33,
    "gn:feature_class":"P",
    "gn:feature_code":"PPL",
    "gn:name":"El Suspiro",
    "gn:population":57,
    "gn:timezone":"America/Mexico_City",
    "iso:country":"MX",
    "wof:name":"El Suspiro",
    "wof:placetype":"locality",
    "wof:population":57
},
  "geometry": {"coordinates":[-94.86389,17.62889],"type":"Point"}
}