{
  "type": "Feature",
  "properties": {
    "gn:admin1_code":"21",
    "gn:admin2_code":"66",
    "gn:asciiname":"Rincon Chiquito",
    "gn:country_code":"MX",
    "gn:dem":1185,
    "gn:feature_class":"P",
    "gn:feature_code":"PPL",
    "gn:name":"Rinc\u00f3n Chiquito",
    "gn:population":19,
    "gn:timezone":"America/Mexico_City",
    "iso:country":"MX",
    "name:und_x_variant":[
        "Rinc\u00f3n Chiquito"
    ],
    "wof:name":"Rincon Chiquito",
    "wof:placetype":"locality",
    "wof:population":19
},
  "geometry": {"coordinates":[-98.11163999999999,18.04604],"type":"Point"}
}