{
  "type": "Feature",
  "properties": {
    "gn:admin1_code":"28.0",
    "gn:admin2_code":"3.0",
    "gn:asciiname":"Mata del Blanco",
    "gn:country_code":"MX",
    "gn:dem":40,
    "gn:feature_class":"P",
    "gn:feature_code":"PPL",
    "gn:name":"Mata del Blanco",
    "gn:population":0,
    "gn:timezone":"America/Monterrey",
    "iso:country":"MX",
    "name:spa_x_preferred":[
        "Mata del Blanco"
    ],
    "wof:name":"Mata del Blanco",
    "wof:placetype":"locality"
},
  "geometry": {"coordinates":[-98.01168,22.52455],"type":"Point"}
}