{
  "type": "Feature",
  "properties": {
    "gn:admin1_code":"5",
    "gn:admin2_code":"22.0",
    "gn:asciiname":"Jolomtic",
    "gn:country_code":"MX",
    "gn:dem":1716,
    "gn:feature_class":"P",
    "gn:feature_code":"PPL",
    "gn:name":"Jolomtic",
    "gn:population":77,
    "gn:timezone":"America/Mexico_City",
    "iso:country":"MX",
    "wof:name":"Jolomtic",
    "wof:placetype":"locality",
    "wof:population":77
},
  "geometry": {"coordinates":[-92.65416999999999,17.01778],"type":"Point"}
}