{
  "type": "Feature",
  "properties": {
    "gn:admin1_code":"5.0",
    "gn:admin2_code":"107.0",
    "gn:asciiname":"Villalar",
    "gn:country_code":"MX",
    "gn:dem":1132,
    "gn:feature_class":"P",
    "gn:feature_code":"PPL",
    "gn:name":"Villal\u00e1r",
    "gn:population":0,
    "gn:timezone":"America/Mexico_City",
    "iso:country":"MX",
    "name:spa_x_preferred":[
        "Villalara"
    ],
    "name:spa_x_variant":[
        "Villal\u00e1r"
    ],
    "wof:name":"Villalar",
    "wof:placetype":"locality"
},
  "geometry": {"coordinates":[-93.38437,15.94816],"type":"Point"}
}