{
  "type": "Feature",
  "properties": {
    "gn:admin1_code":"18.0",
    "gn:admin2_code":"19.0",
    "gn:asciiname":"La Fundicion",
    "gn:country_code":"MX",
    "gn:dem":742,
    "gn:feature_class":"P",
    "gn:feature_code":"PPL",
    "gn:name":"La Fundici\u00f3n",
    "gn:population":0,
    "gn:timezone":"America/Mazatlan",
    "iso:country":"MX",
    "name:spa_x_preferred":[
        "La Fundici\u00f3n"
    ],
    "name:spa_x_variant":[
        "Fundici\u00f3n"
    ],
    "wof:name":"La Fundicion",
    "wof:placetype":"locality"
},
  "geometry": {"coordinates":[-104.33301,21.28551],"type":"Point"}
}