{
  "type": "Feature",
  "properties": {
    "gn:admin1_code":"18",
    "gn:admin2_code":"19.0",
    "gn:asciiname":"Cebolletas (El Maguey)",
    "gn:country_code":"MX",
    "gn:dem":2017,
    "gn:feature_class":"P",
    "gn:feature_code":"PPL",
    "gn:name":"Cebolletas (El Maguey)",
    "gn:population":116,
    "gn:timezone":"America/Mazatlan",
    "iso:country":"MX",
    "wof:name":"Cebolletas (El Maguey)",
    "wof:placetype":"locality",
    "wof:population":116
},
  "geometry": {"coordinates":[-104.24556,21.88222],"type":"Point"}
}