{
  "type": "Feature",
  "properties": {
    "gn:admin1_code":"10",
    "gn:admin2_code":"10.0",
    "gn:asciiname":"Las Playas",
    "gn:country_code":"MX",
    "gn:dem":1957,
    "gn:feature_class":"P",
    "gn:feature_code":"PPL",
    "gn:name":"Las Playas",
    "gn:population":154,
    "gn:timezone":"America/Monterrey",
    "iso:country":"MX",
    "name:spa_x_preferred":[
        "Las Playas"
    ],
    "wof:name":"Las Playas",
    "wof:placetype":"locality",
    "wof:population":154
},
  "geometry": {"coordinates":[-104.77290000000001,25.70079],"type":"Point"}
}