{
  "type": "Feature",
  "properties": {
    "gn:admin1_code":"32.0",
    "gn:admin2_code":"42.0",
    "gn:asciiname":"El Gato",
    "gn:country_code":"MX",
    "gn:dem":2365,
    "gn:feature_class":"P",
    "gn:feature_code":"PPL",
    "gn:name":"El Gato",
    "gn:population":0,
    "gn:timezone":"America/Mexico_City",
    "iso:country":"MX",
    "name:spa_x_preferred":[
        "El Gato"
    ],
    "wof:name":"El Gato",
    "wof:placetype":"locality"
},
  "geometry": {"coordinates":[-103.61035,23.26474],"type":"Point"}
}