{
  "type": "Feature",
  "properties": {
    "gn:admin1_code":"11",
    "gn:admin2_code":"20.0",
    "gn:asciiname":"San Jose de las Piletas (Cerro Gordo)",
    "gn:country_code":"MX",
    "gn:dem":1974,
    "gn:feature_class":"P",
    "gn:feature_code":"PPL",
    "gn:name":"San Jos\u00e9 de las Piletas (Cerro Gordo)",
    "gn:population":7,
    "gn:timezone":"America/Mexico_City",
    "iso:country":"MX",
    "name:und_x_variant":[
        "San Jos\u00e9 de las Piletas (Cerro Gordo)"
    ],
    "wof:name":"San Jose de las Piletas (Cerro Gordo)",
    "wof:placetype":"locality",
    "wof:population":7
},
  "geometry": {"coordinates":[-101.72278,21.15694],"type":"Point"}
}