{
  "type": "Feature",
  "properties": {
    "gn:admin1_code":"19.0",
    "gn:admin2_code":"5.0",
    "gn:asciiname":"Los Garza",
    "gn:country_code":"MX",
    "gn:dem":237,
    "gn:feature_class":"P",
    "gn:feature_code":"PPL",
    "gn:name":"Los Garza",
    "gn:population":1,
    "gn:timezone":"America/Matamoros",
    "iso:country":"MX",
    "name:spa_x_preferred":[
        "Los Garza"
    ],
    "wof:name":"Los Garza",
    "wof:placetype":"locality",
    "wof:population":1
},
  "geometry": {"coordinates":[-100.37451,27.41668],"type":"Point"}
}