{
  "type": "Feature",
  "properties": {
    "gn:admin1_code":"31",
    "gn:admin2_code":"1.0",
    "gn:asciiname":"Temozon Sur",
    "gn:country_code":"MX",
    "gn:dem":13,
    "gn:feature_class":"P",
    "gn:feature_code":"PPL",
    "gn:name":"Temozon Sur",
    "gn:population":0,
    "gn:timezone":"America/Merida",
    "iso:country":"MX",
    "name:und_x_variant":[
        "Temazon",
        "Temos\u00f3n",
        "Temozon Sur",
        "Temoz\u00f3n"
    ],
    "wof:name":"Temozon Sur",
    "wof:placetype":"locality"
},
  "geometry": {"coordinates":[-89.65316999999997,20.68726],"type":"Point"}
}