{
  "type": "Feature",
  "properties": {
    "gn:admin1_code":"5",
    "gn:admin2_code":"75",
    "gn:asciiname":"Los Nardos",
    "gn:country_code":"MX",
    "gn:dem":1099,
    "gn:feature_class":"P",
    "gn:feature_code":"PPL",
    "gn:name":"Los Nardos",
    "gn:population":9,
    "gn:timezone":"America/Mexico_City",
    "iso:country":"MX",
    "wof:name":"Los Nardos",
    "wof:placetype":"locality",
    "wof:population":9
},
  "geometry": {"coordinates":[-92.40472,16.34667],"type":"Point"}
}