{
  "type": "Feature",
  "properties": {
    "gn:admin1_code":"6",
    "gn:admin2_code":"30.0",
    "gn:asciiname":"La Bavisa",
    "gn:country_code":"MX",
    "gn:dem":1536,
    "gn:feature_class":"P",
    "gn:feature_code":"PPL",
    "gn:name":"La Bavisa",
    "gn:population":4,
    "gn:timezone":"America/Chihuahua",
    "iso:country":"MX",
    "wof:name":"La Bavisa",
    "wof:placetype":"locality",
    "wof:population":4
},
  "geometry": {"coordinates":[-108.35178999999999,27.36214],"type":"Point"}
}