{
  "type": "Feature",
  "properties": {
    "gn:admin1_code":"20",
    "gn:admin2_code":"446.0",
    "gn:asciiname":"Mal Paso",
    "gn:country_code":"MX",
    "gn:dem":1867,
    "gn:feature_class":"P",
    "gn:feature_code":"PPL",
    "gn:name":"Mal Paso",
    "gn:population":84,
    "gn:timezone":"America/Mexico_City",
    "iso:country":"MX",
    "wof:name":"Mal Paso",
    "wof:placetype":"locality",
    "wof:population":84
},
  "geometry": {"coordinates":[-97.7975,17.01194],"type":"Point"}
}