{
  "type": "Feature",
  "properties": {
    "gn:admin1_code":"24",
    "gn:admin2_code":"54.0",
    "gn:asciiname":"Llano San Isidro",
    "gn:country_code":"MX",
    "gn:dem":1941,
    "gn:feature_class":"P",
    "gn:feature_code":"PPL",
    "gn:name":"Llano San Isidro",
    "gn:population":0,
    "gn:timezone":"America/Mexico_City",
    "iso:country":"MX",
    "name:spa_x_preferred":[
        "Llano San Isidro"
    ],
    "wof:name":"Llano San Isidro",
    "wof:placetype":"locality"
},
  "geometry": {"coordinates":[-99.071,21.40609],"type":"Point"}
}