{
  "type": "Feature",
  "properties": {
    "gn:admin1_code":"31",
    "gn:admin2_code":"96.0",
    "gn:asciiname":"Xculucmul",
    "gn:country_code":"MX",
    "gn:dem":15,
    "gn:feature_class":"P",
    "gn:feature_code":"PPL",
    "gn:name":"Xculucmul",
    "gn:population":0,
    "gn:timezone":"America/Merida",
    "iso:country":"MX",
    "name:und_x_variant":[
        "Xculucu",
        "Xculucmul"
    ],
    "wof:name":"Xculucmul",
    "wof:placetype":"locality"
},
  "geometry": {"coordinates":[-88.0513,21.12038],"type":"Point"}
}