{
  "type": "Feature",
  "properties": {
    "gn:admin1_code":"13",
    "gn:admin2_code":"37.0",
    "gn:asciiname":"Potrero de Camacho",
    "gn:country_code":"MX",
    "gn:dem":1303,
    "gn:feature_class":"P",
    "gn:feature_code":"PPL",
    "gn:name":"Potrero de Camacho",
    "gn:population":53,
    "gn:timezone":"America/Mexico_City",
    "iso:country":"MX",
    "wof:name":"Potrero de Camacho",
    "wof:placetype":"locality",
    "wof:population":53
},
  "geometry": {"coordinates":[-98.71250000000001,20.50389],"type":"Point"}
}