{
  "type": "Feature",
  "properties": {
    "gn:admin1_code":"19",
    "gn:admin2_code":"12.0",
    "gn:asciiname":"Maria Luisa",
    "gn:country_code":"MX",
    "gn:dem":411,
    "gn:feature_class":"P",
    "gn:feature_code":"PPL",
    "gn:name":"Mar\u00eda Luisa",
    "gn:population":5,
    "gn:timezone":"America/Monterrey",
    "iso:country":"MX",
    "name:und_x_variant":[
        "Mar\u00eda Luisa"
    ],
    "wof:name":"Maria Luisa",
    "wof:placetype":"locality",
    "wof:population":5
},
  "geometry": {"coordinates":[-100.18083,25.94056],"type":"Point"}
}