{
  "type": "Feature",
  "properties": {
    "gn:admin1_code":"12.0",
    "gn:admin2_code":"22.0",
    "gn:asciiname":"La Mastranza",
    "gn:country_code":"MX",
    "gn:dem":290,
    "gn:feature_class":"P",
    "gn:feature_code":"PPL",
    "gn:name":"La Mastranza",
    "gn:population":0,
    "gn:timezone":"America/Mexico_City",
    "iso:country":"MX",
    "name:spa_x_preferred":[
        "La Mastranza"
    ],
    "wof:name":"La Mastranza",
    "wof:placetype":"locality"
},
  "geometry": {"coordinates":[-100.73544,18.26019],"type":"Point"}
}