{
  "type": "Feature",
  "properties": {
    "gn:admin1_code":"5",
    "gn:admin2_code":"69",
    "gn:asciiname":"Los Laureles (Las Delicias)",
    "gn:country_code":"MX",
    "gn:dem":29,
    "gn:feature_class":"P",
    "gn:feature_code":"PPL",
    "gn:name":"Los Laureles (Las Delicias)",
    "gn:population":11,
    "gn:timezone":"America/Mexico_City",
    "iso:country":"MX",
    "wof:name":"Los Laureles (Las Delicias)",
    "wof:placetype":"locality",
    "wof:population":11
},
  "geometry": {"coordinates":[-93.30972,15.73056],"type":"Point"}
}