{
  "type": "Feature",
  "properties": {
    "gn:admin1_code":"26.0",
    "gn:admin2_code":"26.0",
    "gn:asciiname":"El Centenario",
    "gn:country_code":"MX",
    "gn:dem":29,
    "gn:feature_class":"P",
    "gn:feature_code":"PPL",
    "gn:name":"El Centenario",
    "gn:population":447,
    "gn:timezone":"America/Hermosillo",
    "iso:country":"MX",
    "wof:name":"El Centenario",
    "wof:placetype":"locality",
    "wof:population":447
},
  "geometry": {"coordinates":[-109.55837,27.0638],"type":"Point"}
}