{
  "type": "Feature",
  "properties": {
    "gn:admin1_code":"19",
    "gn:admin2_code":"33.0",
    "gn:asciiname":"El Guajolote",
    "gn:country_code":"MX",
    "gn:dem":360,
    "gn:feature_class":"P",
    "gn:feature_code":"PPL",
    "gn:name":"El Guajolote",
    "gn:population":0,
    "gn:timezone":"America/Monterrey",
    "iso:country":"MX",
    "name:spa_x_preferred":[
        "El Guajolote"
    ],
    "wof:name":"El Guajolote",
    "wof:placetype":"locality"
},
  "geometry": {"coordinates":[-99.53386,24.67753],"type":"Point"}
}