{
  "type": "Feature",
  "properties": {
    "gn:admin1_code":"14.0",
    "gn:admin2_code":"94.0",
    "gn:asciiname":"Los Landero",
    "gn:country_code":"MX",
    "gn:dem":1454,
    "gn:feature_class":"P",
    "gn:feature_code":"PPL",
    "gn:name":"Los Landero",
    "gn:population":0,
    "gn:timezone":"America/Mexico_City",
    "iso:country":"MX",
    "name:spa_x_preferred":[
        "Los Landero"
    ],
    "wof:name":"Los Landero",
    "wof:placetype":"locality"
},
  "geometry": {"coordinates":[-103.67898,20.95497],"type":"Point"}
}