{
  "type": "Feature",
  "properties": {
    "gn:admin1_code":"16",
    "gn:admin2_code":"50.0",
    "gn:asciiname":"La Hormiga",
    "gn:country_code":"MX",
    "gn:dem":2075,
    "gn:feature_class":"P",
    "gn:feature_code":"PPL",
    "gn:name":"La Hormiga",
    "gn:population":133,
    "gn:timezone":"America/Mexico_City",
    "iso:country":"MX",
    "wof:name":"La Hormiga",
    "wof:placetype":"locality",
    "wof:population":133
},
  "geometry": {"coordinates":[-100.30611,19.88222],"type":"Point"}
}