{
  "type": "Feature",
  "properties": {
    "gn:admin1_code":"25.0",
    "gn:admin2_code":"14.0",
    "gn:asciiname":"Cacalotan",
    "gn:country_code":"MX",
    "gn:dem":39,
    "gn:feature_class":"P",
    "gn:feature_code":"PPL",
    "gn:name":"Cacalot\u00e1n",
    "gn:population":0,
    "gn:timezone":"America/Mazatlan",
    "iso:country":"MX",
    "wof:name":"Cacalotan",
    "wof:placetype":"locality"
},
  "geometry": {"coordinates":[-105.84193999999999,23.06779],"type":"Point"}
}