{
  "type": "Feature",
  "properties": {
    "gn:admin1_code":"2",
    "gn:admin2_code":"1",
    "gn:asciiname":"Las Cebollas",
    "gn:country_code":"MX",
    "gn:dem":18,
    "gn:feature_class":"P",
    "gn:feature_code":"PPL",
    "gn:name":"Las Cebollas",
    "gn:population":22,
    "gn:timezone":"America/Tijuana",
    "iso:country":"MX",
    "wof:name":"Las Cebollas",
    "wof:placetype":"locality",
    "wof:population":22
},
  "geometry": {"coordinates":[-115.96306,30.57],"type":"Point"}
}