{
  "type": "Feature",
  "properties": {
    "gn:admin1_code":"23",
    "gn:admin2_code":"1.0",
    "gn:asciiname":"Plantas y Jardines",
    "gn:country_code":"MX",
    "gn:dem":7,
    "gn:feature_class":"P",
    "gn:feature_code":"PPL",
    "gn:name":"Plantas y Jardines",
    "gn:population":9,
    "gn:timezone":"America/Cancun",
    "iso:country":"MX",
    "wof:name":"Plantas y Jardines",
    "wof:placetype":"locality",
    "wof:population":9
},
  "geometry": {"coordinates":[-86.92233,20.48901],"type":"Point"}
}