{
  "type": "Feature",
  "properties": {
    "gn:admin1_code":"10",
    "gn:admin2_code":"14",
    "gn:asciiname":"Se Uan Tio",
    "gn:country_code":"MX",
    "gn:dem":1600,
    "gn:feature_class":"P",
    "gn:feature_code":"PPL",
    "gn:name":"Se Uan Tio",
    "gn:population":13,
    "gn:timezone":"America/Monterrey",
    "iso:country":"MX",
    "wof:name":"Se Uan Tio",
    "wof:placetype":"locality",
    "wof:population":13
},
  "geometry": {"coordinates":[-104.71775,23.10503],"type":"Point"}
}