{
  "type": "Feature",
  "properties": {
    "gn:admin1_code":"10",
    "gn:admin2_code":"14",
    "gn:asciiname":"Las Manzanas",
    "gn:country_code":"MX",
    "gn:dem":2320,
    "gn:feature_class":"P",
    "gn:feature_code":"PPL",
    "gn:name":"Las Manzanas",
    "gn:population":11,
    "gn:timezone":"America/Monterrey",
    "iso:country":"MX",
    "wof:name":"Las Manzanas",
    "wof:placetype":"locality",
    "wof:population":11
},
  "geometry": {"coordinates":[-104.50606999999999,22.84948],"type":"Point"}
}