{
  "type": "Feature",
  "properties": {
    "gn:admin1_code":"5",
    "gn:admin2_code":"80.0",
    "gn:asciiname":"Los Girasoles",
    "gn:country_code":"MX",
    "gn:dem":1459,
    "gn:feature_class":"P",
    "gn:feature_code":"PPL",
    "gn:name":"Los Girasoles",
    "gn:population":7,
    "gn:timezone":"America/Mexico_City",
    "iso:country":"MX",
    "wof:name":"Los Girasoles",
    "wof:placetype":"locality",
    "wof:population":7
},
  "geometry": {"coordinates":[-92.59332999999999,15.54778],"type":"Point"}
}