{
  "type": "Feature",
  "properties": {
    "gn:admin1_code":"21.0",
    "gn:admin2_code":"176.0",
    "gn:asciiname":"Ballinas",
    "gn:country_code":"MX",
    "gn:dem":1269,
    "gn:feature_class":"P",
    "gn:feature_code":"PPL",
    "gn:name":"Ballinas",
    "gn:population":0,
    "gn:timezone":"America/Mexico_City",
    "iso:country":"MX",
    "name:spa_x_preferred":[
        "Ballinas"
    ],
    "wof:name":"Ballinas",
    "wof:placetype":"locality"
},
  "geometry": {"coordinates":[-98.56914999999999,18.62306],"type":"Point"}
}