{
  "type": "Feature",
  "properties": {
    "gn:admin1_code":"6.0",
    "gn:asciiname":"Granja la Flor",
    "gn:country_code":"MX",
    "gn:dem":1149,
    "gn:feature_class":"P",
    "gn:feature_code":"PPL",
    "gn:name":"Granja la Flor",
    "gn:population":0,
    "gn:timezone":"America/Chihuahua",
    "iso:country":"MX",
    "name:spa_x_preferred":[
        "Granja la Flor"
    ],
    "name:spa_x_variant":[
        "La Flor"
    ],
    "wof:name":"Granja la Flor",
    "wof:placetype":"locality"
},
  "geometry": {"coordinates":[-105.39054,28.28498],"type":"Point"}
}