{
  "type": "Feature",
  "properties": {
    "gn:admin1_code":"25",
    "gn:admin2_code":"6.0",
    "gn:asciiname":"Lopez Mateos",
    "gn:country_code":"MX",
    "gn:dem":36,
    "gn:feature_class":"P",
    "gn:feature_code":"PPL",
    "gn:name":"L\u00f3pez Mateos",
    "gn:population":0,
    "gn:timezone":"America/Mazatlan",
    "iso:country":"MX",
    "name:und_x_variant":[
        "L\u00f3pez Mateos",
        "Casa Blanca"
    ],
    "wof:name":"Lopez Mateos",
    "wof:placetype":"locality"
},
  "geometry": {"coordinates":[-107.11546,24.25834],"type":"Point"}
}