{
  "type": "Feature",
  "properties": {
    "gn:admin1_code":"30.0",
    "gn:admin2_code":"172.0",
    "gn:asciiname":"San Francisco Tatagapa",
    "gn:country_code":"MX",
    "gn:dem":10,
    "gn:feature_class":"P",
    "gn:feature_code":"PPL",
    "gn:name":"San Francisco Tatagapa",
    "gn:population":0,
    "gn:timezone":"America/Mexico_City",
    "iso:country":"MX",
    "name:spa_x_preferred":[
        "San Francisco Tatagapa"
    ],
    "wof:name":"San Francisco Tatagapa",
    "wof:placetype":"locality"
},
  "geometry": {"coordinates":[-94.81559,17.72792],"type":"Point"}
}