{
  "type": "Feature",
  "properties": {
    "gn:admin1_code":"26.0",
    "gn:admin2_code":"64.0",
    "gn:asciiname":"Arituaba",
    "gn:country_code":"MX",
    "gn:dem":532,
    "gn:feature_class":"P",
    "gn:feature_code":"PPL",
    "gn:name":"Arituaba",
    "gn:population":0,
    "gn:timezone":"America/Hermosillo",
    "iso:country":"MX",
    "name:und_x_variant":[
        "Arituava",
        "Ejido Arituaba"
    ],
    "wof:name":"Arituaba",
    "wof:placetype":"locality"
},
  "geometry": {"coordinates":[-111.4667,30.38813],"type":"Point"}
}