{
  "type": "Feature",
  "properties": {
    "gn:admin1_code":"20",
    "gn:admin2_code":"3",
    "gn:asciiname":"Camino al Albergue",
    "gn:country_code":"MX",
    "gn:dem":1867,
    "gn:feature_class":"P",
    "gn:feature_code":"PPL",
    "gn:name":"Camino al Albergue",
    "gn:population":30,
    "gn:timezone":"America/Mexico_City",
    "iso:country":"MX",
    "wof:name":"Camino al Albergue",
    "wof:placetype":"locality",
    "wof:population":30
},
  "geometry": {"coordinates":[-95.94833,17.03722],"type":"Point"}
}