{
  "type": "Feature",
  "properties": {
    "gn:admin1_code":"18.0",
    "gn:admin2_code":"19.0",
    "gn:asciiname":"El Cepo",
    "gn:country_code":"MX",
    "gn:dem":1787,
    "gn:feature_class":"P",
    "gn:feature_code":"PPL",
    "gn:name":"El Cepo",
    "gn:population":0,
    "gn:timezone":"America/Mazatlan",
    "iso:country":"MX",
    "wof:name":"El Cepo",
    "wof:placetype":"locality"
},
  "geometry": {"coordinates":[-104.1871,21.67999],"type":"Point"}
}