{
  "type": "Feature",
  "properties": {
    "gn:admin1_code":"20",
    "gn:admin2_code":"511",
    "gn:asciiname":"Joya de Mazorca",
    "gn:country_code":"MX",
    "gn:dem":2273,
    "gn:feature_class":"P",
    "gn:feature_code":"PPL",
    "gn:name":"Joya de Mazorca",
    "gn:population":52,
    "gn:timezone":"America/Mexico_City",
    "iso:country":"MX",
    "wof:name":"Joya de Mazorca",
    "wof:placetype":"locality",
    "wof:population":52
},
  "geometry": {"coordinates":[-97.04722,17.1675],"type":"Point"}
}