{
  "type": "Feature",
  "properties": {
    "gn:admin1_code":"3",
    "gn:admin2_code":"1.0",
    "gn:asciiname":"Valenzuela",
    "gn:country_code":"MX",
    "gn:dem":336,
    "gn:feature_class":"P",
    "gn:feature_code":"PPL",
    "gn:name":"Valenzuela",
    "gn:population":5,
    "gn:timezone":"America/Mazatlan",
    "iso:country":"MX",
    "wof:name":"Valenzuela",
    "wof:placetype":"locality",
    "wof:population":5
},
  "geometry": {"coordinates":[-111.15325,25.38078],"type":"Point"}
}