{
  "type": "Feature",
  "properties": {
    "gn:admin1_code":"3",
    "gn:admin2_code":"1.0",
    "gn:asciiname":"Valenzuela",
    "gn:country_code":"MX",
    "gn:dem":336,
    "gn:feature_class":"P",
    "gn:feature_code":"PPL",
    "gn:name":"Valenzuela",
    "gn:population":5,
    "gn:timezone":"America/Mazatlan",
    "iso:country":"MX",
    "name:bcl_x_preferred":[
        "Valenzuela"
    ],
    "name:ceb_x_preferred":[
        "Valenzuela"
    ],
    "name:deu_x_preferred":[
        "Valenzuela"
    ],
    "name:epo_x_preferred":[
        "Valenzuela"
    ],
    "name:fra_x_preferred":[
        "Valenzuela"
    ],
    "name:glg_x_preferred":[
        "Valenzuela"
    ],
    "name:hun_x_preferred":[
        "Valenzuela"
    ],
    "name:ita_x_preferred":[
        "Valenzuela"
    ],
    "name:jpn_x_preferred":[
        "\u30d0\u30ec\u30f3\u30ba\u30a8\u30e9"
    ],
    "name:nld_x_preferred":[
        "Valenzuela"
    ],
    "name:pam_x_preferred":[
        "Valenzuela Lakanbalen"
    ],
    "name:pol_x_preferred":[
        "Valenzuela"
    ],
    "name:por_x_preferred":[
        "Valenzuela"
    ],
    "name:rus_x_preferred":[
        "\u0412\u0430\u043b\u0435\u043d\u0441\u0443\u044d\u043b\u0430"
    ],
    "name:spa_x_preferred":[
        "Valenzuela"
    ],
    "name:swe_x_preferred":[
        "Valenzuela"
    ],
    "name:vie_x_preferred":[
        "Valenzuela"
    ],
    "name:war_x_preferred":[
        "Valenzuela"
    ],
    "wof:name":"Valenzuela",
    "wof:placetype":"locality",
    "wof:population":5
},
  "geometry": {"coordinates":[-111.15325,25.38078],"type":"Point"}
}