{
  "type": "Feature",
  "properties": {
    "gn:admin1_code":"23.0",
    "gn:asciiname":"Balche",
    "gn:country_code":"MX",
    "gn:dem":32,
    "gn:feature_class":"P",
    "gn:feature_code":"PPL",
    "gn:name":"Balch\u00e9",
    "gn:population":0,
    "gn:timezone":"America/Cancun",
    "iso:country":"MX",
    "name:spa_x_preferred":[
        "Balch\u00e9"
    ],
    "wof:name":"Balche",
    "wof:placetype":"locality"
},
  "geometry": {"coordinates":[-88.18857,20.23134],"type":"Point"}
}