{
  "type": "Feature",
  "properties": {
    "gn:admin1_code":"7.0",
    "gn:admin2_code":"13.0",
    "gn:asciiname":"El Chupadero",
    "gn:country_code":"MX",
    "gn:dem":189,
    "gn:feature_class":"P",
    "gn:feature_code":"PPL",
    "gn:name":"El Chupadero",
    "gn:population":6,
    "gn:timezone":"America/Monterrey",
    "iso:country":"MX",
    "name:spa_x_preferred":[
        "Chupaderos"
    ],
    "wof:name":"El Chupadero",
    "wof:placetype":"locality",
    "wof:population":6
},
  "geometry": {"coordinates":[-99.94117,27.86555],"type":"Point"}
}