{
  "type": "Feature",
  "properties": {
    "gn:admin1_code":"32",
    "gn:admin2_code":"21.0",
    "gn:asciiname":"La Higuera",
    "gn:country_code":"MX",
    "gn:dem":1738,
    "gn:feature_class":"P",
    "gn:feature_code":"PPL",
    "gn:name":"La Higuera",
    "gn:population":0,
    "gn:timezone":"America/Mexico_City",
    "iso:country":"MX",
    "name:ara_x_preferred":[
        "\u0644\u0627 \u0647\u064a\u063a\u0648\u064a\u0631\u0627"
    ],
    "name:arg_x_preferred":[
        "La Higuera"
    ],
    "name:ben_x_preferred":[
        "\u09b2\u09be \u09b9\u09bf\u0997\u09c1\u09af\u09bc\u09c7\u09b0\u09be"
    ],
    "name:bul_x_preferred":[
        "\u041b\u0430 \u0418\u0433\u0435\u0440\u0430"
    ],
    "name:cat_x_preferred":[
        "La Higuera"
    ],
    "name:ceb_x_preferred":[
        "La Higuera"
    ],
    "name:deu_x_preferred":[
        "La Higuera"
    ],
    "name:ell_x_preferred":[
        "\u039b\u03b1 \u0399\u03b3\u03ba\u03ad\u03c1\u03b1"
    ],
    "name:epo_x_preferred":[
        "La Higuera"
    ],
    "name:fas_x_preferred":[
        "\u0644\u0627 \u0627\u06cc\u06af\u0631\u0627"
    ],
    "name:fin_x_preferred":[
        "La Higuera"
    ],
    "name:fra_x_preferred":[
        "La Higuera"
    ],
    "name:glg_x_preferred":[
        "La Higuera"
    ],
    "name:hun_x_preferred":[
        "La Higuera"
    ],
    "name:ind_x_preferred":[
        "La Higuera"
    ],
    "name:ita_x_preferred":[
        "La Higuera"
    ],
    "name:jpn_x_preferred":[
        "\u30a4\u30b2\u30e9"
    ],
    "name:kat_x_preferred":[
        "\u10da\u10d0-\u10d8\u10d2\u10d4\u10e0\u10d0"
    ],
    "name:lit_x_preferred":[
        "La Igera"
    ],
    "name:nld_x_preferred":[
        "La Higuera"
    ],
    "name:nor_x_preferred":[
        "La Higuera"
    ],
    "name:oss_x_preferred":[
        "\u041b\u0430-\u0418\u0433\u0435\u0440\u00e6"
    ],
    "name:pol_x_preferred":[
        "La Higuera"
    ],
    "name:por_x_preferred":[
        "La Higuera"
    ],
    "name:que_x_preferred":[
        "La Higuera"
    ],
    "name:ron_x_preferred":[
        "La Higuera"
    ],
    "name:rus_x_preferred":[
        "\u041b\u0430-\u0418\u0433\u0435\u0440\u0430"
    ],
    "name:scn_x_preferred":[
        "La Higuera"
    ],
    "name:spa_x_preferred":[
        "La Higuera"
    ],
    "name:swe_x_preferred":[
        "La Higuera"
    ],
    "name:tur_x_preferred":[
        "La Higuera"
    ],
    "name:ukr_x_preferred":[
        "\u0413\u0415\u0421 \u041b\u0430-\u0406\u0433\u0435\u0440\u0430"
    ],
    "name:urd_x_preferred":[
        "\u0644\u0627 \u06c1\u06cc\u06af\u0648\u06cc\u0631\u0627"
    ],
    "name:vec_x_preferred":[
        "La Higuera"
    ],
    "name:zho_x_preferred":[
        "\u62c9\u4f0a\u683c\u62c9"
    ],
    "wof:name":"La Higuera",
    "wof:placetype":"locality"
},
  "geometry": {"coordinates":[-104.05184,23.05684],"type":"Point"}
}