{
  "type": "Feature",
  "properties": {
    "gn:admin1_code":"26",
    "gn:admin2_code":"55.0",
    "gn:asciiname":"Flor del Desierto",
    "gn:country_code":"MX",
    "gn:dem":111,
    "gn:feature_class":"P",
    "gn:feature_code":"PPL",
    "gn:name":"Flor del Desierto",
    "gn:population":5,
    "gn:timezone":"America/Hermosillo",
    "iso:country":"MX",
    "wof:name":"Flor del Desierto",
    "wof:placetype":"locality",
    "wof:population":5
},
  "geometry": {"coordinates":[-114.42889,32.37306],"type":"Point"}
}