{
  "type": "Feature",
  "properties": {
    "gn:admin1_code":"6.0",
    "gn:admin2_code":"66.0",
    "gn:asciiname":"El Mirasol",
    "gn:country_code":"MX",
    "gn:dem":1259,
    "gn:feature_class":"P",
    "gn:feature_code":"PPL",
    "gn:name":"El Mirasol",
    "gn:population":0,
    "gn:timezone":"America/Chihuahua",
    "iso:country":"MX",
    "name:spa_x_preferred":[
        "El Mirasol"
    ],
    "wof:name":"El Mirasol",
    "wof:placetype":"locality"
},
  "geometry": {"coordinates":[-108.29808,27.78188],"type":"Point"}
}