{
  "type": "Feature",
  "properties": {
    "gn:admin1_code":"9",
    "gn:admin2_code":"12.0",
    "gn:asciiname":"Kilometro 28 Sur",
    "gn:country_code":"MX",
    "gn:dem":2759,
    "gn:feature_class":"P",
    "gn:feature_code":"PPL",
    "gn:name":"Kil\u00f3metro 28 Sur",
    "gn:population":232,
    "gn:timezone":"America/Mexico_City",
    "iso:country":"MX",
    "name:und_x_variant":[
        "Kil\u00f3metro 28 Sur"
    ],
    "wof:name":"Kilometro 28 Sur",
    "wof:placetype":"locality",
    "wof:population":232
},
  "geometry": {"coordinates":[-99.15167,19.2125],"type":"Point"}
}