{
  "type": "Feature",
  "properties": {
    "gn:admin1_code":"5",
    "gn:admin2_code":"79.0",
    "gn:asciiname":"El Carmelo",
    "gn:country_code":"MX",
    "gn:dem":847,
    "gn:feature_class":"P",
    "gn:feature_code":"PPL",
    "gn:name":"El Carmelo",
    "gn:population":730,
    "gn:timezone":"America/Mexico_City",
    "iso:country":"MX",
    "wof:name":"El Carmelo",
    "wof:placetype":"locality",
    "wof:population":730
},
  "geometry": {"coordinates":[-93.12056,16.93194],"type":"Point"}
}