{
  "type": "Feature",
  "properties": {
    "gn:admin1_code":"20.0",
    "gn:asciiname":"Arroyo Culebra el Puente",
    "gn:country_code":"MX",
    "gn:dem":106,
    "gn:feature_class":"P",
    "gn:feature_code":"PPL",
    "gn:name":"Arroyo Culebra el Puente",
    "gn:population":0,
    "gn:timezone":"America/Mexico_City",
    "iso:country":"MX",
    "name:spa_x_preferred":[
        "Arroyo Culebra el Puente"
    ],
    "name:spa_x_variant":[
        "Arroyo Culebra del Puente"
    ],
    "wof:name":"Arroyo Culebra el Puente",
    "wof:placetype":"locality"
},
  "geometry": {"coordinates":[-96.45355000000001,18.06294],"type":"Point"}
}