{
  "type": "Feature",
  "properties": {
    "gn:admin1_code":"24.0",
    "gn:admin2_code":"24.0",
    "gn:asciiname":"La Puerta de la Garrapatilla",
    "gn:country_code":"MX",
    "gn:dem":1032,
    "gn:feature_class":"P",
    "gn:feature_code":"PPL",
    "gn:name":"La Puerta de la Garrapatilla",
    "gn:population":0,
    "gn:timezone":"America/Mexico_City",
    "iso:country":"MX",
    "name:spa_x_preferred":[
        "La Puerta de la Garrapatilla"
    ],
    "wof:name":"La Puerta de la Garrapatilla",
    "wof:placetype":"locality"
},
  "geometry": {"coordinates":[-100.06193,21.86746],"type":"Point"}
}