{
  "type": "Feature",
  "properties": {
    "gn:admin1_code":"20",
    "gn:admin2_code":"459.0",
    "gn:asciiname":"Sociedad Gutierrez (Sociedad Agricola)",
    "gn:country_code":"MX",
    "gn:dem":1739,
    "gn:feature_class":"P",
    "gn:feature_code":"PPL",
    "gn:name":"Sociedad Guti\u00e9rrez (Sociedad Agr\u00edcola)",
    "gn:population":8,
    "gn:timezone":"America/Mexico_City",
    "iso:country":"MX",
    "name:und_x_variant":[
        "Sociedad Guti\u00e9rrez (Sociedad Agr\u00edcola)"
    ],
    "wof:name":"Sociedad Gutierrez (Sociedad Agricola)",
    "wof:placetype":"locality",
    "wof:population":8
},
  "geometry": {"coordinates":[-97.69777999999999,18.18611],"type":"Point"}
}