{
  "type": "Feature",
  "properties": {
    "gn:admin1_code":"18.0",
    "gn:admin2_code":"4.0",
    "gn:asciiname":"El Embocadero",
    "gn:country_code":"MX",
    "gn:dem":920,
    "gn:feature_class":"P",
    "gn:feature_code":"PPL",
    "gn:name":"El Embocadero",
    "gn:population":0,
    "gn:timezone":"America/Mazatlan",
    "iso:country":"MX",
    "wof:name":"El Embocadero",
    "wof:placetype":"locality"
},
  "geometry": {"coordinates":[-104.90158,21.18177],"type":"Point"}
}