{
  "type": "Feature",
  "properties": {
    "gn:admin1_code":"5",
    "gn:admin2_code":"51.0",
    "gn:asciiname":"El Bajio",
    "gn:country_code":"MX",
    "gn:dem":6,
    "gn:feature_class":"P",
    "gn:feature_code":"PPL",
    "gn:name":"El Baj\u00edo",
    "gn:population":5,
    "gn:timezone":"America/Mexico_City",
    "iso:country":"MX",
    "name:und_x_variant":[
        "El Baj\u00edo"
    ],
    "wof:name":"El Bajio",
    "wof:placetype":"locality",
    "wof:population":5
},
  "geometry": {"coordinates":[-93.05889000000001,15.36028],"type":"Point"}
}