{
  "type": "Feature",
  "properties": {
    "gn:admin1_code":"20",
    "gn:admin2_code":"348.0",
    "gn:asciiname":"San Jose el Espinal",
    "gn:country_code":"MX",
    "gn:dem":2096,
    "gn:feature_class":"P",
    "gn:feature_code":"PPL",
    "gn:name":"San Jos\u00e9 el Espinal",
    "gn:population":106,
    "gn:timezone":"America/Mexico_City",
    "iso:country":"MX",
    "name:und_x_variant":[
        "San Jos\u00e9 el Espinal"
    ],
    "wof:name":"San Jose el Espinal",
    "wof:placetype":"locality",
    "wof:population":106
},
  "geometry": {"coordinates":[-98.05249999999999,17.44722],"type":"Point"}
}