{
  "type": "Feature",
  "properties": {
    "gn:admin1_code":"16",
    "gn:admin2_code":"79.0",
    "gn:asciiname":"La Cruz",
    "gn:country_code":"MX",
    "gn:dem":2151,
    "gn:feature_class":"P",
    "gn:feature_code":"PPL",
    "gn:name":"La Cruz",
    "gn:population":72,
    "gn:timezone":"America/Mexico_City",
    "iso:country":"MX",
    "wof:name":"La Cruz",
    "wof:placetype":"locality",
    "wof:population":72
},
  "geometry": {"coordinates":[-101.69,19.40972],"type":"Point"}
}