{
  "type": "Feature",
  "properties": {
    "gn:admin1_code":"11",
    "gn:admin2_code":"7",
    "gn:asciiname":"Jesus Barroso (Santa Teresita)",
    "gn:country_code":"MX",
    "gn:dem":1759,
    "gn:feature_class":"P",
    "gn:feature_code":"PPL",
    "gn:name":"Jes\u00fas Barroso (Santa Teresita)",
    "gn:population":10,
    "gn:timezone":"America/Mexico_City",
    "iso:country":"MX",
    "name:und_x_variant":[
        "Jes\u00fas Barroso (Santa Teresita)"
    ],
    "wof:name":"Jesus Barroso (Santa Teresita)",
    "wof:placetype":"locality",
    "wof:population":10
},
  "geometry": {"coordinates":[-100.76472,20.53778],"type":"Point"}
}