{
  "type": "Feature",
  "properties": {
    "gn:admin1_code":"12",
    "gn:admin2_code":"32.0",
    "gn:asciiname":"El Nanche",
    "gn:country_code":"MX",
    "gn:dem":1124,
    "gn:feature_class":"P",
    "gn:feature_code":"PPL",
    "gn:name":"El Nanche",
    "gn:population":80,
    "gn:timezone":"America/Mexico_City",
    "iso:country":"MX",
    "wof:name":"El Nanche",
    "wof:placetype":"locality",
    "wof:population":80
},
  "geometry": {"coordinates":[-100.16235,17.98544],"type":"Point"}
}