{
  "type": "Feature",
  "properties": {
    "gn:admin1_code":"10",
    "gn:admin2_code":"14",
    "gn:asciiname":"La Guacamaya",
    "gn:country_code":"MX",
    "gn:dem":907,
    "gn:feature_class":"P",
    "gn:feature_code":"PPL",
    "gn:name":"La Guacamaya",
    "gn:population":27,
    "gn:timezone":"America/Monterrey",
    "iso:country":"MX",
    "wof:name":"La Guacamaya",
    "wof:placetype":"locality",
    "wof:population":27
},
  "geometry": {"coordinates":[-104.88691,22.74059],"type":"Point"}
}