{
  "type": "Feature",
  "properties": {
    "gn:admin1_code":"26",
    "gn:admin2_code":"61.0",
    "gn:asciiname":"San Jose El Carrizo",
    "gn:country_code":"MX",
    "gn:dem":1004,
    "gn:feature_class":"P",
    "gn:feature_code":"PPL",
    "gn:name":"San Jos\u00e9 El Carrizo",
    "gn:population":0,
    "gn:timezone":"America/Hermosillo",
    "iso:country":"MX",
    "wof:name":"San Jose El Carrizo",
    "wof:placetype":"locality"
},
  "geometry": {"coordinates":[-109.6751,28.88662],"type":"Point"}
}