{
  "type": "Feature",
  "properties": {
    "gn:admin1_code":"7",
    "gn:admin2_code":"14.0",
    "gn:asciiname":"Nuevo Miravalle",
    "gn:country_code":"MX",
    "gn:dem":334,
    "gn:feature_class":"P",
    "gn:feature_code":"PPL",
    "gn:name":"Nuevo Miravalle",
    "gn:population":0,
    "gn:timezone":"America/Matamoros",
    "iso:country":"MX",
    "name:spa_x_preferred":[
        "Nuevo Miravalle"
    ],
    "name:und_x_variant":[
        "Nueva Miravalle",
        "Rancho Miravalles",
        "Nuevo Miravalles"
    ],
    "wof:name":"Nuevo Miravalle",
    "wof:placetype":"locality"
},
  "geometry": {"coordinates":[-100.9089,29.17598],"type":"Point"}
}