{
  "type": "Feature",
  "properties": {
    "gn:admin1_code":"20",
    "gn:admin2_code":"287.0",
    "gn:asciiname":"Gasucho",
    "gn:country_code":"MX",
    "gn:dem":2246,
    "gn:feature_class":"P",
    "gn:feature_code":"PPL",
    "gn:name":"Gasucho",
    "gn:population":6,
    "gn:timezone":"America/Mexico_City",
    "iso:country":"MX",
    "wof:name":"Gasucho",
    "wof:placetype":"locality",
    "wof:population":6
},
  "geometry": {"coordinates":[-97.45028000000001,17.75389],"type":"Point"}
}