{
  "type": "Feature",
  "properties": {
    "gn:admin1_code":"6.0",
    "gn:asciiname":"Rancho Blanco",
    "gn:country_code":"MX",
    "gn:dem":1195,
    "gn:feature_class":"P",
    "gn:feature_code":"PPL",
    "gn:name":"Rancho Blanco",
    "gn:population":0,
    "gn:timezone":"America/Chihuahua",
    "iso:country":"MX",
    "name:spa_x_preferred":[
        "Rancho Blanco"
    ],
    "wof:name":"Rancho Blanco",
    "wof:placetype":"locality"
},
  "geometry": {"coordinates":[-105.47383000000001,28.15045],"type":"Point"}
}