{
  "type": "Feature",
  "properties": {
    "gn:admin1_code":"20",
    "gn:admin2_code":"149",
    "gn:asciiname":"Yugosica",
    "gn:country_code":"MX",
    "gn:dem":1469,
    "gn:feature_class":"P",
    "gn:feature_code":"PPL",
    "gn:name":"Yugosica",
    "gn:population":11,
    "gn:timezone":"America/Mexico_City",
    "iso:country":"MX",
    "wof:name":"Yugosica",
    "wof:placetype":"locality",
    "wof:population":11
},
  "geometry": {"coordinates":[-96.95583000000001,16.50832999999999],"type":"Point"}
}