{
  "type": "Feature",
  "properties": {
    "gn:admin1_code":"32",
    "gn:admin2_code":"1.0",
    "gn:asciiname":"Palma Cuata",
    "gn:country_code":"MX",
    "gn:dem":1435,
    "gn:feature_class":"P",
    "gn:feature_code":"PPL",
    "gn:name":"Palma Cuata",
    "gn:population":0,
    "gn:timezone":"America/Mexico_City",
    "iso:country":"MX",
    "wof:name":"Palma Cuata",
    "wof:placetype":"locality"
},
  "geometry": {"coordinates":[-103.01812,21.48504],"type":"Point"}
}