{
  "type": "Feature",
  "properties": {
    "gn:admin1_code":"5",
    "gn:admin2_code":"100",
    "gn:asciiname":"Las Estrellas",
    "gn:country_code":"MX",
    "gn:dem":688,
    "gn:feature_class":"P",
    "gn:feature_code":"PPL",
    "gn:name":"Las Estrellas",
    "gn:population":40,
    "gn:timezone":"America/Mexico_City",
    "iso:country":"MX",
    "wof:name":"Las Estrellas",
    "wof:placetype":"locality",
    "wof:population":40
},
  "geometry": {"coordinates":[-92.29000000000001,17.33028],"type":"Point"}
}