{
  "type": "Feature",
  "properties": {
    "gn:admin1_code":"20",
    "gn:admin2_code":"232.0",
    "gn:asciiname":"Arroyo Caracol Arriba",
    "gn:country_code":"MX",
    "gn:dem":89,
    "gn:feature_class":"P",
    "gn:feature_code":"PPL",
    "gn:name":"Arroyo Caracol Arriba",
    "gn:population":172,
    "gn:timezone":"America/Mexico_City",
    "iso:country":"MX",
    "wof:name":"Arroyo Caracol Arriba",
    "wof:placetype":"locality",
    "wof:population":172
},
  "geometry": {"coordinates":[-96.39278,18.10778],"type":"Point"}
}