{
  "type": "Feature",
  "properties": {
    "gn:admin1_code":"26.0",
    "gn:admin2_code":"55.0",
    "gn:asciiname":"El Doctor",
    "gn:country_code":"MX",
    "gn:dem":12,
    "gn:feature_class":"P",
    "gn:feature_code":"PPL",
    "gn:name":"El Doctor",
    "gn:population":0,
    "gn:timezone":"America/Hermosillo",
    "iso:country":"MX",
    "name:spa_x_preferred":[
        "El Doctor"
    ],
    "wof:name":"El Doctor",
    "wof:placetype":"locality"
},
  "geometry": {"coordinates":[-114.7433,31.95984],"type":"Point"}
}