{
  "type": "Feature",
  "properties": {
    "gn:admin1_code":"15",
    "gn:admin2_code":"48.0",
    "gn:asciiname":"Barrio Santa Clara",
    "gn:country_code":"MX",
    "gn:dem":2574,
    "gn:feature_class":"P",
    "gn:feature_code":"PPL",
    "gn:name":"Barrio Santa Clara",
    "gn:population":206,
    "gn:timezone":"America/Mexico_City",
    "iso:country":"MX",
    "wof:name":"Barrio Santa Clara",
    "wof:placetype":"locality",
    "wof:population":206
},
  "geometry": {"coordinates":[-99.80583,19.69694],"type":"Point"}
}