{
  "type": "Feature",
  "properties": {
    "gn:admin1_code":"26",
    "gn:admin2_code":"42.0",
    "gn:asciiname":"Molojoa",
    "gn:country_code":"MX",
    "gn:dem":123,
    "gn:feature_class":"P",
    "gn:feature_code":"PPL",
    "gn:name":"Molojoa",
    "gn:population":0,
    "gn:timezone":"America/Hermosillo",
    "iso:country":"MX",
    "name:spa_x_preferred":[
        "Molojoa"
    ],
    "wof:name":"Molojoa",
    "wof:placetype":"locality"
},
  "geometry": {"coordinates":[-109.27578,26.97333],"type":"Point"}
}