{
  "type": "Feature",
  "properties": {
    "gn:admin1_code":"20",
    "gn:admin2_code":"130.0",
    "gn:asciiname":"Embarcadero",
    "gn:country_code":"MX",
    "gn:dem":26,
    "gn:feature_class":"P",
    "gn:feature_code":"PPL",
    "gn:name":"Embarcadero",
    "gn:population":0,
    "gn:timezone":"America/Mexico_City",
    "iso:country":"MX",
    "name:deu_x_preferred":[
        "Embarcadero"
    ],
    "name:nld_x_preferred":[
        "Embarcadero"
    ],
    "name:spa_x_preferred":[
        "Embarcadero"
    ],
    "wof:name":"Embarcadero",
    "wof:placetype":"locality"
},
  "geometry": {"coordinates":[-94.80916999999999,16.29667],"type":"Point"}
}