{
  "type": "Feature",
  "properties": {
    "gn:admin1_code":"20.0",
    "gn:asciiname":"El Pescadillo",
    "gn:country_code":"MX",
    "gn:dem":2069,
    "gn:feature_class":"P",
    "gn:feature_code":"PPL",
    "gn:name":"El Pescadillo",
    "gn:population":0,
    "gn:timezone":"America/Mexico_City",
    "iso:country":"MX",
    "name:spa_x_preferred":[
        "El Pescadillo"
    ],
    "wof:name":"El Pescadillo",
    "wof:placetype":"locality"
},
  "geometry": {"coordinates":[-97.55643999999999,17.78379],"type":"Point"}
}