{
  "type": "Feature",
  "properties": {
    "gn:admin1_code":"30",
    "gn:admin2_code":"142.0",
    "gn:asciiname":"El Artemio",
    "gn:country_code":"MX",
    "gn:dem":54,
    "gn:feature_class":"P",
    "gn:feature_code":"PPL",
    "gn:name":"El Artemio",
    "gn:population":9,
    "gn:timezone":"America/Mexico_City",
    "iso:country":"MX",
    "wof:name":"El Artemio",
    "wof:placetype":"locality",
    "wof:population":9
},
  "geometry": {"coordinates":[-95.29083,17.73694],"type":"Point"}
}