{
  "type": "Feature",
  "properties": {
    "gn:admin1_code":"11.0",
    "gn:admin2_code":"33.0",
    "gn:asciiname":"Cerrito de Maria",
    "gn:country_code":"MX",
    "gn:dem":2008,
    "gn:feature_class":"P",
    "gn:feature_code":"PPL",
    "gn:name":"Cerrito de Mar\u00eda",
    "gn:population":0,
    "gn:timezone":"America/Mexico_City",
    "iso:country":"MX",
    "name:spa_x_preferred":[
        "Cerco de Mar\u00eda"
    ],
    "name:spa_x_variant":[
        "Cerrito de Mar\u00eda"
    ],
    "wof:name":"Cerrito de Maria",
    "wof:placetype":"locality"
},
  "geometry": {"coordinates":[-100.65612,21.25199],"type":"Point"}
}