{
  "type": "Feature",
  "properties": {
    "gn:admin1_code":"1",
    "gn:admin2_code":"3.0",
    "gn:asciiname":"San Tadeo",
    "gn:country_code":"MX",
    "gn:dem":1703,
    "gn:feature_class":"P",
    "gn:feature_code":"PPL",
    "gn:name":"San Tadeo",
    "gn:population":0,
    "gn:timezone":"America/Mexico_City",
    "iso:country":"MX",
    "name:und_x_variant":[
        "Santo Tomas",
        "San Tadeo"
    ],
    "wof:name":"San Tadeo",
    "wof:placetype":"locality"
},
  "geometry": {"coordinates":[-102.70043,21.91954],"type":"Point"}
}