{
  "type": "Feature",
  "properties": {
    "gn:admin1_code":"12.0",
    "gn:admin2_code":"71.0",
    "gn:asciiname":"El Cura",
    "gn:country_code":"MX",
    "gn:dem":627,
    "gn:feature_class":"P",
    "gn:feature_code":"PPL",
    "gn:name":"El Cura",
    "gn:population":0,
    "gn:timezone":"America/Mexico_City",
    "iso:country":"MX",
    "name:spa_x_preferred":[
        "El Cura"
    ],
    "wof:name":"El Cura",
    "wof:placetype":"locality"
},
  "geometry": {"coordinates":[-98.17641999999999,16.7921],"type":"Point"}
}