{
  "type": "Feature",
  "properties": {
    "gn:admin1_code":"16",
    "gn:admin2_code":"104.0",
    "gn:asciiname":"La Vinata",
    "gn:country_code":"MX",
    "gn:dem":1888,
    "gn:feature_class":"P",
    "gn:feature_code":"PPL",
    "gn:name":"La Vinata",
    "gn:population":6,
    "gn:timezone":"America/Mexico_City",
    "iso:country":"MX",
    "wof:name":"La Vinata",
    "wof:placetype":"locality",
    "wof:population":6
},
  "geometry": {"coordinates":[-102.66110999999999,19.92472],"type":"Point"}
}