{
  "type": "Feature",
  "properties": {
    "gn:admin1_code":"16",
    "gn:admin2_code":"97.0",
    "gn:asciiname":"La Vinata",
    "gn:country_code":"MX",
    "gn:dem":733,
    "gn:feature_class":"P",
    "gn:feature_code":"PPL",
    "gn:name":"La Vinata",
    "gn:population":0,
    "gn:timezone":"America/Mexico_City",
    "iso:country":"MX",
    "name:spa_x_preferred":[
        "La Vinata"
    ],
    "name:und_x_variant":[
        "Vinata"
    ],
    "wof:name":"La Vinata",
    "wof:placetype":"locality"
},
  "geometry": {"coordinates":[-101.35258,18.93524],"type":"Point"}
}