{
  "type": "Feature",
  "properties": {
    "gn:admin1_code":"14",
    "gn:admin2_code":"76",
    "gn:asciiname":"La Garita",
    "gn:country_code":"MX",
    "gn:dem":809,
    "gn:feature_class":"P",
    "gn:feature_code":"PPL",
    "gn:name":"La Garita",
    "gn:population":29,
    "gn:timezone":"America/Mexico_City",
    "iso:country":"MX",
    "wof:name":"La Garita",
    "wof:placetype":"locality",
    "wof:population":29
},
  "geometry": {"coordinates":[-103.80916999999999,21.68778],"type":"Point"}
}