{
  "type": "Feature",
  "properties": {
    "gn:admin1_code":"23",
    "gn:admin2_code":"2.0",
    "gn:asciiname":"Chan Santa Cruz",
    "gn:country_code":"MX",
    "gn:dem":23,
    "gn:feature_class":"P",
    "gn:feature_code":"PPL",
    "gn:name":"Chan Santa Cruz",
    "gn:population":571,
    "gn:timezone":"America/Cancun",
    "iso:country":"MX",
    "wof:name":"Chan Santa Cruz",
    "wof:placetype":"locality",
    "wof:population":571
},
  "geometry": {"coordinates":[-88.33194,19.36806],"type":"Point"}
}