{
  "type": "Feature",
  "properties": {
    "gn:admin1_code":"30",
    "gn:admin2_code":"169.0",
    "gn:asciiname":"El Maguey",
    "gn:country_code":"MX",
    "gn:dem":21,
    "gn:feature_class":"P",
    "gn:feature_code":"PPL",
    "gn:name":"El Maguey",
    "gn:population":595,
    "gn:timezone":"America/Mexico_City",
    "iso:country":"MX",
    "wof:name":"El Maguey",
    "wof:placetype":"locality",
    "wof:population":595
},
  "geometry": {"coordinates":[-95.70056,18.07222],"type":"Point"}
}