{
  "type": "Feature",
  "properties": {
    "gn:admin1_code":"12",
    "gn:admin2_code":"81.0",
    "gn:asciiname":"San Salvador",
    "gn:country_code":"MX",
    "gn:dem":1057,
    "gn:feature_class":"P",
    "gn:feature_code":"PPL",
    "gn:name":"San Salvador",
    "gn:population":0,
    "gn:timezone":"America/Mexico_City",
    "iso:country":"MX",
    "name:spa_x_preferred":[
        "San Salvador"
    ],
    "name:spa_x_variant":[
        "El Aserradero"
    ],
    "wof:name":"San Salvador",
    "wof:placetype":"locality"
},
  "geometry": {"coordinates":[-98.6786,17.00641],"type":"Point"}
}