{
  "type": "Feature",
  "properties": {
    "gn:admin1_code":"13",
    "gn:admin2_code":"60.0",
    "gn:asciiname":"El Temapa",
    "gn:country_code":"MX",
    "gn:dem":1099,
    "gn:feature_class":"P",
    "gn:feature_code":"PPL",
    "gn:name":"El Temapa",
    "gn:population":196,
    "gn:timezone":"America/Mexico_City",
    "iso:country":"MX",
    "wof:name":"El Temapa",
    "wof:placetype":"locality",
    "wof:population":196
},
  "geometry": {"coordinates":[-98.21456999999999,20.36925],"type":"Point"}
}