{
  "type": "Feature",
  "properties": {
    "gn:admin1_code":"25",
    "gn:admin2_code":"17",
    "gn:asciiname":"Tequehuale",
    "gn:country_code":"MX",
    "gn:dem":194,
    "gn:feature_class":"P",
    "gn:feature_code":"PPL",
    "gn:name":"Tequehuale",
    "gn:population":12,
    "gn:timezone":"America/Mazatlan",
    "iso:country":"MX",
    "name:spa_x_preferred":[
        "Tequehuale"
    ],
    "name:und_x_variant":[
        "Tetoguali"
    ],
    "wof:name":"Tequehuale",
    "wof:placetype":"locality",
    "wof:population":12
},
  "geometry": {"coordinates":[-108.20126,26.07106],"type":"Point"}
}