{
  "type": "Feature",
  "properties": {
    "gn:admin1_code":"14",
    "gn:admin2_code":"8",
    "gn:asciiname":"Cruz de Caminos (La Cruz del Sauz)",
    "gn:country_code":"MX",
    "gn:dem":2084,
    "gn:feature_class":"P",
    "gn:feature_code":"PPL",
    "gn:name":"Cruz de Caminos (La Cruz del Sauz)",
    "gn:population":39,
    "gn:timezone":"America/Mexico_City",
    "iso:country":"MX",
    "wof:name":"Cruz de Caminos (La Cruz del Sauz)",
    "wof:placetype":"locality",
    "wof:population":39
},
  "geometry": {"coordinates":[-102.26528,20.79194],"type":"Point"}
}