{
  "type": "Feature",
  "properties": {
    "gn:admin1_code":"26.0",
    "gn:admin2_code":"30.0",
    "gn:asciiname":"Monterrey",
    "gn:country_code":"MX",
    "gn:dem":96,
    "gn:feature_class":"P",
    "gn:feature_code":"PPL",
    "gn:name":"Monterrey",
    "gn:population":0,
    "gn:timezone":"America/Hermosillo",
    "iso:country":"MX",
    "name:und_x_variant":[
        "Campo Monterrey",
        "Monterrey"
    ],
    "wof:name":"Monterrey",
    "wof:placetype":"locality"
},
  "geometry": {"coordinates":[-111.35451999999999,28.88596],"type":"Point"}
}