{
  "type": "Feature",
  "properties": {
    "gn:admin1_code":"11",
    "gn:admin2_code":"17.0",
    "gn:asciiname":"Granja Don Chon",
    "gn:country_code":"MX",
    "gn:dem":1711,
    "gn:feature_class":"P",
    "gn:feature_code":"PPL",
    "gn:name":"Granja Don Chon",
    "gn:population":8,
    "gn:timezone":"America/Mexico_City",
    "iso:country":"MX",
    "wof:name":"Granja Don Chon",
    "wof:placetype":"locality",
    "wof:population":8
},
  "geometry": {"coordinates":[-101.47528,20.61139],"type":"Point"}
}