{
  "type": "Feature",
  "properties": {
    "gn:admin1_code":"30",
    "gn:admin2_code":"3",
    "gn:asciiname":"Vicencio Rodriguez Morales",
    "gn:country_code":"MX",
    "gn:dem":111,
    "gn:feature_class":"P",
    "gn:feature_code":"PPL",
    "gn:name":"Vicencio Rodr\u00edguez Morales",
    "gn:population":36,
    "gn:timezone":"America/Mexico_City",
    "iso:country":"MX",
    "name:und_x_variant":[
        "Vicencio Rodr\u00edguez Morales"
    ],
    "wof:name":"Vicencio Rodriguez Morales",
    "wof:placetype":"locality",
    "wof:population":36
},
  "geometry": {"coordinates":[-94.92222,18.04167],"type":"Point"}
}