{
  "type": "Feature",
  "properties": {
    "gn:admin1_code":"26",
    "gn:admin2_code":"17.0",
    "gn:asciiname":"Poblado Cerro Blanco",
    "gn:country_code":"MX",
    "gn:dem":54,
    "gn:feature_class":"P",
    "gn:feature_code":"PPL",
    "gn:name":"Poblado Cerro Blanco",
    "gn:population":308,
    "gn:timezone":"America/Hermosillo",
    "iso:country":"MX",
    "wof:name":"Poblado Cerro Blanco",
    "wof:placetype":"locality",
    "wof:population":308
},
  "geometry": {"coordinates":[-112.86360999999999,30.77389],"type":"Point"}
}