{
  "type": "Feature",
  "properties": {
    "gn:admin1_code":"29",
    "gn:admin2_code":"18.0",
    "gn:asciiname":"Capula",
    "gn:country_code":"MX",
    "gn:dem":2549,
    "gn:feature_class":"P",
    "gn:feature_code":"PPL",
    "gn:name":"Capula",
    "gn:population":8,
    "gn:timezone":"America/Mexico_City",
    "iso:country":"MX",
    "wof:name":"Capula",
    "wof:placetype":"locality",
    "wof:population":8
},
  "geometry": {"coordinates":[-98.10453,19.32053],"type":"Point"}
}