{
  "type": "Feature",
  "properties": {
    "gn:admin1_code":"25",
    "gn:admin2_code":"3.0",
    "gn:asciiname":"El Zoquital",
    "gn:country_code":"MX",
    "gn:dem":314,
    "gn:feature_class":"P",
    "gn:feature_code":"PPL",
    "gn:name":"El Zoquital",
    "gn:population":0,
    "gn:timezone":"America/Mazatlan",
    "iso:country":"MX",
    "name:spa_x_preferred":[
        "El Zoquital"
    ],
    "wof:name":"El Zoquital",
    "wof:placetype":"locality"
},
  "geometry": {"coordinates":[-107.62461,25.4777],"type":"Point"}
}