{
  "type": "Feature",
  "properties": {
    "gn:admin1_code":"28.0",
    "gn:admin2_code":"13.0",
    "gn:asciiname":"Los Cepeda",
    "gn:country_code":"MX",
    "gn:dem":172,
    "gn:feature_class":"P",
    "gn:feature_code":"PPL",
    "gn:name":"Los Cepeda",
    "gn:population":0,
    "gn:timezone":"America/Monterrey",
    "iso:country":"MX",
    "name:spa_x_preferred":[
        "Los Cepeda"
    ],
    "wof:name":"Los Cepeda",
    "wof:placetype":"locality"
},
  "geometry": {"coordinates":[-98.82120999999999,23.71322],"type":"Point"}
}