{
  "type": "Feature",
  "properties": {
    "gn:admin1_code":"24",
    "gn:admin2_code":"43.0",
    "gn:asciiname":"Platanar",
    "gn:country_code":"MX",
    "gn:dem":1927,
    "gn:feature_class":"P",
    "gn:feature_code":"PPL",
    "gn:name":"Platanar",
    "gn:population":0,
    "gn:timezone":"America/Mexico_City",
    "iso:country":"MX",
    "name:fra_x_preferred":[
        "Platanar"
    ],
    "name:nor_x_preferred":[
        "Platanar"
    ],
    "name:pol_x_preferred":[
        "Platanar"
    ],
    "name:slk_x_preferred":[
        "Platanar"
    ],
    "name:spa_x_preferred":[
        "Volc\u00e1n Platanar"
    ],
    "name:zho_x_preferred":[
        "\u666e\u62c9\u5854\u7d0d\u723e\u706b\u5c71"
    ],
    "wof:name":"Platanar",
    "wof:placetype":"locality"
},
  "geometry": {"coordinates":[-100.31667,21.68333],"type":"Point"}
}