{
  "type": "Feature",
  "properties": {
    "gn:admin1_code":"5.0",
    "gn:asciiname":"Los Tres Potrillos",
    "gn:country_code":"MX",
    "gn:dem":7,
    "gn:feature_class":"P",
    "gn:feature_code":"PPL",
    "gn:name":"Los Tres Potrillos",
    "gn:population":0,
    "gn:timezone":"America/Mexico_City",
    "iso:country":"MX",
    "name:spa_x_preferred":[
        "Los Tres Potrillos"
    ],
    "wof:name":"Los Tres Potrillos",
    "wof:placetype":"locality"
},
  "geometry": {"coordinates":[-93.50044,15.79428],"type":"Point"}
}