{
  "type": "Feature",
  "properties": {
    "gn:admin1_code":"6",
    "gn:admin2_code":"63.0",
    "gn:asciiname":"Rio Verde",
    "gn:country_code":"MX",
    "gn:dem":1741,
    "gn:feature_class":"P",
    "gn:feature_code":"PPL",
    "gn:name":"R\u00edo Verde",
    "gn:population":0,
    "gn:timezone":"America/Chihuahua",
    "iso:country":"MX",
    "wof:name":"Rio Verde",
    "wof:placetype":"locality"
},
  "geometry": {"coordinates":[-107.90344,28.62874],"type":"Point"}
}