{
  "type": "Feature",
  "properties": {
    "gn:admin1_code":"19",
    "gn:admin2_code":"33.0",
    "gn:asciiname":"Dolores",
    "gn:country_code":"MX",
    "gn:dem":304,
    "gn:feature_class":"P",
    "gn:feature_code":"PPL",
    "gn:name":"Dolores",
    "gn:population":0,
    "gn:timezone":"America/Monterrey",
    "iso:country":"MX",
    "name:spa_x_preferred":[
        "Dolores"
    ],
    "wof:name":"Dolores",
    "wof:placetype":"locality"
},
  "geometry": {"coordinates":[-99.40774,25.11975],"type":"Point"}
}