{
  "type": "Feature",
  "properties": {
    "gn:admin1_code":"14",
    "gn:admin2_code":"19.0",
    "gn:asciiname":"Las Manzanitas",
    "gn:country_code":"MX",
    "gn:dem":1379,
    "gn:feature_class":"P",
    "gn:feature_code":"PPL",
    "gn:name":"Las Manzanitas",
    "gn:population":0,
    "gn:timezone":"America/Mexico_City",
    "iso:country":"MX",
    "name:spa_x_preferred":[
        "Las Manzanitas"
    ],
    "wof:name":"Las Manzanitas",
    "wof:placetype":"locality"
},
  "geometry": {"coordinates":[-103.82402999999999,21.85519],"type":"Point"}
}