{
  "type": "Feature",
  "properties": {
    "gn:admin1_code":"5.0",
    "gn:asciiname":"La Estrella",
    "gn:country_code":"MX",
    "gn:dem":775,
    "gn:feature_class":"P",
    "gn:feature_code":"PPL",
    "gn:name":"La Estrella",
    "gn:population":0,
    "gn:timezone":"America/Mexico_City",
    "iso:country":"MX",
    "name:spa_x_preferred":[
        "La Estrella"
    ],
    "wof:name":"La Estrella",
    "wof:placetype":"locality"
},
  "geometry": {"coordinates":[-91.85702999999999,16.98098],"type":"Point"}
}