{
  "type": "Feature",
  "properties": {
    "gn:admin1_code":"27",
    "gn:admin2_code":"3.0",
    "gn:asciiname":"Finca Miramar",
    "gn:country_code":"MX",
    "gn:dem":3,
    "gn:feature_class":"P",
    "gn:feature_code":"PPL",
    "gn:name":"Finca Miramar",
    "gn:population":0,
    "gn:timezone":"America/Mexico_City",
    "iso:country":"MX",
    "name:spa_x_preferred":[
        "Finca Miramar"
    ],
    "wof:name":"Finca Miramar",
    "wof:placetype":"locality"
},
  "geometry": {"coordinates":[-92.77057000000001,18.4846],"type":"Point"}
}