{
  "type": "Feature",
  "properties": {
    "gn:admin1_code":"13.0",
    "gn:asciiname":"Homotitla",
    "gn:country_code":"MX",
    "gn:dem":167,
    "gn:feature_class":"P",
    "gn:feature_code":"PPL",
    "gn:name":"Homotitla",
    "gn:population":0,
    "gn:timezone":"America/Mexico_City",
    "iso:country":"MX",
    "name:spa_x_preferred":[
        "Homotitla"
    ],
    "wof:name":"Homotitla",
    "wof:placetype":"locality"
},
  "geometry": {"coordinates":[-98.36905,21.17547],"type":"Point"}
}