{
  "type": "Feature",
  "properties": {
    "gn:admin1_code":"6",
    "gn:admin2_code":"19.0",
    "gn:asciiname":"Osorio",
    "gn:country_code":"MX",
    "gn:dem":1736,
    "gn:feature_class":"P",
    "gn:feature_code":"PPL",
    "gn:name":"Osorio",
    "gn:population":0,
    "gn:timezone":"America/Chihuahua",
    "iso:country":"MX",
    "name:ceb_x_preferred":[
        "Osorio"
    ],
    "name:deu_x_preferred":[
        "Osorio"
    ],
    "name:fra_x_preferred":[
        "Osorio"
    ],
    "name:ita_x_preferred":[
        "Osorio"
    ],
    "name:jpn_x_preferred":[
        "\u30aa\u30bd\u30ea\u30aa"
    ],
    "name:nor_x_preferred":[
        "Osorio"
    ],
    "name:rus_x_preferred":[
        "\u041e\u0437\u043e\u0440\u0438\u0443"
    ],
    "name:spa_x_preferred":[
        "Osorio"
    ],
    "name:swe_x_preferred":[
        "Osorio"
    ],
    "wof:name":"Osorio",
    "wof:placetype":"locality"
},
  "geometry": {"coordinates":[-106.25,28.48333],"type":"Point"}
}