{
  "type": "Feature",
  "properties": {
    "gn:admin1_code":"10",
    "gn:admin2_code":"14",
    "gn:asciiname":"El Banco",
    "gn:country_code":"MX",
    "gn:dem":2187,
    "gn:feature_class":"P",
    "gn:feature_code":"PPL",
    "gn:name":"El Banco",
    "gn:population":10,
    "gn:timezone":"America/Monterrey",
    "iso:country":"MX",
    "name:ben_x_preferred":[
        "\u098f\u09b2 \u09ac\u09cd\u09af\u09be\u0999\u09cd\u0995\u09cb"
    ],
    "name:ell_x_preferred":[
        "\u0395\u03bb \u039c\u03c0\u03ac\u03bd\u03ba\u03bf"
    ],
    "name:hin_x_preferred":[
        "\u090f\u0932 \u092c\u0948\u0902\u0915\u094b"
    ],
    "name:hun_x_preferred":[
        "El Banco"
    ],
    "name:ind_x_preferred":[
        "El Banco"
    ],
    "name:kor_x_preferred":[
        "\uc5d8 \ubc29\ucf54"
    ],
    "name:tur_x_preferred":[
        "El Banco"
    ],
    "name:urd_x_preferred":[
        "\u0627\u06cc\u0644 \u0628\u0627\u0646\u06a9\u0648"
    ],
    "wof:name":"El Banco",
    "wof:placetype":"locality",
    "wof:population":10
},
  "geometry": {"coordinates":[-104.35023,22.62976],"type":"Point"}
}