{
  "type": "Feature",
  "properties": {
    "gn:admin1_code":"10",
    "gn:admin2_code":"14",
    "gn:asciiname":"El Banco",
    "gn:country_code":"MX",
    "gn:dem":2187,
    "gn:feature_class":"P",
    "gn:feature_code":"PPL",
    "gn:name":"El Banco",
    "gn:population":10,
    "gn:timezone":"America/Monterrey",
    "iso:country":"MX",
    "wof:name":"El Banco",
    "wof:placetype":"locality",
    "wof:population":10
},
  "geometry": {"coordinates":[-104.35023,22.62976],"type":"Point"}
}