{
  "type": "Feature",
  "properties": {
    "gn:admin1_code":"20.0",
    "gn:admin2_code":"203.0",
    "gn:asciiname":"El Copalito",
    "gn:country_code":"MX",
    "gn:dem":1611,
    "gn:feature_class":"P",
    "gn:feature_code":"PPL",
    "gn:name":"El Copalito",
    "gn:population":0,
    "gn:timezone":"America/Mexico_City",
    "iso:country":"MX",
    "name:spa_x_preferred":[
        "El Copalito"
    ],
    "wof:name":"El Copalito",
    "wof:placetype":"locality"
},
  "geometry": {"coordinates":[-96.57237000000001,16.56074],"type":"Point"}
}