{
  "type": "Feature",
  "properties": {
    "gn:admin1_code":"1",
    "gn:admin2_code":"3.0",
    "gn:asciiname":"Tepezalilla de Abajo",
    "gn:country_code":"MX",
    "gn:dem":1668,
    "gn:feature_class":"P",
    "gn:feature_code":"PPL",
    "gn:name":"Tepezalilla de Abajo",
    "gn:population":75,
    "gn:timezone":"America/Mexico_City",
    "iso:country":"MX",
    "wof:name":"Tepezalilla de Abajo",
    "wof:placetype":"locality",
    "wof:population":75
},
  "geometry": {"coordinates":[-102.67139,21.86694],"type":"Point"}
}