{
  "type": "Feature",
  "properties": {
    "gn:admin1_code":"31",
    "gn:admin2_code":"89.0",
    "gn:asciiname":"Balanchechen",
    "gn:country_code":"MX",
    "gn:dem":27,
    "gn:feature_class":"P",
    "gn:feature_code":"PPL",
    "gn:name":"Balanchech\u00e9n",
    "gn:population":0,
    "gn:timezone":"America/Merida",
    "iso:country":"MX",
    "wof:name":"Balanchechen",
    "wof:placetype":"locality"
},
  "geometry": {"coordinates":[-89.51666999999998,20.46667],"type":"Point"}
}