{
  "type": "Feature",
  "properties": {
    "gn:admin1_code":"5",
    "gn:admin2_code":"4",
    "gn:asciiname":"El Horizonte",
    "gn:country_code":"MX",
    "gn:dem":989,
    "gn:feature_class":"P",
    "gn:feature_code":"PPL",
    "gn:name":"El Horizonte",
    "gn:population":22,
    "gn:timezone":"America/Mexico_City",
    "iso:country":"MX",
    "wof:name":"El Horizonte",
    "wof:placetype":"locality",
    "wof:population":22
},
  "geometry": {"coordinates":[-91.78694,16.67861],"type":"Point"}
}