{
  "type": "Feature",
  "properties": {
    "gn:admin1_code":"20",
    "gn:admin2_code":"377.0",
    "gn:asciiname":"Iturbide",
    "gn:country_code":"MX",
    "gn:dem":1403,
    "gn:feature_class":"P",
    "gn:feature_code":"PPL",
    "gn:name":"Iturbide",
    "gn:population":126,
    "gn:timezone":"America/Mexico_City",
    "iso:country":"MX",
    "wof:name":"Iturbide",
    "wof:placetype":"locality",
    "wof:population":126
},
  "geometry": {"coordinates":[-97.57666999999999,16.73361],"type":"Point"}
}