{
  "type": "Feature",
  "properties": {
    "gn:admin1_code":"5",
    "gn:admin2_code":"27.0",
    "gn:asciiname":"Union el Palmar",
    "gn:country_code":"MX",
    "gn:dem":1326,
    "gn:feature_class":"P",
    "gn:feature_code":"PPL",
    "gn:name":"Uni\u00f3n el Palmar",
    "gn:population":347,
    "gn:timezone":"America/Mexico_City",
    "iso:country":"MX",
    "wof:name":"Union el Palmar",
    "wof:placetype":"locality",
    "wof:population":347
},
  "geometry": {"coordinates":[-93.03119,16.87653],"type":"Point"}
}