{
  "type": "Feature",
  "properties": {
    "gn:admin1_code":"13",
    "gn:admin2_code":"73",
    "gn:asciiname":"La Quebradora",
    "gn:country_code":"MX",
    "gn:dem":1109,
    "gn:feature_class":"P",
    "gn:feature_code":"PPL",
    "gn:name":"La Quebradora",
    "gn:population":12,
    "gn:timezone":"America/Mexico_City",
    "iso:country":"MX",
    "wof:name":"La Quebradora",
    "wof:placetype":"locality",
    "wof:population":12
},
  "geometry": {"coordinates":[-98.60805999999999,21.02583],"type":"Point"}
}