{
  "type": "Feature",
  "properties": {
    "gn:admin1_code":"30",
    "gn:admin2_code":"100.0",
    "gn:asciiname":"Paso Higuera (Mirador y Anexos)",
    "gn:country_code":"MX",
    "gn:dem":40,
    "gn:feature_class":"P",
    "gn:feature_code":"PPL",
    "gn:name":"Paso Higuera (Mirador y Anexos)",
    "gn:population":207,
    "gn:timezone":"America/Mexico_City",
    "iso:country":"MX",
    "wof:name":"Paso Higuera (Mirador y Anexos)",
    "wof:placetype":"locality",
    "wof:population":207
},
  "geometry": {"coordinates":[-96.31944,19.01556],"type":"Point"}
}