{
  "type": "Feature",
  "properties": {
    "gn:admin1_code":"15",
    "gn:admin2_code":"59",
    "gn:asciiname":"La Saucera",
    "gn:country_code":"MX",
    "gn:dem":2283,
    "gn:feature_class":"P",
    "gn:feature_code":"PPL",
    "gn:name":"La Saucera",
    "gn:population":45,
    "gn:timezone":"America/Mexico_City",
    "iso:country":"MX",
    "wof:name":"La Saucera",
    "wof:placetype":"locality",
    "wof:population":45
},
  "geometry": {"coordinates":[-99.10603,19.70121],"type":"Point"}
}