{
  "type": "Feature",
  "properties": {
    "gn:admin1_code":"20",
    "gn:admin2_code":"364.0",
    "gn:asciiname":"Barranca Honda",
    "gn:country_code":"MX",
    "gn:dem":558,
    "gn:feature_class":"P",
    "gn:feature_code":"PPL",
    "gn:name":"Barranca Honda",
    "gn:population":0,
    "gn:timezone":"America/Mexico_City",
    "iso:country":"MX",
    "name:spa_x_preferred":[
        "Barranca Honda"
    ],
    "wof:name":"Barranca Honda",
    "wof:placetype":"locality"
},
  "geometry": {"coordinates":[-97.29734999999999,16.03819],"type":"Point"}
}