{
  "type": "Feature",
  "properties": {
    "gn:admin1_code":"30",
    "gn:admin2_code":"201.0",
    "gn:asciiname":"Ejuitepec",
    "gn:country_code":"MX",
    "gn:dem":1234,
    "gn:feature_class":"P",
    "gn:feature_code":"PPL",
    "gn:name":"Ejuitepec",
    "gn:population":217,
    "gn:timezone":"America/Mexico_City",
    "iso:country":"MX",
    "wof:name":"Ejuitepec",
    "wof:placetype":"locality",
    "wof:population":217
},
  "geometry": {"coordinates":[-97.00861,18.69833],"type":"Point"}
}