{
  "type": "Feature",
  "properties": {
    "gn:admin1_code":"16",
    "gn:admin2_code":"2",
    "gn:asciiname":"El Jovero",
    "gn:country_code":"MX",
    "gn:dem":770,
    "gn:feature_class":"P",
    "gn:feature_code":"PPL",
    "gn:name":"El Jovero",
    "gn:population":24,
    "gn:timezone":"America/Mexico_City",
    "iso:country":"MX",
    "wof:name":"El Jovero",
    "wof:placetype":"locality",
    "wof:population":24
},
  "geometry": {"coordinates":[-102.79639,18.57833],"type":"Point"}
}