{
  "type": "Feature",
  "properties": {
    "gn:admin1_code":"23",
    "gn:admin2_code":"3",
    "gn:asciiname":"Residencial Arrecifes",
    "gn:country_code":"MX",
    "gn:dem":4,
    "gn:feature_class":"P",
    "gn:feature_code":"PPL",
    "gn:name":"Residencial Arrecifes",
    "gn:population":20,
    "gn:timezone":"America/Cancun",
    "iso:country":"MX",
    "wof:name":"Residencial Arrecifes",
    "wof:placetype":"locality",
    "wof:population":20
},
  "geometry": {"coordinates":[-86.80348000000002,21.22171],"type":"Point"}
}