{
  "type": "Feature",
  "properties": {
    "gn:admin1_code":"21",
    "gn:admin2_code":"114.0",
    "gn:asciiname":"Guadalupe Victoria Valsequillo",
    "gn:country_code":"MX",
    "gn:dem":2110,
    "gn:feature_class":"P",
    "gn:feature_code":"PPL",
    "gn:name":"Guadalupe Victoria Valsequillo",
    "gn:population":483,
    "gn:timezone":"America/Mexico_City",
    "iso:country":"MX",
    "wof:name":"Guadalupe Victoria Valsequillo",
    "wof:placetype":"locality",
    "wof:population":483
},
  "geometry": {"coordinates":[-98.10472,18.91861],"type":"Point"}
}