{
  "type": "Feature",
  "properties": {
    "gn:admin1_code":"30",
    "gn:admin2_code":"150.0",
    "gn:asciiname":"El Cedral",
    "gn:country_code":"MX",
    "gn:dem":46,
    "gn:feature_class":"P",
    "gn:feature_code":"PPL",
    "gn:name":"El Cedral",
    "gn:population":0,
    "gn:timezone":"America/Mexico_City",
    "iso:country":"MX",
    "wof:name":"El Cedral",
    "wof:placetype":"locality"
},
  "geometry": {"coordinates":[-97.79599,21.42576],"type":"Point"}
}