{
  "type": "Feature",
  "properties": {
    "gn:admin1_code":"5",
    "gn:admin2_code":"50",
    "gn:asciiname":"El Shotal 1ra. Seccion",
    "gn:country_code":"MX",
    "gn:dem":61,
    "gn:feature_class":"P",
    "gn:feature_code":"PPL",
    "gn:name":"El Shotal 1ra. Secci\u00f3n",
    "gn:population":40,
    "gn:timezone":"America/Mexico_City",
    "iso:country":"MX",
    "name:und_x_variant":[
        "El Shotal 1ra. Secci\u00f3n"
    ],
    "wof:name":"El Shotal 1ra. Seccion",
    "wof:placetype":"locality",
    "wof:population":40
},
  "geometry": {"coordinates":[-91.75972,17.53278],"type":"Point"}
}