{
  "type": "Feature",
  "properties": {
    "gn:admin1_code":"25",
    "gn:admin2_code":"14",
    "gn:asciiname":"El Aguacate",
    "gn:country_code":"MX",
    "gn:dem":107,
    "gn:feature_class":"P",
    "gn:feature_code":"PPL",
    "gn:name":"El Aguacate",
    "gn:population":18,
    "gn:timezone":"America/Mazatlan",
    "iso:country":"MX",
    "wof:name":"El Aguacate",
    "wof:placetype":"locality",
    "wof:population":18
},
  "geometry": {"coordinates":[-105.62333999999998,22.97686],"type":"Point"}
}