{
  "type": "Feature",
  "properties": {
    "gn:admin1_code":"20",
    "gn:admin2_code":"71",
    "gn:asciiname":"Rancho Monica",
    "gn:country_code":"MX",
    "gn:dem":599,
    "gn:feature_class":"P",
    "gn:feature_code":"PPL",
    "gn:name":"Rancho M\u00f3nica",
    "gn:population":11,
    "gn:timezone":"America/Mexico_City",
    "iso:country":"MX",
    "name:und_x_variant":[
        "Rancho M\u00f3nica"
    ],
    "wof:name":"Rancho Monica",
    "wof:placetype":"locality",
    "wof:population":11
},
  "geometry": {"coordinates":[-96.47167,15.94639],"type":"Point"}
}