{
  "type": "Feature",
  "properties": {
    "gn:admin1_code":"20.0",
    "gn:asciiname":"Xahayucuanino",
    "gn:country_code":"MX",
    "gn:dem":2198,
    "gn:feature_class":"P",
    "gn:feature_code":"PPL",
    "gn:name":"Xahayucuanino",
    "gn:population":0,
    "gn:timezone":"America/Mexico_City",
    "iso:country":"MX",
    "name:spa_x_preferred":[
        "Xahayucuanino"
    ],
    "wof:name":"Xahayucuanino",
    "wof:placetype":"locality"
},
  "geometry": {"coordinates":[-97.30271999999999,17.50928],"type":"Point"}
}