{
  "type": "Feature",
  "properties": {
    "gn:admin1_code":"26",
    "gn:asciiname":"Pena Blanca",
    "gn:country_code":"MX",
    "gn:dem":1502,
    "gn:feature_class":"P",
    "gn:feature_code":"PPL",
    "gn:name":"Pe\u00f1a Blanca",
    "gn:population":0,
    "gn:timezone":"America/Hermosillo",
    "iso:country":"MX",
    "name:spa_x_preferred":[
        "Pe\u00f1a Blanca"
    ],
    "wof:name":"Pena Blanca",
    "wof:placetype":"locality"
},
  "geometry": {"coordinates":[-108.81331000000002,30.81683],"type":"Point"}
}