{
  "type": "Feature",
  "properties": {
    "gn:admin1_code":"5.0",
    "gn:asciiname":"Irlanda",
    "gn:country_code":"MX",
    "gn:dem":17,
    "gn:feature_class":"P",
    "gn:feature_code":"PPL",
    "gn:name":"Irlanda",
    "gn:population":0,
    "gn:timezone":"America/Mexico_City",
    "iso:country":"MX",
    "name:spa_x_preferred":[
        "Irlanda"
    ],
    "wof:name":"Irlanda",
    "wof:placetype":"locality"
},
  "geometry": {"coordinates":[-93.03879000000001,15.41673],"type":"Point"}
}