{
  "type": "Feature",
  "properties": {
    "gn:admin1_code":"6",
    "gn:admin2_code":"12.0",
    "gn:asciiname":"Baporeachi de Arriba",
    "gn:country_code":"MX",
    "gn:dem":2152,
    "gn:feature_class":"P",
    "gn:feature_code":"PPL",
    "gn:name":"Baporeachi de Arriba",
    "gn:population":8,
    "gn:timezone":"America/Chihuahua",
    "iso:country":"MX",
    "wof:name":"Baporeachi de Arriba",
    "wof:placetype":"locality",
    "wof:population":8
},
  "geometry": {"coordinates":[-107.17383,27.92365],"type":"Point"}
}