{
  "type": "Feature",
  "properties": {
    "gn:admin1_code":"26",
    "gn:admin2_code":"66.0",
    "gn:asciiname":"Coyote",
    "gn:country_code":"MX",
    "gn:dem":390,
    "gn:feature_class":"P",
    "gn:feature_code":"PPL",
    "gn:name":"Coyote",
    "gn:population":0,
    "gn:timezone":"America/Hermosillo",
    "iso:country":"MX",
    "name:spa_x_preferred":[
        "Coyote"
    ],
    "wof:name":"Coyote",
    "wof:placetype":"locality"
},
  "geometry": {"coordinates":[-110.42581,29.35804000000001],"type":"Point"}
}