{
  "type": "Feature",
  "properties": {
    "gn:admin1_code":"19.0",
    "gn:admin2_code":"27.0",
    "gn:asciiname":"Los Dos Ebanitos",
    "gn:country_code":"MX",
    "gn:dem":190,
    "gn:feature_class":"P",
    "gn:feature_code":"PPL",
    "gn:name":"Los Dos Ebanitos",
    "gn:population":0,
    "gn:timezone":"America/Monterrey",
    "iso:country":"MX",
    "name:spa_x_preferred":[
        "Los Dos Ebanitos"
    ],
    "wof:name":"Los Dos Ebanitos",
    "wof:placetype":"locality"
},
  "geometry": {"coordinates":[-99.52593,25.9036],"type":"Point"}
}