{
  "type": "Feature",
  "properties": {
    "gn:admin1_code":"26",
    "gn:admin2_code":"26.0",
    "gn:asciiname":"Colonia Soto",
    "gn:country_code":"MX",
    "gn:dem":14,
    "gn:elevation":"10.0",
    "gn:feature_class":"P",
    "gn:feature_code":"PPL",
    "gn:name":"Colonia Soto",
    "gn:population":429,
    "gn:timezone":"America/Hermosillo",
    "iso:country":"MX",
    "name:spa_x_colloquial":[
        "Soto",
        "Caurar\u00e1",
        "Caurarajaqui"
    ],
    "name:spa_x_preferred":[
        "Soto"
    ],
    "name:spa_x_variant":[
        "Caurar\u00e1",
        "Caurarajaqui",
        "Colonia Soto"
    ],
    "wof:name":"Colonia Soto",
    "wof:placetype":"locality",
    "wof:population":429
},
  "geometry": {"coordinates":[-109.60242,26.90614],"type":"Point"}
}