{
  "type": "Feature",
  "properties": {
    "gn:admin1_code":"11.0",
    "gn:admin2_code":"33.0",
    "gn:asciiname":"El Oriente",
    "gn:country_code":"MX",
    "gn:dem":2167,
    "gn:feature_class":"P",
    "gn:feature_code":"PPL",
    "gn:name":"El Oriente",
    "gn:population":0,
    "gn:timezone":"America/Mexico_City",
    "iso:country":"MX",
    "name:spa_x_preferred":[
        "El Oriente"
    ],
    "wof:name":"El Oriente",
    "wof:placetype":"locality"
},
  "geometry": {"coordinates":[-100.4533,21.23426],"type":"Point"}
}