{
  "type": "Feature",
  "properties": {
    "gn:admin1_code":"14",
    "gn:admin2_code":"105.0",
    "gn:asciiname":"La Tiricia",
    "gn:country_code":"MX",
    "gn:dem":1537,
    "gn:feature_class":"P",
    "gn:feature_code":"PPL",
    "gn:name":"La Tiricia",
    "gn:population":129,
    "gn:timezone":"America/Mexico_City",
    "iso:country":"MX",
    "wof:name":"La Tiricia",
    "wof:placetype":"locality",
    "wof:population":129
},
  "geometry": {"coordinates":[-102.72306,20.47833],"type":"Point"}
}