{
  "type": "Feature",
  "properties": {
    "gn:admin1_code":"10",
    "gn:admin2_code":"7.0",
    "gn:asciiname":"Manantial",
    "gn:country_code":"MX",
    "gn:dem":1115,
    "gn:feature_class":"P",
    "gn:feature_code":"PPL",
    "gn:name":"Manantial",
    "gn:population":0,
    "gn:timezone":"America/Monterrey",
    "iso:country":"MX",
    "name:spa_x_preferred":[
        "Manantial"
    ],
    "wof:name":"Manantial",
    "wof:placetype":"locality"
},
  "geometry": {"coordinates":[-103.57958000000001,25.78218],"type":"Point"}
}