{
  "type": "Feature",
  "properties": {
    "gn:admin1_code":"10",
    "gn:admin2_code":"26.0",
    "gn:asciiname":"Tapestito",
    "gn:country_code":"MX",
    "gn:dem":2639,
    "gn:feature_class":"P",
    "gn:feature_code":"PPL",
    "gn:name":"Tapestito",
    "gn:population":0,
    "gn:timezone":"America/Monterrey",
    "iso:country":"MX",
    "name:spa_x_preferred":[
        "Tapestito"
    ],
    "wof:name":"Tapestito",
    "wof:placetype":"locality"
},
  "geometry": {"coordinates":[-105.82866,24.48131],"type":"Point"}
}