{
  "type": "Feature",
  "properties": {
    "gn:admin1_code":"6",
    "gn:admin2_code":"47.0",
    "gn:asciiname":"La Estacion",
    "gn:country_code":"MX",
    "gn:dem":1463,
    "gn:feature_class":"P",
    "gn:feature_code":"PPL",
    "gn:name":"La Estaci\u00f3n",
    "gn:population":0,
    "gn:timezone":"America/Chihuahua",
    "iso:country":"MX",
    "name:spa_x_preferred":[
        "La Estaci\u00f3n"
    ],
    "wof:name":"La Estacion",
    "wof:placetype":"locality"
},
  "geometry": {"coordinates":[-108.79098,28.20404000000001],"type":"Point"}
}