{
  "type": "Feature",
  "properties": {
    "gn:admin1_code":"5",
    "gn:admin2_code":"6.0",
    "gn:asciiname":"Monte Ordonez",
    "gn:country_code":"MX",
    "gn:dem":1487,
    "gn:feature_class":"P",
    "gn:feature_code":"PPL",
    "gn:name":"Monte Ord\u00f3\u00f1ez",
    "gn:population":0,
    "gn:timezone":"America/Mexico_City",
    "iso:country":"MX",
    "name:spa_x_preferred":[
        "Monte Ord\u00f3\u00f1ez"
    ],
    "wof:name":"Monte Ordonez",
    "wof:placetype":"locality"
},
  "geometry": {"coordinates":[-92.17140000000001,15.56252],"type":"Point"}
}