{
  "type": "Feature",
  "properties": {
    "gn:admin1_code":"19.0",
    "gn:admin2_code":"37.0",
    "gn:asciiname":"Los Remotos",
    "gn:country_code":"MX",
    "gn:dem":756,
    "gn:feature_class":"P",
    "gn:feature_code":"PPL",
    "gn:name":"Los Remotos",
    "gn:population":0,
    "gn:timezone":"America/Monterrey",
    "iso:country":"MX",
    "name:spa_x_preferred":[
        "El Refugio"
    ],
    "name:spa_x_variant":[
        "Los Remotos"
    ],
    "wof:name":"Los Remotos",
    "wof:placetype":"locality"
},
  "geometry": {"coordinates":[-100.70198000000001,26.27269],"type":"Point"}
}