{
  "type": "Feature",
  "properties": {
    "gn:admin1_code":"25.0",
    "gn:asciiname":"Campo Romo",
    "gn:country_code":"MX",
    "gn:dem":26,
    "gn:feature_class":"P",
    "gn:feature_code":"PPL",
    "gn:name":"Campo Romo",
    "gn:population":0,
    "gn:timezone":"America/Mazatlan",
    "iso:country":"MX",
    "name:spa_x_preferred":[
        "Campo Romo"
    ],
    "wof:name":"Campo Romo",
    "wof:placetype":"locality"
},
  "geometry": {"coordinates":[-108.7694,25.86042],"type":"Point"}
}