{
  "type": "Feature",
  "properties": {
    "gn:admin1_code":"16",
    "gn:admin2_code":"2",
    "gn:asciiname":"Los Parajes",
    "gn:country_code":"MX",
    "gn:dem":951,
    "gn:feature_class":"P",
    "gn:feature_code":"PPL",
    "gn:name":"Los Parajes",
    "gn:population":20,
    "gn:timezone":"America/Mexico_City",
    "iso:country":"MX",
    "wof:name":"Los Parajes",
    "wof:placetype":"locality",
    "wof:population":20
},
  "geometry": {"coordinates":[-102.855,18.8675],"type":"Point"}
}