{
  "type": "Feature",
  "properties": {
    "gn:admin1_code":"17",
    "gn:asciiname":"Jaguey Quebrado",
    "gn:country_code":"MX",
    "gn:dem":2837,
    "gn:feature_class":"P",
    "gn:feature_code":"PPL",
    "gn:name":"Jag\u00fcey Quebrado",
    "gn:population":0,
    "gn:timezone":"America/Mexico_City",
    "iso:country":"MX",
    "name:spa_x_preferred":[
        "Jag\u00fcey Quebrado"
    ],
    "wof:name":"Jaguey Quebrado",
    "wof:placetype":"locality"
},
  "geometry": {"coordinates":[-98.71234,19.56201],"type":"Point"}
}