{
  "type": "Feature",
  "properties": {
    "gn:admin1_code":"10",
    "gn:admin2_code":"1.0",
    "gn:asciiname":"Mastranzo",
    "gn:country_code":"MX",
    "gn:dem":1935,
    "gn:feature_class":"P",
    "gn:feature_code":"PPL",
    "gn:name":"Mastranzo",
    "gn:population":0,
    "gn:timezone":"America/Monterrey",
    "iso:country":"MX",
    "name:spa_x_preferred":[
        "Mastranzo"
    ],
    "wof:name":"Mastranzo",
    "wof:placetype":"locality"
},
  "geometry": {"coordinates":[-104.64223,24.42766],"type":"Point"}
}