{
  "type": "Feature",
  "properties": {
    "gn:admin1_code":"16",
    "gn:admin2_code":"82.0",
    "gn:asciiname":"El Olimpo",
    "gn:country_code":"MX",
    "gn:dem":1783,
    "gn:feature_class":"P",
    "gn:feature_code":"PPL",
    "gn:name":"El Olimpo",
    "gn:population":128,
    "gn:timezone":"America/Mexico_City",
    "iso:country":"MX",
    "wof:name":"El Olimpo",
    "wof:placetype":"locality",
    "wof:population":128
},
  "geometry": {"coordinates":[-101.45278,19.25111],"type":"Point"}
}