{
  "type": "Feature",
  "properties": {
    "gn:admin1_code":"5.0",
    "gn:admin2_code":"63.0",
    "gn:asciiname":"Arroyon",
    "gn:country_code":"MX",
    "gn:dem":699,
    "gn:feature_class":"P",
    "gn:feature_code":"PPL",
    "gn:name":"Arroy\u00f3n",
    "gn:population":0,
    "gn:timezone":"America/Mexico_City",
    "iso:country":"MX",
    "name:spa_x_preferred":[
        "Arroy\u00f3n"
    ],
    "wof:name":"Arroyon",
    "wof:placetype":"locality"
},
  "geometry": {"coordinates":[-93.06639,16.87855],"type":"Point"}
}