{
  "type": "Feature",
  "properties": {
    "gn:admin1_code":"14",
    "gn:admin2_code":"87",
    "gn:asciiname":"Los Negros (Los Negros de Arriba)",
    "gn:country_code":"MX",
    "gn:dem":1363,
    "gn:feature_class":"P",
    "gn:feature_code":"PPL",
    "gn:name":"Los Negros (Los Negros de Arriba)",
    "gn:population":43,
    "gn:timezone":"America/Mexico_City",
    "iso:country":"MX",
    "wof:name":"Los Negros (Los Negros de Arriba)",
    "wof:placetype":"locality",
    "wof:population":43
},
  "geometry": {"coordinates":[-103.24306,19.19389],"type":"Point"}
}