{
  "type": "Feature",
  "properties": {
    "gn:admin1_code":"14",
    "gn:admin2_code":"115.0",
    "gn:asciiname":"Santa Cruz",
    "gn:country_code":"MX",
    "gn:dem":1643,
    "gn:feature_class":"P",
    "gn:feature_code":"PPL",
    "gn:name":"Santa Cruz",
    "gn:population":0,
    "gn:timezone":"America/Mexico_City",
    "iso:country":"MX",
    "name:spa_x_preferred":[
        "Santa Cruz"
    ],
    "wof:name":"Santa Cruz",
    "wof:placetype":"locality"
},
  "geometry": {"coordinates":[-103.67703,21.9785],"type":"Point"}
}