{
  "type": "Feature",
  "properties": {
    "gn:admin1_code":"8.0",
    "gn:admin2_code":"1.0",
    "gn:asciiname":"Patty",
    "gn:country_code":"MX",
    "gn:dem":16,
    "gn:feature_class":"P",
    "gn:feature_code":"PPL",
    "gn:name":"Patty",
    "gn:population":0,
    "gn:timezone":"America/Mexico_City",
    "iso:country":"MX",
    "wof:name":"Patty",
    "wof:placetype":"locality"
},
  "geometry": {"coordinates":[-104.06667,18.99167000000001],"type":"Point"}
}