{
  "type": "Feature",
  "properties": {
    "gn:admin1_code":"5.0",
    "gn:asciiname":"Encuentro Chico",
    "gn:country_code":"MX",
    "gn:dem":945,
    "gn:feature_class":"P",
    "gn:feature_code":"PPL",
    "gn:name":"Encuentro Chico",
    "gn:population":0,
    "gn:timezone":"America/Mexico_City",
    "iso:country":"MX",
    "name:spa_x_preferred":[
        "Encuentro Chico"
    ],
    "wof:name":"Encuentro Chico",
    "wof:placetype":"locality"
},
  "geometry": {"coordinates":[-92.37069,15.59554],"type":"Point"}
}