{
  "type": "Feature",
  "properties": {
    "gn:admin1_code":"7.0",
    "gn:admin2_code":"23.0",
    "gn:asciiname":"El Tordillo",
    "gn:country_code":"MX",
    "gn:dem":1140,
    "gn:feature_class":"P",
    "gn:feature_code":"PPL",
    "gn:name":"El Tordillo",
    "gn:population":0,
    "gn:timezone":"America/Monterrey",
    "iso:country":"MX",
    "name:spa_x_preferred":[
        "El Tordillo"
    ],
    "name:und_x_variant":[
        "Rancho El Tordillo"
    ],
    "wof:name":"El Tordillo",
    "wof:placetype":"locality"
},
  "geometry": {"coordinates":[-103.21854,27.41031],"type":"Point"}
}