{
  "type": "Feature",
  "properties": {
    "gn:admin1_code":"24",
    "gn:admin2_code":"22",
    "gn:asciiname":"La Escondida",
    "gn:country_code":"MX",
    "gn:dem":1960,
    "gn:feature_class":"P",
    "gn:feature_code":"PPL",
    "gn:name":"La Escondida",
    "gn:population":15,
    "gn:timezone":"America/Mexico_City",
    "iso:country":"MX",
    "wof:name":"La Escondida",
    "wof:placetype":"locality",
    "wof:population":15
},
  "geometry": {"coordinates":[-101.17333000000001,22.58694],"type":"Point"}
}