{
  "type": "Feature",
  "properties": {
    "gn:admin1_code":"5",
    "gn:admin2_code":"27.0",
    "gn:asciiname":"Salvador Urbina",
    "gn:country_code":"MX",
    "gn:dem":408,
    "gn:feature_class":"P",
    "gn:feature_code":"PPL",
    "gn:name":"Salvador Urbina",
    "gn:population":0,
    "gn:timezone":"America/Mexico_City",
    "iso:country":"MX",
    "name:spa_x_preferred":[
        "Salvador Urbina"
    ],
    "name:und_x_variant":[
        "S. Urbina"
    ],
    "wof:name":"Salvador Urbina",
    "wof:placetype":"locality"
},
  "geometry": {"coordinates":[-93.00248000000001,16.63537],"type":"Point"}
}