{
  "type": "Feature",
  "properties": {
    "gn:admin1_code":"16",
    "gn:admin2_code":"69",
    "gn:asciiname":"Chemita (Benjamin Rojas) [Granja Porcicola]",
    "gn:country_code":"MX",
    "gn:dem":1681,
    "gn:feature_class":"P",
    "gn:feature_code":"PPL",
    "gn:name":"Chemita (Benjam\u00edn Rojas) [Granja Porc\u00edcola]",
    "gn:population":15,
    "gn:timezone":"America/Mexico_City",
    "iso:country":"MX",
    "name:und_x_variant":[
        "Chemita (Benjam\u00edn Rojas) [Granja Porc\u00edcola]"
    ],
    "wof:name":"Chemita (Benjamin Rojas) [Granja Porcicola]",
    "wof:placetype":"locality",
    "wof:population":15
},
  "geometry": {"coordinates":[-102.00528,20.31444],"type":"Point"}
}