{
  "type": "Feature",
  "properties": {
    "gn:admin1_code":"16",
    "gn:admin2_code":"97.0",
    "gn:asciiname":"La Laja",
    "gn:country_code":"MX",
    "gn:dem":761,
    "gn:feature_class":"P",
    "gn:feature_code":"PPL",
    "gn:name":"La Laja",
    "gn:population":8,
    "gn:timezone":"America/Mexico_City",
    "iso:country":"MX",
    "wof:name":"La Laja",
    "wof:placetype":"locality",
    "wof:population":8
},
  "geometry": {"coordinates":[-101.46333,18.97889],"type":"Point"}
}