{
  "type": "Feature",
  "properties": {
    "gn:admin1_code":"10",
    "gn:admin2_code":"9.0",
    "gn:asciiname":"Paraje Arroyo Hondo",
    "gn:country_code":"MX",
    "gn:dem":1973,
    "gn:feature_class":"P",
    "gn:feature_code":"PPL",
    "gn:name":"Paraje Arroyo Hondo",
    "gn:population":0,
    "gn:timezone":"America/Chihuahua",
    "iso:country":"MX",
    "name:spa_x_preferred":[
        "Paraje Arroyo Hondo"
    ],
    "wof:name":"Paraje Arroyo Hondo",
    "wof:placetype":"locality"
},
  "geometry": {"coordinates":[-106.23902,26.43994],"type":"Point"}
}