{
  "type": "Feature",
  "properties": {
    "gn:admin1_code":"30",
    "gn:admin2_code":"48.0",
    "gn:asciiname":"Casas Nuevas",
    "gn:cc2":"MX",
    "gn:country_code":"MX",
    "gn:dem":18,
    "gn:feature_class":"P",
    "gn:feature_code":"PPL",
    "gn:name":"Casas Nuevas",
    "gn:population":0,
    "gn:timezone":"America/Mexico_City",
    "iso:country":"MX",
    "name:und_x_variant":[
        "Casas",
        "Casas Nuevas"
    ],
    "wof:name":"Casas Nuevas",
    "wof:placetype":"locality"
},
  "geometry": {"coordinates":[-94.58333,18.05],"type":"Point"}
}