{
  "type": "Feature",
  "properties": {
    "gn:admin1_code":"30",
    "gn:admin2_code":"63.0",
    "gn:asciiname":"Los Anteojos",
    "gn:country_code":"MX",
    "gn:dem":84,
    "gn:feature_class":"P",
    "gn:feature_code":"PPL",
    "gn:name":"Los Anteojos",
    "gn:population":6,
    "gn:timezone":"America/Mexico_City",
    "iso:country":"MX",
    "wof:name":"Los Anteojos",
    "wof:placetype":"locality",
    "wof:population":6
},
  "geometry": {"coordinates":[-97.97583,21.39889],"type":"Point"}
}