{
  "type": "Feature",
  "properties": {
    "gn:admin1_code":"24",
    "gn:admin2_code":"28.0",
    "gn:asciiname":"El Lindero (Santiago Gutierrez Alvizu)",
    "gn:country_code":"MX",
    "gn:dem":1865,
    "gn:feature_class":"P",
    "gn:feature_code":"PPL",
    "gn:name":"El Lindero (Santiago Guti\u00e9rrez Alvizu)",
    "gn:population":8,
    "gn:timezone":"America/Mexico_City",
    "iso:country":"MX",
    "name:und_x_variant":[
        "El Lindero (Santiago Guti\u00e9rrez Alvizu)"
    ],
    "wof:name":"El Lindero (Santiago Gutierrez Alvizu)",
    "wof:placetype":"locality",
    "wof:population":8
},
  "geometry": {"coordinates":[-100.87056,22.07111],"type":"Point"}
}