{
  "type": "Feature",
  "properties": {
    "gn:admin1_code":"28.0",
    "gn:admin2_code":"35.0",
    "gn:asciiname":"El Perico Viejo",
    "gn:country_code":"MX",
    "gn:dem":49,
    "gn:feature_class":"P",
    "gn:feature_code":"PPL",
    "gn:name":"El Perico Viejo",
    "gn:population":0,
    "gn:timezone":"America/Monterrey",
    "iso:country":"MX",
    "name:spa_x_preferred":[
        "El Perico Viejo"
    ],
    "wof:name":"El Perico Viejo",
    "wof:placetype":"locality"
},
  "geometry": {"coordinates":[-98.26495,24.8871],"type":"Point"}
}