{
  "type": "Feature",
  "properties": {
    "gn:admin1_code":"27.0",
    "gn:asciiname":"La Gloria",
    "gn:country_code":"MX",
    "gn:dem":34,
    "gn:feature_class":"P",
    "gn:feature_code":"PPL",
    "gn:name":"La Gloria",
    "gn:population":0,
    "gn:timezone":"America/Mexico_City",
    "iso:country":"MX",
    "name:spa_x_preferred":[
        "La Gloria"
    ],
    "wof:name":"La Gloria",
    "wof:placetype":"locality"
},
  "geometry": {"coordinates":[-93.70974,17.61117],"type":"Point"}
}