{
  "type": "Feature",
  "properties": {
    "gn:admin1_code":"12",
    "gn:admin2_code":"69.0",
    "gn:asciiname":"San Martin Amatitlan (Amatitlan)",
    "gn:country_code":"MX",
    "gn:dem":1578,
    "gn:feature_class":"P",
    "gn:feature_code":"PPL",
    "gn:name":"San Mart\u00edn Amatitl\u00e1n (Amatitl\u00e1n)",
    "gn:population":218,
    "gn:timezone":"America/Mexico_City",
    "iso:country":"MX",
    "name:und_x_variant":[
        "San Mart\u00edn Amatitl\u00e1n (Amatitl\u00e1n)"
    ],
    "wof:name":"San Martin Amatitlan (Amatitlan)",
    "wof:placetype":"locality",
    "wof:population":218
},
  "geometry": {"coordinates":[-98.53556,17.36167],"type":"Point"}
}