{
  "type": "Feature",
  "properties": {
    "gn:admin1_code":"16.0",
    "gn:asciiname":"El Rincon de Guaraqueo",
    "gn:country_code":"MX",
    "gn:dem":2277,
    "gn:feature_class":"P",
    "gn:feature_code":"PPL",
    "gn:name":"El Rinc\u00f3n de Guaraqueo",
    "gn:population":0,
    "gn:timezone":"America/Mexico_City",
    "iso:country":"MX",
    "name:spa_x_preferred":[
        "El Rinc\u00f3n de Guaraqueo"
    ],
    "wof:name":"El Rincon de Guaraqueo",
    "wof:placetype":"locality"
},
  "geometry": {"coordinates":[-100.5616,19.91912],"type":"Point"}
}