{
  "type": "Feature",
  "properties": {
    "gn:admin1_code":"3",
    "gn:admin2_code":"3.0",
    "gn:asciiname":"El Agua de las Palomas",
    "gn:country_code":"MX",
    "gn:dem":578,
    "gn:feature_class":"P",
    "gn:feature_code":"PPL",
    "gn:name":"El Agua de las Palomas",
    "gn:population":4,
    "gn:timezone":"America/Mazatlan",
    "iso:country":"MX",
    "wof:name":"El Agua de las Palomas",
    "wof:placetype":"locality",
    "wof:population":4
},
  "geometry": {"coordinates":[-110.11790000000001,23.87054],"type":"Point"}
}