{
  "type": "Feature",
  "properties": {
    "gn:admin1_code":"31",
    "gn:admin2_code":"6.0",
    "gn:asciiname":"Kan Ha",
    "gn:country_code":"MX",
    "gn:dem":9,
    "gn:feature_class":"P",
    "gn:feature_code":"PPL",
    "gn:name":"Kan H\u00e1",
    "gn:population":5,
    "gn:timezone":"America/Merida",
    "iso:country":"MX",
    "name:und_x_variant":[
        "Kan H\u00e1"
    ],
    "wof:name":"Kan Ha",
    "wof:placetype":"locality",
    "wof:population":5
},
  "geometry": {"coordinates":[-88.51666999999998,21.27278],"type":"Point"}
}