{
  "type": "Feature",
  "properties": {
    "gn:admin1_code":"6.0",
    "gn:admin2_code":"14.0",
    "gn:asciiname":"Avispa",
    "gn:cc2":"MX",
    "gn:country_code":"MX",
    "gn:dem":1584,
    "gn:feature_class":"P",
    "gn:feature_code":"PPL",
    "gn:name":"Avispa",
    "gn:population":0,
    "gn:timezone":"America/Chihuahua",
    "iso:country":"MX",
    "name:glg_x_preferred":[
        "Avispa Music"
    ],
    "name:ita_x_preferred":[
        "Avispa"
    ],
    "name:por_x_preferred":[
        "Avispa Music"
    ],
    "name:spa_x_preferred":[
        "Avispa Music"
    ],
    "name:und_x_variant":[
        "Abispa",
        "Avispa"
    ],
    "wof:name":"Avispa",
    "wof:placetype":"locality"
},
  "geometry": {"coordinates":[-105.09999999999999,26.73333],"type":"Point"}
}