{
  "type": "Feature",
  "properties": {
    "gn:admin1_code":"25",
    "gn:admin2_code":"8",
    "gn:asciiname":"Casas Nuevas",
    "gn:country_code":"MX",
    "gn:dem":197,
    "gn:feature_class":"P",
    "gn:feature_code":"PPL",
    "gn:name":"Casas Nuevas",
    "gn:population":51,
    "gn:timezone":"America/Mazatlan",
    "iso:country":"MX",
    "wof:name":"Casas Nuevas",
    "wof:placetype":"locality",
    "wof:population":51
},
  "geometry": {"coordinates":[-106.68153999999998,24.20734],"type":"Point"}
}