{
  "type": "Feature",
  "properties": {
    "gn:admin1_code":"16",
    "gn:admin2_code":"6",
    "gn:asciiname":"Colonia la Tamarindera",
    "gn:country_code":"MX",
    "gn:dem":288,
    "gn:feature_class":"P",
    "gn:feature_code":"PPL",
    "gn:name":"Colonia la Tamarindera",
    "gn:population":29,
    "gn:timezone":"America/Mexico_City",
    "iso:country":"MX",
    "wof:name":"Colonia la Tamarindera",
    "wof:placetype":"locality",
    "wof:population":29
},
  "geometry": {"coordinates":[-102.39472000000001,19.08972],"type":"Point"}
}