{
  "type": "Feature",
  "properties": {
    "gn:admin1_code":"30",
    "gn:admin2_code":"65.0",
    "gn:asciiname":"Plan del Rio",
    "gn:country_code":"MX",
    "gn:dem":292,
    "gn:feature_class":"P",
    "gn:feature_code":"PPL",
    "gn:name":"Plan del R\u00edo",
    "gn:population":1331,
    "gn:timezone":"America/Mexico_City",
    "iso:country":"MX",
    "wof:name":"Plan del Rio",
    "wof:placetype":"locality",
    "wof:population":1331
},
  "geometry": {"coordinates":[-96.6525,19.40184],"type":"Point"}
}