{
  "type": "Feature",
  "properties": {
    "gn:admin1_code":"4",
    "gn:admin2_code":"3.0",
    "gn:asciiname":"Juan de la Cabada Vera",
    "gn:country_code":"MX",
    "gn:dem":5,
    "gn:feature_class":"P",
    "gn:feature_code":"PPL",
    "gn:name":"Juan de la Cabada Vera",
    "gn:population":0,
    "gn:timezone":"America/Merida",
    "iso:country":"MX",
    "name:spa_x_preferred":[
        "La Pangola"
    ],
    "name:spa_x_variant":[
        "Juan de la Cabada Vera"
    ],
    "wof:name":"Juan de la Cabada Vera",
    "wof:placetype":"locality"
},
  "geometry": {"coordinates":[-91.43688,18.2823],"type":"Point"}
}