{
  "type": "Feature",
  "properties": {
    "gn:admin1_code":"21",
    "gn:admin2_code":"76.0",
    "gn:asciiname":"Colihui",
    "gn:country_code":"MX",
    "gn:dem":1330,
    "gn:feature_class":"P",
    "gn:feature_code":"PPL",
    "gn:name":"Colihui",
    "gn:population":61,
    "gn:timezone":"America/Mexico_City",
    "iso:country":"MX",
    "wof:name":"Colihui",
    "wof:placetype":"locality",
    "wof:population":61
},
  "geometry": {"coordinates":[-97.30244999999999,19.88287],"type":"Point"}
}