{
  "type": "Feature",
  "properties": {
    "gn:admin1_code":"24",
    "gn:admin2_code":"13.0",
    "gn:asciiname":"Santo Tomas (Campo San Lorenzo)",
    "gn:country_code":"MX",
    "gn:dem":289,
    "gn:feature_class":"P",
    "gn:feature_code":"PPL",
    "gn:name":"Santo Tom\u00e1s (Campo San Lorenzo)",
    "gn:population":6,
    "gn:timezone":"America/Mexico_City",
    "iso:country":"MX",
    "name:und_x_variant":[
        "Santo Tom\u00e1s (Campo San Lorenzo)"
    ],
    "wof:name":"Santo Tomas (Campo San Lorenzo)",
    "wof:placetype":"locality",
    "wof:population":6
},
  "geometry": {"coordinates":[-99.24917000000001,22.10111],"type":"Point"}
}