{
  "type": "Feature",
  "properties": {
    "gn:admin1_code":"2",
    "gn:admin2_code":"1.0",
    "gn:asciiname":"San Judas",
    "gn:country_code":"MX",
    "gn:dem":103,
    "gn:feature_class":"P",
    "gn:feature_code":"PPL",
    "gn:name":"San Judas",
    "gn:population":0,
    "gn:timezone":"America/Tijuana",
    "iso:country":"MX",
    "name:spa_x_preferred":[
        "San Judas"
    ],
    "wof:name":"San Judas",
    "wof:placetype":"locality"
},
  "geometry": {"coordinates":[-114.57575,29.99375],"type":"Point"}
}