{
  "type": "Feature",
  "properties": {
    "gn:admin1_code":"5",
    "gn:admin2_code":"59.0",
    "gn:asciiname":"El Real",
    "gn:country_code":"MX",
    "gn:dem":607,
    "gn:feature_class":"P",
    "gn:feature_code":"PPL",
    "gn:name":"El Real",
    "gn:population":0,
    "gn:timezone":"America/Mexico_City",
    "iso:country":"MX",
    "name:spa_x_preferred":[
        "El Real"
    ],
    "wof:name":"El Real",
    "wof:placetype":"locality"
},
  "geometry": {"coordinates":[-91.75997,16.89583],"type":"Point"}
}