{
  "type": "Feature",
  "properties": {
    "gn:admin1_code":"11",
    "gn:admin2_code":"33.0",
    "gn:asciiname":"Paso de en Medio",
    "gn:country_code":"MX",
    "gn:dem":1286,
    "gn:feature_class":"P",
    "gn:feature_code":"PPL",
    "gn:name":"Paso de en Medio",
    "gn:population":8,
    "gn:timezone":"America/Mexico_City",
    "iso:country":"MX",
    "wof:name":"Paso de en Medio",
    "wof:placetype":"locality",
    "wof:population":8
},
  "geometry": {"coordinates":[-100.34332999999999,21.66556],"type":"Point"}
}