{
  "type": "Feature",
  "properties": {
    "gn:admin1_code":"28",
    "gn:admin2_code":"12.0",
    "gn:asciiname":"Villafana",
    "gn:country_code":"MX",
    "gn:dem":88,
    "gn:feature_class":"P",
    "gn:feature_code":"PPL",
    "gn:name":"Villafa\u00f1a",
    "gn:population":6,
    "gn:timezone":"America/Monterrey",
    "iso:country":"MX",
    "name:und_x_variant":[
        "Villafa\u00f1a"
    ],
    "wof:name":"Villafana",
    "wof:placetype":"locality",
    "wof:population":6
},
  "geometry": {"coordinates":[-98.43040000000001,22.8162],"type":"Point"}
}