{
  "type": "Feature",
  "properties": {
    "gn:admin1_code":"14",
    "gn:admin2_code":"80.0",
    "gn:asciiname":"Pie de la Cuesta",
    "gn:country_code":"MX",
    "gn:dem":391,
    "gn:feature_class":"P",
    "gn:feature_code":"PPL",
    "gn:name":"Pie de la Cuesta",
    "gn:population":8,
    "gn:timezone":"America/Mexico_City",
    "iso:country":"MX",
    "wof:name":"Pie de la Cuesta",
    "wof:placetype":"locality",
    "wof:population":8
},
  "geometry": {"coordinates":[-104.8575,20.87472],"type":"Point"}
}