{
  "type": "Feature",
  "properties": {
    "gn:admin1_code":"12.0",
    "gn:admin2_code":"54.0",
    "gn:asciiname":"Los Cajones",
    "gn:country_code":"MX",
    "gn:dem":546,
    "gn:feature_class":"P",
    "gn:feature_code":"PPL",
    "gn:name":"Los Cajones",
    "gn:population":0,
    "gn:timezone":"America/Mexico_City",
    "iso:country":"MX",
    "name:ceb_x_preferred":[
        "Los Cajones"
    ],
    "name:spa_x_preferred":[
        "Los Cajones"
    ],
    "wof:name":"Los Cajones",
    "wof:placetype":"locality"
},
  "geometry": {"coordinates":[-100.30329,18.04591],"type":"Point"}
}