{
  "type": "Feature",
  "properties": {
    "gn:admin1_code":"6",
    "gn:admin2_code":"65.0",
    "gn:asciiname":"La Tablita",
    "gn:country_code":"MX",
    "gn:dem":1960,
    "gn:feature_class":"P",
    "gn:feature_code":"PPL",
    "gn:name":"La Tablita",
    "gn:population":0,
    "gn:timezone":"America/Chihuahua",
    "iso:country":"MX",
    "name:spa_x_preferred":[
        "La Tablita"
    ],
    "wof:name":"La Tablita",
    "wof:placetype":"locality"
},
  "geometry": {"coordinates":[-108.02427,27.11418],"type":"Point"}
}