{
  "type": "Feature",
  "properties": {
    "gn:admin1_code":"21",
    "gn:admin2_code":"47",
    "gn:asciiname":"El Vado",
    "gn:country_code":"MX",
    "gn:dem":939,
    "gn:feature_class":"P",
    "gn:feature_code":"PPL",
    "gn:name":"El Vado",
    "gn:population":15,
    "gn:timezone":"America/Mexico_City",
    "iso:country":"MX",
    "wof:name":"El Vado",
    "wof:placetype":"locality",
    "wof:population":15
},
  "geometry": {"coordinates":[-98.70944,18.43435],"type":"Point"}
}