{
  "type": "Feature",
  "properties": {
    "gn:admin1_code":"19.0",
    "gn:admin2_code":"44.0",
    "gn:asciiname":"El Nogalar",
    "gn:country_code":"MX",
    "gn:dem":349,
    "gn:feature_class":"P",
    "gn:feature_code":"PPL",
    "gn:name":"El Nogalar",
    "gn:population":0,
    "gn:timezone":"America/Monterrey",
    "iso:country":"MX",
    "name:spa_x_preferred":[
        "El Nogalar"
    ],
    "wof:name":"El Nogalar",
    "wof:placetype":"locality"
},
  "geometry": {"coordinates":[-100.14887,26.41573],"type":"Point"}
}