{
  "type": "Feature",
  "properties": {
    "gn:admin1_code":"6.0",
    "gn:admin2_code":"40.0",
    "gn:asciiname":"El Frijolar",
    "gn:country_code":"MX",
    "gn:dem":1527,
    "gn:feature_class":"P",
    "gn:feature_code":"PPL",
    "gn:name":"El Frijolar",
    "gn:population":0,
    "gn:timezone":"America/Chihuahua",
    "iso:country":"MX",
    "name:spa_x_preferred":[
        "El Frijolar"
    ],
    "wof:name":"El Frijolar",
    "wof:placetype":"locality"
},
  "geometry": {"coordinates":[-108.60317000000001,28.89987],"type":"Point"}
}