{
  "type": "Feature",
  "properties": {
    "gn:admin1_code":"6",
    "gn:admin2_code":"31.0",
    "gn:asciiname":"Mesa los Letreros",
    "gn:country_code":"MX",
    "gn:dem":2402,
    "gn:feature_class":"P",
    "gn:feature_code":"PPL",
    "gn:name":"Mesa los Letreros",
    "gn:population":0,
    "gn:timezone":"America/Chihuahua",
    "iso:country":"MX",
    "name:spa_x_preferred":[
        "Mesa los Letreros"
    ],
    "name:und_x_variant":[
        "Mesa de los Letreros"
    ],
    "wof:name":"Mesa los Letreros",
    "wof:placetype":"locality"
},
  "geometry": {"coordinates":[-108.05226,28.37618],"type":"Point"}
}