{
  "type": "Feature",
  "properties": {
    "gn:admin1_code":"28",
    "gn:admin2_code":"32",
    "gn:asciiname":"La Morita",
    "gn:country_code":"MX",
    "gn:dem":42,
    "gn:feature_class":"P",
    "gn:feature_code":"PPL",
    "gn:name":"La Morita",
    "gn:population":16,
    "gn:timezone":"America/Matamoros",
    "iso:country":"MX",
    "wof:name":"La Morita",
    "wof:placetype":"locality",
    "wof:population":16
},
  "geometry": {"coordinates":[-98.505,26.175],"type":"Point"}
}