{
  "type": "Feature",
  "properties": {
    "gn:admin1_code":"24",
    "gn:admin2_code":"11",
    "gn:asciiname":"Potrero el Jaral",
    "gn:country_code":"MX",
    "gn:dem":1017,
    "gn:feature_class":"P",
    "gn:feature_code":"PPL",
    "gn:name":"Potrero el Jaral",
    "gn:population":20,
    "gn:timezone":"America/Mexico_City",
    "iso:country":"MX",
    "wof:name":"Potrero el Jaral",
    "wof:placetype":"locality",
    "wof:population":20
},
  "geometry": {"coordinates":[-100.05889000000001,21.90306],"type":"Point"}
}