{
  "type": "Feature",
  "properties": {
    "gn:admin1_code":"5",
    "gn:admin2_code":"61.0",
    "gn:asciiname":"Nuevo Santa Fe",
    "gn:country_code":"MX",
    "gn:dem":550,
    "gn:feature_class":"P",
    "gn:feature_code":"PPL",
    "gn:name":"Nuevo Santa Fe",
    "gn:population":156,
    "gn:timezone":"America/Mexico_City",
    "iso:country":"MX",
    "wof:name":"Nuevo Santa Fe",
    "wof:placetype":"locality",
    "wof:population":156
},
  "geometry": {"coordinates":[-93.55306,17.0925],"type":"Point"}
}