{
  "type": "Feature",
  "properties": {
    "gn:admin1_code":"7",
    "gn:admin2_code":"27",
    "gn:asciiname":"Luna (Carlos Pereyra)",
    "gn:country_code":"MX",
    "gn:dem":894,
    "gn:feature_class":"P",
    "gn:feature_code":"PPL",
    "gn:name":"Luna (Carlos Pereyra)",
    "gn:population":9,
    "gn:timezone":"America/Monterrey",
    "iso:country":"MX",
    "wof:name":"Luna (Carlos Pereyra)",
    "wof:placetype":"locality",
    "wof:population":9
},
  "geometry": {"coordinates":[-101.03449999999999,26.03224],"type":"Point"}
}