{
  "type": "Feature",
  "properties": {
    "gn:admin1_code":"20",
    "gn:admin2_code":"551.0",
    "gn:asciiname":"San Francisco Tanivet",
    "gn:country_code":"MX",
    "gn:dem":1651,
    "gn:feature_class":"P",
    "gn:feature_code":"PPL",
    "gn:name":"San Francisco Tanivet",
    "gn:population":0,
    "gn:timezone":"America/Mexico_City",
    "iso:country":"MX",
    "name:spa_x_preferred":[
        "San Francisco Tanivei"
    ],
    "name:spa_x_variant":[
        "San Francisco Tanivet"
    ],
    "name:und_x_variant":[
        "Tanive",
        "Tanivei"
    ],
    "wof:name":"San Francisco Tanivet",
    "wof:placetype":"locality"
},
  "geometry": {"coordinates":[-96.43653999999999,16.92283],"type":"Point"}
}