{
  "type": "Feature",
  "properties": {
    "gn:admin1_code":"24",
    "gn:admin2_code":"40.0",
    "gn:asciiname":"Guayabitos",
    "gn:country_code":"MX",
    "gn:dem":68,
    "gn:feature_class":"P",
    "gn:feature_code":"PPL",
    "gn:name":"Guayabitos",
    "gn:population":0,
    "gn:timezone":"America/Mexico_City",
    "iso:country":"MX",
    "name:spa_x_preferred":[
        "Guayabitos"
    ],
    "wof:name":"Guayabitos",
    "wof:placetype":"locality"
},
  "geometry": {"coordinates":[-98.69455000000001,22.10073],"type":"Point"}
}