{
  "type": "Feature",
  "properties": {
    "gn:admin1_code":"4",
    "gn:admin2_code":"11.0",
    "gn:asciiname":"La Franela",
    "gn:country_code":"MX",
    "gn:dem":84,
    "gn:feature_class":"P",
    "gn:feature_code":"PPL",
    "gn:name":"La Franela",
    "gn:population":2,
    "gn:timezone":"America/Merida",
    "iso:country":"MX",
    "wof:name":"La Franela",
    "wof:placetype":"locality",
    "wof:population":2
},
  "geometry": {"coordinates":[-91.06194000000001,17.99194],"type":"Point"}
}