{
  "type": "Feature",
  "properties": {
    "gn:admin1_code":"11.0",
    "gn:admin2_code":"30.0",
    "gn:asciiname":"San Isidro de Capellania",
    "gn:country_code":"MX",
    "gn:dem":2107,
    "gn:feature_class":"P",
    "gn:feature_code":"PPL",
    "gn:name":"San Isidro de Capellan\u00eda",
    "gn:population":144,
    "gn:timezone":"America/Mexico_City",
    "iso:country":"MX",
    "wof:name":"San Isidro de Capellania",
    "wof:placetype":"locality",
    "wof:population":144
},
  "geometry": {"coordinates":[-101.26555999999999,21.36083],"type":"Point"}
}