{
  "type": "Feature",
  "properties": {
    "gn:admin1_code":"8",
    "gn:admin2_code":"7.0",
    "gn:asciiname":"La Rosa de San Jose Lumber",
    "gn:country_code":"MX",
    "gn:dem":600,
    "gn:feature_class":"P",
    "gn:feature_code":"PPL",
    "gn:name":"La Rosa de San Jos\u00e9 Lumber",
    "gn:population":0,
    "gn:timezone":"America/Mexico_City",
    "iso:country":"MX",
    "name:spa_x_preferred":[
        "La Rosa de San Jos\u00e9 Lumber"
    ],
    "name:spa_x_variant":[
        "La Rosa"
    ],
    "wof:name":"La Rosa de San Jose Lumber",
    "wof:placetype":"locality"
},
  "geometry": {"coordinates":[-104.11099,19.18705],"type":"Point"}
}