{
  "type": "Feature",
  "properties": {
    "gn:admin1_code":"30",
    "gn:admin2_code":"125",
    "gn:asciiname":"Los Paredones",
    "gn:country_code":"MX",
    "gn:dem":608,
    "gn:feature_class":"P",
    "gn:feature_code":"PPL",
    "gn:name":"Los Paredones",
    "gn:population":21,
    "gn:timezone":"America/Mexico_City",
    "iso:country":"MX",
    "wof:name":"Los Paredones",
    "wof:placetype":"locality",
    "wof:population":21
},
  "geometry": {"coordinates":[-96.79111,18.99667],"type":"Point"}
}