{
  "type": "Feature",
  "properties": {
    "gn:admin1_code":"24",
    "gn:admin2_code":"39.0",
    "gn:asciiname":"Santa Anita",
    "gn:country_code":"MX",
    "gn:dem":101,
    "gn:feature_class":"P",
    "gn:feature_code":"PPL",
    "gn:name":"Santa Anita",
    "gn:population":0,
    "gn:timezone":"America/Mexico_City",
    "iso:country":"MX",
    "name:spa_x_preferred":[
        "Santa Anita"
    ],
    "wof:name":"Santa Anita",
    "wof:placetype":"locality"
},
  "geometry": {"coordinates":[-98.79613000000001,21.57412],"type":"Point"}
}