{
  "type": "Feature",
  "properties": {
    "gn:admin1_code":"16",
    "gn:admin2_code":"13",
    "gn:asciiname":"La Palmita",
    "gn:country_code":"MX",
    "gn:dem":823,
    "gn:feature_class":"P",
    "gn:feature_code":"PPL",
    "gn:name":"La Palmita",
    "gn:population":50,
    "gn:timezone":"America/Mexico_City",
    "iso:country":"MX",
    "wof:name":"La Palmita",
    "wof:placetype":"locality",
    "wof:population":50
},
  "geometry": {"coordinates":[-100.97139,19.07056],"type":"Point"}
}