{
  "type": "Feature",
  "properties": {
    "gn:admin1_code":"5",
    "gn:admin2_code":"64.0",
    "gn:asciiname":"Pozo de Piedra",
    "gn:country_code":"MX",
    "gn:dem":2208,
    "gn:feature_class":"P",
    "gn:feature_code":"PPL",
    "gn:name":"Pozo de Piedra",
    "gn:population":72,
    "gn:timezone":"America/Mexico_City",
    "iso:country":"MX",
    "wof:name":"Pozo de Piedra",
    "wof:placetype":"locality",
    "wof:population":72
},
  "geometry": {"coordinates":[-92.36944,16.76167],"type":"Point"}
}