{
  "type": "Feature",
  "properties": {
    "gn:admin1_code":"14",
    "gn:asciiname":"El Salitre",
    "gn:country_code":"MX",
    "gn:dem":316,
    "gn:feature_class":"P",
    "gn:feature_code":"PPL",
    "gn:name":"El Salitre",
    "gn:population":0,
    "gn:timezone":"America/Mexico_City",
    "iso:country":"MX",
    "name:spa_x_preferred":[
        "El Salitre"
    ],
    "wof:name":"El Salitre",
    "wof:placetype":"locality"
},
  "geometry": {"coordinates":[-103.33986,18.97475],"type":"Point"}
}