{
  "type": "Feature",
  "properties": {
    "gn:admin1_code":"14",
    "gn:admin2_code":"27.0",
    "gn:asciiname":"Los Terreros",
    "gn:country_code":"MX",
    "gn:dem":520,
    "gn:feature_class":"P",
    "gn:feature_code":"PPL",
    "gn:name":"Los Terreros",
    "gn:population":56,
    "gn:timezone":"America/Mexico_City",
    "iso:country":"MX",
    "wof:name":"Los Terreros",
    "wof:placetype":"locality",
    "wof:population":56
},
  "geometry": {"coordinates":[-104.28667,19.37361],"type":"Point"}
}