{
  "type": "Feature",
  "properties": {
    "gn:admin1_code":"24",
    "gn:admin2_code":"26.0",
    "gn:asciiname":"Tzabitad",
    "gn:country_code":"MX",
    "gn:dem":215,
    "gn:feature_class":"P",
    "gn:feature_code":"PPL",
    "gn:name":"Tzabitad",
    "gn:population":0,
    "gn:timezone":"America/Mexico_City",
    "iso:country":"MX",
    "name:spa_x_preferred":[
        "Tzabitad"
    ],
    "wof:name":"Tzabitad",
    "wof:placetype":"locality"
},
  "geometry": {"coordinates":[-98.88132,21.6314],"type":"Point"}
}