{
  "type": "Feature",
  "properties": {
    "gn:admin1_code":"10",
    "gn:admin2_code":"5.0",
    "gn:asciiname":"San Antonio de Gigantes",
    "gn:country_code":"MX",
    "gn:dem":2387,
    "gn:feature_class":"P",
    "gn:feature_code":"PPL",
    "gn:name":"San Antonio de Gigantes",
    "gn:population":4,
    "gn:timezone":"America/Monterrey",
    "iso:country":"MX",
    "wof:name":"San Antonio de Gigantes",
    "wof:placetype":"locality",
    "wof:population":4
},
  "geometry": {"coordinates":[-105.18984,24.13337000000001],"type":"Point"}
}