{
  "type": "Feature",
  "properties": {
    "gn:admin1_code":"19.0",
    "gn:asciiname":"La Majada",
    "gn:country_code":"MX",
    "gn:dem":414,
    "gn:feature_class":"P",
    "gn:feature_code":"PPL",
    "gn:name":"La Majada",
    "gn:population":0,
    "gn:timezone":"America/Monterrey",
    "iso:country":"MX",
    "name:spa_x_preferred":[
        "La Majada"
    ],
    "wof:name":"La Majada",
    "wof:placetype":"locality"
},
  "geometry": {"coordinates":[-100.21022000000001,25.96448],"type":"Point"}
}