{
  "type": "Feature",
  "properties": {
    "gn:admin1_code":"19",
    "gn:admin2_code":"15.0",
    "gn:asciiname":"Providencia",
    "gn:country_code":"MX",
    "gn:dem":119,
    "gn:feature_class":"P",
    "gn:feature_code":"PPL",
    "gn:name":"Providencia",
    "gn:population":0,
    "gn:timezone":"America/Monterrey",
    "iso:country":"MX",
    "name:spa_x_preferred":[
        "Providencia"
    ],
    "wof:name":"Providencia",
    "wof:placetype":"locality"
},
  "geometry": {"coordinates":[-98.79861,25.975],"type":"Point"}
}