{
  "type": "Feature",
  "properties": {
    "gn:admin1_code":"15",
    "gn:admin2_code":"25.0",
    "gn:asciiname":"El Retorno",
    "gn:country_code":"MX",
    "gn:dem":2822,
    "gn:feature_class":"P",
    "gn:feature_code":"PPL",
    "gn:name":"El Retorno",
    "gn:population":0,
    "gn:timezone":"America/Mexico_City",
    "iso:country":"MX",
    "name:ceb_x_preferred":[
        "El Retorno"
    ],
    "name:deu_x_preferred":[
        "El Retorno"
    ],
    "name:fra_x_preferred":[
        "El Retorno"
    ],
    "name:ita_x_preferred":[
        "El Retorno"
    ],
    "name:msa_x_preferred":[
        "El Retorno"
    ],
    "name:nld_x_preferred":[
        "El Retorno"
    ],
    "name:pol_x_preferred":[
        "El Retorno"
    ],
    "name:por_x_preferred":[
        "El Retorno"
    ],
    "name:sco_x_preferred":[
        "El Retorno"
    ],
    "name:spa_x_preferred":[
        "El Retorno"
    ],
    "name:swe_x_preferred":[
        "El Retorno"
    ],
    "name:tgl_x_preferred":[
        "El Retorno"
    ],
    "name:vie_x_preferred":[
        "El Retorno"
    ],
    "name:war_x_preferred":[
        "El Retorno"
    ],
    "name:zho_x_preferred":[
        "\u57c3\u723e\u96f7\u6258\u8afe"
    ],
    "wof:name":"El Retorno",
    "wof:placetype":"locality"
},
  "geometry": {"coordinates":[-98.76424,19.30192000000001],"type":"Point"}
}