{
  "type": "Feature",
  "properties": {
    "gn:admin1_code":"15.0",
    "gn:admin2_code":"99.0",
    "gn:asciiname":"Junipero",
    "gn:country_code":"MX",
    "gn:dem":2316,
    "gn:feature_class":"P",
    "gn:feature_code":"PPL",
    "gn:name":"Jun\u00edpero",
    "gn:population":0,
    "gn:timezone":"America/Mexico_City",
    "iso:country":"MX",
    "name:spa_x_preferred":[
        "Junipero"
    ],
    "name:spa_x_variant":[
        "Jun\u00edpero"
    ],
    "wof:name":"Junipero",
    "wof:placetype":"locality"
},
  "geometry": {"coordinates":[-98.86490000000001,19.44492],"type":"Point"}
}