{
  "type": "Feature",
  "properties": {
    "gn:admin1_code":"14.0",
    "gn:admin2_code":"58.0",
    "gn:asciiname":"El Tigrito",
    "gn:country_code":"MX",
    "gn:dem":1040,
    "gn:feature_class":"P",
    "gn:feature_code":"PPL",
    "gn:name":"El Tigrito",
    "gn:population":0,
    "gn:timezone":"America/Mexico_City",
    "iso:country":"MX",
    "name:spa_x_preferred":[
        "El Tigrito"
    ],
    "wof:name":"El Tigrito",
    "wof:placetype":"locality"
},
  "geometry": {"coordinates":[-105.09405,20.63301],"type":"Point"}
}