{
  "type": "Feature",
  "properties": {
    "gn:admin1_code":"30",
    "gn:admin2_code":"77.0",
    "gn:asciiname":"Postrera",
    "gn:country_code":"MX",
    "gn:dem":98,
    "gn:feature_class":"P",
    "gn:feature_code":"PPL",
    "gn:name":"Postrera",
    "gn:population":0,
    "gn:timezone":"America/Mexico_City",
    "iso:country":"MX",
    "wof:name":"Postrera",
    "wof:placetype":"locality"
},
  "geometry": {"coordinates":[-95.46666999999999,17.95],"type":"Point"}
}