{
  "type": "Feature",
  "properties": {
    "gn:admin1_code":"6",
    "gn:admin2_code":"20.0",
    "gn:asciiname":"La Tableta",
    "gn:country_code":"MX",
    "gn:dem":1489,
    "gn:feature_class":"P",
    "gn:feature_code":"PPL",
    "gn:name":"La Tableta",
    "gn:population":0,
    "gn:timezone":"America/Chihuahua",
    "iso:country":"MX",
    "name:spa_x_preferred":[
        "La Tableta"
    ],
    "wof:name":"La Tableta",
    "wof:placetype":"locality"
},
  "geometry": {"coordinates":[-108.54201,27.66527],"type":"Point"}
}