{
  "type": "Feature",
  "properties": {
    "gn:admin1_code":"5",
    "gn:admin2_code":"1.0",
    "gn:asciiname":"Maria Esther Zuno de Echeverria",
    "gn:country_code":"MX",
    "gn:dem":408,
    "gn:feature_class":"P",
    "gn:feature_code":"PPL",
    "gn:name":"Mar\u00eda Esther Zuno de Echeverr\u00eda",
    "gn:population":0,
    "gn:timezone":"America/Mexico_City",
    "iso:country":"MX",
    "name:spa_x_preferred":[
        "Mar\u00eda Esther"
    ],
    "name:spa_x_variant":[
        "Mar\u00eda Esther Zuno de Echeverr\u00eda"
    ],
    "wof:name":"Maria Esther Zuno de Echeverria",
    "wof:placetype":"locality"
},
  "geometry": {"coordinates":[-92.72839999999999,15.40615],"type":"Point"}
}