{
  "type": "Feature",
  "properties": {
    "gn:admin1_code":"26",
    "gn:admin2_code":"37.0",
    "gn:asciiname":"Los Cumbros",
    "gn:country_code":"MX",
    "gn:dem":575,
    "gn:feature_class":"P",
    "gn:feature_code":"PPL",
    "gn:name":"Los Cumbros",
    "gn:population":0,
    "gn:timezone":"America/Hermosillo",
    "iso:country":"MX",
    "name:spa_x_preferred":[
        "Los Cumbros"
    ],
    "wof:name":"Los Cumbros",
    "wof:placetype":"locality"
},
  "geometry": {"coordinates":[-110.09892000000001,29.02334],"type":"Point"}
}