{
  "type": "Feature",
  "properties": {
    "gn:admin1_code":"4",
    "gn:admin2_code":"3.0",
    "gn:asciiname":"El Sembrador",
    "gn:country_code":"MX",
    "gn:dem":18,
    "gn:feature_class":"P",
    "gn:feature_code":"PPL",
    "gn:name":"El Sembrador",
    "gn:population":4,
    "gn:timezone":"America/Merida",
    "iso:country":"MX",
    "wof:name":"El Sembrador",
    "wof:placetype":"locality",
    "wof:population":4
},
  "geometry": {"coordinates":[-90.97667,18.68278],"type":"Point"}
}