{
  "type": "Feature",
  "properties": {
    "gn:admin1_code":"5",
    "gn:admin2_code":"69",
    "gn:asciiname":"Santa Cruz",
    "gn:country_code":"MX",
    "gn:dem":29,
    "gn:feature_class":"P",
    "gn:feature_code":"PPL",
    "gn:name":"Santa Cruz",
    "gn:population":9,
    "gn:timezone":"America/Mexico_City",
    "iso:country":"MX",
    "wof:name":"Santa Cruz",
    "wof:placetype":"locality",
    "wof:population":9
},
  "geometry": {"coordinates":[-93.24722,15.69806],"type":"Point"}
}