{
  "type": "Feature",
  "properties": {
    "gn:admin1_code":"23",
    "gn:admin2_code":"9.0",
    "gn:asciiname":"Lol Beh",
    "gn:country_code":"MX",
    "gn:dem":22,
    "gn:feature_class":"P",
    "gn:feature_code":"PPL",
    "gn:name":"Lol Beh",
    "gn:population":5,
    "gn:timezone":"America/Cancun",
    "iso:country":"MX",
    "wof:name":"Lol Beh",
    "wof:placetype":"locality",
    "wof:population":5
},
  "geometry": {"coordinates":[-87.65111999999998,20.4272],"type":"Point"}
}