{
  "type": "Feature",
  "properties": {
    "gn:admin1_code":"7.0",
    "gn:admin2_code":"17.0",
    "gn:asciiname":"El Torito",
    "gn:country_code":"MX",
    "gn:dem":1155,
    "gn:feature_class":"P",
    "gn:feature_code":"PPL",
    "gn:name":"El Torito",
    "gn:population":0,
    "gn:timezone":"America/Monterrey",
    "iso:country":"MX",
    "name:dan_x_preferred":[
        "El Torito"
    ],
    "name:pol_x_preferred":[
        "El Torito"
    ],
    "name:por_x_preferred":[
        "El Torito"
    ],
    "wof:name":"El Torito",
    "wof:placetype":"locality"
},
  "geometry": {"coordinates":[-103.33333,25.38333],"type":"Point"}
}