{
  "type": "Feature",
  "properties": {
    "gn:admin1_code":"26.0",
    "gn:admin2_code":"59.0",
    "gn:asciiname":"El Alamillo",
    "gn:country_code":"MX",
    "gn:dem":1395,
    "gn:feature_class":"P",
    "gn:feature_code":"PPL",
    "gn:name":"El Alamillo",
    "gn:population":0,
    "gn:timezone":"America/Hermosillo",
    "iso:country":"MX",
    "name:und_x_variant":[
        "Rancho El Alamillo",
        "El Alamillo"
    ],
    "wof:name":"El Alamillo",
    "wof:placetype":"locality"
},
  "geometry": {"coordinates":[-110.58194,31.07994],"type":"Point"}
}