{
  "type": "Feature",
  "properties": {
    "gn:admin1_code":"10",
    "gn:admin2_code":"14.0",
    "gn:asciiname":"Las Mesas",
    "gn:country_code":"MX",
    "gn:dem":2389,
    "gn:feature_class":"P",
    "gn:feature_code":"PPL",
    "gn:name":"Las Mesas",
    "gn:population":0,
    "gn:timezone":"America/Monterrey",
    "iso:country":"MX",
    "name:spa_x_preferred":[
        "Las Mesas"
    ],
    "wof:name":"Las Mesas",
    "wof:placetype":"locality"
},
  "geometry": {"coordinates":[-104.3556,22.80592],"type":"Point"}
}