{
  "type": "Feature",
  "properties": {
    "gn:admin1_code":"12.0",
    "gn:admin2_code":"73.0",
    "gn:asciiname":"El Hilamo",
    "gn:country_code":"MX",
    "gn:dem":486,
    "gn:feature_class":"P",
    "gn:feature_code":"PPL",
    "gn:name":"El Hilamo",
    "gn:population":55,
    "gn:timezone":"America/Mexico_City",
    "iso:country":"MX",
    "wof:name":"El Hilamo",
    "wof:placetype":"locality",
    "wof:population":55
},
  "geometry": {"coordinates":[-101.3079,18.40555],"type":"Point"}
}