{
  "type": "Feature",
  "properties": {
    "gn:admin1_code":"13",
    "gn:admin2_code":"56.0",
    "gn:asciiname":"Colonia Felipe Angeles",
    "gn:country_code":"MX",
    "gn:dem":2258,
    "gn:feature_class":"P",
    "gn:feature_code":"PPL",
    "gn:name":"Colonia Felipe \u00c1ngeles",
    "gn:population":2045,
    "gn:timezone":"America/Mexico_City",
    "iso:country":"MX",
    "name:und_x_variant":[
        "Colonia Felipe \u00c1ngeles"
    ],
    "wof:name":"Colonia Felipe Angeles",
    "wof:placetype":"locality",
    "wof:population":2045
},
  "geometry": {"coordinates":[-98.41861,20.05417000000001],"type":"Point"}
}