{
  "type": "Feature",
  "properties": {
    "gn:admin1_code":"21",
    "gn:admin2_code":"19.0",
    "gn:asciiname":"Los Pericos",
    "gn:country_code":"MX",
    "gn:dem":1810,
    "gn:feature_class":"P",
    "gn:feature_code":"PPL",
    "gn:name":"Los Pericos",
    "gn:population":70,
    "gn:timezone":"America/Mexico_City",
    "iso:country":"MX",
    "wof:name":"Los Pericos",
    "wof:placetype":"locality",
    "wof:population":70
},
  "geometry": {"coordinates":[-98.48081000000001,18.85821],"type":"Point"}
}