{
  "type": "Feature",
  "properties": {
    "gn:admin1_code":"20",
    "gn:admin2_code":"22",
    "gn:asciiname":"Cabrillas",
    "gn:country_code":"MX",
    "gn:dem":1485,
    "gn:feature_class":"P",
    "gn:feature_code":"PPL",
    "gn:name":"Cabrillas",
    "gn:population":14,
    "gn:timezone":"America/Mexico_City",
    "iso:country":"MX",
    "wof:name":"Cabrillas",
    "wof:placetype":"locality",
    "wof:population":14
},
  "geometry": {"coordinates":[-97.85693999999999,18.11194],"type":"Point"}
}