{
  "type": "Feature",
  "properties": {
    "gn:admin1_code":"3",
    "gn:admin2_code":"2.0",
    "gn:asciiname":"El Huerivo",
    "gn:country_code":"MX",
    "gn:dem":743,
    "gn:feature_class":"P",
    "gn:feature_code":"PPL",
    "gn:name":"El Hu\u00e9rivo",
    "gn:population":5,
    "gn:timezone":"America/Mazatlan",
    "iso:country":"MX",
    "name:und_x_variant":[
        "El Hu\u00e9rivo"
    ],
    "wof:name":"El Huerivo",
    "wof:placetype":"locality",
    "wof:population":5
},
  "geometry": {"coordinates":[-112.46469999999999,27.00252],"type":"Point"}
}