{
  "type": "Feature",
  "properties": {
    "gn:admin1_code":"20",
    "gn:admin2_code":"469.0",
    "gn:asciiname":"La Luz Llano Nopal",
    "gn:country_code":"MX",
    "gn:dem":819,
    "gn:feature_class":"P",
    "gn:feature_code":"PPL",
    "gn:name":"La Luz Llano Nopal",
    "gn:population":0,
    "gn:timezone":"America/Mexico_City",
    "iso:country":"MX",
    "name:spa_x_preferred":[
        "Llano del Nopal"
    ],
    "name:und_x_variant":[
        "La Luz"
    ],
    "wof:name":"La Luz Llano Nopal",
    "wof:placetype":"locality"
},
  "geometry": {"coordinates":[-97.97517000000001,17.06252000000001],"type":"Point"}
}