{
  "type": "Feature",
  "properties": {
    "gn:admin1_code":"11",
    "gn:admin2_code":"3.0",
    "gn:asciiname":"San Jose de la Cruz",
    "gn:country_code":"MX",
    "gn:dem":2008,
    "gn:feature_class":"P",
    "gn:feature_code":"PPL",
    "gn:name":"San Jos\u00e9 de la Cruz",
    "gn:population":224,
    "gn:timezone":"America/Mexico_City",
    "iso:country":"MX",
    "name:und_x_variant":[
        "San Jos\u00e9 de la Cruz"
    ],
    "wof:name":"San Jose de la Cruz",
    "wof:placetype":"locality",
    "wof:population":224
},
  "geometry": {"coordinates":[-100.57138999999999,21.09833],"type":"Point"}
}