{
  "type": "Feature",
  "properties": {
    "gn:admin1_code":"20",
    "gn:admin2_code":"431.0",
    "gn:asciiname":"Tres Cruces",
    "gn:country_code":"MX",
    "gn:dem":1317,
    "gn:feature_class":"P",
    "gn:feature_code":"PPL",
    "gn:name":"Tres Cruces",
    "gn:population":0,
    "gn:timezone":"America/Mexico_City",
    "iso:country":"MX",
    "wof:name":"Tres Cruces",
    "wof:placetype":"locality"
},
  "geometry": {"coordinates":[-96.96666999999999,17.96667],"type":"Point"}
}