{
  "type": "Feature",
  "properties": {
    "gn:admin1_code":"15",
    "gn:admin2_code":"117.0",
    "gn:asciiname":"Cerros Cuates",
    "gn:country_code":"MX",
    "gn:dem":2142,
    "gn:feature_class":"P",
    "gn:feature_code":"PPL",
    "gn:name":"Cerros Cuates",
    "gn:population":90,
    "gn:timezone":"America/Mexico_City",
    "iso:country":"MX",
    "wof:name":"Cerros Cuates",
    "wof:placetype":"locality",
    "wof:population":90
},
  "geometry": {"coordinates":[-99.86778,18.68972],"type":"Point"}
}