{
  "type": "Feature",
  "properties": {
    "gn:admin1_code":"20",
    "gn:admin2_code":"378",
    "gn:asciiname":"Yegovego",
    "gn:country_code":"MX",
    "gn:dem":1633,
    "gn:feature_class":"P",
    "gn:feature_code":"PPL",
    "gn:name":"Yegovego",
    "gn:population":32,
    "gn:timezone":"America/Mexico_City",
    "iso:country":"MX",
    "wof:name":"Yegovego",
    "wof:placetype":"locality",
    "wof:population":32
},
  "geometry": {"coordinates":[-96.89694,16.79306],"type":"Point"}
}