{
  "type": "Feature",
  "properties": {
    "gn:admin1_code":"13.0",
    "gn:admin2_code":"53.0",
    "gn:asciiname":"Agua Hedionda",
    "gn:country_code":"MX",
    "gn:dem":1025,
    "gn:feature_class":"P",
    "gn:feature_code":"PPL",
    "gn:name":"Agua Hedionda",
    "gn:population":78,
    "gn:timezone":"America/Mexico_City",
    "iso:country":"MX",
    "name:spa_x_preferred":[
        "Agua Hedionda"
    ],
    "wof:name":"Agua Hedionda",
    "wof:placetype":"locality",
    "wof:population":78
},
  "geometry": {"coordinates":[-98.16083,20.50806],"type":"Point"}
}