{
  "type": "Feature",
  "properties": {
    "gn:admin1_code":"14",
    "gn:admin2_code":"84",
    "gn:asciiname":"El Capulin del Veladero",
    "gn:country_code":"MX",
    "gn:dem":1264,
    "gn:feature_class":"P",
    "gn:feature_code":"PPL",
    "gn:name":"El Capul\u00edn del Veladero",
    "gn:population":12,
    "gn:timezone":"America/Mexico_City",
    "iso:country":"MX",
    "name:und_x_variant":[
        "El Capul\u00edn del Veladero"
    ],
    "wof:name":"El Capulin del Veladero",
    "wof:placetype":"locality",
    "wof:population":12
},
  "geometry": {"coordinates":[-104.79000000000001,20.26944],"type":"Point"}
}