{
  "type": "Feature",
  "properties": {
    "gn:admin1_code":"21.0",
    "gn:asciiname":"El Garambuyo",
    "gn:country_code":"MX",
    "gn:dem":1753,
    "gn:feature_class":"P",
    "gn:feature_code":"PPL",
    "gn:name":"El Garambuyo",
    "gn:population":0,
    "gn:timezone":"America/Mexico_City",
    "iso:country":"MX",
    "name:spa_x_preferred":[
        "El Garambuyo"
    ],
    "wof:name":"El Garambuyo",
    "wof:placetype":"locality"
},
  "geometry": {"coordinates":[-98.11516,18.31115],"type":"Point"}
}