{
  "type": "Feature",
  "properties": {
    "gn:country":"MX",
    "gn:fcode":"PPL",
    "gn:population":0,
    "iso:country":"MX",
    "name:spa_x_preferred":[
        "Milpillas"
    ],
    "name:spa_x_variant":[
        "Milpitas"
    ],
    "qs_pg:aaroncc":"MX",
    "qs_pg:gn_country":"MX",
    "qs_pg:gn_fcode":"PPL",
    "qs_pg:gn_pop":0,
    "qs_pg:name":"Militar",
    "qs_pg:name_adm0":"M\u00e9xico",
    "qs_pg:name_adm1":"Zacatecas",
    "qs_pg:photos":12,
    "qs_pg:photos_1k":2,
    "qs_pg:photos_9k":1,
    "qs_pg:photos_9r":1,
    "qs_pg:photos_all":12,
    "qs_pg:photos_sr":1,
    "qs_pg:pop_sr":0,
    "qs_pg:qs_pg_placetype":"neighbourhood",
    "qs_pg:qs_pg_placetype_gp":"Suburb",
    "qs_pg:woe_adm0":23424900,
    "woe:adm0_id":23424900,
    "woe:name_adm0":"M\u00e9xico",
    "woe:name_adm1":"Zacatecas",
    "woe:placetype":"Suburb",
    "wof:name":"Militar",
    "wof:placetype":"neighbourhood"
},
  "geometry": {"coordinates":[-103.30124000000001,23.10089],"type":"Point"}
}