{
  "type": "Feature",
  "properties": {
    "gn:admin1_code":"30",
    "gn:admin2_code":"83.0",
    "gn:asciiname":"La Pita",
    "gn:country_code":"MX",
    "gn:dem":198,
    "gn:feature_class":"P",
    "gn:feature_code":"PPL",
    "gn:name":"La Pita",
    "gn:population":499,
    "gn:timezone":"America/Mexico_City",
    "iso:country":"MX",
    "wof:name":"La Pita",
    "wof:placetype":"locality",
    "wof:population":499
},
  "geometry": {"coordinates":[-98.05167,20.78694],"type":"Point"}
}