{
  "type": "Feature",
  "properties": {
    "gn:admin1_code":"30",
    "gn:admin2_code":"122.0",
    "gn:asciiname":"El Manantial",
    "gn:country_code":"MX",
    "gn:dem":96,
    "gn:feature_class":"P",
    "gn:feature_code":"PPL",
    "gn:name":"El Manantial",
    "gn:population":6,
    "gn:timezone":"America/Mexico_City",
    "iso:country":"MX",
    "wof:name":"El Manantial",
    "wof:placetype":"locality",
    "wof:population":6
},
  "geometry": {"coordinates":[-94.66972,18.24667],"type":"Point"}
}