{
  "type": "Feature",
  "properties": {
    "gn:admin1_code":"30",
    "gn:admin2_code":"101",
    "gn:asciiname":"Vuelta Grande",
    "gn:country_code":"MX",
    "gn:dem":1815,
    "gn:feature_class":"P",
    "gn:feature_code":"PPL",
    "gn:name":"Vuelta Grande",
    "gn:population":39,
    "gn:timezone":"America/Mexico_City",
    "iso:country":"MX",
    "wof:name":"Vuelta Grande",
    "wof:placetype":"locality",
    "wof:population":39
},
  "geometry": {"coordinates":[-97.15056,18.94222],"type":"Point"}
}