{
  "type": "Feature",
  "properties": {
    "gn:admin1_code":"5",
    "gn:admin2_code":"59.0",
    "gn:asciiname":"Busilja",
    "gn:country_code":"MX",
    "gn:dem":148,
    "gn:feature_class":"P",
    "gn:feature_code":"PPL",
    "gn:name":"Busilj\u00e1",
    "gn:population":0,
    "gn:timezone":"America/Mexico_City",
    "iso:country":"MX",
    "name:spa_x_preferred":[
        "Busilj\u00e1"
    ],
    "wof:name":"Busilja",
    "wof:placetype":"locality"
},
  "geometry": {"coordinates":[-91.36065000000001,17.06078],"type":"Point"}
}