{
  "type": "Feature",
  "properties": {
    "gn:admin1_code":"5",
    "gn:admin2_code":"23.0",
    "gn:asciiname":"Bautista Grande",
    "gn:country_code":"MX",
    "gn:dem":2474,
    "gn:feature_class":"P",
    "gn:feature_code":"PPL",
    "gn:name":"Bautista Grande",
    "gn:population":0,
    "gn:timezone":"America/Mexico_City",
    "iso:country":"MX",
    "name:spa_x_preferred":[
        "Bautista Grande"
    ],
    "wof:name":"Bautista Grande",
    "wof:placetype":"locality"
},
  "geometry": {"coordinates":[-92.73421999999999,16.80205],"type":"Point"}
}