{
  "type": "Feature",
  "properties": {
    "gn:admin1_code":"30",
    "gn:admin2_code":"38.0",
    "gn:asciiname":"El Peru",
    "gn:country_code":"MX",
    "gn:dem":1286,
    "gn:feature_class":"P",
    "gn:feature_code":"PPL",
    "gn:name":"El Per\u00fa",
    "gn:population":8,
    "gn:timezone":"America/Mexico_City",
    "iso:country":"MX",
    "name:und_x_variant":[
        "El Per\u00fa"
    ],
    "wof:name":"El Peru",
    "wof:placetype":"locality",
    "wof:population":8
},
  "geometry": {"coordinates":[-96.98556000000001,19.46056],"type":"Point"}
}