{
  "type": "Feature",
  "properties": {
    "gn:admin1_code":"25",
    "gn:admin2_code":"17.0",
    "gn:asciiname":"La Noria",
    "gn:country_code":"MX",
    "gn:dem":568,
    "gn:feature_class":"P",
    "gn:feature_code":"PPL",
    "gn:name":"La Noria",
    "gn:population":8,
    "gn:timezone":"America/Mazatlan",
    "iso:country":"MX",
    "wof:name":"La Noria",
    "wof:placetype":"locality",
    "wof:population":8
},
  "geometry": {"coordinates":[-107.9365,25.9436],"type":"Point"}
}