{
  "type": "Feature",
  "properties": {
    "gn:admin1_code":"7",
    "gn:admin2_code":"27.0",
    "gn:asciiname":"Landeros",
    "gn:country_code":"MX",
    "gn:dem":1524,
    "gn:feature_class":"P",
    "gn:feature_code":"PPL",
    "gn:name":"Landeros",
    "gn:population":0,
    "gn:timezone":"America/Monterrey",
    "iso:country":"MX",
    "name:spa_x_preferred":[
        "Landeros"
    ],
    "wof:name":"Landeros",
    "wof:placetype":"locality"
},
  "geometry": {"coordinates":[-100.87858,25.50504],"type":"Point"}
}