{
  "type": "Feature",
  "properties": {
    "gn:admin1_code":"20",
    "gn:admin2_code":"273.0",
    "gn:asciiname":"Soledad Peras",
    "gn:country_code":"MX",
    "gn:dem":2733,
    "gn:feature_class":"P",
    "gn:feature_code":"PPL",
    "gn:name":"Soledad Peras",
    "gn:population":0,
    "gn:timezone":"America/Mexico_City",
    "iso:country":"MX",
    "name:spa_x_preferred":[
        "La Soledad Peras"
    ],
    "name:spa_x_variant":[
        "Soledad Peras"
    ],
    "wof:name":"Soledad Peras",
    "wof:placetype":"locality"
},
  "geometry": {"coordinates":[-96.93595000000001,16.9655],"type":"Point"}
}