{
  "type": "Feature",
  "properties": {
    "gn:admin1_code":"2",
    "gn:admin2_code":"4.0",
    "gn:asciiname":"Las Moras (La Nopalera)",
    "gn:country_code":"MX",
    "gn:dem":157,
    "gn:feature_class":"P",
    "gn:feature_code":"PPL",
    "gn:name":"Las Moras (La Nopalera)",
    "gn:population":5,
    "gn:timezone":"America/Tijuana",
    "iso:country":"MX",
    "wof:name":"Las Moras (La Nopalera)",
    "wof:placetype":"locality",
    "wof:population":5
},
  "geometry": {"coordinates":[-116.81667,32.48556],"type":"Point"}
}