{
  "type": "Feature",
  "properties": {
    "gn:admin1_code":"31",
    "gn:admin2_code":"56.0",
    "gn:asciiname":"Jaime",
    "gn:country_code":"MX",
    "gn:dem":30,
    "gn:feature_class":"P",
    "gn:feature_code":"PPL",
    "gn:name":"Jaime",
    "gn:population":8,
    "gn:timezone":"America/Merida",
    "iso:country":"MX",
    "name:deu_x_preferred":[
        "Jaime"
    ],
    "name:ita_x_preferred":[
        "Jaime"
    ],
    "name:jpn_x_preferred":[
        "\u30cf\u30a4\u30e1"
    ],
    "name:por_x_preferred":[
        "Jaime"
    ],
    "name:ukr_x_preferred":[
        "\u0425\u0430\u0439\u043c\u0435"
    ],
    "wof:name":"Jaime",
    "wof:placetype":"locality",
    "wof:population":8
},
  "geometry": {"coordinates":[-89.38472,20.28806],"type":"Point"}
}