{
  "type": "Feature",
  "properties": {
    "gn:admin1_code":"31",
    "gn:admin2_code":"56.0",
    "gn:asciiname":"Jaime",
    "gn:country_code":"MX",
    "gn:dem":30,
    "gn:feature_class":"P",
    "gn:feature_code":"PPL",
    "gn:name":"Jaime",
    "gn:population":8,
    "gn:timezone":"America/Merida",
    "iso:country":"MX",
    "wof:name":"Jaime",
    "wof:placetype":"locality",
    "wof:population":8
},
  "geometry": {"coordinates":[-89.38472,20.28806],"type":"Point"}
}