{
  "type": "Feature",
  "properties": {
    "gn:admin1_code":"4",
    "gn:admin2_code":"11.0",
    "gn:asciiname":"Esmeralda (Samudio)",
    "gn:country_code":"MX",
    "gn:dem":83,
    "gn:feature_class":"P",
    "gn:feature_code":"PPL",
    "gn:name":"Esmeralda (Samudio)",
    "gn:population":8,
    "gn:timezone":"America/Merida",
    "iso:country":"MX",
    "wof:name":"Esmeralda (Samudio)",
    "wof:placetype":"locality",
    "wof:population":8
},
  "geometry": {"coordinates":[-90.67361,18.08583],"type":"Point"}
}