{
  "type": "Feature",
  "properties": {
    "gn:admin1_code":"12",
    "gn:admin2_code":"29.0",
    "gn:asciiname":"Agua de Obispo",
    "gn:country_code":"MX",
    "gn:dem":960,
    "gn:feature_class":"P",
    "gn:feature_code":"PPL",
    "gn:name":"Agua de Obispo",
    "gn:population":8,
    "gn:timezone":"America/Mexico_City",
    "iso:country":"MX",
    "wof:name":"Agua de Obispo",
    "wof:placetype":"locality",
    "wof:population":8
},
  "geometry": {"coordinates":[-99.46821,17.31935],"type":"Point"}
}