{
  "type": "Feature",
  "properties": {
    "gn:admin1_code":"6",
    "gn:admin2_code":"62.0",
    "gn:asciiname":"David Armendariz",
    "gn:country_code":"MX",
    "gn:dem":1205,
    "gn:feature_class":"P",
    "gn:feature_code":"PPL",
    "gn:name":"David Armend\u00e1riz",
    "gn:population":7,
    "gn:timezone":"America/Chihuahua",
    "iso:country":"MX",
    "name:und_x_variant":[
        "David Armend\u00e1riz"
    ],
    "wof:name":"David Armendariz",
    "wof:placetype":"locality",
    "wof:population":7
},
  "geometry": {"coordinates":[-105.23573,27.97577],"type":"Point"}
}