{
  "type": "Feature",
  "properties": {
    "gn:admin1_code":"22",
    "gn:admin2_code":"11",
    "gn:asciiname":"Familia Esteban",
    "gn:country_code":"MX",
    "gn:dem":1920,
    "gn:feature_class":"P",
    "gn:feature_code":"PPL",
    "gn:name":"Familia Esteban",
    "gn:population":27,
    "gn:timezone":"America/Mexico_City",
    "iso:country":"MX",
    "wof:name":"Familia Esteban",
    "wof:placetype":"locality",
    "wof:population":27
},
  "geometry": {"coordinates":[-100.27083,20.69944],"type":"Point"}
}