{
  "type": "Feature",
  "properties": {
    "gn:admin1_code":"6",
    "gn:admin2_code":"44.0",
    "gn:asciiname":"Rancho Los Nogales",
    "gn:country_code":"MX",
    "gn:dem":1754,
    "gn:feature_class":"P",
    "gn:feature_code":"PPL",
    "gn:name":"Rancho Los Nogales",
    "gn:population":0,
    "gn:timezone":"America/Chihuahua",
    "iso:country":"MX",
    "wof:name":"Rancho Los Nogales",
    "wof:placetype":"locality"
},
  "geometry": {"coordinates":[-105.61667,26.78333],"type":"Point"}
}