{
  "type": "Feature",
  "properties": {
    "gn:admin1_code":"18.0",
    "gn:admin2_code":"14.0",
    "gn:asciiname":"Ixtapa",
    "gn:cc2":"MX",
    "gn:country_code":"MX",
    "gn:dem":276,
    "gn:feature_class":"P",
    "gn:feature_code":"PPL",
    "gn:name":"Ixtapa",
    "gn:population":17,
    "gn:timezone":"America/Mazatlan",
    "iso:country":"MX",
    "name:und_x_variant":[
        "Ixtapan",
        "Ixtapa"
    ],
    "wof:name":"Ixtapa",
    "wof:placetype":"locality",
    "wof:population":17
},
  "geometry": {"coordinates":[-104.46583,21.42444],"type":"Point"}
}