{
  "type": "Feature",
  "properties": {
    "gn:admin1_code":"5.0",
    "gn:admin2_code":"108.0",
    "gn:asciiname":"Calzada del Gorro",
    "gn:country_code":"MX",
    "gn:dem":840,
    "gn:feature_class":"P",
    "gn:feature_code":"PPL",
    "gn:name":"Calzada del Gorro",
    "gn:population":0,
    "gn:timezone":"America/Mexico_City",
    "iso:country":"MX",
    "name:spa_x_preferred":[
        "Calzada del Gorro"
    ],
    "wof:name":"Calzada del Gorro",
    "wof:placetype":"locality"
},
  "geometry": {"coordinates":[-93.07899999999999,16.47233],"type":"Point"}
}