{
  "type": "Feature",
  "properties": {
    "gn:admin1_code":"32",
    "gn:admin2_code":"39.0",
    "gn:asciiname":"Anastasio V. Hinojosa",
    "gn:country_code":"MX",
    "gn:dem":2011,
    "gn:feature_class":"P",
    "gn:feature_code":"PPL",
    "gn:name":"Anastasio V. Hinojosa",
    "gn:population":356,
    "gn:timezone":"America/Mexico_City",
    "iso:country":"MX",
    "wof:name":"Anastasio V. Hinojosa",
    "wof:placetype":"locality",
    "wof:population":356
},
  "geometry": {"coordinates":[-102.95556000000001,23.715],"type":"Point"}
}