{
  "type": "Feature",
  "properties": {
    "gn:admin1_code":"30",
    "gn:admin2_code":"128.0",
    "gn:asciiname":"Xaltepec",
    "gn:country_code":"MX",
    "gn:dem":2356,
    "gn:feature_class":"P",
    "gn:feature_code":"PPL",
    "gn:name":"Xaltepec",
    "gn:population":0,
    "gn:timezone":"America/Mexico_City",
    "iso:country":"MX",
    "name:und_x_variant":[
        "San Isidro"
    ],
    "wof:name":"Xaltepec",
    "wof:placetype":"locality"
},
  "geometry": {"coordinates":[-97.35581999999999,19.38097],"type":"Point"}
}