{
  "type": "Feature",
  "properties": {
    "gn:admin1_code":"15",
    "gn:admin2_code":"82",
    "gn:asciiname":"La Angostura Primera",
    "gn:country_code":"MX",
    "gn:dem":1132,
    "gn:feature_class":"P",
    "gn:feature_code":"PPL",
    "gn:name":"La Angostura Primera",
    "gn:population":11,
    "gn:timezone":"America/Mexico_City",
    "iso:country":"MX",
    "wof:name":"La Angostura Primera",
    "wof:placetype":"locality",
    "wof:population":11
},
  "geometry": {"coordinates":[-100.27627,19.00767],"type":"Point"}
}