{
  "type": "Feature",
  "properties": {
    "gn:gn_country":"MX",
    "gn:gn_fcode":"PPL",
    "gn:gn_pop":450,
    "gn:population":450,
    "iso:country":"MX",
    "name:spa_x_preferred":[
        "El Chauz"
    ],
    "qs_pg:aaroncc":"MX",
    "qs_pg:gn_country":"MX",
    "qs_pg:gn_fcode":"PPL",
    "qs_pg:gn_pop":450,
    "qs_pg:name":"El Chauz",
    "qs_pg:photos_9r":0,
    "qs_pg:photos_sr":0,
    "qs_pg:pop_sr":2,
    "qs_pg:qs_pg_placetype":"locality",
    "wof:name":"El Chauz",
    "wof:placetype":"locality",
    "wof:population":450
},
  "geometry": {"coordinates":[-102.03972,18.89233],"type":"Point"}
}