{
  "type": "Feature",
  "properties": {
    "gn:admin1_code":"8.0",
    "gn:admin2_code":"9.0",
    "gn:asciiname":"Doble \"R\"",
    "gn:country_code":"MX",
    "gn:dem":27,
    "gn:feature_class":"P",
    "gn:feature_code":"PPL",
    "gn:name":"Doble \"R\"",
    "gn:population":0,
    "gn:timezone":"America/Mexico_City",
    "iso:country":"MX",
    "name:spa_x_preferred":[
        "Doble \u201dR\u201d"
    ],
    "wof:name":"Doble \"R\"",
    "wof:placetype":"locality"
},
  "geometry": {"coordinates":[-103.84781,18.89026],"type":"Point"}
}