{
  "type": "Feature",
  "properties": {
    "gn:admin1_code":"19.0",
    "gn:admin2_code":"11.0",
    "gn:asciiname":"La Coma Gacha",
    "gn:country_code":"MX",
    "gn:dem":277,
    "gn:feature_class":"P",
    "gn:feature_code":"PPL",
    "gn:name":"La Coma Gacha",
    "gn:population":0,
    "gn:timezone":"America/Monterrey",
    "iso:country":"MX",
    "name:spa_x_preferred":[
        "La Coma Gacha"
    ],
    "wof:name":"La Coma Gacha",
    "wof:placetype":"locality"
},
  "geometry": {"coordinates":[-99.65711,26.19934],"type":"Point"}
}