{
  "type": "Feature",
  "properties": {
    "gn:admin1_code":"1",
    "gn:admin2_code":"7",
    "gn:asciiname":"Rancho de los Suarez",
    "gn:country_code":"MX",
    "gn:dem":1926,
    "gn:feature_class":"P",
    "gn:feature_code":"PPL",
    "gn:name":"Rancho de los Su\u00e1rez",
    "gn:population":11,
    "gn:timezone":"America/Mexico_City",
    "iso:country":"MX",
    "name:und_x_variant":[
        "Rancho de los Su\u00e1rez"
    ],
    "wof:name":"Rancho de los Suarez",
    "wof:placetype":"locality",
    "wof:population":11
},
  "geometry": {"coordinates":[-102.30833,22.19333],"type":"Point"}
}