{
  "type": "Feature",
  "properties": {
    "gn:admin1_code":"6.0",
    "gn:admin2_code":"62.0",
    "gn:asciiname":"Ancon de Carros",
    "gn:country_code":"MX",
    "gn:dem":1190,
    "gn:feature_class":"P",
    "gn:feature_code":"PPL",
    "gn:name":"Anc\u00f3n de Carros",
    "gn:population":0,
    "gn:timezone":"America/Chihuahua",
    "iso:country":"MX",
    "name:spa_x_preferred":[
        "Anc\u00f3n de Carros"
    ],
    "wof:name":"Ancon de Carros",
    "wof:placetype":"locality"
},
  "geometry": {"coordinates":[-105.23694999999999,27.99182],"type":"Point"}
}