{
  "type": "Feature",
  "properties": {
    "gn:admin1_code":"30",
    "gn:admin2_code":"70",
    "gn:asciiname":"Los Arellano",
    "gn:country_code":"MX",
    "gn:dem":26,
    "gn:feature_class":"P",
    "gn:feature_code":"PPL",
    "gn:name":"Los Arellano",
    "gn:population":23,
    "gn:timezone":"America/Mexico_City",
    "iso:country":"MX",
    "wof:name":"Los Arellano",
    "wof:placetype":"locality",
    "wof:population":23
},
  "geometry": {"coordinates":[-94.46528000000001,17.61332999999999],"type":"Point"}
}