{
  "type": "Feature",
  "properties": {
    "gn:admin1_code":"2",
    "gn:admin2_code":"3.0",
    "gn:asciiname":"Familia Luna (Valle de las Palmas)",
    "gn:country_code":"MX",
    "gn:dem":504,
    "gn:feature_class":"P",
    "gn:feature_code":"PPL",
    "gn:name":"Familia Luna (Valle de las Palmas)",
    "gn:population":8,
    "gn:timezone":"America/Tijuana",
    "iso:country":"MX",
    "wof:name":"Familia Luna (Valle de las Palmas)",
    "wof:placetype":"locality",
    "wof:population":8
},
  "geometry": {"coordinates":[-116.67278,32.54361],"type":"Point"}
}