{
  "type": "Feature",
  "properties": {
    "gn:admin1_code":"28.0",
    "gn:admin2_code":"22.0",
    "gn:asciiname":"El Palmito",
    "gn:country_code":"MX",
    "gn:dem":12,
    "gn:feature_class":"P",
    "gn:feature_code":"PPL",
    "gn:name":"El Palmito",
    "gn:population":0,
    "gn:timezone":"America/Matamoros",
    "iso:country":"MX",
    "name:spa_x_preferred":[
        "El Palmito"
    ],
    "wof:name":"El Palmito",
    "wof:placetype":"locality"
},
  "geometry": {"coordinates":[-97.56433,25.75056],"type":"Point"}
}