{
  "type": "Feature",
  "properties": {
    "gn:admin1_code":"21",
    "gn:admin2_code":"74.0",
    "gn:asciiname":"Jose Lopez Portillo",
    "gn:country_code":"MX",
    "gn:dem":2271,
    "gn:feature_class":"P",
    "gn:feature_code":"PPL",
    "gn:name":"Jos\u00e9 L\u00f3pez Portillo",
    "gn:population":156,
    "gn:timezone":"America/Mexico_City",
    "iso:country":"MX",
    "name:und_x_variant":[
        "Jos\u00e9 L\u00f3pez Portillo"
    ],
    "wof:name":"Jose Lopez Portillo",
    "wof:placetype":"locality",
    "wof:population":156
},
  "geometry": {"coordinates":[-98.42283999999999,19.18502],"type":"Point"}
}