{
  "type": "Feature",
  "properties": {
    "gn:admin1_code":"30",
    "gn:admin2_code":"61.0",
    "gn:asciiname":"San Judas Tadeo",
    "gn:country_code":"MX",
    "gn:dem":40,
    "gn:feature_class":"P",
    "gn:feature_code":"PPL",
    "gn:name":"San Judas Tadeo",
    "gn:population":5,
    "gn:timezone":"America/Mexico_City",
    "iso:country":"MX",
    "wof:name":"San Judas Tadeo",
    "wof:placetype":"locality",
    "wof:population":5
},
  "geometry": {"coordinates":[-94.21805999999999,17.92611],"type":"Point"}
}