{
  "type": "Feature",
  "properties": {
    "gn:admin1_code":"6",
    "gn:admin2_code":"1.0",
    "gn:asciiname":"El Medano",
    "gn:country_code":"MX",
    "gn:dem":1411,
    "gn:feature_class":"P",
    "gn:feature_code":"PPL",
    "gn:name":"El M\u00e9dano",
    "gn:population":0,
    "gn:timezone":"America/Chihuahua",
    "iso:country":"MX",
    "name:spa_x_preferred":[
        "El M\u00e9dano"
    ],
    "wof:name":"El Medano",
    "wof:placetype":"locality"
},
  "geometry": {"coordinates":[-105.89931,30.79855],"type":"Point"}
}