{
  "type": "Feature",
  "properties": {
    "gn:admin1_code":"10",
    "gn:admin2_code":"32.0",
    "gn:asciiname":"Cordon del Tabaco",
    "gn:country_code":"MX",
    "gn:dem":2058,
    "gn:feature_class":"P",
    "gn:feature_code":"PPL",
    "gn:name":"Cord\u00f3n del Tabaco",
    "gn:population":4,
    "gn:timezone":"America/Monterrey",
    "iso:country":"MX",
    "name:und_x_variant":[
        "Cord\u00f3n del Tabaco"
    ],
    "wof:name":"Cordon del Tabaco",
    "wof:placetype":"locality",
    "wof:population":4
},
  "geometry": {"coordinates":[-106.39646999999999,25.05137],"type":"Point"}
}