{
  "type": "Feature",
  "properties": {
    "gn:admin1_code":"16",
    "gn:admin2_code":"75",
    "gn:asciiname":"El Corralon de Transito (El Rastro)",
    "gn:country_code":"MX",
    "gn:dem":1301,
    "gn:feature_class":"P",
    "gn:feature_code":"PPL",
    "gn:name":"El Corral\u00f3n de Tr\u00e1nsito (El Rastro)",
    "gn:population":13,
    "gn:timezone":"America/Mexico_City",
    "iso:country":"MX",
    "name:und_x_variant":[
        "El Corral\u00f3n de Tr\u00e1nsito (El Rastro)"
    ],
    "wof:name":"El Corralon de Transito (El Rastro)",
    "wof:placetype":"locality",
    "wof:population":13
},
  "geometry": {"coordinates":[-102.47778,19.60667],"type":"Point"}
}