{
  "type": "Feature",
  "properties": {
    "gn:admin1_code":"16",
    "gn:admin2_code":"92.0",
    "gn:asciiname":"Parota el Reparo",
    "gn:country_code":"MX",
    "gn:dem":872,
    "gn:feature_class":"P",
    "gn:feature_code":"PPL",
    "gn:name":"Parota el Reparo",
    "gn:population":0,
    "gn:timezone":"America/Mexico_City",
    "iso:country":"MX",
    "name:spa_x_preferred":[
        "Parota el Reparo"
    ],
    "wof:name":"Parota el Reparo",
    "wof:placetype":"locality"
},
  "geometry": {"coordinates":[-100.89054,19.19652],"type":"Point"}
}