{
  "type": "Feature",
  "properties": {
    "gn:admin1_code":"30",
    "gn:admin2_code":"56.0",
    "gn:asciiname":"El Tiznado",
    "gn:country_code":"MX",
    "gn:dem":117,
    "gn:feature_class":"P",
    "gn:feature_code":"PPL",
    "gn:name":"El Tiznado",
    "gn:population":78,
    "gn:timezone":"America/Mexico_City",
    "iso:country":"MX",
    "wof:name":"El Tiznado",
    "wof:placetype":"locality",
    "wof:population":78
},
  "geometry": {"coordinates":[-98.46693999999999,21.27583],"type":"Point"}
}