{
  "type": "Feature",
  "properties": {
    "gn:admin1_code":"22",
    "gn:admin2_code":"14.0",
    "gn:asciiname":"Casa Blanca",
    "gn:country_code":"MX",
    "gn:dem":2141,
    "gn:feature_class":"P",
    "gn:feature_code":"PPL",
    "gn:name":"Casa Blanca",
    "gn:population":873,
    "gn:timezone":"America/Mexico_City",
    "iso:country":"MX",
    "wof:name":"Casa Blanca",
    "wof:placetype":"locality",
    "wof:population":873
},
  "geometry": {"coordinates":[-100.505,20.75194],"type":"Point"}
}