{
  "type": "Feature",
  "properties": {
    "gn:admin1_code":"14.0",
    "gn:admin2_code":"116.0",
    "gn:asciiname":"El Bajio Hondo",
    "gn:country_code":"MX",
    "gn:dem":1936,
    "gn:feature_class":"P",
    "gn:feature_code":"PPL",
    "gn:name":"El Bajio Hondo",
    "gn:population":0,
    "gn:timezone":"America/Mexico_City",
    "iso:country":"MX",
    "name:spa_x_preferred":[
        "El Bajio Hondo"
    ],
    "wof:name":"El Bajio Hondo",
    "wof:placetype":"locality"
},
  "geometry": {"coordinates":[-102.59332999999999,21.65532],"type":"Point"}
}