{
  "type": "Feature",
  "properties": {
    "gn:admin1_code":"19",
    "gn:admin2_code":"16.0",
    "gn:asciiname":"La Rosita",
    "gn:country_code":"MX",
    "gn:dem":286,
    "gn:feature_class":"P",
    "gn:feature_code":"PPL",
    "gn:name":"La Rosita",
    "gn:population":0,
    "gn:timezone":"America/Monterrey",
    "iso:country":"MX",
    "name:und_x_variant":[
        "Rosita",
        "La Rosita"
    ],
    "wof:name":"La Rosita",
    "wof:placetype":"locality"
},
  "geometry": {"coordinates":[-99.88885999999999,25.75732],"type":"Point"}
}