{
  "type": "Feature",
  "properties": {
    "gn:admin1_code":"28",
    "gn:admin2_code":"28.0",
    "gn:asciiname":"Ignacia Castillo",
    "gn:country_code":"MX",
    "gn:dem":288,
    "gn:feature_class":"P",
    "gn:feature_code":"PPL",
    "gn:name":"Ignacia Castillo",
    "gn:population":9,
    "gn:timezone":"America/Monterrey",
    "iso:country":"MX",
    "wof:name":"Ignacia Castillo",
    "wof:placetype":"locality",
    "wof:population":9
},
  "geometry": {"coordinates":[-99.21417,22.53417],"type":"Point"}
}