{
  "type": "Feature",
  "properties": {
    "gn:admin1_code":"21",
    "gn:admin2_code":"207.0",
    "gn:asciiname":"Calcahualco",
    "gn:country_code":"MX",
    "gn:dem":2005,
    "gn:feature_class":"P",
    "gn:feature_code":"PPL",
    "gn:name":"Calcahualco",
    "gn:population":348,
    "gn:timezone":"America/Mexico_City",
    "iso:country":"MX",
    "wof:name":"Calcahualco",
    "wof:placetype":"locality",
    "wof:population":348
},
  "geometry": {"coordinates":[-97.58076,19.84262],"type":"Point"}
}