{
  "type": "Feature",
  "properties": {
    "gn:admin1_code":"21",
    "gn:admin2_code":"207.0",
    "gn:asciiname":"Calcahualco",
    "gn:country_code":"MX",
    "gn:dem":2005,
    "gn:feature_class":"P",
    "gn:feature_code":"PPL",
    "gn:name":"Calcahualco",
    "gn:population":348,
    "gn:timezone":"America/Mexico_City",
    "iso:country":"MX",
    "name:ceb_x_preferred":[
        "Calcahualco"
    ],
    "name:epo_x_preferred":[
        "Calcahualco"
    ],
    "name:eus_x_preferred":[
        "Calcahualco"
    ],
    "name:ita_x_preferred":[
        "Calcahualco"
    ],
    "name:rus_x_preferred":[
        "\u041a\u0430\u043b\u044c\u043a\u0430\u0443\u0430\u043b\u044c\u043a\u043e"
    ],
    "name:srp_x_preferred":[
        "\u041e\u043f\u0448\u0442\u0438\u043d\u0430 \u041a\u0430\u043b\u043a\u0430\u0432\u0430\u043b\u043a\u043e"
    ],
    "name:swe_x_preferred":[
        "Calcahualco"
    ],
    "name:vie_x_preferred":[
        "Calcahualco"
    ],
    "wof:name":"Calcahualco",
    "wof:placetype":"locality",
    "wof:population":348
},
  "geometry": {"coordinates":[-97.58076,19.84262],"type":"Point"}
}