{
  "type": "Feature",
  "properties": {
    "gn:admin1_code":"2",
    "gn:admin2_code":"1.0",
    "gn:asciiname":"Miramar",
    "gn:country_code":"MX",
    "gn:dem":550,
    "gn:feature_class":"P",
    "gn:feature_code":"PPL",
    "gn:name":"Miramar",
    "gn:population":0,
    "gn:timezone":"America/Tijuana",
    "iso:country":"MX",
    "wof:name":"Miramar",
    "wof:placetype":"locality"
},
  "geometry": {"coordinates":[-114.76667,30.05],"type":"Point"}
}