{
  "type": "Feature",
  "properties": {
    "gn:admin1_code":"7.0",
    "gn:admin2_code":"22.0",
    "gn:asciiname":"La Pila",
    "gn:country_code":"MX",
    "gn:dem":302,
    "gn:feature_class":"P",
    "gn:feature_code":"PPL",
    "gn:name":"La Pila",
    "gn:population":0,
    "gn:timezone":"America/Monterrey",
    "iso:country":"MX",
    "name:ceb_x_preferred":[
        "La Pila"
    ],
    "name:ita_x_preferred":[
        "La Pila"
    ],
    "name:spa_x_preferred":[
        "La Pila"
    ],
    "name:srp_x_preferred":[
        "\u041b\u0430 \u041f\u0438\u043b\u0430"
    ],
    "wof:name":"La Pila",
    "wof:placetype":"locality"
},
  "geometry": {"coordinates":[-100.69173000000001,28.50365],"type":"Point"}
}