{
  "type": "Feature",
  "properties": {
    "gn:admin1_code":"27.0",
    "gn:admin2_code":"13.0",
    "gn:asciiname":"Rancho Chico",
    "gn:country_code":"MX",
    "gn:dem":7,
    "gn:feature_class":"P",
    "gn:feature_code":"PPL",
    "gn:name":"Rancho Chico",
    "gn:population":0,
    "gn:timezone":"America/Mexico_City",
    "iso:country":"MX",
    "name:spa_x_preferred":[
        "Rancho Chico"
    ],
    "wof:name":"Rancho Chico",
    "wof:placetype":"locality"
},
  "geometry": {"coordinates":[-92.92303,18.07237000000001],"type":"Point"}
}