{
  "type": "Feature",
  "properties": {
    "gn:admin1_code":"20",
    "gn:admin2_code":"79",
    "gn:asciiname":"Colonia 16 de Septiembre",
    "gn:country_code":"MX",
    "gn:dem":43,
    "gn:feature_class":"P",
    "gn:feature_code":"PPL",
    "gn:name":"Colonia 16 de Septiembre",
    "gn:population":36,
    "gn:timezone":"America/Mexico_City",
    "iso:country":"MX",
    "wof:name":"Colonia 16 de Septiembre",
    "wof:placetype":"locality",
    "wof:population":36
},
  "geometry": {"coordinates":[-95.22499999999999,16.22806],"type":"Point"}
}