{
  "type": "Feature",
  "properties": {
    "gn:admin1_code":"30",
    "gn:admin2_code":"76.0",
    "gn:asciiname":"Xaltipa",
    "gn:country_code":"MX",
    "gn:dem":535,
    "gn:feature_class":"P",
    "gn:feature_code":"PPL",
    "gn:name":"Xaltipa",
    "gn:population":144,
    "gn:timezone":"America/Mexico_City",
    "iso:country":"MX",
    "wof:name":"Xaltipa",
    "wof:placetype":"locality",
    "wof:population":144
},
  "geometry": {"coordinates":[-98.45972,20.71639],"type":"Point"}
}