{
  "type": "Feature",
  "properties": {
    "gn:admin1_code":"5",
    "gn:admin2_code":"107.0",
    "gn:asciiname":"Brasilia",
    "gn:country_code":"MX",
    "gn:dem":610,
    "gn:feature_class":"P",
    "gn:feature_code":"PPL",
    "gn:name":"Brasilia",
    "gn:population":5,
    "gn:timezone":"America/Mexico_City",
    "iso:country":"MX",
    "wof:name":"Brasilia",
    "wof:placetype":"locality",
    "wof:population":5
},
  "geometry": {"coordinates":[-93.34694,16.19556],"type":"Point"}
}