{
  "type": "Feature",
  "properties": {
    "gn:admin1_code":"6",
    "gn:admin2_code":"30.0",
    "gn:asciiname":"La Higuerita",
    "gn:country_code":"MX",
    "gn:dem":1418,
    "gn:feature_class":"P",
    "gn:feature_code":"PPL",
    "gn:name":"La Higuerita",
    "gn:population":68,
    "gn:timezone":"America/Chihuahua",
    "iso:country":"MX",
    "wof:name":"La Higuerita",
    "wof:placetype":"locality",
    "wof:population":68
},
  "geometry": {"coordinates":[-108.27631,27.2677],"type":"Point"}
}