{
  "type": "Feature",
  "properties": {
    "gn:admin1_code":"5",
    "gn:admin2_code":"89.0",
    "gn:asciiname":"San Matias",
    "gn:country_code":"MX",
    "gn:dem":21,
    "gn:feature_class":"P",
    "gn:feature_code":"PPL",
    "gn:name":"San Mat\u00edas",
    "gn:population":0,
    "gn:timezone":"America/Mexico_City",
    "iso:country":"MX",
    "name:spa_x_preferred":[
        "San Mat\u00edas"
    ],
    "wof:name":"San Matias",
    "wof:placetype":"locality"
},
  "geometry": {"coordinates":[-92.29837000000001,14.68873],"type":"Point"}
}