{
  "type": "Feature",
  "properties": {
    "gn:admin1_code":"11",
    "gn:admin2_code":"20.0",
    "gn:asciiname":"Granja San Jose de Barron",
    "gn:country_code":"MX",
    "gn:dem":1798,
    "gn:feature_class":"P",
    "gn:feature_code":"PPL",
    "gn:name":"Granja San Jos\u00e9 de Barr\u00f3n",
    "gn:population":6,
    "gn:timezone":"America/Mexico_City",
    "iso:country":"MX",
    "name:und_x_variant":[
        "Granja San Jos\u00e9 de Barr\u00f3n"
    ],
    "wof:name":"Granja San Jose de Barron",
    "wof:placetype":"locality",
    "wof:population":6
},
  "geometry": {"coordinates":[-101.625,21.02556],"type":"Point"}
}