{
  "type": "Feature",
  "properties": {
    "gn:admin1_code":"30",
    "gn:admin2_code":"121.0",
    "gn:asciiname":"Poza del Tule",
    "gn:country_code":"MX",
    "gn:dem":54,
    "gn:feature_class":"P",
    "gn:feature_code":"PPL",
    "gn:name":"Poza del Tule",
    "gn:population":131,
    "gn:timezone":"America/Mexico_City",
    "iso:country":"MX",
    "wof:name":"Poza del Tule",
    "wof:placetype":"locality",
    "wof:population":131
},
  "geometry": {"coordinates":[-97.78778,21.82472000000001],"type":"Point"}
}