{
  "type": "Feature",
  "properties": {
    "gn:admin1_code":"18.0",
    "gn:admin2_code":"1.0",
    "gn:asciiname":"El Resbalon",
    "gn:country_code":"MX",
    "gn:dem":34,
    "gn:feature_class":"P",
    "gn:feature_code":"PPL",
    "gn:name":"El Resbal\u00f3n",
    "gn:population":747,
    "gn:timezone":"America/Mazatlan",
    "iso:country":"MX",
    "wof:name":"El Resbalon",
    "wof:placetype":"locality",
    "wof:population":747
},
  "geometry": {"coordinates":[-105.30083,22.39361],"type":"Point"}
}