{
  "type": "Feature",
  "properties": {
    "gn:admin1_code":"31",
    "gn:admin2_code":"22.0",
    "gn:asciiname":"Sahcabchen",
    "gn:country_code":"MX",
    "gn:dem":33,
    "gn:feature_class":"P",
    "gn:feature_code":"PPL",
    "gn:name":"Sahcabch\u00e9n",
    "gn:population":0,
    "gn:timezone":"America/Merida",
    "iso:country":"MX",
    "name:spa_x_preferred":[
        "Sahcabch\u00e9n"
    ],
    "wof:name":"Sahcabchen",
    "wof:placetype":"locality"
},
  "geometry": {"coordinates":[-88.50235000000001,20.23597],"type":"Point"}
}