{
  "type": "Feature",
  "properties": {
    "gn:admin1_code":"20",
    "gn:admin2_code":"184",
    "gn:asciiname":"Playa del Mono",
    "gn:country_code":"MX",
    "gn:dem":36,
    "gn:feature_class":"P",
    "gn:feature_code":"PPL",
    "gn:name":"Playa del Mono",
    "gn:population":11,
    "gn:timezone":"America/Mexico_City",
    "iso:country":"MX",
    "wof:name":"Playa del Mono",
    "wof:placetype":"locality",
    "wof:population":11
},
  "geometry": {"coordinates":[-96.16361000000001,18.05028],"type":"Point"}
}