{
  "type": "Feature",
  "properties": {
    "gn:admin1_code":"16.0",
    "gn:admin2_code":"8.0",
    "gn:asciiname":"La Cebadilla",
    "gn:country_code":"MX",
    "gn:dem":754,
    "gn:feature_class":"P",
    "gn:feature_code":"PPL",
    "gn:name":"La Cebadilla",
    "gn:population":0,
    "gn:timezone":"America/Mexico_City",
    "iso:country":"MX",
    "name:spa_x_preferred":[
        "La Cebadilla"
    ],
    "wof:name":"La Cebadilla",
    "wof:placetype":"locality"
},
  "geometry": {"coordinates":[-103.21972,18.41364],"type":"Point"}
}