{
  "type": "Feature",
  "properties": {
    "gn:admin1_code":"20",
    "gn:admin2_code":"441.0",
    "gn:asciiname":"Playa Guelaveno",
    "gn:country_code":"MX",
    "gn:dem":5,
    "gn:feature_class":"P",
    "gn:feature_code":"PPL",
    "gn:name":"Playa Guelave\u00f1o",
    "gn:population":0,
    "gn:timezone":"America/Mexico_City",
    "iso:country":"MX",
    "wof:name":"Playa Guelaveno",
    "wof:placetype":"locality"
},
  "geometry": {"coordinates":[-95.03333000000001,16.35],"type":"Point"}
}