{
  "type": "Feature",
  "properties": {
    "gn:admin1_code":"14",
    "gn:admin2_code":"93",
    "gn:asciiname":"Rio Verde [Balneario]",
    "gn:country_code":"MX",
    "gn:dem":1495,
    "gn:feature_class":"P",
    "gn:feature_code":"PPL",
    "gn:name":"R\u00edo Verde [Balneario]",
    "gn:population":12,
    "gn:timezone":"America/Mexico_City",
    "iso:country":"MX",
    "name:und_x_variant":[
        "R\u00edo Verde [Balneario]"
    ],
    "wof:name":"Rio Verde [Balneario]",
    "wof:placetype":"locality",
    "wof:population":12
},
  "geometry": {"coordinates":[-102.81861000000001,21.00556],"type":"Point"}
}