{
  "type": "Feature",
  "properties": {
    "gn:admin1_code":"5",
    "gn:admin2_code":"59.0",
    "gn:asciiname":"Tzitin Tzajala",
    "gn:country_code":"MX",
    "gn:dem":571,
    "gn:feature_class":"P",
    "gn:feature_code":"PPL",
    "gn:name":"Tzit\u00edn Tzajala",
    "gn:population":8,
    "gn:timezone":"America/Mexico_City",
    "iso:country":"MX",
    "name:und_x_variant":[
        "Tzit\u00edn Tzajala"
    ],
    "wof:name":"Tzitin Tzajala",
    "wof:placetype":"locality",
    "wof:population":8
},
  "geometry": {"coordinates":[-91.74056,16.85083],"type":"Point"}
}