{
  "type": "Feature",
  "properties": {
    "gn:admin1_code":"30.0",
    "gn:admin2_code":"155.0",
    "gn:asciiname":"Palmar",
    "gn:country_code":"MX",
    "gn:dem":112,
    "gn:feature_class":"P",
    "gn:feature_code":"PPL",
    "gn:name":"Palmar",
    "gn:population":10,
    "gn:timezone":"America/Mexico_City",
    "iso:country":"MX",
    "name:spa_x_preferred":[
        "Palmar"
    ],
    "wof:name":"Palmar",
    "wof:placetype":"locality",
    "wof:population":10
},
  "geometry": {"coordinates":[-98.16306,21.255],"type":"Point"}
}