{
  "type": "Feature",
  "properties": {
    "gn:admin1_code":"6",
    "gn:admin2_code":"42.0",
    "gn:asciiname":"Escobillas de Abajo",
    "gn:country_code":"MX",
    "gn:dem":951,
    "gn:feature_class":"P",
    "gn:feature_code":"PPL",
    "gn:name":"Escobillas de Abajo",
    "gn:population":0,
    "gn:timezone":"America/Chihuahua",
    "iso:country":"MX",
    "wof:name":"Escobillas de Abajo",
    "wof:placetype":"locality"
},
  "geometry": {"coordinates":[-103.53333000000001,28.81667],"type":"Point"}
}