{
  "type": "Feature",
  "properties": {
    "gn:admin1_code":"5",
    "gn:admin2_code":"66.0",
    "gn:asciiname":"Nueva Galilea",
    "gn:country_code":"MX",
    "gn:dem":1156,
    "gn:feature_class":"P",
    "gn:feature_code":"PPL",
    "gn:name":"Nueva Galilea",
    "gn:population":175,
    "gn:timezone":"America/Mexico_City",
    "iso:country":"MX",
    "wof:name":"Nueva Galilea",
    "wof:placetype":"locality",
    "wof:population":175
},
  "geometry": {"coordinates":[-92.41571,17.1035],"type":"Point"}
}