{
  "type": "Feature",
  "properties": {
    "gn:admin1_code":"20.0",
    "gn:admin2_code":"561.0",
    "gn:asciiname":"Rincon Anona",
    "gn:country_code":"MX",
    "gn:dem":1524,
    "gn:feature_class":"P",
    "gn:feature_code":"PPL",
    "gn:name":"Rinc\u00f3n Anona",
    "gn:population":0,
    "gn:timezone":"America/Mexico_City",
    "iso:country":"MX",
    "name:spa_x_preferred":[
        "Rinc\u00f3n Anona"
    ],
    "wof:name":"Rincon Anona",
    "wof:placetype":"locality"
},
  "geometry": {"coordinates":[-96.46562,16.71652000000001],"type":"Point"}
}