{
  "type": "Feature",
  "properties": {
    "gn:admin1_code":"11.0",
    "gn:admin2_code":"33.0",
    "gn:asciiname":"Canada del Potrero",
    "gn:country_code":"MX",
    "gn:dem":1325,
    "gn:feature_class":"P",
    "gn:feature_code":"PPL",
    "gn:name":"Ca\u00f1ada del Potrero",
    "gn:population":0,
    "gn:timezone":"America/Mexico_City",
    "iso:country":"MX",
    "name:spa_x_preferred":[
        "Ca\u00f1ada del Potrero"
    ],
    "wof:name":"Canada del Potrero",
    "wof:placetype":"locality"
},
  "geometry": {"coordinates":[-100.37259,21.67106],"type":"Point"}
}