{
  "type": "Feature",
  "properties": {
    "gn:admin1_code":"21",
    "gn:admin2_code":"180.0",
    "gn:asciiname":"Centro Acuicola",
    "gn:country_code":"MX",
    "gn:dem":2646,
    "gn:feature_class":"P",
    "gn:feature_code":"PPL",
    "gn:name":"Centro Acu\u00edcola",
    "gn:population":0,
    "gn:timezone":"America/Mexico_City",
    "iso:country":"MX",
    "name:spa_x_preferred":[
        "Centro Acu\u00edcola"
    ],
    "name:spa_x_variant":[
        "Truchas"
    ],
    "wof:name":"Centro Acuicola",
    "wof:placetype":"locality"
},
  "geometry": {"coordinates":[-98.60596,19.35515],"type":"Point"}
}