{
  "type": "Feature",
  "properties": {
    "gn:admin1_code":"32.0",
    "gn:asciiname":"Puerta del Tigre",
    "gn:country_code":"MX",
    "gn:dem":1776,
    "gn:feature_class":"P",
    "gn:feature_code":"PPL",
    "gn:name":"Puerta del Tigre",
    "gn:population":0,
    "gn:timezone":"America/Mexico_City",
    "iso:country":"MX",
    "name:spa_x_preferred":[
        "Puerta del Tigre"
    ],
    "wof:name":"Puerta del Tigre",
    "wof:placetype":"locality"
},
  "geometry": {"coordinates":[-103.67283,22.55937],"type":"Point"}
}