{
  "type": "Feature",
  "properties": {
    "gn:admin1_code":"20",
    "gn:admin2_code":"232.0",
    "gn:asciiname":"Loma San Bernabe",
    "gn:country_code":"MX",
    "gn:dem":96,
    "gn:feature_class":"P",
    "gn:feature_code":"PPL",
    "gn:name":"Loma San Bernab\u00e9",
    "gn:population":385,
    "gn:timezone":"America/Mexico_City",
    "iso:country":"MX",
    "name:und_x_variant":[
        "Loma San Bernab\u00e9"
    ],
    "wof:name":"Loma San Bernabe",
    "wof:placetype":"locality",
    "wof:population":385
},
  "geometry": {"coordinates":[-96.36667,18.08583],"type":"Point"}
}