{
  "type": "Feature",
  "properties": {
    "gn:admin1_code":"24",
    "gn:admin2_code":"14.0",
    "gn:asciiname":"Picholco",
    "gn:country_code":"MX",
    "gn:dem":151,
    "gn:feature_class":"P",
    "gn:feature_code":"PPL",
    "gn:name":"Picholco",
    "gn:population":152,
    "gn:timezone":"America/Mexico_City",
    "iso:country":"MX",
    "wof:name":"Picholco",
    "wof:placetype":"locality",
    "wof:population":152
},
  "geometry": {"coordinates":[-98.88583,21.50417],"type":"Point"}
}