{
  "type": "Feature",
  "properties": {
    "gn:admin1_code":"20",
    "gn:admin2_code":"552",
    "gn:asciiname":"Primera Seccion",
    "gn:country_code":"MX",
    "gn:dem":2177,
    "gn:feature_class":"P",
    "gn:feature_code":"PPL",
    "gn:name":"Primera Secci\u00f3n",
    "gn:population":19,
    "gn:timezone":"America/Mexico_City",
    "iso:country":"MX",
    "name:und_x_variant":[
        "Primera Secci\u00f3n"
    ],
    "wof:name":"Primera Seccion",
    "wof:placetype":"locality",
    "wof:population":19
},
  "geometry": {"coordinates":[-97.43971999999999,17.85861000000001],"type":"Point"}
}