{
  "type": "Feature",
  "properties": {
    "gn:admin1_code":"20",
    "gn:admin2_code":"511",
    "gn:asciiname":"Cerro Ceja",
    "gn:country_code":"MX",
    "gn:dem":2429,
    "gn:feature_class":"P",
    "gn:feature_code":"PPL",
    "gn:name":"Cerro Ceja",
    "gn:population":33,
    "gn:timezone":"America/Mexico_City",
    "iso:country":"MX",
    "wof:name":"Cerro Ceja",
    "wof:placetype":"locality",
    "wof:population":33
},
  "geometry": {"coordinates":[-97.04389,17.15167000000001],"type":"Point"}
}