{
  "type": "Feature",
  "properties": {
    "gn:admin1_code":"7",
    "gn:admin2_code":"31.0",
    "gn:asciiname":"La Remuda",
    "gn:country_code":"MX",
    "gn:dem":1214,
    "gn:feature_class":"P",
    "gn:feature_code":"PPL",
    "gn:name":"La Remuda",
    "gn:population":0,
    "gn:timezone":"America/Monterrey",
    "iso:country":"MX",
    "name:spa_x_preferred":[
        "La Remuda"
    ],
    "name:und_x_variant":[
        "La Zemuda",
        "Rancho de la Remuda"
    ],
    "wof:name":"La Remuda",
    "wof:placetype":"locality"
},
  "geometry": {"coordinates":[-102.11811,28.13466],"type":"Point"}
}