{
  "type": "Feature",
  "properties": {
    "gn:admin1_code":"14",
    "gn:admin2_code":"78",
    "gn:asciiname":"La Vibora",
    "gn:country_code":"MX",
    "gn:dem":2194,
    "gn:feature_class":"P",
    "gn:feature_code":"PPL",
    "gn:name":"La V\u00edbora",
    "gn:population":10,
    "gn:timezone":"America/Mexico_City",
    "iso:country":"MX",
    "name:deu_x_preferred":[
        "La Vibora"
    ],
    "name:fra_x_preferred":[
        "La Vibora"
    ],
    "name:nld_x_preferred":[
        "La Vibora"
    ],
    "name:und_x_variant":[
        "La V\u00edbora"
    ],
    "wof:name":"La Vibora",
    "wof:placetype":"locality",
    "wof:population":10
},
  "geometry": {"coordinates":[-102.31332999999999,20.91583],"type":"Point"}
}