{
  "type": "Feature",
  "properties": {
    "gn:admin1_code":"12.0",
    "gn:admin2_code":"80.0",
    "gn:asciiname":"La Estancia",
    "gn:country_code":"MX",
    "gn:dem":113,
    "gn:feature_class":"P",
    "gn:feature_code":"PPL",
    "gn:name":"La Estancia",
    "gn:population":0,
    "gn:timezone":"America/Mexico_City",
    "iso:country":"MX",
    "name:ceb_x_preferred":[
        "La Estancia"
    ],
    "name:deu_x_preferred":[
        "La Estancia"
    ],
    "name:spa_x_preferred":[
        "La Estancia"
    ],
    "name:swe_x_preferred":[
        "La Estancia"
    ],
    "wof:name":"La Estancia",
    "wof:placetype":"locality"
},
  "geometry": {"coordinates":[-98.66571999999999,16.57203],"type":"Point"}
}