{
  "type": "Feature",
  "properties": {
    "gn:admin1_code":"6",
    "gn:admin2_code":"9.0",
    "gn:asciiname":"Gamego",
    "gn:country_code":"MX",
    "gn:dem":2364,
    "gn:feature_class":"P",
    "gn:feature_code":"PPL",
    "gn:name":"Gameg\u00f3",
    "gn:population":0,
    "gn:timezone":"America/Chihuahua",
    "iso:country":"MX",
    "name:spa_x_preferred":[
        "Gameg\u00f3"
    ],
    "name:und_x_variant":[
        "Camigo"
    ],
    "wof:name":"Gamego",
    "wof:placetype":"locality"
},
  "geometry": {"coordinates":[-107.77228999999998,27.78858],"type":"Point"}
}