{
  "type": "Feature",
  "properties": {
    "gn:admin1_code":"13",
    "gn:admin2_code":"26.0",
    "gn:asciiname":"Tzapotitla",
    "gn:country_code":"MX",
    "gn:dem":373,
    "gn:feature_class":"P",
    "gn:feature_code":"PPL",
    "gn:name":"Tzapotitla",
    "gn:population":277,
    "gn:timezone":"America/Mexico_City",
    "iso:country":"MX",
    "wof:name":"Tzapotitla",
    "wof:placetype":"locality",
    "wof:population":277
},
  "geometry": {"coordinates":[-98.48193999999999,20.97972],"type":"Point"}
}