{
  "type": "Feature",
  "properties": {
    "gn:admin1_code":"6.0",
    "gn:admin2_code":"37.0",
    "gn:asciiname":"La Coyotera",
    "gn:country_code":"MX",
    "gn:dem":1116,
    "gn:feature_class":"P",
    "gn:feature_code":"PPL",
    "gn:name":"La Coyotera",
    "gn:population":0,
    "gn:timezone":"America/Ojinaga",
    "iso:country":"MX",
    "wof:name":"La Coyotera",
    "wof:placetype":"locality"
},
  "geometry": {"coordinates":[-106.34999999999999,31.66667],"type":"Point"}
}