{
  "type": "Feature",
  "properties": {
    "gn:admin1_code":"30",
    "gn:admin2_code":"3.0",
    "gn:asciiname":"Jalapilla",
    "gn:country_code":"MX",
    "gn:dem":83,
    "gn:feature_class":"P",
    "gn:feature_code":"PPL",
    "gn:name":"Jalapilla",
    "gn:population":0,
    "gn:timezone":"America/Mexico_City",
    "iso:country":"MX",
    "name:spa_x_preferred":[
        "Jalapilla"
    ],
    "wof:name":"Jalapilla",
    "wof:placetype":"locality"
},
  "geometry": {"coordinates":[-95.07785,18.01151],"type":"Point"}
}