{
  "type": "Feature",
  "properties": {
    "gn:admin1_code":"5.0",
    "gn:asciiname":"La Trinitaria",
    "gn:country_code":"MX",
    "gn:dem":602,
    "gn:feature_class":"P",
    "gn:feature_code":"PPL",
    "gn:name":"La Trinitaria",
    "gn:population":0,
    "gn:timezone":"America/Mexico_City",
    "iso:country":"MX",
    "name:spa_x_preferred":[
        "La Trinitaria"
    ],
    "wof:name":"La Trinitaria",
    "wof:placetype":"locality"
},
  "geometry": {"coordinates":[-91.68109,16.80632],"type":"Point"}
}