{
  "type": "Feature",
  "properties": {
    "gn:admin1_code":"6",
    "gn:admin2_code":"61.0",
    "gn:asciiname":"La Muralla Duramena",
    "gn:cc2":"MX",
    "gn:country_code":"MX",
    "gn:dem":1417,
    "gn:feature_class":"P",
    "gn:feature_code":"PPL",
    "gn:name":"La Muralla Durame\u00f1a",
    "gn:population":0,
    "gn:timezone":"America/Chihuahua",
    "iso:country":"MX",
    "name:und_x_variant":[
        "Muralla",
        "La Muralla",
        "La Muralla Durame\u00f1a"
    ],
    "wof:name":"La Muralla Duramena",
    "wof:placetype":"locality"
},
  "geometry": {"coordinates":[-106.16667,28.06667],"type":"Point"}
}