{
  "type": "Feature",
  "properties": {
    "gn:admin1_code":"7.0",
    "gn:admin2_code":"12.0",
    "gn:asciiname":"Salitrillo",
    "gn:country_code":"MX",
    "gn:dem":277,
    "gn:feature_class":"P",
    "gn:feature_code":"PPL",
    "gn:name":"Salitrillo",
    "gn:population":0,
    "gn:timezone":"America/Monterrey",
    "iso:country":"MX",
    "name:spa_x_preferred":[
        "Salitrillo"
    ],
    "wof:name":"Salitrillo",
    "wof:placetype":"locality"
},
  "geometry": {"coordinates":[-100.49417,28.26843],"type":"Point"}
}