{
  "type": "Feature",
  "properties": {
    "gn:admin1_code":"28.0",
    "gn:admin2_code":"35.0",
    "gn:asciiname":"El Kilometro",
    "gn:country_code":"MX",
    "gn:dem":28,
    "gn:feature_class":"P",
    "gn:feature_code":"PPL",
    "gn:name":"El Kil\u00f3metro",
    "gn:population":0,
    "gn:timezone":"America/Monterrey",
    "iso:country":"MX",
    "name:spa_x_preferred":[
        "El Kil\u00f3metro"
    ],
    "wof:name":"El Kilometro",
    "wof:placetype":"locality"
},
  "geometry": {"coordinates":[-98.07708,25.07632000000001],"type":"Point"}
}