{
  "type": "Feature",
  "properties": {
    "gn:admin1_code":"30",
    "gn:admin2_code":"84.0",
    "gn:asciiname":"Las Cuatas",
    "gn:country_code":"MX",
    "gn:dem":8,
    "gn:feature_class":"P",
    "gn:feature_code":"PPL",
    "gn:name":"Las Cuatas",
    "gn:population":499,
    "gn:timezone":"America/Mexico_City",
    "iso:country":"MX",
    "wof:name":"Las Cuatas",
    "wof:placetype":"locality",
    "wof:population":499
},
  "geometry": {"coordinates":[-95.90389,18.40528],"type":"Point"}
}