{
  "type": "Feature",
  "properties": {
    "gn:admin1_code":"18.0",
    "gn:admin2_code":"19.0",
    "gn:asciiname":"Los Chiles",
    "gn:country_code":"MX",
    "gn:dem":570,
    "gn:feature_class":"P",
    "gn:feature_code":"PPL",
    "gn:name":"Los Chiles",
    "gn:population":0,
    "gn:timezone":"America/Mazatlan",
    "iso:country":"MX",
    "name:ceb_x_preferred":[
        "Los Chiles"
    ],
    "name:ita_x_preferred":[
        "Los Chiles"
    ],
    "name:nld_x_preferred":[
        "Los Chiles"
    ],
    "name:nor_x_preferred":[
        "Los Chiles"
    ],
    "name:spa_x_preferred":[
        "Los Chiles"
    ],
    "name:swe_x_preferred":[
        "Los Chiles"
    ],
    "name:zho_x_preferred":[
        "\u6d1b\u65af\u5947\u840a\u65af\u5340"
    ],
    "wof:name":"Los Chiles",
    "wof:placetype":"locality"
},
  "geometry": {"coordinates":[-104.34204,21.94662000000001],"type":"Point"}
}