{
  "type": "Feature",
  "properties": {
    "gn:admin1_code":"30",
    "gn:admin2_code":"45.0",
    "gn:asciiname":"Tecoanapa",
    "gn:country_code":"MX",
    "gn:dem":17,
    "gn:feature_class":"P",
    "gn:feature_code":"PPL",
    "gn:name":"Tecoanapa",
    "gn:population":0,
    "gn:timezone":"America/Mexico_City",
    "iso:country":"MX",
    "name:epo_x_preferred":[
        "Tecoanapa"
    ],
    "name:por_x_preferred":[
        "Tecoanapa"
    ],
    "name:spa_x_preferred":[
        "Tecoanapa"
    ],
    "name:und_x_variant":[
        "Tecuimapa",
        "Tecuanapa"
    ],
    "wof:name":"Tecoanapa",
    "wof:placetype":"locality"
},
  "geometry": {"coordinates":[-95.99477,18.2379],"type":"Point"}
}