{
  "type": "Feature",
  "properties": {
    "gn:admin1_code":"11",
    "gn:admin2_code":"2.0",
    "gn:asciiname":"San Francisco Rancho Viejo",
    "gn:country_code":"MX",
    "gn:dem":1884,
    "gn:feature_class":"P",
    "gn:feature_code":"PPL",
    "gn:name":"San Francisco Rancho Viejo",
    "gn:population":490,
    "gn:timezone":"America/Mexico_City",
    "iso:country":"MX",
    "name:und_x_variant":[
        "San Francisco",
        "San Francisco Rancho Viejo"
    ],
    "wof:name":"San Francisco Rancho Viejo",
    "wof:placetype":"locality",
    "wof:population":490
},
  "geometry": {"coordinates":[-100.78999,20.02623],"type":"Point"}
}