{
  "type": "Feature",
  "properties": {
    "gn:admin1_code":"24",
    "gn:admin2_code":"3.0",
    "gn:asciiname":"La Canada (Los Corrales)",
    "gn:country_code":"MX",
    "gn:dem":171,
    "gn:feature_class":"P",
    "gn:feature_code":"PPL",
    "gn:name":"La Ca\u00f1ada (Los Corrales)",
    "gn:population":152,
    "gn:timezone":"America/Mexico_City",
    "iso:country":"MX",
    "wof:name":"La Canada (Los Corrales)",
    "wof:placetype":"locality",
    "wof:population":152
},
  "geometry": {"coordinates":[-99.15197000000001,21.86901],"type":"Point"}
}