{
  "type": "Feature",
  "properties": {
    "gn:admin1_code":"30",
    "gn:admin2_code":"163.0",
    "gn:asciiname":"Barrio del Cafe",
    "gn:country_code":"MX",
    "gn:dem":899,
    "gn:feature_class":"P",
    "gn:feature_code":"PPL",
    "gn:name":"Barrio del Caf\u00e9",
    "gn:population":104,
    "gn:timezone":"America/Mexico_City",
    "iso:country":"MX",
    "name:und_x_variant":[
        "Barrio del Caf\u00e9"
    ],
    "wof:name":"Barrio del Cafe",
    "wof:placetype":"locality",
    "wof:population":104
},
  "geometry": {"coordinates":[-96.94278,19.84306],"type":"Point"}
}