{
  "type": "Feature",
  "properties": {
    "gn:admin1_code":"17",
    "gn:asciiname":"Maxtleca de Galeana",
    "gn:country_code":"MX",
    "gn:dem":2480,
    "gn:feature_class":"P",
    "gn:feature_code":"PPL",
    "gn:name":"Maxtleca de Galeana",
    "gn:population":0,
    "gn:timezone":"America/Mexico_City",
    "iso:country":"MX",
    "name:und_x_variant":[
        "Maxteca de Galeana"
    ],
    "wof:name":"Maxtleca de Galeana",
    "wof:placetype":"locality"
},
  "geometry": {"coordinates":[-99.55710000000001,19.02857],"type":"Point"}
}