{
  "type": "Feature",
  "properties": {
    "gn:admin1_code":"28",
    "gn:admin2_code":"27.0",
    "gn:asciiname":"San Ruben",
    "gn:country_code":"MX",
    "gn:dem":142,
    "gn:feature_class":"P",
    "gn:feature_code":"PPL",
    "gn:name":"San Rub\u00e9n",
    "gn:population":0,
    "gn:timezone":"America/Matamoros",
    "iso:country":"MX",
    "name:spa_x_preferred":[
        "San Rub\u00e9n"
    ],
    "wof:name":"San Ruben",
    "wof:placetype":"locality"
},
  "geometry": {"coordinates":[-99.57334,27.2797],"type":"Point"}
}