{
  "type": "Feature",
  "properties": {
    "gn:admin1_code":"1",
    "gn:admin2_code":"8",
    "gn:asciiname":"Loma Alta",
    "gn:country_code":"MX",
    "gn:dem":2016,
    "gn:feature_class":"P",
    "gn:feature_code":"PPL",
    "gn:name":"Loma Alta",
    "gn:population":13,
    "gn:timezone":"America/Mexico_City",
    "iso:country":"MX",
    "wof:name":"Loma Alta",
    "wof:placetype":"locality",
    "wof:population":13
},
  "geometry": {"coordinates":[-102.42749999999999,22.17861],"type":"Point"}
}