{
  "type": "Feature",
  "properties": {
    "gn:admin1_code":"10",
    "gn:asciiname":"El Relampago",
    "gn:country_code":"MX",
    "gn:dem":1801,
    "gn:feature_class":"P",
    "gn:feature_code":"PPL",
    "gn:name":"El Rel\u00e1mpago",
    "gn:population":0,
    "gn:timezone":"America/Chihuahua",
    "iso:country":"MX",
    "name:spa_x_preferred":[
        "El Rel\u00e1mpago"
    ],
    "wof:name":"El Relampago",
    "wof:placetype":"locality"
},
  "geometry": {"coordinates":[-106.23421999999999,26.55963],"type":"Point"}
}