{
  "type": "Feature",
  "properties": {
    "gn:admin1_code":"11.0",
    "gn:admin2_code":"20.0",
    "gn:asciiname":"Nuevo Lindero",
    "gn:country_code":"MX",
    "gn:dem":1774,
    "gn:feature_class":"P",
    "gn:feature_code":"PPL",
    "gn:name":"Nuevo Lindero",
    "gn:population":896,
    "gn:timezone":"America/Mexico_City",
    "iso:country":"MX",
    "name:spa_x_preferred":[
        "Nuevo Lindero"
    ],
    "name:und_x_variant":[
        "Rancho Viejo",
        "Lindero Nuevo",
        "El Lindero"
    ],
    "wof:name":"Nuevo Lindero",
    "wof:placetype":"locality",
    "wof:population":896
},
  "geometry": {"coordinates":[-101.63767,20.9587],"type":"Point"}
}