{
  "type": "Feature",
  "properties": {
    "gn:admin1_code":"5",
    "gn:admin2_code":"100",
    "gn:asciiname":"La Revancha",
    "gn:country_code":"MX",
    "gn:dem":859,
    "gn:feature_class":"P",
    "gn:feature_code":"PPL",
    "gn:name":"La Revancha",
    "gn:population":50,
    "gn:timezone":"America/Mexico_City",
    "iso:country":"MX",
    "wof:name":"La Revancha",
    "wof:placetype":"locality",
    "wof:population":50
},
  "geometry": {"coordinates":[-92.26667,17.3125],"type":"Point"}
}