{
  "type": "Feature",
  "properties": {
    "gn:admin1_code":"16",
    "gn:admin2_code":"97.0",
    "gn:asciiname":"El Colorin",
    "gn:country_code":"MX",
    "gn:dem":710,
    "gn:feature_class":"P",
    "gn:feature_code":"PPL",
    "gn:name":"El Color\u00edn",
    "gn:population":69,
    "gn:timezone":"America/Mexico_City",
    "iso:country":"MX",
    "name:und_x_variant":[
        "El Color\u00edn"
    ],
    "wof:name":"El Colorin",
    "wof:placetype":"locality",
    "wof:population":69
},
  "geometry": {"coordinates":[-101.45694,18.96972],"type":"Point"}
}