{
  "type": "Feature",
  "properties": {
    "gn:admin1_code":"11.0",
    "gn:admin2_code":"30.0",
    "gn:asciiname":"Buenavista del Cubo",
    "gn:country_code":"MX",
    "gn:dem":2132,
    "gn:feature_class":"P",
    "gn:feature_code":"PPL",
    "gn:name":"Buenavista del Cubo",
    "gn:population":0,
    "gn:timezone":"America/Mexico_City",
    "iso:country":"MX",
    "name:spa_x_preferred":[
        "Buenavista del Cubo"
    ],
    "name:und_x_variant":[
        "Buenavista"
    ],
    "wof:name":"Buenavista del Cubo",
    "wof:placetype":"locality"
},
  "geometry": {"coordinates":[-101.05920999999999,21.38681],"type":"Point"}
}