{
  "type": "Feature",
  "properties": {
    "gn:admin1_code":"19",
    "gn:admin2_code":"17.0",
    "gn:asciiname":"Artemisa",
    "gn:country_code":"MX",
    "gn:dem":1881,
    "gn:feature_class":"P",
    "gn:feature_code":"PPL",
    "gn:name":"Artemisa",
    "gn:population":0,
    "gn:timezone":"America/Monterrey",
    "iso:country":"MX",
    "name:spa_x_preferred":[
        "Artemisa"
    ],
    "wof:name":"Artemisa",
    "wof:placetype":"locality"
},
  "geometry": {"coordinates":[-100.68404,24.99542000000001],"type":"Point"}
}