{
  "type": "Feature",
  "properties": {
    "gn:admin1_code":"19",
    "gn:admin2_code":"17.0",
    "gn:asciiname":"Artemisa",
    "gn:country_code":"MX",
    "gn:dem":1881,
    "gn:feature_class":"P",
    "gn:feature_code":"PPL",
    "gn:name":"Artemisa",
    "gn:population":0,
    "gn:timezone":"America/Monterrey",
    "iso:country":"MX",
    "name:ara_x_preferred":[
        "\u0622\u0631\u062a\u0645\u064a\u0633\u0627"
    ],
    "name:ceb_x_preferred":[
        "Artemisa"
    ],
    "name:deu_x_preferred":[
        "Artemisa"
    ],
    "name:fra_x_preferred":[
        "Artemisa"
    ],
    "name:hat_x_preferred":[
        "Artemisa"
    ],
    "name:ind_x_preferred":[
        "Artemisa"
    ],
    "name:ita_x_preferred":[
        "Artemisa"
    ],
    "name:kat_x_preferred":[
        "\u10d0\u10e0\u10e2\u10d4\u10db\u10d8\u10e1\u10d0"
    ],
    "name:kor_x_preferred":[
        "\uc544\ub974\ud14c\ubbf8\uc0ac"
    ],
    "name:lit_x_preferred":[
        "Artemisa"
    ],
    "name:nor_x_preferred":[
        "Artemisa"
    ],
    "name:pol_x_preferred":[
        "Artemisa"
    ],
    "name:por_x_preferred":[
        "Artemisa"
    ],
    "name:ron_x_preferred":[
        "Artemisa"
    ],
    "name:rus_x_preferred":[
        "\u0410\u0440\u0442\u0435\u043c\u0438\u0441\u0430"
    ],
    "name:sco_x_preferred":[
        "Artemisa"
    ],
    "name:spa_x_preferred":[
        "Artemisa"
    ],
    "name:srp_x_preferred":[
        "\u0410\u0440\u0442\u0435\u043c\u0438\u0441\u0430"
    ],
    "name:tur_x_preferred":[
        "Artemisa"
    ],
    "name:ukr_x_preferred":[
        "\u0410\u0440\u0442\u0435\u043c\u0456\u0441\u0430"
    ],
    "name:urd_x_preferred":[
        "\u0627\u0631\u0679\u06cc\u0645\u06cc\u0633\u0627"
    ],
    "name:vie_x_preferred":[
        "Artemisa"
    ],
    "name:war_x_preferred":[
        "Artemisa"
    ],
    "name:zho_x_preferred":[
        "\u963f\u723e\u7279\u7c73\u85a9"
    ],
    "wof:name":"Artemisa",
    "wof:placetype":"locality"
},
  "geometry": {"coordinates":[-100.68404,24.99542000000001],"type":"Point"}
}