{
  "type": "Feature",
  "properties": {
    "gn:admin1_code":"6",
    "gn:admin2_code":"9.0",
    "gn:asciiname":"Bacuseachi",
    "gn:country_code":"MX",
    "gn:dem":2021,
    "gn:feature_class":"P",
    "gn:feature_code":"PPL",
    "gn:name":"Bacuseachi",
    "gn:population":0,
    "gn:timezone":"America/Chihuahua",
    "iso:country":"MX",
    "name:spa_x_preferred":[
        "Bacuseachi"
    ],
    "wof:name":"Bacuseachi",
    "wof:placetype":"locality"
},
  "geometry": {"coordinates":[-107.83636,27.62982],"type":"Point"}
}