{
  "type": "Feature",
  "properties": {
    "gn:admin1_code":"12",
    "gn:admin2_code":"45.0",
    "gn:asciiname":"Chautipa",
    "gn:country_code":"MX",
    "gn:dem":1216,
    "gn:feature_class":"P",
    "gn:feature_code":"PPL",
    "gn:name":"Chautipa",
    "gn:population":138,
    "gn:timezone":"America/Mexico_City",
    "iso:country":"MX",
    "wof:name":"Chautipa",
    "wof:placetype":"locality",
    "wof:population":138
},
  "geometry": {"coordinates":[-98.87394,17.86163999999999],"type":"Point"}
}