{
  "type": "Feature",
  "properties": {
    "gn:admin1_code":"10.0",
    "gn:admin2_code":"4.0",
    "gn:asciiname":"Agua Vieja",
    "gn:country_code":"MX",
    "gn:dem":1444,
    "gn:feature_class":"P",
    "gn:feature_code":"PPL",
    "gn:name":"Agua Vieja",
    "gn:population":15,
    "gn:timezone":"America/Monterrey",
    "iso:country":"MX",
    "wof:name":"Agua Vieja",
    "wof:placetype":"locality",
    "wof:population":15
},
  "geometry": {"coordinates":[-103.84681999999999,25.02334],"type":"Point"}
}