{
  "type": "Feature",
  "properties": {
    "gn:admin1_code":"10",
    "gn:admin2_code":"10.0",
    "gn:asciiname":"Noria del Coyote",
    "gn:country_code":"MX",
    "gn:dem":1886,
    "gn:feature_class":"P",
    "gn:feature_code":"PPL",
    "gn:name":"Noria del Coyote",
    "gn:population":0,
    "gn:timezone":"America/Monterrey",
    "iso:country":"MX",
    "name:spa_x_preferred":[
        "Noria del Coyote"
    ],
    "wof:name":"Noria del Coyote",
    "wof:placetype":"locality"
},
  "geometry": {"coordinates":[-105.10137,26.25944],"type":"Point"}
}