{
  "type": "Feature",
  "properties": {
    "gn:admin1_code":"25.0",
    "gn:admin2_code":"13.0",
    "gn:asciiname":"La Horqueta",
    "gn:country_code":"MX",
    "gn:dem":28,
    "gn:feature_class":"P",
    "gn:feature_code":"PPL",
    "gn:name":"La Horqueta",
    "gn:population":0,
    "gn:timezone":"America/Mazatlan",
    "iso:country":"MX",
    "name:cat_x_preferred":[
        "Horqueta"
    ],
    "name:fra_x_preferred":[
        "La Horqueta"
    ],
    "name:spa_x_preferred":[
        "La Horqueta"
    ],
    "name:urd_x_preferred":[
        "\u0644\u0627 \u06c1\u0648\u0631\u06a9\u0648\u06cc\u062a\u0627"
    ],
    "wof:name":"La Horqueta",
    "wof:placetype":"locality"
},
  "geometry": {"coordinates":[-107.93013999999999,25.09265],"type":"Point"}
}