{
  "type": "Feature",
  "properties": {
    "gn:admin1_code":"26",
    "gn:admin2_code":"36.0",
    "gn:asciiname":"Las Chivas",
    "gn:cc2":"MX",
    "gn:country_code":"MX",
    "gn:dem":1197,
    "gn:feature_class":"P",
    "gn:feature_code":"PPL",
    "gn:name":"Las Chivas",
    "gn:population":0,
    "gn:timezone":"America/Hermosillo",
    "iso:country":"MX",
    "name:und_x_variant":[
        "Chivas",
        "Las Chivas"
    ],
    "wof:name":"Las Chivas",
    "wof:placetype":"locality"
},
  "geometry": {"coordinates":[-110.78333000000001,30.58333],"type":"Point"}
}