{
  "type": "Feature",
  "properties": {
    "gn:admin1_code":"16",
    "gn:admin2_code":"92.0",
    "gn:asciiname":"El Anono",
    "gn:country_code":"MX",
    "gn:dem":484,
    "gn:feature_class":"P",
    "gn:feature_code":"PPL",
    "gn:name":"El Anono",
    "gn:population":0,
    "gn:timezone":"America/Mexico_City",
    "iso:country":"MX",
    "name:spa_x_preferred":[
        "El Anono"
    ],
    "wof:name":"El Anono",
    "wof:placetype":"locality"
},
  "geometry": {"coordinates":[-100.80043000000001,18.87851],"type":"Point"}
}