{
  "type": "Feature",
  "properties": {
    "gn:admin1_code":"7",
    "gn:admin2_code":"18.0",
    "gn:asciiname":"La Mota",
    "gn:country_code":"MX",
    "gn:dem":639,
    "gn:feature_class":"P",
    "gn:feature_code":"PPL",
    "gn:name":"La Mota",
    "gn:population":0,
    "gn:timezone":"America/Monterrey",
    "iso:country":"MX",
    "name:spa_x_preferred":[
        "La Mota"
    ],
    "name:und_x_variant":[
        "La Mata",
        "Rancho La Mota"
    ],
    "wof:name":"La Mota",
    "wof:placetype":"locality"
},
  "geometry": {"coordinates":[-101.10708,26.83122],"type":"Point"}
}