{
  "type": "Feature",
  "properties": {
    "gn:admin1_code":"32",
    "gn:admin2_code":"19.0",
    "gn:asciiname":"Colonia Arechiga",
    "gn:country_code":"MX",
    "gn:dem":1797,
    "gn:feature_class":"P",
    "gn:feature_code":"PPL",
    "gn:name":"Colonia Ar\u00e9chiga",
    "gn:population":0,
    "gn:timezone":"America/Mexico_City",
    "iso:country":"MX",
    "name:spa_x_preferred":[
        "Colonia Ar\u00e9chiga"
    ],
    "name:und_x_variant":[
        "Ar\u00e9chiga"
    ],
    "wof:name":"Colonia Arechiga",
    "wof:placetype":"locality"
},
  "geometry": {"coordinates":[-103.14484,21.6293],"type":"Point"}
}