{
  "type": "Feature",
  "properties": {
    "gn:admin1_code":"31",
    "gn:admin2_code":"53.0",
    "gn:asciiname":"San Jose Tipceh",
    "gn:country_code":"MX",
    "gn:dem":25,
    "gn:feature_class":"P",
    "gn:feature_code":"PPL",
    "gn:name":"San Jos\u00e9 Tipceh",
    "gn:population":513,
    "gn:timezone":"America/Merida",
    "iso:country":"MX",
    "name:und_x_variant":[
        "San Jos\u00e9 Tipceh"
    ],
    "wof:name":"San Jose Tipceh",
    "wof:placetype":"locality",
    "wof:population":513
},
  "geometry": {"coordinates":[-89.67028000000001,20.46167],"type":"Point"}
}