{
  "type": "Feature",
  "properties": {
    "gn:admin1_code":"32",
    "gn:admin2_code":"18.0",
    "gn:asciiname":"La Guayabera",
    "gn:country_code":"MX",
    "gn:dem":1442,
    "gn:feature_class":"P",
    "gn:feature_code":"PPL",
    "gn:name":"La Guayabera",
    "gn:population":5,
    "gn:timezone":"America/Mexico_City",
    "iso:country":"MX",
    "wof:name":"La Guayabera",
    "wof:placetype":"locality",
    "wof:population":5
},
  "geometry": {"coordinates":[-102.93333,21.76806],"type":"Point"}
}