{
  "type": "Feature",
  "properties": {
    "gn:admin1_code":"20",
    "gn:admin2_code":"559.0",
    "gn:asciiname":"Loma Colorada",
    "gn:country_code":"MX",
    "gn:dem":507,
    "gn:feature_class":"P",
    "gn:feature_code":"PPL",
    "gn:name":"Loma Colorada",
    "gn:population":83,
    "gn:timezone":"America/Mexico_City",
    "iso:country":"MX",
    "wof:name":"Loma Colorada",
    "wof:placetype":"locality",
    "wof:population":83
},
  "geometry": {"coordinates":[-96.38222,17.74361],"type":"Point"}
}