{
  "type": "Feature",
  "properties": {
    "gn:admin1_code":"12.0",
    "gn:admin2_code":"32.0",
    "gn:asciiname":"El Ciruelo",
    "gn:country_code":"MX",
    "gn:dem":671,
    "gn:feature_class":"P",
    "gn:feature_code":"PPL",
    "gn:name":"El Ciruelo",
    "gn:population":0,
    "gn:timezone":"America/Mexico_City",
    "iso:country":"MX",
    "name:spa_x_preferred":[
        "El Ciruelo"
    ],
    "wof:name":"El Ciruelo",
    "wof:placetype":"locality"
},
  "geometry": {"coordinates":[-100.05345,17.98285],"type":"Point"}
}