{
  "type": "Feature",
  "properties": {
    "gn:admin1_code":"4",
    "gn:admin2_code":"7.0",
    "gn:asciiname":"Blanca Mariposa",
    "gn:country_code":"MX",
    "gn:dem":2,
    "gn:feature_class":"P",
    "gn:feature_code":"PPL",
    "gn:name":"Blanca Mariposa",
    "gn:population":5,
    "gn:timezone":"America/Merida",
    "iso:country":"MX",
    "wof:name":"Blanca Mariposa",
    "wof:placetype":"locality",
    "wof:population":5
},
  "geometry": {"coordinates":[-91.86750000000001,18.0475],"type":"Point"}
}