{
  "type": "Feature",
  "properties": {
    "gn:admin1_code":"19",
    "gn:admin2_code":"38.0",
    "gn:asciiname":"Tierras Coloradas",
    "gn:country_code":"MX",
    "gn:dem":349,
    "gn:feature_class":"P",
    "gn:feature_code":"PPL",
    "gn:name":"Tierras Coloradas",
    "gn:population":0,
    "gn:timezone":"America/Monterrey",
    "iso:country":"MX",
    "name:spa_x_preferred":[
        "Tierras Coloradas"
    ],
    "wof:name":"Tierras Coloradas",
    "wof:placetype":"locality"
},
  "geometry": {"coordinates":[-99.88782,25.27346],"type":"Point"}
}