{
  "type": "Feature",
  "properties": {
    "gn:admin1_code":"2",
    "gn:admin2_code":"1.0",
    "gn:asciiname":"Rancho Bahia",
    "gn:country_code":"MX",
    "gn:dem":19,
    "gn:feature_class":"P",
    "gn:feature_code":"PPL",
    "gn:name":"Rancho Bah\u00eda",
    "gn:population":4,
    "gn:timezone":"America/Tijuana",
    "iso:country":"MX",
    "name:und_x_variant":[
        "Rancho Bah\u00eda"
    ],
    "wof:name":"Rancho Bahia",
    "wof:placetype":"locality",
    "wof:population":4
},
  "geometry": {"coordinates":[-116.56806,31.76167],"type":"Point"}
}