{
  "type": "Feature",
  "properties": {
    "gn:admin1_code":"10",
    "gn:admin2_code":"23.0",
    "gn:asciiname":"Bajio Seco",
    "gn:country_code":"MX",
    "gn:dem":2571,
    "gn:feature_class":"P",
    "gn:feature_code":"PPL",
    "gn:name":"Baj\u00edo Seco",
    "gn:population":0,
    "gn:timezone":"America/Monterrey",
    "iso:country":"MX",
    "name:spa_x_preferred":[
        "Baj\u00edo Seco"
    ],
    "wof:name":"Bajio Seco",
    "wof:placetype":"locality"
},
  "geometry": {"coordinates":[-105.4787,23.85432],"type":"Point"}
}