{
  "type": "Feature",
  "properties": {
    "gn:admin1_code":"16",
    "gn:admin2_code":"25",
    "gn:asciiname":"San Daniel",
    "gn:country_code":"MX",
    "gn:dem":1867,
    "gn:feature_class":"P",
    "gn:feature_code":"PPL",
    "gn:name":"San Daniel",
    "gn:population":37,
    "gn:timezone":"America/Mexico_City",
    "iso:country":"MX",
    "wof:name":"San Daniel",
    "wof:placetype":"locality",
    "wof:population":37
},
  "geometry": {"coordinates":[-102.06028000000001,19.85333],"type":"Point"}
}