{
  "type": "Feature",
  "properties": {
    "gn:admin1_code":"22",
    "gn:admin2_code":"9.0",
    "gn:asciiname":"Bosques de la Sierra",
    "gn:country_code":"MX",
    "gn:dem":793,
    "gn:feature_class":"P",
    "gn:feature_code":"PPL",
    "gn:name":"Bosques de la Sierra",
    "gn:population":93,
    "gn:timezone":"America/Mexico_City",
    "iso:country":"MX",
    "wof:name":"Bosques de la Sierra",
    "wof:placetype":"locality",
    "wof:population":93
},
  "geometry": {"coordinates":[-99.48056,21.22583],"type":"Point"}
}