{
  "type": "Feature",
  "properties": {
    "gn:admin1_code":"22",
    "gn:admin2_code":"8",
    "gn:asciiname":"El Mogote",
    "gn:country_code":"MX",
    "gn:dem":1956,
    "gn:feature_class":"P",
    "gn:feature_code":"PPL",
    "gn:name":"El Mogote",
    "gn:population":28,
    "gn:timezone":"America/Mexico_City",
    "iso:country":"MX",
    "wof:name":"El Mogote",
    "wof:placetype":"locality",
    "wof:population":28
},
  "geometry": {"coordinates":[-100.36778,20.49806],"type":"Point"}
}