{
  "type": "Feature",
  "properties": {
    "gn:admin1_code":"16.0",
    "gn:admin2_code":"29.0",
    "gn:asciiname":"El Olvido",
    "gn:country_code":"MX",
    "gn:dem":665,
    "gn:feature_class":"P",
    "gn:feature_code":"PPL",
    "gn:name":"El Olvido",
    "gn:population":0,
    "gn:timezone":"America/Mexico_City",
    "iso:country":"MX",
    "name:spa_x_preferred":[
        "El Olvido"
    ],
    "wof:name":"El Olvido",
    "wof:placetype":"locality"
},
  "geometry": {"coordinates":[-101.58398,18.83746],"type":"Point"}
}