{
  "type": "Feature",
  "properties": {
    "iso:country":"MX",
    "name:spa_x_preferred":[
        "Mitras Norte"
    ],
    "name:unk_x_variant":[
        "Mitras Norte"
    ],
    "qs:gn_adm0_cc":"MX",
    "qs:gn_local":3995465,
    "qs:gn_nam_loc":"Monterrey, Monterrey, Nuevo Leon, MX",
    "qs:gn_namadm1":"19",
    "qs:local_max":2766,
    "qs:local_sum":15661,
    "qs:localhoods":40,
    "qs:name":"Mitras Norte",
    "qs:name_adm0":"M\u00e9xico",
    "qs:name_adm1":"Nuevo Leon",
    "qs:name_adm2":"Monterrey",
    "qs:name_local":"Monterrey",
    "qs:photo_max":1,
    "qs:photo_sum":1,
    "qs:placetype":"Suburb",
    "qs:quad_count":1,
    "qs:woe_adm0":23424900,
    "qs:woe_adm1":2346282,
    "qs:woe_adm2":12600645,
    "qs:woe_lau":0,
    "qs:woe_local":134047,
    "qs:woe_ver":"7.10.0",
    "wof:lang":[
        "spa"
    ],
    "wof:name":"Mitras Norte",
    "wof:placetype":"neighbourhood"
},
  "geometry": {"coordinates":[-100.340881,25.703413],"type":"Point"}
}