{
  "type": "Feature",
  "properties": {
    "gn:admin1_code":"6",
    "gn:admin2_code":"20.0",
    "gn:asciiname":"El Cusal",
    "gn:country_code":"MX",
    "gn:dem":1545,
    "gn:feature_class":"P",
    "gn:feature_code":"PPL",
    "gn:name":"El Cusal",
    "gn:population":4,
    "gn:timezone":"America/Chihuahua",
    "iso:country":"MX",
    "wof:name":"El Cusal",
    "wof:placetype":"locality",
    "wof:population":4
},
  "geometry": {"coordinates":[-108.32716000000001,27.6538],"type":"Point"}
}