{
  "type": "Feature",
  "properties": {
    "gn:admin1_code":"25.0",
    "gn:admin2_code":"6.0",
    "gn:asciiname":"El Limon de los Ramos",
    "gn:country_code":"MX",
    "gn:dem":64,
    "gn:feature_class":"P",
    "gn:feature_code":"PPL",
    "gn:name":"El Lim\u00f3n de los Ramos",
    "gn:population":0,
    "gn:timezone":"America/Mazatlan",
    "iso:country":"MX",
    "name:spa_x_preferred":[
        "El Lim\u00f3n de los Ramos"
    ],
    "name:und_x_variant":[
        "El Lim\u00f3n"
    ],
    "wof:name":"El Limon de los Ramos",
    "wof:placetype":"locality"
},
  "geometry": {"coordinates":[-107.52064,24.91315],"type":"Point"}
}