{
  "type": "Feature",
  "properties": {
    "gn:admin1_code":"25",
    "gn:admin2_code":"13",
    "gn:asciiname":"La Bebelama",
    "gn:country_code":"MX",
    "gn:dem":436,
    "gn:feature_class":"P",
    "gn:feature_code":"PPL",
    "gn:name":"La Bebelama",
    "gn:population":43,
    "gn:timezone":"America/Mazatlan",
    "iso:country":"MX",
    "wof:name":"La Bebelama",
    "wof:placetype":"locality",
    "wof:population":43
},
  "geometry": {"coordinates":[-107.68317999999999,25.70718],"type":"Point"}
}