{
  "type": "Feature",
  "properties": {
    "gn:admin1_code":"12.0",
    "gn:admin2_code":"3.0",
    "gn:asciiname":"El Papayo",
    "gn:cc2":"MX",
    "gn:country_code":"MX",
    "gn:dem":1366,
    "gn:feature_class":"P",
    "gn:feature_code":"PPL",
    "gn:name":"El Papayo",
    "gn:population":0,
    "gn:timezone":"America/Mexico_City",
    "iso:country":"MX",
    "name:und_x_variant":[
        "Papayo",
        "El Papayo"
    ],
    "wof:name":"El Papayo",
    "wof:placetype":"locality"
},
  "geometry": {"coordinates":[-100.53333000000001,17.91667],"type":"Point"}
}