{
  "type": "Feature",
  "properties": {
    "gn:admin1_code":"30",
    "gn:admin2_code":"121.0",
    "gn:asciiname":"Ejido Cebadilla (El Chichonal)",
    "gn:country_code":"MX",
    "gn:dem":38,
    "gn:feature_class":"P",
    "gn:feature_code":"PPL",
    "gn:name":"Ejido Cebadilla (El Chichonal)",
    "gn:population":38,
    "gn:timezone":"America/Mexico_City",
    "iso:country":"MX",
    "name:und_x_variant":[
        "La Cebadilla",
        "Cebadilla",
        "Chichonal"
    ],
    "wof:name":"Ejido Cebadilla (El Chichonal)",
    "wof:placetype":"locality",
    "wof:population":38
},
  "geometry": {"coordinates":[-98.00444,21.88347000000001],"type":"Point"}
}