{
  "type": "Feature",
  "properties": {
    "gn:admin1_code":"23",
    "gn:admin2_code":"2.0",
    "gn:asciiname":"Nuevo Israel",
    "gn:country_code":"MX",
    "gn:dem":29,
    "gn:feature_class":"P",
    "gn:feature_code":"PPL",
    "gn:name":"Nuevo Israel",
    "gn:population":409,
    "gn:timezone":"America/Cancun",
    "iso:country":"MX",
    "wof:name":"Nuevo Israel",
    "wof:placetype":"locality",
    "wof:population":409
},
  "geometry": {"coordinates":[-88.55188000000003,19.24121],"type":"Point"}
}