{
  "type": "Feature",
  "properties": {
    "gn:admin1_code":"14",
    "gn:admin2_code":"30",
    "gn:asciiname":"El Llano",
    "gn:country_code":"MX",
    "gn:dem":1539,
    "gn:feature_class":"P",
    "gn:feature_code":"PPL",
    "gn:name":"El Llano",
    "gn:population":11,
    "gn:timezone":"America/Mexico_City",
    "iso:country":"MX",
    "name:ceb_x_preferred":[
        "El Llano"
    ],
    "name:deu_x_preferred":[
        "El Llano"
    ],
    "name:fra_x_preferred":[
        "El Llano"
    ],
    "name:ita_x_preferred":[
        "El Llano"
    ],
    "name:spa_x_preferred":[
        "El Llano"
    ],
    "name:swe_x_preferred":[
        "El Llano"
    ],
    "wof:name":"El Llano",
    "wof:placetype":"locality",
    "wof:population":11
},
  "geometry": {"coordinates":[-103.14749999999999,20.32111],"type":"Point"}
}