{
  "type": "Feature",
  "properties": {
    "gn:admin1_code":"6",
    "gn:admin2_code":"12.0",
    "gn:asciiname":"Chinaleachi",
    "gn:country_code":"MX",
    "gn:dem":2042,
    "gn:feature_class":"P",
    "gn:feature_code":"PPL",
    "gn:name":"Chinaleachi",
    "gn:population":0,
    "gn:timezone":"America/Chihuahua",
    "iso:country":"MX",
    "name:spa_x_preferred":[
        "Chinaleachi"
    ],
    "wof:name":"Chinaleachi",
    "wof:placetype":"locality"
},
  "geometry": {"coordinates":[-107.13043,27.83027],"type":"Point"}
}