{
  "type": "Feature",
  "properties": {
    "gn:admin1_code":"10",
    "gn:admin2_code":"19.0",
    "gn:asciiname":"El Verano",
    "gn:country_code":"MX",
    "gn:dem":2322,
    "gn:feature_class":"P",
    "gn:feature_code":"PPL",
    "gn:name":"El Verano",
    "gn:population":0,
    "gn:timezone":"America/Monterrey",
    "iso:country":"MX",
    "name:spa_x_preferred":[
        "El Verano"
    ],
    "wof:name":"El Verano",
    "wof:placetype":"locality"
},
  "geometry": {"coordinates":[-106.05437999999999,24.57209],"type":"Point"}
}