{
  "type": "Feature",
  "properties": {
    "gn:admin1_code":"12.0",
    "gn:asciiname":"Yoso Cano",
    "gn:country_code":"MX",
    "gn:dem":2028,
    "gn:feature_class":"P",
    "gn:feature_code":"PPL",
    "gn:name":"Yoso Cano",
    "gn:population":0,
    "gn:timezone":"America/Mexico_City",
    "iso:country":"MX",
    "name:spa_x_preferred":[
        "Yoso Cano"
    ],
    "name:spa_x_variant":[
        "Yoso Kano"
    ],
    "wof:name":"Yoso Cano",
    "wof:placetype":"locality"
},
  "geometry": {"coordinates":[-98.39617,17.19437000000001],"type":"Point"}
}