{
  "type": "Feature",
  "properties": {
    "gn:admin1_code":"1",
    "gn:admin2_code":"1",
    "gn:asciiname":"Las Bugambilias",
    "gn:country_code":"MX",
    "gn:dem":1868,
    "gn:feature_class":"P",
    "gn:feature_code":"PPL",
    "gn:name":"Las Bugambilias",
    "gn:population":18,
    "gn:timezone":"America/Mexico_City",
    "iso:country":"MX",
    "wof:name":"Las Bugambilias",
    "wof:placetype":"locality",
    "wof:population":18
},
  "geometry": {"coordinates":[-102.35083,21.78972000000001],"type":"Point"}
}