{
  "type": "Feature",
  "properties": {
    "gn:admin1_code":"26",
    "gn:admin2_code":"70.0",
    "gn:asciiname":"Villa Tres Cruces",
    "gn:country_code":"MX",
    "gn:dem":427,
    "gn:feature_class":"P",
    "gn:feature_code":"PPL",
    "gn:name":"Villa Tres Cruces",
    "gn:population":6,
    "gn:timezone":"America/Hermosillo",
    "iso:country":"MX",
    "wof:name":"Villa Tres Cruces",
    "wof:placetype":"locality",
    "wof:population":6
},
  "geometry": {"coordinates":[-112.87335,31.67664000000001],"type":"Point"}
}