{
  "type": "Feature",
  "properties": {
    "gn:admin1_code":"7",
    "gn:admin2_code":"37.0",
    "gn:asciiname":"Los Enriquez",
    "gn:country_code":"MX",
    "gn:dem":463,
    "gn:feature_class":"P",
    "gn:feature_code":"PPL",
    "gn:name":"Los Enriquez",
    "gn:population":0,
    "gn:timezone":"America/Monterrey",
    "iso:country":"MX",
    "name:spa_x_preferred":[
        "Los Enriquez"
    ],
    "name:und_x_variant":[
        "Rancho Los Enriques"
    ],
    "wof:name":"Los Enriquez",
    "wof:placetype":"locality"
},
  "geometry": {"coordinates":[-100.88383,27.9134],"type":"Point"}
}