{
  "type": "Feature",
  "properties": {
    "gn:admin1_code":"13",
    "gn:admin2_code":"77.0",
    "gn:asciiname":"Zototlan",
    "gn:country_code":"MX",
    "gn:dem":2138,
    "gn:feature_class":"P",
    "gn:feature_code":"PPL",
    "gn:name":"Zototl\u00e1n",
    "gn:population":189,
    "gn:timezone":"America/Mexico_City",
    "iso:country":"MX",
    "name:und_x_variant":[
        "Zototl\u00e1n"
    ],
    "wof:name":"Zototlan",
    "wof:placetype":"locality",
    "wof:population":189
},
  "geometry": {"coordinates":[-98.35486,20.14093],"type":"Point"}
}