{
  "type": "Feature",
  "properties": {
    "gn:admin1_code":"15",
    "gn:admin2_code":"95.0",
    "gn:asciiname":"Colonia Guadalupe",
    "gn:country_code":"MX",
    "gn:dem":2310,
    "gn:feature_class":"P",
    "gn:feature_code":"PPL",
    "gn:name":"Colonia Guadalupe",
    "gn:population":1178,
    "gn:timezone":"America/Mexico_City",
    "iso:country":"MX",
    "wof:name":"Colonia Guadalupe",
    "wof:placetype":"locality",
    "wof:population":1178
},
  "geometry": {"coordinates":[-99.24972,19.71306],"type":"Point"}
}