{
  "type": "Feature",
  "properties": {
    "gn:admin1_code":"32.0",
    "gn:admin2_code":"42.0",
    "gn:asciiname":"Villa Insurgentes (El Calabazal)",
    "gn:cc2":"MX",
    "gn:country_code":"MX",
    "gn:dem":2159,
    "gn:feature_class":"P",
    "gn:feature_code":"PPL",
    "gn:name":"Villa Insurgentes (El Calabazal)",
    "gn:population":1355,
    "gn:timezone":"America/Mexico_City",
    "iso:country":"MX",
    "name:und_x_variant":[
        "Calabazal",
        "El Calabazal"
    ],
    "wof:name":"Villa Insurgentes (El Calabazal)",
    "wof:placetype":"locality",
    "wof:population":1355
},
  "geometry": {"coordinates":[-103.8425,23.74306],"type":"Point"}
}