{
  "type": "Feature",
  "properties": {
    "gn:admin1_code":"1",
    "gn:admin2_code":"7.0",
    "gn:asciiname":"San Isidro [Rancho]",
    "gn:country_code":"MX",
    "gn:dem":1933,
    "gn:feature_class":"P",
    "gn:feature_code":"PPL",
    "gn:name":"San Isidro [Rancho]",
    "gn:population":4,
    "gn:timezone":"America/Mexico_City",
    "iso:country":"MX",
    "wof:name":"San Isidro [Rancho]",
    "wof:placetype":"locality",
    "wof:population":4
},
  "geometry": {"coordinates":[-102.22333,22.30139],"type":"Point"}
}