{
  "type": "Feature",
  "properties": {
    "gn:admin1_code":"28",
    "gn:admin2_code":"16.0",
    "gn:asciiname":"Capellania",
    "gn:country_code":"MX",
    "gn:dem":264,
    "gn:feature_class":"P",
    "gn:feature_code":"PPL",
    "gn:name":"Capellan\u00eda",
    "gn:population":0,
    "gn:timezone":"America/Monterrey",
    "iso:country":"MX",
    "name:spa_x_preferred":[
        "Capellan\u00eda"
    ],
    "wof:name":"Capellania",
    "wof:placetype":"locality"
},
  "geometry": {"coordinates":[-99.29107999999999,24.00975],"type":"Point"}
}