{
  "type": "Feature",
  "properties": {
    "gn:admin1_code":"5",
    "gn:admin2_code":"84.0",
    "gn:asciiname":"Villaflores",
    "gn:country_code":"MX",
    "gn:dem":835,
    "gn:feature_class":"P",
    "gn:feature_code":"PPL",
    "gn:name":"Villaflores",
    "gn:population":563,
    "gn:timezone":"America/Mexico_City",
    "iso:country":"MX",
    "wof:name":"Villaflores",
    "wof:placetype":"locality",
    "wof:population":563
},
  "geometry": {"coordinates":[-92.96056,17.35639],"type":"Point"}
}