{
  "type": "Feature",
  "properties": {
    "gn:admin1_code":"5",
    "gn:admin2_code":"19",
    "gn:asciiname":"El Corralito",
    "gn:country_code":"MX",
    "gn:dem":662,
    "gn:feature_class":"P",
    "gn:feature_code":"PPL",
    "gn:name":"El Corralito",
    "gn:population":11,
    "gn:timezone":"America/Mexico_City",
    "iso:country":"MX",
    "wof:name":"El Corralito",
    "wof:placetype":"locality",
    "wof:population":11
},
  "geometry": {"coordinates":[-92.20471999999999,16.09361],"type":"Point"}
}