{
  "type": "Feature",
  "properties": {
    "gn:admin1_code":"21",
    "gn:admin2_code":"86.0",
    "gn:asciiname":"El Retiro",
    "gn:country_code":"MX",
    "gn:dem":178,
    "gn:feature_class":"P",
    "gn:feature_code":"PPL",
    "gn:name":"El Retiro",
    "gn:population":217,
    "gn:timezone":"America/Mexico_City",
    "iso:country":"MX",
    "wof:name":"El Retiro",
    "wof:placetype":"locality",
    "wof:population":217
},
  "geometry": {"coordinates":[-97.75360999999999,20.43861],"type":"Point"}
}