{
  "type": "Feature",
  "properties": {
    "gn:admin1_code":"11",
    "gn:admin2_code":"15.0",
    "gn:asciiname":"La Haciendita",
    "gn:country_code":"MX",
    "gn:dem":1840,
    "gn:feature_class":"P",
    "gn:feature_code":"PPL",
    "gn:name":"La Haciendita",
    "gn:population":279,
    "gn:timezone":"America/Mexico_City",
    "iso:country":"MX",
    "wof:name":"La Haciendita",
    "wof:placetype":"locality",
    "wof:population":279
},
  "geometry": {"coordinates":[-101.2812,20.91333],"type":"Point"}
}