{
  "type": "Feature",
  "properties": {
    "gn:admin1_code":"5",
    "gn:admin2_code":"11.0",
    "gn:asciiname":"Nuevo Pacayal",
    "gn:country_code":"MX",
    "gn:dem":674,
    "gn:feature_class":"P",
    "gn:feature_code":"PPL",
    "gn:name":"Nuevo Pacayal",
    "gn:population":0,
    "gn:timezone":"America/Mexico_City",
    "iso:country":"MX",
    "name:spa_x_preferred":[
        "Nuevo Pacayal"
    ],
    "wof:name":"Nuevo Pacayal",
    "wof:placetype":"locality"
},
  "geometry": {"coordinates":[-92.31538,15.6601],"type":"Point"}
}