{
  "type": "Feature",
  "properties": {
    "gn:admin1_code":"13",
    "gn:admin2_code":"27.0",
    "gn:asciiname":"San Clemente",
    "gn:country_code":"MX",
    "gn:dem":897,
    "gn:feature_class":"P",
    "gn:feature_code":"PPL",
    "gn:name":"San Clemente",
    "gn:population":0,
    "gn:timezone":"America/Mexico_City",
    "iso:country":"MX",
    "name:spa_x_preferred":[
        "San Clemente"
    ],
    "wof:name":"San Clemente",
    "wof:placetype":"locality"
},
  "geometry": {"coordinates":[-98.14671,20.40491],"type":"Point"}
}