{
  "type": "Feature",
  "properties": {
    "gn:admin1_code":"30",
    "gn:admin2_code":"189.0",
    "gn:asciiname":"Inigo Laviada",
    "gn:country_code":"MX",
    "gn:dem":6,
    "gn:feature_class":"P",
    "gn:feature_code":"PPL",
    "gn:name":"\u00cd\u00f1igo Laviada",
    "gn:population":5,
    "gn:timezone":"America/Mexico_City",
    "iso:country":"MX",
    "name:und_x_variant":[
        "\u00cd\u00f1igo Laviada"
    ],
    "wof:name":"Inigo Laviada",
    "wof:placetype":"locality",
    "wof:population":5
},
  "geometry": {"coordinates":[-97.42667,20.91694],"type":"Point"}
}