{
  "type": "Feature",
  "properties": {
    "gn:admin1_code":"32",
    "gn:admin2_code":"30.0",
    "gn:asciiname":"Agua Salada",
    "gn:country_code":"MX",
    "gn:dem":1693,
    "gn:feature_class":"P",
    "gn:feature_code":"PPL",
    "gn:name":"Agua Salada",
    "gn:population":0,
    "gn:timezone":"America/Mexico_City",
    "iso:country":"MX",
    "name:spa_x_preferred":[
        "Agua Salada"
    ],
    "wof:name":"Agua Salada",
    "wof:placetype":"locality"
},
  "geometry": {"coordinates":[-103.28203000000001,21.92639],"type":"Point"}
}