{
  "type": "Feature",
  "properties": {
    "gn:admin1_code":"15",
    "gn:admin2_code":"37",
    "gn:asciiname":"Paraje San Miguel",
    "gn:country_code":"MX",
    "gn:dem":2586,
    "gn:feature_class":"P",
    "gn:feature_code":"PPL",
    "gn:name":"Paraje San Miguel",
    "gn:population":21,
    "gn:timezone":"America/Mexico_City",
    "iso:country":"MX",
    "wof:name":"Paraje San Miguel",
    "wof:placetype":"locality",
    "wof:population":21
},
  "geometry": {"coordinates":[-99.3104,19.38003],"type":"Point"}
}