{
  "type": "Feature",
  "properties": {
    "gn:admin1_code":"28",
    "gn:admin2_code":"22.0",
    "gn:asciiname":"Perote",
    "gn:country_code":"MX",
    "gn:dem":15,
    "gn:feature_class":"P",
    "gn:feature_code":"PPL",
    "gn:name":"Perote",
    "gn:population":0,
    "gn:timezone":"America/Matamoros",
    "iso:country":"MX",
    "name:und_x_variant":[
        "Ejido El Perote",
        "Perote",
        "El Perote"
    ],
    "wof:name":"Perote",
    "wof:placetype":"locality"
},
  "geometry": {"coordinates":[-97.69946,25.91414],"type":"Point"}
}