{
  "type": "Feature",
  "properties": {
    "gn:admin1_code":"25",
    "gn:admin2_code":"11.0",
    "gn:asciiname":"El Tasito",
    "gn:country_code":"MX",
    "gn:dem":22,
    "gn:feature_class":"P",
    "gn:feature_code":"PPL",
    "gn:name":"El Tasito",
    "gn:population":0,
    "gn:timezone":"America/Mazatlan",
    "iso:country":"MX",
    "name:spa_x_preferred":[
        "El Tasito"
    ],
    "wof:name":"El Tasito",
    "wof:placetype":"locality"
},
  "geometry": {"coordinates":[-108.62756,25.66348],"type":"Point"}
}