{
  "type": "Feature",
  "properties": {
    "gn:admin1_code":"12",
    "gn:admin2_code":"21",
    "gn:asciiname":"Aguas Calientes",
    "gn:country_code":"MX",
    "gn:dem":67,
    "gn:feature_class":"P",
    "gn:feature_code":"PPL",
    "gn:name":"Aguas Calientes",
    "gn:population":10,
    "gn:timezone":"America/Mexico_City",
    "iso:country":"MX",
    "wof:name":"Aguas Calientes",
    "wof:placetype":"locality",
    "wof:population":10
},
  "geometry": {"coordinates":[-100.06954,17.08737],"type":"Point"}
}