{
  "type": "Feature",
  "properties": {
    "gn:admin1_code":"15",
    "gn:admin2_code":"37.0",
    "gn:asciiname":"Agua Bendita",
    "gn:country_code":"MX",
    "gn:dem":2738,
    "gn:feature_class":"P",
    "gn:feature_code":"PPL",
    "gn:name":"Agua Bendita",
    "gn:population":251,
    "gn:timezone":"America/Mexico_City",
    "iso:country":"MX",
    "name:por_x_preferred":[
        "Agua Bendita"
    ],
    "name:tgl_x_preferred":[
        "Agua Bendita"
    ],
    "wof:name":"Agua Bendita",
    "wof:placetype":"locality",
    "wof:population":251
},
  "geometry": {"coordinates":[-99.36927,19.35868],"type":"Point"}
}