{
  "type": "Feature",
  "properties": {
    "gn:admin1_code":"2.0",
    "gn:asciiname":"Rancho Canada Escondida",
    "gn:country_code":"MX",
    "gn:dem":250,
    "gn:feature_class":"P",
    "gn:feature_code":"PPL",
    "gn:name":"Rancho Ca\u00f1ada Escondida",
    "gn:population":0,
    "gn:timezone":"America/Tijuana",
    "iso:country":"MX",
    "name:spa_x_preferred":[
        "Rancho Ca\u00f1ada Escondida"
    ],
    "wof:name":"Rancho Canada Escondida",
    "wof:placetype":"locality"
},
  "geometry": {"coordinates":[-116.52697000000001,31.89781],"type":"Point"}
}