{
  "type": "Feature",
  "properties": {
    "gn:admin1_code":"6",
    "gn:admin2_code":"44.0",
    "gn:asciiname":"La Cocolista",
    "gn:country_code":"MX",
    "gn:dem":1810,
    "gn:feature_class":"P",
    "gn:feature_code":"PPL",
    "gn:name":"La Cocolista",
    "gn:population":6,
    "gn:timezone":"America/Chihuahua",
    "iso:country":"MX",
    "wof:name":"La Cocolista",
    "wof:placetype":"locality",
    "wof:population":6
},
  "geometry": {"coordinates":[-105.52415999999999,26.5646],"type":"Point"}
}