{
  "type": "Feature",
  "properties": {
    "gn:admin1_code":"16",
    "gn:admin2_code":"59",
    "gn:asciiname":"San Joaquin",
    "gn:country_code":"MX",
    "gn:dem":1251,
    "gn:feature_class":"P",
    "gn:feature_code":"PPL",
    "gn:name":"San Joaqu\u00edn",
    "gn:population":11,
    "gn:timezone":"America/Mexico_City",
    "iso:country":"MX",
    "name:und_x_variant":[
        "San Joaqu\u00edn"
    ],
    "wof:name":"San Joaquin",
    "wof:placetype":"locality",
    "wof:population":11
},
  "geometry": {"coordinates":[-101.77889,19.07111],"type":"Point"}
}