{
  "type": "Feature",
  "properties": {
    "gn:admin1_code":"5",
    "gn:admin2_code":"30.0",
    "gn:asciiname":"La Pinta",
    "gn:country_code":"MX",
    "gn:dem":688,
    "gn:feature_class":"P",
    "gn:feature_code":"PPL",
    "gn:name":"La Pinta",
    "gn:population":0,
    "gn:timezone":"America/Mexico_City",
    "iso:country":"MX",
    "name:spa_x_preferred":[
        "La Pinta"
    ],
    "wof:name":"La Pinta",
    "wof:placetype":"locality"
},
  "geometry": {"coordinates":[-92.44277,15.74216],"type":"Point"}
}