{
  "type": "Feature",
  "properties": {
    "gn:admin1_code":"16.0",
    "gn:asciiname":"El Chino",
    "gn:country_code":"MX",
    "gn:dem":3012,
    "gn:feature_class":"P",
    "gn:feature_code":"PPL",
    "gn:name":"El Chino",
    "gn:population":0,
    "gn:timezone":"America/Mexico_City",
    "iso:country":"MX",
    "name:spa_x_preferred":[
        "El Chino"
    ],
    "wof:name":"El Chino",
    "wof:placetype":"locality"
},
  "geometry": {"coordinates":[-100.66361000000001,19.8074],"type":"Point"}
}