{
  "type": "Feature",
  "properties": {
    "gn:admin1_code":"10",
    "gn:admin2_code":"37",
    "gn:asciiname":"La Huertecilla",
    "gn:country_code":"MX",
    "gn:dem":1901,
    "gn:feature_class":"P",
    "gn:feature_code":"PPL",
    "gn:name":"La Huertecilla",
    "gn:population":20,
    "gn:timezone":"America/Monterrey",
    "iso:country":"MX",
    "wof:name":"La Huertecilla",
    "wof:placetype":"locality",
    "wof:population":20
},
  "geometry": {"coordinates":[-106.54731,25.20386],"type":"Point"}
}