{
  "type": "Feature",
  "properties": {
    "gn:admin1_code":"14.0",
    "gn:admin2_code":"116.0",
    "gn:asciiname":"San Juanico de Enmedio",
    "gn:country_code":"MX",
    "gn:dem":1823,
    "gn:feature_class":"P",
    "gn:feature_code":"PPL",
    "gn:name":"San Juanico de Enmedio",
    "gn:population":0,
    "gn:timezone":"America/Mexico_City",
    "iso:country":"MX",
    "name:spa_x_preferred":[
        "San Juanico de Enmedio"
    ],
    "wof:name":"San Juanico de Enmedio",
    "wof:placetype":"locality"
},
  "geometry": {"coordinates":[-102.53291,21.6546],"type":"Point"}
}