{
  "type": "Feature",
  "properties": {
    "gn:admin1_code":"30",
    "gn:admin2_code":"182.0",
    "gn:asciiname":"Colonia Ejidal (Ejido San Andres)",
    "gn:country_code":"MX",
    "gn:dem":1540,
    "gn:feature_class":"P",
    "gn:feature_code":"PPL",
    "gn:name":"Colonia Ejidal (Ejido San Andr\u00e9s)",
    "gn:population":469,
    "gn:timezone":"America/Mexico_City",
    "iso:country":"MX",
    "name:und_x_variant":[
        "Colonia Ejidal (Ejido San Andr\u00e9s)"
    ],
    "wof:name":"Colonia Ejidal (Ejido San Andres)",
    "wof:placetype":"locality",
    "wof:population":469
},
  "geometry": {"coordinates":[-96.95611,19.56139],"type":"Point"}
}