{
  "type": "Feature",
  "properties": {
    "gn:admin1_code":"32",
    "gn:admin2_code":"10.0",
    "gn:asciiname":"Porfias",
    "gn:country_code":"MX",
    "gn:dem":2263,
    "gn:feature_class":"P",
    "gn:feature_code":"PPL",
    "gn:name":"Porf\u00edas",
    "gn:population":0,
    "gn:timezone":"America/Mexico_City",
    "iso:country":"MX",
    "wof:name":"Porfias",
    "wof:placetype":"locality"
},
  "geometry": {"coordinates":[-103.25,23.11667000000001],"type":"Point"}
}