{
  "type": "Feature",
  "properties": {
    "gn:admin1_code":"5",
    "gn:admin2_code":"30.0",
    "gn:asciiname":"Piedra Labrada",
    "gn:country_code":"MX",
    "gn:dem":634,
    "gn:feature_class":"P",
    "gn:feature_code":"PPL",
    "gn:name":"Piedra Labrada",
    "gn:population":0,
    "gn:timezone":"America/Mexico_City",
    "iso:country":"MX",
    "name:spa_x_preferred":[
        "Piedra Labrada"
    ],
    "wof:name":"Piedra Labrada",
    "wof:placetype":"locality"
},
  "geometry": {"coordinates":[-92.30538,15.68226],"type":"Point"}
}