{
  "type": "Feature",
  "properties": {
    "gn:admin1_code":"20",
    "gn:admin2_code":"427.0",
    "gn:asciiname":"Septune",
    "gn:country_code":"MX",
    "gn:dem":201,
    "gn:feature_class":"P",
    "gn:feature_code":"PPL",
    "gn:name":"Septune",
    "gn:population":329,
    "gn:timezone":"America/Mexico_City",
    "iso:country":"MX",
    "wof:name":"Septune",
    "wof:placetype":"locality",
    "wof:population":329
},
  "geometry": {"coordinates":[-95.0625,16.88806],"type":"Point"}
}