{
  "type": "Feature",
  "properties": {
    "gn:admin1_code":"14",
    "gn:admin2_code":"46",
    "gn:asciiname":"Capellania",
    "gn:country_code":"MX",
    "gn:dem":1703,
    "gn:feature_class":"P",
    "gn:feature_code":"PPL",
    "gn:name":"Capellan\u00eda",
    "gn:population":19,
    "gn:timezone":"America/Mexico_City",
    "iso:country":"MX",
    "name:und_x_variant":[
        "Capellan\u00eda"
    ],
    "wof:name":"Capellania",
    "wof:placetype":"locality",
    "wof:population":19
},
  "geometry": {"coordinates":[-102.47750000000001,21.25389],"type":"Point"}
}