{
  "type": "Feature",
  "properties": {
    "gn:admin1_code":"21",
    "gn:admin2_code":"51.0",
    "gn:asciiname":"San Jose los Laureles",
    "gn:country_code":"MX",
    "gn:dem":1013,
    "gn:feature_class":"P",
    "gn:feature_code":"PPL",
    "gn:name":"San Jos\u00e9 los Laureles",
    "gn:population":0,
    "gn:timezone":"America/Mexico_City",
    "iso:country":"MX",
    "name:spa_x_preferred":[
        "San Jos\u00e9 los Laureles"
    ],
    "name:und_x_variant":[
        "Laureles",
        "San Jos\u00e9 Laureles",
        "San Jos\u00e9 Los Laureles"
    ],
    "wof:name":"San Jose los Laureles",
    "wof:placetype":"locality"
},
  "geometry": {"coordinates":[-98.69882,18.50116],"type":"Point"}
}