{
  "type": "Feature",
  "properties": {
    "gn:admin1_code":"6",
    "gn:admin2_code":"9.0",
    "gn:asciiname":"Sapareachi",
    "gn:country_code":"MX",
    "gn:dem":2177,
    "gn:feature_class":"P",
    "gn:feature_code":"PPL",
    "gn:name":"Sapareachi",
    "gn:population":0,
    "gn:timezone":"America/Chihuahua",
    "iso:country":"MX",
    "name:spa_x_preferred":[
        "Sapareachi"
    ],
    "wof:name":"Sapareachi",
    "wof:placetype":"locality"
},
  "geometry": {"coordinates":[-107.29763,27.68858],"type":"Point"}
}