{
  "type": "Feature",
  "properties": {
    "gn:admin1_code":"6",
    "gn:admin2_code":"46.0",
    "gn:asciiname":"Santa Ana",
    "gn:country_code":"MX",
    "gn:dem":456,
    "gn:feature_class":"P",
    "gn:feature_code":"PPL",
    "gn:name":"Santa Ana",
    "gn:population":0,
    "gn:timezone":"America/Chihuahua",
    "iso:country":"MX",
    "name:afr_x_preferred":[
        "Santa Ana"
    ],
    "name:ara_x_preferred":[
        "\u0633\u0627\u0646\u062a \u0622\u0646\u0627"
    ],
    "name:ara_x_variant":[
        "\u0633\u0627\u0646\u062a\u0627 \u0622\u0646\u0627"
    ],
    "name:ben_x_preferred":[
        "\u09b8\u09be\u09a8\u09cd\u09a4\u09be \u0986\u09a8\u09be"
    ],
    "name:bre_x_preferred":[
        "Santa Ana"
    ],
    "name:bul_x_preferred":[
        "\u0421\u0430\u043d\u0442\u0430 \u0410\u043d\u0430"
    ],
    "name:cat_x_preferred":[
        "Santa Ana"
    ],
    "name:ceb_x_preferred":[
        "Santa Ana"
    ],
    "name:deu_x_preferred":[
        "Santa Ana"
    ],
    "name:ell_x_preferred":[
        "\u0391\u03b3\u03af\u03b1 \u0386\u03bd\u03b1"
    ],
    "name:epo_x_preferred":[
        "Santa Ana"
    ],
    "name:fas_x_preferred":[
        "\u0633\u0627\u0646\u062a\u0627 \u0622\u0646\u0627"
    ],
    "name:fin_x_preferred":[
        "Santa Ana"
    ],
    "name:fra_x_preferred":[
        "Santa Ana"
    ],
    "name:glg_x_preferred":[
        "Santa Ana"
    ],
    "name:heb_x_preferred":[
        "\u05e1\u05e0\u05d8\u05d4 \u05d0\u05e0\u05d4"
    ],
    "name:hin_x_preferred":[
        "\u0938\u0948\u0902\u091f\u093e \u0910\u0928\u093e"
    ],
    "name:hun_x_preferred":[
        "Santa Ana"
    ],
    "name:hye_x_preferred":[
        "\u054d\u0561\u0576\u057f\u0561 \u0531\u0576\u0561"
    ],
    "name:ilo_x_preferred":[
        "Santa Ana"
    ],
    "name:ind_x_preferred":[
        "Santa Ana"
    ],
    "name:ita_x_preferred":[
        "Santa Ana"
    ],
    "name:jpn_x_preferred":[
        "\u30b5\u30f3\u30bf\u30a2\u30ca"
    ],
    "name:kat_x_preferred":[
        "\u10e1\u10d0\u10dc\u10e2\u10d0-\u10d0\u10dc\u10d0"
    ],
    "name:kor_x_preferred":[
        "\uc0b0\ud0c0\uc544\ub098"
    ],
    "name:lav_x_preferred":[
        "Santaana"
    ],
    "name:lit_x_preferred":[
        "Santa Ana"
    ],
    "name:nah_x_preferred":[
        "Santa Ana"
    ],
    "name:nds_x_preferred":[
        "Santa Ana"
    ],
    "name:nld_x_preferred":[
        "Santa Ana"
    ],
    "name:pnb_x_preferred":[
        "\u0633\u0627\u0646\u0679\u0627 \u0627\u06cc\u0646\u0627"
    ],
    "name:pol_x_preferred":[
        "Santa Ana"
    ],
    "name:por_x_preferred":[
        "Santa Ana"
    ],
    "name:que_x_preferred":[
        "Santa Ana"
    ],
    "name:rus_x_preferred":[
        "\u0421\u0430\u043d\u0442\u0430-\u0410\u043d\u0430"
    ],
    "name:sco_x_preferred":[
        "Santa Ana"
    ],
    "name:slk_x_preferred":[
        "Santa Ana"
    ],
    "name:spa_x_preferred":[
        "Santa Ana"
    ],
    "name:srp_x_preferred":[
        "\u0421\u0430\u043d\u0442\u0430 \u0410\u043d\u0430"
    ],
    "name:swe_x_preferred":[
        "Santa Ana"
    ],
    "name:tur_x_preferred":[
        "Santa Ana"
    ],
    "name:ukr_x_preferred":[
        "\u0421\u0430\u043d\u0442\u0430-\u0410\u043d\u0430"
    ],
    "name:urd_x_preferred":[
        "\u0633\u06cc\u0646\u0679\u0627 \u0627\u06cc\u0646\u0627"
    ],
    "name:vie_x_preferred":[
        "Santa Ana"
    ],
    "name:war_x_preferred":[
        "Santa Ana"
    ],
    "wof:name":"Santa Ana",
    "wof:placetype":"locality"
},
  "geometry": {"coordinates":[-107.61923,26.76421],"type":"Point"}
}