{
  "type": "Feature",
  "properties": {
    "gn:admin1_code":"10",
    "gn:admin2_code":"4.0",
    "gn:asciiname":"Alto los Rabones",
    "gn:country_code":"MX",
    "gn:dem":2136,
    "gn:feature_class":"P",
    "gn:feature_code":"PPL",
    "gn:name":"Alto los Rabones",
    "gn:population":0,
    "gn:timezone":"America/Monterrey",
    "iso:country":"MX",
    "name:spa_x_preferred":[
        "Alto los Rabones"
    ],
    "name:spa_x_variant":[
        "El Papalote"
    ],
    "wof:name":"Alto los Rabones",
    "wof:placetype":"locality"
},
  "geometry": {"coordinates":[-103.61818,24.32946],"type":"Point"}
}