{
  "type": "Feature",
  "properties": {
    "gn:admin1_code":"6",
    "gn:admin2_code":"1",
    "gn:asciiname":"El Gavilan",
    "gn:country_code":"MX",
    "gn:dem":1276,
    "gn:feature_class":"P",
    "gn:feature_code":"PPL",
    "gn:name":"El Gavil\u00e1n",
    "gn:population":10,
    "gn:timezone":"America/Chihuahua",
    "iso:country":"MX",
    "name:und_x_variant":[
        "El Gavil\u00e1n"
    ],
    "wof:name":"El Gavilan",
    "wof:placetype":"locality",
    "wof:population":10
},
  "geometry": {"coordinates":[-106.76998,30.30431],"type":"Point"}
}