{
  "type": "Feature",
  "properties": {
    "gn:admin1_code":"26",
    "gn:admin2_code":"3.0",
    "gn:asciiname":"Los Brasiles",
    "gn:country_code":"MX",
    "gn:dem":295,
    "gn:feature_class":"P",
    "gn:feature_code":"PPL",
    "gn:name":"Los Brasiles",
    "gn:population":0,
    "gn:timezone":"America/Hermosillo",
    "iso:country":"MX",
    "name:und_x_variant":[
        "Brasiles",
        "Los Brasiles"
    ],
    "wof:name":"Los Brasiles",
    "wof:placetype":"locality"
},
  "geometry": {"coordinates":[-108.8139,26.82232],"type":"Point"}
}