{
  "type": "Feature",
  "properties": {
    "iso:country":"MX",
    "name:afr_x_preferred":[
        "Monte Alb\u00e1n"
    ],
    "name:ara_x_preferred":[
        "\u0645\u0648\u0646\u062a\u064a \u0623\u0644\u0628\u0627\u0646"
    ],
    "name:arg_x_preferred":[
        "Monte Alb\u00e1n"
    ],
    "name:bul_x_preferred":[
        "\u041c\u043e\u043d\u0442\u0435 \u0410\u043b\u0431\u0430\u043d"
    ],
    "name:cat_x_preferred":[
        "Monte Alb\u00e1n"
    ],
    "name:ces_x_preferred":[
        "Monte Alb\u00e1n"
    ],
    "name:dan_x_preferred":[
        "Monte Alb\u00e1n"
    ],
    "name:deu_x_preferred":[
        "Monte Alb\u00e1n"
    ],
    "name:epo_x_preferred":[
        "Monte Alb\u00e1n"
    ],
    "name:spa_x_preferred":[
        "Monte Alban",
        "Monte Alb\u00e1n"
    ],
    "name:unk_x_variant":[
        "Monte Alban"
    ],
    "qs:gn_adm0_cc":"MX",
    "qs:gn_local":3522507,
    "qs:gn_nam_loc":"Oaxaca de Juarez, Oaxaca de Ju\u00e1rez, Oaxaca, MX",
    "qs:gn_namadm1":"20",
    "qs:local_max":5236,
    "qs:local_sum":18801,
    "qs:localhoods":12,
    "qs:name":"Monte Alban",
    "qs:name_adm0":"M\u00e9xico",
    "qs:name_adm1":"Oaxaca",
    "qs:name_adm2":"Oaxaca de Juarez",
    "qs:name_local":"Oaxaca de Ju\u00e1rez",
    "qs:photo_max":612,
    "qs:photo_sum":3037,
    "qs:placetype":"Suburb",
    "qs:quad_count":46,
    "qs:woe_adm0":23424900,
    "qs:woe_adm1":2346283,
    "qs:woe_adm2":12600729,
    "qs:woe_lau":0,
    "qs:woe_local":134889,
    "qs:woe_ver":"7.10.0",
    "wd:wordcount":3263,
    "wof:lang":[
        "spa"
    ],
    "wof:name":"Monte Alban",
    "wof:placetype":"neighbourhood"
},
  "geometry": {"coordinates":[-96.763655,17.046783],"type":"Point"}
}