{
  "type": "Feature",
  "properties": {
    "gn:admin1_code":"14",
    "gn:admin2_code":"43",
    "gn:asciiname":"Las Higuerillas",
    "gn:country_code":"MX",
    "gn:dem":20,
    "gn:feature_class":"P",
    "gn:feature_code":"PPL",
    "gn:name":"Las Higuerillas",
    "gn:population":15,
    "gn:timezone":"America/Mexico_City",
    "iso:country":"MX",
    "wof:name":"Las Higuerillas",
    "wof:placetype":"locality",
    "wof:population":15
},
  "geometry": {"coordinates":[-105.15389,19.66778],"type":"Point"}
}