{
  "type": "Feature",
  "properties": {
    "gn:admin1_code":"30",
    "gn:admin2_code":"141.0",
    "gn:asciiname":"Cerro Amarillo de Arriba",
    "gn:country_code":"MX",
    "gn:dem":170,
    "gn:feature_class":"P",
    "gn:feature_code":"PPL",
    "gn:name":"Cerro Amarillo de Arriba",
    "gn:population":760,
    "gn:timezone":"America/Mexico_City",
    "iso:country":"MX",
    "wof:name":"Cerro Amarillo de Arriba",
    "wof:placetype":"locality",
    "wof:population":760
},
  "geometry": {"coordinates":[-95.24250000000001,18.42417],"type":"Point"}
}