{
  "type": "Feature",
  "properties": {
    "gn:admin1_code":"31",
    "gn:admin2_code":"48.0",
    "gn:asciiname":"Chen-Chic",
    "gn:country_code":"MX",
    "gn:dem":4,
    "gn:feature_class":"P",
    "gn:feature_code":"PPL",
    "gn:name":"Chen-Chic",
    "gn:population":0,
    "gn:timezone":"America/Merida",
    "iso:country":"MX",
    "name:spa_x_preferred":[
        "Chenchik"
    ],
    "name:spa_x_variant":[
        "Chen-Chic"
    ],
    "wof:name":"Chen-Chic",
    "wof:placetype":"locality"
},
  "geometry": {"coordinates":[-90.12094,20.79614],"type":"Point"}
}