{
  "type": "Feature",
  "properties": {
    "gn:admin1_code":"6.0",
    "gn:admin2_code":"15.0",
    "gn:asciiname":"El Charco de la Yegua",
    "gn:country_code":"MX",
    "gn:dem":1478,
    "gn:feature_class":"P",
    "gn:feature_code":"PPL",
    "gn:name":"El Charco de la Yegua",
    "gn:population":0,
    "gn:timezone":"America/Chihuahua",
    "iso:country":"MX",
    "name:und_x_variant":[
        "Rancho Charco de la Yegua",
        "El Charco de la Yegua"
    ],
    "wof:name":"El Charco de la Yegua",
    "wof:placetype":"locality"
},
  "geometry": {"coordinates":[-105.47409,29.89724],"type":"Point"}
}