{
  "type": "Feature",
  "properties": {
    "gn:admin1_code":"29",
    "gn:admin2_code":"18.0",
    "gn:asciiname":"Santa Maria Aquiahuac",
    "gn:country_code":"MX",
    "gn:dem":2451,
    "gn:feature_class":"P",
    "gn:feature_code":"PPL",
    "gn:name":"Santa Mar\u00eda Aqui\u00e1huac",
    "gn:population":541,
    "gn:timezone":"America/Mexico_City",
    "iso:country":"MX",
    "name:und_x_variant":[
        "Santa Mar\u00eda Aqui\u00e1huac"
    ],
    "wof:name":"Santa Maria Aquiahuac",
    "wof:placetype":"locality",
    "wof:population":541
},
  "geometry": {"coordinates":[-98.12889,19.32194],"type":"Point"}
}