{
  "type": "Feature",
  "properties": {
    "gn:admin1_code":"11",
    "gn:admin2_code":"33.0",
    "gn:asciiname":"El Salitrillo",
    "gn:country_code":"MX",
    "gn:dem":2048,
    "gn:feature_class":"P",
    "gn:feature_code":"PPL",
    "gn:name":"El Salitrillo",
    "gn:population":80,
    "gn:timezone":"America/Mexico_City",
    "iso:country":"MX",
    "wof:name":"El Salitrillo",
    "wof:placetype":"locality",
    "wof:population":80
},
  "geometry": {"coordinates":[-100.49611,21.30278],"type":"Point"}
}