{
  "type": "Feature",
  "properties": {
    "gn:admin1_code":"19",
    "gn:admin2_code":"20",
    "gn:asciiname":"El Huizache",
    "gn:country_code":"MX",
    "gn:dem":118,
    "gn:feature_class":"P",
    "gn:feature_code":"PPL",
    "gn:name":"El Huizache",
    "gn:population":47,
    "gn:timezone":"America/Monterrey",
    "iso:country":"MX",
    "wof:name":"El Huizache",
    "wof:placetype":"locality",
    "wof:population":47
},
  "geometry": {"coordinates":[-99.01835,25.82785],"type":"Point"}
}