{
  "type": "Feature",
  "properties": {
    "gn:admin1_code":"10",
    "gn:admin2_code":"5",
    "gn:asciiname":"El Madrono",
    "gn:country_code":"MX",
    "gn:dem":2651,
    "gn:feature_class":"P",
    "gn:feature_code":"PPL",
    "gn:name":"El Madro\u00f1o",
    "gn:population":34,
    "gn:timezone":"America/Monterrey",
    "iso:country":"MX",
    "name:und_x_variant":[
        "El Madro\u00f1o"
    ],
    "wof:name":"El Madrono",
    "wof:placetype":"locality",
    "wof:population":34
},
  "geometry": {"coordinates":[-105.07834,23.88585],"type":"Point"}
}