{
  "type": "Feature",
  "properties": {
    "gn:admin1_code":"11.0",
    "gn:admin2_code":"30.0",
    "gn:asciiname":"El Agua Fria",
    "gn:country_code":"MX",
    "gn:dem":2392,
    "gn:feature_class":"P",
    "gn:feature_code":"PPL",
    "gn:name":"El Agua Fr\u00eda",
    "gn:population":0,
    "gn:timezone":"America/Mexico_City",
    "iso:country":"MX",
    "name:spa_x_preferred":[
        "El Agua Fr\u00eda"
    ],
    "wof:name":"El Agua Fria",
    "wof:placetype":"locality"
},
  "geometry": {"coordinates":[-101.03238,21.47392],"type":"Point"}
}