{
  "type": "Feature",
  "properties": {
    "gn:admin1_code":"8.0",
    "gn:admin2_code":"7.0",
    "gn:asciiname":"Cedros",
    "gn:country_code":"MX",
    "gn:dem":369,
    "gn:feature_class":"P",
    "gn:feature_code":"PPL",
    "gn:name":"Cedros",
    "gn:population":0,
    "gn:timezone":"America/Mexico_City",
    "iso:country":"MX",
    "name:ceb_x_preferred":[
        "Cedros"
    ],
    "name:deu_x_preferred":[
        "Cedros"
    ],
    "name:fra_x_preferred":[
        "Cedros"
    ],
    "name:nld_x_preferred":[
        "Cedros"
    ],
    "name:por_x_preferred":[
        "Cedros"
    ],
    "name:spa_x_preferred":[
        "Cedros"
    ],
    "name:swe_x_preferred":[
        "Cedros"
    ],
    "name:ukr_x_preferred":[
        "\u0421\u0435\u0434\u0440\u043e\u0441"
    ],
    "wof:name":"Cedros",
    "wof:placetype":"locality"
},
  "geometry": {"coordinates":[-104.23933,19.28387],"type":"Point"}
}