{
  "type": "Feature",
  "properties": {
    "gn:admin1_code":"16.0",
    "gn:admin2_code":"95.0",
    "gn:asciiname":"El Agostadero",
    "gn:country_code":"MX",
    "gn:dem":650,
    "gn:feature_class":"P",
    "gn:feature_code":"PPL",
    "gn:name":"El Agostadero",
    "gn:population":0,
    "gn:timezone":"America/Mexico_City",
    "iso:country":"MX",
    "name:spa_x_preferred":[
        "El Agostadero"
    ],
    "wof:name":"El Agostadero",
    "wof:placetype":"locality"
},
  "geometry": {"coordinates":[-102.71669,19.52761],"type":"Point"}
}