{
  "type": "Feature",
  "properties": {
    "gn:admin1_code":"2",
    "gn:admin2_code":"1.0",
    "gn:asciiname":"El Aguaje",
    "gn:country_code":"MX",
    "gn:dem":135,
    "gn:feature_class":"P",
    "gn:feature_code":"PPL",
    "gn:name":"El Aguaje",
    "gn:population":53,
    "gn:timezone":"America/Tijuana",
    "iso:country":"MX",
    "wof:name":"El Aguaje",
    "wof:placetype":"locality",
    "wof:population":53
},
  "geometry": {"coordinates":[-116.63500000000001,31.69806],"type":"Point"}
}