{
  "type": "Feature",
  "properties": {
    "gn:admin1_code":"11.0",
    "gn:admin2_code":"4.0",
    "gn:asciiname":"Paredones",
    "gn:country_code":"MX",
    "gn:dem":1964,
    "gn:feature_class":"P",
    "gn:feature_code":"PPL",
    "gn:name":"Paredones",
    "gn:population":0,
    "gn:timezone":"America/Mexico_City",
    "iso:country":"MX",
    "name:spa_x_preferred":[
        "Paredones"
    ],
    "wof:name":"Paredones",
    "wof:placetype":"locality"
},
  "geometry": {"coordinates":[-100.5639,20.38874],"type":"Point"}
}