{
  "type": "Feature",
  "properties": {
    "gn:admin1_code":"4",
    "gn:admin2_code":"11",
    "gn:asciiname":"El Borbonal",
    "gn:country_code":"MX",
    "gn:dem":46,
    "gn:feature_class":"P",
    "gn:feature_code":"PPL",
    "gn:name":"El Borbonal",
    "gn:population":10,
    "gn:timezone":"America/Merida",
    "iso:country":"MX",
    "wof:name":"El Borbonal",
    "wof:placetype":"locality",
    "wof:population":10
},
  "geometry": {"coordinates":[-91.15528,18.25861],"type":"Point"}
}