{
  "type": "Feature",
  "properties": {
    "gn:admin1_code":"19",
    "gn:admin2_code":"2.0",
    "gn:asciiname":"Cienaguitas",
    "gn:country_code":"MX",
    "gn:dem":335,
    "gn:feature_class":"P",
    "gn:feature_code":"PPL",
    "gn:name":"Cienaguitas",
    "gn:population":0,
    "gn:timezone":"America/Monterrey",
    "iso:country":"MX",
    "wof:name":"Cienaguitas",
    "wof:placetype":"locality"
},
  "geometry": {"coordinates":[-99.86667,26.33333],"type":"Point"}
}