{
  "type": "Feature",
  "properties": {
    "gn:admin1_code":"6.0",
    "gn:admin2_code":"25.0",
    "gn:asciiname":"Las Malvinas",
    "gn:country_code":"MX",
    "gn:dem":2244,
    "gn:feature_class":"P",
    "gn:feature_code":"PPL",
    "gn:name":"Las Malvinas",
    "gn:population":0,
    "gn:timezone":"America/Chihuahua",
    "iso:country":"MX",
    "name:spa_x_preferred":[
        "Las Malvinas"
    ],
    "wof:name":"Las Malvinas",
    "wof:placetype":"locality"
},
  "geometry": {"coordinates":[-107.64979,29.42598],"type":"Point"}
}