{
  "type": "Feature",
  "properties": {
    "gn:admin1_code":"32",
    "gn:admin2_code":"46.0",
    "gn:asciiname":"Las Cuatro Milpas",
    "gn:country_code":"MX",
    "gn:dem":1969,
    "gn:feature_class":"P",
    "gn:feature_code":"PPL",
    "gn:name":"Las Cuatro Milpas",
    "gn:population":5,
    "gn:timezone":"America/Mexico_City",
    "iso:country":"MX",
    "wof:name":"Las Cuatro Milpas",
    "wof:placetype":"locality",
    "wof:population":5
},
  "geometry": {"coordinates":[-103.12278000000001,22.46417000000001],"type":"Point"}
}