{
  "type": "Feature",
  "properties": {
    "gn:admin1_code":"16.0",
    "gn:admin2_code":"59.0",
    "gn:asciiname":"Los Otates",
    "gn:country_code":"MX",
    "gn:dem":963,
    "gn:feature_class":"P",
    "gn:feature_code":"PPL",
    "gn:name":"Los Otates",
    "gn:population":0,
    "gn:timezone":"America/Mexico_City",
    "iso:country":"MX",
    "name:spa_x_preferred":[
        "Los Otates"
    ],
    "wof:name":"Los Otates",
    "wof:placetype":"locality"
},
  "geometry": {"coordinates":[-101.82653000000001,19.1704],"type":"Point"}
}