{
  "type": "Feature",
  "properties": {
    "gn:admin1_code":"12",
    "gn:admin2_code":"73.0",
    "gn:asciiname":"El Pinzan",
    "gn:country_code":"MX",
    "gn:dem":653,
    "gn:feature_class":"P",
    "gn:feature_code":"PPL",
    "gn:name":"El Pinz\u00e1n",
    "gn:population":0,
    "gn:timezone":"America/Mexico_City",
    "iso:country":"MX",
    "name:spa_x_preferred":[
        "El Pinz\u00e1n"
    ],
    "wof:name":"El Pinzan",
    "wof:placetype":"locality"
},
  "geometry": {"coordinates":[-101.22573,18.34547],"type":"Point"}
}