{
  "type": "Feature",
  "properties": {
    "gn:admin1_code":"25",
    "gn:admin2_code":"4",
    "gn:asciiname":"Los Zacatitos",
    "gn:country_code":"MX",
    "gn:dem":111,
    "gn:feature_class":"P",
    "gn:feature_code":"PPL",
    "gn:name":"Los Zacatitos",
    "gn:population":27,
    "gn:timezone":"America/Mazatlan",
    "iso:country":"MX",
    "wof:name":"Los Zacatitos",
    "wof:placetype":"locality",
    "wof:population":27
},
  "geometry": {"coordinates":[-106.0732,23.29174],"type":"Point"}
}