{
  "type": "Feature",
  "properties": {
    "gn:admin1_code":"30",
    "gn:admin2_code":"139.0",
    "gn:asciiname":"El Zopilote",
    "gn:country_code":"MX",
    "gn:dem":7,
    "gn:feature_class":"P",
    "gn:feature_code":"PPL",
    "gn:name":"El Zopilote",
    "gn:population":0,
    "gn:timezone":"America/Mexico_City",
    "iso:country":"MX",
    "name:spa_x_preferred":[
        "El Zopilote"
    ],
    "wof:name":"El Zopilote",
    "wof:placetype":"locality"
},
  "geometry": {"coordinates":[-95.55622,18.59786],"type":"Point"}
}