{
  "type": "Feature",
  "properties": {
    "gn:admin1_code":"28",
    "gn:admin2_code":"33.0",
    "gn:asciiname":"Pedro Monsivais",
    "gn:country_code":"MX",
    "gn:dem":32,
    "gn:feature_class":"P",
    "gn:feature_code":"PPL",
    "gn:name":"Pedro Monsiv\u00e1is",
    "gn:population":6,
    "gn:timezone":"America/Monterrey",
    "iso:country":"MX",
    "name:und_x_variant":[
        "Pedro Monsiv\u00e1is"
    ],
    "wof:name":"Pedro Monsivais",
    "wof:placetype":"locality",
    "wof:population":6
},
  "geometry": {"coordinates":[-98.11360999999999,25.74861],"type":"Point"}
}