{
  "type": "Feature",
  "properties": {
    "gn:admin1_code":"20.0",
    "gn:admin2_code":"67.0",
    "gn:asciiname":"Donaji",
    "gn:country_code":"MX",
    "gn:dem":1689,
    "gn:feature_class":"P",
    "gn:feature_code":"PPL",
    "gn:name":"Donaji",
    "gn:population":0,
    "gn:timezone":"America/Mexico_City",
    "iso:country":"MX",
    "name:spa_x_preferred":[
        "Donaji"
    ],
    "wof:name":"Donaji",
    "wof:placetype":"locality"
},
  "geometry": {"coordinates":[-96.70202999999999,17.10388],"type":"Point"}
}