{
  "type": "Feature",
  "properties": {
    "gn:admin1_code":"11.0",
    "gn:admin2_code":"7.0",
    "gn:asciiname":"Los Aguirre",
    "gn:country_code":"MX",
    "gn:dem":1762,
    "gn:feature_class":"P",
    "gn:feature_code":"PPL",
    "gn:name":"Los Aguirre",
    "gn:population":0,
    "gn:timezone":"America/Mexico_City",
    "iso:country":"MX",
    "name:spa_x_preferred":[
        "Los Aguirre"
    ],
    "name:spa_x_variant":[
        "Aguirre"
    ],
    "wof:name":"Los Aguirre",
    "wof:placetype":"locality"
},
  "geometry": {"coordinates":[-100.8763,20.60764],"type":"Point"}
}