{
  "type": "Feature",
  "properties": {
    "gn:admin1_code":"20",
    "gn:admin2_code":"107.0",
    "gn:asciiname":"El Palenque",
    "gn:country_code":"MX",
    "gn:dem":1588,
    "gn:feature_class":"P",
    "gn:feature_code":"PPL",
    "gn:name":"El Palenque",
    "gn:population":83,
    "gn:timezone":"America/Mexico_City",
    "iso:country":"MX",
    "wof:name":"El Palenque",
    "wof:placetype":"locality",
    "wof:population":83
},
  "geometry": {"coordinates":[-96.69528,17.02806],"type":"Point"}
}