{
  "type": "Feature",
  "properties": {
    "gn:admin1_code":"16.0",
    "gn:admin2_code":"82.0",
    "gn:asciiname":"Loma Linda",
    "gn:country_code":"MX",
    "gn:dem":2183,
    "gn:feature_class":"P",
    "gn:feature_code":"PPL",
    "gn:name":"Loma Linda",
    "gn:population":0,
    "gn:timezone":"America/Mexico_City",
    "iso:country":"MX",
    "name:spa_x_preferred":[
        "Loma Linda"
    ],
    "wof:name":"Loma Linda",
    "wof:placetype":"locality"
},
  "geometry": {"coordinates":[-101.40269000000001,19.31518],"type":"Point"}
}