{
  "type": "Feature",
  "properties": {
    "gn:admin1_code":"20",
    "gn:admin2_code":"334.0",
    "gn:asciiname":"Penas Negras",
    "gn:country_code":"MX",
    "gn:dem":888,
    "gn:feature_class":"P",
    "gn:feature_code":"PPL",
    "gn:name":"Pe\u00f1as Negras",
    "gn:population":0,
    "gn:timezone":"America/Mexico_City",
    "iso:country":"MX",
    "name:spa_x_preferred":[
        "Pe\u00f1as Negras"
    ],
    "wof:name":"Penas Negras",
    "wof:placetype":"locality"
},
  "geometry": {"coordinates":[-97.48904,16.22619],"type":"Point"}
}