{
  "type": "Feature",
  "properties": {
    "gn:admin1_code":"30",
    "gn:admin2_code":"108.0",
    "gn:asciiname":"Benito Juarez (Cocuite)",
    "gn:country_code":"MX",
    "gn:dem":17,
    "gn:feature_class":"P",
    "gn:feature_code":"PPL",
    "gn:name":"Benito Ju\u00e1rez (Cocuite)",
    "gn:population":127,
    "gn:timezone":"America/Mexico_City",
    "iso:country":"MX",
    "name:und_x_variant":[
        "Benito Ju\u00e1rez (Cocuite)"
    ],
    "wof:name":"Benito Juarez (Cocuite)",
    "wof:placetype":"locality",
    "wof:population":127
},
  "geometry": {"coordinates":[-94.55833,17.68694],"type":"Point"}
}