{
  "type": "Feature",
  "properties": {
    "gn:admin1_code":"21",
    "gn:admin2_code":"51.0",
    "gn:asciiname":"Temaxcalapa de Gabino Barreda",
    "gn:country_code":"MX",
    "gn:dem":1140,
    "gn:feature_class":"P",
    "gn:feature_code":"PPL",
    "gn:name":"Temaxcalapa de Gabino Barreda",
    "gn:population":635,
    "gn:timezone":"America/Mexico_City",
    "iso:country":"MX",
    "wof:name":"Temaxcalapa de Gabino Barreda",
    "wof:placetype":"locality",
    "wof:population":635
},
  "geometry": {"coordinates":[-98.60611,18.55417000000001],"type":"Point"}
}