{
  "type": "Feature",
  "properties": {
    "gn:admin1_code":"22",
    "gn:admin2_code":"9.0",
    "gn:asciiname":"Quirambitos",
    "gn:country_code":"MX",
    "gn:dem":1513,
    "gn:feature_class":"P",
    "gn:feature_code":"PPL",
    "gn:name":"Quirambitos",
    "gn:population":8,
    "gn:timezone":"America/Mexico_City",
    "iso:country":"MX",
    "wof:name":"Quirambitos",
    "wof:placetype":"locality",
    "wof:population":8
},
  "geometry": {"coordinates":[-99.45222,21.13083],"type":"Point"}
}