{
  "type": "Feature",
  "properties": {
    "gn:admin1_code":"25.0",
    "gn:admin2_code":"7.0",
    "gn:asciiname":"Cabayhuaza",
    "gn:cc2":"MX",
    "gn:country_code":"MX",
    "gn:dem":126,
    "gn:feature_class":"P",
    "gn:feature_code":"PPL",
    "gn:name":"Cabayhuaza",
    "gn:population":0,
    "gn:timezone":"America/Mazatlan",
    "iso:country":"MX",
    "name:und_x_variant":[
        "Cabayhuasa",
        "Cabayhauza",
        "Cabayhuaza"
    ],
    "wof:name":"Cabayhuaza",
    "wof:placetype":"locality"
},
  "geometry": {"coordinates":[-108.52972,26.71528],"type":"Point"}
}