{
  "type": "Feature",
  "properties": {
    "gn:admin1_code":"24",
    "gn:admin2_code":"10.0",
    "gn:asciiname":"El Divisadero",
    "gn:country_code":"MX",
    "gn:dem":1033,
    "gn:feature_class":"P",
    "gn:feature_code":"PPL",
    "gn:name":"El Divisadero",
    "gn:population":0,
    "gn:timezone":"America/Mexico_City",
    "iso:country":"MX",
    "name:und_x_variant":[
        "La Garra"
    ],
    "wof:name":"El Divisadero",
    "wof:placetype":"locality"
},
  "geometry": {"coordinates":[-99.79773,22.20798],"type":"Point"}
}