{
  "type": "Feature",
  "properties": {
    "gn:admin1_code":"12",
    "gn:admin2_code":"11",
    "gn:asciiname":"Los Planes",
    "gn:country_code":"MX",
    "gn:dem":853,
    "gn:feature_class":"P",
    "gn:feature_code":"PPL",
    "gn:name":"Los Planes",
    "gn:population":21,
    "gn:timezone":"America/Mexico_City",
    "iso:country":"MX",
    "wof:name":"Los Planes",
    "wof:placetype":"locality",
    "wof:population":21
},
  "geometry": {"coordinates":[-100.30708,17.41561],"type":"Point"}
}