{
  "type": "Feature",
  "properties": {
    "gn:admin1_code":"25.0",
    "gn:admin2_code":"11.0",
    "gn:asciiname":"El Callejon de Tamazula",
    "gn:country_code":"MX",
    "gn:dem":11,
    "gn:feature_class":"P",
    "gn:feature_code":"PPL",
    "gn:name":"El Callej\u00f3n de Tamazula",
    "gn:population":0,
    "gn:timezone":"America/Mazatlan",
    "iso:country":"MX",
    "wof:name":"El Callejon de Tamazula",
    "wof:placetype":"locality"
},
  "geometry": {"coordinates":[-108.43837000000001,25.445],"type":"Point"}
}