{
  "type": "Feature",
  "properties": {
    "gn:admin1_code":"5.0",
    "gn:admin2_code":"19.0",
    "gn:asciiname":"La Poblazon",
    "gn:country_code":"MX",
    "gn:dem":793,
    "gn:feature_class":"P",
    "gn:feature_code":"PPL",
    "gn:name":"La Poblaz\u00f3n",
    "gn:population":0,
    "gn:timezone":"America/Mexico_City",
    "iso:country":"MX",
    "name:spa_x_preferred":[
        "La Poblaz\u00f3n"
    ],
    "wof:name":"La Poblazon",
    "wof:placetype":"locality"
},
  "geometry": {"coordinates":[-92.15792999999999,16.07497],"type":"Point"}
}