{
  "type": "Feature",
  "properties": {
    "gn:admin1_code":"13",
    "gn:admin2_code":"73.0",
    "gn:asciiname":"Moyotla",
    "gn:country_code":"MX",
    "gn:dem":1015,
    "gn:feature_class":"P",
    "gn:feature_code":"PPL",
    "gn:name":"Moyotla",
    "gn:population":0,
    "gn:timezone":"America/Mexico_City",
    "iso:country":"MX",
    "name:spa_x_preferred":[
        "Moyotla"
    ],
    "wof:name":"Moyotla",
    "wof:placetype":"locality"
},
  "geometry": {"coordinates":[-98.66786,21.04763],"type":"Point"}
}