{
  "type": "Feature",
  "properties": {
    "gn:admin1_code":"6.0",
    "gn:admin2_code":"27.0",
    "gn:asciiname":"Mesa de Chihuachi",
    "gn:country_code":"MX",
    "gn:dem":2339,
    "gn:feature_class":"P",
    "gn:feature_code":"PPL",
    "gn:name":"Mesa de Chihuachi",
    "gn:population":0,
    "gn:timezone":"America/Chihuahua",
    "iso:country":"MX",
    "name:spa_x_preferred":[
        "Mesa de Chihuachi"
    ],
    "wof:name":"Mesa de Chihuachi",
    "wof:placetype":"locality"
},
  "geometry": {"coordinates":[-106.95305999999999,27.06495],"type":"Point"}
}