{
  "type": "Feature",
  "properties": {
    "gn:admin1_code":"26",
    "gn:admin2_code":"46.0",
    "gn:asciiname":"San Pascual",
    "gn:country_code":"MX",
    "gn:dem":570,
    "gn:feature_class":"P",
    "gn:feature_code":"PPL",
    "gn:name":"San Pascual",
    "gn:population":9,
    "gn:timezone":"America/Hermosillo",
    "iso:country":"MX",
    "name:ceb_x_preferred":[
        "San Pascual"
    ],
    "name:deu_x_preferred":[
        "San Pascual"
    ],
    "name:fra_x_preferred":[
        "San Pascual"
    ],
    "name:ilo_x_preferred":[
        "San Pascual"
    ],
    "name:ita_x_preferred":[
        "San Pascual"
    ],
    "name:nld_x_preferred":[
        "San Pascual"
    ],
    "name:sco_x_preferred":[
        "San Pascual"
    ],
    "name:spa_x_preferred":[
        "San Pascual"
    ],
    "name:swe_x_preferred":[
        "San Pascual"
    ],
    "name:vie_x_preferred":[
        "San Pascual"
    ],
    "name:war_x_preferred":[
        "San Pascual"
    ],
    "wof:name":"San Pascual",
    "wof:placetype":"locality",
    "wof:population":9
},
  "geometry": {"coordinates":[-111.59166999999999,30.63778],"type":"Point"}
}