{
  "type": "Feature",
  "properties": {
    "gn:admin1_code":"20",
    "gn:admin2_code":"278.0",
    "gn:asciiname":"Cerro de Agua Platanar",
    "gn:country_code":"MX",
    "gn:dem":79,
    "gn:feature_class":"P",
    "gn:feature_code":"PPL",
    "gn:name":"Cerro de Agua Platanar",
    "gn:population":461,
    "gn:timezone":"America/Mexico_City",
    "iso:country":"MX",
    "wof:name":"Cerro de Agua Platanar",
    "wof:placetype":"locality",
    "wof:population":461
},
  "geometry": {"coordinates":[-96.52861,18.37333],"type":"Point"}
}