{
  "type": "Feature",
  "properties": {
    "gn:admin1_code":"15",
    "gn:admin2_code":"63",
    "gn:asciiname":"Tlaltizapan",
    "gn:country_code":"MX",
    "gn:dem":2312,
    "gn:feature_class":"P",
    "gn:feature_code":"PPL",
    "gn:name":"Tlaltizapan",
    "gn:population":45,
    "gn:timezone":"America/Mexico_City",
    "iso:country":"MX",
    "wof:name":"Tlaltizapan",
    "wof:placetype":"locality",
    "wof:population":45
},
  "geometry": {"coordinates":[-99.34278999999999,18.97654],"type":"Point"}
}