{
  "type": "Feature",
  "properties": {
    "gn:admin1_code":"6",
    "gn:admin2_code":"30.0",
    "gn:asciiname":"Cienega Prieta",
    "gn:country_code":"MX",
    "gn:dem":1627,
    "gn:feature_class":"P",
    "gn:feature_code":"PPL",
    "gn:name":"Ci\u00e9nega Prieta",
    "gn:population":7,
    "gn:timezone":"America/Chihuahua",
    "iso:country":"MX",
    "name:und_x_variant":[
        "Ci\u00e9nega Prieta"
    ],
    "wof:name":"Cienega Prieta",
    "wof:placetype":"locality",
    "wof:population":7
},
  "geometry": {"coordinates":[-108.08917,27.40875],"type":"Point"}
}