{
  "type": "Feature",
  "properties": {
    "gn:admin1_code":"5.0",
    "gn:admin2_code":"59.0",
    "gn:asciiname":"Carmen Banavil",
    "gn:country_code":"MX",
    "gn:dem":604,
    "gn:feature_class":"P",
    "gn:feature_code":"PPL",
    "gn:name":"Carmen Banavil",
    "gn:population":0,
    "gn:timezone":"America/Mexico_City",
    "iso:country":"MX",
    "name:spa_x_preferred":[
        "Banavil Pe\u00f1a Blanca"
    ],
    "name:spa_x_variant":[
        "Carmen Banavil"
    ],
    "wof:name":"Carmen Banavil",
    "wof:placetype":"locality"
},
  "geometry": {"coordinates":[-91.68738999999999,16.90293],"type":"Point"}
}