{
  "type": "Feature",
  "properties": {
    "gn:admin1_code":"26",
    "gn:admin2_code":"29.0",
    "gn:asciiname":"La Misa",
    "gn:country_code":"MX",
    "gn:dem":172,
    "gn:feature_class":"P",
    "gn:feature_code":"PPL",
    "gn:name":"La Misa",
    "gn:population":0,
    "gn:timezone":"America/Hermosillo",
    "iso:country":"MX",
    "name:und_x_variant":[
        "Misa",
        "La Misa"
    ],
    "wof:name":"La Misa",
    "wof:placetype":"locality"
},
  "geometry": {"coordinates":[-110.53274999999999,28.37591],"type":"Point"}
}