{
  "type": "Feature",
  "properties": {
    "gn:admin1_code":"30",
    "gn:admin2_code":"148.0",
    "gn:asciiname":"La Union Dos",
    "gn:country_code":"MX",
    "gn:dem":79,
    "gn:feature_class":"P",
    "gn:feature_code":"PPL",
    "gn:name":"La Uni\u00f3n Dos",
    "gn:population":120,
    "gn:timezone":"America/Mexico_City",
    "iso:country":"MX",
    "name:und_x_variant":[
        "La Uni\u00f3n Dos"
    ],
    "wof:name":"La Union Dos",
    "wof:placetype":"locality",
    "wof:population":120
},
  "geometry": {"coordinates":[-96.41028,18.96917],"type":"Point"}
}