{
  "type": "Feature",
  "properties": {
    "gn:admin1_code":"30",
    "gn:admin2_code":"4.0",
    "gn:asciiname":"Colonia Munoz",
    "gn:country_code":"MX",
    "gn:dem":350,
    "gn:feature_class":"P",
    "gn:feature_code":"PPL",
    "gn:name":"Colonia Mu\u00f1oz",
    "gn:population":221,
    "gn:timezone":"America/Mexico_City",
    "iso:country":"MX",
    "name:und_x_variant":[
        "Colonia Mu\u00f1oz"
    ],
    "wof:name":"Colonia Munoz",
    "wof:placetype":"locality",
    "wof:population":221
},
  "geometry": {"coordinates":[-96.66833,19.52667000000001],"type":"Point"}
}