{
  "type": "Feature",
  "properties": {
    "gn:admin1_code":"2.0",
    "gn:admin2_code":"4.0",
    "gn:asciiname":"La Herradura de Oro",
    "gn:country_code":"MX",
    "gn:dem":405,
    "gn:feature_class":"P",
    "gn:feature_code":"PPL",
    "gn:name":"La Herradura de Oro",
    "gn:population":4,
    "gn:timezone":"America/Tijuana",
    "iso:country":"MX",
    "name:spa_x_preferred":[
        "La Herradura de Oro"
    ],
    "wof:name":"La Herradura de Oro",
    "wof:placetype":"locality",
    "wof:population":4
},
  "geometry": {"coordinates":[-116.72,32.52306],"type":"Point"}
}