{
  "type": "Feature",
  "properties": {
    "gn:admin1_code":"14",
    "gn:admin2_code":"72",
    "gn:asciiname":"El Comedero",
    "gn:country_code":"MX",
    "gn:dem":1891,
    "gn:feature_class":"P",
    "gn:feature_code":"PPL",
    "gn:name":"El Comedero",
    "gn:population":15,
    "gn:timezone":"America/Mexico_City",
    "iso:country":"MX",
    "wof:name":"El Comedero",
    "wof:placetype":"locality",
    "wof:population":15
},
  "geometry": {"coordinates":[-101.94944,21.02639],"type":"Point"}
}