{
  "type": "Feature",
  "properties": {
    "gn:admin1_code":"31",
    "gn:admin2_code":"79.0",
    "gn:asciiname":"Poccheil",
    "gn:country_code":"MX",
    "gn:dem":80,
    "gn:feature_class":"P",
    "gn:feature_code":"PPL",
    "gn:name":"Poccheil",
    "gn:population":0,
    "gn:timezone":"America/Merida",
    "iso:country":"MX",
    "name:spa_x_preferred":[
        "Poccheil"
    ],
    "name:und_x_variant":[
        "Pocheil"
    ],
    "wof:name":"Poccheil",
    "wof:placetype":"locality"
},
  "geometry": {"coordinates":[-89.36123000000001,19.78232],"type":"Point"}
}