{
  "type": "Feature",
  "properties": {
    "gn:admin1_code":"1.0",
    "gn:admin2_code":"7.0",
    "gn:asciiname":"Estancia de Mosqueira",
    "gn:country_code":"MX",
    "gn:dem":2005,
    "gn:feature_class":"P",
    "gn:feature_code":"PPL",
    "gn:name":"Estancia de Mosqueira",
    "gn:population":0,
    "gn:timezone":"America/Mexico_City",
    "iso:country":"MX",
    "name:spa_x_preferred":[
        "Estancia de Mosqueira"
    ],
    "wof:name":"Estancia de Mosqueira",
    "wof:placetype":"locality"
},
  "geometry": {"coordinates":[-102.35223000000001,22.14214],"type":"Point"}
}