{
  "type": "Feature",
  "properties": {
    "gn:admin1_code":"7.0",
    "gn:admin2_code":"38.0",
    "gn:asciiname":"El Pensamiento",
    "gn:cc2":"MX",
    "gn:country_code":"MX",
    "gn:dem":426,
    "gn:feature_class":"P",
    "gn:feature_code":"PPL",
    "gn:name":"El Pensamiento",
    "gn:population":0,
    "gn:timezone":"America/Monterrey",
    "iso:country":"MX",
    "name:und_x_variant":[
        "Pensamiento",
        "Rancho El Pensamiento Viejo",
        "El Pensamiento"
    ],
    "wof:name":"El Pensamiento",
    "wof:placetype":"locality"
},
  "geometry": {"coordinates":[-101.11667,28.53333],"type":"Point"}
}