{
  "type": "Feature",
  "properties": {
    "gn:admin1_code":"10",
    "gn:admin2_code":"23",
    "gn:asciiname":"San Jose",
    "gn:country_code":"MX",
    "gn:dem":2649,
    "gn:feature_class":"P",
    "gn:feature_code":"PPL",
    "gn:name":"San Jos\u00e9",
    "gn:population":21,
    "gn:timezone":"America/Monterrey",
    "iso:country":"MX",
    "name:und_x_variant":[
        "San Jos\u00e9"
    ],
    "wof:name":"San Jose",
    "wof:placetype":"locality",
    "wof:population":21
},
  "geometry": {"coordinates":[-104.96913000000001,23.20452],"type":"Point"}
}