{
  "type": "Feature",
  "properties": {
    "gn:admin1_code":"16",
    "gn:admin2_code":"83.0",
    "gn:asciiname":"El Tepehuaje",
    "gn:country_code":"MX",
    "gn:dem":1690,
    "gn:feature_class":"P",
    "gn:feature_code":"PPL",
    "gn:name":"El Tepehuaje",
    "gn:population":64,
    "gn:timezone":"America/Mexico_City",
    "iso:country":"MX",
    "wof:name":"El Tepehuaje",
    "wof:placetype":"locality",
    "wof:population":64
},
  "geometry": {"coordinates":[-102.25528,19.23611],"type":"Point"}
}