{
  "type": "Feature",
  "properties": {
    "gn:admin1_code":"30",
    "gn:admin2_code":"198.0",
    "gn:asciiname":"Monte Obscuro",
    "gn:country_code":"MX",
    "gn:dem":2475,
    "gn:feature_class":"P",
    "gn:feature_code":"PPL",
    "gn:name":"Monte Obscuro",
    "gn:population":0,
    "gn:timezone":"America/Mexico_City",
    "iso:country":"MX",
    "name:spa_x_preferred":[
        "Monte Obscuro"
    ],
    "wof:name":"Monte Obscuro",
    "wof:placetype":"locality"
},
  "geometry": {"coordinates":[-98.4217,20.45209],"type":"Point"}
}