{
  "type": "Feature",
  "properties": {
    "gn:admin1_code":"5",
    "gn:admin2_code":"17.0",
    "gn:asciiname":"Vallarta",
    "gn:country_code":"MX",
    "gn:dem":673,
    "gn:feature_class":"P",
    "gn:feature_code":"PPL",
    "gn:name":"Vallarta",
    "gn:population":4,
    "gn:timezone":"America/Mexico_City",
    "iso:country":"MX",
    "name:deu_x_preferred":[
        "Vallarta"
    ],
    "name:fra_x_preferred":[
        "Vallarta"
    ],
    "wof:name":"Vallarta",
    "wof:placetype":"locality",
    "wof:population":4
},
  "geometry": {"coordinates":[-93.88,16.70222],"type":"Point"}
}