{
  "type": "Feature",
  "properties": {
    "gn:admin1_code":"6.0",
    "gn:admin2_code":"65.0",
    "gn:asciiname":"Cieneguita de Everardo",
    "gn:country_code":"MX",
    "gn:dem":2135,
    "gn:feature_class":"P",
    "gn:feature_code":"PPL",
    "gn:name":"Cieneguita de Everardo",
    "gn:population":0,
    "gn:timezone":"America/Chihuahua",
    "iso:country":"MX",
    "name:spa_x_preferred":[
        "Cieneguita de Everardo"
    ],
    "wof:name":"Cieneguita de Everardo",
    "wof:placetype":"locality"
},
  "geometry": {"coordinates":[-107.77503,27.26995],"type":"Point"}
}