{
  "type": "Feature",
  "properties": {
    "gn:admin1_code":"28",
    "gn:admin2_code":"22",
    "gn:asciiname":"El Ramireno (El Alamo)",
    "gn:country_code":"MX",
    "gn:dem":19,
    "gn:feature_class":"P",
    "gn:feature_code":"PPL",
    "gn:name":"El Ramire\u00f1o (El \u00c1lamo)",
    "gn:population":22,
    "gn:timezone":"America/Matamoros",
    "iso:country":"MX",
    "name:und_x_variant":[
        "El Ramire\u00f1o (El \u00c1lamo)"
    ],
    "wof:name":"El Ramireno (El Alamo)",
    "wof:placetype":"locality",
    "wof:population":22
},
  "geometry": {"coordinates":[-97.78471999999999,25.92306],"type":"Point"}
}