{
  "type": "Feature",
  "properties": {
    "gn:admin1_code":"16",
    "gn:admin2_code":"13.0",
    "gn:asciiname":"Los Limones",
    "gn:country_code":"MX",
    "gn:dem":729,
    "gn:feature_class":"P",
    "gn:feature_code":"PPL",
    "gn:name":"Los Limones",
    "gn:population":0,
    "gn:timezone":"America/Mexico_City",
    "iso:country":"MX",
    "name:spa_x_preferred":[
        "Los Limones"
    ],
    "wof:name":"Los Limones",
    "wof:placetype":"locality"
},
  "geometry": {"coordinates":[-100.90600000000001,18.98168],"type":"Point"}
}