{
  "type": "Feature",
  "properties": {
    "gn:admin1_code":"5",
    "gn:admin2_code":"96.0",
    "gn:asciiname":"El Refugio",
    "gn:country_code":"MX",
    "gn:dem":868,
    "gn:feature_class":"P",
    "gn:feature_code":"PPL",
    "gn:name":"El Refugio",
    "gn:population":85,
    "gn:timezone":"America/Mexico_City",
    "iso:country":"MX",
    "wof:name":"El Refugio",
    "wof:placetype":"locality",
    "wof:population":85
},
  "geometry": {"coordinates":[-92.50389,17.30778],"type":"Point"}
}