{
  "type": "Feature",
  "properties": {
    "gn:admin1_code":"10.0",
    "gn:admin2_code":"35.0",
    "gn:asciiname":"San Joaquin de Cristales",
    "gn:country_code":"MX",
    "gn:dem":2315,
    "gn:feature_class":"P",
    "gn:feature_code":"PPL",
    "gn:name":"San Joaquin de Cristales",
    "gn:population":0,
    "gn:timezone":"America/Monterrey",
    "iso:country":"MX",
    "name:spa_x_preferred":[
        "San Joaquin de Cristales"
    ],
    "wof:name":"San Joaquin de Cristales",
    "wof:placetype":"locality"
},
  "geometry": {"coordinates":[-106.01214,25.722],"type":"Point"}
}