{
  "type": "Feature",
  "properties": {
    "gn:admin1_code":"31",
    "gn:admin2_code":"17",
    "gn:asciiname":"San Isidro",
    "gn:country_code":"MX",
    "gn:dem":33,
    "gn:feature_class":"P",
    "gn:feature_code":"PPL",
    "gn:name":"San Isidro",
    "gn:population":10,
    "gn:timezone":"America/Merida",
    "iso:country":"MX",
    "wof:name":"San Isidro",
    "wof:placetype":"locality",
    "wof:population":10
},
  "geometry": {"coordinates":[-88.49778000000001,20.58833],"type":"Point"}
}