{
  "type": "Feature",
  "properties": {
    "gn:admin1_code":"14",
    "gn:admin2_code":"73",
    "gn:asciiname":"San Antonio Casas Nuevas (El Ojo de Agua)",
    "gn:country_code":"MX",
    "gn:dem":1800,
    "gn:feature_class":"P",
    "gn:feature_code":"PPL",
    "gn:name":"San Antonio Casas Nuevas (El Ojo de Agua)",
    "gn:population":35,
    "gn:timezone":"America/Mexico_City",
    "iso:country":"MX",
    "wof:name":"San Antonio Casas Nuevas (El Ojo de Agua)",
    "wof:placetype":"locality",
    "wof:population":35
},
  "geometry": {"coordinates":[-102.28917,21.37778],"type":"Point"}
}