{
  "type": "Feature",
  "properties": {
    "gn:admin1_code":"28",
    "gn:admin2_code":"3.0",
    "gn:asciiname":"El Barranco (Santiago Yanez)",
    "gn:country_code":"MX",
    "gn:dem":6,
    "gn:feature_class":"P",
    "gn:feature_code":"PPL",
    "gn:name":"El Barranco (Santiago Y\u00e1\u00f1ez)",
    "gn:population":7,
    "gn:timezone":"America/Monterrey",
    "iso:country":"MX",
    "name:und_x_variant":[
        "El Barranco (Santiago Y\u00e1\u00f1ez)"
    ],
    "wof:name":"El Barranco (Santiago Yanez)",
    "wof:placetype":"locality",
    "wof:population":7
},
  "geometry": {"coordinates":[-97.91110999999999,22.57833],"type":"Point"}
}