{
  "type": "Feature",
  "properties": {
    "gn:admin1_code":"22",
    "gn:admin2_code":"11.0",
    "gn:asciiname":"El Marques [Polo Club]",
    "gn:country_code":"MX",
    "gn:dem":1899,
    "gn:feature_class":"P",
    "gn:feature_code":"PPL",
    "gn:name":"El Marqu\u00e9s [Polo Club]",
    "gn:population":8,
    "gn:timezone":"America/Mexico_City",
    "iso:country":"MX",
    "name:und_x_variant":[
        "El Marqu\u00e9s [Polo Club]"
    ],
    "wof:name":"El Marques [Polo Club]",
    "wof:placetype":"locality",
    "wof:population":8
},
  "geometry": {"coordinates":[-100.22221999999999,20.63611],"type":"Point"}
}