{
  "type": "Feature",
  "properties": {
    "gn:admin1_code":"32",
    "gn:asciiname":"San Vicente Banderillas",
    "gn:country_code":"MX",
    "gn:dem":1965,
    "gn:feature_class":"P",
    "gn:feature_code":"PPL",
    "gn:name":"San Vicente Banderillas",
    "gn:population":0,
    "gn:timezone":"America/Mexico_City",
    "iso:country":"MX",
    "name:spa_x_preferred":[
        "San Vicente Banderillas"
    ],
    "wof:name":"San Vicente Banderillas",
    "wof:placetype":"locality"
},
  "geometry": {"coordinates":[-102.10205999999999,23.33575],"type":"Point"}
}