{
  "type": "Feature",
  "properties": {
    "gn:admin1_code":"14",
    "gn:admin2_code":"27.0",
    "gn:asciiname":"El Tizate",
    "gn:country_code":"MX",
    "gn:dem":574,
    "gn:feature_class":"P",
    "gn:feature_code":"PPL",
    "gn:name":"El Tizate",
    "gn:population":5,
    "gn:timezone":"America/Mexico_City",
    "iso:country":"MX",
    "wof:name":"El Tizate",
    "wof:placetype":"locality",
    "wof:population":5
},
  "geometry": {"coordinates":[-104.42278,19.46306],"type":"Point"}
}