{
  "type": "Feature",
  "properties": {
    "gn:admin1_code":"25",
    "gn:admin2_code":"7",
    "gn:asciiname":"La Nopalera",
    "gn:country_code":"MX",
    "gn:dem":680,
    "gn:feature_class":"P",
    "gn:feature_code":"PPL",
    "gn:name":"La Nopalera",
    "gn:population":12,
    "gn:timezone":"America/Mazatlan",
    "iso:country":"MX",
    "wof:name":"La Nopalera",
    "wof:placetype":"locality",
    "wof:population":12
},
  "geometry": {"coordinates":[-108.11573,26.71521],"type":"Point"}
}