{
  "type": "Feature",
  "properties": {
    "gn:admin1_code":"16",
    "gn:admin2_code":"6.0",
    "gn:asciiname":"Paso del Capire",
    "gn:country_code":"MX",
    "gn:dem":223,
    "gn:feature_class":"P",
    "gn:feature_code":"PPL",
    "gn:name":"Paso del Capire",
    "gn:population":87,
    "gn:timezone":"America/Mexico_City",
    "iso:country":"MX",
    "wof:name":"Paso del Capire",
    "wof:placetype":"locality",
    "wof:population":87
},
  "geometry": {"coordinates":[-102.48806,19.00556],"type":"Point"}
}