{
  "type": "Feature",
  "properties": {
    "gn:admin1_code":"6",
    "gn:admin2_code":"36.0",
    "gn:asciiname":"Nuevo Saucillo",
    "gn:country_code":"MX",
    "gn:dem":1331,
    "gn:feature_class":"P",
    "gn:feature_code":"PPL",
    "gn:name":"Nuevo Saucillo",
    "gn:population":0,
    "gn:timezone":"America/Chihuahua",
    "iso:country":"MX",
    "name:spa_x_preferred":[
        "Rancho Nuevo"
    ],
    "name:spa_x_variant":[
        "Nuevo Saucillo"
    ],
    "name:und_x_variant":[
        "Ejido Rancho Nuevo"
    ],
    "wof:name":"Nuevo Saucillo",
    "wof:placetype":"locality"
},
  "geometry": {"coordinates":[-104.87990000000001,27.27804],"type":"Point"}
}