{
  "type": "Feature",
  "properties": {
    "gn:admin1_code":"30.0",
    "gn:admin2_code":"58.0",
    "gn:asciiname":"Alaxtitla Ixcacuatitla",
    "gn:country_code":"MX",
    "gn:dem":413,
    "gn:feature_class":"P",
    "gn:feature_code":"PPL",
    "gn:name":"Alaxtitla Ixcacuatitla",
    "gn:population":313,
    "gn:timezone":"America/Mexico_City",
    "iso:country":"MX",
    "name:spa_x_preferred":[
        "Alaxtitla Ixcacuatitla"
    ],
    "wof:name":"Alaxtitla Ixcacuatitla",
    "wof:placetype":"locality",
    "wof:population":313
},
  "geometry": {"coordinates":[-98.03417,20.92222000000001],"type":"Point"}
}