{
  "type": "Feature",
  "properties": {
    "gn:admin1_code":"5",
    "gn:admin2_code":"38",
    "gn:asciiname":"Los Pinos",
    "gn:country_code":"MX",
    "gn:dem":2388,
    "gn:feature_class":"P",
    "gn:feature_code":"PPL",
    "gn:name":"Los Pinos",
    "gn:population":50,
    "gn:timezone":"America/Mexico_City",
    "iso:country":"MX",
    "wof:name":"Los Pinos",
    "wof:placetype":"locality",
    "wof:population":50
},
  "geometry": {"coordinates":[-92.48444000000001,16.74167000000001],"type":"Point"}
}