{
  "type": "Feature",
  "properties": {
    "gn:admin1_code":"10",
    "gn:admin2_code":"17.0",
    "gn:asciiname":"Las Loberas",
    "gn:country_code":"MX",
    "gn:dem":1783,
    "gn:feature_class":"P",
    "gn:feature_code":"PPL",
    "gn:name":"Las Loberas",
    "gn:population":0,
    "gn:timezone":"America/Monterrey",
    "iso:country":"MX",
    "name:spa_x_preferred":[
        "Las Loberas"
    ],
    "wof:name":"Las Loberas",
    "wof:placetype":"locality"
},
  "geometry": {"coordinates":[-105.58225,26.40841],"type":"Point"}
}