{
  "type": "Feature",
  "properties": {
    "gn:admin1_code":"5.0",
    "gn:asciiname":"Palomar",
    "gn:country_code":"MX",
    "gn:dem":804,
    "gn:feature_class":"P",
    "gn:feature_code":"PPL",
    "gn:name":"Palomar",
    "gn:population":0,
    "gn:timezone":"America/Mexico_City",
    "iso:country":"MX",
    "name:spa_x_preferred":[
        "Palomar"
    ],
    "wof:name":"Palomar",
    "wof:placetype":"locality"
},
  "geometry": {"coordinates":[-91.89174,15.96003],"type":"Point"}
}