{
  "type": "Feature",
  "properties": {
    "gn:admin1_code":"6",
    "gn:admin2_code":"65.0",
    "gn:asciiname":"Repogue",
    "gn:country_code":"MX",
    "gn:dem":2108,
    "gn:feature_class":"P",
    "gn:feature_code":"PPL",
    "gn:name":"Repogue",
    "gn:population":5,
    "gn:timezone":"America/Chihuahua",
    "iso:country":"MX",
    "wof:name":"Repogue",
    "wof:placetype":"locality",
    "wof:population":5
},
  "geometry": {"coordinates":[-107.97547,27.25715],"type":"Point"}
}