{
  "type": "Feature",
  "properties": {
    "gn:admin1_code":"32.0",
    "gn:admin2_code":"37.0",
    "gn:asciiname":"El Quijote",
    "gn:country_code":"MX",
    "gn:dem":1997,
    "gn:feature_class":"P",
    "gn:feature_code":"PPL",
    "gn:name":"El Quijote",
    "gn:population":0,
    "gn:timezone":"America/Mexico_City",
    "iso:country":"MX",
    "name:spa_x_preferred":[
        "El Quijote"
    ],
    "wof:name":"El Quijote",
    "wof:placetype":"locality"
},
  "geometry": {"coordinates":[-102.28023,23.04285],"type":"Point"}
}