{
  "type": "Feature",
  "properties": {
    "gn:admin1_code":"30",
    "gn:admin2_code":"129",
    "gn:asciiname":"Paso de las Yeguas",
    "gn:country_code":"MX",
    "gn:dem":86,
    "gn:feature_class":"P",
    "gn:feature_code":"PPL",
    "gn:name":"Paso de las Yeguas",
    "gn:population":20,
    "gn:timezone":"America/Mexico_City",
    "iso:country":"MX",
    "wof:name":"Paso de las Yeguas",
    "wof:placetype":"locality",
    "wof:population":20
},
  "geometry": {"coordinates":[-98.42639,21.37833],"type":"Point"}
}