{
  "type": "Feature",
  "properties": {
    "gn:admin1_code":"3",
    "gn:admin2_code":"1.0",
    "gn:asciiname":"El Segundo Paso",
    "gn:country_code":"MX",
    "gn:dem":167,
    "gn:feature_class":"P",
    "gn:feature_code":"PPL",
    "gn:name":"El Segundo Paso",
    "gn:population":0,
    "gn:timezone":"America/Mazatlan",
    "iso:country":"MX",
    "name:spa_x_preferred":[
        "El Segundo Paso"
    ],
    "wof:name":"El Segundo Paso",
    "wof:placetype":"locality"
},
  "geometry": {"coordinates":[-112.00606999999999,26.2941],"type":"Point"}
}