{
  "type": "Feature",
  "properties": {
    "gn:admin1_code":"6",
    "gn:admin2_code":"17.0",
    "gn:asciiname":"Bajio Blanco",
    "gn:country_code":"MX",
    "gn:dem":2172,
    "gn:feature_class":"P",
    "gn:feature_code":"PPL",
    "gn:name":"Baj\u00edo Blanco",
    "gn:population":0,
    "gn:timezone":"America/Chihuahua",
    "iso:country":"MX",
    "name:spa_x_preferred":[
        "Baj\u00edo Blanco"
    ],
    "wof:name":"Bajio Blanco",
    "wof:placetype":"locality"
},
  "geometry": {"coordinates":[-107.01769,28.91513],"type":"Point"}
}