{
  "type": "Feature",
  "properties": {
    "gn:admin1_code":"20.0",
    "gn:admin2_code":"105.0",
    "gn:asciiname":"San Isidro Monteverde",
    "gn:country_code":"MX",
    "gn:dem":2669,
    "gn:feature_class":"P",
    "gn:feature_code":"PPL",
    "gn:name":"San Isidro Monteverde",
    "gn:population":0,
    "gn:timezone":"America/Mexico_City",
    "iso:country":"MX",
    "name:spa_x_preferred":[
        "San Isidro Monteverde"
    ],
    "wof:name":"San Isidro Monteverde",
    "wof:placetype":"locality"
},
  "geometry": {"coordinates":[-97.70799,17.46952000000001],"type":"Point"}
}