{
  "type": "Feature",
  "properties": {
    "gn:admin1_code":"24",
    "gn:admin2_code":"36.0",
    "gn:asciiname":"La Tigra",
    "gn:country_code":"MX",
    "gn:dem":295,
    "gn:feature_class":"P",
    "gn:feature_code":"PPL",
    "gn:name":"La Tigra",
    "gn:population":0,
    "gn:timezone":"America/Mexico_City",
    "iso:country":"MX",
    "name:spa_x_preferred":[
        "La Tigra"
    ],
    "name:spa_x_variant":[
        "La Triga"
    ],
    "wof:name":"La Tigra",
    "wof:placetype":"locality"
},
  "geometry": {"coordinates":[-99.2367,21.72178],"type":"Point"}
}