{
  "type": "Feature",
  "properties": {
    "gn:admin1_code":"19",
    "gn:admin2_code":"45.0",
    "gn:asciiname":"Milpillas",
    "gn:country_code":"MX",
    "gn:dem":531,
    "gn:feature_class":"P",
    "gn:feature_code":"PPL",
    "gn:name":"Milpillas",
    "gn:population":7,
    "gn:timezone":"America/Monterrey",
    "iso:country":"MX",
    "name:spa_x_preferred":[
        "Milpillas"
    ],
    "name:und_x_variant":[
        "Rancho Milpillas"
    ],
    "wof:name":"Milpillas",
    "wof:placetype":"locality",
    "wof:population":7
},
  "geometry": {"coordinates":[-100.37560000000001,26.30673],"type":"Point"}
}