{
  "type": "Feature",
  "properties": {
    "gn:admin1_code":"21",
    "gn:admin2_code":"111",
    "gn:asciiname":"La Bahia",
    "gn:country_code":"MX",
    "gn:dem":353,
    "gn:feature_class":"P",
    "gn:feature_code":"PPL",
    "gn:name":"La Bah\u00eda",
    "gn:population":12,
    "gn:timezone":"America/Mexico_City",
    "iso:country":"MX",
    "name:und_x_variant":[
        "La Bah\u00eda"
    ],
    "wof:name":"La Bahia",
    "wof:placetype":"locality",
    "wof:population":12
},
  "geometry": {"coordinates":[-97.91803,20.53504],"type":"Point"}
}