{
  "type": "Feature",
  "properties": {
    "gn:admin1_code":"13",
    "gn:admin2_code":"24",
    "gn:asciiname":"La Palmilla",
    "gn:country_code":"MX",
    "gn:dem":2088,
    "gn:feature_class":"P",
    "gn:feature_code":"PPL",
    "gn:name":"La Palmilla",
    "gn:population":21,
    "gn:timezone":"America/Mexico_City",
    "iso:country":"MX",
    "name:urd_x_preferred":[
        "\u0644\u0627 \u067e\u0627\u0644\u0645\u06cc\u0644\u0627"
    ],
    "wof:name":"La Palmilla",
    "wof:placetype":"locality",
    "wof:population":21
},
  "geometry": {"coordinates":[-98.509,20.23038],"type":"Point"}
}