{
  "type": "Feature",
  "properties": {
    "gn:admin1_code":"20.0",
    "gn:admin2_code":"125.0",
    "gn:asciiname":"La Tejabana",
    "gn:country_code":"MX",
    "gn:dem":883,
    "gn:feature_class":"P",
    "gn:feature_code":"PPL",
    "gn:name":"La Tejabana",
    "gn:population":0,
    "gn:timezone":"America/Mexico_City",
    "iso:country":"MX",
    "name:spa_x_preferred":[
        "La Tejabana"
    ],
    "wof:name":"La Tejabana",
    "wof:placetype":"locality"
},
  "geometry": {"coordinates":[-96.062,16.52476],"type":"Point"}
}