{
  "type": "Feature",
  "properties": {
    "gn:admin1_code":"5",
    "gn:admin2_code":"73.0",
    "gn:asciiname":"El Pinabeto",
    "gn:country_code":"MX",
    "gn:dem":2007,
    "gn:feature_class":"P",
    "gn:feature_code":"PPL",
    "gn:name":"El Pinabeto",
    "gn:population":673,
    "gn:timezone":"America/Mexico_City",
    "iso:country":"MX",
    "wof:name":"El Pinabeto",
    "wof:placetype":"locality",
    "wof:population":673
},
  "geometry": {"coordinates":[-92.95889,17.20722],"type":"Point"}
}