{
  "type": "Feature",
  "properties": {
    "gn:admin1_code":"21",
    "gn:admin2_code":"68.0",
    "gn:asciiname":"Agua Zarca",
    "gn:country_code":"MX",
    "gn:dem":711,
    "gn:feature_class":"P",
    "gn:feature_code":"PPL",
    "gn:name":"Agua Zarca",
    "gn:population":179,
    "gn:timezone":"America/Mexico_City",
    "iso:country":"MX",
    "wof:name":"Agua Zarca",
    "wof:placetype":"locality",
    "wof:population":179
},
  "geometry": {"coordinates":[-97.73117999999999,20.11567],"type":"Point"}
}