{
  "type": "Feature",
  "properties": {
    "gn:admin1_code":"18.0",
    "gn:admin2_code":"9.0",
    "gn:asciiname":"El Pinalito",
    "gn:country_code":"MX",
    "gn:dem":1906,
    "gn:feature_class":"P",
    "gn:feature_code":"PPL",
    "gn:name":"El Pinalito",
    "gn:population":0,
    "gn:timezone":"America/Mazatlan",
    "iso:country":"MX",
    "name:spa_x_preferred":[
        "El Pinalito"
    ],
    "wof:name":"El Pinalito",
    "wof:placetype":"locality"
},
  "geometry": {"coordinates":[-104.75884000000001,22.44606],"type":"Point"}
}