{
  "type": "Feature",
  "properties": {
    "gn:admin1_code":"24",
    "gn:admin2_code":"56",
    "gn:asciiname":"Tanque el Arbol",
    "gn:country_code":"MX",
    "gn:dem":1630,
    "gn:feature_class":"P",
    "gn:feature_code":"PPL",
    "gn:name":"Tanque el \u00c1rbol",
    "gn:population":22,
    "gn:timezone":"America/Mexico_City",
    "iso:country":"MX",
    "name:und_x_variant":[
        "Tanque el \u00c1rbol"
    ],
    "wof:name":"Tanque el Arbol",
    "wof:placetype":"locality",
    "wof:population":22
},
  "geometry": {"coordinates":[-100.86972,22.59889],"type":"Point"}
}