{
  "type": "Feature",
  "properties": {
    "gn:admin1_code":"19",
    "gn:admin2_code":"38.0",
    "gn:asciiname":"El Saucito",
    "gn:country_code":"MX",
    "gn:dem":458,
    "gn:feature_class":"P",
    "gn:feature_code":"PPL",
    "gn:name":"El Saucito",
    "gn:population":79,
    "gn:timezone":"America/Monterrey",
    "iso:country":"MX",
    "name:spa_x_preferred":[
        "El Saucito"
    ],
    "wof:name":"El Saucito",
    "wof:placetype":"locality",
    "wof:population":79
},
  "geometry": {"coordinates":[-99.88916999999999,25.18451],"type":"Point"}
}