{
  "type": "Feature",
  "properties": {
    "gn:admin1_code":"6",
    "gn:admin2_code":"27.0",
    "gn:asciiname":"El Alamito",
    "gn:country_code":"MX",
    "gn:dem":2062,
    "gn:feature_class":"P",
    "gn:feature_code":"PPL",
    "gn:name":"El Alamito",
    "gn:population":5,
    "gn:timezone":"America/Chihuahua",
    "iso:country":"MX",
    "name:spa_x_preferred":[
        "El Alamito"
    ],
    "wof:name":"El Alamito",
    "wof:placetype":"locality",
    "wof:population":5
},
  "geometry": {"coordinates":[-107.42352,26.80976],"type":"Point"}
}