{
  "type": "Feature",
  "properties": {
    "gn:admin1_code":"16.0",
    "gn:admin2_code":"18.0",
    "gn:asciiname":"La Rosa de Castilla",
    "gn:country_code":"MX",
    "gn:dem":2192,
    "gn:feature_class":"P",
    "gn:feature_code":"PPL",
    "gn:name":"La Rosa de Castilla",
    "gn:population":0,
    "gn:timezone":"America/Mexico_City",
    "iso:country":"MX",
    "name:spa_x_preferred":[
        "La Rosa de Castilla"
    ],
    "name:und_x_variant":[
        "Rosa"
    ],
    "wof:name":"La Rosa de Castilla",
    "wof:placetype":"locality"
},
  "geometry": {"coordinates":[-101.28068,19.87652000000001],"type":"Point"}
}