{
  "type": "Feature",
  "properties": {
    "gn:admin1_code":"13",
    "gn:admin2_code":"80.0",
    "gn:asciiname":"Tenamaxtepec",
    "gn:country_code":"MX",
    "gn:dem":681,
    "gn:feature_class":"P",
    "gn:feature_code":"PPL",
    "gn:name":"Tenamaxtepec",
    "gn:population":775,
    "gn:timezone":"America/Mexico_City",
    "iso:country":"MX",
    "wof:name":"Tenamaxtepec",
    "wof:placetype":"locality",
    "wof:population":775
},
  "geometry": {"coordinates":[-98.36159000000001,20.8834],"type":"Point"}
}