{
  "type": "Feature",
  "properties": {
    "gn:admin1_code":"6",
    "gn:admin2_code":"29.0",
    "gn:asciiname":"Mesa del Durazno",
    "gn:country_code":"MX",
    "gn:dem":1916,
    "gn:feature_class":"P",
    "gn:feature_code":"PPL",
    "gn:name":"Mesa del Durazno",
    "gn:population":296,
    "gn:timezone":"America/Chihuahua",
    "iso:country":"MX",
    "wof:name":"Mesa del Durazno",
    "wof:placetype":"locality",
    "wof:population":296
},
  "geometry": {"coordinates":[-106.96972,25.76194],"type":"Point"}
}