{
  "type": "Feature",
  "properties": {
    "gn:admin1_code":"14",
    "gn:admin2_code":"78.0",
    "gn:asciiname":"Magueyes",
    "gn:country_code":"MX",
    "gn:dem":1857,
    "gn:feature_class":"P",
    "gn:feature_code":"PPL",
    "gn:name":"Magueyes",
    "gn:population":9,
    "gn:timezone":"America/Mexico_City",
    "iso:country":"MX",
    "wof:name":"Magueyes",
    "wof:placetype":"locality",
    "wof:population":9
},
  "geometry": {"coordinates":[-102.38778000000001,21.03833],"type":"Point"}
}