{
  "type": "Feature",
  "properties": {
    "gn:admin1_code":"28.0",
    "gn:admin2_code":"43.0",
    "gn:asciiname":"El Gavichan",
    "gn:country_code":"MX",
    "gn:dem":81,
    "gn:feature_class":"P",
    "gn:feature_code":"PPL",
    "gn:name":"El Gavich\u00e1n",
    "gn:population":1,
    "gn:timezone":"America/Monterrey",
    "iso:country":"MX",
    "name:spa_x_preferred":[
        "El Gavich\u00e1n"
    ],
    "wof:name":"El Gavichan",
    "wof:placetype":"locality",
    "wof:population":1
},
  "geometry": {"coordinates":[-98.99154,22.93268],"type":"Point"}
}