{
  "type": "Feature",
  "properties": {
    "gn:admin1_code":"6",
    "gn:admin2_code":"36.0",
    "gn:asciiname":"Zaragoza",
    "gn:country_code":"MX",
    "gn:dem":1400,
    "gn:feature_class":"P",
    "gn:feature_code":"PPL",
    "gn:name":"Zaragoza",
    "gn:population":354,
    "gn:timezone":"America/Chihuahua",
    "iso:country":"MX",
    "wof:name":"Zaragoza",
    "wof:placetype":"locality",
    "wof:population":354
},
  "geometry": {"coordinates":[-104.97638999999999,27.08833],"type":"Point"}
}