{
  "type": "Feature",
  "properties": {
    "gn:admin1_code":"20",
    "gn:admin2_code":"559.0",
    "gn:asciiname":"Palantla",
    "gn:country_code":"MX",
    "gn:dem":502,
    "gn:feature_class":"P",
    "gn:feature_code":"PPL",
    "gn:name":"Palantla",
    "gn:population":0,
    "gn:timezone":"America/Mexico_City",
    "iso:country":"MX",
    "name:spa_x_preferred":[
        "San Juan Palantla"
    ],
    "name:und_x_variant":[
        "San Juan",
        "Palantla"
    ],
    "wof:name":"Palantla",
    "wof:placetype":"locality"
},
  "geometry": {"coordinates":[-96.3947,17.85012],"type":"Point"}
}