{
  "type": "Feature",
  "properties": {
    "gn:admin1_code":"32",
    "gn:admin2_code":"34",
    "gn:asciiname":"Mesa del Agua",
    "gn:country_code":"MX",
    "gn:dem":1923,
    "gn:feature_class":"P",
    "gn:feature_code":"PPL",
    "gn:name":"Mesa del Agua",
    "gn:population":21,
    "gn:timezone":"America/Mexico_City",
    "iso:country":"MX",
    "wof:name":"Mesa del Agua",
    "wof:placetype":"locality",
    "wof:population":21
},
  "geometry": {"coordinates":[-102.86360999999999,21.38722000000001],"type":"Point"}
}