{
  "type": "Feature",
  "properties": {
    "gn:admin1_code":"14.0",
    "gn:admin2_code":"14.0",
    "gn:asciiname":"Cuyacapan",
    "gn:country_code":"MX",
    "gn:dem":1356,
    "gn:feature_class":"P",
    "gn:feature_code":"PPL",
    "gn:name":"Cuyacapan",
    "gn:population":0,
    "gn:timezone":"America/Mexico_City",
    "iso:country":"MX",
    "name:spa_x_preferred":[
        "Cuyacapan"
    ],
    "wof:name":"Cuyacapan",
    "wof:placetype":"locality"
},
  "geometry": {"coordinates":[-103.52384000000001,19.96754],"type":"Point"}
}