{
  "type": "Feature",
  "properties": {
    "gn:admin1_code":"18.0",
    "gn:admin2_code":"14.0",
    "gn:asciiname":"Los Guajes",
    "gn:country_code":"MX",
    "gn:dem":1060,
    "gn:feature_class":"P",
    "gn:feature_code":"PPL",
    "gn:name":"Los Guajes",
    "gn:population":0,
    "gn:timezone":"America/Mazatlan",
    "iso:country":"MX",
    "wof:name":"Los Guajes",
    "wof:placetype":"locality"
},
  "geometry": {"coordinates":[-104.43751,21.31719],"type":"Point"}
}