{
  "type": "Feature",
  "properties": {
    "gn:admin1_code":"26",
    "gn:admin2_code":"30.0",
    "gn:asciiname":"San Valentin",
    "gn:country_code":"MX",
    "gn:dem":33,
    "gn:feature_class":"P",
    "gn:feature_code":"PPL",
    "gn:name":"San Valent\u00edn",
    "gn:population":0,
    "gn:timezone":"America/Hermosillo",
    "iso:country":"MX",
    "name:spa_x_preferred":[
        "San Valent\u00edn"
    ],
    "wof:name":"San Valentin",
    "wof:placetype":"locality"
},
  "geometry": {"coordinates":[-111.45423,28.60164],"type":"Point"}
}