{
  "type": "Feature",
  "properties": {
    "gn:admin1_code":"22",
    "gn:admin2_code":"2.0",
    "gn:asciiname":"El Pinon",
    "gn:country_code":"MX",
    "gn:dem":2766,
    "gn:feature_class":"P",
    "gn:feature_code":"PPL",
    "gn:name":"El Pi\u00f1\u00f3n",
    "gn:population":0,
    "gn:timezone":"America/Mexico_City",
    "iso:country":"MX",
    "wof:name":"El Pinon",
    "wof:placetype":"locality"
},
  "geometry": {"coordinates":[-99.66667,21.17361],"type":"Point"}
}