{
  "type": "Feature",
  "properties": {
    "gn:admin1_code":"26",
    "gn:admin2_code":"59.0",
    "gn:asciiname":"Las Galeras",
    "gn:country_code":"MX",
    "gn:dem":1320,
    "gn:feature_class":"P",
    "gn:feature_code":"PPL",
    "gn:name":"Las Galeras",
    "gn:population":0,
    "gn:timezone":"America/Hermosillo",
    "iso:country":"MX",
    "name:und_x_variant":[
        "Rancho Las Galeras",
        "Las Galeras"
    ],
    "wof:name":"Las Galeras",
    "wof:placetype":"locality"
},
  "geometry": {"coordinates":[-110.60336,31.1832],"type":"Point"}
}