{
  "type": "Feature",
  "properties": {
    "gn:admin1_code":"24",
    "gn:admin2_code":"25.0",
    "gn:asciiname":"Palo Seco",
    "gn:country_code":"MX",
    "gn:dem":2181,
    "gn:feature_class":"P",
    "gn:feature_code":"PPL",
    "gn:name":"Palo Seco",
    "gn:population":0,
    "gn:timezone":"America/Mexico_City",
    "iso:country":"MX",
    "name:ceb_x_preferred":[
        "Palo Seco"
    ],
    "name:nld_x_preferred":[
        "Palo Seco"
    ],
    "name:spa_x_preferred":[
        "Palo Seco"
    ],
    "name:swe_x_preferred":[
        "Palo Seco"
    ],
    "wof:name":"Palo Seco",
    "wof:placetype":"locality"
},
  "geometry": {"coordinates":[-101.85317999999999,22.71991],"type":"Point"}
}