{
  "type": "Feature",
  "properties": {
    "gn:admin1_code":"28.0",
    "gn:admin2_code":"42.0",
    "gn:asciiname":"Loma Blanca",
    "gn:country_code":"MX",
    "gn:dem":340,
    "gn:feature_class":"P",
    "gn:feature_code":"PPL",
    "gn:name":"Loma Blanca",
    "gn:population":0,
    "gn:timezone":"America/Monterrey",
    "iso:country":"MX",
    "name:spa_x_preferred":[
        "Loma Blanca"
    ],
    "wof:name":"Loma Blanca",
    "wof:placetype":"locality"
},
  "geometry": {"coordinates":[-99.42333000000001,24.4725],"type":"Point"}
}