{
  "type": "Feature",
  "properties": {
    "gn:admin1_code":"31",
    "gn:admin2_code":"50.0",
    "gn:asciiname":"Tamanche",
    "gn:country_code":"MX",
    "gn:dem":8,
    "gn:feature_class":"P",
    "gn:feature_code":"PPL",
    "gn:name":"Tamanch\u00e9",
    "gn:population":587,
    "gn:timezone":"America/Merida",
    "iso:country":"MX",
    "wof:name":"Tamanche",
    "wof:placetype":"locality",
    "wof:population":587
},
  "geometry": {"coordinates":[-89.6413,21.1392],"type":"Point"}
}