{
  "type": "Feature",
  "properties": {
    "gn:admin1_code":"5.0",
    "gn:admin2_code":"109.0",
    "gn:asciiname":"Buenavista San Jose Napila",
    "gn:country_code":"MX",
    "gn:dem":1563,
    "gn:feature_class":"P",
    "gn:feature_code":"PPL",
    "gn:name":"Buenavista San Jos\u00e9 Napila",
    "gn:population":0,
    "gn:timezone":"America/Mexico_City",
    "iso:country":"MX",
    "name:spa_x_preferred":[
        "Buenavista San Jos\u00e9 Napila"
    ],
    "wof:name":"Buenavista San Jose Napila",
    "wof:placetype":"locality"
},
  "geometry": {"coordinates":[-92.31962,17.13341],"type":"Point"}
}