{
  "type": "Feature",
  "properties": {
    "gn:admin1_code":"3",
    "gn:admin2_code":"8",
    "gn:asciiname":"El Garambullo",
    "gn:country_code":"MX",
    "gn:dem":276,
    "gn:feature_class":"P",
    "gn:feature_code":"PPL",
    "gn:name":"El Garambullo",
    "gn:population":14,
    "gn:timezone":"America/Mazatlan",
    "iso:country":"MX",
    "wof:name":"El Garambullo",
    "wof:placetype":"locality",
    "wof:population":14
},
  "geometry": {"coordinates":[-109.49036,23.36194],"type":"Point"}
}