{
  "type": "Feature",
  "properties": {
    "gn:admin1_code":"6.0",
    "gn:admin2_code":"20.0",
    "gn:asciiname":"El Trigo",
    "gn:country_code":"MX",
    "gn:dem":1698,
    "gn:feature_class":"P",
    "gn:feature_code":"PPL",
    "gn:name":"El Trigo",
    "gn:population":0,
    "gn:timezone":"America/Chihuahua",
    "iso:country":"MX",
    "name:und_x_variant":[
        "Trigo",
        "El Trigo"
    ],
    "wof:name":"El Trigo",
    "wof:placetype":"locality"
},
  "geometry": {"coordinates":[-108.43089000000001,27.77432],"type":"Point"}
}