{
  "type": "Feature",
  "properties": {
    "gn:admin1_code":"20",
    "gn:admin2_code":"484.0",
    "gn:asciiname":"San Luis Morelia",
    "gn:country_code":"MX",
    "gn:dem":1682,
    "gn:feature_class":"P",
    "gn:feature_code":"PPL",
    "gn:name":"San Luis Morelia",
    "gn:population":0,
    "gn:timezone":"America/Mexico_City",
    "iso:country":"MX",
    "name:spa_x_preferred":[
        "San Luis Morelia"
    ],
    "wof:name":"San Luis Morelia",
    "wof:placetype":"locality"
},
  "geometry": {"coordinates":[-98.21420000000001,17.70344],"type":"Point"}
}