{
  "type": "Feature",
  "properties": {
    "gn:admin1_code":"30",
    "gn:admin2_code":"23.0",
    "gn:asciiname":"Azotillo",
    "gn:country_code":"MX",
    "gn:dem":214,
    "gn:feature_class":"P",
    "gn:feature_code":"PPL",
    "gn:name":"Azotillo",
    "gn:population":286,
    "gn:timezone":"America/Mexico_City",
    "iso:country":"MX",
    "wof:name":"Azotillo",
    "wof:placetype":"locality",
    "wof:population":286
},
  "geometry": {"coordinates":[-97.07333,19.98083],"type":"Point"}
}