{
  "type": "Feature",
  "properties": {
    "gn:admin1_code":"20",
    "gn:admin2_code":"143.0",
    "gn:asciiname":"Colonia Primero de Mayo",
    "gn:country_code":"MX",
    "gn:dem":15,
    "gn:feature_class":"P",
    "gn:feature_code":"PPL",
    "gn:name":"Colonia Primero de Mayo",
    "gn:population":113,
    "gn:timezone":"America/Mexico_City",
    "iso:country":"MX",
    "wof:name":"Colonia Primero de Mayo",
    "wof:placetype":"locality",
    "wof:population":113
},
  "geometry": {"coordinates":[-94.48083,16.34111],"type":"Point"}
}