{
  "type": "Feature",
  "properties": {
    "gn:admin1_code":"10",
    "gn:admin2_code":"14.0",
    "gn:asciiname":"El Duraznito",
    "gn:country_code":"MX",
    "gn:dem":1967,
    "gn:feature_class":"P",
    "gn:feature_code":"PPL",
    "gn:name":"El Duraznito",
    "gn:population":0,
    "gn:timezone":"America/Monterrey",
    "iso:country":"MX",
    "name:spa_x_preferred":[
        "El Duraznito"
    ],
    "wof:name":"El Duraznito",
    "wof:placetype":"locality"
},
  "geometry": {"coordinates":[-104.57273000000001,23.32447],"type":"Point"}
}