{
  "type": "Feature",
  "properties": {
    "gn:admin1_code":"12",
    "gn:admin2_code":"7.0",
    "gn:asciiname":"Colonia Vicente Guerrero (Comol)",
    "gn:country_code":"MX",
    "gn:dem":632,
    "gn:feature_class":"P",
    "gn:feature_code":"PPL",
    "gn:name":"Colonia Vicente Guerrero (Comol)",
    "gn:population":133,
    "gn:timezone":"America/Mexico_City",
    "iso:country":"MX",
    "wof:name":"Colonia Vicente Guerrero (Comol)",
    "wof:placetype":"locality",
    "wof:population":133
},
  "geometry": {"coordinates":[-100.21087,18.21711],"type":"Point"}
}