{
  "type": "Feature",
  "properties": {
    "gn:admin1_code":"30",
    "gn:admin2_code":"78.0",
    "gn:asciiname":"Agua Nacida",
    "gn:country_code":"MX",
    "gn:dem":197,
    "gn:feature_class":"P",
    "gn:feature_code":"PPL",
    "gn:name":"Agua Nacida",
    "gn:population":0,
    "gn:timezone":"America/Mexico_City",
    "iso:country":"MX",
    "name:spa_x_preferred":[
        "Agua Nacida"
    ],
    "wof:name":"Agua Nacida",
    "wof:placetype":"locality"
},
  "geometry": {"coordinates":[-98.08162,21.26293],"type":"Point"}
}