{
  "type": "Feature",
  "properties": {
    "gn:admin1_code":"23.0",
    "gn:asciiname":"Rancho Gabriela",
    "gn:country_code":"MX",
    "gn:dem":5,
    "gn:feature_class":"P",
    "gn:feature_code":"PPL",
    "gn:name":"Rancho Gabriela",
    "gn:population":0,
    "gn:timezone":"America/Cancun",
    "iso:country":"MX",
    "name:spa_x_preferred":[
        "Rancho Gabriela"
    ],
    "wof:name":"Rancho Gabriela",
    "wof:placetype":"locality"
},
  "geometry": {"coordinates":[-87.72686,18.65341],"type":"Point"}
}