{
  "type": "Feature",
  "properties": {
    "gn:admin1_code":"26",
    "gn:admin2_code":"13.0",
    "gn:asciiname":"El Cubo",
    "gn:country_code":"MX",
    "gn:dem":1171,
    "gn:feature_class":"P",
    "gn:feature_code":"PPL",
    "gn:name":"El Cubo",
    "gn:population":0,
    "gn:timezone":"America/Hermosillo",
    "iso:country":"MX",
    "name:spa_x_preferred":[
        "El Cubo"
    ],
    "wof:name":"El Cubo",
    "wof:placetype":"locality"
},
  "geometry": {"coordinates":[-110.50691999999999,30.01123],"type":"Point"}
}