{
  "type": "Feature",
  "properties": {
    "gn:admin1_code":"6.0",
    "gn:admin2_code":"2.0",
    "gn:asciiname":"Boquilla Tendida",
    "gn:country_code":"MX",
    "gn:dem":1063,
    "gn:feature_class":"P",
    "gn:feature_code":"PPL",
    "gn:name":"Boquilla Tendida",
    "gn:population":0,
    "gn:timezone":"America/Chihuahua",
    "iso:country":"MX",
    "wof:name":"Boquilla Tendida",
    "wof:placetype":"locality"
},
  "geometry": {"coordinates":[-105.48333,28.76667],"type":"Point"}
}