{
  "type": "Feature",
  "properties": {
    "gn:admin1_code":"21",
    "gn:admin2_code":"54.0",
    "gn:asciiname":"Tezohuatepec (Tezotepec)",
    "gn:country_code":"MX",
    "gn:dem":2103,
    "gn:feature_class":"P",
    "gn:feature_code":"PPL",
    "gn:name":"Tezohuatepec (Tezotepec)",
    "gn:population":510,
    "gn:timezone":"America/Mexico_City",
    "iso:country":"MX",
    "wof:name":"Tezohuatepec (Tezotepec)",
    "wof:placetype":"locality",
    "wof:population":510
},
  "geometry": {"coordinates":[-97.39917,19.80972],"type":"Point"}
}