{
  "type": "Feature",
  "properties": {
    "gn:admin1_code":"26",
    "gn:admin2_code":"49.0",
    "gn:asciiname":"Los Chinos",
    "gn:country_code":"MX",
    "gn:dem":311,
    "gn:feature_class":"P",
    "gn:feature_code":"PPL",
    "gn:name":"Los Chinos",
    "gn:population":0,
    "gn:timezone":"America/Hermosillo",
    "iso:country":"MX",
    "name:spa_x_preferred":[
        "Los Chinos"
    ],
    "wof:name":"Los Chinos",
    "wof:placetype":"locality"
},
  "geometry": {"coordinates":[-109.13449,27.52178],"type":"Point"}
}