{
  "type": "Feature",
  "properties": {
    "gn:admin1_code":"6",
    "gn:admin2_code":"27.0",
    "gn:asciiname":"Penasco Blanco",
    "gn:country_code":"MX",
    "gn:dem":2223,
    "gn:feature_class":"P",
    "gn:feature_code":"PPL",
    "gn:name":"Pe\u00f1asco Blanco",
    "gn:population":22,
    "gn:timezone":"America/Chihuahua",
    "iso:country":"MX",
    "name:spa_x_preferred":[
        "Pe\u00f1asco Blanco"
    ],
    "name:und_x_variant":[
        "Pe\u00f1ascos Blancos"
    ],
    "wof:name":"Penasco Blanco",
    "wof:placetype":"locality",
    "wof:population":22
},
  "geometry": {"coordinates":[-107.06556999999999,27.38241],"type":"Point"}
}