{
  "type": "Feature",
  "properties": {
    "gn:admin1_code":"15",
    "gn:admin2_code":"123.0",
    "gn:asciiname":"El Campanario",
    "gn:country_code":"MX",
    "gn:dem":1020,
    "gn:feature_class":"P",
    "gn:feature_code":"PPL",
    "gn:name":"El Campanario",
    "gn:population":533,
    "gn:timezone":"America/Mexico_City",
    "iso:country":"MX",
    "wof:name":"El Campanario",
    "wof:placetype":"locality",
    "wof:population":533
},
  "geometry": {"coordinates":[-100.41625999999999,19.03162],"type":"Point"}
}