{
  "type": "Feature",
  "properties": {
    "gn:admin1_code":"20",
    "gn:admin2_code":"217",
    "gn:asciiname":"Cerro de Jarrito",
    "gn:country_code":"MX",
    "gn:dem":1855,
    "gn:feature_class":"P",
    "gn:feature_code":"PPL",
    "gn:name":"Cerro de Jarrito",
    "gn:population":38,
    "gn:timezone":"America/Mexico_City",
    "iso:country":"MX",
    "wof:name":"Cerro de Jarrito",
    "wof:placetype":"locality",
    "wof:population":38
},
  "geometry": {"coordinates":[-97.11972,17.08111],"type":"Point"}
}