{
  "type": "Feature",
  "properties": {
    "gn:admin1_code":"2.0",
    "gn:admin2_code":"2.0",
    "gn:asciiname":"Nayarit",
    "gn:country_code":"MX",
    "gn:dem":15,
    "gn:feature_class":"P",
    "gn:feature_code":"PPL",
    "gn:name":"Nayarit",
    "gn:population":0,
    "gn:timezone":"America/Tijuana",
    "iso:country":"MX",
    "name:rus_x_preferred":[
        "\u041d\u0430\u0439\u044f\u0440\u0438\u0442"
    ],
    "name:und_x_variant":[
        "Ejido Nayarit",
        "Nayarit",
        "Llamada"
    ],
    "wof:name":"Nayarit",
    "wof:placetype":"locality"
},
  "geometry": {"coordinates":[-115.24632,32.31388],"type":"Point"}
}