{
  "type": "Feature",
  "properties": {
    "gn:admin1_code":"5",
    "gn:admin2_code":"102",
    "gn:asciiname":"Piscicola Villa las Hortencias",
    "gn:country_code":"MX",
    "gn:dem":398,
    "gn:feature_class":"P",
    "gn:feature_code":"PPL",
    "gn:name":"Pisc\u00edcola Villa las Hortencias",
    "gn:population":11,
    "gn:timezone":"America/Mexico_City",
    "iso:country":"MX",
    "name:und_x_variant":[
        "Pisc\u00edcola Villa las Hortencias"
    ],
    "wof:name":"Piscicola Villa las Hortencias",
    "wof:placetype":"locality",
    "wof:population":11
},
  "geometry": {"coordinates":[-92.18083,14.97222],"type":"Point"}
}