{
  "type": "Feature",
  "properties": {
    "gn:admin1_code":"32",
    "gn:admin2_code":"45.0",
    "gn:asciiname":"Hacienda de los Davila",
    "gn:country_code":"MX",
    "gn:dem":1813,
    "gn:feature_class":"P",
    "gn:feature_code":"PPL",
    "gn:name":"Hacienda de los D\u00e1vila",
    "gn:population":0,
    "gn:timezone":"America/Mexico_City",
    "iso:country":"MX",
    "name:spa_x_preferred":[
        "Hacienda de los D\u00e1vila"
    ],
    "wof:name":"Hacienda de los Davila",
    "wof:placetype":"locality"
},
  "geometry": {"coordinates":[-103.26425999999999,21.62759],"type":"Point"}
}