{
  "type": "Feature",
  "properties": {
    "gn:admin1_code":"19",
    "gn:admin2_code":"16.0",
    "gn:asciiname":"La Morita (La Mora)",
    "gn:country_code":"MX",
    "gn:dem":344,
    "gn:feature_class":"P",
    "gn:feature_code":"PPL",
    "gn:name":"La Morita (La Mora)",
    "gn:population":24,
    "gn:timezone":"America/Monterrey",
    "iso:country":"MX",
    "wof:name":"La Morita (La Mora)",
    "wof:placetype":"locality",
    "wof:population":24
},
  "geometry": {"coordinates":[-99.91571999999999,25.82564],"type":"Point"}
}