{
  "type": "Feature",
  "properties": {
    "gn:admin1_code":"12",
    "gn:admin2_code":"79",
    "gn:asciiname":"Zacatepec",
    "gn:country_code":"MX",
    "gn:dem":1199,
    "gn:feature_class":"P",
    "gn:feature_code":"PPL",
    "gn:name":"Zacatepec",
    "gn:population":23,
    "gn:timezone":"America/Mexico_City",
    "iso:country":"MX",
    "wof:name":"Zacatepec",
    "wof:placetype":"locality",
    "wof:population":23
},
  "geometry": {"coordinates":[-99.03836,17.42127],"type":"Point"}
}