{
  "type": "Feature",
  "properties": {
    "gn:admin1_code":"20",
    "gn:admin2_code":"117.0",
    "gn:asciiname":"Llano de Sapo",
    "gn:country_code":"MX",
    "gn:dem":1219,
    "gn:feature_class":"P",
    "gn:feature_code":"PPL",
    "gn:name":"Llano de Sapo",
    "gn:population":79,
    "gn:timezone":"America/Mexico_City",
    "iso:country":"MX",
    "wof:name":"Llano de Sapo",
    "wof:placetype":"locality",
    "wof:population":79
},
  "geometry": {"coordinates":[-96.70305999999999,15.97444],"type":"Point"}
}