{
  "type": "Feature",
  "properties": {
    "gn:admin1_code":"31",
    "gn:admin2_code":"58.0",
    "gn:asciiname":"Sak Akal",
    "gn:country_code":"MX",
    "gn:dem":40,
    "gn:feature_class":"P",
    "gn:feature_code":"PPL",
    "gn:name":"Sak Akal",
    "gn:population":0,
    "gn:timezone":"America/Merida",
    "iso:country":"MX",
    "wof:name":"Sak Akal",
    "wof:placetype":"locality"
},
  "geometry": {"coordinates":[-88.96666999999999,20.08333],"type":"Point"}
}