{
  "type": "Feature",
  "properties": {
    "gn:admin1_code":"28",
    "gn:admin2_code":"32.0",
    "gn:asciiname":"Nuevo San Francisco",
    "gn:country_code":"MX",
    "gn:dem":99,
    "gn:feature_class":"P",
    "gn:feature_code":"PPL",
    "gn:name":"Nuevo San Francisco",
    "gn:population":8,
    "gn:timezone":"America/Matamoros",
    "iso:country":"MX",
    "wof:name":"Nuevo San Francisco",
    "wof:placetype":"locality",
    "wof:population":8
},
  "geometry": {"coordinates":[-98.4725,25.69194],"type":"Point"}
}