{
  "type": "Feature",
  "properties": {
    "gn:admin1_code":"21",
    "gn:admin2_code":"2.0",
    "gn:asciiname":"Tres Marias (Corralejo)",
    "gn:country_code":"MX",
    "gn:dem":83,
    "gn:feature_class":"P",
    "gn:feature_code":"PPL",
    "gn:name":"Tres Mar\u00edas (Corralejo)",
    "gn:population":8,
    "gn:timezone":"America/Mexico_City",
    "iso:country":"MX",
    "name:und_x_variant":[
        "Tres Mar\u00edas (Corralejo)"
    ],
    "wof:name":"Tres Marias (Corralejo)",
    "wof:placetype":"locality",
    "wof:population":8
},
  "geometry": {"coordinates":[-97.17744999999999,20.11924],"type":"Point"}
}