{
  "type": "Feature",
  "properties": {
    "gn:admin1_code":"4",
    "gn:admin2_code":"11.0",
    "gn:asciiname":"El Encanto 2",
    "gn:country_code":"MX",
    "gn:dem":82,
    "gn:feature_class":"P",
    "gn:feature_code":"PPL",
    "gn:name":"El Encanto 2",
    "gn:population":95,
    "gn:timezone":"America/Merida",
    "iso:country":"MX",
    "wof:name":"El Encanto 2",
    "wof:placetype":"locality",
    "wof:population":95
},
  "geometry": {"coordinates":[-90.61472000000001,18.39028],"type":"Point"}
}