{
  "type": "Feature",
  "properties": {
    "gn:admin1_code":"22",
    "gn:admin2_code":"2.0",
    "gn:asciiname":"Barranca del Platano",
    "gn:country_code":"MX",
    "gn:dem":1474,
    "gn:feature_class":"P",
    "gn:feature_code":"PPL",
    "gn:name":"Barranca del Pl\u00e1tano",
    "gn:population":90,
    "gn:timezone":"America/Mexico_City",
    "iso:country":"MX",
    "wof:name":"Barranca del Platano",
    "wof:placetype":"locality",
    "wof:population":90
},
  "geometry": {"coordinates":[-99.60472,21.08667],"type":"Point"}
}