{
  "type": "Feature",
  "properties": {
    "gn:admin1_code":"25",
    "gn:admin2_code":"14.0",
    "gn:asciiname":"El Vainillo",
    "gn:country_code":"MX",
    "gn:dem":86,
    "gn:feature_class":"P",
    "gn:feature_code":"PPL",
    "gn:name":"El Vainillo",
    "gn:population":9,
    "gn:timezone":"America/Mazatlan",
    "iso:country":"MX",
    "wof:name":"El Vainillo",
    "wof:placetype":"locality",
    "wof:population":9
},
  "geometry": {"coordinates":[-105.91305,23.17113],"type":"Point"}
}