{
  "type": "Feature",
  "properties": {
    "gn:admin1_code":"30",
    "gn:admin2_code":"17.0",
    "gn:asciiname":"Tigrillos",
    "gn:country_code":"MX",
    "gn:dem":487,
    "gn:feature_class":"P",
    "gn:feature_code":"PPL",
    "gn:name":"Tigrillos",
    "gn:population":0,
    "gn:timezone":"America/Mexico_City",
    "iso:country":"MX",
    "name:spa_x_preferred":[
        "Tigrillos"
    ],
    "wof:name":"Tigrillos",
    "wof:placetype":"locality"
},
  "geometry": {"coordinates":[-96.68792999999999,19.37005],"type":"Point"}
}