{
  "type": "Feature",
  "properties": {
    "gn:admin1_code":"11",
    "gn:admin2_code":"20.0",
    "gn:asciiname":"Mesa de la Virgen",
    "gn:country_code":"MX",
    "gn:dem":2224,
    "gn:feature_class":"P",
    "gn:feature_code":"PPL",
    "gn:name":"Mesa de la Virgen",
    "gn:population":6,
    "gn:timezone":"America/Mexico_City",
    "iso:country":"MX",
    "wof:name":"Mesa de la Virgen",
    "wof:placetype":"locality",
    "wof:population":6
},
  "geometry": {"coordinates":[-101.66278,21.24361],"type":"Point"}
}