{
  "type": "Feature",
  "properties": {
    "gn:admin1_code":"19",
    "gn:admin2_code":"16.0",
    "gn:asciiname":"El Domino (Oscar Flores)",
    "gn:country_code":"MX",
    "gn:dem":355,
    "gn:feature_class":"P",
    "gn:feature_code":"PPL",
    "gn:name":"El Domin\u00f3 (Oscar Flores)",
    "gn:population":5,
    "gn:timezone":"America/Monterrey",
    "iso:country":"MX",
    "name:und_x_variant":[
        "El Domin\u00f3 (Oscar Flores)"
    ],
    "wof:name":"El Domino (Oscar Flores)",
    "wof:placetype":"locality",
    "wof:population":5
},
  "geometry": {"coordinates":[-99.96697,25.85395],"type":"Point"}
}