{
  "type": "Feature",
  "properties": {
    "gn:admin1_code":"6.0",
    "gn:admin2_code":"9.0",
    "gn:asciiname":"Rohuyna",
    "gn:country_code":"MX",
    "gn:dem":2243,
    "gn:feature_class":"P",
    "gn:feature_code":"PPL",
    "gn:name":"Rohuyna",
    "gn:population":0,
    "gn:timezone":"America/Chihuahua",
    "iso:country":"MX",
    "name:spa_x_preferred":[
        "Rohuyna"
    ],
    "wof:name":"Rohuyna",
    "wof:placetype":"locality"
},
  "geometry": {"coordinates":[-107.50028,27.72701],"type":"Point"}
}