{
  "type": "Feature",
  "properties": {
    "gn:admin1_code":"28.0",
    "gn:admin2_code":"12.0",
    "gn:asciiname":"Pedro Jose Mendez",
    "gn:country_code":"MX",
    "gn:dem":87,
    "gn:feature_class":"P",
    "gn:feature_code":"PPL",
    "gn:name":"Pedro Jos\u00e9 M\u00e9ndez",
    "gn:population":0,
    "gn:timezone":"America/Monterrey",
    "iso:country":"MX",
    "name:spa_x_preferred":[
        "Pedro Jos\u00e9 M\u00e9ndez"
    ],
    "name:spa_x_variant":[
        "La Piedra"
    ],
    "wof:name":"Pedro Jose Mendez",
    "wof:placetype":"locality"
},
  "geometry": {"coordinates":[-98.84227,22.88776],"type":"Point"}
}