{
  "type": "Feature",
  "properties": {
    "gn:admin1_code":"11.0",
    "gn:admin2_code":"17.0",
    "gn:asciiname":"San Jose de la Laguna",
    "gn:country_code":"MX",
    "gn:dem":1693,
    "gn:feature_class":"P",
    "gn:feature_code":"PPL",
    "gn:name":"San Jos\u00e9 de la Laguna",
    "gn:population":0,
    "gn:timezone":"America/Mexico_City",
    "iso:country":"MX",
    "name:spa_x_preferred":[
        "San Jos\u00e9 de la Laguna"
    ],
    "wof:name":"San Jose de la Laguna",
    "wof:placetype":"locality"
},
  "geometry": {"coordinates":[-101.49290000000001,20.52494],"type":"Point"}
}