{
  "type": "Feature",
  "properties": {
    "gn:admin1_code":"26",
    "gn:admin2_code":"71",
    "gn:asciiname":"Vargas",
    "gn:country_code":"MX",
    "gn:dem":15,
    "gn:feature_class":"P",
    "gn:feature_code":"PPL",
    "gn:name":"Vargas",
    "gn:population":23,
    "gn:timezone":"America/Hermosillo",
    "iso:country":"MX",
    "wof:name":"Vargas",
    "wof:placetype":"locality",
    "wof:population":23
},
  "geometry": {"coordinates":[-109.8925,27.12861],"type":"Point"}
}