{
  "type": "Feature",
  "properties": {
    "gn:admin1_code":"25",
    "gn:admin2_code":"1.0",
    "gn:asciiname":"Campo Cleyton",
    "gn:country_code":"MX",
    "gn:dem":17,
    "gn:feature_class":"P",
    "gn:feature_code":"PPL",
    "gn:name":"Campo Cleyton",
    "gn:population":76,
    "gn:timezone":"America/Mazatlan",
    "iso:country":"MX",
    "wof:name":"Campo Cleyton",
    "wof:placetype":"locality",
    "wof:population":76
},
  "geometry": {"coordinates":[-108.90636000000001,25.79007],"type":"Point"}
}