{
  "type": "Feature",
  "properties": {
    "gn:admin1_code":"6",
    "gn:admin2_code":"45.0",
    "gn:asciiname":"El Torreon",
    "gn:country_code":"MX",
    "gn:dem":1128,
    "gn:feature_class":"P",
    "gn:feature_code":"PPL",
    "gn:name":"El Torre\u00f3n",
    "gn:population":0,
    "gn:timezone":"America/Chihuahua",
    "iso:country":"MX",
    "name:und_x_variant":[
        "Torre\u00f3n",
        "El Torre\u00f3n"
    ],
    "wof:name":"El Torreon",
    "wof:placetype":"locality"
},
  "geometry": {"coordinates":[-105.4139,28.32612],"type":"Point"}
}