{
  "type": "Feature",
  "properties": {
    "gn:admin1_code":"6",
    "gn:admin2_code":"49.0",
    "gn:asciiname":"El Tapeste",
    "gn:country_code":"MX",
    "gn:dem":1754,
    "gn:feature_class":"P",
    "gn:feature_code":"PPL",
    "gn:name":"El Tapeste",
    "gn:population":0,
    "gn:timezone":"America/Chihuahua",
    "iso:country":"MX",
    "wof:name":"El Tapeste",
    "wof:placetype":"locality"
},
  "geometry": {"coordinates":[-106.72472999999999,27.35226],"type":"Point"}
}