{
  "type": "Feature",
  "properties": {
    "gn:admin1_code":"14",
    "gn:admin2_code":"120",
    "gn:asciiname":"San Jose de las Rosas",
    "gn:country_code":"MX",
    "gn:dem":1619,
    "gn:feature_class":"P",
    "gn:feature_code":"PPL",
    "gn:name":"San Jos\u00e9 de las Rosas",
    "gn:population":14,
    "gn:timezone":"America/Mexico_City",
    "iso:country":"MX",
    "name:und_x_variant":[
        "San Jos\u00e9 de las Rosas"
    ],
    "wof:name":"San Jose de las Rosas",
    "wof:placetype":"locality",
    "wof:population":14
},
  "geometry": {"coordinates":[-103.52943999999999,20.73139],"type":"Point"}
}