{
  "type": "Feature",
  "properties": {
    "gn:admin1_code":"5",
    "gn:admin2_code":"20.0",
    "gn:asciiname":"Monte Bonito",
    "gn:country_code":"MX",
    "gn:dem":715,
    "gn:feature_class":"P",
    "gn:feature_code":"PPL",
    "gn:name":"Monte Bonito",
    "gn:population":8,
    "gn:timezone":"America/Mexico_City",
    "iso:country":"MX",
    "wof:name":"Monte Bonito",
    "wof:placetype":"locality",
    "wof:population":8
},
  "geometry": {"coordinates":[-93.00861,15.93528],"type":"Point"}
}