{
  "type": "Feature",
  "properties": {
    "gn:admin1_code":"30.0",
    "gn:admin2_code":"124.0",
    "gn:asciiname":"Volador",
    "gn:country_code":"MX",
    "gn:dem":150,
    "gn:feature_class":"P",
    "gn:feature_code":"PPL",
    "gn:name":"Volador",
    "gn:population":0,
    "gn:timezone":"America/Mexico_City",
    "iso:country":"MX",
    "name:spa_x_preferred":[
        "Volador"
    ],
    "wof:name":"Volador",
    "wof:placetype":"locality"
},
  "geometry": {"coordinates":[-97.38007,20.59503],"type":"Point"}
}