{
  "type": "Feature",
  "properties": {
    "gn:admin1_code":"28",
    "gn:admin2_code":"35.0",
    "gn:asciiname":"Carvajal",
    "gn:country_code":"MX",
    "gn:dem":6,
    "gn:feature_class":"P",
    "gn:feature_code":"PPL",
    "gn:name":"Carvajal",
    "gn:population":0,
    "gn:timezone":"America/Monterrey",
    "iso:country":"MX",
    "name:cat_x_preferred":[
        "Carvajal"
    ],
    "name:ceb_x_preferred":[
        "Carvajal"
    ],
    "name:deu_x_preferred":[
        "Carvajal"
    ],
    "name:fra_x_preferred":[
        "Carvajal"
    ],
    "name:heb_x_preferred":[
        "\u05e7\u05e8\u05d5\u05d5\u05d7\u05dc"
    ],
    "name:ita_x_preferred":[
        "Carvajal"
    ],
    "name:jpn_x_preferred":[
        "\u30ab\u30eb\u30d0\u30cf\u30eb"
    ],
    "name:pol_x_preferred":[
        "Carvajal"
    ],
    "name:rus_x_preferred":[
        "\u041a\u0430\u0440\u0432\u0430\u0445\u0430\u043b\u044c"
    ],
    "name:spa_x_preferred":[
        "Carvajal"
    ],
    "name:swe_x_preferred":[
        "Carvajal"
    ],
    "name:ukr_x_preferred":[
        "\u041a\u0430\u0440\u0432\u0430\u0445\u0430\u043b\u044c"
    ],
    "name:und_x_variant":[
        "Carbajal"
    ],
    "wof:name":"Carvajal",
    "wof:placetype":"locality"
},
  "geometry": {"coordinates":[-97.73978,24.51311],"type":"Point"}
}