{
  "type": "Feature",
  "properties": {
    "gn:admin1_code":"6.0",
    "gn:admin2_code":"19.0",
    "gn:asciiname":"Rancho el Salitre",
    "gn:country_code":"MX",
    "gn:dem":1468,
    "gn:feature_class":"P",
    "gn:feature_code":"PPL",
    "gn:name":"Rancho el Salitre",
    "gn:population":64,
    "gn:timezone":"America/Chihuahua",
    "iso:country":"MX",
    "wof:name":"Rancho el Salitre",
    "wof:placetype":"locality",
    "wof:population":64
},
  "geometry": {"coordinates":[-106.20062,28.13934],"type":"Point"}
}