{
  "type": "Feature",
  "properties": {
    "gn:admin1_code":"6.0",
    "gn:admin2_code":"66.0",
    "gn:asciiname":"Venustiano Carranza",
    "gn:country_code":"MX",
    "gn:dem":486,
    "gn:feature_class":"P",
    "gn:feature_code":"PPL",
    "gn:name":"Venustiano Carranza",
    "gn:population":0,
    "gn:timezone":"America/Chihuahua",
    "iso:country":"MX",
    "name:spa_x_preferred":[
        "Venustiano Carranza"
    ],
    "wof:name":"Venustiano Carranza",
    "wof:placetype":"locality"
},
  "geometry": {"coordinates":[-108.80889000000001,27.88306],"type":"Point"}
}