{
  "type": "Feature",
  "properties": {
    "gn:admin1_code":"14.0",
    "gn:admin2_code":"17.0",
    "gn:asciiname":"La Ferreria",
    "gn:country_code":"MX",
    "gn:dem":1535,
    "gn:feature_class":"P",
    "gn:feature_code":"PPL",
    "gn:name":"La Ferrer\u00eda",
    "gn:population":0,
    "gn:timezone":"America/Mexico_City",
    "iso:country":"MX",
    "name:spa_x_preferred":[
        "La Ferrer\u00eda"
    ],
    "wof:name":"La Ferreria",
    "wof:placetype":"locality"
},
  "geometry": {"coordinates":[-104.45560999999999,19.96817],"type":"Point"}
}