{
  "type": "Feature",
  "properties": {
    "gn:admin1_code":"14.0",
    "gn:admin2_code":"27.0",
    "gn:asciiname":"El Pedregal",
    "gn:country_code":"MX",
    "gn:dem":1376,
    "gn:feature_class":"P",
    "gn:feature_code":"PPL",
    "gn:name":"El Pedregal",
    "gn:population":0,
    "gn:timezone":"America/Mexico_City",
    "iso:country":"MX",
    "name:spa_x_preferred":[
        "El Pedregal"
    ],
    "wof:name":"El Pedregal",
    "wof:placetype":"locality"
},
  "geometry": {"coordinates":[-104.08382,19.49821],"type":"Point"}
}