{
  "type": "Feature",
  "properties": {
    "gn:admin1_code":"32",
    "gn:admin2_code":"40.0",
    "gn:asciiname":"Santa Eduviges",
    "gn:country_code":"MX",
    "gn:dem":2276,
    "gn:feature_class":"P",
    "gn:feature_code":"PPL",
    "gn:name":"Santa Eduviges",
    "gn:population":0,
    "gn:timezone":"America/Mexico_City",
    "iso:country":"MX",
    "name:spa_x_preferred":[
        "Santa Eduviges"
    ],
    "wof:name":"Santa Eduviges",
    "wof:placetype":"locality"
},
  "geometry": {"coordinates":[-103.20815,23.46806],"type":"Point"}
}