{
  "type": "Feature",
  "properties": {
    "gn:admin1_code":"11",
    "gn:admin2_code":"24.0",
    "gn:asciiname":"Congregacion de Panales",
    "gn:country_code":"MX",
    "gn:dem":1721,
    "gn:feature_class":"P",
    "gn:feature_code":"PPL",
    "gn:name":"Congregaci\u00f3n de Panales",
    "gn:population":317,
    "gn:timezone":"America/Mexico_City",
    "iso:country":"MX",
    "name:und_x_variant":[
        "Congregaci\u00f3n de Panales"
    ],
    "wof:name":"Congregacion de Panales",
    "wof:placetype":"locality",
    "wof:population":317
},
  "geometry": {"coordinates":[-101.33694,20.56167],"type":"Point"}
}