{
  "type": "Feature",
  "properties": {
    "gn:admin1_code":"14",
    "gn:admin2_code":"101",
    "gn:asciiname":"Rancho el Portal",
    "gn:country_code":"MX",
    "gn:dem":1539,
    "gn:feature_class":"P",
    "gn:feature_code":"PPL",
    "gn:name":"Rancho el Portal",
    "gn:population":11,
    "gn:timezone":"America/Mexico_City",
    "iso:country":"MX",
    "wof:name":"Rancho el Portal",
    "wof:placetype":"locality",
    "wof:population":11
},
  "geometry": {"coordinates":[-103.18889,20.54333],"type":"Point"}
}