{
  "type": "Feature",
  "properties": {
    "gn:admin1_code":"12",
    "gn:admin2_code":"10.0",
    "gn:asciiname":"Ahuacatitlan",
    "gn:country_code":"MX",
    "gn:dem":1956,
    "gn:feature_class":"P",
    "gn:feature_code":"PPL",
    "gn:name":"Ahuacatitl\u00e1n",
    "gn:population":374,
    "gn:timezone":"America/Mexico_City",
    "iso:country":"MX",
    "name:und_x_variant":[
        "Ahuacatitl\u00e1n"
    ],
    "wof:name":"Ahuacatitlan",
    "wof:placetype":"locality",
    "wof:population":374
},
  "geometry": {"coordinates":[-98.81690999999999,17.4189],"type":"Point"}
}