{
  "type": "Feature",
  "properties": {
    "gn:admin1_code":"12",
    "gn:admin2_code":"43.0",
    "gn:asciiname":"Llano de la Rana",
    "gn:country_code":"MX",
    "gn:dem":1020,
    "gn:feature_class":"P",
    "gn:feature_code":"PPL",
    "gn:name":"Llano de la Rana",
    "gn:population":0,
    "gn:timezone":"America/Mexico_City",
    "iso:country":"MX",
    "name:spa_x_preferred":[
        "Llano de la Rana"
    ],
    "wof:name":"Llano de la Rana",
    "wof:placetype":"locality"
},
  "geometry": {"coordinates":[-98.32058000000001,17.15612999999999],"type":"Point"}
}