{
  "type": "Feature",
  "properties": {
    "gn:admin1_code":"32",
    "gn:admin2_code":"34",
    "gn:asciiname":"La Laguna",
    "gn:country_code":"MX",
    "gn:dem":1923,
    "gn:feature_class":"P",
    "gn:feature_code":"PPL",
    "gn:name":"La Laguna",
    "gn:population":11,
    "gn:timezone":"America/Mexico_City",
    "iso:country":"MX",
    "wof:name":"La Laguna",
    "wof:placetype":"locality",
    "wof:population":11
},
  "geometry": {"coordinates":[-102.73611,21.4025],"type":"Point"}
}