{
  "type": "Feature",
  "properties": {
    "gn:admin1_code":"16",
    "gn:admin2_code":"88.0",
    "gn:asciiname":"San Jose de la Trinidad",
    "gn:country_code":"MX",
    "gn:dem":1874,
    "gn:feature_class":"P",
    "gn:feature_code":"PPL",
    "gn:name":"San Jos\u00e9 de la Trinidad",
    "gn:population":508,
    "gn:timezone":"America/Mexico_City",
    "iso:country":"MX",
    "wof:name":"San Jose de la Trinidad",
    "wof:placetype":"locality",
    "wof:population":508
},
  "geometry": {"coordinates":[-101.15806000000001,19.7725],"type":"Point"}
}