{
  "type": "Feature",
  "properties": {
    "gn:admin1_code":"7.0",
    "gn:admin2_code":"28.0",
    "gn:asciiname":"Cuco",
    "gn:country_code":"MX",
    "gn:dem":353,
    "gn:feature_class":"P",
    "gn:feature_code":"PPL",
    "gn:name":"Cuco",
    "gn:population":0,
    "gn:timezone":"America/Monterrey",
    "iso:country":"MX",
    "name:spa_x_preferred":[
        "Cuco"
    ],
    "wof:name":"Cuco",
    "wof:placetype":"locality"
},
  "geometry": {"coordinates":[-101.18544,27.89517],"type":"Point"}
}