{
  "type": "Feature",
  "properties": {
    "gn:admin1_code":"6",
    "gn:admin2_code":"3.0",
    "gn:asciiname":"Santa Teresa",
    "gn:country_code":"MX",
    "gn:dem":1381,
    "gn:feature_class":"P",
    "gn:feature_code":"PPL",
    "gn:name":"Santa Teresa",
    "gn:population":0,
    "gn:timezone":"America/Chihuahua",
    "iso:country":"MX",
    "name:spa_x_preferred":[
        "Santa Teresa"
    ],
    "wof:name":"Santa Teresa",
    "wof:placetype":"locality"
},
  "geometry": {"coordinates":[-105.137,27.28451],"type":"Point"}
}