{
  "type": "Feature",
  "properties": {
    "gn:admin1_code":"26",
    "gn:admin2_code":"45.0",
    "gn:asciiname":"Nochebuena",
    "gn:country_code":"MX",
    "gn:dem":752,
    "gn:feature_class":"P",
    "gn:feature_code":"PPL",
    "gn:name":"Nochebuena",
    "gn:population":0,
    "gn:timezone":"America/Hermosillo",
    "iso:country":"MX",
    "name:und_x_variant":[
        "Noche Buena"
    ],
    "wof:name":"Nochebuena",
    "wof:placetype":"locality"
},
  "geometry": {"coordinates":[-111.12978,29.91462000000001],"type":"Point"}
}