{
  "type": "Feature",
  "properties": {
    "gn:admin1_code":"12.0",
    "gn:admin2_code":"29.0",
    "gn:asciiname":"Los Montes",
    "gn:country_code":"MX",
    "gn:dem":2045,
    "gn:feature_class":"P",
    "gn:feature_code":"PPL",
    "gn:name":"Los Montes",
    "gn:population":0,
    "gn:timezone":"America/Mexico_City",
    "iso:country":"MX",
    "name:spa_x_preferred":[
        "Los Montes"
    ],
    "wof:name":"Los Montes",
    "wof:placetype":"locality"
},
  "geometry": {"coordinates":[-99.88433000000001,17.52882],"type":"Point"}
}