{
  "type": "Feature",
  "properties": {
    "gn:admin1_code":"12.0",
    "gn:admin2_code":"29.0",
    "gn:asciiname":"Los Montes",
    "gn:country_code":"MX",
    "gn:dem":2045,
    "gn:feature_class":"P",
    "gn:feature_code":"PPL",
    "gn:name":"Los Montes",
    "gn:population":0,
    "gn:timezone":"America/Mexico_City",
    "iso:country":"MX",
    "name:cat_x_preferred":[
        "Los Montes"
    ],
    "name:deu_x_preferred":[
        "Los Montes"
    ],
    "name:eus_x_preferred":[
        "Los Montes"
    ],
    "name:fra_x_preferred":[
        "Los Montes"
    ],
    "name:ita_x_preferred":[
        "Los Montes"
    ],
    "name:kaz_x_preferred":[
        "\u041b\u043e\u0441-\u041c\u043e\u043d\u0442\u0435\u0441"
    ],
    "name:rus_x_preferred":[
        "\u041b\u043e\u0441-\u041c\u043e\u043d\u0442\u0435\u0441"
    ],
    "name:spa_x_preferred":[
        "Los Montes"
    ],
    "wof:name":"Los Montes",
    "wof:placetype":"locality"
},
  "geometry": {"coordinates":[-99.88433000000001,17.52882],"type":"Point"}
}