{
  "type": "Feature",
  "properties": {
    "gn:admin1_code":"25",
    "gn:admin2_code":"1",
    "gn:asciiname":"San Luis",
    "gn:country_code":"MX",
    "gn:dem":19,
    "gn:feature_class":"P",
    "gn:feature_code":"PPL",
    "gn:name":"San Luis",
    "gn:population":22,
    "gn:timezone":"America/Mazatlan",
    "iso:country":"MX",
    "wof:name":"San Luis",
    "wof:placetype":"locality",
    "wof:population":22
},
  "geometry": {"coordinates":[-109.11001,25.93332],"type":"Point"}
}