{
  "type": "Feature",
  "properties": {
    "gn:admin1_code":"11",
    "gn:admin2_code":"14.0",
    "gn:asciiname":"Penuelas",
    "gn:country_code":"MX",
    "gn:dem":1916,
    "gn:feature_class":"P",
    "gn:feature_code":"PPL",
    "gn:name":"Pe\u00f1uelas",
    "gn:population":0,
    "gn:timezone":"America/Mexico_City",
    "iso:country":"MX",
    "name:spa_x_preferred":[
        "Pe\u00f1uelas"
    ],
    "name:spa_x_variant":[
        "Pe\u00f1uelitas"
    ],
    "wof:name":"Penuelas",
    "wof:placetype":"locality"
},
  "geometry": {"coordinates":[-100.87869000000001,21.10776],"type":"Point"}
}