{
  "type": "Feature",
  "properties": {
    "gn:admin1_code":"19",
    "gn:admin2_code":"13.0",
    "gn:asciiname":"La Fresadita",
    "gn:cc2":"MX",
    "gn:country_code":"MX",
    "gn:dem":183,
    "gn:feature_class":"P",
    "gn:feature_code":"PPL",
    "gn:name":"La Fresadita",
    "gn:population":2,
    "gn:timezone":"America/Monterrey",
    "iso:country":"MX",
    "name:und_x_variant":[
        "Rancho La Fresadita",
        "Frazadita",
        "La Frazadita"
    ],
    "wof:name":"La Fresadita",
    "wof:placetype":"locality",
    "wof:population":2
},
  "geometry": {"coordinates":[-99.41779,25.53285],"type":"Point"}
}