{
  "type": "Feature",
  "properties": {
    "gn:admin1_code":"14",
    "gn:admin2_code":"112",
    "gn:asciiname":"El Algodon",
    "gn:country_code":"MX",
    "gn:dem":1375,
    "gn:feature_class":"P",
    "gn:feature_code":"PPL",
    "gn:name":"El Algod\u00f3n",
    "gn:population":16,
    "gn:timezone":"America/Mexico_City",
    "iso:country":"MX",
    "name:und_x_variant":[
        "El Algod\u00f3n"
    ],
    "wof:name":"El Algodon",
    "wof:placetype":"locality",
    "wof:population":16
},
  "geometry": {"coordinates":[-102.96639,19.69],"type":"Point"}
}