{
  "type": "Feature",
  "properties": {
    "gn:admin1_code":"27",
    "gn:admin2_code":"8.0",
    "gn:asciiname":"Piche Tio Mayo",
    "gn:country_code":"MX",
    "gn:dem":4,
    "gn:feature_class":"P",
    "gn:feature_code":"PPL",
    "gn:name":"Piche T\u00edo Mayo",
    "gn:population":0,
    "gn:timezone":"America/Mexico_City",
    "iso:country":"MX",
    "wof:name":"Piche Tio Mayo",
    "wof:placetype":"locality"
},
  "geometry": {"coordinates":[-93.96666999999999,17.85],"type":"Point"}
}