{
  "type": "Feature",
  "properties": {
    "gn:admin1_code":"10.0",
    "gn:admin2_code":"19.0",
    "gn:asciiname":"El Chirimoyo",
    "gn:country_code":"MX",
    "gn:dem":1040,
    "gn:feature_class":"P",
    "gn:feature_code":"PPL",
    "gn:name":"El Chirimoyo",
    "gn:population":0,
    "gn:timezone":"America/Monterrey",
    "iso:country":"MX",
    "name:spa_x_preferred":[
        "El Chirimoyo"
    ],
    "wof:name":"El Chirimoyo",
    "wof:placetype":"locality"
},
  "geometry": {"coordinates":[-106.19571999999999,24.62639],"type":"Point"}
}