{
  "type": "Feature",
  "properties": {
    "gn:admin1_code":"5",
    "gn:admin2_code":"70.0",
    "gn:asciiname":"Aguacatales",
    "gn:country_code":"MX",
    "gn:dem":1934,
    "gn:feature_class":"P",
    "gn:feature_code":"PPL",
    "gn:name":"Aguacatales",
    "gn:population":236,
    "gn:timezone":"America/Mexico_City",
    "iso:country":"MX",
    "wof:name":"Aguacatales",
    "wof:placetype":"locality",
    "wof:population":236
},
  "geometry": {"coordinates":[-92.2709,15.41702],"type":"Point"}
}