{
  "type": "Feature",
  "properties": {
    "gn:admin1_code":"23",
    "gn:admin2_code":"2",
    "gn:asciiname":"Sahcabchen",
    "gn:country_code":"MX",
    "gn:dem":15,
    "gn:feature_class":"P",
    "gn:feature_code":"PPL",
    "gn:name":"Sahcabch\u00e9n",
    "gn:population":40,
    "gn:timezone":"America/Cancun",
    "iso:country":"MX",
    "name:und_x_variant":[
        "Sahcabch\u00e9n"
    ],
    "wof:name":"Sahcabchen",
    "wof:placetype":"locality",
    "wof:population":40
},
  "geometry": {"coordinates":[-87.93025,20.17111],"type":"Point"}
}