{
  "type": "Feature",
  "properties": {
    "gn:admin1_code":"5",
    "gn:admin2_code":"61.0",
    "gn:asciiname":"San Felipe (Fraccion Monserrat)",
    "gn:country_code":"MX",
    "gn:dem":841,
    "gn:feature_class":"P",
    "gn:feature_code":"PPL",
    "gn:name":"San Felipe (Fracci\u00f3n Monserrat)",
    "gn:population":6,
    "gn:timezone":"America/Mexico_City",
    "iso:country":"MX",
    "name:und_x_variant":[
        "San Felipe (Fracci\u00f3n Monserrat)"
    ],
    "wof:name":"San Felipe (Fraccion Monserrat)",
    "wof:placetype":"locality",
    "wof:population":6
},
  "geometry": {"coordinates":[-93.39333000000001,16.79806],"type":"Point"}
}