{
  "type": "Feature",
  "properties": {
    "gn:admin1_code":"4",
    "gn:admin2_code":"10",
    "gn:asciiname":"Los 6 Hermanos",
    "gn:country_code":"MX",
    "gn:dem":280,
    "gn:feature_class":"P",
    "gn:feature_code":"PPL",
    "gn:name":"Los 6 Hermanos",
    "gn:population":12,
    "gn:timezone":"America/Cancun",
    "iso:country":"MX",
    "wof:name":"Los 6 Hermanos",
    "wof:placetype":"locality",
    "wof:population":12
},
  "geometry": {"coordinates":[-89.38167,18.24056],"type":"Point"}
}