{
  "type": "Feature",
  "properties": {
    "gn:admin1_code":"13",
    "gn:admin2_code":"75.0",
    "gn:asciiname":"Los Pinos [Granja]",
    "gn:country_code":"MX",
    "gn:dem":2344,
    "gn:feature_class":"P",
    "gn:feature_code":"PPL",
    "gn:name":"Los Pinos [Granja]",
    "gn:population":5,
    "gn:timezone":"America/Mexico_City",
    "iso:country":"MX",
    "wof:name":"Los Pinos [Granja]",
    "wof:placetype":"locality",
    "wof:population":5
},
  "geometry": {"coordinates":[-98.90667000000001,19.94722],"type":"Point"}
}