{
  "type": "Feature",
  "properties": {
    "gn:admin1_code":"16.0",
    "gn:admin2_code":"8.0",
    "gn:asciiname":"La Cienega del Diezmo",
    "gn:country_code":"MX",
    "gn:dem":970,
    "gn:feature_class":"P",
    "gn:feature_code":"PPL",
    "gn:name":"La Ci\u00e9nega del Diezmo",
    "gn:population":0,
    "gn:timezone":"America/Mexico_City",
    "iso:country":"MX",
    "name:spa_x_preferred":[
        "La Ci\u00e9nega del Diezmo"
    ],
    "wof:name":"La Cienega del Diezmo",
    "wof:placetype":"locality"
},
  "geometry": {"coordinates":[-103.29644,18.46922],"type":"Point"}
}