{
  "type": "Feature",
  "properties": {
    "gn:admin1_code":"6.0",
    "gn:admin2_code":"35.0",
    "gn:asciiname":"Las Flores",
    "gn:country_code":"MX",
    "gn:dem":1874,
    "gn:feature_class":"P",
    "gn:feature_code":"PPL",
    "gn:name":"Las Flores",
    "gn:population":10,
    "gn:timezone":"America/Chihuahua",
    "iso:country":"MX",
    "name:spa_x_preferred":[
        "Las Flores"
    ],
    "wof:name":"Las Flores",
    "wof:placetype":"locality",
    "wof:population":10
},
  "geometry": {"coordinates":[-108.49133,30.33273],"type":"Point"}
}