{
  "type": "Feature",
  "properties": {
    "gn:admin1_code":"28.0",
    "gn:admin2_code":"35.0",
    "gn:asciiname":"Los Socios",
    "gn:country_code":"MX",
    "gn:dem":115,
    "gn:feature_class":"P",
    "gn:feature_code":"PPL",
    "gn:name":"Los Socios",
    "gn:population":0,
    "gn:timezone":"America/Monterrey",
    "iso:country":"MX",
    "name:spa_x_preferred":[
        "Los Socios"
    ],
    "wof:name":"Los Socios",
    "wof:placetype":"locality"
},
  "geometry": {"coordinates":[-98.36333999999999,24.86074],"type":"Point"}
}