{
  "type": "Feature",
  "properties": {
    "gn:admin1_code":"31",
    "gn:admin2_code":"87.0",
    "gn:asciiname":"Paklam Balam",
    "gn:country_code":"MX",
    "gn:dem":5,
    "gn:feature_class":"P",
    "gn:feature_code":"PPL",
    "gn:name":"Paklam Balam",
    "gn:population":0,
    "gn:timezone":"America/Merida",
    "iso:country":"MX",
    "name:spa_x_preferred":[
        "Paclambalam"
    ],
    "name:spa_x_variant":[
        "Paklam Balam"
    ],
    "wof:name":"Paklam Balam",
    "wof:placetype":"locality"
},
  "geometry": {"coordinates":[-90.05351,20.92927],"type":"Point"}
}