{
  "type": "Feature",
  "properties": {
    "gn:admin1_code":"11",
    "gn:admin2_code":"12.0",
    "gn:asciiname":"Colonia los Reyes Ejido de Chamacua",
    "gn:country_code":"MX",
    "gn:dem":1697,
    "gn:feature_class":"P",
    "gn:feature_code":"PPL",
    "gn:name":"Colonia los Reyes Ejido de Chamacua",
    "gn:population":71,
    "gn:timezone":"America/Mexico_City",
    "iso:country":"MX",
    "wof:name":"Colonia los Reyes Ejido de Chamacua",
    "wof:placetype":"locality",
    "wof:population":71
},
  "geometry": {"coordinates":[-101.58028,20.61917],"type":"Point"}
}