{
  "type": "Feature",
  "properties": {
    "gn:admin1_code":"6",
    "gn:admin2_code":"5.0",
    "gn:asciiname":"Rincon de Chihuahua",
    "gn:country_code":"MX",
    "gn:dem":1223,
    "gn:feature_class":"P",
    "gn:feature_code":"PPL",
    "gn:name":"Rinc\u00f3n de Chihuahua",
    "gn:population":1,
    "gn:timezone":"America/Chihuahua",
    "iso:country":"MX",
    "name:spa_x_preferred":[
        "Rinc\u00f3n de Chihuahua"
    ],
    "name:und_x_variant":[
        "Rancho Rinc\u00f3n de Chihuahua"
    ],
    "wof:name":"Rincon de Chihuahua",
    "wof:placetype":"locality",
    "wof:population":1
},
  "geometry": {"coordinates":[-107.32232999999999,30.84775],"type":"Point"}
}