{
  "type": "Feature",
  "properties": {
    "gn:admin1_code":"17",
    "gn:asciiname":"San Antonio Ometusco",
    "gn:country_code":"MX",
    "gn:dem":2496,
    "gn:feature_class":"P",
    "gn:feature_code":"PPL",
    "gn:name":"San Antonio Ometusco",
    "gn:population":0,
    "gn:timezone":"America/Mexico_City",
    "iso:country":"MX",
    "name:und_x_variant":[
        "Ometusco",
        "San Antonio Ometusco"
    ],
    "wof:name":"San Antonio Ometusco",
    "wof:placetype":"locality"
},
  "geometry": {"coordinates":[-98.62900999999999,19.77923],"type":"Point"}
}