{
  "type": "Feature",
  "properties": {
    "gn:admin1_code":"26.0",
    "gn:admin2_code":"29.0",
    "gn:asciiname":"Aranjuez",
    "gn:country_code":"MX",
    "gn:dem":10,
    "gn:feature_class":"P",
    "gn:feature_code":"PPL",
    "gn:name":"Aranjuez",
    "gn:population":0,
    "gn:timezone":"America/Hermosillo",
    "iso:country":"MX",
    "name:spa_x_preferred":[
        "Aranjuez"
    ],
    "name:und_x_variant":[
        "Hacienda Aranju\u00e9z"
    ],
    "wof:name":"Aranjuez",
    "wof:placetype":"locality"
},
  "geometry": {"coordinates":[-110.9037,27.9894],"type":"Point"}
}