{
  "type": "Feature",
  "properties": {
    "gn:admin1_code":"5",
    "gn:admin2_code":"87.0",
    "gn:asciiname":"Las Aguilas Nortenas",
    "gn:country_code":"MX",
    "gn:dem":14,
    "gn:feature_class":"P",
    "gn:feature_code":"PPL",
    "gn:name":"Las \u00c1guilas Norte\u00f1as",
    "gn:population":6,
    "gn:timezone":"America/Mexico_City",
    "iso:country":"MX",
    "name:und_x_variant":[
        "Las \u00c1guilas Norte\u00f1as"
    ],
    "wof:name":"Las Aguilas Nortenas",
    "wof:placetype":"locality",
    "wof:population":6
},
  "geometry": {"coordinates":[-92.25556,14.62694],"type":"Point"}
}