{
  "type": "Feature",
  "properties": {
    "gn:admin1_code":"9.0",
    "gn:asciiname":"Unidad Habitacional Santa Cruz",
    "gn:country_code":"MX",
    "gn:dem":2248,
    "gn:feature_class":"P",
    "gn:feature_code":"PPL",
    "gn:name":"Unidad Habitacional Santa Cruz",
    "gn:population":0,
    "gn:timezone":"America/Mexico_City",
    "iso:country":"MX",
    "name:spa_x_preferred":[
        "Unidad Habitacional Santa Cruz"
    ],
    "wof:name":"Unidad Habitacional Santa Cruz",
    "wof:placetype":"locality"
},
  "geometry": {"coordinates":[-99.12894,19.25856],"type":"Point"}
}