{
  "type": "Feature",
  "properties": {
    "gn:admin1_code":"26",
    "gn:admin2_code":"51.0",
    "gn:asciiname":"El Aguaje",
    "gn:country_code":"MX",
    "gn:dem":876,
    "gn:feature_class":"P",
    "gn:feature_code":"PPL",
    "gn:name":"El Aguaje",
    "gn:population":0,
    "gn:timezone":"America/Hermosillo",
    "iso:country":"MX",
    "name:spa_x_preferred":[
        "El Aguaje"
    ],
    "wof:name":"El Aguaje",
    "wof:placetype":"locality"
},
  "geometry": {"coordinates":[-109.12562,27.90824000000001],"type":"Point"}
}