{
  "type": "Feature",
  "properties": {
    "gn:admin1_code":"26",
    "gn:admin2_code":"30.0",
    "gn:asciiname":"El Cimarron",
    "gn:country_code":"MX",
    "gn:dem":103,
    "gn:feature_class":"P",
    "gn:feature_code":"PPL",
    "gn:name":"El Cimarr\u00f3n",
    "gn:population":0,
    "gn:timezone":"America/Hermosillo",
    "iso:country":"MX",
    "wof:name":"El Cimarron",
    "wof:placetype":"locality"
},
  "geometry": {"coordinates":[-112.0234,29.23455],"type":"Point"}
}