{
  "type": "Feature",
  "properties": {
    "gn:admin1_code":"28",
    "gn:admin2_code":"6.0",
    "gn:asciiname":"Los Tanques",
    "gn:country_code":"MX",
    "gn:dem":2001,
    "gn:feature_class":"P",
    "gn:feature_code":"PPL",
    "gn:name":"Los Tanques",
    "gn:population":64,
    "gn:timezone":"America/Monterrey",
    "iso:country":"MX",
    "wof:name":"Los Tanques",
    "wof:placetype":"locality",
    "wof:population":64
},
  "geometry": {"coordinates":[-99.99666999999999,23.37417],"type":"Point"}
}