{
  "type": "Feature",
  "properties": {
    "gn:admin1_code":"3",
    "gn:admin2_code":"3.0",
    "gn:asciiname":"El Ancon",
    "gn:country_code":"MX",
    "gn:dem":620,
    "gn:feature_class":"P",
    "gn:feature_code":"PPL",
    "gn:name":"El Anc\u00f3n",
    "gn:population":83,
    "gn:timezone":"America/Mazatlan",
    "iso:country":"MX",
    "name:und_x_variant":[
        "El Anc\u00f3n"
    ],
    "wof:name":"El Ancon",
    "wof:placetype":"locality",
    "wof:population":83
},
  "geometry": {"coordinates":[-110.1011,24.01165],"type":"Point"}
}