{
  "type": "Feature",
  "properties": {
    "gn:admin1_code":"11",
    "gn:admin2_code":"3.0",
    "gn:asciiname":"Santa Elena de la Cruz (San Jose de Laguna)",
    "gn:country_code":"MX",
    "gn:dem":2060,
    "gn:feature_class":"P",
    "gn:feature_code":"PPL",
    "gn:name":"Santa Elena de la Cruz (San Jos\u00e9 de Laguna)",
    "gn:population":302,
    "gn:timezone":"America/Mexico_City",
    "iso:country":"MX",
    "name:und_x_variant":[
        "Santa Elena de la Cruz (San Jos\u00e9 de Laguna)"
    ],
    "wof:name":"Santa Elena de la Cruz (San Jose de Laguna)",
    "wof:placetype":"locality",
    "wof:population":302
},
  "geometry": {"coordinates":[-100.675,20.94222],"type":"Point"}
}