{
  "type": "Feature",
  "properties": {
    "gn:admin1_code":"6",
    "gn:admin2_code":"31.0",
    "gn:asciiname":"Rancho Borreguero",
    "gn:country_code":"MX",
    "gn:dem":2045,
    "gn:feature_class":"P",
    "gn:feature_code":"PPL",
    "gn:name":"Rancho Borreguero",
    "gn:population":4,
    "gn:timezone":"America/Chihuahua",
    "iso:country":"MX",
    "wof:name":"Rancho Borreguero",
    "wof:placetype":"locality",
    "wof:population":4
},
  "geometry": {"coordinates":[-107.42889,28.59389],"type":"Point"}
}