{
  "type": "Feature",
  "properties": {
    "gn:admin1_code":"26",
    "gn:admin2_code":"68.0",
    "gn:asciiname":"El Nacimiento",
    "gn:country_code":"MX",
    "gn:dem":623,
    "gn:feature_class":"P",
    "gn:feature_code":"PPL",
    "gn:name":"El Nacimiento",
    "gn:population":0,
    "gn:timezone":"America/Hermosillo",
    "iso:country":"MX",
    "name:spa_x_preferred":[
        "El Nacimiento"
    ],
    "wof:name":"El Nacimiento",
    "wof:placetype":"locality"
},
  "geometry": {"coordinates":[-110.01972000000001,29.00806],"type":"Point"}
}