{
  "type": "Feature",
  "properties": {
    "gn:admin1_code":"20",
    "gn:admin2_code":"277.0",
    "gn:asciiname":"El Cocoyuche",
    "gn:country_code":"MX",
    "gn:dem":1725,
    "gn:feature_class":"P",
    "gn:feature_code":"PPL",
    "gn:name":"El Cocoyuche",
    "gn:population":54,
    "gn:timezone":"America/Mexico_City",
    "iso:country":"MX",
    "wof:name":"El Cocoyuche",
    "wof:placetype":"locality",
    "wof:population":54
},
  "geometry": {"coordinates":[-97.22611000000001,16.8525],"type":"Point"}
}