{
  "type": "Feature",
  "properties": {
    "gn:admin1_code":"20",
    "gn:admin2_code":"190.0",
    "gn:asciiname":"Rancho los Pinos",
    "gn:country_code":"MX",
    "gn:dem":95,
    "gn:feature_class":"P",
    "gn:feature_code":"PPL",
    "gn:name":"Rancho los Pinos",
    "gn:population":8,
    "gn:timezone":"America/Mexico_City",
    "iso:country":"MX",
    "wof:name":"Rancho los Pinos",
    "wof:placetype":"locality",
    "wof:population":8
},
  "geometry": {"coordinates":[-95.22028,17.475],"type":"Point"}
}