{
  "type": "Feature",
  "properties": {
    "gn:admin1_code":"28.0",
    "gn:admin2_code":"12.0",
    "gn:asciiname":"Rancho Sofia",
    "gn:country_code":"MX",
    "gn:dem":53,
    "gn:feature_class":"P",
    "gn:feature_code":"PPL",
    "gn:name":"Rancho Sof\u00eda",
    "gn:population":0,
    "gn:timezone":"America/Monterrey",
    "iso:country":"MX",
    "name:spa_x_preferred":[
        "Rancho Sof\u00eda"
    ],
    "wof:name":"Rancho Sofia",
    "wof:placetype":"locality"
},
  "geometry": {"coordinates":[-98.70310000000001,22.80813],"type":"Point"}
}