{
  "type": "Feature",
  "properties": {
    "gn:admin1_code":"14",
    "gn:admin2_code":"87",
    "gn:asciiname":"El Gringo (Las Juntas)",
    "gn:country_code":"MX",
    "gn:dem":1366,
    "gn:feature_class":"P",
    "gn:feature_code":"PPL",
    "gn:name":"El Gringo (Las Juntas)",
    "gn:population":11,
    "gn:timezone":"America/Mexico_City",
    "iso:country":"MX",
    "wof:name":"El Gringo (Las Juntas)",
    "wof:placetype":"locality",
    "wof:population":11
},
  "geometry": {"coordinates":[-103.16722,19.38389],"type":"Point"}
}