{
  "type": "Feature",
  "properties": {
    "gn:admin1_code":"14",
    "gn:admin2_code":"81.0",
    "gn:asciiname":"Tecolote",
    "gn:country_code":"MX",
    "gn:dem":1733,
    "gn:feature_class":"P",
    "gn:feature_code":"PPL",
    "gn:name":"Tecolote",
    "gn:population":0,
    "gn:timezone":"America/Mexico_City",
    "iso:country":"MX",
    "name:ceb_x_preferred":[
        "Tecolote"
    ],
    "name:spa_x_preferred":[
        "Tecolote"
    ],
    "name:swe_x_preferred":[
        "Tecolote"
    ],
    "wof:name":"Tecolote",
    "wof:placetype":"locality"
},
  "geometry": {"coordinates":[-103.22006,22.23188],"type":"Point"}
}