{
  "type": "Feature",
  "properties": {
    "gn:admin1_code":"28",
    "gn:admin2_code":"17.0",
    "gn:asciiname":"El Ingenio",
    "gn:country_code":"MX",
    "gn:dem":767,
    "gn:feature_class":"P",
    "gn:feature_code":"PPL",
    "gn:name":"El Ingenio",
    "gn:population":0,
    "gn:timezone":"America/Monterrey",
    "iso:country":"MX",
    "name:spa_x_preferred":[
        "El Ingenio"
    ],
    "wof:name":"El Ingenio",
    "wof:placetype":"locality"
},
  "geometry": {"coordinates":[-99.3978,23.43435],"type":"Point"}
}