{
  "type": "Feature",
  "properties": {
    "gn:admin1_code":"6.0",
    "gn:admin2_code":"29.0",
    "gn:asciiname":"Cacalote de Arriba",
    "gn:country_code":"MX",
    "gn:dem":2028,
    "gn:feature_class":"P",
    "gn:feature_code":"PPL",
    "gn:name":"Cacalote de Arriba",
    "gn:population":0,
    "gn:timezone":"America/Chihuahua",
    "iso:country":"MX",
    "name:spa_x_preferred":[
        "Cacalote de Arriba"
    ],
    "name:und_x_variant":[
        "Rancho Cacalote Arriba"
    ],
    "wof:name":"Cacalote de Arriba",
    "wof:placetype":"locality"
},
  "geometry": {"coordinates":[-107.02161,26.16316],"type":"Point"}
}