{
  "type": "Feature",
  "properties": {
    "gn:admin1_code":"24",
    "gn:admin2_code":"15",
    "gn:asciiname":"Noria de Guadalupito",
    "gn:country_code":"MX",
    "gn:dem":1947,
    "gn:feature_class":"P",
    "gn:feature_code":"PPL",
    "gn:name":"Noria de Guadalupito",
    "gn:population":27,
    "gn:timezone":"America/Mexico_City",
    "iso:country":"MX",
    "wof:name":"Noria de Guadalupito",
    "wof:placetype":"locality",
    "wof:population":27
},
  "geometry": {"coordinates":[-101.00055999999999,23.14861],"type":"Point"}
}