{
  "type": "Feature",
  "properties": {
    "gn:admin1_code":"6.0",
    "gn:admin2_code":"23.0",
    "gn:asciiname":"Nevareno",
    "gn:country_code":"MX",
    "gn:dem":1424,
    "gn:feature_class":"P",
    "gn:feature_code":"PPL",
    "gn:name":"Nevare\u00f1o",
    "gn:population":0,
    "gn:timezone":"America/Chihuahua",
    "iso:country":"MX",
    "name:spa_x_preferred":[
        "Nevare\u00f1o"
    ],
    "wof:name":"Nevareno",
    "wof:placetype":"locality"
},
  "geometry": {"coordinates":[-107.62991,30.12181],"type":"Point"}
}