{
  "type": "Feature",
  "properties": {
    "gn:admin1_code":"18.0",
    "gn:admin2_code":"20.0",
    "gn:asciiname":"Playa Escondida",
    "gn:country_code":"MX",
    "gn:dem":23,
    "gn:feature_class":"P",
    "gn:feature_code":"PPL",
    "gn:name":"Playa Escondida",
    "gn:population":0,
    "gn:timezone":"America/Bahia_Banderas",
    "iso:country":"MX",
    "name:spa_x_preferred":[
        "Playa Escondida"
    ],
    "wof:name":"Playa Escondida",
    "wof:placetype":"locality"
},
  "geometry": {"coordinates":[-105.45468,20.86407],"type":"Point"}
}