{
  "type": "Feature",
  "properties": {
    "gn:admin1_code":"6",
    "gn:admin2_code":"27.0",
    "gn:asciiname":"Aquichi",
    "gn:country_code":"MX",
    "gn:dem":2175,
    "gn:feature_class":"P",
    "gn:feature_code":"PPL",
    "gn:name":"Aquichi",
    "gn:population":14,
    "gn:timezone":"America/Chihuahua",
    "iso:country":"MX",
    "name:spa_x_preferred":[
        "Aquichi"
    ],
    "wof:name":"Aquichi",
    "wof:placetype":"locality",
    "wof:population":14
},
  "geometry": {"coordinates":[-107.08295,27.10716],"type":"Point"}
}