{
  "type": "Feature",
  "properties": {
    "gn:admin1_code":"6.0",
    "gn:admin2_code":"65.0",
    "gn:asciiname":"El Guayabo",
    "gn:country_code":"MX",
    "gn:dem":530,
    "gn:feature_class":"P",
    "gn:feature_code":"PPL",
    "gn:name":"El Guayabo",
    "gn:population":0,
    "gn:timezone":"America/Mazatlan",
    "iso:country":"MX",
    "name:spa_x_preferred":[
        "El Guayabo"
    ],
    "name:und_x_variant":[
        "Guayabo"
    ],
    "wof:name":"El Guayabo",
    "wof:placetype":"locality"
},
  "geometry": {"coordinates":[-108.15143,26.95176],"type":"Point"}
}