{
  "type": "Feature",
  "properties": {
    "gn:admin1_code":"24.0",
    "gn:admin2_code":"46.0",
    "gn:asciiname":"San Juan de Guadalupe",
    "gn:country_code":"MX",
    "gn:dem":2120,
    "gn:feature_class":"P",
    "gn:feature_code":"PPL",
    "gn:name":"San Juan de Guadalupe",
    "gn:population":0,
    "gn:timezone":"America/Mexico_City",
    "iso:country":"MX",
    "name:spa_x_preferred":[
        "San Juan de Guadalupe"
    ],
    "wof:name":"San Juan de Guadalupe",
    "wof:placetype":"locality"
},
  "geometry": {"coordinates":[-101.33807,21.96641],"type":"Point"}
}