{
  "type": "Feature",
  "properties": {
    "gn:admin1_code":"26",
    "gn:admin2_code":"65.0",
    "gn:asciiname":"Rancho Los Ortiz",
    "gn:country_code":"MX",
    "gn:dem":860,
    "gn:feature_class":"P",
    "gn:feature_code":"PPL",
    "gn:name":"Rancho Los Ortiz",
    "gn:population":0,
    "gn:timezone":"America/Hermosillo",
    "iso:country":"MX",
    "wof:name":"Rancho Los Ortiz",
    "wof:placetype":"locality"
},
  "geometry": {"coordinates":[-111.49939999999999,31.071],"type":"Point"}
}