{
  "type": "Feature",
  "properties": {
    "gn:admin1_code":"32",
    "gn:admin2_code":"49.0",
    "gn:asciiname":"Bernalejo",
    "gn:country_code":"MX",
    "gn:dem":2227,
    "gn:feature_class":"P",
    "gn:feature_code":"PPL",
    "gn:name":"Bernalejo",
    "gn:population":0,
    "gn:timezone":"America/Mexico_City",
    "iso:country":"MX",
    "name:spa_x_preferred":[
        "Bernalejo"
    ],
    "wof:name":"Bernalejo",
    "wof:placetype":"locality"
},
  "geometry": {"coordinates":[-104.22775,22.69308],"type":"Point"}
}