{
  "type": "Feature",
  "properties": {
    "gn:admin1_code":"30",
    "gn:admin2_code":"49.0",
    "gn:asciiname":"Piedra Herrada",
    "gn:country_code":"MX",
    "gn:dem":125,
    "gn:feature_class":"P",
    "gn:feature_code":"PPL",
    "gn:name":"Piedra Herrada",
    "gn:population":102,
    "gn:timezone":"America/Mexico_City",
    "iso:country":"MX",
    "wof:name":"Piedra Herrada",
    "wof:placetype":"locality",
    "wof:population":102
},
  "geometry": {"coordinates":[-96.44917,18.76833],"type":"Point"}
}