{
  "type": "Feature",
  "properties": {
    "gn:admin1_code":"20",
    "gn:admin2_code":"401.0",
    "gn:asciiname":"Pena Larga",
    "gn:country_code":"MX",
    "gn:dem":183,
    "gn:feature_class":"P",
    "gn:feature_code":"PPL",
    "gn:name":"Pe\u00f1a Larga",
    "gn:population":0,
    "gn:timezone":"America/Mexico_City",
    "iso:country":"MX",
    "wof:name":"Pena Larga",
    "wof:placetype":"locality"
},
  "geometry": {"coordinates":[-96.88333,15.85],"type":"Point"}
}