{
  "type": "Feature",
  "properties": {
    "gn:admin1_code":"20",
    "gn:admin2_code":"515.0",
    "gn:asciiname":"Colonia Santa Elena de la Cruz",
    "gn:country_code":"MX",
    "gn:dem":46,
    "gn:feature_class":"P",
    "gn:feature_code":"PPL",
    "gn:name":"Colonia Santa Elena de la Cruz",
    "gn:population":59,
    "gn:timezone":"America/Mexico_City",
    "iso:country":"MX",
    "wof:name":"Colonia Santa Elena de la Cruz",
    "wof:placetype":"locality",
    "wof:population":59
},
  "geometry": {"coordinates":[-95.23972000000001,16.2925],"type":"Point"}
}