{
  "type": "Feature",
  "properties": {
    "gn:admin1_code":"15",
    "gn:admin2_code":"110.0",
    "gn:asciiname":"Los Tizates",
    "gn:country_code":"MX",
    "gn:dem":2021,
    "gn:feature_class":"P",
    "gn:feature_code":"PPL",
    "gn:name":"Los Tizates",
    "gn:population":126,
    "gn:timezone":"America/Mexico_City",
    "iso:country":"MX",
    "wof:name":"Los Tizates",
    "wof:placetype":"locality",
    "wof:population":126
},
  "geometry": {"coordinates":[-100.10448,19.20873],"type":"Point"}
}