{
  "type": "Feature",
  "properties": {
    "gn:admin1_code":"16",
    "gn:admin2_code":"49.0",
    "gn:asciiname":"La Hoya",
    "gn:country_code":"MX",
    "gn:dem":1369,
    "gn:feature_class":"P",
    "gn:feature_code":"PPL",
    "gn:name":"La Hoya",
    "gn:population":0,
    "gn:timezone":"America/Mexico_City",
    "iso:country":"MX",
    "name:ceb_x_preferred":[
        "La Hoya"
    ],
    "name:fra_x_preferred":[
        "La Hoya"
    ],
    "name:glg_x_preferred":[
        "La Hoya"
    ],
    "name:spa_x_preferred":[
        "La Hoya"
    ],
    "name:swe_x_preferred":[
        "La Hoya"
    ],
    "wof:name":"La Hoya",
    "wof:placetype":"locality"
},
  "geometry": {"coordinates":[-101.21528000000001,19.23156],"type":"Point"}
}