{
  "type": "Feature",
  "properties": {
    "gn:admin1_code":"30",
    "gn:admin2_code":"117",
    "gn:asciiname":"El Trapiche",
    "gn:country_code":"MX",
    "gn:dem":426,
    "gn:feature_class":"P",
    "gn:feature_code":"PPL",
    "gn:name":"El Trapiche",
    "gn:population":24,
    "gn:timezone":"America/Mexico_City",
    "iso:country":"MX",
    "wof:name":"El Trapiche",
    "wof:placetype":"locality",
    "wof:population":24
},
  "geometry": {"coordinates":[-96.79639,18.74278],"type":"Point"}
}