{
  "type": "Feature",
  "properties": {
    "gn:admin1_code":"30",
    "gn:admin2_code":"172.0",
    "gn:asciiname":"San Lorenzo Potrero Nuevo",
    "gn:country_code":"MX",
    "gn:dem":12,
    "gn:feature_class":"P",
    "gn:feature_code":"PPL",
    "gn:name":"San Lorenzo Potrero Nuevo",
    "gn:population":272,
    "gn:timezone":"America/Mexico_City",
    "iso:country":"MX",
    "wof:name":"San Lorenzo Potrero Nuevo",
    "wof:placetype":"locality",
    "wof:population":272
},
  "geometry": {"coordinates":[-94.74722,17.71389],"type":"Point"}
}