{
  "type": "Feature",
  "properties": {
    "gn:admin1_code":"12",
    "gn:admin2_code":"48.0",
    "gn:asciiname":"Alpuyeque",
    "gn:country_code":"MX",
    "gn:dem":107,
    "gn:feature_class":"P",
    "gn:feature_code":"PPL",
    "gn:name":"Alpuyeque",
    "gn:population":77,
    "gn:timezone":"America/Mexico_City",
    "iso:country":"MX",
    "wof:name":"Alpuyeque",
    "wof:placetype":"locality",
    "wof:population":77
},
  "geometry": {"coordinates":[-101.17605,17.44347999999999],"type":"Point"}
}