{
  "type": "Feature",
  "properties": {
    "gn:admin1_code":"10.0",
    "gn:admin2_code":"26.0",
    "gn:asciiname":"Vencedores",
    "gn:country_code":"MX",
    "gn:dem":2464,
    "gn:feature_class":"P",
    "gn:feature_code":"PPL",
    "gn:name":"Vencedores",
    "gn:population":0,
    "gn:timezone":"America/Monterrey",
    "iso:country":"MX",
    "name:und_x_variant":[
        "Ejido Vencedores",
        "Vencedores"
    ],
    "wof:name":"Vencedores",
    "wof:placetype":"locality"
},
  "geometry": {"coordinates":[-105.71185,24.42816],"type":"Point"}
}