{
  "type": "Feature",
  "properties": {
    "gn:admin1_code":"14.0",
    "gn:admin2_code":"15.0",
    "gn:asciiname":"La Casita",
    "gn:country_code":"MX",
    "gn:dem":883,
    "gn:feature_class":"P",
    "gn:feature_code":"PPL",
    "gn:name":"La Casita",
    "gn:population":0,
    "gn:timezone":"America/Mexico_City",
    "iso:country":"MX",
    "name:spa_x_preferred":[
        "La Casita"
    ],
    "wof:name":"La Casita",
    "wof:placetype":"locality"
},
  "geometry": {"coordinates":[-104.30849000000001,19.76046],"type":"Point"}
}