{
  "type": "Feature",
  "properties": {
    "gn:admin1_code":"19",
    "gn:admin2_code":"37.0",
    "gn:asciiname":"Potrerillos",
    "gn:country_code":"MX",
    "gn:dem":910,
    "gn:feature_class":"P",
    "gn:feature_code":"PPL",
    "gn:name":"Potrerillos",
    "gn:population":0,
    "gn:timezone":"America/Monterrey",
    "iso:country":"MX",
    "wof:name":"Potrerillos",
    "wof:placetype":"locality"
},
  "geometry": {"coordinates":[-100.75,26.06667],"type":"Point"}
}