{
  "type": "Feature",
  "properties": {
    "gn:admin1_code":"13",
    "gn:admin2_code":"84.0",
    "gn:asciiname":"El Tepozan",
    "gn:country_code":"MX",
    "gn:dem":1874,
    "gn:feature_class":"P",
    "gn:feature_code":"PPL",
    "gn:name":"El Tepoz\u00e1n",
    "gn:population":124,
    "gn:timezone":"America/Mexico_City",
    "iso:country":"MX",
    "name:und_x_variant":[
        "El Tepoz\u00e1n"
    ],
    "wof:name":"El Tepozan",
    "wof:placetype":"locality",
    "wof:population":124
},
  "geometry": {"coordinates":[-99.33778,20.68222],"type":"Point"}
}