{
  "type": "Feature",
  "properties": {
    "gn:admin1_code":"19",
    "gn:admin2_code":"20.0",
    "gn:asciiname":"La Plata",
    "gn:country_code":"MX",
    "gn:dem":127,
    "gn:feature_class":"P",
    "gn:feature_code":"PPL",
    "gn:name":"La Plata",
    "gn:population":0,
    "gn:timezone":"America/Monterrey",
    "iso:country":"MX",
    "name:spa_x_preferred":[
        "La Plata"
    ],
    "wof:name":"La Plata",
    "wof:placetype":"locality"
},
  "geometry": {"coordinates":[-98.64834999999999,25.88789],"type":"Point"}
}