{
  "type": "Feature",
  "properties": {
    "gn:admin1_code":"32.0",
    "gn:admin2_code":"10.0",
    "gn:asciiname":"Nueva Generacion",
    "gn:country_code":"MX",
    "gn:dem":2208,
    "gn:feature_class":"P",
    "gn:feature_code":"PPL",
    "gn:name":"Nueva Generaci\u00f3n",
    "gn:population":0,
    "gn:timezone":"America/Mexico_City",
    "iso:country":"MX",
    "name:spa_x_preferred":[
        "Nueva Generaci\u00f3n"
    ],
    "wof:name":"Nueva Generacion",
    "wof:placetype":"locality"
},
  "geometry": {"coordinates":[-103.11897,22.97248],"type":"Point"}
}