{
  "type": "Feature",
  "properties": {
    "gn:admin1_code":"5",
    "gn:admin2_code":"31",
    "gn:asciiname":"Verea Poquil",
    "gn:country_code":"MX",
    "gn:dem":688,
    "gn:feature_class":"P",
    "gn:feature_code":"PPL",
    "gn:name":"Verea Poquil",
    "gn:population":43,
    "gn:timezone":"America/Mexico_City",
    "iso:country":"MX",
    "wof:name":"Verea Poquil",
    "wof:placetype":"locality",
    "wof:population":43
},
  "geometry": {"coordinates":[-92.09166999999999,17.10972000000001],"type":"Point"}
}