{
  "type": "Feature",
  "properties": {
    "gn:admin1_code":"22.0",
    "gn:admin2_code":"16.0",
    "gn:asciiname":"Estancia de Santa Lucia",
    "gn:country_code":"MX",
    "gn:dem":2279,
    "gn:feature_class":"P",
    "gn:feature_code":"PPL",
    "gn:name":"Estancia de Santa Luc\u00eda",
    "gn:population":0,
    "gn:timezone":"America/Mexico_City",
    "iso:country":"MX",
    "name:spa_x_preferred":[
        "Estancia de Santa Luc\u00eda"
    ],
    "wof:name":"Estancia de Santa Lucia",
    "wof:placetype":"locality"
},
  "geometry": {"coordinates":[-100.06294,20.26151],"type":"Point"}
}