{
  "type": "Feature",
  "properties": {
    "gn:admin1_code":"5",
    "gn:admin2_code":"82.0",
    "gn:asciiname":"San Juan Veracruz",
    "gn:country_code":"MX",
    "gn:dem":1132,
    "gn:feature_class":"P",
    "gn:feature_code":"PPL",
    "gn:name":"San Juan Veracruz",
    "gn:population":69,
    "gn:timezone":"America/Mexico_City",
    "iso:country":"MX",
    "wof:name":"San Juan Veracruz",
    "wof:placetype":"locality",
    "wof:population":69
},
  "geometry": {"coordinates":[-92.38527999999999,17.06833],"type":"Point"}
}