{
  "type": "Feature",
  "properties": {
    "gn:admin1_code":"2",
    "gn:admin2_code":"1.0",
    "gn:asciiname":"Cimarron [Campo]",
    "gn:country_code":"MX",
    "gn:dem":3,
    "gn:feature_class":"P",
    "gn:feature_code":"PPL",
    "gn:name":"Cimarr\u00f3n [Campo]",
    "gn:population":5,
    "gn:timezone":"America/Tijuana",
    "iso:country":"MX",
    "name:und_x_variant":[
        "Cimarr\u00f3n [Campo]"
    ],
    "wof:name":"Cimarron [Campo]",
    "wof:placetype":"locality",
    "wof:population":5
},
  "geometry": {"coordinates":[-114.63611000000002,30.40694],"type":"Point"}
}