{
  "type": "Feature",
  "properties": {
    "gn:admin1_code":"30",
    "gn:admin2_code":"11",
    "gn:asciiname":"Monte Alto",
    "gn:country_code":"MX",
    "gn:dem":18,
    "gn:feature_class":"P",
    "gn:feature_code":"PPL",
    "gn:name":"Monte Alto",
    "gn:population":20,
    "gn:timezone":"America/Mexico_City",
    "iso:country":"MX",
    "name:ceb_x_preferred":[
        "Monte Alto"
    ],
    "name:ita_x_preferred":[
        "Monte Alto"
    ],
    "name:mlg_x_preferred":[
        "Monte Alto"
    ],
    "name:nld_x_preferred":[
        "Monte Alto"
    ],
    "name:pol_x_preferred":[
        "Monte Alto"
    ],
    "name:por_x_preferred":[
        "Monte Alto"
    ],
    "name:srp_x_preferred":[
        "\u041c\u043e\u043d\u0442\u0435 \u0410\u043b\u0442\u043e"
    ],
    "name:swe_x_preferred":[
        "Monte Alto"
    ],
    "wof:name":"Monte Alto",
    "wof:placetype":"locality",
    "wof:population":20
},
  "geometry": {"coordinates":[-95.56528,18.69333],"type":"Point"}
}