{
  "type": "Feature",
  "properties": {
    "gn:admin1_code":"30",
    "gn:admin2_code":"11",
    "gn:asciiname":"Monte Alto",
    "gn:country_code":"MX",
    "gn:dem":18,
    "gn:feature_class":"P",
    "gn:feature_code":"PPL",
    "gn:name":"Monte Alto",
    "gn:population":20,
    "gn:timezone":"America/Mexico_City",
    "iso:country":"MX",
    "wof:name":"Monte Alto",
    "wof:placetype":"locality",
    "wof:population":20
},
  "geometry": {"coordinates":[-95.56528,18.69333],"type":"Point"}
}