{
  "type": "Feature",
  "properties": {
    "gn:admin1_code":"19",
    "gn:admin2_code":"31.0",
    "gn:asciiname":"Kilometro 8.5",
    "gn:country_code":"MX",
    "gn:dem":453,
    "gn:feature_class":"P",
    "gn:feature_code":"PPL",
    "gn:name":"Kil\u00f3metro 8.5",
    "gn:population":5,
    "gn:timezone":"America/Monterrey",
    "iso:country":"MX",
    "name:und_x_variant":[
        "Kil\u00f3metro 8.5"
    ],
    "wof:name":"Kilometro 8.5",
    "wof:placetype":"locality",
    "wof:population":5
},
  "geometry": {"coordinates":[-100.12917,25.57389],"type":"Point"}
}