{
  "type": "Feature",
  "properties": {
    "gn:admin1_code":"6.0",
    "gn:admin2_code":"61.0",
    "gn:asciiname":"Las Pilas",
    "gn:country_code":"MX",
    "gn:dem":1571,
    "gn:feature_class":"P",
    "gn:feature_code":"PPL",
    "gn:name":"Las Pilas",
    "gn:population":0,
    "gn:timezone":"America/Chihuahua",
    "iso:country":"MX",
    "name:fra_x_preferred":[
        "Las Pilas"
    ],
    "name:lit_x_preferred":[
        "Las Pilasas"
    ],
    "name:nld_x_preferred":[
        "Las Pilas"
    ],
    "name:rus_x_preferred":[
        "\u041b\u0430\u0441-\u041f\u0438\u043b\u0430\u0441"
    ],
    "name:slk_x_preferred":[
        "Las Pilas"
    ],
    "name:spa_x_preferred":[
        "Las Pilas"
    ],
    "wof:name":"Las Pilas",
    "wof:placetype":"locality"
},
  "geometry": {"coordinates":[-106.29380999999999,27.56889],"type":"Point"}
}