{
  "type": "Feature",
  "properties": {
    "gn:admin1_code":"5",
    "gn:admin2_code":"64.0",
    "gn:asciiname":"Kistolja",
    "gn:country_code":"MX",
    "gn:dem":2189,
    "gn:feature_class":"P",
    "gn:feature_code":"PPL",
    "gn:name":"Kistolja",
    "gn:population":103,
    "gn:timezone":"America/Mexico_City",
    "iso:country":"MX",
    "wof:name":"Kistolja",
    "wof:placetype":"locality",
    "wof:population":103
},
  "geometry": {"coordinates":[-92.35944000000001,16.79194],"type":"Point"}
}