{
  "type": "Feature",
  "properties": {
    "gn:admin1_code":"1",
    "gn:admin2_code":"1.0",
    "gn:asciiname":"Rancho San Felipe",
    "gn:country_code":"MX",
    "gn:dem":1850,
    "gn:feature_class":"P",
    "gn:feature_code":"PPL",
    "gn:name":"Rancho San Felipe",
    "gn:population":6,
    "gn:timezone":"America/Mexico_City",
    "iso:country":"MX",
    "wof:name":"Rancho San Felipe",
    "wof:placetype":"locality",
    "wof:population":6
},
  "geometry": {"coordinates":[-102.33306,21.83194],"type":"Point"}
}