{
  "type": "Feature",
  "properties": {
    "gn:admin1_code":"14",
    "gn:admin2_code":"53.0",
    "gn:asciiname":"El Conejo",
    "gn:country_code":"MX",
    "gn:dem":1918,
    "gn:feature_class":"P",
    "gn:feature_code":"PPL",
    "gn:name":"El Conejo",
    "gn:population":223,
    "gn:timezone":"America/Mexico_City",
    "iso:country":"MX",
    "wof:name":"El Conejo",
    "wof:placetype":"locality",
    "wof:population":223
},
  "geometry": {"coordinates":[-101.86944,21.46528],"type":"Point"}
}