{
  "type": "Feature",
  "properties": {
    "gn:admin1_code":"25",
    "gn:admin2_code":"3.0",
    "gn:asciiname":"Tunita",
    "gn:country_code":"MX",
    "gn:dem":1840,
    "gn:feature_class":"P",
    "gn:feature_code":"PPL",
    "gn:name":"Tunita",
    "gn:population":0,
    "gn:timezone":"America/Mazatlan",
    "iso:country":"MX",
    "name:fas_x_preferred":[
        "\u062a\u0648\u0646\u06cc\u062a\u0627"
    ],
    "wof:name":"Tunita",
    "wof:placetype":"locality"
},
  "geometry": {"coordinates":[-107.40000000000001,26.08333],"type":"Point"}
}