{
  "type": "Feature",
  "properties": {
    "gn:admin1_code":"20",
    "gn:admin2_code":"413",
    "gn:asciiname":"Laguna Seca [Rancho]",
    "gn:country_code":"MX",
    "gn:dem":46,
    "gn:feature_class":"P",
    "gn:feature_code":"PPL",
    "gn:name":"Laguna Seca [Rancho]",
    "gn:population":25,
    "gn:timezone":"America/Mexico_City",
    "iso:country":"MX",
    "wof:name":"Laguna Seca [Rancho]",
    "wof:placetype":"locality",
    "wof:population":25
},
  "geometry": {"coordinates":[-96.12889,15.79444],"type":"Point"}
}