{
  "type": "Feature",
  "properties": {
    "gn:admin1_code":"6",
    "gn:admin2_code":"19.0",
    "gn:asciiname":"General Felipe Angeles",
    "gn:country_code":"MX",
    "gn:dem":1473,
    "gn:feature_class":"P",
    "gn:feature_code":"PPL",
    "gn:name":"General Felipe \u00c1ngeles",
    "gn:population":0,
    "gn:timezone":"America/Chihuahua",
    "iso:country":"MX",
    "name:spa_x_preferred":[
        "General Felipe \u00c1ngeles"
    ],
    "wof:name":"General Felipe Angeles",
    "wof:placetype":"locality"
},
  "geometry": {"coordinates":[-105.95488,28.60017],"type":"Point"}
}