{
  "type": "Feature",
  "properties": {
    "gn:admin1_code":"10",
    "gn:admin2_code":"35.0",
    "gn:asciiname":"Rancho de Abajo",
    "gn:country_code":"MX",
    "gn:dem":1924,
    "gn:feature_class":"P",
    "gn:feature_code":"PPL",
    "gn:name":"Rancho de Abajo",
    "gn:population":0,
    "gn:timezone":"America/Monterrey",
    "iso:country":"MX",
    "name:spa_x_preferred":[
        "Rancho de Abajo"
    ],
    "wof:name":"Rancho de Abajo",
    "wof:placetype":"locality"
},
  "geometry": {"coordinates":[-105.58486000000001,25.29372],"type":"Point"}
}