{
  "type": "Feature",
  "properties": {
    "gn:admin1_code":"31",
    "gn:admin2_code":"81.0",
    "gn:asciiname":"X-Copchen",
    "gn:country_code":"MX",
    "gn:dem":36,
    "gn:feature_class":"P",
    "gn:feature_code":"PPL",
    "gn:name":"X-Copchen",
    "gn:population":0,
    "gn:timezone":"America/Merida",
    "iso:country":"MX",
    "name:spa_x_preferred":[
        "X-Copchen"
    ],
    "wof:name":"X-Copchen",
    "wof:placetype":"locality"
},
  "geometry": {"coordinates":[-88.43434999999999,20.42646],"type":"Point"}
}