{
  "type": "Feature",
  "properties": {
    "gn:admin1_code":"14.0",
    "gn:admin2_code":"61.0",
    "gn:asciiname":"Puertecito del Zapote",
    "gn:country_code":"MX",
    "gn:dem":1561,
    "gn:feature_class":"P",
    "gn:feature_code":"PPL",
    "gn:name":"Puertecito del Zapote",
    "gn:population":0,
    "gn:timezone":"America/Mexico_City",
    "iso:country":"MX",
    "name:spa_x_preferred":[
        "Puertecito del Zapote"
    ],
    "wof:name":"Puertecito del Zapote",
    "wof:placetype":"locality"
},
  "geometry": {"coordinates":[-104.28301,22.02934],"type":"Point"}
}