{
  "type": "Feature",
  "properties": {
    "gn:admin1_code":"5",
    "gn:admin2_code":"72.0",
    "gn:asciiname":"El Triunfo",
    "gn:country_code":"MX",
    "gn:dem":1533,
    "gn:feature_class":"P",
    "gn:feature_code":"PPL",
    "gn:name":"El Triunfo",
    "gn:population":61,
    "gn:timezone":"America/Mexico_City",
    "iso:country":"MX",
    "wof:name":"El Triunfo",
    "wof:placetype":"locality",
    "wof:population":61
},
  "geometry": {"coordinates":[-92.84667,17.19194],"type":"Point"}
}