{
  "type": "Feature",
  "properties": {
    "gn:admin1_code":"13",
    "gn:admin2_code":"40.0",
    "gn:asciiname":"La Ardilla",
    "gn:cc2":"MX",
    "gn:country_code":"MX",
    "gn:dem":989,
    "gn:feature_class":"P",
    "gn:feature_code":"PPL",
    "gn:name":"La Ardilla",
    "gn:population":0,
    "gn:timezone":"America/Mexico_City",
    "iso:country":"MX",
    "name:und_x_variant":[
        "Ardilla",
        "La Ardilla"
    ],
    "wof:name":"La Ardilla",
    "wof:placetype":"locality"
},
  "geometry": {"coordinates":[-99.01667,21.05],"type":"Point"}
}