{
  "type": "Feature",
  "properties": {
    "gn:admin1_code":"6",
    "gn:admin2_code":"65",
    "gn:asciiname":"Sierrita de Cleofas",
    "gn:country_code":"MX",
    "gn:dem":1656,
    "gn:feature_class":"P",
    "gn:feature_code":"PPL",
    "gn:name":"Sierrita de Cleofas",
    "gn:population":13,
    "gn:timezone":"America/Mazatlan",
    "iso:country":"MX",
    "wof:name":"Sierrita de Cleofas",
    "wof:placetype":"locality",
    "wof:population":13
},
  "geometry": {"coordinates":[-108.0299,26.83354000000001],"type":"Point"}
}