{
  "type": "Feature",
  "properties": {
    "gn:admin1_code":"6",
    "gn:admin2_code":"36.0",
    "gn:asciiname":"El Sicomoro",
    "gn:country_code":"MX",
    "gn:dem":1328,
    "gn:feature_class":"P",
    "gn:feature_code":"PPL",
    "gn:name":"El Sicomoro",
    "gn:population":5,
    "gn:timezone":"America/Chihuahua",
    "iso:country":"MX",
    "wof:name":"El Sicomoro",
    "wof:placetype":"locality",
    "wof:population":5
},
  "geometry": {"coordinates":[-104.86381000000002,27.29872],"type":"Point"}
}