{
  "type": "Feature",
  "properties": {
    "gn:admin1_code":"24",
    "gn:admin2_code":"29.0",
    "gn:asciiname":"El Noventa",
    "gn:country_code":"MX",
    "gn:dem":148,
    "gn:feature_class":"P",
    "gn:feature_code":"PPL",
    "gn:name":"El Noventa",
    "gn:population":0,
    "gn:timezone":"America/Mexico_City",
    "iso:country":"MX",
    "name:spa_x_preferred":[
        "El Noventa"
    ],
    "name:spa_x_variant":[
        "El Jacube"
    ],
    "wof:name":"El Noventa",
    "wof:placetype":"locality"
},
  "geometry": {"coordinates":[-98.56892999999999,21.46941],"type":"Point"}
}