{
  "type": "Feature",
  "properties": {
    "gn:admin1_code":"26",
    "gn:admin2_code":"42.0",
    "gn:asciiname":"El Alamito",
    "gn:country_code":"MX",
    "gn:dem":140,
    "gn:feature_class":"P",
    "gn:feature_code":"PPL",
    "gn:name":"El Alamito",
    "gn:population":5,
    "gn:timezone":"America/Hermosillo",
    "iso:country":"MX",
    "wof:name":"El Alamito",
    "wof:placetype":"locality",
    "wof:population":5
},
  "geometry": {"coordinates":[-109.27083,27.08194],"type":"Point"}
}