{
  "type": "Feature",
  "properties": {
    "gn:admin1_code":"5",
    "gn:admin2_code":"59.0",
    "gn:asciiname":"El Chuvish (El Chuvin)",
    "gn:country_code":"MX",
    "gn:dem":865,
    "gn:feature_class":"P",
    "gn:feature_code":"PPL",
    "gn:name":"El Chuvish (El Chuv\u00edn)",
    "gn:population":6,
    "gn:timezone":"America/Mexico_City",
    "iso:country":"MX",
    "name:und_x_variant":[
        "El Chuvish (El Chuv\u00edn)"
    ],
    "wof:name":"El Chuvish (El Chuvin)",
    "wof:placetype":"locality",
    "wof:population":6
},
  "geometry": {"coordinates":[-92.02056,16.89694],"type":"Point"}
}