{
  "type": "Feature",
  "properties": {
    "gn:admin1_code":"19.0",
    "gn:admin2_code":"24.0",
    "gn:asciiname":"Tinajitas",
    "gn:country_code":"MX",
    "gn:dem":2133,
    "gn:feature_class":"P",
    "gn:feature_code":"PPL",
    "gn:name":"Tinajitas",
    "gn:population":16,
    "gn:timezone":"America/Monterrey",
    "iso:country":"MX",
    "name:spa_x_preferred":[
        "Tinajitas"
    ],
    "wof:name":"Tinajitas",
    "wof:placetype":"locality",
    "wof:population":16
},
  "geometry": {"coordinates":[-99.60827999999999,23.96786],"type":"Point"}
}