{
  "type": "Feature",
  "properties": {
    "gn:admin1_code":"1",
    "gn:admin2_code":"11.0",
    "gn:asciiname":"El Chamizal",
    "gn:country_code":"MX",
    "gn:dem":1922,
    "gn:feature_class":"P",
    "gn:feature_code":"PPL",
    "gn:name":"El Chamizal",
    "gn:population":6,
    "gn:timezone":"America/Mexico_City",
    "iso:country":"MX",
    "wof:name":"El Chamizal",
    "wof:placetype":"locality",
    "wof:population":6
},
  "geometry": {"coordinates":[-102.24611,22.07194],"type":"Point"}
}