{
  "type": "Feature",
  "properties": {
    "gn:admin1_code":"11.0",
    "gn:admin2_code":"19.0",
    "gn:asciiname":"El Ojo de Agua",
    "gn:country_code":"MX",
    "gn:dem":2166,
    "gn:feature_class":"P",
    "gn:feature_code":"PPL",
    "gn:name":"El Ojo de Agua",
    "gn:population":0,
    "gn:timezone":"America/Mexico_City",
    "iso:country":"MX",
    "wof:name":"El Ojo de Agua",
    "wof:placetype":"locality"
},
  "geometry": {"coordinates":[-100.58194,20.17028],"type":"Point"}
}