{
  "type": "Feature",
  "properties": {
    "gn:admin1_code":"6.0",
    "gn:admin2_code":"40.0",
    "gn:asciiname":"El Moquete",
    "gn:country_code":"MX",
    "gn:dem":1296,
    "gn:feature_class":"P",
    "gn:feature_code":"PPL",
    "gn:name":"El Moquete",
    "gn:population":0,
    "gn:timezone":"America/Chihuahua",
    "iso:country":"MX",
    "wof:name":"El Moquete",
    "wof:placetype":"locality"
},
  "geometry": {"coordinates":[-108.48333,29.05],"type":"Point"}
}