{
  "type": "Feature",
  "properties": {
    "gn:admin1_code":"5",
    "gn:admin2_code":"107",
    "gn:asciiname":"Grupo las Palomas",
    "gn:country_code":"MX",
    "gn:dem":681,
    "gn:feature_class":"P",
    "gn:feature_code":"PPL",
    "gn:name":"Grupo las Palomas",
    "gn:population":26,
    "gn:timezone":"America/Mexico_City",
    "iso:country":"MX",
    "wof:name":"Grupo las Palomas",
    "wof:placetype":"locality",
    "wof:population":26
},
  "geometry": {"coordinates":[-93.01861,16.35139],"type":"Point"}
}