{
  "type": "Feature",
  "properties": {
    "gn:admin1_code":"14",
    "gn:admin2_code":"86.0",
    "gn:asciiname":"Las Moras",
    "gn:country_code":"MX",
    "gn:dem":1984,
    "gn:feature_class":"P",
    "gn:feature_code":"PPL",
    "gn:name":"Las Moras",
    "gn:population":81,
    "gn:timezone":"America/Mexico_City",
    "iso:country":"MX",
    "wof:name":"Las Moras",
    "wof:placetype":"locality",
    "wof:population":81
},
  "geometry": {"coordinates":[-103.74778000000001,19.89222],"type":"Point"}
}