{
  "type": "Feature",
  "properties": {
    "gn:admin1_code":"6",
    "gn:admin2_code":"54",
    "gn:asciiname":"Campo 61 1/2",
    "gn:country_code":"MX",
    "gn:dem":2305,
    "gn:feature_class":"P",
    "gn:feature_code":"PPL",
    "gn:name":"Campo 61 1/2",
    "gn:population":24,
    "gn:timezone":"America/Chihuahua",
    "iso:country":"MX",
    "wof:name":"Campo 61 1/2",
    "wof:placetype":"locality",
    "wof:population":24
},
  "geometry": {"coordinates":[-106.63821000000002,28.95057000000001],"type":"Point"}
}