{
  "type": "Feature",
  "properties": {
    "gn:admin1_code":"17",
    "gn:admin2_code":"21.0",
    "gn:asciiname":"Rancho San Ignacio",
    "gn:country_code":"MX",
    "gn:dem":1146,
    "gn:feature_class":"P",
    "gn:feature_code":"PPL",
    "gn:name":"Rancho San Ignacio",
    "gn:population":5,
    "gn:timezone":"America/Mexico_City",
    "iso:country":"MX",
    "wof:name":"Rancho San Ignacio",
    "wof:placetype":"locality",
    "wof:population":5
},
  "geometry": {"coordinates":[-99.44944,18.68806],"type":"Point"}
}