{
  "type": "Feature",
  "properties": {
    "gn:admin1_code":"11.0",
    "gn:admin2_code":"23.0",
    "gn:asciiname":"La Cal Grande",
    "gn:country_code":"MX",
    "gn:dem":1678,
    "gn:feature_class":"P",
    "gn:feature_code":"PPL",
    "gn:name":"La Cal Grande",
    "gn:population":0,
    "gn:timezone":"America/Mexico_City",
    "iso:country":"MX",
    "name:und_x_variant":[
        "Cal Grande",
        "La Cal Grande"
    ],
    "wof:name":"La Cal Grande",
    "wof:placetype":"locality"
},
  "geometry": {"coordinates":[-101.94381,20.34365],"type":"Point"}
}