{
  "type": "Feature",
  "properties": {
    "gn:admin1_code":"30",
    "gn:admin2_code":"115.0",
    "gn:asciiname":"Taza de Agua Ojo Zarco",
    "gn:country_code":"MX",
    "gn:dem":1342,
    "gn:feature_class":"P",
    "gn:feature_code":"PPL",
    "gn:name":"Taza de Agua Ojo Zarco",
    "gn:population":1482,
    "gn:timezone":"America/Mexico_City",
    "iso:country":"MX",
    "wof:name":"Taza de Agua Ojo Zarco",
    "wof:placetype":"locality",
    "wof:population":1482
},
  "geometry": {"coordinates":[-97.20222,18.78333],"type":"Point"}
}