{
  "type": "Feature",
  "properties": {
    "gn:admin1_code":"16",
    "gn:admin2_code":"9.0",
    "gn:asciiname":"San Cayetano",
    "gn:country_code":"MX",
    "gn:dem":1310,
    "gn:feature_class":"P",
    "gn:feature_code":"PPL",
    "gn:name":"San Cayetano",
    "gn:population":121,
    "gn:timezone":"America/Mexico_City",
    "iso:country":"MX",
    "name:ceb_x_preferred":[
        "San Cayetano"
    ],
    "name:deu_x_preferred":[
        "San Cayetano"
    ],
    "name:fra_x_preferred":[
        "San Cayetano"
    ],
    "name:ita_x_preferred":[
        "San Cayetano"
    ],
    "name:msa_x_preferred":[
        "San Cayetano"
    ],
    "name:nld_x_preferred":[
        "San Cayetano"
    ],
    "name:por_x_preferred":[
        "San Cayetano"
    ],
    "name:sco_x_preferred":[
        "San Cayetano"
    ],
    "name:spa_x_preferred":[
        "San Cayetano"
    ],
    "name:swe_x_preferred":[
        "San Cayetano"
    ],
    "name:war_x_preferred":[
        "San Cayetano"
    ],
    "wof:name":"San Cayetano",
    "wof:placetype":"locality",
    "wof:population":121
},
  "geometry": {"coordinates":[-101.78667,19.23333],"type":"Point"}
}