{
  "type": "Feature",
  "properties": {
    "gn:admin1_code":"9",
    "gn:admin2_code":"13.0",
    "gn:asciiname":"Tizilingo",
    "gn:country_code":"MX",
    "gn:dem":2396,
    "gn:feature_class":"P",
    "gn:feature_code":"PPL",
    "gn:name":"Tizilingo",
    "gn:population":100,
    "gn:timezone":"America/Mexico_City",
    "iso:country":"MX",
    "wof:name":"Tizilingo",
    "wof:placetype":"locality",
    "wof:population":100
},
  "geometry": {"coordinates":[-99.08278,19.23806],"type":"Point"}
}