{
  "type": "Feature",
  "properties": {
    "gn:admin1_code":"11",
    "gn:admin2_code":"44",
    "gn:asciiname":"Puente Blanco",
    "gn:country_code":"MX",
    "gn:dem":1751,
    "gn:feature_class":"P",
    "gn:feature_code":"PPL",
    "gn:name":"Puente Blanco",
    "gn:population":14,
    "gn:timezone":"America/Mexico_City",
    "iso:country":"MX",
    "name:spa_x_preferred":[
        "Puente Blanco"
    ],
    "wof:name":"Puente Blanco",
    "wof:placetype":"locality",
    "wof:population":14
},
  "geometry": {"coordinates":[-100.91069,20.56473],"type":"Point"}
}