{
  "type": "Feature",
  "properties": {
    "gn:admin1_code":"7",
    "gn:admin2_code":"11.0",
    "gn:asciiname":"Perla Del Carmen",
    "gn:country_code":"MX",
    "gn:dem":1193,
    "gn:feature_class":"P",
    "gn:feature_code":"PPL",
    "gn:name":"Perla Del Carmen",
    "gn:population":0,
    "gn:timezone":"America/Monterrey",
    "iso:country":"MX",
    "name:spa_x_preferred":[
        "Perla Del Carmen"
    ],
    "wof:name":"Perla Del Carmen",
    "wof:placetype":"locality"
},
  "geometry": {"coordinates":[-101.84366,25.65989],"type":"Point"}
}