{
  "type": "Feature",
  "properties": {
    "gn:admin1_code":"5",
    "gn:admin2_code":"97.0",
    "gn:asciiname":"Madre Mia",
    "gn:country_code":"MX",
    "gn:dem":390,
    "gn:feature_class":"P",
    "gn:feature_code":"PPL",
    "gn:name":"Madre M\u00eda",
    "gn:population":0,
    "gn:timezone":"America/Mexico_City",
    "iso:country":"MX",
    "name:spa_x_preferred":[
        "Madre M\u00eda"
    ],
    "wof:name":"Madre Mia",
    "wof:placetype":"locality"
},
  "geometry": {"coordinates":[-93.65911,16.1502],"type":"Point"}
}