{
  "type": "Feature",
  "properties": {
    "gn:admin1_code":"26.0",
    "gn:admin2_code":"18.0",
    "gn:asciiname":"Campo Treinta y Uno (Ampliacion Treinta y Uno)",
    "gn:country_code":"MX",
    "gn:dem":22,
    "gn:feature_class":"P",
    "gn:feature_code":"PPL",
    "gn:name":"Campo Treinta y Uno (Ampliaci\u00f3n Treinta y Uno)",
    "gn:population":36,
    "gn:timezone":"America/Hermosillo",
    "iso:country":"MX",
    "wof:name":"Campo Treinta y Uno (Ampliacion Treinta y Uno)",
    "wof:placetype":"locality",
    "wof:population":36
},
  "geometry": {"coordinates":[-110.05638999999999,27.47694000000001],"type":"Point"}
}