{
  "type": "Feature",
  "properties": {
    "gn:admin1_code":"5",
    "gn:admin2_code":"53.0",
    "gn:asciiname":"El Horizonte",
    "gn:country_code":"MX",
    "gn:dem":1934,
    "gn:feature_class":"P",
    "gn:feature_code":"PPL",
    "gn:name":"El Horizonte",
    "gn:population":0,
    "gn:timezone":"America/Mexico_City",
    "iso:country":"MX",
    "name:spa_x_preferred":[
        "El Horizonte"
    ],
    "name:und_x_variant":[
        "Horizonte"
    ],
    "wof:name":"El Horizonte",
    "wof:placetype":"locality"
},
  "geometry": {"coordinates":[-92.15434999999999,15.36754],"type":"Point"}
}