{
  "type": "Feature",
  "properties": {
    "gn:admin1_code":"6",
    "gn:admin2_code":"29.0",
    "gn:asciiname":"La Entramada",
    "gn:country_code":"MX",
    "gn:dem":2216,
    "gn:feature_class":"P",
    "gn:feature_code":"PPL",
    "gn:name":"La Entramada",
    "gn:population":0,
    "gn:timezone":"America/Chihuahua",
    "iso:country":"MX",
    "name:spa_x_preferred":[
        "La Entramada"
    ],
    "wof:name":"La Entramada",
    "wof:placetype":"locality"
},
  "geometry": {"coordinates":[-107.27110999999999,26.5876],"type":"Point"}
}