{
  "type": "Feature",
  "properties": {
    "gn:admin1_code":"12.0",
    "gn:admin2_code":"73.0",
    "gn:asciiname":"El Soyate",
    "gn:country_code":"MX",
    "gn:dem":2308,
    "gn:feature_class":"P",
    "gn:feature_code":"PPL",
    "gn:name":"El Soyate",
    "gn:population":0,
    "gn:timezone":"America/Mexico_City",
    "iso:country":"MX",
    "name:spa_x_preferred":[
        "El Soyate"
    ],
    "wof:name":"El Soyate",
    "wof:placetype":"locality"
},
  "geometry": {"coordinates":[-101.35614,18.18733],"type":"Point"}
}