{
  "type": "Feature",
  "properties": {
    "gn:admin1_code":"10",
    "gn:admin2_code":"32.0",
    "gn:asciiname":"La Joya de Los Laureles",
    "gn:country_code":"MX",
    "gn:dem":2497,
    "gn:feature_class":"P",
    "gn:feature_code":"PPL",
    "gn:name":"La Joya de Los Laureles",
    "gn:population":0,
    "gn:timezone":"America/Monterrey",
    "iso:country":"MX",
    "name:spa_x_preferred":[
        "La Joya de Los Laureles"
    ],
    "wof:name":"La Joya de Los Laureles",
    "wof:placetype":"locality"
},
  "geometry": {"coordinates":[-106.22939,24.97009],"type":"Point"}
}