{
  "type": "Feature",
  "properties": {
    "gn:admin1_code":"12",
    "gn:admin2_code":"66.0",
    "gn:asciiname":"Zacapexco",
    "gn:country_code":"MX",
    "gn:dem":1514,
    "gn:feature_class":"P",
    "gn:feature_code":"PPL",
    "gn:name":"Zacapexco",
    "gn:population":253,
    "gn:timezone":"America/Mexico_City",
    "iso:country":"MX",
    "wof:name":"Zacapexco",
    "wof:placetype":"locality",
    "wof:population":253
},
  "geometry": {"coordinates":[-98.63778000000001,17.59332999999999],"type":"Point"}
}