{
  "type": "Feature",
  "properties": {
    "gn:admin1_code":"20",
    "gn:admin2_code":"462.0",
    "gn:asciiname":"La Luz Nagore",
    "gn:country_code":"MX",
    "gn:dem":1674,
    "gn:feature_class":"P",
    "gn:feature_code":"PPL",
    "gn:name":"La Luz Nagore",
    "gn:population":0,
    "gn:timezone":"America/Mexico_City",
    "iso:country":"MX",
    "name:und_x_variant":[
        "Luz Nagore"
    ],
    "wof:name":"La Luz Nagore",
    "wof:placetype":"locality"
},
  "geometry": {"coordinates":[-97.71493,17.85584],"type":"Point"}
}