{
  "type": "Feature",
  "properties": {
    "gn:admin1_code":"16",
    "gn:admin2_code":"106",
    "gn:asciiname":"Puente Alto (Santa Anita)",
    "gn:country_code":"MX",
    "gn:dem":1543,
    "gn:feature_class":"P",
    "gn:feature_code":"PPL",
    "gn:name":"Puente Alto (Santa Anita)",
    "gn:population":48,
    "gn:timezone":"America/Mexico_City",
    "iso:country":"MX",
    "wof:name":"Puente Alto (Santa Anita)",
    "wof:placetype":"locality",
    "wof:population":48
},
  "geometry": {"coordinates":[-102.30139,20.3125],"type":"Point"}
}