{
  "type": "Feature",
  "properties": {
    "gn:admin1_code":"5",
    "gn:admin2_code":"51",
    "gn:asciiname":"Camino el Cascaron",
    "gn:country_code":"MX",
    "gn:dem":40,
    "gn:feature_class":"P",
    "gn:feature_code":"PPL",
    "gn:name":"Camino el Cascar\u00f3n",
    "gn:population":26,
    "gn:timezone":"America/Mexico_City",
    "iso:country":"MX",
    "name:und_x_variant":[
        "Camino el Cascar\u00f3n"
    ],
    "wof:name":"Camino el Cascaron",
    "wof:placetype":"locality",
    "wof:population":26
},
  "geometry": {"coordinates":[-92.88194,15.42778],"type":"Point"}
}