{
  "type": "Feature",
  "properties": {
    "gn:admin1_code":"26",
    "gn:admin2_code":"66.0",
    "gn:asciiname":"El Varal",
    "gn:country_code":"MX",
    "gn:dem":454,
    "gn:feature_class":"P",
    "gn:feature_code":"PPL",
    "gn:name":"El Varal",
    "gn:population":2,
    "gn:timezone":"America/Hermosillo",
    "iso:country":"MX",
    "name:spa_x_preferred":[
        "El Varal"
    ],
    "wof:name":"El Varal",
    "wof:placetype":"locality",
    "wof:population":2
},
  "geometry": {"coordinates":[-110.30006000000002,29.14052],"type":"Point"}
}