{
  "type": "Feature",
  "properties": {
    "gn:admin1_code":"11",
    "gn:admin2_code":"23.0",
    "gn:asciiname":"La Villa de Guadalupe",
    "gn:country_code":"MX",
    "gn:dem":1678,
    "gn:feature_class":"P",
    "gn:feature_code":"PPL",
    "gn:name":"La Villa de Guadalupe",
    "gn:population":92,
    "gn:timezone":"America/Mexico_City",
    "iso:country":"MX",
    "wof:name":"La Villa de Guadalupe",
    "wof:placetype":"locality",
    "wof:population":92
},
  "geometry": {"coordinates":[-101.89278,20.34444],"type":"Point"}
}