{
  "type": "Feature",
  "properties": {
    "gn:admin1_code":"5",
    "gn:admin2_code":"54.0",
    "gn:asciiname":"Aquiles Serdan",
    "gn:country_code":"MX",
    "gn:dem":11,
    "gn:feature_class":"P",
    "gn:feature_code":"PPL",
    "gn:name":"Aquiles Serd\u00e1n",
    "gn:population":0,
    "gn:timezone":"America/Mexico_City",
    "iso:country":"MX",
    "name:spa_x_preferred":[
        "Aquiles Serd\u00e1n"
    ],
    "wof:name":"Aquiles Serdan",
    "wof:placetype":"locality"
},
  "geometry": {"coordinates":[-92.51443999999999,14.9398],"type":"Point"}
}