{
  "type": "Feature",
  "properties": {
    "gn:admin1_code":"30",
    "gn:asciiname":"Los Pozorrones",
    "gn:country_code":"MX",
    "gn:dem":122,
    "gn:feature_class":"P",
    "gn:feature_code":"PPL",
    "gn:name":"Los Pozorrones",
    "gn:population":0,
    "gn:timezone":"America/Mexico_City",
    "iso:country":"MX",
    "name:spa_x_preferred":[
        "Los Pozorrones"
    ],
    "wof:name":"Los Pozorrones",
    "wof:placetype":"locality"
},
  "geometry": {"coordinates":[-96.71696,18.526],"type":"Point"}
}