{
  "type": "Feature",
  "properties": {
    "gn:admin1_code":"15.0",
    "gn:asciiname":"Ejido Visitacion",
    "gn:country_code":"MX",
    "gn:dem":2246,
    "gn:feature_class":"P",
    "gn:feature_code":"PPL",
    "gn:name":"Ejido Visitaci\u00f3n",
    "gn:population":0,
    "gn:timezone":"America/Mexico_City",
    "iso:country":"MX",
    "name:spa_x_preferred":[
        "Ejido Visitaci\u00f3n"
    ],
    "wof:name":"Ejido Visitacion",
    "wof:placetype":"locality"
},
  "geometry": {"coordinates":[-99.11275999999999,19.73047],"type":"Point"}
}