{
  "type": "Feature",
  "properties": {
    "gn:admin1_code":"7",
    "gn:admin2_code":"23.0",
    "gn:asciiname":"Ventanas",
    "gn:country_code":"MX",
    "gn:dem":1380,
    "gn:feature_class":"P",
    "gn:feature_code":"PPL",
    "gn:name":"Ventanas",
    "gn:population":0,
    "gn:timezone":"America/Monterrey",
    "iso:country":"MX",
    "name:fas_x_preferred":[
        "\u0648\u0646\u062a\u0646\u0633"
    ],
    "name:pol_x_preferred":[
        "Ventanas"
    ],
    "name:que_x_preferred":[
        "Ventanas"
    ],
    "name:ron_x_preferred":[
        "Ventanas"
    ],
    "name:spa_x_preferred":[
        "Ventanas"
    ],
    "name:und_x_variant":[
        "Rancho de Ventanas"
    ],
    "wof:name":"Ventanas",
    "wof:placetype":"locality"
},
  "geometry": {"coordinates":[-102.33172999999999,27.8266],"type":"Point"}
}