{
  "type": "Feature",
  "properties": {
    "gn:admin1_code":"32",
    "gn:admin2_code":"49.0",
    "gn:asciiname":"Las Pilas del Alamo",
    "gn:country_code":"MX",
    "gn:dem":1843,
    "gn:feature_class":"P",
    "gn:feature_code":"PPL",
    "gn:name":"Las Pilas del \u00c1lamo",
    "gn:population":25,
    "gn:timezone":"America/Mexico_City",
    "iso:country":"MX",
    "wof:name":"Las Pilas del Alamo",
    "wof:placetype":"locality",
    "wof:population":25
},
  "geometry": {"coordinates":[-103.6061,22.6931],"type":"Point"}
}