{
  "type": "Feature",
  "properties": {
    "gn:admin1_code":"10.0",
    "gn:admin2_code":"35.0",
    "gn:asciiname":"Puerto la Tascosa",
    "gn:country_code":"MX",
    "gn:dem":2618,
    "gn:feature_class":"P",
    "gn:feature_code":"PPL",
    "gn:name":"Puerto la Tascosa",
    "gn:population":0,
    "gn:timezone":"America/Monterrey",
    "iso:country":"MX",
    "name:spa_x_preferred":[
        "Puerto la Tascosa"
    ],
    "wof:name":"Puerto la Tascosa",
    "wof:placetype":"locality"
},
  "geometry": {"coordinates":[-106.24858,25.5444],"type":"Point"}
}