{
  "type": "Feature",
  "properties": {
    "gn:admin1_code":"26",
    "gn:admin2_code":"29.0",
    "gn:asciiname":"Nochebuena",
    "gn:country_code":"MX",
    "gn:dem":72,
    "gn:feature_class":"P",
    "gn:feature_code":"PPL",
    "gn:name":"Nochebuena",
    "gn:population":0,
    "gn:timezone":"America/Hermosillo",
    "iso:country":"MX",
    "name:spa_x_preferred":[
        "Nochebuena"
    ],
    "name:und_x_variant":[
        "Noche Buena"
    ],
    "wof:name":"Nochebuena",
    "wof:placetype":"locality"
},
  "geometry": {"coordinates":[-110.9956,28.16382],"type":"Point"}
}