{
  "type": "Feature",
  "properties": {
    "gn:admin1_code":"4.0",
    "gn:asciiname":"Tres Hermanos",
    "gn:country_code":"MX",
    "gn:dem":38,
    "gn:feature_class":"P",
    "gn:feature_code":"PPL",
    "gn:name":"Tres Hermanos",
    "gn:population":0,
    "gn:timezone":"America/Merida",
    "iso:country":"MX",
    "name:spa_x_preferred":[
        "Tres Hermanos"
    ],
    "name:spa_x_variant":[
        "La Esperanza Dos"
    ],
    "wof:name":"Tres Hermanos",
    "wof:placetype":"locality"
},
  "geometry": {"coordinates":[-91.18857,17.98467999999999],"type":"Point"}
}