{
  "type": "Feature",
  "properties": {
    "gn:admin1_code":"5.0",
    "gn:asciiname":"La Victoria",
    "gn:country_code":"MX",
    "gn:dem":1202,
    "gn:feature_class":"P",
    "gn:feature_code":"PPL",
    "gn:name":"La Victoria",
    "gn:population":0,
    "gn:timezone":"America/Mexico_City",
    "iso:country":"MX",
    "name:spa_x_preferred":[
        "La Victoria"
    ],
    "wof:name":"La Victoria",
    "wof:placetype":"locality"
},
  "geometry": {"coordinates":[-93.09296999999999,15.86699],"type":"Point"}
}