{
  "type": "Feature",
  "properties": {
    "gn:admin1_code":"6",
    "gn:admin2_code":"27.0",
    "gn:asciiname":"Paraje Sinforosa",
    "gn:country_code":"MX",
    "gn:dem":1047,
    "gn:feature_class":"P",
    "gn:feature_code":"PPL",
    "gn:name":"Paraje Sinforosa",
    "gn:population":0,
    "gn:timezone":"America/Chihuahua",
    "iso:country":"MX",
    "name:spa_x_preferred":[
        "Paraje Sinforosa"
    ],
    "name:und_x_variant":[
        "Sinforosa"
    ],
    "wof:name":"Paraje Sinforosa",
    "wof:placetype":"locality"
},
  "geometry": {"coordinates":[-107.0907,26.67057],"type":"Point"}
}