{
  "type": "Feature",
  "properties": {
    "gn:admin1_code":"26.0",
    "gn:admin2_code":"69.0",
    "gn:asciiname":"Puerto del Aire",
    "gn:country_code":"MX",
    "gn:dem":1644,
    "gn:feature_class":"P",
    "gn:feature_code":"PPL",
    "gn:name":"Puerto del Aire",
    "gn:population":0,
    "gn:timezone":"America/Hermosillo",
    "iso:country":"MX",
    "name:spa_x_preferred":[
        "Puerto del Aire"
    ],
    "wof:name":"Puerto del Aire",
    "wof:placetype":"locality"
},
  "geometry": {"coordinates":[-108.94278,28.42186],"type":"Point"}
}