{
  "type": "Feature",
  "properties": {
    "gn:admin1_code":"12",
    "gn:admin2_code":"69.0",
    "gn:asciiname":"San Miguelito",
    "gn:country_code":"MX",
    "gn:dem":1829,
    "gn:feature_class":"P",
    "gn:feature_code":"PPL",
    "gn:name":"San Miguelito",
    "gn:population":231,
    "gn:timezone":"America/Mexico_City",
    "iso:country":"MX",
    "name:ceb_x_preferred":[
        "San Miguelito"
    ],
    "name:deu_x_preferred":[
        "San Miguelito"
    ],
    "name:ita_x_preferred":[
        "San Miguelito"
    ],
    "name:nld_x_preferred":[
        "San Miguelito"
    ],
    "name:pol_x_preferred":[
        "San Miguelito"
    ],
    "name:spa_x_preferred":[
        "San Miguelito"
    ],
    "name:swe_x_preferred":[
        "San Miguelito"
    ],
    "wof:name":"San Miguelito",
    "wof:placetype":"locality",
    "wof:population":231
},
  "geometry": {"coordinates":[-98.5992,17.42822],"type":"Point"}
}