{
  "type": "Feature",
  "properties": {
    "gn:admin1_code":"32.0",
    "gn:admin2_code":"14.0",
    "gn:asciiname":"Mesa Grande",
    "gn:country_code":"MX",
    "gn:dem":2022,
    "gn:feature_class":"P",
    "gn:feature_code":"PPL",
    "gn:name":"Mesa Grande",
    "gn:population":0,
    "gn:timezone":"America/Mexico_City",
    "iso:country":"MX",
    "name:rus_x_preferred":[
        "\u041c\u0435\u0441\u0430-\u0413\u0440\u0430\u043d\u0434\u0435"
    ],
    "name:spa_x_preferred":[
        "Mesa Grande"
    ],
    "name:spa_x_variant":[
        "El Jacalon"
    ],
    "wof:name":"Mesa Grande",
    "wof:placetype":"locality"
},
  "geometry": {"coordinates":[-103.02764000000001,24.1008],"type":"Point"}
}