{
  "type": "Feature",
  "properties": {
    "gn:admin1_code":"30",
    "gn:admin2_code":"109",
    "gn:asciiname":"Kilometro Tres",
    "gn:country_code":"MX",
    "gn:dem":273,
    "gn:feature_class":"P",
    "gn:feature_code":"PPL",
    "gn:name":"Kil\u00f3metro Tres",
    "gn:population":47,
    "gn:timezone":"America/Mexico_City",
    "iso:country":"MX",
    "name:und_x_variant":[
        "Kil\u00f3metro Tres"
    ],
    "wof:name":"Kilometro Tres",
    "wof:placetype":"locality",
    "wof:population":47
},
  "geometry": {"coordinates":[-96.93389000000001,19.94722],"type":"Point"}
}