{
  "type": "Feature",
  "properties": {
    "gn:admin1_code":"23",
    "gn:admin2_code":"5.0",
    "gn:asciiname":"Heriberto",
    "gn:country_code":"MX",
    "gn:dem":7,
    "gn:feature_class":"P",
    "gn:feature_code":"PPL",
    "gn:name":"Heriberto",
    "gn:population":0,
    "gn:timezone":"America/Cancun",
    "iso:country":"MX",
    "name:deu_x_preferred":[
        "Heriberto"
    ],
    "name:spa_x_preferred":[
        "Heriberto"
    ],
    "wof:name":"Heriberto",
    "wof:placetype":"locality"
},
  "geometry": {"coordinates":[-86.87094999999999,20.92808],"type":"Point"}
}