{
  "type": "Feature",
  "properties": {
    "gn:admin1_code":"16",
    "gn:admin2_code":"49",
    "gn:asciiname":"Arenal",
    "gn:country_code":"MX",
    "gn:dem":1896,
    "gn:feature_class":"P",
    "gn:feature_code":"PPL",
    "gn:name":"Arenal",
    "gn:population":17,
    "gn:timezone":"America/Mexico_City",
    "iso:country":"MX",
    "wof:name":"Arenal",
    "wof:placetype":"locality",
    "wof:population":17
},
  "geometry": {"coordinates":[-101.03944,19.37639],"type":"Point"}
}