{
  "type": "Feature",
  "properties": {
    "gn:admin1_code":"24",
    "gn:admin2_code":"3",
    "gn:asciiname":"La Mora (El Lindero)",
    "gn:country_code":"MX",
    "gn:dem":734,
    "gn:feature_class":"P",
    "gn:feature_code":"PPL",
    "gn:name":"La Mora (El Lindero)",
    "gn:population":17,
    "gn:timezone":"America/Mexico_City",
    "iso:country":"MX",
    "wof:name":"La Mora (El Lindero)",
    "wof:placetype":"locality",
    "wof:population":17
},
  "geometry": {"coordinates":[-99.13972,21.66222],"type":"Point"}
}