{
  "type": "Feature",
  "properties": {
    "gn:admin1_code":"11",
    "gn:admin2_code":"17",
    "gn:asciiname":"Los Vazquez",
    "gn:country_code":"MX",
    "gn:dem":1730,
    "gn:feature_class":"P",
    "gn:feature_code":"PPL",
    "gn:name":"Los V\u00e1zquez",
    "gn:population":11,
    "gn:timezone":"America/Mexico_City",
    "iso:country":"MX",
    "name:und_x_variant":[
        "Los V\u00e1zquez"
    ],
    "wof:name":"Los Vazquez",
    "wof:placetype":"locality",
    "wof:population":11
},
  "geometry": {"coordinates":[-101.31639,20.71722],"type":"Point"}
}