{
  "type": "Feature",
  "properties": {
    "gn:admin1_code":"24",
    "gn:admin2_code":"20",
    "gn:asciiname":"Presa de los Lirios",
    "gn:country_code":"MX",
    "gn:dem":1505,
    "gn:feature_class":"P",
    "gn:feature_code":"PPL",
    "gn:name":"Presa de los Lirios",
    "gn:population":18,
    "gn:timezone":"America/Mexico_City",
    "iso:country":"MX",
    "wof:name":"Presa de los Lirios",
    "wof:placetype":"locality",
    "wof:population":18
},
  "geometry": {"coordinates":[-100.53972,23.54833],"type":"Point"}
}