{
  "type": "Feature",
  "properties": {
    "gn:admin1_code":"14.0",
    "gn:admin2_code":"12.0",
    "gn:asciiname":"El Carrizalillo",
    "gn:country_code":"MX",
    "gn:dem":1556,
    "gn:feature_class":"P",
    "gn:feature_code":"PPL",
    "gn:name":"El Carrizalillo",
    "gn:population":0,
    "gn:timezone":"America/Mexico_City",
    "iso:country":"MX",
    "name:spa_x_preferred":[
        "El Carrizalillo"
    ],
    "wof:name":"El Carrizalillo",
    "wof:placetype":"locality"
},
  "geometry": {"coordinates":[-104.48746,20.34161],"type":"Point"}
}