{
  "type": "Feature",
  "properties": {
    "gn:admin1_code":"10",
    "gn:admin2_code":"26",
    "gn:asciiname":"Revolcaderos",
    "gn:country_code":"MX",
    "gn:dem":2052,
    "gn:feature_class":"P",
    "gn:feature_code":"PPL",
    "gn:name":"Revolcaderos",
    "gn:population":47,
    "gn:timezone":"America/Mazatlan",
    "iso:country":"MX",
    "wof:name":"Revolcaderos",
    "wof:placetype":"locality",
    "wof:population":47
},
  "geometry": {"coordinates":[-105.84139999999999,23.60945],"type":"Point"}
}