{
  "type": "Feature",
  "properties": {
    "gn:admin1_code":"26",
    "gn:admin2_code":"2.0",
    "gn:asciiname":"El Veinticinco",
    "gn:country_code":"MX",
    "gn:dem":1150,
    "gn:feature_class":"P",
    "gn:feature_code":"PPL",
    "gn:name":"El Veinticinco",
    "gn:population":2,
    "gn:timezone":"America/Hermosillo",
    "iso:country":"MX",
    "wof:name":"El Veinticinco",
    "wof:placetype":"locality",
    "wof:population":2
},
  "geometry": {"coordinates":[-109.57306,31.13389],"type":"Point"}
}