{
  "type": "Feature",
  "properties": {
    "gn:admin1_code":"32",
    "gn:admin2_code":"34.0",
    "gn:asciiname":"El Ojo de Agua",
    "gn:country_code":"MX",
    "gn:dem":1993,
    "gn:feature_class":"P",
    "gn:feature_code":"PPL",
    "gn:name":"El Ojo de Agua",
    "gn:population":72,
    "gn:timezone":"America/Mexico_City",
    "iso:country":"MX",
    "wof:name":"El Ojo de Agua",
    "wof:placetype":"locality",
    "wof:population":72
},
  "geometry": {"coordinates":[-102.77167,21.37639],"type":"Point"}
}