{
  "type": "Feature",
  "properties": {
    "gn:admin1_code":"7.0",
    "gn:admin2_code":"6.0",
    "gn:asciiname":"Granjeno",
    "gn:country_code":"MX",
    "gn:dem":845,
    "gn:feature_class":"P",
    "gn:feature_code":"PPL",
    "gn:name":"Granjeno",
    "gn:population":0,
    "gn:timezone":"America/Monterrey",
    "iso:country":"MX",
    "wof:name":"Granjeno",
    "wof:placetype":"locality"
},
  "geometry": {"coordinates":[-101.45828,26.69569000000001],"type":"Point"}
}