{
  "type": "Feature",
  "properties": {
    "gn:admin1_code":"23",
    "gn:admin2_code":"5.0",
    "gn:asciiname":"La Dama y el Caballero",
    "gn:country_code":"MX",
    "gn:dem":15,
    "gn:feature_class":"P",
    "gn:feature_code":"PPL",
    "gn:name":"La Dama y el Caballero",
    "gn:population":6,
    "gn:timezone":"America/Cancun",
    "iso:country":"MX",
    "wof:name":"La Dama y el Caballero",
    "wof:placetype":"locality",
    "wof:population":6
},
  "geometry": {"coordinates":[-87.09056,21.08583],"type":"Point"}
}