{
  "type": "Feature",
  "properties": {
    "gn:admin1_code":"11.0",
    "gn:asciiname":"Los Pinos del Borrado",
    "gn:country_code":"MX",
    "gn:dem":1721,
    "gn:feature_class":"P",
    "gn:feature_code":"PPL",
    "gn:name":"Los Pinos del Borrado",
    "gn:population":0,
    "gn:timezone":"America/Mexico_City",
    "iso:country":"MX",
    "name:spa_x_preferred":[
        "Los Pinos del Borrado"
    ],
    "name:spa_x_variant":[
        "Los Pinos"
    ],
    "wof:name":"Los Pinos del Borrado",
    "wof:placetype":"locality"
},
  "geometry": {"coordinates":[-101.86296,20.73146],"type":"Point"}
}