{
  "type": "Feature",
  "properties": {
    "gn:admin1_code":"25",
    "gn:admin2_code":"18.0",
    "gn:asciiname":"Berlin",
    "gn:country_code":"MX",
    "gn:dem":10,
    "gn:feature_class":"P",
    "gn:feature_code":"PPL",
    "gn:name":"Berlin",
    "gn:population":0,
    "gn:timezone":"America/Mazatlan",
    "iso:country":"MX",
    "name:spa_x_preferred":[
        "Berlin"
    ],
    "wof:name":"Berlin",
    "wof:placetype":"locality"
},
  "geometry": {"coordinates":[-107.82742,24.80735],"type":"Point"}
}