{
  "type": "Feature",
  "properties": {
    "gn:admin1_code":"6",
    "gn:admin2_code":"10.0",
    "gn:asciiname":"Plan de Alamos",
    "gn:country_code":"MX",
    "gn:dem":1482,
    "gn:feature_class":"P",
    "gn:feature_code":"PPL",
    "gn:name":"Plan de Alamos",
    "gn:population":0,
    "gn:timezone":"America/Chihuahua",
    "iso:country":"MX",
    "name:spa_x_preferred":[
        "Plan de Alamos"
    ],
    "name:und_x_variant":[
        "Rancho Plan del Alamo",
        "Plan de \u00c1lamos"
    ],
    "wof:name":"Plan de Alamos",
    "wof:placetype":"locality"
},
  "geometry": {"coordinates":[-106.66972,29.74933],"type":"Point"}
}