{
  "type": "Feature",
  "properties": {
    "gn:admin1_code":"26",
    "gn:admin2_code":"67.0",
    "gn:asciiname":"Oputo",
    "gn:country_code":"MX",
    "gn:dem":626,
    "gn:feature_class":"P",
    "gn:feature_code":"PPL",
    "gn:name":"Oputo",
    "gn:population":0,
    "gn:timezone":"America/Hermosillo",
    "iso:country":"MX",
    "wof:name":"Oputo",
    "wof:placetype":"locality"
},
  "geometry": {"coordinates":[-109.31667,30.15],"type":"Point"}
}