{
  "type": "Feature",
  "properties": {
    "gn:admin1_code":"25",
    "gn:admin2_code":"4.0",
    "gn:asciiname":"Rancho Don Teofilo",
    "gn:country_code":"MX",
    "gn:dem":236,
    "gn:feature_class":"P",
    "gn:feature_code":"PPL",
    "gn:name":"Rancho Don Te\u00f3filo",
    "gn:population":0,
    "gn:timezone":"America/Mazatlan",
    "iso:country":"MX",
    "name:spa_x_preferred":[
        "Rancho Don Te\u00f3filo"
    ],
    "wof:name":"Rancho Don Teofilo",
    "wof:placetype":"locality"
},
  "geometry": {"coordinates":[-106.06798000000001,23.42882],"type":"Point"}
}