{
  "type": "Feature",
  "properties": {
    "gn:admin1_code":"16",
    "gn:admin2_code":"27.0",
    "gn:asciiname":"La Pitahaya",
    "gn:country_code":"MX",
    "gn:dem":1961,
    "gn:feature_class":"P",
    "gn:feature_code":"PPL",
    "gn:name":"La Pitahaya",
    "gn:population":100,
    "gn:timezone":"America/Mexico_City",
    "iso:country":"MX",
    "wof:name":"La Pitahaya",
    "wof:placetype":"locality",
    "wof:population":100
},
  "geometry": {"coordinates":[-101.29389,19.89056],"type":"Point"}
}