{
  "type": "Feature",
  "properties": {
    "gn:admin1_code":"21.0",
    "gn:admin2_code":"86.0",
    "gn:asciiname":"El Pochote",
    "gn:country_code":"MX",
    "gn:dem":520,
    "gn:feature_class":"P",
    "gn:feature_code":"PPL",
    "gn:name":"El Pochote",
    "gn:population":167,
    "gn:timezone":"America/Mexico_City",
    "iso:country":"MX",
    "name:spa_x_preferred":[
        "El Pochote"
    ],
    "wof:name":"El Pochote",
    "wof:placetype":"locality",
    "wof:population":167
},
  "geometry": {"coordinates":[-97.98453000000001,20.48648],"type":"Point"}
}