{
  "type": "Feature",
  "properties": {
    "gn:admin1_code":"32",
    "gn:admin2_code":"10.0",
    "gn:asciiname":"El Cedrito",
    "gn:country_code":"MX",
    "gn:dem":2373,
    "gn:feature_class":"P",
    "gn:feature_code":"PPL",
    "gn:name":"El Cedrito",
    "gn:population":0,
    "gn:timezone":"America/Mexico_City",
    "iso:country":"MX",
    "name:spa_x_preferred":[
        "El Cedrito"
    ],
    "wof:name":"El Cedrito",
    "wof:placetype":"locality"
},
  "geometry": {"coordinates":[-103.17374,22.91059],"type":"Point"}
}