{
  "type": "Feature",
  "properties": {
    "gn:admin1_code":"24",
    "gn:admin2_code":"29.0",
    "gn:asciiname":"Totolteo",
    "gn:country_code":"MX",
    "gn:dem":300,
    "gn:feature_class":"P",
    "gn:feature_code":"PPL",
    "gn:name":"Totolteo",
    "gn:population":338,
    "gn:timezone":"America/Mexico_City",
    "iso:country":"MX",
    "wof:name":"Totolteo",
    "wof:placetype":"locality",
    "wof:population":338
},
  "geometry": {"coordinates":[-98.70860999999999,21.34917],"type":"Point"}
}