{
  "type": "Feature",
  "properties": {
    "gn:admin1_code":"28.0",
    "gn:admin2_code":"32.0",
    "gn:asciiname":"El Jabali",
    "gn:country_code":"MX",
    "gn:dem":74,
    "gn:feature_class":"P",
    "gn:feature_code":"PPL",
    "gn:name":"El Jabal\u00ed",
    "gn:population":0,
    "gn:timezone":"America/Matamoros",
    "iso:country":"MX",
    "name:spa_x_preferred":[
        "El Jabal\u00ed"
    ],
    "wof:name":"El Jabali",
    "wof:placetype":"locality"
},
  "geometry": {"coordinates":[-98.5594,25.97518],"type":"Point"}
}