{
  "type": "Feature",
  "properties": {
    "gn:admin1_code":"14",
    "gn:admin2_code":"113.0",
    "gn:asciiname":"Jahuiques",
    "gn:country_code":"MX",
    "gn:dem":1514,
    "gn:feature_class":"P",
    "gn:feature_code":"PPL",
    "gn:name":"Jahuiques",
    "gn:population":53,
    "gn:timezone":"America/Mexico_City",
    "iso:country":"MX",
    "wof:name":"Jahuiques",
    "wof:placetype":"locality",
    "wof:population":53
},
  "geometry": {"coordinates":[-103.74167,19.69083],"type":"Point"}
}