{
  "type": "Feature",
  "properties": {
    "gn:admin1_code":"5",
    "gn:admin2_code":"93.0",
    "gn:asciiname":"Ojo de Agua",
    "gn:country_code":"MX",
    "gn:dem":2411,
    "gn:feature_class":"P",
    "gn:feature_code":"PPL",
    "gn:name":"Ojo de Agua",
    "gn:population":88,
    "gn:timezone":"America/Mexico_City",
    "iso:country":"MX",
    "wof:name":"Ojo de Agua",
    "wof:placetype":"locality",
    "wof:population":88
},
  "geometry": {"coordinates":[-92.54519000000001,16.79431],"type":"Point"}
}