{
  "type": "Feature",
  "properties": {
    "gn:admin1_code":"30",
    "gn:admin2_code":"35.0",
    "gn:asciiname":"Felicitas del Angel",
    "gn:country_code":"MX",
    "gn:dem":268,
    "gn:feature_class":"P",
    "gn:feature_code":"PPL",
    "gn:name":"Fel\u00edcitas del \u00c1ngel",
    "gn:population":7,
    "gn:timezone":"America/Mexico_City",
    "iso:country":"MX",
    "name:und_x_variant":[
        "Fel\u00edcitas del \u00c1ngel"
    ],
    "wof:name":"Felicitas del Angel",
    "wof:placetype":"locality",
    "wof:population":7
},
  "geometry": {"coordinates":[-97.87417000000001,21.31944],"type":"Point"}
}