{
  "type": "Feature",
  "properties": {
    "gn:admin1_code":"4.0",
    "gn:asciiname":"Los Laureles",
    "gn:country_code":"MX",
    "gn:dem":64,
    "gn:feature_class":"P",
    "gn:feature_code":"PPL",
    "gn:name":"Los Laureles",
    "gn:population":0,
    "gn:timezone":"America/Merida",
    "iso:country":"MX",
    "name:por_x_preferred":[
        "Los Laureles"
    ],
    "name:spa_x_preferred":[
        "Los Laureles"
    ],
    "name:spa_x_variant":[
        "Los Arroyones"
    ],
    "wof:name":"Los Laureles",
    "wof:placetype":"locality"
},
  "geometry": {"coordinates":[-90.65909000000001,18.09789],"type":"Point"}
}