{
  "type": "Feature",
  "properties": {
    "gn:admin1_code":"12",
    "gn:admin2_code":"27",
    "gn:asciiname":"Loma Bonita",
    "gn:country_code":"MX",
    "gn:dem":312,
    "gn:feature_class":"P",
    "gn:feature_code":"PPL",
    "gn:name":"Loma Bonita",
    "gn:population":44,
    "gn:timezone":"America/Mexico_City",
    "iso:country":"MX",
    "wof:name":"Loma Bonita",
    "wof:placetype":"locality",
    "wof:population":44
},
  "geometry": {"coordinates":[-100.66076,18.59308],"type":"Point"}
}