{
  "type": "Feature",
  "properties": {
    "gn:admin1_code":"12",
    "gn:admin2_code":"57",
    "gn:asciiname":"Los Cimientos",
    "gn:country_code":"MX",
    "gn:dem":972,
    "gn:feature_class":"P",
    "gn:feature_code":"PPL",
    "gn:name":"Los Cimientos",
    "gn:population":28,
    "gn:timezone":"America/Mexico_City",
    "iso:country":"MX",
    "wof:name":"Los Cimientos",
    "wof:placetype":"locality",
    "wof:population":28
},
  "geometry": {"coordinates":[-100.70916,17.56847],"type":"Point"}
}