{
  "type": "Feature",
  "properties": {
    "gn:admin1_code":"14",
    "gn:admin2_code":"92",
    "gn:asciiname":"Puerta de Ramirez",
    "gn:country_code":"MX",
    "gn:dem":1361,
    "gn:feature_class":"P",
    "gn:feature_code":"PPL",
    "gn:name":"Puerta de Ram\u00edrez",
    "gn:population":20,
    "gn:timezone":"America/Mexico_City",
    "iso:country":"MX",
    "name:und_x_variant":[
        "Puerta de Ram\u00edrez"
    ],
    "wof:name":"Puerta de Ramirez",
    "wof:placetype":"locality",
    "wof:population":20
},
  "geometry": {"coordinates":[-103.38361,20.11556],"type":"Point"}
}