{
  "type": "Feature",
  "properties": {
    "gn:admin1_code":"6.0",
    "gn:admin2_code":"48.0",
    "gn:asciiname":"Pena Rajada",
    "gn:country_code":"MX",
    "gn:dem":1811,
    "gn:feature_class":"P",
    "gn:feature_code":"PPL",
    "gn:name":"Pe\u00f1a Rajada",
    "gn:population":0,
    "gn:timezone":"America/Chihuahua",
    "iso:country":"MX",
    "name:spa_x_preferred":[
        "Pe\u00f1a Rajada"
    ],
    "name:spa_x_variant":[
        "Rancho Pe\u00f1a Rajada"
    ],
    "wof:name":"Pena Rajada",
    "wof:placetype":"locality"
},
  "geometry": {"coordinates":[-107.40088,29.30888],"type":"Point"}
}