{
  "type": "Feature",
  "properties": {
    "gn:admin1_code":"24",
    "gn:admin2_code":"52.0",
    "gn:asciiname":"El Tejocote",
    "gn:country_code":"MX",
    "gn:dem":1066,
    "gn:feature_class":"P",
    "gn:feature_code":"PPL",
    "gn:name":"El Tejocote",
    "gn:population":75,
    "gn:timezone":"America/Mexico_City",
    "iso:country":"MX",
    "wof:name":"El Tejocote",
    "wof:placetype":"locality",
    "wof:population":75
},
  "geometry": {"coordinates":[-100.10972,22.30833],"type":"Point"}
}