{
  "type": "Feature",
  "properties": {
    "gn:admin1_code":"30",
    "gn:admin2_code":"209.0",
    "gn:asciiname":"Zapotitlan",
    "gn:country_code":"MX",
    "gn:dem":17,
    "gn:feature_class":"P",
    "gn:feature_code":"PPL",
    "gn:name":"Zapotitl\u00e1n",
    "gn:population":461,
    "gn:timezone":"America/Mexico_City",
    "iso:country":"MX",
    "name:und_x_variant":[
        "Zapotitl\u00e1n"
    ],
    "wof:name":"Zapotitlan",
    "wof:placetype":"locality",
    "wof:population":461
},
  "geometry": {"coordinates":[-94.78888999999999,18.50306],"type":"Point"}
}