{
  "type": "Feature",
  "properties": {
    "gn:admin1_code":"25",
    "gn:admin2_code":"3.0",
    "gn:asciiname":"Taxtecilo",
    "gn:country_code":"MX",
    "gn:dem":1184,
    "gn:feature_class":"P",
    "gn:feature_code":"PPL",
    "gn:name":"Taxtecilo",
    "gn:population":0,
    "gn:timezone":"America/Mazatlan",
    "iso:country":"MX",
    "wof:name":"Taxtecilo",
    "wof:placetype":"locality"
},
  "geometry": {"coordinates":[-107.31667,25.96667],"type":"Point"}
}