{
  "type": "Feature",
  "properties": {
    "gn:admin1_code":"5",
    "gn:admin2_code":"68.0",
    "gn:asciiname":"San Carlos",
    "gn:country_code":"MX",
    "gn:dem":255,
    "gn:feature_class":"P",
    "gn:feature_code":"PPL",
    "gn:name":"San Carlos",
    "gn:population":117,
    "gn:timezone":"America/Mexico_City",
    "iso:country":"MX",
    "wof:name":"San Carlos",
    "wof:placetype":"locality",
    "wof:population":117
},
  "geometry": {"coordinates":[-93.20361,17.45556],"type":"Point"}
}