{
  "type": "Feature",
  "properties": {
    "gn:admin1_code":"7",
    "gn:admin2_code":"33.0",
    "gn:asciiname":"Veinte de Noviembre (Santa Lucia)",
    "gn:country_code":"MX",
    "gn:dem":1106,
    "gn:feature_class":"P",
    "gn:feature_code":"PPL",
    "gn:name":"Veinte de Noviembre (Santa Luc\u00eda)",
    "gn:population":1097,
    "gn:timezone":"America/Monterrey",
    "iso:country":"MX",
    "wof:name":"Veinte de Noviembre (Santa Lucia)",
    "wof:placetype":"locality",
    "wof:population":1097
},
  "geometry": {"coordinates":[-103.15127,25.78923],"type":"Point"}
}