{
  "type": "Feature",
  "properties": {
    "gn:admin1_code":"30",
    "gn:asciiname":"Zacatlan",
    "gn:country_code":"MX",
    "gn:dem":458,
    "gn:feature_class":"P",
    "gn:feature_code":"PPL",
    "gn:name":"Zacatl\u00e1n",
    "gn:population":0,
    "gn:timezone":"America/Mexico_City",
    "iso:country":"MX",
    "name:spa_x_preferred":[
        "Zacatl\u00e1n"
    ],
    "wof:name":"Zacatlan",
    "wof:placetype":"locality"
},
  "geometry": {"coordinates":[-98.27444,20.82077],"type":"Point"}
}