{
  "type": "Feature",
  "properties": {
    "gn:admin1_code":"30",
    "gn:admin2_code":"5.0",
    "gn:asciiname":"Cienega de los Caballos",
    "gn:country_code":"MX",
    "gn:dem":6,
    "gn:feature_class":"P",
    "gn:feature_code":"PPL",
    "gn:name":"Ci\u00e9nega de los Caballos",
    "gn:population":290,
    "gn:timezone":"America/Mexico_City",
    "iso:country":"MX",
    "name:und_x_variant":[
        "Ci\u00e9nega de los Caballos"
    ],
    "wof:name":"Cienega de los Caballos",
    "wof:placetype":"locality",
    "wof:population":290
},
  "geometry": {"coordinates":[-95.82028,18.50972],"type":"Point"}
}