{
  "type": "Feature",
  "properties": {
    "gn:admin1_code":"29",
    "gn:admin2_code":"15.0",
    "gn:asciiname":"Rancho Escondido",
    "gn:country_code":"MX",
    "gn:dem":2251,
    "gn:feature_class":"P",
    "gn:feature_code":"PPL",
    "gn:name":"Rancho Escondido",
    "gn:population":6,
    "gn:timezone":"America/Mexico_City",
    "iso:country":"MX",
    "wof:name":"Rancho Escondido",
    "wof:placetype":"locality",
    "wof:population":6
},
  "geometry": {"coordinates":[-98.39131999999999,19.32721],"type":"Point"}
}