{
  "type": "Feature",
  "properties": {
    "gn:admin1_code":"20",
    "gn:admin2_code":"325.0",
    "gn:asciiname":"El Ciruelo",
    "gn:country_code":"MX",
    "gn:dem":1211,
    "gn:feature_class":"P",
    "gn:feature_code":"PPL",
    "gn:name":"El Ciruelo",
    "gn:population":119,
    "gn:timezone":"America/Mexico_City",
    "iso:country":"MX",
    "wof:name":"El Ciruelo",
    "wof:placetype":"locality",
    "wof:population":119
},
  "geometry": {"coordinates":[-96.00167,16.81944],"type":"Point"}
}