{
  "type": "Feature",
  "properties": {
    "gn:admin1_code":"26",
    "gn:admin2_code":"4.0",
    "gn:asciiname":"Santa Teresita",
    "gn:country_code":"MX",
    "gn:dem":450,
    "gn:feature_class":"P",
    "gn:feature_code":"PPL",
    "gn:name":"Santa Teresita",
    "gn:population":6,
    "gn:timezone":"America/Hermosillo",
    "iso:country":"MX",
    "name:ceb_x_preferred":[
        "Santa Teresita"
    ],
    "name:deu_x_preferred":[
        "Santa Teresita"
    ],
    "name:fra_x_preferred":[
        "Santa Teresita"
    ],
    "name:ilo_x_preferred":[
        "Santa Teresita"
    ],
    "name:ita_x_preferred":[
        "Santa Teresita"
    ],
    "name:nld_x_preferred":[
        "Santa Teresita"
    ],
    "name:sco_x_preferred":[
        "Santa Teresita"
    ],
    "name:spa_x_preferred":[
        "Santa Teresita"
    ],
    "name:srp_x_preferred":[
        "\u0421\u0430\u043d\u0442\u0430 \u0422\u0435\u0440\u0435\u0441\u0438\u0442\u0430"
    ],
    "name:swe_x_preferred":[
        "Santa Teresita"
    ],
    "name:war_x_preferred":[
        "Santa Teresita"
    ],
    "wof:name":"Santa Teresita",
    "wof:placetype":"locality",
    "wof:population":6
},
  "geometry": {"coordinates":[-111.795,30.73417],"type":"Point"}
}