{
  "type": "Feature",
  "properties": {
    "gn:admin1_code":"25",
    "gn:admin2_code":"6.0",
    "gn:asciiname":"El Traky",
    "gn:country_code":"MX",
    "gn:dem":12,
    "gn:feature_class":"P",
    "gn:feature_code":"PPL",
    "gn:name":"El Traky",
    "gn:population":83,
    "gn:timezone":"America/Mazatlan",
    "iso:country":"MX",
    "wof:name":"El Traky",
    "wof:placetype":"locality",
    "wof:population":83
},
  "geometry": {"coordinates":[-107.44465,24.52595],"type":"Point"}
}