{
  "type": "Feature",
  "properties": {
    "gn:admin1_code":"14",
    "gn:admin2_code":"61",
    "gn:asciiname":"Mezquite",
    "gn:country_code":"MX",
    "gn:dem":1624,
    "gn:feature_class":"P",
    "gn:feature_code":"PPL",
    "gn:name":"Mezquite",
    "gn:population":49,
    "gn:timezone":"America/Mexico_City",
    "iso:country":"MX",
    "wof:name":"Mezquite",
    "wof:placetype":"locality",
    "wof:population":49
},
  "geometry": {"coordinates":[-104.28778,22.03778],"type":"Point"}
}