{
  "type": "Feature",
  "properties": {
    "gn:admin1_code":"23.0",
    "gn:admin2_code":"4.0",
    "gn:asciiname":"David Gustavo Gutierrez Ruiz",
    "gn:country_code":"MX",
    "gn:dem":49,
    "gn:feature_class":"P",
    "gn:feature_code":"PPL",
    "gn:name":"David Gustavo Guti\u00e9rrez Ruiz",
    "gn:population":0,
    "gn:timezone":"America/Cancun",
    "iso:country":"MX",
    "name:spa_x_preferred":[
        "David Gustavo"
    ],
    "name:spa_x_variant":[
        "David Gustavo Guti\u00e9rrez Ruiz"
    ],
    "wof:name":"David Gustavo Gutierrez Ruiz",
    "wof:placetype":"locality"
},
  "geometry": {"coordinates":[-88.70584000000002,18.89655],"type":"Point"}
}