{
  "type": "Feature",
  "properties": {
    "gn:admin1_code":"25",
    "gn:admin2_code":"7.0",
    "gn:asciiname":"El Naranjo",
    "gn:country_code":"MX",
    "gn:dem":644,
    "gn:feature_class":"P",
    "gn:feature_code":"PPL",
    "gn:name":"El Naranjo",
    "gn:population":8,
    "gn:timezone":"America/Mazatlan",
    "iso:country":"MX",
    "wof:name":"El Naranjo",
    "wof:placetype":"locality",
    "wof:population":8
},
  "geometry": {"coordinates":[-108.11859,26.50187],"type":"Point"}
}