{
  "type": "Feature",
  "properties": {
    "gn:admin1_code":"10.0",
    "gn:admin2_code":"34.0",
    "gn:asciiname":"Guadalupe de Urrea",
    "gn:country_code":"MX",
    "gn:dem":491,
    "gn:feature_class":"P",
    "gn:feature_code":"PPL",
    "gn:name":"Guadalupe de Urrea",
    "gn:population":0,
    "gn:timezone":"America/Monterrey",
    "iso:country":"MX",
    "name:und_x_variant":[
        "Guadalupe",
        "Guadalupe de Urrea"
    ],
    "wof:name":"Guadalupe de Urrea",
    "wof:placetype":"locality"
},
  "geometry": {"coordinates":[-106.7217,25.03954],"type":"Point"}
}