{
  "type": "Feature",
  "properties": {
    "gn:admin1_code":"12.0",
    "gn:admin2_code":"38.0",
    "gn:asciiname":"El Carrizal",
    "gn:country_code":"MX",
    "gn:dem":698,
    "gn:feature_class":"P",
    "gn:feature_code":"PPL",
    "gn:name":"El Carrizal",
    "gn:population":0,
    "gn:timezone":"America/Mexico_City",
    "iso:country":"MX",
    "name:spa_x_preferred":[
        "El Carrizal"
    ],
    "wof:name":"El Carrizal",
    "wof:placetype":"locality"
},
  "geometry": {"coordinates":[-101.33446000000001,17.89712999999999],"type":"Point"}
}