{
  "type": "Feature",
  "properties": {
    "gn:admin1_code":"11.0",
    "gn:admin2_code":"16.0",
    "gn:asciiname":"Cora",
    "gn:country_code":"MX",
    "gn:dem":1698,
    "gn:feature_class":"P",
    "gn:feature_code":"PPL",
    "gn:name":"Cora",
    "gn:population":0,
    "gn:timezone":"America/Mexico_City",
    "iso:country":"MX",
    "name:bre_x_preferred":[
        "Cora"
    ],
    "name:cat_x_preferred":[
        "Cora"
    ],
    "name:ceb_x_preferred":[
        "Cora"
    ],
    "name:deu_x_preferred":[
        "Cora"
    ],
    "name:fra_x_preferred":[
        "Cora"
    ],
    "name:glg_x_preferred":[
        "Cora"
    ],
    "name:heb_x_preferred":[
        "\u05e7\u05d5\u05e8\u05d4"
    ],
    "name:hrv_x_preferred":[
        "Cora"
    ],
    "name:ita_x_preferred":[
        "Cora"
    ],
    "name:lat_x_preferred":[
        "Cora"
    ],
    "name:nld_x_preferred":[
        "Cora"
    ],
    "name:pol_x_preferred":[
        "Cora"
    ],
    "name:por_x_preferred":[
        "Cora"
    ],
    "name:ron_x_preferred":[
        "Cora"
    ],
    "name:spa_x_preferred":[
        "Cora"
    ],
    "name:swe_x_preferred":[
        "Cora"
    ],
    "wof:name":"Cora",
    "wof:placetype":"locality"
},
  "geometry": {"coordinates":[-101.46736,20.33123],"type":"Point"}
}