{
  "type": "Feature",
  "properties": {
    "gn:admin1_code":"20.0",
    "gn:admin2_code":"366.0",
    "gn:asciiname":"Cerro Tabla",
    "gn:country_code":"MX",
    "gn:dem":971,
    "gn:feature_class":"P",
    "gn:feature_code":"PPL",
    "gn:name":"Cerro Tabla",
    "gn:population":0,
    "gn:timezone":"America/Mexico_City",
    "iso:country":"MX",
    "name:spa_x_preferred":[
        "Cerro Tabla"
    ],
    "wof:name":"Cerro Tabla",
    "wof:placetype":"locality"
},
  "geometry": {"coordinates":[-96.72194,16.06339],"type":"Point"}
}