{
  "type": "Feature",
  "properties": {
    "gn:admin1_code":"16",
    "gn:admin2_code":"19.0",
    "gn:asciiname":"Las Trojas (El Fresno)",
    "gn:country_code":"MX",
    "gn:dem":1598,
    "gn:feature_class":"P",
    "gn:feature_code":"PPL",
    "gn:name":"Las Trojas (El Fresno)",
    "gn:population":81,
    "gn:timezone":"America/Mexico_City",
    "iso:country":"MX",
    "wof:name":"Las Trojas (El Fresno)",
    "wof:placetype":"locality",
    "wof:population":81
},
  "geometry": {"coordinates":[-102.7825,19.64778],"type":"Point"}
}