{
  "type": "Feature",
  "properties": {
    "gn:admin1_code":"24",
    "gn:admin2_code":"5.0",
    "gn:asciiname":"El Derramadero",
    "gn:country_code":"MX",
    "gn:dem":1212,
    "gn:feature_class":"P",
    "gn:feature_code":"PPL",
    "gn:name":"El Derramadero",
    "gn:population":8,
    "gn:timezone":"America/Mexico_City",
    "iso:country":"MX",
    "wof:name":"El Derramadero",
    "wof:placetype":"locality",
    "wof:population":8
},
  "geometry": {"coordinates":[-99.65582999999999,22.02],"type":"Point"}
}