{
  "type": "Feature",
  "properties": {
    "gn:admin1_code":"4",
    "gn:admin2_code":"3.0",
    "gn:asciiname":"Siete de Copas Uno",
    "gn:country_code":"MX",
    "gn:dem":-2,
    "gn:feature_class":"P",
    "gn:feature_code":"PPL",
    "gn:name":"Siete de Copas Uno",
    "gn:population":0,
    "gn:timezone":"America/Merida",
    "iso:country":"MX",
    "name:spa_x_preferred":[
        "Siete Copas"
    ],
    "name:spa_x_variant":[
        "Siete de Copas Uno"
    ],
    "wof:name":"Siete de Copas Uno",
    "wof:placetype":"locality"
},
  "geometry": {"coordinates":[-91.37251999999999,18.39696],"type":"Point"}
}