{
  "type": "Feature",
  "properties": {
    "gn:admin1_code":"26",
    "gn:admin2_code":"3.0",
    "gn:asciiname":"La Soledad",
    "gn:country_code":"MX",
    "gn:dem":377,
    "gn:feature_class":"P",
    "gn:feature_code":"PPL",
    "gn:name":"La Soledad",
    "gn:population":0,
    "gn:timezone":"America/Hermosillo",
    "iso:country":"MX",
    "name:spa_x_preferred":[
        "La Soledad"
    ],
    "wof:name":"La Soledad",
    "wof:placetype":"locality"
},
  "geometry": {"coordinates":[-108.75556,27.02778],"type":"Point"}
}