{
  "type": "Feature",
  "properties": {
    "gn:admin1_code":"5.0",
    "gn:admin2_code":"2.0",
    "gn:asciiname":"El Lagarto",
    "gn:country_code":"MX",
    "gn:dem":436,
    "gn:feature_class":"P",
    "gn:feature_code":"PPL",
    "gn:name":"El Lagarto",
    "gn:population":0,
    "gn:timezone":"America/Mexico_City",
    "iso:country":"MX",
    "name:spa_x_preferred":[
        "El Lagarto"
    ],
    "wof:name":"El Lagarto",
    "wof:placetype":"locality"
},
  "geometry": {"coordinates":[-92.77743,16.568],"type":"Point"}
}