{
  "type": "Feature",
  "properties": {
    "gn:admin1_code":"23",
    "gn:admin2_code":"8",
    "gn:asciiname":"Santa Cecilia",
    "gn:country_code":"MX",
    "gn:dem":8,
    "gn:feature_class":"P",
    "gn:feature_code":"PPL",
    "gn:name":"Santa Cecilia",
    "gn:population":27,
    "gn:timezone":"America/Cancun",
    "iso:country":"MX",
    "wof:name":"Santa Cecilia",
    "wof:placetype":"locality",
    "wof:population":27
},
  "geometry": {"coordinates":[-87.02717,20.79059],"type":"Point"}
}