{
  "type": "Feature",
  "properties": {
    "gn:admin1_code":"11.0",
    "gn:asciiname":"Buenavista de Coloradas",
    "gn:country_code":"MX",
    "gn:dem":1913,
    "gn:feature_class":"P",
    "gn:feature_code":"PPL",
    "gn:name":"Buenavista de Coloradas",
    "gn:population":0,
    "gn:timezone":"America/Mexico_City",
    "iso:country":"MX",
    "name:spa_x_preferred":[
        "Buenavista de Coloradas"
    ],
    "wof:name":"Buenavista de Coloradas",
    "wof:placetype":"locality"
},
  "geometry": {"coordinates":[-101.72803,20.74287],"type":"Point"}
}