{
  "type": "Feature",
  "properties": {
    "gn:admin1_code":"31",
    "gn:admin2_code":"105.0",
    "gn:asciiname":"Alondra",
    "gn:country_code":"MX",
    "gn:dem":9,
    "gn:feature_class":"P",
    "gn:feature_code":"PPL",
    "gn:name":"Alondra",
    "gn:population":9,
    "gn:timezone":"America/Merida",
    "iso:country":"MX",
    "name:spa_x_preferred":[
        "Alondra"
    ],
    "name:srp_x_preferred":[
        "\u0410\u043b\u043e\u043d\u0434\u0440\u0430"
    ],
    "wof:name":"Alondra",
    "wof:placetype":"locality",
    "wof:population":9
},
  "geometry": {"coordinates":[-89.425,21.05944],"type":"Point"}
}