{
  "type": "Feature",
  "properties": {
    "gn:admin1_code":"17",
    "gn:asciiname":"Los Alamos",
    "gn:country_code":"MX",
    "gn:dem":2681,
    "gn:feature_class":"P",
    "gn:feature_code":"PPL",
    "gn:name":"Los \u00c1lamos",
    "gn:population":0,
    "gn:timezone":"America/Mexico_City",
    "iso:country":"MX",
    "name:spa_x_preferred":[
        "Los \u00c1lamos"
    ],
    "wof:name":"Los Alamos",
    "wof:placetype":"locality"
},
  "geometry": {"coordinates":[-98.72887,19.62748],"type":"Point"}
}