{
  "type": "Feature",
  "properties": {
    "gn:admin1_code":"10",
    "gn:admin2_code":"33.0",
    "gn:asciiname":"San Baltasar",
    "gn:country_code":"MX",
    "gn:dem":2231,
    "gn:feature_class":"P",
    "gn:feature_code":"PPL",
    "gn:name":"San Baltasar",
    "gn:population":0,
    "gn:timezone":"America/Monterrey",
    "iso:country":"MX",
    "wof:name":"San Baltasar",
    "wof:placetype":"locality"
},
  "geometry": {"coordinates":[-104.01667,23.58333],"type":"Point"}
}