{
  "type": "Feature",
  "properties": {
    "gn:admin1_code":"26",
    "gn:admin2_code":"29.0",
    "gn:asciiname":"La Cochora",
    "gn:country_code":"MX",
    "gn:dem":12,
    "gn:feature_class":"P",
    "gn:feature_code":"PPL",
    "gn:name":"La Cochora",
    "gn:population":0,
    "gn:timezone":"America/Hermosillo",
    "iso:country":"MX",
    "name:spa_x_preferred":[
        "La Cochora"
    ],
    "wof:name":"La Cochora",
    "wof:placetype":"locality"
},
  "geometry": {"coordinates":[-110.92358,27.99029],"type":"Point"}
}