{
  "type": "Feature",
  "properties": {
    "gn:admin1_code":"27",
    "gn:admin2_code":"6.0",
    "gn:asciiname":"Huimango 1ra. Seccion (El Dren)",
    "gn:country_code":"MX",
    "gn:dem":15,
    "gn:feature_class":"P",
    "gn:feature_code":"PPL",
    "gn:name":"Huimango 1ra. Secci\u00f3n (El Dren)",
    "gn:population":611,
    "gn:timezone":"America/Mexico_City",
    "iso:country":"MX",
    "name:und_x_variant":[
        "Huimango 1ra. Secci\u00f3n (El Dren)"
    ],
    "wof:name":"Huimango 1ra. Seccion (El Dren)",
    "wof:placetype":"locality",
    "wof:population":611
},
  "geometry": {"coordinates":[-93.15306,18.11833],"type":"Point"}
}