{
  "type": "Feature",
  "properties": {
    "gn:admin1_code":"24",
    "gn:admin2_code":"35.0",
    "gn:asciiname":"El Veintiocho (Crucero la Tinaja)",
    "gn:country_code":"MX",
    "gn:dem":1865,
    "gn:feature_class":"P",
    "gn:feature_code":"PPL",
    "gn:name":"El Veintiocho (Crucero la Tinaja)",
    "gn:population":53,
    "gn:timezone":"America/Mexico_City",
    "iso:country":"MX",
    "wof:name":"El Veintiocho (Crucero la Tinaja)",
    "wof:placetype":"locality",
    "wof:population":53
},
  "geometry": {"coordinates":[-100.79806000000001,22.3425],"type":"Point"}
}