{
  "type": "Feature",
  "properties": {
    "gn:admin1_code":"29",
    "gn:admin2_code":"47",
    "gn:asciiname":"El Tecorral",
    "gn:country_code":"MX",
    "gn:dem":2561,
    "gn:feature_class":"P",
    "gn:feature_code":"PPL",
    "gn:name":"El Tecorral",
    "gn:population":23,
    "gn:timezone":"America/Mexico_City",
    "iso:country":"MX",
    "wof:name":"El Tecorral",
    "wof:placetype":"locality",
    "wof:population":23
},
  "geometry": {"coordinates":[-97.98504,19.54583],"type":"Point"}
}