{
  "type": "Feature",
  "properties": {
    "gn:admin1_code":"19.0",
    "gn:admin2_code":"27.0",
    "gn:asciiname":"El Alazan",
    "gn:country_code":"MX",
    "gn:dem":200,
    "gn:feature_class":"P",
    "gn:feature_code":"PPL",
    "gn:name":"El Alaz\u00e1n",
    "gn:population":0,
    "gn:timezone":"America/Monterrey",
    "iso:country":"MX",
    "name:spa_x_preferred":[
        "El Alaz\u00e1n"
    ],
    "wof:name":"El Alazan",
    "wof:placetype":"locality"
},
  "geometry": {"coordinates":[-99.51973,25.93816],"type":"Point"}
}