{
  "type": "Feature",
  "properties": {
    "gn:admin1_code":"18.0",
    "gn:admin2_code":"12.0",
    "gn:asciiname":"Punta Halcones",
    "gn:country_code":"MX",
    "gn:dem":11,
    "gn:feature_class":"P",
    "gn:feature_code":"PPL",
    "gn:name":"Punta Halcones",
    "gn:population":0,
    "gn:timezone":"America/Mazatlan",
    "iso:country":"MX",
    "wof:name":"Punta Halcones",
    "wof:placetype":"locality"
},
  "geometry": {"coordinates":[-106.54167,21.54583],"type":"Point"}
}