{
  "type": "Feature",
  "properties": {
    "gn:admin1_code":"21",
    "gn:admin2_code":"66.0",
    "gn:asciiname":"Vista Hermosa",
    "gn:country_code":"MX",
    "gn:dem":1077,
    "gn:feature_class":"P",
    "gn:feature_code":"PPL",
    "gn:name":"Vista Hermosa",
    "gn:population":533,
    "gn:timezone":"America/Mexico_City",
    "iso:country":"MX",
    "wof:name":"Vista Hermosa",
    "wof:placetype":"locality",
    "wof:population":533
},
  "geometry": {"coordinates":[-98.13333,18.07556],"type":"Point"}
}