{
  "type": "Feature",
  "properties": {
    "gn:admin1_code":"30",
    "gn:admin2_code":"198",
    "gn:asciiname":"Cerro Pelon",
    "gn:country_code":"MX",
    "gn:dem":1853,
    "gn:feature_class":"P",
    "gn:feature_code":"PPL",
    "gn:name":"Cerro Pel\u00f3n",
    "gn:population":13,
    "gn:timezone":"America/Mexico_City",
    "iso:country":"MX",
    "name:und_x_variant":[
        "Cerro Pel\u00f3n"
    ],
    "wof:name":"Cerro Pelon",
    "wof:placetype":"locality",
    "wof:population":13
},
  "geometry": {"coordinates":[-98.35693999999999,20.52333],"type":"Point"}
}