{
  "type": "Feature",
  "properties": {
    "gn:admin1_code":"21",
    "gn:admin2_code":"57.0",
    "gn:asciiname":"Huehuetlilla",
    "gn:country_code":"MX",
    "gn:dem":1653,
    "gn:feature_class":"P",
    "gn:feature_code":"PPL",
    "gn:name":"Huehuetlilla",
    "gn:population":147,
    "gn:timezone":"America/Mexico_City",
    "iso:country":"MX",
    "wof:name":"Huehuetlilla",
    "wof:placetype":"locality",
    "wof:population":147
},
  "geometry": {"coordinates":[-98.20773,20.26906],"type":"Point"}
}