{
  "type": "Feature",
  "properties": {
    "gn:admin1_code":"26",
    "gn:admin2_code":"45.0",
    "gn:asciiname":"El Gueerigo",
    "gn:country_code":"MX",
    "gn:dem":798,
    "gn:feature_class":"P",
    "gn:feature_code":"PPL",
    "gn:name":"El G\u00fc\u00e9rigo",
    "gn:population":0,
    "gn:timezone":"America/Hermosillo",
    "iso:country":"MX",
    "name:spa_x_preferred":[
        "El G\u00fc\u00e9rigo"
    ],
    "wof:name":"El Gueerigo",
    "wof:placetype":"locality"
},
  "geometry": {"coordinates":[-110.68606,29.94851],"type":"Point"}
}