{
  "type": "Feature",
  "properties": {
    "gn:admin1_code":"10",
    "gn:admin2_code":"1.0",
    "gn:asciiname":"La Guarnicion (La Pequena)",
    "gn:country_code":"MX",
    "gn:dem":1932,
    "gn:feature_class":"P",
    "gn:feature_code":"PPL",
    "gn:name":"La Guarnici\u00f3n (La Peque\u00f1a)",
    "gn:population":7,
    "gn:timezone":"America/Monterrey",
    "iso:country":"MX",
    "name:und_x_variant":[
        "La Guarnici\u00f3n (La Peque\u00f1a)"
    ],
    "wof:name":"La Guarnicion (La Pequena)",
    "wof:placetype":"locality",
    "wof:population":7
},
  "geometry": {"coordinates":[-104.74182,24.44764],"type":"Point"}
}