{
  "type": "Feature",
  "properties": {
    "gn:admin1_code":"21.0",
    "gn:admin2_code":"114.0",
    "gn:asciiname":"Nueva Colonia Fuentes de Canoa",
    "gn:country_code":"MX",
    "gn:dem":2639,
    "gn:feature_class":"P",
    "gn:feature_code":"PPL",
    "gn:name":"Nueva Colonia Fuentes de Canoa",
    "gn:population":0,
    "gn:timezone":"America/Mexico_City",
    "iso:country":"MX",
    "name:spa_x_preferred":[
        "Nueva Colonia Fuentes de Canoa"
    ],
    "wof:name":"Nueva Colonia Fuentes de Canoa",
    "wof:placetype":"locality"
},
  "geometry": {"coordinates":[-98.08868,19.14703],"type":"Point"}
}