{
  "type": "Feature",
  "properties": {
    "gn:admin1_code":"15.0",
    "gn:admin2_code":"7.0",
    "gn:asciiname":"Providencia Quinta Seccion San Mateo",
    "gn:country_code":"MX",
    "gn:dem":2611,
    "gn:feature_class":"P",
    "gn:feature_code":"PPL",
    "gn:name":"Providencia Quinta Secci\u00f3n San Mateo",
    "gn:population":0,
    "gn:timezone":"America/Mexico_City",
    "iso:country":"MX",
    "name:spa_x_preferred":[
        "Providencia Quinta Secci\u00f3n San Mateo"
    ],
    "name:und_x_variant":[
        "Providencia"
    ],
    "wof:name":"Providencia Quinta Seccion San Mateo",
    "wof:placetype":"locality"
},
  "geometry": {"coordinates":[-100.04322999999999,19.31538],"type":"Point"}
}