{
  "type": "Feature",
  "properties": {
    "gn:admin1_code":"4",
    "gn:admin2_code":"2.0",
    "gn:asciiname":"Estela Mariana",
    "gn:country_code":"MX",
    "gn:dem":13,
    "gn:feature_class":"P",
    "gn:feature_code":"PPL",
    "gn:name":"Estela Mariana",
    "gn:population":0,
    "gn:timezone":"America/Merida",
    "iso:country":"MX",
    "name:spa_x_preferred":[
        "Estela Mariana"
    ],
    "wof:name":"Estela Mariana",
    "wof:placetype":"locality"
},
  "geometry": {"coordinates":[-90.51596000000001,19.798],"type":"Point"}
}