{
  "type": "Feature",
  "properties": {
    "gn:admin1_code":"26",
    "gn:asciiname":"Tecoyagui",
    "gn:country_code":"MX",
    "gn:dem":727,
    "gn:feature_class":"P",
    "gn:feature_code":"PPL",
    "gn:name":"Tecoyag\u00fci",
    "gn:population":0,
    "gn:timezone":"America/Chihuahua",
    "iso:country":"MX",
    "name:spa_x_preferred":[
        "Tecoyag\u00fci"
    ],
    "wof:name":"Tecoyagui",
    "wof:placetype":"locality"
},
  "geometry": {"coordinates":[-108.67437,27.61313],"type":"Point"}
}