{
  "type": "Feature",
  "properties": {
    "gn:admin1_code":"12",
    "gn:admin2_code":"45.0",
    "gn:asciiname":"Tres Luces (Tlahuitzingo)",
    "gn:country_code":"MX",
    "gn:dem":1558,
    "gn:feature_class":"P",
    "gn:feature_code":"PPL",
    "gn:name":"Tres Luces (Tlahuitzingo)",
    "gn:population":71,
    "gn:timezone":"America/Mexico_City",
    "iso:country":"MX",
    "wof:name":"Tres Luces (Tlahuitzingo)",
    "wof:placetype":"locality",
    "wof:population":71
},
  "geometry": {"coordinates":[-98.70396,17.90661],"type":"Point"}
}