{
  "type": "Feature",
  "properties": {
    "gn:admin1_code":"10",
    "gn:admin2_code":"12.0",
    "gn:asciiname":"Javier Rojo Gomez (La Esperanza)",
    "gn:country_code":"MX",
    "gn:dem":1312,
    "gn:feature_class":"P",
    "gn:feature_code":"PPL",
    "gn:name":"Javier Rojo G\u00f3mez (La Esperanza)",
    "gn:population":90,
    "gn:timezone":"America/Monterrey",
    "iso:country":"MX",
    "name:und_x_variant":[
        "Javier Rojo G\u00f3mez (La Esperanza)"
    ],
    "wof:name":"Javier Rojo Gomez (La Esperanza)",
    "wof:placetype":"locality",
    "wof:population":90
},
  "geometry": {"coordinates":[-103.62949999999999,25.22557],"type":"Point"}
}