{
  "type": "Feature",
  "properties": {
    "gn:admin1_code":"5.0",
    "gn:admin2_code":"71.0",
    "gn:asciiname":"Aguatitlan",
    "gn:country_code":"MX",
    "gn:dem":7,
    "gn:feature_class":"P",
    "gn:feature_code":"PPL",
    "gn:name":"Aguatitl\u00e1n",
    "gn:population":0,
    "gn:timezone":"America/Mexico_City",
    "iso:country":"MX",
    "name:spa_x_preferred":[
        "Aguatitl\u00e1n"
    ],
    "wof:name":"Aguatitlan",
    "wof:placetype":"locality"
},
  "geometry": {"coordinates":[-92.67348,15.07806],"type":"Point"}
}