{
  "type": "Feature",
  "properties": {
    "gn:admin1_code":"26.0",
    "gn:admin2_code":"17.0",
    "gn:asciiname":"Juarez",
    "gn:country_code":"MX",
    "gn:dem":420,
    "gn:feature_class":"P",
    "gn:feature_code":"PPL",
    "gn:name":"Ju\u00e1rez",
    "gn:population":0,
    "gn:timezone":"America/Hermosillo",
    "iso:country":"MX",
    "wof:name":"Juarez",
    "wof:placetype":"locality"
},
  "geometry": {"coordinates":[-112.36667,30.96667],"type":"Point"}
}