{
  "type": "Feature",
  "properties": {
    "gn:admin1_code":"28.0",
    "gn:admin2_code":"19.0",
    "gn:asciiname":"El Cimarron",
    "gn:country_code":"MX",
    "gn:dem":206,
    "gn:feature_class":"P",
    "gn:feature_code":"PPL",
    "gn:name":"El Cimarr\u00f3n",
    "gn:population":5,
    "gn:timezone":"America/Monterrey",
    "iso:country":"MX",
    "name:spa_x_preferred":[
        "El Cimarr\u00f3n"
    ],
    "wof:name":"El Cimarron",
    "wof:placetype":"locality",
    "wof:population":5
},
  "geometry": {"coordinates":[-98.86861,23.28111],"type":"Point"}
}