{
  "type": "Feature",
  "properties": {
    "gn:admin1_code":"32.0",
    "gn:admin2_code":"51.0",
    "gn:asciiname":"La Rosa Amarilla",
    "gn:country_code":"MX",
    "gn:dem":1969,
    "gn:feature_class":"P",
    "gn:feature_code":"PPL",
    "gn:name":"La Rosa Amarilla",
    "gn:population":0,
    "gn:timezone":"America/Mexico_City",
    "iso:country":"MX",
    "name:spa_x_preferred":[
        "La Rosa Amarilla"
    ],
    "wof:name":"La Rosa Amarilla",
    "wof:placetype":"locality"
},
  "geometry": {"coordinates":[-102.08419000000001,23.53961],"type":"Point"}
}