{
  "type": "Feature",
  "properties": {
    "gn:admin1_code":"13",
    "gn:admin2_code":"24.0",
    "gn:asciiname":"El Peral",
    "gn:country_code":"MX",
    "gn:dem":2065,
    "gn:feature_class":"P",
    "gn:feature_code":"PPL",
    "gn:name":"El Peral",
    "gn:population":0,
    "gn:timezone":"America/Mexico_City",
    "iso:country":"MX",
    "name:ara_x_preferred":[
        "\u0625\u0644 \u0628\u064a\u0631\u0627\u0644"
    ],
    "name:arg_x_preferred":[
        "El Peral"
    ],
    "name:cat_x_preferred":[
        "El Peral"
    ],
    "name:ceb_x_preferred":[
        "El Peral"
    ],
    "name:epo_x_preferred":[
        "El Peral"
    ],
    "name:eus_x_preferred":[
        "El Peral"
    ],
    "name:fra_x_preferred":[
        "El Peral"
    ],
    "name:hun_x_preferred":[
        "El Peral"
    ],
    "name:ita_x_preferred":[
        "El Peral"
    ],
    "name:msa_x_preferred":[
        "El Peral"
    ],
    "name:nld_x_preferred":[
        "El Peral"
    ],
    "name:oci_x_preferred":[
        "El Peral"
    ],
    "name:pol_x_preferred":[
        "El Peral"
    ],
    "name:por_x_preferred":[
        "El Peral"
    ],
    "name:rus_x_preferred":[
        "\u042d\u043b\u044c-\u041f\u0435\u0440\u0430\u043b\u044c"
    ],
    "name:spa_x_preferred":[
        "El Peral"
    ],
    "name:ukr_x_preferred":[
        "\u0415\u043b\u044c-\u041f\u0435\u0440\u0430\u043b\u044c"
    ],
    "name:vie_x_preferred":[
        "El Peral"
    ],
    "name:war_x_preferred":[
        "El Peral"
    ],
    "name:zho_x_preferred":[
        "\u57c3\u5c14\u4f69\u62c9\u5c14"
    ],
    "wof:name":"El Peral",
    "wof:placetype":"locality"
},
  "geometry": {"coordinates":[-98.52032,20.23362],"type":"Point"}
}