{
  "type": "Feature",
  "properties": {
    "gn:admin1_code":"13",
    "gn:admin2_code":"24.0",
    "gn:asciiname":"El Peral",
    "gn:country_code":"MX",
    "gn:dem":2065,
    "gn:feature_class":"P",
    "gn:feature_code":"PPL",
    "gn:name":"El Peral",
    "gn:population":0,
    "gn:timezone":"America/Mexico_City",
    "iso:country":"MX",
    "name:spa_x_preferred":[
        "El Peral"
    ],
    "wof:name":"El Peral",
    "wof:placetype":"locality"
},
  "geometry": {"coordinates":[-98.52032,20.23362],"type":"Point"}
}