{
  "type": "Feature",
  "properties": {
    "gn:admin1_code":"18.0",
    "gn:admin2_code":"17.0",
    "gn:asciiname":"Duraznitos",
    "gn:country_code":"MX",
    "gn:dem":1005,
    "gn:feature_class":"P",
    "gn:feature_code":"PPL",
    "gn:name":"Duraznitos",
    "gn:population":46,
    "gn:timezone":"America/Mazatlan",
    "iso:country":"MX",
    "wof:name":"Duraznitos",
    "wof:placetype":"locality",
    "wof:population":46
},
  "geometry": {"coordinates":[-104.95276,21.51722],"type":"Point"}
}