{
  "type": "Feature",
  "properties": {
    "gn:admin1_code":"7",
    "gn:admin2_code":"27.0",
    "gn:asciiname":"San Jose del Valle",
    "gn:country_code":"MX",
    "gn:dem":1058,
    "gn:feature_class":"P",
    "gn:feature_code":"PPL",
    "gn:name":"San Jos\u00e9 del Valle",
    "gn:population":0,
    "gn:timezone":"America/Monterrey",
    "iso:country":"MX",
    "name:und_x_variant":[
        "San Jos\u00e9",
        "San Jos\u00e9 del Valle"
    ],
    "wof:name":"San Jose del Valle",
    "wof:placetype":"locality"
},
  "geometry": {"coordinates":[-100.88746,25.76194],"type":"Point"}
}