{
  "type": "Feature",
  "properties": {
    "gn:admin1_code":"6",
    "gn:admin2_code":"4.0",
    "gn:asciiname":"Los Arenales",
    "gn:country_code":"MX",
    "gn:dem":1698,
    "gn:feature_class":"P",
    "gn:feature_code":"PPL",
    "gn:name":"Los Arenales",
    "gn:population":0,
    "gn:timezone":"America/Chihuahua",
    "iso:country":"MX",
    "name:spa_x_preferred":[
        "Los Arenales"
    ],
    "wof:name":"Los Arenales",
    "wof:placetype":"locality"
},
  "geometry": {"coordinates":[-105.86579999999999,28.56972],"type":"Point"}
}