{
  "type": "Feature",
  "properties": {
    "gn:admin1_code":"5",
    "gn:admin2_code":"34.0",
    "gn:asciiname":"San Isidro",
    "gn:country_code":"MX",
    "gn:dem":712,
    "gn:feature_class":"P",
    "gn:feature_code":"PPL",
    "gn:name":"San Isidro",
    "gn:population":127,
    "gn:timezone":"America/Mexico_City",
    "iso:country":"MX",
    "wof:name":"San Isidro",
    "wof:placetype":"locality",
    "wof:population":127
},
  "geometry": {"coordinates":[-92.04111,15.67278],"type":"Point"}
}