{
  "type": "Feature",
  "properties": {
    "gn:admin1_code":"7.0",
    "gn:admin2_code":"33.0",
    "gn:asciiname":"El Estribo",
    "gn:country_code":"MX",
    "gn:dem":1101,
    "gn:feature_class":"P",
    "gn:feature_code":"PPL",
    "gn:name":"El Estribo",
    "gn:population":967,
    "gn:timezone":"America/Monterrey",
    "iso:country":"MX",
    "wof:name":"El Estribo",
    "wof:placetype":"locality",
    "wof:population":967
},
  "geometry": {"coordinates":[-103.10167,25.84139],"type":"Point"}
}