{
  "type": "Feature",
  "properties": {
    "gn:admin1_code":"6",
    "gn:admin2_code":"33.0",
    "gn:asciiname":"Las Presitas",
    "gn:country_code":"MX",
    "gn:dem":1719,
    "gn:feature_class":"P",
    "gn:feature_code":"PPL",
    "gn:name":"Las Presitas",
    "gn:population":7,
    "gn:timezone":"America/Chihuahua",
    "iso:country":"MX",
    "name:spa_x_preferred":[
        "Las Presitas"
    ],
    "wof:name":"Las Presitas",
    "wof:placetype":"locality",
    "wof:population":7
},
  "geometry": {"coordinates":[-105.9996,27.143],"type":"Point"}
}