{
  "type": "Feature",
  "properties": {
    "gn:admin1_code":"24",
    "gn:admin2_code":"43",
    "gn:asciiname":"Las Castillas",
    "gn:country_code":"MX",
    "gn:dem":2055,
    "gn:feature_class":"P",
    "gn:feature_code":"PPL",
    "gn:name":"Las Castillas",
    "gn:population":22,
    "gn:timezone":"America/Mexico_City",
    "iso:country":"MX",
    "wof:name":"Las Castillas",
    "wof:placetype":"locality",
    "wof:population":22
},
  "geometry": {"coordinates":[-100.5825,21.52639],"type":"Point"}
}