{
  "type": "Feature",
  "properties": {
    "gn:admin1_code":"10.0",
    "gn:admin2_code":"32.0",
    "gn:asciiname":"El Tarahumar",
    "gn:country_code":"MX",
    "gn:dem":2812,
    "gn:feature_class":"P",
    "gn:feature_code":"PPL",
    "gn:name":"El Tarahumar",
    "gn:population":0,
    "gn:timezone":"America/Monterrey",
    "iso:country":"MX",
    "name:spa_x_preferred":[
        "El Tarahumar"
    ],
    "wof:name":"El Tarahumar",
    "wof:placetype":"locality"
},
  "geometry": {"coordinates":[-106.00711,24.93798],"type":"Point"}
}