{
  "type": "Feature",
  "properties": {
    "gn:admin1_code":"9",
    "gn:admin2_code":"12.0",
    "gn:asciiname":"El Oyameyo",
    "gn:country_code":"MX",
    "gn:dem":2920,
    "gn:feature_class":"P",
    "gn:feature_code":"PPL",
    "gn:name":"El Oyameyo",
    "gn:population":183,
    "gn:timezone":"America/Mexico_City",
    "iso:country":"MX",
    "wof:name":"El Oyameyo",
    "wof:placetype":"locality",
    "wof:population":183
},
  "geometry": {"coordinates":[-99.17161,19.18844],"type":"Point"}
}