{
  "type": "Feature",
  "properties": {
    "gn:admin1_code":"32",
    "gn:admin2_code":"17.0",
    "gn:asciiname":"Francisco E. Garcia (Los Rancheros)",
    "gn:country_code":"MX",
    "gn:dem":2016,
    "gn:feature_class":"P",
    "gn:feature_code":"PPL",
    "gn:name":"Francisco E. Garc\u00eda (Los Rancheros)",
    "gn:population":434,
    "gn:timezone":"America/Mexico_City",
    "iso:country":"MX",
    "name:und_x_variant":[
        "Francisco E. Garc\u00eda (Los Rancheros)"
    ],
    "wof:name":"Francisco E. Garcia (Los Rancheros)",
    "wof:placetype":"locality",
    "wof:population":434
},
  "geometry": {"coordinates":[-102.29056,22.99],"type":"Point"}
}