{
  "type": "Feature",
  "properties": {
    "gn:admin1_code":"11",
    "gn:admin2_code":"17.0",
    "gn:asciiname":"Pozo de Parras",
    "gn:country_code":"MX",
    "gn:dem":1743,
    "gn:feature_class":"P",
    "gn:feature_code":"PPL",
    "gn:name":"Pozo de Parras",
    "gn:population":133,
    "gn:timezone":"America/Mexico_City",
    "iso:country":"MX",
    "wof:name":"Pozo de Parras",
    "wof:placetype":"locality",
    "wof:population":133
},
  "geometry": {"coordinates":[-101.36417,20.73694],"type":"Point"}
}