{
  "type": "Feature",
  "properties": {
    "gn:admin1_code":"31",
    "gn:admin2_code":"61.0",
    "gn:asciiname":"San Salvador",
    "gn:country_code":"MX",
    "gn:dem":3,
    "gn:feature_class":"P",
    "gn:feature_code":"PPL",
    "gn:name":"San Salvador",
    "gn:population":0,
    "gn:timezone":"America/Merida",
    "iso:country":"MX",
    "name:spa_x_preferred":[
        "San Salvador"
    ],
    "wof:name":"San Salvador",
    "wof:placetype":"locality"
},
  "geometry": {"coordinates":[-88.05700999999998,21.54173],"type":"Point"}
}