{
  "type": "Feature",
  "properties": {
    "gn:admin1_code":"6",
    "gn:admin2_code":"40.0",
    "gn:asciiname":"Los Muertos",
    "gn:country_code":"MX",
    "gn:dem":1221,
    "gn:feature_class":"P",
    "gn:feature_code":"PPL",
    "gn:name":"Los Muertos",
    "gn:population":6,
    "gn:timezone":"America/Chihuahua",
    "iso:country":"MX",
    "wof:name":"Los Muertos",
    "wof:placetype":"locality",
    "wof:population":6
},
  "geometry": {"coordinates":[-108.41746999999999,29.00206],"type":"Point"}
}