{
  "type": "Feature",
  "properties": {
    "gn:admin1_code":"21",
    "gn:admin2_code":"164",
    "gn:asciiname":"Ejido San Hipolito",
    "gn:country_code":"MX",
    "gn:dem":2151,
    "gn:feature_class":"P",
    "gn:feature_code":"PPL",
    "gn:name":"Ejido San Hip\u00f3lito",
    "gn:population":48,
    "gn:timezone":"America/Mexico_City",
    "iso:country":"MX",
    "name:und_x_variant":[
        "Ejido San Hip\u00f3lito"
    ],
    "wof:name":"Ejido San Hipolito",
    "wof:placetype":"locality",
    "wof:population":48
},
  "geometry": {"coordinates":[-97.85495,18.94126],"type":"Point"}
}