{
  "type": "Feature",
  "properties": {
    "gn:admin1_code":"5",
    "gn:admin2_code":"31.0",
    "gn:asciiname":"Joltacanteal",
    "gn:country_code":"MX",
    "gn:dem":988,
    "gn:feature_class":"P",
    "gn:feature_code":"PPL",
    "gn:name":"Joltacanteal",
    "gn:population":80,
    "gn:timezone":"America/Mexico_City",
    "iso:country":"MX",
    "wof:name":"Joltacanteal",
    "wof:placetype":"locality",
    "wof:population":80
},
  "geometry": {"coordinates":[-92.27889,17.08472],"type":"Point"}
}