{
  "type": "Feature",
  "properties": {
    "gn:admin1_code":"30",
    "gn:admin2_code":"5.0",
    "gn:asciiname":"Cerro de las Flores",
    "gn:country_code":"MX",
    "gn:dem":8,
    "gn:feature_class":"P",
    "gn:feature_code":"PPL",
    "gn:name":"Cerro de las Flores",
    "gn:population":437,
    "gn:timezone":"America/Mexico_City",
    "iso:country":"MX",
    "wof:name":"Cerro de las Flores",
    "wof:placetype":"locality",
    "wof:population":437
},
  "geometry": {"coordinates":[-95.80833,18.495],"type":"Point"}
}