{
  "type": "Feature",
  "properties": {
    "gn:admin1_code":"30",
    "gn:admin2_code":"82.0",
    "gn:asciiname":"Los Cocos",
    "gn:country_code":"MX",
    "gn:dem":25,
    "gn:feature_class":"P",
    "gn:feature_code":"PPL",
    "gn:name":"Los Cocos",
    "gn:population":0,
    "gn:timezone":"America/Mexico_City",
    "iso:country":"MX",
    "name:spa_x_preferred":[
        "Los Cocos"
    ],
    "wof:name":"Los Cocos",
    "wof:placetype":"locality"
},
  "geometry": {"coordinates":[-94.36956000000001,18.0456],"type":"Point"}
}