{
  "type": "Feature",
  "properties": {
    "gn:admin1_code":"30",
    "gn:admin2_code":"148",
    "gn:asciiname":"Mata Pionche",
    "gn:country_code":"MX",
    "gn:dem":98,
    "gn:feature_class":"P",
    "gn:feature_code":"PPL",
    "gn:name":"Mata Pionche",
    "gn:population":42,
    "gn:timezone":"America/Mexico_City",
    "iso:country":"MX",
    "wof:name":"Mata Pionche",
    "wof:placetype":"locality",
    "wof:population":42
},
  "geometry": {"coordinates":[-96.40139000000001,18.9925],"type":"Point"}
}