{
  "type": "Feature",
  "properties": {
    "gn:admin1_code":"30",
    "gn:admin2_code":"133",
    "gn:asciiname":"Jose Asuncion Flores Estrada",
    "gn:country_code":"MX",
    "gn:dem":15,
    "gn:feature_class":"P",
    "gn:feature_code":"PPL",
    "gn:name":"Jos\u00e9 Asunci\u00f3n Flores Estrada",
    "gn:population":20,
    "gn:timezone":"America/Mexico_City",
    "iso:country":"MX",
    "name:und_x_variant":[
        "Jos\u00e9 Asunci\u00f3n Flores Estrada"
    ],
    "wof:name":"Jose Asuncion Flores Estrada",
    "wof:placetype":"locality",
    "wof:population":20
},
  "geometry": {"coordinates":[-97.80611,22.18028],"type":"Point"}
}