{
  "type": "Feature",
  "properties": {
    "gn:admin1_code":"22",
    "gn:admin2_code":"4.0",
    "gn:asciiname":"La Negrita",
    "gn:country_code":"MX",
    "gn:dem":1727,
    "gn:feature_class":"P",
    "gn:feature_code":"PPL",
    "gn:name":"La Negrita",
    "gn:population":0,
    "gn:timezone":"America/Mexico_City",
    "iso:country":"MX",
    "wof:name":"La Negrita",
    "wof:placetype":"locality"
},
  "geometry": {"coordinates":[-99.50972,20.82917],"type":"Point"}
}