{
  "type": "Feature",
  "properties": {
    "gn:admin1_code":"14",
    "gn:admin2_code":"83.0",
    "gn:asciiname":"La Culebra",
    "gn:country_code":"MX",
    "gn:dem":1478,
    "gn:feature_class":"P",
    "gn:feature_code":"PPL",
    "gn:name":"La Culebra",
    "gn:population":63,
    "gn:timezone":"America/Mexico_City",
    "iso:country":"MX",
    "wof:name":"La Culebra",
    "wof:placetype":"locality",
    "wof:population":63
},
  "geometry": {"coordinates":[-103.62555999999999,20.51194],"type":"Point"}
}