{
  "type": "Feature",
  "properties": {
    "gn:admin1_code":"6",
    "gn:admin2_code":"7",
    "gn:asciiname":"Arroyo del Maiz",
    "gn:country_code":"MX",
    "gn:dem":2663,
    "gn:feature_class":"P",
    "gn:feature_code":"PPL",
    "gn:name":"Arroyo del Ma\u00edz",
    "gn:population":9,
    "gn:timezone":"America/Chihuahua",
    "iso:country":"MX",
    "name:und_x_variant":[
        "Arroyo del Ma\u00edz"
    ],
    "wof:name":"Arroyo del Maiz",
    "wof:placetype":"locality",
    "wof:population":9
},
  "geometry": {"coordinates":[-106.33861,26.40862000000001],"type":"Point"}
}