{
  "type": "Feature",
  "properties": {
    "gn:admin1_code":"5.0",
    "gn:asciiname":"Flores de Medina",
    "gn:country_code":"MX",
    "gn:dem":1846,
    "gn:feature_class":"P",
    "gn:feature_code":"PPL",
    "gn:name":"Flores de Medina",
    "gn:population":0,
    "gn:timezone":"America/Mexico_City",
    "iso:country":"MX",
    "name:spa_x_preferred":[
        "Flores de Medina"
    ],
    "wof:name":"Flores de Medina",
    "wof:placetype":"locality"
},
  "geometry": {"coordinates":[-92.18898,16.30176],"type":"Point"}
}