{
  "type": "Feature",
  "properties": {
    "gn:admin1_code":"28",
    "gn:admin2_code":"33.0",
    "gn:asciiname":"Gavilan Dos",
    "gn:country_code":"MX",
    "gn:dem":44,
    "gn:feature_class":"P",
    "gn:feature_code":"PPL",
    "gn:name":"Gavil\u00e1n Dos",
    "gn:population":3,
    "gn:timezone":"America/Monterrey",
    "iso:country":"MX",
    "wof:name":"Gavilan Dos",
    "wof:placetype":"locality",
    "wof:population":3
},
  "geometry": {"coordinates":[-98.13444,25.66583],"type":"Point"}
}