{
  "type": "Feature",
  "properties": {
    "gn:admin1_code":"26",
    "gn:admin2_code":"37.0",
    "gn:asciiname":"Bajada Blanca",
    "gn:country_code":"MX",
    "gn:dem":517,
    "gn:feature_class":"P",
    "gn:feature_code":"PPL",
    "gn:name":"Bajada Blanca",
    "gn:population":0,
    "gn:timezone":"America/Hermosillo",
    "iso:country":"MX",
    "name:spa_x_preferred":[
        "Bajada Blanca"
    ],
    "wof:name":"Bajada Blanca",
    "wof:placetype":"locality"
},
  "geometry": {"coordinates":[-110.13583,28.93528],"type":"Point"}
}