{
  "type": "Feature",
  "properties": {
    "gn:admin1_code":"14",
    "gn:admin2_code":"33",
    "gn:asciiname":"Union de Guadalupe (La Chancla)",
    "gn:country_code":"MX",
    "gn:dem":1774,
    "gn:feature_class":"P",
    "gn:feature_code":"PPL",
    "gn:name":"Uni\u00f3n de Guadalupe (La Chancla)",
    "gn:population":47,
    "gn:timezone":"America/Mexico_City",
    "iso:country":"MX",
    "name:und_x_variant":[
        "Uni\u00f3n de Guadalupe (La Chancla)"
    ],
    "wof:name":"Union de Guadalupe (La Chancla)",
    "wof:placetype":"locality",
    "wof:population":47
},
  "geometry": {"coordinates":[-102.17278,20.46833],"type":"Point"}
}