{
  "type": "Feature",
  "properties": {
    "gn:admin1_code":"25",
    "gn:admin2_code":"12",
    "gn:asciiname":"Ejercito de Salvacion",
    "gn:country_code":"MX",
    "gn:dem":35,
    "gn:feature_class":"P",
    "gn:feature_code":"PPL",
    "gn:name":"Ej\u00e9rcito de Salvaci\u00f3n",
    "gn:population":28,
    "gn:timezone":"America/Mazatlan",
    "iso:country":"MX",
    "name:und_x_variant":[
        "Ej\u00e9rcito de Salvaci\u00f3n"
    ],
    "wof:name":"Ejercito de Salvacion",
    "wof:placetype":"locality",
    "wof:population":28
},
  "geometry": {"coordinates":[-106.41531999999999,23.29419],"type":"Point"}
}