{
  "type": "Feature",
  "properties": {
    "gn:admin1_code":"32",
    "gn:admin2_code":"52.0",
    "gn:asciiname":"Ojo Zarco",
    "gn:country_code":"MX",
    "gn:dem":2026,
    "gn:feature_class":"P",
    "gn:feature_code":"PPL",
    "gn:name":"Ojo Zarco",
    "gn:population":7,
    "gn:timezone":"America/Mexico_City",
    "iso:country":"MX",
    "wof:name":"Ojo Zarco",
    "wof:placetype":"locality",
    "wof:population":7
},
  "geometry": {"coordinates":[-102.01361,22.15639],"type":"Point"}
}