{
  "type": "Feature",
  "properties": {
    "gn:admin1_code":"5",
    "gn:admin2_code":"59.0",
    "gn:asciiname":"Placido Flores",
    "gn:country_code":"MX",
    "gn:dem":667,
    "gn:feature_class":"P",
    "gn:feature_code":"PPL",
    "gn:name":"Pl\u00e1cido Flores",
    "gn:population":0,
    "gn:timezone":"America/Mexico_City",
    "iso:country":"MX",
    "name:spa_x_preferred":[
        "Pl\u00e1cido Flores"
    ],
    "wof:name":"Placido Flores",
    "wof:placetype":"locality"
},
  "geometry": {"coordinates":[-91.63495,16.89907],"type":"Point"}
}