{
  "type": "Feature",
  "properties": {
    "gn:admin1_code":"13.0",
    "gn:admin2_code":"28.0",
    "gn:asciiname":"Chumaquico",
    "gn:country_code":"MX",
    "gn:dem":286,
    "gn:feature_class":"P",
    "gn:feature_code":"PPL",
    "gn:name":"Chumaquico",
    "gn:population":0,
    "gn:timezone":"America/Mexico_City",
    "iso:country":"MX",
    "name:spa_x_preferred":[
        "Chumaquico"
    ],
    "wof:name":"Chumaquico",
    "wof:placetype":"locality"
},
  "geometry": {"coordinates":[-98.48286,21.06706],"type":"Point"}
}