{
  "type": "Feature",
  "properties": {
    "gn:admin1_code":"5",
    "gn:admin2_code":"107.0",
    "gn:asciiname":"El Triangulo",
    "gn:country_code":"MX",
    "gn:dem":660,
    "gn:feature_class":"P",
    "gn:feature_code":"PPL",
    "gn:name":"El Tri\u00e1ngulo",
    "gn:population":6,
    "gn:timezone":"America/Mexico_City",
    "iso:country":"MX",
    "name:und_x_variant":[
        "El Tri\u00e1ngulo"
    ],
    "wof:name":"El Triangulo",
    "wof:placetype":"locality",
    "wof:population":6
},
  "geometry": {"coordinates":[-92.97806,16.32917],"type":"Point"}
}