{
  "type": "Feature",
  "properties": {
    "gn:admin1_code":"31",
    "gn:admin2_code":"102.0",
    "gn:asciiname":"Villa Guadalupe",
    "gn:country_code":"MX",
    "gn:dem":23,
    "gn:feature_class":"P",
    "gn:feature_code":"PPL",
    "gn:name":"Villa Guadalupe",
    "gn:population":0,
    "gn:timezone":"America/Merida",
    "iso:country":"MX",
    "name:spa_x_preferred":[
        "Villa Guadalupe"
    ],
    "wof:name":"Villa Guadalupe",
    "wof:placetype":"locality"
},
  "geometry": {"coordinates":[-88.23436,20.70795],"type":"Point"}
}