{
  "type": "Feature",
  "properties": {
    "gn:admin1_code":"23",
    "gn:admin2_code":"4.0",
    "gn:asciiname":"Achiote",
    "gn:cc2":"BZ",
    "gn:country_code":"MX",
    "gn:dem":3,
    "gn:feature_class":"P",
    "gn:feature_code":"PPL",
    "gn:name":"Achiote",
    "gn:population":0,
    "gn:timezone":"America/Cancun",
    "iso:country":"MX",
    "name:und_x_variant":[
        "Achiotal",
        "Achiote",
        "Achotal"
    ],
    "wof:name":"Achiote",
    "wof:placetype":"locality"
},
  "geometry": {"coordinates":[-88.83253000000001,17.94777999999999],"type":"Point"}
}