{
  "type": "Feature",
  "properties": {
    "gn:admin1_code":"26.0",
    "gn:admin2_code":"51.0",
    "gn:asciiname":"Los Mimbres",
    "gn:country_code":"MX",
    "gn:dem":366,
    "gn:feature_class":"P",
    "gn:feature_code":"PPL",
    "gn:name":"Los Mimbres",
    "gn:population":0,
    "gn:timezone":"America/Hermosillo",
    "iso:country":"MX",
    "name:spa_x_preferred":[
        "Los Mimbres"
    ],
    "wof:name":"Los Mimbres",
    "wof:placetype":"locality"
},
  "geometry": {"coordinates":[-109.40476,28.08388],"type":"Point"}
}