{
  "type": "Feature",
  "properties": {
    "gn:admin1_code":"19",
    "gn:admin2_code":"29",
    "gn:asciiname":"Carrizos",
    "gn:country_code":"MX",
    "gn:dem":437,
    "gn:feature_class":"P",
    "gn:feature_code":"PPL",
    "gn:name":"Carrizos",
    "gn:population":28,
    "gn:timezone":"America/Monterrey",
    "iso:country":"MX",
    "wof:name":"Carrizos",
    "wof:placetype":"locality",
    "wof:population":28
},
  "geometry": {"coordinates":[-99.71167,24.91222],"type":"Point"}
}