{
  "type": "Feature",
  "properties": {
    "gn:admin1_code":"20",
    "gn:admin2_code":"450.0",
    "gn:asciiname":"Las Barrancas",
    "gn:country_code":"MX",
    "gn:dem":1605,
    "gn:feature_class":"P",
    "gn:feature_code":"PPL",
    "gn:name":"Las Barrancas",
    "gn:population":81,
    "gn:timezone":"America/Mexico_City",
    "iso:country":"MX",
    "wof:name":"Las Barrancas",
    "wof:placetype":"locality",
    "wof:population":81
},
  "geometry": {"coordinates":[-97.47917,16.61306],"type":"Point"}
}