{
  "type": "Feature",
  "properties": {
    "gn:admin1_code":"30",
    "gn:admin2_code":"32.0",
    "gn:asciiname":"La Margarita",
    "gn:country_code":"MX",
    "gn:dem":342,
    "gn:feature_class":"P",
    "gn:feature_code":"PPL",
    "gn:name":"La Margarita",
    "gn:population":272,
    "gn:timezone":"America/Mexico_City",
    "iso:country":"MX",
    "wof:name":"La Margarita",
    "wof:placetype":"locality",
    "wof:population":272
},
  "geometry": {"coordinates":[-95.03888999999999,18.36333],"type":"Point"}
}