{
  "type": "Feature",
  "properties": {
    "gn:admin1_code":"6",
    "gn:admin2_code":"61.0",
    "gn:asciiname":"Satevo",
    "gn:country_code":"MX",
    "gn:dem":1365,
    "gn:feature_class":"P",
    "gn:feature_code":"PPL",
    "gn:name":"Satev\u00f3",
    "gn:population":0,
    "gn:timezone":"America/Chihuahua",
    "iso:country":"MX",
    "wof:name":"Satevo",
    "wof:placetype":"locality"
},
  "geometry": {"coordinates":[-106.09999999999999,27.95],"type":"Point"}
}