{
  "type": "Feature",
  "properties": {
    "gn:admin1_code":"6",
    "gn:admin2_code":"61.0",
    "gn:asciiname":"Satevo",
    "gn:country_code":"MX",
    "gn:dem":1365,
    "gn:feature_class":"P",
    "gn:feature_code":"PPL",
    "gn:name":"Satev\u00f3",
    "gn:population":0,
    "gn:timezone":"America/Chihuahua",
    "iso:country":"MX",
    "name:ceb_x_preferred":[
        "Satev\u00f3"
    ],
    "name:epo_x_preferred":[
        "Satev\u00f3"
    ],
    "name:eus_x_preferred":[
        "Satev\u00f3"
    ],
    "name:ita_x_preferred":[
        "Satev\u00f3"
    ],
    "name:por_x_preferred":[
        "Satev\u00f3"
    ],
    "name:rus_x_preferred":[
        "\u0421\u0430\u0442\u0435\u0432\u043e"
    ],
    "name:sco_x_preferred":[
        "Satev\u00f3 Municipality"
    ],
    "name:srp_x_preferred":[
        "\u041e\u043f\u0448\u0442\u0438\u043d\u0430 \u0421\u0430\u0442\u0435\u0432\u043e"
    ],
    "name:swe_x_preferred":[
        "Satev\u00f3"
    ],
    "name:vie_x_preferred":[
        "Satev\u00f3"
    ],
    "wof:name":"Satevo",
    "wof:placetype":"locality"
},
  "geometry": {"coordinates":[-106.09999999999999,27.95],"type":"Point"}
}