{
  "type": "Feature",
  "properties": {
    "gn:admin1_code":"24",
    "gn:admin2_code":"3.0",
    "gn:asciiname":"Tampemoche",
    "gn:country_code":"MX",
    "gn:dem":410,
    "gn:feature_class":"P",
    "gn:feature_code":"PPL",
    "gn:name":"Tampemoche",
    "gn:population":0,
    "gn:timezone":"America/Mexico_City",
    "iso:country":"MX",
    "name:und_x_variant":[
        "Tampenoche",
        "Tampemoche"
    ],
    "wof:name":"Tampemoche",
    "wof:placetype":"locality"
},
  "geometry": {"coordinates":[-99.08174,21.68943],"type":"Point"}
}