{
  "type": "Feature",
  "properties": {
    "gn:admin1_code":"6",
    "gn:admin2_code":"59",
    "gn:asciiname":"Mateo",
    "gn:country_code":"MX",
    "gn:dem":1962,
    "gn:feature_class":"P",
    "gn:feature_code":"PPL",
    "gn:name":"Mateo",
    "gn:population":13,
    "gn:timezone":"America/Chihuahua",
    "iso:country":"MX",
    "name:ceb_x_preferred":[
        "Mateo"
    ],
    "name:deu_x_preferred":[
        "Mateo"
    ],
    "name:epo_x_preferred":[
        "Mateo"
    ],
    "name:eus_x_preferred":[
        "Mateo"
    ],
    "name:fra_x_preferred":[
        "Mateo"
    ],
    "name:glg_x_preferred":[
        "Mateo"
    ],
    "name:jpn_x_preferred":[
        "\u30de\u30c6\u30aa"
    ],
    "name:pol_x_preferred":[
        "Mateos"
    ],
    "name:rus_x_preferred":[
        "\u041c\u0430\u0442\u0435\u043e"
    ],
    "name:spa_x_preferred":[
        "Mateo"
    ],
    "name:swe_x_preferred":[
        "Mateo"
    ],
    "name:tgl_x_preferred":[
        "Mateo"
    ],
    "wof:name":"Mateo",
    "wof:placetype":"locality",
    "wof:population":13
},
  "geometry": {"coordinates":[-105.83126,26.86773],"type":"Point"}
}