{
  "type": "Feature",
  "properties": {
    "gn:admin1_code":"10",
    "gn:admin2_code":"13.0",
    "gn:asciiname":"El Pajarito",
    "gn:country_code":"MX",
    "gn:dem":1247,
    "gn:feature_class":"P",
    "gn:feature_code":"PPL",
    "gn:name":"El Pajarito",
    "gn:population":0,
    "gn:timezone":"America/Monterrey",
    "iso:country":"MX",
    "name:spa_x_preferred":[
        "El Pajarito"
    ],
    "wof:name":"El Pajarito",
    "wof:placetype":"locality"
},
  "geometry": {"coordinates":[-103.8721,25.98781],"type":"Point"}
}