{
  "type": "Feature",
  "properties": {
    "gn:admin1_code":"6.0",
    "gn:admin2_code":"20.0",
    "gn:asciiname":"Carretas",
    "gn:country_code":"MX",
    "gn:dem":1712,
    "gn:feature_class":"P",
    "gn:feature_code":"PPL",
    "gn:name":"Carretas",
    "gn:population":0,
    "gn:timezone":"America/Chihuahua",
    "iso:country":"MX",
    "name:spa_x_preferred":[
        "Carretas"
    ],
    "wof:name":"Carretas",
    "wof:placetype":"locality"
},
  "geometry": {"coordinates":[-108.57799,27.64996],"type":"Point"}
}