{
  "type": "Feature",
  "properties": {
    "gn:admin1_code":"6.0",
    "gn:admin2_code":"7.0",
    "gn:asciiname":"Mesa del Maguey",
    "gn:country_code":"MX",
    "gn:dem":2679,
    "gn:feature_class":"P",
    "gn:feature_code":"PPL",
    "gn:name":"Mesa del Maguey",
    "gn:population":0,
    "gn:timezone":"America/Monterrey",
    "iso:country":"MX",
    "name:spa_x_preferred":[
        "Mesa del Maguey"
    ],
    "wof:name":"Mesa del Maguey",
    "wof:placetype":"locality"
},
  "geometry": {"coordinates":[-106.33620999999999,26.33686],"type":"Point"}
}