{
  "type": "Feature",
  "properties": {
    "gn:admin1_code":"24.0",
    "gn:admin2_code":"32.0",
    "gn:asciiname":"Puerto Hondo",
    "gn:country_code":"MX",
    "gn:dem":2197,
    "gn:feature_class":"P",
    "gn:feature_code":"PPL",
    "gn:name":"Puerto Hondo",
    "gn:population":0,
    "gn:timezone":"America/Mexico_City",
    "iso:country":"MX",
    "name:spa_x_preferred":[
        "Puerto Hondo"
    ],
    "wof:name":"Puerto Hondo",
    "wof:placetype":"locality"
},
  "geometry": {"coordinates":[-100.43543,21.87104],"type":"Point"}
}