{
  "type": "Feature",
  "properties": {
    "gn:admin1_code":"7",
    "gn:admin2_code":"4.0",
    "gn:asciiname":"Los Lirios",
    "gn:country_code":"MX",
    "gn:dem":2342,
    "gn:feature_class":"P",
    "gn:feature_code":"PPL",
    "gn:name":"Los Lirios",
    "gn:population":561,
    "gn:timezone":"America/Monterrey",
    "iso:country":"MX",
    "name:spa_x_preferred":[
        "Los Lirios"
    ],
    "wof:name":"Los Lirios",
    "wof:placetype":"locality",
    "wof:population":561
},
  "geometry": {"coordinates":[-100.58795000000001,25.39377],"type":"Point"}
}