{
  "type": "Feature",
  "properties": {
    "gn:admin1_code":"25",
    "gn:admin2_code":"4.0",
    "gn:asciiname":"Los Vasitos",
    "gn:country_code":"MX",
    "gn:dem":380,
    "gn:feature_class":"P",
    "gn:feature_code":"PPL",
    "gn:name":"Los Vasitos",
    "gn:population":0,
    "gn:timezone":"America/Mazatlan",
    "iso:country":"MX",
    "name:spa_x_preferred":[
        "Los Vasitos"
    ],
    "wof:name":"Los Vasitos",
    "wof:placetype":"locality"
},
  "geometry": {"coordinates":[-105.97723000000001,23.59963],"type":"Point"}
}