{
  "type": "Feature",
  "properties": {
    "gn:admin1_code":"19.0",
    "gn:admin2_code":"32.0",
    "gn:asciiname":"El Tortillero",
    "gn:cc2":"MX",
    "gn:country_code":"MX",
    "gn:dem":281,
    "gn:feature_class":"P",
    "gn:feature_code":"PPL",
    "gn:name":"El Tortillero",
    "gn:population":0,
    "gn:timezone":"America/Monterrey",
    "iso:country":"MX",
    "name:und_x_variant":[
        "Tortillero",
        "El Tortillero"
    ],
    "wof:name":"El Tortillero",
    "wof:placetype":"locality"
},
  "geometry": {"coordinates":[-100.61667,27.13333],"type":"Point"}
}