{
  "type": "Feature",
  "properties": {
    "gn:admin1_code":"6.0",
    "gn:admin2_code":"40.0",
    "gn:asciiname":"El Espinazo del Diablo",
    "gn:country_code":"MX",
    "gn:dem":1909,
    "gn:feature_class":"P",
    "gn:feature_code":"PPL",
    "gn:name":"El Espinazo del Diablo",
    "gn:population":0,
    "gn:timezone":"America/Chihuahua",
    "iso:country":"MX",
    "name:spa_x_preferred":[
        "El Espinazo del Diablo"
    ],
    "wof:name":"El Espinazo del Diablo",
    "wof:placetype":"locality"
},
  "geometry": {"coordinates":[-108.35596,28.84054],"type":"Point"}
}