{
  "type": "Feature",
  "properties": {
    "gn:admin1_code":"5",
    "gn:admin2_code":"16.0",
    "gn:asciiname":"El Pajonal",
    "gn:country_code":"MX",
    "gn:dem":7,
    "gn:feature_class":"P",
    "gn:feature_code":"PPL",
    "gn:name":"El Pajonal",
    "gn:population":299,
    "gn:timezone":"America/Mexico_City",
    "iso:country":"MX",
    "wof:name":"El Pajonal",
    "wof:placetype":"locality",
    "wof:population":299
},
  "geometry": {"coordinates":[-92.01278000000001,17.75417000000001],"type":"Point"}
}