{
  "type": "Feature",
  "properties": {
    "gn:admin1_code":"14.0",
    "gn:asciiname":"Penas Altas",
    "gn:country_code":"MX",
    "gn:dem":1862,
    "gn:feature_class":"P",
    "gn:feature_code":"PPL",
    "gn:name":"Pe\u00f1as Altas",
    "gn:population":0,
    "gn:timezone":"America/Mexico_City",
    "iso:country":"MX",
    "name:spa_x_preferred":[
        "Pe\u00f1as Altas"
    ],
    "wof:name":"Penas Altas",
    "wof:placetype":"locality"
},
  "geometry": {"coordinates":[-102.05086,20.91785],"type":"Point"}
}