{
  "type": "Feature",
  "properties": {
    "gn:admin1_code":"32",
    "gn:admin2_code":"34.0",
    "gn:asciiname":"El Cedro",
    "gn:country_code":"MX",
    "gn:dem":2060,
    "gn:feature_class":"P",
    "gn:feature_code":"PPL",
    "gn:name":"El Cedro",
    "gn:population":6,
    "gn:timezone":"America/Mexico_City",
    "iso:country":"MX",
    "name:ceb_x_preferred":[
        "El Cedro"
    ],
    "name:fra_x_preferred":[
        "El Cedro"
    ],
    "name:ita_x_preferred":[
        "El Cedro"
    ],
    "name:spa_x_preferred":[
        "El Cedro"
    ],
    "name:swe_x_preferred":[
        "El Cedro"
    ],
    "wof:name":"El Cedro",
    "wof:placetype":"locality",
    "wof:population":6
},
  "geometry": {"coordinates":[-102.82389000000001,21.54056],"type":"Point"}
}