{
  "type": "Feature",
  "properties": {
    "gn:admin1_code":"23",
    "gn:admin2_code":"4.0",
    "gn:asciiname":"Nuevo Hoctun",
    "gn:country_code":"MX",
    "gn:dem":53,
    "gn:feature_class":"P",
    "gn:feature_code":"PPL",
    "gn:name":"Nuevo Hoct\u00fan",
    "gn:population":0,
    "gn:timezone":"America/Cancun",
    "iso:country":"MX",
    "name:spa_x_preferred":[
        "Nuevo Hoct\u00fan"
    ],
    "name:und_x_variant":[
        "Nuevo Hoctum"
    ],
    "wof:name":"Nuevo Hoctun",
    "wof:placetype":"locality"
},
  "geometry": {"coordinates":[-88.72126999999998,19.07545],"type":"Point"}
}