{
  "type": "Feature",
  "properties": {
    "gn:admin1_code":"19.0",
    "gn:asciiname":"Casa Roja",
    "gn:country_code":"MX",
    "gn:dem":421,
    "gn:feature_class":"P",
    "gn:feature_code":"PPL",
    "gn:name":"Casa Roja",
    "gn:population":0,
    "gn:timezone":"America/Monterrey",
    "iso:country":"MX",
    "name:spa_x_preferred":[
        "Casa Roja"
    ],
    "wof:name":"Casa Roja",
    "wof:placetype":"locality"
},
  "geometry": {"coordinates":[-100.22046,25.91656],"type":"Point"}
}