{
  "type": "Feature",
  "properties": {
    "gn:admin1_code":"28",
    "gn:admin2_code":"23.0",
    "gn:asciiname":"La Nutria",
    "gn:country_code":"MX",
    "gn:dem":61,
    "gn:feature_class":"P",
    "gn:feature_code":"PPL",
    "gn:name":"La Nutria",
    "gn:population":0,
    "gn:timezone":"America/Monterrey",
    "iso:country":"MX",
    "name:und_x_variant":[
        "Rancho La Nutria",
        "La Nutria"
    ],
    "wof:name":"La Nutria",
    "wof:placetype":"locality"
},
  "geometry": {"coordinates":[-98.22206,25.38414],"type":"Point"}
}