{
  "type": "Feature",
  "properties": {
    "gn:admin1_code":"10",
    "gn:admin2_code":"17.0",
    "gn:asciiname":"Cerrito Prieto",
    "gn:country_code":"MX",
    "gn:dem":1717,
    "gn:feature_class":"P",
    "gn:feature_code":"PPL",
    "gn:name":"Cerrito Prieto",
    "gn:population":4,
    "gn:timezone":"America/Monterrey",
    "iso:country":"MX",
    "wof:name":"Cerrito Prieto",
    "wof:placetype":"locality",
    "wof:population":4
},
  "geometry": {"coordinates":[-105.38818000000001,26.41052],"type":"Point"}
}