{
  "type": "Feature",
  "properties": {
    "gn:admin1_code":"14",
    "gn:admin2_code":"103",
    "gn:asciiname":"Ejido Poblado Juan Barragan",
    "gn:country_code":"MX",
    "gn:dem":1532,
    "gn:feature_class":"P",
    "gn:feature_code":"PPL",
    "gn:name":"Ejido Poblado Juan Barrag\u00e1n",
    "gn:population":51,
    "gn:timezone":"America/Mexico_City",
    "iso:country":"MX",
    "name:und_x_variant":[
        "Ejido Poblado Juan Barrag\u00e1n"
    ],
    "wof:name":"Ejido Poblado Juan Barragan",
    "wof:placetype":"locality",
    "wof:population":51
},
  "geometry": {"coordinates":[-103.53389,19.48056],"type":"Point"}
}