{
  "type": "Feature",
  "properties": {
    "gn:admin1_code":"14",
    "gn:admin2_code":"80.0",
    "gn:asciiname":"Colimilla",
    "gn:country_code":"MX",
    "gn:dem":959,
    "gn:feature_class":"P",
    "gn:feature_code":"PPL",
    "gn:name":"Colimilla",
    "gn:population":61,
    "gn:timezone":"America/Mexico_City",
    "iso:country":"MX",
    "wof:name":"Colimilla",
    "wof:placetype":"locality",
    "wof:population":61
},
  "geometry": {"coordinates":[-104.92028000000001,20.76806],"type":"Point"}
}