{
  "type": "Feature",
  "properties": {
    "gn:admin1_code":"7",
    "gn:admin2_code":"11.0",
    "gn:asciiname":"Macuyu",
    "gn:country_code":"MX",
    "gn:dem":1575,
    "gn:feature_class":"P",
    "gn:feature_code":"PPL",
    "gn:name":"Macuy\u00fa",
    "gn:population":0,
    "gn:timezone":"America/Monterrey",
    "iso:country":"MX",
    "wof:name":"Macuyu",
    "wof:placetype":"locality"
},
  "geometry": {"coordinates":[-101.64688,25.35745],"type":"Point"}
}