{
  "type": "Feature",
  "properties": {
    "gn:admin1_code":"10",
    "gn:admin2_code":"19",
    "gn:asciiname":"El Carrizo",
    "gn:country_code":"MX",
    "gn:dem":2096,
    "gn:feature_class":"P",
    "gn:feature_code":"PPL",
    "gn:name":"El Carrizo",
    "gn:population":14,
    "gn:timezone":"America/Monterrey",
    "iso:country":"MX",
    "wof:name":"El Carrizo",
    "wof:placetype":"locality",
    "wof:population":14
},
  "geometry": {"coordinates":[-106.02033,24.62305],"type":"Point"}
}