{
  "type": "Feature",
  "properties": {
    "gn:admin1_code":"30",
    "gn:admin2_code":"109",
    "gn:asciiname":"Santa Teresa (Kilometro 2)",
    "gn:country_code":"MX",
    "gn:dem":310,
    "gn:feature_class":"P",
    "gn:feature_code":"PPL",
    "gn:name":"Santa Teresa (Kil\u00f3metro 2)",
    "gn:population":17,
    "gn:timezone":"America/Mexico_City",
    "iso:country":"MX",
    "name:und_x_variant":[
        "Santa Teresa (Kil\u00f3metro 2)"
    ],
    "wof:name":"Santa Teresa (Kilometro 2)",
    "wof:placetype":"locality",
    "wof:population":17
},
  "geometry": {"coordinates":[-96.92417,19.95472],"type":"Point"}
}