{
  "type": "Feature",
  "properties": {
    "gn:admin1_code":"26",
    "gn:admin2_code":"30.0",
    "gn:asciiname":"El Cuatro",
    "gn:country_code":"MX",
    "gn:dem":309,
    "gn:feature_class":"P",
    "gn:feature_code":"PPL",
    "gn:name":"El Cuatro",
    "gn:population":0,
    "gn:timezone":"America/Hermosillo",
    "iso:country":"MX",
    "name:spa_x_preferred":[
        "El Cuatro"
    ],
    "wof:name":"El Cuatro",
    "wof:placetype":"locality"
},
  "geometry": {"coordinates":[-110.60722,29.20806],"type":"Point"}
}