{
  "type": "Feature",
  "properties": {
    "gn:admin1_code":"6.0",
    "gn:admin2_code":"11.0",
    "gn:asciiname":"Ejido Division del Norte",
    "gn:country_code":"MX",
    "gn:dem":1351,
    "gn:feature_class":"P",
    "gn:feature_code":"PPL",
    "gn:name":"Ejido Divisi\u00f3n del Norte",
    "gn:population":0,
    "gn:timezone":"America/Chihuahua",
    "iso:country":"MX",
    "name:spa_x_preferred":[
        "Ejido Divisi\u00f3n del Norte"
    ],
    "name:spa_x_variant":[
        "Divisi\u00f3n del Norte"
    ],
    "wof:name":"Ejido Division del Norte",
    "wof:placetype":"locality"
},
  "geometry": {"coordinates":[-104.7178,27.71873],"type":"Point"}
}