{
  "type": "Feature",
  "properties": {
    "gn:admin1_code":"24",
    "gn:admin2_code":"20.0",
    "gn:asciiname":"El Tlacuache",
    "gn:country_code":"MX",
    "gn:dem":1552,
    "gn:feature_class":"P",
    "gn:feature_code":"PPL",
    "gn:name":"El Tlacuache",
    "gn:population":7,
    "gn:timezone":"America/Mexico_City",
    "iso:country":"MX",
    "wof:name":"El Tlacuache",
    "wof:placetype":"locality",
    "wof:population":7
},
  "geometry": {"coordinates":[-100.54722,23.69111],"type":"Point"}
}