{
  "type": "Feature",
  "properties": {
    "gn:admin1_code":"12",
    "gn:admin2_code":"52.0",
    "gn:asciiname":"Horcasitas",
    "gn:country_code":"MX",
    "gn:dem":360,
    "gn:feature_class":"P",
    "gn:feature_code":"PPL",
    "gn:name":"Horcasitas",
    "gn:population":0,
    "gn:timezone":"America/Mexico_City",
    "iso:country":"MX",
    "name:spa_x_preferred":[
        "Atotonilco de Horcasitas"
    ],
    "name:und_x_variant":[
        "Iorcasitas"
    ],
    "wof:name":"Horcasitas",
    "wof:placetype":"locality"
},
  "geometry": {"coordinates":[-98.74609,16.88821],"type":"Point"}
}