{
  "type": "Feature",
  "properties": {
    "gn:admin1_code":"30.0",
    "gn:admin2_code":"160.0",
    "gn:asciiname":"Cerro de Horcones",
    "gn:country_code":"MX",
    "gn:dem":240,
    "gn:feature_class":"P",
    "gn:feature_code":"PPL",
    "gn:name":"Cerro de Horcones",
    "gn:population":132,
    "gn:timezone":"America/Mexico_City",
    "iso:country":"MX",
    "name:spa_x_preferred":[
        "Cerro de Horcones"
    ],
    "wof:name":"Cerro de Horcones",
    "wof:placetype":"locality",
    "wof:population":132
},
  "geometry": {"coordinates":[-97.81278,21.08056],"type":"Point"}
}