{
  "type": "Feature",
  "properties": {
    "gn:admin1_code":"2",
    "gn:admin2_code":"2.0",
    "gn:asciiname":"Islas Agrarias Grupo B",
    "gn:country_code":"MX",
    "gn:dem":11,
    "gn:feature_class":"P",
    "gn:feature_code":"PPL",
    "gn:name":"Islas Agrarias Grupo B",
    "gn:population":0,
    "gn:timezone":"America/Tijuana",
    "iso:country":"MX",
    "name:spa_x_preferred":[
        "Islas Agrarias Grupo B"
    ],
    "name:und_x_variant":[
        "Islas Agrarias-B"
    ],
    "wof:name":"Islas Agrarias Grupo B",
    "wof:placetype":"locality"
},
  "geometry": {"coordinates":[-115.27172,32.60034],"type":"Point"}
}