{
  "type": "Feature",
  "properties": {
    "gn:admin1_code":"24",
    "gn:admin2_code":"24",
    "gn:asciiname":"Las Presitas",
    "gn:country_code":"MX",
    "gn:dem":1215,
    "gn:feature_class":"P",
    "gn:feature_code":"PPL",
    "gn:name":"Las Presitas",
    "gn:population":11,
    "gn:timezone":"America/Mexico_City",
    "iso:country":"MX",
    "wof:name":"Las Presitas",
    "wof:placetype":"locality",
    "wof:population":11
},
  "geometry": {"coordinates":[-100.07861,21.82361],"type":"Point"}
}