{
  "type": "Feature",
  "properties": {
    "gn:admin1_code":"21",
    "gn:admin2_code":"41.0",
    "gn:asciiname":"San Diego los Sauces",
    "gn:country_code":"MX",
    "gn:dem":2159,
    "gn:feature_class":"P",
    "gn:feature_code":"PPL",
    "gn:name":"San Diego los Sauces",
    "gn:population":595,
    "gn:timezone":"America/Mexico_City",
    "iso:country":"MX",
    "wof:name":"San Diego los Sauces",
    "wof:placetype":"locality",
    "wof:population":595
},
  "geometry": {"coordinates":[-98.29443999999999,19.08],"type":"Point"}
}