{
  "type": "Feature",
  "properties": {
    "iso:country":"MX",
    "qs_pg:aaroncc":"MX",
    "qs_pg:name":"Teotihuacan de Arista",
    "qs_pg:name_adm0":"M\u00e9xico",
    "qs_pg:name_adm1":"Mexico",
    "qs_pg:photos":146,
    "qs_pg:photos_1k":30,
    "qs_pg:photos_9k":33,
    "qs_pg:photos_9r":15,
    "qs_pg:photos_all":7532,
    "qs_pg:photos_sr":3,
    "qs_pg:pop_sr":0,
    "qs_pg:qs_pg_placetype":"locality",
    "qs_pg:qs_pg_placetype_gp":"Town",
    "qs_pg:woe_adm0":23424900,
    "woe:adm0_id":23424900,
    "woe:name_adm0":"M\u00e9xico",
    "woe:name_adm1":"Mexico",
    "woe:placetype":"Town",
    "wof:name":"Teotihuacan de Arista",
    "wof:placetype":"locality"
},
  "geometry": {"coordinates":[-98.844251,19.695725],"type":"Point"}
}