{
  "type": "Feature",
  "properties": {
    "gn:admin1_code":"30.0",
    "gn:admin2_code":"121.0",
    "gn:asciiname":"Los Olivos",
    "gn:country_code":"MX",
    "gn:dem":66,
    "gn:feature_class":"P",
    "gn:feature_code":"PPL",
    "gn:name":"Los Olivos",
    "gn:population":7,
    "gn:timezone":"America/Mexico_City",
    "iso:country":"MX",
    "name:spa_x_preferred":[
        "Los Olivos"
    ],
    "wof:name":"Los Olivos",
    "wof:placetype":"locality",
    "wof:population":7
},
  "geometry": {"coordinates":[-97.88949,21.46274],"type":"Point"}
}