{
  "type": "Feature",
  "properties": {
    "gn:admin1_code":"12",
    "gn:admin2_code":"16.0",
    "gn:asciiname":"Gallo de Maciel",
    "gn:country_code":"MX",
    "gn:dem":178,
    "gn:feature_class":"P",
    "gn:feature_code":"PPL",
    "gn:name":"Gallo de Maciel",
    "gn:population":69,
    "gn:timezone":"America/Mexico_City",
    "iso:country":"MX",
    "wof:name":"Gallo de Maciel",
    "wof:placetype":"locality",
    "wof:population":69
},
  "geometry": {"coordinates":[-101.83687999999999,18.41932000000001],"type":"Point"}
}