{
  "type": "Feature",
  "properties": {
    "gn:admin1_code":"28",
    "gn:admin2_code":"33.0",
    "gn:asciiname":"El Olmito",
    "gn:cc2":"MX",
    "gn:country_code":"MX",
    "gn:dem":26,
    "gn:feature_class":"P",
    "gn:feature_code":"PPL",
    "gn:name":"El Olmito",
    "gn:population":2,
    "gn:timezone":"America/Monterrey",
    "iso:country":"MX",
    "name:und_x_variant":[
        "Olmitos",
        "El Olmito"
    ],
    "wof:name":"El Olmito",
    "wof:placetype":"locality",
    "wof:population":2
},
  "geometry": {"coordinates":[-98.06278,26.01389],"type":"Point"}
}