{
  "type": "Feature",
  "properties": {
    "gn:admin1_code":"14",
    "gn:admin2_code":"93",
    "gn:asciiname":"Piedra Blanca",
    "gn:country_code":"MX",
    "gn:dem":1982,
    "gn:feature_class":"P",
    "gn:feature_code":"PPL",
    "gn:name":"Piedra Blanca",
    "gn:population":46,
    "gn:timezone":"America/Mexico_City",
    "iso:country":"MX",
    "wof:name":"Piedra Blanca",
    "wof:placetype":"locality",
    "wof:population":46
},
  "geometry": {"coordinates":[-102.69194,20.91972],"type":"Point"}
}