{
  "type": "Feature",
  "properties": {
    "gn:admin1_code":"30",
    "gn:admin2_code":"174.0",
    "gn:asciiname":"San Nicolas",
    "gn:country_code":"MX",
    "gn:dem":27,
    "gn:feature_class":"P",
    "gn:feature_code":"PPL",
    "gn:name":"San Nicol\u00e1s",
    "gn:population":0,
    "gn:timezone":"America/Mexico_City",
    "iso:country":"MX",
    "name:spa_x_preferred":[
        "San Nicol\u00e1s"
    ],
    "name:spa_x_variant":[
        "La Burrera"
    ],
    "wof:name":"San Nicolas",
    "wof:placetype":"locality"
},
  "geometry": {"coordinates":[-96.14249,18.43613],"type":"Point"}
}