{
  "type": "Feature",
  "properties": {
    "gn:admin1_code":"32.0",
    "gn:asciiname":"Tanque de Guadalupe",
    "gn:country_code":"MX",
    "gn:dem":2009,
    "gn:feature_class":"P",
    "gn:feature_code":"PPL",
    "gn:name":"Tanque de Guadalupe",
    "gn:population":0,
    "gn:timezone":"America/Mexico_City",
    "iso:country":"MX",
    "name:spa_x_preferred":[
        "Tanque de Guadalupe"
    ],
    "wof:name":"Tanque de Guadalupe",
    "wof:placetype":"locality"
},
  "geometry": {"coordinates":[-101.29581,23.86499],"type":"Point"}
}