{
  "type": "Feature",
  "properties": {
    "gn:admin1_code":"6.0",
    "gn:admin2_code":"11.0",
    "gn:asciiname":"El Molino",
    "gn:country_code":"MX",
    "gn:dem":1288,
    "gn:feature_class":"P",
    "gn:feature_code":"PPL",
    "gn:name":"El Molino",
    "gn:population":0,
    "gn:timezone":"America/Chihuahua",
    "iso:country":"MX",
    "name:spa_x_preferred":[
        "El Molino"
    ],
    "wof:name":"El Molino",
    "wof:placetype":"locality"
},
  "geometry": {"coordinates":[-104.93348,27.51236],"type":"Point"}
}