{
  "type": "Feature",
  "properties": {
    "gn:admin1_code":"2",
    "gn:admin2_code":"1",
    "gn:asciiname":"Las Cuatas",
    "gn:country_code":"MX",
    "gn:dem":781,
    "gn:feature_class":"P",
    "gn:feature_code":"PPL",
    "gn:name":"Las Cuatas",
    "gn:population":10,
    "gn:timezone":"America/Tijuana",
    "iso:country":"MX",
    "wof:name":"Las Cuatas",
    "wof:placetype":"locality",
    "wof:population":10
},
  "geometry": {"coordinates":[-115.73888999999998,31.39917],"type":"Point"}
}