{
  "type": "Feature",
  "properties": {
    "gn:admin1_code":"16",
    "gn:admin2_code":"83",
    "gn:asciiname":"El Granado",
    "gn:country_code":"MX",
    "gn:dem":1774,
    "gn:feature_class":"P",
    "gn:feature_code":"PPL",
    "gn:name":"El Granado",
    "gn:population":10,
    "gn:timezone":"America/Mexico_City",
    "iso:country":"MX",
    "name:ara_x_preferred":[
        "\u0625\u0644 \u063a\u0631\u0627\u0646\u062f\u0648"
    ],
    "name:ast_x_preferred":[
        "El Gran\u00e1u"
    ],
    "name:bul_x_preferred":[
        "\u0413\u0440\u0430\u043d\u0430\u0434\u043e"
    ],
    "name:cat_x_preferred":[
        "El Granado"
    ],
    "name:ceb_x_preferred":[
        "El Granado"
    ],
    "name:epo_x_preferred":[
        "El Granado"
    ],
    "name:eus_x_preferred":[
        "El Granado"
    ],
    "name:fra_x_preferred":[
        "El Granado"
    ],
    "name:hat_x_preferred":[
        "El Granado"
    ],
    "name:hun_x_preferred":[
        "El Granado"
    ],
    "name:hye_x_preferred":[
        "\u0537\u056c \u0533\u0580\u0561\u0576\u0561\u0564\u0578"
    ],
    "name:ita_x_preferred":[
        "El Granado"
    ],
    "name:kaz_x_preferred":[
        "\u042d\u043b\u044c-\u0413\u0440\u0430\u043d\u0430\u0434\u043e"
    ],
    "name:lad_x_preferred":[
        "El Granado"
    ],
    "name:msa_x_preferred":[
        "El Granado"
    ],
    "name:nld_x_preferred":[
        "El Granado"
    ],
    "name:oci_x_preferred":[
        "El Granado"
    ],
    "name:pol_x_preferred":[
        "Granado"
    ],
    "name:por_x_preferred":[
        "El Granado"
    ],
    "name:rus_x_preferred":[
        "\u042d\u043b\u044c-\u0413\u0440\u0430\u043d\u0430\u0434\u043e"
    ],
    "name:spa_x_preferred":[
        "El Granado"
    ],
    "name:tur_x_preferred":[
        "El Granado"
    ],
    "name:ukr_x_preferred":[
        "\u0415\u043b\u044c-\u0413\u0440\u0430\u043d\u0430\u0434\u043e"
    ],
    "name:uzb_x_preferred":[
        "El Granado"
    ],
    "name:vie_x_preferred":[
        "El Granado"
    ],
    "name:war_x_preferred":[
        "El Granado"
    ],
    "name:zho_x_preferred":[
        "\u57c3\u5c14\u683c\u62c9\u7eb3\u591a"
    ],
    "wof:name":"El Granado",
    "wof:placetype":"locality",
    "wof:population":10
},
  "geometry": {"coordinates":[-102.25944,19.25389],"type":"Point"}
}