{
  "type": "Feature",
  "properties": {
    "gn:admin1_code":"16",
    "gn:admin2_code":"83",
    "gn:asciiname":"El Granado",
    "gn:country_code":"MX",
    "gn:dem":1774,
    "gn:feature_class":"P",
    "gn:feature_code":"PPL",
    "gn:name":"El Granado",
    "gn:population":10,
    "gn:timezone":"America/Mexico_City",
    "iso:country":"MX",
    "wof:name":"El Granado",
    "wof:placetype":"locality",
    "wof:population":10
},
  "geometry": {"coordinates":[-102.25944,19.25389],"type":"Point"}
}