{
  "type": "Feature",
  "properties": {
    "gn:admin1_code":"28",
    "gn:admin2_code":"24.0",
    "gn:asciiname":"El Rameno",
    "gn:country_code":"MX",
    "gn:dem":82,
    "gn:feature_class":"P",
    "gn:feature_code":"PPL",
    "gn:name":"El Rame\u00f1o",
    "gn:population":0,
    "gn:timezone":"America/Monterrey",
    "iso:country":"MX",
    "name:spa_x_preferred":[
        "El Rame\u00f1o"
    ],
    "name:und_x_variant":[
        "Rancho El Rame\u00f1o"
    ],
    "wof:name":"El Rameno",
    "wof:placetype":"locality"
},
  "geometry": {"coordinates":[-99.23349,26.40962],"type":"Point"}
}