{
  "type": "Feature",
  "properties": {
    "gn:admin1_code":"3",
    "gn:admin2_code":"2.0",
    "gn:asciiname":"El Toribio",
    "gn:country_code":"MX",
    "gn:dem":794,
    "gn:feature_class":"P",
    "gn:feature_code":"PPL",
    "gn:name":"El Toribio",
    "gn:population":0,
    "gn:timezone":"America/Mazatlan",
    "iso:country":"MX",
    "name:spa_x_preferred":[
        "El Toribio"
    ],
    "wof:name":"El Toribio",
    "wof:placetype":"locality"
},
  "geometry": {"coordinates":[-112.12735000000001,26.62259],"type":"Point"}
}