{
  "type": "Feature",
  "properties": {
    "gn:admin1_code":"32",
    "gn:admin2_code":"49.0",
    "gn:asciiname":"El Terrero",
    "gn:country_code":"MX",
    "gn:dem":1812,
    "gn:feature_class":"P",
    "gn:feature_code":"PPL",
    "gn:name":"El Terrero",
    "gn:population":6,
    "gn:timezone":"America/Mexico_City",
    "iso:country":"MX",
    "wof:name":"El Terrero",
    "wof:placetype":"locality",
    "wof:population":6
},
  "geometry": {"coordinates":[-103.81583000000001,22.57944],"type":"Point"}
}