{
  "type": "Feature",
  "properties": {
    "gn:admin1_code":"6",
    "gn:admin2_code":"29.0",
    "gn:asciiname":"Barbechitos",
    "gn:country_code":"MX",
    "gn:dem":2265,
    "gn:feature_class":"P",
    "gn:feature_code":"PPL",
    "gn:name":"Barbechitos",
    "gn:population":378,
    "gn:timezone":"America/Chihuahua",
    "iso:country":"MX",
    "wof:name":"Barbechitos",
    "wof:placetype":"locality",
    "wof:population":378
},
  "geometry": {"coordinates":[-107.02388999999999,26.4125],"type":"Point"}
}