{
  "type": "Feature",
  "properties": {
    "gn:admin1_code":"6",
    "gn:admin2_code":"12.0",
    "gn:asciiname":"Molinares",
    "gn:country_code":"MX",
    "gn:dem":2538,
    "gn:feature_class":"P",
    "gn:feature_code":"PPL",
    "gn:name":"Molinares",
    "gn:population":53,
    "gn:timezone":"America/Chihuahua",
    "iso:country":"MX",
    "wof:name":"Molinares",
    "wof:placetype":"locality",
    "wof:population":53
},
  "geometry": {"coordinates":[-107.34744000000001,27.9542],"type":"Point"}
}