{
  "type": "Feature",
  "properties": {
    "gn:admin1_code":"24",
    "gn:admin2_code":"15.0",
    "gn:asciiname":"Aquiles Serdan",
    "gn:country_code":"MX",
    "gn:dem":1974,
    "gn:feature_class":"P",
    "gn:feature_code":"PPL",
    "gn:name":"Aquiles Serd\u00e1n",
    "gn:population":0,
    "gn:timezone":"America/Mexico_City",
    "iso:country":"MX",
    "name:spa_x_preferred":[
        "Aquiles Serd\u00e1n"
    ],
    "wof:name":"Aquiles Serdan",
    "wof:placetype":"locality"
},
  "geometry": {"coordinates":[-100.92552000000001,23.28482],"type":"Point"}
}