{
  "type": "Feature",
  "properties": {
    "gn:admin1_code":"1.0",
    "gn:admin2_code":"4.0",
    "gn:asciiname":"Cosio",
    "gn:country_code":"MX",
    "gn:dem":2005,
    "gn:feature_class":"P",
    "gn:feature_code":"PPL",
    "gn:name":"Cos\u00edo",
    "gn:population":0,
    "gn:timezone":"America/Mexico_City",
    "iso:country":"MX",
    "name:ind_x_preferred":[
        "Cos\u00edo"
    ],
    "name:pol_x_preferred":[
        "Cos\u00edo"
    ],
    "name:rus_x_preferred":[
        "\u041a\u043e\u0441\u0438\u043e"
    ],
    "name:sco_x_preferred":[
        "Cos\u00edo"
    ],
    "name:srp_x_preferred":[
        "\u041a\u043e\u0441\u0438\u043e"
    ],
    "name:und_x_variant":[
        "Cos\u00edo"
    ],
    "wof:name":"Cosio",
    "wof:placetype":"locality"
},
  "geometry": {"coordinates":[-102.30117,22.36627],"type":"Point"}
}