{
  "type": "Feature",
  "properties": {
    "gn:admin1_code":"24",
    "gn:admin2_code":"37",
    "gn:asciiname":"Jeremias Lopez Hervert",
    "gn:country_code":"MX",
    "gn:dem":215,
    "gn:feature_class":"P",
    "gn:feature_code":"PPL",
    "gn:name":"Jerem\u00edas L\u00f3pez Hervert",
    "gn:population":12,
    "gn:timezone":"America/Mexico_City",
    "iso:country":"MX",
    "name:und_x_variant":[
        "Jerem\u00edas L\u00f3pez Hervert"
    ],
    "wof:name":"Jeremias Lopez Hervert",
    "wof:placetype":"locality",
    "wof:population":12
},
  "geometry": {"coordinates":[-98.79889,21.26139],"type":"Point"}
}