{
  "type": "Feature",
  "properties": {
    "gn:admin1_code":"7",
    "gn:admin2_code":"23.0",
    "gn:asciiname":"Rancho Las Pacas",
    "gn:country_code":"MX",
    "gn:dem":1616,
    "gn:feature_class":"P",
    "gn:feature_code":"PPL",
    "gn:name":"Rancho Las Pacas",
    "gn:population":0,
    "gn:timezone":"America/Monterrey",
    "iso:country":"MX",
    "wof:name":"Rancho Las Pacas",
    "wof:placetype":"locality"
},
  "geometry": {"coordinates":[-102.59999999999999,27.33333],"type":"Point"}
}