{
  "type": "Feature",
  "properties": {
    "gn:admin1_code":"10.0",
    "gn:admin2_code":"35.0",
    "gn:asciiname":"Yesqueros",
    "gn:country_code":"MX",
    "gn:dem":2445,
    "gn:feature_class":"P",
    "gn:feature_code":"PPL",
    "gn:name":"Yesqueros",
    "gn:population":0,
    "gn:timezone":"America/Monterrey",
    "iso:country":"MX",
    "name:spa_x_preferred":[
        "Yesqueros"
    ],
    "wof:name":"Yesqueros",
    "wof:placetype":"locality"
},
  "geometry": {"coordinates":[-106.40231,25.54923],"type":"Point"}
}