{
  "type": "Feature",
  "properties": {
    "gn:admin1_code":"11",
    "gn:admin2_code":"20",
    "gn:asciiname":"La Guadalupana (La Virgencita)",
    "gn:country_code":"MX",
    "gn:dem":1779,
    "gn:feature_class":"P",
    "gn:feature_code":"PPL",
    "gn:name":"La Guadalupana (La Virgencita)",
    "gn:population":25,
    "gn:timezone":"America/Mexico_City",
    "iso:country":"MX",
    "wof:name":"La Guadalupana (La Virgencita)",
    "wof:placetype":"locality",
    "wof:population":25
},
  "geometry": {"coordinates":[-101.71306,21.0625],"type":"Point"}
}