{
  "type": "Feature",
  "properties": {
    "gn:admin1_code":"12.0",
    "gn:asciiname":"Tlahuitepec Dos",
    "gn:country_code":"MX",
    "gn:dem":1198,
    "gn:feature_class":"P",
    "gn:feature_code":"PPL",
    "gn:name":"Tlahuitepec Dos",
    "gn:population":0,
    "gn:timezone":"America/Mexico_City",
    "iso:country":"MX",
    "name:spa_x_preferred":[
        "Tlahuitepec Dos"
    ],
    "wof:name":"Tlahuitepec Dos",
    "wof:placetype":"locality"
},
  "geometry": {"coordinates":[-98.63957000000001,17.00663],"type":"Point"}
}