{
  "type": "Feature",
  "properties": {
    "gn:admin1_code":"13",
    "gn:admin2_code":"28.0",
    "gn:asciiname":"Achichipil",
    "gn:country_code":"MX",
    "gn:dem":97,
    "gn:feature_class":"P",
    "gn:feature_code":"PPL",
    "gn:name":"Achich\u00edpil",
    "gn:population":194,
    "gn:timezone":"America/Mexico_City",
    "iso:country":"MX",
    "name:spa_x_preferred":[
        "Achichipil"
    ],
    "wof:name":"Achichipil",
    "wof:placetype":"locality",
    "wof:population":194
},
  "geometry": {"coordinates":[-98.50781000000001,21.21052],"type":"Point"}
}