{
  "type": "Feature",
  "properties": {
    "gn:admin1_code":"17",
    "gn:admin2_code":"1",
    "gn:asciiname":"Colonia Ampliacion Cuauhtemoc",
    "gn:country_code":"MX",
    "gn:dem":919,
    "gn:feature_class":"P",
    "gn:feature_code":"PPL",
    "gn:name":"Colonia Ampliaci\u00f3n Cuauht\u00e9moc",
    "gn:population":11,
    "gn:timezone":"America/Mexico_City",
    "iso:country":"MX",
    "name:und_x_variant":[
        "Colonia Ampliaci\u00f3n Cuauht\u00e9moc"
    ],
    "wof:name":"Colonia Ampliacion Cuauhtemoc",
    "wof:placetype":"locality",
    "wof:population":11
},
  "geometry": {"coordinates":[-99.34667,18.60778],"type":"Point"}
}