{
  "type": "Feature",
  "properties": {
    "gn:admin1_code":"13",
    "gn:admin2_code":"50",
    "gn:asciiname":"Donija",
    "gn:country_code":"MX",
    "gn:dem":1976,
    "gn:feature_class":"P",
    "gn:feature_code":"PPL",
    "gn:name":"Donija",
    "gn:population":29,
    "gn:timezone":"America/Mexico_City",
    "iso:country":"MX",
    "wof:name":"Donija",
    "wof:placetype":"locality",
    "wof:population":29
},
  "geometry": {"coordinates":[-99.21250000000001,20.31618],"type":"Point"}
}