{
  "type": "Feature",
  "properties": {
    "gn:admin1_code":"30",
    "gn:admin2_code":"207",
    "gn:asciiname":"Santa Fe (Constantino Acosta)",
    "gn:country_code":"MX",
    "gn:dem":52,
    "gn:feature_class":"P",
    "gn:feature_code":"PPL",
    "gn:name":"Santa Fe (Constantino Acosta)",
    "gn:population":17,
    "gn:timezone":"America/Mexico_City",
    "iso:country":"MX",
    "wof:name":"Santa Fe (Constantino Acosta)",
    "wof:placetype":"locality",
    "wof:population":17
},
  "geometry": {"coordinates":[-96.11360999999999,18.27889],"type":"Point"}
}