{
  "type": "Feature",
  "properties": {
    "gn:admin1_code":"17",
    "gn:admin2_code":"29",
    "gn:asciiname":"Ejido Cuahuilotal",
    "gn:country_code":"MX",
    "gn:dem":1230,
    "gn:feature_class":"P",
    "gn:feature_code":"PPL",
    "gn:name":"Ejido Cuahuilotal",
    "gn:population":42,
    "gn:timezone":"America/Mexico_City",
    "iso:country":"MX",
    "wof:name":"Ejido Cuahuilotal",
    "wof:placetype":"locality",
    "wof:population":42
},
  "geometry": {"coordinates":[-99.07056,18.91722],"type":"Point"}
}