{
  "type": "Feature",
  "properties": {
    "gn:admin1_code":"16.0",
    "gn:asciiname":"Pungarancho",
    "gn:country_code":"MX",
    "gn:dem":577,
    "gn:feature_class":"P",
    "gn:feature_code":"PPL",
    "gn:name":"Pungarancho",
    "gn:population":0,
    "gn:timezone":"America/Mexico_City",
    "iso:country":"MX",
    "name:spa_x_preferred":[
        "Pungarancho"
    ],
    "wof:name":"Pungarancho",
    "wof:placetype":"locality"
},
  "geometry": {"coordinates":[-100.47344,19.03032],"type":"Point"}
}