{
  "type": "Feature",
  "properties": {
    "gn:admin1_code":"11",
    "gn:admin2_code":"7",
    "gn:asciiname":"El Capulin (Francisco Javier Gonzalez)",
    "gn:country_code":"MX",
    "gn:dem":1767,
    "gn:feature_class":"P",
    "gn:feature_code":"PPL",
    "gn:name":"El Capul\u00edn (Francisco Javier Gonz\u00e1lez)",
    "gn:population":9,
    "gn:timezone":"America/Mexico_City",
    "iso:country":"MX",
    "name:und_x_variant":[
        "El Capul\u00edn (Francisco Javier Gonz\u00e1lez)"
    ],
    "wof:name":"El Capulin (Francisco Javier Gonzalez)",
    "wof:placetype":"locality",
    "wof:population":9
},
  "geometry": {"coordinates":[-100.75139,20.5875],"type":"Point"}
}