{
  "type": "Feature",
  "properties": {
    "gn:admin1_code":"26",
    "gn:admin2_code":"18.0",
    "gn:asciiname":"Flores Valenzuela (Charco Hondo)",
    "gn:country_code":"MX",
    "gn:dem":36,
    "gn:feature_class":"P",
    "gn:feature_code":"PPL",
    "gn:name":"Flores Valenzuela (Charco Hondo)",
    "gn:population":6,
    "gn:timezone":"America/Hermosillo",
    "iso:country":"MX",
    "wof:name":"Flores Valenzuela (Charco Hondo)",
    "wof:placetype":"locality",
    "wof:population":6
},
  "geometry": {"coordinates":[-109.93416999999999,27.66389],"type":"Point"}
}