{
  "type": "Feature",
  "properties": {
    "gn:admin1_code":"25",
    "gn:admin2_code":"5",
    "gn:asciiname":"Los Aguajitos",
    "gn:country_code":"MX",
    "gn:dem":277,
    "gn:feature_class":"P",
    "gn:feature_code":"PPL",
    "gn:name":"Los Aguajitos",
    "gn:population":31,
    "gn:timezone":"America/Mazatlan",
    "iso:country":"MX",
    "wof:name":"Los Aguajitos",
    "wof:placetype":"locality",
    "wof:population":31
},
  "geometry": {"coordinates":[-106.81713999999999,24.35812],"type":"Point"}
}