{
  "type": "Feature",
  "properties": {
    "gn:admin1_code":"6.0",
    "gn:admin2_code":"47.0",
    "gn:asciiname":"Rincon de Andrade",
    "gn:country_code":"MX",
    "gn:dem":784,
    "gn:feature_class":"P",
    "gn:feature_code":"PPL",
    "gn:name":"Rinc\u00f3n de Andrade",
    "gn:population":0,
    "gn:timezone":"America/Chihuahua",
    "iso:country":"MX",
    "name:spa_x_preferred":[
        "Rinc\u00f3n de Andrade"
    ],
    "wof:name":"Rincon de Andrade",
    "wof:placetype":"locality"
},
  "geometry": {"coordinates":[-108.54559,28.1897],"type":"Point"}
}