{
  "type": "Feature",
  "properties": {
    "gn:admin1_code":"23",
    "gn:admin2_code":"3.0",
    "gn:asciiname":"Boca Iglesia",
    "gn:country_code":"MX",
    "gn:dem":1,
    "gn:feature_class":"P",
    "gn:feature_code":"PPL",
    "gn:name":"Boca Iglesia",
    "gn:population":57,
    "gn:timezone":"America/Cancun",
    "iso:country":"MX",
    "wof:name":"Boca Iglesia",
    "wof:placetype":"locality",
    "wof:population":57
},
  "geometry": {"coordinates":[-86.97255,21.53583],"type":"Point"}
}