{
  "type": "Feature",
  "properties": {
    "gn:admin1_code":"31",
    "gn:admin2_code":"40.0",
    "gn:asciiname":"San Yazke",
    "gn:country_code":"MX",
    "gn:dem":13,
    "gn:feature_class":"P",
    "gn:feature_code":"PPL",
    "gn:name":"San Yazk\u00e9",
    "gn:population":5,
    "gn:timezone":"America/Merida",
    "iso:country":"MX",
    "name:und_x_variant":[
        "San Yazk\u00e9"
    ],
    "wof:name":"San Yazke",
    "wof:placetype":"locality",
    "wof:population":5
},
  "geometry": {"coordinates":[-89.10972,20.95028],"type":"Point"}
}