{
  "type": "Feature",
  "properties": {
    "gn:admin1_code":"14.0",
    "gn:admin2_code":"64.0",
    "gn:asciiname":"San Jose de Arriba",
    "gn:country_code":"MX",
    "gn:dem":2124,
    "gn:feature_class":"P",
    "gn:feature_code":"PPL",
    "gn:name":"San Jos\u00e9 de Arriba",
    "gn:population":0,
    "gn:timezone":"America/Mexico_City",
    "iso:country":"MX",
    "name:spa_x_preferred":[
        "San Jos\u00e9 de Arriba"
    ],
    "wof:name":"San Jose de Arriba",
    "wof:placetype":"locality"
},
  "geometry": {"coordinates":[-101.59801,21.62504],"type":"Point"}
}