{
  "type": "Feature",
  "properties": {
    "gn:admin1_code":"15",
    "gn:admin2_code":"8.0",
    "gn:asciiname":"El Coyol (Coyol de Coahuilotes)",
    "gn:country_code":"MX",
    "gn:dem":1265,
    "gn:feature_class":"P",
    "gn:feature_code":"PPL",
    "gn:name":"El Coyol (Coyol de Coahuilotes)",
    "gn:population":85,
    "gn:timezone":"America/Mexico_City",
    "iso:country":"MX",
    "wof:name":"El Coyol (Coyol de Coahuilotes)",
    "wof:placetype":"locality",
    "wof:population":85
},
  "geometry": {"coordinates":[-100.20843000000001,18.71461],"type":"Point"}
}