{
  "type": "Feature",
  "properties": {
    "gn:admin1_code":"4.0",
    "gn:asciiname":"El Tinaco",
    "gn:country_code":"MX",
    "gn:dem":58,
    "gn:feature_class":"P",
    "gn:feature_code":"PPL",
    "gn:name":"El Tinaco",
    "gn:population":0,
    "gn:timezone":"America/Merida",
    "iso:country":"MX",
    "name:spa_x_preferred":[
        "El Tinaco"
    ],
    "wof:name":"El Tinaco",
    "wof:placetype":"locality"
},
  "geometry": {"coordinates":[-90.82944999999999,17.84167],"type":"Point"}
}