{
  "type": "Feature",
  "properties": {
    "gn:admin1_code":"30",
    "gn:admin2_code":"143",
    "gn:asciiname":"Cobata",
    "gn:country_code":"MX",
    "gn:dem":355,
    "gn:feature_class":"P",
    "gn:feature_code":"PPL",
    "gn:name":"Cobata",
    "gn:population":24,
    "gn:timezone":"America/Mexico_City",
    "iso:country":"MX",
    "wof:name":"Cobata",
    "wof:placetype":"locality",
    "wof:population":24
},
  "geometry": {"coordinates":[-95.34361,18.48833],"type":"Point"}
}