{
  "type": "Feature",
  "properties": {
    "gn:admin1_code":"26",
    "gn:admin2_code":"66.0",
    "gn:asciiname":"Las Glorias",
    "gn:country_code":"MX",
    "gn:dem":489,
    "gn:feature_class":"P",
    "gn:feature_code":"PPL",
    "gn:name":"Las Glorias",
    "gn:population":0,
    "gn:timezone":"America/Hermosillo",
    "iso:country":"MX",
    "name:spa_x_preferred":[
        "Las Glorias"
    ],
    "wof:name":"Las Glorias",
    "wof:placetype":"locality"
},
  "geometry": {"coordinates":[-110.31780999999999,29.20351],"type":"Point"}
}