{
  "type": "Feature",
  "properties": {
    "gn:admin1_code":"24",
    "gn:admin2_code":"28.0",
    "gn:asciiname":"Los Garcia",
    "gn:country_code":"MX",
    "gn:dem":1843,
    "gn:feature_class":"P",
    "gn:feature_code":"PPL",
    "gn:name":"Los Garc\u00eda",
    "gn:population":108,
    "gn:timezone":"America/Mexico_City",
    "iso:country":"MX",
    "name:und_x_variant":[
        "Los Garc\u00eda"
    ],
    "wof:name":"Los Garcia",
    "wof:placetype":"locality",
    "wof:population":108
},
  "geometry": {"coordinates":[-100.95528,22.24306],"type":"Point"}
}