{
  "type": "Feature",
  "properties": {
    "gn:admin1_code":"21",
    "gn:admin2_code":"83.0",
    "gn:asciiname":"Iliyucan",
    "gn:country_code":"MX",
    "gn:dem":2635,
    "gn:feature_class":"P",
    "gn:feature_code":"PPL",
    "gn:name":"Iliyucan",
    "gn:population":210,
    "gn:timezone":"America/Mexico_City",
    "iso:country":"MX",
    "wof:name":"Iliyucan",
    "wof:placetype":"locality",
    "wof:population":210
},
  "geometry": {"coordinates":[-97.93640000000001,19.6367],"type":"Point"}
}