{
  "type": "Feature",
  "properties": {
    "gn:admin1_code":"19",
    "gn:admin2_code":"16.0",
    "gn:asciiname":"La Madera",
    "gn:country_code":"MX",
    "gn:dem":410,
    "gn:feature_class":"P",
    "gn:feature_code":"PPL",
    "gn:name":"La Madera",
    "gn:population":0,
    "gn:timezone":"America/Monterrey",
    "iso:country":"MX",
    "name:spa_x_preferred":[
        "La Madera"
    ],
    "name:urd_x_preferred":[
        "\u0644\u0627 \u0645\u0627\u062f\u06cc\u0631\u0627"
    ],
    "wof:name":"La Madera",
    "wof:placetype":"locality"
},
  "geometry": {"coordinates":[-99.97109,25.87741],"type":"Point"}
}