{
  "type": "Feature",
  "properties": {
    "gn:admin1_code":"2",
    "gn:admin2_code":"1.0",
    "gn:asciiname":"Playa Agua Azul de Acapulco",
    "gn:country_code":"MX",
    "gn:dem":7,
    "gn:feature_class":"P",
    "gn:feature_code":"PPL",
    "gn:name":"Playa Agua Azul de Acapulco",
    "gn:population":0,
    "gn:timezone":"America/Tijuana",
    "iso:country":"MX",
    "name:spa_x_preferred":[
        "Playa Agua Azul de Acapulco"
    ],
    "name:und_x_variant":[
        "Playa Azul de Acapulco"
    ],
    "wof:name":"Playa Agua Azul de Acapulco",
    "wof:placetype":"locality"
},
  "geometry": {"coordinates":[-114.69873,30.64348],"type":"Point"}
}