{
  "type": "Feature",
  "properties": {
    "gn:admin1_code":"14.0",
    "gn:admin2_code":"20.0",
    "gn:asciiname":"Caverna",
    "gn:cc2":"MX",
    "gn:country_code":"MX",
    "gn:dem":781,
    "gn:feature_class":"P",
    "gn:feature_code":"PPL",
    "gn:name":"Caverna",
    "gn:population":0,
    "gn:timezone":"America/Mexico_City",
    "iso:country":"MX",
    "name:und_x_variant":[
        "Caberna",
        "Caverna"
    ],
    "wof:name":"Caverna",
    "wof:placetype":"locality"
},
  "geometry": {"coordinates":[-105.38333,20.33333],"type":"Point"}
}