{
  "type": "Feature",
  "properties": {
    "gn:admin1_code":"12",
    "gn:admin2_code":"2",
    "gn:asciiname":"La Tabernita",
    "gn:country_code":"MX",
    "gn:dem":1345,
    "gn:feature_class":"P",
    "gn:feature_code":"PPL",
    "gn:name":"La Tabernita",
    "gn:population":9,
    "gn:timezone":"America/Mexico_City",
    "iso:country":"MX",
    "wof:name":"La Tabernita",
    "wof:placetype":"locality",
    "wof:population":9
},
  "geometry": {"coordinates":[-99.04197000000001,17.73382],"type":"Point"}
}