{
  "type": "Feature",
  "properties": {
    "gn:admin1_code":"15",
    "gn:admin2_code":"48.0",
    "gn:asciiname":"Santa Maria Endare",
    "gn:cc2":"MX",
    "gn:country_code":"MX",
    "gn:dem":2700,
    "gn:feature_class":"P",
    "gn:feature_code":"PPL",
    "gn:name":"Santa Mar\u00eda Endare",
    "gn:population":1700,
    "gn:timezone":"America/Mexico_City",
    "iso:country":"MX",
    "name:und_x_variant":[
        "Endar\u00e9",
        "Santa Mar\u00eda Endar\u00e9"
    ],
    "wof:name":"Santa Maria Endare",
    "wof:placetype":"locality",
    "wof:population":1700
},
  "geometry": {"coordinates":[-99.81583000000001,19.72556],"type":"Point"}
}