{
  "type": "Feature",
  "properties": {
    "gn:admin1_code":"5",
    "gn:admin2_code":"17",
    "gn:asciiname":"El Guamuchil",
    "gn:country_code":"MX",
    "gn:dem":673,
    "gn:feature_class":"P",
    "gn:feature_code":"PPL",
    "gn:name":"El Guam\u00fachil",
    "gn:population":20,
    "gn:timezone":"America/Mexico_City",
    "iso:country":"MX",
    "name:und_x_variant":[
        "El Guam\u00fachil"
    ],
    "wof:name":"El Guamuchil",
    "wof:placetype":"locality",
    "wof:population":20
},
  "geometry": {"coordinates":[-93.98278000000001,16.51],"type":"Point"}
}