{
  "type": "Feature",
  "properties": {
    "gn:admin1_code":"30",
    "gn:admin2_code":"11.0",
    "gn:asciiname":"Fraccionamiento las Lomas",
    "gn:country_code":"MX",
    "gn:dem":40,
    "gn:feature_class":"P",
    "gn:feature_code":"PPL",
    "gn:name":"Fraccionamiento las Lomas",
    "gn:population":559,
    "gn:timezone":"America/Mexico_City",
    "iso:country":"MX",
    "wof:name":"Fraccionamiento las Lomas",
    "wof:placetype":"locality",
    "wof:population":559
},
  "geometry": {"coordinates":[-96.09721999999999,19.07028],"type":"Point"}
}