{
  "type": "Feature",
  "properties": {
    "gn:admin1_code":"20",
    "gn:admin2_code":"41.0",
    "gn:asciiname":"Agua de Yerba Santa",
    "gn:country_code":"MX",
    "gn:dem":1639,
    "gn:feature_class":"P",
    "gn:feature_code":"PPL",
    "gn:name":"Agua de Yerba Santa",
    "gn:population":116,
    "gn:timezone":"America/Mexico_City",
    "iso:country":"MX",
    "wof:name":"Agua de Yerba Santa",
    "wof:placetype":"locality",
    "wof:population":116
},
  "geometry": {"coordinates":[-96.76778,18.14972],"type":"Point"}
}