{
  "type": "Feature",
  "properties": {
    "gn:admin1_code":"14",
    "gn:admin2_code":"19",
    "gn:asciiname":"Mesa del Carrizal",
    "gn:country_code":"MX",
    "gn:dem":1055,
    "gn:feature_class":"P",
    "gn:feature_code":"PPL",
    "gn:name":"Mesa del Carrizal",
    "gn:population":11,
    "gn:timezone":"America/Mexico_City",
    "iso:country":"MX",
    "wof:name":"Mesa del Carrizal",
    "wof:placetype":"locality",
    "wof:population":11
},
  "geometry": {"coordinates":[-104.06139,21.81194],"type":"Point"}
}