{
  "type": "Feature",
  "properties": {
    "gn:admin1_code":"14",
    "gn:admin2_code":"46.0",
    "gn:asciiname":"Labor de Abalsa",
    "gn:country_code":"MX",
    "gn:dem":1766,
    "gn:feature_class":"P",
    "gn:feature_code":"PPL",
    "gn:name":"Labor de Abalsa",
    "gn:population":7,
    "gn:timezone":"America/Mexico_City",
    "iso:country":"MX",
    "wof:name":"Labor de Abalsa",
    "wof:placetype":"locality",
    "wof:population":7
},
  "geometry": {"coordinates":[-102.43416999999999,21.22667],"type":"Point"}
}