{
  "type": "Feature",
  "properties": {
    "gn:admin1_code":"6.0",
    "gn:admin2_code":"27.0",
    "gn:asciiname":"Rocoachi",
    "gn:country_code":"MX",
    "gn:dem":1938,
    "gn:feature_class":"P",
    "gn:feature_code":"PPL",
    "gn:name":"Rocoachi",
    "gn:population":0,
    "gn:timezone":"America/Chihuahua",
    "iso:country":"MX",
    "name:spa_x_preferred":[
        "Rocoachi"
    ],
    "wof:name":"Rocoachi",
    "wof:placetype":"locality"
},
  "geometry": {"coordinates":[-107.33571999999999,26.9929],"type":"Point"}
}