{
  "type": "Feature",
  "properties": {
    "gn:admin1_code":"31",
    "gn:admin2_code":"17.0",
    "gn:asciiname":"Tzucmuc",
    "gn:country_code":"MX",
    "gn:dem":31,
    "gn:feature_class":"P",
    "gn:feature_code":"PPL",
    "gn:name":"Tzucmuc",
    "gn:population":0,
    "gn:timezone":"America/Merida",
    "iso:country":"MX",
    "name:spa_x_preferred":[
        "Tzucmuc"
    ],
    "name:spa_x_variant":[
        "Tzukmuc"
    ],
    "wof:name":"Tzucmuc",
    "wof:placetype":"locality"
},
  "geometry": {"coordinates":[-88.45666,20.59154],"type":"Point"}
}