{
  "type": "Feature",
  "properties": {
    "gn:admin1_code":"26",
    "gn:admin2_code":"52.0",
    "gn:asciiname":"Los Tezotes",
    "gn:cc2":"MX",
    "gn:country_code":"MX",
    "gn:dem":1028,
    "gn:feature_class":"P",
    "gn:feature_code":"PPL",
    "gn:name":"Los Tezotes",
    "gn:population":0,
    "gn:timezone":"America/Hermosillo",
    "iso:country":"MX",
    "name:und_x_variant":[
        "Las Tezotas",
        "Los Tezotes"
    ],
    "wof:name":"Los Tezotes",
    "wof:placetype":"locality"
},
  "geometry": {"coordinates":[-108.96666999999999,29.25],"type":"Point"}
}