{
  "type": "Feature",
  "properties": {
    "gn:admin1_code":"21",
    "gn:admin2_code":"43.0",
    "gn:asciiname":"Nectepec",
    "gn:country_code":"MX",
    "gn:dem":677,
    "gn:feature_class":"P",
    "gn:feature_code":"PPL",
    "gn:name":"Nectepec",
    "gn:population":700,
    "gn:timezone":"America/Mexico_City",
    "iso:country":"MX",
    "wof:name":"Nectepec",
    "wof:placetype":"locality",
    "wof:population":700
},
  "geometry": {"coordinates":[-97.44122,20.03082],"type":"Point"}
}