{
  "type": "Feature",
  "properties": {
    "gn:admin1_code":"12.0",
    "gn:admin2_code":"45.0",
    "gn:asciiname":"Palito Redondo",
    "gn:country_code":"MX",
    "gn:dem":1591,
    "gn:feature_class":"P",
    "gn:feature_code":"PPL",
    "gn:name":"Palito Redondo",
    "gn:population":0,
    "gn:timezone":"America/Mexico_City",
    "iso:country":"MX",
    "name:spa_x_preferred":[
        "Palito Redondo"
    ],
    "wof:name":"Palito Redondo",
    "wof:placetype":"locality"
},
  "geometry": {"coordinates":[-98.77717,17.74432000000001],"type":"Point"}
}