{
  "type": "Feature",
  "properties": {
    "gn:admin1_code":"10",
    "gn:asciiname":"Valderrama",
    "gn:country_code":"MX",
    "gn:dem":1154,
    "gn:feature_class":"P",
    "gn:feature_code":"PPL",
    "gn:name":"Valderrama",
    "gn:population":0,
    "gn:timezone":"America/Monterrey",
    "iso:country":"MX",
    "name:ceb_x_preferred":[
        "Valderrama"
    ],
    "name:deu_x_preferred":[
        "Valderrama"
    ],
    "name:fra_x_preferred":[
        "Valderrama"
    ],
    "name:ita_x_preferred":[
        "Valderrama"
    ],
    "name:jpn_x_preferred":[
        "\u30d0\u30eb\u30c7\u30e9\u30de"
    ],
    "name:nld_x_preferred":[
        "Valderrama"
    ],
    "name:nor_x_preferred":[
        "Valderrama"
    ],
    "name:pol_x_preferred":[
        "Valderrama"
    ],
    "name:por_x_preferred":[
        "Valderrama"
    ],
    "name:rus_x_preferred":[
        "\u0412\u0430\u043b\u044c\u0434\u0435\u0440\u0440\u0430\u043c\u0430"
    ],
    "name:spa_x_preferred":[
        "Valderrama"
    ],
    "name:swe_x_preferred":[
        "Valderrama"
    ],
    "name:ukr_x_preferred":[
        "\u0412\u0430\u043b\u044c\u0434\u0435\u0440\u0440\u0430\u043c\u0430"
    ],
    "wof:name":"Valderrama",
    "wof:placetype":"locality"
},
  "geometry": {"coordinates":[-105.90149,23.91601],"type":"Point"}
}