{
  "type": "Feature",
  "properties": {
    "gn:admin1_code":"10",
    "gn:asciiname":"Valderrama",
    "gn:country_code":"MX",
    "gn:dem":1154,
    "gn:feature_class":"P",
    "gn:feature_code":"PPL",
    "gn:name":"Valderrama",
    "gn:population":0,
    "gn:timezone":"America/Monterrey",
    "iso:country":"MX",
    "name:spa_x_preferred":[
        "Valderrama"
    ],
    "wof:name":"Valderrama",
    "wof:placetype":"locality"
},
  "geometry": {"coordinates":[-105.90149,23.91601],"type":"Point"}
}