{
  "type": "Feature",
  "properties": {
    "gn:admin1_code":"6",
    "gn:admin2_code":"30.0",
    "gn:asciiname":"Monterde",
    "gn:country_code":"MX",
    "gn:dem":2187,
    "gn:feature_class":"P",
    "gn:feature_code":"PPL",
    "gn:name":"Monterde",
    "gn:population":0,
    "gn:timezone":"America/Chihuahua",
    "iso:country":"MX",
    "name:ara_x_preferred":[
        "\u0645\u0648\u0646\u062a\u064a\u0631\u062f\u064a"
    ],
    "name:arg_x_preferred":[
        "Monterd"
    ],
    "name:azb_x_preferred":[
        "\u0645\u0646\u062a\u0631\u062f\u0647"
    ],
    "name:cat_x_preferred":[
        "Monterde"
    ],
    "name:ceb_x_preferred":[
        "Monterde"
    ],
    "name:eus_x_preferred":[
        "Monterde"
    ],
    "name:fas_x_preferred":[
        "\u0645\u0646\u062a\u0631\u062f\u0647"
    ],
    "name:fra_x_preferred":[
        "Monterde"
    ],
    "name:hun_x_preferred":[
        "Monterde"
    ],
    "name:ita_x_preferred":[
        "Monterde"
    ],
    "name:kaz_x_preferred":[
        "\u041c\u043e\u043d\u0442\u0435\u0440\u0434\u0435"
    ],
    "name:msa_x_preferred":[
        "Monterde"
    ],
    "name:nld_x_preferred":[
        "Monterde"
    ],
    "name:oci_x_preferred":[
        "Monterde"
    ],
    "name:pol_x_preferred":[
        "Monterde"
    ],
    "name:por_x_preferred":[
        "Monterde"
    ],
    "name:rus_x_preferred":[
        "\u041c\u043e\u043d\u0442\u0435\u0440\u0434\u0435"
    ],
    "name:spa_x_preferred":[
        "Monterde"
    ],
    "name:swe_x_preferred":[
        "Monterde"
    ],
    "name:ukr_x_preferred":[
        "\u041c\u043e\u043d\u0442\u0435\u0440\u0434\u0435"
    ],
    "name:uzb_x_preferred":[
        "Monterde"
    ],
    "name:vie_x_preferred":[
        "Monterde"
    ],
    "name:war_x_preferred":[
        "Monterde"
    ],
    "name:zho_x_preferred":[
        "\u8499\u7279\u5c14\u5fb7"
    ],
    "wof:name":"Monterde",
    "wof:placetype":"locality"
},
  "geometry": {"coordinates":[-108.09093,27.57682],"type":"Point"}
}