{
  "type": "Feature",
  "properties": {
    "gn:admin1_code":"24",
    "gn:admin2_code":"26",
    "gn:asciiname":"La Muralla Dos",
    "gn:country_code":"MX",
    "gn:dem":313,
    "gn:feature_class":"P",
    "gn:feature_code":"PPL",
    "gn:name":"La Muralla Dos",
    "gn:population":16,
    "gn:timezone":"America/Mexico_City",
    "iso:country":"MX",
    "wof:name":"La Muralla Dos",
    "wof:placetype":"locality",
    "wof:population":16
},
  "geometry": {"coordinates":[-98.91694,21.62917],"type":"Point"}
}