{
  "type": "Feature",
  "properties": {
    "gn:admin1_code":"21",
    "gn:admin2_code":"158.0",
    "gn:asciiname":"Tenexapa de Allende",
    "gn:country_code":"MX",
    "gn:dem":186,
    "gn:feature_class":"P",
    "gn:feature_code":"PPL",
    "gn:name":"Tenexapa de Allende",
    "gn:population":0,
    "gn:timezone":"America/Mexico_City",
    "iso:country":"MX",
    "name:und_x_variant":[
        "Tenejapan",
        "Tenexapa",
        "Tenexapa de Allende"
    ],
    "wof:name":"Tenexapa de Allende",
    "wof:placetype":"locality"
},
  "geometry": {"coordinates":[-97.33622,20.16723],"type":"Point"}
}