{
  "type": "Feature",
  "properties": {
    "gn:admin1_code":"10",
    "gn:admin2_code":"23.0",
    "gn:asciiname":"La Cumbre",
    "gn:country_code":"MX",
    "gn:dem":2203,
    "gn:feature_class":"P",
    "gn:feature_code":"PPL",
    "gn:name":"La Cumbre",
    "gn:population":207,
    "gn:timezone":"America/Monterrey",
    "iso:country":"MX",
    "wof:name":"La Cumbre",
    "wof:placetype":"locality",
    "wof:population":207
},
  "geometry": {"coordinates":[-105.20332999999999,23.25056],"type":"Point"}
}