{
  "type": "Feature",
  "properties": {
    "gn:admin1_code":"22",
    "gn:admin2_code":"13.0",
    "gn:asciiname":"La Tinaja",
    "gn:country_code":"MX",
    "gn:dem":1382,
    "gn:feature_class":"P",
    "gn:feature_code":"PPL",
    "gn:name":"La Tinaja",
    "gn:population":43,
    "gn:timezone":"America/Mexico_City",
    "iso:country":"MX",
    "wof:name":"La Tinaja",
    "wof:placetype":"locality",
    "wof:population":43
},
  "geometry": {"coordinates":[-99.87944,21.04472],"type":"Point"}
}