{
  "type": "Feature",
  "properties": {
    "gn:admin1_code":"13",
    "gn:admin2_code":"62.0",
    "gn:asciiname":"Molashtitla",
    "gn:country_code":"MX",
    "gn:dem":687,
    "gn:feature_class":"P",
    "gn:feature_code":"PPL",
    "gn:name":"Molasht\u00edtla",
    "gn:population":0,
    "gn:timezone":"America/Mexico_City",
    "iso:country":"MX",
    "name:spa_x_preferred":[
        "Molasht\u00edtla"
    ],
    "wof:name":"Molashtitla",
    "wof:placetype":"locality"
},
  "geometry": {"coordinates":[-98.89671,21.03802],"type":"Point"}
}