{
  "type": "Feature",
  "properties": {
    "gn:admin1_code":"7",
    "gn:admin2_code":"23.0",
    "gn:asciiname":"Palos Blancos",
    "gn:country_code":"MX",
    "gn:dem":1285,
    "gn:feature_class":"P",
    "gn:feature_code":"PPL",
    "gn:name":"Palos Blancos",
    "gn:population":0,
    "gn:timezone":"America/Monterrey",
    "iso:country":"MX",
    "name:spa_x_preferred":[
        "Palos Blancos"
    ],
    "name:und_x_variant":[
        "Rancho Santa Rita",
        "Santa Rita"
    ],
    "wof:name":"Palos Blancos",
    "wof:placetype":"locality"
},
  "geometry": {"coordinates":[-102.20607,27.50514],"type":"Point"}
}