{
  "type": "Feature",
  "properties": {
    "gn:admin1_code":"19.0",
    "gn:admin2_code":"42.0",
    "gn:asciiname":"Trasquilitas",
    "gn:country_code":"MX",
    "gn:dem":194,
    "gn:feature_class":"P",
    "gn:feature_code":"PPL",
    "gn:name":"Trasquilitas",
    "gn:population":0,
    "gn:timezone":"America/Monterrey",
    "iso:country":"MX",
    "name:spa_x_preferred":[
        "Trasquilitas"
    ],
    "wof:name":"Trasquilitas",
    "wof:placetype":"locality"
},
  "geometry": {"coordinates":[-99.56502,25.85781],"type":"Point"}
}