{
  "type": "Feature",
  "properties": {
    "gn:admin1_code":"10",
    "gn:admin2_code":"16.0",
    "gn:asciiname":"Las Granjas",
    "gn:country_code":"MX",
    "gn:dem":1883,
    "gn:feature_class":"P",
    "gn:feature_code":"PPL",
    "gn:name":"Las Granjas",
    "gn:population":0,
    "gn:timezone":"America/Monterrey",
    "iso:country":"MX",
    "name:spa_x_preferred":[
        "Las Granjas"
    ],
    "wof:name":"Las Granjas",
    "wof:placetype":"locality"
},
  "geometry": {"coordinates":[-104.06901000000001,23.81627000000001],"type":"Point"}
}