{
  "type": "Feature",
  "properties": {
    "gn:admin1_code":"24",
    "gn:admin2_code":"40.0",
    "gn:asciiname":"El Caporal",
    "gn:country_code":"MX",
    "gn:dem":42,
    "gn:feature_class":"P",
    "gn:feature_code":"PPL",
    "gn:name":"El Caporal",
    "gn:population":0,
    "gn:timezone":"America/Mexico_City",
    "iso:country":"MX",
    "name:spa_x_preferred":[
        "El Caporal"
    ],
    "wof:name":"El Caporal",
    "wof:placetype":"locality"
},
  "geometry": {"coordinates":[-98.66627,21.9143],"type":"Point"}
}