{
  "type": "Feature",
  "properties": {
    "gn:admin1_code":"26",
    "gn:admin2_code":"71.0",
    "gn:asciiname":"Campo Castelo",
    "gn:country_code":"MX",
    "gn:dem":24,
    "gn:feature_class":"P",
    "gn:feature_code":"PPL",
    "gn:name":"Campo Castelo",
    "gn:population":6,
    "gn:timezone":"America/Hermosillo",
    "iso:country":"MX",
    "wof:name":"Campo Castelo",
    "wof:placetype":"locality",
    "wof:population":6
},
  "geometry": {"coordinates":[-109.84028000000001,27.15222],"type":"Point"}
}