{
  "type": "Feature",
  "properties": {
    "gn:admin1_code":"10",
    "gn:admin2_code":"13.0",
    "gn:asciiname":"Las Vacas",
    "gn:country_code":"MX",
    "gn:dem":1354,
    "gn:feature_class":"P",
    "gn:feature_code":"PPL",
    "gn:name":"Las Vacas",
    "gn:population":0,
    "gn:timezone":"America/Monterrey",
    "iso:country":"MX",
    "name:spa_x_preferred":[
        "Las Vacas"
    ],
    "wof:name":"Las Vacas",
    "wof:placetype":"locality"
},
  "geometry": {"coordinates":[-104.01625,26.02483],"type":"Point"}
}