{
  "type": "Feature",
  "properties": {
    "gn:admin1_code":"28.0",
    "gn:admin2_code":"2.0",
    "gn:asciiname":"Cinco de Febrero",
    "gn:country_code":"MX",
    "gn:dem":104,
    "gn:feature_class":"P",
    "gn:feature_code":"PPL",
    "gn:name":"Cinco de Febrero",
    "gn:population":213,
    "gn:timezone":"America/Monterrey",
    "iso:country":"MX",
    "name:spa_x_preferred":[
        "Cinco de Febrero"
    ],
    "wof:name":"Cinco de Febrero",
    "wof:placetype":"locality",
    "wof:population":213
},
  "geometry": {"coordinates":[-98.29416999999999,22.83333],"type":"Point"}
}