{
  "type": "Feature",
  "properties": {
    "gn:admin1_code":"25",
    "gn:admin2_code":"15.0",
    "gn:asciiname":"San Lorenzo",
    "gn:country_code":"MX",
    "gn:dem":75,
    "gn:feature_class":"P",
    "gn:feature_code":"PPL",
    "gn:name":"San Lorenzo",
    "gn:population":0,
    "gn:timezone":"America/Mazatlan",
    "iso:country":"MX",
    "name:spa_x_preferred":[
        "San Lorenzo"
    ],
    "wof:name":"San Lorenzo",
    "wof:placetype":"locality"
},
  "geometry": {"coordinates":[-108.11801,25.56579],"type":"Point"}
}