{
  "type": "Feature",
  "properties": {
    "gn:admin1_code":"30.0",
    "gn:admin2_code":"83.0",
    "gn:asciiname":"Las Tejas",
    "gn:country_code":"MX",
    "gn:dem":183,
    "gn:feature_class":"P",
    "gn:feature_code":"PPL",
    "gn:name":"Las Tejas",
    "gn:population":27,
    "gn:timezone":"America/Mexico_City",
    "iso:country":"MX",
    "name:ast_x_preferred":[
        "Las Tejas"
    ],
    "name:spa_x_preferred":[
        "Las Tejas"
    ],
    "name:urd_x_preferred":[
        "\u0644\u0627\u0633 \u0679\u06cc\u062c\u0627\u0633"
    ],
    "wof:name":"Las Tejas",
    "wof:placetype":"locality",
    "wof:population":27
},
  "geometry": {"coordinates":[-98.07639,20.66944],"type":"Point"}
}