{
  "type": "Feature",
  "properties": {
    "gn:admin1_code":"25",
    "gn:admin2_code":"1",
    "gn:asciiname":"El Tubo",
    "gn:country_code":"MX",
    "gn:dem":21,
    "gn:feature_class":"P",
    "gn:feature_code":"PPL",
    "gn:name":"El Tubo",
    "gn:population":11,
    "gn:timezone":"America/Mazatlan",
    "iso:country":"MX",
    "wof:name":"El Tubo",
    "wof:placetype":"locality",
    "wof:population":11
},
  "geometry": {"coordinates":[-108.81699999999999,25.8447],"type":"Point"}
}