{
  "type": "Feature",
  "properties": {
    "gn:admin1_code":"6",
    "gn:admin2_code":"12",
    "gn:asciiname":"Banderachi (Bandera)",
    "gn:country_code":"MX",
    "gn:dem":2363,
    "gn:feature_class":"P",
    "gn:feature_code":"PPL",
    "gn:name":"Banderachi (Bandera)",
    "gn:population":39,
    "gn:timezone":"America/Chihuahua",
    "iso:country":"MX",
    "wof:name":"Banderachi (Bandera)",
    "wof:placetype":"locality",
    "wof:population":39
},
  "geometry": {"coordinates":[-107.05955,27.56324],"type":"Point"}
}