{
  "type": "Feature",
  "properties": {
    "gn:admin1_code":"14",
    "gn:admin2_code":"84",
    "gn:asciiname":"Los Rostros",
    "gn:country_code":"MX",
    "gn:dem":909,
    "gn:feature_class":"P",
    "gn:feature_code":"PPL",
    "gn:name":"Los Rostros",
    "gn:population":16,
    "gn:timezone":"America/Mexico_City",
    "iso:country":"MX",
    "wof:name":"Los Rostros",
    "wof:placetype":"locality",
    "wof:population":16
},
  "geometry": {"coordinates":[-104.98833,20.235],"type":"Point"}
}