{
  "type": "Feature",
  "properties": {
    "gn:admin1_code":"10",
    "gn:admin2_code":"7.0",
    "gn:asciiname":"El Rocio",
    "gn:country_code":"MX",
    "gn:dem":1116,
    "gn:feature_class":"P",
    "gn:feature_code":"PPL",
    "gn:name":"El Roc\u00edo",
    "gn:population":0,
    "gn:timezone":"America/Monterrey",
    "iso:country":"MX",
    "name:spa_x_preferred":[
        "El Roc\u00edo"
    ],
    "wof:name":"El Rocio",
    "wof:placetype":"locality"
},
  "geometry": {"coordinates":[-103.51654000000001,25.70007],"type":"Point"}
}