{
  "type": "Feature",
  "properties": {
    "gn:admin1_code":"19",
    "gn:admin2_code":"38.0",
    "gn:asciiname":"Las Perlas",
    "gn:country_code":"MX",
    "gn:dem":382,
    "gn:feature_class":"P",
    "gn:feature_code":"PPL",
    "gn:name":"Las Perlas",
    "gn:population":0,
    "gn:timezone":"America/Monterrey",
    "iso:country":"MX",
    "name:rus_x_preferred":[
        "\u041b\u0430\u0441-\u041f\u0435\u0440\u043b\u0430\u0441"
    ],
    "name:spa_x_preferred":[
        "Las Perlas"
    ],
    "name:urd_x_preferred":[
        "\u0644\u0627\u0633 \u067e\u06cc\u0631\u0644\u0627\u0633"
    ],
    "wof:name":"Las Perlas",
    "wof:placetype":"locality"
},
  "geometry": {"coordinates":[-99.67222,25.0498],"type":"Point"}
}