{
  "type": "Feature",
  "properties": {
    "gn:admin1_code":"10.0",
    "gn:admin2_code":"9.0",
    "gn:asciiname":"El Berro",
    "gn:country_code":"MX",
    "gn:dem":2299,
    "gn:feature_class":"P",
    "gn:feature_code":"PPL",
    "gn:name":"El Berro",
    "gn:population":0,
    "gn:timezone":"America/Monterrey",
    "iso:country":"MX",
    "name:spa_x_preferred":[
        "El Berro"
    ],
    "wof:name":"El Berro",
    "wof:placetype":"locality"
},
  "geometry": {"coordinates":[-106.52484,25.89387],"type":"Point"}
}