{
  "type": "Feature",
  "properties": {
    "gn:admin1_code":"26",
    "gn:admin2_code":"18.0",
    "gn:asciiname":"Martina Quinones Barrera (Predio Tozalcahui)",
    "gn:country_code":"MX",
    "gn:dem":27,
    "gn:feature_class":"P",
    "gn:feature_code":"PPL",
    "gn:name":"Martina Qui\u00f1ones Barrera (Predio Tozalcahui)",
    "gn:population":5,
    "gn:timezone":"America/Hermosillo",
    "iso:country":"MX",
    "name:und_x_variant":[
        "Martina Qui\u00f1ones Barrera (Predio Tozalcahui)"
    ],
    "wof:name":"Martina Quinones Barrera (Predio Tozalcahui)",
    "wof:placetype":"locality",
    "wof:population":5
},
  "geometry": {"coordinates":[-109.96611,27.51306],"type":"Point"}
}