{
  "type": "Feature",
  "properties": {
    "iso:country":"MX",
    "name:spa_x_preferred":[
        "Zona Centro"
    ],
    "name:unk_x_variant":[
        "Zona Centro"
    ],
    "qs:gn_adm0_cc":"MX",
    "qs:gn_local":3530594,
    "qs:gn_nam_loc":"Ciudad Madero, Ciudad Madero, Tamaulipas, MX",
    "qs:gn_namadm1":"28",
    "qs:local_max":173,
    "qs:local_sum":524,
    "qs:localhoods":7,
    "qs:name":"Zona Centro",
    "qs:name_adm0":"M\u00e9xico",
    "qs:name_adm1":"Tamaulipas",
    "qs:name_adm2":"Ciudad Madero",
    "qs:name_local":"Ciudad Madero",
    "qs:photo_max":142,
    "qs:photo_sum":173,
    "qs:placetype":"Suburb",
    "qs:quad_count":5,
    "qs:woe_adm0":23424900,
    "qs:woe_adm1":2346291,
    "qs:woe_adm2":12601640,
    "qs:woe_lau":0,
    "qs:woe_local":116558,
    "qs:woe_ver":"7.10.0",
    "wof:lang":[
        "spa"
    ],
    "wof:name":"Zona Centro",
    "wof:placetype":"neighbourhood"
},
  "geometry": {"coordinates":[-97.837782,22.247026],"type":"Point"}
}