{
  "type": "Feature",
  "properties": {
    "gn:admin1_code":"32",
    "gn:admin2_code":"20.0",
    "gn:asciiname":"El Pulgo",
    "gn:country_code":"MX",
    "gn:dem":2331,
    "gn:feature_class":"P",
    "gn:feature_code":"PPL",
    "gn:name":"El Pulgo",
    "gn:population":0,
    "gn:timezone":"America/Mexico_City",
    "iso:country":"MX",
    "name:spa_x_preferred":[
        "El Pulgo"
    ],
    "wof:name":"El Pulgo",
    "wof:placetype":"locality"
},
  "geometry": {"coordinates":[-103.1713,22.84652],"type":"Point"}
}