{
  "type": "Feature",
  "properties": {
    "gn:admin1_code":"16.0",
    "gn:admin2_code":"15.0",
    "gn:asciiname":"Playa del Pozo",
    "gn:country_code":"MX",
    "gn:dem":1960,
    "gn:feature_class":"P",
    "gn:feature_code":"PPL",
    "gn:name":"Playa del Pozo",
    "gn:population":0,
    "gn:timezone":"America/Mexico_City",
    "iso:country":"MX",
    "name:spa_x_preferred":[
        "Playa del Pozo"
    ],
    "wof:name":"Playa del Pozo",
    "wof:placetype":"locality"
},
  "geometry": {"coordinates":[-103.03815,18.50621],"type":"Point"}
}