{
  "type": "Feature",
  "properties": {
    "gn:admin1_code":"20",
    "gn:admin2_code":"406.0",
    "gn:asciiname":"Amatlan de los Reyes",
    "gn:country_code":"MX",
    "gn:dem":580,
    "gn:feature_class":"P",
    "gn:feature_code":"PPL",
    "gn:name":"Amatl\u00e1n de los Reyes",
    "gn:population":129,
    "gn:timezone":"America/Mexico_City",
    "iso:country":"MX",
    "name:und_x_variant":[
        "Amatl\u00e1n de los Reyes"
    ],
    "wof:name":"Amatlan de los Reyes",
    "wof:placetype":"locality",
    "wof:population":129
},
  "geometry": {"coordinates":[-96.76167,18.3125],"type":"Point"}
}