{
  "type": "Feature",
  "properties": {
    "gn:admin1_code":"16",
    "gn:admin2_code":"13",
    "gn:asciiname":"El Huaco (El Guaco)",
    "gn:country_code":"MX",
    "gn:dem":674,
    "gn:feature_class":"P",
    "gn:feature_code":"PPL",
    "gn:name":"El Huaco (El Guaco)",
    "gn:population":12,
    "gn:timezone":"America/Mexico_City",
    "iso:country":"MX",
    "wof:name":"El Huaco (El Guaco)",
    "wof:placetype":"locality",
    "wof:population":12
},
  "geometry": {"coordinates":[-101.04277999999999,18.9975],"type":"Point"}
}