{
  "type": "Feature",
  "properties": {
    "gn:admin1_code":"5",
    "gn:admin2_code":"97.0",
    "gn:asciiname":"San Antonio",
    "gn:country_code":"MX",
    "gn:dem":9,
    "gn:feature_class":"P",
    "gn:feature_code":"PPL",
    "gn:name":"San Antonio",
    "gn:population":7,
    "gn:timezone":"America/Mexico_City",
    "iso:country":"MX",
    "wof:name":"San Antonio",
    "wof:placetype":"locality",
    "wof:population":7
},
  "geometry": {"coordinates":[-93.64055999999999,15.84556],"type":"Point"}
}