{
  "type": "Feature",
  "properties": {
    "gn:admin1_code":"19",
    "gn:asciiname":"Las Parritas",
    "gn:country_code":"MX",
    "gn:dem":404,
    "gn:feature_class":"P",
    "gn:feature_code":"PPL",
    "gn:name":"Las Parritas",
    "gn:population":0,
    "gn:timezone":"America/Monterrey",
    "iso:country":"MX",
    "name:spa_x_preferred":[
        "Las Parritas"
    ],
    "wof:name":"Las Parritas",
    "wof:placetype":"locality"
},
  "geometry": {"coordinates":[-99.55041,24.61269],"type":"Point"}
}