{
  "type": "Feature",
  "properties": {
    "gn:admin1_code":"25.0",
    "gn:admin2_code":"13.0",
    "gn:asciiname":"La Cascada",
    "gn:country_code":"MX",
    "gn:dem":267,
    "gn:feature_class":"P",
    "gn:feature_code":"PPL",
    "gn:name":"La Cascada",
    "gn:population":0,
    "gn:timezone":"America/Mazatlan",
    "iso:country":"MX",
    "name:spa_x_preferred":[
        "La Cascada"
    ],
    "wof:name":"La Cascada",
    "wof:placetype":"locality"
},
  "geometry": {"coordinates":[-107.71661,25.63901],"type":"Point"}
}