{
  "type": "Feature",
  "properties": {
    "gn:admin1_code":"11.0",
    "gn:admin2_code":"22.0",
    "gn:asciiname":"La Esquina del Monte",
    "gn:country_code":"MX",
    "gn:dem":2240,
    "gn:feature_class":"P",
    "gn:feature_code":"PPL",
    "gn:name":"La Esquina del Monte",
    "gn:population":0,
    "gn:timezone":"America/Mexico_City",
    "iso:country":"MX",
    "name:spa_x_preferred":[
        "La Esquina del Monte"
    ],
    "name:spa_x_variant":[
        "Esquina del Monte"
    ],
    "wof:name":"La Esquina del Monte",
    "wof:placetype":"locality"
},
  "geometry": {"coordinates":[-101.49097,21.56181],"type":"Point"}
}