{
  "type": "Feature",
  "properties": {
    "gn:admin1_code":"23",
    "gn:admin2_code":"8.0",
    "gn:asciiname":"La Plumita",
    "gn:country_code":"MX",
    "gn:dem":13,
    "gn:feature_class":"P",
    "gn:feature_code":"PPL",
    "gn:name":"La Plumita",
    "gn:population":5,
    "gn:timezone":"America/Cancun",
    "iso:country":"MX",
    "wof:name":"La Plumita",
    "wof:placetype":"locality",
    "wof:population":5
},
  "geometry": {"coordinates":[-87.16074999999999,20.67411],"type":"Point"}
}