{
  "type": "Feature",
  "properties": {
    "gn:admin1_code":"16.0",
    "gn:admin2_code":"101.0",
    "gn:asciiname":"Los Ciruelos",
    "gn:country_code":"MX",
    "gn:dem":1443,
    "gn:feature_class":"P",
    "gn:feature_code":"PPL",
    "gn:name":"Los Ciruelos",
    "gn:population":0,
    "gn:timezone":"America/Mexico_City",
    "iso:country":"MX",
    "name:spa_x_preferred":[
        "Los Ciruelos"
    ],
    "wof:name":"Los Ciruelos",
    "wof:placetype":"locality"
},
  "geometry": {"coordinates":[-100.8516,19.58993],"type":"Point"}
}