{
  "type": "Feature",
  "properties": {
    "gn:admin1_code":"5",
    "gn:admin2_code":"107.0",
    "gn:asciiname":"El Manguito",
    "gn:country_code":"MX",
    "gn:dem":541,
    "gn:feature_class":"P",
    "gn:feature_code":"PPL",
    "gn:name":"El Manguito",
    "gn:population":5,
    "gn:timezone":"America/Mexico_City",
    "iso:country":"MX",
    "wof:name":"El Manguito",
    "wof:placetype":"locality",
    "wof:population":5
},
  "geometry": {"coordinates":[-93.02943999999999,16.18528],"type":"Point"}
}