{
  "type": "Feature",
  "properties": {
    "gn:admin1_code":"5",
    "gn:admin2_code":"97.0",
    "gn:asciiname":"Buenavista",
    "gn:country_code":"MX",
    "gn:dem":46,
    "gn:feature_class":"P",
    "gn:feature_code":"PPL",
    "gn:name":"Buenavista",
    "gn:population":98,
    "gn:timezone":"America/Mexico_City",
    "iso:country":"MX",
    "wof:name":"Buenavista",
    "wof:placetype":"locality",
    "wof:population":98
},
  "geometry": {"coordinates":[-93.80942,16.14576],"type":"Point"}
}