{
  "type": "Feature",
  "properties": {
    "gn:admin1_code":"13",
    "gn:admin2_code":"71.0",
    "gn:asciiname":"Agua Grande",
    "gn:country_code":"MX",
    "gn:dem":2019,
    "gn:feature_class":"P",
    "gn:feature_code":"PPL",
    "gn:name":"Agua Grande",
    "gn:population":69,
    "gn:timezone":"America/Mexico_City",
    "iso:country":"MX",
    "name:ceb_x_preferred":[
        "Agua Grande"
    ],
    "name:swe_x_preferred":[
        "Agua Grande"
    ],
    "wof:name":"Agua Grande",
    "wof:placetype":"locality",
    "wof:population":69
},
  "geometry": {"coordinates":[-98.90759,20.90968],"type":"Point"}
}