{
  "type": "Feature",
  "properties": {
    "gn:admin1_code":"21",
    "gn:admin2_code":"19",
    "gn:asciiname":"Cabrera",
    "gn:country_code":"MX",
    "gn:dem":1917,
    "gn:feature_class":"P",
    "gn:feature_code":"PPL",
    "gn:name":"Cabrera",
    "gn:population":46,
    "gn:timezone":"America/Mexico_City",
    "iso:country":"MX",
    "name:cat_x_preferred":[
        "Cabrera"
    ],
    "name:ceb_x_preferred":[
        "Cabrera"
    ],
    "name:ces_x_preferred":[
        "Cabrera"
    ],
    "name:deu_x_preferred":[
        "Cabrera"
    ],
    "name:est_x_preferred":[
        "Cabrera"
    ],
    "name:fin_x_preferred":[
        "Cabrera"
    ],
    "name:fra_x_preferred":[
        "Cabrera"
    ],
    "name:glg_x_preferred":[
        "Cabrera"
    ],
    "name:hye_x_preferred":[
        "\u053f\u0561\u0562\u0580\u0565\u0580\u0561"
    ],
    "name:ita_x_preferred":[
        "Cabrera"
    ],
    "name:jpn_x_preferred":[
        "\u30ab\u30d6\u30ec\u30e9"
    ],
    "name:kor_x_preferred":[
        "\uce74\ube0c\ub808\ub77c"
    ],
    "name:nld_x_preferred":[
        "Cabrera"
    ],
    "name:por_x_preferred":[
        "Cabrera"
    ],
    "name:rus_x_preferred":[
        "\u041a\u0430\u0431\u0440\u0435\u0440\u0430"
    ],
    "name:sco_x_preferred":[
        "Cabrera"
    ],
    "name:slv_x_preferred":[
        "Cabrera"
    ],
    "name:spa_x_preferred":[
        "Cabrera"
    ],
    "name:srp_x_preferred":[
        "\u041a\u0430\u0431\u0440\u0435\u0440\u0430"
    ],
    "name:swe_x_preferred":[
        "Cabrera"
    ],
    "name:ukr_x_preferred":[
        "\u041a\u0430\u0431\u0440\u0435\u0440\u0430"
    ],
    "wof:name":"Cabrera",
    "wof:placetype":"locality",
    "wof:population":46
},
  "geometry": {"coordinates":[-98.45414,18.9282],"type":"Point"}
}