{
  "type": "Feature",
  "properties": {
    "gn:admin1_code":"21",
    "gn:admin2_code":"19",
    "gn:asciiname":"Cabrera",
    "gn:country_code":"MX",
    "gn:dem":1917,
    "gn:feature_class":"P",
    "gn:feature_code":"PPL",
    "gn:name":"Cabrera",
    "gn:population":46,
    "gn:timezone":"America/Mexico_City",
    "iso:country":"MX",
    "wof:name":"Cabrera",
    "wof:placetype":"locality",
    "wof:population":46
},
  "geometry": {"coordinates":[-98.45414,18.9282],"type":"Point"}
}