{
  "type": "Feature",
  "properties": {
    "gn:admin1_code":"24.0",
    "gn:admin2_code":"16.0",
    "gn:asciiname":"Las Angelicas",
    "gn:country_code":"MX",
    "gn:dem":41,
    "gn:feature_class":"P",
    "gn:feature_code":"PPL",
    "gn:name":"Las Ang\u00e9licas",
    "gn:population":1,
    "gn:timezone":"America/Mexico_City",
    "iso:country":"MX",
    "name:spa_x_preferred":[
        "Las Ang\u00e9licas"
    ],
    "wof:name":"Las Angelicas",
    "wof:placetype":"locality",
    "wof:population":1
},
  "geometry": {"coordinates":[-98.49250000000001,22.27944],"type":"Point"}
}