{
  "type": "Feature",
  "properties": {
    "gn:admin1_code":"20",
    "gn:admin2_code":"470.0",
    "gn:asciiname":"El Trapiche",
    "gn:country_code":"MX",
    "gn:dem":376,
    "gn:feature_class":"P",
    "gn:feature_code":"PPL",
    "gn:name":"El Trapiche",
    "gn:population":0,
    "gn:timezone":"America/Mexico_City",
    "iso:country":"MX",
    "name:spa_x_preferred":[
        "El Trapiche"
    ],
    "wof:name":"El Trapiche",
    "wof:placetype":"locality"
},
  "geometry": {"coordinates":[-95.55828,16.88792],"type":"Point"}
}