{
  "type": "Feature",
  "properties": {
    "gn:admin1_code":"11",
    "gn:admin2_code":"20.0",
    "gn:asciiname":"Media Luna",
    "gn:country_code":"MX",
    "gn:dem":2116,
    "gn:feature_class":"P",
    "gn:feature_code":"PPL",
    "gn:name":"Media Luna",
    "gn:population":53,
    "gn:timezone":"America/Mexico_City",
    "iso:country":"MX",
    "name:ina_x_preferred":[
        "Media Luna"
    ],
    "name:por_x_preferred":[
        "Media Luna"
    ],
    "name:spa_x_preferred":[
        "Media Luna"
    ],
    "wof:name":"Media Luna",
    "wof:placetype":"locality",
    "wof:population":53
},
  "geometry": {"coordinates":[-101.63306,21.23333],"type":"Point"}
}