{
  "type": "Feature",
  "properties": {
    "gn:admin1_code":"12",
    "gn:admin2_code":"73",
    "gn:asciiname":"Parota del Cuartel",
    "gn:country_code":"MX",
    "gn:dem":304,
    "gn:feature_class":"P",
    "gn:feature_code":"PPL",
    "gn:name":"Parota del Cuartel",
    "gn:population":23,
    "gn:timezone":"America/Mexico_City",
    "iso:country":"MX",
    "wof:name":"Parota del Cuartel",
    "wof:placetype":"locality",
    "wof:population":23
},
  "geometry": {"coordinates":[-101.04564000000001,18.36638],"type":"Point"}
}