{
  "type": "Feature",
  "properties": {
    "gn:admin1_code":"30.0",
    "gn:admin2_code":"161.0",
    "gn:asciiname":"El Rescate",
    "gn:country_code":"MX",
    "gn:dem":49,
    "gn:feature_class":"P",
    "gn:feature_code":"PPL",
    "gn:name":"El Rescate",
    "gn:population":2,
    "gn:timezone":"America/Mexico_City",
    "iso:country":"MX",
    "name:spa_x_preferred":[
        "El Rescate"
    ],
    "wof:name":"El Rescate",
    "wof:placetype":"locality",
    "wof:population":2
},
  "geometry": {"coordinates":[-98.44556,21.58167000000001],"type":"Point"}
}