{
  "type": "Feature",
  "properties": {
    "gn:admin1_code":"6",
    "gn:admin2_code":"16.0",
    "gn:asciiname":"Pozo Nuevo",
    "gn:country_code":"MX",
    "gn:dem":1269,
    "gn:feature_class":"P",
    "gn:feature_code":"PPL",
    "gn:name":"Pozo Nuevo",
    "gn:population":0,
    "gn:timezone":"America/Chihuahua",
    "iso:country":"MX",
    "name:spa_x_preferred":[
        "Pozo Nuevo"
    ],
    "wof:name":"Pozo Nuevo",
    "wof:placetype":"locality"
},
  "geometry": {"coordinates":[-105.04807,28.02235],"type":"Point"}
}