{
  "type": "Feature",
  "properties": {
    "gn:admin1_code":"31",
    "gn:admin2_code":"57.0",
    "gn:asciiname":"Loche",
    "gn:country_code":"MX",
    "gn:dem":13,
    "gn:feature_class":"P",
    "gn:feature_code":"PPL",
    "gn:name":"Loch\u00e9",
    "gn:population":1237,
    "gn:timezone":"America/Merida",
    "iso:country":"MX",
    "name:ceb_x_preferred":[
        "Loche"
    ],
    "name:deu_x_preferred":[
        "Loche"
    ],
    "name:fra_x_preferred":[
        "Loche"
    ],
    "name:spa_x_preferred":[
        "Loch\u00e9"
    ],
    "name:swe_x_preferred":[
        "Loche"
    ],
    "wof:name":"Loche",
    "wof:placetype":"locality",
    "wof:population":1237
},
  "geometry": {"coordinates":[-88.14565999999998,21.38828],"type":"Point"}
}