{
  "type": "Feature",
  "properties": {
    "gn:admin1_code":"26",
    "gn:admin2_code":"22",
    "gn:asciiname":"6 de Enero",
    "gn:country_code":"MX",
    "gn:dem":1076,
    "gn:feature_class":"P",
    "gn:feature_code":"PPL",
    "gn:name":"6 de Enero",
    "gn:population":13,
    "gn:timezone":"America/Hermosillo",
    "iso:country":"MX",
    "wof:name":"6 de Enero",
    "wof:placetype":"locality",
    "wof:population":13
},
  "geometry": {"coordinates":[-110.63694,30.53806],"type":"Point"}
}