{
  "type": "Feature",
  "properties": {
    "gn:admin1_code":"26",
    "gn:admin2_code":"18.0",
    "gn:asciiname":"Salsipuedes",
    "gn:country_code":"MX",
    "gn:dem":9,
    "gn:feature_class":"P",
    "gn:feature_code":"PPL",
    "gn:name":"Salsipuedes",
    "gn:population":0,
    "gn:timezone":"America/Hermosillo",
    "iso:country":"MX",
    "name:spa_x_preferred":[
        "Salsipuedes"
    ],
    "wof:name":"Salsipuedes",
    "wof:placetype":"locality"
},
  "geometry": {"coordinates":[-110.0361,27.21675],"type":"Point"}
}