{
  "type": "Feature",
  "properties": {
    "gn:admin1_code":"16",
    "gn:admin2_code":"10",
    "gn:asciiname":"Ferreria (Fierreria)",
    "gn:country_code":"MX",
    "gn:dem":612,
    "gn:feature_class":"P",
    "gn:feature_code":"PPL",
    "gn:name":"Ferrer\u00eda (Fierrer\u00eda)",
    "gn:population":27,
    "gn:timezone":"America/Mexico_City",
    "iso:country":"MX",
    "name:und_x_variant":[
        "Ferrer\u00eda (Fierrer\u00eda)"
    ],
    "wof:name":"Ferreria (Fierreria)",
    "wof:placetype":"locality",
    "wof:population":27
},
  "geometry": {"coordinates":[-102.48860999999999,18.33278],"type":"Point"}
}