{
  "type": "Feature",
  "properties": {
    "gn:admin1_code":"30",
    "gn:admin2_code":"87.0",
    "gn:asciiname":"Xoloxtla",
    "gn:country_code":"MX",
    "gn:dem":1477,
    "gn:feature_class":"P",
    "gn:feature_code":"PPL",
    "gn:name":"Xoloxtla",
    "gn:population":479,
    "gn:timezone":"America/Mexico_City",
    "iso:country":"MX",
    "wof:name":"Xoloxtla",
    "wof:placetype":"locality",
    "wof:population":479
},
  "geometry": {"coordinates":[-96.96722,19.54667],"type":"Point"}
}