{
  "type": "Feature",
  "properties": {
    "gn:admin1_code":"30.0",
    "gn:asciiname":"Sagar",
    "gn:country_code":"MX",
    "gn:dem":40,
    "gn:feature_class":"P",
    "gn:feature_code":"PPL",
    "gn:name":"Sagar",
    "gn:population":0,
    "gn:timezone":"America/Mexico_City",
    "iso:country":"MX",
    "name:ceb_x_preferred":[
        "Sagar"
    ],
    "name:deu_x_preferred":[
        "Sagar"
    ],
    "name:fas_x_preferred":[
        "\u0633\u0627\u063a\u0631"
    ],
    "name:hin_x_preferred":[
        "\u0938\u093e\u0917\u0930"
    ],
    "name:nld_x_preferred":[
        "Sagar"
    ],
    "name:rus_x_preferred":[
        "\u0421\u0435\u0439\u0433\u0430\u0440"
    ],
    "name:spa_x_preferred":[
        "Sagar"
    ],
    "name:swe_x_preferred":[
        "Sagar"
    ],
    "name:vie_x_preferred":[
        "Sagar"
    ],
    "wof:name":"Sagar",
    "wof:placetype":"locality"
},
  "geometry": {"coordinates":[-98.51821,21.75253],"type":"Point"}
}