{
  "type": "Feature",
  "properties": {
    "gn:admin1_code":"14.0",
    "gn:admin2_code":"26.0",
    "gn:asciiname":"Rancho Oscuro",
    "gn:country_code":"MX",
    "gn:dem":2118,
    "gn:feature_class":"P",
    "gn:feature_code":"PPL",
    "gn:name":"Rancho Oscuro",
    "gn:population":0,
    "gn:timezone":"America/Mexico_City",
    "iso:country":"MX",
    "name:spa_x_preferred":[
        "Rancho Oscuro"
    ],
    "wof:name":"Rancho Oscuro",
    "wof:placetype":"locality"
},
  "geometry": {"coordinates":[-103.25084,19.96787],"type":"Point"}
}