{
  "type": "Feature",
  "properties": {
    "gn:admin1_code":"32",
    "gn:admin2_code":"38.0",
    "gn:asciiname":"La Presa de San Jose",
    "gn:country_code":"MX",
    "gn:dem":2178,
    "gn:feature_class":"P",
    "gn:feature_code":"PPL",
    "gn:name":"La Presa de San Jos\u00e9",
    "gn:population":240,
    "gn:timezone":"America/Mexico_City",
    "iso:country":"MX",
    "wof:name":"La Presa de San Jose",
    "wof:placetype":"locality",
    "wof:population":240
},
  "geometry": {"coordinates":[-101.52167,22.43611],"type":"Point"}
}