{
  "type": "Feature",
  "properties": {
    "gn:admin1_code":"5",
    "gn:admin2_code":"19.0",
    "gn:asciiname":"El Tuilaito Punta de Diamante",
    "gn:country_code":"MX",
    "gn:dem":1806,
    "gn:feature_class":"P",
    "gn:feature_code":"PPL",
    "gn:name":"El Tuila\u00edto Punta de Diamante",
    "gn:population":150,
    "gn:timezone":"America/Mexico_City",
    "iso:country":"MX",
    "name:und_x_variant":[
        "El Tuila\u00edto Punta de Diamante"
    ],
    "wof:name":"El Tuilaito Punta de Diamante",
    "wof:placetype":"locality",
    "wof:population":150
},
  "geometry": {"coordinates":[-92.15472,16.28083],"type":"Point"}
}