{
  "type": "Feature",
  "properties": {
    "gn:admin1_code":"16.0",
    "gn:admin2_code":"72.0",
    "gn:asciiname":"Las Ahujas",
    "gn:country_code":"MX",
    "gn:dem":1614,
    "gn:feature_class":"P",
    "gn:feature_code":"PPL",
    "gn:name":"Las Ahujas",
    "gn:population":0,
    "gn:timezone":"America/Mexico_City",
    "iso:country":"MX",
    "name:spa_x_preferred":[
        "Las Ahujas"
    ],
    "wof:name":"Las Ahujas",
    "wof:placetype":"locality"
},
  "geometry": {"coordinates":[-100.81958,19.6122],"type":"Point"}
}