{
  "type": "Feature",
  "properties": {
    "gn:admin1_code":"12",
    "gn:admin2_code":"53.0",
    "gn:asciiname":"Carretera Nacional Avenida las Palmas",
    "gn:country_code":"MX",
    "gn:dem":93,
    "gn:feature_class":"P",
    "gn:feature_code":"PPL",
    "gn:name":"Carretera Nacional Avenida las Palmas",
    "gn:population":54,
    "gn:timezone":"America/Mexico_City",
    "iso:country":"MX",
    "wof:name":"Carretera Nacional Avenida las Palmas",
    "wof:placetype":"locality",
    "wof:population":54
},
  "geometry": {"coordinates":[-99.39682999999999,16.78724],"type":"Point"}
}