{
  "type": "Feature",
  "properties": {
    "gn:admin1_code":"17",
    "gn:admin2_code":"29.0",
    "gn:asciiname":"Campo Nuevo",
    "gn:country_code":"MX",
    "gn:dem":1187,
    "gn:feature_class":"P",
    "gn:feature_code":"PPL",
    "gn:name":"Campo Nuevo",
    "gn:population":6,
    "gn:timezone":"America/Mexico_City",
    "iso:country":"MX",
    "wof:name":"Campo Nuevo",
    "wof:placetype":"locality",
    "wof:population":6
},
  "geometry": {"coordinates":[-99.07639,18.86389],"type":"Point"}
}