{
  "type": "Feature",
  "properties": {
    "gn:admin1_code":"10",
    "gn:admin2_code":"34",
    "gn:asciiname":"El Leon",
    "gn:country_code":"MX",
    "gn:dem":568,
    "gn:feature_class":"P",
    "gn:feature_code":"PPL",
    "gn:name":"El Le\u00f3n",
    "gn:population":9,
    "gn:timezone":"America/Monterrey",
    "iso:country":"MX",
    "name:und_x_variant":[
        "El Le\u00f3n"
    ],
    "wof:name":"El Leon",
    "wof:placetype":"locality",
    "wof:population":9
},
  "geometry": {"coordinates":[-106.56977999999999,24.40221],"type":"Point"}
}