{
  "type": "Feature",
  "properties": {
    "gn:admin1_code":"4",
    "gn:admin2_code":"4.0",
    "gn:asciiname":"Ciudad del Sol",
    "gn:country_code":"MX",
    "gn:dem":4,
    "gn:feature_class":"P",
    "gn:feature_code":"PPL",
    "gn:name":"Ciudad del Sol",
    "gn:population":0,
    "gn:timezone":"America/Merida",
    "iso:country":"MX",
    "name:spa_x_preferred":[
        "Ciudad del Sol"
    ],
    "name:und_x_variant":[
        "El Sol"
    ],
    "wof:name":"Ciudad del Sol",
    "wof:placetype":"locality"
},
  "geometry": {"coordinates":[-90.70247000000001,19.47799],"type":"Point"}
}