{
  "type": "Feature",
  "properties": {
    "gn:admin1_code":"1.0",
    "gn:admin2_code":"11.0",
    "gn:asciiname":"La Paz",
    "gn:country_code":"MX",
    "gn:dem":1883,
    "gn:feature_class":"P",
    "gn:feature_code":"PPL",
    "gn:name":"La Paz",
    "gn:population":0,
    "gn:timezone":"America/Mexico_City",
    "iso:country":"MX",
    "name:spa_x_preferred":[
        "La Paz"
    ],
    "wof:name":"La Paz",
    "wof:placetype":"locality"
},
  "geometry": {"coordinates":[-102.28331,22.07418],"type":"Point"}
}