{
  "type": "Feature",
  "properties": {
    "gn:admin1_code":"31.0",
    "gn:admin2_code":"100.0",
    "gn:asciiname":"El Chaparral",
    "gn:country_code":"MX",
    "gn:dem":7,
    "gn:feature_class":"P",
    "gn:feature_code":"PPL",
    "gn:name":"El Chaparral",
    "gn:population":0,
    "gn:timezone":"America/Merida",
    "iso:country":"MX",
    "name:spa_x_preferred":[
        "El Chaparral"
    ],
    "wof:name":"El Chaparral",
    "wof:placetype":"locality"
},
  "geometry": {"coordinates":[-89.72924999999999,21.03537],"type":"Point"}
}