{
  "type": "Feature",
  "properties": {
    "gn:admin1_code":"7.0",
    "gn:asciiname":"La Trampita",
    "gn:country_code":"MX",
    "gn:dem":652,
    "gn:feature_class":"P",
    "gn:feature_code":"PPL",
    "gn:name":"La Trampita",
    "gn:population":0,
    "gn:timezone":"America/Monterrey",
    "iso:country":"MX",
    "name:spa_x_preferred":[
        "La Trampita"
    ],
    "wof:name":"La Trampita",
    "wof:placetype":"locality"
},
  "geometry": {"coordinates":[-101.06191,26.80574],"type":"Point"}
}