{
  "type": "Feature",
  "properties": {
    "gn:admin1_code":"23",
    "gn:admin2_code":"4.0",
    "gn:asciiname":"San Fernando",
    "gn:country_code":"MX",
    "gn:dem":11,
    "gn:feature_class":"P",
    "gn:feature_code":"PPL",
    "gn:name":"San Fernando",
    "gn:population":9,
    "gn:timezone":"America/Cancun",
    "iso:country":"MX",
    "wof:name":"San Fernando",
    "wof:placetype":"locality",
    "wof:population":9
},
  "geometry": {"coordinates":[-88.25917,18.58583],"type":"Point"}
}