{
  "type": "Feature",
  "properties": {
    "gn:admin1_code":"11.0",
    "gn:admin2_code":"30.0",
    "gn:asciiname":"El Pirul",
    "gn:country_code":"MX",
    "gn:dem":2147,
    "gn:feature_class":"P",
    "gn:feature_code":"PPL",
    "gn:name":"El Pirul",
    "gn:population":0,
    "gn:timezone":"America/Mexico_City",
    "iso:country":"MX",
    "name:spa_x_preferred":[
        "El Pirul"
    ],
    "wof:name":"El Pirul",
    "wof:placetype":"locality"
},
  "geometry": {"coordinates":[-101.25731,21.46154],"type":"Point"}
}