{
  "type": "Feature",
  "properties": {
    "gn:admin1_code":"31",
    "gn:admin2_code":"79.0",
    "gn:asciiname":"San Jose Ucil",
    "gn:country_code":"MX",
    "gn:dem":129,
    "gn:feature_class":"P",
    "gn:feature_code":"PPL",
    "gn:name":"San Jos\u00e9 Ucil",
    "gn:population":0,
    "gn:timezone":"America/Merida",
    "iso:country":"MX",
    "name:spa_x_preferred":[
        "San Jos\u00e9 Ucil"
    ],
    "wof:name":"San Jose Ucil",
    "wof:placetype":"locality"
},
  "geometry": {"coordinates":[-89.23713000000002,19.91962],"type":"Point"}
}