{
  "type": "Feature",
  "properties": {
    "gn:admin1_code":"5.0",
    "gn:admin2_code":"107.0",
    "gn:asciiname":"La Asuncion",
    "gn:country_code":"MX",
    "gn:dem":723,
    "gn:feature_class":"P",
    "gn:feature_code":"PPL",
    "gn:name":"La Asunci\u00f3n",
    "gn:population":0,
    "gn:timezone":"America/Mexico_City",
    "iso:country":"MX",
    "name:spa_x_preferred":[
        "La Asunci\u00f3n"
    ],
    "wof:name":"La Asuncion",
    "wof:placetype":"locality"
},
  "geometry": {"coordinates":[-93.26297,16.10055],"type":"Point"}
}