{
  "type": "Feature",
  "properties": {
    "gn:admin1_code":"16.0",
    "gn:admin2_code":"107.0",
    "gn:asciiname":"Quinta Evangelina",
    "gn:country_code":"MX",
    "gn:dem":2304,
    "gn:feature_class":"P",
    "gn:feature_code":"PPL",
    "gn:name":"Quinta Evangelina",
    "gn:population":0,
    "gn:timezone":"America/Mexico_City",
    "iso:country":"MX",
    "name:spa_x_preferred":[
        "Quinta Evangelina"
    ],
    "wof:name":"Quinta Evangelina",
    "wof:placetype":"locality"
},
  "geometry": {"coordinates":[-101.89085,19.81715],"type":"Point"}
}