{
  "type": "Feature",
  "properties": {
    "gn:admin1_code":"26",
    "gn:admin2_code":"60.0",
    "gn:asciiname":"Nogaito",
    "gn:country_code":"MX",
    "gn:dem":742,
    "gn:feature_class":"P",
    "gn:feature_code":"PPL",
    "gn:name":"Nogaito",
    "gn:population":0,
    "gn:timezone":"America/Hermosillo",
    "iso:country":"MX",
    "wof:name":"Nogaito",
    "wof:placetype":"locality"
},
  "geometry": {"coordinates":[-111.3954,31.04801],"type":"Point"}
}