{
  "type": "Feature",
  "properties": {
    "gn:admin1_code":"5",
    "gn:admin2_code":"59.0",
    "gn:asciiname":"El Carmen",
    "gn:country_code":"MX",
    "gn:dem":675,
    "gn:feature_class":"P",
    "gn:feature_code":"PPL",
    "gn:name":"El Carmen",
    "gn:population":66,
    "gn:timezone":"America/Mexico_City",
    "iso:country":"MX",
    "wof:name":"El Carmen",
    "wof:placetype":"locality",
    "wof:population":66
},
  "geometry": {"coordinates":[-91.72417,16.92444],"type":"Point"}
}