{
  "type": "Feature",
  "properties": {
    "gn:admin1_code":"10",
    "gn:admin2_code":"14",
    "gn:asciiname":"Las Joyas",
    "gn:country_code":"MX",
    "gn:dem":1800,
    "gn:feature_class":"P",
    "gn:feature_code":"PPL",
    "gn:name":"Las Joyas",
    "gn:population":37,
    "gn:timezone":"America/Monterrey",
    "iso:country":"MX",
    "wof:name":"Las Joyas",
    "wof:placetype":"locality",
    "wof:population":37
},
  "geometry": {"coordinates":[-104.6444,23.16346],"type":"Point"}
}