{
  "type": "Feature",
  "properties": {
    "gn:admin1_code":"30.0",
    "gn:admin2_code":"13.0",
    "gn:asciiname":"Palizada",
    "gn:country_code":"MX",
    "gn:dem":126,
    "gn:feature_class":"P",
    "gn:feature_code":"PPL",
    "gn:name":"Palizada",
    "gn:population":0,
    "gn:timezone":"America/Mexico_City",
    "iso:country":"MX",
    "name:spa_x_preferred":[
        "Palizada"
    ],
    "wof:name":"Palizada",
    "wof:placetype":"locality"
},
  "geometry": {"coordinates":[-97.67164,21.31833],"type":"Point"}
}