{
  "type": "Feature",
  "properties": {
    "gn:admin1_code":"30.0",
    "gn:admin2_code":"13.0",
    "gn:asciiname":"Palizada",
    "gn:country_code":"MX",
    "gn:dem":126,
    "gn:feature_class":"P",
    "gn:feature_code":"PPL",
    "gn:name":"Palizada",
    "gn:population":0,
    "gn:timezone":"America/Mexico_City",
    "iso:country":"MX",
    "name:deu_x_preferred":[
        "Palizada"
    ],
    "name:ind_x_preferred":[
        "Palizada"
    ],
    "name:jpn_x_preferred":[
        "\u30d1\u30ea\u30b5\u30fc\u30c0"
    ],
    "name:nld_x_preferred":[
        "Palizada"
    ],
    "name:nor_x_preferred":[
        "Palizada"
    ],
    "name:pol_x_preferred":[
        "Palizada"
    ],
    "name:por_x_preferred":[
        "Palizada"
    ],
    "name:rus_x_preferred":[
        "\u041f\u0430\u043b\u0438\u0441\u0430\u0434\u0430"
    ],
    "name:sco_x_preferred":[
        "Palizada"
    ],
    "name:spa_x_preferred":[
        "Palizada"
    ],
    "name:srp_x_preferred":[
        "\u041f\u0430\u043b\u0438\u0437\u0430\u0434\u0430"
    ],
    "wof:name":"Palizada",
    "wof:placetype":"locality"
},
  "geometry": {"coordinates":[-97.67164,21.31833],"type":"Point"}
}