{
  "type": "Feature",
  "properties": {
    "gn:admin1_code":"7",
    "gn:admin2_code":"30.0",
    "gn:asciiname":"Tanque de San Carlos",
    "gn:country_code":"MX",
    "gn:dem":1665,
    "gn:feature_class":"P",
    "gn:feature_code":"PPL",
    "gn:name":"Tanque de San Carlos",
    "gn:population":0,
    "gn:timezone":"America/Monterrey",
    "iso:country":"MX",
    "name:spa_x_preferred":[
        "Tanque de San Carlos"
    ],
    "name:und_x_variant":[
        "Tanque San Carlos"
    ],
    "wof:name":"Tanque de San Carlos",
    "wof:placetype":"locality"
},
  "geometry": {"coordinates":[-101.4597,24.815],"type":"Point"}
}