{
  "type": "Feature",
  "properties": {
    "gn:admin1_code":"6",
    "gn:admin2_code":"19.0",
    "gn:asciiname":"Rancho los Ciruelos",
    "gn:country_code":"MX",
    "gn:dem":1473,
    "gn:feature_class":"P",
    "gn:feature_code":"PPL",
    "gn:name":"Rancho los Ciruelos",
    "gn:population":4,
    "gn:timezone":"America/Chihuahua",
    "iso:country":"MX",
    "wof:name":"Rancho los Ciruelos",
    "wof:placetype":"locality",
    "wof:population":4
},
  "geometry": {"coordinates":[-106.22659,28.17436],"type":"Point"}
}