{
  "type": "Feature",
  "properties": {
    "gn:admin1_code":"5",
    "gn:admin2_code":"33.0",
    "gn:asciiname":"El Zapotal (Buenos Aires)",
    "gn:country_code":"MX",
    "gn:dem":718,
    "gn:feature_class":"P",
    "gn:feature_code":"PPL",
    "gn:name":"El Zapotal (Buenos Aires)",
    "gn:population":5,
    "gn:timezone":"America/Mexico_City",
    "iso:country":"MX",
    "wof:name":"El Zapotal (Buenos Aires)",
    "wof:placetype":"locality",
    "wof:population":5
},
  "geometry": {"coordinates":[-93.26027999999999,17.24611],"type":"Point"}
}