{
  "type": "Feature",
  "properties": {
    "gn:admin1_code":"16",
    "gn:admin2_code":"101",
    "gn:asciiname":"Puerto del Durazno",
    "gn:country_code":"MX",
    "gn:dem":1677,
    "gn:feature_class":"P",
    "gn:feature_code":"PPL",
    "gn:name":"Puerto del Durazno",
    "gn:population":26,
    "gn:timezone":"America/Mexico_City",
    "iso:country":"MX",
    "wof:name":"Puerto del Durazno",
    "wof:placetype":"locality",
    "wof:population":26
},
  "geometry": {"coordinates":[-100.80056,19.40278],"type":"Point"}
}