{
  "type": "Feature",
  "properties": {
    "gn:admin1_code":"14",
    "gn:admin2_code":"30.0",
    "gn:asciiname":"La Tepamera (La Calerita)",
    "gn:country_code":"MX",
    "gn:dem":1599,
    "gn:feature_class":"P",
    "gn:feature_code":"PPL",
    "gn:name":"La Tepamera (La Calerita)",
    "gn:population":5,
    "gn:timezone":"America/Mexico_City",
    "iso:country":"MX",
    "wof:name":"La Tepamera (La Calerita)",
    "wof:placetype":"locality",
    "wof:population":5
},
  "geometry": {"coordinates":[-103.11111,20.36667000000001],"type":"Point"}
}