{
  "type": "Feature",
  "properties": {
    "gn:admin1_code":"5.0",
    "gn:admin2_code":"54.0",
    "gn:asciiname":"Tuxtlita",
    "gn:country_code":"MX",
    "gn:dem":9,
    "gn:feature_class":"P",
    "gn:feature_code":"PPL",
    "gn:name":"Tuxtlita",
    "gn:population":0,
    "gn:timezone":"America/Mexico_City",
    "iso:country":"MX",
    "name:spa_x_preferred":[
        "Tuxtlita"
    ],
    "wof:name":"Tuxtlita",
    "wof:placetype":"locality"
},
  "geometry": {"coordinates":[-92.48873,14.84563],"type":"Point"}
}