{
  "type": "Feature",
  "properties": {
    "gn:admin1_code":"20",
    "gn:admin2_code":"2.0",
    "gn:asciiname":"Veintiuno de Mayo",
    "gn:country_code":"MX",
    "gn:dem":92,
    "gn:feature_class":"P",
    "gn:feature_code":"PPL",
    "gn:name":"Veintiuno de Mayo",
    "gn:population":0,
    "gn:timezone":"America/Mexico_City",
    "iso:country":"MX",
    "name:spa_x_preferred":[
        "Veintiuno de Mayo"
    ],
    "wof:name":"Veintiuno de Mayo",
    "wof:placetype":"locality"
},
  "geometry": {"coordinates":[-96.60550000000001,18.42912],"type":"Point"}
}