{
  "type": "Feature",
  "properties": {
    "gn:admin1_code":"10",
    "gn:admin2_code":"34",
    "gn:asciiname":"La Trampa",
    "gn:country_code":"MX",
    "gn:dem":2504,
    "gn:feature_class":"P",
    "gn:feature_code":"PPL",
    "gn:name":"La Trampa",
    "gn:population":36,
    "gn:timezone":"America/Monterrey",
    "iso:country":"MX",
    "wof:name":"La Trampa",
    "wof:placetype":"locality",
    "wof:population":36
},
  "geometry": {"coordinates":[-106.91011,25.59413],"type":"Point"}
}