{
  "type": "Feature",
  "properties": {
    "gn:admin1_code":"30.0",
    "gn:admin2_code":"151.0",
    "gn:asciiname":"Benito Juarez Segundo",
    "gn:country_code":"MX",
    "gn:dem":22,
    "gn:feature_class":"P",
    "gn:feature_code":"PPL",
    "gn:name":"Benito Ju\u00e1rez Segundo",
    "gn:population":177,
    "gn:timezone":"America/Mexico_City",
    "iso:country":"MX",
    "name:spa_x_preferred":[
        "Benito Ju\u00e1rez Segundo"
    ],
    "wof:name":"Benito Juarez Segundo",
    "wof:placetype":"locality",
    "wof:population":177
},
  "geometry": {"coordinates":[-97.56999999999999,21.36194],"type":"Point"}
}