{
  "type": "Feature",
  "properties": {
    "gn:admin1_code":"24",
    "gn:admin2_code":"30.0",
    "gn:asciiname":"Los Nogales (Nogales de Santa Cruz)",
    "gn:country_code":"MX",
    "gn:dem":1368,
    "gn:feature_class":"P",
    "gn:feature_code":"PPL",
    "gn:name":"Los Nogales (Nogales de Santa Cruz)",
    "gn:population":92,
    "gn:timezone":"America/Mexico_City",
    "iso:country":"MX",
    "wof:name":"Los Nogales (Nogales de Santa Cruz)",
    "wof:placetype":"locality",
    "wof:population":92
},
  "geometry": {"coordinates":[-100.43416999999999,22.15722],"type":"Point"}
}