{
  "type": "Feature",
  "properties": {
    "gn:admin1_code":"11",
    "gn:admin2_code":"2",
    "gn:asciiname":"El Cerrito (El Palillo)",
    "gn:country_code":"MX",
    "gn:dem":1859,
    "gn:feature_class":"P",
    "gn:feature_code":"PPL",
    "gn:name":"El Cerrito (El Palillo)",
    "gn:population":19,
    "gn:timezone":"America/Mexico_City",
    "iso:country":"MX",
    "wof:name":"El Cerrito (El Palillo)",
    "wof:placetype":"locality",
    "wof:population":19
},
  "geometry": {"coordinates":[-100.99946,19.96868],"type":"Point"}
}