{
  "type": "Feature",
  "properties": {
    "iso:country":"MX",
    "name:cat_x_preferred":[
        "Progreso"
    ],
    "name:epo_x_preferred":[
        "Progreso"
    ],
    "name:eus_x_preferred":[
        "Progreso"
    ],
    "name:hbs_x_preferred":[
        "Op\u0161tina Progreso"
    ],
    "name:nld_x_preferred":[
        "Progreso"
    ],
    "name:por_x_preferred":[
        "Progreso"
    ],
    "name:rus_x_preferred":[
        "\u041f\u0440\u043e\u0433\u0440\u0435\u0441\u043e"
    ],
    "name:spa_x_preferred":[
        "Chelem Puerto",
        "Municipio de Progreso"
    ],
    "qs:gn_adm0_cc":"MX",
    "qs:gn_local":3521108,
    "qs:gn_nam_loc":"Progreso, Progreso, Yucatan, MX",
    "qs:gn_namadm1":"31",
    "qs:local_max":324,
    "qs:local_sum":557,
    "qs:localhoods":3,
    "qs:name":"Chelem Puerto",
    "qs:name_adm0":"M\u00e9xico",
    "qs:name_adm1":"Yucatan",
    "qs:name_adm2":"Progreso",
    "qs:name_local":"Progreso",
    "qs:photo_max":5,
    "qs:photo_sum":30,
    "qs:placetype":"Suburb",
    "qs:quad_count":14,
    "qs:woe_adm0":23424900,
    "qs:woe_adm1":2346294,
    "qs:woe_adm2":12601984,
    "qs:woe_lau":0,
    "qs:woe_local":137541,
    "qs:woe_ver":"7.10.0",
    "wof:lang":[
        "spa"
    ],
    "wof:name":"Chelem Puerto",
    "wof:placetype":"neighbourhood"
},
  "geometry": {"coordinates":[-89.74237100000001,21.268558],"type":"Point"}
}