{
  "type": "Feature",
  "properties": {
    "gn:admin1_code":"28.0",
    "gn:admin2_code":"19.0",
    "gn:asciiname":"Quintanillas",
    "gn:country_code":"MX",
    "gn:dem":230,
    "gn:feature_class":"P",
    "gn:feature_code":"PPL",
    "gn:name":"Quintanillas",
    "gn:population":3,
    "gn:timezone":"America/Monterrey",
    "iso:country":"MX",
    "name:spa_x_preferred":[
        "Quintanillas"
    ],
    "wof:name":"Quintanillas",
    "wof:placetype":"locality",
    "wof:population":3
},
  "geometry": {"coordinates":[-98.9425,23.51611],"type":"Point"}
}