{
  "type": "Feature",
  "properties": {
    "gn:admin1_code":"16",
    "gn:admin2_code":"49",
    "gn:asciiname":"El Salto Grande",
    "gn:country_code":"MX",
    "gn:dem":1225,
    "gn:feature_class":"P",
    "gn:feature_code":"PPL",
    "gn:name":"El Salto Grande",
    "gn:population":22,
    "gn:timezone":"America/Mexico_City",
    "iso:country":"MX",
    "wof:name":"El Salto Grande",
    "wof:placetype":"locality",
    "wof:population":22
},
  "geometry": {"coordinates":[-101.0625,19.23639],"type":"Point"}
}