{
  "type": "Feature",
  "properties": {
    "gn:admin1_code":"24.0",
    "gn:admin2_code":"16.0",
    "gn:asciiname":"Los Retonos",
    "gn:country_code":"MX",
    "gn:dem":59,
    "gn:feature_class":"P",
    "gn:feature_code":"PPL",
    "gn:name":"Los Reto\u00f1os",
    "gn:population":0,
    "gn:timezone":"America/Mexico_City",
    "iso:country":"MX",
    "name:spa_x_preferred":[
        "Los Reto\u00f1os"
    ],
    "wof:name":"Los Retonos",
    "wof:placetype":"locality"
},
  "geometry": {"coordinates":[-98.43315,22.25126],"type":"Point"}
}