{
  "type": "Feature",
  "properties": {
    "gn:admin1_code":"24",
    "gn:admin2_code":"30.0",
    "gn:asciiname":"Carrizal de Guadalupe",
    "gn:country_code":"MX",
    "gn:dem":1275,
    "gn:feature_class":"P",
    "gn:feature_code":"PPL",
    "gn:name":"Carrizal de Guadalupe",
    "gn:population":104,
    "gn:timezone":"America/Mexico_City",
    "iso:country":"MX",
    "wof:name":"Carrizal de Guadalupe",
    "wof:placetype":"locality",
    "wof:population":104
},
  "geometry": {"coordinates":[-100.41194,22.13944],"type":"Point"}
}