{
  "type": "Feature",
  "properties": {
    "gn:admin1_code":"6",
    "gn:admin2_code":"27.0",
    "gn:asciiname":"Huichaborare",
    "gn:country_code":"MX",
    "gn:dem":2395,
    "gn:feature_class":"P",
    "gn:feature_code":"PPL",
    "gn:name":"Huichab\u00f3rare",
    "gn:population":0,
    "gn:timezone":"America/Chihuahua",
    "iso:country":"MX",
    "name:spa_x_preferred":[
        "Huichab\u00f3rare"
    ],
    "wof:name":"Huichaborare",
    "wof:placetype":"locality"
},
  "geometry": {"coordinates":[-107.19822000000001,27.02047],"type":"Point"}
}