{
  "type": "Feature",
  "properties": {
    "gn:admin1_code":"14",
    "gn:admin2_code":"80.0",
    "gn:asciiname":"Teleacapan",
    "gn:country_code":"MX",
    "gn:dem":149,
    "gn:feature_class":"P",
    "gn:feature_code":"PPL",
    "gn:name":"Teleacapan",
    "gn:population":102,
    "gn:timezone":"America/Bahia_Banderas",
    "iso:country":"MX",
    "wof:name":"Teleacapan",
    "wof:placetype":"locality",
    "wof:population":102
},
  "geometry": {"coordinates":[-104.98556000000001,20.90833],"type":"Point"}
}