{
  "type": "Feature",
  "properties": {
    "gn:admin1_code":"12",
    "gn:admin2_code":"57.0",
    "gn:asciiname":"Puerto Vicente Guerrero",
    "gn:country_code":"MX",
    "gn:dem":16,
    "gn:feature_class":"P",
    "gn:feature_code":"PPL",
    "gn:name":"Puerto Vicente Guerrero",
    "gn:population":413,
    "gn:timezone":"America/Mexico_City",
    "iso:country":"MX",
    "wof:name":"Puerto Vicente Guerrero",
    "wof:placetype":"locality",
    "wof:population":413
},
  "geometry": {"coordinates":[-101.05500000000001,17.27556],"type":"Point"}
}