{
  "type": "Feature",
  "properties": {
    "gn:admin1_code":"5",
    "gn:admin2_code":"52.0",
    "gn:asciiname":"La Realidad",
    "gn:country_code":"MX",
    "gn:dem":948,
    "gn:feature_class":"P",
    "gn:feature_code":"PPL",
    "gn:name":"La Realidad",
    "gn:population":6,
    "gn:timezone":"America/Mexico_City",
    "iso:country":"MX",
    "wof:name":"La Realidad",
    "wof:placetype":"locality",
    "wof:population":6
},
  "geometry": {"coordinates":[-91.65889,16.255],"type":"Point"}
}