{
  "type": "Feature",
  "properties": {
    "gn:admin1_code":"2.0",
    "gn:admin2_code":"4.0",
    "gn:asciiname":"Los Galleros",
    "gn:country_code":"MX",
    "gn:dem":166,
    "gn:feature_class":"P",
    "gn:feature_code":"PPL",
    "gn:name":"Los Galleros",
    "gn:population":0,
    "gn:timezone":"America/Tijuana",
    "iso:country":"MX",
    "name:spa_x_preferred":[
        "Los Galleros"
    ],
    "wof:name":"Los Galleros",
    "wof:placetype":"locality"
},
  "geometry": {"coordinates":[-117.05918,32.4416],"type":"Point"}
}