{
  "type": "Feature",
  "properties": {
    "gn:admin1_code":"21.0",
    "gn:admin2_code":"197.0",
    "gn:asciiname":"Mecatlan de las Flores",
    "gn:country_code":"MX",
    "gn:dem":854,
    "gn:feature_class":"P",
    "gn:feature_code":"PPL",
    "gn:name":"Mecatl\u00e1n de las Flores",
    "gn:population":379,
    "gn:timezone":"America/Mexico_City",
    "iso:country":"MX",
    "name:spa_x_preferred":[
        "Mecatl\u00e1n de las Flores"
    ],
    "wof:name":"Mecatlan de las Flores",
    "wof:placetype":"locality",
    "wof:population":379
},
  "geometry": {"coordinates":[-97.92806,20.25222],"type":"Point"}
}