{
  "type": "Feature",
  "properties": {
    "gn:admin1_code":"26",
    "gn:admin2_code":"57.0",
    "gn:asciiname":"Las Tinajas",
    "gn:country_code":"MX",
    "gn:dem":949,
    "gn:feature_class":"P",
    "gn:feature_code":"PPL",
    "gn:name":"Las Tinajas",
    "gn:population":0,
    "gn:timezone":"America/Hermosillo",
    "iso:country":"MX",
    "name:spa_x_preferred":[
        "Las Tinajas"
    ],
    "wof:name":"Las Tinajas",
    "wof:placetype":"locality"
},
  "geometry": {"coordinates":[-109.94444,29.47139],"type":"Point"}
}