{
  "type": "Feature",
  "properties": {
    "gn:admin1_code":"21.0",
    "gn:admin2_code":"197.0",
    "gn:asciiname":"El Carpintero",
    "gn:country_code":"MX",
    "gn:dem":166,
    "gn:feature_class":"P",
    "gn:feature_code":"PPL",
    "gn:name":"El Carpintero",
    "gn:population":3,
    "gn:timezone":"America/Mexico_City",
    "iso:country":"MX",
    "name:spa_x_preferred":[
        "El Carpintero"
    ],
    "wof:name":"El Carpintero",
    "wof:placetype":"locality",
    "wof:population":3
},
  "geometry": {"coordinates":[-97.7671,20.42751],"type":"Point"}
}