{
  "type": "Feature",
  "properties": {
    "gn:admin1_code":"26",
    "gn:admin2_code":"51.0",
    "gn:asciiname":"El Sauzal",
    "gn:country_code":"MX",
    "gn:dem":949,
    "gn:feature_class":"P",
    "gn:feature_code":"PPL",
    "gn:name":"El Sauzal",
    "gn:population":1,
    "gn:timezone":"America/Hermosillo",
    "iso:country":"MX",
    "name:spa_x_preferred":[
        "El Sauzal"
    ],
    "wof:name":"El Sauzal",
    "wof:placetype":"locality",
    "wof:population":1
},
  "geometry": {"coordinates":[-109.1425,28.10083],"type":"Point"}
}