{
  "type": "Feature",
  "properties": {
    "gn:admin1_code":"13",
    "gn:admin2_code":"68.0",
    "gn:asciiname":"Chapaltepec",
    "gn:country_code":"MX",
    "gn:dem":719,
    "gn:feature_class":"P",
    "gn:feature_code":"PPL",
    "gn:name":"Chapaltepec",
    "gn:population":0,
    "gn:timezone":"America/Mexico_City",
    "iso:country":"MX",
    "name:spa_x_preferred":[
        "Chapultepec"
    ],
    "name:spa_x_variant":[
        "Chapaltepec"
    ],
    "wof:name":"Chapaltepec",
    "wof:placetype":"locality"
},
  "geometry": {"coordinates":[-98.47069999999999,20.85254],"type":"Point"}
}