{
  "type": "Feature",
  "properties": {
    "gn:admin1_code":"19.0",
    "gn:asciiname":"El Nopal",
    "gn:country_code":"MX",
    "gn:dem":1442,
    "gn:feature_class":"P",
    "gn:feature_code":"PPL",
    "gn:name":"El Nopal",
    "gn:population":0,
    "gn:timezone":"America/Monterrey",
    "iso:country":"MX",
    "name:spa_x_preferred":[
        "El Nopal"
    ],
    "wof:name":"El Nopal",
    "wof:placetype":"locality"
},
  "geometry": {"coordinates":[-100.02491999999999,24.81542],"type":"Point"}
}