{
  "type": "Feature",
  "properties": {
    "gn:admin1_code":"5.0",
    "gn:admin2_code":"97.0",
    "gn:asciiname":"Coral",
    "gn:country_code":"MX",
    "gn:dem":322,
    "gn:feature_class":"P",
    "gn:feature_code":"PPL",
    "gn:name":"Coral",
    "gn:population":0,
    "gn:timezone":"America/Mexico_City",
    "iso:country":"MX",
    "name:spa_x_preferred":[
        "Coral"
    ],
    "wof:name":"Coral",
    "wof:placetype":"locality"
},
  "geometry": {"coordinates":[-93.65273000000001,16.06183],"type":"Point"}
}