{
  "type": "Feature",
  "properties": {
    "gn:admin1_code":"28.0",
    "gn:admin2_code":"35.0",
    "gn:asciiname":"Santa Catalina Numero Uno",
    "gn:country_code":"MX",
    "gn:dem":33,
    "gn:feature_class":"P",
    "gn:feature_code":"PPL",
    "gn:name":"Santa Catalina N\u00famero Uno",
    "gn:population":0,
    "gn:timezone":"America/Monterrey",
    "iso:country":"MX",
    "name:spa_x_preferred":[
        "Santa Catalina N\u00famero Uno"
    ],
    "wof:name":"Santa Catalina Numero Uno",
    "wof:placetype":"locality"
},
  "geometry": {"coordinates":[-98.09143,24.74309],"type":"Point"}
}