{
  "type": "Feature",
  "properties": {
    "gn:admin1_code":"27",
    "gn:admin2_code":"15.0",
    "gn:asciiname":"Mendoza",
    "gn:country_code":"MX",
    "gn:dem":114,
    "gn:feature_class":"P",
    "gn:feature_code":"PPL",
    "gn:name":"Mendoza",
    "gn:population":0,
    "gn:timezone":"America/Mexico_City",
    "iso:country":"MX",
    "wof:name":"Mendoza",
    "wof:placetype":"locality"
},
  "geometry": {"coordinates":[-92.75,17.43333],"type":"Point"}
}