{
  "type": "Feature",
  "properties": {
    "gn:admin1_code":"4",
    "gn:admin2_code":"3.0",
    "gn:asciiname":"Palma Sola",
    "gn:country_code":"MX",
    "gn:dem":32,
    "gn:feature_class":"P",
    "gn:feature_code":"PPL",
    "gn:name":"Palma Sola",
    "gn:population":5,
    "gn:timezone":"America/Merida",
    "iso:country":"MX",
    "name:ceb_x_preferred":[
        "Palma Sola"
    ],
    "name:deu_x_preferred":[
        "Palma Sola"
    ],
    "name:fra_x_preferred":[
        "Palma Sola"
    ],
    "name:spa_x_preferred":[
        "Palma Sola"
    ],
    "name:srp_x_preferred":[
        "\u041f\u0430\u043b\u043c\u0430 \u0421\u043e\u043b\u0430"
    ],
    "name:swe_x_preferred":[
        "Palma Sola"
    ],
    "wof:name":"Palma Sola",
    "wof:placetype":"locality",
    "wof:population":5
},
  "geometry": {"coordinates":[-91.15944,18.35722],"type":"Point"}
}