{
  "type": "Feature",
  "properties": {
    "gn:admin1_code":"5",
    "gn:admin2_code":"109.0",
    "gn:asciiname":"Santa Candelaria",
    "gn:country_code":"MX",
    "gn:dem":933,
    "gn:feature_class":"P",
    "gn:feature_code":"PPL",
    "gn:name":"Santa Candelaria",
    "gn:population":187,
    "gn:timezone":"America/Mexico_City",
    "iso:country":"MX",
    "wof:name":"Santa Candelaria",
    "wof:placetype":"locality",
    "wof:population":187
},
  "geometry": {"coordinates":[-92.31056,17.16222],"type":"Point"}
}