{
  "type": "Feature",
  "properties": {
    "gn:admin1_code":"4",
    "gn:admin2_code":"3.0",
    "gn:asciiname":"Polboxal",
    "gn:country_code":"MX",
    "gn:dem":8,
    "gn:feature_class":"P",
    "gn:feature_code":"PPL",
    "gn:name":"Polboxal",
    "gn:population":0,
    "gn:timezone":"America/Merida",
    "iso:country":"MX",
    "name:spa_x_preferred":[
        "Polboxal"
    ],
    "name:und_x_variant":[
        "Polvoxal y Anexo",
        "Polvaxal",
        "Polvoxal"
    ],
    "wof:name":"Polboxal",
    "wof:placetype":"locality"
},
  "geometry": {"coordinates":[-91.24302,18.5541],"type":"Point"}
}