{
  "type": "Feature",
  "properties": {
    "gn:admin1_code":"32.0",
    "gn:admin2_code":"38.0",
    "gn:asciiname":"El Padre",
    "gn:country_code":"MX",
    "gn:dem":2204,
    "gn:feature_class":"P",
    "gn:feature_code":"PPL",
    "gn:name":"El Padre",
    "gn:population":0,
    "gn:timezone":"America/Mexico_City",
    "iso:country":"MX",
    "wof:name":"El Padre",
    "wof:placetype":"locality"
},
  "geometry": {"coordinates":[-101.71666999999999,22.26667],"type":"Point"}
}