{
  "type": "Feature",
  "properties": {
    "gn:admin1_code":"5",
    "gn:admin2_code":"80.0",
    "gn:asciiname":"San Francisco",
    "gn:country_code":"MX",
    "gn:dem":1701,
    "gn:feature_class":"P",
    "gn:feature_code":"PPL",
    "gn:name":"San Francisco",
    "gn:population":160,
    "gn:timezone":"America/Mexico_City",
    "iso:country":"MX",
    "wof:name":"San Francisco",
    "wof:placetype":"locality",
    "wof:population":160
},
  "geometry": {"coordinates":[-92.455,15.49583],"type":"Point"}
}