{
  "type": "Feature",
  "properties": {
    "gn:admin1_code":"21",
    "gn:admin2_code":"206",
    "gn:asciiname":"Mirador el Chico",
    "gn:country_code":"MX",
    "gn:dem":1485,
    "gn:feature_class":"P",
    "gn:feature_code":"PPL",
    "gn:name":"Mirador el Chico",
    "gn:population":28,
    "gn:timezone":"America/Mexico_City",
    "iso:country":"MX",
    "wof:name":"Mirador el Chico",
    "wof:placetype":"locality",
    "wof:population":28
},
  "geometry": {"coordinates":[-98.06995999999999,18.51489],"type":"Point"}
}