{
  "type": "Feature",
  "properties": {
    "gn:admin1_code":"16",
    "gn:admin2_code":"52.0",
    "gn:asciiname":"Playas Cuatas",
    "gn:country_code":"MX",
    "gn:dem":23,
    "gn:feature_class":"P",
    "gn:feature_code":"PPL",
    "gn:name":"Playas Cuatas",
    "gn:population":0,
    "gn:timezone":"America/Mexico_City",
    "iso:country":"MX",
    "name:spa_x_preferred":[
        "Playas Cuatas"
    ],
    "wof:name":"Playas Cuatas",
    "wof:placetype":"locality"
},
  "geometry": {"coordinates":[-102.67829999999999,18.05805],"type":"Point"}
}