{
  "type": "Feature",
  "properties": {
    "gn:admin1_code":"11",
    "gn:admin2_code":"8",
    "gn:asciiname":"La Calera",
    "gn:country_code":"MX",
    "gn:dem":1724,
    "gn:feature_class":"P",
    "gn:feature_code":"PPL",
    "gn:name":"La Calera",
    "gn:population":12,
    "gn:timezone":"America/Mexico_City",
    "iso:country":"MX",
    "wof:name":"La Calera",
    "wof:placetype":"locality",
    "wof:population":12
},
  "geometry": {"coordinates":[-101.84417000000001,20.7725],"type":"Point"}
}