{
  "type": "Feature",
  "properties": {
    "gn:admin1_code":"16",
    "gn:admin2_code":"108.0",
    "gn:asciiname":"Rancho de los Diaz",
    "gn:country_code":"MX",
    "gn:dem":1562,
    "gn:feature_class":"P",
    "gn:feature_code":"PPL",
    "gn:name":"Rancho de los D\u00edaz",
    "gn:population":5,
    "gn:timezone":"America/Mexico_City",
    "iso:country":"MX",
    "name:und_x_variant":[
        "Rancho de los D\u00edaz"
    ],
    "wof:name":"Rancho de los Diaz",
    "wof:placetype":"locality",
    "wof:population":5
},
  "geometry": {"coordinates":[-102.32111,20.00444],"type":"Point"}
}