{
  "type": "Feature",
  "properties": {
    "gn:admin1_code":"12",
    "gn:admin2_code":"23.0",
    "gn:asciiname":"Pozos de Agua (Pozas de Agua)",
    "gn:country_code":"MX",
    "gn:dem":33,
    "gn:feature_class":"P",
    "gn:feature_code":"PPL",
    "gn:name":"Pozos de Agua (Pozas de Agua)",
    "gn:population":5,
    "gn:timezone":"America/Mexico_City",
    "iso:country":"MX",
    "wof:name":"Pozos de Agua (Pozas de Agua)",
    "wof:placetype":"locality",
    "wof:population":5
},
  "geometry": {"coordinates":[-98.46588,16.51952],"type":"Point"}
}