{
  "type": "Feature",
  "properties": {
    "gn:admin1_code":"10",
    "gn:admin2_code":"5.0",
    "gn:asciiname":"San Isidro",
    "gn:country_code":"MX",
    "gn:dem":1877,
    "gn:feature_class":"P",
    "gn:feature_code":"PPL",
    "gn:name":"San Isidro",
    "gn:population":4,
    "gn:timezone":"America/Monterrey",
    "iso:country":"MX",
    "wof:name":"San Isidro",
    "wof:placetype":"locality",
    "wof:population":4
},
  "geometry": {"coordinates":[-104.59362,23.95585],"type":"Point"}
}