{
  "type": "Feature",
  "properties": {
    "gn:admin1_code":"12",
    "gn:asciiname":"Coycoyan de las Flores",
    "gn:country_code":"MX",
    "gn:dem":1992,
    "gn:feature_class":"P",
    "gn:feature_code":"PPL",
    "gn:name":"Coycoyan de las Flores",
    "gn:population":0,
    "gn:timezone":"America/Mexico_City",
    "iso:country":"MX",
    "name:srp_x_preferred":[
        "\u041e\u043f\u0448\u0442\u0438\u043d\u0430 \u041a\u043e\u0438\u043a\u043e\u0458\u0430\u043d \u0434\u0435 \u043b\u0430\u0441 \u0424\u043b\u043e\u0440\u0435\u0441"
    ],
    "name:und_x_variant":[
        "Coicoyan",
        "Santiago Coicoyan",
        "Coycoyan de las Flores",
        "Coicoyan de las Flores"
    ],
    "wof:name":"Coycoyan de las Flores",
    "wof:placetype":"locality"
},
  "geometry": {"coordinates":[-98.2743,17.27294],"type":"Point"}
}