{
  "type": "Feature",
  "properties": {
    "gn:admin1_code":"12",
    "gn:asciiname":"Coycoyan de las Flores",
    "gn:country_code":"MX",
    "gn:dem":1992,
    "gn:feature_class":"P",
    "gn:feature_code":"PPL",
    "gn:name":"Coycoyan de las Flores",
    "gn:population":0,
    "gn:timezone":"America/Mexico_City",
    "iso:country":"MX",
    "name:und_x_variant":[
        "Coicoyan",
        "Santiago Coicoyan",
        "Coycoyan de las Flores",
        "Coicoyan de las Flores"
    ],
    "wof:name":"Coycoyan de las Flores",
    "wof:placetype":"locality"
},
  "geometry": {"coordinates":[-98.2743,17.27294],"type":"Point"}
}