{
  "type": "Feature",
  "properties": {
    "gn:admin1_code":"30",
    "gn:admin2_code":"114.0",
    "gn:asciiname":"Pachaca",
    "gn:cc2":"MX",
    "gn:country_code":"MX",
    "gn:dem":225,
    "gn:feature_class":"P",
    "gn:feature_code":"PPL",
    "gn:name":"Pachaca",
    "gn:population":0,
    "gn:timezone":"America/Mexico_City",
    "iso:country":"MX",
    "name:und_x_variant":[
        "Cachaca",
        "Pachaca"
    ],
    "wof:name":"Pachaca",
    "wof:placetype":"locality"
},
  "geometry": {"coordinates":[-96.73333,20.03333],"type":"Point"}
}