{
  "type": "Feature",
  "properties": {
    "gn:admin1_code":"7.0",
    "gn:admin2_code":"20.0",
    "gn:asciiname":"Munoz",
    "gn:country_code":"MX",
    "gn:dem":529,
    "gn:feature_class":"P",
    "gn:feature_code":"PPL",
    "gn:name":"Mu\u00f1\u00f3z",
    "gn:population":0,
    "gn:timezone":"America/Monterrey",
    "iso:country":"MX",
    "name:spa_x_preferred":[
        "Mu\u00f1\u00f3z"
    ],
    "wof:name":"Munoz",
    "wof:placetype":"locality"
},
  "geometry": {"coordinates":[-101.44571999999999,27.80184],"type":"Point"}
}