{
  "type": "Feature",
  "properties": {
    "gn:admin1_code":"10",
    "gn:admin2_code":"39",
    "gn:asciiname":"La Cruz (Treinta y Tres)",
    "gn:country_code":"MX",
    "gn:dem":1967,
    "gn:feature_class":"P",
    "gn:feature_code":"PPL",
    "gn:name":"La Cruz (Treinta y Tres)",
    "gn:population":23,
    "gn:timezone":"America/Monterrey",
    "iso:country":"MX",
    "wof:name":"La Cruz (Treinta y Tres)",
    "wof:placetype":"locality",
    "wof:population":23
},
  "geometry": {"coordinates":[-104.97611000000001,24.89055],"type":"Point"}
}