{
  "type": "Feature",
  "properties": {
    "gn:admin1_code":"24",
    "gn:admin2_code":"37.0",
    "gn:asciiname":"Fraccionamiento Maria Isabel",
    "gn:country_code":"MX",
    "gn:dem":133,
    "gn:feature_class":"P",
    "gn:feature_code":"PPL",
    "gn:name":"Fraccionamiento Mar\u00eda Isabel",
    "gn:population":5,
    "gn:timezone":"America/Mexico_City",
    "iso:country":"MX",
    "name:und_x_variant":[
        "Fraccionamiento Mar\u00eda Isabel"
    ],
    "wof:name":"Fraccionamiento Maria Isabel",
    "wof:placetype":"locality",
    "wof:population":5
},
  "geometry": {"coordinates":[-98.7375,21.2725],"type":"Point"}
}