{
  "type": "Feature",
  "properties": {
    "gn:admin1_code":"20",
    "gn:admin2_code":"199.0",
    "gn:asciiname":"Chepetlan",
    "gn:country_code":"MX",
    "gn:dem":1433,
    "gn:feature_class":"P",
    "gn:feature_code":"PPL",
    "gn:name":"Chepetl\u00e1n",
    "gn:population":0,
    "gn:timezone":"America/Mexico_City",
    "iso:country":"MX",
    "name:spa_x_preferred":[
        "San Jos\u00e9 Chepetl\u00e1n"
    ],
    "name:spa_x_variant":[
        "Chepetl\u00e1n"
    ],
    "wof:name":"Chepetlan",
    "wof:placetype":"locality"
},
  "geometry": {"coordinates":[-98.28709000000001,17.82789],"type":"Point"}
}