{
  "type": "Feature",
  "properties": {
    "gn:admin1_code":"21",
    "gn:asciiname":"Cuauhtemoc",
    "gn:country_code":"MX",
    "gn:dem":177,
    "gn:feature_class":"P",
    "gn:feature_code":"PPL",
    "gn:name":"Cuauht\u00e9moc",
    "gn:population":0,
    "gn:timezone":"America/Mexico_City",
    "iso:country":"MX",
    "name:und_x_variant":[
        "Cuauht\u00e9moc",
        "Jobo",
        "El Jobo"
    ],
    "wof:name":"Cuauhtemoc",
    "wof:placetype":"locality"
},
  "geometry": {"coordinates":[-97.60183000000001,20.17636],"type":"Point"}
}