{
  "type": "Feature",
  "properties": {
    "gn:admin1_code":"14.0",
    "gn:asciiname":"La Altamira",
    "gn:country_code":"MX",
    "gn:dem":2001,
    "gn:feature_class":"P",
    "gn:feature_code":"PPL",
    "gn:name":"La Altamira",
    "gn:population":0,
    "gn:timezone":"America/Mexico_City",
    "iso:country":"MX",
    "name:spa_x_preferred":[
        "La Altamira"
    ],
    "wof:name":"La Altamira",
    "wof:placetype":"locality"
},
  "geometry": {"coordinates":[-102.0147,20.99988],"type":"Point"}
}