{
  "type": "Feature",
  "properties": {
    "gn:admin1_code":"12",
    "gn:admin2_code":"34",
    "gn:asciiname":"Las Joyas",
    "gn:country_code":"MX",
    "gn:dem":765,
    "gn:feature_class":"P",
    "gn:feature_code":"PPL",
    "gn:name":"Las Joyas",
    "gn:population":9,
    "gn:timezone":"America/Mexico_City",
    "iso:country":"MX",
    "wof:name":"Las Joyas",
    "wof:placetype":"locality",
    "wof:population":9
},
  "geometry": {"coordinates":[-99.14247,18.47397],"type":"Point"}
}