{
  "type": "Feature",
  "properties": {
    "gn:admin1_code":"26.0",
    "gn:admin2_code":"38.0",
    "gn:asciiname":"La Pitahaya",
    "gn:country_code":"MX",
    "gn:dem":716,
    "gn:feature_class":"P",
    "gn:feature_code":"PPL",
    "gn:name":"La Pitahaya",
    "gn:population":0,
    "gn:timezone":"America/Hermosillo",
    "iso:country":"MX",
    "name:spa_x_preferred":[
        "La Pitahaya"
    ],
    "wof:name":"La Pitahaya",
    "wof:placetype":"locality"
},
  "geometry": {"coordinates":[-109.53394,29.68286],"type":"Point"}
}