{
  "type": "Feature",
  "properties": {
    "gn:admin1_code":"5",
    "gn:admin2_code":"20.0",
    "gn:asciiname":"Mazatlan",
    "gn:country_code":"MX",
    "gn:dem":667,
    "gn:feature_class":"P",
    "gn:feature_code":"PPL",
    "gn:name":"Mazatl\u00e1n",
    "gn:population":8,
    "gn:timezone":"America/Mexico_City",
    "iso:country":"MX",
    "name:und_x_variant":[
        "Mazatl\u00e1n"
    ],
    "wof:name":"Mazatlan",
    "wof:placetype":"locality",
    "wof:population":8
},
  "geometry": {"coordinates":[-92.98611,15.92889],"type":"Point"}
}