{
  "type": "Feature",
  "properties": {
    "gn:admin1_code":"2",
    "gn:admin2_code":"1.0",
    "gn:asciiname":"Mochistlan",
    "gn:country_code":"MX",
    "gn:dem":295,
    "gn:feature_class":"P",
    "gn:feature_code":"PPL",
    "gn:name":"Mochistlan",
    "gn:population":7,
    "gn:timezone":"America/Tijuana",
    "iso:country":"MX",
    "wof:name":"Mochistlan",
    "wof:placetype":"locality",
    "wof:population":7
},
  "geometry": {"coordinates":[-116.67278,32.02278],"type":"Point"}
}