{
  "type": "Feature",
  "properties": {
    "gn:admin1_code":"19.0",
    "gn:admin2_code":"50.0",
    "gn:asciiname":"La Jicama",
    "gn:country_code":"MX",
    "gn:dem":189,
    "gn:feature_class":"P",
    "gn:feature_code":"PPL",
    "gn:name":"La Jicama",
    "gn:population":4,
    "gn:timezone":"America/Monterrey",
    "iso:country":"MX",
    "name:spa_x_preferred":[
        "La J\u00edcama"
    ],
    "wof:name":"La Jicama",
    "wof:placetype":"locality",
    "wof:population":4
},
  "geometry": {"coordinates":[-99.76212,26.52802],"type":"Point"}
}