{
  "type": "Feature",
  "properties": {
    "gn:admin1_code":"5",
    "gn:admin2_code":"99.0",
    "gn:asciiname":"Diez de Abril",
    "gn:country_code":"MX",
    "gn:dem":758,
    "gn:feature_class":"P",
    "gn:feature_code":"PPL",
    "gn:name":"Diez de Abril",
    "gn:population":4,
    "gn:timezone":"America/Mexico_City",
    "iso:country":"MX",
    "wof:name":"Diez de Abril",
    "wof:placetype":"locality",
    "wof:population":4
},
  "geometry": {"coordinates":[-92.04306,16.01194],"type":"Point"}
}