{
  "type": "Feature",
  "properties": {
    "gn:admin1_code":"31.0",
    "gn:asciiname":"Santa Cristina",
    "gn:country_code":"MX",
    "gn:dem":20,
    "gn:feature_class":"P",
    "gn:feature_code":"PPL",
    "gn:name":"Santa Cristina",
    "gn:population":0,
    "gn:timezone":"America/Merida",
    "iso:country":"MX",
    "name:spa_x_preferred":[
        "Santa Cristina"
    ],
    "wof:name":"Santa Cristina",
    "wof:placetype":"locality"
},
  "geometry": {"coordinates":[-88.06466,21.13218],"type":"Point"}
}