{
  "type": "Feature",
  "properties": {
    "gn:admin1_code":"6.0",
    "gn:admin2_code":"9.0",
    "gn:asciiname":"Bolaino",
    "gn:country_code":"MX",
    "gn:dem":2271,
    "gn:feature_class":"P",
    "gn:feature_code":"PPL",
    "gn:name":"Bolaino",
    "gn:population":0,
    "gn:timezone":"America/Chihuahua",
    "iso:country":"MX",
    "name:spa_x_preferred":[
        "Bolaino"
    ],
    "wof:name":"Bolaino",
    "wof:placetype":"locality"
},
  "geometry": {"coordinates":[-107.794,27.71097],"type":"Point"}
}