{
  "type": "Feature",
  "properties": {
    "gn:admin1_code":"21",
    "gn:admin2_code":"2.0",
    "gn:asciiname":"Ejido Copalillo (Topila Palo Gacho)",
    "gn:country_code":"MX",
    "gn:dem":260,
    "gn:feature_class":"P",
    "gn:feature_code":"PPL",
    "gn:name":"Ejido Copalillo (Topila Palo Gacho)",
    "gn:population":99,
    "gn:timezone":"America/Mexico_City",
    "iso:country":"MX",
    "wof:name":"Ejido Copalillo (Topila Palo Gacho)",
    "wof:placetype":"locality",
    "wof:population":99
},
  "geometry": {"coordinates":[-97.23985999999999,20.08849],"type":"Point"}
}