{
  "type": "Feature",
  "properties": {
    "gn:admin1_code":"5",
    "gn:admin2_code":"89.0",
    "gn:asciiname":"Las Galeras",
    "gn:country_code":"MX",
    "gn:dem":52,
    "gn:feature_class":"P",
    "gn:feature_code":"PPL",
    "gn:name":"Las Galeras",
    "gn:population":68,
    "gn:timezone":"America/Mexico_City",
    "iso:country":"MX",
    "name:spa_x_preferred":[
        "Las Galeras"
    ],
    "wof:name":"Las Galeras",
    "wof:placetype":"locality",
    "wof:population":68
},
  "geometry": {"coordinates":[-92.33638999999999,14.84306],"type":"Point"}
}