{
  "type": "Feature",
  "properties": {
    "gn:admin1_code":"21",
    "gn:admin2_code":"194",
    "gn:asciiname":"Palmatlan",
    "gn:country_code":"MX",
    "gn:dem":441,
    "gn:feature_class":"P",
    "gn:feature_code":"PPL",
    "gn:name":"Palmatl\u00e1n",
    "gn:population":10,
    "gn:timezone":"America/Mexico_City",
    "iso:country":"MX",
    "name:und_x_variant":[
        "Palmatl\u00e1n"
    ],
    "wof:name":"Palmatlan",
    "wof:placetype":"locality",
    "wof:population":10
},
  "geometry": {"coordinates":[-97.77916999999999,20.49444],"type":"Point"}
}