{
  "type": "Feature",
  "properties": {
    "gn:admin1_code":"8",
    "gn:admin2_code":"10.0",
    "gn:asciiname":"El Volantin",
    "gn:country_code":"MX",
    "gn:dem":688,
    "gn:feature_class":"P",
    "gn:feature_code":"PPL",
    "gn:name":"El Volant\u00edn",
    "gn:population":4,
    "gn:timezone":"America/Mexico_City",
    "iso:country":"MX",
    "name:und_x_variant":[
        "El Volant\u00edn"
    ],
    "wof:name":"El Volantin",
    "wof:placetype":"locality",
    "wof:population":4
},
  "geometry": {"coordinates":[-103.71306,19.30389],"type":"Point"}
}