{
  "type": "Feature",
  "properties": {
    "gn:admin1_code":"17",
    "gn:admin2_code":"1.0",
    "gn:asciiname":"Campo la Cazuela",
    "gn:country_code":"MX",
    "gn:dem":900,
    "gn:feature_class":"P",
    "gn:feature_code":"PPL",
    "gn:name":"Campo la Cazuela",
    "gn:population":9,
    "gn:timezone":"America/Mexico_City",
    "iso:country":"MX",
    "wof:name":"Campo la Cazuela",
    "wof:placetype":"locality",
    "wof:population":9
},
  "geometry": {"coordinates":[-99.34,18.61528],"type":"Point"}
}