{
  "type": "Feature",
  "properties": {
    "gn:admin1_code":"21",
    "gn:admin2_code":"105.0",
    "gn:asciiname":"Tezoquiticpac",
    "gn:country_code":"MX",
    "gn:dem":2780,
    "gn:feature_class":"P",
    "gn:feature_code":"PPL",
    "gn:name":"Tezoquiticpac",
    "gn:population":152,
    "gn:timezone":"America/Mexico_City",
    "iso:country":"MX",
    "wof:name":"Tezoquiticpac",
    "wof:placetype":"locality",
    "wof:population":152
},
  "geometry": {"coordinates":[-97.68783999999999,19.55879],"type":"Point"}
}