{
  "type": "Feature",
  "properties": {
    "gn:admin1_code":"16",
    "gn:admin2_code":"10.0",
    "gn:asciiname":"Ahuatoso",
    "gn:country_code":"MX",
    "gn:dem":576,
    "gn:feature_class":"P",
    "gn:feature_code":"PPL",
    "gn:name":"Ahuatoso",
    "gn:population":6,
    "gn:timezone":"America/Mexico_City",
    "iso:country":"MX",
    "wof:name":"Ahuatoso",
    "wof:placetype":"locality",
    "wof:population":6
},
  "geometry": {"coordinates":[-102.14167,18.29306],"type":"Point"}
}