{
  "type": "Feature",
  "properties": {
    "gn:admin1_code":"6",
    "gn:admin2_code":"48.0",
    "gn:asciiname":"Las Lechugas",
    "gn:country_code":"MX",
    "gn:dem":1923,
    "gn:feature_class":"P",
    "gn:feature_code":"PPL",
    "gn:name":"Las Lechugas",
    "gn:population":0,
    "gn:timezone":"America/Chihuahua",
    "iso:country":"MX",
    "name:spa_x_preferred":[
        "Las Lechugas"
    ],
    "wof:name":"Las Lechugas",
    "wof:placetype":"locality"
},
  "geometry": {"coordinates":[-107.31166,29.26007],"type":"Point"}
}