{
  "type": "Feature",
  "properties": {
    "gn:admin1_code":"26",
    "gn:admin2_code":"21.0",
    "gn:asciiname":"El Algodon",
    "gn:country_code":"MX",
    "gn:dem":391,
    "gn:feature_class":"P",
    "gn:feature_code":"PPL",
    "gn:name":"El Algod\u00f3n",
    "gn:population":4,
    "gn:timezone":"America/Hermosillo",
    "iso:country":"MX",
    "name:spa_x_preferred":[
        "El Algod\u00f3n"
    ],
    "wof:name":"El Algodon",
    "wof:placetype":"locality",
    "wof:population":4
},
  "geometry": {"coordinates":[-110.31917,28.76917000000001],"type":"Point"}
}