{
  "type": "Feature",
  "properties": {
    "gn:admin1_code":"15",
    "gn:admin2_code":"84.0",
    "gn:asciiname":"Barrio de la Cruz",
    "gn:country_code":"MX",
    "gn:dem":2371,
    "gn:feature_class":"P",
    "gn:feature_code":"PPL",
    "gn:name":"Barrio de la Cruz",
    "gn:population":95,
    "gn:timezone":"America/Mexico_City",
    "iso:country":"MX",
    "wof:name":"Barrio de la Cruz",
    "wof:placetype":"locality",
    "wof:population":95
},
  "geometry": {"coordinates":[-98.90761000000001,19.81891],"type":"Point"}
}