{
  "type": "Feature",
  "properties": {
    "gn:admin1_code":"26",
    "gn:admin2_code":"30.0",
    "gn:asciiname":"Pozo del Negro",
    "gn:country_code":"MX",
    "gn:dem":301,
    "gn:feature_class":"P",
    "gn:feature_code":"PPL",
    "gn:name":"Pozo del Negro",
    "gn:population":0,
    "gn:timezone":"America/Hermosillo",
    "iso:country":"MX",
    "name:und_x_variant":[
        "Rancho Pozo del Negro",
        "Pozo del Negro",
        "Pozo Prieto del Negro"
    ],
    "wof:name":"Pozo del Negro",
    "wof:placetype":"locality"
},
  "geometry": {"coordinates":[-111.51888999999998,29.48918],"type":"Point"}
}