{
  "type": "Feature",
  "properties": {
    "gn:admin1_code":"26.0",
    "gn:admin2_code":"14.0",
    "gn:asciiname":"Los Horcones",
    "gn:country_code":"MX",
    "gn:dem":524,
    "gn:feature_class":"P",
    "gn:feature_code":"PPL",
    "gn:name":"Los Horcones",
    "gn:population":0,
    "gn:timezone":"America/Hermosillo",
    "iso:country":"MX",
    "name:fra_x_preferred":[
        "Los Horcones"
    ],
    "name:por_x_preferred":[
        "Los horcones"
    ],
    "name:spa_x_preferred":[
        "Los Horcones"
    ],
    "wof:name":"Los Horcones",
    "wof:placetype":"locality"
},
  "geometry": {"coordinates":[-110.11252,29.49932],"type":"Point"}
}