{
  "type": "Feature",
  "properties": {
    "gn:admin1_code":"25",
    "gn:admin2_code":"16.0",
    "gn:asciiname":"Los Otates",
    "gn:cc2":"MX",
    "gn:country_code":"MX",
    "gn:dem":49,
    "gn:feature_class":"P",
    "gn:feature_code":"PPL",
    "gn:name":"Los Otates",
    "gn:population":0,
    "gn:timezone":"America/Mazatlan",
    "iso:country":"MX",
    "name:und_x_variant":[
        "Rancho Otates",
        "Los Otates"
    ],
    "wof:name":"Los Otates",
    "wof:placetype":"locality"
},
  "geometry": {"coordinates":[-106.75,23.66667],"type":"Point"}
}