{
  "type": "Feature",
  "properties": {
    "gn:admin1_code":"20",
    "gn:admin2_code":"232.0",
    "gn:asciiname":"Nueva Colonia Jose Lopez Portillo",
    "gn:country_code":"MX",
    "gn:dem":113,
    "gn:feature_class":"P",
    "gn:feature_code":"PPL",
    "gn:name":"Nueva Colonia Jos\u00e9 L\u00f3pez Portillo",
    "gn:population":108,
    "gn:timezone":"America/Mexico_City",
    "iso:country":"MX",
    "name:und_x_variant":[
        "Nueva Colonia Jos\u00e9 L\u00f3pez Portillo"
    ],
    "wof:name":"Nueva Colonia Jose Lopez Portillo",
    "wof:placetype":"locality",
    "wof:population":108
},
  "geometry": {"coordinates":[-96.32083,18.05028],"type":"Point"}
}