{
  "type": "Feature",
  "properties": {
    "gn:admin1_code":"5.0",
    "gn:admin2_code":"39.0",
    "gn:asciiname":"La Sombra",
    "gn:country_code":"MX",
    "gn:dem":1141,
    "gn:feature_class":"P",
    "gn:feature_code":"PPL",
    "gn:name":"La Sombra",
    "gn:population":0,
    "gn:timezone":"America/Mexico_City",
    "iso:country":"MX",
    "name:spa_x_preferred":[
        "La Sombra"
    ],
    "wof:name":"La Sombra",
    "wof:placetype":"locality"
},
  "geometry": {"coordinates":[-92.74379999999999,17.27822999999999],"type":"Point"}
}