{
  "type": "Feature",
  "properties": {
    "gn:admin1_code":"6.0",
    "gn:asciiname":"La Mora",
    "gn:country_code":"MX",
    "gn:dem":1135,
    "gn:feature_class":"P",
    "gn:feature_code":"PPL",
    "gn:name":"La Mora",
    "gn:population":0,
    "gn:timezone":"America/Chihuahua",
    "iso:country":"MX",
    "name:spa_x_preferred":[
        "La Mora"
    ],
    "wof:name":"La Mora",
    "wof:placetype":"locality"
},
  "geometry": {"coordinates":[-105.45086999999999,28.33362],"type":"Point"}
}