{
  "type": "Feature",
  "properties": {
    "gn:admin1_code":"5",
    "gn:admin2_code":"27",
    "gn:asciiname":"Nuevo Ranchito",
    "gn:country_code":"MX",
    "gn:dem":437,
    "gn:feature_class":"P",
    "gn:feature_code":"PPL",
    "gn:name":"Nuevo Ranchito",
    "gn:population":13,
    "gn:timezone":"America/Mexico_City",
    "iso:country":"MX",
    "wof:name":"Nuevo Ranchito",
    "wof:placetype":"locality",
    "wof:population":13
},
  "geometry": {"coordinates":[-92.98317,16.5353],"type":"Point"}
}