{
  "type": "Feature",
  "properties": {
    "gn:admin1_code":"30",
    "gn:admin2_code":"189.0",
    "gn:asciiname":"El Seminario",
    "gn:country_code":"MX",
    "gn:dem":8,
    "gn:feature_class":"P",
    "gn:feature_code":"PPL",
    "gn:name":"El Seminario",
    "gn:population":115,
    "gn:timezone":"America/Mexico_City",
    "iso:country":"MX",
    "wof:name":"El Seminario",
    "wof:placetype":"locality",
    "wof:population":115
},
  "geometry": {"coordinates":[-97.42722000000001,20.9675],"type":"Point"}
}