{
  "type": "Feature",
  "properties": {
    "gn:admin1_code":"20",
    "gn:admin2_code":"28.0",
    "gn:asciiname":"La Lobera",
    "gn:country_code":"MX",
    "gn:dem":1410,
    "gn:feature_class":"P",
    "gn:feature_code":"PPL",
    "gn:name":"La Lobera",
    "gn:population":0,
    "gn:timezone":"America/Mexico_City",
    "iso:country":"MX",
    "name:spa_x_preferred":[
        "La Lobera"
    ],
    "wof:name":"La Lobera",
    "wof:placetype":"locality"
},
  "geometry": {"coordinates":[-96.80816,16.46722999999999],"type":"Point"}
}