{
  "type": "Feature",
  "properties": {
    "gn:gn_country":"MX",
    "gn:gn_fcode":"PPL",
    "gn:gn_pop":4799,
    "gn:population":4799,
    "iso:country":"MX",
    "name:unk_x_variant":[
        "Santa Mar\u00eda Magdalena Ocotitl\u00e1n"
    ],
    "qs_pg:aaroncc":"MX",
    "qs_pg:gn_country":"MX",
    "qs_pg:gn_fcode":"PPL",
    "qs_pg:gn_pop":4799,
    "qs_pg:name":"Santa Maria Magdalena Ocotitlan",
    "qs_pg:name_adm0":"M\u00e9xico",
    "qs_pg:name_adm1":"Mexico",
    "qs_pg:photos_9k":1,
    "qs_pg:photos_9r":1,
    "qs_pg:photos_all":24,
    "qs_pg:photos_sr":0,
    "qs_pg:pop_sr":4,
    "qs_pg:qs_pg_placetype":"locality",
    "qs_pg:qs_pg_placetype_gp":"Town",
    "qs_pg:woe_adm0":23424900,
    "woe:adm0_id":23424900,
    "woe:name_adm0":"M\u00e9xico",
    "woe:name_adm1":"Mexico",
    "woe:placetype":"Town",
    "wof:name":"Santa Maria Magdalena Ocotitlan",
    "wof:placetype":"locality",
    "wof:population":4799
},
  "geometry": {"coordinates":[-99.62313,19.23656],"type":"Point"}
}