{
  "type": "Feature",
  "properties": {
    "gn:admin1_code":"5.0",
    "gn:asciiname":"Melchor Ocampo Tercera Seccion",
    "gn:country_code":"MX",
    "gn:dem":216,
    "gn:feature_class":"P",
    "gn:feature_code":"PPL",
    "gn:name":"Melchor Ocampo Tercera Secci\u00f3n",
    "gn:population":0,
    "gn:timezone":"America/Mexico_City",
    "iso:country":"MX",
    "name:spa_x_preferred":[
        "Melchor Ocampo Tercera Secci\u00f3n"
    ],
    "wof:name":"Melchor Ocampo Tercera Seccion",
    "wof:placetype":"locality"
},
  "geometry": {"coordinates":[-92.42936,17.57829],"type":"Point"}
}