{
  "type": "Feature",
  "properties": {
    "gn:admin1_code":"22.0",
    "gn:asciiname":"Las Lomas de San Cristobal",
    "gn:country_code":"MX",
    "gn:dem":2349,
    "gn:feature_class":"P",
    "gn:feature_code":"PPL",
    "gn:name":"Las Lomas de San Crist\u00f3bal",
    "gn:population":0,
    "gn:timezone":"America/Mexico_City",
    "iso:country":"MX",
    "name:spa_x_preferred":[
        "Las Lomas de San Crist\u00f3bal"
    ],
    "name:spa_x_variant":[
        "Las Lomas"
    ],
    "wof:name":"Las Lomas de San Cristobal",
    "wof:placetype":"locality"
},
  "geometry": {"coordinates":[-99.62356,20.92153],"type":"Point"}
}