{
  "type": "Feature",
  "properties": {
    "gn:admin1_code":"22",
    "gn:admin2_code":"4.0",
    "gn:asciiname":"La Pastilla",
    "gn:country_code":"MX",
    "gn:dem":1777,
    "gn:feature_class":"P",
    "gn:feature_code":"PPL",
    "gn:name":"La Pastilla",
    "gn:population":0,
    "gn:timezone":"America/Mexico_City",
    "iso:country":"MX",
    "name:spa_x_preferred":[
        "La Pastilla"
    ],
    "wof:name":"La Pastilla",
    "wof:placetype":"locality"
},
  "geometry": {"coordinates":[-99.70058,20.94675],"type":"Point"}
}