{
  "type": "Feature",
  "properties": {
    "gn:admin1_code":"16",
    "gn:admin2_code":"101",
    "gn:asciiname":"El Fresno Uno",
    "gn:country_code":"MX",
    "gn:dem":919,
    "gn:feature_class":"P",
    "gn:feature_code":"PPL",
    "gn:name":"El Fresno Uno",
    "gn:population":10,
    "gn:timezone":"America/Mexico_City",
    "iso:country":"MX",
    "wof:name":"El Fresno Uno",
    "wof:placetype":"locality",
    "wof:population":10
},
  "geometry": {"coordinates":[-100.90889,19.38083],"type":"Point"}
}