{
  "type": "Feature",
  "properties": {
    "gn:admin1_code":"26",
    "gn:admin2_code":"25.0",
    "gn:asciiname":"Santa Olga",
    "gn:country_code":"MX",
    "gn:dem":0,
    "gn:feature_class":"P",
    "gn:feature_code":"PPL",
    "gn:name":"Santa Olga",
    "gn:population":0,
    "gn:timezone":"America/Hermosillo",
    "iso:country":"MX",
    "name:spa_x_preferred":[
        "Santa Olga"
    ],
    "wof:name":"Santa Olga",
    "wof:placetype":"locality"
},
  "geometry": {"coordinates":[-110.80396,27.93646],"type":"Point"}
}