{
  "type": "Feature",
  "properties": {
    "gn:admin1_code":"15",
    "gn:admin2_code":"114.0",
    "gn:asciiname":"Cerrillo Grande",
    "gn:country_code":"MX",
    "gn:dem":2701,
    "gn:feature_class":"P",
    "gn:feature_code":"PPL",
    "gn:name":"Cerrillo Grande",
    "gn:population":630,
    "gn:timezone":"America/Mexico_City",
    "iso:country":"MX",
    "wof:name":"Cerrillo Grande",
    "wof:placetype":"locality",
    "wof:population":630
},
  "geometry": {"coordinates":[-100.04528000000001,19.52167],"type":"Point"}
}