{
  "type": "Feature",
  "properties": {
    "gn:admin1_code":"12",
    "gn:admin2_code":"1.0",
    "gn:asciiname":"San Isidro Gallinero (El Gallinero)",
    "gn:country_code":"MX",
    "gn:dem":72,
    "gn:feature_class":"P",
    "gn:feature_code":"PPL",
    "gn:name":"San Isidro Gallinero (El Gallinero)",
    "gn:population":2347,
    "gn:timezone":"America/Mexico_City",
    "iso:country":"MX",
    "wof:name":"San Isidro Gallinero (El Gallinero)",
    "wof:placetype":"locality",
    "wof:population":2347
},
  "geometry": {"coordinates":[-99.71417,16.88139],"type":"Point"}
}