{
  "type": "Feature",
  "properties": {
    "gn:admin1_code":"20",
    "gn:admin2_code":"43.0",
    "gn:asciiname":"Colonia de la Amistad",
    "gn:country_code":"MX",
    "gn:dem":17,
    "gn:feature_class":"P",
    "gn:feature_code":"PPL",
    "gn:name":"Colonia de la Amistad",
    "gn:population":230,
    "gn:timezone":"America/Mexico_City",
    "iso:country":"MX",
    "wof:name":"Colonia de la Amistad",
    "wof:placetype":"locality",
    "wof:population":230
},
  "geometry": {"coordinates":[-95.02861,16.41389],"type":"Point"}
}