{
  "type": "Feature",
  "properties": {
    "gn:admin1_code":"20",
    "gn:admin2_code":"234.0",
    "gn:asciiname":"Cerro de Arena",
    "gn:country_code":"MX",
    "gn:dem":1804,
    "gn:feature_class":"P",
    "gn:feature_code":"PPL",
    "gn:name":"Cerro de Arena",
    "gn:population":70,
    "gn:timezone":"America/Mexico_City",
    "iso:country":"MX",
    "wof:name":"Cerro de Arena",
    "wof:placetype":"locality",
    "wof:population":70
},
  "geometry": {"coordinates":[-96.88694,18.12889],"type":"Point"}
}