{
  "type": "Feature",
  "properties": {
    "gn:admin1_code":"6",
    "gn:admin2_code":"12",
    "gn:asciiname":"Mesa Miquela",
    "gn:country_code":"MX",
    "gn:dem":1976,
    "gn:feature_class":"P",
    "gn:feature_code":"PPL",
    "gn:name":"Mesa Miquela",
    "gn:population":32,
    "gn:timezone":"America/Chihuahua",
    "iso:country":"MX",
    "wof:name":"Mesa Miquela",
    "wof:placetype":"locality",
    "wof:population":32
},
  "geometry": {"coordinates":[-106.88992,27.58173],"type":"Point"}
}