{
  "type": "Feature",
  "properties": {
    "gn:admin1_code":"6.0",
    "gn:admin2_code":"49.0",
    "gn:asciiname":"Llanito de las Viejas",
    "gn:country_code":"MX",
    "gn:dem":1690,
    "gn:feature_class":"P",
    "gn:feature_code":"PPL",
    "gn:name":"Llanito de las Viejas",
    "gn:population":0,
    "gn:timezone":"America/Chihuahua",
    "iso:country":"MX",
    "name:spa_x_preferred":[
        "Llanito de las Viejas"
    ],
    "wof:name":"Llanito de las Viejas",
    "wof:placetype":"locality"
},
  "geometry": {"coordinates":[-106.79301,27.55295],"type":"Point"}
}