{
  "type": "Feature",
  "properties": {
    "gn:admin1_code":"29",
    "gn:admin2_code":"3.0",
    "gn:asciiname":"Ex-Hacienda la Trasquila",
    "gn:country_code":"MX",
    "gn:dem":2501,
    "gn:feature_class":"P",
    "gn:feature_code":"PPL",
    "gn:name":"Ex-Hacienda la Trasquila",
    "gn:population":0,
    "gn:timezone":"America/Mexico_City",
    "iso:country":"MX",
    "name:spa_x_preferred":[
        "Ex-Hacienda la Trasquila"
    ],
    "wof:name":"Ex-Hacienda la Trasquila",
    "wof:placetype":"locality"
},
  "geometry": {"coordinates":[-98.18243,19.51102],"type":"Point"}
}