{
  "type": "Feature",
  "properties": {
    "gn:admin1_code":"19.0",
    "gn:admin2_code":"50.0",
    "gn:asciiname":"La Rosita",
    "gn:country_code":"MX",
    "gn:dem":188,
    "gn:feature_class":"P",
    "gn:feature_code":"PPL",
    "gn:name":"La Rosita",
    "gn:population":1,
    "gn:timezone":"America/Monterrey",
    "iso:country":"MX",
    "name:spa_x_preferred":[
        "La Rosita"
    ],
    "wof:name":"La Rosita",
    "wof:placetype":"locality",
    "wof:population":1
},
  "geometry": {"coordinates":[-99.75476,26.55088],"type":"Point"}
}