{
  "type": "Feature",
  "properties": {
    "gn:admin1_code":"10",
    "gn:admin2_code":"19",
    "gn:asciiname":"El Gatunal",
    "gn:country_code":"MX",
    "gn:dem":1435,
    "gn:feature_class":"P",
    "gn:feature_code":"PPL",
    "gn:name":"El Gatu\u00f1al",
    "gn:population":28,
    "gn:timezone":"America/Monterrey",
    "iso:country":"MX",
    "name:und_x_variant":[
        "El Gatu\u00f1al"
    ],
    "wof:name":"El Gatunal",
    "wof:placetype":"locality",
    "wof:population":28
},
  "geometry": {"coordinates":[-106.12367,24.65749],"type":"Point"}
}