{
  "type": "Feature",
  "properties": {
    "gn:admin1_code":"16",
    "gn:admin2_code":"99",
    "gn:asciiname":"El Tejocote",
    "gn:country_code":"MX",
    "gn:dem":2325,
    "gn:feature_class":"P",
    "gn:feature_code":"PPL",
    "gn:name":"El Tejocote",
    "gn:population":26,
    "gn:timezone":"America/Mexico_City",
    "iso:country":"MX",
    "wof:name":"El Tejocote",
    "wof:placetype":"locality",
    "wof:population":26
},
  "geometry": {"coordinates":[-100.66916999999999,19.40944],"type":"Point"}
}