{
  "type": "Feature",
  "properties": {
    "gn:admin1_code":"24.0",
    "gn:admin2_code":"46.0",
    "gn:asciiname":"Los Franco",
    "gn:country_code":"MX",
    "gn:dem":2218,
    "gn:feature_class":"P",
    "gn:feature_code":"PPL",
    "gn:name":"Los Franco",
    "gn:population":61,
    "gn:timezone":"America/Mexico_City",
    "iso:country":"MX",
    "name:spa_x_preferred":[
        "Los Franco"
    ],
    "name:spa_x_variant":[
        "Franco"
    ],
    "wof:name":"Los Franco",
    "wof:placetype":"locality",
    "wof:population":61
},
  "geometry": {"coordinates":[-101.41423,21.89899],"type":"Point"}
}