{
  "type": "Feature",
  "properties": {
    "gn:admin1_code":"23",
    "gn:admin2_code":"2.0",
    "gn:asciiname":"Santa Rosa Segundo",
    "gn:country_code":"MX",
    "gn:dem":26,
    "gn:feature_class":"P",
    "gn:feature_code":"PPL",
    "gn:name":"Santa Rosa Segundo",
    "gn:population":1068,
    "gn:timezone":"America/Cancun",
    "iso:country":"MX",
    "wof:name":"Santa Rosa Segundo",
    "wof:placetype":"locality",
    "wof:population":1068
},
  "geometry": {"coordinates":[-88.2625,19.97778],"type":"Point"}
}