{
  "type": "Feature",
  "properties": {
    "gn:admin1_code":"5",
    "gn:admin2_code":"107",
    "gn:asciiname":"El Carmen",
    "gn:country_code":"MX",
    "gn:dem":624,
    "gn:feature_class":"P",
    "gn:feature_code":"PPL",
    "gn:name":"El Carmen",
    "gn:population":19,
    "gn:timezone":"America/Mexico_City",
    "iso:country":"MX",
    "wof:name":"El Carmen",
    "wof:placetype":"locality",
    "wof:population":19
},
  "geometry": {"coordinates":[-93.345,16.11028],"type":"Point"}
}