{
  "type": "Feature",
  "properties": {
    "gn:admin1_code":"7.0",
    "gn:admin2_code":"34.0",
    "gn:asciiname":"Comanche",
    "gn:country_code":"MX",
    "gn:dem":1370,
    "gn:feature_class":"P",
    "gn:feature_code":"PPL",
    "gn:name":"Comanche",
    "gn:population":0,
    "gn:timezone":"America/Monterrey",
    "iso:country":"MX",
    "name:afr_x_preferred":[
        "Comanche"
    ],
    "name:ara_x_preferred":[
        "\u0643\u0648\u0645\u0627\u0646\u0634\u064a"
    ],
    "name:azb_x_preferred":[
        "\u06a9\u0648\u0631\u0645\u0627\u0646\u062c\u06cc\u200c\u200c\u0644\u0631"
    ],
    "name:aze_x_preferred":[
        "Koman\u00e7il\u0259r"
    ],
    "name:bel_x_preferred":[
        "\u041a\u0430\u043c\u0430\u043d\u0447\u044b"
    ],
    "name:bre_x_preferred":[
        "Comanched"
    ],
    "name:bul_x_preferred":[
        "\u041a\u043e\u043c\u0430\u043d\u0447\u0438"
    ],
    "name:cat_x_preferred":[
        "Comanxes"
    ],
    "name:ces_x_preferred":[
        "Koman\u010dov\u00e9"
    ],
    "name:chy_x_preferred":[
        "\u0160\u00e9'\u0161enovots\u00e9taneo'o"
    ],
    "name:dan_x_preferred":[
        "Comanche"
    ],
    "name:deu_x_preferred":[
        "Comanche"
    ],
    "name:eus_x_preferred":[
        "Komantxe"
    ],
    "name:fas_x_preferred":[
        "\u06a9\u0648\u0645\u0627\u0646\u0686\u06cc"
    ],
    "name:fin_x_preferred":[
        "Comanchet"
    ],
    "name:fra_x_preferred":[
        "Comanches"
    ],
    "name:gle_x_preferred":[
        "C\u00f3m\u00e1ins\u00ed"
    ],
    "name:glg_x_preferred":[
        "Pobo comanche"
    ],
    "name:heb_x_preferred":[
        "\u05e7\u05d5\u05de\u05d0\u05e0\u05e6'\u05d9"
    ],
    "name:hrv_x_preferred":[
        "Koman\u010di"
    ],
    "name:hun_x_preferred":[
        "Komancsok"
    ],
    "name:hye_x_preferred":[
        "\u053f\u0578\u0574\u0561\u0576\u0579\u0576\u0565\u0580"
    ],
    "name:ita_x_preferred":[
        "Comanche"
    ],
    "name:jpn_x_preferred":[
        "\u30b3\u30de\u30f3\u30c1\u30a7"
    ],
    "name:kat_x_preferred":[
        "\u10d9\u10dd\u10db\u10d0\u10dc\u10e9\u10d4\u10d1\u10d8"
    ],
    "name:kor_x_preferred":[
        "\ucf54\ub9cc\uce58\uc871"
    ],
    "name:lav_x_preferred":[
        "Koman\u010di"
    ],
    "name:lit_x_preferred":[
        "Koman\u010diai"
    ],
    "name:mal_x_preferred":[
        "\u0d15\u0d4a\u0d2e\u0d3e\u0d7b\u0d1a\u0d46"
    ],
    "name:nav_x_preferred":[
        "Naa\u0142\u00e1n\u00ed"
    ],
    "name:nds_x_preferred":[
        "Comanche"
    ],
    "name:nld_x_preferred":[
        "Comanche"
    ],
    "name:nno_x_preferred":[
        "Comanchefolk"
    ],
    "name:nor_x_preferred":[
        "Comanche"
    ],
    "name:pol_x_preferred":[
        "Komancze"
    ],
    "name:por_x_preferred":[
        "Comanches"
    ],
    "name:rus_x_preferred":[
        "\u041a\u043e\u043c\u0430\u043d\u0447\u0438"
    ],
    "name:slk_x_preferred":[
        "Koman\u010di"
    ],
    "name:spa_x_preferred":[
        "Comanche"
    ],
    "name:srp_x_preferred":[
        "\u041a\u043e\u043c\u0430\u043d\u0447\u0438"
    ],
    "name:swe_x_preferred":[
        "Comancher"
    ],
    "name:tur_x_preferred":[
        "Koman\u00e7iler"
    ],
    "name:ukr_x_preferred":[
        "\u041a\u043e\u043c\u0430\u043d\u0447\u0456"
    ],
    "wof:name":"Comanche",
    "wof:placetype":"locality"
},
  "geometry": {"coordinates":[-103.73333,27.16667],"type":"Point"}
}