{
  "type": "Feature",
  "properties": {
    "gn:admin1_code":"7.0",
    "gn:admin2_code":"34.0",
    "gn:asciiname":"Comanche",
    "gn:country_code":"MX",
    "gn:dem":1370,
    "gn:feature_class":"P",
    "gn:feature_code":"PPL",
    "gn:name":"Comanche",
    "gn:population":0,
    "gn:timezone":"America/Monterrey",
    "iso:country":"MX",
    "wof:name":"Comanche",
    "wof:placetype":"locality"
},
  "geometry": {"coordinates":[-103.73333,27.16667],"type":"Point"}
}