{
  "type": "Feature",
  "properties": {
    "gn:admin1_code":"10",
    "gn:admin2_code":"39",
    "gn:asciiname":"Campo de Verano",
    "gn:country_code":"MX",
    "gn:dem":1972,
    "gn:feature_class":"P",
    "gn:feature_code":"PPL",
    "gn:name":"Campo de Verano",
    "gn:population":50,
    "gn:timezone":"America/Monterrey",
    "iso:country":"MX",
    "wof:name":"Campo de Verano",
    "wof:placetype":"locality",
    "wof:population":50
},
  "geometry": {"coordinates":[-105.05166,24.95537],"type":"Point"}
}