{
  "type": "Feature",
  "properties": {
    "gn:admin1_code":"6.0",
    "gn:admin2_code":"24.0",
    "gn:asciiname":"Lajas de Abajo",
    "gn:country_code":"MX",
    "gn:dem":1609,
    "gn:feature_class":"P",
    "gn:feature_code":"PPL",
    "gn:name":"Lajas de Abajo",
    "gn:population":0,
    "gn:timezone":"America/Chihuahua",
    "iso:country":"MX",
    "name:und_x_variant":[
        "Lajas",
        "Lajas de Abajo"
    ],
    "wof:name":"Lajas de Abajo",
    "wof:placetype":"locality"
},
  "geometry": {"coordinates":[-106.30936,28.19633],"type":"Point"}
}