{
  "type": "Feature",
  "properties": {
    "gn:admin1_code":"12.0",
    "gn:admin2_code":"54.0",
    "gn:asciiname":"Pando Loma",
    "gn:country_code":"MX",
    "gn:dem":1680,
    "gn:feature_class":"P",
    "gn:feature_code":"PPL",
    "gn:name":"Pando Loma",
    "gn:population":0,
    "gn:timezone":"America/Mexico_City",
    "iso:country":"MX",
    "name:spa_x_preferred":[
        "Pando Loma"
    ],
    "wof:name":"Pando Loma",
    "wof:placetype":"locality"
},
  "geometry": {"coordinates":[-100.16965999999999,17.65209],"type":"Point"}
}