{
  "type": "Feature",
  "properties": {
    "gn:admin1_code":"25.0",
    "gn:admin2_code":"1.0",
    "gn:asciiname":"La Chiripa",
    "gn:country_code":"MX",
    "gn:dem":8,
    "gn:feature_class":"P",
    "gn:feature_code":"PPL",
    "gn:name":"La Chiripa",
    "gn:population":0,
    "gn:timezone":"America/Mazatlan",
    "iso:country":"MX",
    "name:spa_x_preferred":[
        "La Chiripa"
    ],
    "name:und_x_variant":[
        "Campo Chiripa"
    ],
    "wof:name":"La Chiripa",
    "wof:placetype":"locality"
},
  "geometry": {"coordinates":[-109.01937,25.71042000000001],"type":"Point"}
}