{
  "type": "Feature",
  "properties": {
    "gn:admin1_code":"10",
    "gn:admin2_code":"5.0",
    "gn:asciiname":"El Infiernillo",
    "gn:country_code":"MX",
    "gn:dem":2259,
    "gn:feature_class":"P",
    "gn:feature_code":"PPL",
    "gn:name":"El Infiernillo",
    "gn:population":0,
    "gn:timezone":"America/Monterrey",
    "iso:country":"MX",
    "name:spa_x_preferred":[
        "El Infiernillo"
    ],
    "wof:name":"El Infiernillo",
    "wof:placetype":"locality"
},
  "geometry": {"coordinates":[-104.81176000000001,23.94563],"type":"Point"}
}