{
  "type": "Feature",
  "properties": {
    "gn:admin1_code":"6.0",
    "gn:admin2_code":"61.0",
    "gn:asciiname":"El Portilleno",
    "gn:country_code":"MX",
    "gn:dem":1541,
    "gn:feature_class":"P",
    "gn:feature_code":"PPL",
    "gn:name":"El Portille\u00f1o",
    "gn:population":0,
    "gn:timezone":"America/Chihuahua",
    "iso:country":"MX",
    "name:spa_x_preferred":[
        "El Portille\u00f1o"
    ],
    "wof:name":"El Portilleno",
    "wof:placetype":"locality"
},
  "geometry": {"coordinates":[-106.30193,27.52898],"type":"Point"}
}