{
  "type": "Feature",
  "properties": {
    "gn:admin1_code":"16.0",
    "gn:admin2_code":"74.0",
    "gn:asciiname":"Callejon de la Calera",
    "gn:country_code":"MX",
    "gn:dem":1538,
    "gn:feature_class":"P",
    "gn:feature_code":"PPL",
    "gn:name":"Callej\u00f3n de la Calera",
    "gn:population":0,
    "gn:timezone":"America/Mexico_City",
    "iso:country":"MX",
    "name:und_x_variant":[
        "Cailej\u00f3n de Calera",
        "Calera",
        "Callej\u00f3n de la Calera"
    ],
    "wof:name":"Callejon de la Calera",
    "wof:placetype":"locality"
},
  "geometry": {"coordinates":[-102.89846,20.16115],"type":"Point"}
}