{
  "type": "Feature",
  "properties": {
    "gn:admin1_code":"1",
    "gn:admin2_code":"6.0",
    "gn:asciiname":"Alan [Taller Mecanico]",
    "gn:country_code":"MX",
    "gn:dem":1899,
    "gn:feature_class":"P",
    "gn:feature_code":"PPL",
    "gn:name":"Alan [Taller Mec\u00e1nico]",
    "gn:population":5,
    "gn:timezone":"America/Mexico_City",
    "iso:country":"MX",
    "name:und_x_variant":[
        "Alan [Taller Mec\u00e1nico]"
    ],
    "wof:name":"Alan [Taller Mecanico]",
    "wof:placetype":"locality",
    "wof:population":5
},
  "geometry": {"coordinates":[-102.27249999999999,22.13056],"type":"Point"}
}