{
  "type": "Feature",
  "properties": {
    "gn:admin1_code":"10",
    "gn:admin2_code":"35.0",
    "gn:asciiname":"San Pedro de Pescadores",
    "gn:country_code":"MX",
    "gn:dem":2439,
    "gn:feature_class":"P",
    "gn:feature_code":"PPL",
    "gn:name":"San Pedro de Pescadores",
    "gn:population":0,
    "gn:timezone":"America/Monterrey",
    "iso:country":"MX",
    "name:und_x_variant":[
        "Pescaderos"
    ],
    "wof:name":"San Pedro de Pescadores",
    "wof:placetype":"locality"
},
  "geometry": {"coordinates":[-105.89735,25.16616],"type":"Point"}
}