{
  "type": "Feature",
  "properties": {
    "gn:admin1_code":"6",
    "gn:admin2_code":"37.0",
    "gn:asciiname":"El Alamo",
    "gn:country_code":"MX",
    "gn:dem":1265,
    "gn:feature_class":"P",
    "gn:feature_code":"PPL",
    "gn:name":"El \u00c1lamo",
    "gn:population":3,
    "gn:timezone":"America/Ojinaga",
    "iso:country":"MX",
    "wof:name":"El Alamo",
    "wof:placetype":"locality",
    "wof:population":3
},
  "geometry": {"coordinates":[-106.46108,31.36624],"type":"Point"}
}