{
  "type": "Feature",
  "properties": {
    "gn:admin1_code":"14",
    "gn:admin2_code":"25",
    "gn:asciiname":"Zapote de Abajo",
    "gn:country_code":"MX",
    "gn:dem":1689,
    "gn:feature_class":"P",
    "gn:feature_code":"PPL",
    "gn:name":"Zapote de Abajo",
    "gn:population":38,
    "gn:timezone":"America/Mexico_City",
    "iso:country":"MX",
    "wof:name":"Zapote de Abajo",
    "wof:placetype":"locality",
    "wof:population":38
},
  "geometry": {"coordinates":[-103.31778,22.03222],"type":"Point"}
}