{
  "type": "Feature",
  "properties": {
    "gn:admin1_code":"10",
    "gn:admin2_code":"9.0",
    "gn:asciiname":"Carricitos",
    "gn:country_code":"MX",
    "gn:dem":2095,
    "gn:feature_class":"P",
    "gn:feature_code":"PPL",
    "gn:name":"Carricitos",
    "gn:population":6,
    "gn:timezone":"America/Monterrey",
    "iso:country":"MX",
    "wof:name":"Carricitos",
    "wof:placetype":"locality",
    "wof:population":6
},
  "geometry": {"coordinates":[-105.70565000000001,25.68192],"type":"Point"}
}