{
  "type": "Feature",
  "properties": {
    "gn:admin1_code":"21.0",
    "gn:admin2_code":"111.0",
    "gn:asciiname":"El Pozo",
    "gn:country_code":"MX",
    "gn:dem":498,
    "gn:feature_class":"P",
    "gn:feature_code":"PPL",
    "gn:name":"El Pozo",
    "gn:population":798,
    "gn:timezone":"America/Mexico_City",
    "iso:country":"MX",
    "name:deu_x_preferred":[
        "El Pozo"
    ],
    "name:spa_x_preferred":[
        "El Pozo"
    ],
    "name:srp_x_preferred":[
        "\u0415\u043b \u041f\u043e\u0437\u043e"
    ],
    "wof:name":"El Pozo",
    "wof:placetype":"locality",
    "wof:population":798
},
  "geometry": {"coordinates":[-97.97278,20.51472],"type":"Point"}
}