{
  "type": "Feature",
  "properties": {
    "gn:admin1_code":"12",
    "gn:admin2_code":"45",
    "gn:asciiname":"Colonia Lazaro Cardenas",
    "gn:country_code":"MX",
    "gn:dem":1486,
    "gn:feature_class":"P",
    "gn:feature_code":"PPL",
    "gn:name":"Colonia L\u00e1zaro C\u00e1rdenas",
    "gn:population":28,
    "gn:timezone":"America/Mexico_City",
    "iso:country":"MX",
    "name:und_x_variant":[
        "Colonia L\u00e1zaro C\u00e1rdenas"
    ],
    "wof:name":"Colonia Lazaro Cardenas",
    "wof:placetype":"locality",
    "wof:population":28
},
  "geometry": {"coordinates":[-98.68348,17.85639],"type":"Point"}
}