{
  "type": "Feature",
  "properties": {
    "gn:admin1_code":"32",
    "gn:admin2_code":"24",
    "gn:asciiname":"Las Floridas (Gomez de Palacio)",
    "gn:country_code":"MX",
    "gn:dem":2036,
    "gn:feature_class":"P",
    "gn:feature_code":"PPL",
    "gn:name":"Las Floridas (G\u00f3mez de Palacio)",
    "gn:population":43,
    "gn:timezone":"America/Mexico_City",
    "iso:country":"MX",
    "name:und_x_variant":[
        "Las Floridas (G\u00f3mez de Palacio)"
    ],
    "wof:name":"Las Floridas (Gomez de Palacio)",
    "wof:placetype":"locality",
    "wof:population":43
},
  "geometry": {"coordinates":[-101.97889000000001,22.28167],"type":"Point"}
}