{
  "type": "Feature",
  "properties": {
    "gn:admin1_code":"18.0",
    "gn:admin2_code":"1.0",
    "gn:asciiname":"La Cortes",
    "gn:country_code":"MX",
    "gn:dem":23,
    "gn:feature_class":"P",
    "gn:feature_code":"PPL",
    "gn:name":"La Cort\u00e9s",
    "gn:population":5,
    "gn:timezone":"America/Mazatlan",
    "iso:country":"MX",
    "name:spa_x_preferred":[
        "La Cort\u00e9s"
    ],
    "wof:name":"La Cortes",
    "wof:placetype":"locality",
    "wof:population":5
},
  "geometry": {"coordinates":[-105.36715,22.44663],"type":"Point"}
}