{
  "type": "Feature",
  "properties": {
    "gn:admin1_code":"15",
    "gn:admin2_code":"118.0",
    "gn:asciiname":"Rancho Serraton",
    "gn:country_code":"MX",
    "gn:dem":2700,
    "gn:feature_class":"P",
    "gn:feature_code":"PPL",
    "gn:name":"Rancho Serrat\u00f3n",
    "gn:population":7,
    "gn:timezone":"America/Mexico_City",
    "iso:country":"MX",
    "name:und_x_variant":[
        "Rancho Serrat\u00f3n"
    ],
    "wof:name":"Rancho Serraton",
    "wof:placetype":"locality",
    "wof:population":7
},
  "geometry": {"coordinates":[-99.72268,19.31371],"type":"Point"}
}