{
  "type": "Feature",
  "properties": {
    "gn:admin1_code":"24",
    "gn:admin2_code":"22.0",
    "gn:asciiname":"Rancho la Mesa Larga",
    "gn:country_code":"MX",
    "gn:dem":1777,
    "gn:feature_class":"P",
    "gn:feature_code":"PPL",
    "gn:name":"Rancho la Mesa Larga",
    "gn:population":5,
    "gn:timezone":"America/Mexico_City",
    "iso:country":"MX",
    "wof:name":"Rancho la Mesa Larga",
    "wof:placetype":"locality",
    "wof:population":5
},
  "geometry": {"coordinates":[-101.0925,22.72139],"type":"Point"}
}