{
  "type": "Feature",
  "properties": {
    "gn:admin1_code":"24",
    "gn:admin2_code":"41.0",
    "gn:asciiname":"Rancho San Jose",
    "gn:country_code":"MX",
    "gn:dem":67,
    "gn:feature_class":"P",
    "gn:feature_code":"PPL",
    "gn:name":"Rancho San Jos\u00e9",
    "gn:population":6,
    "gn:timezone":"America/Mexico_City",
    "iso:country":"MX",
    "name:und_x_variant":[
        "Rancho San Jos\u00e9"
    ],
    "wof:name":"Rancho San Jose",
    "wof:placetype":"locality",
    "wof:population":6
},
  "geometry": {"coordinates":[-98.73444000000001,21.67694],"type":"Point"}
}