{
  "type": "Feature",
  "properties": {
    "gn:admin1_code":"30",
    "gn:admin2_code":"9",
    "gn:asciiname":"Los Robles",
    "gn:country_code":"MX",
    "gn:dem":20,
    "gn:feature_class":"P",
    "gn:feature_code":"PPL",
    "gn:name":"Los Robles",
    "gn:population":10,
    "gn:timezone":"America/Mexico_City",
    "iso:country":"MX",
    "name:ceb_x_preferred":[
        "Los Robles"
    ],
    "name:srp_x_preferred":[
        "\u041b\u043e\u0441 \u0420\u043e\u0431\u043b\u0435\u0441"
    ],
    "name:swe_x_preferred":[
        "Los Robles"
    ],
    "wof:name":"Los Robles",
    "wof:placetype":"locality",
    "wof:population":10
},
  "geometry": {"coordinates":[-96.52306,19.8975],"type":"Point"}
}