{
  "type": "Feature",
  "properties": {
    "gn:admin1_code":"14.0",
    "gn:admin2_code":"4.0",
    "gn:asciiname":"La Quebradora",
    "gn:country_code":"MX",
    "gn:dem":2203,
    "gn:feature_class":"P",
    "gn:feature_code":"PPL",
    "gn:name":"La Quebradora",
    "gn:population":0,
    "gn:timezone":"America/Mexico_City",
    "iso:country":"MX",
    "name:spa_x_preferred":[
        "La Quebradora"
    ],
    "wof:name":"La Quebradora",
    "wof:placetype":"locality"
},
  "geometry": {"coordinates":[-103.65869000000001,19.93458],"type":"Point"}
}