{
  "type": "Feature",
  "properties": {
    "gn:admin1_code":"22",
    "gn:admin2_code":"8",
    "gn:asciiname":"San Judas",
    "gn:country_code":"MX",
    "gn:dem":1956,
    "gn:feature_class":"P",
    "gn:feature_code":"PPL",
    "gn:name":"San Judas",
    "gn:population":17,
    "gn:timezone":"America/Mexico_City",
    "iso:country":"MX",
    "wof:name":"San Judas",
    "wof:placetype":"locality",
    "wof:population":17
},
  "geometry": {"coordinates":[-100.37694,20.47972],"type":"Point"}
}