{
  "type": "Feature",
  "properties": {
    "gn:admin1_code":"20",
    "gn:admin2_code":"333",
    "gn:asciiname":"Horno de Cal",
    "gn:country_code":"MX",
    "gn:dem":831,
    "gn:feature_class":"P",
    "gn:feature_code":"PPL",
    "gn:name":"Horno de Cal",
    "gn:population":20,
    "gn:timezone":"America/Mexico_City",
    "iso:country":"MX",
    "wof:name":"Horno de Cal",
    "wof:placetype":"locality",
    "wof:population":20
},
  "geometry": {"coordinates":[-96.12528,16.66306],"type":"Point"}
}