{
  "type": "Feature",
  "properties": {
    "gn:admin1_code":"6.0",
    "gn:admin2_code":"65.0",
    "gn:asciiname":"Turusirabo",
    "gn:country_code":"MX",
    "gn:dem":2046,
    "gn:feature_class":"P",
    "gn:feature_code":"PPL",
    "gn:name":"Turusirabo",
    "gn:population":0,
    "gn:timezone":"America/Chihuahua",
    "iso:country":"MX",
    "name:spa_x_preferred":[
        "Turusirabo"
    ],
    "wof:name":"Turusirabo",
    "wof:placetype":"locality"
},
  "geometry": {"coordinates":[-107.76924,27.43445],"type":"Point"}
}