{
  "type": "Feature",
  "properties": {
    "gn:admin1_code":"12",
    "gn:admin2_code":"17.0",
    "gn:asciiname":"Nuevo Balsas",
    "gn:country_code":"MX",
    "gn:dem":487,
    "gn:feature_class":"P",
    "gn:feature_code":"PPL",
    "gn:name":"Nuevo Balsas",
    "gn:population":1711,
    "gn:timezone":"America/Mexico_City",
    "iso:country":"MX",
    "wof:name":"Nuevo Balsas",
    "wof:placetype":"locality",
    "wof:population":1711
},
  "geometry": {"coordinates":[-99.75913,18.03253],"type":"Point"}
}