{
  "type": "Feature",
  "properties": {
    "gn:admin1_code":"6",
    "gn:admin2_code":"63",
    "gn:asciiname":"El Sauz",
    "gn:country_code":"MX",
    "gn:dem":1775,
    "gn:feature_class":"P",
    "gn:feature_code":"PPL",
    "gn:name":"El Sauz",
    "gn:population":9,
    "gn:timezone":"America/Chihuahua",
    "iso:country":"MX",
    "wof:name":"El Sauz",
    "wof:placetype":"locality",
    "wof:population":9
},
  "geometry": {"coordinates":[-108.11275000000001,28.85656],"type":"Point"}
}