{
  "type": "Feature",
  "properties": {
    "gn:admin1_code":"20.0",
    "gn:admin2_code":"85.0",
    "gn:asciiname":"Tierra Blanca San Vicente",
    "gn:country_code":"MX",
    "gn:dem":1295,
    "gn:feature_class":"P",
    "gn:feature_code":"PPL",
    "gn:name":"Tierra Blanca San Vicente",
    "gn:population":0,
    "gn:timezone":"America/Mexico_City",
    "iso:country":"MX",
    "name:spa_x_preferred":[
        "Tierra Blanca San Vicente"
    ],
    "wof:name":"Tierra Blanca San Vicente",
    "wof:placetype":"locality"
},
  "geometry": {"coordinates":[-96.64615999999999,16.02994],"type":"Point"}
}