{
  "type": "Feature",
  "properties": {
    "gn:admin1_code":"16",
    "gn:admin2_code":"14.0",
    "gn:asciiname":"La Pena del Mar",
    "gn:country_code":"MX",
    "gn:dem":11,
    "gn:feature_class":"P",
    "gn:feature_code":"PPL",
    "gn:name":"La Pe\u00f1a del Mar",
    "gn:population":7,
    "gn:timezone":"America/Mexico_City",
    "iso:country":"MX",
    "name:und_x_variant":[
        "La Pe\u00f1a del Mar"
    ],
    "wof:name":"La Pena del Mar",
    "wof:placetype":"locality",
    "wof:population":7
},
  "geometry": {"coordinates":[-103.72333,18.70167],"type":"Point"}
}