{
  "type": "Feature",
  "properties": {
    "gn:admin1_code":"23.0",
    "gn:asciiname":"Kankabchen",
    "gn:country_code":"MX",
    "gn:dem":37,
    "gn:feature_class":"P",
    "gn:feature_code":"PPL",
    "gn:name":"Kankabch\u00e9n",
    "gn:population":0,
    "gn:timezone":"America/Cancun",
    "iso:country":"MX",
    "name:spa_x_preferred":[
        "Kankabch\u00e9n"
    ],
    "name:spa_x_variant":[
        "Kancabchen",
        "G\u00fciros"
    ],
    "wof:name":"Kankabchen",
    "wof:placetype":"locality"
},
  "geometry": {"coordinates":[-88.62567,19.47056],"type":"Point"}
}