{
  "type": "Feature",
  "properties": {
    "gn:admin1_code":"24",
    "gn:admin2_code":"51.0",
    "gn:asciiname":"El Ojito",
    "gn:country_code":"MX",
    "gn:dem":1751,
    "gn:feature_class":"P",
    "gn:feature_code":"PPL",
    "gn:name":"El Ojito",
    "gn:population":211,
    "gn:timezone":"America/Mexico_City",
    "iso:country":"MX",
    "wof:name":"El Ojito",
    "wof:placetype":"locality",
    "wof:population":211
},
  "geometry": {"coordinates":[-100.907,22.51428],"type":"Point"}
}