{
  "type": "Feature",
  "properties": {
    "gn:admin1_code":"28.0",
    "gn:admin2_code":"8.0",
    "gn:asciiname":"Rodhesia",
    "gn:country_code":"MX",
    "gn:dem":193,
    "gn:feature_class":"P",
    "gn:feature_code":"PPL",
    "gn:name":"Rodhesia",
    "gn:population":0,
    "gn:timezone":"America/Monterrey",
    "iso:country":"MX",
    "name:spa_x_preferred":[
        "Rodhesia"
    ],
    "wof:name":"Rodhesia",
    "wof:placetype":"locality"
},
  "geometry": {"coordinates":[-98.65679,23.74226],"type":"Point"}
}