{
  "type": "Feature",
  "properties": {
    "gn:admin1_code":"26",
    "gn:admin2_code":"34.0",
    "gn:asciiname":"El Alamito",
    "gn:country_code":"MX",
    "gn:dem":1143,
    "gn:feature_class":"P",
    "gn:feature_code":"PPL",
    "gn:name":"El Alamito",
    "gn:population":0,
    "gn:timezone":"America/Hermosillo",
    "iso:country":"MX",
    "name:spa_x_preferred":[
        "El Alamito"
    ],
    "wof:name":"El Alamito",
    "wof:placetype":"locality"
},
  "geometry": {"coordinates":[-110.06283000000001,29.87162],"type":"Point"}
}