{
  "type": "Feature",
  "properties": {
    "gn:admin1_code":"32",
    "gn:admin2_code":"48.0",
    "gn:asciiname":"Cienega de los Fresnos",
    "gn:country_code":"MX",
    "gn:dem":2166,
    "gn:feature_class":"P",
    "gn:feature_code":"PPL",
    "gn:name":"Ci\u00e9nega de los Fresnos",
    "gn:population":0,
    "gn:timezone":"America/Mexico_City",
    "iso:country":"MX",
    "name:spa_x_preferred":[
        "Ci\u00e9nega de los Fresnos"
    ],
    "name:und_x_variant":[
        "La Ci\u00e9nega"
    ],
    "wof:name":"Cienega de los Fresnos",
    "wof:placetype":"locality"
},
  "geometry": {"coordinates":[-103.20743,21.73557000000001],"type":"Point"}
}