{
  "type": "Feature",
  "properties": {
    "gn:admin1_code":"5",
    "gn:admin2_code":"87",
    "gn:asciiname":"Cesalmiro Reyna Hernandez",
    "gn:country_code":"MX",
    "gn:dem":25,
    "gn:feature_class":"P",
    "gn:feature_code":"PPL",
    "gn:name":"Cesalmiro Reyna Hern\u00e1ndez",
    "gn:population":52,
    "gn:timezone":"America/Mexico_City",
    "iso:country":"MX",
    "name:und_x_variant":[
        "Cesalmiro Reyna Hern\u00e1ndez"
    ],
    "wof:name":"Cesalmiro Reyna Hernandez",
    "wof:placetype":"locality",
    "wof:population":52
},
  "geometry": {"coordinates":[-92.17055999999999,14.67194],"type":"Point"}
}