{
  "type": "Feature",
  "properties": {
    "iso:country":"MX",
    "name:fra_x_preferred":[
        "Los Pinos"
    ],
    "name:heb_x_preferred":[
        "\u05dc\u05d5\u05e1 \u05e4\u05d9\u05e0\u05d5\u05e1"
    ],
    "name:ita_x_preferred":[
        "Los Pinos"
    ],
    "name:msa_x_preferred":[
        "Los Pinos"
    ],
    "name:nld_x_preferred":[
        "Los Pinos"
    ],
    "name:nor_x_preferred":[
        "Los Pinos"
    ],
    "name:por_x_preferred":[
        "Los Pinos"
    ],
    "name:rus_x_preferred":[
        "\u041b\u043e\u0441 \u041f\u0438\u043d\u043e\u0441"
    ],
    "name:spa_x_preferred":[
        "Los Pinos"
    ],
    "name:swe_x_preferred":[
        "Los Pinos"
    ],
    "qs_pg:aaroncc":"MX",
    "qs_pg:name":"Los Pinos",
    "qs_pg:name_adm0":"M\u00e9xico",
    "qs_pg:name_adm1":"Guanajuato",
    "qs_pg:photos":1,
    "qs_pg:photos_1k":1,
    "qs_pg:photos_9k":1,
    "qs_pg:photos_9r":1,
    "qs_pg:photos_all":1,
    "qs_pg:photos_sr":1,
    "qs_pg:pop_sr":0,
    "qs_pg:qs_pg_placetype":"neighbourhood",
    "qs_pg:qs_pg_placetype_gp":"Suburb",
    "qs_pg:woe_adm0":23424900,
    "woe:adm0_id":23424900,
    "woe:name_adm0":"M\u00e9xico",
    "woe:name_adm1":"Guanajuato",
    "woe:placetype":"Suburb",
    "wof:name":"Los Pinos",
    "wof:placetype":"neighbourhood"
},
  "geometry": {"coordinates":[-101.260385,21.018409],"type":"Point"}
}