{
  "type": "Feature",
  "properties": {
    "gn:admin1_code":"30",
    "gn:admin2_code":"100.0",
    "gn:asciiname":"La Martucha",
    "gn:country_code":"MX",
    "gn:dem":29,
    "gn:feature_class":"P",
    "gn:feature_code":"PPL",
    "gn:name":"La Martucha",
    "gn:population":90,
    "gn:timezone":"America/Mexico_City",
    "iso:country":"MX",
    "wof:name":"La Martucha",
    "wof:placetype":"locality",
    "wof:population":90
},
  "geometry": {"coordinates":[-96.2925,19.0775],"type":"Point"}
}