{
  "type": "Feature",
  "properties": {
    "gn:admin1_code":"5.0",
    "gn:admin2_code":"23.0",
    "gn:asciiname":"Yutchen",
    "gn:country_code":"MX",
    "gn:dem":2501,
    "gn:feature_class":"P",
    "gn:feature_code":"PPL",
    "gn:name":"Yutchen",
    "gn:population":0,
    "gn:timezone":"America/Mexico_City",
    "iso:country":"MX",
    "name:spa_x_preferred":[
        "Yutchen"
    ],
    "wof:name":"Yutchen",
    "wof:placetype":"locality"
},
  "geometry": {"coordinates":[-92.75011000000001,16.83464],"type":"Point"}
}