{
  "type": "Feature",
  "properties": {
    "gn:admin1_code":"26",
    "gn:admin2_code":"64.0",
    "gn:asciiname":"La Pima",
    "gn:country_code":"MX",
    "gn:dem":611,
    "gn:feature_class":"P",
    "gn:feature_code":"PPL",
    "gn:name":"La Pima",
    "gn:population":0,
    "gn:timezone":"America/Hermosillo",
    "iso:country":"MX",
    "wof:name":"La Pima",
    "wof:placetype":"locality"
},
  "geometry": {"coordinates":[-111.28333000000001,30.48333],"type":"Point"}
}