{
  "type": "Feature",
  "properties": {
    "gn:admin1_code":"21",
    "gn:admin2_code":"110",
    "gn:asciiname":"Cruz Verde",
    "gn:country_code":"MX",
    "gn:dem":2171,
    "gn:feature_class":"P",
    "gn:feature_code":"PPL",
    "gn:name":"Cruz Verde",
    "gn:population":44,
    "gn:timezone":"America/Mexico_City",
    "iso:country":"MX",
    "wof:name":"Cruz Verde",
    "wof:placetype":"locality",
    "wof:population":44
},
  "geometry": {"coordinates":[-97.62936999999999,18.87181],"type":"Point"}
}