{
  "type": "Feature",
  "properties": {
    "gn:admin1_code":"16",
    "gn:admin2_code":"97",
    "gn:asciiname":"Las Canoas Altas",
    "gn:country_code":"MX",
    "gn:dem":1168,
    "gn:feature_class":"P",
    "gn:feature_code":"PPL",
    "gn:name":"Las Canoas Altas",
    "gn:population":16,
    "gn:timezone":"America/Mexico_City",
    "iso:country":"MX",
    "wof:name":"Las Canoas Altas",
    "wof:placetype":"locality",
    "wof:population":16
},
  "geometry": {"coordinates":[-101.53361,19.09861],"type":"Point"}
}