{
  "type": "Feature",
  "properties": {
    "gn:admin1_code":"28.0",
    "gn:admin2_code":"34.0",
    "gn:asciiname":"El Horizonte",
    "gn:country_code":"MX",
    "gn:dem":193,
    "gn:feature_class":"P",
    "gn:feature_code":"PPL",
    "gn:name":"El Horizonte",
    "gn:population":4,
    "gn:timezone":"America/Monterrey",
    "iso:country":"MX",
    "name:spa_x_preferred":[
        "El Horizonte"
    ],
    "wof:name":"El Horizonte",
    "wof:placetype":"locality",
    "wof:population":4
},
  "geometry": {"coordinates":[-98.79132,24.19672000000001],"type":"Point"}
}