{
  "type": "Feature",
  "properties": {
    "gn:admin1_code":"18.0",
    "gn:admin2_code":"11.0",
    "gn:asciiname":"Los Topete",
    "gn:country_code":"MX",
    "gn:dem":734,
    "gn:feature_class":"P",
    "gn:feature_code":"PPL",
    "gn:name":"Los Topete",
    "gn:population":0,
    "gn:timezone":"America/Mazatlan",
    "iso:country":"MX",
    "name:spa_x_preferred":[
        "Los Topete"
    ],
    "wof:name":"Los Topete",
    "wof:placetype":"locality"
},
  "geometry": {"coordinates":[-104.91315,22.0071],"type":"Point"}
}