{
  "type": "Feature",
  "properties": {
    "gn:admin1_code":"24.0",
    "gn:admin2_code":"10.0",
    "gn:asciiname":"Agua Zarca",
    "gn:country_code":"MX",
    "gn:dem":1127,
    "gn:feature_class":"P",
    "gn:feature_code":"PPL",
    "gn:name":"Agua Zarca",
    "gn:population":45,
    "gn:timezone":"America/Mexico_City",
    "iso:country":"MX",
    "name:spa_x_preferred":[
        "Agua Zarca"
    ],
    "wof:name":"Agua Zarca",
    "wof:placetype":"locality",
    "wof:population":45
},
  "geometry": {"coordinates":[-99.49527999999999,22.47083],"type":"Point"}
}