{
  "type": "Feature",
  "properties": {
    "gn:admin1_code":"12.0",
    "gn:admin2_code":"3.0",
    "gn:asciiname":"La Laja",
    "gn:country_code":"MX",
    "gn:dem":317,
    "gn:feature_class":"P",
    "gn:feature_code":"PPL",
    "gn:name":"La Laja",
    "gn:population":0,
    "gn:timezone":"America/Mexico_City",
    "iso:country":"MX",
    "name:ita_x_preferred":[
        "La Laja"
    ],
    "name:spa_x_preferred":[
        "La Laja"
    ],
    "name:zho_x_preferred":[
        "\u62c9\u62c9\u54c8"
    ],
    "wof:name":"La Laja",
    "wof:placetype":"locality"
},
  "geometry": {"coordinates":[-100.48237,18.09961],"type":"Point"}
}