{
  "type": "Feature",
  "properties": {
    "gn:admin1_code":"13",
    "gn:admin2_code":"77.0",
    "gn:asciiname":"La Lagunilla",
    "gn:country_code":"MX",
    "gn:dem":2473,
    "gn:feature_class":"P",
    "gn:feature_code":"PPL",
    "gn:name":"La Lagunilla",
    "gn:population":0,
    "gn:timezone":"America/Mexico_City",
    "iso:country":"MX",
    "name:spa_x_preferred":[
        "La Lagunilla"
    ],
    "wof:name":"La Lagunilla",
    "wof:placetype":"locality"
},
  "geometry": {"coordinates":[-98.47801,20.06787000000001],"type":"Point"}
}