{
  "type": "Feature",
  "properties": {
    "gn:admin1_code":"15",
    "gn:admin2_code":"47.0",
    "gn:asciiname":"San Jose del Sitio",
    "gn:country_code":"MX",
    "gn:dem":2549,
    "gn:feature_class":"P",
    "gn:feature_code":"PPL",
    "gn:name":"San Jos\u00e9 del Sitio",
    "gn:population":0,
    "gn:timezone":"America/Mexico_City",
    "iso:country":"MX",
    "wof:name":"San Jose del Sitio",
    "wof:placetype":"locality"
},
  "geometry": {"coordinates":[-99.6532,19.60428],"type":"Point"}
}