{
  "type": "Feature",
  "properties": {
    "gn:admin1_code":"32",
    "gn:admin2_code":"42",
    "gn:asciiname":"Los Alamos (Las Pilas Troncones)",
    "gn:country_code":"MX",
    "gn:dem":2145,
    "gn:feature_class":"P",
    "gn:feature_code":"PPL",
    "gn:name":"Los \u00c1lamos (Las Pilas Troncones)",
    "gn:population":10,
    "gn:timezone":"America/Mexico_City",
    "iso:country":"MX",
    "name:und_x_variant":[
        "Los \u00c1lamos (Las Pilas Troncones)"
    ],
    "wof:name":"Los Alamos (Las Pilas Troncones)",
    "wof:placetype":"locality",
    "wof:population":10
},
  "geometry": {"coordinates":[-103.61944,23.51806],"type":"Point"}
}