{
  "type": "Feature",
  "properties": {
    "gn:admin1_code":"27",
    "gn:admin2_code":"11.0",
    "gn:asciiname":"El Bolson",
    "gn:country_code":"MX",
    "gn:dem":5,
    "gn:feature_class":"P",
    "gn:feature_code":"PPL",
    "gn:name":"El Bols\u00f3n",
    "gn:population":8,
    "gn:timezone":"America/Mexico_City",
    "iso:country":"MX",
    "name:und_x_variant":[
        "El Bols\u00f3n"
    ],
    "wof:name":"El Bolson",
    "wof:placetype":"locality",
    "wof:population":8
},
  "geometry": {"coordinates":[-92.26111,18.33639],"type":"Point"}
}