{
  "type": "Feature",
  "properties": {
    "gn:admin1_code":"2",
    "gn:admin2_code":"5",
    "gn:asciiname":"Rancho Cota",
    "gn:country_code":"MX",
    "gn:dem":14,
    "gn:feature_class":"P",
    "gn:feature_code":"PPL",
    "gn:name":"Rancho Cota",
    "gn:population":9,
    "gn:timezone":"America/Tijuana",
    "iso:country":"MX",
    "wof:name":"Rancho Cota",
    "wof:placetype":"locality",
    "wof:population":9
},
  "geometry": {"coordinates":[-116.91083,32.2375],"type":"Point"}
}