{
  "type": "Feature",
  "properties": {
    "gn:admin1_code":"25",
    "gn:admin2_code":"6.0",
    "gn:asciiname":"Loma de Rodriguera",
    "gn:country_code":"MX",
    "gn:dem":48,
    "gn:feature_class":"P",
    "gn:feature_code":"PPL",
    "gn:name":"Loma de Rodriguera",
    "gn:population":0,
    "gn:timezone":"America/Mazatlan",
    "iso:country":"MX",
    "name:und_x_variant":[
        "Loma Rodriguera",
        "Loma de Rodriguera",
        "La Loma"
    ],
    "wof:name":"Loma de Rodriguera",
    "wof:placetype":"locality"
},
  "geometry": {"coordinates":[-107.39,24.87163],"type":"Point"}
}