{
  "type": "Feature",
  "properties": {
    "gn:admin1_code":"10",
    "gn:admin2_code":"12.0",
    "gn:asciiname":"Cerro Blanco",
    "gn:country_code":"MX",
    "gn:dem":1322,
    "gn:feature_class":"P",
    "gn:feature_code":"PPL",
    "gn:name":"Cerro Blanco",
    "gn:population":0,
    "gn:timezone":"America/Monterrey",
    "iso:country":"MX",
    "name:spa_x_preferred":[
        "Cerro Blanco"
    ],
    "wof:name":"Cerro Blanco",
    "wof:placetype":"locality"
},
  "geometry": {"coordinates":[-103.72915,25.65433],"type":"Point"}
}