{
  "type": "Feature",
  "properties": {
    "gn:admin1_code":"14",
    "gn:admin2_code":"115",
    "gn:asciiname":"El Pirul",
    "gn:country_code":"MX",
    "gn:dem":1751,
    "gn:feature_class":"P",
    "gn:feature_code":"PPL",
    "gn:name":"El Pirul",
    "gn:population":25,
    "gn:timezone":"America/Mexico_City",
    "iso:country":"MX",
    "wof:name":"El Pirul",
    "wof:placetype":"locality",
    "wof:population":25
},
  "geometry": {"coordinates":[-103.59222,22.05583],"type":"Point"}
}