{
  "type": "Feature",
  "properties": {
    "gn:admin1_code":"11.0",
    "gn:admin2_code":"42.0",
    "gn:asciiname":"El Chiqueo",
    "gn:country_code":"MX",
    "gn:dem":1792,
    "gn:feature_class":"P",
    "gn:feature_code":"PPL",
    "gn:name":"El Chiqueo",
    "gn:population":55,
    "gn:timezone":"America/Mexico_City",
    "iso:country":"MX",
    "name:spa_x_preferred":[
        "El Chiqueo"
    ],
    "wof:name":"El Chiqueo",
    "wof:placetype":"locality",
    "wof:population":55
},
  "geometry": {"coordinates":[-101.34847000000001,20.32135],"type":"Point"}
}