{
  "type": "Feature",
  "properties": {
    "gn:admin1_code":"30.0",
    "gn:admin2_code":"172.0",
    "gn:asciiname":"La Cal",
    "gn:country_code":"MX",
    "gn:dem":8,
    "gn:feature_class":"P",
    "gn:feature_code":"PPL",
    "gn:name":"La Cal",
    "gn:population":0,
    "gn:timezone":"America/Mexico_City",
    "iso:country":"MX",
    "name:spa_x_preferred":[
        "La Cal"
    ],
    "wof:name":"La Cal",
    "wof:placetype":"locality"
},
  "geometry": {"coordinates":[-94.74598,17.72697999999999],"type":"Point"}
}