{
  "type": "Feature",
  "properties": {
    "gn:admin1_code":"19.0",
    "gn:admin2_code":"37.0",
    "gn:asciiname":"San Jose de la Popa",
    "gn:country_code":"MX",
    "gn:dem":950,
    "gn:feature_class":"P",
    "gn:feature_code":"PPL",
    "gn:name":"San Jos\u00e9 de la Popa",
    "gn:population":15,
    "gn:timezone":"America/Monterrey",
    "iso:country":"MX",
    "name:spa_x_preferred":[
        "San Jos\u00e9 de la Popa"
    ],
    "wof:name":"San Jose de la Popa",
    "wof:placetype":"locality",
    "wof:population":15
},
  "geometry": {"coordinates":[-100.82722,26.16417],"type":"Point"}
}