{
  "type": "Feature",
  "properties": {
    "gn:admin1_code":"16.0",
    "gn:admin2_code":"22.0",
    "gn:asciiname":"La Mandarina",
    "gn:country_code":"MX",
    "gn:dem":1559,
    "gn:feature_class":"P",
    "gn:feature_code":"PPL",
    "gn:name":"La Mandarina",
    "gn:population":0,
    "gn:timezone":"America/Mexico_City",
    "iso:country":"MX",
    "name:spa_x_preferred":[
        "La Mandarina"
    ],
    "wof:name":"La Mandarina",
    "wof:placetype":"locality"
},
  "geometry": {"coordinates":[-100.97253000000001,19.58855],"type":"Point"}
}