{
  "type": "Feature",
  "properties": {
    "gn:admin1_code":"11",
    "gn:admin2_code":"2.0",
    "gn:asciiname":"Santiaguillo",
    "gn:country_code":"MX",
    "gn:dem":1913,
    "gn:feature_class":"P",
    "gn:feature_code":"PPL",
    "gn:name":"Santiaguillo",
    "gn:population":886,
    "gn:timezone":"America/Mexico_City",
    "iso:country":"MX",
    "name:spa_x_preferred":[
        "Santiaguillo"
    ],
    "wof:name":"Santiaguillo",
    "wof:placetype":"locality",
    "wof:population":886
},
  "geometry": {"coordinates":[-100.64318,20.11063],"type":"Point"}
}