{
  "type": "Feature",
  "properties": {
    "gn:admin1_code":"28",
    "gn:admin2_code":"2.0",
    "gn:asciiname":"Las Yucas",
    "gn:country_code":"MX",
    "gn:dem":332,
    "gn:feature_class":"P",
    "gn:feature_code":"PPL",
    "gn:name":"Las Yucas",
    "gn:population":0,
    "gn:timezone":"America/Monterrey",
    "iso:country":"MX",
    "name:spa_x_preferred":[
        "Las Yucas"
    ],
    "wof:name":"Las Yucas",
    "wof:placetype":"locality"
},
  "geometry": {"coordinates":[-98.14472000000001,23.22936],"type":"Point"}
}