{
  "type": "Feature",
  "properties": {
    "gn:admin1_code":"11.0",
    "gn:admin2_code":"14.0",
    "gn:asciiname":"La Cabra",
    "gn:country_code":"MX",
    "gn:dem":1978,
    "gn:feature_class":"P",
    "gn:feature_code":"PPL",
    "gn:name":"La Cabra",
    "gn:population":0,
    "gn:timezone":"America/Mexico_City",
    "iso:country":"MX",
    "name:spa_x_preferred":[
        "La Cabra"
    ],
    "wof:name":"La Cabra",
    "wof:placetype":"locality"
},
  "geometry": {"coordinates":[-100.78319999999999,21.19961],"type":"Point"}
}