{
  "type": "Feature",
  "properties": {
    "gn:admin1_code":"30",
    "gn:admin2_code":"204.0",
    "gn:asciiname":"El Tortuguero",
    "gn:country_code":"MX",
    "gn:dem":16,
    "gn:feature_class":"P",
    "gn:feature_code":"PPL",
    "gn:name":"El Tortuguero",
    "gn:population":0,
    "gn:timezone":"America/Mexico_City",
    "iso:country":"MX",
    "wof:name":"El Tortuguero",
    "wof:placetype":"locality"
},
  "geometry": {"coordinates":[-94.20139,18.19167],"type":"Point"}
}