{
  "type": "Feature",
  "properties": {
    "gn:admin1_code":"28.0",
    "gn:admin2_code":"37.0",
    "gn:asciiname":"El Doral",
    "gn:country_code":"MX",
    "gn:dem":73,
    "gn:feature_class":"P",
    "gn:feature_code":"PPL",
    "gn:name":"El Doral",
    "gn:population":6,
    "gn:timezone":"America/Monterrey",
    "iso:country":"MX",
    "name:spa_x_preferred":[
        "El Doral"
    ],
    "wof:name":"El Doral",
    "wof:placetype":"locality",
    "wof:population":6
},
  "geometry": {"coordinates":[-97.89011000000001,23.67599],"type":"Point"}
}