{
  "type": "Feature",
  "properties": {
    "gn:admin1_code":"28.0",
    "gn:admin2_code":"37.0",
    "gn:asciiname":"San Judas Tadeo",
    "gn:country_code":"MX",
    "gn:dem":71,
    "gn:feature_class":"P",
    "gn:feature_code":"PPL",
    "gn:name":"San Judas Tadeo",
    "gn:population":0,
    "gn:timezone":"America/Monterrey",
    "iso:country":"MX",
    "name:spa_x_preferred":[
        "San Judas Tadeo"
    ],
    "wof:name":"San Judas Tadeo",
    "wof:placetype":"locality"
},
  "geometry": {"coordinates":[-98.16500000000001,23.58444],"type":"Point"}
}