{
  "type": "Feature",
  "properties": {
    "gn:admin1_code":"21",
    "gn:admin2_code":"99.0",
    "gn:asciiname":"Puerta Canada",
    "gn:country_code":"MX",
    "gn:dem":2361,
    "gn:feature_class":"P",
    "gn:feature_code":"PPL",
    "gn:name":"Puerta Ca\u00f1ada",
    "gn:population":0,
    "gn:timezone":"America/Mexico_City",
    "iso:country":"MX",
    "name:spa_x_preferred":[
        "Puerta Ca\u00f1ada"
    ],
    "wof:name":"Puerta Canada",
    "wof:placetype":"locality"
},
  "geometry": {"coordinates":[-97.40939,18.81524],"type":"Point"}
}