{
  "type": "Feature",
  "properties": {
    "gn:admin1_code":"24",
    "gn:admin2_code":"12.0",
    "gn:asciiname":"Hual Ja",
    "gn:country_code":"MX",
    "gn:dem":357,
    "gn:feature_class":"P",
    "gn:feature_code":"PPL",
    "gn:name":"Hual Ja",
    "gn:population":75,
    "gn:timezone":"America/Mexico_City",
    "iso:country":"MX",
    "wof:name":"Hual Ja",
    "wof:placetype":"locality",
    "wof:population":75
},
  "geometry": {"coordinates":[-98.94139,21.60333],"type":"Point"}
}