{
  "type": "Feature",
  "properties": {
    "gn:admin1_code":"6.0",
    "gn:admin2_code":"29.0",
    "gn:asciiname":"Puerto Colorado",
    "gn:country_code":"MX",
    "gn:dem":2405,
    "gn:feature_class":"P",
    "gn:feature_code":"PPL",
    "gn:name":"Puerto Colorado",
    "gn:population":0,
    "gn:timezone":"America/Chihuahua",
    "iso:country":"MX",
    "name:spa_x_preferred":[
        "Puerto Colorado"
    ],
    "wof:name":"Puerto Colorado",
    "wof:placetype":"locality"
},
  "geometry": {"coordinates":[-107.30155999999999,26.48226],"type":"Point"}
}