{
  "type": "Feature",
  "properties": {
    "gn:admin1_code":"2.0",
    "gn:admin2_code":"3.0",
    "gn:asciiname":"Conquistador",
    "gn:country_code":"MX",
    "gn:dem":708,
    "gn:feature_class":"P",
    "gn:feature_code":"PPL",
    "gn:name":"Conquistador",
    "gn:population":0,
    "gn:timezone":"America/Tijuana",
    "iso:country":"MX",
    "name:spa_x_preferred":[
        "Conquistador"
    ],
    "wof:name":"Conquistador",
    "wof:placetype":"locality"
},
  "geometry": {"coordinates":[-116.58087999999999,32.51034],"type":"Point"}
}