{
  "type": "Feature",
  "properties": {
    "gn:admin1_code":"30",
    "gn:admin2_code":"61",
    "gn:asciiname":"El Tordo (El Kilometro 5)",
    "gn:country_code":"MX",
    "gn:dem":40,
    "gn:feature_class":"P",
    "gn:feature_code":"PPL",
    "gn:name":"El Tordo (El Kil\u00f3metro 5)",
    "gn:population":16,
    "gn:timezone":"America/Mexico_City",
    "iso:country":"MX",
    "name:und_x_variant":[
        "El Tordo (El Kil\u00f3metro 5)"
    ],
    "wof:name":"El Tordo (El Kilometro 5)",
    "wof:placetype":"locality",
    "wof:population":16
},
  "geometry": {"coordinates":[-94.09556000000001,17.71944],"type":"Point"}
}