{
  "type": "Feature",
  "properties": {
    "gn:admin1_code":"16.0",
    "gn:admin2_code":"15.0",
    "gn:asciiname":"Tashusanich",
    "gn:country_code":"MX",
    "gn:dem":1001,
    "gn:feature_class":"P",
    "gn:feature_code":"PPL",
    "gn:name":"Tashusanich",
    "gn:population":0,
    "gn:timezone":"America/Mexico_City",
    "iso:country":"MX",
    "name:spa_x_preferred":[
        "Tashusanich"
    ],
    "wof:name":"Tashusanich",
    "wof:placetype":"locality"
},
  "geometry": {"coordinates":[-103.18177,18.74833],"type":"Point"}
}