{
  "type": "Feature",
  "properties": {
    "gn:admin1_code":"20",
    "gn:admin2_code":"182",
    "gn:asciiname":"El Platanal Rio Verde (Cerro Escopeta)",
    "gn:country_code":"MX",
    "gn:dem":934,
    "gn:feature_class":"P",
    "gn:feature_code":"PPL",
    "gn:name":"El Platanal R\u00edo Verde (Cerro Escopeta)",
    "gn:population":30,
    "gn:timezone":"America/Mexico_City",
    "iso:country":"MX",
    "name:und_x_variant":[
        "El Platanal R\u00edo Verde (Cerro Escopeta)"
    ],
    "wof:name":"El Platanal Rio Verde (Cerro Escopeta)",
    "wof:placetype":"locality",
    "wof:population":30
},
  "geometry": {"coordinates":[-96.57556,17.90889],"type":"Point"}
}