{
  "type": "Feature",
  "properties": {
    "gn:admin1_code":"7",
    "gn:admin2_code":"5.0",
    "gn:asciiname":"Rancho El Papalote",
    "gn:country_code":"MX",
    "gn:dem":780,
    "gn:feature_class":"P",
    "gn:feature_code":"PPL",
    "gn:name":"Rancho El Papalote",
    "gn:population":0,
    "gn:timezone":"America/Monterrey",
    "iso:country":"MX",
    "wof:name":"Rancho El Papalote",
    "wof:placetype":"locality"
},
  "geometry": {"coordinates":[-101.03333000000001,26.71667],"type":"Point"}
}