{
  "type": "Feature",
  "properties": {
    "gn:admin1_code":"21",
    "gn:admin2_code":"94.0",
    "gn:asciiname":"Ayehualaco (San Martin)",
    "gn:country_code":"MX",
    "gn:dem":2490,
    "gn:feature_class":"P",
    "gn:feature_code":"PPL",
    "gn:name":"Ayehualaco (San Mart\u00edn)",
    "gn:population":636,
    "gn:timezone":"America/Mexico_City",
    "iso:country":"MX",
    "name:und_x_variant":[
        "Ayehualaco (San Mart\u00edn)"
    ],
    "wof:name":"Ayehualaco (San Martin)",
    "wof:placetype":"locality",
    "wof:population":636
},
  "geometry": {"coordinates":[-97.70667,19.43833],"type":"Point"}
}