{
  "type": "Feature",
  "properties": {
    "gn:admin1_code":"5",
    "gn:admin2_code":"57.0",
    "gn:asciiname":"Candelaria",
    "gn:country_code":"MX",
    "gn:dem":1578,
    "gn:feature_class":"P",
    "gn:feature_code":"PPL",
    "gn:name":"Candelaria",
    "gn:population":89,
    "gn:timezone":"America/Mexico_City",
    "iso:country":"MX",
    "wof:name":"Candelaria",
    "wof:placetype":"locality",
    "wof:population":89
},
  "geometry": {"coordinates":[-92.37889,15.40278],"type":"Point"}
}