{
  "type": "Feature",
  "properties": {
    "gn:admin1_code":"20",
    "gn:admin2_code":"477.0",
    "gn:asciiname":"Huajintepec",
    "gn:country_code":"MX",
    "gn:dem":985,
    "gn:feature_class":"P",
    "gn:feature_code":"PPL",
    "gn:name":"Huajintepec",
    "gn:population":0,
    "gn:timezone":"America/Mexico_City",
    "iso:country":"MX",
    "wof:name":"Huajintepec",
    "wof:placetype":"locality"
},
  "geometry": {"coordinates":[-97.21666999999999,16.41667],"type":"Point"}
}