{
  "type": "Feature",
  "properties": {
    "gn:admin1_code":"16",
    "gn:admin2_code":"66.0",
    "gn:asciiname":"Santa Ana Chapitiro",
    "gn:country_code":"MX",
    "gn:dem":2063,
    "gn:feature_class":"P",
    "gn:feature_code":"PPL",
    "gn:name":"Santa Ana Chapitiro",
    "gn:population":1042,
    "gn:timezone":"America/Mexico_City",
    "iso:country":"MX",
    "wof:name":"Santa Ana Chapitiro",
    "wof:placetype":"locality",
    "wof:population":1042
},
  "geometry": {"coordinates":[-101.6525,19.52611],"type":"Point"}
}