{
  "type": "Feature",
  "properties": {
    "gn:admin1_code":"6",
    "gn:admin2_code":"59.0",
    "gn:asciiname":"Granadas",
    "gn:country_code":"MX",
    "gn:dem":1859,
    "gn:feature_class":"P",
    "gn:feature_code":"PPL",
    "gn:name":"Granadas",
    "gn:population":0,
    "gn:timezone":"America/Chihuahua",
    "iso:country":"MX",
    "name:spa_x_preferred":[
        "Granadas"
    ],
    "name:und_x_variant":[
        "Granaditas",
        "San Jos\u00e9 de Granaditas"
    ],
    "wof:name":"Granadas",
    "wof:placetype":"locality"
},
  "geometry": {"coordinates":[-105.85195,26.91104],"type":"Point"}
}