{
  "type": "Feature",
  "properties": {
    "gn:admin1_code":"30",
    "gn:admin2_code":"89.0",
    "gn:asciiname":"Chacalapa",
    "gn:country_code":"MX",
    "gn:dem":44,
    "gn:feature_class":"P",
    "gn:feature_code":"PPL",
    "gn:name":"Chacalapa",
    "gn:population":1,
    "gn:timezone":"America/Mexico_City",
    "iso:country":"MX",
    "wof:name":"Chacalapa",
    "wof:placetype":"locality",
    "wof:population":1
},
  "geometry": {"coordinates":[-94.78306000000001,17.9775],"type":"Point"}
}