{
  "type": "Feature",
  "properties": {
    "gn:admin1_code":"4",
    "gn:admin2_code":"10.0",
    "gn:asciiname":"Sara Simon",
    "gn:country_code":"MX",
    "gn:dem":203,
    "gn:feature_class":"P",
    "gn:feature_code":"PPL",
    "gn:name":"Sara Sim\u00f3n",
    "gn:population":4,
    "gn:timezone":"America/Merida",
    "iso:country":"MX",
    "name:und_x_variant":[
        "Sara Sim\u00f3n"
    ],
    "wof:name":"Sara Simon",
    "wof:placetype":"locality",
    "wof:population":4
},
  "geometry": {"coordinates":[-89.69917,18.52306],"type":"Point"}
}