{
  "type": "Feature",
  "properties": {
    "gn:admin1_code":"1.0",
    "gn:admin2_code":"7.0",
    "gn:asciiname":"La Mision",
    "gn:country_code":"MX",
    "gn:dem":1931,
    "gn:feature_class":"P",
    "gn:feature_code":"PPL",
    "gn:name":"La Misi\u00f3n",
    "gn:population":0,
    "gn:timezone":"America/Mexico_City",
    "iso:country":"MX",
    "name:und_x_variant":[
        "La Misi\u00f3n"
    ],
    "name:urd_x_preferred":[
        "\u0644\u0627 \u0645\u06cc\u0633\u06cc\u0648\u0646"
    ],
    "wof:name":"La Mision",
    "wof:placetype":"locality"
},
  "geometry": {"coordinates":[-102.31050999999999,22.20932],"type":"Point"}
}