{
  "type": "Feature",
  "properties": {
    "gn:admin1_code":"20.0",
    "gn:admin2_code":"36.0",
    "gn:asciiname":"Lashi",
    "gn:country_code":"MX",
    "gn:dem":1063,
    "gn:feature_class":"P",
    "gn:feature_code":"PPL",
    "gn:name":"Lash\u00ed",
    "gn:population":0,
    "gn:timezone":"America/Mexico_City",
    "iso:country":"MX",
    "name:spa_x_preferred":[
        "Lash\u00ed"
    ],
    "wof:name":"Lashi",
    "wof:placetype":"locality"
},
  "geometry": {"coordinates":[-95.40295999999999,16.7972],"type":"Point"}
}