{
  "type": "Feature",
  "properties": {
    "gn:admin1_code":"5",
    "gn:admin2_code":"35.0",
    "gn:asciiname":"Gustavo Diaz Ordaz",
    "gn:country_code":"MX",
    "gn:dem":33,
    "gn:feature_class":"P",
    "gn:feature_code":"PPL",
    "gn:name":"Gustavo D\u00edaz Ordaz",
    "gn:population":0,
    "gn:timezone":"America/Mexico_City",
    "iso:country":"MX",
    "name:spa_x_preferred":[
        "Gustavo D\u00edaz Ord\u00e1z"
    ],
    "name:spa_x_variant":[
        "Gustavo D\u00edaz Ordaz"
    ],
    "name:und_x_variant":[
        "D\u00edaz Ord\u00e1z"
    ],
    "wof:name":"Gustavo Diaz Ordaz",
    "wof:placetype":"locality"
},
  "geometry": {"coordinates":[-92.24456000000001,14.72362],"type":"Point"}
}