{
  "type": "Feature",
  "properties": {
    "gn:admin1_code":"22",
    "gn:admin2_code":"1.0",
    "gn:asciiname":"El Coyote",
    "gn:country_code":"MX",
    "gn:dem":2540,
    "gn:feature_class":"P",
    "gn:feature_code":"PPL",
    "gn:name":"El Coyote",
    "gn:population":258,
    "gn:timezone":"America/Mexico_City",
    "iso:country":"MX",
    "wof:name":"El Coyote",
    "wof:placetype":"locality",
    "wof:population":258
},
  "geometry": {"coordinates":[-100.09028000000001,20.115],"type":"Point"}
}