{
  "type": "Feature",
  "properties": {
    "gn:admin1_code":"6",
    "gn:admin2_code":"16.0",
    "gn:asciiname":"Agua Nueva",
    "gn:country_code":"MX",
    "gn:dem":1362,
    "gn:feature_class":"P",
    "gn:feature_code":"PPL",
    "gn:name":"Agua Nueva",
    "gn:population":0,
    "gn:timezone":"America/Chihuahua",
    "iso:country":"MX",
    "name:spa_x_preferred":[
        "Agua Nueva"
    ],
    "name:spa_x_variant":[
        "Agua nueva"
    ],
    "wof:name":"Agua Nueva",
    "wof:placetype":"locality"
},
  "geometry": {"coordinates":[-104.94083999999999,27.92382000000001],"type":"Point"}
}