{
  "type": "Feature",
  "properties": {
    "gn:admin1_code":"16",
    "gn:admin2_code":"69.0",
    "gn:asciiname":"Colonia Independencia (La Piedad)",
    "gn:country_code":"MX",
    "gn:dem":1761,
    "gn:feature_class":"P",
    "gn:feature_code":"PPL",
    "gn:name":"Colonia Independencia (La Piedad)",
    "gn:population":7,
    "gn:timezone":"America/Mexico_City",
    "iso:country":"MX",
    "wof:name":"Colonia Independencia (La Piedad)",
    "wof:placetype":"locality",
    "wof:population":7
},
  "geometry": {"coordinates":[-102.04833000000001,20.33194],"type":"Point"}
}