{
  "type": "Feature",
  "properties": {
    "gn:admin1_code":"6",
    "gn:admin2_code":"20.0",
    "gn:asciiname":"Cienega de Urias (La Cieneguita)",
    "gn:country_code":"MX",
    "gn:dem":1095,
    "gn:feature_class":"P",
    "gn:feature_code":"PPL",
    "gn:name":"Ci\u00e9nega de Ur\u00edas (La Cieneguita)",
    "gn:population":4,
    "gn:timezone":"America/Chihuahua",
    "iso:country":"MX",
    "name:und_x_variant":[
        "Ci\u00e9nega de Ur\u00edas (La Cieneguita)"
    ],
    "wof:name":"Cienega de Urias (La Cieneguita)",
    "wof:placetype":"locality",
    "wof:population":4
},
  "geometry": {"coordinates":[-108.40854,27.32353],"type":"Point"}
}