{
  "type": "Feature",
  "properties": {
    "gn:admin1_code":"6",
    "gn:admin2_code":"32.0",
    "gn:asciiname":"Las Boquillas",
    "gn:cc2":"MX",
    "gn:country_code":"MX",
    "gn:dem":1750,
    "gn:feature_class":"P",
    "gn:feature_code":"PPL",
    "gn:name":"Las Boquillas",
    "gn:population":0,
    "gn:timezone":"America/Chihuahua",
    "iso:country":"MX",
    "name:und_x_variant":[
        "Boquillas",
        "Bouquillas",
        "Las Boquillas"
    ],
    "wof:name":"Las Boquillas",
    "wof:placetype":"locality"
},
  "geometry": {"coordinates":[-105.81667,27.13333],"type":"Point"}
}