{
  "type": "Feature",
  "properties": {
    "gn:admin1_code":"6",
    "gn:admin2_code":"65.0",
    "gn:asciiname":"El Placer",
    "gn:country_code":"MX",
    "gn:dem":2094,
    "gn:feature_class":"P",
    "gn:feature_code":"PPL",
    "gn:name":"El Placer",
    "gn:population":0,
    "gn:timezone":"America/Chihuahua",
    "iso:country":"MX",
    "name:spa_x_preferred":[
        "El Placer"
    ],
    "wof:name":"El Placer",
    "wof:placetype":"locality"
},
  "geometry": {"coordinates":[-108.01689,27.1371],"type":"Point"}
}