{
  "type": "Feature",
  "properties": {
    "gn:admin1_code":"12",
    "gn:admin2_code":"48.0",
    "gn:asciiname":"Cavaquito",
    "gn:country_code":"MX",
    "gn:dem":16,
    "gn:feature_class":"P",
    "gn:feature_code":"PPL",
    "gn:name":"Cavaquito",
    "gn:population":0,
    "gn:timezone":"America/Mexico_City",
    "iso:country":"MX",
    "name:spa_x_preferred":[
        "Cavaquito"
    ],
    "wof:name":"Cavaquito",
    "wof:placetype":"locality"
},
  "geometry": {"coordinates":[-101.12479999999999,17.37345],"type":"Point"}
}