{
  "type": "Feature",
  "properties": {
    "gn:admin1_code":"6",
    "gn:admin2_code":"8.0",
    "gn:asciiname":"Paraje Guachachi",
    "gn:country_code":"MX",
    "gn:dem":2040,
    "gn:feature_class":"P",
    "gn:feature_code":"PPL",
    "gn:name":"Paraje Guachachi",
    "gn:population":0,
    "gn:timezone":"America/Chihuahua",
    "iso:country":"MX",
    "name:spa_x_preferred":[
        "Paraje Guachachi"
    ],
    "wof:name":"Paraje Guachachi",
    "wof:placetype":"locality"
},
  "geometry": {"coordinates":[-107.47283,27.01788],"type":"Point"}
}