{
  "type": "Feature",
  "properties": {
    "gn:admin1_code":"14",
    "gn:admin2_code":"48",
    "gn:asciiname":"Rincon de Murillo",
    "gn:country_code":"MX",
    "gn:dem":2251,
    "gn:feature_class":"P",
    "gn:feature_code":"PPL",
    "gn:name":"Rinc\u00f3n de Murillo",
    "gn:population":12,
    "gn:timezone":"America/Mexico_City",
    "iso:country":"MX",
    "name:und_x_variant":[
        "Rinc\u00f3n de Murillo"
    ],
    "wof:name":"Rincon de Murillo",
    "wof:placetype":"locality",
    "wof:population":12
},
  "geometry": {"coordinates":[-102.12083,20.74861],"type":"Point"}
}