{
  "type": "Feature",
  "properties": {
    "gn:admin1_code":"5",
    "gn:admin2_code":"101.0",
    "gn:asciiname":"Santa Sofia",
    "gn:country_code":"MX",
    "gn:dem":743,
    "gn:feature_class":"P",
    "gn:feature_code":"PPL",
    "gn:name":"Santa Sof\u00eda",
    "gn:population":59,
    "gn:timezone":"America/Mexico_City",
    "iso:country":"MX",
    "name:und_x_variant":[
        "Santa Sof\u00eda"
    ],
    "wof:name":"Santa Sofia",
    "wof:placetype":"locality",
    "wof:population":59
},
  "geometry": {"coordinates":[-93.11583,16.79667],"type":"Point"}
}