{
  "type": "Feature",
  "properties": {
    "gn:admin1_code":"6",
    "gn:admin2_code":"27",
    "gn:asciiname":"Balibuachi",
    "gn:country_code":"MX",
    "gn:dem":2192,
    "gn:feature_class":"P",
    "gn:feature_code":"PPL",
    "gn:name":"Balibuachi",
    "gn:population":14,
    "gn:timezone":"America/Chihuahua",
    "iso:country":"MX",
    "wof:name":"Balibuachi",
    "wof:placetype":"locality",
    "wof:population":14
},
  "geometry": {"coordinates":[-107.33222000000001,27.54028],"type":"Point"}
}