{
  "type": "Feature",
  "properties": {
    "gn:admin1_code":"16",
    "gn:admin2_code":"10",
    "gn:asciiname":"Paso del Chivo",
    "gn:country_code":"MX",
    "gn:dem":261,
    "gn:feature_class":"P",
    "gn:feature_code":"PPL",
    "gn:name":"Paso del Chivo",
    "gn:population":29,
    "gn:timezone":"America/Mexico_City",
    "iso:country":"MX",
    "wof:name":"Paso del Chivo",
    "wof:placetype":"locality",
    "wof:population":29
},
  "geometry": {"coordinates":[-102.01333,18.495],"type":"Point"}
}