{
  "type": "Feature",
  "properties": {
    "gn:admin1_code":"16.0",
    "gn:admin2_code":"34.0",
    "gn:asciiname":"El Maguey",
    "gn:country_code":"MX",
    "gn:dem":2431,
    "gn:feature_class":"P",
    "gn:feature_code":"PPL",
    "gn:name":"El Maguey",
    "gn:population":0,
    "gn:timezone":"America/Mexico_City",
    "iso:country":"MX",
    "name:spa_x_preferred":[
        "El Maguey"
    ],
    "wof:name":"El Maguey",
    "wof:placetype":"locality"
},
  "geometry": {"coordinates":[-100.76159,19.71848],"type":"Point"}
}