{
  "type": "Feature",
  "properties": {
    "gn:admin1_code":"10",
    "gn:admin2_code":"5.0",
    "gn:asciiname":"Dos Arbolitos [Granja]",
    "gn:country_code":"MX",
    "gn:dem":1866,
    "gn:feature_class":"P",
    "gn:feature_code":"PPL",
    "gn:name":"Dos Arbolitos [Granja]",
    "gn:population":7,
    "gn:timezone":"America/Monterrey",
    "iso:country":"MX",
    "wof:name":"Dos Arbolitos [Granja]",
    "wof:placetype":"locality",
    "wof:population":7
},
  "geometry": {"coordinates":[-104.56695999999999,24.0789],"type":"Point"}
}