{
  "type": "Feature",
  "properties": {
    "gn:admin1_code":"15.0",
    "gn:asciiname":"Acachuen",
    "gn:country_code":"MX",
    "gn:dem":1800,
    "gn:feature_class":"P",
    "gn:feature_code":"PPL",
    "gn:name":"Acachu\u00e9n",
    "gn:population":0,
    "gn:timezone":"America/Mexico_City",
    "iso:country":"MX",
    "name:spa_x_preferred":[
        "Acachu\u00e9n"
    ],
    "wof:name":"Acachuen",
    "wof:placetype":"locality"
},
  "geometry": {"coordinates":[-102.09272,19.84715],"type":"Point"}
}