{
  "type": "Feature",
  "properties": {
    "gn:admin1_code":"19",
    "gn:admin2_code":"22.0",
    "gn:asciiname":"El Tulillo",
    "gn:country_code":"MX",
    "gn:dem":320,
    "gn:feature_class":"P",
    "gn:feature_code":"PPL",
    "gn:name":"El Tulillo",
    "gn:population":0,
    "gn:timezone":"America/Monterrey",
    "iso:country":"MX",
    "name:spa_x_preferred":[
        "El Tulillo"
    ],
    "wof:name":"El Tulillo",
    "wof:placetype":"locality"
},
  "geometry": {"coordinates":[-99.38084000000001,25.16271],"type":"Point"}
}