{
  "type": "Feature",
  "properties": {
    "gn:admin1_code":"5",
    "gn:admin2_code":"99.0",
    "gn:asciiname":"Toma de Zacatecas (Las Flores)",
    "gn:country_code":"MX",
    "gn:dem":735,
    "gn:feature_class":"P",
    "gn:feature_code":"PPL",
    "gn:name":"Toma de Zacatecas (Las Flores)",
    "gn:population":75,
    "gn:timezone":"America/Mexico_City",
    "iso:country":"MX",
    "wof:name":"Toma de Zacatecas (Las Flores)",
    "wof:placetype":"locality",
    "wof:population":75
},
  "geometry": {"coordinates":[-91.51416999999999,16.11889],"type":"Point"}
}