{
  "type": "Feature",
  "properties": {
    "gn:admin1_code":"5",
    "gn:admin2_code":"94",
    "gn:asciiname":"Patria Nueva",
    "gn:country_code":"MX",
    "gn:dem":1778,
    "gn:feature_class":"P",
    "gn:feature_code":"PPL",
    "gn:name":"Patria Nueva",
    "gn:population":36,
    "gn:timezone":"America/Mexico_City",
    "iso:country":"MX",
    "name:spa_x_preferred":[
        "Patria Nueva"
    ],
    "name:tha_x_preferred":[
        "\u0e1b\u0e32\u0e40\u0e15\u0e23\u0e35\u0e22\u0e19\u0e27\u0e22\u0e1a\u0e32"
    ],
    "wof:name":"Patria Nueva",
    "wof:placetype":"locality",
    "wof:population":36
},
  "geometry": {"coordinates":[-92.51528,16.56389],"type":"Point"}
}