{
  "type": "Feature",
  "properties": {
    "gn:admin1_code":"12",
    "gn:admin2_code":"57",
    "gn:asciiname":"Potrerillo",
    "gn:country_code":"MX",
    "gn:dem":397,
    "gn:feature_class":"P",
    "gn:feature_code":"PPL",
    "gn:name":"Potrerillo",
    "gn:population":14,
    "gn:timezone":"America/Mexico_City",
    "iso:country":"MX",
    "name:spa_x_preferred":[
        "Potrerillo"
    ],
    "wof:name":"Potrerillo",
    "wof:placetype":"locality",
    "wof:population":14
},
  "geometry": {"coordinates":[-100.6485,17.31198],"type":"Point"}
}