{
  "type": "Feature",
  "properties": {
    "gn:admin1_code":"18",
    "gn:admin2_code":"9",
    "gn:asciiname":"Los Tabacos",
    "gn:country_code":"MX",
    "gn:dem":1204,
    "gn:feature_class":"P",
    "gn:feature_code":"PPL",
    "gn:name":"Los Tabacos",
    "gn:population":28,
    "gn:timezone":"America/Mazatlan",
    "iso:country":"MX",
    "wof:name":"Los Tabacos",
    "wof:placetype":"locality",
    "wof:population":28
},
  "geometry": {"coordinates":[-104.63667,22.18222],"type":"Point"}
}