{
  "type": "Feature",
  "properties": {
    "gn:admin1_code":"20",
    "gn:admin2_code":"263.0",
    "gn:asciiname":"Llano de Ocote",
    "gn:country_code":"MX",
    "gn:dem":2133,
    "gn:feature_class":"P",
    "gn:feature_code":"PPL",
    "gn:name":"Llano de Ocote",
    "gn:population":96,
    "gn:timezone":"America/Mexico_City",
    "iso:country":"MX",
    "wof:name":"Llano de Ocote",
    "wof:placetype":"locality",
    "wof:population":96
},
  "geometry": {"coordinates":[-96.70332999999999,16.2125],"type":"Point"}
}