{
  "type": "Feature",
  "properties": {
    "gn:admin1_code":"5",
    "gn:admin2_code":"87",
    "gn:asciiname":"Las Flores Uno (Don Herminio)",
    "gn:country_code":"MX",
    "gn:dem":24,
    "gn:feature_class":"P",
    "gn:feature_code":"PPL",
    "gn:name":"Las Flores Uno (Don Herminio)",
    "gn:population":9,
    "gn:timezone":"America/Mexico_City",
    "iso:country":"MX",
    "wof:name":"Las Flores Uno (Don Herminio)",
    "wof:placetype":"locality",
    "wof:population":9
},
  "geometry": {"coordinates":[-92.17917,14.65722],"type":"Point"}
}