{
  "type": "Feature",
  "properties": {
    "gn:admin1_code":"22",
    "gn:admin2_code":"6",
    "gn:asciiname":"Rancho la Pichona",
    "gn:country_code":"MX",
    "gn:dem":1996,
    "gn:feature_class":"P",
    "gn:feature_code":"PPL",
    "gn:name":"Rancho la Pichona",
    "gn:population":10,
    "gn:timezone":"America/Mexico_City",
    "iso:country":"MX",
    "wof:name":"Rancho la Pichona",
    "wof:placetype":"locality",
    "wof:population":10
},
  "geometry": {"coordinates":[-100.40611,20.50833],"type":"Point"}
}