{
  "type": "Feature",
  "properties": {
    "iso:country":"MX",
    "qs_pg:aaroncc":"MX",
    "qs_pg:name":"Fracc Arquitos",
    "qs_pg:name_adm0":"M\u00e9xico",
    "qs_pg:name_adm1":"Queretaro de Arteaga",
    "qs_pg:photos":40,
    "qs_pg:photos_1k":8,
    "qs_pg:photos_9k":1,
    "qs_pg:photos_9r":2,
    "qs_pg:photos_all":40,
    "qs_pg:photos_sr":2,
    "qs_pg:pop_sr":0,
    "qs_pg:qs_pg_placetype":"neighbourhood",
    "qs_pg:qs_pg_placetype_gp":"Suburb",
    "qs_pg:woe_adm0":23424900,
    "woe:adm0_id":23424900,
    "woe:name_adm0":"M\u00e9xico",
    "woe:name_adm1":"Queretaro de Arteaga",
    "woe:placetype":"Suburb",
    "wof:name":"Fracc Arquitos",
    "wof:placetype":"neighbourhood"
},
  "geometry": {"coordinates":[-100.36392249999999,20.5884755],"type":"Point"}
}