{
  "type": "Feature",
  "properties": {
    "gn:admin1_code":"6",
    "gn:admin2_code":"29.0",
    "gn:asciiname":"Laureano",
    "gn:country_code":"MX",
    "gn:dem":953,
    "gn:feature_class":"P",
    "gn:feature_code":"PPL",
    "gn:name":"Laureano",
    "gn:population":0,
    "gn:timezone":"America/Chihuahua",
    "iso:country":"MX",
    "name:deu_x_preferred":[
        "Laureano"
    ],
    "name:fra_x_preferred":[
        "Laurian"
    ],
    "name:ron_x_preferred":[
        "Laurian"
    ],
    "name:spa_x_preferred":[
        "Laureano"
    ],
    "wof:name":"Laureano",
    "wof:placetype":"locality"
},
  "geometry": {"coordinates":[-107.64861000000001,26.19052000000001],"type":"Point"}
}