{
  "type": "Feature",
  "properties": {
    "gn:admin1_code":"5.0",
    "gn:asciiname":"El Rosario",
    "gn:country_code":"MX",
    "gn:dem":33,
    "gn:feature_class":"P",
    "gn:feature_code":"PPL",
    "gn:name":"El Rosario",
    "gn:population":0,
    "gn:timezone":"America/Mexico_City",
    "iso:country":"MX",
    "name:spa_x_preferred":[
        "El Rosario"
    ],
    "wof:name":"El Rosario",
    "wof:placetype":"locality"
},
  "geometry": {"coordinates":[-93.52997000000001,15.89997],"type":"Point"}
}