{
  "type": "Feature",
  "properties": {
    "gn:admin1_code":"30",
    "gn:admin2_code":"191.0",
    "gn:asciiname":"Platas",
    "gn:country_code":"MX",
    "gn:dem":13,
    "gn:feature_class":"P",
    "gn:feature_code":"PPL",
    "gn:name":"Platas",
    "gn:population":5,
    "gn:timezone":"America/Mexico_City",
    "iso:country":"MX",
    "wof:name":"Platas",
    "wof:placetype":"locality",
    "wof:population":5
},
  "geometry": {"coordinates":[-96.37222,19.41333],"type":"Point"}
}