{
  "type": "Feature",
  "properties": {
    "gn:admin1_code":"1",
    "gn:admin2_code":"6.0",
    "gn:asciiname":"Santiago",
    "gn:country_code":"MX",
    "gn:dem":1911,
    "gn:feature_class":"P",
    "gn:feature_code":"PPL",
    "gn:name":"Santiago",
    "gn:population":0,
    "gn:timezone":"America/Mexico_City",
    "iso:country":"MX",
    "name:spa_x_preferred":[
        "Santiago"
    ],
    "wof:name":"Santiago",
    "wof:placetype":"locality"
},
  "geometry": {"coordinates":[-102.33768999999999,22.11948],"type":"Point"}
}