{
  "type": "Feature",
  "properties": {
    "gn:admin1_code":"7",
    "gn:admin2_code":"7.0",
    "gn:asciiname":"Nuevo Venado",
    "gn:country_code":"MX",
    "gn:dem":720,
    "gn:feature_class":"P",
    "gn:feature_code":"PPL",
    "gn:name":"Nuevo Venado",
    "gn:population":0,
    "gn:timezone":"America/Monterrey",
    "iso:country":"MX",
    "wof:name":"Nuevo Venado",
    "wof:placetype":"locality"
},
  "geometry": {"coordinates":[-101.90000000000001,26.81667],"type":"Point"}
}