{
  "type": "Feature",
  "properties": {
    "gn:admin1_code":"23",
    "gn:admin2_code":"4.0",
    "gn:asciiname":"Camara",
    "gn:country_code":"MX",
    "gn:dem":22,
    "gn:feature_class":"P",
    "gn:feature_code":"PPL",
    "gn:name":"C\u00e1mara",
    "gn:population":7,
    "gn:timezone":"America/Cancun",
    "iso:country":"MX",
    "name:cat_x_preferred":[
        "Cambra"
    ],
    "name:deu_x_preferred":[
        "Camara"
    ],
    "name:epo_x_preferred":[
        "Camara"
    ],
    "name:fra_x_preferred":[
        "Camara"
    ],
    "name:ita_x_preferred":[
        "Camara"
    ],
    "name:jpn_x_preferred":[
        "\u30ab\u30de\u30e9"
    ],
    "name:lit_x_preferred":[
        "Camara"
    ],
    "name:nld_x_preferred":[
        "Camara"
    ],
    "name:scn_x_preferred":[
        "C\u00e0mmara"
    ],
    "name:spa_x_preferred":[
        "C\u00e1mara"
    ],
    "name:ukr_x_preferred":[
        "\u041a\u0430\u043c\u0430\u0440\u0430"
    ],
    "name:vec_x_preferred":[
        "C\u00e0mara"
    ],
    "wof:name":"Camara",
    "wof:placetype":"locality",
    "wof:population":7
},
  "geometry": {"coordinates":[-88.45111,18.73833],"type":"Point"}
}