{
  "type": "Feature",
  "properties": {
    "gn:admin1_code":"23",
    "gn:admin2_code":"4.0",
    "gn:asciiname":"Camara",
    "gn:country_code":"MX",
    "gn:dem":22,
    "gn:feature_class":"P",
    "gn:feature_code":"PPL",
    "gn:name":"C\u00e1mara",
    "gn:population":7,
    "gn:timezone":"America/Cancun",
    "iso:country":"MX",
    "name:und_x_variant":[
        "C\u00e1mara"
    ],
    "wof:name":"Camara",
    "wof:placetype":"locality",
    "wof:population":7
},
  "geometry": {"coordinates":[-88.45111,18.73833],"type":"Point"}
}