{
  "type": "Feature",
  "properties": {
    "gn:admin1_code":"1.0",
    "gn:admin2_code":"2.0",
    "gn:asciiname":"El Rosal",
    "gn:country_code":"MX",
    "gn:dem":2008,
    "gn:feature_class":"P",
    "gn:feature_code":"PPL",
    "gn:name":"El Rosal",
    "gn:population":0,
    "gn:timezone":"America/Mexico_City",
    "iso:country":"MX",
    "name:ceb_x_preferred":[
        "El Rosal"
    ],
    "name:deu_x_preferred":[
        "El Rosal"
    ],
    "name:fra_x_preferred":[
        "El Rosal"
    ],
    "name:sco_x_preferred":[
        "El Rosal"
    ],
    "name:spa_x_preferred":[
        "El Rosal"
    ],
    "name:srp_x_preferred":[
        "\u0415\u043b \u0420\u043e\u0441\u0430\u043b"
    ],
    "name:swe_x_preferred":[
        "El Rosal"
    ],
    "name:vie_x_preferred":[
        "El Rosal"
    ],
    "wof:name":"El Rosal",
    "wof:placetype":"locality"
},
  "geometry": {"coordinates":[-102.02249999999999,22.10711],"type":"Point"}
}