{
  "type": "Feature",
  "properties": {
    "gn:admin1_code":"6",
    "gn:admin2_code":"27.0",
    "gn:asciiname":"Los Patos",
    "gn:country_code":"MX",
    "gn:dem":2445,
    "gn:feature_class":"P",
    "gn:feature_code":"PPL",
    "gn:name":"Los Patos",
    "gn:population":0,
    "gn:timezone":"America/Chihuahua",
    "iso:country":"MX",
    "name:spa_x_preferred":[
        "Los Patos"
    ],
    "wof:name":"Los Patos",
    "wof:placetype":"locality"
},
  "geometry": {"coordinates":[-107.15689999999999,26.82808],"type":"Point"}
}