{
  "type": "Feature",
  "properties": {
    "gn:admin1_code":"15",
    "gn:admin2_code":"99.0",
    "gn:asciiname":"Colonia Villas de Tolimpa",
    "gn:country_code":"MX",
    "gn:dem":2258,
    "gn:feature_class":"P",
    "gn:feature_code":"PPL",
    "gn:name":"Colonia Villas de Tolimpa",
    "gn:population":541,
    "gn:timezone":"America/Mexico_City",
    "iso:country":"MX",
    "wof:name":"Colonia Villas de Tolimpa",
    "wof:placetype":"locality",
    "wof:population":541
},
  "geometry": {"coordinates":[-98.88388999999999,19.47472],"type":"Point"}
}