{
  "type": "Feature",
  "properties": {
    "gn:admin1_code":"13",
    "gn:admin2_code":"32.0",
    "gn:asciiname":"Potrero Zactipan",
    "gn:country_code":"MX",
    "gn:dem":131,
    "gn:feature_class":"P",
    "gn:feature_code":"PPL",
    "gn:name":"Potrero Zactip\u00e1n",
    "gn:population":110,
    "gn:timezone":"America/Mexico_City",
    "iso:country":"MX",
    "name:und_x_variant":[
        "Potrero Zactip\u00e1n"
    ],
    "wof:name":"Potrero Zactipan",
    "wof:placetype":"locality",
    "wof:population":110
},
  "geometry": {"coordinates":[-98.52292,21.17179],"type":"Point"}
}