{
  "type": "Feature",
  "properties": {
    "gn:admin1_code":"13",
    "gn:admin2_code":"75.0",
    "gn:asciiname":"Almacen",
    "gn:country_code":"MX",
    "gn:dem":2336,
    "gn:feature_class":"P",
    "gn:feature_code":"PPL",
    "gn:name":"Almac\u00e9n",
    "gn:population":0,
    "gn:timezone":"America/Mexico_City",
    "iso:country":"MX",
    "name:spa_x_preferred":[
        "Almac\u00e9n"
    ],
    "wof:name":"Almacen",
    "wof:placetype":"locality"
},
  "geometry": {"coordinates":[-98.88733000000001,19.94217],"type":"Point"}
}