{
  "type": "Feature",
  "properties": {
    "gn:admin1_code":"3",
    "gn:admin2_code":"1.0",
    "gn:asciiname":"La Poza Grande",
    "gn:cc2":"MX",
    "gn:country_code":"MX",
    "gn:dem":20,
    "gn:feature_class":"P",
    "gn:feature_code":"PPL",
    "gn:name":"La Poza Grande",
    "gn:population":0,
    "gn:timezone":"America/Mazatlan",
    "iso:country":"MX",
    "name:und_x_variant":[
        "Poza Grande",
        "Pozo Grande",
        "La Poza Grande"
    ],
    "wof:name":"La Poza Grande",
    "wof:placetype":"locality"
},
  "geometry": {"coordinates":[-112.08333,25.83333],"type":"Point"}
}