{
  "type": "Feature",
  "properties": {
    "gn:admin1_code":"26.0",
    "gn:admin2_code":"36.0",
    "gn:asciiname":"El Sobaco",
    "gn:country_code":"MX",
    "gn:dem":776,
    "gn:feature_class":"P",
    "gn:feature_code":"PPL",
    "gn:name":"El Sobaco",
    "gn:population":0,
    "gn:timezone":"America/Hermosillo",
    "iso:country":"MX",
    "name:spa_x_preferred":[
        "El Sobaco"
    ],
    "wof:name":"El Sobaco",
    "wof:placetype":"locality"
},
  "geometry": {"coordinates":[-110.94235,30.65437],"type":"Point"}
}