{
  "type": "Feature",
  "properties": {
    "gn:admin1_code":"7",
    "gn:admin2_code":"24.0",
    "gn:asciiname":"Las Artemisas",
    "gn:country_code":"MX",
    "gn:dem":1274,
    "gn:feature_class":"P",
    "gn:feature_code":"PPL",
    "gn:name":"Las Artemisas",
    "gn:population":5,
    "gn:timezone":"America/Monterrey",
    "iso:country":"MX",
    "name:spa_x_preferred":[
        "Las Artemisas"
    ],
    "wof:name":"Las Artemisas",
    "wof:placetype":"locality",
    "wof:population":5
},
  "geometry": {"coordinates":[-102.19126,25.56962],"type":"Point"}
}