{
  "type": "Feature",
  "properties": {
    "gn:admin1_code":"31.0",
    "gn:asciiname":"Santa Librada",
    "gn:country_code":"MX",
    "gn:dem":14,
    "gn:feature_class":"P",
    "gn:feature_code":"PPL",
    "gn:name":"Santa Librada",
    "gn:population":0,
    "gn:timezone":"America/Merida",
    "iso:country":"MX",
    "name:spa_x_preferred":[
        "Santa Librada"
    ],
    "wof:name":"Santa Librada",
    "wof:placetype":"locality"
},
  "geometry": {"coordinates":[-88.30476999999998,21.18981],"type":"Point"}
}