{
  "type": "Feature",
  "properties": {
    "gn:admin1_code":"12.0",
    "gn:admin2_code":"58.0",
    "gn:asciiname":"La Colonia",
    "gn:country_code":"MX",
    "gn:dem":1746,
    "gn:feature_class":"P",
    "gn:feature_code":"PPL",
    "gn:name":"La Colonia",
    "gn:population":0,
    "gn:timezone":"America/Mexico_City",
    "iso:country":"MX",
    "name:spa_x_preferred":[
        "La Colonia"
    ],
    "wof:name":"La Colonia",
    "wof:placetype":"locality"
},
  "geometry": {"coordinates":[-100.02985,18.33367],"type":"Point"}
}