{
  "type": "Feature",
  "properties": {
    "gn:admin1_code":"24",
    "gn:admin2_code":"53",
    "gn:asciiname":"Cuatlacatl",
    "gn:country_code":"MX",
    "gn:dem":107,
    "gn:feature_class":"P",
    "gn:feature_code":"PPL",
    "gn:name":"Cuatl\u00e1catl",
    "gn:population":13,
    "gn:timezone":"America/Mexico_City",
    "iso:country":"MX",
    "name:und_x_variant":[
        "Cuatl\u00e1catl"
    ],
    "wof:name":"Cuatlacatl",
    "wof:placetype":"locality",
    "wof:population":13
},
  "geometry": {"coordinates":[-98.89055999999999,21.45528],"type":"Point"}
}