{
  "type": "Feature",
  "properties": {
    "gn:admin1_code":"14.0",
    "gn:admin2_code":"29.0",
    "gn:asciiname":"Cuacuala",
    "gn:country_code":"MX",
    "gn:dem":1823,
    "gn:feature_class":"P",
    "gn:feature_code":"PPL",
    "gn:name":"Cuacuala",
    "gn:population":0,
    "gn:timezone":"America/Mexico_City",
    "iso:country":"MX",
    "wof:name":"Cuacuala",
    "wof:placetype":"locality"
},
  "geometry": {"coordinates":[-103.07505,20.95964],"type":"Point"}
}