{
  "type": "Feature",
  "properties": {
    "gn:admin1_code":"30",
    "gn:admin2_code":"58.0",
    "gn:asciiname":"Ahuatlan",
    "gn:country_code":"MX",
    "gn:dem":240,
    "gn:feature_class":"P",
    "gn:feature_code":"PPL",
    "gn:name":"Ahuatl\u00e1n",
    "gn:population":0,
    "gn:timezone":"America/Mexico_City",
    "iso:country":"MX",
    "name:spa_x_preferred":[
        "Ahuatl\u00e1n"
    ],
    "wof:name":"Ahuatlan",
    "wof:placetype":"locality"
},
  "geometry": {"coordinates":[-98.08855,20.90782],"type":"Point"}
}