{
  "type": "Feature",
  "properties": {
    "gn:admin1_code":"14",
    "gn:admin2_code":"35",
    "gn:asciiname":"La Calera",
    "gn:country_code":"MX",
    "gn:dem":1817,
    "gn:feature_class":"P",
    "gn:feature_code":"PPL",
    "gn:name":"La Calera",
    "gn:population":11,
    "gn:timezone":"America/Mexico_City",
    "iso:country":"MX",
    "wof:name":"La Calera",
    "wof:placetype":"locality",
    "wof:population":11
},
  "geometry": {"coordinates":[-102.27861,21.39472],"type":"Point"}
}