{
  "type": "Feature",
  "properties": {
    "gn:admin1_code":"22",
    "gn:admin2_code":"3.0",
    "gn:asciiname":"San Jose del Tepame",
    "gn:country_code":"MX",
    "gn:dem":970,
    "gn:feature_class":"P",
    "gn:feature_code":"PPL",
    "gn:name":"San Jos\u00e9 del Tepame",
    "gn:population":0,
    "gn:timezone":"America/Mexico_City",
    "iso:country":"MX",
    "name:spa_x_preferred":[
        "San Jos\u00e9 del Tepame"
    ],
    "wof:name":"San Jose del Tepame",
    "wof:placetype":"locality"
},
  "geometry": {"coordinates":[-99.69338,21.44826],"type":"Point"}
}