{
  "type": "Feature",
  "properties": {
    "gn:admin1_code":"15",
    "gn:admin2_code":"9.0",
    "gn:asciiname":"San Antonio Tlaltecahuacan",
    "gn:country_code":"MX",
    "gn:dem":2478,
    "gn:feature_class":"P",
    "gn:feature_code":"PPL",
    "gn:name":"San Antonio Tlaltecahuac\u00e1n",
    "gn:population":0,
    "gn:timezone":"America/Mexico_City",
    "iso:country":"MX",
    "name:spa_x_preferred":[
        "San Antonio Tlaltecahuac\u00e1n"
    ],
    "wof:name":"San Antonio Tlaltecahuacan",
    "wof:placetype":"locality"
},
  "geometry": {"coordinates":[-98.76895,19.15795],"type":"Point"}
}