{
  "type": "Feature",
  "properties": {
    "gn:admin1_code":"19",
    "gn:admin2_code":"27.0",
    "gn:asciiname":"Loma Redonda",
    "gn:country_code":"MX",
    "gn:dem":160,
    "gn:feature_class":"P",
    "gn:feature_code":"PPL",
    "gn:name":"Loma Redonda",
    "gn:population":0,
    "gn:timezone":"America/Monterrey",
    "iso:country":"MX",
    "name:spa_x_preferred":[
        "Loma Redonda"
    ],
    "wof:name":"Loma Redonda",
    "wof:placetype":"locality"
},
  "geometry": {"coordinates":[-99.41717,25.95134],"type":"Point"}
}