{
  "type": "Feature",
  "properties": {
    "gn:admin1_code":"26",
    "gn:admin2_code":"61.0",
    "gn:asciiname":"Zaporichi",
    "gn:cc2":"MX",
    "gn:country_code":"MX",
    "gn:dem":249,
    "gn:feature_class":"P",
    "gn:feature_code":"PPL",
    "gn:name":"Zaporichi",
    "gn:population":0,
    "gn:timezone":"America/Hermosillo",
    "iso:country":"MX",
    "name:und_x_variant":[
        "Rancho Zaporichi",
        "Zoporiche",
        "Zaporichi"
    ],
    "wof:name":"Zaporichi",
    "wof:placetype":"locality"
},
  "geometry": {"coordinates":[-109.66667,28.78333],"type":"Point"}
}