{
  "type": "Feature",
  "properties": {
    "gn:admin1_code":"19.0",
    "gn:asciiname":"Los Tres Arbolitos",
    "gn:country_code":"MX",
    "gn:dem":624,
    "gn:feature_class":"P",
    "gn:feature_code":"PPL",
    "gn:name":"Los Tres Arbolitos",
    "gn:population":0,
    "gn:timezone":"America/Monterrey",
    "iso:country":"MX",
    "name:spa_x_preferred":[
        "Los Tres Arbolitos"
    ],
    "wof:name":"Los Tres Arbolitos",
    "wof:placetype":"locality"
},
  "geometry": {"coordinates":[-100.48538000000001,25.78755],"type":"Point"}
}