{
  "type": "Feature",
  "properties": {
    "gn:admin1_code":"13",
    "gn:admin2_code":"22.0",
    "gn:asciiname":"Barrio de Tizahuapan",
    "gn:country_code":"MX",
    "gn:dem":2467,
    "gn:feature_class":"P",
    "gn:feature_code":"PPL",
    "gn:name":"Barrio de Tizahuap\u00e1n",
    "gn:population":0,
    "gn:timezone":"America/Mexico_City",
    "iso:country":"MX",
    "name:spa_x_preferred":[
        "Barrio Tizahuap\u00e1n"
    ],
    "name:spa_x_variant":[
        "Barrio de Tizahuap\u00e1n"
    ],
    "wof:name":"Barrio de Tizahuapan",
    "wof:placetype":"locality"
},
  "geometry": {"coordinates":[-98.65337,20.07172000000001],"type":"Point"}
}