{
  "type": "Feature",
  "properties": {
    "gn:admin1_code":"26.0",
    "gn:admin2_code":"3.0",
    "gn:asciiname":"Casita",
    "gn:country_code":"MX",
    "gn:dem":306,
    "gn:feature_class":"P",
    "gn:feature_code":"PPL",
    "gn:name":"Casita",
    "gn:population":0,
    "gn:timezone":"America/Hermosillo",
    "iso:country":"MX",
    "wof:name":"Casita",
    "wof:placetype":"locality"
},
  "geometry": {"coordinates":[-108.84999999999999,26.85],"type":"Point"}
}