{
  "type": "Feature",
  "properties": {
    "gn:admin1_code":"11",
    "gn:admin2_code":"3",
    "gn:asciiname":"Salto del Chiquihuitillo",
    "gn:country_code":"MX",
    "gn:dem":2066,
    "gn:feature_class":"P",
    "gn:feature_code":"PPL",
    "gn:name":"Salto del Chiquihuitillo",
    "gn:population":38,
    "gn:timezone":"America/Mexico_City",
    "iso:country":"MX",
    "wof:name":"Salto del Chiquihuitillo",
    "wof:placetype":"locality",
    "wof:population":38
},
  "geometry": {"coordinates":[-100.58889000000001,21.00389],"type":"Point"}
}