{
  "type": "Feature",
  "properties": {
    "gn:admin1_code":"1",
    "gn:admin2_code":"6",
    "gn:asciiname":"Manuel Delgadillo",
    "gn:country_code":"MX",
    "gn:dem":1892,
    "gn:feature_class":"P",
    "gn:feature_code":"PPL",
    "gn:name":"Manuel Delgadillo",
    "gn:population":9,
    "gn:timezone":"America/Mexico_City",
    "iso:country":"MX",
    "wof:name":"Manuel Delgadillo",
    "wof:placetype":"locality",
    "wof:population":9
},
  "geometry": {"coordinates":[-102.29167,22.12472],"type":"Point"}
}