{
  "type": "Feature",
  "properties": {
    "gn:admin1_code":"27.0",
    "gn:admin2_code":"1.0",
    "gn:asciiname":"El Pobre",
    "gn:country_code":"MX",
    "gn:dem":37,
    "gn:feature_class":"P",
    "gn:feature_code":"PPL",
    "gn:name":"El Pobre",
    "gn:population":0,
    "gn:timezone":"America/Mexico_City",
    "iso:country":"MX",
    "name:spa_x_preferred":[
        "El Pobre"
    ],
    "wof:name":"El Pobre",
    "wof:placetype":"locality"
},
  "geometry": {"coordinates":[-91.19789,17.77645],"type":"Point"}
}