{
  "type": "Feature",
  "properties": {
    "gn:admin1_code":"5",
    "gn:admin2_code":"64",
    "gn:asciiname":"Frontera las Casitas",
    "gn:country_code":"MX",
    "gn:dem":1264,
    "gn:feature_class":"P",
    "gn:feature_code":"PPL",
    "gn:name":"Frontera las Casitas",
    "gn:population":26,
    "gn:timezone":"America/Mexico_City",
    "iso:country":"MX",
    "wof:name":"Frontera las Casitas",
    "wof:placetype":"locality",
    "wof:population":26
},
  "geometry": {"coordinates":[-92.12848,16.74411],"type":"Point"}
}