{
  "type": "Feature",
  "properties": {
    "gn:admin1_code":"10",
    "gn:admin2_code":"34",
    "gn:asciiname":"Las Palmas",
    "gn:country_code":"MX",
    "gn:dem":722,
    "gn:feature_class":"P",
    "gn:feature_code":"PPL",
    "gn:name":"Las Palmas",
    "gn:population":15,
    "gn:timezone":"America/Monterrey",
    "iso:country":"MX",
    "wof:name":"Las Palmas",
    "wof:placetype":"locality",
    "wof:population":15
},
  "geometry": {"coordinates":[-107.08593,25.12719],"type":"Point"}
}