{
  "type": "Feature",
  "properties": {
    "gn:admin1_code":"5",
    "gn:admin2_code":"96",
    "gn:asciiname":"Cerro Santa Cruz",
    "gn:country_code":"MX",
    "gn:dem":1405,
    "gn:feature_class":"P",
    "gn:feature_code":"PPL",
    "gn:name":"Cerro Santa Cruz",
    "gn:population":43,
    "gn:timezone":"America/Mexico_City",
    "iso:country":"MX",
    "wof:name":"Cerro Santa Cruz",
    "wof:placetype":"locality",
    "wof:population":43
},
  "geometry": {"coordinates":[-92.43722,17.30222],"type":"Point"}
}