{
  "type": "Feature",
  "properties": {
    "gn:admin1_code":"17",
    "gn:admin2_code":"4.0",
    "gn:asciiname":"San Juan Ahuehueyo",
    "gn:country_code":"MX",
    "gn:dem":1170,
    "gn:feature_class":"P",
    "gn:feature_code":"PPL",
    "gn:name":"San Juan Ahuehueyo",
    "gn:population":2325,
    "gn:timezone":"America/Mexico_City",
    "iso:country":"MX",
    "wof:name":"San Juan Ahuehueyo",
    "wof:placetype":"locality",
    "wof:population":2325
},
  "geometry": {"coordinates":[-98.93277999999999,18.715],"type":"Point"}
}