{
  "type": "Feature",
  "properties": {
    "gn:admin1_code":"6",
    "gn:admin2_code":"31",
    "gn:asciiname":"Huertas la Nortenita (El Rosario Pozo Tres)",
    "gn:country_code":"MX",
    "gn:dem":2116,
    "gn:feature_class":"P",
    "gn:feature_code":"PPL",
    "gn:name":"Huertas la Norte\u00f1ita (El Rosario Pozo Tres)",
    "gn:population":32,
    "gn:timezone":"America/Chihuahua",
    "iso:country":"MX",
    "name:und_x_variant":[
        "Huertas la Norte\u00f1ita (El Rosario Pozo Tres)"
    ],
    "wof:name":"Huertas la Nortenita (El Rosario Pozo Tres)",
    "wof:placetype":"locality",
    "wof:population":32
},
  "geometry": {"coordinates":[-107.22662,28.45139],"type":"Point"}
}