{
  "type": "Feature",
  "properties": {
    "gn:admin1_code":"26",
    "gn:admin2_code":"18.0",
    "gn:asciiname":"La Diecisiete",
    "gn:country_code":"MX",
    "gn:dem":20,
    "gn:feature_class":"P",
    "gn:feature_code":"PPL",
    "gn:name":"La Diecisiete",
    "gn:population":7,
    "gn:timezone":"America/Hermosillo",
    "iso:country":"MX",
    "wof:name":"La Diecisiete",
    "wof:placetype":"locality",
    "wof:population":7
},
  "geometry": {"coordinates":[-109.92583,27.20833],"type":"Point"}
}