{
  "type": "Feature",
  "properties": {
    "gn:admin1_code":"9",
    "gn:admin2_code":"9.0",
    "gn:asciiname":"Tequimilpa",
    "gn:country_code":"MX",
    "gn:dem":2529,
    "gn:feature_class":"P",
    "gn:feature_code":"PPL",
    "gn:name":"Tequimilpa",
    "gn:population":4,
    "gn:timezone":"America/Mexico_City",
    "iso:country":"MX",
    "wof:name":"Tequimilpa",
    "wof:placetype":"locality",
    "wof:population":4
},
  "geometry": {"coordinates":[-99.0545,19.19396],"type":"Point"}
}