{
  "type": "Feature",
  "properties": {
    "gn:admin1_code":"30.0",
    "gn:admin2_code":"58.0",
    "gn:asciiname":"Las Flores",
    "gn:country_code":"MX",
    "gn:dem":163,
    "gn:feature_class":"P",
    "gn:feature_code":"PPL",
    "gn:name":"Las Flores",
    "gn:population":0,
    "gn:timezone":"America/Mexico_City",
    "iso:country":"MX",
    "name:spa_x_preferred":[
        "Las Flores"
    ],
    "wof:name":"Las Flores",
    "wof:placetype":"locality"
},
  "geometry": {"coordinates":[-98.04358000000001,20.97986],"type":"Point"}
}