{
  "type": "Feature",
  "properties": {
    "gn:admin1_code":"6",
    "gn:admin2_code":"29",
    "gn:asciiname":"El Cebollin",
    "gn:country_code":"MX",
    "gn:dem":2402,
    "gn:feature_class":"P",
    "gn:feature_code":"PPL",
    "gn:name":"El Ceboll\u00edn",
    "gn:population":29,
    "gn:timezone":"America/Chihuahua",
    "iso:country":"MX",
    "name:und_x_variant":[
        "El Ceboll\u00edn"
    ],
    "wof:name":"El Cebollin",
    "wof:placetype":"locality",
    "wof:population":29
},
  "geometry": {"coordinates":[-107.02734,25.69857],"type":"Point"}
}