{
  "type": "Feature",
  "properties": {
    "gn:admin1_code":"30",
    "gn:admin2_code":"153.0",
    "gn:asciiname":"Don Epitacio",
    "gn:country_code":"MX",
    "gn:dem":141,
    "gn:feature_class":"P",
    "gn:feature_code":"PPL",
    "gn:name":"Don Epitacio",
    "gn:population":7,
    "gn:timezone":"America/Mexico_City",
    "iso:country":"MX",
    "wof:name":"Don Epitacio",
    "wof:placetype":"locality",
    "wof:population":7
},
  "geometry": {"coordinates":[-97.73222,21.25],"type":"Point"}
}