{
  "type": "Feature",
  "properties": {
    "gn:admin1_code":"20",
    "gn:admin2_code":"540.0",
    "gn:asciiname":"Rio Oro",
    "gn:country_code":"MX",
    "gn:dem":1923,
    "gn:feature_class":"P",
    "gn:feature_code":"PPL",
    "gn:name":"R\u00edo Oro",
    "gn:population":0,
    "gn:timezone":"America/Mexico_City",
    "iso:country":"MX",
    "name:spa_x_preferred":[
        "R\u00edo del Oro"
    ],
    "name:spa_x_variant":[
        "R\u00edo Oro"
    ],
    "wof:name":"Rio Oro",
    "wof:placetype":"locality"
},
  "geometry": {"coordinates":[-97.60956,17.69557],"type":"Point"}
}