{
  "type": "Feature",
  "properties": {
    "gn:admin1_code":"1.0",
    "gn:admin2_code":"10.0",
    "gn:asciiname":"Las Cuatas",
    "gn:country_code":"MX",
    "gn:dem":2030,
    "gn:feature_class":"P",
    "gn:feature_code":"PPL",
    "gn:name":"Las Cuatas",
    "gn:population":0,
    "gn:timezone":"America/Mexico_City",
    "iso:country":"MX",
    "wof:name":"Las Cuatas",
    "wof:placetype":"locality"
},
  "geometry": {"coordinates":[-102.0295,22.00351],"type":"Point"}
}