{
  "type": "Feature",
  "properties": {
    "gn:admin1_code":"26",
    "gn:admin2_code":"11.0",
    "gn:asciiname":"Unamichi",
    "gn:country_code":"MX",
    "gn:dem":1075,
    "gn:feature_class":"P",
    "gn:feature_code":"PPL",
    "gn:name":"Un\u00e1michi",
    "gn:population":0,
    "gn:timezone":"America/Hermosillo",
    "iso:country":"MX",
    "name:spa_x_colloquial":[
        "Unamichi"
    ],
    "name:spa_x_preferred":[
        "Unamichi"
    ],
    "wof:name":"Unamichi",
    "wof:placetype":"locality"
},
  "geometry": {"coordinates":[-109.9836,30.67401],"type":"Point"}
}