{
  "type": "Feature",
  "properties": {
    "gn:admin1_code":"5.0",
    "gn:admin2_code":"89.0",
    "gn:asciiname":"Las Bodegas",
    "gn:country_code":"MX",
    "gn:dem":13,
    "gn:feature_class":"P",
    "gn:feature_code":"PPL",
    "gn:name":"Las Bodegas",
    "gn:population":0,
    "gn:timezone":"America/Mexico_City",
    "iso:country":"MX",
    "name:spa_x_preferred":[
        "Las Bodegas"
    ],
    "wof:name":"Las Bodegas",
    "wof:placetype":"locality"
},
  "geometry": {"coordinates":[-92.35124999999999,14.69521],"type":"Point"}
}