{
  "type": "Feature",
  "properties": {
    "gn:admin1_code":"24",
    "gn:admin2_code":"40.0",
    "gn:asciiname":"Ejido Estacion Tamuin",
    "gn:country_code":"MX",
    "gn:dem":50,
    "gn:feature_class":"P",
    "gn:feature_code":"PPL",
    "gn:name":"Ejido Estaci\u00f3n Tamu\u00edn",
    "gn:population":8,
    "gn:timezone":"America/Mexico_City",
    "iso:country":"MX",
    "name:und_x_variant":[
        "Ejido Estaci\u00f3n Tamu\u00edn"
    ],
    "wof:name":"Ejido Estacion Tamuin",
    "wof:placetype":"locality",
    "wof:population":8
},
  "geometry": {"coordinates":[-98.82693999999999,22.15417],"type":"Point"}
}