{
  "type": "Feature",
  "properties": {
    "gn:admin1_code":"10.0",
    "gn:admin2_code":"11.0",
    "gn:asciiname":"Cieneguita",
    "gn:country_code":"MX",
    "gn:dem":1557,
    "gn:feature_class":"P",
    "gn:feature_code":"PPL",
    "gn:name":"Cieneguita",
    "gn:population":0,
    "gn:timezone":"America/Monterrey",
    "iso:country":"MX",
    "wof:name":"Cieneguita",
    "wof:placetype":"locality"
},
  "geometry": {"coordinates":[-105.11667,25.76667],"type":"Point"}
}