{
  "type": "Feature",
  "properties": {
    "gn:admin1_code":"20.0",
    "gn:admin2_code":"141.0",
    "gn:asciiname":"Tapesco",
    "gn:country_code":"MX",
    "gn:dem":6,
    "gn:feature_class":"P",
    "gn:feature_code":"PPL",
    "gn:name":"Tapesco",
    "gn:population":0,
    "gn:timezone":"America/Mexico_City",
    "iso:country":"MX",
    "name:spa_x_preferred":[
        "Tapesco"
    ],
    "wof:name":"Tapesco",
    "wof:placetype":"locality"
},
  "geometry": {"coordinates":[-94.57640000000001,16.20904],"type":"Point"}
}