{
  "type": "Feature",
  "properties": {
    "gn:admin1_code":"19.0",
    "gn:asciiname":"Veintiocho de Marzo",
    "gn:country_code":"MX",
    "gn:dem":431,
    "gn:feature_class":"P",
    "gn:feature_code":"PPL",
    "gn:name":"Veintiocho de Marzo",
    "gn:population":0,
    "gn:timezone":"America/Monterrey",
    "iso:country":"MX",
    "name:spa_x_preferred":[
        "Veintiocho de Marzo"
    ],
    "wof:name":"Veintiocho de Marzo",
    "wof:placetype":"locality"
},
  "geometry": {"coordinates":[-100.23806999999999,25.96005],"type":"Point"}
}