{
  "type": "Feature",
  "properties": {
    "gn:admin1_code":"20",
    "gn:admin2_code":"559.0",
    "gn:asciiname":"Colonia Nuevo Valle Real",
    "gn:country_code":"MX",
    "gn:dem":88,
    "gn:feature_class":"P",
    "gn:feature_code":"PPL",
    "gn:name":"Colonia Nuevo Valle Real",
    "gn:population":317,
    "gn:timezone":"America/Mexico_City",
    "iso:country":"MX",
    "wof:name":"Colonia Nuevo Valle Real",
    "wof:placetype":"locality",
    "wof:population":317
},
  "geometry": {"coordinates":[-96.31,17.78194],"type":"Point"}
}