{
  "type": "Feature",
  "properties": {
    "gn:admin1_code":"20",
    "gn:admin2_code":"207.0",
    "gn:asciiname":"San Jeronimo Zoochina",
    "gn:cc2":"MX",
    "gn:country_code":"MX",
    "gn:dem":159,
    "gn:feature_class":"P",
    "gn:feature_code":"PPL",
    "gn:name":"San Jer\u00f3nimo Zoochina",
    "gn:population":0,
    "gn:timezone":"America/Mexico_City",
    "iso:country":"MX",
    "name:und_x_variant":[
        "Zoochina",
        "Zoochila",
        "San Jer\u00f3nimo Zoochina"
    ],
    "wof:name":"San Jeronimo Zoochina",
    "wof:placetype":"locality"
},
  "geometry": {"coordinates":[-95.25,17.21667],"type":"Point"}
}