{
  "type": "Feature",
  "properties": {
    "gn:admin1_code":"10",
    "gn:admin2_code":"34.0",
    "gn:asciiname":"Mantecosa",
    "gn:country_code":"MX",
    "gn:dem":450,
    "gn:feature_class":"P",
    "gn:feature_code":"PPL",
    "gn:name":"Mantecosa",
    "gn:population":0,
    "gn:timezone":"America/Monterrey",
    "iso:country":"MX",
    "name:spa_x_preferred":[
        "Mantecosa"
    ],
    "wof:name":"Mantecosa",
    "wof:placetype":"locality"
},
  "geometry": {"coordinates":[-106.78631,24.91337],"type":"Point"}
}