{
  "type": "Feature",
  "properties": {
    "gn:admin1_code":"26",
    "gn:admin2_code":"38.0",
    "gn:asciiname":"El Recodo",
    "gn:country_code":"MX",
    "gn:dem":660,
    "gn:feature_class":"P",
    "gn:feature_code":"PPL",
    "gn:name":"El Recodo",
    "gn:population":0,
    "gn:timezone":"America/Hermosillo",
    "iso:country":"MX",
    "name:spa_x_preferred":[
        "El Recodo"
    ],
    "wof:name":"El Recodo",
    "wof:placetype":"locality"
},
  "geometry": {"coordinates":[-109.60333,29.73167],"type":"Point"}
}