{
  "type": "Feature",
  "properties": {
    "gn:admin1_code":"15.0",
    "gn:admin2_code":"123.0",
    "gn:asciiname":"Trojes",
    "gn:country_code":"MX",
    "gn:dem":1127,
    "gn:feature_class":"P",
    "gn:feature_code":"PPL",
    "gn:name":"Trojes",
    "gn:population":0,
    "gn:timezone":"America/Mexico_City",
    "iso:country":"MX",
    "name:ceb_x_preferred":[
        "Trojes"
    ],
    "name:fra_x_preferred":[
        "Trojes"
    ],
    "name:ita_x_preferred":[
        "Trojes"
    ],
    "name:nld_x_preferred":[
        "Trojes"
    ],
    "name:pol_x_preferred":[
        "Trojes"
    ],
    "name:por_x_preferred":[
        "Trojes"
    ],
    "name:spa_x_preferred":[
        "Trojes"
    ],
    "name:swe_x_preferred":[
        "Trojes"
    ],
    "name:zho_x_preferred":[
        "\u7279\u7f85\u8d6b\u65af"
    ],
    "wof:name":"Trojes",
    "wof:placetype":"locality"
},
  "geometry": {"coordinates":[-100.27535,18.93139],"type":"Point"}
}