{
  "type": "Feature",
  "properties": {
    "gn:admin1_code":"5",
    "gn:admin2_code":"71",
    "gn:asciiname":"La Victoria",
    "gn:country_code":"MX",
    "gn:dem":17,
    "gn:feature_class":"P",
    "gn:feature_code":"PPL",
    "gn:name":"La Victoria",
    "gn:population":12,
    "gn:timezone":"America/Mexico_City",
    "iso:country":"MX",
    "name:ara_x_preferred":[
        "\u0644\u0627 \u0641\u064a\u0643\u062a\u0648\u0631\u064a\u0627"
    ],
    "name:ben_x_preferred":[
        "\u09b2\u09be \u09ad\u09bf\u0995\u09cd\u099f\u09cb\u09b0\u09bf\u09df\u09be"
    ],
    "name:bre_x_preferred":[
        "La Victoria"
    ],
    "name:ceb_x_preferred":[
        "La Victoria"
    ],
    "name:deu_x_preferred":[
        "La Victoria"
    ],
    "name:ell_x_preferred":[
        "\u039b\u03b1 \u0392\u03b9\u03ba\u03c4\u03cc\u03c1\u03b9\u03b1"
    ],
    "name:eng_x_preferred":[
        "La Victoria"
    ],
    "name:fas_x_preferred":[
        "\u0644\u0627 \u0648\u06cc\u06a9\u062a\u0648\u0631\u06cc\u0627"
    ],
    "name:fra_x_preferred":[
        "La Victoria"
    ],
    "name:glg_x_preferred":[
        "La Victoria"
    ],
    "name:heb_x_preferred":[
        "\u05dc\u05d4 \u05d5\u05d9\u05e7\u05d8\u05d5\u05e8\u05d9\u05d4"
    ],
    "name:hin_x_preferred":[
        "\u0932\u093e \u0935\u093f\u0915\u094d\u091f\u094b\u0930\u093f\u092f\u093e"
    ],
    "name:hun_x_preferred":[
        "La Victoria"
    ],
    "name:ind_x_preferred":[
        "La Victoria"
    ],
    "name:ita_x_preferred":[
        "La Victoria"
    ],
    "name:jpn_x_preferred":[
        "\u30e9\u30d3\u30af\u30c8\u30ea\u30a2"
    ],
    "name:kor_x_preferred":[
        "\ub77c \ube45\ud1a0\ub9ac\uc544"
    ],
    "name:msa_x_preferred":[
        "La Victoria"
    ],
    "name:nld_x_preferred":[
        "La Victoria"
    ],
    "name:pol_x_preferred":[
        "La Victoria"
    ],
    "name:por_x_preferred":[
        "La Victoria"
    ],
    "name:rus_x_preferred":[
        "\u041b\u0430-\u0412\u0438\u043a\u0442\u043e\u0440\u0438\u044f"
    ],
    "name:spa_x_preferred":[
        "La Victoria"
    ],
    "name:swe_x_preferred":[
        "La Victoria"
    ],
    "name:tur_x_preferred":[
        "La Victoria"
    ],
    "name:ukr_x_preferred":[
        "\u041b\u0430-\u0412\u0456\u043a\u0442\u043e\u0440\u0456\u044f"
    ],
    "name:urd_x_preferred":[
        "\u0644\u0627 \u0648\u06a9\u0679\u0648\u0631\u06cc\u0627"
    ],
    "name:vie_x_preferred":[
        "La Victoria"
    ],
    "name:vol_x_preferred":[
        "La Victoria"
    ],
    "name:war_x_preferred":[
        "La Victoria"
    ],
    "name:zho_cn_x_preferred":[
        "\u5361\u8428\u591a\u6e2f"
    ],
    "name:zho_tw_x_preferred":[
        "\u7dad\u591a\u5229\u4e9e"
    ],
    "wof:name":"La Victoria",
    "wof:placetype":"locality",
    "wof:population":12
},
  "geometry": {"coordinates":[-92.62009,15.11953],"type":"Point"}
}