{
  "type": "Feature",
  "properties": {
    "gn:admin1_code":"30",
    "gn:admin2_code":"187.0",
    "gn:asciiname":"Dos Pocitos",
    "gn:country_code":"MX",
    "gn:dem":2109,
    "gn:feature_class":"P",
    "gn:feature_code":"PPL",
    "gn:name":"Dos Pocitos",
    "gn:population":245,
    "gn:timezone":"America/Mexico_City",
    "iso:country":"MX",
    "wof:name":"Dos Pocitos",
    "wof:placetype":"locality",
    "wof:population":245
},
  "geometry": {"coordinates":[-96.90944,19.74139],"type":"Point"}
}