{
  "type": "Feature",
  "properties": {
    "gn:admin1_code":"20",
    "gn:admin2_code":"498.0",
    "gn:asciiname":"Tierra Quemada",
    "gn:country_code":"MX",
    "gn:dem":79,
    "gn:feature_class":"P",
    "gn:feature_code":"PPL",
    "gn:name":"Tierra Quemada",
    "gn:population":0,
    "gn:timezone":"America/Mexico_City",
    "iso:country":"MX",
    "name:spa_x_preferred":[
        "Tierra Quemada"
    ],
    "wof:name":"Tierra Quemada",
    "wof:placetype":"locality"
},
  "geometry": {"coordinates":[-95.39472000000001,17.46991],"type":"Point"}
}