{
  "type": "Feature",
  "properties": {
    "gn:admin1_code":"18",
    "gn:admin2_code":"19.0",
    "gn:asciiname":"El Coyote",
    "gn:country_code":"MX",
    "gn:dem":1574,
    "gn:feature_class":"P",
    "gn:feature_code":"PPL",
    "gn:name":"El Coyote",
    "gn:population":67,
    "gn:timezone":"America/Mazatlan",
    "iso:country":"MX",
    "wof:name":"El Coyote",
    "wof:placetype":"locality",
    "wof:population":67
},
  "geometry": {"coordinates":[-104.14944,21.75667],"type":"Point"}
}