{
  "type": "Feature",
  "properties": {
    "gn:admin1_code":"24.0",
    "gn:admin2_code":"40.0",
    "gn:asciiname":"El Guamuchil",
    "gn:country_code":"MX",
    "gn:dem":47,
    "gn:feature_class":"P",
    "gn:feature_code":"PPL",
    "gn:name":"El Guamuchil",
    "gn:population":0,
    "gn:timezone":"America/Mexico_City",
    "iso:country":"MX",
    "name:spa_x_preferred":[
        "El Guamuchil"
    ],
    "wof:name":"El Guamuchil",
    "wof:placetype":"locality"
},
  "geometry": {"coordinates":[-98.74602,22.14113],"type":"Point"}
}