{
  "type": "Feature",
  "properties": {
    "gn:admin1_code":"19",
    "gn:admin2_code":"45",
    "gn:asciiname":"San Isidro",
    "gn:country_code":"MX",
    "gn:dem":452,
    "gn:feature_class":"P",
    "gn:feature_code":"PPL",
    "gn:name":"San Isidro",
    "gn:population":28,
    "gn:timezone":"America/Monterrey",
    "iso:country":"MX",
    "wof:name":"San Isidro",
    "wof:placetype":"locality",
    "wof:population":28
},
  "geometry": {"coordinates":[-100.31028000000001,25.95583],"type":"Point"}
}