{
  "type": "Feature",
  "properties": {
    "gn:admin1_code":"24.0",
    "gn:admin2_code":"55.0",
    "gn:asciiname":"Animas",
    "gn:country_code":"MX",
    "gn:dem":1989,
    "gn:feature_class":"P",
    "gn:feature_code":"PPL",
    "gn:name":"\u00c1nimas",
    "gn:population":0,
    "gn:timezone":"America/Mexico_City",
    "iso:country":"MX",
    "name:ceb_x_preferred":[
        "Animas"
    ],
    "name:por_x_preferred":[
        "Animas"
    ],
    "name:srp_x_preferred":[
        "\u0410\u043d\u0438\u043c\u0430\u0441"
    ],
    "name:swe_x_preferred":[
        "Animas"
    ],
    "wof:name":"Animas",
    "wof:placetype":"locality"
},
  "geometry": {"coordinates":[-100.73333,22.11667000000001],"type":"Point"}
}