{
  "type": "Feature",
  "properties": {
    "gn:admin1_code":"22",
    "gn:admin2_code":"8",
    "gn:asciiname":"Campestre Bosques del Sur [Fraccionamiento]",
    "gn:country_code":"MX",
    "gn:dem":2425,
    "gn:feature_class":"P",
    "gn:feature_code":"PPL",
    "gn:name":"Campestre Bosques del Sur [Fraccionamiento]",
    "gn:population":10,
    "gn:timezone":"America/Mexico_City",
    "iso:country":"MX",
    "wof:name":"Campestre Bosques del Sur [Fraccionamiento]",
    "wof:placetype":"locality",
    "wof:population":10
},
  "geometry": {"coordinates":[-100.26861,20.31722],"type":"Point"}
}