{
  "type": "Feature",
  "properties": {
    "gn:admin1_code":"5",
    "gn:admin2_code":"59.0",
    "gn:asciiname":"Tomas Munzer (Nueva Patria)",
    "gn:country_code":"MX",
    "gn:dem":1217,
    "gn:feature_class":"P",
    "gn:feature_code":"PPL",
    "gn:name":"Tom\u00e1s Munzer (Nueva Patria)",
    "gn:population":498,
    "gn:timezone":"America/Mexico_City",
    "iso:country":"MX",
    "name:und_x_variant":[
        "Tom\u00e1s Munzer (Nueva Patria)"
    ],
    "wof:name":"Tomas Munzer (Nueva Patria)",
    "wof:placetype":"locality",
    "wof:population":498
},
  "geometry": {"coordinates":[-92.15000000000001,16.78694],"type":"Point"}
}