{
  "type": "Feature",
  "properties": {
    "gn:admin1_code":"5.0",
    "gn:admin2_code":"51.0",
    "gn:asciiname":"Los Luises",
    "gn:country_code":"MX",
    "gn:dem":66,
    "gn:feature_class":"P",
    "gn:feature_code":"PPL",
    "gn:name":"Los Luises",
    "gn:population":0,
    "gn:timezone":"America/Mexico_City",
    "iso:country":"MX",
    "name:spa_x_preferred":[
        "Los Luises"
    ],
    "wof:name":"Los Luises",
    "wof:placetype":"locality"
},
  "geometry": {"coordinates":[-92.86516,15.43155],"type":"Point"}
}