{
  "type": "Feature",
  "properties": {
    "gn:admin1_code":"20",
    "gn:admin2_code":"314.0",
    "gn:asciiname":"Barrio Santa Lucia",
    "gn:country_code":"MX",
    "gn:dem":855,
    "gn:feature_class":"P",
    "gn:feature_code":"PPL",
    "gn:name":"Barrio Santa Luc\u00eda",
    "gn:population":111,
    "gn:timezone":"America/Mexico_City",
    "iso:country":"MX",
    "name:und_x_variant":[
        "Barrio Santa Luc\u00eda"
    ],
    "wof:name":"Barrio Santa Lucia",
    "wof:placetype":"locality",
    "wof:population":111
},
  "geometry": {"coordinates":[-97.08360999999999,16.33527999999999],"type":"Point"}
}