{
  "type": "Feature",
  "properties": {
    "gn:admin1_code":"26",
    "gn:admin2_code":"30.0",
    "gn:asciiname":"Ganadera Contreras",
    "gn:country_code":"MX",
    "gn:dem":159,
    "gn:feature_class":"P",
    "gn:feature_code":"PPL",
    "gn:name":"Ganadera Contreras",
    "gn:population":5,
    "gn:timezone":"America/Hermosillo",
    "iso:country":"MX",
    "wof:name":"Ganadera Contreras",
    "wof:placetype":"locality",
    "wof:population":5
},
  "geometry": {"coordinates":[-111.07056,28.94833],"type":"Point"}
}