{
  "type": "Feature",
  "properties": {
    "gn:admin1_code":"7",
    "gn:admin2_code":"9.0",
    "gn:asciiname":"Dieciocho de Marzo",
    "gn:country_code":"MX",
    "gn:dem":1104,
    "gn:feature_class":"P",
    "gn:feature_code":"PPL",
    "gn:name":"Dieciocho de Marzo",
    "gn:population":331,
    "gn:timezone":"America/Monterrey",
    "iso:country":"MX",
    "wof:name":"Dieciocho de Marzo",
    "wof:placetype":"locality",
    "wof:population":331
},
  "geometry": {"coordinates":[-103.28610999999999,25.92806],"type":"Point"}
}