{
  "type": "Feature",
  "properties": {
    "gn:admin1_code":"28.0",
    "gn:admin2_code":"37.0",
    "gn:asciiname":"Las Margaritas",
    "gn:country_code":"MX",
    "gn:dem":32,
    "gn:feature_class":"P",
    "gn:feature_code":"PPL",
    "gn:name":"Las Margaritas",
    "gn:population":1,
    "gn:timezone":"America/Monterrey",
    "iso:country":"MX",
    "name:spa_x_preferred":[
        "Las Margaritas"
    ],
    "wof:name":"Las Margaritas",
    "wof:placetype":"locality",
    "wof:population":1
},
  "geometry": {"coordinates":[-98.08278,23.60722],"type":"Point"}
}