{
  "type": "Feature",
  "properties": {
    "gn:admin1_code":"32.0",
    "gn:admin2_code":"7.0",
    "gn:asciiname":"Agua Dulce",
    "gn:country_code":"MX",
    "gn:dem":2050,
    "gn:feature_class":"P",
    "gn:feature_code":"PPL",
    "gn:name":"Agua Dulce",
    "gn:population":0,
    "gn:timezone":"America/Mexico_City",
    "iso:country":"MX",
    "wof:name":"Agua Dulce",
    "wof:placetype":"locality"
},
  "geometry": {"coordinates":[-101.06667,24.48333],"type":"Point"}
}