{
  "type": "Feature",
  "properties": {
    "gn:admin1_code":"16.0",
    "gn:admin2_code":"13.0",
    "gn:asciiname":"Sacapungame",
    "gn:country_code":"MX",
    "gn:dem":706,
    "gn:feature_class":"P",
    "gn:feature_code":"PPL",
    "gn:name":"Sacapungame",
    "gn:population":0,
    "gn:timezone":"America/Mexico_City",
    "iso:country":"MX",
    "name:spa_x_preferred":[
        "Sacapungame"
    ],
    "wof:name":"Sacapungame",
    "wof:placetype":"locality"
},
  "geometry": {"coordinates":[-101.07738000000001,18.96786],"type":"Point"}
}