{
  "type": "Feature",
  "properties": {
    "gn:admin1_code":"31",
    "gn:admin2_code":"46.0",
    "gn:asciiname":"Yaxtunil",
    "gn:country_code":"MX",
    "gn:dem":21,
    "gn:feature_class":"P",
    "gn:feature_code":"PPL",
    "gn:name":"Yaxtunil",
    "gn:population":0,
    "gn:timezone":"America/Merida",
    "iso:country":"MX",
    "wof:name":"Yaxtunil",
    "wof:placetype":"locality"
},
  "geometry": {"coordinates":[-89.41667,20.53333],"type":"Point"}
}