{
  "type": "Feature",
  "properties": {
    "gn:admin1_code":"6",
    "gn:admin2_code":"66.0",
    "gn:asciiname":"Corregidora de Abajo",
    "gn:country_code":"MX",
    "gn:dem":771,
    "gn:feature_class":"P",
    "gn:feature_code":"PPL",
    "gn:name":"Corregidora de Abajo",
    "gn:population":0,
    "gn:timezone":"America/Chihuahua",
    "iso:country":"MX",
    "name:spa_x_preferred":[
        "Corregidora de Abajo"
    ],
    "name:spa_x_variant":[
        "La Finca"
    ],
    "wof:name":"Corregidora de Abajo",
    "wof:placetype":"locality"
},
  "geometry": {"coordinates":[-108.27670999999999,27.80779],"type":"Point"}
}