{
  "type": "Feature",
  "properties": {
    "gn:admin1_code":"5",
    "gn:admin2_code":"20.0",
    "gn:asciiname":"Mexicali",
    "gn:country_code":"MX",
    "gn:dem":599,
    "gn:feature_class":"P",
    "gn:feature_code":"PPL",
    "gn:name":"Mexicali",
    "gn:population":4,
    "gn:timezone":"America/Mexico_City",
    "iso:country":"MX",
    "wof:name":"Mexicali",
    "wof:placetype":"locality",
    "wof:population":4
},
  "geometry": {"coordinates":[-92.44611,15.94583],"type":"Point"}
}