{
  "type": "Feature",
  "properties": {
    "gn:admin1_code":"11.0",
    "gn:admin2_code":"30.0",
    "gn:asciiname":"Fabrica de Guadalupe",
    "gn:country_code":"MX",
    "gn:dem":2214,
    "gn:feature_class":"P",
    "gn:feature_code":"PPL",
    "gn:name":"F\u00e1brica de Guadalupe",
    "gn:population":0,
    "gn:timezone":"America/Mexico_City",
    "iso:country":"MX",
    "name:spa_x_preferred":[
        "F\u00e1brica de Guadalupe"
    ],
    "name:spa_x_variant":[
        "F\u00e1brica Guadalupe"
    ],
    "name:und_x_variant":[
        "Potreros La F\u00e1brica"
    ],
    "wof:name":"Fabrica de Guadalupe",
    "wof:placetype":"locality"
},
  "geometry": {"coordinates":[-101.37014000000001,21.68973],"type":"Point"}
}