{
  "type": "Feature",
  "properties": {
    "gn:admin1_code":"6",
    "gn:admin2_code":"27",
    "gn:asciiname":"Mochogueachi",
    "gn:country_code":"MX",
    "gn:dem":2342,
    "gn:feature_class":"P",
    "gn:feature_code":"PPL",
    "gn:name":"Mochogueachi",
    "gn:population":28,
    "gn:timezone":"America/Chihuahua",
    "iso:country":"MX",
    "wof:name":"Mochogueachi",
    "wof:placetype":"locality",
    "wof:population":28
},
  "geometry": {"coordinates":[-107.57241999999999,27.66214],"type":"Point"}
}