{
  "type": "Feature",
  "properties": {
    "gn:admin1_code":"13",
    "gn:admin2_code":"73.0",
    "gn:asciiname":"Totonicapa",
    "gn:country_code":"MX",
    "gn:dem":961,
    "gn:feature_class":"P",
    "gn:feature_code":"PPL",
    "gn:name":"Totonicapa",
    "gn:population":410,
    "gn:timezone":"America/Mexico_City",
    "iso:country":"MX",
    "name:spa_x_preferred":[
        "Totonicapa"
    ],
    "wof:name":"Totonicapa",
    "wof:placetype":"locality",
    "wof:population":410
},
  "geometry": {"coordinates":[-98.64109999999999,20.94864],"type":"Point"}
}