{
  "type": "Feature",
  "properties": {
    "gn:admin1_code":"5",
    "gn:admin2_code":"80.0",
    "gn:asciiname":"La Yayaguita",
    "gn:country_code":"MX",
    "gn:dem":1424,
    "gn:feature_class":"P",
    "gn:feature_code":"PPL",
    "gn:name":"La Yayaguita",
    "gn:population":7,
    "gn:timezone":"America/Mexico_City",
    "iso:country":"MX",
    "wof:name":"La Yayaguita",
    "wof:placetype":"locality",
    "wof:population":7
},
  "geometry": {"coordinates":[-92.41028,15.68667],"type":"Point"}
}