{
  "type": "Feature",
  "properties": {
    "gn:admin1_code":"30.0",
    "gn:admin2_code":"170.0",
    "gn:asciiname":"El Mirral",
    "gn:country_code":"MX",
    "gn:dem":1404,
    "gn:feature_class":"P",
    "gn:feature_code":"PPL",
    "gn:name":"El Mirral",
    "gn:population":61,
    "gn:timezone":"America/Mexico_City",
    "iso:country":"MX",
    "name:spa_x_preferred":[
        "El Mirral"
    ],
    "wof:name":"El Mirral",
    "wof:placetype":"locality",
    "wof:population":61
},
  "geometry": {"coordinates":[-98.28924000000001,20.59544],"type":"Point"}
}