{
  "type": "Feature",
  "properties": {
    "gn:admin1_code":"7.0",
    "gn:admin2_code":"14.0",
    "gn:asciiname":"La Lonja",
    "gn:country_code":"MX",
    "gn:dem":264,
    "gn:feature_class":"P",
    "gn:feature_code":"PPL",
    "gn:name":"La Lonja",
    "gn:population":0,
    "gn:timezone":"America/Monterrey",
    "iso:country":"MX",
    "name:spa_x_preferred":[
        "La Lonja"
    ],
    "wof:name":"La Lonja",
    "wof:placetype":"locality"
},
  "geometry": {"coordinates":[-100.70329,29.00128],"type":"Point"}
}