{
  "type": "Feature",
  "properties": {
    "gn:admin1_code":"20.0",
    "gn:admin2_code":"59.0",
    "gn:asciiname":"El Rodeo",
    "gn:country_code":"MX",
    "gn:dem":1613,
    "gn:feature_class":"P",
    "gn:feature_code":"PPL",
    "gn:name":"El Rodeo",
    "gn:population":0,
    "gn:timezone":"America/Mexico_City",
    "iso:country":"MX",
    "name:spa_x_preferred":[
        "El Rodeo"
    ],
    "wof:name":"El Rodeo",
    "wof:placetype":"locality"
},
  "geometry": {"coordinates":[-96.78319999999999,16.28633],"type":"Point"}
}