{
  "type": "Feature",
  "properties": {
    "gn:admin1_code":"9.0",
    "gn:asciiname":"Tianguillo",
    "gn:country_code":"MX",
    "gn:dem":2972,
    "gn:feature_class":"P",
    "gn:feature_code":"PPL",
    "gn:name":"Tianguillo",
    "gn:population":0,
    "gn:timezone":"America/Mexico_City",
    "iso:country":"MX",
    "name:spa_x_preferred":[
        "Tianguillo"
    ],
    "wof:name":"Tianguillo",
    "wof:placetype":"locality"
},
  "geometry": {"coordinates":[-99.32334,19.31831],"type":"Point"}
}