{
  "type": "Feature",
  "properties": {
    "gn:admin1_code":"14",
    "gn:admin2_code":"90.0",
    "gn:asciiname":"Rancho Santa Rosa",
    "gn:country_code":"MX",
    "gn:dem":1468,
    "gn:feature_class":"P",
    "gn:feature_code":"PPL",
    "gn:name":"Rancho Santa Rosa",
    "gn:population":5,
    "gn:timezone":"America/Mexico_City",
    "iso:country":"MX",
    "wof:name":"Rancho Santa Rosa",
    "wof:placetype":"locality",
    "wof:population":5
},
  "geometry": {"coordinates":[-104.18138999999999,20.23222],"type":"Point"}
}