{
  "type": "Feature",
  "properties": {
    "gn:admin1_code":"30.0",
    "gn:asciiname":"Horcones",
    "gn:country_code":"MX",
    "gn:dem":54,
    "gn:feature_class":"P",
    "gn:feature_code":"PPL",
    "gn:name":"Horcones",
    "gn:population":0,
    "gn:timezone":"America/Mexico_City",
    "iso:country":"MX",
    "name:spa_x_preferred":[
        "Horcones"
    ],
    "wof:name":"Horcones",
    "wof:placetype":"locality"
},
  "geometry": {"coordinates":[-97.52593,20.76578],"type":"Point"}
}