{
  "type": "Feature",
  "properties": {
    "gn:admin1_code":"32.0",
    "gn:admin2_code":"8.0",
    "gn:asciiname":"Segunda Seccion Lazaro Cardenas",
    "gn:country_code":"MX",
    "gn:dem":2027,
    "gn:feature_class":"P",
    "gn:feature_code":"PPL",
    "gn:name":"Segunda Secci\u00f3n L\u00e1zaro C\u00e1rdenas",
    "gn:population":0,
    "gn:timezone":"America/Mexico_City",
    "iso:country":"MX",
    "name:spa_x_preferred":[
        "Segunda Secci\u00f3n L\u00e1zaro C\u00e1rdenas"
    ],
    "wof:name":"Segunda Seccion Lazaro Cardenas",
    "wof:placetype":"locality"
},
  "geometry": {"coordinates":[-102.33765,22.45304],"type":"Point"}
}