{
  "type": "Feature",
  "properties": {
    "gn:admin1_code":"2.0",
    "gn:admin2_code":"1.0",
    "gn:asciiname":"Playa Campo Cadena",
    "gn:country_code":"MX",
    "gn:dem":5,
    "gn:feature_class":"P",
    "gn:feature_code":"PPL",
    "gn:name":"Playa Campo Cadena",
    "gn:population":0,
    "gn:timezone":"America/Tijuana",
    "iso:country":"MX",
    "name:spa_x_preferred":[
        "Playa Campo Cadena"
    ],
    "wof:name":"Playa Campo Cadena",
    "wof:placetype":"locality"
},
  "geometry": {"coordinates":[-114.69956999999999,30.63796],"type":"Point"}
}