{
  "type": "Feature",
  "properties": {
    "gn:admin1_code":"10.0",
    "gn:admin2_code":"5.0",
    "gn:asciiname":"La Pradera",
    "gn:country_code":"MX",
    "gn:dem":1859,
    "gn:feature_class":"P",
    "gn:feature_code":"PPL",
    "gn:name":"La Pradera",
    "gn:population":0,
    "gn:timezone":"America/Monterrey",
    "iso:country":"MX",
    "name:spa_x_preferred":[
        "La Pradera"
    ],
    "wof:name":"La Pradera",
    "wof:placetype":"locality"
},
  "geometry": {"coordinates":[-104.50672,24.14308],"type":"Point"}
}