{
  "type": "Feature",
  "properties": {
    "gn:admin1_code":"11.0",
    "gn:admin2_code":"15.0",
    "gn:asciiname":"Plan de la Mina",
    "gn:country_code":"MX",
    "gn:dem":2247,
    "gn:feature_class":"P",
    "gn:feature_code":"PPL",
    "gn:name":"Plan de la Mina",
    "gn:population":0,
    "gn:timezone":"America/Mexico_City",
    "iso:country":"MX",
    "name:spa_x_preferred":[
        "Plan de la Mina"
    ],
    "wof:name":"Plan de la Mina",
    "wof:placetype":"locality"
},
  "geometry": {"coordinates":[-101.13914,21.07368],"type":"Point"}
}