{
  "type": "Feature",
  "properties": {
    "gn:admin1_code":"20",
    "gn:admin2_code":"58",
    "gn:asciiname":"Nacimiento",
    "gn:country_code":"MX",
    "gn:dem":1957,
    "gn:feature_class":"P",
    "gn:feature_code":"PPL",
    "gn:name":"Nacimiento",
    "gn:population":32,
    "gn:timezone":"America/Mexico_City",
    "iso:country":"MX",
    "wof:name":"Nacimiento",
    "wof:placetype":"locality",
    "wof:population":32
},
  "geometry": {"coordinates":[-96.95556000000001,18.04389],"type":"Point"}
}