{
  "type": "Feature",
  "properties": {
    "gn:admin1_code":"20",
    "gn:admin2_code":"58",
    "gn:asciiname":"Nacimiento",
    "gn:country_code":"MX",
    "gn:dem":1957,
    "gn:feature_class":"P",
    "gn:feature_code":"PPL",
    "gn:name":"Nacimiento",
    "gn:population":32,
    "gn:timezone":"America/Mexico_City",
    "iso:country":"MX",
    "name:ceb_x_preferred":[
        "Nacimiento"
    ],
    "name:deu_x_preferred":[
        "Nacimiento"
    ],
    "name:eus_x_preferred":[
        "Nacimiento"
    ],
    "name:fra_x_preferred":[
        "Nacimiento"
    ],
    "name:glg_x_preferred":[
        "Nacimiento"
    ],
    "name:ita_x_preferred":[
        "Nacimiento"
    ],
    "name:nld_x_preferred":[
        "Nacimiento"
    ],
    "name:oci_x_preferred":[
        "Nacimiento"
    ],
    "name:por_x_preferred":[
        "Nacimiento"
    ],
    "name:ron_x_preferred":[
        "Nacimiento"
    ],
    "name:rus_x_preferred":[
        "\u041d\u0430\u0441\u0438\u043c\u044c\u0435\u043d\u0442\u043e"
    ],
    "name:spa_x_preferred":[
        "Nacimiento"
    ],
    "name:swe_x_preferred":[
        "Nacimiento"
    ],
    "name:tur_x_preferred":[
        "Nacimiento"
    ],
    "wof:name":"Nacimiento",
    "wof:placetype":"locality",
    "wof:population":32
},
  "geometry": {"coordinates":[-96.95556000000001,18.04389],"type":"Point"}
}