{
  "type": "Feature",
  "properties": {
    "gn:admin1_code":"6",
    "gn:admin2_code":"67.0",
    "gn:asciiname":"El Nayar",
    "gn:country_code":"MX",
    "gn:dem":1404,
    "gn:feature_class":"P",
    "gn:feature_code":"PPL",
    "gn:name":"El Nayar",
    "gn:population":0,
    "gn:timezone":"America/Chihuahua",
    "iso:country":"MX",
    "name:deu_x_preferred":[
        "Municipio El Nayar"
    ],
    "name:epo_x_preferred":[
        "Del Nayar"
    ],
    "name:ita_x_preferred":[
        "El Nayar"
    ],
    "name:por_x_preferred":[
        "El Nayar"
    ],
    "name:rus_x_preferred":[
        "\u042d\u043b\u044c-\u041d\u0430\u044f\u0440"
    ],
    "name:spa_x_preferred":[
        "El Nayar"
    ],
    "name:vie_x_preferred":[
        "El Nayar"
    ],
    "wof:name":"El Nayar",
    "wof:placetype":"locality"
},
  "geometry": {"coordinates":[-105.77934,27.61018],"type":"Point"}
}