{
  "type": "Feature",
  "properties": {
    "gn:admin1_code":"7.0",
    "gn:admin2_code":"37.0",
    "gn:asciiname":"Los Papalotes Cuates",
    "gn:country_code":"MX",
    "gn:dem":358,
    "gn:feature_class":"P",
    "gn:feature_code":"PPL",
    "gn:name":"Los Papalotes Cuates",
    "gn:population":0,
    "gn:timezone":"America/Monterrey",
    "iso:country":"MX",
    "name:spa_x_preferred":[
        "Los Papalotes Cuates"
    ],
    "wof:name":"Los Papalotes Cuates",
    "wof:placetype":"locality"
},
  "geometry": {"coordinates":[-100.57168,28.02169],"type":"Point"}
}