{
  "type": "Feature",
  "properties": {
    "gn:admin1_code":"19",
    "gn:admin2_code":"17.0",
    "gn:asciiname":"Valle Hermoso",
    "gn:country_code":"MX",
    "gn:dem":1900,
    "gn:feature_class":"P",
    "gn:feature_code":"PPL",
    "gn:name":"Valle Hermoso",
    "gn:population":0,
    "gn:timezone":"America/Monterrey",
    "iso:country":"MX",
    "name:spa_x_preferred":[
        "Valle Hermoso"
    ],
    "wof:name":"Valle Hermoso",
    "wof:placetype":"locality"
},
  "geometry": {"coordinates":[-100.26721000000001,24.53188],"type":"Point"}
}