{
  "type": "Feature",
  "properties": {
    "gn:admin1_code":"6",
    "gn:admin2_code":"40.0",
    "gn:asciiname":"El Quemado",
    "gn:country_code":"MX",
    "gn:dem":2187,
    "gn:feature_class":"P",
    "gn:feature_code":"PPL",
    "gn:name":"El Quemado",
    "gn:population":4,
    "gn:timezone":"America/Chihuahua",
    "iso:country":"MX",
    "wof:name":"El Quemado",
    "wof:placetype":"locality",
    "wof:population":4
},
  "geometry": {"coordinates":[-108.40889,29.61681],"type":"Point"}
}