{
  "type": "Feature",
  "properties": {
    "gn:admin1_code":"17",
    "gn:admin2_code":"9",
    "gn:asciiname":"Tepetzala",
    "gn:country_code":"MX",
    "gn:dem":2501,
    "gn:feature_class":"P",
    "gn:feature_code":"PPL",
    "gn:name":"Tepetzala",
    "gn:population":37,
    "gn:timezone":"America/Mexico_City",
    "iso:country":"MX",
    "wof:name":"Tepetzala",
    "wof:placetype":"locality",
    "wof:population":37
},
  "geometry": {"coordinates":[-99.26139000000001,19.02583],"type":"Point"}
}