{
  "type": "Feature",
  "properties": {
    "gn:admin1_code":"30",
    "gn:admin2_code":"33.0",
    "gn:asciiname":"Barra de Cazones",
    "gn:country_code":"MX",
    "gn:dem":10,
    "gn:feature_class":"P",
    "gn:feature_code":"PPL",
    "gn:name":"Barra de Cazones",
    "gn:population":0,
    "gn:timezone":"America/Mexico_City",
    "iso:country":"MX",
    "name:und_x_variant":[
        "La Barra de Cazones",
        "Barra de Cazones"
    ],
    "wof:name":"Barra de Cazones",
    "wof:placetype":"locality"
},
  "geometry": {"coordinates":[-97.2032,20.72307],"type":"Point"}
}