{
  "type": "Feature",
  "properties": {
    "gn:admin1_code":"32",
    "gn:admin2_code":"38",
    "gn:asciiname":"La Alcaparra",
    "gn:country_code":"MX",
    "gn:dem":2263,
    "gn:feature_class":"P",
    "gn:feature_code":"PPL",
    "gn:name":"La Alcaparra",
    "gn:population":16,
    "gn:timezone":"America/Mexico_City",
    "iso:country":"MX",
    "wof:name":"La Alcaparra",
    "wof:placetype":"locality",
    "wof:population":16
},
  "geometry": {"coordinates":[-101.6225,22.40444],"type":"Point"}
}