{
  "type": "Feature",
  "properties": {
    "gn:admin1_code":"32",
    "gn:admin2_code":"49.0",
    "gn:asciiname":"El Refugio de Abajo",
    "gn:country_code":"MX",
    "gn:dem":1887,
    "gn:feature_class":"P",
    "gn:feature_code":"PPL",
    "gn:name":"El Refugio de Abajo",
    "gn:population":0,
    "gn:timezone":"America/Mexico_City",
    "iso:country":"MX",
    "name:spa_x_preferred":[
        "El Refugio de Abajo"
    ],
    "wof:name":"El Refugio de Abajo",
    "wof:placetype":"locality"
},
  "geometry": {"coordinates":[-104.26152999999999,22.36478],"type":"Point"}
}