{
  "type": "Feature",
  "properties": {
    "gn:admin1_code":"6",
    "gn:admin2_code":"6.0",
    "gn:asciiname":"San Jose Bachiniva",
    "gn:country_code":"MX",
    "gn:dem":2002,
    "gn:feature_class":"P",
    "gn:feature_code":"PPL",
    "gn:name":"San Jos\u00e9 Bachiniva",
    "gn:population":0,
    "gn:timezone":"America/Chihuahua",
    "iso:country":"MX",
    "name:spa_x_preferred":[
        "San Jos\u00e9 Bachiniva"
    ],
    "name:und_x_variant":[
        "San Jos\u00e9",
        "San Jos\u00e9 de Bach\u00edniva"
    ],
    "wof:name":"San Jose Bachiniva",
    "wof:placetype":"locality"
},
  "geometry": {"coordinates":[-107.24963,28.78972000000001],"type":"Point"}
}