{
  "type": "Feature",
  "properties": {
    "gn:admin1_code":"21",
    "gn:admin2_code":"53.0",
    "gn:asciiname":"Paxtla",
    "gn:country_code":"MX",
    "gn:dem":2369,
    "gn:feature_class":"P",
    "gn:feature_code":"PPL",
    "gn:name":"Paxtla",
    "gn:population":144,
    "gn:timezone":"America/Mexico_City",
    "iso:country":"MX",
    "wof:name":"Paxtla",
    "wof:placetype":"locality",
    "wof:population":144
},
  "geometry": {"coordinates":[-98.08744,19.79863],"type":"Point"}
}