{
  "type": "Feature",
  "properties": {
    "gn:admin1_code":"12",
    "gn:admin2_code":"58.0",
    "gn:asciiname":"Rincon del Sauce",
    "gn:country_code":"MX",
    "gn:dem":1564,
    "gn:feature_class":"P",
    "gn:feature_code":"PPL",
    "gn:name":"Rinc\u00f3n del Sauce",
    "gn:population":201,
    "gn:timezone":"America/Mexico_City",
    "iso:country":"MX",
    "name:und_x_variant":[
        "Rinc\u00f3n del Sauce"
    ],
    "wof:name":"Rincon del Sauce",
    "wof:placetype":"locality",
    "wof:population":201
},
  "geometry": {"coordinates":[-99.83139,18.34528],"type":"Point"}
}