{
  "type": "Feature",
  "properties": {
    "gn:admin1_code":"12.0",
    "gn:admin2_code":"7.0",
    "gn:asciiname":"Quiteria",
    "gn:country_code":"MX",
    "gn:dem":623,
    "gn:feature_class":"P",
    "gn:feature_code":"PPL",
    "gn:name":"Quiteria",
    "gn:population":0,
    "gn:timezone":"America/Mexico_City",
    "iso:country":"MX",
    "name:arg_x_preferred":[
        "Santa Quiteria"
    ],
    "name:cat_x_preferred":[
        "Quit\u00e8ria"
    ],
    "name:deu_x_preferred":[
        "Quiteria"
    ],
    "name:fra_x_preferred":[
        "Sainte Quitterie"
    ],
    "name:ita_x_preferred":[
        "Quiteria"
    ],
    "name:oci_x_preferred":[
        "Quit\u00e8ira"
    ],
    "name:pol_x_preferred":[
        "Kwiteria"
    ],
    "name:rus_x_preferred":[
        "\u041a\u0432\u0438\u0442\u0435\u0440\u0438\u044f"
    ],
    "name:spa_x_preferred":[
        "Quiteria"
    ],
    "name:tam_x_preferred":[
        "\u0b95\u0bc1\u0bb5\u0bbf\u0ba4\u0bcd\u0ba4\u0bc7\u0bb0\u0bbf\u0baf\u0bbe"
    ],
    "wof:name":"Quiteria",
    "wof:placetype":"locality"
},
  "geometry": {"coordinates":[-100.19293,18.41231],"type":"Point"}
}