{
  "type": "Feature",
  "properties": {
    "gn:admin1_code":"19.0",
    "gn:admin2_code":"5.0",
    "gn:asciiname":"La Palma",
    "gn:country_code":"MX",
    "gn:dem":192,
    "gn:feature_class":"P",
    "gn:feature_code":"PPL",
    "gn:name":"La Palma",
    "gn:population":3,
    "gn:timezone":"America/Matamoros",
    "iso:country":"MX",
    "name:spa_x_preferred":[
        "Las Palmas"
    ],
    "wof:name":"La Palma",
    "wof:placetype":"locality",
    "wof:population":3
},
  "geometry": {"coordinates":[-100.14006000000001,27.22141],"type":"Point"}
}