{
  "type": "Feature",
  "properties": {
    "gn:admin1_code":"22",
    "gn:admin2_code":"16.0",
    "gn:asciiname":"Dolores Godoy",
    "gn:country_code":"MX",
    "gn:dem":2091,
    "gn:feature_class":"P",
    "gn:feature_code":"PPL",
    "gn:name":"Dolores Godoy",
    "gn:population":450,
    "gn:timezone":"America/Mexico_City",
    "iso:country":"MX",
    "wof:name":"Dolores Godoy",
    "wof:placetype":"locality",
    "wof:population":450
},
  "geometry": {"coordinates":[-99.95999999999999,20.33278],"type":"Point"}
}