{
  "type": "Feature",
  "properties": {
    "gn:admin1_code":"2",
    "gn:admin2_code":"2",
    "gn:asciiname":"Vulcano",
    "gn:country_code":"MX",
    "gn:dem":17,
    "gn:feature_class":"P",
    "gn:feature_code":"PPL",
    "gn:name":"Vulcano",
    "gn:population":17,
    "gn:timezone":"America/Tijuana",
    "iso:country":"MX",
    "name:ara_x_preferred":[
        "\u0641\u0648\u0644\u0643\u0627\u0646\u0648"
    ],
    "name:bel_x_preferred":[
        "\u0412\u0443\u043b\u043a\u0430\u043d\u0430"
    ],
    "name:bre_x_preferred":[
        "Vulcano"
    ],
    "name:cat_x_preferred":[
        "Vulcano"
    ],
    "name:ceb_x_preferred":[
        "Isola Vulcano"
    ],
    "name:ces_x_preferred":[
        "Vulcano"
    ],
    "name:cos_x_preferred":[
        "Vulcanu"
    ],
    "name:dan_x_preferred":[
        "Vulcano"
    ],
    "name:deu_x_preferred":[
        "Vulcano"
    ],
    "name:ell_x_preferred":[
        "\u0392\u03bf\u03c5\u03bb\u03ba\u03ac\u03bd\u03bf"
    ],
    "name:epo_x_preferred":[
        "Vulcano"
    ],
    "name:est_x_preferred":[
        "Vulcano"
    ],
    "name:eus_x_preferred":[
        "Vulcano"
    ],
    "name:fas_x_preferred":[
        "\u0648\u0648\u0644\u06a9\u0627\u0646\u0648"
    ],
    "name:fra_x_preferred":[
        "Vulcano"
    ],
    "name:glg_x_preferred":[
        "Illa Vulcano"
    ],
    "name:heb_x_preferred":[
        "\u05d5\u05d5\u05dc\u05e7\u05e0\u05d5"
    ],
    "name:hun_x_preferred":[
        "Vulcano"
    ],
    "name:ind_x_preferred":[
        "Vurcanu"
    ],
    "name:jpn_x_preferred":[
        "\u30f4\u30eb\u30ab\u30fc\u30ce\u5cf6"
    ],
    "name:kat_x_preferred":[
        "\u10d5\u10e3\u10da\u10d9\u10d0\u10dc\u10dd"
    ],
    "name:kor_x_preferred":[
        "\ubd88\uce74\ub178\uc12c"
    ],
    "name:lat_x_preferred":[
        "Vulcanus"
    ],
    "name:lav_x_preferred":[
        "Vulk\u0101no"
    ],
    "name:lit_x_preferred":[
        "Vulkanas"
    ],
    "name:mkd_x_preferred":[
        "\u0412\u0443\u043b\u043a\u0430\u043d\u043e"
    ],
    "name:mlt_x_preferred":[
        "Vulcano"
    ],
    "name:nld_x_preferred":[
        "Vulcano"
    ],
    "name:nno_x_preferred":[
        "Vulcano"
    ],
    "name:nor_x_preferred":[
        "Vulcano"
    ],
    "name:oci_x_preferred":[
        "Vulcano"
    ],
    "name:pol_x_preferred":[
        "Vulcano"
    ],
    "name:ron_x_preferred":[
        "Vulcano"
    ],
    "name:rus_x_preferred":[
        "\u0412\u0443\u043b\u044c\u043a\u0430\u043d\u043e"
    ],
    "name:scn_x_preferred":[
        "Vurcanu"
    ],
    "name:sco_x_preferred":[
        "Vulcano"
    ],
    "name:slk_x_preferred":[
        "Vulcano"
    ],
    "name:spa_x_preferred":[
        "Isla Vulcano"
    ],
    "name:srp_x_preferred":[
        "\u0412\u0443\u043b\u043a\u0430\u043d\u043e"
    ],
    "name:swe_x_preferred":[
        "Vulcano"
    ],
    "name:ukr_x_preferred":[
        "\u0412\u0443\u043b\u044c\u043a\u0430\u043d\u043e"
    ],
    "name:zho_x_preferred":[
        "\u6b66\u5c14\u5361\u8bfa\u5c9b"
    ],
    "wof:name":"Vulcano",
    "wof:placetype":"locality",
    "wof:population":17
},
  "geometry": {"coordinates":[-115.10056000000002,32.55083],"type":"Point"}
}