{
  "type": "Feature",
  "properties": {
    "gn:admin1_code":"2",
    "gn:admin2_code":"2",
    "gn:asciiname":"Vulcano",
    "gn:country_code":"MX",
    "gn:dem":17,
    "gn:feature_class":"P",
    "gn:feature_code":"PPL",
    "gn:name":"Vulcano",
    "gn:population":17,
    "gn:timezone":"America/Tijuana",
    "iso:country":"MX",
    "wof:name":"Vulcano",
    "wof:placetype":"locality",
    "wof:population":17
},
  "geometry": {"coordinates":[-115.10056000000002,32.55083],"type":"Point"}
}