{
  "type": "Feature",
  "properties": {
    "gn:admin1_code":"5",
    "gn:admin2_code":"80.0",
    "gn:asciiname":"Villaflores",
    "gn:country_code":"MX",
    "gn:dem":1628,
    "gn:feature_class":"P",
    "gn:feature_code":"PPL",
    "gn:name":"Villaflores",
    "gn:population":177,
    "gn:timezone":"America/Mexico_City",
    "iso:country":"MX",
    "name:ceb_x_preferred":[
        "Villaflores"
    ],
    "name:deu_x_preferred":[
        "Villaflores"
    ],
    "name:fra_x_preferred":[
        "Villaflores"
    ],
    "name:por_x_preferred":[
        "Villaflores"
    ],
    "name:rus_x_preferred":[
        "\u0412\u0438\u043b\u044c\u044f\u0444\u043b\u043e\u0440\u0435\u0441"
    ],
    "name:sco_x_preferred":[
        "Villaflores"
    ],
    "name:spa_x_preferred":[
        "Villaflores"
    ],
    "name:swe_x_preferred":[
        "Villaflores"
    ],
    "name:vie_x_preferred":[
        "Villaflores"
    ],
    "wof:name":"Villaflores",
    "wof:placetype":"locality",
    "wof:population":177
},
  "geometry": {"coordinates":[-92.44389,15.51528],"type":"Point"}
}