{
  "type": "Feature",
  "properties": {
    "gn:admin1_code":"15",
    "gn:asciiname":"Montero",
    "gn:cc2":"MX",
    "gn:country_code":"MX",
    "gn:dem":2294,
    "gn:feature_class":"P",
    "gn:feature_code":"PPL",
    "gn:name":"Montero",
    "gn:population":0,
    "gn:timezone":"America/Mexico_City",
    "iso:country":"MX",
    "name:und_x_variant":[
        "Atotonilco",
        "Montero"
    ],
    "wof:name":"Montero",
    "wof:placetype":"locality"
},
  "geometry": {"coordinates":[-99.21666999999999,19.91667],"type":"Point"}
}