{
  "type": "Feature",
  "properties": {
    "gn:admin1_code":"15",
    "gn:asciiname":"Montero",
    "gn:cc2":"MX",
    "gn:country_code":"MX",
    "gn:dem":2294,
    "gn:feature_class":"P",
    "gn:feature_code":"PPL",
    "gn:name":"Montero",
    "gn:population":0,
    "gn:timezone":"America/Mexico_City",
    "iso:country":"MX",
    "name:afr_x_preferred":[
        "Montero"
    ],
    "name:ara_x_preferred":[
        "\u0645\u0648\u0646\u062a\u064a\u0631\u0648"
    ],
    "name:dan_x_preferred":[
        "Montero"
    ],
    "name:deu_x_preferred":[
        "Montero"
    ],
    "name:epo_x_preferred":[
        "Montero"
    ],
    "name:fas_x_preferred":[
        "\u0645\u0648\u0646\u062a\u0631\u0648"
    ],
    "name:fin_x_preferred":[
        "Montero"
    ],
    "name:fra_x_preferred":[
        "Montero"
    ],
    "name:ita_x_preferred":[
        "Montero"
    ],
    "name:jpn_x_preferred":[
        "\u30e2\u30f3\u30c6\u30ed"
    ],
    "name:kat_x_preferred":[
        "\u10db\u10dd\u10dc\u10e2\u10d4\u10e0\u10dd"
    ],
    "name:kor_x_preferred":[
        "\ubaac\ud14c\ub85c"
    ],
    "name:lit_x_preferred":[
        "Monteras"
    ],
    "name:mkd_x_preferred":[
        "\u041c\u043e\u043d\u0442\u0435\u0440\u043e"
    ],
    "name:nld_x_preferred":[
        "Montero"
    ],
    "name:pol_x_preferred":[
        "Montero"
    ],
    "name:por_x_preferred":[
        "Montero"
    ],
    "name:que_x_preferred":[
        "Montero"
    ],
    "name:ron_x_preferred":[
        "Montero"
    ],
    "name:spa_x_preferred":[
        "Montero"
    ],
    "name:swe_x_preferred":[
        "Montero"
    ],
    "name:tat_x_preferred":[
        "\u041c\u043e\u043d\u0442\u0435\u0440\u043e"
    ],
    "name:und_x_variant":[
        "Atotonilco"
    ],
    "name:vol_x_preferred":[
        "Montero"
    ],
    "name:war_x_preferred":[
        "Montero"
    ],
    "name:zho_x_preferred":[
        "\u8499\u7279\u7f85"
    ],
    "wof:name":"Montero",
    "wof:placetype":"locality"
},
  "geometry": {"coordinates":[-99.21666999999999,19.91667],"type":"Point"}
}