{
  "type": "Feature",
  "properties": {
    "gn:admin1_code":"30",
    "gn:admin2_code":"124.0",
    "gn:asciiname":"Miguel Aleman Velasco",
    "gn:country_code":"MX",
    "gn:dem":93,
    "gn:feature_class":"P",
    "gn:feature_code":"PPL",
    "gn:name":"Miguel Alem\u00e1n Velasco",
    "gn:population":80,
    "gn:timezone":"America/Mexico_City",
    "iso:country":"MX",
    "name:und_x_variant":[
        "Miguel Alem\u00e1n Velasco"
    ],
    "wof:name":"Miguel Aleman Velasco",
    "wof:placetype":"locality",
    "wof:population":80
},
  "geometry": {"coordinates":[-97.18556,20.16028],"type":"Point"}
}