{
  "type": "Feature",
  "properties": {
    "gn:admin1_code":"32.0",
    "gn:admin2_code":"34.0",
    "gn:asciiname":"Rancho Viejo del Sur",
    "gn:country_code":"MX",
    "gn:dem":1794,
    "gn:feature_class":"P",
    "gn:feature_code":"PPL",
    "gn:name":"Rancho Viejo del Sur",
    "gn:population":0,
    "gn:timezone":"America/Mexico_City",
    "iso:country":"MX",
    "name:spa_x_preferred":[
        "Rancho Viejo del Sur"
    ],
    "name:spa_x_variant":[
        "Rancho Viejo"
    ],
    "wof:name":"Rancho Viejo del Sur",
    "wof:placetype":"locality"
},
  "geometry": {"coordinates":[-102.90779000000001,21.2553],"type":"Point"}
}