{
  "type": "Feature",
  "properties": {
    "gn:admin1_code":"14",
    "gn:admin2_code":"34.0",
    "gn:asciiname":"Mesa de San Nicolas",
    "gn:country_code":"MX",
    "gn:dem":1175,
    "gn:feature_class":"P",
    "gn:feature_code":"PPL",
    "gn:name":"Mesa de San Nicol\u00e1s",
    "gn:population":0,
    "gn:timezone":"America/Mexico_City",
    "iso:country":"MX",
    "name:spa_x_preferred":[
        "Mesa de San Nicol\u00e1s"
    ],
    "name:spa_x_variant":[
        "La Mesa"
    ],
    "name:und_x_variant":[
        "San Nicol\u00e1s"
    ],
    "wof:name":"Mesa de San Nicolas",
    "wof:placetype":"locality"
},
  "geometry": {"coordinates":[-104.03823,19.96029],"type":"Point"}
}