{
  "type": "Feature",
  "properties": {
    "gn:admin1_code":"21",
    "gn:admin2_code":"109.0",
    "gn:asciiname":"Atla",
    "gn:country_code":"MX",
    "gn:dem":1128,
    "gn:feature_class":"P",
    "gn:feature_code":"PPL",
    "gn:name":"Atla",
    "gn:population":2172,
    "gn:timezone":"America/Mexico_City",
    "iso:country":"MX",
    "name:ceb_x_preferred":[
        "Atla"
    ],
    "name:deu_x_preferred":[
        "Atla"
    ],
    "name:hye_x_preferred":[
        "\u0531\u057f\u056c\u0561"
    ],
    "name:nld_x_preferred":[
        "Atla"
    ],
    "name:sco_x_preferred":[
        "Atla"
    ],
    "name:spa_x_preferred":[
        "Atla"
    ],
    "name:srp_x_preferred":[
        "\u0410\u0442\u043b\u0430"
    ],
    "name:swe_x_preferred":[
        "Atla"
    ],
    "name:tur_x_preferred":[
        "Atla"
    ],
    "name:vol_x_preferred":[
        "Atla"
    ],
    "wof:name":"Atla",
    "wof:placetype":"locality",
    "wof:population":2172
},
  "geometry": {"coordinates":[-98.12469,20.27527000000001],"type":"Point"}
}