{
  "type": "Feature",
  "properties": {
    "gn:admin1_code":"30",
    "gn:admin2_code":"175.0",
    "gn:asciiname":"Sector la Ceiba (Ejido Poza de Cuero)",
    "gn:country_code":"MX",
    "gn:dem":50,
    "gn:feature_class":"P",
    "gn:feature_code":"PPL",
    "gn:name":"Sector la Ceiba (Ejido Poza de Cuero)",
    "gn:population":147,
    "gn:timezone":"America/Mexico_City",
    "iso:country":"MX",
    "wof:name":"Sector la Ceiba (Ejido Poza de Cuero)",
    "wof:placetype":"locality",
    "wof:population":147
},
  "geometry": {"coordinates":[-97.46167,20.56028],"type":"Point"}
}