{
  "type": "Feature",
  "properties": {
    "gn:admin1_code":"22.0",
    "gn:admin2_code":"11.0",
    "gn:asciiname":"Las Projitas",
    "gn:country_code":"MX",
    "gn:dem":1971,
    "gn:feature_class":"P",
    "gn:feature_code":"PPL",
    "gn:name":"Las Projitas",
    "gn:population":0,
    "gn:timezone":"America/Mexico_City",
    "iso:country":"MX",
    "name:spa_x_preferred":[
        "Las Projitas"
    ],
    "wof:name":"Las Projitas",
    "wof:placetype":"locality"
},
  "geometry": {"coordinates":[-100.27709,20.60769],"type":"Point"}
}