{
  "type": "Feature",
  "properties": {
    "gn:admin1_code":"30.0",
    "gn:admin2_code":"123.0",
    "gn:asciiname":"Anguiano",
    "gn:country_code":"MX",
    "gn:dem":39,
    "gn:feature_class":"P",
    "gn:feature_code":"PPL",
    "gn:name":"Anguiano",
    "gn:population":1,
    "gn:timezone":"America/Mexico_City",
    "iso:country":"MX",
    "name:arg_x_preferred":[
        "Anguiano"
    ],
    "name:ast_x_preferred":[
        "Anguiano"
    ],
    "name:cat_x_preferred":[
        "Anguiano"
    ],
    "name:ceb_x_preferred":[
        "Anguiano"
    ],
    "name:deu_x_preferred":[
        "Anguiano"
    ],
    "name:eus_x_preferred":[
        "Anguiano"
    ],
    "name:fra_x_preferred":[
        "Anguiano"
    ],
    "name:glg_x_preferred":[
        "Anguiano"
    ],
    "name:hun_x_preferred":[
        "Anguiano"
    ],
    "name:hye_x_preferred":[
        "\u0531\u0576\u0563\u056b\u0561\u0576\u0578"
    ],
    "name:ita_x_preferred":[
        "Anguiano"
    ],
    "name:kaz_x_preferred":[
        "\u0410\u043d\u0433\u0438\u0430\u043d\u043e"
    ],
    "name:msa_x_preferred":[
        "Anguiano"
    ],
    "name:nld_x_preferred":[
        "Anguiano"
    ],
    "name:oci_x_preferred":[
        "Anguiano"
    ],
    "name:pol_x_preferred":[
        "Anguiano"
    ],
    "name:por_x_preferred":[
        "Anguiano"
    ],
    "name:rus_x_preferred":[
        "\u0410\u043d\u0433\u044c\u044f\u043d\u043e"
    ],
    "name:spa_x_preferred":[
        "Anguiano"
    ],
    "name:swe_x_preferred":[
        "Anguiano"
    ],
    "name:ukr_x_preferred":[
        "\u0410\u043d\u0433\u0456\u0430\u043d\u043e"
    ],
    "name:uzb_x_preferred":[
        "Anguiano"
    ],
    "name:vie_x_preferred":[
        "Anguiano"
    ],
    "name:war_x_preferred":[
        "Anguiano"
    ],
    "name:zho_x_preferred":[
        "\u5b89\u5409\u4e9a\u8bfa"
    ],
    "wof:name":"Anguiano",
    "wof:placetype":"locality",
    "wof:population":1
},
  "geometry": {"coordinates":[-98.41797,22.30255],"type":"Point"}
}