{
  "type": "Feature",
  "properties": {
    "gn:admin1_code":"25",
    "gn:admin2_code":"6",
    "gn:asciiname":"Kilometro Dos y Medio",
    "gn:country_code":"MX",
    "gn:dem":33,
    "gn:feature_class":"P",
    "gn:feature_code":"PPL",
    "gn:name":"Kil\u00f3metro Dos y Medio",
    "gn:population":11,
    "gn:timezone":"America/Mazatlan",
    "iso:country":"MX",
    "name:und_x_variant":[
        "Kil\u00f3metro Dos y Medio"
    ],
    "wof:name":"Kilometro Dos y Medio",
    "wof:placetype":"locality",
    "wof:population":11
},
  "geometry": {"coordinates":[-107.45083,24.75581],"type":"Point"}
}