{
  "type": "Feature",
  "properties": {
    "gn:admin1_code":"26",
    "gn:admin2_code":"30.0",
    "gn:asciiname":"El Compartidero",
    "gn:country_code":"MX",
    "gn:dem":190,
    "gn:feature_class":"P",
    "gn:feature_code":"PPL",
    "gn:name":"El Compartidero",
    "gn:population":0,
    "gn:timezone":"America/Hermosillo",
    "iso:country":"MX",
    "name:spa_x_preferred":[
        "El Compartidero"
    ],
    "wof:name":"El Compartidero",
    "wof:placetype":"locality"
},
  "geometry": {"coordinates":[-110.98278000000001,29.06679],"type":"Point"}
}