{
  "type": "Feature",
  "properties": {
    "gn:admin1_code":"32",
    "gn:admin2_code":"15.0",
    "gn:asciiname":"Francisco I. Madero",
    "gn:country_code":"MX",
    "gn:dem":2299,
    "gn:feature_class":"P",
    "gn:feature_code":"PPL",
    "gn:name":"Francisco I. Madero",
    "gn:population":0,
    "gn:timezone":"America/Mexico_City",
    "iso:country":"MX",
    "name:spa_x_preferred":[
        "Francisco I. Madero"
    ],
    "name:und_x_variant":[
        "Rancho del Padre"
    ],
    "wof:name":"Francisco I. Madero",
    "wof:placetype":"locality"
},
  "geometry": {"coordinates":[-103.1336,21.98335],"type":"Point"}
}