{
  "type": "Feature",
  "properties": {
    "gn:admin1_code":"5",
    "gn:admin2_code":"30.0",
    "gn:asciiname":"El Sabinalito",
    "gn:country_code":"MX",
    "gn:dem":1418,
    "gn:feature_class":"P",
    "gn:feature_code":"PPL",
    "gn:name":"El Sabinalito",
    "gn:population":243,
    "gn:timezone":"America/Mexico_City",
    "iso:country":"MX",
    "wof:name":"El Sabinalito",
    "wof:placetype":"locality",
    "wof:population":243
},
  "geometry": {"coordinates":[-92.51528,15.76472],"type":"Point"}
}