{
  "type": "Feature",
  "properties": {
    "gn:admin1_code":"10",
    "gn:admin2_code":"32",
    "gn:asciiname":"Ranchito de Juan Angel (La Hielera)",
    "gn:country_code":"MX",
    "gn:dem":2457,
    "gn:feature_class":"P",
    "gn:feature_code":"PPL",
    "gn:name":"Ranchito de Juan \u00c1ngel (La Hielera)",
    "gn:population":28,
    "gn:timezone":"America/Monterrey",
    "iso:country":"MX",
    "name:und_x_variant":[
        "Ranchito de Juan \u00c1ngel (La Hielera)"
    ],
    "wof:name":"Ranchito de Juan Angel (La Hielera)",
    "wof:placetype":"locality",
    "wof:population":28
},
  "geometry": {"coordinates":[-105.51116,24.67611],"type":"Point"}
}