{
  "type": "Feature",
  "properties": {
    "gn:admin1_code":"32",
    "gn:admin2_code":"49.0",
    "gn:asciiname":"El Tulillo",
    "gn:country_code":"MX",
    "gn:dem":1577,
    "gn:feature_class":"P",
    "gn:feature_code":"PPL",
    "gn:name":"El Tulillo",
    "gn:population":161,
    "gn:timezone":"America/Mexico_City",
    "iso:country":"MX",
    "name:spa_x_preferred":[
        "El Tulillo"
    ],
    "wof:name":"El Tulillo",
    "wof:placetype":"locality",
    "wof:population":161
},
  "geometry": {"coordinates":[-104.1262,22.5257],"type":"Point"}
}