{
  "type": "Feature",
  "properties": {
    "gn:admin1_code":"7.0",
    "gn:admin2_code":"2.0",
    "gn:asciiname":"La Encantada",
    "gn:country_code":"MX",
    "gn:dem":1289,
    "gn:feature_class":"P",
    "gn:feature_code":"PPL",
    "gn:name":"La Encantada",
    "gn:population":0,
    "gn:timezone":"America/Matamoros",
    "iso:country":"MX",
    "name:ceb_x_preferred":[
        "La Encantada"
    ],
    "name:spa_x_preferred":[
        "La Encantada"
    ],
    "name:swe_x_preferred":[
        "La Encantada"
    ],
    "name:und_x_variant":[
        "Rancho la Encantada"
    ],
    "wof:name":"La Encantada",
    "wof:placetype":"locality"
},
  "geometry": {"coordinates":[-102.26810999999999,29.08272],"type":"Point"}
}