{
  "type": "Feature",
  "properties": {
    "gn:admin1_code":"30",
    "gn:admin2_code":"121.0",
    "gn:asciiname":"Buenos Aires (El Mante)",
    "gn:country_code":"MX",
    "gn:dem":29,
    "gn:feature_class":"P",
    "gn:feature_code":"PPL",
    "gn:name":"Buenos Aires (El Mante)",
    "gn:population":110,
    "gn:timezone":"America/Mexico_City",
    "iso:country":"MX",
    "wof:name":"Buenos Aires (El Mante)",
    "wof:placetype":"locality",
    "wof:population":110
},
  "geometry": {"coordinates":[-97.77,21.5975],"type":"Point"}
}