{
  "type": "Feature",
  "properties": {
    "gn:admin1_code":"31",
    "gn:admin2_code":"65.0",
    "gn:asciiname":"Dzonot Pinto",
    "gn:country_code":"MX",
    "gn:dem":5,
    "gn:feature_class":"P",
    "gn:feature_code":"PPL",
    "gn:name":"Dzonot Pinto",
    "gn:population":0,
    "gn:timezone":"America/Merida",
    "iso:country":"MX",
    "name:spa_x_preferred":[
        "Dzonot Pinto"
    ],
    "wof:name":"Dzonot Pinto",
    "wof:placetype":"locality"
},
  "geometry": {"coordinates":[-88.33150999999999,21.45079],"type":"Point"}
}