{
  "type": "Feature",
  "properties": {
    "gn:admin1_code":"24",
    "gn:admin2_code":"54.0",
    "gn:asciiname":"La Joya de Tlaletla",
    "gn:country_code":"MX",
    "gn:dem":764,
    "gn:feature_class":"P",
    "gn:feature_code":"PPL",
    "gn:name":"La Joya de Tlaletla",
    "gn:population":199,
    "gn:timezone":"America/Mexico_City",
    "iso:country":"MX",
    "wof:name":"La Joya de Tlaletla",
    "wof:placetype":"locality",
    "wof:population":199
},
  "geometry": {"coordinates":[-98.98667,21.34306],"type":"Point"}
}