{
  "type": "Feature",
  "properties": {
    "gn:admin1_code":"30",
    "gn:admin2_code":"89.0",
    "gn:asciiname":"Luisa Hernandez Geronimo",
    "gn:country_code":"MX",
    "gn:dem":49,
    "gn:feature_class":"P",
    "gn:feature_code":"PPL",
    "gn:name":"Luisa Hern\u00e1ndez Ger\u00f3nimo",
    "gn:population":5,
    "gn:timezone":"America/Mexico_City",
    "iso:country":"MX",
    "name:und_x_variant":[
        "Luisa Hern\u00e1ndez Ger\u00f3nimo"
    ],
    "wof:name":"Luisa Hernandez Geronimo",
    "wof:placetype":"locality",
    "wof:population":5
},
  "geometry": {"coordinates":[-94.77139,17.975],"type":"Point"}
}