{
  "type": "Feature",
  "properties": {
    "gn:admin1_code":"5",
    "gn:admin2_code":"97",
    "gn:asciiname":"El Primor",
    "gn:country_code":"MX",
    "gn:dem":28,
    "gn:feature_class":"P",
    "gn:feature_code":"PPL",
    "gn:name":"El Primor",
    "gn:population":13,
    "gn:timezone":"America/Mexico_City",
    "iso:country":"MX",
    "wof:name":"El Primor",
    "wof:placetype":"locality",
    "wof:population":13
},
  "geometry": {"coordinates":[-93.47944,15.85083],"type":"Point"}
}