{
  "type": "Feature",
  "properties": {
    "gn:admin1_code":"32",
    "gn:admin2_code":"52",
    "gn:asciiname":"Los Vergeles",
    "gn:country_code":"MX",
    "gn:dem":2145,
    "gn:feature_class":"P",
    "gn:feature_code":"PPL",
    "gn:name":"Los Vergeles",
    "gn:population":32,
    "gn:timezone":"America/Mexico_City",
    "iso:country":"MX",
    "wof:name":"Los Vergeles",
    "wof:placetype":"locality",
    "wof:population":32
},
  "geometry": {"coordinates":[-101.965,22.18972],"type":"Point"}
}