{
  "type": "Feature",
  "properties": {
    "gn:admin1_code":"15",
    "gn:admin2_code":"47.0",
    "gn:asciiname":"San Francisco Portezuelo",
    "gn:country_code":"MX",
    "gn:dem":2578,
    "gn:feature_class":"P",
    "gn:feature_code":"PPL",
    "gn:name":"San Francisco Portezuelo",
    "gn:population":320,
    "gn:timezone":"America/Mexico_City",
    "iso:country":"MX",
    "wof:name":"San Francisco Portezuelo",
    "wof:placetype":"locality",
    "wof:population":320
},
  "geometry": {"coordinates":[-99.64709999999999,19.53046],"type":"Point"}
}