{
  "type": "Feature",
  "properties": {
    "gn:admin1_code":"24",
    "gn:admin2_code":"27.0",
    "gn:asciiname":"Corral Quemado",
    "gn:country_code":"MX",
    "gn:dem":1231,
    "gn:feature_class":"P",
    "gn:feature_code":"PPL",
    "gn:name":"Corral Quemado",
    "gn:population":0,
    "gn:timezone":"America/Mexico_City",
    "iso:country":"MX",
    "name:ita_x_preferred":[
        "Corral Quemado"
    ],
    "name:por_x_preferred":[
        "Corral Quemado"
    ],
    "name:spa_x_preferred":[
        "Corral Quemado"
    ],
    "name:und_x_variant":[
        "Quemado"
    ],
    "wof:name":"Corral Quemado",
    "wof:placetype":"locality",
    "wof:population":53
},
  "geometry": {"coordinates":[-99.96704,21.59021],"type":"Point"}
}