{
  "type": "Feature",
  "properties": {
    "gn:admin1_code":"30",
    "gn:admin2_code":"94.0",
    "gn:asciiname":"Nuevo Remolino (El Cincuenta)",
    "gn:country_code":"MX",
    "gn:dem":46,
    "gn:feature_class":"P",
    "gn:feature_code":"PPL",
    "gn:name":"Nuevo Remolino (El Cincuenta)",
    "gn:population":187,
    "gn:timezone":"America/Mexico_City",
    "iso:country":"MX",
    "wof:name":"Nuevo Remolino (El Cincuenta)",
    "wof:placetype":"locality",
    "wof:population":187
},
  "geometry": {"coordinates":[-95.37667,18.09611],"type":"Point"}
}