{
  "type": "Feature",
  "properties": {
    "gn:admin1_code":"30.0",
    "gn:admin2_code":"175.0",
    "gn:asciiname":"Lindero",
    "gn:country_code":"MX",
    "gn:dem":80,
    "gn:feature_class":"P",
    "gn:feature_code":"PPL",
    "gn:name":"Lindero",
    "gn:population":496,
    "gn:timezone":"America/Mexico_City",
    "iso:country":"MX",
    "name:spa_x_preferred":[
        "Lindero"
    ],
    "wof:name":"Lindero",
    "wof:placetype":"locality",
    "wof:population":496
},
  "geometry": {"coordinates":[-97.54056,20.49389],"type":"Point"}
}