{
  "type": "Feature",
  "properties": {
    "gn:admin1_code":"23",
    "gn:admin2_code":"1.0",
    "gn:asciiname":"Juan Leyenda Trigo",
    "gn:country_code":"MX",
    "gn:dem":9,
    "gn:feature_class":"P",
    "gn:feature_code":"PPL",
    "gn:name":"Juan Leyenda Trigo",
    "gn:population":9,
    "gn:timezone":"America/Cancun",
    "iso:country":"MX",
    "wof:name":"Juan Leyenda Trigo",
    "wof:placetype":"locality",
    "wof:population":9
},
  "geometry": {"coordinates":[-86.90888000000002,20.48747],"type":"Point"}
}