{
  "type": "Feature",
  "properties": {
    "gn:admin1_code":"20",
    "gn:admin2_code":"532.0",
    "gn:asciiname":"Morelos",
    "gn:country_code":"MX",
    "gn:dem":2299,
    "gn:feature_class":"P",
    "gn:feature_code":"PPL",
    "gn:name":"Morelos",
    "gn:population":265,
    "gn:timezone":"America/Mexico_City",
    "iso:country":"MX",
    "wof:name":"Morelos",
    "wof:placetype":"locality",
    "wof:population":265
},
  "geometry": {"coordinates":[-97.77028,17.14667],"type":"Point"}
}