{
  "type": "Feature",
  "properties": {
    "gn:admin1_code":"21",
    "gn:admin2_code":"107.0",
    "gn:asciiname":"Lugua",
    "gn:country_code":"MX",
    "gn:dem":608,
    "gn:feature_class":"P",
    "gn:feature_code":"PPL",
    "gn:name":"Lugua",
    "gn:population":0,
    "gn:timezone":"America/Mexico_City",
    "iso:country":"MX",
    "name:spa_x_preferred":[
        "Luhuachuchut"
    ],
    "name:spa_x_variant":[
        "Lugua"
    ],
    "wof:name":"Lugua",
    "wof:placetype":"locality"
},
  "geometry": {"coordinates":[-97.67498000000001,20.08716],"type":"Point"}
}