{
  "type": "Feature",
  "properties": {
    "gn:admin1_code":"25",
    "gn:admin2_code":"1.0",
    "gn:asciiname":"Cuchilla Vieja",
    "gn:country_code":"MX",
    "gn:dem":10,
    "gn:feature_class":"P",
    "gn:feature_code":"PPL",
    "gn:name":"Cuchilla Vieja",
    "gn:population":0,
    "gn:timezone":"America/Mazatlan",
    "iso:country":"MX",
    "name:spa_x_preferred":[
        "Cuchilla Vieja"
    ],
    "name:und_x_variant":[
        "Macapul Viejo"
    ],
    "wof:name":"Cuchilla Vieja",
    "wof:placetype":"locality"
},
  "geometry": {"coordinates":[-109.12506999999999,25.90118],"type":"Point"}
}