{
  "type": "Feature",
  "properties": {
    "gn:admin1_code":"27.0",
    "gn:asciiname":"Chichonal Segunda Seccion",
    "gn:country_code":"MX",
    "gn:dem":28,
    "gn:feature_class":"P",
    "gn:feature_code":"PPL",
    "gn:name":"Chichonal Segunda Secci\u00f3n",
    "gn:population":0,
    "gn:timezone":"America/Mexico_City",
    "iso:country":"MX",
    "name:spa_x_preferred":[
        "Chichonal Segunda Secci\u00f3n"
    ],
    "wof:name":"Chichonal Segunda Seccion",
    "wof:placetype":"locality"
},
  "geometry": {"coordinates":[-92.69655,17.78316000000001],"type":"Point"}
}