{
  "type": "Feature",
  "properties": {
    "gn:admin1_code":"15",
    "gn:admin2_code":"90.0",
    "gn:asciiname":"Loma Rancho Juan Mendez",
    "gn:country_code":"MX",
    "gn:dem":2929,
    "gn:feature_class":"P",
    "gn:feature_code":"PPL",
    "gn:name":"Loma Rancho Juan M\u00e9ndez",
    "gn:population":299,
    "gn:timezone":"America/Mexico_City",
    "iso:country":"MX",
    "name:und_x_variant":[
        "Loma Rancho Juan M\u00e9ndez"
    ],
    "wof:name":"Loma Rancho Juan Mendez",
    "wof:placetype":"locality",
    "wof:population":299
},
  "geometry": {"coordinates":[-99.65558,19.10429],"type":"Point"}
}