{
  "type": "Feature",
  "properties": {
    "gn:admin1_code":"6",
    "gn:admin2_code":"47.0",
    "gn:asciiname":"El Coyote",
    "gn:country_code":"MX",
    "gn:dem":1442,
    "gn:feature_class":"P",
    "gn:feature_code":"PPL",
    "gn:name":"El Coyote",
    "gn:population":0,
    "gn:timezone":"America/Hermosillo",
    "iso:country":"MX",
    "name:spa_x_preferred":[
        "El Coyote"
    ],
    "wof:name":"El Coyote",
    "wof:placetype":"locality"
},
  "geometry": {"coordinates":[-108.67619999999999,28.28733],"type":"Point"}
}