{
  "type": "Feature",
  "properties": {
    "gn:admin1_code":"19.0",
    "gn:admin2_code":"42.0",
    "gn:asciiname":"Las Tres Rositas",
    "gn:country_code":"MX",
    "gn:dem":216,
    "gn:feature_class":"P",
    "gn:feature_code":"PPL",
    "gn:name":"Las Tres Rositas",
    "gn:population":0,
    "gn:timezone":"America/Monterrey",
    "iso:country":"MX",
    "name:spa_x_preferred":[
        "Las Tres Rositas"
    ],
    "wof:name":"Las Tres Rositas",
    "wof:placetype":"locality"
},
  "geometry": {"coordinates":[-99.60978,25.53963],"type":"Point"}
}