{
  "type": "Feature",
  "properties": {
    "gn:admin1_code":"26",
    "gn:admin2_code":"26.0",
    "gn:asciiname":"El Salitral",
    "gn:country_code":"MX",
    "gn:dem":20,
    "gn:feature_class":"P",
    "gn:feature_code":"PPL",
    "gn:name":"El Salitral",
    "gn:population":424,
    "gn:timezone":"America/Hermosillo",
    "iso:country":"MX",
    "wof:name":"El Salitral",
    "wof:placetype":"locality",
    "wof:population":424
},
  "geometry": {"coordinates":[-109.64917,27.02028],"type":"Point"}
}