{
  "type": "Feature",
  "properties": {
    "gn:admin1_code":"2",
    "gn:admin2_code":"2",
    "gn:asciiname":"Familia Hernandez (Veracruz Maritimo)",
    "gn:country_code":"MX",
    "gn:dem":16,
    "gn:feature_class":"P",
    "gn:feature_code":"PPL",
    "gn:name":"Familia Hern\u00e1ndez (Veracruz Mar\u00edtimo)",
    "gn:population":26,
    "gn:timezone":"America/Tijuana",
    "iso:country":"MX",
    "name:und_x_variant":[
        "Familia Hern\u00e1ndez (Veracruz Mar\u00edtimo)"
    ],
    "wof:name":"Familia Hernandez (Veracruz Maritimo)",
    "wof:placetype":"locality",
    "wof:population":26
},
  "geometry": {"coordinates":[-115.10389000000001,32.37472],"type":"Point"}
}