{
  "type": "Feature",
  "properties": {
    "gn:admin1_code":"26",
    "gn:admin2_code":"29.0",
    "gn:asciiname":"Colonia Colinas de Fatima",
    "gn:country_code":"MX",
    "gn:dem":28,
    "gn:feature_class":"P",
    "gn:feature_code":"PPL",
    "gn:name":"Colonia Colinas de F\u00e1tima",
    "gn:population":0,
    "gn:timezone":"America/Hermosillo",
    "iso:country":"MX",
    "name:spa_x_preferred":[
        "Colonia Colinas de F\u00e1tima"
    ],
    "wof:name":"Colonia Colinas de Fatima",
    "wof:placetype":"locality"
},
  "geometry": {"coordinates":[-110.87558,27.94057],"type":"Point"}
}