{
  "type": "Feature",
  "properties": {
    "gn:admin1_code":"25",
    "gn:admin2_code":"13.0",
    "gn:asciiname":"Fraccionamiento las Casitas Nuevas",
    "gn:country_code":"MX",
    "gn:dem":91,
    "gn:feature_class":"P",
    "gn:feature_code":"PPL",
    "gn:name":"Fraccionamiento las Casitas Nuevas",
    "gn:population":179,
    "gn:timezone":"America/Mazatlan",
    "iso:country":"MX",
    "wof:name":"Fraccionamiento las Casitas Nuevas",
    "wof:placetype":"locality",
    "wof:population":179
},
  "geometry": {"coordinates":[-107.91227000000001,25.47568],"type":"Point"}
}