{
  "type": "Feature",
  "properties": {
    "gn:admin1_code":"26",
    "gn:admin2_code":"3",
    "gn:asciiname":"Chihuahua",
    "gn:country_code":"MX",
    "gn:dem":63,
    "gn:feature_class":"P",
    "gn:feature_code":"PPL",
    "gn:name":"Chihuahua",
    "gn:population":13,
    "gn:timezone":"America/Hermosillo",
    "iso:country":"MX",
    "wof:name":"Chihuahua",
    "wof:placetype":"locality",
    "wof:population":13
},
  "geometry": {"coordinates":[-109.01888999999998,26.44722],"type":"Point"}
}