{
  "type": "Feature",
  "properties": {
    "gn:admin1_code":"32",
    "gn:admin2_code":"19.0",
    "gn:asciiname":"Rabion",
    "gn:country_code":"MX",
    "gn:dem":1861,
    "gn:feature_class":"P",
    "gn:feature_code":"PPL",
    "gn:name":"Rabi\u00f3n",
    "gn:population":0,
    "gn:timezone":"America/Mexico_City",
    "iso:country":"MX",
    "name:spa_x_preferred":[
        "Rabi\u00f3n"
    ],
    "name:und_x_variant":[
        "El Rabi\u00f3n"
    ],
    "wof:name":"Rabion",
    "wof:placetype":"locality"
},
  "geometry": {"coordinates":[-103.16227000000001,21.6006],"type":"Point"}
}