{
  "type": "Feature",
  "properties": {
    "gn:admin1_code":"7",
    "gn:admin2_code":"4.0",
    "gn:asciiname":"Veracruz",
    "gn:country_code":"MX",
    "gn:dem":2056,
    "gn:feature_class":"P",
    "gn:feature_code":"PPL",
    "gn:name":"Veracruz",
    "gn:population":0,
    "gn:timezone":"America/Monterrey",
    "iso:country":"MX",
    "name:spa_x_preferred":[
        "Veracruz"
    ],
    "name:und_x_variant":[
        "Rancho Veracruz"
    ],
    "wof:name":"Veracruz",
    "wof:placetype":"locality"
},
  "geometry": {"coordinates":[-100.73142,25.26135],"type":"Point"}
}