{
  "type": "Feature",
  "properties": {
    "gn:admin1_code":"14.0",
    "gn:asciiname":"Potrero Nuevo",
    "gn:country_code":"MX",
    "gn:dem":1842,
    "gn:feature_class":"P",
    "gn:feature_code":"PPL",
    "gn:name":"Potrero Nuevo",
    "gn:population":0,
    "gn:timezone":"America/Mexico_City",
    "iso:country":"MX",
    "name:spa_x_preferred":[
        "Potrero Nuevo"
    ],
    "wof:name":"Potrero Nuevo",
    "wof:placetype":"locality"
},
  "geometry": {"coordinates":[-102.19959,21.13923],"type":"Point"}
}