{
  "type": "Feature",
  "properties": {
    "gn:admin1_code":"2",
    "gn:admin2_code":"5.0",
    "gn:asciiname":"Solano",
    "gn:country_code":"MX",
    "gn:dem":296,
    "gn:feature_class":"P",
    "gn:feature_code":"PPL",
    "gn:name":"Solano",
    "gn:population":0,
    "gn:timezone":"America/Tijuana",
    "iso:country":"MX",
    "name:ceb_x_preferred":[
        "Solano"
    ],
    "name:deu_x_preferred":[
        "Solano"
    ],
    "name:fra_x_preferred":[
        "Solano"
    ],
    "name:ita_x_preferred":[
        "Solano"
    ],
    "name:jpn_x_preferred":[
        "\u30bd\u30e9\u30fc\u30ce"
    ],
    "name:nld_x_preferred":[
        "Solano"
    ],
    "name:pol_x_preferred":[
        "Solano"
    ],
    "name:rus_x_preferred":[
        "\u0421\u043e\u043b\u0430\u043d\u043e"
    ],
    "name:sco_x_preferred":[
        "Solano"
    ],
    "name:spa_x_preferred":[
        "Solano"
    ],
    "name:srp_x_preferred":[
        "\u0421\u043e\u043b\u0430\u043d\u043e"
    ],
    "name:swe_x_preferred":[
        "Solano"
    ],
    "name:vie_x_preferred":[
        "Solano"
    ],
    "name:war_x_preferred":[
        "Solano"
    ],
    "wof:name":"Solano",
    "wof:placetype":"locality"
},
  "geometry": {"coordinates":[-116.79286999999999,32.17192],"type":"Point"}
}