{
  "type": "Feature",
  "properties": {
    "gn:admin1_code":"30",
    "gn:admin2_code":"58.0",
    "gn:asciiname":"El Coyolito",
    "gn:country_code":"MX",
    "gn:dem":141,
    "gn:feature_class":"P",
    "gn:feature_code":"PPL",
    "gn:name":"El Coyolito",
    "gn:population":119,
    "gn:timezone":"America/Mexico_City",
    "iso:country":"MX",
    "name:spa_x_preferred":[
        "El Coyolito"
    ],
    "wof:name":"El Coyolito",
    "wof:placetype":"locality",
    "wof:population":119
},
  "geometry": {"coordinates":[-98.00722,21.04583],"type":"Point"}
}