{
  "type": "Feature",
  "properties": {
    "gn:admin1_code":"12",
    "gn:admin2_code":"1.0",
    "gn:asciiname":"Paso de Texca",
    "gn:country_code":"MX",
    "gn:dem":146,
    "gn:feature_class":"P",
    "gn:feature_code":"PPL",
    "gn:name":"Paso de Texca",
    "gn:population":0,
    "gn:timezone":"America/Mexico_City",
    "iso:country":"MX",
    "name:spa_x_preferred":[
        "Paso de Texca"
    ],
    "name:und_x_variant":[
        "Paso Texca"
    ],
    "wof:name":"Paso de Texca",
    "wof:placetype":"locality"
},
  "geometry": {"coordinates":[-99.81288000000001,16.98188],"type":"Point"}
}