{
  "type": "Feature",
  "properties": {
    "gn:admin1_code":"12",
    "gn:admin2_code":"28.0",
    "gn:asciiname":"Coatzingo",
    "gn:country_code":"MX",
    "gn:dem":1539,
    "gn:feature_class":"P",
    "gn:feature_code":"PPL",
    "gn:name":"Coatzingo",
    "gn:population":331,
    "gn:timezone":"America/Mexico_City",
    "iso:country":"MX",
    "name:ceb_x_preferred":[
        "Coatzingo"
    ],
    "name:epo_x_preferred":[
        "Coatzingo"
    ],
    "name:eus_x_preferred":[
        "Coatzingo"
    ],
    "name:srp_x_preferred":[
        "\u041e\u043f\u0448\u0442\u0438\u043d\u0430 \u041a\u043e\u0430\u0437\u0438\u043d\u0433\u043e"
    ],
    "name:swe_x_preferred":[
        "Coatzingo"
    ],
    "name:vie_x_preferred":[
        "Coatzingo"
    ],
    "wof:name":"Coatzingo",
    "wof:placetype":"locality",
    "wof:population":331
},
  "geometry": {"coordinates":[-99.14095,17.51338],"type":"Point"}
}