{
  "type": "Feature",
  "properties": {
    "gn:admin1_code":"20",
    "gn:admin2_code":"215.0",
    "gn:asciiname":"Barrio del Hua",
    "gn:country_code":"MX",
    "gn:dem":2096,
    "gn:feature_class":"P",
    "gn:feature_code":"PPL",
    "gn:name":"Barrio del Hua",
    "gn:population":8,
    "gn:timezone":"America/Mexico_City",
    "iso:country":"MX",
    "wof:name":"Barrio del Hua",
    "wof:placetype":"locality",
    "wof:population":8
},
  "geometry": {"coordinates":[-97.29111,17.45083],"type":"Point"}
}