{
  "type": "Feature",
  "properties": {
    "gn:admin1_code":"30",
    "gn:admin2_code":"189.0",
    "gn:asciiname":"San Jose el Grande",
    "gn:country_code":"MX",
    "gn:dem":70,
    "gn:feature_class":"P",
    "gn:feature_code":"PPL",
    "gn:name":"San Jos\u00e9 el Grande",
    "gn:population":0,
    "gn:timezone":"America/Mexico_City",
    "iso:country":"MX",
    "name:spa_x_preferred":[
        "San Jos\u00e9 el Grande"
    ],
    "name:spa_x_variant":[
        "San Jos\u00e9 El Grande"
    ],
    "wof:name":"San Jose el Grande",
    "wof:placetype":"locality"
},
  "geometry": {"coordinates":[-97.42164,20.76096],"type":"Point"}
}