{
  "type": "Feature",
  "properties": {
    "gn:admin1_code":"21",
    "gn:admin2_code":"10.0",
    "gn:asciiname":"Xochitzinga",
    "gn:country_code":"MX",
    "gn:dem":2388,
    "gn:feature_class":"P",
    "gn:feature_code":"PPL",
    "gn:name":"Xochitzinga",
    "gn:population":646,
    "gn:timezone":"America/Mexico_City",
    "iso:country":"MX",
    "wof:name":"Xochitzinga",
    "wof:placetype":"locality",
    "wof:population":646
},
  "geometry": {"coordinates":[-97.12860999999999,18.45028],"type":"Point"}
}