{
  "type": "Feature",
  "properties": {
    "gn:admin1_code":"23.0",
    "gn:asciiname":"Tazil",
    "gn:country_code":"MX",
    "gn:dem":25,
    "gn:feature_class":"P",
    "gn:feature_code":"PPL",
    "gn:name":"Tazil",
    "gn:population":0,
    "gn:timezone":"America/Cancun",
    "iso:country":"MX",
    "name:spa_x_preferred":[
        "Tazil"
    ],
    "wof:name":"Tazil",
    "wof:placetype":"locality"
},
  "geometry": {"coordinates":[-88.00444,20.22237],"type":"Point"}
}