{
  "type": "Feature",
  "properties": {
    "gn:admin1_code":"5",
    "gn:admin2_code":"51",
    "gn:asciiname":"Estacion Vieja",
    "gn:country_code":"MX",
    "gn:dem":38,
    "gn:feature_class":"P",
    "gn:feature_code":"PPL",
    "gn:name":"Estaci\u00f3n Vieja",
    "gn:population":10,
    "gn:timezone":"America/Mexico_City",
    "iso:country":"MX",
    "name:und_x_variant":[
        "Estaci\u00f3n Vieja"
    ],
    "wof:name":"Estacion Vieja",
    "wof:placetype":"locality",
    "wof:population":10
},
  "geometry": {"coordinates":[-92.88972,15.42889],"type":"Point"}
}