{
  "type": "Feature",
  "properties": {
    "gn:admin1_code":"14",
    "gn:admin2_code":"80.0",
    "gn:asciiname":"La Minita",
    "gn:country_code":"MX",
    "gn:dem":1212,
    "gn:feature_class":"P",
    "gn:feature_code":"PPL",
    "gn:name":"La Minita",
    "gn:population":7,
    "gn:timezone":"America/Mexico_City",
    "iso:country":"MX",
    "wof:name":"La Minita",
    "wof:placetype":"locality",
    "wof:population":7
},
  "geometry": {"coordinates":[-104.76306,20.795],"type":"Point"}
}