{
  "type": "Feature",
  "properties": {
    "gn:admin1_code":"28.0",
    "gn:admin2_code":"4.0",
    "gn:asciiname":"El Saltito",
    "gn:country_code":"MX",
    "gn:dem":253,
    "gn:feature_class":"P",
    "gn:feature_code":"PPL",
    "gn:name":"El Saltito",
    "gn:population":3,
    "gn:timezone":"America/Monterrey",
    "iso:country":"MX",
    "name:spa_x_preferred":[
        "El Saltito"
    ],
    "wof:name":"El Saltito",
    "wof:placetype":"locality",
    "wof:population":3
},
  "geometry": {"coordinates":[-99.19110999999999,22.70278],"type":"Point"}
}