{
  "type": "Feature",
  "properties": {
    "gn:admin1_code":"26",
    "gn:admin2_code":"30.0",
    "gn:asciiname":"La Loma (La Lomita)",
    "gn:country_code":"MX",
    "gn:dem":240,
    "gn:feature_class":"P",
    "gn:feature_code":"PPL",
    "gn:name":"La Loma (La Lomita)",
    "gn:population":6,
    "gn:timezone":"America/Hermosillo",
    "iso:country":"MX",
    "wof:name":"La Loma (La Lomita)",
    "wof:placetype":"locality",
    "wof:population":6
},
  "geometry": {"coordinates":[-110.83333,29.15667],"type":"Point"}
}