{
  "type": "Feature",
  "properties": {
    "gn:admin1_code":"5",
    "gn:admin2_code":"89.0",
    "gn:asciiname":"Soledad y Progreso",
    "gn:country_code":"MX",
    "gn:dem":1449,
    "gn:feature_class":"P",
    "gn:feature_code":"PPL",
    "gn:name":"Soledad y Progreso",
    "gn:population":0,
    "gn:timezone":"America/Mexico_City",
    "iso:country":"MX",
    "name:spa_x_preferred":[
        "Soledad y Progreso"
    ],
    "wof:name":"Soledad y Progreso",
    "wof:placetype":"locality"
},
  "geometry": {"coordinates":[-92.20990999999999,15.15884],"type":"Point"}
}