{
  "type": "Feature",
  "properties": {
    "gn:admin1_code":"10",
    "gn:admin2_code":"23",
    "gn:asciiname":"San Felipe",
    "gn:country_code":"MX",
    "gn:dem":2376,
    "gn:feature_class":"P",
    "gn:feature_code":"PPL",
    "gn:name":"San Felipe",
    "gn:population":10,
    "gn:timezone":"America/Monterrey",
    "iso:country":"MX",
    "wof:name":"San Felipe",
    "wof:placetype":"locality",
    "wof:population":10
},
  "geometry": {"coordinates":[-104.92057,23.39154],"type":"Point"}
}