{
  "type": "Feature",
  "properties": {
    "gn:admin1_code":"30",
    "gn:admin2_code":"81.0",
    "gn:asciiname":"Rancho del Cristo",
    "gn:country_code":"MX",
    "gn:dem":1348,
    "gn:feature_class":"P",
    "gn:feature_code":"PPL",
    "gn:name":"Rancho del Cristo",
    "gn:population":304,
    "gn:timezone":"America/Mexico_City",
    "iso:country":"MX",
    "wof:name":"Rancho del Cristo",
    "wof:placetype":"locality",
    "wof:population":304
},
  "geometry": {"coordinates":[-97.12972000000001,18.87444],"type":"Point"}
}