{
  "type": "Feature",
  "properties": {
    "gn:admin1_code":"16",
    "gn:admin2_code":"8",
    "gn:asciiname":"Las Gueinas",
    "gn:country_code":"MX",
    "gn:dem":539,
    "gn:feature_class":"P",
    "gn:feature_code":"PPL",
    "gn:name":"Las G\u00fcinas",
    "gn:population":46,
    "gn:timezone":"America/Mexico_City",
    "iso:country":"MX",
    "name:und_x_variant":[
        "Las G\u00fcinas"
    ],
    "wof:name":"Las Gueinas",
    "wof:placetype":"locality",
    "wof:population":46
},
  "geometry": {"coordinates":[-103.03361,18.31444],"type":"Point"}
}