{
  "type": "Feature",
  "properties": {
    "gn:admin1_code":"14",
    "gn:admin2_code":"104.0",
    "gn:asciiname":"Coloteca",
    "gn:country_code":"MX",
    "gn:dem":1947,
    "gn:feature_class":"P",
    "gn:feature_code":"PPL",
    "gn:name":"Coloteca",
    "gn:population":0,
    "gn:timezone":"America/Mexico_City",
    "iso:country":"MX",
    "name:spa_x_preferred":[
        "Coloteca"
    ],
    "wof:name":"Coloteca",
    "wof:placetype":"locality"
},
  "geometry": {"coordinates":[-103.56641,21.8904],"type":"Point"}
}