{
  "type": "Feature",
  "properties": {
    "gn:admin1_code":"7.0",
    "gn:admin2_code":"22.0",
    "gn:asciiname":"Colonia el Paraiso",
    "gn:country_code":"MX",
    "gn:dem":278,
    "gn:feature_class":"P",
    "gn:feature_code":"PPL",
    "gn:name":"Colonia el Para\u00edso",
    "gn:population":0,
    "gn:timezone":"America/Monterrey",
    "iso:country":"MX",
    "name:spa_x_preferred":[
        "Colonia el Para\u00edso"
    ],
    "wof:name":"Colonia el Paraiso",
    "wof:placetype":"locality"
},
  "geometry": {"coordinates":[-100.58392000000001,28.60934],"type":"Point"}
}