{
  "type": "Feature",
  "properties": {
    "gn:admin1_code":"3",
    "gn:admin2_code":"1.0",
    "gn:asciiname":"La Maquina",
    "gn:country_code":"MX",
    "gn:dem":340,
    "gn:feature_class":"P",
    "gn:feature_code":"PPL",
    "gn:name":"La M\u00e1quina",
    "gn:population":0,
    "gn:timezone":"America/Mazatlan",
    "iso:country":"MX",
    "name:spa_x_preferred":[
        "La M\u00e1quina"
    ],
    "wof:name":"La Maquina",
    "wof:placetype":"locality"
},
  "geometry": {"coordinates":[-111.15249,25.38822],"type":"Point"}
}