{
  "type": "Feature",
  "properties": {
    "gn:admin1_code":"4",
    "gn:admin2_code":"7",
    "gn:asciiname":"La Victoria",
    "gn:country_code":"MX",
    "gn:dem":2,
    "gn:feature_class":"P",
    "gn:feature_code":"PPL",
    "gn:name":"La Victoria",
    "gn:population":10,
    "gn:timezone":"America/Merida",
    "iso:country":"MX",
    "wof:name":"La Victoria",
    "wof:placetype":"locality",
    "wof:population":10
},
  "geometry": {"coordinates":[-91.89583,18.04833],"type":"Point"}
}