{
  "type": "Feature",
  "properties": {
    "gn:admin1_code":"26.0",
    "gn:admin2_code":"51.0",
    "gn:asciiname":"Las Tasajeras",
    "gn:country_code":"MX",
    "gn:dem":193,
    "gn:feature_class":"P",
    "gn:feature_code":"PPL",
    "gn:name":"Las Tasajeras",
    "gn:population":0,
    "gn:timezone":"America/Hermosillo",
    "iso:country":"MX",
    "name:spa_x_preferred":[
        "Las Tasajeras"
    ],
    "wof:name":"Las Tasajeras",
    "wof:placetype":"locality"
},
  "geometry": {"coordinates":[-109.63616,28.10796],"type":"Point"}
}