{
  "type": "Feature",
  "properties": {
    "gn:admin1_code":"13",
    "gn:admin2_code":"2.0",
    "gn:asciiname":"Ejido Santa Catarina",
    "gn:country_code":"MX",
    "gn:dem":2115,
    "gn:feature_class":"P",
    "gn:feature_code":"PPL",
    "gn:name":"Ejido Santa Catarina",
    "gn:population":77,
    "gn:timezone":"America/Mexico_City",
    "iso:country":"MX",
    "wof:name":"Ejido Santa Catarina",
    "wof:placetype":"locality",
    "wof:population":77
},
  "geometry": {"coordinates":[-98.11116,20.1274],"type":"Point"}
}