{
  "type": "Feature",
  "properties": {
    "gn:admin1_code":"30",
    "gn:admin2_code":"38.0",
    "gn:asciiname":"El Grande",
    "gn:country_code":"MX",
    "gn:dem":1075,
    "gn:feature_class":"P",
    "gn:feature_code":"PPL",
    "gn:name":"El Grande",
    "gn:population":955,
    "gn:timezone":"America/Mexico_City",
    "iso:country":"MX",
    "wof:name":"El Grande",
    "wof:placetype":"locality",
    "wof:population":955
},
  "geometry": {"coordinates":[-96.91582,19.43362],"type":"Point"}
}