{
  "type": "Feature",
  "properties": {
    "gn:admin1_code":"26",
    "gn:admin2_code":"4.0",
    "gn:asciiname":"Rancho Maria Dolores",
    "gn:country_code":"MX",
    "gn:dem":364,
    "gn:feature_class":"P",
    "gn:feature_code":"PPL",
    "gn:name":"Rancho Mar\u00eda Dolores",
    "gn:population":0,
    "gn:timezone":"America/Hermosillo",
    "iso:country":"MX",
    "wof:name":"Rancho Maria Dolores",
    "wof:placetype":"locality"
},
  "geometry": {"coordinates":[-111.90000000000001,30.63333],"type":"Point"}
}