{
  "type": "Feature",
  "properties": {
    "gn:admin1_code":"30",
    "gn:admin2_code":"152.0",
    "gn:asciiname":"El Caiman",
    "gn:country_code":"MX",
    "gn:dem":21,
    "gn:feature_class":"P",
    "gn:feature_code":"PPL",
    "gn:name":"El Caim\u00e1n",
    "gn:population":16,
    "gn:timezone":"America/Mexico_City",
    "iso:country":"MX",
    "wof:name":"El Caiman",
    "wof:placetype":"locality",
    "wof:population":16
},
  "geometry": {"coordinates":[-97.87944,21.91889],"type":"Point"}
}