{
  "type": "Feature",
  "properties": {
    "gn:admin1_code":"12",
    "gn:admin2_code":"12.0",
    "gn:asciiname":"Tonala",
    "gn:country_code":"MX",
    "gn:dem":327,
    "gn:feature_class":"P",
    "gn:feature_code":"PPL",
    "gn:name":"Tonal\u00e1",
    "gn:population":2176,
    "gn:timezone":"America/Mexico_City",
    "iso:country":"MX",
    "name:und_x_variant":[
        "Tonal\u00e1"
    ],
    "wof:name":"Tonala",
    "wof:placetype":"locality",
    "wof:population":2176
},
  "geometry": {"coordinates":[-99.05444,16.86167],"type":"Point"}
}