{
  "type": "Feature",
  "properties": {
    "gn:admin1_code":"28.0",
    "gn:admin2_code":"3.0",
    "gn:asciiname":"Las Cuatas",
    "gn:country_code":"MX",
    "gn:dem":51,
    "gn:feature_class":"P",
    "gn:feature_code":"PPL",
    "gn:name":"Las Cuatas",
    "gn:population":0,
    "gn:timezone":"America/Monterrey",
    "iso:country":"MX",
    "name:spa_x_preferred":[
        "Las Cuatas"
    ],
    "name:spa_x_variant":[
        "Ampliaci\u00f3n el Pl\u00e1tano"
    ],
    "wof:name":"Las Cuatas",
    "wof:placetype":"locality"
},
  "geometry": {"coordinates":[-98.17646000000001,22.67917000000001],"type":"Point"}
}