{
  "type": "Feature",
  "properties": {
    "gn:admin1_code":"5",
    "gn:admin2_code":"104.0",
    "gn:asciiname":"Doctor Manuel Velazco Suarez",
    "gn:country_code":"MX",
    "gn:dem":693,
    "gn:feature_class":"P",
    "gn:feature_code":"PPL",
    "gn:name":"Doctor Manuel Velazco Su\u00e1rez",
    "gn:population":0,
    "gn:timezone":"America/Mexico_City",
    "iso:country":"MX",
    "name:spa_x_preferred":[
        "Doctor Manuel Velazco Su\u00e1rez"
    ],
    "name:und_x_variant":[
        "Manuel Velazco Su\u00e1rez"
    ],
    "wof:name":"Doctor Manuel Velazco Suarez",
    "wof:placetype":"locality"
},
  "geometry": {"coordinates":[-92.22763999999999,16.13134],"type":"Point"}
}