{
  "type": "Feature",
  "properties": {
    "gn:admin1_code":"32",
    "gn:admin2_code":"46.0",
    "gn:asciiname":"El Ojo de Agua",
    "gn:country_code":"MX",
    "gn:dem":2047,
    "gn:feature_class":"P",
    "gn:feature_code":"PPL",
    "gn:name":"El Ojo de Agua",
    "gn:population":0,
    "gn:timezone":"America/Mexico_City",
    "iso:country":"MX",
    "name:spa_x_preferred":[
        "El Ojo de Agua"
    ],
    "wof:name":"El Ojo de Agua",
    "wof:placetype":"locality"
},
  "geometry": {"coordinates":[-103.24075000000001,22.46775],"type":"Point"}
}