{
  "type": "Feature",
  "properties": {
    "gn:admin1_code":"11.0",
    "gn:admin2_code":"3.0",
    "gn:asciiname":"Palo Colorado",
    "gn:country_code":"MX",
    "gn:dem":2005,
    "gn:feature_class":"P",
    "gn:feature_code":"PPL",
    "gn:name":"Palo Colorado",
    "gn:population":1172,
    "gn:timezone":"America/Mexico_City",
    "iso:country":"MX",
    "name:spa_x_preferred":[
        "Palo Colorado"
    ],
    "wof:name":"Palo Colorado",
    "wof:placetype":"locality",
    "wof:population":1172
},
  "geometry": {"coordinates":[-100.72917,21.00836],"type":"Point"}
}