{
  "type": "Feature",
  "properties": {
    "gn:admin1_code":"14",
    "gn:admin2_code":"28.0",
    "gn:asciiname":"Cuescomata",
    "gn:country_code":"MX",
    "gn:dem":1596,
    "gn:feature_class":"P",
    "gn:feature_code":"PPL",
    "gn:name":"Cuescomata",
    "gn:population":9,
    "gn:timezone":"America/Mexico_City",
    "iso:country":"MX",
    "wof:name":"Cuescomata",
    "wof:placetype":"locality",
    "wof:population":9
},
  "geometry": {"coordinates":[-104.46472,20.13667],"type":"Point"}
}