{
  "type": "Feature",
  "properties": {
    "gn:admin1_code":"29",
    "gn:admin2_code":"13.0",
    "gn:asciiname":"Colonia el Valle",
    "gn:country_code":"MX",
    "gn:dem":2444,
    "gn:feature_class":"P",
    "gn:feature_code":"PPL",
    "gn:name":"Colonia el Valle",
    "gn:population":710,
    "gn:timezone":"America/Mexico_City",
    "iso:country":"MX",
    "wof:name":"Colonia el Valle",
    "wof:placetype":"locality",
    "wof:population":710
},
  "geometry": {"coordinates":[-97.86861,19.35833],"type":"Point"}
}