{
  "type": "Feature",
  "properties": {
    "gn:admin1_code":"21",
    "gn:admin2_code":"53.0",
    "gn:asciiname":"La Campana",
    "gn:country_code":"MX",
    "gn:dem":2400,
    "gn:feature_class":"P",
    "gn:feature_code":"PPL",
    "gn:name":"La Campana",
    "gn:population":0,
    "gn:timezone":"America/Mexico_City",
    "iso:country":"MX",
    "name:spa_x_preferred":[
        "La Campana"
    ],
    "wof:name":"La Campana",
    "wof:placetype":"locality"
},
  "geometry": {"coordinates":[-98.13205000000001,19.77372],"type":"Point"}
}