{
  "type": "Feature",
  "properties": {
    "gn:admin1_code":"21",
    "gn:admin2_code":"53.0",
    "gn:asciiname":"La Campana",
    "gn:country_code":"MX",
    "gn:dem":2400,
    "gn:feature_class":"P",
    "gn:feature_code":"PPL",
    "gn:name":"La Campana",
    "gn:population":0,
    "gn:timezone":"America/Mexico_City",
    "iso:country":"MX",
    "name:arg_x_preferred":[
        "La Campana"
    ],
    "name:ast_x_preferred":[
        "La Campana"
    ],
    "name:azb_x_preferred":[
        "\u0644\u0627 \u06a9\u0627\u0645\u067e\u0627\u0646\u0627"
    ],
    "name:cat_x_preferred":[
        "La Campana"
    ],
    "name:ceb_x_preferred":[
        "La Campana"
    ],
    "name:deu_x_preferred":[
        "La Campana"
    ],
    "name:diq_x_preferred":[
        "La Campana"
    ],
    "name:epo_x_preferred":[
        "La Campana"
    ],
    "name:eus_x_preferred":[
        "La Campana"
    ],
    "name:fas_x_preferred":[
        "\u0644\u0627 \u06a9\u0627\u0645\u067e\u0627\u0646\u0627"
    ],
    "name:fra_x_preferred":[
        "La Campana"
    ],
    "name:glg_x_preferred":[
        "La Campana"
    ],
    "name:hat_x_preferred":[
        "La Campana"
    ],
    "name:hun_x_preferred":[
        "La Campana"
    ],
    "name:hye_x_preferred":[
        "\u053c\u0561 \u053f\u0561\u0574\u057a\u0561\u0576\u0561"
    ],
    "name:ind_x_preferred":[
        "La Campana"
    ],
    "name:ita_x_preferred":[
        "La Campana"
    ],
    "name:kaz_x_preferred":[
        "\u041b\u0430-\u041a\u0430\u043c\u043f\u0430\u043d\u0430"
    ],
    "name:msa_x_preferred":[
        "La Campana"
    ],
    "name:nld_x_preferred":[
        "La Campana"
    ],
    "name:oci_x_preferred":[
        "La Campana"
    ],
    "name:pol_x_preferred":[
        "La Campana"
    ],
    "name:por_x_preferred":[
        "La Campana"
    ],
    "name:ron_x_preferred":[
        "La Campana"
    ],
    "name:rus_x_preferred":[
        "\u041b\u0430-\u041a\u0430\u043c\u043f\u0430\u043d\u0430"
    ],
    "name:spa_x_preferred":[
        "La Campana"
    ],
    "name:tur_x_preferred":[
        "La Campana"
    ],
    "name:ukr_x_preferred":[
        "\u041b\u0430-\u041a\u0430\u043c\u043f\u0430\u043d\u0430"
    ],
    "name:uzb_x_preferred":[
        "La Campana"
    ],
    "name:vie_x_preferred":[
        "La Campana"
    ],
    "name:war_x_preferred":[
        "La Campana"
    ],
    "name:zho_x_preferred":[
        "\u62c9\u574e\u5e15\u7eb3"
    ],
    "wof:name":"La Campana",
    "wof:placetype":"locality"
},
  "geometry": {"coordinates":[-98.13205000000001,19.77372],"type":"Point"}
}