{
  "type": "Feature",
  "properties": {
    "gn:admin1_code":"25",
    "gn:admin2_code":"6.0",
    "gn:asciiname":"Peninsula de Villamoros",
    "gn:country_code":"MX",
    "gn:dem":3,
    "gn:feature_class":"P",
    "gn:feature_code":"PPL",
    "gn:name":"Pen\u00ednsula de Villamoros",
    "gn:population":818,
    "gn:timezone":"America/Mazatlan",
    "iso:country":"MX",
    "wof:name":"Peninsula de Villamoros",
    "wof:placetype":"locality",
    "wof:population":818
},
  "geometry": {"coordinates":[-107.22278,24.16667],"type":"Point"}
}