{
  "type": "Feature",
  "properties": {
    "gn:admin1_code":"5",
    "gn:admin2_code":"12.0",
    "gn:asciiname":"Tuxtlan",
    "gn:country_code":"MX",
    "gn:dem":769,
    "gn:feature_class":"P",
    "gn:feature_code":"PPL",
    "gn:name":"Tuxtl\u00e1n",
    "gn:population":6,
    "gn:timezone":"America/Mexico_City",
    "iso:country":"MX",
    "name:und_x_variant":[
        "Tuxtl\u00e1n"
    ],
    "wof:name":"Tuxtlan",
    "wof:placetype":"locality",
    "wof:population":6
},
  "geometry": {"coordinates":[-93.22472,16.77944],"type":"Point"}
}