{
  "type": "Feature",
  "properties": {
    "gn:admin1_code":"2",
    "gn:admin2_code":"2",
    "gn:asciiname":"Familia Galvan Diaz",
    "gn:country_code":"MX",
    "gn:dem":5,
    "gn:feature_class":"P",
    "gn:feature_code":"PPL",
    "gn:name":"Familia Galv\u00e1n D\u00edaz",
    "gn:population":15,
    "gn:timezone":"America/Tijuana",
    "iso:country":"MX",
    "name:und_x_variant":[
        "Familia Galv\u00e1n D\u00edaz"
    ],
    "wof:name":"Familia Galvan Diaz",
    "wof:placetype":"locality",
    "wof:population":15
},
  "geometry": {"coordinates":[-115.52056,32.5975],"type":"Point"}
}