{
  "type": "Feature",
  "properties": {
    "gn:admin1_code":"13",
    "gn:admin2_code":"8.0",
    "gn:asciiname":"Las Ventas",
    "gn:country_code":"MX",
    "gn:dem":2475,
    "gn:feature_class":"P",
    "gn:feature_code":"PPL",
    "gn:name":"Las Ventas",
    "gn:population":76,
    "gn:timezone":"America/Mexico_City",
    "iso:country":"MX",
    "name:ara_x_preferred":[
        "\u0644\u0627\u0633 \u0641\u064a\u0646\u062a\u0627\u0633"
    ],
    "name:arz_x_preferred":[
        "\u0644\u0627\u0633 \u0641\u064a\u0646\u062a\u0627\u0633"
    ],
    "name:cat_x_preferred":[
        "Las Ventas"
    ],
    "name:deu_x_preferred":[
        "Las Ventas"
    ],
    "name:ell_x_preferred":[
        "\u039b\u03b1\u03c2 \u0392\u03ad\u03bd\u03c4\u03b1\u03c2"
    ],
    "name:epo_x_preferred":[
        "Toreejo Las Ventas"
    ],
    "name:eus_x_preferred":[
        "Las Ventas"
    ],
    "name:fin_x_preferred":[
        "Las Ventas"
    ],
    "name:fra_x_preferred":[
        "Las Ventas"
    ],
    "name:glg_x_preferred":[
        "Las Ventas"
    ],
    "name:heb_x_preferred":[
        "\u05dc\u05e1 \u05d5\u05e0\u05d8\u05d0\u05e1"
    ],
    "name:hun_x_preferred":[
        "Las Ventas bikaviadal-ar\u00e9na"
    ],
    "name:hye_x_preferred":[
        "\u053c\u0561\u057d-\u054e\u0565\u0576\u057f\u0561\u057d\u056b \u0574\u0580\u0581\u0561\u057d\u057a\u0561\u0580\u0565\u0566"
    ],
    "name:ind_x_preferred":[
        "Las Ventas"
    ],
    "name:ita_x_preferred":[
        "Las Ventas"
    ],
    "name:jpn_x_preferred":[
        "\u30e9\u30b9\u30fb\u30d9\u30f3\u30bf\u30b9\u95d8\u725b\u5834"
    ],
    "name:kor_x_preferred":[
        "\ub77c\uc2a4 \ubca4\ud0c0\uc2a4"
    ],
    "name:nld_x_preferred":[
        "Las Ventas"
    ],
    "name:pol_x_preferred":[
        "Las Ventas"
    ],
    "name:por_x_preferred":[
        "Las Ventas"
    ],
    "name:rus_x_preferred":[
        "\u0410\u0440\u0435\u043d\u0430 \u041b\u0430\u0441-\u0412\u0435\u043d\u0442\u0430\u0441"
    ],
    "name:slv_x_preferred":[
        "Las Ventas"
    ],
    "name:spa_x_preferred":[
        "Las Ventas"
    ],
    "name:swe_x_preferred":[
        "Las Ventas"
    ],
    "name:zho_x_preferred":[
        "\u62c9\u65af\u73ed\u5854\u65af\u6597\u725b\u573a"
    ],
    "wof:name":"Las Ventas",
    "wof:placetype":"locality",
    "wof:population":76
},
  "geometry": {"coordinates":[-98.49778000000001,19.72],"type":"Point"}
}