{
  "type": "Feature",
  "properties": {
    "gn:admin1_code":"13",
    "gn:admin2_code":"8.0",
    "gn:asciiname":"Las Ventas",
    "gn:country_code":"MX",
    "gn:dem":2475,
    "gn:feature_class":"P",
    "gn:feature_code":"PPL",
    "gn:name":"Las Ventas",
    "gn:population":76,
    "gn:timezone":"America/Mexico_City",
    "iso:country":"MX",
    "wof:name":"Las Ventas",
    "wof:placetype":"locality",
    "wof:population":76
},
  "geometry": {"coordinates":[-98.49778000000001,19.72],"type":"Point"}
}