{
  "type": "Feature",
  "properties": {
    "gn:admin1_code":"11.0",
    "gn:admin2_code":"14.0",
    "gn:asciiname":"Los Arcos",
    "gn:country_code":"MX",
    "gn:dem":1920,
    "gn:feature_class":"P",
    "gn:feature_code":"PPL",
    "gn:name":"Los Arcos",
    "gn:population":0,
    "gn:timezone":"America/Mexico_City",
    "iso:country":"MX",
    "name:spa_x_preferred":[
        "Los Arcos"
    ],
    "wof:name":"Los Arcos",
    "wof:placetype":"locality"
},
  "geometry": {"coordinates":[-100.94156,21.23153],"type":"Point"}
}