{
  "type": "Feature",
  "properties": {
    "gn:admin1_code":"24",
    "gn:admin2_code":"25.0",
    "gn:asciiname":"Rancho la Esperanza",
    "gn:country_code":"MX",
    "gn:dem":2021,
    "gn:feature_class":"P",
    "gn:feature_code":"PPL",
    "gn:name":"Rancho la Esperanza",
    "gn:population":9,
    "gn:timezone":"America/Mexico_City",
    "iso:country":"MX",
    "wof:name":"Rancho la Esperanza",
    "wof:placetype":"locality",
    "wof:population":9
},
  "geometry": {"coordinates":[-101.55972,23.07444],"type":"Point"}
}