{
  "type": "Feature",
  "properties": {
    "gn:admin1_code":"20.0",
    "gn:asciiname":"Tonalan",
    "gn:country_code":"MX",
    "gn:dem":1493,
    "gn:feature_class":"P",
    "gn:feature_code":"PPL",
    "gn:name":"Tonal\u00e1n",
    "gn:population":0,
    "gn:timezone":"America/Mexico_City",
    "iso:country":"MX",
    "name:spa_x_preferred":[
        "Tonal\u00e1n"
    ],
    "wof:name":"Tonalan",
    "wof:placetype":"locality"
},
  "geometry": {"coordinates":[-97.08727,17.67701],"type":"Point"}
}