{
  "type": "Feature",
  "properties": {
    "gn:admin1_code":"31",
    "gn:admin2_code":"17.0",
    "gn:asciiname":"X-Kopchen",
    "gn:country_code":"MX",
    "gn:dem":34,
    "gn:feature_class":"P",
    "gn:feature_code":"PPL",
    "gn:name":"X-Kopch\u00e9n",
    "gn:population":5,
    "gn:timezone":"America/Merida",
    "iso:country":"MX",
    "name:und_x_variant":[
        "X-Kopch\u00e9n"
    ],
    "wof:name":"X-Kopchen",
    "wof:placetype":"locality",
    "wof:population":5
},
  "geometry": {"coordinates":[-88.50583,20.60139],"type":"Point"}
}