{
  "type": "Feature",
  "properties": {
    "gn:admin1_code":"5",
    "gn:admin2_code":"40.0",
    "gn:asciiname":"Canton las Delicias",
    "gn:country_code":"MX",
    "gn:dem":28,
    "gn:feature_class":"P",
    "gn:feature_code":"PPL",
    "gn:name":"Cant\u00f3n las Delicias",
    "gn:population":0,
    "gn:timezone":"America/Mexico_City",
    "iso:country":"MX",
    "name:spa_x_preferred":[
        "Cant\u00f3n las Delicias"
    ],
    "name:und_x_variant":[
        "Las Delicias"
    ],
    "wof:name":"Canton las Delicias",
    "wof:placetype":"locality"
},
  "geometry": {"coordinates":[-92.50002000000001,15.10245],"type":"Point"}
}