{
  "type": "Feature",
  "properties": {
    "gn:admin1_code":"27",
    "gn:admin2_code":"12.0",
    "gn:asciiname":"Buena Vista (Apasco)",
    "gn:country_code":"MX",
    "gn:dem":27,
    "gn:feature_class":"P",
    "gn:feature_code":"PPL",
    "gn:name":"Buena Vista (Apasco)",
    "gn:population":1638,
    "gn:timezone":"America/Mexico_City",
    "iso:country":"MX",
    "wof:name":"Buena Vista (Apasco)",
    "wof:placetype":"locality",
    "wof:population":1638
},
  "geometry": {"coordinates":[-92.44389,17.65556],"type":"Point"}
}