{
  "type": "Feature",
  "properties": {
    "gn:admin1_code":"20",
    "gn:admin2_code":"178",
    "gn:asciiname":"El Molinito",
    "gn:country_code":"MX",
    "gn:dem":1825,
    "gn:feature_class":"P",
    "gn:feature_code":"PPL",
    "gn:name":"El Molinito",
    "gn:population":29,
    "gn:timezone":"America/Mexico_City",
    "iso:country":"MX",
    "wof:name":"El Molinito",
    "wof:placetype":"locality",
    "wof:population":29
},
  "geometry": {"coordinates":[-96.77361000000001,17.23556],"type":"Point"}
}