{
  "type": "Feature",
  "properties": {
    "gn:admin1_code":"12",
    "gn:admin2_code":"29.0",
    "gn:asciiname":"San Cristobal",
    "gn:country_code":"MX",
    "gn:dem":882,
    "gn:feature_class":"P",
    "gn:feature_code":"PPL",
    "gn:name":"San Crist\u00f3bal",
    "gn:population":0,
    "gn:timezone":"America/Mexico_City",
    "iso:country":"MX",
    "name:spa_x_preferred":[
        "San Crist\u00f3bal"
    ],
    "wof:name":"San Cristobal",
    "wof:placetype":"locality"
},
  "geometry": {"coordinates":[-99.93946,17.27575],"type":"Point"}
}