{
  "type": "Feature",
  "properties": {
    "gn:admin1_code":"10",
    "gn:admin2_code":"14",
    "gn:asciiname":"La Mesa de los Aguacates",
    "gn:country_code":"MX",
    "gn:dem":2063,
    "gn:feature_class":"P",
    "gn:feature_code":"PPL",
    "gn:name":"La Mesa de los Aguacates",
    "gn:population":20,
    "gn:timezone":"America/Monterrey",
    "iso:country":"MX",
    "wof:name":"La Mesa de los Aguacates",
    "wof:placetype":"locality",
    "wof:population":20
},
  "geometry": {"coordinates":[-104.59191,22.92531],"type":"Point"}
}