{
  "type": "Feature",
  "properties": {
    "gn:admin1_code":"6",
    "gn:admin2_code":"38.0",
    "gn:asciiname":"El Dorado (Pena Blanca)",
    "gn:country_code":"MX",
    "gn:dem":1077,
    "gn:feature_class":"P",
    "gn:feature_code":"PPL",
    "gn:name":"El Dorado (Pe\u00f1a Blanca)",
    "gn:population":4,
    "gn:timezone":"America/Chihuahua",
    "iso:country":"MX",
    "name:und_x_variant":[
        "El Dorado (Pe\u00f1a Blanca)"
    ],
    "wof:name":"El Dorado (Pena Blanca)",
    "wof:placetype":"locality",
    "wof:population":4
},
  "geometry": {"coordinates":[-105.42498000000001,28.62292],"type":"Point"}
}