{
  "type": "Feature",
  "properties": {
    "gn:admin1_code":"26",
    "gn:admin2_code":"33.0",
    "gn:asciiname":"Mayobampo",
    "gn:country_code":"MX",
    "gn:dem":90,
    "gn:feature_class":"P",
    "gn:feature_code":"PPL",
    "gn:name":"Mayobampo",
    "gn:population":0,
    "gn:timezone":"America/Hermosillo",
    "iso:country":"MX",
    "name:spa_x_preferred":[
        "Mayobampo"
    ],
    "wof:name":"Mayobampo",
    "wof:placetype":"locality"
},
  "geometry": {"coordinates":[-109.12931,26.62565],"type":"Point"}
}