{
  "type": "Feature",
  "properties": {
    "gn:admin1_code":"6.0",
    "gn:admin2_code":"30.0",
    "gn:asciiname":"El Pinabete",
    "gn:country_code":"MX",
    "gn:dem":2094,
    "gn:feature_class":"P",
    "gn:feature_code":"PPL",
    "gn:name":"El Pinabete",
    "gn:population":0,
    "gn:timezone":"America/Chihuahua",
    "iso:country":"MX",
    "name:spa_x_preferred":[
        "El Pinabete"
    ],
    "wof:name":"El Pinabete",
    "wof:placetype":"locality"
},
  "geometry": {"coordinates":[-108.09742,27.58599],"type":"Point"}
}