{
  "type": "Feature",
  "properties": {
    "gn:admin1_code":"11.0",
    "gn:admin2_code":"30.0",
    "gn:asciiname":"Matamoros",
    "gn:country_code":"MX",
    "gn:dem":1954,
    "gn:feature_class":"P",
    "gn:feature_code":"PPL",
    "gn:name":"Matamoros",
    "gn:population":0,
    "gn:timezone":"America/Mexico_City",
    "iso:country":"MX",
    "name:bre_x_preferred":[
        "Matamoros"
    ],
    "name:ceb_x_preferred":[
        "Matamoros"
    ],
    "name:deu_x_preferred":[
        "Matamoros"
    ],
    "name:epo_x_preferred":[
        "Matamoros"
    ],
    "name:fra_x_preferred":[
        "Matamoros"
    ],
    "name:ita_x_preferred":[
        "Matamoros"
    ],
    "name:jpn_x_preferred":[
        "\u30de\u30bf\u30e2\u30ed\u30b9"
    ],
    "name:nld_x_preferred":[
        "Matamoros"
    ],
    "name:nor_x_preferred":[
        "Matamoros"
    ],
    "name:por_x_preferred":[
        "Matamoros"
    ],
    "name:rus_x_preferred":[
        "\u041c\u0430\u0442\u0430\u043c\u043e\u0440\u043e\u0441"
    ],
    "name:sco_x_preferred":[
        "Matamoros"
    ],
    "name:spa_x_preferred":[
        "Matamoros"
    ],
    "name:srp_x_preferred":[
        "\u041c\u0430\u0442\u0430\u043c\u043e\u0440\u043e\u0441"
    ],
    "name:swe_x_preferred":[
        "Matamoros"
    ],
    "wof:name":"Matamoros",
    "wof:placetype":"locality"
},
  "geometry": {"coordinates":[-101.05403,21.51705],"type":"Point"}
}