{
  "type": "Feature",
  "properties": {
    "gn:admin1_code":"11.0",
    "gn:admin2_code":"30.0",
    "gn:asciiname":"Matamoros",
    "gn:country_code":"MX",
    "gn:dem":1954,
    "gn:feature_class":"P",
    "gn:feature_code":"PPL",
    "gn:name":"Matamoros",
    "gn:population":0,
    "gn:timezone":"America/Mexico_City",
    "iso:country":"MX",
    "name:spa_x_preferred":[
        "Matamoros"
    ],
    "wof:name":"Matamoros",
    "wof:placetype":"locality"
},
  "geometry": {"coordinates":[-101.05403,21.51705],"type":"Point"}
}