{
  "type": "Feature",
  "properties": {
    "gn:admin1_code":"6",
    "gn:admin2_code":"29.0",
    "gn:asciiname":"Aserradero las Delicias",
    "gn:country_code":"MX",
    "gn:dem":2540,
    "gn:feature_class":"P",
    "gn:feature_code":"PPL",
    "gn:name":"Aserradero las Delicias",
    "gn:population":278,
    "gn:timezone":"America/Chihuahua",
    "iso:country":"MX",
    "wof:name":"Aserradero las Delicias",
    "wof:placetype":"locality",
    "wof:population":278
},
  "geometry": {"coordinates":[-106.6447,25.79084],"type":"Point"}
}