{
  "type": "Feature",
  "properties": {
    "gn:admin1_code":"7",
    "gn:admin2_code":"20.0",
    "gn:asciiname":"Roberto Maldonado",
    "gn:country_code":"MX",
    "gn:dem":441,
    "gn:feature_class":"P",
    "gn:feature_code":"PPL",
    "gn:name":"Roberto Maldonado",
    "gn:population":6,
    "gn:timezone":"America/Monterrey",
    "iso:country":"MX",
    "wof:name":"Roberto Maldonado",
    "wof:placetype":"locality",
    "wof:population":6
},
  "geometry": {"coordinates":[-101.5326,27.94276],"type":"Point"}
}