{
  "type": "Feature",
  "properties": {
    "gn:admin1_code":"25",
    "gn:admin2_code":"12.0",
    "gn:asciiname":"Los Pozos",
    "gn:country_code":"MX",
    "gn:dem":12,
    "gn:feature_class":"P",
    "gn:feature_code":"PPL",
    "gn:name":"Los Pozos",
    "gn:population":102,
    "gn:timezone":"America/Mazatlan",
    "iso:country":"MX",
    "wof:name":"Los Pozos",
    "wof:placetype":"locality",
    "wof:population":102
},
  "geometry": {"coordinates":[-106.24261,23.19179],"type":"Point"}
}