{
  "type": "Feature",
  "properties": {
    "gn:admin1_code":"21",
    "gn:admin2_code":"40",
    "gn:asciiname":"Zacatla",
    "gn:country_code":"MX",
    "gn:dem":2165,
    "gn:feature_class":"P",
    "gn:feature_code":"PPL",
    "gn:name":"Zacatla",
    "gn:population":12,
    "gn:timezone":"America/Mexico_City",
    "iso:country":"MX",
    "wof:name":"Zacatla",
    "wof:placetype":"locality",
    "wof:population":12
},
  "geometry": {"coordinates":[-97.99912,18.95653],"type":"Point"}
}