{
  "type": "Feature",
  "properties": {
    "gn:admin1_code":"24",
    "gn:admin2_code":"22.0",
    "gn:asciiname":"El Sureno",
    "gn:country_code":"MX",
    "gn:dem":1637,
    "gn:feature_class":"P",
    "gn:feature_code":"PPL",
    "gn:name":"El Sure\u00f1o",
    "gn:population":8,
    "gn:timezone":"America/Mexico_City",
    "iso:country":"MX",
    "name:und_x_variant":[
        "El Sure\u00f1o"
    ],
    "wof:name":"El Sureno",
    "wof:placetype":"locality",
    "wof:population":8
},
  "geometry": {"coordinates":[-100.95556000000001,22.72278],"type":"Point"}
}