{
  "type": "Feature",
  "properties": {
    "gn:admin1_code":"12",
    "gn:admin2_code":"11.0",
    "gn:asciiname":"Santiago de la Union",
    "gn:country_code":"MX",
    "gn:dem":832,
    "gn:feature_class":"P",
    "gn:feature_code":"PPL",
    "gn:name":"Santiago de la Uni\u00f3n",
    "gn:population":0,
    "gn:timezone":"America/Mexico_City",
    "iso:country":"MX",
    "name:spa_x_preferred":[
        "Santiago de la Uni\u00f3n"
    ],
    "name:und_x_variant":[
        "Santiago"
    ],
    "wof:name":"Santiago de la Union",
    "wof:placetype":"locality"
},
  "geometry": {"coordinates":[-100.34081,17.24855],"type":"Point"}
}