{
  "type": "Feature",
  "properties": {
    "gn:admin1_code":"10",
    "gn:admin2_code":"4.0",
    "gn:asciiname":"Jeronimo",
    "gn:country_code":"MX",
    "gn:dem":1994,
    "gn:feature_class":"P",
    "gn:feature_code":"PPL",
    "gn:name":"Jer\u00f3nimo",
    "gn:population":0,
    "gn:timezone":"America/Monterrey",
    "iso:country":"MX",
    "name:spa_x_preferred":[
        "Jer\u00f3nimo"
    ],
    "wof:name":"Jeronimo",
    "wof:placetype":"locality"
},
  "geometry": {"coordinates":[-103.82277000000001,24.64182000000001],"type":"Point"}
}