{
  "type": "Feature",
  "properties": {
    "gn:admin1_code":"4",
    "gn:admin2_code":"2.0",
    "gn:asciiname":"San Miguel Allende",
    "gn:country_code":"MX",
    "gn:dem":96,
    "gn:feature_class":"P",
    "gn:feature_code":"PPL",
    "gn:name":"San Miguel Allende",
    "gn:population":231,
    "gn:timezone":"America/Merida",
    "iso:country":"MX",
    "wof:name":"San Miguel Allende",
    "wof:placetype":"locality",
    "wof:population":231
},
  "geometry": {"coordinates":[-89.99556,19.46278],"type":"Point"}
}