{
  "type": "Feature",
  "properties": {
    "gn:admin1_code":"10",
    "gn:admin2_code":"39.0",
    "gn:asciiname":"Once de Marzo (Trincheras)",
    "gn:country_code":"MX",
    "gn:dem":2029,
    "gn:feature_class":"P",
    "gn:feature_code":"PPL",
    "gn:name":"Once de Marzo (Trincheras)",
    "gn:population":217,
    "gn:timezone":"America/Monterrey",
    "iso:country":"MX",
    "wof:name":"Once de Marzo (Trincheras)",
    "wof:placetype":"locality",
    "wof:population":217
},
  "geometry": {"coordinates":[-104.81222,24.90972],"type":"Point"}
}