{
  "type": "Feature",
  "properties": {
    "gn:admin1_code":"13",
    "gn:admin2_code":"29.0",
    "gn:asciiname":"P. P. Xindho",
    "gn:country_code":"MX",
    "gn:dem":2102,
    "gn:feature_class":"P",
    "gn:feature_code":"PPL",
    "gn:name":"P. P. Xindho",
    "gn:population":0,
    "gn:timezone":"America/Mexico_City",
    "iso:country":"MX",
    "name:spa_x_preferred":[
        "P. P. Xindho"
    ],
    "name:und_x_variant":[
        "Hindho",
        "Xhind\u00f3",
        "Xindh\u00f3"
    ],
    "wof:name":"P. P. Xindho",
    "wof:placetype":"locality"
},
  "geometry": {"coordinates":[-99.57998000000001,20.45519],"type":"Point"}
}