{
  "type": "Feature",
  "properties": {
    "gn:admin1_code":"31",
    "gn:admin2_code":"32.0",
    "gn:asciiname":"Mahaycab",
    "gn:country_code":"MX",
    "gn:dem":18,
    "gn:feature_class":"P",
    "gn:feature_code":"PPL",
    "gn:name":"Mahaycab",
    "gn:population":0,
    "gn:timezone":"America/Merida",
    "iso:country":"MX",
    "wof:name":"Mahaycab",
    "wof:placetype":"locality"
},
  "geometry": {"coordinates":[-88.38034,21.00734],"type":"Point"}
}