{
  "type": "Feature",
  "properties": {
    "gn:admin1_code":"30",
    "gn:admin2_code":"85.0",
    "gn:asciiname":"Rincon de Tecolayo",
    "gn:country_code":"MX",
    "gn:dem":836,
    "gn:feature_class":"P",
    "gn:feature_code":"PPL",
    "gn:name":"Rinc\u00f3n de Tecolayo",
    "gn:population":195,
    "gn:timezone":"America/Mexico_City",
    "iso:country":"MX",
    "name:und_x_variant":[
        "Rinc\u00f3n de Tecolayo"
    ],
    "wof:name":"Rincon de Tecolayo",
    "wof:placetype":"locality",
    "wof:population":195
},
  "geometry": {"coordinates":[-97.03471999999999,18.79528],"type":"Point"}
}