{
  "type": "Feature",
  "properties": {
    "gn:admin1_code":"5",
    "gn:admin2_code":"111.0",
    "gn:asciiname":"K'Aquete",
    "gn:country_code":"MX",
    "gn:dem":1759,
    "gn:feature_class":"P",
    "gn:feature_code":"PPL",
    "gn:name":"K'Aquete",
    "gn:population":375,
    "gn:timezone":"America/Mexico_City",
    "iso:country":"MX",
    "wof:name":"K'Aquete",
    "wof:placetype":"locality",
    "wof:population":375
},
  "geometry": {"coordinates":[-92.82693999999999,16.72389],"type":"Point"}
}