{
  "type": "Feature",
  "properties": {
    "gn:admin1_code":"32.0",
    "gn:admin2_code":"33.0",
    "gn:asciiname":"Concepcion",
    "gn:country_code":"MX",
    "gn:dem":1160,
    "gn:feature_class":"P",
    "gn:feature_code":"PPL",
    "gn:name":"Concepci\u00f3n",
    "gn:population":0,
    "gn:timezone":"America/Mexico_City",
    "iso:country":"MX",
    "wof:name":"Concepcion",
    "wof:placetype":"locality"
},
  "geometry": {"coordinates":[-103.18640000000001,21.24255],"type":"Point"}
}