{
  "type": "Feature",
  "properties": {
    "gn:admin1_code":"10",
    "gn:admin2_code":"23.0",
    "gn:asciiname":"El Gallito",
    "gn:country_code":"MX",
    "gn:dem":1878,
    "gn:feature_class":"P",
    "gn:feature_code":"PPL",
    "gn:name":"El Gallito",
    "gn:population":0,
    "gn:timezone":"America/Monterrey",
    "iso:country":"MX",
    "name:spa_x_preferred":[
        "El Gallito"
    ],
    "wof:name":"El Gallito",
    "wof:placetype":"locality"
},
  "geometry": {"coordinates":[-105.41558999999999,23.2019],"type":"Point"}
}