{
  "type": "Feature",
  "properties": {
    "gn:admin1_code":"21.0",
    "gn:admin2_code":"70.0",
    "gn:asciiname":"San Nicolas Segunda Seccion",
    "gn:country_code":"MX",
    "gn:dem":1587,
    "gn:feature_class":"P",
    "gn:feature_code":"PPL",
    "gn:name":"San Nicol\u00e1s Segunda Secci\u00f3n",
    "gn:population":0,
    "gn:timezone":"America/Mexico_City",
    "iso:country":"MX",
    "name:spa_x_preferred":[
        "San Nicol\u00e1s Segunda Secci\u00f3n"
    ],
    "wof:name":"San Nicolas Segunda Seccion",
    "wof:placetype":"locality"
},
  "geometry": {"coordinates":[-98.05464000000001,18.68325],"type":"Point"}
}