{
  "type": "Feature",
  "properties": {
    "gn:admin1_code":"24",
    "gn:admin2_code":"11.0",
    "gn:asciiname":"San Onofre",
    "gn:country_code":"MX",
    "gn:dem":1024,
    "gn:feature_class":"P",
    "gn:feature_code":"PPL",
    "gn:name":"San Onofre",
    "gn:population":5,
    "gn:timezone":"America/Mexico_City",
    "iso:country":"MX",
    "name:ceb_x_preferred":[
        "San Onofre"
    ],
    "name:fra_x_preferred":[
        "San Onofre"
    ],
    "name:spa_x_preferred":[
        "San Onofre"
    ],
    "name:srp_x_preferred":[
        "\u0421\u0430\u043d \u041e\u043d\u043e\u0444\u0440\u0435"
    ],
    "name:swe_x_preferred":[
        "San Onofre"
    ],
    "wof:name":"San Onofre",
    "wof:placetype":"locality",
    "wof:population":5
},
  "geometry": {"coordinates":[-100.09389,21.94361],"type":"Point"}
}