{
  "type": "Feature",
  "properties": {
    "gn:admin1_code":"5",
    "gn:admin2_code":"77.0",
    "gn:asciiname":"Cerro Norte Don Juan",
    "gn:country_code":"MX",
    "gn:dem":47,
    "gn:feature_class":"P",
    "gn:feature_code":"PPL",
    "gn:name":"Cerro Norte Don Juan",
    "gn:population":0,
    "gn:timezone":"America/Mexico_City",
    "iso:country":"MX",
    "name:spa_x_preferred":[
        "Cerro Norte Don Juan"
    ],
    "name:spa_x_variant":[
        "Cerro Norte"
    ],
    "wof:name":"Cerro Norte Don Juan",
    "wof:placetype":"locality"
},
  "geometry": {"coordinates":[-92.13298,17.52873],"type":"Point"}
}