{
  "type": "Feature",
  "properties": {
    "gn:admin1_code":"20",
    "gn:admin2_code":"277.0",
    "gn:asciiname":"La Gloria",
    "gn:country_code":"MX",
    "gn:dem":1247,
    "gn:feature_class":"P",
    "gn:feature_code":"PPL",
    "gn:name":"La Gloria",
    "gn:population":8,
    "gn:timezone":"America/Mexico_City",
    "iso:country":"MX",
    "wof:name":"La Gloria",
    "wof:placetype":"locality",
    "wof:population":8
},
  "geometry": {"coordinates":[-97.02722,16.39639],"type":"Point"}
}