{
  "type": "Feature",
  "properties": {
    "gn:admin1_code":"26",
    "gn:admin2_code":"47.0",
    "gn:asciiname":"Santa Eduwiges",
    "gn:country_code":"MX",
    "gn:dem":715,
    "gn:feature_class":"P",
    "gn:feature_code":"PPL",
    "gn:name":"Santa Eduwiges",
    "gn:population":0,
    "gn:timezone":"America/Hermosillo",
    "iso:country":"MX",
    "name:und_x_variant":[
        "Santa Eduviges"
    ],
    "wof:name":"Santa Eduwiges",
    "wof:placetype":"locality"
},
  "geometry": {"coordinates":[-111.72789,29.81483],"type":"Point"}
}