{
  "type": "Feature",
  "properties": {
    "gn:admin1_code":"11",
    "gn:admin2_code":"23.0",
    "gn:asciiname":"Labor de Armenta",
    "gn:country_code":"MX",
    "gn:dem":1699,
    "gn:feature_class":"P",
    "gn:feature_code":"PPL",
    "gn:name":"Labor de Armenta",
    "gn:population":496,
    "gn:timezone":"America/Mexico_City",
    "iso:country":"MX",
    "wof:name":"Labor de Armenta",
    "wof:placetype":"locality",
    "wof:population":496
},
  "geometry": {"coordinates":[-101.65889,20.42556],"type":"Point"}
}