{
  "type": "Feature",
  "properties": {
    "gn:admin1_code":"25",
    "gn:admin2_code":"6.0",
    "gn:asciiname":"JR [Ganadera Agricola]",
    "gn:country_code":"MX",
    "gn:dem":62,
    "gn:feature_class":"P",
    "gn:feature_code":"PPL",
    "gn:name":"JR [Ganadera Agr\u00edcola]",
    "gn:population":5,
    "gn:timezone":"America/Mazatlan",
    "iso:country":"MX",
    "name:und_x_variant":[
        "JR [Ganadera Agr\u00edcola]"
    ],
    "wof:name":"JR [Ganadera Agricola]",
    "wof:placetype":"locality",
    "wof:population":5
},
  "geometry": {"coordinates":[-107.46796999999999,24.85893],"type":"Point"}
}