{
  "type": "Feature",
  "properties": {
    "gn:admin1_code":"8.0",
    "gn:admin2_code":"2.0",
    "gn:asciiname":"El Plan",
    "gn:country_code":"MX",
    "gn:dem":529,
    "gn:feature_class":"P",
    "gn:feature_code":"PPL",
    "gn:name":"El Plan",
    "gn:population":0,
    "gn:timezone":"America/Mexico_City",
    "iso:country":"MX",
    "name:spa_x_preferred":[
        "El Plan"
    ],
    "wof:name":"El Plan",
    "wof:placetype":"locality"
},
  "geometry": {"coordinates":[-103.62671,19.13196],"type":"Point"}
}