{
  "type": "Feature",
  "properties": {
    "gn:admin1_code":"6",
    "gn:admin2_code":"24.0",
    "gn:asciiname":"Perales",
    "gn:country_code":"MX",
    "gn:dem":1663,
    "gn:feature_class":"P",
    "gn:feature_code":"PPL",
    "gn:name":"Perales",
    "gn:population":10,
    "gn:timezone":"America/Chihuahua",
    "iso:country":"MX",
    "wof:name":"Perales",
    "wof:placetype":"locality",
    "wof:population":10
},
  "geometry": {"coordinates":[-106.36964999999999,28.39825],"type":"Point"}
}