{
  "type": "Feature",
  "properties": {
    "gn:admin1_code":"26.0",
    "gn:admin2_code":"40.0",
    "gn:asciiname":"Chinos",
    "gn:country_code":"MX",
    "gn:dem":915,
    "gn:feature_class":"P",
    "gn:feature_code":"PPL",
    "gn:name":"Chinos",
    "gn:population":0,
    "gn:timezone":"America/Hermosillo",
    "iso:country":"MX",
    "wof:name":"Chinos",
    "wof:placetype":"locality"
},
  "geometry": {"coordinates":[-108.86667,29.53333],"type":"Point"}
}