{
  "type": "Feature",
  "properties": {
    "gn:admin1_code":"25.0",
    "gn:admin2_code":"8.0",
    "gn:asciiname":"Guasima Gorda",
    "gn:cc2":"MX",
    "gn:country_code":"MX",
    "gn:dem":31,
    "gn:feature_class":"P",
    "gn:feature_code":"PPL",
    "gn:name":"Gu\u00e1sima Gorda",
    "gn:population":0,
    "gn:timezone":"America/Mazatlan",
    "iso:country":"MX",
    "name:und_x_variant":[
        "Cuasima Gorda",
        "Gu\u00e1sima Gorda"
    ],
    "wof:name":"Guasima Gorda",
    "wof:placetype":"locality"
},
  "geometry": {"coordinates":[-106.91667,24.03333],"type":"Point"}
}