{
  "type": "Feature",
  "properties": {
    "gn:admin1_code":"25",
    "gn:admin2_code":"16.0",
    "gn:asciiname":"Camacho de Abajo",
    "gn:country_code":"MX",
    "gn:dem":110,
    "gn:feature_class":"P",
    "gn:feature_code":"PPL",
    "gn:name":"Camacho de Abajo",
    "gn:population":0,
    "gn:timezone":"America/Mazatlan",
    "iso:country":"MX",
    "name:spa_x_preferred":[
        "Camacho de Abajo"
    ],
    "name:und_x_variant":[
        "Camacho"
    ],
    "wof:name":"Camacho de Abajo",
    "wof:placetype":"locality"
},
  "geometry": {"coordinates":[-106.53595,23.93703],"type":"Point"}
}