{
  "type": "Feature",
  "properties": {
    "gn:admin1_code":"7.0",
    "gn:admin2_code":"10.0",
    "gn:asciiname":"La Molienda",
    "gn:country_code":"MX",
    "gn:dem":606,
    "gn:feature_class":"P",
    "gn:feature_code":"PPL",
    "gn:name":"La Molienda",
    "gn:population":0,
    "gn:timezone":"America/Monterrey",
    "iso:country":"MX",
    "name:spa_x_preferred":[
        "La Molienda"
    ],
    "wof:name":"La Molienda",
    "wof:placetype":"locality"
},
  "geometry": {"coordinates":[-101.56953,26.91555],"type":"Point"}
}