{
  "type": "Feature",
  "properties": {
    "gn:admin1_code":"5",
    "gn:admin2_code":"17.0",
    "gn:asciiname":"Villahermosa",
    "gn:country_code":"MX",
    "gn:dem":617,
    "gn:feature_class":"P",
    "gn:feature_code":"PPL",
    "gn:name":"Villahermosa",
    "gn:population":8,
    "gn:timezone":"America/Mexico_City",
    "iso:country":"MX",
    "wof:name":"Villahermosa",
    "wof:placetype":"locality",
    "wof:population":8
},
  "geometry": {"coordinates":[-93.79083,16.59472],"type":"Point"}
}