{
  "type": "Feature",
  "properties": {
    "gn:admin1_code":"30.0",
    "gn:admin2_code":"32.0",
    "gn:asciiname":"Tres de Mayo",
    "gn:country_code":"MX",
    "gn:dem":101,
    "gn:feature_class":"P",
    "gn:feature_code":"PPL",
    "gn:name":"Tres de Mayo",
    "gn:population":230,
    "gn:timezone":"America/Mexico_City",
    "iso:country":"MX",
    "name:spa_x_preferred":[
        "Tres de Mayo"
    ],
    "wof:name":"Tres de Mayo",
    "wof:placetype":"locality",
    "wof:population":230
},
  "geometry": {"coordinates":[-95.06722000000001,18.53806],"type":"Point"}
}