{
  "type": "Feature",
  "properties": {
    "gn:admin1_code":"6",
    "gn:admin2_code":"35.0",
    "gn:asciiname":"Buenavista (Campo Doscientos Dieciocho)",
    "gn:country_code":"MX",
    "gn:dem":1413,
    "gn:feature_class":"P",
    "gn:feature_code":"PPL",
    "gn:name":"Buenavista (Campo Doscientos Dieciocho)",
    "gn:population":8,
    "gn:timezone":"America/Chihuahua",
    "iso:country":"MX",
    "wof:name":"Buenavista (Campo Doscientos Dieciocho)",
    "wof:placetype":"locality",
    "wof:population":8
},
  "geometry": {"coordinates":[-108.30515,31.14836],"type":"Point"}
}