{
  "type": "Feature",
  "properties": {
    "gn:admin1_code":"30",
    "gn:admin2_code":"109.0",
    "gn:asciiname":"La Reforma (Kilometro 9)",
    "gn:country_code":"MX",
    "gn:dem":630,
    "gn:feature_class":"P",
    "gn:feature_code":"PPL",
    "gn:name":"La Reforma (Kil\u00f3metro 9)",
    "gn:population":639,
    "gn:timezone":"America/Mexico_City",
    "iso:country":"MX",
    "name:und_x_variant":[
        "La Reforma (Kil\u00f3metro 9)"
    ],
    "wof:name":"La Reforma (Kilometro 9)",
    "wof:placetype":"locality",
    "wof:population":639
},
  "geometry": {"coordinates":[-96.80944,19.88722000000001],"type":"Point"}
}