{
  "type": "Feature",
  "properties": {
    "gn:admin1_code":"11",
    "gn:admin2_code":"14.0",
    "gn:asciiname":"Los Lopez de Arriba",
    "gn:country_code":"MX",
    "gn:dem":2269,
    "gn:feature_class":"P",
    "gn:feature_code":"PPL",
    "gn:name":"Los L\u00f3pez de Arriba",
    "gn:population":0,
    "gn:timezone":"America/Mexico_City",
    "iso:country":"MX",
    "name:und_x_variant":[
        "Los L\u00f3pez",
        "Los L\u00f3pez de Arriba"
    ],
    "wof:name":"Los Lopez de Arriba",
    "wof:placetype":"locality"
},
  "geometry": {"coordinates":[-101.08909,21.05506],"type":"Point"}
}