{
  "type": "Feature",
  "properties": {
    "gn:admin1_code":"27",
    "gn:admin2_code":"5.0",
    "gn:asciiname":"Betania",
    "gn:country_code":"MX",
    "gn:dem":12,
    "gn:feature_class":"P",
    "gn:feature_code":"PPL",
    "gn:name":"Betania",
    "gn:population":1125,
    "gn:timezone":"America/Mexico_City",
    "iso:country":"MX",
    "name:bre_x_preferred":[
        "Betania"
    ],
    "name:ceb_x_preferred":[
        "Betania"
    ],
    "name:deu_x_preferred":[
        "Betania"
    ],
    "name:ita_x_preferred":[
        "Betania"
    ],
    "name:nld_x_preferred":[
        "Betania"
    ],
    "name:nor_x_preferred":[
        "Betania"
    ],
    "name:ron_x_preferred":[
        "Betania"
    ],
    "name:sco_x_preferred":[
        "Betania"
    ],
    "name:spa_x_preferred":[
        "Betania"
    ],
    "name:swe_x_preferred":[
        "Betania"
    ],
    "name:tgl_x_preferred":[
        "Betania"
    ],
    "name:war_x_preferred":[
        "Betania"
    ],
    "wof:name":"Betania",
    "wof:placetype":"locality",
    "wof:population":1125
},
  "geometry": {"coordinates":[-93.32080999999999,18.28003],"type":"Point"}
}