{
  "type": "Feature",
  "properties": {
    "gn:admin1_code":"4",
    "gn:admin2_code":"1",
    "gn:asciiname":"Yaxhaltun",
    "gn:country_code":"MX",
    "gn:dem":70,
    "gn:feature_class":"P",
    "gn:feature_code":"PPL",
    "gn:name":"Yaxhalt\u00fan",
    "gn:population":34,
    "gn:timezone":"America/Merida",
    "iso:country":"MX",
    "name:und_x_variant":[
        "Yaxhalt\u00fan"
    ],
    "wof:name":"Yaxhaltun",
    "wof:placetype":"locality",
    "wof:population":34
},
  "geometry": {"coordinates":[-89.88333,20.12861],"type":"Point"}
}