{
  "type": "Feature",
  "properties": {
    "gn:admin1_code":"7",
    "gn:admin2_code":"34.0",
    "gn:asciiname":"Rancho la Eta",
    "gn:country_code":"MX",
    "gn:dem":1427,
    "gn:feature_class":"P",
    "gn:feature_code":"PPL",
    "gn:name":"Rancho la Eta",
    "gn:population":5,
    "gn:timezone":"America/Monterrey",
    "iso:country":"MX",
    "wof:name":"Rancho la Eta",
    "wof:placetype":"locality",
    "wof:population":5
},
  "geometry": {"coordinates":[-103.67847,27.29273],"type":"Point"}
}