{
  "type": "Feature",
  "properties": {
    "gn:admin1_code":"10",
    "gn:admin2_code":"14",
    "gn:asciiname":"La Cofradia",
    "gn:country_code":"MX",
    "gn:dem":1812,
    "gn:feature_class":"P",
    "gn:feature_code":"PPL",
    "gn:name":"La Cofrad\u00eda",
    "gn:population":35,
    "gn:timezone":"America/Monterrey",
    "iso:country":"MX",
    "name:und_x_variant":[
        "La Cofrad\u00eda"
    ],
    "wof:name":"La Cofradia",
    "wof:placetype":"locality",
    "wof:population":35
},
  "geometry": {"coordinates":[-104.81068,22.94062000000001],"type":"Point"}
}