{
  "type": "Feature",
  "properties": {
    "gn:admin1_code":"6.0",
    "gn:admin2_code":"8.0",
    "gn:asciiname":"Najigonachi",
    "gn:country_code":"MX",
    "gn:dem":2205,
    "gn:feature_class":"P",
    "gn:feature_code":"PPL",
    "gn:name":"Najigonachi",
    "gn:population":0,
    "gn:timezone":"America/Chihuahua",
    "iso:country":"MX",
    "name:spa_x_preferred":[
        "Najigonachi"
    ],
    "wof:name":"Najigonachi",
    "wof:placetype":"locality"
},
  "geometry": {"coordinates":[-107.57401000000002,27.06299000000001],"type":"Point"}
}