{
  "type": "Feature",
  "properties": {
    "gn:admin1_code":"25",
    "gn:admin2_code":"14",
    "gn:asciiname":"La Canoa",
    "gn:country_code":"MX",
    "gn:dem":119,
    "gn:feature_class":"P",
    "gn:feature_code":"PPL",
    "gn:name":"La Canoa",
    "gn:population":31,
    "gn:timezone":"America/Mazatlan",
    "iso:country":"MX",
    "wof:name":"La Canoa",
    "wof:placetype":"locality",
    "wof:population":31
},
  "geometry": {"coordinates":[-105.69437000000001,23.09786],"type":"Point"}
}