{
  "type": "Feature",
  "properties": {
    "gn:admin1_code":"14",
    "gn:admin2_code":"35",
    "gn:asciiname":"Villa de Lourdes [Fraccionamiento]",
    "gn:country_code":"MX",
    "gn:dem":1833,
    "gn:feature_class":"P",
    "gn:feature_code":"PPL",
    "gn:name":"Villa de Lourdes [Fraccionamiento]",
    "gn:population":18,
    "gn:timezone":"America/Mexico_City",
    "iso:country":"MX",
    "wof:name":"Villa de Lourdes [Fraccionamiento]",
    "wof:placetype":"locality",
    "wof:population":18
},
  "geometry": {"coordinates":[-102.25806,21.51917000000001],"type":"Point"}
}