{
  "type": "Feature",
  "properties": {
    "gn:admin1_code":"12",
    "gn:admin2_code":"38.0",
    "gn:asciiname":"Los Balsamos",
    "gn:country_code":"MX",
    "gn:dem":1436,
    "gn:feature_class":"P",
    "gn:feature_code":"PPL",
    "gn:name":"Los B\u00e1lsamos",
    "gn:population":7,
    "gn:timezone":"America/Mexico_City",
    "iso:country":"MX",
    "name:und_x_variant":[
        "Los B\u00e1lsamos"
    ],
    "wof:name":"Los Balsamos",
    "wof:placetype":"locality",
    "wof:population":7
},
  "geometry": {"coordinates":[-101.24781,17.98132],"type":"Point"}
}