{
  "type": "Feature",
  "properties": {
    "gn:admin1_code":"18.0",
    "gn:admin2_code":"18.0",
    "gn:asciiname":"El Calabozo",
    "gn:country_code":"MX",
    "gn:dem":7,
    "gn:feature_class":"P",
    "gn:feature_code":"PPL",
    "gn:name":"El Calabozo",
    "gn:population":0,
    "gn:timezone":"America/Mazatlan",
    "iso:country":"MX",
    "name:spa_x_preferred":[
        "El Calabozo"
    ],
    "wof:name":"El Calabozo",
    "wof:placetype":"locality"
},
  "geometry": {"coordinates":[-105.3214,21.87268],"type":"Point"}
}