{
  "type": "Feature",
  "properties": {
    "gn:admin1_code":"31",
    "gn:admin2_code":"79.0",
    "gn:asciiname":"Chulbalam",
    "gn:country_code":"MX",
    "gn:dem":142,
    "gn:feature_class":"P",
    "gn:feature_code":"PPL",
    "gn:name":"Chulbalam",
    "gn:population":0,
    "gn:timezone":"America/Merida",
    "iso:country":"MX",
    "name:spa_x_preferred":[
        "Chulbalam"
    ],
    "wof:name":"Chulbalam",
    "wof:placetype":"locality"
},
  "geometry": {"coordinates":[-89.33941999999998,19.90249],"type":"Point"}
}