{
  "type": "Feature",
  "properties": {
    "gn:admin1_code":"25.0",
    "gn:admin2_code":"16.0",
    "gn:asciiname":"Cabazan",
    "gn:country_code":"MX",
    "gn:dem":177,
    "gn:feature_class":"P",
    "gn:feature_code":"PPL",
    "gn:name":"Cabazan",
    "gn:population":278,
    "gn:timezone":"America/Mazatlan",
    "iso:country":"MX",
    "name:spa_x_preferred":[
        "Cabazan"
    ],
    "name:und_x_variant":[
        "Cabaz\u00e1n"
    ],
    "wof:name":"Cabazan",
    "wof:placetype":"locality",
    "wof:population":278
},
  "geometry": {"coordinates":[-106.49267,23.89087],"type":"Point"}
}