{
  "type": "Feature",
  "properties": {
    "gn:admin1_code":"2",
    "gn:admin2_code":"2",
    "gn:asciiname":"Familia Diaz (Ejido Campeche)",
    "gn:country_code":"MX",
    "gn:dem":24,
    "gn:feature_class":"P",
    "gn:feature_code":"PPL",
    "gn:name":"Familia D\u00edaz (Ejido Campeche)",
    "gn:population":20,
    "gn:timezone":"America/Tijuana",
    "iso:country":"MX",
    "name:und_x_variant":[
        "Familia D\u00edaz (Ejido Campeche)"
    ],
    "wof:name":"Familia Diaz (Ejido Campeche)",
    "wof:placetype":"locality",
    "wof:population":20
},
  "geometry": {"coordinates":[-114.97750000000001,32.53194000000001],"type":"Point"}
}