{
  "type": "Feature",
  "properties": {
    "gn:admin1_code":"5",
    "gn:admin2_code":"118",
    "gn:asciiname":"Lindavista 2da. Fraccion (El Retiro)",
    "gn:country_code":"MX",
    "gn:dem":600,
    "gn:feature_class":"P",
    "gn:feature_code":"PPL",
    "gn:name":"Lindavista 2da. Fracci\u00f3n (El Retiro)",
    "gn:population":34,
    "gn:timezone":"America/Mexico_City",
    "iso:country":"MX",
    "name:und_x_variant":[
        "Lindavista 2da. Fracci\u00f3n (El Retiro)"
    ],
    "wof:name":"Lindavista 2da. Fraccion (El Retiro)",
    "wof:placetype":"locality",
    "wof:population":34
},
  "geometry": {"coordinates":[-92.79443999999999,17.18556],"type":"Point"}
}