{
  "type": "Feature",
  "properties": {
    "gn:admin1_code":"19",
    "gn:admin2_code":"22.0",
    "gn:asciiname":"Colonia Citricultores",
    "gn:country_code":"MX",
    "gn:dem":330,
    "gn:feature_class":"P",
    "gn:feature_code":"PPL",
    "gn:name":"Colonia Citricultores",
    "gn:population":0,
    "gn:timezone":"America/Monterrey",
    "iso:country":"MX",
    "name:spa_x_preferred":[
        "Colonia Citricultores"
    ],
    "wof:name":"Colonia Citricultores",
    "wof:placetype":"locality"
},
  "geometry": {"coordinates":[-99.70285,25.2466],"type":"Point"}
}