{
  "type": "Feature",
  "properties": {
    "gn:admin1_code":"15",
    "gn:admin2_code":"117.0",
    "gn:asciiname":"Los Epazotes",
    "gn:country_code":"MX",
    "gn:dem":1431,
    "gn:feature_class":"P",
    "gn:feature_code":"PPL",
    "gn:name":"Los Epazotes",
    "gn:population":61,
    "gn:timezone":"America/Mexico_City",
    "iso:country":"MX",
    "wof:name":"Los Epazotes",
    "wof:placetype":"locality",
    "wof:population":61
},
  "geometry": {"coordinates":[-99.87177,18.63176],"type":"Point"}
}