{
  "type": "Feature",
  "properties": {
    "gn:admin1_code":"24",
    "gn:admin2_code":"12",
    "gn:asciiname":"Camino Viejo (La Loma)",
    "gn:country_code":"MX",
    "gn:dem":72,
    "gn:feature_class":"P",
    "gn:feature_code":"PPL",
    "gn:name":"Camino Viejo (La Loma)",
    "gn:population":46,
    "gn:timezone":"America/Mexico_City",
    "iso:country":"MX",
    "wof:name":"Camino Viejo (La Loma)",
    "wof:placetype":"locality",
    "wof:population":46
},
  "geometry": {"coordinates":[-98.97638999999999,21.63806],"type":"Point"}
}