{
  "type": "Feature",
  "properties": {
    "gn:admin1_code":"10",
    "gn:admin2_code":"26.0",
    "gn:asciiname":"La Zacatera",
    "gn:country_code":"MX",
    "gn:dem":2457,
    "gn:feature_class":"P",
    "gn:feature_code":"PPL",
    "gn:name":"La Zacatera",
    "gn:population":0,
    "gn:timezone":"America/Monterrey",
    "iso:country":"MX",
    "name:spa_x_preferred":[
        "La Zacatera"
    ],
    "wof:name":"La Zacatera",
    "wof:placetype":"locality"
},
  "geometry": {"coordinates":[-105.75533,24.41298],"type":"Point"}
}