{
  "type": "Feature",
  "properties": {
    "gn:admin1_code":"19",
    "gn:admin2_code":"29",
    "gn:asciiname":"La Purisima",
    "gn:country_code":"MX",
    "gn:dem":407,
    "gn:feature_class":"P",
    "gn:feature_code":"PPL",
    "gn:name":"La Pur\u00edsima",
    "gn:population":35,
    "gn:timezone":"America/Monterrey",
    "iso:country":"MX",
    "name:und_x_variant":[
        "La Pur\u00edsima"
    ],
    "wof:name":"La Purisima",
    "wof:placetype":"locality",
    "wof:population":35
},
  "geometry": {"coordinates":[-99.67610999999999,24.91917],"type":"Point"}
}