{
  "type": "Feature",
  "properties": {
    "gn:admin1_code":"5",
    "gn:admin2_code":"81.0",
    "gn:asciiname":"La Ilusion Uno",
    "gn:country_code":"MX",
    "gn:dem":754,
    "gn:feature_class":"P",
    "gn:feature_code":"PPL",
    "gn:name":"La Ilusi\u00f3n Uno",
    "gn:population":155,
    "gn:timezone":"America/Mexico_City",
    "iso:country":"MX",
    "name:und_x_variant":[
        "La Ilusi\u00f3n Uno"
    ],
    "wof:name":"La Ilusion Uno",
    "wof:placetype":"locality",
    "wof:population":155
},
  "geometry": {"coordinates":[-92.72027,17.13694],"type":"Point"}
}