{
  "type": "Feature",
  "properties": {
    "gn:admin1_code":"5",
    "gn:admin2_code":"46",
    "gn:asciiname":"El Frailescano",
    "gn:country_code":"MX",
    "gn:dem":635,
    "gn:feature_class":"P",
    "gn:feature_code":"PPL",
    "gn:name":"El Frailescano",
    "gn:population":11,
    "gn:timezone":"America/Mexico_City",
    "iso:country":"MX",
    "wof:name":"El Frailescano",
    "wof:placetype":"locality",
    "wof:population":11
},
  "geometry": {"coordinates":[-93.52194,16.56722],"type":"Point"}
}