{
  "type": "Feature",
  "properties": {
    "gn:admin1_code":"6.0",
    "gn:admin2_code":"8.0",
    "gn:asciiname":"El Chalate",
    "gn:country_code":"MX",
    "gn:dem":1011,
    "gn:feature_class":"P",
    "gn:feature_code":"PPL",
    "gn:name":"El Chalate",
    "gn:population":0,
    "gn:timezone":"America/Chihuahua",
    "iso:country":"MX",
    "name:spa_x_preferred":[
        "El Chalate"
    ],
    "wof:name":"El Chalate",
    "wof:placetype":"locality"
},
  "geometry": {"coordinates":[-107.8639,26.94467],"type":"Point"}
}