{
  "type": "Feature",
  "properties": {
    "gn:admin1_code":"16",
    "gn:admin2_code":"112.0",
    "gn:asciiname":"Silva de Abajo",
    "gn:country_code":"MX",
    "gn:dem":2186,
    "gn:feature_class":"P",
    "gn:feature_code":"PPL",
    "gn:name":"Silva de Abajo",
    "gn:population":553,
    "gn:timezone":"America/Mexico_City",
    "iso:country":"MX",
    "wof:name":"Silva de Abajo",
    "wof:placetype":"locality",
    "wof:population":553
},
  "geometry": {"coordinates":[-100.34417000000001,19.38833],"type":"Point"}
}