{
  "type": "Feature",
  "properties": {
    "gn:admin1_code":"5",
    "gn:admin2_code":"66.0",
    "gn:asciiname":"El Porvenir",
    "gn:country_code":"MX",
    "gn:dem":903,
    "gn:feature_class":"P",
    "gn:feature_code":"PPL",
    "gn:name":"El Porvenir",
    "gn:population":313,
    "gn:timezone":"America/Mexico_City",
    "iso:country":"MX",
    "wof:name":"El Porvenir",
    "wof:placetype":"locality",
    "wof:population":313
},
  "geometry": {"coordinates":[-92.43694000000001,17.00056],"type":"Point"}
}