{
  "type": "Feature",
  "properties": {
    "gn:admin1_code":"18",
    "gn:admin2_code":"5.0",
    "gn:asciiname":"Rancho de los Sanchez",
    "gn:country_code":"MX",
    "gn:dem":81,
    "gn:feature_class":"P",
    "gn:feature_code":"PPL",
    "gn:name":"Rancho de los S\u00e1nchez",
    "gn:population":6,
    "gn:timezone":"America/Mazatlan",
    "iso:country":"MX",
    "name:und_x_variant":[
        "Rancho de los S\u00e1nchez"
    ],
    "wof:name":"Rancho de los Sanchez",
    "wof:placetype":"locality",
    "wof:population":6
},
  "geometry": {"coordinates":[-105.31417,22.64944],"type":"Point"}
}