{
  "type": "Feature",
  "properties": {
    "gn:admin1_code":"28.0",
    "gn:admin2_code":"5.0",
    "gn:asciiname":"San Rafael de Buenavista",
    "gn:country_code":"MX",
    "gn:dem":224,
    "gn:feature_class":"P",
    "gn:feature_code":"PPL",
    "gn:name":"San Rafael de Buenavista",
    "gn:population":0,
    "gn:timezone":"America/Monterrey",
    "iso:country":"MX",
    "name:spa_x_preferred":[
        "San Rafael de Buenavista"
    ],
    "wof:name":"San Rafael de Buenavista",
    "wof:placetype":"locality"
},
  "geometry": {"coordinates":[-98.84517,24.91754],"type":"Point"}
}