{
  "type": "Feature",
  "properties": {
    "gn:admin1_code":"12",
    "gn:admin2_code":"61.0",
    "gn:asciiname":"Zacatzonapa",
    "gn:country_code":"MX",
    "gn:dem":1332,
    "gn:feature_class":"P",
    "gn:feature_code":"PPL",
    "gn:name":"Zacatzonapa",
    "gn:population":959,
    "gn:timezone":"America/Mexico_City",
    "iso:country":"MX",
    "name:spa_x_preferred":[
        "Zacatzonapa"
    ],
    "name:und_x_variant":[
        "Zacazonapan"
    ],
    "wof:name":"Zacatzonapa",
    "wof:placetype":"locality",
    "wof:population":959
},
  "geometry": {"coordinates":[-99.34323000000001,17.50212],"type":"Point"}
}