{
  "type": "Feature",
  "properties": {
    "gn:admin1_code":"10.0",
    "gn:admin2_code":"37.0",
    "gn:asciiname":"Los Guayabos",
    "gn:country_code":"MX",
    "gn:dem":1848,
    "gn:feature_class":"P",
    "gn:feature_code":"PPL",
    "gn:name":"Los Guayabos",
    "gn:population":0,
    "gn:timezone":"America/Monterrey",
    "iso:country":"MX",
    "name:spa_x_preferred":[
        "Los Guayabos"
    ],
    "wof:name":"Los Guayabos",
    "wof:placetype":"locality"
},
  "geometry": {"coordinates":[-106.54673,25.19335],"type":"Point"}
}