{
  "type": "Feature",
  "properties": {
    "gn:admin1_code":"5",
    "gn:admin2_code":"100.0",
    "gn:asciiname":"Cacahuatal",
    "gn:country_code":"MX",
    "gn:dem":280,
    "gn:feature_class":"P",
    "gn:feature_code":"PPL",
    "gn:name":"Cacahuatal",
    "gn:population":0,
    "gn:timezone":"America/Mexico_City",
    "iso:country":"MX",
    "name:spa_x_preferred":[
        "Cacahuatal"
    ],
    "wof:name":"Cacahuatal",
    "wof:placetype":"locality"
},
  "geometry": {"coordinates":[-92.22663,17.32323],"type":"Point"}
}