{
  "type": "Feature",
  "properties": {
    "gn:admin1_code":"7",
    "gn:admin2_code":"19.0",
    "gn:asciiname":"Los Tecolotes",
    "gn:country_code":"MX",
    "gn:dem":434,
    "gn:feature_class":"P",
    "gn:feature_code":"PPL",
    "gn:name":"Los Tecolotes",
    "gn:population":6,
    "gn:timezone":"America/Monterrey",
    "iso:country":"MX",
    "wof:name":"Los Tecolotes",
    "wof:placetype":"locality",
    "wof:population":6
},
  "geometry": {"coordinates":[-100.98981999999999,28.2983],"type":"Point"}
}