{
  "type": "Feature",
  "properties": {
    "gn:admin1_code":"16.0",
    "gn:asciiname":"Puerto de la Sepultura",
    "gn:country_code":"MX",
    "gn:dem":2575,
    "gn:feature_class":"P",
    "gn:feature_code":"PPL",
    "gn:name":"Puerto de la Sepultura",
    "gn:population":0,
    "gn:timezone":"America/Mexico_City",
    "iso:country":"MX",
    "name:spa_x_preferred":[
        "Puerto de la Sepultura"
    ],
    "name:spa_x_variant":[
        "El Puerto de la Sepultura"
    ],
    "wof:name":"Puerto de la Sepultura",
    "wof:placetype":"locality"
},
  "geometry": {"coordinates":[-100.58199,19.52366],"type":"Point"}
}