{
  "type": "Feature",
  "properties": {
    "gn:admin1_code":"2",
    "gn:admin2_code":"4",
    "gn:asciiname":"Familia Parra Morales",
    "gn:country_code":"MX",
    "gn:dem":184,
    "gn:feature_class":"P",
    "gn:feature_code":"PPL",
    "gn:name":"Familia Parra Morales",
    "gn:population":9,
    "gn:timezone":"America/Tijuana",
    "iso:country":"MX",
    "wof:name":"Familia Parra Morales",
    "wof:placetype":"locality",
    "wof:population":9
},
  "geometry": {"coordinates":[-116.94667,32.43944],"type":"Point"}
}