{
  "type": "Feature",
  "properties": {
    "gn:admin1_code":"30",
    "gn:admin2_code":"15.0",
    "gn:asciiname":"Finca del Refugio",
    "gn:country_code":"MX",
    "gn:dem":65,
    "gn:feature_class":"P",
    "gn:feature_code":"PPL",
    "gn:name":"Finca del Refugio",
    "gn:population":6,
    "gn:timezone":"America/Mexico_City",
    "iso:country":"MX",
    "wof:name":"Finca del Refugio",
    "wof:placetype":"locality",
    "wof:population":6
},
  "geometry": {"coordinates":[-95.38083,18.58528],"type":"Point"}
}