{
  "type": "Feature",
  "properties": {
    "gn:admin1_code":"5.0",
    "gn:admin2_code":"65.0",
    "gn:asciiname":"Manzanares",
    "gn:country_code":"MX",
    "gn:dem":35,
    "gn:feature_class":"P",
    "gn:feature_code":"PPL",
    "gn:name":"Manzanares",
    "gn:population":0,
    "gn:timezone":"America/Mexico_City",
    "iso:country":"MX",
    "name:arg_x_preferred":[
        "Manzanares"
    ],
    "name:cat_x_preferred":[
        "Manzanares"
    ],
    "name:ceb_x_preferred":[
        "Manzanares"
    ],
    "name:ces_x_preferred":[
        "Manzanares"
    ],
    "name:deu_x_preferred":[
        "Manzanares"
    ],
    "name:eus_x_preferred":[
        "Manzanares"
    ],
    "name:fra_x_preferred":[
        "Manzanares"
    ],
    "name:ita_x_preferred":[
        "Manzanares"
    ],
    "name:jpn_x_preferred":[
        "\u30de\u30f3\u30b5\u30ca\u30fc\u30ec\u30b9"
    ],
    "name:mar_x_preferred":[
        "\u092e\u093e\u0928\u094d\u091d\u093e\u0928\u093e\u0930\u0947\u0938 \u0928\u0926\u0940"
    ],
    "name:mlg_x_preferred":[
        "Manzanares"
    ],
    "name:msa_x_preferred":[
        "Manzanares"
    ],
    "name:nld_x_preferred":[
        "Manzanares"
    ],
    "name:por_x_preferred":[
        "Manzanares"
    ],
    "name:sco_x_preferred":[
        "Manzanares"
    ],
    "name:slk_x_preferred":[
        "Manzanares"
    ],
    "name:spa_x_preferred":[
        "Manzanares"
    ],
    "name:srp_x_preferred":[
        "\u041c\u0430\u043d\u0437\u0430\u043d\u0430\u0440\u0435\u0441"
    ],
    "name:swe_x_preferred":[
        "Manzanares"
    ],
    "name:vie_x_preferred":[
        "Manzanares"
    ],
    "name:war_x_preferred":[
        "Manzanares"
    ],
    "wof:name":"Manzanares",
    "wof:placetype":"locality"
},
  "geometry": {"coordinates":[-91.86991,17.71294],"type":"Point"}
}