{
  "type": "Feature",
  "properties": {
    "gn:admin1_code":"2",
    "gn:admin2_code":"2",
    "gn:asciiname":"Tlaxcala 2",
    "gn:country_code":"MX",
    "gn:dem":15,
    "gn:feature_class":"P",
    "gn:feature_code":"PPL",
    "gn:name":"Tlaxcala 2",
    "gn:population":20,
    "gn:timezone":"America/Tijuana",
    "iso:country":"MX",
    "wof:name":"Tlaxcala 2",
    "wof:placetype":"locality",
    "wof:population":20
},
  "geometry": {"coordinates":[-115.14417,32.46472],"type":"Point"}
}