{
  "type": "Feature",
  "properties": {
    "gn:admin1_code":"32",
    "gn:admin2_code":"54.0",
    "gn:asciiname":"San Gabriel",
    "gn:country_code":"MX",
    "gn:dem":2124,
    "gn:feature_class":"P",
    "gn:feature_code":"PPL",
    "gn:name":"San Gabriel",
    "gn:population":107,
    "gn:timezone":"America/Mexico_City",
    "iso:country":"MX",
    "wof:name":"San Gabriel",
    "wof:placetype":"locality",
    "wof:population":107
},
  "geometry": {"coordinates":[-101.79000000000001,22.35722],"type":"Point"}
}