{
  "type": "Feature",
  "properties": {
    "gn:admin1_code":"30.0",
    "gn:admin2_code":"35.0",
    "gn:asciiname":"San Sebastian el Alto",
    "gn:country_code":"MX",
    "gn:dem":122,
    "gn:feature_class":"P",
    "gn:feature_code":"PPL",
    "gn:name":"San Sebasti\u00e1n el Alto",
    "gn:population":199,
    "gn:timezone":"America/Mexico_City",
    "iso:country":"MX",
    "name:spa_x_preferred":[
        "San Sebasti\u00e1n el Alto"
    ],
    "wof:name":"San Sebastian el Alto",
    "wof:placetype":"locality",
    "wof:population":199
},
  "geometry": {"coordinates":[-97.86528,21.36056],"type":"Point"}
}