{
  "type": "Feature",
  "properties": {
    "gn:admin1_code":"30",
    "gn:admin2_code":"152.0",
    "gn:asciiname":"Palacho",
    "gn:country_code":"MX",
    "gn:dem":21,
    "gn:feature_class":"P",
    "gn:feature_code":"PPL",
    "gn:name":"Palacho",
    "gn:population":0,
    "gn:timezone":"America/Mexico_City",
    "iso:country":"MX",
    "name:und_x_variant":[
        "Estaci\u00f3n Palacho",
        "Palacho Uno"
    ],
    "wof:name":"Palacho",
    "wof:placetype":"locality"
},
  "geometry": {"coordinates":[-97.97172999999999,22.02085],"type":"Point"}
}