{
  "type": "Feature",
  "properties": {
    "gn:admin1_code":"30.0",
    "gn:admin2_code":"124.0",
    "gn:asciiname":"Ignacio Allende",
    "gn:country_code":"MX",
    "gn:dem":82,
    "gn:feature_class":"P",
    "gn:feature_code":"PPL",
    "gn:name":"Ignacio Allende",
    "gn:population":939,
    "gn:timezone":"America/Mexico_City",
    "iso:country":"MX",
    "name:spa_x_preferred":[
        "Ignacio Allende"
    ],
    "wof:name":"Ignacio Allende",
    "wof:placetype":"locality",
    "wof:population":939
},
  "geometry": {"coordinates":[-97.19611,20.31444],"type":"Point"}
}