{
  "type": "Feature",
  "properties": {
    "gn:admin1_code":"16",
    "gn:admin2_code":"99.0",
    "gn:asciiname":"Unas de Gato",
    "gn:country_code":"MX",
    "gn:dem":1800,
    "gn:feature_class":"P",
    "gn:feature_code":"PPL",
    "gn:name":"U\u00f1as de Gato",
    "gn:population":9,
    "gn:timezone":"America/Mexico_City",
    "iso:country":"MX",
    "name:und_x_variant":[
        "U\u00f1as de Gato"
    ],
    "wof:name":"Unas de Gato",
    "wof:placetype":"locality",
    "wof:population":9
},
  "geometry": {"coordinates":[-100.60666999999999,19.41583],"type":"Point"}
}