{
  "type": "Feature",
  "properties": {
    "gn:admin1_code":"14",
    "gn:admin2_code":"82.0",
    "gn:asciiname":"Los Tres Garcias",
    "gn:country_code":"MX",
    "gn:dem":1359,
    "gn:feature_class":"P",
    "gn:feature_code":"PPL",
    "gn:name":"Los Tres Garcias",
    "gn:population":9,
    "gn:timezone":"America/Mexico_City",
    "iso:country":"MX",
    "wof:name":"Los Tres Garcias",
    "wof:placetype":"locality",
    "wof:population":9
},
  "geometry": {"coordinates":[-103.58139,19.88083],"type":"Point"}
}