{
  "type": "Feature",
  "properties": {
    "gn:admin1_code":"20",
    "gn:admin2_code":"392.0",
    "gn:asciiname":"Fortin de Juarez",
    "gn:country_code":"MX",
    "gn:dem":1601,
    "gn:feature_class":"P",
    "gn:feature_code":"PPL",
    "gn:name":"Fort\u00edn de Ju\u00e1rez",
    "gn:population":200,
    "gn:timezone":"America/Mexico_City",
    "iso:country":"MX",
    "name:und_x_variant":[
        "Fort\u00edn de Ju\u00e1rez"
    ],
    "wof:name":"Fortin de Juarez",
    "wof:placetype":"locality",
    "wof:population":200
},
  "geometry": {"coordinates":[-97.71666999999999,16.92972],"type":"Point"}
}