{
  "type": "Feature",
  "properties": {
    "gn:admin1_code":"16",
    "gn:admin2_code":"47.0",
    "gn:asciiname":"La Florida",
    "gn:country_code":"MX",
    "gn:dem":1139,
    "gn:feature_class":"P",
    "gn:feature_code":"PPL",
    "gn:name":"La Florida",
    "gn:population":741,
    "gn:timezone":"America/Mexico_City",
    "iso:country":"MX",
    "wof:name":"La Florida",
    "wof:placetype":"locality",
    "wof:population":741
},
  "geometry": {"coordinates":[-100.50360999999999,19.35722],"type":"Point"}
}