{
  "type": "Feature",
  "properties": {
    "gn:admin1_code":"25.0",
    "gn:admin2_code":"17.0",
    "gn:asciiname":"Los Veneros",
    "gn:country_code":"MX",
    "gn:dem":233,
    "gn:feature_class":"P",
    "gn:feature_code":"PPL",
    "gn:name":"Los Veneros",
    "gn:population":0,
    "gn:timezone":"America/Mazatlan",
    "iso:country":"MX",
    "name:spa_x_preferred":[
        "Los Veneros"
    ],
    "wof:name":"Los Veneros",
    "wof:placetype":"locality"
},
  "geometry": {"coordinates":[-107.96975,25.93628],"type":"Point"}
}