{
  "type": "Feature",
  "properties": {
    "gn:admin1_code":"14",
    "gn:admin2_code":"97",
    "gn:asciiname":"Villa Hermosa (La Villa)",
    "gn:country_code":"MX",
    "gn:dem":1538,
    "gn:feature_class":"P",
    "gn:feature_code":"PPL",
    "gn:name":"Villa Hermosa (La Villa)",
    "gn:population":36,
    "gn:timezone":"America/Mexico_City",
    "iso:country":"MX",
    "wof:name":"Villa Hermosa (La Villa)",
    "wof:placetype":"locality",
    "wof:population":36
},
  "geometry": {"coordinates":[-103.36750000000001,20.51861],"type":"Point"}
}