{
  "type": "Feature",
  "properties": {
    "gn:admin1_code":"24",
    "gn:admin2_code":"56.0",
    "gn:asciiname":"Colonia Guadalupe",
    "gn:country_code":"MX",
    "gn:dem":1611,
    "gn:feature_class":"P",
    "gn:feature_code":"PPL",
    "gn:name":"Colonia Guadalupe",
    "gn:population":76,
    "gn:timezone":"America/Mexico_City",
    "iso:country":"MX",
    "wof:name":"Colonia Guadalupe",
    "wof:placetype":"locality",
    "wof:population":76
},
  "geometry": {"coordinates":[-100.85361,22.65778],"type":"Point"}
}