{
  "type": "Feature",
  "properties": {
    "gn:admin1_code":"23",
    "gn:admin2_code":"4.0",
    "gn:asciiname":"Las Tres Cruces",
    "gn:country_code":"MX",
    "gn:dem":17,
    "gn:feature_class":"P",
    "gn:feature_code":"PPL",
    "gn:name":"Las Tres Cruces",
    "gn:population":5,
    "gn:timezone":"America/Cancun",
    "iso:country":"MX",
    "wof:name":"Las Tres Cruces",
    "wof:placetype":"locality",
    "wof:population":5
},
  "geometry": {"coordinates":[-88.88195,17.91371000000001],"type":"Point"}
}