{
  "type": "Feature",
  "properties": {
    "gn:admin1_code":"13",
    "gn:admin2_code":"68.0",
    "gn:asciiname":"Habitacional Ruperto Alarcon (El Retonal)",
    "gn:country_code":"MX",
    "gn:dem":1565,
    "gn:feature_class":"P",
    "gn:feature_code":"PPL",
    "gn:name":"Habitacional Ruperto Alarc\u00f3n (El Reto\u00f1al)",
    "gn:population":138,
    "gn:timezone":"America/Mexico_City",
    "iso:country":"MX",
    "name:und_x_variant":[
        "Habitacional Ruperto Alarc\u00f3n (El Reto\u00f1al)"
    ],
    "wof:name":"Habitacional Ruperto Alarcon (El Retonal)",
    "wof:placetype":"locality",
    "wof:population":138
},
  "geometry": {"coordinates":[-98.62312,20.72135],"type":"Point"}
}