{
  "type": "Feature",
  "properties": {
    "gn:admin1_code":"19.0",
    "gn:admin2_code":"23.0",
    "gn:asciiname":"El Alto",
    "gn:country_code":"MX",
    "gn:dem":215,
    "gn:feature_class":"P",
    "gn:feature_code":"PPL",
    "gn:name":"El Alto",
    "gn:population":0,
    "gn:timezone":"America/Monterrey",
    "iso:country":"MX",
    "name:spa_x_preferred":[
        "El Alto"
    ],
    "wof:name":"El Alto",
    "wof:placetype":"locality"
},
  "geometry": {"coordinates":[-99.58119000000001,26.21208],"type":"Point"}
}