{
  "type": "Feature",
  "properties": {
    "gn:admin1_code":"3.0",
    "gn:admin2_code":"3.0",
    "gn:asciiname":"Yorigeobe",
    "gn:country_code":"MX",
    "gn:dem":12,
    "gn:feature_class":"P",
    "gn:feature_code":"PPL",
    "gn:name":"Yorigeobe",
    "gn:population":0,
    "gn:timezone":"America/Mazatlan",
    "iso:country":"MX",
    "name:spa_x_preferred":[
        "Yorigeobe"
    ],
    "wof:name":"Yorigeobe",
    "wof:placetype":"locality"
},
  "geometry": {"coordinates":[-110.77124000000001,23.87978],"type":"Point"}
}