{
  "type": "Feature",
  "properties": {
    "gn:admin1_code":"14",
    "gn:admin2_code":"12.0",
    "gn:asciiname":"San Antonio de los Macedo",
    "gn:country_code":"MX",
    "gn:dem":1541,
    "gn:feature_class":"P",
    "gn:feature_code":"PPL",
    "gn:name":"San Antonio de los Macedo",
    "gn:population":0,
    "gn:timezone":"America/Mexico_City",
    "iso:country":"MX",
    "name:spa_x_preferred":[
        "San Antonio de los Macedo"
    ],
    "wof:name":"San Antonio de los Macedo",
    "wof:placetype":"locality"
},
  "geometry": {"coordinates":[-104.55615,20.29833],"type":"Point"}
}