{
  "type": "Feature",
  "properties": {
    "gn:admin1_code":"28",
    "gn:admin2_code":"25.0",
    "gn:asciiname":"El Mezquitito",
    "gn:country_code":"MX",
    "gn:dem":96,
    "gn:feature_class":"P",
    "gn:feature_code":"PPL",
    "gn:name":"El Mezquitito",
    "gn:population":0,
    "gn:timezone":"America/Monterrey",
    "iso:country":"MX",
    "name:spa_x_preferred":[
        "El Mezquitito"
    ],
    "name:und_x_variant":[
        "Rancho El Mezquitito",
        "Mezquitito"
    ],
    "wof:name":"El Mezquitito",
    "wof:placetype":"locality"
},
  "geometry": {"coordinates":[-99.06305,26.31952],"type":"Point"}
}