{
  "type": "Feature",
  "properties": {
    "gn:admin1_code":"16",
    "gn:admin2_code":"85.0",
    "gn:asciiname":"Aranza",
    "gn:country_code":"MX",
    "gn:dem":2288,
    "gn:feature_class":"P",
    "gn:feature_code":"PPL",
    "gn:name":"Aranza",
    "gn:population":396,
    "gn:timezone":"America/Mexico_City",
    "iso:country":"MX",
    "wof:name":"Aranza",
    "wof:placetype":"locality",
    "wof:population":396
},
  "geometry": {"coordinates":[-102.36,19.81917],"type":"Point"}
}