{
  "type": "Feature",
  "properties": {
    "gn:admin1_code":"5.0",
    "gn:asciiname":"Santiago Pojcol",
    "gn:country_code":"MX",
    "gn:dem":1115,
    "gn:feature_class":"P",
    "gn:feature_code":"PPL",
    "gn:name":"Santiago Pojcol",
    "gn:population":0,
    "gn:timezone":"America/Mexico_City",
    "iso:country":"MX",
    "name:spa_x_preferred":[
        "Santiago Pojcol"
    ],
    "wof:name":"Santiago Pojcol",
    "wof:placetype":"locality"
},
  "geometry": {"coordinates":[-91.98071,16.99148],"type":"Point"}
}