{
  "type": "Feature",
  "properties": {
    "gn:admin1_code":"32",
    "gn:admin2_code":"55.0",
    "gn:asciiname":"Los Canos",
    "gn:country_code":"MX",
    "gn:dem":2044,
    "gn:feature_class":"P",
    "gn:feature_code":"PPL",
    "gn:name":"Los Ca\u00f1os",
    "gn:population":116,
    "gn:timezone":"America/Mexico_City",
    "iso:country":"MX",
    "name:und_x_variant":[
        "Los Ca\u00f1os"
    ],
    "wof:name":"Los Canos",
    "wof:placetype":"locality",
    "wof:population":116
},
  "geometry": {"coordinates":[-103.03278,22.30528],"type":"Point"}
}