{
  "type": "Feature",
  "properties": {
    "gn:admin1_code":"25",
    "gn:admin2_code":"4",
    "gn:asciiname":"Los Chinitos",
    "gn:country_code":"MX",
    "gn:dem":203,
    "gn:feature_class":"P",
    "gn:feature_code":"PPL",
    "gn:name":"Los Chinitos",
    "gn:population":20,
    "gn:timezone":"America/Mazatlan",
    "iso:country":"MX",
    "wof:name":"Los Chinitos",
    "wof:placetype":"locality",
    "wof:population":20
},
  "geometry": {"coordinates":[-105.97583,23.32968],"type":"Point"}
}