{
  "type": "Feature",
  "properties": {
    "gn:admin1_code":"30",
    "gn:admin2_code":"153.0",
    "gn:asciiname":"Potrero Negro",
    "gn:cc2":"MX",
    "gn:country_code":"MX",
    "gn:dem":567,
    "gn:feature_class":"P",
    "gn:feature_code":"PPL",
    "gn:name":"Potrero Negro",
    "gn:population":0,
    "gn:timezone":"America/Mexico_City",
    "iso:country":"MX",
    "name:und_x_variant":[
        "Potrero Negros",
        "Potrero Negro"
    ],
    "wof:name":"Potrero Negro",
    "wof:placetype":"locality"
},
  "geometry": {"coordinates":[-97.83333,21.25],"type":"Point"}
}