{
  "type": "Feature",
  "properties": {
    "gn:admin1_code":"14.0",
    "gn:admin2_code":"88.0",
    "gn:asciiname":"La Cruz de Mora",
    "gn:country_code":"MX",
    "gn:dem":1474,
    "gn:feature_class":"P",
    "gn:feature_code":"PPL",
    "gn:name":"La Cruz de Mora",
    "gn:population":0,
    "gn:timezone":"America/Mexico_City",
    "iso:country":"MX",
    "name:spa_x_preferred":[
        "La Cruz de Mora"
    ],
    "wof:name":"La Cruz de Mora",
    "wof:placetype":"locality"
},
  "geometry": {"coordinates":[-104.12511000000001,20.08889],"type":"Point"}
}