{
  "type": "Feature",
  "properties": {
    "gn:admin1_code":"26.0",
    "gn:admin2_code":"2.0",
    "gn:asciiname":"Cuchuverachi",
    "gn:country_code":"MX",
    "gn:dem":978,
    "gn:feature_class":"P",
    "gn:feature_code":"PPL",
    "gn:name":"Cuchuverachi",
    "gn:population":0,
    "gn:timezone":"America/Hermosillo",
    "iso:country":"MX",
    "name:und_x_variant":[
        "Hacienda Cuchuverachic",
        "Cuchuverachi"
    ],
    "wof:name":"Cuchuverachi",
    "wof:placetype":"locality"
},
  "geometry": {"coordinates":[-109.29472,31.12559000000001],"type":"Point"}
}