{
  "type": "Feature",
  "properties": {
    "gn:admin1_code":"22",
    "gn:admin2_code":"6.0",
    "gn:asciiname":"Ejido el Jaral",
    "gn:country_code":"MX",
    "gn:dem":2150,
    "gn:feature_class":"P",
    "gn:feature_code":"PPL",
    "gn:name":"Ejido el Jaral",
    "gn:population":108,
    "gn:timezone":"America/Mexico_City",
    "iso:country":"MX",
    "wof:name":"Ejido el Jaral",
    "wof:placetype":"locality",
    "wof:population":108
},
  "geometry": {"coordinates":[-100.42833,20.39306],"type":"Point"}
}