{
  "type": "Feature",
  "properties": {
    "gn:admin1_code":"22.0",
    "gn:asciiname":"Santa Rosa Finca",
    "gn:country_code":"MX",
    "gn:dem":1936,
    "gn:feature_class":"P",
    "gn:feature_code":"PPL",
    "gn:name":"Santa Rosa Finca",
    "gn:population":0,
    "gn:timezone":"America/Mexico_City",
    "iso:country":"MX",
    "name:spa_x_preferred":[
        "Santa Rosa Finca"
    ],
    "wof:name":"Santa Rosa Finca",
    "wof:placetype":"locality"
},
  "geometry": {"coordinates":[-99.96642,20.66882],"type":"Point"}
}