{
  "type": "Feature",
  "properties": {
    "gn:admin1_code":"23.0",
    "gn:admin2_code":"4.0",
    "gn:asciiname":"Tierra Negra",
    "gn:country_code":"MX",
    "gn:dem":93,
    "gn:feature_class":"P",
    "gn:feature_code":"PPL",
    "gn:name":"Tierra Negra",
    "gn:population":0,
    "gn:timezone":"America/Cancun",
    "iso:country":"MX",
    "name:spa_x_preferred":[
        "Tierras Negras"
    ],
    "name:spa_x_variant":[
        "Tierra Negra"
    ],
    "wof:name":"Tierra Negra",
    "wof:placetype":"locality"
},
  "geometry": {"coordinates":[-88.71507,18.93831],"type":"Point"}
}