{
  "type": "Feature",
  "properties": {
    "gn:admin1_code":"15",
    "gn:admin2_code":"86.0",
    "gn:asciiname":"Carboneras",
    "gn:country_code":"MX",
    "gn:dem":2010,
    "gn:feature_class":"P",
    "gn:feature_code":"PPL",
    "gn:name":"Carboneras",
    "gn:population":0,
    "gn:timezone":"America/Mexico_City",
    "iso:country":"MX",
    "name:und_x_variant":[
        "Carbonera",
        "Carboneras"
    ],
    "wof:name":"Carboneras",
    "wof:placetype":"locality"
},
  "geometry": {"coordinates":[-100.00861999999999,19.05653],"type":"Point"}
}