{
  "type": "Feature",
  "properties": {
    "gn:admin1_code":"13",
    "gn:admin2_code":"10.0",
    "gn:asciiname":"Dendho",
    "gn:country_code":"MX",
    "gn:dem":2103,
    "gn:feature_class":"P",
    "gn:feature_code":"PPL",
    "gn:name":"Dendho",
    "gn:population":0,
    "gn:timezone":"America/Mexico_City",
    "iso:country":"MX",
    "name:spa_x_preferred":[
        "Dendho"
    ],
    "wof:name":"Dendho",
    "wof:placetype":"locality"
},
  "geometry": {"coordinates":[-99.23805,20.06804],"type":"Point"}
}