{
  "type": "Feature",
  "properties": {
    "gn:admin1_code":"5",
    "gn:admin2_code":"104.0",
    "gn:asciiname":"San Cristobalito",
    "gn:country_code":"MX",
    "gn:dem":661,
    "gn:feature_class":"P",
    "gn:feature_code":"PPL",
    "gn:name":"San Cristobalito",
    "gn:population":128,
    "gn:timezone":"America/Mexico_City",
    "iso:country":"MX",
    "wof:name":"San Cristobalito",
    "wof:placetype":"locality",
    "wof:population":128
},
  "geometry": {"coordinates":[-92.27222,16.18194],"type":"Point"}
}