{
  "type": "Feature",
  "properties": {
    "gn:admin1_code":"14",
    "gn:admin2_code":"35.0",
    "gn:asciiname":"Rio de los Lomelines (La Haciendita)",
    "gn:country_code":"MX",
    "gn:dem":1865,
    "gn:feature_class":"P",
    "gn:feature_code":"PPL",
    "gn:name":"R\u00edo de los Lomelines (La Haciendita)",
    "gn:population":110,
    "gn:timezone":"America/Mexico_City",
    "iso:country":"MX",
    "name:und_x_variant":[
        "R\u00edo de los Lomelines (La Haciendita)"
    ],
    "wof:name":"Rio de los Lomelines (La Haciendita)",
    "wof:placetype":"locality",
    "wof:population":110
},
  "geometry": {"coordinates":[-102.17139,21.54417],"type":"Point"}
}