{
  "type": "Feature",
  "properties": {
    "gn:admin1_code":"32",
    "gn:admin2_code":"10.0",
    "gn:asciiname":"La Tinaja",
    "gn:country_code":"MX",
    "gn:dem":2505,
    "gn:feature_class":"P",
    "gn:feature_code":"PPL",
    "gn:name":"La Tinaja",
    "gn:population":0,
    "gn:timezone":"America/Mexico_City",
    "iso:country":"MX",
    "name:spa_x_preferred":[
        "La Tinaja"
    ],
    "wof:name":"La Tinaja",
    "wof:placetype":"locality"
},
  "geometry": {"coordinates":[-103.41959,23.23484],"type":"Point"}
}