{
  "type": "Feature",
  "properties": {
    "gn:gn_country":"MX",
    "gn:gn_fcode":"PPL",
    "gn:gn_pop":10057,
    "gn:population":10057,
    "iso:country":"MX",
    "name:spa_x_preferred":[
        "Miraflores"
    ],
    "name:unk_x_variant":[
        "San Mateo Tezoquipan"
    ],
    "qs_pg:aaroncc":"MX",
    "qs_pg:gn_country":"MX",
    "qs_pg:gn_fcode":"PPL",
    "qs_pg:gn_pop":10057,
    "qs_pg:name":"San Mateo Tecoloapan",
    "qs_pg:name_adm0":"M\u00e9xico",
    "qs_pg:name_adm1":"Mexico",
    "qs_pg:photos":1,
    "qs_pg:photos_1k":1,
    "qs_pg:photos_9k":1,
    "qs_pg:photos_9r":1,
    "qs_pg:photos_all":1,
    "qs_pg:photos_sr":1,
    "qs_pg:pop_sr":6,
    "qs_pg:qs_pg_placetype":"locality",
    "qs_pg:qs_pg_placetype_gp":"Town",
    "qs_pg:woe_adm0":23424900,
    "woe:adm0_id":23424900,
    "woe:name_adm0":"M\u00e9xico",
    "woe:name_adm1":"Mexico",
    "woe:placetype":"Town",
    "wof:name":"San Mateo Tecoloapan",
    "wof:placetype":"locality",
    "wof:population":10057
},
  "geometry": {"coordinates":[-98.81332999999999,19.22492],"type":"Point"}
}