{
  "type": "Feature",
  "properties": {
    "gn:admin1_code":"6",
    "gn:admin2_code":"27",
    "gn:asciiname":"La Luna",
    "gn:country_code":"MX",
    "gn:dem":2202,
    "gn:feature_class":"P",
    "gn:feature_code":"PPL",
    "gn:name":"La Luna",
    "gn:population":9,
    "gn:timezone":"America/Chihuahua",
    "iso:country":"MX",
    "name:ceb_x_preferred":[
        "La Luna"
    ],
    "name:deu_x_preferred":[
        "La Luna"
    ],
    "name:fra_x_preferred":[
        "La Luna"
    ],
    "name:ita_x_preferred":[
        "La luna"
    ],
    "name:nld_x_preferred":[
        "La Luna"
    ],
    "name:srp_x_preferred":[
        "\u041b\u0430 \u041b\u0443\u043d\u0430"
    ],
    "name:swe_x_preferred":[
        "La Luna"
    ],
    "name:uzb_x_preferred":[
        "La Luna"
    ],
    "wof:name":"La Luna",
    "wof:placetype":"locality",
    "wof:population":9
},
  "geometry": {"coordinates":[-107.07129,27.28299],"type":"Point"}
}