{
  "type": "Feature",
  "properties": {
    "gn:admin1_code":"6",
    "gn:admin2_code":"27",
    "gn:asciiname":"La Luna",
    "gn:country_code":"MX",
    "gn:dem":2202,
    "gn:feature_class":"P",
    "gn:feature_code":"PPL",
    "gn:name":"La Luna",
    "gn:population":9,
    "gn:timezone":"America/Chihuahua",
    "iso:country":"MX",
    "wof:name":"La Luna",
    "wof:placetype":"locality",
    "wof:population":9
},
  "geometry": {"coordinates":[-107.07129,27.28299],"type":"Point"}
}