{
  "type": "Feature",
  "properties": {
    "gn:admin1_code":"21",
    "gn:admin2_code":"213.0",
    "gn:asciiname":"El Cafetin",
    "gn:country_code":"MX",
    "gn:dem":810,
    "gn:feature_class":"P",
    "gn:feature_code":"PPL",
    "gn:name":"El Cafet\u00edn",
    "gn:population":7,
    "gn:timezone":"America/Mexico_City",
    "iso:country":"MX",
    "name:und_x_variant":[
        "El Cafet\u00edn"
    ],
    "wof:name":"El Cafetin",
    "wof:placetype":"locality",
    "wof:population":7
},
  "geometry": {"coordinates":[-97.84401,20.27256],"type":"Point"}
}