{
  "type": "Feature",
  "properties": {
    "gn:admin1_code":"5",
    "gn:admin2_code":"19.0",
    "gn:asciiname":"San Antonio Bellavista",
    "gn:country_code":"MX",
    "gn:dem":655,
    "gn:feature_class":"P",
    "gn:feature_code":"PPL",
    "gn:name":"San Antonio Bellavista",
    "gn:population":4,
    "gn:timezone":"America/Mexico_City",
    "iso:country":"MX",
    "wof:name":"San Antonio Bellavista",
    "wof:placetype":"locality",
    "wof:population":4
},
  "geometry": {"coordinates":[-92.20389,16.08889],"type":"Point"}
}