{
  "type": "Feature",
  "properties": {
    "gn:admin1_code":"7",
    "gn:admin2_code":"4.0",
    "gn:asciiname":"El Tesoro",
    "gn:country_code":"MX",
    "gn:dem":2163,
    "gn:feature_class":"P",
    "gn:feature_code":"PPL",
    "gn:name":"El Tesoro",
    "gn:population":7,
    "gn:timezone":"America/Monterrey",
    "iso:country":"MX",
    "wof:name":"El Tesoro",
    "wof:placetype":"locality",
    "wof:population":7
},
  "geometry": {"coordinates":[-100.82084999999999,25.18671],"type":"Point"}
}