{
  "type": "Feature",
  "properties": {
    "gn:admin1_code":"30",
    "gn:admin2_code":"9",
    "gn:asciiname":"Gustavo Rubio Aguilar",
    "gn:country_code":"MX",
    "gn:dem":988,
    "gn:feature_class":"P",
    "gn:feature_code":"PPL",
    "gn:name":"Gustavo Rubio Aguilar",
    "gn:population":10,
    "gn:timezone":"America/Mexico_City",
    "iso:country":"MX",
    "wof:name":"Gustavo Rubio Aguilar",
    "wof:placetype":"locality",
    "wof:population":10
},
  "geometry": {"coordinates":[-96.655,19.74389],"type":"Point"}
}