{
  "type": "Feature",
  "properties": {
    "gn:admin1_code":"25",
    "gn:admin2_code":"13.0",
    "gn:asciiname":"Potrero de los Sanchez (Estacion Techa)",
    "gn:country_code":"MX",
    "gn:dem":43,
    "gn:feature_class":"P",
    "gn:feature_code":"PPL",
    "gn:name":"Potrero de los S\u00e1nchez (Estaci\u00f3n Techa)",
    "gn:population":1205,
    "gn:timezone":"America/Mazatlan",
    "iso:country":"MX",
    "name:und_x_variant":[
        "Potrero de los S\u00e1nchez (Estaci\u00f3n Techa)"
    ],
    "wof:name":"Potrero de los Sanchez (Estacion Techa)",
    "wof:placetype":"locality",
    "wof:population":1205
},
  "geometry": {"coordinates":[-107.90111,25.11],"type":"Point"}
}