{
  "type": "Feature",
  "properties": {
    "gn:admin1_code":"27",
    "gn:admin2_code":"15.0",
    "gn:asciiname":"Chichilte",
    "gn:country_code":"MX",
    "gn:dem":18,
    "gn:feature_class":"P",
    "gn:feature_code":"PPL",
    "gn:name":"Chichilte",
    "gn:population":0,
    "gn:timezone":"America/Mexico_City",
    "iso:country":"MX",
    "name:spa_x_preferred":[
        "Chichilte"
    ],
    "wof:name":"Chichilte",
    "wof:placetype":"locality"
},
  "geometry": {"coordinates":[-92.86375,17.60522000000001],"type":"Point"}
}