{
  "type": "Feature",
  "properties": {
    "gn:admin1_code":"25.0",
    "gn:admin2_code":"6.0",
    "gn:asciiname":"Guadari",
    "gn:cc2":"MX",
    "gn:country_code":"MX",
    "gn:dem":57,
    "gn:feature_class":"P",
    "gn:feature_code":"PPL",
    "gn:name":"Guadari",
    "gn:population":0,
    "gn:timezone":"America/Mazatlan",
    "iso:country":"MX",
    "name:und_x_variant":[
        "El Guadar\u00f3n",
        "Guarad\u00ed",
        "Guadar\u00e9",
        "Guadari"
    ],
    "wof:name":"Guadari",
    "wof:placetype":"locality"
},
  "geometry": {"coordinates":[-107.38361,24.73944],"type":"Point"}
}