{
  "type": "Feature",
  "properties": {
    "gn:admin1_code":"6.0",
    "gn:admin2_code":"66.0",
    "gn:asciiname":"Huiyochi",
    "gn:country_code":"MX",
    "gn:dem":2560,
    "gn:feature_class":"P",
    "gn:feature_code":"PPL",
    "gn:name":"Huiyochi",
    "gn:population":0,
    "gn:timezone":"America/Chihuahua",
    "iso:country":"MX",
    "name:spa_x_preferred":[
        "Huiyochi"
    ],
    "wof:name":"Huiyochi",
    "wof:placetype":"locality"
},
  "geometry": {"coordinates":[-108.20222,27.72612],"type":"Point"}
}