{
  "type": "Feature",
  "properties": {
    "gn:admin1_code":"10",
    "gn:admin2_code":"9.0",
    "gn:asciiname":"Pedernales",
    "gn:country_code":"MX",
    "gn:dem":2668,
    "gn:feature_class":"P",
    "gn:feature_code":"PPL",
    "gn:name":"Pedernales",
    "gn:population":0,
    "gn:timezone":"America/Monterrey",
    "iso:country":"MX",
    "name:ceb_x_preferred":[
        "Pedernales"
    ],
    "name:deu_x_preferred":[
        "Pedernales"
    ],
    "name:fra_x_preferred":[
        "Pedernales"
    ],
    "name:ita_x_preferred":[
        "Pedernales"
    ],
    "name:nld_x_preferred":[
        "Pedernales"
    ],
    "name:pol_x_preferred":[
        "Pedernales"
    ],
    "name:por_x_preferred":[
        "Pedernales"
    ],
    "name:rus_x_preferred":[
        "\u041f\u0435\u0434\u0435\u0440\u043d\u0430\u043b\u0435\u0441"
    ],
    "name:spa_x_preferred":[
        "Los Ancones"
    ],
    "name:spa_x_variant":[
        "Pedernales"
    ],
    "name:srp_x_preferred":[
        "\u041f\u0435\u0434\u0435\u0440\u043d\u0430\u043b\u0435\u0441"
    ],
    "name:swe_x_preferred":[
        "Pedernales"
    ],
    "wof:name":"Pedernales",
    "wof:placetype":"locality"
},
  "geometry": {"coordinates":[-106.40293,26.07969],"type":"Point"}
}