{
  "type": "Feature",
  "properties": {
    "gn:admin1_code":"18",
    "gn:admin2_code":"5",
    "gn:asciiname":"Monte Redondo",
    "gn:country_code":"MX",
    "gn:dem":1426,
    "gn:feature_class":"P",
    "gn:feature_code":"PPL",
    "gn:name":"Monte Redondo",
    "gn:population":18,
    "gn:timezone":"America/Mazatlan",
    "iso:country":"MX",
    "wof:name":"Monte Redondo",
    "wof:placetype":"locality",
    "wof:population":18
},
  "geometry": {"coordinates":[-105.20332999999999,22.71333],"type":"Point"}
}