{
  "type": "Feature",
  "properties": {
    "gn:admin1_code":"19.0",
    "gn:admin2_code":"14.0",
    "gn:asciiname":"El Leoncito",
    "gn:country_code":"MX",
    "gn:dem":1739,
    "gn:feature_class":"P",
    "gn:feature_code":"PPL",
    "gn:name":"El Leoncito",
    "gn:population":0,
    "gn:timezone":"America/Monterrey",
    "iso:country":"MX",
    "name:ceb_x_preferred":[
        "El Leoncito"
    ],
    "name:fra_x_preferred":[
        "El Leoncito"
    ],
    "name:ita_x_preferred":[
        "El Leoncito"
    ],
    "name:spa_x_preferred":[
        "El Leoncito"
    ],
    "name:swe_x_preferred":[
        "El Leoncito"
    ],
    "wof:name":"El Leoncito",
    "wof:placetype":"locality"
},
  "geometry": {"coordinates":[-100.54662999999999,24.41835],"type":"Point"}
}