{
  "type": "Feature",
  "properties": {
    "gn:admin1_code":"5",
    "gn:admin2_code":"97.0",
    "gn:asciiname":"Isla San Marcos",
    "gn:country_code":"MX",
    "gn:dem":1,
    "gn:feature_class":"P",
    "gn:feature_code":"PPL",
    "gn:name":"Isla San Marcos",
    "gn:population":86,
    "gn:timezone":"America/Mexico_City",
    "iso:country":"MX",
    "wof:name":"Isla San Marcos",
    "wof:placetype":"locality",
    "wof:population":86
},
  "geometry": {"coordinates":[-93.67111,15.84611],"type":"Point"}
}