{
  "type": "Feature",
  "properties": {
    "gn:admin1_code":"14",
    "gn:admin2_code":"61",
    "gn:asciiname":"Atotonilco",
    "gn:country_code":"MX",
    "gn:dem":2097,
    "gn:feature_class":"P",
    "gn:feature_code":"PPL",
    "gn:name":"Atotonilco",
    "gn:population":23,
    "gn:timezone":"America/Mexico_City",
    "iso:country":"MX",
    "name:ceb_x_preferred":[
        "Atotonilco"
    ],
    "name:deu_x_preferred":[
        "Atotonilco"
    ],
    "name:ita_x_preferred":[
        "Atotonilco"
    ],
    "name:sco_x_preferred":[
        "Atotonilco"
    ],
    "name:spa_x_preferred":[
        "Atotonilco"
    ],
    "name:swe_x_preferred":[
        "Atotonilco"
    ],
    "wof:name":"Atotonilco",
    "wof:placetype":"locality",
    "wof:population":23
},
  "geometry": {"coordinates":[-104.05167,22.21444],"type":"Point"}
}