{
  "type": "Feature",
  "properties": {
    "gn:admin1_code":"30",
    "gn:admin2_code":"148.0",
    "gn:asciiname":"Valladolid",
    "gn:country_code":"MX",
    "gn:dem":195,
    "gn:feature_class":"P",
    "gn:feature_code":"PPL",
    "gn:name":"Valladolid",
    "gn:population":0,
    "gn:timezone":"America/Mexico_City",
    "iso:country":"MX",
    "name:spa_x_preferred":[
        "Valladolid"
    ],
    "wof:name":"Valladolid",
    "wof:placetype":"locality"
},
  "geometry": {"coordinates":[-96.48882,18.97897],"type":"Point"}
}