{
  "type": "Feature",
  "properties": {
    "gn:admin1_code":"5",
    "gn:admin2_code":"97.0",
    "gn:asciiname":"Las Angustias (Caballero)",
    "gn:country_code":"MX",
    "gn:dem":302,
    "gn:feature_class":"P",
    "gn:feature_code":"PPL",
    "gn:name":"Las Angustias (Caballero)",
    "gn:population":6,
    "gn:timezone":"America/Mexico_City",
    "iso:country":"MX",
    "wof:name":"Las Angustias (Caballero)",
    "wof:placetype":"locality",
    "wof:population":6
},
  "geometry": {"coordinates":[-93.64444,16.05639],"type":"Point"}
}