{
  "type": "Feature",
  "properties": {
    "gn:admin1_code":"25.0",
    "gn:admin2_code":"6.0",
    "gn:asciiname":"Rebeca",
    "gn:country_code":"MX",
    "gn:dem":13,
    "gn:feature_class":"P",
    "gn:feature_code":"PPL",
    "gn:name":"Rebeca",
    "gn:population":0,
    "gn:timezone":"America/Mazatlan",
    "iso:country":"MX",
    "name:spa_x_preferred":[
        "Rebeca"
    ],
    "name:spa_x_variant":[
        "Empaque"
    ],
    "name:und_x_variant":[
        "Campo Rebeca"
    ],
    "wof:name":"Rebeca",
    "wof:placetype":"locality"
},
  "geometry": {"coordinates":[-107.3762,24.44499],"type":"Point"}
}