{
  "type": "Feature",
  "properties": {
    "gn:admin1_code":"26.0",
    "gn:admin2_code":"41.0",
    "gn:asciiname":"El Bellotal",
    "gn:country_code":"MX",
    "gn:dem":1366,
    "gn:feature_class":"P",
    "gn:feature_code":"PPL",
    "gn:name":"El Bellotal",
    "gn:population":0,
    "gn:timezone":"America/Hermosillo",
    "iso:country":"MX",
    "name:und_x_variant":[
        "Rancho El Bellotal",
        "El Bellotal"
    ],
    "wof:name":"El Bellotal",
    "wof:placetype":"locality"
},
  "geometry": {"coordinates":[-109.55148,30.56749000000001],"type":"Point"}
}