{
  "type": "Feature",
  "properties": {
    "gn:admin1_code":"14.0",
    "gn:admin2_code":"48.0",
    "gn:asciiname":"Acumbaro",
    "gn:country_code":"MX",
    "gn:dem":1905,
    "gn:feature_class":"P",
    "gn:feature_code":"PPL",
    "gn:name":"Ac\u00fambaro",
    "gn:population":0,
    "gn:timezone":"America/Mexico_City",
    "iso:country":"MX",
    "wof:name":"Acumbaro",
    "wof:placetype":"locality"
},
  "geometry": {"coordinates":[-102.01667,20.61667000000001],"type":"Point"}
}