{
  "type": "Feature",
  "properties": {
    "gn:admin1_code":"12.0",
    "gn:admin2_code":"27.0",
    "gn:asciiname":"Arroyo del Picacho",
    "gn:country_code":"MX",
    "gn:dem":528,
    "gn:feature_class":"P",
    "gn:feature_code":"PPL",
    "gn:name":"Arroyo del Picacho",
    "gn:population":0,
    "gn:timezone":"America/Mexico_City",
    "iso:country":"MX",
    "name:spa_x_preferred":[
        "Arroyo del Picacho"
    ],
    "wof:name":"Arroyo del Picacho",
    "wof:placetype":"locality"
},
  "geometry": {"coordinates":[-100.58014,18.76331],"type":"Point"}
}