{
  "type": "Feature",
  "properties": {
    "gn:admin1_code":"6",
    "gn:admin2_code":"5.0",
    "gn:asciiname":"La Barranca",
    "gn:country_code":"MX",
    "gn:dem":1187,
    "gn:feature_class":"P",
    "gn:feature_code":"PPL",
    "gn:name":"La Barranca",
    "gn:population":0,
    "gn:timezone":"America/Chihuahua",
    "iso:country":"MX",
    "name:fra_x_preferred":[
        "La Barranca"
    ],
    "name:spa_x_preferred":[
        "La Barranca"
    ],
    "wof:name":"La Barranca",
    "wof:placetype":"locality"
},
  "geometry": {"coordinates":[-107.08926,31.47524],"type":"Point"}
}