{
  "type": "Feature",
  "properties": {
    "gn:admin1_code":"16.0",
    "gn:admin2_code":"29.0",
    "gn:asciiname":"San Antonio",
    "gn:country_code":"MX",
    "gn:dem":386,
    "gn:feature_class":"P",
    "gn:feature_code":"PPL",
    "gn:name":"San Antonio",
    "gn:population":0,
    "gn:timezone":"America/Mexico_City",
    "iso:country":"MX",
    "name:spa_x_preferred":[
        "San Antonio"
    ],
    "wof:name":"San Antonio",
    "wof:placetype":"locality"
},
  "geometry": {"coordinates":[-101.52047,18.66931],"type":"Point"}
}