{
  "type": "Feature",
  "properties": {
    "gn:admin1_code":"5",
    "gn:admin2_code":"37.0",
    "gn:asciiname":"Canton el Tivoli",
    "gn:country_code":"MX",
    "gn:dem":201,
    "gn:feature_class":"P",
    "gn:feature_code":"PPL",
    "gn:name":"Cant\u00f3n el T\u00edvoli",
    "gn:population":323,
    "gn:timezone":"America/Mexico_City",
    "iso:country":"MX",
    "name:und_x_variant":[
        "Cant\u00f3n el T\u00edvoli"
    ],
    "wof:name":"Canton el Tivoli",
    "wof:placetype":"locality",
    "wof:population":323
},
  "geometry": {"coordinates":[-92.33389,15.00639],"type":"Point"}
}