{
  "type": "Feature",
  "properties": {
    "gn:admin1_code":"30",
    "gn:admin2_code":"108.0",
    "gn:asciiname":"El Naranjal",
    "gn:country_code":"MX",
    "gn:dem":7,
    "gn:feature_class":"P",
    "gn:feature_code":"PPL",
    "gn:name":"El Naranjal",
    "gn:population":0,
    "gn:timezone":"America/Mexico_City",
    "iso:country":"MX",
    "name:spa_x_preferred":[
        "El Naranjal"
    ],
    "wof:name":"El Naranjal",
    "wof:placetype":"locality"
},
  "geometry": {"coordinates":[-94.40822,17.8384],"type":"Point"}
}