{
  "type": "Feature",
  "properties": {
    "gn:admin1_code":"20",
    "gn:admin2_code":"280.0",
    "gn:asciiname":"Santa Clara",
    "gn:country_code":"MX",
    "gn:dem":1501,
    "gn:feature_class":"P",
    "gn:feature_code":"PPL",
    "gn:name":"Santa Clara",
    "gn:population":60,
    "gn:timezone":"America/Mexico_City",
    "iso:country":"MX",
    "wof:name":"Santa Clara",
    "wof:placetype":"locality",
    "wof:population":60
},
  "geometry": {"coordinates":[-96.25917,17.34444],"type":"Point"}
}