{
  "type": "Feature",
  "properties": {
    "gn:admin1_code":"5",
    "gn:admin2_code":"3.0",
    "gn:asciiname":"La Palma",
    "gn:country_code":"MX",
    "gn:dem":5,
    "gn:feature_class":"P",
    "gn:feature_code":"PPL",
    "gn:name":"La Palma",
    "gn:population":0,
    "gn:timezone":"America/Mexico_City",
    "iso:country":"MX",
    "name:spa_x_preferred":[
        "La Palma"
    ],
    "wof:name":"La Palma",
    "wof:placetype":"locality"
},
  "geometry": {"coordinates":[-92.83698,15.17247],"type":"Point"}
}