{
  "type": "Feature",
  "properties": {
    "gn:admin1_code":"17",
    "gn:admin2_code":"29.0",
    "gn:asciiname":"El Fortin",
    "gn:country_code":"MX",
    "gn:dem":1100,
    "gn:feature_class":"P",
    "gn:feature_code":"PPL",
    "gn:name":"El Fort\u00edn",
    "gn:population":177,
    "gn:timezone":"America/Mexico_City",
    "iso:country":"MX",
    "name:und_x_variant":[
        "El Fort\u00edn"
    ],
    "wof:name":"El Fortin",
    "wof:placetype":"locality",
    "wof:population":177
},
  "geometry": {"coordinates":[-99.10442999999999,18.82032],"type":"Point"}
}