{
  "type": "Feature",
  "properties": {
    "gn:admin1_code":"14",
    "gn:admin2_code":"35",
    "gn:asciiname":"La Fortuna",
    "gn:country_code":"MX",
    "gn:dem":1994,
    "gn:feature_class":"P",
    "gn:feature_code":"PPL",
    "gn:name":"La Fortuna",
    "gn:population":32,
    "gn:timezone":"America/Mexico_City",
    "iso:country":"MX",
    "wof:name":"La Fortuna",
    "wof:placetype":"locality",
    "wof:population":32
},
  "geometry": {"coordinates":[-102.12611,21.70333],"type":"Point"}
}