{
  "type": "Feature",
  "properties": {
    "gn:admin1_code":"26.0",
    "gn:admin2_code":"68.0",
    "gn:asciiname":"La Mesa del Rincon",
    "gn:country_code":"MX",
    "gn:dem":615,
    "gn:feature_class":"P",
    "gn:feature_code":"PPL",
    "gn:name":"La Mesa del Rinc\u00f3n",
    "gn:population":0,
    "gn:timezone":"America/Hermosillo",
    "iso:country":"MX",
    "name:spa_x_preferred":[
        "La Mesa del Rinc\u00f3n"
    ],
    "wof:name":"La Mesa del Rincon",
    "wof:placetype":"locality"
},
  "geometry": {"coordinates":[-110.04001,28.88597],"type":"Point"}
}