{
  "type": "Feature",
  "properties": {
    "gn:admin1_code":"30",
    "gn:admin2_code":"61",
    "gn:asciiname":"La Carmelita",
    "gn:country_code":"MX",
    "gn:dem":34,
    "gn:feature_class":"P",
    "gn:feature_code":"PPL",
    "gn:name":"La Carmelita",
    "gn:population":20,
    "gn:timezone":"America/Mexico_City",
    "iso:country":"MX",
    "wof:name":"La Carmelita",
    "wof:placetype":"locality",
    "wof:population":20
},
  "geometry": {"coordinates":[-93.89583,17.5925],"type":"Point"}
}