{
  "type": "Feature",
  "properties": {
    "gn:admin1_code":"19.0",
    "gn:admin2_code":"4.0",
    "gn:asciiname":"Las Pleyades",
    "gn:country_code":"MX",
    "gn:dem":406,
    "gn:feature_class":"P",
    "gn:feature_code":"PPL",
    "gn:name":"Las Pl\u00e9yades",
    "gn:population":0,
    "gn:timezone":"America/Monterrey",
    "iso:country":"MX",
    "name:spa_x_preferred":[
        "Las Pl\u00e9yades"
    ],
    "wof:name":"Las Pleyades",
    "wof:placetype":"locality"
},
  "geometry": {"coordinates":[-100.02264,25.32223],"type":"Point"}
}