{
  "type": "Feature",
  "properties": {
    "gn:admin1_code":"5",
    "gn:admin2_code":"80.0",
    "gn:asciiname":"El Tesoro",
    "gn:country_code":"MX",
    "gn:dem":1474,
    "gn:feature_class":"P",
    "gn:feature_code":"PPL",
    "gn:name":"El Tesoro",
    "gn:population":67,
    "gn:timezone":"America/Mexico_City",
    "iso:country":"MX",
    "wof:name":"El Tesoro",
    "wof:placetype":"locality",
    "wof:population":67
},
  "geometry": {"coordinates":[-92.52083,15.52694],"type":"Point"}
}