{
  "type": "Feature",
  "properties": {
    "gn:admin1_code":"26",
    "gn:admin2_code":"3",
    "gn:asciiname":"Las Animas",
    "gn:country_code":"MX",
    "gn:dem":217,
    "gn:feature_class":"P",
    "gn:feature_code":"PPL",
    "gn:name":"Las \u00c1nimas",
    "gn:population":14,
    "gn:timezone":"America/Hermosillo",
    "iso:country":"MX",
    "name:und_x_variant":[
        "Las \u00c1nimas"
    ],
    "wof:name":"Las Animas",
    "wof:placetype":"locality",
    "wof:population":14
},
  "geometry": {"coordinates":[-108.85889,26.56222],"type":"Point"}
}