{
  "type": "Feature",
  "properties": {
    "gn:admin1_code":"5",
    "gn:admin2_code":"107.0",
    "gn:asciiname":"Los Girasoles",
    "gn:country_code":"MX",
    "gn:dem":627,
    "gn:feature_class":"P",
    "gn:feature_code":"PPL",
    "gn:name":"Los Girasoles",
    "gn:population":4,
    "gn:timezone":"America/Mexico_City",
    "iso:country":"MX",
    "wof:name":"Los Girasoles",
    "wof:placetype":"locality",
    "wof:population":4
},
  "geometry": {"coordinates":[-93.17749999999999,16.26611],"type":"Point"}
}