{
  "type": "Feature",
  "properties": {
    "gn:admin1_code":"15",
    "gn:admin2_code":"64.0",
    "gn:asciiname":"Cerro Lloron",
    "gn:country_code":"MX",
    "gn:dem":2997,
    "gn:feature_class":"P",
    "gn:feature_code":"PPL",
    "gn:name":"Cerro Llor\u00f3n",
    "gn:population":729,
    "gn:timezone":"America/Mexico_City",
    "iso:country":"MX",
    "name:und_x_variant":[
        "Cerro Llor\u00f3n"
    ],
    "wof:name":"Cerro Lloron",
    "wof:placetype":"locality",
    "wof:population":729
},
  "geometry": {"coordinates":[-100.12079,19.76483],"type":"Point"}
}