{
  "type": "Feature",
  "properties": {
    "gn:admin1_code":"5.0",
    "gn:admin2_code":"31.0",
    "gn:asciiname":"San Juan Catarraya",
    "gn:country_code":"MX",
    "gn:dem":915,
    "gn:feature_class":"P",
    "gn:feature_code":"PPL",
    "gn:name":"San Juan Catarraya",
    "gn:population":0,
    "gn:timezone":"America/Mexico_City",
    "iso:country":"MX",
    "name:spa_x_preferred":[
        "San Juan Catarraya"
    ],
    "wof:name":"San Juan Catarraya",
    "wof:placetype":"locality"
},
  "geometry": {"coordinates":[-91.79600000000001,17.04036],"type":"Point"}
}