{
  "type": "Feature",
  "properties": {
    "gn:admin1_code":"12",
    "gn:admin2_code":"32.0",
    "gn:asciiname":"Nuevo Poblado el Caracol",
    "gn:country_code":"MX",
    "gn:dem":386,
    "gn:feature_class":"P",
    "gn:feature_code":"PPL",
    "gn:name":"Nuevo Poblado el Caracol",
    "gn:population":511,
    "gn:timezone":"America/Mexico_City",
    "iso:country":"MX",
    "wof:name":"Nuevo Poblado el Caracol",
    "wof:placetype":"locality",
    "wof:population":511
},
  "geometry": {"coordinates":[-100.02249999999999,17.95861],"type":"Point"}
}