{
  "type": "Feature",
  "properties": {
    "gn:admin1_code":"6.0",
    "gn:asciiname":"El Brasil",
    "gn:country_code":"MX",
    "gn:dem":1203,
    "gn:feature_class":"P",
    "gn:feature_code":"PPL",
    "gn:name":"El Brasil",
    "gn:population":0,
    "gn:timezone":"America/Chihuahua",
    "iso:country":"MX",
    "name:spa_x_preferred":[
        "El Brasil"
    ],
    "wof:name":"El Brasil",
    "wof:placetype":"locality"
},
  "geometry": {"coordinates":[-105.38105,28.17854],"type":"Point"}
}