{
  "type": "Feature",
  "properties": {
    "gn:admin1_code":"31",
    "gn:admin2_code":"54.0",
    "gn:asciiname":"San Juan Koop",
    "gn:country_code":"MX",
    "gn:dem":16,
    "gn:feature_class":"P",
    "gn:feature_code":"PPL",
    "gn:name":"San Juan Koop",
    "gn:population":0,
    "gn:timezone":"America/Merida",
    "iso:country":"MX",
    "name:und_x_variant":[
        "San Juan Ko\u00f3p"
    ],
    "wof:name":"San Juan Koop",
    "wof:placetype":"locality"
},
  "geometry": {"coordinates":[-89.34492,21.03023],"type":"Point"}
}