{
  "type": "Feature",
  "properties": {
    "gn:admin1_code":"8",
    "gn:admin2_code":"9.0",
    "gn:asciiname":"Enrique Mendoza",
    "gn:country_code":"MX",
    "gn:dem":29,
    "gn:feature_class":"P",
    "gn:feature_code":"PPL",
    "gn:name":"Enrique Mendoza",
    "gn:population":5,
    "gn:timezone":"America/Mexico_City",
    "iso:country":"MX",
    "name:ara_x_preferred":[
        "\u0625\u0646\u0631\u064a\u0643\u064a \u0645\u0646\u062f\u0648\u0632\u0627"
    ],
    "name:fra_x_preferred":[
        "Enrique Mendoza"
    ],
    "name:spa_x_preferred":[
        "Enrique Mendoza"
    ],
    "wof:name":"Enrique Mendoza",
    "wof:placetype":"locality",
    "wof:population":5
},
  "geometry": {"coordinates":[-103.81471999999999,18.89167],"type":"Point"}
}