{
  "type": "Feature",
  "properties": {
    "gn:admin1_code":"32",
    "gn:admin2_code":"26.0",
    "gn:asciiname":"Benito Juarez (El Tigre)",
    "gn:country_code":"MX",
    "gn:dem":1576,
    "gn:feature_class":"P",
    "gn:feature_code":"PPL",
    "gn:name":"Benito Ju\u00e1rez (El Tigre)",
    "gn:population":72,
    "gn:timezone":"America/Mexico_City",
    "iso:country":"MX",
    "name:und_x_variant":[
        "Benito Ju\u00e1rez (El Tigre)"
    ],
    "wof:name":"Benito Juarez (El Tigre)",
    "wof:placetype":"locality",
    "wof:population":72
},
  "geometry": {"coordinates":[-102.48806,24.73861],"type":"Point"}
}