{
  "type": "Feature",
  "properties": {
    "gn:admin1_code":"20",
    "gn:admin2_code":"505.0",
    "gn:asciiname":"Rio Mico",
    "gn:country_code":"MX",
    "gn:dem":138,
    "gn:feature_class":"P",
    "gn:feature_code":"PPL",
    "gn:name":"R\u00edo Mico",
    "gn:population":0,
    "gn:timezone":"America/Mexico_City",
    "iso:country":"MX",
    "name:spa_x_preferred":[
        "R\u00edo Mico"
    ],
    "wof:name":"Rio Mico",
    "wof:placetype":"locality"
},
  "geometry": {"coordinates":[-94.72547,16.6266],"type":"Point"}
}