{
  "type": "Feature",
  "properties": {
    "gn:admin1_code":"5",
    "gn:admin2_code":"23.0",
    "gn:asciiname":"Macbilotic",
    "gn:country_code":"MX",
    "gn:dem":2380,
    "gn:feature_class":"P",
    "gn:feature_code":"PPL",
    "gn:name":"Macbilotic",
    "gn:population":81,
    "gn:timezone":"America/Mexico_City",
    "iso:country":"MX",
    "wof:name":"Macbilotic",
    "wof:placetype":"locality",
    "wof:population":81
},
  "geometry": {"coordinates":[-92.53749999999999,16.76167],"type":"Point"}
}