{
  "type": "Feature",
  "properties": {
    "gn:admin1_code":"20.0",
    "gn:admin2_code":"347.0",
    "gn:asciiname":"El Cerezal",
    "gn:country_code":"MX",
    "gn:dem":2345,
    "gn:feature_class":"P",
    "gn:feature_code":"PPL",
    "gn:name":"El Cerezal",
    "gn:population":0,
    "gn:timezone":"America/Mexico_City",
    "iso:country":"MX",
    "name:spa_x_preferred":[
        "El Cerezal"
    ],
    "wof:name":"El Cerezal",
    "wof:placetype":"locality"
},
  "geometry": {"coordinates":[-96.44652000000001,16.2175],"type":"Point"}
}