{
  "type": "Feature",
  "properties": {
    "gn:admin1_code":"10",
    "gn:admin2_code":"26",
    "gn:asciiname":"Metatitos",
    "gn:country_code":"MX",
    "gn:dem":2417,
    "gn:feature_class":"P",
    "gn:feature_code":"PPL",
    "gn:name":"Metatitos",
    "gn:population":11,
    "gn:timezone":"America/Monterrey",
    "iso:country":"MX",
    "wof:name":"Metatitos",
    "wof:placetype":"locality",
    "wof:population":11
},
  "geometry": {"coordinates":[-105.54227,24.52166],"type":"Point"}
}