{
  "type": "Feature",
  "properties": {
    "gn:admin1_code":"4.0",
    "gn:asciiname":"Sistema Publico Radiodifusion Toluca Mexico",
    "gn:country_code":"MX",
    "gn:dem":6,
    "gn:feature_class":"P",
    "gn:feature_code":"PPL",
    "gn:name":"Sistema P\u00fablico Radiodifusi\u00f3n Toluca M\u00e9xico",
    "gn:population":0,
    "gn:timezone":"America/Merida",
    "iso:country":"MX",
    "name:spa_x_preferred":[
        "Sistema P\u00fablico Radiodifusi\u00f3n Toluca M\u00e9xico"
    ],
    "name:spa_x_variant":[
        "Toluca M\u00e9xico"
    ],
    "wof:name":"Sistema Publico Radiodifusion Toluca Mexico",
    "wof:placetype":"locality"
},
  "geometry": {"coordinates":[-91.65519999999999,18.078],"type":"Point"}
}