{
  "type": "Feature",
  "properties": {
    "gn:admin1_code":"26.0",
    "gn:admin2_code":"29.0",
    "gn:asciiname":"La Bomba",
    "gn:country_code":"MX",
    "gn:dem":21,
    "gn:feature_class":"P",
    "gn:feature_code":"PPL",
    "gn:name":"La Bomba",
    "gn:population":0,
    "gn:timezone":"America/Hermosillo",
    "iso:country":"MX",
    "name:ceb_x_preferred":[
        "La Bomba"
    ],
    "name:ita_x_preferred":[
        "La bomba"
    ],
    "name:spa_x_preferred":[
        "La Bomba"
    ],
    "name:spa_x_variant":[
        "La bomba"
    ],
    "name:srp_x_preferred":[
        "\u041b\u0430 \u0411\u043e\u043c\u0431\u0430"
    ],
    "name:swe_x_preferred":[
        "La Bomba"
    ],
    "wof:name":"La Bomba",
    "wof:placetype":"locality"
},
  "geometry": {"coordinates":[-110.91781,28.02794],"type":"Point"}
}