{
  "type": "Feature",
  "properties": {
    "gn:admin1_code":"30",
    "gn:admin2_code":"108",
    "gn:asciiname":"El Faisan",
    "gn:country_code":"MX",
    "gn:dem":15,
    "gn:feature_class":"P",
    "gn:feature_code":"PPL",
    "gn:name":"El Fais\u00e1n",
    "gn:population":25,
    "gn:timezone":"America/Mexico_City",
    "iso:country":"MX",
    "name:und_x_variant":[
        "El Fais\u00e1n"
    ],
    "wof:name":"El Faisan",
    "wof:placetype":"locality",
    "wof:population":25
},
  "geometry": {"coordinates":[-94.5475,17.66139],"type":"Point"}
}