{
  "type": "Feature",
  "properties": {
    "gn:admin1_code":"10",
    "gn:admin2_code":"7.0",
    "gn:asciiname":"Pastor Rovaix",
    "gn:country_code":"MX",
    "gn:dem":1115,
    "gn:feature_class":"P",
    "gn:feature_code":"PPL",
    "gn:name":"Pastor Rovaix",
    "gn:population":0,
    "gn:timezone":"America/Monterrey",
    "iso:country":"MX",
    "name:spa_x_preferred":[
        "Pastor Rovaix"
    ],
    "name:spa_x_variant":[
        "P\u00e9njamo"
    ],
    "wof:name":"Pastor Rovaix",
    "wof:placetype":"locality"
},
  "geometry": {"coordinates":[-103.44163,25.73508],"type":"Point"}
}