{
  "type": "Feature",
  "properties": {
    "gn:admin1_code":"14",
    "gn:admin2_code":"108.0",
    "gn:asciiname":"Valle Florido (El Valle)",
    "gn:country_code":"MX",
    "gn:dem":785,
    "gn:feature_class":"P",
    "gn:feature_code":"PPL",
    "gn:name":"Valle Florido (El Valle)",
    "gn:population":7,
    "gn:timezone":"America/Mexico_City",
    "iso:country":"MX",
    "wof:name":"Valle Florido (El Valle)",
    "wof:placetype":"locality",
    "wof:population":7
},
  "geometry": {"coordinates":[-103.43889,19.30778],"type":"Point"}
}