{
  "type": "Feature",
  "properties": {
    "gn:admin1_code":"2",
    "gn:admin2_code":"4.0",
    "gn:asciiname":"El Cerro",
    "gn:country_code":"MX",
    "gn:dem":261,
    "gn:feature_class":"P",
    "gn:feature_code":"PPL",
    "gn:name":"El Cerro",
    "gn:population":7,
    "gn:timezone":"America/Tijuana",
    "iso:country":"MX",
    "wof:name":"El Cerro",
    "wof:placetype":"locality",
    "wof:population":7
},
  "geometry": {"coordinates":[-116.8625,32.42333],"type":"Point"}
}