{
  "type": "Feature",
  "properties": {
    "gn:admin1_code":"6",
    "gn:admin2_code":"11.0",
    "gn:asciiname":"Encinillas",
    "gn:country_code":"MX",
    "gn:dem":1583,
    "gn:feature_class":"P",
    "gn:feature_code":"PPL",
    "gn:name":"Encinillas",
    "gn:population":0,
    "gn:timezone":"America/Chihuahua",
    "iso:country":"MX",
    "name:spa_x_preferred":[
        "Encinillas"
    ],
    "name:und_x_variant":[
        "Encinillos"
    ],
    "wof:name":"Encinillas",
    "wof:placetype":"locality"
},
  "geometry": {"coordinates":[-104.19029999999999,28.23494],"type":"Point"}
}