{
  "type": "Feature",
  "properties": {
    "gn:admin1_code":"19.0",
    "gn:asciiname":"Centenario",
    "gn:country_code":"MX",
    "gn:dem":444,
    "gn:feature_class":"P",
    "gn:feature_code":"PPL",
    "gn:name":"Centenario",
    "gn:population":0,
    "gn:timezone":"America/Monterrey",
    "iso:country":"MX",
    "name:spa_x_preferred":[
        "Centenario"
    ],
    "wof:name":"Centenario",
    "wof:placetype":"locality"
},
  "geometry": {"coordinates":[-100.24352,25.83366],"type":"Point"}
}