{
  "type": "Feature",
  "properties": {
    "gn:admin1_code":"18.0",
    "gn:admin2_code":"9.0",
    "gn:asciiname":"El Algodonal",
    "gn:country_code":"MX",
    "gn:dem":453,
    "gn:feature_class":"P",
    "gn:feature_code":"PPL",
    "gn:name":"El Algodonal",
    "gn:population":0,
    "gn:timezone":"America/Mazatlan",
    "iso:country":"MX",
    "name:spa_x_preferred":[
        "El Algodonal"
    ],
    "wof:name":"El Algodonal",
    "wof:placetype":"locality"
},
  "geometry": {"coordinates":[-104.46805999999999,22.3084],"type":"Point"}
}