{
  "type": "Feature",
  "properties": {
    "gn:admin1_code":"6",
    "gn:admin2_code":"31",
    "gn:asciiname":"Loya",
    "gn:country_code":"MX",
    "gn:dem":2001,
    "gn:feature_class":"P",
    "gn:feature_code":"PPL",
    "gn:name":"Loya",
    "gn:population":45,
    "gn:timezone":"America/Chihuahua",
    "iso:country":"MX",
    "name:deu_x_preferred":[
        "Loya"
    ],
    "wof:name":"Loya",
    "wof:placetype":"locality",
    "wof:population":45
},
  "geometry": {"coordinates":[-107.46467,28.60101],"type":"Point"}
}