{
  "type": "Feature",
  "properties": {
    "gn:admin1_code":"13",
    "gn:admin2_code":"37.0",
    "gn:asciiname":"Tecruz de Anahuac (Tecruz de Jihuico)",
    "gn:country_code":"MX",
    "gn:dem":1293,
    "gn:feature_class":"P",
    "gn:feature_code":"PPL",
    "gn:name":"Tecruz de An\u00e1huac (Tecruz de Jihuico)",
    "gn:population":182,
    "gn:timezone":"America/Mexico_City",
    "iso:country":"MX",
    "name:und_x_variant":[
        "Tecruz de An\u00e1huac (Tecruz de Jihuico)"
    ],
    "wof:name":"Tecruz de Anahuac (Tecruz de Jihuico)",
    "wof:placetype":"locality",
    "wof:population":182
},
  "geometry": {"coordinates":[-98.72667,20.53361],"type":"Point"}
}