{
  "type": "Feature",
  "properties": {
    "gn:admin1_code":"10",
    "gn:admin2_code":"13",
    "gn:asciiname":"El Milagro",
    "gn:country_code":"MX",
    "gn:dem":1202,
    "gn:feature_class":"P",
    "gn:feature_code":"PPL",
    "gn:name":"El Milagro",
    "gn:population":47,
    "gn:timezone":"America/Monterrey",
    "iso:country":"MX",
    "wof:name":"El Milagro",
    "wof:placetype":"locality",
    "wof:population":47
},
  "geometry": {"coordinates":[-104.15707999999999,26.67138],"type":"Point"}
}