{
  "type": "Feature",
  "properties": {
    "gn:admin1_code":"26.0",
    "gn:asciiname":"Guadalupe el Grande",
    "gn:cc2":"MX",
    "gn:country_code":"MX",
    "gn:dem":1279,
    "gn:feature_class":"P",
    "gn:feature_code":"PPL",
    "gn:name":"Guadalupe el Grande",
    "gn:population":0,
    "gn:timezone":"America/Chihuahua",
    "iso:country":"MX",
    "name:und_x_variant":[
        "Guadalupe",
        "Guadalupe el Grande"
    ],
    "wof:name":"Guadalupe el Grande",
    "wof:placetype":"locality"
},
  "geometry": {"coordinates":[-108.63333,28.85],"type":"Point"}
}