{
  "type": "Feature",
  "properties": {
    "gn:admin1_code":"21",
    "gn:admin2_code":"73",
    "gn:asciiname":"San Juanaite",
    "gn:country_code":"MX",
    "gn:dem":894,
    "gn:feature_class":"P",
    "gn:feature_code":"PPL",
    "gn:name":"San Juanaite",
    "gn:population":16,
    "gn:timezone":"America/Mexico_City",
    "iso:country":"MX",
    "wof:name":"San Juanaite",
    "wof:placetype":"locality",
    "wof:population":16
},
  "geometry": {"coordinates":[-98.75360999999999,18.38269],"type":"Point"}
}