{
  "type": "Feature",
  "properties": {
    "gn:admin1_code":"17",
    "gn:admin2_code":"32.0",
    "gn:asciiname":"Colonia Guadalupe Victoria",
    "gn:country_code":"MX",
    "gn:dem":1633,
    "gn:feature_class":"P",
    "gn:feature_code":"PPL",
    "gn:name":"Colonia Guadalupe Victoria",
    "gn:population":159,
    "gn:timezone":"America/Mexico_City",
    "iso:country":"MX",
    "wof:name":"Colonia Guadalupe Victoria",
    "wof:placetype":"locality",
    "wof:population":159
},
  "geometry": {"coordinates":[-98.77274,18.78548],"type":"Point"}
}