{
  "type": "Feature",
  "properties": {
    "gn:admin1_code":"2",
    "gn:admin2_code":"2.0",
    "gn:asciiname":"La Ponderosa",
    "gn:country_code":"MX",
    "gn:dem":6,
    "gn:feature_class":"P",
    "gn:feature_code":"PPL",
    "gn:name":"La Ponderosa",
    "gn:population":0,
    "gn:timezone":"America/Tijuana",
    "iso:country":"MX",
    "name:spa_x_preferred":[
        "La Ponderosa"
    ],
    "wof:name":"La Ponderosa",
    "wof:placetype":"locality"
},
  "geometry": {"coordinates":[-114.89077,31.14877000000001],"type":"Point"}
}