{
  "type": "Feature",
  "properties": {
    "gn:admin1_code":"5",
    "gn:admin2_code":"69",
    "gn:asciiname":"San Dieguito",
    "gn:country_code":"MX",
    "gn:dem":27,
    "gn:feature_class":"P",
    "gn:feature_code":"PPL",
    "gn:name":"San Dieguito",
    "gn:population":10,
    "gn:timezone":"America/Mexico_City",
    "iso:country":"MX",
    "wof:name":"San Dieguito",
    "wof:placetype":"locality",
    "wof:population":10
},
  "geometry": {"coordinates":[-93.31332999999999,15.71472],"type":"Point"}
}