{
  "type": "Feature",
  "properties": {
    "gn:admin1_code":"19",
    "gn:admin2_code":"49",
    "gn:asciiname":"Campestre los Mimbres",
    "gn:country_code":"MX",
    "gn:dem":572,
    "gn:feature_class":"P",
    "gn:feature_code":"PPL",
    "gn:name":"Campestre los Mimbres",
    "gn:population":31,
    "gn:timezone":"America/Monterrey",
    "iso:country":"MX",
    "wof:name":"Campestre los Mimbres",
    "wof:placetype":"locality",
    "wof:population":31
},
  "geometry": {"coordinates":[-100.20361,25.48139],"type":"Point"}
}