{
  "type": "Feature",
  "properties": {
    "gn:admin1_code":"30",
    "gn:admin2_code":"61.0",
    "gn:asciiname":"Plutarco Elias Calles",
    "gn:country_code":"MX",
    "gn:dem":445,
    "gn:feature_class":"P",
    "gn:feature_code":"PPL",
    "gn:name":"Plutarco El\u00edas Calles",
    "gn:population":284,
    "gn:timezone":"America/Mexico_City",
    "iso:country":"MX",
    "name:und_x_variant":[
        "Plutarco El\u00edas Calles"
    ],
    "wof:name":"Plutarco Elias Calles",
    "wof:placetype":"locality",
    "wof:population":284
},
  "geometry": {"coordinates":[-93.64610999999999,17.29472],"type":"Point"}
}