{
  "type": "Feature",
  "properties": {
    "gn:admin1_code":"10",
    "gn:admin2_code":"14.0",
    "gn:asciiname":"La Estancia",
    "gn:country_code":"MX",
    "gn:dem":629,
    "gn:feature_class":"P",
    "gn:feature_code":"PPL",
    "gn:name":"La Estancia",
    "gn:population":93,
    "gn:timezone":"America/Monterrey",
    "iso:country":"MX",
    "wof:name":"La Estancia",
    "wof:placetype":"locality",
    "wof:population":93
},
  "geometry": {"coordinates":[-104.48605999999999,22.58309],"type":"Point"}
}