{
  "type": "Feature",
  "properties": {
    "iso:country":"MX",
    "qs_pg:aaroncc":"MX",
    "qs_pg:name":"Grutas",
    "qs_pg:name_adm0":"M\u00e9xico",
    "qs_pg:name_adm1":"Nuevo Leon",
    "qs_pg:photos":193,
    "qs_pg:photos_1k":39,
    "qs_pg:photos_9k":1,
    "qs_pg:photos_9r":4,
    "qs_pg:photos_all":193,
    "qs_pg:photos_sr":4,
    "qs_pg:pop_sr":0,
    "qs_pg:qs_pg_placetype":"locality",
    "qs_pg:qs_pg_placetype_gp":"Town",
    "qs_pg:woe_adm0":23424900,
    "woe:adm0_id":23424900,
    "woe:name_adm0":"M\u00e9xico",
    "woe:name_adm1":"Nuevo Leon",
    "woe:placetype":"Town",
    "wof:name":"Grutas",
    "wof:placetype":"locality"
},
  "geometry": {"coordinates":[-100.52630600000001,25.853198],"type":"Point"}
}