{
  "type": "Feature",
  "properties": {
    "gn:admin1_code":"6.0",
    "gn:admin2_code":"9.0",
    "gn:asciiname":"Rancho Viejo",
    "gn:country_code":"MX",
    "gn:dem":2368,
    "gn:feature_class":"P",
    "gn:feature_code":"PPL",
    "gn:name":"Rancho Viejo",
    "gn:population":0,
    "gn:timezone":"America/Chihuahua",
    "iso:country":"MX",
    "name:spa_x_preferred":[
        "Rancho Viejo"
    ],
    "wof:name":"Rancho Viejo",
    "wof:placetype":"locality"
},
  "geometry": {"coordinates":[-107.59247999999999,27.72261],"type":"Point"}
}