{
  "type": "Feature",
  "properties": {
    "gn:admin1_code":"24",
    "gn:admin2_code":"12.0",
    "gn:asciiname":"Cuatlamayan",
    "gn:country_code":"MX",
    "gn:dem":170,
    "gn:feature_class":"P",
    "gn:feature_code":"PPL",
    "gn:name":"Cuatlamay\u00e1n",
    "gn:population":419,
    "gn:timezone":"America/Mexico_City",
    "iso:country":"MX",
    "name:und_x_variant":[
        "Cuatlamay\u00e1n"
    ],
    "wof:name":"Cuatlamayan",
    "wof:placetype":"locality",
    "wof:population":419
},
  "geometry": {"coordinates":[-98.93694000000001,21.58917000000001],"type":"Point"}
}