{
  "type": "Feature",
  "properties": {
    "gn:admin1_code":"15.0",
    "gn:admin2_code":"114.0",
    "gn:asciiname":"Barrio el Lindero",
    "gn:country_code":"MX",
    "gn:dem":2832,
    "gn:feature_class":"P",
    "gn:feature_code":"PPL",
    "gn:name":"Barrio el Lindero",
    "gn:population":0,
    "gn:timezone":"America/Mexico_City",
    "iso:country":"MX",
    "name:spa_x_preferred":[
        "Barrio el Lindero"
    ],
    "name:und_x_variant":[
        "El Lindero"
    ],
    "wof:name":"Barrio el Lindero",
    "wof:placetype":"locality"
},
  "geometry": {"coordinates":[-100.02864,19.55171],"type":"Point"}
}