{
  "type": "Feature",
  "properties": {
    "gn:admin1_code":"15.0",
    "gn:admin2_code":"123.0",
    "gn:asciiname":"El Sauz Palo Gordo",
    "gn:country_code":"MX",
    "gn:dem":902,
    "gn:feature_class":"P",
    "gn:feature_code":"PPL",
    "gn:name":"El Sauz Palo Gordo",
    "gn:population":146,
    "gn:timezone":"America/Mexico_City",
    "iso:country":"MX",
    "wof:name":"El Sauz Palo Gordo",
    "wof:placetype":"locality",
    "wof:population":146
},
  "geometry": {"coordinates":[-100.5072,18.87709],"type":"Point"}
}