{
  "type": "Feature",
  "properties": {
    "gn:admin1_code":"16.0",
    "gn:admin2_code":"26.0",
    "gn:asciiname":"El Parejo de Tejeda",
    "gn:country_code":"MX",
    "gn:dem":946,
    "gn:feature_class":"P",
    "gn:feature_code":"PPL",
    "gn:name":"El Parejo de Tejeda",
    "gn:population":0,
    "gn:timezone":"America/Mexico_City",
    "iso:country":"MX",
    "name:spa_x_preferred":[
        "El Parejo de Tejeda"
    ],
    "wof:name":"El Parejo de Tejeda",
    "wof:placetype":"locality"
},
  "geometry": {"coordinates":[-103.5033,18.75929],"type":"Point"}
}