{
  "type": "Feature",
  "properties": {
    "gn:admin1_code":"19.0",
    "gn:admin2_code":"13.0",
    "gn:asciiname":"La Lajita",
    "gn:country_code":"MX",
    "gn:dem":180,
    "gn:feature_class":"P",
    "gn:feature_code":"PPL",
    "gn:name":"La Lajita",
    "gn:population":0,
    "gn:timezone":"America/Monterrey",
    "iso:country":"MX",
    "name:spa_x_preferred":[
        "La Lajita"
    ],
    "wof:name":"La Lajita",
    "wof:placetype":"locality"
},
  "geometry": {"coordinates":[-99.25848999999999,25.56777],"type":"Point"}
}