{
  "type": "Feature",
  "properties": {
    "gn:admin1_code":"19.0",
    "gn:admin2_code":"16.0",
    "gn:asciiname":"Los Chapotes",
    "gn:country_code":"MX",
    "gn:dem":381,
    "gn:feature_class":"P",
    "gn:feature_code":"PPL",
    "gn:name":"Los Chapotes",
    "gn:population":0,
    "gn:timezone":"America/Monterrey",
    "iso:country":"MX",
    "name:spa_x_preferred":[
        "Los Chapotes"
    ],
    "wof:name":"Los Chapotes",
    "wof:placetype":"locality"
},
  "geometry": {"coordinates":[-99.95361,25.86863],"type":"Point"}
}