{
  "type": "Feature",
  "properties": {
    "gn:admin1_code":"12",
    "gn:admin2_code":"37.0",
    "gn:asciiname":"El Potrero",
    "gn:country_code":"MX",
    "gn:dem":2042,
    "gn:feature_class":"P",
    "gn:feature_code":"PPL",
    "gn:name":"El Potrero",
    "gn:population":125,
    "gn:timezone":"America/Mexico_City",
    "iso:country":"MX",
    "name:ceb_x_preferred":[
        "El Potrero"
    ],
    "name:ita_x_preferred":[
        "El Potrero"
    ],
    "name:srp_x_preferred":[
        "\u0415\u043b \u041f\u043e\u0442\u0440\u0435\u0440\u043e"
    ],
    "name:swe_x_preferred":[
        "El Potrero"
    ],
    "wof:name":"El Potrero",
    "wof:placetype":"locality",
    "wof:population":125
},
  "geometry": {"coordinates":[-99.74527999999999,18.45361],"type":"Point"}
}