{
  "type": "Feature",
  "properties": {
    "gn:admin1_code":"12",
    "gn:admin2_code":"37.0",
    "gn:asciiname":"El Potrero",
    "gn:country_code":"MX",
    "gn:dem":2042,
    "gn:feature_class":"P",
    "gn:feature_code":"PPL",
    "gn:name":"El Potrero",
    "gn:population":125,
    "gn:timezone":"America/Mexico_City",
    "iso:country":"MX",
    "wof:name":"El Potrero",
    "wof:placetype":"locality",
    "wof:population":125
},
  "geometry": {"coordinates":[-99.74527999999999,18.45361],"type":"Point"}
}