{
  "type": "Feature",
  "properties": {
    "gn:admin1_code":"21",
    "gn:admin2_code":"66.0",
    "gn:asciiname":"San Fernando",
    "gn:country_code":"MX",
    "gn:dem":1063,
    "gn:feature_class":"P",
    "gn:feature_code":"PPL",
    "gn:name":"San Fernando",
    "gn:population":7,
    "gn:timezone":"America/Mexico_City",
    "iso:country":"MX",
    "wof:name":"San Fernando",
    "wof:placetype":"locality",
    "wof:population":7
},
  "geometry": {"coordinates":[-98.16025999999999,18.06382],"type":"Point"}
}