{
  "type": "Feature",
  "properties": {
    "gn:admin1_code":"12.0",
    "gn:admin2_code":"38.0",
    "gn:asciiname":"Mata de Sandia",
    "gn:country_code":"MX",
    "gn:dem":176,
    "gn:feature_class":"P",
    "gn:feature_code":"PPL",
    "gn:name":"Mata de Sand\u00eda",
    "gn:population":88,
    "gn:timezone":"America/Mexico_City",
    "iso:country":"MX",
    "wof:name":"Mata de Sandia",
    "wof:placetype":"locality",
    "wof:population":88
},
  "geometry": {"coordinates":[-101.5497,17.67836],"type":"Point"}
}