{
  "type": "Feature",
  "properties": {
    "gn:admin1_code":"32",
    "gn:admin2_code":"34.0",
    "gn:asciiname":"Casas Grandes (Santo Domingo)",
    "gn:country_code":"MX",
    "gn:dem":2055,
    "gn:feature_class":"P",
    "gn:feature_code":"PPL",
    "gn:name":"Casas Grandes (Santo Domingo)",
    "gn:population":228,
    "gn:timezone":"America/Mexico_City",
    "iso:country":"MX",
    "wof:name":"Casas Grandes (Santo Domingo)",
    "wof:placetype":"locality",
    "wof:population":228
},
  "geometry": {"coordinates":[-102.76809,21.51976],"type":"Point"}
}