{
  "type": "Feature",
  "properties": {
    "gn:admin1_code":"19",
    "gn:admin2_code":"22.0",
    "gn:asciiname":"Tierra Dura",
    "gn:country_code":"MX",
    "gn:dem":334,
    "gn:feature_class":"P",
    "gn:feature_code":"PPL",
    "gn:name":"Tierra Dura",
    "gn:population":0,
    "gn:timezone":"America/Monterrey",
    "iso:country":"MX",
    "name:spa_x_preferred":[
        "Tierra Dura"
    ],
    "wof:name":"Tierra Dura",
    "wof:placetype":"locality"
},
  "geometry": {"coordinates":[-99.70501,25.23118],"type":"Point"}
}