{
  "type": "Feature",
  "properties": {
    "gn:admin1_code":"20",
    "gn:admin2_code":"46.0",
    "gn:asciiname":"Buenavista Jaltepec",
    "gn:country_code":"MX",
    "gn:dem":2135,
    "gn:feature_class":"P",
    "gn:feature_code":"PPL",
    "gn:name":"Buenavista Jaltepec",
    "gn:population":0,
    "gn:timezone":"America/Mexico_City",
    "iso:country":"MX",
    "name:spa_x_preferred":[
        "Buenavista"
    ],
    "name:spa_x_variant":[
        "Buenavista Jaltepec"
    ],
    "wof:name":"Buenavista Jaltepec",
    "wof:placetype":"locality"
},
  "geometry": {"coordinates":[-97.19834,17.28497999999999],"type":"Point"}
}