{
  "type": "Feature",
  "properties": {
    "gn:admin1_code":"10.0",
    "gn:admin2_code":"34.0",
    "gn:asciiname":"El Potrerito",
    "gn:country_code":"MX",
    "gn:dem":2208,
    "gn:feature_class":"P",
    "gn:feature_code":"PPL",
    "gn:name":"El Potrerito",
    "gn:population":0,
    "gn:timezone":"America/Monterrey",
    "iso:country":"MX",
    "name:spa_x_preferred":[
        "El Potrerito"
    ],
    "name:und_x_variant":[
        "El Potrero"
    ],
    "wof:name":"El Potrerito",
    "wof:placetype":"locality"
},
  "geometry": {"coordinates":[-106.95918,25.39939],"type":"Point"}
}