{
  "type": "Feature",
  "properties": {
    "gn:admin1_code":"5",
    "gn:admin2_code":"77.0",
    "gn:asciiname":"El Faro",
    "gn:country_code":"MX",
    "gn:dem":255,
    "gn:feature_class":"P",
    "gn:feature_code":"PPL",
    "gn:name":"El Faro",
    "gn:population":201,
    "gn:timezone":"America/Mexico_City",
    "iso:country":"MX",
    "wof:name":"El Faro",
    "wof:placetype":"locality",
    "wof:population":201
},
  "geometry": {"coordinates":[-92.14749999999999,17.31278],"type":"Point"}
}