{
  "type": "Feature",
  "properties": {
    "gn:admin1_code":"7.0",
    "gn:admin2_code":"19.0",
    "gn:asciiname":"Jaco Primero",
    "gn:country_code":"MX",
    "gn:dem":456,
    "gn:feature_class":"P",
    "gn:feature_code":"PPL",
    "gn:name":"Jaco Primero",
    "gn:population":0,
    "gn:timezone":"America/Monterrey",
    "iso:country":"MX",
    "name:spa_x_preferred":[
        "Jaco Primero"
    ],
    "wof:name":"Jaco Primero",
    "wof:placetype":"locality"
},
  "geometry": {"coordinates":[-101.05179,28.32339],"type":"Point"}
}