{
  "type": "Feature",
  "properties": {
    "gn:admin1_code":"10",
    "gn:admin2_code":"37.0",
    "gn:asciiname":"La Colmena",
    "gn:country_code":"MX",
    "gn:dem":1524,
    "gn:feature_class":"P",
    "gn:feature_code":"PPL",
    "gn:name":"La Colmena",
    "gn:population":5,
    "gn:timezone":"America/Monterrey",
    "iso:country":"MX",
    "name:ceb_x_preferred":[
        "La Colmena"
    ],
    "name:fra_x_preferred":[
        "La Colmena"
    ],
    "name:glg_x_preferred":[
        "La colmena"
    ],
    "name:nld_x_preferred":[
        "La colmena"
    ],
    "name:spa_x_preferred":[
        "La colmena"
    ],
    "name:swe_x_preferred":[
        "La Colmena"
    ],
    "wof:name":"La Colmena",
    "wof:placetype":"locality",
    "wof:population":5
},
  "geometry": {"coordinates":[-106.55537,25.31525],"type":"Point"}
}