{
  "type": "Feature",
  "properties": {
    "gn:admin1_code":"12.0",
    "gn:admin2_code":"48.0",
    "gn:asciiname":"Barranca de la Mona",
    "gn:country_code":"MX",
    "gn:dem":454,
    "gn:feature_class":"P",
    "gn:feature_code":"PPL",
    "gn:name":"Barranca de la Mona",
    "gn:population":0,
    "gn:timezone":"America/Mexico_City",
    "iso:country":"MX",
    "name:spa_x_preferred":[
        "Barranca de la Mona"
    ],
    "wof:name":"Barranca de la Mona",
    "wof:placetype":"locality"
},
  "geometry": {"coordinates":[-101.07741,17.5045],"type":"Point"}
}