{
  "type": "Feature",
  "properties": {
    "gn:admin1_code":"28.0",
    "gn:admin2_code":"27.0",
    "gn:asciiname":"Gustavo Diaz Ordaz",
    "gn:country_code":"MX",
    "gn:dem":132,
    "gn:feature_class":"P",
    "gn:feature_code":"PPL",
    "gn:name":"Gustavo D\u00edaz Ordaz",
    "gn:population":0,
    "gn:timezone":"America/Matamoros",
    "iso:country":"MX",
    "name:spa_x_preferred":[
        "Gustavo D\u00edaz Ordaz"
    ],
    "name:und_x_variant":[
        "La Sandia"
    ],
    "wof:name":"Gustavo Diaz Ordaz",
    "wof:placetype":"locality"
},
  "geometry": {"coordinates":[-99.55361000000001,27.46328],"type":"Point"}
}