{
  "type": "Feature",
  "properties": {
    "gn:admin1_code":"11.0",
    "gn:asciiname":"Arroyo Hondo del Fresno",
    "gn:country_code":"MX",
    "gn:dem":2092,
    "gn:feature_class":"P",
    "gn:feature_code":"PPL",
    "gn:name":"Arroyo Hondo del Fresno",
    "gn:population":0,
    "gn:timezone":"America/Mexico_City",
    "iso:country":"MX",
    "name:spa_x_preferred":[
        "Arroyo Hondo del Fresno"
    ],
    "wof:name":"Arroyo Hondo del Fresno",
    "wof:placetype":"locality"
},
  "geometry": {"coordinates":[-100.51716,20.25272],"type":"Point"}
}