{
  "type": "Feature",
  "properties": {
    "gn:admin1_code":"28",
    "gn:admin2_code":"19.0",
    "gn:asciiname":"Los Laureles",
    "gn:country_code":"MX",
    "gn:dem":178,
    "gn:feature_class":"P",
    "gn:feature_code":"PPL",
    "gn:name":"Los Laureles",
    "gn:population":9,
    "gn:timezone":"America/Monterrey",
    "iso:country":"MX",
    "name:por_x_preferred":[
        "Los Laureles"
    ],
    "name:spa_x_preferred":[
        "Los Laureles"
    ],
    "wof:name":"Los Laureles",
    "wof:placetype":"locality",
    "wof:population":9
},
  "geometry": {"coordinates":[-99.12639,23.14528],"type":"Point"}
}