{
  "type": "Feature",
  "properties": {
    "gn:admin1_code":"17",
    "gn:admin2_code":"10",
    "gn:asciiname":"Nuevo Xochimilco",
    "gn:country_code":"MX",
    "gn:dem":1391,
    "gn:feature_class":"P",
    "gn:feature_code":"PPL",
    "gn:name":"Nuevo Xochimilco",
    "gn:population":33,
    "gn:timezone":"America/Mexico_City",
    "iso:country":"MX",
    "wof:name":"Nuevo Xochimilco",
    "wof:placetype":"locality",
    "wof:population":33
},
  "geometry": {"coordinates":[-98.80028,18.70222],"type":"Point"}
}