{
  "type": "Feature",
  "properties": {
    "gn:admin1_code":"11",
    "gn:admin2_code":"22.0",
    "gn:asciiname":"Munguia",
    "gn:country_code":"MX",
    "gn:dem":2154,
    "gn:feature_class":"P",
    "gn:feature_code":"PPL",
    "gn:name":"Mungu\u00eda",
    "gn:population":0,
    "gn:timezone":"America/Mexico_City",
    "iso:country":"MX",
    "wof:name":"Munguia",
    "wof:placetype":"locality"
},
  "geometry": {"coordinates":[-101.46666999999999,21.53333],"type":"Point"}
}