{
  "type": "Feature",
  "properties": {
    "gn:admin1_code":"27",
    "gn:admin2_code":"15.0",
    "gn:asciiname":"La Raya",
    "gn:country_code":"MX",
    "gn:dem":20,
    "gn:feature_class":"P",
    "gn:feature_code":"PPL",
    "gn:name":"La Raya",
    "gn:population":0,
    "gn:timezone":"America/Mexico_City",
    "iso:country":"MX",
    "name:spa_x_preferred":[
        "La Raya Primera Secci\u00f3n"
    ],
    "name:spa_x_variant":[
        "La Raya"
    ],
    "wof:name":"La Raya",
    "wof:placetype":"locality"
},
  "geometry": {"coordinates":[-92.80325000000001,17.60819],"type":"Point"}
}