{
  "type": "Feature",
  "properties": {
    "gn:admin1_code":"30.0",
    "gn:admin2_code":"161.0",
    "gn:asciiname":"Las Conchitas",
    "gn:country_code":"MX",
    "gn:dem":66,
    "gn:feature_class":"P",
    "gn:feature_code":"PPL",
    "gn:name":"Las Conchitas",
    "gn:population":2,
    "gn:timezone":"America/Mexico_City",
    "iso:country":"MX",
    "name:spa_x_preferred":[
        "Las Conchitas"
    ],
    "wof:name":"Las Conchitas",
    "wof:placetype":"locality",
    "wof:population":2
},
  "geometry": {"coordinates":[-98.25111,21.68306],"type":"Point"}
}