{
  "type": "Feature",
  "properties": {
    "gn:admin1_code":"14.0",
    "gn:asciiname":"Mesa de Palos Colorados",
    "gn:country_code":"MX",
    "gn:dem":2002,
    "gn:feature_class":"P",
    "gn:feature_code":"PPL",
    "gn:name":"Mesa de Palos Colorados",
    "gn:population":0,
    "gn:timezone":"America/Mexico_City",
    "iso:country":"MX",
    "name:spa_x_preferred":[
        "Mesa de Palos Colorados"
    ],
    "wof:name":"Mesa de Palos Colorados",
    "wof:placetype":"locality"
},
  "geometry": {"coordinates":[-102.15387,20.86985],"type":"Point"}
}