{
  "type": "Feature",
  "properties": {
    "gn:admin1_code":"24",
    "gn:admin2_code":"46.0",
    "gn:asciiname":"Colonia los Manueles",
    "gn:country_code":"MX",
    "gn:dem":2223,
    "gn:feature_class":"P",
    "gn:feature_code":"PPL",
    "gn:name":"Colonia los Manueles",
    "gn:population":205,
    "gn:timezone":"America/Mexico_City",
    "iso:country":"MX",
    "wof:name":"Colonia los Manueles",
    "wof:placetype":"locality",
    "wof:population":205
},
  "geometry": {"coordinates":[-101.32944000000001,21.87583],"type":"Point"}
}