{
  "type": "Feature",
  "properties": {
    "gn:admin1_code":"7",
    "gn:admin2_code":"35.0",
    "gn:asciiname":"Los Garcia",
    "gn:country_code":"MX",
    "gn:dem":1240,
    "gn:feature_class":"P",
    "gn:feature_code":"PPL",
    "gn:name":"Los Garc\u00eda",
    "gn:population":0,
    "gn:timezone":"America/Monterrey",
    "iso:country":"MX",
    "name:spa_x_preferred":[
        "Los Garc\u00eda"
    ],
    "wof:name":"Los Garcia",
    "wof:placetype":"locality"
},
  "geometry": {"coordinates":[-103.39819,25.17003],"type":"Point"}
}