{
  "type": "Feature",
  "properties": {
    "gn:admin1_code":"3.0",
    "gn:admin2_code":"3.0",
    "gn:asciiname":"El Cajete",
    "gn:country_code":"MX",
    "gn:dem":2,
    "gn:feature_class":"P",
    "gn:feature_code":"PPL",
    "gn:name":"El Cajete",
    "gn:population":0,
    "gn:timezone":"America/Mazatlan",
    "iso:country":"MX",
    "name:spa_x_preferred":[
        "El Cajete"
    ],
    "wof:name":"El Cajete",
    "wof:placetype":"locality"
},
  "geometry": {"coordinates":[-110.60850000000001,24.25156],"type":"Point"}
}