{
  "type": "Feature",
  "properties": {
    "gn:admin1_code":"12",
    "gn:admin2_code":"81.0",
    "gn:asciiname":"13 de Septiembre",
    "gn:country_code":"MX",
    "gn:dem":1481,
    "gn:feature_class":"P",
    "gn:feature_code":"PPL",
    "gn:name":"13 de Septiembre",
    "gn:population":114,
    "gn:timezone":"America/Mexico_City",
    "iso:country":"MX",
    "wof:name":"13 de Septiembre",
    "wof:placetype":"locality",
    "wof:population":114
},
  "geometry": {"coordinates":[-98.71332,17.0482],"type":"Point"}
}