{
  "type": "Feature",
  "properties": {
    "gn:admin1_code":"14",
    "gn:admin2_code":"1.0",
    "gn:asciiname":"Tierras Coloradas",
    "gn:country_code":"MX",
    "gn:dem":1767,
    "gn:feature_class":"P",
    "gn:feature_code":"PPL",
    "gn:name":"Tierras Coloradas",
    "gn:population":1546,
    "gn:timezone":"America/Mexico_City",
    "iso:country":"MX",
    "wof:name":"Tierras Coloradas",
    "wof:placetype":"locality",
    "wof:population":1546
},
  "geometry": {"coordinates":[-102.86083000000001,20.72889],"type":"Point"}
}