{
  "type": "Feature",
  "properties": {
    "gn:admin1_code":"15",
    "gn:admin2_code":"50.0",
    "gn:asciiname":"Barrio Santa Rosa de Lima",
    "gn:country_code":"MX",
    "gn:dem":2483,
    "gn:feature_class":"P",
    "gn:feature_code":"PPL",
    "gn:name":"Barrio Santa Rosa de Lima",
    "gn:population":122,
    "gn:timezone":"America/Mexico_City",
    "iso:country":"MX",
    "wof:name":"Barrio Santa Rosa de Lima",
    "wof:placetype":"locality",
    "wof:population":122
},
  "geometry": {"coordinates":[-98.84505,19.07913],"type":"Point"}
}