{
  "type": "Feature",
  "properties": {
    "gn:admin1_code":"13",
    "gn:admin2_code":"30.0",
    "gn:asciiname":"La Heredad",
    "gn:country_code":"MX",
    "gn:dem":1696,
    "gn:feature_class":"P",
    "gn:feature_code":"PPL",
    "gn:name":"La Heredad",
    "gn:population":0,
    "gn:timezone":"America/Mexico_City",
    "iso:country":"MX",
    "name:spa_x_preferred":[
        "La Heredad"
    ],
    "name:und_x_variant":[
        "El Salitre"
    ],
    "wof:name":"La Heredad",
    "wof:placetype":"locality"
},
  "geometry": {"coordinates":[-99.2319,20.51302],"type":"Point"}
}