{
  "type": "Feature",
  "properties": {
    "gn:admin1_code":"6",
    "gn:admin2_code":"29",
    "gn:asciiname":"El Puerto del Riito",
    "gn:country_code":"MX",
    "gn:dem":2083,
    "gn:feature_class":"P",
    "gn:feature_code":"PPL",
    "gn:name":"El Puerto del Ri\u00edto",
    "gn:population":50,
    "gn:timezone":"America/Chihuahua",
    "iso:country":"MX",
    "name:und_x_variant":[
        "El Puerto del Ri\u00edto"
    ],
    "wof:name":"El Puerto del Riito",
    "wof:placetype":"locality",
    "wof:population":50
},
  "geometry": {"coordinates":[-107.26291999999999,26.31273],"type":"Point"}
}