{
  "type": "Feature",
  "properties": {
    "gn:admin1_code":"13",
    "gn:admin2_code":"64.0",
    "gn:asciiname":"Bugambilia",
    "gn:country_code":"MX",
    "gn:dem":2046,
    "gn:feature_class":"P",
    "gn:feature_code":"PPL",
    "gn:name":"Bugambilia",
    "gn:population":0,
    "gn:timezone":"America/Mexico_City",
    "iso:country":"MX",
    "name:spa_x_preferred":[
        "Bugambilia"
    ],
    "wof:name":"Bugambilia",
    "wof:placetype":"locality"
},
  "geometry": {"coordinates":[-99.35109,20.13285],"type":"Point"}
}