{
  "type": "Feature",
  "properties": {
    "gn:admin1_code":"25",
    "gn:admin2_code":"18",
    "gn:asciiname":"Campillo Veronica (Campo Ingenio)",
    "gn:country_code":"MX",
    "gn:dem":10,
    "gn:feature_class":"P",
    "gn:feature_code":"PPL",
    "gn:name":"Campillo Ver\u00f3nica (Campo Ingenio)",
    "gn:population":21,
    "gn:timezone":"America/Mazatlan",
    "iso:country":"MX",
    "name:und_x_variant":[
        "Campillo Ver\u00f3nica (Campo Ingenio)"
    ],
    "wof:name":"Campillo Veronica (Campo Ingenio)",
    "wof:placetype":"locality",
    "wof:population":21
},
  "geometry": {"coordinates":[-107.68778,24.74639],"type":"Point"}
}