{
  "type": "Feature",
  "properties": {
    "gn:admin1_code":"5.0",
    "gn:admin2_code":"82.0",
    "gn:asciiname":"El Anhelo",
    "gn:country_code":"MX",
    "gn:dem":1323,
    "gn:feature_class":"P",
    "gn:feature_code":"PPL",
    "gn:name":"El Anhelo",
    "gn:population":0,
    "gn:timezone":"America/Mexico_City",
    "iso:country":"MX",
    "name:spa_x_preferred":[
        "El Anhelo"
    ],
    "wof:name":"El Anhelo",
    "wof:placetype":"locality"
},
  "geometry": {"coordinates":[-92.32584,17.04208],"type":"Point"}
}