{
  "type": "Feature",
  "properties": {
    "gn:admin1_code":"12",
    "gn:admin2_code":"23.0",
    "gn:asciiname":"Rancho Javier Mendoza Anorve",
    "gn:country_code":"MX",
    "gn:dem":28,
    "gn:feature_class":"P",
    "gn:feature_code":"PPL",
    "gn:name":"Rancho Javier Mendoza A\u00f1orve",
    "gn:population":5,
    "gn:timezone":"America/Mexico_City",
    "iso:country":"MX",
    "name:und_x_variant":[
        "Rancho Javier Mendoza A\u00f1orve"
    ],
    "wof:name":"Rancho Javier Mendoza Anorve",
    "wof:placetype":"locality",
    "wof:population":5
},
  "geometry": {"coordinates":[-98.47649,16.54761],"type":"Point"}
}