{
  "type": "Feature",
  "properties": {
    "gn:admin1_code":"26.0",
    "gn:admin2_code":"11.0",
    "gn:asciiname":"Bajio Quemado",
    "gn:country_code":"MX",
    "gn:dem":1146,
    "gn:feature_class":"P",
    "gn:feature_code":"PPL",
    "gn:name":"Baj\u00edo Quemado",
    "gn:population":0,
    "gn:timezone":"America/Hermosillo",
    "iso:country":"MX",
    "name:spa_x_preferred":[
        "Baj\u00edo Quemado"
    ],
    "wof:name":"Bajio Quemado",
    "wof:placetype":"locality"
},
  "geometry": {"coordinates":[-109.86833,30.61611],"type":"Point"}
}