{
  "type": "Feature",
  "properties": {
    "gn:admin1_code":"6",
    "gn:admin2_code":"29.0",
    "gn:asciiname":"Los Tarros",
    "gn:country_code":"MX",
    "gn:dem":2464,
    "gn:feature_class":"P",
    "gn:feature_code":"PPL",
    "gn:name":"Los Tarros",
    "gn:population":0,
    "gn:timezone":"America/Chihuahua",
    "iso:country":"MX",
    "name:und_x_variant":[
        "Tarros",
        "Los Tarros"
    ],
    "wof:name":"Los Tarros",
    "wof:placetype":"locality"
},
  "geometry": {"coordinates":[-107.17838,26.33633],"type":"Point"}
}