{
  "type": "Feature",
  "properties": {
    "gn:admin1_code":"6.0",
    "gn:admin2_code":"9.0",
    "gn:asciiname":"Rochivo",
    "gn:country_code":"MX",
    "gn:dem":2361,
    "gn:feature_class":"P",
    "gn:feature_code":"PPL",
    "gn:name":"Rochivo",
    "gn:population":330,
    "gn:timezone":"America/Chihuahua",
    "iso:country":"MX",
    "wof:name":"Rochivo",
    "wof:placetype":"locality",
    "wof:population":330
},
  "geometry": {"coordinates":[-107.64694,27.76444],"type":"Point"}
}