{
  "type": "Feature",
  "properties": {
    "gn:admin1_code":"12.0",
    "gn:admin2_code":"3.0",
    "gn:asciiname":"Arroyo Frio",
    "gn:country_code":"MX",
    "gn:dem":2002,
    "gn:feature_class":"P",
    "gn:feature_code":"PPL",
    "gn:name":"Arroyo Fr\u00edo",
    "gn:population":0,
    "gn:timezone":"America/Mexico_City",
    "iso:country":"MX",
    "name:spa_x_preferred":[
        "Arroyo Fr\u00edo"
    ],
    "wof:name":"Arroyo Frio",
    "wof:placetype":"locality"
},
  "geometry": {"coordinates":[-100.68259999999999,17.67806000000001],"type":"Point"}
}