{
  "type": "Feature",
  "properties": {
    "gn:admin1_code":"20",
    "gn:admin2_code":"264.0",
    "gn:asciiname":"Yucuyuchi",
    "gn:country_code":"MX",
    "gn:dem":2396,
    "gn:feature_class":"P",
    "gn:feature_code":"PPL",
    "gn:name":"Yucuyuchi",
    "gn:population":78,
    "gn:timezone":"America/Mexico_City",
    "iso:country":"MX",
    "wof:name":"Yucuyuchi",
    "wof:placetype":"locality",
    "wof:population":78
},
  "geometry": {"coordinates":[-97.19528,17.59806],"type":"Point"}
}