{
  "type": "Feature",
  "properties": {
    "gn:admin1_code":"4",
    "gn:admin2_code":"11",
    "gn:asciiname":"Tres de Mayo Dos",
    "gn:country_code":"MX",
    "gn:dem":95,
    "gn:feature_class":"P",
    "gn:feature_code":"PPL",
    "gn:name":"Tres de Mayo Dos",
    "gn:population":37,
    "gn:timezone":"America/Merida",
    "iso:country":"MX",
    "wof:name":"Tres de Mayo Dos",
    "wof:placetype":"locality",
    "wof:population":37
},
  "geometry": {"coordinates":[-90.46194,18.02833],"type":"Point"}
}