{
  "type": "Feature",
  "properties": {
    "gn:admin1_code":"12.0",
    "gn:admin2_code":"14.0",
    "gn:asciiname":"Monte Alto",
    "gn:country_code":"MX",
    "gn:dem":15,
    "gn:feature_class":"P",
    "gn:feature_code":"PPL",
    "gn:name":"Monte Alto",
    "gn:population":0,
    "gn:timezone":"America/Mexico_City",
    "iso:country":"MX",
    "name:spa_x_preferred":[
        "Monte Alto"
    ],
    "wof:name":"Monte Alto",
    "wof:placetype":"locality"
},
  "geometry": {"coordinates":[-100.52012000000001,17.15673],"type":"Point"}
}