{
  "type": "Feature",
  "properties": {
    "gn:admin1_code":"14.0",
    "gn:admin2_code":"113.0",
    "gn:asciiname":"Jiquilpan",
    "gn:country_code":"MX",
    "gn:dem":1301,
    "gn:feature_class":"P",
    "gn:feature_code":"PPL",
    "gn:name":"Jiquilpan",
    "gn:population":0,
    "gn:timezone":"America/Mexico_City",
    "iso:country":"MX",
    "name:spa_x_preferred":[
        "Jiquilpan"
    ],
    "wof:name":"Jiquilpan",
    "wof:placetype":"locality"
},
  "geometry": {"coordinates":[-103.77894999999999,19.77889],"type":"Point"}
}