{
  "type": "Feature",
  "properties": {
    "gn:admin1_code":"26",
    "gn:admin2_code":"17",
    "gn:asciiname":"Ejido Martires de Cananea",
    "gn:country_code":"MX",
    "gn:dem":51,
    "gn:feature_class":"P",
    "gn:feature_code":"PPL",
    "gn:name":"Ejido M\u00e1rtires de Cananea",
    "gn:population":11,
    "gn:timezone":"America/Hermosillo",
    "iso:country":"MX",
    "name:und_x_variant":[
        "Ejido M\u00e1rtires de Cananea"
    ],
    "wof:name":"Ejido Martires de Cananea",
    "wof:placetype":"locality",
    "wof:population":11
},
  "geometry": {"coordinates":[-112.85972,30.90833],"type":"Point"}
}