{
  "type": "Feature",
  "properties": {
    "gn:admin1_code":"19",
    "gn:admin2_code":"22.0",
    "gn:asciiname":"Cruz Verde",
    "gn:country_code":"MX",
    "gn:dem":253,
    "gn:feature_class":"P",
    "gn:feature_code":"PPL",
    "gn:name":"Cruz Verde",
    "gn:population":0,
    "gn:timezone":"America/Monterrey",
    "iso:country":"MX",
    "name:spa_x_preferred":[
        "Cruz Verde"
    ],
    "wof:name":"Cruz Verde",
    "wof:placetype":"locality"
},
  "geometry": {"coordinates":[-99.32791,25.39667],"type":"Point"}
}