{
  "type": "Feature",
  "properties": {
    "gn:admin1_code":"3",
    "gn:admin2_code":"3.0",
    "gn:asciiname":"Colonia Pitaya Secciones 1, 2 y 4",
    "gn:country_code":"MX",
    "gn:dem":43,
    "gn:feature_class":"P",
    "gn:feature_code":"PPL",
    "gn:name":"Colonia Pitaya Secciones 1, 2 y 4",
    "gn:population":324,
    "gn:timezone":"America/Mazatlan",
    "iso:country":"MX",
    "wof:name":"Colonia Pitaya Secciones 1, 2 y 4",
    "wof:placetype":"locality",
    "wof:population":324
},
  "geometry": {"coordinates":[-110.32193999999998,24.07194],"type":"Point"}
}