{
  "type": "Feature",
  "properties": {
    "gn:admin1_code":"21",
    "gn:admin2_code":"166",
    "gn:asciiname":"Caja de Agua",
    "gn:country_code":"MX",
    "gn:dem":1455,
    "gn:feature_class":"P",
    "gn:feature_code":"PPL",
    "gn:name":"Caja de Agua",
    "gn:population":45,
    "gn:timezone":"America/Mexico_City",
    "iso:country":"MX",
    "wof:name":"Caja de Agua",
    "wof:placetype":"locality",
    "wof:population":45
},
  "geometry": {"coordinates":[-98.4447,18.70017],"type":"Point"}
}