{
  "type": "Feature",
  "properties": {
    "gn:admin1_code":"17",
    "gn:admin2_code":"11.0",
    "gn:asciiname":"Cerro de la Corona",
    "gn:country_code":"MX",
    "gn:dem":1608,
    "gn:feature_class":"P",
    "gn:feature_code":"PPL",
    "gn:name":"Cerro de la Corona",
    "gn:population":191,
    "gn:timezone":"America/Mexico_City",
    "iso:country":"MX",
    "wof:name":"Cerro de la Corona",
    "wof:placetype":"locality",
    "wof:population":191
},
  "geometry": {"coordinates":[-99.13167,18.88194],"type":"Point"}
}