{
  "type": "Feature",
  "properties": {
    "gn:admin1_code":"25",
    "gn:admin2_code":"4.0",
    "gn:asciiname":"Santa Rita",
    "gn:country_code":"MX",
    "gn:dem":1656,
    "gn:feature_class":"P",
    "gn:feature_code":"PPL",
    "gn:name":"Santa Rita",
    "gn:population":84,
    "gn:timezone":"America/Mazatlan",
    "iso:country":"MX",
    "wof:name":"Santa Rita",
    "wof:placetype":"locality",
    "wof:population":84
},
  "geometry": {"coordinates":[-105.83434,23.45839],"type":"Point"}
}