{
  "type": "Feature",
  "properties": {
    "gn:admin1_code":"14",
    "gn:admin2_code":"48.0",
    "gn:asciiname":"Los Ojos de Agua",
    "gn:country_code":"MX",
    "gn:dem":1773,
    "gn:feature_class":"P",
    "gn:feature_code":"PPL",
    "gn:name":"Los Ojos de Agua",
    "gn:population":8,
    "gn:timezone":"America/Mexico_City",
    "iso:country":"MX",
    "wof:name":"Los Ojos de Agua",
    "wof:placetype":"locality",
    "wof:population":8
},
  "geometry": {"coordinates":[-102.21944000000001,20.55222],"type":"Point"}
}