{
  "type": "Feature",
  "properties": {
    "gn:admin1_code":"20",
    "gn:admin2_code":"105.0",
    "gn:asciiname":"San Jose Monteverde",
    "gn:country_code":"MX",
    "gn:dem":2576,
    "gn:feature_class":"P",
    "gn:feature_code":"PPL",
    "gn:name":"San Jos\u00e9 Monteverde",
    "gn:population":737,
    "gn:timezone":"America/Mexico_City",
    "iso:country":"MX",
    "name:und_x_variant":[
        "San Jos\u00e9 Monteverde"
    ],
    "wof:name":"San Jose Monteverde",
    "wof:placetype":"locality",
    "wof:population":737
},
  "geometry": {"coordinates":[-97.72444,17.49361],"type":"Point"}
}