{
  "type": "Feature",
  "properties": {
    "gn:admin1_code":"26.0",
    "gn:admin2_code":"51.0",
    "gn:asciiname":"El Terrero",
    "gn:country_code":"MX",
    "gn:dem":568,
    "gn:feature_class":"P",
    "gn:feature_code":"PPL",
    "gn:name":"El Terrero",
    "gn:population":0,
    "gn:timezone":"America/Hermosillo",
    "iso:country":"MX",
    "wof:name":"El Terrero",
    "wof:placetype":"locality"
},
  "geometry": {"coordinates":[-109.26667,28.15],"type":"Point"}
}