{
  "type": "Feature",
  "properties": {
    "gn:admin1_code":"4.0",
    "gn:asciiname":"La Guadalupe",
    "gn:country_code":"MX",
    "gn:dem":42,
    "gn:feature_class":"P",
    "gn:feature_code":"PPL",
    "gn:name":"La Guadalupe",
    "gn:population":0,
    "gn:timezone":"America/Merida",
    "iso:country":"MX",
    "name:spa_x_preferred":[
        "La Guadalupe"
    ],
    "wof:name":"La Guadalupe",
    "wof:placetype":"locality"
},
  "geometry": {"coordinates":[-90.86433,18.829],"type":"Point"}
}