{
  "type": "Feature",
  "properties": {
    "gn:admin1_code":"30",
    "gn:admin2_code":"175",
    "gn:asciiname":"Entrada a Campo Diez",
    "gn:country_code":"MX",
    "gn:dem":59,
    "gn:feature_class":"P",
    "gn:feature_code":"PPL",
    "gn:name":"Entrada a Campo Diez",
    "gn:population":46,
    "gn:timezone":"America/Mexico_City",
    "iso:country":"MX",
    "wof:name":"Entrada a Campo Diez",
    "wof:placetype":"locality",
    "wof:population":46
},
  "geometry": {"coordinates":[-97.46972,20.55694],"type":"Point"}
}