{
  "type": "Feature",
  "properties": {
    "gn:admin1_code":"7",
    "gn:admin2_code":"23.0",
    "gn:asciiname":"Suenam",
    "gn:country_code":"MX",
    "gn:dem":1035,
    "gn:feature_class":"P",
    "gn:feature_code":"PPL",
    "gn:name":"Suenam",
    "gn:population":0,
    "gn:timezone":"America/Monterrey",
    "iso:country":"MX",
    "wof:name":"Suenam",
    "wof:placetype":"locality"
},
  "geometry": {"coordinates":[-103.03333000000001,28.88333],"type":"Point"}
}