{
  "type": "Feature",
  "properties": {
    "gn:admin1_code":"30",
    "gn:admin2_code":"61.0",
    "gn:asciiname":"El Castano",
    "gn:country_code":"MX",
    "gn:dem":49,
    "gn:feature_class":"P",
    "gn:feature_code":"PPL",
    "gn:name":"El Casta\u00f1o",
    "gn:population":69,
    "gn:timezone":"America/Mexico_City",
    "iso:country":"MX",
    "name:und_x_variant":[
        "El Casta\u00f1o"
    ],
    "wof:name":"El Castano",
    "wof:placetype":"locality",
    "wof:population":69
},
  "geometry": {"coordinates":[-93.90582999999999,17.64917],"type":"Point"}
}