{
  "type": "Feature",
  "properties": {
    "gn:admin1_code":"6",
    "gn:admin2_code":"29.0",
    "gn:asciiname":"Norato",
    "gn:country_code":"MX",
    "gn:dem":1511,
    "gn:feature_class":"P",
    "gn:feature_code":"PPL",
    "gn:name":"Norato",
    "gn:population":0,
    "gn:timezone":"America/Chihuahua",
    "iso:country":"MX",
    "name:spa_x_preferred":[
        "Norato"
    ],
    "wof:name":"Norato",
    "wof:placetype":"locality"
},
  "geometry": {"coordinates":[-107.44217,26.22117],"type":"Point"}
}