{
  "type": "Feature",
  "properties": {
    "gn:admin1_code":"20",
    "gn:admin2_code":"482.0",
    "gn:asciiname":"Tamarindo",
    "gn:country_code":"MX",
    "gn:dem":92,
    "gn:feature_class":"P",
    "gn:feature_code":"PPL",
    "gn:name":"Tamarindo",
    "gn:population":0,
    "gn:timezone":"America/Mexico_City",
    "iso:country":"MX",
    "wof:name":"Tamarindo",
    "wof:placetype":"locality"
},
  "geometry": {"coordinates":[-98.02370000000001,16.28761],"type":"Point"}
}