{
  "type": "Feature",
  "properties": {
    "gn:admin1_code":"2.0",
    "gn:admin2_code":"1.0",
    "gn:asciiname":"Muelle Viejo",
    "gn:country_code":"MX",
    "gn:dem":5,
    "gn:feature_class":"P",
    "gn:feature_code":"PPL",
    "gn:name":"Muelle Viejo",
    "gn:population":5,
    "gn:timezone":"America/Tijuana",
    "iso:country":"MX",
    "name:spa_x_preferred":[
        "Muelle Viejo"
    ],
    "wof:name":"Muelle Viejo",
    "wof:placetype":"locality",
    "wof:population":5
},
  "geometry": {"coordinates":[-115.95833,30.47583],"type":"Point"}
}