{
  "type": "Feature",
  "properties": {
    "gn:admin1_code":"21",
    "gn:admin2_code":"92.0",
    "gn:asciiname":"Panuncio Ramirez Sanchez",
    "gn:country_code":"MX",
    "gn:dem":2115,
    "gn:feature_class":"P",
    "gn:feature_code":"PPL",
    "gn:name":"Panuncio Ram\u00edrez S\u00e1nchez",
    "gn:population":9,
    "gn:timezone":"America/Mexico_City",
    "iso:country":"MX",
    "name:und_x_variant":[
        "Panuncio Ram\u00edrez S\u00e1nchez"
    ],
    "wof:name":"Panuncio Ramirez Sanchez",
    "wof:placetype":"locality",
    "wof:population":9
},
  "geometry": {"coordinates":[-97.68162,18.51684],"type":"Point"}
}