{
  "type": "Feature",
  "properties": {
    "gn:admin1_code":"26.0",
    "gn:admin2_code":"47.0",
    "gn:asciiname":"El Datil",
    "gn:cc2":"MX",
    "gn:country_code":"MX",
    "gn:dem":495,
    "gn:feature_class":"P",
    "gn:feature_code":"PPL",
    "gn:name":"El D\u00e1til",
    "gn:population":0,
    "gn:timezone":"America/Hermosillo",
    "iso:country":"MX",
    "name:und_x_variant":[
        "Pozos del D\u00e1til",
        "El D\u00e1til"
    ],
    "wof:name":"El Datil",
    "wof:placetype":"locality"
},
  "geometry": {"coordinates":[-112.25,30.11667000000001],"type":"Point"}
}