{
  "type": "Feature",
  "properties": {
    "gn:admin1_code":"30.0",
    "gn:admin2_code":"40.0",
    "gn:asciiname":"El Nueve",
    "gn:country_code":"MX",
    "gn:dem":180,
    "gn:feature_class":"P",
    "gn:feature_code":"PPL",
    "gn:name":"El Nueve",
    "gn:population":0,
    "gn:timezone":"America/Mexico_City",
    "iso:country":"MX",
    "name:spa_x_preferred":[
        "El Nueve"
    ],
    "wof:name":"El Nueve",
    "wof:placetype":"locality"
},
  "geometry": {"coordinates":[-97.58638999999999,20.45306],"type":"Point"}
}