{
  "type": "Feature",
  "properties": {
    "gn:admin1_code":"10",
    "gn:admin2_code":"4.0",
    "gn:asciiname":"Doce de Diciembre",
    "gn:country_code":"MX",
    "gn:dem":1942,
    "gn:feature_class":"P",
    "gn:feature_code":"PPL",
    "gn:name":"Doce de Diciembre",
    "gn:population":0,
    "gn:timezone":"America/Monterrey",
    "iso:country":"MX",
    "name:spa_x_preferred":[
        "Sombreretillo"
    ],
    "name:und_x_variant":[
        "Sombreretillos",
        "Doce de Diciembre"
    ],
    "wof:name":"Doce de Diciembre",
    "wof:placetype":"locality"
},
  "geometry": {"coordinates":[-103.5714,24.70757],"type":"Point"}
}