{
  "type": "Feature",
  "properties": {
    "gn:admin1_code":"28",
    "gn:admin2_code":"32.0",
    "gn:asciiname":"El Ausente",
    "gn:country_code":"MX",
    "gn:dem":43,
    "gn:feature_class":"P",
    "gn:feature_code":"PPL",
    "gn:name":"El Ausente",
    "gn:population":5,
    "gn:timezone":"America/Matamoros",
    "iso:country":"MX",
    "wof:name":"El Ausente",
    "wof:placetype":"locality",
    "wof:population":5
},
  "geometry": {"coordinates":[-98.51139000000001,26.21056],"type":"Point"}
}