{
  "type": "Feature",
  "properties": {
    "gn:admin1_code":"6",
    "gn:admin2_code":"30",
    "gn:asciiname":"La Tinaja",
    "gn:country_code":"MX",
    "gn:dem":1491,
    "gn:feature_class":"P",
    "gn:feature_code":"PPL",
    "gn:name":"La Tinaja",
    "gn:population":9,
    "gn:timezone":"America/Chihuahua",
    "iso:country":"MX",
    "wof:name":"La Tinaja",
    "wof:placetype":"locality",
    "wof:population":9
},
  "geometry": {"coordinates":[-108.19154,27.42764],"type":"Point"}
}