{
  "type": "Feature",
  "properties": {
    "gn:admin1_code":"11.0",
    "gn:asciiname":"San Ramon de los Patios",
    "gn:country_code":"MX",
    "gn:dem":1733,
    "gn:feature_class":"P",
    "gn:feature_code":"PPL",
    "gn:name":"San Ram\u00f3n de los Patios",
    "gn:population":0,
    "gn:timezone":"America/Mexico_City",
    "iso:country":"MX",
    "name:spa_x_preferred":[
        "San Ram\u00f3n de los Patios"
    ],
    "wof:name":"San Ramon de los Patios",
    "wof:placetype":"locality"
},
  "geometry": {"coordinates":[-101.30768,20.47672],"type":"Point"}
}