{
  "type": "Feature",
  "properties": {
    "gn:admin1_code":"3",
    "gn:admin2_code":"3.0",
    "gn:asciiname":"Rosy [Restaurante]",
    "gn:country_code":"MX",
    "gn:dem":73,
    "gn:feature_class":"P",
    "gn:feature_code":"PPL",
    "gn:name":"Rosy [Restaurante]",
    "gn:population":8,
    "gn:timezone":"America/Mazatlan",
    "iso:country":"MX",
    "wof:name":"Rosy [Restaurante]",
    "wof:placetype":"locality",
    "wof:population":8
},
  "geometry": {"coordinates":[-111.11915,24.40251],"type":"Point"}
}