{
  "type": "Feature",
  "properties": {
    "gn:admin1_code":"7.0",
    "gn:admin2_code":"13.0",
    "gn:asciiname":"Rancho Nuevo",
    "gn:country_code":"MX",
    "gn:dem":166,
    "gn:feature_class":"P",
    "gn:feature_code":"PPL",
    "gn:name":"Rancho Nuevo",
    "gn:population":3,
    "gn:timezone":"America/Monterrey",
    "iso:country":"MX",
    "name:spa_x_preferred":[
        "Rancho Nuevo"
    ],
    "wof:name":"Rancho Nuevo",
    "wof:placetype":"locality",
    "wof:population":3
},
  "geometry": {"coordinates":[-100.02006,28.04138],"type":"Point"}
}