{
  "type": "Feature",
  "properties": {
    "gn:admin1_code":"26",
    "gn:admin2_code":"30",
    "gn:asciiname":"El Mezquital del Oro (El Aguila)",
    "gn:country_code":"MX",
    "gn:dem":159,
    "gn:feature_class":"P",
    "gn:feature_code":"PPL",
    "gn:name":"El Mezquital del Oro (El \u00c1guila)",
    "gn:population":19,
    "gn:timezone":"America/Hermosillo",
    "iso:country":"MX",
    "name:und_x_variant":[
        "El Mezquital del Oro (El \u00c1guila)"
    ],
    "wof:name":"El Mezquital del Oro (El Aguila)",
    "wof:placetype":"locality",
    "wof:population":19
},
  "geometry": {"coordinates":[-111.14888999999999,29.03056],"type":"Point"}
}