{
  "type": "Feature",
  "properties": {
    "gn:admin1_code":"19",
    "gn:admin2_code":"32.0",
    "gn:asciiname":"Rancho La Represa",
    "gn:country_code":"MX",
    "gn:dem":299,
    "gn:feature_class":"P",
    "gn:feature_code":"PPL",
    "gn:name":"Rancho La Represa",
    "gn:population":0,
    "gn:timezone":"America/Monterrey",
    "iso:country":"MX",
    "wof:name":"Rancho La Represa",
    "wof:placetype":"locality"
},
  "geometry": {"coordinates":[-100.65000000000001,27.11667000000001],"type":"Point"}
}