{
  "type": "Feature",
  "properties": {
    "gn:admin1_code":"31",
    "gn:admin2_code":"96.0",
    "gn:asciiname":"La Mosita",
    "gn:country_code":"MX",
    "gn:dem":11,
    "gn:feature_class":"P",
    "gn:feature_code":"PPL",
    "gn:name":"La Mosita",
    "gn:population":0,
    "gn:timezone":"America/Merida",
    "iso:country":"MX",
    "name:spa_x_preferred":[
        "La Mosita"
    ],
    "wof:name":"La Mosita",
    "wof:placetype":"locality"
},
  "geometry": {"coordinates":[-87.74069,21.26657],"type":"Point"}
}