{
  "type": "Feature",
  "properties": {
    "gn:admin1_code":"5",
    "gn:admin2_code":"46.0",
    "gn:asciiname":"Hierba Santa",
    "gn:country_code":"MX",
    "gn:dem":846,
    "gn:feature_class":"P",
    "gn:feature_code":"PPL",
    "gn:name":"Hierba Santa",
    "gn:population":438,
    "gn:timezone":"America/Mexico_City",
    "iso:country":"MX",
    "wof:name":"Hierba Santa",
    "wof:placetype":"locality",
    "wof:population":438
},
  "geometry": {"coordinates":[-93.57472,16.73556],"type":"Point"}
}