{
  "type": "Feature",
  "properties": {
    "gn:admin1_code":"4.0",
    "gn:admin2_code":"3.0",
    "gn:asciiname":"El Xabin",
    "gn:country_code":"MX",
    "gn:dem":18,
    "gn:feature_class":"P",
    "gn:feature_code":"PPL",
    "gn:name":"El Xab\u00edn",
    "gn:population":0,
    "gn:timezone":"America/Merida",
    "iso:country":"MX",
    "name:spa_x_preferred":[
        "El Xab\u00edn"
    ],
    "wof:name":"El Xabin",
    "wof:placetype":"locality"
},
  "geometry": {"coordinates":[-91.14462,18.45386],"type":"Point"}
}