{
  "type": "Feature",
  "properties": {
    "gn:admin1_code":"12",
    "gn:admin2_code":"73",
    "gn:asciiname":"Corutzen (Corucen)",
    "gn:country_code":"MX",
    "gn:dem":414,
    "gn:feature_class":"P",
    "gn:feature_code":"PPL",
    "gn:name":"Corutz\u00e9n (Coruc\u00e9n)",
    "gn:population":49,
    "gn:timezone":"America/Mexico_City",
    "iso:country":"MX",
    "name:und_x_variant":[
        "Corutz\u00e9n (Coruc\u00e9n)"
    ],
    "wof:name":"Corutzen (Corucen)",
    "wof:placetype":"locality",
    "wof:population":49
},
  "geometry": {"coordinates":[-101.10227,18.40881],"type":"Point"}
}