{
  "type": "Feature",
  "properties": {
    "gn:admin1_code":"19",
    "gn:admin2_code":"22.0",
    "gn:asciiname":"Palmira",
    "gn:country_code":"MX",
    "gn:dem":310,
    "gn:feature_class":"P",
    "gn:feature_code":"PPL",
    "gn:name":"Palmira",
    "gn:population":0,
    "gn:timezone":"America/Monterrey",
    "iso:country":"MX",
    "name:spa_x_preferred":[
        "Palmira"
    ],
    "wof:name":"Palmira",
    "wof:placetype":"locality"
},
  "geometry": {"coordinates":[-99.66414,25.21004],"type":"Point"}
}