{
  "type": "Feature",
  "properties": {
    "gn:gn_country":"MX",
    "gn:gn_fcode":"PPL",
    "gn:gn_pop":0,
    "iso:country":"MX",
    "name:bre_x_preferred":[
        "San Rafael"
    ],
    "name:ceb_x_preferred":[
        "San Rafael"
    ],
    "name:ces_x_preferred":[
        "San Rafael"
    ],
    "name:deu_x_preferred":[
        "San Rafael"
    ],
    "name:fas_x_preferred":[
        "\u0633\u0627\u0646 \u0631\u0627\u0641\u0627\u0626\u0644"
    ],
    "name:fin_x_preferred":[
        "San Rafael"
    ],
    "name:fra_x_preferred":[
        "San Rafael"
    ],
    "name:hun_x_preferred":[
        "San Rafael"
    ],
    "name:hye_x_preferred":[
        "\u054d\u0561\u0576 \u054c\u0561\u0586\u0561\u0575\u0565\u056c"
    ],
    "name:ilo_x_preferred":[
        "San Rafael"
    ],
    "name:ita_x_preferred":[
        "San Rafael"
    ],
    "name:jpn_x_preferred":[
        "\u30b5\u30f3\u30fb\u30e9\u30d5\u30a1\u30a8\u30eb"
    ],
    "name:kor_x_preferred":[
        "\uc0b0\ub77c\ud30c\uc5d8"
    ],
    "name:mlg_x_preferred":[
        "San Rafael"
    ],
    "name:nld_x_preferred":[
        "San Rafael"
    ],
    "name:pol_x_preferred":[
        "San Rafael"
    ],
    "name:por_x_preferred":[
        "San Rafael"
    ],
    "name:rus_x_preferred":[
        "\u0421\u0430\u043d-\u0420\u0430\u0444\u0430\u044d\u043b\u044c"
    ],
    "name:sco_x_preferred":[
        "San Rafael"
    ],
    "name:spa_x_preferred":[
        "San Rafael"
    ],
    "name:srp_x_preferred":[
        "\u0421\u0430\u043d \u0420\u0430\u0444\u0430\u0435\u043b"
    ],
    "name:swe_x_preferred":[
        "San Rafael"
    ],
    "name:unk_x_variant":[
        "San Rafael el Arco"
    ],
    "name:vie_x_preferred":[
        "San Rafael"
    ],
    "name:war_x_preferred":[
        "San Rafael"
    ],
    "qs_pg:aaroncc":"MX",
    "qs_pg:gn_country":"MX",
    "qs_pg:gn_fcode":"PPL",
    "qs_pg:gn_pop":0,
    "qs_pg:name":"San Rafael",
    "qs_pg:name_adm0":"M\u00e9xico",
    "qs_pg:name_adm1":"Chiapas",
    "qs_pg:photos":12,
    "qs_pg:photos_1k":2,
    "qs_pg:photos_9k":1,
    "qs_pg:photos_9r":1,
    "qs_pg:photos_all":12,
    "qs_pg:photos_sr":1,
    "qs_pg:pop_sr":0,
    "qs_pg:qs_pg_placetype":"locality",
    "qs_pg:qs_pg_placetype_gp":"Town",
    "qs_pg:woe_adm0":23424900,
    "woe:adm0_id":23424900,
    "woe:name_adm0":"M\u00e9xico",
    "woe:name_adm1":"Chiapas",
    "woe:placetype":"Town",
    "wof:name":"San Rafael",
    "wof:placetype":"locality"
},
  "geometry": {"coordinates":[-91.81667,16.16667],"type":"Point"}
}