{
  "type": "Feature",
  "properties": {
    "gn:admin1_code":"30",
    "gn:admin2_code":"42",
    "gn:asciiname":"Paso Fresco",
    "gn:country_code":"MX",
    "gn:dem":104,
    "gn:feature_class":"P",
    "gn:feature_code":"PPL",
    "gn:name":"Paso Fresco",
    "gn:population":12,
    "gn:timezone":"America/Mexico_City",
    "iso:country":"MX",
    "wof:name":"Paso Fresco",
    "wof:placetype":"locality",
    "wof:population":12
},
  "geometry": {"coordinates":[-96.66306,19.98111],"type":"Point"}
}