{
  "type": "Feature",
  "properties": {
    "gn:admin1_code":"6",
    "gn:admin2_code":"47.0",
    "gn:asciiname":"Las Cabanas",
    "gn:country_code":"MX",
    "gn:dem":1604,
    "gn:feature_class":"P",
    "gn:feature_code":"PPL",
    "gn:name":"Las Caba\u00f1as",
    "gn:population":8,
    "gn:timezone":"America/Chihuahua",
    "iso:country":"MX",
    "name:und_x_variant":[
        "Las Caba\u00f1as"
    ],
    "wof:name":"Las Cabanas",
    "wof:placetype":"locality",
    "wof:population":8
},
  "geometry": {"coordinates":[-109.05775,28.26879000000001],"type":"Point"}
}