{
  "type": "Feature",
  "properties": {
    "gn:admin1_code":"26",
    "gn:admin2_code":"51.0",
    "gn:asciiname":"Berreyes",
    "gn:country_code":"MX",
    "gn:dem":816,
    "gn:feature_class":"P",
    "gn:feature_code":"PPL",
    "gn:name":"Berreyes",
    "gn:population":0,
    "gn:timezone":"America/Hermosillo",
    "iso:country":"MX",
    "name:spa_x_preferred":[
        "Berreyes"
    ],
    "wof:name":"Berreyes",
    "wof:placetype":"locality"
},
  "geometry": {"coordinates":[-109.17209,28.17252],"type":"Point"}
}