{
  "type": "Feature",
  "properties": {
    "gn:admin1_code":"11.0",
    "gn:asciiname":"Monte Redondo",
    "gn:country_code":"MX",
    "gn:dem":2248,
    "gn:feature_class":"P",
    "gn:feature_code":"PPL",
    "gn:name":"Monte Redondo",
    "gn:population":0,
    "gn:timezone":"America/Mexico_City",
    "iso:country":"MX",
    "name:spa_x_preferred":[
        "Monte Redondo"
    ],
    "wof:name":"Monte Redondo",
    "wof:placetype":"locality"
},
  "geometry": {"coordinates":[-101.78331,20.61643],"type":"Point"}
}