{
  "type": "Feature",
  "properties": {
    "gn:admin1_code":"6",
    "gn:admin2_code":"65.0",
    "gn:asciiname":"Churitavo",
    "gn:country_code":"MX",
    "gn:dem":1899,
    "gn:feature_class":"P",
    "gn:feature_code":"PPL",
    "gn:name":"Churitavo",
    "gn:population":0,
    "gn:timezone":"America/Chihuahua",
    "iso:country":"MX",
    "name:spa_x_preferred":[
        "Churitavo"
    ],
    "wof:name":"Churitavo",
    "wof:placetype":"locality"
},
  "geometry": {"coordinates":[-108.06461000000002,27.45897],"type":"Point"}
}