{
  "type": "Feature",
  "properties": {
    "gn:admin1_code":"5",
    "gn:admin2_code":"97.0",
    "gn:asciiname":"El Trebol (Las Bugambilias)",
    "gn:country_code":"MX",
    "gn:dem":25,
    "gn:feature_class":"P",
    "gn:feature_code":"PPL",
    "gn:name":"El Tr\u00e9bol (Las Bugambilias)",
    "gn:population":5,
    "gn:timezone":"America/Mexico_City",
    "iso:country":"MX",
    "name:und_x_variant":[
        "El Tr\u00e9bol (Las Bugambilias)"
    ],
    "wof:name":"El Trebol (Las Bugambilias)",
    "wof:placetype":"locality",
    "wof:population":5
},
  "geometry": {"coordinates":[-93.86639,16.14722],"type":"Point"}
}