{
  "type": "Feature",
  "properties": {
    "gn:admin1_code":"26.0",
    "gn:admin2_code":"17.0",
    "gn:asciiname":"El Cubo",
    "gn:country_code":"MX",
    "gn:dem":462,
    "gn:feature_class":"P",
    "gn:feature_code":"PPL",
    "gn:name":"El Cubo",
    "gn:population":0,
    "gn:timezone":"America/Hermosillo",
    "iso:country":"MX",
    "name:und_x_variant":[
        "Rancho El Cubo",
        "El Cubo"
    ],
    "wof:name":"El Cubo",
    "wof:placetype":"locality"
},
  "geometry": {"coordinates":[-112.21444,31.09084],"type":"Point"}
}