{
  "type": "Feature",
  "properties": {
    "gn:admin1_code":"23",
    "gn:admin2_code":"2.0",
    "gn:asciiname":"San Felipe Berriozabal",
    "gn:country_code":"MX",
    "gn:dem":25,
    "gn:feature_class":"P",
    "gn:feature_code":"PPL",
    "gn:name":"San Felipe Berrioz\u00e1bal",
    "gn:population":394,
    "gn:timezone":"America/Cancun",
    "iso:country":"MX",
    "name:und_x_variant":[
        "San Felipe Berrioz\u00e1bal"
    ],
    "wof:name":"San Felipe Berriozabal",
    "wof:placetype":"locality",
    "wof:population":394
},
  "geometry": {"coordinates":[-88.16806,20.05278],"type":"Point"}
}