{
  "type": "Feature",
  "properties": {
    "gn:admin1_code":"5",
    "gn:admin2_code":"10",
    "gn:asciiname":"Creston del Gallo",
    "gn:country_code":"MX",
    "gn:dem":2199,
    "gn:feature_class":"P",
    "gn:feature_code":"PPL",
    "gn:name":"Crest\u00f3n del Gallo",
    "gn:population":24,
    "gn:timezone":"America/Mexico_City",
    "iso:country":"MX",
    "name:und_x_variant":[
        "Crest\u00f3n del Gallo"
    ],
    "wof:name":"Creston del Gallo",
    "wof:placetype":"locality",
    "wof:population":24
},
  "geometry": {"coordinates":[-92.14778,15.4875],"type":"Point"}
}