{
  "type": "Feature",
  "properties": {
    "gn:admin1_code":"25.0",
    "gn:asciiname":"Las Lupitas",
    "gn:country_code":"MX",
    "gn:dem":5,
    "gn:feature_class":"P",
    "gn:feature_code":"PPL",
    "gn:name":"Las Lupitas",
    "gn:population":0,
    "gn:timezone":"America/Mazatlan",
    "iso:country":"MX",
    "name:spa_x_preferred":[
        "Las Lupitas"
    ],
    "wof:name":"Las Lupitas",
    "wof:placetype":"locality"
},
  "geometry": {"coordinates":[-105.74487999999999,22.55649],"type":"Point"}
}