{
  "type": "Feature",
  "properties": {
    "gn:admin1_code":"11",
    "gn:admin2_code":"20.0",
    "gn:asciiname":"Nuevo Valle de Moreno",
    "gn:country_code":"MX",
    "gn:dem":2234,
    "gn:feature_class":"P",
    "gn:feature_code":"PPL",
    "gn:name":"Nuevo Valle de Moreno",
    "gn:population":0,
    "gn:timezone":"America/Mexico_City",
    "iso:country":"MX",
    "name:und_x_variant":[
        "Nuevo Valle",
        "Nuevo Valle de Moreno",
        "Tlachiquera"
    ],
    "wof:name":"Nuevo Valle de Moreno",
    "wof:placetype":"locality"
},
  "geometry": {"coordinates":[-101.42482,21.21173],"type":"Point"}
}