{
  "type": "Feature",
  "properties": {
    "gn:admin1_code":"12",
    "gn:admin2_code":"11.0",
    "gn:asciiname":"Colonia Buenos Aires",
    "gn:country_code":"MX",
    "gn:dem":32,
    "gn:feature_class":"P",
    "gn:feature_code":"PPL",
    "gn:name":"Colonia Buenos Aires",
    "gn:population":603,
    "gn:timezone":"America/Mexico_City",
    "iso:country":"MX",
    "wof:name":"Colonia Buenos Aires",
    "wof:placetype":"locality",
    "wof:population":603
},
  "geometry": {"coordinates":[-100.41444,17.15639],"type":"Point"}
}