{
  "type": "Feature",
  "properties": {
    "gn:admin1_code":"16",
    "gn:admin2_code":"96",
    "gn:asciiname":"El Fresnal",
    "gn:country_code":"MX",
    "gn:dem":1580,
    "gn:feature_class":"P",
    "gn:feature_code":"PPL",
    "gn:name":"El Fresnal",
    "gn:population":39,
    "gn:timezone":"America/Mexico_City",
    "iso:country":"MX",
    "wof:name":"El Fresnal",
    "wof:placetype":"locality",
    "wof:population":39
},
  "geometry": {"coordinates":[-102.49861,18.54472],"type":"Point"}
}