{
  "type": "Feature",
  "properties": {
    "gn:admin1_code":"3",
    "gn:admin2_code":"3.0",
    "gn:asciiname":"Las Calabazas",
    "gn:country_code":"MX",
    "gn:dem":497,
    "gn:feature_class":"P",
    "gn:feature_code":"PPL",
    "gn:name":"Las Calabazas",
    "gn:population":0,
    "gn:timezone":"America/Mazatlan",
    "iso:country":"MX",
    "name:und_x_variant":[
        "Calabazas",
        "Las Calabazas"
    ],
    "wof:name":"Las Calabazas",
    "wof:placetype":"locality"
},
  "geometry": {"coordinates":[-110.15971999999999,23.95159],"type":"Point"}
}