{
  "type": "Feature",
  "properties": {
    "gn:admin1_code":"5",
    "gn:admin2_code":"108.0",
    "gn:asciiname":"San Gabriel",
    "gn:country_code":"MX",
    "gn:dem":575,
    "gn:feature_class":"P",
    "gn:feature_code":"PPL",
    "gn:name":"San Gabriel",
    "gn:population":6,
    "gn:timezone":"America/Mexico_City",
    "iso:country":"MX",
    "name:cat_x_preferred":[
        "San Gabriel"
    ],
    "name:ceb_x_preferred":[
        "San Gabriel"
    ],
    "name:deu_x_preferred":[
        "San Gabriel"
    ],
    "name:eus_x_preferred":[
        "San Gabriel"
    ],
    "name:fra_x_preferred":[
        "San Gabriel"
    ],
    "name:glg_x_preferred":[
        "San Gabriel"
    ],
    "name:heb_x_preferred":[
        "\u05e1\u05df \u05d2\u05d1\u05e8\u05d9\u05d0\u05dc"
    ],
    "name:ita_x_preferred":[
        "San Gabriel"
    ],
    "name:nld_x_preferred":[
        "San Gabriel"
    ],
    "name:pol_x_preferred":[
        "San Gabriel"
    ],
    "name:por_x_preferred":[
        "San Gabriel"
    ],
    "name:rus_x_preferred":[
        "\u0421\u0430\u043d-\u0413\u0430\u0431\u0440\u0438\u044d\u043b\u044c"
    ],
    "name:rus_x_variant":[
        "\u0421\u0430\u043d-\u0413\u0435\u0439\u0431\u0440\u0438\u0435\u043b"
    ],
    "name:sco_x_preferred":[
        "San Gabriel"
    ],
    "name:spa_x_preferred":[
        "San Gabriel"
    ],
    "name:srp_x_preferred":[
        "San Gabriel"
    ],
    "name:swe_x_preferred":[
        "San Gabriel"
    ],
    "name:tur_x_preferred":[
        "San Gabriel"
    ],
    "name:ukr_x_preferred":[
        "\u0421\u0430\u043d-\u0413\u0430\u0431\u0440\u0456\u0435\u043b\u044c"
    ],
    "name:urd_x_preferred":[
        "\u0633\u06cc\u0646 \u06af\u0628\u0631\u0627\u0626\u0644"
    ],
    "name:vie_x_preferred":[
        "San Gabriel"
    ],
    "name:war_x_preferred":[
        "San Gabriel"
    ],
    "wof:name":"San Gabriel",
    "wof:placetype":"locality",
    "wof:population":6
},
  "geometry": {"coordinates":[-93.29306,16.22472],"type":"Point"}
}