{
  "type": "Feature",
  "properties": {
    "gn:admin1_code":"11",
    "gn:admin2_code":"20.0",
    "gn:asciiname":"Rancho Nuevo de la Venta",
    "gn:country_code":"MX",
    "gn:dem":1913,
    "gn:feature_class":"P",
    "gn:feature_code":"PPL",
    "gn:name":"Rancho Nuevo de la Venta",
    "gn:population":450,
    "gn:timezone":"America/Mexico_City",
    "iso:country":"MX",
    "wof:name":"Rancho Nuevo de la Venta",
    "wof:placetype":"locality",
    "wof:population":450
},
  "geometry": {"coordinates":[-101.79167,21.0775],"type":"Point"}
}