{
  "type": "Feature",
  "properties": {
    "gn:admin1_code":"6",
    "gn:admin2_code":"45.0",
    "gn:asciiname":"El Olivo",
    "gn:country_code":"MX",
    "gn:dem":1135,
    "gn:feature_class":"P",
    "gn:feature_code":"PPL",
    "gn:name":"El Olivo",
    "gn:population":5,
    "gn:timezone":"America/Chihuahua",
    "iso:country":"MX",
    "wof:name":"El Olivo",
    "wof:placetype":"locality",
    "wof:population":5
},
  "geometry": {"coordinates":[-105.45273,28.33024],"type":"Point"}
}