{
  "type": "Feature",
  "properties": {
    "gn:admin1_code":"11.0",
    "gn:admin2_code":"11.0",
    "gn:asciiname":"Santa Teresa",
    "gn:country_code":"MX",
    "gn:dem":1739,
    "gn:feature_class":"P",
    "gn:feature_code":"PPL",
    "gn:name":"Santa Teresa",
    "gn:population":5,
    "gn:timezone":"America/Mexico_City",
    "iso:country":"MX",
    "name:bpy_x_preferred":[
        "\u09b8\u09be\u09a8\u09cd\u099f\u09be \u099f\u09c7\u09b0\u09c7\u09b8\u09be"
    ],
    "name:cat_x_preferred":[
        "Santa Teresa"
    ],
    "name:ceb_x_preferred":[
        "Santa Teresa"
    ],
    "name:deu_x_preferred":[
        "Santa Teresa"
    ],
    "name:eus_x_preferred":[
        "Santa Teresa"
    ],
    "name:fra_x_preferred":[
        "Santa Teresa"
    ],
    "name:ita_x_preferred":[
        "Santa Teresa"
    ],
    "name:nds_x_preferred":[
        "Santa Teresa"
    ],
    "name:nld_x_preferred":[
        "Santa Teresa"
    ],
    "name:nor_x_preferred":[
        "Santa Teresa"
    ],
    "name:pms_x_preferred":[
        "Santa Teresa"
    ],
    "name:pol_x_preferred":[
        "Santa Teresa"
    ],
    "name:por_x_preferred":[
        "Santa Teresa"
    ],
    "name:rus_x_preferred":[
        "\u0421\u0430\u043d\u0442\u0430-\u0422\u0435\u0440\u0435\u0437\u0430"
    ],
    "name:spa_x_preferred":[
        "Santa Teresa"
    ],
    "name:srp_x_preferred":[
        "Santa Teresa"
    ],
    "name:swe_x_preferred":[
        "Santa Teresa"
    ],
    "name:vie_x_preferred":[
        "Santa Teresa"
    ],
    "name:vol_x_preferred":[
        "Santa Teresa"
    ],
    "wof:name":"Santa Teresa",
    "wof:placetype":"locality",
    "wof:population":5
},
  "geometry": {"coordinates":[-101.00167,20.4975],"type":"Point"}
}