{
  "type": "Feature",
  "properties": {
    "gn:admin1_code":"14",
    "gn:admin2_code":"19.0",
    "gn:asciiname":"Coamostita",
    "gn:country_code":"MX",
    "gn:dem":1068,
    "gn:feature_class":"P",
    "gn:feature_code":"PPL",
    "gn:name":"Coamostita",
    "gn:population":187,
    "gn:timezone":"America/Mexico_City",
    "iso:country":"MX",
    "wof:name":"Coamostita",
    "wof:placetype":"locality",
    "wof:population":187
},
  "geometry": {"coordinates":[-103.99083,21.92833],"type":"Point"}
}