{
  "type": "Feature",
  "properties": {
    "gn:admin1_code":"14",
    "gn:admin2_code":"25.0",
    "gn:asciiname":"La Mesita",
    "gn:country_code":"MX",
    "gn:dem":2078,
    "gn:feature_class":"P",
    "gn:feature_code":"PPL",
    "gn:name":"La Mesita",
    "gn:population":0,
    "gn:timezone":"America/Mexico_City",
    "iso:country":"MX",
    "name:spa_x_preferred":[
        "La Mesita"
    ],
    "wof:name":"La Mesita",
    "wof:placetype":"locality"
},
  "geometry": {"coordinates":[-103.17458000000001,22.10577],"type":"Point"}
}