{
  "type": "Feature",
  "properties": {
    "gn:admin1_code":"22",
    "gn:admin2_code":"12",
    "gn:asciiname":"Familia Rivera Gonzalez (Hacienda San Clemente)",
    "gn:country_code":"MX",
    "gn:dem":1960,
    "gn:feature_class":"P",
    "gn:feature_code":"PPL",
    "gn:name":"Familia Rivera Gonz\u00e1lez (Hacienda San Clemente)",
    "gn:population":20,
    "gn:timezone":"America/Mexico_City",
    "iso:country":"MX",
    "name:und_x_variant":[
        "Familia Rivera Gonz\u00e1lez (Hacienda San Clemente)"
    ],
    "wof:name":"Familia Rivera Gonzalez (Hacienda San Clemente)",
    "wof:placetype":"locality",
    "wof:population":20
},
  "geometry": {"coordinates":[-100.07861,20.51361],"type":"Point"}
}