{
  "type": "Feature",
  "properties": {
    "gn:admin1_code":"11",
    "gn:admin2_code":"22",
    "gn:asciiname":"Tanque Colorado",
    "gn:country_code":"MX",
    "gn:dem":2248,
    "gn:feature_class":"P",
    "gn:feature_code":"PPL",
    "gn:name":"Tanque Colorado",
    "gn:population":12,
    "gn:timezone":"America/Mexico_City",
    "iso:country":"MX",
    "wof:name":"Tanque Colorado",
    "wof:placetype":"locality",
    "wof:population":12
},
  "geometry": {"coordinates":[-101.35722,21.67222000000001],"type":"Point"}
}