{
  "type": "Feature",
  "properties": {
    "gn:admin1_code":"31",
    "gn:admin2_code":"50.0",
    "gn:asciiname":"Suytunchen",
    "gn:country_code":"MX",
    "gn:dem":8,
    "gn:feature_class":"P",
    "gn:feature_code":"PPL",
    "gn:name":"Suytunch\u00e9n",
    "gn:population":0,
    "gn:timezone":"America/Merida",
    "iso:country":"MX",
    "name:spa_x_preferred":[
        "Suytunch\u00e9n"
    ],
    "wof:name":"Suytunchen",
    "wof:placetype":"locality"
},
  "geometry": {"coordinates":[-89.73210999999998,21.10263],"type":"Point"}
}