{
  "type": "Feature",
  "properties": {
    "gn:admin1_code":"5",
    "gn:admin2_code":"11.0",
    "gn:asciiname":"Los Pocitos",
    "gn:country_code":"MX",
    "gn:dem":1935,
    "gn:feature_class":"P",
    "gn:feature_code":"PPL",
    "gn:name":"Los Pocitos",
    "gn:population":75,
    "gn:timezone":"America/Mexico_City",
    "iso:country":"MX",
    "wof:name":"Los Pocitos",
    "wof:placetype":"locality",
    "wof:population":75
},
  "geometry": {"coordinates":[-92.25055999999999,15.56972],"type":"Point"}
}