{
  "type": "Feature",
  "properties": {
    "gn:admin1_code":"6",
    "gn:admin2_code":"21.0",
    "gn:asciiname":"Rancho de Terriz (San Jose)",
    "gn:country_code":"MX",
    "gn:dem":1209,
    "gn:feature_class":"P",
    "gn:feature_code":"PPL",
    "gn:name":"Rancho de Terriz (San Jos\u00e9)",
    "gn:population":5,
    "gn:timezone":"America/Chihuahua",
    "iso:country":"MX",
    "name:und_x_variant":[
        "Rancho de Terriz (San Jos\u00e9)"
    ],
    "wof:name":"Rancho de Terriz (San Jose)",
    "wof:placetype":"locality",
    "wof:population":5
},
  "geometry": {"coordinates":[-105.42861000000001,28.13591],"type":"Point"}
}