{
  "type": "Feature",
  "properties": {
    "gn:admin1_code":"14",
    "gn:admin2_code":"20.0",
    "gn:asciiname":"Platanar",
    "gn:country_code":"MX",
    "gn:dem":287,
    "gn:feature_class":"P",
    "gn:feature_code":"PPL",
    "gn:name":"Platanar",
    "gn:population":0,
    "gn:timezone":"America/Mexico_City",
    "iso:country":"MX",
    "name:spa_x_preferred":[
        "Platanar"
    ],
    "wof:name":"Platanar",
    "wof:placetype":"locality"
},
  "geometry": {"coordinates":[-105.51499,20.37317],"type":"Point"}
}