{
  "type": "Feature",
  "properties": {
    "gn:admin1_code":"13",
    "gn:admin2_code":"18.0",
    "gn:asciiname":"Mesa Juarez",
    "gn:country_code":"MX",
    "gn:dem":285,
    "gn:feature_class":"P",
    "gn:feature_code":"PPL",
    "gn:name":"Mesa Ju\u00e1rez",
    "gn:population":0,
    "gn:timezone":"America/Mexico_City",
    "iso:country":"MX",
    "wof:name":"Mesa Juarez",
    "wof:placetype":"locality"
},
  "geometry": {"coordinates":[-98.96666999999999,21.18333],"type":"Point"}
}