{
  "type": "Feature",
  "properties": {
    "gn:admin1_code":"32",
    "gn:admin2_code":"35.0",
    "gn:asciiname":"El Salvador",
    "gn:country_code":"MX",
    "gn:dem":2148,
    "gn:feature_class":"P",
    "gn:feature_code":"PPL",
    "gn:name":"El Salvador",
    "gn:population":105,
    "gn:timezone":"America/Mexico_City",
    "iso:country":"MX",
    "wof:name":"El Salvador",
    "wof:placetype":"locality",
    "wof:population":105
},
  "geometry": {"coordinates":[-101.81778,22.34944],"type":"Point"}
}