{
  "type": "Feature",
  "properties": {
    "gn:admin1_code":"26.0",
    "gn:admin2_code":"26.0",
    "gn:asciiname":"Campo de Palomares",
    "gn:country_code":"MX",
    "gn:dem":11,
    "gn:feature_class":"P",
    "gn:feature_code":"PPL",
    "gn:name":"Campo de Palomares",
    "gn:population":0,
    "gn:timezone":"America/Hermosillo",
    "iso:country":"MX",
    "name:spa_x_preferred":[
        "Campo de Palomares"
    ],
    "wof:name":"Campo de Palomares",
    "wof:placetype":"locality"
},
  "geometry": {"coordinates":[-109.62982,26.90109],"type":"Point"}
}