{
  "type": "Feature",
  "properties": {
    "gn:admin1_code":"12.0",
    "gn:admin2_code":"43.0",
    "gn:asciiname":"Ibixana",
    "gn:country_code":"MX",
    "gn:dem":1768,
    "gn:feature_class":"P",
    "gn:feature_code":"PPL",
    "gn:name":"Ibixana",
    "gn:population":0,
    "gn:timezone":"America/Mexico_City",
    "iso:country":"MX",
    "name:spa_x_preferred":[
        "Ibixana"
    ],
    "wof:name":"Ibixana",
    "wof:placetype":"locality"
},
  "geometry": {"coordinates":[-98.42022,17.25982999999999],"type":"Point"}
}