{
  "type": "Feature",
  "properties": {
    "gn:admin1_code":"19.0",
    "gn:admin2_code":"17.0",
    "gn:asciiname":"Santa Amalia",
    "gn:country_code":"MX",
    "gn:dem":1906,
    "gn:feature_class":"P",
    "gn:feature_code":"PPL",
    "gn:name":"Santa Amalia",
    "gn:population":0,
    "gn:timezone":"America/Monterrey",
    "iso:country":"MX",
    "name:spa_x_preferred":[
        "Santa Amalia"
    ],
    "name:spa_x_variant":[
        "El Toro"
    ],
    "wof:name":"Santa Amalia",
    "wof:placetype":"locality"
},
  "geometry": {"coordinates":[-100.78695,24.69543],"type":"Point"}
}