{
  "type": "Feature",
  "properties": {
    "gn:admin1_code":"30.0",
    "gn:admin2_code":"151.0",
    "gn:asciiname":"Francisco Gonzalez Bocanegra",
    "gn:country_code":"MX",
    "gn:dem":60,
    "gn:feature_class":"P",
    "gn:feature_code":"PPL",
    "gn:name":"Francisco Gonz\u00e1lez Bocanegra",
    "gn:population":87,
    "gn:timezone":"America/Mexico_City",
    "iso:country":"MX",
    "name:spa_x_preferred":[
        "Francisco Gonz\u00e1lez Bocanegra"
    ],
    "wof:name":"Francisco Gonzalez Bocanegra",
    "wof:placetype":"locality",
    "wof:population":87
},
  "geometry": {"coordinates":[-97.56652,21.1749],"type":"Point"}
}