{
  "type": "Feature",
  "properties": {
    "gn:admin1_code":"32.0",
    "gn:admin2_code":"13.0",
    "gn:asciiname":"Cienega de Tapia",
    "gn:country_code":"MX",
    "gn:dem":2174,
    "gn:feature_class":"P",
    "gn:feature_code":"PPL",
    "gn:name":"Cienega de Tapia",
    "gn:population":0,
    "gn:timezone":"America/Mexico_City",
    "iso:country":"MX",
    "name:spa_x_preferred":[
        "Cienega de Tapia"
    ],
    "name:und_x_variant":[
        "Cieneguita",
        "Cieneguilla"
    ],
    "wof:name":"Cienega de Tapia",
    "wof:placetype":"locality"
},
  "geometry": {"coordinates":[-102.78176000000001,23.02251],"type":"Point"}
}