{
  "type": "Feature",
  "properties": {
    "gn:admin1_code":"7.0",
    "gn:admin2_code":"38.0",
    "gn:asciiname":"Lopez",
    "gn:country_code":"MX",
    "gn:dem":347,
    "gn:feature_class":"P",
    "gn:feature_code":"PPL",
    "gn:name":"L\u00f3pez",
    "gn:population":0,
    "gn:timezone":"America/Monterrey",
    "iso:country":"MX",
    "name:spa_x_preferred":[
        "L\u00f3pez"
    ],
    "wof:name":"Lopez",
    "wof:placetype":"locality"
},
  "geometry": {"coordinates":[-100.85257,28.44682],"type":"Point"}
}