{
  "type": "Feature",
  "properties": {
    "gn:admin1_code":"21",
    "gn:admin2_code":"75.0",
    "gn:asciiname":"Gardenias",
    "gn:country_code":"MX",
    "gn:dem":839,
    "gn:feature_class":"P",
    "gn:feature_code":"PPL",
    "gn:name":"Gardenias",
    "gn:population":55,
    "gn:timezone":"America/Mexico_City",
    "iso:country":"MX",
    "wof:name":"Gardenias",
    "wof:placetype":"locality",
    "wof:population":55
},
  "geometry": {"coordinates":[-97.37900999999999,19.95829],"type":"Point"}
}