{
  "type": "Feature",
  "properties": {
    "gn:gn_country":"MX",
    "gn:gn_fcode":"PPL",
    "gn:gn_pop":23150,
    "gn:population":23150,
    "iso:country":"MX",
    "name:baq_x_preferred":[
        "Ciudad Ixtepec"
    ],
    "name:chi_x_preferred":[
        "\u4f0a\u65af\u5fb7\u67cf\u514b"
    ],
    "name:dut_x_preferred":[
        "Ixtepec"
    ],
    "name:eng_x_preferred":[
        "Ixtepec"
    ],
    "name:epo_x_preferred":[
        "Ciudad Ixtepec"
    ],
    "name:jpn_x_preferred":[
        "\u30b7\u30a6\u30bf\u30fc\u30c9\u30fb\u30a4\u30b9\u30c6\u30da\u30af"
    ],
    "name:rus_x_preferred":[
        "\u0421\u044c\u044e\u0434\u0430\u0434-\u0418\u0441\u0442\u0435\u043f\u0435\u043a"
    ],
    "name:sco_x_preferred":[
        "Ciudad Ixtepec"
    ],
    "name:spa_x_preferred":[
        "Ixtepec"
    ],
    "name:spa_x_variant":[
        "San Geronimo Ixtepec",
        "Ciudad Ixtepec"
    ],
    "name:swe_x_preferred":[
        "Ciudad Ixtepec"
    ],
    "name:vie_x_preferred":[
        "Ciudad Ixtepec"
    ],
    "qs_pg:aaroncc":"MX",
    "qs_pg:gn_country":"MX",
    "qs_pg:gn_fcode":"PPL",
    "qs_pg:gn_pop":23150,
    "qs_pg:name":"San Jer\u00f3nimo Ixtepec",
    "qs_pg:photos_9r":0,
    "qs_pg:photos_sr":0,
    "qs_pg:pop_sr":7,
    "qs_pg:qs_pg_placetype":"locality",
    "wof:name":"San Jer\u00f3nimo Ixtepec",
    "wof:placetype":"locality",
    "wof:population":23150
},
  "geometry": {"coordinates":[-95.10223000000001,16.57855],"type":"Point"}
}