{
  "type": "Feature",
  "properties": {
    "gn:admin1_code":"5.0",
    "gn:admin2_code":"65.0",
    "gn:asciiname":"San Simon",
    "gn:country_code":"MX",
    "gn:dem":46,
    "gn:feature_class":"P",
    "gn:feature_code":"PPL",
    "gn:name":"San Sim\u00f3n",
    "gn:population":0,
    "gn:timezone":"America/Mexico_City",
    "iso:country":"MX",
    "name:spa_x_preferred":[
        "San Sim\u00f3n"
    ],
    "wof:name":"San Simon",
    "wof:placetype":"locality"
},
  "geometry": {"coordinates":[-92.13168,17.72193],"type":"Point"}
}