{
  "type": "Feature",
  "properties": {
    "gn:admin1_code":"31",
    "gn:admin2_code":"102.0",
    "gn:asciiname":"X-bacaba",
    "gn:country_code":"MX",
    "gn:dem":20,
    "gn:feature_class":"P",
    "gn:feature_code":"PPL",
    "gn:name":"X-bacaba",
    "gn:population":0,
    "gn:timezone":"America/Merida",
    "iso:country":"MX",
    "name:spa_x_preferred":[
        "X-bacaba"
    ],
    "wof:name":"X-bacaba",
    "wof:placetype":"locality"
},
  "geometry": {"coordinates":[-88.00599,20.79166],"type":"Point"}
}