{
  "type": "Feature",
  "properties": {
    "gn:admin1_code":"25",
    "gn:admin2_code":"12.0",
    "gn:asciiname":"San Pablo",
    "gn:country_code":"MX",
    "gn:dem":56,
    "gn:feature_class":"P",
    "gn:feature_code":"PPL",
    "gn:name":"San Pablo",
    "gn:population":54,
    "gn:timezone":"America/Mazatlan",
    "iso:country":"MX",
    "wof:name":"San Pablo",
    "wof:placetype":"locality",
    "wof:population":54
},
  "geometry": {"coordinates":[-106.42167000000001,23.44274],"type":"Point"}
}