{
  "type": "Feature",
  "properties": {
    "gn:admin1_code":"24.0",
    "gn:admin2_code":"40.0",
    "gn:asciiname":"Estacion Celis",
    "gn:country_code":"MX",
    "gn:dem":50,
    "gn:feature_class":"P",
    "gn:feature_code":"PPL",
    "gn:name":"Estaci\u00f3n Celis",
    "gn:population":5,
    "gn:timezone":"America/Mexico_City",
    "iso:country":"MX",
    "name:spa_x_preferred":[
        "Estaci\u00f3n Celis"
    ],
    "wof:name":"Estacion Celis",
    "wof:placetype":"locality",
    "wof:population":5
},
  "geometry": {"coordinates":[-98.65494,22.16925],"type":"Point"}
}