{
  "type": "Feature",
  "properties": {
    "gn:admin1_code":"25.0",
    "gn:admin2_code":"10.0",
    "gn:asciiname":"Los Ganaderos",
    "gn:country_code":"MX",
    "gn:dem":114,
    "gn:feature_class":"P",
    "gn:feature_code":"PPL",
    "gn:name":"Los Ganaderos",
    "gn:population":0,
    "gn:timezone":"America/Mazatlan",
    "iso:country":"MX",
    "name:spa_x_preferred":[
        "Los Ganaderos"
    ],
    "wof:name":"Los Ganaderos",
    "wof:placetype":"locality"
},
  "geometry": {"coordinates":[-108.6651,26.47121],"type":"Point"}
}