{
  "type": "Feature",
  "properties": {
    "gn:admin1_code":"32",
    "gn:admin2_code":"49.0",
    "gn:asciiname":"La Mesa de Arriba",
    "gn:country_code":"MX",
    "gn:dem":1733,
    "gn:feature_class":"P",
    "gn:feature_code":"PPL",
    "gn:name":"La Mesa de Arriba",
    "gn:population":0,
    "gn:timezone":"America/Mexico_City",
    "iso:country":"MX",
    "name:spa_x_preferred":[
        "La Mesa de Arriba"
    ],
    "wof:name":"La Mesa de Arriba",
    "wof:placetype":"locality"
},
  "geometry": {"coordinates":[-104.06774,22.84201],"type":"Point"}
}