{
  "type": "Feature",
  "properties": {
    "gn:admin1_code":"13.0",
    "gn:asciiname":"Jonatal Progreso",
    "gn:country_code":"MX",
    "gn:dem":335,
    "gn:feature_class":"P",
    "gn:feature_code":"PPL",
    "gn:name":"Jonatal Progreso",
    "gn:population":0,
    "gn:timezone":"America/Mexico_City",
    "iso:country":"MX",
    "name:spa_x_preferred":[
        "Jonatal Progreso"
    ],
    "wof:name":"Jonatal Progreso",
    "wof:placetype":"locality"
},
  "geometry": {"coordinates":[-98.01345000000001,20.6476],"type":"Point"}
}