{
  "type": "Feature",
  "properties": {
    "gn:admin1_code":"11",
    "gn:admin2_code":"5.0",
    "gn:asciiname":"Minitas",
    "gn:country_code":"MX",
    "gn:dem":1803,
    "gn:feature_class":"P",
    "gn:feature_code":"PPL",
    "gn:name":"Minitas",
    "gn:population":88,
    "gn:timezone":"America/Mexico_City",
    "iso:country":"MX",
    "wof:name":"Minitas",
    "wof:placetype":"locality",
    "wof:population":88
},
  "geometry": {"coordinates":[-100.61028,20.57306],"type":"Point"}
}