{
  "type": "Feature",
  "properties": {
    "gn:admin1_code":"14",
    "gn:admin2_code":"80.0",
    "gn:asciiname":"Milpillas",
    "gn:country_code":"MX",
    "gn:dem":1222,
    "gn:feature_class":"P",
    "gn:feature_code":"PPL",
    "gn:name":"Milpillas",
    "gn:population":0,
    "gn:timezone":"America/Mexico_City",
    "iso:country":"MX",
    "name:und_x_variant":[
        "Milpillas de Abajo"
    ],
    "wof:name":"Milpillas",
    "wof:placetype":"locality"
},
  "geometry": {"coordinates":[-104.893,20.74341],"type":"Point"}
}