{
  "type": "Feature",
  "properties": {
    "gn:admin1_code":"11",
    "gn:admin2_code":"23.0",
    "gn:asciiname":"El Romeral",
    "gn:country_code":"MX",
    "gn:dem":1700,
    "gn:feature_class":"P",
    "gn:feature_code":"PPL",
    "gn:name":"El Romeral",
    "gn:population":375,
    "gn:timezone":"America/Mexico_City",
    "iso:country":"MX",
    "name:arg_x_preferred":[
        "El Romeral"
    ],
    "name:azb_x_preferred":[
        "\u0627\u0644 \u0631\u0645\u0631\u0627\u0644"
    ],
    "name:cat_x_preferred":[
        "El Romeral"
    ],
    "name:ceb_x_preferred":[
        "Romeral"
    ],
    "name:epo_x_preferred":[
        "El Romeral"
    ],
    "name:eus_x_preferred":[
        "El Romeral"
    ],
    "name:fas_x_preferred":[
        "\u0627\u0644 \u0631\u0645\u0631\u0627\u0644"
    ],
    "name:fra_x_preferred":[
        "El Romeral"
    ],
    "name:hun_x_preferred":[
        "El Romeral"
    ],
    "name:hye_x_preferred":[
        "\u0537\u056c \u054c\u0578\u0574\u0565\u0580\u0561\u056c"
    ],
    "name:ina_x_preferred":[
        "El Romeral"
    ],
    "name:ita_x_preferred":[
        "El Romeral"
    ],
    "name:kaz_x_preferred":[
        "\u042d\u043b\u044c-\u0420\u043e\u043c\u0435\u0440\u0430\u043b\u044c"
    ],
    "name:msa_x_preferred":[
        "El Romeral"
    ],
    "name:nld_x_preferred":[
        "El Romeral"
    ],
    "name:oci_x_preferred":[
        "El Romeral"
    ],
    "name:pol_x_preferred":[
        "El Romeral"
    ],
    "name:por_x_preferred":[
        "El Romeral"
    ],
    "name:ron_x_preferred":[
        "El Romeral"
    ],
    "name:rus_x_preferred":[
        "\u042d\u043b\u044c-\u0420\u043e\u043c\u0435\u0440\u0430\u043b\u044c"
    ],
    "name:spa_x_preferred":[
        "El Romeral"
    ],
    "name:swe_x_preferred":[
        "Romeral"
    ],
    "name:ukr_x_preferred":[
        "\u0415\u043b\u044c-\u0420\u043e\u043c\u0435\u0440\u0430\u043b\u044c"
    ],
    "name:vie_x_preferred":[
        "El Romeral"
    ],
    "name:war_x_preferred":[
        "El Romeral"
    ],
    "name:zho_x_preferred":[
        "\u57c3\u5c14\u7f57\u6885\u62c9\u5c14"
    ],
    "wof:name":"El Romeral",
    "wof:placetype":"locality",
    "wof:population":375
},
  "geometry": {"coordinates":[-101.64583,20.43417],"type":"Point"}
}