{
  "type": "Feature",
  "properties": {
    "gn:admin1_code":"5",
    "gn:admin2_code":"97.0",
    "gn:asciiname":"Fraccion Rustica (El Estio)",
    "gn:country_code":"MX",
    "gn:dem":11,
    "gn:feature_class":"P",
    "gn:feature_code":"PPL",
    "gn:name":"Fracci\u00f3n Rustica (El Est\u00edo)",
    "gn:population":4,
    "gn:timezone":"America/Mexico_City",
    "iso:country":"MX",
    "name:und_x_variant":[
        "Fracci\u00f3n Rustica (El Est\u00edo)"
    ],
    "wof:name":"Fraccion Rustica (El Estio)",
    "wof:placetype":"locality",
    "wof:population":4
},
  "geometry": {"coordinates":[-93.53471999999999,15.82],"type":"Point"}
}