{
  "type": "Feature",
  "properties": {
    "gn:admin1_code":"16",
    "gn:admin2_code":"101.0",
    "gn:asciiname":"El Buey",
    "gn:country_code":"MX",
    "gn:dem":2051,
    "gn:feature_class":"P",
    "gn:feature_code":"PPL",
    "gn:name":"El Buey",
    "gn:population":93,
    "gn:timezone":"America/Mexico_City",
    "iso:country":"MX",
    "wof:name":"El Buey",
    "wof:placetype":"locality",
    "wof:population":93
},
  "geometry": {"coordinates":[-101.04416999999999,19.51333],"type":"Point"}
}