{
  "type": "Feature",
  "properties": {
    "gn:admin1_code":"32",
    "gn:admin2_code":"51",
    "gn:asciiname":"Lorenzo Juarez",
    "gn:country_code":"MX",
    "gn:dem":2018,
    "gn:feature_class":"P",
    "gn:feature_code":"PPL",
    "gn:name":"Lorenzo Ju\u00e1rez",
    "gn:population":12,
    "gn:timezone":"America/Mexico_City",
    "iso:country":"MX",
    "name:und_x_variant":[
        "Lorenzo Ju\u00e1rez"
    ],
    "wof:name":"Lorenzo Juarez",
    "wof:placetype":"locality",
    "wof:population":12
},
  "geometry": {"coordinates":[-102.44611,23.45167],"type":"Point"}
}