{
  "type": "Feature",
  "properties": {
    "gn:admin1_code":"19.0",
    "gn:asciiname":"El Canada",
    "gn:country_code":"MX",
    "gn:dem":1880,
    "gn:feature_class":"P",
    "gn:feature_code":"PPL",
    "gn:name":"El Canad\u00e1",
    "gn:population":0,
    "gn:timezone":"America/Monterrey",
    "iso:country":"MX",
    "name:spa_x_preferred":[
        "El Canad\u00e1"
    ],
    "wof:name":"El Canada",
    "wof:placetype":"locality"
},
  "geometry": {"coordinates":[-100.66670000000001,25.01469],"type":"Point"}
}