{
  "type": "Feature",
  "properties": {
    "gn:admin1_code":"5",
    "gn:admin2_code":"89.0",
    "gn:asciiname":"Cabanas de Alboradas",
    "gn:country_code":"MX",
    "gn:dem":657,
    "gn:feature_class":"P",
    "gn:feature_code":"PPL",
    "gn:name":"Caba\u00f1as de Alboradas",
    "gn:population":6,
    "gn:timezone":"America/Mexico_City",
    "iso:country":"MX",
    "name:und_x_variant":[
        "Caba\u00f1as de Alboradas"
    ],
    "wof:name":"Cabanas de Alboradas",
    "wof:placetype":"locality",
    "wof:population":6
},
  "geometry": {"coordinates":[-92.31028000000001,15.13833],"type":"Point"}
}