{
  "type": "Feature",
  "properties": {
    "gn:admin1_code":"5",
    "gn:admin2_code":"76",
    "gn:asciiname":"San Marcos",
    "gn:country_code":"MX",
    "gn:dem":132,
    "gn:feature_class":"P",
    "gn:feature_code":"PPL",
    "gn:name":"San Marcos",
    "gn:population":51,
    "gn:timezone":"America/Mexico_City",
    "iso:country":"MX",
    "wof:name":"San Marcos",
    "wof:placetype":"locality",
    "wof:population":51
},
  "geometry": {"coordinates":[-92.63639000000001,17.3775],"type":"Point"}
}