{
  "type": "Feature",
  "properties": {
    "gn:admin1_code":"6.0",
    "gn:asciiname":"Rancho la Piedra",
    "gn:country_code":"MX",
    "gn:dem":1160,
    "gn:feature_class":"P",
    "gn:feature_code":"PPL",
    "gn:name":"Rancho la Piedra",
    "gn:population":0,
    "gn:timezone":"America/Chihuahua",
    "iso:country":"MX",
    "name:spa_x_preferred":[
        "Rancho la Piedra"
    ],
    "wof:name":"Rancho la Piedra",
    "wof:placetype":"locality"
},
  "geometry": {"coordinates":[-105.49915,28.20525],"type":"Point"}
}