{
  "type": "Feature",
  "properties": {
    "gn:admin1_code":"3.0",
    "gn:admin2_code":"2.0",
    "gn:asciiname":"Los Tres Elefantes",
    "gn:country_code":"MX",
    "gn:dem":27,
    "gn:feature_class":"P",
    "gn:feature_code":"PPL",
    "gn:name":"Los Tres Elefantes",
    "gn:population":0,
    "gn:timezone":"America/Mazatlan",
    "iso:country":"MX",
    "name:spa_x_preferred":[
        "Los Tres Elefantes"
    ],
    "wof:name":"Los Tres Elefantes",
    "wof:placetype":"locality"
},
  "geometry": {"coordinates":[-112.03933000000001,26.86186],"type":"Point"}
}