{
  "type": "Feature",
  "properties": {
    "gn:admin1_code":"7",
    "gn:admin2_code":"14.0",
    "gn:asciiname":"Victoria",
    "gn:country_code":"MX",
    "gn:dem":289,
    "gn:feature_class":"P",
    "gn:feature_code":"PPL",
    "gn:name":"Victoria",
    "gn:population":0,
    "gn:timezone":"America/Monterrey",
    "iso:country":"MX",
    "wof:name":"Victoria",
    "wof:placetype":"locality"
},
  "geometry": {"coordinates":[-100.76667,28.95],"type":"Point"}
}