{
  "type": "Feature",
  "properties": {
    "gn:admin1_code":"19",
    "gn:admin2_code":"14.0",
    "gn:asciiname":"San Felipe",
    "gn:country_code":"MX",
    "gn:dem":1677,
    "gn:feature_class":"P",
    "gn:feature_code":"PPL",
    "gn:name":"San Felipe",
    "gn:population":89,
    "gn:timezone":"America/Monterrey",
    "iso:country":"MX",
    "name:spa_x_preferred":[
        "San Felipe"
    ],
    "wof:name":"San Felipe",
    "wof:placetype":"locality",
    "wof:population":89
},
  "geometry": {"coordinates":[-100.29958999999999,24.10117],"type":"Point"}
}