{
  "type": "Feature",
  "properties": {
    "gn:admin1_code":"21",
    "gn:admin2_code":"77.0",
    "gn:asciiname":"Skansipi",
    "gn:country_code":"MX",
    "gn:dem":892,
    "gn:feature_class":"P",
    "gn:feature_code":"PPL",
    "gn:name":"Skansipi",
    "gn:population":321,
    "gn:timezone":"America/Mexico_City",
    "iso:country":"MX",
    "wof:name":"Skansipi",
    "wof:placetype":"locality",
    "wof:population":321
},
  "geometry": {"coordinates":[-97.66806,20.04616],"type":"Point"}
}