{
  "type": "Feature",
  "properties": {
    "gn:admin1_code":"16",
    "gn:admin2_code":"92",
    "gn:asciiname":"Los Jazmines",
    "gn:country_code":"MX",
    "gn:dem":1016,
    "gn:feature_class":"P",
    "gn:feature_code":"PPL",
    "gn:name":"Los Jazmines",
    "gn:population":36,
    "gn:timezone":"America/Mexico_City",
    "iso:country":"MX",
    "wof:name":"Los Jazmines",
    "wof:placetype":"locality",
    "wof:population":36
},
  "geometry": {"coordinates":[-100.89833,19.24444],"type":"Point"}
}