{
  "type": "Feature",
  "properties": {
    "gn:admin1_code":"21",
    "gn:admin2_code":"43.0",
    "gn:asciiname":"Ayotzinapan",
    "gn:country_code":"MX",
    "gn:dem":578,
    "gn:feature_class":"P",
    "gn:feature_code":"PPL",
    "gn:name":"Ayotzinapan",
    "gn:population":817,
    "gn:timezone":"America/Mexico_City",
    "iso:country":"MX",
    "wof:name":"Ayotzinapan",
    "wof:placetype":"locality",
    "wof:population":817
},
  "geometry": {"coordinates":[-97.53771999999999,20.05633],"type":"Point"}
}