{
  "type": "Feature",
  "properties": {
    "gn:admin1_code":"24",
    "gn:admin2_code":"6",
    "gn:asciiname":"Tahonas del Jordan",
    "gn:country_code":"MX",
    "gn:dem":2512,
    "gn:feature_class":"P",
    "gn:feature_code":"PPL",
    "gn:name":"Tahonas del Jord\u00e1n",
    "gn:population":52,
    "gn:timezone":"America/Mexico_City",
    "iso:country":"MX",
    "name:und_x_variant":[
        "Tahonas del Jord\u00e1n"
    ],
    "wof:name":"Tahonas del Jordan",
    "wof:placetype":"locality",
    "wof:population":52
},
  "geometry": {"coordinates":[-100.855,23.56917],"type":"Point"}
}