{
  "type": "Feature",
  "properties": {
    "gn:admin1_code":"17",
    "gn:admin2_code":"29.0",
    "gn:asciiname":"Ampliacion Atlihuayan",
    "gn:cc2":"MX",
    "gn:country_code":"MX",
    "gn:dem":1197,
    "gn:feature_class":"P",
    "gn:feature_code":"PPL",
    "gn:name":"Ampliaci\u00f3n Atlihuayan",
    "gn:population":76,
    "gn:timezone":"America/Mexico_City",
    "iso:country":"MX",
    "name:und_x_variant":[
        "Altlihuayan",
        "Atlihuayan"
    ],
    "wof:name":"Ampliacion Atlihuayan",
    "wof:placetype":"locality",
    "wof:population":76
},
  "geometry": {"coordinates":[-99.08222000000001,18.86167],"type":"Point"}
}