{
  "type": "Feature",
  "properties": {
    "gn:admin1_code":"13",
    "gn:admin2_code":"40.0",
    "gn:asciiname":"La Cienega",
    "gn:country_code":"MX",
    "gn:dem":1278,
    "gn:feature_class":"P",
    "gn:feature_code":"PPL",
    "gn:name":"La Ci\u00e9nega",
    "gn:population":267,
    "gn:timezone":"America/Mexico_City",
    "iso:country":"MX",
    "name:ceb_x_preferred":[
        "La Cienega"
    ],
    "name:spa_x_preferred":[
        "La Ci\u00e9nega"
    ],
    "name:swe_x_preferred":[
        "La Cienega"
    ],
    "name:und_x_variant":[
        "Ci\u00e9nega",
        "Ci\u00e9naga"
    ],
    "wof:name":"La Cienega",
    "wof:placetype":"locality",
    "wof:population":267
},
  "geometry": {"coordinates":[-99.04589,21.0142],"type":"Point"}
}