{
  "type": "Feature",
  "properties": {
    "gn:admin1_code":"20",
    "gn:admin2_code":"136.0",
    "gn:asciiname":"Colonia Ampliacion Aeropuerto",
    "gn:country_code":"MX",
    "gn:dem":118,
    "gn:feature_class":"P",
    "gn:feature_code":"PPL",
    "gn:name":"Colonia Ampliaci\u00f3n Aeropuerto",
    "gn:population":595,
    "gn:timezone":"America/Mexico_City",
    "iso:country":"MX",
    "name:und_x_variant":[
        "Colonia Ampliaci\u00f3n Aeropuerto"
    ],
    "wof:name":"Colonia Ampliacion Aeropuerto",
    "wof:placetype":"locality",
    "wof:population":595
},
  "geometry": {"coordinates":[-96.51582999999999,17.89333],"type":"Point"}
}