{
  "type": "Feature",
  "properties": {
    "gn:admin1_code":"2",
    "gn:admin2_code":"1.0",
    "gn:asciiname":"Villa de Juarez",
    "gn:country_code":"MX",
    "gn:dem":235,
    "gn:feature_class":"P",
    "gn:feature_code":"PPL",
    "gn:name":"Villa de Ju\u00e1rez",
    "gn:population":0,
    "gn:timezone":"America/Tijuana",
    "iso:country":"MX",
    "name:spa_x_preferred":[
        "Villa de Ju\u00e1rez"
    ],
    "name:spa_x_variant":[
        "San Antonio de las Minas"
    ],
    "wof:name":"Villa de Juarez",
    "wof:placetype":"locality"
},
  "geometry": {"coordinates":[-116.65237,31.97037000000001],"type":"Point"}
}