{
  "type": "Feature",
  "properties": {
    "gn:admin1_code":"5",
    "gn:admin2_code":"26.0",
    "gn:asciiname":"Chen Hoc",
    "gn:country_code":"MX",
    "gn:dem":1318,
    "gn:feature_class":"P",
    "gn:feature_code":"PPL",
    "gn:name":"Chen Hoc",
    "gn:population":176,
    "gn:timezone":"America/Mexico_City",
    "iso:country":"MX",
    "wof:name":"Chen Hoc",
    "wof:placetype":"locality",
    "wof:population":176
},
  "geometry": {"coordinates":[-92.6675,16.9525],"type":"Point"}
}