{
  "type": "Feature",
  "properties": {
    "gn:admin1_code":"3",
    "gn:admin2_code":"9.0",
    "gn:asciiname":"Ensenada Blanca",
    "gn:country_code":"MX",
    "gn:dem":-3,
    "gn:feature_class":"P",
    "gn:feature_code":"PPL",
    "gn:name":"Ensenada Blanca",
    "gn:population":255,
    "gn:timezone":"America/Mazatlan",
    "iso:country":"MX",
    "name:sco_x_preferred":[
        "Ensenada Blanca"
    ],
    "name:srp_x_preferred":[
        "\u0415\u043d\u0441\u0435\u043d\u0430\u0434\u0430 \u0411\u043b\u0430\u043d\u043a\u0430"
    ],
    "wof:name":"Ensenada Blanca",
    "wof:placetype":"locality",
    "wof:population":255
},
  "geometry": {"coordinates":[-111.24984000000001,25.72698],"type":"Point"}
}