{
  "type": "Feature",
  "properties": {
    "gn:admin1_code":"26",
    "gn:admin2_code":"18.0",
    "gn:asciiname":"Mexico (Grupo Mexico)",
    "gn:country_code":"MX",
    "gn:dem":39,
    "gn:feature_class":"P",
    "gn:feature_code":"PPL",
    "gn:name":"M\u00e9xico (Grupo M\u00e9xico)",
    "gn:population":77,
    "gn:timezone":"America/Hermosillo",
    "iso:country":"MX",
    "name:und_x_variant":[
        "M\u00e9xico (Grupo M\u00e9xico)"
    ],
    "wof:name":"Mexico (Grupo Mexico)",
    "wof:placetype":"locality",
    "wof:population":77
},
  "geometry": {"coordinates":[-109.93389000000001,27.41806],"type":"Point"}
}