{
  "type": "Feature",
  "properties": {
    "gn:admin1_code":"26.0",
    "gn:admin2_code":"18.0",
    "gn:asciiname":"Jupapobampo",
    "gn:country_code":"MX",
    "gn:dem":222,
    "gn:feature_class":"P",
    "gn:feature_code":"PPL",
    "gn:name":"Jupapobampo",
    "gn:population":0,
    "gn:timezone":"America/Hermosillo",
    "iso:country":"MX",
    "name:spa_x_preferred":[
        "Jupapobampo"
    ],
    "name:und_x_variant":[
        "Jupababpo"
    ],
    "wof:name":"Jupapobampo",
    "wof:placetype":"locality"
},
  "geometry": {"coordinates":[-110.10341,28.00135],"type":"Point"}
}