{
  "type": "Feature",
  "properties": {
    "gn:admin1_code":"32",
    "gn:admin2_code":"51.0",
    "gn:asciiname":"San Luisito (Olivia Martinez de Carrera)",
    "gn:country_code":"MX",
    "gn:dem":1842,
    "gn:feature_class":"P",
    "gn:feature_code":"PPL",
    "gn:name":"San Luisito (Olivia Mart\u00ednez de Carrera)",
    "gn:population":7,
    "gn:timezone":"America/Mexico_City",
    "iso:country":"MX",
    "name:und_x_variant":[
        "San Luisito (Olivia Mart\u00ednez de Carrera)"
    ],
    "wof:name":"San Luisito (Olivia Martinez de Carrera)",
    "wof:placetype":"locality",
    "wof:population":7
},
  "geometry": {"coordinates":[-102.32889,23.87056],"type":"Point"}
}