{
  "type": "Feature",
  "properties": {
    "gn:admin1_code":"14",
    "gn:admin2_code":"97.0",
    "gn:asciiname":"Real del Valle (El Paraiso) [Fraccionamiento]",
    "gn:country_code":"MX",
    "gn:dem":1533,
    "gn:feature_class":"P",
    "gn:feature_code":"PPL",
    "gn:name":"Real del Valle (El Para\u00edso) [Fraccionamiento]",
    "gn:population":13949,
    "gn:timezone":"America/Mexico_City",
    "iso:country":"MX",
    "name:und_x_variant":[
        "Real del Valle (El Para\u00edso) [Fraccionamiento]"
    ],
    "wof:name":"Real del Valle (El Paraiso) [Fraccionamiento]",
    "wof:placetype":"locality",
    "wof:population":13949
},
  "geometry": {"coordinates":[-103.36972,20.54556],"type":"Point"}
}