{
  "type": "Feature",
  "properties": {
    "gn:admin1_code":"24.0",
    "gn:admin2_code":"58.0",
    "gn:asciiname":"La Balsa",
    "gn:country_code":"MX",
    "gn:dem":252,
    "gn:feature_class":"P",
    "gn:feature_code":"PPL",
    "gn:name":"La Balsa",
    "gn:population":0,
    "gn:timezone":"America/Mexico_City",
    "iso:country":"MX",
    "name:spa_x_preferred":[
        "La Balsa"
    ],
    "wof:name":"La Balsa",
    "wof:placetype":"locality"
},
  "geometry": {"coordinates":[-99.27312000000001,22.38538],"type":"Point"}
}