{
  "type": "Feature",
  "properties": {
    "gn:admin1_code":"5",
    "gn:admin2_code":"101.0",
    "gn:asciiname":"El Sabino",
    "gn:country_code":"MX",
    "gn:dem":693,
    "gn:feature_class":"P",
    "gn:feature_code":"PPL",
    "gn:name":"El Sabino",
    "gn:population":38,
    "gn:timezone":"America/Mexico_City",
    "iso:country":"MX",
    "name:spa_x_preferred":[
        "El Sabino"
    ],
    "name:und_x_variant":[
        "Sabinito",
        "El Sabinito"
    ],
    "wof:name":"El Sabino",
    "wof:placetype":"locality",
    "wof:population":38
},
  "geometry": {"coordinates":[-93.04771,16.69068],"type":"Point"}
}