{
  "type": "Feature",
  "properties": {
    "gn:admin1_code":"15.0",
    "gn:asciiname":"Huitzo",
    "gn:country_code":"MX",
    "gn:dem":1781,
    "gn:feature_class":"P",
    "gn:feature_code":"PPL",
    "gn:name":"Huitz\u00f3",
    "gn:population":0,
    "gn:timezone":"America/Mexico_City",
    "iso:country":"MX",
    "name:spa_x_preferred":[
        "Huitz\u00f3"
    ],
    "wof:name":"Huitzo",
    "wof:placetype":"locality"
},
  "geometry": {"coordinates":[-102.07388,19.98485],"type":"Point"}
}