{
  "type": "Feature",
  "properties": {
    "gn:admin1_code":"5.0",
    "gn:asciiname":"El Geranio",
    "gn:country_code":"MX",
    "gn:dem":795,
    "gn:feature_class":"P",
    "gn:feature_code":"PPL",
    "gn:name":"El Geranio",
    "gn:population":0,
    "gn:timezone":"America/Mexico_City",
    "iso:country":"MX",
    "name:spa_x_preferred":[
        "El Geranio"
    ],
    "wof:name":"El Geranio",
    "wof:placetype":"locality"
},
  "geometry": {"coordinates":[-93.06707,15.93822],"type":"Point"}
}