{
  "type": "Feature",
  "properties": {
    "gn:admin1_code":"20",
    "gn:admin2_code":"502.0",
    "gn:asciiname":"Barrio Guadalupe",
    "gn:country_code":"MX",
    "gn:dem":1433,
    "gn:feature_class":"P",
    "gn:feature_code":"PPL",
    "gn:name":"Barrio Guadalupe",
    "gn:population":91,
    "gn:timezone":"America/Mexico_City",
    "iso:country":"MX",
    "wof:name":"Barrio Guadalupe",
    "wof:placetype":"locality",
    "wof:population":91
},
  "geometry": {"coordinates":[-95.91972,17.15611],"type":"Point"}
}