{
  "type": "Feature",
  "properties": {
    "gn:admin1_code":"23.0",
    "gn:asciiname":"Yodzonot",
    "gn:country_code":"MX",
    "gn:dem":32,
    "gn:feature_class":"P",
    "gn:feature_code":"PPL",
    "gn:name":"Yodzonot",
    "gn:population":0,
    "gn:timezone":"America/Cancun",
    "iso:country":"MX",
    "name:spa_x_preferred":[
        "Yodzonot"
    ],
    "wof:name":"Yodzonot",
    "wof:placetype":"locality"
},
  "geometry": {"coordinates":[-88.2124,20.18609],"type":"Point"}
}