{
  "type": "Feature",
  "properties": {
    "gn:admin1_code":"25",
    "gn:admin2_code":"10.0",
    "gn:asciiname":"Las Estacas",
    "gn:country_code":"MX",
    "gn:dem":51,
    "gn:feature_class":"P",
    "gn:feature_code":"PPL",
    "gn:name":"Las Estacas",
    "gn:population":0,
    "gn:timezone":"America/Mazatlan",
    "iso:country":"MX",
    "name:und_x_variant":[
        "Estacas",
        "Las Estacas"
    ],
    "wof:name":"Las Estacas",
    "wof:placetype":"locality"
},
  "geometry": {"coordinates":[-108.76560000000001,26.26872],"type":"Point"}
}