{
  "type": "Feature",
  "properties": {
    "gn:admin1_code":"19.0",
    "gn:admin2_code":"20.0",
    "gn:asciiname":"Las Penitas",
    "gn:country_code":"MX",
    "gn:dem":160,
    "gn:feature_class":"P",
    "gn:feature_code":"PPL",
    "gn:name":"Las Pe\u00f1itas",
    "gn:population":0,
    "gn:timezone":"America/Monterrey",
    "iso:country":"MX",
    "name:spa_x_preferred":[
        "Las Pe\u00f1itas"
    ],
    "wof:name":"Las Penitas",
    "wof:placetype":"locality"
},
  "geometry": {"coordinates":[-98.70791,25.91826],"type":"Point"}
}