{
  "type": "Feature",
  "properties": {
    "gn:admin1_code":"12",
    "gn:admin2_code":"7.0",
    "gn:asciiname":"Copaltepec",
    "gn:country_code":"MX",
    "gn:dem":1255,
    "gn:feature_class":"P",
    "gn:feature_code":"PPL",
    "gn:name":"Copaltepec",
    "gn:population":150,
    "gn:timezone":"America/Mexico_City",
    "iso:country":"MX",
    "wof:name":"Copaltepec",
    "wof:placetype":"locality",
    "wof:population":150
},
  "geometry": {"coordinates":[-100.10865,18.26908],"type":"Point"}
}