{
  "type": "Feature",
  "properties": {
    "gn:admin1_code":"28.0",
    "gn:admin2_code":"24.0",
    "gn:asciiname":"La Pita",
    "gn:country_code":"MX",
    "gn:dem":92,
    "gn:feature_class":"P",
    "gn:feature_code":"PPL",
    "gn:name":"La Pita",
    "gn:population":0,
    "gn:timezone":"America/Monterrey",
    "iso:country":"MX",
    "name:spa_x_preferred":[
        "La Pita"
    ],
    "wof:name":"La Pita",
    "wof:placetype":"locality"
},
  "geometry": {"coordinates":[-99.12260999999999,26.34833],"type":"Point"}
}