{
  "type": "Feature",
  "properties": {
    "gn:admin1_code":"21",
    "gn:admin2_code":"88",
    "gn:asciiname":"Plan de Guadalupe (Barrio del Penon)",
    "gn:country_code":"MX",
    "gn:dem":932,
    "gn:feature_class":"P",
    "gn:feature_code":"PPL",
    "gn:name":"Plan de Guadalupe (Barrio del Pe\u00f1\u00f3n)",
    "gn:population":25,
    "gn:timezone":"America/Mexico_City",
    "iso:country":"MX",
    "name:und_x_variant":[
        "Plan de Guadalupe (Barrio del Pe\u00f1\u00f3n)"
    ],
    "wof:name":"Plan de Guadalupe (Barrio del Penon)",
    "wof:placetype":"locality",
    "wof:population":25
},
  "geometry": {"coordinates":[-97.57904000000001,20.02604],"type":"Point"}
}