{
  "type": "Feature",
  "properties": {
    "gn:admin1_code":"16",
    "gn:admin2_code":"83",
    "gn:asciiname":"El Aguililla",
    "gn:country_code":"MX",
    "gn:dem":1705,
    "gn:feature_class":"P",
    "gn:feature_code":"PPL",
    "gn:name":"El Aguililla",
    "gn:population":11,
    "gn:timezone":"America/Mexico_City",
    "iso:country":"MX",
    "wof:name":"El Aguililla",
    "wof:placetype":"locality",
    "wof:population":11
},
  "geometry": {"coordinates":[-102.31889,19.23333],"type":"Point"}
}