{
  "type": "Feature",
  "properties": {
    "gn:admin1_code":"23",
    "gn:admin2_code":"7.0",
    "gn:asciiname":"San Martiniano",
    "gn:country_code":"MX",
    "gn:dem":13,
    "gn:feature_class":"P",
    "gn:feature_code":"PPL",
    "gn:name":"San Martiniano",
    "gn:population":206,
    "gn:timezone":"America/Cancun",
    "iso:country":"MX",
    "name:spa_x_preferred":[
        "San Martiniano"
    ],
    "wof:name":"San Martiniano",
    "wof:placetype":"locality",
    "wof:population":206
},
  "geometry": {"coordinates":[-87.28238,20.82937],"type":"Point"}
}