{
  "type": "Feature",
  "properties": {
    "gn:admin1_code":"12",
    "gn:admin2_code":"79.0",
    "gn:asciiname":"Ixcatla",
    "gn:country_code":"MX",
    "gn:dem":1495,
    "gn:feature_class":"P",
    "gn:feature_code":"PPL",
    "gn:name":"Ixcatla",
    "gn:population":1382,
    "gn:timezone":"America/Mexico_City",
    "iso:country":"MX",
    "wof:name":"Ixcatla",
    "wof:placetype":"locality",
    "wof:population":1382
},
  "geometry": {"coordinates":[-98.99944000000001,17.4225],"type":"Point"}
}