{
  "type": "Feature",
  "properties": {
    "gn:admin1_code":"1",
    "gn:admin2_code":"1.0",
    "gn:asciiname":"Rancho Benjamin Chavez Ruiz",
    "gn:country_code":"MX",
    "gn:dem":1904,
    "gn:feature_class":"P",
    "gn:feature_code":"PPL",
    "gn:name":"Rancho Benjam\u00edn Ch\u00e1vez Ruiz",
    "gn:population":6,
    "gn:timezone":"America/Mexico_City",
    "iso:country":"MX",
    "name:und_x_variant":[
        "Rancho Benjam\u00edn Ch\u00e1vez Ruiz"
    ],
    "wof:name":"Rancho Benjamin Chavez Ruiz",
    "wof:placetype":"locality",
    "wof:population":6
},
  "geometry": {"coordinates":[-102.26694000000001,21.82222],"type":"Point"}
}