{
  "type": "Feature",
  "properties": {
    "gn:admin1_code":"4",
    "gn:admin2_code":"11.0",
    "gn:asciiname":"Ramonal",
    "gn:country_code":"MX",
    "gn:dem":46,
    "gn:feature_class":"P",
    "gn:feature_code":"PPL",
    "gn:name":"Ramonal",
    "gn:population":0,
    "gn:timezone":"America/Merida",
    "iso:country":"MX",
    "name:spa_x_preferred":[
        "Ramonal"
    ],
    "wof:name":"Ramonal",
    "wof:placetype":"locality"
},
  "geometry": {"coordinates":[-91.1279,18.1004],"type":"Point"}
}