{
  "type": "Feature",
  "properties": {
    "gn:admin1_code":"21",
    "gn:admin2_code":"207.0",
    "gn:asciiname":"Tatzecuala",
    "gn:country_code":"MX",
    "gn:dem":2078,
    "gn:feature_class":"P",
    "gn:feature_code":"PPL",
    "gn:name":"Tatzecuala",
    "gn:population":762,
    "gn:timezone":"America/Mexico_City",
    "iso:country":"MX",
    "wof:name":"Tatzecuala",
    "wof:placetype":"locality",
    "wof:population":762
},
  "geometry": {"coordinates":[-97.53722,19.86944],"type":"Point"}
}