{
  "type": "Feature",
  "properties": {
    "gn:admin1_code":"5",
    "gn:admin2_code":"44.0",
    "gn:asciiname":"Cacate",
    "gn:country_code":"MX",
    "gn:dem":1476,
    "gn:feature_class":"P",
    "gn:feature_code":"PPL",
    "gn:name":"Cacat\u00e9",
    "gn:population":0,
    "gn:timezone":"America/Mexico_City",
    "iso:country":"MX",
    "name:spa_x_preferred":[
        "Cacat\u00e9"
    ],
    "name:und_x_variant":[
        "Cadate",
        "Cacate"
    ],
    "wof:name":"Cacate",
    "wof:placetype":"locality"
},
  "geometry": {"coordinates":[-92.83485,16.84534],"type":"Point"}
}