{
  "type": "Feature",
  "properties": {
    "gn:admin1_code":"24",
    "gn:admin2_code":"35",
    "gn:asciiname":"Doctor Everardo Neumann Pena [Clinica Psiquiatrica]",
    "gn:country_code":"MX",
    "gn:dem":1843,
    "gn:feature_class":"P",
    "gn:feature_code":"PPL",
    "gn:name":"Doctor Everardo Neumann Pe\u00f1a [Cl\u00ednica Psiqui\u00e1trica]",
    "gn:population":35,
    "gn:timezone":"America/Mexico_City",
    "iso:country":"MX",
    "name:und_x_variant":[
        "Doctor Everardo Neumann Pe\u00f1a [Cl\u00ednica Psiqui\u00e1trica]"
    ],
    "wof:name":"Doctor Everardo Neumann Pena [Clinica Psiquiatrica]",
    "wof:placetype":"locality",
    "wof:population":35
},
  "geometry": {"coordinates":[-100.90139000000001,22.20972],"type":"Point"}
}