{
  "type": "Feature",
  "properties": {
    "gn:admin1_code":"30.0",
    "gn:admin2_code":"161.0",
    "gn:asciiname":"El Jalamate",
    "gn:country_code":"MX",
    "gn:dem":66,
    "gn:feature_class":"P",
    "gn:feature_code":"PPL",
    "gn:name":"El Jalamate",
    "gn:population":1,
    "gn:timezone":"America/Mexico_City",
    "iso:country":"MX",
    "name:spa_x_preferred":[
        "El Jalamate"
    ],
    "wof:name":"El Jalamate",
    "wof:placetype":"locality",
    "wof:population":1
},
  "geometry": {"coordinates":[-98.37056,21.54639],"type":"Point"}
}