{
  "type": "Feature",
  "properties": {
    "gn:admin1_code":"11",
    "gn:admin2_code":"3.0",
    "gn:asciiname":"Bonito",
    "gn:country_code":"MX",
    "gn:dem":2010,
    "gn:feature_class":"P",
    "gn:feature_code":"PPL",
    "gn:name":"Bonito",
    "gn:population":116,
    "gn:timezone":"America/Mexico_City",
    "iso:country":"MX",
    "wof:name":"Bonito",
    "wof:placetype":"locality",
    "wof:population":116
},
  "geometry": {"coordinates":[-100.61833,21.03722],"type":"Point"}
}