{
  "type": "Feature",
  "properties": {
    "gn:admin1_code":"16.0",
    "gn:admin2_code":"96.0",
    "gn:asciiname":"Los Culebros",
    "gn:country_code":"MX",
    "gn:dem":533,
    "gn:feature_class":"P",
    "gn:feature_code":"PPL",
    "gn:name":"Los Culebros",
    "gn:population":0,
    "gn:timezone":"America/Mexico_City",
    "iso:country":"MX",
    "name:spa_x_preferred":[
        "Los Culebros"
    ],
    "wof:name":"Los Culebros",
    "wof:placetype":"locality"
},
  "geometry": {"coordinates":[-102.36077,18.63716],"type":"Point"}
}