{
  "type": "Feature",
  "properties": {
    "iso:country":"MX",
    "qs_pg:aaroncc":"MX",
    "qs_pg:name":"Infonavit la Huasteca",
    "qs_pg:name_adm0":"M\u00e9xico",
    "qs_pg:name_adm1":"Nuevo Leon",
    "qs_pg:photos":37,
    "qs_pg:photos_1k":7,
    "qs_pg:photos_9k":1,
    "qs_pg:photos_9r":2,
    "qs_pg:photos_all":37,
    "qs_pg:photos_sr":2,
    "qs_pg:pop_sr":0,
    "qs_pg:qs_pg_placetype":"neighbourhood",
    "qs_pg:qs_pg_placetype_gp":"Suburb",
    "qs_pg:woe_adm0":23424900,
    "woe:adm0_id":23424900,
    "woe:name_adm0":"M\u00e9xico",
    "woe:name_adm1":"Nuevo Leon",
    "woe:placetype":"Suburb",
    "wof:name":"Infonavit la Huasteca",
    "wof:placetype":"neighbourhood"
},
  "geometry": {"coordinates":[-100.46130100000001,25.651855],"type":"Point"}
}