{
  "type": "Feature",
  "properties": {
    "gn:admin1_code":"23",
    "gn:admin2_code":"3",
    "gn:asciiname":"Sufre y Calla",
    "gn:country_code":"MX",
    "gn:dem":5,
    "gn:feature_class":"P",
    "gn:feature_code":"PPL",
    "gn:name":"Sufre y Calla",
    "gn:population":14,
    "gn:timezone":"America/Cancun",
    "iso:country":"MX",
    "wof:name":"Sufre y Calla",
    "wof:placetype":"locality",
    "wof:population":14
},
  "geometry": {"coordinates":[-86.86067,21.24019],"type":"Point"}
}