{
  "type": "Feature",
  "properties": {
    "gn:admin1_code":"28",
    "gn:admin2_code":"3.0",
    "gn:asciiname":"Unidos Avanzamos",
    "gn:country_code":"MX",
    "gn:dem":17,
    "gn:feature_class":"P",
    "gn:feature_code":"PPL",
    "gn:name":"Unidos Avanzamos",
    "gn:population":1008,
    "gn:timezone":"America/Monterrey",
    "iso:country":"MX",
    "wof:name":"Unidos Avanzamos",
    "wof:placetype":"locality",
    "wof:population":1008
},
  "geometry": {"coordinates":[-97.97167,22.43389],"type":"Point"}
}