{
  "type": "Feature",
  "properties": {
    "gn:admin1_code":"27",
    "gn:admin2_code":"6.0",
    "gn:asciiname":"Libertad Quinta Seccion",
    "gn:country_code":"MX",
    "gn:dem":14,
    "gn:feature_class":"P",
    "gn:feature_code":"PPL",
    "gn:name":"Libertad Quinta Secci\u00f3n",
    "gn:population":0,
    "gn:timezone":"America/Mexico_City",
    "iso:country":"MX",
    "name:spa_x_preferred":[
        "Libertad Quinta Secci\u00f3n"
    ],
    "wof:name":"Libertad Quinta Seccion",
    "wof:placetype":"locality"
},
  "geometry": {"coordinates":[-93.38236999999999,18.16136],"type":"Point"}
}