{
  "type": "Feature",
  "properties": {
    "gn:admin1_code":"11",
    "gn:admin2_code":"14",
    "gn:asciiname":"Regalada de Arriba",
    "gn:country_code":"MX",
    "gn:dem":1894,
    "gn:feature_class":"P",
    "gn:feature_code":"PPL",
    "gn:name":"Regalada de Arriba",
    "gn:population":31,
    "gn:timezone":"America/Mexico_City",
    "iso:country":"MX",
    "wof:name":"Regalada de Arriba",
    "wof:placetype":"locality",
    "wof:population":31
},
  "geometry": {"coordinates":[-100.80444,21.11028],"type":"Point"}
}