{
  "type": "Feature",
  "properties": {
    "gn:admin1_code":"7",
    "gn:admin2_code":"23.0",
    "gn:asciiname":"Santa Fe del Pino",
    "gn:country_code":"MX",
    "gn:dem":890,
    "gn:feature_class":"P",
    "gn:feature_code":"PPL",
    "gn:name":"Santa Fe del Pino",
    "gn:population":0,
    "gn:timezone":"America/Monterrey",
    "iso:country":"MX",
    "name:und_x_variant":[
        "La Morita"
    ],
    "wof:name":"Santa Fe del Pino",
    "wof:placetype":"locality"
},
  "geometry": {"coordinates":[-103.19925000000001,28.65619],"type":"Point"}
}