{
  "type": "Feature",
  "properties": {
    "gn:admin1_code":"20",
    "gn:admin2_code":"9.0",
    "gn:asciiname":"San Pedro Ozumacin",
    "gn:country_code":"MX",
    "gn:dem":398,
    "gn:feature_class":"P",
    "gn:feature_code":"PPL",
    "gn:name":"San Pedro Ozumac\u00edn",
    "gn:population":1783,
    "gn:timezone":"America/Mexico_City",
    "iso:country":"MX",
    "name:und_x_variant":[
        "San Pedro Ozumac\u00edn"
    ],
    "wof:name":"San Pedro Ozumacin",
    "wof:placetype":"locality",
    "wof:population":1783
},
  "geometry": {"coordinates":[-96.22556,17.67861],"type":"Point"}
}