{
  "type": "Feature",
  "properties": {
    "gn:admin1_code":"21.0",
    "gn:asciiname":"Amecatitla",
    "gn:country_code":"MX",
    "gn:dem":96,
    "gn:feature_class":"P",
    "gn:feature_code":"PPL",
    "gn:name":"Amecatitla",
    "gn:population":0,
    "gn:timezone":"America/Mexico_City",
    "iso:country":"MX",
    "name:spa_x_preferred":[
        "Amecatitla"
    ],
    "wof:name":"Amecatitla",
    "wof:placetype":"locality"
},
  "geometry": {"coordinates":[-96.84818,18.49036],"type":"Point"}
}