{
  "type": "Feature",
  "properties": {
    "gn:admin1_code":"20.0",
    "gn:admin2_code":"327.0",
    "gn:asciiname":"El Desvelo",
    "gn:country_code":"MX",
    "gn:dem":16,
    "gn:feature_class":"P",
    "gn:feature_code":"PPL",
    "gn:name":"El Desvelo",
    "gn:population":0,
    "gn:timezone":"America/Mexico_City",
    "iso:country":"MX",
    "name:spa_x_preferred":[
        "El Desvelo"
    ],
    "wof:name":"El Desvelo",
    "wof:placetype":"locality"
},
  "geometry": {"coordinates":[-94.14691000000001,16.27175],"type":"Point"}
}