{
  "type": "Feature",
  "properties": {
    "gn:admin1_code":"6",
    "gn:admin2_code":"2.0",
    "gn:asciiname":"La Herradura",
    "gn:country_code":"MX",
    "gn:dem":1238,
    "gn:feature_class":"P",
    "gn:feature_code":"PPL",
    "gn:name":"La Herradura",
    "gn:population":0,
    "gn:timezone":"America/Chihuahua",
    "iso:country":"MX",
    "name:spa_x_preferred":[
        "La Herradura"
    ],
    "name:und_x_variant":[
        "Rancho La Herradura"
    ],
    "wof:name":"La Herradura",
    "wof:placetype":"locality"
},
  "geometry": {"coordinates":[-105.85601,28.90891],"type":"Point"}
}