{
  "type": "Feature",
  "properties": {
    "gn:admin1_code":"11",
    "gn:admin2_code":"3",
    "gn:asciiname":"La Picuda",
    "gn:country_code":"MX",
    "gn:dem":2169,
    "gn:feature_class":"P",
    "gn:feature_code":"PPL",
    "gn:name":"La Picuda",
    "gn:population":11,
    "gn:timezone":"America/Mexico_City",
    "iso:country":"MX",
    "wof:name":"La Picuda",
    "wof:placetype":"locality",
    "wof:population":11
},
  "geometry": {"coordinates":[-100.57389000000001,20.77528],"type":"Point"}
}