{
  "type": "Feature",
  "properties": {
    "gn:admin1_code":"20",
    "gn:admin2_code":"254.0",
    "gn:asciiname":"El Progreso",
    "gn:country_code":"MX",
    "gn:dem":2311,
    "gn:feature_class":"P",
    "gn:feature_code":"PPL",
    "gn:name":"El Progreso",
    "gn:population":61,
    "gn:timezone":"America/Mexico_City",
    "iso:country":"MX",
    "wof:name":"El Progreso",
    "wof:placetype":"locality",
    "wof:population":61
},
  "geometry": {"coordinates":[-96.51389,16.05611],"type":"Point"}
}