{
  "type": "Feature",
  "properties": {
    "gn:admin1_code":"5",
    "gn:admin2_code":"92.0",
    "gn:asciiname":"Monte Alegre",
    "gn:country_code":"MX",
    "gn:dem":252,
    "gn:feature_class":"P",
    "gn:feature_code":"PPL",
    "gn:name":"Monte Alegre",
    "gn:population":194,
    "gn:timezone":"America/Mexico_City",
    "iso:country":"MX",
    "wof:name":"Monte Alegre",
    "wof:placetype":"locality",
    "wof:population":194
},
  "geometry": {"coordinates":[-93.395,17.04056],"type":"Point"}
}