{
  "type": "Feature",
  "properties": {
    "gn:admin1_code":"15.0",
    "gn:admin2_code":"8.0",
    "gn:asciiname":"El Convento",
    "gn:country_code":"MX",
    "gn:dem":903,
    "gn:feature_class":"P",
    "gn:feature_code":"PPL",
    "gn:name":"El Convento",
    "gn:population":32,
    "gn:timezone":"America/Mexico_City",
    "iso:country":"MX",
    "name:spa_x_preferred":[
        "El Convento"
    ],
    "wof:name":"El Convento",
    "wof:placetype":"locality",
    "wof:population":32
},
  "geometry": {"coordinates":[-100.35697,18.68224],"type":"Point"}
}