{
  "type": "Feature",
  "properties": {
    "gn:admin1_code":"21",
    "gn:admin2_code":"108.0",
    "gn:asciiname":"Chimeca",
    "gn:country_code":"MX",
    "gn:dem":2359,
    "gn:feature_class":"P",
    "gn:feature_code":"PPL",
    "gn:name":"Chimeca",
    "gn:population":3,
    "gn:timezone":"America/Mexico_City",
    "iso:country":"MX",
    "wof:name":"Chimeca",
    "wof:placetype":"locality",
    "wof:population":3
},
  "geometry": {"coordinates":[-97.56522,19.38178],"type":"Point"}
}