{
  "type": "Feature",
  "properties": {
    "gn:admin1_code":"28",
    "gn:admin2_code":"2.0",
    "gn:asciiname":"Jarcias",
    "gn:country_code":"MX",
    "gn:dem":8,
    "gn:feature_class":"P",
    "gn:feature_code":"PPL",
    "gn:name":"Jarcias",
    "gn:population":8,
    "gn:timezone":"America/Monterrey",
    "iso:country":"MX",
    "wof:name":"Jarcias",
    "wof:placetype":"locality",
    "wof:population":8
},
  "geometry": {"coordinates":[-97.93805999999999,22.83917000000001],"type":"Point"}
}