{
  "type": "Feature",
  "properties": {
    "gn:admin1_code":"26",
    "gn:admin2_code":"29.0",
    "gn:asciiname":"El Lares",
    "gn:country_code":"MX",
    "gn:dem":279,
    "gn:feature_class":"P",
    "gn:feature_code":"PPL",
    "gn:name":"El Lares",
    "gn:population":0,
    "gn:timezone":"America/Hermosillo",
    "iso:country":"MX",
    "name:spa_x_preferred":[
        "El Lares"
    ],
    "wof:name":"El Lares",
    "wof:placetype":"locality"
},
  "geometry": {"coordinates":[-110.3175,28.49944],"type":"Point"}
}