{
  "type": "Feature",
  "properties": {
    "gn:admin1_code":"22.0",
    "gn:admin2_code":"8.0",
    "gn:asciiname":"Pio Doce",
    "gn:country_code":"MX",
    "gn:dem":2375,
    "gn:feature_class":"P",
    "gn:feature_code":"PPL",
    "gn:name":"P\u00edo Doce",
    "gn:population":0,
    "gn:timezone":"America/Mexico_City",
    "iso:country":"MX",
    "name:spa_x_preferred":[
        "P\u00edo Doce"
    ],
    "wof:name":"Pio Doce",
    "wof:placetype":"locality"
},
  "geometry": {"coordinates":[-100.25676,20.32924],"type":"Point"}
}