{
  "type": "Feature",
  "properties": {
    "gn:admin1_code":"30",
    "gn:admin2_code":"58.0",
    "gn:asciiname":"Emiliano Zapata",
    "gn:country_code":"MX",
    "gn:dem":151,
    "gn:feature_class":"P",
    "gn:feature_code":"PPL",
    "gn:name":"Emiliano Zapata",
    "gn:population":138,
    "gn:timezone":"America/Mexico_City",
    "iso:country":"MX",
    "name:spa_x_preferred":[
        "Emiliano Zapata"
    ],
    "wof:name":"Emiliano Zapata",
    "wof:placetype":"locality",
    "wof:population":138
},
  "geometry": {"coordinates":[-98.07473,21.11648],"type":"Point"}
}