{
  "type": "Feature",
  "properties": {
    "gn:admin1_code":"4.0",
    "gn:asciiname":"El Hular",
    "gn:country_code":"MX",
    "gn:dem":101,
    "gn:feature_class":"P",
    "gn:feature_code":"PPL",
    "gn:name":"El Hular",
    "gn:population":0,
    "gn:timezone":"America/Merida",
    "iso:country":"MX",
    "name:spa_x_preferred":[
        "El Hular"
    ],
    "wof:name":"El Hular",
    "wof:placetype":"locality"
},
  "geometry": {"coordinates":[-90.69511,18.67226],"type":"Point"}
}