{
  "type": "Feature",
  "properties": {
    "gn:admin1_code":"29",
    "gn:admin2_code":"10.0",
    "gn:asciiname":"San Antonotla",
    "gn:country_code":"MX",
    "gn:dem":2498,
    "gn:feature_class":"P",
    "gn:feature_code":"PPL",
    "gn:name":"San Anto\u00f1otla",
    "gn:population":73,
    "gn:timezone":"America/Mexico_City",
    "iso:country":"MX",
    "name:und_x_variant":[
        "San Anto\u00f1otla"
    ],
    "wof:name":"San Antonotla",
    "wof:placetype":"locality",
    "wof:population":73
},
  "geometry": {"coordinates":[-98.13365,19.29845],"type":"Point"}
}