{
  "type": "Feature",
  "properties": {
    "gn:admin1_code":"28",
    "gn:admin2_code":"35.0",
    "gn:asciiname":"San Pablo",
    "gn:country_code":"MX",
    "gn:dem":103,
    "gn:feature_class":"P",
    "gn:feature_code":"PPL",
    "gn:name":"San Pablo",
    "gn:population":0,
    "gn:timezone":"America/Monterrey",
    "iso:country":"MX",
    "name:und_x_variant":[
        "Rancho San Pablo",
        "San Pablo"
    ],
    "wof:name":"San Pablo",
    "wof:placetype":"locality"
},
  "geometry": {"coordinates":[-98.10818999999999,24.59742],"type":"Point"}
}