{
  "type": "Feature",
  "properties": {
    "gn:admin1_code":"2.0",
    "gn:admin2_code":"3.0",
    "gn:asciiname":"El Arco Caido",
    "gn:country_code":"MX",
    "gn:dem":998,
    "gn:feature_class":"P",
    "gn:feature_code":"PPL",
    "gn:name":"El Arco Ca\u00eddo",
    "gn:population":2,
    "gn:timezone":"America/Tijuana",
    "iso:country":"MX",
    "name:spa_x_preferred":[
        "El Escondido"
    ],
    "wof:name":"El Arco Caido",
    "wof:placetype":"locality",
    "wof:population":2
},
  "geometry": {"coordinates":[-116.34111,32.54917],"type":"Point"}
}