{
  "type": "Feature",
  "properties": {
    "gn:admin1_code":"30",
    "gn:admin2_code":"158.0",
    "gn:asciiname":"Vicente Riano",
    "gn:country_code":"MX",
    "gn:dem":27,
    "gn:feature_class":"P",
    "gn:feature_code":"PPL",
    "gn:name":"Vicente Ria\u00f1o",
    "gn:population":7,
    "gn:timezone":"America/Mexico_City",
    "iso:country":"MX",
    "name:und_x_variant":[
        "Vicente Ria\u00f1o"
    ],
    "wof:name":"Vicente Riano",
    "wof:placetype":"locality",
    "wof:population":7
},
  "geometry": {"coordinates":[-97.005,20.33889],"type":"Point"}
}