{
  "type": "Feature",
  "properties": {
    "gn:admin1_code":"13",
    "gn:admin2_code":"48.0",
    "gn:asciiname":"San Pedro Nopancalco",
    "gn:country_code":"MX",
    "gn:dem":2412,
    "gn:feature_class":"P",
    "gn:feature_code":"PPL",
    "gn:name":"San Pedro Nopancalco",
    "gn:population":0,
    "gn:timezone":"America/Mexico_City",
    "iso:country":"MX",
    "name:spa_x_preferred":[
        "San Pedro Nopancalco"
    ],
    "wof:name":"San Pedro Nopancalco",
    "wof:placetype":"locality"
},
  "geometry": {"coordinates":[-98.78982000000001,20.08952],"type":"Point"}
}