{
  "type": "Feature",
  "properties": {
    "gn:admin1_code":"25",
    "gn:admin2_code":"9.0",
    "gn:asciiname":"Agua Caliente",
    "gn:country_code":"MX",
    "gn:dem":61,
    "gn:feature_class":"P",
    "gn:feature_code":"PPL",
    "gn:name":"Agua Caliente",
    "gn:population":22,
    "gn:timezone":"America/Mazatlan",
    "iso:country":"MX",
    "wof:name":"Agua Caliente",
    "wof:placetype":"locality",
    "wof:population":22
},
  "geometry": {"coordinates":[-105.47629999999999,22.63519],"type":"Point"}
}