{
  "type": "Feature",
  "properties": {
    "gn:admin1_code":"16",
    "gn:admin2_code":"15.0",
    "gn:asciiname":"Los Cabos",
    "gn:country_code":"MX",
    "gn:dem":1750,
    "gn:feature_class":"P",
    "gn:feature_code":"PPL",
    "gn:name":"Los Cabos",
    "gn:population":9,
    "gn:timezone":"America/Mexico_City",
    "iso:country":"MX",
    "wof:name":"Los Cabos",
    "wof:placetype":"locality",
    "wof:population":9
},
  "geometry": {"coordinates":[-103.16722,18.54417],"type":"Point"}
}