{
  "type": "Feature",
  "properties": {
    "gn:admin1_code":"28.0",
    "gn:admin2_code":"27.0",
    "gn:asciiname":"Santa Cecilia",
    "gn:country_code":"MX",
    "gn:dem":123,
    "gn:feature_class":"P",
    "gn:feature_code":"PPL",
    "gn:name":"Santa Cecilia",
    "gn:population":3,
    "gn:timezone":"America/Matamoros",
    "iso:country":"MX",
    "name:spa_x_preferred":[
        "Santa Cecilia"
    ],
    "wof:name":"Santa Cecilia",
    "wof:placetype":"locality",
    "wof:population":3
},
  "geometry": {"coordinates":[-99.50749999999999,27.3925],"type":"Point"}
}