{
  "type": "Feature",
  "properties": {
    "gn:country":"MX",
    "gn:fcode":"PPL",
    "gn:population":0,
    "iso:country":"MX",
    "name:ara_x_preferred":[
        "\u0627\u0648\u0631\u064a\u0632\u0627\u0628\u0627"
    ],
    "name:cat_x_preferred":[
        "Orizaba"
    ],
    "name:deu_x_preferred":[
        "Orizaba"
    ],
    "name:est_x_preferred":[
        "Orizaba"
    ],
    "name:fas_x_preferred":[
        "\u0627\u0648\u0631\u06cc\u0632\u0627\u0628\u0627"
    ],
    "name:fra_x_preferred":[
        "Orizaba"
    ],
    "name:hun_x_preferred":[
        "Orizaba"
    ],
    "name:ita_x_preferred":[
        "Orizaba"
    ],
    "name:lad_x_preferred":[
        "Orizaba"
    ],
    "name:lit_x_preferred":[
        "Orisaba"
    ],
    "name:nld_x_preferred":[
        "Orizaba"
    ],
    "name:nor_x_preferred":[
        "Orizaba"
    ],
    "name:pol_x_preferred":[
        "Orizaba"
    ],
    "name:por_x_preferred":[
        "Orizaba"
    ],
    "name:rus_x_preferred":[
        "\u041e\u0440\u0438\u0441\u0430\u0431\u0430"
    ],
    "name:spa_x_preferred":[
        "Orizaba"
    ],
    "name:srp_x_preferred":[
        "\u041e\u0440\u0438\u0437\u0430\u0431\u0430"
    ],
    "name:swe_x_preferred":[
        "Orizaba"
    ],
    "name:urd_x_preferred":[
        "\u0627\u0648\u0631\u06cc\u0633\u0627\u0628\u0627"
    ],
    "name:vie_x_preferred":[
        "Orizaba"
    ],
    "name:war_x_preferred":[
        "Orizaba"
    ],
    "name:zho_x_preferred":[
        "\u5967\u91cc\u85a9\u5df4"
    ],
    "qs_pg:aaroncc":"MX",
    "qs_pg:gn_country":"MX",
    "qs_pg:gn_fcode":"PPL",
    "qs_pg:gn_pop":0,
    "qs_pg:name":"Orizaba",
    "qs_pg:name_adm0":"M\u00e9xico",
    "qs_pg:name_adm1":"Chiapas",
    "qs_pg:photos":8,
    "qs_pg:photos_1k":2,
    "qs_pg:photos_9k":1,
    "qs_pg:photos_9r":1,
    "qs_pg:photos_all":8,
    "qs_pg:photos_sr":1,
    "qs_pg:pop_sr":0,
    "qs_pg:qs_pg_placetype":"locality",
    "qs_pg:qs_pg_placetype_gp":"Town",
    "qs_pg:woe_adm0":23424900,
    "woe:adm0_id":23424900,
    "woe:name_adm0":"M\u00e9xico",
    "woe:name_adm1":"Chiapas",
    "woe:placetype":"Town",
    "wof:name":"Orizaba",
    "wof:placetype":"locality"
},
  "geometry": {"coordinates":[-94.08333,16.48333],"type":"Point"}
}