{
  "type": "Feature",
  "properties": {
    "gn:admin1_code":"4",
    "gn:admin2_code":"10.0",
    "gn:asciiname":"Santa Paulina",
    "gn:country_code":"MX",
    "gn:dem":118,
    "gn:feature_class":"P",
    "gn:feature_code":"PPL",
    "gn:name":"Santa Paulina",
    "gn:population":0,
    "gn:timezone":"America/Cancun",
    "iso:country":"MX",
    "name:spa_x_preferred":[
        "Santa Paulina"
    ],
    "wof:name":"Santa Paulina",
    "wof:placetype":"locality"
},
  "geometry": {"coordinates":[-89.21521,18.01151],"type":"Point"}
}