{
  "type": "Feature",
  "properties": {
    "gn:admin1_code":"25",
    "gn:admin2_code":"17.0",
    "gn:asciiname":"Ranchito",
    "gn:country_code":"MX",
    "gn:dem":71,
    "gn:feature_class":"P",
    "gn:feature_code":"PPL",
    "gn:name":"Ranchito",
    "gn:population":0,
    "gn:timezone":"America/Mazatlan",
    "iso:country":"MX",
    "wof:name":"Ranchito",
    "wof:placetype":"locality"
},
  "geometry": {"coordinates":[-108.23333,25.75],"type":"Point"}
}