{
  "type": "Feature",
  "properties": {
    "gn:admin1_code":"19.0",
    "gn:admin2_code":"44.0",
    "gn:asciiname":"El Cedrito",
    "gn:country_code":"MX",
    "gn:dem":300,
    "gn:feature_class":"P",
    "gn:feature_code":"PPL",
    "gn:name":"El Cedrito",
    "gn:population":0,
    "gn:timezone":"America/Monterrey",
    "iso:country":"MX",
    "name:spa_x_preferred":[
        "El Cedrito"
    ],
    "wof:name":"El Cedrito",
    "wof:placetype":"locality"
},
  "geometry": {"coordinates":[-100.19468999999999,26.81143],"type":"Point"}
}