{
  "type": "Feature",
  "properties": {
    "gn:admin1_code":"16",
    "gn:admin2_code":"112.0",
    "gn:asciiname":"Las Casas Blancas",
    "gn:country_code":"MX",
    "gn:dem":1710,
    "gn:feature_class":"P",
    "gn:feature_code":"PPL",
    "gn:name":"Las Casas Blancas",
    "gn:population":8,
    "gn:timezone":"America/Mexico_City",
    "iso:country":"MX",
    "wof:name":"Las Casas Blancas",
    "wof:placetype":"locality",
    "wof:population":8
},
  "geometry": {"coordinates":[-100.42028000000001,19.38583],"type":"Point"}
}