{
  "type": "Feature",
  "properties": {
    "gn:admin1_code":"10",
    "gn:admin2_code":"32.0",
    "gn:asciiname":"La Hermosa",
    "gn:country_code":"MX",
    "gn:dem":2073,
    "gn:feature_class":"P",
    "gn:feature_code":"PPL",
    "gn:name":"La Hermosa",
    "gn:population":0,
    "gn:timezone":"America/Monterrey",
    "iso:country":"MX",
    "name:spa_x_preferred":[
        "La Hermosa"
    ],
    "wof:name":"La Hermosa",
    "wof:placetype":"locality"
},
  "geometry": {"coordinates":[-105.29461000000001,24.89688],"type":"Point"}
}