{
  "type": "Feature",
  "properties": {
    "gn:admin1_code":"7",
    "gn:admin2_code":"35.0",
    "gn:asciiname":"La Joyita (Recreativo la Hacienda)",
    "gn:country_code":"MX",
    "gn:dem":1118,
    "gn:feature_class":"P",
    "gn:feature_code":"PPL",
    "gn:name":"La Joyita (Recreativo la Hacienda)",
    "gn:population":6,
    "gn:timezone":"America/Monterrey",
    "iso:country":"MX",
    "wof:name":"La Joyita (Recreativo la Hacienda)",
    "wof:placetype":"locality",
    "wof:population":6
},
  "geometry": {"coordinates":[-103.34638,25.56161],"type":"Point"}
}