{
  "type": "Feature",
  "properties": {
    "gn:admin1_code":"30",
    "gn:admin2_code":"151.0",
    "gn:asciiname":"Ojital",
    "gn:country_code":"MX",
    "gn:dem":70,
    "gn:feature_class":"P",
    "gn:feature_code":"PPL",
    "gn:name":"Ojital",
    "gn:population":0,
    "gn:timezone":"America/Mexico_City",
    "iso:country":"MX",
    "wof:name":"Ojital",
    "wof:placetype":"locality"
},
  "geometry": {"coordinates":[-97.58333,21.23333],"type":"Point"}
}