{
  "type": "Feature",
  "properties": {
    "gn:country":"MX",
    "gn:fcode":"PPL",
    "gn:population":0,
    "iso:country":"MX",
    "name:ara_x_preferred":[
        "\u0644\u0627 \u0647\u064a\u063a\u0648\u064a\u0631\u0627"
    ],
    "name:arg_x_preferred":[
        "La Higuera"
    ],
    "name:ben_x_preferred":[
        "\u09b2\u09be \u09b9\u09bf\u0997\u09c1\u09af\u09bc\u09c7\u09b0\u09be"
    ],
    "name:bul_x_preferred":[
        "\u041b\u0430 \u0418\u0433\u0435\u0440\u0430"
    ],
    "name:cat_x_preferred":[
        "La Higuera"
    ],
    "name:ceb_x_preferred":[
        "La Higuera"
    ],
    "name:deu_x_preferred":[
        "La Higuera"
    ],
    "name:ell_x_preferred":[
        "\u039b\u03b1 \u0399\u03b3\u03ba\u03ad\u03c1\u03b1"
    ],
    "name:epo_x_preferred":[
        "La Higuera"
    ],
    "name:fas_x_preferred":[
        "\u0644\u0627 \u0627\u06cc\u06af\u0631\u0627"
    ],
    "name:fin_x_preferred":[
        "La Higuera"
    ],
    "name:fra_x_preferred":[
        "La Higuera"
    ],
    "name:glg_x_preferred":[
        "La Higuera"
    ],
    "name:hun_x_preferred":[
        "La Higuera"
    ],
    "name:ind_x_preferred":[
        "La Higuera"
    ],
    "name:ita_x_preferred":[
        "La Higuera"
    ],
    "name:jpn_x_preferred":[
        "\u30a4\u30b2\u30e9"
    ],
    "name:kat_x_preferred":[
        "\u10da\u10d0-\u10d8\u10d2\u10d4\u10e0\u10d0"
    ],
    "name:lit_x_preferred":[
        "La Igera"
    ],
    "name:nld_x_preferred":[
        "La Higuera"
    ],
    "name:nor_x_preferred":[
        "La Higuera"
    ],
    "name:oss_x_preferred":[
        "\u041b\u0430-\u0418\u0433\u0435\u0440\u00e6"
    ],
    "name:pol_x_preferred":[
        "La Higuera"
    ],
    "name:por_x_preferred":[
        "La Higuera"
    ],
    "name:que_x_preferred":[
        "La Higuera"
    ],
    "name:ron_x_preferred":[
        "La Higuera"
    ],
    "name:rus_x_preferred":[
        "\u041b\u0430-\u0418\u0433\u0435\u0440\u0430"
    ],
    "name:scn_x_preferred":[
        "La Higuera"
    ],
    "name:spa_x_preferred":[
        "La Higuera"
    ],
    "name:swe_x_preferred":[
        "La Higuera"
    ],
    "name:tur_x_preferred":[
        "La Higuera"
    ],
    "name:ukr_x_preferred":[
        "\u0413\u0415\u0421 \u041b\u0430-\u0406\u0433\u0435\u0440\u0430"
    ],
    "name:und_x_variant":[
        "Higuera"
    ],
    "name:urd_x_preferred":[
        "\u0644\u0627 \u06c1\u06cc\u06af\u0648\u06cc\u0631\u0627"
    ],
    "name:vec_x_preferred":[
        "La Higuera"
    ],
    "name:zho_x_preferred":[
        "\u62c9\u4f0a\u683c\u62c9"
    ],
    "qs_pg:aaroncc":"MX",
    "qs_pg:gn_country":"MX",
    "qs_pg:gn_fcode":"PPL",
    "qs_pg:gn_pop":0,
    "qs_pg:name":"La Higuera",
    "qs_pg:name_adm0":"M\u00e9xico",
    "qs_pg:name_adm1":"Jalisco",
    "qs_pg:photos_9r":0,
    "qs_pg:photos_sr":0,
    "qs_pg:pop_sr":0,
    "qs_pg:qs_pg_placetype":"locality",
    "qs_pg:qs_pg_placetype_gp":"Town",
    "qs_pg:woe_adm0":23424900,
    "woe:adm0_id":23424900,
    "woe:name_adm0":"M\u00e9xico",
    "woe:name_adm1":"Jalisco",
    "woe:placetype":"Town",
    "wof:name":"La Higuera",
    "wof:placetype":"locality",
    "wof:population":324
},
  "geometry": {"coordinates":[-104.07680999999999,20.54528],"type":"Point"}
}