{
  "type": "Feature",
  "properties": {
    "gn:admin1_code":"10.0",
    "gn:admin2_code":"5.0",
    "gn:asciiname":"Labor de Guadalupe",
    "gn:country_code":"MX",
    "gn:dem":1867,
    "gn:feature_class":"P",
    "gn:feature_code":"PPL",
    "gn:name":"Labor de Guadalupe",
    "gn:population":0,
    "gn:timezone":"America/Monterrey",
    "iso:country":"MX",
    "name:und_x_variant":[
        "Labor de Guadaloupe"
    ],
    "wof:name":"Labor de Guadalupe",
    "wof:placetype":"locality"
},
  "geometry": {"coordinates":[-104.59569999999999,24.16333],"type":"Point"}
}