{
  "type": "Feature",
  "properties": {
    "gn:admin1_code":"20",
    "gn:admin2_code":"171.0",
    "gn:asciiname":"Piedra del Sol",
    "gn:country_code":"MX",
    "gn:dem":662,
    "gn:feature_class":"P",
    "gn:feature_code":"PPL",
    "gn:name":"Piedra del Sol",
    "gn:population":80,
    "gn:timezone":"America/Mexico_City",
    "iso:country":"MX",
    "wof:name":"Piedra del Sol",
    "wof:placetype":"locality",
    "wof:population":80
},
  "geometry": {"coordinates":[-96.71611,18.17028],"type":"Point"}
}