{
  "type": "Feature",
  "properties": {
    "gn:admin1_code":"19.0",
    "gn:admin2_code":"51.0",
    "gn:asciiname":"Carrizalejo",
    "gn:country_code":"MX",
    "gn:dem":429,
    "gn:feature_class":"P",
    "gn:feature_code":"PPL",
    "gn:name":"Carrizalejo",
    "gn:population":0,
    "gn:timezone":"America/Monterrey",
    "iso:country":"MX",
    "name:spa_x_preferred":[
        "Carrizalejo"
    ],
    "wof:name":"Carrizalejo",
    "wof:placetype":"locality"
},
  "geometry": {"coordinates":[-100.34639,26.42972],"type":"Point"}
}