{
  "type": "Feature",
  "properties": {
    "gn:admin1_code":"11",
    "gn:admin2_code":"33",
    "gn:asciiname":"La Canada del Pueblito",
    "gn:country_code":"MX",
    "gn:dem":1837,
    "gn:feature_class":"P",
    "gn:feature_code":"PPL",
    "gn:name":"La Ca\u00f1ada del Pueblito",
    "gn:population":30,
    "gn:timezone":"America/Mexico_City",
    "iso:country":"MX",
    "name:und_x_variant":[
        "La Ca\u00f1ada del Pueblito"
    ],
    "wof:name":"La Canada del Pueblito",
    "wof:placetype":"locality",
    "wof:population":30
},
  "geometry": {"coordinates":[-100.38306,21.47694],"type":"Point"}
}