{
  "type": "Feature",
  "properties": {
    "gn:admin1_code":"26.0",
    "gn:admin2_code":"58.0",
    "gn:asciiname":"Tule Viejo",
    "gn:country_code":"MX",
    "gn:dem":910,
    "gn:feature_class":"P",
    "gn:feature_code":"PPL",
    "gn:name":"Tule Viejo",
    "gn:population":0,
    "gn:timezone":"America/Hermosillo",
    "iso:country":"MX",
    "name:spa_x_preferred":[
        "Tule Viejo"
    ],
    "name:und_x_variant":[
        "Rancho El Tule"
    ],
    "wof:name":"Tule Viejo",
    "wof:placetype":"locality"
},
  "geometry": {"coordinates":[-110.83145,30.22941],"type":"Point"}
}