{
  "type": "Feature",
  "properties": {
    "gn:admin1_code":"30.0",
    "gn:asciiname":"El Zafiro",
    "gn:country_code":"MX",
    "gn:dem":53,
    "gn:feature_class":"P",
    "gn:feature_code":"PPL",
    "gn:name":"El Zafiro",
    "gn:population":0,
    "gn:timezone":"America/Mexico_City",
    "iso:country":"MX",
    "name:spa_x_preferred":[
        "El Zafiro"
    ],
    "wof:name":"El Zafiro",
    "wof:placetype":"locality"
},
  "geometry": {"coordinates":[-95.70101,17.85432999999999],"type":"Point"}
}