{
  "type": "Feature",
  "properties": {
    "gn:admin1_code":"14",
    "gn:admin2_code":"108",
    "gn:asciiname":"Piedra Blanca",
    "gn:country_code":"MX",
    "gn:dem":1105,
    "gn:feature_class":"P",
    "gn:feature_code":"PPL",
    "gn:name":"Piedra Blanca",
    "gn:population":16,
    "gn:timezone":"America/Mexico_City",
    "iso:country":"MX",
    "name:ceb_x_preferred":[
        "Piedra Blanca"
    ],
    "name:fra_x_preferred":[
        "Piedra Blanca"
    ],
    "name:ita_x_preferred":[
        "Piedra Blanca"
    ],
    "name:por_x_preferred":[
        "Piedra Blanca"
    ],
    "name:spa_x_preferred":[
        "Piedra Blanca"
    ],
    "name:zho_x_preferred":[
        "\u5f7c\u5fb7\u62c9\u5e03\u862d\u5361"
    ],
    "wof:name":"Piedra Blanca",
    "wof:placetype":"locality",
    "wof:population":16
},
  "geometry": {"coordinates":[-103.39778,19.4975],"type":"Point"}
}