{
  "type": "Feature",
  "properties": {
    "gn:admin1_code":"25",
    "gn:admin2_code":"16.0",
    "gn:asciiname":"Piaxtla de Abajo",
    "gn:country_code":"MX",
    "gn:dem":36,
    "gn:feature_class":"P",
    "gn:feature_code":"PPL",
    "gn:name":"Piaxtla de Abajo",
    "gn:population":0,
    "gn:timezone":"America/Mazatlan",
    "iso:country":"MX",
    "name:spa_x_preferred":[
        "Piaxtla de Abajo"
    ],
    "wof:name":"Piaxtla de Abajo",
    "wof:placetype":"locality"
},
  "geometry": {"coordinates":[-106.65922999999999,23.83254],"type":"Point"}
}