{
  "type": "Feature",
  "properties": {
    "gn:admin1_code":"6",
    "gn:admin2_code":"21",
    "gn:asciiname":"Castillon",
    "gn:country_code":"MX",
    "gn:dem":1211,
    "gn:feature_class":"P",
    "gn:feature_code":"PPL",
    "gn:name":"Castill\u00f3n",
    "gn:population":10,
    "gn:timezone":"America/Chihuahua",
    "iso:country":"MX",
    "name:und_x_variant":[
        "Castill\u00f3n"
    ],
    "wof:name":"Castillon",
    "wof:placetype":"locality",
    "wof:population":10
},
  "geometry": {"coordinates":[-105.40678,28.15504],"type":"Point"}
}