{
  "type": "Feature",
  "properties": {
    "gn:admin1_code":"6",
    "gn:admin2_code":"21",
    "gn:asciiname":"Castillon",
    "gn:country_code":"MX",
    "gn:dem":1211,
    "gn:feature_class":"P",
    "gn:feature_code":"PPL",
    "gn:name":"Castill\u00f3n",
    "gn:population":10,
    "gn:timezone":"America/Chihuahua",
    "iso:country":"MX",
    "name:cat_x_preferred":[
        "Castillon"
    ],
    "name:ceb_x_preferred":[
        "Castillon"
    ],
    "name:deu_x_preferred":[
        "Castillon"
    ],
    "name:fra_x_preferred":[
        "Castillon"
    ],
    "name:ind_x_preferred":[
        "Castillon"
    ],
    "name:ita_x_preferred":[
        "Castillon"
    ],
    "name:jpn_x_preferred":[
        "\u30ab\u30b9\u30c6\u30a3\u30e8\u30f3"
    ],
    "name:nds_x_preferred":[
        "Castillon"
    ],
    "name:nld_x_preferred":[
        "Castillon"
    ],
    "name:pms_x_preferred":[
        "Castillon"
    ],
    "name:pol_x_preferred":[
        "Castillon"
    ],
    "name:por_x_preferred":[
        "Castillon"
    ],
    "name:rus_x_preferred":[
        "\u041a\u0430\u0441\u0442\u0438\u0439\u043e\u043d"
    ],
    "name:slk_x_preferred":[
        "Castillon"
    ],
    "name:spa_x_preferred":[
        "Castillon"
    ],
    "name:srp_x_preferred":[
        "\u041a\u0430\u0441\u0442\u0438\u0458\u043e\u043d"
    ],
    "name:swe_x_preferred":[
        "Castillon"
    ],
    "name:ukr_x_preferred":[
        "\u041a\u0430\u0441\u0442\u0456\u0439\u043e\u043d"
    ],
    "name:und_x_variant":[
        "Castill\u00f3n"
    ],
    "name:zho_x_preferred":[
        "\u5361\u65af\u8482\u7fc1"
    ],
    "wof:name":"Castillon",
    "wof:placetype":"locality",
    "wof:population":10
},
  "geometry": {"coordinates":[-105.40678,28.15504],"type":"Point"}
}