{
  "type": "Feature",
  "properties": {
    "gn:admin1_code":"24",
    "gn:admin2_code":"34",
    "gn:asciiname":"La Primavera",
    "gn:country_code":"MX",
    "gn:dem":39,
    "gn:feature_class":"P",
    "gn:feature_code":"PPL",
    "gn:name":"La Primavera",
    "gn:population":13,
    "gn:timezone":"America/Mexico_City",
    "iso:country":"MX",
    "wof:name":"La Primavera",
    "wof:placetype":"locality",
    "wof:population":13
},
  "geometry": {"coordinates":[-98.63861,21.89583],"type":"Point"}
}