{
  "type": "Feature",
  "properties": {
    "gn:admin1_code":"26",
    "gn:admin2_code":"30.0",
    "gn:asciiname":"Santa Trinidad",
    "gn:country_code":"MX",
    "gn:dem":304,
    "gn:feature_class":"P",
    "gn:feature_code":"PPL",
    "gn:name":"Santa Trinidad",
    "gn:population":3,
    "gn:timezone":"America/Hermosillo",
    "iso:country":"MX",
    "name:spa_x_preferred":[
        "Santa Trinidad"
    ],
    "wof:name":"Santa Trinidad",
    "wof:placetype":"locality",
    "wof:population":3
},
  "geometry": {"coordinates":[-110.84667,29.3175],"type":"Point"}
}