{
  "type": "Feature",
  "properties": {
    "gn:admin1_code":"16",
    "gn:admin2_code":"50.0",
    "gn:asciiname":"Huanimoro",
    "gn:country_code":"MX",
    "gn:dem":2128,
    "gn:feature_class":"P",
    "gn:feature_code":"PPL",
    "gn:name":"Huanimoro",
    "gn:population":216,
    "gn:timezone":"America/Mexico_City",
    "iso:country":"MX",
    "wof:name":"Huanimoro",
    "wof:placetype":"locality",
    "wof:population":216
},
  "geometry": {"coordinates":[-100.50221999999999,19.90139],"type":"Point"}
}