{
  "type": "Feature",
  "properties": {
    "gn:admin1_code":"13",
    "gn:admin2_code":"84",
    "gn:asciiname":"Puerto Ingeniero Isidro Diaz",
    "gn:country_code":"MX",
    "gn:dem":2060,
    "gn:feature_class":"P",
    "gn:feature_code":"PPL",
    "gn:name":"Puerto Ingeniero Isidro D\u00edaz",
    "gn:population":13,
    "gn:timezone":"America/Mexico_City",
    "iso:country":"MX",
    "name:und_x_variant":[
        "Puerto Ingeniero Isidro D\u00edaz"
    ],
    "wof:name":"Puerto Ingeniero Isidro Diaz",
    "wof:placetype":"locality",
    "wof:population":13
},
  "geometry": {"coordinates":[-99.26027999999999,20.8075],"type":"Point"}
}