{
  "type": "Feature",
  "properties": {
    "gn:admin1_code":"10",
    "gn:admin2_code":"14",
    "gn:asciiname":"Mesilla Huizache",
    "gn:country_code":"MX",
    "gn:dem":1670,
    "gn:feature_class":"P",
    "gn:feature_code":"PPL",
    "gn:name":"Mesilla Huizache",
    "gn:population":12,
    "gn:timezone":"America/Monterrey",
    "iso:country":"MX",
    "wof:name":"Mesilla Huizache",
    "wof:placetype":"locality",
    "wof:population":12
},
  "geometry": {"coordinates":[-104.56778,23.15611],"type":"Point"}
}