{
  "type": "Feature",
  "properties": {
    "gn:admin1_code":"30",
    "gn:admin2_code":"23.0",
    "gn:asciiname":"Novara",
    "gn:country_code":"MX",
    "gn:dem":100,
    "gn:feature_class":"P",
    "gn:feature_code":"PPL",
    "gn:name":"Novara",
    "gn:population":0,
    "gn:timezone":"America/Mexico_City",
    "iso:country":"MX",
    "name:spa_x_preferred":[
        "Novara"
    ],
    "name:und_x_variant":[
        "Navara",
        "Javier Rojo G\u00f3mez",
        "Ejido Javier Rojo G\u00f3mez"
    ],
    "wof:name":"Novara",
    "wof:placetype":"locality"
},
  "geometry": {"coordinates":[-97.09291,20.02629],"type":"Point"}
}