{
  "type": "Feature",
  "properties": {
    "gn:admin1_code":"25.0",
    "gn:admin2_code":"7.0",
    "gn:asciiname":"La Sabana",
    "gn:country_code":"MX",
    "gn:dem":236,
    "gn:feature_class":"P",
    "gn:feature_code":"PPL",
    "gn:name":"La Sabana",
    "gn:population":0,
    "gn:timezone":"America/Mazatlan",
    "iso:country":"MX",
    "name:ceb_x_preferred":[
        "La S\u00e1bana"
    ],
    "name:spa_x_preferred":[
        "La Sabana"
    ],
    "name:und_x_variant":[
        "Sabinito",
        "El Sabino"
    ],
    "name:urd_x_preferred":[
        "\u0644\u0627 \u0633\u0627\u0628\u0627\u0646\u0627"
    ],
    "wof:name":"La Sabana",
    "wof:placetype":"locality"
},
  "geometry": {"coordinates":[-108.32243,26.69489],"type":"Point"}
}