{
  "type": "Feature",
  "properties": {
    "gn:admin1_code":"6",
    "gn:admin2_code":"29.0",
    "gn:asciiname":"La Hurta",
    "gn:country_code":"MX",
    "gn:dem":2017,
    "gn:feature_class":"P",
    "gn:feature_code":"PPL",
    "gn:name":"La Hurta",
    "gn:population":0,
    "gn:timezone":"America/Chihuahua",
    "iso:country":"MX",
    "name:spa_x_preferred":[
        "La Hurta"
    ],
    "wof:name":"La Hurta",
    "wof:placetype":"locality"
},
  "geometry": {"coordinates":[-107.42713000000001,26.16902],"type":"Point"}
}