{
  "type": "Feature",
  "properties": {
    "gn:admin1_code":"11.0",
    "gn:asciiname":"La Estaqueria",
    "gn:country_code":"MX",
    "gn:dem":2159,
    "gn:feature_class":"P",
    "gn:feature_code":"PPL",
    "gn:name":"La Estaquer\u00eda",
    "gn:population":0,
    "gn:timezone":"America/Mexico_City",
    "iso:country":"MX",
    "name:spa_x_preferred":[
        "La Estaquer\u00eda"
    ],
    "wof:name":"La Estaqueria",
    "wof:placetype":"locality"
},
  "geometry": {"coordinates":[-100.49772,20.29117],"type":"Point"}
}