{
  "type": "Feature",
  "properties": {
    "gn:admin1_code":"6.0",
    "gn:admin2_code":"2.0",
    "gn:asciiname":"La Compuerta",
    "gn:country_code":"MX",
    "gn:dem":976,
    "gn:feature_class":"P",
    "gn:feature_code":"PPL",
    "gn:name":"La Compuerta",
    "gn:population":0,
    "gn:timezone":"America/Chihuahua",
    "iso:country":"MX",
    "name:spa_x_preferred":[
        "La Compuerta"
    ],
    "name:und_x_variant":[
        "Compuerta"
    ],
    "wof:name":"La Compuerta",
    "wof:placetype":"locality"
},
  "geometry": {"coordinates":[-105.12291,29.0887],"type":"Point"}
}