{
  "type": "Feature",
  "properties": {
    "gn:admin1_code":"20",
    "gn:admin2_code":"114.0",
    "gn:asciiname":"San Jeronimo Zoochina",
    "gn:country_code":"MX",
    "gn:dem":1714,
    "gn:feature_class":"P",
    "gn:feature_code":"PPL",
    "gn:name":"San Jer\u00f3nimo Zoochina",
    "gn:population":105,
    "gn:timezone":"America/Mexico_City",
    "iso:country":"MX",
    "name:und_x_variant":[
        "San Jer\u00f3nimo Zoochina"
    ],
    "wof:name":"San Jeronimo Zoochina",
    "wof:placetype":"locality",
    "wof:population":105
},
  "geometry": {"coordinates":[-96.2475,17.22667],"type":"Point"}
}