{
  "type": "Feature",
  "properties": {
    "gn:admin1_code":"6",
    "gn:admin2_code":"12.0",
    "gn:asciiname":"Riqueachi",
    "gn:country_code":"MX",
    "gn:dem":2009,
    "gn:feature_class":"P",
    "gn:feature_code":"PPL",
    "gn:name":"Riqueachi",
    "gn:population":8,
    "gn:timezone":"America/Chihuahua",
    "iso:country":"MX",
    "wof:name":"Riqueachi",
    "wof:placetype":"locality",
    "wof:population":8
},
  "geometry": {"coordinates":[-107.24437,27.612],"type":"Point"}
}