{
  "type": "Feature",
  "properties": {
    "gn:admin1_code":"30.0",
    "gn:admin2_code":"123.0",
    "gn:asciiname":"Tanchicuin Boca del Estero",
    "gn:country_code":"MX",
    "gn:dem":13,
    "gn:feature_class":"P",
    "gn:feature_code":"PPL",
    "gn:name":"Tanchicu\u00edn Boca del Estero",
    "gn:population":200,
    "gn:timezone":"America/Mexico_City",
    "iso:country":"MX",
    "name:spa_x_preferred":[
        "Tanchicu\u00edn Boca del Estero"
    ],
    "wof:name":"Tanchicuin Boca del Estero",
    "wof:placetype":"locality",
    "wof:population":200
},
  "geometry": {"coordinates":[-98.25111,22.07056],"type":"Point"}
}