{
  "type": "Feature",
  "properties": {
    "gn:admin1_code":"26",
    "gn:admin2_code":"25.0",
    "gn:asciiname":"Lourdes",
    "gn:country_code":"MX",
    "gn:dem":34,
    "gn:feature_class":"P",
    "gn:feature_code":"PPL",
    "gn:name":"Lourdes",
    "gn:population":0,
    "gn:timezone":"America/Hermosillo",
    "iso:country":"MX",
    "name:spa_x_preferred":[
        "Lourdes"
    ],
    "name:spa_x_variant":[
        "San Enrique"
    ],
    "wof:name":"Lourdes",
    "wof:placetype":"locality"
},
  "geometry": {"coordinates":[-110.62939,28.01508],"type":"Point"}
}