{
  "type": "Feature",
  "properties": {
    "gn:admin1_code":"6",
    "gn:admin2_code":"25.0",
    "gn:asciiname":"La Soledad",
    "gn:country_code":"MX",
    "gn:dem":2217,
    "gn:feature_class":"P",
    "gn:feature_code":"PPL",
    "gn:name":"La Soledad",
    "gn:population":0,
    "gn:timezone":"America/Chihuahua",
    "iso:country":"MX",
    "name:spa_x_preferred":[
        "La Soledad"
    ],
    "wof:name":"La Soledad",
    "wof:placetype":"locality"
},
  "geometry": {"coordinates":[-107.65825,29.39284],"type":"Point"}
}