{
  "type": "Feature",
  "properties": {
    "gn:admin1_code":"6",
    "gn:admin2_code":"30.0",
    "gn:asciiname":"El Mochomo",
    "gn:country_code":"MX",
    "gn:dem":721,
    "gn:feature_class":"P",
    "gn:feature_code":"PPL",
    "gn:name":"El Mochomo",
    "gn:population":0,
    "gn:timezone":"America/Chihuahua",
    "iso:country":"MX",
    "name:spa_x_preferred":[
        "El Mochomo"
    ],
    "wof:name":"El Mochomo",
    "wof:placetype":"locality"
},
  "geometry": {"coordinates":[-108.26494,27.45894],"type":"Point"}
}