{
  "type": "Feature",
  "properties": {
    "gn:admin1_code":"32",
    "gn:admin2_code":"17.0",
    "gn:asciiname":"La Alcaparra",
    "gn:country_code":"MX",
    "gn:dem":2137,
    "gn:feature_class":"P",
    "gn:feature_code":"PPL",
    "gn:name":"La Alcaparra",
    "gn:population":5,
    "gn:timezone":"America/Mexico_City",
    "iso:country":"MX",
    "wof:name":"La Alcaparra",
    "wof:placetype":"locality",
    "wof:population":5
},
  "geometry": {"coordinates":[-102.42306000000001,22.81444],"type":"Point"}
}