{
  "type": "Feature",
  "properties": {
    "gn:admin1_code":"16",
    "gn:admin2_code":"52",
    "gn:asciiname":"Colonia los Puentes Cuates (El Sembrador)",
    "gn:country_code":"MX",
    "gn:dem":16,
    "gn:feature_class":"P",
    "gn:feature_code":"PPL",
    "gn:name":"Colonia los Puentes Cuates (El Sembrador)",
    "gn:population":11,
    "gn:timezone":"America/Mexico_City",
    "iso:country":"MX",
    "wof:name":"Colonia los Puentes Cuates (El Sembrador)",
    "wof:placetype":"locality",
    "wof:population":11
},
  "geometry": {"coordinates":[-102.19889000000001,17.97694],"type":"Point"}
}