{
  "type": "Feature",
  "properties": {
    "gn:admin1_code":"19",
    "gn:admin2_code":"3.0",
    "gn:asciiname":"Paso la Cuna",
    "gn:country_code":"MX",
    "gn:dem":105,
    "gn:feature_class":"P",
    "gn:feature_code":"PPL",
    "gn:name":"Paso la Cuna",
    "gn:population":6,
    "gn:timezone":"America/Monterrey",
    "iso:country":"MX",
    "wof:name":"Paso la Cuna",
    "wof:placetype":"locality",
    "wof:population":6
},
  "geometry": {"coordinates":[-99.20169,26.12201],"type":"Point"}
}