{
  "type": "Feature",
  "properties": {
    "gn:admin1_code":"21",
    "gn:admin2_code":"39.0",
    "gn:asciiname":"Texocotitan",
    "gn:country_code":"MX",
    "gn:dem":1773,
    "gn:feature_class":"P",
    "gn:feature_code":"PPL",
    "gn:name":"Texocotit\u00e1n",
    "gn:population":111,
    "gn:timezone":"America/Mexico_City",
    "iso:country":"MX",
    "name:und_x_variant":[
        "Texocotit\u00e1n"
    ],
    "wof:name":"Texocotitan",
    "wof:placetype":"locality",
    "wof:population":111
},
  "geometry": {"coordinates":[-97.78274999999999,19.91137],"type":"Point"}
}