{
  "type": "Feature",
  "properties": {
    "gn:admin1_code":"14",
    "gn:admin2_code":"115.0",
    "gn:asciiname":"La Palma del Tule",
    "gn:country_code":"MX",
    "gn:dem":1487,
    "gn:feature_class":"P",
    "gn:feature_code":"PPL",
    "gn:name":"La Palma del Tule",
    "gn:population":0,
    "gn:timezone":"America/Mexico_City",
    "iso:country":"MX",
    "name:spa_x_preferred":[
        "La Palma del Tule"
    ],
    "wof:name":"La Palma del Tule",
    "wof:placetype":"locality"
},
  "geometry": {"coordinates":[-103.80712,21.97096],"type":"Point"}
}