{
  "type": "Feature",
  "properties": {
    "gn:admin1_code":"12.0",
    "gn:asciiname":"Llano Grande",
    "gn:country_code":"MX",
    "gn:dem":773,
    "gn:feature_class":"P",
    "gn:feature_code":"PPL",
    "gn:name":"Llano Grande",
    "gn:population":0,
    "gn:timezone":"America/Mexico_City",
    "iso:country":"MX",
    "name:ceb_x_preferred":[
        "Llano Grande"
    ],
    "name:deu_x_preferred":[
        "Llano Grande"
    ],
    "name:fra_x_preferred":[
        "Llano Grande"
    ],
    "name:ita_x_preferred":[
        "Llano Grande"
    ],
    "name:spa_x_preferred":[
        "Llano Grande"
    ],
    "name:swe_x_preferred":[
        "Llano Grande"
    ],
    "wof:name":"Llano Grande",
    "wof:placetype":"locality"
},
  "geometry": {"coordinates":[-99.77479,17.41655],"type":"Point"}
}