{
  "type": "Feature",
  "properties": {
    "gn:admin1_code":"17.0",
    "gn:asciiname":"Campamento Kilometro Cuarenta y Ocho",
    "gn:country_code":"MX",
    "gn:dem":2671,
    "gn:feature_class":"P",
    "gn:feature_code":"PPL",
    "gn:name":"Campamento Kil\u00f3metro Cuarenta y Ocho",
    "gn:population":0,
    "gn:timezone":"America/Mexico_City",
    "iso:country":"MX",
    "name:spa_x_preferred":[
        "Campamento Kil\u00f3metro Cuarenta y Ocho"
    ],
    "wof:name":"Campamento Kilometro Cuarenta y Ocho",
    "wof:placetype":"locality"
},
  "geometry": {"coordinates":[-99.57032,19.45501],"type":"Point"}
}