{
  "type": "Feature",
  "properties": {
    "iso:country":"MX",
    "name:spa_x_preferred":[
        "Res Valle Real"
    ],
    "qs:gn_local":0,
    "qs:local_max":22,
    "qs:local_sum":22,
    "qs:localhoods":1,
    "qs:name":"Res Valle Real",
    "qs:name_adm0":"M\u00e9xico",
    "qs:name_adm1":"Queretaro de Arteaga",
    "qs:name_adm2":"Corregidora",
    "qs:name_local":"Venceremos",
    "qs:photo_max":10,
    "qs:photo_sum":22,
    "qs:placetype":"Suburb",
    "qs:quad_count":3,
    "qs:woe_adm0":23424900,
    "qs:woe_adm1":2346285,
    "qs:woe_adm2":12601448,
    "qs:woe_lau":0,
    "qs:woe_local":55888078,
    "qs:woe_ver":"7.10.0",
    "wof:lang":[
        "spa"
    ],
    "wof:name":"Res Valle Real",
    "wof:placetype":"neighbourhood"
},
  "geometry": {"coordinates":[-100.400059,20.549574],"type":"Point"}
}