{
  "type": "Feature",
  "properties": {
    "gn:admin1_code":"20",
    "gn:admin2_code":"339",
    "gn:asciiname":"Guadalupe Tiza",
    "gn:country_code":"MX",
    "gn:dem":2172,
    "gn:feature_class":"P",
    "gn:feature_code":"PPL",
    "gn:name":"Guadalupe Tiz\u00e1",
    "gn:population":51,
    "gn:timezone":"America/Mexico_City",
    "iso:country":"MX",
    "name:und_x_variant":[
        "Guadalupe Tiz\u00e1"
    ],
    "wof:name":"Guadalupe Tiza",
    "wof:placetype":"locality",
    "wof:population":51
},
  "geometry": {"coordinates":[-97.5175,17.50861],"type":"Point"}
}