{
  "type": "Feature",
  "properties": {
    "gn:admin1_code":"18",
    "gn:admin2_code":"9",
    "gn:asciiname":"El Tenamaiste",
    "gn:country_code":"MX",
    "gn:dem":1152,
    "gn:feature_class":"P",
    "gn:feature_code":"PPL",
    "gn:name":"El Tenamaiste",
    "gn:population":19,
    "gn:timezone":"America/Mazatlan",
    "iso:country":"MX",
    "wof:name":"El Tenamaiste",
    "wof:placetype":"locality",
    "wof:population":19
},
  "geometry": {"coordinates":[-104.83638999999999,22.23444],"type":"Point"}
}