{
  "type": "Feature",
  "properties": {
    "gn:admin1_code":"29",
    "gn:admin2_code":"25.0",
    "gn:asciiname":"Xahuen Vargas",
    "gn:country_code":"MX",
    "gn:dem":2430,
    "gn:feature_class":"P",
    "gn:feature_code":"PPL",
    "gn:name":"Xahu\u00e9n Vargas",
    "gn:population":113,
    "gn:timezone":"America/Mexico_City",
    "iso:country":"MX",
    "name:und_x_variant":[
        "Xahu\u00e9n Vargas"
    ],
    "wof:name":"Xahuen Vargas",
    "wof:placetype":"locality",
    "wof:population":113
},
  "geometry": {"coordinates":[-98.1375,19.13917],"type":"Point"}
}