{
  "type": "Feature",
  "properties": {
    "gn:admin1_code":"26",
    "gn:admin2_code":"17",
    "gn:asciiname":"Los Franciscos",
    "gn:country_code":"MX",
    "gn:dem":175,
    "gn:feature_class":"P",
    "gn:feature_code":"PPL",
    "gn:name":"Los Franciscos",
    "gn:population":22,
    "gn:timezone":"America/Hermosillo",
    "iso:country":"MX",
    "wof:name":"Los Franciscos",
    "wof:placetype":"locality",
    "wof:population":22
},
  "geometry": {"coordinates":[-112.45611,30.72639],"type":"Point"}
}