{
  "type": "Feature",
  "properties": {
    "gn:admin1_code":"14.0",
    "gn:admin2_code":"58.0",
    "gn:asciiname":"Cerro Grande",
    "gn:country_code":"MX",
    "gn:dem":1865,
    "gn:feature_class":"P",
    "gn:feature_code":"PPL",
    "gn:name":"Cerro Grande",
    "gn:population":0,
    "gn:timezone":"America/Mexico_City",
    "iso:country":"MX",
    "name:ara_x_preferred":[
        "\u0633\u064a\u0631\u0648 \u063a\u0631\u0627\u0646\u062f\u064a"
    ],
    "name:ben_x_preferred":[
        "\u09b8\u09c7\u09b0\u09b0\u09cb \u0997\u09cd\u09b0\u09cd\u09af\u09be\u09a8\u09cd\u09a1\u09c7"
    ],
    "name:ceb_x_preferred":[
        "Cerro Grande"
    ],
    "name:deu_x_preferred":[
        "Cerro Grande"
    ],
    "name:ell_x_preferred":[
        "\u03a3\u03ad\u03c1\u03c1\u03bf \u0393\u03ba\u03c1\u03ac\u03bd\u03c4\u03b5"
    ],
    "name:fas_x_preferred":[
        "\u0633\u0631\u0648 \u06af\u0631\u0646\u062f"
    ],
    "name:fra_x_preferred":[
        "Cerro Grande"
    ],
    "name:heb_x_preferred":[
        "\u05d4\u05e8 \u05d2\u05e8\u05e0\u05d3\u05d4"
    ],
    "name:hin_x_preferred":[
        "\u0938\u0947\u0930\u094b \u0917\u094d\u0930\u0948\u0902\u0921"
    ],
    "name:hun_x_preferred":[
        "Cerro Grande"
    ],
    "name:ind_x_preferred":[
        "Cerro Grande"
    ],
    "name:ita_x_preferred":[
        "Cerro Grande"
    ],
    "name:jpn_x_preferred":[
        "\u30bb\u30ed\u30fb\u30b0\u30e9\u30f3\u30c7\u5c71"
    ],
    "name:kor_x_preferred":[
        "\uc138\ub85c \uadf8\ub780\ub370"
    ],
    "name:nld_x_preferred":[
        "Cerro Grande"
    ],
    "name:pol_x_preferred":[
        "Cerro Grande"
    ],
    "name:por_x_preferred":[
        "Cerro Grande"
    ],
    "name:rus_x_preferred":[
        "\u0421\u0435\u0440\u0440\u0443-\u0413\u0440\u0430\u043d\u0434\u0438"
    ],
    "name:spa_x_preferred":[
        "Cerro Grande"
    ],
    "name:swe_x_preferred":[
        "Cerro Grande"
    ],
    "name:tur_x_preferred":[
        "Cerro Grande"
    ],
    "name:ukr_x_preferred":[
        "\u0421\u0435\u0440\u0440\u043e-\u0413\u0440\u0430\u043d\u0434\u0435"
    ],
    "name:urd_x_preferred":[
        "\u06a9\u06cc\u0631\u0648 \u06af\u0631\u0627\u0646\u0688\u06d2"
    ],
    "name:vie_x_preferred":[
        "N\u00fai Grande"
    ],
    "name:zho_cn_x_preferred":[
        "\u683c\u5170\u5fb7\u5c71"
    ],
    "name:zho_tw_x_preferred":[
        "\u683c\u862d\u5fb7\u5c71"
    ],
    "wof:name":"Cerro Grande",
    "wof:placetype":"locality"
},
  "geometry": {"coordinates":[-104.65299,20.54233],"type":"Point"}
}