{
  "type": "Feature",
  "properties": {
    "gn:admin1_code":"14.0",
    "gn:admin2_code":"43.0",
    "gn:asciiname":"Dominguez",
    "gn:country_code":"MX",
    "gn:dem":40,
    "gn:feature_class":"P",
    "gn:feature_code":"PPL",
    "gn:name":"Dom\u00ednguez",
    "gn:population":0,
    "gn:timezone":"America/Mexico_City",
    "iso:country":"MX",
    "wof:name":"Dominguez",
    "wof:placetype":"locality"
},
  "geometry": {"coordinates":[-104.95,19.38333],"type":"Point"}
}