{
  "type": "Feature",
  "properties": {
    "gn:admin1_code":"12.0",
    "gn:admin2_code":"11.0",
    "gn:asciiname":"La Remonta Grande",
    "gn:country_code":"MX",
    "gn:dem":531,
    "gn:feature_class":"P",
    "gn:feature_code":"PPL",
    "gn:name":"La Remonta Grande",
    "gn:population":0,
    "gn:timezone":"America/Mexico_City",
    "iso:country":"MX",
    "name:spa_x_preferred":[
        "La Remonta Grande"
    ],
    "wof:name":"La Remonta Grande",
    "wof:placetype":"locality"
},
  "geometry": {"coordinates":[-100.2191,17.24449],"type":"Point"}
}