{
  "type": "Feature",
  "properties": {
    "gn:admin1_code":"14.0",
    "gn:admin2_code":"85.0",
    "gn:asciiname":"El Cirimo",
    "gn:country_code":"MX",
    "gn:dem":1581,
    "gn:feature_class":"P",
    "gn:feature_code":"PPL",
    "gn:name":"El Cirimo",
    "gn:population":0,
    "gn:timezone":"America/Mexico_City",
    "iso:country":"MX",
    "name:spa_x_preferred":[
        "El Cirimo"
    ],
    "wof:name":"El Cirimo",
    "wof:placetype":"locality"
},
  "geometry": {"coordinates":[-103.13118,19.54017],"type":"Point"}
}