{
  "type": "Feature",
  "properties": {
    "gn:admin1_code":"4",
    "gn:admin2_code":"9.0",
    "gn:asciiname":"Kilometro Setenta y Cuatro",
    "gn:country_code":"MX",
    "gn:dem":65,
    "gn:feature_class":"P",
    "gn:feature_code":"PPL",
    "gn:name":"Kil\u00f3metro Setenta y Cuatro",
    "gn:population":0,
    "gn:timezone":"America/Merida",
    "iso:country":"MX",
    "name:spa_x_preferred":[
        "Kil\u00f3metro Sesenta y Cuatro"
    ],
    "name:und_x_variant":[
        "Kil\u00f3metro Setenta y Cuatro"
    ],
    "wof:name":"Kilometro Setenta y Cuatro",
    "wof:placetype":"locality"
},
  "geometry": {"coordinates":[-90.75574,18.70258],"type":"Point"}
}