{
  "type": "Feature",
  "properties": {
    "gn:admin1_code":"30.0",
    "gn:admin2_code":"63.0",
    "gn:asciiname":"Queseria",
    "gn:country_code":"MX",
    "gn:dem":69,
    "gn:feature_class":"P",
    "gn:feature_code":"PPL",
    "gn:name":"Queser\u00eda",
    "gn:population":0,
    "gn:timezone":"America/Mexico_City",
    "iso:country":"MX",
    "name:spa_x_preferred":[
        "Queser\u00eda"
    ],
    "wof:name":"Queseria",
    "wof:placetype":"locality"
},
  "geometry": {"coordinates":[-97.99421,21.50223],"type":"Point"}
}