{
  "type": "Feature",
  "properties": {
    "gn:admin1_code":"11",
    "gn:admin2_code":"43.0",
    "gn:asciiname":"Salitrera",
    "gn:country_code":"MX",
    "gn:dem":1693,
    "gn:feature_class":"P",
    "gn:feature_code":"PPL",
    "gn:name":"Salitrera",
    "gn:population":180,
    "gn:timezone":"America/Mexico_City",
    "iso:country":"MX",
    "wof:name":"Salitrera",
    "wof:placetype":"locality",
    "wof:population":180
},
  "geometry": {"coordinates":[-100.14082999999999,21.18444],"type":"Point"}
}