{
  "type": "Feature",
  "properties": {
    "gn:admin1_code":"5.0",
    "gn:admin2_code":"65.0",
    "gn:asciiname":"Tucuman",
    "gn:country_code":"MX",
    "gn:dem":22,
    "gn:feature_class":"P",
    "gn:feature_code":"PPL",
    "gn:name":"Tucum\u00e1n",
    "gn:population":0,
    "gn:timezone":"America/Mexico_City",
    "iso:country":"MX",
    "name:spa_x_preferred":[
        "Tucum\u00e1n"
    ],
    "wof:name":"Tucuman",
    "wof:placetype":"locality"
},
  "geometry": {"coordinates":[-91.94092999999999,17.70332999999999],"type":"Point"}
}