{
  "type": "Feature",
  "properties": {
    "gn:admin1_code":"30",
    "gn:admin2_code":"108.0",
    "gn:asciiname":"El Progreso",
    "gn:country_code":"MX",
    "gn:dem":51,
    "gn:feature_class":"P",
    "gn:feature_code":"PPL",
    "gn:name":"El Progreso",
    "gn:population":0,
    "gn:timezone":"America/Mexico_City",
    "iso:country":"MX",
    "name:spa_x_preferred":[
        "El Progreso"
    ],
    "wof:name":"El Progreso",
    "wof:placetype":"locality"
},
  "geometry": {"coordinates":[-94.47360999999999,17.84877000000001],"type":"Point"}
}