{
  "type": "Feature",
  "properties": {
    "gn:admin1_code":"6",
    "gn:admin2_code":"27",
    "gn:asciiname":"Zapareachi [Aserradero]",
    "gn:country_code":"MX",
    "gn:dem":2338,
    "gn:feature_class":"P",
    "gn:feature_code":"PPL",
    "gn:name":"Zapareachi [Aserradero]",
    "gn:population":22,
    "gn:timezone":"America/Chihuahua",
    "iso:country":"MX",
    "wof:name":"Zapareachi [Aserradero]",
    "wof:placetype":"locality",
    "wof:population":22
},
  "geometry": {"coordinates":[-106.97516,26.77994],"type":"Point"}
}