{
  "type": "Feature",
  "properties": {
    "gn:admin1_code":"13",
    "gn:admin2_code":"22.0",
    "gn:asciiname":"Escobillas",
    "gn:country_code":"MX",
    "gn:dem":2637,
    "gn:feature_class":"P",
    "gn:feature_code":"PPL",
    "gn:name":"Escobillas",
    "gn:population":208,
    "gn:timezone":"America/Mexico_City",
    "iso:country":"MX",
    "name:spa_x_preferred":[
        "Escobillas"
    ],
    "wof:name":"Escobillas",
    "wof:placetype":"locality",
    "wof:population":208
},
  "geometry": {"coordinates":[-98.60231,20.00167],"type":"Point"}
}