{
  "type": "Feature",
  "properties": {
    "gn:admin1_code":"14.0",
    "gn:admin2_code":"36.0",
    "gn:asciiname":"La Embocada",
    "gn:country_code":"MX",
    "gn:dem":1690,
    "gn:feature_class":"P",
    "gn:feature_code":"PPL",
    "gn:name":"La Embocada",
    "gn:population":0,
    "gn:timezone":"America/Mexico_City",
    "iso:country":"MX",
    "name:und_x_variant":[
        "El Amparo",
        "La Embocada"
    ],
    "wof:name":"La Embocada",
    "wof:placetype":"locality"
},
  "geometry": {"coordinates":[-104.09369,20.70381],"type":"Point"}
}