{
  "type": "Feature",
  "properties": {
    "gn:admin1_code":"12",
    "gn:admin2_code":"21.0",
    "gn:asciiname":"Las Compuertas",
    "gn:country_code":"MX",
    "gn:dem":900,
    "gn:feature_class":"P",
    "gn:feature_code":"PPL",
    "gn:name":"Las Compuertas",
    "gn:population":0,
    "gn:timezone":"America/Mexico_City",
    "iso:country":"MX",
    "name:spa_x_preferred":[
        "Las Compuertas"
    ],
    "wof:name":"Las Compuertas",
    "wof:placetype":"locality"
},
  "geometry": {"coordinates":[-100.00839999999999,17.19559],"type":"Point"}
}