{
  "type": "Feature",
  "properties": {
    "gn:admin1_code":"26",
    "gn:admin2_code":"66.0",
    "gn:asciiname":"El Ranchito",
    "gn:country_code":"MX",
    "gn:dem":403,
    "gn:feature_class":"P",
    "gn:feature_code":"PPL",
    "gn:name":"El Ranchito",
    "gn:population":0,
    "gn:timezone":"America/Hermosillo",
    "iso:country":"MX",
    "name:spa_x_preferred":[
        "El Ranchito"
    ],
    "wof:name":"El Ranchito",
    "wof:placetype":"locality"
},
  "geometry": {"coordinates":[-110.38849999999999,29.39056],"type":"Point"}
}