{
  "type": "Feature",
  "properties": {
    "gn:admin1_code":"14",
    "gn:admin2_code":"120.0",
    "gn:asciiname":"Los Arcos",
    "gn:country_code":"MX",
    "gn:dem":1459,
    "gn:feature_class":"P",
    "gn:feature_code":"PPL",
    "gn:name":"Los Arcos",
    "gn:population":6,
    "gn:timezone":"America/Mexico_City",
    "iso:country":"MX",
    "name:arg_x_preferred":[
        "Los Arcos"
    ],
    "name:ast_x_preferred":[
        "Los Arcos"
    ],
    "name:bre_x_preferred":[
        "Urantzia"
    ],
    "name:cat_x_preferred":[
        "Los Arcos"
    ],
    "name:ceb_x_preferred":[
        "Los Arcos"
    ],
    "name:deu_x_preferred":[
        "Los Arcos"
    ],
    "name:eus_x_preferred":[
        "Los Arcos"
    ],
    "name:fra_x_preferred":[
        "Los Arcos"
    ],
    "name:glg_x_preferred":[
        "Los Arcos"
    ],
    "name:hun_x_preferred":[
        "Los Arcos"
    ],
    "name:ita_x_preferred":[
        "Los Arcos"
    ],
    "name:lat_x_preferred":[
        "Arcus"
    ],
    "name:msa_x_preferred":[
        "Los Arcos"
    ],
    "name:nld_x_preferred":[
        "Los Arcos"
    ],
    "name:oci_x_preferred":[
        "Los Arcos"
    ],
    "name:pol_x_preferred":[
        "Los Arcos"
    ],
    "name:por_x_preferred":[
        "Los Arcos"
    ],
    "name:rus_x_preferred":[
        "\u041b\u043e\u0441-\u0410\u0440\u043a\u043e\u0441"
    ],
    "name:sco_x_preferred":[
        "Los Arcos"
    ],
    "name:spa_x_preferred":[
        "Los Arcos"
    ],
    "name:ukr_x_preferred":[
        "\u041b\u043e\u0441-\u0410\u0440\u043a\u043e\u0441"
    ],
    "name:uzb_x_preferred":[
        "Los Arcos"
    ],
    "name:vie_x_preferred":[
        "Los Arcos"
    ],
    "name:war_x_preferred":[
        "Los Arcos"
    ],
    "name:zho_x_preferred":[
        "\u6d1b\u8428\u5c14\u79d1\u65af"
    ],
    "wof:name":"Los Arcos",
    "wof:placetype":"locality",
    "wof:population":6
},
  "geometry": {"coordinates":[-103.63478000000001,20.71695],"type":"Point"}
}