{
  "type": "Feature",
  "properties": {
    "gn:admin1_code":"14",
    "gn:admin2_code":"120.0",
    "gn:asciiname":"Los Arcos",
    "gn:country_code":"MX",
    "gn:dem":1459,
    "gn:feature_class":"P",
    "gn:feature_code":"PPL",
    "gn:name":"Los Arcos",
    "gn:population":6,
    "gn:timezone":"America/Mexico_City",
    "iso:country":"MX",
    "wof:name":"Los Arcos",
    "wof:placetype":"locality",
    "wof:population":6
},
  "geometry": {"coordinates":[-103.63478000000001,20.71695],"type":"Point"}
}