{
  "type": "Feature",
  "properties": {
    "gn:admin1_code":"6.0",
    "gn:admin2_code":"10.0",
    "gn:asciiname":"El Dame",
    "gn:country_code":"MX",
    "gn:dem":1452,
    "gn:feature_class":"P",
    "gn:feature_code":"PPL",
    "gn:name":"El Dame",
    "gn:population":6,
    "gn:timezone":"America/Chihuahua",
    "iso:country":"MX",
    "wof:name":"El Dame",
    "wof:placetype":"locality",
    "wof:population":6
},
  "geometry": {"coordinates":[-106.98248,29.94459],"type":"Point"}
}