{
  "type": "Feature",
  "properties": {
    "gn:admin1_code":"31",
    "gn:admin2_code":"50.0",
    "gn:asciiname":"Dxililchaltun",
    "gn:country_code":"MX",
    "gn:dem":8,
    "gn:feature_class":"P",
    "gn:feature_code":"PPL",
    "gn:name":"Dxililchalt\u00fan",
    "gn:population":0,
    "gn:timezone":"America/Merida",
    "iso:country":"MX",
    "wof:name":"Dxililchaltun",
    "wof:placetype":"locality"
},
  "geometry": {"coordinates":[-89.59999999999999,21.08333],"type":"Point"}
}