{
  "type": "Feature",
  "properties": {
    "gn:admin1_code":"21",
    "gn:admin2_code":"85",
    "gn:asciiname":"San Francisco",
    "gn:country_code":"MX",
    "gn:dem":1299,
    "gn:feature_class":"P",
    "gn:feature_code":"PPL",
    "gn:name":"San Francisco",
    "gn:population":27,
    "gn:timezone":"America/Mexico_City",
    "iso:country":"MX",
    "wof:name":"San Francisco",
    "wof:placetype":"locality",
    "wof:population":27
},
  "geometry": {"coordinates":[-98.51721000000001,18.4788],"type":"Point"}
}