{
  "type": "Feature",
  "properties": {
    "gn:admin1_code":"32.0",
    "gn:asciiname":"Charco Verde",
    "gn:country_code":"MX",
    "gn:dem":1930,
    "gn:feature_class":"P",
    "gn:feature_code":"PPL",
    "gn:name":"Charco Verde",
    "gn:population":0,
    "gn:timezone":"America/Mexico_City",
    "iso:country":"MX",
    "name:spa_x_preferred":[
        "Charco Verde"
    ],
    "wof:name":"Charco Verde",
    "wof:placetype":"locality"
},
  "geometry": {"coordinates":[-102.84689,21.50386],"type":"Point"}
}