{
  "type": "Feature",
  "properties": {
    "gn:admin1_code":"6",
    "gn:admin2_code":"35.0",
    "gn:asciiname":"Las Varas",
    "gn:cc2":"MX",
    "gn:country_code":"MX",
    "gn:dem":1410,
    "gn:feature_class":"P",
    "gn:feature_code":"PPL",
    "gn:name":"Las Varas",
    "gn:population":0,
    "gn:timezone":"America/Chihuahua",
    "iso:country":"MX",
    "name:ceb_x_preferred":[
        "Las Varas"
    ],
    "name:srp_x_preferred":[
        "\u041b\u0430\u0441 \u0412\u0430\u0440\u0430\u0441"
    ],
    "name:swe_x_preferred":[
        "Las Varas"
    ],
    "name:und_x_variant":[
        "Aguaje de las Varas",
        "Aguaje de las Vacas",
        "Las Varas"
    ],
    "wof:name":"Las Varas",
    "wof:placetype":"locality"
},
  "geometry": {"coordinates":[-108.63333,30.86667000000001],"type":"Point"}
}