{
  "type": "Feature",
  "properties": {
    "gn:admin1_code":"6",
    "gn:admin2_code":"31.0",
    "gn:asciiname":"San Pablo de la Sierra",
    "gn:country_code":"MX",
    "gn:dem":2311,
    "gn:feature_class":"P",
    "gn:feature_code":"PPL",
    "gn:name":"San Pablo de la Sierra",
    "gn:population":0,
    "gn:timezone":"America/Chihuahua",
    "iso:country":"MX",
    "name:und_x_variant":[
        "Cochinito",
        "San Pablo de la Sierra",
        "Cochinitos"
    ],
    "wof:name":"San Pablo de la Sierra",
    "wof:placetype":"locality"
},
  "geometry": {"coordinates":[-107.75,28.08333],"type":"Point"}
}