{
  "type": "Feature",
  "properties": {
    "gn:admin1_code":"14.0",
    "gn:admin2_code":"94.0",
    "gn:asciiname":"Montones",
    "gn:country_code":"MX",
    "gn:dem":1853,
    "gn:feature_class":"P",
    "gn:feature_code":"PPL",
    "gn:name":"Montones",
    "gn:population":0,
    "gn:timezone":"America/Mexico_City",
    "iso:country":"MX",
    "name:spa_x_preferred":[
        "Montones"
    ],
    "wof:name":"Montones",
    "wof:placetype":"locality"
},
  "geometry": {"coordinates":[-103.75163000000001,20.99218],"type":"Point"}
}