{
  "type": "Feature",
  "properties": {
    "gn:admin1_code":"24",
    "gn:admin2_code":"53.0",
    "gn:asciiname":"Tepetlaco",
    "gn:country_code":"MX",
    "gn:dem":83,
    "gn:feature_class":"P",
    "gn:feature_code":"PPL",
    "gn:name":"Tepetlaco",
    "gn:population":9,
    "gn:timezone":"America/Mexico_City",
    "iso:country":"MX",
    "wof:name":"Tepetlaco",
    "wof:placetype":"locality",
    "wof:population":9
},
  "geometry": {"coordinates":[-98.82944000000001,21.43639],"type":"Point"}
}