{
  "type": "Feature",
  "properties": {
    "gn:admin1_code":"14",
    "gn:admin2_code":"113.0",
    "gn:asciiname":"Salsipuedes",
    "gn:country_code":"MX",
    "gn:dem":1829,
    "gn:feature_class":"P",
    "gn:feature_code":"PPL",
    "gn:name":"Salsipuedes",
    "gn:population":0,
    "gn:timezone":"America/Mexico_City",
    "iso:country":"MX",
    "name:ceb_x_preferred":[
        "Salsipuedes"
    ],
    "name:spa_x_preferred":[
        "Salsipuedes"
    ],
    "name:swe_x_preferred":[
        "Salsipuedes"
    ],
    "name:und_x_variant":[
        "Salispuedos"
    ],
    "wof:name":"Salsipuedes",
    "wof:placetype":"locality"
},
  "geometry": {"coordinates":[-103.67661,19.74893],"type":"Point"}
}