{
  "type": "Feature",
  "properties": {
    "gn:admin1_code":"25.0",
    "gn:admin2_code":"16.0",
    "gn:asciiname":"Espadanal",
    "gn:country_code":"MX",
    "gn:dem":806,
    "gn:feature_class":"P",
    "gn:feature_code":"PPL",
    "gn:name":"Espada\u00f1al",
    "gn:population":0,
    "gn:timezone":"America/Mazatlan",
    "iso:country":"MX",
    "name:spa_x_preferred":[
        "Espada\u00f1al"
    ],
    "name:und_x_variant":[
        "Rancho Espado\u00f1al",
        "Espada\u00f1a"
    ],
    "wof:name":"Espadanal",
    "wof:placetype":"locality"
},
  "geometry": {"coordinates":[-106.14118000000001,24.2628],"type":"Point"}
}