{
  "type": "Feature",
  "properties": {
    "gn:admin1_code":"23",
    "gn:admin2_code":"4.0",
    "gn:asciiname":"Chary",
    "gn:country_code":"MX",
    "gn:dem":165,
    "gn:feature_class":"P",
    "gn:feature_code":"PPL",
    "gn:name":"Chary",
    "gn:population":0,
    "gn:timezone":"America/Cancun",
    "iso:country":"MX",
    "name:spa_x_preferred":[
        "Chary"
    ],
    "wof:name":"Chary",
    "wof:placetype":"locality"
},
  "geometry": {"coordinates":[-89.00221999999999,18.45795],"type":"Point"}
}