{
  "type": "Feature",
  "properties": {
    "gn:admin1_code":"25.0",
    "gn:admin2_code":"10.0",
    "gn:asciiname":"La Cabeza del Toro",
    "gn:country_code":"MX",
    "gn:dem":117,
    "gn:feature_class":"P",
    "gn:feature_code":"PPL",
    "gn:name":"La Cabeza del Toro",
    "gn:population":0,
    "gn:timezone":"America/Mazatlan",
    "iso:country":"MX",
    "name:spa_x_preferred":[
        "La Cabeza del Toro"
    ],
    "wof:name":"La Cabeza del Toro",
    "wof:placetype":"locality"
},
  "geometry": {"coordinates":[-108.7093,26.49121],"type":"Point"}
}