{
  "type": "Feature",
  "properties": {
    "gn:admin1_code":"14",
    "gn:admin2_code":"97.0",
    "gn:asciiname":"Santa Cruz de la Loma (Tepetates)",
    "gn:country_code":"MX",
    "gn:dem":1510,
    "gn:feature_class":"P",
    "gn:feature_code":"PPL",
    "gn:name":"Santa Cruz de la Loma (Tepetates)",
    "gn:population":1290,
    "gn:timezone":"America/Mexico_City",
    "iso:country":"MX",
    "wof:name":"Santa Cruz de la Loma (Tepetates)",
    "wof:placetype":"locality",
    "wof:population":1290
},
  "geometry": {"coordinates":[-103.54971999999999,20.48806],"type":"Point"}
}