{
  "type": "Feature",
  "properties": {
    "gn:admin1_code":"3",
    "gn:admin2_code":"1.0",
    "gn:asciiname":"Mezquitito",
    "gn:country_code":"MX",
    "gn:dem":394,
    "gn:feature_class":"P",
    "gn:feature_code":"PPL",
    "gn:name":"Mezquitito",
    "gn:population":0,
    "gn:timezone":"America/Mazatlan",
    "iso:country":"MX",
    "wof:name":"Mezquitito",
    "wof:placetype":"locality"
},
  "geometry": {"coordinates":[-111.74506,26.24488],"type":"Point"}
}