{
  "type": "Feature",
  "properties": {
    "gn:admin1_code":"11.0",
    "gn:admin2_code":"27.0",
    "gn:asciiname":"Los Lobos",
    "gn:country_code":"MX",
    "gn:dem":1725,
    "gn:feature_class":"P",
    "gn:feature_code":"PPL",
    "gn:name":"Los Lobos",
    "gn:population":0,
    "gn:timezone":"America/Mexico_City",
    "iso:country":"MX",
    "name:spa_x_preferred":[
        "Los Lobos"
    ],
    "name:spa_x_variant":[
        "Rancho los Lobos"
    ],
    "wof:name":"Los Lobos",
    "wof:placetype":"locality"
},
  "geometry": {"coordinates":[-101.20003,20.47392],"type":"Point"}
}