{
  "type": "Feature",
  "properties": {
    "gn:admin1_code":"15",
    "gn:admin2_code":"117",
    "gn:asciiname":"Cruz Blanca",
    "gn:country_code":"MX",
    "gn:dem":2260,
    "gn:feature_class":"P",
    "gn:feature_code":"PPL",
    "gn:name":"Cruz Blanca",
    "gn:population":25,
    "gn:timezone":"America/Mexico_City",
    "iso:country":"MX",
    "wof:name":"Cruz Blanca",
    "wof:placetype":"locality",
    "wof:population":25
},
  "geometry": {"coordinates":[-99.80365,18.64435],"type":"Point"}
}