{
  "type": "Feature",
  "properties": {
    "gn:admin1_code":"26.0",
    "gn:admin2_code":"42.0",
    "gn:asciiname":"Bacabachi",
    "gn:country_code":"MX",
    "gn:dem":56,
    "gn:feature_class":"P",
    "gn:feature_code":"PPL",
    "gn:name":"Bacabachi",
    "gn:population":0,
    "gn:timezone":"America/Hermosillo",
    "iso:country":"MX",
    "name:und_x_variant":[
        "Bacavachi",
        "Bacab\u00e1che",
        "Bacabachi"
    ],
    "wof:name":"Bacabachi",
    "wof:placetype":"locality"
},
  "geometry": {"coordinates":[-109.39319999999999,26.89471],"type":"Point"}
}