{
  "type": "Feature",
  "properties": {
    "gn:admin1_code":"32",
    "gn:admin2_code":"39.0",
    "gn:asciiname":"Residencia",
    "gn:country_code":"MX",
    "gn:dem":1924,
    "gn:feature_class":"P",
    "gn:feature_code":"PPL",
    "gn:name":"Residencia",
    "gn:population":0,
    "gn:timezone":"America/Mexico_City",
    "iso:country":"MX",
    "name:spa_x_preferred":[
        "Residencia"
    ],
    "wof:name":"Residencia",
    "wof:placetype":"locality"
},
  "geometry": {"coordinates":[-103.09426999999999,23.69285],"type":"Point"}
}