{
  "type": "Feature",
  "properties": {
    "gn:admin1_code":"28",
    "gn:admin2_code":"32",
    "gn:asciiname":"Lagunitas Uno",
    "gn:country_code":"MX",
    "gn:dem":81,
    "gn:feature_class":"P",
    "gn:feature_code":"PPL",
    "gn:name":"Lagunitas Uno",
    "gn:population":12,
    "gn:timezone":"America/Matamoros",
    "iso:country":"MX",
    "wof:name":"Lagunitas Uno",
    "wof:placetype":"locality",
    "wof:population":12
},
  "geometry": {"coordinates":[-98.57389000000001,25.96139],"type":"Point"}
}