{
  "type": "Feature",
  "properties": {
    "gn:admin1_code":"23",
    "gn:admin2_code":"4.0",
    "gn:asciiname":"El Zaspa",
    "gn:country_code":"MX",
    "gn:dem":8,
    "gn:feature_class":"P",
    "gn:feature_code":"PPL",
    "gn:name":"El Zaspa",
    "gn:population":7,
    "gn:timezone":"America/Cancun",
    "iso:country":"MX",
    "wof:name":"El Zaspa",
    "wof:placetype":"locality",
    "wof:population":7
},
  "geometry": {"coordinates":[-88.04858,18.97646],"type":"Point"}
}