{
  "type": "Feature",
  "properties": {
    "gn:admin1_code":"16.0",
    "gn:admin2_code":"79.0",
    "gn:asciiname":"El Romero",
    "gn:country_code":"MX",
    "gn:dem":1731,
    "gn:feature_class":"P",
    "gn:feature_code":"PPL",
    "gn:name":"El Romero",
    "gn:population":0,
    "gn:timezone":"America/Mexico_City",
    "iso:country":"MX",
    "name:spa_x_preferred":[
        "El Romero"
    ],
    "wof:name":"El Romero",
    "wof:placetype":"locality"
},
  "geometry": {"coordinates":[-101.7612,19.30492000000001],"type":"Point"}
}