{
  "type": "Feature",
  "properties": {
    "gn:admin1_code":"14",
    "gn:admin2_code":"18",
    "gn:asciiname":"El Seminario",
    "gn:country_code":"MX",
    "gn:dem":1537,
    "gn:feature_class":"P",
    "gn:feature_code":"PPL",
    "gn:name":"El Seminario",
    "gn:population":48,
    "gn:timezone":"America/Mexico_City",
    "iso:country":"MX",
    "wof:name":"El Seminario",
    "wof:placetype":"locality",
    "wof:population":48
},
  "geometry": {"coordinates":[-102.56194000000001,20.30444],"type":"Point"}
}