{
  "type": "Feature",
  "properties": {
    "gn:admin1_code":"19.0",
    "gn:admin2_code":"51.0",
    "gn:asciiname":"Majada",
    "gn:country_code":"MX",
    "gn:dem":464,
    "gn:feature_class":"P",
    "gn:feature_code":"PPL",
    "gn:name":"Majada",
    "gn:population":0,
    "gn:timezone":"America/Monterrey",
    "iso:country":"MX",
    "name:spa_x_preferred":[
        "Majada"
    ],
    "wof:name":"Majada",
    "wof:placetype":"locality"
},
  "geometry": {"coordinates":[-100.30632,26.44857],"type":"Point"}
}