{
  "type": "Feature",
  "properties": {
    "gn:admin1_code":"26",
    "gn:admin2_code":"42.0",
    "gn:asciiname":"Jusibampo",
    "gn:country_code":"MX",
    "gn:dem":132,
    "gn:feature_class":"P",
    "gn:feature_code":"PPL",
    "gn:name":"Jusibampo",
    "gn:population":93,
    "gn:timezone":"America/Hermosillo",
    "iso:country":"MX",
    "wof:name":"Jusibampo",
    "wof:placetype":"locality",
    "wof:population":93
},
  "geometry": {"coordinates":[-109.27083,27.07361],"type":"Point"}
}