{
  "type": "Feature",
  "properties": {
    "gn:admin1_code":"7",
    "gn:admin2_code":"30.0",
    "gn:asciiname":"Los Encinitos",
    "gn:country_code":"MX",
    "gn:dem":1572,
    "gn:feature_class":"P",
    "gn:feature_code":"PPL",
    "gn:name":"Los Encinitos",
    "gn:population":0,
    "gn:timezone":"America/Monterrey",
    "iso:country":"MX",
    "name:spa_x_preferred":[
        "Los Encinitos"
    ],
    "wof:name":"Los Encinitos",
    "wof:placetype":"locality"
},
  "geometry": {"coordinates":[-101.03488,25.49125],"type":"Point"}
}