{
  "type": "Feature",
  "properties": {
    "gn:admin1_code":"20",
    "gn:admin2_code":"406.0",
    "gn:asciiname":"Barrio San Antonio",
    "gn:country_code":"MX",
    "gn:dem":524,
    "gn:feature_class":"P",
    "gn:feature_code":"PPL",
    "gn:name":"Barrio San Antonio",
    "gn:population":57,
    "gn:timezone":"America/Mexico_City",
    "iso:country":"MX",
    "wof:name":"Barrio San Antonio",
    "wof:placetype":"locality",
    "wof:population":57
},
  "geometry": {"coordinates":[-96.7375,18.275],"type":"Point"}
}