{
  "type": "Feature",
  "properties": {
    "gn:admin1_code":"14",
    "gn:admin2_code":"120.0",
    "gn:asciiname":"San Rafael Tercero",
    "gn:country_code":"MX",
    "gn:dem":1625,
    "gn:feature_class":"P",
    "gn:feature_code":"PPL",
    "gn:name":"San Rafael Tercero",
    "gn:population":102,
    "gn:timezone":"America/Mexico_City",
    "iso:country":"MX",
    "wof:name":"San Rafael Tercero",
    "wof:placetype":"locality",
    "wof:population":102
},
  "geometry": {"coordinates":[-103.41889,20.795],"type":"Point"}
}