{
  "type": "Feature",
  "properties": {
    "gn:admin1_code":"8.0",
    "gn:admin2_code":"2.0",
    "gn:asciiname":"El Bordo",
    "gn:country_code":"MX",
    "gn:dem":614,
    "gn:feature_class":"P",
    "gn:feature_code":"PPL",
    "gn:name":"El Bordo",
    "gn:population":0,
    "gn:timezone":"America/Mexico_City",
    "iso:country":"MX",
    "name:spa_x_preferred":[
        "El Bordo"
    ],
    "wof:name":"El Bordo",
    "wof:placetype":"locality"
},
  "geometry": {"coordinates":[-103.53169,19.20768],"type":"Point"}
}