{
  "type": "Feature",
  "properties": {
    "gn:admin1_code":"24",
    "gn:admin2_code":"31",
    "gn:asciiname":"Los Duraznos",
    "gn:country_code":"MX",
    "gn:dem":480,
    "gn:feature_class":"P",
    "gn:feature_code":"PPL",
    "gn:name":"Los Duraznos",
    "gn:population":11,
    "gn:timezone":"America/Mexico_City",
    "iso:country":"MX",
    "wof:name":"Los Duraznos",
    "wof:placetype":"locality",
    "wof:population":11
},
  "geometry": {"coordinates":[-99.37611,21.63833],"type":"Point"}
}