{
  "type": "Feature",
  "properties": {
    "gn:admin1_code":"12",
    "gn:admin2_code":"75.0",
    "gn:asciiname":"La Tranca (La Uva)",
    "gn:country_code":"MX",
    "gn:dem":1471,
    "gn:feature_class":"P",
    "gn:feature_code":"PPL",
    "gn:name":"La Tranca (La Uva)",
    "gn:population":6,
    "gn:timezone":"America/Mexico_City",
    "iso:country":"MX",
    "wof:name":"La Tranca (La Uva)",
    "wof:placetype":"locality",
    "wof:population":6
},
  "geometry": {"coordinates":[-99.69656000000001,17.85114],"type":"Point"}
}