{
  "type": "Feature",
  "properties": {
    "gn:admin1_code":"5",
    "gn:admin2_code":"41.0",
    "gn:asciiname":"La Alianza",
    "gn:country_code":"MX",
    "gn:dem":1169,
    "gn:feature_class":"P",
    "gn:feature_code":"PPL",
    "gn:name":"La Alianza",
    "gn:population":53,
    "gn:timezone":"America/Mexico_City",
    "iso:country":"MX",
    "wof:name":"La Alianza",
    "wof:placetype":"locality",
    "wof:population":53
},
  "geometry": {"coordinates":[-91.67083,16.23167],"type":"Point"}
}