{
  "type": "Feature",
  "properties": {
    "gn:admin1_code":"14",
    "gn:admin2_code":"22.0",
    "gn:asciiname":"Rancho del Gueero Corona [Subestacion Melaque]",
    "gn:country_code":"MX",
    "gn:dem":42,
    "gn:feature_class":"P",
    "gn:feature_code":"PPL",
    "gn:name":"Rancho del G\u00fcero Corona [Subestaci\u00f3n Melaque]",
    "gn:population":7,
    "gn:timezone":"America/Mexico_City",
    "iso:country":"MX",
    "name:und_x_variant":[
        "Rancho del G\u00fcero Corona [Subestaci\u00f3n Melaque]"
    ],
    "wof:name":"Rancho del Gueero Corona [Subestacion Melaque]",
    "wof:placetype":"locality",
    "wof:population":7
},
  "geometry": {"coordinates":[-104.71222,19.26222000000001],"type":"Point"}
}