{
  "type": "Feature",
  "properties": {
    "gn:admin1_code":"32",
    "gn:admin2_code":"38",
    "gn:asciiname":"La Nopalera",
    "gn:country_code":"MX",
    "gn:dem":2012,
    "gn:feature_class":"P",
    "gn:feature_code":"PPL",
    "gn:name":"La Nopalera",
    "gn:population":12,
    "gn:timezone":"America/Mexico_City",
    "iso:country":"MX",
    "wof:name":"La Nopalera",
    "wof:placetype":"locality",
    "wof:population":12
},
  "geometry": {"coordinates":[-101.42889,22.62111],"type":"Point"}
}