{
  "type": "Feature",
  "properties": {
    "gn:admin1_code":"16",
    "gn:admin2_code":"63.0",
    "gn:asciiname":"La Cordoba",
    "gn:country_code":"MX",
    "gn:dem":1799,
    "gn:feature_class":"P",
    "gn:feature_code":"PPL",
    "gn:name":"La C\u00f3rdoba",
    "gn:population":234,
    "gn:timezone":"America/Mexico_City",
    "iso:country":"MX",
    "name:und_x_variant":[
        "La C\u00f3rdoba"
    ],
    "wof:name":"La Cordoba",
    "wof:placetype":"locality",
    "wof:population":234
},
  "geometry": {"coordinates":[-101.71639,19.97889],"type":"Point"}
}