{
  "type": "Feature",
  "properties": {
    "gn:admin1_code":"6.0",
    "gn:admin2_code":"27.0",
    "gn:asciiname":"Indio Lucas",
    "gn:country_code":"MX",
    "gn:dem":2374,
    "gn:feature_class":"P",
    "gn:feature_code":"PPL",
    "gn:name":"Indio Lucas",
    "gn:population":0,
    "gn:timezone":"America/Chihuahua",
    "iso:country":"MX",
    "wof:name":"Indio Lucas",
    "wof:placetype":"locality"
},
  "geometry": {"coordinates":[-107.15000000000001,26.91667],"type":"Point"}
}