{
  "type": "Feature",
  "properties": {
    "gn:admin1_code":"10.0",
    "gn:admin2_code":"7.0",
    "gn:asciiname":"Bucareli",
    "gn:country_code":"MX",
    "gn:dem":1121,
    "gn:feature_class":"P",
    "gn:feature_code":"PPL",
    "gn:name":"Bucareli",
    "gn:population":505,
    "gn:timezone":"America/Monterrey",
    "iso:country":"MX",
    "name:spa_x_preferred":[
        "Bucareli"
    ],
    "wof:name":"Bucareli",
    "wof:placetype":"locality",
    "wof:population":505
},
  "geometry": {"coordinates":[-103.53515,25.66334],"type":"Point"}
}