{
  "type": "Feature",
  "properties": {
    "gn:admin1_code":"32",
    "gn:admin2_code":"30.0",
    "gn:asciiname":"Atotonilco",
    "gn:country_code":"MX",
    "gn:dem":1650,
    "gn:feature_class":"P",
    "gn:feature_code":"PPL",
    "gn:name":"Atotonilco",
    "gn:population":76,
    "gn:timezone":"America/Mexico_City",
    "iso:country":"MX",
    "name:ceb_x_preferred":[
        "Atotonilco"
    ],
    "name:deu_x_preferred":[
        "Atotonilco"
    ],
    "name:ita_x_preferred":[
        "Atotonilco"
    ],
    "name:sco_x_preferred":[
        "Atotonilco"
    ],
    "name:spa_x_preferred":[
        "Atotonilco"
    ],
    "name:swe_x_preferred":[
        "Atotonilco"
    ],
    "wof:name":"Atotonilco",
    "wof:placetype":"locality",
    "wof:population":76
},
  "geometry": {"coordinates":[-103.32666999999999,21.92278],"type":"Point"}
}