{
  "type": "Feature",
  "properties": {
    "gn:admin1_code":"13",
    "gn:admin2_code":"43.0",
    "gn:asciiname":"Castadho",
    "gn:country_code":"MX",
    "gn:dem":1773,
    "gn:feature_class":"P",
    "gn:feature_code":"PPL",
    "gn:name":"Castadho",
    "gn:population":219,
    "gn:timezone":"America/Mexico_City",
    "iso:country":"MX",
    "wof:name":"Castadho",
    "wof:placetype":"locality",
    "wof:population":219
},
  "geometry": {"coordinates":[-99.17431999999999,20.79568],"type":"Point"}
}