{
  "type": "Feature",
  "properties": {
    "gn:admin1_code":"28.0",
    "gn:admin2_code":"11.0",
    "gn:asciiname":"Las Auroras",
    "gn:country_code":"MX",
    "gn:dem":91,
    "gn:feature_class":"P",
    "gn:feature_code":"PPL",
    "gn:name":"Las Auroras",
    "gn:population":5,
    "gn:timezone":"America/Monterrey",
    "iso:country":"MX",
    "name:spa_x_preferred":[
        "Las Auroras"
    ],
    "wof:name":"Las Auroras",
    "wof:placetype":"locality",
    "wof:population":5
},
  "geometry": {"coordinates":[-99.08278,22.92528],"type":"Point"}
}