{
  "type": "Feature",
  "properties": {
    "gn:admin1_code":"21",
    "gn:admin2_code":"4.0",
    "gn:asciiname":"Los Corralitos",
    "gn:country_code":"MX",
    "gn:dem":2187,
    "gn:feature_class":"P",
    "gn:feature_code":"PPL",
    "gn:name":"Los Corralitos",
    "gn:population":200,
    "gn:timezone":"America/Mexico_City",
    "iso:country":"MX",
    "wof:name":"Los Corralitos",
    "wof:placetype":"locality",
    "wof:population":200
},
  "geometry": {"coordinates":[-97.77106999999999,19.00653],"type":"Point"}
}