{
  "type": "Feature",
  "properties": {
    "gn:admin1_code":"13",
    "gn:admin2_code":"49.0",
    "gn:asciiname":"Tlacuilola",
    "gn:country_code":"MX",
    "gn:dem":986,
    "gn:feature_class":"P",
    "gn:feature_code":"PPL",
    "gn:name":"Tlacuilola",
    "gn:population":393,
    "gn:timezone":"America/Mexico_City",
    "iso:country":"MX",
    "wof:name":"Tlacuilola",
    "wof:placetype":"locality",
    "wof:population":393
},
  "geometry": {"coordinates":[-99.05897,21.23258],"type":"Point"}
}