{
  "type": "Feature",
  "properties": {
    "gn:admin1_code":"5",
    "gn:admin2_code":"61",
    "gn:asciiname":"Bellavista",
    "gn:country_code":"MX",
    "gn:dem":256,
    "gn:feature_class":"P",
    "gn:feature_code":"PPL",
    "gn:name":"Bellavista",
    "gn:population":25,
    "gn:timezone":"America/Mexico_City",
    "iso:country":"MX",
    "name:cat_x_preferred":[
        "Bellavista"
    ],
    "name:ceb_x_preferred":[
        "Bellavista"
    ],
    "name:deu_x_preferred":[
        "Bellavista"
    ],
    "name:fra_x_preferred":[
        "Bellavista"
    ],
    "name:ita_x_preferred":[
        "Bellavista"
    ],
    "name:kor_x_preferred":[
        "\ubca8\ub77c\ube44\uc2a4\ud0c0"
    ],
    "name:nld_x_preferred":[
        "Bellavista"
    ],
    "name:pol_x_preferred":[
        "Bellavista"
    ],
    "name:por_x_preferred":[
        "Bellavista"
    ],
    "name:spa_x_preferred":[
        "Bellavista"
    ],
    "name:srp_x_preferred":[
        "Bellavista"
    ],
    "name:swe_x_preferred":[
        "Bellavista"
    ],
    "wof:name":"Bellavista",
    "wof:placetype":"locality",
    "wof:population":25
},
  "geometry": {"coordinates":[-93.57277999999999,17.08694],"type":"Point"}
}