{
  "type": "Feature",
  "properties": {
    "gn:admin1_code":"16",
    "gn:admin2_code":"95.0",
    "gn:asciiname":"Puente de Tocumbo",
    "gn:country_code":"MX",
    "gn:dem":1594,
    "gn:feature_class":"P",
    "gn:feature_code":"PPL",
    "gn:name":"Puente de Tocumbo",
    "gn:population":0,
    "gn:timezone":"America/Mexico_City",
    "iso:country":"MX",
    "name:spa_x_preferred":[
        "Puente de Tocumbo"
    ],
    "wof:name":"Puente de Tocumbo",
    "wof:placetype":"locality"
},
  "geometry": {"coordinates":[-102.49463,19.70085],"type":"Point"}
}