{
  "type": "Feature",
  "properties": {
    "gn:admin1_code":"19",
    "gn:admin2_code":"40.0",
    "gn:asciiname":"Paso Nogal",
    "gn:country_code":"MX",
    "gn:dem":156,
    "gn:feature_class":"P",
    "gn:feature_code":"PPL",
    "gn:name":"Paso Nogal",
    "gn:population":0,
    "gn:timezone":"America/Monterrey",
    "iso:country":"MX",
    "wof:name":"Paso Nogal",
    "wof:placetype":"locality"
},
  "geometry": {"coordinates":[-99.61185999999999,26.49855],"type":"Point"}
}