{
  "type": "Feature",
  "properties": {
    "gn:admin1_code":"30",
    "gn:admin2_code":"121.0",
    "gn:asciiname":"El Moralillo",
    "gn:country_code":"MX",
    "gn:dem":81,
    "gn:feature_class":"P",
    "gn:feature_code":"PPL",
    "gn:name":"El Moralillo",
    "gn:population":0,
    "gn:timezone":"America/Mexico_City",
    "iso:country":"MX",
    "name:spa_x_preferred":[
        "El Moralillo"
    ],
    "name:spa_x_variant":[
        "Moralillo"
    ],
    "wof:name":"El Moralillo",
    "wof:placetype":"locality"
},
  "geometry": {"coordinates":[-97.96621,21.49387],"type":"Point"}
}