{
  "type": "Feature",
  "properties": {
    "gn:admin1_code":"21",
    "gn:admin2_code":"217.0",
    "gn:asciiname":"Tecolotleapa",
    "gn:country_code":"MX",
    "gn:dem":2418,
    "gn:feature_class":"P",
    "gn:feature_code":"PPL",
    "gn:name":"Tecolotleapa",
    "gn:population":276,
    "gn:timezone":"America/Mexico_City",
    "iso:country":"MX",
    "wof:name":"Tecolotleapa",
    "wof:placetype":"locality",
    "wof:population":276
},
  "geometry": {"coordinates":[-97.05306,18.33861],"type":"Point"}
}