{
  "type": "Feature",
  "properties": {
    "gn:admin1_code":"26",
    "gn:admin2_code":"60",
    "gn:asciiname":"Aquimuri (Veredas Curvosas)",
    "gn:country_code":"MX",
    "gn:dem":910,
    "gn:feature_class":"P",
    "gn:feature_code":"PPL",
    "gn:name":"Aquimuri (Veredas Curvosas)",
    "gn:population":17,
    "gn:timezone":"America/Hermosillo",
    "iso:country":"MX",
    "wof:name":"Aquimuri (Veredas Curvosas)",
    "wof:placetype":"locality",
    "wof:population":17
},
  "geometry": {"coordinates":[-111.425,31.11333],"type":"Point"}
}