{
  "type": "Feature",
  "properties": {
    "gn:admin1_code":"10.0",
    "gn:admin2_code":"30.0",
    "gn:asciiname":"San Jose del Carmen",
    "gn:country_code":"MX",
    "gn:dem":1556,
    "gn:feature_class":"P",
    "gn:feature_code":"PPL",
    "gn:name":"San Jos\u00e9 del Carmen",
    "gn:population":0,
    "gn:timezone":"America/Monterrey",
    "iso:country":"MX",
    "name:spa_x_preferred":[
        "San Jos\u00e9 del Carmen"
    ],
    "wof:name":"San Jose del Carmen",
    "wof:placetype":"locality"
},
  "geometry": {"coordinates":[-104.21504,25.50879],"type":"Point"}
}