{
  "type": "Feature",
  "properties": {
    "gn:admin1_code":"16",
    "gn:admin2_code":"12",
    "gn:asciiname":"San Isidro (Capullo)",
    "gn:country_code":"MX",
    "gn:dem":480,
    "gn:feature_class":"P",
    "gn:feature_code":"PPL",
    "gn:name":"San Isidro (Capullo)",
    "gn:population":17,
    "gn:timezone":"America/Mexico_City",
    "iso:country":"MX",
    "wof:name":"San Isidro (Capullo)",
    "wof:placetype":"locality",
    "wof:population":17
},
  "geometry": {"coordinates":[-102.60583,19.21528],"type":"Point"}
}