{
  "type": "Feature",
  "properties": {
    "gn:admin1_code":"6",
    "gn:admin2_code":"7.0",
    "gn:asciiname":"El Alamo",
    "gn:country_code":"MX",
    "gn:dem":1599,
    "gn:feature_class":"P",
    "gn:feature_code":"PPL",
    "gn:name":"El \u00c1lamo",
    "gn:population":6,
    "gn:timezone":"America/Chihuahua",
    "iso:country":"MX",
    "name:und_x_variant":[
        "El \u00c1lamo"
    ],
    "wof:name":"El Alamo",
    "wof:placetype":"locality",
    "wof:population":6
},
  "geometry": {"coordinates":[-106.37783,26.98318],"type":"Point"}
}