{
  "type": "Feature",
  "properties": {
    "gn:admin1_code":"27",
    "gn:admin2_code":"4.0",
    "gn:asciiname":"Flores del Tropico",
    "gn:country_code":"MX",
    "gn:dem":8,
    "gn:feature_class":"P",
    "gn:feature_code":"PPL",
    "gn:name":"Flores del Tr\u00f3pico",
    "gn:population":499,
    "gn:timezone":"America/Mexico_City",
    "iso:country":"MX",
    "name:und_x_variant":[
        "Flores del Tr\u00f3pico"
    ],
    "wof:name":"Flores del Tropico",
    "wof:placetype":"locality",
    "wof:population":499
},
  "geometry": {"coordinates":[-92.97528,18.00389],"type":"Point"}
}