{
  "type": "Feature",
  "properties": {
    "gn:admin1_code":"1.0",
    "gn:admin2_code":"2.0",
    "gn:asciiname":"Pozo Ave Maria",
    "gn:country_code":"MX",
    "gn:dem":2030,
    "gn:feature_class":"P",
    "gn:feature_code":"PPL",
    "gn:name":"Pozo Ave Mar\u00eda",
    "gn:population":4,
    "gn:timezone":"America/Mexico_City",
    "iso:country":"MX",
    "wof:name":"Pozo Ave Maria",
    "wof:placetype":"locality",
    "wof:population":4
},
  "geometry": {"coordinates":[-102.03861000000001,22.26222000000001],"type":"Point"}
}