{
  "type": "Feature",
  "properties": {
    "gn:admin1_code":"26",
    "gn:admin2_code":"20.0",
    "gn:asciiname":"San Fernando",
    "gn:country_code":"MX",
    "gn:dem":431,
    "gn:feature_class":"P",
    "gn:feature_code":"PPL",
    "gn:name":"San Fernando",
    "gn:population":0,
    "gn:timezone":"America/Hermosillo",
    "iso:country":"MX",
    "name:spa_x_preferred":[
        "San Fernando"
    ],
    "wof:name":"San Fernando",
    "wof:placetype":"locality"
},
  "geometry": {"coordinates":[-110.98118999999998,29.53452],"type":"Point"}
}