{
  "type": "Feature",
  "properties": {
    "gn:admin1_code":"30",
    "gn:admin2_code":"4.0",
    "gn:asciiname":"Triangulo M",
    "gn:country_code":"MX",
    "gn:dem":70,
    "gn:feature_class":"P",
    "gn:feature_code":"PPL",
    "gn:name":"Tri\u00e1ngulo M",
    "gn:population":0,
    "gn:timezone":"America/Mexico_City",
    "iso:country":"MX",
    "name:spa_x_preferred":[
        "Tri\u00e1ngulo M"
    ],
    "wof:name":"Triangulo M",
    "wof:placetype":"locality"
},
  "geometry": {"coordinates":[-96.46155,19.48422],"type":"Point"}
}