{
  "type": "Feature",
  "properties": {
    "gn:admin1_code":"20.0",
    "gn:admin2_code":"318.0",
    "gn:asciiname":"El Tlachicon",
    "gn:country_code":"MX",
    "gn:dem":427,
    "gn:feature_class":"P",
    "gn:feature_code":"PPL",
    "gn:name":"El Tlachic\u00f3n",
    "gn:population":0,
    "gn:timezone":"America/Mexico_City",
    "iso:country":"MX",
    "name:spa_x_preferred":[
        "El Tlachic\u00f3n"
    ],
    "wof:name":"El Tlachicon",
    "wof:placetype":"locality"
},
  "geometry": {"coordinates":[-97.02736,15.99812],"type":"Point"}
}