{
  "type": "Feature",
  "properties": {
    "gn:admin1_code":"22.0",
    "gn:admin2_code":"2.0",
    "gn:asciiname":"Puerto del Derramadero",
    "gn:country_code":"MX",
    "gn:dem":2174,
    "gn:feature_class":"P",
    "gn:feature_code":"PPL",
    "gn:name":"Puerto del Derramadero",
    "gn:population":0,
    "gn:timezone":"America/Mexico_City",
    "iso:country":"MX",
    "name:spa_x_preferred":[
        "Puerto del Derramadero"
    ],
    "wof:name":"Puerto del Derramadero",
    "wof:placetype":"locality"
},
  "geometry": {"coordinates":[-99.62775999999999,21.10638],"type":"Point"}
}