{
  "type": "Feature",
  "properties": {
    "gn:admin1_code":"26.0",
    "gn:asciiname":"La Atravesada",
    "gn:country_code":"MX",
    "gn:dem":714,
    "gn:feature_class":"P",
    "gn:feature_code":"PPL",
    "gn:name":"La Atravesada",
    "gn:population":0,
    "gn:timezone":"America/Hermosillo",
    "iso:country":"MX",
    "name:spa_x_preferred":[
        "La Atravesada"
    ],
    "wof:name":"La Atravesada",
    "wof:placetype":"locality"
},
  "geometry": {"coordinates":[-109.19766,27.92243],"type":"Point"}
}