{
  "type": "Feature",
  "properties": {
    "gn:admin1_code":"14.0",
    "gn:asciiname":"Presa de San Agustin",
    "gn:country_code":"MX",
    "gn:dem":1808,
    "gn:feature_class":"P",
    "gn:feature_code":"PPL",
    "gn:name":"Presa de San Agust\u00edn",
    "gn:population":0,
    "gn:timezone":"America/Mexico_City",
    "iso:country":"MX",
    "name:spa_x_preferred":[
        "Presa de San Agust\u00edn"
    ],
    "wof:name":"Presa de San Agustin",
    "wof:placetype":"locality"
},
  "geometry": {"coordinates":[-102.12184999999999,21.1636],"type":"Point"}
}