{
  "type": "Feature",
  "properties": {
    "gn:admin1_code":"6",
    "gn:admin2_code":"13.0",
    "gn:asciiname":"Vado del Coche",
    "gn:country_code":"MX",
    "gn:dem":1567,
    "gn:feature_class":"P",
    "gn:feature_code":"PPL",
    "gn:name":"Vado del Coche",
    "gn:population":0,
    "gn:timezone":"America/Chihuahua",
    "iso:country":"MX",
    "wof:name":"Vado del Coche",
    "wof:placetype":"locality"
},
  "geometry": {"coordinates":[-107.96666999999999,30.28333],"type":"Point"}
}