{
  "type": "Feature",
  "properties": {
    "gn:admin1_code":"5",
    "gn:admin2_code":"92.0",
    "gn:asciiname":"Trece de Septiembre",
    "gn:country_code":"MX",
    "gn:dem":178,
    "gn:feature_class":"P",
    "gn:feature_code":"PPL",
    "gn:name":"Trece de Septiembre",
    "gn:population":77,
    "gn:timezone":"America/Mexico_City",
    "iso:country":"MX",
    "wof:name":"Trece de Septiembre",
    "wof:placetype":"locality",
    "wof:population":77
},
  "geometry": {"coordinates":[-93.52694,17.12083],"type":"Point"}
}