{
  "type": "Feature",
  "properties": {
    "gn:admin1_code":"6",
    "gn:admin2_code":"65.0",
    "gn:asciiname":"Huicorachi",
    "gn:country_code":"MX",
    "gn:dem":1911,
    "gn:feature_class":"P",
    "gn:feature_code":"PPL",
    "gn:name":"Huic\u00f3rachi",
    "gn:population":0,
    "gn:timezone":"America/Chihuahua",
    "iso:country":"MX",
    "name:spa_x_preferred":[
        "Bahuechi"
    ],
    "name:spa_x_variant":[
        "Huic\u00f3rachi"
    ],
    "wof:name":"Huicorachi",
    "wof:placetype":"locality"
},
  "geometry": {"coordinates":[-107.95135999999999,27.29185],"type":"Point"}
}