{
  "type": "Feature",
  "properties": {
    "gn:admin1_code":"11",
    "gn:admin2_code":"26.0",
    "gn:asciiname":"Capilla Blanca (Rancho de los Perez)",
    "gn:country_code":"MX",
    "gn:dem":1741,
    "gn:feature_class":"P",
    "gn:feature_code":"PPL",
    "gn:name":"Capilla Blanca (Rancho de los P\u00e9rez)",
    "gn:population":6,
    "gn:timezone":"America/Mexico_City",
    "iso:country":"MX",
    "name:und_x_variant":[
        "Capilla Blanca (Rancho de los P\u00e9rez)"
    ],
    "wof:name":"Capilla Blanca (Rancho de los Perez)",
    "wof:placetype":"locality",
    "wof:population":6
},
  "geometry": {"coordinates":[-101.52694,20.84],"type":"Point"}
}