{
  "type": "Feature",
  "properties": {
    "gn:admin1_code":"6",
    "gn:admin2_code":"34.0",
    "gn:asciiname":"Los Mendoza",
    "gn:country_code":"MX",
    "gn:dem":2153,
    "gn:feature_class":"P",
    "gn:feature_code":"PPL",
    "gn:name":"Los Mendoza",
    "gn:population":0,
    "gn:timezone":"America/Chihuahua",
    "iso:country":"MX",
    "name:spa_x_preferred":[
        "Los Mendoza"
    ],
    "wof:name":"Los Mendoza",
    "wof:placetype":"locality"
},
  "geometry": {"coordinates":[-107.67314,29.66228],"type":"Point"}
}