{
  "type": "Feature",
  "properties": {
    "gn:admin1_code":"28",
    "gn:admin2_code":"2.0",
    "gn:asciiname":"Galeras",
    "gn:country_code":"MX",
    "gn:dem":63,
    "gn:feature_class":"P",
    "gn:feature_code":"PPL",
    "gn:name":"Galeras",
    "gn:population":9,
    "gn:timezone":"America/Monterrey",
    "iso:country":"MX",
    "name:ara_x_preferred":[
        "\u063a\u0627\u0644\u064a\u0631\u0627"
    ],
    "name:bul_x_preferred":[
        "\u0413\u0430\u043b\u0435\u0440\u0430\u0441"
    ],
    "name:cat_x_preferred":[
        "Galeras"
    ],
    "name:ceb_x_preferred":[
        "Volc\u00e1n Galeras"
    ],
    "name:ces_x_preferred":[
        "Galeras"
    ],
    "name:deu_x_preferred":[
        "Galeras"
    ],
    "name:epo_x_preferred":[
        "Galeras"
    ],
    "name:est_x_preferred":[
        "Galerase vulkaan"
    ],
    "name:fao_x_preferred":[
        "Galeras"
    ],
    "name:fas_x_preferred":[
        "\u06af\u0627\u0644\u0631\u0627\u0633"
    ],
    "name:fin_x_preferred":[
        "Galeras"
    ],
    "name:fra_x_preferred":[
        "Galeras"
    ],
    "name:glg_x_preferred":[
        "Volc\u00e1n Galeras"
    ],
    "name:heb_x_preferred":[
        "\u05d2\u05dc\u05e8\u05d0\u05e1"
    ],
    "name:hrv_x_preferred":[
        "Galeras"
    ],
    "name:hun_x_preferred":[
        "Galeras"
    ],
    "name:ind_x_preferred":[
        "Galeras"
    ],
    "name:ita_x_preferred":[
        "Galeras"
    ],
    "name:jpn_x_preferred":[
        "\u30ac\u30ec\u30e9\u30b9\u5c71"
    ],
    "name:kat_x_preferred":[
        "\u10d2\u10d0\u10da\u10d4\u10e0\u10d0\u10e1\u10d8"
    ],
    "name:kor_x_preferred":[
        "\uac08\ub808\ub77c\uc2a4 \ud654\uc0b0"
    ],
    "name:lit_x_preferred":[
        "Galeras"
    ],
    "name:mkd_x_preferred":[
        "\u0413\u0430\u043b\u0435\u0440\u0430\u0441"
    ],
    "name:msa_x_preferred":[
        "Galeras"
    ],
    "name:nld_x_preferred":[
        "Galeras"
    ],
    "name:nor_x_preferred":[
        "Galeras"
    ],
    "name:oss_x_preferred":[
        "\u0413\u0430\u043b\u0435\u0440\u0430\u0441"
    ],
    "name:pol_x_preferred":[
        "Galeras"
    ],
    "name:por_x_preferred":[
        "Galeras"
    ],
    "name:rus_x_preferred":[
        "\u0413\u0430\u043b\u0435\u0440\u0430\u0441"
    ],
    "name:slk_x_preferred":[
        "Galeras"
    ],
    "name:spa_x_preferred":[
        "Volc\u00e1n Galeras"
    ],
    "name:swa_x_preferred":[
        "Galeras"
    ],
    "name:swe_x_preferred":[
        "Galeras"
    ],
    "name:ukr_x_preferred":[
        "\u0490\u0430\u043b\u0435\u0440\u0430\u0441"
    ],
    "name:zho_x_preferred":[
        "\u52a0\u52d2\u62c9\u65af\u706b\u5c71"
    ],
    "wof:name":"Galeras",
    "wof:placetype":"locality",
    "wof:population":9
},
  "geometry": {"coordinates":[-97.84389,23.06861],"type":"Point"}
}