{
  "type": "Feature",
  "properties": {
    "gn:admin1_code":"11",
    "gn:admin2_code":"22.0",
    "gn:asciiname":"El Tropezon",
    "gn:country_code":"MX",
    "gn:dem":2193,
    "gn:feature_class":"P",
    "gn:feature_code":"PPL",
    "gn:name":"El Tropez\u00f3n",
    "gn:population":84,
    "gn:timezone":"America/Mexico_City",
    "iso:country":"MX",
    "name:und_x_variant":[
        "El Tropez\u00f3n"
    ],
    "wof:name":"El Tropezon",
    "wof:placetype":"locality",
    "wof:population":84
},
  "geometry": {"coordinates":[-101.43944,21.64083],"type":"Point"}
}