{
  "type": "Feature",
  "properties": {
    "gn:admin1_code":"9",
    "gn:admin2_code":"5.0",
    "gn:asciiname":"Villahermosa",
    "gn:country_code":"MX",
    "gn:dem":2237,
    "gn:feature_class":"P",
    "gn:feature_code":"PPL",
    "gn:name":"Villahermosa",
    "gn:population":0,
    "gn:timezone":"America/Mexico_City",
    "iso:country":"MX",
    "wof:name":"Villahermosa",
    "wof:placetype":"locality"
},
  "geometry": {"coordinates":[-99.09999999999999,19.48333],"type":"Point"}
}