{
  "type": "Feature",
  "properties": {
    "gn:admin1_code":"28",
    "gn:admin2_code":"32.0",
    "gn:asciiname":"El Valereno",
    "gn:country_code":"MX",
    "gn:dem":118,
    "gn:feature_class":"P",
    "gn:feature_code":"PPL",
    "gn:name":"El Valere\u00f1o",
    "gn:population":0,
    "gn:timezone":"America/Matamoros",
    "iso:country":"MX",
    "name:spa_x_preferred":[
        "El Valere\u00f1o"
    ],
    "wof:name":"El Valereno",
    "wof:placetype":"locality"
},
  "geometry": {"coordinates":[-98.52059,25.94206],"type":"Point"}
}