{
  "type": "Feature",
  "properties": {
    "gn:admin1_code":"21.0",
    "gn:admin2_code":"197.0",
    "gn:asciiname":"Nactanca Grande",
    "gn:country_code":"MX",
    "gn:dem":962,
    "gn:feature_class":"P",
    "gn:feature_code":"PPL",
    "gn:name":"Nactanca Grande",
    "gn:population":460,
    "gn:timezone":"America/Mexico_City",
    "iso:country":"MX",
    "name:spa_x_preferred":[
        "Nactanca Grande"
    ],
    "wof:name":"Nactanca Grande",
    "wof:placetype":"locality",
    "wof:population":460
},
  "geometry": {"coordinates":[-97.90721000000001,20.30012],"type":"Point"}
}