{
  "type": "Feature",
  "properties": {
    "gn:admin1_code":"26",
    "gn:admin2_code":"30.0",
    "gn:asciiname":"Villa Benetto",
    "gn:country_code":"MX",
    "gn:dem":60,
    "gn:feature_class":"P",
    "gn:feature_code":"PPL",
    "gn:name":"Villa Benetto",
    "gn:population":0,
    "gn:timezone":"America/Hermosillo",
    "iso:country":"MX",
    "name:spa_x_preferred":[
        "Villa Benetto"
    ],
    "name:spa_x_variant":[
        "Las Calvas de Enmedio"
    ],
    "wof:name":"Villa Benetto",
    "wof:placetype":"locality"
},
  "geometry": {"coordinates":[-111.40271,28.70016],"type":"Point"}
}