{
  "type": "Feature",
  "properties": {
    "gn:admin1_code":"20",
    "gn:admin2_code":"437.0",
    "gn:asciiname":"Arroyo Frijol",
    "gn:country_code":"MX",
    "gn:dem":1644,
    "gn:feature_class":"P",
    "gn:feature_code":"PPL",
    "gn:name":"Arroyo Frijol",
    "gn:population":102,
    "gn:timezone":"America/Mexico_City",
    "iso:country":"MX",
    "wof:name":"Arroyo Frijol",
    "wof:placetype":"locality",
    "wof:population":102
},
  "geometry": {"coordinates":[-96.08028,17.12694],"type":"Point"}
}