{
  "type": "Feature",
  "properties": {
    "gn:admin1_code":"20",
    "gn:admin2_code":"366",
    "gn:asciiname":"Llano San Juan",
    "gn:country_code":"MX",
    "gn:dem":670,
    "gn:feature_class":"P",
    "gn:feature_code":"PPL",
    "gn:name":"Llano San Juan",
    "gn:population":14,
    "gn:timezone":"America/Mexico_City",
    "iso:country":"MX",
    "wof:name":"Llano San Juan",
    "wof:placetype":"locality",
    "wof:population":14
},
  "geometry": {"coordinates":[-96.655,16.07278],"type":"Point"}
}