{
  "type": "Feature",
  "properties": {
    "gn:admin1_code":"30",
    "gn:admin2_code":"72.0",
    "gn:asciiname":"Puerto Lobo",
    "gn:country_code":"MX",
    "gn:dem":2466,
    "gn:feature_class":"P",
    "gn:feature_code":"PPL",
    "gn:name":"Puerto Lobo",
    "gn:population":0,
    "gn:timezone":"America/Mexico_City",
    "iso:country":"MX",
    "name:spa_x_preferred":[
        "Puerto Lobo"
    ],
    "name:spa_x_variant":[
        "Puerto de Lobos"
    ],
    "wof:name":"Puerto Lobo",
    "wof:placetype":"locality"
},
  "geometry": {"coordinates":[-98.42001999999999,20.38024],"type":"Point"}
}