{
  "type": "Feature",
  "properties": {
    "gn:admin1_code":"5",
    "gn:admin2_code":"3.0",
    "gn:asciiname":"La Lupita",
    "gn:country_code":"MX",
    "gn:dem":45,
    "gn:feature_class":"P",
    "gn:feature_code":"PPL",
    "gn:name":"La Lupita",
    "gn:population":7,
    "gn:timezone":"America/Mexico_City",
    "iso:country":"MX",
    "name:spa_x_preferred":[
        "La Lupita"
    ],
    "wof:name":"La Lupita",
    "wof:placetype":"locality",
    "wof:population":7
},
  "geometry": {"coordinates":[-92.67861000000001,15.29917],"type":"Point"}
}