{
  "type": "Feature",
  "properties": {
    "gn:admin1_code":"5",
    "gn:admin2_code":"99",
    "gn:asciiname":"Morelia",
    "gn:country_code":"MX",
    "gn:dem":744,
    "gn:feature_class":"P",
    "gn:feature_code":"PPL",
    "gn:name":"Morelia",
    "gn:population":11,
    "gn:timezone":"America/Mexico_City",
    "iso:country":"MX",
    "wof:name":"Morelia",
    "wof:placetype":"locality",
    "wof:population":11
},
  "geometry": {"coordinates":[-91.93083,15.88],"type":"Point"}
}