{
  "type": "Feature",
  "properties": {
    "gn:admin1_code":"5.0",
    "gn:admin2_code":"14.0",
    "gn:asciiname":"Cocalguitz",
    "gn:country_code":"MX",
    "gn:dem":1042,
    "gn:feature_class":"P",
    "gn:feature_code":"PPL",
    "gn:name":"Cocalguitz",
    "gn:population":0,
    "gn:timezone":"America/Mexico_City",
    "iso:country":"MX",
    "name:spa_x_preferred":[
        "Cocalguitz"
    ],
    "wof:name":"Cocalguitz",
    "wof:placetype":"locality"
},
  "geometry": {"coordinates":[-92.76878000000001,17.00339],"type":"Point"}
}