{
  "type": "Feature",
  "properties": {
    "gn:admin1_code":"2",
    "gn:admin2_code":"2.0",
    "gn:asciiname":"Rancho Mendivil",
    "gn:country_code":"MX",
    "gn:dem":34,
    "gn:feature_class":"P",
    "gn:feature_code":"PPL",
    "gn:name":"Rancho Mend\u00edvil",
    "gn:population":5,
    "gn:timezone":"America/Tijuana",
    "iso:country":"MX",
    "name:und_x_variant":[
        "Rancho Mend\u00edvil"
    ],
    "wof:name":"Rancho Mendivil",
    "wof:placetype":"locality",
    "wof:population":5
},
  "geometry": {"coordinates":[-114.74639000000001,32.69778],"type":"Point"}
}