{
  "type": "Feature",
  "properties": {
    "gn:admin1_code":"16",
    "gn:admin2_code":"58",
    "gn:asciiname":"Mesa de Tavera (La Joya)",
    "gn:country_code":"MX",
    "gn:dem":1860,
    "gn:feature_class":"P",
    "gn:feature_code":"PPL",
    "gn:name":"Mesa de Tavera (La Joya)",
    "gn:population":47,
    "gn:timezone":"America/Mexico_City",
    "iso:country":"MX",
    "wof:name":"Mesa de Tavera (La Joya)",
    "wof:placetype":"locality",
    "wof:population":47
},
  "geometry": {"coordinates":[-102.11722,19.38417],"type":"Point"}
}