{
  "type": "Feature",
  "properties": {
    "gn:admin1_code":"15",
    "gn:admin2_code":"114.0",
    "gn:asciiname":"Los Aviones",
    "gn:country_code":"MX",
    "gn:dem":2749,
    "gn:feature_class":"P",
    "gn:feature_code":"PPL",
    "gn:name":"Los Aviones",
    "gn:population":142,
    "gn:timezone":"America/Mexico_City",
    "iso:country":"MX",
    "wof:name":"Los Aviones",
    "wof:placetype":"locality",
    "wof:population":142
},
  "geometry": {"coordinates":[-100.11333,19.50167],"type":"Point"}
}