{
  "type": "Feature",
  "properties": {
    "gn:admin1_code":"14",
    "gn:admin2_code":"85.0",
    "gn:asciiname":"Portezuelo Viejo",
    "gn:country_code":"MX",
    "gn:dem":1193,
    "gn:feature_class":"P",
    "gn:feature_code":"PPL",
    "gn:name":"Portezuelo Viejo",
    "gn:population":0,
    "gn:timezone":"America/Mexico_City",
    "iso:country":"MX",
    "name:spa_x_preferred":[
        "Portezuelo Viejo"
    ],
    "wof:name":"Portezuelo Viejo",
    "wof:placetype":"locality"
},
  "geometry": {"coordinates":[-103.2829,19.63835],"type":"Point"}
}