{
  "type": "Feature",
  "properties": {
    "gn:admin1_code":"6.0",
    "gn:admin2_code":"17.0",
    "gn:asciiname":"Colonia Maurilio Ortiz",
    "gn:country_code":"MX",
    "gn:dem":2184,
    "gn:feature_class":"P",
    "gn:feature_code":"PPL",
    "gn:name":"Colonia Maurilio Ortiz",
    "gn:population":0,
    "gn:timezone":"America/Chihuahua",
    "iso:country":"MX",
    "name:spa_x_preferred":[
        "Colonia Maurilio Ortiz"
    ],
    "name:und_x_variant":[
        "Colonia Ort\u00edz"
    ],
    "wof:name":"Colonia Maurilio Ortiz",
    "wof:placetype":"locality"
},
  "geometry": {"coordinates":[-106.7847,28.9539],"type":"Point"}
}