{
  "type": "Feature",
  "properties": {
    "gn:admin1_code":"3",
    "gn:admin2_code":"8",
    "gn:asciiname":"Luna del Tezal",
    "gn:country_code":"MX",
    "gn:dem":110,
    "gn:feature_class":"P",
    "gn:feature_code":"PPL",
    "gn:name":"Luna del Tezal",
    "gn:population":13,
    "gn:timezone":"America/Mazatlan",
    "iso:country":"MX",
    "wof:name":"Luna del Tezal",
    "wof:placetype":"locality",
    "wof:population":13
},
  "geometry": {"coordinates":[-109.88484,22.91914],"type":"Point"}
}