{
  "type": "Feature",
  "properties": {
    "gn:admin1_code":"5",
    "gn:admin2_code":"87",
    "gn:asciiname":"El Cascabel",
    "gn:country_code":"MX",
    "gn:dem":20,
    "gn:feature_class":"P",
    "gn:feature_code":"PPL",
    "gn:name":"El Cascabel",
    "gn:population":11,
    "gn:timezone":"America/Mexico_City",
    "iso:country":"MX",
    "wof:name":"El Cascabel",
    "wof:placetype":"locality",
    "wof:population":11
},
  "geometry": {"coordinates":[-92.175,14.64722],"type":"Point"}
}