{
  "type": "Feature",
  "properties": {
    "gn:admin1_code":"5.0",
    "gn:asciiname":"San Jose Magallanes",
    "gn:country_code":"MX",
    "gn:dem":1526,
    "gn:feature_class":"P",
    "gn:feature_code":"PPL",
    "gn:name":"San Jos\u00e9 Magallanes",
    "gn:population":0,
    "gn:timezone":"America/Mexico_City",
    "iso:country":"MX",
    "name:spa_x_preferred":[
        "San Jos\u00e9 Magallanes"
    ],
    "wof:name":"San Jose Magallanes",
    "wof:placetype":"locality"
},
  "geometry": {"coordinates":[-93.00499000000001,15.76999],"type":"Point"}
}