{
  "type": "Feature",
  "properties": {
    "gn:admin1_code":"30.0",
    "gn:admin2_code":"161.0",
    "gn:asciiname":"Dos Potrillos",
    "gn:country_code":"MX",
    "gn:dem":67,
    "gn:feature_class":"P",
    "gn:feature_code":"PPL",
    "gn:name":"Dos Potrillos",
    "gn:population":0,
    "gn:timezone":"America/Mexico_City",
    "iso:country":"MX",
    "name:spa_x_preferred":[
        "Dos Potrillos"
    ],
    "wof:name":"Dos Potrillos",
    "wof:placetype":"locality"
},
  "geometry": {"coordinates":[-98.39194000000001,21.56056],"type":"Point"}
}