{
  "type": "Feature",
  "properties": {
    "gn:admin1_code":"24",
    "gn:admin2_code":"3.0",
    "gn:asciiname":"Xolmon",
    "gn:country_code":"MX",
    "gn:dem":598,
    "gn:feature_class":"P",
    "gn:feature_code":"PPL",
    "gn:name":"Xolm\u00f3n",
    "gn:population":0,
    "gn:timezone":"America/Mexico_City",
    "iso:country":"MX",
    "name:spa_x_preferred":[
        "Xolm\u00f3n"
    ],
    "name:spa_x_variant":[
        "Xolm\u00e1n"
    ],
    "wof:name":"Xolmon",
    "wof:placetype":"locality"
},
  "geometry": {"coordinates":[-99.05092999999999,21.5412],"type":"Point"}
}