{
  "type": "Feature",
  "properties": {
    "gn:admin1_code":"24",
    "gn:admin2_code":"10.0",
    "gn:asciiname":"El Custodio",
    "gn:country_code":"MX",
    "gn:dem":1018,
    "gn:feature_class":"P",
    "gn:feature_code":"PPL",
    "gn:name":"El Custodio",
    "gn:population":0,
    "gn:timezone":"America/Mexico_City",
    "iso:country":"MX",
    "name:spa_x_preferred":[
        "El Custodio"
    ],
    "name:und_x_variant":[
        "Custodio"
    ],
    "wof:name":"El Custodio",
    "wof:placetype":"locality"
},
  "geometry": {"coordinates":[-99.96955,22.65154],"type":"Point"}
}