{
  "type": "Feature",
  "properties": {
    "gn:admin1_code":"6.0",
    "gn:asciiname":"Jaboncillos",
    "gn:country_code":"MX",
    "gn:dem":1472,
    "gn:feature_class":"P",
    "gn:feature_code":"PPL",
    "gn:name":"Jaboncillos",
    "gn:population":0,
    "gn:timezone":"America/Monterrey",
    "iso:country":"MX",
    "wof:name":"Jaboncillos",
    "wof:placetype":"locality"
},
  "geometry": {"coordinates":[-102.65000000000001,28.95],"type":"Point"}
}