{
  "type": "Feature",
  "properties": {
    "gn:admin1_code":"10",
    "gn:admin2_code":"2",
    "gn:asciiname":"El Tepehuaje",
    "gn:country_code":"MX",
    "gn:dem":952,
    "gn:feature_class":"P",
    "gn:feature_code":"PPL",
    "gn:name":"El Tepehuaje",
    "gn:population":9,
    "gn:timezone":"America/Monterrey",
    "iso:country":"MX",
    "wof:name":"El Tepehuaje",
    "wof:placetype":"locality",
    "wof:population":9
},
  "geometry": {"coordinates":[-106.60147000000001,25.04303],"type":"Point"}
}