{
  "type": "Feature",
  "properties": {
    "gn:admin1_code":"30",
    "gn:admin2_code":"193",
    "gn:asciiname":"El Cortijo",
    "gn:country_code":"MX",
    "gn:dem":48,
    "gn:feature_class":"P",
    "gn:feature_code":"PPL",
    "gn:name":"El Cortijo",
    "gn:population":25,
    "gn:timezone":"America/Mexico_City",
    "iso:country":"MX",
    "wof:name":"El Cortijo",
    "wof:placetype":"locality",
    "wof:population":25
},
  "geometry": {"coordinates":[-96.22944,19.14889],"type":"Point"}
}