{
  "type": "Feature",
  "properties": {
    "gn:admin1_code":"6",
    "gn:admin2_code":"66.0",
    "gn:asciiname":"San Fernando",
    "gn:country_code":"MX",
    "gn:dem":879,
    "gn:feature_class":"P",
    "gn:feature_code":"PPL",
    "gn:name":"San Fernando",
    "gn:population":15,
    "gn:timezone":"America/Chihuahua",
    "iso:country":"MX",
    "name:spa_x_preferred":[
        "San Fernando"
    ],
    "wof:name":"San Fernando",
    "wof:placetype":"locality",
    "wof:population":15
},
  "geometry": {"coordinates":[-108.72244999999999,27.74213],"type":"Point"}
}