{
  "type": "Feature",
  "properties": {
    "gn:admin1_code":"8.0",
    "gn:admin2_code":"4.0",
    "gn:asciiname":"Los Gallos",
    "gn:country_code":"MX",
    "gn:dem":304,
    "gn:feature_class":"P",
    "gn:feature_code":"PPL",
    "gn:name":"Los Gallos",
    "gn:population":0,
    "gn:timezone":"America/Mexico_City",
    "iso:country":"MX",
    "name:spa_x_preferred":[
        "Los Gallos"
    ],
    "wof:name":"Los Gallos",
    "wof:placetype":"locality"
},
  "geometry": {"coordinates":[-103.79758,19.16011],"type":"Point"}
}