{
  "type": "Feature",
  "properties": {
    "gn:admin1_code":"30",
    "gn:asciiname":"Dona Mariana",
    "gn:country_code":"MX",
    "gn:dem":36,
    "gn:feature_class":"P",
    "gn:feature_code":"PPL",
    "gn:name":"Do\u00f1a Mariana",
    "gn:population":0,
    "gn:timezone":"America/Mexico_City",
    "iso:country":"MX",
    "wof:name":"Dona Mariana",
    "wof:placetype":"locality"
},
  "geometry": {"coordinates":[-94.96666999999999,17.31667],"type":"Point"}
}