{
  "type": "Feature",
  "properties": {
    "gn:admin1_code":"10",
    "gn:admin2_code":"14",
    "gn:asciiname":"Isquelta",
    "gn:country_code":"MX",
    "gn:dem":1120,
    "gn:feature_class":"P",
    "gn:feature_code":"PPL",
    "gn:name":"Isquelta",
    "gn:population":20,
    "gn:timezone":"America/Monterrey",
    "iso:country":"MX",
    "wof:name":"Isquelta",
    "wof:placetype":"locality",
    "wof:population":20
},
  "geometry": {"coordinates":[-104.43716999999999,22.6292],"type":"Point"}
}