{
  "type": "Feature",
  "properties": {
    "gn:admin1_code":"10",
    "gn:admin2_code":"23.0",
    "gn:asciiname":"Estacion Coyotes (Jose Maria Morelos)",
    "gn:country_code":"MX",
    "gn:dem":2466,
    "gn:feature_class":"P",
    "gn:feature_code":"PPL",
    "gn:name":"Estaci\u00f3n Coyotes (Jos\u00e9 Mar\u00eda Morelos)",
    "gn:population":668,
    "gn:timezone":"America/Monterrey",
    "iso:country":"MX",
    "name:und_x_variant":[
        "Estaci\u00f3n Coyotes (Jos\u00e9 Mar\u00eda Morelos)"
    ],
    "wof:name":"Estacion Coyotes (Jose Maria Morelos)",
    "wof:placetype":"locality",
    "wof:population":668
},
  "geometry": {"coordinates":[-105.315,23.86361],"type":"Point"}
}