{
  "type": "Feature",
  "properties": {
    "gn:admin1_code":"27",
    "gn:admin2_code":"1.0",
    "gn:asciiname":"El Ramonal",
    "gn:country_code":"MX",
    "gn:dem":48,
    "gn:feature_class":"P",
    "gn:feature_code":"PPL",
    "gn:name":"El Ramonal",
    "gn:population":0,
    "gn:timezone":"America/Mexico_City",
    "iso:country":"MX",
    "name:spa_x_preferred":[
        "Ramonal"
    ],
    "name:spa_x_variant":[
        "El Ramonal"
    ],
    "wof:name":"El Ramonal",
    "wof:placetype":"locality"
},
  "geometry": {"coordinates":[-91.02755000000001,17.68488],"type":"Point"}
}