{
  "type": "Feature",
  "properties": {
    "gn:admin1_code":"21",
    "gn:admin2_code":"19.0",
    "gn:asciiname":"Juan Uvera",
    "gn:country_code":"MX",
    "gn:dem":1752,
    "gn:feature_class":"P",
    "gn:feature_code":"PPL",
    "gn:name":"Juan Uvera",
    "gn:population":586,
    "gn:timezone":"America/Mexico_City",
    "iso:country":"MX",
    "wof:name":"Juan Uvera",
    "wof:placetype":"locality",
    "wof:population":586
},
  "geometry": {"coordinates":[-98.4225,18.86444],"type":"Point"}
}