{
  "type": "Feature",
  "properties": {
    "gn:admin1_code":"26",
    "gn:admin2_code":"42.0",
    "gn:asciiname":"La Esmeralda",
    "gn:country_code":"MX",
    "gn:dem":140,
    "gn:feature_class":"P",
    "gn:feature_code":"PPL",
    "gn:name":"La Esmeralda",
    "gn:population":0,
    "gn:timezone":"America/Hermosillo",
    "iso:country":"MX",
    "name:spa_x_preferred":[
        "La Esmeralda"
    ],
    "wof:name":"La Esmeralda",
    "wof:placetype":"locality"
},
  "geometry": {"coordinates":[-109.10626000000001,26.74456],"type":"Point"}
}