{
  "type": "Feature",
  "properties": {
    "gn:admin1_code":"26.0",
    "gn:admin2_code":"25.0",
    "gn:asciiname":"Dieciseis",
    "gn:country_code":"MX",
    "gn:dem":64,
    "gn:feature_class":"P",
    "gn:feature_code":"PPL",
    "gn:name":"Diecis\u00e9is",
    "gn:population":0,
    "gn:timezone":"America/Hermosillo",
    "iso:country":"MX",
    "name:spa_x_preferred":[
        "Diecis\u00e9is"
    ],
    "wof:name":"Dieciseis",
    "wof:placetype":"locality"
},
  "geometry": {"coordinates":[-110.64982000000001,28.12688],"type":"Point"}
}