{
  "type": "Feature",
  "properties": {
    "gn:admin1_code":"26",
    "gn:admin2_code":"21.0",
    "gn:asciiname":"Las Canoas",
    "gn:country_code":"MX",
    "gn:dem":327,
    "gn:feature_class":"P",
    "gn:feature_code":"PPL",
    "gn:name":"Las Canoas",
    "gn:population":2,
    "gn:timezone":"America/Hermosillo",
    "iso:country":"MX",
    "name:spa_x_preferred":[
        "Las Canoas"
    ],
    "wof:name":"Las Canoas",
    "wof:placetype":"locality",
    "wof:population":2
},
  "geometry": {"coordinates":[-110.33778999999998,28.63907],"type":"Point"}
}