{
  "type": "Feature",
  "properties": {
    "gn:admin1_code":"20",
    "gn:admin2_code":"548.0",
    "gn:asciiname":"El Izote",
    "gn:country_code":"MX",
    "gn:dem":2188,
    "gn:feature_class":"P",
    "gn:feature_code":"PPL",
    "gn:name":"El Izote",
    "gn:population":7,
    "gn:timezone":"America/Mexico_City",
    "iso:country":"MX",
    "wof:name":"El Izote",
    "wof:placetype":"locality",
    "wof:population":7
},
  "geometry": {"coordinates":[-97.36694,17.95417],"type":"Point"}
}