{
  "type": "Feature",
  "properties": {
    "gn:admin1_code":"13",
    "gn:admin2_code":"56",
    "gn:asciiname":"Santa Ana del Monte",
    "gn:country_code":"MX",
    "gn:dem":2349,
    "gn:feature_class":"P",
    "gn:feature_code":"PPL",
    "gn:name":"Santa Ana del Monte",
    "gn:population":10,
    "gn:timezone":"America/Mexico_City",
    "iso:country":"MX",
    "wof:name":"Santa Ana del Monte",
    "wof:placetype":"locality",
    "wof:population":10
},
  "geometry": {"coordinates":[-98.44712,20.06039],"type":"Point"}
}