{
  "type": "Feature",
  "properties": {
    "gn:admin1_code":"32",
    "gn:admin2_code":"38.0",
    "gn:asciiname":"El Rayo",
    "gn:country_code":"MX",
    "gn:dem":2152,
    "gn:feature_class":"P",
    "gn:feature_code":"PPL",
    "gn:name":"El Rayo",
    "gn:population":403,
    "gn:timezone":"America/Mexico_City",
    "iso:country":"MX",
    "wof:name":"El Rayo",
    "wof:placetype":"locality",
    "wof:population":403
},
  "geometry": {"coordinates":[-101.61056000000001,21.98139],"type":"Point"}
}