{
  "type": "Feature",
  "properties": {
    "gn:admin1_code":"13",
    "gn:admin2_code":"28.0",
    "gn:asciiname":"Coco Grande",
    "gn:country_code":"MX",
    "gn:dem":145,
    "gn:feature_class":"P",
    "gn:feature_code":"PPL",
    "gn:name":"Coco Grande",
    "gn:population":232,
    "gn:timezone":"America/Mexico_City",
    "iso:country":"MX",
    "wof:name":"Coco Grande",
    "wof:placetype":"locality",
    "wof:population":232
},
  "geometry": {"coordinates":[-98.42092,21.16133],"type":"Point"}
}