{
  "type": "Feature",
  "properties": {
    "gn:admin1_code":"11.0",
    "gn:admin2_code":"15.0",
    "gn:asciiname":"Cienega de Negros",
    "gn:country_code":"MX",
    "gn:dem":2665,
    "gn:feature_class":"P",
    "gn:feature_code":"PPL",
    "gn:name":"Ci\u00e9nega de Negros",
    "gn:population":101,
    "gn:timezone":"America/Mexico_City",
    "iso:country":"MX",
    "wof:name":"Cienega de Negros",
    "wof:placetype":"locality",
    "wof:population":101
},
  "geometry": {"coordinates":[-101.24944000000001,21.14694],"type":"Point"}
}