{
  "type": "Feature",
  "properties": {
    "gn:admin1_code":"14.0",
    "gn:admin2_code":"56.0",
    "gn:asciiname":"La Jabalina",
    "gn:country_code":"MX",
    "gn:dem":991,
    "gn:feature_class":"P",
    "gn:feature_code":"PPL",
    "gn:name":"La Jabalina",
    "gn:population":0,
    "gn:timezone":"America/Mexico_City",
    "iso:country":"MX",
    "name:spa_x_preferred":[
        "La Jabalina"
    ],
    "wof:name":"La Jabalina",
    "wof:placetype":"locality"
},
  "geometry": {"coordinates":[-102.91537,19.54684],"type":"Point"}
}