{
  "type": "Feature",
  "properties": {
    "gn:admin1_code":"16",
    "gn:admin2_code":"101.0",
    "gn:asciiname":"Paramo",
    "gn:country_code":"MX",
    "gn:dem":1910,
    "gn:feature_class":"P",
    "gn:feature_code":"PPL",
    "gn:name":"P\u00e1ramo",
    "gn:population":118,
    "gn:timezone":"America/Mexico_City",
    "iso:country":"MX",
    "name:und_x_variant":[
        "P\u00e1ramo"
    ],
    "wof:name":"Paramo",
    "wof:placetype":"locality",
    "wof:population":118
},
  "geometry": {"coordinates":[-101.10389000000001,19.55361],"type":"Point"}
}