{
  "type": "Feature",
  "properties": {
    "gn:admin1_code":"7",
    "gn:admin2_code":"24.0",
    "gn:asciiname":"Talia",
    "gn:country_code":"MX",
    "gn:dem":1091,
    "gn:feature_class":"P",
    "gn:feature_code":"PPL",
    "gn:name":"Tal\u00eda",
    "gn:population":0,
    "gn:timezone":"America/Monterrey",
    "iso:country":"MX",
    "name:spa_x_preferred":[
        "Tal\u00eda"
    ],
    "wof:name":"Talia",
    "wof:placetype":"locality"
},
  "geometry": {"coordinates":[-102.41457,25.73185],"type":"Point"}
}