{
  "type": "Feature",
  "properties": {
    "gn:admin1_code":"16",
    "gn:admin2_code":"19.0",
    "gn:asciiname":"San Pablo",
    "gn:country_code":"MX",
    "gn:dem":1608,
    "gn:feature_class":"P",
    "gn:feature_code":"PPL",
    "gn:name":"San Pablo",
    "gn:population":219,
    "gn:timezone":"America/Mexico_City",
    "iso:country":"MX",
    "wof:name":"San Pablo",
    "wof:placetype":"locality",
    "wof:population":219
},
  "geometry": {"coordinates":[-102.61278,19.81778],"type":"Point"}
}