{
  "type": "Feature",
  "properties": {
    "gn:admin1_code":"20",
    "gn:admin2_code":"162.0",
    "gn:asciiname":"Portillo el Guayabal",
    "gn:country_code":"MX",
    "gn:dem":1695,
    "gn:feature_class":"P",
    "gn:feature_code":"PPL",
    "gn:name":"Portillo el Guayabal",
    "gn:population":72,
    "gn:timezone":"America/Mexico_City",
    "iso:country":"MX",
    "wof:name":"Portillo el Guayabal",
    "wof:placetype":"locality",
    "wof:population":72
},
  "geometry": {"coordinates":[-96.58833,16.70139],"type":"Point"}
}