{
  "type": "Feature",
  "properties": {
    "gn:admin1_code":"31",
    "gn:admin2_code":"68.0",
    "gn:asciiname":"Kansacopo",
    "gn:country_code":"MX",
    "gn:dem":7,
    "gn:feature_class":"P",
    "gn:feature_code":"PPL",
    "gn:name":"Kansacopo",
    "gn:population":0,
    "gn:timezone":"America/Merida",
    "iso:country":"MX",
    "name:spa_x_preferred":[
        "Kansacopo"
    ],
    "name:spa_x_variant":[
        "Kansucop\u00f3"
    ],
    "wof:name":"Kansacopo",
    "wof:placetype":"locality"
},
  "geometry": {"coordinates":[-89.22066,21.19866],"type":"Point"}
}