{
  "type": "Feature",
  "properties": {
    "gn:admin1_code":"24",
    "gn:admin2_code":"37.0",
    "gn:asciiname":"La Reforma (El Lindero)",
    "gn:country_code":"MX",
    "gn:dem":827,
    "gn:feature_class":"P",
    "gn:feature_code":"PPL",
    "gn:name":"La Reforma (El Lindero)",
    "gn:population":210,
    "gn:timezone":"America/Mexico_City",
    "iso:country":"MX",
    "wof:name":"La Reforma (El Lindero)",
    "wof:placetype":"locality",
    "wof:population":210
},
  "geometry": {"coordinates":[-98.92,21.27917],"type":"Point"}
}