{
  "type": "Feature",
  "properties": {
    "gn:admin1_code":"24.0",
    "gn:admin2_code":"43.0",
    "gn:asciiname":"El Minero",
    "gn:cc2":"MX",
    "gn:country_code":"MX",
    "gn:dem":1998,
    "gn:feature_class":"P",
    "gn:feature_code":"PPL",
    "gn:name":"El Minero",
    "gn:population":31,
    "gn:timezone":"America/Mexico_City",
    "iso:country":"MX",
    "name:und_x_variant":[
        "Minero",
        "El Minero"
    ],
    "wof:name":"El Minero",
    "wof:placetype":"locality",
    "wof:population":31
},
  "geometry": {"coordinates":[-100.59999999999999,21.55222],"type":"Point"}
}