{
  "type": "Feature",
  "properties": {
    "gn:admin1_code":"16",
    "gn:admin2_code":"113",
    "gn:asciiname":"Colonia Jose J. Mugica",
    "gn:country_code":"MX",
    "gn:dem":1692,
    "gn:feature_class":"P",
    "gn:feature_code":"PPL",
    "gn:name":"Colonia Jos\u00e9 J. M\u00fagica",
    "gn:population":48,
    "gn:timezone":"America/Mexico_City",
    "iso:country":"MX",
    "name:und_x_variant":[
        "Colonia Jos\u00e9 J. M\u00fagica"
    ],
    "wof:name":"Colonia Jose J. Mugica",
    "wof:placetype":"locality",
    "wof:population":48
},
  "geometry": {"coordinates":[-101.59639,20.29639],"type":"Point"}
}