{
  "type": "Feature",
  "properties": {
    "gn:admin1_code":"14",
    "gn:admin2_code":"125.0",
    "gn:asciiname":"Ojo de Agua de Coyotes",
    "gn:country_code":"MX",
    "gn:dem":2059,
    "gn:feature_class":"P",
    "gn:feature_code":"PPL",
    "gn:name":"Ojo de Agua de Coyotes",
    "gn:population":0,
    "gn:timezone":"America/Mexico_City",
    "iso:country":"MX",
    "name:und_x_variant":[
        "Los Coyotes"
    ],
    "wof:name":"Ojo de Agua de Coyotes",
    "wof:placetype":"locality"
},
  "geometry": {"coordinates":[-102.44996999999999,20.73862],"type":"Point"}
}