{
  "type": "Feature",
  "properties": {
    "gn:admin1_code":"7",
    "gn:asciiname":"La Soledad de las Palmas",
    "gn:country_code":"MX",
    "gn:dem":1506,
    "gn:feature_class":"P",
    "gn:feature_code":"PPL",
    "gn:name":"La Soledad de las Palmas",
    "gn:population":0,
    "gn:timezone":"America/Chihuahua",
    "iso:country":"MX",
    "name:und_x_variant":[
        "Rancho Soledad de las Palmas",
        "La Soledad de las Palmas",
        "La Chole",
        "Rancho Soledad Las Palmas"
    ],
    "wof:name":"La Soledad de las Palmas",
    "wof:placetype":"locality"
},
  "geometry": {"coordinates":[-103.96720000000001,27.73131],"type":"Point"}
}