{
  "type": "Feature",
  "properties": {
    "gn:admin1_code":"18",
    "gn:admin2_code":"1.0",
    "gn:asciiname":"Las Lunas",
    "gn:country_code":"MX",
    "gn:dem":320,
    "gn:feature_class":"P",
    "gn:feature_code":"PPL",
    "gn:name":"Las Lunas",
    "gn:population":0,
    "gn:timezone":"America/Mazatlan",
    "iso:country":"MX",
    "name:spa_x_preferred":[
        "Las Lunas"
    ],
    "wof:name":"Las Lunas",
    "wof:placetype":"locality"
},
  "geometry": {"coordinates":[-105.03887,22.37916],"type":"Point"}
}