{
  "type": "Feature",
  "properties": {
    "gn:admin1_code":"15.0",
    "gn:admin2_code":"111.0",
    "gn:asciiname":"Las Dalias",
    "gn:country_code":"MX",
    "gn:dem":2903,
    "gn:feature_class":"P",
    "gn:feature_code":"PPL",
    "gn:name":"Las Dalias",
    "gn:population":0,
    "gn:timezone":"America/Mexico_City",
    "iso:country":"MX",
    "name:und_x_variant":[
        "San Miguel"
    ],
    "wof:name":"Las Dalias",
    "wof:placetype":"locality"
},
  "geometry": {"coordinates":[-100.1631,19.44232],"type":"Point"}
}