{
  "type": "Feature",
  "properties": {
    "gn:admin1_code":"5",
    "gn:admin2_code":"93.0",
    "gn:asciiname":"Sibanilja Pocolum",
    "gn:country_code":"MX",
    "gn:dem":1478,
    "gn:feature_class":"P",
    "gn:feature_code":"PPL",
    "gn:name":"Sibanilj\u00e1 Pocolum",
    "gn:population":1419,
    "gn:timezone":"America/Mexico_City",
    "iso:country":"MX",
    "name:und_x_variant":[
        "Sibanilj\u00e1 Pocolum"
    ],
    "wof:name":"Sibanilja Pocolum",
    "wof:placetype":"locality",
    "wof:population":1419
},
  "geometry": {"coordinates":[-92.46111000000001,16.87639],"type":"Point"}
}