{
  "type": "Feature",
  "properties": {
    "gn:admin1_code":"18.0",
    "gn:admin2_code":"1.0",
    "gn:asciiname":"La Guitarra",
    "gn:country_code":"MX",
    "gn:dem":808,
    "gn:feature_class":"P",
    "gn:feature_code":"PPL",
    "gn:name":"La Guitarra",
    "gn:population":0,
    "gn:timezone":"America/Mazatlan",
    "iso:country":"MX",
    "name:spa_x_preferred":[
        "La Guitarra"
    ],
    "wof:name":"La Guitarra",
    "wof:placetype":"locality"
},
  "geometry": {"coordinates":[-105.06856999999999,22.48225],"type":"Point"}
}