{
  "type": "Feature",
  "properties": {
    "gn:admin1_code":"27",
    "gn:admin2_code":"3.0",
    "gn:asciiname":"La Suiza Uno (San Martin)",
    "gn:country_code":"MX",
    "gn:dem":2,
    "gn:feature_class":"P",
    "gn:feature_code":"PPL",
    "gn:name":"La Suiza Uno (San Mart\u00edn)",
    "gn:population":6,
    "gn:timezone":"America/Mexico_City",
    "iso:country":"MX",
    "name:und_x_variant":[
        "La Suiza Uno (San Mart\u00edn)"
    ],
    "wof:name":"La Suiza Uno (San Martin)",
    "wof:placetype":"locality",
    "wof:population":6
},
  "geometry": {"coordinates":[-92.76778,18.42556],"type":"Point"}
}