{
  "type": "Feature",
  "properties": {
    "gn:admin1_code":"30",
    "gn:admin2_code":"15",
    "gn:asciiname":"Tulapa de Abajo",
    "gn:country_code":"MX",
    "gn:dem":18,
    "gn:feature_class":"P",
    "gn:feature_code":"PPL",
    "gn:name":"Tulapa de Abajo",
    "gn:population":18,
    "gn:timezone":"America/Mexico_City",
    "iso:country":"MX",
    "wof:name":"Tulapa de Abajo",
    "wof:placetype":"locality",
    "wof:population":18
},
  "geometry": {"coordinates":[-95.44389,18.62333],"type":"Point"}
}