{
  "type": "Feature",
  "properties": {
    "gn:admin1_code":"7",
    "gn:admin2_code":"20.0",
    "gn:asciiname":"La Cuchilla",
    "gn:country_code":"MX",
    "gn:dem":438,
    "gn:feature_class":"P",
    "gn:feature_code":"PPL",
    "gn:name":"La Cuchilla",
    "gn:population":0,
    "gn:timezone":"America/Monterrey",
    "iso:country":"MX",
    "name:und_x_variant":[
        "Cuchilla",
        "La Cuchilla",
        "Ejido la Cuchilla"
    ],
    "wof:name":"La Cuchilla",
    "wof:placetype":"locality"
},
  "geometry": {"coordinates":[-101.42323,27.87601],"type":"Point"}
}