{
  "type": "Feature",
  "properties": {
    "gn:admin1_code":"32.0",
    "gn:admin2_code":"51.0",
    "gn:asciiname":"El Borrego",
    "gn:country_code":"MX",
    "gn:dem":2014,
    "gn:feature_class":"P",
    "gn:feature_code":"PPL",
    "gn:name":"El Borrego",
    "gn:population":0,
    "gn:timezone":"America/Mexico_City",
    "iso:country":"MX",
    "name:spa_x_preferred":[
        "El Borrego"
    ],
    "wof:name":"El Borrego",
    "wof:placetype":"locality"
},
  "geometry": {"coordinates":[-102.30674999999999,23.67689],"type":"Point"}
}