{
  "type": "Feature",
  "properties": {
    "gn:admin1_code":"30",
    "gn:admin2_code":"40",
    "gn:asciiname":"Colonia Valle Dorado",
    "gn:country_code":"MX",
    "gn:dem":107,
    "gn:feature_class":"P",
    "gn:feature_code":"PPL",
    "gn:name":"Colonia Valle Dorado",
    "gn:population":14,
    "gn:timezone":"America/Mexico_City",
    "iso:country":"MX",
    "wof:name":"Colonia Valle Dorado",
    "wof:placetype":"locality",
    "wof:population":14
},
  "geometry": {"coordinates":[-97.44194,20.48056],"type":"Point"}
}