{
  "type": "Feature",
  "properties": {
    "gn:admin1_code":"14",
    "gn:admin2_code":"120.0",
    "gn:asciiname":"Puerta del Llano",
    "gn:country_code":"MX",
    "gn:dem":1604,
    "gn:feature_class":"P",
    "gn:feature_code":"PPL",
    "gn:name":"Puerta del Llano",
    "gn:population":1224,
    "gn:timezone":"America/Mexico_City",
    "iso:country":"MX",
    "wof:name":"Puerta del Llano",
    "wof:placetype":"locality",
    "wof:population":1224
},
  "geometry": {"coordinates":[-103.46138999999999,20.78528],"type":"Point"}
}