{
  "type": "Feature",
  "properties": {
    "gn:admin1_code":"4",
    "gn:admin2_code":"6.0",
    "gn:asciiname":"Nucuchich",
    "gn:country_code":"MX",
    "gn:dem":73,
    "gn:feature_class":"P",
    "gn:feature_code":"PPL",
    "gn:name":"Nucuchich",
    "gn:population":0,
    "gn:timezone":"America/Merida",
    "iso:country":"MX",
    "name:spa_x_preferred":[
        "Nucuchich"
    ],
    "wof:name":"Nucuchich",
    "wof:placetype":"locality"
},
  "geometry": {"coordinates":[-89.76505999999998,19.72441],"type":"Point"}
}