{
  "type": "Feature",
  "properties": {
    "gn:admin1_code":"26",
    "gn:admin2_code":"30",
    "gn:asciiname":"Casa Blanca",
    "gn:country_code":"MX",
    "gn:dem":323,
    "gn:feature_class":"P",
    "gn:feature_code":"PPL",
    "gn:name":"Casa Blanca",
    "gn:population":12,
    "gn:timezone":"America/Hermosillo",
    "iso:country":"MX",
    "wof:name":"Casa Blanca",
    "wof:placetype":"locality",
    "wof:population":12
},
  "geometry": {"coordinates":[-110.82056,29.35417],"type":"Point"}
}