{
  "type": "Feature",
  "properties": {
    "gn:admin1_code":"10.0",
    "gn:admin2_code":"9.0",
    "gn:asciiname":"La Cieneguita",
    "gn:country_code":"MX",
    "gn:dem":2551,
    "gn:feature_class":"P",
    "gn:feature_code":"PPL",
    "gn:name":"La Cieneguita",
    "gn:population":0,
    "gn:timezone":"America/Monterrey",
    "iso:country":"MX",
    "name:spa_x_preferred":[
        "La Cieneguita"
    ],
    "wof:name":"La Cieneguita",
    "wof:placetype":"locality"
},
  "geometry": {"coordinates":[-106.18510999999999,26.01592],"type":"Point"}
}