{
  "type": "Feature",
  "properties": {
    "gn:admin1_code":"11",
    "gn:admin2_code":"33.0",
    "gn:asciiname":"San Rafael de la Curva",
    "gn:country_code":"MX",
    "gn:dem":1987,
    "gn:feature_class":"P",
    "gn:feature_code":"PPL",
    "gn:name":"San Rafael de la Curva",
    "gn:population":168,
    "gn:timezone":"America/Mexico_City",
    "iso:country":"MX",
    "wof:name":"San Rafael de la Curva",
    "wof:placetype":"locality",
    "wof:population":168
},
  "geometry": {"coordinates":[-100.58889000000001,21.2975],"type":"Point"}
}