{
  "type": "Feature",
  "properties": {
    "gn:admin1_code":"6",
    "gn:admin2_code":"19.0",
    "gn:asciiname":"El Faro",
    "gn:country_code":"MX",
    "gn:dem":1547,
    "gn:feature_class":"P",
    "gn:feature_code":"PPL",
    "gn:name":"El Faro",
    "gn:population":0,
    "gn:timezone":"America/Chihuahua",
    "iso:country":"MX",
    "name:und_x_variant":[
        "Ejido el Faro",
        "El Faro"
    ],
    "wof:name":"El Faro",
    "wof:placetype":"locality"
},
  "geometry": {"coordinates":[-106.35465000000001,29.36818],"type":"Point"}
}