{
  "type": "Feature",
  "properties": {
    "gn:admin1_code":"10",
    "gn:admin2_code":"5.0",
    "gn:asciiname":"Andres Soto",
    "gn:country_code":"MX",
    "gn:dem":1875,
    "gn:feature_class":"P",
    "gn:feature_code":"PPL",
    "gn:name":"Andr\u00e9s Soto",
    "gn:population":8,
    "gn:timezone":"America/Monterrey",
    "iso:country":"MX",
    "name:und_x_variant":[
        "Andr\u00e9s Soto"
    ],
    "wof:name":"Andres Soto",
    "wof:placetype":"locality",
    "wof:population":8
},
  "geometry": {"coordinates":[-104.54222,23.94611],"type":"Point"}
}