{
  "type": "Feature",
  "properties": {
    "gn:admin1_code":"27",
    "gn:admin2_code":"8.0",
    "gn:asciiname":"Guiral y Gonzalez Segunda Seccion",
    "gn:country_code":"MX",
    "gn:dem":35,
    "gn:feature_class":"P",
    "gn:feature_code":"PPL",
    "gn:name":"G\u00fciral y Gonz\u00e1lez Segunda Secci\u00f3n",
    "gn:population":0,
    "gn:timezone":"America/Mexico_City",
    "iso:country":"MX",
    "name:spa_x_preferred":[
        "Guiral y Gonzalez Segunda Secci\u00f3n"
    ],
    "name:spa_x_variant":[
        "G\u00fciral y Gonz\u00e1lez Segunda Secci\u00f3n",
        "G\u00fciral y Gonz\u00e1lez",
        "Segunda Secci\u00f3n"
    ],
    "wof:name":"Guiral y Gonzalez Segunda Seccion",
    "wof:placetype":"locality"
},
  "geometry": {"coordinates":[-93.41842,17.92555],"type":"Point"}
}