{
  "type": "Feature",
  "properties": {
    "gn:admin1_code":"11.0",
    "gn:admin2_code":"30.0",
    "gn:asciiname":"Santa Maria Uno",
    "gn:country_code":"MX",
    "gn:dem":1911,
    "gn:feature_class":"P",
    "gn:feature_code":"PPL",
    "gn:name":"Santa Mar\u00eda Uno",
    "gn:population":0,
    "gn:timezone":"America/Mexico_City",
    "iso:country":"MX",
    "name:spa_x_preferred":[
        "Santa Mar\u00eda Uno"
    ],
    "wof:name":"Santa Maria Uno",
    "wof:placetype":"locality"
},
  "geometry": {"coordinates":[-101.07799,21.53391],"type":"Point"}
}