{
  "type": "Feature",
  "properties": {
    "gn:admin1_code":"2.0",
    "gn:admin2_code":"3.0",
    "gn:asciiname":"El Risco",
    "gn:country_code":"MX",
    "gn:dem":600,
    "gn:feature_class":"P",
    "gn:feature_code":"PPL",
    "gn:name":"El Risco",
    "gn:population":0,
    "gn:timezone":"America/Tijuana",
    "iso:country":"MX",
    "name:spa_x_preferred":[
        "El Risco"
    ],
    "wof:name":"El Risco",
    "wof:placetype":"locality"
},
  "geometry": {"coordinates":[-116.64046999999999,32.54517],"type":"Point"}
}