{
  "type": "Feature",
  "properties": {
    "gn:admin1_code":"32",
    "gn:admin2_code":"55.0",
    "gn:asciiname":"Saucillo",
    "gn:country_code":"MX",
    "gn:dem":2235,
    "gn:feature_class":"P",
    "gn:feature_code":"PPL",
    "gn:name":"Saucillo",
    "gn:population":1,
    "gn:timezone":"America/Mexico_City",
    "iso:country":"MX",
    "wof:name":"Saucillo",
    "wof:placetype":"locality",
    "wof:population":1
},
  "geometry": {"coordinates":[-102.76721999999999,22.40806],"type":"Point"}
}