{
  "type": "Feature",
  "properties": {
    "gn:admin1_code":"11",
    "gn:admin2_code":"23.0",
    "gn:asciiname":"El Huizache",
    "gn:country_code":"MX",
    "gn:dem":1734,
    "gn:feature_class":"P",
    "gn:feature_code":"PPL",
    "gn:name":"El Huizache",
    "gn:population":170,
    "gn:timezone":"America/Mexico_City",
    "iso:country":"MX",
    "wof:name":"El Huizache",
    "wof:placetype":"locality",
    "wof:population":170
},
  "geometry": {"coordinates":[-101.73444000000001,20.34944],"type":"Point"}
}