{
  "type": "Feature",
  "properties": {
    "gn:admin1_code":"16.0",
    "gn:admin2_code":"14.0",
    "gn:asciiname":"Achotan",
    "gn:country_code":"MX",
    "gn:dem":120,
    "gn:feature_class":"P",
    "gn:feature_code":"PPL",
    "gn:name":"Achot\u00e1n",
    "gn:population":169,
    "gn:timezone":"America/Mexico_City",
    "iso:country":"MX",
    "name:und_x_variant":[
        "Achotl\u00e1n",
        "Achot\u00e1n"
    ],
    "wof:name":"Achotan",
    "wof:placetype":"locality",
    "wof:population":169
},
  "geometry": {"coordinates":[-103.59393,18.7477],"type":"Point"}
}