{
  "type": "Feature",
  "properties": {
    "gn:admin1_code":"12",
    "gn:admin2_code":"54",
    "gn:asciiname":"El Temaxcal",
    "gn:country_code":"MX",
    "gn:dem":1782,
    "gn:feature_class":"P",
    "gn:feature_code":"PPL",
    "gn:name":"El Temaxcal",
    "gn:population":21,
    "gn:timezone":"America/Mexico_City",
    "iso:country":"MX",
    "wof:name":"El Temaxcal",
    "wof:placetype":"locality",
    "wof:population":21
},
  "geometry": {"coordinates":[-100.30858000000001,17.98616],"type":"Point"}
}