{
  "type": "Feature",
  "properties": {
    "gn:admin1_code":"6",
    "gn:admin2_code":"29.0",
    "gn:asciiname":"Basonopita de Abajo",
    "gn:country_code":"MX",
    "gn:dem":758,
    "gn:feature_class":"P",
    "gn:feature_code":"PPL",
    "gn:name":"Basonopita de Abajo",
    "gn:population":116,
    "gn:timezone":"America/Chihuahua",
    "iso:country":"MX",
    "wof:name":"Basonopita de Abajo",
    "wof:placetype":"locality",
    "wof:population":116
},
  "geometry": {"coordinates":[-107.25708,26.04523],"type":"Point"}
}