{
  "type": "Feature",
  "properties": {
    "gn:admin1_code":"20",
    "gn:admin2_code":"73.0",
    "gn:asciiname":"Llano de San Vicente",
    "gn:country_code":"MX",
    "gn:dem":1067,
    "gn:feature_class":"P",
    "gn:feature_code":"PPL",
    "gn:name":"Llano de San Vicente",
    "gn:population":0,
    "gn:timezone":"America/Mexico_City",
    "iso:country":"MX",
    "name:und_x_variant":[
        "San Vicente"
    ],
    "wof:name":"Llano de San Vicente",
    "wof:placetype":"locality"
},
  "geometry": {"coordinates":[-97.86431,17.08604],"type":"Point"}
}