{
  "type": "Feature",
  "properties": {
    "gn:admin1_code":"19",
    "gn:admin2_code":"48.0",
    "gn:asciiname":"Aqua Blanca",
    "gn:country_code":"MX",
    "gn:dem":1828,
    "gn:feature_class":"P",
    "gn:feature_code":"PPL",
    "gn:name":"Aqua Blanca",
    "gn:population":0,
    "gn:timezone":"America/Monterrey",
    "iso:country":"MX",
    "name:spa_x_preferred":[
        "Aqua Blanca"
    ],
    "name:und_x_variant":[
        "Rancho Agua Blanca"
    ],
    "wof:name":"Aqua Blanca",
    "wof:placetype":"locality"
},
  "geometry": {"coordinates":[-100.50663,25.53278],"type":"Point"}
}