{
  "type": "Feature",
  "properties": {
    "gn:admin1_code":"27",
    "gn:admin2_code":"16.0",
    "gn:asciiname":"Mariano Pedrero 1ra. Seccion (La Providencia)",
    "gn:country_code":"MX",
    "gn:dem":17,
    "gn:feature_class":"P",
    "gn:feature_code":"PPL",
    "gn:name":"Mariano Pedrero 1ra. Secci\u00f3n (La Providencia)",
    "gn:population":381,
    "gn:timezone":"America/Mexico_City",
    "iso:country":"MX",
    "name:und_x_variant":[
        "Mariano Pedrero 1ra. Secci\u00f3n (La Providencia)"
    ],
    "wof:name":"Mariano Pedrero 1ra. Seccion (La Providencia)",
    "wof:placetype":"locality",
    "wof:population":381
},
  "geometry": {"coordinates":[-92.94167,17.67806000000001],"type":"Point"}
}