{
  "type": "Feature",
  "properties": {
    "gn:admin1_code":"30",
    "gn:admin2_code":"104.0",
    "gn:asciiname":"La Mina (Guillermo Castro Cervantes)",
    "gn:country_code":"MX",
    "gn:dem":50,
    "gn:feature_class":"P",
    "gn:feature_code":"PPL",
    "gn:name":"La Mina (Guillermo Castro Cervantes)",
    "gn:population":7,
    "gn:timezone":"America/Mexico_City",
    "iso:country":"MX",
    "wof:name":"La Mina (Guillermo Castro Cervantes)",
    "wof:placetype":"locality",
    "wof:population":7
},
  "geometry": {"coordinates":[-94.85333,18.5025],"type":"Point"}
}