{
  "type": "Feature",
  "properties": {
    "gn:admin1_code":"2",
    "gn:admin2_code":"2.0",
    "gn:asciiname":"Linch",
    "gn:cc2":"MX",
    "gn:country_code":"MX",
    "gn:dem":28,
    "gn:feature_class":"P",
    "gn:feature_code":"PPL",
    "gn:name":"Linch",
    "gn:population":0,
    "gn:timezone":"America/Tijuana",
    "iso:country":"MX",
    "name:ceb_x_preferred":[
        "Linch"
    ],
    "name:nld_x_preferred":[
        "Linch"
    ],
    "name:pol_x_preferred":[
        "Linch"
    ],
    "name:swe_x_preferred":[
        "Linch"
    ],
    "name:und_x_variant":[
        "Rancho Linch",
        "Linch"
    ],
    "wof:name":"Linch",
    "wof:placetype":"locality"
},
  "geometry": {"coordinates":[-114.83360999999999,32.62944],"type":"Point"}
}