{
  "type": "Feature",
  "properties": {
    "gn:admin1_code":"5",
    "gn:admin2_code":"116.0",
    "gn:asciiname":"Tlaltizapan",
    "gn:country_code":"MX",
    "gn:dem":146,
    "gn:feature_class":"P",
    "gn:feature_code":"PPL",
    "gn:name":"Tlaltizap\u00e1n",
    "gn:population":0,
    "gn:timezone":"America/Mexico_City",
    "iso:country":"MX",
    "wof:name":"Tlaltizapan",
    "wof:placetype":"locality"
},
  "geometry": {"coordinates":[-90.86667,16.28333],"type":"Point"}
}