{
  "type": "Feature",
  "properties": {
    "gn:admin1_code":"30",
    "gn:admin2_code":"148",
    "gn:asciiname":"Paso de Cabra",
    "gn:country_code":"MX",
    "gn:dem":86,
    "gn:feature_class":"P",
    "gn:feature_code":"PPL",
    "gn:name":"Paso de Cabra",
    "gn:population":12,
    "gn:timezone":"America/Mexico_City",
    "iso:country":"MX",
    "wof:name":"Paso de Cabra",
    "wof:placetype":"locality",
    "wof:population":12
},
  "geometry": {"coordinates":[-96.38583,18.99722],"type":"Point"}
}