{
  "type": "Feature",
  "properties": {
    "gn:admin1_code":"12.0",
    "gn:admin2_code":"48.0",
    "gn:asciiname":"El Remanse",
    "gn:country_code":"MX",
    "gn:dem":129,
    "gn:feature_class":"P",
    "gn:feature_code":"PPL",
    "gn:name":"El Remanse",
    "gn:population":0,
    "gn:timezone":"America/Mexico_City",
    "iso:country":"MX",
    "name:spa_x_preferred":[
        "El Remanse"
    ],
    "wof:name":"El Remanse",
    "wof:placetype":"locality"
},
  "geometry": {"coordinates":[-101.30962,17.69369],"type":"Point"}
}