{
  "type": "Feature",
  "properties": {
    "gn:admin1_code":"25",
    "gn:admin2_code":"16.0",
    "gn:asciiname":"El Frijolar",
    "gn:country_code":"MX",
    "gn:dem":384,
    "gn:feature_class":"P",
    "gn:feature_code":"PPL",
    "gn:name":"El Frijolar",
    "gn:population":0,
    "gn:timezone":"America/Mazatlan",
    "iso:country":"MX",
    "name:spa_x_preferred":[
        "El Frijolar"
    ],
    "wof:name":"El Frijolar",
    "wof:placetype":"locality"
},
  "geometry": {"coordinates":[-106.07259999999999,24.03992],"type":"Point"}
}