{
  "type": "Feature",
  "properties": {
    "gn:admin1_code":"5",
    "gn:admin2_code":"81",
    "gn:asciiname":"Candelaria",
    "gn:country_code":"MX",
    "gn:dem":831,
    "gn:feature_class":"P",
    "gn:feature_code":"PPL",
    "gn:name":"Candelaria",
    "gn:population":33,
    "gn:timezone":"America/Mexico_City",
    "iso:country":"MX",
    "wof:name":"Candelaria",
    "wof:placetype":"locality",
    "wof:population":33
},
  "geometry": {"coordinates":[-92.76833000000001,17.19833],"type":"Point"}
}