{
  "type": "Feature",
  "properties": {
    "iso:country":"MX",
    "name:spa_x_preferred":[
        "Chalco Centro"
    ],
    "qs:gn_adm0_cc":"MX",
    "qs:gn_local":3531200,
    "qs:gn_nam_loc":"Chalco, Chalco de D\u00edaz Covarrubias, Mexico, MX",
    "qs:gn_namadm1":"15",
    "qs:local_max":28,
    "qs:local_sum":28,
    "qs:localhoods":1,
    "qs:name":"Chalco Centro",
    "qs:name_adm0":"M\u00e9xico",
    "qs:name_adm1":"Mexico",
    "qs:name_adm2":"Chalco",
    "qs:name_local":"Chalco de D\u00edaz Covarrubias",
    "qs:photo_max":27,
    "qs:photo_sum":28,
    "qs:placetype":"Suburb",
    "qs:quad_count":2,
    "qs:woe_adm0":23424900,
    "qs:woe_adm1":2346278,
    "qs:woe_adm2":12600337,
    "qs:woe_lau":0,
    "qs:woe_local":115566,
    "qs:woe_ver":"7.10.0",
    "wof:lang":[
        "spa"
    ],
    "wof:name":"Chalco Centro",
    "wof:placetype":"neighbourhood"
},
  "geometry": {"coordinates":[-98.896376,19.261886],"type":"Point"}
}