{
  "type": "Feature",
  "properties": {
    "gn:admin1_code":"21",
    "gn:admin2_code":"75.0",
    "gn:asciiname":"Paso Real",
    "gn:country_code":"MX",
    "gn:dem":541,
    "gn:feature_class":"P",
    "gn:feature_code":"PPL",
    "gn:name":"Paso Real",
    "gn:population":163,
    "gn:timezone":"America/Mexico_City",
    "iso:country":"MX",
    "wof:name":"Paso Real",
    "wof:placetype":"locality",
    "wof:population":163
},
  "geometry": {"coordinates":[-97.38361,19.98417],"type":"Point"}
}