{
  "type": "Feature",
  "properties": {
    "gn:admin1_code":"15.0",
    "gn:asciiname":"Nezahualcoyotl-Ixtapan",
    "gn:country_code":"MX",
    "gn:dem":2244,
    "gn:feature_class":"P",
    "gn:feature_code":"PPL",
    "gn:name":"Nezahualcoyotl-Ixtapan",
    "gn:population":0,
    "gn:timezone":"America/Mexico_City",
    "iso:country":"MX",
    "name:spa_x_preferred":[
        "Nezahualcoyotl-Ixtapan"
    ],
    "name:spa_x_variant":[
        "Colonia Nezahualcoyotl"
    ],
    "wof:name":"Nezahualcoyotl-Ixtapan",
    "wof:placetype":"locality"
},
  "geometry": {"coordinates":[-98.94522000000001,19.58125],"type":"Point"}
}