{
  "type": "Feature",
  "properties": {
    "gn:admin1_code":"12",
    "gn:admin2_code":"28.0",
    "gn:asciiname":"Tetitlan de la Lima",
    "gn:country_code":"MX",
    "gn:dem":1766,
    "gn:feature_class":"P",
    "gn:feature_code":"PPL",
    "gn:name":"Tetitl\u00e1n de la Lima",
    "gn:population":105,
    "gn:timezone":"America/Mexico_City",
    "iso:country":"MX",
    "name:und_x_variant":[
        "Tetitl\u00e1n de la Lima"
    ],
    "wof:name":"Tetitlan de la Lima",
    "wof:placetype":"locality",
    "wof:population":105
},
  "geometry": {"coordinates":[-99.24448,17.62255],"type":"Point"}
}