{
  "type": "Feature",
  "properties": {
    "gn:admin1_code":"6.0",
    "gn:admin2_code":"67.0",
    "gn:asciiname":"La Laborcita",
    "gn:country_code":"MX",
    "gn:dem":1407,
    "gn:feature_class":"P",
    "gn:feature_code":"PPL",
    "gn:name":"La Laborcita",
    "gn:population":0,
    "gn:timezone":"America/Chihuahua",
    "iso:country":"MX",
    "name:und_x_variant":[
        "Rancho La Laborcita",
        "Laborcita",
        "La Laborcita"
    ],
    "wof:name":"La Laborcita",
    "wof:placetype":"locality"
},
  "geometry": {"coordinates":[-105.88576,27.52841],"type":"Point"}
}