{
  "type": "Feature",
  "properties": {
    "gn:admin1_code":"7",
    "gn:admin2_code":"9.0",
    "gn:asciiname":"Villa Verde",
    "gn:country_code":"MX",
    "gn:dem":1103,
    "gn:feature_class":"P",
    "gn:feature_code":"PPL",
    "gn:name":"Villa Verde",
    "gn:population":0,
    "gn:timezone":"America/Monterrey",
    "iso:country":"MX",
    "name:spa_x_preferred":[
        "Villa Verde"
    ],
    "wof:name":"Villa Verde",
    "wof:placetype":"locality"
},
  "geometry": {"coordinates":[-103.33927,25.91106],"type":"Point"}
}