{
  "type": "Feature",
  "properties": {
    "gn:admin1_code":"31",
    "gn:admin2_code":"4.0",
    "gn:asciiname":"Chen Paloma",
    "gn:country_code":"MX",
    "gn:dem":8,
    "gn:feature_class":"P",
    "gn:feature_code":"PPL",
    "gn:name":"Chen Paloma",
    "gn:population":0,
    "gn:timezone":"America/Merida",
    "iso:country":"MX",
    "name:spa_x_preferred":[
        "Chen Paloma"
    ],
    "wof:name":"Chen Paloma",
    "wof:placetype":"locality"
},
  "geometry": {"coordinates":[-89.42503000000001,21.17661],"type":"Point"}
}