{
  "type": "Feature",
  "properties": {
    "gn:admin1_code":"32",
    "gn:admin2_code":"49.0",
    "gn:asciiname":"Fresnillo",
    "gn:country_code":"MX",
    "gn:dem":1611,
    "gn:feature_class":"P",
    "gn:feature_code":"PPL",
    "gn:name":"Fresnillo",
    "gn:population":0,
    "gn:timezone":"America/Mexico_City",
    "iso:country":"MX",
    "name:spa_x_preferred":[
        "Fresnillo"
    ],
    "wof:name":"Fresnillo",
    "wof:placetype":"locality"
},
  "geometry": {"coordinates":[-104.07091,22.83438],"type":"Point"}
}