{
  "type": "Feature",
  "properties": {
    "gn:admin1_code":"5",
    "gn:admin2_code":"42.0",
    "gn:asciiname":"El Mirador",
    "gn:country_code":"MX",
    "gn:dem":1502,
    "gn:feature_class":"P",
    "gn:feature_code":"PPL",
    "gn:name":"El Mirador",
    "gn:population":122,
    "gn:timezone":"America/Mexico_City",
    "iso:country":"MX",
    "wof:name":"El Mirador",
    "wof:placetype":"locality",
    "wof:population":122
},
  "geometry": {"coordinates":[-93.035,17.31833],"type":"Point"}
}