{
  "type": "Feature",
  "properties": {
    "gn:admin1_code":"30",
    "gn:admin2_code":"211.0",
    "gn:asciiname":"Nuevo Faisan",
    "gn:country_code":"MX",
    "gn:dem":56,
    "gn:feature_class":"P",
    "gn:feature_code":"PPL",
    "gn:name":"Nuevo Fais\u00e1n",
    "gn:population":289,
    "gn:timezone":"America/Mexico_City",
    "iso:country":"MX",
    "name:und_x_variant":[
        "Nuevo Fais\u00e1n"
    ],
    "wof:name":"Nuevo Faisan",
    "wof:placetype":"locality",
    "wof:population":289
},
  "geometry": {"coordinates":[-96.99417,20.18333],"type":"Point"}
}