{
  "type": "Feature",
  "properties": {
    "gn:admin1_code":"11",
    "gn:admin2_code":"12.0",
    "gn:asciiname":"Colonia San Miguel",
    "gn:country_code":"MX",
    "gn:dem":1710,
    "gn:feature_class":"P",
    "gn:feature_code":"PPL",
    "gn:name":"Colonia San Miguel",
    "gn:population":356,
    "gn:timezone":"America/Mexico_City",
    "iso:country":"MX",
    "wof:name":"Colonia San Miguel",
    "wof:placetype":"locality",
    "wof:population":356
},
  "geometry": {"coordinates":[-101.65333,20.61028],"type":"Point"}
}