{
  "type": "Feature",
  "properties": {
    "gn:admin1_code":"5",
    "gn:admin2_code":"81.0",
    "gn:asciiname":"Revolucion Cardenista",
    "gn:country_code":"MX",
    "gn:dem":759,
    "gn:feature_class":"P",
    "gn:feature_code":"PPL",
    "gn:name":"Revoluci\u00f3n Cardenista",
    "gn:population":90,
    "gn:timezone":"America/Mexico_City",
    "iso:country":"MX",
    "name:und_x_variant":[
        "Revoluci\u00f3n Cardenista"
    ],
    "wof:name":"Revolucion Cardenista",
    "wof:placetype":"locality",
    "wof:population":90
},
  "geometry": {"coordinates":[-92.76972000000001,17.19389],"type":"Point"}
}