{
  "type": "Feature",
  "properties": {
    "gn:admin1_code":"4.0",
    "gn:asciiname":"Luis Donaldo Colosio",
    "gn:country_code":"MX",
    "gn:dem":229,
    "gn:feature_class":"P",
    "gn:feature_code":"PPL",
    "gn:name":"Luis Donaldo Colosio",
    "gn:population":0,
    "gn:timezone":"America/Cancun",
    "iso:country":"MX",
    "name:ara_x_preferred":[
        "\u0644\u0648\u064a\u0633 \u062f\u0648\u0646\u0627\u0644\u062f\u0648 \u0643\u0648\u0644\u0648\u0633\u064a\u0648"
    ],
    "name:dan_x_preferred":[
        "Luis Donaldo Colosio"
    ],
    "name:deu_x_preferred":[
        "Luis Donaldo Colosio"
    ],
    "name:fas_x_preferred":[
        "\u0644\u0648\u0626\u06cc\u0633 \u062f\u0648\u0646\u0627\u0644\u062f\u0648 \u06a9\u0648\u0644\u0648\u0633\u06cc\u0648"
    ],
    "name:fra_x_preferred":[
        "Luis Donaldo Colosio"
    ],
    "name:ind_x_preferred":[
        "Luis Donaldo Colosio"
    ],
    "name:jpn_x_preferred":[
        "\u30eb\u30a4\u30b9\u30fb\u30c9\u30ca\u30eb\u30c9\u30fb\u30b3\u30ed\u30b7\u30aa"
    ],
    "name:nah_x_preferred":[
        "Luis Donaldo Colosio"
    ],
    "name:nld_x_preferred":[
        "Luis Donaldo Colosio"
    ],
    "name:nor_x_preferred":[
        "Luis Donaldo Colosio"
    ],
    "name:pol_x_preferred":[
        "Luis Colosio"
    ],
    "name:por_x_preferred":[
        "Luis Donaldo Colosio"
    ],
    "name:rus_x_preferred":[
        "\u041a\u043e\u043b\u043e\u0441\u0438\u043e"
    ],
    "name:spa_x_preferred":[
        "Luis Donaldo Colosio"
    ],
    "name:srp_x_preferred":[
        "\u041b\u0443\u0438\u0441 \u0414\u043e\u043d\u0430\u043b\u0434\u043e \u041a\u043e\u043b\u043e\u0441\u0438\u043e"
    ],
    "wof:name":"Luis Donaldo Colosio",
    "wof:placetype":"locality"
},
  "geometry": {"coordinates":[-89.35826,18.49498],"type":"Point"}
}