{
  "type": "Feature",
  "properties": {
    "gn:admin1_code":"21",
    "gn:admin2_code":"76.0",
    "gn:asciiname":"Altamira",
    "gn:country_code":"MX",
    "gn:dem":429,
    "gn:feature_class":"P",
    "gn:feature_code":"PPL",
    "gn:name":"Altamira",
    "gn:population":0,
    "gn:timezone":"America/Mexico_City",
    "iso:country":"MX",
    "name:spa_x_preferred":[
        "Altamira"
    ],
    "wof:name":"Altamira",
    "wof:placetype":"locality"
},
  "geometry": {"coordinates":[-97.36472999999999,20.08048],"type":"Point"}
}