{
  "type": "Feature",
  "properties": {
    "gn:admin1_code":"6.0",
    "gn:admin2_code":"65.0",
    "gn:asciiname":"Charabuchi",
    "gn:country_code":"MX",
    "gn:dem":1568,
    "gn:feature_class":"P",
    "gn:feature_code":"PPL",
    "gn:name":"Charabuchi",
    "gn:population":0,
    "gn:timezone":"America/Chihuahua",
    "iso:country":"MX",
    "name:spa_x_preferred":[
        "Charabuchi"
    ],
    "wof:name":"Charabuchi",
    "wof:placetype":"locality"
},
  "geometry": {"coordinates":[-107.85701,27.41994],"type":"Point"}
}