{
  "type": "Feature",
  "properties": {
    "gn:admin1_code":"6",
    "gn:admin2_code":"65",
    "gn:asciiname":"El Fresno",
    "gn:country_code":"MX",
    "gn:dem":2170,
    "gn:feature_class":"P",
    "gn:feature_code":"PPL",
    "gn:name":"El Fresno",
    "gn:population":10,
    "gn:timezone":"America/Chihuahua",
    "iso:country":"MX",
    "wof:name":"El Fresno",
    "wof:placetype":"locality",
    "wof:population":10
},
  "geometry": {"coordinates":[-107.88603000000001,27.33465],"type":"Point"}
}