{
  "type": "Feature",
  "properties": {
    "gn:admin1_code":"32.0",
    "gn:admin2_code":"56.0",
    "gn:asciiname":"El Pachon",
    "gn:country_code":"MX",
    "gn:dem":2356,
    "gn:feature_class":"P",
    "gn:feature_code":"PPL",
    "gn:name":"El Pach\u00f3n",
    "gn:population":0,
    "gn:timezone":"America/Mexico_City",
    "iso:country":"MX",
    "name:spa_x_preferred":[
        "El Pach\u00f3n"
    ],
    "wof:name":"El Pachon",
    "wof:placetype":"locality"
},
  "geometry": {"coordinates":[-102.61399,22.7465],"type":"Point"}
}