{
  "type": "Feature",
  "properties": {
    "gn:admin1_code":"9",
    "gn:admin2_code":"12",
    "gn:asciiname":"La Trinidad",
    "gn:country_code":"MX",
    "gn:dem":3054,
    "gn:feature_class":"P",
    "gn:feature_code":"PPL",
    "gn:name":"La Trinidad",
    "gn:population":10,
    "gn:timezone":"America/Mexico_City",
    "iso:country":"MX",
    "wof:name":"La Trinidad",
    "wof:placetype":"locality",
    "wof:population":10
},
  "geometry": {"coordinates":[-99.22,19.21],"type":"Point"}
}