{
  "type": "Feature",
  "properties": {
    "gn:admin1_code":"32",
    "gn:admin2_code":"38.0",
    "gn:asciiname":"La Chiquilla",
    "gn:country_code":"MX",
    "gn:dem":2123,
    "gn:feature_class":"P",
    "gn:feature_code":"PPL",
    "gn:name":"La Chiquilla",
    "gn:population":0,
    "gn:timezone":"America/Mexico_City",
    "iso:country":"MX",
    "wof:name":"La Chiquilla",
    "wof:placetype":"locality"
},
  "geometry": {"coordinates":[-101.39737,22.15821],"type":"Point"}
}