{
  "type": "Feature",
  "properties": {
    "gn:admin1_code":"7",
    "gn:admin2_code":"28.0",
    "gn:asciiname":"Rancho El Barbon",
    "gn:country_code":"MX",
    "gn:dem":350,
    "gn:feature_class":"P",
    "gn:feature_code":"PPL",
    "gn:name":"Rancho El Barbon",
    "gn:population":0,
    "gn:timezone":"America/Monterrey",
    "iso:country":"MX",
    "wof:name":"Rancho El Barbon",
    "wof:placetype":"locality"
},
  "geometry": {"coordinates":[-101.08333,27.86667000000001],"type":"Point"}
}