{
  "type": "Feature",
  "properties": {
    "gn:admin1_code":"5",
    "gn:admin2_code":"12.0",
    "gn:asciiname":"Tierra y Libertad",
    "gn:country_code":"MX",
    "gn:dem":1051,
    "gn:feature_class":"P",
    "gn:feature_code":"PPL",
    "gn:name":"Tierra y Libertad",
    "gn:population":496,
    "gn:timezone":"America/Mexico_City",
    "iso:country":"MX",
    "wof:name":"Tierra y Libertad",
    "wof:placetype":"locality",
    "wof:population":496
},
  "geometry": {"coordinates":[-93.32333,16.8375],"type":"Point"}
}