{
  "type": "Feature",
  "properties": {
    "gn:admin1_code":"20",
    "gn:admin2_code":"469.0",
    "gn:asciiname":"San Miguel de Cardenas",
    "gn:country_code":"MX",
    "gn:dem":1748,
    "gn:feature_class":"P",
    "gn:feature_code":"PPL",
    "gn:name":"San Miguel de C\u00e1rdenas",
    "gn:population":112,
    "gn:timezone":"America/Mexico_City",
    "iso:country":"MX",
    "name:und_x_variant":[
        "San Miguel de C\u00e1rdenas"
    ],
    "wof:name":"San Miguel de Cardenas",
    "wof:placetype":"locality",
    "wof:population":112
},
  "geometry": {"coordinates":[-98.00360999999999,17.25222],"type":"Point"}
}