{
  "type": "Feature",
  "properties": {
    "gn:admin1_code":"13",
    "gn:admin2_code":"8.0",
    "gn:asciiname":"Zacatepec",
    "gn:country_code":"MX",
    "gn:dem":2529,
    "gn:feature_class":"P",
    "gn:feature_code":"PPL",
    "gn:name":"Zacatepec",
    "gn:population":5,
    "gn:timezone":"America/Mexico_City",
    "iso:country":"MX",
    "wof:name":"Zacatepec",
    "wof:placetype":"locality",
    "wof:population":5
},
  "geometry": {"coordinates":[-98.40485,19.67467000000001],"type":"Point"}
}