{
  "type": "Feature",
  "properties": {
    "gn:admin1_code":"30",
    "gn:admin2_code":"184",
    "gn:asciiname":"Tepexitlampa",
    "gn:country_code":"MX",
    "gn:dem":2421,
    "gn:feature_class":"P",
    "gn:feature_code":"PPL",
    "gn:name":"Tepexitlampa",
    "gn:population":29,
    "gn:timezone":"America/Mexico_City",
    "iso:country":"MX",
    "wof:name":"Tepexitlampa",
    "wof:placetype":"locality",
    "wof:population":29
},
  "geometry": {"coordinates":[-97.10666999999999,18.62694],"type":"Point"}
}