{
  "type": "Feature",
  "properties": {
    "gn:admin1_code":"21.0",
    "gn:admin2_code":"86.0",
    "gn:asciiname":"Agua Hedionda",
    "gn:country_code":"MX",
    "gn:dem":775,
    "gn:feature_class":"P",
    "gn:feature_code":"PPL",
    "gn:name":"Agua Hedionda",
    "gn:population":84,
    "gn:timezone":"America/Mexico_City",
    "iso:country":"MX",
    "name:spa_x_preferred":[
        "Agua Hedionda"
    ],
    "wof:name":"Agua Hedionda",
    "wof:placetype":"locality",
    "wof:population":84
},
  "geometry": {"coordinates":[-97.99305,20.47111],"type":"Point"}
}