{
  "type": "Feature",
  "properties": {
    "gn:admin1_code":"32",
    "gn:admin2_code":"49.0",
    "gn:asciiname":"La Chicharra",
    "gn:country_code":"MX",
    "gn:dem":1834,
    "gn:feature_class":"P",
    "gn:feature_code":"PPL",
    "gn:name":"La Chicharra",
    "gn:population":5,
    "gn:timezone":"America/Mexico_City",
    "iso:country":"MX",
    "wof:name":"La Chicharra",
    "wof:placetype":"locality",
    "wof:population":5
},
  "geometry": {"coordinates":[-103.99139,22.45306],"type":"Point"}
}