{
  "type": "Feature",
  "properties": {
    "gn:admin1_code":"14.0",
    "gn:admin2_code":"68.0",
    "gn:asciiname":"El Angelin",
    "gn:country_code":"MX",
    "gn:dem":560,
    "gn:feature_class":"P",
    "gn:feature_code":"PPL",
    "gn:name":"El Angel\u00edn",
    "gn:population":0,
    "gn:timezone":"America/Mexico_City",
    "iso:country":"MX",
    "name:spa_x_preferred":[
        "El Angel\u00edn"
    ],
    "wof:name":"El Angelin",
    "wof:placetype":"locality"
},
  "geometry": {"coordinates":[-104.54397,19.75909],"type":"Point"}
}