{
  "type": "Feature",
  "properties": {
    "gn:admin1_code":"20",
    "gn:admin2_code":"437.0",
    "gn:asciiname":"Santa Ana",
    "gn:country_code":"MX",
    "gn:dem":2063,
    "gn:feature_class":"P",
    "gn:feature_code":"PPL",
    "gn:name":"Santa Ana",
    "gn:population":569,
    "gn:timezone":"America/Mexico_City",
    "iso:country":"MX",
    "wof:name":"Santa Ana",
    "wof:placetype":"locality",
    "wof:population":569
},
  "geometry": {"coordinates":[-96.05472,17.09528],"type":"Point"}
}