{
  "type": "Feature",
  "properties": {
    "gn:admin1_code":"14",
    "gn:admin2_code":"35.0",
    "gn:asciiname":"El Tepozan",
    "gn:country_code":"MX",
    "gn:dem":1988,
    "gn:feature_class":"P",
    "gn:feature_code":"PPL",
    "gn:name":"El Tepoz\u00e1n",
    "gn:population":84,
    "gn:timezone":"America/Mexico_City",
    "iso:country":"MX",
    "name:und_x_variant":[
        "El Tepoz\u00e1n"
    ],
    "wof:name":"El Tepozan",
    "wof:placetype":"locality",
    "wof:population":84
},
  "geometry": {"coordinates":[-102.07222,21.7075],"type":"Point"}
}