{
  "type": "Feature",
  "properties": {
    "gn:admin1_code":"5",
    "gn:admin2_code":"49.0",
    "gn:asciiname":"Pena Blanca",
    "gn:country_code":"MX",
    "gn:dem":1825,
    "gn:feature_class":"P",
    "gn:feature_code":"PPL",
    "gn:name":"Pe\u00f1a Blanca",
    "gn:population":113,
    "gn:timezone":"America/Mexico_City",
    "iso:country":"MX",
    "name:und_x_variant":[
        "Pe\u00f1a Blanca"
    ],
    "wof:name":"Pena Blanca",
    "wof:placetype":"locality",
    "wof:population":113
},
  "geometry": {"coordinates":[-92.81247999999999,16.89834],"type":"Point"}
}