{
  "type": "Feature",
  "properties": {
    "gn:admin1_code":"15",
    "gn:admin2_code":"89",
    "gn:asciiname":"Colonia el Mirador",
    "gn:country_code":"MX",
    "gn:dem":2386,
    "gn:feature_class":"P",
    "gn:feature_code":"PPL",
    "gn:name":"Colonia el Mirador",
    "gn:population":28,
    "gn:timezone":"America/Mexico_City",
    "iso:country":"MX",
    "wof:name":"Colonia el Mirador",
    "wof:placetype":"locality",
    "wof:population":28
},
  "geometry": {"coordinates":[-98.85098000000001,19.15461],"type":"Point"}
}