{
  "type": "Feature",
  "properties": {
    "gn:admin1_code":"26.0",
    "gn:admin2_code":"59.0",
    "gn:asciiname":"Los Medina",
    "gn:country_code":"MX",
    "gn:dem":1348,
    "gn:feature_class":"P",
    "gn:feature_code":"PPL",
    "gn:name":"Los Medina",
    "gn:population":0,
    "gn:timezone":"America/Hermosillo",
    "iso:country":"MX",
    "name:spa_x_preferred":[
        "Los Medina"
    ],
    "wof:name":"Los Medina",
    "wof:placetype":"locality"
},
  "geometry": {"coordinates":[-110.58958,31.22501],"type":"Point"}
}