{
  "type": "Feature",
  "properties": {
    "gn:admin1_code":"30.0",
    "gn:admin2_code":"114.0",
    "gn:asciiname":"Arbolitos",
    "gn:country_code":"MX",
    "gn:dem":14,
    "gn:feature_class":"P",
    "gn:feature_code":"PPL",
    "gn:name":"Arbolitos",
    "gn:population":0,
    "gn:timezone":"America/Mexico_City",
    "iso:country":"MX",
    "name:spa_x_preferred":[
        "Arbolitos"
    ],
    "wof:name":"Arbolitos",
    "wof:placetype":"locality"
},
  "geometry": {"coordinates":[-96.71221,20.12523],"type":"Point"}
}