{
  "type": "Feature",
  "properties": {
    "gn:admin1_code":"23",
    "gn:admin2_code":"2.0",
    "gn:asciiname":"Senor Dos Esperanzas",
    "gn:country_code":"MX",
    "gn:dem":8,
    "gn:feature_class":"P",
    "gn:feature_code":"PPL",
    "gn:name":"Se\u00f1or Dos Esperanzas",
    "gn:population":0,
    "gn:timezone":"America/Cancun",
    "iso:country":"MX",
    "wof:name":"Senor Dos Esperanzas",
    "wof:placetype":"locality"
},
  "geometry": {"coordinates":[-87.78333000000001,19.76667],"type":"Point"}
}