{
  "type": "Feature",
  "properties": {
    "gn:admin1_code":"28",
    "gn:admin2_code":"22",
    "gn:asciiname":"Las Esquinas",
    "gn:country_code":"MX",
    "gn:dem":14,
    "gn:feature_class":"P",
    "gn:feature_code":"PPL",
    "gn:name":"Las Esquinas",
    "gn:population":32,
    "gn:timezone":"America/Matamoros",
    "iso:country":"MX",
    "wof:name":"Las Esquinas",
    "wof:placetype":"locality",
    "wof:population":32
},
  "geometry": {"coordinates":[-97.62833000000001,25.85389],"type":"Point"}
}