{
  "type": "Feature",
  "properties": {
    "gn:admin1_code":"13",
    "gn:asciiname":"Pastoria",
    "gn:country_code":"MX",
    "gn:dem":94,
    "gn:feature_class":"P",
    "gn:feature_code":"PPL",
    "gn:name":"Pastor\u00eda",
    "gn:population":0,
    "gn:timezone":"America/Mexico_City",
    "iso:country":"MX",
    "name:spa_x_preferred":[
        "Pastor\u00eda"
    ],
    "wof:name":"Pastoria",
    "wof:placetype":"locality"
},
  "geometry": {"coordinates":[-98.14049,21.08803],"type":"Point"}
}