{
  "type": "Feature",
  "properties": {
    "gn:admin1_code":"2.0",
    "gn:admin2_code":"3.0",
    "gn:asciiname":"Valle las Palmas",
    "gn:country_code":"MX",
    "gn:dem":437,
    "gn:feature_class":"P",
    "gn:feature_code":"PPL",
    "gn:name":"Valle las Palmas",
    "gn:population":0,
    "gn:timezone":"America/Tijuana",
    "iso:country":"MX",
    "name:spa_x_preferred":[
        "Valle las Palmas"
    ],
    "wof:name":"Valle las Palmas",
    "wof:placetype":"locality"
},
  "geometry": {"coordinates":[-116.59414,32.40381],"type":"Point"}
}