{
  "type": "Feature",
  "properties": {
    "gn:admin1_code":"26",
    "gn:admin2_code":"64.0",
    "gn:asciiname":"El Prieto",
    "gn:country_code":"MX",
    "gn:dem":454,
    "gn:feature_class":"P",
    "gn:feature_code":"PPL",
    "gn:name":"El Prieto",
    "gn:population":6,
    "gn:timezone":"America/Hermosillo",
    "iso:country":"MX",
    "wof:name":"El Prieto",
    "wof:placetype":"locality",
    "wof:population":6
},
  "geometry": {"coordinates":[-111.64278,30.47889],"type":"Point"}
}