{
  "type": "Feature",
  "properties": {
    "gn:admin1_code":"26.0",
    "gn:admin2_code":"35.0",
    "gn:asciiname":"Los Caloncitos",
    "gn:country_code":"MX",
    "gn:dem":838,
    "gn:feature_class":"P",
    "gn:feature_code":"PPL",
    "gn:name":"Los Caloncitos",
    "gn:population":0,
    "gn:timezone":"America/Hermosillo",
    "iso:country":"MX",
    "name:spa_x_preferred":[
        "Los Caloncitos"
    ],
    "wof:name":"Los Caloncitos",
    "wof:placetype":"locality"
},
  "geometry": {"coordinates":[-110.86367,30.76936],"type":"Point"}
}