{
  "type": "Feature",
  "properties": {
    "gn:admin1_code":"5",
    "gn:admin2_code":"97",
    "gn:asciiname":"El Morrito",
    "gn:country_code":"MX",
    "gn:dem":72,
    "gn:feature_class":"P",
    "gn:feature_code":"PPL",
    "gn:name":"El Morrito",
    "gn:population":11,
    "gn:timezone":"America/Mexico_City",
    "iso:country":"MX",
    "wof:name":"El Morrito",
    "wof:placetype":"locality",
    "wof:population":11
},
  "geometry": {"coordinates":[-93.64292,15.97917],"type":"Point"}
}