{
  "type": "Feature",
  "properties": {
    "gn:admin1_code":"30.0",
    "gn:admin2_code":"123.0",
    "gn:asciiname":"Santa Erendira",
    "gn:country_code":"MX",
    "gn:dem":43,
    "gn:feature_class":"P",
    "gn:feature_code":"PPL",
    "gn:name":"Santa Er\u00e9ndira",
    "gn:population":0,
    "gn:timezone":"America/Mexico_City",
    "iso:country":"MX",
    "name:spa_x_preferred":[
        "Santa Er\u00e9ndira"
    ],
    "wof:name":"Santa Erendira",
    "wof:placetype":"locality"
},
  "geometry": {"coordinates":[-98.23621,21.79953],"type":"Point"}
}