{
  "type": "Feature",
  "properties": {
    "gn:admin1_code":"19",
    "gn:admin2_code":"7.0",
    "gn:asciiname":"Ibarrilla",
    "gn:country_code":"MX",
    "gn:dem":718,
    "gn:feature_class":"P",
    "gn:feature_code":"PPL",
    "gn:name":"Ibarrilla",
    "gn:population":0,
    "gn:timezone":"America/Monterrey",
    "iso:country":"MX",
    "name:spa_x_preferred":[
        "Ibarilla"
    ],
    "wof:name":"Ibarrilla",
    "wof:placetype":"locality"
},
  "geometry": {"coordinates":[-99.67292999999999,24.37356],"type":"Point"}
}