{
  "type": "Feature",
  "properties": {
    "gn:admin1_code":"5",
    "gn:admin2_code":"89.0",
    "gn:asciiname":"Poligono de Tiro",
    "gn:country_code":"MX",
    "gn:dem":45,
    "gn:feature_class":"P",
    "gn:feature_code":"PPL",
    "gn:name":"Pol\u00edgono de Tiro",
    "gn:population":4,
    "gn:timezone":"America/Mexico_City",
    "iso:country":"MX",
    "name:und_x_variant":[
        "Pol\u00edgono de Tiro"
    ],
    "wof:name":"Poligono de Tiro",
    "wof:placetype":"locality",
    "wof:population":4
},
  "geometry": {"coordinates":[-92.36583,14.93361],"type":"Point"}
}