{
  "type": "Feature",
  "properties": {
    "gn:admin1_code":"28",
    "gn:admin2_code":"5.0",
    "gn:asciiname":"El Coronel",
    "gn:country_code":"MX",
    "gn:dem":266,
    "gn:feature_class":"P",
    "gn:feature_code":"PPL",
    "gn:name":"El Coronel",
    "gn:population":0,
    "gn:timezone":"America/Monterrey",
    "iso:country":"MX",
    "name:spa_x_preferred":[
        "El Coronel"
    ],
    "name:und_x_variant":[
        "Rancho El Coronel"
    ],
    "wof:name":"El Coronel",
    "wof:placetype":"locality"
},
  "geometry": {"coordinates":[-98.65841,24.82379],"type":"Point"}
}