{
  "type": "Feature",
  "properties": {
    "gn:admin1_code":"30",
    "gn:admin2_code":"144",
    "gn:asciiname":"Yerbabuena",
    "gn:country_code":"MX",
    "gn:dem":88,
    "gn:feature_class":"P",
    "gn:feature_code":"PPL",
    "gn:name":"Yerbabuena",
    "gn:population":26,
    "gn:timezone":"America/Mexico_City",
    "iso:country":"MX",
    "wof:name":"Yerbabuena",
    "wof:placetype":"locality",
    "wof:population":26
},
  "geometry": {"coordinates":[-94.96111000000001,17.90139],"type":"Point"}
}