{
  "type": "Feature",
  "properties": {
    "gn:admin1_code":"20",
    "gn:admin2_code":"5.0",
    "gn:asciiname":"Boca del Monte",
    "gn:country_code":"MX",
    "gn:dem":228,
    "gn:feature_class":"P",
    "gn:feature_code":"PPL",
    "gn:name":"Boca del Monte",
    "gn:population":0,
    "gn:timezone":"America/Mexico_City",
    "iso:country":"MX",
    "name:spa_x_preferred":[
        "Boca del Monte"
    ],
    "wof:name":"Boca del Monte",
    "wof:placetype":"locality"
},
  "geometry": {"coordinates":[-94.84461,16.69174],"type":"Point"}
}