{
  "type": "Feature",
  "properties": {
    "gn:admin1_code":"19.0",
    "gn:admin2_code":"5.0",
    "gn:asciiname":"Tanque Colorado",
    "gn:country_code":"MX",
    "gn:dem":235,
    "gn:feature_class":"P",
    "gn:feature_code":"PPL",
    "gn:name":"Tanque Colorado",
    "gn:population":0,
    "gn:timezone":"America/Matamoros",
    "iso:country":"MX",
    "name:spa_x_preferred":[
        "Tanque Colorado"
    ],
    "wof:name":"Tanque Colorado",
    "wof:placetype":"locality"
},
  "geometry": {"coordinates":[-100.25269,27.47466],"type":"Point"}
}