{
  "type": "Feature",
  "properties": {
    "gn:admin1_code":"25",
    "gn:admin2_code":"15.0",
    "gn:asciiname":"Rancho Alegre",
    "gn:country_code":"MX",
    "gn:dem":107,
    "gn:feature_class":"P",
    "gn:feature_code":"PPL",
    "gn:name":"Rancho Alegre",
    "gn:population":0,
    "gn:timezone":"America/Mazatlan",
    "iso:country":"MX",
    "name:ceb_x_preferred":[
        "Rancho Alegre"
    ],
    "name:nld_x_preferred":[
        "Rancho Alegre"
    ],
    "name:por_x_preferred":[
        "Rancho Alegre"
    ],
    "name:spa_x_preferred":[
        "Rancho Alegre"
    ],
    "name:swe_x_preferred":[
        "Rancho Alegre"
    ],
    "name:vol_x_preferred":[
        "Rancho Alegre"
    ],
    "wof:name":"Rancho Alegre",
    "wof:placetype":"locality"
},
  "geometry": {"coordinates":[-108.01663000000001,25.38143],"type":"Point"}
}