{
  "type": "Feature",
  "properties": {
    "gn:admin1_code":"16",
    "gn:admin2_code":"13.0",
    "gn:asciiname":"El Cuitzillo",
    "gn:country_code":"MX",
    "gn:dem":553,
    "gn:feature_class":"P",
    "gn:feature_code":"PPL",
    "gn:name":"El Cuitzillo",
    "gn:population":129,
    "gn:timezone":"America/Mexico_City",
    "iso:country":"MX",
    "wof:name":"El Cuitzillo",
    "wof:placetype":"locality",
    "wof:population":129
},
  "geometry": {"coordinates":[-101.10306,19.02028],"type":"Point"}
}