{
  "type": "Feature",
  "properties": {
    "gn:admin1_code":"31",
    "gn:admin2_code":"12.0",
    "gn:asciiname":"Xmactun",
    "gn:country_code":"MX",
    "gn:dem":19,
    "gn:feature_class":"P",
    "gn:feature_code":"PPL",
    "gn:name":"Xmact\u00fan",
    "gn:population":0,
    "gn:timezone":"America/Merida",
    "iso:country":"MX",
    "name:spa_x_preferred":[
        "Xmact\u00fan"
    ],
    "wof:name":"Xmactun",
    "wof:placetype":"locality"
},
  "geometry": {"coordinates":[-88.62254,20.97104],"type":"Point"}
}