{
  "type": "Feature",
  "properties": {
    "gn:admin1_code":"11",
    "gn:admin2_code":"3.0",
    "gn:asciiname":"San Jose de Viborillas",
    "gn:country_code":"MX",
    "gn:dem":2043,
    "gn:feature_class":"P",
    "gn:feature_code":"PPL",
    "gn:name":"San Jos\u00e9 de Viborillas",
    "gn:population":210,
    "gn:timezone":"America/Mexico_City",
    "iso:country":"MX",
    "name:und_x_variant":[
        "San Jos\u00e9 de Viborillas"
    ],
    "wof:name":"San Jose de Viborillas",
    "wof:placetype":"locality",
    "wof:population":210
},
  "geometry": {"coordinates":[-100.63194,20.97],"type":"Point"}
}