{
  "type": "Feature",
  "properties": {
    "gn:admin1_code":"30",
    "gn:admin2_code":"173.0",
    "gn:asciiname":"Las Maravillas",
    "gn:country_code":"MX",
    "gn:dem":609,
    "gn:feature_class":"P",
    "gn:feature_code":"PPL",
    "gn:name":"Las Maravillas",
    "gn:population":0,
    "gn:timezone":"America/Mexico_City",
    "iso:country":"MX",
    "name:spa_x_preferred":[
        "Las Maravillas"
    ],
    "wof:name":"Las Maravillas",
    "wof:placetype":"locality"
},
  "geometry": {"coordinates":[-96.75332,18.57766],"type":"Point"}
}