{
  "type": "Feature",
  "properties": {
    "gn:admin1_code":"23",
    "gn:admin2_code":"6.0",
    "gn:asciiname":"Kancabchen",
    "gn:country_code":"MX",
    "gn:dem":20,
    "gn:feature_class":"P",
    "gn:feature_code":"PPL",
    "gn:name":"Kancabch\u00e9n",
    "gn:population":1083,
    "gn:timezone":"America/Cancun",
    "iso:country":"MX",
    "wof:name":"Kancabchen",
    "wof:placetype":"locality",
    "wof:population":1083
},
  "geometry": {"coordinates":[-88.86166999999998,19.71389],"type":"Point"}
}