{
  "type": "Feature",
  "properties": {
    "gn:admin1_code":"20",
    "gn:admin2_code":"426.0",
    "gn:asciiname":"Rio Contreras",
    "gn:country_code":"MX",
    "gn:dem":2073,
    "gn:feature_class":"P",
    "gn:feature_code":"PPL",
    "gn:name":"R\u00edo Contreras",
    "gn:population":229,
    "gn:timezone":"America/Mexico_City",
    "iso:country":"MX",
    "name:und_x_variant":[
        "R\u00edo Contreras"
    ],
    "wof:name":"Rio Contreras",
    "wof:placetype":"locality",
    "wof:population":229
},
  "geometry": {"coordinates":[-96.98583000000001,17.0925],"type":"Point"}
}