{
  "type": "Feature",
  "properties": {
    "gn:admin1_code":"32.0",
    "gn:admin2_code":"46.0",
    "gn:asciiname":"El Llano de Buenavista",
    "gn:country_code":"MX",
    "gn:dem":1928,
    "gn:feature_class":"P",
    "gn:feature_code":"PPL",
    "gn:name":"El Llano de Buenavista",
    "gn:population":0,
    "gn:timezone":"America/Mexico_City",
    "iso:country":"MX",
    "name:spa_x_preferred":[
        "El Llano de Buenavista"
    ],
    "wof:name":"El Llano de Buenavista",
    "wof:placetype":"locality"
},
  "geometry": {"coordinates":[-103.06106,22.46695],"type":"Point"}
}