{
  "type": "Feature",
  "properties": {
    "gn:admin1_code":"16",
    "gn:admin2_code":"79.0",
    "gn:asciiname":"Plutarco Elias Calles (Copandaro)",
    "gn:country_code":"MX",
    "gn:dem":2111,
    "gn:feature_class":"P",
    "gn:feature_code":"PPL",
    "gn:name":"Plutarco El\u00edas Calles (Cop\u00e1ndaro)",
    "gn:population":403,
    "gn:timezone":"America/Mexico_City",
    "iso:country":"MX",
    "name:und_x_variant":[
        "Plutarco El\u00edas Calles (Cop\u00e1ndaro)"
    ],
    "wof:name":"Plutarco Elias Calles (Copandaro)",
    "wof:placetype":"locality",
    "wof:population":403
},
  "geometry": {"coordinates":[-101.76167,19.43722],"type":"Point"}
}