{
  "type": "Feature",
  "properties": {
    "gn:admin1_code":"10.0",
    "gn:admin2_code":"9.0",
    "gn:asciiname":"Los Pocitos",
    "gn:country_code":"MX",
    "gn:dem":2385,
    "gn:feature_class":"P",
    "gn:feature_code":"PPL",
    "gn:name":"Los Pocitos",
    "gn:population":0,
    "gn:timezone":"America/Monterrey",
    "iso:country":"MX",
    "name:spa_x_preferred":[
        "Los Pocitos"
    ],
    "wof:name":"Los Pocitos",
    "wof:placetype":"locality"
},
  "geometry": {"coordinates":[-105.985,25.74899],"type":"Point"}
}