{
  "type": "Feature",
  "properties": {
    "gn:admin1_code":"14.0",
    "gn:admin2_code":"48.0",
    "gn:asciiname":"La Leonera",
    "gn:country_code":"MX",
    "gn:dem":2148,
    "gn:feature_class":"P",
    "gn:feature_code":"PPL",
    "gn:name":"La Leonera",
    "gn:population":0,
    "gn:timezone":"America/Mexico_City",
    "iso:country":"MX",
    "wof:name":"La Leonera",
    "wof:placetype":"locality"
},
  "geometry": {"coordinates":[-102.14767999999999,20.58381],"type":"Point"}
}