{
  "type": "Feature",
  "properties": {
    "gn:admin1_code":"5",
    "gn:admin2_code":"27.0",
    "gn:asciiname":"Distrito Federal",
    "gn:country_code":"MX",
    "gn:dem":450,
    "gn:feature_class":"P",
    "gn:feature_code":"PPL",
    "gn:name":"Distrito Federal",
    "gn:population":744,
    "gn:timezone":"America/Mexico_City",
    "iso:country":"MX",
    "wof:name":"Distrito Federal",
    "wof:placetype":"locality",
    "wof:population":744
},
  "geometry": {"coordinates":[-93.02694,16.59],"type":"Point"}
}