{
  "type": "Feature",
  "properties": {
    "gn:admin1_code":"1.0",
    "gn:admin2_code":"3.0",
    "gn:asciiname":"Tanque de los Serna",
    "gn:country_code":"MX",
    "gn:dem":2266,
    "gn:feature_class":"P",
    "gn:feature_code":"PPL",
    "gn:name":"Tanque de los Serna",
    "gn:population":19,
    "gn:timezone":"America/Mexico_City",
    "iso:country":"MX",
    "wof:name":"Tanque de los Serna",
    "wof:placetype":"locality",
    "wof:population":19
},
  "geometry": {"coordinates":[-102.81959999999999,21.89722],"type":"Point"}
}