{
  "type": "Feature",
  "properties": {
    "gn:admin1_code":"16",
    "gn:admin2_code":"49.0",
    "gn:asciiname":"Huajiniquil",
    "gn:country_code":"MX",
    "gn:dem":1633,
    "gn:feature_class":"P",
    "gn:feature_code":"PPL",
    "gn:name":"Huajiniquil",
    "gn:population":67,
    "gn:timezone":"America/Mexico_City",
    "iso:country":"MX",
    "wof:name":"Huajiniquil",
    "wof:placetype":"locality",
    "wof:population":67
},
  "geometry": {"coordinates":[-101.03778,19.34139],"type":"Point"}
}