{
  "type": "Feature",
  "properties": {
    "gn:admin1_code":"29",
    "gn:admin2_code":"40.0",
    "gn:asciiname":"La Alcaparrosa",
    "gn:country_code":"MX",
    "gn:dem":2592,
    "gn:feature_class":"P",
    "gn:feature_code":"PPLL",
    "gn:name":"La Alcaparrosa",
    "gn:population":0,
    "gn:timezone":"America/Mexico_City",
    "iso:country":"MX",
    "name:spa_x_preferred":[
        "La Alcaparrosa"
    ],
    "wof:name":"La Alcaparrosa",
    "wof:placetype":"locality"
},
  "geometry": {"coordinates":[-98.28222,19.45563],"type":"Point"}
}