{
  "type": "Feature",
  "properties": {
    "gn:admin1_code":"12",
    "gn:admin2_code":"22",
    "gn:asciiname":"El Billete",
    "gn:country_code":"MX",
    "gn:dem":2567,
    "gn:feature_class":"P",
    "gn:feature_code":"PPL",
    "gn:name":"El Billete",
    "gn:population":12,
    "gn:timezone":"America/Mexico_City",
    "iso:country":"MX",
    "wof:name":"El Billete",
    "wof:placetype":"locality",
    "wof:population":12
},
  "geometry": {"coordinates":[-101.32449,18.13909],"type":"Point"}
}