{
  "type": "Feature",
  "properties": {
    "gn:admin1_code":"16",
    "gn:admin2_code":"87",
    "gn:asciiname":"Presa San Juan",
    "gn:country_code":"MX",
    "gn:dem":1179,
    "gn:feature_class":"P",
    "gn:feature_code":"PPL",
    "gn:name":"Presa San Juan",
    "gn:population":36,
    "gn:timezone":"America/Mexico_City",
    "iso:country":"MX",
    "wof:name":"Presa San Juan",
    "wof:placetype":"locality",
    "wof:population":36
},
  "geometry": {"coordinates":[-101.92610999999999,19.35806],"type":"Point"}
}