{
  "type": "Feature",
  "properties": {
    "gn:admin1_code":"11",
    "gn:admin2_code":"30",
    "gn:asciiname":"Los Juanes",
    "gn:country_code":"MX",
    "gn:dem":2483,
    "gn:feature_class":"P",
    "gn:feature_code":"PPL",
    "gn:name":"Los Juanes",
    "gn:population":28,
    "gn:timezone":"America/Mexico_City",
    "iso:country":"MX",
    "wof:name":"Los Juanes",
    "wof:placetype":"locality",
    "wof:population":28
},
  "geometry": {"coordinates":[-101.24028,21.26],"type":"Point"}
}