{
  "type": "Feature",
  "properties": {
    "gn:admin1_code":"6",
    "gn:admin2_code":"40.0",
    "gn:asciiname":"El Hoyo",
    "gn:country_code":"MX",
    "gn:dem":2240,
    "gn:feature_class":"P",
    "gn:feature_code":"PPL",
    "gn:name":"El Hoyo",
    "gn:population":7,
    "gn:timezone":"America/Chihuahua",
    "iso:country":"MX",
    "wof:name":"El Hoyo",
    "wof:placetype":"locality",
    "wof:population":7
},
  "geometry": {"coordinates":[-108.21889,29.71126],"type":"Point"}
}