{
  "type": "Feature",
  "properties": {
    "gn:admin1_code":"21",
    "gn:admin2_code":"77.0",
    "gn:asciiname":"Cajalan",
    "gn:country_code":"MX",
    "gn:dem":874,
    "gn:feature_class":"P",
    "gn:feature_code":"PPL",
    "gn:name":"Cajal\u00e1n",
    "gn:population":80,
    "gn:timezone":"America/Mexico_City",
    "iso:country":"MX",
    "name:und_x_variant":[
        "Cajal\u00e1n"
    ],
    "wof:name":"Cajalan",
    "wof:placetype":"locality",
    "wof:population":80
},
  "geometry": {"coordinates":[-97.66468,20.03008],"type":"Point"}
}