{
  "type": "Feature",
  "properties": {
    "gn:admin1_code":"26",
    "gn:asciiname":"La Enramada",
    "gn:country_code":"MX",
    "gn:dem":1530,
    "gn:feature_class":"P",
    "gn:feature_code":"PPL",
    "gn:name":"La Enramada",
    "gn:population":0,
    "gn:timezone":"America/Hermosillo",
    "iso:country":"MX",
    "name:spa_x_preferred":[
        "La Enramada"
    ],
    "wof:name":"La Enramada",
    "wof:placetype":"locality"
},
  "geometry": {"coordinates":[-108.82046,30.72748],"type":"Point"}
}