{
  "type": "Feature",
  "properties": {
    "gn:admin1_code":"5.0",
    "gn:admin2_code":"107.0",
    "gn:asciiname":"El Saucito",
    "gn:country_code":"MX",
    "gn:dem":840,
    "gn:feature_class":"P",
    "gn:feature_code":"PPL",
    "gn:name":"El Saucito",
    "gn:population":0,
    "gn:timezone":"America/Mexico_City",
    "iso:country":"MX",
    "name:spa_x_preferred":[
        "El Saucito"
    ],
    "wof:name":"El Saucito",
    "wof:placetype":"locality"
},
  "geometry": {"coordinates":[-93.24397999999999,15.97565],"type":"Point"}
}