{
  "type": "Feature",
  "properties": {
    "gn:admin1_code":"15",
    "gn:admin2_code":"82.0",
    "gn:asciiname":"Rinconada de la Labor",
    "gn:country_code":"MX",
    "gn:dem":1370,
    "gn:feature_class":"P",
    "gn:feature_code":"PPL",
    "gn:name":"Rinconada de la Labor",
    "gn:population":211,
    "gn:timezone":"America/Mexico_City",
    "iso:country":"MX",
    "wof:name":"Rinconada de la Labor",
    "wof:placetype":"locality",
    "wof:population":211
},
  "geometry": {"coordinates":[-100.10283,18.88539],"type":"Point"}
}