{
  "type": "Feature",
  "properties": {
    "gn:admin1_code":"8",
    "gn:admin2_code":"5.0",
    "gn:asciiname":"Karin Urzua",
    "gn:country_code":"MX",
    "gn:dem":1483,
    "gn:feature_class":"P",
    "gn:feature_code":"PPL",
    "gn:name":"Kar\u00edn Urz\u00faa",
    "gn:population":5,
    "gn:timezone":"America/Mexico_City",
    "iso:country":"MX",
    "name:und_x_variant":[
        "Kar\u00edn Urz\u00faa"
    ],
    "wof:name":"Karin Urzua",
    "wof:placetype":"locality",
    "wof:population":5
},
  "geometry": {"coordinates":[-103.64167,19.41],"type":"Point"}
}