{
  "type": "Feature",
  "properties": {
    "gn:admin1_code":"21",
    "gn:admin2_code":"35.0",
    "gn:asciiname":"Calpuhuacan",
    "gn:country_code":"MX",
    "gn:dem":1964,
    "gn:feature_class":"P",
    "gn:feature_code":"PPL",
    "gn:name":"Calpuhuacan",
    "gn:population":176,
    "gn:timezone":"America/Mexico_City",
    "iso:country":"MX",
    "wof:name":"Calpuhuacan",
    "wof:placetype":"locality",
    "wof:population":176
},
  "geometry": {"coordinates":[-97.11472000000001,18.31509],"type":"Point"}
}