{
  "type": "Feature",
  "properties": {
    "gn:admin1_code":"32",
    "gn:admin2_code":"56",
    "gn:asciiname":"Ojo de Agua de Melendez (Ojo de Agua)",
    "gn:country_code":"MX",
    "gn:dem":2432,
    "gn:feature_class":"P",
    "gn:feature_code":"PPL",
    "gn:name":"Ojo de Agua de Mel\u00e9ndez (Ojo de Agua)",
    "gn:population":37,
    "gn:timezone":"America/Mexico_City",
    "iso:country":"MX",
    "name:und_x_variant":[
        "Ojo de Agua de Mel\u00e9ndez (Ojo de Agua)"
    ],
    "wof:name":"Ojo de Agua de Melendez (Ojo de Agua)",
    "wof:placetype":"locality",
    "wof:population":37
},
  "geometry": {"coordinates":[-102.58389,22.73333],"type":"Point"}
}