{
  "type": "Feature",
  "properties": {
    "iso:country":"MX",
    "name:spa_x_preferred":[
        "Unidad Magisterial"
    ],
    "qs:gn_local":0,
    "qs:local_max":899,
    "qs:local_sum":2928,
    "qs:localhoods":15,
    "qs:name":"Unidad Magisterial",
    "qs:name_adm0":"M\u00e9xico",
    "qs:name_adm1":"Veracruz-Llave",
    "qs:name_adm2":"Xalapa",
    "qs:name_local":"Jalapa de Enriquez",
    "qs:photo_max":105,
    "qs:photo_sum":117,
    "qs:placetype":"Suburb",
    "qs:quad_count":2,
    "qs:woe_adm0":23424900,
    "qs:woe_adm1":2346293,
    "qs:woe_adm2":12601915,
    "qs:woe_lau":0,
    "qs:woe_local":55903793,
    "qs:woe_ver":"7.10.0",
    "wof:lang":[
        "spa"
    ],
    "wof:name":"Unidad Magisterial",
    "wof:placetype":"neighbourhood"
},
  "geometry": {"coordinates":[-96.93142,19.550864],"type":"Point"}
}