{
  "type": "Feature",
  "properties": {
    "gn:admin1_code":"10",
    "gn:admin2_code":"34.0",
    "gn:asciiname":"El Bajio",
    "gn:country_code":"MX",
    "gn:dem":2210,
    "gn:feature_class":"P",
    "gn:feature_code":"PPL",
    "gn:name":"El Baj\u00edo",
    "gn:population":157,
    "gn:timezone":"America/Monterrey",
    "iso:country":"MX",
    "name:und_x_variant":[
        "El Baj\u00edo"
    ],
    "wof:name":"El Bajio",
    "wof:placetype":"locality",
    "wof:population":157
},
  "geometry": {"coordinates":[-106.62306,24.93444],"type":"Point"}
}