{
  "type": "Feature",
  "properties": {
    "gn:gn_country":"MX",
    "gn:gn_fcode":"PPL",
    "gn:gn_pop":0,
    "iso:country":"MX",
    "name:eng_x_preferred":[
        "Uayalceh"
    ],
    "name:rus_x_preferred":[
        "\u0423\u0430\u044f\u043b\u044c\u0441\u0435\u0445"
    ],
    "name:spa_x_preferred":[
        "Uayalceh de Pe\u00f3n"
    ],
    "name:spa_x_variant":[
        "Uayalceh"
    ],
    "name:srp_x_preferred":[
        "\u0423\u0430\u0458\u0430\u043b\u0441\u0435"
    ],
    "name:unk_x_variant":[
        "Uyalceh"
    ],
    "qs_pg:aaroncc":"MX",
    "qs_pg:gn_country":"MX",
    "qs_pg:gn_fcode":"PPL",
    "qs_pg:gn_pop":0,
    "qs_pg:name":"Uayalceh",
    "qs_pg:name_adm0":"M\u00e9xico",
    "qs_pg:name_adm1":"Yucatan",
    "qs_pg:photos":84,
    "qs_pg:photos_1k":17,
    "qs_pg:photos_9k":1,
    "qs_pg:photos_9r":3,
    "qs_pg:photos_all":84,
    "qs_pg:photos_sr":3,
    "qs_pg:pop_sr":0,
    "qs_pg:qs_pg_placetype":"locality",
    "qs_pg:qs_pg_placetype_gp":"Town",
    "qs_pg:woe_adm0":23424900,
    "woe:adm0_id":23424900,
    "woe:name_adm0":"M\u00e9xico",
    "woe:name_adm1":"Yucatan",
    "woe:placetype":"Town",
    "wof:name":"Uayalceh",
    "wof:placetype":"locality"
},
  "geometry": {"coordinates":[-89.595,20.69403],"type":"Point"}
}