{
  "type": "Feature",
  "properties": {
    "gn:admin1_code":"20.0",
    "gn:admin2_code":"498.0",
    "gn:asciiname":"Dos Arbolitos",
    "gn:country_code":"MX",
    "gn:dem":101,
    "gn:feature_class":"P",
    "gn:feature_code":"PPL",
    "gn:name":"Dos Arbolitos",
    "gn:population":0,
    "gn:timezone":"America/Mexico_City",
    "iso:country":"MX",
    "name:spa_x_preferred":[
        "Dos Arbolitos"
    ],
    "wof:name":"Dos Arbolitos",
    "wof:placetype":"locality"
},
  "geometry": {"coordinates":[-95.52845000000001,17.51279],"type":"Point"}
}