{
  "type": "Feature",
  "properties": {
    "gn:admin1_code":"30",
    "gn:admin2_code":"207.0",
    "gn:asciiname":"Martin Olivares",
    "gn:country_code":"MX",
    "gn:dem":19,
    "gn:feature_class":"P",
    "gn:feature_code":"PPL",
    "gn:name":"Mart\u00edn Olivares",
    "gn:population":5,
    "gn:timezone":"America/Mexico_City",
    "iso:country":"MX",
    "name:und_x_variant":[
        "Mart\u00edn Olivares"
    ],
    "wof:name":"Martin Olivares",
    "wof:placetype":"locality",
    "wof:population":5
},
  "geometry": {"coordinates":[-96.11944,18.41861],"type":"Point"}
}