{
  "type": "Feature",
  "properties": {
    "gn:admin1_code":"11",
    "gn:admin2_code":"27",
    "gn:asciiname":"Familia Ruelas Andrade",
    "gn:country_code":"MX",
    "gn:dem":1723,
    "gn:feature_class":"P",
    "gn:feature_code":"PPL",
    "gn:name":"Familia Ruelas Andrade",
    "gn:population":29,
    "gn:timezone":"America/Mexico_City",
    "iso:country":"MX",
    "wof:name":"Familia Ruelas Andrade",
    "wof:placetype":"locality",
    "wof:population":29
},
  "geometry": {"coordinates":[-101.08722,20.475],"type":"Point"}
}