{
  "type": "Feature",
  "properties": {
    "gn:admin1_code":"19",
    "gn:admin2_code":"14.0",
    "gn:asciiname":"La Escondida de Arzola",
    "gn:country_code":"MX",
    "gn:dem":1735,
    "gn:feature_class":"P",
    "gn:feature_code":"PPL",
    "gn:name":"La Escondida de Arzola",
    "gn:population":0,
    "gn:timezone":"America/Monterrey",
    "iso:country":"MX",
    "name:spa_x_preferred":[
        "La Escondida de Arzola"
    ],
    "wof:name":"La Escondida de Arzola",
    "wof:placetype":"locality"
},
  "geometry": {"coordinates":[-100.46501000000001,23.88259],"type":"Point"}
}