{
  "type": "Feature",
  "properties": {
    "gn:admin1_code":"19.0",
    "gn:admin2_code":"20.0",
    "gn:asciiname":"El Coronel",
    "gn:country_code":"MX",
    "gn:dem":141,
    "gn:feature_class":"P",
    "gn:feature_code":"PPL",
    "gn:name":"El Coronel",
    "gn:population":0,
    "gn:timezone":"America/Monterrey",
    "iso:country":"MX",
    "name:spa_x_preferred":[
        "El Coronel"
    ],
    "wof:name":"El Coronel",
    "wof:placetype":"locality"
},
  "geometry": {"coordinates":[-98.84381999999999,25.89409],"type":"Point"}
}