{
  "type": "Feature",
  "properties": {
    "gn:admin1_code":"24",
    "gn:admin2_code":"23",
    "gn:asciiname":"San Antonio del Perrillal",
    "gn:country_code":"MX",
    "gn:dem":1007,
    "gn:feature_class":"P",
    "gn:feature_code":"PPL",
    "gn:name":"San Antonio del Perrillal",
    "gn:population":18,
    "gn:timezone":"America/Mexico_City",
    "iso:country":"MX",
    "wof:name":"San Antonio del Perrillal",
    "wof:placetype":"locality",
    "wof:population":18
},
  "geometry": {"coordinates":[-99.67111,21.79028],"type":"Point"}
}