{
  "type": "Feature",
  "properties": {
    "gn:admin1_code":"14.0",
    "gn:admin2_code":"52.0",
    "gn:asciiname":"Aguacate de Abajo",
    "gn:country_code":"MX",
    "gn:dem":1385,
    "gn:feature_class":"P",
    "gn:feature_code":"PPL",
    "gn:name":"Aguacate de Abajo",
    "gn:population":0,
    "gn:timezone":"America/Mexico_City",
    "iso:country":"MX",
    "name:spa_x_preferred":[
        "Aguacate de Abajo"
    ],
    "wof:name":"Aguacate de Abajo",
    "wof:placetype":"locality"
},
  "geometry": {"coordinates":[-104.00668,20.06847],"type":"Point"}
}