{
  "type": "Feature",
  "properties": {
    "gn:admin1_code":"10.0",
    "gn:admin2_code":"5.0",
    "gn:asciiname":"Animas",
    "gn:cc2":"MX",
    "gn:country_code":"MX",
    "gn:dem":2241,
    "gn:feature_class":"P",
    "gn:feature_code":"PPL",
    "gn:name":"\u00c1nimas",
    "gn:population":0,
    "gn:timezone":"America/Monterrey",
    "iso:country":"MX",
    "name:und_x_variant":[
        "Animas de Cerro Verde",
        "\u00c1nimas"
    ],
    "wof:name":"Animas",
    "wof:placetype":"locality"
},
  "geometry": {"coordinates":[-105.51667,23.98333],"type":"Point"}
}