{
  "type": "Feature",
  "properties": {
    "gn:admin1_code":"28",
    "gn:admin2_code":"41.0",
    "gn:asciiname":"El Agua de las Minas",
    "gn:country_code":"MX",
    "gn:dem":934,
    "gn:feature_class":"P",
    "gn:feature_code":"PPL",
    "gn:name":"El Agua de las Minas",
    "gn:population":6,
    "gn:timezone":"America/Monterrey",
    "iso:country":"MX",
    "wof:name":"El Agua de las Minas",
    "wof:placetype":"locality",
    "wof:population":6
},
  "geometry": {"coordinates":[-99.23721999999999,23.58333],"type":"Point"}
}