{
  "type": "Feature",
  "properties": {
    "gn:admin1_code":"5",
    "gn:admin2_code":"1.0",
    "gn:asciiname":"Nueva Libertad",
    "gn:country_code":"MX",
    "gn:dem":269,
    "gn:feature_class":"P",
    "gn:feature_code":"PPL",
    "gn:name":"Nueva Libertad",
    "gn:population":0,
    "gn:timezone":"America/Mexico_City",
    "iso:country":"MX",
    "name:spa_x_preferred":[
        "La Libertad"
    ],
    "name:spa_x_variant":[
        "Nueva Libertad"
    ],
    "name:und_x_variant":[
        "Libertad"
    ],
    "wof:name":"Nueva Libertad",
    "wof:placetype":"locality"
},
  "geometry": {"coordinates":[-92.70572,15.40676],"type":"Point"}
}