{
  "type": "Feature",
  "properties": {
    "gn:admin1_code":"19.0",
    "gn:admin2_code":"32.0",
    "gn:asciiname":"Los Tomates",
    "gn:country_code":"MX",
    "gn:dem":208,
    "gn:feature_class":"P",
    "gn:feature_code":"PPL",
    "gn:name":"Los Tomates",
    "gn:population":0,
    "gn:timezone":"America/Matamoros",
    "iso:country":"MX",
    "name:spa_x_preferred":[
        "Los Tomates"
    ],
    "wof:name":"Los Tomates",
    "wof:placetype":"locality"
},
  "geometry": {"coordinates":[-100.13746999999999,27.02823],"type":"Point"}
}