{
  "type": "Feature",
  "properties": {
    "gn:admin1_code":"14.0",
    "gn:admin2_code":"35.0",
    "gn:asciiname":"Buenavista de Parga",
    "gn:country_code":"MX",
    "gn:dem":2022,
    "gn:feature_class":"P",
    "gn:feature_code":"PPL",
    "gn:name":"Buenavista de Parga",
    "gn:population":0,
    "gn:timezone":"America/Mexico_City",
    "iso:country":"MX",
    "name:spa_x_preferred":[
        "Buenavista de Parga"
    ],
    "name:spa_x_variant":[
        "Buenavista"
    ],
    "wof:name":"Buenavista de Parga",
    "wof:placetype":"locality"
},
  "geometry": {"coordinates":[-102.15522,21.68747],"type":"Point"}
}