{
  "type": "Feature",
  "properties": {
    "gn:admin1_code":"14",
    "gn:admin2_code":"124.0",
    "gn:asciiname":"San Rafael (La Huizachera)",
    "gn:country_code":"MX",
    "gn:dem":1485,
    "gn:feature_class":"P",
    "gn:feature_code":"PPL",
    "gn:name":"San Rafael (La Huizachera)",
    "gn:population":143,
    "gn:timezone":"America/Mexico_City",
    "iso:country":"MX",
    "wof:name":"San Rafael (La Huizachera)",
    "wof:placetype":"locality",
    "wof:population":143
},
  "geometry": {"coordinates":[-103.06278,20.53639],"type":"Point"}
}