{
  "type": "Feature",
  "properties": {
    "gn:admin1_code":"10.0",
    "gn:admin2_code":"34.0",
    "gn:asciiname":"Yerbabuena",
    "gn:country_code":"MX",
    "gn:dem":994,
    "gn:feature_class":"P",
    "gn:feature_code":"PPL",
    "gn:name":"Yerbabuena",
    "gn:population":0,
    "gn:timezone":"America/Mazatlan",
    "iso:country":"MX",
    "name:spa_x_preferred":[
        "Yerbabuena"
    ],
    "wof:name":"Yerbabuena",
    "wof:placetype":"locality"
},
  "geometry": {"coordinates":[-107.13,25.51398],"type":"Point"}
}