{
  "type": "Feature",
  "properties": {
    "gn:admin1_code":"13",
    "gn:admin2_code":"16.0",
    "gn:asciiname":"Lomas de Ojulla",
    "gn:country_code":"MX",
    "gn:dem":2565,
    "gn:feature_class":"P",
    "gn:feature_code":"PPL",
    "gn:name":"Lomas de Ojulla",
    "gn:population":0,
    "gn:timezone":"America/Mexico_City",
    "iso:country":"MX",
    "name:spa_x_preferred":[
        "Lomas de Ojuela"
    ],
    "name:spa_x_variant":[
        "Lomas de Ojulla"
    ],
    "wof:name":"Lomas de Ojulla",
    "wof:placetype":"locality"
},
  "geometry": {"coordinates":[-98.31762999999999,19.88657000000001],"type":"Point"}
}