{
  "type": "Feature",
  "properties": {
    "gn:admin1_code":"21",
    "gn:admin2_code":"204.0",
    "gn:asciiname":"Mazatonal",
    "gn:country_code":"MX",
    "gn:dem":1737,
    "gn:feature_class":"P",
    "gn:feature_code":"PPL",
    "gn:name":"Mazatonal",
    "gn:population":124,
    "gn:timezone":"America/Mexico_City",
    "iso:country":"MX",
    "wof:name":"Mazatonal",
    "wof:placetype":"locality",
    "wof:population":124
},
  "geometry": {"coordinates":[-97.45995000000001,19.88369],"type":"Point"}
}