{
  "type": "Feature",
  "properties": {
    "gn:admin1_code":"30.0",
    "gn:asciiname":"El Tesoro",
    "gn:country_code":"MX",
    "gn:dem":142,
    "gn:feature_class":"P",
    "gn:feature_code":"PPL",
    "gn:name":"El Tesoro",
    "gn:population":0,
    "gn:timezone":"America/Mexico_City",
    "iso:country":"MX",
    "name:spa_x_preferred":[
        "El Tesoro"
    ],
    "wof:name":"El Tesoro",
    "wof:placetype":"locality"
},
  "geometry": {"coordinates":[-95.55415000000001,17.8473],"type":"Point"}
}