{
  "type": "Feature",
  "properties": {
    "gn:admin1_code":"28",
    "gn:admin2_code":"27.0",
    "gn:asciiname":"El Nido",
    "gn:country_code":"MX",
    "gn:dem":194,
    "gn:feature_class":"P",
    "gn:feature_code":"PPL",
    "gn:name":"El Nido",
    "gn:population":0,
    "gn:timezone":"America/Matamoros",
    "iso:country":"MX",
    "name:spa_x_preferred":[
        "El Nido"
    ],
    "wof:name":"El Nido",
    "wof:placetype":"locality"
},
  "geometry": {"coordinates":[-99.81616,27.59328],"type":"Point"}
}