{
  "type": "Feature",
  "properties": {
    "gn:admin1_code":"25.0",
    "gn:asciiname":"El Arroyo",
    "gn:country_code":"MX",
    "gn:dem":138,
    "gn:feature_class":"P",
    "gn:feature_code":"PPL",
    "gn:name":"El Arroyo",
    "gn:population":0,
    "gn:timezone":"America/Mazatlan",
    "iso:country":"MX",
    "name:spa_x_preferred":[
        "El Arroyo"
    ],
    "wof:name":"El Arroyo",
    "wof:placetype":"locality"
},
  "geometry": {"coordinates":[-106.88589,24.53915],"type":"Point"}
}