{
  "type": "Feature",
  "properties": {
    "gn:admin1_code":"2",
    "gn:admin2_code":"3.0",
    "gn:asciiname":"Agua Viva",
    "gn:country_code":"MX",
    "gn:dem":518,
    "gn:feature_class":"P",
    "gn:feature_code":"PPL",
    "gn:name":"Agua Viva",
    "gn:population":7,
    "gn:timezone":"America/Tijuana",
    "iso:country":"MX",
    "wof:name":"Agua Viva",
    "wof:placetype":"locality",
    "wof:population":7
},
  "geometry": {"coordinates":[-116.48444000000001,32.25167],"type":"Point"}
}