{
  "type": "Feature",
  "properties": {
    "gn:admin1_code":"15",
    "gn:admin2_code":"95.0",
    "gn:asciiname":"Rancho el Arroyo",
    "gn:country_code":"MX",
    "gn:dem":2278,
    "gn:feature_class":"P",
    "gn:feature_code":"PPL",
    "gn:name":"Rancho el Arroyo",
    "gn:population":8,
    "gn:timezone":"America/Mexico_City",
    "iso:country":"MX",
    "wof:name":"Rancho el Arroyo",
    "wof:placetype":"locality",
    "wof:population":8
},
  "geometry": {"coordinates":[-99.21526,19.72901],"type":"Point"}
}