{
  "type": "Feature",
  "properties": {
    "gn:admin1_code":"20",
    "gn:admin2_code":"337.0",
    "gn:asciiname":"El Duraznal",
    "gn:country_code":"MX",
    "gn:dem":1849,
    "gn:feature_class":"P",
    "gn:feature_code":"PPL",
    "gn:name":"El Duraznal",
    "gn:population":0,
    "gn:timezone":"America/Mexico_City",
    "iso:country":"MX",
    "name:spa_x_preferred":[
        "El Duraznal"
    ],
    "name:und_x_variant":[
        "Duraznal"
    ],
    "wof:name":"El Duraznal",
    "wof:placetype":"locality"
},
  "geometry": {"coordinates":[-96.16759,17.03098],"type":"Point"}
}