{
  "type": "Feature",
  "properties": {
    "gn:admin1_code":"14.0",
    "gn:admin2_code":"43.0",
    "gn:asciiname":"Piratas",
    "gn:country_code":"MX",
    "gn:dem":6,
    "gn:feature_class":"P",
    "gn:feature_code":"PPL",
    "gn:name":"Piratas",
    "gn:population":0,
    "gn:timezone":"America/Mexico_City",
    "iso:country":"MX",
    "name:spa_x_preferred":[
        "Piratas"
    ],
    "wof:name":"Piratas",
    "wof:placetype":"locality"
},
  "geometry": {"coordinates":[-104.97525,19.34601],"type":"Point"}
}