{
  "type": "Feature",
  "properties": {
    "gn:admin1_code":"30",
    "gn:admin2_code":"27.0",
    "gn:asciiname":"Doroteo Arango",
    "gn:country_code":"MX",
    "gn:dem":253,
    "gn:feature_class":"P",
    "gn:feature_code":"PPL",
    "gn:name":"Doroteo Arango",
    "gn:population":123,
    "gn:timezone":"America/Mexico_City",
    "iso:country":"MX",
    "wof:name":"Doroteo Arango",
    "wof:placetype":"locality",
    "wof:population":123
},
  "geometry": {"coordinates":[-98.22417,20.88694],"type":"Point"}
}