{
  "type": "Feature",
  "properties": {
    "gn:admin1_code":"26",
    "gn:admin2_code":"42.0",
    "gn:asciiname":"Godinez",
    "gn:country_code":"MX",
    "gn:dem":28,
    "gn:feature_class":"P",
    "gn:feature_code":"PPL",
    "gn:name":"God\u00ednez",
    "gn:population":5,
    "gn:timezone":"America/Hermosillo",
    "iso:country":"MX",
    "name:und_x_variant":[
        "God\u00ednez"
    ],
    "wof:name":"Godinez",
    "wof:placetype":"locality",
    "wof:population":5
},
  "geometry": {"coordinates":[-109.49722,26.98528],"type":"Point"}
}