{
  "type": "Feature",
  "properties": {
    "gn:admin1_code":"13",
    "gn:admin2_code":"28.0",
    "gn:asciiname":"Rancho Nuevo Macuxtepetla",
    "gn:country_code":"MX",
    "gn:dem":442,
    "gn:feature_class":"P",
    "gn:feature_code":"PPL",
    "gn:name":"Rancho Nuevo Macuxtepetla",
    "gn:population":147,
    "gn:timezone":"America/Mexico_City",
    "iso:country":"MX",
    "wof:name":"Rancho Nuevo Macuxtepetla",
    "wof:placetype":"locality",
    "wof:population":147
},
  "geometry": {"coordinates":[-98.49861,21.11222],"type":"Point"}
}