{
  "type": "Feature",
  "properties": {
    "gn:admin1_code":"26.0",
    "gn:admin2_code":"34.0",
    "gn:asciiname":"El Batamote",
    "gn:country_code":"MX",
    "gn:dem":871,
    "gn:feature_class":"P",
    "gn:feature_code":"PPL",
    "gn:name":"El Batamote",
    "gn:population":0,
    "gn:timezone":"America/Hermosillo",
    "iso:country":"MX",
    "name:spa_x_preferred":[
        "El Batamote"
    ],
    "name:und_x_variant":[
        "Balamote",
        "Batamote"
    ],
    "wof:name":"El Batamote",
    "wof:placetype":"locality"
},
  "geometry": {"coordinates":[-110.11375,29.92158],"type":"Point"}
}