{
  "type": "Feature",
  "properties": {
    "gn:admin1_code":"20",
    "gn:admin2_code":"401.0",
    "gn:asciiname":"Chagues",
    "gn:country_code":"MX",
    "gn:dem":17,
    "gn:feature_class":"P",
    "gn:feature_code":"PPL",
    "gn:name":"Chagues",
    "gn:population":0,
    "gn:timezone":"America/Mexico_City",
    "iso:country":"MX",
    "wof:name":"Chagues",
    "wof:placetype":"locality"
},
  "geometry": {"coordinates":[-97.01667,15.86667],"type":"Point"}
}