{
  "type": "Feature",
  "properties": {
    "gn:admin1_code":"30.0",
    "gn:admin2_code":"78.0",
    "gn:asciiname":"Lazaro Cardenas",
    "gn:country_code":"MX",
    "gn:dem":117,
    "gn:feature_class":"P",
    "gn:feature_code":"PPL",
    "gn:name":"Lazaro C\u00e1rdenas",
    "gn:population":0,
    "gn:timezone":"America/Mexico_City",
    "iso:country":"MX",
    "name:spa_x_preferred":[
        "Lazaro C\u00e1rdenas"
    ],
    "wof:name":"Lazaro Cardenas",
    "wof:placetype":"locality"
},
  "geometry": {"coordinates":[-98.07468,21.25851],"type":"Point"}
}