{
  "type": "Feature",
  "properties": {
    "gn:admin1_code":"14",
    "gn:admin2_code":"53",
    "gn:asciiname":"Alto de la Cantera",
    "gn:country_code":"MX",
    "gn:dem":1883,
    "gn:feature_class":"P",
    "gn:feature_code":"PPL",
    "gn:name":"Alto de la Cantera",
    "gn:population":18,
    "gn:timezone":"America/Mexico_City",
    "iso:country":"MX",
    "wof:name":"Alto de la Cantera",
    "wof:placetype":"locality",
    "wof:population":18
},
  "geometry": {"coordinates":[-102.01056,21.3275],"type":"Point"}
}