{
  "type": "Feature",
  "properties": {
    "gn:admin1_code":"32",
    "gn:admin2_code":"10",
    "gn:asciiname":"Santa Fe",
    "gn:country_code":"MX",
    "gn:dem":2150,
    "gn:feature_class":"P",
    "gn:feature_code":"PPL",
    "gn:name":"Santa Fe",
    "gn:population":21,
    "gn:timezone":"America/Mexico_City",
    "iso:country":"MX",
    "wof:name":"Santa Fe",
    "wof:placetype":"locality",
    "wof:population":21
},
  "geometry": {"coordinates":[-103.29472,23.24278],"type":"Point"}
}