{
  "type": "Feature",
  "properties": {
    "gn:admin1_code":"30",
    "gn:admin2_code":"123.0",
    "gn:asciiname":"Reventadero",
    "gn:country_code":"MX",
    "gn:dem":14,
    "gn:feature_class":"P",
    "gn:feature_code":"PPL",
    "gn:name":"Reventadero",
    "gn:population":0,
    "gn:timezone":"America/Mexico_City",
    "iso:country":"MX",
    "name:und_x_variant":[
        "El Reventadero",
        "Reventadero"
    ],
    "wof:name":"Reventadero",
    "wof:placetype":"locality"
},
  "geometry": {"coordinates":[-98.20173,22.11763],"type":"Point"}
}