{
  "type": "Feature",
  "properties": {
    "gn:admin1_code":"5.0",
    "gn:asciiname":"Independencia Noventa y Seis",
    "gn:country_code":"MX",
    "gn:dem":308,
    "gn:feature_class":"P",
    "gn:feature_code":"PPL",
    "gn:name":"Independencia Noventa y Seis",
    "gn:population":0,
    "gn:timezone":"America/Mexico_City",
    "iso:country":"MX",
    "name:spa_x_preferred":[
        "Independencia Noventa y Seis"
    ],
    "name:spa_x_variant":[
        "Independencia 96"
    ],
    "wof:name":"Independencia Noventa y Seis",
    "wof:placetype":"locality"
},
  "geometry": {"coordinates":[-92.33347000000001,15.05803],"type":"Point"}
}