{
  "type": "Feature",
  "properties": {
    "gn:admin1_code":"14",
    "gn:admin2_code":"29",
    "gn:asciiname":"El Cerrito de los Gutierrez",
    "gn:country_code":"MX",
    "gn:dem":1972,
    "gn:feature_class":"P",
    "gn:feature_code":"PPL",
    "gn:name":"El Cerrito de los Guti\u00e9rrez",
    "gn:population":26,
    "gn:timezone":"America/Mexico_City",
    "iso:country":"MX",
    "name:und_x_variant":[
        "El Cerrito de los Guti\u00e9rrez"
    ],
    "wof:name":"El Cerrito de los Gutierrez",
    "wof:placetype":"locality",
    "wof:population":26
},
  "geometry": {"coordinates":[-103.04222,21.05972],"type":"Point"}
}