{
  "type": "Feature",
  "properties": {
    "gn:admin1_code":"15",
    "gn:admin2_code":"105",
    "gn:asciiname":"El Manguito",
    "gn:country_code":"MX",
    "gn:dem":444,
    "gn:feature_class":"P",
    "gn:feature_code":"PPL",
    "gn:name":"El Manguito",
    "gn:population":16,
    "gn:timezone":"America/Mexico_City",
    "iso:country":"MX",
    "wof:name":"El Manguito",
    "wof:placetype":"locality",
    "wof:population":16
},
  "geometry": {"coordinates":[-100.23775999999999,18.41812],"type":"Point"}
}