{
  "type": "Feature",
  "properties": {
    "gn:admin1_code":"15.0",
    "gn:admin2_code":"86.0",
    "gn:asciiname":"La Cuerva",
    "gn:country_code":"MX",
    "gn:dem":2864,
    "gn:feature_class":"P",
    "gn:feature_code":"PPL",
    "gn:name":"La Cuerva",
    "gn:population":0,
    "gn:timezone":"America/Mexico_City",
    "iso:country":"MX",
    "name:spa_x_preferred":[
        "La Cuerva"
    ],
    "wof:name":"La Cuerva",
    "wof:placetype":"locality"
},
  "geometry": {"coordinates":[-99.85491,19.0025],"type":"Point"}
}