{
  "type": "Feature",
  "properties": {
    "gn:admin1_code":"22.0",
    "gn:admin2_code":"5.0",
    "gn:asciiname":"El Lindero",
    "gn:country_code":"MX",
    "gn:dem":1961,
    "gn:feature_class":"P",
    "gn:feature_code":"PPL",
    "gn:name":"El Lindero",
    "gn:population":0,
    "gn:timezone":"America/Mexico_City",
    "iso:country":"MX",
    "name:und_x_variant":[
        "Lindero",
        "Linderos",
        "El Lindero"
    ],
    "wof:name":"El Lindero",
    "wof:placetype":"locality"
},
  "geometry": {"coordinates":[-100.03335,20.74616],"type":"Point"}
}