{
  "type": "Feature",
  "properties": {
    "gn:admin1_code":"25",
    "gn:admin2_code":"8.0",
    "gn:asciiname":"Nuevo Tecuyo",
    "gn:country_code":"MX",
    "gn:dem":51,
    "gn:feature_class":"P",
    "gn:feature_code":"PPL",
    "gn:name":"Nuevo Tecuyo",
    "gn:population":0,
    "gn:timezone":"America/Mazatlan",
    "iso:country":"MX",
    "name:spa_x_preferred":[
        "Nuevo Tecuyo"
    ],
    "name:spa_x_variant":[
        "Tepalcate"
    ],
    "wof:name":"Nuevo Tecuyo",
    "wof:placetype":"locality"
},
  "geometry": {"coordinates":[-106.72772999999999,23.92266],"type":"Point"}
}