{
  "type": "Feature",
  "properties": {
    "gn:admin1_code":"30",
    "gn:admin2_code":"144.0",
    "gn:asciiname":"El Jaibolito",
    "gn:country_code":"MX",
    "gn:dem":72,
    "gn:feature_class":"P",
    "gn:feature_code":"PPL",
    "gn:name":"El Jaibolito",
    "gn:population":8,
    "gn:timezone":"America/Mexico_City",
    "iso:country":"MX",
    "wof:name":"El Jaibolito",
    "wof:placetype":"locality",
    "wof:population":8
},
  "geometry": {"coordinates":[-94.98389,17.85027999999999],"type":"Point"}
}