{
  "type": "Feature",
  "properties": {
    "gn:admin1_code":"12",
    "gn:admin2_code":"21.0",
    "gn:asciiname":"Colonia Brasilia",
    "gn:country_code":"MX",
    "gn:dem":33,
    "gn:feature_class":"P",
    "gn:feature_code":"PPL",
    "gn:name":"Colonia Brasilia",
    "gn:population":387,
    "gn:timezone":"America/Mexico_City",
    "iso:country":"MX",
    "wof:name":"Colonia Brasilia",
    "wof:placetype":"locality",
    "wof:population":387
},
  "geometry": {"coordinates":[-99.99250000000001,16.96722],"type":"Point"}
}