{
  "type": "Feature",
  "properties": {
    "gn:admin1_code":"20",
    "gn:admin2_code":"326.0",
    "gn:asciiname":"El Retumbadero",
    "gn:country_code":"MX",
    "gn:dem":1349,
    "gn:feature_class":"P",
    "gn:feature_code":"PPL",
    "gn:name":"El Retumbadero",
    "gn:population":162,
    "gn:timezone":"America/Mexico_City",
    "iso:country":"MX",
    "wof:name":"El Retumbadero",
    "wof:placetype":"locality",
    "wof:population":162
},
  "geometry": {"coordinates":[-96.65056,17.80389],"type":"Point"}
}