{
  "type": "Feature",
  "properties": {
    "gn:admin1_code":"31",
    "gn:admin2_code":"87.0",
    "gn:asciiname":"Chen Luk",
    "gn:country_code":"MX",
    "gn:dem":7,
    "gn:feature_class":"P",
    "gn:feature_code":"PPL",
    "gn:name":"Chen Luk",
    "gn:population":0,
    "gn:timezone":"America/Merida",
    "iso:country":"MX",
    "name:spa_x_preferred":[
        "Chenlu"
    ],
    "name:spa_x_variant":[
        "Chen Luk"
    ],
    "wof:name":"Chen Luk",
    "wof:placetype":"locality"
},
  "geometry": {"coordinates":[-90.00785,20.95562],"type":"Point"}
}