{
  "type": "Feature",
  "properties": {
    "gn:admin1_code":"10.0",
    "gn:admin2_code":"5.0",
    "gn:asciiname":"San Diego del Ojo",
    "gn:country_code":"MX",
    "gn:dem":1927,
    "gn:feature_class":"P",
    "gn:feature_code":"PPL",
    "gn:name":"San Diego del Ojo",
    "gn:population":0,
    "gn:timezone":"America/Monterrey",
    "iso:country":"MX",
    "name:spa_x_preferred":[
        "San Diego del Ojo"
    ],
    "wof:name":"San Diego del Ojo",
    "wof:placetype":"locality"
},
  "geometry": {"coordinates":[-104.20816000000001,24.15645],"type":"Point"}
}