{
  "type": "Feature",
  "properties": {
    "gn:admin1_code":"6",
    "gn:admin2_code":"7.0",
    "gn:asciiname":"Baquiriachi",
    "gn:country_code":"MX",
    "gn:dem":2434,
    "gn:feature_class":"P",
    "gn:feature_code":"PPL",
    "gn:name":"Baquiriachi",
    "gn:population":0,
    "gn:timezone":"America/Chihuahua",
    "iso:country":"MX",
    "name:spa_x_preferred":[
        "Baquiriachi"
    ],
    "wof:name":"Baquiriachi",
    "wof:placetype":"locality"
},
  "geometry": {"coordinates":[-106.76788999999999,26.69035],"type":"Point"}
}