{
  "type": "Feature",
  "properties": {
    "gn:admin1_code":"5",
    "gn:admin2_code":"2",
    "gn:asciiname":"Dolores Buenavista",
    "gn:country_code":"MX",
    "gn:dem":455,
    "gn:feature_class":"P",
    "gn:feature_code":"PPL",
    "gn:name":"Dolores Buenavista",
    "gn:population":13,
    "gn:timezone":"America/Mexico_City",
    "iso:country":"MX",
    "wof:name":"Dolores Buenavista",
    "wof:placetype":"locality",
    "wof:population":13
},
  "geometry": {"coordinates":[-92.92,16.56889],"type":"Point"}
}