{
  "type": "Feature",
  "properties": {
    "gn:admin1_code":"21",
    "gn:admin2_code":"195",
    "gn:asciiname":"Alzoquitzintle",
    "gn:country_code":"MX",
    "gn:dem":2654,
    "gn:feature_class":"P",
    "gn:feature_code":"PPL",
    "gn:name":"Alzoquitzintle",
    "gn:population":12,
    "gn:timezone":"America/Mexico_City",
    "iso:country":"MX",
    "wof:name":"Alzoquitzintle",
    "wof:placetype":"locality",
    "wof:population":12
},
  "geometry": {"coordinates":[-97.18214999999999,18.56295],"type":"Point"}
}