{
  "type": "Feature",
  "properties": {
    "gn:admin1_code":"12",
    "gn:admin2_code":"78.0",
    "gn:asciiname":"San Miguel Amoltepec Viejo",
    "gn:country_code":"MX",
    "gn:dem":2205,
    "gn:feature_class":"P",
    "gn:feature_code":"PPL",
    "gn:name":"San Miguel Amoltepec Viejo",
    "gn:population":211,
    "gn:timezone":"America/Mexico_City",
    "iso:country":"MX",
    "wof:name":"San Miguel Amoltepec Viejo",
    "wof:placetype":"locality",
    "wof:population":211
},
  "geometry": {"coordinates":[-98.50536,17.21365],"type":"Point"}
}