{
  "type": "Feature",
  "properties": {
    "gn:admin1_code":"30",
    "gn:admin2_code":"141.0",
    "gn:asciiname":"Roberto Enriquez Ruiz",
    "gn:country_code":"MX",
    "gn:dem":226,
    "gn:feature_class":"P",
    "gn:feature_code":"PPL",
    "gn:name":"Roberto Enr\u00edquez Ruiz",
    "gn:population":234,
    "gn:timezone":"America/Mexico_City",
    "iso:country":"MX",
    "name:und_x_variant":[
        "Roberto Enr\u00edquez Ruiz"
    ],
    "wof:name":"Roberto Enriquez Ruiz",
    "wof:placetype":"locality",
    "wof:population":234
},
  "geometry": {"coordinates":[-95.17556,18.41333],"type":"Point"}
}