{
  "type": "Feature",
  "properties": {
    "gn:admin1_code":"11",
    "gn:admin2_code":"20.0",
    "gn:asciiname":"El Molino Viejo",
    "gn:country_code":"MX",
    "gn:dem":2237,
    "gn:feature_class":"P",
    "gn:feature_code":"PPL",
    "gn:name":"El Molino Viejo",
    "gn:population":5,
    "gn:timezone":"America/Mexico_City",
    "iso:country":"MX",
    "wof:name":"El Molino Viejo",
    "wof:placetype":"locality",
    "wof:population":5
},
  "geometry": {"coordinates":[-101.42694,21.22028],"type":"Point"}
}