{
  "type": "Feature",
  "properties": {
    "gn:admin1_code":"26",
    "gn:admin2_code":"55",
    "gn:asciiname":"Don Porfirio",
    "gn:country_code":"MX",
    "gn:dem":16,
    "gn:feature_class":"P",
    "gn:feature_code":"PPL",
    "gn:name":"Don Porfirio",
    "gn:population":11,
    "gn:timezone":"America/Hermosillo",
    "iso:country":"MX",
    "wof:name":"Don Porfirio",
    "wof:placetype":"locality",
    "wof:population":11
},
  "geometry": {"coordinates":[-114.95860999999999,32.24861],"type":"Point"}
}