{
  "type": "Feature",
  "properties": {
    "gn:admin1_code":"20",
    "gn:admin2_code":"50.0",
    "gn:asciiname":"El Carrizal (Loma Tichi)",
    "gn:country_code":"MX",
    "gn:dem":2226,
    "gn:feature_class":"P",
    "gn:feature_code":"PPL",
    "gn:name":"El Carrizal (Loma Tichi)",
    "gn:population":90,
    "gn:timezone":"America/Mexico_City",
    "iso:country":"MX",
    "wof:name":"El Carrizal (Loma Tichi)",
    "wof:placetype":"locality",
    "wof:population":90
},
  "geometry": {"coordinates":[-97.57778,17.24944],"type":"Point"}
}