{
  "type": "Feature",
  "properties": {
    "gn:admin1_code":"14",
    "gn:admin2_code":"118.0",
    "gn:asciiname":"Palmarejillo",
    "gn:country_code":"MX",
    "gn:dem":2343,
    "gn:feature_class":"P",
    "gn:feature_code":"PPL",
    "gn:name":"Palmarejillo",
    "gn:population":7,
    "gn:timezone":"America/Mexico_City",
    "iso:country":"MX",
    "wof:name":"Palmarejillo",
    "wof:placetype":"locality",
    "wof:population":7
},
  "geometry": {"coordinates":[-103.06944,21.19889],"type":"Point"}
}