{
  "type": "Feature",
  "properties": {
    "gn:admin1_code":"15",
    "gn:admin2_code":"8",
    "gn:asciiname":"Tezululoma (Teshululoma)",
    "gn:country_code":"MX",
    "gn:dem":1075,
    "gn:feature_class":"P",
    "gn:feature_code":"PPL",
    "gn:name":"Tezululoma (Teshululoma)",
    "gn:population":25,
    "gn:timezone":"America/Mexico_City",
    "iso:country":"MX",
    "wof:name":"Tezululoma (Teshululoma)",
    "wof:placetype":"locality",
    "wof:population":25
},
  "geometry": {"coordinates":[-100.18563,18.78562],"type":"Point"}
}