{
  "type": "Feature",
  "properties": {
    "gn:admin1_code":"5",
    "gn:admin2_code":"40.0",
    "gn:asciiname":"Francisco I. Madero",
    "gn:country_code":"MX",
    "gn:dem":15,
    "gn:feature_class":"P",
    "gn:feature_code":"PPL",
    "gn:name":"Francisco I. Madero",
    "gn:population":1804,
    "gn:timezone":"America/Mexico_City",
    "iso:country":"MX",
    "name:spa_x_preferred":[
        "Francisco I. Madero"
    ],
    "wof:name":"Francisco I. Madero",
    "wof:placetype":"locality",
    "wof:population":1804
},
  "geometry": {"coordinates":[-92.54434999999999,15.06996],"type":"Point"}
}