{
  "type": "Feature",
  "properties": {
    "gn:admin1_code":"24",
    "gn:admin2_code":"21",
    "gn:asciiname":"Roman Hernandez Jacobo",
    "gn:country_code":"MX",
    "gn:dem":2064,
    "gn:feature_class":"P",
    "gn:feature_code":"PPL",
    "gn:name":"Rom\u00e1n Hern\u00e1ndez Jacobo",
    "gn:population":10,
    "gn:timezone":"America/Mexico_City",
    "iso:country":"MX",
    "name:und_x_variant":[
        "Rom\u00e1n Hern\u00e1ndez Jacobo"
    ],
    "wof:name":"Roman Hernandez Jacobo",
    "wof:placetype":"locality",
    "wof:population":10
},
  "geometry": {"coordinates":[-101.13833,22.27417],"type":"Point"}
}