{
  "type": "Feature",
  "properties": {
    "gn:admin1_code":"7",
    "gn:admin2_code":"17.0",
    "gn:asciiname":"El Rosario",
    "gn:country_code":"MX",
    "gn:dem":1117,
    "gn:feature_class":"P",
    "gn:feature_code":"PPL",
    "gn:name":"El Rosario",
    "gn:population":4,
    "gn:timezone":"America/Monterrey",
    "iso:country":"MX",
    "wof:name":"El Rosario",
    "wof:placetype":"locality",
    "wof:population":4
},
  "geometry": {"coordinates":[-103.24563000000001,25.69388],"type":"Point"}
}