{
  "type": "Feature",
  "properties": {
    "gn:admin1_code":"12.0",
    "gn:asciiname":"Xaha Kava Yaa",
    "gn:country_code":"MX",
    "gn:dem":1557,
    "gn:feature_class":"P",
    "gn:feature_code":"PPL",
    "gn:name":"Xaha Kava Yaa",
    "gn:population":0,
    "gn:timezone":"America/Mexico_City",
    "iso:country":"MX",
    "name:spa_x_preferred":[
        "Xaha Kava Yaa"
    ],
    "wof:name":"Xaha Kava Yaa",
    "wof:placetype":"locality"
},
  "geometry": {"coordinates":[-98.36478,17.1335],"type":"Point"}
}