{
  "type": "Feature",
  "properties": {
    "gn:admin1_code":"14",
    "gn:admin2_code":"13",
    "gn:asciiname":"El Saucillo",
    "gn:country_code":"MX",
    "gn:dem":1946,
    "gn:feature_class":"P",
    "gn:feature_code":"PPL",
    "gn:name":"El Saucillo",
    "gn:population":12,
    "gn:timezone":"America/Mexico_City",
    "iso:country":"MX",
    "wof:name":"El Saucillo",
    "wof:placetype":"locality",
    "wof:population":12
},
  "geometry": {"coordinates":[-102.49972,20.63083],"type":"Point"}
}