{
  "type": "Feature",
  "properties": {
    "gn:admin1_code":"26",
    "gn:admin2_code":"67.0",
    "gn:asciiname":"Cruz de Canada",
    "gn:country_code":"MX",
    "gn:dem":871,
    "gn:feature_class":"P",
    "gn:feature_code":"PPL",
    "gn:name":"Cruz de Ca\u00f1ada",
    "gn:population":0,
    "gn:timezone":"America/Hermosillo",
    "iso:country":"MX",
    "name:spa_x_preferred":[
        "Cruz de Ca\u00f1ada"
    ],
    "wof:name":"Cruz de Canada",
    "wof:placetype":"locality"
},
  "geometry": {"coordinates":[-109.45891,30.3092],"type":"Point"}
}