{
  "type": "Feature",
  "properties": {
    "gn:admin1_code":"20",
    "gn:admin2_code":"58.0",
    "gn:asciiname":"Durazno (5 de Mayo)",
    "gn:country_code":"MX",
    "gn:dem":1663,
    "gn:feature_class":"P",
    "gn:feature_code":"PPL",
    "gn:name":"Durazno (5 de Mayo)",
    "gn:population":86,
    "gn:timezone":"America/Mexico_City",
    "iso:country":"MX",
    "wof:name":"Durazno (5 de Mayo)",
    "wof:placetype":"locality",
    "wof:population":86
},
  "geometry": {"coordinates":[-96.95611,17.97],"type":"Point"}
}