{
  "type": "Feature",
  "properties": {
    "gn:admin1_code":"21",
    "gn:admin2_code":"208.0",
    "gn:asciiname":"Coyotepec",
    "gn:country_code":"MX",
    "gn:dem":2114,
    "gn:feature_class":"P",
    "gn:feature_code":"PPL",
    "gn:name":"Coyotepec",
    "gn:population":7,
    "gn:timezone":"America/Mexico_City",
    "iso:country":"MX",
    "wof:name":"Coyotepec",
    "wof:placetype":"locality",
    "wof:population":7
},
  "geometry": {"coordinates":[-97.97162,19.95282000000001],"type":"Point"}
}