{
  "type": "Feature",
  "properties": {
    "gn:admin1_code":"16",
    "gn:admin2_code":"76.0",
    "gn:asciiname":"Colonia Independencia (Coyacho)",
    "gn:country_code":"MX",
    "gn:dem":1553,
    "gn:feature_class":"P",
    "gn:feature_code":"PPL",
    "gn:name":"Colonia Independencia (Coyacho)",
    "gn:population":473,
    "gn:timezone":"America/Mexico_City",
    "iso:country":"MX",
    "wof:name":"Colonia Independencia (Coyacho)",
    "wof:placetype":"locality",
    "wof:population":473
},
  "geometry": {"coordinates":[-102.72360999999999,20.00528],"type":"Point"}
}