{
  "type": "Feature",
  "properties": {
    "gn:admin1_code":"13",
    "gn:admin2_code":"22.0",
    "gn:asciiname":"Jometitlan",
    "gn:country_code":"MX",
    "gn:dem":2405,
    "gn:feature_class":"P",
    "gn:feature_code":"PPL",
    "gn:name":"Jometitl\u00e1n",
    "gn:population":0,
    "gn:timezone":"America/Mexico_City",
    "iso:country":"MX",
    "name:spa_x_preferred":[
        "Jometitl\u00e1n"
    ],
    "wof:name":"Jometitlan",
    "wof:placetype":"locality"
},
  "geometry": {"coordinates":[-98.65300999999999,19.98948],"type":"Point"}
}