{
  "type": "Feature",
  "properties": {
    "gn:admin1_code":"14.0",
    "gn:admin2_code":"69.0",
    "gn:asciiname":"Juaguique",
    "gn:country_code":"MX",
    "gn:dem":1380,
    "gn:feature_class":"P",
    "gn:feature_code":"PPL",
    "gn:name":"Juaguique",
    "gn:population":0,
    "gn:timezone":"America/Mexico_City",
    "iso:country":"MX",
    "name:spa_x_preferred":[
        "Juaguique"
    ],
    "wof:name":"Juaguique",
    "wof:placetype":"locality"
},
  "geometry": {"coordinates":[-102.85777,19.72976],"type":"Point"}
}