{
  "type": "Feature",
  "properties": {
    "gn:admin1_code":"18",
    "gn:admin2_code":"20",
    "gn:asciiname":"Las Amapas (Pontoque)",
    "gn:country_code":"MX",
    "gn:dem":21,
    "gn:feature_class":"P",
    "gn:feature_code":"PPL",
    "gn:name":"Las Amapas (Pontoque)",
    "gn:population":23,
    "gn:timezone":"America/Bahia_Banderas",
    "iso:country":"MX",
    "wof:name":"Las Amapas (Pontoque)",
    "wof:placetype":"locality",
    "wof:population":23
},
  "geometry": {"coordinates":[-105.46722,20.75917],"type":"Point"}
}