{
  "type": "Feature",
  "properties": {
    "gn:admin1_code":"6",
    "gn:admin2_code":"29",
    "gn:asciiname":"Bajiitos",
    "gn:country_code":"MX",
    "gn:dem":2724,
    "gn:feature_class":"P",
    "gn:feature_code":"PPL",
    "gn:name":"Baji\u00edtos",
    "gn:population":16,
    "gn:timezone":"America/Chihuahua",
    "iso:country":"MX",
    "name:und_x_variant":[
        "Baji\u00edtos"
    ],
    "wof:name":"Bajiitos",
    "wof:placetype":"locality",
    "wof:population":16
},
  "geometry": {"coordinates":[-106.60355,26.21532],"type":"Point"}
}