{
  "type": "Feature",
  "properties": {
    "gn:admin1_code":"23",
    "gn:asciiname":"San Pedro Rompoy",
    "gn:country_code":"MX",
    "gn:dem":99,
    "gn:feature_class":"P",
    "gn:feature_code":"PPL",
    "gn:name":"San Pedro Rompoy",
    "gn:population":0,
    "gn:timezone":"America/Cancun",
    "iso:country":"MX",
    "name:spa_x_preferred":[
        "San Pedro Rompoy"
    ],
    "wof:name":"San Pedro Rompoy",
    "wof:placetype":"locality"
},
  "geometry": {"coordinates":[-89.14799000000002,19.72378],"type":"Point"}
}