{
  "type": "Feature",
  "properties": {
    "gn:admin1_code":"30",
    "gn:admin2_code":"149.0",
    "gn:asciiname":"El Mango",
    "gn:country_code":"MX",
    "gn:dem":248,
    "gn:feature_class":"P",
    "gn:feature_code":"PPL",
    "gn:name":"El Mango",
    "gn:population":0,
    "gn:timezone":"America/Mexico_City",
    "iso:country":"MX",
    "name:spa_x_preferred":[
        "El Mango"
    ],
    "wof:name":"El Mango",
    "wof:placetype":"locality"
},
  "geometry": {"coordinates":[-94.91968,18.16462000000001],"type":"Point"}
}