{
  "type": "Feature",
  "properties": {
    "gn:admin1_code":"5.0",
    "gn:asciiname":"Valle Hermoso",
    "gn:country_code":"MX",
    "gn:dem":838,
    "gn:feature_class":"P",
    "gn:feature_code":"PPL",
    "gn:name":"Valle Hermoso",
    "gn:population":0,
    "gn:timezone":"America/Mexico_City",
    "iso:country":"MX",
    "name:ceb_x_preferred":[
        "Valle Hermoso"
    ],
    "name:deu_x_preferred":[
        "Valle Hermoso"
    ],
    "name:fra_x_preferred":[
        "Valle Hermoso"
    ],
    "name:ita_x_preferred":[
        "Valle Hermoso"
    ],
    "name:rus_x_preferred":[
        "\u0412\u0430\u043b\u044c\u0435-\u042d\u0440\u043c\u043e\u0441\u043e"
    ],
    "name:spa_x_preferred":[
        "Valle Hermoso"
    ],
    "name:swe_x_preferred":[
        "Valle Hermoso"
    ],
    "wof:name":"Valle Hermoso",
    "wof:placetype":"locality"
},
  "geometry": {"coordinates":[-92.58725,15.70954],"type":"Point"}
}