{
  "type": "Feature",
  "properties": {
    "gn:admin1_code":"5.0",
    "gn:asciiname":"Valle Hermoso",
    "gn:country_code":"MX",
    "gn:dem":838,
    "gn:feature_class":"P",
    "gn:feature_code":"PPL",
    "gn:name":"Valle Hermoso",
    "gn:population":0,
    "gn:timezone":"America/Mexico_City",
    "iso:country":"MX",
    "name:spa_x_preferred":[
        "Valle Hermoso"
    ],
    "wof:name":"Valle Hermoso",
    "wof:placetype":"locality"
},
  "geometry": {"coordinates":[-92.58725,15.70954],"type":"Point"}
}