{
  "type": "Feature",
  "properties": {
    "gn:admin1_code":"31",
    "gn:admin2_code":"79.0",
    "gn:asciiname":"Tixcuytun",
    "gn:country_code":"MX",
    "gn:dem":27,
    "gn:feature_class":"P",
    "gn:feature_code":"PPL",
    "gn:name":"Tixcuytun",
    "gn:population":0,
    "gn:timezone":"America/Merida",
    "iso:country":"MX",
    "name:spa_x_preferred":[
        "Tixcuytun"
    ],
    "name:und_x_variant":[
        "Tixcuitum",
        "Tixcuitun",
        "Tixcuyt\u00fan"
    ],
    "wof:name":"Tixcuytun",
    "wof:placetype":"locality"
},
  "geometry": {"coordinates":[-89.20426999999999,20.20921],"type":"Point"}
}