{
  "type": "Feature",
  "properties": {
    "gn:admin1_code":"25",
    "gn:admin2_code":"18.0",
    "gn:asciiname":"Campo la Pequena Joya",
    "gn:country_code":"MX",
    "gn:dem":17,
    "gn:feature_class":"P",
    "gn:feature_code":"PPL",
    "gn:name":"Campo la Peque\u00f1a Joya",
    "gn:population":8,
    "gn:timezone":"America/Mazatlan",
    "iso:country":"MX",
    "name:und_x_variant":[
        "Campo la Peque\u00f1a Joya"
    ],
    "wof:name":"Campo la Pequena Joya",
    "wof:placetype":"locality",
    "wof:population":8
},
  "geometry": {"coordinates":[-107.47306,24.68278],"type":"Point"}
}