{
  "type": "Feature",
  "properties": {
    "gn:admin1_code":"14.0",
    "gn:admin2_code":"4.0",
    "gn:asciiname":"Los Gatos",
    "gn:country_code":"MX",
    "gn:dem":2033,
    "gn:feature_class":"P",
    "gn:feature_code":"PPL",
    "gn:name":"Los Gatos",
    "gn:population":0,
    "gn:timezone":"America/Mexico_City",
    "iso:country":"MX",
    "name:spa_x_preferred":[
        "Los Gatos"
    ],
    "wof:name":"Los Gatos",
    "wof:placetype":"locality"
},
  "geometry": {"coordinates":[-103.66316,19.97129],"type":"Point"}
}