{
  "type": "Feature",
  "properties": {
    "gn:admin1_code":"3",
    "gn:admin2_code":"1.0",
    "gn:asciiname":"Las Perdidas",
    "gn:country_code":"MX",
    "gn:dem":743,
    "gn:feature_class":"P",
    "gn:feature_code":"PPL",
    "gn:name":"Las Perdidas",
    "gn:population":0,
    "gn:timezone":"America/Mazatlan",
    "iso:country":"MX",
    "name:spa_x_preferred":[
        "Las Perdidas"
    ],
    "wof:name":"Las Perdidas",
    "wof:placetype":"locality"
},
  "geometry": {"coordinates":[-112.25341,26.53359],"type":"Point"}
}