{
  "type": "Feature",
  "properties": {
    "gn:admin1_code":"7.0",
    "gn:admin2_code":"20.0",
    "gn:asciiname":"Las Cruces",
    "gn:country_code":"MX",
    "gn:dem":1482,
    "gn:feature_class":"P",
    "gn:feature_code":"PPL",
    "gn:name":"Las Cruces",
    "gn:population":0,
    "gn:timezone":"America/Monterrey",
    "iso:country":"MX",
    "name:ast_x_preferred":[
        "Las Cruces"
    ],
    "name:ben_x_preferred":[
        "\u09b2\u09be\u09b8 \u0995\u09cd\u09b0\u09c1\u09b8\u09c7\u09b8"
    ],
    "name:bre_x_preferred":[
        "Cruces"
    ],
    "name:ceb_x_preferred":[
        "Las Cruces"
    ],
    "name:fra_x_preferred":[
        "Las Cruces"
    ],
    "name:hin_x_preferred":[
        "\u0932\u093e \u0915\u094d\u0930\u0942\u0938\u0947\u0938"
    ],
    "name:ind_x_preferred":[
        "Las Cruces"
    ],
    "name:ita_x_preferred":[
        "Las Cruces"
    ],
    "name:sco_x_preferred":[
        "Las Cruces"
    ],
    "name:spa_x_preferred":[
        "Las Cruces"
    ],
    "name:spa_x_variant":[
        "Cruces"
    ],
    "name:swe_x_preferred":[
        "Las Cruces"
    ],
    "wof:name":"Las Cruces",
    "wof:placetype":"locality"
},
  "geometry": {"coordinates":[-102.49709,28.89021],"type":"Point"}
}