{
  "type": "Feature",
  "properties": {
    "gn:admin1_code":"25",
    "gn:admin2_code":"5.0",
    "gn:asciiname":"Molinitos",
    "gn:country_code":"MX",
    "gn:dem":449,
    "gn:feature_class":"P",
    "gn:feature_code":"PPL",
    "gn:name":"Molinitos",
    "gn:population":0,
    "gn:timezone":"America/Mazatlan",
    "iso:country":"MX",
    "name:spa_x_preferred":[
        "Molinitos"
    ],
    "wof:name":"Molinitos",
    "wof:placetype":"locality"
},
  "geometry": {"coordinates":[-106.70693,24.46432],"type":"Point"}
}