{
  "type": "Feature",
  "properties": {
    "gn:admin1_code":"26.0",
    "gn:admin2_code":"56.0",
    "gn:asciiname":"La Asuncion",
    "gn:country_code":"MX",
    "gn:dem":322,
    "gn:feature_class":"P",
    "gn:feature_code":"PPL",
    "gn:name":"La Asunci\u00f3n",
    "gn:population":0,
    "gn:timezone":"America/Hermosillo",
    "iso:country":"MX",
    "name:spa_x_preferred":[
        "La Asunci\u00f3n"
    ],
    "wof:name":"La Asuncion",
    "wof:placetype":"locality"
},
  "geometry": {"coordinates":[-110.88988999999999,29.34401],"type":"Point"}
}