{
  "type": "Feature",
  "properties": {
    "gn:admin1_code":"11.0",
    "gn:asciiname":"El Zamorano",
    "gn:country_code":"MX",
    "gn:dem":3347,
    "gn:feature_class":"P",
    "gn:feature_code":"PPL",
    "gn:name":"El Zamorano",
    "gn:population":0,
    "gn:timezone":"America/Mexico_City",
    "iso:country":"MX",
    "name:spa_x_preferred":[
        "El Zamorano"
    ],
    "wof:name":"El Zamorano",
    "wof:placetype":"locality"
},
  "geometry": {"coordinates":[-100.18038,20.93297],"type":"Point"}
}