{
  "type": "Feature",
  "properties": {
    "gn:admin1_code":"27",
    "gn:admin2_code":"12.0",
    "gn:asciiname":"El Reventon",
    "gn:country_code":"MX",
    "gn:dem":30,
    "gn:feature_class":"P",
    "gn:feature_code":"PPL",
    "gn:name":"El Revent\u00f3n",
    "gn:population":65,
    "gn:timezone":"America/Mexico_City",
    "iso:country":"MX",
    "name:und_x_variant":[
        "El Revent\u00f3n"
    ],
    "wof:name":"El Reventon",
    "wof:placetype":"locality",
    "wof:population":65
},
  "geometry": {"coordinates":[-92.54833000000001,17.84667],"type":"Point"}
}