{
  "type": "Feature",
  "properties": {
    "gn:admin1_code":"5",
    "gn:admin2_code":"65",
    "gn:asciiname":"San Jesus",
    "gn:country_code":"MX",
    "gn:dem":153,
    "gn:feature_class":"P",
    "gn:feature_code":"PPL",
    "gn:name":"San Jes\u00fas",
    "gn:population":10,
    "gn:timezone":"America/Mexico_City",
    "iso:country":"MX",
    "name:und_x_variant":[
        "San Jes\u00fas"
    ],
    "wof:name":"San Jesus",
    "wof:placetype":"locality",
    "wof:population":10
},
  "geometry": {"coordinates":[-91.68583,17.38639],"type":"Point"}
}