{
  "type": "Feature",
  "properties": {
    "gn:admin1_code":"12",
    "gn:admin2_code":"57.0",
    "gn:asciiname":"Rancho los Armadillos",
    "gn:country_code":"MX",
    "gn:dem":546,
    "gn:feature_class":"P",
    "gn:feature_code":"PPL",
    "gn:name":"Rancho los Armadillos",
    "gn:population":5,
    "gn:timezone":"America/Mexico_City",
    "iso:country":"MX",
    "wof:name":"Rancho los Armadillos",
    "wof:placetype":"locality",
    "wof:population":5
},
  "geometry": {"coordinates":[-100.60917999999999,17.47107],"type":"Point"}
}