{
  "type": "Feature",
  "properties": {
    "gn:admin1_code":"13",
    "gn:admin2_code":"58.0",
    "gn:asciiname":"La Candelaria",
    "gn:country_code":"MX",
    "gn:dem":1675,
    "gn:feature_class":"P",
    "gn:feature_code":"PPL",
    "gn:name":"La Candelaria",
    "gn:population":0,
    "gn:timezone":"America/Mexico_City",
    "iso:country":"MX",
    "name:ceb_x_preferred":[
        "La Candelaria"
    ],
    "name:deu_x_preferred":[
        "La Candelaria"
    ],
    "name:epo_x_preferred":[
        "La Candelaria"
    ],
    "name:fra_x_preferred":[
        "La Candelaria"
    ],
    "name:glg_x_preferred":[
        "La Candelaria"
    ],
    "name:ita_x_preferred":[
        "La Candelaria"
    ],
    "name:msa_x_preferred":[
        "La Candelaria"
    ],
    "name:nor_x_preferred":[
        "La Candelaria"
    ],
    "name:por_x_preferred":[
        "La Candelaria"
    ],
    "name:spa_x_preferred":[
        "La Candelapa"
    ],
    "name:spa_x_variant":[
        "La Candelaria"
    ],
    "wof:name":"La Candelaria",
    "wof:placetype":"locality"
},
  "geometry": {"coordinates":[-99.30864,20.56566],"type":"Point"}
}