{
  "type": "Feature",
  "properties": {
    "gn:admin1_code":"5",
    "gn:admin2_code":"6",
    "gn:asciiname":"San Jose de los Pozos",
    "gn:country_code":"MX",
    "gn:dem":2037,
    "gn:feature_class":"P",
    "gn:feature_code":"PPL",
    "gn:name":"San Jos\u00e9 de los Pozos",
    "gn:population":31,
    "gn:timezone":"America/Mexico_City",
    "iso:country":"MX",
    "name:und_x_variant":[
        "San Jos\u00e9 de los Pozos"
    ],
    "wof:name":"San Jose de los Pozos",
    "wof:placetype":"locality",
    "wof:population":31
},
  "geometry": {"coordinates":[-92.06167000000001,15.52944],"type":"Point"}
}