{
  "type": "Feature",
  "properties": {
    "gn:admin1_code":"11",
    "gn:admin2_code":"16.0",
    "gn:asciiname":"Granja la Joya",
    "gn:country_code":"MX",
    "gn:dem":1722,
    "gn:feature_class":"P",
    "gn:feature_code":"PPL",
    "gn:name":"Granja la Joya",
    "gn:population":7,
    "gn:timezone":"America/Mexico_City",
    "iso:country":"MX",
    "wof:name":"Granja la Joya",
    "wof:placetype":"locality",
    "wof:population":7
},
  "geometry": {"coordinates":[-101.48860999999999,20.34917],"type":"Point"}
}