{
  "type": "Feature",
  "properties": {
    "gn:admin1_code":"5",
    "gn:admin2_code":"59.0",
    "gn:asciiname":"Nuevo Guadalupe el Silencio",
    "gn:country_code":"MX",
    "gn:dem":712,
    "gn:feature_class":"P",
    "gn:feature_code":"PPL",
    "gn:name":"Nuevo Guadalupe el Silencio",
    "gn:population":111,
    "gn:timezone":"America/Mexico_City",
    "iso:country":"MX",
    "wof:name":"Nuevo Guadalupe el Silencio",
    "wof:placetype":"locality",
    "wof:population":111
},
  "geometry": {"coordinates":[-91.72499999999999,16.92972],"type":"Point"}
}