{
  "type": "Feature",
  "properties": {
    "gn:admin1_code":"26",
    "gn:admin2_code":"68.0",
    "gn:asciiname":"Canori",
    "gn:country_code":"MX",
    "gn:dem":776,
    "gn:feature_class":"P",
    "gn:feature_code":"PPL",
    "gn:name":"Canori",
    "gn:population":0,
    "gn:timezone":"America/Hermosillo",
    "iso:country":"MX",
    "name:spa_x_preferred":[
        "Canori"
    ],
    "wof:name":"Canori",
    "wof:placetype":"locality"
},
  "geometry": {"coordinates":[-109.94667,29.10833],"type":"Point"}
}