{
  "type": "Feature",
  "properties": {
    "gn:admin1_code":"32",
    "gn:admin2_code":"44.0",
    "gn:asciiname":"Remudadero de Arriba",
    "gn:country_code":"MX",
    "gn:dem":1484,
    "gn:feature_class":"P",
    "gn:feature_code":"PPL",
    "gn:name":"Remudadero de Arriba",
    "gn:population":97,
    "gn:timezone":"America/Mexico_City",
    "iso:country":"MX",
    "wof:name":"Remudadero de Arriba",
    "wof:placetype":"locality",
    "wof:population":97
},
  "geometry": {"coordinates":[-102.92870000000001,21.82512],"type":"Point"}
}