{
  "type": "Feature",
  "properties": {
    "gn:admin1_code":"12",
    "gn:admin2_code":"32.0",
    "gn:asciiname":"Las Joyas",
    "gn:country_code":"MX",
    "gn:dem":1532,
    "gn:feature_class":"P",
    "gn:feature_code":"PPL",
    "gn:name":"Las Joyas",
    "gn:population":5,
    "gn:timezone":"America/Mexico_City",
    "iso:country":"MX",
    "wof:name":"Las Joyas",
    "wof:placetype":"locality",
    "wof:population":5
},
  "geometry": {"coordinates":[-99.93746,17.7489],"type":"Point"}
}