{
  "type": "Feature",
  "properties": {
    "gn:admin1_code":"26",
    "gn:admin2_code":"26.0",
    "gn:asciiname":"Rochin (Establo los Datiles)",
    "gn:country_code":"MX",
    "gn:dem":19,
    "gn:feature_class":"P",
    "gn:feature_code":"PPL",
    "gn:name":"Roch\u00edn (Establo los D\u00e1tiles)",
    "gn:population":9,
    "gn:timezone":"America/Hermosillo",
    "iso:country":"MX",
    "name:und_x_variant":[
        "Roch\u00edn (Establo los D\u00e1tiles)"
    ],
    "wof:name":"Rochin (Establo los Datiles)",
    "wof:placetype":"locality",
    "wof:population":9
},
  "geometry": {"coordinates":[-109.66333,27.00444],"type":"Point"}
}