{
  "type": "Feature",
  "properties": {
    "gn:admin1_code":"6.0",
    "gn:admin2_code":"15.0",
    "gn:asciiname":"El Cuatro",
    "gn:country_code":"MX",
    "gn:dem":1547,
    "gn:feature_class":"P",
    "gn:feature_code":"PPL",
    "gn:name":"El Cuatro",
    "gn:population":0,
    "gn:timezone":"America/Chihuahua",
    "iso:country":"MX",
    "name:und_x_variant":[
        "Rancho El Cuatro",
        "El Cuatro"
    ],
    "wof:name":"El Cuatro",
    "wof:placetype":"locality"
},
  "geometry": {"coordinates":[-105.32038,29.9503],"type":"Point"}
}