{
  "type": "Feature",
  "properties": {
    "gn:admin1_code":"14",
    "gn:admin2_code":"61.0",
    "gn:asciiname":"La Capilla",
    "gn:country_code":"MX",
    "gn:dem":2167,
    "gn:feature_class":"P",
    "gn:feature_code":"PPL",
    "gn:name":"La Capilla",
    "gn:population":6,
    "gn:timezone":"America/Mexico_City",
    "iso:country":"MX",
    "name:ceb_x_preferred":[
        "La Capilla"
    ],
    "name:fra_x_preferred":[
        "La Capilla"
    ],
    "name:ita_x_preferred":[
        "La Capilla"
    ],
    "name:kat_x_preferred":[
        "\u10da\u10d0-\u10d9\u10d0\u10de\u10d8\u10da\u10d8\u10d0"
    ],
    "name:msa_x_preferred":[
        "La Capilla"
    ],
    "name:nld_x_preferred":[
        "La Capilla"
    ],
    "name:por_x_preferred":[
        "La Capilla"
    ],
    "name:rus_x_preferred":[
        "\u041b\u0430-\u041a\u0430\u043f\u0438\u043b\u044c\u044f"
    ],
    "name:spa_x_preferred":[
        "La Capilla"
    ],
    "name:swe_x_preferred":[
        "La Capilla"
    ],
    "name:tgl_x_preferred":[
        "La Capilla"
    ],
    "name:urd_x_preferred":[
        "\u0644\u0627 \u06a9\u0627\u067e\u06cc\u0644\u0627"
    ],
    "name:vie_x_preferred":[
        "La Capilla"
    ],
    "name:war_x_preferred":[
        "La Capilla"
    ],
    "name:zho_x_preferred":[
        "\u62c9\u5361\u76ae\u4e9e"
    ],
    "wof:name":"La Capilla",
    "wof:placetype":"locality",
    "wof:population":6
},
  "geometry": {"coordinates":[-104.08278,22.21],"type":"Point"}
}