{
  "type": "Feature",
  "properties": {
    "gn:admin1_code":"14",
    "gn:admin2_code":"44.0",
    "gn:asciiname":"Las Humedades",
    "gn:country_code":"MX",
    "gn:dem":1546,
    "gn:feature_class":"P",
    "gn:feature_code":"PPL",
    "gn:name":"Las Humedades",
    "gn:population":6,
    "gn:timezone":"America/Mexico_City",
    "iso:country":"MX",
    "wof:name":"Las Humedades",
    "wof:placetype":"locality",
    "wof:population":6
},
  "geometry": {"coordinates":[-103.21389000000001,20.3975],"type":"Point"}
}