{
  "type": "Feature",
  "properties": {
    "gn:admin1_code":"23.0",
    "gn:admin2_code":"4.0",
    "gn:asciiname":"Los Cascos",
    "gn:country_code":"MX",
    "gn:dem":17,
    "gn:feature_class":"P",
    "gn:feature_code":"PPL",
    "gn:name":"Los Cascos",
    "gn:population":3,
    "gn:timezone":"America/Cancun",
    "iso:country":"MX",
    "name:spa_x_preferred":[
        "Los Cascos"
    ],
    "wof:name":"Los Cascos",
    "wof:placetype":"locality",
    "wof:population":3
},
  "geometry": {"coordinates":[-88.38611,18.96639],"type":"Point"}
}