{
  "type": "Feature",
  "properties": {
    "gn:admin1_code":"7.0",
    "gn:admin2_code":"28.0",
    "gn:asciiname":"Los Arizpes",
    "gn:country_code":"MX",
    "gn:dem":340,
    "gn:feature_class":"P",
    "gn:feature_code":"PPL",
    "gn:name":"Los Arizpes",
    "gn:population":0,
    "gn:timezone":"America/Monterrey",
    "iso:country":"MX",
    "name:spa_x_preferred":[
        "Los Arizpes"
    ],
    "wof:name":"Los Arizpes",
    "wof:placetype":"locality"
},
  "geometry": {"coordinates":[-101.09206,27.8528],"type":"Point"}
}