{
  "type": "Feature",
  "properties": {
    "gn:admin1_code":"27",
    "gn:admin2_code":"11.0",
    "gn:asciiname":"Federico Alvarez Segunda Seccion",
    "gn:country_code":"MX",
    "gn:dem":4,
    "gn:feature_class":"P",
    "gn:feature_code":"PPL",
    "gn:name":"Federico \u00c1lvarez Segunda Secci\u00f3n",
    "gn:population":0,
    "gn:timezone":"America/Mexico_City",
    "iso:country":"MX",
    "name:spa_x_preferred":[
        "Federico \u00c1lvarez Segunda Secci\u00f3n"
    ],
    "wof:name":"Federico Alvarez Segunda Seccion",
    "wof:placetype":"locality"
},
  "geometry": {"coordinates":[-92.17586,18.02184],"type":"Point"}
}