{
  "type": "Feature",
  "properties": {
    "gn:admin1_code":"6.0",
    "gn:admin2_code":"44.0",
    "gn:asciiname":"Rancho de Enmedio",
    "gn:country_code":"MX",
    "gn:dem":1701,
    "gn:feature_class":"P",
    "gn:feature_code":"PPL",
    "gn:name":"Rancho de Enmedio",
    "gn:population":0,
    "gn:timezone":"America/Chihuahua",
    "iso:country":"MX",
    "name:spa_x_preferred":[
        "Rancho de Enmedio"
    ],
    "name:und_x_variant":[
        "Rancho En Medio",
        "De Enmedio",
        "Enmedio"
    ],
    "wof:name":"Rancho de Enmedio",
    "wof:placetype":"locality"
},
  "geometry": {"coordinates":[-105.53488,26.77789000000001],"type":"Point"}
}