{
  "type": "Feature",
  "properties": {
    "gn:admin1_code":"26",
    "gn:admin2_code":"64.0",
    "gn:asciiname":"San Agustin",
    "gn:country_code":"MX",
    "gn:dem":607,
    "gn:feature_class":"P",
    "gn:feature_code":"PPL",
    "gn:name":"San Agust\u00edn",
    "gn:population":0,
    "gn:timezone":"America/Hermosillo",
    "iso:country":"MX",
    "name:spa_x_preferred":[
        "San Agust\u00edn"
    ],
    "name:und_x_variant":[
        "Rancho San August\u00edn"
    ],
    "wof:name":"San Agustin",
    "wof:placetype":"locality"
},
  "geometry": {"coordinates":[-111.42037999999999,30.61127],"type":"Point"}
}