{
  "type": "Feature",
  "properties": {
    "gn:admin1_code":"30",
    "gn:admin2_code":"63.0",
    "gn:asciiname":"Juan N. Troncoso",
    "gn:country_code":"MX",
    "gn:dem":626,
    "gn:feature_class":"P",
    "gn:feature_code":"PPL",
    "gn:name":"Juan N. Troncoso",
    "gn:population":0,
    "gn:timezone":"America/Mexico_City",
    "iso:country":"MX",
    "name:und_x_variant":[
        "Juan N. Tloncoso",
        "San Juan Otontepec"
    ],
    "wof:name":"Juan N. Troncoso",
    "wof:placetype":"locality"
},
  "geometry": {"coordinates":[-97.90461000000001,21.23603],"type":"Point"}
}