{
  "type": "Feature",
  "properties": {
    "gn:admin1_code":"30",
    "gn:admin2_code":"86.0",
    "gn:asciiname":"Xalatahui",
    "gn:country_code":"MX",
    "gn:dem":2700,
    "gn:feature_class":"P",
    "gn:feature_code":"PPL",
    "gn:name":"Xalatahu\u00ed",
    "gn:population":0,
    "gn:timezone":"America/Mexico_City",
    "iso:country":"MX",
    "name:spa_x_preferred":[
        "Xalatahu\u00ed"
    ],
    "wof:name":"Xalatahui",
    "wof:placetype":"locality"
},
  "geometry": {"coordinates":[-97.35632,19.64586],"type":"Point"}
}