{
  "type": "Feature",
  "properties": {
    "gn:admin1_code":"16.0",
    "gn:admin2_code":"64.0",
    "gn:asciiname":"Los Nopales",
    "gn:country_code":"MX",
    "gn:dem":417,
    "gn:feature_class":"P",
    "gn:feature_code":"PPL",
    "gn:name":"Los Nopales",
    "gn:population":0,
    "gn:timezone":"America/Mexico_City",
    "iso:country":"MX",
    "name:spa_x_preferred":[
        "Los Nopales"
    ],
    "wof:name":"Los Nopales",
    "wof:placetype":"locality"
},
  "geometry": {"coordinates":[-102.23771000000001,19.08407],"type":"Point"}
}