{
  "type": "Feature",
  "properties": {
    "gn:admin1_code":"29",
    "gn:admin2_code":"8.0",
    "gn:asciiname":"La Granja (Camino a Franco)",
    "gn:country_code":"MX",
    "gn:dem":2464,
    "gn:feature_class":"P",
    "gn:feature_code":"PPL",
    "gn:name":"La Granja (Camino a Franco)",
    "gn:population":129,
    "gn:timezone":"America/Mexico_City",
    "iso:country":"MX",
    "wof:name":"La Granja (Camino a Franco)",
    "wof:placetype":"locality",
    "wof:population":129
},
  "geometry": {"coordinates":[-97.82111,19.35528],"type":"Point"}
}