{
  "type": "Feature",
  "properties": {
    "gn:admin1_code":"18.0",
    "gn:admin2_code":"6.0",
    "gn:asciiname":"El Platanillo",
    "gn:country_code":"MX",
    "gn:dem":797,
    "gn:feature_class":"P",
    "gn:feature_code":"PPL",
    "gn:name":"El Platanillo",
    "gn:population":0,
    "gn:timezone":"America/Mazatlan",
    "iso:country":"MX",
    "wof:name":"El Platanillo",
    "wof:placetype":"locality"
},
  "geometry": {"coordinates":[-104.25592,21.20457],"type":"Point"}
}