{
  "type": "Feature",
  "properties": {
    "gn:admin1_code":"5",
    "gn:admin2_code":"77.0",
    "gn:asciiname":"San Javier Lopez Moreno (La Viena)",
    "gn:country_code":"MX",
    "gn:dem":75,
    "gn:feature_class":"P",
    "gn:feature_code":"PPL",
    "gn:name":"San Javier L\u00f3pez Moreno (La Viena)",
    "gn:population":188,
    "gn:timezone":"America/Mexico_City",
    "iso:country":"MX",
    "name:und_x_variant":[
        "San Javier L\u00f3pez Moreno (La Viena)"
    ],
    "wof:name":"San Javier Lopez Moreno (La Viena)",
    "wof:placetype":"locality",
    "wof:population":188
},
  "geometry": {"coordinates":[-92.13306,17.32806],"type":"Point"}
}