{
  "type": "Feature",
  "properties": {
    "gn:admin1_code":"25",
    "gn:admin2_code":"7",
    "gn:asciiname":"Potrero de los Cecena",
    "gn:country_code":"MX",
    "gn:dem":775,
    "gn:feature_class":"P",
    "gn:feature_code":"PPL",
    "gn:name":"Potrero de los Cece\u00f1a",
    "gn:population":21,
    "gn:timezone":"America/Mazatlan",
    "iso:country":"MX",
    "name:und_x_variant":[
        "Potrero de los Cece\u00f1a"
    ],
    "wof:name":"Potrero de los Cecena",
    "wof:placetype":"locality",
    "wof:population":21
},
  "geometry": {"coordinates":[-108.06338999999998,26.44548],"type":"Point"}
}