{
  "type": "Feature",
  "properties": {
    "gn:admin1_code":"10.0",
    "gn:admin2_code":"37.0",
    "gn:asciiname":"El Mecatal",
    "gn:country_code":"MX",
    "gn:dem":554,
    "gn:feature_class":"P",
    "gn:feature_code":"PPL",
    "gn:name":"El Mecatal",
    "gn:population":0,
    "gn:timezone":"America/Monterrey",
    "iso:country":"MX",
    "name:spa_x_preferred":[
        "El Mecatal"
    ],
    "wof:name":"El Mecatal",
    "wof:placetype":"locality"
},
  "geometry": {"coordinates":[-106.83319,25.19954],"type":"Point"}
}