{
  "type": "Feature",
  "properties": {
    "gn:admin1_code":"21",
    "gn:admin2_code":"194.0",
    "gn:asciiname":"Rancho Monserrat",
    "gn:country_code":"MX",
    "gn:dem":202,
    "gn:feature_class":"P",
    "gn:feature_code":"PPL",
    "gn:name":"Rancho Monserrat",
    "gn:population":5,
    "gn:timezone":"America/Mexico_City",
    "iso:country":"MX",
    "wof:name":"Rancho Monserrat",
    "wof:placetype":"locality",
    "wof:population":5
},
  "geometry": {"coordinates":[-97.55721,20.50475],"type":"Point"}
}