{
  "type": "Feature",
  "properties": {
    "gn:admin1_code":"7",
    "gn:admin2_code":"12",
    "gn:asciiname":"El Centeno",
    "gn:country_code":"MX",
    "gn:dem":265,
    "gn:feature_class":"P",
    "gn:feature_code":"PPL",
    "gn:name":"El Centeno",
    "gn:population":10,
    "gn:timezone":"America/Monterrey",
    "iso:country":"MX",
    "wof:name":"El Centeno",
    "wof:placetype":"locality",
    "wof:population":10
},
  "geometry": {"coordinates":[-100.43925,28.44109000000001],"type":"Point"}
}