{
  "type": "Feature",
  "properties": {
    "gn:admin1_code":"30.0",
    "gn:admin2_code":"180.0",
    "gn:asciiname":"El Coyol",
    "gn:country_code":"MX",
    "gn:dem":461,
    "gn:feature_class":"P",
    "gn:feature_code":"PPL",
    "gn:name":"El Coyol",
    "gn:population":219,
    "gn:timezone":"America/Mexico_City",
    "iso:country":"MX",
    "name:spa_x_preferred":[
        "El Coyol"
    ],
    "wof:name":"El Coyol",
    "wof:placetype":"locality",
    "wof:population":219
},
  "geometry": {"coordinates":[-98.18501999999999,20.67423],"type":"Point"}
}