{
  "type": "Feature",
  "properties": {
    "gn:admin1_code":"5",
    "gn:admin2_code":"77.0",
    "gn:asciiname":"Amuypa Chico",
    "gn:country_code":"MX",
    "gn:dem":65,
    "gn:feature_class":"P",
    "gn:feature_code":"PPL",
    "gn:name":"Amuypa Chico",
    "gn:population":99,
    "gn:timezone":"America/Mexico_City",
    "iso:country":"MX",
    "wof:name":"Amuypa Chico",
    "wof:placetype":"locality",
    "wof:population":99
},
  "geometry": {"coordinates":[-92.13667,17.36194],"type":"Point"}
}