{
  "type": "Feature",
  "properties": {
    "gn:admin1_code":"6.0",
    "gn:admin2_code":"52.0",
    "gn:asciiname":"Navarrete",
    "gn:country_code":"MX",
    "gn:dem":1127,
    "gn:feature_class":"P",
    "gn:feature_code":"PPL",
    "gn:name":"Navarrete",
    "gn:population":0,
    "gn:timezone":"America/Ojinaga",
    "iso:country":"MX",
    "name:ceb_x_preferred":[
        "Navarrete"
    ],
    "name:deu_x_preferred":[
        "Navarrete"
    ],
    "name:fra_x_preferred":[
        "Navarrete"
    ],
    "name:jpn_x_preferred":[
        "\u30ca\u30d0\u30ec\u30c6"
    ],
    "name:rus_x_preferred":[
        "\u041d\u0430\u0432\u0430\u0440\u0440\u0435\u0442\u0435"
    ],
    "name:spa_x_preferred":[
        "Navarrete"
    ],
    "name:swe_x_preferred":[
        "Navarrete"
    ],
    "wof:name":"Navarrete",
    "wof:placetype":"locality"
},
  "geometry": {"coordinates":[-104.78189,30.05292],"type":"Point"}
}