{
  "type": "Feature",
  "properties": {
    "gn:admin1_code":"6.0",
    "gn:admin2_code":"52.0",
    "gn:asciiname":"Navarrete",
    "gn:country_code":"MX",
    "gn:dem":1127,
    "gn:feature_class":"P",
    "gn:feature_code":"PPL",
    "gn:name":"Navarrete",
    "gn:population":0,
    "gn:timezone":"America/Ojinaga",
    "iso:country":"MX",
    "name:spa_x_preferred":[
        "Navarrete"
    ],
    "wof:name":"Navarrete",
    "wof:placetype":"locality"
},
  "geometry": {"coordinates":[-104.78189,30.05292],"type":"Point"}
}