{
  "type": "Feature",
  "properties": {
    "gn:admin1_code":"1.0",
    "gn:admin2_code":"2.0",
    "gn:asciiname":"Lomas de Valadez",
    "gn:country_code":"MX",
    "gn:dem":2017,
    "gn:feature_class":"P",
    "gn:feature_code":"PPL",
    "gn:name":"Lomas de Valadez",
    "gn:population":2,
    "gn:timezone":"America/Mexico_City",
    "iso:country":"MX",
    "wof:name":"Lomas de Valadez",
    "wof:placetype":"locality",
    "wof:population":2
},
  "geometry": {"coordinates":[-102.03993,22.11817000000001],"type":"Point"}
}