{
  "type": "Feature",
  "properties": {
    "gn:admin1_code":"2",
    "gn:admin2_code":"3.0",
    "gn:asciiname":"Tepatitlan",
    "gn:country_code":"MX",
    "gn:dem":523,
    "gn:feature_class":"P",
    "gn:feature_code":"PPL",
    "gn:name":"Tepatitl\u00e1n",
    "gn:population":4,
    "gn:timezone":"America/Tijuana",
    "iso:country":"MX",
    "name:und_x_variant":[
        "Tepatitl\u00e1n"
    ],
    "wof:name":"Tepatitlan",
    "wof:placetype":"locality",
    "wof:population":4
},
  "geometry": {"coordinates":[-116.67028000000001,32.56139],"type":"Point"}
}