{
  "type": "Feature",
  "properties": {
    "gn:admin1_code":"12.0",
    "gn:admin2_code":"48.0",
    "gn:asciiname":"El Sereno",
    "gn:country_code":"MX",
    "gn:dem":965,
    "gn:feature_class":"P",
    "gn:feature_code":"PPL",
    "gn:name":"El Sereno",
    "gn:population":0,
    "gn:timezone":"America/Mexico_City",
    "iso:country":"MX",
    "name:spa_x_preferred":[
        "El Sereno"
    ],
    "wof:name":"El Sereno",
    "wof:placetype":"locality"
},
  "geometry": {"coordinates":[-101.14749999999999,17.81653],"type":"Point"}
}