{
  "type": "Feature",
  "properties": {
    "gn:admin1_code":"14.0",
    "gn:admin2_code":"77.0",
    "gn:asciiname":"El Cabezon",
    "gn:cc2":"MX",
    "gn:country_code":"MX",
    "gn:dem":1263,
    "gn:feature_class":"P",
    "gn:feature_code":"PPL",
    "gn:name":"El Cabez\u00f3n",
    "gn:population":0,
    "gn:timezone":"America/Mexico_City",
    "iso:country":"MX",
    "name:und_x_variant":[
        "Cabez\u00f3n",
        "El Cabez\u00f3n"
    ],
    "wof:name":"El Cabezon",
    "wof:placetype":"locality"
},
  "geometry": {"coordinates":[-103.86667,20.51667],"type":"Point"}
}