{
  "type": "Feature",
  "properties": {
    "gn:admin1_code":"10.0",
    "gn:admin2_code":"26.0",
    "gn:asciiname":"El Sobaco",
    "gn:country_code":"MX",
    "gn:dem":2504,
    "gn:feature_class":"P",
    "gn:feature_code":"PPL",
    "gn:name":"El Sobaco",
    "gn:population":0,
    "gn:timezone":"America/Monterrey",
    "iso:country":"MX",
    "name:spa_x_preferred":[
        "El Sobaco"
    ],
    "wof:name":"El Sobaco",
    "wof:placetype":"locality"
},
  "geometry": {"coordinates":[-105.64428999999998,24.51675],"type":"Point"}
}