{
  "type": "Feature",
  "properties": {
    "gn:admin1_code":"20.0",
    "gn:admin2_code":"277.0",
    "gn:asciiname":"Arena",
    "gn:country_code":"MX",
    "gn:dem":1261,
    "gn:feature_class":"P",
    "gn:feature_code":"PPL",
    "gn:name":"Arena",
    "gn:population":0,
    "gn:timezone":"America/Mexico_City",
    "iso:country":"MX",
    "name:spa_x_preferred":[
        "Arena"
    ],
    "wof:name":"Arena",
    "wof:placetype":"locality"
},
  "geometry": {"coordinates":[-97.03552000000001,16.37778],"type":"Point"}
}