{
  "type": "Feature",
  "properties": {
    "gn:admin1_code":"20.0",
    "gn:admin2_code":"277.0",
    "gn:asciiname":"Arena",
    "gn:country_code":"MX",
    "gn:dem":1261,
    "gn:feature_class":"P",
    "gn:feature_code":"PPL",
    "gn:name":"Arena",
    "gn:population":0,
    "gn:timezone":"America/Mexico_City",
    "iso:country":"MX",
    "name:ara_x_preferred":[
        "\u0635\u0627\u0644\u0629"
    ],
    "name:bel_x_preferred":[
        "\u0410\u0440\u044d\u043d\u0430"
    ],
    "name:bul_x_preferred":[
        "\u0410\u0440\u0435\u043d\u0430"
    ],
    "name:ces_x_preferred":[
        "Ar\u00e9na"
    ],
    "name:dan_x_preferred":[
        "Arena"
    ],
    "name:deu_x_preferred":[
        "Arena"
    ],
    "name:diq_x_preferred":[
        "Arena"
    ],
    "name:epo_x_preferred":[
        "Areno"
    ],
    "name:est_x_preferred":[
        "Areen"
    ],
    "name:fas_x_preferred":[
        "\u0633\u0627\u0644\u0646 \u0633\u0631\u067e\u0648\u0634\u06cc\u062f\u0647"
    ],
    "name:fra_x_preferred":[
        "Ar\u00e9na"
    ],
    "name:glg_x_preferred":[
        "Arena"
    ],
    "name:heb_x_preferred":[
        "\u05d6\u05d9\u05e8\u05d4"
    ],
    "name:hrv_x_preferred":[
        "Arena"
    ],
    "name:ido_x_preferred":[
        "Areno"
    ],
    "name:ind_x_preferred":[
        "Arena"
    ],
    "name:ita_x_preferred":[
        "Arena"
    ],
    "name:jpn_x_preferred":[
        "\u30a2\u30ea\u30fc\u30ca"
    ],
    "name:kor_x_preferred":[
        "\uc544\ub808\ub098"
    ],
    "name:nld_x_preferred":[
        "Arena"
    ],
    "name:pol_x_preferred":[
        "Arena"
    ],
    "name:por_x_preferred":[
        "Arena"
    ],
    "name:ron_x_preferred":[
        "Aren\u0103"
    ],
    "name:rus_x_preferred":[
        "\u0410\u0440\u0435\u043d\u0430"
    ],
    "name:sco_x_preferred":[
        "Arena"
    ],
    "name:slv_x_preferred":[
        "Arena"
    ],
    "name:spa_x_preferred":[
        "Arena"
    ],
    "name:srp_x_preferred":[
        "\u0410\u0440\u0435\u043d\u0430"
    ],
    "name:swe_x_preferred":[
        "Arena"
    ],
    "name:tur_x_preferred":[
        "Arena"
    ],
    "name:ukr_x_preferred":[
        "\u0410\u0440\u0435\u043d\u0430"
    ],
    "name:zho_x_preferred":[
        "\u7ade\u6280\u573a"
    ],
    "wof:name":"Arena",
    "wof:placetype":"locality"
},
  "geometry": {"coordinates":[-97.03552000000001,16.37778],"type":"Point"}
}