{
  "type": "Feature",
  "properties": {
    "iso:country":"MX",
    "name:spa_x_preferred":[
        "Barrio Balcones"
    ],
    "qs:gn_adm0_cc":"MX",
    "qs:gn_local":3980621,
    "qs:gn_nam_loc":"Valle de Bravo, Valle de Bravo, Mexico, MX",
    "qs:gn_namadm1":"15",
    "qs:local_max":506,
    "qs:local_sum":1200,
    "qs:localhoods":7,
    "qs:name":"Barrio Balcones",
    "qs:name_adm0":"M\u00e9xico",
    "qs:name_adm1":"Mexico",
    "qs:name_adm2":"Valle de Bravo",
    "qs:name_local":"Valle de Bravo",
    "qs:photo_max":50,
    "qs:photo_sum":143,
    "qs:placetype":"Suburb",
    "qs:quad_count":7,
    "qs:woe_adm0":23424900,
    "qs:woe_adm1":2346278,
    "qs:woe_adm2":12600429,
    "qs:woe_lau":0,
    "qs:woe_local":150492,
    "qs:woe_ver":"7.10.0",
    "wof:lang":[
        "spa"
    ],
    "wof:name":"Barrio Balcones",
    "wof:placetype":"neighbourhood"
},
  "geometry": {"coordinates":[-100.125013,19.165489],"type":"Point"}
}