{
  "type": "Feature",
  "properties": {
    "gn:admin1_code":"16.0",
    "gn:admin2_code":"29.0",
    "gn:asciiname":"Ejido de Cotio",
    "gn:country_code":"MX",
    "gn:dem":179,
    "gn:feature_class":"P",
    "gn:feature_code":"PPL",
    "gn:name":"Ejido de Cot\u00edo",
    "gn:population":0,
    "gn:timezone":"America/Mexico_City",
    "iso:country":"MX",
    "wof:name":"Ejido de Cotio",
    "wof:placetype":"locality"
},
  "geometry": {"coordinates":[-101.66388999999999,18.60278],"type":"Point"}
}