{
  "type": "Feature",
  "properties": {
    "gn:admin1_code":"30",
    "gn:admin2_code":"189.0",
    "gn:asciiname":"Leopoldo Gareli",
    "gn:country_code":"MX",
    "gn:dem":16,
    "gn:feature_class":"P",
    "gn:feature_code":"PPL",
    "gn:name":"Leopoldo Gareli",
    "gn:population":6,
    "gn:timezone":"America/Mexico_City",
    "iso:country":"MX",
    "wof:name":"Leopoldo Gareli",
    "wof:placetype":"locality",
    "wof:population":6
},
  "geometry": {"coordinates":[-97.41278,21.01556],"type":"Point"}
}