{
  "type": "Feature",
  "properties": {
    "gn:admin1_code":"6.0",
    "gn:admin2_code":"15.0",
    "gn:asciiname":"La Veladora",
    "gn:country_code":"MX",
    "gn:dem":1341,
    "gn:feature_class":"P",
    "gn:feature_code":"PPL",
    "gn:name":"La Veladora",
    "gn:population":0,
    "gn:timezone":"America/Chihuahua",
    "iso:country":"MX",
    "name:spa_x_preferred":[
        "La Veladora"
    ],
    "wof:name":"La Veladora",
    "wof:placetype":"locality"
},
  "geometry": {"coordinates":[-105.64794999999999,29.81751],"type":"Point"}
}