{
  "type": "Feature",
  "properties": {
    "gn:admin1_code":"14.0",
    "gn:admin2_code":"34.0",
    "gn:asciiname":"Los Datiles",
    "gn:country_code":"MX",
    "gn:dem":813,
    "gn:feature_class":"P",
    "gn:feature_code":"PPL",
    "gn:name":"Los Datiles",
    "gn:population":0,
    "gn:timezone":"America/Mexico_City",
    "iso:country":"MX",
    "name:spa_x_preferred":[
        "Los Datiles"
    ],
    "wof:name":"Los Datiles",
    "wof:placetype":"locality"
},
  "geometry": {"coordinates":[-104.07210000000001,19.89263],"type":"Point"}
}