{
  "type": "Feature",
  "properties": {
    "gn:admin1_code":"18.0",
    "gn:admin2_code":"9.0",
    "gn:asciiname":"San Luisito",
    "gn:country_code":"MX",
    "gn:dem":494,
    "gn:feature_class":"P",
    "gn:feature_code":"PPL",
    "gn:name":"San Luisito",
    "gn:population":4,
    "gn:timezone":"America/Mazatlan",
    "iso:country":"MX",
    "wof:name":"San Luisito",
    "wof:placetype":"locality",
    "wof:population":4
},
  "geometry": {"coordinates":[-104.59583000000001,21.73167],"type":"Point"}
}