{
  "type": "Feature",
  "properties": {
    "gn:admin1_code":"28.0",
    "gn:admin2_code":"37.0",
    "gn:asciiname":"San Isidro",
    "gn:country_code":"MX",
    "gn:dem":65,
    "gn:feature_class":"P",
    "gn:feature_code":"PPL",
    "gn:name":"San Isidro",
    "gn:population":2,
    "gn:timezone":"America/Monterrey",
    "iso:country":"MX",
    "name:spa_x_preferred":[
        "San Isidro"
    ],
    "wof:name":"San Isidro",
    "wof:placetype":"locality",
    "wof:population":2
},
  "geometry": {"coordinates":[-98.07592,23.52128],"type":"Point"}
}