{
  "type": "Feature",
  "properties": {
    "gn:admin1_code":"25.0",
    "gn:asciiname":"La Villita de Guadalupe",
    "gn:country_code":"MX",
    "gn:dem":6,
    "gn:feature_class":"P",
    "gn:feature_code":"PPL",
    "gn:name":"La Villita de Guadalupe",
    "gn:population":0,
    "gn:timezone":"America/Mazatlan",
    "iso:country":"MX",
    "name:spa_x_preferred":[
        "La Villita de Guadalupe"
    ],
    "wof:name":"La Villita de Guadalupe",
    "wof:placetype":"locality"
},
  "geometry": {"coordinates":[-105.79335,22.64734],"type":"Point"}
}