{
  "type": "Feature",
  "properties": {
    "gn:admin1_code":"6",
    "gn:admin2_code":"23.0",
    "gn:asciiname":"Harvard And Sons Ranch (San Joaquin)",
    "gn:country_code":"MX",
    "gn:dem":1527,
    "gn:feature_class":"P",
    "gn:feature_code":"PPL",
    "gn:name":"Harvard And Sons Ranch (San Joaqu\u00edn)",
    "gn:population":75,
    "gn:timezone":"America/Chihuahua",
    "iso:country":"MX",
    "name:und_x_variant":[
        "Harvard And Sons Ranch (San Joaqu\u00edn)"
    ],
    "wof:name":"Harvard And Sons Ranch (San Joaquin)",
    "wof:placetype":"locality",
    "wof:population":75
},
  "geometry": {"coordinates":[-107.74666000000001,30.03764],"type":"Point"}
}