{
  "type": "Feature",
  "properties": {
    "gn:admin1_code":"27",
    "gn:admin2_code":"5.0",
    "gn:asciiname":"Arena Tercera Seccion",
    "gn:country_code":"MX",
    "gn:dem":17,
    "gn:feature_class":"P",
    "gn:feature_code":"PPL",
    "gn:name":"Arena Tercera Secci\u00f3n",
    "gn:population":0,
    "gn:timezone":"America/Mexico_City",
    "iso:country":"MX",
    "name:spa_x_preferred":[
        "La Arena Tercera Secci\u00f3n"
    ],
    "name:spa_x_variant":[
        "Arena Tercera Secci\u00f3n"
    ],
    "wof:name":"Arena Tercera Seccion",
    "wof:placetype":"locality"
},
  "geometry": {"coordinates":[-93.40218,18.19152],"type":"Point"}
}