{
  "type": "Feature",
  "properties": {
    "gn:admin1_code":"10",
    "gn:admin2_code":"7",
    "gn:asciiname":"Colonia Establera San Francisco",
    "gn:country_code":"MX",
    "gn:dem":1126,
    "gn:feature_class":"P",
    "gn:feature_code":"PPL",
    "gn:name":"Colonia Establera San Francisco",
    "gn:population":20,
    "gn:timezone":"America/Monterrey",
    "iso:country":"MX",
    "wof:name":"Colonia Establera San Francisco",
    "wof:placetype":"locality",
    "wof:population":20
},
  "geometry": {"coordinates":[-103.56868,25.61167],"type":"Point"}
}