{
  "type": "Feature",
  "properties": {
    "gn:admin1_code":"12",
    "gn:admin2_code":"38.0",
    "gn:asciiname":"La Colorada (El Callejon de la Colorada)",
    "gn:country_code":"MX",
    "gn:dem":18,
    "gn:feature_class":"P",
    "gn:feature_code":"PPL",
    "gn:name":"La Colorada (El Callej\u00f3n de la Colorada)",
    "gn:population":6,
    "gn:timezone":"America/Mexico_City",
    "iso:country":"MX",
    "name:und_x_variant":[
        "La Colorada (El Callej\u00f3n de la Colorada)"
    ],
    "wof:name":"La Colorada (El Callejon de la Colorada)",
    "wof:placetype":"locality",
    "wof:population":6
},
  "geometry": {"coordinates":[-101.4319,17.56445],"type":"Point"}
}