{
  "type": "Feature",
  "properties": {
    "gn:admin1_code":"18.0",
    "gn:admin2_code":"8.0",
    "gn:asciiname":"Los Compadres",
    "gn:country_code":"MX",
    "gn:dem":1038,
    "gn:feature_class":"P",
    "gn:feature_code":"PPL",
    "gn:name":"Los Compadres",
    "gn:population":0,
    "gn:timezone":"America/Mazatlan",
    "iso:country":"MX",
    "name:spa_x_preferred":[
        "Los Compadres"
    ],
    "name:spa_x_variant":[
        "El Marinero",
        "El Marino"
    ],
    "wof:name":"Los Compadres",
    "wof:placetype":"locality"
},
  "geometry": {"coordinates":[-104.9066,21.43133],"type":"Point"}
}