{
  "type": "Feature",
  "properties": {
    "gn:admin1_code":"30",
    "gn:admin2_code":"158.0",
    "gn:asciiname":"Margarito Marin Reyes",
    "gn:country_code":"MX",
    "gn:dem":21,
    "gn:feature_class":"P",
    "gn:feature_code":"PPL",
    "gn:name":"Margarito Mar\u00edn Reyes",
    "gn:population":6,
    "gn:timezone":"America/Mexico_City",
    "iso:country":"MX",
    "name:und_x_variant":[
        "Margarito Mar\u00edn Reyes"
    ],
    "wof:name":"Margarito Marin Reyes",
    "wof:placetype":"locality",
    "wof:population":6
},
  "geometry": {"coordinates":[-96.99250000000001,20.30806],"type":"Point"}
}