{
  "type": "Feature",
  "properties": {
    "gn:admin1_code":"25",
    "gn:admin2_code":"6",
    "gn:asciiname":"El Vino",
    "gn:country_code":"MX",
    "gn:dem":738,
    "gn:feature_class":"P",
    "gn:feature_code":"PPL",
    "gn:name":"El Vino",
    "gn:population":10,
    "gn:timezone":"America/Mazatlan",
    "iso:country":"MX",
    "wof:name":"El Vino",
    "wof:placetype":"locality",
    "wof:population":10
},
  "geometry": {"coordinates":[-107.18219999999999,25.13636],"type":"Point"}
}