{
  "type": "Feature",
  "properties": {
    "gn:admin1_code":"32",
    "gn:admin2_code":"31.0",
    "gn:asciiname":"Puentecillas",
    "gn:country_code":"MX",
    "gn:dem":1895,
    "gn:feature_class":"P",
    "gn:feature_code":"PPL",
    "gn:name":"Puentecillas",
    "gn:population":0,
    "gn:timezone":"America/Mexico_City",
    "iso:country":"MX",
    "name:spa_x_preferred":[
        "Puentecillas"
    ],
    "wof:name":"Puentecillas",
    "wof:placetype":"locality"
},
  "geometry": {"coordinates":[-103.60234,22.20465],"type":"Point"}
}