{
  "type": "Feature",
  "properties": {
    "iso:country":"MX",
    "name:spa_x_preferred":[
        "Cuicalli"
    ],
    "qs:gn_adm0_cc":"MX",
    "qs:gn_local":3522790,
    "qs:gn_nam_loc":"Naucalpan de Juarez, Naucalpan de Ju\u00e1rez, Mexico, MX",
    "qs:gn_namadm1":"15",
    "qs:local_max":835,
    "qs:local_sum":2795,
    "qs:localhoods":16,
    "qs:name":"Cuicalli",
    "qs:name_adm0":"M\u00e9xico",
    "qs:name_adm1":"Mexico",
    "qs:name_adm2":"Naucalpan de Juarez",
    "qs:name_local":"Naucalpan de Ju\u00e1rez",
    "qs:photo_max":110,
    "qs:photo_sum":119,
    "qs:placetype":"Suburb",
    "qs:quad_count":5,
    "qs:woe_adm0":23424900,
    "qs:woe_adm1":2346278,
    "qs:woe_adm2":12600377,
    "qs:woe_lau":0,
    "qs:woe_local":134395,
    "qs:woe_ver":"7.10.0",
    "qs_pg:name":"Cuicalli",
    "qs_pg:name_adm0":"M\u00e9xico",
    "qs_pg:name_adm1":"Mexico",
    "qs_pg:photos":119,
    "qs_pg:photos_1k":24,
    "qs_pg:photos_9k":1,
    "qs_pg:photos_9r":3,
    "qs_pg:photos_all":119,
    "qs_pg:photos_sr":3,
    "qs_pg:pop_sr":0,
    "qs_pg:qs_pg_placetype":"neighbourhood",
    "qs_pg:qs_pg_placetype_gp":"Suburb",
    "qs_pg:woe_adm0":23424900,
    "woe:adm0_id":23424900,
    "woe:name_adm0":"M\u00e9xico",
    "woe:name_adm1":"Mexico",
    "woe:placetype":"Suburb",
    "wof:lang":[
        "spa"
    ],
    "wof:name":"Cuicalli",
    "wof:placetype":"neighbourhood"
},
  "geometry": {"coordinates":[-99.241276,19.506672],"type":"Point"}
}