{
  "type": "Feature",
  "properties": {
    "gn:admin1_code":"30.0",
    "gn:admin2_code":"51.0",
    "gn:asciiname":"Independencia",
    "gn:country_code":"MX",
    "gn:dem":113,
    "gn:feature_class":"P",
    "gn:feature_code":"PPL",
    "gn:name":"Independencia",
    "gn:population":269,
    "gn:timezone":"America/Mexico_City",
    "iso:country":"MX",
    "name:cat_x_preferred":[
        "Independ\u00e8ncia"
    ],
    "name:ceb_x_preferred":[
        "Independencia"
    ],
    "name:deu_x_preferred":[
        "Independencia"
    ],
    "name:epo_x_preferred":[
        "Independencia"
    ],
    "name:fra_x_preferred":[
        "Independencia"
    ],
    "name:heb_x_preferred":[
        "\u05d0\u05d9\u05e0\u05d3\u05e4\u05e0\u05d3\u05e0\u05e1\u05d9\u05d4"
    ],
    "name:hun_x_preferred":[
        "Independencia"
    ],
    "name:ita_x_preferred":[
        "Independencia"
    ],
    "name:kor_x_preferred":[
        "\uc778\ub370\ud39c\ub374\uc2dc\uc544"
    ],
    "name:nld_x_preferred":[
        "Independencia"
    ],
    "name:nor_x_preferred":[
        "Independencia"
    ],
    "name:rus_x_preferred":[
        "\u0418\u043d\u0434\u0435\u043f\u0435\u043d\u0434\u0435\u043d\u0441\u0438\u044f"
    ],
    "name:sco_x_preferred":[
        "Independencia"
    ],
    "name:spa_x_preferred":[
        "Independencia"
    ],
    "name:swe_x_preferred":[
        "Independencia"
    ],
    "name:ukr_x_preferred":[
        "\u0406\u043d\u0434\u0435\u043f\u0435\u043d\u0434\u0435\u043d\u0441\u0456\u044f"
    ],
    "wof:name":"Independencia",
    "wof:placetype":"locality",
    "wof:population":269
},
  "geometry": {"coordinates":[-97.65139000000001,20.39944],"type":"Point"}
}