{
  "type": "Feature",
  "properties": {
    "gn:admin1_code":"30.0",
    "gn:admin2_code":"51.0",
    "gn:asciiname":"Independencia",
    "gn:country_code":"MX",
    "gn:dem":113,
    "gn:feature_class":"P",
    "gn:feature_code":"PPL",
    "gn:name":"Independencia",
    "gn:population":269,
    "gn:timezone":"America/Mexico_City",
    "iso:country":"MX",
    "name:spa_x_preferred":[
        "Independencia"
    ],
    "wof:name":"Independencia",
    "wof:placetype":"locality",
    "wof:population":269
},
  "geometry": {"coordinates":[-97.65139000000001,20.39944],"type":"Point"}
}