{
  "type": "Feature",
  "properties": {
    "gn:admin1_code":"32",
    "gn:admin2_code":"9.0",
    "gn:asciiname":"San Antonio de Guadalupe",
    "gn:country_code":"MX",
    "gn:dem":2203,
    "gn:feature_class":"P",
    "gn:feature_code":"PPL",
    "gn:name":"San Antonio de Guadalupe",
    "gn:population":0,
    "gn:timezone":"America/Mexico_City",
    "iso:country":"MX",
    "name:spa_x_preferred":[
        "San Antonio de Guadalupe"
    ],
    "name:spa_x_variant":[
        "San Antonio"
    ],
    "wof:name":"San Antonio de Guadalupe",
    "wof:placetype":"locality"
},
  "geometry": {"coordinates":[-103.97311999999999,23.49297],"type":"Point"}
}