{
  "type": "Feature",
  "properties": {
    "gn:admin1_code":"16.0",
    "gn:asciiname":"El Oyamel",
    "gn:country_code":"MX",
    "gn:dem":2352,
    "gn:feature_class":"P",
    "gn:feature_code":"PPL",
    "gn:name":"El Oyamel",
    "gn:population":0,
    "gn:timezone":"America/Mexico_City",
    "iso:country":"MX",
    "name:spa_x_preferred":[
        "El Oyamel"
    ],
    "wof:name":"El Oyamel",
    "wof:placetype":"locality"
},
  "geometry": {"coordinates":[-100.54521,19.59886],"type":"Point"}
}