{
  "type": "Feature",
  "properties": {
    "gn:admin1_code":"27",
    "gn:admin2_code":"12.0",
    "gn:asciiname":"Chilapilla Primera Seccion",
    "gn:country_code":"MX",
    "gn:dem":6,
    "gn:feature_class":"P",
    "gn:feature_code":"PPL",
    "gn:name":"Chilapilla Primera Secci\u00f3n",
    "gn:population":0,
    "gn:timezone":"America/Mexico_City",
    "iso:country":"MX",
    "name:spa_x_preferred":[
        "Chilapilla Primera Secci\u00f3n"
    ],
    "name:spa_x_variant":[
        "Chilapilla",
        "Primera Secci\u00f3n"
    ],
    "wof:name":"Chilapilla Primera Seccion",
    "wof:placetype":"locality"
},
  "geometry": {"coordinates":[-92.53072,17.97456],"type":"Point"}
}