{
  "type": "Feature",
  "properties": {
    "gn:admin1_code":"27",
    "gn:admin2_code":"8.0",
    "gn:asciiname":"La Vencedora",
    "gn:country_code":"MX",
    "gn:dem":12,
    "gn:feature_class":"P",
    "gn:feature_code":"PPL",
    "gn:name":"La Vencedora",
    "gn:population":708,
    "gn:timezone":"America/Mexico_City",
    "iso:country":"MX",
    "wof:name":"La Vencedora",
    "wof:placetype":"locality",
    "wof:population":708
},
  "geometry": {"coordinates":[-93.84,18.05],"type":"Point"}
}