{
  "type": "Feature",
  "properties": {
    "gn:admin1_code":"26.0",
    "gn:admin2_code":"38.0",
    "gn:asciiname":"El Reparo",
    "gn:country_code":"MX",
    "gn:dem":754,
    "gn:feature_class":"P",
    "gn:feature_code":"PPL",
    "gn:name":"El Reparo",
    "gn:population":0,
    "gn:timezone":"America/Hermosillo",
    "iso:country":"MX",
    "name:spa_x_preferred":[
        "El Reparo"
    ],
    "wof:name":"El Reparo",
    "wof:placetype":"locality"
},
  "geometry": {"coordinates":[-109.62497999999999,29.89199],"type":"Point"}
}