{
  "type": "Feature",
  "properties": {
    "gn:admin1_code":"16",
    "gn:admin2_code":"89",
    "gn:asciiname":"El Colomo",
    "gn:country_code":"MX",
    "gn:dem":406,
    "gn:feature_class":"P",
    "gn:feature_code":"PPL",
    "gn:name":"El Colomo",
    "gn:population":23,
    "gn:timezone":"America/Mexico_City",
    "iso:country":"MX",
    "name:spa_x_preferred":[
        "El Colomo"
    ],
    "wof:name":"El Colomo",
    "wof:placetype":"locality",
    "wof:population":23
},
  "geometry": {"coordinates":[-102.87860999999999,19.01667],"type":"Point"}
}