{
  "type": "Feature",
  "properties": {
    "gn:admin1_code":"4",
    "gn:admin2_code":"3.0",
    "gn:asciiname":"El Progreso del Sultan",
    "gn:country_code":"MX",
    "gn:dem":16,
    "gn:feature_class":"P",
    "gn:feature_code":"PPL",
    "gn:name":"El Progreso del Sult\u00e1n",
    "gn:population":4,
    "gn:timezone":"America/Merida",
    "iso:country":"MX",
    "name:und_x_variant":[
        "El Progreso del Sult\u00e1n"
    ],
    "wof:name":"El Progreso del Sultan",
    "wof:placetype":"locality",
    "wof:population":4
},
  "geometry": {"coordinates":[-91.43694000000001,18.10556],"type":"Point"}
}