{
  "type": "Feature",
  "properties": {
    "gn:admin1_code":"19.0",
    "gn:admin2_code":"5.0",
    "gn:asciiname":"El Puente del Rio Salado",
    "gn:country_code":"MX",
    "gn:dem":157,
    "gn:feature_class":"P",
    "gn:feature_code":"PPL",
    "gn:name":"El Puente del R\u00edo Salado",
    "gn:population":0,
    "gn:timezone":"America/Matamoros",
    "iso:country":"MX",
    "name:spa_x_preferred":[
        "El Puente del R\u00edo Salado"
    ],
    "wof:name":"El Puente del Rio Salado",
    "wof:placetype":"locality"
},
  "geometry": {"coordinates":[-99.85563999999999,26.94001],"type":"Point"}
}