{
  "type": "Feature",
  "properties": {
    "gn:admin1_code":"15",
    "gn:admin2_code":"124.0",
    "gn:asciiname":"San Miguel Chisda",
    "gn:country_code":"MX",
    "gn:dem":2792,
    "gn:feature_class":"P",
    "gn:feature_code":"PPL",
    "gn:name":"San Miguel Chisda",
    "gn:population":352,
    "gn:timezone":"America/Mexico_City",
    "iso:country":"MX",
    "wof:name":"San Miguel Chisda",
    "wof:placetype":"locality",
    "wof:population":352
},
  "geometry": {"coordinates":[-100.07444,19.62861],"type":"Point"}
}