{
  "type": "Feature",
  "properties": {
    "gn:admin1_code":"14.0",
    "gn:admin2_code":"61.0",
    "gn:asciiname":"El Huizachal",
    "gn:country_code":"MX",
    "gn:dem":1419,
    "gn:feature_class":"P",
    "gn:feature_code":"PPL",
    "gn:name":"El Huizachal",
    "gn:population":0,
    "gn:timezone":"America/Mexico_City",
    "iso:country":"MX",
    "name:spa_x_preferred":[
        "El Huizachal"
    ],
    "wof:name":"El Huizachal",
    "wof:placetype":"locality"
},
  "geometry": {"coordinates":[-104.17427000000001,22.49625],"type":"Point"}
}