{
  "type": "Feature",
  "properties": {
    "gn:admin1_code":"20",
    "gn:admin2_code":"131",
    "gn:asciiname":"Portillo Zapoteco",
    "gn:country_code":"MX",
    "gn:dem":1685,
    "gn:feature_class":"P",
    "gn:feature_code":"PPL",
    "gn:name":"Portillo Zapoteco",
    "gn:population":30,
    "gn:timezone":"America/Mexico_City",
    "iso:country":"MX",
    "wof:name":"Portillo Zapoteco",
    "wof:placetype":"locality",
    "wof:population":30
},
  "geometry": {"coordinates":[-96.40361,16.79556],"type":"Point"}
}