{
  "type": "Feature",
  "properties": {
    "gn:admin1_code":"10",
    "gn:admin2_code":"7.0",
    "gn:asciiname":"Jose Maria Morelos y Pavon",
    "gn:country_code":"MX",
    "gn:dem":1110,
    "gn:feature_class":"P",
    "gn:feature_code":"PPL",
    "gn:name":"Jos\u00e9 Mar\u00eda Morelos y Pav\u00f3n",
    "gn:population":341,
    "gn:timezone":"America/Monterrey",
    "iso:country":"MX",
    "wof:name":"Jose Maria Morelos y Pavon",
    "wof:placetype":"locality",
    "wof:population":341
},
  "geometry": {"coordinates":[-103.57143000000001,25.86068],"type":"Point"}
}