{
  "type": "Feature",
  "properties": {
    "gn:admin1_code":"5",
    "gn:admin2_code":"52.0",
    "gn:asciiname":"Montes de los Olivos (Anexo San Carlos)",
    "gn:country_code":"MX",
    "gn:dem":553,
    "gn:feature_class":"P",
    "gn:feature_code":"PPL",
    "gn:name":"Montes de los Olivos (Anexo San Carlos)",
    "gn:population":8,
    "gn:timezone":"America/Mexico_City",
    "iso:country":"MX",
    "wof:name":"Montes de los Olivos (Anexo San Carlos)",
    "wof:placetype":"locality",
    "wof:population":8
},
  "geometry": {"coordinates":[-91.46257,16.25917999999999],"type":"Point"}
}