{
  "type": "Feature",
  "properties": {
    "gn:admin1_code":"5",
    "gn:admin2_code":"59",
    "gn:asciiname":"3 de Mayo",
    "gn:country_code":"MX",
    "gn:dem":882,
    "gn:feature_class":"P",
    "gn:feature_code":"PPL",
    "gn:name":"3 de Mayo",
    "gn:population":12,
    "gn:timezone":"America/Mexico_City",
    "iso:country":"MX",
    "wof:name":"3 de Mayo",
    "wof:placetype":"locality",
    "wof:population":12
},
  "geometry": {"coordinates":[-91.90694000000001,16.81167],"type":"Point"}
}