{
  "type": "Feature",
  "properties": {
    "gn:admin1_code":"5",
    "gn:admin2_code":"2",
    "gn:asciiname":"Las Grutas",
    "gn:country_code":"MX",
    "gn:dem":684,
    "gn:feature_class":"P",
    "gn:feature_code":"PPL",
    "gn:name":"Las Grutas",
    "gn:population":50,
    "gn:timezone":"America/Mexico_City",
    "iso:country":"MX",
    "name:ceb_x_preferred":[
        "Las Grutas"
    ],
    "name:deu_x_preferred":[
        "Las Grutas"
    ],
    "name:rus_x_preferred":[
        "\u041b\u0430\u0441-\u0413\u0440\u0443\u0442\u0430\u0441"
    ],
    "name:spa_x_preferred":[
        "Las Grutas"
    ],
    "wof:name":"Las Grutas",
    "wof:placetype":"locality",
    "wof:population":50
},
  "geometry": {"coordinates":[-92.855,16.41667],"type":"Point"}
}