{
  "type": "Feature",
  "properties": {
    "gn:admin1_code":"25",
    "gn:admin2_code":"10.0",
    "gn:asciiname":"Vega",
    "gn:country_code":"MX",
    "gn:dem":47,
    "gn:feature_class":"P",
    "gn:feature_code":"PPL",
    "gn:name":"Vega",
    "gn:population":0,
    "gn:timezone":"America/Mazatlan",
    "iso:country":"MX",
    "wof:name":"Vega",
    "wof:placetype":"locality"
},
  "geometry": {"coordinates":[-108.71666999999999,26.16667],"type":"Point"}
}