{
  "type": "Feature",
  "properties": {
    "gn:admin1_code":"24",
    "gn:admin2_code":"46.0",
    "gn:asciiname":"Puerto Espino",
    "gn:country_code":"MX",
    "gn:dem":2185,
    "gn:feature_class":"P",
    "gn:feature_code":"PPL",
    "gn:name":"Puerto Espino",
    "gn:population":0,
    "gn:timezone":"America/Mexico_City",
    "iso:country":"MX",
    "name:und_x_variant":[
        "Puerto de Espino",
        "Puerto Espino"
    ],
    "wof:name":"Puerto Espino",
    "wof:placetype":"locality"
},
  "geometry": {"coordinates":[-101.25991,22.1203],"type":"Point"}
}