{
  "type": "Feature",
  "properties": {
    "gn:admin1_code":"10.0",
    "gn:admin2_code":"24.0",
    "gn:asciiname":"Jesus Gonzalez Ortega",
    "gn:country_code":"MX",
    "gn:dem":1362,
    "gn:feature_class":"P",
    "gn:feature_code":"PPL",
    "gn:name":"Jes\u00fas Gonz\u00e1lez Ortega",
    "gn:population":0,
    "gn:timezone":"America/Monterrey",
    "iso:country":"MX",
    "name:spa_x_preferred":[
        "Jes\u00fas Gonz\u00e1lez Ortega"
    ],
    "name:spa_x_variant":[
        "El Callej\u00f3n"
    ],
    "name:und_x_variant":[
        "Jes\u00fas Gonzalez Ort\u00e9ga"
    ],
    "wof:name":"Jesus Gonzalez Ortega",
    "wof:placetype":"locality"
},
  "geometry": {"coordinates":[-104.5997,25.2887],"type":"Point"}
}