{
  "type": "Feature",
  "properties": {
    "gn:admin1_code":"5",
    "gn:admin2_code":"59.0",
    "gn:asciiname":"Pena Blanca",
    "gn:country_code":"MX",
    "gn:dem":209,
    "gn:feature_class":"P",
    "gn:feature_code":"PPL",
    "gn:name":"Pe\u00f1a Blanca",
    "gn:population":302,
    "gn:timezone":"America/Mexico_City",
    "iso:country":"MX",
    "name:und_x_variant":[
        "Pe\u00f1a Blanca"
    ],
    "wof:name":"Pena Blanca",
    "wof:placetype":"locality",
    "wof:population":302
},
  "geometry": {"coordinates":[-91.15472,16.10389],"type":"Point"}
}