{
  "type": "Feature",
  "properties": {
    "gn:admin1_code":"5",
    "gn:admin2_code":"85.0",
    "gn:asciiname":"Adolfo Lopez Mateos",
    "gn:country_code":"MX",
    "gn:dem":1185,
    "gn:feature_class":"P",
    "gn:feature_code":"PPL",
    "gn:name":"Adolfo L\u00f3pez Mateos",
    "gn:population":500,
    "gn:timezone":"America/Mexico_City",
    "iso:country":"MX",
    "name:und_x_variant":[
        "Adolfo L\u00f3pez Mateos"
    ],
    "wof:name":"Adolfo Lopez Mateos",
    "wof:placetype":"locality",
    "wof:population":500
},
  "geometry": {"coordinates":[-92.93611,16.89306],"type":"Point"}
}