{
  "type": "Feature",
  "properties": {
    "gn:admin1_code":"30",
    "gn:admin2_code":"108",
    "gn:asciiname":"Mata Redonda",
    "gn:country_code":"MX",
    "gn:dem":15,
    "gn:feature_class":"P",
    "gn:feature_code":"PPL",
    "gn:name":"Mata Redonda",
    "gn:population":15,
    "gn:timezone":"America/Mexico_City",
    "iso:country":"MX",
    "wof:name":"Mata Redonda",
    "wof:placetype":"locality",
    "wof:population":15
},
  "geometry": {"coordinates":[-94.49833,17.82943999999999],"type":"Point"}
}