{
  "type": "Feature",
  "properties": {
    "gn:admin1_code":"27",
    "gn:admin2_code":"1.0",
    "gn:asciiname":"Potrero del Llano",
    "gn:country_code":"MX",
    "gn:dem":42,
    "gn:feature_class":"P",
    "gn:feature_code":"PPL",
    "gn:name":"Potrero del Llano",
    "gn:population":6,
    "gn:timezone":"America/Mexico_City",
    "iso:country":"MX",
    "name:ceb_x_preferred":[
        "Potrero del Llano"
    ],
    "name:sco_x_preferred":[
        "Potrero del Llano"
    ],
    "name:swe_x_preferred":[
        "Potrero del Llano"
    ],
    "wof:name":"Potrero del Llano",
    "wof:placetype":"locality",
    "wof:population":6
},
  "geometry": {"coordinates":[-91.39167,17.95917],"type":"Point"}
}