{
  "type": "Feature",
  "properties": {
    "gn:admin1_code":"6.0",
    "gn:admin2_code":"65.0",
    "gn:asciiname":"Sehuarabo",
    "gn:country_code":"MX",
    "gn:dem":2155,
    "gn:feature_class":"P",
    "gn:feature_code":"PPL",
    "gn:name":"Sehuarabo",
    "gn:population":0,
    "gn:timezone":"America/Chihuahua",
    "iso:country":"MX",
    "name:spa_x_preferred":[
        "Sehuarabo"
    ],
    "wof:name":"Sehuarabo",
    "wof:placetype":"locality"
},
  "geometry": {"coordinates":[-107.89091999999999,27.38893],"type":"Point"}
}