{
  "type": "Feature",
  "properties": {
    "gn:admin1_code":"11.0",
    "gn:admin2_code":"8.0",
    "gn:asciiname":"Sitio de Maravillas",
    "gn:country_code":"MX",
    "gn:dem":1728,
    "gn:feature_class":"P",
    "gn:feature_code":"PPL",
    "gn:name":"Sitio de Maravillas",
    "gn:population":0,
    "gn:timezone":"America/Mexico_City",
    "iso:country":"MX",
    "name:spa_x_preferred":[
        "Sitio de Maravillas"
    ],
    "name:spa_x_variant":[
        "El Sitio de Maravillas"
    ],
    "name:und_x_variant":[
        "El Sitio"
    ],
    "wof:name":"Sitio de Maravillas",
    "wof:placetype":"locality"
},
  "geometry": {"coordinates":[-101.8967,20.78634],"type":"Point"}
}