{
  "type": "Feature",
  "properties": {
    "gn:admin1_code":"7",
    "gn:admin2_code":"5.0",
    "gn:asciiname":"Los San Migueles",
    "gn:country_code":"MX",
    "gn:dem":450,
    "gn:feature_class":"P",
    "gn:feature_code":"PPL",
    "gn:name":"Los San Migueles",
    "gn:population":0,
    "gn:timezone":"America/Monterrey",
    "iso:country":"MX",
    "name:spa_x_preferred":[
        "Los San Migueles"
    ],
    "wof:name":"Los San Migueles",
    "wof:placetype":"locality"
},
  "geometry": {"coordinates":[-100.5926,26.80279],"type":"Point"}
}