{
  "type": "Feature",
  "properties": {
    "gn:admin1_code":"27",
    "gn:admin2_code":"16.0",
    "gn:asciiname":"Ignacio Lopez Rayon",
    "gn:country_code":"MX",
    "gn:dem":22,
    "gn:feature_class":"P",
    "gn:feature_code":"PPL",
    "gn:name":"Ignacio L\u00f3pez Ray\u00f3n",
    "gn:population":0,
    "gn:timezone":"America/Mexico_City",
    "iso:country":"MX",
    "name:spa_x_preferred":[
        "Ignacio L\u00f3pez Ray\u00f3n"
    ],
    "name:spa_x_variant":[
        "Segunda Secci\u00f3n"
    ],
    "wof:name":"Ignacio Lopez Rayon",
    "wof:placetype":"locality"
},
  "geometry": {"coordinates":[-92.96418,17.62911],"type":"Point"}
}