{
  "type": "Feature",
  "properties": {
    "gn:admin1_code":"5.0",
    "gn:asciiname":"Jutube",
    "gn:country_code":"MX",
    "gn:dem":1817,
    "gn:feature_class":"P",
    "gn:feature_code":"PPL",
    "gn:name":"Jutub\u00e9",
    "gn:population":0,
    "gn:timezone":"America/Mexico_City",
    "iso:country":"MX",
    "name:spa_x_preferred":[
        "Jutub\u00e9"
    ],
    "wof:name":"Jutube",
    "wof:placetype":"locality"
},
  "geometry": {"coordinates":[-92.34694,16.81407],"type":"Point"}
}