{
  "type": "Feature",
  "properties": {
    "gn:admin1_code":"16",
    "gn:admin2_code":"22.0",
    "gn:asciiname":"El Columpio",
    "gn:country_code":"MX",
    "gn:dem":2102,
    "gn:feature_class":"P",
    "gn:feature_code":"PPL",
    "gn:name":"El Columpio",
    "gn:population":8,
    "gn:timezone":"America/Mexico_City",
    "iso:country":"MX",
    "wof:name":"El Columpio",
    "wof:placetype":"locality",
    "wof:population":8
},
  "geometry": {"coordinates":[-101.07832999999999,19.675],"type":"Point"}
}