{
  "type": "Feature",
  "properties": {
    "gn:admin1_code":"21",
    "gn:admin2_code":"189",
    "gn:asciiname":"Cristo Rey",
    "gn:country_code":"MX",
    "gn:dem":1981,
    "gn:feature_class":"P",
    "gn:feature_code":"PPL",
    "gn:name":"Cristo Rey",
    "gn:population":27,
    "gn:timezone":"America/Mexico_City",
    "iso:country":"MX",
    "name:ceb_x_preferred":[
        "Cristo Rey"
    ],
    "name:fra_x_preferred":[
        "Statue du Christ-Roi"
    ],
    "name:hun_x_preferred":[
        "Krisztus kir\u00e1ly szobor"
    ],
    "name:nds_x_preferred":[
        "Cristo Rey"
    ],
    "name:spa_x_preferred":[
        "Cristo Rey"
    ],
    "name:swe_x_preferred":[
        "Cristo Rey"
    ],
    "wof:name":"Cristo Rey",
    "wof:placetype":"locality",
    "wof:population":27
},
  "geometry": {"coordinates":[-97.81995000000001,18.82904],"type":"Point"}
}