{
  "type": "Feature",
  "properties": {
    "gn:admin1_code":"18.0",
    "gn:admin2_code":"9.0",
    "gn:asciiname":"Los Ranchos",
    "gn:country_code":"MX",
    "gn:dem":1494,
    "gn:feature_class":"P",
    "gn:feature_code":"PPL",
    "gn:name":"Los Ranchos",
    "gn:population":0,
    "gn:timezone":"America/Mazatlan",
    "iso:country":"MX",
    "name:ceb_x_preferred":[
        "Los Ranchos"
    ],
    "name:spa_x_preferred":[
        "Los Ranchos"
    ],
    "name:swe_x_preferred":[
        "Los Ranchos"
    ],
    "wof:name":"Los Ranchos",
    "wof:placetype":"locality"
},
  "geometry": {"coordinates":[-104.67944,22.23203],"type":"Point"}
}