{
  "type": "Feature",
  "properties": {
    "gn:admin1_code":"12",
    "gn:admin2_code":"73.0",
    "gn:asciiname":"El Ocotito",
    "gn:country_code":"MX",
    "gn:dem":1098,
    "gn:feature_class":"P",
    "gn:feature_code":"PPL",
    "gn:name":"El Ocotito",
    "gn:population":8,
    "gn:timezone":"America/Mexico_City",
    "iso:country":"MX",
    "wof:name":"El Ocotito",
    "wof:placetype":"locality",
    "wof:population":8
},
  "geometry": {"coordinates":[-101.15615,18.18632],"type":"Point"}
}