{
  "type": "Feature",
  "properties": {
    "gn:admin1_code":"21",
    "gn:admin2_code":"67.0",
    "gn:asciiname":"Rancho los Gomez (Rancho Nuevo)",
    "gn:country_code":"MX",
    "gn:dem":2503,
    "gn:feature_class":"P",
    "gn:feature_code":"PPL",
    "gn:name":"Rancho los G\u00f3mez (Rancho Nuevo)",
    "gn:population":9,
    "gn:timezone":"America/Mexico_City",
    "iso:country":"MX",
    "name:und_x_variant":[
        "Rancho los G\u00f3mez (Rancho Nuevo)"
    ],
    "wof:name":"Rancho los Gomez (Rancho Nuevo)",
    "wof:placetype":"locality",
    "wof:population":9
},
  "geometry": {"coordinates":[-97.42976,19.28537],"type":"Point"}
}