{
  "type": "Feature",
  "properties": {
    "gn:admin1_code":"14",
    "gn:admin2_code":"61",
    "gn:asciiname":"Agua Puerca",
    "gn:country_code":"MX",
    "gn:dem":1950,
    "gn:feature_class":"P",
    "gn:feature_code":"PPL",
    "gn:name":"Agua Puerca",
    "gn:population":20,
    "gn:timezone":"America/Mexico_City",
    "iso:country":"MX",
    "name:srp_x_preferred":[
        "\u0410\u0433\u0432\u0430 \u041f\u0443\u0435\u0440\u043a\u0430"
    ],
    "wof:name":"Agua Puerca",
    "wof:placetype":"locality",
    "wof:population":20
},
  "geometry": {"coordinates":[-104.25472000000001,22.25833],"type":"Point"}
}