{
  "type": "Feature",
  "properties": {
    "gn:admin1_code":"20",
    "gn:admin2_code":"327.0",
    "gn:asciiname":"Lagunillas",
    "gn:country_code":"MX",
    "gn:dem":42,
    "gn:feature_class":"P",
    "gn:feature_code":"PPL",
    "gn:name":"Lagunillas",
    "gn:population":5,
    "gn:timezone":"America/Mexico_City",
    "iso:country":"MX",
    "name:ceb_x_preferred":[
        "Lagunillas"
    ],
    "name:deu_x_preferred":[
        "Lagunillas"
    ],
    "name:fra_x_preferred":[
        "Lagunillas"
    ],
    "name:ita_x_preferred":[
        "Lagunillas"
    ],
    "name:lit_x_preferred":[
        "Laguniljasas"
    ],
    "name:nld_x_preferred":[
        "Lagunillas"
    ],
    "name:sco_x_preferred":[
        "Lagunillas"
    ],
    "name:spa_x_preferred":[
        "Lagunillas"
    ],
    "name:swe_x_preferred":[
        "Lagunillas"
    ],
    "wof:name":"Lagunillas",
    "wof:placetype":"locality",
    "wof:population":5
},
  "geometry": {"coordinates":[-94.23721999999999,16.32777999999999],"type":"Point"}
}