{
  "type": "Feature",
  "properties": {
    "gn:admin1_code":"22",
    "gn:admin2_code":"17.0",
    "gn:asciiname":"Rancho el Batan",
    "gn:country_code":"MX",
    "gn:dem":1999,
    "gn:feature_class":"P",
    "gn:feature_code":"PPL",
    "gn:name":"Rancho el Bat\u00e1n",
    "gn:population":5,
    "gn:timezone":"America/Mexico_City",
    "iso:country":"MX",
    "name:und_x_variant":[
        "Rancho el Bat\u00e1n"
    ],
    "wof:name":"Rancho el Batan",
    "wof:placetype":"locality",
    "wof:population":5
},
  "geometry": {"coordinates":[-100.05611,20.62056],"type":"Point"}
}