{
  "type": "Feature",
  "properties": {
    "gn:admin1_code":"26.0",
    "gn:admin2_code":"69.0",
    "gn:asciiname":"Cajon de en Medio",
    "gn:country_code":"MX",
    "gn:dem":1426,
    "gn:feature_class":"P",
    "gn:feature_code":"PPL",
    "gn:name":"Caj\u00f3n de en Medio",
    "gn:population":0,
    "gn:timezone":"America/Hermosillo",
    "iso:country":"MX",
    "name:spa_x_preferred":[
        "Caj\u00f3n de en Medio"
    ],
    "wof:name":"Cajon de en Medio",
    "wof:placetype":"locality"
},
  "geometry": {"coordinates":[-109.09601000000001,28.27898],"type":"Point"}
}