{
  "type": "Feature",
  "properties": {
    "gn:admin1_code":"15",
    "gn:admin2_code":"21.0",
    "gn:asciiname":"San Jose del Progreso",
    "gn:country_code":"MX",
    "gn:dem":2348,
    "gn:feature_class":"P",
    "gn:feature_code":"PPL",
    "gn:name":"San Jos\u00e9 del Progreso",
    "gn:population":0,
    "gn:timezone":"America/Mexico_City",
    "iso:country":"MX",
    "name:spa_x_preferred":[
        "San Jos\u00e9 del Progreso"
    ],
    "name:und_x_variant":[
        "San Jos\u00e9 de Progreso"
    ],
    "wof:name":"San Jose del Progreso",
    "wof:placetype":"locality"
},
  "geometry": {"coordinates":[-99.7923,18.93443],"type":"Point"}
}