{
  "type": "Feature",
  "properties": {
    "gn:admin1_code":"30.0",
    "gn:asciiname":"Las Pocitas",
    "gn:country_code":"MX",
    "gn:dem":52,
    "gn:feature_class":"P",
    "gn:feature_code":"PPL",
    "gn:name":"Las Pocitas",
    "gn:population":0,
    "gn:timezone":"America/Mexico_City",
    "iso:country":"MX",
    "name:spa_x_preferred":[
        "Las Pocitas"
    ],
    "wof:name":"Las Pocitas",
    "wof:placetype":"locality"
},
  "geometry": {"coordinates":[-97.77318,21.91842],"type":"Point"}
}