{
  "type": "Feature",
  "properties": {
    "gn:admin1_code":"12",
    "gn:admin2_code":"46.0",
    "gn:asciiname":"Las Iguanas",
    "gn:country_code":"MX",
    "gn:dem":38,
    "gn:feature_class":"P",
    "gn:feature_code":"PPL",
    "gn:name":"Las Iguanas",
    "gn:population":448,
    "gn:timezone":"America/Mexico_City",
    "iso:country":"MX",
    "wof:name":"Las Iguanas",
    "wof:placetype":"locality",
    "wof:population":448
},
  "geometry": {"coordinates":[-98.42,16.63],"type":"Point"}
}