{
  "type": "Feature",
  "properties": {
    "gn:admin1_code":"32",
    "gn:admin2_code":"55.0",
    "gn:asciiname":"Colonia Lazaro Cardenas",
    "gn:country_code":"MX",
    "gn:dem":2099,
    "gn:feature_class":"P",
    "gn:feature_code":"PPL",
    "gn:name":"Colonia L\u00e1zaro C\u00e1rdenas",
    "gn:population":102,
    "gn:timezone":"America/Mexico_City",
    "iso:country":"MX",
    "wof:name":"Colonia Lazaro Cardenas",
    "wof:placetype":"locality",
    "wof:population":102
},
  "geometry": {"coordinates":[-103.01949999999999,22.19342],"type":"Point"}
}