{
  "type": "Feature",
  "properties": {
    "gn:admin1_code":"20",
    "gn:admin2_code":"280.0",
    "gn:asciiname":"San Bartolome Yatoni",
    "gn:country_code":"MX",
    "gn:dem":1641,
    "gn:feature_class":"P",
    "gn:feature_code":"PPL",
    "gn:name":"San Bartolom\u00e9 Yatoni",
    "gn:population":293,
    "gn:timezone":"America/Mexico_City",
    "iso:country":"MX",
    "name:und_x_variant":[
        "San Bartolom\u00e9 Yatoni"
    ],
    "wof:name":"San Bartolome Yatoni",
    "wof:placetype":"locality",
    "wof:population":293
},
  "geometry": {"coordinates":[-96.24889,17.37917],"type":"Point"}
}