{
  "type": "Feature",
  "properties": {
    "gn:admin1_code":"11",
    "gn:admin2_code":"15",
    "gn:asciiname":"La Presa de Burrones",
    "gn:country_code":"MX",
    "gn:dem":1998,
    "gn:feature_class":"P",
    "gn:feature_code":"PPL",
    "gn:name":"La Presa de Burrones",
    "gn:population":10,
    "gn:timezone":"America/Mexico_City",
    "iso:country":"MX",
    "wof:name":"La Presa de Burrones",
    "wof:placetype":"locality",
    "wof:population":10
},
  "geometry": {"coordinates":[-101.29333,21.01472],"type":"Point"}
}