{
  "type": "Feature",
  "properties": {
    "gn:admin1_code":"6",
    "gn:admin2_code":"5.0",
    "gn:asciiname":"Santa Maria",
    "gn:country_code":"MX",
    "gn:dem":1215,
    "gn:feature_class":"P",
    "gn:feature_code":"PPL",
    "gn:name":"Santa Mar\u00eda",
    "gn:population":6,
    "gn:timezone":"America/Chihuahua",
    "iso:country":"MX",
    "name:spa_x_preferred":[
        "Santa Mar\u00eda"
    ],
    "name:und_x_variant":[
        "Santa Marta"
    ],
    "wof:name":"Santa Maria",
    "wof:placetype":"locality",
    "wof:population":6
},
  "geometry": {"coordinates":[-107.20795,30.88015],"type":"Point"}
}