{
  "type": "Feature",
  "properties": {
    "gn:admin1_code":"15.0",
    "gn:admin2_code":"89.0",
    "gn:asciiname":"Santiago Tepopula",
    "gn:country_code":"MX",
    "gn:dem":2418,
    "gn:feature_class":"P",
    "gn:feature_code":"PPL",
    "gn:name":"Santiago Tepopula",
    "gn:population":0,
    "gn:timezone":"America/Mexico_City",
    "iso:country":"MX",
    "name:spa_x_preferred":[
        "Santiago Tepopula"
    ],
    "wof:name":"Santiago Tepopula",
    "wof:placetype":"locality"
},
  "geometry": {"coordinates":[-98.85692,19.14399],"type":"Point"}
}