{
  "type": "Feature",
  "properties": {
    "gn:admin1_code":"2",
    "gn:admin2_code":"2.0",
    "gn:asciiname":"Familia Gutierrez",
    "gn:country_code":"MX",
    "gn:dem":13,
    "gn:feature_class":"P",
    "gn:feature_code":"PPL",
    "gn:name":"Familia Guti\u00e9rrez",
    "gn:population":8,
    "gn:timezone":"America/Tijuana",
    "iso:country":"MX",
    "name:und_x_variant":[
        "Familia Guti\u00e9rrez"
    ],
    "wof:name":"Familia Gutierrez",
    "wof:placetype":"locality",
    "wof:population":8
},
  "geometry": {"coordinates":[-115.1375,32.34917],"type":"Point"}
}