{
  "type": "Feature",
  "properties": {
    "gn:admin1_code":"6",
    "gn:admin2_code":"51.0",
    "gn:asciiname":"La Huerta Tolano",
    "gn:country_code":"MX",
    "gn:dem":1731,
    "gn:feature_class":"P",
    "gn:feature_code":"PPL",
    "gn:name":"La Huerta Tolano",
    "gn:population":8,
    "gn:timezone":"America/Chihuahua",
    "iso:country":"MX",
    "wof:name":"La Huerta Tolano",
    "wof:placetype":"locality",
    "wof:population":8
},
  "geometry": {"coordinates":[-108.32496,28.28962000000001],"type":"Point"}
}