{
  "type": "Feature",
  "properties": {
    "gn:admin1_code":"6.0",
    "gn:admin2_code":"1.0",
    "gn:asciiname":"El Apache",
    "gn:country_code":"MX",
    "gn:dem":1251,
    "gn:feature_class":"P",
    "gn:feature_code":"PPL",
    "gn:name":"El Apache",
    "gn:population":0,
    "gn:timezone":"America/Chihuahua",
    "iso:country":"MX",
    "name:und_x_variant":[
        "Pozo El Apache",
        "El Apache"
    ],
    "wof:name":"El Apache",
    "wof:placetype":"locality"
},
  "geometry": {"coordinates":[-106.65288,30.34203],"type":"Point"}
}