{
  "type": "Feature",
  "properties": {
    "gn:admin1_code":"12",
    "gn:admin2_code":"45",
    "gn:asciiname":"Metlatijca",
    "gn:country_code":"MX",
    "gn:dem":1646,
    "gn:feature_class":"P",
    "gn:feature_code":"PPL",
    "gn:name":"Metlatijca",
    "gn:population":45,
    "gn:timezone":"America/Mexico_City",
    "iso:country":"MX",
    "wof:name":"Metlatijca",
    "wof:placetype":"locality",
    "wof:population":45
},
  "geometry": {"coordinates":[-98.69334000000001,17.86022999999999],"type":"Point"}
}