{
  "type": "Feature",
  "properties": {
    "gn:admin1_code":"6",
    "gn:admin2_code":"40.0",
    "gn:asciiname":"Sahuarachic",
    "gn:country_code":"MX",
    "gn:dem":2302,
    "gn:feature_class":"P",
    "gn:feature_code":"PPL",
    "gn:name":"Sahuarachic",
    "gn:population":0,
    "gn:timezone":"America/Chihuahua",
    "iso:country":"MX",
    "wof:name":"Sahuarachic",
    "wof:placetype":"locality"
},
  "geometry": {"coordinates":[-108.23333,28.76667],"type":"Point"}
}