{
  "type": "Feature",
  "properties": {
    "gn:admin1_code":"6.0",
    "gn:admin2_code":"65.0",
    "gn:asciiname":"Mesa del Manzano",
    "gn:country_code":"MX",
    "gn:dem":2194,
    "gn:feature_class":"P",
    "gn:feature_code":"PPL",
    "gn:name":"Mesa del Manzano",
    "gn:population":0,
    "gn:timezone":"America/Chihuahua",
    "iso:country":"MX",
    "name:spa_x_preferred":[
        "Mesa del Manzano"
    ],
    "wof:name":"Mesa del Manzano",
    "wof:placetype":"locality"
},
  "geometry": {"coordinates":[-107.88629,27.34564],"type":"Point"}
}