{
  "type": "Feature",
  "properties": {
    "gn:admin1_code":"6.0",
    "gn:admin2_code":"40.0",
    "gn:asciiname":"El Bajio",
    "gn:country_code":"MX",
    "gn:dem":1642,
    "gn:feature_class":"P",
    "gn:feature_code":"PPL",
    "gn:name":"El Baj\u00edo",
    "gn:population":0,
    "gn:timezone":"America/Chihuahua",
    "iso:country":"MX",
    "name:spa_x_preferred":[
        "El Baj\u00edo"
    ],
    "name:spa_x_variant":[
        "El Bajio"
    ],
    "wof:name":"El Bajio",
    "wof:placetype":"locality"
},
  "geometry": {"coordinates":[-108.50301,29.22497000000001],"type":"Point"}
}