{
  "type": "Feature",
  "properties": {
    "gn:admin1_code":"28.0",
    "gn:admin2_code":"35.0",
    "gn:asciiname":"Poza Rica",
    "gn:country_code":"MX",
    "gn:dem":84,
    "gn:feature_class":"P",
    "gn:feature_code":"PPL",
    "gn:name":"Poza Rica",
    "gn:population":0,
    "gn:timezone":"America/Monterrey",
    "iso:country":"MX",
    "name:spa_x_preferred":[
        "Poza Rica"
    ],
    "wof:name":"Poza Rica",
    "wof:placetype":"locality"
},
  "geometry": {"coordinates":[-98.19646,24.80817],"type":"Point"}
}