{
  "type": "Feature",
  "properties": {
    "gn:admin1_code":"28.0",
    "gn:admin2_code":"35.0",
    "gn:asciiname":"Poza Rica",
    "gn:country_code":"MX",
    "gn:dem":84,
    "gn:feature_class":"P",
    "gn:feature_code":"PPL",
    "gn:name":"Poza Rica",
    "gn:population":0,
    "gn:timezone":"America/Monterrey",
    "iso:country":"MX",
    "name:fas_x_preferred":[
        "\u067e\u0648\u0632\u0627 \u0631\u06cc\u06a9\u0627"
    ],
    "name:fra_x_preferred":[
        "Poza Rica"
    ],
    "name:ita_x_preferred":[
        "Poza Rica"
    ],
    "name:lit_x_preferred":[
        "Posa Rika"
    ],
    "name:nld_x_preferred":[
        "Poza Rica"
    ],
    "name:pol_x_preferred":[
        "Poza Rica"
    ],
    "name:por_x_preferred":[
        "Poza Rica"
    ],
    "name:rus_x_preferred":[
        "\u041f\u043e\u0441\u0430-\u0420\u0438\u043a\u0430-\u0434\u0435-\u0418\u0434\u0430\u043b\u044c\u0433\u043e"
    ],
    "name:spa_x_preferred":[
        "Poza Rica"
    ],
    "name:srp_x_preferred":[
        "\u041f\u043e\u0437\u0430 \u0420\u0438\u043a\u0430 \u0434\u0435 \u0418\u0434\u0430\u043b\u0433\u043e"
    ],
    "name:urd_x_preferred":[
        "\u067e\u0648\u0633\u0627 \u0631\u06cc\u06a9\u0627"
    ],
    "name:zho_x_preferred":[
        "\u6ce2\u85a9\u91cc\u5361"
    ],
    "wof:name":"Poza Rica",
    "wof:placetype":"locality"
},
  "geometry": {"coordinates":[-98.19646,24.80817],"type":"Point"}
}