{
  "type": "Feature",
  "properties": {
    "gn:admin1_code":"6",
    "gn:admin2_code":"19.0",
    "gn:asciiname":"El Sahuaro",
    "gn:country_code":"MX",
    "gn:dem":1549,
    "gn:feature_class":"P",
    "gn:feature_code":"PPL",
    "gn:name":"El Sahuaro",
    "gn:population":4,
    "gn:timezone":"America/Chihuahua",
    "iso:country":"MX",
    "wof:name":"El Sahuaro",
    "wof:placetype":"locality",
    "wof:population":4
},
  "geometry": {"coordinates":[-106.20022,28.84685],"type":"Point"}
}