{
  "type": "Feature",
  "properties": {
    "gn:admin1_code":"26",
    "gn:admin2_code":"57.0",
    "gn:asciiname":"La Leonera",
    "gn:country_code":"MX",
    "gn:dem":541,
    "gn:feature_class":"P",
    "gn:feature_code":"PPL",
    "gn:name":"La Leonera",
    "gn:population":0,
    "gn:timezone":"America/Hermosillo",
    "iso:country":"MX",
    "name:spa_x_preferred":[
        "La Leonera"
    ],
    "wof:name":"La Leonera",
    "wof:placetype":"locality"
},
  "geometry": {"coordinates":[-109.82222,29.49013],"type":"Point"}
}