{
  "type": "Feature",
  "properties": {
    "gn:admin1_code":"30",
    "gn:admin2_code":"158.0",
    "gn:asciiname":"Chichicatzapan Mendez",
    "gn:country_code":"MX",
    "gn:dem":41,
    "gn:feature_class":"P",
    "gn:feature_code":"PPL",
    "gn:name":"Chichicatzapan M\u00e9ndez",
    "gn:population":0,
    "gn:timezone":"America/Mexico_City",
    "iso:country":"MX",
    "name:spa_x_preferred":[
        "Chichicatzapan M\u00e9ndez"
    ],
    "name:spa_x_variant":[
        "Chichicatzapah G\u00f3mez"
    ],
    "name:und_x_variant":[
        "Chichicatzapa",
        "Chichicazap\u00e1n M\u00e9ndez",
        "Chichicatzap\u00e1n M\u00e9ndez",
        "Chichicatzap\u00e1n G\u00f3mez",
        "Chichicatzap\u00e1n"
    ],
    "wof:name":"Chichicatzapan Mendez",
    "wof:placetype":"locality"
},
  "geometry": {"coordinates":[-97.10771,20.34705],"type":"Point"}
}