{
  "type": "Feature",
  "properties": {
    "gn:admin1_code":"12.0",
    "gn:admin2_code":"68.0",
    "gn:asciiname":"La Barranca de San Diego",
    "gn:country_code":"MX",
    "gn:dem":187,
    "gn:feature_class":"P",
    "gn:feature_code":"PPL",
    "gn:name":"La Barranca de San Diego",
    "gn:population":0,
    "gn:timezone":"America/Mexico_City",
    "iso:country":"MX",
    "name:spa_x_preferred":[
        "La Barranca de San Diego"
    ],
    "name:und_x_variant":[
        "Barranca San Diego"
    ],
    "wof:name":"La Barranca de San Diego",
    "wof:placetype":"locality"
},
  "geometry": {"coordinates":[-101.8955,18.21131],"type":"Point"}
}