{
  "type": "Feature",
  "properties": {
    "gn:admin1_code":"11",
    "gn:admin2_code":"37.0",
    "gn:asciiname":"Colonia Juan Jose Torres Landa",
    "gn:country_code":"MX",
    "gn:dem":1804,
    "gn:feature_class":"P",
    "gn:feature_code":"PPL",
    "gn:name":"Colonia Juan Jos\u00e9 Torres Landa",
    "gn:population":116,
    "gn:timezone":"America/Mexico_City",
    "iso:country":"MX",
    "name:und_x_variant":[
        "Colonia Juan Jos\u00e9 Torres Landa"
    ],
    "wof:name":"Colonia Juan Jose Torres Landa",
    "wof:placetype":"locality",
    "wof:population":116
},
  "geometry": {"coordinates":[-101.56194000000001,21.01194],"type":"Point"}
}