{
  "type": "Feature",
  "properties": {
    "gn:admin1_code":"18.0",
    "gn:admin2_code":"9.0",
    "gn:asciiname":"El Guaco",
    "gn:country_code":"MX",
    "gn:dem":885,
    "gn:feature_class":"P",
    "gn:feature_code":"PPL",
    "gn:name":"El Guaco",
    "gn:population":0,
    "gn:timezone":"America/Mazatlan",
    "iso:country":"MX",
    "name:spa_x_preferred":[
        "El Guaco"
    ],
    "wof:name":"El Guaco",
    "wof:placetype":"locality"
},
  "geometry": {"coordinates":[-104.54504,22.2345],"type":"Point"}
}