{
  "type": "Feature",
  "properties": {
    "gn:admin1_code":"2",
    "gn:admin2_code":"1.0",
    "gn:asciiname":"Chula Vista",
    "gn:country_code":"MX",
    "gn:dem":17,
    "gn:feature_class":"P",
    "gn:feature_code":"PPL",
    "gn:name":"Chula Vista",
    "gn:population":0,
    "gn:timezone":"America/Tijuana",
    "iso:country":"MX",
    "name:spa_x_preferred":[
        "Chula Vista"
    ],
    "wof:name":"Chula Vista",
    "wof:placetype":"locality"
},
  "geometry": {"coordinates":[-114.0436,28.49972],"type":"Point"}
}