{
  "type": "Feature",
  "properties": {
    "gn:admin1_code":"14.0",
    "gn:admin2_code":"49.0",
    "gn:asciiname":"Las Fabricas",
    "gn:country_code":"MX",
    "gn:dem":985,
    "gn:feature_class":"P",
    "gn:feature_code":"PPL",
    "gn:name":"Las Fabricas",
    "gn:population":0,
    "gn:timezone":"America/Mexico_City",
    "iso:country":"MX",
    "name:spa_x_preferred":[
        "Las Fabricas"
    ],
    "wof:name":"Las Fabricas",
    "wof:placetype":"locality"
},
  "geometry": {"coordinates":[-103.04719,19.16841],"type":"Point"}
}