{
  "type": "Feature",
  "properties": {
    "gn:admin1_code":"3",
    "gn:admin2_code":"1.0",
    "gn:asciiname":"Santa Adelaida",
    "gn:country_code":"MX",
    "gn:dem":11,
    "gn:feature_class":"P",
    "gn:feature_code":"PPL",
    "gn:name":"Santa Adelaida",
    "gn:population":8,
    "gn:timezone":"America/Mazatlan",
    "iso:country":"MX",
    "wof:name":"Santa Adelaida",
    "wof:placetype":"locality",
    "wof:population":8
},
  "geometry": {"coordinates":[-111.90298,24.94801],"type":"Point"}
}