{
  "type": "Feature",
  "properties": {
    "gn:admin1_code":"13",
    "gn:admin2_code":"57",
    "gn:asciiname":"Loma del Toro",
    "gn:country_code":"MX",
    "gn:dem":2607,
    "gn:feature_class":"P",
    "gn:feature_code":"PPL",
    "gn:name":"Loma del Toro",
    "gn:population":26,
    "gn:timezone":"America/Mexico_City",
    "iso:country":"MX",
    "wof:name":"Loma del Toro",
    "wof:placetype":"locality",
    "wof:population":26
},
  "geometry": {"coordinates":[-98.54694000000001,19.96],"type":"Point"}
}