{
  "type": "Feature",
  "properties": {
    "gn:admin1_code":"5",
    "gn:admin2_code":"19.0",
    "gn:asciiname":"San Rafael Chacaljemel",
    "gn:country_code":"MX",
    "gn:dem":1576,
    "gn:feature_class":"P",
    "gn:feature_code":"PPL",
    "gn:name":"San Rafael Chacaljemel",
    "gn:population":191,
    "gn:timezone":"America/Mexico_City",
    "iso:country":"MX",
    "wof:name":"San Rafael Chacaljemel",
    "wof:placetype":"locality",
    "wof:population":191
},
  "geometry": {"coordinates":[-92.10138999999999,16.16639],"type":"Point"}
}