{
  "type": "Feature",
  "properties": {
    "gn:admin1_code":"2",
    "gn:admin2_code":"4",
    "gn:asciiname":"Rancho Mariscal",
    "gn:country_code":"MX",
    "gn:dem":194,
    "gn:feature_class":"P",
    "gn:feature_code":"PPL",
    "gn:name":"Rancho Mariscal",
    "gn:population":10,
    "gn:timezone":"America/Tijuana",
    "iso:country":"MX",
    "wof:name":"Rancho Mariscal",
    "wof:placetype":"locality",
    "wof:population":10
},
  "geometry": {"coordinates":[-116.79806000000001,32.49610999999999],"type":"Point"}
}