{
  "type": "Feature",
  "properties": {
    "gn:admin1_code":"28",
    "gn:admin2_code":"21",
    "gn:asciiname":"Juan Andrade Izaguirre",
    "gn:country_code":"MX",
    "gn:dem":86,
    "gn:feature_class":"P",
    "gn:feature_code":"PPL",
    "gn:name":"Juan Andrade Izaguirre",
    "gn:population":11,
    "gn:timezone":"America/Monterrey",
    "iso:country":"MX",
    "wof:name":"Juan Andrade Izaguirre",
    "wof:placetype":"locality",
    "wof:population":11
},
  "geometry": {"coordinates":[-98.80638999999999,22.38889],"type":"Point"}
}