{
  "type": "Feature",
  "properties": {
    "gn:admin1_code":"14.0",
    "gn:admin2_code":"56.0",
    "gn:asciiname":"Tepehuaje",
    "gn:country_code":"MX",
    "gn:dem":681,
    "gn:feature_class":"P",
    "gn:feature_code":"PPL",
    "gn:name":"Tepehuaje",
    "gn:population":0,
    "gn:timezone":"America/Mexico_City",
    "iso:country":"MX",
    "name:spa_x_preferred":[
        "Tepehuaje"
    ],
    "wof:name":"Tepehuaje",
    "wof:placetype":"locality"
},
  "geometry": {"coordinates":[-102.84593,19.39978],"type":"Point"}
}