{
  "type": "Feature",
  "properties": {
    "gn:admin1_code":"20.0",
    "gn:admin2_code":"73.0",
    "gn:asciiname":"Canada del Tejocote",
    "gn:country_code":"MX",
    "gn:dem":2431,
    "gn:feature_class":"P",
    "gn:feature_code":"PPL",
    "gn:name":"Ca\u00f1ada del Tejocote",
    "gn:population":0,
    "gn:timezone":"America/Mexico_City",
    "iso:country":"MX",
    "name:spa_x_preferred":[
        "Ca\u00f1ada del Tejocote"
    ],
    "wof:name":"Canada del Tejocote",
    "wof:placetype":"locality"
},
  "geometry": {"coordinates":[-97.82799,17.17077],"type":"Point"}
}