{
  "type": "Feature",
  "properties": {
    "gn:admin1_code":"16",
    "gn:admin2_code":"83",
    "gn:asciiname":"Las Higueras",
    "gn:country_code":"MX",
    "gn:dem":2066,
    "gn:feature_class":"P",
    "gn:feature_code":"PPL",
    "gn:name":"Las Higueras",
    "gn:population":22,
    "gn:timezone":"America/Mexico_City",
    "iso:country":"MX",
    "wof:name":"Las Higueras",
    "wof:placetype":"locality",
    "wof:population":22
},
  "geometry": {"coordinates":[-102.37472,19.35167],"type":"Point"}
}