{
  "type": "Feature",
  "properties": {
    "gn:admin1_code":"15",
    "gn:admin2_code":"124.0",
    "gn:asciiname":"Jesus Carranza",
    "gn:country_code":"MX",
    "gn:dem":2701,
    "gn:feature_class":"P",
    "gn:feature_code":"PPL",
    "gn:name":"Jes\u00fas Carranza",
    "gn:population":527,
    "gn:timezone":"America/Mexico_City",
    "iso:country":"MX",
    "name:und_x_variant":[
        "Jes\u00fas Carranza"
    ],
    "wof:name":"Jesus Carranza",
    "wof:placetype":"locality",
    "wof:population":527
},
  "geometry": {"coordinates":[-100.0997,19.70366],"type":"Point"}
}