{
  "type": "Feature",
  "properties": {
    "gn:admin1_code":"24.0",
    "gn:admin2_code":"43.0",
    "gn:asciiname":"Cerro de la Virgen",
    "gn:country_code":"MX",
    "gn:dem":1782,
    "gn:feature_class":"P",
    "gn:feature_code":"PPL",
    "gn:name":"Cerro de la V\u00edrgen",
    "gn:population":0,
    "gn:timezone":"America/Mexico_City",
    "iso:country":"MX",
    "name:spa_x_preferred":[
        "Cerro de la V\u00edrgen"
    ],
    "name:und_x_variant":[
        "Cerro Virgen"
    ],
    "wof:name":"Cerro de la Virgen",
    "wof:placetype":"locality"
},
  "geometry": {"coordinates":[-100.57658000000001,21.69232],"type":"Point"}
}