{
  "type": "Feature",
  "properties": {
    "gn:admin1_code":"5",
    "gn:admin2_code":"3.0",
    "gn:asciiname":"Los Cocos",
    "gn:country_code":"MX",
    "gn:dem":23,
    "gn:feature_class":"P",
    "gn:feature_code":"PPL",
    "gn:name":"Los Cocos",
    "gn:population":7,
    "gn:timezone":"America/Mexico_City",
    "iso:country":"MX",
    "name:nld_x_preferred":[
        "Los Cocos"
    ],
    "name:por_x_preferred":[
        "Los Cocos"
    ],
    "name:spa_x_preferred":[
        "Los Cocos"
    ],
    "wof:name":"Los Cocos",
    "wof:placetype":"locality",
    "wof:population":7
},
  "geometry": {"coordinates":[-92.65278000000001,15.22139],"type":"Point"}
}