{
  "type": "Feature",
  "properties": {
    "gn:admin1_code":"16.0",
    "gn:asciiname":"El Gigantito",
    "gn:country_code":"MX",
    "gn:dem":1989,
    "gn:feature_class":"P",
    "gn:feature_code":"PPL",
    "gn:name":"El Gigantito",
    "gn:population":0,
    "gn:timezone":"America/Mexico_City",
    "iso:country":"MX",
    "name:spa_x_preferred":[
        "El Gigantito"
    ],
    "name:spa_x_variant":[
        "Rancho el Gigantito"
    ],
    "wof:name":"El Gigantito",
    "wof:placetype":"locality"
},
  "geometry": {"coordinates":[-100.44569,19.96213],"type":"Point"}
}