{
  "type": "Feature",
  "properties": {
    "gn:admin1_code":"10",
    "gn:admin2_code":"19",
    "gn:asciiname":"Piloncillos",
    "gn:country_code":"MX",
    "gn:dem":2453,
    "gn:feature_class":"P",
    "gn:feature_code":"PPL",
    "gn:name":"Piloncillos",
    "gn:population":13,
    "gn:timezone":"America/Monterrey",
    "iso:country":"MX",
    "wof:name":"Piloncillos",
    "wof:placetype":"locality",
    "wof:population":13
},
  "geometry": {"coordinates":[-105.89117,24.73027],"type":"Point"}
}