{
  "type": "Feature",
  "properties": {
    "gn:admin1_code":"11",
    "gn:admin2_code":"20.0",
    "gn:asciiname":"Jorge Andrade Espinoza",
    "gn:country_code":"MX",
    "gn:dem":1799,
    "gn:feature_class":"P",
    "gn:feature_code":"PPL",
    "gn:name":"Jorge Andrade Espinoza",
    "gn:population":8,
    "gn:timezone":"America/Mexico_City",
    "iso:country":"MX",
    "wof:name":"Jorge Andrade Espinoza",
    "wof:placetype":"locality",
    "wof:population":8
},
  "geometry": {"coordinates":[-101.60944000000001,21.01472],"type":"Point"}
}