{
  "type": "Feature",
  "properties": {
    "gn:admin1_code":"17",
    "gn:asciiname":"Acayucan",
    "gn:country_code":"MX",
    "gn:dem":2414,
    "gn:feature_class":"P",
    "gn:feature_code":"PPL",
    "gn:name":"Acayucan",
    "gn:population":0,
    "gn:timezone":"America/Mexico_City",
    "iso:country":"MX",
    "name:cat_x_preferred":[
        "Acayucan"
    ],
    "name:ceb_x_preferred":[
        "Acayucan"
    ],
    "name:epo_x_preferred":[
        "Acayucan"
    ],
    "name:fas_x_preferred":[
        "\u0627\u06a9\u0627\u06cc\u0648\u06a9\u0627\u0646"
    ],
    "name:nld_x_preferred":[
        "Acayucan"
    ],
    "name:pol_x_preferred":[
        "Acayucan"
    ],
    "name:por_x_preferred":[
        "Acayucan"
    ],
    "name:rus_x_preferred":[
        "\u0410\u043a\u0430\u044e\u043a\u0430\u043d"
    ],
    "name:sco_x_preferred":[
        "Acayucan"
    ],
    "name:spa_x_preferred":[
        "Acayucan"
    ],
    "name:srp_x_preferred":[
        "\u0410\u043a\u0430\u0458\u0443\u043a\u0430\u043d"
    ],
    "name:swe_x_preferred":[
        "Acayucan"
    ],
    "name:vie_x_preferred":[
        "Acayucan"
    ],
    "name:zho_x_preferred":[
        "\u963f\u5361\u5c24\u574e"
    ],
    "wof:name":"Acayucan",
    "wof:placetype":"locality"
},
  "geometry": {"coordinates":[-98.86637,19.73856],"type":"Point"}
}