{
  "type": "Feature",
  "properties": {
    "gn:admin1_code":"17",
    "gn:asciiname":"Acayucan",
    "gn:country_code":"MX",
    "gn:dem":2414,
    "gn:feature_class":"P",
    "gn:feature_code":"PPL",
    "gn:name":"Acayucan",
    "gn:population":0,
    "gn:timezone":"America/Mexico_City",
    "iso:country":"MX",
    "name:spa_x_preferred":[
        "Acayucan"
    ],
    "wof:name":"Acayucan",
    "wof:placetype":"locality"
},
  "geometry": {"coordinates":[-98.86637,19.73856],"type":"Point"}
}