{
  "type": "Feature",
  "properties": {
    "gn:admin1_code":"6",
    "gn:admin2_code":"26.0",
    "gn:asciiname":"Juan Diaz",
    "gn:country_code":"MX",
    "gn:dem":1728,
    "gn:feature_class":"P",
    "gn:feature_code":"PPL",
    "gn:name":"Juan D\u00edaz",
    "gn:population":0,
    "gn:timezone":"America/Chihuahua",
    "iso:country":"MX",
    "wof:name":"Juan Diaz",
    "wof:placetype":"locality"
},
  "geometry": {"coordinates":[-106.55,28.28333],"type":"Point"}
}