{
  "type": "Feature",
  "properties": {
    "gn:admin1_code":"31.0",
    "gn:asciiname":"Chapultepec",
    "gn:country_code":"MX",
    "gn:dem":18,
    "gn:feature_class":"P",
    "gn:feature_code":"PPL",
    "gn:name":"Chapultepec",
    "gn:population":0,
    "gn:timezone":"America/Merida",
    "iso:country":"MX",
    "name:spa_x_preferred":[
        "Chapultepec"
    ],
    "wof:name":"Chapultepec",
    "wof:placetype":"locality"
},
  "geometry": {"coordinates":[-88.01552,21.08778],"type":"Point"}
}