{
  "type": "Feature",
  "properties": {
    "gn:admin1_code":"6",
    "gn:admin2_code":"66",
    "gn:asciiname":"Los Lajeros",
    "gn:country_code":"MX",
    "gn:dem":1758,
    "gn:feature_class":"P",
    "gn:feature_code":"PPL",
    "gn:name":"Los Lajeros",
    "gn:population":31,
    "gn:timezone":"America/Chihuahua",
    "iso:country":"MX",
    "wof:name":"Los Lajeros",
    "wof:placetype":"locality",
    "wof:population":31
},
  "geometry": {"coordinates":[-108.55995,27.86574],"type":"Point"}
}