{
  "type": "Feature",
  "properties": {
    "gn:admin1_code":"30",
    "gn:admin2_code":"45",
    "gn:asciiname":"El Coyote",
    "gn:country_code":"MX",
    "gn:dem":9,
    "gn:feature_class":"P",
    "gn:feature_code":"PPL",
    "gn:name":"El Coyote",
    "gn:population":16,
    "gn:timezone":"America/Mexico_City",
    "iso:country":"MX",
    "wof:name":"El Coyote",
    "wof:placetype":"locality",
    "wof:population":16
},
  "geometry": {"coordinates":[-95.99806,18.36778],"type":"Point"}
}