{
  "type": "Feature",
  "properties": {
    "gn:admin1_code":"16",
    "gn:admin2_code":"97.0",
    "gn:asciiname":"Caiman",
    "gn:country_code":"MX",
    "gn:dem":623,
    "gn:feature_class":"P",
    "gn:feature_code":"PPL",
    "gn:name":"Caim\u00e1n",
    "gn:population":7,
    "gn:timezone":"America/Mexico_City",
    "iso:country":"MX",
    "name:und_x_variant":[
        "Caim\u00e1n"
    ],
    "wof:name":"Caiman",
    "wof:placetype":"locality",
    "wof:population":7
},
  "geometry": {"coordinates":[-101.39472000000001,18.9675],"type":"Point"}
}