{
  "type": "Feature",
  "properties": {
    "gn:admin1_code":"11",
    "gn:admin2_code":"1",
    "gn:asciiname":"La Estancia de Orozco (Cuatro Milpas)",
    "gn:country_code":"MX",
    "gn:dem":1695,
    "gn:feature_class":"P",
    "gn:feature_code":"PPL",
    "gn:name":"La Estancia de Orozco (Cuatro Milpas)",
    "gn:population":11,
    "gn:timezone":"America/Mexico_City",
    "iso:country":"MX",
    "wof:name":"La Estancia de Orozco (Cuatro Milpas)",
    "wof:placetype":"locality",
    "wof:population":11
},
  "geometry": {"coordinates":[-101.56444,20.46639],"type":"Point"}
}