{
  "type": "Feature",
  "properties": {
    "gn:admin1_code":"32",
    "gn:admin2_code":"41",
    "gn:asciiname":"El Surco (El Surco de Magueyes)",
    "gn:country_code":"MX",
    "gn:dem":2446,
    "gn:feature_class":"P",
    "gn:feature_code":"PPL",
    "gn:name":"El Surco (El Surco de Magueyes)",
    "gn:population":12,
    "gn:timezone":"America/Mexico_City",
    "iso:country":"MX",
    "wof:name":"El Surco (El Surco de Magueyes)",
    "wof:placetype":"locality",
    "wof:population":12
},
  "geometry": {"coordinates":[-101.00972,24.55333],"type":"Point"}
}