{
  "type": "Feature",
  "properties": {
    "gn:admin1_code":"25",
    "gn:asciiname":"El Pirame",
    "gn:country_code":"MX",
    "gn:dem":968,
    "gn:feature_class":"P",
    "gn:feature_code":"PPL",
    "gn:name":"El Pirame",
    "gn:population":0,
    "gn:timezone":"America/Mazatlan",
    "iso:country":"MX",
    "name:spa_x_preferred":[
        "El Pirame"
    ],
    "wof:name":"El Pirame",
    "wof:placetype":"locality"
},
  "geometry": {"coordinates":[-107.84021,26.18986],"type":"Point"}
}