{
  "type": "Feature",
  "properties": {
    "gn:admin1_code":"7",
    "gn:admin2_code":"33.0",
    "gn:asciiname":"Tacubaya",
    "gn:country_code":"MX",
    "gn:dem":1109,
    "gn:feature_class":"P",
    "gn:feature_code":"PPL",
    "gn:name":"Tacubaya",
    "gn:population":0,
    "gn:timezone":"America/Monterrey",
    "iso:country":"MX",
    "name:spa_x_preferred":[
        "Tacubaya"
    ],
    "name:und_x_variant":[
        "Tacuboya",
        "San Jos\u00e9"
    ],
    "wof:name":"Tacubaya",
    "wof:placetype":"locality"
},
  "geometry": {"coordinates":[-103.0681,25.68281],"type":"Point"}
}