{
  "type": "Feature",
  "properties": {
    "gn:admin1_code":"7",
    "gn:admin2_code":"33.0",
    "gn:asciiname":"Tacubaya",
    "gn:country_code":"MX",
    "gn:dem":1109,
    "gn:feature_class":"P",
    "gn:feature_code":"PPL",
    "gn:name":"Tacubaya",
    "gn:population":0,
    "gn:timezone":"America/Monterrey",
    "iso:country":"MX",
    "name:ceb_x_preferred":[
        "Tacubaya"
    ],
    "name:deu_x_preferred":[
        "Tacubaya"
    ],
    "name:ind_x_preferred":[
        "Tacubaya"
    ],
    "name:nld_x_preferred":[
        "Tacubaya"
    ],
    "name:nor_x_preferred":[
        "Tacubaya"
    ],
    "name:spa_x_preferred":[
        "Tacubaya"
    ],
    "name:tam_x_preferred":[
        "\u0b87\u0b9f\u0bcd\u0b9f\u0bbe\u0b95\u0bcd\u0b95\u0bc1\u0baa\u0bc8\u0baf\u0bbe"
    ],
    "name:und_x_variant":[
        "Tacuboya",
        "San Jos\u00e9"
    ],
    "wof:name":"Tacubaya",
    "wof:placetype":"locality",
    "wof:population":1433
},
  "geometry": {"coordinates":[-103.0681,25.68281],"type":"Point"}
}