{
  "type": "Feature",
  "properties": {
    "gn:admin1_code":"22",
    "gn:admin2_code":"2.0",
    "gn:asciiname":"La Quebradora",
    "gn:country_code":"MX",
    "gn:dem":2500,
    "gn:feature_class":"P",
    "gn:feature_code":"PPL",
    "gn:name":"La Quebradora",
    "gn:population":93,
    "gn:timezone":"America/Mexico_City",
    "iso:country":"MX",
    "wof:name":"La Quebradora",
    "wof:placetype":"locality",
    "wof:population":93
},
  "geometry": {"coordinates":[-99.645,21.12444],"type":"Point"}
}