{
  "type": "Feature",
  "properties": {
    "gn:admin1_code":"6.0",
    "gn:admin2_code":"61.0",
    "gn:asciiname":"La Boquilla (Colonia Calles)",
    "gn:country_code":"MX",
    "gn:dem":1460,
    "gn:feature_class":"P",
    "gn:feature_code":"PPL",
    "gn:name":"La Boquilla (Colonia Calles)",
    "gn:population":38,
    "gn:timezone":"America/Chihuahua",
    "iso:country":"MX",
    "name:und_x_variant":[
        "La Boquilla",
        "Colonia Calles"
    ],
    "wof:name":"La Boquilla (Colonia Calles)",
    "wof:placetype":"locality",
    "wof:population":38
},
  "geometry": {"coordinates":[-106.22574,27.80882],"type":"Point"}
}