{
  "type": "Feature",
  "properties": {
    "gn:admin1_code":"30",
    "gn:admin2_code":"80",
    "gn:asciiname":"La Monera",
    "gn:country_code":"MX",
    "gn:dem":1944,
    "gn:feature_class":"P",
    "gn:feature_code":"PPL",
    "gn:name":"La Monera",
    "gn:population":20,
    "gn:timezone":"America/Mexico_City",
    "iso:country":"MX",
    "wof:name":"La Monera",
    "wof:placetype":"locality",
    "wof:population":20
},
  "geometry": {"coordinates":[-96.88278,19.01333],"type":"Point"}
}