{
  "type": "Feature",
  "properties": {
    "gn:admin1_code":"23",
    "gn:admin2_code":"6.0",
    "gn:asciiname":"Huay Max",
    "gn:country_code":"MX",
    "gn:dem":27,
    "gn:feature_class":"P",
    "gn:feature_code":"PPL",
    "gn:name":"Huay Max",
    "gn:population":0,
    "gn:timezone":"America/Cancun",
    "iso:country":"MX",
    "name:spa_x_preferred":[
        "Huay Max"
    ],
    "wof:name":"Huay Max",
    "wof:placetype":"locality"
},
  "geometry": {"coordinates":[-88.52588,20.04173],"type":"Point"}
}