{
  "type": "Feature",
  "properties": {
    "gn:admin1_code":"24",
    "gn:admin2_code":"3.0",
    "gn:asciiname":"San Benito",
    "gn:country_code":"MX",
    "gn:dem":502,
    "gn:feature_class":"P",
    "gn:feature_code":"PPL",
    "gn:name":"San Benito",
    "gn:population":0,
    "gn:timezone":"America/Mexico_City",
    "iso:country":"MX",
    "name:spa_x_preferred":[
        "San Benito"
    ],
    "wof:name":"San Benito",
    "wof:placetype":"locality"
},
  "geometry": {"coordinates":[-99.18491,21.71112],"type":"Point"}
}