{
  "type": "Feature",
  "properties": {
    "gn:admin1_code":"12",
    "gn:admin2_code":"53.0",
    "gn:asciiname":"Tigre",
    "gn:country_code":"MX",
    "gn:dem":46,
    "gn:feature_class":"P",
    "gn:feature_code":"PPL",
    "gn:name":"Tigre",
    "gn:population":0,
    "gn:timezone":"America/Mexico_City",
    "iso:country":"MX",
    "name:arg_x_preferred":[
        "Tigre"
    ],
    "name:cat_x_preferred":[
        "Tigre"
    ],
    "name:ceb_x_preferred":[
        "Tigre"
    ],
    "name:ces_x_preferred":[
        "Tigre"
    ],
    "name:deu_x_preferred":[
        "Tigre"
    ],
    "name:fin_x_preferred":[
        "Tigre"
    ],
    "name:fra_x_preferred":[
        "Tigre"
    ],
    "name:heb_x_preferred":[
        "\u05ea\u05d2\u05e8\u05d9\u05dd"
    ],
    "name:ina_x_preferred":[
        "Tigre"
    ],
    "name:ita_x_preferred":[
        "Tigre"
    ],
    "name:jpn_x_preferred":[
        "\u30c6\u30a3\u30b0\u30ec"
    ],
    "name:kor_x_preferred":[
        "\ud2f0\uadf8\ub808"
    ],
    "name:lit_x_preferred":[
        "Tigr\u0117"
    ],
    "name:nld_x_preferred":[
        "Tigre"
    ],
    "name:nor_x_preferred":[
        "Tigre"
    ],
    "name:oci_x_preferred":[
        "Tigre"
    ],
    "name:por_x_preferred":[
        "Tigre"
    ],
    "name:rus_x_preferred":[
        "\u0422\u0438\u0433\u0440\u0435"
    ],
    "name:spa_x_preferred":[
        "Tigre"
    ],
    "name:srp_x_preferred":[
        "\u0422\u0438\u0433\u0440\u0435"
    ],
    "name:swe_x_preferred":[
        "Tigre"
    ],
    "name:ukr_x_preferred":[
        "\u0422\u0438\u0433\u0440\u0435"
    ],
    "name:uzb_x_preferred":[
        "Tigre"
    ],
    "wof:name":"Tigre",
    "wof:placetype":"locality"
},
  "geometry": {"coordinates":[-99.58333,16.78333],"type":"Point"}
}