{
  "type": "Feature",
  "properties": {
    "gn:admin1_code":"5",
    "gn:admin2_code":"69.0",
    "gn:asciiname":"Cuatro Hermanos (Los Manguitos)",
    "gn:country_code":"MX",
    "gn:dem":44,
    "gn:feature_class":"P",
    "gn:feature_code":"PPL",
    "gn:name":"Cuatro Hermanos (Los Manguitos)",
    "gn:population":5,
    "gn:timezone":"America/Mexico_City",
    "iso:country":"MX",
    "wof:name":"Cuatro Hermanos (Los Manguitos)",
    "wof:placetype":"locality",
    "wof:population":5
},
  "geometry": {"coordinates":[-93.39,15.79556],"type":"Point"}
}