{
  "type": "Feature",
  "properties": {
    "gn:admin1_code":"19",
    "gn:admin2_code":"18",
    "gn:asciiname":"Montana (Maravillas)",
    "gn:country_code":"MX",
    "gn:dem":784,
    "gn:feature_class":"P",
    "gn:feature_code":"PPL",
    "gn:name":"Montana (Maravillas)",
    "gn:population":18,
    "gn:timezone":"America/Monterrey",
    "iso:country":"MX",
    "wof:name":"Montana (Maravillas)",
    "wof:placetype":"locality",
    "wof:population":18
},
  "geometry": {"coordinates":[-100.65861,25.80167],"type":"Point"}
}