{
  "type": "Feature",
  "properties": {
    "gn:admin1_code":"14",
    "gn:admin2_code":"99",
    "gn:asciiname":"La Lima",
    "gn:country_code":"MX",
    "gn:dem":1513,
    "gn:feature_class":"P",
    "gn:feature_code":"PPL",
    "gn:name":"La Lima",
    "gn:population":47,
    "gn:timezone":"America/Mexico_City",
    "iso:country":"MX",
    "wof:name":"La Lima",
    "wof:placetype":"locality",
    "wof:population":47
},
  "geometry": {"coordinates":[-104.0625,19.51611],"type":"Point"}
}