{
  "type": "Feature",
  "properties": {
    "gn:admin1_code":"14",
    "gn:admin2_code":"99",
    "gn:asciiname":"La Lima",
    "gn:country_code":"MX",
    "gn:dem":1513,
    "gn:feature_class":"P",
    "gn:feature_code":"PPL",
    "gn:name":"La Lima",
    "gn:population":47,
    "gn:timezone":"America/Mexico_City",
    "iso:country":"MX",
    "name:bul_x_preferred":[
        "\u041b\u0438\u043c\u0430"
    ],
    "name:fra_x_preferred":[
        "La Lima"
    ],
    "name:ita_x_preferred":[
        "La Lima"
    ],
    "name:lit_x_preferred":[
        "La Lima"
    ],
    "name:nld_x_preferred":[
        "La Lima"
    ],
    "name:pol_x_preferred":[
        "La Lima"
    ],
    "name:por_x_preferred":[
        "La Lima"
    ],
    "name:rus_x_preferred":[
        "\u041b\u0430-\u041b\u0438\u043c\u0430"
    ],
    "name:spa_x_preferred":[
        "La Lima"
    ],
    "name:zho_x_preferred":[
        "\u62c9\u5229\u99ac"
    ],
    "wof:name":"La Lima",
    "wof:placetype":"locality",
    "wof:population":47
},
  "geometry": {"coordinates":[-104.0625,19.51611],"type":"Point"}
}