{
  "type": "Feature",
  "properties": {
    "gn:admin1_code":"6",
    "gn:admin2_code":"14.0",
    "gn:asciiname":"Ex-Hacienda Emiliano Zapata",
    "gn:cc2":"MX",
    "gn:country_code":"MX",
    "gn:dem":1467,
    "gn:feature_class":"P",
    "gn:feature_code":"PPL",
    "gn:name":"Ex-Hacienda Emiliano Zapata",
    "gn:population":7,
    "gn:timezone":"America/Chihuahua",
    "iso:country":"MX",
    "name:und_x_variant":[
        "Ejido Emiliano Zapata",
        "Ya\u00f1iz",
        "Zapata"
    ],
    "wof:name":"Ex-Hacienda Emiliano Zapata",
    "wof:placetype":"locality",
    "wof:population":7
},
  "geometry": {"coordinates":[-105.1268,26.8794],"type":"Point"}
}