{
  "type": "Feature",
  "properties": {
    "gn:admin1_code":"16.0",
    "gn:admin2_code":"15.0",
    "gn:asciiname":"Agua Hedionda",
    "gn:country_code":"MX",
    "gn:dem":1314,
    "gn:feature_class":"P",
    "gn:feature_code":"PPL",
    "gn:name":"Agua Hedionda",
    "gn:population":0,
    "gn:timezone":"America/Mexico_City",
    "iso:country":"MX",
    "name:spa_x_preferred":[
        "Agua Hedionda"
    ],
    "wof:name":"Agua Hedionda",
    "wof:placetype":"locality"
},
  "geometry": {"coordinates":[-103.07929,18.73893],"type":"Point"}
}