{
  "type": "Feature",
  "properties": {
    "gn:admin1_code":"30",
    "gn:admin2_code":"125.0",
    "gn:asciiname":"Moron Uno",
    "gn:country_code":"MX",
    "gn:dem":449,
    "gn:feature_class":"P",
    "gn:feature_code":"PPL",
    "gn:name":"Mor\u00f3n Uno",
    "gn:population":72,
    "gn:timezone":"America/Mexico_City",
    "iso:country":"MX",
    "name:und_x_variant":[
        "Mor\u00f3n Uno"
    ],
    "wof:name":"Moron Uno",
    "wof:placetype":"locality",
    "wof:population":72
},
  "geometry": {"coordinates":[-96.67306000000001,19.0375],"type":"Point"}
}