{
  "type": "Feature",
  "properties": {
    "gn:admin1_code":"10",
    "gn:admin2_code":"24.0",
    "gn:asciiname":"San Antonio de las Cuevas",
    "gn:cc2":"MX",
    "gn:country_code":"MX",
    "gn:dem":1473,
    "gn:feature_class":"P",
    "gn:feature_code":"PPL",
    "gn:name":"San Antonio de las Cuevas",
    "gn:population":0,
    "gn:timezone":"America/Monterrey",
    "iso:country":"MX",
    "name:und_x_variant":[
        "San Antonio Cueva",
        "San Antonio de las Cuevas"
    ],
    "wof:name":"San Antonio de las Cuevas",
    "wof:placetype":"locality"
},
  "geometry": {"coordinates":[-104.56667,25.13333],"type":"Point"}
}