{
  "type": "Feature",
  "properties": {
    "gn:admin1_code":"20",
    "gn:admin2_code":"470",
    "gn:asciiname":"Guacamaya",
    "gn:country_code":"MX",
    "gn:dem":480,
    "gn:feature_class":"P",
    "gn:feature_code":"PPL",
    "gn:name":"Guacamaya",
    "gn:population":15,
    "gn:timezone":"America/Mexico_City",
    "iso:country":"MX",
    "name:ceb_x_preferred":[
        "Guacamaya"
    ],
    "name:swe_x_preferred":[
        "Guacamaya"
    ],
    "wof:name":"Guacamaya",
    "wof:placetype":"locality",
    "wof:population":15
},
  "geometry": {"coordinates":[-95.54611,16.63861],"type":"Point"}
}