{
  "type": "Feature",
  "properties": {
    "gn:admin1_code":"12",
    "gn:admin2_code":"61",
    "gn:asciiname":"Las Mojoneras",
    "gn:country_code":"MX",
    "gn:dem":1335,
    "gn:feature_class":"P",
    "gn:feature_code":"PPL",
    "gn:name":"Las Mojoneras",
    "gn:population":21,
    "gn:timezone":"America/Mexico_City",
    "iso:country":"MX",
    "wof:name":"Las Mojoneras",
    "wof:placetype":"locality",
    "wof:population":21
},
  "geometry": {"coordinates":[-99.37101,17.62152],"type":"Point"}
}