{
  "type": "Feature",
  "properties": {
    "gn:admin1_code":"7.0",
    "gn:admin2_code":"20.0",
    "gn:asciiname":"La Mexicana",
    "gn:country_code":"MX",
    "gn:dem":395,
    "gn:feature_class":"P",
    "gn:feature_code":"PPL",
    "gn:name":"La Mexicana",
    "gn:population":0,
    "gn:timezone":"America/Monterrey",
    "iso:country":"MX",
    "name:spa_x_preferred":[
        "La Mexicana"
    ],
    "wof:name":"La Mexicana",
    "wof:placetype":"locality"
},
  "geometry": {"coordinates":[-101.38119,27.95915],"type":"Point"}
}