{
  "type": "Feature",
  "properties": {
    "gn:admin1_code":"12",
    "gn:admin2_code":"54",
    "gn:asciiname":"Las Parotas",
    "gn:country_code":"MX",
    "gn:dem":677,
    "gn:feature_class":"P",
    "gn:feature_code":"PPL",
    "gn:name":"Las Parotas",
    "gn:population":37,
    "gn:timezone":"America/Mexico_City",
    "iso:country":"MX",
    "wof:name":"Las Parotas",
    "wof:placetype":"locality",
    "wof:population":37
},
  "geometry": {"coordinates":[-100.1756,17.78167000000001],"type":"Point"}
}