{
  "type": "Feature",
  "properties": {
    "gn:admin1_code":"5.0",
    "gn:admin2_code":"23.0",
    "gn:asciiname":"Ti Komon",
    "gn:country_code":"MX",
    "gn:dem":2447,
    "gn:feature_class":"P",
    "gn:feature_code":"PPL",
    "gn:name":"Ti Kom\u00f3n",
    "gn:population":0,
    "gn:timezone":"America/Mexico_City",
    "iso:country":"MX",
    "name:spa_x_preferred":[
        "Tikomuntik"
    ],
    "name:spa_x_variant":[
        "Ti Kom\u00f3n"
    ],
    "wof:name":"Ti Komon",
    "wof:placetype":"locality"
},
  "geometry": {"coordinates":[-92.74469999999999,16.8491],"type":"Point"}
}