{
  "type": "Feature",
  "properties": {
    "gn:admin1_code":"17",
    "gn:admin2_code":"18.0",
    "gn:asciiname":"Colonia Aeropuerto 5ta. Seccion los Pinos",
    "gn:country_code":"MX",
    "gn:dem":1279,
    "gn:feature_class":"P",
    "gn:feature_code":"PPL",
    "gn:name":"Colonia Aeropuerto 5ta. Secci\u00f3n los Pinos",
    "gn:population":98,
    "gn:timezone":"America/Mexico_City",
    "iso:country":"MX",
    "name:und_x_variant":[
        "Colonia Aeropuerto 5ta. Secci\u00f3n los Pinos"
    ],
    "wof:name":"Colonia Aeropuerto 5ta. Seccion los Pinos",
    "wof:placetype":"locality",
    "wof:population":98
},
  "geometry": {"coordinates":[-99.26555999999999,18.82389],"type":"Point"}
}