{
  "type": "Feature",
  "properties": {
    "gn:admin1_code":"6",
    "gn:admin2_code":"9",
    "gn:asciiname":"Aguayna",
    "gn:country_code":"MX",
    "gn:dem":2326,
    "gn:feature_class":"P",
    "gn:feature_code":"PPL",
    "gn:name":"Aguayna",
    "gn:population":10,
    "gn:timezone":"America/Chihuahua",
    "iso:country":"MX",
    "wof:name":"Aguayna",
    "wof:placetype":"locality",
    "wof:population":10
},
  "geometry": {"coordinates":[-107.63243,27.72131],"type":"Point"}
}