{
  "type": "Feature",
  "properties": {
    "gn:admin1_code":"5",
    "gn:admin2_code":"39.0",
    "gn:asciiname":"Las Casitas",
    "gn:country_code":"MX",
    "gn:dem":825,
    "gn:feature_class":"P",
    "gn:feature_code":"PPL",
    "gn:name":"Las Casitas",
    "gn:population":4,
    "gn:timezone":"America/Mexico_City",
    "iso:country":"MX",
    "wof:name":"Las Casitas",
    "wof:placetype":"locality",
    "wof:population":4
},
  "geometry": {"coordinates":[-92.74527999999999,17.2025],"type":"Point"}
}