{
  "type": "Feature",
  "properties": {
    "gn:admin1_code":"30",
    "gn:admin2_code":"112.0",
    "gn:asciiname":"Paso Escondido (Chiveria)",
    "gn:country_code":"MX",
    "gn:dem":882,
    "gn:feature_class":"P",
    "gn:feature_code":"PPL",
    "gn:name":"Paso Escondido (Chiver\u00eda)",
    "gn:population":8,
    "gn:timezone":"America/Mexico_City",
    "iso:country":"MX",
    "name:und_x_variant":[
        "Paso Escondido (Chiver\u00eda)"
    ],
    "wof:name":"Paso Escondido (Chiveria)",
    "wof:placetype":"locality",
    "wof:population":8
},
  "geometry": {"coordinates":[-96.86167,19.6075],"type":"Point"}
}