{
  "type": "Feature",
  "properties": {
    "gn:admin1_code":"32",
    "gn:admin2_code":"38.0",
    "gn:asciiname":"El Rincon de Pina",
    "gn:country_code":"MX",
    "gn:dem":2204,
    "gn:feature_class":"P",
    "gn:feature_code":"PPL",
    "gn:name":"El Rinc\u00f3n de Pi\u00f1a",
    "gn:population":99,
    "gn:timezone":"America/Mexico_City",
    "iso:country":"MX",
    "name:und_x_variant":[
        "El Rinc\u00f3n de Pi\u00f1a"
    ],
    "wof:name":"El Rincon de Pina",
    "wof:placetype":"locality",
    "wof:population":99
},
  "geometry": {"coordinates":[-101.80194,22.24167000000001],"type":"Point"}
}