{
  "type": "Feature",
  "properties": {
    "gn:admin1_code":"10",
    "gn:admin2_code":"14.0",
    "gn:asciiname":"Los Limones",
    "gn:country_code":"MX",
    "gn:dem":938,
    "gn:feature_class":"P",
    "gn:feature_code":"PPL",
    "gn:name":"Los Limones",
    "gn:population":0,
    "gn:timezone":"America/Monterrey",
    "iso:country":"MX",
    "name:spa_x_preferred":[
        "Los Limones"
    ],
    "wof:name":"Los Limones",
    "wof:placetype":"locality"
},
  "geometry": {"coordinates":[-104.43095,22.48806],"type":"Point"}
}