{
  "type": "Feature",
  "properties": {
    "gn:admin1_code":"16.0",
    "gn:admin2_code":"8.0",
    "gn:asciiname":"Playa del Limon",
    "gn:country_code":"MX",
    "gn:dem":781,
    "gn:feature_class":"P",
    "gn:feature_code":"PPL",
    "gn:name":"Playa del Lim\u00f3n",
    "gn:population":32,
    "gn:timezone":"America/Mexico_City",
    "iso:country":"MX",
    "wof:name":"Playa del Limon",
    "wof:placetype":"locality",
    "wof:population":32
},
  "geometry": {"coordinates":[-103.0775,18.37083],"type":"Point"}
}