{
  "type": "Feature",
  "properties": {
    "gn:admin1_code":"32",
    "gn:admin2_code":"57",
    "gn:asciiname":"San Felipe de Jesus (Rancho de Pascual)",
    "gn:country_code":"MX",
    "gn:dem":2080,
    "gn:feature_class":"P",
    "gn:feature_code":"PPL",
    "gn:name":"San Felipe de Jes\u00fas (Rancho de Pascual)",
    "gn:population":23,
    "gn:timezone":"America/Mexico_City",
    "iso:country":"MX",
    "name:und_x_variant":[
        "San Felipe de Jes\u00fas (Rancho de Pascual)"
    ],
    "wof:name":"San Felipe de Jesus (Rancho de Pascual)",
    "wof:placetype":"locality",
    "wof:population":23
},
  "geometry": {"coordinates":[-102.26111,22.80722],"type":"Point"}
}