{
  "type": "Feature",
  "properties": {
    "gn:admin1_code":"20",
    "gn:admin2_code":"66.0",
    "gn:asciiname":"El Huamol",
    "gn:country_code":"MX",
    "gn:dem":34,
    "gn:feature_class":"P",
    "gn:feature_code":"PPL",
    "gn:name":"El Huamol",
    "gn:population":0,
    "gn:timezone":"America/Mexico_City",
    "iso:country":"MX",
    "name:spa_x_preferred":[
        "El Huamol"
    ],
    "wof:name":"El Huamol",
    "wof:placetype":"locality"
},
  "geometry": {"coordinates":[-94.47266,16.49037],"type":"Point"}
}