{
  "type": "Feature",
  "properties": {
    "gn:admin1_code":"10",
    "gn:admin2_code":"34",
    "gn:asciiname":"Cerro Blanco",
    "gn:country_code":"MX",
    "gn:dem":1146,
    "gn:feature_class":"P",
    "gn:feature_code":"PPL",
    "gn:name":"Cerro Blanco",
    "gn:population":39,
    "gn:timezone":"America/Monterrey",
    "iso:country":"MX",
    "wof:name":"Cerro Blanco",
    "wof:placetype":"locality",
    "wof:population":39
},
  "geometry": {"coordinates":[-106.68258,25.02498],"type":"Point"}
}