{
  "type": "Feature",
  "properties": {
    "gn:admin1_code":"31",
    "gn:admin2_code":"96",
    "gn:asciiname":"Adolfo Lopez Mateos",
    "gn:country_code":"MX",
    "gn:dem":13,
    "gn:feature_class":"P",
    "gn:feature_code":"PPL",
    "gn:name":"Adolfo L\u00f3pez Mateos",
    "gn:population":23,
    "gn:timezone":"America/Merida",
    "iso:country":"MX",
    "name:und_x_variant":[
        "Adolfo L\u00f3pez Mateos"
    ],
    "wof:name":"Adolfo Lopez Mateos",
    "wof:placetype":"locality",
    "wof:population":23
},
  "geometry": {"coordinates":[-87.69944,21.15944],"type":"Point"}
}