{
  "type": "Feature",
  "properties": {
    "gn:admin1_code":"28.0",
    "gn:admin2_code":"14.0",
    "gn:asciiname":"Novillo Barroso",
    "gn:country_code":"MX",
    "gn:dem":110,
    "gn:feature_class":"P",
    "gn:feature_code":"PPL",
    "gn:name":"Novillo Barroso",
    "gn:population":0,
    "gn:timezone":"America/Monterrey",
    "iso:country":"MX",
    "name:spa_x_preferred":[
        "Novillo Barroso"
    ],
    "wof:name":"Novillo Barroso",
    "wof:placetype":"locality"
},
  "geometry": {"coordinates":[-99.52575,27.02921],"type":"Point"}
}