{
  "type": "Feature",
  "properties": {
    "gn:admin1_code":"26",
    "gn:admin2_code":"3.0",
    "gn:asciiname":"El Chilar",
    "gn:country_code":"MX",
    "gn:dem":200,
    "gn:feature_class":"P",
    "gn:feature_code":"PPL",
    "gn:name":"El Chilar",
    "gn:population":0,
    "gn:timezone":"America/Hermosillo",
    "iso:country":"MX",
    "name:spa_x_preferred":[
        "El Chilar"
    ],
    "wof:name":"El Chilar",
    "wof:placetype":"locality"
},
  "geometry": {"coordinates":[-108.87148999999999,26.60794000000001],"type":"Point"}
}