{
  "type": "Feature",
  "properties": {
    "gn:admin1_code":"17",
    "gn:asciiname":"San Juan Atzingo",
    "gn:country_code":"MX",
    "gn:dem":2583,
    "gn:feature_class":"P",
    "gn:feature_code":"PPL",
    "gn:name":"San Juan Atzingo",
    "gn:population":0,
    "gn:timezone":"America/Mexico_City",
    "iso:country":"MX",
    "name:spa_x_preferred":[
        "San Juan Atzingo"
    ],
    "wof:name":"San Juan Atzingo",
    "wof:placetype":"locality"
},
  "geometry": {"coordinates":[-99.38545000000001,19.01007],"type":"Point"}
}