{
  "type": "Feature",
  "properties": {
    "gn:admin1_code":"13",
    "gn:admin2_code":"19.0",
    "gn:asciiname":"Rancho Zinthe",
    "gn:country_code":"MX",
    "gn:dem":1980,
    "gn:feature_class":"P",
    "gn:feature_code":"PPL",
    "gn:name":"Rancho Zinthe",
    "gn:population":0,
    "gn:timezone":"America/Mexico_City",
    "iso:country":"MX",
    "name:spa_x_preferred":[
        "Rancho Zintl\u00e9"
    ],
    "name:spa_x_variant":[
        "Rancho Zinthe"
    ],
    "wof:name":"Rancho Zinthe",
    "wof:placetype":"locality"
},
  "geometry": {"coordinates":[-99.26048,20.30899],"type":"Point"}
}