{
  "type": "Feature",
  "properties": {
    "gn:admin1_code":"14.0",
    "gn:admin2_code":"17.0",
    "gn:asciiname":"Tachichilco",
    "gn:country_code":"MX",
    "gn:dem":1469,
    "gn:feature_class":"P",
    "gn:feature_code":"PPL",
    "gn:name":"Tachichilco",
    "gn:population":0,
    "gn:timezone":"America/Mexico_City",
    "iso:country":"MX",
    "name:spa_x_preferred":[
        "Tachichilco"
    ],
    "wof:name":"Tachichilco",
    "wof:placetype":"locality"
},
  "geometry": {"coordinates":[-104.46061,19.89898],"type":"Point"}
}