{
  "type": "Feature",
  "properties": {
    "gn:admin1_code":"5",
    "gn:admin2_code":"19.0",
    "gn:asciiname":"El Tanque",
    "gn:country_code":"MX",
    "gn:dem":2304,
    "gn:feature_class":"P",
    "gn:feature_code":"PPL",
    "gn:name":"El Tanque",
    "gn:population":155,
    "gn:timezone":"America/Mexico_City",
    "iso:country":"MX",
    "wof:name":"El Tanque",
    "wof:placetype":"locality",
    "wof:population":155
},
  "geometry": {"coordinates":[-92.30583,16.48111],"type":"Point"}
}