{
  "type": "Feature",
  "properties": {
    "gn:admin1_code":"15",
    "gn:admin2_code":"105",
    "gn:asciiname":"Cuadrilla de las Flores",
    "gn:country_code":"MX",
    "gn:dem":1030,
    "gn:feature_class":"P",
    "gn:feature_code":"PPL",
    "gn:name":"Cuadrilla de las Flores",
    "gn:population":21,
    "gn:timezone":"America/Mexico_City",
    "iso:country":"MX",
    "wof:name":"Cuadrilla de las Flores",
    "wof:placetype":"locality",
    "wof:population":21
},
  "geometry": {"coordinates":[-100.23699000000001,18.63686],"type":"Point"}
}