{
  "type": "Feature",
  "properties": {
    "gn:admin1_code":"22.0",
    "gn:admin2_code":"1.0",
    "gn:asciiname":"La Piedad",
    "gn:country_code":"MX",
    "gn:dem":2463,
    "gn:feature_class":"P",
    "gn:feature_code":"PPL",
    "gn:name":"La Piedad",
    "gn:population":0,
    "gn:timezone":"America/Mexico_City",
    "iso:country":"MX",
    "name:und_x_variant":[
        "Jacal de la Piedad"
    ],
    "wof:name":"La Piedad",
    "wof:placetype":"locality"
},
  "geometry": {"coordinates":[-100.02637,20.09605],"type":"Point"}
}