{
  "type": "Feature",
  "properties": {
    "gn:admin1_code":"22.0",
    "gn:admin2_code":"1.0",
    "gn:asciiname":"La Piedad",
    "gn:country_code":"MX",
    "gn:dem":2463,
    "gn:feature_class":"P",
    "gn:feature_code":"PPL",
    "gn:name":"La Piedad",
    "gn:population":0,
    "gn:timezone":"America/Mexico_City",
    "iso:country":"MX",
    "name:epo_x_preferred":[
        "La Piedad"
    ],
    "name:eus_x_preferred":[
        "La Piedad"
    ],
    "name:ita_x_preferred":[
        "La Piedad"
    ],
    "name:por_x_preferred":[
        "La Piedad"
    ],
    "name:rus_x_preferred":[
        "\u041b\u0430-\u041f\u044c\u0435\u0434\u0430\u0434"
    ],
    "name:srp_x_preferred":[
        "\u041e\u043f\u0448\u0442\u0438\u043d\u0430 \u041b\u0430 \u041f\u0438\u0458\u0435\u0434\u0430\u0434"
    ],
    "name:und_x_variant":[
        "Jacal de la Piedad"
    ],
    "name:urd_x_preferred":[
        "\u0644\u0627 \u067e\u06cc\u0688\u0627\u0688"
    ],
    "name:vie_x_preferred":[
        "La Piedad"
    ],
    "wof:name":"La Piedad",
    "wof:placetype":"locality"
},
  "geometry": {"coordinates":[-100.02637,20.09605],"type":"Point"}
}