{
  "type": "Feature",
  "properties": {
    "gn:admin1_code":"5",
    "gn:admin2_code":"48.0",
    "gn:asciiname":"Las Mirandas",
    "gn:country_code":"MX",
    "gn:dem":11,
    "gn:feature_class":"P",
    "gn:feature_code":"PPL",
    "gn:name":"Las Mirandas",
    "gn:population":0,
    "gn:timezone":"America/Mexico_City",
    "iso:country":"MX",
    "name:spa_x_preferred":[
        "Las Mirandas"
    ],
    "name:und_x_variant":[
        "Los Miranda"
    ],
    "wof:name":"Las Mirandas",
    "wof:placetype":"locality"
},
  "geometry": {"coordinates":[-93.03814,17.76965],"type":"Point"}
}