{
  "type": "Feature",
  "properties": {
    "gn:admin1_code":"12",
    "gn:admin2_code":"35",
    "gn:asciiname":"Colonia el Capire",
    "gn:country_code":"MX",
    "gn:dem":734,
    "gn:feature_class":"P",
    "gn:feature_code":"PPL",
    "gn:name":"Colonia el Capire",
    "gn:population":13,
    "gn:timezone":"America/Mexico_City",
    "iso:country":"MX",
    "wof:name":"Colonia el Capire",
    "wof:placetype":"locality",
    "wof:population":13
},
  "geometry": {"coordinates":[-99.54711,18.32505],"type":"Point"}
}