{
  "type": "Feature",
  "properties": {
    "gn:admin1_code":"30",
    "gn:admin2_code":"155.0",
    "gn:asciiname":"El Aquichal (Laja Segunda)",
    "gn:country_code":"MX",
    "gn:dem":124,
    "gn:feature_class":"P",
    "gn:feature_code":"PPL",
    "gn:name":"El Aquichal (Laja Segunda)",
    "gn:population":380,
    "gn:timezone":"America/Mexico_City",
    "iso:country":"MX",
    "wof:name":"El Aquichal (Laja Segunda)",
    "wof:placetype":"locality",
    "wof:population":380
},
  "geometry": {"coordinates":[-98.26139000000001,21.44972000000001],"type":"Point"}
}