{
  "type": "Feature",
  "properties": {
    "gn:admin1_code":"20",
    "gn:admin2_code":"401.0",
    "gn:asciiname":"El Malucano",
    "gn:country_code":"MX",
    "gn:dem":36,
    "gn:feature_class":"P",
    "gn:feature_code":"PPL",
    "gn:name":"El Malucano",
    "gn:population":0,
    "gn:timezone":"America/Mexico_City",
    "iso:country":"MX",
    "name:spa_x_preferred":[
        "El Malucano"
    ],
    "name:und_x_variant":[
        "Malucano"
    ],
    "wof:name":"El Malucano",
    "wof:placetype":"locality"
},
  "geometry": {"coordinates":[-97.01725999999999,15.8624],"type":"Point"}
}