{
  "type": "Feature",
  "properties": {
    "gn:admin1_code":"18.0",
    "gn:admin2_code":"9.0",
    "gn:asciiname":"La Cienega",
    "gn:country_code":"MX",
    "gn:dem":737,
    "gn:feature_class":"P",
    "gn:feature_code":"PPL",
    "gn:name":"La Ci\u00e9nega",
    "gn:population":0,
    "gn:timezone":"America/Mazatlan",
    "iso:country":"MX",
    "name:ceb_x_preferred":[
        "La Cienega"
    ],
    "name:spa_x_preferred":[
        "La Ci\u00e9nega"
    ],
    "name:swe_x_preferred":[
        "La Cienega"
    ],
    "wof:name":"La Cienega",
    "wof:placetype":"locality"
},
  "geometry": {"coordinates":[-104.54698,21.67234],"type":"Point"}
}