{
  "type": "Feature",
  "properties": {
    "gn:admin1_code":"26",
    "gn:admin2_code":"35.0",
    "gn:asciiname":"El Rincon (Los Alisos)",
    "gn:country_code":"MX",
    "gn:dem":964,
    "gn:feature_class":"P",
    "gn:feature_code":"PPL",
    "gn:name":"El Rinc\u00f3n (Los Alisos)",
    "gn:population":6,
    "gn:timezone":"America/Hermosillo",
    "iso:country":"MX",
    "name:und_x_variant":[
        "El Rinc\u00f3n (Los Alisos)"
    ],
    "wof:name":"El Rincon (Los Alisos)",
    "wof:placetype":"locality",
    "wof:population":6
},
  "geometry": {"coordinates":[-110.86139,30.93722],"type":"Point"}
}