{
  "type": "Feature",
  "properties": {
    "gn:admin1_code":"24",
    "gn:admin2_code":"6.0",
    "gn:asciiname":"El Pastor de Coronados",
    "gn:country_code":"MX",
    "gn:dem":2768,
    "gn:feature_class":"P",
    "gn:feature_code":"PPL",
    "gn:name":"El Pastor de Coronados",
    "gn:population":0,
    "gn:timezone":"America/Mexico_City",
    "iso:country":"MX",
    "name:spa_x_preferred":[
        "El Pastor de Coronados"
    ],
    "wof:name":"El Pastor de Coronados",
    "wof:placetype":"locality"
},
  "geometry": {"coordinates":[-100.87969,23.5858],"type":"Point"}
}