{
  "type": "Feature",
  "properties": {
    "gn:admin1_code":"16",
    "gn:admin2_code":"13.0",
    "gn:asciiname":"Chupaderos",
    "gn:country_code":"MX",
    "gn:dem":947,
    "gn:feature_class":"P",
    "gn:feature_code":"PPL",
    "gn:name":"Chupaderos",
    "gn:population":0,
    "gn:timezone":"America/Mexico_City",
    "iso:country":"MX",
    "name:spa_x_preferred":[
        "Chupaderos"
    ],
    "wof:name":"Chupaderos",
    "wof:placetype":"locality"
},
  "geometry": {"coordinates":[-101.09763,19.14364],"type":"Point"}
}