{
  "type": "Feature",
  "properties": {
    "gn:admin1_code":"15",
    "gn:admin2_code":"103.0",
    "gn:asciiname":"Rancho Alfa y Omega",
    "gn:country_code":"MX",
    "gn:dem":2490,
    "gn:feature_class":"P",
    "gn:feature_code":"PPL",
    "gn:name":"Rancho Alfa y Omega",
    "gn:population":7,
    "gn:timezone":"America/Mexico_City",
    "iso:country":"MX",
    "wof:name":"Rancho Alfa y Omega",
    "wof:placetype":"locality",
    "wof:population":7
},
  "geometry": {"coordinates":[-98.80723,19.19346],"type":"Point"}
}