{
  "type": "Feature",
  "properties": {
    "gn:admin1_code":"6",
    "gn:admin2_code":"65.0",
    "gn:asciiname":"Muchimari",
    "gn:country_code":"MX",
    "gn:dem":1690,
    "gn:feature_class":"P",
    "gn:feature_code":"PPL",
    "gn:name":"Muchimari",
    "gn:population":0,
    "gn:timezone":"America/Chihuahua",
    "iso:country":"MX",
    "name:spa_x_preferred":[
        "Muchimari"
    ],
    "wof:name":"Muchimari",
    "wof:placetype":"locality"
},
  "geometry": {"coordinates":[-107.74242,27.2952],"type":"Point"}
}