{
  "type": "Feature",
  "properties": {
    "gn:admin1_code":"6",
    "gn:admin2_code":"47.0",
    "gn:asciiname":"Los Alamillos",
    "gn:country_code":"MX",
    "gn:dem":1387,
    "gn:feature_class":"P",
    "gn:feature_code":"PPL",
    "gn:name":"Los Alamillos",
    "gn:population":8,
    "gn:timezone":"America/Chihuahua",
    "iso:country":"MX",
    "name:spa_x_preferred":[
        "Los Alamillos"
    ],
    "wof:name":"Los Alamillos",
    "wof:placetype":"locality",
    "wof:population":8
},
  "geometry": {"coordinates":[-108.62384,28.07185],"type":"Point"}
}