{
  "type": "Feature",
  "properties": {
    "gn:admin1_code":"12.0",
    "gn:admin2_code":"14.0",
    "gn:asciiname":"Vereda al Zapotillo",
    "gn:country_code":"MX",
    "gn:dem":7,
    "gn:feature_class":"P",
    "gn:feature_code":"PPL",
    "gn:name":"Vereda al Zapotillo",
    "gn:population":0,
    "gn:timezone":"America/Mexico_City",
    "iso:country":"MX",
    "name:spa_x_preferred":[
        "Vereda al Zapotillo"
    ],
    "wof:name":"Vereda al Zapotillo",
    "wof:placetype":"locality"
},
  "geometry": {"coordinates":[-100.45487,17.0712],"type":"Point"}
}