{
  "type": "Feature",
  "properties": {
    "gn:admin1_code":"32",
    "gn:admin2_code":"42.0",
    "gn:asciiname":"El Saucillo",
    "gn:country_code":"MX",
    "gn:dem":2137,
    "gn:feature_class":"P",
    "gn:feature_code":"PPL",
    "gn:name":"El Saucillo",
    "gn:population":203,
    "gn:timezone":"America/Mexico_City",
    "iso:country":"MX",
    "wof:name":"El Saucillo",
    "wof:placetype":"locality",
    "wof:population":203
},
  "geometry": {"coordinates":[-103.79694000000001,23.59194],"type":"Point"}
}