{
  "type": "Feature",
  "properties": {
    "gn:admin1_code":"6",
    "gn:admin2_code":"48.0",
    "gn:asciiname":"Campo Doscientos Cincuenta y Uno (Jagueeyes)",
    "gn:country_code":"MX",
    "gn:dem":1971,
    "gn:feature_class":"P",
    "gn:feature_code":"PPL",
    "gn:name":"Campo Doscientos Cincuenta y Uno (Jag\u00fceyes)",
    "gn:population":80,
    "gn:timezone":"America/Chihuahua",
    "iso:country":"MX",
    "name:und_x_variant":[
        "Campo Doscientos Cincuenta y Uno (Jag\u00fceyes)"
    ],
    "wof:name":"Campo Doscientos Cincuenta y Uno (Jagueeyes)",
    "wof:placetype":"locality",
    "wof:population":80
},
  "geometry": {"coordinates":[-107.08223999999998,29.18459],"type":"Point"}
}