{
  "type": "Feature",
  "properties": {
    "gn:admin1_code":"4",
    "gn:admin2_code":"7.0",
    "gn:asciiname":"San Angel",
    "gn:country_code":"MX",
    "gn:dem":4,
    "gn:feature_class":"P",
    "gn:feature_code":"PPL",
    "gn:name":"San \u00c1ngel",
    "gn:population":0,
    "gn:timezone":"America/Merida",
    "iso:country":"MX",
    "name:spa_x_preferred":[
        "San \u00c1ngel"
    ],
    "wof:name":"San Angel",
    "wof:placetype":"locality"
},
  "geometry": {"coordinates":[-91.87963999999999,18.08614],"type":"Point"}
}