{
  "type": "Feature",
  "properties": {
    "gn:admin1_code":"14",
    "gn:admin2_code":"52",
    "gn:asciiname":"Los Ojos de Agua",
    "gn:country_code":"MX",
    "gn:dem":1207,
    "gn:feature_class":"P",
    "gn:feature_code":"PPL",
    "gn:name":"Los Ojos de Agua",
    "gn:population":17,
    "gn:timezone":"America/Mexico_City",
    "iso:country":"MX",
    "wof:name":"Los Ojos de Agua",
    "wof:placetype":"locality",
    "wof:population":17
},
  "geometry": {"coordinates":[-104.04277999999999,20.12722],"type":"Point"}
}