{
  "type": "Feature",
  "properties": {
    "gn:admin1_code":"5",
    "gn:admin2_code":"27.0",
    "gn:asciiname":"Grijalva [Viveros]",
    "gn:country_code":"MX",
    "gn:dem":409,
    "gn:feature_class":"P",
    "gn:feature_code":"PPL",
    "gn:name":"Grijalva [Viveros]",
    "gn:population":6,
    "gn:timezone":"America/Mexico_City",
    "iso:country":"MX",
    "wof:name":"Grijalva [Viveros]",
    "wof:placetype":"locality",
    "wof:population":6
},
  "geometry": {"coordinates":[-92.98222,16.68417],"type":"Point"}
}