{
  "type": "Feature",
  "properties": {
    "gn:admin1_code":"30",
    "gn:admin2_code":"128.0",
    "gn:asciiname":"Tenextepec",
    "gn:country_code":"MX",
    "gn:dem":2541,
    "gn:feature_class":"P",
    "gn:feature_code":"PPL",
    "gn:name":"Tenextepec",
    "gn:population":0,
    "gn:timezone":"America/Mexico_City",
    "iso:country":"MX",
    "name:spa_x_preferred":[
        "Tenextepec"
    ],
    "wof:name":"Tenextepec",
    "wof:placetype":"locality"
},
  "geometry": {"coordinates":[-97.26184000000001,19.48724],"type":"Point"}
}