{
  "type": "Feature",
  "properties": {
    "gn:country":"MX",
    "gn:fcode":"PPL",
    "gn:population":0,
    "iso:country":"MX",
    "name:ces_x_preferred":[
        "Chapultepec"
    ],
    "name:deu_x_preferred":[
        "Chapultepec"
    ],
    "name:epo_x_preferred":[
        "Chapultepec"
    ],
    "name:fin_x_preferred":[
        "Chapultepec"
    ],
    "name:fra_x_preferred":[
        "Chapultepec"
    ],
    "name:heb_x_preferred":[
        "\u05e6'\u05e4\u05d5\u05dc\u05d8\u05e4\u05e7"
    ],
    "name:hye_x_preferred":[
        "\u0549\u0561\u057a\u0578\u0582\u056c\u057f\u0565\u057a\u0565\u056f \u0566\u0562\u0578\u057d\u0561\u0575\u0563\u056b"
    ],
    "name:ind_x_preferred":[
        "Chapultepec"
    ],
    "name:ita_x_preferred":[
        "Chapultepec"
    ],
    "name:lit_x_preferred":[
        "\u010capultepekas"
    ],
    "name:nld_x_preferred":[
        "Chapultepec"
    ],
    "name:nor_x_preferred":[
        "Chapultepec"
    ],
    "name:por_x_preferred":[
        "Chapultepec"
    ],
    "name:rus_x_preferred":[
        "\u0427\u0430\u043f\u0443\u043b\u044c\u0442\u0435\u043f\u0435\u043a"
    ],
    "name:spa_x_preferred":[
        "Chapultepec"
    ],
    "name:swe_x_preferred":[
        "Chapultepec"
    ],
    "name:tur_x_preferred":[
        "Chapultepec"
    ],
    "name:ukr_x_preferred":[
        "\u0427\u0430\u043f\u0443\u043b\u044c\u0442\u0435\u043f\u0435\u043a"
    ],
    "name:vie_x_preferred":[
        "Chapultepec"
    ],
    "qs_pg:aaroncc":"MX",
    "qs_pg:gn_country":"MX",
    "qs_pg:gn_fcode":"PPL",
    "qs_pg:gn_pop":0,
    "qs_pg:name":"Chapultepec",
    "qs_pg:name_adm0":"M\u00e9xico",
    "qs_pg:name_adm1":"Baja California",
    "qs_pg:photos":189,
    "qs_pg:photos_1k":38,
    "qs_pg:photos_9k":1,
    "qs_pg:photos_9r":4,
    "qs_pg:photos_all":189,
    "qs_pg:photos_sr":4,
    "qs_pg:pop_sr":0,
    "qs_pg:qs_pg_placetype":"locality",
    "qs_pg:qs_pg_placetype_gp":"Town",
    "qs_pg:woe_adm0":23424900,
    "woe:adm0_id":23424900,
    "woe:name_adm0":"M\u00e9xico",
    "woe:name_adm1":"Baja California",
    "woe:placetype":"Town",
    "wof:name":"Chapultepec",
    "wof:placetype":"locality"
},
  "geometry": {"coordinates":[-116.59180000000001,31.78161],"type":"Point"}
}