{
  "type": "Feature",
  "properties": {
    "gn:admin1_code":"20",
    "gn:admin2_code":"118",
    "gn:asciiname":"Paraje Rugeolach",
    "gn:country_code":"MX",
    "gn:dem":1774,
    "gn:feature_class":"P",
    "gn:feature_code":"PPL",
    "gn:name":"Paraje Rugeolach",
    "gn:population":25,
    "gn:timezone":"America/Mexico_City",
    "iso:country":"MX",
    "wof:name":"Paraje Rugeolach",
    "wof:placetype":"locality",
    "wof:population":25
},
  "geometry": {"coordinates":[-96.49778000000001,16.9025],"type":"Point"}
}