{
  "type": "Feature",
  "properties": {
    "gn:admin1_code":"26.0",
    "gn:admin2_code":"42.0",
    "gn:asciiname":"Juan Diego",
    "gn:country_code":"MX",
    "gn:dem":128,
    "gn:feature_class":"P",
    "gn:feature_code":"PPL",
    "gn:name":"Juan Diego",
    "gn:population":0,
    "gn:timezone":"America/Hermosillo",
    "iso:country":"MX",
    "name:spa_x_preferred":[
        "Juan Diego"
    ],
    "name:und_x_variant":[
        "Rancho Juan D\u00edego"
    ],
    "wof:name":"Juan Diego",
    "wof:placetype":"locality"
},
  "geometry": {"coordinates":[-109.35590000000001,27.34263],"type":"Point"}
}