{
  "type": "Feature",
  "properties": {
    "gn:admin1_code":"27.0",
    "gn:admin2_code":"8.0",
    "gn:asciiname":"Huapacal Cuarta Seccion",
    "gn:country_code":"MX",
    "gn:dem":20,
    "gn:feature_class":"P",
    "gn:feature_code":"PPL",
    "gn:name":"Huapacal Cuarta Secci\u00f3n",
    "gn:population":0,
    "gn:timezone":"America/Mexico_City",
    "iso:country":"MX",
    "name:spa_x_preferred":[
        "Huapacal Cuarta Secci\u00f3n"
    ],
    "wof:name":"Huapacal Cuarta Seccion",
    "wof:placetype":"locality"
},
  "geometry": {"coordinates":[-93.82349000000001,17.85125],"type":"Point"}
}