{
  "type": "Feature",
  "properties": {
    "gn:admin1_code":"30",
    "gn:admin2_code":"119",
    "gn:asciiname":"San Lorenzo",
    "gn:country_code":"MX",
    "gn:dem":17,
    "gn:feature_class":"P",
    "gn:feature_code":"PPL",
    "gn:name":"San Lorenzo",
    "gn:population":16,
    "gn:timezone":"America/Mexico_City",
    "iso:country":"MX",
    "wof:name":"San Lorenzo",
    "wof:placetype":"locality",
    "wof:population":16
},
  "geometry": {"coordinates":[-96.0275,18.20944],"type":"Point"}
}