{
  "type": "Feature",
  "properties": {
    "gn:admin1_code":"5",
    "gn:admin2_code":"50",
    "gn:asciiname":"Estrella de Belen 2da. Seccion",
    "gn:country_code":"MX",
    "gn:dem":76,
    "gn:feature_class":"P",
    "gn:feature_code":"PPL",
    "gn:name":"Estrella de Bel\u00e9n 2da. Secci\u00f3n",
    "gn:population":50,
    "gn:timezone":"America/Mexico_City",
    "iso:country":"MX",
    "name:und_x_variant":[
        "Estrella de Bel\u00e9n 2da. Secci\u00f3n"
    ],
    "wof:name":"Estrella de Belen 2da. Seccion",
    "wof:placetype":"locality",
    "wof:population":50
},
  "geometry": {"coordinates":[-91.73917,17.5325],"type":"Point"}
}