{
  "type": "Feature",
  "properties": {
    "gn:admin1_code":"24",
    "gn:admin2_code":"46.0",
    "gn:asciiname":"Providencia",
    "gn:country_code":"MX",
    "gn:dem":2139,
    "gn:feature_class":"P",
    "gn:feature_code":"PPL",
    "gn:name":"Providencia",
    "gn:population":0,
    "gn:timezone":"America/Mexico_City",
    "iso:country":"MX",
    "wof:name":"Providencia",
    "wof:placetype":"locality"
},
  "geometry": {"coordinates":[-101.25,21.95],"type":"Point"}
}