{
  "type": "Feature",
  "properties": {
    "gn:admin1_code":"1",
    "gn:admin2_code":"3.0",
    "gn:asciiname":"El Salitrillo",
    "gn:country_code":"MX",
    "gn:dem":1756,
    "gn:feature_class":"P",
    "gn:feature_code":"PPL",
    "gn:name":"El Salitrillo",
    "gn:population":54,
    "gn:timezone":"America/Mexico_City",
    "iso:country":"MX",
    "wof:name":"El Salitrillo",
    "wof:placetype":"locality",
    "wof:population":54
},
  "geometry": {"coordinates":[-102.68722,21.97417],"type":"Point"}
}