{
  "type": "Feature",
  "properties": {
    "gn:admin1_code":"16.0",
    "gn:admin2_code":"45.0",
    "gn:asciiname":"Francisco Sarabia (Cerrito Pelon)",
    "gn:country_code":"MX",
    "gn:dem":1531,
    "gn:feature_class":"P",
    "gn:feature_code":"PPL",
    "gn:name":"Francisco Sarabia (Cerrito Pel\u00f3n)",
    "gn:population":2056,
    "gn:timezone":"America/Mexico_City",
    "iso:country":"MX",
    "name:und_x_variant":[
        "Cerrito Pel\u00f3n",
        "Francisco Sarabia"
    ],
    "wof:name":"Francisco Sarabia (Cerrito Pelon)",
    "wof:placetype":"locality",
    "wof:population":2056
},
  "geometry": {"coordinates":[-102.70158000000001,20.03086],"type":"Point"}
}