{
  "type": "Feature",
  "properties": {
    "gn:admin1_code":"10",
    "gn:admin2_code":"1.0",
    "gn:asciiname":"La Alcancia",
    "gn:country_code":"MX",
    "gn:dem":1944,
    "gn:feature_class":"P",
    "gn:feature_code":"PPL",
    "gn:name":"La Alcanc\u00eda",
    "gn:population":0,
    "gn:timezone":"America/Monterrey",
    "iso:country":"MX",
    "name:spa_x_preferred":[
        "La Alcanc\u00eda"
    ],
    "wof:name":"La Alcancia",
    "wof:placetype":"locality"
},
  "geometry": {"coordinates":[-104.77813999999999,24.30625],"type":"Point"}
}