{
  "type": "Feature",
  "properties": {
    "gn:admin1_code":"22",
    "gn:admin2_code":"3.0",
    "gn:asciiname":"Laguna de la Cruz",
    "gn:country_code":"MX",
    "gn:dem":1178,
    "gn:feature_class":"P",
    "gn:feature_code":"PPL",
    "gn:name":"Laguna de la Cruz",
    "gn:population":0,
    "gn:timezone":"America/Mexico_City",
    "iso:country":"MX",
    "name:spa_x_preferred":[
        "Laguna de la Cruz"
    ],
    "wof:name":"Laguna de la Cruz",
    "wof:placetype":"locality"
},
  "geometry": {"coordinates":[-99.50636,21.36183],"type":"Point"}
}