{
  "type": "Feature",
  "properties": {
    "gn:admin1_code":"28",
    "gn:admin2_code":"33.0",
    "gn:asciiname":"Santa Isabel",
    "gn:country_code":"MX",
    "gn:dem":18,
    "gn:feature_class":"P",
    "gn:feature_code":"PPL",
    "gn:name":"Santa Isabel",
    "gn:population":3,
    "gn:timezone":"America/Monterrey",
    "iso:country":"MX",
    "wof:name":"Santa Isabel",
    "wof:placetype":"locality",
    "wof:population":3
},
  "geometry": {"coordinates":[-97.94806,25.77111],"type":"Point"}
}