{
  "type": "Feature",
  "properties": {
    "gn:admin1_code":"16",
    "gn:admin2_code":"6",
    "gn:asciiname":"Fraccionamiento Solidaridad",
    "gn:country_code":"MX",
    "gn:dem":272,
    "gn:feature_class":"P",
    "gn:feature_code":"PPL",
    "gn:name":"Fraccionamiento Solidaridad",
    "gn:population":48,
    "gn:timezone":"America/Mexico_City",
    "iso:country":"MX",
    "wof:name":"Fraccionamiento Solidaridad",
    "wof:placetype":"locality",
    "wof:population":48
},
  "geometry": {"coordinates":[-102.40416999999999,19.08944],"type":"Point"}
}