{
  "type": "Feature",
  "properties": {
    "gn:admin1_code":"26",
    "gn:admin2_code":"3.0",
    "gn:asciiname":"Las Cebollas",
    "gn:country_code":"MX",
    "gn:dem":166,
    "gn:feature_class":"P",
    "gn:feature_code":"PPL",
    "gn:name":"Las Cebollas",
    "gn:population":0,
    "gn:timezone":"America/Hermosillo",
    "iso:country":"MX",
    "name:spa_x_preferred":[
        "Las Cebollas"
    ],
    "wof:name":"Las Cebollas",
    "wof:placetype":"locality"
},
  "geometry": {"coordinates":[-108.96137,27.26994],"type":"Point"}
}