{
  "type": "Feature",
  "properties": {
    "gn:admin1_code":"30",
    "gn:admin2_code":"207.0",
    "gn:asciiname":"San Martin (Abel Martinez Delfin)",
    "gn:country_code":"MX",
    "gn:dem":27,
    "gn:feature_class":"P",
    "gn:feature_code":"PPL",
    "gn:name":"San Mart\u00edn (Abel Mart\u00ednez Delf\u00edn)",
    "gn:population":7,
    "gn:timezone":"America/Mexico_City",
    "iso:country":"MX",
    "name:und_x_variant":[
        "San Mart\u00edn (Abel Mart\u00ednez Delf\u00edn)"
    ],
    "wof:name":"San Martin (Abel Martinez Delfin)",
    "wof:placetype":"locality",
    "wof:population":7
},
  "geometry": {"coordinates":[-96.0825,18.38917],"type":"Point"}
}