{
  "type": "Feature",
  "properties": {
    "gn:admin1_code":"28.0",
    "gn:admin2_code":"35.0",
    "gn:asciiname":"Los Caballos (Los Villarreal)",
    "gn:country_code":"MX",
    "gn:dem":6,
    "gn:feature_class":"P",
    "gn:feature_code":"PPL",
    "gn:name":"Los Caballos (Los Villarreal)",
    "gn:population":2,
    "gn:timezone":"America/Monterrey",
    "iso:country":"MX",
    "name:spa_x_preferred":[
        "Los Villarreal"
    ],
    "wof:name":"Los Caballos (Los Villarreal)",
    "wof:placetype":"locality",
    "wof:population":2
},
  "geometry": {"coordinates":[-97.86028,24.89833],"type":"Point"}
}