{
  "type": "Feature",
  "properties": {
    "gn:admin1_code":"24",
    "gn:admin2_code":"43.0",
    "gn:asciiname":"Paso de la Ordena",
    "gn:country_code":"MX",
    "gn:dem":1624,
    "gn:feature_class":"P",
    "gn:feature_code":"PPL",
    "gn:name":"Paso de la Orde\u00f1a",
    "gn:population":0,
    "gn:timezone":"America/Mexico_City",
    "iso:country":"MX",
    "name:spa_x_preferred":[
        "Paso de la Orde\u00f1a"
    ],
    "name:und_x_variant":[
        "Paso de la Ordo\u00f1a",
        "Paso Orde\u00f1a"
    ],
    "wof:name":"Paso de la Ordena",
    "wof:placetype":"locality"
},
  "geometry": {"coordinates":[-100.46105,21.6283],"type":"Point"}
}