{
  "type": "Feature",
  "properties": {
    "gn:admin1_code":"20",
    "gn:admin2_code":"509.0",
    "gn:asciiname":"Cerro Campana",
    "gn:country_code":"MX",
    "gn:dem":427,
    "gn:feature_class":"P",
    "gn:feature_code":"PPL",
    "gn:name":"Cerro Campana",
    "gn:population":0,
    "gn:timezone":"America/Mexico_City",
    "iso:country":"MX",
    "name:spa_x_preferred":[
        "Cerro Campana"
    ],
    "wof:name":"Cerro Campana",
    "wof:placetype":"locality"
},
  "geometry": {"coordinates":[-96.643,15.85388],"type":"Point"}
}