{
  "type": "Feature",
  "properties": {
    "gn:admin1_code":"10",
    "gn:admin2_code":"24.0",
    "gn:asciiname":"La Canada",
    "gn:country_code":"MX",
    "gn:dem":1689,
    "gn:feature_class":"P",
    "gn:feature_code":"PPL",
    "gn:name":"La Ca\u00f1ada",
    "gn:population":0,
    "gn:timezone":"America/Monterrey",
    "iso:country":"MX",
    "name:spa_x_preferred":[
        "La Ca\u00f1ada"
    ],
    "wof:name":"La Canada",
    "wof:placetype":"locality"
},
  "geometry": {"coordinates":[-104.71108,25.15458],"type":"Point"}
}