{
  "type": "Feature",
  "properties": {
    "gn:admin1_code":"10",
    "gn:admin2_code":"17.0",
    "gn:asciiname":"Moscu",
    "gn:country_code":"MX",
    "gn:dem":1699,
    "gn:feature_class":"P",
    "gn:feature_code":"PPL",
    "gn:name":"Mosc\u00fa",
    "gn:population":76,
    "gn:timezone":"America/Monterrey",
    "iso:country":"MX",
    "name:und_x_variant":[
        "Mosc\u00fa"
    ],
    "wof:name":"Moscu",
    "wof:placetype":"locality",
    "wof:population":76
},
  "geometry": {"coordinates":[-105.37152,26.37101],"type":"Point"}
}