{
  "type": "Feature",
  "properties": {
    "gn:admin1_code":"11",
    "gn:admin2_code":"32",
    "gn:asciiname":"Granja Santa Imelda",
    "gn:country_code":"MX",
    "gn:dem":2076,
    "gn:feature_class":"P",
    "gn:feature_code":"PPL",
    "gn:name":"Granja Santa Imelda",
    "gn:population":32,
    "gn:timezone":"America/Mexico_City",
    "iso:country":"MX",
    "wof:name":"Granja Santa Imelda",
    "wof:placetype":"locality",
    "wof:population":32
},
  "geometry": {"coordinates":[-100.40083,21.00556],"type":"Point"}
}