{
  "type": "Feature",
  "properties": {
    "gn:admin1_code":"21",
    "gn:admin2_code":"3",
    "gn:asciiname":"La Sandia",
    "gn:country_code":"MX",
    "gn:dem":1425,
    "gn:feature_class":"P",
    "gn:feature_code":"PPL",
    "gn:name":"La Sand\u00eda",
    "gn:population":51,
    "gn:timezone":"America/Mexico_City",
    "iso:country":"MX",
    "name:und_x_variant":[
        "La Sand\u00eda"
    ],
    "wof:name":"La Sandia",
    "wof:placetype":"locality",
    "wof:population":51
},
  "geometry": {"coordinates":[-98.14637,18.20631],"type":"Point"}
}