{
  "type": "Feature",
  "properties": {
    "gn:admin1_code":"5",
    "gn:admin2_code":"96.0",
    "gn:asciiname":"Chayilja",
    "gn:country_code":"MX",
    "gn:dem":1040,
    "gn:feature_class":"P",
    "gn:feature_code":"PPL",
    "gn:name":"Chayilj\u00e1",
    "gn:population":6,
    "gn:timezone":"America/Mexico_City",
    "iso:country":"MX",
    "name:und_x_variant":[
        "Chayilj\u00e1"
    ],
    "wof:name":"Chayilja",
    "wof:placetype":"locality",
    "wof:population":6
},
  "geometry": {"coordinates":[-92.44,17.21667],"type":"Point"}
}