{
  "type": "Feature",
  "properties": {
    "gn:admin1_code":"21",
    "gn:admin2_code":"207.0",
    "gn:asciiname":"Cuacuilco",
    "gn:country_code":"MX",
    "gn:dem":2312,
    "gn:feature_class":"P",
    "gn:feature_code":"PPL",
    "gn:name":"Cuacuilco",
    "gn:population":577,
    "gn:timezone":"America/Mexico_City",
    "iso:country":"MX",
    "wof:name":"Cuacuilco",
    "wof:placetype":"locality",
    "wof:population":577
},
  "geometry": {"coordinates":[-97.54361,19.85111],"type":"Point"}
}