{
  "type": "Feature",
  "properties": {
    "gn:admin1_code":"2",
    "gn:admin2_code":"3",
    "gn:asciiname":"El Molino",
    "gn:country_code":"MX",
    "gn:dem":447,
    "gn:feature_class":"P",
    "gn:feature_code":"PPL",
    "gn:name":"El Molino",
    "gn:population":31,
    "gn:timezone":"America/Tijuana",
    "iso:country":"MX",
    "wof:name":"El Molino",
    "wof:placetype":"locality",
    "wof:population":31
},
  "geometry": {"coordinates":[-116.69444,32.5175],"type":"Point"}
}