{
  "type": "Feature",
  "properties": {
    "gn:admin1_code":"11",
    "gn:admin2_code":"22",
    "gn:asciiname":"El Terrero (Estaneros)",
    "gn:country_code":"MX",
    "gn:dem":2138,
    "gn:feature_class":"P",
    "gn:feature_code":"PPL",
    "gn:name":"El Terrero (Esta\u00f1eros)",
    "gn:population":9,
    "gn:timezone":"America/Mexico_City",
    "iso:country":"MX",
    "name:und_x_variant":[
        "El Terrero (Esta\u00f1eros)"
    ],
    "wof:name":"El Terrero (Estaneros)",
    "wof:placetype":"locality",
    "wof:population":9
},
  "geometry": {"coordinates":[-101.52500000000001,21.48639],"type":"Point"}
}