{
  "type": "Feature",
  "properties": {
    "gn:admin1_code":"15",
    "gn:admin2_code":"110.0",
    "gn:asciiname":"Mata Redonda (Paso Hondo)",
    "gn:country_code":"MX",
    "gn:dem":2099,
    "gn:feature_class":"P",
    "gn:feature_code":"PPL",
    "gn:name":"Mata Redonda (Paso Hondo)",
    "gn:population":5,
    "gn:timezone":"America/Mexico_City",
    "iso:country":"MX",
    "wof:name":"Mata Redonda (Paso Hondo)",
    "wof:placetype":"locality",
    "wof:population":5
},
  "geometry": {"coordinates":[-100.15607,19.141],"type":"Point"}
}