{
  "type": "Feature",
  "properties": {
    "gn:admin1_code":"24",
    "gn:admin2_code":"38",
    "gn:asciiname":"Tomas Antonio (Chimimexco)",
    "gn:country_code":"MX",
    "gn:dem":84,
    "gn:feature_class":"P",
    "gn:feature_code":"PPL",
    "gn:name":"Tom\u00e1s Antonio (Chimimexco)",
    "gn:population":21,
    "gn:timezone":"America/Mexico_City",
    "iso:country":"MX",
    "name:und_x_variant":[
        "Tom\u00e1s Antonio (Chimimexco)"
    ],
    "wof:name":"Tomas Antonio (Chimimexco)",
    "wof:placetype":"locality",
    "wof:population":21
},
  "geometry": {"coordinates":[-98.80361000000001,21.41],"type":"Point"}
}