{
  "type": "Feature",
  "properties": {
    "gn:admin1_code":"11",
    "gn:admin2_code":"2.0",
    "gn:asciiname":"La Joya",
    "gn:country_code":"MX",
    "gn:dem":1902,
    "gn:feature_class":"P",
    "gn:feature_code":"PPL",
    "gn:name":"La Joya",
    "gn:population":167,
    "gn:timezone":"America/Mexico_City",
    "iso:country":"MX",
    "name:ceb_x_preferred":[
        "La Joya"
    ],
    "name:deu_x_preferred":[
        "La Joya"
    ],
    "name:nld_x_preferred":[
        "La Joya"
    ],
    "name:que_x_preferred":[
        "La Joya"
    ],
    "name:spa_x_preferred":[
        "La Joya"
    ],
    "name:srp_x_preferred":[
        "\u041b\u0430 \u0425\u043e\u0458\u0430"
    ],
    "name:swe_x_preferred":[
        "La Joya"
    ],
    "wof:name":"La Joya",
    "wof:placetype":"locality",
    "wof:population":167
},
  "geometry": {"coordinates":[-100.70999999999999,20.00444],"type":"Point"}
}