{
  "type": "Feature",
  "properties": {
    "gn:admin1_code":"5",
    "gn:admin2_code":"29.0",
    "gn:asciiname":"Monte Grande",
    "gn:country_code":"MX",
    "gn:dem":485,
    "gn:feature_class":"P",
    "gn:feature_code":"PPL",
    "gn:name":"Monte Grande",
    "gn:population":115,
    "gn:timezone":"America/Mexico_City",
    "iso:country":"MX",
    "name:spa_x_preferred":[
        "Monte Grande"
    ],
    "wof:name":"Monte Grande",
    "wof:placetype":"locality",
    "wof:population":115
},
  "geometry": {"coordinates":[-93.14263,16.97231],"type":"Point"}
}