{
  "type": "Feature",
  "properties": {
    "gn:admin1_code":"5",
    "gn:admin2_code":"29.0",
    "gn:asciiname":"Monte Grande",
    "gn:country_code":"MX",
    "gn:dem":485,
    "gn:feature_class":"P",
    "gn:feature_code":"PPL",
    "gn:name":"Monte Grande",
    "gn:population":115,
    "gn:timezone":"America/Mexico_City",
    "iso:country":"MX",
    "name:ara_x_preferred":[
        "\u0645\u0648\u0646\u062a\u064a \u063a\u0631\u0627\u0646\u062f\u064a"
    ],
    "name:azb_x_preferred":[
        "\u0645\u0648\u0646\u062a\u0647 \u0642\u0631\u0627\u0646\u062f\u0647"
    ],
    "name:deu_x_preferred":[
        "Monte Grande"
    ],
    "name:epo_x_preferred":[
        "Monte Grande"
    ],
    "name:fas_x_preferred":[
        "\u0645\u0648\u0646\u062a\u0647 \u06af\u0631\u0627\u0646\u062f\u0647"
    ],
    "name:fra_x_preferred":[
        "Monte Grande"
    ],
    "name:ita_x_preferred":[
        "Monte Grande"
    ],
    "name:kat_x_preferred":[
        "\u10db\u10dd\u10dc\u10e2\u10d4-\u10d2\u10e0\u10d0\u10dc\u10d3\u10d4"
    ],
    "name:nld_x_preferred":[
        "Monte Grande"
    ],
    "name:pol_x_preferred":[
        "Monte Grande"
    ],
    "name:sco_x_preferred":[
        "Monte Grande"
    ],
    "name:spa_x_preferred":[
        "Monte Grande"
    ],
    "name:zho_x_preferred":[
        "\u8499\u7279\u683c\u862d\u5fb7"
    ],
    "wof:name":"Monte Grande",
    "wof:placetype":"locality",
    "wof:population":115
},
  "geometry": {"coordinates":[-93.14263,16.97231],"type":"Point"}
}