{
  "type": "Feature",
  "properties": {
    "gn:admin1_code":"26",
    "gn:admin2_code":"18.0",
    "gn:asciiname":"Los Tortugas",
    "gn:country_code":"MX",
    "gn:dem":62,
    "gn:feature_class":"P",
    "gn:feature_code":"PPL",
    "gn:name":"Los Tortugas",
    "gn:population":0,
    "gn:timezone":"America/Hermosillo",
    "iso:country":"MX",
    "name:spa_x_preferred":[
        "Los Tortugas"
    ],
    "name:und_x_variant":[
        "Rancho Las Tortugas"
    ],
    "wof:name":"Los Tortugas",
    "wof:placetype":"locality"
},
  "geometry": {"coordinates":[-109.9665,27.72295],"type":"Point"}
}