{
  "type": "Feature",
  "properties": {
    "gn:admin1_code":"5",
    "gn:admin2_code":"32.0",
    "gn:asciiname":"El Horizonte I",
    "gn:country_code":"MX",
    "gn:dem":1721,
    "gn:feature_class":"P",
    "gn:feature_code":"PPL",
    "gn:name":"El Horizonte I",
    "gn:population":129,
    "gn:timezone":"America/Mexico_City",
    "iso:country":"MX",
    "wof:name":"El Horizonte I",
    "wof:placetype":"locality",
    "wof:population":129
},
  "geometry": {"coordinates":[-92.46778,15.38],"type":"Point"}
}