{
  "type": "Feature",
  "properties": {
    "gn:admin1_code":"11.0",
    "gn:asciiname":"Polvorines",
    "gn:country_code":"MX",
    "gn:dem":1909,
    "gn:feature_class":"P",
    "gn:feature_code":"PPL",
    "gn:name":"Polvorines",
    "gn:population":0,
    "gn:timezone":"America/Mexico_City",
    "iso:country":"MX",
    "name:spa_x_preferred":[
        "Polvorines"
    ],
    "wof:name":"Polvorines",
    "wof:placetype":"locality"
},
  "geometry": {"coordinates":[-101.31292999999999,20.9425],"type":"Point"}
}