{
  "type": "Feature",
  "properties": {
    "gn:admin1_code":"6",
    "gn:admin2_code":"5.0",
    "gn:asciiname":"El Diez",
    "gn:country_code":"MX",
    "gn:dem":1310,
    "gn:feature_class":"P",
    "gn:feature_code":"PPL",
    "gn:name":"El Diez",
    "gn:population":5,
    "gn:timezone":"America/Chihuahua",
    "iso:country":"MX",
    "wof:name":"El Diez",
    "wof:placetype":"locality",
    "wof:population":5
},
  "geometry": {"coordinates":[-108.06975,31.07123],"type":"Point"}
}