{
  "type": "Feature",
  "properties": {
    "iso:country":"MX",
    "name:ara_x_preferred":[
        "\u0625\u0633\u0645\u0627\u0639\u064a\u0644 \u063a\u0627\u0631\u0633\u064a\u0627"
    ],
    "name:ast_x_preferred":[
        "Ismael Garc\u00eda"
    ],
    "name:deu_x_preferred":[
        "Ismael Garc\u00eda"
    ],
    "name:eng_x_preferred":[
        "Ismael Garc\u00eda"
    ],
    "name:fra_x_preferred":[
        "Ismael Garc\u00eda"
    ],
    "name:hun_x_preferred":[
        "Ismael Garc\u00eda"
    ],
    "name:nld_x_preferred":[
        "Ismael Garc\u00eda"
    ],
    "name:slv_x_preferred":[
        "Ismael Garc\u00eda"
    ],
    "name:spa_x_preferred":[
        "Ismael Garcia",
        "Ismael Garc\u00eda"
    ],
    "qs:gn_adm0_cc":"MX",
    "qs:gn_local":3521108,
    "qs:gn_nam_loc":"Progreso, Progreso, Yucatan, MX",
    "qs:gn_namadm1":"31",
    "qs:local_max":324,
    "qs:local_sum":557,
    "qs:localhoods":3,
    "qs:name":"Ismael Garcia",
    "qs:name_adm0":"M\u00e9xico",
    "qs:name_adm1":"Yucatan",
    "qs:name_adm2":"Progreso",
    "qs:name_local":"Progreso",
    "qs:photo_max":44,
    "qs:photo_sum":203,
    "qs:placetype":"Suburb",
    "qs:quad_count":17,
    "qs:woe_adm0":23424900,
    "qs:woe_adm1":2346294,
    "qs:woe_adm2":12601984,
    "qs:woe_lau":0,
    "qs:woe_local":137541,
    "qs:woe_ver":"7.10.0",
    "wd:wordcount":202,
    "wof:lang":[
        "spa"
    ],
    "wof:name":"Ismael Garcia",
    "wof:placetype":"neighbourhood"
},
  "geometry": {"coordinates":[-89.658055,21.288358],"type":"Point"}
}