{
  "type": "Feature",
  "properties": {
    "gn:admin1_code":"26",
    "gn:admin2_code":"55.0",
    "gn:asciiname":"El Herrero",
    "gn:country_code":"MX",
    "gn:dem":27,
    "gn:feature_class":"P",
    "gn:feature_code":"PPL",
    "gn:name":"El Herrero",
    "gn:population":6,
    "gn:timezone":"America/Hermosillo",
    "iso:country":"MX",
    "wof:name":"El Herrero",
    "wof:placetype":"locality",
    "wof:population":6
},
  "geometry": {"coordinates":[-114.86499999999999,32.44889000000001],"type":"Point"}
}