{
  "type": "Feature",
  "properties": {
    "gn:admin1_code":"12.0",
    "gn:admin2_code":"52.0",
    "gn:asciiname":"Guitarra",
    "gn:country_code":"MX",
    "gn:dem":1292,
    "gn:feature_class":"P",
    "gn:feature_code":"PPL",
    "gn:name":"Guitarra",
    "gn:population":0,
    "gn:timezone":"America/Mexico_City",
    "iso:country":"MX",
    "name:spa_x_preferred":[
        "Guitarra"
    ],
    "wof:name":"Guitarra",
    "wof:placetype":"locality"
},
  "geometry": {"coordinates":[-98.90143,17.00974],"type":"Point"}
}