{
  "type": "Feature",
  "properties": {
    "gn:admin1_code":"14.0",
    "gn:admin2_code":"35.0",
    "gn:asciiname":"Las Majadas de Arriba",
    "gn:country_code":"MX",
    "gn:dem":1937,
    "gn:feature_class":"P",
    "gn:feature_code":"PPL",
    "gn:name":"Las Majadas de Arriba",
    "gn:population":0,
    "gn:timezone":"America/Mexico_City",
    "iso:country":"MX",
    "name:spa_x_preferred":[
        "Las Majadas de Arriba"
    ],
    "wof:name":"Las Majadas de Arriba",
    "wof:placetype":"locality"
},
  "geometry": {"coordinates":[-102.09907,21.64988],"type":"Point"}
}