{
  "type": "Feature",
  "properties": {
    "gn:admin1_code":"23",
    "gn:admin2_code":"5.0",
    "gn:asciiname":"Cardenal",
    "gn:country_code":"MX",
    "gn:dem":14,
    "gn:feature_class":"P",
    "gn:feature_code":"PPL",
    "gn:name":"Cardenal",
    "gn:population":0,
    "gn:timezone":"America/Cancun",
    "iso:country":"MX",
    "name:spa_x_preferred":[
        "Cardenal"
    ],
    "wof:name":"Cardenal",
    "wof:placetype":"locality"
},
  "geometry": {"coordinates":[-86.8638,20.96928],"type":"Point"}
}