{
  "type": "Feature",
  "properties": {
    "gn:admin1_code":"4",
    "gn:admin2_code":"3.0",
    "gn:asciiname":"Ojo de Agua de Cuyoc",
    "gn:country_code":"MX",
    "gn:dem":20,
    "gn:feature_class":"P",
    "gn:feature_code":"PPL",
    "gn:name":"Ojo de Agua de Cuyoc",
    "gn:population":6,
    "gn:timezone":"America/Merida",
    "iso:country":"MX",
    "wof:name":"Ojo de Agua de Cuyoc",
    "wof:placetype":"locality",
    "wof:population":6
},
  "geometry": {"coordinates":[-91.16361000000001,18.42889],"type":"Point"}
}