{
  "type": "Feature",
  "properties": {
    "gn:admin1_code":"30",
    "gn:admin2_code":"58.0",
    "gn:asciiname":"Huacango",
    "gn:country_code":"MX",
    "gn:dem":307,
    "gn:feature_class":"P",
    "gn:feature_code":"PPL",
    "gn:name":"Huacango",
    "gn:population":0,
    "gn:timezone":"America/Mexico_City",
    "iso:country":"MX",
    "name:und_x_variant":[
        "Huacatigo",
        "Huacango"
    ],
    "wof:name":"Huacango",
    "wof:placetype":"locality"
},
  "geometry": {"coordinates":[-98.11122,20.94617],"type":"Point"}
}