{
  "type": "Feature",
  "properties": {
    "gn:admin1_code":"11.0",
    "gn:admin2_code":"20.0",
    "gn:asciiname":"Capellania de Loera",
    "gn:country_code":"MX",
    "gn:dem":1810,
    "gn:feature_class":"P",
    "gn:feature_code":"PPL",
    "gn:name":"Capellan\u00eda de Loera",
    "gn:population":0,
    "gn:timezone":"America/Mexico_City",
    "iso:country":"MX",
    "name:spa_x_preferred":[
        "Capellan\u00eda de Loera"
    ],
    "wof:name":"Capellania de Loera",
    "wof:placetype":"locality"
},
  "geometry": {"coordinates":[-101.5976,21.03448],"type":"Point"}
}