{
  "type": "Feature",
  "properties": {
    "gn:admin1_code":"11",
    "gn:admin2_code":"19.0",
    "gn:asciiname":"Corrales de la Ordena",
    "gn:country_code":"MX",
    "gn:dem":2244,
    "gn:feature_class":"P",
    "gn:feature_code":"PPL",
    "gn:name":"Corrales de la Orde\u00f1a",
    "gn:population":203,
    "gn:timezone":"America/Mexico_City",
    "iso:country":"MX",
    "name:und_x_variant":[
        "Corrales de la Orde\u00f1a"
    ],
    "wof:name":"Corrales de la Ordena",
    "wof:placetype":"locality",
    "wof:population":203
},
  "geometry": {"coordinates":[-100.47972,20.30306],"type":"Point"}
}