{
  "type": "Feature",
  "properties": {
    "gn:admin1_code":"14",
    "gn:admin2_code":"13.0",
    "gn:asciiname":"El Crucerito (El Bramido)",
    "gn:country_code":"MX",
    "gn:dem":1551,
    "gn:feature_class":"P",
    "gn:feature_code":"PPL",
    "gn:name":"El Crucerito (El Bramido)",
    "gn:population":54,
    "gn:timezone":"America/Mexico_City",
    "iso:country":"MX",
    "wof:name":"El Crucerito (El Bramido)",
    "wof:placetype":"locality",
    "wof:population":54
},
  "geometry": {"coordinates":[-102.49639000000001,20.47806],"type":"Point"}
}