{
  "type": "Feature",
  "properties": {
    "gn:admin1_code":"30",
    "gn:admin2_code":"192.0",
    "gn:asciiname":"Tacahuite Viejo",
    "gn:country_code":"MX",
    "gn:dem":33,
    "gn:feature_class":"P",
    "gn:feature_code":"PPL",
    "gn:name":"Tacahuite Viejo",
    "gn:population":5,
    "gn:timezone":"America/Mexico_City",
    "iso:country":"MX",
    "wof:name":"Tacahuite Viejo",
    "wof:placetype":"locality",
    "wof:population":5
},
  "geometry": {"coordinates":[-96.66,20.00806],"type":"Point"}
}