{
  "type": "Feature",
  "properties": {
    "gn:admin1_code":"10",
    "gn:admin2_code":"37.0",
    "gn:asciiname":"El Burro",
    "gn:country_code":"MX",
    "gn:dem":1052,
    "gn:feature_class":"P",
    "gn:feature_code":"PPL",
    "gn:name":"El Burro",
    "gn:population":0,
    "gn:timezone":"America/Monterrey",
    "iso:country":"MX",
    "name:spa_x_preferred":[
        "El Burro"
    ],
    "wof:name":"El Burro",
    "wof:placetype":"locality"
},
  "geometry": {"coordinates":[-106.63196000000001,25.33477],"type":"Point"}
}