{
  "type": "Feature",
  "properties": {
    "gn:admin1_code":"30",
    "gn:admin2_code":"14.0",
    "gn:asciiname":"Ojo de Agua Grande",
    "gn:country_code":"MX",
    "gn:dem":592,
    "gn:feature_class":"P",
    "gn:feature_code":"PPL",
    "gn:name":"Ojo de Agua Grande",
    "gn:population":0,
    "gn:timezone":"America/Mexico_City",
    "iso:country":"MX",
    "wof:name":"Ojo de Agua Grande",
    "wof:placetype":"locality"
},
  "geometry": {"coordinates":[-96.85293,18.90142],"type":"Point"}
}