{
  "type": "Feature",
  "properties": {
    "gn:admin1_code":"6.0",
    "gn:admin2_code":"46.0",
    "gn:asciiname":"Batosachi",
    "gn:country_code":"MX",
    "gn:dem":2270,
    "gn:feature_class":"P",
    "gn:feature_code":"PPL",
    "gn:name":"Batosachi",
    "gn:population":0,
    "gn:timezone":"America/Chihuahua",
    "iso:country":"MX",
    "name:spa_x_preferred":[
        "Batosachi"
    ],
    "wof:name":"Batosachi",
    "wof:placetype":"locality"
},
  "geometry": {"coordinates":[-107.44504000000001,26.63797000000001],"type":"Point"}
}