{
  "type": "Feature",
  "properties": {
    "gn:admin1_code":"5.0",
    "gn:admin2_code":"57.0",
    "gn:asciiname":"El Progreso",
    "gn:country_code":"MX",
    "gn:dem":506,
    "gn:feature_class":"P",
    "gn:feature_code":"PPL",
    "gn:name":"El Progreso",
    "gn:population":0,
    "gn:timezone":"America/Mexico_City",
    "iso:country":"MX",
    "name:ara_x_preferred":[
        "\u0625\u064a\u0644 \u0628\u0631\u0648\u062c\u0631\u064a\u0633\u0648"
    ],
    "name:ben_x_preferred":[
        "\u098f\u09b2 \u09aa\u09cd\u09b0\u09cb\u0997\u09cd\u09b0\u09c7\u09b8\u09cb"
    ],
    "name:bul_x_preferred":[
        "\u0415\u043b \u041f\u0440\u043e\u0433\u0440\u0435\u0441\u043e"
    ],
    "name:cat_x_preferred":[
        "El Progreso"
    ],
    "name:ceb_x_preferred":[
        "El Progreso"
    ],
    "name:deu_x_preferred":[
        "El Progreso"
    ],
    "name:ell_x_preferred":[
        "\u0395\u03bb \u03a0\u03c1\u03bf\u03b3\u03ba\u03c1\u03ad\u03c3\u03bf"
    ],
    "name:fas_x_preferred":[
        "\u0627\u0644 \u067e\u0631\u0648\u06af\u0631\u0633\u0648"
    ],
    "name:fra_x_preferred":[
        "El Progreso"
    ],
    "name:heb_x_preferred":[
        "\u05d0\u05dc \u05e4\u05e8\u05d5\u05d2\u05e8\u05e1\u05d5"
    ],
    "name:hin_x_preferred":[
        "\u090f\u0932 \u092a\u094d\u0930\u094b\u0917\u094d\u0930\u0947\u0938\u094b"
    ],
    "name:hun_x_preferred":[
        "El Progreso"
    ],
    "name:ind_x_preferred":[
        "El Progreso"
    ],
    "name:ita_x_preferred":[
        "El Progreso"
    ],
    "name:jpn_x_preferred":[
        "\u30a8\u30eb\u30fb\u30d7\u30ed\u30b0\u30ec\u30bd"
    ],
    "name:kor_x_preferred":[
        "\uc5d8 \ud504\ub85c\uadf8\ub808\uc18c"
    ],
    "name:lit_x_preferred":[
        "El Progresas"
    ],
    "name:nld_x_preferred":[
        "El Progreso"
    ],
    "name:pol_x_preferred":[
        "El Progreso"
    ],
    "name:por_x_preferred":[
        "El Progreso"
    ],
    "name:rus_x_preferred":[
        "\u042d\u043b\u044c-\u041f\u0440\u043e\u0433\u0440\u0435\u0441\u043e"
    ],
    "name:spa_x_preferred":[
        "El Progreso"
    ],
    "name:swe_x_preferred":[
        "El Progreso"
    ],
    "name:tur_x_preferred":[
        "El Progreso"
    ],
    "name:ukr_x_preferred":[
        "\u0415\u043b\u044c-\u041f\u0440\u043e\u0433\u0440\u0435\u0441\u043e"
    ],
    "name:urd_x_preferred":[
        "\u0627\u06cc\u0644 \u067e\u0631\u0648\u06af\u0631\u06cc\u0633\u0648"
    ],
    "name:vie_x_preferred":[
        "El Progreso"
    ],
    "name:war_x_preferred":[
        "El Progreso"
    ],
    "name:zho_x_preferred":[
        "\u57c3\u723e\u666e\u7f85\u683c\u96f7\u7d22"
    ],
    "wof:name":"El Progreso",
    "wof:placetype":"locality"
},
  "geometry": {"coordinates":[-92.39854,15.26443],"type":"Point"}
}