{
  "type": "Feature",
  "properties": {
    "gn:admin1_code":"30",
    "gn:admin2_code":"197",
    "gn:asciiname":"Colonia Saltillo",
    "gn:country_code":"MX",
    "gn:dem":502,
    "gn:feature_class":"P",
    "gn:feature_code":"PPL",
    "gn:name":"Colonia Saltillo",
    "gn:population":12,
    "gn:timezone":"America/Mexico_City",
    "iso:country":"MX",
    "wof:name":"Colonia Saltillo",
    "wof:placetype":"locality",
    "wof:population":12
},
  "geometry": {"coordinates":[-96.7375,19.84889],"type":"Point"}
}