{
  "type": "Feature",
  "properties": {
    "gn:admin1_code":"18.0",
    "gn:admin2_code":"13.0",
    "gn:asciiname":"Camichin de Jauja",
    "gn:cc2":"MX",
    "gn:country_code":"MX",
    "gn:dem":505,
    "gn:feature_class":"P",
    "gn:feature_code":"PPL",
    "gn:name":"Camich\u00edn de Jauja",
    "gn:population":0,
    "gn:timezone":"America/Mexico_City",
    "iso:country":"MX",
    "name:und_x_variant":[
        "Camichin",
        "Camich\u00edn de Jauja"
    ],
    "wof:name":"Camichin de Jauja",
    "wof:placetype":"locality"
},
  "geometry": {"coordinates":[-104.76667,21.01667],"type":"Point"}
}