{
  "type": "Feature",
  "properties": {
    "gn:admin1_code":"32",
    "gn:admin2_code":"51.0",
    "gn:asciiname":"El Arbolito",
    "gn:country_code":"MX",
    "gn:dem":1995,
    "gn:feature_class":"P",
    "gn:feature_code":"PPL",
    "gn:name":"El Arbolito",
    "gn:population":6,
    "gn:timezone":"America/Mexico_City",
    "iso:country":"MX",
    "wof:name":"El Arbolito",
    "wof:placetype":"locality",
    "wof:population":6
},
  "geometry": {"coordinates":[-102.30249999999999,23.0525],"type":"Point"}
}