{
  "type": "Feature",
  "properties": {
    "gn:admin1_code":"6",
    "gn:admin2_code":"9.0",
    "gn:asciiname":"Humachique (Cuevas de Leones)",
    "gn:country_code":"MX",
    "gn:dem":2379,
    "gn:feature_class":"P",
    "gn:feature_code":"PPL",
    "gn:name":"Humachique (Cuevas de Leones)",
    "gn:population":76,
    "gn:timezone":"America/Chihuahua",
    "iso:country":"MX",
    "wof:name":"Humachique (Cuevas de Leones)",
    "wof:placetype":"locality",
    "wof:population":76
},
  "geometry": {"coordinates":[-107.64825999999999,27.74242000000001],"type":"Point"}
}