{
  "type": "Feature",
  "properties": {
    "gn:admin1_code":"3",
    "gn:admin2_code":"8.0",
    "gn:asciiname":"El Agua de Paloma",
    "gn:country_code":"MX",
    "gn:dem":211,
    "gn:feature_class":"P",
    "gn:feature_code":"PPL",
    "gn:name":"El Agua de Paloma",
    "gn:population":5,
    "gn:timezone":"America/Mazatlan",
    "iso:country":"MX",
    "wof:name":"El Agua de Paloma",
    "wof:placetype":"locality",
    "wof:population":5
},
  "geometry": {"coordinates":[-110.0283,23.02405],"type":"Point"}
}