{
  "type": "Feature",
  "properties": {
    "gn:admin1_code":"20",
    "gn:admin2_code":"377.0",
    "gn:asciiname":"Morelos",
    "gn:country_code":"MX",
    "gn:dem":1545,
    "gn:feature_class":"P",
    "gn:feature_code":"PPL",
    "gn:name":"Morelos",
    "gn:population":560,
    "gn:timezone":"America/Mexico_City",
    "iso:country":"MX",
    "wof:name":"Morelos",
    "wof:placetype":"locality",
    "wof:population":560
},
  "geometry": {"coordinates":[-97.67694,16.79472],"type":"Point"}
}