{
  "type": "Feature",
  "properties": {
    "gn:admin1_code":"10",
    "gn:admin2_code":"37",
    "gn:asciiname":"El Nurito",
    "gn:country_code":"MX",
    "gn:dem":1388,
    "gn:feature_class":"P",
    "gn:feature_code":"PPL",
    "gn:name":"El Nurito",
    "gn:population":49,
    "gn:timezone":"America/Monterrey",
    "iso:country":"MX",
    "wof:name":"El Nurito",
    "wof:placetype":"locality",
    "wof:population":49
},
  "geometry": {"coordinates":[-106.74231,25.1522],"type":"Point"}
}