{
  "type": "Feature",
  "properties": {
    "gn:admin1_code":"26",
    "gn:admin2_code":"18.0",
    "gn:asciiname":"La Ventana",
    "gn:country_code":"MX",
    "gn:dem":102,
    "gn:feature_class":"P",
    "gn:feature_code":"PPL",
    "gn:name":"La Ventana",
    "gn:population":0,
    "gn:timezone":"America/Hermosillo",
    "iso:country":"MX",
    "name:spa_x_preferred":[
        "La Ventana"
    ],
    "wof:name":"La Ventana",
    "wof:placetype":"locality"
},
  "geometry": {"coordinates":[-109.81999999999999,28.06609000000001],"type":"Point"}
}