{
  "type": "Feature",
  "properties": {
    "gn:admin1_code":"16",
    "gn:admin2_code":"97",
    "gn:asciiname":"El Limon de Apo",
    "gn:country_code":"MX",
    "gn:dem":785,
    "gn:feature_class":"P",
    "gn:feature_code":"PPL",
    "gn:name":"El Lim\u00f3n de Apo",
    "gn:population":42,
    "gn:timezone":"America/Mexico_City",
    "iso:country":"MX",
    "name:und_x_variant":[
        "El Lim\u00f3n de Apo"
    ],
    "wof:name":"El Limon de Apo",
    "wof:placetype":"locality",
    "wof:population":42
},
  "geometry": {"coordinates":[-101.37889,19.08111],"type":"Point"}
}