{
  "type": "Feature",
  "properties": {
    "gn:admin1_code":"16",
    "gn:admin2_code":"17.0",
    "gn:asciiname":"Cerro Agujerado (Cuartel Tercero)",
    "gn:country_code":"MX",
    "gn:dem":2398,
    "gn:feature_class":"P",
    "gn:feature_code":"PPL",
    "gn:name":"Cerro Agujerado (Cuartel Tercero)",
    "gn:population":182,
    "gn:timezone":"America/Mexico_City",
    "iso:country":"MX",
    "wof:name":"Cerro Agujerado (Cuartel Tercero)",
    "wof:placetype":"locality",
    "wof:population":182
},
  "geometry": {"coordinates":[-100.16667,19.93222],"type":"Point"}
}