{
  "type": "Feature",
  "properties": {
    "gn:admin1_code":"10",
    "gn:admin2_code":"14.0",
    "gn:asciiname":"El Cerro de la Flor",
    "gn:country_code":"MX",
    "gn:dem":2037,
    "gn:feature_class":"P",
    "gn:feature_code":"PPL",
    "gn:name":"El Cerro de la Flor",
    "gn:population":5,
    "gn:timezone":"America/Monterrey",
    "iso:country":"MX",
    "wof:name":"El Cerro de la Flor",
    "wof:placetype":"locality",
    "wof:population":5
},
  "geometry": {"coordinates":[-104.79470000000001,23.22808],"type":"Point"}
}