{
  "type": "Feature",
  "properties": {
    "gn:admin1_code":"30",
    "gn:admin2_code":"8.0",
    "gn:asciiname":"Loma de Buenos Aires",
    "gn:country_code":"MX",
    "gn:dem":2327,
    "gn:feature_class":"P",
    "gn:feature_code":"PPL",
    "gn:name":"Loma de Buenos Aires",
    "gn:population":156,
    "gn:timezone":"America/Mexico_City",
    "iso:country":"MX",
    "wof:name":"Loma de Buenos Aires",
    "wof:placetype":"locality",
    "wof:population":156
},
  "geometry": {"coordinates":[-97.12721999999999,19.11528],"type":"Point"}
}