{
  "type": "Feature",
  "properties": {
    "gn:admin1_code":"6",
    "gn:admin2_code":"41.0",
    "gn:asciiname":"Basoneachi",
    "gn:country_code":"MX",
    "gn:dem":2229,
    "gn:feature_class":"P",
    "gn:feature_code":"PPL",
    "gn:name":"Basoneachi",
    "gn:population":0,
    "gn:timezone":"America/Chihuahua",
    "iso:country":"MX",
    "name:spa_x_preferred":[
        "Basoneachi"
    ],
    "wof:name":"Basoneachi",
    "wof:placetype":"locality"
},
  "geometry": {"coordinates":[-107.86803,27.70041],"type":"Point"}
}