{
  "type": "Feature",
  "properties": {
    "gn:admin1_code":"30",
    "gn:admin2_code":"61.0",
    "gn:asciiname":"Francisco I. Madero",
    "gn:country_code":"MX",
    "gn:dem":369,
    "gn:feature_class":"P",
    "gn:feature_code":"PPL",
    "gn:name":"Francisco I. Madero",
    "gn:population":109,
    "gn:timezone":"America/Mexico_City",
    "iso:country":"MX",
    "wof:name":"Francisco I. Madero",
    "wof:placetype":"locality",
    "wof:population":109
},
  "geometry": {"coordinates":[-93.78861000000001,17.27167],"type":"Point"}
}