{
  "type": "Feature",
  "properties": {
    "gn:admin1_code":"5",
    "gn:admin2_code":"77",
    "gn:asciiname":"El Cause",
    "gn:country_code":"MX",
    "gn:dem":76,
    "gn:feature_class":"P",
    "gn:feature_code":"PPL",
    "gn:name":"El Cause",
    "gn:population":9,
    "gn:timezone":"America/Mexico_City",
    "iso:country":"MX",
    "wof:name":"El Cause",
    "wof:placetype":"locality",
    "wof:population":9
},
  "geometry": {"coordinates":[-92.05333,17.30111],"type":"Point"}
}