{
  "type": "Feature",
  "properties": {
    "gn:admin1_code":"23",
    "gn:admin2_code":"2.0",
    "gn:asciiname":"Polinquin",
    "gn:country_code":"MX",
    "gn:dem":13,
    "gn:feature_class":"P",
    "gn:feature_code":"PPL",
    "gn:name":"Polinquin",
    "gn:population":0,
    "gn:timezone":"America/Cancun",
    "iso:country":"MX",
    "name:und_x_variant":[
        "Polink\u00edn",
        "Poluincil",
        "Poluink\u00edn"
    ],
    "wof:name":"Polinquin",
    "wof:placetype":"locality"
},
  "geometry": {"coordinates":[-88.17017,19.17495],"type":"Point"}
}