{
  "type": "Feature",
  "properties": {
    "gn:admin1_code":"20.0",
    "gn:admin2_code":"465.0",
    "gn:asciiname":"El Morro",
    "gn:country_code":"MX",
    "gn:dem":878,
    "gn:feature_class":"P",
    "gn:feature_code":"PPL",
    "gn:name":"El Morro",
    "gn:population":0,
    "gn:timezone":"America/Mexico_City",
    "iso:country":"MX",
    "name:ceb_x_preferred":[
        "El Morro"
    ],
    "name:deu_x_preferred":[
        "El Morro"
    ],
    "name:fra_x_preferred":[
        "El Morro"
    ],
    "name:spa_x_preferred":[
        "El Morro"
    ],
    "name:swe_x_preferred":[
        "El Morro"
    ],
    "wof:name":"El Morro",
    "wof:placetype":"locality"
},
  "geometry": {"coordinates":[-95.59936,16.89862999999999],"type":"Point"}
}