{
  "type": "Feature",
  "properties": {
    "gn:admin1_code":"31",
    "gn:admin2_code":"15.0",
    "gn:asciiname":"Nohchacan",
    "gn:country_code":"MX",
    "gn:dem":15,
    "gn:feature_class":"P",
    "gn:feature_code":"PPL",
    "gn:name":"Nohchacan",
    "gn:population":0,
    "gn:timezone":"America/Merida",
    "iso:country":"MX",
    "name:und_x_variant":[
        "Nohchak\u00e1n",
        "Nohchakain"
    ],
    "wof:name":"Nohchacan",
    "wof:placetype":"locality"
},
  "geometry": {"coordinates":[-89.33633,20.74619],"type":"Point"}
}