{
  "type": "Feature",
  "properties": {
    "gn:admin1_code":"2.0",
    "gn:admin2_code":"2.0",
    "gn:asciiname":"Colonia Silva Sur (Las Playitas)",
    "gn:country_code":"MX",
    "gn:dem":19,
    "gn:feature_class":"P",
    "gn:feature_code":"PPL",
    "gn:name":"Colonia Silva Sur (Las Playitas)",
    "gn:population":263,
    "gn:timezone":"America/Tijuana",
    "iso:country":"MX",
    "name:spa_x_preferred":[
        "Colonia Silva Sur"
    ],
    "wof:name":"Colonia Silva Sur (Las Playitas)",
    "wof:placetype":"locality",
    "wof:population":263
},
  "geometry": {"coordinates":[-115.04000000000001,32.36944],"type":"Point"}
}