{
  "type": "Feature",
  "properties": {
    "gn:admin1_code":"5",
    "gn:admin2_code":"100.0",
    "gn:asciiname":"Sombra Chica",
    "gn:country_code":"MX",
    "gn:dem":1250,
    "gn:feature_class":"P",
    "gn:feature_code":"PPL",
    "gn:name":"Sombra Chica",
    "gn:population":59,
    "gn:timezone":"America/Mexico_City",
    "iso:country":"MX",
    "wof:name":"Sombra Chica",
    "wof:placetype":"locality",
    "wof:population":59
},
  "geometry": {"coordinates":[-92.30889000000001,17.29583],"type":"Point"}
}