{
  "type": "Feature",
  "properties": {
    "gn:admin1_code":"28",
    "gn:admin2_code":"32",
    "gn:asciiname":"Ideales de la Revolucion",
    "gn:country_code":"MX",
    "gn:dem":65,
    "gn:feature_class":"P",
    "gn:feature_code":"PPL",
    "gn:name":"Ideales de la Revoluci\u00f3n",
    "gn:population":30,
    "gn:timezone":"America/Matamoros",
    "iso:country":"MX",
    "name:und_x_variant":[
        "Ideales de la Revoluci\u00f3n"
    ],
    "wof:name":"Ideales de la Revolucion",
    "wof:placetype":"locality",
    "wof:population":30
},
  "geometry": {"coordinates":[-98.25861,25.78222],"type":"Point"}
}