{
  "type": "Feature",
  "properties": {
    "gn:admin1_code":"32",
    "gn:admin2_code":"10.0",
    "gn:asciiname":"Tapias de Mezquite",
    "gn:cc2":"MX",
    "gn:country_code":"MX",
    "gn:dem":2081,
    "gn:feature_class":"P",
    "gn:feature_code":"PPL",
    "gn:name":"Tapias de Mezquite",
    "gn:population":0,
    "gn:timezone":"America/Mexico_City",
    "iso:country":"MX",
    "name:und_x_variant":[
        "Tapias",
        "Tapias de Mezquite"
    ],
    "wof:name":"Tapias de Mezquite",
    "wof:placetype":"locality"
},
  "geometry": {"coordinates":[-102.58333,23.46667],"type":"Point"}
}