{
  "type": "Feature",
  "properties": {
    "gn:admin1_code":"16",
    "gn:admin2_code":"66",
    "gn:asciiname":"Ampliacion Buena Vista",
    "gn:country_code":"MX",
    "gn:dem":2051,
    "gn:feature_class":"P",
    "gn:feature_code":"PPL",
    "gn:name":"Ampliaci\u00f3n Buena Vista",
    "gn:population":47,
    "gn:timezone":"America/Mexico_City",
    "iso:country":"MX",
    "name:und_x_variant":[
        "Ampliaci\u00f3n Buena Vista"
    ],
    "wof:name":"Ampliacion Buena Vista",
    "wof:placetype":"locality",
    "wof:population":47
},
  "geometry": {"coordinates":[-101.55056,19.54833],"type":"Point"}
}