{
  "type": "Feature",
  "properties": {
    "gn:admin1_code":"3",
    "gn:admin2_code":"2.0",
    "gn:asciiname":"Una de Gato",
    "gn:country_code":"MX",
    "gn:dem":237,
    "gn:feature_class":"P",
    "gn:feature_code":"PPL",
    "gn:name":"U\u00f1a de Gato",
    "gn:population":5,
    "gn:timezone":"America/Mazatlan",
    "iso:country":"MX",
    "name:und_x_variant":[
        "U\u00f1a de Gato"
    ],
    "wof:name":"Una de Gato",
    "wof:placetype":"locality",
    "wof:population":5
},
  "geometry": {"coordinates":[-112.21151,26.97355],"type":"Point"}
}