{
  "type": "Feature",
  "properties": {
    "gn:admin1_code":"6",
    "gn:admin2_code":"62.0",
    "gn:asciiname":"Campo Viejo de Beisbol",
    "gn:country_code":"MX",
    "gn:dem":1305,
    "gn:feature_class":"P",
    "gn:feature_code":"PPL",
    "gn:name":"Campo Viejo de Beisbol",
    "gn:population":7,
    "gn:timezone":"America/Chihuahua",
    "iso:country":"MX",
    "wof:name":"Campo Viejo de Beisbol",
    "wof:placetype":"locality",
    "wof:population":7
},
  "geometry": {"coordinates":[-105.48629,27.86132000000001],"type":"Point"}
}