{
  "type": "Feature",
  "properties": {
    "gn:admin1_code":"22",
    "gn:admin2_code":"14.0",
    "gn:asciiname":"Rancho la Tinaja",
    "gn:country_code":"MX",
    "gn:dem":2144,
    "gn:feature_class":"P",
    "gn:feature_code":"PPL",
    "gn:name":"Rancho la Tinaja",
    "gn:population":0,
    "gn:timezone":"America/Mexico_City",
    "iso:country":"MX",
    "name:spa_x_preferred":[
        "Rancho la Tinaja"
    ],
    "name:und_x_variant":[
        "Tinaja",
        "La Tinaja de la Estancia"
    ],
    "wof:name":"Rancho la Tinaja",
    "wof:placetype":"locality"
},
  "geometry": {"coordinates":[-100.55961000000001,20.71364],"type":"Point"}
}