{
  "type": "Feature",
  "properties": {
    "gn:admin1_code":"20",
    "gn:admin2_code":"470.0",
    "gn:asciiname":"La Union",
    "gn:country_code":"MX",
    "gn:dem":739,
    "gn:feature_class":"P",
    "gn:feature_code":"PPL",
    "gn:name":"La Uni\u00f3n",
    "gn:population":6,
    "gn:timezone":"America/Mexico_City",
    "iso:country":"MX",
    "name:und_x_variant":[
        "La Uni\u00f3n"
    ],
    "wof:name":"La Union",
    "wof:placetype":"locality",
    "wof:population":6
},
  "geometry": {"coordinates":[-95.54056,16.87444],"type":"Point"}
}