{
  "type": "Feature",
  "properties": {
    "gn:admin1_code":"5.0",
    "gn:asciiname":"Las Guayabas",
    "gn:country_code":"MX",
    "gn:dem":592,
    "gn:feature_class":"P",
    "gn:feature_code":"PPL",
    "gn:name":"Las Guayabas",
    "gn:population":0,
    "gn:timezone":"America/Mexico_City",
    "iso:country":"MX",
    "name:spa_x_preferred":[
        "Las Guayabas"
    ],
    "wof:name":"Las Guayabas",
    "wof:placetype":"locality"
},
  "geometry": {"coordinates":[-92.31104999999999,15.74303],"type":"Point"}
}