{
  "type": "Feature",
  "properties": {
    "gn:admin1_code":"30",
    "gn:admin2_code":"69.0",
    "gn:asciiname":"Anclon y Arenal",
    "gn:country_code":"MX",
    "gn:dem":15,
    "gn:feature_class":"P",
    "gn:feature_code":"PPL",
    "gn:name":"Ancl\u00f3n y Arenal",
    "gn:population":0,
    "gn:timezone":"America/Mexico_City",
    "iso:country":"MX",
    "name:und_x_variant":[
        "Ancl\u00f3n",
        "Ancl\u00f3n y Arenal"
    ],
    "wof:name":"Anclon y Arenal",
    "wof:placetype":"locality"
},
  "geometry": {"coordinates":[-97.11648,20.43514],"type":"Point"}
}