{
  "type": "Feature",
  "properties": {
    "gn:admin1_code":"26.0",
    "gn:admin2_code":"4.0",
    "gn:asciiname":"La Ponderosa",
    "gn:country_code":"MX",
    "gn:dem":413,
    "gn:feature_class":"P",
    "gn:feature_code":"PPL",
    "gn:name":"La Ponderosa",
    "gn:population":0,
    "gn:timezone":"America/Hermosillo",
    "iso:country":"MX",
    "name:spa_x_preferred":[
        "La Ponderosa"
    ],
    "name:und_x_variant":[
        "Los Chacuales"
    ],
    "wof:name":"La Ponderosa",
    "wof:placetype":"locality"
},
  "geometry": {"coordinates":[-111.7612,30.60245],"type":"Point"}
}