{
  "type": "Feature",
  "properties": {
    "gn:admin1_code":"32",
    "gn:admin2_code":"36",
    "gn:asciiname":"Las Minas [Granja]",
    "gn:country_code":"MX",
    "gn:dem":2062,
    "gn:feature_class":"P",
    "gn:feature_code":"PPL",
    "gn:name":"Las Minas [Granja]",
    "gn:population":10,
    "gn:timezone":"America/Mexico_City",
    "iso:country":"MX",
    "wof:name":"Las Minas [Granja]",
    "wof:placetype":"locality",
    "wof:population":10
},
  "geometry": {"coordinates":[-102.23027999999999,22.53],"type":"Point"}
}