{
  "type": "Feature",
  "properties": {
    "gn:admin1_code":"6",
    "gn:admin2_code":"52.0",
    "gn:asciiname":"La Mula",
    "gn:country_code":"MX",
    "gn:dem":1023,
    "gn:feature_class":"P",
    "gn:feature_code":"PPL",
    "gn:name":"La Mula",
    "gn:population":0,
    "gn:timezone":"America/Ojinaga",
    "iso:country":"MX",
    "wof:name":"La Mula",
    "wof:placetype":"locality"
},
  "geometry": {"coordinates":[-104.43333,29.21667],"type":"Point"}
}