{
  "type": "Feature",
  "properties": {
    "gn:admin1_code":"26",
    "gn:admin2_code":"38.0",
    "gn:asciiname":"Tonibabi",
    "gn:country_code":"MX",
    "gn:dem":779,
    "gn:feature_class":"P",
    "gn:feature_code":"PPL",
    "gn:name":"Tonibabi",
    "gn:population":0,
    "gn:timezone":"America/Hermosillo",
    "iso:country":"MX",
    "name:spa_x_preferred":[
        "Tonibabi"
    ],
    "name:und_x_variant":[
        "Rancho Tombabi"
    ],
    "wof:name":"Tonibabi",
    "wof:placetype":"locality"
},
  "geometry": {"coordinates":[-109.5605,29.83627000000001],"type":"Point"}
}