{
  "type": "Feature",
  "properties": {
    "gn:admin1_code":"30",
    "gn:admin2_code":"121.0",
    "gn:asciiname":"El Plan",
    "gn:cc2":"MX",
    "gn:country_code":"MX",
    "gn:dem":75,
    "gn:feature_class":"P",
    "gn:feature_code":"PPL",
    "gn:name":"El Plan",
    "gn:population":5,
    "gn:timezone":"America/Mexico_City",
    "iso:country":"MX",
    "name:und_x_variant":[
        "Plan de Lucas",
        "El Plan"
    ],
    "wof:name":"El Plan",
    "wof:placetype":"locality",
    "wof:population":5
},
  "geometry": {"coordinates":[-97.92778,21.52361],"type":"Point"}
}