{
  "type": "Feature",
  "properties": {
    "gn:admin1_code":"11.0",
    "gn:admin2_code":"7.0",
    "gn:asciiname":"Primera Fraccion de Crespo",
    "gn:country_code":"MX",
    "gn:dem":1750,
    "gn:feature_class":"P",
    "gn:feature_code":"PPL",
    "gn:name":"Primera Fracci\u00f3n de Crespo",
    "gn:population":0,
    "gn:timezone":"America/Mexico_City",
    "iso:country":"MX",
    "name:spa_x_preferred":[
        "Primera Fracci\u00f3n de Crespo"
    ],
    "name:und_x_variant":[
        "Crespo"
    ],
    "wof:name":"Primera Fraccion de Crespo",
    "wof:placetype":"locality"
},
  "geometry": {"coordinates":[-100.8515,20.49638],"type":"Point"}
}