{
  "type": "Feature",
  "properties": {
    "gn:admin1_code":"5",
    "gn:admin2_code":"13.0",
    "gn:asciiname":"La Naranja",
    "gn:country_code":"MX",
    "gn:dem":1319,
    "gn:feature_class":"P",
    "gn:feature_code":"PPL",
    "gn:name":"La Naranja",
    "gn:population":401,
    "gn:timezone":"America/Mexico_City",
    "iso:country":"MX",
    "wof:name":"La Naranja",
    "wof:placetype":"locality",
    "wof:population":401
},
  "geometry": {"coordinates":[-92.87278000000001,16.96306],"type":"Point"}
}