{
  "type": "Feature",
  "properties": {
    "gn:admin1_code":"12.0",
    "gn:admin2_code":"68.0",
    "gn:asciiname":"El Cedral",
    "gn:country_code":"MX",
    "gn:dem":340,
    "gn:feature_class":"P",
    "gn:feature_code":"PPL",
    "gn:name":"El Cedral",
    "gn:population":0,
    "gn:timezone":"America/Mexico_City",
    "iso:country":"MX",
    "name:spa_x_preferred":[
        "El Cedral"
    ],
    "wof:name":"El Cedral",
    "wof:placetype":"locality"
},
  "geometry": {"coordinates":[-101.65724,17.96427000000001],"type":"Point"}
}