{
  "type": "Feature",
  "properties": {
    "gn:admin1_code":"20",
    "gn:admin2_code":"21.0",
    "gn:asciiname":"Miguel Hidalgo (Colonia Agricola)",
    "gn:country_code":"MX",
    "gn:dem":118,
    "gn:feature_class":"P",
    "gn:feature_code":"PPL",
    "gn:name":"Miguel Hidalgo (Colonia Agr\u00edcola)",
    "gn:population":135,
    "gn:timezone":"America/Mexico_City",
    "iso:country":"MX",
    "name:und_x_variant":[
        "Miguel Hidalgo (Colonia Agr\u00edcola)"
    ],
    "wof:name":"Miguel Hidalgo (Colonia Agricola)",
    "wof:placetype":"locality",
    "wof:population":135
},
  "geometry": {"coordinates":[-96.71639,18.52778],"type":"Point"}
}