{
  "type": "Feature",
  "properties": {
    "gn:admin1_code":"10",
    "gn:admin2_code":"7.0",
    "gn:asciiname":"San Angel",
    "gn:country_code":"MX",
    "gn:dem":1149,
    "gn:feature_class":"P",
    "gn:feature_code":"PPL",
    "gn:name":"San Angel",
    "gn:population":0,
    "gn:timezone":"America/Monterrey",
    "iso:country":"MX",
    "name:spa_x_preferred":[
        "San Angel"
    ],
    "wof:name":"San Angel",
    "wof:placetype":"locality"
},
  "geometry": {"coordinates":[-103.61870999999999,25.73977],"type":"Point"}
}