{
  "type": "Feature",
  "properties": {
    "gn:admin1_code":"25",
    "gn:admin2_code":"6",
    "gn:asciiname":"Campo Agricola Mac",
    "gn:country_code":"MX",
    "gn:dem":23,
    "gn:feature_class":"P",
    "gn:feature_code":"PPL",
    "gn:name":"Campo Agr\u00edcola Mac",
    "gn:population":13,
    "gn:timezone":"America/Mazatlan",
    "iso:country":"MX",
    "name:und_x_variant":[
        "Campo Agr\u00edcola Mac"
    ],
    "wof:name":"Campo Agricola Mac",
    "wof:placetype":"locality",
    "wof:population":13
},
  "geometry": {"coordinates":[-107.44167,24.64361],"type":"Point"}
}