{
  "type": "Feature",
  "properties": {
    "gn:admin1_code":"30.0",
    "gn:admin2_code":"144.0",
    "gn:asciiname":"Santa Apolonia",
    "gn:country_code":"MX",
    "gn:dem":116,
    "gn:feature_class":"P",
    "gn:feature_code":"PPL",
    "gn:name":"Santa Apolonia",
    "gn:population":0,
    "gn:timezone":"America/Mexico_City",
    "iso:country":"MX",
    "name:spa_x_preferred":[
        "Santa Apolonia"
    ],
    "wof:name":"Santa Apolonia",
    "wof:placetype":"locality"
},
  "geometry": {"coordinates":[-94.98584,17.82339],"type":"Point"}
}