{
  "type": "Feature",
  "properties": {
    "gn:admin1_code":"5.0",
    "gn:admin2_code":"20.0",
    "gn:asciiname":"El Bosque",
    "gn:country_code":"MX",
    "gn:dem":756,
    "gn:feature_class":"P",
    "gn:feature_code":"PPL",
    "gn:name":"El Bosque",
    "gn:population":0,
    "gn:timezone":"America/Mexico_City",
    "iso:country":"MX",
    "name:spa_x_preferred":[
        "El Bosque"
    ],
    "wof:name":"El Bosque",
    "wof:placetype":"locality"
},
  "geometry": {"coordinates":[-92.96899999999999,15.84399],"type":"Point"}
}