{
  "type": "Feature",
  "properties": {
    "gn:admin1_code":"21",
    "gn:admin2_code":"93.0",
    "gn:asciiname":"Gonzalez Ortega",
    "gn:country_code":"MX",
    "gn:dem":2847,
    "gn:feature_class":"P",
    "gn:feature_code":"PPL",
    "gn:name":"Gonz\u00e1lez Ortega",
    "gn:population":2041,
    "gn:timezone":"America/Mexico_City",
    "iso:country":"MX",
    "name:spa_x_preferred":[
        "Gonz\u00e1lez Ortega"
    ],
    "wof:name":"Gonzalez Ortega",
    "wof:placetype":"locality",
    "wof:population":2041
},
  "geometry": {"coordinates":[-97.27023,19.34268],"type":"Point"}
}