{
  "type": "Feature",
  "properties": {
    "gn:admin1_code":"21",
    "gn:admin2_code":"208.0",
    "gn:asciiname":"Tepexco",
    "gn:country_code":"MX",
    "gn:dem":1927,
    "gn:feature_class":"P",
    "gn:feature_code":"PPL",
    "gn:name":"Tepexco",
    "gn:population":0,
    "gn:timezone":"America/Mexico_City",
    "iso:country":"MX",
    "name:ceb_x_preferred":[
        "Tepexco"
    ],
    "name:epo_x_preferred":[
        "Tepexco"
    ],
    "name:eus_x_preferred":[
        "Tepexco"
    ],
    "name:spa_x_preferred":[
        "Tepexco"
    ],
    "name:srp_x_preferred":[
        "\u041e\u043f\u0448\u0442\u0438\u043d\u0430 \u0422\u0435\u043f\u0435\u0441\u043a\u043e"
    ],
    "name:swe_x_preferred":[
        "Tepexco"
    ],
    "name:und_x_variant":[
        "Tepeixco"
    ],
    "name:vie_x_preferred":[
        "Tepexco"
    ],
    "wof:name":"Tepexco",
    "wof:placetype":"locality"
},
  "geometry": {"coordinates":[-97.95808,20.02906],"type":"Point"}
}