{
  "type": "Feature",
  "properties": {
    "gn:admin1_code":"6.0",
    "gn:admin2_code":"29.0",
    "gn:asciiname":"El Granizo",
    "gn:country_code":"MX",
    "gn:dem":2285,
    "gn:feature_class":"P",
    "gn:feature_code":"PPL",
    "gn:name":"El Granizo",
    "gn:population":210,
    "gn:timezone":"America/Chihuahua",
    "iso:country":"MX",
    "name:und_x_variant":[
        "Granizo",
        "El Granizo"
    ],
    "wof:name":"El Granizo",
    "wof:placetype":"locality",
    "wof:population":210
},
  "geometry": {"coordinates":[-106.60487999999999,25.88207],"type":"Point"}
}