{
  "type": "Feature",
  "properties": {
    "gn:admin1_code":"6",
    "gn:admin2_code":"35",
    "gn:asciiname":"Campo Uno y Medio (Colonia Buenos Aires)",
    "gn:country_code":"MX",
    "gn:dem":1462,
    "gn:feature_class":"P",
    "gn:feature_code":"PPL",
    "gn:name":"Campo Uno y Medio (Colonia Buenos Aires)",
    "gn:population":10,
    "gn:timezone":"America/Chihuahua",
    "iso:country":"MX",
    "wof:name":"Campo Uno y Medio (Colonia Buenos Aires)",
    "wof:placetype":"locality",
    "wof:population":10
},
  "geometry": {"coordinates":[-108.37304,30.74231],"type":"Point"}
}