{
  "type": "Feature",
  "properties": {
    "gn:admin1_code":"5",
    "gn:admin2_code":"119.0",
    "gn:asciiname":"Nachon",
    "gn:country_code":"MX",
    "gn:dem":1683,
    "gn:feature_class":"P",
    "gn:feature_code":"PPL",
    "gn:name":"Nach\u00f3n",
    "gn:population":206,
    "gn:timezone":"America/Mexico_City",
    "iso:country":"MX",
    "name:und_x_variant":[
        "Nach\u00f3n"
    ],
    "wof:name":"Nachon",
    "wof:placetype":"locality",
    "wof:population":206
},
  "geometry": {"coordinates":[-92.71874,16.94191],"type":"Point"}
}