{
  "type": "Feature",
  "properties": {
    "gn:admin1_code":"15.0",
    "gn:admin2_code":"124.0",
    "gn:asciiname":"El Valerio",
    "gn:country_code":"MX",
    "gn:dem":2696,
    "gn:feature_class":"P",
    "gn:feature_code":"PPL",
    "gn:name":"El Valerio",
    "gn:population":0,
    "gn:timezone":"America/Mexico_City",
    "iso:country":"MX",
    "name:spa_x_preferred":[
        "El Valerio"
    ],
    "name:und_x_variant":[
        "Valerio"
    ],
    "wof:name":"El Valerio",
    "wof:placetype":"locality"
},
  "geometry": {"coordinates":[-100.09909,19.65178],"type":"Point"}
}