{
  "type": "Feature",
  "properties": {
    "gn:admin1_code":"5",
    "gn:admin2_code":"89.0",
    "gn:asciiname":"Acaxman",
    "gn:country_code":"MX",
    "gn:dem":58,
    "gn:feature_class":"P",
    "gn:feature_code":"PPL",
    "gn:name":"Acaxm\u00e1n",
    "gn:population":0,
    "gn:timezone":"America/Mexico_City",
    "iso:country":"MX",
    "name:spa_x_preferred":[
        "Acaxm\u00e1n"
    ],
    "wof:name":"Acaxman",
    "wof:placetype":"locality"
},
  "geometry": {"coordinates":[-92.32073,14.82904],"type":"Point"}
}