{
  "type": "Feature",
  "properties": {
    "gn:admin1_code":"23.0",
    "gn:admin2_code":"4.0",
    "gn:asciiname":"El Capricho",
    "gn:country_code":"MX",
    "gn:dem":5,
    "gn:feature_class":"P",
    "gn:feature_code":"PPL",
    "gn:name":"El Capricho",
    "gn:population":0,
    "gn:timezone":"America/Cancun",
    "iso:country":"MX",
    "name:spa_x_preferred":[
        "El Capricho"
    ],
    "wof:name":"El Capricho",
    "wof:placetype":"locality"
},
  "geometry": {"coordinates":[-87.64129,18.86947],"type":"Point"}
}