{
  "type": "Feature",
  "properties": {
    "gn:admin1_code":"10",
    "gn:admin2_code":"32",
    "gn:asciiname":"El Alazan",
    "gn:country_code":"MX",
    "gn:dem":2622,
    "gn:feature_class":"P",
    "gn:feature_code":"PPL",
    "gn:name":"El Alaz\u00e1n",
    "gn:population":19,
    "gn:timezone":"America/Monterrey",
    "iso:country":"MX",
    "name:und_x_variant":[
        "El Alaz\u00e1n"
    ],
    "wof:name":"El Alazan",
    "wof:placetype":"locality",
    "wof:population":19
},
  "geometry": {"coordinates":[-106.11888,25.05345],"type":"Point"}
}