{
  "type": "Feature",
  "properties": {
    "gn:admin1_code":"23.0",
    "gn:asciiname":"Sand Wood Villas",
    "gn:country_code":"MX",
    "gn:dem":3,
    "gn:feature_class":"P",
    "gn:feature_code":"PPL",
    "gn:name":"Sand Wood Villas",
    "gn:population":0,
    "gn:timezone":"America/Cancun",
    "iso:country":"MX",
    "name:spa_x_preferred":[
        "Sand Wood Villas"
    ],
    "wof:name":"Sand Wood Villas",
    "wof:placetype":"locality"
},
  "geometry": {"coordinates":[-87.81208000000002,18.3421],"type":"Point"}
}