{
  "type": "Feature",
  "properties": {
    "gn:admin1_code":"6",
    "gn:admin2_code":"65.0",
    "gn:asciiname":"El Modrono",
    "gn:country_code":"MX",
    "gn:dem":2247,
    "gn:feature_class":"P",
    "gn:feature_code":"PPL",
    "gn:name":"El Modro\u00f1o",
    "gn:population":0,
    "gn:timezone":"America/Chihuahua",
    "iso:country":"MX",
    "name:spa_x_preferred":[
        "El Modro\u00f1o"
    ],
    "wof:name":"El Modrono",
    "wof:placetype":"locality"
},
  "geometry": {"coordinates":[-107.84157,27.51459],"type":"Point"}
}