{
  "type": "Feature",
  "properties": {
    "gn:admin1_code":"5",
    "gn:admin2_code":"32.0",
    "gn:asciiname":"Vega de Juarez",
    "gn:country_code":"MX",
    "gn:dem":849,
    "gn:feature_class":"P",
    "gn:feature_code":"PPL",
    "gn:name":"Vega de Ju\u00e1rez",
    "gn:population":102,
    "gn:timezone":"America/Mexico_City",
    "iso:country":"MX",
    "name:und_x_variant":[
        "Vega de Ju\u00e1rez"
    ],
    "wof:name":"Vega de Juarez",
    "wof:placetype":"locality",
    "wof:population":102
},
  "geometry": {"coordinates":[-92.48889,15.38389],"type":"Point"}
}