{
  "type": "Feature",
  "properties": {
    "gn:admin1_code":"10.0",
    "gn:admin2_code":"26.0",
    "gn:asciiname":"La Flor",
    "gn:country_code":"MX",
    "gn:dem":2660,
    "gn:feature_class":"P",
    "gn:feature_code":"PPL",
    "gn:name":"La Flor",
    "gn:population":0,
    "gn:timezone":"America/Monterrey",
    "iso:country":"MX",
    "name:fra_x_preferred":[
        "La flor"
    ],
    "name:spa_x_preferred":[
        "La Flor"
    ],
    "wof:name":"La Flor",
    "wof:placetype":"locality"
},
  "geometry": {"coordinates":[-105.76752,24.26924],"type":"Point"}
}