{
  "type": "Feature",
  "properties": {
    "gn:admin1_code":"26",
    "gn:admin2_code":"61.0",
    "gn:asciiname":"Tinaja",
    "gn:country_code":"MX",
    "gn:dem":198,
    "gn:feature_class":"P",
    "gn:feature_code":"PPL",
    "gn:name":"Tinaja",
    "gn:population":0,
    "gn:timezone":"America/Hermosillo",
    "iso:country":"MX",
    "wof:name":"Tinaja",
    "wof:placetype":"locality"
},
  "geometry": {"coordinates":[-109.56667,28.56667],"type":"Point"}
}