{
  "type": "Feature",
  "properties": {
    "gn:admin1_code":"10.0",
    "gn:asciiname":"La Tarumala",
    "gn:country_code":"MX",
    "gn:dem":1704,
    "gn:feature_class":"P",
    "gn:feature_code":"PPL",
    "gn:name":"La Tarumala",
    "gn:population":0,
    "gn:timezone":"America/Monterrey",
    "iso:country":"MX",
    "name:spa_x_preferred":[
        "La Tarumala"
    ],
    "wof:name":"La Tarumala",
    "wof:placetype":"locality"
},
  "geometry": {"coordinates":[-103.31826,24.56071],"type":"Point"}
}