{
  "type": "Feature",
  "properties": {
    "gn:admin1_code":"25",
    "gn:admin2_code":"6",
    "gn:asciiname":"Campo la Guadalupana",
    "gn:country_code":"MX",
    "gn:dem":22,
    "gn:feature_class":"P",
    "gn:feature_code":"PPL",
    "gn:name":"Campo la Guadalupana",
    "gn:population":31,
    "gn:timezone":"America/Mazatlan",
    "iso:country":"MX",
    "wof:name":"Campo la Guadalupana",
    "wof:placetype":"locality",
    "wof:population":31
},
  "geometry": {"coordinates":[-107.16058999999998,24.23705],"type":"Point"}
}