{
  "type": "Feature",
  "properties": {
    "gn:admin1_code":"6.0",
    "gn:admin2_code":"41.0",
    "gn:asciiname":"La Mesa",
    "gn:country_code":"MX",
    "gn:dem":1782,
    "gn:feature_class":"P",
    "gn:feature_code":"PPL",
    "gn:name":"La Mesa",
    "gn:population":0,
    "gn:timezone":"America/Chihuahua",
    "iso:country":"MX",
    "name:spa_x_preferred":[
        "La Mesa"
    ],
    "wof:name":"La Mesa",
    "wof:placetype":"locality"
},
  "geometry": {"coordinates":[-108.00586,27.85586],"type":"Point"}
}