{
  "type": "Feature",
  "properties": {
    "gn:admin1_code":"6.0",
    "gn:admin2_code":"16.0",
    "gn:asciiname":"El Maton",
    "gn:country_code":"MX",
    "gn:dem":1326,
    "gn:feature_class":"P",
    "gn:feature_code":"PPL",
    "gn:name":"El Mat\u00f3n",
    "gn:population":0,
    "gn:timezone":"America/Chihuahua",
    "iso:country":"MX",
    "name:spa_x_preferred":[
        "El Mat\u00f3n"
    ],
    "wof:name":"El Maton",
    "wof:placetype":"locality"
},
  "geometry": {"coordinates":[-105.09823,27.85438],"type":"Point"}
}