{
  "type": "Feature",
  "properties": {
    "gn:admin1_code":"13",
    "gn:admin2_code":"71.0",
    "gn:asciiname":"La Ciruela",
    "gn:country_code":"MX",
    "gn:dem":519,
    "gn:feature_class":"P",
    "gn:feature_code":"PPL",
    "gn:name":"La Ciruela",
    "gn:population":7,
    "gn:timezone":"America/Mexico_City",
    "iso:country":"MX",
    "wof:name":"La Ciruela",
    "wof:placetype":"locality",
    "wof:population":7
},
  "geometry": {"coordinates":[-98.98833,20.99139],"type":"Point"}
}