{
  "type": "Feature",
  "properties": {
    "gn:admin1_code":"30",
    "gn:admin2_code":"77.0",
    "gn:asciiname":"Octavio Gonzalez",
    "gn:country_code":"MX",
    "gn:dem":26,
    "gn:feature_class":"P",
    "gn:feature_code":"PPL",
    "gn:name":"Octavio Gonz\u00e1lez",
    "gn:population":6,
    "gn:timezone":"America/Mexico_City",
    "iso:country":"MX",
    "name:und_x_variant":[
        "Octavio Gonz\u00e1lez"
    ],
    "wof:name":"Octavio Gonzalez",
    "wof:placetype":"locality",
    "wof:population":6
},
  "geometry": {"coordinates":[-95.485,18.20389],"type":"Point"}
}