{
  "type": "Feature",
  "properties": {
    "gn:admin1_code":"6.0",
    "gn:admin2_code":"5.0",
    "gn:asciiname":"Los Juncos",
    "gn:country_code":"MX",
    "gn:dem":1257,
    "gn:feature_class":"P",
    "gn:feature_code":"PPL",
    "gn:name":"Los Juncos",
    "gn:population":0,
    "gn:timezone":"America/Chihuahua",
    "iso:country":"MX",
    "name:spa_x_preferred":[
        "Los Juncos"
    ],
    "wof:name":"Los Juncos",
    "wof:placetype":"locality"
},
  "geometry": {"coordinates":[-107.41983999999999,30.85321],"type":"Point"}
}