{
  "type": "Feature",
  "properties": {
    "gn:admin1_code":"20",
    "gn:admin2_code":"72.0",
    "gn:asciiname":"El Porvenir",
    "gn:country_code":"MX",
    "gn:dem":1623,
    "gn:feature_class":"P",
    "gn:feature_code":"PPL",
    "gn:name":"El Porvenir",
    "gn:population":489,
    "gn:timezone":"America/Mexico_City",
    "iso:country":"MX",
    "wof:name":"El Porvenir",
    "wof:placetype":"locality",
    "wof:population":489
},
  "geometry": {"coordinates":[-96.64556,16.70222],"type":"Point"}
}