{
  "type": "Feature",
  "properties": {
    "gn:admin1_code":"26.0",
    "gn:asciiname":"La Mezcalera",
    "gn:country_code":"MX",
    "gn:dem":475,
    "gn:feature_class":"P",
    "gn:feature_code":"PPL",
    "gn:name":"La Mezcalera",
    "gn:population":0,
    "gn:timezone":"America/Hermosillo",
    "iso:country":"MX",
    "name:spa_x_preferred":[
        "La Mezcalera"
    ],
    "wof:name":"La Mezcalera",
    "wof:placetype":"locality"
},
  "geometry": {"coordinates":[-109.24635000000001,27.81486],"type":"Point"}
}