{
  "type": "Feature",
  "properties": {
    "gn:admin1_code":"14",
    "gn:admin2_code":"68.0",
    "gn:asciiname":"Pabelo",
    "gn:country_code":"MX",
    "gn:dem":662,
    "gn:feature_class":"P",
    "gn:feature_code":"PPL",
    "gn:name":"Pabelo",
    "gn:population":0,
    "gn:timezone":"America/Mexico_City",
    "iso:country":"MX",
    "name:spa_x_preferred":[
        "Pabelo"
    ],
    "wof:name":"Pabelo",
    "wof:placetype":"locality"
},
  "geometry": {"coordinates":[-104.63500999999999,19.88056],"type":"Point"}
}