{
  "type": "Feature",
  "properties": {
    "gn:admin1_code":"30",
    "gn:admin2_code":"171.0",
    "gn:asciiname":"Apoxteca",
    "gn:country_code":"MX",
    "gn:dem":1453,
    "gn:feature_class":"P",
    "gn:feature_code":"PPL",
    "gn:name":"Apoxteca",
    "gn:population":135,
    "gn:timezone":"America/Mexico_City",
    "iso:country":"MX",
    "wof:name":"Apoxteca",
    "wof:placetype":"locality",
    "wof:population":135
},
  "geometry": {"coordinates":[-97.01111,18.61639],"type":"Point"}
}