{
  "type": "Feature",
  "properties": {
    "gn:admin1_code":"12",
    "gn:admin2_code":"12.0",
    "gn:asciiname":"Barranca Tecoani",
    "gn:country_code":"MX",
    "gn:dem":1077,
    "gn:feature_class":"P",
    "gn:feature_code":"PPL",
    "gn:name":"Barranca Tecoani",
    "gn:population":341,
    "gn:timezone":"America/Mexico_City",
    "iso:country":"MX",
    "wof:name":"Barranca Tecoani",
    "wof:placetype":"locality",
    "wof:population":341
},
  "geometry": {"coordinates":[-98.98479,17.04147],"type":"Point"}
}