{
  "type": "Feature",
  "properties": {
    "gn:admin1_code":"15",
    "gn:admin2_code":"113.0",
    "gn:asciiname":"Totolmajac",
    "gn:country_code":"MX",
    "gn:dem":2043,
    "gn:feature_class":"P",
    "gn:feature_code":"PPL",
    "gn:name":"Totolmajac",
    "gn:population":0,
    "gn:timezone":"America/Mexico_City",
    "iso:country":"MX",
    "name:spa_x_preferred":[
        "Totolmajac"
    ],
    "wof:name":"Totolmajac",
    "wof:placetype":"locality"
},
  "geometry": {"coordinates":[-99.68593,18.92694],"type":"Point"}
}