{
  "type": "Feature",
  "properties": {
    "gn:admin1_code":"28.0",
    "gn:admin2_code":"12.0",
    "gn:asciiname":"El Bernal",
    "gn:country_code":"MX",
    "gn:dem":57,
    "gn:feature_class":"P",
    "gn:feature_code":"PPL",
    "gn:name":"El Bernal",
    "gn:population":0,
    "gn:timezone":"America/Monterrey",
    "iso:country":"MX",
    "name:spa_x_preferred":[
        "El Bernal"
    ],
    "wof:name":"El Bernal",
    "wof:placetype":"locality"
},
  "geometry": {"coordinates":[-98.53636,22.77055],"type":"Point"}
}