{
  "type": "Feature",
  "properties": {
    "gn:admin1_code":"16",
    "gn:admin2_code":"9.0",
    "gn:asciiname":"El Cipres",
    "gn:country_code":"MX",
    "gn:dem":2100,
    "gn:feature_class":"P",
    "gn:feature_code":"PPL",
    "gn:name":"El Cipr\u00e9s",
    "gn:population":58,
    "gn:timezone":"America/Mexico_City",
    "iso:country":"MX",
    "name:und_x_variant":[
        "El Cipr\u00e9s"
    ],
    "wof:name":"El Cipres",
    "wof:placetype":"locality",
    "wof:population":58
},
  "geometry": {"coordinates":[-101.65416999999999,19.15389],"type":"Point"}
}