{
  "type": "Feature",
  "properties": {
    "gn:admin1_code":"14.0",
    "gn:asciiname":"La Estanzuela",
    "gn:country_code":"MX",
    "gn:dem":1858,
    "gn:feature_class":"P",
    "gn:feature_code":"PPL",
    "gn:name":"La Estanzuela",
    "gn:population":0,
    "gn:timezone":"America/Mexico_City",
    "iso:country":"MX",
    "name:spa_x_preferred":[
        "La Estanzuela"
    ],
    "wof:name":"La Estanzuela",
    "wof:placetype":"locality"
},
  "geometry": {"coordinates":[-102.32691,21.12804],"type":"Point"}
}