{
  "type": "Feature",
  "properties": {
    "gn:admin1_code":"14",
    "gn:admin2_code":"124",
    "gn:asciiname":"Villa de Guadalupe",
    "gn:country_code":"MX",
    "gn:dem":1536,
    "gn:feature_class":"P",
    "gn:feature_code":"PPL",
    "gn:name":"Villa de Guadalupe",
    "gn:population":16,
    "gn:timezone":"America/Mexico_City",
    "iso:country":"MX",
    "wof:name":"Villa de Guadalupe",
    "wof:placetype":"locality",
    "wof:population":16
},
  "geometry": {"coordinates":[-103.075,20.67222000000001],"type":"Point"}
}