{
  "type": "Feature",
  "properties": {
    "gn:admin1_code":"7.0",
    "gn:admin2_code":"37.0",
    "gn:asciiname":"Ejido La Luz",
    "gn:country_code":"MX",
    "gn:dem":411,
    "gn:feature_class":"P",
    "gn:feature_code":"PPL",
    "gn:name":"Ejido La Luz",
    "gn:population":0,
    "gn:timezone":"America/Monterrey",
    "iso:country":"MX",
    "wof:name":"Ejido La Luz",
    "wof:placetype":"locality"
},
  "geometry": {"coordinates":[-100.73333,28.15],"type":"Point"}
}