{
  "type": "Feature",
  "properties": {
    "gn:admin1_code":"16",
    "gn:admin2_code":"50.0",
    "gn:asciiname":"San Nicolasito",
    "gn:country_code":"MX",
    "gn:dem":2048,
    "gn:feature_class":"P",
    "gn:feature_code":"PPL",
    "gn:name":"San Nicolasito",
    "gn:population":440,
    "gn:timezone":"America/Mexico_City",
    "iso:country":"MX",
    "wof:name":"San Nicolasito",
    "wof:placetype":"locality",
    "wof:population":440
},
  "geometry": {"coordinates":[-100.375,19.92417],"type":"Point"}
}