{
  "type": "Feature",
  "properties": {
    "gn:admin1_code":"5.0",
    "gn:admin2_code":"99.0",
    "gn:asciiname":"Libertad Primero de Enero",
    "gn:country_code":"MX",
    "gn:dem":546,
    "gn:feature_class":"P",
    "gn:feature_code":"PPL",
    "gn:name":"Libertad Primero de Enero",
    "gn:population":0,
    "gn:timezone":"America/Mexico_City",
    "iso:country":"MX",
    "name:spa_x_preferred":[
        "Libertad Primero de Enero"
    ],
    "wof:name":"Libertad Primero de Enero",
    "wof:placetype":"locality"
},
  "geometry": {"coordinates":[-92.12629,15.92867],"type":"Point"}
}