{
  "type": "Feature",
  "properties": {
    "gn:admin1_code":"24",
    "gn:admin2_code":"32.0",
    "gn:asciiname":"La Cuesta",
    "gn:country_code":"MX",
    "gn:dem":2013,
    "gn:feature_class":"P",
    "gn:feature_code":"PPL",
    "gn:name":"La Cuesta",
    "gn:population":0,
    "gn:timezone":"America/Mexico_City",
    "iso:country":"MX",
    "wof:name":"La Cuesta",
    "wof:placetype":"locality"
},
  "geometry": {"coordinates":[-100.64749999999999,21.90889],"type":"Point"}
}