{
  "type": "Feature",
  "properties": {
    "gn:admin1_code":"22",
    "gn:admin2_code":"9.0",
    "gn:asciiname":"Lagunitas",
    "gn:country_code":"MX",
    "gn:dem":1095,
    "gn:feature_class":"P",
    "gn:feature_code":"PPL",
    "gn:name":"Lagunitas",
    "gn:population":0,
    "gn:timezone":"America/Mexico_City",
    "iso:country":"MX",
    "name:ceb_x_preferred":[
        "Lagunitas"
    ],
    "name:deu_x_preferred":[
        "Lagunitas"
    ],
    "name:fra_x_preferred":[
        "Lagunitas"
    ],
    "name:spa_x_preferred":[
        "Lagunitas"
    ],
    "name:srp_x_preferred":[
        "\u041b\u0430\u0433\u0443\u043d\u0438\u0442\u0430\u0441"
    ],
    "name:swe_x_preferred":[
        "Lagunitas"
    ],
    "wof:name":"Lagunitas",
    "wof:placetype":"locality"
},
  "geometry": {"coordinates":[-99.25747,21.47225],"type":"Point"}
}