{
  "type": "Feature",
  "properties": {
    "gn:admin1_code":"25.0",
    "gn:admin2_code":"13.0",
    "gn:asciiname":"Boca de Arroyo",
    "gn:country_code":"MX",
    "gn:dem":70,
    "gn:feature_class":"P",
    "gn:feature_code":"PPL",
    "gn:name":"Boca de Arroyo",
    "gn:population":189,
    "gn:timezone":"America/Mazatlan",
    "iso:country":"MX",
    "wof:name":"Boca de Arroyo",
    "wof:placetype":"locality",
    "wof:population":189
},
  "geometry": {"coordinates":[-107.97169,25.46368],"type":"Point"}
}