{
  "type": "Feature",
  "properties": {
    "gn:admin1_code":"16.0",
    "gn:admin2_code":"95.0",
    "gn:asciiname":"La Calera",
    "gn:cc2":"MX",
    "gn:country_code":"MX",
    "gn:dem":1320,
    "gn:feature_class":"P",
    "gn:feature_code":"PPL",
    "gn:name":"La Calera",
    "gn:population":77,
    "gn:timezone":"America/Mexico_City",
    "iso:country":"MX",
    "name:und_x_variant":[
        "Calera",
        "La Calera"
    ],
    "wof:name":"La Calera",
    "wof:placetype":"locality",
    "wof:population":77
},
  "geometry": {"coordinates":[-102.51194,19.63861],"type":"Point"}
}