{
  "type": "Feature",
  "properties": {
    "gn:admin1_code":"19",
    "gn:admin2_code":"20.0",
    "gn:asciiname":"Mojarras",
    "gn:country_code":"MX",
    "gn:dem":117,
    "gn:feature_class":"P",
    "gn:feature_code":"PPL",
    "gn:name":"Mojarras",
    "gn:population":0,
    "gn:timezone":"America/Monterrey",
    "iso:country":"MX",
    "name:und_x_variant":[
        "Rancho Mojarras",
        "Mojarras"
    ],
    "wof:name":"Mojarras",
    "wof:placetype":"locality"
},
  "geometry": {"coordinates":[-98.93443000000001,25.86138],"type":"Point"}
}