{
  "type": "Feature",
  "properties": {
    "gn:admin1_code":"4",
    "gn:admin2_code":"9",
    "gn:asciiname":"El Gallo Samuel (El Gallito)",
    "gn:country_code":"MX",
    "gn:dem":55,
    "gn:feature_class":"P",
    "gn:feature_code":"PPL",
    "gn:name":"El Gallo Samuel (El Gallito)",
    "gn:population":14,
    "gn:timezone":"America/Merida",
    "iso:country":"MX",
    "wof:name":"El Gallo Samuel (El Gallito)",
    "wof:placetype":"locality",
    "wof:population":14
},
  "geometry": {"coordinates":[-90.73721999999999,18.41611],"type":"Point"}
}