{
  "type": "Feature",
  "properties": {
    "gn:admin1_code":"24.0",
    "gn:admin2_code":"16.0",
    "gn:asciiname":"Los Conejos",
    "gn:country_code":"MX",
    "gn:dem":42,
    "gn:feature_class":"P",
    "gn:feature_code":"PPL",
    "gn:name":"Los Conejos",
    "gn:population":0,
    "gn:timezone":"America/Mexico_City",
    "iso:country":"MX",
    "name:spa_x_preferred":[
        "Los Conejos"
    ],
    "wof:name":"Los Conejos",
    "wof:placetype":"locality"
},
  "geometry": {"coordinates":[-98.43492999999999,22.2267],"type":"Point"}
}