{
  "type": "Feature",
  "properties": {
    "gn:admin1_code":"2.0",
    "gn:admin2_code":"2.0",
    "gn:asciiname":"Colonia Estacion Dieguinos",
    "gn:country_code":"MX",
    "gn:dem":33,
    "gn:feature_class":"P",
    "gn:feature_code":"PPL",
    "gn:name":"Colonia Estaci\u00f3n Dieguinos",
    "gn:population":0,
    "gn:timezone":"America/Tijuana",
    "iso:country":"MX",
    "name:spa_x_preferred":[
        "Colonia Estaci\u00f3n Dieguinos"
    ],
    "name:und_x_variant":[
        "Dieguinos"
    ],
    "wof:name":"Colonia Estacion Dieguinos",
    "wof:placetype":"locality"
},
  "geometry": {"coordinates":[-114.79053,32.65170999999999],"type":"Point"}
}