{
  "type": "Feature",
  "properties": {
    "gn:admin1_code":"7",
    "gn:admin2_code":"12.0",
    "gn:asciiname":"Rancho La Burra",
    "gn:country_code":"MX",
    "gn:dem":220,
    "gn:feature_class":"P",
    "gn:feature_code":"PPL",
    "gn:name":"Rancho La Burra",
    "gn:population":0,
    "gn:timezone":"America/Monterrey",
    "iso:country":"MX",
    "wof:name":"Rancho La Burra",
    "wof:placetype":"locality"
},
  "geometry": {"coordinates":[-100.15000000000001,28.05],"type":"Point"}
}