{
  "type": "Feature",
  "properties": {
    "gn:admin1_code":"5",
    "gn:admin2_code":"108",
    "gn:asciiname":"San Joseito",
    "gn:country_code":"MX",
    "gn:dem":592,
    "gn:feature_class":"P",
    "gn:feature_code":"PPL",
    "gn:name":"San Joseito",
    "gn:population":25,
    "gn:timezone":"America/Mexico_City",
    "iso:country":"MX",
    "wof:name":"San Joseito",
    "wof:placetype":"locality",
    "wof:population":25
},
  "geometry": {"coordinates":[-93.26889,16.285],"type":"Point"}
}