{
  "type": "Feature",
  "properties": {
    "gn:admin1_code":"5",
    "gn:admin2_code":"92",
    "gn:asciiname":"Mazatlan de la Selva",
    "gn:country_code":"MX",
    "gn:dem":271,
    "gn:feature_class":"P",
    "gn:feature_code":"PPL",
    "gn:name":"Mazatl\u00e1n de la Selva",
    "gn:population":12,
    "gn:timezone":"America/Mexico_City",
    "iso:country":"MX",
    "name:und_x_variant":[
        "Mazatl\u00e1n de la Selva"
    ],
    "wof:name":"Mazatlan de la Selva",
    "wof:placetype":"locality",
    "wof:population":12
},
  "geometry": {"coordinates":[-93.755,17.10778],"type":"Point"}
}