{
  "type": "Feature",
  "properties": {
    "gn:admin1_code":"26",
    "gn:admin2_code":"69.0",
    "gn:asciiname":"Cebadillitas",
    "gn:country_code":"MX",
    "gn:dem":1654,
    "gn:feature_class":"P",
    "gn:feature_code":"PPL",
    "gn:name":"Cebadillitas",
    "gn:population":0,
    "gn:timezone":"America/Hermosillo",
    "iso:country":"MX",
    "name:spa_x_preferred":[
        "Cebadillitas"
    ],
    "wof:name":"Cebadillitas",
    "wof:placetype":"locality"
},
  "geometry": {"coordinates":[-108.98718999999998,28.467],"type":"Point"}
}