{
  "type": "Feature",
  "properties": {
    "gn:admin1_code":"11",
    "gn:admin2_code":"1.0",
    "gn:asciiname":"Emiliano Zapata (La Colonia)",
    "gn:country_code":"MX",
    "gn:dem":1736,
    "gn:feature_class":"P",
    "gn:feature_code":"PPL",
    "gn:name":"Emiliano Zapata (La Colonia)",
    "gn:population":363,
    "gn:timezone":"America/Mexico_City",
    "iso:country":"MX",
    "wof:name":"Emiliano Zapata (La Colonia)",
    "wof:placetype":"locality",
    "wof:population":363
},
  "geometry": {"coordinates":[-101.55249999999999,20.41806],"type":"Point"}
}