{
  "type": "Feature",
  "properties": {
    "gn:admin1_code":"20",
    "gn:admin2_code":"12.0",
    "gn:asciiname":"El Caulote",
    "gn:country_code":"MX",
    "gn:dem":140,
    "gn:feature_class":"P",
    "gn:feature_code":"PPL",
    "gn:name":"El Caulote",
    "gn:population":245,
    "gn:timezone":"America/Mexico_City",
    "iso:country":"MX",
    "wof:name":"El Caulote",
    "wof:placetype":"locality",
    "wof:population":245
},
  "geometry": {"coordinates":[-96.55638999999999,15.80889],"type":"Point"}
}