{
  "type": "Feature",
  "properties": {
    "gn:admin1_code":"5",
    "gn:admin2_code":"115.0",
    "gn:asciiname":"Nuevo San Andres la Paz",
    "gn:country_code":"MX",
    "gn:dem":190,
    "gn:feature_class":"P",
    "gn:feature_code":"PPL",
    "gn:name":"Nuevo San Andr\u00e9s la Paz",
    "gn:population":0,
    "gn:timezone":"America/Mexico_City",
    "iso:country":"MX",
    "name:spa_x_preferred":[
        "Nuevo San Andr\u00e9s de la Paz"
    ],
    "name:spa_x_variant":[
        "Nuevo San Andr\u00e9s",
        "Nuevo San Andr\u00e9s la Paz"
    ],
    "wof:name":"Nuevo San Andres la Paz",
    "wof:placetype":"locality"
},
  "geometry": {"coordinates":[-91.15582999999999,16.14397],"type":"Point"}
}