{
  "type": "Feature",
  "properties": {
    "gn:admin1_code":"17",
    "gn:admin2_code":"9",
    "gn:asciiname":"Saint Moritz",
    "gn:country_code":"MX",
    "gn:dem":2615,
    "gn:feature_class":"P",
    "gn:feature_code":"PPL",
    "gn:name":"Saint Moritz",
    "gn:population":38,
    "gn:timezone":"America/Mexico_City",
    "iso:country":"MX",
    "wof:name":"Saint Moritz",
    "wof:placetype":"locality",
    "wof:population":38
},
  "geometry": {"coordinates":[-99.22314,19.02764],"type":"Point"}
}