{
  "type": "Feature",
  "properties": {
    "gn:admin1_code":"9",
    "gn:admin2_code":"9",
    "gn:asciiname":"Prolongacion Justo Sierra",
    "gn:country_code":"MX",
    "gn:dem":2501,
    "gn:feature_class":"P",
    "gn:feature_code":"PPL",
    "gn:name":"Prolongaci\u00f3n Justo Sierra",
    "gn:population":24,
    "gn:timezone":"America/Mexico_City",
    "iso:country":"MX",
    "name:und_x_variant":[
        "Prolongaci\u00f3n Justo Sierra"
    ],
    "wof:name":"Prolongacion Justo Sierra",
    "wof:placetype":"locality",
    "wof:population":24
},
  "geometry": {"coordinates":[-99.06305999999999,19.20056],"type":"Point"}
}