{
  "type": "Feature",
  "properties": {
    "gn:admin1_code":"7.0",
    "gn:admin2_code":"23.0",
    "gn:asciiname":"El Chale",
    "gn:country_code":"MX",
    "gn:dem":1279,
    "gn:feature_class":"P",
    "gn:feature_code":"PPL",
    "gn:name":"El Chale",
    "gn:population":0,
    "gn:timezone":"America/Monterrey",
    "iso:country":"MX",
    "name:spa_x_preferred":[
        "El Chale"
    ],
    "wof:name":"El Chale",
    "wof:placetype":"locality"
},
  "geometry": {"coordinates":[-102.31849,27.60585],"type":"Point"}
}