{
  "type": "Feature",
  "properties": {
    "gn:admin1_code":"26",
    "gn:admin2_code":"14.0",
    "gn:asciiname":"Las Moras",
    "gn:country_code":"MX",
    "gn:dem":672,
    "gn:feature_class":"P",
    "gn:feature_code":"PPL",
    "gn:name":"Las Moras",
    "gn:population":0,
    "gn:timezone":"America/Hermosillo",
    "iso:country":"MX",
    "name:spa_x_preferred":[
        "Las Moras"
    ],
    "wof:name":"Las Moras",
    "wof:placetype":"locality"
},
  "geometry": {"coordinates":[-110.20323999999999,29.61946],"type":"Point"}
}