{
  "type": "Feature",
  "properties": {
    "gn:admin1_code":"6",
    "gn:admin2_code":"40.0",
    "gn:asciiname":"El Alto de Dolores",
    "gn:country_code":"MX",
    "gn:dem":2119,
    "gn:feature_class":"P",
    "gn:feature_code":"PPL",
    "gn:name":"El Alto de Dolores",
    "gn:population":0,
    "gn:timezone":"America/Chihuahua",
    "iso:country":"MX",
    "name:spa_x_preferred":[
        "El Alto de Dolores"
    ],
    "wof:name":"El Alto de Dolores",
    "wof:placetype":"locality"
},
  "geometry": {"coordinates":[-108.26288,29.64103],"type":"Point"}
}