{
  "type": "Feature",
  "properties": {
    "gn:admin1_code":"25",
    "gn:admin2_code":"5.0",
    "gn:asciiname":"Tanjas",
    "gn:country_code":"MX",
    "gn:dem":120,
    "gn:feature_class":"P",
    "gn:feature_code":"PPL",
    "gn:name":"Tanjas",
    "gn:population":0,
    "gn:timezone":"America/Mazatlan",
    "iso:country":"MX",
    "wof:name":"Tanjas",
    "wof:placetype":"locality"
},
  "geometry": {"coordinates":[-107.05,24.45],"type":"Point"}
}