{
  "type": "Feature",
  "properties": {
    "gn:admin1_code":"30",
    "gn:admin2_code":"174",
    "gn:asciiname":"Las Amazonas",
    "gn:country_code":"MX",
    "gn:dem":70,
    "gn:feature_class":"P",
    "gn:feature_code":"PPL",
    "gn:name":"Las Amazonas",
    "gn:population":12,
    "gn:timezone":"America/Mexico_City",
    "iso:country":"MX",
    "wof:name":"Las Amazonas",
    "wof:placetype":"locality",
    "wof:population":12
},
  "geometry": {"coordinates":[-96.35805999999999,18.51917000000001],"type":"Point"}
}