{
  "type": "Feature",
  "properties": {
    "gn:admin1_code":"5",
    "gn:admin2_code":"93.0",
    "gn:asciiname":"Guadalupe",
    "gn:country_code":"MX",
    "gn:dem":2273,
    "gn:feature_class":"P",
    "gn:feature_code":"PPL",
    "gn:name":"Guadalupe",
    "gn:population":56,
    "gn:timezone":"America/Mexico_City",
    "iso:country":"MX",
    "wof:name":"Guadalupe",
    "wof:placetype":"locality",
    "wof:population":56
},
  "geometry": {"coordinates":[-92.53194000000001,16.79139],"type":"Point"}
}