{
  "type": "Feature",
  "properties": {
    "gn:admin1_code":"16",
    "gn:admin2_code":"57.0",
    "gn:asciiname":"La Cablotera",
    "gn:country_code":"MX",
    "gn:dem":1338,
    "gn:feature_class":"P",
    "gn:feature_code":"PPL",
    "gn:name":"La Cablotera",
    "gn:population":0,
    "gn:timezone":"America/Mexico_City",
    "iso:country":"MX",
    "name:spa_x_preferred":[
        "La Cablotera"
    ],
    "wof:name":"La Cablotera",
    "wof:placetype":"locality"
},
  "geometry": {"coordinates":[-101.22223,19.21089],"type":"Point"}
}