{
  "type": "Feature",
  "properties": {
    "gn:admin1_code":"30",
    "gn:admin2_code":"23.0",
    "gn:asciiname":"Cueva Santa",
    "gn:country_code":"MX",
    "gn:dem":243,
    "gn:feature_class":"P",
    "gn:feature_code":"PPL",
    "gn:name":"Cueva Santa",
    "gn:population":0,
    "gn:timezone":"America/Mexico_City",
    "iso:country":"MX",
    "name:spa_x_preferred":[
        "Cueva Santa"
    ],
    "wof:name":"Cueva Santa",
    "wof:placetype":"locality"
},
  "geometry": {"coordinates":[-97.08668,19.95356],"type":"Point"}
}