{
  "type": "Feature",
  "properties": {
    "gn:admin1_code":"3",
    "gn:admin2_code":"2.0",
    "gn:asciiname":"Molina [Taller]",
    "gn:country_code":"MX",
    "gn:dem":82,
    "gn:feature_class":"P",
    "gn:feature_code":"PPL",
    "gn:name":"Molina [Taller]",
    "gn:population":5,
    "gn:timezone":"America/Mazatlan",
    "iso:country":"MX",
    "wof:name":"Molina [Taller]",
    "wof:placetype":"locality",
    "wof:population":5
},
  "geometry": {"coordinates":[-113.38858,27.65666],"type":"Point"}
}