{
  "type": "Feature",
  "properties": {
    "gn:admin1_code":"30.0",
    "gn:admin2_code":"138.0",
    "gn:asciiname":"Atitla",
    "gn:country_code":"MX",
    "gn:dem":1818,
    "gn:feature_class":"P",
    "gn:feature_code":"PPL",
    "gn:name":"Atitla",
    "gn:population":0,
    "gn:timezone":"America/Mexico_City",
    "iso:country":"MX",
    "name:spa_x_preferred":[
        "Atitla"
    ],
    "wof:name":"Atitla",
    "wof:placetype":"locality"
},
  "geometry": {"coordinates":[-97.16795999999999,18.85401],"type":"Point"}
}