{
  "type": "Feature",
  "properties": {
    "gn:admin1_code":"6.0",
    "gn:admin2_code":"2.0",
    "gn:asciiname":"Las Boquillas",
    "gn:country_code":"MX",
    "gn:dem":1225,
    "gn:feature_class":"P",
    "gn:feature_code":"PPL",
    "gn:name":"Las Boquillas",
    "gn:population":0,
    "gn:timezone":"America/Chihuahua",
    "iso:country":"MX",
    "name:spa_x_preferred":[
        "Las Boquillas"
    ],
    "name:und_x_variant":[
        "Rancho de la Boquilla",
        "La Boquilla"
    ],
    "wof:name":"Las Boquillas",
    "wof:placetype":"locality"
},
  "geometry": {"coordinates":[-105.69046000000002,29.14102],"type":"Point"}
}