{
  "type": "Feature",
  "properties": {
    "gn:admin1_code":"20",
    "gn:admin2_code":"543.0",
    "gn:asciiname":"Boca del Rio",
    "gn:country_code":"MX",
    "gn:dem":52,
    "gn:feature_class":"P",
    "gn:feature_code":"PPL",
    "gn:name":"Boca del R\u00edo",
    "gn:population":0,
    "gn:timezone":"America/Mexico_City",
    "iso:country":"MX",
    "name:spa_x_preferred":[
        "R\u00edo Leche"
    ],
    "name:spa_x_variant":[
        "Boca del R\u00edo"
    ],
    "wof:name":"Boca del Rio",
    "wof:placetype":"locality"
},
  "geometry": {"coordinates":[-97.592,16.24124],"type":"Point"}
}