{
  "type": "Feature",
  "properties": {
    "gn:admin1_code":"16",
    "gn:admin2_code":"65",
    "gn:asciiname":"Los Reyes",
    "gn:country_code":"MX",
    "gn:dem":2258,
    "gn:feature_class":"P",
    "gn:feature_code":"PPL",
    "gn:name":"Los Reyes",
    "gn:population":10,
    "gn:timezone":"America/Mexico_City",
    "iso:country":"MX",
    "name:ceb_x_preferred":[
        "Los Reyes"
    ],
    "name:deu_x_preferred":[
        "Los Reyes"
    ],
    "name:epo_x_preferred":[
        "Los Reyes"
    ],
    "name:nds_x_preferred":[
        "Los Reyes"
    ],
    "name:spa_x_preferred":[
        "Los Reyes"
    ],
    "name:swe_x_preferred":[
        "Los Reyes"
    ],
    "wof:name":"Los Reyes",
    "wof:placetype":"locality",
    "wof:population":10
},
  "geometry": {"coordinates":[-102.04083,19.64056],"type":"Point"}
}