{
  "type": "Feature",
  "properties": {
    "gn:admin1_code":"16",
    "gn:admin2_code":"6.0",
    "gn:asciiname":"Colonia los Arquitos",
    "gn:country_code":"MX",
    "gn:dem":339,
    "gn:feature_class":"P",
    "gn:feature_code":"PPL",
    "gn:name":"Colonia los Arquitos",
    "gn:population":9,
    "gn:timezone":"America/Mexico_City",
    "iso:country":"MX",
    "wof:name":"Colonia los Arquitos",
    "wof:placetype":"locality",
    "wof:population":9
},
  "geometry": {"coordinates":[-102.32832999999999,19.07083],"type":"Point"}
}