{
  "type": "Feature",
  "properties": {
    "gn:admin1_code":"4",
    "gn:admin2_code":"10.0",
    "gn:asciiname":"Central Altamira",
    "gn:country_code":"MX",
    "gn:dem":266,
    "gn:feature_class":"P",
    "gn:feature_code":"PPL",
    "gn:name":"Central Altamira",
    "gn:population":0,
    "gn:timezone":"America/Merida",
    "iso:country":"MX",
    "name:spa_x_preferred":[
        "Altamira"
    ],
    "name:spa_x_variant":[
        "Central Altamira"
    ],
    "wof:name":"Central Altamira",
    "wof:placetype":"locality"
},
  "geometry": {"coordinates":[-89.52743000000002,17.96021],"type":"Point"}
}