{
  "type": "Feature",
  "properties": {
    "gn:admin1_code":"2",
    "gn:admin2_code":"1.0",
    "gn:asciiname":"Rancho Pasillas",
    "gn:country_code":"MX",
    "gn:dem":20,
    "gn:feature_class":"P",
    "gn:feature_code":"PPL",
    "gn:name":"Rancho Pasillas",
    "gn:population":5,
    "gn:timezone":"America/Tijuana",
    "iso:country":"MX",
    "wof:name":"Rancho Pasillas",
    "wof:placetype":"locality",
    "wof:population":5
},
  "geometry": {"coordinates":[-115.95694,30.595],"type":"Point"}
}