{
  "type": "Feature",
  "properties": {
    "gn:admin1_code":"10",
    "gn:asciiname":"El Chato",
    "gn:country_code":"MX",
    "gn:dem":1920,
    "gn:feature_class":"P",
    "gn:feature_code":"PPL",
    "gn:name":"El Chato",
    "gn:population":0,
    "gn:timezone":"America/Monterrey",
    "iso:country":"MX",
    "name:spa_x_preferred":[
        "El Chato"
    ],
    "wof:name":"El Chato",
    "wof:placetype":"locality"
},
  "geometry": {"coordinates":[-106.82312,25.57923],"type":"Point"}
}