{
  "type": "Feature",
  "properties": {
    "gn:admin1_code":"20",
    "gn:admin2_code":"500",
    "gn:asciiname":"Yuku Yuu",
    "gn:country_code":"MX",
    "gn:dem":1104,
    "gn:feature_class":"P",
    "gn:feature_code":"PPL",
    "gn:name":"Yuku Yuu",
    "gn:population":47,
    "gn:timezone":"America/Mexico_City",
    "iso:country":"MX",
    "wof:name":"Yuku Yuu",
    "wof:placetype":"locality",
    "wof:population":47
},
  "geometry": {"coordinates":[-97.57028,16.78472],"type":"Point"}
}