{
  "type": "Feature",
  "properties": {
    "gn:admin1_code":"5",
    "gn:admin2_code":"47",
    "gn:asciiname":"Paraje San Antonio",
    "gn:country_code":"MX",
    "gn:dem":1098,
    "gn:feature_class":"P",
    "gn:feature_code":"PPL",
    "gn:name":"Paraje San Antonio",
    "gn:population":50,
    "gn:timezone":"America/Mexico_City",
    "iso:country":"MX",
    "wof:name":"Paraje San Antonio",
    "wof:placetype":"locality",
    "wof:population":50
},
  "geometry": {"coordinates":[-92.78471999999999,17.10444],"type":"Point"}
}