{
  "type": "Feature",
  "properties": {
    "gn:admin1_code":"16",
    "gn:admin2_code":"96",
    "gn:asciiname":"Apo Nuevo",
    "gn:country_code":"MX",
    "gn:dem":1323,
    "gn:feature_class":"P",
    "gn:feature_code":"PPL",
    "gn:name":"Apo Nuevo",
    "gn:population":12,
    "gn:timezone":"America/Mexico_City",
    "iso:country":"MX",
    "wof:name":"Apo Nuevo",
    "wof:placetype":"locality",
    "wof:population":12
},
  "geometry": {"coordinates":[-102.58,18.48833],"type":"Point"}
}