{
  "type": "Feature",
  "properties": {
    "gn:admin1_code":"10",
    "gn:admin2_code":"14",
    "gn:asciiname":"La Cueva",
    "gn:country_code":"MX",
    "gn:dem":1242,
    "gn:feature_class":"P",
    "gn:feature_code":"PPL",
    "gn:name":"La Cueva",
    "gn:population":30,
    "gn:timezone":"America/Monterrey",
    "iso:country":"MX",
    "wof:name":"La Cueva",
    "wof:placetype":"locality",
    "wof:population":30
},
  "geometry": {"coordinates":[-104.63829,22.79864],"type":"Point"}
}