{
  "type": "Feature",
  "properties": {
    "gn:admin1_code":"5",
    "gn:admin2_code":"17.0",
    "gn:asciiname":"Ocotlan",
    "gn:country_code":"MX",
    "gn:dem":791,
    "gn:feature_class":"P",
    "gn:feature_code":"PPL",
    "gn:name":"Ocotl\u00e1n",
    "gn:population":7,
    "gn:timezone":"America/Mexico_City",
    "iso:country":"MX",
    "name:und_x_variant":[
        "Ocotl\u00e1n"
    ],
    "wof:name":"Ocotlan",
    "wof:placetype":"locality",
    "wof:population":7
},
  "geometry": {"coordinates":[-93.80806,16.51778],"type":"Point"}
}