{
  "type": "Feature",
  "properties": {
    "gn:admin1_code":"15",
    "gn:admin2_code":"39.0",
    "gn:asciiname":"Xocolines",
    "gn:country_code":"MX",
    "gn:dem":2312,
    "gn:feature_class":"P",
    "gn:feature_code":"PPL",
    "gn:name":"Xocolines",
    "gn:population":0,
    "gn:timezone":"America/Mexico_City",
    "iso:country":"MX",
    "name:spa_x_preferred":[
        "Xocolines"
    ],
    "wof:name":"Xocolines",
    "wof:placetype":"locality"
},
  "geometry": {"coordinates":[-98.89964000000001,19.33018],"type":"Point"}
}