{
  "type": "Feature",
  "properties": {
    "gn:admin1_code":"5.0",
    "gn:admin2_code":"96.0",
    "gn:asciiname":"San Jose Changueinic",
    "gn:country_code":"MX",
    "gn:dem":984,
    "gn:feature_class":"P",
    "gn:feature_code":"PPL",
    "gn:name":"San Jos\u00e9 Chang\u00fcinic",
    "gn:population":0,
    "gn:timezone":"America/Mexico_City",
    "iso:country":"MX",
    "name:spa_x_preferred":[
        "San Jos\u00e9 Chang\u00fcinic"
    ],
    "wof:name":"San Jose Changueinic",
    "wof:placetype":"locality"
},
  "geometry": {"coordinates":[-92.40034,17.20285],"type":"Point"}
}