{
  "type": "Feature",
  "properties": {
    "gn:admin1_code":"2",
    "gn:admin2_code":"1.0",
    "gn:asciiname":"Yaqui",
    "gn:country_code":"MX",
    "gn:dem":662,
    "gn:feature_class":"P",
    "gn:feature_code":"PPL",
    "gn:name":"Yaqui",
    "gn:population":0,
    "gn:timezone":"America/Tijuana",
    "iso:country":"MX",
    "name:ara_x_preferred":[
        "\u064a\u0627\u0643\u064a"
    ],
    "name:ben_x_preferred":[
        "\u0987\u09af\u09bc\u09be\u0995\u09c1\u0987"
    ],
    "name:bul_x_preferred":[
        "\u042f\u043a\u0438"
    ],
    "name:cat_x_preferred":[
        "Yaquis"
    ],
    "name:ces_x_preferred":[
        "Jakiov\u00e9"
    ],
    "name:deu_x_preferred":[
        "Yaqui"
    ],
    "name:ell_x_preferred":[
        "\u0393\u03b9\u03ac\u03ba\u03b9"
    ],
    "name:epo_x_preferred":[
        "Jakioj"
    ],
    "name:fas_x_preferred":[
        "\u06cc\u0627\u06a9\u0648\u0626\u06cc"
    ],
    "name:fra_x_preferred":[
        "Yaquis"
    ],
    "name:hin_x_preferred":[
        "\u092f\u093e\u0915\u0940"
    ],
    "name:hrv_x_preferred":[
        "Yaqui"
    ],
    "name:hun_x_preferred":[
        "Yaqui"
    ],
    "name:ind_x_preferred":[
        "Yaqui"
    ],
    "name:ita_x_preferred":[
        "Yaqui"
    ],
    "name:kor_x_preferred":[
        "\uc57c\ud0a4"
    ],
    "name:lit_x_preferred":[
        "Jakiai"
    ],
    "name:nld_x_preferred":[
        "Yaqui"
    ],
    "name:pol_x_preferred":[
        "Yaqui"
    ],
    "name:por_x_preferred":[
        "Yaquis"
    ],
    "name:rus_x_preferred":[
        "\u042f\u043a\u0438"
    ],
    "name:spa_x_preferred":[
        "Yaqui"
    ],
    "name:spa_x_variant":[
        "Pueblo yaqui"
    ],
    "name:swe_x_preferred":[
        "Yaqui River"
    ],
    "name:swe_x_variant":[
        "Yaqui"
    ],
    "name:tur_x_preferred":[
        "Yaqui"
    ],
    "name:urd_x_preferred":[
        "\u06cc\u0627\u0642\u06cc"
    ],
    "name:vie_x_preferred":[
        "S\u00f4ng Yaqui"
    ],
    "wof:name":"Yaqui",
    "wof:placetype":"locality"
},
  "geometry": {"coordinates":[-116.32008,31.98352],"type":"Point"}
}