{
  "type": "Feature",
  "properties": {
    "gn:admin1_code":"2",
    "gn:admin2_code":"1.0",
    "gn:asciiname":"Yaqui",
    "gn:country_code":"MX",
    "gn:dem":662,
    "gn:feature_class":"P",
    "gn:feature_code":"PPL",
    "gn:name":"Yaqui",
    "gn:population":0,
    "gn:timezone":"America/Tijuana",
    "iso:country":"MX",
    "name:bul_x_preferred":[
        "\u042f\u043a\u0438"
    ],
    "name:cat_x_preferred":[
        "Yaquis"
    ],
    "name:ces_x_preferred":[
        "Jakiov\u00e9"
    ],
    "name:deu_x_preferred":[
        "Yaqui"
    ],
    "name:epo_x_preferred":[
        "Jakioj"
    ],
    "name:fra_x_preferred":[
        "Yaquis"
    ],
    "name:hrv_x_preferred":[
        "Yaqui"
    ],
    "name:ind_x_preferred":[
        "Yaqui"
    ],
    "name:ita_x_preferred":[
        "Yaqui"
    ],
    "name:lit_x_preferred":[
        "Jakiai"
    ],
    "name:nld_x_preferred":[
        "Yaqui"
    ],
    "name:pol_x_preferred":[
        "Yaqui"
    ],
    "name:por_x_preferred":[
        "Yaquis"
    ],
    "name:rus_x_preferred":[
        "\u042f\u043a\u0438"
    ],
    "name:spa_x_preferred":[
        "Yaqui"
    ],
    "name:spa_x_variant":[
        "Pueblo yaqui"
    ],
    "name:swe_x_preferred":[
        "Yaqui"
    ],
    "wof:name":"Yaqui",
    "wof:placetype":"locality"
},
  "geometry": {"coordinates":[-116.32008,31.98352],"type":"Point"}
}