{
  "type": "Feature",
  "properties": {
    "gn:admin1_code":"4",
    "gn:admin2_code":"1",
    "gn:asciiname":"Anexo San Mateo",
    "gn:country_code":"MX",
    "gn:dem":21,
    "gn:feature_class":"P",
    "gn:feature_code":"PPL",
    "gn:name":"Anexo San Mateo",
    "gn:population":37,
    "gn:timezone":"America/Merida",
    "iso:country":"MX",
    "wof:name":"Anexo San Mateo",
    "wof:placetype":"locality",
    "wof:population":37
},
  "geometry": {"coordinates":[-90.04194,20.31722],"type":"Point"}
}