{
  "type": "Feature",
  "properties": {
    "gn:admin1_code":"14",
    "gn:admin2_code":"35.0",
    "gn:asciiname":"El Huizache",
    "gn:country_code":"MX",
    "gn:dem":1781,
    "gn:feature_class":"P",
    "gn:feature_code":"PPL",
    "gn:name":"El Huizache",
    "gn:population":7,
    "gn:timezone":"America/Mexico_City",
    "iso:country":"MX",
    "wof:name":"El Huizache",
    "wof:placetype":"locality",
    "wof:population":7
},
  "geometry": {"coordinates":[-102.34833,21.53],"type":"Point"}
}