{
  "type": "Feature",
  "properties": {
    "gn:admin1_code":"10",
    "gn:admin2_code":"23",
    "gn:asciiname":"La Escondida",
    "gn:country_code":"MX",
    "gn:dem":2112,
    "gn:feature_class":"P",
    "gn:feature_code":"PPL",
    "gn:name":"La Escondida",
    "gn:population":12,
    "gn:timezone":"America/Monterrey",
    "iso:country":"MX",
    "wof:name":"La Escondida",
    "wof:placetype":"locality",
    "wof:population":12
},
  "geometry": {"coordinates":[-105.64863,23.86445],"type":"Point"}
}