{
  "type": "Feature",
  "properties": {
    "gn:admin1_code":"16",
    "gn:admin2_code":"8.0",
    "gn:asciiname":"La Joya Verde",
    "gn:country_code":"MX",
    "gn:dem":1161,
    "gn:feature_class":"P",
    "gn:feature_code":"PPL",
    "gn:name":"La Joya Verde",
    "gn:population":8,
    "gn:timezone":"America/Mexico_City",
    "iso:country":"MX",
    "wof:name":"La Joya Verde",
    "wof:placetype":"locality",
    "wof:population":8
},
  "geometry": {"coordinates":[-103.13139,18.34417],"type":"Point"}
}