{
  "type": "Feature",
  "properties": {
    "gn:admin1_code":"30",
    "gn:admin2_code":"174.0",
    "gn:asciiname":"Nuevo Porvenir de Hidalgo (Dicha Tuerta)",
    "gn:country_code":"MX",
    "gn:dem":26,
    "gn:feature_class":"P",
    "gn:feature_code":"PPL",
    "gn:name":"Nuevo Porvenir de Hidalgo (Dicha Tuerta)",
    "gn:population":282,
    "gn:timezone":"America/Mexico_City",
    "iso:country":"MX",
    "wof:name":"Nuevo Porvenir de Hidalgo (Dicha Tuerta)",
    "wof:placetype":"locality",
    "wof:population":282
},
  "geometry": {"coordinates":[-96.16306,18.60417],"type":"Point"}
}