{
  "type": "Feature",
  "properties": {
    "gn:admin1_code":"20",
    "gn:admin2_code":"37.0",
    "gn:asciiname":"Llano la Plaza",
    "gn:country_code":"MX",
    "gn:dem":515,
    "gn:feature_class":"P",
    "gn:feature_code":"PPL",
    "gn:name":"Llano la Plaza",
    "gn:population":121,
    "gn:timezone":"America/Mexico_City",
    "iso:country":"MX",
    "wof:name":"Llano la Plaza",
    "wof:placetype":"locality",
    "wof:population":121
},
  "geometry": {"coordinates":[-97.95,16.92083],"type":"Point"}
}