{
  "type": "Feature",
  "properties": {
    "gn:admin1_code":"30.0",
    "gn:admin2_code":"158.0",
    "gn:asciiname":"Plan de Ayala",
    "gn:country_code":"MX",
    "gn:dem":35,
    "gn:feature_class":"P",
    "gn:feature_code":"PPL",
    "gn:name":"Plan de Ayala",
    "gn:population":89,
    "gn:timezone":"America/Mexico_City",
    "iso:country":"MX",
    "name:spa_x_preferred":[
        "Plan de Ayala"
    ],
    "wof:name":"Plan de Ayala",
    "wof:placetype":"locality",
    "wof:population":89
},
  "geometry": {"coordinates":[-97.16887,20.57629],"type":"Point"}
}