{
  "type": "Feature",
  "properties": {
    "gn:admin1_code":"15",
    "gn:admin2_code":"36.0",
    "gn:asciiname":"Tezontlalpan",
    "gn:country_code":"MX",
    "gn:dem":2430,
    "gn:feature_class":"P",
    "gn:feature_code":"PPL",
    "gn:name":"Tezontlalpan",
    "gn:population":0,
    "gn:timezone":"America/Mexico_City",
    "iso:country":"MX",
    "name:und_x_variant":[
        "Tezontlalpa de Zapata"
    ],
    "wof:name":"Tezontlalpan",
    "wof:placetype":"locality"
},
  "geometry": {"coordinates":[-98.99307,20.02009],"type":"Point"}
}