{
  "type": "Feature",
  "properties": {
    "gn:admin1_code":"16",
    "gn:admin2_code":"97",
    "gn:asciiname":"La Joya",
    "gn:country_code":"MX",
    "gn:dem":684,
    "gn:feature_class":"P",
    "gn:feature_code":"PPL",
    "gn:name":"La Joya",
    "gn:population":40,
    "gn:timezone":"America/Mexico_City",
    "iso:country":"MX",
    "wof:name":"La Joya",
    "wof:placetype":"locality",
    "wof:population":40
},
  "geometry": {"coordinates":[-101.39833,18.82778],"type":"Point"}
}