{
  "type": "Feature",
  "properties": {
    "gn:admin1_code":"12",
    "gn:admin2_code":"41.0",
    "gn:asciiname":"El Paraiso",
    "gn:country_code":"MX",
    "gn:dem":1049,
    "gn:feature_class":"P",
    "gn:feature_code":"PPL",
    "gn:name":"El Para\u00edso",
    "gn:population":67,
    "gn:timezone":"America/Mexico_City",
    "iso:country":"MX",
    "name:und_x_variant":[
        "El Para\u00edso"
    ],
    "wof:name":"El Paraiso",
    "wof:placetype":"locality",
    "wof:population":67
},
  "geometry": {"coordinates":[-98.76609000000001,17.0311],"type":"Point"}
}