{
  "type": "Feature",
  "properties": {
    "gn:admin1_code":"30",
    "gn:admin2_code":"23.0",
    "gn:asciiname":"Santa Teresa",
    "gn:country_code":"MX",
    "gn:dem":379,
    "gn:feature_class":"P",
    "gn:feature_code":"PPL",
    "gn:name":"Santa Teresa",
    "gn:population":7,
    "gn:timezone":"America/Mexico_City",
    "iso:country":"MX",
    "wof:name":"Santa Teresa",
    "wof:placetype":"locality",
    "wof:population":7
},
  "geometry": {"coordinates":[-97.03278,19.96222],"type":"Point"}
}