{
  "type": "Feature",
  "properties": {
    "gn:admin1_code":"10",
    "gn:admin2_code":"12",
    "gn:asciiname":"El Guaje",
    "gn:country_code":"MX",
    "gn:dem":1138,
    "gn:feature_class":"P",
    "gn:feature_code":"PPL",
    "gn:name":"El Guaje",
    "gn:population":19,
    "gn:timezone":"America/Monterrey",
    "iso:country":"MX",
    "wof:name":"El Guaje",
    "wof:placetype":"locality",
    "wof:population":19
},
  "geometry": {"coordinates":[-103.51524000000001,25.5149],"type":"Point"}
}