{
  "type": "Feature",
  "properties": {
    "gn:admin1_code":"5.0",
    "gn:admin2_code":"31.0",
    "gn:asciiname":"Yetalmap",
    "gn:country_code":"MX",
    "gn:dem":913,
    "gn:feature_class":"P",
    "gn:feature_code":"PPL",
    "gn:name":"Yetalmap",
    "gn:population":0,
    "gn:timezone":"America/Mexico_City",
    "iso:country":"MX",
    "name:spa_x_preferred":[
        "Yetalmap"
    ],
    "wof:name":"Yetalmap",
    "wof:placetype":"locality"
},
  "geometry": {"coordinates":[-92.19123,17.0787],"type":"Point"}
}