{
  "type": "Feature",
  "properties": {
    "gn:admin1_code":"26.0",
    "gn:admin2_code":"52.0",
    "gn:asciiname":"La Cueva Colorada",
    "gn:country_code":"MX",
    "gn:dem":1037,
    "gn:feature_class":"P",
    "gn:feature_code":"PPL",
    "gn:name":"La Cueva Colorada",
    "gn:population":0,
    "gn:timezone":"America/Hermosillo",
    "iso:country":"MX",
    "name:spa_x_preferred":[
        "La Cueva Colorada"
    ],
    "wof:name":"La Cueva Colorada",
    "wof:placetype":"locality"
},
  "geometry": {"coordinates":[-108.83693999999998,28.87953],"type":"Point"}
}