{
  "type": "Feature",
  "properties": {
    "gn:admin1_code":"16.0",
    "gn:admin2_code":"81.0",
    "gn:asciiname":"Pie de la Cuesta (La Uva)",
    "gn:country_code":"MX",
    "gn:dem":1128,
    "gn:feature_class":"P",
    "gn:feature_code":"PPL",
    "gn:name":"Pie de la Cuesta (La Uva)",
    "gn:population":0,
    "gn:timezone":"America/Mexico_City",
    "iso:country":"MX",
    "name:spa_x_preferred":[
        "Pie de la Cuesta (La Uva)"
    ],
    "name:spa_x_variant":[
        "La Uva"
    ],
    "wof:name":"Pie de la Cuesta (La Uva)",
    "wof:placetype":"locality"
},
  "geometry": {"coordinates":[-100.41289999999999,19.18826],"type":"Point"}
}