{
  "type": "Feature",
  "properties": {
    "gn:admin1_code":"6.0",
    "gn:admin2_code":"28.0",
    "gn:asciiname":"El Uno",
    "gn:country_code":"MX",
    "gn:dem":1502,
    "gn:feature_class":"P",
    "gn:feature_code":"PPL",
    "gn:name":"El Uno",
    "gn:population":3,
    "gn:timezone":"America/Chihuahua",
    "iso:country":"MX",
    "name:spa_x_preferred":[
        "El Uno"
    ],
    "wof:name":"El Uno",
    "wof:placetype":"locality",
    "wof:population":3
},
  "geometry": {"coordinates":[-105.81059,30.8428],"type":"Point"}
}