{
  "type": "Feature",
  "properties": {
    "gn:admin1_code":"14",
    "gn:admin2_code":"93",
    "gn:asciiname":"Los Sauces de Franco",
    "gn:country_code":"MX",
    "gn:dem":2051,
    "gn:feature_class":"P",
    "gn:feature_code":"PPL",
    "gn:name":"Los Sauces de Franco",
    "gn:population":44,
    "gn:timezone":"America/Mexico_City",
    "iso:country":"MX",
    "wof:name":"Los Sauces de Franco",
    "wof:placetype":"locality",
    "wof:population":44
},
  "geometry": {"coordinates":[-102.60194,20.79944],"type":"Point"}
}