{
  "type": "Feature",
  "properties": {
    "gn:admin1_code":"30",
    "gn:admin2_code":"184.0",
    "gn:asciiname":"Cuigcuautitla",
    "gn:country_code":"MX",
    "gn:dem":2512,
    "gn:feature_class":"P",
    "gn:feature_code":"PPL",
    "gn:name":"Cuigcuautitla",
    "gn:population":57,
    "gn:timezone":"America/Mexico_City",
    "iso:country":"MX",
    "wof:name":"Cuigcuautitla",
    "wof:placetype":"locality",
    "wof:population":57
},
  "geometry": {"coordinates":[-97.10444,18.62194],"type":"Point"}
}