{
  "type": "Feature",
  "properties": {
    "gn:admin1_code":"2.0",
    "gn:admin2_code":"1.0",
    "gn:asciiname":"Burro",
    "gn:cc2":"MX",
    "gn:country_code":"MX",
    "gn:dem":1208,
    "gn:feature_class":"P",
    "gn:feature_code":"PPL",
    "gn:name":"Burro",
    "gn:population":0,
    "gn:timezone":"America/Tijuana",
    "iso:country":"MX",
    "name:und_x_variant":[
        "Aguaje",
        "Burro"
    ],
    "wof:name":"Burro",
    "wof:placetype":"locality"
},
  "geometry": {"coordinates":[-116.25,32.11667],"type":"Point"}
}