{
  "type": "Feature",
  "properties": {
    "gn:admin1_code":"15.0",
    "gn:asciiname":"Yereje",
    "gn:country_code":"MX",
    "gn:dem":2386,
    "gn:feature_class":"P",
    "gn:feature_code":"PPL",
    "gn:name":"Yereje",
    "gn:population":0,
    "gn:timezone":"America/Mexico_City",
    "iso:country":"MX",
    "name:spa_x_preferred":[
        "Yereje"
    ],
    "name:spa_x_variant":[
        "Yerege"
    ],
    "wof:name":"Yereje",
    "wof:placetype":"locality"
},
  "geometry": {"coordinates":[-100.19174,20.00491],"type":"Point"}
}