{
  "type": "Feature",
  "properties": {
    "gn:admin1_code":"16",
    "gn:admin2_code":"8",
    "gn:asciiname":"El Coyulito",
    "gn:country_code":"MX",
    "gn:dem":248,
    "gn:feature_class":"P",
    "gn:feature_code":"PPL",
    "gn:name":"El Coyulito",
    "gn:population":10,
    "gn:timezone":"America/Mexico_City",
    "iso:country":"MX",
    "wof:name":"El Coyulito",
    "wof:placetype":"locality",
    "wof:population":10
},
  "geometry": {"coordinates":[-103.04167,18.28278],"type":"Point"}
}