{
  "type": "Feature",
  "properties": {
    "gn:admin1_code":"28",
    "gn:admin2_code":"25.0",
    "gn:asciiname":"Guardados de Arriba",
    "gn:country_code":"MX",
    "gn:dem":61,
    "gn:feature_class":"P",
    "gn:feature_code":"PPL",
    "gn:name":"Guardados de Arriba",
    "gn:population":0,
    "gn:timezone":"America/Monterrey",
    "iso:country":"MX",
    "name:und_x_variant":[
        "Guardado de Arriba"
    ],
    "wof:name":"Guardados de Arriba",
    "wof:placetype":"locality"
},
  "geometry": {"coordinates":[-98.96574,26.38041],"type":"Point"}
}