{
  "type": "Feature",
  "properties": {
    "gn:admin1_code":"14",
    "gn:admin2_code":"83.0",
    "gn:asciiname":"La Martina",
    "gn:country_code":"MX",
    "gn:dem":1373,
    "gn:feature_class":"P",
    "gn:feature_code":"PPL",
    "gn:name":"La Martina",
    "gn:population":9,
    "gn:timezone":"America/Mexico_City",
    "iso:country":"MX",
    "name:deu_x_preferred":[
        "La Martina"
    ],
    "name:ita_x_preferred":[
        "La Martina"
    ],
    "name:spa_x_preferred":[
        "La Martina"
    ],
    "wof:name":"La Martina",
    "wof:placetype":"locality",
    "wof:population":9
},
  "geometry": {"coordinates":[-103.6825,20.63611],"type":"Point"}
}