{
  "type": "Feature",
  "properties": {
    "gn:admin1_code":"6",
    "gn:admin2_code":"29",
    "gn:asciiname":"Arroyo de la Rata",
    "gn:country_code":"MX",
    "gn:dem":2407,
    "gn:feature_class":"P",
    "gn:feature_code":"PPL",
    "gn:name":"Arroyo de la Rata",
    "gn:population":14,
    "gn:timezone":"America/Chihuahua",
    "iso:country":"MX",
    "wof:name":"Arroyo de la Rata",
    "wof:placetype":"locality",
    "wof:population":14
},
  "geometry": {"coordinates":[-107.05667,26.59167],"type":"Point"}
}