{
  "type": "Feature",
  "properties": {
    "gn:admin1_code":"30.0",
    "gn:admin2_code":"155.0",
    "gn:asciiname":"La Pitahaya Laja Segunda",
    "gn:country_code":"MX",
    "gn:dem":131,
    "gn:feature_class":"P",
    "gn:feature_code":"PPL",
    "gn:name":"La Pitahaya Laja Segunda",
    "gn:population":0,
    "gn:timezone":"America/Mexico_City",
    "iso:country":"MX",
    "name:spa_x_preferred":[
        "La Pitahaya Laja Segunda"
    ],
    "wof:name":"La Pitahaya Laja Segunda",
    "wof:placetype":"locality"
},
  "geometry": {"coordinates":[-98.28484,21.46775],"type":"Point"}
}