{
  "type": "Feature",
  "properties": {
    "gn:admin1_code":"11",
    "gn:admin2_code":"32.0",
    "gn:asciiname":"El Cerrito del Arenal",
    "gn:country_code":"MX",
    "gn:dem":2126,
    "gn:feature_class":"P",
    "gn:feature_code":"PPL",
    "gn:name":"El Cerrito del Arenal",
    "gn:population":644,
    "gn:timezone":"America/Mexico_City",
    "iso:country":"MX",
    "wof:name":"El Cerrito del Arenal",
    "wof:placetype":"locality",
    "wof:population":644
},
  "geometry": {"coordinates":[-100.43556,20.97083],"type":"Point"}
}