{
  "type": "Feature",
  "properties": {
    "gn:admin1_code":"32",
    "gn:admin2_code":"55",
    "gn:asciiname":"Consejo Tutelar para Menores",
    "gn:country_code":"MX",
    "gn:dem":2121,
    "gn:feature_class":"P",
    "gn:feature_code":"PPL",
    "gn:name":"Consejo Tutelar para Menores",
    "gn:population":16,
    "gn:timezone":"America/Mexico_City",
    "iso:country":"MX",
    "wof:name":"Consejo Tutelar para Menores",
    "wof:placetype":"locality",
    "wof:population":16
},
  "geometry": {"coordinates":[-102.77333,22.58611],"type":"Point"}
}