{
  "type": "Feature",
  "properties": {
    "gn:admin1_code":"15.0",
    "gn:admin2_code":"123.0",
    "gn:asciiname":"Pie de la Loma",
    "gn:country_code":"MX",
    "gn:dem":1007,
    "gn:feature_class":"P",
    "gn:feature_code":"PPL",
    "gn:name":"Pie de la Loma",
    "gn:population":0,
    "gn:timezone":"America/Mexico_City",
    "iso:country":"MX",
    "name:spa_x_preferred":[
        "Pie de la Loma"
    ],
    "wof:name":"Pie de la Loma",
    "wof:placetype":"locality"
},
  "geometry": {"coordinates":[-100.29048,18.85113],"type":"Point"}
}