{
  "type": "Feature",
  "properties": {
    "gn:admin1_code":"6",
    "gn:admin2_code":"16.0",
    "gn:asciiname":"Tierra Azul",
    "gn:country_code":"MX",
    "gn:dem":1201,
    "gn:feature_class":"P",
    "gn:feature_code":"PPL",
    "gn:name":"Tierra Azul",
    "gn:population":0,
    "gn:timezone":"America/Chihuahua",
    "iso:country":"MX",
    "name:spa_x_preferred":[
        "Tierra Azul"
    ],
    "wof:name":"Tierra Azul",
    "wof:placetype":"locality"
},
  "geometry": {"coordinates":[-105.19212,27.90426],"type":"Point"}
}