{
  "type": "Feature",
  "properties": {
    "gn:admin1_code":"28",
    "gn:admin2_code":"42.0",
    "gn:asciiname":"La Rosita",
    "gn:country_code":"MX",
    "gn:dem":328,
    "gn:feature_class":"P",
    "gn:feature_code":"PPL",
    "gn:name":"La Rosita",
    "gn:population":0,
    "gn:timezone":"America/Monterrey",
    "iso:country":"MX",
    "name:und_x_variant":[
        "Santa Rosalia",
        "La Rosita",
        "Rosal\u00eda"
    ],
    "wof:name":"La Rosita",
    "wof:placetype":"locality"
},
  "geometry": {"coordinates":[-99.40933,24.5149],"type":"Point"}
}