{
  "type": "Feature",
  "properties": {
    "gn:admin1_code":"25",
    "gn:admin2_code":"3",
    "gn:asciiname":"El Garbancito",
    "gn:country_code":"MX",
    "gn:dem":1104,
    "gn:feature_class":"P",
    "gn:feature_code":"PPL",
    "gn:name":"El Garbancito",
    "gn:population":24,
    "gn:timezone":"America/Mazatlan",
    "iso:country":"MX",
    "wof:name":"El Garbancito",
    "wof:placetype":"locality",
    "wof:population":24
},
  "geometry": {"coordinates":[-107.52325,25.91602],"type":"Point"}
}