{
  "type": "Feature",
  "properties": {
    "gn:admin1_code":"16",
    "gn:admin2_code":"10.0",
    "gn:asciiname":"La Bocana",
    "gn:country_code":"MX",
    "gn:dem":436,
    "gn:feature_class":"P",
    "gn:feature_code":"PPL",
    "gn:name":"La Bocana",
    "gn:population":7,
    "gn:timezone":"America/Mexico_City",
    "iso:country":"MX",
    "wof:name":"La Bocana",
    "wof:placetype":"locality",
    "wof:population":7
},
  "geometry": {"coordinates":[-102.155,18.32611],"type":"Point"}
}