{
  "type": "Feature",
  "properties": {
    "gn:admin1_code":"10.0",
    "gn:admin2_code":"39.0",
    "gn:asciiname":"La Concha",
    "gn:country_code":"MX",
    "gn:dem":2013,
    "gn:feature_class":"P",
    "gn:feature_code":"PPL",
    "gn:name":"La Concha",
    "gn:population":0,
    "gn:timezone":"America/Monterrey",
    "iso:country":"MX",
    "name:ceb_x_preferred":[
        "La Concha"
    ],
    "name:spa_x_preferred":[
        "La Concha"
    ],
    "name:swe_x_preferred":[
        "La Concha"
    ],
    "name:und_x_variant":[
        "Concha"
    ],
    "wof:name":"La Concha",
    "wof:placetype":"locality"
},
  "geometry": {"coordinates":[-105.11706,24.91908],"type":"Point"}
}