{
  "type": "Feature",
  "properties": {
    "gn:admin1_code":"14.0",
    "gn:admin2_code":"6.0",
    "gn:asciiname":"Labor de Solis",
    "gn:country_code":"MX",
    "gn:dem":1252,
    "gn:feature_class":"P",
    "gn:feature_code":"PPL",
    "gn:name":"Labor de Sol\u00eds",
    "gn:population":0,
    "gn:timezone":"America/Mexico_City",
    "iso:country":"MX",
    "wof:name":"Labor de Solis",
    "wof:placetype":"locality"
},
  "geometry": {"coordinates":[-103.98639,20.56816],"type":"Point"}
}