{
  "type": "Feature",
  "properties": {
    "gn:admin1_code":"30",
    "gn:admin2_code":"155.0",
    "gn:asciiname":"El Porvenir Chopopo",
    "gn:country_code":"MX",
    "gn:dem":146,
    "gn:feature_class":"P",
    "gn:feature_code":"PPL",
    "gn:name":"El Porvenir Chopopo",
    "gn:population":0,
    "gn:timezone":"America/Mexico_City",
    "iso:country":"MX",
    "name:und_x_variant":[
        "Chopo",
        "El Chopo",
        "Chopopo",
        "El Chopopo",
        "El Porvenir Chopopo",
        "El Porvenir"
    ],
    "wof:name":"El Porvenir Chopopo",
    "wof:placetype":"locality"
},
  "geometry": {"coordinates":[-98.17234999999999,21.3687],"type":"Point"}
}