{
  "type": "Feature",
  "properties": {
    "gn:admin1_code":"17.0",
    "gn:asciiname":"La Mesa del Venado",
    "gn:country_code":"MX",
    "gn:dem":2637,
    "gn:feature_class":"P",
    "gn:feature_code":"PPL",
    "gn:name":"La Mesa del Venado",
    "gn:population":0,
    "gn:timezone":"America/Mexico_City",
    "iso:country":"MX",
    "name:spa_x_preferred":[
        "La Mesa del Venado"
    ],
    "wof:name":"La Mesa del Venado",
    "wof:placetype":"locality"
},
  "geometry": {"coordinates":[-100.09986000000001,19.96307],"type":"Point"}
}