{
  "type": "Feature",
  "properties": {
    "gn:admin1_code":"25.0",
    "gn:admin2_code":"6.0",
    "gn:asciiname":"Estacion Abuya",
    "gn:country_code":"MX",
    "gn:dem":18,
    "gn:feature_class":"P",
    "gn:feature_code":"PPL",
    "gn:name":"Estaci\u00f3n Abuya",
    "gn:population":277,
    "gn:timezone":"America/Mazatlan",
    "iso:country":"MX",
    "wof:name":"Estacion Abuya",
    "wof:placetype":"locality",
    "wof:population":277
},
  "geometry": {"coordinates":[-107.10083,24.18361],"type":"Point"}
}