{
  "type": "Feature",
  "properties": {
    "gn:admin1_code":"3",
    "gn:admin2_code":"3",
    "gn:asciiname":"El Scirocco",
    "gn:country_code":"MX",
    "gn:dem":65,
    "gn:feature_class":"P",
    "gn:feature_code":"PPL",
    "gn:name":"El Scirocco",
    "gn:population":11,
    "gn:timezone":"America/Mazatlan",
    "iso:country":"MX",
    "wof:name":"El Scirocco",
    "wof:placetype":"locality",
    "wof:population":11
},
  "geometry": {"coordinates":[-110.31116000000002,24.06371],"type":"Point"}
}