{
  "type": "Feature",
  "properties": {
    "gn:admin1_code":"25",
    "gn:admin2_code":"3",
    "gn:asciiname":"La Coronilla",
    "gn:country_code":"MX",
    "gn:dem":342,
    "gn:feature_class":"P",
    "gn:feature_code":"PPL",
    "gn:name":"La Coronilla",
    "gn:population":18,
    "gn:timezone":"America/Mazatlan",
    "iso:country":"MX",
    "wof:name":"La Coronilla",
    "wof:placetype":"locality",
    "wof:population":18
},
  "geometry": {"coordinates":[-107.27101999999999,25.16635],"type":"Point"}
}