{
  "type": "Feature",
  "properties": {
    "gn:admin1_code":"25",
    "gn:admin2_code":"3",
    "gn:asciiname":"La Coronilla",
    "gn:country_code":"MX",
    "gn:dem":342,
    "gn:feature_class":"P",
    "gn:feature_code":"PPL",
    "gn:name":"La Coronilla",
    "gn:population":18,
    "gn:timezone":"America/Mazatlan",
    "iso:country":"MX",
    "name:cat_x_preferred":[
        "La Coronilla"
    ],
    "name:ceb_x_preferred":[
        "La Coronilla"
    ],
    "name:deu_x_preferred":[
        "La Coronilla"
    ],
    "name:fra_x_preferred":[
        "La Coronilla"
    ],
    "name:hye_x_preferred":[
        "\u053c\u0561 \u053f\u0578\u0580\u0578\u0576\u056b\u056c\u056b\u0561"
    ],
    "name:nor_x_preferred":[
        "La Coronilla"
    ],
    "name:por_x_preferred":[
        "La Coronilla"
    ],
    "name:rus_x_preferred":[
        "\u041b\u0430-\u041a\u043e\u0440\u043e\u043d\u0438\u043b\u044c\u044f"
    ],
    "name:spa_x_preferred":[
        "La Coronilla"
    ],
    "name:urd_x_preferred":[
        "\u0644\u0627 \u06a9\u0648\u0631\u0648\u0646\u06cc\u0644\u0627"
    ],
    "wof:name":"La Coronilla",
    "wof:placetype":"locality",
    "wof:population":18
},
  "geometry": {"coordinates":[-107.27101999999999,25.16635],"type":"Point"}
}