{
  "type": "Feature",
  "properties": {
    "gn:admin1_code":"5",
    "gn:admin2_code":"61",
    "gn:asciiname":"Monno",
    "gn:country_code":"MX",
    "gn:dem":883,
    "gn:feature_class":"P",
    "gn:feature_code":"PPL",
    "gn:name":"Monno",
    "gn:population":13,
    "gn:timezone":"America/Mexico_City",
    "iso:country":"MX",
    "name:azb_x_preferred":[
        "\u0645\u0648\u0646\u0646\u0648"
    ],
    "name:bel_x_preferred":[
        "\u041c\u043e\u043d\u0430"
    ],
    "name:bul_x_preferred":[
        "\u041c\u043e\u043d\u043e"
    ],
    "name:ceb_x_preferred":[
        "Monno"
    ],
    "name:deu_x_preferred":[
        "Monno"
    ],
    "name:epo_x_preferred":[
        "Monno"
    ],
    "name:eus_x_preferred":[
        "Monno"
    ],
    "name:fas_x_preferred":[
        "\u0645\u0648\u0646\u0646\u0648"
    ],
    "name:fra_x_preferred":[
        "Monno"
    ],
    "name:hun_x_preferred":[
        "Monno"
    ],
    "name:hye_x_preferred":[
        "\u0544\u0578\u0576\u0576\u0578"
    ],
    "name:ita_x_preferred":[
        "Monno"
    ],
    "name:jpn_x_preferred":[
        "\u30e2\u30f3\u30ce"
    ],
    "name:kaz_x_preferred":[
        "\u041c\u043e\u043d\u043d\u043e"
    ],
    "name:lat_x_preferred":[
        "Monnum"
    ],
    "name:lmo_x_preferred":[
        "M\u00f2n"
    ],
    "name:msa_x_preferred":[
        "Monno"
    ],
    "name:nap_x_preferred":[
        "Monno"
    ],
    "name:nld_x_preferred":[
        "Monno"
    ],
    "name:pms_x_preferred":[
        "Monno"
    ],
    "name:pol_x_preferred":[
        "Monno"
    ],
    "name:por_x_preferred":[
        "Monno"
    ],
    "name:ron_x_preferred":[
        "Monno"
    ],
    "name:rus_x_preferred":[
        "\u041c\u043e\u043d\u043d\u043e"
    ],
    "name:scn_x_preferred":[
        "Monno"
    ],
    "name:spa_x_preferred":[
        "Monno"
    ],
    "name:srp_x_preferred":[
        "\u041c\u043e\u043d\u043e"
    ],
    "name:tgl_x_preferred":[
        "Monno"
    ],
    "name:ukr_x_preferred":[
        "\u041c\u043e\u043d\u043d\u043e"
    ],
    "name:uzb_x_preferred":[
        "Monno"
    ],
    "name:vie_x_preferred":[
        "Monno"
    ],
    "name:vol_x_preferred":[
        "Monno"
    ],
    "name:war_x_preferred":[
        "Monno"
    ],
    "wof:name":"Monno",
    "wof:placetype":"locality",
    "wof:population":13
},
  "geometry": {"coordinates":[-93.46333,16.85972000000001],"type":"Point"}
}