{
  "type": "Feature",
  "properties": {
    "gn:admin1_code":"5",
    "gn:admin2_code":"61",
    "gn:asciiname":"Monno",
    "gn:country_code":"MX",
    "gn:dem":883,
    "gn:feature_class":"P",
    "gn:feature_code":"PPL",
    "gn:name":"Monno",
    "gn:population":13,
    "gn:timezone":"America/Mexico_City",
    "iso:country":"MX",
    "wof:name":"Monno",
    "wof:placetype":"locality",
    "wof:population":13
},
  "geometry": {"coordinates":[-93.46333,16.85972000000001],"type":"Point"}
}