{
  "type": "Feature",
  "properties": {
    "gn:admin1_code":"15.0",
    "gn:admin2_code":"82.0",
    "gn:asciiname":"Picacho del Guayabal",
    "gn:country_code":"MX",
    "gn:dem":881,
    "gn:feature_class":"P",
    "gn:feature_code":"PPL",
    "gn:name":"Picacho del Guayabal",
    "gn:population":0,
    "gn:timezone":"America/Mexico_City",
    "iso:country":"MX",
    "name:spa_x_preferred":[
        "Picacho del Guayabal"
    ],
    "wof:name":"Picacho del Guayabal",
    "wof:placetype":"locality"
},
  "geometry": {"coordinates":[-100.36816,18.83396],"type":"Point"}
}