{
  "type": "Feature",
  "properties": {
    "gn:admin1_code":"26",
    "gn:admin2_code":"66.0",
    "gn:asciiname":"Las Piedras",
    "gn:country_code":"MX",
    "gn:dem":802,
    "gn:feature_class":"P",
    "gn:feature_code":"PPL",
    "gn:name":"Las Piedras",
    "gn:population":0,
    "gn:timezone":"America/Hermosillo",
    "iso:country":"MX",
    "name:spa_x_preferred":[
        "Las Piedras"
    ],
    "wof:name":"Las Piedras",
    "wof:placetype":"locality"
},
  "geometry": {"coordinates":[-110.10389000000001,29.30583],"type":"Point"}
}