{
  "type": "Feature",
  "properties": {
    "gn:admin1_code":"30",
    "gn:admin2_code":"80.0",
    "gn:asciiname":"Presidio",
    "gn:country_code":"MX",
    "gn:dem":1330,
    "gn:feature_class":"P",
    "gn:feature_code":"PPL",
    "gn:name":"Presidio",
    "gn:population":2075,
    "gn:timezone":"America/Mexico_City",
    "iso:country":"MX",
    "name:epo_x_preferred":[
        "Presidio"
    ],
    "name:fra_x_preferred":[
        "Presidio"
    ],
    "name:nld_x_preferred":[
        "Presidio"
    ],
    "name:scn_x_preferred":[
        "Galera"
    ],
    "name:spa_x_preferred":[
        "Presidio"
    ],
    "name:swe_x_preferred":[
        "Presidio"
    ],
    "wof:name":"Presidio",
    "wof:placetype":"locality",
    "wof:population":2075
},
  "geometry": {"coordinates":[-96.97208999999999,19.06933],"type":"Point"}
}