{
  "type": "Feature",
  "properties": {
    "gn:admin1_code":"30",
    "gn:admin2_code":"197.0",
    "gn:asciiname":"El Mirador",
    "gn:country_code":"MX",
    "gn:dem":590,
    "gn:feature_class":"P",
    "gn:feature_code":"PPL",
    "gn:name":"El Mirador",
    "gn:population":287,
    "gn:timezone":"America/Mexico_City",
    "iso:country":"MX",
    "wof:name":"El Mirador",
    "wof:placetype":"locality",
    "wof:population":287
},
  "geometry": {"coordinates":[-96.78888999999999,19.87528],"type":"Point"}
}