{
  "type": "Feature",
  "properties": {
    "gn:admin1_code":"19",
    "gn:admin2_code":"50.0",
    "gn:asciiname":"Matatenas",
    "gn:country_code":"MX",
    "gn:dem":237,
    "gn:feature_class":"P",
    "gn:feature_code":"PPL",
    "gn:name":"Matatenas",
    "gn:population":0,
    "gn:timezone":"America/Monterrey",
    "iso:country":"MX",
    "name:und_x_variant":[
        "Matatena",
        "Matatenas"
    ],
    "wof:name":"Matatenas",
    "wof:placetype":"locality"
},
  "geometry": {"coordinates":[-99.99733999999999,26.5195],"type":"Point"}
}