{
  "type": "Feature",
  "properties": {
    "gn:admin1_code":"11",
    "gn:admin2_code":"7.0",
    "gn:asciiname":"Ex-Hacienda de Trojes",
    "gn:country_code":"MX",
    "gn:dem":1754,
    "gn:feature_class":"P",
    "gn:feature_code":"PPL",
    "gn:name":"Ex-Hacienda de Trojes",
    "gn:population":153,
    "gn:timezone":"America/Mexico_City",
    "iso:country":"MX",
    "wof:name":"Ex-Hacienda de Trojes",
    "wof:placetype":"locality",
    "wof:population":153
},
  "geometry": {"coordinates":[-100.77611,20.50028],"type":"Point"}
}