{
  "type": "Feature",
  "properties": {
    "gn:admin1_code":"14",
    "gn:admin2_code":"72",
    "gn:asciiname":"El Monte (Puerta del Monte)",
    "gn:country_code":"MX",
    "gn:dem":1940,
    "gn:feature_class":"P",
    "gn:feature_code":"PPL",
    "gn:name":"El Monte (Puerta del Monte)",
    "gn:population":47,
    "gn:timezone":"America/Mexico_City",
    "iso:country":"MX",
    "wof:name":"El Monte (Puerta del Monte)",
    "wof:placetype":"locality",
    "wof:population":47
},
  "geometry": {"coordinates":[-101.96972,21.00583],"type":"Point"}
}