{
  "type": "Feature",
  "properties": {
    "gn:admin1_code":"30.0",
    "gn:asciiname":"Tenejapan",
    "gn:country_code":"MX",
    "gn:dem":42,
    "gn:feature_class":"P",
    "gn:feature_code":"PPL",
    "gn:name":"Tenejapan",
    "gn:population":0,
    "gn:timezone":"America/Mexico_City",
    "iso:country":"MX",
    "name:spa_x_preferred":[
        "Tenejapan"
    ],
    "wof:name":"Tenejapan",
    "wof:placetype":"locality"
},
  "geometry": {"coordinates":[-95.38539,18.42874],"type":"Point"}
}