{
  "type": "Feature",
  "properties": {
    "gn:admin1_code":"32.0",
    "gn:admin2_code":"14.0",
    "gn:asciiname":"La Casa del Bajio",
    "gn:country_code":"MX",
    "gn:dem":1857,
    "gn:feature_class":"P",
    "gn:feature_code":"PPL",
    "gn:name":"La Casa del Bajio",
    "gn:population":0,
    "gn:timezone":"America/Mexico_City",
    "iso:country":"MX",
    "name:spa_x_preferred":[
        "La Casa del Bajio"
    ],
    "wof:name":"La Casa del Bajio",
    "wof:placetype":"locality"
},
  "geometry": {"coordinates":[-102.93237999999999,24.01394],"type":"Point"}
}