{
  "type": "Feature",
  "properties": {
    "gn:admin1_code":"18.0",
    "gn:admin2_code":"14.0",
    "gn:asciiname":"El Espino",
    "gn:country_code":"MX",
    "gn:dem":1188,
    "gn:feature_class":"P",
    "gn:feature_code":"PPL",
    "gn:name":"El Espino",
    "gn:population":0,
    "gn:timezone":"America/Mazatlan",
    "iso:country":"MX",
    "name:ceb_x_preferred":[
        "El Espino"
    ],
    "name:deu_x_preferred":[
        "El Espino"
    ],
    "name:ita_x_preferred":[
        "El Espino"
    ],
    "name:spa_x_preferred":[
        "El Espino"
    ],
    "name:srp_x_preferred":[
        "\u0415\u043b \u0415\u0441\u043f\u0438\u043d\u043e"
    ],
    "name:swe_x_preferred":[
        "El Espino"
    ],
    "wof:name":"El Espino",
    "wof:placetype":"locality"
},
  "geometry": {"coordinates":[-104.64297999999999,21.24335],"type":"Point"}
}