{
  "type": "Feature",
  "properties": {
    "gn:admin1_code":"20",
    "gn:admin2_code":"437.0",
    "gn:asciiname":"Carrizal",
    "gn:country_code":"MX",
    "gn:dem":1633,
    "gn:feature_class":"P",
    "gn:feature_code":"PPL",
    "gn:name":"Carrizal",
    "gn:population":111,
    "gn:timezone":"America/Mexico_City",
    "iso:country":"MX",
    "wof:name":"Carrizal",
    "wof:placetype":"locality",
    "wof:population":111
},
  "geometry": {"coordinates":[-96.12528,17.08972],"type":"Point"}
}