{
  "type": "Feature",
  "properties": {
    "gn:admin1_code":"13.0",
    "gn:asciiname":"Gumbho",
    "gn:country_code":"MX",
    "gn:dem":1884,
    "gn:feature_class":"P",
    "gn:feature_code":"PPL",
    "gn:name":"Gumbho",
    "gn:population":0,
    "gn:timezone":"America/Mexico_City",
    "iso:country":"MX",
    "name:spa_x_preferred":[
        "Gumbho"
    ],
    "wof:name":"Gumbho",
    "wof:placetype":"locality"
},
  "geometry": {"coordinates":[-99.70158000000001,20.48467],"type":"Point"}
}