{
  "type": "Feature",
  "properties": {
    "gn:admin1_code":"24",
    "gn:admin2_code":"18.0",
    "gn:asciiname":"Tantocoy Uno",
    "gn:country_code":"MX",
    "gn:dem":345,
    "gn:feature_class":"P",
    "gn:feature_code":"PPL",
    "gn:name":"Tantocoy Uno",
    "gn:population":925,
    "gn:timezone":"America/Mexico_City",
    "iso:country":"MX",
    "wof:name":"Tantocoy Uno",
    "wof:placetype":"locality",
    "wof:population":925
},
  "geometry": {"coordinates":[-98.99139,21.53083],"type":"Point"}
}