{
  "type": "Feature",
  "properties": {
    "gn:admin1_code":"16",
    "gn:admin2_code":"49",
    "gn:asciiname":"Las Charandas (La Zarcita)",
    "gn:country_code":"MX",
    "gn:dem":1953,
    "gn:feature_class":"P",
    "gn:feature_code":"PPL",
    "gn:name":"Las Charandas (La Zarcita)",
    "gn:population":10,
    "gn:timezone":"America/Mexico_City",
    "iso:country":"MX",
    "wof:name":"Las Charandas (La Zarcita)",
    "wof:placetype":"locality",
    "wof:population":10
},
  "geometry": {"coordinates":[-101.08889000000001,19.43556],"type":"Point"}
}