{
  "type": "Feature",
  "properties": {
    "gn:admin1_code":"1.0",
    "gn:admin2_code":"7.0",
    "gn:asciiname":"Presa San Elias",
    "gn:country_code":"MX",
    "gn:dem":1996,
    "gn:feature_class":"P",
    "gn:feature_code":"PPL",
    "gn:name":"Presa San El\u00edas",
    "gn:population":0,
    "gn:timezone":"America/Mexico_City",
    "iso:country":"MX",
    "name:spa_x_preferred":[
        "Presa San El\u00edas"
    ],
    "wof:name":"Presa San Elias",
    "wof:placetype":"locality"
},
  "geometry": {"coordinates":[-102.33884999999999,22.21944],"type":"Point"}
}