{
  "type": "Feature",
  "properties": {
    "gn:admin1_code":"8",
    "gn:admin2_code":"2",
    "gn:asciiname":"Los Garcia (El Bordo)",
    "gn:country_code":"MX",
    "gn:dem":613,
    "gn:feature_class":"P",
    "gn:feature_code":"PPL",
    "gn:name":"Los Garc\u00eda (El Bordo)",
    "gn:population":14,
    "gn:timezone":"America/Mexico_City",
    "iso:country":"MX",
    "name:und_x_variant":[
        "Los Garc\u00eda (El Bordo)"
    ],
    "wof:name":"Los Garcia (El Bordo)",
    "wof:placetype":"locality",
    "wof:population":14
},
  "geometry": {"coordinates":[-103.52028,19.20806],"type":"Point"}
}