{
  "type": "Feature",
  "properties": {
    "gn:admin1_code":"6.0",
    "gn:admin2_code":"19.0",
    "gn:asciiname":"El Arbolito",
    "gn:country_code":"MX",
    "gn:dem":1661,
    "gn:feature_class":"P",
    "gn:feature_code":"PPL",
    "gn:name":"El Arbolito",
    "gn:population":0,
    "gn:timezone":"America/Chihuahua",
    "iso:country":"MX",
    "name:spa_x_preferred":[
        "El Arbolito"
    ],
    "wof:name":"El Arbolito",
    "wof:placetype":"locality"
},
  "geometry": {"coordinates":[-106.36309,28.86079],"type":"Point"}
}