{
  "type": "Feature",
  "properties": {
    "gn:admin1_code":"12.0",
    "gn:admin2_code":"11.0",
    "gn:asciiname":"Huerta de Hugo Galeana",
    "gn:country_code":"MX",
    "gn:dem":25,
    "gn:feature_class":"P",
    "gn:feature_code":"PPL",
    "gn:name":"Huerta de Hugo Galeana",
    "gn:population":0,
    "gn:timezone":"America/Mexico_City",
    "iso:country":"MX",
    "name:spa_x_preferred":[
        "Huerta de Hugo Galeana"
    ],
    "name:spa_x_variant":[
        "Palo Verde"
    ],
    "wof:name":"Huerta de Hugo Galeana",
    "wof:placetype":"locality"
},
  "geometry": {"coordinates":[-100.36425,17.11978],"type":"Point"}
}