{
  "type": "Feature",
  "properties": {
    "gn:admin1_code":"19",
    "gn:admin2_code":"7.0",
    "gn:asciiname":"Los Cuartitos",
    "gn:country_code":"MX",
    "gn:dem":990,
    "gn:feature_class":"P",
    "gn:feature_code":"PPL",
    "gn:name":"Los Cuartitos",
    "gn:population":0,
    "gn:timezone":"America/Monterrey",
    "iso:country":"MX",
    "name:spa_x_preferred":[
        "Los Cuartitos"
    ],
    "name:spa_x_variant":[
        "Cuartitos"
    ],
    "wof:name":"Los Cuartitos",
    "wof:placetype":"locality"
},
  "geometry": {"coordinates":[-99.78484,24.15614],"type":"Point"}
}