{
  "type": "Feature",
  "properties": {
    "gn:admin1_code":"12",
    "gn:admin2_code":"28.0",
    "gn:asciiname":"Los Magueyes",
    "gn:country_code":"MX",
    "gn:dem":1457,
    "gn:feature_class":"P",
    "gn:feature_code":"PPL",
    "gn:name":"Los Magueyes",
    "gn:population":772,
    "gn:timezone":"America/Mexico_City",
    "iso:country":"MX",
    "wof:name":"Los Magueyes",
    "wof:placetype":"locality",
    "wof:population":772
},
  "geometry": {"coordinates":[-99.17167000000001,17.62806],"type":"Point"}
}