{
  "type": "Feature",
  "properties": {
    "gn:admin1_code":"12.0",
    "gn:admin2_code":"11.0",
    "gn:asciiname":"Rio Santiago",
    "gn:country_code":"MX",
    "gn:dem":694,
    "gn:feature_class":"P",
    "gn:feature_code":"PPL",
    "gn:name":"R\u00edo Santiago",
    "gn:population":0,
    "gn:timezone":"America/Mexico_City",
    "iso:country":"MX",
    "name:ceb_x_preferred":[
        "Rio Santiago"
    ],
    "name:spa_x_preferred":[
        "R\u00edo Santiago"
    ],
    "name:swe_x_preferred":[
        "Rio Santiago"
    ],
    "name:und_x_variant":[
        "Los Llanos de Santiago"
    ],
    "wof:name":"Rio Santiago",
    "wof:placetype":"locality"
},
  "geometry": {"coordinates":[-100.31729,17.25345],"type":"Point"}
}