{
  "type": "Feature",
  "properties": {
    "gn:admin1_code":"6",
    "gn:admin2_code":"40.0",
    "gn:asciiname":"Duarte",
    "gn:country_code":"MX",
    "gn:dem":2167,
    "gn:feature_class":"P",
    "gn:feature_code":"PPL",
    "gn:name":"Duarte",
    "gn:population":0,
    "gn:timezone":"America/Chihuahua",
    "iso:country":"MX",
    "name:spa_x_preferred":[
        "Duarte"
    ],
    "wof:name":"Duarte",
    "wof:placetype":"locality"
},
  "geometry": {"coordinates":[-108.30239,28.94197],"type":"Point"}
}