{
  "type": "Feature",
  "properties": {
    "gn:admin1_code":"20",
    "gn:admin2_code":"10.0",
    "gn:asciiname":"Las Palmitas",
    "gn:country_code":"MX",
    "gn:dem":237,
    "gn:feature_class":"P",
    "gn:feature_code":"PPL",
    "gn:name":"Las Palmitas",
    "gn:population":137,
    "gn:timezone":"America/Mexico_City",
    "iso:country":"MX",
    "name:ceb_x_preferred":[
        "Las Palmitas"
    ],
    "name:ita_x_preferred":[
        "Las Palmitas"
    ],
    "name:spa_x_preferred":[
        "Las Palmitas"
    ],
    "name:srp_x_preferred":[
        "\u041b\u0430\u0441 \u041f\u0430\u043b\u043c\u0438\u0442\u0430\u0441"
    ],
    "name:swe_x_preferred":[
        "Las Palmitas"
    ],
    "wof:name":"Las Palmitas",
    "wof:placetype":"locality",
    "wof:population":137
},
  "geometry": {"coordinates":[-95.05611,16.81861],"type":"Point"}
}