{
  "type": "Feature",
  "properties": {
    "gn:admin1_code":"11.0",
    "gn:admin2_code":"3.0",
    "gn:asciiname":"Pozo de los Liceas",
    "gn:country_code":"MX",
    "gn:dem":2012,
    "gn:feature_class":"P",
    "gn:feature_code":"PPL",
    "gn:name":"Pozo de los Liceas",
    "gn:population":0,
    "gn:timezone":"America/Mexico_City",
    "iso:country":"MX",
    "name:spa_x_preferred":[
        "Pozo de los Liceas"
    ],
    "wof:name":"Pozo de los Liceas",
    "wof:placetype":"locality"
},
  "geometry": {"coordinates":[-100.62842000000001,21.03164],"type":"Point"}
}