{
  "type": "Feature",
  "properties": {
    "gn:admin1_code":"15.0",
    "gn:admin2_code":"99.0",
    "gn:asciiname":"Pimiango",
    "gn:country_code":"MX",
    "gn:dem":2253,
    "gn:feature_class":"P",
    "gn:feature_code":"PPL",
    "gn:name":"Pimiango",
    "gn:population":0,
    "gn:timezone":"America/Mexico_City",
    "iso:country":"MX",
    "name:spa_x_preferred":[
        "Pimiango"
    ],
    "wof:name":"Pimiango",
    "wof:placetype":"locality"
},
  "geometry": {"coordinates":[-98.90430000000001,19.44055],"type":"Point"}
}