{
  "type": "Feature",
  "properties": {
    "gn:admin1_code":"12",
    "gn:admin2_code":"73.0",
    "gn:asciiname":"El Arrayan",
    "gn:country_code":"MX",
    "gn:dem":687,
    "gn:feature_class":"P",
    "gn:feature_code":"PPL",
    "gn:name":"El Array\u00e1n",
    "gn:population":0,
    "gn:timezone":"America/Mexico_City",
    "iso:country":"MX",
    "name:spa_x_preferred":[
        "El Array\u00e1n"
    ],
    "wof:name":"El Arrayan",
    "wof:placetype":"locality"
},
  "geometry": {"coordinates":[-101.24853,18.29755],"type":"Point"}
}