{
  "type": "Feature",
  "properties": {
    "gn:admin1_code":"17",
    "gn:admin2_code":"11.0",
    "gn:asciiname":"Colonia Agua Fria",
    "gn:country_code":"MX",
    "gn:dem":1330,
    "gn:feature_class":"P",
    "gn:feature_code":"PPL",
    "gn:name":"Colonia Agua Fr\u00eda",
    "gn:population":65,
    "gn:timezone":"America/Mexico_City",
    "iso:country":"MX",
    "name:und_x_variant":[
        "Colonia Agua Fr\u00eda"
    ],
    "wof:name":"Colonia Agua Fria",
    "wof:placetype":"locality",
    "wof:population":65
},
  "geometry": {"coordinates":[-99.16556,18.86972],"type":"Point"}
}