{
  "type": "Feature",
  "properties": {
    "gn:admin1_code":"28.0",
    "gn:admin2_code":"43.0",
    "gn:asciiname":"El Peluquero",
    "gn:country_code":"MX",
    "gn:dem":142,
    "gn:feature_class":"P",
    "gn:feature_code":"PPL",
    "gn:name":"El Peluquero",
    "gn:population":0,
    "gn:timezone":"America/Monterrey",
    "iso:country":"MX",
    "name:spa_x_preferred":[
        "El Peluquero"
    ],
    "wof:name":"El Peluquero",
    "wof:placetype":"locality"
},
  "geometry": {"coordinates":[-98.99038,23.06808],"type":"Point"}
}