{
  "type": "Feature",
  "properties": {
    "gn:admin1_code":"6",
    "gn:admin2_code":"67.0",
    "gn:asciiname":"Najareno",
    "gn:cc2":"MX",
    "gn:country_code":"MX",
    "gn:dem":1363,
    "gn:feature_class":"P",
    "gn:feature_code":"PPL",
    "gn:name":"Najare\u00f1o",
    "gn:population":0,
    "gn:timezone":"America/Chihuahua",
    "iso:country":"MX",
    "name:und_x_variant":[
        "Naranje\u00f1o",
        "Najare\u00f1o"
    ],
    "wof:name":"Najareno",
    "wof:placetype":"locality"
},
  "geometry": {"coordinates":[-105.83333,27.46667],"type":"Point"}
}