{
  "type": "Feature",
  "properties": {
    "gn:admin1_code":"14",
    "gn:admin2_code":"31.0",
    "gn:asciiname":"Tepizuac",
    "gn:country_code":"MX",
    "gn:dem":1964,
    "gn:feature_class":"P",
    "gn:feature_code":"PPL",
    "gn:name":"Tepizuac",
    "gn:population":516,
    "gn:timezone":"America/Mexico_City",
    "iso:country":"MX",
    "wof:name":"Tepizuac",
    "wof:placetype":"locality",
    "wof:population":516
},
  "geometry": {"coordinates":[-103.63939000000001,21.62506],"type":"Point"}
}