{
  "type": "Feature",
  "properties": {
    "gn:admin1_code":"3",
    "gn:admin2_code":"8.0",
    "gn:asciiname":"El Encino",
    "gn:country_code":"MX",
    "gn:dem":407,
    "gn:feature_class":"P",
    "gn:feature_code":"PPL",
    "gn:name":"El Encino",
    "gn:population":0,
    "gn:timezone":"America/Mazatlan",
    "iso:country":"MX",
    "name:spa_x_preferred":[
        "El Encino"
    ],
    "wof:name":"El Encino",
    "wof:placetype":"locality"
},
  "geometry": {"coordinates":[-109.82470000000001,23.05722],"type":"Point"}
}