{
  "type": "Feature",
  "properties": {
    "gn:admin1_code":"14",
    "gn:admin2_code":"120.0",
    "gn:asciiname":"Rancho del Angel",
    "gn:country_code":"MX",
    "gn:dem":1591,
    "gn:feature_class":"P",
    "gn:feature_code":"PPL",
    "gn:name":"Rancho del \u00c1ngel",
    "gn:population":6,
    "gn:timezone":"America/Mexico_City",
    "iso:country":"MX",
    "name:und_x_variant":[
        "Rancho del \u00c1ngel"
    ],
    "wof:name":"Rancho del Angel",
    "wof:placetype":"locality",
    "wof:population":6
},
  "geometry": {"coordinates":[-103.42749999999999,20.82417],"type":"Point"}
}