{
  "type": "Feature",
  "properties": {
    "gn:admin1_code":"11.0",
    "gn:asciiname":"La Concha",
    "gn:country_code":"MX",
    "gn:dem":1797,
    "gn:feature_class":"P",
    "gn:feature_code":"PPL",
    "gn:name":"La Concha",
    "gn:population":0,
    "gn:timezone":"America/Mexico_City",
    "iso:country":"MX",
    "name:ceb_x_preferred":[
        "La Concha"
    ],
    "name:spa_x_preferred":[
        "La Concha"
    ],
    "name:swe_x_preferred":[
        "La Concha"
    ],
    "wof:name":"La Concha",
    "wof:placetype":"locality"
},
  "geometry": {"coordinates":[-101.76434999999999,20.91079],"type":"Point"}
}