{
  "type": "Feature",
  "properties": {
    "gn:admin1_code":"32",
    "gn:admin2_code":"55.0",
    "gn:asciiname":"General Francisco Murguia",
    "gn:country_code":"MX",
    "gn:dem":2042,
    "gn:feature_class":"P",
    "gn:feature_code":"PPL",
    "gn:name":"General Francisco Murgu\u00eda",
    "gn:population":0,
    "gn:timezone":"America/Mexico_City",
    "iso:country":"MX",
    "name:spa_x_preferred":[
        "General Francisco Murgu\u00eda"
    ],
    "name:spa_x_variant":[
        "Francisco Murgu\u00eda"
    ],
    "wof:name":"General Francisco Murguia",
    "wof:placetype":"locality"
},
  "geometry": {"coordinates":[-102.77414,22.48754],"type":"Point"}
}