{
  "type": "Feature",
  "properties": {
    "gn:admin1_code":"24",
    "gn:admin2_code":"13.0",
    "gn:asciiname":"Reforma",
    "gn:country_code":"MX",
    "gn:dem":433,
    "gn:feature_class":"P",
    "gn:feature_code":"PPL",
    "gn:name":"Reforma",
    "gn:population":0,
    "gn:timezone":"America/Mexico_City",
    "iso:country":"MX",
    "wof:name":"Reforma",
    "wof:placetype":"locality"
},
  "geometry": {"coordinates":[-99.21666999999999,22.05],"type":"Point"}
}