{
  "type": "Feature",
  "properties": {
    "gn:admin1_code":"7.0",
    "gn:admin2_code":"22.0",
    "gn:asciiname":"Garza",
    "gn:country_code":"MX",
    "gn:dem":328,
    "gn:feature_class":"P",
    "gn:feature_code":"PPL",
    "gn:name":"Garza",
    "gn:population":0,
    "gn:timezone":"America/Monterrey",
    "iso:country":"MX",
    "name:ast_x_preferred":[
        "Garza"
    ],
    "name:ceb_x_preferred":[
        "Garza"
    ],
    "name:ces_x_preferred":[
        "Garza"
    ],
    "name:deu_x_preferred":[
        "Garza"
    ],
    "name:fra_x_preferred":[
        "Garza"
    ],
    "name:ita_x_preferred":[
        "Garza"
    ],
    "name:nld_x_preferred":[
        "Garza"
    ],
    "name:rus_x_preferred":[
        "\u0413\u0430\u0440\u0441\u0430"
    ],
    "name:spa_x_preferred":[
        "Garza"
    ],
    "name:swe_x_preferred":[
        "Garza"
    ],
    "wof:name":"Garza",
    "wof:placetype":"locality"
},
  "geometry": {"coordinates":[-100.79458,28.47404],"type":"Point"}
}