{
  "type": "Feature",
  "properties": {
    "gn:admin1_code":"7",
    "gn:admin2_code":"30.0",
    "gn:asciiname":"Rancho Ledesma",
    "gn:country_code":"MX",
    "gn:dem":1822,
    "gn:feature_class":"P",
    "gn:feature_code":"PPL",
    "gn:name":"Rancho Ledesma",
    "gn:population":0,
    "gn:timezone":"America/Monterrey",
    "iso:country":"MX",
    "wof:name":"Rancho Ledesma",
    "wof:placetype":"locality"
},
  "geometry": {"coordinates":[-100.93333,24.86667000000001],"type":"Point"}
}