{
  "type": "Feature",
  "properties": {
    "gn:admin1_code":"14.0",
    "gn:admin2_code":"18.0",
    "gn:asciiname":"El Sartenejo",
    "gn:country_code":"MX",
    "gn:dem":1544,
    "gn:feature_class":"P",
    "gn:feature_code":"PPL",
    "gn:name":"El Sartenejo",
    "gn:population":0,
    "gn:timezone":"America/Mexico_City",
    "iso:country":"MX",
    "name:spa_x_preferred":[
        "El Sartenejo"
    ],
    "wof:name":"El Sartenejo",
    "wof:placetype":"locality"
},
  "geometry": {"coordinates":[-102.64297999999999,20.37994],"type":"Point"}
}