{
  "type": "Feature",
  "properties": {
    "gn:admin1_code":"21",
    "gn:admin2_code":"45.0",
    "gn:asciiname":"Miguel Velazquez",
    "gn:country_code":"MX",
    "gn:dem":2661,
    "gn:feature_class":"P",
    "gn:feature_code":"PPL",
    "gn:name":"Miguel Vel\u00e1zquez",
    "gn:population":8,
    "gn:timezone":"America/Mexico_City",
    "iso:country":"MX",
    "name:und_x_variant":[
        "Miguel Vel\u00e1zquez"
    ],
    "wof:name":"Miguel Velazquez",
    "wof:placetype":"locality",
    "wof:population":8
},
  "geometry": {"coordinates":[-97.42744,18.99098],"type":"Point"}
}