{
  "type": "Feature",
  "properties": {
    "gn:admin1_code":"6.0",
    "gn:admin2_code":"37.0",
    "gn:asciiname":"La Leona",
    "gn:country_code":"MX",
    "gn:dem":1356,
    "gn:feature_class":"P",
    "gn:feature_code":"PPL",
    "gn:name":"La Leona",
    "gn:population":0,
    "gn:timezone":"America/Ojinaga",
    "iso:country":"MX",
    "name:spa_x_preferred":[
        "La Leona"
    ],
    "wof:name":"La Leona",
    "wof:placetype":"locality"
},
  "geometry": {"coordinates":[-106.41254000000001,31.20715],"type":"Point"}
}