{
  "type": "Feature",
  "properties": {
    "gn:admin1_code":"2",
    "gn:admin2_code":"1.0",
    "gn:asciiname":"El Descanso",
    "gn:country_code":"MX",
    "gn:dem":538,
    "gn:feature_class":"P",
    "gn:feature_code":"PPL",
    "gn:name":"El Descanso",
    "gn:population":0,
    "gn:timezone":"America/Tijuana",
    "iso:country":"MX",
    "wof:name":"El Descanso",
    "wof:placetype":"locality"
},
  "geometry": {"coordinates":[-114.74245000000001,29.74951],"type":"Point"}
}