{
  "type": "Feature",
  "properties": {
    "gn:admin1_code":"16",
    "gn:admin2_code":"97",
    "gn:asciiname":"La Capilla",
    "gn:country_code":"MX",
    "gn:dem":1522,
    "gn:feature_class":"P",
    "gn:feature_code":"PPL",
    "gn:name":"La Capilla",
    "gn:population":17,
    "gn:timezone":"America/Mexico_City",
    "iso:country":"MX",
    "wof:name":"La Capilla",
    "wof:placetype":"locality",
    "wof:population":17
},
  "geometry": {"coordinates":[-101.6125,18.99778],"type":"Point"}
}