{
  "type": "Feature",
  "properties": {
    "gn:admin1_code":"11.0",
    "gn:admin2_code":"33.0",
    "gn:asciiname":"El Porvenir",
    "gn:country_code":"MX",
    "gn:dem":1987,
    "gn:feature_class":"P",
    "gn:feature_code":"PPL",
    "gn:name":"El Porvenir",
    "gn:population":0,
    "gn:timezone":"America/Mexico_City",
    "iso:country":"MX",
    "name:spa_x_preferred":[
        "El Porvenir"
    ],
    "wof:name":"El Porvenir",
    "wof:placetype":"locality"
},
  "geometry": {"coordinates":[-100.57237000000001,21.2864],"type":"Point"}
}