{
  "type": "Feature",
  "properties": {
    "gn:admin1_code":"14.0",
    "gn:asciiname":"El Tianguillo",
    "gn:country_code":"MX",
    "gn:dem":1885,
    "gn:feature_class":"P",
    "gn:feature_code":"PPL",
    "gn:name":"El Tianguillo",
    "gn:population":0,
    "gn:timezone":"America/Mexico_City",
    "iso:country":"MX",
    "name:spa_x_preferred":[
        "El Tianguillo"
    ],
    "wof:name":"El Tianguillo",
    "wof:placetype":"locality"
},
  "geometry": {"coordinates":[-102.24694,21.16972],"type":"Point"}
}