{
  "type": "Feature",
  "properties": {
    "gn:admin1_code":"10",
    "gn:admin2_code":"14.0",
    "gn:asciiname":"Puerto el Colorado",
    "gn:country_code":"MX",
    "gn:dem":1929,
    "gn:feature_class":"P",
    "gn:feature_code":"PPL",
    "gn:name":"Puerto el Colorado",
    "gn:population":0,
    "gn:timezone":"America/Monterrey",
    "iso:country":"MX",
    "name:spa_x_preferred":[
        "Puerto el Colorado"
    ],
    "wof:name":"Puerto el Colorado",
    "wof:placetype":"locality"
},
  "geometry": {"coordinates":[-104.6375,23.20683],"type":"Point"}
}