{
  "type": "Feature",
  "properties": {
    "gn:admin1_code":"13",
    "gn:admin2_code":"60",
    "gn:asciiname":"El Tramo",
    "gn:country_code":"MX",
    "gn:dem":1194,
    "gn:feature_class":"P",
    "gn:feature_code":"PPL",
    "gn:name":"El Tramo",
    "gn:population":37,
    "gn:timezone":"America/Mexico_City",
    "iso:country":"MX",
    "wof:name":"El Tramo",
    "wof:placetype":"locality",
    "wof:population":37
},
  "geometry": {"coordinates":[-98.22389,20.36194],"type":"Point"}
}