{
  "type": "Feature",
  "properties": {
    "gn:admin1_code":"28.0",
    "gn:admin2_code":"2.0",
    "gn:asciiname":"El Paquete",
    "gn:country_code":"MX",
    "gn:dem":144,
    "gn:feature_class":"P",
    "gn:feature_code":"PPL",
    "gn:name":"El Paquete",
    "gn:population":0,
    "gn:timezone":"America/Monterrey",
    "iso:country":"MX",
    "name:spa_x_preferred":[
        "El Paquete"
    ],
    "wof:name":"El Paquete",
    "wof:placetype":"locality"
},
  "geometry": {"coordinates":[-98.07167,23.30917],"type":"Point"}
}