{
  "type": "Feature",
  "properties": {
    "gn:admin1_code":"12",
    "gn:admin2_code":"44.0",
    "gn:asciiname":"Lagunilla",
    "gn:country_code":"MX",
    "gn:dem":1147,
    "gn:feature_class":"P",
    "gn:feature_code":"PPL",
    "gn:name":"Lagunilla",
    "gn:population":342,
    "gn:timezone":"America/Mexico_City",
    "iso:country":"MX",
    "wof:name":"Lagunilla",
    "wof:placetype":"locality",
    "wof:population":342
},
  "geometry": {"coordinates":[-99.43277999999999,17.39306],"type":"Point"}
}