{
  "type": "Feature",
  "properties": {
    "gn:admin1_code":"12",
    "gn:admin2_code":"44.0",
    "gn:asciiname":"Lagunilla",
    "gn:country_code":"MX",
    "gn:dem":1147,
    "gn:feature_class":"P",
    "gn:feature_code":"PPL",
    "gn:name":"Lagunilla",
    "gn:population":342,
    "gn:timezone":"America/Mexico_City",
    "iso:country":"MX",
    "name:ara_x_preferred":[
        "\u0644\u0627\u063a\u0648\u0646\u064a\u0627"
    ],
    "name:arg_x_preferred":[
        "Lagunilla"
    ],
    "name:cat_x_preferred":[
        "Lagunilla"
    ],
    "name:ceb_x_preferred":[
        "Lagunilla"
    ],
    "name:eus_x_preferred":[
        "Lagunilla"
    ],
    "name:fra_x_preferred":[
        "Lagunilla"
    ],
    "name:haw_x_preferred":[
        "Lagunilla"
    ],
    "name:hun_x_preferred":[
        "Lagunilla"
    ],
    "name:ina_x_preferred":[
        "Lagunilla"
    ],
    "name:ita_x_preferred":[
        "Lagunilla"
    ],
    "name:kaz_x_preferred":[
        "\u041b\u0430\u0433\u0443\u043d\u0438\u043b\u044c\u044f"
    ],
    "name:msa_x_preferred":[
        "Lagunilla"
    ],
    "name:nld_x_preferred":[
        "Lagunilla"
    ],
    "name:oci_x_preferred":[
        "Lagunilla"
    ],
    "name:pol_x_preferred":[
        "Lagunilla"
    ],
    "name:por_x_preferred":[
        "Lagunilla"
    ],
    "name:rus_x_preferred":[
        "\u041b\u0430\u0433\u0443\u043d\u0438\u043b\u044c\u044f"
    ],
    "name:spa_x_preferred":[
        "Lagunilla"
    ],
    "name:swe_x_preferred":[
        "Lagunilla"
    ],
    "name:ukr_x_preferred":[
        "\u041b\u0430\u0433\u0443\u043d\u0456\u043b\u044c\u044f"
    ],
    "name:war_x_preferred":[
        "Lagunilla"
    ],
    "name:zho_x_preferred":[
        "\u62c9\u53e4\u5c3c\u5229\u4e9a"
    ],
    "wof:name":"Lagunilla",
    "wof:placetype":"locality",
    "wof:population":342
},
  "geometry": {"coordinates":[-99.43277999999999,17.39306],"type":"Point"}
}