{
  "type": "Feature",
  "properties": {
    "gn:admin1_code":"7.0",
    "gn:asciiname":"Santa Isidra",
    "gn:country_code":"MX",
    "gn:dem":762,
    "gn:feature_class":"P",
    "gn:feature_code":"PPL",
    "gn:name":"Santa Isidra",
    "gn:population":0,
    "gn:timezone":"America/Monterrey",
    "iso:country":"MX",
    "name:spa_x_preferred":[
        "Santa Isidra"
    ],
    "wof:name":"Santa Isidra",
    "wof:placetype":"locality"
},
  "geometry": {"coordinates":[-100.90044,25.92942],"type":"Point"}
}