{
  "type": "Feature",
  "properties": {
    "gn:admin1_code":"26.0",
    "gn:admin2_code":"3.0",
    "gn:asciiname":"Chino Gordo",
    "gn:country_code":"MX",
    "gn:dem":222,
    "gn:feature_class":"P",
    "gn:feature_code":"PPL",
    "gn:name":"Chino Gordo",
    "gn:population":2,
    "gn:timezone":"America/Hermosillo",
    "iso:country":"MX",
    "name:und_x_variant":[
        "Rancho Chino Gordo",
        "Chino Gordo"
    ],
    "wof:name":"Chino Gordo",
    "wof:placetype":"locality",
    "wof:population":2
},
  "geometry": {"coordinates":[-108.97114000000001,26.79794],"type":"Point"}
}