{
  "type": "Feature",
  "properties": {
    "gn:admin1_code":"6.0",
    "gn:admin2_code":"61.0",
    "gn:asciiname":"El Puerto",
    "gn:country_code":"MX",
    "gn:dem":1667,
    "gn:feature_class":"P",
    "gn:feature_code":"PPL",
    "gn:name":"El Puerto",
    "gn:population":0,
    "gn:timezone":"America/Chihuahua",
    "iso:country":"MX",
    "name:spa_x_preferred":[
        "El Puerto"
    ],
    "wof:name":"El Puerto",
    "wof:placetype":"locality"
},
  "geometry": {"coordinates":[-106.28452,27.94421],"type":"Point"}
}