{
  "type": "Feature",
  "properties": {
    "gn:admin1_code":"14.0",
    "gn:admin2_code":"104.0",
    "gn:asciiname":"Barranca de Cardos",
    "gn:country_code":"MX",
    "gn:dem":1466,
    "gn:feature_class":"P",
    "gn:feature_code":"PPL",
    "gn:name":"Barranca de Cardos",
    "gn:population":0,
    "gn:timezone":"America/Mexico_City",
    "iso:country":"MX",
    "name:spa_x_preferred":[
        "Barranca de Cardos"
    ],
    "wof:name":"Barranca de Cardos",
    "wof:placetype":"locality"
},
  "geometry": {"coordinates":[-103.40501,22.08894],"type":"Point"}
}