{
  "type": "Feature",
  "properties": {
    "gn:admin1_code":"26",
    "gn:admin2_code":"3.0",
    "gn:asciiname":"Quintera",
    "gn:country_code":"MX",
    "gn:dem":836,
    "gn:feature_class":"P",
    "gn:feature_code":"PPL",
    "gn:name":"Quintera",
    "gn:population":0,
    "gn:timezone":"America/Hermosillo",
    "iso:country":"MX",
    "wof:name":"Quintera",
    "wof:placetype":"locality"
},
  "geometry": {"coordinates":[-109.03333000000001,27.03333],"type":"Point"}
}