{
  "type": "Feature",
  "properties": {
    "gn:admin1_code":"26.0",
    "gn:admin2_code":"52.0",
    "gn:asciiname":"Maguechi de Chayo",
    "gn:country_code":"MX",
    "gn:dem":1743,
    "gn:feature_class":"P",
    "gn:feature_code":"PPL",
    "gn:name":"Maguechi de Chayo",
    "gn:population":0,
    "gn:timezone":"America/Chihuahua",
    "iso:country":"MX",
    "name:spa_x_preferred":[
        "Maguechi de Chayo"
    ],
    "wof:name":"Maguechi de Chayo",
    "wof:placetype":"locality"
},
  "geometry": {"coordinates":[-108.62302,28.58895],"type":"Point"}
}