{
  "type": "Feature",
  "properties": {
    "gn:admin1_code":"28",
    "gn:admin2_code":"33",
    "gn:asciiname":"Jose Bravo",
    "gn:country_code":"MX",
    "gn:dem":18,
    "gn:feature_class":"P",
    "gn:feature_code":"PPL",
    "gn:name":"Jos\u00e9 Bravo",
    "gn:population":14,
    "gn:timezone":"America/Monterrey",
    "iso:country":"MX",
    "name:und_x_variant":[
        "Jos\u00e9 Bravo"
    ],
    "wof:name":"Jose Bravo",
    "wof:placetype":"locality",
    "wof:population":14
},
  "geometry": {"coordinates":[-97.96861,25.51389],"type":"Point"}
}