{
  "type": "Feature",
  "properties": {
    "gn:admin1_code":"21",
    "gn:admin2_code":"115.0",
    "gn:asciiname":"Villa del Alto (Colonia Nueva)",
    "gn:country_code":"MX",
    "gn:dem":2256,
    "gn:feature_class":"P",
    "gn:feature_code":"PPL",
    "gn:name":"Villa del Alto (Colonia Nueva)",
    "gn:population":133,
    "gn:timezone":"America/Mexico_City",
    "iso:country":"MX",
    "wof:name":"Villa del Alto (Colonia Nueva)",
    "wof:placetype":"locality",
    "wof:population":133
},
  "geometry": {"coordinates":[-97.59056,18.90139],"type":"Point"}
}