{
  "type": "Feature",
  "properties": {
    "gn:admin1_code":"19",
    "gn:admin2_code":"38.0",
    "gn:asciiname":"El Colorado",
    "gn:country_code":"MX",
    "gn:dem":433,
    "gn:feature_class":"P",
    "gn:feature_code":"PPL",
    "gn:name":"El Colorado",
    "gn:population":0,
    "gn:timezone":"America/Monterrey",
    "iso:country":"MX",
    "name:deu_x_preferred":[
        "El Colorado"
    ],
    "name:fra_x_preferred":[
        "El Colorado"
    ],
    "name:nld_x_preferred":[
        "El Colorado"
    ],
    "name:pol_x_preferred":[
        "El Colorado"
    ],
    "name:por_x_preferred":[
        "El Colorado"
    ],
    "name:spa_x_preferred":[
        "El Colorado"
    ],
    "wof:name":"El Colorado",
    "wof:placetype":"locality"
},
  "geometry": {"coordinates":[-99.68624,25.09346],"type":"Point"}
}