{
  "type": "Feature",
  "properties": {
    "gn:admin1_code":"16",
    "gn:admin2_code":"69.0",
    "gn:asciiname":"Ticuitaco",
    "gn:country_code":"MX",
    "gn:dem":1724,
    "gn:feature_class":"P",
    "gn:feature_code":"PPL",
    "gn:name":"Ticuitaco",
    "gn:population":0,
    "gn:timezone":"America/Mexico_City",
    "iso:country":"MX",
    "name:spa_x_preferred":[
        "Ticuitaco"
    ],
    "name:spa_x_variant":[
        "Tocuitaco"
    ],
    "wof:name":"Ticuitaco",
    "wof:placetype":"locality"
},
  "geometry": {"coordinates":[-102.0081,20.2753],"type":"Point"}
}