{
  "type": "Feature",
  "properties": {
    "gn:admin1_code":"12",
    "gn:admin2_code":"35.0",
    "gn:asciiname":"Zacacoyuca",
    "gn:country_code":"MX",
    "gn:dem":907,
    "gn:feature_class":"P",
    "gn:feature_code":"PPL",
    "gn:name":"Zacacoyuca",
    "gn:population":0,
    "gn:timezone":"America/Mexico_City",
    "iso:country":"MX",
    "name:spa_x_preferred":[
        "Zacacoyuca"
    ],
    "wof:name":"Zacacoyuca",
    "wof:placetype":"locality"
},
  "geometry": {"coordinates":[-99.52763,18.25029],"type":"Point"}
}