{
  "type": "Feature",
  "properties": {
    "gn:admin1_code":"25",
    "gn:admin2_code":"17.0",
    "gn:asciiname":"La Huerta",
    "gn:country_code":"MX",
    "gn:dem":247,
    "gn:feature_class":"P",
    "gn:feature_code":"PPL",
    "gn:name":"La Huerta",
    "gn:population":147,
    "gn:timezone":"America/Mazatlan",
    "iso:country":"MX",
    "name:ceb_x_preferred":[
        "La Huerta"
    ],
    "name:spa_x_preferred":[
        "La Huerta"
    ],
    "name:swe_x_preferred":[
        "La Huerta"
    ],
    "wof:name":"La Huerta",
    "wof:placetype":"locality",
    "wof:population":147
},
  "geometry": {"coordinates":[-107.87139000000001,25.97472],"type":"Point"}
}