{
  "type": "Feature",
  "properties": {
    "gn:admin1_code":"24",
    "gn:asciiname":"Los Alemanes",
    "gn:country_code":"MX",
    "gn:dem":1977,
    "gn:feature_class":"P",
    "gn:feature_code":"PPL",
    "gn:name":"Los Alemanes",
    "gn:population":0,
    "gn:timezone":"America/Mexico_City",
    "iso:country":"MX",
    "wof:name":"Los Alemanes",
    "wof:placetype":"locality"
},
  "geometry": {"coordinates":[-101.86708,23.44092],"type":"Point"}
}