{
  "type": "Feature",
  "properties": {
    "gn:admin1_code":"30",
    "gn:admin2_code":"129",
    "gn:asciiname":"Los Costenos",
    "gn:country_code":"MX",
    "gn:dem":50,
    "gn:feature_class":"P",
    "gn:feature_code":"PPL",
    "gn:name":"Los Coste\u00f1os",
    "gn:population":12,
    "gn:timezone":"America/Mexico_City",
    "iso:country":"MX",
    "name:und_x_variant":[
        "Los Coste\u00f1os"
    ],
    "wof:name":"Los Costenos",
    "wof:placetype":"locality",
    "wof:population":12
},
  "geometry": {"coordinates":[-98.38556,21.36667000000001],"type":"Point"}
}