{
  "type": "Feature",
  "properties": {
    "gn:admin1_code":"16",
    "gn:admin2_code":"82.0",
    "gn:asciiname":"San Jose Grande",
    "gn:country_code":"MX",
    "gn:dem":1870,
    "gn:feature_class":"P",
    "gn:feature_code":"PPL",
    "gn:name":"San Jos\u00e9 Grande",
    "gn:population":515,
    "gn:timezone":"America/Mexico_City",
    "iso:country":"MX",
    "name:und_x_variant":[
        "San Jos\u00e9 Grande"
    ],
    "wof:name":"San Jose Grande",
    "wof:placetype":"locality",
    "wof:population":515
},
  "geometry": {"coordinates":[-101.56056,19.22333],"type":"Point"}
}