{
  "type": "Feature",
  "properties": {
    "gn:admin1_code":"5.0",
    "gn:admin2_code":"99.0",
    "gn:asciiname":"Plan de Guadalupe",
    "gn:country_code":"MX",
    "gn:dem":649,
    "gn:feature_class":"P",
    "gn:feature_code":"PPL",
    "gn:name":"Plan de Guadalupe",
    "gn:population":0,
    "gn:timezone":"America/Mexico_City",
    "iso:country":"MX",
    "name:spa_x_preferred":[
        "Plan de Guadalupe"
    ],
    "wof:name":"Plan de Guadalupe",
    "wof:placetype":"locality"
},
  "geometry": {"coordinates":[-92.14861999999999,15.95425],"type":"Point"}
}