{
  "type": "Feature",
  "properties": {
    "gn:admin1_code":"28",
    "gn:admin2_code":"30.0",
    "gn:asciiname":"La Retama",
    "gn:country_code":"MX",
    "gn:dem":160,
    "gn:feature_class":"P",
    "gn:feature_code":"PPL",
    "gn:name":"La Retama",
    "gn:population":0,
    "gn:timezone":"America/Monterrey",
    "iso:country":"MX",
    "name:spa_x_preferred":[
        "La Retama"
    ],
    "wof:name":"La Retama",
    "wof:placetype":"locality"
},
  "geometry": {"coordinates":[-98.79503,23.99316],"type":"Point"}
}