{
  "type": "Feature",
  "properties": {
    "gn:admin1_code":"6",
    "gn:admin2_code":"19.0",
    "gn:asciiname":"Rancho las Elisas",
    "gn:country_code":"MX",
    "gn:dem":1611,
    "gn:feature_class":"P",
    "gn:feature_code":"PPL",
    "gn:name":"Rancho las Elisas",
    "gn:population":4,
    "gn:timezone":"America/Chihuahua",
    "iso:country":"MX",
    "wof:name":"Rancho las Elisas",
    "wof:placetype":"locality",
    "wof:population":4
},
  "geometry": {"coordinates":[-106.29243999999998,28.92462],"type":"Point"}
}