{
  "type": "Feature",
  "properties": {
    "gn:admin1_code":"4",
    "gn:admin2_code":"7.0",
    "gn:asciiname":"San Jose Victoria",
    "gn:country_code":"MX",
    "gn:dem":5,
    "gn:feature_class":"P",
    "gn:feature_code":"PPL",
    "gn:name":"San Jos\u00e9 Victoria",
    "gn:population":0,
    "gn:timezone":"America/Merida",
    "iso:country":"MX",
    "name:spa_x_preferred":[
        "San Jos\u00e9 Victoria"
    ],
    "wof:name":"San Jose Victoria",
    "wof:placetype":"locality"
},
  "geometry": {"coordinates":[-91.92816999999999,18.22803],"type":"Point"}
}