{
  "type": "Feature",
  "properties": {
    "gn:admin1_code":"32",
    "gn:admin2_code":"38.0",
    "gn:asciiname":"La Pachona",
    "gn:country_code":"MX",
    "gn:dem":2202,
    "gn:feature_class":"P",
    "gn:feature_code":"PPL",
    "gn:name":"La Pachona",
    "gn:population":0,
    "gn:timezone":"America/Mexico_City",
    "iso:country":"MX",
    "name:spa_x_preferred":[
        "La Pachona"
    ],
    "name:und_x_variant":[
        "Pachona"
    ],
    "wof:name":"La Pachona",
    "wof:placetype":"locality"
},
  "geometry": {"coordinates":[-101.73902,22.22768],"type":"Point"}
}