{
  "type": "Feature",
  "properties": {
    "gn:admin1_code":"10.0",
    "gn:admin2_code":"19.0",
    "gn:asciiname":"Bozos",
    "gn:country_code":"MX",
    "gn:dem":1573,
    "gn:feature_class":"P",
    "gn:feature_code":"PPL",
    "gn:name":"Bozos",
    "gn:population":0,
    "gn:timezone":"America/Monterrey",
    "iso:country":"MX",
    "name:und_x_variant":[
        "Bosas",
        "Bosos",
        "Bozos"
    ],
    "wof:name":"Bozos",
    "wof:placetype":"locality"
},
  "geometry": {"coordinates":[-106.03592999999999,24.65173],"type":"Point"}
}