{
  "type": "Feature",
  "properties": {
    "gn:admin1_code":"12",
    "gn:admin2_code":"54",
    "gn:asciiname":"Vallecitos",
    "gn:country_code":"MX",
    "gn:dem":1416,
    "gn:feature_class":"P",
    "gn:feature_code":"PPL",
    "gn:name":"Vallecitos",
    "gn:population":46,
    "gn:timezone":"America/Mexico_City",
    "iso:country":"MX",
    "name:ceb_x_preferred":[
        "Vallecitos"
    ],
    "name:swe_x_preferred":[
        "Vallecitos"
    ],
    "wof:name":"Vallecitos",
    "wof:placetype":"locality",
    "wof:population":46
},
  "geometry": {"coordinates":[-100.47049,17.92823],"type":"Point"}
}