{
  "type": "Feature",
  "properties": {
    "gn:admin1_code":"10",
    "gn:admin2_code":"17.0",
    "gn:asciiname":"Caseta Fiscal",
    "gn:country_code":"MX",
    "gn:dem":2187,
    "gn:feature_class":"P",
    "gn:feature_code":"PPL",
    "gn:name":"Caseta Fiscal",
    "gn:population":7,
    "gn:timezone":"America/Monterrey",
    "iso:country":"MX",
    "wof:name":"Caseta Fiscal",
    "wof:placetype":"locality",
    "wof:population":7
},
  "geometry": {"coordinates":[-106.0198,26.80032000000001],"type":"Point"}
}