{
  "type": "Feature",
  "properties": {
    "gn:admin1_code":"19.0",
    "gn:admin2_code":"50.0",
    "gn:asciiname":"Violeta",
    "gn:country_code":"MX",
    "gn:dem":247,
    "gn:feature_class":"P",
    "gn:feature_code":"PPL",
    "gn:name":"Violeta",
    "gn:population":0,
    "gn:timezone":"America/Monterrey",
    "iso:country":"MX",
    "name:cat_x_preferred":[
        "Violeta"
    ],
    "name:ceb_x_preferred":[
        "Violeta"
    ],
    "name:glg_x_preferred":[
        "Violeta"
    ],
    "name:por_x_preferred":[
        "Violeta"
    ],
    "name:spa_x_preferred":[
        "Violeta"
    ],
    "name:swe_x_preferred":[
        "Violeta"
    ],
    "wof:name":"Violeta",
    "wof:placetype":"locality"
},
  "geometry": {"coordinates":[-99.96211,26.41923],"type":"Point"}
}