{
  "type": "Feature",
  "properties": {
    "gn:admin1_code":"14.0",
    "gn:admin2_code":"53.0",
    "gn:asciiname":"Valenciana",
    "gn:country_code":"MX",
    "gn:dem":1955,
    "gn:feature_class":"P",
    "gn:feature_code":"PPL",
    "gn:name":"Valenciana",
    "gn:population":0,
    "gn:timezone":"America/Mexico_City",
    "iso:country":"MX",
    "name:ceb_x_preferred":[
        "Valenciana"
    ],
    "name:spa_x_preferred":[
        "Valenciana"
    ],
    "name:swe_x_preferred":[
        "Valenciana"
    ],
    "wof:name":"Valenciana",
    "wof:placetype":"locality"
},
  "geometry": {"coordinates":[-101.80543,21.43681],"type":"Point"}
}