{
  "type": "Feature",
  "properties": {
    "gn:admin1_code":"26",
    "gn:admin2_code":"26.0",
    "gn:asciiname":"Dos Arbolitos",
    "gn:country_code":"MX",
    "gn:dem":21,
    "gn:feature_class":"P",
    "gn:feature_code":"PPL",
    "gn:name":"Dos Arbolitos",
    "gn:population":53,
    "gn:timezone":"America/Hermosillo",
    "iso:country":"MX",
    "name:spa_x_preferred":[
        "Dos Arbolitos"
    ],
    "wof:name":"Dos Arbolitos",
    "wof:placetype":"locality",
    "wof:population":53
},
  "geometry": {"coordinates":[-109.64444,26.99944],"type":"Point"}
}