{
  "type": "Feature",
  "properties": {
    "iso:country":"MX",
    "name:spa_x_preferred":[
        "Barrio Lourdes"
    ],
    "name:unk_x_variant":[
        "Barrio Lourdes"
    ],
    "qs:gn_adm0_cc":"MX",
    "qs:gn_local":4014553,
    "qs:gn_nam_loc":"Chapala, Chapala, Jalisco, MX",
    "qs:gn_namadm1":"14",
    "qs:local_max":980,
    "qs:local_sum":1512,
    "qs:localhoods":5,
    "qs:name":"Barrio Lourdes",
    "qs:name_adm0":"M\u00e9xico",
    "qs:name_adm1":"Jalisco",
    "qs:name_adm2":"Chapala",
    "qs:name_local":"Chapala",
    "qs:photo_max":8,
    "qs:photo_sum":18,
    "qs:placetype":"Suburb",
    "qs:quad_count":5,
    "qs:woe_adm0":23424900,
    "qs:woe_adm1":2346277,
    "qs:woe_adm2":12600215,
    "qs:woe_lau":0,
    "qs:woe_local":115648,
    "qs:woe_ver":"7.10.0",
    "wof:lang":[
        "spa"
    ],
    "wof:name":"Barrio Lourdes",
    "wof:placetype":"neighbourhood"
},
  "geometry": {"coordinates":[-103.20373499999999,20.292541],"type":"Point"}
}