{
  "type": "Feature",
  "properties": {
    "gn:admin1_code":"24",
    "gn:admin2_code":"40.0",
    "gn:asciiname":"La Rosita",
    "gn:country_code":"MX",
    "gn:dem":34,
    "gn:feature_class":"P",
    "gn:feature_code":"PPL",
    "gn:name":"La Rosita",
    "gn:population":7,
    "gn:timezone":"America/Mexico_City",
    "iso:country":"MX",
    "wof:name":"La Rosita",
    "wof:placetype":"locality",
    "wof:population":7
},
  "geometry": {"coordinates":[-98.67667,22.06361],"type":"Point"}
}