{
  "type": "Feature",
  "properties": {
    "gn:admin1_code":"6",
    "gn:admin2_code":"10.0",
    "gn:asciiname":"Santa Eduviges",
    "gn:country_code":"MX",
    "gn:dem":1339,
    "gn:feature_class":"P",
    "gn:feature_code":"PPL",
    "gn:name":"Santa Eduviges",
    "gn:population":5,
    "gn:timezone":"America/Chihuahua",
    "iso:country":"MX",
    "wof:name":"Santa Eduviges",
    "wof:placetype":"locality",
    "wof:population":5
},
  "geometry": {"coordinates":[-106.87803,30.13431],"type":"Point"}
}