{
  "type": "Feature",
  "properties": {
    "gn:admin1_code":"5",
    "gn:admin2_code":"92.0",
    "gn:asciiname":"San Fernando Diaz (Maritano)",
    "gn:country_code":"MX",
    "gn:dem":193,
    "gn:feature_class":"P",
    "gn:feature_code":"PPL",
    "gn:name":"San Fernando D\u00edaz (Maritano)",
    "gn:population":432,
    "gn:timezone":"America/Mexico_City",
    "iso:country":"MX",
    "wof:name":"San Fernando Diaz (Maritano)",
    "wof:placetype":"locality",
    "wof:population":432
},
  "geometry": {"coordinates":[-93.77676,17.19455],"type":"Point"}
}