{
  "type": "Feature",
  "properties": {
    "gn:admin1_code":"16",
    "gn:admin2_code":"8.0",
    "gn:asciiname":"Playa del Limon",
    "gn:country_code":"MX",
    "gn:dem":154,
    "gn:feature_class":"P",
    "gn:feature_code":"PPL",
    "gn:name":"Playa del Lim\u00f3n",
    "gn:population":0,
    "gn:timezone":"America/Mexico_City",
    "iso:country":"MX",
    "name:spa_x_preferred":[
        "Playa del Lim\u00f3n"
    ],
    "wof:name":"Playa del Limon",
    "wof:placetype":"locality"
},
  "geometry": {"coordinates":[-102.79779000000001,18.17225],"type":"Point"}
}