{
  "type": "Feature",
  "properties": {
    "gn:admin1_code":"15",
    "gn:admin2_code":"21.0",
    "gn:asciiname":"Santo Nino",
    "gn:country_code":"MX",
    "gn:dem":2250,
    "gn:feature_class":"P",
    "gn:feature_code":"PPL",
    "gn:name":"Santo Ni\u00f1o",
    "gn:population":341,
    "gn:timezone":"America/Mexico_City",
    "iso:country":"MX",
    "name:und_x_variant":[
        "Santo Ni\u00f1o"
    ],
    "wof:name":"Santo Nino",
    "wof:placetype":"locality",
    "wof:population":341
},
  "geometry": {"coordinates":[-99.78306000000001,18.92194],"type":"Point"}
}