{
  "type": "Feature",
  "properties": {
    "gn:admin1_code":"21",
    "gn:admin2_code":"89.0",
    "gn:asciiname":"Buenos Aires",
    "gn:country_code":"MX",
    "gn:dem":585,
    "gn:feature_class":"P",
    "gn:feature_code":"PPL",
    "gn:name":"Buenos Aires",
    "gn:population":1711,
    "gn:timezone":"America/Mexico_City",
    "iso:country":"MX",
    "wof:name":"Buenos Aires",
    "wof:placetype":"locality",
    "wof:population":1711
},
  "geometry": {"coordinates":[-97.74833,20.15333],"type":"Point"}
}