{
  "type": "Feature",
  "properties": {
    "gn:admin1_code":"30.0",
    "gn:admin2_code":"124.0",
    "gn:asciiname":"Rodolfo Curti",
    "gn:country_code":"MX",
    "gn:dem":96,
    "gn:feature_class":"P",
    "gn:feature_code":"PPL",
    "gn:name":"Rodolfo Curti",
    "gn:population":488,
    "gn:timezone":"America/Mexico_City",
    "iso:country":"MX",
    "name:spa_x_preferred":[
        "Rodolfo Curti"
    ],
    "wof:name":"Rodolfo Curti",
    "wof:placetype":"locality",
    "wof:population":488
},
  "geometry": {"coordinates":[-97.20639,20.39611],"type":"Point"}
}