{
  "type": "Feature",
  "properties": {
    "gn:admin1_code":"19",
    "gn:admin2_code":"22",
    "gn:asciiname":"El Canelo",
    "gn:country_code":"MX",
    "gn:dem":351,
    "gn:feature_class":"P",
    "gn:feature_code":"PPL",
    "gn:name":"El Canelo",
    "gn:population":32,
    "gn:timezone":"America/Monterrey",
    "iso:country":"MX",
    "wof:name":"El Canelo",
    "wof:placetype":"locality",
    "wof:population":32
},
  "geometry": {"coordinates":[-99.74028,25.24035],"type":"Point"}
}