{
  "type": "Feature",
  "properties": {
    "gn:admin1_code":"15.0",
    "gn:admin2_code":"114.0",
    "gn:asciiname":"La Puerta del Pilar",
    "gn:country_code":"MX",
    "gn:dem":2629,
    "gn:feature_class":"P",
    "gn:feature_code":"PPL",
    "gn:name":"La Puerta del Pilar",
    "gn:population":0,
    "gn:timezone":"America/Mexico_City",
    "iso:country":"MX",
    "name:spa_x_preferred":[
        "La Puerta del Pilar"
    ],
    "wof:name":"La Puerta del Pilar",
    "wof:placetype":"locality"
},
  "geometry": {"coordinates":[-100.01577,19.46018],"type":"Point"}
}