{
  "type": "Feature",
  "properties": {
    "gn:admin1_code":"25",
    "gn:admin2_code":"16.0",
    "gn:asciiname":"Las Trompetas",
    "gn:country_code":"MX",
    "gn:dem":626,
    "gn:feature_class":"P",
    "gn:feature_code":"PPL",
    "gn:name":"Las Trompetas",
    "gn:population":0,
    "gn:timezone":"America/Mazatlan",
    "iso:country":"MX",
    "name:spa_x_preferred":[
        "Las Trompetas"
    ],
    "wof:name":"Las Trompetas",
    "wof:placetype":"locality"
},
  "geometry": {"coordinates":[-106.27272000000001,23.78976],"type":"Point"}
}