{
  "type": "Feature",
  "properties": {
    "gn:admin1_code":"17",
    "gn:admin2_code":"18.0",
    "gn:asciiname":"Campo las Martinicas (Las Higueras)",
    "gn:country_code":"MX",
    "gn:dem":1219,
    "gn:feature_class":"P",
    "gn:feature_code":"PPL",
    "gn:name":"Campo las Martinicas (Las Higueras)",
    "gn:population":7,
    "gn:timezone":"America/Mexico_City",
    "iso:country":"MX",
    "wof:name":"Campo las Martinicas (Las Higueras)",
    "wof:placetype":"locality",
    "wof:population":7
},
  "geometry": {"coordinates":[-99.21278,18.82361],"type":"Point"}
}