{
  "type": "Feature",
  "properties": {
    "gn:admin1_code":"12",
    "gn:admin2_code":"38",
    "gn:asciiname":"Los Angelitos (Los Angellitos)",
    "gn:country_code":"MX",
    "gn:dem":1195,
    "gn:feature_class":"P",
    "gn:feature_code":"PPL",
    "gn:name":"Los Angelitos (Los Angellitos)",
    "gn:population":16,
    "gn:timezone":"America/Mexico_City",
    "iso:country":"MX",
    "wof:name":"Los Angelitos (Los Angellitos)",
    "wof:placetype":"locality",
    "wof:population":16
},
  "geometry": {"coordinates":[-101.32892,18.02715],"type":"Point"}
}