{
  "type": "Feature",
  "properties": {
    "gn:admin1_code":"23",
    "gn:admin2_code":"4",
    "gn:asciiname":"Gabino Vazquez",
    "gn:country_code":"MX",
    "gn:dem":54,
    "gn:feature_class":"P",
    "gn:feature_code":"PPL",
    "gn:name":"Gabino V\u00e1zquez",
    "gn:population":52,
    "gn:timezone":"America/Cancun",
    "iso:country":"MX",
    "name:und_x_variant":[
        "Gabino V\u00e1zquez"
    ],
    "wof:name":"Gabino Vazquez",
    "wof:placetype":"locality",
    "wof:population":52
},
  "geometry": {"coordinates":[-88.75139,19.04306],"type":"Point"}
}