{
  "type": "Feature",
  "properties": {
    "gn:admin1_code":"2",
    "gn:admin2_code":"1.0",
    "gn:asciiname":"Enrique Vargas Gastelum",
    "gn:country_code":"MX",
    "gn:dem":771,
    "gn:feature_class":"P",
    "gn:feature_code":"PPL",
    "gn:name":"Enrique Vargas Gast\u00e9lum",
    "gn:population":7,
    "gn:timezone":"America/Tijuana",
    "iso:country":"MX",
    "name:und_x_variant":[
        "Enrique Vargas Gast\u00e9lum"
    ],
    "wof:name":"Enrique Vargas Gastelum",
    "wof:placetype":"locality",
    "wof:population":7
},
  "geometry": {"coordinates":[-115.74806,31.35611],"type":"Point"}
}