{
  "type": "Feature",
  "properties": {
    "gn:admin1_code":"22",
    "gn:admin2_code":"17",
    "gn:asciiname":"Camino al Ciervo (Familia Benitez Ordonez)",
    "gn:country_code":"MX",
    "gn:dem":1909,
    "gn:feature_class":"P",
    "gn:feature_code":"PPL",
    "gn:name":"Camino al Ciervo (Familia Ben\u00edtez Ordo\u00f1ez)",
    "gn:population":12,
    "gn:timezone":"America/Mexico_City",
    "iso:country":"MX",
    "name:und_x_variant":[
        "Camino al Ciervo (Familia Ben\u00edtez Ordo\u00f1ez)"
    ],
    "wof:name":"Camino al Ciervo (Familia Benitez Ordonez)",
    "wof:placetype":"locality",
    "wof:population":12
},
  "geometry": {"coordinates":[-99.88472,20.57083],"type":"Point"}
}