{
  "type": "Feature",
  "properties": {
    "gn:admin1_code":"3",
    "gn:admin2_code":"1.0",
    "gn:asciiname":"San Rafael Uno",
    "gn:country_code":"MX",
    "gn:dem":116,
    "gn:feature_class":"P",
    "gn:feature_code":"PPL",
    "gn:name":"San Rafael Uno",
    "gn:population":2,
    "gn:timezone":"America/Mazatlan",
    "iso:country":"MX",
    "wof:name":"San Rafael Uno",
    "wof:placetype":"locality",
    "wof:population":2
},
  "geometry": {"coordinates":[-111.50422,25.40732],"type":"Point"}
}