{
  "type": "Feature",
  "properties": {
    "gn:admin1_code":"5",
    "gn:admin2_code":"107.0",
    "gn:asciiname":"Las Maravillas",
    "gn:country_code":"MX",
    "gn:dem":643,
    "gn:feature_class":"P",
    "gn:feature_code":"PPL",
    "gn:name":"Las Maravillas",
    "gn:population":8,
    "gn:timezone":"America/Mexico_City",
    "iso:country":"MX",
    "wof:name":"Las Maravillas",
    "wof:placetype":"locality",
    "wof:population":8
},
  "geometry": {"coordinates":[-93.38556,16.18333],"type":"Point"}
}