{
  "type": "Feature",
  "properties": {
    "gn:admin1_code":"28.0",
    "gn:admin2_code":"21.0",
    "gn:asciiname":"Dieciocho de Febrero",
    "gn:country_code":"MX",
    "gn:dem":54,
    "gn:feature_class":"P",
    "gn:feature_code":"PPL",
    "gn:name":"Dieciocho de Febrero",
    "gn:population":80,
    "gn:timezone":"America/Monterrey",
    "iso:country":"MX",
    "name:spa_x_preferred":[
        "Dieciocho de Febrero"
    ],
    "wof:name":"Dieciocho de Febrero",
    "wof:placetype":"locality",
    "wof:population":80
},
  "geometry": {"coordinates":[-98.85722,22.73],"type":"Point"}
}