{
  "type": "Feature",
  "properties": {
    "gn:admin1_code":"30",
    "gn:admin2_code":"108",
    "gn:asciiname":"Los Arrayanes",
    "gn:country_code":"MX",
    "gn:dem":16,
    "gn:feature_class":"P",
    "gn:feature_code":"PPL",
    "gn:name":"Los Arrayanes",
    "gn:population":11,
    "gn:timezone":"America/Mexico_City",
    "iso:country":"MX",
    "wof:name":"Los Arrayanes",
    "wof:placetype":"locality",
    "wof:population":11
},
  "geometry": {"coordinates":[-94.37417000000001,17.80639],"type":"Point"}
}