{
  "type": "Feature",
  "properties": {
    "gn:admin1_code":"21",
    "gn:admin2_code":"108.0",
    "gn:asciiname":"Santa Cruz Magdalena",
    "gn:country_code":"MX",
    "gn:dem":2387,
    "gn:feature_class":"P",
    "gn:feature_code":"PPL",
    "gn:name":"Santa Cruz Magdalena",
    "gn:population":704,
    "gn:timezone":"America/Mexico_City",
    "iso:country":"MX",
    "wof:name":"Santa Cruz Magdalena",
    "wof:placetype":"locality",
    "wof:population":704
},
  "geometry": {"coordinates":[-97.64861000000001,19.37],"type":"Point"}
}