{
  "type": "Feature",
  "properties": {
    "gn:admin1_code":"14.0",
    "gn:admin2_code":"69.0",
    "gn:asciiname":"Los Chacones",
    "gn:country_code":"MX",
    "gn:dem":1454,
    "gn:feature_class":"P",
    "gn:feature_code":"PPL",
    "gn:name":"Los Chacones",
    "gn:population":0,
    "gn:timezone":"America/Mexico_City",
    "iso:country":"MX",
    "name:spa_x_preferred":[
        "Los Chacones"
    ],
    "wof:name":"Los Chacones",
    "wof:placetype":"locality"
},
  "geometry": {"coordinates":[-102.94506,19.67546],"type":"Point"}
}