{
  "type": "Feature",
  "properties": {
    "gn:country":"MX",
    "gn:fcode":"PPL",
    "gn:population":0,
    "iso:country":"MX",
    "name:afr_x_preferred":[
        "Amado Nervo"
    ],
    "name:ara_x_preferred":[
        "\u0623\u0645\u0627\u062f\u0648 \u0646\u064a\u0631\u0641\u0648"
    ],
    "name:cat_x_preferred":[
        "Amado Nervo"
    ],
    "name:deu_x_preferred":[
        "Amado Nervo"
    ],
    "name:epo_x_preferred":[
        "Amado Nervo"
    ],
    "name:eus_x_preferred":[
        "Amado Nervo"
    ],
    "name:fas_x_preferred":[
        "\u0622\u0645\u0627\u062f\u0648\u0648 \u0646\u0631\u0648\u0648"
    ],
    "name:fra_x_preferred":[
        "Amado Nervo"
    ],
    "name:ina_x_preferred":[
        "Amado Nervo"
    ],
    "name:ita_x_preferred":[
        "Amado Nervo"
    ],
    "name:nah_x_preferred":[
        "Amado Nervo"
    ],
    "name:nld_x_preferred":[
        "Amado Nervo"
    ],
    "name:pol_x_preferred":[
        "Amado Nervo"
    ],
    "name:por_x_preferred":[
        "Amado Nervo"
    ],
    "name:que_x_preferred":[
        "Amado Nervo"
    ],
    "name:ron_x_preferred":[
        "Amado Nervo"
    ],
    "name:rus_x_preferred":[
        "\u0410\u043c\u0430\u0434\u043e \u041d\u0435\u0440\u0432\u043e"
    ],
    "name:spa_x_preferred":[
        "Amado Nervo"
    ],
    "name:ukr_x_preferred":[
        "\u0410\u043c\u0430\u0434\u043e \u041d\u0435\u0440\u0432\u043e"
    ],
    "qs_pg:aaroncc":"MX",
    "qs_pg:gn_country":"MX",
    "qs_pg:gn_fcode":"PPL",
    "qs_pg:gn_pop":0,
    "qs_pg:name":"Amado Nervo",
    "qs_pg:name_adm0":"M\u00e9xico",
    "qs_pg:name_adm1":"Nayarit",
    "qs_pg:photos":12,
    "qs_pg:photos_1k":2,
    "qs_pg:photos_9k":1,
    "qs_pg:photos_9r":1,
    "qs_pg:photos_all":12,
    "qs_pg:photos_sr":1,
    "qs_pg:pop_sr":0,
    "qs_pg:qs_pg_placetype":"neighbourhood",
    "qs_pg:qs_pg_placetype_gp":"Suburb",
    "qs_pg:woe_adm0":23424900,
    "woe:adm0_id":23424900,
    "woe:name_adm0":"M\u00e9xico",
    "woe:name_adm1":"Nayarit",
    "woe:placetype":"Suburb",
    "wof:name":"Amado Nervo",
    "wof:placetype":"neighbourhood",
    "wof:population":114
},
  "geometry": {"coordinates":[-105.34786,22.38432],"type":"Point"}
}