{
  "type": "Feature",
  "properties": {
    "gn:gn_country":"MX",
    "gn:gn_fcode":"PPL",
    "gn:gn_pop":0,
    "gn:population":114,
    "iso:country":"MX",
    "name:spa_x_preferred":[
        "Amado Nervo"
    ],
    "qs_pg:aaroncc":"MX",
    "qs_pg:gn_country":"MX",
    "qs_pg:gn_fcode":"PPL",
    "qs_pg:gn_pop":0,
    "qs_pg:name":"Amado Nervo",
    "qs_pg:name_adm0":"M\u00e9xico",
    "qs_pg:name_adm1":"Nayarit",
    "qs_pg:photos":12,
    "qs_pg:photos_1k":2,
    "qs_pg:photos_9k":1,
    "qs_pg:photos_9r":1,
    "qs_pg:photos_all":12,
    "qs_pg:photos_sr":1,
    "qs_pg:pop_sr":0,
    "qs_pg:qs_pg_placetype":"neighbourhood",
    "qs_pg:qs_pg_placetype_gp":"Suburb",
    "qs_pg:woe_adm0":23424900,
    "woe:adm0_id":23424900,
    "woe:name_adm0":"M\u00e9xico",
    "woe:name_adm1":"Nayarit",
    "woe:placetype":"Suburb",
    "wof:name":"Amado Nervo",
    "wof:placetype":"neighbourhood",
    "wof:population":114
},
  "geometry": {"coordinates":[-105.34786,22.38432],"type":"Point"}
}