{
  "type": "Feature",
  "properties": {
    "gn:admin1_code":"21",
    "gn:admin2_code":"145.0",
    "gn:asciiname":"Tepexilotla",
    "gn:country_code":"MX",
    "gn:dem":820,
    "gn:feature_class":"P",
    "gn:feature_code":"PPL",
    "gn:name":"Tepexilotla",
    "gn:population":274,
    "gn:timezone":"America/Mexico_City",
    "iso:country":"MX",
    "wof:name":"Tepexilotla",
    "wof:placetype":"locality",
    "wof:population":274
},
  "geometry": {"coordinates":[-96.86861,18.28611],"type":"Point"}
}