{
  "type": "Feature",
  "properties": {
    "gn:admin1_code":"14",
    "gn:admin2_code":"17.0",
    "gn:asciiname":"Yerbabuena de las Palmas",
    "gn:country_code":"MX",
    "gn:dem":1455,
    "gn:feature_class":"P",
    "gn:feature_code":"PPL",
    "gn:name":"Yerbabuena de las Palmas",
    "gn:population":0,
    "gn:timezone":"America/Mexico_City",
    "iso:country":"MX",
    "name:spa_x_preferred":[
        "Yerbabuena de las Palmas"
    ],
    "name:und_x_variant":[
        "La Yerbabuena de las Palmas"
    ],
    "wof:name":"Yerbabuena de las Palmas",
    "wof:placetype":"locality"
},
  "geometry": {"coordinates":[-104.4507,19.93967],"type":"Point"}
}