{
  "type": "Feature",
  "properties": {
    "gn:admin1_code":"6",
    "gn:admin2_code":"12.0",
    "gn:asciiname":"Cuacharachi",
    "gn:country_code":"MX",
    "gn:dem":1960,
    "gn:feature_class":"P",
    "gn:feature_code":"PPL",
    "gn:name":"Cuach\u00e1rachi",
    "gn:population":0,
    "gn:timezone":"America/Chihuahua",
    "iso:country":"MX",
    "name:spa_x_preferred":[
        "Cuach\u00e1rachi"
    ],
    "wof:name":"Cuacharachi",
    "wof:placetype":"locality"
},
  "geometry": {"coordinates":[-107.11365000000001,27.58584],"type":"Point"}
}