{
  "type": "Feature",
  "properties": {
    "gn:admin1_code":"24.0",
    "gn:asciiname":"Los Cuatillos",
    "gn:country_code":"MX",
    "gn:dem":1825,
    "gn:feature_class":"P",
    "gn:feature_code":"PPL",
    "gn:name":"Los Cuatillos",
    "gn:population":0,
    "gn:timezone":"America/Mexico_City",
    "iso:country":"MX",
    "name:spa_x_preferred":[
        "Los Cuatillos"
    ],
    "wof:name":"Los Cuatillos",
    "wof:placetype":"locality"
},
  "geometry": {"coordinates":[-101.06234000000001,23.86283],"type":"Point"}
}