{
  "type": "Feature",
  "properties": {
    "gn:admin1_code":"19",
    "gn:admin2_code":"5.0",
    "gn:asciiname":"Las Bugambilias",
    "gn:country_code":"MX",
    "gn:dem":138,
    "gn:feature_class":"P",
    "gn:feature_code":"PPL",
    "gn:name":"Las Bugambilias",
    "gn:population":8,
    "gn:timezone":"America/Monterrey",
    "iso:country":"MX",
    "wof:name":"Las Bugambilias",
    "wof:placetype":"locality",
    "wof:population":8
},
  "geometry": {"coordinates":[-99.77699,26.91976],"type":"Point"}
}