{
  "type": "Feature",
  "properties": {
    "gn:admin1_code":"20",
    "gn:admin2_code":"30.0",
    "gn:asciiname":"Rancho Claudio Toledo Villalobos",
    "gn:country_code":"MX",
    "gn:dem":29,
    "gn:feature_class":"P",
    "gn:feature_code":"PPL",
    "gn:name":"Rancho Claudio Toledo Villalobos",
    "gn:population":5,
    "gn:timezone":"America/Mexico_City",
    "iso:country":"MX",
    "wof:name":"Rancho Claudio Toledo Villalobos",
    "wof:placetype":"locality",
    "wof:population":5
},
  "geometry": {"coordinates":[-94.99361,16.49278],"type":"Point"}
}