{
  "type": "Feature",
  "properties": {
    "gn:admin1_code":"6",
    "gn:admin2_code":"27.0",
    "gn:asciiname":"Quirare",
    "gn:country_code":"MX",
    "gn:dem":2075,
    "gn:feature_class":"P",
    "gn:feature_code":"PPL",
    "gn:name":"Qu\u00edrare",
    "gn:population":0,
    "gn:timezone":"America/Chihuahua",
    "iso:country":"MX",
    "name:spa_x_preferred":[
        "Qu\u00edrare"
    ],
    "wof:name":"Quirare",
    "wof:placetype":"locality"
},
  "geometry": {"coordinates":[-107.56126,27.16289],"type":"Point"}
}