{
  "type": "Feature",
  "properties": {
    "gn:admin1_code":"5.0",
    "gn:admin2_code":"35.0",
    "gn:asciiname":"Santa Lucia Dos",
    "gn:country_code":"MX",
    "gn:dem":34,
    "gn:feature_class":"P",
    "gn:feature_code":"PPL",
    "gn:name":"Santa Luc\u00eda Dos",
    "gn:population":0,
    "gn:timezone":"America/Mexico_City",
    "iso:country":"MX",
    "name:spa_x_preferred":[
        "Santa Luc\u00eda Dos"
    ],
    "wof:name":"Santa Lucia Dos",
    "wof:placetype":"locality"
},
  "geometry": {"coordinates":[-92.23990000000001,14.71433],"type":"Point"}
}