{
  "type": "Feature",
  "properties": {
    "gn:admin1_code":"19.0",
    "gn:admin2_code":"45.0",
    "gn:asciiname":"Los Trevino",
    "gn:country_code":"MX",
    "gn:dem":408,
    "gn:feature_class":"P",
    "gn:feature_code":"PPL",
    "gn:name":"Los Trevi\u00f1o",
    "gn:population":0,
    "gn:timezone":"America/Monterrey",
    "iso:country":"MX",
    "name:spa_x_preferred":[
        "Los Trevi\u00f1o"
    ],
    "wof:name":"Los Trevino",
    "wof:placetype":"locality"
},
  "geometry": {"coordinates":[-100.10204,26.29968],"type":"Point"}
}