{
  "type": "Feature",
  "properties": {
    "gn:admin1_code":"24",
    "gn:admin2_code":"29.0",
    "gn:asciiname":"La Granja",
    "gn:country_code":"MX",
    "gn:dem":219,
    "gn:feature_class":"P",
    "gn:feature_code":"PPL",
    "gn:name":"La Granja",
    "gn:population":8,
    "gn:timezone":"America/Mexico_City",
    "iso:country":"MX",
    "name:ceb_x_preferred":[
        "La Granja"
    ],
    "name:deu_x_preferred":[
        "La Granja"
    ],
    "name:eus_x_preferred":[
        "La Granja"
    ],
    "name:fra_x_preferred":[
        "La Granja"
    ],
    "name:glg_x_preferred":[
        "La Granja"
    ],
    "name:hun_x_preferred":[
        "La Granja"
    ],
    "name:msa_x_preferred":[
        "La Granja"
    ],
    "name:nld_x_preferred":[
        "La Granja"
    ],
    "name:oci_x_preferred":[
        "La Granja"
    ],
    "name:pol_x_preferred":[
        "La Granja"
    ],
    "name:por_x_preferred":[
        "La Granja"
    ],
    "name:ron_x_preferred":[
        "La Granja"
    ],
    "name:rus_x_preferred":[
        "\u041b\u0430-\u0413\u0440\u0430\u043d\u0445\u0430"
    ],
    "name:spa_x_preferred":[
        "La granja"
    ],
    "name:swe_x_preferred":[
        "La Granja"
    ],
    "name:ukr_x_preferred":[
        "\u041b\u0430 \u0413\u0440\u0430\u043d\u0445\u0430"
    ],
    "name:vie_x_preferred":[
        "La Granja"
    ],
    "name:war_x_preferred":[
        "La Granja"
    ],
    "wof:name":"La Granja",
    "wof:placetype":"locality",
    "wof:population":8
},
  "geometry": {"coordinates":[-98.67528,21.36778],"type":"Point"}
}