{
  "type": "Feature",
  "properties": {
    "gn:admin1_code":"24",
    "gn:admin2_code":"29.0",
    "gn:asciiname":"La Granja",
    "gn:country_code":"MX",
    "gn:dem":219,
    "gn:feature_class":"P",
    "gn:feature_code":"PPL",
    "gn:name":"La Granja",
    "gn:population":8,
    "gn:timezone":"America/Mexico_City",
    "iso:country":"MX",
    "wof:name":"La Granja",
    "wof:placetype":"locality",
    "wof:population":8
},
  "geometry": {"coordinates":[-98.67528,21.36778],"type":"Point"}
}