{
  "type": "Feature",
  "properties": {
    "gn:admin1_code":"25",
    "gn:admin2_code":"3",
    "gn:asciiname":"Baymusari",
    "gn:country_code":"MX",
    "gn:dem":665,
    "gn:feature_class":"P",
    "gn:feature_code":"PPL",
    "gn:name":"Baymusari",
    "gn:population":35,
    "gn:timezone":"America/Mazatlan",
    "iso:country":"MX",
    "wof:name":"Baymusari",
    "wof:placetype":"locality",
    "wof:population":35
},
  "geometry": {"coordinates":[-107.37152,25.44994],"type":"Point"}
}