{
  "type": "Feature",
  "properties": {
    "gn:admin1_code":"20",
    "gn:admin2_code":"57",
    "gn:asciiname":"Cuatro Caminos",
    "gn:country_code":"MX",
    "gn:dem":108,
    "gn:feature_class":"P",
    "gn:feature_code":"PPL",
    "gn:name":"Cuatro Caminos",
    "gn:population":12,
    "gn:timezone":"America/Mexico_City",
    "iso:country":"MX",
    "name:spa_x_preferred":[
        "Cuatro caminos"
    ],
    "wof:name":"Cuatro Caminos",
    "wof:placetype":"locality",
    "wof:population":12
},
  "geometry": {"coordinates":[-94.78139,17.10167],"type":"Point"}
}