{
  "type": "Feature",
  "properties": {
    "gn:admin1_code":"26.0",
    "gn:admin2_code":"52.0",
    "gn:asciiname":"Matias",
    "gn:country_code":"MX",
    "gn:dem":1481,
    "gn:feature_class":"P",
    "gn:feature_code":"PPL",
    "gn:name":"Mat\u00edas",
    "gn:population":0,
    "gn:timezone":"America/Hermosillo",
    "iso:country":"MX",
    "name:spa_x_preferred":[
        "Mat\u00edas"
    ],
    "wof:name":"Matias",
    "wof:placetype":"locality"
},
  "geometry": {"coordinates":[-108.80734,28.87644],"type":"Point"}
}