{
  "type": "Feature",
  "properties": {
    "gn:admin1_code":"10",
    "gn:admin2_code":"14",
    "gn:asciiname":"Los Sapos",
    "gn:country_code":"MX",
    "gn:dem":725,
    "gn:feature_class":"P",
    "gn:feature_code":"PPL",
    "gn:name":"Los Sapos",
    "gn:population":13,
    "gn:timezone":"America/Mazatlan",
    "iso:country":"MX",
    "wof:name":"Los Sapos",
    "wof:placetype":"locality",
    "wof:population":13
},
  "geometry": {"coordinates":[-104.43689000000001,22.42865],"type":"Point"}
}