{
  "type": "Feature",
  "properties": {
    "gn:admin1_code":"28.0",
    "gn:admin2_code":"19.0",
    "gn:asciiname":"Agua Fria Segundo",
    "gn:country_code":"MX",
    "gn:dem":187,
    "gn:feature_class":"P",
    "gn:feature_code":"PPL",
    "gn:name":"Agua Fr\u00eda Segundo",
    "gn:population":0,
    "gn:timezone":"America/Monterrey",
    "iso:country":"MX",
    "name:spa_x_preferred":[
        "Agua Fr\u00eda Segundo"
    ],
    "wof:name":"Agua Fria Segundo",
    "wof:placetype":"locality"
},
  "geometry": {"coordinates":[-98.93544,23.18538],"type":"Point"}
}