{
  "type": "Feature",
  "properties": {
    "gn:admin1_code":"28.0",
    "gn:admin2_code":"37.0",
    "gn:asciiname":"Mauro Rodriguez",
    "gn:country_code":"MX",
    "gn:dem":6,
    "gn:feature_class":"P",
    "gn:feature_code":"PPL",
    "gn:name":"Mauro Rodr\u00edguez",
    "gn:population":0,
    "gn:timezone":"America/Monterrey",
    "iso:country":"MX",
    "name:spa_x_preferred":[
        "Mauro Rodr\u00edguez"
    ],
    "wof:name":"Mauro Rodriguez",
    "wof:placetype":"locality"
},
  "geometry": {"coordinates":[-97.78252999999999,23.88619],"type":"Point"}
}