{
  "type": "Feature",
  "properties": {
    "gn:admin1_code":"17",
    "gn:admin2_code":"25",
    "gn:asciiname":"La Maroma",
    "gn:country_code":"MX",
    "gn:dem":937,
    "gn:feature_class":"P",
    "gn:feature_code":"PPL",
    "gn:name":"La Maroma",
    "gn:population":30,
    "gn:timezone":"America/Mexico_City",
    "iso:country":"MX",
    "wof:name":"La Maroma",
    "wof:placetype":"locality",
    "wof:population":30
},
  "geometry": {"coordinates":[-99.14639,18.62167],"type":"Point"}
}