{
  "type": "Feature",
  "properties": {
    "gn:admin1_code":"28",
    "gn:admin2_code":"33.0",
    "gn:asciiname":"Ruben y Bruno Ojeda",
    "gn:country_code":"MX",
    "gn:dem":32,
    "gn:feature_class":"P",
    "gn:feature_code":"PPL",
    "gn:name":"Rub\u00e9n y Bruno Ojeda",
    "gn:population":5,
    "gn:timezone":"America/Monterrey",
    "iso:country":"MX",
    "name:und_x_variant":[
        "Rub\u00e9n y Bruno Ojeda"
    ],
    "wof:name":"Ruben y Bruno Ojeda",
    "wof:placetype":"locality",
    "wof:population":5
},
  "geometry": {"coordinates":[-98.05472,25.96556],"type":"Point"}
}