{
  "type": "Feature",
  "properties": {
    "gn:admin1_code":"8.0",
    "gn:admin2_code":"8.0",
    "gn:asciiname":"El Convento",
    "gn:country_code":"MX",
    "gn:dem":757,
    "gn:feature_class":"P",
    "gn:feature_code":"PPL",
    "gn:name":"El Convento",
    "gn:population":17,
    "gn:timezone":"America/Mexico_City",
    "iso:country":"MX",
    "wof:name":"El Convento",
    "wof:placetype":"locality",
    "wof:population":17
},
  "geometry": {"coordinates":[-104.06694,19.34028],"type":"Point"}
}