{
  "type": "Feature",
  "properties": {
    "gn:admin1_code":"25.0",
    "gn:admin2_code":"10.0",
    "gn:asciiname":"Campo Mendivil",
    "gn:country_code":"MX",
    "gn:dem":8,
    "gn:feature_class":"P",
    "gn:feature_code":"PPL",
    "gn:name":"Campo Mendivil",
    "gn:population":0,
    "gn:timezone":"America/Mazatlan",
    "iso:country":"MX",
    "name:spa_x_preferred":[
        "Campo Mendivil"
    ],
    "wof:name":"Campo Mendivil",
    "wof:placetype":"locality"
},
  "geometry": {"coordinates":[-109.02898999999999,26.2439],"type":"Point"}
}