{
  "type": "Feature",
  "properties": {
    "gn:admin1_code":"20.0",
    "gn:admin2_code":"391.0",
    "gn:asciiname":"La Joroba",
    "gn:country_code":"MX",
    "gn:dem":1380,
    "gn:feature_class":"P",
    "gn:feature_code":"PPL",
    "gn:name":"La Joroba",
    "gn:population":0,
    "gn:timezone":"America/Mexico_City",
    "iso:country":"MX",
    "name:spa_x_preferred":[
        "La Joroba"
    ],
    "wof:name":"La Joroba",
    "wof:placetype":"locality"
},
  "geometry": {"coordinates":[-96.61311000000001,16.16694],"type":"Point"}
}