{
  "type": "Feature",
  "properties": {
    "gn:admin1_code":"10",
    "gn:admin2_code":"23.0",
    "gn:asciiname":"El Grullo",
    "gn:country_code":"MX",
    "gn:dem":2717,
    "gn:feature_class":"P",
    "gn:feature_code":"PPL",
    "gn:name":"El Grullo",
    "gn:population":0,
    "gn:timezone":"America/Monterrey",
    "iso:country":"MX",
    "name:spa_x_preferred":[
        "El Grullo"
    ],
    "wof:name":"El Grullo",
    "wof:placetype":"locality"
},
  "geometry": {"coordinates":[-105.34524999999999,23.48524],"type":"Point"}
}