{
  "type": "Feature",
  "properties": {
    "gn:admin1_code":"10",
    "gn:admin2_code":"23.0",
    "gn:asciiname":"El Grullo",
    "gn:country_code":"MX",
    "gn:dem":2717,
    "gn:feature_class":"P",
    "gn:feature_code":"PPL",
    "gn:name":"El Grullo",
    "gn:population":0,
    "gn:timezone":"America/Monterrey",
    "iso:country":"MX",
    "name:ceb_x_preferred":[
        "El Grullo"
    ],
    "name:epo_x_preferred":[
        "El Grullo"
    ],
    "name:eus_x_preferred":[
        "El Grullo"
    ],
    "name:fra_x_preferred":[
        "El Grullo"
    ],
    "name:ita_x_preferred":[
        "El Grullo"
    ],
    "name:nor_x_preferred":[
        "El Grullo"
    ],
    "name:pol_x_preferred":[
        "El Grullo"
    ],
    "name:por_x_preferred":[
        "El Grullo"
    ],
    "name:spa_x_preferred":[
        "El Grullo"
    ],
    "name:srp_x_preferred":[
        "\u041e\u043f\u0448\u0442\u0438\u043d\u0430 \u0415\u043b \u0413\u0440\u0443\u0459\u043e"
    ],
    "name:swe_x_preferred":[
        "El Grullo"
    ],
    "name:vie_x_preferred":[
        "El Grullo"
    ],
    "wof:name":"El Grullo",
    "wof:placetype":"locality"
},
  "geometry": {"coordinates":[-105.34524999999999,23.48524],"type":"Point"}
}