{
  "type": "Feature",
  "properties": {
    "gn:admin1_code":"30",
    "gn:admin2_code":"61.0",
    "gn:asciiname":"Guadalupe Victoria",
    "gn:country_code":"MX",
    "gn:dem":116,
    "gn:feature_class":"P",
    "gn:feature_code":"PPL",
    "gn:name":"Guadalupe Victoria",
    "gn:population":126,
    "gn:timezone":"America/Mexico_City",
    "iso:country":"MX",
    "wof:name":"Guadalupe Victoria",
    "wof:placetype":"locality",
    "wof:population":126
},
  "geometry": {"coordinates":[-93.9825,17.49889],"type":"Point"}
}