{
  "type": "Feature",
  "properties": {
    "gn:admin1_code":"5.0",
    "gn:admin2_code":"59.0",
    "gn:asciiname":"Morelos",
    "gn:country_code":"MX",
    "gn:dem":353,
    "gn:feature_class":"P",
    "gn:feature_code":"PPL",
    "gn:name":"Morelos",
    "gn:population":0,
    "gn:timezone":"America/Mexico_City",
    "iso:country":"MX",
    "name:spa_x_preferred":[
        "Morelos"
    ],
    "wof:name":"Morelos",
    "wof:placetype":"locality"
},
  "geometry": {"coordinates":[-91.51721999999999,17.11463],"type":"Point"}
}