{
  "type": "Feature",
  "properties": {
    "gn:admin1_code":"19.0",
    "gn:admin2_code":"32.0",
    "gn:asciiname":"La Pila",
    "gn:country_code":"MX",
    "gn:dem":436,
    "gn:feature_class":"P",
    "gn:feature_code":"PPL",
    "gn:name":"La Pila",
    "gn:population":0,
    "gn:timezone":"America/Monterrey",
    "iso:country":"MX",
    "name:spa_x_preferred":[
        "La Pila"
    ],
    "wof:name":"La Pila",
    "wof:placetype":"locality"
},
  "geometry": {"coordinates":[-100.48052,26.68824],"type":"Point"}
}