{
  "type": "Feature",
  "properties": {
    "gn:admin1_code":"5",
    "gn:admin2_code":"100",
    "gn:asciiname":"Lote 20 Fraccion",
    "gn:country_code":"MX",
    "gn:dem":96,
    "gn:feature_class":"P",
    "gn:feature_code":"PPL",
    "gn:name":"Lote 20 Fracci\u00f3n",
    "gn:population":28,
    "gn:timezone":"America/Mexico_City",
    "iso:country":"MX",
    "name:und_x_variant":[
        "Lote 20 Fracci\u00f3n"
    ],
    "wof:name":"Lote 20 Fraccion",
    "wof:placetype":"locality",
    "wof:population":28
},
  "geometry": {"coordinates":[-92.13667,17.27917],"type":"Point"}
}