{
  "type": "Feature",
  "properties": {
    "gn:admin1_code":"1",
    "gn:admin2_code":"6",
    "gn:asciiname":"Antonio Castaneda Almanza",
    "gn:country_code":"MX",
    "gn:dem":1892,
    "gn:feature_class":"P",
    "gn:feature_code":"PPL",
    "gn:name":"Antonio Casta\u00f1eda Almanza",
    "gn:population":12,
    "gn:timezone":"America/Mexico_City",
    "iso:country":"MX",
    "name:und_x_variant":[
        "Antonio Casta\u00f1eda Almanza"
    ],
    "wof:name":"Antonio Castaneda Almanza",
    "wof:placetype":"locality",
    "wof:population":12
},
  "geometry": {"coordinates":[-102.2675,22.14],"type":"Point"}
}