{
  "type": "Feature",
  "properties": {
    "gn:admin1_code":"30.0",
    "gn:admin2_code":"155.0",
    "gn:asciiname":"Falde Damas",
    "gn:country_code":"MX",
    "gn:dem":148,
    "gn:feature_class":"P",
    "gn:feature_code":"PPL",
    "gn:name":"Falde Damas",
    "gn:population":2,
    "gn:timezone":"America/Mexico_City",
    "iso:country":"MX",
    "name:spa_x_preferred":[
        "Falde Damas"
    ],
    "wof:name":"Falde Damas",
    "wof:placetype":"locality",
    "wof:population":2
},
  "geometry": {"coordinates":[-98.09305999999999,21.36167],"type":"Point"}
}