{
  "type": "Feature",
  "properties": {
    "gn:admin1_code":"18",
    "gn:admin2_code":"19",
    "gn:asciiname":"El Chorizo",
    "gn:country_code":"MX",
    "gn:dem":1116,
    "gn:feature_class":"P",
    "gn:feature_code":"PPL",
    "gn:name":"El Chorizo",
    "gn:population":10,
    "gn:timezone":"America/Mexico_City",
    "iso:country":"MX",
    "wof:name":"El Chorizo",
    "wof:placetype":"locality",
    "wof:population":10
},
  "geometry": {"coordinates":[-104.04694000000001,21.78028],"type":"Point"}
}