{
  "type": "Feature",
  "properties": {
    "gn:admin1_code":"2",
    "gn:admin2_code":"1.0",
    "gn:asciiname":"Ruben Jaramillo",
    "gn:country_code":"MX",
    "gn:dem":55,
    "gn:feature_class":"P",
    "gn:feature_code":"PPL",
    "gn:name":"Rub\u00e9n Jaramillo",
    "gn:population":0,
    "gn:timezone":"America/Tijuana",
    "iso:country":"MX",
    "name:spa_x_preferred":[
        "Rub\u00e9n Jaramillo"
    ],
    "wof:name":"Ruben Jaramillo",
    "wof:placetype":"locality"
},
  "geometry": {"coordinates":[-116.12973,30.92271],"type":"Point"}
}