{
  "type": "Feature",
  "properties": {
    "iso:country":"MX",
    "name:eng_x_variant":[
        "PCM",
        "MX-PCM"
    ],
    "name:fas_x_preferred":[
        "\u0641\u0631\u0648\u062f\u06af\u0627\u0647 \u067e\u0644\u0646\u062a \u0633\u06cc\u062a\u06cc"
    ],
    "name:tgk_x_preferred":[
        "\u0424\u0443\u0440\u0443\u0434\u0433\u043e\u04b3\u0438 \u043f\u043b\u043d\u0442 \u0441\u0435\u0442\u04e3 \u0435"
    ],
    "oa:type":"small_airport",
    "wd:wordcount":386,
    "woe:hierarchy":{
        "country_id":23424977,
        "county_id":12587831,
        "planet_id":1,
        "state_id":2347568
    },
    "wof:name":"Plant City Municipal Airport",
    "wof:placetype":"campus"
},
  "geometry": {"coordinates":[-87.082199,20.622499],"type":"Point"}
}