{
  "type": "Feature",
  "properties": {
    "gn:admin1_code":"21.0",
    "gn:admin2_code":"47.0",
    "gn:asciiname":"Tlaica",
    "gn:country_code":"MX",
    "gn:dem":1025,
    "gn:feature_class":"P",
    "gn:feature_code":"PPL",
    "gn:name":"Tlaica",
    "gn:population":0,
    "gn:timezone":"America/Mexico_City",
    "iso:country":"MX",
    "name:spa_x_preferred":[
        "Tlaica"
    ],
    "wof:name":"Tlaica",
    "wof:placetype":"locality"
},
  "geometry": {"coordinates":[-98.59255,18.30402],"type":"Point"}
}