{
  "type": "Feature",
  "properties": {
    "gn:admin1_code":"10",
    "gn:admin2_code":"34.0",
    "gn:asciiname":"Las Trancas",
    "gn:country_code":"MX",
    "gn:dem":317,
    "gn:feature_class":"P",
    "gn:feature_code":"PPL",
    "gn:name":"Las Trancas",
    "gn:population":8,
    "gn:timezone":"America/Monterrey",
    "iso:country":"MX",
    "name:ceb_x_preferred":[
        "Las Trancas"
    ],
    "name:ita_x_preferred":[
        "Las Trancas"
    ],
    "name:spa_x_preferred":[
        "Las Trancas"
    ],
    "name:urd_x_preferred":[
        "\u0644\u0627\u0633 \u0679\u0631\u0627\u0646\u06a9\u0627\u0633"
    ],
    "name:zho_x_preferred":[
        "\u62c9\u65af\u7279\u862d\u5361\u65af"
    ],
    "wof:name":"Las Trancas",
    "wof:placetype":"locality",
    "wof:population":8
},
  "geometry": {"coordinates":[-106.87231,25.0397],"type":"Point"}
}