{
  "type": "Feature",
  "properties": {
    "gn:admin1_code":"19",
    "gn:admin2_code":"5.0",
    "gn:asciiname":"San Bernardo",
    "gn:country_code":"MX",
    "gn:dem":139,
    "gn:feature_class":"P",
    "gn:feature_code":"PPL",
    "gn:name":"San Bernardo",
    "gn:population":0,
    "gn:timezone":"America/Monterrey",
    "iso:country":"MX",
    "name:spa_x_preferred":[
        "San Bernardo"
    ],
    "wof:name":"San Bernardo",
    "wof:placetype":"locality"
},
  "geometry": {"coordinates":[-99.70650000000001,27.13902],"type":"Point"}
}