{
  "type": "Feature",
  "properties": {
    "gn:admin1_code":"25",
    "gn:admin2_code":"11.0",
    "gn:asciiname":"San Sebastian Numero Dos",
    "gn:country_code":"MX",
    "gn:dem":30,
    "gn:feature_class":"P",
    "gn:feature_code":"PPL",
    "gn:name":"San Sebasti\u00e1n N\u00famero Dos",
    "gn:population":613,
    "gn:timezone":"America/Mazatlan",
    "iso:country":"MX",
    "name:und_x_variant":[
        "San Sebasti\u00e1n N\u00famero Dos"
    ],
    "wof:name":"San Sebastian Numero Dos",
    "wof:placetype":"locality",
    "wof:population":613
},
  "geometry": {"coordinates":[-108.39833,25.67389],"type":"Point"}
}