{
  "type": "Feature",
  "properties": {
    "gn:admin1_code":"11.0",
    "gn:admin2_code":"1.0",
    "gn:asciiname":"San Francisco de Martinez",
    "gn:country_code":"MX",
    "gn:dem":1694,
    "gn:feature_class":"P",
    "gn:feature_code":"PPL",
    "gn:name":"San Francisco de Mart\u00ednez",
    "gn:population":0,
    "gn:timezone":"America/Mexico_City",
    "iso:country":"MX",
    "name:spa_x_preferred":[
        "San Francisco de Mart\u00ednez"
    ],
    "wof:name":"San Francisco de Martinez",
    "wof:placetype":"locality"
},
  "geometry": {"coordinates":[-101.5215,20.54001],"type":"Point"}
}