{
  "type": "Feature",
  "properties": {
    "gn:admin1_code":"5.0",
    "gn:admin2_code":"59.0",
    "gn:asciiname":"Nuevo Bachajon",
    "gn:country_code":"MX",
    "gn:dem":646,
    "gn:feature_class":"P",
    "gn:feature_code":"PPL",
    "gn:name":"Nuevo Bachaj\u00f3n",
    "gn:population":0,
    "gn:timezone":"America/Mexico_City",
    "iso:country":"MX",
    "name:spa_x_preferred":[
        "Bachajan"
    ],
    "name:spa_x_variant":[
        "Nuevo Bachaj\u00f3n"
    ],
    "wof:name":"Nuevo Bachajon",
    "wof:placetype":"locality"
},
  "geometry": {"coordinates":[-91.60921,16.89783],"type":"Point"}
}