{
  "type": "Feature",
  "properties": {
    "gn:admin1_code":"16.0",
    "gn:admin2_code":"99.0",
    "gn:asciiname":"El Cajon",
    "gn:country_code":"MX",
    "gn:dem":584,
    "gn:feature_class":"P",
    "gn:feature_code":"PPL",
    "gn:name":"El Caj\u00f3n",
    "gn:population":0,
    "gn:timezone":"America/Mexico_City",
    "iso:country":"MX",
    "name:spa_x_preferred":[
        "El Caj\u00f3n"
    ],
    "wof:name":"El Cajon",
    "wof:placetype":"locality"
},
  "geometry": {"coordinates":[-100.486,19.02889],"type":"Point"}
}