{
  "type": "Feature",
  "properties": {
    "gn:admin1_code":"25",
    "gn:admin2_code":"17.0",
    "gn:asciiname":"El Pueblito",
    "gn:country_code":"MX",
    "gn:dem":356,
    "gn:feature_class":"P",
    "gn:feature_code":"PPL",
    "gn:name":"El Pueblito",
    "gn:population":132,
    "gn:timezone":"America/Mazatlan",
    "iso:country":"MX",
    "wof:name":"El Pueblito",
    "wof:placetype":"locality",
    "wof:population":132
},
  "geometry": {"coordinates":[-107.74431,25.75697000000001],"type":"Point"}
}