{
  "type": "Feature",
  "properties": {
    "gn:admin1_code":"30",
    "gn:admin2_code":"111.0",
    "gn:asciiname":"La Bombilla",
    "gn:country_code":"MX",
    "gn:dem":77,
    "gn:feature_class":"P",
    "gn:feature_code":"PPL",
    "gn:name":"La Bombilla",
    "gn:population":0,
    "gn:timezone":"America/Mexico_City",
    "iso:country":"MX",
    "name:spa_x_preferred":[
        "La Bombilla"
    ],
    "wof:name":"La Bombilla",
    "wof:placetype":"locality"
},
  "geometry": {"coordinates":[-94.22553000000001,18.00473999999999],"type":"Point"}
}