{
  "type": "Feature",
  "properties": {
    "gn:admin1_code":"5",
    "gn:admin2_code":"93.0",
    "gn:asciiname":"Ococh",
    "gn:country_code":"MX",
    "gn:dem":1943,
    "gn:feature_class":"P",
    "gn:feature_code":"PPL",
    "gn:name":"Ococh",
    "gn:population":1187,
    "gn:timezone":"America/Mexico_City",
    "iso:country":"MX",
    "wof:name":"Ococh",
    "wof:placetype":"locality",
    "wof:population":1187
},
  "geometry": {"coordinates":[-92.47528,16.83806],"type":"Point"}
}