{
  "type": "Feature",
  "properties": {
    "gn:admin1_code":"5",
    "gn:admin2_code":"17.0",
    "gn:asciiname":"El Manguito",
    "gn:country_code":"MX",
    "gn:dem":582,
    "gn:feature_class":"P",
    "gn:feature_code":"PPL",
    "gn:name":"El Manguito",
    "gn:population":7,
    "gn:timezone":"America/Mexico_City",
    "iso:country":"MX",
    "wof:name":"El Manguito",
    "wof:placetype":"locality",
    "wof:population":7
},
  "geometry": {"coordinates":[-93.78861000000001,16.65056],"type":"Point"}
}