{
  "type": "Feature",
  "properties": {
    "gn:admin1_code":"30",
    "gn:admin2_code":"174.0",
    "gn:asciiname":"Las Prietas",
    "gn:country_code":"MX",
    "gn:dem":77,
    "gn:feature_class":"P",
    "gn:feature_code":"PPL",
    "gn:name":"Las Prietas",
    "gn:population":0,
    "gn:timezone":"America/Mexico_City",
    "iso:country":"MX",
    "name:spa_x_preferred":[
        "Las Prietas"
    ],
    "wof:name":"Las Prietas",
    "wof:placetype":"locality"
},
  "geometry": {"coordinates":[-96.41200000000001,18.5022],"type":"Point"}
}