{
  "type": "Feature",
  "properties": {
    "gn:admin1_code":"8",
    "gn:admin2_code":"9",
    "gn:asciiname":"El Sifon",
    "gn:country_code":"MX",
    "gn:dem":16,
    "gn:feature_class":"P",
    "gn:feature_code":"PPL",
    "gn:name":"El Sif\u00f3n",
    "gn:population":9,
    "gn:timezone":"America/Mexico_City",
    "iso:country":"MX",
    "name:und_x_variant":[
        "El Sif\u00f3n"
    ],
    "wof:name":"El Sifon",
    "wof:placetype":"locality",
    "wof:population":9
},
  "geometry": {"coordinates":[-103.715,18.77861],"type":"Point"}
}