{
  "type": "Feature",
  "properties": {
    "gn:admin1_code":"28",
    "gn:admin2_code":"40",
    "gn:asciiname":"16 de Septiembre (Brecha 126 entre Sur 91 y Sur 93)",
    "gn:country_code":"MX",
    "gn:dem":11,
    "gn:feature_class":"P",
    "gn:feature_code":"PPL",
    "gn:name":"16 de Septiembre (Brecha 126 entre Sur 91 y Sur 93)",
    "gn:population":16,
    "gn:timezone":"America/Matamoros",
    "iso:country":"MX",
    "wof:name":"16 de Septiembre (Brecha 126 entre Sur 91 y Sur 93)",
    "wof:placetype":"locality",
    "wof:population":16
},
  "geometry": {"coordinates":[-97.75583,25.57806],"type":"Point"}
}