{
  "type": "Feature",
  "properties": {
    "gn:admin1_code":"14",
    "gn:admin2_code":"115.0",
    "gn:asciiname":"Los Sabinos",
    "gn:country_code":"MX",
    "gn:dem":1297,
    "gn:feature_class":"P",
    "gn:feature_code":"PPL",
    "gn:name":"Los Sabinos",
    "gn:population":0,
    "gn:timezone":"America/Mexico_City",
    "iso:country":"MX",
    "name:spa_x_preferred":[
        "Los Sabinos"
    ],
    "wof:name":"Los Sabinos",
    "wof:placetype":"locality"
},
  "geometry": {"coordinates":[-103.69508,21.99306],"type":"Point"}
}