{
  "type": "Feature",
  "properties": {
    "gn:admin1_code":"6",
    "gn:admin2_code":"3.0",
    "gn:asciiname":"Rancho Blanco",
    "gn:country_code":"MX",
    "gn:dem":1541,
    "gn:feature_class":"P",
    "gn:feature_code":"PPL",
    "gn:name":"Rancho Blanco",
    "gn:population":123,
    "gn:timezone":"America/Chihuahua",
    "iso:country":"MX",
    "name:spa_x_preferred":[
        "Rancho Blanco"
    ],
    "wof:name":"Rancho Blanco",
    "wof:placetype":"locality",
    "wof:population":123
},
  "geometry": {"coordinates":[-105.26621000000002,26.99223],"type":"Point"}
}