{
  "type": "Feature",
  "properties": {
    "gn:admin1_code":"27",
    "gn:admin2_code":"12.0",
    "gn:asciiname":"Melchor Ocampo Primera Seccion",
    "gn:country_code":"MX",
    "gn:dem":47,
    "gn:feature_class":"P",
    "gn:feature_code":"PPL",
    "gn:name":"Melchor Ocampo Primera Secci\u00f3n",
    "gn:population":0,
    "gn:timezone":"America/Mexico_City",
    "iso:country":"MX",
    "name:spa_x_preferred":[
        "Melchor Ocampo"
    ],
    "name:spa_x_variant":[
        "Melchor Ocampo Primera Secci\u00f3n"
    ],
    "wof:name":"Melchor Ocampo Primera Seccion",
    "wof:placetype":"locality"
},
  "geometry": {"coordinates":[-92.48368000000001,17.579],"type":"Point"}
}