{
  "type": "Feature",
  "properties": {
    "gn:admin1_code":"28.0",
    "gn:admin2_code":"21.0",
    "gn:asciiname":"Porvenir del Campesino",
    "gn:country_code":"MX",
    "gn:dem":67,
    "gn:feature_class":"P",
    "gn:feature_code":"PPL",
    "gn:name":"Porvenir del Campesino",
    "gn:population":49,
    "gn:timezone":"America/Monterrey",
    "iso:country":"MX",
    "name:spa_x_preferred":[
        "Porvenir del Campesino"
    ],
    "wof:name":"Porvenir del Campesino",
    "wof:placetype":"locality",
    "wof:population":49
},
  "geometry": {"coordinates":[-98.97139,22.79694],"type":"Point"}
}