{
  "type": "Feature",
  "properties": {
    "gn:admin1_code":"5",
    "gn:admin2_code":"108",
    "gn:asciiname":"Santo Domingo",
    "gn:country_code":"MX",
    "gn:dem":1214,
    "gn:feature_class":"P",
    "gn:feature_code":"PPL",
    "gn:name":"Santo Domingo",
    "gn:population":16,
    "gn:timezone":"America/Mexico_City",
    "iso:country":"MX",
    "wof:name":"Santo Domingo",
    "wof:placetype":"locality",
    "wof:population":16
},
  "geometry": {"coordinates":[-93.16222,16.38694],"type":"Point"}
}