{
  "type": "Feature",
  "properties": {
    "gn:admin1_code":"19",
    "gn:admin2_code":"22.0",
    "gn:asciiname":"La Escondida",
    "gn:country_code":"MX",
    "gn:dem":208,
    "gn:feature_class":"P",
    "gn:feature_code":"PPL",
    "gn:name":"La Escondida",
    "gn:population":0,
    "gn:timezone":"America/Monterrey",
    "iso:country":"MX",
    "name:spa_x_preferred":[
        "La Escondida"
    ],
    "wof:name":"La Escondida",
    "wof:placetype":"locality"
},
  "geometry": {"coordinates":[-99.27931,25.15741],"type":"Point"}
}