{
  "type": "Feature",
  "properties": {
    "gn:admin1_code":"5.0",
    "gn:admin2_code":"94.0",
    "gn:asciiname":"Los Nogales",
    "gn:country_code":"MX",
    "gn:dem":1822,
    "gn:feature_class":"P",
    "gn:feature_code":"PPL",
    "gn:name":"Los Nogales",
    "gn:population":0,
    "gn:timezone":"America/Mexico_City",
    "iso:country":"MX",
    "name:spa_x_preferred":[
        "Los Nogales"
    ],
    "wof:name":"Los Nogales",
    "wof:placetype":"locality"
},
  "geometry": {"coordinates":[-92.4939,16.56512],"type":"Point"}
}