{
  "type": "Feature",
  "properties": {
    "gn:admin1_code":"22.0",
    "gn:admin2_code":"14.0",
    "gn:asciiname":"El Tajo",
    "gn:country_code":"MX",
    "gn:dem":2227,
    "gn:feature_class":"P",
    "gn:feature_code":"PPL",
    "gn:name":"El Tajo",
    "gn:population":0,
    "gn:timezone":"America/Mexico_City",
    "iso:country":"MX",
    "name:spa_x_preferred":[
        "El Tajo"
    ],
    "wof:name":"El Tajo",
    "wof:placetype":"locality"
},
  "geometry": {"coordinates":[-100.38693000000001,20.88581],"type":"Point"}
}