{
  "type": "Feature",
  "properties": {
    "gn:admin1_code":"13",
    "gn:admin2_code":"10.0",
    "gn:asciiname":"Napoles",
    "gn:country_code":"MX",
    "gn:dem":2184,
    "gn:feature_class":"P",
    "gn:feature_code":"PPL",
    "gn:name":"N\u00e1poles",
    "gn:population":0,
    "gn:timezone":"America/Mexico_City",
    "iso:country":"MX",
    "name:und_x_variant":[
        "N\u00e1poles"
    ],
    "wof:name":"Napoles",
    "wof:placetype":"locality"
},
  "geometry": {"coordinates":[-99.18333,20.05],"type":"Point"}
}