{
  "type": "Feature",
  "properties": {
    "gn:admin1_code":"22",
    "gn:admin2_code":"1.0",
    "gn:asciiname":"Los Argueta",
    "gn:country_code":"MX",
    "gn:dem":2706,
    "gn:feature_class":"P",
    "gn:feature_code":"PPL",
    "gn:name":"Los Argueta",
    "gn:population":67,
    "gn:timezone":"America/Mexico_City",
    "iso:country":"MX",
    "wof:name":"Los Argueta",
    "wof:placetype":"locality",
    "wof:population":67
},
  "geometry": {"coordinates":[-100.13833,20.17028],"type":"Point"}
}