{
  "type": "Feature",
  "properties": {
    "gn:admin1_code":"26.0",
    "gn:admin2_code":"47.0",
    "gn:asciiname":"La Rama",
    "gn:country_code":"MX",
    "gn:dem":364,
    "gn:feature_class":"P",
    "gn:feature_code":"PPL",
    "gn:name":"La Rama",
    "gn:population":0,
    "gn:timezone":"America/Hermosillo",
    "iso:country":"MX",
    "name:spa_x_preferred":[
        "La Rama"
    ],
    "wof:name":"La Rama",
    "wof:placetype":"locality"
},
  "geometry": {"coordinates":[-111.89558999999998,30.58291],"type":"Point"}
}