{
  "type": "Feature",
  "properties": {
    "gn:admin1_code":"30",
    "gn:admin2_code":"141.0",
    "gn:asciiname":"El Huidero",
    "gn:country_code":"MX",
    "gn:dem":264,
    "gn:feature_class":"P",
    "gn:feature_code":"PPL",
    "gn:name":"El Huidero",
    "gn:population":1010,
    "gn:timezone":"America/Mexico_City",
    "iso:country":"MX",
    "wof:name":"El Huidero",
    "wof:placetype":"locality",
    "wof:population":1010
},
  "geometry": {"coordinates":[-95.17917,18.3875],"type":"Point"}
}