{
  "type": "Feature",
  "properties": {
    "gn:admin1_code":"28",
    "gn:admin2_code":"27.0",
    "gn:asciiname":"Bayito Arriba",
    "gn:country_code":"MX",
    "gn:dem":119,
    "gn:feature_class":"P",
    "gn:feature_code":"PPL",
    "gn:name":"Bayito Arriba",
    "gn:population":0,
    "gn:timezone":"America/Matamoros",
    "iso:country":"MX",
    "wof:name":"Bayito Arriba",
    "wof:placetype":"locality"
},
  "geometry": {"coordinates":[-99.51667,27.56667],"type":"Point"}
}