{
  "type": "Feature",
  "properties": {
    "gn:admin1_code":"14",
    "gn:admin2_code":"46",
    "gn:asciiname":"Vallarta (El Halcon)",
    "gn:country_code":"MX",
    "gn:dem":1801,
    "gn:feature_class":"P",
    "gn:feature_code":"PPL",
    "gn:name":"Vallarta (El Halc\u00f3n)",
    "gn:population":22,
    "gn:timezone":"America/Mexico_City",
    "iso:country":"MX",
    "name:und_x_variant":[
        "Vallarta (El Halc\u00f3n)"
    ],
    "wof:name":"Vallarta (El Halcon)",
    "wof:placetype":"locality",
    "wof:population":22
},
  "geometry": {"coordinates":[-102.48889,21.24722],"type":"Point"}
}