{
  "type": "Feature",
  "properties": {
    "gn:admin1_code":"6",
    "gn:admin2_code":"41.0",
    "gn:asciiname":"Secomachi",
    "gn:country_code":"MX",
    "gn:dem":1953,
    "gn:feature_class":"P",
    "gn:feature_code":"PPL",
    "gn:name":"Sec\u00f3machi",
    "gn:population":0,
    "gn:timezone":"America/Chihuahua",
    "iso:country":"MX",
    "name:spa_x_preferred":[
        "Sec\u00f3machi"
    ],
    "wof:name":"Secomachi",
    "wof:placetype":"locality"
},
  "geometry": {"coordinates":[-107.90407999999999,27.81111],"type":"Point"}
}