{
  "type": "Feature",
  "properties": {
    "gn:admin1_code":"21",
    "gn:admin2_code":"99.0",
    "gn:asciiname":"San Miguel Cuesta Chica",
    "gn:country_code":"MX",
    "gn:dem":2413,
    "gn:feature_class":"P",
    "gn:feature_code":"PPL",
    "gn:name":"San Miguel Cuesta Chica",
    "gn:population":258,
    "gn:timezone":"America/Mexico_City",
    "iso:country":"MX",
    "wof:name":"San Miguel Cuesta Chica",
    "wof:placetype":"locality",
    "wof:population":258
},
  "geometry": {"coordinates":[-97.3884,18.81126],"type":"Point"}
}