{
  "type": "Feature",
  "properties": {
    "gn:admin1_code":"5",
    "gn:admin2_code":"59.0",
    "gn:asciiname":"Nueva las Tacitas",
    "gn:country_code":"MX",
    "gn:dem":829,
    "gn:feature_class":"P",
    "gn:feature_code":"PPL",
    "gn:name":"Nueva las Tacitas",
    "gn:population":383,
    "gn:timezone":"America/Mexico_City",
    "iso:country":"MX",
    "wof:name":"Nueva las Tacitas",
    "wof:placetype":"locality",
    "wof:population":383
},
  "geometry": {"coordinates":[-91.53639,16.66722],"type":"Point"}
}