{
  "type": "Feature",
  "properties": {
    "gn:admin1_code":"8",
    "gn:admin2_code":"9.0",
    "gn:asciiname":"Silvestre (El Fenix)",
    "gn:country_code":"MX",
    "gn:dem":46,
    "gn:feature_class":"P",
    "gn:feature_code":"PPL",
    "gn:name":"Silvestre (El F\u00e9nix)",
    "gn:population":6,
    "gn:timezone":"America/Mexico_City",
    "iso:country":"MX",
    "name:und_x_variant":[
        "Silvestre (El F\u00e9nix)"
    ],
    "wof:name":"Silvestre (El Fenix)",
    "wof:placetype":"locality",
    "wof:population":6
},
  "geometry": {"coordinates":[-103.85194,18.93806],"type":"Point"}
}