{
  "type": "Feature",
  "properties": {
    "gn:admin1_code":"31",
    "gn:admin2_code":"26.0",
    "gn:asciiname":"Xtampu",
    "gn:country_code":"MX",
    "gn:dem":2,
    "gn:feature_class":"P",
    "gn:feature_code":"PPL",
    "gn:name":"Xtamp\u00fa",
    "gn:population":4,
    "gn:timezone":"America/Merida",
    "iso:country":"MX",
    "wof:name":"Xtampu",
    "wof:placetype":"locality",
    "wof:population":4
},
  "geometry": {"coordinates":[-89.34860999999999,21.33417],"type":"Point"}
}