{
  "type": "Feature",
  "properties": {
    "gn:admin1_code":"25",
    "gn:admin2_code":"12.0",
    "gn:asciiname":"La Mariposa",
    "gn:country_code":"MX",
    "gn:dem":45,
    "gn:feature_class":"P",
    "gn:feature_code":"PPL",
    "gn:name":"La Mariposa",
    "gn:population":0,
    "gn:timezone":"America/Mazatlan",
    "iso:country":"MX",
    "name:spa_x_preferred":[
        "La Mariposa"
    ],
    "wof:name":"La Mariposa",
    "wof:placetype":"locality"
},
  "geometry": {"coordinates":[-106.46588,23.50309],"type":"Point"}
}