{
  "type": "Feature",
  "properties": {
    "gn:admin1_code":"5",
    "gn:admin2_code":"77.0",
    "gn:asciiname":"El Progreso",
    "gn:country_code":"MX",
    "gn:dem":69,
    "gn:feature_class":"P",
    "gn:feature_code":"PPL",
    "gn:name":"El Progreso",
    "gn:population":924,
    "gn:timezone":"America/Mexico_City",
    "iso:country":"MX",
    "wof:name":"El Progreso",
    "wof:placetype":"locality",
    "wof:population":924
},
  "geometry": {"coordinates":[-92.37111,17.40889],"type":"Point"}
}