{
  "type": "Feature",
  "properties": {
    "gn:admin1_code":"5",
    "gn:admin2_code":"77.0",
    "gn:asciiname":"El Progreso",
    "gn:country_code":"MX",
    "gn:dem":69,
    "gn:feature_class":"P",
    "gn:feature_code":"PPL",
    "gn:name":"El Progreso",
    "gn:population":924,
    "gn:timezone":"America/Mexico_City",
    "iso:country":"MX",
    "name:bul_x_preferred":[
        "\u0415\u043b \u041f\u0440\u043e\u0433\u0440\u0435\u0441\u043e"
    ],
    "name:cat_x_preferred":[
        "El Progreso"
    ],
    "name:ceb_x_preferred":[
        "El Progreso"
    ],
    "name:fra_x_preferred":[
        "El Progreso"
    ],
    "name:ita_x_preferred":[
        "El Progreso"
    ],
    "name:jpn_x_preferred":[
        "\u30a8\u30eb\u30fb\u30d7\u30ed\u30b0\u30ec\u30bd"
    ],
    "name:lit_x_preferred":[
        "El Progresas"
    ],
    "name:nld_x_preferred":[
        "El Progreso"
    ],
    "name:pol_x_preferred":[
        "El Progreso"
    ],
    "name:por_x_preferred":[
        "El Progreso"
    ],
    "name:rus_x_preferred":[
        "\u042d\u043b\u044c-\u041f\u0440\u043e\u0433\u0440\u0435\u0441\u043e"
    ],
    "name:spa_x_preferred":[
        "El Progreso"
    ],
    "name:swe_x_preferred":[
        "El Progreso"
    ],
    "name:ukr_x_preferred":[
        "\u0415\u043b\u044c-\u041f\u0440\u043e\u0433\u0440\u0435\u0441\u043e"
    ],
    "name:war_x_preferred":[
        "El Progreso"
    ],
    "name:zho_x_preferred":[
        "\u57c3\u723e\u666e\u7f85\u683c\u96f7\u7d22"
    ],
    "wof:name":"El Progreso",
    "wof:placetype":"locality",
    "wof:population":924
},
  "geometry": {"coordinates":[-92.37111,17.40889],"type":"Point"}
}