{
  "type": "Feature",
  "properties": {
    "gn:admin1_code":"28",
    "gn:admin2_code":"14.0",
    "gn:asciiname":"Penitas",
    "gn:country_code":"MX",
    "gn:dem":128,
    "gn:feature_class":"P",
    "gn:feature_code":"PPL",
    "gn:name":"Pe\u00f1itas",
    "gn:population":1,
    "gn:timezone":"America/Monterrey",
    "iso:country":"MX",
    "name:und_x_variant":[
        "Rancho Pe\u00f1ita",
        "Pe\u00f1itas"
    ],
    "wof:name":"Penitas",
    "wof:placetype":"locality",
    "wof:population":1
},
  "geometry": {"coordinates":[-99.49841000000001,27.17711],"type":"Point"}
}