{
  "type": "Feature",
  "properties": {
    "gn:admin1_code":"24",
    "gn:admin2_code":"25.0",
    "gn:asciiname":"El Cuervo",
    "gn:country_code":"MX",
    "gn:dem":2103,
    "gn:feature_class":"P",
    "gn:feature_code":"PPL",
    "gn:name":"El Cuervo",
    "gn:population":149,
    "gn:timezone":"America/Mexico_City",
    "iso:country":"MX",
    "name:ceb_x_preferred":[
        "El Cuervo"
    ],
    "name:deu_x_preferred":[
        "El Cuervo"
    ],
    "name:spa_x_preferred":[
        "El cuervo"
    ],
    "name:swe_x_preferred":[
        "El Cuervo"
    ],
    "wof:name":"El Cuervo",
    "wof:placetype":"locality",
    "wof:population":149
},
  "geometry": {"coordinates":[-101.79778,22.47972],"type":"Point"}
}