{
  "type": "Feature",
  "properties": {
    "gn:admin1_code":"5",
    "gn:admin2_code":"102.0",
    "gn:asciiname":"Fraccion la Jeringa",
    "gn:country_code":"MX",
    "gn:dem":110,
    "gn:feature_class":"P",
    "gn:feature_code":"PPL",
    "gn:name":"Fracci\u00f3n la Jeringa",
    "gn:population":135,
    "gn:timezone":"America/Mexico_City",
    "iso:country":"MX",
    "name:und_x_variant":[
        "Fracci\u00f3n la Jeringa"
    ],
    "wof:name":"Fraccion la Jeringa",
    "wof:placetype":"locality",
    "wof:population":135
},
  "geometry": {"coordinates":[-92.23611,14.85194],"type":"Point"}
}