{
  "type": "Feature",
  "properties": {
    "gn:admin1_code":"26",
    "gn:admin2_code":"18.0",
    "gn:asciiname":"Jesus Roman",
    "gn:country_code":"MX",
    "gn:dem":53,
    "gn:feature_class":"P",
    "gn:feature_code":"PPL",
    "gn:name":"Jes\u00fas Rom\u00e1n",
    "gn:population":6,
    "gn:timezone":"America/Hermosillo",
    "iso:country":"MX",
    "name:und_x_variant":[
        "Jes\u00fas Rom\u00e1n"
    ],
    "wof:name":"Jesus Roman",
    "wof:placetype":"locality",
    "wof:population":6
},
  "geometry": {"coordinates":[-109.86917,27.47417],"type":"Point"}
}