{
  "type": "Feature",
  "properties": {
    "gn:admin1_code":"9",
    "gn:admin2_code":"9.0",
    "gn:asciiname":"Tecpallo",
    "gn:country_code":"MX",
    "gn:dem":2396,
    "gn:feature_class":"P",
    "gn:feature_code":"PPL",
    "gn:name":"Tecpallo",
    "gn:population":117,
    "gn:timezone":"America/Mexico_City",
    "iso:country":"MX",
    "wof:name":"Tecpallo",
    "wof:placetype":"locality",
    "wof:population":117
},
  "geometry": {"coordinates":[-98.98999999999999,19.19667],"type":"Point"}
}