{
  "type": "Feature",
  "properties": {
    "gn:admin1_code":"14.0",
    "gn:asciiname":"Casco Viejo",
    "gn:country_code":"MX",
    "gn:dem":1795,
    "gn:feature_class":"P",
    "gn:feature_code":"PPL",
    "gn:name":"Casco Viejo",
    "gn:population":0,
    "gn:timezone":"America/Mexico_City",
    "iso:country":"MX",
    "wof:name":"Casco Viejo",
    "wof:placetype":"locality"
},
  "geometry": {"coordinates":[-101.86667,21.06667],"type":"Point"}
}