{
  "type": "Feature",
  "properties": {
    "gn:admin1_code":"14.0",
    "gn:asciiname":"Casco Viejo",
    "gn:country_code":"MX",
    "gn:dem":1795,
    "gn:feature_class":"P",
    "gn:feature_code":"PPL",
    "gn:name":"Casco Viejo",
    "gn:population":0,
    "gn:timezone":"America/Mexico_City",
    "iso:country":"MX",
    "name:cat_x_preferred":[
        "Zazpikaleak"
    ],
    "name:eus_x_preferred":[
        "Zazpikaleak"
    ],
    "name:fra_x_preferred":[
        "Zazpi Kaleak"
    ],
    "name:jpn_x_preferred":[
        "\u30ab\u30b9\u30b3\u30fb\u30d3\u30a8\u30db"
    ],
    "name:olo_x_preferred":[
        "Zazpikaleak"
    ],
    "name:spa_x_preferred":[
        "Casco Viejo"
    ],
    "name:zho_x_preferred":[
        "\u7562\u723e\u5305\u820a\u57ce"
    ],
    "wof:name":"Casco Viejo",
    "wof:placetype":"locality"
},
  "geometry": {"coordinates":[-101.86667,21.06667],"type":"Point"}
}