{
  "type": "Feature",
  "properties": {
    "gn:admin1_code":"5",
    "gn:admin2_code":"61.0",
    "gn:asciiname":"La Piedrona",
    "gn:country_code":"MX",
    "gn:dem":830,
    "gn:feature_class":"P",
    "gn:feature_code":"PPL",
    "gn:name":"La Piedrona",
    "gn:population":8,
    "gn:timezone":"America/Mexico_City",
    "iso:country":"MX",
    "wof:name":"La Piedrona",
    "wof:placetype":"locality",
    "wof:population":8
},
  "geometry": {"coordinates":[-93.47806,16.47083],"type":"Point"}
}