{
  "type": "Feature",
  "properties": {
    "gn:admin1_code":"7",
    "gn:admin2_code":"7.0",
    "gn:asciiname":"Nuevo Atalaya",
    "gn:country_code":"MX",
    "gn:dem":780,
    "gn:feature_class":"P",
    "gn:feature_code":"PPL",
    "gn:name":"Nuevo Atalaya",
    "gn:population":0,
    "gn:timezone":"America/Monterrey",
    "iso:country":"MX",
    "name:spa_x_preferred":[
        "Nuevo Atalaya"
    ],
    "name:spa_x_variant":[
        "San Marcos"
    ],
    "wof:name":"Nuevo Atalaya",
    "wof:placetype":"locality"
},
  "geometry": {"coordinates":[-102.15264000000001,26.80739],"type":"Point"}
}