{
  "type": "Feature",
  "properties": {
    "gn:admin1_code":"11",
    "gn:admin2_code":"20.0",
    "gn:asciiname":"Las Coloradas",
    "gn:country_code":"MX",
    "gn:dem":1968,
    "gn:feature_class":"P",
    "gn:feature_code":"PPL",
    "gn:name":"Las Coloradas",
    "gn:population":647,
    "gn:timezone":"America/Mexico_City",
    "iso:country":"MX",
    "wof:name":"Las Coloradas",
    "wof:placetype":"locality",
    "wof:population":647
},
  "geometry": {"coordinates":[-101.5025,21.0975],"type":"Point"}
}