{
  "type": "Feature",
  "properties": {
    "gn:admin1_code":"28",
    "gn:admin2_code":"2.0",
    "gn:asciiname":"El Pichijumo",
    "gn:country_code":"MX",
    "gn:dem":113,
    "gn:feature_class":"P",
    "gn:feature_code":"PPL",
    "gn:name":"El Pichijumo",
    "gn:population":0,
    "gn:timezone":"America/Monterrey",
    "iso:country":"MX",
    "name:spa_x_preferred":[
        "El Pichijumo"
    ],
    "name:und_x_variant":[
        "Pichujumo"
    ],
    "wof:name":"El Pichijumo",
    "wof:placetype":"locality"
},
  "geometry": {"coordinates":[-98.03231,23.26937],"type":"Point"}
}