{
  "type": "Feature",
  "properties": {
    "gn:admin1_code":"3",
    "gn:admin2_code":"1.0",
    "gn:asciiname":"Colonia Cuauhtemoc",
    "gn:country_code":"MX",
    "gn:dem":57,
    "gn:feature_class":"P",
    "gn:feature_code":"PPL",
    "gn:name":"Colonia Cuauht\u00e9moc",
    "gn:population":0,
    "gn:timezone":"America/Mazatlan",
    "iso:country":"MX",
    "name:spa_x_preferred":[
        "Colonia Cuauht\u00e9moc"
    ],
    "wof:name":"Colonia Cuauhtemoc",
    "wof:placetype":"locality"
},
  "geometry": {"coordinates":[-111.66365,25.17505],"type":"Point"}
}