{
  "type": "Feature",
  "properties": {
    "gn:admin1_code":"5",
    "gn:admin2_code":"22.0",
    "gn:asciiname":"Tzunumil",
    "gn:country_code":"MX",
    "gn:dem":977,
    "gn:feature_class":"P",
    "gn:feature_code":"PPL",
    "gn:name":"Tzunumil",
    "gn:population":0,
    "gn:timezone":"America/Mexico_City",
    "iso:country":"MX",
    "name:spa_x_preferred":[
        "Tzunumil"
    ],
    "name:spa_x_variant":[
        "Tzununil"
    ],
    "wof:name":"Tzunumil",
    "wof:placetype":"locality"
},
  "geometry": {"coordinates":[-92.60599999999999,17.05567000000001],"type":"Point"}
}