{
  "type": "Feature",
  "properties": {
    "gn:admin1_code":"13",
    "gn:admin2_code":"6.0",
    "gn:asciiname":"La Fe",
    "gn:country_code":"MX",
    "gn:dem":1997,
    "gn:feature_class":"P",
    "gn:feature_code":"PPL",
    "gn:name":"La Fe",
    "gn:population":0,
    "gn:timezone":"America/Mexico_City",
    "iso:country":"MX",
    "name:spa_x_preferred":[
        "La Fe"
    ],
    "name:srp_x_preferred":[
        "\u041b\u0430 \u0424\u0435"
    ],
    "wof:name":"La Fe",
    "wof:placetype":"locality"
},
  "geometry": {"coordinates":[-99.34865000000001,20.35222000000001],"type":"Point"}
}