{
  "type": "Feature",
  "properties": {
    "gn:admin1_code":"19.0",
    "gn:admin2_code":"5.0",
    "gn:asciiname":"El Setenta",
    "gn:country_code":"MX",
    "gn:dem":144,
    "gn:feature_class":"P",
    "gn:feature_code":"PPL",
    "gn:name":"El Setenta",
    "gn:population":1,
    "gn:timezone":"America/Matamoros",
    "iso:country":"MX",
    "name:spa_x_preferred":[
        "El Carmen"
    ],
    "wof:name":"El Setenta",
    "wof:placetype":"locality",
    "wof:population":1
},
  "geometry": {"coordinates":[-99.87286,26.89922],"type":"Point"}
}