{
  "type": "Feature",
  "properties": {
    "gn:admin1_code":"10",
    "gn:admin2_code":"37.0",
    "gn:asciiname":"Canada de las Becerras",
    "gn:country_code":"MX",
    "gn:dem":2578,
    "gn:feature_class":"P",
    "gn:feature_code":"PPL",
    "gn:name":"Ca\u00f1ada de las Becerras",
    "gn:population":0,
    "gn:timezone":"America/Monterrey",
    "iso:country":"MX",
    "name:spa_x_preferred":[
        "Ca\u00f1ada de las Becerras"
    ],
    "wof:name":"Canada de las Becerras",
    "wof:placetype":"locality"
},
  "geometry": {"coordinates":[-106.49003999999999,25.20288],"type":"Point"}
}