{
  "type": "Feature",
  "properties": {
    "gn:admin1_code":"6",
    "gn:admin2_code":"29",
    "gn:asciiname":"Puerto Blanco (Puerto Carnero)",
    "gn:country_code":"MX",
    "gn:dem":2858,
    "gn:feature_class":"P",
    "gn:feature_code":"PPL",
    "gn:name":"Puerto Blanco (Puerto Carnero)",
    "gn:population":10,
    "gn:timezone":"America/Chihuahua",
    "iso:country":"MX",
    "wof:name":"Puerto Blanco (Puerto Carnero)",
    "wof:placetype":"locality",
    "wof:population":10
},
  "geometry": {"coordinates":[-106.56263,26.13051],"type":"Point"}
}