{
  "type": "Feature",
  "properties": {
    "gn:admin1_code":"27",
    "gn:asciiname":"Bajadas Grandes",
    "gn:country_code":"MX",
    "gn:dem":20,
    "gn:feature_class":"P",
    "gn:feature_code":"PPL",
    "gn:name":"Bajadas Grandes",
    "gn:population":0,
    "gn:timezone":"America/Mexico_City",
    "iso:country":"MX",
    "name:spa_x_preferred":[
        "Bajadas Grandes"
    ],
    "wof:name":"Bajadas Grandes",
    "wof:placetype":"locality"
},
  "geometry": {"coordinates":[-92.26166000000001,17.7008],"type":"Point"}
}