{
  "type": "Feature",
  "properties": {
    "gn:admin1_code":"28.0",
    "gn:admin2_code":"27.0",
    "gn:asciiname":"San Vicente",
    "gn:country_code":"MX",
    "gn:dem":142,
    "gn:feature_class":"P",
    "gn:feature_code":"PPL",
    "gn:name":"San Vicente",
    "gn:population":2,
    "gn:timezone":"America/Matamoros",
    "iso:country":"MX",
    "name:spa_x_preferred":[
        "San Vicente"
    ],
    "wof:name":"San Vicente",
    "wof:placetype":"locality",
    "wof:population":2
},
  "geometry": {"coordinates":[-99.67639,27.64222],"type":"Point"}
}