{
  "type": "Feature",
  "properties": {
    "gn:admin1_code":"21",
    "gn:admin2_code":"172.0",
    "gn:asciiname":"Tateno",
    "gn:country_code":"MX",
    "gn:dem":1853,
    "gn:feature_class":"P",
    "gn:feature_code":"PPL",
    "gn:name":"Tateno",
    "gn:population":170,
    "gn:timezone":"America/Mexico_City",
    "iso:country":"MX",
    "wof:name":"Tateno",
    "wof:placetype":"locality",
    "wof:population":170
},
  "geometry": {"coordinates":[-97.71986,19.83553],"type":"Point"}
}