{
  "type": "Feature",
  "properties": {
    "gn:admin1_code":"30.0",
    "gn:admin2_code":"155.0",
    "gn:asciiname":"Dos Hermanos",
    "gn:country_code":"MX",
    "gn:dem":105,
    "gn:feature_class":"P",
    "gn:feature_code":"PPL",
    "gn:name":"Dos Hermanos",
    "gn:population":0,
    "gn:timezone":"America/Mexico_City",
    "iso:country":"MX",
    "name:spa_x_preferred":[
        "Dos Hermanos"
    ],
    "wof:name":"Dos Hermanos",
    "wof:placetype":"locality"
},
  "geometry": {"coordinates":[-98.16556,21.52722],"type":"Point"}
}