{
  "type": "Feature",
  "properties": {
    "gn:admin1_code":"20",
    "gn:admin2_code":"515.0",
    "gn:asciiname":"Guelaguechi",
    "gn:country_code":"MX",
    "gn:dem":14,
    "gn:feature_class":"P",
    "gn:feature_code":"PPL",
    "gn:name":"Guelaguechi",
    "gn:population":515,
    "gn:timezone":"America/Mexico_City",
    "iso:country":"MX",
    "wof:name":"Guelaguechi",
    "wof:placetype":"locality",
    "wof:population":515
},
  "geometry": {"coordinates":[-95.29611,16.12028],"type":"Point"}
}