{
  "type": "Feature",
  "properties": {
    "gn:admin1_code":"6",
    "gn:admin2_code":"27.0",
    "gn:asciiname":"Somarachi",
    "gn:country_code":"MX",
    "gn:dem":2210,
    "gn:feature_class":"P",
    "gn:feature_code":"PPL",
    "gn:name":"Som\u00e1rachi",
    "gn:population":0,
    "gn:timezone":"America/Chihuahua",
    "iso:country":"MX",
    "name:spa_x_preferred":[
        "Som\u00e1rachi"
    ],
    "wof:name":"Somarachi",
    "wof:placetype":"locality"
},
  "geometry": {"coordinates":[-107.56977000000001,27.49536],"type":"Point"}
}