{
  "type": "Feature",
  "properties": {
    "gn:admin1_code":"6",
    "gn:admin2_code":"7.0",
    "gn:asciiname":"El Burro",
    "gn:country_code":"MX",
    "gn:dem":2471,
    "gn:feature_class":"P",
    "gn:feature_code":"PPL",
    "gn:name":"El Burro",
    "gn:population":0,
    "gn:timezone":"America/Chihuahua",
    "iso:country":"MX",
    "name:spa_x_preferred":[
        "El Burro"
    ],
    "name:spa_x_variant":[
        "Humedal El Burro"
    ],
    "wof:name":"El Burro",
    "wof:placetype":"locality"
},
  "geometry": {"coordinates":[-106.58450999999999,26.563],"type":"Point"}
}