{
  "type": "Feature",
  "properties": {
    "gn:admin1_code":"5.0",
    "gn:asciiname":"El Vertedor",
    "gn:country_code":"MX",
    "gn:dem":1100,
    "gn:feature_class":"P",
    "gn:feature_code":"PPL",
    "gn:name":"El Vertedor",
    "gn:population":0,
    "gn:timezone":"America/Mexico_City",
    "iso:country":"MX",
    "name:spa_x_preferred":[
        "El Vertedor"
    ],
    "wof:name":"El Vertedor",
    "wof:placetype":"locality"
},
  "geometry": {"coordinates":[-92.40582000000001,16.36226],"type":"Point"}
}