{
  "type": "Feature",
  "properties": {
    "gn:admin1_code":"3.0",
    "gn:admin2_code":"3.0",
    "gn:asciiname":"Los Inocentes",
    "gn:country_code":"MX",
    "gn:dem":8,
    "gn:feature_class":"P",
    "gn:feature_code":"PPL",
    "gn:name":"Los Inocentes",
    "gn:population":0,
    "gn:timezone":"America/Mazatlan",
    "iso:country":"MX",
    "name:und_x_variant":[
        "Inocentes"
    ],
    "wof:name":"Los Inocentes",
    "wof:placetype":"locality"
},
  "geometry": {"coordinates":[-110.66974999999999,23.77267],"type":"Point"}
}