{
  "type": "Feature",
  "properties": {
    "iso:country":"MX",
    "name:arg_x_preferred":[
        "El Cerro"
    ],
    "name:cat_x_preferred":[
        "El Cerro"
    ],
    "name:ceb_x_preferred":[
        "El Cerro"
    ],
    "name:eus_x_preferred":[
        "El Cerro"
    ],
    "name:fra_x_preferred":[
        "El Cerro"
    ],
    "name:haw_x_preferred":[
        "El Cerro"
    ],
    "name:hun_x_preferred":[
        "El Cerro"
    ],
    "name:ina_x_preferred":[
        "El Cerro"
    ],
    "name:ita_x_preferred":[
        "El Cerro"
    ],
    "name:kaz_x_preferred":[
        "\u042d\u043b\u044c-\u0421\u0435\u0440\u0440\u043e"
    ],
    "name:msa_x_preferred":[
        "El Cerro"
    ],
    "name:nld_x_preferred":[
        "El Cerro"
    ],
    "name:oci_x_preferred":[
        "El Cerro"
    ],
    "name:pol_x_preferred":[
        "El Cerro"
    ],
    "name:por_x_preferred":[
        "El Cerro"
    ],
    "name:rus_x_preferred":[
        "\u042d\u043b\u044c-\u0421\u0435\u0440\u0440\u043e"
    ],
    "name:spa_x_preferred":[
        "El Cerro"
    ],
    "name:swe_x_preferred":[
        "El Cerro"
    ],
    "name:ukr_x_preferred":[
        "\u0415\u043b\u044c-\u0421\u0435\u0440\u0440\u043e"
    ],
    "name:vie_x_preferred":[
        "El Cerro"
    ],
    "name:war_x_preferred":[
        "El Cerro"
    ],
    "name:zho_min_nan_x_preferred":[
        "El Cerro"
    ],
    "name:zho_x_preferred":[
        "\u57c3\u5c14\u585e\u7f57"
    ],
    "qs:gn_adm0_cc":"MX",
    "qs:gn_fcode":"PPL",
    "qs:gn_local":3991328,
    "qs:gn_nam_loc":"Puerto Vallarta, Puerto Vallarta, Jalisco, MX",
    "qs:gn_namadm1":"18",
    "qs:gn_name":"El Cerro",
    "qs:local_max":6256,
    "qs:local_sum":18911,
    "qs:localhoods":15,
    "qs:name":"El Cerro",
    "qs:name_adm0":"M\u00e9xico",
    "qs:name_adm1":"Jalisco",
    "qs:name_adm2":"Puerto Vallarta",
    "qs:name_local":"Puerto Vallarta",
    "qs:photo_max":563,
    "qs:photo_sum":1236,
    "qs:placetype":"Suburb",
    "qs:quad_count":7,
    "qs:woe_adm0":23424900,
    "qs:woe_adm1":2346277,
    "qs:woe_adm2":12600264,
    "qs:woe_lau":0,
    "qs:woe_local":137895,
    "qs:woe_ver":"7.10.0",
    "wof:lang":[
        "spa"
    ],
    "wof:name":"El Cerro",
    "wof:placetype":"neighbourhood"
},
  "geometry": {"coordinates":[-105.234751,20.607304],"type":"Point"}
}