{
  "type": "Feature",
  "properties": {
    "gn:admin1_code":"29",
    "gn:admin2_code":"23.0",
    "gn:asciiname":"Santa Clara Atoyac",
    "gn:country_code":"MX",
    "gn:dem":2194,
    "gn:feature_class":"P",
    "gn:feature_code":"PPL",
    "gn:name":"Santa Clara Atoyac",
    "gn:population":117,
    "gn:timezone":"America/Mexico_City",
    "iso:country":"MX",
    "wof:name":"Santa Clara Atoyac",
    "wof:placetype":"locality",
    "wof:population":117
},
  "geometry": {"coordinates":[-98.33,19.19139],"type":"Point"}
}