{
  "type": "Feature",
  "properties": {
    "gn:admin1_code":"6",
    "gn:admin2_code":"10.0",
    "gn:asciiname":"El Menon (Rancho de Chumel)",
    "gn:country_code":"MX",
    "gn:dem":1552,
    "gn:feature_class":"P",
    "gn:feature_code":"PPL",
    "gn:name":"El Men\u00f3n (Rancho de Chumel)",
    "gn:population":4,
    "gn:timezone":"America/Chihuahua",
    "iso:country":"MX",
    "name:und_x_variant":[
        "El Men\u00f3n (Rancho de Chumel)"
    ],
    "wof:name":"El Menon (Rancho de Chumel)",
    "wof:placetype":"locality",
    "wof:population":4
},
  "geometry": {"coordinates":[-107.46509,29.83371],"type":"Point"}
}