{
  "type": "Feature",
  "properties": {
    "gn:admin1_code":"19",
    "gn:admin2_code":"33.0",
    "gn:asciiname":"Loma Alta",
    "gn:country_code":"MX",
    "gn:dem":575,
    "gn:feature_class":"P",
    "gn:feature_code":"PPL",
    "gn:name":"Loma Alta",
    "gn:population":0,
    "gn:timezone":"America/Monterrey",
    "iso:country":"MX",
    "name:spa_x_preferred":[
        "Loma Alta"
    ],
    "wof:name":"Loma Alta",
    "wof:placetype":"locality"
},
  "geometry": {"coordinates":[-99.83721,24.9389],"type":"Point"}
}