{
  "type": "Feature",
  "properties": {
    "gn:admin1_code":"11.0",
    "gn:admin2_code":"41.0",
    "gn:asciiname":"La Minita",
    "gn:country_code":"MX",
    "gn:dem":1833,
    "gn:feature_class":"P",
    "gn:feature_code":"PPL",
    "gn:name":"La Minita",
    "gn:population":0,
    "gn:timezone":"America/Mexico_City",
    "iso:country":"MX",
    "wof:name":"La Minita",
    "wof:placetype":"locality"
},
  "geometry": {"coordinates":[-101.15778,20.15111],"type":"Point"}
}