{
  "type": "Feature",
  "properties": {
    "gn:admin1_code":"10.0",
    "gn:admin2_code":"35.0",
    "gn:asciiname":"Carreras",
    "gn:country_code":"MX",
    "gn:dem":1786,
    "gn:feature_class":"P",
    "gn:feature_code":"PPL",
    "gn:name":"Carreras",
    "gn:population":0,
    "gn:timezone":"America/Monterrey",
    "iso:country":"MX",
    "name:cat_x_preferred":[
        "Carreras"
    ],
    "name:deu_x_preferred":[
        "Carreras"
    ],
    "name:fra_x_preferred":[
        "Carreras"
    ],
    "name:nds_x_preferred":[
        "Carreras"
    ],
    "name:nld_x_preferred":[
        "Carreras"
    ],
    "name:rus_x_preferred":[
        "\u041a\u0430\u0440\u0440\u0435\u0440\u0430\u0441"
    ],
    "name:spa_x_preferred":[
        "Carreras"
    ],
    "wof:name":"Carreras",
    "wof:placetype":"locality"
},
  "geometry": {"coordinates":[-105.69274,25.31401],"type":"Point"}
}