{
  "type": "Feature",
  "properties": {
    "gn:admin1_code":"30",
    "gn:admin2_code":"172.0",
    "gn:asciiname":"Jose Maria Morelos y Pavon",
    "gn:country_code":"MX",
    "gn:dem":14,
    "gn:feature_class":"P",
    "gn:feature_code":"PPL",
    "gn:name":"Jos\u00e9 Mar\u00eda Morelos y Pav\u00f3n",
    "gn:population":212,
    "gn:timezone":"America/Mexico_City",
    "iso:country":"MX",
    "name:und_x_variant":[
        "Jos\u00e9 Mar\u00eda Morelos y Pav\u00f3n"
    ],
    "wof:name":"Jose Maria Morelos y Pavon",
    "wof:placetype":"locality",
    "wof:population":212
},
  "geometry": {"coordinates":[-94.71278,17.73139],"type":"Point"}
}