{
  "type": "Feature",
  "properties": {
    "gn:admin1_code":"20",
    "gn:admin2_code":"348",
    "gn:asciiname":"Los Alvarado",
    "gn:country_code":"MX",
    "gn:dem":1659,
    "gn:feature_class":"P",
    "gn:feature_code":"PPL",
    "gn:name":"Los Alvarado",
    "gn:population":41,
    "gn:timezone":"America/Mexico_City",
    "iso:country":"MX",
    "wof:name":"Los Alvarado",
    "wof:placetype":"locality",
    "wof:population":41
},
  "geometry": {"coordinates":[-98.0175,17.38472],"type":"Point"}
}