{
  "type": "Feature",
  "properties": {
    "gn:admin1_code":"6",
    "gn:admin2_code":"27.0",
    "gn:asciiname":"Boreachi",
    "gn:country_code":"MX",
    "gn:dem":2341,
    "gn:feature_class":"P",
    "gn:feature_code":"PPL",
    "gn:name":"Boreachi",
    "gn:population":0,
    "gn:timezone":"America/Chihuahua",
    "iso:country":"MX",
    "name:spa_x_preferred":[
        "Recan\u00e1puchi"
    ],
    "name:spa_x_variant":[
        "Boreachi"
    ],
    "wof:name":"Boreachi",
    "wof:placetype":"locality"
},
  "geometry": {"coordinates":[-107.63154,27.38971],"type":"Point"}
}