{
  "type": "Feature",
  "properties": {
    "gn:admin1_code":"20",
    "gn:admin2_code":"348.0",
    "gn:asciiname":"Constitucional",
    "gn:country_code":"MX",
    "gn:dem":2199,
    "gn:feature_class":"P",
    "gn:feature_code":"PPL",
    "gn:name":"Constitucional",
    "gn:population":0,
    "gn:timezone":"America/Mexico_City",
    "iso:country":"MX",
    "name:spa_x_preferred":[
        "Constituci\u00f3n"
    ],
    "name:und_x_variant":[
        "Yucuyi"
    ],
    "wof:name":"Constitucional",
    "wof:placetype":"locality"
},
  "geometry": {"coordinates":[-98.10706999999999,17.2952],"type":"Point"}
}