{
  "type": "Feature",
  "properties": {
    "gn:admin1_code":"14",
    "gn:admin2_code":"100.0",
    "gn:asciiname":"El Nogal",
    "gn:country_code":"MX",
    "gn:dem":341,
    "gn:feature_class":"P",
    "gn:feature_code":"PPL",
    "gn:name":"El Nogal",
    "gn:population":64,
    "gn:timezone":"America/Mexico_City",
    "iso:country":"MX",
    "wof:name":"El Nogal",
    "wof:placetype":"locality",
    "wof:population":64
},
  "geometry": {"coordinates":[-105.13443999999998,20.18444],"type":"Point"}
}