{
  "type": "Feature",
  "properties": {
    "gn:admin1_code":"12",
    "gn:admin2_code":"16.0",
    "gn:asciiname":"Paso de Vacas",
    "gn:country_code":"MX",
    "gn:dem":208,
    "gn:feature_class":"P",
    "gn:feature_code":"PPL",
    "gn:name":"Paso de Vacas",
    "gn:population":0,
    "gn:timezone":"America/Mexico_City",
    "iso:country":"MX",
    "name:und_x_variant":[
        "Paso de la Vacas"
    ],
    "wof:name":"Paso de Vacas",
    "wof:placetype":"locality"
},
  "geometry": {"coordinates":[-101.81756,18.44818],"type":"Point"}
}