{
  "type": "Feature",
  "properties": {
    "gn:admin1_code":"4.0",
    "gn:admin2_code":"11.0",
    "gn:asciiname":"El Treinta",
    "gn:country_code":"MX",
    "gn:dem":45,
    "gn:feature_class":"P",
    "gn:feature_code":"PPL",
    "gn:name":"El Treinta",
    "gn:population":0,
    "gn:timezone":"America/Merida",
    "iso:country":"MX",
    "name:spa_x_preferred":[
        "El Treinta"
    ],
    "name:und_x_variant":[
        "Las \u00c1guilas"
    ],
    "wof:name":"El Treinta",
    "wof:placetype":"locality"
},
  "geometry": {"coordinates":[-90.93145,17.99212],"type":"Point"}
}