{
  "type": "Feature",
  "properties": {
    "gn:admin1_code":"13",
    "gn:admin2_code":"12.0",
    "gn:asciiname":"Paredones",
    "gn:country_code":"MX",
    "gn:dem":1970,
    "gn:feature_class":"P",
    "gn:feature_code":"PPL",
    "gn:name":"Paredones",
    "gn:population":176,
    "gn:timezone":"America/Mexico_City",
    "iso:country":"MX",
    "wof:name":"Paredones",
    "wof:placetype":"locality",
    "wof:population":176
},
  "geometry": {"coordinates":[-98.57389000000001,20.41333],"type":"Point"}
}