{
  "type": "Feature",
  "properties": {
    "gn:admin1_code":"13",
    "gn:admin2_code":"12.0",
    "gn:asciiname":"Paredones",
    "gn:country_code":"MX",
    "gn:dem":1970,
    "gn:feature_class":"P",
    "gn:feature_code":"PPL",
    "gn:name":"Paredones",
    "gn:population":176,
    "gn:timezone":"America/Mexico_City",
    "iso:country":"MX",
    "name:bak_x_preferred":[
        "\u041f\u0430\u0440\u0435\u0434\u043e\u043d\u0435\u0441"
    ],
    "name:ceb_x_preferred":[
        "Paredones"
    ],
    "name:eus_x_preferred":[
        "Paredones"
    ],
    "name:fas_x_preferred":[
        "\u067e\u0627\u0631\u062f\u0648\u0646\u0633"
    ],
    "name:fra_x_preferred":[
        "Paredones"
    ],
    "name:glg_x_preferred":[
        "Paredones"
    ],
    "name:ita_x_preferred":[
        "Paredones"
    ],
    "name:kor_x_preferred":[
        "\ud30c\ub808\ub3c4\ub124\uc2a4"
    ],
    "name:nld_x_preferred":[
        "Paredones"
    ],
    "name:por_x_preferred":[
        "Paredones"
    ],
    "name:ron_x_preferred":[
        "Paredones"
    ],
    "name:rus_x_preferred":[
        "\u041f\u0430\u0440\u0435\u0434\u043e\u043d\u0435\u0441"
    ],
    "name:sco_x_preferred":[
        "Paredones"
    ],
    "name:spa_x_preferred":[
        "Paredones"
    ],
    "name:swe_x_preferred":[
        "Paredones"
    ],
    "name:zho_x_preferred":[
        "\u5e15\u96f7\u591a\u5167\u65af"
    ],
    "wof:name":"Paredones",
    "wof:placetype":"locality",
    "wof:population":176
},
  "geometry": {"coordinates":[-98.57389000000001,20.41333],"type":"Point"}
}