{
  "type": "Feature",
  "properties": {
    "gn:admin1_code":"12",
    "gn:admin2_code":"74.0",
    "gn:asciiname":"Tizayucan",
    "gn:country_code":"MX",
    "gn:dem":1324,
    "gn:feature_class":"P",
    "gn:feature_code":"PPL",
    "gn:name":"Tizayucan",
    "gn:population":100,
    "gn:timezone":"America/Mexico_City",
    "iso:country":"MX",
    "wof:name":"Tizayucan",
    "wof:placetype":"locality",
    "wof:population":100
},
  "geometry": {"coordinates":[-99.19474,17.73357],"type":"Point"}
}