{
  "type": "Feature",
  "properties": {
    "gn:admin1_code":"32",
    "gn:admin2_code":"38",
    "gn:asciiname":"La Sauceda",
    "gn:country_code":"MX",
    "gn:dem":2279,
    "gn:feature_class":"P",
    "gn:feature_code":"PPL",
    "gn:name":"La Sauceda",
    "gn:population":43,
    "gn:timezone":"America/Mexico_City",
    "iso:country":"MX",
    "wof:name":"La Sauceda",
    "wof:placetype":"locality",
    "wof:population":43
},
  "geometry": {"coordinates":[-101.55028,22.23389],"type":"Point"}
}