{
  "type": "Feature",
  "properties": {
    "gn:admin1_code":"11",
    "gn:admin2_code":"39",
    "gn:asciiname":"Casa de Oracion, Silencio y Paz",
    "gn:country_code":"MX",
    "gn:dem":1756,
    "gn:feature_class":"P",
    "gn:feature_code":"PPL",
    "gn:name":"Casa de Oraci\u00f3n, Silencio y Paz",
    "gn:population":11,
    "gn:timezone":"America/Mexico_City",
    "iso:country":"MX",
    "name:und_x_variant":[
        "Casa de Oraci\u00f3n, Silencio y Paz"
    ],
    "wof:name":"Casa de Oracion, Silencio y Paz",
    "wof:placetype":"locality",
    "wof:population":11
},
  "geometry": {"coordinates":[-100.81528,20.30306],"type":"Point"}
}