{
  "type": "Feature",
  "properties": {
    "gn:admin1_code":"32",
    "gn:admin2_code":"51.0",
    "gn:asciiname":"Eduardo Aguirre",
    "gn:country_code":"MX",
    "gn:dem":1844,
    "gn:feature_class":"P",
    "gn:feature_code":"PPL",
    "gn:name":"Eduardo Aguirre",
    "gn:population":7,
    "gn:timezone":"America/Mexico_City",
    "iso:country":"MX",
    "wof:name":"Eduardo Aguirre",
    "wof:placetype":"locality",
    "wof:population":7
},
  "geometry": {"coordinates":[-102.33417,23.87083],"type":"Point"}
}