{
  "type": "Feature",
  "properties": {
    "gn:admin1_code":"25",
    "gn:admin2_code":"8.0",
    "gn:asciiname":"Campo la Paloma (Agricola el Chaparral)",
    "gn:country_code":"MX",
    "gn:dem":9,
    "gn:feature_class":"P",
    "gn:feature_code":"PPL",
    "gn:name":"Campo la Paloma (Agr\u00edcola el Chaparral)",
    "gn:population":192,
    "gn:timezone":"America/Mazatlan",
    "iso:country":"MX",
    "name:und_x_variant":[
        "Campo la Paloma (Agr\u00edcola el Chaparral)"
    ],
    "wof:name":"Campo la Paloma (Agricola el Chaparral)",
    "wof:placetype":"locality",
    "wof:population":192
},
  "geometry": {"coordinates":[-106.99639000000001,24.01111],"type":"Point"}
}