{
  "type": "Feature",
  "properties": {
    "gn:admin1_code":"20",
    "gn:admin2_code":"229.0",
    "gn:asciiname":"Sigala",
    "gn:country_code":"MX",
    "gn:dem":1870,
    "gn:feature_class":"P",
    "gn:feature_code":"PPL",
    "gn:name":"Sigala",
    "gn:population":0,
    "gn:timezone":"America/Mexico_City",
    "iso:country":"MX",
    "name:arg_x_preferred":[
        "Sigala"
    ],
    "name:ces_x_preferred":[
        "Sigala"
    ],
    "name:deu_x_preferred":[
        "Sigala"
    ],
    "name:est_x_preferred":[
        "Sigala"
    ],
    "name:ita_x_preferred":[
        "Sigala"
    ],
    "name:kor_x_preferred":[
        "\uc2dc\uac08\ub77c"
    ],
    "name:nld_x_preferred":[
        "Sigala"
    ],
    "name:por_x_preferred":[
        "Sigala"
    ],
    "name:rus_x_preferred":[
        "Sigala"
    ],
    "name:sco_x_preferred":[
        "Sigala"
    ],
    "name:spa_x_preferred":[
        "Sigala"
    ],
    "wof:name":"Sigala",
    "wof:placetype":"locality"
},
  "geometry": {"coordinates":[-97.18333,16.48333],"type":"Point"}
}