{
  "type": "Feature",
  "properties": {
    "gn:admin1_code":"26",
    "gn:asciiname":"Minihuaza",
    "gn:country_code":"MX",
    "gn:dem":1629,
    "gn:feature_class":"P",
    "gn:feature_code":"PPL",
    "gn:name":"Minihuaza",
    "gn:population":0,
    "gn:timezone":"America/Chihuahua",
    "iso:country":"MX",
    "wof:name":"Minihuaza",
    "wof:placetype":"locality"
},
  "geometry": {"coordinates":[-108.15000000000001,27.15],"type":"Point"}
}