{
  "type": "Feature",
  "properties": {
    "gn:admin1_code":"18",
    "gn:admin2_code":"11.0",
    "gn:asciiname":"Rancho Alfonso Vidal (El Mirador)",
    "gn:country_code":"MX",
    "gn:dem":50,
    "gn:feature_class":"P",
    "gn:feature_code":"PPL",
    "gn:name":"Rancho Alfonso Vidal (El Mirador)",
    "gn:population":7,
    "gn:timezone":"America/Mazatlan",
    "iso:country":"MX",
    "wof:name":"Rancho Alfonso Vidal (El Mirador)",
    "wof:placetype":"locality",
    "wof:population":7
},
  "geometry": {"coordinates":[-105.05694,21.91583],"type":"Point"}
}