{
  "type": "Feature",
  "properties": {
    "gn:admin1_code":"10",
    "gn:admin2_code":"5.0",
    "gn:asciiname":"Rancho el Paraiso",
    "gn:country_code":"MX",
    "gn:dem":2000,
    "gn:feature_class":"P",
    "gn:feature_code":"PPL",
    "gn:name":"Rancho el Para\u00edso",
    "gn:population":7,
    "gn:timezone":"America/Monterrey",
    "iso:country":"MX",
    "name:und_x_variant":[
        "Rancho el Para\u00edso"
    ],
    "wof:name":"Rancho el Paraiso",
    "wof:placetype":"locality",
    "wof:population":7
},
  "geometry": {"coordinates":[-104.70166999999999,24.12194],"type":"Point"}
}