{
  "type": "Feature",
  "properties": {
    "gn:admin1_code":"32",
    "gn:asciiname":"Mesa de los Saucedos",
    "gn:country_code":"MX",
    "gn:dem":1429,
    "gn:feature_class":"P",
    "gn:feature_code":"PPL",
    "gn:name":"Mesa de los Saucedos",
    "gn:population":0,
    "gn:timezone":"America/Mexico_City",
    "iso:country":"MX",
    "name:spa_x_preferred":[
        "Mesa de los Saucedos"
    ],
    "name:und_x_variant":[
        "Mesa Los Saucedd"
    ],
    "wof:name":"Mesa de los Saucedos",
    "wof:placetype":"locality"
},
  "geometry": {"coordinates":[-103.98018,21.4601],"type":"Point"}
}