{
  "type": "Feature",
  "properties": {
    "gn:admin1_code":"28",
    "gn:admin2_code":"3.0",
    "gn:asciiname":"Los Pepes",
    "gn:country_code":"MX",
    "gn:dem":39,
    "gn:feature_class":"P",
    "gn:feature_code":"PPL",
    "gn:name":"Los Pepes",
    "gn:population":5,
    "gn:timezone":"America/Monterrey",
    "iso:country":"MX",
    "name:ara_x_preferred":[
        "\u0644\u0648\u0633 \u0628\u064a\u0628\u064a\u0633"
    ],
    "name:cat_x_preferred":[
        "Los Pepes"
    ],
    "name:deu_x_preferred":[
        "Los Pepes"
    ],
    "name:ell_x_preferred":[
        "\u039b\u03bf\u03c2 \u03a0\u03ad\u03c0\u03b5\u03c2"
    ],
    "name:fas_x_preferred":[
        "\u0644\u0648\u0633 \u067e\u067e\u0633"
    ],
    "name:fra_x_preferred":[
        "Los Pepes"
    ],
    "name:ita_x_preferred":[
        "Los Pepes"
    ],
    "name:nor_x_preferred":[
        "Los Pepes"
    ],
    "name:pol_x_preferred":[
        "Los Pepes"
    ],
    "name:por_x_preferred":[
        "Los Pepes"
    ],
    "name:rus_x_preferred":[
        "\u041b\u043e\u0441 \u041f\u0435\u043f\u0435\u0441"
    ],
    "name:spa_x_preferred":[
        "Los Pepes"
    ],
    "name:srp_x_preferred":[
        "\u041b\u043e\u0441 \u041f\u0435\u043f\u0435\u0441"
    ],
    "name:urd_x_preferred":[
        "\u0644\u0648\u0633 \u067e\u06cc\u067e\u06cc\u0633"
    ],
    "wof:name":"Los Pepes",
    "wof:placetype":"locality",
    "wof:population":5
},
  "geometry": {"coordinates":[-98.00028,22.47583],"type":"Point"}
}