{
  "type": "Feature",
  "properties": {
    "gn:admin1_code":"28",
    "gn:admin2_code":"3.0",
    "gn:asciiname":"Los Pepes",
    "gn:country_code":"MX",
    "gn:dem":39,
    "gn:feature_class":"P",
    "gn:feature_code":"PPL",
    "gn:name":"Los Pepes",
    "gn:population":5,
    "gn:timezone":"America/Monterrey",
    "iso:country":"MX",
    "wof:name":"Los Pepes",
    "wof:placetype":"locality",
    "wof:population":5
},
  "geometry": {"coordinates":[-98.00028,22.47583],"type":"Point"}
}