{
  "type": "Feature",
  "properties": {
    "gn:admin1_code":"24",
    "gn:admin2_code":"3.0",
    "gn:asciiname":"Barrio de Jolja",
    "gn:country_code":"MX",
    "gn:dem":760,
    "gn:feature_class":"P",
    "gn:feature_code":"PPL",
    "gn:name":"Barrio de Jolja",
    "gn:population":207,
    "gn:timezone":"America/Mexico_City",
    "iso:country":"MX",
    "wof:name":"Barrio de Jolja",
    "wof:placetype":"locality",
    "wof:population":207
},
  "geometry": {"coordinates":[-99.05667,21.52917],"type":"Point"}
}