{
  "type": "Feature",
  "properties": {
    "gn:admin1_code":"11.0",
    "gn:admin2_code":"17.0",
    "gn:asciiname":"San Jose de las Dalias",
    "gn:country_code":"MX",
    "gn:dem":1701,
    "gn:feature_class":"P",
    "gn:feature_code":"PPL",
    "gn:name":"San Jos\u00e9 de las Dalias",
    "gn:population":0,
    "gn:timezone":"America/Mexico_City",
    "iso:country":"MX",
    "name:spa_x_preferred":[
        "San Jos\u00e9 de las Dalias"
    ],
    "wof:name":"San Jose de las Dalias",
    "wof:placetype":"locality"
},
  "geometry": {"coordinates":[-101.44307999999999,20.50348],"type":"Point"}
}