{
  "type": "Feature",
  "properties": {
    "gn:admin1_code":"14.0",
    "gn:admin2_code":"20.0",
    "gn:asciiname":"Los Embeles",
    "gn:country_code":"MX",
    "gn:dem":594,
    "gn:feature_class":"P",
    "gn:feature_code":"PPL",
    "gn:name":"Los Embeles",
    "gn:population":0,
    "gn:timezone":"America/Mexico_City",
    "iso:country":"MX",
    "name:spa_x_preferred":[
        "Los Embeles"
    ],
    "wof:name":"Los Embeles",
    "wof:placetype":"locality"
},
  "geometry": {"coordinates":[-105.33099,20.32696],"type":"Point"}
}