{
  "type": "Feature",
  "properties": {
    "gn:admin1_code":"5",
    "gn:admin2_code":"100",
    "gn:asciiname":"El Pedregal",
    "gn:country_code":"MX",
    "gn:dem":1199,
    "gn:feature_class":"P",
    "gn:feature_code":"PPL",
    "gn:name":"El Pedregal",
    "gn:population":16,
    "gn:timezone":"America/Mexico_City",
    "iso:country":"MX",
    "wof:name":"El Pedregal",
    "wof:placetype":"locality",
    "wof:population":16
},
  "geometry": {"coordinates":[-92.34,17.34722],"type":"Point"}
}