{
  "type": "Feature",
  "properties": {
    "gn:admin1_code":"5",
    "gn:admin2_code":"100",
    "gn:asciiname":"El Pedregal",
    "gn:country_code":"MX",
    "gn:dem":1199,
    "gn:feature_class":"P",
    "gn:feature_code":"PPL",
    "gn:name":"El Pedregal",
    "gn:population":16,
    "gn:timezone":"America/Mexico_City",
    "iso:country":"MX",
    "name:arg_x_preferred":[
        "El Pedregal"
    ],
    "name:ast_x_preferred":[
        "El Pedregal"
    ],
    "name:cat_x_preferred":[
        "El Pedregal"
    ],
    "name:ceb_x_preferred":[
        "El Pedregal"
    ],
    "name:epo_x_preferred":[
        "El Pedregal"
    ],
    "name:eus_x_preferred":[
        "El Pedregal"
    ],
    "name:fra_x_preferred":[
        "El Pedregal"
    ],
    "name:hun_x_preferred":[
        "El Pedregal"
    ],
    "name:ina_x_preferred":[
        "El Pedregal"
    ],
    "name:ita_x_preferred":[
        "El Pedregal"
    ],
    "name:kaz_x_preferred":[
        "\u042d\u043b\u044c-\u041f\u0435\u0434\u0440\u0435\u0433\u0430\u043b\u044c"
    ],
    "name:msa_x_preferred":[
        "El Pedregal"
    ],
    "name:nld_x_preferred":[
        "El Pedregal"
    ],
    "name:oci_x_preferred":[
        "El Pedregal"
    ],
    "name:pol_x_preferred":[
        "El Pedregal"
    ],
    "name:por_x_preferred":[
        "El Pedregal"
    ],
    "name:rus_x_preferred":[
        "\u042d\u043b\u044c-\u041f\u0435\u0434\u0440\u0435\u0433\u0430\u043b\u044c"
    ],
    "name:spa_x_preferred":[
        "El Pedregal"
    ],
    "name:ukr_x_preferred":[
        "\u0415\u043b\u044c-\u041f\u0435\u0434\u0440\u0435\u0433\u0430\u043b\u044c"
    ],
    "name:vie_x_preferred":[
        "El Pedregal"
    ],
    "name:war_x_preferred":[
        "El Pedregal"
    ],
    "name:zho_x_preferred":[
        "\u57c3\u5c14\u4f69\u5fb7\u96f7\u52a0\u5c14"
    ],
    "wof:name":"El Pedregal",
    "wof:placetype":"locality",
    "wof:population":16
},
  "geometry": {"coordinates":[-92.34,17.34722],"type":"Point"}
}