{
  "type": "Feature",
  "properties": {
    "gn:admin1_code":"5",
    "gn:admin2_code":"60.0",
    "gn:asciiname":"San Pedro",
    "gn:country_code":"MX",
    "gn:dem":1500,
    "gn:feature_class":"P",
    "gn:feature_code":"PPL",
    "gn:name":"San Pedro",
    "gn:population":183,
    "gn:timezone":"America/Mexico_City",
    "iso:country":"MX",
    "wof:name":"San Pedro",
    "wof:placetype":"locality",
    "wof:population":183
},
  "geometry": {"coordinates":[-93.15194,17.22417],"type":"Point"}
}