{
  "type": "Feature",
  "properties": {
    "gn:admin1_code":"5",
    "gn:admin2_code":"92",
    "gn:asciiname":"Isla San Antonio (Isla la Carofa)",
    "gn:country_code":"MX",
    "gn:dem":197,
    "gn:feature_class":"P",
    "gn:feature_code":"PPL",
    "gn:name":"Isla San Antonio (Isla la Carofa)",
    "gn:population":14,
    "gn:timezone":"America/Mexico_City",
    "iso:country":"MX",
    "wof:name":"Isla San Antonio (Isla la Carofa)",
    "wof:placetype":"locality",
    "wof:population":14
},
  "geometry": {"coordinates":[-93.82472,17.12056],"type":"Point"}
}