{
  "type": "Feature",
  "properties": {
    "gn:admin1_code":"26.0",
    "gn:admin2_code":"17.0",
    "gn:asciiname":"Banori",
    "gn:country_code":"MX",
    "gn:dem":716,
    "gn:feature_class":"P",
    "gn:feature_code":"PPL",
    "gn:name":"B\u00e1nori",
    "gn:population":0,
    "gn:timezone":"America/Hermosillo",
    "iso:country":"MX",
    "name:und_x_variant":[
        "Bamori",
        "B\u00e1nori"
    ],
    "wof:name":"Banori",
    "wof:placetype":"locality"
},
  "geometry": {"coordinates":[-112.1605,31.59368],"type":"Point"}
}