{
  "type": "Feature",
  "properties": {
    "gn:admin1_code":"30",
    "gn:admin2_code":"178.0",
    "gn:asciiname":"Dona Celia",
    "gn:country_code":"MX",
    "gn:dem":6,
    "gn:feature_class":"P",
    "gn:feature_code":"PPL",
    "gn:name":"Do\u00f1a Celia",
    "gn:population":7,
    "gn:timezone":"America/Mexico_City",
    "iso:country":"MX",
    "name:und_x_variant":[
        "Do\u00f1a Celia"
    ],
    "wof:name":"Dona Celia",
    "wof:placetype":"locality",
    "wof:population":7
},
  "geometry": {"coordinates":[-95.71693999999999,18.56889],"type":"Point"}
}