{
  "type": "Feature",
  "properties": {
    "gn:admin1_code":"6.0",
    "gn:asciiname":"La Negra",
    "gn:country_code":"MX",
    "gn:dem":1360,
    "gn:feature_class":"P",
    "gn:feature_code":"PPL",
    "gn:name":"La Negra",
    "gn:population":0,
    "gn:timezone":"America/Chihuahua",
    "iso:country":"MX",
    "name:ceb_x_preferred":[
        "La Negra"
    ],
    "name:spa_x_preferred":[
        "La Negra"
    ],
    "name:srp_x_preferred":[
        "\u041b\u0430 \u041d\u0435\u0433\u0440\u0430"
    ],
    "name:swe_x_preferred":[
        "La Negra"
    ],
    "wof:name":"La Negra",
    "wof:placetype":"locality"
},
  "geometry": {"coordinates":[-107.84954999999999,31.18831],"type":"Point"}
}