{
  "type": "Feature",
  "properties": {
    "gn:admin1_code":"3",
    "gn:admin2_code":"3",
    "gn:asciiname":"Nopolo",
    "gn:country_code":"MX",
    "gn:dem":5,
    "gn:feature_class":"P",
    "gn:feature_code":"PPL",
    "gn:name":"Nopol\u00f3",
    "gn:population":11,
    "gn:timezone":"America/Mazatlan",
    "iso:country":"MX",
    "name:und_x_variant":[
        "Nopol\u00f3"
    ],
    "wof:name":"Nopolo",
    "wof:placetype":"locality",
    "wof:population":11
},
  "geometry": {"coordinates":[-110.75994,24.99813],"type":"Point"}
}