{
  "type": "Feature",
  "properties": {
    "gn:admin1_code":"25",
    "gn:admin2_code":"6.0",
    "gn:asciiname":"Chiquerito",
    "gn:country_code":"MX",
    "gn:dem":20,
    "gn:feature_class":"P",
    "gn:feature_code":"PPL",
    "gn:name":"Chiquerito",
    "gn:population":0,
    "gn:timezone":"America/Mazatlan",
    "iso:country":"MX",
    "name:spa_x_preferred":[
        "Chiquerito"
    ],
    "wof:name":"Chiquerito",
    "wof:placetype":"locality"
},
  "geometry": {"coordinates":[-107.35715,24.48465],"type":"Point"}
}