{
  "type": "Feature",
  "properties": {
    "gn:admin1_code":"21",
    "gn:admin2_code":"2.0",
    "gn:asciiname":"La Cantina",
    "gn:country_code":"MX",
    "gn:dem":328,
    "gn:feature_class":"P",
    "gn:feature_code":"PPL",
    "gn:name":"La Cantina",
    "gn:population":99,
    "gn:timezone":"America/Mexico_City",
    "iso:country":"MX",
    "wof:name":"La Cantina",
    "wof:placetype":"locality",
    "wof:population":99
},
  "geometry": {"coordinates":[-97.25134,20.10063],"type":"Point"}
}