{
  "type": "Feature",
  "properties": {
    "gn:admin1_code":"25",
    "gn:admin2_code":"6.0",
    "gn:asciiname":"Nuevo Seminario",
    "gn:country_code":"MX",
    "gn:dem":70,
    "gn:feature_class":"P",
    "gn:feature_code":"PPL",
    "gn:name":"Nuevo Seminario",
    "gn:population":104,
    "gn:timezone":"America/Mazatlan",
    "iso:country":"MX",
    "wof:name":"Nuevo Seminario",
    "wof:placetype":"locality",
    "wof:population":104
},
  "geometry": {"coordinates":[-107.48083,24.87611],"type":"Point"}
}