{
  "type": "Feature",
  "properties": {
    "gn:admin1_code":"25",
    "gn:admin2_code":"8",
    "gn:asciiname":"La Resbalosa",
    "gn:country_code":"MX",
    "gn:dem":198,
    "gn:feature_class":"P",
    "gn:feature_code":"PPL",
    "gn:name":"La Resbalosa",
    "gn:population":15,
    "gn:timezone":"America/Mazatlan",
    "iso:country":"MX",
    "wof:name":"La Resbalosa",
    "wof:placetype":"locality",
    "wof:population":15
},
  "geometry": {"coordinates":[-106.62009,24.19444],"type":"Point"}
}