{
  "type": "Feature",
  "properties": {
    "gn:admin1_code":"7",
    "gn:admin2_code":"4.0",
    "gn:asciiname":"Daniel Garcia Najera",
    "gn:country_code":"MX",
    "gn:dem":1962,
    "gn:feature_class":"P",
    "gn:feature_code":"PPL",
    "gn:name":"Daniel Garc\u00eda N\u00e1jera",
    "gn:population":4,
    "gn:timezone":"America/Monterrey",
    "iso:country":"MX",
    "name:und_x_variant":[
        "Daniel Garc\u00eda N\u00e1jera"
    ],
    "wof:name":"Daniel Garcia Najera",
    "wof:placetype":"locality",
    "wof:population":4
},
  "geometry": {"coordinates":[-100.74309,25.45365],"type":"Point"}
}