{
  "type": "Feature",
  "properties": {
    "gn:admin1_code":"18.0",
    "gn:admin2_code":"19.0",
    "gn:asciiname":"Los Pozos",
    "gn:country_code":"MX",
    "gn:dem":1448,
    "gn:feature_class":"P",
    "gn:feature_code":"PPL",
    "gn:name":"Los Pozos",
    "gn:population":0,
    "gn:timezone":"America/Mazatlan",
    "iso:country":"MX",
    "wof:name":"Los Pozos",
    "wof:placetype":"locality"
},
  "geometry": {"coordinates":[-104.20766999999999,21.50416],"type":"Point"}
}