{
  "type": "Feature",
  "properties": {
    "gn:admin1_code":"5",
    "gn:admin2_code":"83.0",
    "gn:asciiname":"Puerto Rico",
    "gn:country_code":"MX",
    "gn:dem":541,
    "gn:feature_class":"P",
    "gn:feature_code":"PPL",
    "gn:name":"Puerto Rico",
    "gn:population":0,
    "gn:timezone":"America/Mexico_City",
    "iso:country":"MX",
    "name:spa_x_preferred":[
        "Puerto Rico"
    ],
    "wof:name":"Puerto Rico",
    "wof:placetype":"locality"
},
  "geometry": {"coordinates":[-92.25488,15.93488],"type":"Point"}
}