{
  "type": "Feature",
  "properties": {
    "gn:admin1_code":"30",
    "gn:admin2_code":"124",
    "gn:asciiname":"El Rolex",
    "gn:country_code":"MX",
    "gn:dem":158,
    "gn:feature_class":"P",
    "gn:feature_code":"PPL",
    "gn:name":"El Rolex",
    "gn:population":10,
    "gn:timezone":"America/Mexico_City",
    "iso:country":"MX",
    "wof:name":"El Rolex",
    "wof:placetype":"locality",
    "wof:population":10
},
  "geometry": {"coordinates":[-97.40443999999999,20.53722],"type":"Point"}
}