{
  "type": "Feature",
  "properties": {
    "gn:admin1_code":"32",
    "gn:admin2_code":"48.0",
    "gn:asciiname":"Los Fresnos",
    "gn:country_code":"MX",
    "gn:dem":2063,
    "gn:feature_class":"P",
    "gn:feature_code":"PPL",
    "gn:name":"Los Fresnos",
    "gn:population":317,
    "gn:timezone":"America/Mexico_City",
    "iso:country":"MX",
    "wof:name":"Los Fresnos",
    "wof:placetype":"locality",
    "wof:population":317
},
  "geometry": {"coordinates":[-103.21226,21.73028],"type":"Point"}
}