{
  "type": "Feature",
  "properties": {
    "gn:admin1_code":"32",
    "gn:admin2_code":"58.0",
    "gn:asciiname":"El Picacho (Hidalgo)",
    "gn:country_code":"MX",
    "gn:dem":1914,
    "gn:feature_class":"P",
    "gn:feature_code":"PPL",
    "gn:name":"El Picacho (Hidalgo)",
    "gn:population":109,
    "gn:timezone":"America/Mexico_City",
    "iso:country":"MX",
    "wof:name":"El Picacho (Hidalgo)",
    "wof:placetype":"locality",
    "wof:population":109
},
  "geometry": {"coordinates":[-103.44917,21.54806],"type":"Point"}
}