{
  "type": "Feature",
  "properties": {
    "gn:admin1_code":"5",
    "gn:admin2_code":"89.0",
    "gn:asciiname":"Primera Seccion de Tinajas",
    "gn:country_code":"MX",
    "gn:dem":26,
    "gn:feature_class":"P",
    "gn:feature_code":"PPL",
    "gn:name":"Primera Secci\u00f3n de Tinajas",
    "gn:population":0,
    "gn:timezone":"America/Mexico_City",
    "iso:country":"MX",
    "name:spa_x_preferred":[
        "Primera Secci\u00f3n de Tinajas"
    ],
    "name:und_x_variant":[
        "Tinajas",
        "Las Tinajas"
    ],
    "wof:name":"Primera Seccion de Tinajas",
    "wof:placetype":"locality"
},
  "geometry": {"coordinates":[-92.31542,14.72398],"type":"Point"}
}