{
  "type": "Feature",
  "properties": {
    "gn:admin1_code":"6",
    "gn:admin2_code":"19",
    "gn:asciiname":"Santa Martha",
    "gn:country_code":"MX",
    "gn:dem":1619,
    "gn:feature_class":"P",
    "gn:feature_code":"PPL",
    "gn:name":"Santa Martha",
    "gn:population":9,
    "gn:timezone":"America/Chihuahua",
    "iso:country":"MX",
    "wof:name":"Santa Martha",
    "wof:placetype":"locality",
    "wof:population":9
},
  "geometry": {"coordinates":[-106.30137000000001,28.93619],"type":"Point"}
}