{
  "type": "Feature",
  "properties": {
    "gn:admin1_code":"5.0",
    "gn:asciiname":"Santo Tomas Palmas Cuachas",
    "gn:country_code":"MX",
    "gn:dem":675,
    "gn:feature_class":"P",
    "gn:feature_code":"PPL",
    "gn:name":"Santo Tom\u00e1s Palmas Cuachas",
    "gn:population":0,
    "gn:timezone":"America/Mexico_City",
    "iso:country":"MX",
    "name:spa_x_preferred":[
        "Santo Tom\u00e1s Palmas Cuachas"
    ],
    "wof:name":"Santo Tomas Palmas Cuachas",
    "wof:placetype":"locality"
},
  "geometry": {"coordinates":[-92.13489,16.04116],"type":"Point"}
}