{
  "type": "Feature",
  "properties": {
    "gn:admin1_code":"2",
    "gn:admin2_code":"1.0",
    "gn:asciiname":"La Ramona",
    "gn:country_code":"MX",
    "gn:dem":433,
    "gn:feature_class":"P",
    "gn:feature_code":"PPL",
    "gn:name":"La Ramona",
    "gn:population":0,
    "gn:timezone":"America/Tijuana",
    "iso:country":"MX",
    "name:spa_x_preferred":[
        "La Ramona"
    ],
    "name:und_x_variant":[
        "Romana",
        "Ramona"
    ],
    "wof:name":"La Ramona",
    "wof:placetype":"locality"
},
  "geometry": {"coordinates":[-115.08584,29.81539],"type":"Point"}
}