{
  "type": "Feature",
  "properties": {
    "gn:admin1_code":"6",
    "gn:admin2_code":"29.0",
    "gn:asciiname":"Piedras Coloradas",
    "gn:country_code":"MX",
    "gn:dem":2589,
    "gn:feature_class":"P",
    "gn:feature_code":"PPL",
    "gn:name":"Piedras Coloradas",
    "gn:population":7,
    "gn:timezone":"America/Chihuahua",
    "iso:country":"MX",
    "wof:name":"Piedras Coloradas",
    "wof:placetype":"locality",
    "wof:population":7
},
  "geometry": {"coordinates":[-106.97096000000001,26.03579],"type":"Point"}
}