{
  "type": "Feature",
  "properties": {
    "gn:admin1_code":"6",
    "gn:admin2_code":"29.0",
    "gn:asciiname":"Piedras Coloradas",
    "gn:country_code":"MX",
    "gn:dem":2589,
    "gn:feature_class":"P",
    "gn:feature_code":"PPL",
    "gn:name":"Piedras Coloradas",
    "gn:population":7,
    "gn:timezone":"America/Chihuahua",
    "iso:country":"MX",
    "name:cat_x_preferred":[
        "Piedras Coloradas"
    ],
    "name:deu_x_preferred":[
        "Piedras Coloradas"
    ],
    "name:fra_x_preferred":[
        "Piedras Coloradas"
    ],
    "name:hye_x_preferred":[
        "\u054a\u0565\u0564\u0580\u0561\u057d \u053f\u0578\u056c\u0578\u0580\u0561\u0564\u0561\u057d"
    ],
    "name:ita_x_preferred":[
        "Piedras Coloradas"
    ],
    "name:nor_x_preferred":[
        "Piedras Coloradas"
    ],
    "name:rus_x_preferred":[
        "\u041f\u044c\u0435\u0434\u0440\u0430\u0441-\u041a\u043e\u043b\u043e\u0440\u0430\u0434\u0430\u0441"
    ],
    "name:spa_x_preferred":[
        "Piedras Coloradas"
    ],
    "wof:name":"Piedras Coloradas",
    "wof:placetype":"locality",
    "wof:population":7
},
  "geometry": {"coordinates":[-106.97096000000001,26.03579],"type":"Point"}
}