{
  "type": "Feature",
  "properties": {
    "gn:admin1_code":"32",
    "gn:admin2_code":"19.0",
    "gn:asciiname":"Mana",
    "gn:country_code":"MX",
    "gn:dem":1369,
    "gn:feature_class":"P",
    "gn:feature_code":"PPL",
    "gn:name":"Ma\u00f1a",
    "gn:population":0,
    "gn:timezone":"America/Mexico_City",
    "iso:country":"MX",
    "name:spa_x_preferred":[
        "Ma\u00f1a"
    ],
    "wof:name":"Mana",
    "wof:placetype":"locality"
},
  "geometry": {"coordinates":[-103.00899,21.56686],"type":"Point"}
}