{
  "type": "Feature",
  "properties": {
    "gn:admin1_code":"32",
    "gn:admin2_code":"19.0",
    "gn:asciiname":"Mana",
    "gn:country_code":"MX",
    "gn:dem":1369,
    "gn:feature_class":"P",
    "gn:feature_code":"PPL",
    "gn:name":"Ma\u00f1a",
    "gn:population":0,
    "gn:timezone":"America/Mexico_City",
    "iso:country":"MX",
    "name:afr_x_preferred":[
        "Mana"
    ],
    "name:cat_x_preferred":[
        "Mana"
    ],
    "name:ces_x_preferred":[
        "Mana"
    ],
    "name:dan_x_preferred":[
        "Mana"
    ],
    "name:deu_x_preferred":[
        "Mana"
    ],
    "name:fas_x_preferred":[
        "\u0645\u0627\u0646\u0627"
    ],
    "name:fin_x_preferred":[
        "Mana"
    ],
    "name:fra_x_preferred":[
        "Mana"
    ],
    "name:hun_x_preferred":[
        "Mana"
    ],
    "name:ind_x_preferred":[
        "Mana"
    ],
    "name:ita_x_preferred":[
        "Mana"
    ],
    "name:lat_x_preferred":[
        "Mana"
    ],
    "name:lit_x_preferred":[
        "Magin\u0117 energija"
    ],
    "name:mkd_x_preferred":[
        "\u041c\u0430\u043d\u0430"
    ],
    "name:nld_x_preferred":[
        "Mana"
    ],
    "name:pol_x_preferred":[
        "Mana"
    ],
    "name:por_x_preferred":[
        "Mana"
    ],
    "name:rus_x_preferred":[
        "\u041c\u0430\u043d\u0430"
    ],
    "name:slk_x_preferred":[
        "Mana"
    ],
    "name:spa_x_preferred":[
        "Ma\u00f1a"
    ],
    "name:spa_x_variant":[
        "Mana"
    ],
    "name:swe_x_preferred":[
        "Mana"
    ],
    "name:ukr_x_preferred":[
        "\u041c\u0430\u043d\u0430"
    ],
    "wof:name":"Mana",
    "wof:placetype":"locality"
},
  "geometry": {"coordinates":[-103.00899,21.56686],"type":"Point"}
}