{
  "type": "Feature",
  "properties": {
    "gn:admin1_code":"11.0",
    "gn:admin2_code":"1.0",
    "gn:asciiname":"Estacion Joaquin",
    "gn:country_code":"MX",
    "gn:dem":1695,
    "gn:feature_class":"P",
    "gn:feature_code":"PPL",
    "gn:name":"Estaci\u00f3n Joaqu\u00edn",
    "gn:population":0,
    "gn:timezone":"America/Mexico_City",
    "iso:country":"MX",
    "name:spa_x_preferred":[
        "Estaci\u00f3n Joaqu\u00edn"
    ],
    "name:und_x_variant":[
        "El Alto",
        "Joaqu\u00edn El Alto",
        "Joaqu\u00edn"
    ],
    "wof:name":"Estacion Joaquin",
    "wof:placetype":"locality"
},
  "geometry": {"coordinates":[-101.51993,20.56082],"type":"Point"}
}