{
  "type": "Feature",
  "properties": {
    "gn:admin1_code":"5",
    "gn:admin2_code":"23.0",
    "gn:asciiname":"Tzajalchen",
    "gn:country_code":"MX",
    "gn:dem":2010,
    "gn:feature_class":"P",
    "gn:feature_code":"PPL",
    "gn:name":"Tzajalch\u00e9n",
    "gn:population":635,
    "gn:timezone":"America/Mexico_City",
    "iso:country":"MX",
    "name:und_x_variant":[
        "Tzajalch\u00e9n"
    ],
    "wof:name":"Tzajalchen",
    "wof:placetype":"locality",
    "wof:population":635
},
  "geometry": {"coordinates":[-92.64610999999999,16.83722],"type":"Point"}
}