{
  "type": "Feature",
  "properties": {
    "gn:admin1_code":"16",
    "gn:admin2_code":"13",
    "gn:asciiname":"Puerto Blanco (Parras del Puerto)",
    "gn:country_code":"MX",
    "gn:dem":1311,
    "gn:feature_class":"P",
    "gn:feature_code":"PPL",
    "gn:name":"Puerto Blanco (Parras del Puerto)",
    "gn:population":37,
    "gn:timezone":"America/Mexico_City",
    "iso:country":"MX",
    "wof:name":"Puerto Blanco (Parras del Puerto)",
    "wof:placetype":"locality",
    "wof:population":37
},
  "geometry": {"coordinates":[-101.03167000000001,19.13639],"type":"Point"}
}