{
  "type": "Feature",
  "properties": {
    "gn:admin1_code":"20.0",
    "gn:admin2_code":"302.0",
    "gn:asciiname":"Las Palmas",
    "gn:country_code":"MX",
    "gn:dem":349,
    "gn:feature_class":"P",
    "gn:feature_code":"PPL",
    "gn:name":"Las Palmas",
    "gn:population":0,
    "gn:timezone":"America/Mexico_City",
    "iso:country":"MX",
    "name:spa_x_preferred":[
        "Las Palmas"
    ],
    "wof:name":"Las Palmas",
    "wof:placetype":"locality"
},
  "geometry": {"coordinates":[-97.99131,16.52512999999999],"type":"Point"}
}