{
  "type": "Feature",
  "properties": {
    "gn:admin1_code":"18",
    "gn:admin2_code":"9.0",
    "gn:asciiname":"La Guasimita",
    "gn:country_code":"MX",
    "gn:dem":801,
    "gn:feature_class":"P",
    "gn:feature_code":"PPL",
    "gn:name":"La Guasimita",
    "gn:population":7,
    "gn:timezone":"America/Mazatlan",
    "iso:country":"MX",
    "wof:name":"La Guasimita",
    "wof:placetype":"locality",
    "wof:population":7
},
  "geometry": {"coordinates":[-104.80972,21.86889],"type":"Point"}
}