{
  "type": "Feature",
  "properties": {
    "gn:admin1_code":"25",
    "gn:admin2_code":"13.0",
    "gn:asciiname":"La Ponderosa",
    "gn:country_code":"MX",
    "gn:dem":160,
    "gn:feature_class":"P",
    "gn:feature_code":"PPL",
    "gn:name":"La Ponderosa",
    "gn:population":8,
    "gn:timezone":"America/Mazatlan",
    "iso:country":"MX",
    "wof:name":"La Ponderosa",
    "wof:placetype":"locality",
    "wof:population":8
},
  "geometry": {"coordinates":[-107.58861,25.17692000000001],"type":"Point"}
}