{
  "type": "Feature",
  "properties": {
    "gn:admin1_code":"23",
    "gn:admin2_code":"4.0",
    "gn:asciiname":"Miguel Aleman",
    "gn:country_code":"MX",
    "gn:dem":90,
    "gn:feature_class":"P",
    "gn:feature_code":"PPL",
    "gn:name":"Miguel Alem\u00e1n",
    "gn:population":688,
    "gn:timezone":"America/Cancun",
    "iso:country":"MX",
    "name:und_x_variant":[
        "Miguel Alem\u00e1n"
    ],
    "wof:name":"Miguel Aleman",
    "wof:placetype":"locality",
    "wof:population":688
},
  "geometry": {"coordinates":[-89.09333000000002,18.91361],"type":"Point"}
}