{
  "type": "Feature",
  "properties": {
    "gn:gn_country":"MX",
    "gn:gn_fcode":"PPL",
    "gn:gn_pop":0,
    "iso:country":"MX",
    "name:arg_x_preferred":[
        "Los Arcos"
    ],
    "name:ast_x_preferred":[
        "Los Arcos"
    ],
    "name:bre_x_preferred":[
        "Urantzia"
    ],
    "name:cat_x_preferred":[
        "Los Arcos"
    ],
    "name:ceb_x_preferred":[
        "Los Arcos"
    ],
    "name:deu_x_preferred":[
        "Los Arcos"
    ],
    "name:eus_x_preferred":[
        "Los Arcos"
    ],
    "name:fra_x_preferred":[
        "Los Arcos"
    ],
    "name:glg_x_preferred":[
        "Los Arcos"
    ],
    "name:hun_x_preferred":[
        "Los Arcos"
    ],
    "name:ita_x_preferred":[
        "Los Arcos"
    ],
    "name:lat_x_preferred":[
        "Arcus"
    ],
    "name:msa_x_preferred":[
        "Los Arcos"
    ],
    "name:nld_x_preferred":[
        "Los Arcos"
    ],
    "name:oci_x_preferred":[
        "Los Arcos"
    ],
    "name:pol_x_preferred":[
        "Los Arcos"
    ],
    "name:por_x_preferred":[
        "Los Arcos"
    ],
    "name:rus_x_preferred":[
        "\u041b\u043e\u0441-\u0410\u0440\u043a\u043e\u0441"
    ],
    "name:sco_x_preferred":[
        "Los Arcos"
    ],
    "name:spa_x_preferred":[
        "Los Arcos"
    ],
    "name:ukr_x_preferred":[
        "\u041b\u043e\u0441-\u0410\u0440\u043a\u043e\u0441"
    ],
    "name:uzb_x_preferred":[
        "Los Arcos"
    ],
    "name:vie_x_preferred":[
        "Los Arcos"
    ],
    "name:war_x_preferred":[
        "Los Arcos"
    ],
    "name:zho_x_preferred":[
        "\u6d1b\u8428\u5c14\u79d1\u65af"
    ],
    "qs_pg:aaroncc":"MX",
    "qs_pg:gn_country":"MX",
    "qs_pg:gn_fcode":"PPL",
    "qs_pg:gn_pop":0,
    "qs_pg:name":"Los Arcos",
    "qs_pg:name_adm0":"M\u00e9xico",
    "qs_pg:name_adm1":"San Luis Potosi",
    "qs_pg:photos":1,
    "qs_pg:photos_1k":1,
    "qs_pg:photos_9k":1,
    "qs_pg:photos_9r":1,
    "qs_pg:photos_all":1,
    "qs_pg:photos_sr":1,
    "qs_pg:pop_sr":0,
    "qs_pg:qs_pg_placetype":"neighbourhood",
    "qs_pg:qs_pg_placetype_gp":"Suburb",
    "qs_pg:woe_adm0":23424900,
    "woe:adm0_id":23424900,
    "woe:name_adm0":"M\u00e9xico",
    "woe:name_adm1":"San Luis Potosi",
    "woe:placetype":"Suburb",
    "wof:name":"Los Arcos",
    "wof:placetype":"neighbourhood"
},
  "geometry": {"coordinates":[-101.23333,23.23333],"type":"Point"}
}