{
  "type": "Feature",
  "properties": {
    "gn:admin1_code":"26.0",
    "gn:admin2_code":"51.0",
    "gn:asciiname":"Opata",
    "gn:country_code":"MX",
    "gn:dem":132,
    "gn:feature_class":"P",
    "gn:feature_code":"PPL",
    "gn:name":"\u00d3pata",
    "gn:population":0,
    "gn:timezone":"America/Hermosillo",
    "iso:country":"MX",
    "name:bul_x_preferred":[
        "\u041e\u043f\u0430\u0442\u0430"
    ],
    "name:cat_x_preferred":[
        "\u00d3pates"
    ],
    "name:deu_x_preferred":[
        "Opata"
    ],
    "name:fra_x_preferred":[
        "Opata"
    ],
    "name:hrv_x_preferred":[
        "\u00d3pata"
    ],
    "name:lit_x_preferred":[
        "Opatai"
    ],
    "name:mal_x_preferred":[
        "\u0d12\u0d2a\u0d3e\u0d31\u0d4d\u0d31"
    ],
    "name:spa_x_preferred":[
        "\u00d3pata"
    ],
    "wof:name":"Opata",
    "wof:placetype":"locality"
},
  "geometry": {"coordinates":[-109.65983,28.12865],"type":"Point"}
}