{
  "type": "Feature",
  "properties": {
    "gn:admin1_code":"16.0",
    "gn:admin2_code":"9.0",
    "gn:asciiname":"Las Caramicuas",
    "gn:country_code":"MX",
    "gn:dem":1774,
    "gn:feature_class":"P",
    "gn:feature_code":"PPL",
    "gn:name":"Las Caramicuas",
    "gn:population":0,
    "gn:timezone":"America/Mexico_City",
    "iso:country":"MX",
    "name:spa_x_preferred":[
        "Las Caramicuas"
    ],
    "name:und_x_variant":[
        "Las Carrmicuas"
    ],
    "wof:name":"Las Caramicuas",
    "wof:placetype":"locality"
},
  "geometry": {"coordinates":[-101.63793,19.05334],"type":"Point"}
}