{
  "type": "Feature",
  "properties": {
    "gn:admin1_code":"24.0",
    "gn:admin2_code":"7.0",
    "gn:asciiname":"Lagunillas",
    "gn:country_code":"MX",
    "gn:dem":1671,
    "gn:feature_class":"P",
    "gn:feature_code":"PPL",
    "gn:name":"Lagunillas",
    "gn:population":0,
    "gn:timezone":"America/Mexico_City",
    "iso:country":"MX",
    "name:ceb_x_preferred":[
        "Lagunillas"
    ],
    "name:deu_x_preferred":[
        "Lagunillas"
    ],
    "name:fra_x_preferred":[
        "Lagunillas"
    ],
    "name:ita_x_preferred":[
        "Lagunillas"
    ],
    "name:lit_x_preferred":[
        "Laguniljasas"
    ],
    "name:nld_x_preferred":[
        "Lagunillas"
    ],
    "name:sco_x_preferred":[
        "Lagunillas"
    ],
    "name:spa_x_preferred":[
        "Lagunillas"
    ],
    "name:swe_x_preferred":[
        "Lagunillas"
    ],
    "name:und_x_variant":[
        "Lagunilla",
        "Lagunillas"
    ],
    "wof:name":"Lagunillas",
    "wof:placetype":"locality"
},
  "geometry": {"coordinates":[-100.57262,23.78196],"type":"Point"}
}