{
  "type": "Feature",
  "properties": {
    "gn:admin1_code":"11.0",
    "gn:admin2_code":"17.0",
    "gn:asciiname":"El Copal",
    "gn:country_code":"MX",
    "gn:dem":1753,
    "gn:feature_class":"P",
    "gn:feature_code":"PPL",
    "gn:name":"El Copal",
    "gn:population":0,
    "gn:timezone":"America/Mexico_City",
    "iso:country":"MX",
    "name:spa_x_preferred":[
        "El Copal"
    ],
    "wof:name":"El Copal",
    "wof:placetype":"locality"
},
  "geometry": {"coordinates":[-101.33709,20.73967],"type":"Point"}
}