{
  "type": "Feature",
  "properties": {
    "gn:admin1_code":"13",
    "gn:admin2_code":"36.0",
    "gn:asciiname":"Atecoxco",
    "gn:country_code":"MX",
    "gn:dem":1609,
    "gn:feature_class":"P",
    "gn:feature_code":"PPL",
    "gn:name":"Atecoxco",
    "gn:population":0,
    "gn:timezone":"America/Mexico_City",
    "iso:country":"MX",
    "name:und_x_variant":[
        "San Nicol\u00e1s"
    ],
    "wof:name":"Atecoxco",
    "wof:placetype":"locality"
},
  "geometry": {"coordinates":[-98.58816,20.50802],"type":"Point"}
}