{
  "type": "Feature",
  "properties": {
    "gn:admin1_code":"6",
    "gn:admin2_code":"20.0",
    "gn:asciiname":"El Potrerito",
    "gn:country_code":"MX",
    "gn:dem":1339,
    "gn:feature_class":"P",
    "gn:feature_code":"PPL",
    "gn:name":"El Potrerito",
    "gn:population":0,
    "gn:timezone":"America/Chihuahua",
    "iso:country":"MX",
    "name:spa_x_preferred":[
        "El Potrerito"
    ],
    "name:spa_x_variant":[
        "Potrero"
    ],
    "wof:name":"El Potrerito",
    "wof:placetype":"locality"
},
  "geometry": {"coordinates":[-108.37492,27.40217],"type":"Point"}
}