{
  "type": "Feature",
  "properties": {
    "gn:admin1_code":"32",
    "gn:admin2_code":"10.0",
    "gn:asciiname":"San Jose Gandara",
    "gn:country_code":"MX",
    "gn:dem":2092,
    "gn:feature_class":"P",
    "gn:feature_code":"PPL",
    "gn:name":"San Jose Gandara",
    "gn:population":0,
    "gn:timezone":"America/Mexico_City",
    "iso:country":"MX",
    "name:spa_x_preferred":[
        "San Jose Gandara"
    ],
    "wof:name":"San Jose Gandara",
    "wof:placetype":"locality"
},
  "geometry": {"coordinates":[-102.75969000000001,23.15788],"type":"Point"}
}