{
  "type": "Feature",
  "properties": {
    "gn:admin1_code":"11.0",
    "gn:admin2_code":"23.0",
    "gn:asciiname":"Trinidad de los Angeles (La Jabonera)",
    "gn:country_code":"MX",
    "gn:dem":1691,
    "gn:feature_class":"P",
    "gn:feature_code":"PPL",
    "gn:name":"Trinidad de los \u00c1ngeles (La Jabonera)",
    "gn:population":131,
    "gn:timezone":"America/Mexico_City",
    "iso:country":"MX",
    "wof:name":"Trinidad de los Angeles (La Jabonera)",
    "wof:placetype":"locality",
    "wof:population":131
},
  "geometry": {"coordinates":[-101.69861,20.19694],"type":"Point"}
}