{
  "type": "Feature",
  "properties": {
    "gn:admin1_code":"10",
    "gn:admin2_code":"7.0",
    "gn:asciiname":"Cuatro de Diciembre (Sagundo)",
    "gn:country_code":"MX",
    "gn:dem":1125,
    "gn:feature_class":"P",
    "gn:feature_code":"PPL",
    "gn:name":"Cuatro de Diciembre (Sagundo)",
    "gn:population":258,
    "gn:timezone":"America/Monterrey",
    "iso:country":"MX",
    "wof:name":"Cuatro de Diciembre (Sagundo)",
    "wof:placetype":"locality",
    "wof:population":258
},
  "geometry": {"coordinates":[-103.58944,25.71611],"type":"Point"}
}