{
  "type": "Feature",
  "properties": {
    "gn:admin1_code":"18.0",
    "gn:admin2_code":"14.0",
    "gn:asciiname":"El Suspiro",
    "gn:country_code":"MX",
    "gn:dem":1073,
    "gn:feature_class":"P",
    "gn:feature_code":"PPL",
    "gn:name":"El Suspiro",
    "gn:population":0,
    "gn:timezone":"America/Mazatlan",
    "iso:country":"MX",
    "name:spa_x_preferred":[
        "El Suspiro"
    ],
    "wof:name":"El Suspiro",
    "wof:placetype":"locality"
},
  "geometry": {"coordinates":[-104.75397,21.36804],"type":"Point"}
}