{
  "type": "Feature",
  "properties": {
    "gn:admin1_code":"20",
    "gn:admin2_code":"155",
    "gn:asciiname":"Palo Blanco",
    "gn:country_code":"MX",
    "gn:dem":1938,
    "gn:feature_class":"P",
    "gn:feature_code":"PPL",
    "gn:name":"Palo Blanco",
    "gn:population":18,
    "gn:timezone":"America/Mexico_City",
    "iso:country":"MX",
    "wof:name":"Palo Blanco",
    "wof:placetype":"locality",
    "wof:population":18
},
  "geometry": {"coordinates":[-96.96083,16.58806],"type":"Point"}
}