{
  "type": "Feature",
  "properties": {
    "gn:admin1_code":"26",
    "gn:admin2_code":"3.0",
    "gn:asciiname":"El Bebedero",
    "gn:country_code":"MX",
    "gn:dem":220,
    "gn:feature_class":"P",
    "gn:feature_code":"PPL",
    "gn:name":"El Bebedero",
    "gn:population":0,
    "gn:timezone":"America/Hermosillo",
    "iso:country":"MX",
    "name:ita_x_preferred":[
        "El Bebedero"
    ],
    "name:spa_x_preferred":[
        "El Bebedero"
    ],
    "name:zho_x_preferred":[
        "\u57c3\u723e\u8c9d\u8c9d\u5fb7\u7f85"
    ],
    "wof:name":"El Bebedero",
    "wof:placetype":"locality"
},
  "geometry": {"coordinates":[-109.20921,27.12234],"type":"Point"}
}