{
  "type": "Feature",
  "properties": {
    "gn:admin1_code":"2",
    "gn:admin2_code":"1",
    "gn:asciiname":"Familia Perez (El Cuartel)",
    "gn:country_code":"MX",
    "gn:dem":35,
    "gn:feature_class":"P",
    "gn:feature_code":"PPL",
    "gn:name":"Familia P\u00e9rez (El Cuartel)",
    "gn:population":30,
    "gn:timezone":"America/Tijuana",
    "iso:country":"MX",
    "name:und_x_variant":[
        "Familia P\u00e9rez (El Cuartel)"
    ],
    "wof:name":"Familia Perez (El Cuartel)",
    "wof:placetype":"locality",
    "wof:population":30
},
  "geometry": {"coordinates":[-115.97056000000001,30.72889],"type":"Point"}
}