{
  "type": "Feature",
  "properties": {
    "gn:admin1_code":"5",
    "gn:admin2_code":"73",
    "gn:asciiname":"Nopalito",
    "gn:country_code":"MX",
    "gn:dem":1971,
    "gn:feature_class":"P",
    "gn:feature_code":"PPL",
    "gn:name":"Nopalito",
    "gn:population":28,
    "gn:timezone":"America/Mexico_City",
    "iso:country":"MX",
    "name:spa_x_preferred":[
        "Nopal#Gastronomia"
    ],
    "wof:name":"Nopalito",
    "wof:placetype":"locality",
    "wof:population":28
},
  "geometry": {"coordinates":[-92.95972,17.21083],"type":"Point"}
}