{
  "type": "Feature",
  "properties": {
    "iso:country":"MX",
    "name:spa_x_preferred":[
        "Z Milit Hca Escuela Naval Militar"
    ],
    "name:unk_x_variant":[
        "Z Milit Hca Escuela Naval Militar"
    ],
    "qs:gn_adm0_cc":"MX",
    "qs:gn_local":3532821,
    "qs:gn_nam_loc":"anton lizardo",
    "qs:gn_namadm1":"30",
    "qs:local_max":30,
    "qs:local_sum":30,
    "qs:localhoods":1,
    "qs:name":"Z Milit Hca Escuela Naval Militar",
    "qs:name_adm0":"M\u00e9xico",
    "qs:name_adm1":"Veracruz-Llave",
    "qs:name_adm2":"Alvarado",
    "qs:name_local":"Ant\u00f3n Lizardo",
    "qs:photo_max":11,
    "qs:photo_sum":30,
    "qs:placetype":"Suburb",
    "qs:quad_count":9,
    "qs:woe_adm0":23424900,
    "qs:woe_adm1":2346293,
    "qs:woe_adm2":12601729,
    "qs:woe_lau":0,
    "qs:woe_local":112208,
    "qs:woe_ver":"7.10.0",
    "wof:lang":[
        "spa"
    ],
    "wof:name":"Z Milit Hca Escuela Naval Militar",
    "wof:placetype":"neighbourhood"
},
  "geometry": {"coordinates":[-95.992493,19.062118],"type":"Point"}
}