{
  "type": "Feature",
  "properties": {
    "gn:admin1_code":"2",
    "gn:admin2_code":"2",
    "gn:asciiname":"Rancho de Ramon Leyva",
    "gn:country_code":"MX",
    "gn:dem":-1,
    "gn:feature_class":"P",
    "gn:feature_code":"PPL",
    "gn:name":"Rancho de Ram\u00f3n Leyva",
    "gn:population":9,
    "gn:timezone":"America/Tijuana",
    "iso:country":"MX",
    "name:und_x_variant":[
        "Rancho de Ram\u00f3n Leyva"
    ],
    "wof:name":"Rancho de Ramon Leyva",
    "wof:placetype":"locality",
    "wof:population":9
},
  "geometry": {"coordinates":[-115.60805999999999,32.63583],"type":"Point"}
}