{
  "type": "Feature",
  "properties": {
    "gn:admin1_code":"30",
    "gn:admin2_code":"100",
    "gn:asciiname":"Colonia Francisco Villa",
    "gn:country_code":"MX",
    "gn:dem":37,
    "gn:feature_class":"P",
    "gn:feature_code":"PPL",
    "gn:name":"Colonia Francisco Villa",
    "gn:population":35,
    "gn:timezone":"America/Mexico_City",
    "iso:country":"MX",
    "wof:name":"Colonia Francisco Villa",
    "wof:placetype":"locality",
    "wof:population":35
},
  "geometry": {"coordinates":[-96.32417,19.04472],"type":"Point"}
}