{
  "type": "Feature",
  "properties": {
    "gn:admin1_code":"6.0",
    "gn:admin2_code":"40.0",
    "gn:asciiname":"El Hains",
    "gn:country_code":"MX",
    "gn:dem":1701,
    "gn:feature_class":"P",
    "gn:feature_code":"PPL",
    "gn:name":"El Hains",
    "gn:population":0,
    "gn:timezone":"America/Chihuahua",
    "iso:country":"MX",
    "name:spa_x_preferred":[
        "El Hains"
    ],
    "name:spa_x_variant":[
        "Sainz",
        "El Hainz"
    ],
    "wof:name":"El Hains",
    "wof:placetype":"locality"
},
  "geometry": {"coordinates":[-108.58985,29.44752],"type":"Point"}
}