{
  "type": "Feature",
  "properties": {
    "gn:admin1_code":"30",
    "gn:admin2_code":"143.0",
    "gn:asciiname":"El Tular",
    "gn:country_code":"MX",
    "gn:dem":19,
    "gn:feature_class":"P",
    "gn:feature_code":"PPL",
    "gn:name":"El Tular",
    "gn:population":277,
    "gn:timezone":"America/Mexico_City",
    "iso:country":"MX",
    "wof:name":"El Tular",
    "wof:placetype":"locality",
    "wof:population":277
},
  "geometry": {"coordinates":[-95.44833,18.29444],"type":"Point"}
}