{
  "type": "Feature",
  "properties": {
    "gn:admin1_code":"24",
    "gn:admin2_code":"18.0",
    "gn:asciiname":"Chununtzen",
    "gn:country_code":"MX",
    "gn:dem":99,
    "gn:feature_class":"P",
    "gn:feature_code":"PPL",
    "gn:name":"Chununtzen",
    "gn:population":0,
    "gn:timezone":"America/Mexico_City",
    "iso:country":"MX",
    "wof:name":"Chununtzen",
    "wof:placetype":"locality"
},
  "geometry": {"coordinates":[-98.97425,21.48598],"type":"Point"}
}