{
  "type": "Feature",
  "properties": {
    "gn:admin1_code":"3.0",
    "gn:admin2_code":"3.0",
    "gn:asciiname":"San Francisco de la Costa",
    "gn:country_code":"MX",
    "gn:dem":16,
    "gn:feature_class":"P",
    "gn:feature_code":"PPL",
    "gn:name":"San Francisco de la Costa",
    "gn:population":0,
    "gn:timezone":"America/Mazatlan",
    "iso:country":"MX",
    "name:spa_x_preferred":[
        "San Francisco de la Costa"
    ],
    "name:und_x_variant":[
        "San Francisco"
    ],
    "wof:name":"San Francisco de la Costa",
    "wof:placetype":"locality"
},
  "geometry": {"coordinates":[-111.56641999999999,24.52924],"type":"Point"}
}