{
  "type": "Feature",
  "properties": {
    "gn:admin1_code":"14.0",
    "gn:admin2_code":"6.0",
    "gn:asciiname":"El Cabezon",
    "gn:country_code":"MX",
    "gn:dem":1270,
    "gn:feature_class":"P",
    "gn:feature_code":"PPL",
    "gn:name":"El Cabez\u00f3n",
    "gn:population":0,
    "gn:timezone":"America/Mexico_City",
    "iso:country":"MX",
    "wof:name":"El Cabezon",
    "wof:placetype":"locality"
},
  "geometry": {"coordinates":[-103.95144000000001,20.49569],"type":"Point"}
}