{
  "type": "Feature",
  "properties": {
    "gn:admin1_code":"8.0",
    "gn:admin2_code":"7.0",
    "gn:asciiname":"Rancho los Nopales",
    "gn:country_code":"MX",
    "gn:dem":8,
    "gn:feature_class":"P",
    "gn:feature_code":"PPL",
    "gn:name":"Rancho los Nopales",
    "gn:population":0,
    "gn:timezone":"America/Mexico_City",
    "iso:country":"MX",
    "name:spa_x_preferred":[
        "Rancho los Nopales"
    ],
    "wof:name":"Rancho los Nopales",
    "wof:placetype":"locality"
},
  "geometry": {"coordinates":[-104.20726999999999,19.02971],"type":"Point"}
}