{
  "type": "Feature",
  "properties": {
    "gn:admin1_code":"7",
    "gn:admin2_code":"24.0",
    "gn:asciiname":"Rancho Los Hoveros",
    "gn:country_code":"MX",
    "gn:dem":1584,
    "gn:feature_class":"P",
    "gn:feature_code":"PPL",
    "gn:name":"Rancho Los Hoveros",
    "gn:population":0,
    "gn:timezone":"America/Monterrey",
    "iso:country":"MX",
    "wof:name":"Rancho Los Hoveros",
    "wof:placetype":"locality"
},
  "geometry": {"coordinates":[-102.13333,25.41667],"type":"Point"}
}