{
  "type": "Feature",
  "properties": {
    "gn:admin1_code":"6",
    "gn:admin2_code":"37.0",
    "gn:asciiname":"El Zorro Plateado",
    "gn:country_code":"MX",
    "gn:dem":1276,
    "gn:feature_class":"P",
    "gn:feature_code":"PPL",
    "gn:name":"El Zorro Plateado",
    "gn:population":0,
    "gn:timezone":"America/Ojinaga",
    "iso:country":"MX",
    "wof:name":"El Zorro Plateado",
    "wof:placetype":"locality"
},
  "geometry": {"coordinates":[-106.48585,31.29034],"type":"Point"}
}