{
  "type": "Feature",
  "properties": {
    "gn:admin1_code":"7",
    "gn:admin2_code":"33.0",
    "gn:asciiname":"Ejido Santa Rita",
    "gn:country_code":"MX",
    "gn:dem":1092,
    "gn:feature_class":"P",
    "gn:feature_code":"PPL",
    "gn:name":"Ejido Santa Rita",
    "gn:population":0,
    "gn:timezone":"America/Monterrey",
    "iso:country":"MX",
    "name:spa_x_preferred":[
        "Ejido Santa Rita"
    ],
    "name:und_x_variant":[
        "Santa Rita"
    ],
    "wof:name":"Ejido Santa Rita",
    "wof:placetype":"locality"
},
  "geometry": {"coordinates":[-102.81129,25.68393],"type":"Point"}
}