{
  "type": "Feature",
  "properties": {
    "gn:admin1_code":"15.0",
    "gn:asciiname":"La Dieta",
    "gn:country_code":"MX",
    "gn:dem":2758,
    "gn:feature_class":"P",
    "gn:feature_code":"PPL",
    "gn:name":"La Dieta",
    "gn:population":0,
    "gn:timezone":"America/Mexico_City",
    "iso:country":"MX",
    "name:und_x_variant":[
        "Dieta",
        "Las Dietas"
    ],
    "wof:name":"La Dieta",
    "wof:placetype":"locality"
},
  "geometry": {"coordinates":[-100.20458000000001,19.44765],"type":"Point"}
}