{
  "type": "Feature",
  "properties": {
    "gn:admin1_code":"20",
    "gn:admin2_code":"43.0",
    "gn:asciiname":"Pedro Gallegos",
    "gn:country_code":"MX",
    "gn:dem":18,
    "gn:feature_class":"P",
    "gn:feature_code":"PPL",
    "gn:name":"Pedro Gallegos",
    "gn:population":0,
    "gn:timezone":"America/Mexico_City",
    "iso:country":"MX",
    "wof:name":"Pedro Gallegos",
    "wof:placetype":"locality"
},
  "geometry": {"coordinates":[-95.05,16.41667],"type":"Point"}
}