{
  "type": "Feature",
  "properties": {
    "gn:admin1_code":"5",
    "gn:admin2_code":"108.0",
    "gn:asciiname":"Montebello",
    "gn:country_code":"MX",
    "gn:dem":683,
    "gn:feature_class":"P",
    "gn:feature_code":"PPL",
    "gn:name":"Montebello",
    "gn:population":7,
    "gn:timezone":"America/Mexico_City",
    "iso:country":"MX",
    "wof:name":"Montebello",
    "wof:placetype":"locality",
    "wof:population":7
},
  "geometry": {"coordinates":[-93.27861,16.33389],"type":"Point"}
}