{
  "type": "Feature",
  "properties": {
    "gn:admin1_code":"11",
    "gn:admin2_code":"30.0",
    "gn:asciiname":"San Antonio de las Alazanas (Buenos Aires)",
    "gn:country_code":"MX",
    "gn:dem":2273,
    "gn:feature_class":"P",
    "gn:feature_code":"PPL",
    "gn:name":"San Antonio de las Alazanas (Buenos Aires)",
    "gn:population":52,
    "gn:timezone":"America/Mexico_City",
    "iso:country":"MX",
    "wof:name":"San Antonio de las Alazanas (Buenos Aires)",
    "wof:placetype":"locality",
    "wof:population":52
},
  "geometry": {"coordinates":[-101.43832999999999,21.25056],"type":"Point"}
}