{
  "type": "Feature",
  "properties": {
    "gn:admin1_code":"6.0",
    "gn:asciiname":"Silos del Campo",
    "gn:country_code":"MX",
    "gn:dem":2091,
    "gn:feature_class":"P",
    "gn:feature_code":"PPL",
    "gn:name":"Silos del Campo",
    "gn:population":0,
    "gn:timezone":"America/Chihuahua",
    "iso:country":"MX",
    "name:spa_x_preferred":[
        "Silos del Campo"
    ],
    "wof:name":"Silos del Campo",
    "wof:placetype":"locality"
},
  "geometry": {"coordinates":[-106.72011000000001,29.12837],"type":"Point"}
}