{
  "type": "Feature",
  "properties": {
    "gn:admin1_code":"14",
    "gn:admin2_code":"49",
    "gn:asciiname":"El Saucito",
    "gn:country_code":"MX",
    "gn:dem":1301,
    "gn:feature_class":"P",
    "gn:feature_code":"PPL",
    "gn:name":"El Saucito",
    "gn:population":14,
    "gn:timezone":"America/Mexico_City",
    "iso:country":"MX",
    "name:spa_x_preferred":[
        "El Saucito"
    ],
    "wof:name":"El Saucito",
    "wof:placetype":"locality",
    "wof:population":14
},
  "geometry": {"coordinates":[-103.08667,19.29139],"type":"Point"}
}