{
  "type": "Feature",
  "properties": {
    "gn:admin1_code":"16",
    "gn:admin2_code":"35",
    "gn:asciiname":"El Carro",
    "gn:country_code":"MX",
    "gn:dem":500,
    "gn:feature_class":"P",
    "gn:feature_code":"PPL",
    "gn:name":"El Carro",
    "gn:population":41,
    "gn:timezone":"America/Mexico_City",
    "iso:country":"MX",
    "wof:name":"El Carro",
    "wof:placetype":"locality",
    "wof:population":41
},
  "geometry": {"coordinates":[-101.72944,18.89444],"type":"Point"}
}