{
  "type": "Feature",
  "properties": {
    "gn:admin1_code":"20",
    "gn:admin2_code":"317.0",
    "gn:asciiname":"Guadalupe Hidalgo",
    "gn:country_code":"MX",
    "gn:dem":2235,
    "gn:feature_class":"P",
    "gn:feature_code":"PPL",
    "gn:name":"Guadalupe Hidalgo",
    "gn:population":0,
    "gn:timezone":"America/Mexico_City",
    "iso:country":"MX",
    "name:spa_x_preferred":[
        "Guadalupe Hidalgo"
    ],
    "wof:name":"Guadalupe Hidalgo",
    "wof:placetype":"locality"
},
  "geometry": {"coordinates":[-97.62129,17.46557],"type":"Point"}
}