{
  "type": "Feature",
  "properties": {
    "gn:admin1_code":"14",
    "gn:admin2_code":"25.0",
    "gn:asciiname":"Mexiquito",
    "gn:country_code":"MX",
    "gn:dem":1754,
    "gn:feature_class":"P",
    "gn:feature_code":"PPL",
    "gn:name":"Mexiquito",
    "gn:population":0,
    "gn:timezone":"America/Mexico_City",
    "iso:country":"MX",
    "name:spa_x_preferred":[
        "Mexiquito"
    ],
    "wof:name":"Mexiquito",
    "wof:placetype":"locality"
},
  "geometry": {"coordinates":[-103.22868,21.99644],"type":"Point"}
}