{
  "type": "Feature",
  "properties": {
    "gn:admin1_code":"15.0",
    "gn:admin2_code":"9.0",
    "gn:asciiname":"Xachaltitla",
    "gn:country_code":"MX",
    "gn:dem":2539,
    "gn:feature_class":"P",
    "gn:feature_code":"PPL",
    "gn:name":"Xachaltitla",
    "gn:population":0,
    "gn:timezone":"America/Mexico_City",
    "iso:country":"MX",
    "name:spa_x_preferred":[
        "Xachaltitla"
    ],
    "wof:name":"Xachaltitla",
    "wof:placetype":"locality"
},
  "geometry": {"coordinates":[-98.79498,19.16781],"type":"Point"}
}