{
  "type": "Feature",
  "properties": {
    "gn:admin1_code":"3",
    "gn:admin2_code":"3",
    "gn:asciiname":"El Manantial",
    "gn:country_code":"MX",
    "gn:dem":34,
    "gn:feature_class":"P",
    "gn:feature_code":"PPL",
    "gn:name":"El Manantial",
    "gn:population":10,
    "gn:timezone":"America/Mazatlan",
    "iso:country":"MX",
    "wof:name":"El Manantial",
    "wof:placetype":"locality",
    "wof:population":10
},
  "geometry": {"coordinates":[-109.94608999999998,23.95088],"type":"Point"}
}