{
  "type": "Feature",
  "properties": {
    "gn:admin1_code":"28",
    "gn:admin2_code":"22.0",
    "gn:asciiname":"Los Naranjos",
    "gn:country_code":"MX",
    "gn:dem":11,
    "gn:feature_class":"P",
    "gn:feature_code":"PPL",
    "gn:name":"Los Naranjos",
    "gn:population":8,
    "gn:timezone":"America/Matamoros",
    "iso:country":"MX",
    "wof:name":"Los Naranjos",
    "wof:placetype":"locality",
    "wof:population":8
},
  "geometry": {"coordinates":[-97.78528,25.34278],"type":"Point"}
}