{
  "type": "Feature",
  "properties": {
    "gn:admin1_code":"30",
    "gn:admin2_code":"143.0",
    "gn:asciiname":"Cinco de Mayo",
    "gn:country_code":"MX",
    "gn:dem":18,
    "gn:feature_class":"P",
    "gn:feature_code":"PPL",
    "gn:name":"Cinco de Mayo",
    "gn:population":374,
    "gn:timezone":"America/Mexico_City",
    "iso:country":"MX",
    "wof:name":"Cinco de Mayo",
    "wof:placetype":"locality",
    "wof:population":374
},
  "geometry": {"coordinates":[-95.45833,18.33722],"type":"Point"}
}