{
  "type": "Feature",
  "properties": {
    "gn:admin1_code":"26.0",
    "gn:admin2_code":"36.0",
    "gn:asciiname":"La Cebolla",
    "gn:country_code":"MX",
    "gn:dem":765,
    "gn:feature_class":"P",
    "gn:feature_code":"PPL",
    "gn:name":"La Cebolla",
    "gn:population":0,
    "gn:timezone":"America/Hermosillo",
    "iso:country":"MX",
    "wof:name":"La Cebolla",
    "wof:placetype":"locality"
},
  "geometry": {"coordinates":[-111.14536,30.7575],"type":"Point"}
}