{
  "type": "Feature",
  "properties": {
    "gn:admin1_code":"5",
    "gn:admin2_code":"9.0",
    "gn:asciiname":"La Azteca Dos (San Francisco)",
    "gn:country_code":"MX",
    "gn:dem":10,
    "gn:feature_class":"P",
    "gn:feature_code":"PPL",
    "gn:name":"La Azteca Dos (San Francisco)",
    "gn:population":5,
    "gn:timezone":"America/Mexico_City",
    "iso:country":"MX",
    "wof:name":"La Azteca Dos (San Francisco)",
    "wof:placetype":"locality",
    "wof:population":5
},
  "geometry": {"coordinates":[-94.0363,16.15428],"type":"Point"}
}