{
  "type": "Feature",
  "properties": {
    "gn:admin1_code":"16.0",
    "gn:admin2_code":"110.0",
    "gn:asciiname":"Colonia Guadalupe Bocaneo",
    "gn:country_code":"MX",
    "gn:dem":1910,
    "gn:feature_class":"P",
    "gn:feature_code":"PPL",
    "gn:name":"Colonia Guadalupe Bocaneo",
    "gn:population":0,
    "gn:timezone":"America/Mexico_City",
    "iso:country":"MX",
    "name:spa_x_preferred":[
        "Colonia Guadalupe Bocaneo"
    ],
    "wof:name":"Colonia Guadalupe Bocaneo",
    "wof:placetype":"locality"
},
  "geometry": {"coordinates":[-100.82216,19.82823],"type":"Point"}
}