{
  "type": "Feature",
  "properties": {
    "gn:admin1_code":"4",
    "gn:admin2_code":"3.0",
    "gn:asciiname":"Puerto Escondido",
    "gn:country_code":"MX",
    "gn:dem":-1,
    "gn:feature_class":"P",
    "gn:feature_code":"PPL",
    "gn:name":"Puerto Escondido",
    "gn:population":0,
    "gn:timezone":"America/Merida",
    "iso:country":"MX",
    "name:ceb_x_preferred":[
        "Puerto Escondido"
    ],
    "name:deu_x_preferred":[
        "Puerto Escondido"
    ],
    "name:fra_x_preferred":[
        "Puerto Escondido"
    ],
    "name:ita_x_preferred":[
        "Puerto Escondido"
    ],
    "name:nld_x_preferred":[
        "Puerto Escondido"
    ],
    "name:pol_x_preferred":[
        "Puerto Escondido"
    ],
    "name:rus_x_preferred":[
        "\u041f\u0443\u044d\u0440\u0442\u043e-\u042d\u0441\u043a\u043e\u043d\u0434\u0438\u0434\u043e"
    ],
    "name:sco_x_preferred":[
        "Puerto Escondido"
    ],
    "name:spa_x_preferred":[
        "Puerto Escondido"
    ],
    "name:swe_x_preferred":[
        "Puerto Escondido"
    ],
    "name:vie_x_preferred":[
        "Puerto Escondido"
    ],
    "wof:name":"Puerto Escondido",
    "wof:placetype":"locality"
},
  "geometry": {"coordinates":[-91.41473000000001,18.86749],"type":"Point"}
}