{
  "type": "Feature",
  "properties": {
    "gn:admin1_code":"5",
    "gn:admin2_code":"3.0",
    "gn:asciiname":"El Arenal",
    "gn:country_code":"MX",
    "gn:dem":11,
    "gn:feature_class":"P",
    "gn:feature_code":"PPL",
    "gn:name":"El Arenal",
    "gn:population":0,
    "gn:timezone":"America/Mexico_City",
    "iso:country":"MX",
    "name:spa_x_preferred":[
        "El Arenal"
    ],
    "wof:name":"El Arenal",
    "wof:placetype":"locality"
},
  "geometry": {"coordinates":[-92.69923,15.17273],"type":"Point"}
}