{
  "type": "Feature",
  "properties": {
    "gn:admin1_code":"32",
    "gn:admin2_code":"46.0",
    "gn:asciiname":"Los Dolores",
    "gn:country_code":"MX",
    "gn:dem":2017,
    "gn:feature_class":"P",
    "gn:feature_code":"PPL",
    "gn:name":"Los Dolores",
    "gn:population":0,
    "gn:timezone":"America/Mexico_City",
    "iso:country":"MX",
    "wof:name":"Los Dolores",
    "wof:placetype":"locality"
},
  "geometry": {"coordinates":[-103.25,22.45],"type":"Point"}
}