{
  "type": "Feature",
  "properties": {
    "gn:admin1_code":"20",
    "gn:admin2_code":"123",
    "gn:asciiname":"El Cuajilote",
    "gn:country_code":"MX",
    "gn:dem":1715,
    "gn:feature_class":"P",
    "gn:feature_code":"PPL",
    "gn:name":"El Cuajilote",
    "gn:population":25,
    "gn:timezone":"America/Mexico_City",
    "iso:country":"MX",
    "name:spa_x_preferred":[
        "El Cuajilote"
    ],
    "wof:name":"El Cuajilote",
    "wof:placetype":"locality",
    "wof:population":25
},
  "geometry": {"coordinates":[-96.90582999999999,16.82278],"type":"Point"}
}