{
  "type": "Feature",
  "properties": {
    "gn:admin1_code":"4",
    "gn:admin2_code":"6.0",
    "gn:asciiname":"Yaxche Akal",
    "gn:country_code":"MX",
    "gn:dem":105,
    "gn:feature_class":"P",
    "gn:feature_code":"PPL",
    "gn:name":"Yaxch\u00e9 Akal",
    "gn:population":140,
    "gn:timezone":"America/Merida",
    "iso:country":"MX",
    "wof:name":"Yaxche Akal",
    "wof:placetype":"locality",
    "wof:population":140
},
  "geometry": {"coordinates":[-89.70444000000001,19.81778],"type":"Point"}
}