{
  "type": "Feature",
  "properties": {
    "gn:admin1_code":"13",
    "gn:admin2_code":"20",
    "gn:asciiname":"Patoloya",
    "gn:country_code":"MX",
    "gn:dem":1131,
    "gn:feature_class":"P",
    "gn:feature_code":"PPL",
    "gn:name":"Patoloya",
    "gn:population":9,
    "gn:timezone":"America/Mexico_City",
    "iso:country":"MX",
    "wof:name":"Patoloya",
    "wof:placetype":"locality",
    "wof:population":9
},
  "geometry": {"coordinates":[-98.95744000000001,20.72539],"type":"Point"}
}