{
  "type": "Feature",
  "properties": {
    "gn:admin1_code":"28.0",
    "gn:admin2_code":"3.0",
    "gn:asciiname":"El Sacrificio",
    "gn:country_code":"MX",
    "gn:dem":51,
    "gn:feature_class":"P",
    "gn:feature_code":"PPL",
    "gn:name":"El Sacrificio",
    "gn:population":0,
    "gn:timezone":"America/Monterrey",
    "iso:country":"MX",
    "name:spa_x_preferred":[
        "El Sacrificio"
    ],
    "name:spa_x_variant":[
        "El Chupido"
    ],
    "wof:name":"El Sacrificio",
    "wof:placetype":"locality"
},
  "geometry": {"coordinates":[-98.06986000000001,22.52567],"type":"Point"}
}