{
  "type": "Feature",
  "properties": {
    "gn:admin1_code":"26",
    "gn:admin2_code":"25.0",
    "gn:asciiname":"Vicente Guerrero",
    "gn:country_code":"MX",
    "gn:dem":53,
    "gn:feature_class":"P",
    "gn:feature_code":"PPL",
    "gn:name":"Vicente Guerrero",
    "gn:population":7,
    "gn:timezone":"America/Hermosillo",
    "iso:country":"MX",
    "wof:name":"Vicente Guerrero",
    "wof:placetype":"locality",
    "wof:population":7
},
  "geometry": {"coordinates":[-110.51611,28.02917],"type":"Point"}
}