{
  "type": "Feature",
  "properties": {
    "gn:admin1_code":"32.0",
    "gn:admin2_code":"52.0",
    "gn:asciiname":"Canoas",
    "gn:country_code":"MX",
    "gn:dem":2377,
    "gn:feature_class":"P",
    "gn:feature_code":"PPL",
    "gn:name":"Canoas",
    "gn:population":0,
    "gn:timezone":"America/Mexico_City",
    "iso:country":"MX",
    "name:spa_x_preferred":[
        "Canoas"
    ],
    "wof:name":"Canoas",
    "wof:placetype":"locality"
},
  "geometry": {"coordinates":[-101.8802,22.17718],"type":"Point"}
}