{
  "type": "Feature",
  "properties": {
    "gn:admin1_code":"30",
    "gn:admin2_code":"91",
    "gn:asciiname":"San Javier",
    "gn:country_code":"MX",
    "gn:dem":67,
    "gn:feature_class":"P",
    "gn:feature_code":"PPL",
    "gn:name":"San Javier",
    "gn:population":10,
    "gn:timezone":"America/Mexico_City",
    "iso:country":"MX",
    "name:ceb_x_preferred":[
        "San Javier"
    ],
    "name:deu_x_preferred":[
        "San Javier"
    ],
    "name:fra_x_preferred":[
        "San Javier"
    ],
    "name:ita_x_preferred":[
        "San Javier"
    ],
    "name:mlg_x_preferred":[
        "San Javier"
    ],
    "name:nld_x_preferred":[
        "San Javier"
    ],
    "name:pol_x_preferred":[
        "San Javier"
    ],
    "name:por_x_preferred":[
        "San Javier"
    ],
    "name:ron_x_preferred":[
        "San Javier"
    ],
    "name:rus_x_preferred":[
        "\u0421\u0430\u043d-\u0425\u0430\u0432\u044c\u0435\u0440"
    ],
    "name:sco_x_preferred":[
        "San Javier"
    ],
    "name:spa_x_preferred":[
        "San Javier"
    ],
    "name:swe_x_preferred":[
        "San Javier"
    ],
    "wof:name":"San Javier",
    "wof:placetype":"locality",
    "wof:population":10
},
  "geometry": {"coordinates":[-95.09556000000001,17.53111],"type":"Point"}
}