{
  "type": "Feature",
  "properties": {
    "gn:admin1_code":"32.0",
    "gn:admin2_code":"47.0",
    "gn:asciiname":"El Jongo",
    "gn:country_code":"MX",
    "gn:dem":1933,
    "gn:feature_class":"P",
    "gn:feature_code":"PPL",
    "gn:name":"El Jongo",
    "gn:population":0,
    "gn:timezone":"America/Mexico_City",
    "iso:country":"MX",
    "name:spa_x_preferred":[
        "El Jongo"
    ],
    "wof:name":"El Jongo",
    "wof:placetype":"locality"
},
  "geometry": {"coordinates":[-103.68523999999999,21.31165],"type":"Point"}
}