{
  "type": "Feature",
  "properties": {
    "iso:country":"MX",
    "name:spa_x_preferred":[
        "Nicte - Ha"
    ],
    "qs:gn_adm0_cc":"MX",
    "qs:gn_local":3521342,
    "qs:gn_nam_loc":"playa del carmen",
    "qs:gn_namadm1":"23",
    "qs:local_max":10960,
    "qs:local_sum":28603,
    "qs:localhoods":9,
    "qs:name":"Nicte - Ha",
    "qs:name_adm0":"M\u00e9xico",
    "qs:name_adm1":"Quintana Roo",
    "qs:name_adm2":"Solidaridad",
    "qs:name_local":"Playa del Carmen",
    "qs:photo_max":796,
    "qs:photo_sum":2262,
    "qs:placetype":"Suburb",
    "qs:quad_count":37,
    "qs:woe_adm0":23424900,
    "qs:woe_adm1":2346286,
    "qs:woe_adm2":24550675,
    "qs:woe_lau":0,
    "qs:woe_local":136973,
    "qs:woe_ver":"7.10.0",
    "wof:lang":[
        "spa"
    ],
    "wof:name":"Nicte - Ha",
    "wof:placetype":"neighbourhood"
},
  "geometry": {"coordinates":[-87.037753,20.662113],"type":"Point"}
}