{
  "type": "Feature",
  "properties": {
    "gn:admin1_code":"15",
    "gn:admin2_code":"82.0",
    "gn:asciiname":"Jumiltepec",
    "gn:country_code":"MX",
    "gn:dem":1664,
    "gn:feature_class":"P",
    "gn:feature_code":"PPL",
    "gn:name":"Jumiltepec",
    "gn:population":292,
    "gn:timezone":"America/Mexico_City",
    "iso:country":"MX",
    "wof:name":"Jumiltepec",
    "wof:placetype":"locality",
    "wof:population":292
},
  "geometry": {"coordinates":[-100.18521,18.92899],"type":"Point"}
}