{
  "type": "Feature",
  "properties": {
    "gn:admin1_code":"25.0",
    "gn:admin2_code":"6.0",
    "gn:asciiname":"La Presa Jaus",
    "gn:country_code":"MX",
    "gn:dem":106,
    "gn:feature_class":"P",
    "gn:feature_code":"PPL",
    "gn:name":"La Presa Jaus",
    "gn:population":0,
    "gn:timezone":"America/Mazatlan",
    "iso:country":"MX",
    "name:spa_x_preferred":[
        "La Presa Jaus"
    ],
    "wof:name":"La Presa Jaus",
    "wof:placetype":"locality"
},
  "geometry": {"coordinates":[-107.42195,25.0593],"type":"Point"}
}