{
  "type": "Feature",
  "properties": {
    "gn:admin1_code":"32.0",
    "gn:admin2_code":"47.0",
    "gn:asciiname":"Los Yerbanises",
    "gn:country_code":"MX",
    "gn:dem":1705,
    "gn:feature_class":"P",
    "gn:feature_code":"PPL",
    "gn:name":"Los Yerbanises",
    "gn:population":0,
    "gn:timezone":"America/Mexico_City",
    "iso:country":"MX",
    "name:spa_x_preferred":[
        "Los Yerbanises"
    ],
    "wof:name":"Los Yerbanises",
    "wof:placetype":"locality"
},
  "geometry": {"coordinates":[-103.71324,21.285],"type":"Point"}
}