{
  "type": "Feature",
  "properties": {
    "gn:admin1_code":"26.0",
    "gn:admin2_code":"17.0",
    "gn:asciiname":"Ejido Fronteras",
    "gn:country_code":"MX",
    "gn:dem":238,
    "gn:feature_class":"P",
    "gn:feature_code":"PPL",
    "gn:name":"Ejido Fronteras",
    "gn:population":0,
    "gn:timezone":"America/Hermosillo",
    "iso:country":"MX",
    "name:spa_x_preferred":[
        "Ejido Fronteras"
    ],
    "wof:name":"Ejido Fronteras",
    "wof:placetype":"locality"
},
  "geometry": {"coordinates":[-112.25787,30.65839],"type":"Point"}
}