{
  "type": "Feature",
  "properties": {
    "gn:admin1_code":"5",
    "gn:admin2_code":"59.0",
    "gn:asciiname":"Rosario la Pacaya",
    "gn:country_code":"MX",
    "gn:dem":1047,
    "gn:feature_class":"P",
    "gn:feature_code":"PPL",
    "gn:name":"Rosario la Pacaya",
    "gn:population":258,
    "gn:timezone":"America/Mexico_City",
    "iso:country":"MX",
    "wof:name":"Rosario la Pacaya",
    "wof:placetype":"locality",
    "wof:population":258
},
  "geometry": {"coordinates":[-91.63249999999999,16.71806],"type":"Point"}
}