{
  "type": "Feature",
  "properties": {
    "gn:admin1_code":"3",
    "gn:admin2_code":"8.0",
    "gn:asciiname":"Agua Hedionda",
    "gn:country_code":"MX",
    "gn:dem":369,
    "gn:feature_class":"P",
    "gn:feature_code":"PPL",
    "gn:name":"Agua Hedionda",
    "gn:population":0,
    "gn:timezone":"America/Mazatlan",
    "iso:country":"MX",
    "name:ceb_x_preferred":[
        "Agua Hedionda"
    ],
    "name:spa_x_preferred":[
        "Agua Hedionda"
    ],
    "name:swe_x_preferred":[
        "Agua Hedionda"
    ],
    "wof:name":"Agua Hedionda",
    "wof:placetype":"locality"
},
  "geometry": {"coordinates":[-109.79682,23.0856],"type":"Point"}
}