{
  "type": "Feature",
  "properties": {
    "gn:admin1_code":"21",
    "gn:admin2_code":"195.0",
    "gn:asciiname":"Zacatianquixco",
    "gn:country_code":"MX",
    "gn:dem":2642,
    "gn:feature_class":"P",
    "gn:feature_code":"PPL",
    "gn:name":"Zacatianquixco",
    "gn:population":106,
    "gn:timezone":"America/Mexico_City",
    "iso:country":"MX",
    "wof:name":"Zacatianquixco",
    "wof:placetype":"locality",
    "wof:population":106
},
  "geometry": {"coordinates":[-97.24355,18.53185],"type":"Point"}
}