{
  "type": "Feature",
  "properties": {
    "gn:admin1_code":"7",
    "gn:admin2_code":"33.0",
    "gn:asciiname":"El Pinto",
    "gn:country_code":"MX",
    "gn:dem":846,
    "gn:feature_class":"P",
    "gn:feature_code":"PPL",
    "gn:name":"El Pinto",
    "gn:population":0,
    "gn:timezone":"America/Monterrey",
    "iso:country":"MX",
    "name:spa_x_preferred":[
        "El Pinto"
    ],
    "wof:name":"El Pinto",
    "wof:placetype":"locality"
},
  "geometry": {"coordinates":[-102.65472,26.31431],"type":"Point"}
}