{
  "type": "Feature",
  "properties": {
    "gn:admin1_code":"26",
    "gn:admin2_code":"29.0",
    "gn:asciiname":"Los Limones",
    "gn:country_code":"MX",
    "gn:dem":13,
    "gn:feature_class":"P",
    "gn:feature_code":"PPL",
    "gn:name":"Los Limones",
    "gn:population":44,
    "gn:timezone":"America/Hermosillo",
    "iso:country":"MX",
    "name:spa_x_preferred":[
        "Los Limones"
    ],
    "wof:name":"Los Limones",
    "wof:placetype":"locality",
    "wof:population":44
},
  "geometry": {"coordinates":[-110.33611000000001,27.59028],"type":"Point"}
}