{
  "type": "Feature",
  "properties": {
    "gn:admin1_code":"17",
    "gn:admin2_code":"17.0",
    "gn:asciiname":"Colonia la Providencia",
    "gn:country_code":"MX",
    "gn:dem":911,
    "gn:feature_class":"P",
    "gn:feature_code":"PPL",
    "gn:name":"Colonia la Providencia",
    "gn:population":84,
    "gn:timezone":"America/Mexico_City",
    "iso:country":"MX",
    "wof:name":"Colonia la Providencia",
    "wof:placetype":"locality",
    "wof:population":84
},
  "geometry": {"coordinates":[-99.30816,18.62595],"type":"Point"}
}