{
  "type": "Feature",
  "properties": {
    "gn:admin1_code":"30",
    "gn:admin2_code":"189",
    "gn:asciiname":"El Charro",
    "gn:country_code":"MX",
    "gn:dem":16,
    "gn:feature_class":"P",
    "gn:feature_code":"PPL",
    "gn:name":"El Charro",
    "gn:population":15,
    "gn:timezone":"America/Mexico_City",
    "iso:country":"MX",
    "wof:name":"El Charro",
    "wof:placetype":"locality",
    "wof:population":15
},
  "geometry": {"coordinates":[-97.43416999999999,20.9025],"type":"Point"}
}