{
  "type": "Feature",
  "properties": {
    "gn:admin1_code":"16",
    "gn:admin2_code":"38",
    "gn:asciiname":"La Parotita (Pitayo Manzo)",
    "gn:country_code":"MX",
    "gn:dem":201,
    "gn:feature_class":"P",
    "gn:feature_code":"PPL",
    "gn:name":"La Parotita (Pitayo Manzo)",
    "gn:population":33,
    "gn:timezone":"America/Mexico_City",
    "iso:country":"MX",
    "wof:name":"La Parotita (Pitayo Manzo)",
    "wof:placetype":"locality",
    "wof:population":33
},
  "geometry": {"coordinates":[-101.09361,18.51056],"type":"Point"}
}