{
  "type": "Feature",
  "properties": {
    "gn:admin1_code":"5",
    "gn:admin2_code":"30",
    "gn:asciiname":"Piedra Blanca",
    "gn:country_code":"MX",
    "gn:dem":593,
    "gn:feature_class":"P",
    "gn:feature_code":"PPL",
    "gn:name":"Piedra Blanca",
    "gn:population":11,
    "gn:timezone":"America/Mexico_City",
    "iso:country":"MX",
    "name:ceb_x_preferred":[
        "Piedra Blanca"
    ],
    "name:fra_x_preferred":[
        "Piedra Blanca"
    ],
    "name:ita_x_preferred":[
        "Piedra Blanca"
    ],
    "name:por_x_preferred":[
        "Piedra Blanca"
    ],
    "name:spa_x_preferred":[
        "Piedra Blanca"
    ],
    "name:zho_x_preferred":[
        "\u5f7c\u5fb7\u62c9\u5e03\u862d\u5361"
    ],
    "wof:name":"Piedra Blanca",
    "wof:placetype":"locality",
    "wof:population":11
},
  "geometry": {"coordinates":[-92.30972,15.80139],"type":"Point"}
}