{
  "type": "Feature",
  "properties": {
    "gn:admin1_code":"11",
    "gn:admin2_code":"27.0",
    "gn:asciiname":"Campo Sarabia",
    "gn:country_code":"MX",
    "gn:dem":1727,
    "gn:feature_class":"P",
    "gn:feature_code":"PPL",
    "gn:name":"Campo Sarabia",
    "gn:population":553,
    "gn:timezone":"America/Mexico_City",
    "iso:country":"MX",
    "wof:name":"Campo Sarabia",
    "wof:placetype":"locality",
    "wof:population":553
},
  "geometry": {"coordinates":[-101.06778,20.50194],"type":"Point"}
}