{
  "type": "Feature",
  "properties": {
    "gn:admin1_code":"20",
    "gn:admin2_code":"88.0",
    "gn:asciiname":"Villa Alta (San Cosme la Paz)",
    "gn:country_code":"MX",
    "gn:dem":1106,
    "gn:feature_class":"P",
    "gn:feature_code":"PPL",
    "gn:name":"Villa Alta (San Cosme la Paz)",
    "gn:population":118,
    "gn:timezone":"America/Mexico_City",
    "iso:country":"MX",
    "wof:name":"Villa Alta (San Cosme la Paz)",
    "wof:placetype":"locality",
    "wof:population":118
},
  "geometry": {"coordinates":[-97.76721999999999,16.88694],"type":"Point"}
}