{
  "type": "Feature",
  "properties": {
    "gn:admin1_code":"17",
    "gn:admin2_code":"9.0",
    "gn:asciiname":"Huertas de San Pedro",
    "gn:country_code":"MX",
    "gn:dem":2242,
    "gn:feature_class":"P",
    "gn:feature_code":"PPL",
    "gn:name":"Huertas de San Pedro",
    "gn:population":0,
    "gn:timezone":"America/Mexico_City",
    "iso:country":"MX",
    "name:spa_x_preferred":[
        "Huertas de San Pedro"
    ],
    "wof:name":"Huertas de San Pedro",
    "wof:placetype":"locality"
},
  "geometry": {"coordinates":[-99.26461,19.00665],"type":"Point"}
}