{
  "type": "Feature",
  "properties": {
    "gn:admin1_code":"17",
    "gn:admin2_code":"4",
    "gn:asciiname":"Colonia Ampliacion Norte",
    "gn:country_code":"MX",
    "gn:dem":1363,
    "gn:feature_class":"P",
    "gn:feature_code":"PPL",
    "gn:name":"Colonia Ampliaci\u00f3n Norte",
    "gn:population":52,
    "gn:timezone":"America/Mexico_City",
    "iso:country":"MX",
    "name:und_x_variant":[
        "Colonia Ampliaci\u00f3n Norte"
    ],
    "wof:name":"Colonia Ampliacion Norte",
    "wof:placetype":"locality",
    "wof:population":52
},
  "geometry": {"coordinates":[-98.99417,18.78222],"type":"Point"}
}