{
  "type": "Feature",
  "properties": {
    "gn:admin1_code":"16",
    "gn:admin2_code":"82",
    "gn:asciiname":"Huizachera",
    "gn:country_code":"MX",
    "gn:dem":1362,
    "gn:feature_class":"P",
    "gn:feature_code":"PPL",
    "gn:name":"Huizachera",
    "gn:population":36,
    "gn:timezone":"America/Mexico_City",
    "iso:country":"MX",
    "wof:name":"Huizachera",
    "wof:placetype":"locality",
    "wof:population":36
},
  "geometry": {"coordinates":[-101.34028000000001,19.19667],"type":"Point"}
}