{
  "type": "Feature",
  "properties": {
    "gn:admin1_code":"32",
    "gn:admin2_code":"56.0",
    "gn:asciiname":"Rancho el Canelo (Casa Blanca)",
    "gn:country_code":"MX",
    "gn:dem":2181,
    "gn:feature_class":"P",
    "gn:feature_code":"PPL",
    "gn:name":"Rancho el Canelo (Casa Blanca)",
    "gn:population":5,
    "gn:timezone":"America/Mexico_City",
    "iso:country":"MX",
    "wof:name":"Rancho el Canelo (Casa Blanca)",
    "wof:placetype":"locality",
    "wof:population":5
},
  "geometry": {"coordinates":[-102.72360999999999,22.68667],"type":"Point"}
}