{
  "type": "Feature",
  "properties": {
    "gn:admin1_code":"6",
    "gn:admin2_code":"10.0",
    "gn:asciiname":"Las Varas",
    "gn:country_code":"MX",
    "gn:dem":1599,
    "gn:feature_class":"P",
    "gn:feature_code":"PPL",
    "gn:name":"Las Varas",
    "gn:population":0,
    "gn:timezone":"America/Chihuahua",
    "iso:country":"MX",
    "name:ceb_x_preferred":[
        "Las Varas"
    ],
    "name:srp_x_preferred":[
        "\u041b\u0430\u0441 \u0412\u0430\u0440\u0430\u0441"
    ],
    "name:swe_x_preferred":[
        "Las Varas"
    ],
    "wof:name":"Las Varas",
    "wof:placetype":"locality"
},
  "geometry": {"coordinates":[-107.44229,29.74445],"type":"Point"}
}