{
  "type": "Feature",
  "properties": {
    "gn:admin1_code":"4",
    "gn:admin2_code":"7.0",
    "gn:asciiname":"Villa Rosa",
    "gn:country_code":"MX",
    "gn:dem":4,
    "gn:feature_class":"P",
    "gn:feature_code":"PPL",
    "gn:name":"Villa Rosa",
    "gn:population":4,
    "gn:timezone":"America/Merida",
    "iso:country":"MX",
    "wof:name":"Villa Rosa",
    "wof:placetype":"locality",
    "wof:population":4
},
  "geometry": {"coordinates":[-91.88194,18.04806],"type":"Point"}
}