{
  "type": "Feature",
  "properties": {
    "gn:admin1_code":"14",
    "gn:admin2_code":"53.0",
    "gn:asciiname":"San Jose del Potrero",
    "gn:country_code":"MX",
    "gn:dem":1869,
    "gn:feature_class":"P",
    "gn:feature_code":"PPL",
    "gn:name":"San Jos\u00e9 del Potrero",
    "gn:population":171,
    "gn:timezone":"America/Mexico_City",
    "iso:country":"MX",
    "name:und_x_variant":[
        "San Jos\u00e9 del Potrero"
    ],
    "wof:name":"San Jose del Potrero",
    "wof:placetype":"locality",
    "wof:population":171
},
  "geometry": {"coordinates":[-102.04694000000001,21.30889],"type":"Point"}
}