{
  "type": "Feature",
  "properties": {
    "gn:admin1_code":"6",
    "gn:admin2_code":"7.0",
    "gn:asciiname":"Satevo",
    "gn:country_code":"MX",
    "gn:dem":2379,
    "gn:feature_class":"P",
    "gn:feature_code":"PPL",
    "gn:name":"Satevo",
    "gn:population":0,
    "gn:timezone":"America/Chihuahua",
    "iso:country":"MX",
    "name:spa_x_preferred":[
        "Satevo"
    ],
    "name:und_x_variant":[
        "Satev\u00f3"
    ],
    "wof:name":"Satevo",
    "wof:placetype":"locality"
},
  "geometry": {"coordinates":[-106.69889999999999,26.7201],"type":"Point"}
}