{
  "type": "Feature",
  "properties": {
    "gn:admin1_code":"7",
    "gn:admin2_code":"24.0",
    "gn:asciiname":"Alamo de Paila",
    "gn:country_code":"MX",
    "gn:dem":1175,
    "gn:feature_class":"P",
    "gn:feature_code":"PPL",
    "gn:name":"Alamo de Paila",
    "gn:population":0,
    "gn:timezone":"America/Monterrey",
    "iso:country":"MX",
    "name:spa_x_preferred":[
        "Alamo de Paila"
    ],
    "name:und_x_variant":[
        "Rancho Vi\u00f1edos Alamo Paila"
    ],
    "wof:name":"Alamo de Paila",
    "wof:placetype":"locality"
},
  "geometry": {"coordinates":[-102.00342999999999,25.64742],"type":"Point"}
}