{
  "type": "Feature",
  "properties": {
    "gn:admin1_code":"18",
    "gn:admin2_code":"20.0",
    "gn:asciiname":"Colonia Nueva Galicia",
    "gn:country_code":"MX",
    "gn:dem":26,
    "gn:feature_class":"P",
    "gn:feature_code":"PPL",
    "gn:name":"Colonia Nueva Galicia",
    "gn:population":6,
    "gn:timezone":"America/Bahia_Banderas",
    "iso:country":"MX",
    "wof:name":"Colonia Nueva Galicia",
    "wof:placetype":"locality",
    "wof:population":6
},
  "geometry": {"coordinates":[-105.29555999999999,20.75667],"type":"Point"}
}