{
  "type": "Feature",
  "properties": {
    "gn:admin1_code":"30",
    "gn:admin2_code":"178",
    "gn:asciiname":"Las Canillas",
    "gn:country_code":"MX",
    "gn:dem":6,
    "gn:feature_class":"P",
    "gn:feature_code":"PPL",
    "gn:name":"Las Canillas",
    "gn:population":15,
    "gn:timezone":"America/Mexico_City",
    "iso:country":"MX",
    "wof:name":"Las Canillas",
    "wof:placetype":"locality",
    "wof:population":15
},
  "geometry": {"coordinates":[-95.60028,18.52111],"type":"Point"}
}