{
  "type": "Feature",
  "properties": {
    "gn:admin1_code":"32",
    "gn:admin2_code":"26.0",
    "gn:asciiname":"La Palmilla",
    "gn:country_code":"MX",
    "gn:dem":1601,
    "gn:feature_class":"P",
    "gn:feature_code":"PPL",
    "gn:name":"La Palmilla",
    "gn:population":0,
    "gn:timezone":"America/Mexico_City",
    "iso:country":"MX",
    "name:spa_x_preferred":[
        "La Palmilla"
    ],
    "name:urd_x_preferred":[
        "\u0644\u0627 \u067e\u0627\u0644\u0645\u06cc\u0644\u0627"
    ],
    "wof:name":"La Palmilla",
    "wof:placetype":"locality"
},
  "geometry": {"coordinates":[-102.29998000000001,24.51556],"type":"Point"}
}