{
  "type": "Feature",
  "properties": {
    "gn:admin1_code":"1",
    "gn:admin2_code":"7",
    "gn:asciiname":"El Durazno [Rancho]",
    "gn:country_code":"MX",
    "gn:dem":1928,
    "gn:feature_class":"P",
    "gn:feature_code":"PPL",
    "gn:name":"El Durazno [Rancho]",
    "gn:population":13,
    "gn:timezone":"America/Mexico_City",
    "iso:country":"MX",
    "wof:name":"El Durazno [Rancho]",
    "wof:placetype":"locality",
    "wof:population":13
},
  "geometry": {"coordinates":[-102.33889000000001,22.14556],"type":"Point"}
}