{
  "type": "Feature",
  "properties": {
    "gn:admin1_code":"6.0",
    "gn:admin2_code":"40.0",
    "gn:asciiname":"Los Llanitos",
    "gn:country_code":"MX",
    "gn:dem":1196,
    "gn:feature_class":"P",
    "gn:feature_code":"PPL",
    "gn:name":"Los Llanitos",
    "gn:population":0,
    "gn:timezone":"America/Chihuahua",
    "iso:country":"MX",
    "name:ita_x_preferred":[
        "Los Llanitos"
    ],
    "name:spa_x_preferred":[
        "Los Llanitos"
    ],
    "name:zho_x_preferred":[
        "\u6d1b\u65af\u5229\u4e9e\u5c3c\u6258\u65af"
    ],
    "wof:name":"Los Llanitos",
    "wof:placetype":"locality"
},
  "geometry": {"coordinates":[-108.49715999999999,28.93133],"type":"Point"}
}