{
  "type": "Feature",
  "properties": {
    "gn:admin1_code":"6",
    "gn:admin2_code":"7.0",
    "gn:asciiname":"Paraje Los Barbechos",
    "gn:country_code":"MX",
    "gn:dem":2118,
    "gn:feature_class":"P",
    "gn:feature_code":"PPL",
    "gn:name":"Paraje Los Barbechos",
    "gn:population":0,
    "gn:timezone":"America/Chihuahua",
    "iso:country":"MX",
    "name:spa_x_preferred":[
        "Paraje Los Barbechos"
    ],
    "wof:name":"Paraje Los Barbechos",
    "wof:placetype":"locality"
},
  "geometry": {"coordinates":[-106.85433,27.1972],"type":"Point"}
}