{
  "type": "Feature",
  "properties": {
    "gn:admin1_code":"4",
    "gn:admin2_code":"10.0",
    "gn:asciiname":"King-Kong",
    "gn:country_code":"MX",
    "gn:dem":205,
    "gn:feature_class":"P",
    "gn:feature_code":"PPL",
    "gn:name":"King-Kong",
    "gn:population":4,
    "gn:timezone":"America/Merida",
    "iso:country":"MX",
    "wof:name":"King-Kong",
    "wof:placetype":"locality",
    "wof:population":4
},
  "geometry": {"coordinates":[-89.62,18.52833],"type":"Point"}
}