{
  "type": "Feature",
  "properties": {
    "gn:admin1_code":"5.0",
    "gn:admin2_code":"81.0",
    "gn:asciiname":"Pensil",
    "gn:country_code":"MX",
    "gn:dem":939,
    "gn:feature_class":"P",
    "gn:feature_code":"PPL",
    "gn:name":"Pensil",
    "gn:population":0,
    "gn:timezone":"America/Mexico_City",
    "iso:country":"MX",
    "name:spa_x_preferred":[
        "Pensil"
    ],
    "wof:name":"Pensil",
    "wof:placetype":"locality"
},
  "geometry": {"coordinates":[-92.56715,17.15927000000001],"type":"Point"}
}