{
  "type": "Feature",
  "properties": {
    "gn:admin1_code":"31",
    "gn:admin2_code":"104.0",
    "gn:asciiname":"Popola",
    "gn:country_code":"MX",
    "gn:dem":21,
    "gn:feature_class":"P",
    "gn:feature_code":"PPL",
    "gn:name":"Popol\u00e1",
    "gn:population":0,
    "gn:timezone":"America/Merida",
    "iso:country":"MX",
    "name:spa_x_preferred":[
        "Popol\u00e1"
    ],
    "wof:name":"Popola",
    "wof:placetype":"locality"
},
  "geometry": {"coordinates":[-88.65097,20.59409],"type":"Point"}
}