{
  "type": "Feature",
  "properties": {
    "gn:admin1_code":"21",
    "gn:admin2_code":"48",
    "gn:asciiname":"Huixtla",
    "gn:country_code":"MX",
    "gn:dem":2392,
    "gn:feature_class":"P",
    "gn:feature_code":"PPL",
    "gn:name":"Huixtla",
    "gn:population":35,
    "gn:timezone":"America/Mexico_City",
    "iso:country":"MX",
    "wof:name":"Huixtla",
    "wof:placetype":"locality",
    "wof:population":35
},
  "geometry": {"coordinates":[-98.46576,19.19041],"type":"Point"}
}