{
  "type": "Feature",
  "properties": {
    "gn:admin1_code":"21",
    "gn:admin2_code":"48",
    "gn:asciiname":"Huixtla",
    "gn:country_code":"MX",
    "gn:dem":2392,
    "gn:feature_class":"P",
    "gn:feature_code":"PPL",
    "gn:name":"Huixtla",
    "gn:population":35,
    "gn:timezone":"America/Mexico_City",
    "iso:country":"MX",
    "name:ceb_x_preferred":[
        "Huixtla"
    ],
    "name:deu_x_preferred":[
        "Municipio Huixtla"
    ],
    "name:epo_x_preferred":[
        "Huixtla"
    ],
    "name:eus_x_preferred":[
        "Huixtla"
    ],
    "name:fra_x_preferred":[
        "Huixtla"
    ],
    "name:por_x_preferred":[
        "Huixtla"
    ],
    "name:rus_x_preferred":[
        "\u0423\u0438\u0441\u0442\u043b\u0430"
    ],
    "name:sco_x_preferred":[
        "Huixtla"
    ],
    "name:spa_x_preferred":[
        "Huixtla"
    ],
    "name:srp_x_preferred":[
        "\u041e\u043f\u0448\u0442\u0438\u043d\u0430 \u0423\u0438\u0441\u0442\u043b\u0430"
    ],
    "name:swe_x_preferred":[
        "Huixtla"
    ],
    "name:vie_x_preferred":[
        "Huixtla"
    ],
    "wof:name":"Huixtla",
    "wof:placetype":"locality",
    "wof:population":35
},
  "geometry": {"coordinates":[-98.46576,19.19041],"type":"Point"}
}