{
  "type": "Feature",
  "properties": {
    "gn:admin1_code":"6.0",
    "gn:admin2_code":"40.0",
    "gn:asciiname":"El Boruco",
    "gn:country_code":"MX",
    "gn:dem":1642,
    "gn:feature_class":"P",
    "gn:feature_code":"PPL",
    "gn:name":"El Boruco",
    "gn:population":0,
    "gn:timezone":"America/Chihuahua",
    "iso:country":"MX",
    "name:spa_x_preferred":[
        "El Boruco"
    ],
    "wof:name":"El Boruco",
    "wof:placetype":"locality"
},
  "geometry": {"coordinates":[-108.25502,29.05085],"type":"Point"}
}