{
  "type": "Feature",
  "properties": {
    "gn:admin1_code":"25",
    "gn:admin2_code":"3.0",
    "gn:asciiname":"San Luis Gonzaga",
    "gn:country_code":"MX",
    "gn:dem":1524,
    "gn:feature_class":"P",
    "gn:feature_code":"PPL",
    "gn:name":"San Luis Gonzaga",
    "gn:population":5,
    "gn:timezone":"America/Chihuahua",
    "iso:country":"MX",
    "wof:name":"San Luis Gonzaga",
    "wof:placetype":"locality",
    "wof:population":5
},
  "geometry": {"coordinates":[-107.07159,25.69899],"type":"Point"}
}