{
  "type": "Feature",
  "properties": {
    "gn:admin1_code":"20",
    "gn:admin2_code":"12",
    "gn:asciiname":"Manga del Surco (Los Garcia)",
    "gn:country_code":"MX",
    "gn:dem":484,
    "gn:feature_class":"P",
    "gn:feature_code":"PPL",
    "gn:name":"Manga del Surco (Los Garc\u00eda)",
    "gn:population":17,
    "gn:timezone":"America/Mexico_City",
    "iso:country":"MX",
    "name:und_x_variant":[
        "Manga del Surco (Los Garc\u00eda)"
    ],
    "wof:name":"Manga del Surco (Los Garcia)",
    "wof:placetype":"locality",
    "wof:population":17
},
  "geometry": {"coordinates":[-96.49833,15.91972],"type":"Point"}
}