{
  "type": "Feature",
  "properties": {
    "gn:admin1_code":"9",
    "gn:admin2_code":"9",
    "gn:asciiname":"Huacaltunco",
    "gn:country_code":"MX",
    "gn:dem":2521,
    "gn:feature_class":"P",
    "gn:feature_code":"PPL",
    "gn:name":"Huacaltunco",
    "gn:population":22,
    "gn:timezone":"America/Mexico_City",
    "iso:country":"MX",
    "wof:name":"Huacaltunco",
    "wof:placetype":"locality",
    "wof:population":22
},
  "geometry": {"coordinates":[-99.00360999999999,19.18278],"type":"Point"}
}