{
  "type": "Feature",
  "properties": {
    "gn:admin1_code":"13",
    "gn:admin2_code":"54",
    "gn:asciiname":"Ejido Santa Teresa (El Tablon)",
    "gn:country_code":"MX",
    "gn:dem":2010,
    "gn:feature_class":"P",
    "gn:feature_code":"PPL",
    "gn:name":"Ejido Santa Teresa (El Tabl\u00f3n)",
    "gn:population":36,
    "gn:timezone":"America/Mexico_City",
    "iso:country":"MX",
    "name:und_x_variant":[
        "Ejido Santa Teresa (El Tabl\u00f3n)"
    ],
    "wof:name":"Ejido Santa Teresa (El Tablon)",
    "wof:placetype":"locality",
    "wof:population":36
},
  "geometry": {"coordinates":[-98.98083,20.33139],"type":"Point"}
}