{
  "type": "Feature",
  "properties": {
    "gn:admin1_code":"14.0",
    "gn:asciiname":"Apanico",
    "gn:country_code":"MX",
    "gn:dem":941,
    "gn:feature_class":"P",
    "gn:feature_code":"PPL",
    "gn:name":"Ap\u00e1nico",
    "gn:population":0,
    "gn:timezone":"America/Mexico_City",
    "iso:country":"MX",
    "name:spa_x_preferred":[
        "Ap\u00e1nico"
    ],
    "wof:name":"Apanico",
    "wof:placetype":"locality"
},
  "geometry": {"coordinates":[-103.93385000000001,21.27402],"type":"Point"}
}