{
  "type": "Feature",
  "properties": {
    "gn:admin1_code":"21",
    "gn:admin2_code":"43.0",
    "gn:asciiname":"Las Vigas",
    "gn:country_code":"MX",
    "gn:dem":1454,
    "gn:feature_class":"P",
    "gn:feature_code":"PPL",
    "gn:name":"Las Vigas",
    "gn:population":86,
    "gn:timezone":"America/Mexico_City",
    "iso:country":"MX",
    "wof:name":"Las Vigas",
    "wof:placetype":"locality",
    "wof:population":86
},
  "geometry": {"coordinates":[-97.55025999999999,19.98225],"type":"Point"}
}