{
  "type": "Feature",
  "properties": {
    "gn:admin1_code":"12.0",
    "gn:admin2_code":"21.0",
    "gn:asciiname":"Boca de Mitla",
    "gn:country_code":"MX",
    "gn:dem":10,
    "gn:feature_class":"P",
    "gn:feature_code":"PPL",
    "gn:name":"Boca de Mitla",
    "gn:population":0,
    "gn:timezone":"America/Mexico_City",
    "iso:country":"MX",
    "name:spa_x_preferred":[
        "Boca de Mitla"
    ],
    "wof:name":"Boca de Mitla",
    "wof:placetype":"locality"
},
  "geometry": {"coordinates":[-100.20125,16.98645],"type":"Point"}
}