{
  "type": "Feature",
  "properties": {
    "gn:admin1_code":"30.0",
    "gn:asciiname":"La Rucia",
    "gn:country_code":"MX",
    "gn:dem":42,
    "gn:feature_class":"P",
    "gn:feature_code":"PPL",
    "gn:name":"La Rucia",
    "gn:population":0,
    "gn:timezone":"America/Mexico_City",
    "iso:country":"MX",
    "name:spa_x_preferred":[
        "La Rucia"
    ],
    "wof:name":"La Rucia",
    "wof:placetype":"locality"
},
  "geometry": {"coordinates":[-97.95484999999999,21.88162],"type":"Point"}
}