{
  "type": "Feature",
  "properties": {
    "gn:admin1_code":"17",
    "gn:asciiname":"Granja Anzu Tlazintla",
    "gn:country_code":"MX",
    "gn:dem":2251,
    "gn:feature_class":"P",
    "gn:feature_code":"PPL",
    "gn:name":"Granja Anzu Tlazintla",
    "gn:population":0,
    "gn:timezone":"America/Mexico_City",
    "iso:country":"MX",
    "name:spa_x_preferred":[
        "Granja Anzu Tlazintla"
    ],
    "wof:name":"Granja Anzu Tlazintla",
    "wof:placetype":"locality"
},
  "geometry": {"coordinates":[-98.97069,19.72507],"type":"Point"}
}