{
  "type": "Feature",
  "properties": {
    "gn:admin1_code":"6",
    "gn:admin2_code":"9.0",
    "gn:asciiname":"Orasabichic",
    "gn:country_code":"MX",
    "gn:dem":2364,
    "gn:feature_class":"P",
    "gn:feature_code":"PPL",
    "gn:name":"Orasabichic",
    "gn:population":0,
    "gn:timezone":"America/Chihuahua",
    "iso:country":"MX",
    "wof:name":"Orasabichic",
    "wof:placetype":"locality"
},
  "geometry": {"coordinates":[-107.26667,27.71667],"type":"Point"}
}