{
  "type": "Feature",
  "properties": {
    "gn:admin1_code":"21",
    "gn:admin2_code":"69.0",
    "gn:asciiname":"San Antonio Cuautla",
    "gn:country_code":"MX",
    "gn:dem":1698,
    "gn:feature_class":"P",
    "gn:feature_code":"PPL",
    "gn:name":"San Antonio Cuautla",
    "gn:population":227,
    "gn:timezone":"America/Mexico_City",
    "iso:country":"MX",
    "wof:name":"San Antonio Cuautla",
    "wof:placetype":"locality",
    "wof:population":227
},
  "geometry": {"coordinates":[-98.55444,18.805],"type":"Point"}
}