{
  "type": "Feature",
  "properties": {
    "gn:admin1_code":"18.0",
    "gn:admin2_code":"9.0",
    "gn:asciiname":"El Cordon",
    "gn:country_code":"MX",
    "gn:dem":942,
    "gn:feature_class":"P",
    "gn:feature_code":"PPL",
    "gn:name":"El Cord\u00f3n",
    "gn:population":0,
    "gn:timezone":"America/Mazatlan",
    "iso:country":"MX",
    "wof:name":"El Cordon",
    "wof:placetype":"locality"
},
  "geometry": {"coordinates":[-104.80146000000001,21.86727],"type":"Point"}
}