{
  "type": "Feature",
  "properties": {
    "gn:admin1_code":"15",
    "gn:admin2_code":"110.0",
    "gn:asciiname":"Escalerillas",
    "gn:country_code":"MX",
    "gn:dem":2044,
    "gn:feature_class":"P",
    "gn:feature_code":"PPL",
    "gn:name":"Escalerillas",
    "gn:population":141,
    "gn:timezone":"America/Mexico_City",
    "iso:country":"MX",
    "wof:name":"Escalerillas",
    "wof:placetype":"locality",
    "wof:population":141
},
  "geometry": {"coordinates":[-100.11591,19.14188],"type":"Point"}
}