{
  "type": "Feature",
  "properties": {
    "gn:admin1_code":"10",
    "gn:admin2_code":"13.0",
    "gn:asciiname":"Chihuahuita",
    "gn:country_code":"MX",
    "gn:dem":1170,
    "gn:feature_class":"P",
    "gn:feature_code":"PPL",
    "gn:name":"Chihuahuita",
    "gn:population":0,
    "gn:timezone":"America/Monterrey",
    "iso:country":"MX",
    "name:spa_x_preferred":[
        "Chihuahuita"
    ],
    "wof:name":"Chihuahuita",
    "wof:placetype":"locality"
},
  "geometry": {"coordinates":[-103.99253,26.28663],"type":"Point"}
}