{
  "type": "Feature",
  "properties": {
    "gn:admin1_code":"13",
    "gn:admin2_code":"11.0",
    "gn:asciiname":"Cuatapo",
    "gn:country_code":"MX",
    "gn:dem":375,
    "gn:feature_class":"P",
    "gn:feature_code":"PPL",
    "gn:name":"Cuatapo",
    "gn:population":0,
    "gn:timezone":"America/Mexico_City",
    "iso:country":"MX",
    "name:spa_x_preferred":[
        "Cuatapo"
    ],
    "name:und_x_variant":[
        "Coatapa",
        "Cuatapa"
    ],
    "wof:name":"Cuatapo",
    "wof:placetype":"locality"
},
  "geometry": {"coordinates":[-98.37475999999999,21.07325],"type":"Point"}
}