{
  "type": "Feature",
  "properties": {
    "gn:admin1_code":"30.0",
    "gn:admin2_code":"123.0",
    "gn:asciiname":"Paso Potrero",
    "gn:country_code":"MX",
    "gn:dem":13,
    "gn:feature_class":"P",
    "gn:feature_code":"PPL",
    "gn:name":"Paso Potrero",
    "gn:population":134,
    "gn:timezone":"America/Mexico_City",
    "iso:country":"MX",
    "name:spa_x_preferred":[
        "Paso Potrero"
    ],
    "wof:name":"Paso Potrero",
    "wof:placetype":"locality",
    "wof:population":134
},
  "geometry": {"coordinates":[-98.11139,22.04472],"type":"Point"}
}