{
  "type": "Feature",
  "properties": {
    "gn:admin1_code":"30.0",
    "gn:admin2_code":"123.0",
    "gn:asciiname":"El Infierno",
    "gn:country_code":"MX",
    "gn:dem":16,
    "gn:feature_class":"P",
    "gn:feature_code":"PPL",
    "gn:name":"El Infierno",
    "gn:population":5,
    "gn:timezone":"America/Mexico_City",
    "iso:country":"MX",
    "name:spa_x_preferred":[
        "El Infierno"
    ],
    "wof:name":"El Infierno",
    "wof:placetype":"locality",
    "wof:population":5
},
  "geometry": {"coordinates":[-98.36389,22.00222],"type":"Point"}
}