{
  "type": "Feature",
  "properties": {
    "gn:admin1_code":"10",
    "gn:admin2_code":"30.0",
    "gn:asciiname":"Terreritos",
    "gn:country_code":"MX",
    "gn:dem":1879,
    "gn:feature_class":"P",
    "gn:feature_code":"PPL",
    "gn:name":"Terreritos",
    "gn:population":0,
    "gn:timezone":"America/Monterrey",
    "iso:country":"MX",
    "name:spa_x_preferred":[
        "Terreritos"
    ],
    "wof:name":"Terreritos",
    "wof:placetype":"locality"
},
  "geometry": {"coordinates":[-104.58132000000001,25.62373],"type":"Point"}
}