{
  "type": "Feature",
  "properties": {
    "gn:admin1_code":"30",
    "gn:admin2_code":"27",
    "gn:asciiname":"Acxitla",
    "gn:country_code":"MX",
    "gn:dem":573,
    "gn:feature_class":"P",
    "gn:feature_code":"PPL",
    "gn:name":"Acxitla",
    "gn:population":38,
    "gn:timezone":"America/Mexico_City",
    "iso:country":"MX",
    "wof:name":"Acxitla",
    "wof:placetype":"locality",
    "wof:population":38
},
  "geometry": {"coordinates":[-98.23139,20.85611],"type":"Point"}
}