{
  "type": "Feature",
  "properties": {
    "gn:admin1_code":"15.0",
    "gn:admin2_code":"80.0",
    "gn:asciiname":"Santa Cruz Texcalapa",
    "gn:country_code":"MX",
    "gn:dem":1517,
    "gn:feature_class":"P",
    "gn:feature_code":"PPL",
    "gn:name":"Santa Cruz Texcalapa",
    "gn:population":0,
    "gn:timezone":"America/Mexico_City",
    "iso:country":"MX",
    "name:spa_x_preferred":[
        "Santa Cruz Texcalapa"
    ],
    "wof:name":"Santa Cruz Texcalapa",
    "wof:placetype":"locality"
},
  "geometry": {"coordinates":[-100.0153,18.82783],"type":"Point"}
}