{
  "type": "Feature",
  "properties": {
    "gn:admin1_code":"11.0",
    "gn:admin2_code":"2.0",
    "gn:asciiname":"Pantaleon",
    "gn:country_code":"MX",
    "gn:dem":1982,
    "gn:feature_class":"P",
    "gn:feature_code":"PPL",
    "gn:name":"Pantale\u00f3n",
    "gn:population":0,
    "gn:timezone":"America/Mexico_City",
    "iso:country":"MX",
    "name:spa_x_preferred":[
        "Pantale\u00f3n"
    ],
    "wof:name":"Pantaleon",
    "wof:placetype":"locality"
},
  "geometry": {"coordinates":[-100.79528999999999,19.9899],"type":"Point"}
}