{
  "type": "Feature",
  "properties": {
    "gn:admin1_code":"21",
    "gn:admin2_code":"36.0",
    "gn:asciiname":"San Pedro Tepeyac",
    "gn:country_code":"MX",
    "gn:dem":2541,
    "gn:feature_class":"P",
    "gn:feature_code":"PPL",
    "gn:name":"San Pedro Tepeyac",
    "gn:population":109,
    "gn:timezone":"America/Mexico_City",
    "iso:country":"MX",
    "wof:name":"San Pedro Tepeyac",
    "wof:placetype":"locality",
    "wof:population":109
},
  "geometry": {"coordinates":[-96.95683,18.26681],"type":"Point"}
}