{
  "type": "Feature",
  "properties": {
    "gn:admin1_code":"5",
    "gn:admin2_code":"97",
    "gn:asciiname":"Costa Rica",
    "gn:country_code":"MX",
    "gn:dem":574,
    "gn:feature_class":"P",
    "gn:feature_code":"PPL",
    "gn:name":"Costa Rica",
    "gn:population":18,
    "gn:timezone":"America/Mexico_City",
    "iso:country":"MX",
    "wof:name":"Costa Rica",
    "wof:placetype":"locality",
    "wof:population":18
},
  "geometry": {"coordinates":[-93.63417,16.15194],"type":"Point"}
}