{
  "type": "Feature",
  "properties": {
    "gn:admin1_code":"13",
    "gn:admin2_code":"35.0",
    "gn:asciiname":"El Acocul",
    "gn:country_code":"MX",
    "gn:dem":2175,
    "gn:feature_class":"P",
    "gn:feature_code":"PPL",
    "gn:name":"El Acocul",
    "gn:population":0,
    "gn:timezone":"America/Mexico_City",
    "iso:country":"MX",
    "name:spa_x_preferred":[
        "El Acocul"
    ],
    "wof:name":"El Acocul",
    "wof:placetype":"locality"
},
  "geometry": {"coordinates":[-98.38565,20.22266],"type":"Point"}
}