{
  "type": "Feature",
  "properties": {
    "gn:admin1_code":"16",
    "gn:admin2_code":"13.0",
    "gn:asciiname":"Juntas del Anono (Juntas de la Torre)",
    "gn:country_code":"MX",
    "gn:dem":859,
    "gn:feature_class":"P",
    "gn:feature_code":"PPL",
    "gn:name":"Juntas del Anono (Juntas de la Torre)",
    "gn:population":5,
    "gn:timezone":"America/Mexico_City",
    "iso:country":"MX",
    "wof:name":"Juntas del Anono (Juntas de la Torre)",
    "wof:placetype":"locality",
    "wof:population":5
},
  "geometry": {"coordinates":[-101.04028,19.09972],"type":"Point"}
}