{
  "type": "Feature",
  "properties": {
    "gn:admin1_code":"24",
    "gn:admin2_code":"31",
    "gn:asciiname":"Mesa del Aguacate",
    "gn:country_code":"MX",
    "gn:dem":986,
    "gn:feature_class":"P",
    "gn:feature_code":"PPL",
    "gn:name":"Mesa del Aguacate",
    "gn:population":15,
    "gn:timezone":"America/Mexico_City",
    "iso:country":"MX",
    "wof:name":"Mesa del Aguacate",
    "wof:placetype":"locality",
    "wof:population":15
},
  "geometry": {"coordinates":[-99.51528,21.49],"type":"Point"}
}