{
  "type": "Feature",
  "properties": {
    "gn:country":"MX",
    "gn:fcode":"PPL",
    "gn:population":0,
    "iso:country":"MX",
    "name:ben_x_preferred":[
        "\u09b8\u09be\u09a8\u09cd\u09a4\u09be \u0987\u09b8\u09be\u09ac\u09c7\u09b2"
    ],
    "name:cat_x_preferred":[
        "Santa Isabel"
    ],
    "name:ceb_x_preferred":[
        "Santa Isabel"
    ],
    "name:deu_x_preferred":[
        "Santa Isabel"
    ],
    "name:ell_x_preferred":[
        "\u03a3\u03ac\u03bd\u03c4\u03b1 \u0399\u03b6\u03b1\u03bc\u03c0\u03ad\u03bb"
    ],
    "name:epo_x_preferred":[
        "Santa Isabel"
    ],
    "name:est_x_preferred":[
        "Santa Isabel"
    ],
    "name:fra_x_preferred":[
        "Santa Isabel"
    ],
    "name:glg_x_preferred":[
        "Santa Isabel"
    ],
    "name:heb_x_preferred":[
        "\u05d0\u05d9\u05d9 \u05e1\u05e0\u05d8\u05d4 \u05d0\u05d9\u05d6\u05d1\u05dc"
    ],
    "name:hin_x_preferred":[
        "\u0938\u0947\u0902\u091f\u093e \u0907\u0938\u093e\u092c\u0947\u0932"
    ],
    "name:hun_x_preferred":[
        "Santa Isabel"
    ],
    "name:ita_x_preferred":[
        "Santa Isabel"
    ],
    "name:lit_x_preferred":[
        "Santa Isabel\u0117"
    ],
    "name:mlg_x_preferred":[
        "Santa Isabel"
    ],
    "name:nld_x_preferred":[
        "Santa Isabel"
    ],
    "name:nor_x_preferred":[
        "Santa Isabel"
    ],
    "name:pol_x_preferred":[
        "Santa Isabel"
    ],
    "name:por_x_preferred":[
        "Santa Isabel"
    ],
    "name:rus_x_preferred":[
        "\u0421\u0430\u043d\u0442\u0430-\u0418\u0441\u0430\u0431\u0435\u043b\u044c"
    ],
    "name:sco_x_preferred":[
        "Santa Isabel"
    ],
    "name:slk_x_preferred":[
        "Santa Isabel"
    ],
    "name:spa_x_preferred":[
        "Santa Isabel"
    ],
    "name:srp_x_preferred":[
        "\u0421\u0430\u043d\u0442\u0430 \u0418\u0441\u0430\u0431\u0435\u043b"
    ],
    "name:swe_x_preferred":[
        "Santa Isabel"
    ],
    "name:tur_x_preferred":[
        "Santa Isabel"
    ],
    "name:ukr_x_preferred":[
        "\u0421\u0430\u043d\u0442\u0430-\u0406\u0437\u0430\u0431\u0435\u043b"
    ],
    "name:vol_x_preferred":[
        "Santa Isabel"
    ],
    "name:war_x_preferred":[
        "Santa Isabel"
    ],
    "qs_pg:aaroncc":"MX",
    "qs_pg:gn_country":"MX",
    "qs_pg:gn_fcode":"PPL",
    "qs_pg:gn_pop":0,
    "qs_pg:name":"Santa Isabel",
    "qs_pg:name_adm0":"M\u00e9xico",
    "qs_pg:name_adm1":"Nayarit",
    "qs_pg:photos_9k":1,
    "qs_pg:photos_9r":1,
    "qs_pg:photos_all":2,
    "qs_pg:photos_sr":0,
    "qs_pg:pop_sr":0,
    "qs_pg:qs_pg_placetype":"locality",
    "qs_pg:qs_pg_placetype_gp":"Town",
    "qs_pg:woe_adm0":23424900,
    "woe:adm0_id":23424900,
    "woe:name_adm0":"M\u00e9xico",
    "woe:name_adm1":"Nayarit",
    "woe:placetype":"Town",
    "wof:name":"Santa Isabel",
    "wof:placetype":"locality"
},
  "geometry": {"coordinates":[-104.62491,21.16306],"type":"Point"}
}