{
  "type": "Feature",
  "properties": {
    "gn:admin1_code":"20",
    "gn:admin2_code":"426.0",
    "gn:asciiname":"San Pedro Cholula",
    "gn:country_code":"MX",
    "gn:dem":2051,
    "gn:feature_class":"P",
    "gn:feature_code":"PPL",
    "gn:name":"San Pedro Cholula",
    "gn:population":0,
    "gn:timezone":"America/Mexico_City",
    "iso:country":"MX",
    "name:ceb_x_preferred":[
        "San Pedro Cholula"
    ],
    "name:epo_x_preferred":[
        "San Pedro Cholula"
    ],
    "name:eus_x_preferred":[
        "San Pedro Cholula"
    ],
    "name:fas_x_preferred":[
        "\u0633\u0646 \u067e\u062f\u0631\u0648 \u0686\u0648\u0644\u0648\u0644\u0627"
    ],
    "name:rus_x_preferred":[
        "\u0421\u0430\u043d-\u041f\u0435\u0434\u0440\u043e-\u0427\u043e\u043b\u0443\u043b\u0430"
    ],
    "name:spa_x_preferred":[
        "San Pedro Cholula"
    ],
    "name:srp_x_preferred":[
        "\u041e\u043f\u0448\u0442\u0438\u043d\u0430 \u0421\u0430\u043d \u041f\u0435\u0434\u0440\u043e \u0427\u043e\u043b\u0443\u043b\u0430"
    ],
    "name:swe_x_preferred":[
        "San Pedro Cholula"
    ],
    "name:und_x_variant":[
        "Cholula"
    ],
    "name:vie_x_preferred":[
        "San Pedro Cholula"
    ],
    "name:zho_x_preferred":[
        "\u8056\u4f69\u5fb7\u7f85\u55ac\u76e7\u62c9"
    ],
    "wof:name":"San Pedro Cholula",
    "wof:placetype":"locality"
},
  "geometry": {"coordinates":[-97.05215,17.03436],"type":"Point"}
}