{
  "type": "Feature",
  "properties": {
    "gn:admin1_code":"20",
    "gn:admin2_code":"426.0",
    "gn:asciiname":"San Pedro Cholula",
    "gn:country_code":"MX",
    "gn:dem":2051,
    "gn:feature_class":"P",
    "gn:feature_code":"PPL",
    "gn:name":"San Pedro Cholula",
    "gn:population":0,
    "gn:timezone":"America/Mexico_City",
    "iso:country":"MX",
    "name:spa_x_preferred":[
        "San Pedro Cholula"
    ],
    "name:und_x_variant":[
        "Cholula"
    ],
    "wof:name":"San Pedro Cholula",
    "wof:placetype":"locality"
},
  "geometry": {"coordinates":[-97.05215,17.03436],"type":"Point"}
}