{
  "type": "Feature",
  "properties": {
    "gn:admin1_code":"6",
    "gn:admin2_code":"65.0",
    "gn:asciiname":"Recomachi",
    "gn:country_code":"MX",
    "gn:dem":2014,
    "gn:feature_class":"P",
    "gn:feature_code":"PPL",
    "gn:name":"Rec\u00f3machi",
    "gn:population":0,
    "gn:timezone":"America/Chihuahua",
    "iso:country":"MX",
    "name:spa_x_preferred":[
        "Rec\u00f3machi"
    ],
    "wof:name":"Recomachi",
    "wof:placetype":"locality"
},
  "geometry": {"coordinates":[-107.72808000000001,27.37],"type":"Point"}
}