{
  "type": "Feature",
  "properties": {
    "gn:admin1_code":"28.0",
    "gn:admin2_code":"12.0",
    "gn:asciiname":"El Serrucho",
    "gn:country_code":"MX",
    "gn:dem":52,
    "gn:feature_class":"P",
    "gn:feature_code":"PPL",
    "gn:name":"El Serrucho",
    "gn:population":1,
    "gn:timezone":"America/Monterrey",
    "iso:country":"MX",
    "name:spa_x_preferred":[
        "El Serrucho"
    ],
    "wof:name":"El Serrucho",
    "wof:placetype":"locality",
    "wof:population":1
},
  "geometry": {"coordinates":[-98.69,22.7675],"type":"Point"}
}