{
  "type": "Feature",
  "properties": {
    "gn:admin1_code":"6",
    "gn:admin2_code":"63.0",
    "gn:asciiname":"Bacoseachic",
    "gn:country_code":"MX",
    "gn:dem":1868,
    "gn:feature_class":"P",
    "gn:feature_code":"PPL",
    "gn:name":"Bacoseachic",
    "gn:population":0,
    "gn:timezone":"America/Chihuahua",
    "iso:country":"MX",
    "name:spa_x_preferred":[
        "Bacoseachic"
    ],
    "wof:name":"Bacoseachic",
    "wof:placetype":"locality"
},
  "geometry": {"coordinates":[-108.29819000000001,28.56103],"type":"Point"}
}