{
  "type": "Feature",
  "properties": {
    "gn:admin1_code":"30",
    "gn:admin2_code":"116",
    "gn:asciiname":"Las Perlas",
    "gn:country_code":"MX",
    "gn:dem":93,
    "gn:feature_class":"P",
    "gn:feature_code":"PPL",
    "gn:name":"Las Perlas",
    "gn:population":10,
    "gn:timezone":"America/Mexico_City",
    "iso:country":"MX",
    "name:rus_x_preferred":[
        "\u041b\u0430\u0441-\u041f\u0435\u0440\u043b\u0430\u0441"
    ],
    "name:spa_x_preferred":[
        "Las Perlas"
    ],
    "name:urd_x_preferred":[
        "\u0644\u0627\u0633 \u067e\u06cc\u0631\u0644\u0627\u0633"
    ],
    "wof:name":"Las Perlas",
    "wof:placetype":"locality",
    "wof:population":10
},
  "geometry": {"coordinates":[-94.89,17.90611],"type":"Point"}
}