{
  "type": "Feature",
  "properties": {
    "gn:admin1_code":"5",
    "gn:admin2_code":"108",
    "gn:asciiname":"Lindavista",
    "gn:country_code":"MX",
    "gn:dem":661,
    "gn:feature_class":"P",
    "gn:feature_code":"PPL",
    "gn:name":"Lindavista",
    "gn:population":11,
    "gn:timezone":"America/Mexico_City",
    "iso:country":"MX",
    "wof:name":"Lindavista",
    "wof:placetype":"locality",
    "wof:population":11
},
  "geometry": {"coordinates":[-93.35527999999999,16.32611],"type":"Point"}
}