{
  "type": "Feature",
  "properties": {
    "gn:admin1_code":"13",
    "gn:admin2_code":"24.0",
    "gn:asciiname":"Santa Maria Regla",
    "gn:country_code":"MX",
    "gn:dem":1990,
    "gn:feature_class":"P",
    "gn:feature_code":"PPL",
    "gn:name":"Santa Mar\u00eda Regla",
    "gn:population":231,
    "gn:timezone":"America/Mexico_City",
    "iso:country":"MX",
    "name:spa_x_preferred":[
        "Santa Mar\u00eda Regla"
    ],
    "wof:name":"Santa Maria Regla",
    "wof:placetype":"locality",
    "wof:population":231
},
  "geometry": {"coordinates":[-98.56207000000001,20.239],"type":"Point"}
}