{
  "type": "Feature",
  "properties": {
    "gn:admin1_code":"7",
    "gn:admin2_code":"18.0",
    "gn:asciiname":"Posada del Sol",
    "gn:country_code":"MX",
    "gn:dem":692,
    "gn:feature_class":"P",
    "gn:feature_code":"PPL",
    "gn:name":"Posada del Sol",
    "gn:population":6,
    "gn:timezone":"America/Monterrey",
    "iso:country":"MX",
    "wof:name":"Posada del Sol",
    "wof:placetype":"locality",
    "wof:population":6
},
  "geometry": {"coordinates":[-101.37361,26.89889],"type":"Point"}
}