{
  "type": "Feature",
  "properties": {
    "gn:admin1_code":"11",
    "gn:admin2_code":"30.0",
    "gn:asciiname":"San Juan de Llanos",
    "gn:country_code":"MX",
    "gn:dem":2117,
    "gn:feature_class":"P",
    "gn:feature_code":"PPL",
    "gn:name":"San Juan de Llanos",
    "gn:population":0,
    "gn:timezone":"America/Mexico_City",
    "iso:country":"MX",
    "name:und_x_variant":[
        "San Juan del Llanos",
        "San Juan de los Llanos"
    ],
    "wof:name":"San Juan de Llanos",
    "wof:placetype":"locality"
},
  "geometry": {"coordinates":[-101.31565000000001,21.2779],"type":"Point"}
}