{
  "type": "Feature",
  "properties": {
    "gn:admin1_code":"3",
    "gn:admin2_code":"3.0",
    "gn:asciiname":"El Bethel",
    "gn:country_code":"MX",
    "gn:dem":36,
    "gn:feature_class":"P",
    "gn:feature_code":"PPL",
    "gn:name":"El Bethel",
    "gn:population":5,
    "gn:timezone":"America/Mazatlan",
    "iso:country":"MX",
    "wof:name":"El Bethel",
    "wof:placetype":"locality",
    "wof:population":5
},
  "geometry": {"coordinates":[-110.41356,24.06982],"type":"Point"}
}