{
  "type": "Feature",
  "properties": {
    "gn:admin1_code":"24.0",
    "gn:admin2_code":"42.0",
    "gn:asciiname":"Alto el Jobo",
    "gn:country_code":"MX",
    "gn:dem":72,
    "gn:feature_class":"P",
    "gn:feature_code":"PPL",
    "gn:name":"Alto el Jobo",
    "gn:population":1,
    "gn:timezone":"America/Mexico_City",
    "iso:country":"MX",
    "name:spa_x_preferred":[
        "Alto el Jobo"
    ],
    "wof:name":"Alto el Jobo",
    "wof:placetype":"locality",
    "wof:population":1
},
  "geometry": {"coordinates":[-98.63667,21.57333],"type":"Point"}
}