{
  "type": "Feature",
  "properties": {
    "gn:admin1_code":"16",
    "gn:admin2_code":"50.0",
    "gn:asciiname":"Cerro Azul",
    "gn:country_code":"MX",
    "gn:dem":2576,
    "gn:feature_class":"P",
    "gn:feature_code":"PPL",
    "gn:name":"Cerro Azul",
    "gn:population":75,
    "gn:timezone":"America/Mexico_City",
    "iso:country":"MX",
    "wof:name":"Cerro Azul",
    "wof:placetype":"locality",
    "wof:population":75
},
  "geometry": {"coordinates":[-100.51639,19.78333],"type":"Point"}
}