{
  "type": "Feature",
  "properties": {
    "gn:admin1_code":"16",
    "gn:admin2_code":"50.0",
    "gn:asciiname":"Cerro Azul",
    "gn:country_code":"MX",
    "gn:dem":2576,
    "gn:feature_class":"P",
    "gn:feature_code":"PPL",
    "gn:name":"Cerro Azul",
    "gn:population":75,
    "gn:timezone":"America/Mexico_City",
    "iso:country":"MX",
    "name:bpy_x_preferred":[
        "\u09b8\u09c7\u09b0\u09cd\u09b0\u09cb \u0986\u099c\u09c1\u09b2"
    ],
    "name:ceb_x_preferred":[
        "Cerro Azul"
    ],
    "name:ces_x_preferred":[
        "Cerro Azul"
    ],
    "name:deu_x_preferred":[
        "Cerro Azul"
    ],
    "name:est_x_preferred":[
        "Cerro Azul"
    ],
    "name:fra_x_preferred":[
        "Cerro Azul"
    ],
    "name:ita_x_preferred":[
        "Cerro Azul"
    ],
    "name:kor_x_preferred":[
        "\uc138\ub85c\uc544\uc904"
    ],
    "name:nld_x_preferred":[
        "Cerro Azul"
    ],
    "name:por_x_preferred":[
        "Cerro Azul"
    ],
    "name:rus_x_preferred":[
        "\u0421\u0435\u0440\u0440\u043e-\u0410\u0441\u0443\u043b\u044c"
    ],
    "name:sco_x_preferred":[
        "Cerro Azul"
    ],
    "name:slk_x_preferred":[
        "Cerro Azul"
    ],
    "name:spa_x_preferred":[
        "Cerro Azul"
    ],
    "name:swe_x_preferred":[
        "Cerro Azul"
    ],
    "name:vie_x_preferred":[
        "Cerro Azul"
    ],
    "wof:name":"Cerro Azul",
    "wof:placetype":"locality",
    "wof:population":75
},
  "geometry": {"coordinates":[-100.51639,19.78333],"type":"Point"}
}