{
  "type": "Feature",
  "properties": {
    "gn:admin1_code":"5",
    "gn:admin2_code":"43.0",
    "gn:asciiname":"Rio Blanco",
    "gn:country_code":"MX",
    "gn:dem":134,
    "gn:feature_class":"P",
    "gn:feature_code":"PPL",
    "gn:name":"R\u00edo Blanco",
    "gn:population":4,
    "gn:timezone":"America/Mexico_City",
    "iso:country":"MX",
    "name:und_x_variant":[
        "R\u00edo Blanco"
    ],
    "wof:name":"Rio Blanco",
    "wof:placetype":"locality",
    "wof:population":4
},
  "geometry": {"coordinates":[-93.10250000000001,17.42167],"type":"Point"}
}