{
  "type": "Feature",
  "properties": {
    "gn:admin1_code":"23",
    "gn:admin2_code":"5.0",
    "gn:asciiname":"Lagos del Sol",
    "gn:country_code":"MX",
    "gn:dem":10,
    "gn:feature_class":"P",
    "gn:feature_code":"PPL",
    "gn:name":"Lagos del Sol",
    "gn:population":156,
    "gn:timezone":"America/Cancun",
    "iso:country":"MX",
    "wof:name":"Lagos del Sol",
    "wof:placetype":"locality",
    "wof:population":156
},
  "geometry": {"coordinates":[-86.84860999999999,21.05417000000001],"type":"Point"}
}