{
  "type": "Feature",
  "properties": {
    "gn:admin1_code":"14.0",
    "gn:admin2_code":"61.0",
    "gn:asciiname":"Pueblo Celoso",
    "gn:country_code":"MX",
    "gn:dem":2109,
    "gn:feature_class":"P",
    "gn:feature_code":"PPL",
    "gn:name":"Pueblo Celoso",
    "gn:population":0,
    "gn:timezone":"America/Mexico_City",
    "iso:country":"MX",
    "name:spa_x_preferred":[
        "Pueblo Celoso"
    ],
    "wof:name":"Pueblo Celoso",
    "wof:placetype":"locality"
},
  "geometry": {"coordinates":[-104.06224,22.20817000000001],"type":"Point"}
}