{
  "type": "Feature",
  "properties": {
    "gn:admin1_code":"16.0",
    "gn:admin2_code":"73.0",
    "gn:asciiname":"Sanambo",
    "gn:country_code":"MX",
    "gn:dem":2488,
    "gn:feature_class":"P",
    "gn:feature_code":"PPL",
    "gn:name":"Sanambo",
    "gn:population":0,
    "gn:timezone":"America/Mexico_City",
    "iso:country":"MX",
    "name:spa_x_preferred":[
        "Sanambo"
    ],
    "wof:name":"Sanambo",
    "wof:placetype":"locality"
},
  "geometry": {"coordinates":[-101.45593,19.64576],"type":"Point"}
}