{
  "type": "Feature",
  "properties": {
    "gn:admin1_code":"30.0",
    "gn:admin2_code":"127.0",
    "gn:asciiname":"Macuilacatl Chico",
    "gn:country_code":"MX",
    "gn:dem":1969,
    "gn:feature_class":"P",
    "gn:feature_code":"PPL",
    "gn:name":"Macuilac\u00e1tl Chico",
    "gn:population":0,
    "gn:timezone":"America/Mexico_City",
    "iso:country":"MX",
    "name:spa_x_preferred":[
        "Macuilac\u00e1tl Chico"
    ],
    "wof:name":"Macuilacatl Chico",
    "wof:placetype":"locality"
},
  "geometry": {"coordinates":[-97.11814,18.94117],"type":"Point"}
}