{
  "type": "Feature",
  "properties": {
    "gn:admin1_code":"12",
    "gn:admin2_code":"43.0",
    "gn:asciiname":"Yuvinani",
    "gn:country_code":"MX",
    "gn:dem":2125,
    "gn:feature_class":"P",
    "gn:feature_code":"PPL",
    "gn:name":"Yuvinani",
    "gn:population":593,
    "gn:timezone":"America/Mexico_City",
    "iso:country":"MX",
    "wof:name":"Yuvinani",
    "wof:placetype":"locality",
    "wof:population":593
},
  "geometry": {"coordinates":[-98.39389,17.21306],"type":"Point"}
}