{
  "type": "Feature",
  "properties": {
    "gn:admin1_code":"26",
    "gn:admin2_code":"30.0",
    "gn:asciiname":"San Fernando (Nuevo Guadalupe)",
    "gn:country_code":"MX",
    "gn:dem":35,
    "gn:feature_class":"P",
    "gn:feature_code":"PPL",
    "gn:name":"San Fernando (Nuevo Guadalupe)",
    "gn:population":5,
    "gn:timezone":"America/Hermosillo",
    "iso:country":"MX",
    "wof:name":"San Fernando (Nuevo Guadalupe)",
    "wof:placetype":"locality",
    "wof:population":5
},
  "geometry": {"coordinates":[-111.41528,28.57694],"type":"Point"}
}