{
  "type": "Feature",
  "properties": {
    "gn:admin1_code":"11",
    "gn:admin2_code":"42",
    "gn:asciiname":"El Timbinal",
    "gn:country_code":"MX",
    "gn:dem":1897,
    "gn:feature_class":"P",
    "gn:feature_code":"PPL",
    "gn:name":"El Timbinal",
    "gn:population":13,
    "gn:timezone":"America/Mexico_City",
    "iso:country":"MX",
    "wof:name":"El Timbinal",
    "wof:placetype":"locality",
    "wof:population":13
},
  "geometry": {"coordinates":[-101.33056000000001,20.29639],"type":"Point"}
}