{
  "type": "Feature",
  "properties": {
    "gn:admin1_code":"24",
    "gn:admin2_code":"13",
    "gn:asciiname":"Campo Atonatilco",
    "gn:country_code":"MX",
    "gn:dem":85,
    "gn:feature_class":"P",
    "gn:feature_code":"PPL",
    "gn:name":"Campo Atonatilco",
    "gn:population":14,
    "gn:timezone":"America/Mexico_City",
    "iso:country":"MX",
    "wof:name":"Campo Atonatilco",
    "wof:placetype":"locality",
    "wof:population":14
},
  "geometry": {"coordinates":[-99.08083000000001,22.04778],"type":"Point"}
}