{
  "type": "Feature",
  "properties": {
    "gn:admin1_code":"14",
    "gn:admin2_code":"100",
    "gn:asciiname":"Crucero del Aval",
    "gn:country_code":"MX",
    "gn:dem":87,
    "gn:feature_class":"P",
    "gn:feature_code":"PPL",
    "gn:name":"Crucero del Aval",
    "gn:population":24,
    "gn:timezone":"America/Mexico_City",
    "iso:country":"MX",
    "wof:name":"Crucero del Aval",
    "wof:placetype":"locality",
    "wof:population":24
},
  "geometry": {"coordinates":[-105.30722,20.10361],"type":"Point"}
}