{
  "type": "Feature",
  "properties": {
    "gn:admin1_code":"6",
    "gn:admin2_code":"46.0",
    "gn:asciiname":"Aserradero Las Palomas",
    "gn:country_code":"MX",
    "gn:dem":2209,
    "gn:feature_class":"P",
    "gn:feature_code":"PPL",
    "gn:name":"Aserradero Las Palomas",
    "gn:population":0,
    "gn:timezone":"America/Chihuahua",
    "iso:country":"MX",
    "name:spa_x_preferred":[
        "Aserradero Las Palomas"
    ],
    "wof:name":"Aserradero Las Palomas",
    "wof:placetype":"locality"
},
  "geometry": {"coordinates":[-107.78749999999999,26.53551],"type":"Point"}
}