{
  "type": "Feature",
  "properties": {
    "gn:admin1_code":"14.0",
    "gn:admin2_code":"69.0",
    "gn:asciiname":"El Palo Dulce",
    "gn:country_code":"MX",
    "gn:dem":1478,
    "gn:feature_class":"P",
    "gn:feature_code":"PPL",
    "gn:name":"El Palo Dulce",
    "gn:population":0,
    "gn:timezone":"America/Mexico_City",
    "iso:country":"MX",
    "name:spa_x_preferred":[
        "El Palo Dulce"
    ],
    "wof:name":"El Palo Dulce",
    "wof:placetype":"locality"
},
  "geometry": {"coordinates":[-102.86019,19.7944],"type":"Point"}
}