{
  "type": "Feature",
  "properties": {
    "gn:admin1_code":"21",
    "gn:admin2_code":"36.0",
    "gn:asciiname":"Caxalli",
    "gn:country_code":"MX",
    "gn:dem":2509,
    "gn:feature_class":"P",
    "gn:feature_code":"PPL",
    "gn:name":"Caxalli",
    "gn:population":194,
    "gn:timezone":"America/Mexico_City",
    "iso:country":"MX",
    "wof:name":"Caxalli",
    "wof:placetype":"locality",
    "wof:population":194
},
  "geometry": {"coordinates":[-96.96775,18.28174],"type":"Point"}
}