{
  "type": "Feature",
  "properties": {
    "gn:admin1_code":"23.0",
    "gn:admin2_code":"4.0",
    "gn:asciiname":"El Crucero Miguel Hidalgo",
    "gn:country_code":"MX",
    "gn:dem":29,
    "gn:feature_class":"P",
    "gn:feature_code":"PPL",
    "gn:name":"El Crucero Miguel Hidalgo",
    "gn:population":0,
    "gn:timezone":"America/Cancun",
    "iso:country":"MX",
    "name:spa_x_preferred":[
        "El Crucero Miguel Hidalgo"
    ],
    "wof:name":"El Crucero Miguel Hidalgo",
    "wof:placetype":"locality"
},
  "geometry": {"coordinates":[-88.31748,18.7907],"type":"Point"}
}