{
  "type": "Feature",
  "properties": {
    "gn:admin1_code":"31",
    "gn:admin2_code":"81.0",
    "gn:asciiname":"Crucero",
    "gn:country_code":"MX",
    "gn:dem":23,
    "gn:feature_class":"P",
    "gn:feature_code":"PPL",
    "gn:name":"Crucero",
    "gn:population":0,
    "gn:timezone":"America/Merida",
    "iso:country":"MX",
    "name:ceb_x_preferred":[
        "Crucero"
    ],
    "name:fas_x_preferred":[
        "\u06a9\u0631\u0648\u062b\u0631\u0648"
    ],
    "name:swe_x_preferred":[
        "Crucero"
    ],
    "wof:name":"Crucero",
    "wof:placetype":"locality"
},
  "geometry": {"coordinates":[-88.33333,20.55],"type":"Point"}
}