{
  "type": "Feature",
  "properties": {
    "gn:admin1_code":"16",
    "gn:admin2_code":"102.0",
    "gn:asciiname":"Tzintzicataro (El Arenal)",
    "gn:country_code":"MX",
    "gn:dem":2233,
    "gn:feature_class":"P",
    "gn:feature_code":"PPL",
    "gn:name":"Tzintzic\u00e1taro (El Arenal)",
    "gn:population":8,
    "gn:timezone":"America/Mexico_City",
    "iso:country":"MX",
    "name:und_x_variant":[
        "Tzintzic\u00e1taro (El Arenal)"
    ],
    "wof:name":"Tzintzicataro (El Arenal)",
    "wof:placetype":"locality",
    "wof:population":8
},
  "geometry": {"coordinates":[-102.29443999999999,19.52139],"type":"Point"}
}