{
  "type": "Feature",
  "properties": {
    "gn:admin1_code":"7.0",
    "gn:admin2_code":"35.0",
    "gn:asciiname":"Los Milagros",
    "gn:country_code":"MX",
    "gn:dem":1264,
    "gn:feature_class":"P",
    "gn:feature_code":"PPL",
    "gn:name":"Los Milagros",
    "gn:population":0,
    "gn:timezone":"America/Monterrey",
    "iso:country":"MX",
    "name:ita_x_preferred":[
        "Los Milagros"
    ],
    "name:spa_x_preferred":[
        "Los Milagros"
    ],
    "name:zho_x_preferred":[
        "\u6d1b\u65af\u7c73\u62c9\u683c\u7f57\u65af"
    ],
    "wof:name":"Los Milagros",
    "wof:placetype":"locality"
},
  "geometry": {"coordinates":[-103.38388999999999,25.16553],"type":"Point"}
}