{
  "type": "Feature",
  "properties": {
    "gn:admin1_code":"11",
    "gn:admin2_code":"7",
    "gn:asciiname":"Lucero del Rio",
    "gn:country_code":"MX",
    "gn:dem":1754,
    "gn:feature_class":"P",
    "gn:feature_code":"PPL",
    "gn:name":"Lucero del R\u00edo",
    "gn:population":26,
    "gn:timezone":"America/Mexico_City",
    "iso:country":"MX",
    "name:und_x_variant":[
        "Lucero del R\u00edo"
    ],
    "wof:name":"Lucero del Rio",
    "wof:placetype":"locality",
    "wof:population":26
},
  "geometry": {"coordinates":[-100.78944,20.49583],"type":"Point"}
}