{
  "type": "Feature",
  "properties": {
    "gn:admin1_code":"14.0",
    "gn:admin2_code":"56.0",
    "gn:asciiname":"La Alegria",
    "gn:country_code":"MX",
    "gn:dem":573,
    "gn:feature_class":"P",
    "gn:feature_code":"PPL",
    "gn:name":"La Alegr\u00eda",
    "gn:population":0,
    "gn:timezone":"America/Mexico_City",
    "iso:country":"MX",
    "name:spa_x_preferred":[
        "La Alegr\u00eda"
    ],
    "wof:name":"La Alegria",
    "wof:placetype":"locality"
},
  "geometry": {"coordinates":[-102.77659,19.44608],"type":"Point"}
}