{
  "type": "Feature",
  "properties": {
    "gn:admin1_code":"21",
    "gn:admin2_code":"54.0",
    "gn:asciiname":"Ateta",
    "gn:country_code":"MX",
    "gn:dem":1917,
    "gn:feature_class":"P",
    "gn:feature_code":"PPL",
    "gn:name":"Ateta",
    "gn:population":125,
    "gn:timezone":"America/Mexico_City",
    "iso:country":"MX",
    "wof:name":"Ateta",
    "wof:placetype":"locality",
    "wof:population":125
},
  "geometry": {"coordinates":[-97.38667,19.82417],"type":"Point"}
}