{
  "type": "Feature",
  "properties": {
    "gn:admin1_code":"18",
    "gn:admin2_code":"19.0",
    "gn:asciiname":"El Puertecito",
    "gn:country_code":"MX",
    "gn:dem":1869,
    "gn:feature_class":"P",
    "gn:feature_code":"PPL",
    "gn:name":"El Puertecito",
    "gn:population":6,
    "gn:timezone":"America/Mexico_City",
    "iso:country":"MX",
    "wof:name":"El Puertecito",
    "wof:placetype":"locality",
    "wof:population":6
},
  "geometry": {"coordinates":[-103.98972000000001,21.56806],"type":"Point"}
}