{
  "type": "Feature",
  "properties": {
    "gn:admin1_code":"30",
    "gn:admin2_code":"152.0",
    "gn:asciiname":"El Tular",
    "gn:country_code":"MX",
    "gn:dem":8,
    "gn:feature_class":"P",
    "gn:feature_code":"PPL",
    "gn:name":"El Tular",
    "gn:population":0,
    "gn:timezone":"America/Mexico_City",
    "iso:country":"MX",
    "name:und_x_variant":[
        "Tular",
        "El Tular"
    ],
    "wof:name":"El Tular",
    "wof:placetype":"locality"
},
  "geometry": {"coordinates":[-97.63059,21.81473],"type":"Point"}
}