{
  "type": "Feature",
  "properties": {
    "gn:admin1_code":"20",
    "gn:admin2_code":"549.0",
    "gn:asciiname":"Rancho Senor",
    "gn:country_code":"MX",
    "gn:dem":1765,
    "gn:feature_class":"P",
    "gn:feature_code":"PPL",
    "gn:name":"Rancho Se\u00f1or",
    "gn:population":8,
    "gn:timezone":"America/Mexico_City",
    "iso:country":"MX",
    "name:und_x_variant":[
        "Rancho Se\u00f1or"
    ],
    "wof:name":"Rancho Senor",
    "wof:placetype":"locality",
    "wof:population":8
},
  "geometry": {"coordinates":[-97.81471999999999,17.605],"type":"Point"}
}