{
  "type": "Feature",
  "properties": {
    "gn:admin1_code":"19",
    "gn:admin2_code":"32.0",
    "gn:asciiname":"La Aguirrena",
    "gn:country_code":"MX",
    "gn:dem":380,
    "gn:feature_class":"P",
    "gn:feature_code":"PPL",
    "gn:name":"La Aguirre\u00f1a",
    "gn:population":0,
    "gn:timezone":"America/Monterrey",
    "iso:country":"MX",
    "name:spa_x_preferred":[
        "La Aguirre\u00f1a"
    ],
    "name:und_x_variant":[
        "Rancho La Aguirre\u00f1a"
    ],
    "wof:name":"La Aguirrena",
    "wof:placetype":"locality"
},
  "geometry": {"coordinates":[-100.78,27.11072],"type":"Point"}
}