{
  "type": "Feature",
  "properties": {
    "gn:admin1_code":"24.0",
    "gn:admin2_code":"34.0",
    "gn:asciiname":"Umemukniguan",
    "gn:country_code":"MX",
    "gn:dem":42,
    "gn:feature_class":"P",
    "gn:feature_code":"PPL",
    "gn:name":"Umemukniguan",
    "gn:population":0,
    "gn:timezone":"America/Mexico_City",
    "iso:country":"MX",
    "name:spa_x_preferred":[
        "Umemukniguan"
    ],
    "name:spa_x_variant":[
        "Dos Hermanas"
    ],
    "wof:name":"Umemukniguan",
    "wof:placetype":"locality"
},
  "geometry": {"coordinates":[-98.54206000000001,21.74294],"type":"Point"}
}