{
  "type": "Feature",
  "properties": {
    "gn:admin1_code":"21",
    "gn:admin2_code":"186.0",
    "gn:asciiname":"Mecalucan",
    "gn:country_code":"MX",
    "gn:dem":1722,
    "gn:feature_class":"P",
    "gn:feature_code":"PPL",
    "gn:name":"Mecalucan",
    "gn:population":0,
    "gn:timezone":"America/Mexico_City",
    "iso:country":"MX",
    "name:spa_x_preferred":[
        "Mecalucan"
    ],
    "wof:name":"Mecalucan",
    "wof:placetype":"locality"
},
  "geometry": {"coordinates":[-97.48739,19.87157],"type":"Point"}
}