{
  "type": "Feature",
  "properties": {
    "gn:admin1_code":"28.0",
    "gn:admin2_code":"32.0",
    "gn:asciiname":"Vista Arreola",
    "gn:country_code":"MX",
    "gn:dem":56,
    "gn:feature_class":"P",
    "gn:feature_code":"PPL",
    "gn:name":"Vista Arreola",
    "gn:population":0,
    "gn:timezone":"America/Matamoros",
    "iso:country":"MX",
    "name:spa_x_preferred":[
        "Vista Arreola"
    ],
    "wof:name":"Vista Arreola",
    "wof:placetype":"locality"
},
  "geometry": {"coordinates":[-98.34281,26.05129],"type":"Point"}
}