{
  "type": "Feature",
  "properties": {
    "gn:admin1_code":"10",
    "gn:admin2_code":"7.0",
    "gn:asciiname":"Pequena Bahia",
    "gn:country_code":"MX",
    "gn:dem":1111,
    "gn:feature_class":"P",
    "gn:feature_code":"PPL",
    "gn:name":"Peque\u00f1a Bah\u00eda",
    "gn:population":5,
    "gn:timezone":"America/Monterrey",
    "iso:country":"MX",
    "name:und_x_variant":[
        "Peque\u00f1a Bah\u00eda"
    ],
    "wof:name":"Pequena Bahia",
    "wof:placetype":"locality",
    "wof:population":5
},
  "geometry": {"coordinates":[-103.52867999999999,25.73361],"type":"Point"}
}