{
  "type": "Feature",
  "properties": {
    "gn:admin1_code":"25",
    "gn:admin2_code":"17.0",
    "gn:asciiname":"Los Rosarios",
    "gn:country_code":"MX",
    "gn:dem":602,
    "gn:feature_class":"P",
    "gn:feature_code":"PPL",
    "gn:name":"Los Rosarios",
    "gn:population":53,
    "gn:timezone":"America/Mazatlan",
    "iso:country":"MX",
    "wof:name":"Los Rosarios",
    "wof:placetype":"locality",
    "wof:population":53
},
  "geometry": {"coordinates":[-107.76958999999999,26.01467],"type":"Point"}
}