{
  "type": "Feature",
  "properties": {
    "gn:admin1_code":"16",
    "gn:admin2_code":"13.0",
    "gn:asciiname":"La Tejeria",
    "gn:country_code":"MX",
    "gn:dem":391,
    "gn:feature_class":"P",
    "gn:feature_code":"PPL",
    "gn:name":"La Tejer\u00eda",
    "gn:population":7,
    "gn:timezone":"America/Mexico_City",
    "iso:country":"MX",
    "name:und_x_variant":[
        "La Tejer\u00eda"
    ],
    "wof:name":"La Tejeria",
    "wof:placetype":"locality",
    "wof:population":7
},
  "geometry": {"coordinates":[-101.18667000000001,18.85111],"type":"Point"}
}