{
  "type": "Feature",
  "properties": {
    "gn:admin1_code":"14.0",
    "gn:admin2_code":"57.0",
    "gn:asciiname":"Las Verdologas",
    "gn:country_code":"MX",
    "gn:dem":1858,
    "gn:feature_class":"P",
    "gn:feature_code":"PPL",
    "gn:name":"Las Verdologas",
    "gn:population":0,
    "gn:timezone":"America/Mexico_City",
    "iso:country":"MX",
    "name:spa_x_preferred":[
        "Las Verdologas"
    ],
    "wof:name":"Las Verdologas",
    "wof:placetype":"locality"
},
  "geometry": {"coordinates":[-103.0562,19.99783],"type":"Point"}
}