{
  "type": "Feature",
  "properties": {
    "gn:admin1_code":"6",
    "gn:admin2_code":"63.0",
    "gn:asciiname":"El Durazno",
    "gn:country_code":"MX",
    "gn:dem":2032,
    "gn:feature_class":"P",
    "gn:feature_code":"PPL",
    "gn:name":"El Durazno",
    "gn:population":0,
    "gn:timezone":"America/Chihuahua",
    "iso:country":"MX",
    "name:ceb_x_preferred":[
        "El Durazno"
    ],
    "name:spa_x_preferred":[
        "El Durazno"
    ],
    "name:swe_x_preferred":[
        "El Durazno"
    ],
    "wof:name":"El Durazno",
    "wof:placetype":"locality"
},
  "geometry": {"coordinates":[-107.73775000000001,29.01572],"type":"Point"}
}