{
  "type": "Feature",
  "properties": {
    "gn:admin1_code":"19",
    "gn:admin2_code":"22.0",
    "gn:asciiname":"Los Nogales",
    "gn:country_code":"MX",
    "gn:dem":314,
    "gn:feature_class":"P",
    "gn:feature_code":"PPL",
    "gn:name":"Los Nogales",
    "gn:population":6,
    "gn:timezone":"America/Monterrey",
    "iso:country":"MX",
    "wof:name":"Los Nogales",
    "wof:placetype":"locality",
    "wof:population":6
},
  "geometry": {"coordinates":[-99.69362,25.29146],"type":"Point"}
}