{
  "type": "Feature",
  "properties": {
    "gn:admin1_code":"24",
    "gn:admin2_code":"24.0",
    "gn:asciiname":"Palmillas",
    "gn:cc2":"MX",
    "gn:country_code":"MX",
    "gn:dem":1049,
    "gn:feature_class":"P",
    "gn:feature_code":"PPL",
    "gn:name":"Palmillas",
    "gn:population":80,
    "gn:timezone":"America/Mexico_City",
    "iso:country":"MX",
    "name:und_x_variant":[
        "Palmitas",
        "Palmita"
    ],
    "wof:name":"Palmillas",
    "wof:placetype":"locality",
    "wof:population":80
},
  "geometry": {"coordinates":[-100.02388999999999,21.80028],"type":"Point"}
}