{
  "type": "Feature",
  "properties": {
    "gn:admin1_code":"15",
    "gn:admin2_code":"92",
    "gn:asciiname":"Granja Avicola Tecorral",
    "gn:country_code":"MX",
    "gn:dem":2301,
    "gn:feature_class":"P",
    "gn:feature_code":"PPL",
    "gn:name":"Granja Av\u00edcola Tecorral",
    "gn:population":27,
    "gn:timezone":"America/Mexico_City",
    "iso:country":"MX",
    "name:und_x_variant":[
        "Granja Av\u00edcola Tecorral"
    ],
    "wof:name":"Granja Avicola Tecorral",
    "wof:placetype":"locality",
    "wof:population":27
},
  "geometry": {"coordinates":[-98.82335,19.67805],"type":"Point"}
}