{
  "type": "Feature",
  "properties": {
    "gn:admin1_code":"16.0",
    "gn:admin2_code":"81.0",
    "gn:asciiname":"Lechuguillas",
    "gn:country_code":"MX",
    "gn:dem":1718,
    "gn:feature_class":"P",
    "gn:feature_code":"PPL",
    "gn:name":"Lechuguillas",
    "gn:population":0,
    "gn:timezone":"America/Mexico_City",
    "iso:country":"MX",
    "name:spa_x_preferred":[
        "Lechuguillas"
    ],
    "wof:name":"Lechuguillas",
    "wof:placetype":"locality"
},
  "geometry": {"coordinates":[-100.36474,19.24119],"type":"Point"}
}