{
  "type": "Feature",
  "properties": {
    "gn:admin1_code":"14",
    "gn:admin2_code":"35.0",
    "gn:asciiname":"Rio de la Tiza",
    "gn:country_code":"MX",
    "gn:dem":1794,
    "gn:feature_class":"P",
    "gn:feature_code":"PPL",
    "gn:name":"R\u00edo de la Tiza",
    "gn:population":7,
    "gn:timezone":"America/Mexico_City",
    "iso:country":"MX",
    "name:und_x_variant":[
        "R\u00edo de la Tiza"
    ],
    "wof:name":"Rio de la Tiza",
    "wof:placetype":"locality",
    "wof:population":7
},
  "geometry": {"coordinates":[-102.25389,21.53028],"type":"Point"}
}