{
  "type": "Feature",
  "properties": {
    "gn:admin1_code":"30",
    "gn:admin2_code":"23.0",
    "gn:asciiname":"Sompazol",
    "gn:country_code":"MX",
    "gn:dem":1575,
    "gn:feature_class":"P",
    "gn:feature_code":"PPL",
    "gn:name":"Sompazol",
    "gn:population":198,
    "gn:timezone":"America/Mexico_City",
    "iso:country":"MX",
    "wof:name":"Sompazol",
    "wof:placetype":"locality",
    "wof:population":198
},
  "geometry": {"coordinates":[-97.23389,19.81667],"type":"Point"}
}