{
  "type": "Feature",
  "properties": {
    "gn:admin1_code":"30",
    "gn:admin2_code":"210.0",
    "gn:asciiname":"Buena Vista",
    "gn:country_code":"MX",
    "gn:dem":126,
    "gn:feature_class":"P",
    "gn:feature_code":"PPL",
    "gn:name":"Buena Vista",
    "gn:population":154,
    "gn:timezone":"America/Mexico_City",
    "iso:country":"MX",
    "wof:name":"Buena Vista",
    "wof:placetype":"locality",
    "wof:population":154
},
  "geometry": {"coordinates":[-94.12306,17.26444],"type":"Point"}
}