{
  "type": "Feature",
  "properties": {
    "gn:admin1_code":"30",
    "gn:admin2_code":"184",
    "gn:asciiname":"Xochitepetl",
    "gn:country_code":"MX",
    "gn:dem":2302,
    "gn:feature_class":"P",
    "gn:feature_code":"PPL",
    "gn:name":"Xochit\u00e9petl",
    "gn:population":36,
    "gn:timezone":"America/Mexico_City",
    "iso:country":"MX",
    "name:und_x_variant":[
        "Xochit\u00e9petl"
    ],
    "wof:name":"Xochitepetl",
    "wof:placetype":"locality",
    "wof:population":36
},
  "geometry": {"coordinates":[-97.08833,18.59972],"type":"Point"}
}