{
  "type": "Feature",
  "properties": {
    "gn:admin1_code":"14",
    "gn:admin2_code":"15",
    "gn:asciiname":"La Tuna",
    "gn:country_code":"MX",
    "gn:dem":883,
    "gn:feature_class":"P",
    "gn:feature_code":"PPL",
    "gn:name":"La Tuna",
    "gn:population":30,
    "gn:timezone":"America/Mexico_City",
    "iso:country":"MX",
    "wof:name":"La Tuna",
    "wof:placetype":"locality",
    "wof:population":30
},
  "geometry": {"coordinates":[-104.25167,19.74417],"type":"Point"}
}