{
  "type": "Feature",
  "properties": {
    "gn:admin1_code":"12",
    "gn:admin2_code":"6",
    "gn:asciiname":"Los Limones",
    "gn:country_code":"MX",
    "gn:dem":1131,
    "gn:feature_class":"P",
    "gn:feature_code":"PPL",
    "gn:name":"Los Limones",
    "gn:population":52,
    "gn:timezone":"America/Mexico_City",
    "iso:country":"MX",
    "wof:name":"Los Limones",
    "wof:placetype":"locality",
    "wof:population":52
},
  "geometry": {"coordinates":[-100.09207000000001,18.1973],"type":"Point"}
}