{
  "type": "Feature",
  "properties": {
    "gn:admin1_code":"6",
    "gn:admin2_code":"61.0",
    "gn:asciiname":"San Juan de la Veracruz",
    "gn:country_code":"MX",
    "gn:dem":1452,
    "gn:feature_class":"P",
    "gn:feature_code":"PPL",
    "gn:name":"San Juan de la Veracruz",
    "gn:population":0,
    "gn:timezone":"America/Chihuahua",
    "iso:country":"MX",
    "name:und_x_variant":[
        "Colonia San Juan de la Veracruz",
        "San Juan de la Veracruz"
    ],
    "wof:name":"San Juan de la Veracruz",
    "wof:placetype":"locality"
},
  "geometry": {"coordinates":[-106.19284,28.09397],"type":"Point"}
}