{
  "type": "Feature",
  "properties": {
    "gn:admin1_code":"30.0",
    "gn:admin2_code":"123.0",
    "gn:asciiname":"El Chintoncito",
    "gn:country_code":"MX",
    "gn:dem":42,
    "gn:feature_class":"P",
    "gn:feature_code":"PPL",
    "gn:name":"El Chintoncito",
    "gn:population":0,
    "gn:timezone":"America/Mexico_City",
    "iso:country":"MX",
    "name:spa_x_preferred":[
        "El Chintoncito"
    ],
    "wof:name":"El Chintoncito",
    "wof:placetype":"locality"
},
  "geometry": {"coordinates":[-98.34399999999999,21.91638],"type":"Point"}
}