{
  "type": "Feature",
  "properties": {
    "gn:admin1_code":"12",
    "gn:admin2_code":"7",
    "gn:asciiname":"Caloxtitlan",
    "gn:country_code":"MX",
    "gn:dem":1091,
    "gn:feature_class":"P",
    "gn:feature_code":"PPL",
    "gn:name":"Caloxtitl\u00e1n",
    "gn:population":47,
    "gn:timezone":"America/Mexico_City",
    "iso:country":"MX",
    "name:und_x_variant":[
        "Caloxtitl\u00e1n"
    ],
    "wof:name":"Caloxtitlan",
    "wof:placetype":"locality",
    "wof:population":47
},
  "geometry": {"coordinates":[-100.09658,18.3156],"type":"Point"}
}