{
  "type": "Feature",
  "properties": {
    "gn:admin1_code":"12",
    "gn:admin2_code":"16.0",
    "gn:asciiname":"El Coacoyol",
    "gn:country_code":"MX",
    "gn:dem":483,
    "gn:feature_class":"P",
    "gn:feature_code":"PPL",
    "gn:name":"El Coacoyol",
    "gn:population":0,
    "gn:timezone":"America/Mexico_City",
    "iso:country":"MX",
    "name:spa_x_preferred":[
        "El Coacoyol"
    ],
    "wof:name":"El Coacoyol",
    "wof:placetype":"locality"
},
  "geometry": {"coordinates":[-101.65988,18.33995],"type":"Point"}
}