{
  "type": "Feature",
  "properties": {
    "gn:admin1_code":"21",
    "gn:admin2_code":"53.0",
    "gn:asciiname":"Lazaro Cardenas (Tzitla)",
    "gn:country_code":"MX",
    "gn:dem":2368,
    "gn:feature_class":"P",
    "gn:feature_code":"PPL",
    "gn:name":"L\u00e1zaro C\u00e1rdenas (Tzitla)",
    "gn:population":631,
    "gn:timezone":"America/Mexico_City",
    "iso:country":"MX",
    "name:und_x_variant":[
        "L\u00e1zaro C\u00e1rdenas (Tzitla)"
    ],
    "wof:name":"Lazaro Cardenas (Tzitla)",
    "wof:placetype":"locality",
    "wof:population":631
},
  "geometry": {"coordinates":[-98.05333,19.81639],"type":"Point"}
}