{
  "type": "Feature",
  "properties": {
    "gn:admin1_code":"19.0",
    "gn:admin2_code":"5.0",
    "gn:asciiname":"Numero Dos",
    "gn:country_code":"MX",
    "gn:dem":255,
    "gn:feature_class":"P",
    "gn:feature_code":"PPL",
    "gn:name":"N\u00famero Dos",
    "gn:population":0,
    "gn:timezone":"America/Matamoros",
    "iso:country":"MX",
    "name:spa_x_preferred":[
        "N\u00famero Dos"
    ],
    "wof:name":"Numero Dos",
    "wof:placetype":"locality"
},
  "geometry": {"coordinates":[-100.23152,27.60757000000001],"type":"Point"}
}