{
  "type": "Feature",
  "properties": {
    "gn:admin1_code":"12",
    "gn:admin2_code":"35.0",
    "gn:asciiname":"Colonia el Tomatal (Kilometro 128)",
    "gn:country_code":"MX",
    "gn:dem":873,
    "gn:feature_class":"P",
    "gn:feature_code":"PPL",
    "gn:name":"Colonia el Tomatal (Kil\u00f3metro 128)",
    "gn:population":16,
    "gn:timezone":"America/Mexico_City",
    "iso:country":"MX",
    "wof:name":"Colonia el Tomatal (Kilometro 128)",
    "wof:placetype":"locality",
    "wof:population":16
},
  "geometry": {"coordinates":[-99.50639,18.30167],"type":"Point"}
}