{
  "type": "Feature",
  "properties": {
    "iso:country":"MX",
    "name:spa_x_preferred":[
        "San Rafael Insurgentes"
    ],
    "name:unk_x_variant":[
        "San Rafael Insurgentes"
    ],
    "qs:gn_adm0_cc":"MX",
    "qs:gn_local":3985344,
    "qs:gn_nam_loc":"san miguel de allende",
    "qs:gn_namadm1":"11",
    "qs:local_max":3714,
    "qs:local_sum":6237,
    "qs:localhoods":10,
    "qs:name":"San Rafael Insurgentes",
    "qs:name_adm0":"M\u00e9xico",
    "qs:name_adm1":"Guanajuato",
    "qs:name_adm2":"Allende",
    "qs:name_local":"San Miguel de Allende",
    "qs:photo_max":118,
    "qs:photo_sum":248,
    "qs:placetype":"Suburb",
    "qs:quad_count":7,
    "qs:woe_adm0":23424900,
    "qs:woe_adm1":2346274,
    "qs:woe_adm2":12599991,
    "qs:woe_lau":0,
    "qs:woe_local":144620,
    "qs:woe_ver":"7.10.0",
    "wof:lang":[
        "spa"
    ],
    "wof:name":"San Rafael Insurgentes",
    "wof:placetype":"neighbourhood"
},
  "geometry": {"coordinates":[-100.750837,20.918517],"type":"Point"}
}