{
  "type": "Feature",
  "properties": {
    "gn:admin1_code":"15.0",
    "gn:admin2_code":"118.0",
    "gn:asciiname":"La Ciervita",
    "gn:country_code":"MX",
    "gn:dem":3436,
    "gn:feature_class":"P",
    "gn:feature_code":"PPL",
    "gn:name":"La Ciervita",
    "gn:population":0,
    "gn:timezone":"America/Mexico_City",
    "iso:country":"MX",
    "name:spa_x_preferred":[
        "La Ciervita"
    ],
    "wof:name":"La Ciervita",
    "wof:placetype":"locality"
},
  "geometry": {"coordinates":[-99.80766,19.18013],"type":"Point"}
}