{
  "type": "Feature",
  "properties": {
    "gn:admin1_code":"14",
    "gn:admin2_code":"53.0",
    "gn:asciiname":"Las Memelas",
    "gn:country_code":"MX",
    "gn:dem":1951,
    "gn:feature_class":"P",
    "gn:feature_code":"PPL",
    "gn:name":"Las Memelas",
    "gn:population":0,
    "gn:timezone":"America/Mexico_City",
    "iso:country":"MX",
    "name:spa_x_preferred":[
        "Las Memelas"
    ],
    "name:und_x_variant":[
        "Las Molleras"
    ],
    "wof:name":"Las Memelas",
    "wof:placetype":"locality"
},
  "geometry": {"coordinates":[-101.79667000000001,21.45569],"type":"Point"}
}