{
  "type": "Feature",
  "properties": {
    "gn:admin1_code":"20",
    "gn:admin2_code":"549.0",
    "gn:asciiname":"San Vicente del Palmar",
    "gn:country_code":"MX",
    "gn:dem":1793,
    "gn:feature_class":"P",
    "gn:feature_code":"PPL",
    "gn:name":"San Vicente del Palmar",
    "gn:population":216,
    "gn:timezone":"America/Mexico_City",
    "iso:country":"MX",
    "name:spa_x_preferred":[
        "San Vicente del Palmar"
    ],
    "wof:name":"San Vicente del Palmar",
    "wof:placetype":"locality",
    "wof:population":216
},
  "geometry": {"coordinates":[-97.94806,17.58472],"type":"Point"}
}