{
  "type": "Feature",
  "properties": {
    "gn:admin1_code":"9",
    "gn:admin2_code":"8",
    "gn:asciiname":"Paraje el Rancho",
    "gn:country_code":"MX",
    "gn:dem":2650,
    "gn:feature_class":"P",
    "gn:feature_code":"PPL",
    "gn:name":"Paraje el Rancho",
    "gn:population":23,
    "gn:timezone":"America/Mexico_City",
    "iso:country":"MX",
    "wof:name":"Paraje el Rancho",
    "wof:placetype":"locality",
    "wof:population":23
},
  "geometry": {"coordinates":[-99.25458,19.29324],"type":"Point"}
}