{
  "type": "Feature",
  "properties": {
    "gn:admin1_code":"29",
    "gn:admin2_code":"21.0",
    "gn:asciiname":"Las Maravillas",
    "gn:country_code":"MX",
    "gn:dem":2767,
    "gn:feature_class":"P",
    "gn:feature_code":"PPL",
    "gn:name":"Las Maravillas",
    "gn:population":0,
    "gn:timezone":"America/Mexico_City",
    "iso:country":"MX",
    "name:spa_x_preferred":[
        "Las Maravillas"
    ],
    "wof:name":"Las Maravillas",
    "wof:placetype":"locality"
},
  "geometry": {"coordinates":[-98.55410000000001,19.48241],"type":"Point"}
}