{
  "type": "Feature",
  "properties": {
    "gn:country":"MX",
    "gn:fcode":"PPL",
    "gn:population":0,
    "iso:country":"MX",
    "name:ara_x_preferred":[
        "\u0633\u0627\u0643\u0631\u0645\u064a\u0646\u062a\u0648"
    ],
    "name:ben_x_preferred":[
        "\u09b8\u09cd\u09af\u09be\u0995\u09cd\u09b0\u09be\u09ae\u09c7\u09a8\u09cd\u099f\u09cb"
    ],
    "name:ell_x_preferred":[
        "\u03a3\u03b1\u03ba\u03c1\u03b1\u03bc\u03ad\u03bd\u03c4\u03bf"
    ],
    "name:hin_x_preferred":[
        "\u0938\u0948\u0915\u094d\u0930\u093e\u092e\u0947\u0902\u091f\u094b"
    ],
    "name:hun_x_preferred":[
        "Sacramento"
    ],
    "name:ind_x_preferred":[
        "Sacramento"
    ],
    "name:tur_x_preferred":[
        "Sacramento"
    ],
    "name:und_x_variant":[
        "Colonia Sacramento"
    ],
    "qs_pg:aaroncc":"MX",
    "qs_pg:gn_country":"MX",
    "qs_pg:gn_fcode":"PPL",
    "qs_pg:gn_pop":0,
    "qs_pg:name":"Sacramento",
    "qs_pg:name_adm0":"M\u00e9xico",
    "qs_pg:name_adm1":"Chihuahua",
    "qs_pg:photos_9k":1,
    "qs_pg:photos_9r":1,
    "qs_pg:photos_all":4,
    "qs_pg:photos_sr":0,
    "qs_pg:pop_sr":4,
    "qs_pg:qs_pg_placetype":"locality",
    "qs_pg:qs_pg_placetype_gp":"Town",
    "qs_pg:woe_adm0":23424900,
    "woe:adm0_id":23424900,
    "woe:name_adm0":"M\u00e9xico",
    "woe:name_adm1":"Chihuahua",
    "woe:placetype":"Town",
    "wof:name":"Sacramento",
    "wof:placetype":"locality"
},
  "geometry": {"coordinates":[-106.20361,28.8535],"type":"Point"}
}