{
  "type": "Feature",
  "properties": {
    "gn:admin1_code":"26.0",
    "gn:admin2_code":"35.0",
    "gn:asciiname":"Estacion Cumeral",
    "gn:country_code":"MX",
    "gn:dem":937,
    "gn:feature_class":"P",
    "gn:feature_code":"PPL",
    "gn:name":"Estaci\u00f3n Cumeral",
    "gn:population":0,
    "gn:timezone":"America/Hermosillo",
    "iso:country":"MX",
    "name:spa_x_preferred":[
        "Estaci\u00f3n Cumeral"
    ],
    "name:und_x_variant":[
        "Cumeral"
    ],
    "wof:name":"Estacion Cumeral",
    "wof:placetype":"locality"
},
  "geometry": {"coordinates":[-110.85028,30.88913],"type":"Point"}
}