{
  "type": "Feature",
  "properties": {
    "gn:admin1_code":"6.0",
    "gn:admin2_code":"13.0",
    "gn:asciiname":"Ejido Ignacio Zaragoza",
    "gn:country_code":"MX",
    "gn:dem":1888,
    "gn:feature_class":"P",
    "gn:feature_code":"PPL",
    "gn:name":"Ejido Ignacio Zaragoza",
    "gn:population":0,
    "gn:timezone":"America/Chihuahua",
    "iso:country":"MX",
    "wof:name":"Ejido Ignacio Zaragoza",
    "wof:placetype":"locality"
},
  "geometry": {"coordinates":[-108.31667,30.18333],"type":"Point"}
}