{
  "type": "Feature",
  "properties": {
    "iso:country":"MX",
    "name:deu_x_preferred":[
        "Universidad de Sonora"
    ],
    "name:fra_x_preferred":[
        "Universit\u00e9 du Sonora"
    ],
    "name:rus_x_preferred":[
        "\u0421\u043e\u043d\u043e\u0440\u0430"
    ],
    "name:spa_x_preferred":[
        "Universidad de Sonora"
    ],
    "name:unk_x_variant":[
        "Ejido Sonora"
    ],
    "wd:wordcount":450,
    "wof:lang":[
        "spa"
    ],
    "wof:name":"Universidad de Sonora",
    "wof:placetype":"neighbourhood"
},
  "geometry": {"coordinates":[-110.96276,29.08433],"type":"Point"}
}