{
  "type": "Feature",
  "properties": {
    "gn:admin1_code":"13",
    "gn:admin2_code":"23.0",
    "gn:asciiname":"Colonia el Veinte",
    "gn:country_code":"MX",
    "gn:dem":1983,
    "gn:feature_class":"P",
    "gn:feature_code":"PPL",
    "gn:name":"Colonia el Veinte",
    "gn:population":245,
    "gn:timezone":"America/Mexico_City",
    "iso:country":"MX",
    "wof:name":"Colonia el Veinte",
    "wof:placetype":"locality",
    "wof:population":245
},
  "geometry": {"coordinates":[-99.04555999999999,20.23333],"type":"Point"}
}