{
  "type": "Feature",
  "properties": {
    "gn:admin1_code":"30",
    "gn:admin2_code":"68.0",
    "gn:asciiname":"Monte Salas",
    "gn:country_code":"MX",
    "gn:dem":1180,
    "gn:feature_class":"P",
    "gn:feature_code":"PPL",
    "gn:name":"Monte Salas",
    "gn:population":1850,
    "gn:timezone":"America/Mexico_City",
    "iso:country":"MX",
    "wof:name":"Monte Salas",
    "wof:placetype":"locality",
    "wof:population":1850
},
  "geometry": {"coordinates":[-97.01833000000001,18.93722],"type":"Point"}
}