{
  "type": "Feature",
  "properties": {
    "gn:admin1_code":"6",
    "gn:admin2_code":"9.0",
    "gn:asciiname":"Rancheria Nerochachi",
    "gn:country_code":"MX",
    "gn:dem":2271,
    "gn:feature_class":"P",
    "gn:feature_code":"PPL",
    "gn:name":"Rancher\u00eda Ner\u00f3chachi",
    "gn:population":0,
    "gn:timezone":"America/Chihuahua",
    "iso:country":"MX",
    "name:spa_x_preferred":[
        "Rancher\u00eda Ner\u00f3chachi"
    ],
    "name:und_x_variant":[
        "Rancho Nerochahic"
    ],
    "wof:name":"Rancheria Nerochachi",
    "wof:placetype":"locality"
},
  "geometry": {"coordinates":[-107.53086999999999,27.83981],"type":"Point"}
}