{
  "type": "Feature",
  "properties": {
    "gn:admin1_code":"26",
    "gn:admin2_code":"66.0",
    "gn:asciiname":"La Leona",
    "gn:country_code":"MX",
    "gn:dem":510,
    "gn:feature_class":"P",
    "gn:feature_code":"PPL",
    "gn:name":"La Leona",
    "gn:population":0,
    "gn:timezone":"America/Hermosillo",
    "iso:country":"MX",
    "name:ceb_x_preferred":[
        "La Leona"
    ],
    "name:spa_x_preferred":[
        "La Leona"
    ],
    "name:spa_x_variant":[
        "La leona"
    ],
    "name:srp_x_preferred":[
        "\u041b\u0430 \u041b\u0435\u043e\u043d\u0430"
    ],
    "name:swe_x_preferred":[
        "La Leona"
    ],
    "wof:name":"La Leona",
    "wof:placetype":"locality"
},
  "geometry": {"coordinates":[-110.21362000000001,29.17594],"type":"Point"}
}