{
  "type": "Feature",
  "properties": {
    "gn:admin1_code":"15",
    "gn:admin2_code":"48.0",
    "gn:asciiname":"Los Javieres",
    "gn:country_code":"MX",
    "gn:dem":2691,
    "gn:feature_class":"P",
    "gn:feature_code":"PPL",
    "gn:name":"Los Javieres",
    "gn:population":232,
    "gn:timezone":"America/Mexico_City",
    "iso:country":"MX",
    "wof:name":"Los Javieres",
    "wof:placetype":"locality",
    "wof:population":232
},
  "geometry": {"coordinates":[-99.76228,19.69773],"type":"Point"}
}