{
  "type": "Feature",
  "properties": {
    "gn:admin1_code":"19.0",
    "gn:admin2_code":"13.0",
    "gn:asciiname":"El Canelo",
    "gn:country_code":"MX",
    "gn:dem":169,
    "gn:feature_class":"P",
    "gn:feature_code":"PPL",
    "gn:name":"El Canelo",
    "gn:population":0,
    "gn:timezone":"America/Monterrey",
    "iso:country":"MX",
    "name:spa_x_preferred":[
        "El Canelo"
    ],
    "wof:name":"El Canelo",
    "wof:placetype":"locality"
},
  "geometry": {"coordinates":[-99.07098999999999,25.53524],"type":"Point"}
}