{
  "type": "Feature",
  "properties": {
    "gn:admin1_code":"11.0",
    "gn:admin2_code":"30.0",
    "gn:asciiname":"Coyotes",
    "gn:country_code":"MX",
    "gn:dem":2107,
    "gn:feature_class":"P",
    "gn:feature_code":"PPL",
    "gn:name":"Coyotes",
    "gn:population":0,
    "gn:timezone":"America/Mexico_City",
    "iso:country":"MX",
    "name:spa_x_preferred":[
        "Coyotes"
    ],
    "name:spa_x_variant":[
        "Ojo de Agua de San Miguel"
    ],
    "wof:name":"Coyotes",
    "wof:placetype":"locality"
},
  "geometry": {"coordinates":[-101.18415,21.63391],"type":"Point"}
}