{
  "type": "Feature",
  "properties": {
    "gn:admin1_code":"2.0",
    "gn:admin2_code":"1.0",
    "gn:asciiname":"San Angel",
    "gn:country_code":"MX",
    "gn:dem":20,
    "gn:feature_class":"P",
    "gn:feature_code":"PPL",
    "gn:name":"San \u00c1ngel",
    "gn:population":0,
    "gn:timezone":"America/Tijuana",
    "iso:country":"MX",
    "name:spa_x_preferred":[
        "San \u00c1ngel"
    ],
    "wof:name":"San Angel",
    "wof:placetype":"locality"
},
  "geometry": {"coordinates":[-116.04309000000001,30.81671],"type":"Point"}
}