{
  "type": "Feature",
  "properties": {
    "gn:admin1_code":"10",
    "gn:admin2_code":"2.0",
    "gn:asciiname":"El Pinal",
    "gn:country_code":"MX",
    "gn:dem":1449,
    "gn:feature_class":"P",
    "gn:feature_code":"PPL",
    "gn:name":"El Pinal",
    "gn:population":8,
    "gn:timezone":"America/Monterrey",
    "iso:country":"MX",
    "wof:name":"El Pinal",
    "wof:placetype":"locality",
    "wof:population":8
},
  "geometry": {"coordinates":[-106.57331000000001,25.14577],"type":"Point"}
}