{
  "type": "Feature",
  "properties": {
    "gn:admin1_code":"19.0",
    "gn:asciiname":"Raquel",
    "gn:country_code":"MX",
    "gn:dem":336,
    "gn:feature_class":"P",
    "gn:feature_code":"PPL",
    "gn:name":"Raquel",
    "gn:population":0,
    "gn:timezone":"America/Monterrey",
    "iso:country":"MX",
    "name:spa_x_preferred":[
        "Raquel"
    ],
    "wof:name":"Raquel",
    "wof:placetype":"locality"
},
  "geometry": {"coordinates":[-99.54275,24.86081],"type":"Point"}
}