{
  "type": "Feature",
  "properties": {
    "gn:admin1_code":"32",
    "gn:admin2_code":"34",
    "gn:asciiname":"El Picacho",
    "gn:country_code":"MX",
    "gn:dem":1960,
    "gn:feature_class":"P",
    "gn:feature_code":"PPL",
    "gn:name":"El Picacho",
    "gn:population":10,
    "gn:timezone":"America/Mexico_City",
    "iso:country":"MX",
    "wof:name":"El Picacho",
    "wof:placetype":"locality",
    "wof:population":10
},
  "geometry": {"coordinates":[-102.73639,21.45139],"type":"Point"}
}