{
  "type": "Feature",
  "properties": {
    "gn:admin1_code":"13",
    "gn:admin2_code":"60.0",
    "gn:asciiname":"El Gosco",
    "gn:country_code":"MX",
    "gn:dem":1689,
    "gn:feature_class":"P",
    "gn:feature_code":"PPL",
    "gn:name":"El Gosco",
    "gn:population":143,
    "gn:timezone":"America/Mexico_City",
    "iso:country":"MX",
    "wof:name":"El Gosco",
    "wof:placetype":"locality",
    "wof:population":143
},
  "geometry": {"coordinates":[-98.24399,20.32858],"type":"Point"}
}