{
  "type": "Feature",
  "properties": {
    "gn:admin1_code":"5",
    "gn:admin2_code":"57.0",
    "gn:asciiname":"Matasano",
    "gn:country_code":"MX",
    "gn:dem":1785,
    "gn:feature_class":"P",
    "gn:feature_code":"PPL",
    "gn:name":"Matasano",
    "gn:population":228,
    "gn:timezone":"America/Mexico_City",
    "iso:country":"MX",
    "wof:name":"Matasano",
    "wof:placetype":"locality",
    "wof:population":228
},
  "geometry": {"coordinates":[-92.37166999999999,15.40639],"type":"Point"}
}