{
  "type": "Feature",
  "properties": {
    "gn:admin1_code":"16",
    "gn:admin2_code":"50.0",
    "gn:asciiname":"Cliserio Villafuerte el Chico",
    "gn:country_code":"MX",
    "gn:dem":2401,
    "gn:feature_class":"P",
    "gn:feature_code":"PPL",
    "gn:name":"Cliserio Villafuerte el Chico",
    "gn:population":274,
    "gn:timezone":"America/Mexico_City",
    "iso:country":"MX",
    "wof:name":"Cliserio Villafuerte el Chico",
    "wof:placetype":"locality",
    "wof:population":274
},
  "geometry": {"coordinates":[-100.53158999999999,19.84191],"type":"Point"}
}