{
  "type": "Feature",
  "properties": {
    "gn:admin1_code":"31",
    "gn:admin2_code":"104.0",
    "gn:asciiname":"Xlapak",
    "gn:country_code":"MX",
    "gn:dem":31,
    "gn:feature_class":"P",
    "gn:feature_code":"PPL",
    "gn:name":"Xlapak",
    "gn:population":0,
    "gn:timezone":"America/Merida",
    "iso:country":"MX",
    "name:deu_x_preferred":[
        "Xlapak"
    ],
    "name:hun_x_preferred":[
        "Xlapak"
    ],
    "name:ita_x_preferred":[
        "Xlapak"
    ],
    "name:spa_x_preferred":[
        "Xlapak"
    ],
    "wof:name":"Xlapak",
    "wof:placetype":"locality"
},
  "geometry": {"coordinates":[-88.6297,20.25635],"type":"Point"}
}