{
  "type": "Feature",
  "properties": {
    "gn:admin1_code":"5",
    "gn:admin2_code":"107.0",
    "gn:asciiname":"Merida",
    "gn:country_code":"MX",
    "gn:dem":625,
    "gn:feature_class":"P",
    "gn:feature_code":"PPL",
    "gn:name":"M\u00e9rida",
    "gn:population":0,
    "gn:timezone":"America/Mexico_City",
    "iso:country":"MX",
    "name:spa_x_preferred":[
        "M\u00e9rida"
    ],
    "wof:name":"Merida",
    "wof:placetype":"locality"
},
  "geometry": {"coordinates":[-93.33087999999999,16.11111],"type":"Point"}
}