{
  "type": "Feature",
  "properties": {
    "gn:admin1_code":"10.0",
    "gn:admin2_code":"34.0",
    "gn:asciiname":"Las Higuerillas",
    "gn:country_code":"MX",
    "gn:dem":486,
    "gn:feature_class":"P",
    "gn:feature_code":"PPL",
    "gn:name":"Las Higuerillas",
    "gn:population":0,
    "gn:timezone":"America/Mazatlan",
    "iso:country":"MX",
    "name:spa_x_preferred":[
        "Las Higuerillas"
    ],
    "wof:name":"Las Higuerillas",
    "wof:placetype":"locality"
},
  "geometry": {"coordinates":[-107.148,25.47799],"type":"Point"}
}