{
  "type": "Feature",
  "properties": {
    "gn:admin1_code":"14",
    "gn:admin2_code":"29.0",
    "gn:asciiname":"El Pochote",
    "gn:country_code":"MX",
    "gn:dem":1979,
    "gn:feature_class":"P",
    "gn:feature_code":"PPL",
    "gn:name":"El Pochote",
    "gn:population":8,
    "gn:timezone":"America/Mexico_City",
    "iso:country":"MX",
    "wof:name":"El Pochote",
    "wof:placetype":"locality",
    "wof:population":8
},
  "geometry": {"coordinates":[-102.99472,20.9975],"type":"Point"}
}