{
  "type": "Feature",
  "properties": {
    "iso:country":"MX",
    "name:spa_x_preferred":[
        "Fracc Zona de Granjas"
    ],
    "qs:gn_adm0_cc":"MX",
    "qs:gn_local":3531023,
    "qs:local_max":294,
    "qs:local_sum":545,
    "qs:localhoods":7,
    "qs:name":"Fracc Zona de Granjas",
    "qs:name_adm0":"M\u00e9xico",
    "qs:name_adm1":"Quintana Roo",
    "qs:name_adm2":"Othon P. Blanco",
    "qs:name_local":"Chetumal",
    "qs:photo_max":10,
    "qs:photo_sum":23,
    "qs:placetype":"Suburb",
    "qs:quad_count":7,
    "qs:woe_adm0":23424900,
    "qs:woe_adm1":2346286,
    "qs:woe_adm2":12601468,
    "qs:woe_lau":0,
    "qs:woe_local":115828,
    "qs:woe_ver":"7.10.0",
    "wof:lang":[
        "spa"
    ],
    "wof:name":"Fracc Zona de Granjas",
    "wof:placetype":"neighbourhood"
},
  "geometry": {"coordinates":[-88.274547,18.516867],"type":"Point"}
}