{
  "type": "Feature",
  "properties": {
    "gn:admin1_code":"7",
    "gn:admin2_code":"2.0",
    "gn:asciiname":"El Rey",
    "gn:country_code":"MX",
    "gn:dem":405,
    "gn:feature_class":"P",
    "gn:feature_code":"PPL",
    "gn:name":"El Rey",
    "gn:population":0,
    "gn:timezone":"America/Matamoros",
    "iso:country":"MX",
    "name:ceb_x_preferred":[
        "El Rey"
    ],
    "name:hun_x_preferred":[
        "El Rey"
    ],
    "name:spa_x_preferred":[
        "El Rey"
    ],
    "name:swe_x_preferred":[
        "El Rey"
    ],
    "wof:name":"El Rey",
    "wof:placetype":"locality"
},
  "geometry": {"coordinates":[-101.44964,29.54192],"type":"Point"}
}