{
  "type": "Feature",
  "properties": {
    "gn:admin1_code":"6",
    "gn:admin2_code":"20.0",
    "gn:asciiname":"Chichimochi",
    "gn:country_code":"MX",
    "gn:dem":1124,
    "gn:feature_class":"P",
    "gn:feature_code":"PPL",
    "gn:name":"Chichimochi",
    "gn:population":0,
    "gn:timezone":"America/Chihuahua",
    "iso:country":"MX",
    "name:spa_x_preferred":[
        "Chichimochi"
    ],
    "wof:name":"Chichimochi",
    "wof:placetype":"locality"
},
  "geometry": {"coordinates":[-108.31739,27.62954],"type":"Point"}
}