{
  "type": "Feature",
  "properties": {
    "gn:admin1_code":"6",
    "gn:admin2_code":"40.0",
    "gn:asciiname":"Los Cachos",
    "gn:country_code":"MX",
    "gn:dem":2181,
    "gn:feature_class":"P",
    "gn:feature_code":"PPL",
    "gn:name":"Los Cachos",
    "gn:population":0,
    "gn:timezone":"America/Chihuahua",
    "iso:country":"MX",
    "name:spa_x_preferred":[
        "Los Cachos"
    ],
    "wof:name":"Los Cachos",
    "wof:placetype":"locality"
},
  "geometry": {"coordinates":[-108.24361,29.64306],"type":"Point"}
}