{
  "type": "Feature",
  "properties": {
    "gn:admin1_code":"3",
    "gn:admin2_code":"1.0",
    "gn:asciiname":"El Cielito",
    "gn:country_code":"MX",
    "gn:dem":32,
    "gn:feature_class":"P",
    "gn:feature_code":"PPL",
    "gn:name":"El Cielito",
    "gn:population":0,
    "gn:timezone":"America/Mazatlan",
    "iso:country":"MX",
    "name:spa_x_preferred":[
        "El Cielito"
    ],
    "wof:name":"El Cielito",
    "wof:placetype":"locality"
},
  "geometry": {"coordinates":[-112.05253999999999,25.85241],"type":"Point"}
}