{
  "type": "Feature",
  "properties": {
    "gn:admin1_code":"14",
    "gn:admin2_code":"65",
    "gn:asciiname":"El Naranjito",
    "gn:country_code":"MX",
    "gn:dem":711,
    "gn:feature_class":"P",
    "gn:feature_code":"PPL",
    "gn:name":"El Naranjito",
    "gn:population":24,
    "gn:timezone":"America/Mexico_City",
    "iso:country":"MX",
    "wof:name":"El Naranjito",
    "wof:placetype":"locality",
    "wof:population":24
},
  "geometry": {"coordinates":[-103.38527999999999,19.26222000000001],"type":"Point"}
}