{
  "type": "Feature",
  "properties": {
    "gn:admin1_code":"16",
    "gn:admin2_code":"92",
    "gn:asciiname":"Agua Zarca",
    "gn:country_code":"MX",
    "gn:dem":558,
    "gn:feature_class":"P",
    "gn:feature_code":"PPL",
    "gn:name":"Agua Zarca",
    "gn:population":40,
    "gn:timezone":"America/Mexico_City",
    "iso:country":"MX",
    "wof:name":"Agua Zarca",
    "wof:placetype":"locality",
    "wof:population":40
},
  "geometry": {"coordinates":[-100.56361,18.95944],"type":"Point"}
}