{
  "type": "Feature",
  "properties": {
    "gn:admin1_code":"28.0",
    "gn:admin2_code":"35.0",
    "gn:asciiname":"Veinte de Noviembre",
    "gn:country_code":"MX",
    "gn:dem":59,
    "gn:feature_class":"P",
    "gn:feature_code":"PPL",
    "gn:name":"Veinte de Noviembre",
    "gn:population":233,
    "gn:timezone":"America/Monterrey",
    "iso:country":"MX",
    "name:spa_x_preferred":[
        "Veinte de Noviembre"
    ],
    "wof:name":"Veinte de Noviembre",
    "wof:placetype":"locality",
    "wof:population":233
},
  "geometry": {"coordinates":[-98.15304,25.14036],"type":"Point"}
}