{
  "type": "Feature",
  "properties": {
    "gn:admin1_code":"21",
    "gn:admin2_code":"19.0",
    "gn:asciiname":"Ex-Hacienda Tizayuca",
    "gn:country_code":"MX",
    "gn:dem":1911,
    "gn:feature_class":"P",
    "gn:feature_code":"PPL",
    "gn:name":"Ex-Hacienda Tizayuca",
    "gn:population":133,
    "gn:timezone":"America/Mexico_City",
    "iso:country":"MX",
    "wof:name":"Ex-Hacienda Tizayuca",
    "wof:placetype":"locality",
    "wof:population":133
},
  "geometry": {"coordinates":[-98.41506,18.92795],"type":"Point"}
}