{
  "type": "Feature",
  "properties": {
    "gn:admin1_code":"12",
    "gn:admin2_code":"40.0",
    "gn:asciiname":"Los Morros",
    "gn:country_code":"MX",
    "gn:dem":2103,
    "gn:feature_class":"P",
    "gn:feature_code":"PPL",
    "gn:name":"Los Morros",
    "gn:population":431,
    "gn:timezone":"America/Mexico_City",
    "iso:country":"MX",
    "wof:name":"Los Morros",
    "wof:placetype":"locality",
    "wof:population":431
},
  "geometry": {"coordinates":[-99.80224,17.68722],"type":"Point"}
}