{
  "type": "Feature",
  "properties": {
    "gn:admin1_code":"10",
    "gn:admin2_code":"32",
    "gn:asciiname":"Potrerillos",
    "gn:country_code":"MX",
    "gn:dem":1536,
    "gn:feature_class":"P",
    "gn:feature_code":"PPL",
    "gn:name":"Potrerillos",
    "gn:population":31,
    "gn:timezone":"America/Monterrey",
    "iso:country":"MX",
    "name:ceb_x_preferred":[
        "Potrerillos"
    ],
    "name:deu_x_preferred":[
        "Potrerillos"
    ],
    "name:fra_x_preferred":[
        "Potrerillos"
    ],
    "name:ita_x_preferred":[
        "Potrerillos"
    ],
    "name:nld_x_preferred":[
        "Potrerillos"
    ],
    "name:pol_x_preferred":[
        "Potrerillos"
    ],
    "name:por_x_preferred":[
        "Potrerillos"
    ],
    "name:spa_x_preferred":[
        "Potrerillos"
    ],
    "name:swe_x_preferred":[
        "Potrerillos"
    ],
    "wof:name":"Potrerillos",
    "wof:placetype":"locality",
    "wof:population":31
},
  "geometry": {"coordinates":[-106.31841,24.92443],"type":"Point"}
}