{
  "type": "Feature",
  "properties": {
    "gn:admin1_code":"20",
    "gn:admin2_code":"464.0",
    "gn:asciiname":"San Antonio Abad",
    "gn:country_code":"MX",
    "gn:dem":2160,
    "gn:feature_class":"P",
    "gn:feature_code":"PPL",
    "gn:name":"San Antonio Abad",
    "gn:population":0,
    "gn:timezone":"America/Mexico_City",
    "iso:country":"MX",
    "name:und_x_variant":[
        "San Antonio",
        "San Antonio Abad"
    ],
    "wof:name":"San Antonio Abad",
    "wof:placetype":"locality"
},
  "geometry": {"coordinates":[-97.44813000000001,17.89415],"type":"Point"}
}