{
  "type": "Feature",
  "properties": {
    "gn:admin1_code":"24",
    "gn:admin2_code":"10.0",
    "gn:asciiname":"Las Gavias",
    "gn:country_code":"MX",
    "gn:dem":1318,
    "gn:feature_class":"P",
    "gn:feature_code":"PPL",
    "gn:name":"Las Gavias",
    "gn:population":115,
    "gn:timezone":"America/Mexico_City",
    "iso:country":"MX",
    "name:spa_x_preferred":[
        "Las Gavias"
    ],
    "wof:name":"Las Gavias",
    "wof:placetype":"locality",
    "wof:population":115
},
  "geometry": {"coordinates":[-99.51027000000001,22.22889],"type":"Point"}
}