{
  "type": "Feature",
  "properties": {
    "gn:admin1_code":"7.0",
    "gn:admin2_code":"23.0",
    "gn:asciiname":"Chapala",
    "gn:country_code":"MX",
    "gn:dem":1006,
    "gn:feature_class":"P",
    "gn:feature_code":"PPL",
    "gn:name":"Chapala",
    "gn:population":0,
    "gn:timezone":"America/Monterrey",
    "iso:country":"MX",
    "name:ceb_x_preferred":[
        "Chapala"
    ],
    "name:rus_x_preferred":[
        "\u0427\u0430\u043f\u0430\u043b\u0430"
    ],
    "name:spa_x_preferred":[
        "Chapala"
    ],
    "name:swe_x_preferred":[
        "Chapala"
    ],
    "name:und_x_variant":[
        "Rancho Chapala"
    ],
    "wof:name":"Chapala",
    "wof:placetype":"locality"
},
  "geometry": {"coordinates":[-102.81843000000001,28.35829],"type":"Point"}
}