{
  "type": "Feature",
  "properties": {
    "gn:admin1_code":"5",
    "gn:admin2_code":"97.0",
    "gn:asciiname":"Santa Delia",
    "gn:country_code":"MX",
    "gn:dem":6,
    "gn:feature_class":"P",
    "gn:feature_code":"PPL",
    "gn:name":"Santa Delia",
    "gn:population":0,
    "gn:timezone":"America/Mexico_City",
    "iso:country":"MX",
    "name:spa_x_preferred":[
        "Santa Delia"
    ],
    "wof:name":"Santa Delia",
    "wof:placetype":"locality"
},
  "geometry": {"coordinates":[-93.54718,15.77436],"type":"Point"}
}