{
  "type": "Feature",
  "properties": {
    "gn:admin1_code":"26",
    "gn:admin2_code":"18.0",
    "gn:asciiname":"Chimbampo",
    "gn:country_code":"MX",
    "gn:dem":97,
    "gn:feature_class":"P",
    "gn:feature_code":"PPL",
    "gn:name":"Chimbampo",
    "gn:population":0,
    "gn:timezone":"America/Hermosillo",
    "iso:country":"MX",
    "name:spa_x_preferred":[
        "Chimbampo"
    ],
    "wof:name":"Chimbampo",
    "wof:placetype":"locality"
},
  "geometry": {"coordinates":[-109.83551,27.62651],"type":"Point"}
}