{
  "type": "Feature",
  "properties": {
    "gn:admin1_code":"8.0",
    "gn:admin2_code":"1.0",
    "gn:asciiname":"El Caminero",
    "gn:country_code":"MX",
    "gn:dem":15,
    "gn:feature_class":"P",
    "gn:feature_code":"PPL",
    "gn:name":"El Caminero",
    "gn:population":0,
    "gn:timezone":"America/Mexico_City",
    "iso:country":"MX",
    "name:spa_x_preferred":[
        "El Caminero"
    ],
    "wof:name":"El Caminero",
    "wof:placetype":"locality"
},
  "geometry": {"coordinates":[-104.05189,18.96547],"type":"Point"}
}