{
  "type": "Feature",
  "properties": {
    "gn:admin1_code":"31.0",
    "gn:asciiname":"Mexquituk",
    "gn:country_code":"MX",
    "gn:dem":138,
    "gn:feature_class":"P",
    "gn:feature_code":"PPL",
    "gn:name":"Mexquituk",
    "gn:population":0,
    "gn:timezone":"America/Merida",
    "iso:country":"MX",
    "name:spa_x_preferred":[
        "Mexquituk"
    ],
    "wof:name":"Mexquituk",
    "wof:placetype":"locality"
},
  "geometry": {"coordinates":[-89.34164,19.95239],"type":"Point"}
}