{
  "type": "Feature",
  "properties": {
    "gn:admin1_code":"13",
    "gn:admin2_code":"63",
    "gn:asciiname":"Lumbrera 19 (Barranca del Muerto)",
    "gn:country_code":"MX",
    "gn:dem":2234,
    "gn:feature_class":"P",
    "gn:feature_code":"PPL",
    "gn:name":"Lumbrera 19 (Barranca del Muerto)",
    "gn:population":12,
    "gn:timezone":"America/Mexico_City",
    "iso:country":"MX",
    "wof:name":"Lumbrera 19 (Barranca del Muerto)",
    "wof:placetype":"locality",
    "wof:population":12
},
  "geometry": {"coordinates":[-99.28028,19.91083],"type":"Point"}
}