{
  "type": "Feature",
  "properties": {
    "gn:admin1_code":"28.0",
    "gn:admin2_code":"42.0",
    "gn:asciiname":"El Realito",
    "gn:country_code":"MX",
    "gn:dem":316,
    "gn:feature_class":"P",
    "gn:feature_code":"PPL",
    "gn:name":"El Realito",
    "gn:population":0,
    "gn:timezone":"America/Monterrey",
    "iso:country":"MX",
    "name:spa_x_preferred":[
        "El Realito"
    ],
    "wof:name":"El Realito",
    "wof:placetype":"locality"
},
  "geometry": {"coordinates":[-99.31599,24.58583],"type":"Point"}
}