{
  "type": "Feature",
  "properties": {
    "gn:admin1_code":"16.0",
    "gn:admin2_code":"8.0",
    "gn:asciiname":"La Cofradia",
    "gn:country_code":"MX",
    "gn:dem":459,
    "gn:feature_class":"P",
    "gn:feature_code":"PPL",
    "gn:name":"La Cofrad\u00eda",
    "gn:population":0,
    "gn:timezone":"America/Mexico_City",
    "iso:country":"MX",
    "name:spa_x_preferred":[
        "La Cofrad\u00eda"
    ],
    "wof:name":"La Cofradia",
    "wof:placetype":"locality"
},
  "geometry": {"coordinates":[-103.22098,18.33347],"type":"Point"}
}