{
  "type": "Feature",
  "properties": {
    "gn:admin1_code":"32.0",
    "gn:admin2_code":"42.0",
    "gn:asciiname":"Gonzalez Ortega",
    "gn:country_code":"MX",
    "gn:dem":2210,
    "gn:feature_class":"P",
    "gn:feature_code":"PPL",
    "gn:name":"Gonz\u00e1lez Ortega",
    "gn:population":0,
    "gn:timezone":"America/Mexico_City",
    "iso:country":"MX",
    "name:spa_x_preferred":[
        "Gonz\u00e1lez Ortega"
    ],
    "name:und_x_variant":[
        "Colonia Ortega"
    ],
    "wof:name":"Gonzalez Ortega",
    "wof:placetype":"locality"
},
  "geometry": {"coordinates":[-103.4558,23.95976],"type":"Point"}
}