{
  "type": "Feature",
  "properties": {
    "gn:admin1_code":"23",
    "gn:admin2_code":"2.0",
    "gn:asciiname":"Chan Dzonot",
    "gn:country_code":"MX",
    "gn:dem":34,
    "gn:feature_class":"P",
    "gn:feature_code":"PPL",
    "gn:name":"Chan Dzonot",
    "gn:population":8,
    "gn:timezone":"America/Cancun",
    "iso:country":"MX",
    "wof:name":"Chan Dzonot",
    "wof:placetype":"locality",
    "wof:population":8
},
  "geometry": {"coordinates":[-88.35417,20.19194],"type":"Point"}
}