{
  "type": "Feature",
  "properties": {
    "gn:admin1_code":"4",
    "gn:admin2_code":"10.0",
    "gn:asciiname":"Nuevo Veracruz",
    "gn:country_code":"MX",
    "gn:dem":166,
    "gn:feature_class":"P",
    "gn:feature_code":"PPL",
    "gn:name":"Nuevo Veracruz",
    "gn:population":0,
    "gn:timezone":"America/Cancun",
    "iso:country":"MX",
    "name:spa_x_preferred":[
        "Nuevo Veracruz"
    ],
    "wof:name":"Nuevo Veracruz",
    "wof:placetype":"locality"
},
  "geometry": {"coordinates":[-89.17281,18.05659],"type":"Point"}
}