{
  "type": "Feature",
  "properties": {
    "gn:admin1_code":"13",
    "gn:admin2_code":"63.0",
    "gn:asciiname":"Vega de Madero",
    "gn:country_code":"MX",
    "gn:dem":2474,
    "gn:feature_class":"P",
    "gn:feature_code":"PPL",
    "gn:name":"Vega de Madero",
    "gn:population":0,
    "gn:timezone":"America/Mexico_City",
    "iso:country":"MX",
    "name:und_x_variant":[
        "La Vega",
        "Loma El Panal"
    ],
    "wof:name":"Vega de Madero",
    "wof:placetype":"locality"
},
  "geometry": {"coordinates":[-99.44145,19.90779],"type":"Point"}
}