{
  "type": "Feature",
  "properties": {
    "gn:admin1_code":"32.0",
    "gn:asciiname":"La Mulita",
    "gn:country_code":"MX",
    "gn:dem":2369,
    "gn:feature_class":"P",
    "gn:feature_code":"PPL",
    "gn:name":"La Mulita",
    "gn:population":0,
    "gn:timezone":"America/Mexico_City",
    "iso:country":"MX",
    "name:spa_x_preferred":[
        "La Mulita"
    ],
    "wof:name":"La Mulita",
    "wof:placetype":"locality"
},
  "geometry": {"coordinates":[-101.56462999999999,22.27815],"type":"Point"}
}