{
  "type": "Feature",
  "properties": {
    "gn:admin1_code":"15",
    "gn:admin2_code":"58.0",
    "gn:asciiname":"Nezahualcoyotl Segundo [Relleno Sanitario]",
    "gn:country_code":"MX",
    "gn:dem":2238,
    "gn:feature_class":"P",
    "gn:feature_code":"PPL",
    "gn:name":"Nezahualc\u00f3yotl Segundo [Relleno Sanitario]",
    "gn:population":64,
    "gn:timezone":"America/Mexico_City",
    "iso:country":"MX",
    "name:und_x_variant":[
        "Nezahualc\u00f3yotl Segundo [Relleno Sanitario]"
    ],
    "wof:name":"Nezahualcoyotl Segundo [Relleno Sanitario]",
    "wof:placetype":"locality",
    "wof:population":64
},
  "geometry": {"coordinates":[-99.00548000000001,19.42048],"type":"Point"}
}