{
  "type": "Feature",
  "properties": {
    "gn:admin1_code":"5.0",
    "gn:asciiname":"San Carlitos",
    "gn:country_code":"MX",
    "gn:dem":579,
    "gn:feature_class":"P",
    "gn:feature_code":"PPL",
    "gn:name":"San Carlitos",
    "gn:population":0,
    "gn:timezone":"America/Mexico_City",
    "iso:country":"MX",
    "name:spa_x_preferred":[
        "San Carlitos"
    ],
    "wof:name":"San Carlitos",
    "wof:placetype":"locality"
},
  "geometry": {"coordinates":[-92.25192,15.04729],"type":"Point"}
}