{
  "type": "Feature",
  "properties": {
    "gn:admin1_code":"25",
    "gn:admin2_code":"11.0",
    "gn:asciiname":"Doce de Octubre",
    "gn:country_code":"MX",
    "gn:dem":11,
    "gn:feature_class":"P",
    "gn:feature_code":"PPL",
    "gn:name":"Doce de Octubre",
    "gn:population":0,
    "gn:timezone":"America/Mazatlan",
    "iso:country":"MX",
    "name:spa_x_preferred":[
        "Doce de Octubre"
    ],
    "wof:name":"Doce de Octubre",
    "wof:placetype":"locality"
},
  "geometry": {"coordinates":[-108.63068,25.57849],"type":"Point"}
}