{
  "type": "Feature",
  "properties": {
    "gn:admin1_code":"14",
    "gn:admin2_code":"46",
    "gn:asciiname":"El Pesebre",
    "gn:country_code":"MX",
    "gn:dem":1816,
    "gn:feature_class":"P",
    "gn:feature_code":"PPL",
    "gn:name":"El Pesebre",
    "gn:population":14,
    "gn:timezone":"America/Mexico_City",
    "iso:country":"MX",
    "wof:name":"El Pesebre",
    "wof:placetype":"locality",
    "wof:population":14
},
  "geometry": {"coordinates":[-102.47750000000001,21.15167000000001],"type":"Point"}
}