{
  "type": "Feature",
  "properties": {
    "gn:admin1_code":"6",
    "gn:admin2_code":"40.0",
    "gn:asciiname":"Ancones de Arriba",
    "gn:country_code":"MX",
    "gn:dem":2158,
    "gn:feature_class":"P",
    "gn:feature_code":"PPL",
    "gn:name":"Ancones de Arriba",
    "gn:population":0,
    "gn:timezone":"America/Chihuahua",
    "iso:country":"MX",
    "name:spa_x_preferred":[
        "Ancones de Arriba"
    ],
    "wof:name":"Ancones de Arriba",
    "wof:placetype":"locality"
},
  "geometry": {"coordinates":[-108.24729000000001,29.70843],"type":"Point"}
}