{
  "type": "Feature",
  "properties": {
    "gn:admin1_code":"4",
    "gn:admin2_code":"4.0",
    "gn:asciiname":"Monte de Horeb",
    "gn:country_code":"MX",
    "gn:dem":95,
    "gn:feature_class":"P",
    "gn:feature_code":"PPL",
    "gn:name":"Monte de Horeb",
    "gn:population":7,
    "gn:timezone":"America/Merida",
    "iso:country":"MX",
    "wof:name":"Monte de Horeb",
    "wof:placetype":"locality",
    "wof:population":7
},
  "geometry": {"coordinates":[-90.4875,18.57417],"type":"Point"}
}