{
  "type": "Feature",
  "properties": {
    "gn:admin1_code":"26",
    "gn:admin2_code":"18.0",
    "gn:asciiname":"El Guamuchil",
    "gn:country_code":"MX",
    "gn:dem":51,
    "gn:feature_class":"P",
    "gn:feature_code":"PPL",
    "gn:name":"El Guamuchil",
    "gn:population":5,
    "gn:timezone":"America/Hermosillo",
    "iso:country":"MX",
    "wof:name":"El Guamuchil",
    "wof:placetype":"locality",
    "wof:population":5
},
  "geometry": {"coordinates":[-109.90139000000001,27.55222],"type":"Point"}
}