{
  "type": "Feature",
  "properties": {
    "gn:admin1_code":"24",
    "gn:admin2_code":"52.0",
    "gn:asciiname":"La Cardona",
    "gn:country_code":"MX",
    "gn:dem":1154,
    "gn:feature_class":"P",
    "gn:feature_code":"PPL",
    "gn:name":"La Cardona",
    "gn:population":0,
    "gn:timezone":"America/Mexico_City",
    "iso:country":"MX",
    "wof:name":"La Cardona",
    "wof:placetype":"locality"
},
  "geometry": {"coordinates":[-100.13728,22.39296],"type":"Point"}
}