{
  "type": "Feature",
  "properties": {
    "gn:admin1_code":"30",
    "gn:admin2_code":"70.0",
    "gn:asciiname":"El Compromiso",
    "gn:country_code":"MX",
    "gn:dem":26,
    "gn:feature_class":"P",
    "gn:feature_code":"PPL",
    "gn:name":"El Compromiso",
    "gn:population":0,
    "gn:timezone":"America/Mexico_City",
    "iso:country":"MX",
    "name:spa_x_preferred":[
        "El Compromiso"
    ],
    "wof:name":"El Compromiso",
    "wof:placetype":"locality"
},
  "geometry": {"coordinates":[-94.52213999999999,17.56796],"type":"Point"}
}