{
  "type": "Feature",
  "properties": {
    "gn:admin1_code":"31",
    "gn:admin2_code":"96.0",
    "gn:asciiname":"San Francisco Yohactun",
    "gn:country_code":"MX",
    "gn:dem":11,
    "gn:feature_class":"P",
    "gn:feature_code":"PPL",
    "gn:name":"San Francisco Yohact\u00fan",
    "gn:population":0,
    "gn:timezone":"America/Merida",
    "iso:country":"MX",
    "name:spa_x_preferred":[
        "San Francisco Yohact\u00fan"
    ],
    "name:spa_x_variant":[
        "San Francisco"
    ],
    "wof:name":"San Francisco Yohactun",
    "wof:placetype":"locality"
},
  "geometry": {"coordinates":[-87.92884000000002,21.43158],"type":"Point"}
}