{
  "type": "Feature",
  "properties": {
    "gn:admin1_code":"6.0",
    "gn:admin2_code":"31.0",
    "gn:asciiname":"La Cienega",
    "gn:cc2":"MX",
    "gn:country_code":"MX",
    "gn:dem":2245,
    "gn:feature_class":"P",
    "gn:feature_code":"PPL",
    "gn:name":"La Ci\u00e9nega",
    "gn:population":17,
    "gn:timezone":"America/Chihuahua",
    "iso:country":"MX",
    "name:ceb_x_preferred":[
        "La Cienega"
    ],
    "name:swe_x_preferred":[
        "La Cienega"
    ],
    "name:und_x_variant":[
        "Rancho Cienega",
        "Ci\u00e9nega"
    ],
    "wof:name":"La Cienega",
    "wof:placetype":"locality",
    "wof:population":17
},
  "geometry": {"coordinates":[-107.05522999999999,28.40056],"type":"Point"}
}