{
  "type": "Feature",
  "properties": {
    "gn:admin1_code":"15",
    "gn:admin2_code":"81",
    "gn:asciiname":"El Chivo [Relleno Sanitario Municipal]",
    "gn:country_code":"MX",
    "gn:dem":2304,
    "gn:feature_class":"P",
    "gn:feature_code":"PPL",
    "gn:name":"El Chivo [Relleno Sanitario Municipal]",
    "gn:population":31,
    "gn:timezone":"America/Mexico_City",
    "iso:country":"MX",
    "wof:name":"El Chivo [Relleno Sanitario Municipal]",
    "wof:placetype":"locality",
    "wof:population":31
},
  "geometry": {"coordinates":[-98.96767,19.78574],"type":"Point"}
}