{
  "type": "Feature",
  "properties": {
    "gn:admin1_code":"25",
    "gn:admin2_code":"10.0",
    "gn:asciiname":"Los Brasiles",
    "gn:country_code":"MX",
    "gn:dem":167,
    "gn:feature_class":"P",
    "gn:feature_code":"PPL",
    "gn:name":"Los Brasiles",
    "gn:population":0,
    "gn:timezone":"America/Mazatlan",
    "iso:country":"MX",
    "name:spa_x_preferred":[
        "Los Brasiles"
    ],
    "wof:name":"Los Brasiles",
    "wof:placetype":"locality"
},
  "geometry": {"coordinates":[-108.54286999999999,26.21827],"type":"Point"}
}