{
  "type": "Feature",
  "properties": {
    "gn:admin1_code":"30",
    "gn:admin2_code":"80",
    "gn:asciiname":"Ixviontla",
    "gn:country_code":"MX",
    "gn:dem":1676,
    "gn:feature_class":"P",
    "gn:feature_code":"PPL",
    "gn:name":"Ixviontla",
    "gn:population":49,
    "gn:timezone":"America/Mexico_City",
    "iso:country":"MX",
    "wof:name":"Ixviontla",
    "wof:placetype":"locality",
    "wof:population":49
},
  "geometry": {"coordinates":[-96.88722,19.02861],"type":"Point"}
}