{
  "type": "Feature",
  "properties": {
    "gn:admin1_code":"15",
    "gn:admin2_code":"68",
    "gn:asciiname":"Barrio Actopan",
    "gn:country_code":"MX",
    "gn:dem":2330,
    "gn:feature_class":"P",
    "gn:feature_code":"PPL",
    "gn:name":"Barrio Actopan",
    "gn:population":39,
    "gn:timezone":"America/Mexico_City",
    "iso:country":"MX",
    "wof:name":"Barrio Actopan",
    "wof:placetype":"locality",
    "wof:population":39
},
  "geometry": {"coordinates":[-98.80970000000001,19.03904],"type":"Point"}
}