{
  "type": "Feature",
  "properties": {
    "gn:admin1_code":"4",
    "gn:admin2_code":"3",
    "gn:asciiname":"Santa Lucia",
    "gn:country_code":"MX",
    "gn:dem":16,
    "gn:feature_class":"P",
    "gn:feature_code":"PPL",
    "gn:name":"Santa Luc\u00eda",
    "gn:population":14,
    "gn:timezone":"America/Merida",
    "iso:country":"MX",
    "name:und_x_variant":[
        "Santa Luc\u00eda"
    ],
    "wof:name":"Santa Lucia",
    "wof:placetype":"locality",
    "wof:population":14
},
  "geometry": {"coordinates":[-91.12417000000001,18.48],"type":"Point"}
}