{
  "type": "Feature",
  "properties": {
    "gn:admin1_code":"6",
    "gn:admin2_code":"53.0",
    "gn:asciiname":"Rancho Rodela",
    "gn:country_code":"MX",
    "gn:dem":1079,
    "gn:feature_class":"P",
    "gn:feature_code":"PPL",
    "gn:name":"Rancho Rodela",
    "gn:population":5,
    "gn:timezone":"America/Chihuahua",
    "iso:country":"MX",
    "wof:name":"Rancho Rodela",
    "wof:placetype":"locality",
    "wof:population":5
},
  "geometry": {"coordinates":[-105.99642,31.36529],"type":"Point"}
}