{
  "type": "Feature",
  "properties": {
    "gn:admin1_code":"19.0",
    "gn:admin2_code":"13.0",
    "gn:asciiname":"Los Novillos",
    "gn:country_code":"MX",
    "gn:dem":203,
    "gn:feature_class":"P",
    "gn:feature_code":"PPL",
    "gn:name":"Los Novillos",
    "gn:population":0,
    "gn:timezone":"America/Monterrey",
    "iso:country":"MX",
    "name:spa_x_preferred":[
        "Los Novillos"
    ],
    "wof:name":"Los Novillos",
    "wof:placetype":"locality"
},
  "geometry": {"coordinates":[-99.25416,25.45603],"type":"Point"}
}