{
  "type": "Feature",
  "properties": {
    "gn:admin1_code":"3",
    "gn:admin2_code":"2.0",
    "gn:asciiname":"Tata Viejo",
    "gn:country_code":"MX",
    "gn:dem":249,
    "gn:feature_class":"P",
    "gn:feature_code":"PPL",
    "gn:name":"Tata Viejo",
    "gn:population":8,
    "gn:timezone":"America/Mazatlan",
    "iso:country":"MX",
    "wof:name":"Tata Viejo",
    "wof:placetype":"locality",
    "wof:population":8
},
  "geometry": {"coordinates":[-112.7804,27.1474],"type":"Point"}
}