{
  "type": "Feature",
  "properties": {
    "gn:admin1_code":"24",
    "gn:admin2_code":"6",
    "gn:asciiname":"Desmontes de Catorce (Los Tahonitas)",
    "gn:country_code":"MX",
    "gn:dem":1766,
    "gn:feature_class":"P",
    "gn:feature_code":"PPL",
    "gn:name":"Desmontes de Catorce (Los Tahonitas)",
    "gn:population":14,
    "gn:timezone":"America/Mexico_City",
    "iso:country":"MX",
    "wof:name":"Desmontes de Catorce (Los Tahonitas)",
    "wof:placetype":"locality",
    "wof:population":14
},
  "geometry": {"coordinates":[-100.93083,23.81944],"type":"Point"}
}