{
  "type": "Feature",
  "properties": {
    "gn:admin1_code":"31",
    "gn:admin2_code":"32.0",
    "gn:asciiname":"Noha",
    "gn:cc2":"MX",
    "gn:country_code":"MX",
    "gn:dem":13,
    "gn:feature_class":"P",
    "gn:feature_code":"PPL",
    "gn:name":"Noha",
    "gn:population":0,
    "gn:timezone":"America/Merida",
    "iso:country":"MX",
    "name:ara_x_preferred":[
        "\u0646\u0647\u0649"
    ],
    "name:fas_x_preferred":[
        "\u0646\u0648\u062d\u0647"
    ],
    "name:snd_x_preferred":[
        "\u0627\u0648\u0633\u0627\u0631\u0627"
    ],
    "name:und_x_variant":[
        "Noh-ha",
        "Noha"
    ],
    "name:urd_x_preferred":[
        "\u0646\u0648\u062d\u06c1"
    ],
    "wof:name":"Noha",
    "wof:placetype":"locality"
},
  "geometry": {"coordinates":[-88.46666999999999,21.13333],"type":"Point"}
}