{
  "type": "Feature",
  "properties": {
    "gn:admin1_code":"30",
    "gn:admin2_code":"141.0",
    "gn:asciiname":"Juan Jacobo Torres [Bodega de Totontepec]",
    "gn:country_code":"MX",
    "gn:dem":40,
    "gn:feature_class":"P",
    "gn:feature_code":"PPL",
    "gn:name":"Juan Jacobo Torres [Bodega de Totontepec]",
    "gn:population":1734,
    "gn:timezone":"America/Mexico_City",
    "iso:country":"MX",
    "wof:name":"Juan Jacobo Torres [Bodega de Totontepec]",
    "wof:placetype":"locality",
    "wof:population":1734
},
  "geometry": {"coordinates":[-95.26033,18.33645],"type":"Point"}
}