{
  "type": "Feature",
  "properties": {
    "gn:admin1_code":"14",
    "gn:admin2_code":"61.0",
    "gn:asciiname":"Cabeza del Llano",
    "gn:country_code":"MX",
    "gn:dem":2177,
    "gn:feature_class":"P",
    "gn:feature_code":"PPL",
    "gn:name":"Cabeza del Llano",
    "gn:population":6,
    "gn:timezone":"America/Mexico_City",
    "iso:country":"MX",
    "wof:name":"Cabeza del Llano",
    "wof:placetype":"locality",
    "wof:population":6
},
  "geometry": {"coordinates":[-104.2925,22.33306],"type":"Point"}
}