{
  "type": "Feature",
  "properties": {
    "gn:admin1_code":"28",
    "gn:admin2_code":"1.0",
    "gn:asciiname":"Alfredo V. Bonfil Uno (Alfonso Ledezma)",
    "gn:country_code":"MX",
    "gn:dem":57,
    "gn:feature_class":"P",
    "gn:feature_code":"PPL",
    "gn:name":"Alfredo V. Bonfil Uno (Alfonso Ledezma)",
    "gn:population":7,
    "gn:timezone":"America/Monterrey",
    "iso:country":"MX",
    "wof:name":"Alfredo V. Bonfil Uno (Alfonso Ledezma)",
    "wof:placetype":"locality",
    "wof:population":7
},
  "geometry": {"coordinates":[-98.26528,24.0875],"type":"Point"}
}