{
  "type": "Feature",
  "properties": {
    "gn:admin1_code":"12",
    "gn:admin2_code":"29.0",
    "gn:asciiname":"Huacalapa",
    "gn:country_code":"MX",
    "gn:dem":2224,
    "gn:feature_class":"P",
    "gn:feature_code":"PPL",
    "gn:name":"Huacalapa",
    "gn:population":108,
    "gn:timezone":"America/Mexico_City",
    "iso:country":"MX",
    "wof:name":"Huacalapa",
    "wof:placetype":"locality",
    "wof:population":108
},
  "geometry": {"coordinates":[-99.6174,17.47919],"type":"Point"}
}