{
  "type": "Feature",
  "properties": {
    "gn:admin1_code":"13",
    "gn:admin2_code":"52.0",
    "gn:asciiname":"Barrio el Dajie",
    "gn:country_code":"MX",
    "gn:dem":2227,
    "gn:feature_class":"P",
    "gn:feature_code":"PPL",
    "gn:name":"Barrio el Dajie",
    "gn:population":525,
    "gn:timezone":"America/Mexico_City",
    "iso:country":"MX",
    "wof:name":"Barrio el Dajie",
    "wof:placetype":"locality",
    "wof:population":525
},
  "geometry": {"coordinates":[-98.93583,20.12417],"type":"Point"}
}