{
  "type": "Feature",
  "properties": {
    "gn:admin1_code":"2",
    "gn:admin2_code":"4",
    "gn:asciiname":"Rancho Ruiz",
    "gn:country_code":"MX",
    "gn:dem":223,
    "gn:feature_class":"P",
    "gn:feature_code":"PPL",
    "gn:name":"Rancho Ruiz",
    "gn:population":11,
    "gn:timezone":"America/Tijuana",
    "iso:country":"MX",
    "wof:name":"Rancho Ruiz",
    "wof:placetype":"locality",
    "wof:population":11
},
  "geometry": {"coordinates":[-116.78888999999999,32.48667],"type":"Point"}
}