{
  "type": "Feature",
  "properties": {
    "gn:admin1_code":"6",
    "gn:admin2_code":"9.0",
    "gn:asciiname":"Talayotes (Talayotes de los Volcanes)",
    "gn:country_code":"MX",
    "gn:dem":2322,
    "gn:feature_class":"P",
    "gn:feature_code":"PPL",
    "gn:name":"Talayotes (Talayotes de los Volcanes)",
    "gn:population":113,
    "gn:timezone":"America/Chihuahua",
    "iso:country":"MX",
    "wof:name":"Talayotes (Talayotes de los Volcanes)",
    "wof:placetype":"locality",
    "wof:population":113
},
  "geometry": {"coordinates":[-107.81139,27.91917],"type":"Point"}
}