{
  "type": "Feature",
  "properties": {
    "gn:admin1_code":"13",
    "gn:admin2_code":"53",
    "gn:asciiname":"Loma Larga",
    "gn:country_code":"MX",
    "gn:dem":1412,
    "gn:feature_class":"P",
    "gn:feature_code":"PPL",
    "gn:name":"Loma Larga",
    "gn:population":31,
    "gn:timezone":"America/Mexico_City",
    "iso:country":"MX",
    "wof:name":"Loma Larga",
    "wof:placetype":"locality",
    "wof:population":31
},
  "geometry": {"coordinates":[-98.27972,20.44917],"type":"Point"}
}