{
  "type": "Feature",
  "properties": {
    "gn:admin1_code":"28.0",
    "gn:admin2_code":"32.0",
    "gn:asciiname":"La Brisa",
    "gn:country_code":"MX",
    "gn:dem":91,
    "gn:feature_class":"P",
    "gn:feature_code":"PPL",
    "gn:name":"La Brisa",
    "gn:population":0,
    "gn:timezone":"America/Matamoros",
    "iso:country":"MX",
    "name:spa_x_preferred":[
        "La Brisa"
    ],
    "wof:name":"La Brisa",
    "wof:placetype":"locality"
},
  "geometry": {"coordinates":[-98.48721999999999,26.03689],"type":"Point"}
}