{
  "type": "Feature",
  "properties": {
    "gn:admin1_code":"19",
    "gn:admin2_code":"6.0",
    "gn:asciiname":"El Venado (Grupo Libra)",
    "gn:country_code":"MX",
    "gn:dem":448,
    "gn:feature_class":"P",
    "gn:feature_code":"PPL",
    "gn:name":"El Venado (Grupo Libra)",
    "gn:population":6,
    "gn:timezone":"America/Monterrey",
    "iso:country":"MX",
    "wof:name":"El Venado (Grupo Libra)",
    "wof:placetype":"locality",
    "wof:population":6
},
  "geometry": {"coordinates":[-100.24337,25.84588],"type":"Point"}
}