{
  "type": "Feature",
  "properties": {
    "gn:admin1_code":"14",
    "gn:admin2_code":"35.0",
    "gn:asciiname":"Rancho de Abajo",
    "gn:country_code":"MX",
    "gn:dem":1999,
    "gn:feature_class":"P",
    "gn:feature_code":"PPL",
    "gn:name":"Rancho de Abajo",
    "gn:population":229,
    "gn:timezone":"America/Mexico_City",
    "iso:country":"MX",
    "wof:name":"Rancho de Abajo",
    "wof:placetype":"locality",
    "wof:population":229
},
  "geometry": {"coordinates":[-102.02028,21.65639],"type":"Point"}
}