{
  "type": "Feature",
  "properties": {
    "gn:admin1_code":"1",
    "gn:admin2_code":"1.0",
    "gn:asciiname":"El Refugio I",
    "gn:country_code":"MX",
    "gn:dem":1935,
    "gn:feature_class":"P",
    "gn:feature_code":"PPL",
    "gn:name":"El Refugio I",
    "gn:population":6,
    "gn:timezone":"America/Mexico_City",
    "iso:country":"MX",
    "wof:name":"El Refugio I",
    "wof:placetype":"locality",
    "wof:population":6
},
  "geometry": {"coordinates":[-102.22722,21.80278],"type":"Point"}
}