{
  "type": "Feature",
  "properties": {
    "gn:admin1_code":"20.0",
    "gn:admin2_code":"325.0",
    "gn:asciiname":"Cerro Culebra",
    "gn:country_code":"MX",
    "gn:dem":1736,
    "gn:feature_class":"P",
    "gn:feature_code":"PPL",
    "gn:name":"Cerro Culebra",
    "gn:population":0,
    "gn:timezone":"America/Mexico_City",
    "iso:country":"MX",
    "name:spa_x_preferred":[
        "Cerro Culebra"
    ],
    "wof:name":"Cerro Culebra",
    "wof:placetype":"locality"
},
  "geometry": {"coordinates":[-96.03615000000001,16.87314],"type":"Point"}
}