{
  "type": "Feature",
  "properties": {
    "gn:admin1_code":"22",
    "gn:admin2_code":"4.0",
    "gn:asciiname":"Los Maqueda",
    "gn:country_code":"MX",
    "gn:dem":2168,
    "gn:feature_class":"P",
    "gn:feature_code":"PPL",
    "gn:name":"Los Maqueda",
    "gn:population":363,
    "gn:timezone":"America/Mexico_City",
    "iso:country":"MX",
    "name:spa_x_preferred":[
        "Los Maqueda"
    ],
    "name:und_x_variant":[
        "San Francisco de los Marqueda"
    ],
    "wof:name":"Los Maqueda",
    "wof:placetype":"locality",
    "wof:population":363
},
  "geometry": {"coordinates":[-99.74111000000001,20.7075],"type":"Point"}
}