{
  "type": "Feature",
  "properties": {
    "gn:admin1_code":"5",
    "gn:admin2_code":"31.0",
    "gn:asciiname":"El Eden",
    "gn:country_code":"MX",
    "gn:dem":1254,
    "gn:feature_class":"P",
    "gn:feature_code":"PPL",
    "gn:name":"El Ed\u00e9n",
    "gn:population":290,
    "gn:timezone":"America/Mexico_City",
    "iso:country":"MX",
    "name:und_x_variant":[
        "El Ed\u00e9n"
    ],
    "wof:name":"El Eden",
    "wof:placetype":"locality",
    "wof:population":290
},
  "geometry": {"coordinates":[-92.25476,16.98109],"type":"Point"}
}