{
  "type": "Feature",
  "properties": {
    "gn:country":"MX",
    "gn:fcode":"PPL",
    "gn:population":0,
    "iso:country":"MX",
    "name:und_x_variant":[
        "Bondoyito"
    ],
    "qs_pg:aaroncc":"MX",
    "qs_pg:gn_country":"MX",
    "qs_pg:gn_fcode":"PPL",
    "qs_pg:gn_pop":0,
    "qs_pg:name":"Bondojito",
    "qs_pg:name_adm0":"M\u00e9xico",
    "qs_pg:name_adm1":"Hidalgo",
    "qs_pg:photos_9r":0,
    "qs_pg:photos_sr":0,
    "qs_pg:pop_sr":0,
    "qs_pg:qs_pg_placetype":"locality",
    "qs_pg:qs_pg_placetype_gp":"Town",
    "qs_pg:woe_adm0":23424900,
    "woe:adm0_id":23424900,
    "woe:name_adm0":"M\u00e9xico",
    "woe:name_adm1":"Hidalgo",
    "woe:placetype":"Town",
    "wof:name":"Bondojito",
    "wof:placetype":"locality"
},
  "geometry": {"coordinates":[-99.69777000000001,20.44331],"type":"Point"}
}