{
  "type": "Feature",
  "properties": {
    "gn:admin1_code":"6",
    "gn:admin2_code":"29",
    "gn:asciiname":"Las Crucesitas",
    "gn:country_code":"MX",
    "gn:dem":2675,
    "gn:feature_class":"P",
    "gn:feature_code":"PPL",
    "gn:name":"Las Crucesitas",
    "gn:population":10,
    "gn:timezone":"America/Chihuahua",
    "iso:country":"MX",
    "wof:name":"Las Crucesitas",
    "wof:placetype":"locality",
    "wof:population":10
},
  "geometry": {"coordinates":[-107.05929999999999,26.02996],"type":"Point"}
}