{
  "type": "Feature",
  "properties": {
    "gn:admin1_code":"5",
    "gn:admin2_code":"16.0",
    "gn:asciiname":"Cuyo Alvaro Obregon",
    "gn:country_code":"MX",
    "gn:dem":9,
    "gn:feature_class":"P",
    "gn:feature_code":"PPL",
    "gn:name":"Cuyo \u00c1lvaro Obreg\u00f3n",
    "gn:population":0,
    "gn:timezone":"America/Mexico_City",
    "iso:country":"MX",
    "wof:name":"Cuyo Alvaro Obregon",
    "wof:placetype":"locality"
},
  "geometry": {"coordinates":[-92.00069999999999,17.84914],"type":"Point"}
}