{
  "type": "Feature",
  "properties": {
    "gn:admin1_code":"14.0",
    "gn:admin2_code":"96.0",
    "gn:asciiname":"El Refugio",
    "gn:country_code":"MX",
    "gn:dem":1769,
    "gn:feature_class":"P",
    "gn:feature_code":"PPL",
    "gn:name":"El Refugio",
    "gn:population":372,
    "gn:timezone":"America/Mexico_City",
    "iso:country":"MX",
    "wof:name":"El Refugio",
    "wof:placetype":"locality",
    "wof:population":372
},
  "geometry": {"coordinates":[-103.14516,20.12231],"type":"Point"}
}