{
  "type": "Feature",
  "properties": {
    "gn:admin1_code":"16",
    "gn:admin2_code":"55",
    "gn:asciiname":"Crucero de Carrera de Mata",
    "gn:country_code":"MX",
    "gn:dem":227,
    "gn:feature_class":"P",
    "gn:feature_code":"PPL",
    "gn:name":"Crucero de Carrera de Mata",
    "gn:population":10,
    "gn:timezone":"America/Mexico_City",
    "iso:country":"MX",
    "wof:name":"Crucero de Carrera de Mata",
    "wof:placetype":"locality",
    "wof:population":10
},
  "geometry": {"coordinates":[-102.12611,18.88083],"type":"Point"}
}