{
  "type": "Feature",
  "properties": {
    "gn:admin1_code":"6",
    "gn:admin2_code":"17.0",
    "gn:asciiname":"Campo Numero Veintiuno",
    "gn:country_code":"MX",
    "gn:dem":2002,
    "gn:feature_class":"P",
    "gn:feature_code":"PPL",
    "gn:name":"Campo N\u00famero Veintiuno",
    "gn:population":244,
    "gn:timezone":"America/Chihuahua",
    "iso:country":"MX",
    "name:und_x_variant":[
        "Campo N\u00famero Veintiuno"
    ],
    "wof:name":"Campo Numero Veintiuno",
    "wof:placetype":"locality",
    "wof:population":244
},
  "geometry": {"coordinates":[-106.85722,28.49167000000001],"type":"Point"}
}