{
  "type": "Feature",
  "properties": {
    "iso:country":"MX",
    "qs_pg:aaroncc":"MX",
    "qs_pg:name":"Fracc Juan Pablo Ii",
    "qs_pg:name_adm0":"M\u00e9xico",
    "qs_pg:name_adm1":"Yucatan",
    "qs_pg:photos":170,
    "qs_pg:photos_1k":34,
    "qs_pg:photos_9k":1,
    "qs_pg:photos_9r":4,
    "qs_pg:photos_all":170,
    "qs_pg:photos_sr":4,
    "qs_pg:pop_sr":0,
    "qs_pg:qs_pg_placetype":"neighbourhood",
    "qs_pg:qs_pg_placetype_gp":"Suburb",
    "qs_pg:woe_adm0":23424900,
    "woe:adm0_id":23424900,
    "woe:name_adm0":"M\u00e9xico",
    "woe:name_adm1":"Yucatan",
    "woe:placetype":"Suburb",
    "wof:name":"Fracc Juan Pablo Ii",
    "wof:placetype":"neighbourhood"
},
  "geometry": {"coordinates":[-89.01427700000001,20.932573],"type":"Point"}
}