{
  "type": "Feature",
  "properties": {
    "gn:admin1_code":"1",
    "gn:admin2_code":"1.0",
    "gn:asciiname":"Cabecita 3 Marias (Rancho Nuevo)",
    "gn:country_code":"MX",
    "gn:dem":1914,
    "gn:feature_class":"P",
    "gn:feature_code":"PPL",
    "gn:name":"Cabecita 3 Mar\u00edas (Rancho Nuevo)",
    "gn:population":184,
    "gn:timezone":"America/Mexico_City",
    "iso:country":"MX",
    "name:und_x_variant":[
        "Cabecita 3 Mar\u00edas (Rancho Nuevo)"
    ],
    "wof:name":"Cabecita 3 Marias (Rancho Nuevo)",
    "wof:placetype":"locality",
    "wof:population":184
},
  "geometry": {"coordinates":[-102.41306,21.77472],"type":"Point"}
}