{
  "type": "Feature",
  "properties": {
    "gn:admin1_code":"21.0",
    "gn:admin2_code":"128.0",
    "gn:asciiname":"Macondo",
    "gn:country_code":"MX",
    "gn:dem":2360,
    "gn:feature_class":"P",
    "gn:feature_code":"PPL",
    "gn:name":"Macondo",
    "gn:population":0,
    "gn:timezone":"America/Mexico_City",
    "iso:country":"MX",
    "name:spa_x_preferred":[
        "Macondo"
    ],
    "wof:name":"Macondo",
    "wof:placetype":"locality"
},
  "geometry": {"coordinates":[-97.72305,19.22923],"type":"Point"}
}