{
  "type": "Feature",
  "properties": {
    "gn:admin1_code":"21.0",
    "gn:admin2_code":"128.0",
    "gn:asciiname":"Macondo",
    "gn:country_code":"MX",
    "gn:dem":2360,
    "gn:feature_class":"P",
    "gn:feature_code":"PPL",
    "gn:name":"Macondo",
    "gn:population":0,
    "gn:timezone":"America/Mexico_City",
    "iso:country":"MX",
    "name:ara_x_preferred":[
        "\u0645\u0627\u0643\u0648\u0646\u062f\u0648"
    ],
    "name:bos_x_preferred":[
        "Macondo"
    ],
    "name:bul_x_preferred":[
        "\u041c\u0430\u043a\u043e\u043d\u0434\u043e"
    ],
    "name:cat_x_preferred":[
        "Macondo"
    ],
    "name:epo_x_preferred":[
        "Macondo"
    ],
    "name:eus_x_preferred":[
        "Macondo"
    ],
    "name:fas_x_preferred":[
        "\u0645\u0627\u06a9\u0648\u0646\u062f\u0648"
    ],
    "name:fin_x_preferred":[
        "Macondo"
    ],
    "name:fra_x_preferred":[
        "Macondo"
    ],
    "name:heb_x_preferred":[
        "\u05de\u05e7\u05d5\u05e0\u05d3\u05d5"
    ],
    "name:hrv_x_preferred":[
        "Macondo"
    ],
    "name:hun_x_preferred":[
        "Macondo"
    ],
    "name:hye_x_preferred":[
        "\u0544\u0561\u056f\u0578\u0576\u0564\u0578"
    ],
    "name:jpn_x_preferred":[
        "\u30de\u30b3\u30f3\u30c9"
    ],
    "name:pol_x_preferred":[
        "Macondo"
    ],
    "name:por_x_preferred":[
        "Macondo"
    ],
    "name:spa_x_preferred":[
        "Macondo"
    ],
    "name:zho_x_preferred":[
        "\u9a6c\u8d21\u591a"
    ],
    "wof:name":"Macondo",
    "wof:placetype":"locality"
},
  "geometry": {"coordinates":[-97.72305,19.22923],"type":"Point"}
}