{
  "type": "Feature",
  "properties": {
    "gn:admin1_code":"26",
    "gn:admin2_code":"30.0",
    "gn:asciiname":"La Primavera [Vivero]",
    "gn:country_code":"MX",
    "gn:dem":289,
    "gn:feature_class":"P",
    "gn:feature_code":"PPL",
    "gn:name":"La Primavera [Vivero]",
    "gn:population":5,
    "gn:timezone":"America/Hermosillo",
    "iso:country":"MX",
    "wof:name":"La Primavera [Vivero]",
    "wof:placetype":"locality",
    "wof:population":5
},
  "geometry": {"coordinates":[-110.88443999999998,29.28222],"type":"Point"}
}