{
  "type": "Feature",
  "properties": {
    "gn:admin1_code":"5",
    "gn:admin2_code":"17.0",
    "gn:asciiname":"Gracias a Dios",
    "gn:country_code":"MX",
    "gn:dem":1013,
    "gn:feature_class":"P",
    "gn:feature_code":"PPL",
    "gn:name":"Gracias a Dios",
    "gn:population":75,
    "gn:timezone":"America/Mexico_City",
    "iso:country":"MX",
    "wof:name":"Gracias a Dios",
    "wof:placetype":"locality",
    "wof:population":75
},
  "geometry": {"coordinates":[-93.79778,16.51917000000001],"type":"Point"}
}