{
  "type": "Feature",
  "properties": {
    "gn:admin1_code":"24.0",
    "gn:admin2_code":"33.0",
    "gn:asciiname":"La Larga",
    "gn:country_code":"MX",
    "gn:dem":1968,
    "gn:feature_class":"P",
    "gn:feature_code":"PPL",
    "gn:name":"La Larga",
    "gn:population":0,
    "gn:timezone":"America/Mexico_City",
    "iso:country":"MX",
    "name:spa_x_preferred":[
        "La Larga"
    ],
    "wof:name":"La Larga",
    "wof:placetype":"locality"
},
  "geometry": {"coordinates":[-102.155,23.17898],"type":"Point"}
}