{
  "type": "Feature",
  "properties": {
    "gn:admin1_code":"16",
    "gn:admin2_code":"99.0",
    "gn:asciiname":"El Paso de la Virgen",
    "gn:country_code":"MX",
    "gn:dem":615,
    "gn:feature_class":"P",
    "gn:feature_code":"PPL",
    "gn:name":"El Paso de la Virgen",
    "gn:population":249,
    "gn:timezone":"America/Mexico_City",
    "iso:country":"MX",
    "wof:name":"El Paso de la Virgen",
    "wof:placetype":"locality",
    "wof:population":249
},
  "geometry": {"coordinates":[-100.56111,19.22722000000001],"type":"Point"}
}