{
  "type": "Feature",
  "properties": {
    "gn:admin1_code":"26",
    "gn:admin2_code":"29.0",
    "gn:asciiname":"La Cuadrita",
    "gn:country_code":"MX",
    "gn:dem":10,
    "gn:feature_class":"P",
    "gn:feature_code":"PPL",
    "gn:name":"La Cuadrita",
    "gn:population":181,
    "gn:timezone":"America/Hermosillo",
    "iso:country":"MX",
    "name:spa_x_preferred":[
        "La Cuadrita"
    ],
    "wof:name":"La Cuadrita",
    "wof:placetype":"locality",
    "wof:population":181
},
  "geometry": {"coordinates":[-110.88916999999999,28.00417],"type":"Point"}
}