{
  "type": "Feature",
  "properties": {
    "gn:admin1_code":"26.0",
    "gn:admin2_code":"29.0",
    "gn:asciiname":"La Bandera Uno",
    "gn:country_code":"MX",
    "gn:dem":88,
    "gn:feature_class":"P",
    "gn:feature_code":"PPL",
    "gn:name":"La Bandera Uno",
    "gn:population":0,
    "gn:timezone":"America/Hermosillo",
    "iso:country":"MX",
    "name:spa_x_preferred":[
        "La Bandera Uno"
    ],
    "wof:name":"La Bandera Uno",
    "wof:placetype":"locality"
},
  "geometry": {"coordinates":[-111.06113999999999,28.30755],"type":"Point"}
}