{
  "type": "Feature",
  "properties": {
    "gn:admin1_code":"15.0",
    "gn:asciiname":"La Milpillera",
    "gn:country_code":"MX",
    "gn:dem":385,
    "gn:feature_class":"P",
    "gn:feature_code":"PPL",
    "gn:name":"La Milpillera",
    "gn:population":0,
    "gn:timezone":"America/Mexico_City",
    "iso:country":"MX",
    "name:spa_x_preferred":[
        "La Milpillera"
    ],
    "wof:name":"La Milpillera",
    "wof:placetype":"locality"
},
  "geometry": {"coordinates":[-102.3805,18.16178],"type":"Point"}
}