{
  "type": "Feature",
  "properties": {
    "gn:admin1_code":"16",
    "gn:admin2_code":"13.0",
    "gn:asciiname":"El Escorpion",
    "gn:country_code":"MX",
    "gn:dem":825,
    "gn:feature_class":"P",
    "gn:feature_code":"PPL",
    "gn:name":"El Escorpi\u00f3n",
    "gn:population":8,
    "gn:timezone":"America/Mexico_City",
    "iso:country":"MX",
    "name:und_x_variant":[
        "El Escorpi\u00f3n"
    ],
    "wof:name":"El Escorpion",
    "wof:placetype":"locality",
    "wof:population":8
},
  "geometry": {"coordinates":[-101.07583,19.11972],"type":"Point"}
}