{
  "type": "Feature",
  "properties": {
    "gn:admin1_code":"27",
    "gn:admin2_code":"4.0",
    "gn:asciiname":"Tierra Amarilla 3ra. Seccion",
    "gn:country_code":"MX",
    "gn:dem":9,
    "gn:feature_class":"P",
    "gn:feature_code":"PPL",
    "gn:name":"Tierra Amarilla 3ra. Secci\u00f3n",
    "gn:population":984,
    "gn:timezone":"America/Mexico_City",
    "iso:country":"MX",
    "name:und_x_variant":[
        "Tierra Amarilla 3ra. Secci\u00f3n"
    ],
    "wof:name":"Tierra Amarilla 3ra. Seccion",
    "wof:placetype":"locality",
    "wof:population":984
},
  "geometry": {"coordinates":[-92.89806,18.06556],"type":"Point"}
}