{
  "type": "Feature",
  "properties": {
    "gn:admin1_code":"16",
    "gn:admin2_code":"67",
    "gn:asciiname":"La Laborcilla",
    "gn:country_code":"MX",
    "gn:dem":1706,
    "gn:feature_class":"P",
    "gn:feature_code":"PPL",
    "gn:name":"La Laborcilla",
    "gn:population":50,
    "gn:timezone":"America/Mexico_City",
    "iso:country":"MX",
    "wof:name":"La Laborcilla",
    "wof:placetype":"locality",
    "wof:population":50
},
  "geometry": {"coordinates":[-101.86083000000001,20.21],"type":"Point"}
}