{
  "type": "Feature",
  "properties": {
    "gn:admin1_code":"10",
    "gn:admin2_code":"14.0",
    "gn:asciiname":"Los Armadillos",
    "gn:country_code":"MX",
    "gn:dem":1769,
    "gn:feature_class":"P",
    "gn:feature_code":"PPL",
    "gn:name":"Los Armadillos",
    "gn:population":7,
    "gn:timezone":"America/Monterrey",
    "iso:country":"MX",
    "wof:name":"Los Armadillos",
    "wof:placetype":"locality",
    "wof:population":7
},
  "geometry": {"coordinates":[-104.82080000000001,22.80642000000001],"type":"Point"}
}