{
  "type": "Feature",
  "properties": {
    "gn:admin1_code":"7",
    "gn:admin2_code":"7.0",
    "gn:asciiname":"Poza la Becerra",
    "gn:country_code":"MX",
    "gn:dem":767,
    "gn:feature_class":"P",
    "gn:feature_code":"PPL",
    "gn:name":"Poza la Becerra",
    "gn:population":0,
    "gn:timezone":"America/Monterrey",
    "iso:country":"MX",
    "name:spa_x_preferred":[
        "Poza la Becerra"
    ],
    "name:und_x_variant":[
        "La Becerra",
        "Pozo de la Becerra"
    ],
    "wof:name":"Poza la Becerra",
    "wof:placetype":"locality"
},
  "geometry": {"coordinates":[-102.13782999999999,26.87779],"type":"Point"}
}