{
  "type": "Feature",
  "properties": {
    "gn:admin1_code":"6.0",
    "gn:admin2_code":"29.0",
    "gn:asciiname":"La Cueva",
    "gn:country_code":"MX",
    "gn:dem":1753,
    "gn:feature_class":"P",
    "gn:feature_code":"PPL",
    "gn:name":"La Cueva",
    "gn:population":0,
    "gn:timezone":"America/Chihuahua",
    "iso:country":"MX",
    "name:und_x_variant":[
        "Cueva",
        "La Cueva"
    ],
    "wof:name":"La Cueva",
    "wof:placetype":"locality"
},
  "geometry": {"coordinates":[-107.34653,26.62052000000001],"type":"Point"}
}