{
  "type": "Feature",
  "properties": {
    "gn:admin1_code":"11",
    "gn:admin2_code":"30.0",
    "gn:asciiname":"La Laguna del Sapo",
    "gn:country_code":"MX",
    "gn:dem":2478,
    "gn:feature_class":"P",
    "gn:feature_code":"PPL",
    "gn:name":"La Laguna del Sapo",
    "gn:population":7,
    "gn:timezone":"America/Mexico_City",
    "iso:country":"MX",
    "wof:name":"La Laguna del Sapo",
    "wof:placetype":"locality",
    "wof:population":7
},
  "geometry": {"coordinates":[-101.41806,21.30167],"type":"Point"}
}