{
  "type": "Feature",
  "properties": {
    "gn:admin1_code":"30",
    "gn:admin2_code":"144.0",
    "gn:asciiname":"Cidonio Contreras",
    "gn:country_code":"MX",
    "gn:dem":101,
    "gn:feature_class":"P",
    "gn:feature_code":"PPL",
    "gn:name":"Cidonio Contreras",
    "gn:population":8,
    "gn:timezone":"America/Mexico_City",
    "iso:country":"MX",
    "wof:name":"Cidonio Contreras",
    "wof:placetype":"locality",
    "wof:population":8
},
  "geometry": {"coordinates":[-94.99083,17.90417],"type":"Point"}
}