{
  "type": "Feature",
  "properties": {
    "gn:admin1_code":"5.0",
    "gn:admin2_code":"32.0",
    "gn:asciiname":"Las Luces",
    "gn:country_code":"MX",
    "gn:dem":887,
    "gn:feature_class":"P",
    "gn:feature_code":"PPL",
    "gn:name":"Las Luces",
    "gn:population":0,
    "gn:timezone":"America/Mexico_City",
    "iso:country":"MX",
    "name:spa_x_preferred":[
        "Las Luces"
    ],
    "wof:name":"Las Luces",
    "wof:placetype":"locality"
},
  "geometry": {"coordinates":[-92.51864999999999,15.36572],"type":"Point"}
}