{
  "type": "Feature",
  "properties": {
    "gn:admin1_code":"5",
    "gn:admin2_code":"26.0",
    "gn:asciiname":"Canolal",
    "gn:country_code":"MX",
    "gn:dem":1467,
    "gn:feature_class":"P",
    "gn:feature_code":"PPL",
    "gn:name":"Canolal",
    "gn:population":783,
    "gn:timezone":"America/Mexico_City",
    "iso:country":"MX",
    "wof:name":"Canolal",
    "wof:placetype":"locality",
    "wof:population":783
},
  "geometry": {"coordinates":[-92.51639,17.0175],"type":"Point"}
}