{
  "type": "Feature",
  "properties": {
    "gn:admin1_code":"17",
    "gn:admin2_code":"29",
    "gn:asciiname":"El Rocio",
    "gn:country_code":"MX",
    "gn:dem":1191,
    "gn:feature_class":"P",
    "gn:feature_code":"PPL",
    "gn:name":"El Roc\u00edo",
    "gn:population":49,
    "gn:timezone":"America/Mexico_City",
    "iso:country":"MX",
    "name:und_x_variant":[
        "El Roc\u00edo"
    ],
    "wof:name":"El Rocio",
    "wof:placetype":"locality",
    "wof:population":49
},
  "geometry": {"coordinates":[-99.07722,18.85306],"type":"Point"}
}