{
  "type": "Feature",
  "properties": {
    "gn:admin1_code":"11",
    "gn:admin2_code":"31.0",
    "gn:asciiname":"El Ranchito",
    "gn:country_code":"MX",
    "gn:dem":1835,
    "gn:feature_class":"P",
    "gn:feature_code":"PPL",
    "gn:name":"El Ranchito",
    "gn:population":8,
    "gn:timezone":"America/Mexico_City",
    "iso:country":"MX",
    "wof:name":"El Ranchito",
    "wof:placetype":"locality",
    "wof:population":8
},
  "geometry": {"coordinates":[-101.76361,20.85861],"type":"Point"}
}