{
  "type": "Feature",
  "properties": {
    "gn:admin1_code":"12",
    "gn:admin2_code":"1.0",
    "gn:asciiname":"San Andres Playa Encantada (El Podrido)",
    "gn:country_code":"MX",
    "gn:dem":5,
    "gn:feature_class":"P",
    "gn:feature_code":"PPL",
    "gn:name":"San Andr\u00e9s Playa Encantada (El Podrido)",
    "gn:population":1333,
    "gn:timezone":"America/Mexico_City",
    "iso:country":"MX",
    "name:und_x_variant":[
        "San Andr\u00e9s Playa Encantada (El Podrido)"
    ],
    "wof:name":"San Andres Playa Encantada (El Podrido)",
    "wof:placetype":"locality",
    "wof:population":1333
},
  "geometry": {"coordinates":[-99.63388999999999,16.69222],"type":"Point"}
}