{
  "type": "Feature",
  "properties": {
    "gn:admin1_code":"10.0",
    "gn:admin2_code":"7.0",
    "gn:asciiname":"Villa Gregorio Garcia",
    "gn:country_code":"MX",
    "gn:dem":1114,
    "gn:feature_class":"P",
    "gn:feature_code":"PPL",
    "gn:name":"Villa Gregorio Garc\u00eda",
    "gn:population":0,
    "gn:timezone":"America/Monterrey",
    "iso:country":"MX",
    "name:spa_x_preferred":[
        "Gregorio Garc\u00eda"
    ],
    "name:spa_x_variant":[
        "Villa Gregorio Garc\u00eda"
    ],
    "wof:name":"Villa Gregorio Garcia",
    "wof:placetype":"locality"
},
  "geometry": {"coordinates":[-103.35214999999999,25.75221],"type":"Point"}
}