{
  "type": "Feature",
  "properties": {
    "gn:admin1_code":"30",
    "gn:admin2_code":"108.0",
    "gn:asciiname":"Sitio Viejo",
    "gn:country_code":"MX",
    "gn:dem":13,
    "gn:feature_class":"P",
    "gn:feature_code":"PPL",
    "gn:name":"Sitio Viejo",
    "gn:population":0,
    "gn:timezone":"America/Mexico_City",
    "iso:country":"MX",
    "name:spa_x_preferred":[
        "Sitio Viejo"
    ],
    "wof:name":"Sitio Viejo",
    "wof:placetype":"locality"
},
  "geometry": {"coordinates":[-94.49189,17.91491],"type":"Point"}
}