{
  "type": "Feature",
  "properties": {
    "gn:admin1_code":"25.0",
    "gn:asciiname":"Los Mimbritos",
    "gn:country_code":"MX",
    "gn:dem":275,
    "gn:feature_class":"P",
    "gn:feature_code":"PPL",
    "gn:name":"Los Mimbritos",
    "gn:population":0,
    "gn:timezone":"America/Mazatlan",
    "iso:country":"MX",
    "name:spa_x_preferred":[
        "Los Mimbritos"
    ],
    "wof:name":"Los Mimbritos",
    "wof:placetype":"locality"
},
  "geometry": {"coordinates":[-106.95701,24.63964],"type":"Point"}
}