{
  "type": "Feature",
  "properties": {
    "gn:admin1_code":"24",
    "gn:admin2_code":"29.0",
    "gn:asciiname":"El Caballito",
    "gn:country_code":"MX",
    "gn:dem":103,
    "gn:feature_class":"P",
    "gn:feature_code":"PPL",
    "gn:name":"El Caballito",
    "gn:population":0,
    "gn:timezone":"America/Mexico_City",
    "iso:country":"MX",
    "name:spa_x_preferred":[
        "El Caballito"
    ],
    "wof:name":"El Caballito",
    "wof:placetype":"locality"
},
  "geometry": {"coordinates":[-98.55486000000001,21.48415],"type":"Point"}
}