{
  "type": "Feature",
  "properties": {
    "gn:admin1_code":"20",
    "gn:admin2_code":"413",
    "gn:asciiname":"Llano Ciruelo (Samaria)",
    "gn:country_code":"MX",
    "gn:dem":169,
    "gn:feature_class":"P",
    "gn:feature_code":"PPL",
    "gn:name":"Llano Ciruelo (Samaria)",
    "gn:population":36,
    "gn:timezone":"America/Mexico_City",
    "iso:country":"MX",
    "wof:name":"Llano Ciruelo (Samaria)",
    "wof:placetype":"locality",
    "wof:population":36
},
  "geometry": {"coordinates":[-96.30444,15.79861],"type":"Point"}
}