{
  "type": "Feature",
  "properties": {
    "gn:admin1_code":"10.0",
    "gn:admin2_code":"1.0",
    "gn:asciiname":"Los Aniegos",
    "gn:country_code":"MX",
    "gn:dem":1930,
    "gn:feature_class":"P",
    "gn:feature_code":"PPL",
    "gn:name":"Los Aniegos",
    "gn:population":0,
    "gn:timezone":"America/Monterrey",
    "iso:country":"MX",
    "name:spa_x_preferred":[
        "Los Aniegos"
    ],
    "wof:name":"Los Aniegos",
    "wof:placetype":"locality"
},
  "geometry": {"coordinates":[-104.71454,24.46593],"type":"Point"}
}