{
  "type": "Feature",
  "properties": {
    "gn:admin1_code":"23",
    "gn:admin2_code":"6.0",
    "gn:asciiname":"San Felipe Primero",
    "gn:country_code":"MX",
    "gn:dem":34,
    "gn:feature_class":"P",
    "gn:feature_code":"PPL",
    "gn:name":"San Felipe Primero",
    "gn:population":703,
    "gn:timezone":"America/Cancun",
    "iso:country":"MX",
    "wof:name":"San Felipe Primero",
    "wof:placetype":"locality",
    "wof:population":703
},
  "geometry": {"coordinates":[-88.83278,19.81278],"type":"Point"}
}