{
  "type": "Feature",
  "properties": {
    "gn:admin1_code":"20",
    "gn:admin2_code":"229.0",
    "gn:asciiname":"Rio de Talea",
    "gn:country_code":"MX",
    "gn:dem":1869,
    "gn:feature_class":"P",
    "gn:feature_code":"PPL",
    "gn:name":"R\u00edo de Talea",
    "gn:population":484,
    "gn:timezone":"America/Mexico_City",
    "iso:country":"MX",
    "name:und_x_variant":[
        "R\u00edo de Talea"
    ],
    "wof:name":"Rio de Talea",
    "wof:placetype":"locality",
    "wof:population":484
},
  "geometry": {"coordinates":[-97.16194,16.50861],"type":"Point"}
}