{
  "type": "Feature",
  "properties": {
    "gn:admin1_code":"26.0",
    "gn:admin2_code":"26.0",
    "gn:asciiname":"Culacatecapo",
    "gn:country_code":"MX",
    "gn:dem":28,
    "gn:feature_class":"P",
    "gn:feature_code":"PPL",
    "gn:name":"Culacatecapo",
    "gn:population":0,
    "gn:timezone":"America/Hermosillo",
    "iso:country":"MX",
    "wof:name":"Culacatecapo",
    "wof:placetype":"locality"
},
  "geometry": {"coordinates":[-109.61667,27.03333],"type":"Point"}
}