{
  "type": "Feature",
  "properties": {
    "gn:admin1_code":"6",
    "gn:admin2_code":"35.0",
    "gn:asciiname":"Punta de la Sierra",
    "gn:country_code":"MX",
    "gn:dem":1479,
    "gn:feature_class":"P",
    "gn:feature_code":"PPL",
    "gn:name":"Punta de la Sierra",
    "gn:population":0,
    "gn:timezone":"America/Chihuahua",
    "iso:country":"MX",
    "name:spa_x_preferred":[
        "Punta de la Sierra"
    ],
    "name:und_x_variant":[
        "Los Mimbres",
        "Punta de Sierra"
    ],
    "wof:name":"Punta de la Sierra",
    "wof:placetype":"locality"
},
  "geometry": {"coordinates":[-108.61991,31.20105],"type":"Point"}
}