{
  "type": "Feature",
  "properties": {
    "gn:admin1_code":"2",
    "gn:admin2_code":"3.0",
    "gn:asciiname":"La Zacatosa",
    "gn:country_code":"MX",
    "gn:dem":1293,
    "gn:feature_class":"P",
    "gn:feature_code":"PPL",
    "gn:name":"La Zacatosa",
    "gn:population":0,
    "gn:timezone":"America/Tijuana",
    "iso:country":"MX",
    "name:spa_x_preferred":[
        "La Zacatosa"
    ],
    "name:und_x_variant":[
        "Rancho La Zacatosa"
    ],
    "wof:name":"La Zacatosa",
    "wof:placetype":"locality"
},
  "geometry": {"coordinates":[-116.17622,32.45734],"type":"Point"}
}