{
  "type": "Feature",
  "properties": {
    "gn:admin1_code":"5",
    "gn:admin2_code":"57.0",
    "gn:asciiname":"El Horizonte (Santa Elena)",
    "gn:country_code":"MX",
    "gn:dem":619,
    "gn:feature_class":"P",
    "gn:feature_code":"PPL",
    "gn:name":"El Horizonte (Santa Elena)",
    "gn:population":107,
    "gn:timezone":"America/Mexico_City",
    "iso:country":"MX",
    "wof:name":"El Horizonte (Santa Elena)",
    "wof:placetype":"locality",
    "wof:population":107
},
  "geometry": {"coordinates":[-92.38861,15.27889],"type":"Point"}
}