{
  "type": "Feature",
  "properties": {
    "gn:admin1_code":"12.0",
    "gn:admin2_code":"48.0",
    "gn:asciiname":"Chaveta",
    "gn:country_code":"MX",
    "gn:dem":144,
    "gn:feature_class":"P",
    "gn:feature_code":"PPL",
    "gn:name":"Chaveta",
    "gn:population":0,
    "gn:timezone":"America/Mexico_City",
    "iso:country":"MX",
    "name:und_x_variant":[
        "Chavela",
        "Chuveta",
        "Chayeta",
        "Chaveta"
    ],
    "wof:name":"Chaveta",
    "wof:placetype":"locality"
},
  "geometry": {"coordinates":[-101.38471,17.69629],"type":"Point"}
}