{
  "type": "Feature",
  "properties": {
    "gn:admin1_code":"14.0",
    "gn:admin2_code":"116.0",
    "gn:asciiname":"La Barrosa",
    "gn:country_code":"MX",
    "gn:dem":2061,
    "gn:feature_class":"P",
    "gn:feature_code":"PPL",
    "gn:name":"La Barrosa",
    "gn:population":0,
    "gn:timezone":"America/Mexico_City",
    "iso:country":"MX",
    "name:spa_x_preferred":[
        "La Barrosa"
    ],
    "wof:name":"La Barrosa",
    "wof:placetype":"locality"
},
  "geometry": {"coordinates":[-102.63799,21.72301],"type":"Point"}
}