{
  "type": "Feature",
  "properties": {
    "gn:admin1_code":"2",
    "gn:admin2_code":"4.0",
    "gn:asciiname":"Familia Munoz",
    "gn:country_code":"MX",
    "gn:dem":232,
    "gn:feature_class":"P",
    "gn:feature_code":"PPL",
    "gn:name":"Familia Mu\u00f1oz",
    "gn:population":4,
    "gn:timezone":"America/Tijuana",
    "iso:country":"MX",
    "name:und_x_variant":[
        "Familia Mu\u00f1oz"
    ],
    "wof:name":"Familia Munoz",
    "wof:placetype":"locality",
    "wof:population":4
},
  "geometry": {"coordinates":[-116.76639,32.54555999999999],"type":"Point"}
}