{
  "type": "Feature",
  "properties": {
    "gn:admin1_code":"8",
    "gn:admin2_code":"9",
    "gn:asciiname":"Rancho W",
    "gn:country_code":"MX",
    "gn:dem":28,
    "gn:feature_class":"P",
    "gn:feature_code":"PPL",
    "gn:name":"Rancho W",
    "gn:population":9,
    "gn:timezone":"America/Mexico_City",
    "iso:country":"MX",
    "wof:name":"Rancho W",
    "wof:placetype":"locality",
    "wof:population":9
},
  "geometry": {"coordinates":[-103.89583,18.89444],"type":"Point"}
}