{
  "type": "Feature",
  "properties": {
    "gn:admin1_code":"6",
    "gn:admin2_code":"67.0",
    "gn:asciiname":"Agostadero de Abajo",
    "gn:country_code":"MX",
    "gn:dem":1436,
    "gn:feature_class":"P",
    "gn:feature_code":"PPL",
    "gn:name":"Agostadero de Abajo",
    "gn:population":0,
    "gn:timezone":"America/Chihuahua",
    "iso:country":"MX",
    "name:spa_x_preferred":[
        "Agostadero de Abajo"
    ],
    "wof:name":"Agostadero de Abajo",
    "wof:placetype":"locality"
},
  "geometry": {"coordinates":[-105.90510999999999,27.51688],"type":"Point"}
}