{
  "type": "Feature",
  "properties": {
    "gn:admin1_code":"10",
    "gn:admin2_code":"35.0",
    "gn:asciiname":"San Isidro de las Calabazas (Las Calabazas)",
    "gn:country_code":"MX",
    "gn:dem":2380,
    "gn:feature_class":"P",
    "gn:feature_code":"PPL",
    "gn:name":"San Isidro de las Calabazas (Las Calabazas)",
    "gn:population":57,
    "gn:timezone":"America/Monterrey",
    "iso:country":"MX",
    "wof:name":"San Isidro de las Calabazas (Las Calabazas)",
    "wof:placetype":"locality",
    "wof:population":57
},
  "geometry": {"coordinates":[-105.95256999999999,25.21108],"type":"Point"}
}