{
  "type": "Feature",
  "properties": {
    "gn:admin1_code":"14",
    "gn:admin2_code":"69.0",
    "gn:asciiname":"Cuesta del Burro",
    "gn:country_code":"MX",
    "gn:dem":1012,
    "gn:feature_class":"P",
    "gn:feature_code":"PPL",
    "gn:name":"Cuesta del Burro",
    "gn:population":8,
    "gn:timezone":"America/Mexico_City",
    "iso:country":"MX",
    "wof:name":"Cuesta del Burro",
    "wof:placetype":"locality",
    "wof:population":8
},
  "geometry": {"coordinates":[-102.83278,19.69194],"type":"Point"}
}