{
  "type": "Feature",
  "properties": {
    "gn:admin1_code":"32",
    "gn:admin2_code":"9",
    "gn:asciiname":"Los Tamayo",
    "gn:country_code":"MX",
    "gn:dem":2313,
    "gn:feature_class":"P",
    "gn:feature_code":"PPL",
    "gn:name":"Los Tamayo",
    "gn:population":48,
    "gn:timezone":"America/Mexico_City",
    "iso:country":"MX",
    "wof:name":"Los Tamayo",
    "wof:placetype":"locality",
    "wof:population":48
},
  "geometry": {"coordinates":[-103.87555999999999,23.48444],"type":"Point"}
}