{
  "type": "Feature",
  "properties": {
    "gn:admin1_code":"30",
    "gn:admin2_code":"173.0",
    "gn:asciiname":"Ursulo Galvan",
    "gn:country_code":"MX",
    "gn:dem":887,
    "gn:feature_class":"P",
    "gn:feature_code":"PPL",
    "gn:name":"\u00darsulo Galv\u00e1n",
    "gn:population":223,
    "gn:timezone":"America/Mexico_City",
    "iso:country":"MX",
    "name:und_x_variant":[
        "\u00darsulo Galv\u00e1n"
    ],
    "wof:name":"Ursulo Galvan",
    "wof:placetype":"locality",
    "wof:population":223
},
  "geometry": {"coordinates":[-96.76306,18.59417],"type":"Point"}
}