{
  "type": "Feature",
  "properties": {
    "gn:admin1_code":"30.0",
    "gn:admin2_code":"202.0",
    "gn:asciiname":"Tenango",
    "gn:country_code":"MX",
    "gn:dem":588,
    "gn:feature_class":"P",
    "gn:feature_code":"PPL",
    "gn:name":"Tenango",
    "gn:population":8,
    "gn:timezone":"America/Mexico_City",
    "iso:country":"MX",
    "name:ceb_x_preferred":[
        "Tenango"
    ],
    "name:deu_x_preferred":[
        "Tenango"
    ],
    "name:sco_x_preferred":[
        "Tenango"
    ],
    "name:spa_x_preferred":[
        "Tenango"
    ],
    "name:srp_x_preferred":[
        "\u0422\u0435\u043d\u0430\u043d\u0433\u043e"
    ],
    "name:swe_x_preferred":[
        "Tenango"
    ],
    "wof:name":"Tenango",
    "wof:placetype":"locality",
    "wof:population":8
},
  "geometry": {"coordinates":[-98.31028000000001,20.78528],"type":"Point"}
}