{
  "type": "Feature",
  "properties": {
    "gn:admin1_code":"6",
    "gn:admin2_code":"66.0",
    "gn:asciiname":"Batapilillas",
    "gn:country_code":"MX",
    "gn:dem":980,
    "gn:feature_class":"P",
    "gn:feature_code":"PPL",
    "gn:name":"Batapilillas",
    "gn:population":0,
    "gn:timezone":"America/Chihuahua",
    "iso:country":"MX",
    "name:spa_x_preferred":[
        "Batapilillas"
    ],
    "name:und_x_variant":[
        "Batopilitas",
        "Batopilillas"
    ],
    "wof:name":"Batapilillas",
    "wof:placetype":"locality"
},
  "geometry": {"coordinates":[-108.4452,27.89312],"type":"Point"}
}