{
  "type": "Feature",
  "properties": {
    "gn:admin1_code":"20.0",
    "gn:admin2_code":"515.0",
    "gn:asciiname":"Rincon Viejo",
    "gn:country_code":"MX",
    "gn:dem":125,
    "gn:feature_class":"P",
    "gn:feature_code":"PPL",
    "gn:name":"Rinc\u00f3n Viejo",
    "gn:population":0,
    "gn:timezone":"America/Mexico_City",
    "iso:country":"MX",
    "name:spa_x_preferred":[
        "Rinc\u00f3n Viejo"
    ],
    "wof:name":"Rincon Viejo",
    "wof:placetype":"locality"
},
  "geometry": {"coordinates":[-95.32462,16.24435],"type":"Point"}
}