{
  "type": "Feature",
  "properties": {
    "gn:admin1_code":"5.0",
    "gn:asciiname":"Nuestra Senora",
    "gn:country_code":"MX",
    "gn:dem":644,
    "gn:feature_class":"P",
    "gn:feature_code":"PPL",
    "gn:name":"Nuestra Se\u00f1ora",
    "gn:population":0,
    "gn:timezone":"America/Mexico_City",
    "iso:country":"MX",
    "name:spa_x_preferred":[
        "Nuestra Se\u00f1ora"
    ],
    "wof:name":"Nuestra Senora",
    "wof:placetype":"locality"
},
  "geometry": {"coordinates":[-92.88800000000001,15.944],"type":"Point"}
}