{
  "type": "Feature",
  "properties": {
    "iso:country":"MX",
    "name:spa_x_preferred":[
        "Centro"
    ],
    "name:unk_x_variant":[
        "Centro"
    ],
    "qs:gn_adm0_cc":"MX",
    "qs:gn_fcode":"PPL",
    "qs:gn_local":4005539,
    "qs:gn_nam_loc":"Guadalajara, Guadalajara, Jalisco, MX",
    "qs:gn_namadm1":"32",
    "qs:gn_name":"Centro",
    "qs:local_max":6158,
    "qs:local_sum":19156,
    "qs:localhoods":41,
    "qs:name":"Centro",
    "qs:name_adm0":"M\u00e9xico",
    "qs:name_adm1":"Jalisco",
    "qs:name_adm2":"Guadalajara",
    "qs:name_local":"Guadalajara",
    "qs:photo_max":156,
    "qs:photo_sum":224,
    "qs:placetype":"Suburb",
    "qs:quad_count":3,
    "qs:woe_adm0":23424900,
    "qs:woe_adm1":2346277,
    "qs:woe_adm2":12600236,
    "qs:woe_lau":0,
    "qs:woe_local":124162,
    "qs:woe_ver":"7.10.0",
    "wof:lang":[
        "spa"
    ],
    "wof:name":"Centro",
    "wof:placetype":"neighbourhood"
},
  "geometry": {"coordinates":[-103.35059,20.687981],"type":"Point"}
}