{
  "type": "Feature",
  "properties": {
    "gn:admin1_code":"15",
    "gn:admin2_code":"47.0",
    "gn:asciiname":"Ejido de Mani",
    "gn:country_code":"MX",
    "gn:dem":2575,
    "gn:feature_class":"P",
    "gn:feature_code":"PPL",
    "gn:name":"Ejido de Ma\u00f1i",
    "gn:population":943,
    "gn:timezone":"America/Mexico_City",
    "iso:country":"MX",
    "wof:name":"Ejido de Mani",
    "wof:placetype":"locality",
    "wof:population":943
},
  "geometry": {"coordinates":[-99.66722,19.56333],"type":"Point"}
}