{
  "type": "Feature",
  "properties": {
    "gn:admin1_code":"24.0",
    "gn:admin2_code":"8.0",
    "gn:asciiname":"El Sauz",
    "gn:country_code":"MX",
    "gn:dem":1274,
    "gn:feature_class":"P",
    "gn:feature_code":"PPL",
    "gn:name":"El Sauz",
    "gn:population":468,
    "gn:timezone":"America/Mexico_City",
    "iso:country":"MX",
    "name:und_x_variant":[
        "Sauz",
        "Sauza",
        "El Sauz"
    ],
    "wof:name":"El Sauz",
    "wof:placetype":"locality",
    "wof:population":468
},
  "geometry": {"coordinates":[-100.23058,22.52732],"type":"Point"}
}