{
  "type": "Feature",
  "properties": {
    "gn:admin1_code":"11.0",
    "gn:asciiname":"Ejido de Don Diego",
    "gn:country_code":"MX",
    "gn:dem":1861,
    "gn:feature_class":"P",
    "gn:feature_code":"PPL",
    "gn:name":"Ejido de Don Diego",
    "gn:population":0,
    "gn:timezone":"America/Mexico_City",
    "iso:country":"MX",
    "name:spa_x_preferred":[
        "Ejido de Don Diego"
    ],
    "name:spa_x_variant":[
        "Presa la Cantera"
    ],
    "wof:name":"Ejido de Don Diego",
    "wof:placetype":"locality"
},
  "geometry": {"coordinates":[-100.77409,20.89292],"type":"Point"}
}