{
  "type": "Feature",
  "properties": {
    "gn:admin1_code":"26",
    "gn:admin2_code":"18.0",
    "gn:asciiname":"Cutabanco",
    "gn:country_code":"MX",
    "gn:dem":28,
    "gn:feature_class":"P",
    "gn:feature_code":"PPL",
    "gn:name":"Cutabanco",
    "gn:population":0,
    "gn:timezone":"America/Hermosillo",
    "iso:country":"MX",
    "name:spa_x_preferred":[
        "Cutabanco"
    ],
    "wof:name":"Cutabanco",
    "wof:placetype":"locality"
},
  "geometry": {"coordinates":[-110.00757,27.55975],"type":"Point"}
}