{
  "type": "Feature",
  "properties": {
    "gn:admin1_code":"5",
    "gn:admin2_code":"52.0",
    "gn:asciiname":"Nuevo Santo Tomas",
    "gn:country_code":"MX",
    "gn:dem":319,
    "gn:feature_class":"P",
    "gn:feature_code":"PPL",
    "gn:name":"Nuevo Santo Tom\u00e1s",
    "gn:population":519,
    "gn:timezone":"America/Mexico_City",
    "iso:country":"MX",
    "name:und_x_variant":[
        "Nuevo Santo Tom\u00e1s"
    ],
    "wof:name":"Nuevo Santo Tomas",
    "wof:placetype":"locality",
    "wof:population":519
},
  "geometry": {"coordinates":[-91.41028,16.20333],"type":"Point"}
}