{
  "type": "Feature",
  "properties": {
    "gn:admin1_code":"30.0",
    "gn:admin2_code":"151.0",
    "gn:asciiname":"La Palmasola",
    "gn:country_code":"MX",
    "gn:dem":172,
    "gn:feature_class":"P",
    "gn:feature_code":"PPL",
    "gn:name":"La Palmasola",
    "gn:population":0,
    "gn:timezone":"America/Mexico_City",
    "iso:country":"MX",
    "name:spa_x_preferred":[
        "La Palmasola"
    ],
    "wof:name":"La Palmasola",
    "wof:placetype":"locality"
},
  "geometry": {"coordinates":[-97.67572,21.24307],"type":"Point"}
}