{
  "type": "Feature",
  "properties": {
    "gn:admin1_code":"8.0",
    "gn:admin2_code":"5.0",
    "gn:asciiname":"El Ramalazo",
    "gn:country_code":"MX",
    "gn:dem":1033,
    "gn:feature_class":"P",
    "gn:feature_code":"PPL",
    "gn:name":"El Ramalazo",
    "gn:population":0,
    "gn:timezone":"America/Mexico_City",
    "iso:country":"MX",
    "name:spa_x_preferred":[
        "El Ramalazo"
    ],
    "name:und_x_variant":[
        "El Pamalazo"
    ],
    "wof:name":"El Ramalazo",
    "wof:placetype":"locality"
},
  "geometry": {"coordinates":[-103.58405999999999,19.34399],"type":"Point"}
}