{
  "type": "Feature",
  "properties": {
    "gn:admin1_code":"3.0",
    "gn:admin2_code":"1.0",
    "gn:asciiname":"El Horno",
    "gn:country_code":"MX",
    "gn:dem":315,
    "gn:feature_class":"P",
    "gn:feature_code":"PPL",
    "gn:name":"El Horno",
    "gn:population":0,
    "gn:timezone":"America/Mazatlan",
    "iso:country":"MX",
    "name:spa_x_preferred":[
        "El Horno"
    ],
    "wof:name":"El Horno",
    "wof:placetype":"locality"
},
  "geometry": {"coordinates":[-111.76260000000001,26.28462],"type":"Point"}
}