{
  "type": "Feature",
  "properties": {
    "gn:admin1_code":"20",
    "gn:admin2_code":"184.0",
    "gn:asciiname":"Arroyo Seco",
    "gn:country_code":"MX",
    "gn:dem":62,
    "gn:feature_class":"P",
    "gn:feature_code":"PPL",
    "gn:name":"Arroyo Seco",
    "gn:population":0,
    "gn:timezone":"America/Mexico_City",
    "iso:country":"MX",
    "name:spa_x_preferred":[
        "Arroyo Seco"
    ],
    "wof:name":"Arroyo Seco",
    "wof:placetype":"locality"
},
  "geometry": {"coordinates":[-96.03111,18.07667],"type":"Point"}
}