{
  "type": "Feature",
  "properties": {
    "gn:admin1_code":"30",
    "gn:admin2_code":"32.0",
    "gn:asciiname":"San Juan Seco de Valencia",
    "gn:country_code":"MX",
    "gn:dem":408,
    "gn:feature_class":"P",
    "gn:feature_code":"PPL",
    "gn:name":"San Juan Seco de Valencia",
    "gn:population":0,
    "gn:timezone":"America/Mexico_City",
    "iso:country":"MX",
    "name:spa_x_preferred":[
        "San Juan Seco de Valencia"
    ],
    "name:spa_x_variant":[
        "Tres Chorros"
    ],
    "wof:name":"San Juan Seco de Valencia",
    "wof:placetype":"locality"
},
  "geometry": {"coordinates":[-95.15604999999999,18.30946],"type":"Point"}
}