{
  "type": "Feature",
  "properties": {
    "gn:admin1_code":"10",
    "gn:admin2_code":"5.0",
    "gn:asciiname":"Santiago Bayacora",
    "gn:country_code":"MX",
    "gn:dem":1895,
    "gn:feature_class":"P",
    "gn:feature_code":"PPL",
    "gn:name":"Santiago Bayacora",
    "gn:population":0,
    "gn:timezone":"America/Monterrey",
    "iso:country":"MX",
    "name:und_x_variant":[
        "Bay\u00e1cora",
        "Santiago Bayacora"
    ],
    "wof:name":"Santiago Bayacora",
    "wof:placetype":"locality"
},
  "geometry": {"coordinates":[-104.61275999999999,23.89373],"type":"Point"}
}