{
  "type": "Feature",
  "properties": {
    "gn:admin1_code":"2",
    "gn:admin2_code":"1.0",
    "gn:asciiname":"Valle Dorado",
    "gn:country_code":"MX",
    "gn:dem":35,
    "gn:feature_class":"P",
    "gn:feature_code":"PPL",
    "gn:name":"Valle Dorado",
    "gn:population":479,
    "gn:timezone":"America/Tijuana",
    "iso:country":"MX",
    "wof:name":"Valle Dorado",
    "wof:placetype":"locality",
    "wof:population":479
},
  "geometry": {"coordinates":[-115.925,30.55056],"type":"Point"}
}