{
  "type": "Feature",
  "properties": {
    "gn:admin1_code":"20",
    "gn:admin2_code":"421.0",
    "gn:asciiname":"La Cantera",
    "gn:country_code":"MX",
    "gn:dem":81,
    "gn:feature_class":"P",
    "gn:feature_code":"PPL",
    "gn:name":"La Cantera",
    "gn:population":74,
    "gn:timezone":"America/Mexico_City",
    "iso:country":"MX",
    "wof:name":"La Cantera",
    "wof:placetype":"locality",
    "wof:population":74
},
  "geometry": {"coordinates":[-95.27222,16.37472],"type":"Point"}
}