{
  "type": "Feature",
  "properties": {
    "gn:admin1_code":"26.0",
    "gn:admin2_code":"35.0",
    "gn:asciiname":"La Bellota",
    "gn:country_code":"MX",
    "gn:dem":1056,
    "gn:feature_class":"P",
    "gn:feature_code":"PPL",
    "gn:name":"La Bellota",
    "gn:population":3,
    "gn:timezone":"America/Hermosillo",
    "iso:country":"MX",
    "wof:name":"La Bellota",
    "wof:placetype":"locality",
    "wof:population":3
},
  "geometry": {"coordinates":[-110.59833,30.93028],"type":"Point"}
}