{
  "type": "Feature",
  "properties": {
    "gn:admin1_code":"21",
    "gn:admin2_code":"195.0",
    "gn:asciiname":"Hijadero",
    "gn:country_code":"MX",
    "gn:dem":2639,
    "gn:feature_class":"P",
    "gn:feature_code":"PPL",
    "gn:name":"Hijadero",
    "gn:population":88,
    "gn:timezone":"America/Mexico_City",
    "iso:country":"MX",
    "wof:name":"Hijadero",
    "wof:placetype":"locality",
    "wof:population":88
},
  "geometry": {"coordinates":[-97.18049000000001,18.56129],"type":"Point"}
}