{
  "type": "Feature",
  "properties": {
    "gn:admin1_code":"25.0",
    "gn:admin2_code":"10.0",
    "gn:asciiname":"Tetarobita",
    "gn:country_code":"MX",
    "gn:dem":171,
    "gn:feature_class":"P",
    "gn:feature_code":"PPL",
    "gn:name":"Tetarobita",
    "gn:population":0,
    "gn:timezone":"America/Mazatlan",
    "iso:country":"MX",
    "name:spa_x_preferred":[
        "Tetarobita"
    ],
    "wof:name":"Tetarobita",
    "wof:placetype":"locality"
},
  "geometry": {"coordinates":[-108.48271,26.38846],"type":"Point"}
}