{
  "type": "Feature",
  "properties": {
    "gn:admin1_code":"16",
    "gn:admin2_code":"96",
    "gn:asciiname":"La Tigra",
    "gn:country_code":"MX",
    "gn:dem":438,
    "gn:feature_class":"P",
    "gn:feature_code":"PPL",
    "gn:name":"La Tigra",
    "gn:population":12,
    "gn:timezone":"America/Mexico_City",
    "iso:country":"MX",
    "wof:name":"La Tigra",
    "wof:placetype":"locality",
    "wof:population":12
},
  "geometry": {"coordinates":[-102.76389,18.435],"type":"Point"}
}