{
  "type": "Feature",
  "properties": {
    "gn:admin1_code":"4",
    "gn:admin2_code":"3.0",
    "gn:asciiname":"El Arca",
    "gn:country_code":"MX",
    "gn:dem":7,
    "gn:feature_class":"P",
    "gn:feature_code":"PPL",
    "gn:name":"El Arca",
    "gn:population":302,
    "gn:timezone":"America/Merida",
    "iso:country":"MX",
    "wof:name":"El Arca",
    "wof:placetype":"locality",
    "wof:population":302
},
  "geometry": {"coordinates":[-90.90971999999999,18.90056],"type":"Point"}
}