{
  "type": "Feature",
  "properties": {
    "gn:admin1_code":"25",
    "gn:admin2_code":"15.0",
    "gn:asciiname":"Cruz Blanca",
    "gn:country_code":"MX",
    "gn:dem":16,
    "gn:feature_class":"P",
    "gn:feature_code":"PPL",
    "gn:name":"Cruz Blanca",
    "gn:population":538,
    "gn:timezone":"America/Mazatlan",
    "iso:country":"MX",
    "wof:name":"Cruz Blanca",
    "wof:placetype":"locality",
    "wof:population":538
},
  "geometry": {"coordinates":[-108.27388999999999,25.45028],"type":"Point"}
}