{
  "type": "Feature",
  "properties": {
    "gn:admin1_code":"25.0",
    "gn:admin2_code":"11.0",
    "gn:asciiname":"Ejido Tecomate",
    "gn:country_code":"MX",
    "gn:dem":18,
    "gn:feature_class":"P",
    "gn:feature_code":"PPL",
    "gn:name":"Ejido Tecomate",
    "gn:population":0,
    "gn:timezone":"America/Mazatlan",
    "iso:country":"MX",
    "name:spa_x_preferred":[
        "Las Gu\u00e1simas"
    ],
    "name:spa_x_variant":[
        "Ejido Tecomate"
    ],
    "name:und_x_variant":[
        "Gu\u00e1simas"
    ],
    "wof:name":"Ejido Tecomate",
    "wof:placetype":"locality"
},
  "geometry": {"coordinates":[-108.52754,25.58423],"type":"Point"}
}