{
  "type": "Feature",
  "properties": {
    "gn:admin1_code":"16",
    "gn:admin2_code":"81.0",
    "gn:asciiname":"Genguaro",
    "gn:country_code":"MX",
    "gn:dem":1842,
    "gn:feature_class":"P",
    "gn:feature_code":"PPL",
    "gn:name":"Genguaro",
    "gn:population":95,
    "gn:timezone":"America/Mexico_City",
    "iso:country":"MX",
    "wof:name":"Genguaro",
    "wof:placetype":"locality",
    "wof:population":95
},
  "geometry": {"coordinates":[-100.37166999999999,19.29417],"type":"Point"}
}