{
  "type": "Feature",
  "properties": {
    "gn:admin1_code":"26",
    "gn:admin2_code":"68.0",
    "gn:asciiname":"San Enrique",
    "gn:country_code":"MX",
    "gn:dem":620,
    "gn:feature_class":"P",
    "gn:feature_code":"PPL",
    "gn:name":"San Enrique",
    "gn:population":1,
    "gn:timezone":"America/Hermosillo",
    "iso:country":"MX",
    "name:spa_x_preferred":[
        "San Enrique"
    ],
    "wof:name":"San Enrique",
    "wof:placetype":"locality",
    "wof:population":1
},
  "geometry": {"coordinates":[-110.01416999999999,29.00667],"type":"Point"}
}