{
  "type": "Feature",
  "properties": {
    "gn:admin1_code":"16",
    "gn:admin2_code":"15",
    "gn:asciiname":"El Tarasco",
    "gn:country_code":"MX",
    "gn:dem":784,
    "gn:feature_class":"P",
    "gn:feature_code":"PPL",
    "gn:name":"El Tarasco",
    "gn:population":12,
    "gn:timezone":"America/Mexico_City",
    "iso:country":"MX",
    "wof:name":"El Tarasco",
    "wof:placetype":"locality",
    "wof:population":12
},
  "geometry": {"coordinates":[-103.21722,18.61417],"type":"Point"}
}