{
  "type": "Feature",
  "properties": {
    "gn:admin1_code":"7.0",
    "gn:admin2_code":"30.0",
    "gn:asciiname":"El Chiflon",
    "gn:country_code":"MX",
    "gn:dem":1370,
    "gn:feature_class":"P",
    "gn:feature_code":"PPL",
    "gn:name":"El Chifl\u00f3n",
    "gn:population":0,
    "gn:timezone":"America/Monterrey",
    "iso:country":"MX",
    "name:spa_x_preferred":[
        "El Chifl\u00f3n"
    ],
    "wof:name":"El Chiflon",
    "wof:placetype":"locality"
},
  "geometry": {"coordinates":[-101.32003,25.46099],"type":"Point"}
}