{
  "type": "Feature",
  "properties": {
    "gn:admin1_code":"20.0",
    "gn:admin2_code":"450.0",
    "gn:asciiname":"Llano Colorado",
    "gn:country_code":"MX",
    "gn:dem":1470,
    "gn:feature_class":"P",
    "gn:feature_code":"PPL",
    "gn:name":"Llano Colorado",
    "gn:population":0,
    "gn:timezone":"America/Mexico_City",
    "iso:country":"MX",
    "name:spa_x_preferred":[
        "Llano Colorado"
    ],
    "wof:name":"Llano Colorado",
    "wof:placetype":"locality"
},
  "geometry": {"coordinates":[-97.46435,16.60333],"type":"Point"}
}