{
  "type": "Feature",
  "properties": {
    "gn:admin1_code":"8",
    "gn:admin2_code":"3.0",
    "gn:asciiname":"Beto Llerenas",
    "gn:country_code":"MX",
    "gn:dem":829,
    "gn:feature_class":"P",
    "gn:feature_code":"PPL",
    "gn:name":"Beto Llerenas",
    "gn:population":5,
    "gn:timezone":"America/Mexico_City",
    "iso:country":"MX",
    "wof:name":"Beto Llerenas",
    "wof:placetype":"locality",
    "wof:population":5
},
  "geometry": {"coordinates":[-103.77694,19.38556],"type":"Point"}
}