{
  "type": "Feature",
  "properties": {
    "gn:admin1_code":"24",
    "gn:admin2_code":"27.0",
    "gn:asciiname":"Guerrero",
    "gn:country_code":"MX",
    "gn:dem":1188,
    "gn:feature_class":"P",
    "gn:feature_code":"PPL",
    "gn:name":"Guerrero",
    "gn:population":0,
    "gn:timezone":"America/Mexico_City",
    "iso:country":"MX",
    "name:spa_x_preferred":[
        "Guerrero"
    ],
    "wof:name":"Guerrero",
    "wof:placetype":"locality"
},
  "geometry": {"coordinates":[-99.79103000000001,21.55104],"type":"Point"}
}