{
  "type": "Feature",
  "properties": {
    "gn:admin1_code":"10",
    "gn:admin2_code":"3.0",
    "gn:asciiname":"Los Fresnos",
    "gn:country_code":"MX",
    "gn:dem":1648,
    "gn:feature_class":"P",
    "gn:feature_code":"PPL",
    "gn:name":"Los Fresnos",
    "gn:population":0,
    "gn:timezone":"America/Monterrey",
    "iso:country":"MX",
    "name:spa_x_preferred":[
        "Los Fresnos"
    ],
    "wof:name":"Los Fresnos",
    "wof:placetype":"locality"
},
  "geometry": {"coordinates":[-104.62860999999999,24.98218],"type":"Point"}
}