{
  "type": "Feature",
  "properties": {
    "gn:admin1_code":"16",
    "gn:admin2_code":"10.0",
    "gn:asciiname":"Las Ollas",
    "gn:country_code":"MX",
    "gn:dem":1106,
    "gn:feature_class":"P",
    "gn:feature_code":"PPL",
    "gn:name":"Las Ollas",
    "gn:population":0,
    "gn:timezone":"America/Mexico_City",
    "iso:country":"MX",
    "name:und_x_variant":[
        "Las Solas",
        "Las Ollas"
    ],
    "wof:name":"Las Ollas",
    "wof:placetype":"locality"
},
  "geometry": {"coordinates":[-102.34717999999999,18.35636],"type":"Point"}
}