{
  "type": "Feature",
  "properties": {
    "gn:admin1_code":"12",
    "gn:admin2_code":"54",
    "gn:asciiname":"Los Naranjos",
    "gn:country_code":"MX",
    "gn:dem":1696,
    "gn:feature_class":"P",
    "gn:feature_code":"PPL",
    "gn:name":"Los Naranjos",
    "gn:population":35,
    "gn:timezone":"America/Mexico_City",
    "iso:country":"MX",
    "name:bre_x_preferred":[
        "Los Naranjos"
    ],
    "name:ceb_x_preferred":[
        "Los Naranjos"
    ],
    "name:deu_x_preferred":[
        "Los Naranjos"
    ],
    "name:spa_x_preferred":[
        "Los Naranjos"
    ],
    "name:swe_x_preferred":[
        "Los Naranjos"
    ],
    "wof:name":"Los Naranjos",
    "wof:placetype":"locality",
    "wof:population":35
},
  "geometry": {"coordinates":[-100.21946,17.8827],"type":"Point"}
}