{
  "type": "Feature",
  "properties": {
    "gn:admin1_code":"11.0",
    "gn:admin2_code":"43.0",
    "gn:asciiname":"Las Higueras",
    "gn:country_code":"MX",
    "gn:dem":1913,
    "gn:feature_class":"P",
    "gn:feature_code":"PPL",
    "gn:name":"Las Higueras",
    "gn:population":0,
    "gn:timezone":"America/Mexico_City",
    "iso:country":"MX",
    "name:und_x_variant":[
        "Higuera",
        "Higueras"
    ],
    "wof:name":"Las Higueras",
    "wof:placetype":"locality"
},
  "geometry": {"coordinates":[-100.16952000000001,21.26119],"type":"Point"}
}