{
  "type": "Feature",
  "properties": {
    "gn:admin1_code":"5",
    "gn:admin2_code":"59",
    "gn:asciiname":"San Antonio Tijuana",
    "gn:country_code":"MX",
    "gn:dem":711,
    "gn:feature_class":"P",
    "gn:feature_code":"PPL",
    "gn:name":"San Antonio Tijuana",
    "gn:population":15,
    "gn:timezone":"America/Mexico_City",
    "iso:country":"MX",
    "wof:name":"San Antonio Tijuana",
    "wof:placetype":"locality",
    "wof:population":15
},
  "geometry": {"coordinates":[-91.76278000000001,16.93667],"type":"Point"}
}