{
  "type": "Feature",
  "properties": {
    "gn:admin1_code":"25",
    "gn:admin2_code":"5.0",
    "gn:asciiname":"La Crosolia",
    "gn:country_code":"MX",
    "gn:dem":510,
    "gn:feature_class":"P",
    "gn:feature_code":"PPL",
    "gn:name":"La Crosolia",
    "gn:population":8,
    "gn:timezone":"America/Mazatlan",
    "iso:country":"MX",
    "wof:name":"La Crosolia",
    "wof:placetype":"locality",
    "wof:population":8
},
  "geometry": {"coordinates":[-106.53331,24.27977000000001],"type":"Point"}
}