{
  "type": "Feature",
  "properties": {
    "gn:admin1_code":"30.0",
    "gn:admin2_code":"123.0",
    "gn:asciiname":"Hermanos Rodriguez",
    "gn:country_code":"MX",
    "gn:dem":17,
    "gn:feature_class":"P",
    "gn:feature_code":"PPL",
    "gn:name":"Hermanos Rodr\u00edguez",
    "gn:population":0,
    "gn:timezone":"America/Mexico_City",
    "iso:country":"MX",
    "name:spa_x_preferred":[
        "Hermanos Rodr\u00edguez"
    ],
    "wof:name":"Hermanos Rodriguez",
    "wof:placetype":"locality"
},
  "geometry": {"coordinates":[-98.39648,22.37157],"type":"Point"}
}