{
  "type": "Feature",
  "properties": {
    "gn:admin1_code":"2",
    "gn:admin2_code":"3",
    "gn:asciiname":"Rancho Mendez",
    "gn:country_code":"MX",
    "gn:dem":477,
    "gn:feature_class":"P",
    "gn:feature_code":"PPL",
    "gn:name":"Rancho M\u00e9ndez",
    "gn:population":13,
    "gn:timezone":"America/Tijuana",
    "iso:country":"MX",
    "name:und_x_variant":[
        "Rancho M\u00e9ndez"
    ],
    "wof:name":"Rancho Mendez",
    "wof:placetype":"locality",
    "wof:population":13
},
  "geometry": {"coordinates":[-116.67139,32.54778],"type":"Point"}
}