{
  "type": "Feature",
  "properties": {
    "gn:admin1_code":"11.0",
    "gn:admin2_code":"14.0",
    "gn:asciiname":"Las Lozas",
    "gn:country_code":"MX",
    "gn:dem":2186,
    "gn:feature_class":"P",
    "gn:feature_code":"PPL",
    "gn:name":"Las Lozas",
    "gn:population":0,
    "gn:timezone":"America/Mexico_City",
    "iso:country":"MX",
    "name:spa_x_preferred":[
        "Las Lozas"
    ],
    "wof:name":"Las Lozas",
    "wof:placetype":"locality"
},
  "geometry": {"coordinates":[-101.05313,21.09496],"type":"Point"}
}