{
  "type": "Feature",
  "properties": {
    "gn:admin1_code":"15",
    "gn:admin2_code":"21.0",
    "gn:asciiname":"Segunda de San Miguel (El Cerrito)",
    "gn:country_code":"MX",
    "gn:dem":2231,
    "gn:feature_class":"P",
    "gn:feature_code":"PPL",
    "gn:name":"Segunda de San Miguel (El Cerrito)",
    "gn:population":425,
    "gn:timezone":"America/Mexico_City",
    "iso:country":"MX",
    "wof:name":"Segunda de San Miguel (El Cerrito)",
    "wof:placetype":"locality",
    "wof:population":425
},
  "geometry": {"coordinates":[-99.76611,18.90667],"type":"Point"}
}