{
  "type": "Feature",
  "properties": {
    "gn:admin1_code":"26.0",
    "gn:admin2_code":"26.0",
    "gn:asciiname":"Baychacove",
    "gn:country_code":"MX",
    "gn:dem":15,
    "gn:feature_class":"P",
    "gn:feature_code":"PPL",
    "gn:name":"Baychacove",
    "gn:population":0,
    "gn:timezone":"America/Hermosillo",
    "iso:country":"MX",
    "wof:name":"Baychacove",
    "wof:placetype":"locality"
},
  "geometry": {"coordinates":[-109.66667,27.05],"type":"Point"}
}