{
  "type": "Feature",
  "properties": {
    "gn:admin1_code":"3",
    "gn:admin2_code":"3.0",
    "gn:asciiname":"El Pintado",
    "gn:country_code":"MX",
    "gn:dem":465,
    "gn:feature_class":"P",
    "gn:feature_code":"PPL",
    "gn:name":"El Pintado",
    "gn:population":5,
    "gn:timezone":"America/Mazatlan",
    "iso:country":"MX",
    "wof:name":"El Pintado",
    "wof:placetype":"locality",
    "wof:population":5
},
  "geometry": {"coordinates":[-110.11479,23.6186],"type":"Point"}
}