{
  "type": "Feature",
  "properties": {
    "gn:admin1_code":"6",
    "gn:admin2_code":"29.0",
    "gn:asciiname":"Mesa del Triguito",
    "gn:country_code":"MX",
    "gn:dem":2263,
    "gn:feature_class":"P",
    "gn:feature_code":"PPL",
    "gn:name":"Mesa del Triguito",
    "gn:population":0,
    "gn:timezone":"America/Chihuahua",
    "iso:country":"MX",
    "name:spa_x_preferred":[
        "Mesa del Triguito"
    ],
    "wof:name":"Mesa del Triguito",
    "wof:placetype":"locality"
},
  "geometry": {"coordinates":[-107.03505,26.16587],"type":"Point"}
}