{
  "type": "Feature",
  "properties": {
    "gn:admin1_code":"30",
    "gn:admin2_code":"144.0",
    "gn:asciiname":"Palma Morena",
    "gn:country_code":"MX",
    "gn:dem":34,
    "gn:feature_class":"P",
    "gn:feature_code":"PPL",
    "gn:name":"Palma Morena",
    "gn:population":186,
    "gn:timezone":"America/Mexico_City",
    "iso:country":"MX",
    "wof:name":"Palma Morena",
    "wof:placetype":"locality",
    "wof:population":186
},
  "geometry": {"coordinates":[-94.93416999999999,17.58028],"type":"Point"}
}