{
  "type": "Feature",
  "properties": {
    "gn:admin1_code":"17",
    "gn:admin2_code":"4.0",
    "gn:asciiname":"Campo Agua de los Patos",
    "gn:country_code":"MX",
    "gn:dem":1130,
    "gn:feature_class":"P",
    "gn:feature_code":"PPL",
    "gn:name":"Campo Agua de los Patos",
    "gn:population":9,
    "gn:timezone":"America/Mexico_City",
    "iso:country":"MX",
    "wof:name":"Campo Agua de los Patos",
    "wof:placetype":"locality",
    "wof:population":9
},
  "geometry": {"coordinates":[-98.94667,18.63778],"type":"Point"}
}