{
  "type": "Feature",
  "properties": {
    "gn:admin1_code":"11",
    "gn:admin2_code":"23",
    "gn:asciiname":"Las Carretas",
    "gn:country_code":"MX",
    "gn:dem":2210,
    "gn:feature_class":"P",
    "gn:feature_code":"PPL",
    "gn:name":"Las Carretas",
    "gn:population":16,
    "gn:timezone":"America/Mexico_City",
    "iso:country":"MX",
    "wof:name":"Las Carretas",
    "wof:placetype":"locality",
    "wof:population":16
},
  "geometry": {"coordinates":[-101.78389,20.52361],"type":"Point"}
}