{
  "type": "Feature",
  "properties": {
    "gn:admin1_code":"21.0",
    "gn:admin2_code":"114.0",
    "gn:asciiname":"Toltepec",
    "gn:country_code":"MX",
    "gn:dem":2275,
    "gn:feature_class":"P",
    "gn:feature_code":"PPL",
    "gn:name":"Toltepec",
    "gn:population":0,
    "gn:timezone":"America/Mexico_City",
    "iso:country":"MX",
    "name:spa_x_preferred":[
        "Toltepec"
    ],
    "wof:name":"Toltepec",
    "wof:placetype":"locality"
},
  "geometry": {"coordinates":[-98.14064999999999,19.01336],"type":"Point"}
}