{
  "type": "Feature",
  "properties": {
    "gn:admin1_code":"12",
    "gn:admin2_code":"45",
    "gn:asciiname":"Rancho el Mirador",
    "gn:country_code":"MX",
    "gn:dem":1486,
    "gn:feature_class":"P",
    "gn:feature_code":"PPL",
    "gn:name":"Rancho el Mirador",
    "gn:population":16,
    "gn:timezone":"America/Mexico_City",
    "iso:country":"MX",
    "wof:name":"Rancho el Mirador",
    "wof:placetype":"locality",
    "wof:population":16
},
  "geometry": {"coordinates":[-98.65661,17.87012],"type":"Point"}
}