{
  "type": "Feature",
  "properties": {
    "gn:admin1_code":"21",
    "gn:admin2_code":"71.0",
    "gn:asciiname":"Teopancingo",
    "gn:country_code":"MX",
    "gn:dem":2339,
    "gn:feature_class":"P",
    "gn:feature_code":"PPL",
    "gn:name":"Teopancingo",
    "gn:population":0,
    "gn:timezone":"America/Mexico_City",
    "iso:country":"MX",
    "name:spa_x_preferred":[
        "Teopancingo"
    ],
    "wof:name":"Teopancingo",
    "wof:placetype":"locality"
},
  "geometry": {"coordinates":[-98.06953,20.0941],"type":"Point"}
}