{
  "type": "Feature",
  "properties": {
    "gn:admin1_code":"16",
    "gn:admin2_code":"82",
    "gn:asciiname":"Colonia Amalia Solorzano",
    "gn:country_code":"MX",
    "gn:dem":1529,
    "gn:feature_class":"P",
    "gn:feature_code":"PPL",
    "gn:name":"Colonia Amalia Sol\u00f3rzano",
    "gn:population":51,
    "gn:timezone":"America/Mexico_City",
    "iso:country":"MX",
    "name:und_x_variant":[
        "Colonia Amalia Sol\u00f3rzano"
    ],
    "wof:name":"Colonia Amalia Solorzano",
    "wof:placetype":"locality",
    "wof:population":51
},
  "geometry": {"coordinates":[-101.4425,19.22639],"type":"Point"}
}