{
  "type": "Feature",
  "properties": {
    "gn:admin1_code":"5.0",
    "gn:admin2_code":"23.0",
    "gn:asciiname":"Macvilho",
    "gn:country_code":"MX",
    "gn:dem":2156,
    "gn:feature_class":"P",
    "gn:feature_code":"PPL",
    "gn:name":"Macvilh\u00f3",
    "gn:population":0,
    "gn:timezone":"America/Mexico_City",
    "iso:country":"MX",
    "name:spa_x_preferred":[
        "Teatiks"
    ],
    "name:spa_x_variant":[
        "Macvilh\u00f3"
    ],
    "wof:name":"Macvilho",
    "wof:placetype":"locality"
},
  "geometry": {"coordinates":[-92.69419000000001,16.8576],"type":"Point"}
}