{
  "type": "Feature",
  "properties": {
    "gn:admin1_code":"26.0",
    "gn:admin2_code":"64.0",
    "gn:asciiname":"Fatima",
    "gn:country_code":"MX",
    "gn:dem":412,
    "gn:feature_class":"P",
    "gn:feature_code":"PPL",
    "gn:name":"F\u00e1tima",
    "gn:population":0,
    "gn:timezone":"America/Hermosillo",
    "iso:country":"MX",
    "name:spa_x_preferred":[
        "F\u00e1tima"
    ],
    "name:und_x_variant":[
        "Rancho F\u00e1tima"
    ],
    "wof:name":"Fatima",
    "wof:placetype":"locality"
},
  "geometry": {"coordinates":[-111.73953,30.51741],"type":"Point"}
}