{
  "type": "Feature",
  "properties": {
    "gn:admin1_code":"25.0",
    "gn:admin2_code":"6.0",
    "gn:asciiname":"Corral Viejo",
    "gn:country_code":"MX",
    "gn:dem":246,
    "gn:feature_class":"P",
    "gn:feature_code":"PPL",
    "gn:name":"Corral Viejo",
    "gn:population":0,
    "gn:timezone":"America/Mazatlan",
    "iso:country":"MX",
    "name:spa_x_preferred":[
        "Corral Viejo"
    ],
    "wof:name":"Corral Viejo",
    "wof:placetype":"locality"
},
  "geometry": {"coordinates":[-106.98809,24.80956],"type":"Point"}
}