{
  "type": "Feature",
  "properties": {
    "gn:admin1_code":"10",
    "gn:admin2_code":"18.0",
    "gn:asciiname":"Boca de Alamo",
    "gn:country_code":"MX",
    "gn:dem":1599,
    "gn:feature_class":"P",
    "gn:feature_code":"PPL",
    "gn:name":"Boca de Alamo",
    "gn:population":0,
    "gn:timezone":"America/Monterrey",
    "iso:country":"MX",
    "name:spa_x_preferred":[
        "Boca de Alamo"
    ],
    "wof:name":"Boca de Alamo",
    "wof:placetype":"locality"
},
  "geometry": {"coordinates":[-104.92989,25.4085],"type":"Point"}
}