{
  "type": "Feature",
  "properties": {
    "gn:admin1_code":"19.0",
    "gn:asciiname":"Cerrito Blanco",
    "gn:country_code":"MX",
    "gn:dem":1700,
    "gn:feature_class":"P",
    "gn:feature_code":"PPL",
    "gn:name":"Cerrito Blanco",
    "gn:population":0,
    "gn:timezone":"America/Monterrey",
    "iso:country":"MX",
    "name:spa_x_preferred":[
        "Cerrito Blanco"
    ],
    "wof:name":"Cerrito Blanco",
    "wof:placetype":"locality"
},
  "geometry": {"coordinates":[-99.92431999999999,24.14618],"type":"Point"}
}