{
  "type": "Feature",
  "properties": {
    "gn:admin1_code":"21",
    "gn:admin2_code":"198.0",
    "gn:asciiname":"Coacalco",
    "gn:country_code":"MX",
    "gn:dem":715,
    "gn:feature_class":"P",
    "gn:feature_code":"PPL",
    "gn:name":"Coacalco",
    "gn:population":0,
    "gn:timezone":"America/Mexico_City",
    "iso:country":"MX",
    "name:spa_x_preferred":[
        "Coacalco"
    ],
    "wof:name":"Coacalco",
    "wof:placetype":"locality"
},
  "geometry": {"coordinates":[-98.66755999999999,18.0715],"type":"Point"}
}