{
  "type": "Feature",
  "properties": {
    "gn:admin1_code":"25",
    "gn:admin2_code":"12.0",
    "gn:asciiname":"La Sabila",
    "gn:country_code":"MX",
    "gn:dem":88,
    "gn:feature_class":"P",
    "gn:feature_code":"PPL",
    "gn:name":"La S\u00e1bila",
    "gn:population":271,
    "gn:timezone":"America/Mazatlan",
    "iso:country":"MX",
    "wof:name":"La Sabila",
    "wof:placetype":"locality",
    "wof:population":271
},
  "geometry": {"coordinates":[-106.44278,23.60222000000001],"type":"Point"}
}