{
  "type": "Feature",
  "properties": {
    "gn:country":"MX",
    "gn:fcode":"PPL",
    "gn:population":0,
    "iso:country":"MX",
    "name:spa_x_preferred":[
        "Tecocomulco de Ju\u00e1rez"
    ],
    "name:und_x_variant":[
        "Huipanguillo Tecocomulco"
    ],
    "qs_pg:aaroncc":"MX",
    "qs_pg:gn_country":"MX",
    "qs_pg:gn_fcode":"PPL",
    "qs_pg:gn_pop":0,
    "qs_pg:name":"Tecocomulco",
    "qs_pg:name_adm0":"M\u00e9xico",
    "qs_pg:name_adm1":"Hidalgo",
    "qs_pg:photos":20,
    "qs_pg:photos_1k":4,
    "qs_pg:photos_9k":1,
    "qs_pg:photos_9r":1,
    "qs_pg:photos_all":20,
    "qs_pg:photos_sr":1,
    "qs_pg:pop_sr":3,
    "qs_pg:qs_pg_placetype":"locality",
    "qs_pg:qs_pg_placetype_gp":"Town",
    "qs_pg:woe_adm0":23424900,
    "woe:adm0_id":23424900,
    "woe:name_adm0":"M\u00e9xico",
    "woe:name_adm1":"Hidalgo",
    "woe:placetype":"Town",
    "wof:name":"Tecocomulco",
    "wof:placetype":"locality",
    "wof:population":599
},
  "geometry": {"coordinates":[-98.35133,19.90529],"type":"Point"}
}