{
  "type": "Feature",
  "properties": {
    "gn:admin1_code":"12.0",
    "gn:admin2_code":"16.0",
    "gn:asciiname":"La Tasajera",
    "gn:country_code":"MX",
    "gn:dem":277,
    "gn:feature_class":"P",
    "gn:feature_code":"PPL",
    "gn:name":"La Tasajera",
    "gn:population":0,
    "gn:timezone":"America/Mexico_City",
    "iso:country":"MX",
    "name:spa_x_preferred":[
        "La Tasajera"
    ],
    "wof:name":"La Tasajera",
    "wof:placetype":"locality"
},
  "geometry": {"coordinates":[-101.79776,18.44782],"type":"Point"}
}