{
  "type": "Feature",
  "properties": {
    "gn:admin1_code":"17",
    "gn:admin2_code":"12",
    "gn:asciiname":"La Catalana",
    "gn:country_code":"MX",
    "gn:dem":932,
    "gn:feature_class":"P",
    "gn:feature_code":"PPL",
    "gn:name":"La Catalana",
    "gn:population":16,
    "gn:timezone":"America/Mexico_City",
    "iso:country":"MX",
    "wof:name":"La Catalana",
    "wof:placetype":"locality",
    "wof:population":16
},
  "geometry": {"coordinates":[-99.29056,18.58306],"type":"Point"}
}