{
  "type": "Feature",
  "properties": {
    "gn:admin1_code":"16",
    "gn:admin2_code":"35.0",
    "gn:asciiname":"La Caja de Zicuiran (El Jazmin)",
    "gn:country_code":"MX",
    "gn:dem":277,
    "gn:feature_class":"P",
    "gn:feature_code":"PPL",
    "gn:name":"La Caja de Zicuir\u00e1n (El Jazm\u00edn)",
    "gn:population":68,
    "gn:timezone":"America/Mexico_City",
    "iso:country":"MX",
    "name:und_x_variant":[
        "La Caja de Zicuir\u00e1n (El Jazm\u00edn)"
    ],
    "wof:name":"La Caja de Zicuiran (El Jazmin)",
    "wof:placetype":"locality",
    "wof:population":68
},
  "geometry": {"coordinates":[-101.90528,18.83083],"type":"Point"}
}