{
  "type": "Feature",
  "properties": {
    "gn:admin1_code":"13",
    "gn:admin2_code":"63.0",
    "gn:asciiname":"San Mateo Segunda Seccion",
    "gn:country_code":"MX",
    "gn:dem":2204,
    "gn:feature_class":"P",
    "gn:feature_code":"PPL",
    "gn:name":"San Mateo Segunda Secci\u00f3n",
    "gn:population":7,
    "gn:timezone":"America/Mexico_City",
    "iso:country":"MX",
    "name:und_x_variant":[
        "San Mateo Segunda Secci\u00f3n"
    ],
    "wof:name":"San Mateo Segunda Seccion",
    "wof:placetype":"locality",
    "wof:population":7
},
  "geometry": {"coordinates":[-99.32944000000001,19.89222],"type":"Point"}
}