{
  "type": "Feature",
  "properties": {
    "gn:admin1_code":"11.0",
    "gn:asciiname":"La Piedad Buenavista",
    "gn:country_code":"MX",
    "gn:dem":2076,
    "gn:feature_class":"P",
    "gn:feature_code":"PPL",
    "gn:name":"La Piedad Buenavista",
    "gn:population":0,
    "gn:timezone":"America/Mexico_City",
    "iso:country":"MX",
    "name:spa_x_preferred":[
        "La Piedad Buenavista"
    ],
    "wof:name":"La Piedad Buenavista",
    "wof:placetype":"locality"
},
  "geometry": {"coordinates":[-100.53915000000001,20.32152],"type":"Point"}
}