{
  "type": "Feature",
  "properties": {
    "gn:admin1_code":"24",
    "gn:admin2_code":"38.0",
    "gn:asciiname":"Lazaro Cardenas",
    "gn:country_code":"MX",
    "gn:dem":330,
    "gn:feature_class":"P",
    "gn:feature_code":"PPL",
    "gn:name":"L\u00e1zaro C\u00e1rdenas",
    "gn:population":233,
    "gn:timezone":"America/Mexico_City",
    "iso:country":"MX",
    "name:und_x_variant":[
        "L\u00e1zaro C\u00e1rdenas"
    ],
    "wof:name":"Lazaro Cardenas",
    "wof:placetype":"locality",
    "wof:population":233
},
  "geometry": {"coordinates":[-98.68667000000001,21.39722],"type":"Point"}
}