{
  "type": "Feature",
  "properties": {
    "gn:admin1_code":"30",
    "gn:admin2_code":"32.0",
    "gn:asciiname":"Rancho Nuevo",
    "gn:country_code":"MX",
    "gn:dem":33,
    "gn:feature_class":"P",
    "gn:feature_code":"PPL",
    "gn:name":"Rancho Nuevo",
    "gn:population":9,
    "gn:timezone":"America/Mexico_City",
    "iso:country":"MX",
    "wof:name":"Rancho Nuevo",
    "wof:placetype":"locality",
    "wof:population":9
},
  "geometry": {"coordinates":[-94.97556,18.55444],"type":"Point"}
}