{
  "type": "Feature",
  "properties": {
    "gn:admin1_code":"2.0",
    "gn:admin2_code":"3.0",
    "gn:asciiname":"El Granate",
    "gn:country_code":"MX",
    "gn:dem":1413,
    "gn:feature_class":"P",
    "gn:feature_code":"PPL",
    "gn:name":"El Granate",
    "gn:population":0,
    "gn:timezone":"America/Tijuana",
    "iso:country":"MX",
    "name:spa_x_preferred":[
        "El Granate"
    ],
    "wof:name":"El Granate",
    "wof:placetype":"locality"
},
  "geometry": {"coordinates":[-116.07904000000001,32.33537],"type":"Point"}
}