{
  "type": "Feature",
  "properties": {
    "gn:admin1_code":"30.0",
    "gn:asciiname":"Colonia Juan Morales Aldana",
    "gn:country_code":"MX",
    "gn:dem":28,
    "gn:feature_class":"P",
    "gn:feature_code":"PPL",
    "gn:name":"Colonia Juan Morales Aldana",
    "gn:population":0,
    "gn:timezone":"America/Mexico_City",
    "iso:country":"MX",
    "name:spa_x_preferred":[
        "Colonia Juan Morales Aldana"
    ],
    "name:spa_x_variant":[
        "Juan Morales Aldana"
    ],
    "wof:name":"Colonia Juan Morales Aldana",
    "wof:placetype":"locality"
},
  "geometry": {"coordinates":[-94.39099,17.98264],"type":"Point"}
}