{
  "type": "Feature",
  "properties": {
    "gn:admin1_code":"30",
    "gn:admin2_code":"115.0",
    "gn:asciiname":"Fernando Lopez Arias",
    "gn:country_code":"MX",
    "gn:dem":1364,
    "gn:feature_class":"P",
    "gn:feature_code":"PPL",
    "gn:name":"Fernando L\u00f3pez Arias",
    "gn:population":187,
    "gn:timezone":"America/Mexico_City",
    "iso:country":"MX",
    "name:und_x_variant":[
        "Fernando L\u00f3pez Arias"
    ],
    "wof:name":"Fernando Lopez Arias",
    "wof:placetype":"locality",
    "wof:population":187
},
  "geometry": {"coordinates":[-97.18944,18.81667],"type":"Point"}
}