{
  "type": "Feature",
  "properties": {
    "gn:admin1_code":"10",
    "gn:admin2_code":"14.0",
    "gn:asciiname":"El Jabali",
    "gn:country_code":"MX",
    "gn:dem":1739,
    "gn:feature_class":"P",
    "gn:feature_code":"PPL",
    "gn:name":"El Jabal\u00ed",
    "gn:population":0,
    "gn:timezone":"America/Mexico_City",
    "iso:country":"MX",
    "name:spa_x_preferred":[
        "El Jabal\u00ed"
    ],
    "wof:name":"El Jabali",
    "wof:placetype":"locality"
},
  "geometry": {"coordinates":[-104.1722,22.79613],"type":"Point"}
}