{
  "type": "Feature",
  "properties": {
    "gn:admin1_code":"11",
    "gn:admin2_code":"33.0",
    "gn:asciiname":"Las Tortugas",
    "gn:country_code":"MX",
    "gn:dem":2239,
    "gn:feature_class":"P",
    "gn:feature_code":"PPL",
    "gn:name":"Las Tortugas",
    "gn:population":5,
    "gn:timezone":"America/Mexico_City",
    "iso:country":"MX",
    "wof:name":"Las Tortugas",
    "wof:placetype":"locality",
    "wof:population":5
},
  "geometry": {"coordinates":[-100.49444,21.42167],"type":"Point"}
}