{
  "type": "Feature",
  "properties": {
    "gn:admin1_code":"25",
    "gn:admin2_code":"12.0",
    "gn:asciiname":"La Amapa",
    "gn:country_code":"MX",
    "gn:dem":96,
    "gn:feature_class":"P",
    "gn:feature_code":"PPL",
    "gn:name":"La Amapa",
    "gn:population":0,
    "gn:timezone":"America/Mazatlan",
    "iso:country":"MX",
    "name:spa_x_preferred":[
        "La Amapa"
    ],
    "name:und_x_variant":[
        "Amapa",
        "Las Amapas"
    ],
    "wof:name":"La Amapa",
    "wof:placetype":"locality"
},
  "geometry": {"coordinates":[-106.42261999999999,23.61759],"type":"Point"}
}