{
  "type": "Feature",
  "properties": {
    "gn:admin1_code":"20",
    "gn:admin2_code":"171.0",
    "gn:asciiname":"Agua Apestosa",
    "gn:country_code":"MX",
    "gn:dem":1152,
    "gn:feature_class":"P",
    "gn:feature_code":"PPL",
    "gn:name":"Agua Apestosa",
    "gn:population":141,
    "gn:timezone":"America/Mexico_City",
    "iso:country":"MX",
    "wof:name":"Agua Apestosa",
    "wof:placetype":"locality",
    "wof:population":141
},
  "geometry": {"coordinates":[-96.65139000000001,18.15111],"type":"Point"}
}