{
  "type": "Feature",
  "properties": {
    "gn:admin1_code":"6",
    "gn:admin2_code":"31",
    "gn:asciiname":"La Lagunita",
    "gn:country_code":"MX",
    "gn:dem":2283,
    "gn:feature_class":"P",
    "gn:feature_code":"PPL",
    "gn:name":"La Lagunita",
    "gn:population":20,
    "gn:timezone":"America/Chihuahua",
    "iso:country":"MX",
    "wof:name":"La Lagunita",
    "wof:placetype":"locality",
    "wof:population":20
},
  "geometry": {"coordinates":[-107.76439999999999,28.1053],"type":"Point"}
}