{
  "type": "Feature",
  "properties": {
    "gn:admin1_code":"26.0",
    "gn:admin2_code":"30.0",
    "gn:asciiname":"Pozo Nuevo",
    "gn:country_code":"MX",
    "gn:dem":103,
    "gn:feature_class":"P",
    "gn:feature_code":"PPL",
    "gn:name":"Pozo Nuevo",
    "gn:population":0,
    "gn:timezone":"America/Hermosillo",
    "iso:country":"MX",
    "name:spa_x_preferred":[
        "Pozo Nuevo"
    ],
    "wof:name":"Pozo Nuevo",
    "wof:placetype":"locality"
},
  "geometry": {"coordinates":[-111.42846000000002,29.08218],"type":"Point"}
}