{
  "type": "Feature",
  "properties": {
    "gn:admin1_code":"30",
    "gn:admin2_code":"142.0",
    "gn:asciiname":"Mata de Cana",
    "gn:country_code":"MX",
    "gn:dem":69,
    "gn:feature_class":"P",
    "gn:feature_code":"PPL",
    "gn:name":"Mata de Ca\u00f1a",
    "gn:population":0,
    "gn:timezone":"America/Mexico_City",
    "iso:country":"MX",
    "name:spa_x_preferred":[
        "Mata de Ca\u00f1a"
    ],
    "wof:name":"Mata de Cana",
    "wof:placetype":"locality"
},
  "geometry": {"coordinates":[-95.01438,17.64747999999999],"type":"Point"}
}