{
  "type": "Feature",
  "properties": {
    "gn:admin1_code":"6",
    "gn:admin2_code":"20.0",
    "gn:asciiname":"Pie de la Cuesta",
    "gn:country_code":"MX",
    "gn:dem":1541,
    "gn:feature_class":"P",
    "gn:feature_code":"PPL",
    "gn:name":"Pie de la Cuesta",
    "gn:population":0,
    "gn:timezone":"America/Chihuahua",
    "iso:country":"MX",
    "name:spa_x_preferred":[
        "Pie de la Cuesta"
    ],
    "name:und_x_variant":[
        "Rancho Pie de la Cuesta"
    ],
    "wof:name":"Pie de la Cuesta",
    "wof:placetype":"locality"
},
  "geometry": {"coordinates":[-108.57198,27.74395],"type":"Point"}
}