{
  "type": "Feature",
  "properties": {
    "gn:admin1_code":"7",
    "gn:admin2_code":"17",
    "gn:asciiname":"Bascula la Sandillita",
    "gn:country_code":"MX",
    "gn:dem":1109,
    "gn:feature_class":"P",
    "gn:feature_code":"PPL",
    "gn:name":"B\u00e1scula la Sandillita",
    "gn:population":9,
    "gn:timezone":"America/Monterrey",
    "iso:country":"MX",
    "name:und_x_variant":[
        "B\u00e1scula la Sandillita"
    ],
    "wof:name":"Bascula la Sandillita",
    "wof:placetype":"locality",
    "wof:population":9
},
  "geometry": {"coordinates":[-103.17784,25.51694],"type":"Point"}
}