{
  "type": "Feature",
  "properties": {
    "gn:admin1_code":"15.0",
    "gn:admin2_code":"32.0",
    "gn:asciiname":"El Chirimoyo",
    "gn:country_code":"MX",
    "gn:dem":2020,
    "gn:feature_class":"P",
    "gn:feature_code":"PPL",
    "gn:name":"El Chirimoyo",
    "gn:population":0,
    "gn:timezone":"America/Mexico_City",
    "iso:country":"MX",
    "name:spa_x_preferred":[
        "El Chirimoyo"
    ],
    "wof:name":"El Chirimoyo",
    "wof:placetype":"locality"
},
  "geometry": {"coordinates":[-100.24545000000001,19.30242],"type":"Point"}
}