{
  "type": "Feature",
  "properties": {
    "gn:admin1_code":"17",
    "gn:admin2_code":"29",
    "gn:asciiname":"Jovito Serrano",
    "gn:country_code":"MX",
    "gn:dem":1206,
    "gn:feature_class":"P",
    "gn:feature_code":"PPL",
    "gn:name":"Jovito Serrano",
    "gn:population":21,
    "gn:timezone":"America/Mexico_City",
    "iso:country":"MX",
    "wof:name":"Jovito Serrano",
    "wof:placetype":"locality",
    "wof:population":21
},
  "geometry": {"coordinates":[-99.05806,18.86639],"type":"Point"}
}