{
  "type": "Feature",
  "properties": {
    "gn:admin1_code":"18.0",
    "gn:admin2_code":"19.0",
    "gn:asciiname":"La Manga",
    "gn:country_code":"MX",
    "gn:dem":1727,
    "gn:feature_class":"P",
    "gn:feature_code":"PPL",
    "gn:name":"La Manga",
    "gn:population":0,
    "gn:timezone":"America/Mazatlan",
    "iso:country":"MX",
    "name:aze_x_preferred":[
        "La-Manqa dili"
    ],
    "name:ceb_x_preferred":[
        "Manga del Mar Menor"
    ],
    "name:dan_x_preferred":[
        "La Manga"
    ],
    "name:fra_x_preferred":[
        "La Manga"
    ],
    "name:jpn_x_preferred":[
        "\u30e9\u30fb\u30de\u30f3\u30ac"
    ],
    "name:nno_x_preferred":[
        "La Manga"
    ],
    "name:nor_x_preferred":[
        "La Manga"
    ],
    "name:pol_x_preferred":[
        "La Manga"
    ],
    "name:rus_x_preferred":[
        "\u041b\u0430-\u041c\u0430\u043d\u0433\u0430"
    ],
    "name:spa_x_preferred":[
        "La Manga"
    ],
    "name:swe_x_preferred":[
        "La Manga"
    ],
    "name:ukr_x_preferred":[
        "\u041b\u0430-\u041c\u0430\u043d\u0433\u0430"
    ],
    "wof:name":"La Manga",
    "wof:placetype":"locality"
},
  "geometry": {"coordinates":[-104.14774,21.48531],"type":"Point"}
}