{
  "type": "Feature",
  "properties": {
    "gn:admin1_code":"20",
    "gn:admin2_code":"515.0",
    "gn:asciiname":"El Jordan",
    "gn:country_code":"MX",
    "gn:dem":39,
    "gn:feature_class":"P",
    "gn:feature_code":"PPL",
    "gn:name":"El Jord\u00e1n",
    "gn:population":0,
    "gn:timezone":"America/Mexico_City",
    "iso:country":"MX",
    "name:spa_x_preferred":[
        "El Jord\u00e1n"
    ],
    "wof:name":"El Jordan",
    "wof:placetype":"locality"
},
  "geometry": {"coordinates":[-95.20735999999999,16.38041],"type":"Point"}
}