{
  "type": "Feature",
  "properties": {
    "gn:admin1_code":"12",
    "gn:admin2_code":"32.0",
    "gn:asciiname":"Coatepec",
    "gn:country_code":"MX",
    "gn:dem":1577,
    "gn:feature_class":"P",
    "gn:feature_code":"PPL",
    "gn:name":"Coatepec",
    "gn:population":0,
    "gn:timezone":"America/Mexico_City",
    "iso:country":"MX",
    "name:und_x_variant":[
        "Cuatepec",
        "Coatepec"
    ],
    "wof:name":"Coatepec",
    "wof:placetype":"locality"
},
  "geometry": {"coordinates":[-99.85465000000001,17.78302],"type":"Point"}
}