{
  "type": "Feature",
  "properties": {
    "gn:admin1_code":"11",
    "gn:admin2_code":"33.0",
    "gn:asciiname":"Puerto de Leon",
    "gn:country_code":"MX",
    "gn:dem":1851,
    "gn:feature_class":"P",
    "gn:feature_code":"PPL",
    "gn:name":"Puerto de Le\u00f3n",
    "gn:population":8,
    "gn:timezone":"America/Mexico_City",
    "iso:country":"MX",
    "name:und_x_variant":[
        "Puerto de Le\u00f3n"
    ],
    "wof:name":"Puerto de Leon",
    "wof:placetype":"locality",
    "wof:population":8
},
  "geometry": {"coordinates":[-100.405,21.54472],"type":"Point"}
}