{
  "type": "Feature",
  "properties": {
    "gn:admin1_code":"2",
    "gn:admin2_code":"4",
    "gn:asciiname":"El Valle",
    "gn:country_code":"MX",
    "gn:dem":245,
    "gn:feature_class":"P",
    "gn:feature_code":"PPL",
    "gn:name":"El Valle",
    "gn:population":23,
    "gn:timezone":"America/Tijuana",
    "iso:country":"MX",
    "name:ast_x_preferred":[
        "El Valle"
    ],
    "name:ceb_x_preferred":[
        "El Valle"
    ],
    "name:deu_x_preferred":[
        "El Valle"
    ],
    "name:fra_x_preferred":[
        "El Valle"
    ],
    "name:jpn_x_preferred":[
        "\u30a8\u30eb\u30d0\u30b8\u30a7"
    ],
    "name:nld_x_preferred":[
        "El Valle"
    ],
    "name:spa_x_preferred":[
        "El Valle"
    ],
    "name:swe_x_preferred":[
        "El Valle"
    ],
    "wof:name":"El Valle",
    "wof:placetype":"locality",
    "wof:population":23
},
  "geometry": {"coordinates":[-116.76027999999999,32.54083],"type":"Point"}
}