{
  "type": "Feature",
  "properties": {
    "gn:admin1_code":"26",
    "gn:admin2_code":"30.0",
    "gn:asciiname":"Nueva Ilusion [Campestre]",
    "gn:country_code":"MX",
    "gn:dem":207,
    "gn:feature_class":"P",
    "gn:feature_code":"PPL",
    "gn:name":"Nueva Ilusi\u00f3n [Campestre]",
    "gn:population":5,
    "gn:timezone":"America/Hermosillo",
    "iso:country":"MX",
    "name:und_x_variant":[
        "Nueva Ilusi\u00f3n [Campestre]"
    ],
    "wof:name":"Nueva Ilusion [Campestre]",
    "wof:placetype":"locality",
    "wof:population":5
},
  "geometry": {"coordinates":[-110.99527999999999,29.0175],"type":"Point"}
}