{
  "type": "Feature",
  "properties": {
    "gn:admin1_code":"20",
    "gn:admin2_code":"553.0",
    "gn:asciiname":"El Baratillo (Los Guajales)",
    "gn:country_code":"MX",
    "gn:dem":1630,
    "gn:feature_class":"P",
    "gn:feature_code":"PPL",
    "gn:name":"El Baratillo (Los Guajales)",
    "gn:population":6,
    "gn:timezone":"America/Mexico_City",
    "iso:country":"MX",
    "wof:name":"El Baratillo (Los Guajales)",
    "wof:placetype":"locality",
    "wof:population":6
},
  "geometry": {"coordinates":[-96.65333,17.09278],"type":"Point"}
}