{
  "type": "Feature",
  "properties": {
    "gn:admin1_code":"26",
    "gn:admin2_code":"26.0",
    "gn:asciiname":"Baynorillo",
    "gn:country_code":"MX",
    "gn:dem":11,
    "gn:feature_class":"P",
    "gn:feature_code":"PPL",
    "gn:name":"Baynorillo",
    "gn:population":0,
    "gn:timezone":"America/Hermosillo",
    "iso:country":"MX",
    "name:spa_x_preferred":[
        "Bainorillo"
    ],
    "name:und_x_variant":[
        "Vainorillo"
    ],
    "wof:name":"Baynorillo",
    "wof:placetype":"locality"
},
  "geometry": {"coordinates":[-109.617,26.8663],"type":"Point"}
}