{
  "type": "Feature",
  "properties": {
    "gn:admin1_code":"32",
    "gn:admin2_code":"26.0",
    "gn:asciiname":"Balones",
    "gn:country_code":"MX",
    "gn:dem":1880,
    "gn:feature_class":"P",
    "gn:feature_code":"PPL",
    "gn:name":"Balones",
    "gn:population":0,
    "gn:timezone":"America/Mexico_City",
    "iso:country":"MX",
    "name:ara_x_preferred":[
        "\u0628\u0627\u0644\u0648\u0646\u064a\u0633"
    ],
    "name:arg_x_preferred":[
        "Balones"
    ],
    "name:ast_x_preferred":[
        "Balones"
    ],
    "name:cat_x_preferred":[
        "Balones"
    ],
    "name:ceb_x_preferred":[
        "Balones"
    ],
    "name:eus_x_preferred":[
        "Balones"
    ],
    "name:fas_x_preferred":[
        "\u0628\u0627\u0644\u0648\u0646\u0633"
    ],
    "name:fra_x_preferred":[
        "Balones"
    ],
    "name:hun_x_preferred":[
        "Balones"
    ],
    "name:ita_x_preferred":[
        "Balones"
    ],
    "name:kaz_x_preferred":[
        "\u0411\u0430\u043b\u043e\u043d\u0435\u0441"
    ],
    "name:msa_x_preferred":[
        "Balones"
    ],
    "name:nld_x_preferred":[
        "Balones"
    ],
    "name:oci_x_preferred":[
        "Balones"
    ],
    "name:pol_x_preferred":[
        "Balones"
    ],
    "name:por_x_preferred":[
        "Balones"
    ],
    "name:rus_x_preferred":[
        "\u0411\u0430\u043b\u043e\u043d\u0435\u0441"
    ],
    "name:spa_x_preferred":[
        "Balones"
    ],
    "name:sqi_x_preferred":[
        "Balones"
    ],
    "name:swe_x_preferred":[
        "Balones"
    ],
    "name:ukr_x_preferred":[
        "\u0411\u0430\u043b\u043e\u043d\u0435\u0441"
    ],
    "name:uzb_x_preferred":[
        "Balones"
    ],
    "name:war_x_preferred":[
        "Balones"
    ],
    "name:zho_x_preferred":[
        "\u5df4\u6d1b\u5185\u65af"
    ],
    "wof:name":"Balones",
    "wof:placetype":"locality"
},
  "geometry": {"coordinates":[-102.0498,24.71649],"type":"Point"}
}