{
  "type": "Feature",
  "properties": {
    "gn:admin1_code":"32",
    "gn:admin2_code":"26.0",
    "gn:asciiname":"Balones",
    "gn:country_code":"MX",
    "gn:dem":1880,
    "gn:feature_class":"P",
    "gn:feature_code":"PPL",
    "gn:name":"Balones",
    "gn:population":0,
    "gn:timezone":"America/Mexico_City",
    "iso:country":"MX",
    "name:spa_x_preferred":[
        "Balones"
    ],
    "wof:name":"Balones",
    "wof:placetype":"locality"
},
  "geometry": {"coordinates":[-102.0498,24.71649],"type":"Point"}
}