{
  "type": "Feature",
  "properties": {
    "gn:admin1_code":"5",
    "gn:admin2_code":"6.0",
    "gn:asciiname":"Nueva America",
    "gn:country_code":"MX",
    "gn:dem":1725,
    "gn:feature_class":"P",
    "gn:feature_code":"PPL",
    "gn:name":"Nueva Am\u00e9rica",
    "gn:population":177,
    "gn:timezone":"America/Mexico_City",
    "iso:country":"MX",
    "name:und_x_variant":[
        "Nueva Am\u00e9rica"
    ],
    "wof:name":"Nueva America",
    "wof:placetype":"locality",
    "wof:population":177
},
  "geometry": {"coordinates":[-92.08796,15.47158],"type":"Point"}
}