{
  "type": "Feature",
  "properties": {
    "gn:admin1_code":"24",
    "gn:admin2_code":"26.0",
    "gn:asciiname":"Xolol",
    "gn:country_code":"MX",
    "gn:dem":216,
    "gn:feature_class":"P",
    "gn:feature_code":"PPL",
    "gn:name":"Xolol",
    "gn:population":233,
    "gn:timezone":"America/Mexico_City",
    "iso:country":"MX",
    "wof:name":"Xolol",
    "wof:placetype":"locality",
    "wof:population":233
},
  "geometry": {"coordinates":[-98.88056,21.63361],"type":"Point"}
}