{
  "type": "Feature",
  "properties": {
    "gn:admin1_code":"2.0",
    "gn:admin2_code":"2.0",
    "gn:asciiname":"Campo la Curva (Colonia Silva)",
    "gn:country_code":"MX",
    "gn:dem":23,
    "gn:feature_class":"P",
    "gn:feature_code":"PPL",
    "gn:name":"Campo la Curva (Colonia Silva)",
    "gn:population":345,
    "gn:timezone":"America/Tijuana",
    "iso:country":"MX",
    "name:spa_x_preferred":[
        "La Curva"
    ],
    "wof:name":"Campo la Curva (Colonia Silva)",
    "wof:placetype":"locality",
    "wof:population":345
},
  "geometry": {"coordinates":[-114.99111000000001,32.41222],"type":"Point"}
}