{
  "type": "Feature",
  "properties": {
    "gn:admin1_code":"20",
    "gn:admin2_code":"205.0",
    "gn:asciiname":"San Juan Evangelista",
    "gn:country_code":"MX",
    "gn:dem":446,
    "gn:feature_class":"P",
    "gn:feature_code":"PPL",
    "gn:name":"San Juan Evangelista",
    "gn:population":373,
    "gn:timezone":"America/Mexico_City",
    "iso:country":"MX",
    "wof:name":"San Juan Evangelista",
    "wof:placetype":"locality",
    "wof:population":373
},
  "geometry": {"coordinates":[-95.84332999999999,17.46],"type":"Point"}
}