{
  "type": "Feature",
  "properties": {
    "gn:admin1_code":"20",
    "gn:admin2_code":"205.0",
    "gn:asciiname":"San Juan Evangelista",
    "gn:country_code":"MX",
    "gn:dem":446,
    "gn:feature_class":"P",
    "gn:feature_code":"PPL",
    "gn:name":"San Juan Evangelista",
    "gn:population":373,
    "gn:timezone":"America/Mexico_City",
    "iso:country":"MX",
    "name:ceb_x_preferred":[
        "San Juan Evangelista"
    ],
    "name:epo_x_preferred":[
        "San Juan Evangelista"
    ],
    "name:eus_x_preferred":[
        "San Juan Evangelista"
    ],
    "name:srp_x_preferred":[
        "\u041e\u043f\u0448\u0442\u0438\u043d\u0430 \u0421\u0430\u043d \u0425\u0443\u0430\u043d \u0415\u0432\u0430\u043d\u0445\u0435\u043b\u0438\u0441\u0442\u0430"
    ],
    "name:swe_x_preferred":[
        "San Juan Evangelista"
    ],
    "name:vie_x_preferred":[
        "San Juan Evangelista"
    ],
    "wof:name":"San Juan Evangelista",
    "wof:placetype":"locality",
    "wof:population":373
},
  "geometry": {"coordinates":[-95.84332999999999,17.46],"type":"Point"}
}