{
  "type": "Feature",
  "properties": {
    "gn:admin1_code":"5",
    "gn:admin2_code":"107",
    "gn:asciiname":"Perseverancia (El Rosario)",
    "gn:country_code":"MX",
    "gn:dem":590,
    "gn:feature_class":"P",
    "gn:feature_code":"PPL",
    "gn:name":"Perseverancia (El Rosario)",
    "gn:population":16,
    "gn:timezone":"America/Mexico_City",
    "iso:country":"MX",
    "wof:name":"Perseverancia (El Rosario)",
    "wof:placetype":"locality",
    "wof:population":16
},
  "geometry": {"coordinates":[-93.04083,16.20333],"type":"Point"}
}