{
  "type": "Feature",
  "properties": {
    "gn:admin1_code":"6",
    "gn:admin2_code":"32.0",
    "gn:asciiname":"El Cofleno",
    "gn:country_code":"MX",
    "gn:dem":1685,
    "gn:feature_class":"P",
    "gn:feature_code":"PPL",
    "gn:name":"El Cofle\u00f1o",
    "gn:population":7,
    "gn:timezone":"America/Chihuahua",
    "iso:country":"MX",
    "name:und_x_variant":[
        "El Cofle\u00f1o"
    ],
    "wof:name":"El Cofleno",
    "wof:placetype":"locality",
    "wof:population":7
},
  "geometry": {"coordinates":[-105.65321000000002,27.06384000000001],"type":"Point"}
}