{
  "type": "Feature",
  "properties": {
    "gn:admin1_code":"30",
    "gn:admin2_code":"89.0",
    "gn:asciiname":"San Rafael Dos [Granja]",
    "gn:country_code":"MX",
    "gn:dem":57,
    "gn:feature_class":"P",
    "gn:feature_code":"PPL",
    "gn:name":"San Rafael Dos [Granja]",
    "gn:population":7,
    "gn:timezone":"America/Mexico_City",
    "iso:country":"MX",
    "wof:name":"San Rafael Dos [Granja]",
    "wof:placetype":"locality",
    "wof:population":7
},
  "geometry": {"coordinates":[-94.70278,17.95194],"type":"Point"}
}