{
  "type": "Feature",
  "properties": {
    "gn:admin1_code":"21",
    "gn:admin2_code":"197.0",
    "gn:asciiname":"Unidad Deportiva (Ocotzotal)",
    "gn:country_code":"MX",
    "gn:dem":1190,
    "gn:feature_class":"P",
    "gn:feature_code":"PPL",
    "gn:name":"Unidad Deportiva (Ocotzotal)",
    "gn:population":280,
    "gn:timezone":"America/Mexico_City",
    "iso:country":"MX",
    "wof:name":"Unidad Deportiva (Ocotzotal)",
    "wof:placetype":"locality",
    "wof:population":280
},
  "geometry": {"coordinates":[-97.96881999999999,20.24572],"type":"Point"}
}