{
  "type": "Feature",
  "properties": {
    "gn:admin1_code":"15",
    "gn:admin2_code":"23.0",
    "gn:asciiname":"La Planada",
    "gn:country_code":"MX",
    "gn:dem":2251,
    "gn:feature_class":"P",
    "gn:feature_code":"PPL",
    "gn:name":"La Planada",
    "gn:population":2554,
    "gn:timezone":"America/Mexico_City",
    "iso:country":"MX",
    "wof:name":"La Planada",
    "wof:placetype":"locality",
    "wof:population":2554
},
  "geometry": {"coordinates":[-99.18267,19.78129],"type":"Point"}
}