{
  "type": "Feature",
  "properties": {
    "gn:admin1_code":"11",
    "gn:admin2_code":"9",
    "gn:asciiname":"El Rocio",
    "gn:country_code":"MX",
    "gn:dem":1840,
    "gn:feature_class":"P",
    "gn:feature_code":"PPL",
    "gn:name":"El Roc\u00edo",
    "gn:population":19,
    "gn:timezone":"America/Mexico_City",
    "iso:country":"MX",
    "name:und_x_variant":[
        "El Roc\u00edo"
    ],
    "wof:name":"El Rocio",
    "wof:placetype":"locality",
    "wof:population":19
},
  "geometry": {"coordinates":[-100.71333,20.73778],"type":"Point"}
}