{
  "type": "Feature",
  "properties": {
    "gn:admin1_code":"6",
    "gn:asciiname":"Bajio Largo",
    "gn:country_code":"MX",
    "gn:dem":2687,
    "gn:feature_class":"P",
    "gn:feature_code":"PPL",
    "gn:name":"Baj\u00edo Largo",
    "gn:population":0,
    "gn:timezone":"America/Monterrey",
    "iso:country":"MX",
    "wof:name":"Bajio Largo",
    "wof:placetype":"locality"
},
  "geometry": {"coordinates":[-106.2141,25.94971],"type":"Point"}
}