{
  "type": "Feature",
  "properties": {
    "gn:admin1_code":"5",
    "gn:admin2_code":"79",
    "gn:asciiname":"El Refugio",
    "gn:country_code":"MX",
    "gn:dem":937,
    "gn:feature_class":"P",
    "gn:feature_code":"PPL",
    "gn:name":"El Refugio",
    "gn:population":9,
    "gn:timezone":"America/Mexico_City",
    "iso:country":"MX",
    "name:ceb_x_preferred":[
        "El Refugio"
    ],
    "name:deu_x_preferred":[
        "El Refugio"
    ],
    "name:ita_x_preferred":[
        "El Refugio"
    ],
    "name:nld_x_preferred":[
        "El Refugio"
    ],
    "name:por_x_preferred":[
        "El Refugio"
    ],
    "name:spa_x_preferred":[
        "El refugio"
    ],
    "name:swe_x_preferred":[
        "El Refugio"
    ],
    "wof:name":"El Refugio",
    "wof:placetype":"locality",
    "wof:population":9
},
  "geometry": {"coordinates":[-93.2225,16.89],"type":"Point"}
}