{
  "type": "Feature",
  "properties": {
    "gn:admin1_code":"11",
    "gn:admin2_code":"43",
    "gn:asciiname":"La Pena Colorada",
    "gn:country_code":"MX",
    "gn:dem":2097,
    "gn:feature_class":"P",
    "gn:feature_code":"PPL",
    "gn:name":"La Pe\u00f1a Colorada",
    "gn:population":14,
    "gn:timezone":"America/Mexico_City",
    "iso:country":"MX",
    "name:und_x_variant":[
        "La Pe\u00f1a Colorada"
    ],
    "wof:name":"La Pena Colorada",
    "wof:placetype":"locality",
    "wof:population":14
},
  "geometry": {"coordinates":[-100.24333,21.32083],"type":"Point"}
}