{
  "type": "Feature",
  "properties": {
    "gn:admin1_code":"30",
    "gn:admin2_code":"80.0",
    "gn:asciiname":"Zacamitla",
    "gn:country_code":"MX",
    "gn:dem":1189,
    "gn:feature_class":"P",
    "gn:feature_code":"PPL",
    "gn:name":"Zacamitla",
    "gn:population":0,
    "gn:timezone":"America/Mexico_City",
    "iso:country":"MX",
    "name:spa_x_preferred":[
        "Zacamitla"
    ],
    "wof:name":"Zacamitla",
    "wof:placetype":"locality"
},
  "geometry": {"coordinates":[-96.92424,19.05085],"type":"Point"}
}