{
  "type": "Feature",
  "properties": {
    "gn:admin1_code":"11",
    "gn:admin2_code":"17",
    "gn:asciiname":"Pozo del Soliman",
    "gn:country_code":"MX",
    "gn:dem":1733,
    "gn:feature_class":"P",
    "gn:feature_code":"PPL",
    "gn:name":"Pozo del Solim\u00e1n",
    "gn:population":24,
    "gn:timezone":"America/Mexico_City",
    "iso:country":"MX",
    "name:und_x_variant":[
        "Pozo del Solim\u00e1n"
    ],
    "wof:name":"Pozo del Soliman",
    "wof:placetype":"locality",
    "wof:population":24
},
  "geometry": {"coordinates":[-101.33611000000001,20.71333],"type":"Point"}
}