{
  "type": "Feature",
  "properties": {
    "gn:admin1_code":"22",
    "gn:admin2_code":"14",
    "gn:asciiname":"La Milpa",
    "gn:country_code":"MX",
    "gn:dem":1959,
    "gn:feature_class":"P",
    "gn:feature_code":"PPL",
    "gn:name":"La Milpa",
    "gn:population":28,
    "gn:timezone":"America/Mexico_City",
    "iso:country":"MX",
    "wof:name":"La Milpa",
    "wof:placetype":"locality",
    "wof:population":28
},
  "geometry": {"coordinates":[-100.45028000000001,20.75111],"type":"Point"}
}