{
  "type": "Feature",
  "properties": {
    "gn:admin1_code":"7",
    "gn:admin2_code":"5.0",
    "gn:asciiname":"Veintidos de Febrero",
    "gn:country_code":"MX",
    "gn:dem":390,
    "gn:feature_class":"P",
    "gn:feature_code":"PPL",
    "gn:name":"Veintid\u00f3s de Febrero",
    "gn:population":4,
    "gn:timezone":"America/Monterrey",
    "iso:country":"MX",
    "name:und_x_variant":[
        "Veintid\u00f3s de Febrero"
    ],
    "wof:name":"Veintidos de Febrero",
    "wof:placetype":"locality",
    "wof:population":4
},
  "geometry": {"coordinates":[-100.58479,26.83501],"type":"Point"}
}