{
  "type": "Feature",
  "properties": {
    "gn:admin1_code":"15.0",
    "gn:admin2_code":"124.0",
    "gn:asciiname":"Las Suizas",
    "gn:country_code":"MX",
    "gn:dem":2684,
    "gn:feature_class":"P",
    "gn:feature_code":"PPL",
    "gn:name":"Las Suizas",
    "gn:population":0,
    "gn:timezone":"America/Mexico_City",
    "iso:country":"MX",
    "name:spa_x_preferred":[
        "Las Suizas"
    ],
    "wof:name":"Las Suizas",
    "wof:placetype":"locality"
},
  "geometry": {"coordinates":[-100.11351000000001,19.53499],"type":"Point"}
}