{
  "type": "Feature",
  "properties": {
    "gn:admin1_code":"30",
    "gn:admin2_code":"163.0",
    "gn:asciiname":"La Canada",
    "gn:country_code":"MX",
    "gn:dem":1013,
    "gn:feature_class":"P",
    "gn:feature_code":"PPL",
    "gn:name":"La Ca\u00f1ada",
    "gn:population":110,
    "gn:timezone":"America/Mexico_City",
    "iso:country":"MX",
    "name:und_x_variant":[
        "La Ca\u00f1ada"
    ],
    "wof:name":"La Canada",
    "wof:placetype":"locality",
    "wof:population":110
},
  "geometry": {"coordinates":[-96.95111,19.79833],"type":"Point"}
}