{
  "type": "Feature",
  "properties": {
    "gn:admin1_code":"6",
    "gn:admin2_code":"8",
    "gn:asciiname":"Aguaje la Trinidad",
    "gn:country_code":"MX",
    "gn:dem":615,
    "gn:feature_class":"P",
    "gn:feature_code":"PPL",
    "gn:name":"Aguaje la Trinidad",
    "gn:population":9,
    "gn:timezone":"America/Chihuahua",
    "iso:country":"MX",
    "wof:name":"Aguaje la Trinidad",
    "wof:placetype":"locality",
    "wof:population":9
},
  "geometry": {"coordinates":[-107.84685,27.0041],"type":"Point"}
}