{
  "type": "Feature",
  "properties": {
    "gn:admin1_code":"4",
    "gn:admin2_code":"10.0",
    "gn:asciiname":"Manuel Castilla Brito",
    "gn:country_code":"MX",
    "gn:dem":245,
    "gn:feature_class":"P",
    "gn:feature_code":"PPL",
    "gn:name":"Manuel Castilla Brito",
    "gn:population":0,
    "gn:timezone":"America/Merida",
    "iso:country":"MX",
    "name:spa_x_preferred":[
        "El Diecisiete"
    ],
    "name:spa_x_variant":[
        "General Manuel Castilla Brito",
        "Manuel Castilla Brito"
    ],
    "wof:name":"Manuel Castilla Brito",
    "wof:placetype":"locality"
},
  "geometry": {"coordinates":[-89.44062,18.35954],"type":"Point"}
}