{
  "type": "Feature",
  "properties": {
    "gn:admin1_code":"25",
    "gn:admin2_code":"4.0",
    "gn:asciiname":"Mololoa",
    "gn:country_code":"MX",
    "gn:dem":144,
    "gn:feature_class":"P",
    "gn:feature_code":"PPL",
    "gn:name":"Mololoa",
    "gn:population":0,
    "gn:timezone":"America/Mazatlan",
    "iso:country":"MX",
    "name:spa_x_preferred":[
        "Mololoa"
    ],
    "wof:name":"Mololoa",
    "wof:placetype":"locality"
},
  "geometry": {"coordinates":[-106.09901000000001,23.28935],"type":"Point"}
}