{
  "type": "Feature",
  "properties": {
    "gn:admin1_code":"25.0",
    "gn:admin2_code":"6.0",
    "gn:asciiname":"Los Sabinos",
    "gn:country_code":"MX",
    "gn:dem":61,
    "gn:feature_class":"P",
    "gn:feature_code":"PPL",
    "gn:name":"Los Sabinos",
    "gn:population":0,
    "gn:timezone":"America/Mazatlan",
    "iso:country":"MX",
    "name:spa_x_preferred":[
        "Los Sabinos"
    ],
    "wof:name":"Los Sabinos",
    "wof:placetype":"locality"
},
  "geometry": {"coordinates":[-107.36633999999999,24.92844],"type":"Point"}
}