{
  "type": "Feature",
  "properties": {
    "gn:admin1_code":"14.0",
    "gn:admin2_code":"79.0",
    "gn:asciiname":"La Mojonera",
    "gn:country_code":"MX",
    "gn:dem":2031,
    "gn:feature_class":"P",
    "gn:feature_code":"PPL",
    "gn:name":"La Mojonera",
    "gn:population":0,
    "gn:timezone":"America/Mexico_City",
    "iso:country":"MX",
    "name:spa_x_preferred":[
        "La Mojonera"
    ],
    "wof:name":"La Mojonera",
    "wof:placetype":"locality"
},
  "geometry": {"coordinates":[-103.4062,19.92508],"type":"Point"}
}