{
  "type": "Feature",
  "properties": {
    "gn:admin1_code":"25.0",
    "gn:admin2_code":"10.0",
    "gn:asciiname":"Cacalotan",
    "gn:cc2":"MX",
    "gn:country_code":"MX",
    "gn:dem":397,
    "gn:feature_class":"P",
    "gn:feature_code":"PPL",
    "gn:name":"Cacalot\u00e1n",
    "gn:population":0,
    "gn:timezone":"America/Mazatlan",
    "iso:country":"MX",
    "name:und_x_variant":[
        "Cacalat\u00e1n",
        "Cacalot\u00e1n"
    ],
    "wof:name":"Cacalotan",
    "wof:placetype":"locality"
},
  "geometry": {"coordinates":[-108.38333,26.18333],"type":"Point"}
}