{
  "type": "Feature",
  "properties": {
    "gn:admin1_code":"6",
    "gn:admin2_code":"18.0",
    "gn:asciiname":"La Muralla",
    "gn:cc2":"MX",
    "gn:country_code":"MX",
    "gn:dem":1793,
    "gn:feature_class":"P",
    "gn:feature_code":"PPL",
    "gn:name":"La Muralla",
    "gn:population":0,
    "gn:timezone":"America/Chihuahua",
    "iso:country":"MX",
    "name:und_x_variant":[
        "Muralla",
        "La Muralla"
    ],
    "wof:name":"La Muralla",
    "wof:placetype":"locality"
},
  "geometry": {"coordinates":[-106.68333,28.26667],"type":"Point"}
}