{
  "type": "Feature",
  "properties": {
    "gn:admin1_code":"29",
    "gn:admin2_code":"43.0",
    "gn:asciiname":"Covadonga",
    "gn:country_code":"MX",
    "gn:dem":2409,
    "gn:feature_class":"P",
    "gn:feature_code":"PPL",
    "gn:name":"Covadonga",
    "gn:population":0,
    "gn:timezone":"America/Mexico_City",
    "iso:country":"MX",
    "name:spa_x_preferred":[
        "Covadonga"
    ],
    "wof:name":"Covadonga",
    "wof:placetype":"locality"
},
  "geometry": {"coordinates":[-98.16213999999999,19.39488],"type":"Point"}
}