{
  "type": "Feature",
  "properties": {
    "gn:admin1_code":"26",
    "gn:admin2_code":"20.0",
    "gn:asciiname":"La Pilarena",
    "gn:country_code":"MX",
    "gn:dem":463,
    "gn:feature_class":"P",
    "gn:feature_code":"PPL",
    "gn:name":"La Pilare\u00f1a",
    "gn:population":0,
    "gn:timezone":"America/Hermosillo",
    "iso:country":"MX",
    "name:spa_x_preferred":[
        "La Pilare\u00f1a"
    ],
    "wof:name":"La Pilarena",
    "wof:placetype":"locality"
},
  "geometry": {"coordinates":[-110.9378,29.67939],"type":"Point"}
}