{
  "type": "Feature",
  "properties": {
    "gn:admin1_code":"23",
    "gn:admin2_code":"9.0",
    "gn:asciiname":"Balam Canche",
    "gn:country_code":"MX",
    "gn:dem":13,
    "gn:feature_class":"P",
    "gn:feature_code":"PPL",
    "gn:name":"Balam Canch\u00e9",
    "gn:population":5,
    "gn:timezone":"America/Cancun",
    "iso:country":"MX",
    "name:und_x_variant":[
        "Balam Canch\u00e9"
    ],
    "wof:name":"Balam Canche",
    "wof:placetype":"locality",
    "wof:population":5
},
  "geometry": {"coordinates":[-87.39372,20.28251],"type":"Point"}
}