{
  "type": "Feature",
  "properties": {
    "gn:admin1_code":"7",
    "gn:admin2_code":"7.0",
    "gn:asciiname":"Rancho San Fernando",
    "gn:country_code":"MX",
    "gn:dem":822,
    "gn:feature_class":"P",
    "gn:feature_code":"PPL",
    "gn:name":"Rancho San Fernando",
    "gn:population":0,
    "gn:timezone":"America/Monterrey",
    "iso:country":"MX",
    "wof:name":"Rancho San Fernando",
    "wof:placetype":"locality"
},
  "geometry": {"coordinates":[-102.51667,26.61667000000001],"type":"Point"}
}