{
  "type": "Feature",
  "properties": {
    "gn:admin1_code":"20",
    "gn:admin2_code":"217",
    "gn:asciiname":"Ladera de Encino Amarillo",
    "gn:country_code":"MX",
    "gn:dem":2343,
    "gn:feature_class":"P",
    "gn:feature_code":"PPL",
    "gn:name":"Ladera de Encino Amarillo",
    "gn:population":35,
    "gn:timezone":"America/Mexico_City",
    "iso:country":"MX",
    "wof:name":"Ladera de Encino Amarillo",
    "wof:placetype":"locality",
    "wof:population":35
},
  "geometry": {"coordinates":[-97.06917,17.13611],"type":"Point"}
}