{
  "type": "Feature",
  "properties": {
    "gn:admin1_code":"6",
    "gn:admin2_code":"8.0",
    "gn:asciiname":"Coreareachi",
    "gn:country_code":"MX",
    "gn:dem":2151,
    "gn:feature_class":"P",
    "gn:feature_code":"PPL",
    "gn:name":"Coreareachi",
    "gn:population":15,
    "gn:timezone":"America/Chihuahua",
    "iso:country":"MX",
    "name:spa_x_preferred":[
        "Coreareachi"
    ],
    "wof:name":"Coreareachi",
    "wof:placetype":"locality",
    "wof:population":15
},
  "geometry": {"coordinates":[-107.50601,26.95438],"type":"Point"}
}