{
  "type": "Feature",
  "properties": {
    "gn:admin1_code":"27",
    "gn:admin2_code":"2.0",
    "gn:asciiname":"Ulloa",
    "gn:cc2":"MX",
    "gn:country_code":"MX",
    "gn:dem":6,
    "gn:feature_class":"P",
    "gn:feature_code":"PPL",
    "gn:name":"Ulloa",
    "gn:population":0,
    "gn:timezone":"America/Mexico_City",
    "iso:country":"MX",
    "name:ceb_x_preferred":[
        "Ulloa"
    ],
    "name:deu_x_preferred":[
        "Ulloa"
    ],
    "name:fra_x_preferred":[
        "Ulloa"
    ],
    "name:glg_x_preferred":[
        "Ulloa"
    ],
    "name:ita_x_preferred":[
        "Ulloa"
    ],
    "name:jpn_x_preferred":[
        "\u30a6\u30b8\u30e7\u30a2"
    ],
    "name:msa_x_preferred":[
        "Ulloa"
    ],
    "name:rus_x_preferred":[
        "\u0423\u043b\u044c\u043e\u0430"
    ],
    "name:sco_x_preferred":[
        "Ulloa"
    ],
    "name:spa_x_preferred":[
        "Ulloa"
    ],
    "name:swe_x_preferred":[
        "Ulloa"
    ],
    "name:ukr_x_preferred":[
        "\u0423\u043b\u044c\u043e\u0430"
    ],
    "name:und_x_variant":[
        "Ullua"
    ],
    "name:vie_x_preferred":[
        "Ulloa"
    ],
    "wof:name":"Ulloa",
    "wof:placetype":"locality"
},
  "geometry": {"coordinates":[-93.56667,18.23333],"type":"Point"}
}