{
  "type": "Feature",
  "properties": {
    "gn:admin1_code":"32",
    "gn:admin2_code":"31.0",
    "gn:asciiname":"Tanque",
    "gn:country_code":"MX",
    "gn:dem":2414,
    "gn:feature_class":"P",
    "gn:feature_code":"PPL",
    "gn:name":"Tanque",
    "gn:population":0,
    "gn:timezone":"America/Mexico_City",
    "iso:country":"MX",
    "name:ita_x_preferred":[
        "Tanque"
    ],
    "name:por_x_preferred":[
        "Tanque"
    ],
    "name:spa_x_preferred":[
        "Tanque"
    ],
    "wof:name":"Tanque",
    "wof:placetype":"locality"
},
  "geometry": {"coordinates":[-103.59350999999999,22.33388],"type":"Point"}
}