{
  "type": "Feature",
  "properties": {
    "gn:admin1_code":"27",
    "gn:admin2_code":"3.0",
    "gn:asciiname":"El Zapotal",
    "gn:country_code":"MX",
    "gn:dem":1,
    "gn:feature_class":"P",
    "gn:feature_code":"PPL",
    "gn:name":"El Zapotal",
    "gn:population":0,
    "gn:timezone":"America/Mexico_City",
    "iso:country":"MX",
    "name:fra_x_preferred":[
        "El Zapotal"
    ],
    "name:spa_x_preferred":[
        "El Zapotal"
    ],
    "wof:name":"El Zapotal",
    "wof:placetype":"locality"
},
  "geometry": {"coordinates":[-92.57619,18.55257000000001],"type":"Point"}
}