{
  "type": "Feature",
  "properties": {
    "gn:gn_country":"MX",
    "gn:gn_fcode":"PPL",
    "gn:gn_pop":0,
    "iso:country":"MX",
    "name:spa_x_preferred":[
        "Garza Gonz\u00e1lez"
    ],
    "qs_pg:aaroncc":"MX",
    "qs_pg:gn_country":"MX",
    "qs_pg:gn_fcode":"PPL",
    "qs_pg:gn_pop":0,
    "qs_pg:name":"Garza Gonz\u00e1lez",
    "qs_pg:name_adm0":"M\u00e9xico",
    "qs_pg:name_adm1":"Nuevo Leon",
    "qs_pg:photos_9k":1,
    "qs_pg:photos_9r":1,
    "qs_pg:photos_all":11,
    "qs_pg:photos_sr":0,
    "qs_pg:pop_sr":0,
    "qs_pg:qs_pg_placetype":"locality",
    "qs_pg:qs_pg_placetype_gp":"Town",
    "qs_pg:woe_adm0":23424900,
    "woe:adm0_id":23424900,
    "woe:name_adm0":"M\u00e9xico",
    "woe:name_adm1":"Nuevo Leon",
    "woe:placetype":"Town",
    "wof:name":"Garza Gonz\u00e1lez",
    "wof:placetype":"locality"
},
  "geometry": {"coordinates":[-99.62528,25.83176],"type":"Point"}
}