{
  "type": "Feature",
  "properties": {
    "gn:admin1_code":"26",
    "gn:admin2_code":"3.0",
    "gn:asciiname":"Choquinahui (El Cobre)",
    "gn:country_code":"MX",
    "gn:dem":575,
    "gn:feature_class":"P",
    "gn:feature_code":"PPL",
    "gn:name":"Choquinahui (El Cobre)",
    "gn:population":61,
    "gn:timezone":"America/Hermosillo",
    "iso:country":"MX",
    "wof:name":"Choquinahui (El Cobre)",
    "wof:placetype":"locality",
    "wof:population":61
},
  "geometry": {"coordinates":[-108.67749999999999,26.98194],"type":"Point"}
}