{
  "type": "Feature",
  "properties": {
    "gn:admin1_code":"5.0",
    "gn:admin2_code":"106.0",
    "gn:asciiname":"San Antonio Chilaljob",
    "gn:country_code":"MX",
    "gn:dem":615,
    "gn:feature_class":"P",
    "gn:feature_code":"PPL",
    "gn:name":"San Antonio Chilaljob",
    "gn:population":0,
    "gn:timezone":"America/Mexico_City",
    "iso:country":"MX",
    "name:spa_x_preferred":[
        "Chilaljob"
    ],
    "name:spa_x_variant":[
        "San Antonio Chilaljob"
    ],
    "wof:name":"San Antonio Chilaljob",
    "wof:placetype":"locality"
},
  "geometry": {"coordinates":[-92.51309999999999,16.28672000000001],"type":"Point"}
}