{
  "type": "Feature",
  "properties": {
    "gn:admin1_code":"28",
    "gn:admin2_code":"41.0",
    "gn:asciiname":"El Olvido",
    "gn:cc2":"MX",
    "gn:country_code":"MX",
    "gn:dem":878,
    "gn:feature_class":"P",
    "gn:feature_code":"PPL",
    "gn:name":"El Olvido",
    "gn:population":0,
    "gn:timezone":"America/Monterrey",
    "iso:country":"MX",
    "name:und_x_variant":[
        "Olvido",
        "El Olvido"
    ],
    "wof:name":"El Olvido",
    "wof:placetype":"locality"
},
  "geometry": {"coordinates":[-99.21666999999999,23.58333],"type":"Point"}
}