{
  "type": "Feature",
  "properties": {
    "gn:admin1_code":"6",
    "gn:admin2_code":"9",
    "gn:asciiname":"Rosanachi (Ricubitare)",
    "gn:country_code":"MX",
    "gn:dem":2385,
    "gn:feature_class":"P",
    "gn:feature_code":"PPL",
    "gn:name":"Rosanachi (Ricubitare)",
    "gn:population":9,
    "gn:timezone":"America/Chihuahua",
    "iso:country":"MX",
    "wof:name":"Rosanachi (Ricubitare)",
    "wof:placetype":"locality",
    "wof:population":9
},
  "geometry": {"coordinates":[-107.61909,27.74408],"type":"Point"}
}