{
  "type": "Feature",
  "properties": {
    "gn:admin1_code":"30",
    "gn:admin2_code":"127.0",
    "gn:asciiname":"Potrero Nuevo",
    "gn:country_code":"MX",
    "gn:dem":3232,
    "gn:feature_class":"P",
    "gn:feature_code":"PPL",
    "gn:name":"Potrero Nuevo",
    "gn:population":175,
    "gn:timezone":"America/Mexico_City",
    "iso:country":"MX",
    "wof:name":"Potrero Nuevo",
    "wof:placetype":"locality",
    "wof:population":175
},
  "geometry": {"coordinates":[-97.20083,19.03917],"type":"Point"}
}