{
  "type": "Feature",
  "properties": {
    "gn:admin1_code":"21",
    "gn:admin2_code":"174.0",
    "gn:asciiname":"Chicolate",
    "gn:country_code":"MX",
    "gn:dem":1585,
    "gn:feature_class":"P",
    "gn:feature_code":"PPL",
    "gn:name":"Chicolate",
    "gn:population":6,
    "gn:timezone":"America/Mexico_City",
    "iso:country":"MX",
    "wof:name":"Chicolate",
    "wof:placetype":"locality",
    "wof:population":6
},
  "geometry": {"coordinates":[-97.35634,19.89214],"type":"Point"}
}