{
  "type": "Feature",
  "properties": {
    "gn:admin1_code":"22",
    "gn:admin2_code":"13.0",
    "gn:asciiname":"El Motoshi (La Paz)",
    "gn:country_code":"MX",
    "gn:dem":1340,
    "gn:feature_class":"P",
    "gn:feature_code":"PPL",
    "gn:name":"El Motosh\u00ed (La Paz)",
    "gn:population":65,
    "gn:timezone":"America/Mexico_City",
    "iso:country":"MX",
    "wof:name":"El Motoshi (La Paz)",
    "wof:placetype":"locality",
    "wof:population":65
},
  "geometry": {"coordinates":[-99.77861,21.05806],"type":"Point"}
}