{
  "type": "Feature",
  "properties": {
    "gn:admin1_code":"30",
    "gn:admin2_code":"175",
    "gn:asciiname":"Las Hamacas (Kilometro 5)",
    "gn:country_code":"MX",
    "gn:dem":67,
    "gn:feature_class":"P",
    "gn:feature_code":"PPL",
    "gn:name":"Las Hamacas (Kil\u00f3metro 5)",
    "gn:population":10,
    "gn:timezone":"America/Mexico_City",
    "iso:country":"MX",
    "name:und_x_variant":[
        "Las Hamacas (Kil\u00f3metro 5)"
    ],
    "wof:name":"Las Hamacas (Kilometro 5)",
    "wof:placetype":"locality",
    "wof:population":10
},
  "geometry": {"coordinates":[-97.48111,20.56667],"type":"Point"}
}