{
  "type": "Feature",
  "properties": {
    "gn:admin1_code":"14",
    "gn:admin2_code":"85.0",
    "gn:asciiname":"Nigromante",
    "gn:country_code":"MX",
    "gn:dem":1596,
    "gn:feature_class":"P",
    "gn:feature_code":"PPL",
    "gn:name":"Nigromante",
    "gn:population":0,
    "gn:timezone":"America/Mexico_City",
    "iso:country":"MX",
    "name:spa_x_preferred":[
        "Nigromante"
    ],
    "name:spa_x_variant":[
        "San Juan de la Monta\u00f1a"
    ],
    "wof:name":"Nigromante",
    "wof:placetype":"locality"
},
  "geometry": {"coordinates":[-103.08938000000001,19.66253],"type":"Point"}
}