{
  "type": "Feature",
  "properties": {
    "gn:admin1_code":"25",
    "gn:admin2_code":"12.0",
    "gn:asciiname":"La Embocada",
    "gn:country_code":"MX",
    "gn:dem":56,
    "gn:feature_class":"P",
    "gn:feature_code":"PPL",
    "gn:name":"La Embocada",
    "gn:population":0,
    "gn:timezone":"America/Mazatlan",
    "iso:country":"MX",
    "name:spa_x_preferred":[
        "La Embocada"
    ],
    "wof:name":"La Embocada",
    "wof:placetype":"locality"
},
  "geometry": {"coordinates":[-106.45808,23.41117],"type":"Point"}
}