{
  "type": "Feature",
  "properties": {
    "gn:admin1_code":"32",
    "gn:admin2_code":"52.0",
    "gn:asciiname":"Francisco I. Madero (Aguas Muertas)",
    "gn:country_code":"MX",
    "gn:dem":2408,
    "gn:feature_class":"P",
    "gn:feature_code":"PPL",
    "gn:name":"Francisco I. Madero (Aguas Muertas)",
    "gn:population":191,
    "gn:timezone":"America/Mexico_City",
    "iso:country":"MX",
    "wof:name":"Francisco I. Madero (Aguas Muertas)",
    "wof:placetype":"locality",
    "wof:population":191
},
  "geometry": {"coordinates":[-101.82444,22.12722],"type":"Point"}
}