{
  "type": "Feature",
  "properties": {
    "gn:admin1_code":"26",
    "gn:admin2_code":"26.0",
    "gn:asciiname":"El Resbalon",
    "gn:country_code":"MX",
    "gn:dem":19,
    "gn:feature_class":"P",
    "gn:feature_code":"PPL",
    "gn:name":"El Resbal\u00f3n",
    "gn:population":0,
    "gn:timezone":"America/Hermosillo",
    "iso:country":"MX",
    "name:spa_x_preferred":[
        "El Resbal\u00f3n"
    ],
    "wof:name":"El Resbalon",
    "wof:placetype":"locality"
},
  "geometry": {"coordinates":[-109.65649999999999,26.99642],"type":"Point"}
}