{
  "type": "Feature",
  "properties": {
    "gn:admin1_code":"4.0",
    "gn:asciiname":"Cocoite",
    "gn:country_code":"MX",
    "gn:dem":29,
    "gn:feature_class":"P",
    "gn:feature_code":"PPL",
    "gn:name":"Cocoite",
    "gn:population":0,
    "gn:timezone":"America/Merida",
    "iso:country":"MX",
    "name:spa_x_preferred":[
        "Cocoite"
    ],
    "wof:name":"Cocoite",
    "wof:placetype":"locality"
},
  "geometry": {"coordinates":[-90.32831,19.09958],"type":"Point"}
}