{
  "type": "Feature",
  "properties": {
    "gn:admin1_code":"30",
    "gn:admin2_code":"48",
    "gn:asciiname":"Ejido la Colmena",
    "gn:country_code":"MX",
    "gn:dem":35,
    "gn:feature_class":"P",
    "gn:feature_code":"PPL",
    "gn:name":"Ejido la Colmena",
    "gn:population":25,
    "gn:timezone":"America/Mexico_City",
    "iso:country":"MX",
    "wof:name":"Ejido la Colmena",
    "wof:placetype":"locality",
    "wof:population":25
},
  "geometry": {"coordinates":[-94.63889,17.985],"type":"Point"}
}