{
  "type": "Feature",
  "properties": {
    "gn:admin1_code":"30.0",
    "gn:admin2_code":"150.0",
    "gn:asciiname":"El Eden",
    "gn:country_code":"MX",
    "gn:dem":7,
    "gn:feature_class":"P",
    "gn:feature_code":"PPL",
    "gn:name":"El Ed\u00e9n",
    "gn:population":0,
    "gn:timezone":"America/Mexico_City",
    "iso:country":"MX",
    "name:spa_x_preferred":[
        "El Ed\u00e9n"
    ],
    "wof:name":"El Eden",
    "wof:placetype":"locality"
},
  "geometry": {"coordinates":[-97.63479,21.56458],"type":"Point"}
}