{
  "type": "Feature",
  "properties": {
    "gn:admin1_code":"10",
    "gn:admin2_code":"14.0",
    "gn:asciiname":"Los Limoncitos",
    "gn:country_code":"MX",
    "gn:dem":1801,
    "gn:feature_class":"P",
    "gn:feature_code":"PPL",
    "gn:name":"Los Limoncitos",
    "gn:population":0,
    "gn:timezone":"America/Mexico_City",
    "iso:country":"MX",
    "name:spa_x_preferred":[
        "Los Limoncitos"
    ],
    "wof:name":"Los Limoncitos",
    "wof:placetype":"locality"
},
  "geometry": {"coordinates":[-104.20198000000001,22.81994],"type":"Point"}
}