{
  "type": "Feature",
  "properties": {
    "gn:admin1_code":"12.0",
    "gn:admin2_code":"48.0",
    "gn:asciiname":"Barranca las Parotas",
    "gn:country_code":"MX",
    "gn:dem":695,
    "gn:feature_class":"P",
    "gn:feature_code":"PPL",
    "gn:name":"Barranca las Parotas",
    "gn:population":0,
    "gn:timezone":"America/Mexico_City",
    "iso:country":"MX",
    "name:spa_x_preferred":[
        "Barranca las Parotas"
    ],
    "wof:name":"Barranca las Parotas",
    "wof:placetype":"locality"
},
  "geometry": {"coordinates":[-101.18474000000001,17.81121],"type":"Point"}
}