{
  "type": "Feature",
  "properties": {
    "gn:admin1_code":"26",
    "gn:asciiname":"Jocopori",
    "gn:country_code":"MX",
    "gn:dem":716,
    "gn:feature_class":"P",
    "gn:feature_code":"PPL",
    "gn:name":"Jocopori",
    "gn:population":0,
    "gn:timezone":"America/Mazatlan",
    "iso:country":"MX",
    "name:spa_x_preferred":[
        "Jocopori"
    ],
    "wof:name":"Jocopori",
    "wof:placetype":"locality"
},
  "geometry": {"coordinates":[-108.41404,26.96905],"type":"Point"}
}