{
  "type": "Feature",
  "properties": {
    "gn:admin1_code":"30",
    "gn:admin2_code":"125.0",
    "gn:asciiname":"Pozo del Monte",
    "gn:country_code":"MX",
    "gn:dem":572,
    "gn:feature_class":"P",
    "gn:feature_code":"PPL",
    "gn:name":"Pozo del Monte",
    "gn:population":0,
    "gn:timezone":"America/Mexico_City",
    "iso:country":"MX",
    "name:spa_x_preferred":[
        "Pozo del Monte"
    ],
    "wof:name":"Pozo del Monte",
    "wof:placetype":"locality"
},
  "geometry": {"coordinates":[-96.74587,19.01855],"type":"Point"}
}