{
  "type": "Feature",
  "properties": {
    "gn:admin1_code":"6.0",
    "gn:admin2_code":"27.0",
    "gn:asciiname":"Jose Maria",
    "gn:country_code":"MX",
    "gn:dem":2306,
    "gn:feature_class":"P",
    "gn:feature_code":"PPL",
    "gn:name":"Jos\u00e9 Mar\u00eda",
    "gn:population":0,
    "gn:timezone":"America/Chihuahua",
    "iso:country":"MX",
    "wof:name":"Jose Maria",
    "wof:placetype":"locality"
},
  "geometry": {"coordinates":[-107.11667,27.51667],"type":"Point"}
}