{
  "type": "Feature",
  "properties": {
    "gn:admin1_code":"6.0",
    "gn:admin2_code":"40.0",
    "gn:asciiname":"La Huerta Escondida",
    "gn:country_code":"MX",
    "gn:dem":2112,
    "gn:feature_class":"P",
    "gn:feature_code":"PPL",
    "gn:name":"La Huerta Escondida",
    "gn:population":0,
    "gn:timezone":"America/Chihuahua",
    "iso:country":"MX",
    "name:spa_x_preferred":[
        "La Huerta Escondida"
    ],
    "wof:name":"La Huerta Escondida",
    "wof:placetype":"locality"
},
  "geometry": {"coordinates":[-108.13056,29.15091],"type":"Point"}
}