{
  "type": "Feature",
  "properties": {
    "gn:admin1_code":"23",
    "gn:admin2_code":"7.0",
    "gn:asciiname":"Arizona",
    "gn:country_code":"MX",
    "gn:dem":9,
    "gn:feature_class":"P",
    "gn:feature_code":"PPL",
    "gn:name":"Arizona",
    "gn:population":0,
    "gn:timezone":"America/Cancun",
    "iso:country":"MX",
    "name:spa_x_preferred":[
        "Arizona"
    ],
    "wof:name":"Arizona",
    "wof:placetype":"locality"
},
  "geometry": {"coordinates":[-87.46446999999998,20.91744],"type":"Point"}
}