{
  "type": "Feature",
  "properties": {
    "gn:admin1_code":"15.0",
    "gn:admin2_code":"99.0",
    "gn:asciiname":"Palo Gacho",
    "gn:country_code":"MX",
    "gn:dem":2238,
    "gn:feature_class":"P",
    "gn:feature_code":"PPL",
    "gn:name":"Palo Gacho",
    "gn:population":0,
    "gn:timezone":"America/Mexico_City",
    "iso:country":"MX",
    "name:spa_x_preferred":[
        "Palo Gacho"
    ],
    "wof:name":"Palo Gacho",
    "wof:placetype":"locality"
},
  "geometry": {"coordinates":[-98.91806,19.4997],"type":"Point"}
}