{
  "type": "Feature",
  "properties": {
    "gn:admin1_code":"24",
    "gn:admin2_code":"10.0",
    "gn:asciiname":"Los Charcos del Poniente",
    "gn:country_code":"MX",
    "gn:dem":1217,
    "gn:feature_class":"P",
    "gn:feature_code":"PPL",
    "gn:name":"Los Charcos del Poniente",
    "gn:population":0,
    "gn:timezone":"America/Mexico_City",
    "iso:country":"MX",
    "name:spa_x_preferred":[
        "Los Charcos del Poniente"
    ],
    "wof:name":"Los Charcos del Poniente",
    "wof:placetype":"locality"
},
  "geometry": {"coordinates":[-99.64227,22.37182],"type":"Point"}
}