{
  "type": "Feature",
  "properties": {
    "gn:admin1_code":"10.0",
    "gn:admin2_code":"26.0",
    "gn:asciiname":"San Rafael de Arriba",
    "gn:country_code":"MX",
    "gn:dem":2497,
    "gn:feature_class":"P",
    "gn:feature_code":"PPL",
    "gn:name":"San Rafael de Arriba",
    "gn:population":0,
    "gn:timezone":"America/Monterrey",
    "iso:country":"MX",
    "name:spa_x_preferred":[
        "San Rafael de Arriba"
    ],
    "wof:name":"San Rafael de Arriba",
    "wof:placetype":"locality"
},
  "geometry": {"coordinates":[-105.78435,24.31583],"type":"Point"}
}