{
  "type": "Feature",
  "properties": {
    "gn:admin1_code":"21",
    "gn:admin2_code":"43",
    "gn:asciiname":"Cuaololtitan",
    "gn:country_code":"MX",
    "gn:dem":446,
    "gn:feature_class":"P",
    "gn:feature_code":"PPL",
    "gn:name":"Cuaololtit\u00e1n",
    "gn:population":10,
    "gn:timezone":"America/Mexico_City",
    "iso:country":"MX",
    "name:und_x_variant":[
        "Cuaololtit\u00e1n"
    ],
    "wof:name":"Cuaololtitan",
    "wof:placetype":"locality",
    "wof:population":10
},
  "geometry": {"coordinates":[-97.44862000000001,20.04111],"type":"Point"}
}