{
  "type": "Feature",
  "properties": {
    "gn:admin1_code":"14.0",
    "gn:admin2_code":"53.0",
    "gn:asciiname":"El Alto de Encinillas",
    "gn:country_code":"MX",
    "gn:dem":1959,
    "gn:feature_class":"P",
    "gn:feature_code":"PPL",
    "gn:name":"El Alto de Encinillas",
    "gn:population":0,
    "gn:timezone":"America/Mexico_City",
    "iso:country":"MX",
    "name:spa_x_preferred":[
        "El Alto de Encinillas"
    ],
    "wof:name":"El Alto de Encinillas",
    "wof:placetype":"locality"
},
  "geometry": {"coordinates":[-102.11615,21.27796],"type":"Point"}
}