{
  "type": "Feature",
  "properties": {
    "gn:admin1_code":"26.0",
    "gn:admin2_code":"36.0",
    "gn:asciiname":"La Tinaja Bonita",
    "gn:country_code":"MX",
    "gn:dem":967,
    "gn:feature_class":"P",
    "gn:feature_code":"PPL",
    "gn:name":"La Tinaja Bonita",
    "gn:population":3,
    "gn:timezone":"America/Hermosillo",
    "iso:country":"MX",
    "name:spa_x_preferred":[
        "La Tinaja BonIta"
    ],
    "wof:name":"La Tinaja Bonita",
    "wof:placetype":"locality",
    "wof:population":3
},
  "geometry": {"coordinates":[-110.87222,30.49167000000001],"type":"Point"}
}