{
  "type": "Feature",
  "properties": {
    "gn:admin1_code":"26",
    "gn:admin2_code":"56",
    "gn:asciiname":"Vinedo la Tracalita",
    "gn:country_code":"MX",
    "gn:dem":387,
    "gn:feature_class":"P",
    "gn:feature_code":"PPL",
    "gn:name":"Vi\u00f1edo la Tracalita",
    "gn:population":31,
    "gn:timezone":"America/Hermosillo",
    "iso:country":"MX",
    "name:und_x_variant":[
        "Vi\u00f1edo la Tracalita"
    ],
    "wof:name":"Vinedo la Tracalita",
    "wof:placetype":"locality",
    "wof:population":31
},
  "geometry": {"coordinates":[-110.93917,29.38028],"type":"Point"}
}