{
  "type": "Feature",
  "properties": {
    "gn:admin1_code":"10",
    "gn:admin2_code":"11.0",
    "gn:asciiname":"Soledad",
    "gn:country_code":"MX",
    "gn:dem":1613,
    "gn:feature_class":"P",
    "gn:feature_code":"PPL",
    "gn:name":"Soledad",
    "gn:population":0,
    "gn:timezone":"America/Monterrey",
    "iso:country":"MX",
    "name:und_x_variant":[
        "La Soledad",
        "Soledad"
    ],
    "wof:name":"Soledad",
    "wof:placetype":"locality"
},
  "geometry": {"coordinates":[-105.13051000000002,25.81344],"type":"Point"}
}