{
  "type": "Feature",
  "properties": {
    "gn:admin1_code":"25",
    "gn:admin2_code":"14.0",
    "gn:asciiname":"El Limon [Centro Fruticola]",
    "gn:country_code":"MX",
    "gn:dem":42,
    "gn:feature_class":"P",
    "gn:feature_code":"PPL",
    "gn:name":"El Lim\u00f3n [Centro Frut\u00edcola]",
    "gn:population":5,
    "gn:timezone":"America/Mazatlan",
    "iso:country":"MX",
    "name:und_x_variant":[
        "El Lim\u00f3n [Centro Frut\u00edcola]"
    ],
    "wof:name":"El Limon [Centro Fruticola]",
    "wof:placetype":"locality",
    "wof:population":5
},
  "geometry": {"coordinates":[-105.96278,23.06323],"type":"Point"}
}