{
  "type": "Feature",
  "properties": {
    "gn:admin1_code":"24",
    "gn:admin2_code":"19.0",
    "gn:asciiname":"Tortugas",
    "gn:country_code":"MX",
    "gn:dem":1213,
    "gn:feature_class":"P",
    "gn:feature_code":"PPL",
    "gn:name":"Tortugas",
    "gn:population":0,
    "gn:timezone":"America/Mexico_City",
    "iso:country":"MX",
    "name:spa_x_preferred":[
        "Tortugas"
    ],
    "wof:name":"Tortugas",
    "wof:placetype":"locality"
},
  "geometry": {"coordinates":[-99.62184000000001,21.59207],"type":"Point"}
}