{
  "type": "Feature",
  "properties": {
    "gn:admin1_code":"6.0",
    "gn:admin2_code":"40.0",
    "gn:asciiname":"Cuatro Vientos",
    "gn:country_code":"MX",
    "gn:dem":2303,
    "gn:feature_class":"P",
    "gn:feature_code":"PPL",
    "gn:name":"Cuatro Vientos",
    "gn:population":0,
    "gn:timezone":"America/Chihuahua",
    "iso:country":"MX",
    "name:cat_x_preferred":[
        "Cuatro Vientos"
    ],
    "name:eus_x_preferred":[
        "Cuatro Vientos"
    ],
    "name:por_x_preferred":[
        "Cuatro Vientos"
    ],
    "name:spa_x_preferred":[
        "Cuatro Vientos"
    ],
    "wof:name":"Cuatro Vientos",
    "wof:placetype":"locality"
},
  "geometry": {"coordinates":[-108.44665000000001,29.19985],"type":"Point"}
}