{
  "type": "Feature",
  "properties": {
    "gn:admin1_code":"20",
    "gn:admin2_code":"324.0",
    "gn:asciiname":"Palmarillo (Palmarillo San Martin)",
    "gn:country_code":"MX",
    "gn:dem":259,
    "gn:feature_class":"P",
    "gn:feature_code":"PPL",
    "gn:name":"Palmarillo (Palmarillo San Mart\u00edn)",
    "gn:population":211,
    "gn:timezone":"America/Mexico_City",
    "iso:country":"MX",
    "name:und_x_variant":[
        "Palmarillo (Palmarillo San Mart\u00edn)"
    ],
    "wof:name":"Palmarillo (Palmarillo San Martin)",
    "wof:placetype":"locality",
    "wof:population":211
},
  "geometry": {"coordinates":[-96.4575,15.83972],"type":"Point"}
}