{
  "type": "Feature",
  "properties": {
    "gn:admin1_code":"14.0",
    "gn:asciiname":"El Nehual",
    "gn:country_code":"MX",
    "gn:dem":1883,
    "gn:feature_class":"P",
    "gn:feature_code":"PPL",
    "gn:name":"El Nehual",
    "gn:population":0,
    "gn:timezone":"America/Mexico_City",
    "iso:country":"MX",
    "name:spa_x_preferred":[
        "El Nehual"
    ],
    "wof:name":"El Nehual",
    "wof:placetype":"locality"
},
  "geometry": {"coordinates":[-103.67327,22.28434],"type":"Point"}
}