{
  "type": "Feature",
  "properties": {
    "gn:admin1_code":"6",
    "gn:admin2_code":"20.0",
    "gn:asciiname":"El Rincon la Canoa",
    "gn:country_code":"MX",
    "gn:dem":555,
    "gn:feature_class":"P",
    "gn:feature_code":"PPL",
    "gn:name":"El Rinc\u00f3n la Canoa",
    "gn:population":0,
    "gn:timezone":"America/Chihuahua",
    "iso:country":"MX",
    "name:spa_x_preferred":[
        "El Rinc\u00f3n la Canoa"
    ],
    "wof:name":"El Rincon la Canoa",
    "wof:placetype":"locality"
},
  "geometry": {"coordinates":[-108.50673999999999,27.43303],"type":"Point"}
}