{
  "type": "Feature",
  "properties": {
    "gn:admin1_code":"10",
    "gn:admin2_code":"3.0",
    "gn:asciiname":"Pipila (Chiganayo)",
    "gn:country_code":"MX",
    "gn:dem":1674,
    "gn:feature_class":"P",
    "gn:feature_code":"PPL",
    "gn:name":"P\u00edpila (Chiganayo)",
    "gn:population":246,
    "gn:timezone":"America/Monterrey",
    "iso:country":"MX",
    "name:und_x_variant":[
        "P\u00edpila (Chiganayo)"
    ],
    "wof:name":"Pipila (Chiganayo)",
    "wof:placetype":"locality",
    "wof:population":246
},
  "geometry": {"coordinates":[-104.60889,24.95806],"type":"Point"}
}