{
  "type": "Feature",
  "properties": {
    "gn:admin1_code":"24",
    "gn:admin2_code":"12.0",
    "gn:asciiname":"Mexcala",
    "gn:country_code":"MX",
    "gn:dem":304,
    "gn:feature_class":"P",
    "gn:feature_code":"PPL",
    "gn:name":"Mexcala",
    "gn:population":53,
    "gn:timezone":"America/Mexico_City",
    "iso:country":"MX",
    "name:ceb_x_preferred":[
        "Mexcala"
    ],
    "name:fra_x_preferred":[
        "Mexcala"
    ],
    "name:ita_x_preferred":[
        "Mexcala"
    ],
    "name:nld_x_preferred":[
        "Mexcala"
    ],
    "name:ron_x_preferred":[
        "Mexcala"
    ],
    "name:swe_x_preferred":[
        "Mexcala"
    ],
    "name:vie_x_preferred":[
        "Mexcala"
    ],
    "name:war_x_preferred":[
        "Mexcala"
    ],
    "wof:name":"Mexcala",
    "wof:placetype":"locality",
    "wof:population":53
},
  "geometry": {"coordinates":[-98.97694,21.57944],"type":"Point"}
}