{
  "type": "Feature",
  "properties": {
    "gn:admin1_code":"5.0",
    "gn:asciiname":"Vistahermosa",
    "gn:country_code":"MX",
    "gn:dem":1459,
    "gn:feature_class":"P",
    "gn:feature_code":"PPL",
    "gn:name":"Vistahermosa",
    "gn:population":0,
    "gn:timezone":"America/Mexico_City",
    "iso:country":"MX",
    "name:spa_x_preferred":[
        "Vistahermosa"
    ],
    "wof:name":"Vistahermosa",
    "wof:placetype":"locality"
},
  "geometry": {"coordinates":[-92.50282,16.99663],"type":"Point"}
}