{
  "type": "Feature",
  "properties": {
    "gn:admin1_code":"14.0",
    "gn:asciiname":"Rio de Chan Miguel",
    "gn:country_code":"MX",
    "gn:dem":366,
    "gn:feature_class":"P",
    "gn:feature_code":"PPL",
    "gn:name":"R\u00edo de Chan Miguel",
    "gn:population":0,
    "gn:timezone":"America/Mexico_City",
    "iso:country":"MX",
    "name:spa_x_preferred":[
        "R\u00edo de Chan Miguel"
    ],
    "wof:name":"Rio de Chan Miguel",
    "wof:placetype":"locality"
},
  "geometry": {"coordinates":[-103.30047999999999,18.99171],"type":"Point"}
}