{
  "type": "Feature",
  "properties": {
    "gn:admin1_code":"25",
    "gn:admin2_code":"3.0",
    "gn:asciiname":"Campo Los Tascaderitos",
    "gn:country_code":"MX",
    "gn:dem":286,
    "gn:feature_class":"P",
    "gn:feature_code":"PPL",
    "gn:name":"Campo Los Tascaderitos",
    "gn:population":0,
    "gn:timezone":"America/Mazatlan",
    "iso:country":"MX",
    "name:spa_x_preferred":[
        "Campo Los Tascaderitos"
    ],
    "wof:name":"Campo Los Tascaderitos",
    "wof:placetype":"locality"
},
  "geometry": {"coordinates":[-107.44031,25.31524],"type":"Point"}
}