{
  "type": "Feature",
  "properties": {
    "gn:admin1_code":"6",
    "gn:admin2_code":"18.0",
    "gn:asciiname":"Campo Veintinueve",
    "gn:country_code":"MX",
    "gn:dem":2127,
    "gn:feature_class":"P",
    "gn:feature_code":"PPL",
    "gn:name":"Campo Veintinueve",
    "gn:population":56,
    "gn:timezone":"America/Chihuahua",
    "iso:country":"MX",
    "wof:name":"Campo Veintinueve",
    "wof:placetype":"locality",
    "wof:population":56
},
  "geometry": {"coordinates":[-106.90860000000001,28.27195],"type":"Point"}
}