{
  "type": "Feature",
  "properties": {
    "gn:admin1_code":"19",
    "gn:admin2_code":"13.0",
    "gn:asciiname":"Las Comitas",
    "gn:country_code":"MX",
    "gn:dem":194,
    "gn:feature_class":"P",
    "gn:feature_code":"PPL",
    "gn:name":"Las Comitas",
    "gn:population":5,
    "gn:timezone":"America/Monterrey",
    "iso:country":"MX",
    "wof:name":"Las Comitas",
    "wof:placetype":"locality",
    "wof:population":5
},
  "geometry": {"coordinates":[-99.44391,25.68201],"type":"Point"}
}