{
  "type": "Feature",
  "properties": {
    "gn:admin1_code":"20",
    "gn:admin2_code":"57",
    "gn:asciiname":"Paisanos Atitlan",
    "gn:country_code":"MX",
    "gn:dem":194,
    "gn:feature_class":"P",
    "gn:feature_code":"PPL",
    "gn:name":"Paisanos Atitl\u00e1n",
    "gn:population":46,
    "gn:timezone":"America/Mexico_City",
    "iso:country":"MX",
    "name:und_x_variant":[
        "Paisanos Atitl\u00e1n"
    ],
    "wof:name":"Paisanos Atitlan",
    "wof:placetype":"locality",
    "wof:population":46
},
  "geometry": {"coordinates":[-95.03722,16.86056],"type":"Point"}
}