{
  "type": "Feature",
  "properties": {
    "gn:admin1_code":"20",
    "gn:admin2_code":"26.0",
    "gn:asciiname":"Zaragoza",
    "gn:country_code":"MX",
    "gn:dem":2476,
    "gn:feature_class":"P",
    "gn:feature_code":"PPL",
    "gn:name":"Zaragoza",
    "gn:population":475,
    "gn:timezone":"America/Mexico_City",
    "iso:country":"MX",
    "wof:name":"Zaragoza",
    "wof:placetype":"locality",
    "wof:population":475
},
  "geometry": {"coordinates":[-97.57333,17.01611],"type":"Point"}
}