{
  "type": "Feature",
  "properties": {
    "gn:admin1_code":"14.0",
    "gn:admin2_code":"87.0",
    "gn:asciiname":"Gaytan",
    "gn:country_code":"MX",
    "gn:dem":1528,
    "gn:feature_class":"P",
    "gn:feature_code":"PPL",
    "gn:name":"Gayt\u00e1n",
    "gn:population":0,
    "gn:timezone":"America/Mexico_City",
    "iso:country":"MX",
    "name:spa_x_preferred":[
        "Gayt\u00e1n"
    ],
    "wof:name":"Gaytan",
    "wof:placetype":"locality"
},
  "geometry": {"coordinates":[-103.23298,19.46729],"type":"Point"}
}