{
  "type": "Feature",
  "properties": {
    "gn:admin1_code":"30",
    "gn:admin2_code":"77.0",
    "gn:asciiname":"La Pastoria",
    "gn:country_code":"MX",
    "gn:dem":36,
    "gn:feature_class":"P",
    "gn:feature_code":"PPL",
    "gn:name":"La Pastor\u00eda",
    "gn:population":0,
    "gn:timezone":"America/Mexico_City",
    "iso:country":"MX",
    "name:spa_x_preferred":[
        "La Pastor\u00eda"
    ],
    "wof:name":"La Pastoria",
    "wof:placetype":"locality"
},
  "geometry": {"coordinates":[-95.56726999999999,18.12403],"type":"Point"}
}