{
  "type": "Feature",
  "properties": {
    "gn:admin1_code":"13",
    "gn:admin2_code":"25.0",
    "gn:asciiname":"El Ixtle",
    "gn:country_code":"MX",
    "gn:dem":142,
    "gn:feature_class":"P",
    "gn:feature_code":"PPL",
    "gn:name":"El Ixtle",
    "gn:population":0,
    "gn:timezone":"America/Mexico_City",
    "iso:country":"MX",
    "name:und_x_variant":[
        "Ixtle",
        "El Ixtle"
    ],
    "wof:name":"El Ixtle",
    "wof:placetype":"locality"
},
  "geometry": {"coordinates":[-98.16061000000001,21.04568],"type":"Point"}
}