{
  "type": "Feature",
  "properties": {
    "gn:admin1_code":"25",
    "gn:admin2_code":"14.0",
    "gn:asciiname":"Rancho Apolonio",
    "gn:country_code":"MX",
    "gn:dem":4,
    "gn:feature_class":"P",
    "gn:feature_code":"PPL",
    "gn:name":"Rancho Apolonio",
    "gn:population":0,
    "gn:timezone":"America/Mazatlan",
    "iso:country":"MX",
    "name:spa_x_preferred":[
        "Rancho Apolonio"
    ],
    "wof:name":"Rancho Apolonio",
    "wof:placetype":"locality"
},
  "geometry": {"coordinates":[-106.10117,22.92434],"type":"Point"}
}