{
  "type": "Feature",
  "properties": {
    "gn:admin1_code":"5",
    "gn:admin2_code":"15.0",
    "gn:asciiname":"Fraccionamiento San Antonio",
    "gn:country_code":"MX",
    "gn:dem":485,
    "gn:feature_class":"P",
    "gn:feature_code":"PPL",
    "gn:name":"Fraccionamiento San Antonio",
    "gn:population":99,
    "gn:timezone":"America/Mexico_City",
    "iso:country":"MX",
    "wof:name":"Fraccionamiento San Antonio",
    "wof:placetype":"locality",
    "wof:population":99
},
  "geometry": {"coordinates":[-92.17967,14.99322],"type":"Point"}
}