{
  "type": "Feature",
  "properties": {
    "gn:admin1_code":"14",
    "gn:admin2_code":"124.0",
    "gn:asciiname":"Las Latas",
    "gn:cc2":"MX",
    "gn:country_code":"MX",
    "gn:dem":1914,
    "gn:feature_class":"P",
    "gn:feature_code":"PPL",
    "gn:name":"Las Latas",
    "gn:population":138,
    "gn:timezone":"America/Mexico_City",
    "iso:country":"MX",
    "name:und_x_variant":[
        "Latas",
        "Las Latas"
    ],
    "wof:name":"Las Latas",
    "wof:placetype":"locality",
    "wof:population":138
},
  "geometry": {"coordinates":[-102.96444,20.59083],"type":"Point"}
}