{
  "type": "Feature",
  "properties": {
    "gn:admin1_code":"14.0",
    "gn:admin2_code":"96.0",
    "gn:asciiname":"El Volantin",
    "gn:country_code":"MX",
    "gn:dem":1899,
    "gn:feature_class":"P",
    "gn:feature_code":"PPL",
    "gn:name":"El Volant\u00edn",
    "gn:population":0,
    "gn:timezone":"America/Mexico_City",
    "iso:country":"MX",
    "wof:name":"El Volantin",
    "wof:placetype":"locality"
},
  "geometry": {"coordinates":[-103.10594,20.05493],"type":"Point"}
}