{
  "type": "Feature",
  "properties": {
    "gn:admin1_code":"6",
    "gn:admin2_code":"21.0",
    "gn:asciiname":"Granja Cielo Vista",
    "gn:country_code":"MX",
    "gn:dem":1194,
    "gn:feature_class":"P",
    "gn:feature_code":"PPL",
    "gn:name":"Granja Cielo Vista",
    "gn:population":4,
    "gn:timezone":"America/Chihuahua",
    "iso:country":"MX",
    "wof:name":"Granja Cielo Vista",
    "wof:placetype":"locality",
    "wof:population":4
},
  "geometry": {"coordinates":[-105.43434999999999,28.18986],"type":"Point"}
}