{
  "type": "Feature",
  "properties": {
    "gn:admin1_code":"20",
    "gn:admin2_code":"39",
    "gn:asciiname":"Tabaco",
    "gn:country_code":"MX",
    "gn:dem":1708,
    "gn:feature_class":"P",
    "gn:feature_code":"PPL",
    "gn:name":"Tabaco",
    "gn:population":33,
    "gn:timezone":"America/Mexico_City",
    "iso:country":"MX",
    "wof:name":"Tabaco",
    "wof:placetype":"locality",
    "wof:population":33
},
  "geometry": {"coordinates":[-97.75556,17.87556],"type":"Point"}
}