{
  "type": "Feature",
  "properties": {
    "gn:admin1_code":"20",
    "gn:admin2_code":"39",
    "gn:asciiname":"Tabaco",
    "gn:country_code":"MX",
    "gn:dem":1708,
    "gn:feature_class":"P",
    "gn:feature_code":"PPL",
    "gn:name":"Tabaco",
    "gn:population":33,
    "gn:timezone":"America/Mexico_City",
    "iso:country":"MX",
    "name:ara_x_preferred":[
        "\u062a\u0627\u0628\u0627\u0643\u0648"
    ],
    "name:ceb_x_preferred":[
        "Tabaco"
    ],
    "name:deu_x_preferred":[
        "Tabaco"
    ],
    "name:fra_x_preferred":[
        "Tabaco"
    ],
    "name:gor_x_preferred":[
        "Tabaco"
    ],
    "name:ilo_x_preferred":[
        "Tabaco"
    ],
    "name:ind_x_preferred":[
        "Tabaco"
    ],
    "name:ita_x_preferred":[
        "Tabaco"
    ],
    "name:jpn_x_preferred":[
        "\u30bf\u30d0\u30b3\u5e02"
    ],
    "name:kor_x_preferred":[
        "\ud0c0\ubc14\ucf54"
    ],
    "name:nld_x_preferred":[
        "Tabaco"
    ],
    "name:nor_x_preferred":[
        "Tabaco"
    ],
    "name:pag_x_preferred":[
        "Tabaco"
    ],
    "name:pam_x_preferred":[
        "Tabaco"
    ],
    "name:pol_x_preferred":[
        "Tabaco"
    ],
    "name:swe_x_preferred":[
        "Tabaco"
    ],
    "name:tgl_x_preferred":[
        "Tabaco"
    ],
    "name:urd_x_preferred":[
        "\u062a\u0627\u0628\u0627\u06a9\u0648"
    ],
    "name:war_x_preferred":[
        "Tabaco"
    ],
    "wof:name":"Tabaco",
    "wof:placetype":"locality",
    "wof:population":33
},
  "geometry": {"coordinates":[-97.75556,17.87556],"type":"Point"}
}