{
  "type": "Feature",
  "properties": {
    "gn:admin1_code":"32",
    "gn:admin2_code":"10",
    "gn:asciiname":"Clarisas Franciscanas",
    "gn:country_code":"MX",
    "gn:dem":2169,
    "gn:feature_class":"P",
    "gn:feature_code":"PPL",
    "gn:name":"Clarisas Franciscanas",
    "gn:population":19,
    "gn:timezone":"America/Mexico_City",
    "iso:country":"MX",
    "wof:name":"Clarisas Franciscanas",
    "wof:placetype":"locality",
    "wof:population":19
},
  "geometry": {"coordinates":[-102.84111,23.15139],"type":"Point"}
}