{
  "type": "Feature",
  "properties": {
    "gn:admin1_code":"12.0",
    "gn:asciiname":"Cerro Pelon",
    "gn:country_code":"MX",
    "gn:dem":1585,
    "gn:feature_class":"P",
    "gn:feature_code":"PPL",
    "gn:name":"Cerro Pel\u00f3n",
    "gn:population":0,
    "gn:timezone":"America/Mexico_City",
    "iso:country":"MX",
    "name:spa_x_preferred":[
        "Cerro Pel\u00f3n"
    ],
    "wof:name":"Cerro Pelon",
    "wof:placetype":"locality"
},
  "geometry": {"coordinates":[-100.49003999999999,18.83571],"type":"Point"}
}