{
  "type": "Feature",
  "properties": {
    "gn:admin1_code":"6.0",
    "gn:admin2_code":"34.0",
    "gn:asciiname":"Arroyo del Borrego",
    "gn:country_code":"MX",
    "gn:dem":2104,
    "gn:feature_class":"P",
    "gn:feature_code":"PPL",
    "gn:name":"Arroyo del Borrego",
    "gn:population":0,
    "gn:timezone":"America/Chihuahua",
    "iso:country":"MX",
    "name:spa_x_preferred":[
        "Arroyo del Borrego"
    ],
    "wof:name":"Arroyo del Borrego",
    "wof:placetype":"locality"
},
  "geometry": {"coordinates":[-107.73096,29.77991],"type":"Point"}
}