{
  "type": "Feature",
  "properties": {
    "gn:admin1_code":"30",
    "gn:admin2_code":"24.0",
    "gn:asciiname":"Imverxotla",
    "gn:country_code":"MX",
    "gn:dem":186,
    "gn:feature_class":"P",
    "gn:feature_code":"PPL",
    "gn:name":"Imverxotla",
    "gn:population":5,
    "gn:timezone":"America/Mexico_City",
    "iso:country":"MX",
    "wof:name":"Imverxotla",
    "wof:placetype":"locality",
    "wof:population":5
},
  "geometry": {"coordinates":[-96.60222,19.32889],"type":"Point"}
}