{
  "type": "Feature",
  "properties": {
    "gn:admin1_code":"6",
    "gn:admin2_code":"13.0",
    "gn:asciiname":"Pena Verde",
    "gn:country_code":"MX",
    "gn:dem":1598,
    "gn:feature_class":"P",
    "gn:feature_code":"PPL",
    "gn:name":"Pe\u00f1a Verde",
    "gn:population":0,
    "gn:timezone":"America/Chihuahua",
    "iso:country":"MX",
    "name:spa_x_preferred":[
        "Pe\u00f1a Verde"
    ],
    "wof:name":"Pena Verde",
    "wof:placetype":"locality"
},
  "geometry": {"coordinates":[-108.087,30.38727],"type":"Point"}
}