{
  "type": "Feature",
  "properties": {
    "gn:admin1_code":"6",
    "gn:admin2_code":"13.0",
    "gn:asciiname":"Pena Verde",
    "gn:country_code":"MX",
    "gn:dem":1598,
    "gn:feature_class":"P",
    "gn:feature_code":"PPL",
    "gn:name":"Pe\u00f1a Verde",
    "gn:population":0,
    "gn:timezone":"America/Chihuahua",
    "iso:country":"MX",
    "name:ceb_x_preferred":[
        "Pena Verde"
    ],
    "name:deu_x_preferred":[
        "Pena Verde"
    ],
    "name:kaz_x_preferred":[
        "\u041f\u0435\u043d\u0430-\u0412\u0435\u0440\u0434\u0435"
    ],
    "name:mwl_x_preferred":[
        "Pena Verde"
    ],
    "name:nld_x_preferred":[
        "Pena Verde"
    ],
    "name:por_x_preferred":[
        "Pena Verde"
    ],
    "name:rus_x_preferred":[
        "\u041f\u0435\u043d\u0430-\u0412\u0435\u0440\u0434\u0435"
    ],
    "name:spa_x_preferred":[
        "Pe\u00f1a Verde"
    ],
    "name:spa_x_variant":[
        "Pena Verde"
    ],
    "name:tur_x_preferred":[
        "Pena Verde"
    ],
    "wof:name":"Pena Verde",
    "wof:placetype":"locality"
},
  "geometry": {"coordinates":[-108.087,30.38727],"type":"Point"}
}