{
  "type": "Feature",
  "properties": {
    "gn:admin1_code":"26",
    "gn:admin2_code":"50.0",
    "gn:asciiname":"De Salas",
    "gn:country_code":"MX",
    "gn:dem":691,
    "gn:feature_class":"P",
    "gn:feature_code":"PPL",
    "gn:name":"De Salas",
    "gn:population":0,
    "gn:timezone":"America/Hermosillo",
    "iso:country":"MX",
    "name:spa_x_preferred":[
        "De Salas"
    ],
    "wof:name":"De Salas",
    "wof:placetype":"locality"
},
  "geometry": {"coordinates":[-110.48386000000001,29.77202],"type":"Point"}
}