{
  "type": "Feature",
  "properties": {
    "gn:admin1_code":"30",
    "gn:admin2_code":"55.0",
    "gn:asciiname":"El Aguacate Grande",
    "gn:country_code":"MX",
    "gn:dem":92,
    "gn:feature_class":"P",
    "gn:feature_code":"PPL",
    "gn:name":"El Aguacate Grande",
    "gn:population":55,
    "gn:timezone":"America/Mexico_City",
    "iso:country":"MX",
    "name:spa_x_preferred":[
        "El Aguacate Grande"
    ],
    "wof:name":"El Aguacate Grande",
    "wof:placetype":"locality",
    "wof:population":55
},
  "geometry": {"coordinates":[-98.31305999999999,21.18806],"type":"Point"}
}