{
  "type": "Feature",
  "properties": {
    "gn:admin1_code":"5",
    "gn:admin2_code":"79.0",
    "gn:asciiname":"San Pedro Muniz",
    "gn:country_code":"MX",
    "gn:dem":982,
    "gn:feature_class":"P",
    "gn:feature_code":"PPL",
    "gn:name":"San Pedro Mu\u00f1iz",
    "gn:population":12,
    "gn:timezone":"America/Mexico_City",
    "iso:country":"MX",
    "wof:name":"San Pedro Muniz",
    "wof:placetype":"locality",
    "wof:population":12
},
  "geometry": {"coordinates":[-93.17083,16.9125],"type":"Point"}
}