{
  "type": "Feature",
  "properties": {
    "gn:admin1_code":"28.0",
    "gn:admin2_code":"32.0",
    "gn:asciiname":"San Vincente",
    "gn:country_code":"MX",
    "gn:dem":65,
    "gn:feature_class":"P",
    "gn:feature_code":"PPL",
    "gn:name":"San Vincente",
    "gn:population":0,
    "gn:timezone":"America/Matamoros",
    "iso:country":"MX",
    "name:spa_x_preferred":[
        "San Vincente"
    ],
    "wof:name":"San Vincente",
    "wof:placetype":"locality"
},
  "geometry": {"coordinates":[-98.36866000000001,26.09026],"type":"Point"}
}