{
  "type": "Feature",
  "properties": {
    "gn:admin1_code":"26.0",
    "gn:admin2_code":"36.0",
    "gn:asciiname":"El Saguarito",
    "gn:country_code":"MX",
    "gn:dem":791,
    "gn:feature_class":"P",
    "gn:feature_code":"PPL",
    "gn:name":"El Saguarito",
    "gn:population":0,
    "gn:timezone":"America/Hermosillo",
    "iso:country":"MX",
    "wof:name":"El Saguarito",
    "wof:placetype":"locality"
},
  "geometry": {"coordinates":[-111.11378000000001,30.76994],"type":"Point"}
}