{
  "type": "Feature",
  "properties": {
    "gn:admin1_code":"14",
    "gn:admin2_code":"118.0",
    "gn:asciiname":"Mesa del Apozol",
    "gn:country_code":"MX",
    "gn:dem":1869,
    "gn:feature_class":"P",
    "gn:feature_code":"PPL",
    "gn:name":"Mesa del Apozol",
    "gn:population":58,
    "gn:timezone":"America/Mexico_City",
    "iso:country":"MX",
    "wof:name":"Mesa del Apozol",
    "wof:placetype":"locality",
    "wof:population":58
},
  "geometry": {"coordinates":[-102.8925,21.08167000000001],"type":"Point"}
}