{
  "type": "Feature",
  "properties": {
    "gn:admin1_code":"16.0",
    "gn:admin2_code":"10.0",
    "gn:asciiname":"El Ancon",
    "gn:country_code":"MX",
    "gn:dem":305,
    "gn:feature_class":"P",
    "gn:feature_code":"PPL",
    "gn:name":"El Anc\u00f3n",
    "gn:population":0,
    "gn:timezone":"America/Mexico_City",
    "iso:country":"MX",
    "name:spa_x_preferred":[
        "El Anc\u00f3n"
    ],
    "wof:name":"El Ancon",
    "wof:placetype":"locality"
},
  "geometry": {"coordinates":[-102.77301,18.36066],"type":"Point"}
}