{
  "type": "Feature",
  "properties": {
    "gn:admin1_code":"28.0",
    "gn:admin2_code":"14.0",
    "gn:asciiname":"El Chapotito",
    "gn:country_code":"MX",
    "gn:dem":114,
    "gn:feature_class":"P",
    "gn:feature_code":"PPL",
    "gn:name":"El Chapotito",
    "gn:population":0,
    "gn:timezone":"America/Monterrey",
    "iso:country":"MX",
    "name:spa_x_preferred":[
        "El Chapotito"
    ],
    "wof:name":"El Chapotito",
    "wof:placetype":"locality"
},
  "geometry": {"coordinates":[-99.27509000000001,26.58883],"type":"Point"}
}