{
  "type": "Feature",
  "properties": {
    "gn:admin1_code":"21",
    "gn:admin2_code":"195",
    "gn:asciiname":"Ocotlamanca",
    "gn:country_code":"MX",
    "gn:dem":2104,
    "gn:feature_class":"P",
    "gn:feature_code":"PPL",
    "gn:name":"Ocotlamanca",
    "gn:population":13,
    "gn:timezone":"America/Mexico_City",
    "iso:country":"MX",
    "wof:name":"Ocotlamanca",
    "wof:placetype":"locality",
    "wof:population":13
},
  "geometry": {"coordinates":[-97.12437,18.52601],"type":"Point"}
}