{
  "type": "Feature",
  "properties": {
    "gn:admin1_code":"26",
    "gn:admin2_code":"43.0",
    "gn:asciiname":"Licenciado Adolfo Lopez Mateos",
    "gn:country_code":"MX",
    "gn:dem":1185,
    "gn:feature_class":"P",
    "gn:feature_code":"PPL",
    "gn:name":"Licenciado Adolfo L\u00f3pez Mateos",
    "gn:population":60,
    "gn:timezone":"America/Hermosillo",
    "iso:country":"MX",
    "name:und_x_variant":[
        "Licenciado Adolfo L\u00f3pez Mateos"
    ],
    "wof:name":"Licenciado Adolfo Lopez Mateos",
    "wof:placetype":"locality",
    "wof:population":60
},
  "geometry": {"coordinates":[-110.78139,31.25306],"type":"Point"}
}