{
  "type": "Feature",
  "properties": {
    "gn:admin1_code":"25.0",
    "gn:admin2_code":"6.0",
    "gn:asciiname":"El Zapote de los Beltranes",
    "gn:country_code":"MX",
    "gn:dem":615,
    "gn:feature_class":"P",
    "gn:feature_code":"PPL",
    "gn:name":"El Zapote de los Beltranes",
    "gn:population":0,
    "gn:timezone":"America/Mazatlan",
    "iso:country":"MX",
    "name:spa_x_preferred":[
        "El Zapote de los Beltranes"
    ],
    "wof:name":"El Zapote de los Beltranes",
    "wof:placetype":"locality"
},
  "geometry": {"coordinates":[-107.19499,25.26],"type":"Point"}
}