{
  "type": "Feature",
  "properties": {
    "gn:admin1_code":"13",
    "gn:admin2_code":"12.0",
    "gn:asciiname":"Una de Gato",
    "gn:country_code":"MX",
    "gn:dem":1899,
    "gn:feature_class":"P",
    "gn:feature_code":"PPL",
    "gn:name":"U\u00f1a de Gato",
    "gn:population":0,
    "gn:timezone":"America/Mexico_City",
    "iso:country":"MX",
    "name:spa_x_preferred":[
        "U\u00f1a de Gato"
    ],
    "wof:name":"Una de Gato",
    "wof:placetype":"locality"
},
  "geometry": {"coordinates":[-98.57344000000001,20.34858],"type":"Point"}
}