{
  "type": "Feature",
  "properties": {
    "gn:admin1_code":"5",
    "gn:admin2_code":"19.0",
    "gn:asciiname":"San Isidro la Arena",
    "gn:country_code":"MX",
    "gn:dem":1425,
    "gn:feature_class":"P",
    "gn:feature_code":"PPL",
    "gn:name":"San Isidro la Arena",
    "gn:population":6,
    "gn:timezone":"America/Mexico_City",
    "iso:country":"MX",
    "wof:name":"San Isidro la Arena",
    "wof:placetype":"locality",
    "wof:population":6
},
  "geometry": {"coordinates":[-92.31389,16.29083],"type":"Point"}
}