{
  "type": "Feature",
  "properties": {
    "gn:admin1_code":"21",
    "gn:admin2_code":"173",
    "gn:asciiname":"Huixta",
    "gn:country_code":"MX",
    "gn:dem":1855,
    "gn:feature_class":"P",
    "gn:feature_code":"PPL",
    "gn:name":"Huixta",
    "gn:population":11,
    "gn:timezone":"America/Mexico_City",
    "iso:country":"MX",
    "wof:name":"Huixta",
    "wof:placetype":"locality",
    "wof:population":11
},
  "geometry": {"coordinates":[-97.45337000000001,19.86091],"type":"Point"}
}