{
  "type": "Feature",
  "properties": {
    "gn:admin1_code":"15",
    "gn:admin2_code":"64.0",
    "gn:asciiname":"Pueblo Nuevo de los Angeles",
    "gn:country_code":"MX",
    "gn:dem":2902,
    "gn:feature_class":"P",
    "gn:feature_code":"PPL",
    "gn:name":"Pueblo Nuevo de los \u00c1ngeles",
    "gn:population":958,
    "gn:timezone":"America/Mexico_City",
    "iso:country":"MX",
    "name:und_x_variant":[
        "Pueblo Nuevo de los \u00c1ngeles"
    ],
    "wof:name":"Pueblo Nuevo de los Angeles",
    "wof:placetype":"locality",
    "wof:population":958
},
  "geometry": {"coordinates":[-100.00833,19.77583],"type":"Point"}
}