{
  "type": "Feature",
  "properties": {
    "gn:admin1_code":"6",
    "gn:admin2_code":"45.0",
    "gn:asciiname":"Rancho Armendariz",
    "gn:country_code":"MX",
    "gn:dem":1148,
    "gn:feature_class":"P",
    "gn:feature_code":"PPL",
    "gn:name":"Rancho Armend\u00e1riz",
    "gn:population":5,
    "gn:timezone":"America/Chihuahua",
    "iso:country":"MX",
    "name:und_x_variant":[
        "Rancho Armend\u00e1riz"
    ],
    "wof:name":"Rancho Armendariz",
    "wof:placetype":"locality",
    "wof:population":5
},
  "geometry": {"coordinates":[-105.53686,28.46936],"type":"Point"}
}