{
  "type": "Feature",
  "properties": {
    "gn:admin1_code":"16",
    "gn:admin2_code":"49",
    "gn:asciiname":"Pena Redonda",
    "gn:country_code":"MX",
    "gn:dem":1467,
    "gn:feature_class":"P",
    "gn:feature_code":"PPL",
    "gn:name":"Pe\u00f1a Redonda",
    "gn:population":30,
    "gn:timezone":"America/Mexico_City",
    "iso:country":"MX",
    "name:und_x_variant":[
        "Pe\u00f1a Redonda"
    ],
    "wof:name":"Pena Redonda",
    "wof:placetype":"locality",
    "wof:population":30
},
  "geometry": {"coordinates":[-101.06361,19.27861],"type":"Point"}
}