{
  "type": "Feature",
  "properties": {
    "gn:admin1_code":"3",
    "gn:admin2_code":"3.0",
    "gn:asciiname":"NCPE Conquista Agraria",
    "gn:country_code":"MX",
    "gn:dem":63,
    "gn:feature_class":"P",
    "gn:feature_code":"PPL",
    "gn:name":"NCPE Conquista Agraria",
    "gn:population":160,
    "gn:timezone":"America/Mazatlan",
    "iso:country":"MX",
    "wof:name":"NCPE Conquista Agraria",
    "wof:placetype":"locality",
    "wof:population":160
},
  "geometry": {"coordinates":[-110.81528,23.98194],"type":"Point"}
}