{
  "type": "Feature",
  "properties": {
    "gn:admin1_code":"30",
    "gn:admin2_code":"207.0",
    "gn:asciiname":"Casa Blanca",
    "gn:country_code":"MX",
    "gn:dem":41,
    "gn:feature_class":"P",
    "gn:feature_code":"PPL",
    "gn:name":"Casa Blanca",
    "gn:population":5,
    "gn:timezone":"America/Mexico_City",
    "iso:country":"MX",
    "wof:name":"Casa Blanca",
    "wof:placetype":"locality",
    "wof:population":5
},
  "geometry": {"coordinates":[-96.20722000000001,18.34167],"type":"Point"}
}