{
  "type": "Feature",
  "properties": {
    "gn:admin1_code":"24",
    "gn:admin2_code":"55.0",
    "gn:asciiname":"Agua Blanca",
    "gn:country_code":"MX",
    "gn:dem":2324,
    "gn:feature_class":"P",
    "gn:feature_code":"PPL",
    "gn:name":"Agua Blanca",
    "gn:population":63,
    "gn:timezone":"America/Mexico_City",
    "iso:country":"MX",
    "name:bre_x_preferred":[
        "Agua Blanca"
    ],
    "name:ceb_x_preferred":[
        "Agua Blanca"
    ],
    "name:deu_x_preferred":[
        "Agua Blanca"
    ],
    "name:fra_x_preferred":[
        "Agua Blanca"
    ],
    "name:nld_x_preferred":[
        "Agua Blanca"
    ],
    "name:por_x_preferred":[
        "Agua Blanca"
    ],
    "name:sco_x_preferred":[
        "Agua Blanca"
    ],
    "name:spa_x_preferred":[
        "Agua Blanca"
    ],
    "name:swe_x_preferred":[
        "Agua Blanca"
    ],
    "wof:name":"Agua Blanca",
    "wof:placetype":"locality",
    "wof:population":63
},
  "geometry": {"coordinates":[-100.62056,22.06139],"type":"Point"}
}