{
  "type": "Feature",
  "properties": {
    "gn:admin1_code":"12",
    "gn:admin2_code":"58.0",
    "gn:asciiname":"Coatepec Costales",
    "gn:country_code":"MX",
    "gn:dem":1291,
    "gn:feature_class":"P",
    "gn:feature_code":"PPL",
    "gn:name":"Coatepec Costales",
    "gn:population":0,
    "gn:timezone":"America/Mexico_City",
    "iso:country":"MX",
    "name:und_x_variant":[
        "Coatepec",
        "Coatepec Costales"
    ],
    "wof:name":"Coatepec Costales",
    "wof:placetype":"locality"
},
  "geometry": {"coordinates":[-99.7214,18.33922],"type":"Point"}
}