{
  "type": "Feature",
  "properties": {
    "gn:admin1_code":"21",
    "gn:admin2_code":"161.0",
    "gn:asciiname":"Pino Suarez",
    "gn:country_code":"MX",
    "gn:dem":1741,
    "gn:feature_class":"P",
    "gn:feature_code":"PPL",
    "gn:name":"Pino Su\u00e1rez",
    "gn:population":0,
    "gn:timezone":"America/Mexico_City",
    "iso:country":"MX",
    "name:spa_x_preferred":[
        "Pino Su\u00e1rez"
    ],
    "wof:name":"Pino Suarez",
    "wof:placetype":"locality"
},
  "geometry": {"coordinates":[-97.49666999999999,18.51327],"type":"Point"}
}