{
  "type": "Feature",
  "properties": {
    "gn:admin1_code":"5.0",
    "gn:asciiname":"Sanjon Grande",
    "gn:country_code":"MX",
    "gn:dem":1326,
    "gn:feature_class":"P",
    "gn:feature_code":"PPL",
    "gn:name":"Sanj\u00f3n Grande",
    "gn:population":0,
    "gn:timezone":"America/Mexico_City",
    "iso:country":"MX",
    "name:spa_x_preferred":[
        "Sanj\u00f3n Grande"
    ],
    "wof:name":"Sanjon Grande",
    "wof:placetype":"locality"
},
  "geometry": {"coordinates":[-93.39399,16.52728],"type":"Point"}
}