{
  "type": "Feature",
  "properties": {
    "gn:admin1_code":"7",
    "gn:admin2_code":"10.0",
    "gn:asciiname":"La Gamuza",
    "gn:country_code":"MX",
    "gn:dem":594,
    "gn:feature_class":"P",
    "gn:feature_code":"PPL",
    "gn:name":"La Gamuza",
    "gn:population":0,
    "gn:timezone":"America/Monterrey",
    "iso:country":"MX",
    "name:spa_x_preferred":[
        "La Gamuza"
    ],
    "name:und_x_variant":[
        "Rancho La Gamuza"
    ],
    "wof:name":"La Gamuza",
    "wof:placetype":"locality"
},
  "geometry": {"coordinates":[-101.56435,26.94871],"type":"Point"}
}