{
  "type": "Feature",
  "properties": {
    "gn:admin1_code":"10",
    "gn:admin2_code":"14.0",
    "gn:asciiname":"La Herradura",
    "gn:country_code":"MX",
    "gn:dem":1517,
    "gn:feature_class":"P",
    "gn:feature_code":"PPL",
    "gn:name":"La Herradura",
    "gn:population":6,
    "gn:timezone":"America/Monterrey",
    "iso:country":"MX",
    "wof:name":"La Herradura",
    "wof:placetype":"locality",
    "wof:population":6
},
  "geometry": {"coordinates":[-104.50024999999999,23.08892],"type":"Point"}
}