{
  "type": "Feature",
  "properties": {
    "gn:admin1_code":"25",
    "gn:admin2_code":"4.0",
    "gn:asciiname":"Casas Viejas",
    "gn:country_code":"MX",
    "gn:dem":103,
    "gn:feature_class":"P",
    "gn:feature_code":"PPL",
    "gn:name":"Casas Viejas",
    "gn:population":0,
    "gn:timezone":"America/Mazatlan",
    "iso:country":"MX",
    "name:spa_x_preferred":[
        "Casas Viejas"
    ],
    "wof:name":"Casas Viejas",
    "wof:placetype":"locality"
},
  "geometry": {"coordinates":[-106.19495999999999,23.50827],"type":"Point"}
}