{
  "type": "Feature",
  "properties": {
    "gn:admin1_code":"10",
    "gn:admin2_code":"26",
    "gn:asciiname":"El Paso del Arroyo",
    "gn:country_code":"MX",
    "gn:dem":697,
    "gn:feature_class":"P",
    "gn:feature_code":"PPL",
    "gn:name":"El Paso del Arroyo",
    "gn:population":22,
    "gn:timezone":"America/Monterrey",
    "iso:country":"MX",
    "wof:name":"El Paso del Arroyo",
    "wof:placetype":"locality",
    "wof:population":22
},
  "geometry": {"coordinates":[-105.71808,23.87917],"type":"Point"}
}