{
  "type": "Feature",
  "properties": {
    "gn:admin1_code":"5",
    "gn:admin2_code":"81.0",
    "gn:asciiname":"Concepcion Buenavista",
    "gn:country_code":"MX",
    "gn:dem":513,
    "gn:feature_class":"P",
    "gn:feature_code":"PPL",
    "gn:name":"Concepci\u00f3n Buenavista",
    "gn:population":89,
    "gn:timezone":"America/Mexico_City",
    "iso:country":"MX",
    "name:und_x_variant":[
        "Concepci\u00f3n Buenavista"
    ],
    "wof:name":"Concepcion Buenavista",
    "wof:placetype":"locality",
    "wof:population":89
},
  "geometry": {"coordinates":[-92.75194,17.17806],"type":"Point"}
}