{
  "type": "Feature",
  "properties": {
    "gn:admin1_code":"30",
    "gn:admin2_code":"100.0",
    "gn:asciiname":"El Cacahuatal",
    "gn:country_code":"MX",
    "gn:dem":27,
    "gn:feature_class":"P",
    "gn:feature_code":"PPL",
    "gn:name":"El Cacahuatal",
    "gn:population":9,
    "gn:timezone":"America/Mexico_City",
    "iso:country":"MX",
    "wof:name":"El Cacahuatal",
    "wof:placetype":"locality",
    "wof:population":9
},
  "geometry": {"coordinates":[-96.35194,19.18806],"type":"Point"}
}