{
  "type": "Feature",
  "properties": {
    "gn:admin1_code":"26",
    "gn:admin2_code":"33.0",
    "gn:asciiname":"Moroncarit",
    "gn:country_code":"MX",
    "gn:dem":6,
    "gn:feature_class":"P",
    "gn:feature_code":"PPL",
    "gn:name":"Moroncarit",
    "gn:population":0,
    "gn:timezone":"America/Hermosillo",
    "iso:country":"MX",
    "name:und_x_variant":[
        "Moroneari",
        "Moroncari",
        "Moroncarit"
    ],
    "wof:name":"Moroncarit",
    "wof:placetype":"locality"
},
  "geometry": {"coordinates":[-109.61676,26.73307],"type":"Point"}
}