{
  "type": "Feature",
  "properties": {
    "gn:admin1_code":"14",
    "gn:admin2_code":"61.0",
    "gn:asciiname":"Mesa de Zapopan (Zapopan)",
    "gn:country_code":"MX",
    "gn:dem":1336,
    "gn:feature_class":"P",
    "gn:feature_code":"PPL",
    "gn:name":"Mesa de Zapopan (Zapopan)",
    "gn:population":9,
    "gn:timezone":"America/Mexico_City",
    "iso:country":"MX",
    "wof:name":"Mesa de Zapopan (Zapopan)",
    "wof:placetype":"locality",
    "wof:population":9
},
  "geometry": {"coordinates":[-104.01944,21.965],"type":"Point"}
}