{
  "type": "Feature",
  "properties": {
    "gn:admin1_code":"14.0",
    "gn:admin2_code":"20.0",
    "gn:asciiname":"El Habillo",
    "gn:country_code":"MX",
    "gn:dem":624,
    "gn:feature_class":"P",
    "gn:feature_code":"PPL",
    "gn:name":"El Habillo",
    "gn:population":0,
    "gn:timezone":"America/Mexico_City",
    "iso:country":"MX",
    "name:spa_x_preferred":[
        "El Habillo"
    ],
    "wof:name":"El Habillo",
    "wof:placetype":"locality"
},
  "geometry": {"coordinates":[-105.31107,20.31187000000001],"type":"Point"}
}