{
  "type": "Feature",
  "properties": {
    "gn:admin1_code":"30.0",
    "gn:admin2_code":"114.0",
    "gn:asciiname":"Pilancones",
    "gn:country_code":"MX",
    "gn:dem":83,
    "gn:feature_class":"P",
    "gn:feature_code":"PPL",
    "gn:name":"Pilancones",
    "gn:population":4,
    "gn:timezone":"America/Mexico_City",
    "iso:country":"MX",
    "name:spa_x_preferred":[
        "Pilancones"
    ],
    "wof:name":"Pilancones",
    "wof:placetype":"locality",
    "wof:population":4
},
  "geometry": {"coordinates":[-96.72167,20.04861],"type":"Point"}
}