{
  "type": "Feature",
  "properties": {
    "gn:admin1_code":"19",
    "gn:admin2_code":"20",
    "gn:asciiname":"Los Gutierrez",
    "gn:country_code":"MX",
    "gn:dem":110,
    "gn:feature_class":"P",
    "gn:feature_code":"PPL",
    "gn:name":"Los Guti\u00e9rrez",
    "gn:population":10,
    "gn:timezone":"America/Monterrey",
    "iso:country":"MX",
    "name:und_x_variant":[
        "Los Guti\u00e9rrez"
    ],
    "wof:name":"Los Gutierrez",
    "wof:placetype":"locality",
    "wof:population":10
},
  "geometry": {"coordinates":[-98.74558,25.99591],"type":"Point"}
}