{
  "type": "Feature",
  "properties": {
    "gn:admin1_code":"21",
    "gn:admin2_code":"156",
    "gn:asciiname":"El Cocopache",
    "gn:country_code":"MX",
    "gn:dem":1947,
    "gn:feature_class":"P",
    "gn:feature_code":"PPL",
    "gn:name":"El Cocopache",
    "gn:population":12,
    "gn:timezone":"America/Mexico_City",
    "iso:country":"MX",
    "wof:name":"El Cocopache",
    "wof:placetype":"locality",
    "wof:population":12
},
  "geometry": {"coordinates":[-97.57495,18.38797000000001],"type":"Point"}
}