{
  "type": "Feature",
  "properties": {
    "iso:country":"MX",
    "name:spa_x_preferred":[
        "Benito Juarez"
    ],
    "qs:gn_adm0_cc":"MX",
    "qs:gn_local":3979673,
    "qs:gn_nam_loc":"zihuatanejo",
    "qs:gn_namadm1":"12",
    "qs:local_max":906,
    "qs:local_sum":1803,
    "qs:localhoods":4,
    "qs:name":"Benito Juarez",
    "qs:name_adm0":"M\u00e9xico",
    "qs:name_adm1":"Guerrero",
    "qs:name_adm2":"Jose Azueta",
    "qs:name_local":"Zihuatanejo",
    "qs:photo_max":51,
    "qs:photo_sum":83,
    "qs:placetype":"Suburb",
    "qs:quad_count":8,
    "qs:woe_adm0":23424900,
    "qs:woe_adm1":2346275,
    "qs:woe_adm2":12600073,
    "qs:woe_lau":0,
    "qs:woe_local":151732,
    "qs:woe_ver":"7.10.0",
    "wof:lang":[
        "spa"
    ],
    "wof:name":"Benito Juarez",
    "wof:placetype":"neighbourhood"
},
  "geometry": {"coordinates":[-101.55997600000001,17.636662],"type":"Point"}
}