{
  "type": "Feature",
  "properties": {
    "gn:admin1_code":"2.0",
    "gn:admin2_code":"3.0",
    "gn:asciiname":"Rancho el Jonuco",
    "gn:country_code":"MX",
    "gn:dem":728,
    "gn:feature_class":"P",
    "gn:feature_code":"PPL",
    "gn:name":"Rancho el Jonuco",
    "gn:population":0,
    "gn:timezone":"America/Tijuana",
    "iso:country":"MX",
    "name:spa_x_preferred":[
        "Rancho el Jonuco"
    ],
    "wof:name":"Rancho el Jonuco",
    "wof:placetype":"locality"
},
  "geometry": {"coordinates":[-116.59444999999999,32.49584],"type":"Point"}
}