{
  "type": "Feature",
  "properties": {
    "gn:admin1_code":"24",
    "gn:admin2_code":"55.0",
    "gn:asciiname":"Santo Domingo",
    "gn:country_code":"MX",
    "gn:dem":1981,
    "gn:feature_class":"P",
    "gn:feature_code":"PPL",
    "gn:name":"Santo Domingo",
    "gn:population":0,
    "gn:timezone":"America/Mexico_City",
    "iso:country":"MX",
    "name:spa_x_preferred":[
        "Santo Domingo"
    ],
    "wof:name":"Santo Domingo",
    "wof:placetype":"locality"
},
  "geometry": {"coordinates":[-100.74405,22.09944],"type":"Point"}
}