{
  "type": "Feature",
  "properties": {
    "gn:admin1_code":"6",
    "gn:admin2_code":"8.0",
    "gn:asciiname":"Puerto Colorado",
    "gn:country_code":"MX",
    "gn:dem":1017,
    "gn:feature_class":"P",
    "gn:feature_code":"PPL",
    "gn:name":"Puerto Colorado",
    "gn:population":6,
    "gn:timezone":"America/Chihuahua",
    "iso:country":"MX",
    "wof:name":"Puerto Colorado",
    "wof:placetype":"locality",
    "wof:population":6
},
  "geometry": {"coordinates":[-107.79212,26.88632],"type":"Point"}
}