{
  "type": "Feature",
  "properties": {
    "gn:admin1_code":"21",
    "gn:admin2_code":"45.0",
    "gn:asciiname":"Alvaro Obregon",
    "gn:country_code":"MX",
    "gn:dem":2478,
    "gn:feature_class":"P",
    "gn:feature_code":"PPL",
    "gn:name":"\u00c1lvaro Obreg\u00f3n",
    "gn:population":505,
    "gn:timezone":"America/Mexico_City",
    "iso:country":"MX",
    "name:und_x_variant":[
        "\u00c1lvaro Obreg\u00f3n"
    ],
    "wof:name":"Alvaro Obregon",
    "wof:placetype":"locality",
    "wof:population":505
},
  "geometry": {"coordinates":[-97.42471999999999,18.90417],"type":"Point"}
}