{
  "type": "Feature",
  "properties": {
    "gn:admin1_code":"31",
    "gn:admin2_code":"102.0",
    "gn:asciiname":"Papagayo",
    "gn:country_code":"MX",
    "gn:dem":22,
    "gn:feature_class":"P",
    "gn:feature_code":"PPL",
    "gn:name":"Papagayo",
    "gn:population":91,
    "gn:timezone":"America/Merida",
    "iso:country":"MX",
    "wof:name":"Papagayo",
    "wof:placetype":"locality",
    "wof:population":91
},
  "geometry": {"coordinates":[-88.15555999999999,20.71306],"type":"Point"}
}