{
  "type": "Feature",
  "properties": {
    "iso:country":"MX",
    "name:epo_x_preferred":[
        "Petatl\u00e1n"
    ],
    "name:eus_x_preferred":[
        "Petatl\u00e1n"
    ],
    "name:rus_x_preferred":[
        "\u041f\u0435\u0442\u0430\u0442\u043b\u0430\u043d"
    ],
    "name:spa_x_preferred":[
        "Teniente Azueta",
        "Petatl\u00e1n"
    ],
    "qs:gn_adm0_cc":"MX",
    "qs:gn_local":3987544,
    "qs:gn_nam_loc":"San Blas, San Blas, Nayarit, MX",
    "qs:gn_namadm1":"18",
    "qs:local_max":50,
    "qs:local_sum":91,
    "qs:localhoods":4,
    "qs:name":"Teniente Azueta",
    "qs:name_adm0":"M\u00e9xico",
    "qs:name_adm1":"Nayarit",
    "qs:name_adm2":"San Blas",
    "qs:name_local":"San Blas",
    "qs:photo_max":11,
    "qs:photo_sum":19,
    "qs:placetype":"Suburb",
    "qs:quad_count":3,
    "qs:woe_adm0":23424900,
    "qs:woe_adm1":2346281,
    "qs:woe_adm2":12600598,
    "qs:woe_lau":0,
    "qs:woe_local":142028,
    "qs:woe_ver":"7.10.0",
    "wof:lang":[
        "spa"
    ],
    "wof:name":"Teniente Azueta",
    "wof:placetype":"neighbourhood"
},
  "geometry": {"coordinates":[-105.285307,21.53014],"type":"Point"}
}