{
  "type": "Feature",
  "properties": {
    "gn:admin1_code":"6",
    "gn:admin2_code":"27.0",
    "gn:asciiname":"Bajio de Tonachi",
    "gn:country_code":"MX",
    "gn:dem":2418,
    "gn:feature_class":"P",
    "gn:feature_code":"PPL",
    "gn:name":"Baj\u00edo de T\u00f3nachi",
    "gn:population":0,
    "gn:timezone":"America/Chihuahua",
    "iso:country":"MX",
    "name:spa_x_preferred":[
        "Baj\u00edo de T\u00f3nachi"
    ],
    "name:und_x_variant":[
        "Baj\u00edo de Conachi"
    ],
    "wof:name":"Bajio de Tonachi",
    "wof:placetype":"locality"
},
  "geometry": {"coordinates":[-107.1352,26.85682000000001],"type":"Point"}
}