{
  "type": "Feature",
  "properties": {
    "gn:admin1_code":"28",
    "gn:admin2_code":"35.0",
    "gn:asciiname":"Hualala",
    "gn:country_code":"MX",
    "gn:dem":76,
    "gn:feature_class":"P",
    "gn:feature_code":"PPL",
    "gn:name":"Hualal\u00e1",
    "gn:population":0,
    "gn:timezone":"America/Monterrey",
    "iso:country":"MX",
    "name:spa_x_preferred":[
        "Hualal\u00e1"
    ],
    "name:und_x_variant":[
        "Rancho Hualala"
    ],
    "wof:name":"Hualala",
    "wof:placetype":"locality"
},
  "geometry": {"coordinates":[-98.06237,24.52372],"type":"Point"}
}