{
  "type": "Feature",
  "properties": {
    "gn:admin1_code":"16.0",
    "gn:admin2_code":"94.0",
    "gn:asciiname":"El Tecolote",
    "gn:country_code":"MX",
    "gn:dem":1833,
    "gn:feature_class":"P",
    "gn:feature_code":"PPL",
    "gn:name":"El Tecolote",
    "gn:population":0,
    "gn:timezone":"America/Mexico_City",
    "iso:country":"MX",
    "name:ceb_x_preferred":[
        "El Tecolote"
    ],
    "name:swe_x_preferred":[
        "El Tecolote"
    ],
    "wof:name":"El Tecolote",
    "wof:placetype":"locality"
},
  "geometry": {"coordinates":[-102.09941999999999,20.0051],"type":"Point"}
}