{
  "type": "Feature",
  "properties": {
    "gn:admin1_code":"30",
    "gn:admin2_code":"154.0",
    "gn:asciiname":"San Lorenzo",
    "gn:country_code":"MX",
    "gn:dem":41,
    "gn:feature_class":"P",
    "gn:feature_code":"PPL",
    "gn:name":"San Lorenzo",
    "gn:population":0,
    "gn:timezone":"America/Mexico_City",
    "iso:country":"MX",
    "wof:name":"San Lorenzo",
    "wof:placetype":"locality"
},
  "geometry": {"coordinates":[-97.68386,21.45755],"type":"Point"}
}