{
  "type": "Feature",
  "properties": {
    "gn:admin1_code":"11",
    "gn:admin2_code":"20.0",
    "gn:asciiname":"Seminario Conciliar de Leon",
    "gn:country_code":"MX",
    "gn:dem":1780,
    "gn:feature_class":"P",
    "gn:feature_code":"PPL",
    "gn:name":"Seminario Conciliar de Le\u00f3n",
    "gn:population":80,
    "gn:timezone":"America/Mexico_City",
    "iso:country":"MX",
    "name:und_x_variant":[
        "Seminario Conciliar de Le\u00f3n"
    ],
    "wof:name":"Seminario Conciliar de Leon",
    "wof:placetype":"locality",
    "wof:population":80
},
  "geometry": {"coordinates":[-101.715,21.06222],"type":"Point"}
}