{
  "type": "Feature",
  "properties": {
    "gn:admin1_code":"5",
    "gn:admin2_code":"69.0",
    "gn:asciiname":"La Piana",
    "gn:country_code":"MX",
    "gn:dem":13,
    "gn:feature_class":"P",
    "gn:feature_code":"PPL",
    "gn:name":"La Pia\u00f1a",
    "gn:population":118,
    "gn:timezone":"America/Mexico_City",
    "iso:country":"MX",
    "name:und_x_variant":[
        "La Pia\u00f1a"
    ],
    "wof:name":"La Piana",
    "wof:placetype":"locality",
    "wof:population":118
},
  "geometry": {"coordinates":[-93.20332999999999,15.59028],"type":"Point"}
}