{
  "type": "Feature",
  "properties": {
    "gn:admin1_code":"30",
    "gn:admin2_code":"192.0",
    "gn:asciiname":"El Zapote",
    "gn:country_code":"MX",
    "gn:dem":46,
    "gn:feature_class":"P",
    "gn:feature_code":"PPL",
    "gn:name":"El Zapote",
    "gn:population":71,
    "gn:timezone":"America/Mexico_City",
    "iso:country":"MX",
    "name:und_x_variant":[
        "Zapote",
        "El Zapote"
    ],
    "wof:name":"El Zapote",
    "wof:placetype":"locality",
    "wof:population":71
},
  "geometry": {"coordinates":[-96.57314,19.92817],"type":"Point"}
}