{
  "type": "Feature",
  "properties": {
    "gn:admin1_code":"11",
    "gn:admin2_code":"7",
    "gn:asciiname":"Ruben Nolasco Hernandez",
    "gn:country_code":"MX",
    "gn:dem":1781,
    "gn:feature_class":"P",
    "gn:feature_code":"PPL",
    "gn:name":"Rub\u00e9n Nolasco Hern\u00e1ndez",
    "gn:population":24,
    "gn:timezone":"America/Mexico_City",
    "iso:country":"MX",
    "name:und_x_variant":[
        "Rub\u00e9n Nolasco Hern\u00e1ndez"
    ],
    "wof:name":"Ruben Nolasco Hernandez",
    "wof:placetype":"locality",
    "wof:population":24
},
  "geometry": {"coordinates":[-100.78471999999999,20.64167],"type":"Point"}
}