{
  "type": "Feature",
  "properties": {
    "gn:admin1_code":"12",
    "gn:admin2_code":"16.0",
    "gn:asciiname":"El Jicaral",
    "gn:country_code":"MX",
    "gn:dem":829,
    "gn:feature_class":"P",
    "gn:feature_code":"PPL",
    "gn:name":"El Jicaral",
    "gn:population":1089,
    "gn:timezone":"America/Mexico_City",
    "iso:country":"MX",
    "name:spa_x_preferred":[
        "El Jicaral"
    ],
    "wof:name":"El Jicaral",
    "wof:placetype":"locality",
    "wof:population":1089
},
  "geometry": {"coordinates":[-98.19696999999999,17.12617],"type":"Point"}
}