{
  "type": "Feature",
  "properties": {
    "gn:admin1_code":"5",
    "gn:admin2_code":"5.0",
    "gn:asciiname":"La Lomita",
    "gn:country_code":"MX",
    "gn:dem":437,
    "gn:feature_class":"P",
    "gn:feature_code":"PPL",
    "gn:name":"La Lomita",
    "gn:population":62,
    "gn:timezone":"America/Mexico_City",
    "iso:country":"MX",
    "wof:name":"La Lomita",
    "wof:placetype":"locality",
    "wof:population":62
},
  "geometry": {"coordinates":[-92.84778,17.35],"type":"Point"}
}