{
  "type": "Feature",
  "properties": {
    "gn:admin1_code":"20",
    "gn:admin2_code":"275.0",
    "gn:asciiname":"El Zacatal",
    "gn:country_code":"MX",
    "gn:dem":1298,
    "gn:feature_class":"P",
    "gn:feature_code":"PPL",
    "gn:name":"El Zacatal",
    "gn:population":6,
    "gn:timezone":"America/Mexico_City",
    "iso:country":"MX",
    "wof:name":"El Zacatal",
    "wof:placetype":"locality",
    "wof:population":6
},
  "geometry": {"coordinates":[-95.74861,16.95861],"type":"Point"}
}