{
  "type": "Feature",
  "properties": {
    "gn:admin1_code":"21",
    "gn:admin2_code":"208",
    "gn:asciiname":"Xatohuanco",
    "gn:country_code":"MX",
    "gn:dem":1991,
    "gn:feature_class":"P",
    "gn:feature_code":"PPL",
    "gn:name":"Xatohuanco",
    "gn:population":13,
    "gn:timezone":"America/Mexico_City",
    "iso:country":"MX",
    "wof:name":"Xatohuanco",
    "wof:placetype":"locality",
    "wof:population":13
},
  "geometry": {"coordinates":[-97.92891,19.88946],"type":"Point"}
}