{
  "type": "Feature",
  "properties": {
    "gn:admin1_code":"11",
    "gn:admin2_code":"43.0",
    "gn:asciiname":"Los Parajitos",
    "gn:country_code":"MX",
    "gn:dem":2080,
    "gn:feature_class":"P",
    "gn:feature_code":"PPL",
    "gn:name":"Los Parajitos",
    "gn:population":6,
    "gn:timezone":"America/Mexico_City",
    "iso:country":"MX",
    "wof:name":"Los Parajitos",
    "wof:placetype":"locality",
    "wof:population":6
},
  "geometry": {"coordinates":[-100.20056,21.29306],"type":"Point"}
}