{
  "type": "Feature",
  "properties": {
    "gn:admin1_code":"30",
    "gn:admin2_code":"154.0",
    "gn:asciiname":"Los Panchos",
    "gn:country_code":"MX",
    "gn:dem":48,
    "gn:feature_class":"P",
    "gn:feature_code":"PPL",
    "gn:name":"Los Panchos",
    "gn:population":5,
    "gn:timezone":"America/Mexico_City",
    "iso:country":"MX",
    "wof:name":"Los Panchos",
    "wof:placetype":"locality",
    "wof:population":5
},
  "geometry": {"coordinates":[-97.76667,21.45944],"type":"Point"}
}