{
  "type": "Feature",
  "properties": {
    "gn:admin1_code":"30",
    "gn:admin2_code":"154.0",
    "gn:asciiname":"Los Panchos",
    "gn:country_code":"MX",
    "gn:dem":48,
    "gn:feature_class":"P",
    "gn:feature_code":"PPL",
    "gn:name":"Los Panchos",
    "gn:population":5,
    "gn:timezone":"America/Mexico_City",
    "iso:country":"MX",
    "name:azb_x_preferred":[
        "\u067e\u0627\u0646\u0686\u0648\u0633"
    ],
    "name:bre_x_preferred":[
        "Los Panchos"
    ],
    "name:cat_x_preferred":[
        "Los Panchos"
    ],
    "name:epo_x_preferred":[
        "Los Panchos"
    ],
    "name:eus_x_preferred":[
        "Los Panchos"
    ],
    "name:fas_x_preferred":[
        "\u067e\u0627\u0646\u0686\u0648\u0633"
    ],
    "name:fin_x_preferred":[
        "Los Panchos"
    ],
    "name:fra_x_preferred":[
        "Los Panchos"
    ],
    "name:glg_x_preferred":[
        "Los Panchos"
    ],
    "name:ind_x_preferred":[
        "Los Panchos"
    ],
    "name:ita_x_preferred":[
        "Los Panchos"
    ],
    "name:jpn_x_preferred":[
        "\u30ed\u30b9\u30fb\u30d1\u30f3\u30c1\u30e7\u30b9"
    ],
    "name:kor_x_preferred":[
        "\ud2b8\ub9ac\uc624 \ub85c\uc2a4 \ud310\ucd08\uc2a4"
    ],
    "name:por_x_preferred":[
        "Los Panchos"
    ],
    "name:que_x_preferred":[
        "Los Panchos"
    ],
    "name:spa_x_preferred":[
        "Los Panchos"
    ],
    "name:war_x_preferred":[
        "Los Panchos"
    ],
    "wof:name":"Los Panchos",
    "wof:placetype":"locality",
    "wof:population":5
},
  "geometry": {"coordinates":[-97.76667,21.45944],"type":"Point"}
}