{
  "type": "Feature",
  "properties": {
    "gn:admin1_code":"2",
    "gn:admin2_code":"2.0",
    "gn:asciiname":"Zaragoza",
    "gn:country_code":"MX",
    "gn:dem":5,
    "gn:feature_class":"P",
    "gn:feature_code":"PPL",
    "gn:name":"Zaragoza",
    "gn:population":0,
    "gn:timezone":"America/Tijuana",
    "iso:country":"MX",
    "name:spa_x_preferred":[
        "Zaragoza"
    ],
    "name:und_x_variant":[
        "Zaragoza Segunda Secci\u00f3n"
    ],
    "wof:name":"Zaragoza",
    "wof:placetype":"locality"
},
  "geometry": {"coordinates":[-115.53305,32.60187],"type":"Point"}
}