{
  "type": "Feature",
  "properties": {
    "gn:admin1_code":"10",
    "gn:asciiname":"Mezcalera",
    "gn:country_code":"MX",
    "gn:dem":2237,
    "gn:feature_class":"P",
    "gn:feature_code":"PPL",
    "gn:name":"Mezcalera",
    "gn:population":0,
    "gn:timezone":"America/Monterrey",
    "iso:country":"MX",
    "name:spa_x_preferred":[
        "Mezcalera"
    ],
    "wof:name":"Mezcalera",
    "wof:placetype":"locality"
},
  "geometry": {"coordinates":[-106.84748,25.61196],"type":"Point"}
}