{
  "type": "Feature",
  "properties": {
    "gn:admin1_code":"14",
    "gn:admin2_code":"86.0",
    "gn:asciiname":"Cabana el Chivo Alegre",
    "gn:country_code":"MX",
    "gn:dem":2489,
    "gn:feature_class":"P",
    "gn:feature_code":"PPL",
    "gn:name":"Caba\u00f1a el Chivo Alegre",
    "gn:population":5,
    "gn:timezone":"America/Mexico_City",
    "iso:country":"MX",
    "name:und_x_variant":[
        "Caba\u00f1a el Chivo Alegre"
    ],
    "wof:name":"Cabana el Chivo Alegre",
    "wof:placetype":"locality",
    "wof:population":5
},
  "geometry": {"coordinates":[-103.71693999999999,20.00472],"type":"Point"}
}