{
  "type": "Feature",
  "properties": {
    "gn:admin1_code":"16",
    "gn:admin2_code":"19.0",
    "gn:asciiname":"Plan del Cerro (La Playa)",
    "gn:country_code":"MX",
    "gn:dem":2217,
    "gn:feature_class":"P",
    "gn:feature_code":"PPL",
    "gn:name":"Plan del Cerro (La Playa)",
    "gn:population":67,
    "gn:timezone":"America/Mexico_City",
    "iso:country":"MX",
    "wof:name":"Plan del Cerro (La Playa)",
    "wof:placetype":"locality",
    "wof:population":67
},
  "geometry": {"coordinates":[-102.72806,19.75972],"type":"Point"}
}