{
  "type": "Feature",
  "properties": {
    "gn:admin1_code":"26",
    "gn:admin2_code":"49.0",
    "gn:asciiname":"Mutica",
    "gn:country_code":"MX",
    "gn:dem":485,
    "gn:feature_class":"P",
    "gn:feature_code":"PPL",
    "gn:name":"M\u00fatica",
    "gn:population":0,
    "gn:timezone":"America/Hermosillo",
    "iso:country":"MX",
    "name:und_x_variant":[
        "Rancho M\u00fatica",
        "M\u00fatica"
    ],
    "wof:name":"Mutica",
    "wof:placetype":"locality"
},
  "geometry": {"coordinates":[-109.50566999999999,27.79136],"type":"Point"}
}