{
  "type": "Feature",
  "properties": {
    "gn:admin1_code":"5",
    "gn:admin2_code":"17",
    "gn:asciiname":"Siete Hermanos",
    "gn:country_code":"MX",
    "gn:dem":725,
    "gn:feature_class":"P",
    "gn:feature_code":"PPL",
    "gn:name":"Siete Hermanos",
    "gn:population":14,
    "gn:timezone":"America/Mexico_City",
    "iso:country":"MX",
    "wof:name":"Siete Hermanos",
    "wof:placetype":"locality",
    "wof:population":14
},
  "geometry": {"coordinates":[-94.05222000000001,16.50972],"type":"Point"}
}