{
  "type": "Feature",
  "properties": {
    "gn:admin1_code":"13",
    "gn:admin2_code":"3.0",
    "gn:asciiname":"Saucillo",
    "gn:country_code":"MX",
    "gn:dem":2178,
    "gn:feature_class":"P",
    "gn:feature_code":"PPL",
    "gn:name":"Saucillo",
    "gn:population":0,
    "gn:timezone":"America/Mexico_City",
    "iso:country":"MX",
    "name:spa_x_preferred":[
        "Saucillo"
    ],
    "wof:name":"Saucillo",
    "wof:placetype":"locality"
},
  "geometry": {"coordinates":[-98.88552,20.35114],"type":"Point"}
}