{
  "type": "Feature",
  "properties": {
    "gn:admin1_code":"13",
    "gn:admin2_code":"3.0",
    "gn:asciiname":"Saucillo",
    "gn:country_code":"MX",
    "gn:dem":2178,
    "gn:feature_class":"P",
    "gn:feature_code":"PPL",
    "gn:name":"Saucillo",
    "gn:population":0,
    "gn:timezone":"America/Mexico_City",
    "iso:country":"MX",
    "name:ara_x_preferred":[
        "\u0633\u0627\u0648\u0633\u064a\u0644\u0644\u0648"
    ],
    "name:ita_x_preferred":[
        "Saucillo"
    ],
    "name:por_x_preferred":[
        "Saucillo"
    ],
    "name:rus_x_preferred":[
        "\u0421\u0430\u0443\u0441\u0438\u043b\u044c\u043e"
    ],
    "name:sco_x_preferred":[
        "Saucillo"
    ],
    "name:spa_x_preferred":[
        "Saucillo"
    ],
    "name:srp_x_preferred":[
        "\u0421\u0430\u0443\u0441\u0438\u0459\u043e"
    ],
    "wof:name":"Saucillo",
    "wof:placetype":"locality"
},
  "geometry": {"coordinates":[-98.88552,20.35114],"type":"Point"}
}