{
  "type": "Feature",
  "properties": {
    "gn:admin1_code":"25",
    "gn:admin2_code":"7",
    "gn:asciiname":"Los Cauques",
    "gn:country_code":"MX",
    "gn:dem":183,
    "gn:feature_class":"P",
    "gn:feature_code":"PPL",
    "gn:name":"Los Cauques",
    "gn:population":15,
    "gn:timezone":"America/Mazatlan",
    "iso:country":"MX",
    "wof:name":"Los Cauques",
    "wof:placetype":"locality",
    "wof:population":15
},
  "geometry": {"coordinates":[-108.48273,26.67099],"type":"Point"}
}