{
  "type": "Feature",
  "properties": {
    "gn:admin1_code":"21.0",
    "gn:asciiname":"Vaquerias",
    "gn:country_code":"MX",
    "gn:dem":157,
    "gn:feature_class":"P",
    "gn:feature_code":"PPL",
    "gn:name":"Vaquer\u00edas",
    "gn:population":0,
    "gn:timezone":"America/Mexico_City",
    "iso:country":"MX",
    "name:spa_x_preferred":[
        "Vaquer\u00edas"
    ],
    "wof:name":"Vaquerias",
    "wof:placetype":"locality"
},
  "geometry": {"coordinates":[-97.64464,20.56572],"type":"Point"}
}