{
  "type": "Feature",
  "properties": {
    "gn:admin1_code":"24",
    "gn:admin2_code":"15",
    "gn:asciiname":"Nabor Moreno",
    "gn:country_code":"MX",
    "gn:dem":2067,
    "gn:feature_class":"P",
    "gn:feature_code":"PPL",
    "gn:name":"Nabor Moreno",
    "gn:population":21,
    "gn:timezone":"America/Mexico_City",
    "iso:country":"MX",
    "wof:name":"Nabor Moreno",
    "wof:placetype":"locality",
    "wof:population":21
},
  "geometry": {"coordinates":[-101.02943999999999,23.205],"type":"Point"}
}