{
  "type": "Feature",
  "properties": {
    "gn:admin1_code":"25",
    "gn:admin2_code":"13.0",
    "gn:asciiname":"Juan Escutia",
    "gn:country_code":"MX",
    "gn:dem":32,
    "gn:feature_class":"P",
    "gn:feature_code":"PPL",
    "gn:name":"Juan Escutia",
    "gn:population":624,
    "gn:timezone":"America/Mazatlan",
    "iso:country":"MX",
    "wof:name":"Juan Escutia",
    "wof:placetype":"locality",
    "wof:population":624
},
  "geometry": {"coordinates":[-107.73444000000001,24.94083],"type":"Point"}
}