{
  "type": "Feature",
  "properties": {
    "gn:admin1_code":"5",
    "gn:admin2_code":"19.0",
    "gn:asciiname":"Los Girasoles",
    "gn:country_code":"MX",
    "gn:dem":1568,
    "gn:feature_class":"P",
    "gn:feature_code":"PPL",
    "gn:name":"Los Girasoles",
    "gn:population":5,
    "gn:timezone":"America/Mexico_City",
    "iso:country":"MX",
    "wof:name":"Los Girasoles",
    "wof:placetype":"locality",
    "wof:population":5
},
  "geometry": {"coordinates":[-92.14118999999999,16.1987],"type":"Point"}
}