{
  "type": "Feature",
  "properties": {
    "gn:admin1_code":"13",
    "gn:admin2_code":"40.0",
    "gn:asciiname":"El Chamal",
    "gn:country_code":"MX",
    "gn:dem":1606,
    "gn:feature_class":"P",
    "gn:feature_code":"PPL",
    "gn:name":"El Chamal",
    "gn:population":157,
    "gn:timezone":"America/Mexico_City",
    "iso:country":"MX",
    "wof:name":"El Chamal",
    "wof:placetype":"locality",
    "wof:population":157
},
  "geometry": {"coordinates":[-99.075,21.0575],"type":"Point"}
}