{
  "type": "Feature",
  "properties": {
    "gn:admin1_code":"30",
    "gn:admin2_code":"108.0",
    "gn:asciiname":"La Victoria",
    "gn:country_code":"MX",
    "gn:dem":13,
    "gn:feature_class":"P",
    "gn:feature_code":"PPL",
    "gn:name":"La Victoria",
    "gn:population":5,
    "gn:timezone":"America/Mexico_City",
    "iso:country":"MX",
    "wof:name":"La Victoria",
    "wof:placetype":"locality",
    "wof:population":5
},
  "geometry": {"coordinates":[-94.20444000000001,17.85389],"type":"Point"}
}