{
  "type": "Feature",
  "properties": {
    "gn:admin1_code":"14",
    "gn:admin2_code":"5.0",
    "gn:asciiname":"Chome (Achio)",
    "gn:country_code":"MX",
    "gn:dem":999,
    "gn:feature_class":"P",
    "gn:feature_code":"PPL",
    "gn:name":"Chome (Ach\u00edo)",
    "gn:population":190,
    "gn:timezone":"America/Mexico_City",
    "iso:country":"MX",
    "name:und_x_variant":[
        "Chome (Ach\u00edo)"
    ],
    "wof:name":"Chome (Achio)",
    "wof:placetype":"locality",
    "wof:population":190
},
  "geometry": {"coordinates":[-103.73528,20.89528],"type":"Point"}
}