{
  "type": "Feature",
  "properties": {
    "gn:admin1_code":"14",
    "gn:admin2_code":"85",
    "gn:asciiname":"El Lindero (El Rebaje)",
    "gn:country_code":"MX",
    "gn:dem":1205,
    "gn:feature_class":"P",
    "gn:feature_code":"PPL",
    "gn:name":"El Lindero (El Rebaje)",
    "gn:population":37,
    "gn:timezone":"America/Mexico_City",
    "iso:country":"MX",
    "wof:name":"El Lindero (El Rebaje)",
    "wof:placetype":"locality",
    "wof:population":37
},
  "geometry": {"coordinates":[-103.24028,19.61361],"type":"Point"}
}