{
  "type": "Feature",
  "properties": {
    "gn:admin1_code":"11.0",
    "gn:admin2_code":"14.0",
    "gn:asciiname":"Garabatillo",
    "gn:country_code":"MX",
    "gn:dem":2028,
    "gn:feature_class":"P",
    "gn:feature_code":"PPL",
    "gn:name":"Garabatillo",
    "gn:population":0,
    "gn:timezone":"America/Mexico_City",
    "iso:country":"MX",
    "name:spa_x_preferred":[
        "Garabatillo"
    ],
    "wof:name":"Garabatillo",
    "wof:placetype":"locality"
},
  "geometry": {"coordinates":[-100.74844,21.31354],"type":"Point"}
}