{
  "type": "Feature",
  "properties": {
    "gn:admin1_code":"16",
    "gn:admin2_code":"38.0",
    "gn:asciiname":"Los Aguadalitos (Arroyo Zarco)",
    "gn:country_code":"MX",
    "gn:dem":357,
    "gn:feature_class":"P",
    "gn:feature_code":"PPL",
    "gn:name":"Los Aguadalitos (Arroyo Zarco)",
    "gn:population":6,
    "gn:timezone":"America/Mexico_City",
    "iso:country":"MX",
    "wof:name":"Los Aguadalitos (Arroyo Zarco)",
    "wof:placetype":"locality",
    "wof:population":6
},
  "geometry": {"coordinates":[-101.08833,18.62833],"type":"Point"}
}