{
  "type": "Feature",
  "properties": {
    "gn:admin1_code":"22",
    "gn:admin2_code":"1.0",
    "gn:asciiname":"Loma del Chivo",
    "gn:country_code":"MX",
    "gn:dem":2553,
    "gn:feature_class":"P",
    "gn:feature_code":"PPL",
    "gn:name":"Loma del Chivo",
    "gn:population":54,
    "gn:timezone":"America/Mexico_City",
    "iso:country":"MX",
    "wof:name":"Loma del Chivo",
    "wof:placetype":"locality",
    "wof:population":54
},
  "geometry": {"coordinates":[-100.06444,20.11806],"type":"Point"}
}