{
  "type": "Feature",
  "properties": {
    "gn:admin1_code":"11.0",
    "gn:admin2_code":"33.0",
    "gn:asciiname":"San Juan de la Enramada",
    "gn:country_code":"MX",
    "gn:dem":2026,
    "gn:feature_class":"P",
    "gn:feature_code":"PPL",
    "gn:name":"San Juan de la Enramada",
    "gn:population":57,
    "gn:timezone":"America/Mexico_City",
    "iso:country":"MX",
    "wof:name":"San Juan de la Enramada",
    "wof:placetype":"locality",
    "wof:population":57
},
  "geometry": {"coordinates":[-100.66694,21.29472],"type":"Point"}
}