{
  "type": "Feature",
  "properties": {
    "gn:admin1_code":"7",
    "gn:admin2_code":"11.0",
    "gn:asciiname":"Sabanilla",
    "gn:country_code":"MX",
    "gn:dem":1288,
    "gn:feature_class":"P",
    "gn:feature_code":"PPL",
    "gn:name":"Sabanilla",
    "gn:population":4,
    "gn:timezone":"America/Monterrey",
    "iso:country":"MX",
    "wof:name":"Sabanilla",
    "wof:placetype":"locality",
    "wof:population":4
},
  "geometry": {"coordinates":[-101.41476,25.4753],"type":"Point"}
}