{
  "type": "Feature",
  "properties": {
    "gn:admin1_code":"28",
    "gn:admin2_code":"1.0",
    "gn:asciiname":"Santa Fe de la Ceja",
    "gn:country_code":"MX",
    "gn:dem":162,
    "gn:feature_class":"P",
    "gn:feature_code":"PPL",
    "gn:name":"Santa Fe de la Ceja",
    "gn:population":0,
    "gn:timezone":"America/Monterrey",
    "iso:country":"MX",
    "name:spa_x_preferred":[
        "Santa Fe de la Ceja"
    ],
    "name:und_x_variant":[
        "La Ceja"
    ],
    "wof:name":"Santa Fe de la Ceja",
    "wof:placetype":"locality"
},
  "geometry": {"coordinates":[-98.30240000000001,24.20665],"type":"Point"}
}