{
  "type": "Feature",
  "properties": {
    "gn:admin1_code":"7",
    "gn:admin2_code":"33.0",
    "gn:asciiname":"Ejido San Nicolas",
    "gn:country_code":"MX",
    "gn:dem":1093,
    "gn:feature_class":"P",
    "gn:feature_code":"PPL",
    "gn:name":"Ejido San Nicol\u00e1s",
    "gn:population":0,
    "gn:timezone":"America/Monterrey",
    "iso:country":"MX",
    "name:spa_x_preferred":[
        "Ejido San Nicol\u00e1s"
    ],
    "name:und_x_variant":[
        "San Nicol\u00e1s"
    ],
    "wof:name":"Ejido San Nicolas",
    "wof:placetype":"locality"
},
  "geometry": {"coordinates":[-102.79237000000001,25.71362],"type":"Point"}
}