{
  "type": "Feature",
  "properties": {
    "gn:admin1_code":"5",
    "gn:admin2_code":"31.0",
    "gn:asciiname":"Rio San Pedro",
    "gn:country_code":"MX",
    "gn:dem":358,
    "gn:feature_class":"P",
    "gn:feature_code":"PPL",
    "gn:name":"R\u00edo San Pedro",
    "gn:population":58,
    "gn:timezone":"America/Mexico_City",
    "iso:country":"MX",
    "name:und_x_variant":[
        "R\u00edo San Pedro"
    ],
    "wof:name":"Rio San Pedro",
    "wof:placetype":"locality",
    "wof:population":58
},
  "geometry": {"coordinates":[-92.12694,17.22444],"type":"Point"}
}