{
  "type": "Feature",
  "properties": {
    "gn:admin1_code":"5",
    "gn:admin2_code":"97.0",
    "gn:asciiname":"Ocuilapa",
    "gn:cc2":"MX",
    "gn:country_code":"MX",
    "gn:dem":83,
    "gn:feature_class":"P",
    "gn:feature_code":"PPL",
    "gn:name":"Ocuilapa",
    "gn:population":38,
    "gn:timezone":"America/Mexico_City",
    "iso:country":"MX",
    "name:und_x_variant":[
        "Ocuilapan",
        "Ocuilapa"
    ],
    "wof:name":"Ocuilapa",
    "wof:placetype":"locality",
    "wof:population":38
},
  "geometry": {"coordinates":[-93.67139,16.0125],"type":"Point"}
}