{
  "type": "Feature",
  "properties": {
    "gn:admin1_code":"18.0",
    "gn:admin2_code":"17.0",
    "gn:asciiname":"El Ahuacate",
    "gn:country_code":"MX",
    "gn:dem":995,
    "gn:feature_class":"P",
    "gn:feature_code":"PPL",
    "gn:name":"El Ahuacate",
    "gn:population":0,
    "gn:timezone":"America/Mazatlan",
    "iso:country":"MX",
    "name:spa_x_preferred":[
        "El Ahuacate"
    ],
    "name:und_x_variant":[
        "Aguacate",
        "El Aguacate"
    ],
    "wof:name":"El Ahuacate",
    "wof:placetype":"locality"
},
  "geometry": {"coordinates":[-104.94436,21.51535],"type":"Point"}
}