{
  "type": "Feature",
  "properties": {
    "gn:admin1_code":"23",
    "gn:admin2_code":"5.0",
    "gn:asciiname":"Aduana",
    "gn:country_code":"MX",
    "gn:dem":8,
    "gn:feature_class":"P",
    "gn:feature_code":"PPL",
    "gn:name":"Aduana",
    "gn:population":0,
    "gn:timezone":"America/Cancun",
    "iso:country":"MX",
    "wof:name":"Aduana",
    "wof:placetype":"locality"
},
  "geometry": {"coordinates":[-86.86667,20.99167000000001],"type":"Point"}
}