{
  "type": "Feature",
  "properties": {
    "gn:admin1_code":"20",
    "gn:admin2_code":"236.0",
    "gn:asciiname":"La Luz del Oriente",
    "gn:country_code":"MX",
    "gn:dem":2067,
    "gn:feature_class":"P",
    "gn:feature_code":"PPL",
    "gn:name":"La Luz del Oriente",
    "gn:population":92,
    "gn:timezone":"America/Mexico_City",
    "iso:country":"MX",
    "wof:name":"La Luz del Oriente",
    "wof:placetype":"locality",
    "wof:population":92
},
  "geometry": {"coordinates":[-96.3875,16.04],"type":"Point"}
}