{
  "type": "Feature",
  "properties": {
    "gn:gn_country":"MX",
    "gn:gn_fcode":"PPL",
    "gn:gn_pop":4749,
    "gn:population":4749,
    "iso:country":"MX",
    "name:spa_x_preferred":[
        "San Francisco Pich\u00e1taro"
    ],
    "name:unk_x_variant":[
        "Pich\u00e1taro"
    ],
    "qs_pg:aaroncc":"MX",
    "qs_pg:gn_country":"MX",
    "qs_pg:gn_fcode":"PPL",
    "qs_pg:gn_pop":4749,
    "qs_pg:name":"San Francisco Pichataro",
    "qs_pg:name_adm0":"M\u00e9xico",
    "qs_pg:name_adm1":"Michoacan de Ocampo",
    "qs_pg:photos_9k":1,
    "qs_pg:photos_9r":1,
    "qs_pg:photos_all":1,
    "qs_pg:photos_sr":0,
    "qs_pg:pop_sr":4,
    "qs_pg:qs_pg_placetype":"locality",
    "qs_pg:qs_pg_placetype_gp":"Town",
    "qs_pg:woe_adm0":23424900,
    "woe:adm0_id":23424900,
    "woe:name_adm0":"M\u00e9xico",
    "woe:name_adm1":"Michoacan de Ocampo",
    "woe:placetype":"Town",
    "wof:name":"San Francisco Pichataro",
    "wof:placetype":"locality",
    "wof:population":4749
},
  "geometry": {"coordinates":[-101.80750999999999,19.57335],"type":"Point"}
}