{
  "type": "Feature",
  "properties": {
    "gn:admin1_code":"16.0",
    "gn:asciiname":"La Joya de Magallanes",
    "gn:country_code":"MX",
    "gn:dem":1649,
    "gn:feature_class":"P",
    "gn:feature_code":"PPL",
    "gn:name":"La Joya de Magallanes",
    "gn:population":0,
    "gn:timezone":"America/Mexico_City",
    "iso:country":"MX",
    "name:spa_x_preferred":[
        "La Joya de Magallanes"
    ],
    "name:spa_x_variant":[
        "La Joya"
    ],
    "wof:name":"La Joya de Magallanes",
    "wof:placetype":"locality"
},
  "geometry": {"coordinates":[-102.492,20.04912],"type":"Point"}
}