{
  "type": "Feature",
  "properties": {
    "gn:admin1_code":"16",
    "gn:admin2_code":"101.0",
    "gn:asciiname":"Puerto la Pionia",
    "gn:country_code":"MX",
    "gn:dem":1620,
    "gn:feature_class":"P",
    "gn:feature_code":"PPL",
    "gn:name":"Puerto la Pionia",
    "gn:population":0,
    "gn:timezone":"America/Mexico_City",
    "iso:country":"MX",
    "name:spa_x_preferred":[
        "Puerto la Pionia"
    ],
    "wof:name":"Puerto la Pionia",
    "wof:placetype":"locality"
},
  "geometry": {"coordinates":[-100.79732,19.37036],"type":"Point"}
}