{
  "type": "Feature",
  "properties": {
    "gn:admin1_code":"16",
    "gn:admin2_code":"52.0",
    "gn:asciiname":"Puerto la Piedra",
    "gn:country_code":"MX",
    "gn:dem":426,
    "gn:feature_class":"P",
    "gn:feature_code":"PPL",
    "gn:name":"Puerto la Piedra",
    "gn:population":7,
    "gn:timezone":"America/Mexico_City",
    "iso:country":"MX",
    "wof:name":"Puerto la Piedra",
    "wof:placetype":"locality",
    "wof:population":7
},
  "geometry": {"coordinates":[-102.48139,18.07722],"type":"Point"}
}