{
  "type": "Feature",
  "properties": {
    "gn:admin1_code":"15.0",
    "gn:admin2_code":"123.0",
    "gn:asciiname":"San Juan Acatitlan",
    "gn:country_code":"MX",
    "gn:dem":1093,
    "gn:feature_class":"P",
    "gn:feature_code":"PPL",
    "gn:name":"San Juan Acatitl\u00e1n",
    "gn:population":0,
    "gn:timezone":"America/Mexico_City",
    "iso:country":"MX",
    "name:spa_x_preferred":[
        "San Juan Acatitl\u00e1n"
    ],
    "name:spa_x_variant":[
        "El Grande"
    ],
    "wof:name":"San Juan Acatitlan",
    "wof:placetype":"locality"
},
  "geometry": {"coordinates":[-100.28955000000001,19.00987000000001],"type":"Point"}
}