{
  "type": "Feature",
  "properties": {
    "gn:admin1_code":"10.0",
    "gn:admin2_code":"14.0",
    "gn:asciiname":"El Juego de Hule",
    "gn:country_code":"MX",
    "gn:dem":1315,
    "gn:feature_class":"P",
    "gn:feature_code":"PPL",
    "gn:name":"El Juego de Hule",
    "gn:population":0,
    "gn:timezone":"America/Mazatlan",
    "iso:country":"MX",
    "name:spa_x_preferred":[
        "El Juego de Hule"
    ],
    "wof:name":"El Juego de Hule",
    "wof:placetype":"locality"
},
  "geometry": {"coordinates":[-104.58696,22.44201],"type":"Point"}
}