{
  "type": "Feature",
  "properties": {
    "gn:admin1_code":"30",
    "gn:admin2_code":"144.0",
    "gn:asciiname":"General Miguel Aleman",
    "gn:country_code":"MX",
    "gn:dem":51,
    "gn:feature_class":"P",
    "gn:feature_code":"PPL",
    "gn:name":"General Miguel Alem\u00e1n",
    "gn:population":117,
    "gn:timezone":"America/Mexico_City",
    "iso:country":"MX",
    "wof:name":"General Miguel Aleman",
    "wof:placetype":"locality",
    "wof:population":117
},
  "geometry": {"coordinates":[-94.95556000000001,17.76],"type":"Point"}
}