{
  "type": "Feature",
  "properties": {
    "gn:admin1_code":"26.0",
    "gn:admin2_code":"6.0",
    "gn:asciiname":"La Cueva",
    "gn:country_code":"MX",
    "gn:dem":1316,
    "gn:feature_class":"P",
    "gn:feature_code":"PPL",
    "gn:name":"La Cueva",
    "gn:population":0,
    "gn:timezone":"America/Hermosillo",
    "iso:country":"MX",
    "name:spa_x_preferred":[
        "La Cueva"
    ],
    "wof:name":"La Cueva",
    "wof:placetype":"locality"
},
  "geometry": {"coordinates":[-110.40116999999999,30.70604],"type":"Point"}
}