{
  "type": "Feature",
  "properties": {
    "gn:admin1_code":"25",
    "gn:admin2_code":"11.0",
    "gn:asciiname":"Las Quemazones",
    "gn:country_code":"MX",
    "gn:dem":36,
    "gn:feature_class":"P",
    "gn:feature_code":"PPL",
    "gn:name":"Las Quemazones",
    "gn:population":1319,
    "gn:timezone":"America/Mazatlan",
    "iso:country":"MX",
    "name:spa_x_preferred":[
        "Las Quemazones"
    ],
    "wof:name":"Las Quemazones",
    "wof:placetype":"locality",
    "wof:population":1319
},
  "geometry": {"coordinates":[-108.45243000000001,25.68583],"type":"Point"}
}