{
  "type": "Feature",
  "properties": {
    "gn:admin1_code":"18",
    "gn:admin2_code":"11",
    "gn:asciiname":"La Frontera",
    "gn:country_code":"MX",
    "gn:dem":19,
    "gn:feature_class":"P",
    "gn:feature_code":"PPL",
    "gn:name":"La Frontera",
    "gn:population":12,
    "gn:timezone":"America/Mazatlan",
    "iso:country":"MX",
    "wof:name":"La Frontera",
    "wof:placetype":"locality",
    "wof:population":12
},
  "geometry": {"coordinates":[-105.22139,21.95083],"type":"Point"}
}