{
  "type": "Feature",
  "properties": {
    "gn:admin1_code":"18",
    "gn:admin2_code":"11",
    "gn:asciiname":"La Frontera",
    "gn:country_code":"MX",
    "gn:dem":19,
    "gn:feature_class":"P",
    "gn:feature_code":"PPL",
    "gn:name":"La Frontera",
    "gn:population":12,
    "gn:timezone":"America/Mazatlan",
    "iso:country":"MX",
    "name:cat_x_preferred":[
        "La Frontera"
    ],
    "name:ceb_x_preferred":[
        "La Frontera"
    ],
    "name:deu_x_preferred":[
        "La Frontera"
    ],
    "name:eus_x_preferred":[
        "La Frontera"
    ],
    "name:fra_x_preferred":[
        "La Frontera"
    ],
    "name:glg_x_preferred":[
        "La Frontera"
    ],
    "name:hun_x_preferred":[
        "La Frontera"
    ],
    "name:ita_x_preferred":[
        "La Frontera"
    ],
    "name:msa_x_preferred":[
        "La Frontera"
    ],
    "name:nld_x_preferred":[
        "La Frontera"
    ],
    "name:oci_x_preferred":[
        "La Frontera"
    ],
    "name:pol_x_preferred":[
        "La Frontera"
    ],
    "name:por_x_preferred":[
        "La Frontera"
    ],
    "name:spa_x_preferred":[
        "La Frontera"
    ],
    "name:srp_x_preferred":[
        "\u041b\u0430 \u0424\u0440\u043e\u043d\u0442\u0435\u0440\u0430"
    ],
    "name:swe_x_preferred":[
        "La Frontera"
    ],
    "name:uzb_x_preferred":[
        "La Frontera"
    ],
    "name:vie_x_preferred":[
        "La Frontera"
    ],
    "name:war_x_preferred":[
        "La Frontera"
    ],
    "wof:name":"La Frontera",
    "wof:placetype":"locality",
    "wof:population":12
},
  "geometry": {"coordinates":[-105.22139,21.95083],"type":"Point"}
}