{
  "type": "Feature",
  "properties": {
    "gn:admin1_code":"6",
    "gn:admin2_code":"27.0",
    "gn:asciiname":"Muracharachi",
    "gn:country_code":"MX",
    "gn:dem":2113,
    "gn:feature_class":"P",
    "gn:feature_code":"PPL",
    "gn:name":"Muracharachi",
    "gn:population":113,
    "gn:timezone":"America/Chihuahua",
    "iso:country":"MX",
    "wof:name":"Muracharachi",
    "wof:placetype":"locality",
    "wof:population":113
},
  "geometry": {"coordinates":[-106.9949,27.2866],"type":"Point"}
}