{
  "type": "Feature",
  "properties": {
    "gn:admin1_code":"13",
    "gn:asciiname":"Las Pampas",
    "gn:country_code":"MX",
    "gn:dem":67,
    "gn:feature_class":"P",
    "gn:feature_code":"PPL",
    "gn:name":"Las Pampas",
    "gn:population":0,
    "gn:timezone":"America/Mexico_City",
    "iso:country":"MX",
    "name:spa_x_preferred":[
        "Las Pampas"
    ],
    "wof:name":"Las Pampas",
    "wof:placetype":"locality"
},
  "geometry": {"coordinates":[-98.50103,21.39801],"type":"Point"}
}