{
  "type": "Feature",
  "properties": {
    "gn:admin1_code":"18",
    "gn:admin2_code":"14.0",
    "gn:asciiname":"Los Jazmines",
    "gn:country_code":"MX",
    "gn:dem":1237,
    "gn:feature_class":"P",
    "gn:feature_code":"PPL",
    "gn:name":"Los Jazmines",
    "gn:population":0,
    "gn:timezone":"America/Mazatlan",
    "iso:country":"MX",
    "name:und_x_variant":[
        "Jazmines",
        "Los Jazmines"
    ],
    "wof:name":"Los Jazmines",
    "wof:placetype":"locality"
},
  "geometry": {"coordinates":[-104.64534999999999,21.25518],"type":"Point"}
}