{
  "type": "Feature",
  "properties": {
    "gn:admin1_code":"10.0",
    "gn:admin2_code":"5.0",
    "gn:asciiname":"El Maguey",
    "gn:country_code":"MX",
    "gn:dem":1865,
    "gn:feature_class":"P",
    "gn:feature_code":"PPL",
    "gn:name":"El Maguey",
    "gn:population":0,
    "gn:timezone":"America/Monterrey",
    "iso:country":"MX",
    "name:spa_x_preferred":[
        "El Maguey"
    ],
    "wof:name":"El Maguey",
    "wof:placetype":"locality"
},
  "geometry": {"coordinates":[-104.57201999999999,24.08479],"type":"Point"}
}