{
  "type": "Feature",
  "properties": {
    "gn:admin1_code":"1",
    "gn:admin2_code":"7.0",
    "gn:asciiname":"Granja Andalucia",
    "gn:country_code":"MX",
    "gn:dem":1903,
    "gn:feature_class":"P",
    "gn:feature_code":"PPL",
    "gn:name":"Granja Andaluc\u00eda",
    "gn:population":4,
    "gn:timezone":"America/Mexico_City",
    "iso:country":"MX",
    "name:und_x_variant":[
        "Granja Andaluc\u00eda"
    ],
    "wof:name":"Granja Andalucia",
    "wof:placetype":"locality",
    "wof:population":4
},
  "geometry": {"coordinates":[-102.31528,22.14361],"type":"Point"}
}