{
  "type": "Feature",
  "properties": {
    "gn:admin1_code":"30.0",
    "gn:admin2_code":"109.0",
    "gn:asciiname":"Troncones",
    "gn:country_code":"MX",
    "gn:dem":18,
    "gn:feature_class":"P",
    "gn:feature_code":"PPL",
    "gn:name":"Troncones",
    "gn:population":372,
    "gn:timezone":"America/Mexico_City",
    "iso:country":"MX",
    "name:spa_x_preferred":[
        "Troncones"
    ],
    "name:zho_x_preferred":[
        "\u7279\u9f99\u79d1\u5185\u65af"
    ],
    "wof:name":"Troncones",
    "wof:placetype":"locality",
    "wof:population":372
},
  "geometry": {"coordinates":[-96.90732,20.12098],"type":"Point"}
}