{
  "type": "Feature",
  "properties": {
    "gn:admin1_code":"6",
    "gn:admin2_code":"7",
    "gn:asciiname":"Boquirare",
    "gn:country_code":"MX",
    "gn:dem":2452,
    "gn:feature_class":"P",
    "gn:feature_code":"PPL",
    "gn:name":"Boqu\u00edrare",
    "gn:population":27,
    "gn:timezone":"America/Chihuahua",
    "iso:country":"MX",
    "name:und_x_variant":[
        "Boqu\u00edrare"
    ],
    "wof:name":"Boquirare",
    "wof:placetype":"locality",
    "wof:population":27
},
  "geometry": {"coordinates":[-106.66611,26.6575],"type":"Point"}
}