{
  "type": "Feature",
  "properties": {
    "gn:admin1_code":"21",
    "gn:admin2_code":"77.0",
    "gn:asciiname":"Teskgau",
    "gn:country_code":"MX",
    "gn:dem":645,
    "gn:feature_class":"P",
    "gn:feature_code":"PPL",
    "gn:name":"Teskgau",
    "gn:population":89,
    "gn:timezone":"America/Mexico_City",
    "iso:country":"MX",
    "wof:name":"Teskgau",
    "wof:placetype":"locality",
    "wof:population":89
},
  "geometry": {"coordinates":[-97.66773000000001,20.05285],"type":"Point"}
}