{
  "type": "Feature",
  "properties": {
    "gn:admin1_code":"30",
    "gn:admin2_code":"208.0",
    "gn:asciiname":"La Barranca",
    "gn:country_code":"MX",
    "gn:dem":11,
    "gn:feature_class":"P",
    "gn:feature_code":"PPL",
    "gn:name":"La Barranca",
    "gn:population":0,
    "gn:timezone":"America/Mexico_City",
    "iso:country":"MX",
    "name:spa_x_preferred":[
        "La Barranca"
    ],
    "name:und_x_variant":[
        "Paso Barranca"
    ],
    "wof:name":"La Barranca",
    "wof:placetype":"locality"
},
  "geometry": {"coordinates":[-95.75438,18.32274],"type":"Point"}
}