{
  "type": "Feature",
  "properties": {
    "gn:admin1_code":"18.0",
    "gn:admin2_code":"10.0",
    "gn:asciiname":"Rosarito",
    "gn:country_code":"MX",
    "gn:dem":412,
    "gn:feature_class":"P",
    "gn:feature_code":"PPL",
    "gn:name":"Rosarito",
    "gn:population":287,
    "gn:timezone":"America/Mazatlan",
    "iso:country":"MX",
    "wof:name":"Rosarito",
    "wof:placetype":"locality",
    "wof:population":287
},
  "geometry": {"coordinates":[-105.00494,22.1674],"type":"Point"}
}