{
  "type": "Feature",
  "properties": {
    "gn:admin1_code":"30",
    "gn:admin2_code":"77.0",
    "gn:asciiname":"El Maguial (La Laguna)",
    "gn:country_code":"MX",
    "gn:dem":83,
    "gn:feature_class":"P",
    "gn:feature_code":"PPL",
    "gn:name":"El Maguial (La Laguna)",
    "gn:population":200,
    "gn:timezone":"America/Mexico_City",
    "iso:country":"MX",
    "wof:name":"El Maguial (La Laguna)",
    "wof:placetype":"locality",
    "wof:population":200
},
  "geometry": {"coordinates":[-95.46778,17.93277999999999],"type":"Point"}
}