{
  "type": "Feature",
  "properties": {
    "gn:admin1_code":"28",
    "gn:admin2_code":"40.0",
    "gn:asciiname":"Dieciocho De Marzo",
    "gn:country_code":"MX",
    "gn:dem":18,
    "gn:feature_class":"P",
    "gn:feature_code":"PPL",
    "gn:name":"Dieciocho De Marzo",
    "gn:population":0,
    "gn:timezone":"America/Monterrey",
    "iso:country":"MX",
    "name:spa_x_preferred":[
        "Dieciocho De Marzo"
    ],
    "wof:name":"Dieciocho De Marzo",
    "wof:placetype":"locality"
},
  "geometry": {"coordinates":[-97.91473999999999,25.66256],"type":"Point"}
}