{
  "type": "Feature",
  "properties": {
    "gn:admin1_code":"14",
    "gn:admin2_code":"20.0",
    "gn:asciiname":"Peregrina de Gomez (La Boquita)",
    "gn:country_code":"MX",
    "gn:dem":23,
    "gn:feature_class":"P",
    "gn:feature_code":"PPL",
    "gn:name":"Peregrina de G\u00f3mez (La Boquita)",
    "gn:population":46,
    "gn:timezone":"America/Mexico_City",
    "iso:country":"MX",
    "name:und_x_variant":[
        "La Boquita",
        "Peregrina"
    ],
    "wof:name":"Peregrina de Gomez (La Boquita)",
    "wof:placetype":"locality",
    "wof:population":46
},
  "geometry": {"coordinates":[-105.53722999999999,20.18795],"type":"Point"}
}