{
  "type": "Feature",
  "properties": {
    "gn:admin1_code":"32",
    "gn:admin2_code":"17.0",
    "gn:asciiname":"El Pedregal (El Mirador)",
    "gn:country_code":"MX",
    "gn:dem":2331,
    "gn:feature_class":"P",
    "gn:feature_code":"PPL",
    "gn:name":"El Pedregal (El Mirador)",
    "gn:population":6,
    "gn:timezone":"America/Mexico_City",
    "iso:country":"MX",
    "wof:name":"El Pedregal (El Mirador)",
    "wof:placetype":"locality",
    "wof:population":6
},
  "geometry": {"coordinates":[-102.52916999999999,22.72278],"type":"Point"}
}