{
  "type": "Feature",
  "properties": {
    "gn:admin1_code":"6",
    "gn:admin2_code":"8.0",
    "gn:asciiname":"Pedregal de Abajo",
    "gn:country_code":"MX",
    "gn:dem":888,
    "gn:feature_class":"P",
    "gn:feature_code":"PPL",
    "gn:name":"Pedregal de Abajo",
    "gn:population":61,
    "gn:timezone":"America/Chihuahua",
    "iso:country":"MX",
    "wof:name":"Pedregal de Abajo",
    "wof:placetype":"locality",
    "wof:population":61
},
  "geometry": {"coordinates":[-107.67795,26.92938],"type":"Point"}
}