{
  "type": "Feature",
  "properties": {
    "gn:admin1_code":"32",
    "gn:admin2_code":"37.0",
    "gn:asciiname":"Huilanchita",
    "gn:country_code":"MX",
    "gn:dem":2043,
    "gn:feature_class":"P",
    "gn:feature_code":"PPL",
    "gn:name":"Huilanchita",
    "gn:population":0,
    "gn:timezone":"America/Mexico_City",
    "iso:country":"MX",
    "name:spa_x_preferred":[
        "Huilanchita"
    ],
    "wof:name":"Huilanchita",
    "wof:placetype":"locality"
},
  "geometry": {"coordinates":[-102.39608,22.97565],"type":"Point"}
}