{
  "type": "Feature",
  "properties": {
    "gn:admin1_code":"30",
    "gn:admin2_code":"175.0",
    "gn:asciiname":"El Reparo",
    "gn:country_code":"MX",
    "gn:dem":92,
    "gn:feature_class":"P",
    "gn:feature_code":"PPL",
    "gn:name":"El Reparo",
    "gn:population":5,
    "gn:timezone":"America/Mexico_City",
    "iso:country":"MX",
    "wof:name":"El Reparo",
    "wof:placetype":"locality",
    "wof:population":5
},
  "geometry": {"coordinates":[-97.52222,20.69389],"type":"Point"}
}