{
  "type": "Feature",
  "properties": {
    "gn:admin1_code":"26",
    "gn:admin2_code":"20.0",
    "gn:asciiname":"Cerro Napa [Ganaderia]",
    "gn:country_code":"MX",
    "gn:dem":389,
    "gn:feature_class":"P",
    "gn:feature_code":"PPL",
    "gn:name":"Cerro Napa [Ganader\u00eda]",
    "gn:population":7,
    "gn:timezone":"America/Hermosillo",
    "iso:country":"MX",
    "name:und_x_variant":[
        "Cerro Napa [Ganader\u00eda]"
    ],
    "wof:name":"Cerro Napa [Ganaderia]",
    "wof:placetype":"locality",
    "wof:population":7
},
  "geometry": {"coordinates":[-110.92917,29.5325],"type":"Point"}
}