{
  "type": "Feature",
  "properties": {
    "gn:admin1_code":"5.0",
    "gn:admin2_code":"52.0",
    "gn:asciiname":"Mariscal",
    "gn:country_code":"MX",
    "gn:dem":1271,
    "gn:feature_class":"P",
    "gn:feature_code":"PPL",
    "gn:name":"Mariscal",
    "gn:population":0,
    "gn:timezone":"America/Mexico_City",
    "iso:country":"MX",
    "name:spa_x_preferred":[
        "Mariscal"
    ],
    "wof:name":"Mariscal",
    "wof:placetype":"locality"
},
  "geometry": {"coordinates":[-91.77199,16.29556],"type":"Point"}
}