{
  "type": "Feature",
  "properties": {
    "gn:admin1_code":"17",
    "gn:asciiname":"Puxtla",
    "gn:country_code":"MX",
    "gn:dem":2273,
    "gn:feature_class":"P",
    "gn:feature_code":"PPL",
    "gn:name":"Puxtla",
    "gn:population":0,
    "gn:timezone":"America/Mexico_City",
    "iso:country":"MX",
    "name:spa_x_preferred":[
        "Puxtla"
    ],
    "wof:name":"Puxtla",
    "wof:placetype":"locality"
},
  "geometry": {"coordinates":[-98.87831,19.67749],"type":"Point"}
}