{
  "type": "Feature",
  "properties": {
    "gn:admin1_code":"14.0",
    "gn:admin2_code":"86.0",
    "gn:asciiname":"Crucero de la Yerbabuena",
    "gn:country_code":"MX",
    "gn:dem":1953,
    "gn:feature_class":"P",
    "gn:feature_code":"PPL",
    "gn:name":"Crucero de la Yerbabuena",
    "gn:population":0,
    "gn:timezone":"America/Mexico_City",
    "iso:country":"MX",
    "name:spa_x_preferred":[
        "Crucero de la Yerbabuena"
    ],
    "wof:name":"Crucero de la Yerbabuena",
    "wof:placetype":"locality"
},
  "geometry": {"coordinates":[-103.80274,19.85951],"type":"Point"}
}