{
  "type": "Feature",
  "properties": {
    "gn:admin1_code":"31",
    "gn:admin2_code":"57.0",
    "gn:asciiname":"San Roman",
    "gn:country_code":"MX",
    "gn:dem":17,
    "gn:feature_class":"P",
    "gn:feature_code":"PPL",
    "gn:name":"San Rom\u00e1n",
    "gn:population":0,
    "gn:timezone":"America/Merida",
    "iso:country":"MX",
    "name:spa_x_preferred":[
        "San Rom\u00e1n"
    ],
    "wof:name":"San Roman",
    "wof:placetype":"locality"
},
  "geometry": {"coordinates":[-88.20069000000002,21.29724],"type":"Point"}
}