{
  "type": "Feature",
  "properties": {
    "gn:admin1_code":"5",
    "gn:admin2_code":"107.0",
    "gn:asciiname":"Arroyo del Sauz",
    "gn:country_code":"MX",
    "gn:dem":971,
    "gn:feature_class":"P",
    "gn:feature_code":"PPL",
    "gn:name":"Arroyo del Sauz",
    "gn:population":7,
    "gn:timezone":"America/Mexico_City",
    "iso:country":"MX",
    "wof:name":"Arroyo del Sauz",
    "wof:placetype":"locality",
    "wof:population":7
},
  "geometry": {"coordinates":[-93.37139000000001,16.08861],"type":"Point"}
}