{
  "type": "Feature",
  "properties": {
    "gn:admin1_code":"11",
    "gn:admin2_code":"3.0",
    "gn:asciiname":"Vivienda de Abajo Urbana",
    "gn:country_code":"MX",
    "gn:dem":1862,
    "gn:feature_class":"P",
    "gn:feature_code":"PPL",
    "gn:name":"Vivienda de Abajo Urbana",
    "gn:population":317,
    "gn:timezone":"America/Mexico_City",
    "iso:country":"MX",
    "wof:name":"Vivienda de Abajo Urbana",
    "wof:placetype":"locality",
    "wof:population":317
},
  "geometry": {"coordinates":[-100.80944,20.93528],"type":"Point"}
}