{
  "type": "Feature",
  "properties": {
    "gn:admin1_code":"26.0",
    "gn:admin2_code":"4.0",
    "gn:asciiname":"Ejido Dieciseis de Septiembre",
    "gn:country_code":"MX",
    "gn:dem":382,
    "gn:feature_class":"P",
    "gn:feature_code":"PPL",
    "gn:name":"Ejido Diecis\u00e9is de Septiembre",
    "gn:population":0,
    "gn:timezone":"America/Hermosillo",
    "iso:country":"MX",
    "name:spa_x_preferred":[
        "Ejido Diecis\u00e9is de Septiembre"
    ],
    "wof:name":"Ejido Dieciseis de Septiembre",
    "wof:placetype":"locality"
},
  "geometry": {"coordinates":[-111.9194,30.7059],"type":"Point"}
}