{
  "type": "Feature",
  "properties": {
    "gn:admin1_code":"28.0",
    "gn:admin2_code":"21.0",
    "gn:asciiname":"La Casa Blanca",
    "gn:country_code":"MX",
    "gn:dem":111,
    "gn:feature_class":"P",
    "gn:feature_code":"PPL",
    "gn:name":"La Casa Blanca",
    "gn:population":0,
    "gn:timezone":"America/Monterrey",
    "iso:country":"MX",
    "name:spa_x_preferred":[
        "La Casa Blanca"
    ],
    "wof:name":"La Casa Blanca",
    "wof:placetype":"locality"
},
  "geometry": {"coordinates":[-98.98806,22.66528],"type":"Point"}
}