{
  "type": "Feature",
  "properties": {
    "gn:admin1_code":"17",
    "gn:admin2_code":"24",
    "gn:asciiname":"Fraccionamiento Bonanza (Condominios Pontevedra)",
    "gn:country_code":"MX",
    "gn:dem":1118,
    "gn:feature_class":"P",
    "gn:feature_code":"PPL",
    "gn:name":"Fraccionamiento Bonanza (Condominios Pontevedra)",
    "gn:population":22,
    "gn:timezone":"America/Mexico_City",
    "iso:country":"MX",
    "wof:name":"Fraccionamiento Bonanza (Condominios Pontevedra)",
    "wof:placetype":"locality",
    "wof:population":22
},
  "geometry": {"coordinates":[-99.19028,18.74028],"type":"Point"}
}