{
  "type": "Feature",
  "properties": {
    "gn:admin1_code":"14",
    "gn:admin2_code":"48",
    "gn:asciiname":"El Tepetate",
    "gn:country_code":"MX",
    "gn:dem":2015,
    "gn:feature_class":"P",
    "gn:feature_code":"PPL",
    "gn:name":"El Tepetate",
    "gn:population":45,
    "gn:timezone":"America/Mexico_City",
    "iso:country":"MX",
    "wof:name":"El Tepetate",
    "wof:placetype":"locality",
    "wof:population":45
},
  "geometry": {"coordinates":[-102.03583,20.56667],"type":"Point"}
}