{
  "type": "Feature",
  "properties": {
    "gn:admin1_code":"16",
    "gn:admin2_code":"112.0",
    "gn:asciiname":"Las Majadas (Rancho de Guadalupe)",
    "gn:country_code":"MX",
    "gn:dem":1428,
    "gn:feature_class":"P",
    "gn:feature_code":"PPL",
    "gn:name":"Las Majadas (Rancho de Guadalupe)",
    "gn:population":410,
    "gn:timezone":"America/Mexico_City",
    "iso:country":"MX",
    "wof:name":"Las Majadas (Rancho de Guadalupe)",
    "wof:placetype":"locality",
    "wof:population":410
},
  "geometry": {"coordinates":[-100.46917000000001,19.37972],"type":"Point"}
}