{
  "type": "Feature",
  "properties": {
    "gn:admin1_code":"5",
    "gn:admin2_code":"61.0",
    "gn:asciiname":"La Union",
    "gn:country_code":"MX",
    "gn:dem":841,
    "gn:feature_class":"P",
    "gn:feature_code":"PPL",
    "gn:name":"La Uni\u00f3n",
    "gn:population":0,
    "gn:timezone":"America/Mexico_City",
    "iso:country":"MX",
    "wof:name":"La Union",
    "wof:placetype":"locality"
},
  "geometry": {"coordinates":[-93.42592999999999,16.68843],"type":"Point"}
}