{
  "type": "Feature",
  "properties": {
    "gn:admin1_code":"28",
    "gn:admin2_code":"19.0",
    "gn:asciiname":"Ampliacion Huerta Estela",
    "gn:country_code":"MX",
    "gn:dem":216,
    "gn:feature_class":"P",
    "gn:feature_code":"PPL",
    "gn:name":"Ampliaci\u00f3n Huerta Estela",
    "gn:population":9,
    "gn:timezone":"America/Monterrey",
    "iso:country":"MX",
    "name:und_x_variant":[
        "Ampliaci\u00f3n Huerta Estela"
    ],
    "wof:name":"Ampliacion Huerta Estela",
    "wof:placetype":"locality",
    "wof:population":9
},
  "geometry": {"coordinates":[-98.88861,23.27889],"type":"Point"}
}