{
  "type": "Feature",
  "properties": {
    "gn:admin1_code":"7.0",
    "gn:admin2_code":"20.0",
    "gn:asciiname":"Las Granjas",
    "gn:country_code":"MX",
    "gn:dem":442,
    "gn:feature_class":"P",
    "gn:feature_code":"PPL",
    "gn:name":"Las Granjas",
    "gn:population":0,
    "gn:timezone":"America/Monterrey",
    "iso:country":"MX",
    "name:spa_x_preferred":[
        "Las Granjas"
    ],
    "wof:name":"Las Granjas",
    "wof:placetype":"locality"
},
  "geometry": {"coordinates":[-101.50843,27.93554],"type":"Point"}
}