{
  "type": "Feature",
  "properties": {
    "gn:admin1_code":"25",
    "gn:admin2_code":"10.0",
    "gn:asciiname":"Producto de la Revolucion",
    "gn:country_code":"MX",
    "gn:dem":38,
    "gn:feature_class":"P",
    "gn:feature_code":"PPL",
    "gn:name":"Producto de la Revoluci\u00f3n",
    "gn:population":401,
    "gn:timezone":"America/Mazatlan",
    "iso:country":"MX",
    "name:und_x_variant":[
        "Producto de la Revoluci\u00f3n"
    ],
    "wof:name":"Producto de la Revolucion",
    "wof:placetype":"locality",
    "wof:population":401
},
  "geometry": {"coordinates":[-108.78082999999999,25.92583],"type":"Point"}
}