{
  "type": "Feature",
  "properties": {
    "gn:admin1_code":"24",
    "gn:admin2_code":"6",
    "gn:asciiname":"Los Azules",
    "gn:country_code":"MX",
    "gn:dem":2066,
    "gn:feature_class":"P",
    "gn:feature_code":"PPL",
    "gn:name":"Los Azules",
    "gn:population":25,
    "gn:timezone":"America/Mexico_City",
    "iso:country":"MX",
    "wof:name":"Los Azules",
    "wof:placetype":"locality",
    "wof:population":25
},
  "geometry": {"coordinates":[-101.16583,23.77611],"type":"Point"}
}