{
  "type": "Feature",
  "properties": {
    "gn:admin1_code":"12",
    "gn:admin2_code":"30.0",
    "gn:asciiname":"Cuatro Bancos",
    "gn:country_code":"MX",
    "gn:dem":12,
    "gn:feature_class":"P",
    "gn:feature_code":"PPL",
    "gn:name":"Cuatro Bancos",
    "gn:population":734,
    "gn:timezone":"America/Mexico_City",
    "iso:country":"MX",
    "name:spa_x_preferred":[
        "Cuatro Bancos"
    ],
    "wof:name":"Cuatro Bancos",
    "wof:placetype":"locality",
    "wof:population":734
},
  "geometry": {"coordinates":[-99.17764,16.67641],"type":"Point"}
}