{
  "type": "Feature",
  "properties": {
    "gn:admin1_code":"12",
    "gn:admin2_code":"58.0",
    "gn:asciiname":"Los Coajiotes",
    "gn:country_code":"MX",
    "gn:dem":803,
    "gn:feature_class":"P",
    "gn:feature_code":"PPL",
    "gn:name":"Los Coajiotes",
    "gn:population":71,
    "gn:timezone":"America/Mexico_City",
    "iso:country":"MX",
    "wof:name":"Los Coajiotes",
    "wof:placetype":"locality",
    "wof:population":71
},
  "geometry": {"coordinates":[-99.66783,18.34916],"type":"Point"}
}