{
  "type": "Feature",
  "properties": {
    "gn:admin1_code":"31",
    "gn:admin2_code":"35.0",
    "gn:asciiname":"Xi-itz",
    "gn:country_code":"MX",
    "gn:dem":13,
    "gn:feature_class":"P",
    "gn:feature_code":"PPL",
    "gn:name":"Xi-itz",
    "gn:population":0,
    "gn:timezone":"America/Merida",
    "iso:country":"MX",
    "name:spa_x_preferred":[
        "Xi-itz"
    ],
    "wof:name":"Xi-itz",
    "wof:placetype":"locality"
},
  "geometry": {"coordinates":[-89.20902,20.93691],"type":"Point"}
}