{
  "type": "Feature",
  "properties": {
    "gn:admin1_code":"14",
    "gn:admin2_code":"61.0",
    "gn:asciiname":"Temohaya",
    "gn:country_code":"MX",
    "gn:dem":1215,
    "gn:feature_class":"P",
    "gn:feature_code":"PPL",
    "gn:name":"Temohaya",
    "gn:population":0,
    "gn:timezone":"America/Mexico_City",
    "iso:country":"MX",
    "name:spa_x_preferred":[
        "Temohaya"
    ],
    "wof:name":"Temohaya",
    "wof:placetype":"locality"
},
  "geometry": {"coordinates":[-103.72693,22.22759],"type":"Point"}
}