{
  "type": "Feature",
  "properties": {
    "gn:admin1_code":"14.0",
    "gn:admin2_code":"59.0",
    "gn:asciiname":"La Ruana",
    "gn:country_code":"MX",
    "gn:dem":1514,
    "gn:feature_class":"P",
    "gn:feature_code":"PPL",
    "gn:name":"La Ruana",
    "gn:population":0,
    "gn:timezone":"America/Mexico_City",
    "iso:country":"MX",
    "name:spa_x_preferred":[
        "La Ruana"
    ],
    "wof:name":"La Ruana",
    "wof:placetype":"locality"
},
  "geometry": {"coordinates":[-103.0424,19.81896],"type":"Point"}
}