{
  "type": "Feature",
  "properties": {
    "gn:admin1_code":"27",
    "gn:admin2_code":"4.0",
    "gn:asciiname":"Barrancas y Amate 3ra. Seccion",
    "gn:country_code":"MX",
    "gn:dem":19,
    "gn:feature_class":"P",
    "gn:feature_code":"PPL",
    "gn:name":"Barrancas y Amate 3ra. Secci\u00f3n",
    "gn:population":1095,
    "gn:timezone":"America/Mexico_City",
    "iso:country":"MX",
    "name:und_x_variant":[
        "Barrancas y Amate 3ra. Secci\u00f3n"
    ],
    "wof:name":"Barrancas y Amate 3ra. Seccion",
    "wof:placetype":"locality",
    "wof:population":1095
},
  "geometry": {"coordinates":[-92.76173,17.971],"type":"Point"}
}