{
  "type": "Feature",
  "properties": {
    "gn:admin1_code":"31",
    "gn:admin2_code":"57.0",
    "gn:asciiname":"Santiaguito",
    "gn:country_code":"MX",
    "gn:dem":6,
    "gn:feature_class":"P",
    "gn:feature_code":"PPL",
    "gn:name":"Santiaguito",
    "gn:population":0,
    "gn:timezone":"America/Merida",
    "iso:country":"MX",
    "name:spa_x_preferred":[
        "Santiaguito"
    ],
    "wof:name":"Santiaguito",
    "wof:placetype":"locality"
},
  "geometry": {"coordinates":[-88.44416,21.37628],"type":"Point"}
}