{
  "type": "Feature",
  "properties": {
    "gn:admin1_code":"30",
    "gn:admin2_code":"77.0",
    "gn:asciiname":"Ruperto Perez Arizmendi",
    "gn:country_code":"MX",
    "gn:dem":22,
    "gn:feature_class":"P",
    "gn:feature_code":"PPL",
    "gn:name":"Ruperto P\u00e9rez Arizmendi",
    "gn:population":5,
    "gn:timezone":"America/Mexico_City",
    "iso:country":"MX",
    "name:und_x_variant":[
        "Ruperto P\u00e9rez Arizmendi"
    ],
    "wof:name":"Ruperto Perez Arizmendi",
    "wof:placetype":"locality",
    "wof:population":5
},
  "geometry": {"coordinates":[-95.47221999999999,18.22917],"type":"Point"}
}