{
  "type": "Feature",
  "properties": {
    "gn:admin1_code":"26",
    "gn:admin2_code":"51.0",
    "gn:asciiname":"Pena",
    "gn:country_code":"MX",
    "gn:dem":432,
    "gn:feature_class":"P",
    "gn:feature_code":"PPL",
    "gn:name":"Pe\u00f1a",
    "gn:population":0,
    "gn:timezone":"America/Hermosillo",
    "iso:country":"MX",
    "name:ast_x_preferred":[
        "Pena"
    ],
    "name:cat_x_preferred":[
        "Pena"
    ],
    "name:ceb_x_preferred":[
        "Pena"
    ],
    "name:ces_x_preferred":[
        "Pena"
    ],
    "name:che_x_preferred":[
        "\u042f\u0437\u043e\u043b\u0433"
    ],
    "name:deu_x_preferred":[
        "Pena"
    ],
    "name:fin_x_preferred":[
        "Pena"
    ],
    "name:fra_x_preferred":[
        "Pena"
    ],
    "name:glg_x_preferred":[
        "Pena"
    ],
    "name:ita_x_preferred":[
        "Pena"
    ],
    "name:nld_x_preferred":[
        "Pena"
    ],
    "name:por_x_preferred":[
        "Pena"
    ],
    "name:rus_x_preferred":[
        "\u041f\u0435\u043d\u0430"
    ],
    "name:slk_x_preferred":[
        "Pena"
    ],
    "name:spa_x_preferred":[
        "Pena"
    ],
    "name:srp_x_preferred":[
        "\u041f\u0435\u043d\u0430"
    ],
    "name:swe_x_preferred":[
        "Pena"
    ],
    "name:ukr_x_preferred":[
        "\u041f\u0435\u043d\u0430"
    ],
    "wof:name":"Pena",
    "wof:placetype":"locality"
},
  "geometry": {"coordinates":[-109.46666999999999,28.28333],"type":"Point"}
}