{
  "type": "Feature",
  "properties": {
    "gn:admin1_code":"4",
    "gn:admin2_code":"11.0",
    "gn:asciiname":"El Herradero",
    "gn:country_code":"MX",
    "gn:dem":48,
    "gn:feature_class":"P",
    "gn:feature_code":"PPL",
    "gn:name":"El Herradero",
    "gn:population":4,
    "gn:timezone":"America/Merida",
    "iso:country":"MX",
    "wof:name":"El Herradero",
    "wof:placetype":"locality",
    "wof:population":4
},
  "geometry": {"coordinates":[-91.03,18.18667],"type":"Point"}
}