{
  "type": "Feature",
  "properties": {
    "gn:admin1_code":"18.0",
    "gn:admin2_code":"5.0",
    "gn:asciiname":"El Lunarcito",
    "gn:country_code":"MX",
    "gn:dem":76,
    "gn:feature_class":"P",
    "gn:feature_code":"PPL",
    "gn:name":"El Lunarcito",
    "gn:population":16,
    "gn:timezone":"America/Mazatlan",
    "iso:country":"MX",
    "wof:name":"El Lunarcito",
    "wof:placetype":"locality",
    "wof:population":16
},
  "geometry": {"coordinates":[-105.36556000000002,22.64611],"type":"Point"}
}