{
  "type": "Feature",
  "properties": {
    "gn:admin1_code":"5",
    "gn:admin2_code":"55.0",
    "gn:asciiname":"Los Hules",
    "gn:country_code":"MX",
    "gn:dem":136,
    "gn:feature_class":"P",
    "gn:feature_code":"PPL",
    "gn:name":"Los Hules",
    "gn:population":503,
    "gn:timezone":"America/Mexico_City",
    "iso:country":"MX",
    "wof:name":"Los Hules",
    "wof:placetype":"locality",
    "wof:population":503
},
  "geometry": {"coordinates":[-92.19082,14.85008],"type":"Point"}
}