{
  "type": "Feature",
  "properties": {
    "gn:admin1_code":"26.0",
    "gn:admin2_code":"3.0",
    "gn:asciiname":"Jacalitos",
    "gn:country_code":"MX",
    "gn:dem":321,
    "gn:feature_class":"P",
    "gn:feature_code":"PPL",
    "gn:name":"Jacalitos",
    "gn:population":0,
    "gn:timezone":"America/Hermosillo",
    "iso:country":"MX",
    "name:spa_x_preferred":[
        "Jacalitos"
    ],
    "name:und_x_variant":[
        "Jacalito"
    ],
    "wof:name":"Jacalitos",
    "wof:placetype":"locality"
},
  "geometry": {"coordinates":[-108.72007000000001,26.79622],"type":"Point"}
}