{
  "type": "Feature",
  "properties": {
    "gn:admin1_code":"30",
    "gn:admin2_code":"94.0",
    "gn:asciiname":"Palo Miguel",
    "gn:country_code":"MX",
    "gn:dem":34,
    "gn:feature_class":"P",
    "gn:feature_code":"PPL",
    "gn:name":"Palo Miguel",
    "gn:population":0,
    "gn:timezone":"America/Mexico_City",
    "iso:country":"MX",
    "name:und_x_variant":[
        "Palo de Miguel"
    ],
    "wof:name":"Palo Miguel",
    "wof:placetype":"locality"
},
  "geometry": {"coordinates":[-95.43898,18.14966],"type":"Point"}
}