{
  "type": "Feature",
  "properties": {
    "gn:admin1_code":"22",
    "gn:admin2_code":"16.0",
    "gn:asciiname":"Santa Matilde",
    "gn:country_code":"MX",
    "gn:dem":1908,
    "gn:feature_class":"P",
    "gn:feature_code":"PPL",
    "gn:name":"Santa Matilde",
    "gn:population":0,
    "gn:timezone":"America/Mexico_City",
    "iso:country":"MX",
    "name:cat_x_preferred":[
        "Santa Matilde"
    ],
    "name:deu_x_preferred":[
        "Santa Matilde"
    ],
    "name:por_x_preferred":[
        "Santa Matilde"
    ],
    "name:spa_x_preferred":[
        "Santa Matilde"
    ],
    "wof:name":"Santa Matilde",
    "wof:placetype":"locality"
},
  "geometry": {"coordinates":[-100.02611,20.43268],"type":"Point"}
}