{
  "type": "Feature",
  "properties": {
    "gn:admin1_code":"30.0",
    "gn:admin2_code":"83.0",
    "gn:asciiname":"El Tepetate",
    "gn:country_code":"MX",
    "gn:dem":198,
    "gn:feature_class":"P",
    "gn:feature_code":"PPL",
    "gn:name":"El Tepetate",
    "gn:population":529,
    "gn:timezone":"America/Mexico_City",
    "iso:country":"MX",
    "name:spa_x_preferred":[
        "El Tepetate"
    ],
    "wof:name":"El Tepetate",
    "wof:placetype":"locality",
    "wof:population":529
},
  "geometry": {"coordinates":[-97.92444,20.58083],"type":"Point"}
}