{
  "type": "Feature",
  "properties": {
    "gn:admin1_code":"6.0",
    "gn:admin2_code":"42.0",
    "gn:asciiname":"La Mota",
    "gn:country_code":"MX",
    "gn:dem":1495,
    "gn:feature_class":"P",
    "gn:feature_code":"PPL",
    "gn:name":"La Mota",
    "gn:population":3,
    "gn:timezone":"America/Chihuahua",
    "iso:country":"MX",
    "name:spa_x_preferred":[
        "La Mota"
    ],
    "wof:name":"La Mota",
    "wof:placetype":"locality",
    "wof:population":3
},
  "geometry": {"coordinates":[-103.74545999999999,28.80854],"type":"Point"}
}