{
  "type": "Feature",
  "properties": {
    "gn:admin1_code":"24",
    "gn:admin2_code":"19.0",
    "gn:asciiname":"El Limon",
    "gn:country_code":"MX",
    "gn:dem":1109,
    "gn:feature_class":"P",
    "gn:feature_code":"PPL",
    "gn:name":"El Lim\u00f3n",
    "gn:population":111,
    "gn:timezone":"America/Mexico_City",
    "iso:country":"MX",
    "name:und_x_variant":[
        "El Lim\u00f3n"
    ],
    "wof:name":"El Limon",
    "wof:placetype":"locality",
    "wof:population":111
},
  "geometry": {"coordinates":[-99.61333,21.56806],"type":"Point"}
}