{
  "type": "Feature",
  "properties": {
    "gn:admin1_code":"32",
    "gn:admin2_code":"42.0",
    "gn:asciiname":"Refugio de Los Pozos",
    "gn:country_code":"MX",
    "gn:dem":2448,
    "gn:feature_class":"P",
    "gn:feature_code":"PPL",
    "gn:name":"Refugio de Los Pozos",
    "gn:population":0,
    "gn:timezone":"America/Mexico_City",
    "iso:country":"MX",
    "name:spa_x_preferred":[
        "Refugio de Los Pozos"
    ],
    "wof:name":"Refugio de Los Pozos",
    "wof:placetype":"locality"
},
  "geometry": {"coordinates":[-103.72571000000001,23.14803],"type":"Point"}
}