{
  "type": "Feature",
  "properties": {
    "gn:admin1_code":"26.0",
    "gn:admin2_code":"29.0",
    "gn:asciiname":"Las Norias",
    "gn:country_code":"MX",
    "gn:dem":4,
    "gn:feature_class":"P",
    "gn:feature_code":"PPL",
    "gn:name":"Las Norias",
    "gn:population":0,
    "gn:timezone":"America/Hermosillo",
    "iso:country":"MX",
    "name:spa_x_preferred":[
        "Las Norias"
    ],
    "wof:name":"Las Norias",
    "wof:placetype":"locality"
},
  "geometry": {"coordinates":[-110.86798,28.02096],"type":"Point"}
}