{
  "type": "Feature",
  "properties": {
    "gn:admin1_code":"20",
    "gn:admin2_code":"482",
    "gn:asciiname":"El Mirador (Colonia el Mirador)",
    "gn:country_code":"MX",
    "gn:dem":257,
    "gn:feature_class":"P",
    "gn:feature_code":"PPL",
    "gn:name":"El Mirador (Colonia el Mirador)",
    "gn:population":14,
    "gn:timezone":"America/Mexico_City",
    "iso:country":"MX",
    "wof:name":"El Mirador (Colonia el Mirador)",
    "wof:placetype":"locality",
    "wof:population":14
},
  "geometry": {"coordinates":[-98.07250000000001,16.34861],"type":"Point"}
}