{
  "type": "Feature",
  "properties": {
    "gn:admin1_code":"24",
    "gn:admin2_code":"37.0",
    "gn:asciiname":"Coapilo",
    "gn:country_code":"MX",
    "gn:dem":320,
    "gn:feature_class":"P",
    "gn:feature_code":"PPL",
    "gn:name":"Coapilo",
    "gn:population":0,
    "gn:timezone":"America/Mexico_City",
    "iso:country":"MX",
    "name:spa_x_preferred":[
        "Coapilo"
    ],
    "wof:name":"Coapilo",
    "wof:placetype":"locality"
},
  "geometry": {"coordinates":[-98.81209,21.28014],"type":"Point"}
}