{
  "type": "Feature",
  "properties": {
    "gn:admin1_code":"26",
    "gn:admin2_code":"27.0",
    "gn:asciiname":"La Bloquera",
    "gn:country_code":"MX",
    "gn:dem":1210,
    "gn:feature_class":"P",
    "gn:feature_code":"PPL",
    "gn:name":"La Bloquera",
    "gn:population":6,
    "gn:timezone":"America/Hermosillo",
    "iso:country":"MX",
    "wof:name":"La Bloquera",
    "wof:placetype":"locality",
    "wof:population":6
},
  "geometry": {"coordinates":[-109.58638999999999,30.71556],"type":"Point"}
}