{
  "type": "Feature",
  "properties": {
    "gn:admin1_code":"20",
    "gn:admin2_code":"50.0",
    "gn:asciiname":"Mirasol",
    "gn:country_code":"MX",
    "gn:dem":2077,
    "gn:feature_class":"P",
    "gn:feature_code":"PPL",
    "gn:name":"Mirasol",
    "gn:population":107,
    "gn:timezone":"America/Mexico_City",
    "iso:country":"MX",
    "wof:name":"Mirasol",
    "wof:placetype":"locality",
    "wof:population":107
},
  "geometry": {"coordinates":[-97.54139000000001,17.22083],"type":"Point"}
}