{
  "type": "Feature",
  "properties": {
    "gn:admin1_code":"26",
    "gn:admin2_code":"68.0",
    "gn:asciiname":"El Consejo",
    "gn:country_code":"MX",
    "gn:dem":660,
    "gn:feature_class":"P",
    "gn:feature_code":"PPL",
    "gn:name":"El Consejo",
    "gn:population":0,
    "gn:timezone":"America/Hermosillo",
    "iso:country":"MX",
    "name:fra_x_preferred":[
        "El Consejo"
    ],
    "name:ita_x_preferred":[
        "El Consejo"
    ],
    "name:pol_x_preferred":[
        "El Consejo"
    ],
    "name:por_x_preferred":[
        "El Consejo"
    ],
    "name:rus_x_preferred":[
        "\u042d\u043b\u044c-\u041a\u043e\u043d\u0441\u0435\u0445\u043e"
    ],
    "name:sco_x_preferred":[
        "El Consejo"
    ],
    "name:spa_x_preferred":[
        "El Consejo"
    ],
    "name:zho_x_preferred":[
        "\u57c3\u723e\u5b54\u585e\u970d"
    ],
    "wof:name":"El Consejo",
    "wof:placetype":"locality"
},
  "geometry": {"coordinates":[-110.03433,29.09663],"type":"Point"}
}