{
  "type": "Feature",
  "properties": {
    "gn:admin1_code":"19.0",
    "gn:admin2_code":"44.0",
    "gn:asciiname":"El Encino",
    "gn:country_code":"MX",
    "gn:dem":311,
    "gn:feature_class":"P",
    "gn:feature_code":"PPL",
    "gn:name":"El Encino",
    "gn:population":0,
    "gn:timezone":"America/Monterrey",
    "iso:country":"MX",
    "wof:name":"El Encino",
    "wof:placetype":"locality"
},
  "geometry": {"coordinates":[-100.06667,26.36667000000001],"type":"Point"}
}