{
  "type": "Feature",
  "properties": {
    "gn:admin1_code":"32",
    "gn:admin2_code":"52.0",
    "gn:asciiname":"Los Horcones",
    "gn:country_code":"MX",
    "gn:dem":2400,
    "gn:feature_class":"P",
    "gn:feature_code":"PPL",
    "gn:name":"Los Horcones",
    "gn:population":170,
    "gn:timezone":"America/Mexico_City",
    "iso:country":"MX",
    "name:fra_x_preferred":[
        "Los Horcones"
    ],
    "name:por_x_preferred":[
        "Los horcones"
    ],
    "wof:name":"Los Horcones",
    "wof:placetype":"locality",
    "wof:population":170
},
  "geometry": {"coordinates":[-101.84472,22.14583],"type":"Point"}
}