{
  "type": "Feature",
  "properties": {
    "gn:admin1_code":"10",
    "gn:admin2_code":"34.0",
    "gn:asciiname":"San Juachin",
    "gn:country_code":"MX",
    "gn:dem":410,
    "gn:feature_class":"P",
    "gn:feature_code":"PPL",
    "gn:name":"San Juach\u00edn",
    "gn:population":0,
    "gn:timezone":"America/Monterrey",
    "iso:country":"MX",
    "name:spa_x_preferred":[
        "San Juach\u00edn"
    ],
    "wof:name":"San Juachin",
    "wof:placetype":"locality"
},
  "geometry": {"coordinates":[-107.07755,25.30546],"type":"Point"}
}