{
  "type": "Feature",
  "properties": {
    "gn:admin1_code":"25.0",
    "gn:admin2_code":"7.0",
    "gn:asciiname":"Hierba Buena",
    "gn:country_code":"MX",
    "gn:dem":753,
    "gn:feature_class":"P",
    "gn:feature_code":"PPL",
    "gn:name":"Hierba Buena",
    "gn:population":0,
    "gn:timezone":"America/Mazatlan",
    "iso:country":"MX",
    "name:spa_x_preferred":[
        "Hierba Buena"
    ],
    "wof:name":"Hierba Buena",
    "wof:placetype":"locality"
},
  "geometry": {"coordinates":[-108.18397,26.83793],"type":"Point"}
}