{
  "type": "Feature",
  "properties": {
    "gn:admin1_code":"32",
    "gn:admin2_code":"51.0",
    "gn:asciiname":"Flores Magon",
    "gn:country_code":"MX",
    "gn:dem":2023,
    "gn:feature_class":"P",
    "gn:feature_code":"PPL",
    "gn:name":"Flores Magon",
    "gn:population":0,
    "gn:timezone":"America/Mexico_City",
    "iso:country":"MX",
    "name:spa_x_preferred":[
        "Flores Magon"
    ],
    "wof:name":"Flores Magon",
    "wof:placetype":"locality"
},
  "geometry": {"coordinates":[-102.24115999999999,23.69308],"type":"Point"}
}