{
  "type": "Feature",
  "properties": {
    "gn:admin1_code":"5.0",
    "gn:asciiname":"Los Jazmines",
    "gn:country_code":"MX",
    "gn:dem":1114,
    "gn:feature_class":"P",
    "gn:feature_code":"PPL",
    "gn:name":"Los Jazmines",
    "gn:population":0,
    "gn:timezone":"America/Mexico_City",
    "iso:country":"MX",
    "name:spa_x_preferred":[
        "Los Jazmines"
    ],
    "wof:name":"Los Jazmines",
    "wof:placetype":"locality"
},
  "geometry": {"coordinates":[-92.65893,15.74584],"type":"Point"}
}