{
  "type": "Feature",
  "properties": {
    "gn:admin1_code":"30",
    "gn:admin2_code":"139.0",
    "gn:asciiname":"Boca de la Sierra",
    "gn:country_code":"MX",
    "gn:dem":7,
    "gn:feature_class":"P",
    "gn:feature_code":"PPL",
    "gn:name":"Boca de la Sierra",
    "gn:population":134,
    "gn:timezone":"America/Mexico_City",
    "iso:country":"MX",
    "wof:name":"Boca de la Sierra",
    "wof:placetype":"locality",
    "wof:population":134
},
  "geometry": {"coordinates":[-95.54277999999999,18.53278],"type":"Point"}
}