{
  "type": "Feature",
  "properties": {
    "gn:admin1_code":"31",
    "gn:admin2_code":"57",
    "gn:asciiname":"Nohsubul",
    "gn:country_code":"MX",
    "gn:dem":7,
    "gn:feature_class":"P",
    "gn:feature_code":"PPL",
    "gn:name":"Nohsubul",
    "gn:population":10,
    "gn:timezone":"America/Merida",
    "iso:country":"MX",
    "wof:name":"Nohsubul",
    "wof:placetype":"locality",
    "wof:population":10
},
  "geometry": {"coordinates":[-88.15833000000001,21.42194],"type":"Point"}
}