{
  "type": "Feature",
  "properties": {
    "gn:admin1_code":"6.0",
    "gn:admin2_code":"16.0",
    "gn:asciiname":"El Temporal",
    "gn:country_code":"MX",
    "gn:dem":1295,
    "gn:feature_class":"P",
    "gn:feature_code":"PPL",
    "gn:name":"El Temporal",
    "gn:population":0,
    "gn:timezone":"America/Chihuahua",
    "iso:country":"MX",
    "name:spa_x_preferred":[
        "El Temporal"
    ],
    "wof:name":"El Temporal",
    "wof:placetype":"locality"
},
  "geometry": {"coordinates":[-105.0245,27.93302000000001],"type":"Point"}
}