{
  "type": "Feature",
  "properties": {
    "gn:admin1_code":"1.0",
    "gn:admin2_code":"1.0",
    "gn:asciiname":"Ojo de Agua de las Palmitas",
    "gn:country_code":"MX",
    "gn:dem":1975,
    "gn:feature_class":"P",
    "gn:feature_code":"PPL",
    "gn:name":"Ojo de Agua de las Palmitas",
    "gn:population":0,
    "gn:timezone":"America/Mexico_City",
    "iso:country":"MX",
    "wof:name":"Ojo de Agua de las Palmitas",
    "wof:placetype":"locality"
},
  "geometry": {"coordinates":[-102.24281999999999,21.85471],"type":"Point"}
}