{
  "type": "Feature",
  "properties": {
    "gn:admin1_code":"10",
    "gn:admin2_code":"5.0",
    "gn:asciiname":"Ex-Hacienda de San Vicente (La Hacienda)",
    "gn:country_code":"MX",
    "gn:dem":1961,
    "gn:feature_class":"P",
    "gn:feature_code":"PPL",
    "gn:name":"Ex-Hacienda de San Vicente (La Hacienda)",
    "gn:population":6,
    "gn:timezone":"America/Monterrey",
    "iso:country":"MX",
    "wof:name":"Ex-Hacienda de San Vicente (La Hacienda)",
    "wof:placetype":"locality",
    "wof:population":6
},
  "geometry": {"coordinates":[-104.71835,24.1189],"type":"Point"}
}