{
  "type": "Feature",
  "properties": {
    "gn:admin1_code":"15",
    "gn:admin2_code":"63",
    "gn:asciiname":"Acahualtzingo",
    "gn:country_code":"MX",
    "gn:dem":2484,
    "gn:feature_class":"P",
    "gn:feature_code":"PPL",
    "gn:name":"Acahualtzingo",
    "gn:population":37,
    "gn:timezone":"America/Mexico_City",
    "iso:country":"MX",
    "wof:name":"Acahualtzingo",
    "wof:placetype":"locality",
    "wof:population":37
},
  "geometry": {"coordinates":[-99.37112999999999,18.97793],"type":"Point"}
}