{
  "type": "Feature",
  "properties": {
    "gn:admin1_code":"21",
    "gn:admin2_code":"53.0",
    "gn:asciiname":"Hueymac",
    "gn:country_code":"MX",
    "gn:dem":2336,
    "gn:feature_class":"P",
    "gn:feature_code":"PPL",
    "gn:name":"Hu\u00e9ymac",
    "gn:population":7,
    "gn:timezone":"America/Mexico_City",
    "iso:country":"MX",
    "name:und_x_variant":[
        "Hu\u00e9ymac"
    ],
    "wof:name":"Hueymac",
    "wof:placetype":"locality",
    "wof:population":7
},
  "geometry": {"coordinates":[-98.03946000000001,19.88393],"type":"Point"}
}