{
  "type": "Feature",
  "properties": {
    "gn:admin1_code":"24.0",
    "gn:asciiname":"Puerto Colorado",
    "gn:country_code":"MX",
    "gn:dem":2215,
    "gn:feature_class":"P",
    "gn:feature_code":"PPL",
    "gn:name":"Puerto Colorado",
    "gn:population":0,
    "gn:timezone":"America/Mexico_City",
    "iso:country":"MX",
    "name:spa_x_preferred":[
        "Puerto Colorado"
    ],
    "wof:name":"Puerto Colorado",
    "wof:placetype":"locality"
},
  "geometry": {"coordinates":[-101.20018,23.03696],"type":"Point"}
}