{
  "type": "Feature",
  "properties": {
    "gn:admin1_code":"5",
    "gn:admin2_code":"40.0",
    "gn:asciiname":"Fraccion Santa Teresa",
    "gn:country_code":"MX",
    "gn:dem":30,
    "gn:feature_class":"P",
    "gn:feature_code":"PPL",
    "gn:name":"Fracci\u00f3n Santa Teresa",
    "gn:population":4,
    "gn:timezone":"America/Mexico_City",
    "iso:country":"MX",
    "name:und_x_variant":[
        "Fracci\u00f3n Santa Teresa"
    ],
    "wof:name":"Fraccion Santa Teresa",
    "wof:placetype":"locality",
    "wof:population":4
},
  "geometry": {"coordinates":[-92.52028,15.15889],"type":"Point"}
}