{
  "type": "Feature",
  "properties": {
    "gn:admin1_code":"21",
    "gn:admin2_code":"45.0",
    "gn:asciiname":"Arcos Ojo de Agua",
    "gn:country_code":"MX",
    "gn:dem":2802,
    "gn:feature_class":"P",
    "gn:feature_code":"PPL",
    "gn:name":"Arcos Ojo de Agua",
    "gn:population":0,
    "gn:timezone":"America/Mexico_City",
    "iso:country":"MX",
    "name:spa_x_preferred":[
        "Arcos Ojo de Agua"
    ],
    "wof:name":"Arcos Ojo de Agua",
    "wof:placetype":"locality"
},
  "geometry": {"coordinates":[-97.39529,19.00481],"type":"Point"}
}