{
  "type": "Feature",
  "properties": {
    "gn:admin1_code":"14",
    "gn:admin2_code":"123.0",
    "gn:asciiname":"Los Orozco",
    "gn:country_code":"MX",
    "gn:dem":1890,
    "gn:feature_class":"P",
    "gn:feature_code":"PPL",
    "gn:name":"Los Orozco",
    "gn:population":5,
    "gn:timezone":"America/Mexico_City",
    "iso:country":"MX",
    "wof:name":"Los Orozco",
    "wof:placetype":"locality",
    "wof:population":5
},
  "geometry": {"coordinates":[-102.88861,20.53472],"type":"Point"}
}