{
  "type": "Feature",
  "properties": {
    "gn:admin1_code":"14",
    "gn:admin2_code":"104.0",
    "gn:asciiname":"La Cementera",
    "gn:country_code":"MX",
    "gn:dem":2055,
    "gn:feature_class":"P",
    "gn:feature_code":"PPL",
    "gn:name":"La Cementera",
    "gn:population":0,
    "gn:timezone":"America/Mexico_City",
    "iso:country":"MX",
    "name:spa_x_preferred":[
        "La Cementera"
    ],
    "name:und_x_variant":[
        "Sementera"
    ],
    "wof:name":"La Cementera",
    "wof:placetype":"locality"
},
  "geometry": {"coordinates":[-103.46872,21.87873],"type":"Point"}
}