{
  "type": "Feature",
  "properties": {
    "gn:admin1_code":"2",
    "gn:admin2_code":"1.0",
    "gn:asciiname":"El Jorol",
    "gn:country_code":"MX",
    "gn:dem":218,
    "gn:feature_class":"P",
    "gn:feature_code":"PPL",
    "gn:name":"El Jorol",
    "gn:population":4,
    "gn:timezone":"America/Tijuana",
    "iso:country":"MX",
    "wof:name":"El Jorol",
    "wof:placetype":"locality",
    "wof:population":4
},
  "geometry": {"coordinates":[-116.73389,31.96611],"type":"Point"}
}