{
  "type": "Feature",
  "properties": {
    "gn:admin1_code":"5.0",
    "gn:asciiname":"Calzada de los Mangos",
    "gn:country_code":"MX",
    "gn:dem":801,
    "gn:feature_class":"P",
    "gn:feature_code":"PPL",
    "gn:name":"Calzada de los Mangos",
    "gn:population":0,
    "gn:timezone":"America/Mexico_City",
    "iso:country":"MX",
    "name:spa_x_preferred":[
        "Calzada de los Mangos"
    ],
    "wof:name":"Calzada de los Mangos",
    "wof:placetype":"locality"
},
  "geometry": {"coordinates":[-93.46098000000001,16.69029],"type":"Point"}
}