{
  "type": "Feature",
  "properties": {
    "gn:admin1_code":"30.0",
    "gn:admin2_code":"40.0",
    "gn:asciiname":"Los Polvorones",
    "gn:country_code":"MX",
    "gn:dem":86,
    "gn:feature_class":"P",
    "gn:feature_code":"PPL",
    "gn:name":"Los Polvorones",
    "gn:population":5,
    "gn:timezone":"America/Mexico_City",
    "iso:country":"MX",
    "name:spa_x_preferred":[
        "Los Polvorones"
    ],
    "wof:name":"Los Polvorones",
    "wof:placetype":"locality",
    "wof:population":5
},
  "geometry": {"coordinates":[-97.55417,20.47444],"type":"Point"}
}