{
  "type": "Feature",
  "properties": {
    "gn:admin1_code":"32.0",
    "gn:admin2_code":"10.0",
    "gn:asciiname":"Atenas",
    "gn:country_code":"MX",
    "gn:dem":2124,
    "gn:feature_class":"P",
    "gn:feature_code":"PPL",
    "gn:name":"Atenas",
    "gn:population":0,
    "gn:timezone":"America/Mexico_City",
    "iso:country":"MX",
    "name:ceb_x_preferred":[
        "Atenas"
    ],
    "name:ell_x_preferred":[
        "\u0391\u03b8\u03ae\u03bd\u03b1"
    ],
    "name:fas_x_preferred":[
        "\u0622\u062a\u0646\u0627\u0633"
    ],
    "name:fra_x_preferred":[
        "Atenas"
    ],
    "name:ita_x_preferred":[
        "Atenas"
    ],
    "name:lit_x_preferred":[
        "Atenasas"
    ],
    "name:nld_x_preferred":[
        "Atenas"
    ],
    "name:nor_x_preferred":[
        "Atenas"
    ],
    "name:spa_x_preferred":[
        "Atenas"
    ],
    "name:swe_x_preferred":[
        "Atenas"
    ],
    "name:zho_x_preferred":[
        "\u963f\u7279\u7d0d\u65af\u5340"
    ],
    "wof:name":"Atenas",
    "wof:placetype":"locality"
},
  "geometry": {"coordinates":[-103.25235000000001,23.2219],"type":"Point"}
}