{
  "type": "Feature",
  "properties": {
    "gn:admin1_code":"30",
    "gn:admin2_code":"87",
    "gn:asciiname":"Vaqueria (Pailas)",
    "gn:country_code":"MX",
    "gn:dem":752,
    "gn:feature_class":"P",
    "gn:feature_code":"PPL",
    "gn:name":"Vaquer\u00eda (Pailas)",
    "gn:population":10,
    "gn:timezone":"America/Mexico_City",
    "iso:country":"MX",
    "name:und_x_variant":[
        "Vaquer\u00eda (Pailas)"
    ],
    "wof:name":"Vaqueria (Pailas)",
    "wof:placetype":"locality",
    "wof:population":10
},
  "geometry": {"coordinates":[-96.80722,19.56667],"type":"Point"}
}