{
  "type": "Feature",
  "properties": {
    "gn:admin1_code":"6",
    "gn:admin2_code":"29.0",
    "gn:asciiname":"Triana",
    "gn:country_code":"MX",
    "gn:dem":829,
    "gn:feature_class":"P",
    "gn:feature_code":"PPL",
    "gn:name":"Triana",
    "gn:population":75,
    "gn:timezone":"America/Chihuahua",
    "iso:country":"MX",
    "wof:name":"Triana",
    "wof:placetype":"locality",
    "wof:population":75
},
  "geometry": {"coordinates":[-107.1893,25.96968],"type":"Point"}
}