{
  "type": "Feature",
  "properties": {
    "gn:admin1_code":"5",
    "gn:admin2_code":"31.0",
    "gn:asciiname":"Guadalupe Pojcol",
    "gn:country_code":"MX",
    "gn:dem":1130,
    "gn:feature_class":"P",
    "gn:feature_code":"PPL",
    "gn:name":"Guadalupe Pojcol",
    "gn:population":0,
    "gn:timezone":"America/Mexico_City",
    "iso:country":"MX",
    "name:spa_x_preferred":[
        "Guadalupe Pojcol"
    ],
    "name:spa_x_variant":[
        "Pojcol"
    ],
    "wof:name":"Guadalupe Pojcol",
    "wof:placetype":"locality"
},
  "geometry": {"coordinates":[-91.99258,16.99801],"type":"Point"}
}