{
  "type": "Feature",
  "properties": {
    "gn:admin1_code":"6",
    "gn:admin2_code":"30.0",
    "gn:asciiname":"La Junta",
    "gn:country_code":"MX",
    "gn:dem":827,
    "gn:feature_class":"P",
    "gn:feature_code":"PPL",
    "gn:name":"La Junta",
    "gn:population":7,
    "gn:timezone":"America/Chihuahua",
    "iso:country":"MX",
    "wof:name":"La Junta",
    "wof:placetype":"locality",
    "wof:population":7
},
  "geometry": {"coordinates":[-108.36078000000001,27.41058],"type":"Point"}
}