{
  "type": "Feature",
  "properties": {
    "gn:admin1_code":"30.0",
    "gn:asciiname":"Los Encinitos",
    "gn:country_code":"MX",
    "gn:dem":148,
    "gn:feature_class":"P",
    "gn:feature_code":"PPL",
    "gn:name":"Los Encinitos",
    "gn:population":0,
    "gn:timezone":"America/Mexico_City",
    "iso:country":"MX",
    "name:spa_x_preferred":[
        "Los Encinitos"
    ],
    "wof:name":"Los Encinitos",
    "wof:placetype":"locality"
},
  "geometry": {"coordinates":[-95.34452,17.91899],"type":"Point"}
}