{
  "type": "Feature",
  "properties": {
    "gn:admin1_code":"30",
    "gn:admin2_code":"130",
    "gn:asciiname":"La Admiracion",
    "gn:country_code":"MX",
    "gn:dem":37,
    "gn:feature_class":"P",
    "gn:feature_code":"PPL",
    "gn:name":"La Admiraci\u00f3n",
    "gn:population":12,
    "gn:timezone":"America/Mexico_City",
    "iso:country":"MX",
    "name:und_x_variant":[
        "La Admiraci\u00f3n"
    ],
    "wof:name":"La Admiracion",
    "wof:placetype":"locality",
    "wof:population":12
},
  "geometry": {"coordinates":[-95.71056,17.88361],"type":"Point"}
}