{
  "type": "Feature",
  "properties": {
    "gn:admin1_code":"5",
    "gn:admin2_code":"107.0",
    "gn:asciiname":"El Norteno",
    "gn:country_code":"MX",
    "gn:dem":623,
    "gn:feature_class":"P",
    "gn:feature_code":"PPL",
    "gn:name":"El Norte\u00f1o",
    "gn:population":4,
    "gn:timezone":"America/Mexico_City",
    "iso:country":"MX",
    "name:und_x_variant":[
        "El Norte\u00f1o"
    ],
    "wof:name":"El Norteno",
    "wof:placetype":"locality",
    "wof:population":4
},
  "geometry": {"coordinates":[-92.98583000000001,16.25832999999999],"type":"Point"}
}