{
  "type": "Feature",
  "properties": {
    "gn:admin1_code":"30",
    "gn:admin2_code":"23.0",
    "gn:asciiname":"Zapote Redondo",
    "gn:country_code":"MX",
    "gn:dem":337,
    "gn:feature_class":"P",
    "gn:feature_code":"PPL",
    "gn:name":"Zapote Redondo",
    "gn:population":383,
    "gn:timezone":"America/Mexico_City",
    "iso:country":"MX",
    "wof:name":"Zapote Redondo",
    "wof:placetype":"locality",
    "wof:population":383
},
  "geometry": {"coordinates":[-97.10693999999999,19.97167],"type":"Point"}
}