{
  "type": "Feature",
  "properties": {
    "gn:admin1_code":"10",
    "gn:admin2_code":"37.0",
    "gn:asciiname":"Cuartillos",
    "gn:country_code":"MX",
    "gn:dem":687,
    "gn:feature_class":"P",
    "gn:feature_code":"PPL",
    "gn:name":"Cuartillos",
    "gn:population":0,
    "gn:timezone":"America/Monterrey",
    "iso:country":"MX",
    "name:spa_x_preferred":[
        "Cuartillos"
    ],
    "wof:name":"Cuartillos",
    "wof:placetype":"locality"
},
  "geometry": {"coordinates":[-106.79747999999999,25.35317],"type":"Point"}
}