{
  "type": "Feature",
  "properties": {
    "gn:admin1_code":"6.0",
    "gn:admin2_code":"61.0",
    "gn:asciiname":"Borunda",
    "gn:country_code":"MX",
    "gn:dem":1364,
    "gn:feature_class":"P",
    "gn:feature_code":"PPL",
    "gn:name":"Borunda",
    "gn:population":0,
    "gn:timezone":"America/Chihuahua",
    "iso:country":"MX",
    "name:spa_x_preferred":[
        "Borunda"
    ],
    "name:spa_x_variant":[
        "Rancho Borunda"
    ],
    "wof:name":"Borunda",
    "wof:placetype":"locality"
},
  "geometry": {"coordinates":[-106.10299999999999,27.90599000000001],"type":"Point"}
}