{
  "type": "Feature",
  "properties": {
    "gn:admin1_code":"14.0",
    "gn:admin2_code":"49.0",
    "gn:asciiname":"El Soyatal",
    "gn:country_code":"MX",
    "gn:dem":1213,
    "gn:feature_class":"P",
    "gn:feature_code":"PPL",
    "gn:name":"El Soyatal",
    "gn:population":0,
    "gn:timezone":"America/Mexico_City",
    "iso:country":"MX",
    "name:spa_x_preferred":[
        "El Soyatal"
    ],
    "name:und_x_variant":[
        "El Soyotal"
    ],
    "wof:name":"El Soyatal",
    "wof:placetype":"locality",
    "wof:population":82
},
  "geometry": {"coordinates":[-103.11744,19.27742],"type":"Point"}
}