{
  "type": "Feature",
  "properties": {
    "gn:admin1_code":"11",
    "gn:admin2_code":"1.0",
    "gn:asciiname":"La Mina",
    "gn:country_code":"MX",
    "gn:dem":1758,
    "gn:feature_class":"P",
    "gn:feature_code":"PPL",
    "gn:name":"La Mina",
    "gn:population":152,
    "gn:timezone":"America/Mexico_City",
    "iso:country":"MX",
    "name:ita_x_preferred":[
        "La Mina"
    ],
    "name:und_x_variant":[
        "Mina",
        "La Mina"
    ],
    "wof:name":"La Mina",
    "wof:placetype":"locality",
    "wof:population":152
},
  "geometry": {"coordinates":[-101.54859999999999,20.42034],"type":"Point"}
}