{
  "type": "Feature",
  "properties": {
    "gn:admin1_code":"26.0",
    "gn:admin2_code":"47.0",
    "gn:asciiname":"El Banco",
    "gn:country_code":"MX",
    "gn:dem":690,
    "gn:feature_class":"P",
    "gn:feature_code":"PPL",
    "gn:name":"El Banco",
    "gn:population":0,
    "gn:timezone":"America/Hermosillo",
    "iso:country":"MX",
    "name:und_x_variant":[
        "Rancho El Banco",
        "El Banco"
    ],
    "wof:name":"El Banco",
    "wof:placetype":"locality"
},
  "geometry": {"coordinates":[-111.46561,29.86876],"type":"Point"}
}