{
  "type": "Feature",
  "properties": {
    "gn:admin1_code":"26",
    "gn:admin2_code":"42.0",
    "gn:asciiname":"Sapochopo",
    "gn:country_code":"MX",
    "gn:dem":32,
    "gn:feature_class":"P",
    "gn:feature_code":"PPL",
    "gn:name":"Sapochopo",
    "gn:population":408,
    "gn:timezone":"America/Hermosillo",
    "iso:country":"MX",
    "wof:name":"Sapochopo",
    "wof:placetype":"locality",
    "wof:population":408
},
  "geometry": {"coordinates":[-109.49722,27.05417000000001],"type":"Point"}
}