{
  "type": "Feature",
  "properties": {
    "gn:admin1_code":"3",
    "gn:admin2_code":"1",
    "gn:asciiname":"El Esteron",
    "gn:country_code":"MX",
    "gn:dem":123,
    "gn:feature_class":"P",
    "gn:feature_code":"PPL",
    "gn:name":"El Ester\u00f3n",
    "gn:population":10,
    "gn:timezone":"America/Mazatlan",
    "iso:country":"MX",
    "name:und_x_variant":[
        "El Ester\u00f3n"
    ],
    "wof:name":"El Esteron",
    "wof:placetype":"locality",
    "wof:population":10
},
  "geometry": {"coordinates":[-111.40636000000001,25.18461],"type":"Point"}
}