{
  "type": "Feature",
  "properties": {
    "gn:admin1_code":"20",
    "gn:admin2_code":"159.0",
    "gn:asciiname":"Ocote Largo",
    "gn:country_code":"MX",
    "gn:dem":2405,
    "gn:feature_class":"P",
    "gn:feature_code":"PPL",
    "gn:name":"Ocote Largo",
    "gn:population":0,
    "gn:timezone":"America/Mexico_City",
    "iso:country":"MX",
    "name:spa_x_preferred":[
        "Ocote Largo"
    ],
    "wof:name":"Ocote Largo",
    "wof:placetype":"locality"
},
  "geometry": {"coordinates":[-96.9811,16.23308],"type":"Point"}
}