{
  "type": "Feature",
  "properties": {
    "gn:admin1_code":"13",
    "gn:admin2_code":"76.0",
    "gn:asciiname":"La Amistad",
    "gn:country_code":"MX",
    "gn:dem":2101,
    "gn:feature_class":"P",
    "gn:feature_code":"PPL",
    "gn:name":"La Amistad",
    "gn:population":1401,
    "gn:timezone":"America/Mexico_City",
    "iso:country":"MX",
    "wof:name":"La Amistad",
    "wof:placetype":"locality",
    "wof:population":1401
},
  "geometry": {"coordinates":[-99.32028,20.00833],"type":"Point"}
}