{
  "type": "Feature",
  "properties": {
    "gn:admin1_code":"30.0",
    "gn:admin2_code":"55.0",
    "gn:asciiname":"Pachahuala",
    "gn:country_code":"MX",
    "gn:dem":111,
    "gn:feature_class":"P",
    "gn:feature_code":"PPL",
    "gn:name":"Pachahuala",
    "gn:population":0,
    "gn:timezone":"America/Mexico_City",
    "iso:country":"MX",
    "name:spa_x_preferred":[
        "Pachahuala"
    ],
    "wof:name":"Pachahuala",
    "wof:placetype":"locality"
},
  "geometry": {"coordinates":[-98.38355,21.22541],"type":"Point"}
}