{
  "type": "Feature",
  "properties": {
    "gn:admin1_code":"26",
    "gn:admin2_code":"12.0",
    "gn:asciiname":"La Tina",
    "gn:country_code":"MX",
    "gn:dem":119,
    "gn:feature_class":"P",
    "gn:feature_code":"PPL",
    "gn:name":"La Tina",
    "gn:population":1,
    "gn:timezone":"America/Hermosillo",
    "iso:country":"MX",
    "wof:name":"La Tina",
    "wof:placetype":"locality",
    "wof:population":1
},
  "geometry": {"coordinates":[-110.15584,27.81737],"type":"Point"}
}