{
  "type": "Feature",
  "properties": {
    "gn:admin1_code":"20",
    "gn:admin2_code":"207.0",
    "gn:asciiname":"Tutla",
    "gn:country_code":"MX",
    "gn:dem":174,
    "gn:feature_class":"P",
    "gn:feature_code":"PPL",
    "gn:name":"Tutla",
    "gn:population":0,
    "gn:timezone":"America/Mexico_City",
    "iso:country":"MX",
    "name:und_x_variant":[
        "Putla",
        "Santiago",
        "Tutla"
    ],
    "wof:name":"Tutla",
    "wof:placetype":"locality"
},
  "geometry": {"coordinates":[-95.44911999999999,17.18743],"type":"Point"}
}