{
  "type": "Feature",
  "properties": {
    "gn:admin1_code":"20",
    "gn:admin2_code":"30.0",
    "gn:asciiname":"La Cabana del Tio Pou",
    "gn:country_code":"MX",
    "gn:dem":31,
    "gn:feature_class":"P",
    "gn:feature_code":"PPL",
    "gn:name":"La Caba\u00f1a del T\u00edo Pou",
    "gn:population":8,
    "gn:timezone":"America/Mexico_City",
    "iso:country":"MX",
    "name:und_x_variant":[
        "La Caba\u00f1a del T\u00edo Pou"
    ],
    "wof:name":"La Cabana del Tio Pou",
    "wof:placetype":"locality",
    "wof:population":8
},
  "geometry": {"coordinates":[-95.03111,16.47332999999999],"type":"Point"}
}