{
  "type": "Feature",
  "properties": {
    "gn:admin1_code":"25",
    "gn:admin2_code":"18.0",
    "gn:asciiname":"Granja Bachoco Pollo 23",
    "gn:country_code":"MX",
    "gn:dem":15,
    "gn:feature_class":"P",
    "gn:feature_code":"PPL",
    "gn:name":"Granja Bachoco Pollo 23",
    "gn:population":8,
    "gn:timezone":"America/Mazatlan",
    "iso:country":"MX",
    "wof:name":"Granja Bachoco Pollo 23",
    "wof:placetype":"locality",
    "wof:population":8
},
  "geometry": {"coordinates":[-107.64549,24.75904],"type":"Point"}
}