{
  "type": "Feature",
  "properties": {
    "gn:admin1_code":"32.0",
    "gn:admin2_code":"7.0",
    "gn:asciiname":"Siete Hermanos",
    "gn:country_code":"MX",
    "gn:dem":1932,
    "gn:feature_class":"P",
    "gn:feature_code":"PPL",
    "gn:name":"Siete Hermanos",
    "gn:population":0,
    "gn:timezone":"America/Mexico_City",
    "iso:country":"MX",
    "name:spa_x_preferred":[
        "Siete Hermanos"
    ],
    "wof:name":"Siete Hermanos",
    "wof:placetype":"locality"
},
  "geometry": {"coordinates":[-101.01755,24.39019],"type":"Point"}
}