{
  "type": "Feature",
  "properties": {
    "gn:admin1_code":"18.0",
    "gn:admin2_code":"10.0",
    "gn:asciiname":"El Mezcal",
    "gn:country_code":"MX",
    "gn:dem":11,
    "gn:feature_class":"P",
    "gn:feature_code":"PPL",
    "gn:name":"El Mezcal",
    "gn:population":0,
    "gn:timezone":"America/Mazatlan",
    "iso:country":"MX",
    "wof:name":"El Mezcal",
    "wof:placetype":"locality"
},
  "geometry": {"coordinates":[-105.28333000000001,22.05],"type":"Point"}
}