{
  "type": "Feature",
  "properties": {
    "gn:admin1_code":"31",
    "gn:admin2_code":"2.0",
    "gn:asciiname":"Las Margaritas",
    "gn:country_code":"MX",
    "gn:dem":16,
    "gn:feature_class":"P",
    "gn:feature_code":"PPL",
    "gn:name":"Las Margaritas",
    "gn:population":9,
    "gn:timezone":"America/Merida",
    "iso:country":"MX",
    "name:ceb_x_preferred":[
        "Las Margaritas"
    ],
    "name:deu_x_preferred":[
        "Las Margaritas"
    ],
    "name:fra_x_preferred":[
        "Las Margaritas"
    ],
    "name:ita_x_preferred":[
        "Las Margaritas"
    ],
    "name:sco_x_preferred":[
        "Las Margaritas"
    ],
    "name:spa_x_preferred":[
        "Las margaritas"
    ],
    "name:srp_x_preferred":[
        "\u041b\u0430\u0441 \u041c\u0430\u0440\u0433\u0430\u0440\u0438\u0442\u0430\u0441"
    ],
    "name:swe_x_preferred":[
        "Las Margaritas"
    ],
    "wof:name":"Las Margaritas",
    "wof:placetype":"locality",
    "wof:population":9
},
  "geometry": {"coordinates":[-89.42416999999998,20.855],"type":"Point"}
}