{
  "type": "Feature",
  "properties": {
    "gn:admin1_code":"6.0",
    "gn:admin2_code":"67.0",
    "gn:asciiname":"Arcadio",
    "gn:country_code":"MX",
    "gn:dem":1375,
    "gn:feature_class":"P",
    "gn:feature_code":"PPL",
    "gn:name":"Arcadio",
    "gn:population":0,
    "gn:timezone":"America/Chihuahua",
    "iso:country":"MX",
    "wof:name":"Arcadio",
    "wof:placetype":"locality"
},
  "geometry": {"coordinates":[-105.83333,27.41667],"type":"Point"}
}