{
  "type": "Feature",
  "properties": {
    "gn:admin1_code":"21",
    "gn:admin2_code":"45.0",
    "gn:asciiname":"Jesus Nazareno (Rancho Nuevo)",
    "gn:country_code":"MX",
    "gn:dem":2436,
    "gn:feature_class":"P",
    "gn:feature_code":"PPL",
    "gn:name":"Jes\u00fas Nazareno (Rancho Nuevo)",
    "gn:population":681,
    "gn:timezone":"America/Mexico_City",
    "iso:country":"MX",
    "name:und_x_variant":[
        "Jes\u00fas Nazareno (Rancho Nuevo)"
    ],
    "wof:name":"Jesus Nazareno (Rancho Nuevo)",
    "wof:placetype":"locality",
    "wof:population":681
},
  "geometry": {"coordinates":[-97.45833,18.90611],"type":"Point"}
}