{
  "type": "Feature",
  "properties": {
    "gn:admin1_code":"6.0",
    "gn:admin2_code":"20.0",
    "gn:asciiname":"Naranjitos",
    "gn:country_code":"MX",
    "gn:dem":1779,
    "gn:feature_class":"P",
    "gn:feature_code":"PPL",
    "gn:name":"Naranjitos",
    "gn:population":0,
    "gn:timezone":"America/Chihuahua",
    "iso:country":"MX",
    "name:spa_x_preferred":[
        "Naranjitos"
    ],
    "wof:name":"Naranjitos",
    "wof:placetype":"locality"
},
  "geometry": {"coordinates":[-108.40141,27.71941],"type":"Point"}
}