{
  "type": "Feature",
  "properties": {
    "gn:admin1_code":"13",
    "gn:admin2_code":"83.0",
    "gn:asciiname":"Santa Maria Tecajete",
    "gn:country_code":"MX",
    "gn:dem":2569,
    "gn:feature_class":"P",
    "gn:feature_code":"PPL",
    "gn:name":"Santa Mar\u00eda Tecajete",
    "gn:population":0,
    "gn:timezone":"America/Mexico_City",
    "iso:country":"MX",
    "name:und_x_variant":[
        "Santa Maria",
        "Tecajete",
        "Santa Mar\u00eda Tecajete"
    ],
    "wof:name":"Santa Maria Tecajete",
    "wof:placetype":"locality"
},
  "geometry": {"coordinates":[-98.59439999999999,19.93945],"type":"Point"}
}