{
  "type": "Feature",
  "properties": {
    "gn:admin1_code":"30",
    "gn:admin2_code":"77.0",
    "gn:asciiname":"La Providencia",
    "gn:country_code":"MX",
    "gn:dem":63,
    "gn:feature_class":"P",
    "gn:feature_code":"PPL",
    "gn:name":"La Providencia",
    "gn:population":0,
    "gn:timezone":"America/Mexico_City",
    "iso:country":"MX",
    "wof:name":"La Providencia",
    "wof:placetype":"locality"
},
  "geometry": {"coordinates":[-95.55638999999999,17.98139],"type":"Point"}
}