{
  "type": "Feature",
  "properties": {
    "gn:admin1_code":"2",
    "gn:admin2_code":"1.0",
    "gn:asciiname":"Adobe Guadalupe",
    "gn:country_code":"MX",
    "gn:dem":317,
    "gn:feature_class":"P",
    "gn:feature_code":"PPL",
    "gn:name":"Adobe Guadalupe",
    "gn:population":5,
    "gn:timezone":"America/Tijuana",
    "iso:country":"MX",
    "wof:name":"Adobe Guadalupe",
    "wof:placetype":"locality",
    "wof:population":5
},
  "geometry": {"coordinates":[-116.62417000000001,32.08583],"type":"Point"}
}