{
  "type": "Feature",
  "properties": {
    "gn:gn_country":"MX",
    "gn:gn_fcode":"PPL",
    "gn:gn_pop":0,
    "gn:population":227,
    "iso:country":"MX",
    "name:spa_x_preferred":[
        "Lindavista"
    ],
    "qs_pg:aaroncc":"MX",
    "qs_pg:gn_country":"MX",
    "qs_pg:gn_fcode":"PPL",
    "qs_pg:gn_pop":0,
    "qs_pg:name":"Linda Vista",
    "qs_pg:name_adm0":"M\u00e9xico",
    "qs_pg:name_adm1":"Veracruz-Llave",
    "qs_pg:photos_9r":0,
    "qs_pg:photos_sr":0,
    "qs_pg:pop_sr":0,
    "qs_pg:qs_pg_placetype":"neighbourhood",
    "qs_pg:qs_pg_placetype_gp":"Suburb",
    "qs_pg:woe_adm0":23424900,
    "woe:adm0_id":23424900,
    "woe:name_adm0":"M\u00e9xico",
    "woe:name_adm1":"Veracruz-Llave",
    "woe:placetype":"Suburb",
    "wof:name":"Linda Vista",
    "wof:placetype":"neighbourhood",
    "wof:population":227
},
  "geometry": {"coordinates":[-97.25057,20.7847],"type":"Point"}
}