{
  "type": "Feature",
  "properties": {
    "gn:admin1_code":"14.0",
    "gn:asciiname":"La Anilera",
    "gn:country_code":"MX",
    "gn:dem":1896,
    "gn:feature_class":"P",
    "gn:feature_code":"PPL",
    "gn:name":"La A\u00f1ilera",
    "gn:population":0,
    "gn:timezone":"America/Mexico_City",
    "iso:country":"MX",
    "name:spa_x_preferred":[
        "La A\u00f1ilera"
    ],
    "wof:name":"La Anilera",
    "wof:placetype":"locality"
},
  "geometry": {"coordinates":[-103.86794,19.4228],"type":"Point"}
}