{
  "type": "Feature",
  "properties": {
    "gn:admin1_code":"12",
    "gn:admin2_code":"25",
    "gn:asciiname":"Los Hornos",
    "gn:country_code":"MX",
    "gn:dem":85,
    "gn:feature_class":"P",
    "gn:feature_code":"PPL",
    "gn:name":"Los Hornos",
    "gn:population":9,
    "gn:timezone":"America/Mexico_City",
    "iso:country":"MX",
    "wof:name":"Los Hornos",
    "wof:placetype":"locality",
    "wof:population":9
},
  "geometry": {"coordinates":[-99.03335,16.73354],"type":"Point"}
}