{
  "type": "Feature",
  "properties": {
    "gn:admin1_code":"14.0",
    "gn:admin2_code":"87.0",
    "gn:asciiname":"Palos Altos",
    "gn:country_code":"MX",
    "gn:dem":1602,
    "gn:feature_class":"P",
    "gn:feature_code":"PPL",
    "gn:name":"Palos Altos",
    "gn:population":0,
    "gn:timezone":"America/Mexico_City",
    "iso:country":"MX",
    "name:spa_x_preferred":[
        "Palos Altos"
    ],
    "wof:name":"Palos Altos",
    "wof:placetype":"locality"
},
  "geometry": {"coordinates":[-103.33046,19.39411],"type":"Point"}
}