{
  "type": "Feature",
  "properties": {
    "gn:admin1_code":"32",
    "gn:admin2_code":"26.0",
    "gn:asciiname":"Majada Severino Robles (Santa Teresita de Jesus)",
    "gn:country_code":"MX",
    "gn:dem":1613,
    "gn:feature_class":"P",
    "gn:feature_code":"PPL",
    "gn:name":"Majada Severino Robles (Santa Teresita de Jes\u00fas)",
    "gn:population":7,
    "gn:timezone":"America/Mexico_City",
    "iso:country":"MX",
    "name:und_x_variant":[
        "Majada Severino Robles (Santa Teresita de Jes\u00fas)"
    ],
    "wof:name":"Majada Severino Robles (Santa Teresita de Jesus)",
    "wof:placetype":"locality",
    "wof:population":7
},
  "geometry": {"coordinates":[-102.25583,24.48472000000001],"type":"Point"}
}