{
  "type": "Feature",
  "properties": {
    "gn:admin1_code":"10",
    "gn:admin2_code":"13",
    "gn:asciiname":"Santa Rosenda",
    "gn:country_code":"MX",
    "gn:dem":1172,
    "gn:feature_class":"P",
    "gn:feature_code":"PPL",
    "gn:name":"Santa Rosenda",
    "gn:population":24,
    "gn:timezone":"America/Monterrey",
    "iso:country":"MX",
    "wof:name":"Santa Rosenda",
    "wof:placetype":"locality",
    "wof:population":24
},
  "geometry": {"coordinates":[-104.05956999999999,26.58061],"type":"Point"}
}