{
  "type": "Feature",
  "properties": {
    "gn:admin1_code":"26.0",
    "gn:admin2_code":"3.0",
    "gn:asciiname":"Gochico Nuevo",
    "gn:country_code":"MX",
    "gn:dem":642,
    "gn:feature_class":"P",
    "gn:feature_code":"PPL",
    "gn:name":"Gochico Nuevo",
    "gn:population":0,
    "gn:timezone":"America/Hermosillo",
    "iso:country":"MX",
    "name:und_x_variant":[
        "Cochico",
        "Gochico",
        "Gochico Nuevo"
    ],
    "wof:name":"Gochico Nuevo",
    "wof:placetype":"locality"
},
  "geometry": {"coordinates":[-108.69044,27.41224],"type":"Point"}
}