{
  "type": "Feature",
  "properties": {
    "gn:admin1_code":"5",
    "gn:admin2_code":"31.0",
    "gn:asciiname":"Pantelha",
    "gn:country_code":"MX",
    "gn:dem":1174,
    "gn:feature_class":"P",
    "gn:feature_code":"PPL",
    "gn:name":"Pantelh\u00e1",
    "gn:population":305,
    "gn:timezone":"America/Mexico_City",
    "iso:country":"MX",
    "name:und_x_variant":[
        "Pantelh\u00e1"
    ],
    "wof:name":"Pantelha",
    "wof:placetype":"locality",
    "wof:population":305
},
  "geometry": {"coordinates":[-92.27889,17.15556],"type":"Point"}
}