{
  "type": "Feature",
  "properties": {
    "gn:admin1_code":"2.0",
    "gn:admin2_code":"1.0",
    "gn:asciiname":"Chamula",
    "gn:country_code":"MX",
    "gn:dem":11,
    "gn:feature_class":"P",
    "gn:feature_code":"PPL",
    "gn:name":"Chamula",
    "gn:population":0,
    "gn:timezone":"America/Tijuana",
    "iso:country":"MX",
    "name:ceb_x_preferred":[
        "Chamula"
    ],
    "name:deu_x_preferred":[
        "Municipio Chamula"
    ],
    "name:epo_x_preferred":[
        "Chamula"
    ],
    "name:eus_x_preferred":[
        "Chamula"
    ],
    "name:por_x_preferred":[
        "Chamula"
    ],
    "name:rus_x_preferred":[
        "\u0427\u0430\u043c\u0443\u043b\u0430"
    ],
    "name:sco_x_preferred":[
        "Chamula"
    ],
    "name:spa_x_preferred":[
        "Chamula"
    ],
    "name:srp_x_preferred":[
        "\u041e\u043f\u0448\u0442\u0438\u043d\u0430 \u0427\u0430\u043c\u0443\u043b\u0430"
    ],
    "name:swe_x_preferred":[
        "Chamula"
    ],
    "name:urd_x_preferred":[
        "\u0686\u0627\u0645\u0648\u0644\u0627"
    ],
    "name:vie_x_preferred":[
        "Chamula"
    ],
    "wof:name":"Chamula",
    "wof:placetype":"locality"
},
  "geometry": {"coordinates":[-115.89823,30.43643],"type":"Point"}
}