{
  "type": "Feature",
  "properties": {
    "gn:admin1_code":"12",
    "gn:admin2_code":"68.0",
    "gn:asciiname":"El Naranjo",
    "gn:country_code":"MX",
    "gn:dem":175,
    "gn:feature_class":"P",
    "gn:feature_code":"PPL",
    "gn:name":"El Naranjo",
    "gn:population":8,
    "gn:timezone":"America/Mexico_City",
    "iso:country":"MX",
    "wof:name":"El Naranjo",
    "wof:placetype":"locality",
    "wof:population":8
},
  "geometry": {"coordinates":[-101.97750000000001,18.10405],"type":"Point"}
}