{
  "type": "Feature",
  "properties": {
    "gn:admin1_code":"30",
    "gn:admin2_code":"174.0",
    "gn:asciiname":"Buena Vista",
    "gn:country_code":"MX",
    "gn:dem":133,
    "gn:feature_class":"P",
    "gn:feature_code":"PPL",
    "gn:name":"Buena Vista",
    "gn:population":141,
    "gn:timezone":"America/Mexico_City",
    "iso:country":"MX",
    "wof:name":"Buena Vista",
    "wof:placetype":"locality",
    "wof:population":141
},
  "geometry": {"coordinates":[-96.51167,18.61583],"type":"Point"}
}