{
  "type": "Feature",
  "properties": {
    "gn:admin1_code":"21",
    "gn:admin2_code":"172.0",
    "gn:asciiname":"Xaltatempa de Lucas",
    "gn:country_code":"MX",
    "gn:dem":1586,
    "gn:feature_class":"P",
    "gn:feature_code":"PPL",
    "gn:name":"Xaltatempa de Lucas",
    "gn:population":543,
    "gn:timezone":"America/Mexico_City",
    "iso:country":"MX",
    "wof:name":"Xaltatempa de Lucas",
    "wof:placetype":"locality",
    "wof:population":543
},
  "geometry": {"coordinates":[-97.84639,19.87833],"type":"Point"}
}