{
  "type": "Feature",
  "properties": {
    "gn:admin1_code":"10",
    "gn:admin2_code":"35.0",
    "gn:asciiname":"San Ignacio de la Sierra",
    "gn:country_code":"MX",
    "gn:dem":2444,
    "gn:feature_class":"P",
    "gn:feature_code":"PPL",
    "gn:name":"San Ignacio de la Sierra",
    "gn:population":0,
    "gn:timezone":"America/Monterrey",
    "iso:country":"MX",
    "name:und_x_variant":[
        "San Ignacio",
        "San Ignacio de la Sierra"
    ],
    "wof:name":"San Ignacio de la Sierra",
    "wof:placetype":"locality"
},
  "geometry": {"coordinates":[-106.10751999999999,25.45207000000001],"type":"Point"}
}