{
  "type": "Feature",
  "properties": {
    "gn:admin1_code":"19.0",
    "gn:admin2_code":"8.0",
    "gn:asciiname":"Valle del Marques (Sierra Morena)",
    "gn:country_code":"MX",
    "gn:dem":479,
    "gn:feature_class":"P",
    "gn:feature_code":"PPL",
    "gn:name":"Valle del Marqu\u00e9s (Sierra Morena)",
    "gn:population":1,
    "gn:timezone":"America/Monterrey",
    "iso:country":"MX",
    "name:spa_x_preferred":[
        "Valle del Marqu\u00e9s"
    ],
    "name:und_x_variant":[
        "Sierra Morena"
    ],
    "wof:name":"Valle del Marques (Sierra Morena)",
    "wof:placetype":"locality",
    "wof:population":1
},
  "geometry": {"coordinates":[-100.53005,26.53864],"type":"Point"}
}