{
  "type": "Feature",
  "properties": {
    "gn:admin1_code":"27",
    "gn:admin2_code":"15.0",
    "gn:asciiname":"Libertad",
    "gn:country_code":"MX",
    "gn:dem":239,
    "gn:feature_class":"P",
    "gn:feature_code":"PPL",
    "gn:name":"Libertad",
    "gn:population":1042,
    "gn:timezone":"America/Mexico_City",
    "iso:country":"MX",
    "name:spa_x_preferred":[
        "Libertad"
    ],
    "wof:name":"Libertad",
    "wof:placetype":"locality",
    "wof:population":1042
},
  "geometry": {"coordinates":[-92.71502,17.41027],"type":"Point"}
}