{
  "type": "Feature",
  "properties": {
    "gn:admin1_code":"26",
    "gn:admin2_code":"17.0",
    "gn:asciiname":"Vinedo Viva (Pozo 5)",
    "gn:country_code":"MX",
    "gn:dem":221,
    "gn:feature_class":"P",
    "gn:feature_code":"PPL",
    "gn:name":"Vi\u00f1edo Viva (Pozo 5)",
    "gn:population":557,
    "gn:timezone":"America/Hermosillo",
    "iso:country":"MX",
    "name:und_x_variant":[
        "Vi\u00f1edo Viva (Pozo 5)"
    ],
    "wof:name":"Vinedo Viva (Pozo 5)",
    "wof:placetype":"locality",
    "wof:population":557
},
  "geometry": {"coordinates":[-112.32138999999999,30.69778],"type":"Point"}
}