{
  "type": "Feature",
  "properties": {
    "gn:admin1_code":"14",
    "gn:admin2_code":"66.0",
    "gn:asciiname":"Colonia la Granjena",
    "gn:country_code":"MX",
    "gn:dem":1537,
    "gn:feature_class":"P",
    "gn:feature_code":"PPL",
    "gn:name":"Colonia la Granjena",
    "gn:population":336,
    "gn:timezone":"America/Mexico_City",
    "iso:country":"MX",
    "wof:name":"Colonia la Granjena",
    "wof:placetype":"locality",
    "wof:population":336
},
  "geometry": {"coordinates":[-102.79639,20.35167],"type":"Point"}
}