{
  "type": "Feature",
  "properties": {
    "gn:admin1_code":"5",
    "gn:admin2_code":"11.0",
    "gn:asciiname":"Pacayal Viejo",
    "gn:country_code":"MX",
    "gn:dem":1221,
    "gn:feature_class":"P",
    "gn:feature_code":"PPL",
    "gn:name":"Pacayal Viejo",
    "gn:population":0,
    "gn:timezone":"America/Mexico_City",
    "iso:country":"MX",
    "name:spa_x_preferred":[
        "Pacayal"
    ],
    "wof:name":"Pacayal Viejo",
    "wof:placetype":"locality"
},
  "geometry": {"coordinates":[-92.30936,15.63457],"type":"Point"}
}