{
  "type": "Feature",
  "properties": {
    "gn:admin1_code":"21",
    "gn:admin2_code":"19.0",
    "gn:asciiname":"El Encanto del Cerril",
    "gn:country_code":"MX",
    "gn:dem":1898,
    "gn:feature_class":"P",
    "gn:feature_code":"PPL",
    "gn:name":"El Encanto del Cerril",
    "gn:population":2191,
    "gn:timezone":"America/Mexico_City",
    "iso:country":"MX",
    "wof:name":"El Encanto del Cerril",
    "wof:placetype":"locality",
    "wof:population":2191
},
  "geometry": {"coordinates":[-98.42556,18.93194],"type":"Point"}
}