{
  "type": "Feature",
  "properties": {
    "gn:admin1_code":"30.0",
    "gn:asciiname":"Pompal",
    "gn:country_code":"MX",
    "gn:dem":101,
    "gn:feature_class":"P",
    "gn:feature_code":"PPL",
    "gn:name":"Pompal",
    "gn:population":0,
    "gn:timezone":"America/Mexico_City",
    "iso:country":"MX",
    "name:spa_x_preferred":[
        "Pompal"
    ],
    "wof:name":"Pompal",
    "wof:placetype":"locality"
},
  "geometry": {"coordinates":[-95.00969000000001,17.84505],"type":"Point"}
}