{
  "type": "Feature",
  "properties": {
    "gn:admin1_code":"16",
    "gn:admin2_code":"35",
    "gn:asciiname":"San Ignacio",
    "gn:country_code":"MX",
    "gn:dem":746,
    "gn:feature_class":"P",
    "gn:feature_code":"PPL",
    "gn:name":"San Ignacio",
    "gn:population":39,
    "gn:timezone":"America/Mexico_City",
    "iso:country":"MX",
    "wof:name":"San Ignacio",
    "wof:placetype":"locality",
    "wof:population":39
},
  "geometry": {"coordinates":[-101.67972,18.93889],"type":"Point"}
}