{
  "type": "Feature",
  "properties": {
    "gn:admin1_code":"7",
    "gn:admin2_code":"17",
    "gn:asciiname":"Lazaro Cardenas (Benito Juarez Seis)",
    "gn:country_code":"MX",
    "gn:dem":1106,
    "gn:feature_class":"P",
    "gn:feature_code":"PPL",
    "gn:name":"L\u00e1zaro C\u00e1rdenas (Benito Ju\u00e1rez Seis)",
    "gn:population":11,
    "gn:timezone":"America/Monterrey",
    "iso:country":"MX",
    "name:und_x_variant":[
        "L\u00e1zaro C\u00e1rdenas (Benito Ju\u00e1rez Seis)"
    ],
    "wof:name":"Lazaro Cardenas (Benito Juarez Seis)",
    "wof:placetype":"locality",
    "wof:population":11
},
  "geometry": {"coordinates":[-103.10284,25.52444],"type":"Point"}
}