{
  "type": "Feature",
  "properties": {
    "gn:admin1_code":"6",
    "gn:admin2_code":"27",
    "gn:asciiname":"Los Tordillos",
    "gn:country_code":"MX",
    "gn:dem":2410,
    "gn:feature_class":"P",
    "gn:feature_code":"PPL",
    "gn:name":"Los Tordillos",
    "gn:population":20,
    "gn:timezone":"America/Chihuahua",
    "iso:country":"MX",
    "wof:name":"Los Tordillos",
    "wof:placetype":"locality",
    "wof:population":20
},
  "geometry": {"coordinates":[-107.09989,26.84188],"type":"Point"}
}