{
  "type": "Feature",
  "properties": {
    "gn:admin1_code":"31",
    "gn:admin2_code":"32.0",
    "gn:asciiname":"Holca",
    "gn:country_code":"MX",
    "gn:dem":28,
    "gn:feature_class":"P",
    "gn:feature_code":"PPL",
    "gn:name":"Holc\u00e1",
    "gn:population":552,
    "gn:timezone":"America/Merida",
    "iso:country":"MX",
    "name:spa_x_preferred":[
        "Holc\u00e1"
    ],
    "name:spa_x_variant":[
        "Holca"
    ],
    "wof:name":"Holca",
    "wof:placetype":"locality",
    "wof:population":552
},
  "geometry": {"coordinates":[-88.26881999999998,21.09153],"type":"Point"}
}