{
  "type": "Feature",
  "properties": {
    "gn:admin1_code":"20",
    "gn:admin2_code":"453.0",
    "gn:asciiname":"Lumpeme",
    "gn:country_code":"MX",
    "gn:dem":142,
    "gn:feature_class":"P",
    "gn:feature_code":"PPL",
    "gn:name":"Lumpeme",
    "gn:population":0,
    "gn:timezone":"America/Mexico_City",
    "iso:country":"MX",
    "wof:name":"Lumpeme",
    "wof:placetype":"locality"
},
  "geometry": {"coordinates":[-95.58333,16.01667],"type":"Point"}
}