{
  "type": "Feature",
  "properties": {
    "gn:admin1_code":"21",
    "gn:admin2_code":"183.0",
    "gn:asciiname":"Tzitzicazapa",
    "gn:country_code":"MX",
    "gn:dem":1041,
    "gn:feature_class":"P",
    "gn:feature_code":"PPL",
    "gn:name":"Tzitzicazapa",
    "gn:population":704,
    "gn:timezone":"America/Mexico_City",
    "iso:country":"MX",
    "wof:name":"Tzitzicazapa",
    "wof:placetype":"locality",
    "wof:population":704
},
  "geometry": {"coordinates":[-97.93778,20.20333],"type":"Point"}
}