{
  "type": "Feature",
  "properties": {
    "gn:admin1_code":"8",
    "gn:admin2_code":"9.0",
    "gn:asciiname":"Las Parotas (Humberto Vargas)",
    "gn:country_code":"MX",
    "gn:dem":20,
    "gn:feature_class":"P",
    "gn:feature_code":"PPL",
    "gn:name":"Las Parotas (Humberto Vargas)",
    "gn:population":7,
    "gn:timezone":"America/Mexico_City",
    "iso:country":"MX",
    "wof:name":"Las Parotas (Humberto Vargas)",
    "wof:placetype":"locality",
    "wof:population":7
},
  "geometry": {"coordinates":[-103.72611000000001,18.7725],"type":"Point"}
}