{
  "type": "Feature",
  "properties": {
    "gn:admin1_code":"14.0",
    "gn:admin2_code":"13.0",
    "gn:asciiname":"El Valle",
    "gn:country_code":"MX",
    "gn:dem":1552,
    "gn:feature_class":"P",
    "gn:feature_code":"PPL",
    "gn:name":"El Valle",
    "gn:population":0,
    "gn:timezone":"America/Mexico_City",
    "iso:country":"MX",
    "name:ast_x_preferred":[
        "El Valle"
    ],
    "name:ceb_x_preferred":[
        "El Valle"
    ],
    "name:deu_x_preferred":[
        "El Valle"
    ],
    "name:fra_x_preferred":[
        "El Valle"
    ],
    "name:jpn_x_preferred":[
        "\u30a8\u30eb\u30d0\u30b8\u30a7"
    ],
    "name:nld_x_preferred":[
        "El Valle"
    ],
    "name:spa_x_preferred":[
        "El Valle"
    ],
    "name:swe_x_preferred":[
        "El Valle"
    ],
    "wof:name":"El Valle",
    "wof:placetype":"locality"
},
  "geometry": {"coordinates":[-102.51667,20.48333],"type":"Point"}
}