{
  "type": "Feature",
  "properties": {
    "gn:admin1_code":"10",
    "gn:admin2_code":"10.0",
    "gn:asciiname":"Los Jarales",
    "gn:country_code":"MX",
    "gn:dem":1875,
    "gn:feature_class":"P",
    "gn:feature_code":"PPL",
    "gn:name":"Los Jarales",
    "gn:population":0,
    "gn:timezone":"America/Monterrey",
    "iso:country":"MX",
    "name:spa_x_preferred":[
        "Los Jarales"
    ],
    "wof:name":"Los Jarales",
    "wof:placetype":"locality"
},
  "geometry": {"coordinates":[-105.09493999999999,26.2008],"type":"Point"}
}