{
  "type": "Feature",
  "properties": {
    "gn:admin1_code":"6.0",
    "gn:admin2_code":"15.0",
    "gn:asciiname":"El Fortin",
    "gn:country_code":"MX",
    "gn:dem":953,
    "gn:feature_class":"P",
    "gn:feature_code":"PPL",
    "gn:name":"El Fort\u00edn",
    "gn:population":0,
    "gn:timezone":"America/Chihuahua",
    "iso:country":"MX",
    "name:spa_x_preferred":[
        "El Fort\u00edn"
    ],
    "name:und_x_variant":[
        "Rancho el Fort\u00edn"
    ],
    "wof:name":"El Fortin",
    "wof:placetype":"locality"
},
  "geometry": {"coordinates":[-104.92658,29.56166],"type":"Point"}
}