{
  "type": "Feature",
  "properties": {
    "gn:admin1_code":"10",
    "gn:admin2_code":"26.0",
    "gn:asciiname":"Mala Noche",
    "gn:country_code":"MX",
    "gn:dem":967,
    "gn:feature_class":"P",
    "gn:feature_code":"PPL",
    "gn:name":"Mala Noche",
    "gn:population":0,
    "gn:timezone":"America/Monterrey",
    "iso:country":"MX",
    "name:spa_x_preferred":[
        "Mala Noche"
    ],
    "wof:name":"Mala Noche",
    "wof:placetype":"locality"
},
  "geometry": {"coordinates":[-105.75367,23.90682],"type":"Point"}
}