{
  "type": "Feature",
  "properties": {
    "gn:admin1_code":"7.0",
    "gn:admin2_code":"18.0",
    "gn:asciiname":"Canas",
    "gn:country_code":"MX",
    "gn:dem":651,
    "gn:feature_class":"P",
    "gn:feature_code":"PPL",
    "gn:name":"Ca\u00f1as",
    "gn:population":0,
    "gn:timezone":"America/Monterrey",
    "iso:country":"MX",
    "name:ceb_x_preferred":[
        "Canas"
    ],
    "name:deu_x_preferred":[
        "Canas"
    ],
    "name:nld_x_preferred":[
        "Canas"
    ],
    "name:por_x_preferred":[
        "Canas"
    ],
    "name:ron_x_preferred":[
        "Canas"
    ],
    "name:rus_x_preferred":[
        "\u041a\u0430\u043d\u0430\u0441"
    ],
    "name:spa_x_preferred":[
        "Ca\u00f1as"
    ],
    "name:swe_x_preferred":[
        "Canas"
    ],
    "wof:name":"Canas",
    "wof:placetype":"locality"
},
  "geometry": {"coordinates":[-101.34077000000001,26.91486],"type":"Point"}
}