{
  "type": "Feature",
  "properties": {
    "gn:admin1_code":"12",
    "gn:admin2_code":"57.0",
    "gn:asciiname":"La Palma de Cayaco (La Cayaca)",
    "gn:country_code":"MX",
    "gn:dem":92,
    "gn:feature_class":"P",
    "gn:feature_code":"PPL",
    "gn:name":"La Palma de Cayaco (La Cayaca)",
    "gn:population":71,
    "gn:timezone":"America/Mexico_City",
    "iso:country":"MX",
    "wof:name":"La Palma de Cayaco (La Cayaca)",
    "wof:placetype":"locality",
    "wof:population":71
},
  "geometry": {"coordinates":[-100.58463999999999,17.22876],"type":"Point"}
}