{
  "type": "Feature",
  "properties": {
    "gn:admin1_code":"28.0",
    "gn:asciiname":"La Chencha",
    "gn:country_code":"MX",
    "gn:dem":384,
    "gn:feature_class":"P",
    "gn:feature_code":"PPL",
    "gn:name":"La Chencha",
    "gn:population":0,
    "gn:timezone":"America/Monterrey",
    "iso:country":"MX",
    "name:spa_x_preferred":[
        "La Chencha"
    ],
    "wof:name":"La Chencha",
    "wof:placetype":"locality"
},
  "geometry": {"coordinates":[-99.53681,24.6218],"type":"Point"}
}