{
  "type": "Feature",
  "properties": {
    "iso:country":"MX",
    "ne:ADM0CAP":0.0,
    "ne:ADM0NAME":"Mexico",
    "ne:ADM0_A3":"MEX",
    "ne:ADM1NAME":"Durango",
    "ne:ADMIN1_COD":10,
    "ne:CAPALT":0,
    "ne:CHANGED":0,
    "ne:CHECKME":0,
    "ne:COMPARE":0,
    "ne:DIFFASCII":0,
    "ne:ELEVATION":0.0,
    "ne:FEATURECLA":"Populated place",
    "ne:FEATURE_CL":"P",
    "ne:FEATURE_CO":"PPL",
    "ne:GEONAMEID":3985327,
    "ne:GEONAMESNO":"GeoNames spatial join with similar names only.",
    "ne:GN_ASCII":"San Miguel Papasquiaro",
    "ne:GN_POP":22750,
    "ne:GTOPO30":1843.0,
    "ne:ISO_A2":"MX",
    "ne:LABELRANK":2,
    "ne:LATITUDE":24.830408,
    "ne:LONGITUDE":-105.339989,
    "ne:LS_MATCH":1,
    "ne:LS_NAME":"Papasquiaro",
    "ne:MAX_AREAKM":1.0,
    "ne:MAX_AREAMI":0.0,
    "ne:MAX_BBXMAX":-105.333333,
    "ne:MAX_BBXMIN":-105.341667,
    "ne:MAX_BBYMAX":24.833333,
    "ne:MAX_BBYMIN":24.825,
    "ne:MAX_NATSCA":20.0,
    "ne:MAX_PERKM":4.0,
    "ne:MAX_PERMI":2.0,
    "ne:MAX_POP10":521,
    "ne:MAX_POP20":521,
    "ne:MAX_POP300":0,
    "ne:MAX_POP310":0,
    "ne:MAX_POP50":0,
    "ne:MEAN_BBXC":-105.3375,
    "ne:MEAN_BBYC":24.829167,
    "ne:MEGACITY":0,
    "ne:MIN_AREAKM":1.0,
    "ne:MIN_AREAMI":0.0,
    "ne:MIN_BBXMAX":-105.333333,
    "ne:MIN_BBXMIN":-105.341667,
    "ne:MIN_BBYMAX":24.833333,
    "ne:MIN_BBYMIN":24.825,
    "ne:MIN_PERKM":4.0,
    "ne:MIN_PERMI":2.0,
    "ne:NAME":"Papasquiaro",
    "ne:NAMEASCII":"Papasquiaro",
    "ne:NAMEDIFF":0,
    "ne:NATSCALE":20,
    "ne:POP1950":0,
    "ne:POP1955":0,
    "ne:POP1960":0,
    "ne:POP1965":0,
    "ne:POP1970":0,
    "ne:POP1975":0,
    "ne:POP1980":0,
    "ne:POP1985":0,
    "ne:POP1990":0,
    "ne:POP1995":0,
    "ne:POP2000":0,
    "ne:POP2005":0,
    "ne:POP2010":0,
    "ne:POP2015":0,
    "ne:POP2020":0,
    "ne:POP2025":0,
    "ne:POP2050":0,
    "ne:POP_MAX":22750,
    "ne:POP_MIN":521,
    "ne:POP_OTHER":521,
    "ne:RANK_MAX":7,
    "ne:RANK_MIN":2,
    "ne:SCALERANK":7,
    "ne:SOV0NAME":"Mexico",
    "ne:SOV_A3":"MEX",
    "ne:TIMEZONE":"America/Monterrey",
    "ne:UN_FID":0,
    "ne:UN_LAT":0.0,
    "ne:UN_LONG":0.0,
    "ne:WORLDCITY":0,
    "ne:min_zoom":6.7,
    "wof:name":"Papasquiaro",
    "wof:placetype":"locality"
},
  "geometry": {"coordinates":[-105.33998905619802,24.83040814106636],"type":"Point"}
}