{
  "type": "Feature",
  "properties": {
    "gn:admin1_code":"28",
    "gn:admin2_code":"17.0",
    "gn:asciiname":"Rancho Nuevo Canitas",
    "gn:country_code":"MX",
    "gn:dem":634,
    "gn:feature_class":"P",
    "gn:feature_code":"PPL",
    "gn:name":"Rancho Nuevo Ca\u00f1itas",
    "gn:population":0,
    "gn:timezone":"America/Monterrey",
    "iso:country":"MX",
    "name:spa_x_preferred":[
        "Rancho Nuevo Ca\u00f1itas"
    ],
    "wof:name":"Rancho Nuevo Canitas",
    "wof:placetype":"locality"
},
  "geometry": {"coordinates":[-99.30846,23.47978],"type":"Point"}
}