{
  "type": "Feature",
  "properties": {
    "gn:admin1_code":"15",
    "gn:admin2_code":"5.0",
    "gn:asciiname":"El Rio",
    "gn:country_code":"MX",
    "gn:dem":2558,
    "gn:feature_class":"P",
    "gn:feature_code":"PPL",
    "gn:name":"El R\u00edo",
    "gn:population":0,
    "gn:timezone":"America/Mexico_City",
    "iso:country":"MX",
    "wof:name":"El Rio",
    "wof:placetype":"locality"
},
  "geometry": {"coordinates":[-99.75763999999999,19.46131],"type":"Point"}
}