{
  "type": "Feature",
  "properties": {
    "gn:admin1_code":"21",
    "gn:admin2_code":"197.0",
    "gn:asciiname":"Los Arroyos",
    "gn:country_code":"MX",
    "gn:dem":386,
    "gn:feature_class":"P",
    "gn:feature_code":"PPL",
    "gn:name":"Los Arroyos",
    "gn:population":124,
    "gn:timezone":"America/Mexico_City",
    "iso:country":"MX",
    "wof:name":"Los Arroyos",
    "wof:placetype":"locality",
    "wof:population":124
},
  "geometry": {"coordinates":[-97.89073999999999,20.30217],"type":"Point"}
}