{
  "type": "Feature",
  "properties": {
    "gn:admin1_code":"24",
    "gn:admin2_code":"33.0",
    "gn:asciiname":"Rancho Cinco Hermanos (La Tapona)",
    "gn:country_code":"MX",
    "gn:dem":1988,
    "gn:feature_class":"P",
    "gn:feature_code":"PPL",
    "gn:name":"Rancho Cinco Hermanos (La Tapona)",
    "gn:population":16,
    "gn:timezone":"America/Mexico_City",
    "iso:country":"MX",
    "wof:name":"Rancho Cinco Hermanos (La Tapona)",
    "wof:placetype":"locality",
    "wof:population":16
},
  "geometry": {"coordinates":[-101.67956,23.3482],"type":"Point"}
}