{
  "type": "Feature",
  "properties": {
    "gn:admin1_code":"16",
    "gn:admin2_code":"99.0",
    "gn:asciiname":"Ojo de Agua de la Gallina",
    "gn:country_code":"MX",
    "gn:dem":639,
    "gn:feature_class":"P",
    "gn:feature_code":"PPL",
    "gn:name":"Ojo de Agua de la Gallina",
    "gn:population":0,
    "gn:timezone":"America/Mexico_City",
    "iso:country":"MX",
    "name:spa_x_preferred":[
        "Ojo de Agua de la Gallina"
    ],
    "wof:name":"Ojo de Agua de la Gallina",
    "wof:placetype":"locality"
},
  "geometry": {"coordinates":[-100.71675999999999,19.20686],"type":"Point"}
}