{
  "type": "Feature",
  "properties": {
    "gn:admin1_code":"20",
    "gn:admin2_code":"227",
    "gn:asciiname":"El Paston",
    "gn:country_code":"MX",
    "gn:dem":1574,
    "gn:feature_class":"P",
    "gn:feature_code":"PPL",
    "gn:name":"El Past\u00f3n",
    "gn:population":32,
    "gn:timezone":"America/Mexico_City",
    "iso:country":"MX",
    "name:und_x_variant":[
        "El Past\u00f3n"
    ],
    "wof:name":"El Paston",
    "wof:placetype":"locality",
    "wof:population":32
},
  "geometry": {"coordinates":[-96.77916999999999,17.13111],"type":"Point"}
}