{
  "type": "Feature",
  "properties": {
    "gn:admin1_code":"15.0",
    "gn:asciiname":"El Rincon de Don Pedro",
    "gn:country_code":"MX",
    "gn:dem":2153,
    "gn:feature_class":"P",
    "gn:feature_code":"PPL",
    "gn:name":"El Rinc\u00f3n de Don Pedro",
    "gn:population":0,
    "gn:timezone":"America/Mexico_City",
    "iso:country":"MX",
    "name:spa_x_preferred":[
        "El Rinc\u00f3n de Don Pedro"
    ],
    "wof:name":"El Rincon de Don Pedro",
    "wof:placetype":"locality"
},
  "geometry": {"coordinates":[-101.47026,20.04997],"type":"Point"}
}