{
  "type": "Feature",
  "properties": {
    "gn:admin1_code":"30",
    "gn:admin2_code":"84.0",
    "gn:asciiname":"Chapabaya",
    "gn:country_code":"MX",
    "gn:dem":5,
    "gn:feature_class":"P",
    "gn:feature_code":"PPL",
    "gn:name":"Chapabaya",
    "gn:population":0,
    "gn:timezone":"America/Mexico_City",
    "iso:country":"MX",
    "name:spa_x_preferred":[
        "Chapabaya"
    ],
    "name:und_x_variant":[
        "Chapa Baya"
    ],
    "wof:name":"Chapabaya",
    "wof:placetype":"locality"
},
  "geometry": {"coordinates":[-95.86065000000001,18.46901],"type":"Point"}
}