{
  "type": "Feature",
  "properties": {
    "gn:admin1_code":"10",
    "gn:admin2_code":"31.0",
    "gn:asciiname":"La Milpa",
    "gn:country_code":"MX",
    "gn:dem":1733,
    "gn:feature_class":"P",
    "gn:feature_code":"PPL",
    "gn:name":"La Milpa",
    "gn:population":0,
    "gn:timezone":"America/Monterrey",
    "iso:country":"MX",
    "name:spa_x_preferred":[
        "La Milpa"
    ],
    "name:und_x_variant":[
        "Milpa",
        "Milpas"
    ],
    "wof:name":"La Milpa",
    "wof:placetype":"locality"
},
  "geometry": {"coordinates":[-103.3412,24.5438],"type":"Point"}
}