{
  "type": "Feature",
  "properties": {
    "gn:admin1_code":"10.0",
    "gn:admin2_code":"6.0",
    "gn:asciiname":"Anton Martin",
    "gn:country_code":"MX",
    "gn:dem":1492,
    "gn:feature_class":"P",
    "gn:feature_code":"PPL",
    "gn:name":"Ant\u00f3n Mart\u00edn",
    "gn:population":169,
    "gn:timezone":"America/Monterrey",
    "iso:country":"MX",
    "name:spa_x_preferred":[
        "Aguaje de San Mart\u00edn"
    ],
    "name:und_x_variant":[
        "Ant\u00f3n Mart\u00edn"
    ],
    "wof:name":"Anton Martin",
    "wof:placetype":"locality",
    "wof:population":169
},
  "geometry": {"coordinates":[-103.26979,24.77442000000001],"type":"Point"}
}