{
  "type": "Feature",
  "properties": {
    "gn:admin1_code":"20.0",
    "gn:admin2_code":"266.0",
    "gn:asciiname":"Majahual",
    "gn:country_code":"MX",
    "gn:dem":29,
    "gn:feature_class":"P",
    "gn:feature_code":"PPL",
    "gn:name":"Majahual",
    "gn:population":0,
    "gn:timezone":"America/Mexico_City",
    "iso:country":"MX",
    "name:spa_x_preferred":[
        "Majahual"
    ],
    "wof:name":"Majahual",
    "wof:placetype":"locality"
},
  "geometry": {"coordinates":[-96.01663000000001,15.80867],"type":"Point"}
}