{
  "type": "Feature",
  "properties": {
    "gn:admin1_code":"20",
    "gn:admin2_code":"176",
    "gn:asciiname":"Chaxenga",
    "gn:country_code":"MX",
    "gn:dem":2358,
    "gn:feature_class":"P",
    "gn:feature_code":"PPL",
    "gn:name":"Chaxenga",
    "gn:population":23,
    "gn:timezone":"America/Mexico_City",
    "iso:country":"MX",
    "wof:name":"Chaxenga",
    "wof:placetype":"locality",
    "wof:population":23
},
  "geometry": {"coordinates":[-97.28389,17.68778],"type":"Point"}
}