{
  "type": "Feature",
  "properties": {
    "gn:admin1_code":"16",
    "gn:admin2_code":"2.0",
    "gn:asciiname":"Tepostan",
    "gn:country_code":"MX",
    "gn:dem":1476,
    "gn:feature_class":"P",
    "gn:feature_code":"PPL",
    "gn:name":"Tepost\u00e1n",
    "gn:population":0,
    "gn:timezone":"America/Mexico_City",
    "iso:country":"MX",
    "name:und_x_variant":[
        "Tepozt\u00e1n",
        "Tepost\u00e1n"
    ],
    "wof:name":"Tepostan",
    "wof:placetype":"locality"
},
  "geometry": {"coordinates":[-102.68007,18.68241],"type":"Point"}
}