{
  "type": "Feature",
  "properties": {
    "gn:admin1_code":"5",
    "gn:admin2_code":"76",
    "gn:asciiname":"El Capuyil",
    "gn:country_code":"MX",
    "gn:dem":366,
    "gn:feature_class":"P",
    "gn:feature_code":"PPL",
    "gn:name":"El Capuyil",
    "gn:population":49,
    "gn:timezone":"America/Mexico_City",
    "iso:country":"MX",
    "wof:name":"El Capuyil",
    "wof:placetype":"locality",
    "wof:population":49
},
  "geometry": {"coordinates":[-92.59028000000001,17.32361],"type":"Point"}
}