{
  "type": "Feature",
  "properties": {
    "gn:admin1_code":"31.0",
    "gn:asciiname":"Bondzonot Numero Dos",
    "gn:country_code":"MX",
    "gn:dem":15,
    "gn:feature_class":"P",
    "gn:feature_code":"PPL",
    "gn:name":"Bondzonot N\u00famero Dos",
    "gn:population":0,
    "gn:timezone":"America/Merida",
    "iso:country":"MX",
    "name:spa_x_preferred":[
        "Bondzonot N\u00famero Dos"
    ],
    "wof:name":"Bondzonot Numero Dos",
    "wof:placetype":"locality"
},
  "geometry": {"coordinates":[-88.09076,21.24218],"type":"Point"}
}