{
  "type": "Feature",
  "properties": {
    "gn:admin1_code":"24.0",
    "gn:admin2_code":"13.0",
    "gn:asciiname":"El Competidor",
    "gn:country_code":"MX",
    "gn:dem":266,
    "gn:feature_class":"P",
    "gn:feature_code":"PPL",
    "gn:name":"El Competidor",
    "gn:population":0,
    "gn:timezone":"America/Mexico_City",
    "iso:country":"MX",
    "name:spa_x_preferred":[
        "El Competidor"
    ],
    "wof:name":"El Competidor",
    "wof:placetype":"locality"
},
  "geometry": {"coordinates":[-99.20835,22.0173],"type":"Point"}
}