{
  "type": "Feature",
  "properties": {
    "gn:admin1_code":"19",
    "gn:admin2_code":"49.0",
    "gn:asciiname":"Las Manzanillas",
    "gn:country_code":"MX",
    "gn:dem":2084,
    "gn:feature_class":"P",
    "gn:feature_code":"PPL",
    "gn:name":"Las Manzanillas",
    "gn:population":11,
    "gn:timezone":"America/Monterrey",
    "iso:country":"MX",
    "name:spa_x_preferred":[
        "Las Manzanillas"
    ],
    "wof:name":"Las Manzanillas",
    "wof:placetype":"locality",
    "wof:population":11
},
  "geometry": {"coordinates":[-100.40807,25.35339],"type":"Point"}
}