{
  "type": "Feature",
  "properties": {
    "gn:admin1_code":"16",
    "gn:admin2_code":"101.0",
    "gn:asciiname":"Los Ailes",
    "gn:country_code":"MX",
    "gn:dem":1932,
    "gn:feature_class":"P",
    "gn:feature_code":"PPL",
    "gn:name":"Los Ailes",
    "gn:population":9,
    "gn:timezone":"America/Mexico_City",
    "iso:country":"MX",
    "wof:name":"Los Ailes",
    "wof:placetype":"locality",
    "wof:population":9
},
  "geometry": {"coordinates":[-100.94417,19.59861],"type":"Point"}
}