{
  "type": "Feature",
  "properties": {
    "gn:admin1_code":"16.0",
    "gn:admin2_code":"97.0",
    "gn:asciiname":"Cieneguitas",
    "gn:country_code":"MX",
    "gn:dem":1872,
    "gn:feature_class":"P",
    "gn:feature_code":"PPL",
    "gn:name":"Cieneguitas",
    "gn:population":0,
    "gn:timezone":"America/Mexico_City",
    "iso:country":"MX",
    "wof:name":"Cieneguitas",
    "wof:placetype":"locality"
},
  "geometry": {"coordinates":[-101.60833,19.08333],"type":"Point"}
}