{
  "type": "Feature",
  "properties": {
    "gn:admin1_code":"7.0",
    "gn:admin2_code":"31.0",
    "gn:asciiname":"El Limon",
    "gn:country_code":"MX",
    "gn:dem":965,
    "gn:feature_class":"P",
    "gn:feature_code":"PPL",
    "gn:name":"El Lim\u00f3n",
    "gn:population":0,
    "gn:timezone":"America/Monterrey",
    "iso:country":"MX",
    "wof:name":"El Limon",
    "wof:placetype":"locality"
},
  "geometry": {"coordinates":[-101.86667,27.71667],"type":"Point"}
}