{
  "type": "Feature",
  "properties": {
    "gn:admin1_code":"6",
    "gn:admin2_code":"27.0",
    "gn:asciiname":"Choachique",
    "gn:country_code":"MX",
    "gn:dem":2056,
    "gn:feature_class":"P",
    "gn:feature_code":"PPL",
    "gn:name":"Choachique",
    "gn:population":0,
    "gn:timezone":"America/Chihuahua",
    "iso:country":"MX",
    "name:spa_x_preferred":[
        "Choachique"
    ],
    "wof:name":"Choachique",
    "wof:placetype":"locality"
},
  "geometry": {"coordinates":[-107.51094000000001,27.2007],"type":"Point"}
}