{
  "type": "Feature",
  "properties": {
    "gn:admin1_code":"12.0",
    "gn:admin2_code":"30.0",
    "gn:asciiname":"Los Achiotes",
    "gn:country_code":"MX",
    "gn:dem":40,
    "gn:feature_class":"P",
    "gn:feature_code":"PPL",
    "gn:name":"Los Achiotes",
    "gn:population":0,
    "gn:timezone":"America/Mexico_City",
    "iso:country":"MX",
    "name:spa_x_preferred":[
        "Los Achiotes"
    ],
    "wof:name":"Los Achiotes",
    "wof:placetype":"locality"
},
  "geometry": {"coordinates":[-99.15505,16.75218],"type":"Point"}
}