{
  "type": "Feature",
  "properties": {
    "gn:admin1_code":"12",
    "gn:admin2_code":"14",
    "gn:asciiname":"La Brecha",
    "gn:country_code":"MX",
    "gn:dem":19,
    "gn:feature_class":"P",
    "gn:feature_code":"PPL",
    "gn:name":"La Brecha",
    "gn:population":14,
    "gn:timezone":"America/Mexico_City",
    "iso:country":"MX",
    "wof:name":"La Brecha",
    "wof:placetype":"locality",
    "wof:population":14
},
  "geometry": {"coordinates":[-100.44978999999999,17.11556],"type":"Point"}
}