{
  "type": "Feature",
  "properties": {
    "gn:admin1_code":"10",
    "gn:admin2_code":"32.0",
    "gn:asciiname":"La Madre Juana",
    "gn:country_code":"MX",
    "gn:dem":2392,
    "gn:feature_class":"P",
    "gn:feature_code":"PPL",
    "gn:name":"La Madre Juana",
    "gn:population":6,
    "gn:timezone":"America/Monterrey",
    "iso:country":"MX",
    "wof:name":"La Madre Juana",
    "wof:placetype":"locality",
    "wof:population":6
},
  "geometry": {"coordinates":[-105.50894,24.68972],"type":"Point"}
}