{
  "type": "Feature",
  "properties": {
    "gn:admin1_code":"6.0",
    "gn:admin2_code":"63.0",
    "gn:asciiname":"La Junta",
    "gn:country_code":"MX",
    "gn:dem":1782,
    "gn:feature_class":"P",
    "gn:feature_code":"PPL",
    "gn:name":"La Junta",
    "gn:population":4,
    "gn:timezone":"America/Chihuahua",
    "iso:country":"MX",
    "name:spa_x_preferred":[
        "La Junta"
    ],
    "wof:name":"La Junta",
    "wof:placetype":"locality",
    "wof:population":4
},
  "geometry": {"coordinates":[-107.94173000000001,28.9188],"type":"Point"}
}