{
  "type": "Feature",
  "properties": {
    "gn:admin1_code":"24",
    "gn:admin2_code":"16.0",
    "gn:asciiname":"Rancho las Animas",
    "gn:country_code":"MX",
    "gn:dem":60,
    "gn:feature_class":"P",
    "gn:feature_code":"PPL",
    "gn:name":"Rancho las \u00c1nimas",
    "gn:population":5,
    "gn:timezone":"America/Mexico_City",
    "iso:country":"MX",
    "name:und_x_variant":[
        "Rancho las \u00c1nimas"
    ],
    "wof:name":"Rancho las Animas",
    "wof:placetype":"locality",
    "wof:population":5
},
  "geometry": {"coordinates":[-98.59944,22.28333],"type":"Point"}
}