{
  "type": "Feature",
  "properties": {
    "gn:admin1_code":"5",
    "gn:admin2_code":"2.0",
    "gn:asciiname":"La Rocallosa",
    "gn:country_code":"MX",
    "gn:dem":406,
    "gn:feature_class":"P",
    "gn:feature_code":"PPL",
    "gn:name":"La Rocallosa",
    "gn:population":5,
    "gn:timezone":"America/Mexico_City",
    "iso:country":"MX",
    "wof:name":"La Rocallosa",
    "wof:placetype":"locality",
    "wof:population":5
},
  "geometry": {"coordinates":[-92.80694,16.54639],"type":"Point"}
}