{
  "type": "Feature",
  "properties": {
    "gn:admin1_code":"6.0",
    "gn:admin2_code":"7.0",
    "gn:asciiname":"Chiquihuite",
    "gn:country_code":"MX",
    "gn:dem":2274,
    "gn:feature_class":"P",
    "gn:feature_code":"PPL",
    "gn:name":"Chiquihuite",
    "gn:population":0,
    "gn:timezone":"America/Chihuahua",
    "iso:country":"MX",
    "wof:name":"Chiquihuite",
    "wof:placetype":"locality"
},
  "geometry": {"coordinates":[-106.64055999999999,26.87124],"type":"Point"}
}