{
  "type": "Feature",
  "properties": {
    "gn:admin1_code":"23",
    "gn:admin2_code":"8",
    "gn:asciiname":"Guadalupano",
    "gn:country_code":"MX",
    "gn:dem":10,
    "gn:feature_class":"P",
    "gn:feature_code":"PPL",
    "gn:name":"Guadalupano",
    "gn:population":18,
    "gn:timezone":"America/Cancun",
    "iso:country":"MX",
    "wof:name":"Guadalupano",
    "wof:placetype":"locality",
    "wof:population":18
},
  "geometry": {"coordinates":[-87.12056,20.59861],"type":"Point"}
}