{
  "type": "Feature",
  "properties": {
    "gn:admin1_code":"26",
    "gn:admin2_code":"39.0",
    "gn:asciiname":"San Pedro Palomina",
    "gn:country_code":"MX",
    "gn:dem":1350,
    "gn:feature_class":"P",
    "gn:feature_code":"PPL",
    "gn:name":"San Pedro Palomina",
    "gn:population":0,
    "gn:timezone":"America/Hermosillo",
    "iso:country":"MX",
    "name:und_x_variant":[
        "San Pedro"
    ],
    "wof:name":"San Pedro Palomina",
    "wof:placetype":"locality"
},
  "geometry": {"coordinates":[-110.18742,31.23908],"type":"Point"}
}