{
  "type": "Feature",
  "properties": {
    "gn:admin1_code":"2",
    "gn:admin2_code":"1.0",
    "gn:asciiname":"Ejido Valle de la Trinidad",
    "gn:country_code":"MX",
    "gn:dem":735,
    "gn:feature_class":"P",
    "gn:feature_code":"PPL",
    "gn:name":"Ejido Valle de la Trinidad",
    "gn:population":0,
    "gn:timezone":"America/Tijuana",
    "iso:country":"MX",
    "name:spa_x_preferred":[
        "Ejido Valle de la Trinidad"
    ],
    "name:und_x_variant":[
        "Valle la Trinidad"
    ],
    "wof:name":"Ejido Valle de la Trinidad",
    "wof:placetype":"locality"
},
  "geometry": {"coordinates":[-115.77757,31.38919000000001],"type":"Point"}
}