{
  "type": "Feature",
  "properties": {
    "gn:admin1_code":"2",
    "gn:admin2_code":"1.0",
    "gn:asciiname":"San Antonio [Vinedos]",
    "gn:country_code":"MX",
    "gn:dem":246,
    "gn:feature_class":"P",
    "gn:feature_code":"PPL",
    "gn:name":"San Antonio [Vi\u00f1edos]",
    "gn:population":6,
    "gn:timezone":"America/Tijuana",
    "iso:country":"MX",
    "name:und_x_variant":[
        "San Antonio [Vi\u00f1edos]"
    ],
    "wof:name":"San Antonio [Vinedos]",
    "wof:placetype":"locality",
    "wof:population":6
},
  "geometry": {"coordinates":[-116.66222,31.96778],"type":"Point"}
}