{
  "type": "Feature",
  "properties": {
    "gn:admin1_code":"5.0",
    "gn:admin2_code":"9.0",
    "gn:asciiname":"San Angel",
    "gn:country_code":"MX",
    "gn:dem":7,
    "gn:feature_class":"P",
    "gn:feature_code":"PPL",
    "gn:name":"San Angel",
    "gn:population":0,
    "gn:timezone":"America/Mexico_City",
    "iso:country":"MX",
    "name:spa_x_preferred":[
        "San Angel"
    ],
    "wof:name":"San Angel",
    "wof:placetype":"locality"
},
  "geometry": {"coordinates":[-94.0545,16.15276],"type":"Point"}
}