{
  "type": "Feature",
  "properties": {
    "gn:admin1_code":"19",
    "gn:admin2_code":"42.0",
    "gn:asciiname":"El Resbaladero",
    "gn:country_code":"MX",
    "gn:dem":182,
    "gn:feature_class":"P",
    "gn:feature_code":"PPL",
    "gn:name":"El Resbaladero",
    "gn:population":0,
    "gn:timezone":"America/Monterrey",
    "iso:country":"MX",
    "name:spa_x_preferred":[
        "El Resbaladero"
    ],
    "name:und_x_variant":[
        "Resbaladero"
    ],
    "wof:name":"El Resbaladero",
    "wof:placetype":"locality"
},
  "geometry": {"coordinates":[-99.52418,25.77288],"type":"Point"}
}