{
  "type": "Feature",
  "properties": {
    "gn:admin1_code":"26",
    "gn:admin2_code":"31.0",
    "gn:asciiname":"Basoberachi",
    "gn:country_code":"MX",
    "gn:dem":1131,
    "gn:feature_class":"P",
    "gn:feature_code":"PPL",
    "gn:name":"Basoberachi",
    "gn:population":0,
    "gn:timezone":"America/Hermosillo",
    "iso:country":"MX",
    "name:spa_x_preferred":[
        "Basoberachi"
    ],
    "wof:name":"Basoberachi",
    "wof:placetype":"locality"
},
  "geometry": {"coordinates":[-108.99135,30.1672],"type":"Point"}
}