{
  "type": "Feature",
  "properties": {
    "gn:admin1_code":"21",
    "gn:admin2_code":"145.0",
    "gn:asciiname":"Cuaxuchpa",
    "gn:country_code":"MX",
    "gn:dem":526,
    "gn:feature_class":"P",
    "gn:feature_code":"PPL",
    "gn:name":"Cuaxuchpa",
    "gn:population":449,
    "gn:timezone":"America/Mexico_City",
    "iso:country":"MX",
    "wof:name":"Cuaxuchpa",
    "wof:placetype":"locality",
    "wof:population":449
},
  "geometry": {"coordinates":[-96.83808000000001,18.44283],"type":"Point"}
}