{
  "type": "Feature",
  "properties": {
    "gn:admin1_code":"24.0",
    "gn:admin2_code":"47.0",
    "gn:asciiname":"Guadalupito",
    "gn:country_code":"MX",
    "gn:dem":1508,
    "gn:feature_class":"P",
    "gn:feature_code":"PPL",
    "gn:name":"Guadalupito",
    "gn:population":0,
    "gn:timezone":"America/Mexico_City",
    "iso:country":"MX",
    "name:spa_x_preferred":[
        "Guadalupito"
    ],
    "wof:name":"Guadalupito",
    "wof:placetype":"locality"
},
  "geometry": {"coordinates":[-100.67613,23.43183],"type":"Point"}
}