{
  "type": "Feature",
  "properties": {
    "gn:admin1_code":"10",
    "gn:admin2_code":"28.0",
    "gn:asciiname":"Francisco Primo Verdad",
    "gn:country_code":"MX",
    "gn:dem":1566,
    "gn:feature_class":"P",
    "gn:feature_code":"PPL",
    "gn:name":"Francisco Primo Verdad",
    "gn:population":0,
    "gn:timezone":"America/Monterrey",
    "iso:country":"MX",
    "name:spa_x_preferred":[
        "Francisco Primo Verdad"
    ],
    "name:und_x_variant":[
        "Ejido Francisco Primo Verdad",
        "Menores de Arriba",
        "Menores de Abajo",
        "Primo Verdad"
    ],
    "wof:name":"Francisco Primo Verdad",
    "wof:placetype":"locality"
},
  "geometry": {"coordinates":[-104.45610000000001,24.9036],"type":"Point"}
}