{
  "type": "Feature",
  "properties": {
    "gn:admin1_code":"15",
    "gn:admin2_code":"29.0",
    "gn:asciiname":"Ejido la Venta Cuautlalpan",
    "gn:country_code":"MX",
    "gn:dem":2298,
    "gn:feature_class":"P",
    "gn:feature_code":"PPL",
    "gn:name":"Ejido la Venta Cuautlalpan",
    "gn:population":539,
    "gn:timezone":"America/Mexico_City",
    "iso:country":"MX",
    "wof:name":"Ejido la Venta Cuautlalpan",
    "wof:placetype":"locality",
    "wof:population":539
},
  "geometry": {"coordinates":[-98.87417000000001,19.41944],"type":"Point"}
}