{
  "type": "Feature",
  "properties": {
    "gn:admin1_code":"15",
    "gn:admin2_code":"105.0",
    "gn:asciiname":"Corral Parota (Tepehuastitlan)",
    "gn:country_code":"MX",
    "gn:dem":971,
    "gn:feature_class":"P",
    "gn:feature_code":"PPL",
    "gn:name":"Corral Parota (Tepehuastitl\u00e1n)",
    "gn:population":153,
    "gn:timezone":"America/Mexico_City",
    "iso:country":"MX",
    "name:und_x_variant":[
        "Corral Parota (Tepehuastitl\u00e1n)"
    ],
    "wof:name":"Corral Parota (Tepehuastitlan)",
    "wof:placetype":"locality",
    "wof:population":153
},
  "geometry": {"coordinates":[-100.12394999999999,18.59064],"type":"Point"}
}