{
  "type": "Feature",
  "properties": {
    "gn:admin1_code":"12",
    "gn:admin2_code":"47.0",
    "gn:asciiname":"La Campana",
    "gn:country_code":"MX",
    "gn:dem":1397,
    "gn:feature_class":"P",
    "gn:feature_code":"PPL",
    "gn:name":"La Campana",
    "gn:population":74,
    "gn:timezone":"America/Mexico_City",
    "iso:country":"MX",
    "wof:name":"La Campana",
    "wof:placetype":"locality",
    "wof:population":74
},
  "geometry": {"coordinates":[-99.87912,18.6128],"type":"Point"}
}