{
  "type": "Feature",
  "properties": {
    "gn:admin1_code":"10.0",
    "gn:admin2_code":"37.0",
    "gn:asciiname":"Los Arados",
    "gn:country_code":"MX",
    "gn:dem":659,
    "gn:feature_class":"P",
    "gn:feature_code":"PPL",
    "gn:name":"Los Arados",
    "gn:population":0,
    "gn:timezone":"America/Monterrey",
    "iso:country":"MX",
    "name:spa_x_preferred":[
        "Los Arados"
    ],
    "wof:name":"Los Arados",
    "wof:placetype":"locality"
},
  "geometry": {"coordinates":[-106.65667999999999,25.36442000000001],"type":"Point"}
}