{
  "type": "Feature",
  "properties": {
    "gn:admin1_code":"16.0",
    "gn:admin2_code":"9.0",
    "gn:asciiname":"La Golondrina",
    "gn:country_code":"MX",
    "gn:dem":1487,
    "gn:feature_class":"P",
    "gn:feature_code":"PPL",
    "gn:name":"La Golondrina",
    "gn:population":0,
    "gn:timezone":"America/Mexico_City",
    "iso:country":"MX",
    "name:spa_x_preferred":[
        "La Golondrina"
    ],
    "name:und_x_variant":[
        "Las Golondrinas"
    ],
    "wof:name":"La Golondrina",
    "wof:placetype":"locality"
},
  "geometry": {"coordinates":[-101.73716,19.10225],"type":"Point"}
}