{
  "type": "Feature",
  "properties": {
    "gn:admin1_code":"7",
    "gn:admin2_code":"4.0",
    "gn:asciiname":"La Luz",
    "gn:country_code":"MX",
    "gn:dem":2053,
    "gn:feature_class":"P",
    "gn:feature_code":"PPL",
    "gn:name":"La Luz",
    "gn:population":0,
    "gn:timezone":"America/Monterrey",
    "iso:country":"MX",
    "name:spa_x_preferred":[
        "La Luz"
    ],
    "wof:name":"La Luz",
    "wof:placetype":"locality"
},
  "geometry": {"coordinates":[-100.70046000000001,25.32562],"type":"Point"}
}