{
  "type": "Feature",
  "properties": {
    "gn:admin1_code":"6",
    "gn:admin2_code":"19.0",
    "gn:asciiname":"Granja Gonzalez",
    "gn:country_code":"MX",
    "gn:dem":1424,
    "gn:feature_class":"P",
    "gn:feature_code":"PPL",
    "gn:name":"Granja Gonz\u00e1lez",
    "gn:population":4,
    "gn:timezone":"America/Chihuahua",
    "iso:country":"MX",
    "name:und_x_variant":[
        "Granja Gonz\u00e1lez"
    ],
    "wof:name":"Granja Gonzalez",
    "wof:placetype":"locality",
    "wof:population":4
},
  "geometry": {"coordinates":[-106.08217,28.71307],"type":"Point"}
}