{
  "type": "Feature",
  "properties": {
    "gn:admin1_code":"25",
    "gn:admin2_code":"3",
    "gn:asciiname":"Mesa Colorada",
    "gn:country_code":"MX",
    "gn:dem":1097,
    "gn:feature_class":"P",
    "gn:feature_code":"PPL",
    "gn:name":"Mesa Colorada",
    "gn:population":18,
    "gn:timezone":"America/Mazatlan",
    "iso:country":"MX",
    "wof:name":"Mesa Colorada",
    "wof:placetype":"locality",
    "wof:population":18
},
  "geometry": {"coordinates":[-107.34172,26.00975],"type":"Point"}
}