{
  "type": "Feature",
  "properties": {
    "gn:admin1_code":"6.0",
    "gn:admin2_code":"65.0",
    "gn:asciiname":"Mares",
    "gn:country_code":"MX",
    "gn:dem":1851,
    "gn:feature_class":"P",
    "gn:feature_code":"PPL",
    "gn:name":"Mares",
    "gn:population":0,
    "gn:timezone":"America/Chihuahua",
    "iso:country":"MX",
    "name:spa_x_preferred":[
        "Mares"
    ],
    "wof:name":"Mares",
    "wof:placetype":"locality"
},
  "geometry": {"coordinates":[-108.08953,27.13691],"type":"Point"}
}