{
  "type": "Feature",
  "properties": {
    "gn:admin1_code":"16",
    "gn:admin2_code":"63.0",
    "gn:asciiname":"Rubalcabo",
    "gn:country_code":"MX",
    "gn:dem":1896,
    "gn:feature_class":"P",
    "gn:feature_code":"PPL",
    "gn:name":"Rubalcabo",
    "gn:population":187,
    "gn:timezone":"America/Mexico_City",
    "iso:country":"MX",
    "wof:name":"Rubalcabo",
    "wof:placetype":"locality",
    "wof:population":187
},
  "geometry": {"coordinates":[-101.68333,20.01556],"type":"Point"}
}