{
  "type": "Feature",
  "properties": {
    "gn:admin1_code":"25.0",
    "gn:admin2_code":"5.0",
    "gn:asciiname":"El Sauce",
    "gn:country_code":"MX",
    "gn:dem":421,
    "gn:feature_class":"P",
    "gn:feature_code":"PPL",
    "gn:name":"El Sauce",
    "gn:population":0,
    "gn:timezone":"America/Mazatlan",
    "iso:country":"MX",
    "name:ceb_x_preferred":[
        "El Sauce"
    ],
    "name:ita_x_preferred":[
        "El Sauce"
    ],
    "name:por_x_preferred":[
        "El Sauce"
    ],
    "name:spa_x_preferred":[
        "El Sauce"
    ],
    "name:spa_x_variant":[
        "Acatita"
    ],
    "name:zho_x_preferred":[
        "\u57c3\u723e\u7d39\u585e"
    ],
    "wof:name":"El Sauce",
    "wof:placetype":"locality"
},
  "geometry": {"coordinates":[-106.89622,24.68534],"type":"Point"}
}