{
  "type": "Feature",
  "properties": {
    "gn:admin1_code":"20",
    "gn:admin2_code":"515.0",
    "gn:asciiname":"El Cairo",
    "gn:country_code":"MX",
    "gn:dem":43,
    "gn:feature_class":"P",
    "gn:feature_code":"PPL",
    "gn:name":"El Cairo",
    "gn:population":244,
    "gn:timezone":"America/Mexico_City",
    "iso:country":"MX",
    "name:ceb_x_preferred":[
        "El Cairo"
    ],
    "name:fra_x_preferred":[
        "El Cairo"
    ],
    "name:ita_x_preferred":[
        "El Cairo"
    ],
    "name:kat_x_preferred":[
        "\u10d4\u10da-\u10d9\u10d0\u10d8\u10e0\u10dd"
    ],
    "name:msa_x_preferred":[
        "El Cairo"
    ],
    "name:nld_x_preferred":[
        "El Cairo"
    ],
    "name:sco_x_preferred":[
        "El Cairo"
    ],
    "name:spa_x_preferred":[
        "El Cairo"
    ],
    "name:swe_x_preferred":[
        "El Cairo"
    ],
    "name:urd_x_preferred":[
        "\u0627\u06cc\u0644 \u0642\u0627\u0626\u0631\u0648"
    ],
    "name:vie_x_preferred":[
        "El Cairo"
    ],
    "name:war_x_preferred":[
        "El Cairo"
    ],
    "name:zho_x_preferred":[
        "\u57c3\u723e\u51f1\u7f85"
    ],
    "wof:name":"El Cairo",
    "wof:placetype":"locality",
    "wof:population":244
},
  "geometry": {"coordinates":[-95.22360999999999,16.35167],"type":"Point"}
}