{
  "type": "Feature",
  "properties": {
    "gn:admin1_code":"5",
    "gn:admin2_code":"52.0",
    "gn:asciiname":"Doctor Belisario Dominguez",
    "gn:country_code":"MX",
    "gn:dem":2064,
    "gn:feature_class":"P",
    "gn:feature_code":"PPL",
    "gn:name":"Doctor Belisario Dom\u00ednguez",
    "gn:population":165,
    "gn:timezone":"America/Mexico_City",
    "iso:country":"MX",
    "wof:name":"Doctor Belisario Dominguez",
    "wof:placetype":"locality",
    "wof:population":165
},
  "geometry": {"coordinates":[-91.90944,16.48222],"type":"Point"}
}