{
  "type": "Feature",
  "properties": {
    "gn:admin1_code":"11.0",
    "gn:admin2_code":"29.0",
    "gn:asciiname":"El Pedregal",
    "gn:country_code":"MX",
    "gn:dem":2044,
    "gn:feature_class":"P",
    "gn:feature_code":"PPL",
    "gn:name":"El Pedregal",
    "gn:population":68,
    "gn:timezone":"America/Mexico_City",
    "iso:country":"MX",
    "wof:name":"El Pedregal",
    "wof:placetype":"locality",
    "wof:population":68
},
  "geometry": {"coordinates":[-100.61972,21.35639],"type":"Point"}
}