{
  "type": "Feature",
  "properties": {
    "gn:admin1_code":"24.0",
    "gn:admin2_code":"46.0",
    "gn:asciiname":"Las Tapias",
    "gn:country_code":"MX",
    "gn:dem":2174,
    "gn:feature_class":"P",
    "gn:feature_code":"PPL",
    "gn:name":"Las Tapias",
    "gn:population":0,
    "gn:timezone":"America/Mexico_City",
    "iso:country":"MX",
    "name:spa_x_preferred":[
        "Las Tapias"
    ],
    "wof:name":"Las Tapias",
    "wof:placetype":"locality"
},
  "geometry": {"coordinates":[-101.14400999999999,21.964],"type":"Point"}
}