{
  "type": "Feature",
  "properties": {
    "gn:admin1_code":"28",
    "gn:admin2_code":"39.0",
    "gn:asciiname":"Alberto Carrera Torres",
    "gn:country_code":"MX",
    "gn:dem":1119,
    "gn:feature_class":"P",
    "gn:feature_code":"PPL",
    "gn:name":"Alberto Carrera Torres",
    "gn:population":0,
    "gn:timezone":"America/Monterrey",
    "iso:country":"MX",
    "wof:name":"Alberto Carrera Torres",
    "wof:placetype":"locality"
},
  "geometry": {"coordinates":[-99.58333,22.73333],"type":"Point"}
}