{
  "type": "Feature",
  "properties": {
    "gn:admin1_code":"14.0",
    "gn:admin2_code":"68.0",
    "gn:asciiname":"Los Mangos",
    "gn:country_code":"MX",
    "gn:dem":469,
    "gn:feature_class":"P",
    "gn:feature_code":"PPL",
    "gn:name":"Los Mangos",
    "gn:population":0,
    "gn:timezone":"America/Mexico_City",
    "iso:country":"MX",
    "name:spa_x_preferred":[
        "Los Mangos"
    ],
    "wof:name":"Los Mangos",
    "wof:placetype":"locality"
},
  "geometry": {"coordinates":[-104.70798000000001,19.73932000000001],"type":"Point"}
}