{
  "type": "Feature",
  "properties": {
    "gn:admin1_code":"5",
    "gn:admin2_code":"96.0",
    "gn:asciiname":"Palo Negro",
    "gn:country_code":"MX",
    "gn:dem":1268,
    "gn:feature_class":"P",
    "gn:feature_code":"PPL",
    "gn:name":"Palo Negro",
    "gn:population":75,
    "gn:timezone":"America/Mexico_City",
    "iso:country":"MX",
    "wof:name":"Palo Negro",
    "wof:placetype":"locality",
    "wof:population":75
},
  "geometry": {"coordinates":[-92.60833,17.44722],"type":"Point"}
}