{
  "type": "Feature",
  "properties": {
    "gn:admin1_code":"5.0",
    "gn:admin2_code":"65.0",
    "gn:asciiname":"Victor Manuel Reyna",
    "gn:country_code":"MX",
    "gn:dem":131,
    "gn:feature_class":"P",
    "gn:feature_code":"PPL",
    "gn:name":"Victor Manuel Reyna",
    "gn:population":0,
    "gn:timezone":"America/Mexico_City",
    "iso:country":"MX",
    "name:spa_x_preferred":[
        "Victor Manuel Reyna"
    ],
    "wof:name":"Victor Manuel Reyna",
    "wof:placetype":"locality"
},
  "geometry": {"coordinates":[-91.70201,17.43751],"type":"Point"}
}