{
  "type": "Feature",
  "properties": {
    "gn:admin1_code":"14",
    "gn:admin2_code":"115",
    "gn:asciiname":"El Plan",
    "gn:country_code":"MX",
    "gn:dem":1707,
    "gn:feature_class":"P",
    "gn:feature_code":"PPL",
    "gn:name":"El Plan",
    "gn:population":11,
    "gn:timezone":"America/Mexico_City",
    "iso:country":"MX",
    "wof:name":"El Plan",
    "wof:placetype":"locality",
    "wof:population":11
},
  "geometry": {"coordinates":[-103.64444,21.99444],"type":"Point"}
}