{
  "type": "Feature",
  "properties": {
    "gn:admin1_code":"12",
    "gn:admin2_code":"47",
    "gn:asciiname":"Pena del Chivo",
    "gn:country_code":"MX",
    "gn:dem":1023,
    "gn:feature_class":"P",
    "gn:feature_code":"PPL",
    "gn:name":"Pe\u00f1a del Chivo",
    "gn:population":22,
    "gn:timezone":"America/Mexico_City",
    "iso:country":"MX",
    "name:und_x_variant":[
        "Pe\u00f1a del Chivo"
    ],
    "wof:name":"Pena del Chivo",
    "wof:placetype":"locality",
    "wof:population":22
},
  "geometry": {"coordinates":[-99.93455,18.57733],"type":"Point"}
}