{
  "type": "Feature",
  "properties": {
    "gn:admin1_code":"30",
    "gn:admin2_code":"210.0",
    "gn:asciiname":"Bajo Grande",
    "gn:country_code":"MX",
    "gn:dem":124,
    "gn:feature_class":"P",
    "gn:feature_code":"PPL",
    "gn:name":"Bajo Grande",
    "gn:population":93,
    "gn:timezone":"America/Mexico_City",
    "iso:country":"MX",
    "wof:name":"Bajo Grande",
    "wof:placetype":"locality",
    "wof:population":93
},
  "geometry": {"coordinates":[-94.34999999999999,17.21722],"type":"Point"}
}