{
  "type": "Feature",
  "properties": {
    "gn:admin1_code":"10.0",
    "gn:admin2_code":"9.0",
    "gn:asciiname":"Santa Elena",
    "gn:country_code":"MX",
    "gn:dem":2347,
    "gn:feature_class":"P",
    "gn:feature_code":"PPL",
    "gn:name":"Santa Elena",
    "gn:population":0,
    "gn:timezone":"America/Monterrey",
    "iso:country":"MX",
    "name:spa_x_preferred":[
        "Santa Elena"
    ],
    "wof:name":"Santa Elena",
    "wof:placetype":"locality"
},
  "geometry": {"coordinates":[-105.99795,25.95296],"type":"Point"}
}