{
  "type": "Feature",
  "properties": {
    "gn:admin1_code":"12",
    "gn:admin2_code":"78.0",
    "gn:asciiname":"Cerro de la Lluvia",
    "gn:country_code":"MX",
    "gn:dem":1942,
    "gn:feature_class":"P",
    "gn:feature_code":"PPL",
    "gn:name":"Cerro de la Lluvia",
    "gn:population":56,
    "gn:timezone":"America/Mexico_City",
    "iso:country":"MX",
    "wof:name":"Cerro de la Lluvia",
    "wof:placetype":"locality",
    "wof:population":56
},
  "geometry": {"coordinates":[-98.33722,17.09528],"type":"Point"}
}