{
  "type": "Feature",
  "properties": {
    "gn:admin1_code":"16",
    "gn:admin2_code":"88.0",
    "gn:asciiname":"La Noria",
    "gn:country_code":"MX",
    "gn:dem":1870,
    "gn:feature_class":"P",
    "gn:feature_code":"PPL",
    "gn:name":"La Noria",
    "gn:population":694,
    "gn:timezone":"America/Mexico_City",
    "iso:country":"MX",
    "wof:name":"La Noria",
    "wof:placetype":"locality",
    "wof:population":694
},
  "geometry": {"coordinates":[-101.11778,19.84167],"type":"Point"}
}