{
  "type": "Feature",
  "properties": {
    "gn:admin1_code":"18.0",
    "gn:admin2_code":"7.0",
    "gn:asciiname":"Las Coles",
    "gn:country_code":"MX",
    "gn:dem":1414,
    "gn:feature_class":"P",
    "gn:feature_code":"PPL",
    "gn:name":"Las Coles",
    "gn:population":0,
    "gn:timezone":"America/Mazatlan",
    "iso:country":"MX",
    "name:spa_x_preferred":[
        "Las Coles"
    ],
    "wof:name":"Las Coles",
    "wof:placetype":"locality"
},
  "geometry": {"coordinates":[-104.51242000000001,21.17894],"type":"Point"}
}