{
  "type": "Feature",
  "properties": {
    "gn:admin1_code":"6",
    "gn:admin2_code":"65",
    "gn:asciiname":"Pechi",
    "gn:country_code":"MX",
    "gn:dem":1770,
    "gn:feature_class":"P",
    "gn:feature_code":"PPL",
    "gn:name":"Pechi",
    "gn:population":17,
    "gn:timezone":"America/Chihuahua",
    "iso:country":"MX",
    "wof:name":"Pechi",
    "wof:placetype":"locality",
    "wof:population":17
},
  "geometry": {"coordinates":[-107.78561999999999,27.39318],"type":"Point"}
}