{
  "type": "Feature",
  "properties": {
    "gn:admin1_code":"6",
    "gn:admin2_code":"8.0",
    "gn:asciiname":"Norihui",
    "gn:country_code":"MX",
    "gn:dem":2130,
    "gn:feature_class":"P",
    "gn:feature_code":"PPL",
    "gn:name":"Norihui",
    "gn:population":92,
    "gn:timezone":"America/Chihuahua",
    "iso:country":"MX",
    "wof:name":"Norihui",
    "wof:placetype":"locality",
    "wof:population":92
},
  "geometry": {"coordinates":[-107.53934,26.91799],"type":"Point"}
}