{
  "type": "Feature",
  "properties": {
    "gn:admin1_code":"32",
    "gn:admin2_code":"38",
    "gn:asciiname":"El Cajon",
    "gn:country_code":"MX",
    "gn:dem":2704,
    "gn:feature_class":"P",
    "gn:feature_code":"PPL",
    "gn:name":"El Caj\u00f3n",
    "gn:population":13,
    "gn:timezone":"America/Mexico_City",
    "iso:country":"MX",
    "name:und_x_variant":[
        "El Caj\u00f3n"
    ],
    "wof:name":"El Cajon",
    "wof:placetype":"locality",
    "wof:population":13
},
  "geometry": {"coordinates":[-101.53917,22.33778],"type":"Point"}
}