{
  "type": "Feature",
  "properties": {
    "gn:admin1_code":"11",
    "gn:admin2_code":"8.0",
    "gn:asciiname":"Presa del Sauz",
    "gn:country_code":"MX",
    "gn:dem":1723,
    "gn:feature_class":"P",
    "gn:feature_code":"PPL",
    "gn:name":"Presa del Sauz",
    "gn:population":90,
    "gn:timezone":"America/Mexico_City",
    "iso:country":"MX",
    "wof:name":"Presa del Sauz",
    "wof:placetype":"locality",
    "wof:population":90
},
  "geometry": {"coordinates":[-101.92944,20.70639],"type":"Point"}
}