{
  "type": "Feature",
  "properties": {
    "gn:admin1_code":"6",
    "gn:admin2_code":"9.0",
    "gn:asciiname":"Cerayna",
    "gn:country_code":"MX",
    "gn:dem":2195,
    "gn:feature_class":"P",
    "gn:feature_code":"PPL",
    "gn:name":"Cerayna",
    "gn:population":6,
    "gn:timezone":"America/Chihuahua",
    "iso:country":"MX",
    "wof:name":"Cerayna",
    "wof:placetype":"locality",
    "wof:population":6
},
  "geometry": {"coordinates":[-107.31944,27.8125],"type":"Point"}
}