{
  "type": "Feature",
  "properties": {
    "gn:admin1_code":"14",
    "gn:admin2_code":"118",
    "gn:asciiname":"La Labor de Vargas",
    "gn:country_code":"MX",
    "gn:dem":1665,
    "gn:feature_class":"P",
    "gn:feature_code":"PPL",
    "gn:name":"La Labor de Vargas",
    "gn:population":40,
    "gn:timezone":"America/Mexico_City",
    "iso:country":"MX",
    "wof:name":"La Labor de Vargas",
    "wof:placetype":"locality",
    "wof:population":40
},
  "geometry": {"coordinates":[-102.88916999999999,21.02167],"type":"Point"}
}