{
  "type": "Feature",
  "properties": {
    "gn:admin1_code":"5",
    "gn:admin2_code":"84",
    "gn:asciiname":"Lucio Cabanas",
    "gn:country_code":"MX",
    "gn:dem":330,
    "gn:feature_class":"P",
    "gn:feature_code":"PPL",
    "gn:name":"Lucio Caba\u00f1as",
    "gn:population":34,
    "gn:timezone":"America/Mexico_City",
    "iso:country":"MX",
    "name:und_x_variant":[
        "Lucio Caba\u00f1as"
    ],
    "wof:name":"Lucio Cabanas",
    "wof:placetype":"locality",
    "wof:population":34
},
  "geometry": {"coordinates":[-93.03722,17.41056],"type":"Point"}
}