{
  "type": "Feature",
  "properties": {
    "gn:admin1_code":"13.0",
    "gn:admin2_code":"26.0",
    "gn:asciiname":"Otecom",
    "gn:country_code":"MX",
    "gn:dem":475,
    "gn:feature_class":"P",
    "gn:feature_code":"PPL",
    "gn:name":"Otecom",
    "gn:population":0,
    "gn:timezone":"America/Mexico_City",
    "iso:country":"MX",
    "name:spa_x_preferred":[
        "Otecom"
    ],
    "wof:name":"Otecom",
    "wof:placetype":"locality"
},
  "geometry": {"coordinates":[-98.46234,21.01556],"type":"Point"}
}