{
  "type": "Feature",
  "properties": {
    "gn:admin1_code":"22",
    "gn:admin2_code":"3.0",
    "gn:asciiname":"La Mohonera",
    "gn:country_code":"MX",
    "gn:dem":1415,
    "gn:feature_class":"P",
    "gn:feature_code":"PPL",
    "gn:name":"La Mohonera",
    "gn:population":156,
    "gn:timezone":"America/Mexico_City",
    "iso:country":"MX",
    "wof:name":"La Mohonera",
    "wof:placetype":"locality",
    "wof:population":156
},
  "geometry": {"coordinates":[-99.4444,21.33671],"type":"Point"}
}