{
  "type": "Feature",
  "properties": {
    "gn:admin1_code":"6.0",
    "gn:admin2_code":"29.0",
    "gn:asciiname":"Polvorin",
    "gn:country_code":"MX",
    "gn:dem":2665,
    "gn:feature_class":"P",
    "gn:feature_code":"PPL",
    "gn:name":"Polvor\u00edn",
    "gn:population":0,
    "gn:timezone":"America/Chihuahua",
    "iso:country":"MX",
    "name:spa_x_preferred":[
        "Polvor\u00edn"
    ],
    "wof:name":"Polvorin",
    "wof:placetype":"locality"
},
  "geometry": {"coordinates":[-107.00911000000001,26.03998],"type":"Point"}
}