{
  "type": "Feature",
  "properties": {
    "gn:admin1_code":"12",
    "gn:admin2_code":"29.0",
    "gn:asciiname":"La Haciendita",
    "gn:country_code":"MX",
    "gn:dem":646,
    "gn:feature_class":"P",
    "gn:feature_code":"PPL",
    "gn:name":"La Haciendita",
    "gn:population":374,
    "gn:timezone":"America/Mexico_City",
    "iso:country":"MX",
    "wof:name":"La Haciendita",
    "wof:placetype":"locality",
    "wof:population":374
},
  "geometry": {"coordinates":[-99.49694,17.205],"type":"Point"}
}