{
  "type": "Feature",
  "properties": {
    "gn:admin1_code":"2.0",
    "gn:admin2_code":"2.0",
    "gn:asciiname":"Ejido Benito Juarez",
    "gn:country_code":"MX",
    "gn:dem":9,
    "gn:feature_class":"P",
    "gn:feature_code":"PPL",
    "gn:name":"Ejido Benito Ju\u00e1rez",
    "gn:population":109,
    "gn:timezone":"America/Tijuana",
    "iso:country":"MX",
    "name:spa_x_preferred":[
        "Ejido Benito Ju\u00e1rez"
    ],
    "wof:name":"Ejido Benito Juarez",
    "wof:placetype":"locality",
    "wof:population":109
},
  "geometry": {"coordinates":[-115.44417,32.48944],"type":"Point"}
}