{
  "type": "Feature",
  "properties": {
    "gn:admin1_code":"7.0",
    "gn:admin2_code":"27.0",
    "gn:asciiname":"Guajardo",
    "gn:country_code":"MX",
    "gn:dem":1593,
    "gn:feature_class":"P",
    "gn:feature_code":"PPL",
    "gn:name":"Guajardo",
    "gn:population":190,
    "gn:timezone":"America/Monterrey",
    "iso:country":"MX",
    "name:spa_x_preferred":[
        "Guajardo"
    ],
    "wof:name":"Guajardo",
    "wof:placetype":"locality",
    "wof:population":190
},
  "geometry": {"coordinates":[-101.23466999999999,25.45383],"type":"Point"}
}