{
  "type": "Feature",
  "properties": {
    "gn:admin1_code":"14",
    "gn:admin2_code":"15.0",
    "gn:asciiname":"La Maroma Uno",
    "gn:country_code":"MX",
    "gn:dem":891,
    "gn:feature_class":"P",
    "gn:feature_code":"PPL",
    "gn:name":"La Maroma Uno",
    "gn:population":5,
    "gn:timezone":"America/Mexico_City",
    "iso:country":"MX",
    "wof:name":"La Maroma Uno",
    "wof:placetype":"locality",
    "wof:population":5
},
  "geometry": {"coordinates":[-104.33139,19.74917],"type":"Point"}
}