{
  "type": "Feature",
  "properties": {
    "gn:admin1_code":"26.0",
    "gn:admin2_code":"23.0",
    "gn:asciiname":"Jecori",
    "gn:country_code":"MX",
    "gn:dem":710,
    "gn:feature_class":"P",
    "gn:feature_code":"PPL",
    "gn:name":"J\u00e9cori",
    "gn:population":611,
    "gn:timezone":"America/Hermosillo",
    "iso:country":"MX",
    "wof:name":"Jecori",
    "wof:placetype":"locality",
    "wof:population":611
},
  "geometry": {"coordinates":[-109.73611,29.93667],"type":"Point"}
}