{
  "type": "Feature",
  "properties": {
    "gn:admin1_code":"10",
    "gn:admin2_code":"26.0",
    "gn:asciiname":"Yerbaniz",
    "gn:country_code":"MX",
    "gn:dem":2590,
    "gn:feature_class":"P",
    "gn:feature_code":"PPL",
    "gn:name":"Yerban\u00edz",
    "gn:population":185,
    "gn:timezone":"America/Monterrey",
    "iso:country":"MX",
    "name:und_x_variant":[
        "Yerban\u00edz"
    ],
    "wof:name":"Yerbaniz",
    "wof:placetype":"locality",
    "wof:population":185
},
  "geometry": {"coordinates":[-105.675,24.03167],"type":"Point"}
}