{
  "type": "Feature",
  "properties": {
    "gn:admin1_code":"28",
    "gn:admin2_code":"14.0",
    "gn:asciiname":"Los Leones",
    "gn:country_code":"MX",
    "gn:dem":127,
    "gn:feature_class":"P",
    "gn:feature_code":"PPL",
    "gn:name":"Los Leones",
    "gn:population":0,
    "gn:timezone":"America/Monterrey",
    "iso:country":"MX",
    "name:spa_x_preferred":[
        "Los Leones"
    ],
    "wof:name":"Los Leones",
    "wof:placetype":"locality"
},
  "geometry": {"coordinates":[-99.44346,27.19705],"type":"Point"}
}