{
  "type": "Feature",
  "properties": {
    "gn:admin1_code":"20",
    "gn:admin2_code":"277.0",
    "gn:asciiname":"Israel Figueroa",
    "gn:country_code":"MX",
    "gn:dem":1677,
    "gn:feature_class":"P",
    "gn:feature_code":"PPL",
    "gn:name":"Israel Figueroa",
    "gn:population":6,
    "gn:timezone":"America/Mexico_City",
    "iso:country":"MX",
    "wof:name":"Israel Figueroa",
    "wof:placetype":"locality",
    "wof:population":6
},
  "geometry": {"coordinates":[-96.97056000000001,16.45556],"type":"Point"}
}