{
  "type": "Feature",
  "properties": {
    "gn:admin1_code":"7.0",
    "gn:admin2_code":"20.0",
    "gn:asciiname":"Trampas",
    "gn:country_code":"MX",
    "gn:dem":560,
    "gn:feature_class":"P",
    "gn:feature_code":"PPL",
    "gn:name":"Trampas",
    "gn:population":0,
    "gn:timezone":"America/Monterrey",
    "iso:country":"MX",
    "name:spa_x_preferred":[
        "Trampas"
    ],
    "wof:name":"Trampas",
    "wof:placetype":"locality"
},
  "geometry": {"coordinates":[-101.58487,28.38289],"type":"Point"}
}