{
  "type": "Feature",
  "properties": {
    "gn:admin1_code":"28.0",
    "gn:admin2_code":"24.0",
    "gn:asciiname":"Las Acacias",
    "gn:country_code":"MX",
    "gn:dem":105,
    "gn:feature_class":"P",
    "gn:feature_code":"PPL",
    "gn:name":"Las Acacias",
    "gn:population":0,
    "gn:timezone":"America/Monterrey",
    "iso:country":"MX",
    "name:spa_x_preferred":[
        "Las Acacias"
    ],
    "wof:name":"Las Acacias",
    "wof:placetype":"locality"
},
  "geometry": {"coordinates":[-99.18446,26.40098],"type":"Point"}
}