{
  "type": "Feature",
  "properties": {
    "gn:admin1_code":"16.0",
    "gn:admin2_code":"38.0",
    "gn:asciiname":"Ocuaro",
    "gn:country_code":"MX",
    "gn:dem":694,
    "gn:feature_class":"P",
    "gn:feature_code":"PPL",
    "gn:name":"Ocuaro",
    "gn:population":0,
    "gn:timezone":"America/Mexico_City",
    "iso:country":"MX",
    "name:spa_x_preferred":[
        "Ocuaro"
    ],
    "wof:name":"Ocuaro",
    "wof:placetype":"locality"
},
  "geometry": {"coordinates":[-100.92205,18.79119],"type":"Point"}
}