{
  "type": "Feature",
  "properties": {
    "gn:admin1_code":"11",
    "gn:admin2_code":"33",
    "gn:asciiname":"San Agustin",
    "gn:country_code":"MX",
    "gn:dem":2021,
    "gn:feature_class":"P",
    "gn:feature_code":"PPL",
    "gn:name":"San Agust\u00edn",
    "gn:population":31,
    "gn:timezone":"America/Mexico_City",
    "iso:country":"MX",
    "name:und_x_variant":[
        "San Agust\u00edn"
    ],
    "wof:name":"San Agustin",
    "wof:placetype":"locality",
    "wof:population":31
},
  "geometry": {"coordinates":[-100.68028,21.29639],"type":"Point"}
}