{
  "type": "Feature",
  "properties": {
    "gn:admin1_code":"7.0",
    "gn:admin2_code":"38.0",
    "gn:asciiname":"La Maroma",
    "gn:country_code":"MX",
    "gn:dem":280,
    "gn:feature_class":"P",
    "gn:feature_code":"PPL",
    "gn:name":"La Maroma",
    "gn:population":0,
    "gn:timezone":"America/Monterrey",
    "iso:country":"MX",
    "name:deu_x_preferred":[
        "La Maroma"
    ],
    "name:nno_x_preferred":[
        "La Maroma"
    ],
    "name:nor_x_preferred":[
        "La Maroma"
    ],
    "name:spa_x_preferred":[
        "La Maroma"
    ],
    "name:zho_x_preferred":[
        "\u99ac\u7f85\u99ac\u5cf0"
    ],
    "wof:name":"La Maroma",
    "wof:placetype":"locality"
},
  "geometry": {"coordinates":[-100.71099,28.60319],"type":"Point"}
}