{
  "type": "Feature",
  "properties": {
    "gn:admin1_code":"15.0",
    "gn:admin2_code":"8.0",
    "gn:asciiname":"Meyuca",
    "gn:country_code":"MX",
    "gn:dem":565,
    "gn:feature_class":"P",
    "gn:feature_code":"PPL",
    "gn:name":"Meyuca",
    "gn:population":25,
    "gn:timezone":"America/Mexico_City",
    "iso:country":"MX",
    "name:spa_x_preferred":[
        "Meyuca"
    ],
    "wof:name":"Meyuca",
    "wof:placetype":"locality",
    "wof:population":25
},
  "geometry": {"coordinates":[-100.404,18.73515],"type":"Point"}
}