{
  "type": "Feature",
  "properties": {
    "gn:admin1_code":"28.0",
    "gn:admin2_code":"21.0",
    "gn:asciiname":"San Gerardo",
    "gn:country_code":"MX",
    "gn:dem":78,
    "gn:feature_class":"P",
    "gn:feature_code":"PPL",
    "gn:name":"San Gerardo",
    "gn:population":1,
    "gn:timezone":"America/Monterrey",
    "iso:country":"MX",
    "name:ceb_x_preferred":[
        "San Gerardo"
    ],
    "name:ita_x_preferred":[
        "San Gerardo"
    ],
    "name:por_x_preferred":[
        "San Gerardo"
    ],
    "name:spa_x_preferred":[
        "San Gerardo"
    ],
    "name:zho_x_preferred":[
        "\u8056\u8d6b\u62c9\u723e\u591a"
    ],
    "wof:name":"San Gerardo",
    "wof:placetype":"locality",
    "wof:population":1
},
  "geometry": {"coordinates":[-98.92568,22.68005],"type":"Point"}
}