{
  "type": "Feature",
  "properties": {
    "gn:admin1_code":"10.0",
    "gn:admin2_code":"35.0",
    "gn:asciiname":"Lajas",
    "gn:country_code":"MX",
    "gn:dem":2313,
    "gn:feature_class":"P",
    "gn:feature_code":"PPL",
    "gn:name":"Lajas",
    "gn:population":6,
    "gn:timezone":"America/Monterrey",
    "iso:country":"MX",
    "name:ceb_x_preferred":[
        "Lajas"
    ],
    "name:fra_x_preferred":[
        "Lajas"
    ],
    "name:ita_x_preferred":[
        "Lajas"
    ],
    "name:nld_x_preferred":[
        "Lajas"
    ],
    "name:pol_x_preferred":[
        "Lajas"
    ],
    "name:swe_x_preferred":[
        "Lajas"
    ],
    "wof:name":"Lajas",
    "wof:placetype":"locality",
    "wof:population":6
},
  "geometry": {"coordinates":[-106.23674,25.58747],"type":"Point"}
}