{
  "type": "Feature",
  "properties": {
    "gn:admin1_code":"7",
    "gn:admin2_code":"32.0",
    "gn:asciiname":"Ramos [Minera]",
    "gn:country_code":"MX",
    "gn:dem":371,
    "gn:feature_class":"P",
    "gn:feature_code":"PPL",
    "gn:name":"Ramos [Minera]",
    "gn:population":6,
    "gn:timezone":"America/Monterrey",
    "iso:country":"MX",
    "wof:name":"Ramos [Minera]",
    "wof:placetype":"locality",
    "wof:population":6
},
  "geometry": {"coordinates":[-101.25648,27.93776],"type":"Point"}
}