{
  "type": "Feature",
  "properties": {
    "gn:admin1_code":"30.0",
    "gn:admin2_code":"155.0",
    "gn:asciiname":"Callejon Santa Clara",
    "gn:country_code":"MX",
    "gn:dem":130,
    "gn:feature_class":"P",
    "gn:feature_code":"PPL",
    "gn:name":"Callej\u00f3n Santa Clara",
    "gn:population":676,
    "gn:timezone":"America/Mexico_City",
    "iso:country":"MX",
    "name:spa_x_preferred":[
        "Callej\u00f3n Santa Clara"
    ],
    "wof:name":"Callejon Santa Clara",
    "wof:placetype":"locality",
    "wof:population":676
},
  "geometry": {"coordinates":[-98.13,21.27639],"type":"Point"}
}