{
  "type": "Feature",
  "properties": {
    "gn:admin1_code":"5",
    "gn:admin2_code":"109",
    "gn:asciiname":"Ixcamut",
    "gn:country_code":"MX",
    "gn:dem":793,
    "gn:feature_class":"P",
    "gn:feature_code":"PPL",
    "gn:name":"Ixcamut",
    "gn:population":47,
    "gn:timezone":"America/Mexico_City",
    "iso:country":"MX",
    "wof:name":"Ixcamut",
    "wof:placetype":"locality",
    "wof:population":47
},
  "geometry": {"coordinates":[-92.3475,17.18139],"type":"Point"}
}