{
  "type": "Feature",
  "properties": {
    "gn:admin1_code":"14",
    "gn:admin2_code":"6",
    "gn:asciiname":"Loma de San Javier",
    "gn:country_code":"MX",
    "gn:dem":1249,
    "gn:feature_class":"P",
    "gn:feature_code":"PPL",
    "gn:name":"Loma de San Javier",
    "gn:population":13,
    "gn:timezone":"America/Mexico_City",
    "iso:country":"MX",
    "wof:name":"Loma de San Javier",
    "wof:placetype":"locality",
    "wof:population":13
},
  "geometry": {"coordinates":[-104.05389,20.53167],"type":"Point"}
}