{
  "type": "Feature",
  "properties": {
    "gn:admin1_code":"7",
    "gn:admin2_code":"4.0",
    "gn:asciiname":"Luis Jaime Tamayo [Fabricaciones Metalicas]",
    "gn:country_code":"MX",
    "gn:dem":1618,
    "gn:feature_class":"P",
    "gn:feature_code":"PPL",
    "gn:name":"Luis Jaime Tamayo [Fabricaciones Met\u00e1licas]",
    "gn:population":7,
    "gn:timezone":"America/Monterrey",
    "iso:country":"MX",
    "name:und_x_variant":[
        "Luis Jaime Tamayo [Fabricaciones Met\u00e1licas]"
    ],
    "wof:name":"Luis Jaime Tamayo [Fabricaciones Metalicas]",
    "wof:placetype":"locality",
    "wof:population":7
},
  "geometry": {"coordinates":[-100.88114,25.4417],"type":"Point"}
}