{
  "type": "Feature",
  "properties": {
    "gn:admin1_code":"25.0",
    "gn:admin2_code":"12.0",
    "gn:asciiname":"El Bule",
    "gn:country_code":"MX",
    "gn:dem":53,
    "gn:feature_class":"P",
    "gn:feature_code":"PPL",
    "gn:name":"El Bule",
    "gn:population":0,
    "gn:timezone":"America/Mazatlan",
    "iso:country":"MX",
    "name:spa_x_preferred":[
        "El Bule"
    ],
    "wof:name":"El Bule",
    "wof:placetype":"locality"
},
  "geometry": {"coordinates":[-106.40639,23.32623],"type":"Point"}
}