{
  "type": "Feature",
  "properties": {
    "gn:admin1_code":"6",
    "gn:admin2_code":"1.0",
    "gn:asciiname":"El Ojo Santo Domingo",
    "gn:country_code":"MX",
    "gn:dem":1227,
    "gn:feature_class":"P",
    "gn:feature_code":"PPL",
    "gn:name":"El Ojo Santo Domingo",
    "gn:population":0,
    "gn:timezone":"America/Chihuahua",
    "iso:country":"MX",
    "name:spa_x_preferred":[
        "El Ojo Santo Domingo"
    ],
    "name:und_x_variant":[
        "Hacienda Santo Domingo",
        "Santo Domingo"
    ],
    "wof:name":"El Ojo Santo Domingo",
    "wof:placetype":"locality"
},
  "geometry": {"coordinates":[-106.83629999999999,30.56127],"type":"Point"}
}