{
  "type": "Feature",
  "properties": {
    "gn:admin1_code":"20",
    "gn:admin2_code":"313",
    "gn:asciiname":"Cerro de la Cruz",
    "gn:country_code":"MX",
    "gn:dem":2077,
    "gn:feature_class":"P",
    "gn:feature_code":"PPL",
    "gn:name":"Cerro de la Cruz",
    "gn:population":36,
    "gn:timezone":"America/Mexico_City",
    "iso:country":"MX",
    "wof:name":"Cerro de la Cruz",
    "wof:placetype":"locality",
    "wof:population":36
},
  "geometry": {"coordinates":[-97.08360999999999,17.76333],"type":"Point"}
}