{
  "type": "Feature",
  "properties": {
    "gn:admin1_code":"30",
    "gn:admin2_code":"70",
    "gn:asciiname":"Nuevo Mundo",
    "gn:country_code":"MX",
    "gn:dem":20,
    "gn:feature_class":"P",
    "gn:feature_code":"PPL",
    "gn:name":"Nuevo Mundo",
    "gn:population":43,
    "gn:timezone":"America/Mexico_City",
    "iso:country":"MX",
    "name:ceb_x_preferred":[
        "Nuevo Mundo"
    ],
    "name:deu_x_preferred":[
        "Nuevo Mundo"
    ],
    "name:fra_x_preferred":[
        "Nuevo Mundo"
    ],
    "name:por_x_preferred":[
        "Novo Mundo"
    ],
    "name:spa_x_preferred":[
        "Nuevo Mundo"
    ],
    "name:swe_x_preferred":[
        "Nuevo Mundo"
    ],
    "wof:name":"Nuevo Mundo",
    "wof:placetype":"locality",
    "wof:population":43
},
  "geometry": {"coordinates":[-94.81778,17.47667],"type":"Point"}
}