{
  "type": "Feature",
  "properties": {
    "gn:admin1_code":"20",
    "gn:admin2_code":"457.0",
    "gn:asciiname":"La Chachalaca",
    "gn:country_code":"MX",
    "gn:dem":137,
    "gn:feature_class":"P",
    "gn:feature_code":"PPL",
    "gn:name":"La Chachalaca",
    "gn:population":255,
    "gn:timezone":"America/Mexico_City",
    "iso:country":"MX",
    "wof:name":"La Chachalaca",
    "wof:placetype":"locality",
    "wof:population":255
},
  "geometry": {"coordinates":[-96.14556,17.63806],"type":"Point"}
}