{
  "type": "Feature",
  "properties": {
    "gn:admin1_code":"26.0",
    "gn:admin2_code":"5.0",
    "gn:asciiname":"La Mesita",
    "gn:country_code":"MX",
    "gn:dem":500,
    "gn:feature_class":"P",
    "gn:feature_code":"PPL",
    "gn:name":"La Mesita",
    "gn:population":0,
    "gn:timezone":"America/Hermosillo",
    "iso:country":"MX",
    "name:spa_x_preferred":[
        "La Mesita"
    ],
    "wof:name":"La Mesita",
    "wof:placetype":"locality"
},
  "geometry": {"coordinates":[-109.18102,28.89799],"type":"Point"}
}