{
  "type": "Feature",
  "properties": {
    "gn:admin1_code":"6.0",
    "gn:admin2_code":"5.0",
    "gn:asciiname":"El Espia",
    "gn:country_code":"MX",
    "gn:dem":1276,
    "gn:feature_class":"P",
    "gn:feature_code":"PPL",
    "gn:name":"El Esp\u00eda",
    "gn:population":0,
    "gn:timezone":"America/Chihuahua",
    "iso:country":"MX",
    "name:und_x_variant":[
        "Rancho El Espia",
        "La Esp\u00eda",
        "El Esp\u00eda"
    ],
    "wof:name":"El Espia",
    "wof:placetype":"locality"
},
  "geometry": {"coordinates":[-107.97072,31.35268],"type":"Point"}
}