{
  "type": "Feature",
  "properties": {
    "gn:admin1_code":"14.0",
    "gn:admin2_code":"52.0",
    "gn:asciiname":"Chimingalo",
    "gn:country_code":"MX",
    "gn:dem":905,
    "gn:feature_class":"P",
    "gn:feature_code":"PPL",
    "gn:name":"Chimingalo",
    "gn:population":0,
    "gn:timezone":"America/Mexico_City",
    "iso:country":"MX",
    "name:spa_x_preferred":[
        "Chimingalo"
    ],
    "name:spa_x_variant":[
        "Comingalo"
    ],
    "wof:name":"Chimingalo",
    "wof:placetype":"locality"
},
  "geometry": {"coordinates":[-104.03308,19.98641],"type":"Point"}
}