{
  "type": "Feature",
  "properties": {
    "gn:admin1_code":"11",
    "gn:admin2_code":"8.0",
    "gn:asciiname":"Rancho Nuevo de Atotonilquillo",
    "gn:country_code":"MX",
    "gn:dem":1734,
    "gn:feature_class":"P",
    "gn:feature_code":"PPL",
    "gn:name":"Rancho Nuevo de Atotonilquillo",
    "gn:population":0,
    "gn:timezone":"America/Mexico_City",
    "iso:country":"MX",
    "name:und_x_variant":[
        "Rancho Nuevo",
        "Rancho Nuevo de Atotonilquillo"
    ],
    "wof:name":"Rancho Nuevo de Atotonilquillo",
    "wof:placetype":"locality"
},
  "geometry": {"coordinates":[-101.89587,20.67503],"type":"Point"}
}