{
  "type": "Feature",
  "properties": {
    "gn:admin1_code":"16.0",
    "gn:admin2_code":"53.0",
    "gn:asciiname":"Capulin",
    "gn:country_code":"MX",
    "gn:dem":2245,
    "gn:feature_class":"P",
    "gn:feature_code":"PPL",
    "gn:name":"Capul\u00edn",
    "gn:population":0,
    "gn:timezone":"America/Mexico_City",
    "iso:country":"MX",
    "wof:name":"Capulin",
    "wof:placetype":"locality"
},
  "geometry": {"coordinates":[-101.20564,19.53741],"type":"Point"}
}