{
  "type": "Feature",
  "properties": {
    "gn:admin1_code":"29",
    "gn:admin2_code":"34.0",
    "gn:asciiname":"Acopinalco del Penon",
    "gn:country_code":"MX",
    "gn:dem":2650,
    "gn:feature_class":"P",
    "gn:feature_code":"PPL",
    "gn:name":"Acopinalco del Pe\u00f1\u00f3n",
    "gn:population":0,
    "gn:timezone":"America/Mexico_City",
    "iso:country":"MX",
    "name:spa_x_preferred":[
        "El Pe\u00f1\u00f3n"
    ],
    "name:und_x_variant":[
        "Acopinalco",
        "Acopinalco del Pe\u00f1\u00f3n"
    ],
    "wof:name":"Acopinalco del Penon",
    "wof:placetype":"locality"
},
  "geometry": {"coordinates":[-98.16298999999999,19.65929],"type":"Point"}
}