{
  "type": "Feature",
  "properties": {
    "gn:admin1_code":"10",
    "gn:admin2_code":"37",
    "gn:asciiname":"Los Chilillos",
    "gn:country_code":"MX",
    "gn:dem":760,
    "gn:feature_class":"P",
    "gn:feature_code":"PPL",
    "gn:name":"Los Chilillos",
    "gn:population":9,
    "gn:timezone":"America/Monterrey",
    "iso:country":"MX",
    "wof:name":"Los Chilillos",
    "wof:placetype":"locality",
    "wof:population":9
},
  "geometry": {"coordinates":[-106.78263,25.26137],"type":"Point"}
}