{
  "type": "Feature",
  "properties": {
    "gn:admin1_code":"15",
    "gn:admin2_code":"83",
    "gn:asciiname":"Ampliacion Potrero",
    "gn:country_code":"MX",
    "gn:dem":2269,
    "gn:feature_class":"P",
    "gn:feature_code":"PPL",
    "gn:name":"Ampliaci\u00f3n Potrero",
    "gn:population":22,
    "gn:timezone":"America/Mexico_City",
    "iso:country":"MX",
    "name:und_x_variant":[
        "Ampliaci\u00f3n Potrero"
    ],
    "wof:name":"Ampliacion Potrero",
    "wof:placetype":"locality",
    "wof:population":22
},
  "geometry": {"coordinates":[-98.88481,19.20243],"type":"Point"}
}