{
  "type": "Feature",
  "properties": {
    "gn:admin1_code":"12.0",
    "gn:admin2_code":"27.0",
    "gn:asciiname":"Arroyo Salado",
    "gn:country_code":"MX",
    "gn:dem":460,
    "gn:feature_class":"P",
    "gn:feature_code":"PPL",
    "gn:name":"Arroyo Salado",
    "gn:population":0,
    "gn:timezone":"America/Mexico_City",
    "iso:country":"MX",
    "name:ceb_x_preferred":[
        "Arroyo Salado"
    ],
    "name:spa_x_preferred":[
        "Arroyo Salado"
    ],
    "name:swe_x_preferred":[
        "Arroyo Salado"
    ],
    "wof:name":"Arroyo Salado",
    "wof:placetype":"locality"
},
  "geometry": {"coordinates":[-100.48938,18.75997000000001],"type":"Point"}
}