{
  "type": "Feature",
  "properties": {
    "gn:admin1_code":"14",
    "gn:admin2_code":"30",
    "gn:asciiname":"Tres Canadas (El Estrellon)",
    "gn:country_code":"MX",
    "gn:dem":1560,
    "gn:feature_class":"P",
    "gn:feature_code":"PPL",
    "gn:name":"Tres Ca\u00f1adas (El Estrell\u00f3n)",
    "gn:population":16,
    "gn:timezone":"America/Mexico_City",
    "iso:country":"MX",
    "name:und_x_variant":[
        "Tres Ca\u00f1adas (El Estrell\u00f3n)"
    ],
    "wof:name":"Tres Canadas (El Estrellon)",
    "wof:placetype":"locality",
    "wof:population":16
},
  "geometry": {"coordinates":[-103.29667000000001,20.29667],"type":"Point"}
}