{
  "type": "Feature",
  "properties": {
    "gn:admin1_code":"16",
    "gn:admin2_code":"85.0",
    "gn:asciiname":"Colonia Emiliano Zapata",
    "gn:country_code":"MX",
    "gn:dem":1738,
    "gn:feature_class":"P",
    "gn:feature_code":"PPL",
    "gn:name":"Colonia Emiliano Zapata",
    "gn:population":129,
    "gn:timezone":"America/Mexico_City",
    "iso:country":"MX",
    "wof:name":"Colonia Emiliano Zapata",
    "wof:placetype":"locality",
    "wof:population":129
},
  "geometry": {"coordinates":[-102.13500000000001,19.94556],"type":"Point"}
}