{
  "type": "Feature",
  "properties": {
    "gn:admin1_code":"10",
    "gn:admin2_code":"33",
    "gn:asciiname":"Los Corrales",
    "gn:country_code":"MX",
    "gn:dem":2299,
    "gn:feature_class":"P",
    "gn:feature_code":"PPL",
    "gn:name":"Los Corrales",
    "gn:population":9,
    "gn:timezone":"America/Monterrey",
    "iso:country":"MX",
    "wof:name":"Los Corrales",
    "wof:placetype":"locality",
    "wof:population":9
},
  "geometry": {"coordinates":[-104.13803,23.40975],"type":"Point"}
}