{
  "type": "Feature",
  "properties": {
    "gn:admin1_code":"30",
    "gn:admin2_code":"110",
    "gn:asciiname":"Tenayoca",
    "gn:country_code":"MX",
    "gn:dem":1854,
    "gn:feature_class":"P",
    "gn:feature_code":"PPL",
    "gn:name":"Tenayoca",
    "gn:population":11,
    "gn:timezone":"America/Mexico_City",
    "iso:country":"MX",
    "wof:name":"Tenayoca",
    "wof:placetype":"locality",
    "wof:population":11
},
  "geometry": {"coordinates":[-96.97667,18.59556],"type":"Point"}
}