{
  "type": "Feature",
  "properties": {
    "gn:admin1_code":"5",
    "gn:admin2_code":"31.0",
    "gn:asciiname":"San Martin T'Uliha",
    "gn:country_code":"MX",
    "gn:dem":537,
    "gn:feature_class":"P",
    "gn:feature_code":"PPL",
    "gn:name":"San Mart\u00edn T'Uliha",
    "gn:population":5,
    "gn:timezone":"America/Mexico_City",
    "iso:country":"MX",
    "name:und_x_variant":[
        "San Mart\u00edn T'Uliha"
    ],
    "wof:name":"San Martin T'Uliha",
    "wof:placetype":"locality",
    "wof:population":5
},
  "geometry": {"coordinates":[-91.86667,17.21583],"type":"Point"}
}