{
  "type": "Feature",
  "properties": {
    "gn:admin1_code":"29",
    "gn:admin2_code":"13",
    "gn:asciiname":"Fraccion Soltepec (El Rincon)",
    "gn:country_code":"MX",
    "gn:dem":2455,
    "gn:feature_class":"P",
    "gn:feature_code":"PPL",
    "gn:name":"Fracci\u00f3n Soltepec (El Rinc\u00f3n)",
    "gn:population":22,
    "gn:timezone":"America/Mexico_City",
    "iso:country":"MX",
    "name:und_x_variant":[
        "Fracci\u00f3n Soltepec (El Rinc\u00f3n)"
    ],
    "wof:name":"Fraccion Soltepec (El Rincon)",
    "wof:placetype":"locality",
    "wof:population":22
},
  "geometry": {"coordinates":[-97.90228,19.30937],"type":"Point"}
}