{
  "type": "Feature",
  "properties": {
    "gn:admin1_code":"19.0",
    "gn:asciiname":"Laguna San Antonio",
    "gn:country_code":"MX",
    "gn:dem":1858,
    "gn:feature_class":"P",
    "gn:feature_code":"PPL",
    "gn:name":"Laguna San Antonio",
    "gn:population":0,
    "gn:timezone":"America/Monterrey",
    "iso:country":"MX",
    "name:spa_x_preferred":[
        "Laguna San Antonio"
    ],
    "wof:name":"Laguna San Antonio",
    "wof:placetype":"locality"
},
  "geometry": {"coordinates":[-99.78154000000001,24.04931],"type":"Point"}
}