{
  "type": "Feature",
  "properties": {
    "gn:admin1_code":"26.0",
    "gn:admin2_code":"3.0",
    "gn:asciiname":"Santa Amalia",
    "gn:country_code":"MX",
    "gn:dem":305,
    "gn:feature_class":"P",
    "gn:feature_code":"PPL",
    "gn:name":"Santa Amalia",
    "gn:population":0,
    "gn:timezone":"America/Hermosillo",
    "iso:country":"MX",
    "name:spa_x_preferred":[
        "Santa Amalia"
    ],
    "wof:name":"Santa Amalia",
    "wof:placetype":"locality"
},
  "geometry": {"coordinates":[-108.98596999999999,27.10887],"type":"Point"}
}