{
  "type": "Feature",
  "properties": {
    "gn:admin1_code":"26.0",
    "gn:admin2_code":"3.0",
    "gn:asciiname":"Santa Amalia",
    "gn:country_code":"MX",
    "gn:dem":305,
    "gn:feature_class":"P",
    "gn:feature_code":"PPL",
    "gn:name":"Santa Amalia",
    "gn:population":0,
    "gn:timezone":"America/Hermosillo",
    "iso:country":"MX",
    "name:ara_x_preferred":[
        "\u0633\u0627\u0646\u062a\u0627 \u0623\u0645\u0627\u0644\u064a\u0627"
    ],
    "name:arg_x_preferred":[
        "Santa Amalia"
    ],
    "name:azb_x_preferred":[
        "\u0633\u0627\u0646\u062a\u0627 \u0622\u0645\u0627\u0644\u06cc\u0627"
    ],
    "name:cat_x_preferred":[
        "Santa Amalia"
    ],
    "name:ceb_x_preferred":[
        "Santa Amalia"
    ],
    "name:ces_x_preferred":[
        "Santa Amalia"
    ],
    "name:epo_x_preferred":[
        "Santa Amalia"
    ],
    "name:eus_x_preferred":[
        "Santa Amalia"
    ],
    "name:fas_x_preferred":[
        "\u0633\u0627\u0646\u062a\u0627 \u0622\u0645\u0627\u0644\u06cc\u0627"
    ],
    "name:fra_x_preferred":[
        "Santa Amalia"
    ],
    "name:hun_x_preferred":[
        "Santa Amalia"
    ],
    "name:hye_x_preferred":[
        "\u054d\u0561\u0576\u057f\u0561 \u0531\u0574\u0561\u056c\u056b\u0561"
    ],
    "name:ido_x_preferred":[
        "Santa Amalia"
    ],
    "name:ina_x_preferred":[
        "Santa Amalia"
    ],
    "name:ita_x_preferred":[
        "Santa Amalia"
    ],
    "name:mkd_x_preferred":[
        "\u0421\u0430\u043d\u0442\u0430 \u0410\u043c\u0430\u043b\u0438\u0458\u0430"
    ],
    "name:msa_x_preferred":[
        "Santa Amalia"
    ],
    "name:nld_x_preferred":[
        "Santa Amalia"
    ],
    "name:oci_x_preferred":[
        "Santa Amalia"
    ],
    "name:pol_x_preferred":[
        "Santa Amalia"
    ],
    "name:por_x_preferred":[
        "Santa Amalia"
    ],
    "name:ron_x_preferred":[
        "Santa Amalia"
    ],
    "name:rus_x_preferred":[
        "\u0421\u0430\u043d\u0442\u0430-\u0410\u043c\u0430\u043b\u0438\u044f"
    ],
    "name:spa_x_preferred":[
        "Santa Amalia"
    ],
    "name:swe_x_preferred":[
        "Santa Amalia"
    ],
    "name:ukr_x_preferred":[
        "\u0421\u0430\u043d\u0442\u0430-\u0410\u043c\u0430\u043b\u0456\u044f"
    ],
    "name:uzb_x_preferred":[
        "Santa Amalia"
    ],
    "name:vie_x_preferred":[
        "Santa Amalia"
    ],
    "name:war_x_preferred":[
        "Santa Amalia"
    ],
    "name:zho_x_preferred":[
        "\u5723\u963f\u9a6c\u5229\u4e9a"
    ],
    "wof:name":"Santa Amalia",
    "wof:placetype":"locality"
},
  "geometry": {"coordinates":[-108.98596999999999,27.10887],"type":"Point"}
}