{
  "type": "Feature",
  "properties": {
    "gn:admin1_code":"6",
    "gn:admin2_code":"19.0",
    "gn:asciiname":"Orizaba",
    "gn:country_code":"MX",
    "gn:dem":1619,
    "gn:feature_class":"P",
    "gn:feature_code":"PPL",
    "gn:name":"Orizaba",
    "gn:population":0,
    "gn:timezone":"America/Chihuahua",
    "iso:country":"MX",
    "name:und_x_variant":[
        "Rancho de Orizaba",
        "Orizaba"
    ],
    "wof:name":"Orizaba",
    "wof:placetype":"locality"
},
  "geometry": {"coordinates":[-106.06501000000002,28.54349],"type":"Point"}
}