{
  "type": "Feature",
  "properties": {
    "gn:admin1_code":"25.0",
    "gn:asciiname":"El Negrito",
    "gn:country_code":"MX",
    "gn:dem":4,
    "gn:feature_class":"P",
    "gn:feature_code":"PPL",
    "gn:name":"El Negrito",
    "gn:population":0,
    "gn:timezone":"America/Mazatlan",
    "iso:country":"MX",
    "name:ceb_x_preferred":[
        "El Negrito"
    ],
    "name:fra_x_preferred":[
        "El Negrito"
    ],
    "name:ita_x_preferred":[
        "El Negrito"
    ],
    "name:nld_x_preferred":[
        "El Negrito"
    ],
    "name:por_x_preferred":[
        "El Negrito"
    ],
    "name:spa_x_preferred":[
        "El Negrito"
    ],
    "name:swe_x_preferred":[
        "El Negrito"
    ],
    "name:zho_x_preferred":[
        "\u57c3\u723e\u5167\u683c\u91cc\u6258"
    ],
    "wof:name":"El Negrito",
    "wof:placetype":"locality"
},
  "geometry": {"coordinates":[-105.72873,22.58978],"type":"Point"}
}