{
  "type": "Feature",
  "properties": {
    "gn:admin1_code":"30.0",
    "gn:admin2_code":"121.0",
    "gn:asciiname":"Palma Chaya",
    "gn:country_code":"MX",
    "gn:dem":47,
    "gn:feature_class":"P",
    "gn:feature_code":"PPL",
    "gn:name":"Palma Chaya",
    "gn:population":0,
    "gn:timezone":"America/Mexico_City",
    "iso:country":"MX",
    "name:spa_x_preferred":[
        "Palma Chaya"
    ],
    "wof:name":"Palma Chaya",
    "wof:placetype":"locality"
},
  "geometry": {"coordinates":[-97.89533,21.51139],"type":"Point"}
}