{
  "type": "Feature",
  "properties": {
    "gn:admin1_code":"14",
    "gn:admin2_code":"110.0",
    "gn:asciiname":"Tacotan",
    "gn:country_code":"MX",
    "gn:dem":1329,
    "gn:feature_class":"P",
    "gn:feature_code":"PPL",
    "gn:name":"Tacot\u00e1n",
    "gn:population":0,
    "gn:timezone":"America/Mexico_City",
    "iso:country":"MX",
    "name:spa_x_preferred":[
        "Tacot\u00e1n"
    ],
    "name:spa_x_variant":[
        "La Alpatahua"
    ],
    "wof:name":"Tacotan",
    "wof:placetype":"locality"
},
  "geometry": {"coordinates":[-104.29877999999999,20.03097],"type":"Point"}
}