{
  "type": "Feature",
  "properties": {
    "gn:admin1_code":"5",
    "gn:admin2_code":"107",
    "gn:asciiname":"Puerto de Veracruz",
    "gn:country_code":"MX",
    "gn:dem":1469,
    "gn:feature_class":"P",
    "gn:feature_code":"PPL",
    "gn:name":"Puerto de Veracruz",
    "gn:population":11,
    "gn:timezone":"America/Mexico_City",
    "iso:country":"MX",
    "wof:name":"Puerto de Veracruz",
    "wof:placetype":"locality",
    "wof:population":11
},
  "geometry": {"coordinates":[-93.38056,15.9575],"type":"Point"}
}