{
  "type": "Feature",
  "properties": {
    "gn:admin1_code":"26.0",
    "gn:admin2_code":"69.0",
    "gn:asciiname":"Cabana los Nabos",
    "gn:country_code":"MX",
    "gn:dem":2162,
    "gn:feature_class":"P",
    "gn:feature_code":"PPL",
    "gn:name":"Caba\u00f1a los Nabos",
    "gn:population":0,
    "gn:timezone":"America/Hermosillo",
    "iso:country":"MX",
    "name:spa_x_preferred":[
        "Caba\u00f1a los Nabos"
    ],
    "wof:name":"Cabana los Nabos",
    "wof:placetype":"locality"
},
  "geometry": {"coordinates":[-109.03897000000001,28.33097],"type":"Point"}
}