{
  "type": "Feature",
  "properties": {
    "gn:admin1_code":"14",
    "gn:admin2_code":"94",
    "gn:asciiname":"El Carrizal",
    "gn:country_code":"MX",
    "gn:dem":1715,
    "gn:feature_class":"P",
    "gn:feature_code":"PPL",
    "gn:name":"El Carrizal",
    "gn:population":11,
    "gn:timezone":"America/Mexico_City",
    "iso:country":"MX",
    "wof:name":"El Carrizal",
    "wof:placetype":"locality",
    "wof:population":11
},
  "geometry": {"coordinates":[-103.70694,21.13972],"type":"Point"}
}