{
  "type": "Feature",
  "properties": {
    "gn:admin1_code":"14.0",
    "gn:admin2_code":"102.0",
    "gn:asciiname":"La Barranca",
    "gn:country_code":"MX",
    "gn:dem":784,
    "gn:feature_class":"P",
    "gn:feature_code":"PPL",
    "gn:name":"La Barranca",
    "gn:population":0,
    "gn:timezone":"America/Mexico_City",
    "iso:country":"MX",
    "name:fra_x_preferred":[
        "La Barranca"
    ],
    "name:spa_x_preferred":[
        "La Barranca"
    ],
    "wof:name":"La Barranca",
    "wof:placetype":"locality"
},
  "geometry": {"coordinates":[-103.99797,19.75795],"type":"Point"}
}