{
  "type": "Feature",
  "properties": {
    "gn:admin1_code":"26.0",
    "gn:admin2_code":"59.0",
    "gn:asciiname":"Kitovaca",
    "gn:country_code":"MX",
    "gn:dem":1371,
    "gn:feature_class":"P",
    "gn:feature_code":"PPL",
    "gn:name":"Kitovaca",
    "gn:population":0,
    "gn:timezone":"America/Hermosillo",
    "iso:country":"MX",
    "name:spa_x_preferred":[
        "Kitovaca"
    ],
    "wof:name":"Kitovaca",
    "wof:placetype":"locality"
},
  "geometry": {"coordinates":[-110.5972,31.26742],"type":"Point"}
}