{
  "type": "Feature",
  "properties": {
    "gn:admin1_code":"14",
    "gn:admin2_code":"29.0",
    "gn:asciiname":"San Juan del Monte",
    "gn:country_code":"MX",
    "gn:dem":1788,
    "gn:feature_class":"P",
    "gn:feature_code":"PPL",
    "gn:name":"San Juan del Monte",
    "gn:population":0,
    "gn:timezone":"America/Mexico_City",
    "iso:country":"MX",
    "wof:name":"San Juan del Monte",
    "wof:placetype":"locality"
},
  "geometry": {"coordinates":[-103.12685,20.91668],"type":"Point"}
}