{
  "type": "Feature",
  "properties": {
    "gn:admin1_code":"25.0",
    "gn:asciiname":"San Isidro",
    "gn:country_code":"MX",
    "gn:dem":30,
    "gn:feature_class":"P",
    "gn:feature_code":"PPL",
    "gn:name":"San Isidro",
    "gn:population":0,
    "gn:timezone":"America/Mazatlan",
    "iso:country":"MX",
    "name:spa_x_preferred":[
        "San Isidro"
    ],
    "wof:name":"San Isidro",
    "wof:placetype":"locality"
},
  "geometry": {"coordinates":[-105.94244999999999,22.92139],"type":"Point"}
}