{
  "type": "Feature",
  "properties": {
    "gn:admin1_code":"26",
    "gn:admin2_code":"68.0",
    "gn:asciiname":"Campo Minero",
    "gn:country_code":"MX",
    "gn:dem":727,
    "gn:feature_class":"P",
    "gn:feature_code":"PPL",
    "gn:name":"Campo Minero",
    "gn:population":0,
    "gn:timezone":"America/Hermosillo",
    "iso:country":"MX",
    "name:spa_x_preferred":[
        "Campo Minero"
    ],
    "wof:name":"Campo Minero",
    "wof:placetype":"locality"
},
  "geometry": {"coordinates":[-109.95081999999999,29.0284],"type":"Point"}
}