{
  "type": "Feature",
  "properties": {
    "gn:admin1_code":"15.0",
    "gn:admin2_code":"124.0",
    "gn:asciiname":"Mesa del Mirto",
    "gn:country_code":"MX",
    "gn:dem":2728,
    "gn:feature_class":"P",
    "gn:feature_code":"PPL",
    "gn:name":"Mesa del Mirto",
    "gn:population":0,
    "gn:timezone":"America/Mexico_City",
    "iso:country":"MX",
    "name:spa_x_preferred":[
        "Mesa del Mirto"
    ],
    "wof:name":"Mesa del Mirto",
    "wof:placetype":"locality"
},
  "geometry": {"coordinates":[-100.13298,19.58767000000001],"type":"Point"}
}