{
  "type": "Feature",
  "properties": {
    "gn:admin1_code":"1",
    "gn:admin2_code":"1",
    "gn:asciiname":"La Cachucha (El Salero)",
    "gn:country_code":"MX",
    "gn:dem":1976,
    "gn:feature_class":"P",
    "gn:feature_code":"PPL",
    "gn:name":"La Cachucha (El Salero)",
    "gn:population":10,
    "gn:timezone":"America/Mexico_City",
    "iso:country":"MX",
    "wof:name":"La Cachucha (El Salero)",
    "wof:placetype":"locality",
    "wof:population":10
},
  "geometry": {"coordinates":[-102.16722,21.74222],"type":"Point"}
}