{
  "type": "Feature",
  "properties": {
    "gn:admin1_code":"24.0",
    "gn:admin2_code":"16.0",
    "gn:asciiname":"San Judas Tadeo",
    "gn:country_code":"MX",
    "gn:dem":25,
    "gn:feature_class":"P",
    "gn:feature_code":"PPL",
    "gn:name":"San Judas Tadeo",
    "gn:population":4,
    "gn:timezone":"America/Mexico_City",
    "iso:country":"MX",
    "name:spa_x_preferred":[
        "San Judas Tadeo"
    ],
    "wof:name":"San Judas Tadeo",
    "wof:placetype":"locality",
    "wof:population":4
},
  "geometry": {"coordinates":[-98.455,22.20333],"type":"Point"}
}