{
  "type": "Feature",
  "properties": {
    "gn:admin1_code":"14",
    "gn:admin2_code":"43.0",
    "gn:asciiname":"La Parota",
    "gn:country_code":"MX",
    "gn:dem":263,
    "gn:feature_class":"P",
    "gn:feature_code":"PPL",
    "gn:name":"La Parota",
    "gn:population":7,
    "gn:timezone":"America/Mexico_City",
    "iso:country":"MX",
    "wof:name":"La Parota",
    "wof:placetype":"locality",
    "wof:population":7
},
  "geometry": {"coordinates":[-104.67028000000001,19.49472],"type":"Point"}
}