{
  "type": "Feature",
  "properties": {
    "gn:admin1_code":"11.0",
    "gn:admin2_code":"14.0",
    "gn:asciiname":"San Nicolas de Trancas",
    "gn:country_code":"MX",
    "gn:dem":1949,
    "gn:feature_class":"P",
    "gn:feature_code":"PPL",
    "gn:name":"San Nicol\u00e1s de Trancas",
    "gn:population":0,
    "gn:timezone":"America/Mexico_City",
    "iso:country":"MX",
    "name:spa_x_preferred":[
        "San Nicol\u00e1s de Trancas"
    ],
    "wof:name":"San Nicolas de Trancas",
    "wof:placetype":"locality"
},
  "geometry": {"coordinates":[-100.99567999999999,21.29432000000001],"type":"Point"}
}