{
  "type": "Feature",
  "properties": {
    "gn:admin1_code":"11",
    "gn:admin2_code":"27.0",
    "gn:asciiname":"Locos de Domenzain (Los Loquitos)",
    "gn:country_code":"MX",
    "gn:dem":1729,
    "gn:feature_class":"P",
    "gn:feature_code":"PPL",
    "gn:name":"Locos de Domenz\u00e1in (Los Loquitos)",
    "gn:population":174,
    "gn:timezone":"America/Mexico_City",
    "iso:country":"MX",
    "name:und_x_variant":[
        "Locos de Domenz\u00e1in (Los Loquitos)"
    ],
    "wof:name":"Locos de Domenzain (Los Loquitos)",
    "wof:placetype":"locality",
    "wof:population":174
},
  "geometry": {"coordinates":[-101.1825,20.6575],"type":"Point"}
}