{
  "type": "Feature",
  "properties": {
    "gn:admin1_code":"6",
    "gn:admin2_code":"19.0",
    "gn:asciiname":"Soledad de Majalca",
    "gn:country_code":"MX",
    "gn:dem":2105,
    "gn:feature_class":"P",
    "gn:feature_code":"PPL",
    "gn:name":"Soledad de Majalca",
    "gn:population":0,
    "gn:timezone":"America/Chihuahua",
    "iso:country":"MX",
    "name:spa_x_preferred":[
        "Soledad de Majalca"
    ],
    "name:und_x_variant":[
        "Soledad",
        "La Soledad"
    ],
    "wof:name":"Soledad de Majalca",
    "wof:placetype":"locality"
},
  "geometry": {"coordinates":[-106.49745,28.79788],"type":"Point"}
}