{
  "type": "Feature",
  "properties": {
    "gn:admin1_code":"20",
    "gn:admin2_code":"334.0",
    "gn:asciiname":"San Jose Manialtepec",
    "gn:country_code":"MX",
    "gn:dem":22,
    "gn:feature_class":"P",
    "gn:feature_code":"PPL",
    "gn:name":"San Jos\u00e9 Manialtepec",
    "gn:population":0,
    "gn:timezone":"America/Mexico_City",
    "iso:country":"MX",
    "name:spa_x_preferred":[
        "San Jos\u00e9 Manialtepec"
    ],
    "wof:name":"San Jose Manialtepec",
    "wof:placetype":"locality"
},
  "geometry": {"coordinates":[-97.24413,15.97477],"type":"Point"}
}