{
  "type": "Feature",
  "properties": {
    "gn:admin1_code":"11",
    "gn:admin2_code":"14.0",
    "gn:asciiname":"Ojo de Agua de Cervantes",
    "gn:country_code":"MX",
    "gn:dem":2052,
    "gn:feature_class":"P",
    "gn:feature_code":"PPL",
    "gn:name":"Ojo de Agua de Cervantes",
    "gn:population":229,
    "gn:timezone":"America/Mexico_City",
    "iso:country":"MX",
    "wof:name":"Ojo de Agua de Cervantes",
    "wof:placetype":"locality",
    "wof:population":229
},
  "geometry": {"coordinates":[-101.04806000000001,21.16722],"type":"Point"}
}