{
  "type": "Feature",
  "properties": {
    "gn:admin1_code":"12",
    "gn:admin2_code":"45.0",
    "gn:asciiname":"San Lazaro (Tecojcosco)",
    "gn:country_code":"MX",
    "gn:dem":1716,
    "gn:feature_class":"P",
    "gn:feature_code":"PPL",
    "gn:name":"San L\u00e1zaro (Tecojcosco)",
    "gn:population":470,
    "gn:timezone":"America/Mexico_City",
    "iso:country":"MX",
    "name:und_x_variant":[
        "San L\u00e1zaro (Tecojcosco)"
    ],
    "wof:name":"San Lazaro (Tecojcosco)",
    "wof:placetype":"locality",
    "wof:population":470
},
  "geometry": {"coordinates":[-98.70426,17.89278],"type":"Point"}
}