{
  "type": "Feature",
  "properties": {
    "gn:admin1_code":"28.0",
    "gn:admin2_code":"12.0",
    "gn:asciiname":"Las Avelinas",
    "gn:country_code":"MX",
    "gn:dem":52,
    "gn:feature_class":"P",
    "gn:feature_code":"PPL",
    "gn:name":"Las Avelinas",
    "gn:population":2,
    "gn:timezone":"America/Monterrey",
    "iso:country":"MX",
    "name:spa_x_preferred":[
        "Las Avelinas"
    ],
    "name:spa_x_variant":[
        "La Loma"
    ],
    "wof:name":"Las Avelinas",
    "wof:placetype":"locality",
    "wof:population":2
},
  "geometry": {"coordinates":[-98.505,22.72639],"type":"Point"}
}