{
  "type": "Feature",
  "properties": {
    "gn:admin1_code":"30",
    "gn:admin2_code":"123.0",
    "gn:asciiname":"Chijol Diecisiete",
    "gn:country_code":"MX",
    "gn:dem":70,
    "gn:feature_class":"P",
    "gn:feature_code":"PPL",
    "gn:name":"Chijol Diecisiete",
    "gn:population":0,
    "gn:timezone":"America/Mexico_City",
    "iso:country":"MX",
    "name:spa_x_preferred":[
        "Chijol Diecisiete"
    ],
    "wof:name":"Chijol Diecisiete",
    "wof:placetype":"locality"
},
  "geometry": {"coordinates":[-98.27434,22.25035],"type":"Point"}
}