{
  "type": "Feature",
  "properties": {
    "gn:admin1_code":"3",
    "gn:admin2_code":"1.0",
    "gn:asciiname":"Punta el Cerro",
    "gn:country_code":"MX",
    "gn:dem":214,
    "gn:feature_class":"P",
    "gn:feature_code":"PPL",
    "gn:name":"Punta el Cerro",
    "gn:population":0,
    "gn:timezone":"America/Mazatlan",
    "iso:country":"MX",
    "name:spa_x_preferred":[
        "Punta el Cerro"
    ],
    "wof:name":"Punta el Cerro",
    "wof:placetype":"locality"
},
  "geometry": {"coordinates":[-111.70882,25.77644],"type":"Point"}
}