{
  "type": "Feature",
  "properties": {
    "gn:admin1_code":"5",
    "gn:admin2_code":"89.0",
    "gn:asciiname":"Astillero",
    "gn:country_code":"MX",
    "gn:dem":536,
    "gn:feature_class":"P",
    "gn:feature_code":"PPL",
    "gn:name":"Astillero",
    "gn:population":60,
    "gn:timezone":"America/Mexico_City",
    "iso:country":"MX",
    "wof:name":"Astillero",
    "wof:placetype":"locality",
    "wof:population":60
},
  "geometry": {"coordinates":[-92.20611,15.01861],"type":"Point"}
}