{
  "type": "Feature",
  "properties": {
    "gn:admin1_code":"29",
    "gn:admin2_code":"34.0",
    "gn:asciiname":"Tetechilco",
    "gn:country_code":"MX",
    "gn:dem":2691,
    "gn:feature_class":"P",
    "gn:feature_code":"PPL",
    "gn:name":"Tetechilco",
    "gn:population":0,
    "gn:timezone":"America/Mexico_City",
    "iso:country":"MX",
    "name:spa_x_preferred":[
        "Tetechilco"
    ],
    "wof:name":"Tetechilco",
    "wof:placetype":"locality"
},
  "geometry": {"coordinates":[-98.08871000000001,19.57221],"type":"Point"}
}