{
  "type": "Feature",
  "properties": {
    "gn:admin1_code":"24",
    "gn:admin2_code":"36.0",
    "gn:asciiname":"Pozo Cuates",
    "gn:country_code":"MX",
    "gn:dem":1045,
    "gn:feature_class":"P",
    "gn:feature_code":"PPL",
    "gn:name":"Pozo Cuates",
    "gn:population":84,
    "gn:timezone":"America/Mexico_City",
    "iso:country":"MX",
    "wof:name":"Pozo Cuates",
    "wof:placetype":"locality",
    "wof:population":84
},
  "geometry": {"coordinates":[-99.49222,21.80028],"type":"Point"}
}