{
  "type": "Feature",
  "properties": {
    "gn:admin1_code":"13",
    "gn:admin2_code":"7.0",
    "gn:asciiname":"Portezuelo",
    "gn:country_code":"MX",
    "gn:dem":2805,
    "gn:feature_class":"P",
    "gn:feature_code":"PPL",
    "gn:name":"Portezuelo",
    "gn:population":0,
    "gn:timezone":"America/Mexico_City",
    "iso:country":"MX",
    "name:spa_x_preferred":[
        "Portezuelo"
    ],
    "name:spa_x_variant":[
        "El Portezuelo"
    ],
    "wof:name":"Portezuelo",
    "wof:placetype":"locality"
},
  "geometry": {"coordinates":[-98.28158999999999,19.79424],"type":"Point"}
}