{
  "type": "Feature",
  "properties": {
    "gn:admin1_code":"13",
    "gn:admin2_code":"73.0",
    "gn:asciiname":"Cuatatlan",
    "gn:country_code":"MX",
    "gn:dem":1183,
    "gn:feature_class":"P",
    "gn:feature_code":"PPL",
    "gn:name":"Cuatatl\u00e1n",
    "gn:population":0,
    "gn:timezone":"America/Mexico_City",
    "iso:country":"MX",
    "name:spa_x_preferred":[
        "Cuatatl\u00e1n"
    ],
    "name:spa_x_variant":[
        "Cuatlat\u00e1n"
    ],
    "wof:name":"Cuatatlan",
    "wof:placetype":"locality"
},
  "geometry": {"coordinates":[-98.61262000000001,20.99933],"type":"Point"}
}