{
  "type": "Feature",
  "properties": {
    "gn:country":"MX",
    "gn:fcode":"PPL",
    "gn:population":0,
    "iso:country":"MX",
    "name:cat_x_preferred":[
        "Independ\u00e8ncia"
    ],
    "name:ceb_x_preferred":[
        "Independencia"
    ],
    "name:deu_x_preferred":[
        "Independencia"
    ],
    "name:epo_x_preferred":[
        "Independencia"
    ],
    "name:fra_x_preferred":[
        "Independencia"
    ],
    "name:heb_x_preferred":[
        "\u05d0\u05d9\u05e0\u05d3\u05e4\u05e0\u05d3\u05e0\u05e1\u05d9\u05d4"
    ],
    "name:hun_x_preferred":[
        "Independencia"
    ],
    "name:ita_x_preferred":[
        "Independencia"
    ],
    "name:kor_x_preferred":[
        "\uc778\ub370\ud39c\ub374\uc2dc\uc544"
    ],
    "name:nld_x_preferred":[
        "Independencia"
    ],
    "name:nor_x_preferred":[
        "Independencia"
    ],
    "name:rus_x_preferred":[
        "\u0418\u043d\u0434\u0435\u043f\u0435\u043d\u0434\u0435\u043d\u0441\u0438\u044f"
    ],
    "name:sco_x_preferred":[
        "Independencia"
    ],
    "name:spa_x_preferred":[
        "Independencia"
    ],
    "name:swe_x_preferred":[
        "Independencia"
    ],
    "name:ukr_x_preferred":[
        "\u0406\u043d\u0434\u0435\u043f\u0435\u043d\u0434\u0435\u043d\u0441\u0456\u044f"
    ],
    "qs_pg:aaroncc":"MX",
    "qs_pg:gn_country":"MX",
    "qs_pg:gn_fcode":"PPL",
    "qs_pg:gn_pop":0,
    "qs_pg:name":"Independencia",
    "qs_pg:name_adm0":"M\u00e9xico",
    "qs_pg:name_adm1":"Tamaulipas",
    "qs_pg:photos":1,
    "qs_pg:photos_1k":1,
    "qs_pg:photos_9k":1,
    "qs_pg:photos_9r":1,
    "qs_pg:photos_all":1,
    "qs_pg:photos_sr":1,
    "qs_pg:pop_sr":0,
    "qs_pg:qs_pg_placetype":"neighbourhood",
    "qs_pg:qs_pg_placetype_gp":"Suburb",
    "qs_pg:woe_adm0":23424900,
    "woe:adm0_id":23424900,
    "woe:name_adm0":"M\u00e9xico",
    "woe:name_adm1":"Tamaulipas",
    "woe:placetype":"Suburb",
    "wof:name":"Independencia",
    "wof:placetype":"neighbourhood"
},
  "geometry": {"coordinates":[-98.96424,23.29792],"type":"Point"}
}