{
  "type": "Feature",
  "properties": {
    "gn:admin1_code":"26",
    "gn:admin2_code":"30.0",
    "gn:asciiname":"Santa Eduwiges",
    "gn:country_code":"MX",
    "gn:dem":283,
    "gn:feature_class":"P",
    "gn:feature_code":"PPL",
    "gn:name":"Santa Eduwiges",
    "gn:population":6,
    "gn:timezone":"America/Hermosillo",
    "iso:country":"MX",
    "wof:name":"Santa Eduwiges",
    "wof:placetype":"locality",
    "wof:population":6
},
  "geometry": {"coordinates":[-110.87944,29.27167],"type":"Point"}
}