{
  "type": "Feature",
  "properties": {
    "gn:admin1_code":"14",
    "gn:admin2_code":"3.0",
    "gn:asciiname":"Santa Cruz Dos [Granja]",
    "gn:country_code":"MX",
    "gn:dem":1360,
    "gn:feature_class":"P",
    "gn:feature_code":"PPL",
    "gn:name":"Santa Cruz Dos [Granja]",
    "gn:population":7,
    "gn:timezone":"America/Mexico_City",
    "iso:country":"MX",
    "wof:name":"Santa Cruz Dos [Granja]",
    "wof:placetype":"locality",
    "wof:population":7
},
  "geometry": {"coordinates":[-103.99806,20.68389],"type":"Point"}
}