{
  "type": "Feature",
  "properties": {
    "gn:admin1_code":"7",
    "gn:admin2_code":"4.0",
    "gn:asciiname":"Las Sombrillas",
    "gn:country_code":"MX",
    "gn:dem":2183,
    "gn:feature_class":"P",
    "gn:feature_code":"PPL",
    "gn:name":"Las Sombrillas",
    "gn:population":0,
    "gn:timezone":"America/Monterrey",
    "iso:country":"MX",
    "name:spa_x_preferred":[
        "Las Sombrillas"
    ],
    "wof:name":"Las Sombrillas",
    "wof:placetype":"locality"
},
  "geometry": {"coordinates":[-100.48455,25.40473],"type":"Point"}
}