{
  "type": "Feature",
  "properties": {
    "gn:admin1_code":"11.0",
    "gn:admin2_code":"20.0",
    "gn:asciiname":"La Estancia Nueva",
    "gn:country_code":"MX",
    "gn:dem":1776,
    "gn:feature_class":"P",
    "gn:feature_code":"PPL",
    "gn:name":"La Estancia Nueva",
    "gn:population":0,
    "gn:timezone":"America/Mexico_City",
    "iso:country":"MX",
    "name:spa_x_preferred":[
        "La Estancia Nueva"
    ],
    "wof:name":"La Estancia Nueva",
    "wof:placetype":"locality"
},
  "geometry": {"coordinates":[-101.75703,21.02106],"type":"Point"}
}