{
  "type": "Feature",
  "properties": {
    "gn:admin1_code":"30",
    "gn:admin2_code":"172.0",
    "gn:asciiname":"San Miguel",
    "gn:country_code":"MX",
    "gn:dem":29,
    "gn:feature_class":"P",
    "gn:feature_code":"PPL",
    "gn:name":"San Miguel",
    "gn:population":6,
    "gn:timezone":"America/Mexico_City",
    "iso:country":"MX",
    "name:bre_x_preferred":[
        "San Miguel"
    ],
    "name:bul_x_preferred":[
        "\u0421\u0430\u043d \u041c\u0438\u0433\u0435\u043b"
    ],
    "name:cat_x_preferred":[
        "San Miguel"
    ],
    "name:ceb_x_preferred":[
        "San Miguel"
    ],
    "name:deu_x_preferred":[
        "San Miguel"
    ],
    "name:est_x_preferred":[
        "San Miguel"
    ],
    "name:eus_x_preferred":[
        "San Miguel"
    ],
    "name:fra_x_preferred":[
        "San Miguel"
    ],
    "name:glg_x_preferred":[
        "San Miguel"
    ],
    "name:heb_x_preferred":[
        "\u05e1\u05df \u05de\u05d9\u05d2\u05dc"
    ],
    "name:ilo_x_preferred":[
        "San Miguel"
    ],
    "name:ita_x_preferred":[
        "San Miguel"
    ],
    "name:jpn_x_preferred":[
        "\u30b5\u30f3\u30fb\u30df\u30b2\u30eb"
    ],
    "name:kat_x_preferred":[
        "\u10e1\u10d0\u10dc-\u10db\u10d8\u10d2\u10d4\u10da\u10d8"
    ],
    "name:kor_x_preferred":[
        "\uc0b0\ubbf8\uac94"
    ],
    "name:lit_x_preferred":[
        "San Migelis"
    ],
    "name:nah_x_preferred":[
        "San Miguel"
    ],
    "name:nds_x_preferred":[
        "San Miguel"
    ],
    "name:nld_x_preferred":[
        "San Miguel"
    ],
    "name:pol_x_preferred":[
        "San Miguel"
    ],
    "name:por_x_preferred":[
        "San Miguel"
    ],
    "name:que_x_preferred":[
        "San Miyil"
    ],
    "name:ron_x_preferred":[
        "San Miguel"
    ],
    "name:rus_x_preferred":[
        "\u0421\u0430\u043d-\u041c\u0438\u0433\u0435\u043b\u044c"
    ],
    "name:sco_x_preferred":[
        "San Miguel"
    ],
    "name:slk_x_preferred":[
        "San Miguel"
    ],
    "name:spa_x_preferred":[
        "San Miguel"
    ],
    "name:srp_x_preferred":[
        "\u0421\u0430\u043d \u041c\u0438\u0433\u0435\u043b"
    ],
    "name:swe_x_preferred":[
        "San Miguel"
    ],
    "name:tgl_x_preferred":[
        "San Miguel"
    ],
    "name:ukr_x_preferred":[
        "\u0421\u0430\u043d-\u041c\u0456\u0433\u0435\u043b\u044c"
    ],
    "name:war_x_preferred":[
        "San Miguel"
    ],
    "wof:name":"San Miguel",
    "wof:placetype":"locality",
    "wof:population":6
},
  "geometry": {"coordinates":[-94.83889000000001,17.91222],"type":"Point"}
}