{
  "type": "Feature",
  "properties": {
    "gn:admin1_code":"16",
    "gn:admin2_code":"110.0",
    "gn:asciiname":"San Ildefonso",
    "gn:country_code":"MX",
    "gn:dem":2471,
    "gn:feature_class":"P",
    "gn:feature_code":"PPL",
    "gn:name":"San Ildefonso",
    "gn:population":664,
    "gn:timezone":"America/Mexico_City",
    "iso:country":"MX",
    "wof:name":"San Ildefonso",
    "wof:placetype":"locality",
    "wof:population":664
},
  "geometry": {"coordinates":[-100.61888999999999,19.92722],"type":"Point"}
}