{
  "type": "Feature",
  "properties": {
    "gn:admin1_code":"13",
    "gn:admin2_code":"14.0",
    "gn:asciiname":"Ahuamolos",
    "gn:country_code":"MX",
    "gn:dem":784,
    "gn:feature_class":"P",
    "gn:feature_code":"PPL",
    "gn:name":"Ahuamolos",
    "gn:population":75,
    "gn:timezone":"America/Mexico_City",
    "iso:country":"MX",
    "wof:name":"Ahuamolos",
    "wof:placetype":"locality",
    "wof:population":75
},
  "geometry": {"coordinates":[-98.52623,20.8894],"type":"Point"}
}