{
  "type": "Feature",
  "properties": {
    "gn:admin1_code":"12",
    "gn:admin2_code":"23.0",
    "gn:asciiname":"Rancho Euripides Navarrete",
    "gn:country_code":"MX",
    "gn:dem":22,
    "gn:feature_class":"P",
    "gn:feature_code":"PPL",
    "gn:name":"Rancho Eur\u00edpides Navarrete",
    "gn:population":5,
    "gn:timezone":"America/Mexico_City",
    "iso:country":"MX",
    "name:und_x_variant":[
        "Rancho Eur\u00edpides Navarrete"
    ],
    "wof:name":"Rancho Euripides Navarrete",
    "wof:placetype":"locality",
    "wof:population":5
},
  "geometry": {"coordinates":[-98.49766,16.48657],"type":"Point"}
}