{
  "type": "Feature",
  "properties": {
    "gn:admin1_code":"12",
    "gn:admin2_code":"41.0",
    "gn:asciiname":"Huehuetepec",
    "gn:country_code":"MX",
    "gn:dem":1436,
    "gn:feature_class":"P",
    "gn:feature_code":"PPL",
    "gn:name":"Huehuetepec",
    "gn:population":0,
    "gn:timezone":"America/Mexico_City",
    "iso:country":"MX",
    "wof:name":"Huehuetepec",
    "wof:placetype":"locality"
},
  "geometry": {"coordinates":[-98.63333,17.13332999999999],"type":"Point"}
}