{
  "type": "Feature",
  "properties": {
    "gn:admin1_code":"21",
    "gn:admin2_code":"154",
    "gn:asciiname":"Barrio de Jalacingo (San Mateo Seccion 23)",
    "gn:country_code":"MX",
    "gn:dem":2120,
    "gn:feature_class":"P",
    "gn:feature_code":"PPL",
    "gn:name":"Barrio de Jalacingo (San Mateo Secci\u00f3n 23)",
    "gn:population":34,
    "gn:timezone":"America/Mexico_City",
    "iso:country":"MX",
    "name:und_x_variant":[
        "Barrio de Jalacingo (San Mateo Secci\u00f3n 23)"
    ],
    "wof:name":"Barrio de Jalacingo (San Mateo Seccion 23)",
    "wof:placetype":"locality",
    "wof:population":34
},
  "geometry": {"coordinates":[-97.72384,18.92182],"type":"Point"}
}