{
  "type": "Feature",
  "properties": {
    "gn:gn_country":"MX",
    "gn:gn_fcode":"PPL",
    "gn:gn_pop":5411,
    "gn:population":5411,
    "iso:country":"MX",
    "name:spa_x_preferred":[
        "San Pedro Tlanixco"
    ],
    "name:unk_x_variant":[
        "Tlanixco"
    ],
    "qs_pg:aaroncc":"MX",
    "qs_pg:gn_country":"MX",
    "qs_pg:gn_fcode":"PPL",
    "qs_pg:gn_pop":5411,
    "qs_pg:name":"San Pedro Tlanisco",
    "qs_pg:name_adm0":"M\u00e9xico",
    "qs_pg:name_adm1":"Mexico",
    "qs_pg:photos_9k":2,
    "qs_pg:photos_9r":5,
    "qs_pg:photos_all":369,
    "qs_pg:photos_sr":0,
    "qs_pg:pop_sr":5,
    "qs_pg:qs_pg_placetype":"locality",
    "qs_pg:qs_pg_placetype_gp":"Town",
    "qs_pg:woe_adm0":23424900,
    "woe:adm0_id":23424900,
    "woe:name_adm0":"M\u00e9xico",
    "woe:name_adm1":"Mexico",
    "woe:placetype":"Town",
    "wof:name":"San Pedro Tlanisco",
    "wof:placetype":"locality",
    "wof:population":5411
},
  "geometry": {"coordinates":[-99.65260000000001,19.0636],"type":"Point"}
}