{
  "type": "Feature",
  "properties": {
    "gn:admin1_code":"25.0",
    "gn:admin2_code":"3.0",
    "gn:asciiname":"El Encinal",
    "gn:country_code":"MX",
    "gn:dem":1072,
    "gn:feature_class":"P",
    "gn:feature_code":"PPL",
    "gn:name":"El Encinal",
    "gn:population":0,
    "gn:timezone":"America/Mazatlan",
    "iso:country":"MX",
    "name:spa_x_preferred":[
        "El Encinal"
    ],
    "wof:name":"El Encinal",
    "wof:placetype":"locality"
},
  "geometry": {"coordinates":[-107.24500999999999,25.60499],"type":"Point"}
}