{
  "type": "Feature",
  "properties": {
    "gn:admin1_code":"5.0",
    "gn:asciiname":"El Cielito",
    "gn:country_code":"MX",
    "gn:dem":772,
    "gn:feature_class":"P",
    "gn:feature_code":"PPL",
    "gn:name":"El Cielito",
    "gn:population":0,
    "gn:timezone":"America/Mexico_City",
    "iso:country":"MX",
    "name:spa_x_preferred":[
        "El Cielito"
    ],
    "wof:name":"El Cielito",
    "wof:placetype":"locality"
},
  "geometry": {"coordinates":[-93.41142000000001,16.69965],"type":"Point"}
}