{
  "type": "Feature",
  "properties": {
    "gn:admin1_code":"30",
    "gn:admin2_code":"71.0",
    "gn:asciiname":"Alta Luz",
    "gn:country_code":"MX",
    "gn:dem":1147,
    "gn:feature_class":"P",
    "gn:feature_code":"PPL",
    "gn:name":"Alta Luz",
    "gn:population":655,
    "gn:timezone":"America/Mexico_City",
    "iso:country":"MX",
    "wof:name":"Alta Luz",
    "wof:placetype":"locality",
    "wof:population":655
},
  "geometry": {"coordinates":[-96.95,19.08583],"type":"Point"}
}