{
  "type": "Feature",
  "properties": {
    "gn:admin1_code":"30.0",
    "gn:admin2_code":"123.0",
    "gn:asciiname":"El Cuadro",
    "gn:country_code":"MX",
    "gn:dem":19,
    "gn:feature_class":"P",
    "gn:feature_code":"PPL",
    "gn:name":"El Cuadro",
    "gn:population":0,
    "gn:timezone":"America/Mexico_City",
    "iso:country":"MX",
    "name:spa_x_preferred":[
        "El Cuadro"
    ],
    "wof:name":"El Cuadro",
    "wof:placetype":"locality"
},
  "geometry": {"coordinates":[-98.50917,21.95826],"type":"Point"}
}