{
  "type": "Feature",
  "properties": {
    "gn:admin1_code":"20",
    "gn:admin2_code":"551",
    "gn:asciiname":"El Baratillo",
    "gn:country_code":"MX",
    "gn:dem":1605,
    "gn:feature_class":"P",
    "gn:feature_code":"PPL",
    "gn:name":"El Baratillo",
    "gn:population":16,
    "gn:timezone":"America/Mexico_City",
    "iso:country":"MX",
    "wof:name":"El Baratillo",
    "wof:placetype":"locality",
    "wof:population":16
},
  "geometry": {"coordinates":[-96.49194,16.95972],"type":"Point"}
}