{
  "type": "Feature",
  "properties": {
    "gn:admin1_code":"25",
    "gn:admin2_code":"16.0",
    "gn:asciiname":"El Cuichi",
    "gn:country_code":"MX",
    "gn:dem":183,
    "gn:feature_class":"P",
    "gn:feature_code":"PPL",
    "gn:name":"El Cuichi",
    "gn:population":0,
    "gn:timezone":"America/Mazatlan",
    "iso:country":"MX",
    "name:spa_x_preferred":[
        "El Cuichi"
    ],
    "name:und_x_variant":[
        "El Cuhichi"
    ],
    "wof:name":"El Cuichi",
    "wof:placetype":"locality"
},
  "geometry": {"coordinates":[-106.54165,23.8175],"type":"Point"}
}