{
  "type": "Feature",
  "properties": {
    "gn:admin1_code":"12.0",
    "gn:admin2_code":"57.0",
    "gn:asciiname":"Puerto de la Angostura",
    "gn:country_code":"MX",
    "gn:dem":1225,
    "gn:feature_class":"P",
    "gn:feature_code":"PPL",
    "gn:name":"Puerto de la Angostura",
    "gn:population":0,
    "gn:timezone":"America/Mexico_City",
    "iso:country":"MX",
    "name:spa_x_preferred":[
        "Puerto de la Angostura"
    ],
    "wof:name":"Puerto de la Angostura",
    "wof:placetype":"locality"
},
  "geometry": {"coordinates":[-100.96241999999999,17.45896],"type":"Point"}
}