{
  "type": "Feature",
  "properties": {
    "gn:admin1_code":"14.0",
    "gn:admin2_code":"43.0",
    "gn:asciiname":"El Tres",
    "gn:country_code":"MX",
    "gn:dem":18,
    "gn:feature_class":"P",
    "gn:feature_code":"PPL",
    "gn:name":"El Tres",
    "gn:population":0,
    "gn:timezone":"America/Mexico_City",
    "iso:country":"MX",
    "name:spa_x_preferred":[
        "El Tres"
    ],
    "wof:name":"El Tres",
    "wof:placetype":"locality"
},
  "geometry": {"coordinates":[-105.09578,19.59159],"type":"Point"}
}