{
  "type": "Feature",
  "properties": {
    "gn:admin1_code":"18",
    "gn:admin2_code":"9.0",
    "gn:asciiname":"Palma Chica",
    "gn:country_code":"MX",
    "gn:dem":1057,
    "gn:feature_class":"P",
    "gn:feature_code":"PPL",
    "gn:name":"Palma Chica",
    "gn:population":114,
    "gn:timezone":"America/Mazatlan",
    "iso:country":"MX",
    "wof:name":"Palma Chica",
    "wof:placetype":"locality",
    "wof:population":114
},
  "geometry": {"coordinates":[-104.39028,21.97944],"type":"Point"}
}