{
  "type": "Feature",
  "properties": {
    "gn:admin1_code":"18",
    "gn:admin2_code":"19.0",
    "gn:asciiname":"La Minita",
    "gn:country_code":"MX",
    "gn:dem":747,
    "gn:feature_class":"P",
    "gn:feature_code":"PPL",
    "gn:name":"La Minita",
    "gn:population":6,
    "gn:timezone":"America/Mazatlan",
    "iso:country":"MX",
    "wof:name":"La Minita",
    "wof:placetype":"locality",
    "wof:population":6
},
  "geometry": {"coordinates":[-104.21693999999999,21.19],"type":"Point"}
}