{
  "type": "Feature",
  "properties": {
    "gn:admin1_code":"19",
    "gn:admin2_code":"11.0",
    "gn:asciiname":"La Bermeja",
    "gn:country_code":"MX",
    "gn:dem":190,
    "gn:feature_class":"P",
    "gn:feature_code":"PPL",
    "gn:name":"La Bermeja",
    "gn:population":0,
    "gn:timezone":"America/Monterrey",
    "iso:country":"MX",
    "name:spa_x_preferred":[
        "La Bermeja"
    ],
    "name:und_x_variant":[
        "Bermeja"
    ],
    "wof:name":"La Bermeja",
    "wof:placetype":"locality"
},
  "geometry": {"coordinates":[-99.55135,25.89654],"type":"Point"}
}