{
  "type": "Feature",
  "properties": {
    "gn:admin1_code":"24.0",
    "gn:admin2_code":"24.0",
    "gn:asciiname":"Agua del Venado",
    "gn:country_code":"MX",
    "gn:dem":1461,
    "gn:feature_class":"P",
    "gn:feature_code":"PPL",
    "gn:name":"Agua del Venado",
    "gn:population":0,
    "gn:timezone":"America/Mexico_City",
    "iso:country":"MX",
    "name:spa_x_preferred":[
        "Agua del Venado"
    ],
    "wof:name":"Agua del Venado",
    "wof:placetype":"locality"
},
  "geometry": {"coordinates":[-100.16007999999999,21.75937],"type":"Point"}
}