{
  "type": "Feature",
  "properties": {
    "gn:admin1_code":"32",
    "gn:admin2_code":"42.0",
    "gn:asciiname":"San Antonio del Cerrito (El Cerrito)",
    "gn:country_code":"MX",
    "gn:dem":2074,
    "gn:feature_class":"P",
    "gn:feature_code":"PPL",
    "gn:name":"San Antonio del Cerrito (El Cerrito)",
    "gn:population":201,
    "gn:timezone":"America/Mexico_City",
    "iso:country":"MX",
    "wof:name":"San Antonio del Cerrito (El Cerrito)",
    "wof:placetype":"locality",
    "wof:population":201
},
  "geometry": {"coordinates":[-103.7565,23.53169],"type":"Point"}
}