{
  "type": "Feature",
  "properties": {
    "gn:admin1_code":"21",
    "gn:admin2_code":"40",
    "gn:asciiname":"Totoquetzale",
    "gn:country_code":"MX",
    "gn:dem":2213,
    "gn:feature_class":"P",
    "gn:feature_code":"PPL",
    "gn:name":"Totoquetzale",
    "gn:population":14,
    "gn:timezone":"America/Mexico_City",
    "iso:country":"MX",
    "wof:name":"Totoquetzale",
    "wof:placetype":"locality",
    "wof:population":14
},
  "geometry": {"coordinates":[-97.98496,18.93321],"type":"Point"}
}