{
  "type": "Feature",
  "properties": {
    "gn:admin1_code":"30.0",
    "gn:admin2_code":"145.0",
    "gn:asciiname":"Villalta",
    "gn:country_code":"MX",
    "gn:dem":69,
    "gn:feature_class":"P",
    "gn:feature_code":"PPL",
    "gn:name":"Villalta",
    "gn:population":0,
    "gn:timezone":"America/Mexico_City",
    "iso:country":"MX",
    "name:rus_x_preferred":[
        "\u0412\u0438\u043b\u044c\u044f\u043b\u044c\u0442\u0430"
    ],
    "name:spa_x_preferred":[
        "Villalta"
    ],
    "wof:name":"Villalta",
    "wof:placetype":"locality"
},
  "geometry": {"coordinates":[-94.88479,17.95377000000001],"type":"Point"}
}