{
  "type": "Feature",
  "properties": {
    "gn:admin1_code":"2",
    "gn:admin2_code":"1.0",
    "gn:asciiname":"Parcela Setenta y Nueve",
    "gn:country_code":"MX",
    "gn:dem":339,
    "gn:feature_class":"P",
    "gn:feature_code":"PPL",
    "gn:name":"Parcela Setenta y Nueve",
    "gn:population":57,
    "gn:timezone":"America/Tijuana",
    "iso:country":"MX",
    "wof:name":"Parcela Setenta y Nueve",
    "wof:placetype":"locality",
    "wof:population":57
},
  "geometry": {"coordinates":[-116.64639,32.08556],"type":"Point"}
}