{
  "type": "Feature",
  "properties": {
    "gn:admin1_code":"21",
    "gn:admin2_code":"128",
    "gn:asciiname":"Santa Martha",
    "gn:country_code":"MX",
    "gn:dem":2420,
    "gn:feature_class":"P",
    "gn:feature_code":"PPL",
    "gn:name":"Santa Martha",
    "gn:population":30,
    "gn:timezone":"America/Mexico_City",
    "iso:country":"MX",
    "wof:name":"Santa Martha",
    "wof:placetype":"locality",
    "wof:population":30
},
  "geometry": {"coordinates":[-97.76716999999999,19.28401],"type":"Point"}
}