{
  "type": "Feature",
  "properties": {
    "gn:admin1_code":"19.0",
    "gn:admin2_code":"20.0",
    "gn:asciiname":"La Corona",
    "gn:country_code":"MX",
    "gn:dem":184,
    "gn:feature_class":"P",
    "gn:feature_code":"PPL",
    "gn:name":"La Corona",
    "gn:population":0,
    "gn:timezone":"America/Monterrey",
    "iso:country":"MX",
    "name:spa_x_preferred":[
        "La Corona"
    ],
    "wof:name":"La Corona",
    "wof:placetype":"locality"
},
  "geometry": {"coordinates":[-98.81258,25.69],"type":"Point"}
}