{
  "type": "Feature",
  "properties": {
    "gn:admin1_code":"23",
    "gn:admin2_code":"9.0",
    "gn:asciiname":"Yodzont",
    "gn:country_code":"MX",
    "gn:dem":17,
    "gn:feature_class":"P",
    "gn:feature_code":"PPL",
    "gn:name":"Yodzont",
    "gn:population":0,
    "gn:timezone":"America/Cancun",
    "iso:country":"MX",
    "name:spa_x_preferred":[
        "Yodzont"
    ],
    "name:und_x_variant":[
        "Yodzonot"
    ],
    "wof:name":"Yodzont",
    "wof:placetype":"locality"
},
  "geometry": {"coordinates":[-87.65602,20.46373],"type":"Point"}
}