{
  "type": "Feature",
  "properties": {
    "gn:admin1_code":"14.0",
    "gn:admin2_code":"38.0",
    "gn:asciiname":"El Barquieno",
    "gn:country_code":"MX",
    "gn:dem":1308,
    "gn:feature_class":"P",
    "gn:feature_code":"PPL",
    "gn:name":"El Barquie\u00f1o",
    "gn:population":0,
    "gn:timezone":"America/Mexico_City",
    "iso:country":"MX",
    "name:spa_x_preferred":[
        "El Barquie\u00f1o"
    ],
    "wof:name":"El Barquieno",
    "wof:placetype":"locality"
},
  "geometry": {"coordinates":[-104.47534,20.61925],"type":"Point"}
}