{
  "type": "Feature",
  "properties": {
    "gn:admin1_code":"17",
    "gn:admin2_code":"3.0",
    "gn:asciiname":"Joaquin Camano",
    "gn:country_code":"MX",
    "gn:dem":998,
    "gn:feature_class":"P",
    "gn:feature_code":"PPL",
    "gn:name":"Joaqu\u00edn Cama\u00f1o",
    "gn:population":411,
    "gn:timezone":"America/Mexico_City",
    "iso:country":"MX",
    "name:und_x_variant":[
        "Joaqu\u00edn Cama\u00f1o"
    ],
    "wof:name":"Joaquin Camano",
    "wof:placetype":"locality",
    "wof:population":411
},
  "geometry": {"coordinates":[-98.79639,18.49833],"type":"Point"}
}