{
  "type": "Feature",
  "properties": {
    "gn:admin1_code":"10.0",
    "gn:admin2_code":"26.0",
    "gn:asciiname":"Cielo Azul",
    "gn:country_code":"MX",
    "gn:dem":2752,
    "gn:feature_class":"P",
    "gn:feature_code":"PPL",
    "gn:name":"Cielo Azul",
    "gn:population":0,
    "gn:timezone":"America/Monterrey",
    "iso:country":"MX",
    "name:spa_x_preferred":[
        "Cielo Azul"
    ],
    "wof:name":"Cielo Azul",
    "wof:placetype":"locality"
},
  "geometry": {"coordinates":[-105.89622,24.3758],"type":"Point"}
}