{
  "type": "Feature",
  "properties": {
    "gn:admin1_code":"5",
    "gn:admin2_code":"38.0",
    "gn:asciiname":"San Jose la Nueva",
    "gn:country_code":"MX",
    "gn:dem":1832,
    "gn:feature_class":"P",
    "gn:feature_code":"PPL",
    "gn:name":"San Jos\u00e9 la Nueva",
    "gn:population":336,
    "gn:timezone":"America/Mexico_City",
    "iso:country":"MX",
    "name:und_x_variant":[
        "San Jos\u00e9 la Nueva"
    ],
    "wof:name":"San Jose la Nueva",
    "wof:placetype":"locality",
    "wof:population":336
},
  "geometry": {"coordinates":[-92.32889,16.675],"type":"Point"}
}