{
  "type": "Feature",
  "properties": {
    "gn:admin1_code":"20.0",
    "gn:admin2_code":"207.0",
    "gn:asciiname":"La Esperanza Segunda Seccion",
    "gn:country_code":"MX",
    "gn:dem":160,
    "gn:feature_class":"P",
    "gn:feature_code":"PPL",
    "gn:name":"La Esperanza Segunda Secci\u00f3n",
    "gn:population":0,
    "gn:timezone":"America/Mexico_City",
    "iso:country":"MX",
    "name:spa_x_preferred":[
        "La Esperanza Segunda Secci\u00f3n"
    ],
    "wof:name":"La Esperanza Segunda Seccion",
    "wof:placetype":"locality"
},
  "geometry": {"coordinates":[-95.19034000000001,17.29674],"type":"Point"}
}