{
  "type": "Feature",
  "properties": {
    "gn:admin1_code":"1",
    "gn:admin2_code":"6",
    "gn:asciiname":"El Infierno [Rancho]",
    "gn:country_code":"MX",
    "gn:dem":1920,
    "gn:feature_class":"P",
    "gn:feature_code":"PPL",
    "gn:name":"El Infierno [Rancho]",
    "gn:population":9,
    "gn:timezone":"America/Mexico_City",
    "iso:country":"MX",
    "wof:name":"El Infierno [Rancho]",
    "wof:placetype":"locality",
    "wof:population":9
},
  "geometry": {"coordinates":[-102.24806,22.14139],"type":"Point"}
}