{
  "type": "Feature",
  "properties": {
    "gn:admin1_code":"5",
    "gn:admin2_code":"89.0",
    "gn:asciiname":"Andalucia",
    "gn:country_code":"MX",
    "gn:dem":459,
    "gn:feature_class":"P",
    "gn:feature_code":"PPL",
    "gn:name":"Andaluc\u00eda",
    "gn:population":5,
    "gn:timezone":"America/Mexico_City",
    "iso:country":"MX",
    "name:und_x_variant":[
        "Andaluc\u00eda"
    ],
    "wof:name":"Andalucia",
    "wof:placetype":"locality",
    "wof:population":5
},
  "geometry": {"coordinates":[-92.31389,15.04444],"type":"Point"}
}