{
  "type": "Feature",
  "properties": {
    "gn:admin1_code":"5",
    "gn:admin2_code":"89.0",
    "gn:asciiname":"Esmeralda",
    "gn:cc2":"MX",
    "gn:country_code":"MX",
    "gn:dem":459,
    "gn:feature_class":"P",
    "gn:feature_code":"PPL",
    "gn:name":"Esmeralda",
    "gn:population":3,
    "gn:timezone":"America/Mexico_City",
    "iso:country":"MX",
    "name:und_x_variant":[
        "La Esmeralda"
    ],
    "wof:name":"Esmeralda",
    "wof:placetype":"locality",
    "wof:population":3
},
  "geometry": {"coordinates":[-92.31528,15.04194],"type":"Point"}
}