{
  "type": "Feature",
  "properties": {
    "gn:admin1_code":"16.0",
    "gn:admin2_code":"67.0",
    "gn:asciiname":"Tirimacuaro (Valanciana)",
    "gn:country_code":"MX",
    "gn:dem":1695,
    "gn:feature_class":"P",
    "gn:feature_code":"PPL",
    "gn:name":"Tirim\u00e1cuaro (Valanciana)",
    "gn:population":919,
    "gn:timezone":"America/Mexico_City",
    "iso:country":"MX",
    "wof:name":"Tirimacuaro (Valanciana)",
    "wof:placetype":"locality",
    "wof:population":919
},
  "geometry": {"coordinates":[-101.90777,20.10587],"type":"Point"}
}