{
  "type": "Feature",
  "properties": {
    "gn:admin1_code":"30",
    "gn:admin2_code":"178.0",
    "gn:asciiname":"Nueva Era",
    "gn:country_code":"MX",
    "gn:dem":6,
    "gn:feature_class":"P",
    "gn:feature_code":"PPL",
    "gn:name":"Nueva Era",
    "gn:population":152,
    "gn:timezone":"America/Mexico_City",
    "iso:country":"MX",
    "wof:name":"Nueva Era",
    "wof:placetype":"locality",
    "wof:population":152
},
  "geometry": {"coordinates":[-95.72833,18.55444],"type":"Point"}
}