{
  "type": "Feature",
  "properties": {
    "gn:admin1_code":"2.0",
    "gn:admin2_code":"1.0",
    "gn:asciiname":"Colonia Cuauhtemoc",
    "gn:country_code":"MX",
    "gn:dem":41,
    "gn:feature_class":"P",
    "gn:feature_code":"PPL",
    "gn:name":"Colonia Cuauhtemoc",
    "gn:population":0,
    "gn:timezone":"America/Tijuana",
    "iso:country":"MX",
    "wof:name":"Colonia Cuauhtemoc",
    "wof:placetype":"locality"
},
  "geometry": {"coordinates":[-116.58333,31.85],"type":"Point"}
}