{
  "type": "Feature",
  "properties": {
    "gn:admin1_code":"21",
    "gn:admin2_code":"158",
    "gn:asciiname":"El Palenque",
    "gn:country_code":"MX",
    "gn:dem":211,
    "gn:feature_class":"P",
    "gn:feature_code":"PPL",
    "gn:name":"El Palenque",
    "gn:population":40,
    "gn:timezone":"America/Mexico_City",
    "iso:country":"MX",
    "wof:name":"El Palenque",
    "wof:placetype":"locality",
    "wof:population":40
},
  "geometry": {"coordinates":[-97.4057,20.17375],"type":"Point"}
}