{
  "type": "Feature",
  "properties": {
    "gn:admin1_code":"15",
    "gn:admin2_code":"5.0",
    "gn:asciiname":"San Lorenzo Cuauhtenco",
    "gn:country_code":"MX",
    "gn:dem":2607,
    "gn:feature_class":"P",
    "gn:feature_code":"PPL",
    "gn:name":"San Lorenzo Cuauhtenco",
    "gn:population":0,
    "gn:timezone":"America/Mexico_City",
    "iso:country":"MX",
    "name:und_x_variant":[
        "San Lorenzo",
        "San Lorenzo Cuauhtenco"
    ],
    "wof:name":"San Lorenzo Cuauhtenco",
    "wof:placetype":"locality"
},
  "geometry": {"coordinates":[-99.77567000000001,19.37005],"type":"Point"}
}