{
  "type": "Feature",
  "properties": {
    "gn:admin1_code":"3",
    "gn:admin2_code":"1.0",
    "gn:asciiname":"La Machaca",
    "gn:country_code":"MX",
    "gn:dem":399,
    "gn:feature_class":"P",
    "gn:feature_code":"PPL",
    "gn:name":"La Machaca",
    "gn:population":0,
    "gn:timezone":"America/Mazatlan",
    "iso:country":"MX",
    "name:spa_x_preferred":[
        "La Machaca"
    ],
    "wof:name":"La Machaca",
    "wof:placetype":"locality"
},
  "geometry": {"coordinates":[-111.88408,26.28442],"type":"Point"}
}