{
  "type": "Feature",
  "properties": {
    "gn:admin1_code":"30.0",
    "gn:admin2_code":"70.0",
    "gn:asciiname":"Las Cabras",
    "gn:country_code":"MX",
    "gn:dem":21,
    "gn:feature_class":"P",
    "gn:feature_code":"PPL",
    "gn:name":"Las Cabras",
    "gn:population":0,
    "gn:timezone":"America/Mexico_City",
    "iso:country":"MX",
    "name:ceb_x_preferred":[
        "Las Cabras"
    ],
    "name:kor_x_preferred":[
        "\ub77c\uc2a4\uce74\ube0c\ub77c\uc2a4"
    ],
    "name:spa_x_preferred":[
        "Las Cabras"
    ],
    "name:swe_x_preferred":[
        "Las Cabras"
    ],
    "wof:name":"Las Cabras",
    "wof:placetype":"locality"
},
  "geometry": {"coordinates":[-94.46823999999999,17.61556000000001],"type":"Point"}
}