{
  "type": "Feature",
  "properties": {
    "gn:admin1_code":"16",
    "gn:admin2_code":"10",
    "gn:asciiname":"El Agustin",
    "gn:country_code":"MX",
    "gn:dem":700,
    "gn:feature_class":"P",
    "gn:feature_code":"PPL",
    "gn:name":"El Agust\u00edn",
    "gn:population":10,
    "gn:timezone":"America/Mexico_City",
    "iso:country":"MX",
    "name:und_x_variant":[
        "El Agust\u00edn"
    ],
    "wof:name":"El Agustin",
    "wof:placetype":"locality",
    "wof:population":10
},
  "geometry": {"coordinates":[-102.46556,18.19528],"type":"Point"}
}