{
  "type": "Feature",
  "properties": {
    "gn:admin1_code":"25",
    "gn:admin2_code":"10.0",
    "gn:asciiname":"Chulavista",
    "gn:country_code":"MX",
    "gn:dem":136,
    "gn:feature_class":"P",
    "gn:feature_code":"PPL",
    "gn:name":"Chulavista",
    "gn:population":0,
    "gn:timezone":"America/Mazatlan",
    "iso:country":"MX",
    "name:spa_x_preferred":[
        "Chulavista"
    ],
    "wof:name":"Chulavista",
    "wof:placetype":"locality"
},
  "geometry": {"coordinates":[-108.55663,26.52441],"type":"Point"}
}