{
  "type": "Feature",
  "properties": {
    "gn:gn_country":"MX",
    "gn:gn_fcode":"PPL",
    "gn:gn_pop":0,
    "iso:country":"MX",
    "name:ceb_x_preferred":[
        "Potrero"
    ],
    "name:deu_x_preferred":[
        "Potrero"
    ],
    "name:ita_x_preferred":[
        "Potrero"
    ],
    "name:spa_x_preferred":[
        "El Potrero"
    ],
    "name:spa_x_variant":[
        "Potrero"
    ],
    "name:srp_x_preferred":[
        "\u041f\u043e\u0442\u0440\u0435\u0440\u043e"
    ],
    "name:swe_x_preferred":[
        "Potrero"
    ],
    "qs_pg:aaroncc":"MX",
    "qs_pg:gn_country":"MX",
    "qs_pg:gn_fcode":"PPL",
    "qs_pg:gn_pop":0,
    "qs_pg:name":"Potrero",
    "qs_pg:name_adm0":"M\u00e9xico",
    "qs_pg:name_adm1":"Tlaxcala",
    "qs_pg:photos":9,
    "qs_pg:photos_1k":2,
    "qs_pg:photos_9k":1,
    "qs_pg:photos_9r":1,
    "qs_pg:photos_all":9,
    "qs_pg:photos_sr":1,
    "qs_pg:pop_sr":0,
    "qs_pg:qs_pg_placetype":"neighbourhood",
    "qs_pg:qs_pg_placetype_gp":"Suburb",
    "qs_pg:woe_adm0":23424900,
    "woe:adm0_id":23424900,
    "woe:name_adm0":"M\u00e9xico",
    "woe:name_adm1":"Tlaxcala",
    "woe:placetype":"Suburb",
    "wof:name":"Potrero",
    "wof:placetype":"neighbourhood"
},
  "geometry": {"coordinates":[-98.0779,19.91778],"type":"Point"}
}