{
  "type": "Feature",
  "properties": {
    "gn:admin1_code":"10",
    "gn:admin2_code":"26.0",
    "gn:asciiname":"El Apomito",
    "gn:country_code":"MX",
    "gn:dem":700,
    "gn:feature_class":"P",
    "gn:feature_code":"PPL",
    "gn:name":"El Apomito",
    "gn:population":6,
    "gn:timezone":"America/Mazatlan",
    "iso:country":"MX",
    "wof:name":"El Apomito",
    "wof:placetype":"locality",
    "wof:population":6
},
  "geometry": {"coordinates":[-105.96615,24.12306],"type":"Point"}
}