{
  "type": "Feature",
  "properties": {
    "gn:admin1_code":"14.0",
    "gn:admin2_code":"64.0",
    "gn:asciiname":"Los Parajes",
    "gn:country_code":"MX",
    "gn:dem":2114,
    "gn:feature_class":"P",
    "gn:feature_code":"PPL",
    "gn:name":"Los Parajes",
    "gn:population":0,
    "gn:timezone":"America/Mexico_City",
    "iso:country":"MX",
    "name:spa_x_preferred":[
        "Los Parajes"
    ],
    "wof:name":"Los Parajes",
    "wof:placetype":"locality"
},
  "geometry": {"coordinates":[-101.66336,21.56487000000001],"type":"Point"}
}