{
  "type": "Feature",
  "properties": {
    "gn:admin1_code":"28",
    "gn:admin2_code":"41",
    "gn:asciiname":"Monasterio de Adoracion Perpetua",
    "gn:country_code":"MX",
    "gn:dem":283,
    "gn:feature_class":"P",
    "gn:feature_code":"PPL",
    "gn:name":"Monasterio de Adoraci\u00f3n Perpetua",
    "gn:population":12,
    "gn:timezone":"America/Monterrey",
    "iso:country":"MX",
    "name:und_x_variant":[
        "Monasterio de Adoraci\u00f3n Perpetua"
    ],
    "wof:name":"Monasterio de Adoracion Perpetua",
    "wof:placetype":"locality",
    "wof:population":12
},
  "geometry": {"coordinates":[-99.14082999999999,23.77583],"type":"Point"}
}