{
  "type": "Feature",
  "properties": {
    "gn:admin1_code":"14",
    "gn:admin2_code":"61.0",
    "gn:asciiname":"Nueva Colonia",
    "gn:country_code":"MX",
    "gn:dem":2262,
    "gn:feature_class":"P",
    "gn:feature_code":"PPL",
    "gn:name":"Nueva Colonia",
    "gn:population":0,
    "gn:timezone":"America/Mexico_City",
    "iso:country":"MX",
    "name:spa_x_preferred":[
        "Nueva Colonia"
    ],
    "wof:name":"Nueva Colonia",
    "wof:placetype":"locality"
},
  "geometry": {"coordinates":[-104.02526,22.31128],"type":"Point"}
}