{
  "type": "Feature",
  "properties": {
    "gn:admin1_code":"14",
    "gn:admin2_code":"93.0",
    "gn:asciiname":"Palos Altos",
    "gn:country_code":"MX",
    "gn:dem":1738,
    "gn:feature_class":"P",
    "gn:feature_code":"PPL",
    "gn:name":"Palos Altos",
    "gn:population":73,
    "gn:timezone":"America/Mexico_City",
    "iso:country":"MX",
    "wof:name":"Palos Altos",
    "wof:placetype":"locality",
    "wof:population":73
},
  "geometry": {"coordinates":[-102.87361,20.67111],"type":"Point"}
}