{
  "type": "Feature",
  "properties": {
    "gn:admin1_code":"11",
    "gn:admin2_code":"37",
    "gn:asciiname":"El Amparo",
    "gn:country_code":"MX",
    "gn:dem":1746,
    "gn:feature_class":"P",
    "gn:feature_code":"PPL",
    "gn:name":"El Amparo",
    "gn:population":10,
    "gn:timezone":"America/Mexico_City",
    "iso:country":"MX",
    "name:spa_x_preferred":[
        "El Amparo"
    ],
    "wof:name":"El Amparo",
    "wof:placetype":"locality",
    "wof:population":10
},
  "geometry": {"coordinates":[-101.41722,20.83389],"type":"Point"}
}