{
  "type": "Feature",
  "properties": {
    "gn:admin1_code":"6.0",
    "gn:asciiname":"El Concheno",
    "gn:country_code":"MX",
    "gn:dem":1981,
    "gn:feature_class":"P",
    "gn:feature_code":"PPL",
    "gn:name":"El Conche\u00f1o",
    "gn:population":0,
    "gn:timezone":"America/Chihuahua",
    "iso:country":"MX",
    "name:spa_x_preferred":[
        "El Conche\u00f1o"
    ],
    "wof:name":"El Concheno",
    "wof:placetype":"locality"
},
  "geometry": {"coordinates":[-106.99102000000001,29.10795],"type":"Point"}
}