{
  "type": "Feature",
  "properties": {
    "gn:admin1_code":"15.0",
    "gn:admin2_code":"8.0",
    "gn:asciiname":"Los Planes",
    "gn:country_code":"MX",
    "gn:dem":873,
    "gn:feature_class":"P",
    "gn:feature_code":"PPL",
    "gn:name":"Los Planes",
    "gn:population":0,
    "gn:timezone":"America/Mexico_City",
    "iso:country":"MX",
    "name:spa_x_preferred":[
        "Los Planes"
    ],
    "wof:name":"Los Planes",
    "wof:placetype":"locality"
},
  "geometry": {"coordinates":[-100.20180000000001,18.79726],"type":"Point"}
}