{
  "type": "Feature",
  "properties": {
    "gn:admin1_code":"11.0",
    "gn:admin2_code":"14.0",
    "gn:asciiname":"La Puerta de San Francisco",
    "gn:country_code":"MX",
    "gn:dem":1974,
    "gn:feature_class":"P",
    "gn:feature_code":"PPL",
    "gn:name":"La Puerta de San Francisco",
    "gn:population":322,
    "gn:timezone":"America/Mexico_City",
    "iso:country":"MX",
    "name:spa_x_preferred":[
        "La Puerta de San Francisco"
    ],
    "wof:name":"La Puerta de San Francisco",
    "wof:placetype":"locality",
    "wof:population":322
},
  "geometry": {"coordinates":[-100.7603,21.20877],"type":"Point"}
}