{
  "type": "Feature",
  "properties": {
    "gn:admin1_code":"31",
    "gn:admin2_code":"13.0",
    "gn:asciiname":"Las Palomas",
    "gn:country_code":"MX",
    "gn:dem":7,
    "gn:feature_class":"P",
    "gn:feature_code":"PPL",
    "gn:name":"Las Palomas",
    "gn:population":5,
    "gn:timezone":"America/Merida",
    "iso:country":"MX",
    "wof:name":"Las Palomas",
    "wof:placetype":"locality",
    "wof:population":5
},
  "geometry": {"coordinates":[-89.51721999999999,21.10972000000001],"type":"Point"}
}