{
  "type": "Feature",
  "properties": {
    "gn:admin1_code":"30",
    "gn:admin2_code":"130.0",
    "gn:asciiname":"Nuevo Raya Caracol (Zanja Seca)",
    "gn:country_code":"MX",
    "gn:dem":68,
    "gn:feature_class":"P",
    "gn:feature_code":"PPL",
    "gn:name":"Nuevo Raya Caracol (Zanja Seca)",
    "gn:population":420,
    "gn:timezone":"America/Mexico_City",
    "iso:country":"MX",
    "wof:name":"Nuevo Raya Caracol (Zanja Seca)",
    "wof:placetype":"locality",
    "wof:population":420
},
  "geometry": {"coordinates":[-95.41194,17.66082999999999],"type":"Point"}
}