{
  "type": "Feature",
  "properties": {
    "gn:admin1_code":"26",
    "gn:admin2_code":"31.0",
    "gn:asciiname":"Las Moras",
    "gn:country_code":"MX",
    "gn:dem":1229,
    "gn:feature_class":"P",
    "gn:feature_code":"PPL",
    "gn:name":"Las Moras",
    "gn:population":0,
    "gn:timezone":"America/Hermosillo",
    "iso:country":"MX",
    "name:spa_x_preferred":[
        "Las Moras"
    ],
    "wof:name":"Las Moras",
    "wof:placetype":"locality"
},
  "geometry": {"coordinates":[-109.04394000000001,30.12922],"type":"Point"}
}