{
  "type": "Feature",
  "properties": {
    "gn:admin1_code":"30",
    "gn:admin2_code":"109.0",
    "gn:asciiname":"Cerro Quebrado Uno (San Felipe)",
    "gn:country_code":"MX",
    "gn:dem":437,
    "gn:feature_class":"P",
    "gn:feature_code":"PPL",
    "gn:name":"Cerro Quebrado Uno (San Felipe)",
    "gn:population":198,
    "gn:timezone":"America/Mexico_City",
    "iso:country":"MX",
    "wof:name":"Cerro Quebrado Uno (San Felipe)",
    "wof:placetype":"locality",
    "wof:population":198
},
  "geometry": {"coordinates":[-96.91722,20.00944],"type":"Point"}
}