{
  "type": "Feature",
  "properties": {
    "gn:admin1_code":"28",
    "gn:admin2_code":"10",
    "gn:asciiname":"Norberto Trevino Zapata (El Palmar)",
    "gn:country_code":"MX",
    "gn:dem":210,
    "gn:feature_class":"P",
    "gn:feature_code":"PPL",
    "gn:name":"Norberto Trevi\u00f1o Zapata (El Palmar)",
    "gn:population":34,
    "gn:timezone":"America/Monterrey",
    "iso:country":"MX",
    "name:und_x_variant":[
        "Norberto Trevi\u00f1o Zapata (El Palmar)"
    ],
    "wof:name":"Norberto Trevino Zapata (El Palmar)",
    "wof:placetype":"locality",
    "wof:population":34
},
  "geometry": {"coordinates":[-98.53222,24.83722],"type":"Point"}
}