{
  "type": "Feature",
  "properties": {
    "gn:admin1_code":"5",
    "gn:admin2_code":"57.0",
    "gn:asciiname":"Berriozabal",
    "gn:country_code":"MX",
    "gn:dem":1918,
    "gn:feature_class":"P",
    "gn:feature_code":"PPL",
    "gn:name":"Berrioz\u00e1bal",
    "gn:population":0,
    "gn:timezone":"America/Mexico_City",
    "iso:country":"MX",
    "name:spa_x_preferred":[
        "Berrioz\u00e1bal"
    ],
    "wof:name":"Berriozabal",
    "wof:placetype":"locality"
},
  "geometry": {"coordinates":[-92.28269,15.26579],"type":"Point"}
}