{
  "type": "Feature",
  "properties": {
    "gn:admin1_code":"25",
    "gn:admin2_code":"11.0",
    "gn:asciiname":"Kilometro Ciento Cuarenta y Uno",
    "gn:country_code":"MX",
    "gn:dem":16,
    "gn:feature_class":"P",
    "gn:feature_code":"PPL",
    "gn:name":"Kil\u00f3metro Ciento Cuarenta y Uno",
    "gn:population":7,
    "gn:timezone":"America/Mazatlan",
    "iso:country":"MX",
    "name:und_x_variant":[
        "Kil\u00f3metro Ciento Cuarenta y Uno"
    ],
    "wof:name":"Kilometro Ciento Cuarenta y Uno",
    "wof:placetype":"locality",
    "wof:population":7
},
  "geometry": {"coordinates":[-108.42072,25.55067],"type":"Point"}
}