{
  "type": "Feature",
  "properties": {
    "gn:admin1_code":"10",
    "gn:admin2_code":"21.0",
    "gn:asciiname":"El Charco de Piedra",
    "gn:country_code":"MX",
    "gn:dem":1762,
    "gn:feature_class":"P",
    "gn:feature_code":"PPL",
    "gn:name":"El Charco de Piedra",
    "gn:population":0,
    "gn:timezone":"America/Monterrey",
    "iso:country":"MX",
    "name:spa_x_preferred":[
        "El Charco de Piedra"
    ],
    "wof:name":"El Charco de Piedra",
    "wof:placetype":"locality"
},
  "geometry": {"coordinates":[-103.85787000000001,24.82782000000001],"type":"Point"}
}