{
  "type": "Feature",
  "properties": {
    "gn:admin1_code":"6.0",
    "gn:admin2_code":"19.0",
    "gn:asciiname":"El Comiteco",
    "gn:country_code":"MX",
    "gn:dem":1580,
    "gn:feature_class":"P",
    "gn:feature_code":"PPL",
    "gn:name":"El Comiteco",
    "gn:population":0,
    "gn:timezone":"America/Chihuahua",
    "iso:country":"MX",
    "name:spa_x_preferred":[
        "El Comiteco"
    ],
    "wof:name":"El Comiteco",
    "wof:placetype":"locality"
},
  "geometry": {"coordinates":[-106.38281000000001,29.24898],"type":"Point"}
}