{
  "type": "Feature",
  "properties": {
    "gn:admin1_code":"11.0",
    "gn:asciiname":"Las Canoas",
    "gn:country_code":"MX",
    "gn:dem":1944,
    "gn:feature_class":"P",
    "gn:feature_code":"PPL",
    "gn:name":"Las Canoas",
    "gn:population":0,
    "gn:timezone":"America/Mexico_City",
    "iso:country":"MX",
    "name:spa_x_preferred":[
        "Las Canoas"
    ],
    "wof:name":"Las Canoas",
    "wof:placetype":"locality"
},
  "geometry": {"coordinates":[-101.98584,20.67267],"type":"Point"}
}