{
  "type": "Feature",
  "properties": {
    "gn:admin1_code":"22",
    "gn:admin2_code":"14.0",
    "gn:asciiname":"Charape de los Pelones",
    "gn:country_code":"MX",
    "gn:dem":2279,
    "gn:feature_class":"P",
    "gn:feature_code":"PPL",
    "gn:name":"Charape de los Pelones",
    "gn:population":295,
    "gn:timezone":"America/Mexico_City",
    "iso:country":"MX",
    "wof:name":"Charape de los Pelones",
    "wof:placetype":"locality",
    "wof:population":295
},
  "geometry": {"coordinates":[-100.45361,20.91806],"type":"Point"}
}