{
  "type": "Feature",
  "properties": {
    "gn:admin1_code":"16",
    "gn:admin2_code":"8",
    "gn:asciiname":"El Aviare",
    "gn:country_code":"MX",
    "gn:dem":601,
    "gn:feature_class":"P",
    "gn:feature_code":"PPL",
    "gn:name":"El Aviare",
    "gn:population":10,
    "gn:timezone":"America/Mexico_City",
    "iso:country":"MX",
    "wof:name":"El Aviare",
    "wof:placetype":"locality",
    "wof:population":10
},
  "geometry": {"coordinates":[-103.32472,18.41556],"type":"Point"}
}