{
  "type": "Feature",
  "properties": {
    "gn:admin1_code":"11",
    "gn:admin2_code":"15.0",
    "gn:asciiname":"Los Gasca",
    "gn:country_code":"MX",
    "gn:dem":2418,
    "gn:feature_class":"P",
    "gn:feature_code":"PPL",
    "gn:name":"Los Gasca",
    "gn:population":7,
    "gn:timezone":"America/Mexico_City",
    "iso:country":"MX",
    "wof:name":"Los Gasca",
    "wof:placetype":"locality",
    "wof:population":7
},
  "geometry": {"coordinates":[-101.34139,21.05611],"type":"Point"}
}