{
  "type": "Feature",
  "properties": {
    "gn:admin1_code":"26",
    "gn:admin2_code":"3.0",
    "gn:asciiname":"Los Muertos",
    "gn:country_code":"MX",
    "gn:dem":177,
    "gn:feature_class":"P",
    "gn:feature_code":"PPL",
    "gn:name":"Los Muertos",
    "gn:population":0,
    "gn:timezone":"America/Hermosillo",
    "iso:country":"MX",
    "name:und_x_variant":[
        "Muertos",
        "Los Muertos"
    ],
    "wof:name":"Los Muertos",
    "wof:placetype":"locality"
},
  "geometry": {"coordinates":[-108.90966,26.7406],"type":"Point"}
}