{
  "type": "Feature",
  "properties": {
    "gn:admin1_code":"5.0",
    "gn:asciiname":"Pino Suarez",
    "gn:country_code":"MX",
    "gn:dem":745,
    "gn:feature_class":"P",
    "gn:feature_code":"PPL",
    "gn:name":"Pino Su\u00e1rez",
    "gn:population":0,
    "gn:timezone":"America/Mexico_City",
    "iso:country":"MX",
    "name:spa_x_preferred":[
        "Pino Su\u00e1rez"
    ],
    "wof:name":"Pino Suarez",
    "wof:placetype":"locality"
},
  "geometry": {"coordinates":[-92.21302,16.12503],"type":"Point"}
}