{
  "type": "Feature",
  "properties": {
    "gn:admin1_code":"30",
    "gn:admin2_code":"170",
    "gn:asciiname":"El Puerto",
    "gn:country_code":"MX",
    "gn:dem":935,
    "gn:feature_class":"P",
    "gn:feature_code":"PPL",
    "gn:name":"El Puerto",
    "gn:population":41,
    "gn:timezone":"America/Mexico_City",
    "iso:country":"MX",
    "wof:name":"El Puerto",
    "wof:placetype":"locality",
    "wof:population":41
},
  "geometry": {"coordinates":[-98.33306,20.67556],"type":"Point"}
}