{
  "type": "Feature",
  "properties": {
    "gn:admin1_code":"18",
    "gn:admin2_code":"19.0",
    "gn:asciiname":"La Frontana",
    "gn:country_code":"MX",
    "gn:dem":1192,
    "gn:feature_class":"P",
    "gn:feature_code":"PPL",
    "gn:name":"La Frontana",
    "gn:population":6,
    "gn:timezone":"America/Mazatlan",
    "iso:country":"MX",
    "wof:name":"La Frontana",
    "wof:placetype":"locality",
    "wof:population":6
},
  "geometry": {"coordinates":[-104.30249999999999,21.30444],"type":"Point"}
}