{
  "type": "Feature",
  "properties": {
    "gn:admin1_code":"7.0",
    "gn:admin2_code":"36.0",
    "gn:asciiname":"Ahuichila",
    "gn:country_code":"MX",
    "gn:dem":1437,
    "gn:feature_class":"P",
    "gn:feature_code":"PPL",
    "gn:name":"Ahuichila",
    "gn:population":0,
    "gn:timezone":"America/Mexico_City",
    "iso:country":"MX",
    "name:spa_x_preferred":[
        "Ahuichila"
    ],
    "name:und_x_variant":[
        "Rancho Ahuichila"
    ],
    "wof:name":"Ahuichila",
    "wof:placetype":"locality"
},
  "geometry": {"coordinates":[-102.66669,25.07867],"type":"Point"}
}