{
  "type": "Feature",
  "properties": {
    "gn:gn_country":"MX",
    "gn:gn_fcode":"PPL",
    "gn:gn_pop":0,
    "iso:country":"MX",
    "name:dan_x_preferred":[
        "La Rumorosa"
    ],
    "name:eng_x_preferred":[
        "La Rumorosa"
    ],
    "name:fra_x_preferred":[
        "La Rumorosa"
    ],
    "name:nld_x_preferred":[
        "La Rumorosa"
    ],
    "name:nob_x_preferred":[
        "La Rumorosa"
    ],
    "name:rus_x_preferred":[
        "\u041b\u0430-\u0420\u0443\u043c\u043e\u0440\u043e\u0441\u0430"
    ],
    "name:spa_x_preferred":[
        "Rumorosa"
    ],
    "name:spa_x_variant":[
        "La Rumorosa"
    ],
    "name:urd_x_preferred":[
        "\u0644\u0627 \u0631\u0648\u0645\u0648\u0631\u0648\u0633\u0627"
    ],
    "qs_pg:aaroncc":"MX",
    "qs_pg:gn_country":"MX",
    "qs_pg:gn_fcode":"PPL",
    "qs_pg:gn_pop":0,
    "qs_pg:name":"La Rumorosa",
    "qs_pg:name_adm0":"M\u00e9xico",
    "qs_pg:name_adm1":"Baja California",
    "qs_pg:photos":282,
    "qs_pg:photos_1k":57,
    "qs_pg:photos_9k":1,
    "qs_pg:photos_9r":4,
    "qs_pg:photos_all":282,
    "qs_pg:photos_sr":5,
    "qs_pg:pop_sr":0,
    "qs_pg:qs_pg_placetype":"locality",
    "qs_pg:qs_pg_placetype_gp":"Town",
    "qs_pg:woe_adm0":23424900,
    "woe:adm0_id":23424900,
    "woe:name_adm0":"M\u00e9xico",
    "woe:name_adm1":"Baja California",
    "woe:placetype":"Town",
    "wof:name":"La Rumorosa",
    "wof:placetype":"locality"
},
  "geometry": {"coordinates":[-116.05397000000001,32.52396],"type":"Point"}
}