{
  "type": "Feature",
  "properties": {
    "gn:admin1_code":"15",
    "gn:admin2_code":"114.0",
    "gn:asciiname":"Vaquerias Palizada",
    "gn:country_code":"MX",
    "gn:dem":2879,
    "gn:feature_class":"P",
    "gn:feature_code":"PPL",
    "gn:name":"Vaquer\u00edas Palizada",
    "gn:population":151,
    "gn:timezone":"America/Mexico_City",
    "iso:country":"MX",
    "name:und_x_variant":[
        "Vaquer\u00edas Palizada"
    ],
    "wof:name":"Vaquerias Palizada",
    "wof:placetype":"locality",
    "wof:population":151
},
  "geometry": {"coordinates":[-100.14528,19.475],"type":"Point"}
}