{
  "type": "Feature",
  "properties": {
    "gn:admin1_code":"13",
    "gn:admin2_code":"28",
    "gn:asciiname":"Las Palomitas",
    "gn:country_code":"MX",
    "gn:dem":165,
    "gn:feature_class":"P",
    "gn:feature_code":"PPL",
    "gn:name":"Las Palomitas",
    "gn:population":25,
    "gn:timezone":"America/Mexico_City",
    "iso:country":"MX",
    "wof:name":"Las Palomitas",
    "wof:placetype":"locality",
    "wof:population":25
},
  "geometry": {"coordinates":[-98.43572,21.14809],"type":"Point"}
}