{
  "type": "Feature",
  "properties": {
    "gn:admin1_code":"22",
    "gn:admin2_code":"2",
    "gn:asciiname":"Loma de las Minas",
    "gn:country_code":"MX",
    "gn:dem":1322,
    "gn:feature_class":"P",
    "gn:feature_code":"PPL",
    "gn:name":"Loma de las Minas",
    "gn:population":11,
    "gn:timezone":"America/Mexico_City",
    "iso:country":"MX",
    "wof:name":"Loma de las Minas",
    "wof:placetype":"locality",
    "wof:population":11
},
  "geometry": {"coordinates":[-99.60778000000001,21.19667],"type":"Point"}
}