{
  "type": "Feature",
  "properties": {
    "gn:admin1_code":"15",
    "gn:admin2_code":"86.0",
    "gn:asciiname":"La Orejeta",
    "gn:country_code":"MX",
    "gn:dem":2973,
    "gn:feature_class":"P",
    "gn:feature_code":"PPL",
    "gn:name":"La Orejeta",
    "gn:population":150,
    "gn:timezone":"America/Mexico_City",
    "iso:country":"MX",
    "wof:name":"La Orejeta",
    "wof:placetype":"locality",
    "wof:population":150
},
  "geometry": {"coordinates":[-99.88651,19.0762],"type":"Point"}
}