{
  "type": "Feature",
  "properties": {
    "gn:admin1_code":"32",
    "gn:admin2_code":"12.0",
    "gn:asciiname":"La Chavenita",
    "gn:country_code":"MX",
    "gn:dem":2365,
    "gn:feature_class":"P",
    "gn:feature_code":"PPL",
    "gn:name":"La Chave\u00f1ita",
    "gn:population":0,
    "gn:timezone":"America/Mexico_City",
    "iso:country":"MX",
    "wof:name":"La Chavenita",
    "wof:placetype":"locality"
},
  "geometry": {"coordinates":[-102.61667,22.48333],"type":"Point"}
}