{
  "type": "Feature",
  "properties": {
    "gn:admin1_code":"2.0",
    "gn:admin2_code":"2.0",
    "gn:asciiname":"La Primavera (Colonia Zacatecas)",
    "gn:country_code":"MX",
    "gn:dem":7,
    "gn:feature_class":"P",
    "gn:feature_code":"PPL",
    "gn:name":"La Primavera (Colonia Zacatecas)",
    "gn:population":5,
    "gn:timezone":"America/Tijuana",
    "iso:country":"MX",
    "wof:name":"La Primavera (Colonia Zacatecas)",
    "wof:placetype":"locality",
    "wof:population":5
},
  "geometry": {"coordinates":[-115.05667,32.17194],"type":"Point"}
}