{
  "type": "Feature",
  "properties": {
    "gn:admin1_code":"11.0",
    "gn:admin2_code":"7.0",
    "gn:asciiname":"Los Colorines",
    "gn:country_code":"MX",
    "gn:dem":1763,
    "gn:feature_class":"P",
    "gn:feature_code":"PPL",
    "gn:name":"Los Colorines",
    "gn:population":0,
    "gn:timezone":"America/Mexico_City",
    "iso:country":"MX",
    "name:spa_x_preferred":[
        "Los Colorines"
    ],
    "wof:name":"Los Colorines",
    "wof:placetype":"locality"
},
  "geometry": {"coordinates":[-100.87455,20.58462],"type":"Point"}
}