{
  "type": "Feature",
  "properties": {
    "gn:admin1_code":"21.0",
    "gn:admin2_code":"197.0",
    "gn:asciiname":"El Paranal",
    "gn:country_code":"MX",
    "gn:dem":170,
    "gn:feature_class":"P",
    "gn:feature_code":"PPL",
    "gn:name":"El Paranal",
    "gn:population":5,
    "gn:timezone":"America/Mexico_City",
    "iso:country":"MX",
    "name:spa_x_preferred":[
        "El Paranal"
    ],
    "wof:name":"El Paranal",
    "wof:placetype":"locality",
    "wof:population":5
},
  "geometry": {"coordinates":[-97.76367,20.42381],"type":"Point"}
}