{
  "type": "Feature",
  "properties": {
    "gn:admin1_code":"12",
    "gn:admin2_code":"81.0",
    "gn:asciiname":"Moyotepec de Juarez",
    "gn:cc2":"MX",
    "gn:country_code":"MX",
    "gn:dem":1653,
    "gn:feature_class":"P",
    "gn:feature_code":"PPL",
    "gn:name":"Moyotepec de Ju\u00e1rez",
    "gn:population":0,
    "gn:timezone":"America/Mexico_City",
    "iso:country":"MX",
    "name:und_x_variant":[
        "Moyotepec",
        "Moyotepec de Ju\u00e1rez"
    ],
    "wof:name":"Moyotepec de Juarez",
    "wof:placetype":"locality"
},
  "geometry": {"coordinates":[-98.66667,17.06667],"type":"Point"}
}