{
  "type": "Feature",
  "properties": {
    "gn:admin1_code":"5",
    "gn:admin2_code":"65.0",
    "gn:asciiname":"San Miguel",
    "gn:country_code":"MX",
    "gn:dem":41,
    "gn:feature_class":"P",
    "gn:feature_code":"PPL",
    "gn:name":"San Miguel",
    "gn:population":7,
    "gn:timezone":"America/Mexico_City",
    "iso:country":"MX",
    "wof:name":"San Miguel",
    "wof:placetype":"locality",
    "wof:population":7
},
  "geometry": {"coordinates":[-91.86083000000001,17.76167000000001],"type":"Point"}
}