{
  "type": "Feature",
  "properties": {
    "gn:admin1_code":"12.0",
    "gn:admin2_code":"6.0",
    "gn:asciiname":"El Coyul",
    "gn:country_code":"MX",
    "gn:dem":1330,
    "gn:feature_class":"P",
    "gn:feature_code":"PPL",
    "gn:name":"El Coyul",
    "gn:population":0,
    "gn:timezone":"America/Mexico_City",
    "iso:country":"MX",
    "name:spa_x_preferred":[
        "El Coyul"
    ],
    "wof:name":"El Coyul",
    "wof:placetype":"locality"
},
  "geometry": {"coordinates":[-100.02632,18.1611],"type":"Point"}
}