{
  "type": "Feature",
  "properties": {
    "gn:admin1_code":"5.0",
    "gn:admin2_code":"84.0",
    "gn:asciiname":"Monteoreb",
    "gn:country_code":"MX",
    "gn:dem":713,
    "gn:feature_class":"P",
    "gn:feature_code":"PPL",
    "gn:name":"Monteoreb",
    "gn:population":0,
    "gn:timezone":"America/Mexico_City",
    "iso:country":"MX",
    "name:spa_x_preferred":[
        "Monteoreb"
    ],
    "wof:name":"Monteoreb",
    "wof:placetype":"locality"
},
  "geometry": {"coordinates":[-92.99428,17.34785],"type":"Point"}
}