{
  "type": "Feature",
  "properties": {
    "gn:admin1_code":"13",
    "gn:admin2_code":"28.0",
    "gn:asciiname":"Cuapaxtitla",
    "gn:country_code":"MX",
    "gn:dem":243,
    "gn:feature_class":"P",
    "gn:feature_code":"PPL",
    "gn:name":"Cuapaxtitla",
    "gn:population":0,
    "gn:timezone":"America/Mexico_City",
    "iso:country":"MX",
    "name:spa_x_preferred":[
        "Cuapaxtitla"
    ],
    "wof:name":"Cuapaxtitla",
    "wof:placetype":"locality"
},
  "geometry": {"coordinates":[-98.55264,21.13292],"type":"Point"}
}