{
  "type": "Feature",
  "properties": {
    "gn:admin1_code":"20",
    "gn:admin2_code":"190.0",
    "gn:asciiname":"Albino Velasco",
    "gn:country_code":"MX",
    "gn:dem":104,
    "gn:feature_class":"P",
    "gn:feature_code":"PPL",
    "gn:name":"Albino Velasco",
    "gn:population":7,
    "gn:timezone":"America/Mexico_City",
    "iso:country":"MX",
    "wof:name":"Albino Velasco",
    "wof:placetype":"locality",
    "wof:population":7
},
  "geometry": {"coordinates":[-95.24556,17.50778],"type":"Point"}
}