{
  "type": "Feature",
  "properties": {
    "gn:admin1_code":"15.0",
    "gn:asciiname":"Dongu Barrio Uno",
    "gn:country_code":"MX",
    "gn:dem":2543,
    "gn:feature_class":"P",
    "gn:feature_code":"PPL",
    "gn:name":"Dong\u00fa Barrio Uno",
    "gn:population":0,
    "gn:timezone":"America/Mexico_City",
    "iso:country":"MX",
    "name:spa_x_preferred":[
        "Dong\u00fa Barrio Uno"
    ],
    "wof:name":"Dongu Barrio Uno",
    "wof:placetype":"locality"
},
  "geometry": {"coordinates":[-99.87038,19.96761],"type":"Point"}
}