{
  "type": "Feature",
  "properties": {
    "gn:admin1_code":"1",
    "gn:admin2_code":"7.0",
    "gn:asciiname":"El Sabino [Granja]",
    "gn:country_code":"MX",
    "gn:dem":1923,
    "gn:feature_class":"P",
    "gn:feature_code":"PPL",
    "gn:name":"El Sabino [Granja]",
    "gn:population":6,
    "gn:timezone":"America/Mexico_City",
    "iso:country":"MX",
    "wof:name":"El Sabino [Granja]",
    "wof:placetype":"locality",
    "wof:population":6
},
  "geometry": {"coordinates":[-102.30028,22.17333],"type":"Point"}
}