{
  "type": "Feature",
  "properties": {
    "gn:admin1_code":"19",
    "gn:asciiname":"La Casa de Madera",
    "gn:country_code":"MX",
    "gn:dem":2127,
    "gn:feature_class":"P",
    "gn:feature_code":"PPL",
    "gn:name":"La Casa de Madera",
    "gn:population":0,
    "gn:timezone":"America/Monterrey",
    "iso:country":"MX",
    "name:spa_x_preferred":[
        "La Casa de Madera"
    ],
    "wof:name":"La Casa de Madera",
    "wof:placetype":"locality"
},
  "geometry": {"coordinates":[-100.6384,25.27462],"type":"Point"}
}