{
  "type": "Feature",
  "properties": {
    "gn:admin1_code":"30.0",
    "gn:asciiname":"La Cimarrona",
    "gn:country_code":"MX",
    "gn:dem":10,
    "gn:feature_class":"P",
    "gn:feature_code":"PPL",
    "gn:name":"La Cimarrona",
    "gn:population":0,
    "gn:timezone":"America/Mexico_City",
    "iso:country":"MX",
    "name:spa_x_preferred":[
        "La Cimarrona"
    ],
    "wof:name":"La Cimarrona",
    "wof:placetype":"locality"
},
  "geometry": {"coordinates":[-95.52366000000001,18.27465],"type":"Point"}
}