{
  "type": "Feature",
  "properties": {
    "gn:admin1_code":"20",
    "gn:admin2_code":"198.0",
    "gn:asciiname":"Lomeria",
    "gn:country_code":"MX",
    "gn:dem":240,
    "gn:feature_class":"P",
    "gn:feature_code":"PPL",
    "gn:name":"Lomer\u00eda",
    "gn:population":129,
    "gn:timezone":"America/Mexico_City",
    "iso:country":"MX",
    "name:und_x_variant":[
        "Lomer\u00eda"
    ],
    "wof:name":"Lomeria",
    "wof:placetype":"locality",
    "wof:population":129
},
  "geometry": {"coordinates":[-95.06972,16.94778],"type":"Point"}
}