{
  "type": "Feature",
  "properties": {
    "gn:admin1_code":"20",
    "gn:admin2_code":"462.0",
    "gn:asciiname":"San Francisco el Chico",
    "gn:country_code":"MX",
    "gn:dem":1684,
    "gn:feature_class":"P",
    "gn:feature_code":"PPL",
    "gn:name":"San Francisco el Chico",
    "gn:population":0,
    "gn:timezone":"America/Mexico_City",
    "iso:country":"MX",
    "name:spa_x_preferred":[
        "San Francisco el Chico"
    ],
    "wof:name":"San Francisco el Chico",
    "wof:placetype":"locality"
},
  "geometry": {"coordinates":[-97.71426,17.78977],"type":"Point"}
}