{
  "type": "Feature",
  "properties": {
    "gn:admin1_code":"6",
    "gn:admin2_code":"40.0",
    "gn:asciiname":"Moctezuma",
    "gn:country_code":"MX",
    "gn:dem":2379,
    "gn:feature_class":"P",
    "gn:feature_code":"PPL",
    "gn:name":"Moctezuma",
    "gn:population":0,
    "gn:timezone":"America/Chihuahua",
    "iso:country":"MX",
    "name:und_x_variant":[
        "Rancho Moctezuma",
        "Moctezuma"
    ],
    "wof:name":"Moctezuma",
    "wof:placetype":"locality"
},
  "geometry": {"coordinates":[-108.26213,29.88107],"type":"Point"}
}