{
  "type": "Feature",
  "properties": {
    "gn:admin1_code":"18.0",
    "gn:admin2_code":"5.0",
    "gn:asciiname":"Jocochota",
    "gn:country_code":"MX",
    "gn:dem":1794,
    "gn:feature_class":"P",
    "gn:feature_code":"PPL",
    "gn:name":"Jocochota",
    "gn:population":0,
    "gn:timezone":"America/Mazatlan",
    "iso:country":"MX",
    "name:spa_x_preferred":[
        "Jocochota"
    ],
    "wof:name":"Jocochota",
    "wof:placetype":"locality"
},
  "geometry": {"coordinates":[-105.06573,22.76882],"type":"Point"}
}