{
  "type": "Feature",
  "properties": {
    "gn:admin1_code":"25",
    "gn:admin2_code":"15.0",
    "gn:asciiname":"Veinte de Noviembre",
    "gn:country_code":"MX",
    "gn:dem":53,
    "gn:feature_class":"P",
    "gn:feature_code":"PPL",
    "gn:name":"Veinte de Noviembre",
    "gn:population":0,
    "gn:timezone":"America/Mazatlan",
    "iso:country":"MX",
    "name:spa_x_preferred":[
        "Veinte de Noviembre"
    ],
    "wof:name":"Veinte de Noviembre",
    "wof:placetype":"locality"
},
  "geometry": {"coordinates":[-108.17292,25.60243],"type":"Point"}
}