{
  "type": "Feature",
  "properties": {
    "gn:admin1_code":"15",
    "gn:admin2_code":"37.0",
    "gn:asciiname":"El Manzano",
    "gn:country_code":"MX",
    "gn:dem":2510,
    "gn:feature_class":"P",
    "gn:feature_code":"PPL",
    "gn:name":"El Manzano",
    "gn:population":86,
    "gn:timezone":"America/Mexico_City",
    "iso:country":"MX",
    "wof:name":"El Manzano",
    "wof:placetype":"locality",
    "wof:population":86
},
  "geometry": {"coordinates":[-99.31195,19.4115],"type":"Point"}
}