{
  "type": "Feature",
  "properties": {
    "gn:admin1_code":"15",
    "gn:admin2_code":"37.0",
    "gn:asciiname":"El Manzano",
    "gn:country_code":"MX",
    "gn:dem":2510,
    "gn:feature_class":"P",
    "gn:feature_code":"PPL",
    "gn:name":"El Manzano",
    "gn:population":86,
    "gn:timezone":"America/Mexico_City",
    "iso:country":"MX",
    "name:arg_x_preferred":[
        "El Manzano"
    ],
    "name:ast_x_preferred":[
        "El Manzano"
    ],
    "name:cat_x_preferred":[
        "El Manzano"
    ],
    "name:ceb_x_preferred":[
        "El Manzano"
    ],
    "name:eus_x_preferred":[
        "El Manzano"
    ],
    "name:fra_x_preferred":[
        "El Manzano"
    ],
    "name:haw_x_preferred":[
        "El Manzano"
    ],
    "name:hun_x_preferred":[
        "El Manzano"
    ],
    "name:ina_x_preferred":[
        "El Manzano"
    ],
    "name:ita_x_preferred":[
        "El Manzano"
    ],
    "name:kaz_x_preferred":[
        "\u042d\u043b\u044c-\u041c\u0430\u043d\u0441\u0430\u043d\u043e"
    ],
    "name:msa_x_preferred":[
        "El Manzano"
    ],
    "name:nld_x_preferred":[
        "El Manzano"
    ],
    "name:oci_x_preferred":[
        "El Manzano"
    ],
    "name:pol_x_preferred":[
        "El Manzano"
    ],
    "name:por_x_preferred":[
        "El Manzano"
    ],
    "name:rus_x_preferred":[
        "\u042d\u043b\u044c-\u041c\u0430\u043d\u0441\u0430\u043d\u043e"
    ],
    "name:spa_x_preferred":[
        "El Manzano"
    ],
    "name:ukr_x_preferred":[
        "\u0415\u043b\u044c-\u041c\u0430\u043d\u0441\u0430\u043d\u043e"
    ],
    "name:uzb_x_preferred":[
        "El Manzano"
    ],
    "name:vie_x_preferred":[
        "El Manzano"
    ],
    "name:war_x_preferred":[
        "El Manzano"
    ],
    "name:zho_x_preferred":[
        "\u57c3\u5c14\u66fc\u8428\u8bfa"
    ],
    "wof:name":"El Manzano",
    "wof:placetype":"locality",
    "wof:population":86
},
  "geometry": {"coordinates":[-99.31195,19.4115],"type":"Point"}
}