{
  "type": "Feature",
  "properties": {
    "gn:admin1_code":"30.0",
    "gn:admin2_code":"70.0",
    "gn:asciiname":"Piedra Mate",
    "gn:country_code":"MX",
    "gn:dem":34,
    "gn:feature_class":"P",
    "gn:feature_code":"PPL",
    "gn:name":"Piedra Mate",
    "gn:population":0,
    "gn:timezone":"America/Mexico_City",
    "iso:country":"MX",
    "name:spa_x_preferred":[
        "Piedra Mate"
    ],
    "wof:name":"Piedra Mate",
    "wof:placetype":"locality"
},
  "geometry": {"coordinates":[-94.67031,17.38077],"type":"Point"}
}