{
  "type": "Feature",
  "properties": {
    "gn:admin1_code":"6.0",
    "gn:admin2_code":"15.0",
    "gn:asciiname":"Boquilla de Quinones de Abajo",
    "gn:country_code":"MX",
    "gn:dem":1120,
    "gn:feature_class":"P",
    "gn:feature_code":"PPL",
    "gn:name":"Boquilla de Qui\u00f1ones de Abajo",
    "gn:population":0,
    "gn:timezone":"America/Chihuahua",
    "iso:country":"MX",
    "name:spa_x_preferred":[
        "Boquilla de Qui\u00f1ones de Abajo"
    ],
    "name:und_x_variant":[
        "Boquilla"
    ],
    "wof:name":"Boquilla de Quinones de Abajo",
    "wof:placetype":"locality"
},
  "geometry": {"coordinates":[-104.98276,29.46907],"type":"Point"}
}