{
  "type": "Feature",
  "properties": {
    "gn:admin1_code":"14.0",
    "gn:admin2_code":"17.0",
    "gn:asciiname":"El Tambor",
    "gn:country_code":"MX",
    "gn:dem":1476,
    "gn:feature_class":"P",
    "gn:feature_code":"PPL",
    "gn:name":"El Tambor",
    "gn:population":54,
    "gn:timezone":"America/Mexico_City",
    "iso:country":"MX",
    "name:spa_x_preferred":[
        "El Tambor"
    ],
    "wof:name":"El Tambor",
    "wof:placetype":"locality",
    "wof:population":54
},
  "geometry": {"coordinates":[-104.30873,20.14626],"type":"Point"}
}