{
  "type": "Feature",
  "properties": {
    "gn:admin1_code":"1",
    "gn:admin2_code":"5",
    "gn:asciiname":"Las Huertas",
    "gn:country_code":"MX",
    "gn:dem":1868,
    "gn:feature_class":"P",
    "gn:feature_code":"PPL",
    "gn:name":"Las Huertas",
    "gn:population":15,
    "gn:timezone":"America/Mexico_City",
    "iso:country":"MX",
    "wof:name":"Las Huertas",
    "wof:placetype":"locality",
    "wof:population":15
},
  "geometry": {"coordinates":[-102.31833,22.00528],"type":"Point"}
}