{
  "type": "Feature",
  "properties": {
    "gn:admin1_code":"5",
    "gn:admin2_code":"57.0",
    "gn:asciiname":"Tierra Linda (Vuelta Caracol)",
    "gn:country_code":"MX",
    "gn:dem":1493,
    "gn:feature_class":"P",
    "gn:feature_code":"PPL",
    "gn:name":"Tierra Linda (Vuelta Caracol)",
    "gn:population":178,
    "gn:timezone":"America/Mexico_City",
    "iso:country":"MX",
    "wof:name":"Tierra Linda (Vuelta Caracol)",
    "wof:placetype":"locality",
    "wof:population":178
},
  "geometry": {"coordinates":[-92.25167,15.35444],"type":"Point"}
}