{
  "type": "Feature",
  "properties": {
    "gn:admin1_code":"30",
    "gn:admin2_code":"150.0",
    "gn:asciiname":"Santa Laura",
    "gn:country_code":"MX",
    "gn:dem":7,
    "gn:feature_class":"P",
    "gn:feature_code":"PPL",
    "gn:name":"Santa Laura",
    "gn:population":5,
    "gn:timezone":"America/Mexico_City",
    "iso:country":"MX",
    "name:ceb_x_preferred":[
        "Santa Laura"
    ],
    "name:ita_x_preferred":[
        "Santa Laura"
    ],
    "name:rus_x_preferred":[
        "\u041b\u0430\u0443\u0440\u0430"
    ],
    "name:spa_x_preferred":[
        "Santa Laura"
    ],
    "name:srp_x_preferred":[
        "\u0421\u0430\u043d\u0442\u0430 \u041b\u0430\u0443\u0440\u0430"
    ],
    "name:swe_x_preferred":[
        "Santa Laura"
    ],
    "wof:name":"Santa Laura",
    "wof:placetype":"locality",
    "wof:population":5
},
  "geometry": {"coordinates":[-97.64972,21.59389],"type":"Point"}
}