{
  "type": "Feature",
  "properties": {
    "gn:admin1_code":"24",
    "gn:admin2_code":"24.0",
    "gn:asciiname":"Rancho del Puente (Puente Prieto)",
    "gn:country_code":"MX",
    "gn:dem":1307,
    "gn:feature_class":"P",
    "gn:feature_code":"PPL",
    "gn:name":"Rancho del Puente (Puente Prieto)",
    "gn:population":560,
    "gn:timezone":"America/Mexico_City",
    "iso:country":"MX",
    "wof:name":"Rancho del Puente (Puente Prieto)",
    "wof:placetype":"locality",
    "wof:population":560
},
  "geometry": {"coordinates":[-100.37222,21.9775],"type":"Point"}
}