{
  "type": "Feature",
  "properties": {
    "gn:admin1_code":"5",
    "gn:admin2_code":"64.0",
    "gn:asciiname":"Paxtonticja",
    "gn:country_code":"MX",
    "gn:dem":1756,
    "gn:feature_class":"P",
    "gn:feature_code":"PPL",
    "gn:name":"Paxtonticj\u00e1",
    "gn:population":0,
    "gn:timezone":"America/Mexico_City",
    "iso:country":"MX",
    "name:spa_x_preferred":[
        "Pashtonticja"
    ],
    "name:spa_x_variant":[
        "Paxtontij\u00e1",
        "Paxtonticj\u00e1"
    ],
    "wof:name":"Paxtonticja",
    "wof:placetype":"locality"
},
  "geometry": {"coordinates":[-92.27658,16.77469],"type":"Point"}
}