{
  "type": "Feature",
  "properties": {
    "gn:admin1_code":"27",
    "gn:admin2_code":"8.0",
    "gn:asciiname":"El Relajo",
    "gn:country_code":"MX",
    "gn:dem":12,
    "gn:feature_class":"P",
    "gn:feature_code":"PPL",
    "gn:name":"El Relajo",
    "gn:population":0,
    "gn:timezone":"America/Mexico_City",
    "iso:country":"MX",
    "name:spa_x_preferred":[
        "El Relajo"
    ],
    "wof:name":"El Relajo",
    "wof:placetype":"locality"
},
  "geometry": {"coordinates":[-93.91249999999999,17.75417000000001],"type":"Point"}
}