{
  "type": "Feature",
  "properties": {
    "gn:admin1_code":"14",
    "gn:admin2_code":"18.0",
    "gn:asciiname":"El Cuadro",
    "gn:country_code":"MX",
    "gn:dem":1543,
    "gn:feature_class":"P",
    "gn:feature_code":"PPL",
    "gn:name":"El Cuadro",
    "gn:population":6,
    "gn:timezone":"America/Mexico_City",
    "iso:country":"MX",
    "wof:name":"El Cuadro",
    "wof:placetype":"locality",
    "wof:population":6
},
  "geometry": {"coordinates":[-102.52694,20.38111],"type":"Point"}
}