{
  "type": "Feature",
  "properties": {
    "gn:admin1_code":"13",
    "gn:admin2_code":"49.0",
    "gn:asciiname":"Escondida de San Rafael",
    "gn:country_code":"MX",
    "gn:dem":735,
    "gn:feature_class":"P",
    "gn:feature_code":"PPL",
    "gn:name":"Escondida de San Rafael",
    "gn:population":0,
    "gn:timezone":"America/Mexico_City",
    "iso:country":"MX",
    "name:und_x_variant":[
        "La Escondida",
        "Escondida",
        "Escondida de San Rafael"
    ],
    "wof:name":"Escondida de San Rafael",
    "wof:placetype":"locality"
},
  "geometry": {"coordinates":[-99.01649999999999,21.24976],"type":"Point"}
}