{
  "type": "Feature",
  "properties": {
    "gn:admin1_code":"19",
    "gn:admin2_code":"16.0",
    "gn:asciiname":"La Florena",
    "gn:country_code":"MX",
    "gn:dem":274,
    "gn:feature_class":"P",
    "gn:feature_code":"PPL",
    "gn:name":"La Flore\u00f1a",
    "gn:population":0,
    "gn:timezone":"America/Monterrey",
    "iso:country":"MX",
    "name:spa_x_preferred":[
        "La Flore\u00f1a"
    ],
    "wof:name":"La Florena",
    "wof:placetype":"locality"
},
  "geometry": {"coordinates":[-99.8125,25.73611],"type":"Point"}
}