{
  "type": "Feature",
  "properties": {
    "gn:admin1_code":"20",
    "gn:admin2_code":"324.0",
    "gn:asciiname":"Comala",
    "gn:country_code":"MX",
    "gn:dem":303,
    "gn:feature_class":"P",
    "gn:feature_code":"PPL",
    "gn:name":"Comala",
    "gn:population":0,
    "gn:timezone":"America/Mexico_City",
    "iso:country":"MX",
    "name:spa_x_preferred":[
        "Comala"
    ],
    "name:und_x_variant":[
        "Comal"
    ],
    "wof:name":"Comala",
    "wof:placetype":"locality"
},
  "geometry": {"coordinates":[-96.47987999999999,15.86872],"type":"Point"}
}