{
  "type": "Feature",
  "properties": {
    "gn:admin1_code":"20",
    "gn:admin2_code":"324.0",
    "gn:asciiname":"Comala",
    "gn:country_code":"MX",
    "gn:dem":303,
    "gn:feature_class":"P",
    "gn:feature_code":"PPL",
    "gn:name":"Comala",
    "gn:population":0,
    "gn:timezone":"America/Mexico_City",
    "iso:country":"MX",
    "name:deu_x_preferred":[
        "Comala"
    ],
    "name:fra_x_preferred":[
        "Comala"
    ],
    "name:hun_x_preferred":[
        "Comala"
    ],
    "name:ind_x_preferred":[
        "Comala"
    ],
    "name:ita_x_preferred":[
        "Comala"
    ],
    "name:jpn_x_preferred":[
        "\u30b3\u30de\u30e9"
    ],
    "name:lad_x_preferred":[
        "Comala"
    ],
    "name:nld_x_preferred":[
        "Comala"
    ],
    "name:nor_x_preferred":[
        "Comala"
    ],
    "name:pol_x_preferred":[
        "Comala"
    ],
    "name:rus_x_preferred":[
        "\u041a\u043e\u043c\u0430\u043b\u0430"
    ],
    "name:spa_x_preferred":[
        "Comala"
    ],
    "name:srp_x_preferred":[
        "\u041a\u043e\u043c\u0430\u043b\u0430"
    ],
    "name:und_x_variant":[
        "Comal"
    ],
    "name:vie_x_preferred":[
        "Comala"
    ],
    "wof:name":"Comala",
    "wof:placetype":"locality"
},
  "geometry": {"coordinates":[-96.47987999999999,15.86872],"type":"Point"}
}