{
  "type": "Feature",
  "properties": {
    "gn:admin1_code":"26",
    "gn:admin2_code":"18.0",
    "gn:asciiname":"El Dieciocho",
    "gn:country_code":"MX",
    "gn:dem":41,
    "gn:feature_class":"P",
    "gn:feature_code":"PPL",
    "gn:name":"El Dieciocho",
    "gn:population":0,
    "gn:timezone":"America/Hermosillo",
    "iso:country":"MX",
    "name:spa_x_preferred":[
        "El Dieciocho"
    ],
    "wof:name":"El Dieciocho",
    "wof:placetype":"locality"
},
  "geometry": {"coordinates":[-109.92740000000001,27.70105],"type":"Point"}
}