{
  "type": "Feature",
  "properties": {
    "gn:admin1_code":"30",
    "gn:admin2_code":"105",
    "gn:asciiname":"Paso Chocolate",
    "gn:country_code":"MX",
    "gn:dem":38,
    "gn:feature_class":"P",
    "gn:feature_code":"PPL",
    "gn:name":"Paso Chocolate",
    "gn:population":25,
    "gn:timezone":"America/Mexico_City",
    "iso:country":"MX",
    "wof:name":"Paso Chocolate",
    "wof:placetype":"locality",
    "wof:population":25
},
  "geometry": {"coordinates":[-96.25806,18.91306],"type":"Point"}
}