{
  "type": "Feature",
  "properties": {
    "gn:admin1_code":"20",
    "gn:admin2_code":"277",
    "gn:asciiname":"Chinigue Segunda Seccion (La Quebradora)",
    "gn:country_code":"MX",
    "gn:dem":1478,
    "gn:feature_class":"P",
    "gn:feature_code":"PPL",
    "gn:name":"Chinigue Segunda Secci\u00f3n (La Quebradora)",
    "gn:population":39,
    "gn:timezone":"America/Mexico_City",
    "iso:country":"MX",
    "name:und_x_variant":[
        "Chinigue Segunda Secci\u00f3n (La Quebradora)"
    ],
    "wof:name":"Chinigue Segunda Seccion (La Quebradora)",
    "wof:placetype":"locality",
    "wof:population":39
},
  "geometry": {"coordinates":[-96.97694,16.53361],"type":"Point"}
}