{
  "type": "Feature",
  "properties": {
    "gn:admin1_code":"3.0",
    "gn:admin2_code":"1.0",
    "gn:asciiname":"Juncal",
    "gn:country_code":"MX",
    "gn:dem":15,
    "gn:feature_class":"P",
    "gn:feature_code":"PPL",
    "gn:name":"Juncal",
    "gn:population":0,
    "gn:timezone":"America/Mazatlan",
    "iso:country":"MX",
    "name:ceb_x_preferred":[
        "Juncal"
    ],
    "name:fra_x_preferred":[
        "Juncal"
    ],
    "name:kaz_x_preferred":[
        "\u0416\u0443\u043d\u043a\u0430\u043b"
    ],
    "name:msa_x_preferred":[
        "Juncal"
    ],
    "name:rus_x_preferred":[
        "\u0416\u0443\u043d\u043a\u0430\u043b"
    ],
    "wof:name":"Juncal",
    "wof:placetype":"locality"
},
  "geometry": {"coordinates":[-111.78333000000001,24.83333],"type":"Point"}
}