{
  "type": "Feature",
  "properties": {
    "gn:admin1_code":"30",
    "gn:admin2_code":"110.0",
    "gn:asciiname":"Tecolotla",
    "gn:country_code":"MX",
    "gn:dem":989,
    "gn:feature_class":"P",
    "gn:feature_code":"PPL",
    "gn:name":"Tecolotla",
    "gn:population":0,
    "gn:timezone":"America/Mexico_City",
    "iso:country":"MX",
    "name:spa_x_preferred":[
        "Tecolotla"
    ],
    "wof:name":"Tecolotla",
    "wof:placetype":"locality"
},
  "geometry": {"coordinates":[-96.95359000000001,18.58791],"type":"Point"}
}