{
  "type": "Feature",
  "properties": {
    "gn:admin1_code":"30",
    "gn:admin2_code":"144.0",
    "gn:asciiname":"El Veintisiete",
    "gn:country_code":"MX",
    "gn:dem":23,
    "gn:feature_class":"P",
    "gn:feature_code":"PPL",
    "gn:name":"El Veintisiete",
    "gn:population":0,
    "gn:timezone":"America/Mexico_City",
    "iso:country":"MX",
    "name:spa_x_preferred":[
        "El Veintisiete"
    ],
    "wof:name":"El Veintisiete",
    "wof:placetype":"locality"
},
  "geometry": {"coordinates":[-94.81553,17.66847000000001],"type":"Point"}
}