{
  "type": "Feature",
  "properties": {
    "gn:admin1_code":"5",
    "gn:admin2_code":"17.0",
    "gn:asciiname":"Villamorelos",
    "gn:country_code":"MX",
    "gn:dem":707,
    "gn:feature_class":"P",
    "gn:feature_code":"PPL",
    "gn:name":"Villamorelos",
    "gn:population":1677,
    "gn:timezone":"America/Mexico_City",
    "iso:country":"MX",
    "wof:name":"Villamorelos",
    "wof:placetype":"locality",
    "wof:population":1677
},
  "geometry": {"coordinates":[-93.92778,16.48],"type":"Point"}
}