{
  "type": "Feature",
  "properties": {
    "gn:admin1_code":"6",
    "gn:admin2_code":"19.0",
    "gn:asciiname":"Ejido Sacramento",
    "gn:country_code":"MX",
    "gn:dem":1527,
    "gn:feature_class":"P",
    "gn:feature_code":"PPL",
    "gn:name":"Ejido Sacramento",
    "gn:population":0,
    "gn:timezone":"America/Chihuahua",
    "iso:country":"MX",
    "name:und_x_variant":[
        "Nuevo Sacramento"
    ],
    "wof:name":"Ejido Sacramento",
    "wof:placetype":"locality"
},
  "geometry": {"coordinates":[-106.18021,28.82848],"type":"Point"}
}