{
  "type": "Feature",
  "properties": {
    "gn:admin1_code":"20",
    "gn:admin2_code":"182.0",
    "gn:asciiname":"San Esteban Tectitlan",
    "gn:country_code":"MX",
    "gn:dem":244,
    "gn:elevation":"240.0",
    "gn:feature_class":"P",
    "gn:feature_code":"PPL",
    "gn:name":"San Esteban Tectitl\u00e1n",
    "gn:population":0,
    "gn:timezone":"America/Mexico_City",
    "iso:country":"MX",
    "wof:name":"San Esteban Tectitlan",
    "wof:placetype":"locality"
},
  "geometry": {"coordinates":[-96.55028,17.87082999999999],"type":"Point"}
}