{
  "type": "Feature",
  "properties": {
    "gn:admin1_code":"5.0",
    "gn:admin2_code":"3.0",
    "gn:asciiname":"Las Morenas",
    "gn:country_code":"MX",
    "gn:dem":9,
    "gn:feature_class":"P",
    "gn:feature_code":"PPL",
    "gn:name":"Las Morenas",
    "gn:population":0,
    "gn:timezone":"America/Mexico_City",
    "iso:country":"MX",
    "name:spa_x_preferred":[
        "Las Morenas"
    ],
    "wof:name":"Las Morenas",
    "wof:placetype":"locality"
},
  "geometry": {"coordinates":[-92.77797,15.20797],"type":"Point"}
}