{
  "type": "Feature",
  "properties": {
    "gn:admin1_code":"30",
    "gn:admin2_code":"8.0",
    "gn:asciiname":"Acolco",
    "gn:country_code":"MX",
    "gn:dem":1771,
    "gn:feature_class":"P",
    "gn:feature_code":"PPL",
    "gn:name":"Acolco",
    "gn:population":463,
    "gn:timezone":"America/Mexico_City",
    "iso:country":"MX",
    "wof:name":"Acolco",
    "wof:placetype":"locality",
    "wof:population":463
},
  "geometry": {"coordinates":[-97.08139,19.1125],"type":"Point"}
}