{
  "type": "Feature",
  "properties": {
    "gn:admin1_code":"27.0",
    "gn:admin2_code":"8.0",
    "gn:asciiname":"Oxtitan",
    "gn:country_code":"MX",
    "gn:dem":39,
    "gn:feature_class":"P",
    "gn:feature_code":"PPL",
    "gn:name":"Oxtit\u00e1n",
    "gn:population":0,
    "gn:timezone":"America/Mexico_City",
    "iso:country":"MX",
    "name:spa_x_preferred":[
        "Oxtit\u00e1n"
    ],
    "name:spa_x_variant":[
        "Segunda Secci\u00f3n"
    ],
    "wof:name":"Oxtitan",
    "wof:placetype":"locality"
},
  "geometry": {"coordinates":[-93.41603000000001,17.74907],"type":"Point"}
}