{
  "type": "Feature",
  "properties": {
    "gn:admin1_code":"14",
    "gn:admin2_code":"111.0",
    "gn:asciiname":"Puerta de Medina",
    "gn:country_code":"MX",
    "gn:dem":1872,
    "gn:feature_class":"P",
    "gn:feature_code":"PPL",
    "gn:name":"Puerta de Medina",
    "gn:population":6,
    "gn:timezone":"America/Mexico_City",
    "iso:country":"MX",
    "wof:name":"Puerta de Medina",
    "wof:placetype":"locality",
    "wof:population":6
},
  "geometry": {"coordinates":[-102.60194,21.08639],"type":"Point"}
}