{
  "type": "Feature",
  "properties": {
    "gn:admin1_code":"14.0",
    "gn:admin2_code":"43.0",
    "gn:asciiname":"Paraiso Nuevo",
    "gn:country_code":"MX",
    "gn:dem":121,
    "gn:feature_class":"P",
    "gn:feature_code":"PPL",
    "gn:name":"Para\u00edso Nuevo",
    "gn:population":0,
    "gn:timezone":"America/Mexico_City",
    "iso:country":"MX",
    "name:spa_x_preferred":[
        "Para\u00edso Nuevo"
    ],
    "wof:name":"Paraiso Nuevo",
    "wof:placetype":"locality"
},
  "geometry": {"coordinates":[-104.84005000000001,19.55093],"type":"Point"}
}