{
  "type": "Feature",
  "properties": {
    "gn:admin1_code":"7.0",
    "gn:admin2_code":"38.0",
    "gn:asciiname":"El Gato",
    "gn:country_code":"MX",
    "gn:dem":388,
    "gn:feature_class":"P",
    "gn:feature_code":"PPL",
    "gn:name":"El Gato",
    "gn:population":0,
    "gn:timezone":"America/Monterrey",
    "iso:country":"MX",
    "name:spa_x_preferred":[
        "El Gato"
    ],
    "wof:name":"El Gato",
    "wof:placetype":"locality"
},
  "geometry": {"coordinates":[-100.97675,28.43772],"type":"Point"}
}