{
  "type": "Feature",
  "properties": {
    "gn:admin1_code":"14",
    "gn:admin2_code":"8.0",
    "gn:asciiname":"Salto de Nogales",
    "gn:country_code":"MX",
    "gn:dem":2029,
    "gn:feature_class":"P",
    "gn:feature_code":"PPL",
    "gn:name":"Salto de Nogales",
    "gn:population":0,
    "gn:timezone":"America/Mexico_City",
    "iso:country":"MX",
    "name:spa_x_preferred":[
        "Salto de Nogales"
    ],
    "wof:name":"Salto de Nogales",
    "wof:placetype":"locality"
},
  "geometry": {"coordinates":[-102.19614,20.81344],"type":"Point"}
}