{
  "type": "Feature",
  "properties": {
    "gn:admin1_code":"10",
    "gn:admin2_code":"35.0",
    "gn:asciiname":"Rancho de Enmedio",
    "gn:country_code":"MX",
    "gn:dem":2193,
    "gn:feature_class":"P",
    "gn:feature_code":"PPL",
    "gn:name":"Rancho de Enmedio",
    "gn:population":6,
    "gn:timezone":"America/Monterrey",
    "iso:country":"MX",
    "wof:name":"Rancho de Enmedio",
    "wof:placetype":"locality",
    "wof:population":6
},
  "geometry": {"coordinates":[-106.33566,25.47903],"type":"Point"}
}