{
  "type": "Feature",
  "properties": {
    "gn:admin1_code":"23",
    "gn:admin2_code":"4.0",
    "gn:asciiname":"Modesto Camara",
    "gn:country_code":"MX",
    "gn:dem":68,
    "gn:feature_class":"P",
    "gn:feature_code":"PPL",
    "gn:name":"Modesto C\u00e1mara",
    "gn:population":0,
    "gn:timezone":"America/Cancun",
    "iso:country":"MX",
    "wof:name":"Modesto Camara",
    "wof:placetype":"locality"
},
  "geometry": {"coordinates":[-88.65000000000001,18.95],"type":"Point"}
}