{
  "type": "Feature",
  "properties": {
    "gn:admin1_code":"6",
    "gn:admin2_code":"9",
    "gn:asciiname":"Magueyito",
    "gn:country_code":"MX",
    "gn:dem":2541,
    "gn:feature_class":"P",
    "gn:feature_code":"PPL",
    "gn:name":"Magueyito",
    "gn:population":13,
    "gn:timezone":"America/Chihuahua",
    "iso:country":"MX",
    "wof:name":"Magueyito",
    "wof:placetype":"locality",
    "wof:population":13
},
  "geometry": {"coordinates":[-107.35075999999999,27.88075],"type":"Point"}
}