{
  "type": "Feature",
  "properties": {
    "gn:admin1_code":"30",
    "gn:admin2_code":"174",
    "gn:asciiname":"La Tepetaca",
    "gn:country_code":"MX",
    "gn:dem":54,
    "gn:feature_class":"P",
    "gn:feature_code":"PPL",
    "gn:name":"La Tepetaca",
    "gn:population":11,
    "gn:timezone":"America/Mexico_City",
    "iso:country":"MX",
    "wof:name":"La Tepetaca",
    "wof:placetype":"locality",
    "wof:population":11
},
  "geometry": {"coordinates":[-96.29306,18.54389],"type":"Point"}
}