{
  "type": "Feature",
  "properties": {
    "gn:admin1_code":"3",
    "gn:admin2_code":"1.0",
    "gn:asciiname":"Pozo Hondo",
    "gn:country_code":"MX",
    "gn:dem":48,
    "gn:feature_class":"P",
    "gn:feature_code":"PPL",
    "gn:name":"Pozo Hondo",
    "gn:population":0,
    "gn:timezone":"America/Mazatlan",
    "iso:country":"MX",
    "name:ceb_x_preferred":[
        "Pozo Hondo"
    ],
    "name:deu_x_preferred":[
        "Pozo Hondo"
    ],
    "name:fra_x_preferred":[
        "Pozo Hondo"
    ],
    "name:ita_x_preferred":[
        "Pozo Hondo"
    ],
    "name:nld_x_preferred":[
        "Pozo Hondo"
    ],
    "name:spa_x_preferred":[
        "Pozo Hondo"
    ],
    "name:zho_x_preferred":[
        "\u6ce2\u7d22\u7fc1\u591a"
    ],
    "wof:name":"Pozo Hondo",
    "wof:placetype":"locality"
},
  "geometry": {"coordinates":[-111.59999999999999,24.88333],"type":"Point"}
}