{
  "type": "Feature",
  "properties": {
    "gn:admin1_code":"26",
    "gn:admin2_code":"43.0",
    "gn:asciiname":"Los Adobes",
    "gn:country_code":"MX",
    "gn:dem":1195,
    "gn:feature_class":"P",
    "gn:feature_code":"PPL",
    "gn:name":"Los Adobes",
    "gn:population":0,
    "gn:timezone":"America/Hermosillo",
    "iso:country":"MX",
    "name:und_x_variant":[
        "Adobes",
        "Los Adobes"
    ],
    "wof:name":"Los Adobes",
    "wof:placetype":"locality"
},
  "geometry": {"coordinates":[-111.16029,31.30508],"type":"Point"}
}