{
  "type": "Feature",
  "properties": {
    "gn:admin1_code":"2",
    "gn:admin2_code":"1.0",
    "gn:asciiname":"El Sauce de Carter",
    "gn:country_code":"MX",
    "gn:dem":527,
    "gn:feature_class":"P",
    "gn:feature_code":"PPL",
    "gn:name":"El Sauce de Carter",
    "gn:population":0,
    "gn:timezone":"America/Tijuana",
    "iso:country":"MX",
    "name:spa_x_preferred":[
        "El Sauce de Carter"
    ],
    "wof:name":"El Sauce de Carter",
    "wof:placetype":"locality"
},
  "geometry": {"coordinates":[-115.22614,30.24082000000001],"type":"Point"}
}