{
  "type": "Feature",
  "properties": {
    "gn:admin1_code":"23",
    "gn:admin2_code":"6.0",
    "gn:asciiname":"San Nicolas Uno",
    "gn:country_code":"MX",
    "gn:dem":52,
    "gn:feature_class":"P",
    "gn:feature_code":"PPL",
    "gn:name":"San Nicol\u00e1s Uno",
    "gn:population":0,
    "gn:timezone":"America/Cancun",
    "iso:country":"MX",
    "name:spa_x_preferred":[
        "San Nicol\u00e1s Uno"
    ],
    "wof:name":"San Nicolas Uno",
    "wof:placetype":"locality"
},
  "geometry": {"coordinates":[-88.98874000000001,19.6541],"type":"Point"}
}