{
  "type": "Feature",
  "properties": {
    "gn:admin1_code":"8.0",
    "gn:admin2_code":"2.0",
    "gn:asciiname":"La Higuerita",
    "gn:country_code":"MX",
    "gn:dem":701,
    "gn:feature_class":"P",
    "gn:feature_code":"PPL",
    "gn:name":"La Higuerita",
    "gn:population":0,
    "gn:timezone":"America/Mexico_City",
    "iso:country":"MX",
    "name:spa_x_preferred":[
        "La Higuerita"
    ],
    "name:und_x_variant":[
        "La Huiguerita"
    ],
    "wof:name":"La Higuerita",
    "wof:placetype":"locality"
},
  "geometry": {"coordinates":[-103.62975,19.04928],"type":"Point"}
}