{
  "type": "Feature",
  "properties": {
    "gn:admin1_code":"11.0",
    "gn:admin2_code":"30.0",
    "gn:asciiname":"Canada de Leon",
    "gn:country_code":"MX",
    "gn:dem":2153,
    "gn:feature_class":"P",
    "gn:feature_code":"PPL",
    "gn:name":"Ca\u00f1ada de Le\u00f3n",
    "gn:population":54,
    "gn:timezone":"America/Mexico_City",
    "iso:country":"MX",
    "wof:name":"Canada de Leon",
    "wof:placetype":"locality",
    "wof:population":54
},
  "geometry": {"coordinates":[-101.26917,21.43028],"type":"Point"}
}