{
  "type": "Feature",
  "properties": {
    "gn:admin1_code":"5.0",
    "gn:asciiname":"Santa Isela",
    "gn:country_code":"MX",
    "gn:dem":12,
    "gn:feature_class":"P",
    "gn:feature_code":"PPL",
    "gn:name":"Santa Isela",
    "gn:population":0,
    "gn:timezone":"America/Mexico_City",
    "iso:country":"MX",
    "name:spa_x_preferred":[
        "Santa Isela"
    ],
    "wof:name":"Santa Isela",
    "wof:placetype":"locality"
},
  "geometry": {"coordinates":[-93.05,15.40001],"type":"Point"}
}