{
  "type": "Feature",
  "properties": {
    "gn:admin1_code":"6",
    "gn:admin2_code":"27.0",
    "gn:asciiname":"Orachi",
    "gn:country_code":"MX",
    "gn:dem":2410,
    "gn:feature_class":"P",
    "gn:feature_code":"PPL",
    "gn:name":"Orachi",
    "gn:population":74,
    "gn:timezone":"America/Chihuahua",
    "iso:country":"MX",
    "wof:name":"Orachi",
    "wof:placetype":"locality",
    "wof:population":74
},
  "geometry": {"coordinates":[-107.39543999999999,26.77466],"type":"Point"}
}