{
  "type": "Feature",
  "properties": {
    "gn:admin1_code":"6",
    "gn:admin2_code":"19.0",
    "gn:asciiname":"Colonia Roberto Orozco",
    "gn:country_code":"MX",
    "gn:dem":1465,
    "gn:feature_class":"P",
    "gn:feature_code":"PPL",
    "gn:name":"Colonia Roberto Orozco",
    "gn:population":6,
    "gn:timezone":"America/Chihuahua",
    "iso:country":"MX",
    "wof:name":"Colonia Roberto Orozco",
    "wof:placetype":"locality",
    "wof:population":6
},
  "geometry": {"coordinates":[-106.10196999999999,28.76689],"type":"Point"}
}