{
  "type": "Feature",
  "properties": {
    "gn:admin1_code":"26.0",
    "gn:admin2_code":"39.0",
    "gn:asciiname":"Papalote el Coyote",
    "gn:country_code":"MX",
    "gn:dem":1362,
    "gn:feature_class":"P",
    "gn:feature_code":"PPL",
    "gn:name":"Papalote el Coyote",
    "gn:population":0,
    "gn:timezone":"America/Hermosillo",
    "iso:country":"MX",
    "name:spa_x_preferred":[
        "Papalote el Coyote"
    ],
    "wof:name":"Papalote el Coyote",
    "wof:placetype":"locality"
},
  "geometry": {"coordinates":[-110.18339,31.31946],"type":"Point"}
}