{
  "type": "Feature",
  "properties": {
    "gn:admin1_code":"3.0",
    "gn:admin2_code":"1.0",
    "gn:asciiname":"La Jicama",
    "gn:country_code":"MX",
    "gn:dem":544,
    "gn:feature_class":"P",
    "gn:feature_code":"PPL",
    "gn:name":"La Jicama",
    "gn:population":0,
    "gn:timezone":"America/Mazatlan",
    "iso:country":"MX",
    "name:spa_x_preferred":[
        "La Jicama"
    ],
    "wof:name":"La Jicama",
    "wof:placetype":"locality"
},
  "geometry": {"coordinates":[-112.02551,26.40122],"type":"Point"}
}