{
  "type": "Feature",
  "properties": {
    "gn:admin1_code":"20",
    "gn:admin2_code":"24",
    "gn:asciiname":"Naranjo",
    "gn:country_code":"MX",
    "gn:dem":1466,
    "gn:feature_class":"P",
    "gn:feature_code":"PPL",
    "gn:name":"Naranjo",
    "gn:population":11,
    "gn:timezone":"America/Mexico_City",
    "iso:country":"MX",
    "name:deu_x_preferred":[
        "Naranjo"
    ],
    "name:fra_x_preferred":[
        "Naranjo"
    ],
    "name:ind_x_preferred":[
        "Naranjo"
    ],
    "name:ita_x_preferred":[
        "Naranjo"
    ],
    "name:jpn_x_preferred":[
        "\u30ca\u30e9\u30f3\u30db"
    ],
    "name:lit_x_preferred":[
        "Naranchas"
    ],
    "name:rus_x_preferred":[
        "\u041d\u0430\u0440\u0430\u043d\u0445\u043e"
    ],
    "name:spa_x_preferred":[
        "El Naranjo"
    ],
    "name:ukr_x_preferred":[
        "\u041d\u0430\u0440\u0430\u043d\u0445\u043e"
    ],
    "name:zho_x_preferred":[
        "\u7eb3\u5170\u6c38"
    ],
    "wof:name":"Naranjo",
    "wof:placetype":"locality",
    "wof:population":11
},
  "geometry": {"coordinates":[-96.83750000000001,17.96611],"type":"Point"}
}