{
  "type": "Feature",
  "properties": {
    "gn:admin1_code":"12",
    "gn:admin2_code":"23.0",
    "gn:asciiname":"El Vaiven",
    "gn:country_code":"MX",
    "gn:dem":26,
    "gn:feature_class":"P",
    "gn:feature_code":"PPL",
    "gn:name":"El Vaiv\u00e9n",
    "gn:population":258,
    "gn:timezone":"America/Mexico_City",
    "iso:country":"MX",
    "name:und_x_variant":[
        "El Vaiv\u00e9n"
    ],
    "wof:name":"El Vaiven",
    "wof:placetype":"locality",
    "wof:population":258
},
  "geometry": {"coordinates":[-98.65944,16.50306],"type":"Point"}
}