{
  "type": "Feature",
  "properties": {
    "gn:admin1_code":"5",
    "gn:admin2_code":"65.0",
    "gn:asciiname":"El Espejo",
    "gn:country_code":"MX",
    "gn:dem":437,
    "gn:feature_class":"P",
    "gn:feature_code":"PPL",
    "gn:name":"El Espejo",
    "gn:population":76,
    "gn:timezone":"America/Mexico_City",
    "iso:country":"MX",
    "wof:name":"El Espejo",
    "wof:placetype":"locality",
    "wof:population":76
},
  "geometry": {"coordinates":[-91.47,17.105],"type":"Point"}
}