{
  "type": "Feature",
  "properties": {
    "gn:admin1_code":"29",
    "gn:admin2_code":"53.0",
    "gn:asciiname":"Xalatla",
    "gn:country_code":"MX",
    "gn:dem":2205,
    "gn:feature_class":"P",
    "gn:feature_code":"PPL",
    "gn:name":"Xalatla",
    "gn:population":58,
    "gn:timezone":"America/Mexico_City",
    "iso:country":"MX",
    "wof:name":"Xalatla",
    "wof:placetype":"locality",
    "wof:population":58
},
  "geometry": {"coordinates":[-98.25424,19.24074],"type":"Point"}
}