{
  "type": "Feature",
  "properties": {
    "gn:admin1_code":"16.0",
    "gn:admin2_code":"12.0",
    "gn:asciiname":"El Gapiri",
    "gn:country_code":"MX",
    "gn:dem":915,
    "gn:feature_class":"P",
    "gn:feature_code":"PPL",
    "gn:name":"El Gapiri",
    "gn:population":0,
    "gn:timezone":"America/Mexico_City",
    "iso:country":"MX",
    "name:spa_x_preferred":[
        "El Gapiri"
    ],
    "wof:name":"El Gapiri",
    "wof:placetype":"locality"
},
  "geometry": {"coordinates":[-102.52011,19.25266],"type":"Point"}
}