{
  "type": "Feature",
  "properties": {
    "gn:admin1_code":"30",
    "gn:admin2_code":"142.0",
    "gn:asciiname":"La Caudalosa",
    "gn:country_code":"MX",
    "gn:dem":139,
    "gn:feature_class":"P",
    "gn:feature_code":"PPL",
    "gn:name":"La Caudalosa",
    "gn:population":914,
    "gn:timezone":"America/Mexico_City",
    "iso:country":"MX",
    "wof:name":"La Caudalosa",
    "wof:placetype":"locality",
    "wof:population":914
},
  "geometry": {"coordinates":[-95.0675,17.82082999999999],"type":"Point"}
}