{
  "type": "Feature",
  "properties": {
    "gn:admin1_code":"19",
    "gn:admin2_code":"45.0",
    "gn:asciiname":"Palo Blanco",
    "gn:country_code":"MX",
    "gn:dem":560,
    "gn:feature_class":"P",
    "gn:feature_code":"PPL",
    "gn:name":"Palo Blanco",
    "gn:population":5,
    "gn:timezone":"America/Monterrey",
    "iso:country":"MX",
    "name:ceb_x_preferred":[
        "Palo Blanco"
    ],
    "name:spa_x_preferred":[
        "Palo blanco"
    ],
    "name:swe_x_preferred":[
        "Palo Blanco"
    ],
    "name:und_x_variant":[
        "Rancho Palo Blanco",
        "Estaci\u00f3n Palo Blanco"
    ],
    "wof:name":"Palo Blanco",
    "wof:placetype":"locality",
    "wof:population":5
},
  "geometry": {"coordinates":[-100.36662,26.26401],"type":"Point"}
}