{
  "type": "Feature",
  "properties": {
    "gn:admin1_code":"32.0",
    "gn:admin2_code":"17.0",
    "gn:asciiname":"Las Mangas",
    "gn:country_code":"MX",
    "gn:dem":2388,
    "gn:feature_class":"P",
    "gn:feature_code":"PPL",
    "gn:name":"Las Mangas",
    "gn:population":0,
    "gn:timezone":"America/Mexico_City",
    "iso:country":"MX",
    "name:spa_x_preferred":[
        "Las Mangas"
    ],
    "wof:name":"Las Mangas",
    "wof:placetype":"locality"
},
  "geometry": {"coordinates":[-102.54781,22.59299],"type":"Point"}
}