{
  "type": "Feature",
  "properties": {
    "gn:admin1_code":"27",
    "gn:admin2_code":"5.0",
    "gn:asciiname":"Progreso Tular Primera Seccion",
    "gn:country_code":"MX",
    "gn:dem":13,
    "gn:feature_class":"P",
    "gn:feature_code":"PPL",
    "gn:name":"Progreso Tular Primera Secci\u00f3n",
    "gn:population":0,
    "gn:timezone":"America/Mexico_City",
    "iso:country":"MX",
    "name:spa_x_preferred":[
        "Progreso Tular Primera Secci\u00f3n"
    ],
    "wof:name":"Progreso Tular Primera Seccion",
    "wof:placetype":"locality"
},
  "geometry": {"coordinates":[-93.39709999999999,18.29287],"type":"Point"}
}