{
  "type": "Feature",
  "properties": {
    "gn:admin1_code":"6.0",
    "gn:admin2_code":"27.0",
    "gn:asciiname":"Basaseachi",
    "gn:country_code":"MX",
    "gn:dem":2303,
    "gn:feature_class":"P",
    "gn:feature_code":"PPL",
    "gn:name":"Basaseachi",
    "gn:population":0,
    "gn:timezone":"America/Chihuahua",
    "iso:country":"MX",
    "name:spa_x_preferred":[
        "Basaseachi"
    ],
    "wof:name":"Basaseachi",
    "wof:placetype":"locality"
},
  "geometry": {"coordinates":[-107.48900999999999,27.51097],"type":"Point"}
}