{
  "type": "Feature",
  "properties": {
    "gn:admin1_code":"12.0",
    "gn:admin2_code":"11.0",
    "gn:asciiname":"Finca la Flor del Cafe",
    "gn:country_code":"MX",
    "gn:dem":1305,
    "gn:feature_class":"P",
    "gn:feature_code":"PPL",
    "gn:name":"Finca la Flor del Caf\u00e9",
    "gn:population":0,
    "gn:timezone":"America/Mexico_City",
    "iso:country":"MX",
    "name:spa_x_preferred":[
        "Finca la Flor del Caf\u00e9"
    ],
    "wof:name":"Finca la Flor del Cafe",
    "wof:placetype":"locality"
},
  "geometry": {"coordinates":[-100.15076999999999,17.34302000000001],"type":"Point"}
}