{
  "type": "Feature",
  "properties": {
    "gn:admin1_code":"19",
    "gn:admin2_code":"17.0",
    "gn:asciiname":"Salida a San Lucas (Virgilio Alejandro A.)",
    "gn:country_code":"MX",
    "gn:dem":1683,
    "gn:feature_class":"P",
    "gn:feature_code":"PPL",
    "gn:name":"Salida a San Lucas (Virgilio Alejandro A.)",
    "gn:population":9,
    "gn:timezone":"America/Monterrey",
    "iso:country":"MX",
    "wof:name":"Salida a San Lucas (Virgilio Alejandro A.)",
    "wof:placetype":"locality",
    "wof:population":9
},
  "geometry": {"coordinates":[-100.08194,24.83396],"type":"Point"}
}