{
  "type": "Feature",
  "properties": {
    "gn:admin1_code":"25.0",
    "gn:asciiname":"El Oso de Arriba",
    "gn:country_code":"MX",
    "gn:dem":1073,
    "gn:feature_class":"P",
    "gn:feature_code":"PPL",
    "gn:name":"El Oso de Arriba",
    "gn:population":0,
    "gn:timezone":"America/Mazatlan",
    "iso:country":"MX",
    "name:spa_x_preferred":[
        "El Oso de Arriba"
    ],
    "wof:name":"El Oso de Arriba",
    "wof:placetype":"locality"
},
  "geometry": {"coordinates":[-106.23239,24.28019],"type":"Point"}
}