{
  "type": "Feature",
  "properties": {
    "gn:admin1_code":"5",
    "gn:admin2_code":"97.0",
    "gn:asciiname":"Cosolapa",
    "gn:country_code":"MX",
    "gn:dem":64,
    "gn:feature_class":"P",
    "gn:feature_code":"PPL",
    "gn:name":"Cosolapa",
    "gn:population":0,
    "gn:timezone":"America/Mexico_City",
    "iso:country":"MX",
    "name:ceb_x_preferred":[
        "Cosolapa"
    ],
    "name:epo_x_preferred":[
        "Cosolapa"
    ],
    "name:eus_x_preferred":[
        "Cosolapa"
    ],
    "name:ita_x_preferred":[
        "Cosolapa"
    ],
    "name:rus_x_preferred":[
        "\u041a\u043e\u0441\u043e\u043b\u0430\u043f\u0430"
    ],
    "name:sco_x_preferred":[
        "Cosolapa"
    ],
    "name:spa_x_preferred":[
        "Cosolapa"
    ],
    "name:srp_x_preferred":[
        "\u041a\u043e\u0441\u043e\u043b\u0430\u043f\u0430"
    ],
    "name:swe_x_preferred":[
        "Cosolapa"
    ],
    "name:vie_x_preferred":[
        "Cosolapa"
    ],
    "wof:name":"Cosolapa",
    "wof:placetype":"locality"
},
  "geometry": {"coordinates":[-93.71666999999999,16.03333],"type":"Point"}
}