{
  "type": "Feature",
  "properties": {
    "gn:admin1_code":"6",
    "gn:admin2_code":"41.0",
    "gn:asciiname":"Choreachi",
    "gn:country_code":"MX",
    "gn:dem":2122,
    "gn:feature_class":"P",
    "gn:feature_code":"PPL",
    "gn:name":"Choreachi",
    "gn:population":7,
    "gn:timezone":"America/Chihuahua",
    "iso:country":"MX",
    "wof:name":"Choreachi",
    "wof:placetype":"locality",
    "wof:population":7
},
  "geometry": {"coordinates":[-107.94132,27.69186],"type":"Point"}
}