{
  "type": "Feature",
  "properties": {
    "gn:admin1_code":"14",
    "gn:admin2_code":"45",
    "gn:asciiname":"La Presa",
    "gn:country_code":"MX",
    "gn:dem":1899,
    "gn:feature_class":"P",
    "gn:feature_code":"PPL",
    "gn:name":"La Presa",
    "gn:population":24,
    "gn:timezone":"America/Mexico_City",
    "iso:country":"MX",
    "wof:name":"La Presa",
    "wof:placetype":"locality",
    "wof:population":24
},
  "geometry": {"coordinates":[-103.17892999999999,20.94176],"type":"Point"}
}