{
  "type": "Feature",
  "properties": {
    "gn:admin1_code":"7",
    "gn:admin2_code":"18",
    "gn:asciiname":"Fraccion San Miguel (Jesus de la Cruz)",
    "gn:country_code":"MX",
    "gn:dem":592,
    "gn:feature_class":"P",
    "gn:feature_code":"PPL",
    "gn:name":"Fracci\u00f3n San Miguel (Jes\u00fas de la Cruz)",
    "gn:population":15,
    "gn:timezone":"America/Monterrey",
    "iso:country":"MX",
    "name:und_x_variant":[
        "Fracci\u00f3n San Miguel (Jes\u00fas de la Cruz)"
    ],
    "wof:name":"Fraccion San Miguel (Jesus de la Cruz)",
    "wof:placetype":"locality",
    "wof:population":15
},
  "geometry": {"coordinates":[-101.34341000000001,26.93694],"type":"Point"}
}