{
  "type": "Feature",
  "properties": {
    "gn:admin1_code":"15",
    "gn:admin2_code":"40.0",
    "gn:asciiname":"Meson Nuevo",
    "gn:country_code":"MX",
    "gn:dem":1759,
    "gn:feature_class":"P",
    "gn:feature_code":"PPL",
    "gn:name":"Mes\u00f3n Nuevo",
    "gn:population":0,
    "gn:timezone":"America/Mexico_City",
    "iso:country":"MX",
    "name:spa_x_preferred":[
        "Mes\u00f3n Nuevo"
    ],
    "wof:name":"Meson Nuevo",
    "wof:placetype":"locality"
},
  "geometry": {"coordinates":[-99.71742999999999,18.81079],"type":"Point"}
}