{
  "type": "Feature",
  "properties": {
    "gn:admin1_code":"30",
    "gn:admin2_code":"123.0",
    "gn:asciiname":"Barrotera del Tamesi",
    "gn:country_code":"MX",
    "gn:dem":7,
    "gn:feature_class":"P",
    "gn:feature_code":"PPL",
    "gn:name":"Barrotera del Tames\u00ed",
    "gn:population":89,
    "gn:timezone":"America/Mexico_City",
    "iso:country":"MX",
    "name:und_x_variant":[
        "Barrotera del Tames\u00ed"
    ],
    "wof:name":"Barrotera del Tamesi",
    "wof:placetype":"locality",
    "wof:population":89
},
  "geometry": {"coordinates":[-98.31917,22.42222000000001],"type":"Point"}
}