{
  "type": "Feature",
  "properties": {
    "gn:admin1_code":"5",
    "gn:admin2_code":"69.0",
    "gn:asciiname":"Las Marias",
    "gn:country_code":"MX",
    "gn:dem":52,
    "gn:feature_class":"P",
    "gn:feature_code":"PPL",
    "gn:name":"Las Mar\u00edas",
    "gn:population":5,
    "gn:timezone":"America/Mexico_City",
    "iso:country":"MX",
    "name:und_x_variant":[
        "Las Mar\u00edas"
    ],
    "wof:name":"Las Marias",
    "wof:placetype":"locality",
    "wof:population":5
},
  "geometry": {"coordinates":[-93.22111,15.69972],"type":"Point"}
}