{
  "type": "Feature",
  "properties": {
    "gn:admin1_code":"30",
    "gn:admin2_code":"72.0",
    "gn:asciiname":"Corcovado",
    "gn:country_code":"MX",
    "gn:dem":2198,
    "gn:feature_class":"P",
    "gn:feature_code":"PPL",
    "gn:name":"Corcovado",
    "gn:population":87,
    "gn:timezone":"America/Mexico_City",
    "iso:country":"MX",
    "name:ara_x_preferred":[
        "\u0643\u0648\u0631\u0643\u0648\u0641\u0627\u062f\u0648"
    ],
    "name:bel_x_preferred":[
        "\u041a\u0430\u0440\u043a\u0430\u0432\u0430\u0434\u0443"
    ],
    "name:bos_x_preferred":[
        "Corcovado"
    ],
    "name:bre_x_preferred":[
        "Corcovado"
    ],
    "name:bul_x_preferred":[
        "\u041a\u043e\u0440\u043a\u043e\u0432\u0430\u0434\u043e"
    ],
    "name:ces_x_preferred":[
        "Corcovado"
    ],
    "name:deu_x_preferred":[
        "Corcovado"
    ],
    "name:est_x_preferred":[
        "Corcovado"
    ],
    "name:eus_x_preferred":[
        "Corcovado"
    ],
    "name:fin_x_preferred":[
        "Corcovado"
    ],
    "name:fra_x_preferred":[
        "Corcovado"
    ],
    "name:gle_x_preferred":[
        "Corcovado"
    ],
    "name:heb_x_preferred":[
        "\u05d4\u05e8 \u05e7\u05d5\u05e8\u05e7\u05d5\u05d1\u05d3\u05d5"
    ],
    "name:hrv_x_preferred":[
        "Corcovado"
    ],
    "name:hun_x_preferred":[
        "Corcovado-hegy"
    ],
    "name:ita_x_preferred":[
        "Corcovado"
    ],
    "name:jpn_x_preferred":[
        "\u30b3\u30eb\u30b3\u30d0\u30fc\u30c9"
    ],
    "name:kat_x_preferred":[
        "\u10d9\u10dd\u10e0\u10d9\u10dd\u10d5\u10d0\u10d3\u10dd"
    ],
    "name:lit_x_preferred":[
        "Korkovadas"
    ],
    "name:ltz_x_preferred":[
        "Corcovado"
    ],
    "name:nld_x_preferred":[
        "Corcovado"
    ],
    "name:nor_x_preferred":[
        "Corcovado"
    ],
    "name:pol_x_preferred":[
        "Corcovado"
    ],
    "name:por_x_preferred":[
        "Corcovado"
    ],
    "name:ron_x_preferred":[
        "Corcovado"
    ],
    "name:rus_x_preferred":[
        "\u041a\u043e\u0440\u043a\u043e\u0432\u0430\u0434\u0443"
    ],
    "name:srp_x_preferred":[
        "\u041a\u043e\u0440\u043a\u043e\u0432\u0430\u0434\u043e"
    ],
    "name:swe_x_preferred":[
        "Corcovado"
    ],
    "name:tur_x_preferred":[
        "Corcovado"
    ],
    "name:ukr_x_preferred":[
        "\u041a\u043e\u0440\u043a\u043e\u0432\u0430\u0434\u0443"
    ],
    "name:zho_x_preferred":[
        "\u9a7c\u80cc\u5c71"
    ],
    "wof:name":"Corcovado",
    "wof:placetype":"locality",
    "wof:population":87
},
  "geometry": {"coordinates":[-98.4725,20.58694],"type":"Point"}
}