{
  "type": "Feature",
  "properties": {
    "gn:admin1_code":"10.0",
    "gn:admin2_code":"35.0",
    "gn:asciiname":"Aguacaliente",
    "gn:country_code":"MX",
    "gn:dem":1966,
    "gn:feature_class":"P",
    "gn:feature_code":"PPL",
    "gn:name":"Aguacaliente",
    "gn:population":0,
    "gn:timezone":"America/Monterrey",
    "iso:country":"MX",
    "name:spa_x_preferred":[
        "Aguacaliente"
    ],
    "wof:name":"Aguacaliente",
    "wof:placetype":"locality"
},
  "geometry": {"coordinates":[-106.49484,25.64023],"type":"Point"}
}