{
  "type": "Feature",
  "properties": {
    "gn:admin1_code":"27",
    "gn:admin2_code":"10.0",
    "gn:asciiname":"Huapacal Primera Seccion",
    "gn:country_code":"MX",
    "gn:dem":14,
    "gn:feature_class":"P",
    "gn:feature_code":"PPL",
    "gn:name":"Huapacal Primera Secci\u00f3n",
    "gn:population":0,
    "gn:timezone":"America/Mexico_City",
    "iso:country":"MX",
    "name:spa_x_preferred":[
        "Huapacal Primera Secci\u00f3n"
    ],
    "wof:name":"Huapacal Primera Seccion",
    "wof:placetype":"locality"
},
  "geometry": {"coordinates":[-93.14122,18.20707],"type":"Point"}
}