{
  "type": "Feature",
  "properties": {
    "gn:admin1_code":"4",
    "gn:admin2_code":"2.0",
    "gn:asciiname":"Calaktoc",
    "gn:country_code":"MX",
    "gn:dem":45,
    "gn:feature_class":"P",
    "gn:feature_code":"PPL",
    "gn:name":"Calaktoc",
    "gn:population":0,
    "gn:timezone":"America/Merida",
    "iso:country":"MX",
    "name:spa_x_preferred":[
        "Calaktoc"
    ],
    "wof:name":"Calaktoc",
    "wof:placetype":"locality"
},
  "geometry": {"coordinates":[-90.53578,19.78682],"type":"Point"}
}