{
  "type": "Feature",
  "properties": {
    "gn:admin1_code":"14",
    "gn:admin2_code":"104.0",
    "gn:asciiname":"Sanguijuelas",
    "gn:country_code":"MX",
    "gn:dem":1761,
    "gn:feature_class":"P",
    "gn:feature_code":"PPL",
    "gn:name":"Sanguijuelas",
    "gn:population":7,
    "gn:timezone":"America/Mexico_City",
    "iso:country":"MX",
    "wof:name":"Sanguijuelas",
    "wof:placetype":"locality",
    "wof:population":7
},
  "geometry": {"coordinates":[-103.45056,21.93444],"type":"Point"}
}