{
  "type": "Feature",
  "properties": {
    "gn:admin1_code":"6.0",
    "gn:admin2_code":"7.0",
    "gn:asciiname":"Ejido Guazarachi",
    "gn:country_code":"MX",
    "gn:dem":2144,
    "gn:feature_class":"P",
    "gn:feature_code":"PPL",
    "gn:name":"Ejido Guaz\u00e1rachi",
    "gn:population":0,
    "gn:timezone":"America/Chihuahua",
    "iso:country":"MX",
    "name:spa_x_preferred":[
        "Ejido Guaz\u00e1rachi"
    ],
    "name:und_x_variant":[
        "Guasarachic",
        "Guaz\u00e1rachic"
    ],
    "wof:name":"Ejido Guazarachi",
    "wof:placetype":"locality"
},
  "geometry": {"coordinates":[-106.7114,26.98818],"type":"Point"}
}