{
  "type": "Feature",
  "properties": {
    "gn:admin1_code":"5",
    "gn:admin2_code":"81.0",
    "gn:asciiname":"El Ocotal",
    "gn:country_code":"MX",
    "gn:dem":1021,
    "gn:feature_class":"P",
    "gn:feature_code":"PPL",
    "gn:name":"El Ocotal",
    "gn:population":753,
    "gn:timezone":"America/Mexico_City",
    "iso:country":"MX",
    "wof:name":"El Ocotal",
    "wof:placetype":"locality",
    "wof:population":753
},
  "geometry": {"coordinates":[-92.75230999999999,17.20082],"type":"Point"}
}