{
  "type": "Feature",
  "properties": {
    "gn:admin1_code":"26.0",
    "gn:admin2_code":"11.0",
    "gn:asciiname":"El Pueblito",
    "gn:country_code":"MX",
    "gn:dem":1061,
    "gn:feature_class":"P",
    "gn:feature_code":"PPL",
    "gn:name":"El Pueblito",
    "gn:population":6,
    "gn:timezone":"America/Hermosillo",
    "iso:country":"MX",
    "name:ceb_x_preferred":[
        "El Pueblito"
    ],
    "name:deu_x_preferred":[
        "El Pueblito"
    ],
    "name:spa_x_preferred":[
        "El Pueblito"
    ],
    "name:srp_x_preferred":[
        "\u0415\u043b \u041f\u0443\u0435\u0431\u043b\u0438\u0442\u043e"
    ],
    "name:swe_x_preferred":[
        "El Pueblito"
    ],
    "wof:name":"El Pueblito",
    "wof:placetype":"locality",
    "wof:population":6
},
  "geometry": {"coordinates":[-109.99306,30.67278],"type":"Point"}
}