{
  "type": "Feature",
  "properties": {
    "gn:admin1_code":"15",
    "gn:admin2_code":"97",
    "gn:asciiname":"Agua del Trebol",
    "gn:country_code":"MX",
    "gn:dem":2961,
    "gn:feature_class":"P",
    "gn:feature_code":"PPL",
    "gn:name":"Agua del Tr\u00e9bol",
    "gn:population":25,
    "gn:timezone":"America/Mexico_City",
    "iso:country":"MX",
    "name:und_x_variant":[
        "Agua del Tr\u00e9bol"
    ],
    "wof:name":"Agua del Trebol",
    "wof:placetype":"locality",
    "wof:population":25
},
  "geometry": {"coordinates":[-99.97808999999999,18.92572],"type":"Point"}
}