{
  "type": "Feature",
  "properties": {
    "gn:admin1_code":"26",
    "gn:admin2_code":"48.0",
    "gn:asciiname":"Rancho Pozo Hielo Estrella",
    "gn:country_code":"MX",
    "gn:dem":69,
    "gn:feature_class":"P",
    "gn:feature_code":"PPL",
    "gn:name":"Rancho Pozo Hielo Estrella",
    "gn:population":0,
    "gn:timezone":"America/Hermosillo",
    "iso:country":"MX",
    "wof:name":"Rancho Pozo Hielo Estrella",
    "wof:placetype":"locality"
},
  "geometry": {"coordinates":[-113.40000000000001,31.53333],"type":"Point"}
}