{
  "type": "Feature",
  "properties": {
    "gn:gn_country":"MX",
    "gn:gn_fcode":"PPL",
    "gn:gn_pop":5993,
    "gn:population":5993,
    "iso:country":"MX",
    "name:unk_x_variant":[
        "Copalillo"
    ],
    "qs_pg:aaroncc":"MX",
    "qs_pg:gn_country":"MX",
    "qs_pg:gn_fcode":"PPL",
    "qs_pg:gn_pop":5993,
    "qs_pg:name":"Guerrero",
    "qs_pg:name_adm0":"M\u00e9xico",
    "qs_pg:name_adm1":"Guerrero",
    "qs_pg:photos_9r":0,
    "qs_pg:photos_sr":0,
    "qs_pg:pop_sr":5,
    "qs_pg:qs_pg_placetype":"neighbourhood",
    "qs_pg:qs_pg_placetype_gp":"Suburb",
    "qs_pg:woe_adm0":23424900,
    "woe:adm0_id":23424900,
    "woe:name_adm0":"M\u00e9xico",
    "woe:name_adm1":"Guerrero",
    "woe:placetype":"Suburb",
    "wof:name":"Guerrero",
    "wof:placetype":"neighbourhood",
    "wof:population":5993
},
  "geometry": {"coordinates":[-99.04058000000001,18.03537],"type":"Point"}
}