{
  "type": "Feature",
  "properties": {
    "gn:admin1_code":"14",
    "gn:admin2_code":"58.0",
    "gn:asciiname":"Los Tejabanes",
    "gn:country_code":"MX",
    "gn:dem":1242,
    "gn:feature_class":"P",
    "gn:feature_code":"PPL",
    "gn:name":"Los Tejabanes",
    "gn:population":5,
    "gn:timezone":"America/Mexico_City",
    "iso:country":"MX",
    "wof:name":"Los Tejabanes",
    "wof:placetype":"locality",
    "wof:population":5
},
  "geometry": {"coordinates":[-104.78222,20.53861],"type":"Point"}
}