{
  "type": "Feature",
  "properties": {
    "gn:admin1_code":"11",
    "gn:admin2_code":"19.0",
    "gn:asciiname":"La Loma (Las Tres Esquinas)",
    "gn:country_code":"MX",
    "gn:dem":2100,
    "gn:feature_class":"P",
    "gn:feature_code":"PPL",
    "gn:name":"La Loma (Las Tres Esquinas)",
    "gn:population":105,
    "gn:timezone":"America/Mexico_City",
    "iso:country":"MX",
    "wof:name":"La Loma (Las Tres Esquinas)",
    "wof:placetype":"locality",
    "wof:population":105
},
  "geometry": {"coordinates":[-100.50703,20.21706],"type":"Point"}
}