{
  "type": "Feature",
  "properties": {
    "gn:admin1_code":"5.0",
    "gn:admin2_code":"27.0",
    "gn:asciiname":"Nandabuita",
    "gn:country_code":"MX",
    "gn:dem":530,
    "gn:feature_class":"P",
    "gn:feature_code":"PPL",
    "gn:name":"Nandabuita",
    "gn:population":0,
    "gn:timezone":"America/Mexico_City",
    "iso:country":"MX",
    "name:spa_x_preferred":[
        "Nandabuita"
    ],
    "wof:name":"Nandabuita",
    "wof:placetype":"locality"
},
  "geometry": {"coordinates":[-92.96496,16.68291],"type":"Point"}
}