{
  "type": "Feature",
  "properties": {
    "gn:admin1_code":"20",
    "gn:admin2_code":"187.0",
    "gn:asciiname":"Loma de Hueso",
    "gn:country_code":"MX",
    "gn:dem":1683,
    "gn:feature_class":"P",
    "gn:feature_code":"PPL",
    "gn:name":"Loma de Hueso",
    "gn:population":53,
    "gn:timezone":"America/Mexico_City",
    "iso:country":"MX",
    "wof:name":"Loma de Hueso",
    "wof:placetype":"locality",
    "wof:population":53
},
  "geometry": {"coordinates":[-96.76833000000001,18.03861],"type":"Point"}
}