{
  "type": "Feature",
  "properties": {
    "gn:admin1_code":"10.0",
    "gn:admin2_code":"17.0",
    "gn:asciiname":"Las Aguilas",
    "gn:country_code":"MX",
    "gn:dem":1752,
    "gn:feature_class":"P",
    "gn:feature_code":"PPL",
    "gn:name":"Las Aguilas",
    "gn:population":0,
    "gn:timezone":"America/Chihuahua",
    "iso:country":"MX",
    "name:spa_x_preferred":[
        "Las Aguilas"
    ],
    "wof:name":"Las Aguilas",
    "wof:placetype":"locality"
},
  "geometry": {"coordinates":[-106.22202,26.63],"type":"Point"}
}