{
  "type": "Feature",
  "properties": {
    "gn:admin1_code":"7",
    "gn:admin2_code":"2.0",
    "gn:asciiname":"La Parrita",
    "gn:country_code":"MX",
    "gn:dem":468,
    "gn:feature_class":"P",
    "gn:feature_code":"PPL",
    "gn:name":"La Parrita",
    "gn:population":0,
    "gn:timezone":"America/Matamoros",
    "iso:country":"MX",
    "name:und_x_variant":[
        "Parrita"
    ],
    "wof:name":"La Parrita",
    "wof:placetype":"locality"
},
  "geometry": {"coordinates":[-101.77494,29.74081],"type":"Point"}
}