{
  "type": "Feature",
  "properties": {
    "gn:admin1_code":"20",
    "gn:admin2_code":"511.0",
    "gn:asciiname":"Canada de Chiquihuite",
    "gn:country_code":"MX",
    "gn:dem":2083,
    "gn:feature_class":"P",
    "gn:feature_code":"PPL",
    "gn:name":"Ca\u00f1ada de Chiquihuite",
    "gn:population":57,
    "gn:timezone":"America/Mexico_City",
    "iso:country":"MX",
    "name:und_x_variant":[
        "Ca\u00f1ada de Chiquihuite"
    ],
    "wof:name":"Canada de Chiquihuite",
    "wof:placetype":"locality",
    "wof:population":57
},
  "geometry": {"coordinates":[-97.04555999999999,17.11389],"type":"Point"}
}