{
  "type": "Feature",
  "properties": {
    "gn:admin1_code":"15",
    "gn:admin2_code":"18.0",
    "gn:asciiname":"Rancho Villa Verde",
    "gn:country_code":"MX",
    "gn:dem":2694,
    "gn:feature_class":"P",
    "gn:feature_code":"PPL",
    "gn:name":"Rancho Villa Verde",
    "gn:population":5,
    "gn:timezone":"America/Mexico_City",
    "iso:country":"MX",
    "wof:name":"Rancho Villa Verde",
    "wof:placetype":"locality",
    "wof:population":5
},
  "geometry": {"coordinates":[-99.61358,19.15022],"type":"Point"}
}