{
  "type": "Feature",
  "properties": {
    "gn:admin1_code":"19",
    "gn:admin2_code":"33.0",
    "gn:asciiname":"Magueiras",
    "gn:country_code":"MX",
    "gn:dem":317,
    "gn:feature_class":"P",
    "gn:feature_code":"PPL",
    "gn:name":"Mag\u00fciras",
    "gn:population":0,
    "gn:timezone":"America/Monterrey",
    "iso:country":"MX",
    "name:spa_x_preferred":[
        "Mag\u00fciras"
    ],
    "wof:name":"Magueiras",
    "wof:placetype":"locality"
},
  "geometry": {"coordinates":[-99.47837,24.73652],"type":"Point"}
}