{
  "type": "Feature",
  "properties": {
    "gn:admin1_code":"30",
    "gn:admin2_code":"49.0",
    "gn:asciiname":"Loma Bonita (La Chicharra)",
    "gn:country_code":"MX",
    "gn:dem":89,
    "gn:feature_class":"P",
    "gn:feature_code":"PPL",
    "gn:name":"Loma Bonita (La Chicharra)",
    "gn:population":123,
    "gn:timezone":"America/Mexico_City",
    "iso:country":"MX",
    "wof:name":"Loma Bonita (La Chicharra)",
    "wof:placetype":"locality",
    "wof:population":123
},
  "geometry": {"coordinates":[-96.41028,18.90333],"type":"Point"}
}