{
  "type": "Feature",
  "properties": {
    "gn:admin1_code":"14.0",
    "gn:asciiname":"Charcos de Catana",
    "gn:country_code":"MX",
    "gn:dem":1994,
    "gn:feature_class":"P",
    "gn:feature_code":"PPL",
    "gn:name":"Charcos de Catana",
    "gn:population":0,
    "gn:timezone":"America/Mexico_City",
    "iso:country":"MX",
    "name:spa_x_preferred":[
        "Charcos de Catana"
    ],
    "wof:name":"Charcos de Catana",
    "wof:placetype":"locality"
},
  "geometry": {"coordinates":[-102.17377999999999,20.80419],"type":"Point"}
}