{
  "type": "Feature",
  "properties": {
    "gn:admin1_code":"16",
    "gn:admin2_code":"100.0",
    "gn:asciiname":"El Jagueey (El Molino)",
    "gn:country_code":"MX",
    "gn:dem":2062,
    "gn:feature_class":"P",
    "gn:feature_code":"PPL",
    "gn:name":"El Jag\u00fcey (El Molino)",
    "gn:population":302,
    "gn:timezone":"America/Mexico_City",
    "iso:country":"MX",
    "name:und_x_variant":[
        "El Jag\u00fcey (El Molino)"
    ],
    "wof:name":"El Jagueey (El Molino)",
    "wof:placetype":"locality",
    "wof:population":302
},
  "geometry": {"coordinates":[-101.52194,19.5775],"type":"Point"}
}