{
  "type": "Feature",
  "properties": {
    "gn:admin1_code":"14.0",
    "gn:admin2_code":"6.0",
    "gn:asciiname":"Los Camichines",
    "gn:country_code":"MX",
    "gn:dem":1408,
    "gn:feature_class":"P",
    "gn:feature_code":"PPL",
    "gn:name":"Los Camichines",
    "gn:population":0,
    "gn:timezone":"America/Mexico_City",
    "iso:country":"MX",
    "name:spa_x_preferred":[
        "Los Camichines"
    ],
    "wof:name":"Los Camichines",
    "wof:placetype":"locality"
},
  "geometry": {"coordinates":[-104.13306,20.50369],"type":"Point"}
}