{
  "type": "Feature",
  "properties": {
    "gn:admin1_code":"12",
    "gn:admin2_code":"22.0",
    "gn:asciiname":"Manchon de Amuco (Llano de Guadalupe)",
    "gn:country_code":"MX",
    "gn:dem":265,
    "gn:feature_class":"P",
    "gn:feature_code":"PPL",
    "gn:name":"Manch\u00f3n de Amuco (Llano de Guadalupe)",
    "gn:population":107,
    "gn:timezone":"America/Mexico_City",
    "iso:country":"MX",
    "name:und_x_variant":[
        "Manch\u00f3n de Amuco (Llano de Guadalupe)"
    ],
    "wof:name":"Manchon de Amuco (Llano de Guadalupe)",
    "wof:placetype":"locality",
    "wof:population":107
},
  "geometry": {"coordinates":[-100.65389,18.29833],"type":"Point"}
}