{
  "type": "Feature",
  "properties": {
    "gn:admin1_code":"16.0",
    "gn:admin2_code":"81.0",
    "gn:asciiname":"Molino Viejo",
    "gn:country_code":"MX",
    "gn:dem":1434,
    "gn:feature_class":"P",
    "gn:feature_code":"PPL",
    "gn:name":"Molino Viejo",
    "gn:population":0,
    "gn:timezone":"America/Mexico_City",
    "iso:country":"MX",
    "name:spa_x_preferred":[
        "Molino Viejo"
    ],
    "wof:name":"Molino Viejo",
    "wof:placetype":"locality"
},
  "geometry": {"coordinates":[-100.39588000000001,19.18561],"type":"Point"}
}