{
  "type": "Feature",
  "properties": {
    "gn:admin1_code":"3",
    "gn:admin2_code":"1.0",
    "gn:asciiname":"Palo Estribo",
    "gn:country_code":"MX",
    "gn:dem":376,
    "gn:feature_class":"P",
    "gn:feature_code":"PPL",
    "gn:name":"Palo Estribo",
    "gn:population":0,
    "gn:timezone":"America/Mazatlan",
    "iso:country":"MX",
    "name:spa_x_preferred":[
        "Palo Estribo"
    ],
    "wof:name":"Palo Estribo",
    "wof:placetype":"locality"
},
  "geometry": {"coordinates":[-112.21652,26.45973],"type":"Point"}
}