{
  "type": "Feature",
  "properties": {
    "gn:admin1_code":"5",
    "gn:admin2_code":"46.0",
    "gn:asciiname":"Miguel Hidalgo",
    "gn:country_code":"MX",
    "gn:dem":545,
    "gn:feature_class":"P",
    "gn:feature_code":"PPL",
    "gn:name":"Miguel Hidalgo",
    "gn:population":658,
    "gn:timezone":"America/Mexico_City",
    "iso:country":"MX",
    "wof:name":"Miguel Hidalgo",
    "wof:placetype":"locality",
    "wof:population":658
},
  "geometry": {"coordinates":[-93.6575,16.56083],"type":"Point"}
}