{
  "type": "Feature",
  "properties": {
    "gn:admin1_code":"20",
    "gn:admin2_code":"171.0",
    "gn:asciiname":"Cerro Alto",
    "gn:country_code":"MX",
    "gn:dem":1094,
    "gn:feature_class":"P",
    "gn:feature_code":"PPL",
    "gn:name":"Cerro Alto",
    "gn:population":237,
    "gn:timezone":"America/Mexico_City",
    "iso:country":"MX",
    "name:ceb_x_preferred":[
        "Cerro Alto"
    ],
    "name:swe_x_preferred":[
        "Cerro Alto"
    ],
    "wof:name":"Cerro Alto",
    "wof:placetype":"locality",
    "wof:population":237
},
  "geometry": {"coordinates":[-96.63972,18.14833],"type":"Point"}
}