{
  "type": "Feature",
  "properties": {
    "gn:admin1_code":"6.0",
    "gn:admin2_code":"7.0",
    "gn:asciiname":"Guagueachi",
    "gn:country_code":"MX",
    "gn:dem":2293,
    "gn:feature_class":"P",
    "gn:feature_code":"PPL",
    "gn:name":"Guagueachi",
    "gn:population":0,
    "gn:timezone":"America/Chihuahua",
    "iso:country":"MX",
    "name:spa_x_preferred":[
        "Guagueachi"
    ],
    "name:und_x_variant":[
        "Rancho Guagueachic"
    ],
    "wof:name":"Guagueachi",
    "wof:placetype":"locality"
},
  "geometry": {"coordinates":[-106.7448,26.80444],"type":"Point"}
}