{
  "type": "Feature",
  "properties": {
    "gn:admin1_code":"10.0",
    "gn:asciiname":"Las Gueras",
    "gn:country_code":"MX",
    "gn:dem":1986,
    "gn:feature_class":"P",
    "gn:feature_code":"PPL",
    "gn:name":"Las G\u00fceras",
    "gn:population":0,
    "gn:timezone":"America/Monterrey",
    "iso:country":"MX",
    "name:spa_x_preferred":[
        "Las G\u00fceras"
    ],
    "wof:name":"Las Gueras",
    "wof:placetype":"locality"
},
  "geometry": {"coordinates":[-106.03331,24.41474],"type":"Point"}
}