{
  "type": "Feature",
  "properties": {
    "gn:admin1_code":"6.0",
    "gn:admin2_code":"1.0",
    "gn:asciiname":"El Cuatro",
    "gn:country_code":"MX",
    "gn:dem":1222,
    "gn:feature_class":"P",
    "gn:feature_code":"PPL",
    "gn:name":"El Cuatro",
    "gn:population":0,
    "gn:timezone":"America/Chihuahua",
    "iso:country":"MX",
    "name:spa_x_preferred":[
        "El Cuatro"
    ],
    "wof:name":"El Cuatro",
    "wof:placetype":"locality"
},
  "geometry": {"coordinates":[-106.35886000000001,30.7168],"type":"Point"}
}