{
  "type": "Feature",
  "properties": {
    "gn:admin1_code":"18",
    "gn:admin2_code":"17.0",
    "gn:asciiname":"Mesa de Picachos (El Casco)",
    "gn:country_code":"MX",
    "gn:dem":95,
    "gn:feature_class":"P",
    "gn:feature_code":"PPL",
    "gn:name":"Mesa de Picachos (El Casco)",
    "gn:population":221,
    "gn:timezone":"America/Mazatlan",
    "iso:country":"MX",
    "wof:name":"Mesa de Picachos (El Casco)",
    "wof:placetype":"locality",
    "wof:population":221
},
  "geometry": {"coordinates":[-104.85521,21.7726],"type":"Point"}
}