{
  "type": "Feature",
  "properties": {
    "gn:admin1_code":"21",
    "gn:admin2_code":"172.0",
    "gn:asciiname":"Tecuicuilco",
    "gn:country_code":"MX",
    "gn:dem":1571,
    "gn:feature_class":"P",
    "gn:feature_code":"PPL",
    "gn:name":"Tecuicuilco",
    "gn:population":0,
    "gn:timezone":"America/Mexico_City",
    "iso:country":"MX",
    "name:und_x_variant":[
        "Tequiquilco",
        "Tecuicuilco"
    ],
    "wof:name":"Tecuicuilco",
    "wof:placetype":"locality"
},
  "geometry": {"coordinates":[-97.65622,19.89549],"type":"Point"}
}