{
  "type": "Feature",
  "properties": {
    "gn:admin1_code":"13",
    "gn:admin2_code":"62.0",
    "gn:asciiname":"Aquilastec",
    "gn:country_code":"MX",
    "gn:dem":1076,
    "gn:feature_class":"P",
    "gn:feature_code":"PPL",
    "gn:name":"Aquilastec",
    "gn:population":0,
    "gn:timezone":"America/Mexico_City",
    "iso:country":"MX",
    "name:und_x_variant":[
        "Aquilastepec",
        "Aquilastec"
    ],
    "wof:name":"Aquilastec",
    "wof:placetype":"locality"
},
  "geometry": {"coordinates":[-98.75830999999999,21.01608],"type":"Point"}
}