{
  "type": "Feature",
  "properties": {
    "gn:admin1_code":"3",
    "gn:admin2_code":"8.0",
    "gn:asciiname":"Mesa Verde",
    "gn:country_code":"MX",
    "gn:dem":518,
    "gn:feature_class":"P",
    "gn:feature_code":"PPL",
    "gn:name":"Mesa Verde",
    "gn:population":4,
    "gn:timezone":"America/Mazatlan",
    "iso:country":"MX",
    "wof:name":"Mesa Verde",
    "wof:placetype":"locality",
    "wof:population":4
},
  "geometry": {"coordinates":[-109.95537,23.09972],"type":"Point"}
}