{
  "type": "Feature",
  "properties": {
    "gn:admin1_code":"23",
    "gn:asciiname":"X-Uilub",
    "gn:country_code":"MX",
    "gn:dem":22,
    "gn:feature_class":"P",
    "gn:feature_code":"PPL",
    "gn:name":"X-Uilub",
    "gn:population":0,
    "gn:timezone":"America/Cancun",
    "iso:country":"MX",
    "name:spa_x_preferred":[
        "X-Uilub"
    ],
    "name:spa_x_variant":[
        "Xuiluh"
    ],
    "wof:name":"X-Uilub",
    "wof:placetype":"locality"
},
  "geometry": {"coordinates":[-88.03022,20.4185],"type":"Point"}
}