{
  "type": "Feature",
  "properties": {
    "gn:admin1_code":"14",
    "gn:admin2_code":"8.0",
    "gn:asciiname":"Yerbabuena (Huizachal)",
    "gn:country_code":"MX",
    "gn:dem":1902,
    "gn:feature_class":"P",
    "gn:feature_code":"PPL",
    "gn:name":"Yerbabuena (Huizachal)",
    "gn:population":137,
    "gn:timezone":"America/Mexico_City",
    "iso:country":"MX",
    "wof:name":"Yerbabuena (Huizachal)",
    "wof:placetype":"locality",
    "wof:population":137
},
  "geometry": {"coordinates":[-102.15722,20.84278],"type":"Point"}
}