{
  "type": "Feature",
  "properties": {
    "gn:admin1_code":"28",
    "gn:admin2_code":"37",
    "gn:asciiname":"La Concepcion (La Florena)",
    "gn:country_code":"MX",
    "gn:dem":44,
    "gn:feature_class":"P",
    "gn:feature_code":"PPL",
    "gn:name":"La Concepci\u00f3n (La Flore\u00f1a)",
    "gn:population":15,
    "gn:timezone":"America/Monterrey",
    "iso:country":"MX",
    "name:und_x_variant":[
        "La Concepci\u00f3n (La Flore\u00f1a)"
    ],
    "wof:name":"La Concepcion (La Florena)",
    "wof:placetype":"locality",
    "wof:population":15
},
  "geometry": {"coordinates":[-97.83638999999999,23.44806],"type":"Point"}
}