{
  "type": "Feature",
  "properties": {
    "gn:admin1_code":"10",
    "gn:admin2_code":"36.0",
    "gn:asciiname":"Kilo Doce-Doce",
    "gn:country_code":"MX",
    "gn:dem":1122,
    "gn:feature_class":"P",
    "gn:feature_code":"PPL",
    "gn:name":"Kilo Doce-Doce",
    "gn:population":0,
    "gn:timezone":"America/Monterrey",
    "iso:country":"MX",
    "name:spa_x_preferred":[
        "Kilo Doce-Doce"
    ],
    "wof:name":"Kilo Doce-Doce",
    "wof:placetype":"locality"
},
  "geometry": {"coordinates":[-103.76784000000001,26.14526],"type":"Point"}
}