{
  "type": "Feature",
  "properties": {
    "gn:admin1_code":"17.0",
    "gn:asciiname":"Cruz de Lima",
    "gn:country_code":"MX",
    "gn:dem":1717,
    "gn:feature_class":"P",
    "gn:feature_code":"PPL",
    "gn:name":"Cruz de Lima",
    "gn:population":0,
    "gn:timezone":"America/Mexico_City",
    "iso:country":"MX",
    "name:spa_x_preferred":[
        "Cruz de Lima"
    ],
    "wof:name":"Cruz de Lima",
    "wof:placetype":"locality"
},
  "geometry": {"coordinates":[-98.81304,18.84472],"type":"Point"}
}