{
  "type": "Feature",
  "properties": {
    "gn:admin1_code":"24",
    "gn:admin2_code":"3",
    "gn:asciiname":"La Pena Blanca",
    "gn:country_code":"MX",
    "gn:dem":1042,
    "gn:feature_class":"P",
    "gn:feature_code":"PPL",
    "gn:name":"La Pe\u00f1a Blanca",
    "gn:population":34,
    "gn:timezone":"America/Mexico_City",
    "iso:country":"MX",
    "name:und_x_variant":[
        "La Pe\u00f1a Blanca"
    ],
    "wof:name":"La Pena Blanca",
    "wof:placetype":"locality",
    "wof:population":34
},
  "geometry": {"coordinates":[-99.11472000000001,21.53444],"type":"Point"}
}