{
  "type": "Feature",
  "properties": {
    "gn:admin1_code":"16",
    "gn:admin2_code":"93.0",
    "gn:asciiname":"El Jazmin",
    "gn:country_code":"MX",
    "gn:dem":2747,
    "gn:feature_class":"P",
    "gn:feature_code":"PPL",
    "gn:name":"El Jazm\u00edn",
    "gn:population":449,
    "gn:timezone":"America/Mexico_City",
    "iso:country":"MX",
    "name:und_x_variant":[
        "El Jazm\u00edn"
    ],
    "wof:name":"El Jazmin",
    "wof:placetype":"locality",
    "wof:population":449
},
  "geometry": {"coordinates":[-100.17944,19.73444],"type":"Point"}
}