{
  "type": "Feature",
  "properties": {
    "gn:admin1_code":"24",
    "gn:admin2_code":"41",
    "gn:asciiname":"Ampliacion Colonia las Brisas",
    "gn:country_code":"MX",
    "gn:dem":200,
    "gn:feature_class":"P",
    "gn:feature_code":"PPL",
    "gn:name":"Ampliaci\u00f3n Colonia las Brisas",
    "gn:population":17,
    "gn:timezone":"America/Mexico_City",
    "iso:country":"MX",
    "name:und_x_variant":[
        "Ampliaci\u00f3n Colonia las Brisas"
    ],
    "wof:name":"Ampliacion Colonia las Brisas",
    "wof:placetype":"locality",
    "wof:population":17
},
  "geometry": {"coordinates":[-98.89167,21.66778],"type":"Point"}
}