{
  "type": "Feature",
  "properties": {
    "gn:admin1_code":"20",
    "gn:admin2_code":"392.0",
    "gn:asciiname":"Yuyi",
    "gn:country_code":"MX",
    "gn:dem":2425,
    "gn:feature_class":"P",
    "gn:feature_code":"PPL",
    "gn:name":"Yuyi",
    "gn:population":0,
    "gn:timezone":"America/Mexico_City",
    "iso:country":"MX",
    "wof:name":"Yuyi",
    "wof:placetype":"locality"
},
  "geometry": {"coordinates":[-97.66667,16.96667],"type":"Point"}
}