{
  "type": "Feature",
  "properties": {
    "gn:admin1_code":"31",
    "gn:admin2_code":"96.0",
    "gn:asciiname":"La Lupita",
    "gn:country_code":"MX",
    "gn:dem":12,
    "gn:feature_class":"P",
    "gn:feature_code":"PPL",
    "gn:name":"La Lupita",
    "gn:population":0,
    "gn:timezone":"America/Merida",
    "iso:country":"MX",
    "name:spa_x_preferred":[
        "La Lupita"
    ],
    "wof:name":"La Lupita",
    "wof:placetype":"locality"
},
  "geometry": {"coordinates":[-87.77279,21.35605],"type":"Point"}
}