{
  "type": "Feature",
  "properties": {
    "gn:admin1_code":"14.0",
    "gn:admin2_code":"53.0",
    "gn:asciiname":"San Javier",
    "gn:country_code":"MX",
    "gn:dem":2014,
    "gn:feature_class":"P",
    "gn:feature_code":"PPL",
    "gn:name":"San Javier",
    "gn:population":0,
    "gn:timezone":"America/Mexico_City",
    "iso:country":"MX",
    "name:spa_x_preferred":[
        "San Javier"
    ],
    "wof:name":"San Javier",
    "wof:placetype":"locality"
},
  "geometry": {"coordinates":[-101.97384,21.77371],"type":"Point"}
}