{
  "type": "Feature",
  "properties": {
    "gn:admin1_code":"26",
    "gn:admin2_code":"22.0",
    "gn:asciiname":"El Ranchito",
    "gn:country_code":"MX",
    "gn:dem":833,
    "gn:feature_class":"P",
    "gn:feature_code":"PPL",
    "gn:name":"El Ranchito",
    "gn:population":0,
    "gn:timezone":"America/Hermosillo",
    "iso:country":"MX",
    "name:spa_x_preferred":[
        "El Ranchito"
    ],
    "wof:name":"El Ranchito",
    "wof:placetype":"locality"
},
  "geometry": {"coordinates":[-110.71348,30.28907],"type":"Point"}
}