{
  "type": "Feature",
  "properties": {
    "gn:admin1_code":"10.0",
    "gn:admin2_code":"5.0",
    "gn:asciiname":"La Parra",
    "gn:country_code":"MX",
    "gn:dem":1861,
    "gn:feature_class":"P",
    "gn:feature_code":"PPL",
    "gn:name":"La Parra",
    "gn:population":0,
    "gn:timezone":"America/Monterrey",
    "iso:country":"MX",
    "name:ara_x_preferred":[
        "\u0644\u0627 \u0628\u0627\u0631\u0627"
    ],
    "name:azb_x_preferred":[
        "\u0644\u0627 \u067e\u0627\u0631\u0627"
    ],
    "name:cat_x_preferred":[
        "La Parra"
    ],
    "name:ces_x_preferred":[
        "La Parra"
    ],
    "name:epo_x_preferred":[
        "La Parra"
    ],
    "name:eus_x_preferred":[
        "La Parra"
    ],
    "name:fas_x_preferred":[
        "\u0644\u0627 \u067e\u0627\u0631\u0627"
    ],
    "name:fra_x_preferred":[
        "La Parra"
    ],
    "name:hun_x_preferred":[
        "La Parra"
    ],
    "name:ina_x_preferred":[
        "La Parra"
    ],
    "name:ita_x_preferred":[
        "La Parra"
    ],
    "name:mkd_x_preferred":[
        "\u041b\u0430 \u041f\u0430\u0440\u0430"
    ],
    "name:msa_x_preferred":[
        "La Parra"
    ],
    "name:nld_x_preferred":[
        "La Parra"
    ],
    "name:oci_x_preferred":[
        "La Parra"
    ],
    "name:pol_x_preferred":[
        "La Parra"
    ],
    "name:por_x_preferred":[
        "La Parra"
    ],
    "name:ron_x_preferred":[
        "La Parra"
    ],
    "name:rus_x_preferred":[
        "\u041b\u0430-\u041f\u0430\u0440\u0440\u0430"
    ],
    "name:spa_x_preferred":[
        "La Parra"
    ],
    "name:ukr_x_preferred":[
        "\u041b\u0430-\u041f\u0430\u0440\u0440\u0430"
    ],
    "name:uzb_x_preferred":[
        "La Parra"
    ],
    "name:vie_x_preferred":[
        "La Parra"
    ],
    "name:war_x_preferred":[
        "La Parra"
    ],
    "name:zho_x_preferred":[
        "\u62c9\u5e15\u62c9"
    ],
    "wof:name":"La Parra",
    "wof:placetype":"locality"
},
  "geometry": {"coordinates":[-104.55692000000001,24.11269],"type":"Point"}
}