{
  "type": "Feature",
  "properties": {
    "gn:admin1_code":"12",
    "gn:admin2_code":"4",
    "gn:asciiname":"Colonia el Arenal",
    "gn:country_code":"MX",
    "gn:dem":2129,
    "gn:feature_class":"P",
    "gn:feature_code":"PPL",
    "gn:name":"Colonia el Arenal",
    "gn:population":23,
    "gn:timezone":"America/Mexico_City",
    "iso:country":"MX",
    "wof:name":"Colonia el Arenal",
    "wof:placetype":"locality",
    "wof:population":23
},
  "geometry": {"coordinates":[-98.34923000000001,17.32151],"type":"Point"}
}