{
  "type": "Feature",
  "properties": {
    "gn:admin1_code":"5",
    "gn:admin2_code":"107",
    "gn:asciiname":"Octavio Perez N.",
    "gn:country_code":"MX",
    "gn:dem":651,
    "gn:feature_class":"P",
    "gn:feature_code":"PPL",
    "gn:name":"Octavio P\u00e9rez N.",
    "gn:population":14,
    "gn:timezone":"America/Mexico_City",
    "iso:country":"MX",
    "name:und_x_variant":[
        "Octavio P\u00e9rez N."
    ],
    "wof:name":"Octavio Perez N.",
    "wof:placetype":"locality",
    "wof:population":14
},
  "geometry": {"coordinates":[-92.98166999999999,16.34222],"type":"Point"}
}