{
  "type": "Feature",
  "properties": {
    "gn:admin1_code":"12",
    "gn:admin2_code":"57.0",
    "gn:asciiname":"La Sierrita Bajos de Balzamar",
    "gn:country_code":"MX",
    "gn:dem":1844,
    "gn:feature_class":"P",
    "gn:feature_code":"PPL",
    "gn:name":"La Sierrita Bajos de Balzamar",
    "gn:population":172,
    "gn:timezone":"America/Mexico_City",
    "iso:country":"MX",
    "wof:name":"La Sierrita Bajos de Balzamar",
    "wof:placetype":"locality",
    "wof:population":172
},
  "geometry": {"coordinates":[-100.83674000000001,17.67114],"type":"Point"}
}