{
  "type": "Feature",
  "properties": {
    "gn:admin1_code":"1",
    "gn:admin2_code":"9.0",
    "gn:asciiname":"Puerto la Concepcion",
    "gn:country_code":"MX",
    "gn:dem":2305,
    "gn:feature_class":"P",
    "gn:feature_code":"PPL",
    "gn:name":"Puerto la Concepci\u00f3n",
    "gn:population":0,
    "gn:timezone":"America/Mexico_City",
    "iso:country":"MX",
    "name:und_x_variant":[
        "Puerto Concepci\u00f4n",
        "Puerto de la Concepci\u00f3n",
        "Puerto la Concepci\u00f3n"
    ],
    "wof:name":"Puerto la Concepcion",
    "wof:placetype":"locality"
},
  "geometry": {"coordinates":[-102.13562,22.20192],"type":"Point"}
}