{
  "type": "Feature",
  "properties": {
    "gn:admin1_code":"30",
    "gn:admin2_code":"80.0",
    "gn:asciiname":"Ejido los Naranjos",
    "gn:country_code":"MX",
    "gn:dem":993,
    "gn:feature_class":"P",
    "gn:feature_code":"PPL",
    "gn:name":"Ejido los Naranjos",
    "gn:population":528,
    "gn:timezone":"America/Mexico_City",
    "iso:country":"MX",
    "wof:name":"Ejido los Naranjos",
    "wof:placetype":"locality",
    "wof:population":528
},
  "geometry": {"coordinates":[-96.85805999999999,18.96694],"type":"Point"}
}