{
  "type": "Feature",
  "properties": {
    "gn:admin1_code":"24",
    "gn:admin2_code":"52.0",
    "gn:asciiname":"Mineral de Guaxcama",
    "gn:country_code":"MX",
    "gn:dem":1273,
    "gn:feature_class":"P",
    "gn:feature_code":"PPL",
    "gn:name":"Mineral de Guaxcama",
    "gn:population":0,
    "gn:timezone":"America/Mexico_City",
    "iso:country":"MX",
    "wof:name":"Mineral de Guaxcama",
    "wof:placetype":"locality"
},
  "geometry": {"coordinates":[-100.27928,22.18772],"type":"Point"}
}