{
  "type": "Feature",
  "properties": {
    "gn:admin1_code":"20.0",
    "gn:admin2_code":"407.0",
    "gn:asciiname":"Hermosillo",
    "gn:country_code":"MX",
    "gn:dem":618,
    "gn:feature_class":"P",
    "gn:feature_code":"PPL",
    "gn:name":"Hermosillo",
    "gn:population":0,
    "gn:timezone":"America/Mexico_City",
    "iso:country":"MX",
    "name:spa_x_preferred":[
        "Hermosillo"
    ],
    "wof:name":"Hermosillo",
    "wof:placetype":"locality"
},
  "geometry": {"coordinates":[-94.64516999999999,16.78446],"type":"Point"}
}