{
  "type": "Feature",
  "properties": {
    "gn:admin1_code":"13",
    "gn:admin2_code":"71.0",
    "gn:asciiname":"El Nenfi",
    "gn:country_code":"MX",
    "gn:dem":1824,
    "gn:feature_class":"P",
    "gn:feature_code":"PPL",
    "gn:name":"El Nenfi",
    "gn:population":6,
    "gn:timezone":"America/Mexico_City",
    "iso:country":"MX",
    "wof:name":"El Nenfi",
    "wof:placetype":"locality",
    "wof:population":6
},
  "geometry": {"coordinates":[-98.92769,20.88575],"type":"Point"}
}