{
  "type": "Feature",
  "properties": {
    "gn:admin1_code":"30.0",
    "gn:admin2_code":"151.0",
    "gn:asciiname":"El Aguacatal",
    "gn:country_code":"MX",
    "gn:dem":5,
    "gn:feature_class":"P",
    "gn:feature_code":"PPL",
    "gn:name":"El Aguacatal",
    "gn:population":0,
    "gn:timezone":"America/Mexico_City",
    "iso:country":"MX",
    "name:spa_x_preferred":[
        "El Aguacatal"
    ],
    "wof:name":"El Aguacatal",
    "wof:placetype":"locality"
},
  "geometry": {"coordinates":[-97.42628999999999,21.41749],"type":"Point"}
}