{
  "type": "Feature",
  "properties": {
    "gn:admin1_code":"32",
    "gn:admin2_code":"19",
    "gn:asciiname":"La Marchagua",
    "gn:country_code":"MX",
    "gn:dem":1401,
    "gn:feature_class":"P",
    "gn:feature_code":"PPL",
    "gn:name":"La Marchagua",
    "gn:population":12,
    "gn:timezone":"America/Mexico_City",
    "iso:country":"MX",
    "wof:name":"La Marchagua",
    "wof:placetype":"locality",
    "wof:population":12
},
  "geometry": {"coordinates":[-102.94389,21.67333],"type":"Point"}
}