{
  "type": "Feature",
  "properties": {
    "gn:admin1_code":"21",
    "gn:admin2_code":"50.0",
    "gn:asciiname":"San Jose de las Flores",
    "gn:country_code":"MX",
    "gn:dem":1278,
    "gn:feature_class":"P",
    "gn:feature_code":"PPL",
    "gn:name":"San Jos\u00e9 de las Flores",
    "gn:population":80,
    "gn:timezone":"America/Mexico_City",
    "iso:country":"MX",
    "name:und_x_variant":[
        "San Jos\u00e9 de las Flores"
    ],
    "wof:name":"San Jose de las Flores",
    "wof:placetype":"locality",
    "wof:population":80
},
  "geometry": {"coordinates":[-97.00506,19.25598],"type":"Point"}
}