{
  "type": "Feature",
  "properties": {
    "gn:admin1_code":"24.0",
    "gn:admin2_code":"28.0",
    "gn:asciiname":"El Penasco",
    "gn:country_code":"MX",
    "gn:dem":1829,
    "gn:feature_class":"P",
    "gn:feature_code":"PPL",
    "gn:name":"El Pe\u00f1asco",
    "gn:population":0,
    "gn:timezone":"America/Mexico_City",
    "iso:country":"MX",
    "name:und_x_variant":[
        "Pe\u00f1asco",
        "El Pe\u00f1asco"
    ],
    "wof:name":"El Penasco",
    "wof:placetype":"locality"
},
  "geometry": {"coordinates":[-100.95014,22.32534],"type":"Point"}
}