{
  "type": "Feature",
  "properties": {
    "gn:admin1_code":"5",
    "gn:admin2_code":"64.0",
    "gn:asciiname":"Ijk'Alajaw",
    "gn:country_code":"MX",
    "gn:dem":2027,
    "gn:feature_class":"P",
    "gn:feature_code":"PPL",
    "gn:name":"Ijk'Alajaw",
    "gn:population":171,
    "gn:timezone":"America/Mexico_City",
    "iso:country":"MX",
    "wof:name":"Ijk'Alajaw",
    "wof:placetype":"locality",
    "wof:population":171
},
  "geometry": {"coordinates":[-92.31108999999999,16.80062],"type":"Point"}
}