{
  "type": "Feature",
  "properties": {
    "gn:admin1_code":"13",
    "gn:admin2_code":"3.0",
    "gn:asciiname":"Corazon Chico",
    "gn:country_code":"MX",
    "gn:dem":2034,
    "gn:feature_class":"P",
    "gn:feature_code":"PPL",
    "gn:name":"Coraz\u00f3n Chico",
    "gn:population":0,
    "gn:timezone":"America/Mexico_City",
    "iso:country":"MX",
    "name:spa_x_preferred":[
        "Coraz\u00f3n Chico"
    ],
    "wof:name":"Corazon Chico",
    "wof:placetype":"locality"
},
  "geometry": {"coordinates":[-98.8249,20.37304],"type":"Point"}
}