{
  "type": "Feature",
  "properties": {
    "gn:admin1_code":"16",
    "gn:admin2_code":"57.0",
    "gn:asciiname":"Las Juntas",
    "gn:country_code":"MX",
    "gn:dem":726,
    "gn:feature_class":"P",
    "gn:feature_code":"PPL",
    "gn:name":"Las Juntas",
    "gn:population":0,
    "gn:timezone":"America/Mexico_City",
    "iso:country":"MX",
    "name:spa_x_preferred":[
        "Las Juntas"
    ],
    "wof:name":"Las Juntas",
    "wof:placetype":"locality"
},
  "geometry": {"coordinates":[-101.27614,19.07272],"type":"Point"}
}