{
  "type": "Feature",
  "properties": {
    "gn:admin1_code":"4.0",
    "gn:admin2_code":"3.0",
    "gn:asciiname":"El Pepito",
    "gn:country_code":"MX",
    "gn:dem":10,
    "gn:feature_class":"P",
    "gn:feature_code":"PPL",
    "gn:name":"El Pepito",
    "gn:population":0,
    "gn:timezone":"America/Merida",
    "iso:country":"MX",
    "name:spa_x_preferred":[
        "Pepito"
    ],
    "name:spa_x_variant":[
        "El Pepito"
    ],
    "wof:name":"El Pepito",
    "wof:placetype":"locality"
},
  "geometry": {"coordinates":[-91.41898999999999,18.15797],"type":"Point"}
}