{
  "type": "Feature",
  "properties": {
    "gn:admin1_code":"15",
    "gn:admin2_code":"14.0",
    "gn:asciiname":"Colonia Rio Lerma (Tic Ti)",
    "gn:country_code":"MX",
    "gn:dem":2546,
    "gn:feature_class":"P",
    "gn:feature_code":"PPL",
    "gn:name":"Colonia R\u00edo Lerma (Tic Ti)",
    "gn:population":2331,
    "gn:timezone":"America/Mexico_City",
    "iso:country":"MX",
    "name:und_x_variant":[
        "Colonia R\u00edo Lerma (Tic Ti)"
    ],
    "wof:name":"Colonia Rio Lerma (Tic Ti)",
    "wof:placetype":"locality",
    "wof:population":2331
},
  "geometry": {"coordinates":[-99.89722,19.80556],"type":"Point"}
}