{
  "type": "Feature",
  "properties": {
    "gn:admin1_code":"17",
    "gn:admin2_code":"26.0",
    "gn:asciiname":"Camino Real los Reyes",
    "gn:country_code":"MX",
    "gn:dem":1623,
    "gn:feature_class":"P",
    "gn:feature_code":"PPL",
    "gn:name":"Camino Real los Reyes",
    "gn:population":5,
    "gn:timezone":"America/Mexico_City",
    "iso:country":"MX",
    "wof:name":"Camino Real los Reyes",
    "wof:placetype":"locality",
    "wof:population":5
},
  "geometry": {"coordinates":[-98.96693999999999,18.94833],"type":"Point"}
}