{
  "type": "Feature",
  "properties": {
    "iso:country":"MX",
    "name:spa_x_preferred":[
        "Hugo Cervantes Del Rio"
    ],
    "name:unk_x_variant":[
        "Hugo Cervantes Del Rio"
    ],
    "qs:gn_adm0_cc":"MX",
    "qs:gn_local":3515431,
    "qs:gn_nam_loc":"Tlalnepantla de baz, Tlalnepantla de Comonfort, Mexico, MX",
    "qs:gn_namadm1":"15",
    "qs:local_max":248,
    "qs:local_sum":369,
    "qs:localhoods":6,
    "qs:name":"Hugo Cervantes Del Rio",
    "qs:name_adm0":"M\u00e9xico",
    "qs:name_adm1":"Mexico",
    "qs:name_adm2":"Tlalnepantla de Baz",
    "qs:name_local":"Tlalnepantla de Comonfort",
    "qs:photo_max":17,
    "qs:photo_sum":32,
    "qs:placetype":"Suburb",
    "qs:quad_count":3,
    "qs:woe_adm0":23424900,
    "qs:woe_adm1":2346278,
    "qs:woe_adm2":12600423,
    "qs:woe_lau":0,
    "qs:woe_local":149595,
    "qs:woe_ver":"7.10.0",
    "wof:lang":[
        "spa"
    ],
    "wof:name":"Hugo Cervantes Del Rio",
    "wof:placetype":"neighbourhood"
},
  "geometry": {"coordinates":[-99.172037,19.552025],"type":"Point"}
}