{
  "type": "Feature",
  "properties": {
    "gn:admin1_code":"12",
    "gn:admin2_code":"1.0",
    "gn:asciiname":"Colonia la Gloria",
    "gn:country_code":"MX",
    "gn:dem":29,
    "gn:feature_class":"P",
    "gn:feature_code":"PPL",
    "gn:name":"Colonia la Gloria",
    "gn:population":241,
    "gn:timezone":"America/Mexico_City",
    "iso:country":"MX",
    "wof:name":"Colonia la Gloria",
    "wof:placetype":"locality",
    "wof:population":241
},
  "geometry": {"coordinates":[-99.80361000000001,16.89944],"type":"Point"}
}