{
  "type": "Feature",
  "properties": {
    "gn:admin1_code":"4",
    "gn:admin2_code":"3.0",
    "gn:asciiname":"Orizaba",
    "gn:country_code":"MX",
    "gn:dem":2,
    "gn:feature_class":"P",
    "gn:feature_code":"PPL",
    "gn:name":"Orizaba",
    "gn:population":0,
    "gn:timezone":"America/Merida",
    "iso:country":"MX",
    "wof:name":"Orizaba",
    "wof:placetype":"locality"
},
  "geometry": {"coordinates":[-91.22861,18.96972],"type":"Point"}
}