{
  "type": "Feature",
  "properties": {
    "gn:admin1_code":"4",
    "gn:admin2_code":"3.0",
    "gn:asciiname":"Orizaba",
    "gn:country_code":"MX",
    "gn:dem":2,
    "gn:feature_class":"P",
    "gn:feature_code":"PPL",
    "gn:name":"Orizaba",
    "gn:population":0,
    "gn:timezone":"America/Merida",
    "iso:country":"MX",
    "name:ara_x_preferred":[
        "\u0627\u0648\u0631\u064a\u0632\u0627\u0628\u0627"
    ],
    "name:cat_x_preferred":[
        "Orizaba"
    ],
    "name:deu_x_preferred":[
        "Orizaba"
    ],
    "name:est_x_preferred":[
        "Orizaba"
    ],
    "name:fas_x_preferred":[
        "\u0627\u0648\u0631\u06cc\u0632\u0627\u0628\u0627"
    ],
    "name:fra_x_preferred":[
        "Orizaba"
    ],
    "name:hun_x_preferred":[
        "Orizaba"
    ],
    "name:ita_x_preferred":[
        "Orizaba"
    ],
    "name:lad_x_preferred":[
        "Orizaba"
    ],
    "name:lit_x_preferred":[
        "Orisaba"
    ],
    "name:nld_x_preferred":[
        "Orizaba"
    ],
    "name:nor_x_preferred":[
        "Orizaba"
    ],
    "name:pol_x_preferred":[
        "Orizaba"
    ],
    "name:por_x_preferred":[
        "Orizaba"
    ],
    "name:rus_x_preferred":[
        "\u041e\u0440\u0438\u0441\u0430\u0431\u0430"
    ],
    "name:spa_x_preferred":[
        "Orizaba"
    ],
    "name:srp_x_preferred":[
        "\u041e\u0440\u0438\u0437\u0430\u0431\u0430"
    ],
    "name:swe_x_preferred":[
        "Orizaba"
    ],
    "name:urd_x_preferred":[
        "\u0627\u0648\u0631\u06cc\u0633\u0627\u0628\u0627"
    ],
    "name:vie_x_preferred":[
        "Orizaba"
    ],
    "name:war_x_preferred":[
        "Orizaba"
    ],
    "name:zho_x_preferred":[
        "\u5967\u91cc\u85a9\u5df4"
    ],
    "wof:name":"Orizaba",
    "wof:placetype":"locality"
},
  "geometry": {"coordinates":[-91.22861,18.96972],"type":"Point"}
}