{
  "type": "Feature",
  "properties": {
    "gn:admin1_code":"12.0",
    "gn:admin2_code":"48.0",
    "gn:asciiname":"La Calavera",
    "gn:country_code":"MX",
    "gn:dem":767,
    "gn:feature_class":"P",
    "gn:feature_code":"PPL",
    "gn:name":"La Calavera",
    "gn:population":0,
    "gn:timezone":"America/Mexico_City",
    "iso:country":"MX",
    "name:spa_x_preferred":[
        "La Calavera"
    ],
    "wof:name":"La Calavera",
    "wof:placetype":"locality"
},
  "geometry": {"coordinates":[-101.21541000000001,17.64557000000001],"type":"Point"}
}