{
  "type": "Feature",
  "properties": {
    "gn:admin1_code":"28",
    "gn:admin2_code":"21.0",
    "gn:asciiname":"El Indio",
    "gn:country_code":"MX",
    "gn:dem":90,
    "gn:feature_class":"P",
    "gn:feature_code":"PPL",
    "gn:name":"El Indio",
    "gn:population":5,
    "gn:timezone":"America/Monterrey",
    "iso:country":"MX",
    "name:ceb_x_preferred":[
        "El Indio"
    ],
    "name:ita_x_preferred":[
        "El Indio"
    ],
    "name:srp_x_preferred":[
        "\u0415\u043b \u0418\u043d\u0434\u0438\u043e"
    ],
    "name:swe_x_preferred":[
        "El Indio"
    ],
    "wof:name":"El Indio",
    "wof:placetype":"locality",
    "wof:population":5
},
  "geometry": {"coordinates":[-99.04389,22.70056],"type":"Point"}
}