{
  "type": "Feature",
  "properties": {
    "gn:admin1_code":"14",
    "gn:admin2_code":"77.0",
    "gn:asciiname":"Salitre",
    "gn:country_code":"MX",
    "gn:dem":1260,
    "gn:feature_class":"P",
    "gn:feature_code":"PPL",
    "gn:name":"Salitre",
    "gn:population":0,
    "gn:timezone":"America/Mexico_City",
    "iso:country":"MX",
    "name:ceb_x_preferred":[
        "Salitre"
    ],
    "name:por_x_preferred":[
        "Salitre"
    ],
    "name:srp_x_preferred":[
        "\u0421\u0430\u043b\u0438\u0442\u0440\u0435"
    ],
    "name:swe_x_preferred":[
        "Salitre"
    ],
    "wof:name":"Salitre",
    "wof:placetype":"locality"
},
  "geometry": {"coordinates":[-103.85736,20.51048],"type":"Point"}
}