{
  "type": "Feature",
  "properties": {
    "gn:admin1_code":"10",
    "gn:admin2_code":"4.0",
    "gn:asciiname":"San Jose Berros",
    "gn:country_code":"MX",
    "gn:dem":1993,
    "gn:feature_class":"P",
    "gn:feature_code":"PPL",
    "gn:name":"San Jos\u00e9 Berros",
    "gn:population":0,
    "gn:timezone":"America/Monterrey",
    "iso:country":"MX",
    "name:spa_x_preferred":[
        "San Francissco de Berros"
    ],
    "name:spa_x_variant":[
        "San Jos\u00e9 Berros"
    ],
    "name:und_x_variant":[
        "Rancho San Francisco De Berros"
    ],
    "wof:name":"San Jose Berros",
    "wof:placetype":"locality"
},
  "geometry": {"coordinates":[-103.61601,24.55159],"type":"Point"}
}