{
  "type": "Feature",
  "properties": {
    "gn:admin1_code":"25.0",
    "gn:admin2_code":"7.0",
    "gn:asciiname":"Japaraqui",
    "gn:cc2":"MX",
    "gn:country_code":"MX",
    "gn:dem":126,
    "gn:feature_class":"P",
    "gn:feature_code":"PPL",
    "gn:name":"Japaraqui",
    "gn:population":0,
    "gn:timezone":"America/Mazatlan",
    "iso:country":"MX",
    "name:und_x_variant":[
        "Saparahui",
        "Japaraqui"
    ],
    "wof:name":"Japaraqui",
    "wof:placetype":"locality"
},
  "geometry": {"coordinates":[-108.53333000000001,26.58333],"type":"Point"}
}