{
  "type": "Feature",
  "properties": {
    "gn:admin1_code":"5",
    "gn:admin2_code":"93.0",
    "gn:asciiname":"El Corralito",
    "gn:country_code":"MX",
    "gn:dem":2189,
    "gn:feature_class":"P",
    "gn:feature_code":"PPL",
    "gn:name":"El Corralito",
    "gn:population":237,
    "gn:timezone":"America/Mexico_City",
    "iso:country":"MX",
    "wof:name":"El Corralito",
    "wof:placetype":"locality",
    "wof:population":237
},
  "geometry": {"coordinates":[-92.51701,16.80159],"type":"Point"}
}