{
  "type": "Feature",
  "properties": {
    "gn:admin1_code":"5.0",
    "gn:admin2_code":"80.0",
    "gn:asciiname":"Chiishel",
    "gn:country_code":"MX",
    "gn:dem":1484,
    "gn:feature_class":"P",
    "gn:feature_code":"PPL",
    "gn:name":"Chiishel",
    "gn:population":0,
    "gn:timezone":"America/Mexico_City",
    "iso:country":"MX",
    "name:spa_x_preferred":[
        "Chiishel"
    ],
    "wof:name":"Chiishel",
    "wof:placetype":"locality"
},
  "geometry": {"coordinates":[-92.44315,15.56599],"type":"Point"}
}