{
  "type": "Feature",
  "properties": {
    "gn:admin1_code":"2",
    "gn:admin2_code":"2",
    "gn:asciiname":"Familia Martinez (Colonia Polvora)",
    "gn:country_code":"MX",
    "gn:dem":9,
    "gn:feature_class":"P",
    "gn:feature_code":"PPL",
    "gn:name":"Familia Mart\u00ednez (Colonia P\u00f3lvora)",
    "gn:population":12,
    "gn:timezone":"America/Tijuana",
    "iso:country":"MX",
    "name:und_x_variant":[
        "Familia Mart\u00ednez (Colonia P\u00f3lvora)"
    ],
    "wof:name":"Familia Martinez (Colonia Polvora)",
    "wof:placetype":"locality",
    "wof:population":12
},
  "geometry": {"coordinates":[-115.20332999999999,32.50667],"type":"Point"}
}