{
  "type": "Feature",
  "properties": {
    "gn:admin1_code":"10.0",
    "gn:admin2_code":"8.0",
    "gn:asciiname":"Felipe Carrillo Puerto",
    "gn:country_code":"MX",
    "gn:dem":2049,
    "gn:feature_class":"P",
    "gn:feature_code":"PPL",
    "gn:name":"Felipe Carrillo Puerto",
    "gn:population":0,
    "gn:timezone":"America/Monterrey",
    "iso:country":"MX",
    "name:deu_x_preferred":[
        "Felipe Carrillo"
    ],
    "name:fra_x_preferred":[
        "Felipe Carrillo Puerto"
    ],
    "name:nld_x_preferred":[
        "Felipe Carrillo Puerto"
    ],
    "name:spa_x_preferred":[
        "Tarabillas"
    ],
    "name:spa_x_variant":[
        "Felipe Carrillo Puerto"
    ],
    "name:und_x_variant":[
        "Taravillas",
        "San Juan de Taravillas",
        "Carillo Puerto",
        "Felipe Carrillo Puerto"
    ],
    "wof:name":"Felipe Carrillo Puerto",
    "wof:placetype":"locality"
},
  "geometry": {"coordinates":[-104.01105,24.33305],"type":"Point"}
}