{
  "type": "Feature",
  "properties": {
    "gn:admin1_code":"30",
    "gn:admin2_code":"154.0",
    "gn:asciiname":"San Alfonso",
    "gn:country_code":"MX",
    "gn:dem":40,
    "gn:feature_class":"P",
    "gn:feature_code":"PPL",
    "gn:name":"San Alfonso",
    "gn:population":0,
    "gn:timezone":"America/Mexico_City",
    "iso:country":"MX",
    "wof:name":"San Alfonso",
    "wof:placetype":"locality"
},
  "geometry": {"coordinates":[-97.87273999999999,21.43692],"type":"Point"}
}