{
  "type": "Feature",
  "properties": {
    "gn:admin1_code":"27",
    "gn:admin2_code":"3.0",
    "gn:asciiname":"La Trinidad",
    "gn:cc2":"MX",
    "gn:country_code":"MX",
    "gn:dem":0,
    "gn:feature_class":"P",
    "gn:feature_code":"PPL",
    "gn:name":"La Trinidad",
    "gn:population":0,
    "gn:timezone":"America/Mexico_City",
    "iso:country":"MX",
    "name:und_x_variant":[
        "Trinidad",
        "La Trinidad"
    ],
    "wof:name":"La Trinidad",
    "wof:placetype":"locality"
},
  "geometry": {"coordinates":[-92.66667,18.36667000000001],"type":"Point"}
}