{
  "type": "Feature",
  "properties": {
    "gn:admin1_code":"30",
    "gn:admin2_code":"128.0",
    "gn:asciiname":"Fuerte de Perote",
    "gn:country_code":"MX",
    "gn:dem":2536,
    "gn:feature_class":"P",
    "gn:feature_code":"PPL",
    "gn:name":"Fuerte de Perote",
    "gn:population":0,
    "gn:timezone":"America/Mexico_City",
    "iso:country":"MX",
    "wof:name":"Fuerte de Perote",
    "wof:placetype":"locality"
},
  "geometry": {"coordinates":[-97.21666999999999,19.56667],"type":"Point"}
}