{
  "type": "Feature",
  "properties": {
    "gn:admin1_code":"11",
    "gn:admin2_code":"12",
    "gn:asciiname":"Colonia Nuevo Michoacan",
    "gn:country_code":"MX",
    "gn:dem":1712,
    "gn:feature_class":"P",
    "gn:feature_code":"PPL",
    "gn:name":"Colonia Nuevo Michoac\u00e1n",
    "gn:population":26,
    "gn:timezone":"America/Mexico_City",
    "iso:country":"MX",
    "name:und_x_variant":[
        "Colonia Nuevo Michoac\u00e1n"
    ],
    "wof:name":"Colonia Nuevo Michoacan",
    "wof:placetype":"locality",
    "wof:population":26
},
  "geometry": {"coordinates":[-101.65582999999999,20.61306],"type":"Point"}
}