{
  "type": "Feature",
  "properties": {
    "gn:admin1_code":"20",
    "gn:admin2_code":"236",
    "gn:asciiname":"El Manzanal",
    "gn:country_code":"MX",
    "gn:dem":2446,
    "gn:feature_class":"P",
    "gn:feature_code":"PPL",
    "gn:name":"El Manzanal",
    "gn:population":24,
    "gn:timezone":"America/Mexico_City",
    "iso:country":"MX",
    "wof:name":"El Manzanal",
    "wof:placetype":"locality",
    "wof:population":24
},
  "geometry": {"coordinates":[-96.39167,16.09139],"type":"Point"}
}