{
  "type": "Feature",
  "properties": {
    "gn:admin1_code":"12",
    "gn:admin2_code":"63.0",
    "gn:asciiname":"Tlacotepec",
    "gn:country_code":"MX",
    "gn:dem":2056,
    "gn:feature_class":"P",
    "gn:feature_code":"PPL",
    "gn:name":"Tlacotepec",
    "gn:population":388,
    "gn:timezone":"America/Mexico_City",
    "iso:country":"MX",
    "name:ita_x_preferred":[
        "Tlacotepec"
    ],
    "name:sco_x_preferred":[
        "Tlacotepec"
    ],
    "name:spa_x_preferred":[
        "Tlacotepec"
    ],
    "name:srp_x_preferred":[
        "\u0422\u043b\u0430\u043a\u043e\u0442\u0435\u043f\u0435\u043a"
    ],
    "wof:name":"Tlacotepec",
    "wof:placetype":"locality",
    "wof:population":388
},
  "geometry": {"coordinates":[-98.76555999999999,17.24722],"type":"Point"}
}