{
  "type": "Feature",
  "properties": {
    "gn:admin1_code":"12",
    "gn:admin2_code":"63.0",
    "gn:asciiname":"Tlacotepec",
    "gn:country_code":"MX",
    "gn:dem":2056,
    "gn:feature_class":"P",
    "gn:feature_code":"PPL",
    "gn:name":"Tlacotepec",
    "gn:population":388,
    "gn:timezone":"America/Mexico_City",
    "iso:country":"MX",
    "wof:name":"Tlacotepec",
    "wof:placetype":"locality",
    "wof:population":388
},
  "geometry": {"coordinates":[-98.76555999999999,17.24722],"type":"Point"}
}