{
  "type": "Feature",
  "properties": {
    "gn:admin1_code":"32",
    "gn:admin2_code":"10.0",
    "gn:asciiname":"Santa Elena",
    "gn:country_code":"MX",
    "gn:dem":2067,
    "gn:feature_class":"P",
    "gn:feature_code":"PPL",
    "gn:name":"Santa Elena",
    "gn:population":0,
    "gn:timezone":"America/Mexico_City",
    "iso:country":"MX",
    "name:spa_x_preferred":[
        "Santa Elena"
    ],
    "wof:name":"Santa Elena",
    "wof:placetype":"locality"
},
  "geometry": {"coordinates":[-102.70390999999999,23.27139],"type":"Point"}
}