{
  "type": "Feature",
  "properties": {
    "gn:admin1_code":"5.0",
    "gn:asciiname":"Cielito Lindo",
    "gn:country_code":"MX",
    "gn:dem":131,
    "gn:feature_class":"P",
    "gn:feature_code":"PPL",
    "gn:name":"Cielito Lindo",
    "gn:population":0,
    "gn:timezone":"America/Mexico_City",
    "iso:country":"MX",
    "name:spa_x_preferred":[
        "Cielito Lindo"
    ],
    "wof:name":"Cielito Lindo",
    "wof:placetype":"locality"
},
  "geometry": {"coordinates":[-93.24559000000001,15.75562],"type":"Point"}
}