{
  "type": "Feature",
  "properties": {
    "gn:admin1_code":"5.0",
    "gn:asciiname":"Cielito Lindo",
    "gn:country_code":"MX",
    "gn:dem":131,
    "gn:feature_class":"P",
    "gn:feature_code":"PPL",
    "gn:name":"Cielito Lindo",
    "gn:population":0,
    "gn:timezone":"America/Mexico_City",
    "iso:country":"MX",
    "name:bre_x_preferred":[
        "Cielito lindo"
    ],
    "name:deu_x_preferred":[
        "Cielito lindo"
    ],
    "name:fra_x_preferred":[
        "Cielito lindo"
    ],
    "name:hun_x_preferred":[
        "Cielito lindo"
    ],
    "name:ita_x_preferred":[
        "Cielito lindo"
    ],
    "name:jpn_x_preferred":[
        "\u30b7\u30a8\u30ea\u30c8\u30fb\u30ea\u30f3\u30c9"
    ],
    "name:nor_x_preferred":[
        "Cielito Lindo"
    ],
    "name:pol_x_preferred":[
        "Cielito Lindo"
    ],
    "name:por_x_preferred":[
        "Cielito Lindo"
    ],
    "name:rus_x_preferred":[
        "\u0421\u044c\u0435\u043b\u0438\u0442\u043e \u043b\u0438\u043d\u0434\u043e"
    ],
    "name:spa_x_preferred":[
        "Cielito Lindo"
    ],
    "name:spa_x_variant":[
        "Cielito lindo"
    ],
    "wof:name":"Cielito Lindo",
    "wof:placetype":"locality"
},
  "geometry": {"coordinates":[-93.24559000000001,15.75562],"type":"Point"}
}