{
  "type": "Feature",
  "properties": {
    "gn:admin1_code":"30",
    "gn:admin2_code":"9.0",
    "gn:asciiname":"Consolacion",
    "gn:country_code":"MX",
    "gn:dem":1014,
    "gn:feature_class":"P",
    "gn:feature_code":"PPL",
    "gn:name":"Consolaci\u00f3n",
    "gn:population":0,
    "gn:timezone":"America/Mexico_City",
    "iso:country":"MX",
    "wof:name":"Consolacion",
    "wof:placetype":"locality"
},
  "geometry": {"coordinates":[-96.66667,19.65],"type":"Point"}
}