{
  "type": "Feature",
  "properties": {
    "gn:admin1_code":"30",
    "gn:admin2_code":"43",
    "gn:asciiname":"El Ciruelo",
    "gn:country_code":"MX",
    "gn:dem":466,
    "gn:feature_class":"P",
    "gn:feature_code":"PPL",
    "gn:name":"El Ciruelo",
    "gn:population":15,
    "gn:timezone":"America/Mexico_City",
    "iso:country":"MX",
    "wof:name":"El Ciruelo",
    "wof:placetype":"locality",
    "wof:population":15
},
  "geometry": {"coordinates":[-96.66110999999999,19.11611],"type":"Point"}
}