{
  "type": "Feature",
  "properties": {
    "gn:admin1_code":"30",
    "gn:admin2_code":"155.0",
    "gn:asciiname":"Tortugas",
    "gn:country_code":"MX",
    "gn:dem":101,
    "gn:feature_class":"P",
    "gn:feature_code":"PPL",
    "gn:name":"Tortugas",
    "gn:population":43,
    "gn:timezone":"America/Mexico_City",
    "iso:country":"MX",
    "name:spa_x_preferred":[
        "Tortugas"
    ],
    "wof:name":"Tortugas",
    "wof:placetype":"locality",
    "wof:population":43
},
  "geometry": {"coordinates":[-98.11498,21.44792],"type":"Point"}
}