{
  "type": "Feature",
  "properties": {
    "gn:admin1_code":"14",
    "gn:admin2_code":"61",
    "gn:asciiname":"La Mesa (Mesa Alta)",
    "gn:country_code":"MX",
    "gn:dem":1817,
    "gn:feature_class":"P",
    "gn:feature_code":"PPL",
    "gn:name":"La Mesa (Mesa Alta)",
    "gn:population":20,
    "gn:timezone":"America/Mexico_City",
    "iso:country":"MX",
    "wof:name":"La Mesa (Mesa Alta)",
    "wof:placetype":"locality",
    "wof:population":20
},
  "geometry": {"coordinates":[-104.22,22.07028],"type":"Point"}
}