{
  "type": "Feature",
  "properties": {
    "gn:admin1_code":"5",
    "gn:admin2_code":"51.0",
    "gn:asciiname":"Maria Esther Gutierrez E.",
    "gn:country_code":"MX",
    "gn:dem":23,
    "gn:feature_class":"P",
    "gn:feature_code":"PPL",
    "gn:name":"Mar\u00eda Esther Guti\u00e9rrez E.",
    "gn:population":8,
    "gn:timezone":"America/Mexico_City",
    "iso:country":"MX",
    "name:und_x_variant":[
        "Mar\u00eda Esther Guti\u00e9rrez E."
    ],
    "wof:name":"Maria Esther Gutierrez E.",
    "wof:placetype":"locality",
    "wof:population":8
},
  "geometry": {"coordinates":[-92.83417,15.37333],"type":"Point"}
}