{
  "type": "Feature",
  "properties": {
    "gn:admin1_code":"10",
    "gn:admin2_code":"23",
    "gn:asciiname":"Piedra Encajada",
    "gn:country_code":"MX",
    "gn:dem":1553,
    "gn:feature_class":"P",
    "gn:feature_code":"PPL",
    "gn:name":"Piedra Encajada",
    "gn:population":15,
    "gn:timezone":"America/Monterrey",
    "iso:country":"MX",
    "wof:name":"Piedra Encajada",
    "wof:placetype":"locality",
    "wof:population":15
},
  "geometry": {"coordinates":[-105.11681000000002,23.11366],"type":"Point"}
}