{
  "type": "Feature",
  "properties": {
    "gn:admin1_code":"12",
    "gn:admin2_code":"22",
    "gn:asciiname":"La Canita",
    "gn:country_code":"MX",
    "gn:dem":431,
    "gn:feature_class":"P",
    "gn:feature_code":"PPL",
    "gn:name":"La Ca\u00f1ita",
    "gn:population":27,
    "gn:timezone":"America/Mexico_City",
    "iso:country":"MX",
    "name:und_x_variant":[
        "La Ca\u00f1ita"
    ],
    "wof:name":"La Canita",
    "wof:placetype":"locality",
    "wof:population":27
},
  "geometry": {"coordinates":[-100.88666000000001,18.1662],"type":"Point"}
}