{
  "type": "Feature",
  "properties": {
    "gn:admin1_code":"16",
    "gn:admin2_code":"101",
    "gn:asciiname":"Agua Zarca Uno",
    "gn:country_code":"MX",
    "gn:dem":847,
    "gn:feature_class":"P",
    "gn:feature_code":"PPL",
    "gn:name":"Agua Zarca Uno",
    "gn:population":31,
    "gn:timezone":"America/Mexico_City",
    "iso:country":"MX",
    "wof:name":"Agua Zarca Uno",
    "wof:placetype":"locality",
    "wof:population":31
},
  "geometry": {"coordinates":[-100.81444,19.3325],"type":"Point"}
}