{
  "type": "Feature",
  "properties": {
    "gn:admin1_code":"28",
    "gn:admin2_code":"22.0",
    "gn:asciiname":"Paso del Aguila",
    "gn:country_code":"MX",
    "gn:dem":12,
    "gn:feature_class":"P",
    "gn:feature_code":"PPL",
    "gn:name":"Paso del \u00c1guila",
    "gn:population":7,
    "gn:timezone":"America/Matamoros",
    "iso:country":"MX",
    "wof:name":"Paso del Aguila",
    "wof:placetype":"locality",
    "wof:population":7
},
  "geometry": {"coordinates":[-97.60126,25.6649],"type":"Point"}
}