{
  "type": "Feature",
  "properties": {
    "gn:admin1_code":"4",
    "gn:admin2_code":"2.0",
    "gn:asciiname":"La Adelita",
    "gn:country_code":"MX",
    "gn:dem":31,
    "gn:feature_class":"P",
    "gn:feature_code":"PPL",
    "gn:name":"La Adelita",
    "gn:population":0,
    "gn:timezone":"America/Merida",
    "iso:country":"MX",
    "name:spa_x_preferred":[
        "La Adelita"
    ],
    "wof:name":"La Adelita",
    "wof:placetype":"locality"
},
  "geometry": {"coordinates":[-90.51385999999999,19.65663],"type":"Point"}
}