{
  "type": "Feature",
  "properties": {
    "gn:admin1_code":"16.0",
    "gn:admin2_code":"102.0",
    "gn:asciiname":"Los Angeles",
    "gn:country_code":"MX",
    "gn:dem":2351,
    "gn:feature_class":"P",
    "gn:feature_code":"PPL",
    "gn:name":"Los Angeles",
    "gn:population":0,
    "gn:timezone":"America/Mexico_City",
    "iso:country":"MX",
    "name:spa_x_preferred":[
        "Los Angeles"
    ],
    "wof:name":"Los Angeles",
    "wof:placetype":"locality"
},
  "geometry": {"coordinates":[-102.17579000000001,19.51887],"type":"Point"}
}