{
  "type": "Feature",
  "properties": {
    "gn:admin1_code":"14.0",
    "gn:admin2_code":"33.0",
    "gn:asciiname":"Huascato",
    "gn:country_code":"MX",
    "gn:dem":1617,
    "gn:feature_class":"P",
    "gn:feature_code":"PPL",
    "gn:name":"Hu\u00e1scato",
    "gn:population":0,
    "gn:timezone":"America/Mexico_City",
    "iso:country":"MX",
    "name:spa_x_preferred":[
        "Hu\u00e1scato"
    ],
    "name:spa_x_variant":[
        "Huascato"
    ],
    "wof:name":"Huascato",
    "wof:placetype":"locality"
},
  "geometry": {"coordinates":[-102.24806,20.47951],"type":"Point"}
}