{
  "type": "Feature",
  "properties": {
    "gn:admin1_code":"5",
    "gn:admin2_code":"17.0",
    "gn:asciiname":"La Argentina",
    "gn:country_code":"MX",
    "gn:dem":732,
    "gn:feature_class":"P",
    "gn:feature_code":"PPL",
    "gn:name":"La Argentina",
    "gn:population":4,
    "gn:timezone":"America/Mexico_City",
    "iso:country":"MX",
    "name:ceb_x_preferred":[
        "La Argentina"
    ],
    "name:deu_x_preferred":[
        "La Argentina"
    ],
    "name:fra_x_preferred":[
        "La Argentina"
    ],
    "name:ita_x_preferred":[
        "La Argentina"
    ],
    "name:swe_x_preferred":[
        "La Argentina"
    ],
    "name:tur_x_preferred":[
        "La Argentina"
    ],
    "wof:name":"La Argentina",
    "wof:placetype":"locality",
    "wof:population":4
},
  "geometry": {"coordinates":[-93.74972,16.7825],"type":"Point"}
}