{
  "type": "Feature",
  "properties": {
    "gn:gn_country":"MX",
    "iso:country":"MX",
    "name:ast_x_preferred":[
        "Castiellu"
    ],
    "name:cat_x_preferred":[
        "Castillo"
    ],
    "name:ceb_x_preferred":[
        "Castillo"
    ],
    "name:ces_x_preferred":[
        "Castillo"
    ],
    "name:deu_x_preferred":[
        "Castillo"
    ],
    "name:fin_x_preferred":[
        "Castillo"
    ],
    "name:fra_x_preferred":[
        "Castillo"
    ],
    "name:glg_x_preferred":[
        "Castillo"
    ],
    "name:ita_x_preferred":[
        "Castillo"
    ],
    "name:jpn_x_preferred":[
        "\u30ab\u30b9\u30c6\u30a3\u30ea\u30e7"
    ],
    "name:nld_x_preferred":[
        "Castillo"
    ],
    "name:rus_x_preferred":[
        "\u041a\u0430\u0441\u0442\u0438\u043b\u044c\u043e"
    ],
    "name:sco_x_preferred":[
        "Castillo"
    ],
    "name:spa_x_preferred":[
        "Castillo"
    ],
    "name:swe_x_preferred":[
        "Castillo"
    ],
    "name:ukr_x_preferred":[
        "\u041a\u0430\u0441\u0442\u0456\u043b\u044c\u0439\u043e"
    ],
    "name:zho_x_preferred":[
        "\u5361\u65af\u8482\u7565"
    ],
    "qs_pg:aaroncc":"MX",
    "qs_pg:gn_country":"MX",
    "qs_pg:name":"Castillo",
    "qs_pg:name_adm0":"M\u00e9xico",
    "qs_pg:name_adm1":"Baja California",
    "qs_pg:photos":150,
    "qs_pg:photos_1k":30,
    "qs_pg:photos_9k":1,
    "qs_pg:photos_9r":3,
    "qs_pg:photos_all":150,
    "qs_pg:photos_sr":3,
    "qs_pg:pop_sr":0,
    "qs_pg:qs_pg_placetype":"neighbourhood",
    "qs_pg:qs_pg_placetype_gp":"Suburb",
    "qs_pg:woe_adm0":23424900,
    "woe:adm0_id":23424900,
    "woe:name_adm0":"M\u00e9xico",
    "woe:name_adm1":"Baja California",
    "woe:placetype":"Suburb",
    "wof:name":"Castillo",
    "wof:placetype":"neighbourhood"
},
  "geometry": {"coordinates":[-117.055657,32.537608],"type":"Point"}
}