{
  "type": "Feature",
  "properties": {
    "gn:admin1_code":"21",
    "gn:admin2_code":"3",
    "gn:asciiname":"El Chaparro",
    "gn:country_code":"MX",
    "gn:dem":1274,
    "gn:feature_class":"P",
    "gn:feature_code":"PPL",
    "gn:name":"El Chaparro",
    "gn:population":46,
    "gn:timezone":"America/Mexico_City",
    "iso:country":"MX",
    "wof:name":"El Chaparro",
    "wof:placetype":"locality",
    "wof:population":46
},
  "geometry": {"coordinates":[-98.03109000000001,18.12215],"type":"Point"}
}