{
  "type": "Feature",
  "properties": {
    "gn:admin1_code":"23.0",
    "gn:admin2_code":"4.0",
    "gn:asciiname":"Playa Pescar",
    "gn:country_code":"MX",
    "gn:dem":4,
    "gn:feature_class":"P",
    "gn:feature_code":"PPL",
    "gn:name":"Playa Pescar",
    "gn:population":0,
    "gn:timezone":"America/Cancun",
    "iso:country":"MX",
    "name:spa_x_preferred":[
        "Playa Pescar"
    ],
    "wof:name":"Playa Pescar",
    "wof:placetype":"locality"
},
  "geometry": {"coordinates":[-87.79523,18.37077],"type":"Point"}
}