{
  "type": "Feature",
  "properties": {
    "gn:admin1_code":"15.0",
    "gn:admin2_code":"8.0",
    "gn:asciiname":"Huixtitla",
    "gn:country_code":"MX",
    "gn:dem":987,
    "gn:feature_class":"P",
    "gn:feature_code":"PPL",
    "gn:name":"Huixtitla",
    "gn:population":0,
    "gn:timezone":"America/Mexico_City",
    "iso:country":"MX",
    "name:spa_x_preferred":[
        "Huixtitla"
    ],
    "name:und_x_variant":[
        "Huistitla"
    ],
    "wof:name":"Huixtitla",
    "wof:placetype":"locality"
},
  "geometry": {"coordinates":[-100.35614,18.63167],"type":"Point"}
}