{
  "type": "Feature",
  "properties": {
    "gn:admin1_code":"6",
    "gn:admin2_code":"34.0",
    "gn:asciiname":"Corralitos",
    "gn:country_code":"MX",
    "gn:dem":1933,
    "gn:feature_class":"P",
    "gn:feature_code":"PPL",
    "gn:name":"Corralitos",
    "gn:population":0,
    "gn:timezone":"America/Chihuahua",
    "iso:country":"MX",
    "wof:name":"Corralitos",
    "wof:placetype":"locality"
},
  "geometry": {"coordinates":[-107.5493,29.64386],"type":"Point"}
}