{
  "type": "Feature",
  "properties": {
    "gn:admin1_code":"28",
    "gn:admin2_code":"32.0",
    "gn:asciiname":"Pancho Villa (Francisco Villa)",
    "gn:country_code":"MX",
    "gn:dem":114,
    "gn:feature_class":"P",
    "gn:feature_code":"PPL",
    "gn:name":"Pancho Villa (Francisco Villa)",
    "gn:population":159,
    "gn:timezone":"America/Matamoros",
    "iso:country":"MX",
    "wof:name":"Pancho Villa (Francisco Villa)",
    "wof:placetype":"locality",
    "wof:population":159
},
  "geometry": {"coordinates":[-98.48083,25.6525],"type":"Point"}
}