{
  "type": "Feature",
  "properties": {
    "gn:admin1_code":"12",
    "gn:admin2_code":"76.0",
    "gn:asciiname":"Colonia Progreso (Cerro Gavilan)",
    "gn:country_code":"MX",
    "gn:dem":1397,
    "gn:feature_class":"P",
    "gn:feature_code":"PPL",
    "gn:name":"Colonia Progreso (Cerro Gavil\u00e1n)",
    "gn:population":302,
    "gn:timezone":"America/Mexico_City",
    "iso:country":"MX",
    "name:und_x_variant":[
        "Colonia Progreso (Cerro Gavil\u00e1n)"
    ],
    "wof:name":"Colonia Progreso (Cerro Gavilan)",
    "wof:placetype":"locality",
    "wof:population":302
},
  "geometry": {"coordinates":[-98.9051,17.05499],"type":"Point"}
}