{
  "type": "Feature",
  "properties": {
    "gn:admin1_code":"21",
    "gn:admin2_code":"148.0",
    "gn:asciiname":"San Martin Tlamapa",
    "gn:country_code":"MX",
    "gn:dem":2127,
    "gn:feature_class":"P",
    "gn:feature_code":"PPL",
    "gn:name":"San Mart\u00edn Tlamapa",
    "gn:population":1636,
    "gn:timezone":"America/Mexico_City",
    "iso:country":"MX",
    "name:und_x_variant":[
        "San Mart\u00edn Tlamapa"
    ],
    "wof:name":"San Martin Tlamapa",
    "wof:placetype":"locality",
    "wof:population":1636
},
  "geometry": {"coordinates":[-98.39694,18.9775],"type":"Point"}
}