{
  "type": "Feature",
  "properties": {
    "gn:admin1_code":"26",
    "gn:admin2_code":"33.0",
    "gn:asciiname":"Torocoba",
    "gn:country_code":"MX",
    "gn:dem":5,
    "gn:feature_class":"P",
    "gn:feature_code":"PPL",
    "gn:name":"Torocoba",
    "gn:population":251,
    "gn:timezone":"America/Hermosillo",
    "iso:country":"MX",
    "name:spa_x_preferred":[
        "Torocoba"
    ],
    "wof:name":"Torocoba",
    "wof:placetype":"locality",
    "wof:population":251
},
  "geometry": {"coordinates":[-109.70823,26.75219],"type":"Point"}
}