{
  "type": "Feature",
  "properties": {
    "gn:admin1_code":"19.0",
    "gn:admin2_code":"28.0",
    "gn:asciiname":"Buenavista Dos",
    "gn:country_code":"MX",
    "gn:dem":497,
    "gn:feature_class":"P",
    "gn:feature_code":"PPL",
    "gn:name":"Buenavista Dos",
    "gn:population":0,
    "gn:timezone":"America/Monterrey",
    "iso:country":"MX",
    "name:spa_x_preferred":[
        "Buenavista Dos"
    ],
    "wof:name":"Buenavista Dos",
    "wof:placetype":"locality"
},
  "geometry": {"coordinates":[-100.10625,26.01939],"type":"Point"}
}