{
  "type": "Feature",
  "properties": {
    "gn:admin1_code":"10",
    "gn:admin2_code":"5.0",
    "gn:asciiname":"Sebastian Lerdo de Tejada",
    "gn:country_code":"MX",
    "gn:dem":1884,
    "gn:feature_class":"P",
    "gn:feature_code":"PPL",
    "gn:name":"Sebasti\u00e1n Lerdo de Tejada",
    "gn:population":1712,
    "gn:timezone":"America/Monterrey",
    "iso:country":"MX",
    "name:und_x_variant":[
        "Sebasti\u00e1n Lerdo de Tejada"
    ],
    "wof:name":"Sebastian Lerdo de Tejada",
    "wof:placetype":"locality",
    "wof:population":1712
},
  "geometry": {"coordinates":[-104.63639000000001,23.95444],"type":"Point"}
}