{
  "type": "Feature",
  "properties": {
    "gn:admin1_code":"26",
    "gn:admin2_code":"22.0",
    "gn:asciiname":"La Malenita",
    "gn:country_code":"MX",
    "gn:dem":825,
    "gn:feature_class":"P",
    "gn:feature_code":"PPL",
    "gn:name":"La Malenita",
    "gn:population":0,
    "gn:timezone":"America/Hermosillo",
    "iso:country":"MX",
    "name:spa_x_preferred":[
        "La Malenita"
    ],
    "name:und_x_variant":[
        "Malenita"
    ],
    "wof:name":"La Malenita",
    "wof:placetype":"locality"
},
  "geometry": {"coordinates":[-110.71003,30.26734],"type":"Point"}
}