{
  "type": "Feature",
  "properties": {
    "gn:admin1_code":"5",
    "gn:admin2_code":"32.0",
    "gn:asciiname":"El Mango",
    "gn:country_code":"MX",
    "gn:dem":575,
    "gn:feature_class":"P",
    "gn:feature_code":"PPL",
    "gn:name":"El Mango",
    "gn:population":95,
    "gn:timezone":"America/Mexico_City",
    "iso:country":"MX",
    "wof:name":"El Mango",
    "wof:placetype":"locality",
    "wof:population":95
},
  "geometry": {"coordinates":[-92.55249999999999,15.36306],"type":"Point"}
}