{
  "type": "Feature",
  "properties": {
    "gn:admin1_code":"11",
    "gn:admin2_code":"3.0",
    "gn:asciiname":"Santa Teresita de Don Diego",
    "gn:country_code":"MX",
    "gn:dem":1896,
    "gn:feature_class":"P",
    "gn:feature_code":"PPL",
    "gn:name":"Santa Teresita de Don Diego",
    "gn:population":1487,
    "gn:timezone":"America/Mexico_City",
    "iso:country":"MX",
    "wof:name":"Santa Teresita de Don Diego",
    "wof:placetype":"locality",
    "wof:population":1487
},
  "geometry": {"coordinates":[-100.77861,20.88],"type":"Point"}
}