{
  "type": "Feature",
  "properties": {
    "gn:admin1_code":"14.0",
    "gn:admin2_code":"115.0",
    "gn:asciiname":"La Fragua",
    "gn:country_code":"MX",
    "gn:dem":1779,
    "gn:feature_class":"P",
    "gn:feature_code":"PPL",
    "gn:name":"La Fragua",
    "gn:population":0,
    "gn:timezone":"America/Mexico_City",
    "iso:country":"MX",
    "name:spa_x_preferred":[
        "La Fragua"
    ],
    "wof:name":"La Fragua",
    "wof:placetype":"locality"
},
  "geometry": {"coordinates":[-103.62357,22.05429],"type":"Point"}
}