{
  "type": "Feature",
  "properties": {
    "gn:admin1_code":"5.0",
    "gn:admin2_code":"81.0",
    "gn:asciiname":"El Paraiso",
    "gn:country_code":"MX",
    "gn:dem":306,
    "gn:feature_class":"P",
    "gn:feature_code":"PPL",
    "gn:name":"El Para\u00edso",
    "gn:population":0,
    "gn:timezone":"America/Mexico_City",
    "iso:country":"MX",
    "name:spa_x_preferred":[
        "El Para\u00edso"
    ],
    "wof:name":"El Paraiso",
    "wof:placetype":"locality"
},
  "geometry": {"coordinates":[-92.62944,17.14551],"type":"Point"}
}