{
  "type": "Feature",
  "properties": {
    "gn:admin1_code":"16",
    "gn:admin2_code":"16.0",
    "gn:asciiname":"Colonia Primo Tapia (El Chirimoyo)",
    "gn:country_code":"MX",
    "gn:dem":1992,
    "gn:feature_class":"P",
    "gn:feature_code":"PPL",
    "gn:name":"Colonia Primo Tapia (El Chirimoyo)",
    "gn:population":280,
    "gn:timezone":"America/Mexico_City",
    "iso:country":"MX",
    "wof:name":"Colonia Primo Tapia (El Chirimoyo)",
    "wof:placetype":"locality",
    "wof:population":280
},
  "geometry": {"coordinates":[-101.64972,19.84056],"type":"Point"}
}