{
  "type": "Feature",
  "properties": {
    "gn:admin1_code":"12.0",
    "gn:asciiname":"Los Tlacololes",
    "gn:country_code":"MX",
    "gn:dem":1180,
    "gn:feature_class":"P",
    "gn:feature_code":"PPL",
    "gn:name":"Los Tlacololes",
    "gn:population":0,
    "gn:timezone":"America/Mexico_City",
    "iso:country":"MX",
    "name:spa_x_preferred":[
        "Los Tlacololes"
    ],
    "wof:name":"Los Tlacololes",
    "wof:placetype":"locality"
},
  "geometry": {"coordinates":[-98.74437,18.09761],"type":"Point"}
}