{
  "type": "Feature",
  "properties": {
    "gn:admin1_code":"30",
    "gn:admin2_code":"173",
    "gn:asciiname":"El Crucero (Colonia las Josefinas)",
    "gn:country_code":"MX",
    "gn:dem":97,
    "gn:feature_class":"P",
    "gn:feature_code":"PPL",
    "gn:name":"El Crucero (Colonia las Josefinas)",
    "gn:population":39,
    "gn:timezone":"America/Mexico_City",
    "iso:country":"MX",
    "wof:name":"El Crucero (Colonia las Josefinas)",
    "wof:placetype":"locality",
    "wof:population":39
},
  "geometry": {"coordinates":[-96.71972,18.40278],"type":"Point"}
}