{
  "type": "Feature",
  "properties": {
    "gn:admin1_code":"30",
    "gn:admin2_code":"33",
    "gn:asciiname":"La Guasima",
    "gn:country_code":"MX",
    "gn:dem":29,
    "gn:feature_class":"P",
    "gn:feature_code":"PPL",
    "gn:name":"La Gu\u00e1sima",
    "gn:population":44,
    "gn:timezone":"America/Mexico_City",
    "iso:country":"MX",
    "name:und_x_variant":[
        "La Gu\u00e1sima"
    ],
    "wof:name":"La Guasima",
    "wof:placetype":"locality",
    "wof:population":44
},
  "geometry": {"coordinates":[-97.31722000000001,20.68639],"type":"Point"}
}