{
  "type": "Feature",
  "properties": {
    "gn:admin1_code":"30",
    "gn:admin2_code":"136.0",
    "gn:asciiname":"Xoteopan",
    "gn:country_code":"MX",
    "gn:dem":1871,
    "gn:feature_class":"P",
    "gn:feature_code":"PPL",
    "gn:name":"Xoteopan",
    "gn:population":64,
    "gn:timezone":"America/Mexico_City",
    "iso:country":"MX",
    "wof:name":"Xoteopan",
    "wof:placetype":"locality",
    "wof:population":64
},
  "geometry": {"coordinates":[-96.99722,19.57917],"type":"Point"}
}