{
  "type": "Feature",
  "properties": {
    "gn:admin1_code":"31",
    "gn:admin2_code":"28.0",
    "gn:asciiname":"Santa Ursula",
    "gn:country_code":"MX",
    "gn:dem":5,
    "gn:feature_class":"P",
    "gn:feature_code":"PPL",
    "gn:name":"Santa \u00darsula",
    "gn:population":0,
    "gn:timezone":"America/Merida",
    "iso:country":"MX",
    "wof:name":"Santa Ursula",
    "wof:placetype":"locality"
},
  "geometry": {"coordinates":[-88.74418,21.34567],"type":"Point"}
}