{
  "type": "Feature",
  "properties": {
    "gn:admin1_code":"26",
    "gn:admin2_code":"47.0",
    "gn:asciiname":"El Yeso",
    "gn:country_code":"MX",
    "gn:dem":701,
    "gn:feature_class":"P",
    "gn:feature_code":"PPL",
    "gn:name":"El Yeso",
    "gn:population":0,
    "gn:timezone":"America/Hermosillo",
    "iso:country":"MX",
    "name:spa_x_preferred":[
        "El Yeso"
    ],
    "wof:name":"El Yeso",
    "wof:placetype":"locality"
},
  "geometry": {"coordinates":[-111.56529,29.83784],"type":"Point"}
}