{
  "type": "Feature",
  "properties": {
    "gn:admin1_code":"14.0",
    "gn:asciiname":"La Alameda",
    "gn:country_code":"MX",
    "gn:dem":1866,
    "gn:feature_class":"P",
    "gn:feature_code":"PPL",
    "gn:name":"La Alameda",
    "gn:population":0,
    "gn:timezone":"America/Mexico_City",
    "iso:country":"MX",
    "name:spa_x_preferred":[
        "La Alameda"
    ],
    "wof:name":"La Alameda",
    "wof:placetype":"locality"
},
  "geometry": {"coordinates":[-102.14384,20.91446],"type":"Point"}
}