{
  "type": "Feature",
  "properties": {
    "gn:admin1_code":"18",
    "gn:admin2_code":"12.0",
    "gn:asciiname":"Mogote",
    "gn:country_code":"MX",
    "gn:dem":8,
    "gn:feature_class":"P",
    "gn:feature_code":"PPL",
    "gn:name":"Mogote",
    "gn:population":0,
    "gn:timezone":"America/Mazatlan",
    "iso:country":"MX",
    "wof:name":"Mogote",
    "wof:placetype":"locality"
},
  "geometry": {"coordinates":[-105.28333000000001,21.71667],"type":"Point"}
}