{
  "type": "Feature",
  "properties": {
    "gn:admin1_code":"28.0",
    "gn:admin2_code":"12.0",
    "gn:asciiname":"El Trebol",
    "gn:country_code":"MX",
    "gn:dem":18,
    "gn:feature_class":"P",
    "gn:feature_code":"PPL",
    "gn:name":"El Tr\u00e9bol",
    "gn:population":2,
    "gn:timezone":"America/Monterrey",
    "iso:country":"MX",
    "name:spa_x_preferred":[
        "El Tr\u00e9bol"
    ],
    "wof:name":"El Trebol",
    "wof:placetype":"locality",
    "wof:population":2
},
  "geometry": {"coordinates":[-98.52083,22.46639],"type":"Point"}
}