{
  "type": "Feature",
  "properties": {
    "gn:admin1_code":"3",
    "gn:admin2_code":"3.0",
    "gn:asciiname":"El Cardon",
    "gn:country_code":"MX",
    "gn:dem":162,
    "gn:feature_class":"P",
    "gn:feature_code":"PPL",
    "gn:name":"El Card\u00f3n",
    "gn:population":4,
    "gn:timezone":"America/Mazatlan",
    "iso:country":"MX",
    "name:und_x_variant":[
        "El Card\u00f3n"
    ],
    "wof:name":"El Cardon",
    "wof:placetype":"locality",
    "wof:population":4
},
  "geometry": {"coordinates":[-110.28505,23.97786],"type":"Point"}
}