{
  "type": "Feature",
  "properties": {
    "gn:admin1_code":"6",
    "gn:admin2_code":"47.0",
    "gn:asciiname":"El Saucito",
    "gn:country_code":"MX",
    "gn:dem":1326,
    "gn:feature_class":"P",
    "gn:feature_code":"PPL",
    "gn:name":"El Saucito",
    "gn:population":71,
    "gn:timezone":"America/Chihuahua",
    "iso:country":"MX",
    "name:spa_x_preferred":[
        "El Saucito"
    ],
    "wof:name":"El Saucito",
    "wof:placetype":"locality",
    "wof:population":71
},
  "geometry": {"coordinates":[-108.58273,28.09324],"type":"Point"}
}