{
  "type": "Feature",
  "properties": {
    "gn:admin1_code":"29",
    "gn:admin2_code":"6.0",
    "gn:asciiname":"Las Calandrias",
    "gn:country_code":"MX",
    "gn:dem":2621,
    "gn:feature_class":"P",
    "gn:feature_code":"PPL",
    "gn:name":"Las Calandrias",
    "gn:population":0,
    "gn:timezone":"America/Mexico_City",
    "iso:country":"MX",
    "name:spa_x_preferred":[
        "Las Calandrias"
    ],
    "wof:name":"Las Calandrias",
    "wof:placetype":"locality"
},
  "geometry": {"coordinates":[-98.53628,19.54171],"type":"Point"}
}