{
  "type": "Feature",
  "properties": {
    "gn:admin1_code":"21",
    "gn:admin2_code":"36.0",
    "gn:asciiname":"Xochiapa",
    "gn:country_code":"MX",
    "gn:dem":1691,
    "gn:feature_class":"P",
    "gn:feature_code":"PPL",
    "gn:name":"Xochiapa",
    "gn:population":168,
    "gn:timezone":"America/Mexico_City",
    "iso:country":"MX",
    "wof:name":"Xochiapa",
    "wof:placetype":"locality",
    "wof:population":168
},
  "geometry": {"coordinates":[-96.92667,18.24639],"type":"Point"}
}