{
  "type": "Feature",
  "properties": {
    "gn:admin1_code":"26",
    "gn:admin2_code":"12.0",
    "gn:asciiname":"El Pochote",
    "gn:country_code":"MX",
    "gn:dem":86,
    "gn:feature_class":"P",
    "gn:feature_code":"PPL",
    "gn:name":"El Pochote",
    "gn:population":0,
    "gn:timezone":"America/Hermosillo",
    "iso:country":"MX",
    "name:spa_x_preferred":[
        "El Pochote"
    ],
    "wof:name":"El Pochote",
    "wof:placetype":"locality"
},
  "geometry": {"coordinates":[-110.11479,27.76839],"type":"Point"}
}