{
  "type": "Feature",
  "properties": {
    "gn:admin1_code":"10.0",
    "gn:admin2_code":"32.0",
    "gn:asciiname":"Coyotillos",
    "gn:cc2":"MX",
    "gn:country_code":"MX",
    "gn:dem":1819,
    "gn:feature_class":"P",
    "gn:feature_code":"PPL",
    "gn:name":"Coyotillos",
    "gn:population":16,
    "gn:timezone":"America/Monterrey",
    "iso:country":"MX",
    "name:und_x_variant":[
        "Coyotitos",
        "Coyotillos"
    ],
    "wof:name":"Coyotillos",
    "wof:placetype":"locality",
    "wof:population":16
},
  "geometry": {"coordinates":[-105.39033999999999,24.8986],"type":"Point"}
}