{
  "type": "Feature",
  "properties": {
    "gn:admin1_code":"22",
    "gn:admin2_code":"8",
    "gn:asciiname":"Los Cabrera",
    "gn:country_code":"MX",
    "gn:dem":2403,
    "gn:feature_class":"P",
    "gn:feature_code":"PPL",
    "gn:name":"Los Cabrera",
    "gn:population":11,
    "gn:timezone":"America/Mexico_City",
    "iso:country":"MX",
    "wof:name":"Los Cabrera",
    "wof:placetype":"locality",
    "wof:population":11
},
  "geometry": {"coordinates":[-100.38861,20.31528],"type":"Point"}
}