{
  "type": "Feature",
  "properties": {
    "gn:admin1_code":"25.0",
    "gn:admin2_code":"6.0",
    "gn:asciiname":"La Pradera",
    "gn:country_code":"MX",
    "gn:dem":56,
    "gn:feature_class":"P",
    "gn:feature_code":"PPL",
    "gn:name":"La Pradera",
    "gn:population":0,
    "gn:timezone":"America/Mazatlan",
    "iso:country":"MX",
    "name:spa_x_preferred":[
        "La Pradera"
    ],
    "wof:name":"La Pradera",
    "wof:placetype":"locality"
},
  "geometry": {"coordinates":[-107.56834000000001,24.89557000000001],"type":"Point"}
}