{
  "type": "Feature",
  "properties": {
    "gn:admin1_code":"16",
    "gn:admin2_code":"15.0",
    "gn:asciiname":"Los Rodriguez",
    "gn:country_code":"MX",
    "gn:dem":1222,
    "gn:feature_class":"P",
    "gn:feature_code":"PPL",
    "gn:name":"Los Rodr\u00edguez",
    "gn:population":5,
    "gn:timezone":"America/Mexico_City",
    "iso:country":"MX",
    "name:und_x_variant":[
        "Los Rodr\u00edguez"
    ],
    "wof:name":"Los Rodriguez",
    "wof:placetype":"locality",
    "wof:population":5
},
  "geometry": {"coordinates":[-103.03082999999999,18.42917000000001],"type":"Point"}
}