{
  "type": "Feature",
  "properties": {
    "gn:admin1_code":"30",
    "gn:admin2_code":"101.0",
    "gn:asciiname":"San Isidro el Berro",
    "gn:country_code":"MX",
    "gn:dem":2594,
    "gn:feature_class":"P",
    "gn:feature_code":"PPL",
    "gn:name":"San Isidro el Berro",
    "gn:population":1219,
    "gn:timezone":"America/Mexico_City",
    "iso:country":"MX",
    "wof:name":"San Isidro el Berro",
    "wof:placetype":"locality",
    "wof:population":1219
},
  "geometry": {"coordinates":[-97.20556000000001,18.92722],"type":"Point"}
}