{
  "type": "Feature",
  "properties": {
    "gn:admin1_code":"10",
    "gn:admin2_code":"12.0",
    "gn:asciiname":"Los Pirules",
    "gn:country_code":"MX",
    "gn:dem":1143,
    "gn:feature_class":"P",
    "gn:feature_code":"PPL",
    "gn:name":"Los Pirules",
    "gn:population":4,
    "gn:timezone":"America/Monterrey",
    "iso:country":"MX",
    "wof:name":"Los Pirules",
    "wof:placetype":"locality",
    "wof:population":4
},
  "geometry": {"coordinates":[-103.58784,25.51028],"type":"Point"}
}