{
  "type": "Feature",
  "properties": {
    "gn:admin1_code":"30",
    "gn:admin2_code":"89",
    "gn:asciiname":"Arroyo Blanco",
    "gn:country_code":"MX",
    "gn:dem":12,
    "gn:feature_class":"P",
    "gn:feature_code":"PPL",
    "gn:name":"Arroyo Blanco",
    "gn:population":34,
    "gn:timezone":"America/Mexico_City",
    "iso:country":"MX",
    "wof:name":"Arroyo Blanco",
    "wof:placetype":"locality",
    "wof:population":34
},
  "geometry": {"coordinates":[-94.68028,17.75861],"type":"Point"}
}