{
  "type": "Feature",
  "properties": {
    "gn:admin1_code":"26",
    "gn:admin2_code":"18.0",
    "gn:asciiname":"El Paraiso [Restaurante]",
    "gn:country_code":"MX",
    "gn:dem":62,
    "gn:feature_class":"P",
    "gn:feature_code":"PPL",
    "gn:name":"El Para\u00edso [Restaurante]",
    "gn:population":5,
    "gn:timezone":"America/Hermosillo",
    "iso:country":"MX",
    "name:und_x_variant":[
        "El Para\u00edso [Restaurante]"
    ],
    "wof:name":"El Paraiso [Restaurante]",
    "wof:placetype":"locality",
    "wof:population":5
},
  "geometry": {"coordinates":[-109.875,27.73],"type":"Point"}
}