{
  "type": "Feature",
  "properties": {
    "gn:admin1_code":"5.0",
    "gn:asciiname":"San Caralampio la Morena",
    "gn:country_code":"MX",
    "gn:dem":335,
    "gn:feature_class":"P",
    "gn:feature_code":"PPL",
    "gn:name":"San Caralampio la Morena",
    "gn:population":0,
    "gn:timezone":"America/Mexico_City",
    "iso:country":"MX",
    "name:spa_x_preferred":[
        "San Caralampio la Morena"
    ],
    "wof:name":"San Caralampio la Morena",
    "wof:placetype":"locality"
},
  "geometry": {"coordinates":[-91.40552,16.24854],"type":"Point"}
}