{
  "type": "Feature",
  "properties": {
    "gn:admin1_code":"14",
    "gn:admin2_code":"84.0",
    "gn:asciiname":"Ocotes",
    "gn:country_code":"MX",
    "gn:dem":1152,
    "gn:feature_class":"P",
    "gn:feature_code":"PPL",
    "gn:name":"Ocotes",
    "gn:population":0,
    "gn:timezone":"America/Mexico_City",
    "iso:country":"MX",
    "name:und_x_variant":[
        "Los Ocotes",
        "Ocotes"
    ],
    "wof:name":"Ocotes",
    "wof:placetype":"locality"
},
  "geometry": {"coordinates":[-104.85137,20.42278],"type":"Point"}
}