{
  "type": "Feature",
  "properties": {
    "gn:admin1_code":"6",
    "gn:admin2_code":"37.0",
    "gn:asciiname":"Manuel F. Martinez",
    "gn:country_code":"MX",
    "gn:dem":1122,
    "gn:feature_class":"P",
    "gn:feature_code":"PPL",
    "gn:name":"Manuel F. Mart\u00ednez",
    "gn:population":0,
    "gn:timezone":"America/Ojinaga",
    "iso:country":"MX",
    "wof:name":"Manuel F. Martinez",
    "wof:placetype":"locality"
},
  "geometry": {"coordinates":[-106.41667,31.68333],"type":"Point"}
}