{
  "type": "Feature",
  "properties": {
    "gn:admin1_code":"6",
    "gn:admin2_code":"9.0",
    "gn:asciiname":"Awaravo",
    "gn:country_code":"MX",
    "gn:dem":2373,
    "gn:feature_class":"P",
    "gn:feature_code":"PPL",
    "gn:name":"Awaravo",
    "gn:population":5,
    "gn:timezone":"America/Chihuahua",
    "iso:country":"MX",
    "wof:name":"Awaravo",
    "wof:placetype":"locality",
    "wof:population":5
},
  "geometry": {"coordinates":[-107.61882,27.74325],"type":"Point"}
}