{
  "type": "Feature",
  "properties": {
    "gn:admin1_code":"7.0",
    "gn:admin2_code":"24.0",
    "gn:asciiname":"Cienaga del Carmen",
    "gn:country_code":"MX",
    "gn:dem":1299,
    "gn:feature_class":"P",
    "gn:feature_code":"PPL",
    "gn:name":"Ci\u00e9naga del Carmen",
    "gn:population":0,
    "gn:timezone":"America/Monterrey",
    "iso:country":"MX",
    "name:spa_x_preferred":[
        "Ci\u00e9naga del Carmen"
    ],
    "name:und_x_variant":[
        "Ci\u00e9nega del Carmen"
    ],
    "wof:name":"Cienaga del Carmen",
    "wof:placetype":"locality"
},
  "geometry": {"coordinates":[-101.9466,25.55476],"type":"Point"}
}