{
  "type": "Feature",
  "properties": {
    "gn:admin1_code":"10",
    "gn:admin2_code":"14",
    "gn:asciiname":"Zopilotes",
    "gn:country_code":"MX",
    "gn:dem":1293,
    "gn:feature_class":"P",
    "gn:feature_code":"PPL",
    "gn:name":"Zopilotes",
    "gn:population":12,
    "gn:timezone":"America/Mazatlan",
    "iso:country":"MX",
    "wof:name":"Zopilotes",
    "wof:placetype":"locality",
    "wof:population":12
},
  "geometry": {"coordinates":[-104.89762,22.85033],"type":"Point"}
}