{
  "type": "Feature",
  "properties": {
    "gn:admin1_code":"25",
    "gn:asciiname":"Tepalcates",
    "gn:country_code":"MX",
    "gn:dem":1101,
    "gn:feature_class":"P",
    "gn:feature_code":"PPL",
    "gn:name":"Tepalcates",
    "gn:population":0,
    "gn:timezone":"America/Mazatlan",
    "iso:country":"MX",
    "wof:name":"Tepalcates",
    "wof:placetype":"locality"
},
  "geometry": {"coordinates":[-105.88333,23.73333],"type":"Point"}
}