{
  "type": "Feature",
  "properties": {
    "gn:admin1_code":"1",
    "gn:admin2_code":"4.0",
    "gn:asciiname":"Soledad de Abajo",
    "gn:country_code":"MX",
    "gn:dem":1975,
    "gn:feature_class":"P",
    "gn:feature_code":"PPL",
    "gn:name":"Soledad de Abajo",
    "gn:population":0,
    "gn:timezone":"America/Mexico_City",
    "iso:country":"MX",
    "name:spa_x_preferred":[
        "Estaci\u00f3n de Adames"
    ],
    "name:und_x_variant":[
        "Soledad",
        "La Soledad",
        "Soledad de Abajo"
    ],
    "wof:name":"Soledad de Abajo",
    "wof:placetype":"locality"
},
  "geometry": {"coordinates":[-102.28608,22.40834],"type":"Point"}
}