{
  "type": "Feature",
  "properties": {
    "gn:admin1_code":"32",
    "gn:admin2_code":"35.0",
    "gn:asciiname":"Coronel Lauro G. Caloca",
    "gn:country_code":"MX",
    "gn:dem":2046,
    "gn:feature_class":"P",
    "gn:feature_code":"PPL",
    "gn:name":"Coronel Lauro G. Caloca",
    "gn:population":0,
    "gn:timezone":"America/Mexico_City",
    "iso:country":"MX",
    "name:spa_x_preferred":[
        "Coronel Lauro G. Caloca"
    ],
    "name:spa_x_variant":[
        "El Rasc\u00f3n"
    ],
    "wof:name":"Coronel Lauro G. Caloca",
    "wof:placetype":"locality"
},
  "geometry": {"coordinates":[-102.05744,22.38051],"type":"Point"}
}