{
  "type": "Feature",
  "properties": {
    "gn:admin1_code":"14",
    "gn:admin2_code":"66.0",
    "gn:asciiname":"La Ladrillera",
    "gn:country_code":"MX",
    "gn:dem":1536,
    "gn:feature_class":"P",
    "gn:feature_code":"PPL",
    "gn:name":"La Ladrillera",
    "gn:population":92,
    "gn:timezone":"America/Mexico_City",
    "iso:country":"MX",
    "wof:name":"La Ladrillera",
    "wof:placetype":"locality",
    "wof:population":92
},
  "geometry": {"coordinates":[-102.87027999999999,20.36472],"type":"Point"}
}