{
  "type": "Feature",
  "properties": {
    "gn:admin1_code":"13",
    "gn:admin2_code":"61.0",
    "gn:asciiname":"Alambique",
    "gn:country_code":"MX",
    "gn:dem":2743,
    "gn:feature_class":"P",
    "gn:feature_code":"PPL",
    "gn:name":"Alambique",
    "gn:population":0,
    "gn:timezone":"America/Mexico_City",
    "iso:country":"MX",
    "wof:name":"Alambique",
    "wof:placetype":"locality"
},
  "geometry": {"coordinates":[-98.43333,19.88333],"type":"Point"}
}