{
  "type": "Feature",
  "properties": {
    "gn:admin1_code":"10",
    "gn:admin2_code":"18.0",
    "gn:asciiname":"Guzman y Hernandez",
    "gn:country_code":"MX",
    "gn:dem":1576,
    "gn:feature_class":"P",
    "gn:feature_code":"PPL",
    "gn:name":"Guzm\u00e1n y Hern\u00e1ndez",
    "gn:population":0,
    "gn:timezone":"America/Monterrey",
    "iso:country":"MX",
    "name:spa_x_preferred":[
        "Guzm\u00e1n y Hern\u00e1ndez"
    ],
    "name:spa_x_variant":[
        "La Noria"
    ],
    "name:und_x_variant":[
        "Guzm\u00e1n y Hernandez"
    ],
    "wof:name":"Guzman y Hernandez",
    "wof:placetype":"locality"
},
  "geometry": {"coordinates":[-105.1872,25.59823],"type":"Point"}
}