{
  "type": "Feature",
  "properties": {
    "gn:admin1_code":"10",
    "gn:admin2_code":"9.0",
    "gn:asciiname":"La Punta de la Mesa",
    "gn:country_code":"MX",
    "gn:dem":2154,
    "gn:feature_class":"P",
    "gn:feature_code":"PPL",
    "gn:name":"La Punta de la Mesa",
    "gn:population":0,
    "gn:timezone":"America/Monterrey",
    "iso:country":"MX",
    "name:spa_x_preferred":[
        "La Punta de la Mesa"
    ],
    "wof:name":"La Punta de la Mesa",
    "wof:placetype":"locality"
},
  "geometry": {"coordinates":[-106.15568,26.36716],"type":"Point"}
}