{
  "type": "Feature",
  "properties": {
    "gn:admin1_code":"26",
    "gn:admin2_code":"23.0",
    "gn:asciiname":"Los Hoyos",
    "gn:country_code":"MX",
    "gn:dem":843,
    "gn:feature_class":"P",
    "gn:feature_code":"PPL",
    "gn:name":"Los Hoyos",
    "gn:population":0,
    "gn:timezone":"America/Hermosillo",
    "iso:country":"MX",
    "name:spa_x_preferred":[
        "Los Hoyos"
    ],
    "wof:name":"Los Hoyos",
    "wof:placetype":"locality"
},
  "geometry": {"coordinates":[-109.89185000000001,29.94998],"type":"Point"}
}