{
  "type": "Feature",
  "properties": {
    "gn:admin1_code":"27",
    "gn:admin2_code":"12.0",
    "gn:asciiname":"Las Lomas de Caparroso",
    "gn:country_code":"MX",
    "gn:dem":147,
    "gn:feature_class":"P",
    "gn:feature_code":"PPL",
    "gn:name":"Las Lomas de Caparroso",
    "gn:population":60,
    "gn:timezone":"America/Mexico_City",
    "iso:country":"MX",
    "wof:name":"Las Lomas de Caparroso",
    "wof:placetype":"locality",
    "wof:population":60
},
  "geometry": {"coordinates":[-92.47806,17.58889],"type":"Point"}
}