{
  "type": "Feature",
  "properties": {
    "gn:admin1_code":"26",
    "gn:admin2_code":"41.0",
    "gn:asciiname":"Nacozari de Garcia",
    "gn:country_code":"MX",
    "gn:dem":1106,
    "gn:feature_class":"P",
    "gn:feature_code":"PPLA2",
    "gn:name":"Nacozari de Garc\u00eda",
    "gn:population":0,
    "gn:timezone":"America/Hermosillo",
    "iso:country":"MX",
    "name:und_x_variant":[
        "Placeritos de Nacozari",
        "Nacozari",
        "Nacozari de Garc\u00eda"
    ],
    "wof:name":"Nacozari de Garcia",
    "wof:placetype":"locality"
},
  "geometry": {"coordinates":[-109.68898,30.37489],"type":"Point"}
}