{
  "type": "Feature",
  "properties": {
    "gn:admin1_code":"6",
    "gn:admin2_code":"66.0",
    "gn:asciiname":"Sepayvo",
    "gn:country_code":"MX",
    "gn:dem":893,
    "gn:feature_class":"P",
    "gn:feature_code":"PPL",
    "gn:name":"Sepayvo",
    "gn:population":0,
    "gn:timezone":"America/Chihuahua",
    "iso:country":"MX",
    "name:und_x_variant":[
        "Sepaiva",
        "Sepayvo"
    ],
    "wof:name":"Sepayvo",
    "wof:placetype":"locality"
},
  "geometry": {"coordinates":[-108.4008,27.99004],"type":"Point"}
}