{
  "type": "Feature",
  "properties": {
    "gn:admin1_code":"20.0",
    "gn:admin2_code":"272.0",
    "gn:asciiname":"Cerro Ombligo",
    "gn:country_code":"MX",
    "gn:dem":650,
    "gn:feature_class":"P",
    "gn:feature_code":"PPL",
    "gn:name":"Cerro Ombligo",
    "gn:population":0,
    "gn:timezone":"America/Mexico_City",
    "iso:country":"MX",
    "name:spa_x_preferred":[
        "Cerro Ombligo"
    ],
    "wof:name":"Cerro Ombligo",
    "wof:placetype":"locality"
},
  "geometry": {"coordinates":[-97.43416000000001,16.26781],"type":"Point"}
}