{
  "type": "Feature",
  "properties": {
    "gn:admin1_code":"22",
    "gn:admin2_code":"12.0",
    "gn:asciiname":"Rancho Casa Blanca",
    "gn:country_code":"MX",
    "gn:dem":1911,
    "gn:feature_class":"P",
    "gn:feature_code":"PPL",
    "gn:name":"Rancho Casa Blanca",
    "gn:population":6,
    "gn:timezone":"America/Mexico_City",
    "iso:country":"MX",
    "wof:name":"Rancho Casa Blanca",
    "wof:placetype":"locality",
    "wof:population":6
},
  "geometry": {"coordinates":[-100.1725,20.505],"type":"Point"}
}