{
  "type": "Feature",
  "properties": {
    "gn:admin1_code":"7",
    "gn:admin2_code":"10.0",
    "gn:asciiname":"Pozuelos de Arriba",
    "gn:country_code":"MX",
    "gn:dem":610,
    "gn:feature_class":"P",
    "gn:feature_code":"PPL",
    "gn:name":"Pozuelos de Arriba",
    "gn:population":0,
    "gn:timezone":"America/Monterrey",
    "iso:country":"MX",
    "name:spa_x_preferred":[
        "Pozuelos de Arriba"
    ],
    "wof:name":"Pozuelos de Arriba",
    "wof:placetype":"locality"
},
  "geometry": {"coordinates":[-101.57975999999999,26.91171],"type":"Point"}
}