{
  "type": "Feature",
  "properties": {
    "gn:admin1_code":"21",
    "gn:admin2_code":"76.0",
    "gn:asciiname":"Mazolapa",
    "gn:country_code":"MX",
    "gn:dem":775,
    "gn:feature_class":"P",
    "gn:feature_code":"PPL",
    "gn:name":"Mazolapa",
    "gn:population":186,
    "gn:timezone":"America/Mexico_City",
    "iso:country":"MX",
    "wof:name":"Mazolapa",
    "wof:placetype":"locality",
    "wof:population":186
},
  "geometry": {"coordinates":[-97.31050999999999,19.94792],"type":"Point"}
}