{
  "type": "Feature",
  "properties": {
    "gn:admin1_code":"24",
    "gn:admin2_code":"45",
    "gn:asciiname":"Viborillas",
    "gn:country_code":"MX",
    "gn:dem":2172,
    "gn:feature_class":"P",
    "gn:feature_code":"PPL",
    "gn:name":"Viborillas",
    "gn:population":17,
    "gn:timezone":"America/Mexico_City",
    "iso:country":"MX",
    "wof:name":"Viborillas",
    "wof:placetype":"locality",
    "wof:population":17
},
  "geometry": {"coordinates":[-101.31278,22.98167],"type":"Point"}
}