{
  "type": "Feature",
  "properties": {
    "gn:admin1_code":"20",
    "gn:admin2_code":"412",
    "gn:asciiname":"El Trapiche Guienagati",
    "gn:country_code":"MX",
    "gn:dem":774,
    "gn:feature_class":"P",
    "gn:feature_code":"PPL",
    "gn:name":"El Trapiche Guienagati",
    "gn:population":52,
    "gn:timezone":"America/Mexico_City",
    "iso:country":"MX",
    "wof:name":"El Trapiche Guienagati",
    "wof:placetype":"locality",
    "wof:population":52
},
  "geometry": {"coordinates":[-95.41694,16.7575],"type":"Point"}
}