{
  "type": "Feature",
  "properties": {
    "gn:admin1_code":"20",
    "gn:admin2_code":"363.0",
    "gn:asciiname":"Rosa Blanca",
    "gn:country_code":"MX",
    "gn:dem":2461,
    "gn:feature_class":"P",
    "gn:feature_code":"PPL",
    "gn:name":"Rosa Blanca",
    "gn:population":56,
    "gn:timezone":"America/Mexico_City",
    "iso:country":"MX",
    "name:spa_x_preferred":[
        "Rosa Blanca"
    ],
    "wof:name":"Rosa Blanca",
    "wof:placetype":"locality",
    "wof:population":56
},
  "geometry": {"coordinates":[-96.61028,17.16639],"type":"Point"}
}