{
  "type": "Feature",
  "properties": {
    "gn:admin1_code":"30",
    "gn:admin2_code":"113.0",
    "gn:asciiname":"Tequecholapa",
    "gn:cc2":"MX",
    "gn:country_code":"MX",
    "gn:dem":709,
    "gn:feature_class":"P",
    "gn:feature_code":"PPL",
    "gn:name":"Tequecholapa",
    "gn:population":359,
    "gn:timezone":"America/Mexico_City",
    "iso:country":"MX",
    "name:und_x_variant":[
        "Tecuecholapa",
        "Tequecholapan",
        "Tequecholapa"
    ],
    "wof:name":"Tequecholapa",
    "wof:placetype":"locality",
    "wof:population":359
},
  "geometry": {"coordinates":[-96.94944,18.80167],"type":"Point"}
}