{
  "type": "Feature",
  "properties": {
    "gn:admin1_code":"4",
    "gn:admin2_code":"9.0",
    "gn:asciiname":"Miguel Hidalgo (Caracol)",
    "gn:country_code":"MX",
    "gn:dem":108,
    "gn:feature_class":"P",
    "gn:feature_code":"PPL",
    "gn:name":"Miguel Hidalgo (Caracol)",
    "gn:population":259,
    "gn:timezone":"America/Merida",
    "iso:country":"MX",
    "wof:name":"Miguel Hidalgo (Caracol)",
    "wof:placetype":"locality",
    "wof:population":259
},
  "geometry": {"coordinates":[-90.66639000000001,18.545],"type":"Point"}
}