{
  "type": "Feature",
  "properties": {
    "gn:admin1_code":"28",
    "gn:admin2_code":"21.0",
    "gn:asciiname":"Cuauhtemoc",
    "gn:country_code":"MX",
    "gn:dem":82,
    "gn:feature_class":"P",
    "gn:feature_code":"PPL",
    "gn:name":"Cuauhtemoc",
    "gn:population":0,
    "gn:timezone":"America/Monterrey",
    "iso:country":"MX",
    "name:spa_x_preferred":[
        "Cuauhtemoc"
    ],
    "name:und_x_variant":[
        "Cuauht\u00e9moc"
    ],
    "wof:name":"Cuauhtemoc",
    "wof:placetype":"locality"
},
  "geometry": {"coordinates":[-99.02076,22.75051],"type":"Point"}
}