{
  "type": "Feature",
  "properties": {
    "gn:admin1_code":"20",
    "gn:admin2_code":"324.0",
    "gn:asciiname":"Palo de Arco",
    "gn:country_code":"MX",
    "gn:dem":136,
    "gn:feature_class":"P",
    "gn:feature_code":"PPL",
    "gn:name":"Palo de Arco",
    "gn:population":0,
    "gn:timezone":"America/Mexico_City",
    "iso:country":"MX",
    "name:spa_x_preferred":[
        "Palo de Arco"
    ],
    "wof:name":"Palo de Arco",
    "wof:placetype":"locality"
},
  "geometry": {"coordinates":[-96.39657,15.75942],"type":"Point"}
}