{
  "type": "Feature",
  "properties": {
    "gn:admin1_code":"21",
    "gn:admin2_code":"76.0",
    "gn:asciiname":"Pezmaco",
    "gn:country_code":"MX",
    "gn:dem":690,
    "gn:feature_class":"P",
    "gn:feature_code":"PPL",
    "gn:name":"Pezmaco",
    "gn:population":0,
    "gn:timezone":"America/Mexico_City",
    "iso:country":"MX",
    "name:spa_x_preferred":[
        "Pezmaco"
    ],
    "wof:name":"Pezmaco",
    "wof:placetype":"locality"
},
  "geometry": {"coordinates":[-97.32153,19.96277000000001],"type":"Point"}
}