{
  "type": "Feature",
  "properties": {
    "gn:admin1_code":"12.0",
    "gn:admin2_code":"22.0",
    "gn:asciiname":"El Manchon",
    "gn:country_code":"MX",
    "gn:dem":263,
    "gn:feature_class":"P",
    "gn:feature_code":"PPL",
    "gn:name":"El Manch\u00f3n",
    "gn:population":0,
    "gn:timezone":"America/Mexico_City",
    "iso:country":"MX",
    "name:spa_x_preferred":[
        "El Manch\u00f3n"
    ],
    "wof:name":"El Manchon",
    "wof:placetype":"locality"
},
  "geometry": {"coordinates":[-100.65363000000001,18.29866],"type":"Point"}
}