{
  "type": "Feature",
  "properties": {
    "gn:admin1_code":"14.0",
    "gn:admin2_code":"25.0",
    "gn:asciiname":"La Notaria",
    "gn:country_code":"MX",
    "gn:dem":1693,
    "gn:feature_class":"P",
    "gn:feature_code":"PPL",
    "gn:name":"La Notaria",
    "gn:population":0,
    "gn:timezone":"America/Mexico_City",
    "iso:country":"MX",
    "name:spa_x_preferred":[
        "La Notaria"
    ],
    "wof:name":"La Notaria",
    "wof:placetype":"locality"
},
  "geometry": {"coordinates":[-103.31899,22.04996],"type":"Point"}
}