{
  "type": "Feature",
  "properties": {
    "gn:admin1_code":"6",
    "gn:admin2_code":"17.0",
    "gn:asciiname":"Real del Monte",
    "gn:country_code":"MX",
    "gn:dem":2094,
    "gn:feature_class":"P",
    "gn:feature_code":"PPL",
    "gn:name":"Real del Monte",
    "gn:population":5,
    "gn:timezone":"America/Chihuahua",
    "iso:country":"MX",
    "wof:name":"Real del Monte",
    "wof:placetype":"locality",
    "wof:population":5
},
  "geometry": {"coordinates":[-106.82942,28.39218],"type":"Point"}
}