{
  "type": "Feature",
  "properties": {
    "gn:admin1_code":"20",
    "gn:admin2_code":"253",
    "gn:asciiname":"Cerro Minas",
    "gn:country_code":"MX",
    "gn:dem":1237,
    "gn:feature_class":"P",
    "gn:feature_code":"PPL",
    "gn:name":"Cerro Minas",
    "gn:population":25,
    "gn:timezone":"America/Mexico_City",
    "iso:country":"MX",
    "wof:name":"Cerro Minas",
    "wof:placetype":"locality",
    "wof:population":25
},
  "geometry": {"coordinates":[-96.28361,15.94528],"type":"Point"}
}