{
  "type": "Feature",
  "properties": {
    "gn:admin1_code":"5",
    "gn:admin2_code":"49.0",
    "gn:asciiname":"Bayalemo Dos",
    "gn:country_code":"MX",
    "gn:dem":1774,
    "gn:feature_class":"P",
    "gn:feature_code":"PPL",
    "gn:name":"Bayalemo Dos",
    "gn:population":630,
    "gn:timezone":"America/Mexico_City",
    "iso:country":"MX",
    "wof:name":"Bayalemo Dos",
    "wof:placetype":"locality",
    "wof:population":630
},
  "geometry": {"coordinates":[-92.76694999999999,16.93364],"type":"Point"}
}