{
  "type": "Feature",
  "properties": {
    "gn:admin1_code":"6",
    "gn:admin2_code":"32.0",
    "gn:asciiname":"El Martirio",
    "gn:country_code":"MX",
    "gn:dem":1392,
    "gn:feature_class":"P",
    "gn:feature_code":"PPL",
    "gn:name":"El Martirio",
    "gn:population":0,
    "gn:timezone":"America/Chihuahua",
    "iso:country":"MX",
    "name:spa_x_preferred":[
        "El Martirio"
    ],
    "wof:name":"El Martirio",
    "wof:placetype":"locality"
},
  "geometry": {"coordinates":[-105.94525,27.3086],"type":"Point"}
}