{
  "type": "Feature",
  "properties": {
    "gn:admin1_code":"26",
    "gn:admin2_code":"43.0",
    "gn:asciiname":"El Represo",
    "gn:country_code":"MX",
    "gn:dem":1140,
    "gn:feature_class":"P",
    "gn:feature_code":"PPL",
    "gn:name":"El Represo",
    "gn:population":9,
    "gn:timezone":"America/Hermosillo",
    "iso:country":"MX",
    "wof:name":"El Represo",
    "wof:placetype":"locality",
    "wof:population":9
},
  "geometry": {"coordinates":[-110.95305999999999,31.135],"type":"Point"}
}