{
  "type": "Feature",
  "properties": {
    "gn:admin1_code":"20",
    "gn:admin2_code":"277.0",
    "gn:asciiname":"Seccion Cuarta",
    "gn:country_code":"MX",
    "gn:dem":1445,
    "gn:feature_class":"P",
    "gn:feature_code":"PPL",
    "gn:name":"Secci\u00f3n Cuarta",
    "gn:population":0,
    "gn:timezone":"America/Mexico_City",
    "iso:country":"MX",
    "name:spa_x_preferred":[
        "Secci\u00f3n Cuarta"
    ],
    "wof:name":"Seccion Cuarta",
    "wof:placetype":"locality"
},
  "geometry": {"coordinates":[-96.94583,16.46778],"type":"Point"}
}