{
  "type": "Feature",
  "properties": {
    "gn:admin1_code":"25",
    "gn:admin2_code":"7.0",
    "gn:asciiname":"La Cieneguita de Nunez",
    "gn:country_code":"MX",
    "gn:dem":1134,
    "gn:feature_class":"P",
    "gn:feature_code":"PPL",
    "gn:name":"La Cieneguita de N\u00fa\u00f1ez",
    "gn:population":106,
    "gn:timezone":"America/Mazatlan",
    "iso:country":"MX",
    "name:und_x_variant":[
        "La Cieneguita de N\u00fa\u00f1ez"
    ],
    "wof:name":"La Cieneguita de Nunez",
    "wof:placetype":"locality",
    "wof:population":106
},
  "geometry": {"coordinates":[-108.1699,26.8291],"type":"Point"}
}