{
  "type": "Feature",
  "properties": {
    "gn:admin1_code":"28",
    "gn:admin2_code":"10.0",
    "gn:asciiname":"La Coma",
    "gn:country_code":"MX",
    "gn:dem":175,
    "gn:feature_class":"P",
    "gn:feature_code":"PPL",
    "gn:name":"La Coma",
    "gn:population":0,
    "gn:timezone":"America/Monterrey",
    "iso:country":"MX",
    "name:spa_x_preferred":[
        "La Coma"
    ],
    "wof:name":"La Coma",
    "wof:placetype":"locality"
},
  "geometry": {"coordinates":[-98.34496,24.4591],"type":"Point"}
}