{
  "type": "Feature",
  "properties": {
    "gn:admin1_code":"25.0",
    "gn:asciiname":"Campo Gallo",
    "gn:country_code":"MX",
    "gn:dem":20,
    "gn:feature_class":"P",
    "gn:feature_code":"PPL",
    "gn:name":"Campo Gallo",
    "gn:population":0,
    "gn:timezone":"America/Mazatlan",
    "iso:country":"MX",
    "name:spa_x_preferred":[
        "Campo Gallo"
    ],
    "wof:name":"Campo Gallo",
    "wof:placetype":"locality"
},
  "geometry": {"coordinates":[-108.89532,25.82597],"type":"Point"}
}