{
  "type": "Feature",
  "properties": {
    "gn:admin1_code":"6",
    "gn:admin2_code":"40.0",
    "gn:asciiname":"Arroyo Amplio",
    "gn:country_code":"MX",
    "gn:dem":1831,
    "gn:feature_class":"P",
    "gn:feature_code":"PPL",
    "gn:name":"Arroyo Amplio",
    "gn:population":0,
    "gn:timezone":"America/Chihuahua",
    "iso:country":"MX",
    "name:spa_x_preferred":[
        "Arroyo Amplio"
    ],
    "wof:name":"Arroyo Amplio",
    "wof:placetype":"locality"
},
  "geometry": {"coordinates":[-108.56534000000001,28.98353],"type":"Point"}
}