{
  "type": "Feature",
  "properties": {
    "gn:admin1_code":"24",
    "gn:admin2_code":"32.0",
    "gn:asciiname":"La Espanita",
    "gn:country_code":"MX",
    "gn:dem":2158,
    "gn:feature_class":"P",
    "gn:feature_code":"PPL",
    "gn:name":"La Espa\u00f1ita",
    "gn:population":6,
    "gn:timezone":"America/Mexico_City",
    "iso:country":"MX",
    "name:und_x_variant":[
        "La Espa\u00f1ita"
    ],
    "wof:name":"La Espanita",
    "wof:placetype":"locality",
    "wof:population":6
},
  "geometry": {"coordinates":[-100.56583000000001,21.87778],"type":"Point"}
}