{
  "type": "Feature",
  "properties": {
    "gn:admin1_code":"26.0",
    "gn:admin2_code":"40.0",
    "gn:asciiname":"Puerto Bonito",
    "gn:country_code":"MX",
    "gn:dem":1849,
    "gn:feature_class":"P",
    "gn:feature_code":"PPL",
    "gn:name":"Puerto Bonito",
    "gn:population":0,
    "gn:timezone":"America/Hermosillo",
    "iso:country":"MX",
    "name:spa_x_preferred":[
        "Puerto Bonito"
    ],
    "wof:name":"Puerto Bonito",
    "wof:placetype":"locality"
},
  "geometry": {"coordinates":[-108.62895,29.92096],"type":"Point"}
}