{
  "type": "Feature",
  "properties": {
    "gn:admin1_code":"19.0",
    "gn:admin2_code":"48.0",
    "gn:asciiname":"Colonia Infonavit la Huasteca",
    "gn:country_code":"MX",
    "gn:dem":681,
    "gn:feature_class":"P",
    "gn:feature_code":"PPL",
    "gn:name":"Colonia Infonavit la Huasteca",
    "gn:population":0,
    "gn:timezone":"America/Monterrey",
    "iso:country":"MX",
    "name:spa_x_preferred":[
        "Colonia Infonavit la Huasteca"
    ],
    "name:spa_x_variant":[
        "Parque ecol\u00f3gico La Huasteca"
    ],
    "name:und_x_variant":[
        "La Huasteca"
    ],
    "wof:name":"Colonia Infonavit la Huasteca",
    "wof:placetype":"locality"
},
  "geometry": {"coordinates":[-100.45108999999999,25.65047],"type":"Point"}
}