{
  "type": "Feature",
  "properties": {
    "gn:admin1_code":"21",
    "gn:admin2_code":"3.0",
    "gn:asciiname":"El Cuajilote",
    "gn:country_code":"MX",
    "gn:dem":1182,
    "gn:feature_class":"P",
    "gn:feature_code":"PPL",
    "gn:name":"El Cuajilote",
    "gn:population":71,
    "gn:timezone":"America/Mexico_City",
    "iso:country":"MX",
    "name:spa_x_preferred":[
        "El Cuajilote"
    ],
    "wof:name":"El Cuajilote",
    "wof:placetype":"locality",
    "wof:population":71
},
  "geometry": {"coordinates":[-98.0372,18.09159],"type":"Point"}
}