{
  "type": "Feature",
  "properties": {
    "gn:admin1_code":"32",
    "gn:admin2_code":"42.0",
    "gn:asciiname":"Alfredo V. Bonfil (Alfredo Bonfil)",
    "gn:country_code":"MX",
    "gn:dem":2332,
    "gn:feature_class":"P",
    "gn:feature_code":"PPL",
    "gn:name":"Alfredo V. Bonfil (Alfredo Bonfil)",
    "gn:population":459,
    "gn:timezone":"America/Mexico_City",
    "iso:country":"MX",
    "wof:name":"Alfredo V. Bonfil (Alfredo Bonfil)",
    "wof:placetype":"locality",
    "wof:population":459
},
  "geometry": {"coordinates":[-103.60666999999999,23.77611],"type":"Point"}
}