{
  "type": "Feature",
  "properties": {
    "gn:admin1_code":"10",
    "gn:admin2_code":"35",
    "gn:asciiname":"Los Bajios",
    "gn:country_code":"MX",
    "gn:dem":2550,
    "gn:feature_class":"P",
    "gn:feature_code":"PPL",
    "gn:name":"Los Baj\u00edos",
    "gn:population":12,
    "gn:timezone":"America/Monterrey",
    "iso:country":"MX",
    "name:spa_x_preferred":[
        "Los Bajios"
    ],
    "name:und_x_variant":[
        "Los Baj\u00edos"
    ],
    "wof:name":"Los Bajios",
    "wof:placetype":"locality",
    "wof:population":12
},
  "geometry": {"coordinates":[-106.32759,25.6663],"type":"Point"}
}