{
  "type": "Feature",
  "properties": {
    "gn:admin1_code":"14.0",
    "gn:admin2_code":"7.0",
    "gn:asciiname":"El Portezuelo",
    "gn:cc2":"MX",
    "gn:country_code":"MX",
    "gn:dem":1421,
    "gn:feature_class":"P",
    "gn:feature_code":"PPL",
    "gn:name":"El Portezuelo",
    "gn:population":0,
    "gn:timezone":"America/Mexico_City",
    "iso:country":"MX",
    "name:spa_x_preferred":[
        "El Portezuelo"
    ],
    "name:und_x_variant":[
        "Portezuelo"
    ],
    "wof:name":"El Portezuelo",
    "wof:placetype":"locality"
},
  "geometry": {"coordinates":[-103.98333,20.83333],"type":"Point"}
}