{
  "type": "Feature",
  "properties": {
    "gn:admin1_code":"22",
    "gn:admin2_code":"8.0",
    "gn:asciiname":"La Trasquila",
    "gn:cc2":"MX",
    "gn:country_code":"MX",
    "gn:dem":2319,
    "gn:feature_class":"P",
    "gn:feature_code":"PPL",
    "gn:name":"La Trasquila",
    "gn:population":1,
    "gn:timezone":"America/Mexico_City",
    "iso:country":"MX",
    "name:und_x_variant":[
        "Trasquilas",
        "Trasquila",
        "La Trasquila"
    ],
    "wof:name":"La Trasquila",
    "wof:placetype":"locality",
    "wof:population":1
},
  "geometry": {"coordinates":[-100.27943999999999,20.36083],"type":"Point"}
}