{
  "type": "Feature",
  "properties": {
    "gn:admin1_code":"32.0",
    "gn:admin2_code":"16.0",
    "gn:asciiname":"El Coleadero",
    "gn:country_code":"MX",
    "gn:dem":2064,
    "gn:feature_class":"P",
    "gn:feature_code":"PPL",
    "gn:name":"El Coleadero",
    "gn:population":0,
    "gn:timezone":"America/Mexico_City",
    "iso:country":"MX",
    "name:spa_x_preferred":[
        "El Coleadero"
    ],
    "wof:name":"El Coleadero",
    "wof:placetype":"locality"
},
  "geometry": {"coordinates":[-102.05911999999999,22.71795],"type":"Point"}
}