{
  "type": "Feature",
  "properties": {
    "gn:admin1_code":"16",
    "gn:admin2_code":"112.0",
    "gn:asciiname":"Ojo de Agua de San Felipe (Primera Manzana)",
    "gn:country_code":"MX",
    "gn:dem":1899,
    "gn:feature_class":"P",
    "gn:feature_code":"PPL",
    "gn:name":"Ojo de Agua de San Felipe (Primera Manzana)",
    "gn:population":118,
    "gn:timezone":"America/Mexico_City",
    "iso:country":"MX",
    "wof:name":"Ojo de Agua de San Felipe (Primera Manzana)",
    "wof:placetype":"locality",
    "wof:population":118
},
  "geometry": {"coordinates":[-100.37806,19.4925],"type":"Point"}
}