{
  "type": "Feature",
  "properties": {
    "gn:admin1_code":"14.0",
    "gn:admin2_code":"26.0",
    "gn:asciiname":"Palos Verdes",
    "gn:country_code":"MX",
    "gn:dem":2173,
    "gn:feature_class":"P",
    "gn:feature_code":"PPL",
    "gn:name":"Palos Verdes",
    "gn:population":0,
    "gn:timezone":"America/Mexico_City",
    "iso:country":"MX",
    "name:spa_x_preferred":[
        "Palos Verdes"
    ],
    "wof:name":"Palos Verdes",
    "wof:placetype":"locality"
},
  "geometry": {"coordinates":[-103.30286,19.96755],"type":"Point"}
}