{
  "type": "Feature",
  "properties": {
    "gn:admin1_code":"20",
    "gn:admin2_code":"41.0",
    "gn:asciiname":"Plan de Basura",
    "gn:country_code":"MX",
    "gn:dem":1386,
    "gn:feature_class":"P",
    "gn:feature_code":"PPL",
    "gn:name":"Plan de Basura",
    "gn:population":170,
    "gn:timezone":"America/Mexico_City",
    "iso:country":"MX",
    "wof:name":"Plan de Basura",
    "wof:placetype":"locality",
    "wof:population":170
},
  "geometry": {"coordinates":[-96.85666999999999,18.13028],"type":"Point"}
}