{
  "type": "Feature",
  "properties": {
    "gn:admin1_code":"28.0",
    "gn:admin2_code":"2.0",
    "gn:asciiname":"Torrecitas",
    "gn:country_code":"MX",
    "gn:dem":133,
    "gn:feature_class":"P",
    "gn:feature_code":"PPL",
    "gn:name":"Torrecitas",
    "gn:population":64,
    "gn:timezone":"America/Monterrey",
    "iso:country":"MX",
    "name:spa_x_preferred":[
        "Torrecitas"
    ],
    "wof:name":"Torrecitas",
    "wof:placetype":"locality",
    "wof:population":64
},
  "geometry": {"coordinates":[-98.05831000000001,23.25965],"type":"Point"}
}