{
  "type": "Feature",
  "properties": {
    "gn:admin1_code":"5.0",
    "gn:admin2_code":"92.0",
    "gn:asciiname":"Reacomodo Nuevo Mexico Kilometro Cincuenta y Nueve",
    "gn:country_code":"MX",
    "gn:dem":246,
    "gn:feature_class":"P",
    "gn:feature_code":"PPL",
    "gn:name":"Reacomodo Nuevo M\u00e9xico Kil\u00f3metro Cincuenta y Nueve",
    "gn:population":0,
    "gn:timezone":"America/Mexico_City",
    "iso:country":"MX",
    "name:spa_x_preferred":[
        "Reacomodo Nuevo M\u00e9xico Kil\u00f3metro Cincuenta y Nueve"
    ],
    "wof:name":"Reacomodo Nuevo Mexico Kilometro Cincuenta y Nueve",
    "wof:placetype":"locality"
},
  "geometry": {"coordinates":[-93.56977000000001,17.26637],"type":"Point"}
}