{
  "type": "Feature",
  "properties": {
    "gn:admin1_code":"32",
    "gn:admin2_code":"9",
    "gn:asciiname":"Chupaderos",
    "gn:country_code":"MX",
    "gn:dem":2201,
    "gn:feature_class":"P",
    "gn:feature_code":"PPL",
    "gn:name":"Chupaderos",
    "gn:population":19,
    "gn:timezone":"America/Mexico_City",
    "iso:country":"MX",
    "wof:name":"Chupaderos",
    "wof:placetype":"locality",
    "wof:population":19
},
  "geometry": {"coordinates":[-103.87860999999999,23.37222],"type":"Point"}
}