{
  "type": "Feature",
  "properties": {
    "gn:admin1_code":"5",
    "gn:admin2_code":"114.0",
    "gn:asciiname":"Sonia Noyola Valencia",
    "gn:country_code":"MX",
    "gn:dem":133,
    "gn:feature_class":"P",
    "gn:feature_code":"PPL",
    "gn:name":"Sonia Noyola Valencia",
    "gn:population":7,
    "gn:timezone":"America/Mexico_City",
    "iso:country":"MX",
    "wof:name":"Sonia Noyola Valencia",
    "wof:placetype":"locality",
    "wof:population":7
},
  "geometry": {"coordinates":[-90.62472,16.45556],"type":"Point"}
}