{
  "type": "Feature",
  "properties": {
    "gn:admin1_code":"20",
    "gn:admin2_code":"509.0",
    "gn:asciiname":"Paso San Antonio",
    "gn:country_code":"MX",
    "gn:dem":229,
    "gn:feature_class":"P",
    "gn:feature_code":"PPL",
    "gn:name":"Paso San Antonio",
    "gn:population":317,
    "gn:timezone":"America/Mexico_City",
    "iso:country":"MX",
    "wof:name":"Paso San Antonio",
    "wof:placetype":"locality",
    "wof:population":317
},
  "geometry": {"coordinates":[-96.65833000000001,15.84694],"type":"Point"}
}