{
  "type": "Feature",
  "properties": {
    "gn:admin1_code":"20",
    "gn:admin2_code":"550.0",
    "gn:asciiname":"San Mateo Macuilxochitl",
    "gn:country_code":"MX",
    "gn:dem":1637,
    "gn:feature_class":"P",
    "gn:feature_code":"PPL",
    "gn:name":"San Mateo Macuilx\u00f3chitl",
    "gn:population":0,
    "gn:timezone":"America/Mexico_City",
    "iso:country":"MX",
    "name:und_x_variant":[
        "Macuilzochil",
        "San Mateo Macuilz\u00f3chitl",
        "Macuilzochitl",
        "San Mateo Macuilx\u00f3chitl"
    ],
    "wof:name":"San Mateo Macuilxochitl",
    "wof:placetype":"locality"
},
  "geometry": {"coordinates":[-96.54082,17.01592999999999],"type":"Point"}
}