{
  "type": "Feature",
  "properties": {
    "gn:admin1_code":"26",
    "gn:admin2_code":"57.0",
    "gn:asciiname":"El Volcancito",
    "gn:country_code":"MX",
    "gn:dem":960,
    "gn:feature_class":"P",
    "gn:feature_code":"PPL",
    "gn:name":"El Volcancito",
    "gn:population":0,
    "gn:timezone":"America/Hermosillo",
    "iso:country":"MX",
    "name:spa_x_preferred":[
        "El Volcancito"
    ],
    "wof:name":"El Volcancito",
    "wof:placetype":"locality"
},
  "geometry": {"coordinates":[-109.77885000000001,29.48009],"type":"Point"}
}