{
  "type": "Feature",
  "properties": {
    "gn:admin1_code":"25",
    "gn:admin2_code":"5.0",
    "gn:asciiname":"El Portezuelo",
    "gn:country_code":"MX",
    "gn:dem":470,
    "gn:feature_class":"P",
    "gn:feature_code":"PPL",
    "gn:name":"El Portezuelo",
    "gn:population":108,
    "gn:timezone":"America/Mazatlan",
    "iso:country":"MX",
    "name:spa_x_preferred":[
        "El Portezuelo"
    ],
    "wof:name":"El Portezuelo",
    "wof:placetype":"locality",
    "wof:population":108
},
  "geometry": {"coordinates":[-106.70583000000001,24.45333],"type":"Point"}
}