{
  "type": "Feature",
  "properties": {
    "gn:admin1_code":"19.0",
    "gn:admin2_code":"5.0",
    "gn:asciiname":"La Margarita",
    "gn:country_code":"MX",
    "gn:dem":249,
    "gn:feature_class":"P",
    "gn:feature_code":"PPL",
    "gn:name":"La Margarita",
    "gn:population":0,
    "gn:timezone":"America/Matamoros",
    "iso:country":"MX",
    "name:spa_x_preferred":[
        "La Margarita"
    ],
    "wof:name":"La Margarita",
    "wof:placetype":"locality"
},
  "geometry": {"coordinates":[-100.02359,27.63589],"type":"Point"}
}