{
  "type": "Feature",
  "properties": {
    "gn:admin1_code":"13",
    "gn:admin2_code":"43.0",
    "gn:asciiname":"Agua Limpia",
    "gn:country_code":"MX",
    "gn:dem":1564,
    "gn:feature_class":"P",
    "gn:feature_code":"PPL",
    "gn:name":"Agua Limpia",
    "gn:population":0,
    "gn:timezone":"America/Mexico_City",
    "iso:country":"MX",
    "name:spa_x_preferred":[
        "Agua Limpia"
    ],
    "wof:name":"Agua Limpia",
    "wof:placetype":"locality"
},
  "geometry": {"coordinates":[-99.12815999999999,20.79003],"type":"Point"}
}