{
  "type": "Feature",
  "properties": {
    "gn:admin1_code":"25.0",
    "gn:asciiname":"Kilometro Veinticinco",
    "gn:country_code":"MX",
    "gn:dem":26,
    "gn:feature_class":"P",
    "gn:feature_code":"PPL",
    "gn:name":"Kil\u00f3metro Veinticinco",
    "gn:population":0,
    "gn:timezone":"America/Mazatlan",
    "iso:country":"MX",
    "name:spa_x_preferred":[
        "Kil\u00f3metro Veinticinco"
    ],
    "wof:name":"Kilometro Veinticinco",
    "wof:placetype":"locality"
},
  "geometry": {"coordinates":[-108.81404999999999,25.8849],"type":"Point"}
}