{
  "type": "Feature",
  "properties": {
    "gn:admin1_code":"23",
    "gn:admin2_code":"6.0",
    "gn:asciiname":"Colmenitas",
    "gn:country_code":"MX",
    "gn:dem":93,
    "gn:feature_class":"P",
    "gn:feature_code":"PPL",
    "gn:name":"Colmenitas",
    "gn:population":40,
    "gn:timezone":"America/Cancun",
    "iso:country":"MX",
    "name:spa_x_preferred":[
        "Colmenitas"
    ],
    "wof:name":"Colmenitas",
    "wof:placetype":"locality",
    "wof:population":40
},
  "geometry": {"coordinates":[-88.7778,19.50433],"type":"Point"}
}