{
  "type": "Feature",
  "properties": {
    "gn:admin1_code":"27.0",
    "gn:asciiname":"La Villa",
    "gn:country_code":"MX",
    "gn:dem":56,
    "gn:feature_class":"P",
    "gn:feature_code":"PPL",
    "gn:name":"La Villa",
    "gn:population":0,
    "gn:timezone":"America/Mexico_City",
    "iso:country":"MX",
    "name:spa_x_preferred":[
        "La Villa"
    ],
    "wof:name":"La Villa",
    "wof:placetype":"locality"
},
  "geometry": {"coordinates":[-91.64239000000001,17.70641],"type":"Point"}
}