{
  "type": "Feature",
  "properties": {
    "gn:admin1_code":"14.0",
    "gn:admin2_code":"123.0",
    "gn:asciiname":"Chila",
    "gn:country_code":"MX",
    "gn:dem":1558,
    "gn:feature_class":"P",
    "gn:feature_code":"PPL",
    "gn:name":"Chila",
    "gn:population":0,
    "gn:timezone":"America/Mexico_City",
    "iso:country":"MX",
    "name:ceb_x_preferred":[
        "Chila"
    ],
    "name:deu_x_preferred":[
        "Chila"
    ],
    "name:spa_x_preferred":[
        "Chila"
    ],
    "name:swe_x_preferred":[
        "Chila"
    ],
    "name:und_x_variant":[
        "La Chila"
    ],
    "name:vie_x_preferred":[
        "Chila"
    ],
    "wof:name":"Chila",
    "wof:placetype":"locality"
},
  "geometry": {"coordinates":[-102.97038999999999,20.46078],"type":"Point"}
}