{
  "type": "Feature",
  "properties": {
    "gn:admin1_code":"6.0",
    "gn:asciiname":"Yonque",
    "gn:country_code":"MX",
    "gn:dem":1170,
    "gn:feature_class":"P",
    "gn:feature_code":"PPL",
    "gn:name":"Yonque",
    "gn:population":0,
    "gn:timezone":"America/Chihuahua",
    "iso:country":"MX",
    "name:spa_x_preferred":[
        "Yonque"
    ],
    "wof:name":"Yonque",
    "wof:placetype":"locality"
},
  "geometry": {"coordinates":[-105.45643,28.22092],"type":"Point"}
}