{
  "type": "Feature",
  "properties": {
    "gn:admin1_code":"30",
    "gn:admin2_code":"160.0",
    "gn:asciiname":"Rancho El Ciruelo",
    "gn:country_code":"MX",
    "gn:dem":50,
    "gn:feature_class":"P",
    "gn:feature_code":"PPL",
    "gn:name":"Rancho El Ciruelo",
    "gn:population":0,
    "gn:timezone":"America/Mexico_City",
    "iso:country":"MX",
    "name:spa_x_preferred":[
        "Rancho El Ciruelo"
    ],
    "wof:name":"Rancho El Ciruelo",
    "wof:placetype":"locality"
},
  "geometry": {"coordinates":[-97.77290000000001,20.9586],"type":"Point"}
}