{
  "type": "Feature",
  "properties": {
    "gn:admin1_code":"7.0",
    "gn:admin2_code":"20.0",
    "gn:asciiname":"Chupadero",
    "gn:country_code":"MX",
    "gn:dem":540,
    "gn:feature_class":"P",
    "gn:feature_code":"PPL",
    "gn:name":"Chupadero",
    "gn:population":0,
    "gn:timezone":"America/Monterrey",
    "iso:country":"MX",
    "wof:name":"Chupadero",
    "wof:placetype":"locality"
},
  "geometry": {"coordinates":[-101.76667,28.06667],"type":"Point"}
}