{
  "type": "Feature",
  "properties": {
    "gn:admin1_code":"13",
    "gn:admin2_code":"77.0",
    "gn:asciiname":"Pedregal de San Jose",
    "gn:country_code":"MX",
    "gn:dem":2179,
    "gn:feature_class":"P",
    "gn:feature_code":"PPL",
    "gn:name":"Pedregal de San Jos\u00e9",
    "gn:population":0,
    "gn:timezone":"America/Mexico_City",
    "iso:country":"MX",
    "name:spa_x_preferred":[
        "Pedregal San Jos\u00e9"
    ],
    "name:spa_x_variant":[
        "Pedregal de San Jos\u00e9"
    ],
    "wof:name":"Pedregal de San Jose",
    "wof:placetype":"locality"
},
  "geometry": {"coordinates":[-98.40703000000001,20.06616],"type":"Point"}
}