{
  "type": "Feature",
  "properties": {
    "gn:admin1_code":"6.0",
    "gn:admin2_code":"51.0",
    "gn:asciiname":"El Pinito",
    "gn:country_code":"MX",
    "gn:dem":1591,
    "gn:feature_class":"P",
    "gn:feature_code":"PPL",
    "gn:name":"El Pinito",
    "gn:population":0,
    "gn:timezone":"America/Chihuahua",
    "iso:country":"MX",
    "name:spa_x_preferred":[
        "El Pinito"
    ],
    "wof:name":"El Pinito",
    "wof:placetype":"locality"
},
  "geometry": {"coordinates":[-108.44996999999999,28.19004],"type":"Point"}
}