{
  "type": "Feature",
  "properties": {
    "gn:admin1_code":"25",
    "gn:admin2_code":"6.0",
    "gn:asciiname":"Campo Maralena",
    "gn:country_code":"MX",
    "gn:dem":46,
    "gn:feature_class":"P",
    "gn:feature_code":"PPL",
    "gn:name":"Campo Maralena",
    "gn:population":0,
    "gn:timezone":"America/Mazatlan",
    "iso:country":"MX",
    "name:spa_x_preferred":[
        "Campo Maralena"
    ],
    "wof:name":"Campo Maralena",
    "wof:placetype":"locality"
},
  "geometry": {"coordinates":[-107.53267,24.86951],"type":"Point"}
}