{
  "type": "Feature",
  "properties": {
    "gn:admin1_code":"21",
    "gn:admin2_code":"193.0",
    "gn:asciiname":"San Jose Texaluca",
    "gn:country_code":"MX",
    "gn:dem":2120,
    "gn:feature_class":"P",
    "gn:feature_code":"PPL",
    "gn:name":"San Jos\u00e9 Texaluca",
    "gn:population":776,
    "gn:timezone":"America/Mexico_City",
    "iso:country":"MX",
    "name:und_x_variant":[
        "San Jos\u00e9 Texaluca"
    ],
    "wof:name":"San Jose Texaluca",
    "wof:placetype":"locality",
    "wof:population":776
},
  "geometry": {"coordinates":[-98.13222,18.8975],"type":"Point"}
}