{
  "type": "Feature",
  "properties": {
    "gn:admin1_code":"30",
    "gn:admin2_code":"142.0",
    "gn:asciiname":"Tachicon",
    "gn:cc2":"MX",
    "gn:country_code":"MX",
    "gn:dem":49,
    "gn:feature_class":"P",
    "gn:feature_code":"PPL",
    "gn:name":"Tachic\u00f3n",
    "gn:population":12,
    "gn:timezone":"America/Mexico_City",
    "iso:country":"MX",
    "name:und_x_variant":[
        "Tachic\u00e1n"
    ],
    "wof:name":"Tachicon",
    "wof:placetype":"locality",
    "wof:population":12
},
  "geometry": {"coordinates":[-95.19611,17.82528],"type":"Point"}
}