{
  "type": "Feature",
  "properties": {
    "gn:admin1_code":"15",
    "gn:admin2_code":"26.0",
    "gn:asciiname":"Dhalle (Ejido de Dongu)",
    "gn:country_code":"MX",
    "gn:dem":2645,
    "gn:feature_class":"P",
    "gn:feature_code":"PPL",
    "gn:name":"Dhalle (Ejido de Dongu)",
    "gn:population":179,
    "gn:timezone":"America/Mexico_City",
    "iso:country":"MX",
    "wof:name":"Dhalle (Ejido de Dongu)",
    "wof:placetype":"locality",
    "wof:population":179
},
  "geometry": {"coordinates":[-99.58417,19.86194],"type":"Point"}
}