{
  "type": "Feature",
  "properties": {
    "gn:admin1_code":"19",
    "gn:admin2_code":"13.0",
    "gn:asciiname":"Las Blanquitas",
    "gn:country_code":"MX",
    "gn:dem":105,
    "gn:feature_class":"P",
    "gn:feature_code":"PPL",
    "gn:name":"Las Blanquitas",
    "gn:population":7,
    "gn:timezone":"America/Monterrey",
    "iso:country":"MX",
    "wof:name":"Las Blanquitas",
    "wof:placetype":"locality",
    "wof:population":7
},
  "geometry": {"coordinates":[-98.70417,25.41556],"type":"Point"}
}