{
  "type": "Feature",
  "properties": {
    "gn:admin1_code":"21",
    "gn:asciiname":"El Viudon",
    "gn:country_code":"MX",
    "gn:dem":84,
    "gn:feature_class":"P",
    "gn:feature_code":"PPL",
    "gn:name":"El Viud\u00f3n",
    "gn:population":0,
    "gn:timezone":"America/Mexico_City",
    "iso:country":"MX",
    "name:spa_x_preferred":[
        "El Viud\u00f3n"
    ],
    "wof:name":"El Viudon",
    "wof:placetype":"locality"
},
  "geometry": {"coordinates":[-97.2513,20.19933],"type":"Point"}
}