{
  "type": "Feature",
  "properties": {
    "gn:admin1_code":"17",
    "gn:admin2_code":"29.0",
    "gn:asciiname":"Kilometro 32",
    "gn:country_code":"MX",
    "gn:dem":1252,
    "gn:feature_class":"P",
    "gn:feature_code":"PPL",
    "gn:name":"Kil\u00f3metro 32",
    "gn:population":123,
    "gn:timezone":"America/Mexico_City",
    "iso:country":"MX",
    "name:und_x_variant":[
        "Kil\u00f3metro 32"
    ],
    "wof:name":"Kilometro 32",
    "wof:placetype":"locality",
    "wof:population":123
},
  "geometry": {"coordinates":[-99.01806000000001,18.89278],"type":"Point"}
}