{
  "type": "Feature",
  "properties": {
    "gn:admin1_code":"7.0",
    "gn:admin2_code":"14.0",
    "gn:asciiname":"El Divisadero",
    "gn:country_code":"MX",
    "gn:dem":344,
    "gn:feature_class":"P",
    "gn:feature_code":"PPL",
    "gn:name":"El Divisadero",
    "gn:population":0,
    "gn:timezone":"America/Monterrey",
    "iso:country":"MX",
    "name:und_x_variant":[
        "Rancho El Divisadero",
        "El Divisadero"
    ],
    "wof:name":"El Divisadero",
    "wof:placetype":"locality"
},
  "geometry": {"coordinates":[-100.97029000000001,29.15975],"type":"Point"}
}