{
  "type": "Feature",
  "properties": {
    "gn:admin1_code":"14",
    "gn:admin2_code":"67",
    "gn:asciiname":"Las Higueras del Hundido",
    "gn:country_code":"MX",
    "gn:dem":627,
    "gn:feature_class":"P",
    "gn:feature_code":"PPL",
    "gn:name":"Las Higueras del Hundido",
    "gn:population":12,
    "gn:timezone":"America/Mexico_City",
    "iso:country":"MX",
    "wof:name":"Las Higueras del Hundido",
    "wof:placetype":"locality",
    "wof:population":12
},
  "geometry": {"coordinates":[-105.14972,20.585],"type":"Point"}
}