{
  "type": "Feature",
  "properties": {
    "gn:admin1_code":"28",
    "gn:admin2_code":"10.0",
    "gn:asciiname":"Las Enramadas",
    "gn:country_code":"MX",
    "gn:dem":279,
    "gn:feature_class":"P",
    "gn:feature_code":"PPL",
    "gn:name":"Las Enramadas",
    "gn:population":0,
    "gn:timezone":"America/Monterrey",
    "iso:country":"MX",
    "name:spa_x_preferred":[
        "Las Enramadas"
    ],
    "name:und_x_variant":[
        "Rancho Las Enramadas"
    ],
    "wof:name":"Las Enramadas",
    "wof:placetype":"locality"
},
  "geometry": {"coordinates":[-98.62533999999999,24.80578],"type":"Point"}
}