{
  "type": "Feature",
  "properties": {
    "gn:admin1_code":"3",
    "gn:admin2_code":"1.0",
    "gn:asciiname":"San Cipriano",
    "gn:country_code":"MX",
    "gn:dem":194,
    "gn:feature_class":"P",
    "gn:feature_code":"PPL",
    "gn:name":"San Cipriano",
    "gn:population":5,
    "gn:timezone":"America/Mazatlan",
    "iso:country":"MX",
    "wof:name":"San Cipriano",
    "wof:placetype":"locality",
    "wof:population":5
},
  "geometry": {"coordinates":[-111.38061,25.35339],"type":"Point"}
}