{
  "type": "Feature",
  "properties": {
    "gn:admin1_code":"10",
    "gn:admin2_code":"26.0",
    "gn:asciiname":"Las Camichinas",
    "gn:country_code":"MX",
    "gn:dem":1362,
    "gn:feature_class":"P",
    "gn:feature_code":"PPL",
    "gn:name":"Las Camichinas",
    "gn:population":4,
    "gn:timezone":"America/Monterrey",
    "iso:country":"MX",
    "wof:name":"Las Camichinas",
    "wof:placetype":"locality",
    "wof:population":4
},
  "geometry": {"coordinates":[-105.67641,23.95001],"type":"Point"}
}