{
  "type": "Feature",
  "properties": {
    "gn:admin1_code":"12",
    "gn:admin2_code":"32",
    "gn:asciiname":"Rancho la Gloria",
    "gn:country_code":"MX",
    "gn:dem":1538,
    "gn:feature_class":"P",
    "gn:feature_code":"PPL",
    "gn:name":"Rancho la Gloria",
    "gn:population":9,
    "gn:timezone":"America/Mexico_City",
    "iso:country":"MX",
    "wof:name":"Rancho la Gloria",
    "wof:placetype":"locality",
    "wof:population":9
},
  "geometry": {"coordinates":[-99.8531,17.87107],"type":"Point"}
}