{
  "type": "Feature",
  "properties": {
    "gn:admin1_code":"15",
    "gn:admin2_code":"85.0",
    "gn:asciiname":"Barrio de Corona",
    "gn:country_code":"MX",
    "gn:dem":2518,
    "gn:feature_class":"P",
    "gn:feature_code":"PPL",
    "gn:name":"Barrio de Corona",
    "gn:population":508,
    "gn:timezone":"America/Mexico_City",
    "iso:country":"MX",
    "wof:name":"Barrio de Corona",
    "wof:placetype":"locality",
    "wof:population":508
},
  "geometry": {"coordinates":[-99.99111000000001,19.90528],"type":"Point"}
}