{
  "type": "Feature",
  "properties": {
    "gn:admin1_code":"19.0",
    "gn:asciiname":"San Paulo",
    "gn:country_code":"MX",
    "gn:dem":366,
    "gn:feature_class":"P",
    "gn:feature_code":"PPL",
    "gn:name":"San Paulo",
    "gn:population":0,
    "gn:timezone":"America/Monterrey",
    "iso:country":"MX",
    "name:spa_x_preferred":[
        "San Paulo"
    ],
    "wof:name":"San Paulo",
    "wof:placetype":"locality"
},
  "geometry": {"coordinates":[-99.52813999999999,24.83278],"type":"Point"}
}