{
  "type": "Feature",
  "properties": {
    "gn:admin1_code":"6",
    "gn:admin2_code":"27.0",
    "gn:asciiname":"Rehuisuchi",
    "gn:country_code":"MX",
    "gn:dem":2253,
    "gn:feature_class":"P",
    "gn:feature_code":"PPL",
    "gn:name":"Rehuisuchi",
    "gn:population":0,
    "gn:timezone":"America/Chihuahua",
    "iso:country":"MX",
    "name:spa_x_preferred":[
        "Arroyo Colorados"
    ],
    "name:spa_x_variant":[
        "Rehuisuchi"
    ],
    "wof:name":"Rehuisuchi",
    "wof:placetype":"locality"
},
  "geometry": {"coordinates":[-107.50785,27.52397],"type":"Point"}
}