{
  "type": "Feature",
  "properties": {
    "gn:admin1_code":"24",
    "gn:admin2_code":"50.0",
    "gn:asciiname":"Rancho el Porvenir",
    "gn:country_code":"MX",
    "gn:dem":1811,
    "gn:feature_class":"P",
    "gn:feature_code":"PPL",
    "gn:name":"Rancho el Porvenir",
    "gn:population":7,
    "gn:timezone":"America/Mexico_City",
    "iso:country":"MX",
    "wof:name":"Rancho el Porvenir",
    "wof:placetype":"locality",
    "wof:population":7
},
  "geometry": {"coordinates":[-100.88527999999999,21.90972],"type":"Point"}
}