{
  "type": "Feature",
  "properties": {
    "gn:admin1_code":"12",
    "gn:admin2_code":"68.0",
    "gn:asciiname":"Estero Salado",
    "gn:country_code":"MX",
    "gn:dem":22,
    "gn:feature_class":"P",
    "gn:feature_code":"PPL",
    "gn:name":"Estero Salado",
    "gn:population":0,
    "gn:timezone":"America/Mexico_City",
    "iso:country":"MX",
    "name:spa_x_preferred":[
        "Estero Salado"
    ],
    "name:und_x_variant":[
        "Salado"
    ],
    "wof:name":"Estero Salado",
    "wof:placetype":"locality"
},
  "geometry": {"coordinates":[-101.78042000000001,17.87617999999999],"type":"Point"}
}