{
  "type": "Feature",
  "properties": {
    "gn:admin1_code":"2.0",
    "gn:admin2_code":"1.0",
    "gn:asciiname":"Junco",
    "gn:cc2":"MX",
    "gn:country_code":"MX",
    "gn:dem":537,
    "gn:feature_class":"P",
    "gn:feature_code":"PPL",
    "gn:name":"Junco",
    "gn:population":0,
    "gn:timezone":"America/Tijuana",
    "iso:country":"MX",
    "name:und_x_variant":[
        "Juncos",
        "Junco"
    ],
    "wof:name":"Junco",
    "wof:placetype":"locality"
},
  "geometry": {"coordinates":[-114.56667,29.95],"type":"Point"}
}