{
  "type": "Feature",
  "properties": {
    "gn:admin1_code":"14",
    "gn:admin2_code":"33.0",
    "gn:asciiname":"Barbechitos (Barbechos)",
    "gn:country_code":"MX",
    "gn:dem":1795,
    "gn:feature_class":"P",
    "gn:feature_code":"PPL",
    "gn:name":"Barbechitos (Barbechos)",
    "gn:population":68,
    "gn:timezone":"America/Mexico_City",
    "iso:country":"MX",
    "wof:name":"Barbechitos (Barbechos)",
    "wof:placetype":"locality",
    "wof:population":68
},
  "geometry": {"coordinates":[-102.11639,20.52333],"type":"Point"}
}