{
  "type": "Feature",
  "properties": {
    "gn:admin1_code":"30.0",
    "gn:asciiname":"El Capricho",
    "gn:country_code":"MX",
    "gn:dem":51,
    "gn:feature_class":"P",
    "gn:feature_code":"PPL",
    "gn:name":"El Capricho",
    "gn:population":0,
    "gn:timezone":"America/Mexico_City",
    "iso:country":"MX",
    "name:spa_x_preferred":[
        "El Capricho"
    ],
    "wof:name":"El Capricho",
    "wof:placetype":"locality"
},
  "geometry": {"coordinates":[-95.76779000000001,17.8851],"type":"Point"}
}