{
  "type": "Feature",
  "properties": {
    "gn:admin1_code":"14",
    "gn:admin2_code":"8.0",
    "gn:asciiname":"Las Joyas (Hacienda de los Torres)",
    "gn:country_code":"MX",
    "gn:dem":2052,
    "gn:feature_class":"P",
    "gn:feature_code":"PPL",
    "gn:name":"Las Joyas (Hacienda de los Torres)",
    "gn:population":6,
    "gn:timezone":"America/Mexico_City",
    "iso:country":"MX",
    "wof:name":"Las Joyas (Hacienda de los Torres)",
    "wof:placetype":"locality",
    "wof:population":6
},
  "geometry": {"coordinates":[-102.38500000000001,20.72972],"type":"Point"}
}