{
  "type": "Feature",
  "properties": {
    "gn:admin1_code":"5",
    "gn:admin2_code":"15.0",
    "gn:asciiname":"24 de Junio (La Gallera)",
    "gn:country_code":"MX",
    "gn:dem":616,
    "gn:feature_class":"P",
    "gn:feature_code":"PPL",
    "gn:name":"24 de Junio (La Gallera)",
    "gn:population":74,
    "gn:timezone":"America/Mexico_City",
    "iso:country":"MX",
    "wof:name":"24 de Junio (La Gallera)",
    "wof:placetype":"locality",
    "wof:population":74
},
  "geometry": {"coordinates":[-92.20056,15.04778],"type":"Point"}
}