{
  "type": "Feature",
  "properties": {
    "gn:admin1_code":"24",
    "gn:admin2_code":"25",
    "gn:asciiname":"Laguna el Marrano",
    "gn:country_code":"MX",
    "gn:dem":2037,
    "gn:feature_class":"P",
    "gn:feature_code":"PPL",
    "gn:name":"Laguna el Marrano",
    "gn:population":32,
    "gn:timezone":"America/Mexico_City",
    "iso:country":"MX",
    "wof:name":"Laguna el Marrano",
    "wof:placetype":"locality",
    "wof:population":32
},
  "geometry": {"coordinates":[-101.60889,22.76139],"type":"Point"}
}