{
  "type": "Feature",
  "properties": {
    "gn:admin1_code":"5",
    "gn:admin2_code":"5.0",
    "gn:asciiname":"San Miguel 3 Picos",
    "gn:country_code":"MX",
    "gn:dem":744,
    "gn:feature_class":"P",
    "gn:feature_code":"PPL",
    "gn:name":"San Miguel 3 Picos",
    "gn:population":213,
    "gn:timezone":"America/Mexico_City",
    "iso:country":"MX",
    "wof:name":"San Miguel 3 Picos",
    "wof:placetype":"locality",
    "wof:population":213
},
  "geometry": {"coordinates":[-92.8625,17.32278],"type":"Point"}
}