{
  "type": "Feature",
  "properties": {
    "gn:admin1_code":"5.0",
    "gn:asciiname":"El Quelite",
    "gn:country_code":"MX",
    "gn:dem":6,
    "gn:feature_class":"P",
    "gn:feature_code":"PPL",
    "gn:name":"El Quelite",
    "gn:population":0,
    "gn:timezone":"America/Mexico_City",
    "iso:country":"MX",
    "name:spa_x_preferred":[
        "El Quelite"
    ],
    "wof:name":"El Quelite",
    "wof:placetype":"locality"
},
  "geometry": {"coordinates":[-93.59804,15.81796],"type":"Point"}
}