{
  "type": "Feature",
  "properties": {
    "gn:admin1_code":"30",
    "gn:admin2_code":"121.0",
    "gn:asciiname":"La Semilla",
    "gn:country_code":"MX",
    "gn:dem":46,
    "gn:feature_class":"P",
    "gn:feature_code":"PPL",
    "gn:name":"La Semilla",
    "gn:population":2,
    "gn:timezone":"America/Mexico_City",
    "iso:country":"MX",
    "name:spa_x_preferred":[
        "La Semilla"
    ],
    "wof:name":"La Semilla",
    "wof:placetype":"locality",
    "wof:population":2
},
  "geometry": {"coordinates":[-97.93219999999999,21.74261],"type":"Point"}
}