{
  "type": "Feature",
  "properties": {
    "gn:admin1_code":"19.0",
    "gn:admin2_code":"50.0",
    "gn:asciiname":"Labor Grande",
    "gn:country_code":"MX",
    "gn:dem":238,
    "gn:feature_class":"P",
    "gn:feature_code":"PPL",
    "gn:name":"Labor Grande",
    "gn:population":0,
    "gn:timezone":"America/Monterrey",
    "iso:country":"MX",
    "name:spa_x_preferred":[
        "Labor Grande"
    ],
    "wof:name":"Labor Grande",
    "wof:placetype":"locality"
},
  "geometry": {"coordinates":[-99.89328,26.41404],"type":"Point"}
}