{
  "type": "Feature",
  "properties": {
    "gn:admin1_code":"10",
    "gn:admin2_code":"19",
    "gn:asciiname":"El Polvorin",
    "gn:country_code":"MX",
    "gn:dem":2244,
    "gn:feature_class":"P",
    "gn:feature_code":"PPL",
    "gn:name":"El Polvor\u00edn",
    "gn:population":9,
    "gn:timezone":"America/Monterrey",
    "iso:country":"MX",
    "name:und_x_variant":[
        "El Polvor\u00edn"
    ],
    "wof:name":"El Polvorin",
    "wof:placetype":"locality",
    "wof:population":9
},
  "geometry": {"coordinates":[-106.21523999999999,24.67063],"type":"Point"}
}