{
  "type": "Feature",
  "properties": {
    "gn:admin1_code":"30",
    "gn:admin2_code":"83.0",
    "gn:asciiname":"Chapopote",
    "gn:country_code":"MX",
    "gn:dem":366,
    "gn:feature_class":"P",
    "gn:feature_code":"PPL",
    "gn:name":"Chapopote",
    "gn:population":365,
    "gn:timezone":"America/Mexico_City",
    "iso:country":"MX",
    "name:spa_x_preferred":[
        "Chapopote"
    ],
    "wof:name":"Chapopote",
    "wof:placetype":"locality",
    "wof:population":365
},
  "geometry": {"coordinates":[-97.99361,20.85083],"type":"Point"}
}