{
  "type": "Feature",
  "properties": {
    "gn:admin1_code":"6",
    "gn:admin2_code":"17.0",
    "gn:asciiname":"Alvaro Obregon",
    "gn:country_code":"MX",
    "gn:dem":2069,
    "gn:feature_class":"P",
    "gn:feature_code":"PPL",
    "gn:name":"\u00c1lvaro Obreg\u00f3n",
    "gn:population":0,
    "gn:timezone":"America/Chihuahua",
    "iso:country":"MX",
    "wof:name":"Alvaro Obregon",
    "wof:placetype":"locality"
},
  "geometry": {"coordinates":[-106.86667,28.75],"type":"Point"}
}