{
  "type": "Feature",
  "properties": {
    "gn:admin1_code":"11",
    "gn:admin2_code":"17.0",
    "gn:asciiname":"Camino Real de lo de Juarez",
    "gn:country_code":"MX",
    "gn:dem":1732,
    "gn:feature_class":"P",
    "gn:feature_code":"PPL",
    "gn:name":"Camino Real de lo de Ju\u00e1rez",
    "gn:population":8,
    "gn:timezone":"America/Mexico_City",
    "iso:country":"MX",
    "name:und_x_variant":[
        "Camino Real de lo de Ju\u00e1rez"
    ],
    "wof:name":"Camino Real de lo de Juarez",
    "wof:placetype":"locality",
    "wof:population":8
},
  "geometry": {"coordinates":[-101.36806,20.71639],"type":"Point"}
}