{
  "type": "Feature",
  "properties": {
    "gn:admin1_code":"28",
    "gn:admin2_code":"16.0",
    "gn:asciiname":"San Juana",
    "gn:country_code":"MX",
    "gn:dem":365,
    "gn:feature_class":"P",
    "gn:feature_code":"PPL",
    "gn:name":"San Juana",
    "gn:population":0,
    "gn:timezone":"America/Monterrey",
    "iso:country":"MX",
    "name:spa_x_preferred":[
        "San Juana"
    ],
    "name:und_x_variant":[
        "La San Juana"
    ],
    "wof:name":"San Juana",
    "wof:placetype":"locality"
},
  "geometry": {"coordinates":[-99.48889,24.27293],"type":"Point"}
}