{
  "type": "Feature",
  "properties": {
    "gn:admin1_code":"25",
    "gn:admin2_code":"7",
    "gn:asciiname":"El Sauz",
    "gn:country_code":"MX",
    "gn:dem":877,
    "gn:feature_class":"P",
    "gn:feature_code":"PPL",
    "gn:name":"El Sauz",
    "gn:population":42,
    "gn:timezone":"America/Mazatlan",
    "iso:country":"MX",
    "wof:name":"El Sauz",
    "wof:placetype":"locality",
    "wof:population":42
},
  "geometry": {"coordinates":[-108.09811999999999,26.74251],"type":"Point"}
}