{
  "type": "Feature",
  "properties": {
    "gn:admin1_code":"5",
    "gn:admin2_code":"2.0",
    "gn:asciiname":"San Jose de Jesus",
    "gn:country_code":"MX",
    "gn:dem":578,
    "gn:feature_class":"P",
    "gn:feature_code":"PPL",
    "gn:name":"San Jos\u00e9 de Jes\u00fas",
    "gn:population":90,
    "gn:timezone":"America/Mexico_City",
    "iso:country":"MX",
    "name:und_x_variant":[
        "San Jos\u00e9 de Jes\u00fas"
    ],
    "wof:name":"San Jose de Jesus",
    "wof:placetype":"locality",
    "wof:population":90
},
  "geometry": {"coordinates":[-92.81305999999999,16.44333],"type":"Point"}
}