{
  "type": "Feature",
  "properties": {
    "gn:admin1_code":"12",
    "gn:admin2_code":"76.0",
    "gn:asciiname":"Cerro Tigre (Cerro del Tigre)",
    "gn:country_code":"MX",
    "gn:dem":1664,
    "gn:feature_class":"P",
    "gn:feature_code":"PPL",
    "gn:name":"Cerro Tigre (Cerro del Tigre)",
    "gn:population":349,
    "gn:timezone":"America/Mexico_City",
    "iso:country":"MX",
    "wof:name":"Cerro Tigre (Cerro del Tigre)",
    "wof:placetype":"locality",
    "wof:population":349
},
  "geometry": {"coordinates":[-98.97598000000001,17.25757999999999],"type":"Point"}
}