{
  "type": "Feature",
  "properties": {
    "gn:admin1_code":"28.0",
    "gn:admin2_code":"37.0",
    "gn:asciiname":"El Chito",
    "gn:country_code":"MX",
    "gn:dem":46,
    "gn:feature_class":"P",
    "gn:feature_code":"PPL",
    "gn:name":"El Chito",
    "gn:population":3,
    "gn:timezone":"America/Monterrey",
    "iso:country":"MX",
    "name:spa_x_preferred":[
        "El Chito"
    ],
    "wof:name":"El Chito",
    "wof:placetype":"locality",
    "wof:population":3
},
  "geometry": {"coordinates":[-97.90778,23.95056],"type":"Point"}
}