{
  "type": "Feature",
  "properties": {
    "gn:admin1_code":"20",
    "gn:admin2_code":"318.0",
    "gn:asciiname":"La Cofradia",
    "gn:country_code":"MX",
    "gn:dem":362,
    "gn:feature_class":"P",
    "gn:feature_code":"PPL",
    "gn:name":"La Cofrad\u00eda",
    "gn:population":5,
    "gn:timezone":"America/Mexico_City",
    "iso:country":"MX",
    "name:und_x_variant":[
        "La Cofrad\u00eda"
    ],
    "wof:name":"La Cofradia",
    "wof:placetype":"locality",
    "wof:population":5
},
  "geometry": {"coordinates":[-97.03888999999999,15.96861],"type":"Point"}
}