{
  "type": "Feature",
  "properties": {
    "gn:admin1_code":"26",
    "gn:admin2_code":"51.0",
    "gn:asciiname":"Santa Ana de Padilla",
    "gn:country_code":"MX",
    "gn:dem":456,
    "gn:feature_class":"P",
    "gn:feature_code":"PPL",
    "gn:name":"Santa Ana de Padilla",
    "gn:population":12,
    "gn:timezone":"America/Hermosillo",
    "iso:country":"MX",
    "wof:name":"Santa Ana de Padilla",
    "wof:placetype":"locality",
    "wof:population":12
},
  "geometry": {"coordinates":[-109.38,27.75806],"type":"Point"}
}