{
  "type": "Feature",
  "properties": {
    "gn:admin1_code":"6",
    "gn:admin2_code":"29",
    "gn:asciiname":"Pino Gordo",
    "gn:country_code":"MX",
    "gn:dem":2630,
    "gn:feature_class":"P",
    "gn:feature_code":"PPL",
    "gn:name":"Pino Gordo",
    "gn:population":18,
    "gn:timezone":"America/Chihuahua",
    "iso:country":"MX",
    "wof:name":"Pino Gordo",
    "wof:placetype":"locality",
    "wof:population":18
},
  "geometry": {"coordinates":[-106.97318,25.91301],"type":"Point"}
}