{
  "type": "Feature",
  "properties": {
    "gn:admin1_code":"16",
    "gn:admin2_code":"38",
    "gn:asciiname":"Piriticuaro",
    "gn:country_code":"MX",
    "gn:dem":364,
    "gn:feature_class":"P",
    "gn:feature_code":"PPL",
    "gn:name":"Pirit\u00edcuaro",
    "gn:population":37,
    "gn:timezone":"America/Mexico_City",
    "iso:country":"MX",
    "name:und_x_variant":[
        "Pirit\u00edcuaro"
    ],
    "wof:name":"Piriticuaro",
    "wof:placetype":"locality",
    "wof:population":37
},
  "geometry": {"coordinates":[-100.88833,18.68083],"type":"Point"}
}