{
  "type": "Feature",
  "properties": {
    "gn:admin1_code":"5",
    "gn:admin2_code":"5.0",
    "gn:asciiname":"Los Olivares",
    "gn:country_code":"MX",
    "gn:dem":254,
    "gn:feature_class":"P",
    "gn:feature_code":"PPL",
    "gn:name":"Los Olivares",
    "gn:population":130,
    "gn:timezone":"America/Mexico_City",
    "iso:country":"MX",
    "wof:name":"Los Olivares",
    "wof:placetype":"locality",
    "wof:population":130
},
  "geometry": {"coordinates":[-92.76667,17.35611],"type":"Point"}
}