{
  "type": "Feature",
  "properties": {
    "gn:admin1_code":"15",
    "gn:admin2_code":"80.0",
    "gn:asciiname":"Barrio la Laguna",
    "gn:country_code":"MX",
    "gn:dem":1491,
    "gn:feature_class":"P",
    "gn:feature_code":"PPL",
    "gn:name":"Barrio la Laguna",
    "gn:population":200,
    "gn:timezone":"America/Mexico_City",
    "iso:country":"MX",
    "wof:name":"Barrio la Laguna",
    "wof:placetype":"locality",
    "wof:population":200
},
  "geometry": {"coordinates":[-100.02618,18.81522],"type":"Point"}
}