{
  "type": "Feature",
  "properties": {
    "gn:admin1_code":"31",
    "gn:admin2_code":"96.0",
    "gn:asciiname":"San Jose Xcobo",
    "gn:country_code":"MX",
    "gn:dem":10,
    "gn:feature_class":"P",
    "gn:feature_code":"PPL",
    "gn:name":"San Jos\u00e9 Xcobo",
    "gn:population":0,
    "gn:timezone":"America/Merida",
    "iso:country":"MX",
    "name:spa_x_preferred":[
        "San Jos\u00e9 Xcobo"
    ],
    "name:spa_x_variant":[
        "San Jos\u00e9"
    ],
    "wof:name":"San Jose Xcobo",
    "wof:placetype":"locality"
},
  "geometry": {"coordinates":[-87.78025,21.43027],"type":"Point"}
}