{
  "type": "Feature",
  "properties": {
    "gn:admin1_code":"5",
    "gn:admin2_code":"12",
    "gn:asciiname":"La Planada",
    "gn:country_code":"MX",
    "gn:dem":820,
    "gn:feature_class":"P",
    "gn:feature_code":"PPL",
    "gn:name":"La Planada",
    "gn:population":13,
    "gn:timezone":"America/Mexico_City",
    "iso:country":"MX",
    "wof:name":"La Planada",
    "wof:placetype":"locality",
    "wof:population":13
},
  "geometry": {"coordinates":[-93.23694,16.80639],"type":"Point"}
}