{
  "type": "Feature",
  "properties": {
    "gn:admin1_code":"30",
    "gn:admin2_code":"23.0",
    "gn:asciiname":"San Isidro (El Barranco)",
    "gn:country_code":"MX",
    "gn:dem":769,
    "gn:feature_class":"P",
    "gn:feature_code":"PPL",
    "gn:name":"San Isidro (El Barranco)",
    "gn:population":363,
    "gn:timezone":"America/Mexico_City",
    "iso:country":"MX",
    "wof:name":"San Isidro (El Barranco)",
    "wof:placetype":"locality",
    "wof:population":363
},
  "geometry": {"coordinates":[-97.09721999999999,19.89667],"type":"Point"}
}