{
  "type": "Feature",
  "properties": {
    "gn:admin1_code":"26",
    "gn:admin2_code":"30",
    "gn:asciiname":"El Tejaban",
    "gn:country_code":"MX",
    "gn:dem":36,
    "gn:feature_class":"P",
    "gn:feature_code":"PPL",
    "gn:name":"El Tejab\u00e1n",
    "gn:population":16,
    "gn:timezone":"America/Hermosillo",
    "iso:country":"MX",
    "name:und_x_variant":[
        "El Tejab\u00e1n"
    ],
    "wof:name":"El Tejaban",
    "wof:placetype":"locality",
    "wof:population":16
},
  "geometry": {"coordinates":[-111.56361,28.73028],"type":"Point"}
}