{
  "type": "Feature",
  "properties": {
    "gn:admin1_code":"11",
    "gn:admin2_code":"17",
    "gn:asciiname":"Nuevo Ejido Emiliano Zapata",
    "gn:country_code":"MX",
    "gn:dem":1718,
    "gn:feature_class":"P",
    "gn:feature_code":"PPL",
    "gn:name":"Nuevo Ejido Emiliano Zapata",
    "gn:population":21,
    "gn:timezone":"America/Mexico_City",
    "iso:country":"MX",
    "wof:name":"Nuevo Ejido Emiliano Zapata",
    "wof:placetype":"locality",
    "wof:population":21
},
  "geometry": {"coordinates":[-101.35833,20.63167],"type":"Point"}
}