{
  "type": "Feature",
  "properties": {
    "gn:admin1_code":"20",
    "gn:admin2_code":"476.0",
    "gn:asciiname":"Al Final de la Calle Allende",
    "gn:country_code":"MX",
    "gn:dem":1873,
    "gn:feature_class":"P",
    "gn:feature_code":"PPL",
    "gn:name":"Al Final de la Calle Allende",
    "gn:population":9,
    "gn:timezone":"America/Mexico_City",
    "iso:country":"MX",
    "wof:name":"Al Final de la Calle Allende",
    "wof:placetype":"locality",
    "wof:population":9
},
  "geometry": {"coordinates":[-97.69333,17.98472000000001],"type":"Point"}
}