{
  "type": "Feature",
  "properties": {
    "gn:admin1_code":"5",
    "gn:admin2_code":"66.0",
    "gn:asciiname":"Santiago los Sabinos",
    "gn:country_code":"MX",
    "gn:dem":430,
    "gn:feature_class":"P",
    "gn:feature_code":"PPL",
    "gn:name":"Santiago los Sabinos",
    "gn:population":73,
    "gn:timezone":"America/Mexico_City",
    "iso:country":"MX",
    "wof:name":"Santiago los Sabinos",
    "wof:placetype":"locality",
    "wof:population":73
},
  "geometry": {"coordinates":[-92.45972,17.05972],"type":"Point"}
}