{
  "type": "Feature",
  "properties": {
    "gn:admin1_code":"14",
    "gn:admin2_code":"84.0",
    "gn:asciiname":"Soyatan",
    "gn:country_code":"MX",
    "gn:dem":414,
    "gn:feature_class":"P",
    "gn:feature_code":"PPL",
    "gn:name":"Soyat\u00e1n",
    "gn:population":0,
    "gn:timezone":"America/Mexico_City",
    "iso:country":"MX",
    "name:spa_x_preferred":[
        "Soyat\u00e1n"
    ],
    "wof:name":"Soyatan",
    "wof:placetype":"locality"
},
  "geometry": {"coordinates":[-104.85907,20.13294],"type":"Point"}
}