{
  "type": "Feature",
  "properties": {
    "gn:admin1_code":"25",
    "gn:admin2_code":"17.0",
    "gn:asciiname":"Mazocari",
    "gn:country_code":"MX",
    "gn:dem":207,
    "gn:feature_class":"P",
    "gn:feature_code":"PPL",
    "gn:name":"Mazocari",
    "gn:population":426,
    "gn:timezone":"America/Mazatlan",
    "iso:country":"MX",
    "name:spa_x_preferred":[
        "Mazocari"
    ],
    "name:und_x_variant":[
        "Masocari"
    ],
    "wof:name":"Mazocari",
    "wof:placetype":"locality",
    "wof:population":426
},
  "geometry": {"coordinates":[-108.19643000000001,26.0834],"type":"Point"}
}