{
  "type": "Feature",
  "properties": {
    "gn:admin1_code":"6",
    "gn:admin2_code":"27.0",
    "gn:asciiname":"Rancheria Sitanapurachi",
    "gn:country_code":"MX",
    "gn:dem":2252,
    "gn:feature_class":"P",
    "gn:feature_code":"PPL",
    "gn:name":"Rancher\u00eda Sitan\u00e1purachi",
    "gn:population":0,
    "gn:timezone":"America/Chihuahua",
    "iso:country":"MX",
    "name:spa_x_preferred":[
        "Rancher\u00eda Sitan\u00e1purachi"
    ],
    "wof:name":"Rancheria Sitanapurachi",
    "wof:placetype":"locality"
},
  "geometry": {"coordinates":[-107.39428999999998,27.14685],"type":"Point"}
}