{
  "type": "Feature",
  "properties": {
    "gn:admin1_code":"6",
    "gn:admin2_code":"7.0",
    "gn:asciiname":"La Yerbabuena",
    "gn:country_code":"MX",
    "gn:dem":1962,
    "gn:feature_class":"P",
    "gn:feature_code":"PPL",
    "gn:name":"La Yerbabuena",
    "gn:population":0,
    "gn:timezone":"America/Chihuahua",
    "iso:country":"MX",
    "name:spa_x_preferred":[
        "La Yerbabuena"
    ],
    "name:und_x_variant":[
        "Rancho Yerbabuena",
        "Yerbabuena"
    ],
    "wof:name":"La Yerbabuena",
    "wof:placetype":"locality"
},
  "geometry": {"coordinates":[-106.51926,26.9911],"type":"Point"}
}