{
  "type": "Feature",
  "properties": {
    "gn:admin1_code":"13",
    "gn:admin2_code":"47.0",
    "gn:asciiname":"Jinapan",
    "gn:country_code":"MX",
    "gn:dem":1435,
    "gn:feature_class":"P",
    "gn:feature_code":"PPL",
    "gn:name":"Jinap\u00e1n",
    "gn:population":0,
    "gn:timezone":"America/Mexico_City",
    "iso:country":"MX",
    "name:spa_x_preferred":[
        "Jinap\u00e1n"
    ],
    "wof:name":"Jinapan",
    "wof:placetype":"locality"
},
  "geometry": {"coordinates":[-99.34305999999999,20.98333],"type":"Point"}
}