{
  "type": "Feature",
  "properties": {
    "gn:admin1_code":"26",
    "gn:admin2_code":"71.0",
    "gn:asciiname":"Malbaso",
    "gn:country_code":"MX",
    "gn:dem":18,
    "gn:feature_class":"P",
    "gn:feature_code":"PPL",
    "gn:name":"Malbaso",
    "gn:population":5,
    "gn:timezone":"America/Hermosillo",
    "iso:country":"MX",
    "name:spa_x_preferred":[
        "Malbaso"
    ],
    "wof:name":"Malbaso",
    "wof:placetype":"locality",
    "wof:population":5
},
  "geometry": {"coordinates":[-109.78888999999999,27.11028],"type":"Point"}
}