{
  "type": "Feature",
  "properties": {
    "gn:admin1_code":"6.0",
    "gn:admin2_code":"52.0",
    "gn:asciiname":"Barrancos de Guadalupe",
    "gn:country_code":"MX",
    "gn:dem":886,
    "gn:feature_class":"P",
    "gn:feature_code":"PPL",
    "gn:name":"Barrancos de Guadalupe",
    "gn:population":0,
    "gn:timezone":"America/Ojinaga",
    "iso:country":"MX",
    "name:und_x_variant":[
        "Barranco de Guadalupe",
        "Barrancos de Guadalupe"
    ],
    "wof:name":"Barrancos de Guadalupe",
    "wof:placetype":"locality"
},
  "geometry": {"coordinates":[-104.69695,29.99112],"type":"Point"}
}