{
  "type": "Feature",
  "properties": {
    "gn:admin1_code":"10",
    "gn:admin2_code":"12.0",
    "gn:asciiname":"Salamanca",
    "gn:country_code":"MX",
    "gn:dem":1168,
    "gn:feature_class":"P",
    "gn:feature_code":"PPL",
    "gn:name":"Salamanca",
    "gn:population":0,
    "gn:timezone":"America/Monterrey",
    "iso:country":"MX",
    "name:spa_x_preferred":[
        "Salamanca"
    ],
    "wof:name":"Salamanca",
    "wof:placetype":"locality"
},
  "geometry": {"coordinates":[-103.6982,25.51581],"type":"Point"}
}