{
  "type": "Feature",
  "properties": {
    "gn:admin1_code":"32",
    "gn:admin2_code":"10",
    "gn:asciiname":"Santa Cruz [Vinedos]",
    "gn:country_code":"MX",
    "gn:dem":2029,
    "gn:feature_class":"P",
    "gn:feature_code":"PPL",
    "gn:name":"Santa Cruz [Vi\u00f1edos]",
    "gn:population":24,
    "gn:timezone":"America/Mexico_City",
    "iso:country":"MX",
    "name:und_x_variant":[
        "Santa Cruz [Vi\u00f1edos]"
    ],
    "wof:name":"Santa Cruz [Vinedos]",
    "wof:placetype":"locality",
    "wof:population":24
},
  "geometry": {"coordinates":[-102.98778,23.35556],"type":"Point"}
}