{
  "type": "Feature",
  "properties": {
    "gn:admin1_code":"16.0",
    "gn:admin2_code":"75.0",
    "gn:asciiname":"Uringuitiro",
    "gn:country_code":"MX",
    "gn:dem":2632,
    "gn:feature_class":"P",
    "gn:feature_code":"PPL",
    "gn:name":"Uringuitiro",
    "gn:population":0,
    "gn:timezone":"America/Mexico_City",
    "iso:country":"MX",
    "name:spa_x_preferred":[
        "Uringuitiro"
    ],
    "wof:name":"Uringuitiro",
    "wof:placetype":"locality"
},
  "geometry": {"coordinates":[-102.30382,19.75048],"type":"Point"}
}