{
  "type": "Feature",
  "properties": {
    "gn:admin1_code":"32",
    "gn:admin2_code":"19.0",
    "gn:asciiname":"Don Martin",
    "gn:country_code":"MX",
    "gn:dem":1427,
    "gn:feature_class":"P",
    "gn:feature_code":"PPL",
    "gn:name":"Don Mart\u00edn",
    "gn:population":0,
    "gn:timezone":"America/Mexico_City",
    "iso:country":"MX",
    "name:ceb_x_preferred":[
        "Don Martin"
    ],
    "name:deu_x_preferred":[
        "Don Martin"
    ],
    "name:pol_x_preferred":[
        "Donald Martin"
    ],
    "name:spa_x_preferred":[
        "Don Mart\u00edn"
    ],
    "name:srp_x_preferred":[
        "\u0414\u043e\u043d \u041c\u0430\u0440\u0442\u0438\u043d"
    ],
    "name:swe_x_preferred":[
        "Don Martin"
    ],
    "wof:name":"Don Martin",
    "wof:placetype":"locality"
},
  "geometry": {"coordinates":[-103.02589999999999,21.62727000000001],"type":"Point"}
}