{
  "type": "Feature",
  "properties": {
    "gn:admin1_code":"27",
    "gn:admin2_code":"8.0",
    "gn:asciiname":"Blasillo Primera Seccion",
    "gn:country_code":"MX",
    "gn:dem":8,
    "gn:feature_class":"P",
    "gn:feature_code":"PPL",
    "gn:name":"Blasillo Primera Secci\u00f3n",
    "gn:population":0,
    "gn:timezone":"America/Mexico_City",
    "iso:country":"MX",
    "name:spa_x_preferred":[
        "Blasillo Primera Secci\u00f3n"
    ],
    "wof:name":"Blasillo Primera Seccion",
    "wof:placetype":"locality"
},
  "geometry": {"coordinates":[-93.90000000000001,18.06667],"type":"Point"}
}