{
  "type": "Feature",
  "properties": {
    "gn:admin1_code":"15",
    "gn:asciiname":"Tanaquillo",
    "gn:country_code":"MX",
    "gn:dem":1789,
    "gn:feature_class":"P",
    "gn:feature_code":"PPL",
    "gn:name":"Tanaquillo",
    "gn:population":0,
    "gn:timezone":"America/Mexico_City",
    "iso:country":"MX",
    "name:spa_x_preferred":[
        "Tanaquillo"
    ],
    "wof:name":"Tanaquillo",
    "wof:placetype":"locality"
},
  "geometry": {"coordinates":[-102.09797,19.84611],"type":"Point"}
}