{
  "type": "Feature",
  "properties": {
    "gn:admin1_code":"12",
    "gn:admin2_code":"57",
    "gn:asciiname":"Estate",
    "gn:country_code":"MX",
    "gn:dem":175,
    "gn:feature_class":"P",
    "gn:feature_code":"PPL",
    "gn:name":"Estate",
    "gn:population":12,
    "gn:timezone":"America/Mexico_City",
    "iso:country":"MX",
    "name:ita_x_preferred":[
        "Estate"
    ],
    "name:jpn_x_preferred":[
        "\u30a8\u30b9\u30c6\u30fc\u30c8"
    ],
    "name:kor_x_preferred":[
        "\uc5d0\uc2a4\ud14c\uc774\ud2b8"
    ],
    "wof:name":"Estate",
    "wof:placetype":"locality",
    "wof:population":12
},
  "geometry": {"coordinates":[-100.87314000000001,17.38298],"type":"Point"}
}