{
  "type": "Feature",
  "properties": {
    "gn:admin1_code":"14",
    "gn:admin2_code":"53.0",
    "gn:asciiname":"El Mesoncito",
    "gn:country_code":"MX",
    "gn:dem":1998,
    "gn:feature_class":"P",
    "gn:feature_code":"PPL",
    "gn:name":"El Mesoncito",
    "gn:population":108,
    "gn:timezone":"America/Mexico_City",
    "iso:country":"MX",
    "wof:name":"El Mesoncito",
    "wof:placetype":"locality",
    "wof:population":108
},
  "geometry": {"coordinates":[-101.99701,21.43087],"type":"Point"}
}