{
  "type": "Feature",
  "properties": {
    "gn:admin1_code":"15.0",
    "gn:asciiname":"Tepanquiahac",
    "gn:country_code":"MX",
    "gn:dem":2256,
    "gn:feature_class":"P",
    "gn:feature_code":"PPL",
    "gn:name":"Tepanquiahac",
    "gn:population":0,
    "gn:timezone":"America/Mexico_City",
    "iso:country":"MX",
    "name:spa_x_preferred":[
        "Tepanquiahac"
    ],
    "wof:name":"Tepanquiahac",
    "wof:placetype":"locality"
},
  "geometry": {"coordinates":[-99.18966,19.72415],"type":"Point"}
}