{
  "type": "Feature",
  "properties": {
    "gn:admin1_code":"6",
    "gn:admin2_code":"20.0",
    "gn:asciiname":"Gorogachic",
    "gn:country_code":"MX",
    "gn:dem":821,
    "gn:feature_class":"P",
    "gn:feature_code":"PPL",
    "gn:name":"Gorogachic",
    "gn:population":0,
    "gn:timezone":"America/Chihuahua",
    "iso:country":"MX",
    "name:spa_x_preferred":[
        "Gorogachic"
    ],
    "wof:name":"Gorogachic",
    "wof:placetype":"locality"
},
  "geometry": {"coordinates":[-108.50369999999999,27.24617000000001],"type":"Point"}
}