{
  "type": "Feature",
  "properties": {
    "gn:admin1_code":"30.0",
    "gn:admin2_code":"180.0",
    "gn:asciiname":"Texca Chiquito",
    "gn:country_code":"MX",
    "gn:dem":607,
    "gn:feature_class":"P",
    "gn:feature_code":"PPL",
    "gn:name":"Texca Chiquito",
    "gn:population":0,
    "gn:timezone":"America/Mexico_City",
    "iso:country":"MX",
    "name:spa_x_preferred":[
        "Texca Chiquito"
    ],
    "wof:name":"Texca Chiquito",
    "wof:placetype":"locality"
},
  "geometry": {"coordinates":[-98.17204,20.64273],"type":"Point"}
}