{
  "type": "Feature",
  "properties": {
    "gn:admin1_code":"10",
    "gn:admin2_code":"23.0",
    "gn:asciiname":"El Gualamo",
    "gn:country_code":"MX",
    "gn:dem":1095,
    "gn:feature_class":"P",
    "gn:feature_code":"PPL",
    "gn:name":"El Gualamo",
    "gn:population":0,
    "gn:timezone":"America/Monterrey",
    "iso:country":"MX",
    "name:spa_x_preferred":[
        "El Gualamo"
    ],
    "wof:name":"El Gualamo",
    "wof:placetype":"locality"
},
  "geometry": {"coordinates":[-105.61312,23.38141],"type":"Point"}
}