{
  "type": "Feature",
  "properties": {
    "gn:admin1_code":"32.0",
    "gn:admin2_code":"36.0",
    "gn:asciiname":"La Pena Colorada",
    "gn:country_code":"MX",
    "gn:dem":2127,
    "gn:feature_class":"P",
    "gn:feature_code":"PPL",
    "gn:name":"La Pe\u00f1a Colorada",
    "gn:population":0,
    "gn:timezone":"America/Mexico_City",
    "iso:country":"MX",
    "name:spa_x_preferred":[
        "La Pe\u00f1a Colorada"
    ],
    "wof:name":"La Pena Colorada",
    "wof:placetype":"locality"
},
  "geometry": {"coordinates":[-102.21608999999999,22.63112000000001],"type":"Point"}
}