{
  "type": "Feature",
  "properties": {
    "gn:admin1_code":"5",
    "gn:admin2_code":"2",
    "gn:asciiname":"Las Carolinas",
    "gn:country_code":"MX",
    "gn:dem":608,
    "gn:feature_class":"P",
    "gn:feature_code":"PPL",
    "gn:name":"Las Carolinas",
    "gn:population":25,
    "gn:timezone":"America/Mexico_City",
    "iso:country":"MX",
    "wof:name":"Las Carolinas",
    "wof:placetype":"locality",
    "wof:population":25
},
  "geometry": {"coordinates":[-92.81,16.43778],"type":"Point"}
}