{
  "type": "Feature",
  "properties": {
    "gn:admin1_code":"16",
    "gn:admin2_code":"92.0",
    "gn:asciiname":"El Inventario",
    "gn:country_code":"MX",
    "gn:dem":2027,
    "gn:feature_class":"P",
    "gn:feature_code":"PPL",
    "gn:name":"El Inventario",
    "gn:population":5,
    "gn:timezone":"America/Mexico_City",
    "iso:country":"MX",
    "wof:name":"El Inventario",
    "wof:placetype":"locality",
    "wof:population":5
},
  "geometry": {"coordinates":[-100.94222000000001,19.2475],"type":"Point"}
}