{
  "type": "Feature",
  "properties": {
    "gn:admin1_code":"6.0",
    "gn:admin2_code":"52.0",
    "gn:asciiname":"Boquilla",
    "gn:country_code":"MX",
    "gn:dem":909,
    "gn:feature_class":"P",
    "gn:feature_code":"PPL",
    "gn:name":"Boquilla",
    "gn:population":0,
    "gn:timezone":"America/Ojinaga",
    "iso:country":"MX",
    "wof:name":"Boquilla",
    "wof:placetype":"locality"
},
  "geometry": {"coordinates":[-104.71666999999999,30.18333],"type":"Point"}
}