{
  "type": "Feature",
  "properties": {
    "gn:admin1_code":"24",
    "gn:admin2_code":"28.0",
    "gn:asciiname":"Julio Meza Hernandez",
    "gn:country_code":"MX",
    "gn:dem":1831,
    "gn:feature_class":"P",
    "gn:feature_code":"PPL",
    "gn:name":"Julio Meza Hern\u00e1ndez",
    "gn:population":8,
    "gn:timezone":"America/Mexico_City",
    "iso:country":"MX",
    "name:und_x_variant":[
        "Julio Meza Hern\u00e1ndez"
    ],
    "wof:name":"Julio Meza Hernandez",
    "wof:placetype":"locality",
    "wof:population":8
},
  "geometry": {"coordinates":[-100.95471999999999,22.31111],"type":"Point"}
}