{
  "type": "Feature",
  "properties": {
    "gn:admin1_code":"5",
    "gn:admin2_code":"21.0",
    "gn:asciiname":"Rosario",
    "gn:country_code":"MX",
    "gn:dem":655,
    "gn:feature_class":"P",
    "gn:feature_code":"PPL",
    "gn:name":"Rosario",
    "gn:population":0,
    "gn:timezone":"America/Mexico_City",
    "iso:country":"MX",
    "name:spa_x_preferred":[
        "Rosario"
    ],
    "name:spa_x_variant":[
        "El Rosario"
    ],
    "wof:name":"Rosario",
    "wof:placetype":"locality"
},
  "geometry": {"coordinates":[-93.24288,17.08921],"type":"Point"}
}