{
  "type": "Feature",
  "properties": {
    "gn:admin1_code":"16",
    "gn:admin2_code":"99.0",
    "gn:asciiname":"El Mango",
    "gn:country_code":"MX",
    "gn:dem":1009,
    "gn:feature_class":"P",
    "gn:feature_code":"PPL",
    "gn:name":"El Mango",
    "gn:population":6,
    "gn:timezone":"America/Mexico_City",
    "iso:country":"MX",
    "wof:name":"El Mango",
    "wof:placetype":"locality",
    "wof:population":6
},
  "geometry": {"coordinates":[-100.65582999999999,19.32139],"type":"Point"}
}