{
  "type": "Feature",
  "properties": {
    "gn:admin1_code":"3",
    "gn:admin2_code":"1.0",
    "gn:asciiname":"El Sauce",
    "gn:country_code":"MX",
    "gn:dem":286,
    "gn:feature_class":"P",
    "gn:feature_code":"PPL",
    "gn:name":"El Sauce",
    "gn:population":8,
    "gn:timezone":"America/Mazatlan",
    "iso:country":"MX",
    "wof:name":"El Sauce",
    "wof:placetype":"locality",
    "wof:population":8
},
  "geometry": {"coordinates":[-111.16204999999999,25.28315],"type":"Point"}
}