{
  "type": "Feature",
  "properties": {
    "gn:admin1_code":"12",
    "gn:admin2_code":"46.0",
    "gn:asciiname":"Arroyo Zapote",
    "gn:country_code":"MX",
    "gn:dem":287,
    "gn:feature_class":"P",
    "gn:feature_code":"PPL",
    "gn:name":"Arroyo Zapote",
    "gn:population":65,
    "gn:timezone":"America/Mexico_City",
    "iso:country":"MX",
    "wof:name":"Arroyo Zapote",
    "wof:placetype":"locality",
    "wof:population":65
},
  "geometry": {"coordinates":[-98.26414,16.76141],"type":"Point"}
}