{
  "type": "Feature",
  "properties": {
    "gn:admin1_code":"20",
    "gn:admin2_code":"105.0",
    "gn:asciiname":"San Miguel Monteverde",
    "gn:country_code":"MX",
    "gn:dem":2176,
    "gn:feature_class":"P",
    "gn:feature_code":"PPL",
    "gn:name":"San Miguel Monteverde",
    "gn:population":1857,
    "gn:timezone":"America/Mexico_City",
    "iso:country":"MX",
    "wof:name":"San Miguel Monteverde",
    "wof:placetype":"locality",
    "wof:population":1857
},
  "geometry": {"coordinates":[-97.7925,17.53111],"type":"Point"}
}