{
  "type": "Feature",
  "properties": {
    "gn:admin1_code":"2",
    "gn:admin2_code":"4.0",
    "gn:asciiname":"Los Espitia",
    "gn:country_code":"MX",
    "gn:dem":252,
    "gn:feature_class":"P",
    "gn:feature_code":"PPL",
    "gn:name":"Los Espitia",
    "gn:population":6,
    "gn:timezone":"America/Tijuana",
    "iso:country":"MX",
    "wof:name":"Los Espitia",
    "wof:placetype":"locality",
    "wof:population":6
},
  "geometry": {"coordinates":[-116.95056,32.41361],"type":"Point"}
}