{
  "type": "Feature",
  "properties": {
    "gn:admin1_code":"14.0",
    "gn:admin2_code":"85.0",
    "gn:asciiname":"La Palmilla",
    "gn:country_code":"MX",
    "gn:dem":1394,
    "gn:feature_class":"P",
    "gn:feature_code":"PPL",
    "gn:name":"La Palmilla",
    "gn:population":0,
    "gn:timezone":"America/Mexico_City",
    "iso:country":"MX",
    "name:spa_x_preferred":[
        "La Palmilla"
    ],
    "wof:name":"La Palmilla",
    "wof:placetype":"locality"
},
  "geometry": {"coordinates":[-103.09319000000001,19.80059],"type":"Point"}
}