{
  "type": "Feature",
  "properties": {
    "gn:admin1_code":"6",
    "gn:admin2_code":"36",
    "gn:asciiname":"Rancho la Chiripa",
    "gn:country_code":"MX",
    "gn:dem":1122,
    "gn:feature_class":"P",
    "gn:feature_code":"PPL",
    "gn:name":"Rancho la Chiripa",
    "gn:population":9,
    "gn:timezone":"America/Chihuahua",
    "iso:country":"MX",
    "wof:name":"Rancho la Chiripa",
    "wof:placetype":"locality",
    "wof:population":9
},
  "geometry": {"coordinates":[-103.97262000000001,26.90636],"type":"Point"}
}