{
  "type": "Feature",
  "properties": {
    "gn:admin1_code":"25",
    "gn:admin2_code":"7.0",
    "gn:asciiname":"San Jose de los Pericos",
    "gn:country_code":"MX",
    "gn:dem":502,
    "gn:feature_class":"P",
    "gn:feature_code":"PPL",
    "gn:name":"San Jos\u00e9 de los Pericos",
    "gn:population":155,
    "gn:timezone":"America/Mazatlan",
    "iso:country":"MX",
    "wof:name":"San Jose de los Pericos",
    "wof:placetype":"locality",
    "wof:population":155
},
  "geometry": {"coordinates":[-108.27594000000001,26.39177],"type":"Point"}
}