{
  "type": "Feature",
  "properties": {
    "gn:admin1_code":"19",
    "gn:admin2_code":"29.0",
    "gn:asciiname":"Cinco Senores (Los Angeles)",
    "gn:country_code":"MX",
    "gn:dem":368,
    "gn:feature_class":"P",
    "gn:feature_code":"PPL",
    "gn:name":"Cinco Se\u00f1ores (Los \u00c1ngeles)",
    "gn:population":102,
    "gn:timezone":"America/Monterrey",
    "iso:country":"MX",
    "name:und_x_variant":[
        "Cinco Se\u00f1ores (Los \u00c1ngeles)"
    ],
    "wof:name":"Cinco Senores (Los Angeles)",
    "wof:placetype":"locality",
    "wof:population":102
},
  "geometry": {"coordinates":[-99.62277,24.8748],"type":"Point"}
}