{
  "type": "Feature",
  "properties": {
    "gn:admin1_code":"5",
    "gn:admin2_code":"107",
    "gn:asciiname":"Nuevo Poblado las Carolinas",
    "gn:country_code":"MX",
    "gn:dem":645,
    "gn:feature_class":"P",
    "gn:feature_code":"PPL",
    "gn:name":"Nuevo Poblado las Carolinas",
    "gn:population":52,
    "gn:timezone":"America/Mexico_City",
    "iso:country":"MX",
    "wof:name":"Nuevo Poblado las Carolinas",
    "wof:placetype":"locality",
    "wof:population":52
},
  "geometry": {"coordinates":[-92.99167,16.2475],"type":"Point"}
}