{
  "type": "Feature",
  "properties": {
    "gn:admin1_code":"28.0",
    "gn:admin2_code":"14.0",
    "gn:asciiname":"El Garceno",
    "gn:country_code":"MX",
    "gn:dem":118,
    "gn:feature_class":"P",
    "gn:feature_code":"PPL",
    "gn:name":"El Garce\u00f1o",
    "gn:population":0,
    "gn:timezone":"America/Monterrey",
    "iso:country":"MX",
    "name:spa_x_preferred":[
        "El Garce\u00f1o"
    ],
    "wof:name":"El Garceno",
    "wof:placetype":"locality"
},
  "geometry": {"coordinates":[-99.51557,26.77641],"type":"Point"}
}