{
  "type": "Feature",
  "properties": {
    "gn:admin1_code":"16",
    "gn:admin2_code":"53",
    "gn:asciiname":"La Amargosilla",
    "gn:country_code":"MX",
    "gn:dem":2293,
    "gn:feature_class":"P",
    "gn:feature_code":"PPL",
    "gn:name":"La Amargosilla",
    "gn:population":10,
    "gn:timezone":"America/Mexico_City",
    "iso:country":"MX",
    "wof:name":"La Amargosilla",
    "wof:placetype":"locality",
    "wof:population":10
},
  "geometry": {"coordinates":[-101.32971999999999,19.84083],"type":"Point"}
}