{
  "type": "Feature",
  "properties": {
    "gn:admin1_code":"20",
    "gn:admin2_code":"248.0",
    "gn:asciiname":"Costa Rica",
    "gn:country_code":"MX",
    "gn:dem":11,
    "gn:feature_class":"P",
    "gn:feature_code":"PPL",
    "gn:name":"Costa Rica",
    "gn:population":0,
    "gn:timezone":"America/Mexico_City",
    "iso:country":"MX",
    "name:spa_x_preferred":[
        "Costa Rica"
    ],
    "wof:name":"Costa Rica",
    "wof:placetype":"locality"
},
  "geometry": {"coordinates":[-95.00145000000001,16.20798],"type":"Point"}
}