{
  "type": "Feature",
  "properties": {
    "gn:admin1_code":"20",
    "gn:admin2_code":"298.0",
    "gn:asciiname":"San Miguel Albarradas",
    "gn:country_code":"MX",
    "gn:dem":1943,
    "gn:feature_class":"P",
    "gn:feature_code":"PPL",
    "gn:name":"San Miguel Albarradas",
    "gn:population":0,
    "gn:timezone":"America/Mexico_City",
    "iso:country":"MX",
    "name:und_x_variant":[
        "San Miguel",
        "Albarradas",
        "San Miguel Albarradas"
    ],
    "wof:name":"San Miguel Albarradas",
    "wof:placetype":"locality"
},
  "geometry": {"coordinates":[-96.27124999999999,17.0367],"type":"Point"}
}