{
  "type": "Feature",
  "properties": {
    "gn:admin1_code":"29",
    "gn:admin2_code":"25.0",
    "gn:asciiname":"Juquila",
    "gn:country_code":"MX",
    "gn:dem":2583,
    "gn:feature_class":"P",
    "gn:feature_code":"PPL",
    "gn:name":"Juquila",
    "gn:population":61,
    "gn:timezone":"America/Mexico_City",
    "iso:country":"MX",
    "wof:name":"Juquila",
    "wof:placetype":"locality",
    "wof:population":61
},
  "geometry": {"coordinates":[-98.11681,19.1611],"type":"Point"}
}