{
  "type": "Feature",
  "properties": {
    "gn:admin1_code":"19",
    "gn:admin2_code":"17.0",
    "gn:asciiname":"Rancho Alegre",
    "gn:country_code":"MX",
    "gn:dem":2246,
    "gn:feature_class":"P",
    "gn:feature_code":"PPL",
    "gn:name":"Rancho Alegre",
    "gn:population":2,
    "gn:timezone":"America/Monterrey",
    "iso:country":"MX",
    "wof:name":"Rancho Alegre",
    "wof:placetype":"locality",
    "wof:population":2
},
  "geometry": {"coordinates":[-100.57557,25.17061],"type":"Point"}
}