{
  "type": "Feature",
  "properties": {
    "gn:admin1_code":"30.0",
    "gn:admin2_code":"123.0",
    "gn:asciiname":"Rancho Olvera",
    "gn:country_code":"MX",
    "gn:dem":56,
    "gn:feature_class":"P",
    "gn:feature_code":"PPL",
    "gn:name":"Rancho Olvera",
    "gn:population":0,
    "gn:timezone":"America/Mexico_City",
    "iso:country":"MX",
    "name:spa_x_preferred":[
        "Rancho Olvera"
    ],
    "wof:name":"Rancho Olvera",
    "wof:placetype":"locality"
},
  "geometry": {"coordinates":[-98.23963000000001,22.22919],"type":"Point"}
}