{
  "type": "Feature",
  "properties": {
    "gn:admin1_code":"30",
    "gn:admin2_code":"181.0",
    "gn:asciiname":"Colonia Fernando Gutierrez Barrios",
    "gn:country_code":"MX",
    "gn:dem":20,
    "gn:feature_class":"P",
    "gn:feature_code":"PPL",
    "gn:name":"Colonia Fernando Guti\u00e9rrez Barrios",
    "gn:population":204,
    "gn:timezone":"America/Mexico_City",
    "iso:country":"MX",
    "name:und_x_variant":[
        "Colonia Fernando Guti\u00e9rrez Barrios"
    ],
    "wof:name":"Colonia Fernando Gutierrez Barrios",
    "wof:placetype":"locality",
    "wof:population":204
},
  "geometry": {"coordinates":[-96.11028,18.72194],"type":"Point"}
}