{
  "type": "Feature",
  "properties": {
    "gn:admin1_code":"7",
    "gn:admin2_code":"35",
    "gn:asciiname":"Ciudad de los Ninos [Internado]",
    "gn:country_code":"MX",
    "gn:dem":1116,
    "gn:feature_class":"P",
    "gn:feature_code":"PPL",
    "gn:name":"Ciudad de los Ni\u00f1os [Internado]",
    "gn:population":32,
    "gn:timezone":"America/Monterrey",
    "iso:country":"MX",
    "name:und_x_variant":[
        "Ciudad de los Ni\u00f1os [Internado]"
    ],
    "wof:name":"Ciudad de los Ninos [Internado]",
    "wof:placetype":"locality",
    "wof:population":32
},
  "geometry": {"coordinates":[-103.32229,25.59611],"type":"Point"}
}