{
  "type": "Feature",
  "properties": {
    "gn:admin1_code":"29",
    "gn:admin2_code":"9.0",
    "gn:asciiname":"San Lorenzo Xaltelulco",
    "gn:country_code":"MX",
    "gn:dem":2474,
    "gn:feature_class":"P",
    "gn:feature_code":"PPL",
    "gn:name":"San Lorenzo Xaltelulco",
    "gn:population":0,
    "gn:timezone":"America/Mexico_City",
    "iso:country":"MX",
    "name:und_x_variant":[
        "Xaltelulco"
    ],
    "wof:name":"San Lorenzo Xaltelulco",
    "wof:placetype":"locality"
},
  "geometry": {"coordinates":[-98.10585,19.34075],"type":"Point"}
}