{
  "type": "Feature",
  "properties": {
    "gn:admin1_code":"28",
    "gn:admin2_code":"37.0",
    "gn:asciiname":"El Esmeril",
    "gn:country_code":"MX",
    "gn:dem":88,
    "gn:feature_class":"P",
    "gn:feature_code":"PPL",
    "gn:name":"El Esmeril",
    "gn:population":0,
    "gn:timezone":"America/Monterrey",
    "iso:country":"MX",
    "name:und_x_variant":[
        "El Porvenir"
    ],
    "wof:name":"El Esmeril",
    "wof:placetype":"locality"
},
  "geometry": {"coordinates":[-97.88018,23.51048],"type":"Point"}
}