{
  "type": "Feature",
  "properties": {
    "gn:admin1_code":"26.0",
    "gn:admin2_code":"43.0",
    "gn:asciiname":"Las Chimeneas",
    "gn:country_code":"MX",
    "gn:dem":1300,
    "gn:feature_class":"P",
    "gn:feature_code":"PPL",
    "gn:name":"Las Chimeneas",
    "gn:population":0,
    "gn:timezone":"America/Hermosillo",
    "iso:country":"MX",
    "name:spa_x_preferred":[
        "Las Chimeneas"
    ],
    "wof:name":"Las Chimeneas",
    "wof:placetype":"locality"
},
  "geometry": {"coordinates":[-110.98023999999999,31.27701],"type":"Point"}
}