{
  "type": "Feature",
  "properties": {
    "gn:admin1_code":"28.0",
    "gn:admin2_code":"37.0",
    "gn:asciiname":"Kilomentro Noventa y Nueve",
    "gn:country_code":"MX",
    "gn:dem":94,
    "gn:feature_class":"P",
    "gn:feature_code":"PPL",
    "gn:name":"Kil\u00f3mentro Noventa y Nueve",
    "gn:population":0,
    "gn:timezone":"America/Monterrey",
    "iso:country":"MX",
    "name:spa_x_preferred":[
        "Kil\u00f3mentro Noventa y Nueve"
    ],
    "wof:name":"Kilomentro Noventa y Nueve",
    "wof:placetype":"locality"
},
  "geometry": {"coordinates":[-98.02804999999999,23.41491],"type":"Point"}
}