{
  "type": "Feature",
  "properties": {
    "gn:admin1_code":"16",
    "gn:admin2_code":"34",
    "gn:asciiname":"Barcino",
    "gn:country_code":"MX",
    "gn:dem":2582,
    "gn:feature_class":"P",
    "gn:feature_code":"PPL",
    "gn:name":"Barcino",
    "gn:population":34,
    "gn:timezone":"America/Mexico_City",
    "iso:country":"MX",
    "name:ceb_x_preferred":[
        "Barcino"
    ],
    "name:lat_x_preferred":[
        "Barcino"
    ],
    "name:spa_x_preferred":[
        "Barcino"
    ],
    "name:swe_x_preferred":[
        "Barcino"
    ],
    "wof:name":"Barcino",
    "wof:placetype":"locality",
    "wof:population":34
},
  "geometry": {"coordinates":[-100.63667,19.50944],"type":"Point"}
}