{
  "type": "Feature",
  "properties": {
    "gn:admin1_code":"6",
    "gn:admin2_code":"40.0",
    "gn:asciiname":"La Bandera",
    "gn:country_code":"MX",
    "gn:dem":1494,
    "gn:feature_class":"P",
    "gn:feature_code":"PPL",
    "gn:name":"La Bandera",
    "gn:population":0,
    "gn:timezone":"America/Chihuahua",
    "iso:country":"MX",
    "name:spa_x_preferred":[
        "La Bandera"
    ],
    "wof:name":"La Bandera",
    "wof:placetype":"locality"
},
  "geometry": {"coordinates":[-108.20252000000001,28.96898],"type":"Point"}
}