{
  "type": "Feature",
  "properties": {
    "gn:admin1_code":"12",
    "gn:admin2_code":"1.0",
    "gn:asciiname":"La Sierrita",
    "gn:country_code":"MX",
    "gn:dem":571,
    "gn:feature_class":"P",
    "gn:feature_code":"PPL",
    "gn:name":"La Sierrita",
    "gn:population":335,
    "gn:timezone":"America/Mexico_City",
    "iso:country":"MX",
    "wof:name":"La Sierrita",
    "wof:placetype":"locality",
    "wof:population":335
},
  "geometry": {"coordinates":[-99.73944,17.05556],"type":"Point"}
}