{
  "type": "Feature",
  "properties": {
    "gn:admin1_code":"2",
    "gn:admin2_code":"5",
    "gn:asciiname":"Familia Sandoval (Los Tres Chichos)",
    "gn:country_code":"MX",
    "gn:dem":119,
    "gn:feature_class":"P",
    "gn:feature_code":"PPL",
    "gn:name":"Familia Sandoval (Los Tres Chichos)",
    "gn:population":9,
    "gn:timezone":"America/Tijuana",
    "iso:country":"MX",
    "wof:name":"Familia Sandoval (Los Tres Chichos)",
    "wof:placetype":"locality",
    "wof:population":9
},
  "geometry": {"coordinates":[-116.94693999999998,32.26278],"type":"Point"}
}