{
  "type": "Feature",
  "properties": {
    "gn:admin1_code":"5",
    "gn:asciiname":"Estacion Chacamax Reforma",
    "gn:country_code":"MX",
    "gn:dem":30,
    "gn:feature_class":"P",
    "gn:feature_code":"PPL",
    "gn:name":"Estaci\u00f3n Chacamax Reforma",
    "gn:population":0,
    "gn:timezone":"America/Mexico_City",
    "iso:country":"MX",
    "wof:name":"Estacion Chacamax Reforma",
    "wof:placetype":"locality"
},
  "geometry": {"coordinates":[-91.66667,17.46528],"type":"Point"}
}