{
  "type": "Feature",
  "properties": {
    "gn:admin1_code":"14",
    "gn:admin2_code":"82.0",
    "gn:asciiname":"Estanque C",
    "gn:country_code":"MX",
    "gn:dem":1372,
    "gn:feature_class":"P",
    "gn:feature_code":"PPL",
    "gn:name":"Estanque C",
    "gn:population":6,
    "gn:timezone":"America/Mexico_City",
    "iso:country":"MX",
    "wof:name":"Estanque C",
    "wof:placetype":"locality",
    "wof:population":6
},
  "geometry": {"coordinates":[-103.54000000000001,19.86528],"type":"Point"}
}