{
  "type": "Feature",
  "properties": {
    "gn:admin1_code":"22.0",
    "gn:admin2_code":"1.0",
    "gn:asciiname":"El Apartadero",
    "gn:country_code":"MX",
    "gn:dem":2540,
    "gn:feature_class":"P",
    "gn:feature_code":"PPL",
    "gn:name":"El Apartadero",
    "gn:population":0,
    "gn:timezone":"America/Mexico_City",
    "iso:country":"MX",
    "name:spa_x_preferred":[
        "El Apartadero"
    ],
    "wof:name":"El Apartadero",
    "wof:placetype":"locality"
},
  "geometry": {"coordinates":[-100.06895,20.15467],"type":"Point"}
}