{
  "type": "Feature",
  "properties": {
    "gn:admin1_code":"19",
    "gn:admin2_code":"14",
    "gn:asciiname":"La Zorra",
    "gn:country_code":"MX",
    "gn:dem":1608,
    "gn:feature_class":"P",
    "gn:feature_code":"PPL",
    "gn:name":"La Zorra",
    "gn:population":42,
    "gn:timezone":"America/Monterrey",
    "iso:country":"MX",
    "wof:name":"La Zorra",
    "wof:placetype":"locality",
    "wof:population":42
},
  "geometry": {"coordinates":[-100.06722000000001,23.92194],"type":"Point"}
}