{
  "type": "Feature",
  "properties": {
    "gn:admin1_code":"3",
    "gn:admin2_code":"2.0",
    "gn:asciiname":"La Y",
    "gn:country_code":"MX",
    "gn:dem":532,
    "gn:feature_class":"P",
    "gn:feature_code":"PPL",
    "gn:name":"La Y",
    "gn:population":7,
    "gn:timezone":"America/Mazatlan",
    "iso:country":"MX",
    "wof:name":"La Y",
    "wof:placetype":"locality",
    "wof:population":7
},
  "geometry": {"coordinates":[-112.09215,26.56463],"type":"Point"}
}