{
  "type": "Feature",
  "properties": {
    "gn:admin1_code":"30",
    "gn:admin2_code":"68.0",
    "gn:asciiname":"Colonia Esperanza",
    "gn:country_code":"MX",
    "gn:dem":1222,
    "gn:feature_class":"P",
    "gn:feature_code":"PPL",
    "gn:name":"Colonia Esperanza",
    "gn:population":106,
    "gn:timezone":"America/Mexico_City",
    "iso:country":"MX",
    "wof:name":"Colonia Esperanza",
    "wof:placetype":"locality",
    "wof:population":106
},
  "geometry": {"coordinates":[-97.01861,18.95111],"type":"Point"}
}