{
  "type": "Feature",
  "properties": {
    "gn:admin1_code":"25.0",
    "gn:admin2_code":"17.0",
    "gn:asciiname":"El Zapotillo",
    "gn:country_code":"MX",
    "gn:dem":495,
    "gn:feature_class":"P",
    "gn:feature_code":"PPL",
    "gn:name":"El Zapotillo",
    "gn:population":0,
    "gn:timezone":"America/Mazatlan",
    "iso:country":"MX",
    "name:spa_x_preferred":[
        "El Zapotillo"
    ],
    "wof:name":"El Zapotillo",
    "wof:placetype":"locality"
},
  "geometry": {"coordinates":[-108.04006,26.13394],"type":"Point"}
}