{
  "type": "Feature",
  "properties": {
    "gn:admin1_code":"16",
    "gn:admin2_code":"75.0",
    "gn:asciiname":"Urascato",
    "gn:country_code":"MX",
    "gn:dem":2282,
    "gn:feature_class":"P",
    "gn:feature_code":"PPL",
    "gn:name":"Urascato",
    "gn:population":0,
    "gn:timezone":"America/Mexico_City",
    "iso:country":"MX",
    "wof:name":"Urascato",
    "wof:placetype":"locality"
},
  "geometry": {"coordinates":[-102.36667,19.68333],"type":"Point"}
}