{
  "type": "Feature",
  "properties": {
    "gn:admin1_code":"12",
    "gn:admin2_code":"42.0",
    "gn:asciiname":"Hueyitlalpan",
    "gn:country_code":"MX",
    "gn:dem":1660,
    "gn:feature_class":"P",
    "gn:feature_code":"PPL",
    "gn:name":"Hueyitlalpan",
    "gn:population":1619,
    "gn:timezone":"America/Mexico_City",
    "iso:country":"MX",
    "wof:name":"Hueyitlalpan",
    "wof:placetype":"locality",
    "wof:population":1619
},
  "geometry": {"coordinates":[-99.29555999999999,17.67527999999999],"type":"Point"}
}