{
  "type": "Feature",
  "properties": {
    "gn:admin1_code":"20",
    "gn:admin2_code":"113.0",
    "gn:asciiname":"Macahuite",
    "gn:country_code":"MX",
    "gn:dem":202,
    "gn:feature_class":"P",
    "gn:feature_code":"PPL",
    "gn:name":"Macahuite",
    "gn:population":0,
    "gn:timezone":"America/Mexico_City",
    "iso:country":"MX",
    "wof:name":"Macahuite",
    "wof:placetype":"locality"
},
  "geometry": {"coordinates":[-96.81332999999999,15.96583],"type":"Point"}
}