{
  "type": "Feature",
  "properties": {
    "gn:admin1_code":"20",
    "gn:admin2_code":"510.0",
    "gn:asciiname":"Barrio Guadalupe",
    "gn:country_code":"MX",
    "gn:dem":2275,
    "gn:feature_class":"P",
    "gn:feature_code":"PPL",
    "gn:name":"Barrio Guadalupe",
    "gn:population":8,
    "gn:timezone":"America/Mexico_City",
    "iso:country":"MX",
    "wof:name":"Barrio Guadalupe",
    "wof:placetype":"locality",
    "wof:population":8
},
  "geometry": {"coordinates":[-97.52249999999999,16.91361],"type":"Point"}
}