{
  "type": "Feature",
  "properties": {
    "gn:admin1_code":"15",
    "gn:admin2_code":"67.0",
    "gn:asciiname":"Seccion Sieste San Andres Cuexcontitlan",
    "gn:country_code":"MX",
    "gn:dem":2580,
    "gn:feature_class":"P",
    "gn:feature_code":"PPL",
    "gn:name":"Secci\u00f3n Sieste San Andr\u00e9s Cuexcontitlan",
    "gn:population":0,
    "gn:timezone":"America/Mexico_City",
    "iso:country":"MX",
    "name:spa_x_preferred":[
        "Secci\u00f3n Sieste San Andr\u00e9s Cuexcontitlan"
    ],
    "name:spa_x_variant":[
        "Secci\u00f3n Siete"
    ],
    "wof:name":"Seccion Sieste San Andres Cuexcontitlan",
    "wof:placetype":"locality"
},
  "geometry": {"coordinates":[-99.61346,19.39515],"type":"Point"}
}