{
  "type": "Feature",
  "properties": {
    "gn:admin1_code":"20",
    "gn:admin2_code":"305.0",
    "gn:asciiname":"Noria",
    "gn:country_code":"MX",
    "gn:dem":55,
    "gn:feature_class":"P",
    "gn:feature_code":"PPL",
    "gn:name":"Noria",
    "gn:population":0,
    "gn:timezone":"America/Mexico_City",
    "iso:country":"MX",
    "wof:name":"Noria",
    "wof:placetype":"locality"
},
  "geometry": {"coordinates":[-95.15000000000001,16.46667],"type":"Point"}
}