{
  "type": "Feature",
  "properties": {
    "gn:admin1_code":"20",
    "gn:admin2_code":"305.0",
    "gn:asciiname":"Noria",
    "gn:country_code":"MX",
    "gn:dem":55,
    "gn:feature_class":"P",
    "gn:feature_code":"PPL",
    "gn:name":"Noria",
    "gn:population":0,
    "gn:timezone":"America/Mexico_City",
    "iso:country":"MX",
    "name:cat_x_preferred":[
        "S\u00ednia"
    ],
    "name:ces_x_preferred":[
        "Zdvi\u017en\u00e9 \u010derpadlo"
    ],
    "name:deu_x_preferred":[
        "Sch\u00f6pfrad"
    ],
    "name:epo_x_preferred":[
        "Norio"
    ],
    "name:fra_x_preferred":[
        "Noria"
    ],
    "name:glg_x_preferred":[
        "Nora"
    ],
    "name:hun_x_preferred":[
        "V\u00edzemel\u0151 ker\u00e9k"
    ],
    "name:ido_x_preferred":[
        "Norio"
    ],
    "name:ita_x_preferred":[
        "Noria"
    ],
    "name:jpn_x_preferred":[
        "\u6c34\u6c72\u307f\u6c34\u8eca"
    ],
    "name:kat_x_preferred":[
        "\u10dc\u10dd\u10e0\u10d8\u10d0"
    ],
    "name:lat_x_preferred":[
        "Antlitrochus"
    ],
    "name:lav_x_preferred":[
        "Norija"
    ],
    "name:msa_x_preferred":[
        "Noria"
    ],
    "name:nld_x_preferred":[
        "Noria"
    ],
    "name:pol_x_preferred":[
        "Noria"
    ],
    "name:por_x_preferred":[
        "Nora"
    ],
    "name:rus_x_preferred":[
        "\u041d\u043e\u0440\u0438\u044f"
    ],
    "name:spa_x_preferred":[
        "Noria"
    ],
    "name:tel_x_preferred":[
        "\u0c1c\u0c32\u0c30\u0c3e\u0c1f\u0c4d\u0c28\u0c02"
    ],
    "name:tha_x_preferred":[
        "\u0e23\u0e30\u0e2b\u0e31\u0e14"
    ],
    "name:ukr_x_preferred":[
        "\u041d\u043e\u0440\u0456\u044f"
    ],
    "wof:name":"Noria",
    "wof:placetype":"locality"
},
  "geometry": {"coordinates":[-95.15000000000001,16.46667],"type":"Point"}
}