{
  "type": "Feature",
  "properties": {
    "gn:admin1_code":"25",
    "gn:admin2_code":"11.0",
    "gn:asciiname":"Ejido el Tecomate",
    "gn:country_code":"MX",
    "gn:dem":29,
    "gn:feature_class":"P",
    "gn:feature_code":"PPL",
    "gn:name":"Ejido el Tecomate",
    "gn:population":210,
    "gn:timezone":"America/Mazatlan",
    "iso:country":"MX",
    "wof:name":"Ejido el Tecomate",
    "wof:placetype":"locality",
    "wof:population":210
},
  "geometry": {"coordinates":[-108.35666999999999,25.57639],"type":"Point"}
}