{
  "type": "Feature",
  "properties": {
    "gn:admin1_code":"7",
    "gn:admin2_code":"2.0",
    "gn:asciiname":"La Mula",
    "gn:country_code":"MX",
    "gn:dem":1087,
    "gn:feature_class":"P",
    "gn:feature_code":"PPL",
    "gn:name":"La Mula",
    "gn:population":4,
    "gn:timezone":"America/Matamoros",
    "iso:country":"MX",
    "wof:name":"La Mula",
    "wof:placetype":"locality",
    "wof:population":4
},
  "geometry": {"coordinates":[-102.15125,29.2952],"type":"Point"}
}