{
  "type": "Feature",
  "properties": {
    "gn:admin1_code":"32",
    "gn:admin2_code":"27.0",
    "gn:asciiname":"Las Mesas el Norte",
    "gn:country_code":"MX",
    "gn:dem":1764,
    "gn:feature_class":"P",
    "gn:feature_code":"PPL",
    "gn:name":"Las Mesas el Norte",
    "gn:population":0,
    "gn:timezone":"America/Mexico_City",
    "iso:country":"MX",
    "name:spa_x_preferred":[
        "Las Mesas el Norte"
    ],
    "wof:name":"Las Mesas el Norte",
    "wof:placetype":"locality"
},
  "geometry": {"coordinates":[-101.78919,24.72833],"type":"Point"}
}