{
  "type": "Feature",
  "properties": {
    "gn:admin1_code":"14.0",
    "gn:admin2_code":"43.0",
    "gn:asciiname":"El Guamuchal",
    "gn:country_code":"MX",
    "gn:dem":47,
    "gn:feature_class":"P",
    "gn:feature_code":"PPL",
    "gn:name":"El Guamuchal",
    "gn:population":0,
    "gn:timezone":"America/Mexico_City",
    "iso:country":"MX",
    "name:spa_x_preferred":[
        "El Guamuchal"
    ],
    "wof:name":"El Guamuchal",
    "wof:placetype":"locality"
},
  "geometry": {"coordinates":[-104.89519,19.49671],"type":"Point"}
}