{
  "type": "Feature",
  "properties": {
    "gn:admin1_code":"6",
    "gn:admin2_code":"63.0",
    "gn:asciiname":"Las Huertas",
    "gn:country_code":"MX",
    "gn:dem":1846,
    "gn:feature_class":"P",
    "gn:feature_code":"PPL",
    "gn:name":"Las Huertas",
    "gn:population":0,
    "gn:timezone":"America/Chihuahua",
    "iso:country":"MX",
    "name:und_x_variant":[
        "Rancho Las Huertas",
        "Las Huertas"
    ],
    "wof:name":"Las Huertas",
    "wof:placetype":"locality"
},
  "geometry": {"coordinates":[-107.85645,28.69406],"type":"Point"}
}