{
  "type": "Feature",
  "properties": {
    "gn:admin1_code":"3",
    "gn:admin2_code":"2.0",
    "gn:asciiname":"El Mezquitalito",
    "gn:country_code":"MX",
    "gn:dem":903,
    "gn:feature_class":"P",
    "gn:feature_code":"PPL",
    "gn:name":"El Mezquitalito",
    "gn:population":5,
    "gn:timezone":"America/Mazatlan",
    "iso:country":"MX",
    "wof:name":"El Mezquitalito",
    "wof:placetype":"locality",
    "wof:population":5
},
  "geometry": {"coordinates":[-112.49630999999999,26.99258],"type":"Point"}
}