{
  "type": "Feature",
  "properties": {
    "gn:admin1_code":"5.0",
    "gn:admin2_code":"99.0",
    "gn:asciiname":"El Chiro",
    "gn:country_code":"MX",
    "gn:dem":737,
    "gn:feature_class":"P",
    "gn:feature_code":"PPL",
    "gn:name":"El Chiro",
    "gn:population":0,
    "gn:timezone":"America/Mexico_City",
    "iso:country":"MX",
    "name:spa_x_preferred":[
        "El Chiro"
    ],
    "wof:name":"El Chiro",
    "wof:placetype":"locality"
},
  "geometry": {"coordinates":[-92.02409,15.99197],"type":"Point"}
}