{
  "type": "Feature",
  "properties": {
    "gn:admin1_code":"23",
    "gn:admin2_code":"9.0",
    "gn:asciiname":"Tankah Cuatro",
    "gn:country_code":"MX",
    "gn:dem":4,
    "gn:feature_class":"P",
    "gn:feature_code":"PPL",
    "gn:name":"Tankah Cuatro",
    "gn:population":68,
    "gn:timezone":"America/Cancun",
    "iso:country":"MX",
    "wof:name":"Tankah Cuatro",
    "wof:placetype":"locality",
    "wof:population":68
},
  "geometry": {"coordinates":[-87.37944,20.28361],"type":"Point"}
}