{
  "type": "Feature",
  "properties": {
    "gn:admin1_code":"16",
    "gn:admin2_code":"74",
    "gn:asciiname":"La Llave",
    "gn:country_code":"MX",
    "gn:dem":1536,
    "gn:feature_class":"P",
    "gn:feature_code":"PPL",
    "gn:name":"La Llave",
    "gn:population":22,
    "gn:timezone":"America/Mexico_City",
    "iso:country":"MX",
    "wof:name":"La Llave",
    "wof:placetype":"locality",
    "wof:population":22
},
  "geometry": {"coordinates":[-102.81917,20.10528],"type":"Point"}
}