{
  "type": "Feature",
  "properties": {
    "gn:admin1_code":"29",
    "gn:admin2_code":"41.0",
    "gn:asciiname":"San Buenaventura",
    "gn:country_code":"MX",
    "gn:dem":2190,
    "gn:feature_class":"P",
    "gn:feature_code":"PPL",
    "gn:name":"San Buenaventura",
    "gn:population":0,
    "gn:timezone":"America/Mexico_City",
    "iso:country":"MX",
    "name:spa_x_preferred":[
        "San Buenaventura"
    ],
    "name:und_x_variant":[
        "San Benaventura"
    ],
    "wof:name":"San Buenaventura",
    "wof:placetype":"locality"
},
  "geometry": {"coordinates":[-98.22698,19.15604],"type":"Point"}
}