{
  "type": "Feature",
  "properties": {
    "gn:admin1_code":"21.0",
    "gn:admin2_code":"135.0",
    "gn:asciiname":"Santa Cruz Encinal",
    "gn:country_code":"MX",
    "gn:dem":1823,
    "gn:feature_class":"P",
    "gn:feature_code":"PPL",
    "gn:name":"Santa Cruz Encinal",
    "gn:population":0,
    "gn:timezone":"America/Mexico_City",
    "iso:country":"MX",
    "name:spa_x_preferred":[
        "Santa Cruz Encinal"
    ],
    "wof:name":"Santa Cruz Encinal",
    "wof:placetype":"locality"
},
  "geometry": {"coordinates":[-97.77673,18.05532],"type":"Point"}
}