{
  "type": "Feature",
  "properties": {
    "gn:admin1_code":"16.0",
    "gn:admin2_code":"15.0",
    "gn:asciiname":"Los Molinos",
    "gn:country_code":"MX",
    "gn:dem":1473,
    "gn:feature_class":"P",
    "gn:feature_code":"PPL",
    "gn:name":"Los Molinos",
    "gn:population":0,
    "gn:timezone":"America/Mexico_City",
    "iso:country":"MX",
    "name:ceb_x_preferred":[
        "Los Molinos"
    ],
    "name:fra_x_preferred":[
        "Los Molinos"
    ],
    "name:nld_x_preferred":[
        "Los Molinos"
    ],
    "name:por_x_preferred":[
        "Los Molinos"
    ],
    "name:spa_x_preferred":[
        "Los Molinos"
    ],
    "name:srp_x_preferred":[
        "\u041b\u043e\u0441 \u041c\u043e\u043b\u0438\u043d\u043e\u0441"
    ],
    "name:swe_x_preferred":[
        "Los Molinos"
    ],
    "wof:name":"Los Molinos",
    "wof:placetype":"locality"
},
  "geometry": {"coordinates":[-103.09963,18.63743],"type":"Point"}
}