{
  "type": "Feature",
  "properties": {
    "gn:admin1_code":"14.0",
    "gn:admin2_code":"60.0",
    "gn:asciiname":"Los Tanques Cuates",
    "gn:country_code":"MX",
    "gn:dem":1824,
    "gn:feature_class":"P",
    "gn:feature_code":"PPL",
    "gn:name":"Los Tanques Cuates",
    "gn:population":0,
    "gn:timezone":"America/Mexico_City",
    "iso:country":"MX",
    "name:spa_x_preferred":[
        "Los Tanques Cuates"
    ],
    "wof:name":"Los Tanques Cuates",
    "wof:placetype":"locality"
},
  "geometry": {"coordinates":[-102.71509,21.33177],"type":"Point"}
}