{
  "type": "Feature",
  "properties": {
    "gn:admin1_code":"26",
    "gn:admin2_code":"66.0",
    "gn:asciiname":"Dique Viejo",
    "gn:country_code":"MX",
    "gn:dem":496,
    "gn:feature_class":"P",
    "gn:feature_code":"PPL",
    "gn:name":"Dique Viejo",
    "gn:population":0,
    "gn:timezone":"America/Hermosillo",
    "iso:country":"MX",
    "name:spa_x_preferred":[
        "Dique Viejo"
    ],
    "wof:name":"Dique Viejo",
    "wof:placetype":"locality"
},
  "geometry": {"coordinates":[-110.25320000000001,29.16765],"type":"Point"}
}