{
  "type": "Feature",
  "properties": {
    "gn:admin1_code":"15.0",
    "gn:admin2_code":"8.0",
    "gn:asciiname":"El Panteon de San Felipe",
    "gn:country_code":"MX",
    "gn:dem":1196,
    "gn:feature_class":"P",
    "gn:feature_code":"PPL",
    "gn:name":"El Pante\u00f3n de San Felipe",
    "gn:population":0,
    "gn:timezone":"America/Mexico_City",
    "iso:country":"MX",
    "name:spa_x_preferred":[
        "El Pante\u00f3n de San Felipe"
    ],
    "name:spa_x_variant":[
        "Cuadrilla de Gregorios"
    ],
    "wof:name":"El Panteon de San Felipe",
    "wof:placetype":"locality"
},
  "geometry": {"coordinates":[-100.16078,18.78217],"type":"Point"}
}