{
  "type": "Feature",
  "properties": {
    "gn:admin1_code":"21",
    "gn:admin2_code":"19.0",
    "gn:asciiname":"San Felix Hidalgo",
    "gn:country_code":"MX",
    "gn:dem":1822,
    "gn:feature_class":"P",
    "gn:feature_code":"PPL",
    "gn:name":"San F\u00e9lix Hidalgo",
    "gn:population":0,
    "gn:timezone":"America/Mexico_City",
    "iso:country":"MX",
    "name:und_x_variant":[
        "Ejido San F\u00e9lix Hidalgo",
        "San F\u00e9lix",
        "San F\u00e9lix Hidalgo"
    ],
    "wof:name":"San Felix Hidalgo",
    "wof:placetype":"locality"
},
  "geometry": {"coordinates":[-98.39908,18.89888],"type":"Point"}
}