{
  "type": "Feature",
  "properties": {
    "gn:admin1_code":"30",
    "gn:admin2_code":"15.0",
    "gn:asciiname":"El Zapote",
    "gn:country_code":"MX",
    "gn:dem":63,
    "gn:feature_class":"P",
    "gn:feature_code":"PPL",
    "gn:name":"El Zapote",
    "gn:population":8,
    "gn:timezone":"America/Mexico_City",
    "iso:country":"MX",
    "wof:name":"El Zapote",
    "wof:placetype":"locality",
    "wof:population":8
},
  "geometry": {"coordinates":[-95.38,18.59472],"type":"Point"}
}