{
  "type": "Feature",
  "properties": {
    "gn:admin1_code":"23.0",
    "gn:admin2_code":"8.0",
    "gn:asciiname":"Cuatro Hermanos",
    "gn:country_code":"MX",
    "gn:dem":10,
    "gn:feature_class":"P",
    "gn:feature_code":"PPL",
    "gn:name":"Cuatro Hermanos",
    "gn:population":0,
    "gn:timezone":"America/Cancun",
    "iso:country":"MX",
    "name:spa_x_preferred":[
        "Cuatro Hermanos"
    ],
    "wof:name":"Cuatro Hermanos",
    "wof:placetype":"locality"
},
  "geometry": {"coordinates":[-87.23948,20.49849],"type":"Point"}
}