{
  "type": "Feature",
  "properties": {
    "gn:admin1_code":"5.0",
    "gn:asciiname":"El Portacelis",
    "gn:country_code":"MX",
    "gn:dem":33,
    "gn:feature_class":"P",
    "gn:feature_code":"PPL",
    "gn:name":"El Portacelis",
    "gn:population":0,
    "gn:timezone":"America/Mexico_City",
    "iso:country":"MX",
    "name:spa_x_preferred":[
        "El Portacelis"
    ],
    "wof:name":"El Portacelis",
    "wof:placetype":"locality"
},
  "geometry": {"coordinates":[-93.52503,15.89902],"type":"Point"}
}