{
  "type": "Feature",
  "properties": {
    "gn:admin1_code":"20",
    "gn:admin2_code":"507.0",
    "gn:asciiname":"Callejon de Romulo",
    "gn:country_code":"MX",
    "gn:dem":11,
    "gn:feature_class":"P",
    "gn:feature_code":"PPL",
    "gn:name":"Callej\u00f3n de R\u00f3mulo",
    "gn:population":494,
    "gn:timezone":"America/Mexico_City",
    "iso:country":"MX",
    "name:und_x_variant":[
        "Callej\u00f3n de R\u00f3mulo"
    ],
    "wof:name":"Callejon de Romulo",
    "wof:placetype":"locality",
    "wof:population":494
},
  "geometry": {"coordinates":[-98.35083,16.27222],"type":"Point"}
}