{
  "type": "Feature",
  "properties": {
    "gn:admin1_code":"7.0",
    "gn:admin2_code":"7.0",
    "gn:asciiname":"San Jose el Anteojo",
    "gn:country_code":"MX",
    "gn:dem":737,
    "gn:feature_class":"P",
    "gn:feature_code":"PPL",
    "gn:name":"San Jos\u00e9 el Anteojo",
    "gn:population":0,
    "gn:timezone":"America/Monterrey",
    "iso:country":"MX",
    "name:spa_x_preferred":[
        "San Jos\u00e9 el Anteojo"
    ],
    "name:und_x_variant":[
        "Rancho El Anteojo",
        "El Anteojo",
        "El Anteojito"
    ],
    "wof:name":"San Jose el Anteojo",
    "wof:placetype":"locality"
},
  "geometry": {"coordinates":[-102.12272,26.96919],"type":"Point"}
}