{
  "type": "Feature",
  "properties": {
    "gn:admin1_code":"11",
    "gn:admin2_code":"30.0",
    "gn:asciiname":"La Pila",
    "gn:country_code":"MX",
    "gn:dem":2234,
    "gn:feature_class":"P",
    "gn:feature_code":"PPL",
    "gn:name":"La Pila",
    "gn:population":5,
    "gn:timezone":"America/Mexico_City",
    "iso:country":"MX",
    "name:ceb_x_preferred":[
        "La Pila"
    ],
    "name:ita_x_preferred":[
        "La Pila"
    ],
    "name:srp_x_preferred":[
        "\u041b\u0430 \u041f\u0438\u043b\u0430"
    ],
    "wof:name":"La Pila",
    "wof:placetype":"locality",
    "wof:population":5
},
  "geometry": {"coordinates":[-101.34083,21.78361],"type":"Point"}
}