{
  "type": "Feature",
  "properties": {
    "gn:admin1_code":"11",
    "gn:admin2_code":"9",
    "gn:asciiname":"Hilario Sosa Hernandez (La Granjita)",
    "gn:country_code":"MX",
    "gn:dem":2012,
    "gn:feature_class":"P",
    "gn:feature_code":"PPL",
    "gn:name":"Hilario Sosa Hern\u00e1ndez (La Granjita)",
    "gn:population":17,
    "gn:timezone":"America/Mexico_City",
    "iso:country":"MX",
    "name:und_x_variant":[
        "Hilario Sosa Hern\u00e1ndez (La Granjita)"
    ],
    "wof:name":"Hilario Sosa Hernandez (La Granjita)",
    "wof:placetype":"locality",
    "wof:population":17
},
  "geometry": {"coordinates":[-100.95722000000001,20.7525],"type":"Point"}
}