{
  "type": "Feature",
  "properties": {
    "gn:admin1_code":"14",
    "gn:admin2_code":"49",
    "gn:asciiname":"El Mariz",
    "gn:country_code":"MX",
    "gn:dem":782,
    "gn:feature_class":"P",
    "gn:feature_code":"PPL",
    "gn:name":"El Mar\u00edz",
    "gn:population":17,
    "gn:timezone":"America/Mexico_City",
    "iso:country":"MX",
    "name:und_x_variant":[
        "El Mar\u00edz"
    ],
    "wof:name":"El Mariz",
    "wof:placetype":"locality",
    "wof:population":17
},
  "geometry": {"coordinates":[-103.02806,19.36972],"type":"Point"}
}