{
  "type": "Feature",
  "properties": {
    "gn:admin1_code":"5",
    "gn:admin2_code":"51.0",
    "gn:asciiname":"Claro Leyva Farrera",
    "gn:country_code":"MX",
    "gn:dem":14,
    "gn:feature_class":"P",
    "gn:feature_code":"PPL",
    "gn:name":"Claro Leyva Farrera",
    "gn:population":5,
    "gn:timezone":"America/Mexico_City",
    "iso:country":"MX",
    "wof:name":"Claro Leyva Farrera",
    "wof:placetype":"locality",
    "wof:population":5
},
  "geometry": {"coordinates":[-92.85583,15.34167],"type":"Point"}
}