{
  "type": "Feature",
  "properties": {
    "gn:admin1_code":"9",
    "gn:admin2_code":"12",
    "gn:asciiname":"Cuailacastitla",
    "gn:country_code":"MX",
    "gn:dem":2892,
    "gn:feature_class":"P",
    "gn:feature_code":"PPL",
    "gn:name":"Cuailacastitla",
    "gn:population":13,
    "gn:timezone":"America/Mexico_City",
    "iso:country":"MX",
    "wof:name":"Cuailacastitla",
    "wof:placetype":"locality",
    "wof:population":13
},
  "geometry": {"coordinates":[-99.1675,19.18444],"type":"Point"}
}