{
  "type": "Feature",
  "properties": {
    "gn:admin1_code":"26",
    "gn:admin2_code":"30.0",
    "gn:asciiname":"Colon del Norte",
    "gn:country_code":"MX",
    "gn:dem":101,
    "gn:feature_class":"P",
    "gn:feature_code":"PPL",
    "gn:name":"Col\u00f3n del Norte",
    "gn:population":0,
    "gn:timezone":"America/Hermosillo",
    "iso:country":"MX",
    "name:spa_x_preferred":[
        "Col\u00f3n del Norte"
    ],
    "name:spa_x_variant":[
        "Guamuchilar"
    ],
    "wof:name":"Colon del Norte",
    "wof:placetype":"locality"
},
  "geometry": {"coordinates":[-111.33582,28.87109],"type":"Point"}
}