{
  "type": "Feature",
  "properties": {
    "gn:admin1_code":"6",
    "gn:asciiname":"Los Llanos de San Juan Bautista",
    "gn:cc2":"MX",
    "gn:country_code":"MX",
    "gn:dem":545,
    "gn:feature_class":"P",
    "gn:feature_code":"PPL",
    "gn:name":"Los Llanos de San Juan Bautista",
    "gn:population":0,
    "gn:timezone":"America/Monterrey",
    "iso:country":"MX",
    "name:und_x_variant":[
        "San Juan Bautista",
        "Los Llanos",
        "Los Llanos de San Juan Bautista"
    ],
    "wof:name":"Los Llanos de San Juan Bautista",
    "wof:placetype":"locality"
},
  "geometry": {"coordinates":[-101.01667,28.18333],"type":"Point"}
}