{
  "type": "Feature",
  "properties": {
    "gn:admin1_code":"26",
    "gn:admin2_code":"18.0",
    "gn:asciiname":"Reproductora Pesada 2515 o 2415",
    "gn:country_code":"MX",
    "gn:dem":33,
    "gn:feature_class":"P",
    "gn:feature_code":"PPL",
    "gn:name":"Reproductora Pesada 2515 \u00f3 2415",
    "gn:population":6,
    "gn:timezone":"America/Hermosillo",
    "iso:country":"MX",
    "name:und_x_variant":[
        "Reproductora Pesada 2515 \u00f3 2415"
    ],
    "wof:name":"Reproductora Pesada 2515 o 2415",
    "wof:placetype":"locality",
    "wof:population":6
},
  "geometry": {"coordinates":[-109.89055999999999,27.27194],"type":"Point"}
}