{
  "type": "Feature",
  "properties": {
    "gn:admin1_code":"18.0",
    "gn:admin2_code":"11.0",
    "gn:asciiname":"Los Cimientos",
    "gn:country_code":"MX",
    "gn:dem":907,
    "gn:feature_class":"P",
    "gn:feature_code":"PPL",
    "gn:name":"Los Cimientos",
    "gn:population":0,
    "gn:timezone":"America/Mazatlan",
    "iso:country":"MX",
    "name:spa_x_preferred":[
        "Los Cimientos"
    ],
    "wof:name":"Los Cimientos",
    "wof:placetype":"locality"
},
  "geometry": {"coordinates":[-104.86114000000001,21.9774],"type":"Point"}
}