{
  "type": "Feature",
  "properties": {
    "gn:admin1_code":"6.0",
    "gn:asciiname":"La Noria",
    "gn:country_code":"MX",
    "gn:dem":1176,
    "gn:feature_class":"P",
    "gn:feature_code":"PPL",
    "gn:name":"La Noria",
    "gn:population":0,
    "gn:timezone":"America/Chihuahua",
    "iso:country":"MX",
    "name:spa_x_preferred":[
        "La Noria"
    ],
    "wof:name":"La Noria",
    "wof:placetype":"locality"
},
  "geometry": {"coordinates":[-105.55015,28.21001],"type":"Point"}
}