{
  "type": "Feature",
  "properties": {
    "gn:admin1_code":"11",
    "gn:admin2_code":"9",
    "gn:asciiname":"Alvaro Obregon",
    "gn:country_code":"MX",
    "gn:dem":1795,
    "gn:feature_class":"P",
    "gn:feature_code":"PPL",
    "gn:name":"\u00c1lvaro Obreg\u00f3n",
    "gn:population":25,
    "gn:timezone":"America/Mexico_City",
    "iso:country":"MX",
    "name:und_x_variant":[
        "\u00c1lvaro Obreg\u00f3n"
    ],
    "wof:name":"Alvaro Obregon",
    "wof:placetype":"locality",
    "wof:population":25
},
  "geometry": {"coordinates":[-100.76972000000001,20.69222],"type":"Point"}
}