{
  "type": "Feature",
  "properties": {
    "gn:admin1_code":"24",
    "gn:admin2_code":"28.0",
    "gn:asciiname":"Santo Domingo",
    "gn:country_code":"MX",
    "gn:dem":1783,
    "gn:feature_class":"P",
    "gn:feature_code":"PPL",
    "gn:name":"Santo Domingo",
    "gn:population":55,
    "gn:timezone":"America/Mexico_City",
    "iso:country":"MX",
    "wof:name":"Santo Domingo",
    "wof:placetype":"locality",
    "wof:population":55
},
  "geometry": {"coordinates":[-101.07832999999999,22.54472],"type":"Point"}
}