{
  "type": "Feature",
  "properties": {
    "gn:admin1_code":"5",
    "gn:admin2_code":"17.0",
    "gn:asciiname":"La Candelaria",
    "gn:country_code":"MX",
    "gn:dem":586,
    "gn:feature_class":"P",
    "gn:feature_code":"PPL",
    "gn:name":"La Candelaria",
    "gn:population":5,
    "gn:timezone":"America/Mexico_City",
    "iso:country":"MX",
    "name:ceb_x_preferred":[
        "La Candelaria"
    ],
    "name:deu_x_preferred":[
        "La Candelaria"
    ],
    "name:epo_x_preferred":[
        "La Candelaria"
    ],
    "name:fra_x_preferred":[
        "La Candelaria"
    ],
    "name:glg_x_preferred":[
        "La Candelaria"
    ],
    "name:ita_x_preferred":[
        "La Candelaria"
    ],
    "name:msa_x_preferred":[
        "La Candelaria"
    ],
    "name:nor_x_preferred":[
        "La Candelaria"
    ],
    "name:por_x_preferred":[
        "La Candelaria"
    ],
    "name:spa_x_preferred":[
        "La Candelaria"
    ],
    "wof:name":"La Candelaria",
    "wof:placetype":"locality",
    "wof:population":5
},
  "geometry": {"coordinates":[-93.73860999999999,16.65889],"type":"Point"}
}