{
  "type": "Feature",
  "properties": {
    "gn:admin1_code":"25.0",
    "gn:admin2_code":"10.0",
    "gn:asciiname":"Realito",
    "gn:country_code":"MX",
    "gn:dem":182,
    "gn:feature_class":"P",
    "gn:feature_code":"PPL",
    "gn:name":"Realito",
    "gn:population":0,
    "gn:timezone":"America/Mazatlan",
    "iso:country":"MX",
    "name:spa_x_preferred":[
        "Realito"
    ],
    "name:und_x_variant":[
        "El Realito"
    ],
    "wof:name":"Realito",
    "wof:placetype":"locality"
},
  "geometry": {"coordinates":[-108.47018,26.38336],"type":"Point"}
}