{
  "type": "Feature",
  "properties": {
    "gn:admin1_code":"10",
    "gn:admin2_code":"1.0",
    "gn:asciiname":"Predio Santa Cruz de las Huertas",
    "gn:country_code":"MX",
    "gn:dem":1953,
    "gn:feature_class":"P",
    "gn:feature_code":"PPL",
    "gn:name":"Predio Santa Cruz de las Huertas",
    "gn:population":137,
    "gn:timezone":"America/Monterrey",
    "iso:country":"MX",
    "wof:name":"Predio Santa Cruz de las Huertas",
    "wof:placetype":"locality",
    "wof:population":137
},
  "geometry": {"coordinates":[-104.76528,24.54917],"type":"Point"}
}