{
  "type": "Feature",
  "properties": {
    "gn:admin1_code":"20",
    "gn:admin2_code":"334.0",
    "gn:asciiname":"Maximino Rios",
    "gn:country_code":"MX",
    "gn:dem":15,
    "gn:feature_class":"P",
    "gn:feature_code":"PPL",
    "gn:name":"Maximino R\u00edos",
    "gn:population":7,
    "gn:timezone":"America/Mexico_City",
    "iso:country":"MX",
    "name:und_x_variant":[
        "Maximino R\u00edos"
    ],
    "wof:name":"Maximino Rios",
    "wof:placetype":"locality",
    "wof:population":7
},
  "geometry": {"coordinates":[-97.4175,15.96389],"type":"Point"}
}