{
  "type": "Feature",
  "properties": {
    "gn:admin1_code":"5.0",
    "gn:admin2_code":"37.0",
    "gn:asciiname":"Diecinueve de Abril",
    "gn:country_code":"MX",
    "gn:dem":16,
    "gn:feature_class":"P",
    "gn:feature_code":"PPL",
    "gn:name":"Diecinueve de Abril",
    "gn:population":0,
    "gn:timezone":"America/Mexico_City",
    "iso:country":"MX",
    "name:spa_x_preferred":[
        "Diecinueve de Abril"
    ],
    "wof:name":"Diecinueve de Abril",
    "wof:placetype":"locality"
},
  "geometry": {"coordinates":[-92.47197,14.94571],"type":"Point"}
}