{
  "type": "Feature",
  "properties": {
    "gn:admin1_code":"9",
    "gn:admin2_code":"9.0",
    "gn:asciiname":"Texacazintla (Xacalixpa)",
    "gn:country_code":"MX",
    "gn:dem":2880,
    "gn:feature_class":"P",
    "gn:feature_code":"PPL",
    "gn:name":"Texacazintla (Xacalixpa)",
    "gn:population":96,
    "gn:timezone":"America/Mexico_City",
    "iso:country":"MX",
    "wof:name":"Texacazintla (Xacalixpa)",
    "wof:placetype":"locality",
    "wof:population":96
},
  "geometry": {"coordinates":[-99.07902,19.17797],"type":"Point"}
}