{
  "type": "Feature",
  "properties": {
    "gn:admin1_code":"28.0",
    "gn:admin2_code":"3.0",
    "gn:asciiname":"San Carlitos",
    "gn:country_code":"MX",
    "gn:dem":40,
    "gn:feature_class":"P",
    "gn:feature_code":"PPL",
    "gn:name":"San Carlitos",
    "gn:population":1,
    "gn:timezone":"America/Monterrey",
    "iso:country":"MX",
    "name:spa_x_preferred":[
        "San Carlitos"
    ],
    "wof:name":"San Carlitos",
    "wof:placetype":"locality",
    "wof:population":1
},
  "geometry": {"coordinates":[-98.05988000000001,22.53786],"type":"Point"}
}