{
  "type": "Feature",
  "properties": {
    "gn:admin1_code":"28",
    "gn:asciiname":"El Bayo Rosillo",
    "gn:country_code":"MX",
    "gn:dem":122,
    "gn:feature_class":"P",
    "gn:feature_code":"PPL",
    "gn:name":"El Bayo Rosillo",
    "gn:population":0,
    "gn:timezone":"America/Monterrey",
    "iso:country":"MX",
    "wof:name":"El Bayo Rosillo",
    "wof:placetype":"locality"
},
  "geometry": {"coordinates":[-98.92473,25.08612],"type":"Point"}
}