{
  "type": "Feature",
  "properties": {
    "gn:admin1_code":"32",
    "gn:admin2_code":"14.0",
    "gn:asciiname":"San Jose de Gracia",
    "gn:country_code":"MX",
    "gn:dem":2036,
    "gn:feature_class":"P",
    "gn:feature_code":"PPL",
    "gn:name":"San Jose de Gracia",
    "gn:population":0,
    "gn:timezone":"America/Mexico_City",
    "iso:country":"MX",
    "name:spa_x_preferred":[
        "San Jose de Gracia"
    ],
    "name:und_x_variant":[
        "San Jos\u00e9"
    ],
    "wof:name":"San Jose de Gracia",
    "wof:placetype":"locality"
},
  "geometry": {"coordinates":[-103.15589,24.20996],"type":"Point"}
}