{
  "type": "Feature",
  "properties": {
    "gn:admin1_code":"20",
    "gn:admin2_code":"505.0",
    "gn:asciiname":"Ocotal",
    "gn:country_code":"MX",
    "gn:dem":247,
    "gn:feature_class":"P",
    "gn:feature_code":"PPL",
    "gn:name":"Ocotal",
    "gn:population":0,
    "gn:timezone":"America/Mexico_City",
    "iso:country":"MX",
    "wof:name":"Ocotal",
    "wof:placetype":"locality"
},
  "geometry": {"coordinates":[-94.66667,16.63332999999999],"type":"Point"}
}