{
  "type": "Feature",
  "properties": {
    "gn:admin1_code":"6",
    "gn:admin2_code":"63.0",
    "gn:asciiname":"Pino Redondeado",
    "gn:country_code":"MX",
    "gn:dem":1926,
    "gn:feature_class":"P",
    "gn:feature_code":"PPL",
    "gn:name":"Pino Redondeado",
    "gn:population":0,
    "gn:timezone":"America/Chihuahua",
    "iso:country":"MX",
    "name:spa_x_preferred":[
        "Pino Redondeado"
    ],
    "wof:name":"Pino Redondeado",
    "wof:placetype":"locality"
},
  "geometry": {"coordinates":[-108.38396000000002,28.38659],"type":"Point"}
}