{
  "type": "Feature",
  "properties": {
    "gn:admin1_code":"32",
    "gn:admin2_code":"42.0",
    "gn:asciiname":"La Parada",
    "gn:country_code":"MX",
    "gn:dem":2142,
    "gn:feature_class":"P",
    "gn:feature_code":"PPL",
    "gn:name":"La Parada",
    "gn:population":0,
    "gn:timezone":"America/Mexico_City",
    "iso:country":"MX",
    "wof:name":"La Parada",
    "wof:placetype":"locality"
},
  "geometry": {"coordinates":[-103.65000000000001,23.53333],"type":"Point"}
}