{
  "type": "Feature",
  "properties": {
    "gn:admin1_code":"6.0",
    "gn:admin2_code":"29.0",
    "gn:asciiname":"Arroyo los Estantes",
    "gn:country_code":"MX",
    "gn:dem":2432,
    "gn:feature_class":"P",
    "gn:feature_code":"PPL",
    "gn:name":"Arroyo los Estantes",
    "gn:population":0,
    "gn:timezone":"America/Chihuahua",
    "iso:country":"MX",
    "name:spa_x_preferred":[
        "Arroyo los Estantes"
    ],
    "wof:name":"Arroyo los Estantes",
    "wof:placetype":"locality"
},
  "geometry": {"coordinates":[-106.77294000000001,25.95782],"type":"Point"}
}