{
  "type": "Feature",
  "properties": {
    "gn:admin1_code":"30.0",
    "gn:admin2_code":"4.0",
    "gn:asciiname":"Rancho Nuevo Dos",
    "gn:country_code":"MX",
    "gn:dem":183,
    "gn:feature_class":"P",
    "gn:feature_code":"PPL",
    "gn:name":"Rancho Nuevo Dos",
    "gn:population":0,
    "gn:timezone":"America/Mexico_City",
    "iso:country":"MX",
    "name:spa_x_preferred":[
        "Rancho Nuevo Dos"
    ],
    "wof:name":"Rancho Nuevo Dos",
    "wof:placetype":"locality"
},
  "geometry": {"coordinates":[-96.57704,19.49377],"type":"Point"}
}