{
  "type": "Feature",
  "properties": {
    "gn:admin1_code":"24",
    "gn:admin2_code":"10.0",
    "gn:asciiname":"Desmonte",
    "gn:country_code":"MX",
    "gn:dem":1332,
    "gn:feature_class":"P",
    "gn:feature_code":"PPL",
    "gn:name":"Desmonte",
    "gn:population":0,
    "gn:timezone":"America/Mexico_City",
    "iso:country":"MX",
    "wof:name":"Desmonte",
    "wof:placetype":"locality"
},
  "geometry": {"coordinates":[-99.46666999999999,22.26667],"type":"Point"}
}