{
  "type": "Feature",
  "properties": {
    "gn:admin1_code":"32",
    "gn:admin2_code":"26.0",
    "gn:asciiname":"Tortugas",
    "gn:country_code":"MX",
    "gn:dem":2032,
    "gn:feature_class":"P",
    "gn:feature_code":"PPL",
    "gn:name":"Tortugas",
    "gn:population":0,
    "gn:timezone":"America/Mexico_City",
    "iso:country":"MX",
    "name:spa_x_preferred":[
        "Tortugas"
    ],
    "name:und_x_variant":[
        "La Tortuga"
    ],
    "wof:name":"Tortugas",
    "wof:placetype":"locality"
},
  "geometry": {"coordinates":[-102.1525,24.67128],"type":"Point"}
}