{
  "type": "Feature",
  "properties": {
    "gn:admin1_code":"20",
    "gn:admin2_code":"277.0",
    "gn:asciiname":"Yolere",
    "gn:country_code":"MX",
    "gn:dem":1545,
    "gn:feature_class":"P",
    "gn:feature_code":"PPL",
    "gn:name":"Yoler\u00e9",
    "gn:population":5,
    "gn:timezone":"America/Mexico_City",
    "iso:country":"MX",
    "name:und_x_variant":[
        "Yoler\u00e9"
    ],
    "wof:name":"Yolere",
    "wof:placetype":"locality",
    "wof:population":5
},
  "geometry": {"coordinates":[-96.98389,16.49611],"type":"Point"}
}