{
  "type": "Feature",
  "properties": {
    "gn:admin1_code":"28",
    "gn:admin2_code":"33.0",
    "gn:asciiname":"Irrigacion Palmito",
    "gn:country_code":"MX",
    "gn:dem":20,
    "gn:feature_class":"P",
    "gn:feature_code":"PPL",
    "gn:name":"Irrigaci\u00f3n Palmito",
    "gn:population":34,
    "gn:timezone":"America/Monterrey",
    "iso:country":"MX",
    "wof:name":"Irrigacion Palmito",
    "wof:placetype":"locality",
    "wof:population":34
},
  "geometry": {"coordinates":[-97.96862,25.53654],"type":"Point"}
}