{
  "type": "Feature",
  "properties": {
    "gn:admin1_code":"17",
    "gn:admin2_code":"25",
    "gn:asciiname":"Paso de Palapa",
    "gn:country_code":"MX",
    "gn:dem":801,
    "gn:feature_class":"P",
    "gn:feature_code":"PPL",
    "gn:name":"Paso de Palapa",
    "gn:population":15,
    "gn:timezone":"America/Mexico_City",
    "iso:country":"MX",
    "wof:name":"Paso de Palapa",
    "wof:placetype":"locality",
    "wof:population":15
},
  "geometry": {"coordinates":[-99.14,18.53],"type":"Point"}
}