{
  "type": "Feature",
  "properties": {
    "gn:admin1_code":"6",
    "gn:admin2_code":"46.0",
    "gn:asciiname":"Rancho Coheche",
    "gn:country_code":"MX",
    "gn:dem":1776,
    "gn:feature_class":"P",
    "gn:feature_code":"PPL",
    "gn:name":"Rancho Coheche",
    "gn:population":0,
    "gn:timezone":"America/Chihuahua",
    "iso:country":"MX",
    "name:spa_x_preferred":[
        "Rancho Coheche"
    ],
    "wof:name":"Rancho Coheche",
    "wof:placetype":"locality"
},
  "geometry": {"coordinates":[-107.6185,26.48699],"type":"Point"}
}