{
  "type": "Feature",
  "properties": {
    "gn:admin1_code":"28.0",
    "gn:admin2_code":"35.0",
    "gn:asciiname":"Luz Maria",
    "gn:country_code":"MX",
    "gn:dem":13,
    "gn:feature_class":"P",
    "gn:feature_code":"PPL",
    "gn:name":"Luz Mar\u00eda",
    "gn:population":4,
    "gn:timezone":"America/Monterrey",
    "iso:country":"MX",
    "name:spa_x_preferred":[
        "Luz Mar\u00eda"
    ],
    "wof:name":"Luz Maria",
    "wof:placetype":"locality",
    "wof:population":4
},
  "geometry": {"coordinates":[-97.91722,24.85778],"type":"Point"}
}