{
  "type": "Feature",
  "properties": {
    "gn:admin1_code":"11",
    "gn:admin2_code":"32.0",
    "gn:asciiname":"La Acequia (Las Canoas)",
    "gn:country_code":"MX",
    "gn:dem":2100,
    "gn:feature_class":"P",
    "gn:feature_code":"PPL",
    "gn:name":"La Acequia (Las Canoas)",
    "gn:population":62,
    "gn:timezone":"America/Mexico_City",
    "iso:country":"MX",
    "wof:name":"La Acequia (Las Canoas)",
    "wof:placetype":"locality",
    "wof:population":62
},
  "geometry": {"coordinates":[-100.35444,21.05778],"type":"Point"}
}