{
  "type": "Feature",
  "properties": {
    "gn:admin1_code":"16",
    "gn:admin2_code":"55",
    "gn:asciiname":"Cama de Piedra",
    "gn:country_code":"MX",
    "gn:dem":363,
    "gn:feature_class":"P",
    "gn:feature_code":"PPL",
    "gn:name":"Cama de Piedra",
    "gn:population":12,
    "gn:timezone":"America/Mexico_City",
    "iso:country":"MX",
    "wof:name":"Cama de Piedra",
    "wof:placetype":"locality",
    "wof:population":12
},
  "geometry": {"coordinates":[-102.13222,18.99056],"type":"Point"}
}