{
  "type": "Feature",
  "properties": {
    "gn:admin1_code":"32",
    "gn:admin2_code":"36.0",
    "gn:asciiname":"Lluvia de Estrellas",
    "gn:country_code":"MX",
    "gn:dem":2088,
    "gn:feature_class":"P",
    "gn:feature_code":"PPL",
    "gn:name":"Lluvia de Estrellas",
    "gn:population":8,
    "gn:timezone":"America/Mexico_City",
    "iso:country":"MX",
    "wof:name":"Lluvia de Estrellas",
    "wof:placetype":"locality",
    "wof:population":8
},
  "geometry": {"coordinates":[-102.23694,22.56472],"type":"Point"}
}