{
  "type": "Feature",
  "properties": {
    "gn:admin1_code":"10",
    "gn:admin2_code":"23",
    "gn:asciiname":"El Carrizo",
    "gn:country_code":"MX",
    "gn:dem":1576,
    "gn:feature_class":"P",
    "gn:feature_code":"PPL",
    "gn:name":"El Carrizo",
    "gn:population":25,
    "gn:timezone":"America/Monterrey",
    "iso:country":"MX",
    "wof:name":"El Carrizo",
    "wof:placetype":"locality",
    "wof:population":25
},
  "geometry": {"coordinates":[-104.85438000000001,23.181],"type":"Point"}
}