{
  "type": "Feature",
  "properties": {
    "gn:admin1_code":"14",
    "gn:admin2_code":"99.0",
    "gn:asciiname":"Toxin",
    "gn:country_code":"MX",
    "gn:dem":1260,
    "gn:feature_class":"P",
    "gn:feature_code":"PPL",
    "gn:name":"Tox\u00edn",
    "gn:population":0,
    "gn:timezone":"America/Mexico_City",
    "iso:country":"MX",
    "wof:name":"Toxin",
    "wof:placetype":"locality"
},
  "geometry": {"coordinates":[-103.86667,19.46667],"type":"Point"}
}