{
  "type": "Feature",
  "properties": {
    "gn:admin1_code":"24",
    "gn:admin2_code":"50.0",
    "gn:asciiname":"Alberto Carrera Torres",
    "gn:country_code":"MX",
    "gn:dem":1841,
    "gn:feature_class":"P",
    "gn:feature_code":"PPL",
    "gn:name":"Alberto Carrera Torres",
    "gn:population":0,
    "gn:timezone":"America/Mexico_City",
    "iso:country":"MX",
    "name:spa_x_preferred":[
        "Alberto Carrera Torres"
    ],
    "wof:name":"Alberto Carrera Torres",
    "wof:placetype":"locality"
},
  "geometry": {"coordinates":[-101.01193000000001,21.7724],"type":"Point"}
}