{
  "type": "Feature",
  "properties": {
    "gn:admin1_code":"27",
    "gn:admin2_code":"13.0",
    "gn:asciiname":"El Cometa",
    "gn:country_code":"MX",
    "gn:dem":5,
    "gn:feature_class":"P",
    "gn:feature_code":"PPL",
    "gn:name":"El Cometa",
    "gn:population":66,
    "gn:timezone":"America/Mexico_City",
    "iso:country":"MX",
    "wof:name":"El Cometa",
    "wof:placetype":"locality",
    "wof:population":66
},
  "geometry": {"coordinates":[-92.9075,18.19083],"type":"Point"}
}