{
  "type": "Feature",
  "properties": {
    "gn:admin1_code":"30.0",
    "gn:admin2_code":"83.0",
    "gn:asciiname":"Los Lagartos",
    "gn:country_code":"MX",
    "gn:dem":223,
    "gn:feature_class":"P",
    "gn:feature_code":"PPL",
    "gn:name":"Los Lagartos",
    "gn:population":2,
    "gn:timezone":"America/Mexico_City",
    "iso:country":"MX",
    "name:spa_x_preferred":[
        "Los Lagartos"
    ],
    "wof:name":"Los Lagartos",
    "wof:placetype":"locality",
    "wof:population":2
},
  "geometry": {"coordinates":[-97.9875,20.64444],"type":"Point"}
}