{
  "type": "Feature",
  "properties": {
    "gn:admin1_code":"14",
    "gn:admin2_code":"44",
    "gn:asciiname":"El Cerrito",
    "gn:country_code":"MX",
    "gn:dem":1562,
    "gn:feature_class":"P",
    "gn:feature_code":"PPL",
    "gn:name":"El Cerrito",
    "gn:population":11,
    "gn:timezone":"America/Mexico_City",
    "iso:country":"MX",
    "wof:name":"El Cerrito",
    "wof:placetype":"locality",
    "wof:population":11
},
  "geometry": {"coordinates":[-103.20583000000001,20.3875],"type":"Point"}
}