{
  "type": "Feature",
  "properties": {
    "gn:admin1_code":"14",
    "gn:admin2_code":"47.0",
    "gn:asciiname":"Grupo del Refugio",
    "gn:country_code":"MX",
    "gn:dem":1536,
    "gn:feature_class":"P",
    "gn:feature_code":"PPL",
    "gn:name":"Grupo del Refugio",
    "gn:population":8,
    "gn:timezone":"America/Mexico_City",
    "iso:country":"MX",
    "wof:name":"Grupo del Refugio",
    "wof:placetype":"locality",
    "wof:population":8
},
  "geometry": {"coordinates":[-102.60527999999999,20.29139],"type":"Point"}
}