{
  "type": "Feature",
  "properties": {
    "gn:admin1_code":"6.0",
    "gn:admin2_code":"48.0",
    "gn:asciiname":"Ortega",
    "gn:country_code":"MX",
    "gn:dem":1882,
    "gn:feature_class":"P",
    "gn:feature_code":"PPL",
    "gn:name":"Ortega",
    "gn:population":0,
    "gn:timezone":"America/Chihuahua",
    "iso:country":"MX",
    "name:spa_x_preferred":[
        "Ortega"
    ],
    "name:spa_x_variant":[
        "Rancho Ortega"
    ],
    "wof:name":"Ortega",
    "wof:placetype":"locality"
},
  "geometry": {"coordinates":[-107.4701,29.01092],"type":"Point"}
}