{
  "type": "Feature",
  "properties": {
    "gn:admin1_code":"7.0",
    "gn:admin2_code":"23.0",
    "gn:asciiname":"La Fortuna",
    "gn:country_code":"MX",
    "gn:dem":1257,
    "gn:feature_class":"P",
    "gn:feature_code":"PPL",
    "gn:name":"La Fortuna",
    "gn:population":0,
    "gn:timezone":"America/Monterrey",
    "iso:country":"MX",
    "name:ceb_x_preferred":[
        "La Fortuna"
    ],
    "name:deu_x_preferred":[
        "O Fortuna"
    ],
    "name:fra_x_preferred":[
        "La Fortuna"
    ],
    "name:spa_x_preferred":[
        "La Fortuna"
    ],
    "name:spa_x_variant":[
        "Fortuna de Arocha"
    ],
    "name:srp_x_preferred":[
        "\u041b\u0430 \u0424\u043e\u0440\u0442\u0443\u043d\u0430"
    ],
    "name:swe_x_preferred":[
        "La Fortuna"
    ],
    "name:und_x_variant":[
        "Rancho La Fortuna"
    ],
    "wof:name":"La Fortuna",
    "wof:placetype":"locality"
},
  "geometry": {"coordinates":[-102.44154,27.83541],"type":"Point"}
}