{
  "type": "Feature",
  "properties": {
    "gn:country":"MX",
    "gn:fcode":"PPL",
    "gn:population":5965,
    "iso:country":"MX",
    "name:spa_x_preferred":[
        "El Triunfo"
    ],
    "name:spa_x_variant":[
        "Villa el Triunfo"
    ],
    "qs_pg:aaroncc":"MX",
    "qs_pg:gn_country":"MX",
    "qs_pg:gn_fcode":"PPL",
    "qs_pg:gn_pop":5965,
    "qs_pg:name":"Villa El Triunfo",
    "qs_pg:name_adm0":"M\u00e9xico",
    "qs_pg:name_adm1":"Tabasco",
    "qs_pg:photos_9r":0,
    "qs_pg:photos_sr":0,
    "qs_pg:pop_sr":5,
    "qs_pg:qs_pg_placetype":"locality",
    "qs_pg:qs_pg_placetype_gp":"Town",
    "qs_pg:woe_adm0":23424900,
    "woe:adm0_id":23424900,
    "woe:name_adm0":"M\u00e9xico",
    "woe:name_adm1":"Tabasco",
    "woe:placetype":"Town",
    "wof:name":"Villa El Triunfo",
    "wof:placetype":"locality",
    "wof:population":5965
},
  "geometry": {"coordinates":[-91.17049,17.92323],"type":"Point"}
}