{
  "type": "Feature",
  "properties": {
    "gn:admin1_code":"30",
    "gn:admin2_code":"121",
    "gn:asciiname":"El Paraiso",
    "gn:country_code":"MX",
    "gn:dem":37,
    "gn:feature_class":"P",
    "gn:feature_code":"PPL",
    "gn:name":"El Para\u00edso",
    "gn:population":23,
    "gn:timezone":"America/Mexico_City",
    "iso:country":"MX",
    "name:und_x_variant":[
        "El Para\u00edso"
    ],
    "wof:name":"El Paraiso",
    "wof:placetype":"locality",
    "wof:population":23
},
  "geometry": {"coordinates":[-97.90167,21.78556],"type":"Point"}
}