{
  "type": "Feature",
  "properties": {
    "gn:admin1_code":"30",
    "gn:admin2_code":"148.0",
    "gn:asciiname":"Mata Copite",
    "gn:country_code":"MX",
    "gn:dem":89,
    "gn:feature_class":"P",
    "gn:feature_code":"PPL",
    "gn:name":"Mata Copite",
    "gn:population":6,
    "gn:timezone":"America/Mexico_City",
    "iso:country":"MX",
    "wof:name":"Mata Copite",
    "wof:placetype":"locality",
    "wof:population":6
},
  "geometry": {"coordinates":[-96.39389,18.99222],"type":"Point"}
}