{
  "type": "Feature",
  "properties": {
    "gn:admin1_code":"24.0",
    "gn:admin2_code":"41.0",
    "gn:asciiname":"La Bomba",
    "gn:country_code":"MX",
    "gn:dem":41,
    "gn:feature_class":"P",
    "gn:feature_code":"PPL",
    "gn:name":"La Bomba",
    "gn:population":0,
    "gn:timezone":"America/Mexico_City",
    "iso:country":"MX",
    "name:spa_x_preferred":[
        "La Bomba"
    ],
    "wof:name":"La Bomba",
    "wof:placetype":"locality"
},
  "geometry": {"coordinates":[-98.83767,21.81887],"type":"Point"}
}