{
  "type": "Feature",
  "properties": {
    "gn:admin1_code":"5",
    "gn:admin2_code":"99.0",
    "gn:asciiname":"Jose Castillo Tielemans",
    "gn:country_code":"MX",
    "gn:dem":468,
    "gn:feature_class":"P",
    "gn:feature_code":"PPL",
    "gn:name":"Jos\u00e9 Castillo Ti\u00e9lemans",
    "gn:population":365,
    "gn:timezone":"America/Mexico_City",
    "iso:country":"MX",
    "name:und_x_variant":[
        "Jos\u00e9 Castillo Ti\u00e9lemans"
    ],
    "wof:name":"Jose Castillo Tielemans",
    "wof:placetype":"locality",
    "wof:population":365
},
  "geometry": {"coordinates":[-91.40889,16.10889],"type":"Point"}
}