{
  "type": "Feature",
  "properties": {
    "gn:admin1_code":"5.0",
    "gn:admin2_code":"24.0",
    "gn:asciiname":"Sakilchen",
    "gn:country_code":"MX",
    "gn:dem":1853,
    "gn:feature_class":"P",
    "gn:feature_code":"PPL",
    "gn:name":"Sakilchen",
    "gn:population":0,
    "gn:timezone":"America/Mexico_City",
    "iso:country":"MX",
    "name:spa_x_preferred":[
        "Sakilchen"
    ],
    "wof:name":"Sakilchen",
    "wof:placetype":"locality"
},
  "geometry": {"coordinates":[-92.16030000000001,16.66749],"type":"Point"}
}