{
  "type": "Feature",
  "properties": {
    "gn:admin1_code":"24",
    "gn:admin2_code":"32.0",
    "gn:asciiname":"Santa Anita",
    "gn:country_code":"MX",
    "gn:dem":1951,
    "gn:feature_class":"P",
    "gn:feature_code":"PPL",
    "gn:name":"Santa Anita",
    "gn:population":0,
    "gn:timezone":"America/Mexico_City",
    "iso:country":"MX",
    "name:ceb_x_preferred":[
        "Santa Anita"
    ],
    "name:deu_x_preferred":[
        "Santa Anita"
    ],
    "name:spa_x_preferred":[
        "Santa Anita"
    ],
    "name:srp_x_preferred":[
        "\u0421\u0430\u043d\u0442\u0430 \u0410\u043d\u0438\u0442\u0430"
    ],
    "name:swe_x_preferred":[
        "Santa Anita"
    ],
    "wof:name":"Santa Anita",
    "wof:placetype":"locality"
},
  "geometry": {"coordinates":[-100.62367999999999,21.5842],"type":"Point"}
}