{
  "type": "Feature",
  "properties": {
    "gn:admin1_code":"28.0",
    "gn:admin2_code":"39.0",
    "gn:asciiname":"El Cascabel",
    "gn:country_code":"MX",
    "gn:dem":1496,
    "gn:feature_class":"P",
    "gn:feature_code":"PPL",
    "gn:name":"El Cascabel",
    "gn:population":0,
    "gn:timezone":"America/Monterrey",
    "iso:country":"MX",
    "name:spa_x_preferred":[
        "El Cascabel"
    ],
    "wof:name":"El Cascabel",
    "wof:placetype":"locality"
},
  "geometry": {"coordinates":[-99.64278,22.91083],"type":"Point"}
}