{
  "type": "Feature",
  "properties": {
    "gn:admin1_code":"17.0",
    "gn:asciiname":"Ejido Santa Ana Venshu",
    "gn:country_code":"MX",
    "gn:dem":2572,
    "gn:feature_class":"P",
    "gn:feature_code":"PPL",
    "gn:name":"Ejido Santa Ana Venshu",
    "gn:population":0,
    "gn:timezone":"America/Mexico_City",
    "iso:country":"MX",
    "name:und_x_variant":[
        "La Venta",
        "Ejido Santa Ana Venshu"
    ],
    "wof:name":"Ejido Santa Ana Venshu",
    "wof:placetype":"locality"
},
  "geometry": {"coordinates":[-100.02725,19.82185],"type":"Point"}
}