{
  "type": "Feature",
  "properties": {
    "gn:admin1_code":"32.0",
    "gn:asciiname":"La Cantera",
    "gn:country_code":"MX",
    "gn:dem":2394,
    "gn:feature_class":"P",
    "gn:feature_code":"PPL",
    "gn:name":"La Cantera",
    "gn:population":0,
    "gn:timezone":"America/Mexico_City",
    "iso:country":"MX",
    "name:spa_x_preferred":[
        "La Cantera"
    ],
    "wof:name":"La Cantera",
    "wof:placetype":"locality"
},
  "geometry": {"coordinates":[-101.59978,22.35452],"type":"Point"}
}