{
  "type": "Feature",
  "properties": {
    "gn:admin1_code":"24",
    "gn:admin2_code":"58.0",
    "gn:asciiname":"Kilometro Cuarenta y Dos",
    "gn:country_code":"MX",
    "gn:dem":274,
    "gn:feature_class":"P",
    "gn:feature_code":"PPL",
    "gn:name":"Kil\u00f3metro Cuarenta y Dos",
    "gn:population":0,
    "gn:timezone":"America/Mexico_City",
    "iso:country":"MX",
    "name:spa_x_preferred":[
        "Kil\u00f3metro Cuarenta y Dos"
    ],
    "wof:name":"Kilometro Cuarenta y Dos",
    "wof:placetype":"locality"
},
  "geometry": {"coordinates":[-99.31198000000001,22.45156],"type":"Point"}
}