{
  "type": "Feature",
  "properties": {
    "gn:admin1_code":"30.0",
    "gn:asciiname":"La Matatena",
    "gn:country_code":"MX",
    "gn:dem":114,
    "gn:feature_class":"P",
    "gn:feature_code":"PPL",
    "gn:name":"La Matatena",
    "gn:population":0,
    "gn:timezone":"America/Mexico_City",
    "iso:country":"MX",
    "name:spa_x_preferred":[
        "La Matatena"
    ],
    "wof:name":"La Matatena",
    "wof:placetype":"locality"
},
  "geometry": {"coordinates":[-95.00114000000001,17.90442999999999],"type":"Point"}
}