{
  "type": "Feature",
  "properties": {
    "gn:admin1_code":"15",
    "gn:admin2_code":"1.0",
    "gn:asciiname":"Las Chivas (El Cerro)",
    "gn:country_code":"MX",
    "gn:dem":2737,
    "gn:feature_class":"P",
    "gn:feature_code":"PPL",
    "gn:name":"Las Chivas (El Cerro)",
    "gn:population":59,
    "gn:timezone":"America/Mexico_City",
    "iso:country":"MX",
    "wof:name":"Las Chivas (El Cerro)",
    "wof:placetype":"locality",
    "wof:population":59
},
  "geometry": {"coordinates":[-99.79389999999999,19.85119],"type":"Point"}
}