{
  "type": "Feature",
  "properties": {
    "gn:admin1_code":"12",
    "gn:admin2_code":"63.0",
    "gn:asciiname":"Plan Jacaranda",
    "gn:country_code":"MX",
    "gn:dem":1305,
    "gn:feature_class":"P",
    "gn:feature_code":"PPL",
    "gn:name":"Plan Jacaranda",
    "gn:population":122,
    "gn:timezone":"America/Mexico_City",
    "iso:country":"MX",
    "wof:name":"Plan Jacaranda",
    "wof:placetype":"locality",
    "wof:population":122
},
  "geometry": {"coordinates":[-98.8159,17.2097],"type":"Point"}
}