{
  "type": "Feature",
  "properties": {
    "gn:admin1_code":"16",
    "gn:admin2_code":"112.0",
    "gn:asciiname":"La Presa (Segunda Manzana Barrio de Santa Cruz)",
    "gn:country_code":"MX",
    "gn:dem":2167,
    "gn:feature_class":"P",
    "gn:feature_code":"PPL",
    "gn:name":"La Presa (Segunda Manzana Barrio de Santa Cruz)",
    "gn:population":535,
    "gn:timezone":"America/Mexico_City",
    "iso:country":"MX",
    "wof:name":"La Presa (Segunda Manzana Barrio de Santa Cruz)",
    "wof:placetype":"locality",
    "wof:population":535
},
  "geometry": {"coordinates":[-100.40778,19.52861],"type":"Point"}
}