{
  "type": "Feature",
  "properties": {
    "gn:admin1_code":"6.0",
    "gn:admin2_code":"16.0",
    "gn:asciiname":"La Puerta",
    "gn:country_code":"MX",
    "gn:dem":1380,
    "gn:feature_class":"P",
    "gn:feature_code":"PPL",
    "gn:name":"La Puerta",
    "gn:population":3,
    "gn:timezone":"America/Chihuahua",
    "iso:country":"MX",
    "name:spa_x_preferred":[
        "La Puerta"
    ],
    "wof:name":"La Puerta",
    "wof:placetype":"locality",
    "wof:population":3
},
  "geometry": {"coordinates":[-105.02517,27.873],"type":"Point"}
}