{
  "type": "Feature",
  "properties": {
    "gn:admin1_code":"6",
    "gn:admin2_code":"30",
    "gn:asciiname":"Las Animas",
    "gn:country_code":"MX",
    "gn:dem":1483,
    "gn:feature_class":"P",
    "gn:feature_code":"PPL",
    "gn:name":"Las \u00c1nimas",
    "gn:population":17,
    "gn:timezone":"America/Chihuahua",
    "iso:country":"MX",
    "name:ceb_x_preferred":[
        "Las Animas"
    ],
    "name:deu_x_preferred":[
        "Las \u00c1nimas"
    ],
    "name:nld_x_preferred":[
        "Las Animas"
    ],
    "name:pol_x_preferred":[
        "Las Animas"
    ],
    "name:spa_x_preferred":[
        "Las \u00c1nimas"
    ],
    "name:srp_x_preferred":[
        "\u041b\u0430\u0441 \u0410\u043d\u0438\u043c\u0430\u0441"
    ],
    "name:swe_x_preferred":[
        "Las Animas"
    ],
    "name:und_x_variant":[
        "Las \u00c1nimas"
    ],
    "wof:name":"Las Animas",
    "wof:placetype":"locality",
    "wof:population":17
},
  "geometry": {"coordinates":[-108.20659000000001,27.4202],"type":"Point"}
}