{
  "type": "Feature",
  "properties": {
    "gn:admin1_code":"3.0",
    "gn:admin2_code":"3.0",
    "gn:asciiname":"Guamuchil",
    "gn:country_code":"MX",
    "gn:dem":177,
    "gn:feature_class":"P",
    "gn:feature_code":"PPL",
    "gn:name":"Guamuchil",
    "gn:population":0,
    "gn:timezone":"America/Mazatlan",
    "iso:country":"MX",
    "name:spa_x_preferred":[
        "Guamuchil"
    ],
    "name:und_x_variant":[
        "El Huamuchil",
        "Guaymochile",
        "Guam\u00fachil"
    ],
    "wof:name":"Guamuchil",
    "wof:placetype":"locality"
},
  "geometry": {"coordinates":[-110.44774,23.94811],"type":"Point"}
}