{
  "type": "Feature",
  "properties": {
    "gn:admin1_code":"5",
    "gn:admin2_code":"6.0",
    "gn:asciiname":"Platanillo",
    "gn:country_code":"MX",
    "gn:dem":1617,
    "gn:feature_class":"P",
    "gn:feature_code":"PPL",
    "gn:name":"Platanillo",
    "gn:population":153,
    "gn:timezone":"America/Mexico_City",
    "iso:country":"MX",
    "name:ceb_x_preferred":[
        "Platanillo"
    ],
    "name:spa_x_preferred":[
        "Platanillo"
    ],
    "name:swe_x_preferred":[
        "Platanillo"
    ],
    "wof:name":"Platanillo",
    "wof:placetype":"locality",
    "wof:population":153
},
  "geometry": {"coordinates":[-92.09528,15.47778],"type":"Point"}
}