{
  "type": "Feature",
  "properties": {
    "gn:admin1_code":"14",
    "gn:admin2_code":"91.0",
    "gn:asciiname":"El Saucito",
    "gn:country_code":"MX",
    "gn:dem":1965,
    "gn:feature_class":"P",
    "gn:feature_code":"PPL",
    "gn:name":"El Saucito",
    "gn:population":222,
    "gn:timezone":"America/Mexico_City",
    "iso:country":"MX",
    "wof:name":"El Saucito",
    "wof:placetype":"locality",
    "wof:population":222
},
  "geometry": {"coordinates":[-102.65778,21.5675],"type":"Point"}
}