{
  "type": "Feature",
  "properties": {
    "gn:admin1_code":"26.0",
    "gn:admin2_code":"14.0",
    "gn:asciiname":"Estancia",
    "gn:country_code":"MX",
    "gn:dem":581,
    "gn:feature_class":"P",
    "gn:feature_code":"PPL",
    "gn:name":"Estancia",
    "gn:population":0,
    "gn:timezone":"America/Hermosillo",
    "iso:country":"MX",
    "name:cat_x_preferred":[
        "Estancia"
    ],
    "name:deu_x_preferred":[
        "Estancia"
    ],
    "name:fra_x_preferred":[
        "Estancia"
    ],
    "name:kor_x_preferred":[
        "\uc5d0\uc2a4\ud0c4\uc2dc\uc544"
    ],
    "name:pol_x_preferred":[
        "Estancja"
    ],
    "name:por_x_preferred":[
        "Est\u00e2ncia"
    ],
    "name:spa_x_preferred":[
        "Estancia"
    ],
    "name:swe_x_preferred":[
        "Estancia"
    ],
    "wof:name":"Estancia",
    "wof:placetype":"locality"
},
  "geometry": {"coordinates":[-110.15000000000001,29.56667],"type":"Point"}
}