{
  "type": "Feature",
  "properties": {
    "gn:admin1_code":"21",
    "gn:admin2_code":"208.0",
    "gn:asciiname":"Tlalhuapan",
    "gn:country_code":"MX",
    "gn:dem":1031,
    "gn:feature_class":"P",
    "gn:feature_code":"PPL",
    "gn:name":"Tlalhuapan",
    "gn:population":0,
    "gn:timezone":"America/Mexico_City",
    "iso:country":"MX",
    "name:und_x_variant":[
        "Tlahuapan",
        "Tlalhuapan"
    ],
    "wof:name":"Tlalhuapan",
    "wof:placetype":"locality"
},
  "geometry": {"coordinates":[-97.91359,20.06074],"type":"Point"}
}