{
  "type": "Feature",
  "properties": {
    "gn:admin1_code":"20",
    "gn:admin2_code":"469.0",
    "gn:asciiname":"San Miguel Copala",
    "gn:country_code":"MX",
    "gn:dem":880,
    "gn:feature_class":"P",
    "gn:feature_code":"PPL",
    "gn:name":"San Miguel Copala",
    "gn:population":0,
    "gn:timezone":"America/Mexico_City",
    "iso:country":"MX",
    "name:spa_x_preferred":[
        "San Miguel Copala"
    ],
    "wof:name":"San Miguel Copala",
    "wof:placetype":"locality"
},
  "geometry": {"coordinates":[-97.92693,17.06162],"type":"Point"}
}