{
  "type": "Feature",
  "properties": {
    "gn:admin1_code":"11.0",
    "gn:admin2_code":"2.0",
    "gn:asciiname":"La Presa de Santa Ines",
    "gn:country_code":"MX",
    "gn:dem":2052,
    "gn:feature_class":"P",
    "gn:feature_code":"PPL",
    "gn:name":"La Presa de Santa In\u00e9s",
    "gn:population":0,
    "gn:timezone":"America/Mexico_City",
    "iso:country":"MX",
    "name:spa_x_preferred":[
        "La Presa de Santa In\u00e9s"
    ],
    "name:spa_x_variant":[
        "Presa de Santa In\u00e9s"
    ],
    "name:und_x_variant":[
        "La Presa"
    ],
    "wof:name":"La Presa de Santa Ines",
    "wof:placetype":"locality"
},
  "geometry": {"coordinates":[-100.60088,19.98897],"type":"Point"}
}