{
  "type": "Feature",
  "properties": {
    "gn:admin1_code":"19.0",
    "gn:asciiname":"La Sultana",
    "gn:country_code":"MX",
    "gn:dem":481,
    "gn:feature_class":"P",
    "gn:feature_code":"PPL",
    "gn:name":"La Sultana",
    "gn:population":0,
    "gn:timezone":"America/Monterrey",
    "iso:country":"MX",
    "name:spa_x_preferred":[
        "La Sultana"
    ],
    "wof:name":"La Sultana",
    "wof:placetype":"locality"
},
  "geometry": {"coordinates":[-100.30716,25.97894],"type":"Point"}
}