{
  "type": "Feature",
  "properties": {
    "gn:admin1_code":"6",
    "gn:admin2_code":"7.0",
    "gn:asciiname":"La Garrapata",
    "gn:country_code":"MX",
    "gn:dem":2211,
    "gn:feature_class":"P",
    "gn:feature_code":"PPL",
    "gn:name":"La Garrapata",
    "gn:population":6,
    "gn:timezone":"America/Chihuahua",
    "iso:country":"MX",
    "wof:name":"La Garrapata",
    "wof:placetype":"locality",
    "wof:population":6
},
  "geometry": {"coordinates":[-106.62957,26.90022],"type":"Point"}
}