{
  "type": "Feature",
  "properties": {
    "gn:admin1_code":"30",
    "gn:admin2_code":"210.0",
    "gn:asciiname":"Nuevo Canton",
    "gn:country_code":"MX",
    "gn:dem":86,
    "gn:feature_class":"P",
    "gn:feature_code":"PPL",
    "gn:name":"Nuevo Cant\u00f3n",
    "gn:population":0,
    "gn:timezone":"America/Mexico_City",
    "iso:country":"MX",
    "name:und_x_variant":[
        "Poblado Siete",
        "Nuevo Cant\u00f3n"
    ],
    "wof:name":"Nuevo Canton",
    "wof:placetype":"locality"
},
  "geometry": {"coordinates":[-94.52717,17.32403],"type":"Point"}
}