{
  "type": "Feature",
  "properties": {
    "gn:admin1_code":"23.0",
    "gn:asciiname":"El Mulato",
    "gn:country_code":"MX",
    "gn:dem":6,
    "gn:feature_class":"P",
    "gn:feature_code":"PPL",
    "gn:name":"El Mulato",
    "gn:population":0,
    "gn:timezone":"America/Cancun",
    "iso:country":"MX",
    "name:spa_x_preferred":[
        "El Mulato"
    ],
    "wof:name":"El Mulato",
    "wof:placetype":"locality"
},
  "geometry": {"coordinates":[-88.24003,18.57789],"type":"Point"}
}