{
  "type": "Feature",
  "properties": {
    "gn:admin1_code":"28",
    "gn:admin2_code":"21.0",
    "gn:asciiname":"El Africa",
    "gn:country_code":"MX",
    "gn:dem":87,
    "gn:feature_class":"P",
    "gn:feature_code":"PPL",
    "gn:name":"El \u00c1frica",
    "gn:population":6,
    "gn:timezone":"America/Monterrey",
    "iso:country":"MX",
    "name:und_x_variant":[
        "El \u00c1frica"
    ],
    "wof:name":"El Africa",
    "wof:placetype":"locality",
    "wof:population":6
},
  "geometry": {"coordinates":[-99.09056,22.79889],"type":"Point"}
}