{
  "type": "Feature",
  "properties": {
    "gn:admin1_code":"20.0",
    "gn:asciiname":"Loma Latzanyco",
    "gn:country_code":"MX",
    "gn:dem":2293,
    "gn:feature_class":"P",
    "gn:feature_code":"PPL",
    "gn:name":"Loma Latzanyco",
    "gn:population":0,
    "gn:timezone":"America/Mexico_City",
    "iso:country":"MX",
    "name:spa_x_preferred":[
        "Loma Latzanyco"
    ],
    "wof:name":"Loma Latzanyco",
    "wof:placetype":"locality"
},
  "geometry": {"coordinates":[-97.1794,17.64124],"type":"Point"}
}