{
  "type": "Feature",
  "properties": {
    "gn:admin1_code":"26.0",
    "gn:admin2_code":"1.0",
    "gn:asciiname":"La Capilla",
    "gn:cc2":"MX",
    "gn:country_code":"MX",
    "gn:dem":608,
    "gn:feature_class":"P",
    "gn:feature_code":"PPL",
    "gn:name":"La Capilla",
    "gn:population":0,
    "gn:timezone":"America/Hermosillo",
    "iso:country":"MX",
    "name:und_x_variant":[
        "Capilla",
        "La Capilla"
    ],
    "wof:name":"La Capilla",
    "wof:placetype":"locality"
},
  "geometry": {"coordinates":[-110.18333,29.76667],"type":"Point"}
}