{
  "type": "Feature",
  "properties": {
    "gn:admin1_code":"26",
    "gn:admin2_code":"3.0",
    "gn:asciiname":"Las Pilas",
    "gn:cc2":"MX",
    "gn:country_code":"MX",
    "gn:dem":203,
    "gn:feature_class":"P",
    "gn:feature_code":"PPL",
    "gn:name":"Las Pilas",
    "gn:population":0,
    "gn:timezone":"America/Hermosillo",
    "iso:country":"MX",
    "name:fra_x_preferred":[
        "Las Pilas"
    ],
    "name:lit_x_preferred":[
        "Las Pilasas"
    ],
    "name:nld_x_preferred":[
        "Las Pilas"
    ],
    "name:rus_x_preferred":[
        "\u041b\u0430\u0441-\u041f\u0438\u043b\u0430\u0441"
    ],
    "name:slk_x_preferred":[
        "Las Pilas"
    ],
    "name:und_x_variant":[
        "Pilas"
    ],
    "wof:name":"Las Pilas",
    "wof:placetype":"locality"
},
  "geometry": {"coordinates":[-108.75,26.66667],"type":"Point"}
}