{
  "type": "Feature",
  "properties": {
    "gn:admin1_code":"20",
    "gn:admin2_code":"278.0",
    "gn:asciiname":"Corral de Piedra",
    "gn:country_code":"MX",
    "gn:dem":61,
    "gn:feature_class":"P",
    "gn:feature_code":"PPL",
    "gn:name":"Corral de Piedra",
    "gn:population":1066,
    "gn:timezone":"America/Mexico_City",
    "iso:country":"MX",
    "wof:name":"Corral de Piedra",
    "wof:placetype":"locality",
    "wof:population":1066
},
  "geometry": {"coordinates":[-96.30556,18.24528],"type":"Point"}
}