{
  "type": "Feature",
  "properties": {
    "gn:admin1_code":"32.0",
    "gn:admin2_code":"34.0",
    "gn:asciiname":"Plan de los Timones",
    "gn:country_code":"MX",
    "gn:dem":2186,
    "gn:feature_class":"P",
    "gn:feature_code":"PPL",
    "gn:name":"Plan de los Timones",
    "gn:population":0,
    "gn:timezone":"America/Mexico_City",
    "iso:country":"MX",
    "name:spa_x_preferred":[
        "Plan de los Timones"
    ],
    "wof:name":"Plan de los Timones",
    "wof:placetype":"locality"
},
  "geometry": {"coordinates":[-102.943,21.35597000000001],"type":"Point"}
}