{
  "type": "Feature",
  "properties": {
    "gn:admin1_code":"30",
    "gn:admin2_code":"201.0",
    "gn:asciiname":"Tecoxco",
    "gn:country_code":"MX",
    "gn:dem":1224,
    "gn:feature_class":"P",
    "gn:feature_code":"PPL",
    "gn:name":"Tecoxco",
    "gn:population":228,
    "gn:timezone":"America/Mexico_City",
    "iso:country":"MX",
    "wof:name":"Tecoxco",
    "wof:placetype":"locality",
    "wof:population":228
},
  "geometry": {"coordinates":[-96.97889000000001,18.72056],"type":"Point"}
}