{
  "type": "Feature",
  "properties": {
    "gn:admin1_code":"5",
    "gn:admin2_code":"76.0",
    "gn:asciiname":"Union Hidalgo (El Chorro)",
    "gn:country_code":"MX",
    "gn:dem":658,
    "gn:feature_class":"P",
    "gn:feature_code":"PPL",
    "gn:name":"Uni\u00f3n Hidalgo (El Chorro)",
    "gn:population":912,
    "gn:timezone":"America/Mexico_City",
    "iso:country":"MX",
    "name:und_x_variant":[
        "Uni\u00f3n Hidalgo (El Chorro)"
    ],
    "wof:name":"Union Hidalgo (El Chorro)",
    "wof:placetype":"locality",
    "wof:population":912
},
  "geometry": {"coordinates":[-92.60167,17.36139],"type":"Point"}
}