{
  "type": "Feature",
  "properties": {
    "gn:admin1_code":"12",
    "gn:admin2_code":"52.0",
    "gn:asciiname":"Rancho Rivera (La Cuesta del Nanche)",
    "gn:country_code":"MX",
    "gn:dem":296,
    "gn:feature_class":"P",
    "gn:feature_code":"PPL",
    "gn:name":"Rancho Rivera (La Cuesta del Nanche)",
    "gn:population":5,
    "gn:timezone":"America/Mexico_City",
    "iso:country":"MX",
    "wof:name":"Rancho Rivera (La Cuesta del Nanche)",
    "wof:placetype":"locality",
    "wof:population":5
},
  "geometry": {"coordinates":[-98.74720000000001,16.77585],"type":"Point"}
}