{
  "type": "Feature",
  "properties": {
    "gn:admin1_code":"24.0",
    "gn:admin2_code":"49.0",
    "gn:asciiname":"Hernandez",
    "gn:country_code":"MX",
    "gn:dem":2035,
    "gn:feature_class":"P",
    "gn:feature_code":"PPLL",
    "gn:name":"Hern\u00e1ndez",
    "gn:population":0,
    "gn:timezone":"America/Mexico_City",
    "iso:country":"MX",
    "wof:name":"Hernandez",
    "wof:placetype":"locality"
},
  "geometry": {"coordinates":[-102.03762999999999,23.03337],"type":"Point"}
}