{
  "type": "Feature",
  "properties": {
    "gn:admin1_code":"6",
    "gn:admin2_code":"65",
    "gn:asciiname":"Casa Colorada",
    "gn:country_code":"MX",
    "gn:dem":319,
    "gn:feature_class":"P",
    "gn:feature_code":"PPL",
    "gn:name":"Casa Colorada",
    "gn:population":29,
    "gn:timezone":"America/Chihuahua",
    "iso:country":"MX",
    "name:por_x_preferred":[
        "Casa Colorada"
    ],
    "name:spa_x_preferred":[
        "Casa Colorada"
    ],
    "wof:name":"Casa Colorada",
    "wof:placetype":"locality",
    "wof:population":29
},
  "geometry": {"coordinates":[-107.97185,26.94576],"type":"Point"}
}