{
  "type": "Feature",
  "properties": {
    "gn:admin1_code":"14",
    "gn:admin2_code":"43",
    "gn:asciiname":"Chancoa",
    "gn:country_code":"MX",
    "gn:dem":48,
    "gn:feature_class":"P",
    "gn:feature_code":"PPL",
    "gn:name":"Chancoa",
    "gn:population":50,
    "gn:timezone":"America/Mexico_City",
    "iso:country":"MX",
    "wof:name":"Chancoa",
    "wof:placetype":"locality",
    "wof:population":50
},
  "geometry": {"coordinates":[-105.05167,19.74611],"type":"Point"}
}