{
  "type": "Feature",
  "properties": {
    "gn:admin1_code":"21",
    "gn:admin2_code":"1.0",
    "gn:asciiname":"Cuatzapalo",
    "gn:country_code":"MX",
    "gn:dem":2491,
    "gn:feature_class":"P",
    "gn:feature_code":"PPL",
    "gn:name":"Cuatzapalo",
    "gn:population":8,
    "gn:timezone":"America/Mexico_City",
    "iso:country":"MX",
    "wof:name":"Cuatzapalo",
    "wof:placetype":"locality",
    "wof:population":8
},
  "geometry": {"coordinates":[-97.90573000000001,19.12172],"type":"Point"}
}