{
  "type": "Feature",
  "properties": {
    "gn:admin1_code":"26",
    "gn:admin2_code":"30.0",
    "gn:asciiname":"Chula Vista",
    "gn:country_code":"MX",
    "gn:dem":47,
    "gn:feature_class":"P",
    "gn:feature_code":"PPL",
    "gn:name":"Chula Vista",
    "gn:population":0,
    "gn:timezone":"America/Hermosillo",
    "iso:country":"MX",
    "name:spa_x_preferred":[
        "Chula Vista"
    ],
    "name:und_x_variant":[
        "Rancho Chula Vista"
    ],
    "wof:name":"Chula Vista",
    "wof:placetype":"locality"
},
  "geometry": {"coordinates":[-111.78115,29.11471],"type":"Point"}
}