{
  "type": "Feature",
  "properties": {
    "gn:admin1_code":"6",
    "gn:admin2_code":"30",
    "gn:asciiname":"Navojoa",
    "gn:country_code":"MX",
    "gn:dem":1647,
    "gn:feature_class":"P",
    "gn:feature_code":"PPL",
    "gn:name":"Navojoa",
    "gn:population":24,
    "gn:timezone":"America/Chihuahua",
    "iso:country":"MX",
    "name:dan_x_preferred":[
        "Navojoa"
    ],
    "name:deu_x_preferred":[
        "Navojoa"
    ],
    "name:epo_x_preferred":[
        "Navojoa"
    ],
    "name:fas_x_preferred":[
        "\u0646\u0627\u0648\u0648\u06cc\u0648\u0627"
    ],
    "name:ita_x_preferred":[
        "Navojoa"
    ],
    "name:kor_x_preferred":[
        "\ub098\ubcf4\ud638\uc544"
    ],
    "name:nld_x_preferred":[
        "Navojoa"
    ],
    "name:nor_x_preferred":[
        "Navojoa"
    ],
    "name:pol_x_preferred":[
        "Navojoa"
    ],
    "name:por_x_preferred":[
        "Navojoa"
    ],
    "name:ron_x_preferred":[
        "Navojoa"
    ],
    "name:rus_x_preferred":[
        "\u041d\u0430\u0432\u043e\u0445\u043e\u0430"
    ],
    "name:spa_x_preferred":[
        "Navojoa"
    ],
    "name:srp_x_preferred":[
        "\u041d\u0430\u0432\u043e\u0445\u043e\u0430"
    ],
    "name:swe_x_preferred":[
        "Navojoa"
    ],
    "name:urd_x_preferred":[
        "\u0646\u0627\u0648\u0648\u062e\u0648\u0627"
    ],
    "name:vie_x_preferred":[
        "Navojoa"
    ],
    "name:war_x_preferred":[
        "Navojoa"
    ],
    "name:zho_x_preferred":[
        "\u7d0d\u6c83\u83ef"
    ],
    "wof:name":"Navojoa",
    "wof:placetype":"locality",
    "wof:population":24
},
  "geometry": {"coordinates":[-108.20326,27.52047],"type":"Point"}
}