{
  "type": "Feature",
  "properties": {
    "gn:admin1_code":"6",
    "gn:admin2_code":"30",
    "gn:asciiname":"Navojoa",
    "gn:country_code":"MX",
    "gn:dem":1647,
    "gn:feature_class":"P",
    "gn:feature_code":"PPL",
    "gn:name":"Navojoa",
    "gn:population":24,
    "gn:timezone":"America/Chihuahua",
    "iso:country":"MX",
    "wof:name":"Navojoa",
    "wof:placetype":"locality",
    "wof:population":24
},
  "geometry": {"coordinates":[-108.20326,27.52047],"type":"Point"}
}