{
  "type": "Feature",
  "properties": {
    "gn:admin1_code":"12.0",
    "gn:asciiname":"Azizintla",
    "gn:country_code":"MX",
    "gn:dem":1319,
    "gn:feature_class":"P",
    "gn:feature_code":"PPL",
    "gn:name":"Azizintla",
    "gn:population":0,
    "gn:timezone":"America/Mexico_City",
    "iso:country":"MX",
    "name:spa_x_preferred":[
        "Azizintla"
    ],
    "name:spa_x_variant":[
        "Tlalcopantla"
    ],
    "wof:name":"Azizintla",
    "wof:placetype":"locality"
},
  "geometry": {"coordinates":[-99.55784,17.61061],"type":"Point"}
}