{
  "type": "Feature",
  "properties": {
    "gn:admin1_code":"7",
    "gn:admin2_code":"17.0",
    "gn:asciiname":"Las Carolinas",
    "gn:country_code":"MX",
    "gn:dem":1115,
    "gn:feature_class":"P",
    "gn:feature_code":"PPL",
    "gn:name":"Las Carolinas",
    "gn:population":0,
    "gn:timezone":"America/Monterrey",
    "iso:country":"MX",
    "name:spa_x_preferred":[
        "Las Carolinas"
    ],
    "wof:name":"Las Carolinas",
    "wof:placetype":"locality"
},
  "geometry": {"coordinates":[-103.21968,25.52187],"type":"Point"}
}