{
  "type": "Feature",
  "properties": {
    "gn:admin1_code":"28.0",
    "gn:admin2_code":"2.0",
    "gn:asciiname":"El Naranjo",
    "gn:country_code":"MX",
    "gn:dem":98,
    "gn:feature_class":"P",
    "gn:feature_code":"PPL",
    "gn:name":"El Naranjo",
    "gn:population":14,
    "gn:timezone":"America/Monterrey",
    "iso:country":"MX",
    "name:spa_x_preferred":[
        "El Naranjo"
    ],
    "wof:name":"El Naranjo",
    "wof:placetype":"locality",
    "wof:population":14
},
  "geometry": {"coordinates":[-98.20041999999999,22.85031],"type":"Point"}
}