{
  "type": "Feature",
  "properties": {
    "gn:admin1_code":"26",
    "gn:admin2_code":"58.0",
    "gn:asciiname":"El Represo",
    "gn:country_code":"MX",
    "gn:dem":752,
    "gn:feature_class":"P",
    "gn:feature_code":"PPL",
    "gn:name":"El Represo",
    "gn:population":0,
    "gn:timezone":"America/Hermosillo",
    "iso:country":"MX",
    "name:spa_x_preferred":[
        "El Represo"
    ],
    "name:und_x_variant":[
        "Rancho El Represo"
    ],
    "wof:name":"El Represo",
    "wof:placetype":"locality"
},
  "geometry": {"coordinates":[-111.06864,30.55609],"type":"Point"}
}