{
  "type": "Feature",
  "properties": {
    "gn:admin1_code":"6",
    "gn:admin2_code":"7.0",
    "gn:asciiname":"Rancheria Banos de Arriba",
    "gn:country_code":"MX",
    "gn:dem":1637,
    "gn:feature_class":"P",
    "gn:feature_code":"PPL",
    "gn:name":"Rancher\u00eda Ba\u00f1os de Arriba",
    "gn:population":0,
    "gn:timezone":"America/Chihuahua",
    "iso:country":"MX",
    "name:spa_x_preferred":[
        "Rancher\u00eda Ba\u00f1os de Arriba"
    ],
    "name:und_x_variant":[
        "Ba\u00f1os de Arriba",
        "Los Ba\u00f1os"
    ],
    "wof:name":"Rancheria Banos de Arriba",
    "wof:placetype":"locality"
},
  "geometry": {"coordinates":[-106.2856,26.80519],"type":"Point"}
}