{
  "type": "Feature",
  "properties": {
    "gn:admin1_code":"6.0",
    "gn:admin2_code":"48.0",
    "gn:asciiname":"Las Hierbas",
    "gn:country_code":"MX",
    "gn:dem":1902,
    "gn:feature_class":"P",
    "gn:feature_code":"PPL",
    "gn:name":"Las Hierbas",
    "gn:population":0,
    "gn:timezone":"America/Chihuahua",
    "iso:country":"MX",
    "name:spa_x_preferred":[
        "Las Hierbas"
    ],
    "wof:name":"Las Hierbas",
    "wof:placetype":"locality"
},
  "geometry": {"coordinates":[-107.43892,29.176],"type":"Point"}
}