{
  "type": "Feature",
  "properties": {
    "gn:admin1_code":"6",
    "gn:admin2_code":"29",
    "gn:asciiname":"Arroyo Hondo",
    "gn:country_code":"MX",
    "gn:dem":1995,
    "gn:feature_class":"P",
    "gn:feature_code":"PPL",
    "gn:name":"Arroyo Hondo",
    "gn:population":13,
    "gn:timezone":"America/Chihuahua",
    "iso:country":"MX",
    "name:ceb_x_preferred":[
        "Arroyo Hondo"
    ],
    "name:swe_x_preferred":[
        "Arroyo Hondo"
    ],
    "wof:name":"Arroyo Hondo",
    "wof:placetype":"locality",
    "wof:population":13
},
  "geometry": {"coordinates":[-106.96903,26.28356],"type":"Point"}
}