{
  "type": "Feature",
  "properties": {
    "gn:admin1_code":"15",
    "gn:admin2_code":"60.0",
    "gn:asciiname":"Barrio de Guadalupe",
    "gn:country_code":"MX",
    "gn:dem":2836,
    "gn:feature_class":"P",
    "gn:feature_code":"PPL",
    "gn:name":"Barrio de Guadalupe",
    "gn:population":945,
    "gn:timezone":"America/Mexico_City",
    "iso:country":"MX",
    "wof:name":"Barrio de Guadalupe",
    "wof:placetype":"locality",
    "wof:population":945
},
  "geometry": {"coordinates":[-99.42104,19.60138],"type":"Point"}
}