{
  "type": "Feature",
  "properties": {
    "gn:admin1_code":"27",
    "gn:admin2_code":"16.0",
    "gn:asciiname":"Mariano Matamoros",
    "gn:country_code":"MX",
    "gn:dem":20,
    "gn:feature_class":"P",
    "gn:feature_code":"PPL",
    "gn:name":"Mariano Matamoros",
    "gn:population":0,
    "gn:timezone":"America/Mexico_City",
    "iso:country":"MX",
    "name:deu_x_preferred":[
        "Mariano Matamoros"
    ],
    "name:fra_x_preferred":[
        "Mariano Matamoros"
    ],
    "name:hun_x_preferred":[
        "Mariano Matamoros"
    ],
    "name:ita_x_preferred":[
        "Mariano Matamoros"
    ],
    "name:nah_x_preferred":[
        "Mariano Matamoros"
    ],
    "name:nor_x_preferred":[
        "Mariano Matamoros"
    ],
    "name:por_x_preferred":[
        "Mariano Matamoros"
    ],
    "name:rus_x_preferred":[
        "\u041c\u0430\u0442\u0430\u043c\u043e\u0440\u043e\u0441"
    ],
    "name:spa_x_preferred":[
        "Matamoros"
    ],
    "name:spa_x_variant":[
        "Mariano Matamoros"
    ],
    "name:swe_x_preferred":[
        "Mariano Matamoros"
    ],
    "wof:name":"Mariano Matamoros",
    "wof:placetype":"locality"
},
  "geometry": {"coordinates":[-92.88773999999999,17.58144],"type":"Point"}
}