{
  "type": "Feature",
  "properties": {
    "gn:admin1_code":"27",
    "gn:admin2_code":"16.0",
    "gn:asciiname":"Mariano Matamoros",
    "gn:country_code":"MX",
    "gn:dem":20,
    "gn:feature_class":"P",
    "gn:feature_code":"PPL",
    "gn:name":"Mariano Matamoros",
    "gn:population":0,
    "gn:timezone":"America/Mexico_City",
    "iso:country":"MX",
    "name:spa_x_preferred":[
        "Matamoros"
    ],
    "name:spa_x_variant":[
        "Mariano Matamoros"
    ],
    "wof:name":"Mariano Matamoros",
    "wof:placetype":"locality"
},
  "geometry": {"coordinates":[-92.88773999999999,17.58144],"type":"Point"}
}