{
  "type": "Feature",
  "properties": {
    "gn:admin1_code":"5",
    "gn:admin2_code":"32",
    "gn:asciiname":"Ojo de Agua II",
    "gn:country_code":"MX",
    "gn:dem":2052,
    "gn:feature_class":"P",
    "gn:feature_code":"PPL",
    "gn:name":"Ojo de Agua II",
    "gn:population":48,
    "gn:timezone":"America/Mexico_City",
    "iso:country":"MX",
    "wof:name":"Ojo de Agua II",
    "wof:placetype":"locality",
    "wof:population":48
},
  "geometry": {"coordinates":[-92.53583,15.47083],"type":"Point"}
}