{
  "type": "Feature",
  "properties": {
    "gn:admin1_code":"10",
    "gn:admin2_code":"5.0",
    "gn:asciiname":"El Guarda Ganado",
    "gn:country_code":"MX",
    "gn:dem":2559,
    "gn:feature_class":"P",
    "gn:feature_code":"PPL",
    "gn:name":"El Guarda Ganado",
    "gn:population":4,
    "gn:timezone":"America/Monterrey",
    "iso:country":"MX",
    "wof:name":"El Guarda Ganado",
    "wof:placetype":"locality",
    "wof:population":4
},
  "geometry": {"coordinates":[-105.05222999999999,23.88807000000001],"type":"Point"}
}