{
  "type": "Feature",
  "properties": {
    "gn:country":"MX",
    "gn:fcode":"PPL",
    "gn:population":0,
    "iso:country":"MX",
    "qs_pg:aaroncc":"MX",
    "qs_pg:gn_country":"MX",
    "qs_pg:gn_fcode":"PPL",
    "qs_pg:gn_pop":0,
    "qs_pg:name":"Tolom\u00e9",
    "qs_pg:name_adm0":"M\u00e9xico",
    "qs_pg:name_adm1":"Veracruz-Llave",
    "qs_pg:photos_9k":1,
    "qs_pg:photos_9r":1,
    "qs_pg:photos_all":8,
    "qs_pg:photos_sr":0,
    "qs_pg:pop_sr":0,
    "qs_pg:qs_pg_placetype":"locality",
    "qs_pg:qs_pg_placetype_gp":"Town",
    "qs_pg:woe_adm0":23424900,
    "woe:adm0_id":23424900,
    "woe:name_adm0":"M\u00e9xico",
    "woe:name_adm1":"Veracruz-Llave",
    "woe:placetype":"Town",
    "wof:name":"Tolom\u00e9",
    "wof:placetype":"locality",
    "wof:population":2715
},
  "geometry": {"coordinates":[-96.38333,19.26667],"type":"Point"}
}