{
  "type": "Feature",
  "properties": {
    "gn:admin1_code":"5.0",
    "gn:admin2_code":"31.0",
    "gn:asciiname":"Canenab",
    "gn:country_code":"MX",
    "gn:dem":1097,
    "gn:feature_class":"P",
    "gn:feature_code":"PPL",
    "gn:name":"Canenab",
    "gn:population":0,
    "gn:timezone":"America/Mexico_City",
    "iso:country":"MX",
    "name:spa_x_preferred":[
        "Canenab"
    ],
    "wof:name":"Canenab",
    "wof:placetype":"locality"
},
  "geometry": {"coordinates":[-92.29018000000001,17.14773],"type":"Point"}
}