{
  "type": "Feature",
  "properties": {
    "gn:admin1_code":"4",
    "gn:admin2_code":"6.0",
    "gn:asciiname":"Nuevo Durango Cuatro",
    "gn:country_code":"MX",
    "gn:dem":134,
    "gn:feature_class":"P",
    "gn:feature_code":"PPL",
    "gn:name":"Nuevo Durango Cuatro",
    "gn:population":178,
    "gn:timezone":"America/Cancun",
    "iso:country":"MX",
    "wof:name":"Nuevo Durango Cuatro",
    "wof:placetype":"locality",
    "wof:population":178
},
  "geometry": {"coordinates":[-89.34971999999998,19.4025],"type":"Point"}
}