{
  "type": "Feature",
  "properties": {
    "gn:admin1_code":"6.0",
    "gn:admin2_code":"60.0",
    "gn:asciiname":"Llanos de Casa Colorada (Francisco I. Madero)",
    "gn:country_code":"MX",
    "gn:dem":1843,
    "gn:feature_class":"P",
    "gn:feature_code":"PPL",
    "gn:name":"Llanos de Casa Colorada (Francisco I. Madero)",
    "gn:population":17,
    "gn:timezone":"America/Chihuahua",
    "iso:country":"MX",
    "wof:name":"Llanos de Casa Colorada (Francisco I. Madero)",
    "wof:placetype":"locality",
    "wof:population":17
},
  "geometry": {"coordinates":[-105.77417,26.85528],"type":"Point"}
}