{
  "type": "Feature",
  "properties": {
    "gn:admin1_code":"14",
    "gn:admin2_code":"94.0",
    "gn:asciiname":"La Presita (La Ladrillera)",
    "gn:country_code":"MX",
    "gn:dem":1149,
    "gn:feature_class":"P",
    "gn:feature_code":"PPL",
    "gn:name":"La Presita (La Ladrillera)",
    "gn:population":5,
    "gn:timezone":"America/Mexico_City",
    "iso:country":"MX",
    "wof:name":"La Presita (La Ladrillera)",
    "wof:placetype":"locality",
    "wof:population":5
},
  "geometry": {"coordinates":[-103.84028000000001,20.92528],"type":"Point"}
}