{
  "type": "Feature",
  "properties": {
    "gn:admin1_code":"11",
    "gn:admin2_code":"14",
    "gn:asciiname":"Colonia el Cedro",
    "gn:country_code":"MX",
    "gn:dem":1948,
    "gn:feature_class":"P",
    "gn:feature_code":"PPL",
    "gn:name":"Colonia el Cedro",
    "gn:population":30,
    "gn:timezone":"America/Mexico_City",
    "iso:country":"MX",
    "wof:name":"Colonia el Cedro",
    "wof:placetype":"locality",
    "wof:population":30
},
  "geometry": {"coordinates":[-100.95166999999999,21.17611],"type":"Point"}
}