{
  "type": "Feature",
  "properties": {
    "gn:admin1_code":"25.0",
    "gn:admin2_code":"18.0",
    "gn:asciiname":"Batauto (Laguna de Batauto)",
    "gn:cc2":"MX",
    "gn:country_code":"MX",
    "gn:dem":5,
    "gn:feature_class":"P",
    "gn:feature_code":"PPL",
    "gn:name":"Batauto (Laguna de Batauto)",
    "gn:population":245,
    "gn:timezone":"America/Mazatlan",
    "iso:country":"MX",
    "name:und_x_variant":[
        "Balaote",
        "Balaoto",
        "Campo Batauto",
        "Batauto"
    ],
    "wof:name":"Batauto (Laguna de Batauto)",
    "wof:placetype":"locality",
    "wof:population":245
},
  "geometry": {"coordinates":[-107.58417,24.57111],"type":"Point"}
}