{
  "type": "Feature",
  "properties": {
    "gn:admin1_code":"6.0",
    "gn:admin2_code":"40.0",
    "gn:asciiname":"Dos Hermanos",
    "gn:country_code":"MX",
    "gn:dem":2057,
    "gn:feature_class":"P",
    "gn:feature_code":"PPL",
    "gn:name":"Dos Hermanos",
    "gn:population":0,
    "gn:timezone":"America/Chihuahua",
    "iso:country":"MX",
    "name:spa_x_preferred":[
        "Dos Hermanos"
    ],
    "name:und_x_variant":[
        "Rancho Dos Hermanos"
    ],
    "wof:name":"Dos Hermanos",
    "wof:placetype":"locality"
},
  "geometry": {"coordinates":[-108.02611,29.73155],"type":"Point"}
}