{
  "type": "Feature",
  "properties": {
    "gn:admin1_code":"12",
    "gn:admin2_code":"27.0",
    "gn:asciiname":"La Mohonera (La Monera)",
    "gn:country_code":"MX",
    "gn:dem":325,
    "gn:feature_class":"P",
    "gn:feature_code":"PPL",
    "gn:name":"La Mohonera (La Monera)",
    "gn:population":209,
    "gn:timezone":"America/Mexico_City",
    "iso:country":"MX",
    "wof:name":"La Mohonera (La Monera)",
    "wof:placetype":"locality",
    "wof:population":209
},
  "geometry": {"coordinates":[-100.67139,18.58222],"type":"Point"}
}