{
  "type": "Feature",
  "properties": {
    "gn:admin1_code":"14",
    "gn:admin2_code":"84.0",
    "gn:asciiname":"Los Encinos",
    "gn:country_code":"MX",
    "gn:dem":221,
    "gn:feature_class":"P",
    "gn:feature_code":"PPL",
    "gn:name":"Los Encinos",
    "gn:population":0,
    "gn:timezone":"America/Mexico_City",
    "iso:country":"MX",
    "wof:name":"Los Encinos",
    "wof:placetype":"locality"
},
  "geometry": {"coordinates":[-105.02384000000001,20.15085],"type":"Point"}
}