{
  "type": "Feature",
  "properties": {
    "gn:admin1_code":"2",
    "gn:admin2_code":"1",
    "gn:asciiname":"Ampliacion Balcones de la Presa",
    "gn:country_code":"MX",
    "gn:dem":124,
    "gn:feature_class":"P",
    "gn:feature_code":"PPL",
    "gn:name":"Ampliaci\u00f3n Balcones de la Presa",
    "gn:population":41,
    "gn:timezone":"America/Tijuana",
    "iso:country":"MX",
    "name:und_x_variant":[
        "Ampliaci\u00f3n Balcones de la Presa"
    ],
    "wof:name":"Ampliacion Balcones de la Presa",
    "wof:placetype":"locality",
    "wof:population":41
},
  "geometry": {"coordinates":[-116.605,31.89667],"type":"Point"}
}