{
  "type": "Feature",
  "properties": {
    "gn:admin1_code":"28.0",
    "gn:admin2_code":"19.0",
    "gn:asciiname":"Los Altos",
    "gn:country_code":"MX",
    "gn:dem":256,
    "gn:feature_class":"P",
    "gn:feature_code":"PPL",
    "gn:name":"Los Altos",
    "gn:population":0,
    "gn:timezone":"America/Monterrey",
    "iso:country":"MX",
    "name:spa_x_preferred":[
        "Los Altos"
    ],
    "wof:name":"Los Altos",
    "wof:placetype":"locality"
},
  "geometry": {"coordinates":[-98.73575,23.37403],"type":"Point"}
}