{
  "type": "Feature",
  "properties": {
    "gn:admin1_code":"11",
    "gn:admin2_code":"4",
    "gn:asciiname":"Los Cervantes (San Antonio de los Cervantes)",
    "gn:country_code":"MX",
    "gn:dem":2088,
    "gn:feature_class":"P",
    "gn:feature_code":"PPL",
    "gn:name":"Los Cervantes (San Antonio de los Cervantes)",
    "gn:population":43,
    "gn:timezone":"America/Mexico_City",
    "iso:country":"MX",
    "wof:name":"Los Cervantes (San Antonio de los Cervantes)",
    "wof:placetype":"locality",
    "wof:population":43
},
  "geometry": {"coordinates":[-100.52667,20.34083],"type":"Point"}
}