{
  "type": "Feature",
  "properties": {
    "gn:admin1_code":"28",
    "gn:admin2_code":"37.0",
    "gn:asciiname":"Enramadas",
    "gn:country_code":"MX",
    "gn:dem":6,
    "gn:feature_class":"P",
    "gn:feature_code":"PPL",
    "gn:name":"Enramadas",
    "gn:population":0,
    "gn:timezone":"America/Monterrey",
    "iso:country":"MX",
    "name:spa_x_preferred":[
        "Enramadas"
    ],
    "name:und_x_variant":[
        "La Enramada"
    ],
    "wof:name":"Enramadas",
    "wof:placetype":"locality"
},
  "geometry": {"coordinates":[-97.80540999999999,24.23693],"type":"Point"}
}