{
  "type": "Feature",
  "properties": {
    "gn:admin1_code":"2.0",
    "gn:admin2_code":"4.0",
    "gn:asciiname":"La Flor del Sol",
    "gn:country_code":"MX",
    "gn:dem":210,
    "gn:feature_class":"P",
    "gn:feature_code":"PPL",
    "gn:name":"La Flor del Sol",
    "gn:population":0,
    "gn:timezone":"America/Tijuana",
    "iso:country":"MX",
    "name:spa_x_preferred":[
        "La Flor del Sol"
    ],
    "wof:name":"La Flor del Sol",
    "wof:placetype":"locality"
},
  "geometry": {"coordinates":[-116.94285000000001,32.42232],"type":"Point"}
}