{
  "type": "Feature",
  "properties": {
    "gn:admin1_code":"20",
    "gn:admin2_code":"16.0",
    "gn:asciiname":"Llano Encino Amarillo",
    "gn:country_code":"MX",
    "gn:dem":1669,
    "gn:feature_class":"P",
    "gn:feature_code":"PPL",
    "gn:name":"Llano Encino Amarillo",
    "gn:population":475,
    "gn:timezone":"America/Mexico_City",
    "iso:country":"MX",
    "wof:name":"Llano Encino Amarillo",
    "wof:placetype":"locality",
    "wof:population":475
},
  "geometry": {"coordinates":[-98.19139,17.22],"type":"Point"}
}