{
  "type": "Feature",
  "properties": {
    "gn:admin1_code":"6",
    "gn:admin2_code":"54.0",
    "gn:asciiname":"Campo Treinta y Cinco y Medio",
    "gn:country_code":"MX",
    "gn:dem":2052,
    "gn:feature_class":"P",
    "gn:feature_code":"PPL",
    "gn:name":"Campo Treinta y Cinco y Medio",
    "gn:population":0,
    "gn:timezone":"America/Chihuahua",
    "iso:country":"MX",
    "name:spa_x_preferred":[
        "Campo Treinta y Cinco y Medio"
    ],
    "wof:name":"Campo Treinta y Cinco y Medio",
    "wof:placetype":"locality"
},
  "geometry": {"coordinates":[-106.85644000000001,28.79971],"type":"Point"}
}