{
  "type": "Feature",
  "properties": {
    "gn:admin1_code":"26",
    "gn:admin2_code":"30.0",
    "gn:asciiname":"Ejido Francisco Aispuro (El Apache)",
    "gn:country_code":"MX",
    "gn:dem":25,
    "gn:feature_class":"P",
    "gn:feature_code":"PPL",
    "gn:name":"Ejido Francisco Aispuro (El Apache)",
    "gn:population":6,
    "gn:timezone":"America/Hermosillo",
    "iso:country":"MX",
    "wof:name":"Ejido Francisco Aispuro (El Apache)",
    "wof:placetype":"locality",
    "wof:population":6
},
  "geometry": {"coordinates":[-111.79889,29.01667],"type":"Point"}
}