{
  "type": "Feature",
  "properties": {
    "gn:admin1_code":"21",
    "gn:admin2_code":"15.0",
    "gn:asciiname":"Jose Lino Miguel Lopez de la Rosa",
    "gn:country_code":"MX",
    "gn:dem":2336,
    "gn:feature_class":"P",
    "gn:feature_code":"PPL",
    "gn:name":"Jos\u00e9 Lino Miguel L\u00f3pez de la Rosa",
    "gn:population":87,
    "gn:timezone":"America/Mexico_City",
    "iso:country":"MX",
    "name:und_x_variant":[
        "Jos\u00e9 Lino Miguel L\u00f3pez de la Rosa"
    ],
    "wof:name":"Jose Lino Miguel Lopez de la Rosa",
    "wof:placetype":"locality",
    "wof:population":87
},
  "geometry": {"coordinates":[-98.0519,19.06014],"type":"Point"}
}