{
  "type": "Feature",
  "properties": {
    "gn:admin1_code":"14",
    "gn:admin2_code":"64",
    "gn:asciiname":"La Blanquita",
    "gn:country_code":"MX",
    "gn:dem":2126,
    "gn:feature_class":"P",
    "gn:feature_code":"PPL",
    "gn:name":"La Blanquita",
    "gn:population":32,
    "gn:timezone":"America/Mexico_City",
    "iso:country":"MX",
    "wof:name":"La Blanquita",
    "wof:placetype":"locality",
    "wof:population":32
},
  "geometry": {"coordinates":[-101.72499999999999,21.90333],"type":"Point"}
}