{
  "type": "Feature",
  "properties": {
    "gn:admin1_code":"13",
    "gn:admin2_code":"60.0",
    "gn:asciiname":"El Lindero",
    "gn:country_code":"MX",
    "gn:dem":1523,
    "gn:feature_class":"P",
    "gn:feature_code":"PPL",
    "gn:name":"El Lindero",
    "gn:population":149,
    "gn:timezone":"America/Mexico_City",
    "iso:country":"MX",
    "wof:name":"El Lindero",
    "wof:placetype":"locality",
    "wof:population":149
},
  "geometry": {"coordinates":[-98.11556,20.35917],"type":"Point"}
}