{
  "type": "Feature",
  "properties": {
    "gn:admin1_code":"6.0",
    "gn:admin2_code":"67.0",
    "gn:asciiname":"El Palomo",
    "gn:country_code":"MX",
    "gn:dem":1639,
    "gn:feature_class":"P",
    "gn:feature_code":"PPL",
    "gn:name":"El Palomo",
    "gn:population":0,
    "gn:timezone":"America/Chihuahua",
    "iso:country":"MX",
    "name:und_x_variant":[
        "Palonjo",
        "El Palonio",
        "Rancho El Palomo",
        "El Palomo"
    ],
    "wof:name":"El Palomo",
    "wof:placetype":"locality"
},
  "geometry": {"coordinates":[-106.04159,27.64583],"type":"Point"}
}