{
  "type": "Feature",
  "properties": {
    "gn:admin1_code":"18",
    "gn:admin2_code":"9.0",
    "gn:asciiname":"Las Cuevas",
    "gn:country_code":"MX",
    "gn:dem":233,
    "gn:feature_class":"P",
    "gn:feature_code":"PPL",
    "gn:name":"Las Cuevas",
    "gn:population":57,
    "gn:timezone":"America/Mazatlan",
    "iso:country":"MX",
    "name:ceb_x_preferred":[
        "Las Cuevas"
    ],
    "name:deu_x_preferred":[
        "Las Cuevas"
    ],
    "name:nds_x_preferred":[
        "Las Cuevas"
    ],
    "name:spa_x_preferred":[
        "Las Cuevas"
    ],
    "name:swe_x_preferred":[
        "Las Cuevas"
    ],
    "wof:name":"Las Cuevas",
    "wof:placetype":"locality",
    "wof:population":57
},
  "geometry": {"coordinates":[-104.76139000000001,21.91222],"type":"Point"}
}