{
  "type": "Feature",
  "properties": {
    "gn:admin1_code":"24",
    "gn:admin2_code":"4.0",
    "gn:asciiname":"El Alguacil",
    "gn:country_code":"MX",
    "gn:dem":1950,
    "gn:feature_class":"P",
    "gn:feature_code":"PPL",
    "gn:name":"El Alguacil",
    "gn:population":9,
    "gn:timezone":"America/Mexico_City",
    "iso:country":"MX",
    "wof:name":"El Alguacil",
    "wof:placetype":"locality",
    "wof:population":9
},
  "geometry": {"coordinates":[-100.60250000000001,22.15333],"type":"Point"}
}