{
  "type": "Feature",
  "properties": {
    "gn:admin1_code":"13",
    "gn:admin2_code":"15.0",
    "gn:asciiname":"Tepozan",
    "gn:country_code":"MX",
    "gn:dem":2244,
    "gn:feature_class":"P",
    "gn:feature_code":"PPL",
    "gn:name":"Tepoz\u00e1n",
    "gn:population":57,
    "gn:timezone":"America/Mexico_City",
    "iso:country":"MX",
    "name:und_x_variant":[
        "Tepoz\u00e1n"
    ],
    "wof:name":"Tepozan",
    "wof:placetype":"locality",
    "wof:population":57
},
  "geometry": {"coordinates":[-99.05481,20.71182],"type":"Point"}
}