{
  "type": "Feature",
  "properties": {
    "gn:admin1_code":"5",
    "gn:admin2_code":"78",
    "gn:asciiname":"La Fortuna",
    "gn:country_code":"MX",
    "gn:dem":1945,
    "gn:feature_class":"P",
    "gn:feature_code":"PPL",
    "gn:name":"La Fortuna",
    "gn:population":45,
    "gn:timezone":"America/Mexico_City",
    "iso:country":"MX",
    "wof:name":"La Fortuna",
    "wof:placetype":"locality",
    "wof:population":45
},
  "geometry": {"coordinates":[-92.68083,16.67694],"type":"Point"}
}