{
  "type": "Feature",
  "properties": {
    "gn:admin1_code":"17",
    "gn:admin2_code":"32.0",
    "gn:asciiname":"Campo Potrerillo",
    "gn:country_code":"MX",
    "gn:dem":1769,
    "gn:feature_class":"P",
    "gn:feature_code":"PPL",
    "gn:name":"Campo Potrerillo",
    "gn:population":7,
    "gn:timezone":"America/Mexico_City",
    "iso:country":"MX",
    "wof:name":"Campo Potrerillo",
    "wof:placetype":"locality",
    "wof:population":7
},
  "geometry": {"coordinates":[-98.74028,18.81083],"type":"Point"}
}