{
  "type": "Feature",
  "properties": {
    "gn:admin1_code":"6",
    "gn:admin2_code":"41.0",
    "gn:asciiname":"Rancho Blanco",
    "gn:country_code":"MX",
    "gn:dem":2020,
    "gn:feature_class":"P",
    "gn:feature_code":"PPL",
    "gn:name":"Rancho Blanco",
    "gn:population":0,
    "gn:timezone":"America/Chihuahua",
    "iso:country":"MX",
    "name:spa_x_preferred":[
        "Rancho Blanco"
    ],
    "wof:name":"Rancho Blanco",
    "wof:placetype":"locality"
},
  "geometry": {"coordinates":[-107.91591,27.8068],"type":"Point"}
}