{
  "type": "Feature",
  "properties": {
    "gn:admin1_code":"11.0",
    "gn:admin2_code":"33.0",
    "gn:asciiname":"Puerto Blanco",
    "gn:country_code":"MX",
    "gn:dem":2040,
    "gn:feature_class":"P",
    "gn:feature_code":"PPL",
    "gn:name":"Puerto Blanco",
    "gn:population":0,
    "gn:timezone":"America/Mexico_City",
    "iso:country":"MX",
    "name:und_x_variant":[
        "Pueblo Blanco",
        "Puerto Blanco"
    ],
    "wof:name":"Puerto Blanco",
    "wof:placetype":"locality"
},
  "geometry": {"coordinates":[-100.5177,21.08572],"type":"Point"}
}