{
  "type": "Feature",
  "properties": {
    "gn:admin1_code":"16.0",
    "gn:asciiname":"La Postena",
    "gn:country_code":"MX",
    "gn:dem":1558,
    "gn:feature_class":"P",
    "gn:feature_code":"PPL",
    "gn:name":"La Poste\u00f1a",
    "gn:population":0,
    "gn:timezone":"America/Mexico_City",
    "iso:country":"MX",
    "name:spa_x_preferred":[
        "La Poste\u00f1a"
    ],
    "wof:name":"La Postena",
    "wof:placetype":"locality"
},
  "geometry": {"coordinates":[-102.36825,20.07738],"type":"Point"}
}