{
  "type": "Feature",
  "properties": {
    "gn:admin1_code":"25",
    "gn:admin2_code":"11.0",
    "gn:asciiname":"La Huerta (Los Juncos)",
    "gn:country_code":"MX",
    "gn:dem":17,
    "gn:feature_class":"P",
    "gn:feature_code":"PPL",
    "gn:name":"La Huerta (Los Juncos)",
    "gn:population":9,
    "gn:timezone":"America/Mazatlan",
    "iso:country":"MX",
    "wof:name":"La Huerta (Los Juncos)",
    "wof:placetype":"locality",
    "wof:population":9
},
  "geometry": {"coordinates":[-108.76304,25.75252],"type":"Point"}
}