{
  "type": "Feature",
  "properties": {
    "gn:admin1_code":"26",
    "gn:admin2_code":"37.0",
    "gn:asciiname":"El Alcabuz",
    "gn:country_code":"MX",
    "gn:dem":550,
    "gn:feature_class":"P",
    "gn:feature_code":"PPL",
    "gn:name":"El Alcabuz",
    "gn:population":0,
    "gn:timezone":"America/Hermosillo",
    "iso:country":"MX",
    "name:spa_x_preferred":[
        "El Alcabuz"
    ],
    "wof:name":"El Alcabuz",
    "wof:placetype":"locality"
},
  "geometry": {"coordinates":[-110.13187000000001,29.01413],"type":"Point"}
}