{
  "type": "Feature",
  "properties": {
    "gn:admin1_code":"23.0",
    "gn:admin2_code":"4.0",
    "gn:asciiname":"El Pedregal",
    "gn:country_code":"MX",
    "gn:dem":26,
    "gn:feature_class":"P",
    "gn:feature_code":"PPL",
    "gn:name":"El Pedregal",
    "gn:population":8,
    "gn:timezone":"America/Cancun",
    "iso:country":"MX",
    "name:spa_x_preferred":[
        "El Pedregal"
    ],
    "wof:name":"El Pedregal",
    "wof:placetype":"locality",
    "wof:population":8
},
  "geometry": {"coordinates":[-88.55583,18.78778],"type":"Point"}
}