{
  "type": "Feature",
  "properties": {
    "gn:admin1_code":"16",
    "gn:admin2_code":"49.0",
    "gn:asciiname":"Timbiriche",
    "gn:country_code":"MX",
    "gn:dem":1170,
    "gn:feature_class":"P",
    "gn:feature_code":"PPL",
    "gn:name":"Timbiriche",
    "gn:population":53,
    "gn:timezone":"America/Mexico_City",
    "iso:country":"MX",
    "name:ell_x_preferred":[
        "\u03a4\u03b9\u03bc\u03c0\u03b9\u03c1\u03af\u03c4\u03c3\u03b5"
    ],
    "name:fra_x_preferred":[
        "Timbiriche"
    ],
    "name:hun_x_preferred":[
        "Timbiriche"
    ],
    "name:por_x_preferred":[
        "Timbiriche"
    ],
    "name:ron_x_preferred":[
        "Timbiriche"
    ],
    "name:rus_x_preferred":[
        "Timbiriche"
    ],
    "name:slk_x_preferred":[
        "Timbiriche"
    ],
    "name:spa_x_preferred":[
        "Timbiriche"
    ],
    "wof:name":"Timbiriche",
    "wof:placetype":"locality",
    "wof:population":53
},
  "geometry": {"coordinates":[-101.14055999999999,19.30556],"type":"Point"}
}