{
  "type": "Feature",
  "properties": {
    "gn:admin1_code":"16",
    "gn:admin2_code":"49.0",
    "gn:asciiname":"Timbiriche",
    "gn:country_code":"MX",
    "gn:dem":1170,
    "gn:feature_class":"P",
    "gn:feature_code":"PPL",
    "gn:name":"Timbiriche",
    "gn:population":53,
    "gn:timezone":"America/Mexico_City",
    "iso:country":"MX",
    "wof:name":"Timbiriche",
    "wof:placetype":"locality",
    "wof:population":53
},
  "geometry": {"coordinates":[-101.14055999999999,19.30556],"type":"Point"}
}