{
  "type": "Feature",
  "properties": {
    "gn:admin1_code":"5.0",
    "gn:admin2_code":"31.0",
    "gn:asciiname":"Crucero Sacun Saquila",
    "gn:country_code":"MX",
    "gn:dem":865,
    "gn:feature_class":"P",
    "gn:feature_code":"PPL",
    "gn:name":"Crucero Sac\u00fan Saquil\u00e1",
    "gn:population":0,
    "gn:timezone":"America/Mexico_City",
    "iso:country":"MX",
    "name:spa_x_preferred":[
        "Crucero Sac\u00fan Saquil\u00e1"
    ],
    "wof:name":"Crucero Sacun Saquila",
    "wof:placetype":"locality"
},
  "geometry": {"coordinates":[-91.92225000000001,17.12597],"type":"Point"}
}