{
  "type": "Feature",
  "properties": {
    "gn:admin1_code":"32",
    "gn:admin2_code":"26.0",
    "gn:asciiname":"Rincon de San Feliciano",
    "gn:country_code":"MX",
    "gn:dem":2002,
    "gn:feature_class":"P",
    "gn:feature_code":"PPL",
    "gn:name":"Rinc\u00f3n de San Feliciano",
    "gn:population":0,
    "gn:timezone":"America/Mexico_City",
    "iso:country":"MX",
    "name:spa_x_preferred":[
        "Rinc\u00f3n de San Feliciano"
    ],
    "wof:name":"Rincon de San Feliciano",
    "wof:placetype":"locality"
},
  "geometry": {"coordinates":[-101.42515,24.43349],"type":"Point"}
}