{
  "type": "Feature",
  "properties": {
    "gn:admin1_code":"20",
    "gn:admin2_code":"377",
    "gn:asciiname":"Pie del Cerro de Yucucasa",
    "gn:country_code":"MX",
    "gn:dem":2237,
    "gn:feature_class":"P",
    "gn:feature_code":"PPL",
    "gn:name":"Pie del Cerro de Yucucasa",
    "gn:population":48,
    "gn:timezone":"America/Mexico_City",
    "iso:country":"MX",
    "wof:name":"Pie del Cerro de Yucucasa",
    "wof:placetype":"locality",
    "wof:population":48
},
  "geometry": {"coordinates":[-97.60722,16.71027999999999],"type":"Point"}
}