{
  "type": "Feature",
  "properties": {
    "gn:admin1_code":"25",
    "gn:admin2_code":"17.0",
    "gn:asciiname":"Elsa",
    "gn:country_code":"MX",
    "gn:dem":228,
    "gn:feature_class":"P",
    "gn:feature_code":"PPL",
    "gn:name":"Elsa",
    "gn:population":0,
    "gn:timezone":"America/Mazatlan",
    "iso:country":"MX",
    "name:ceb_x_preferred":[
        "Elsa"
    ],
    "name:deu_x_preferred":[
        "Elsa"
    ],
    "name:epo_x_preferred":[
        "Elsa"
    ],
    "name:fas_x_preferred":[
        "\u0627\u0644\u0633\u0627"
    ],
    "name:fin_x_preferred":[
        "Elsa"
    ],
    "name:fra_x_preferred":[
        "Elsa"
    ],
    "name:ita_x_preferred":[
        "Elsa"
    ],
    "name:jpn_x_preferred":[
        "\u30a8\u30eb\u30b6"
    ],
    "name:lat_x_preferred":[
        "Elsa"
    ],
    "name:nld_x_preferred":[
        "Elsa"
    ],
    "name:pol_x_preferred":[
        "Elsa"
    ],
    "name:por_x_preferred":[
        "Elsa"
    ],
    "name:spa_x_preferred":[
        "Elsa"
    ],
    "name:srp_x_preferred":[
        "\u0415\u043b\u0441\u0430"
    ],
    "name:swe_x_preferred":[
        "Elsa"
    ],
    "name:tur_x_preferred":[
        "Elsa"
    ],
    "wof:name":"Elsa",
    "wof:placetype":"locality"
},
  "geometry": {"coordinates":[-107.87678,25.99305],"type":"Point"}
}