{
  "type": "Feature",
  "properties": {
    "gn:admin1_code":"25",
    "gn:admin2_code":"7",
    "gn:asciiname":"Tararancito",
    "gn:country_code":"MX",
    "gn:dem":932,
    "gn:feature_class":"P",
    "gn:feature_code":"PPL",
    "gn:name":"Tararancito",
    "gn:population":49,
    "gn:timezone":"America/Mazatlan",
    "iso:country":"MX",
    "wof:name":"Tararancito",
    "wof:placetype":"locality",
    "wof:population":49
},
  "geometry": {"coordinates":[-108.05906,26.71688],"type":"Point"}
}