{
  "type": "Feature",
  "properties": {
    "gn:admin1_code":"26.0",
    "gn:admin2_code":"69.0",
    "gn:asciiname":"Arroyo del Moro",
    "gn:country_code":"MX",
    "gn:dem":832,
    "gn:feature_class":"P",
    "gn:feature_code":"PPL",
    "gn:name":"Arroyo del Moro",
    "gn:population":0,
    "gn:timezone":"America/Hermosillo",
    "iso:country":"MX",
    "name:spa_x_preferred":[
        "Arroyo del Moro"
    ],
    "wof:name":"Arroyo del Moro",
    "wof:placetype":"locality"
},
  "geometry": {"coordinates":[-109.11142,28.4425],"type":"Point"}
}