{
  "type": "Feature",
  "properties": {
    "gn:admin1_code":"30",
    "gn:admin2_code":"19.0",
    "gn:asciiname":"Comolica",
    "gn:country_code":"MX",
    "gn:dem":2345,
    "gn:feature_class":"P",
    "gn:feature_code":"PPL",
    "gn:name":"Comolica",
    "gn:population":374,
    "gn:timezone":"America/Mexico_City",
    "iso:country":"MX",
    "wof:name":"Comolica",
    "wof:placetype":"locality",
    "wof:population":374
},
  "geometry": {"coordinates":[-97.1075,18.56333],"type":"Point"}
}