{
  "type": "Feature",
  "properties": {
    "gn:admin1_code":"16",
    "gn:admin2_code":"101",
    "gn:asciiname":"El Aguacate",
    "gn:country_code":"MX",
    "gn:dem":1047,
    "gn:feature_class":"P",
    "gn:feature_code":"PPL",
    "gn:name":"El Aguacate",
    "gn:population":18,
    "gn:timezone":"America/Mexico_City",
    "iso:country":"MX",
    "wof:name":"El Aguacate",
    "wof:placetype":"locality",
    "wof:population":18
},
  "geometry": {"coordinates":[-100.82666999999999,19.39583],"type":"Point"}
}