{
  "type": "Feature",
  "properties": {
    "gn:admin1_code":"22",
    "gn:admin2_code":"10.0",
    "gn:asciiname":"El Charco",
    "gn:country_code":"MX",
    "gn:dem":1690,
    "gn:feature_class":"P",
    "gn:feature_code":"PPL",
    "gn:name":"El Charco",
    "gn:population":0,
    "gn:timezone":"America/Mexico_City",
    "iso:country":"MX",
    "name:spa_x_preferred":[
        "El Charco"
    ],
    "wof:name":"El Charco",
    "wof:placetype":"locality"
},
  "geometry": {"coordinates":[-99.19168999999999,21.39144],"type":"Point"}
}