{
  "type": "Feature",
  "properties": {
    "gn:admin1_code":"6",
    "gn:admin2_code":"65.0",
    "gn:asciiname":"Nogopamo",
    "gn:country_code":"MX",
    "gn:dem":1682,
    "gn:feature_class":"P",
    "gn:feature_code":"PPL",
    "gn:name":"Nogopamo",
    "gn:population":8,
    "gn:timezone":"America/Chihuahua",
    "iso:country":"MX",
    "wof:name":"Nogopamo",
    "wof:placetype":"locality",
    "wof:population":8
},
  "geometry": {"coordinates":[-107.77603000000001,27.3627],"type":"Point"}
}