{
  "type": "Feature",
  "properties": {
    "gn:admin1_code":"24",
    "gn:admin2_code":"24.0",
    "gn:asciiname":"San Marcos",
    "gn:country_code":"MX",
    "gn:dem":1024,
    "gn:feature_class":"P",
    "gn:feature_code":"PPL",
    "gn:name":"San Marcos",
    "gn:population":0,
    "gn:timezone":"America/Mexico_City",
    "iso:country":"MX",
    "wof:name":"San Marcos",
    "wof:placetype":"locality"
},
  "geometry": {"coordinates":[-99.96666999999999,22.18333],"type":"Point"}
}