{
  "type": "Feature",
  "properties": {
    "gn:admin1_code":"30",
    "gn:admin2_code":"101.0",
    "gn:asciiname":"Texmalaca",
    "gn:country_code":"MX",
    "gn:dem":2109,
    "gn:feature_class":"P",
    "gn:feature_code":"PPL",
    "gn:name":"Texmalaca",
    "gn:population":720,
    "gn:timezone":"America/Mexico_City",
    "iso:country":"MX",
    "wof:name":"Texmalaca",
    "wof:placetype":"locality",
    "wof:population":720
},
  "geometry": {"coordinates":[-97.18138999999999,18.95333],"type":"Point"}
}