{
  "type": "Feature",
  "properties": {
    "gn:admin1_code":"6.0",
    "gn:admin2_code":"32.0",
    "gn:asciiname":"El Tallen",
    "gn:country_code":"MX",
    "gn:dem":2090,
    "gn:feature_class":"P",
    "gn:feature_code":"PPL",
    "gn:name":"El Tallen",
    "gn:population":0,
    "gn:timezone":"America/Chihuahua",
    "iso:country":"MX",
    "wof:name":"El Tallen",
    "wof:placetype":"locality"
},
  "geometry": {"coordinates":[-105.71666999999999,26.98333],"type":"Point"}
}