{
  "type": "Feature",
  "properties": {
    "gn:admin1_code":"6",
    "gn:admin2_code":"46.0",
    "gn:asciiname":"San Jose de los Llanos",
    "gn:country_code":"MX",
    "gn:dem":1666,
    "gn:feature_class":"P",
    "gn:feature_code":"PPL",
    "gn:name":"San Jose de los Llanos",
    "gn:population":0,
    "gn:timezone":"America/Mazatlan",
    "iso:country":"MX",
    "name:spa_x_preferred":[
        "San Jose de los Llanos"
    ],
    "wof:name":"San Jose de los Llanos",
    "wof:placetype":"locality"
},
  "geometry": {"coordinates":[-107.84384,26.51953],"type":"Point"}
}