{
  "type": "Feature",
  "properties": {
    "gn:admin1_code":"11",
    "gn:admin2_code":"23.0",
    "gn:asciiname":"El Pochote",
    "gn:country_code":"MX",
    "gn:dem":1740,
    "gn:feature_class":"P",
    "gn:feature_code":"PPL",
    "gn:name":"El Pochote",
    "gn:population":309,
    "gn:timezone":"America/Mexico_City",
    "iso:country":"MX",
    "wof:name":"El Pochote",
    "wof:placetype":"locality",
    "wof:population":309
},
  "geometry": {"coordinates":[-101.72638999999999,20.39167],"type":"Point"}
}