{
  "type": "Feature",
  "properties": {
    "gn:admin1_code":"30",
    "gn:admin2_code":"3.0",
    "gn:asciiname":"Cabanas",
    "gn:country_code":"MX",
    "gn:dem":184,
    "gn:feature_class":"P",
    "gn:feature_code":"PPL",
    "gn:name":"Caba\u00f1as",
    "gn:population":300,
    "gn:timezone":"America/Mexico_City",
    "iso:country":"MX",
    "name:spa_x_preferred":[
        "Caba\u00f1as"
    ],
    "wof:name":"Cabanas",
    "wof:placetype":"locality",
    "wof:population":300
},
  "geometry": {"coordinates":[-94.99198,18.10051],"type":"Point"}
}