{
  "type": "Feature",
  "properties": {
    "gn:admin1_code":"14",
    "gn:admin2_code":"19.0",
    "gn:asciiname":"El Escondido (El Monte)",
    "gn:country_code":"MX",
    "gn:dem":1802,
    "gn:feature_class":"P",
    "gn:feature_code":"PPL",
    "gn:name":"El Escondido (El Monte)",
    "gn:population":5,
    "gn:timezone":"America/Mexico_City",
    "iso:country":"MX",
    "wof:name":"El Escondido (El Monte)",
    "wof:placetype":"locality",
    "wof:population":5
},
  "geometry": {"coordinates":[-104.16139,21.88583],"type":"Point"}
}