{
  "type": "Feature",
  "properties": {
    "gn:admin1_code":"12.0",
    "gn:admin2_code":"22.0",
    "gn:asciiname":"La Cuevita",
    "gn:country_code":"MX",
    "gn:dem":869,
    "gn:feature_class":"P",
    "gn:feature_code":"PPL",
    "gn:name":"La Cuevita",
    "gn:population":0,
    "gn:timezone":"America/Mexico_City",
    "iso:country":"MX",
    "name:spa_x_preferred":[
        "La Cuevita"
    ],
    "wof:name":"La Cuevita",
    "wof:placetype":"locality"
},
  "geometry": {"coordinates":[-100.97485,17.97198999999999],"type":"Point"}
}