{
  "type": "Feature",
  "properties": {
    "gn:admin1_code":"28.0",
    "gn:admin2_code":"8.0",
    "gn:asciiname":"Praxedis Balboa",
    "gn:country_code":"MX",
    "gn:dem":203,
    "gn:feature_class":"P",
    "gn:feature_code":"PPL",
    "gn:name":"Praxedis Balboa",
    "gn:population":98,
    "gn:timezone":"America/Monterrey",
    "iso:country":"MX",
    "name:spa_x_preferred":[
        "Praxedis Balboa"
    ],
    "wof:name":"Praxedis Balboa",
    "wof:placetype":"locality",
    "wof:population":98
},
  "geometry": {"coordinates":[-98.90533000000001,23.61749],"type":"Point"}
}