{
  "type": "Feature",
  "properties": {
    "gn:admin1_code":"14.0",
    "gn:asciiname":"Palo Redondo",
    "gn:country_code":"MX",
    "gn:dem":1927,
    "gn:feature_class":"P",
    "gn:feature_code":"PPL",
    "gn:name":"Palo Redondo",
    "gn:population":0,
    "gn:timezone":"America/Mexico_City",
    "iso:country":"MX",
    "name:spa_x_preferred":[
        "Palo Redondo"
    ],
    "wof:name":"Palo Redondo",
    "wof:placetype":"locality"
},
  "geometry": {"coordinates":[-103.94765,22.3515],"type":"Point"}
}