{
  "type": "Feature",
  "properties": {
    "gn:admin1_code":"30.0",
    "gn:admin2_code":"144.0",
    "gn:asciiname":"El Colibri",
    "gn:country_code":"MX",
    "gn:dem":73,
    "gn:feature_class":"P",
    "gn:feature_code":"PPL",
    "gn:name":"El Colibr\u00ed",
    "gn:population":0,
    "gn:timezone":"America/Mexico_City",
    "iso:country":"MX",
    "name:spa_x_preferred":[
        "El Colibr\u00ed"
    ],
    "wof:name":"El Colibri",
    "wof:placetype":"locality"
},
  "geometry": {"coordinates":[-94.93889,17.82968],"type":"Point"}
}