{
  "type": "Feature",
  "properties": {
    "gn:admin1_code":"20",
    "gn:admin2_code":"76",
    "gn:asciiname":"Zocoteaca (Segunda Seccion)",
    "gn:country_code":"MX",
    "gn:dem":896,
    "gn:feature_class":"P",
    "gn:feature_code":"PPL",
    "gn:name":"Zocoteaca (Segunda Secci\u00f3n)",
    "gn:population":52,
    "gn:timezone":"America/Mexico_City",
    "iso:country":"MX",
    "name:und_x_variant":[
        "Zocoteaca (Segunda Secci\u00f3n)"
    ],
    "wof:name":"Zocoteaca (Segunda Seccion)",
    "wof:placetype":"locality",
    "wof:population":52
},
  "geometry": {"coordinates":[-97.84889,16.66694],"type":"Point"}
}