{
  "type": "Feature",
  "properties": {
    "gn:admin1_code":"5",
    "gn:admin2_code":"99",
    "gn:asciiname":"Los Manguimbos",
    "gn:country_code":"MX",
    "gn:dem":775,
    "gn:feature_class":"P",
    "gn:feature_code":"PPL",
    "gn:name":"Los Manguimbos",
    "gn:population":14,
    "gn:timezone":"America/Mexico_City",
    "iso:country":"MX",
    "wof:name":"Los Manguimbos",
    "wof:placetype":"locality",
    "wof:population":14
},
  "geometry": {"coordinates":[-91.99083,15.91917],"type":"Point"}
}