{
  "type": "Feature",
  "properties": {
    "gn:admin1_code":"5.0",
    "gn:admin2_code":"15.0",
    "gn:asciiname":"La Boquilla",
    "gn:country_code":"MX",
    "gn:dem":681,
    "gn:feature_class":"P",
    "gn:feature_code":"PPL",
    "gn:name":"La Boquilla",
    "gn:population":0,
    "gn:timezone":"America/Mexico_City",
    "iso:country":"MX",
    "name:spa_x_preferred":[
        "La Horquilla"
    ],
    "name:spa_x_variant":[
        "La Boquilla"
    ],
    "wof:name":"La Boquilla",
    "wof:placetype":"locality"
},
  "geometry": {"coordinates":[-92.20740000000001,15.09589],"type":"Point"}
}