{
  "type": "Feature",
  "properties": {
    "gn:admin1_code":"30",
    "gn:admin2_code":"187.0",
    "gn:asciiname":"Ixtapan",
    "gn:country_code":"MX",
    "gn:dem":1154,
    "gn:feature_class":"P",
    "gn:feature_code":"PPL",
    "gn:name":"Ixtapan",
    "gn:population":156,
    "gn:timezone":"America/Mexico_City",
    "iso:country":"MX",
    "wof:name":"Ixtapan",
    "wof:placetype":"locality",
    "wof:population":156
},
  "geometry": {"coordinates":[-96.88611,19.76806],"type":"Point"}
}