{
  "type": "Feature",
  "properties": {
    "gn:admin1_code":"5",
    "gn:admin2_code":"32.0",
    "gn:asciiname":"San Lucas",
    "gn:country_code":"MX",
    "gn:dem":876,
    "gn:feature_class":"P",
    "gn:feature_code":"PPL",
    "gn:name":"San Lucas",
    "gn:population":119,
    "gn:timezone":"America/Mexico_City",
    "iso:country":"MX",
    "wof:name":"San Lucas",
    "wof:placetype":"locality",
    "wof:population":119
},
  "geometry": {"coordinates":[-92.47917,15.29333],"type":"Point"}
}