{
  "type": "Feature",
  "properties": {
    "gn:admin1_code":"20",
    "gn:admin2_code":"483.0",
    "gn:asciiname":"Santa Cruz Lachixolana",
    "gn:country_code":"MX",
    "gn:dem":1656,
    "gn:feature_class":"P",
    "gn:feature_code":"PPL",
    "gn:name":"Santa Cruz Lachixolana",
    "gn:population":0,
    "gn:timezone":"America/Mexico_City",
    "iso:country":"MX",
    "name:spa_x_preferred":[
        "Santa Cruz Lachixolana"
    ],
    "name:und_x_variant":[
        "Lechizolapa",
        "Lachizolapa",
        "Santa Cruz Lachizolana"
    ],
    "wof:name":"Santa Cruz Lachixolana",
    "wof:placetype":"locality"
},
  "geometry": {"coordinates":[-96.85561,17.22784],"type":"Point"}
}