{
  "type": "Feature",
  "properties": {
    "gn:admin1_code":"28",
    "gn:admin2_code":"40.0",
    "gn:asciiname":"Ensenada",
    "gn:country_code":"MX",
    "gn:dem":23,
    "gn:feature_class":"P",
    "gn:feature_code":"PPL",
    "gn:name":"Ensenada",
    "gn:population":0,
    "gn:timezone":"America/Monterrey",
    "iso:country":"MX",
    "name:spa_x_preferred":[
        "Ensenada"
    ],
    "wof:name":"Ensenada",
    "wof:placetype":"locality"
},
  "geometry": {"coordinates":[-97.86757,25.86961],"type":"Point"}
}