{
  "type": "Feature",
  "properties": {
    "gn:admin1_code":"15",
    "gn:admin2_code":"110",
    "gn:asciiname":"Santa Rosa",
    "gn:country_code":"MX",
    "gn:dem":2111,
    "gn:feature_class":"P",
    "gn:feature_code":"PPL",
    "gn:name":"Santa Rosa",
    "gn:population":15,
    "gn:timezone":"America/Mexico_City",
    "iso:country":"MX",
    "wof:name":"Santa Rosa",
    "wof:placetype":"locality",
    "wof:population":15
},
  "geometry": {"coordinates":[-100.08309,19.20069],"type":"Point"}
}