{
  "type": "Feature",
  "properties": {
    "gn:admin1_code":"26.0",
    "gn:admin2_code":"33.0",
    "gn:asciiname":"Santini",
    "gn:country_code":"MX",
    "gn:dem":8,
    "gn:feature_class":"P",
    "gn:feature_code":"PPL",
    "gn:name":"Santini",
    "gn:population":0,
    "gn:timezone":"America/Hermosillo",
    "iso:country":"MX",
    "name:ceb_x_preferred":[
        "Santini"
    ],
    "name:ces_x_preferred":[
        "Santini"
    ],
    "name:deu_x_preferred":[
        "Santini"
    ],
    "name:fra_x_preferred":[
        "Santini"
    ],
    "name:ita_x_preferred":[
        "Santini"
    ],
    "name:rus_x_preferred":[
        "\u0421\u0430\u043d\u0442\u0438\u043d\u0438"
    ],
    "name:spa_x_preferred":[
        "Santini"
    ],
    "name:swe_x_preferred":[
        "Santini"
    ],
    "wof:name":"Santini",
    "wof:placetype":"locality"
},
  "geometry": {"coordinates":[-109.62412999999999,26.79263],"type":"Point"}
}