{
  "type": "Feature",
  "properties": {
    "gn:admin1_code":"7",
    "gn:admin2_code":"11.0",
    "gn:asciiname":"Dulces Nombres",
    "gn:country_code":"MX",
    "gn:dem":1178,
    "gn:feature_class":"P",
    "gn:feature_code":"PPL",
    "gn:name":"Dulces Nombres",
    "gn:population":0,
    "gn:timezone":"America/Monterrey",
    "iso:country":"MX",
    "name:spa_x_preferred":[
        "Dulces Nombres"
    ],
    "wof:name":"Dulces Nombres",
    "wof:placetype":"locality"
},
  "geometry": {"coordinates":[-101.7286,25.65944],"type":"Point"}
}