{
  "type": "Feature",
  "properties": {
    "gn:admin1_code":"23.0",
    "gn:admin2_code":"4.0",
    "gn:asciiname":"Nuevos Horizontes",
    "gn:country_code":"MX",
    "gn:dem":20,
    "gn:feature_class":"P",
    "gn:feature_code":"PPL",
    "gn:name":"Nuevos Horizontes",
    "gn:population":0,
    "gn:timezone":"America/Cancun",
    "iso:country":"MX",
    "name:spa_x_preferred":[
        "Nuevos Horizontes"
    ],
    "wof:name":"Nuevos Horizontes",
    "wof:placetype":"locality"
},
  "geometry": {"coordinates":[-88.60417,18.81611],"type":"Point"}
}