{
  "type": "Feature",
  "properties": {
    "gn:admin1_code":"26.0",
    "gn:admin2_code":"52.0",
    "gn:asciiname":"Palo Dulce",
    "gn:country_code":"MX",
    "gn:dem":1152,
    "gn:feature_class":"P",
    "gn:feature_code":"PPL",
    "gn:name":"Palo Dulce",
    "gn:population":0,
    "gn:timezone":"America/Hermosillo",
    "iso:country":"MX",
    "name:spa_x_preferred":[
        "Palo Dulce"
    ],
    "wof:name":"Palo Dulce",
    "wof:placetype":"locality"
},
  "geometry": {"coordinates":[-108.75498,28.71688],"type":"Point"}
}