{
  "type": "Feature",
  "properties": {
    "gn:admin1_code":"20",
    "gn:admin2_code":"12.0",
    "gn:asciiname":"El Chilar",
    "gn:country_code":"MX",
    "gn:dem":362,
    "gn:feature_class":"P",
    "gn:feature_code":"PPL",
    "gn:name":"El Chilar",
    "gn:population":307,
    "gn:timezone":"America/Mexico_City",
    "iso:country":"MX",
    "wof:name":"El Chilar",
    "wof:placetype":"locality",
    "wof:population":307
},
  "geometry": {"coordinates":[-96.53111,15.82194],"type":"Point"}
}