{
  "type": "Feature",
  "properties": {
    "gn:admin1_code":"30",
    "gn:admin2_code":"193.0",
    "gn:asciiname":"Colonia Chalchihuecan",
    "gn:country_code":"MX",
    "gn:dem":23,
    "gn:feature_class":"P",
    "gn:feature_code":"PPL",
    "gn:name":"Colonia Chalchihuecan",
    "gn:population":1472,
    "gn:timezone":"America/Mexico_City",
    "iso:country":"MX",
    "wof:name":"Colonia Chalchihuecan",
    "wof:placetype":"locality",
    "wof:population":1472
},
  "geometry": {"coordinates":[-96.21444,19.21417000000001],"type":"Point"}
}