{
  "type": "Feature",
  "properties": {
    "gn:admin1_code":"30",
    "gn:admin2_code":"192.0",
    "gn:asciiname":"La Palma",
    "gn:country_code":"MX",
    "gn:dem":26,
    "gn:feature_class":"P",
    "gn:feature_code":"PPL",
    "gn:name":"La Palma",
    "gn:population":0,
    "gn:timezone":"America/Mexico_City",
    "iso:country":"MX",
    "name:und_x_variant":[
        "Tacahuite",
        "El Tecahuite",
        "El Tacahuite",
        "La Palma"
    ],
    "wof:name":"La Palma",
    "wof:placetype":"locality"
},
  "geometry": {"coordinates":[-96.65658999999999,20.01568],"type":"Point"}
}