{
  "type": "Feature",
  "properties": {
    "gn:admin1_code":"15",
    "gn:admin2_code":"79.0",
    "gn:asciiname":"Agua Fria",
    "gn:country_code":"MX",
    "gn:dem":2300,
    "gn:feature_class":"P",
    "gn:feature_code":"PPL",
    "gn:name":"Agua Fr\u00eda",
    "gn:population":0,
    "gn:timezone":"America/Mexico_City",
    "iso:country":"MX",
    "wof:name":"Agua Fria",
    "wof:placetype":"locality"
},
  "geometry": {"coordinates":[-99.47408,20.04821],"type":"Point"}
}