{
  "type": "Feature",
  "properties": {
    "gn:admin1_code":"23.0",
    "gn:asciiname":"San Jose Segundo",
    "gn:country_code":"MX",
    "gn:dem":29,
    "gn:feature_class":"P",
    "gn:feature_code":"PPL",
    "gn:name":"San Jos\u00e9 Segundo",
    "gn:population":0,
    "gn:timezone":"America/Cancun",
    "iso:country":"MX",
    "name:spa_x_preferred":[
        "San Jos\u00e9 Segundo"
    ],
    "wof:name":"San Jose Segundo",
    "wof:placetype":"locality"
},
  "geometry": {"coordinates":[-88.22714000000001,19.96981],"type":"Point"}
}