{
  "type": "Feature",
  "properties": {
    "gn:admin1_code":"20",
    "gn:admin2_code":"431.0",
    "gn:asciiname":"Santiago el Viejo",
    "gn:country_code":"MX",
    "gn:dem":1878,
    "gn:feature_class":"P",
    "gn:feature_code":"PPL",
    "gn:name":"Santiago el Viejo",
    "gn:population":31,
    "gn:timezone":"America/Mexico_City",
    "iso:country":"MX",
    "name:spa_x_preferred":[
        "Santiago Viejo"
    ],
    "wof:name":"Santiago el Viejo",
    "wof:placetype":"locality",
    "wof:population":31
},
  "geometry": {"coordinates":[-96.98166999999999,18.02083],"type":"Point"}
}