{
  "type": "Feature",
  "properties": {
    "gn:admin1_code":"21",
    "gn:admin2_code":"68.0",
    "gn:asciiname":"Cerro de Zaragoza",
    "gn:country_code":"MX",
    "gn:dem":826,
    "gn:feature_class":"P",
    "gn:feature_code":"PPL",
    "gn:name":"Cerro de Zaragoza",
    "gn:population":120,
    "gn:timezone":"America/Mexico_City",
    "iso:country":"MX",
    "wof:name":"Cerro de Zaragoza",
    "wof:placetype":"locality",
    "wof:population":120
},
  "geometry": {"coordinates":[-97.74806,20.11916],"type":"Point"}
}