{
  "type": "Feature",
  "properties": {
    "gn:admin1_code":"24",
    "gn:admin2_code":"18.0",
    "gn:asciiname":"Chununtzen Dos Seccion Siete",
    "gn:country_code":"MX",
    "gn:dem":313,
    "gn:feature_class":"P",
    "gn:feature_code":"PPL",
    "gn:name":"Chununtzen Dos Secci\u00f3n Siete",
    "gn:population":0,
    "gn:timezone":"America/Mexico_City",
    "iso:country":"MX",
    "name:spa_x_preferred":[
        "Chununtzen Dos Secci\u00f3n Siete"
    ],
    "wof:name":"Chununtzen Dos Seccion Siete",
    "wof:placetype":"locality"
},
  "geometry": {"coordinates":[-98.97602000000001,21.50777],"type":"Point"}
}