{
  "type": "Feature",
  "properties": {
    "gn:admin1_code":"27",
    "gn:admin2_code":"12.0",
    "gn:asciiname":"Virginio Chan",
    "gn:country_code":"MX",
    "gn:dem":4,
    "gn:feature_class":"P",
    "gn:feature_code":"PPL",
    "gn:name":"Virginio Ch\u00e1n",
    "gn:population":0,
    "gn:timezone":"America/Mexico_City",
    "iso:country":"MX",
    "name:spa_x_preferred":[
        "Virginio Chan Tercera Secci\u00f3n"
    ],
    "name:spa_x_variant":[
        "Virginio Ch\u00e1n",
        "Tercera Secci\u00f3n",
        "Virginio Chan"
    ],
    "wof:name":"Virginio Chan",
    "wof:placetype":"locality"
},
  "geometry": {"coordinates":[-92.38188,17.90921],"type":"Point"}
}