{
  "type": "Feature",
  "properties": {
    "gn:admin1_code":"5.0",
    "gn:asciiname":"Trece de Septiembre",
    "gn:country_code":"MX",
    "gn:dem":161,
    "gn:feature_class":"P",
    "gn:feature_code":"PPL",
    "gn:name":"Trece de Septiembre",
    "gn:population":0,
    "gn:timezone":"America/Mexico_City",
    "iso:country":"MX",
    "name:spa_x_preferred":[
        "Trece de Septiembre"
    ],
    "wof:name":"Trece de Septiembre",
    "wof:placetype":"locality"
},
  "geometry": {"coordinates":[-91.02315,16.07985],"type":"Point"}
}