{
  "type": "Feature",
  "properties": {
    "gn:admin1_code":"27.0",
    "gn:asciiname":"Emiliano Zapata Segunda Seccion",
    "gn:country_code":"MX",
    "gn:dem":27,
    "gn:feature_class":"P",
    "gn:feature_code":"PPL",
    "gn:name":"Emiliano Zapata Segunda Secci\u00f3n",
    "gn:population":0,
    "gn:timezone":"America/Mexico_City",
    "iso:country":"MX",
    "name:spa_x_preferred":[
        "Emiliano Zapata Segunda Secci\u00f3n"
    ],
    "name:spa_x_variant":[
        "Paso Ancho",
        "Emiliano Zapata",
        "Segunda Secci\u00f3n"
    ],
    "wof:name":"Emiliano Zapata Segunda Seccion",
    "wof:placetype":"locality"
},
  "geometry": {"coordinates":[-92.59523,17.84887],"type":"Point"}
}