{
  "type": "Feature",
  "properties": {
    "gn:admin1_code":"26",
    "gn:admin2_code":"66.0",
    "gn:asciiname":"La Cimbrena",
    "gn:country_code":"MX",
    "gn:dem":450,
    "gn:feature_class":"P",
    "gn:feature_code":"PPL",
    "gn:name":"La Cimbre\u00f1a",
    "gn:population":3,
    "gn:timezone":"America/Hermosillo",
    "iso:country":"MX",
    "name:spa_x_preferred":[
        "La Cimbre\u00f1a"
    ],
    "wof:name":"La Cimbrena",
    "wof:placetype":"locality",
    "wof:population":3
},
  "geometry": {"coordinates":[-110.31559,29.115],"type":"Point"}
}