{
  "type": "Feature",
  "properties": {
    "gn:admin1_code":"6.0",
    "gn:admin2_code":"40.0",
    "gn:asciiname":"Cuatro Zonas",
    "gn:country_code":"MX",
    "gn:dem":2044,
    "gn:feature_class":"P",
    "gn:feature_code":"PPL",
    "gn:name":"Cuatro Zonas",
    "gn:population":0,
    "gn:timezone":"America/Chihuahua",
    "iso:country":"MX",
    "name:spa_x_preferred":[
        "Cuatro Zonas"
    ],
    "name:spa_x_variant":[
        "Rancho Cuarta Zona"
    ],
    "wof:name":"Cuatro Zonas",
    "wof:placetype":"locality"
},
  "geometry": {"coordinates":[-108.19929,29.55474],"type":"Point"}
}