{
  "type": "Feature",
  "properties": {
    "gn:admin1_code":"20",
    "gn:admin2_code":"169",
    "gn:asciiname":"Colonia Roma (Agua Azul)",
    "gn:country_code":"MX",
    "gn:dem":123,
    "gn:feature_class":"P",
    "gn:feature_code":"PPL",
    "gn:name":"Colonia Roma (Agua Azul)",
    "gn:population":24,
    "gn:timezone":"America/Mexico_City",
    "iso:country":"MX",
    "wof:name":"Colonia Roma (Agua Azul)",
    "wof:placetype":"locality",
    "wof:population":24
},
  "geometry": {"coordinates":[-96.64694,18.22917],"type":"Point"}
}