{
  "type": "Feature",
  "properties": {
    "gn:admin1_code":"26",
    "gn:admin2_code":"58.0",
    "gn:asciiname":"Santa Julia",
    "gn:country_code":"MX",
    "gn:dem":830,
    "gn:feature_class":"P",
    "gn:feature_code":"PPL",
    "gn:name":"Santa Julia",
    "gn:population":0,
    "gn:timezone":"America/Hermosillo",
    "iso:country":"MX",
    "name:spa_x_preferred":[
        "Santa Julia"
    ],
    "name:und_x_variant":[
        "Rancho Santa Julia"
    ],
    "wof:name":"Santa Julia",
    "wof:placetype":"locality"
},
  "geometry": {"coordinates":[-110.89790000000001,30.22948],"type":"Point"}
}