{
  "type": "Feature",
  "properties": {
    "gn:admin1_code":"26",
    "gn:admin2_code":"23.0",
    "gn:asciiname":"Rancho de Meza",
    "gn:country_code":"MX",
    "gn:dem":798,
    "gn:feature_class":"P",
    "gn:feature_code":"PPL",
    "gn:name":"Rancho de Meza",
    "gn:population":0,
    "gn:timezone":"America/Hermosillo",
    "iso:country":"MX",
    "name:und_x_variant":[
        "Rancho Meza",
        "Rancho de Meza",
        "El Valle"
    ],
    "wof:name":"Rancho de Meza",
    "wof:placetype":"locality"
},
  "geometry": {"coordinates":[-109.78288000000001,30.09074],"type":"Point"}
}