{
  "type": "Feature",
  "properties": {
    "gn:admin1_code":"24",
    "gn:admin2_code":"10",
    "gn:asciiname":"La Cuesta (Ejido Ganadero Papagayos)",
    "gn:country_code":"MX",
    "gn:dem":1225,
    "gn:feature_class":"P",
    "gn:feature_code":"PPL",
    "gn:name":"La Cuesta (Ejido Ganadero Papagayos)",
    "gn:population":16,
    "gn:timezone":"America/Mexico_City",
    "iso:country":"MX",
    "wof:name":"La Cuesta (Ejido Ganadero Papagayos)",
    "wof:placetype":"locality",
    "wof:population":16
},
  "geometry": {"coordinates":[-99.49639000000001,22.42917000000001],"type":"Point"}
}