{
  "type": "Feature",
  "properties": {
    "gn:admin1_code":"7",
    "gn:admin2_code":"24",
    "gn:asciiname":"Lagunilla",
    "gn:country_code":"MX",
    "gn:dem":1496,
    "gn:feature_class":"P",
    "gn:feature_code":"PPL",
    "gn:name":"Lagunilla",
    "gn:population":20,
    "gn:timezone":"America/Monterrey",
    "iso:country":"MX",
    "wof:name":"Lagunilla",
    "wof:placetype":"locality",
    "wof:population":20
},
  "geometry": {"coordinates":[-101.8681,25.46391],"type":"Point"}
}