{
  "type": "Feature",
  "properties": {
    "gn:admin1_code":"10.0",
    "gn:admin2_code":"26.0",
    "gn:asciiname":"La Guitarrita",
    "gn:country_code":"MX",
    "gn:dem":2500,
    "gn:feature_class":"P",
    "gn:feature_code":"PPL",
    "gn:name":"La Guitarrita",
    "gn:population":0,
    "gn:timezone":"America/Monterrey",
    "iso:country":"MX",
    "name:spa_x_preferred":[
        "La Guitarrita"
    ],
    "wof:name":"La Guitarrita",
    "wof:placetype":"locality"
},
  "geometry": {"coordinates":[-105.60498,24.48753],"type":"Point"}
}