{
  "type": "Feature",
  "properties": {
    "gn:admin1_code":"10",
    "gn:admin2_code":"35",
    "gn:asciiname":"La Barranca",
    "gn:country_code":"MX",
    "gn:dem":2292,
    "gn:feature_class":"P",
    "gn:feature_code":"PPL",
    "gn:name":"La Barranca",
    "gn:population":24,
    "gn:timezone":"America/Monterrey",
    "iso:country":"MX",
    "name:fra_x_preferred":[
        "La Barranca"
    ],
    "name:spa_x_preferred":[
        "La Barranca"
    ],
    "wof:name":"La Barranca",
    "wof:placetype":"locality",
    "wof:population":24
},
  "geometry": {"coordinates":[-106.16231000000001,25.36825],"type":"Point"}
}