{
  "type": "Feature",
  "properties": {
    "gn:admin1_code":"16.0",
    "gn:admin2_code":"89.0",
    "gn:asciiname":"El Palo Colorado",
    "gn:country_code":"MX",
    "gn:dem":288,
    "gn:feature_class":"P",
    "gn:feature_code":"PPL",
    "gn:name":"El Palo Colorado",
    "gn:population":0,
    "gn:timezone":"America/Mexico_City",
    "iso:country":"MX",
    "name:spa_x_preferred":[
        "El Palo Colorado"
    ],
    "wof:name":"El Palo Colorado",
    "wof:placetype":"locality"
},
  "geometry": {"coordinates":[-102.74023,19.04465],"type":"Point"}
}