{
  "type": "Feature",
  "properties": {
    "gn:admin1_code":"16",
    "gn:admin2_code":"112.0",
    "gn:asciiname":"Zirahuato de los Bernal",
    "gn:country_code":"MX",
    "gn:dem":2126,
    "gn:feature_class":"P",
    "gn:feature_code":"PPL",
    "gn:name":"Zirahuato de los Bernal",
    "gn:population":0,
    "gn:timezone":"America/Mexico_City",
    "iso:country":"MX",
    "name:spa_x_preferred":[
        "Zirahuato de los Bernal"
    ],
    "name:und_x_variant":[
        "Zirahuato"
    ],
    "wof:name":"Zirahuato de los Bernal",
    "wof:placetype":"locality"
},
  "geometry": {"coordinates":[-100.40662,19.52124],"type":"Point"}
}