{
  "type": "Feature",
  "properties": {
    "gn:admin1_code":"14.0",
    "gn:admin2_code":"116.0",
    "gn:asciiname":"La Boquilla Negra",
    "gn:country_code":"MX",
    "gn:dem":1918,
    "gn:feature_class":"P",
    "gn:feature_code":"PPL",
    "gn:name":"La Boquilla Negra",
    "gn:population":0,
    "gn:timezone":"America/Mexico_City",
    "iso:country":"MX",
    "name:spa_x_preferred":[
        "La Boquilla Negra"
    ],
    "wof:name":"La Boquilla Negra",
    "wof:placetype":"locality"
},
  "geometry": {"coordinates":[-102.55094,21.67719],"type":"Point"}
}