{
  "type": "Feature",
  "properties": {
    "gn:admin1_code":"26.0",
    "gn:admin2_code":"33.0",
    "gn:asciiname":"Camajoa",
    "gn:country_code":"MX",
    "gn:dem":6,
    "gn:feature_class":"P",
    "gn:feature_code":"PPL",
    "gn:name":"Camajoa",
    "gn:population":0,
    "gn:timezone":"America/Hermosillo",
    "iso:country":"MX",
    "name:spa_x_preferred":[
        "Camajoa"
    ],
    "name:und_x_variant":[
        "Rancho Camajoa"
    ],
    "wof:name":"Camajoa",
    "wof:placetype":"locality"
},
  "geometry": {"coordinates":[-109.77096,26.78742],"type":"Point"}
}