{
  "type": "Feature",
  "properties": {
    "gn:admin1_code":"30",
    "gn:asciiname":"Los Gaviales",
    "gn:country_code":"MX",
    "gn:dem":109,
    "gn:feature_class":"P",
    "gn:feature_code":"PPL",
    "gn:name":"Los Gaviales",
    "gn:population":0,
    "gn:timezone":"America/Mexico_City",
    "iso:country":"MX",
    "name:spa_x_preferred":[
        "Los Gaviales"
    ],
    "wof:name":"Los Gaviales",
    "wof:placetype":"locality"
},
  "geometry": {"coordinates":[-98.53103,21.45803],"type":"Point"}
}