{
  "type": "Feature",
  "properties": {
    "gn:admin1_code":"28",
    "gn:admin2_code":"30.0",
    "gn:asciiname":"La Borbolla",
    "gn:cc2":"MX",
    "gn:country_code":"MX",
    "gn:dem":156,
    "gn:feature_class":"P",
    "gn:feature_code":"PPL",
    "gn:name":"La Borbolla",
    "gn:population":3,
    "gn:timezone":"America/Monterrey",
    "iso:country":"MX",
    "name:und_x_variant":[
        "Rancho La Borboya",
        "La Barbolla",
        "La Borbolla"
    ],
    "wof:name":"La Borbolla",
    "wof:placetype":"locality",
    "wof:population":3
},
  "geometry": {"coordinates":[-98.76778,24.10972000000001],"type":"Point"}
}