{
  "type": "Feature",
  "properties": {
    "gn:admin1_code":"19",
    "gn:admin2_code":"41.0",
    "gn:asciiname":"Pepe y Alex",
    "gn:country_code":"MX",
    "gn:dem":339,
    "gn:feature_class":"P",
    "gn:feature_code":"PPL",
    "gn:name":"Pepe y Alex",
    "gn:population":5,
    "gn:timezone":"America/Monterrey",
    "iso:country":"MX",
    "wof:name":"Pepe y Alex",
    "wof:placetype":"locality",
    "wof:population":5
},
  "geometry": {"coordinates":[-100.05611,25.80861],"type":"Point"}
}