{
  "type": "Feature",
  "properties": {
    "gn:admin1_code":"25",
    "gn:admin2_code":"3.0",
    "gn:asciiname":"Vainillita",
    "gn:country_code":"MX",
    "gn:dem":1358,
    "gn:feature_class":"P",
    "gn:feature_code":"PPL",
    "gn:name":"Vainillita",
    "gn:population":0,
    "gn:timezone":"America/Mazatlan",
    "iso:country":"MX",
    "name:spa_x_preferred":[
        "Vainillita"
    ],
    "name:und_x_variant":[
        "Vainillitas",
        "La Vainillita"
    ],
    "wof:name":"Vainillita",
    "wof:placetype":"locality"
},
  "geometry": {"coordinates":[-107.46665,25.67804],"type":"Point"}
}