{
  "type": "Feature",
  "properties": {
    "gn:admin1_code":"21",
    "gn:admin2_code":"155.0",
    "gn:asciiname":"Tezoquipan",
    "gn:country_code":"MX",
    "gn:dem":949,
    "gn:feature_class":"P",
    "gn:feature_code":"PPL",
    "gn:name":"Tezoquipan",
    "gn:population":170,
    "gn:timezone":"America/Mexico_City",
    "iso:country":"MX",
    "wof:name":"Tezoquipan",
    "wof:placetype":"locality",
    "wof:population":170
},
  "geometry": {"coordinates":[-98.32666999999999,18.08361],"type":"Point"}
}