{
  "type": "Feature",
  "properties": {
    "gn:admin1_code":"21",
    "gn:admin2_code":"156.0",
    "gn:asciiname":"Colonia del Carmen Sur",
    "gn:country_code":"MX",
    "gn:dem":1467,
    "gn:feature_class":"P",
    "gn:feature_code":"PPL",
    "gn:name":"Colonia del Carmen Sur",
    "gn:population":5,
    "gn:timezone":"America/Mexico_City",
    "iso:country":"MX",
    "wof:name":"Colonia del Carmen Sur",
    "wof:placetype":"locality",
    "wof:population":5
},
  "geometry": {"coordinates":[-97.36226000000001,18.4256],"type":"Point"}
}