{
  "type": "Feature",
  "properties": {
    "gn:admin1_code":"6.0",
    "gn:admin2_code":"21.0",
    "gn:asciiname":"Colonia Cuauhtemoc",
    "gn:country_code":"MX",
    "gn:dem":1163,
    "gn:feature_class":"P",
    "gn:feature_code":"PPL",
    "gn:name":"Colonia Cuauht\u00e9moc",
    "gn:population":260,
    "gn:timezone":"America/Chihuahua",
    "iso:country":"MX",
    "name:spa_x_preferred":[
        "Colonia Cuauht\u00e9moc"
    ],
    "wof:name":"Colonia Cuauhtemoc",
    "wof:placetype":"locality",
    "wof:population":260
},
  "geometry": {"coordinates":[-105.39637999999999,28.26898],"type":"Point"}
}