{
  "type": "Feature",
  "properties": {
    "gn:admin1_code":"26",
    "gn:admin2_code":"61.0",
    "gn:asciiname":"Soyopa",
    "gn:country_code":"MX",
    "gn:dem":229,
    "gn:feature_class":"P",
    "gn:feature_code":"PPLA2",
    "gn:name":"Soyopa",
    "gn:population":0,
    "gn:timezone":"America/Hermosillo",
    "iso:country":"MX",
    "wof:name":"Soyopa",
    "wof:placetype":"locality"
},
  "geometry": {"coordinates":[-109.63453,28.76424],"type":"Point"}
}