{
  "type": "Feature",
  "properties": {
    "gn:admin1_code":"6",
    "gn:admin2_code":"27",
    "gn:asciiname":"Nahuajirachi",
    "gn:country_code":"MX",
    "gn:dem":2202,
    "gn:feature_class":"P",
    "gn:feature_code":"PPL",
    "gn:name":"Nahuajirachi",
    "gn:population":27,
    "gn:timezone":"America/Chihuahua",
    "iso:country":"MX",
    "wof:name":"Nahuajirachi",
    "wof:placetype":"locality",
    "wof:population":27
},
  "geometry": {"coordinates":[-107.56242,27.60631],"type":"Point"}
}