{
  "type": "Feature",
  "properties": {
    "gn:admin1_code":"30",
    "gn:admin2_code":"182.0",
    "gn:asciiname":"La Espinita",
    "gn:country_code":"MX",
    "gn:dem":1429,
    "gn:feature_class":"P",
    "gn:feature_code":"PPL",
    "gn:name":"La Espinita",
    "gn:population":5,
    "gn:timezone":"America/Mexico_City",
    "iso:country":"MX",
    "wof:name":"La Espinita",
    "wof:placetype":"locality",
    "wof:population":5
},
  "geometry": {"coordinates":[-96.97389,19.52889],"type":"Point"}
}