{
  "type": "Feature",
  "properties": {
    "gn:admin1_code":"14.0",
    "gn:admin2_code":"15.0",
    "gn:asciiname":"Tilzapote",
    "gn:country_code":"MX",
    "gn:dem":1067,
    "gn:feature_class":"P",
    "gn:feature_code":"PPL",
    "gn:name":"Tilzapote",
    "gn:population":0,
    "gn:timezone":"America/Mexico_City",
    "iso:country":"MX",
    "name:spa_x_preferred":[
        "Tilzapote"
    ],
    "wof:name":"Tilzapote",
    "wof:placetype":"locality"
},
  "geometry": {"coordinates":[-104.37671,19.8112],"type":"Point"}
}