{
  "type": "Feature",
  "properties": {
    "gn:admin1_code":"16",
    "gn:admin2_code":"41.0",
    "gn:asciiname":"San Vicente el Chico",
    "gn:country_code":"MX",
    "gn:dem":2257,
    "gn:feature_class":"P",
    "gn:feature_code":"PPL",
    "gn:name":"San Vicente el Chico",
    "gn:population":0,
    "gn:timezone":"America/Mexico_City",
    "iso:country":"MX",
    "name:spa_x_preferred":[
        "San Vicente el Chico"
    ],
    "name:spa_x_variant":[
        "Manzana de San Vicente"
    ],
    "name:und_x_variant":[
        "San Vicente"
    ],
    "wof:name":"San Vicente el Chico",
    "wof:placetype":"locality"
},
  "geometry": {"coordinates":[-100.48099999999999,19.77736],"type":"Point"}
}