{
  "type": "Feature",
  "properties": {
    "gn:admin1_code":"31",
    "gn:admin2_code":"50.0",
    "gn:asciiname":"Santa Maria Yaxche",
    "gn:country_code":"MX",
    "gn:dem":7,
    "gn:feature_class":"P",
    "gn:feature_code":"PPL",
    "gn:name":"Santa Mar\u00eda Yaxch\u00e9",
    "gn:population":54,
    "gn:timezone":"America/Merida",
    "iso:country":"MX",
    "name:und_x_variant":[
        "Santa Mar\u00eda Yaxch\u00e9"
    ],
    "wof:name":"Santa Maria Yaxche",
    "wof:placetype":"locality",
    "wof:population":54
},
  "geometry": {"coordinates":[-89.63500000000001,21.11722],"type":"Point"}
}