{
  "type": "Feature",
  "properties": {
    "gn:admin1_code":"10",
    "gn:admin2_code":"9.0",
    "gn:asciiname":"Los Bueyes",
    "gn:country_code":"MX",
    "gn:dem":2542,
    "gn:feature_class":"P",
    "gn:feature_code":"PPL",
    "gn:name":"Los Bueyes",
    "gn:population":0,
    "gn:timezone":"America/Monterrey",
    "iso:country":"MX",
    "name:spa_x_preferred":[
        "Los Bueyes"
    ],
    "wof:name":"Los Bueyes",
    "wof:placetype":"locality"
},
  "geometry": {"coordinates":[-105.96657,26.36123],"type":"Point"}
}