{
  "type": "Feature",
  "properties": {
    "gn:admin1_code":"30",
    "gn:admin2_code":"134.0",
    "gn:asciiname":"Paso Mariano",
    "gn:country_code":"MX",
    "gn:dem":101,
    "gn:feature_class":"P",
    "gn:feature_code":"PPL",
    "gn:name":"Paso Mariano",
    "gn:population":388,
    "gn:timezone":"America/Mexico_City",
    "iso:country":"MX",
    "name:spa_x_preferred":[
        "Paso Mariano"
    ],
    "wof:name":"Paso Mariano",
    "wof:placetype":"locality",
    "wof:population":388
},
  "geometry": {"coordinates":[-96.46079,19.32777],"type":"Point"}
}