{
  "type": "Feature",
  "properties": {
    "gn:admin1_code":"5",
    "gn:admin2_code":"87.0",
    "gn:asciiname":"El Parralito",
    "gn:country_code":"MX",
    "gn:dem":22,
    "gn:feature_class":"P",
    "gn:feature_code":"PPL",
    "gn:name":"El Parralito",
    "gn:population":7,
    "gn:timezone":"America/Mexico_City",
    "iso:country":"MX",
    "wof:name":"El Parralito",
    "wof:placetype":"locality",
    "wof:population":7
},
  "geometry": {"coordinates":[-92.18556,14.67639],"type":"Point"}
}