{
  "type": "Feature",
  "properties": {
    "gn:admin1_code":"4",
    "gn:admin2_code":"10.0",
    "gn:asciiname":"Central Villahermosa",
    "gn:country_code":"MX",
    "gn:dem":250,
    "gn:feature_class":"P",
    "gn:feature_code":"PPL",
    "gn:name":"Central Villahermosa",
    "gn:population":0,
    "gn:timezone":"America/Merida",
    "iso:country":"MX",
    "name:spa_x_preferred":[
        "Villahermosa"
    ],
    "name:spa_x_variant":[
        "Central Villahermosa"
    ],
    "name:und_x_variant":[
        "Villa Hermosa"
    ],
    "wof:name":"Central Villahermosa",
    "wof:placetype":"locality"
},
  "geometry": {"coordinates":[-89.68774000000001,17.91534],"type":"Point"}
}