{
  "type": "Feature",
  "properties": {
    "gn:admin1_code":"6",
    "gn:admin2_code":"55.0",
    "gn:asciiname":"San Silvano",
    "gn:country_code":"MX",
    "gn:dem":1162,
    "gn:feature_class":"P",
    "gn:feature_code":"PPL",
    "gn:name":"San Silvano",
    "gn:population":5,
    "gn:timezone":"America/Chihuahua",
    "iso:country":"MX",
    "wof:name":"San Silvano",
    "wof:placetype":"locality",
    "wof:population":5
},
  "geometry": {"coordinates":[-105.5163,28.21048],"type":"Point"}
}