{
  "type": "Feature",
  "properties": {
    "gn:admin1_code":"6",
    "gn:admin2_code":"9.0",
    "gn:asciiname":"Morirabo",
    "gn:country_code":"MX",
    "gn:dem":2355,
    "gn:feature_class":"P",
    "gn:feature_code":"PPL",
    "gn:name":"Mor\u00edrabo",
    "gn:population":0,
    "gn:timezone":"America/Chihuahua",
    "iso:country":"MX",
    "name:spa_x_preferred":[
        "Mor\u00edrabo"
    ],
    "wof:name":"Morirabo",
    "wof:placetype":"locality"
},
  "geometry": {"coordinates":[-107.66448,27.64769],"type":"Point"}
}