{
  "type": "Feature",
  "properties": {
    "gn:admin1_code":"7",
    "gn:admin2_code":"18.0",
    "gn:asciiname":"El Rubio",
    "gn:country_code":"MX",
    "gn:dem":503,
    "gn:feature_class":"P",
    "gn:feature_code":"PPL",
    "gn:name":"El Rubio",
    "gn:population":0,
    "gn:timezone":"America/Monterrey",
    "iso:country":"MX",
    "name:arg_x_preferred":[
        "El Rubio"
    ],
    "name:ast_x_preferred":[
        "El Rubio"
    ],
    "name:bul_x_preferred":[
        "\u0415\u043b \u0420\u0443\u0431\u0438\u043e"
    ],
    "name:cat_x_preferred":[
        "El Rubio"
    ],
    "name:ceb_x_preferred":[
        "El Rubio"
    ],
    "name:epo_x_preferred":[
        "El Rubio"
    ],
    "name:eus_x_preferred":[
        "El Rubio"
    ],
    "name:fra_x_preferred":[
        "El Rubio"
    ],
    "name:glg_x_preferred":[
        "El Rubio"
    ],
    "name:hat_x_preferred":[
        "El Rubio"
    ],
    "name:hun_x_preferred":[
        "El Rubio"
    ],
    "name:hye_x_preferred":[
        "\u0537\u056c \u054c\u0578\u0582\u0562\u056b\u0578"
    ],
    "name:ind_x_preferred":[
        "El Rubio"
    ],
    "name:ita_x_preferred":[
        "El Rubio"
    ],
    "name:kaz_x_preferred":[
        "\u042d\u043b\u044c-\u0420\u0443\u0431\u0438\u043e"
    ],
    "name:msa_x_preferred":[
        "El Rubio"
    ],
    "name:nld_x_preferred":[
        "El Rubio"
    ],
    "name:oci_x_preferred":[
        "El Rubio"
    ],
    "name:pol_x_preferred":[
        "El Rubio"
    ],
    "name:por_x_preferred":[
        "El Rubio"
    ],
    "name:ron_x_preferred":[
        "El Rubio"
    ],
    "name:rus_x_preferred":[
        "\u042d\u043b\u044c-\u0420\u0443\u0431\u0438\u043e"
    ],
    "name:spa_x_preferred":[
        "El Rubio"
    ],
    "name:tur_x_preferred":[
        "El Rubio"
    ],
    "name:ukr_x_preferred":[
        "\u0415\u043b\u044c-\u0420\u0443\u0431\u0456\u043e"
    ],
    "name:und_x_variant":[
        "Rancho El Rubio"
    ],
    "name:uzb_x_preferred":[
        "El Rubio"
    ],
    "name:vie_x_preferred":[
        "El Rubio"
    ],
    "name:war_x_preferred":[
        "El Rubio"
    ],
    "name:zho_x_preferred":[
        "\u57c3\u5c14\u9c81\u7ef4\u5965"
    ],
    "wof:name":"El Rubio",
    "wof:placetype":"locality"
},
  "geometry": {"coordinates":[-101.34206,26.99771],"type":"Point"}
}