{
  "type": "Feature",
  "properties": {
    "gn:admin1_code":"7",
    "gn:admin2_code":"18.0",
    "gn:asciiname":"El Rubio",
    "gn:country_code":"MX",
    "gn:dem":503,
    "gn:feature_class":"P",
    "gn:feature_code":"PPL",
    "gn:name":"El Rubio",
    "gn:population":0,
    "gn:timezone":"America/Monterrey",
    "iso:country":"MX",
    "name:spa_x_preferred":[
        "El Rubio"
    ],
    "name:und_x_variant":[
        "Rancho El Rubio"
    ],
    "wof:name":"El Rubio",
    "wof:placetype":"locality"
},
  "geometry": {"coordinates":[-101.34206,26.99771],"type":"Point"}
}