{
  "type": "Feature",
  "properties": {
    "gn:admin1_code":"25",
    "gn:admin2_code":"12.0",
    "gn:asciiname":"La Vibora",
    "gn:country_code":"MX",
    "gn:dem":150,
    "gn:feature_class":"P",
    "gn:feature_code":"PPL",
    "gn:name":"La V\u00edbora",
    "gn:population":0,
    "gn:timezone":"America/Mazatlan",
    "iso:country":"MX",
    "name:spa_x_preferred":[
        "La V\u00edbora"
    ],
    "wof:name":"La Vibora",
    "wof:placetype":"locality"
},
  "geometry": {"coordinates":[-106.33401000000001,23.51066],"type":"Point"}
}