{
  "type": "Feature",
  "properties": {
    "gn:admin1_code":"11.0",
    "gn:asciiname":"Gato de Palomas",
    "gn:country_code":"MX",
    "gn:dem":1475,
    "gn:feature_class":"P",
    "gn:feature_code":"PPL",
    "gn:name":"Gato de Palomas",
    "gn:population":0,
    "gn:timezone":"America/Mexico_City",
    "iso:country":"MX",
    "name:spa_x_preferred":[
        "Gato de Palomas"
    ],
    "wof:name":"Gato de Palomas",
    "wof:placetype":"locality"
},
  "geometry": {"coordinates":[-99.82344999999999,21.38351],"type":"Point"}
}