{
  "type": "Feature",
  "properties": {
    "gn:admin1_code":"19.0",
    "gn:admin2_code":"43.0",
    "gn:asciiname":"Pedro Carrizales",
    "gn:country_code":"MX",
    "gn:dem":975,
    "gn:feature_class":"P",
    "gn:feature_code":"PPL",
    "gn:name":"Pedro Carrizales",
    "gn:population":0,
    "gn:timezone":"America/Monterrey",
    "iso:country":"MX",
    "name:spa_x_preferred":[
        "Pedro Carrizales"
    ],
    "name:und_x_variant":[
        "Rancho Pedro Carrical"
    ],
    "wof:name":"Pedro Carrizales",
    "wof:placetype":"locality"
},
  "geometry": {"coordinates":[-100.06507000000001,24.98082],"type":"Point"}
}