{
  "type": "Feature",
  "properties": {
    "gn:admin1_code":"20",
    "gn:admin2_code":"2.0",
    "gn:asciiname":"Plan de Ayala",
    "gn:country_code":"MX",
    "gn:dem":83,
    "gn:feature_class":"P",
    "gn:feature_code":"PPL",
    "gn:name":"Plan de Ayala",
    "gn:population":145,
    "gn:timezone":"America/Mexico_City",
    "iso:country":"MX",
    "wof:name":"Plan de Ayala",
    "wof:placetype":"locality",
    "wof:population":145
},
  "geometry": {"coordinates":[-96.66611,18.37444],"type":"Point"}
}