{
  "type": "Feature",
  "properties": {
    "gn:admin1_code":"12",
    "gn:admin2_code":"73.0",
    "gn:asciiname":"Los Cimientos",
    "gn:country_code":"MX",
    "gn:dem":550,
    "gn:feature_class":"P",
    "gn:feature_code":"PPL",
    "gn:name":"Los Cimientos",
    "gn:population":184,
    "gn:timezone":"America/Mexico_City",
    "iso:country":"MX",
    "wof:name":"Los Cimientos",
    "wof:placetype":"locality",
    "wof:population":184
},
  "geometry": {"coordinates":[-101.08965999999999,18.26732],"type":"Point"}
}