{
  "type": "Feature",
  "properties": {
    "gn:admin1_code":"26",
    "gn:admin2_code":"3.0",
    "gn:asciiname":"La Cana",
    "gn:country_code":"MX",
    "gn:dem":395,
    "gn:feature_class":"P",
    "gn:feature_code":"PPL",
    "gn:name":"La Ca\u00f1a",
    "gn:population":0,
    "gn:timezone":"America/Chihuahua",
    "iso:country":"MX",
    "name:spa_x_preferred":[
        "La Ca\u00f1a"
    ],
    "wof:name":"La Cana",
    "wof:placetype":"locality"
},
  "geometry": {"coordinates":[-108.80757,27.73758],"type":"Point"}
}