{
  "type": "Feature",
  "properties": {
    "gn:admin1_code":"2.0",
    "gn:admin2_code":"1.0",
    "gn:asciiname":"El Escondido",
    "gn:country_code":"MX",
    "gn:dem":735,
    "gn:feature_class":"P",
    "gn:feature_code":"PPL",
    "gn:name":"El Escondido",
    "gn:population":0,
    "gn:timezone":"America/Tijuana",
    "iso:country":"MX",
    "name:spa_x_preferred":[
        "El Escondido"
    ],
    "wof:name":"El Escondido",
    "wof:placetype":"locality"
},
  "geometry": {"coordinates":[-116.24388999999999,31.75972],"type":"Point"}
}