{
  "type": "Feature",
  "properties": {
    "gn:admin1_code":"30.0",
    "gn:admin2_code":"144.0",
    "gn:asciiname":"La Cangrejera",
    "gn:country_code":"MX",
    "gn:dem":11,
    "gn:feature_class":"P",
    "gn:feature_code":"PPL",
    "gn:name":"La Cangrejera",
    "gn:population":0,
    "gn:timezone":"America/Mexico_City",
    "iso:country":"MX",
    "name:spa_x_preferred":[
        "La Cangrejera"
    ],
    "name:spa_x_variant":[
        "La Providencia"
    ],
    "wof:name":"La Cangrejera",
    "wof:placetype":"locality"
},
  "geometry": {"coordinates":[-94.86172000000001,17.65631],"type":"Point"}
}