{
  "type": "Feature",
  "properties": {
    "iso:country":"MX",
    "name:spa_x_preferred":[
        "Infonavit San Jose El Eden"
    ],
    "qs:gn_adm0_cc":"MX",
    "qs:gn_local":3516266,
    "qs:gn_nam_loc":"Tapachula, Tapachula, Chiapas, MX",
    "qs:gn_namadm1":"05",
    "qs:local_max":346,
    "qs:local_sum":418,
    "qs:localhoods":4,
    "qs:name":"Infonavit San Jose El Eden",
    "qs:name_adm0":"M\u00e9xico",
    "qs:name_adm1":"Chiapas",
    "qs:name_adm2":"Tapachula",
    "qs:name_local":"Tapachula",
    "qs:photo_max":11,
    "qs:photo_sum":13,
    "qs:placetype":"Suburb",
    "qs:quad_count":2,
    "qs:woe_adm0":23424900,
    "qs:woe_adm1":2346268,
    "qs:woe_adm2":12599798,
    "qs:woe_lau":0,
    "qs:woe_local":148261,
    "qs:woe_ver":"7.10.0",
    "wof:lang":[
        "spa"
    ],
    "wof:name":"Infonavit San Jose El Eden",
    "wof:placetype":"neighbourhood"
},
  "geometry": {"coordinates":[-92.254943,14.889868],"type":"Point"}
}