{
  "type": "Feature",
  "properties": {
    "gn:admin1_code":"11.0",
    "gn:admin2_code":"19.0",
    "gn:asciiname":"Ojo Seco",
    "gn:country_code":"MX",
    "gn:dem":2242,
    "gn:feature_class":"P",
    "gn:feature_code":"PPL",
    "gn:name":"Ojo Seco",
    "gn:population":0,
    "gn:timezone":"America/Mexico_City",
    "iso:country":"MX",
    "name:spa_x_preferred":[
        "Ojo Seco"
    ],
    "wof:name":"Ojo Seco",
    "wof:placetype":"locality"
},
  "geometry": {"coordinates":[-100.4186,20.06907],"type":"Point"}
}