{
  "type": "Feature",
  "properties": {
    "gn:admin1_code":"14.0",
    "gn:admin2_code":"113.0",
    "gn:asciiname":"El Carbunco",
    "gn:country_code":"MX",
    "gn:dem":911,
    "gn:feature_class":"P",
    "gn:feature_code":"PPL",
    "gn:name":"El Carbunco",
    "gn:population":0,
    "gn:timezone":"America/Mexico_City",
    "iso:country":"MX",
    "name:spa_x_preferred":[
        "El Carbunco"
    ],
    "wof:name":"El Carbunco",
    "wof:placetype":"locality"
},
  "geometry": {"coordinates":[-103.94459000000001,19.76304],"type":"Point"}
}