{
  "type": "Feature",
  "properties": {
    "gn:admin1_code":"2",
    "gn:admin2_code":"5.0",
    "gn:asciiname":"Santa Martha",
    "gn:country_code":"MX",
    "gn:dem":88,
    "gn:feature_class":"P",
    "gn:feature_code":"PPL",
    "gn:name":"Santa Martha",
    "gn:population":7,
    "gn:timezone":"America/Tijuana",
    "iso:country":"MX",
    "wof:name":"Santa Martha",
    "wof:placetype":"locality",
    "wof:population":7
},
  "geometry": {"coordinates":[-116.97944,32.33972],"type":"Point"}
}