{
  "type": "Feature",
  "properties": {
    "gn:admin1_code":"5",
    "gn:admin2_code":"52.0",
    "gn:asciiname":"Ignacio Allende",
    "gn:country_code":"MX",
    "gn:dem":1499,
    "gn:feature_class":"P",
    "gn:feature_code":"PPL",
    "gn:name":"Ignacio Allende",
    "gn:population":552,
    "gn:timezone":"America/Mexico_City",
    "iso:country":"MX",
    "wof:name":"Ignacio Allende",
    "wof:placetype":"locality",
    "wof:population":552
},
  "geometry": {"coordinates":[-91.88306,16.31722],"type":"Point"}
}