{
  "type": "Feature",
  "properties": {
    "gn:admin1_code":"6",
    "gn:admin2_code":"8",
    "gn:asciiname":"El Pino",
    "gn:country_code":"MX",
    "gn:dem":1410,
    "gn:feature_class":"P",
    "gn:feature_code":"PPL",
    "gn:name":"El Pino",
    "gn:population":26,
    "gn:timezone":"America/Chihuahua",
    "iso:country":"MX",
    "wof:name":"El Pino",
    "wof:placetype":"locality",
    "wof:population":26
},
  "geometry": {"coordinates":[-107.79046,27.0341],"type":"Point"}
}