{
  "type": "Feature",
  "properties": {
    "gn:admin1_code":"7",
    "gn:admin2_code":"38.0",
    "gn:asciiname":"Las Albercas",
    "gn:country_code":"MX",
    "gn:dem":441,
    "gn:feature_class":"P",
    "gn:feature_code":"PPL",
    "gn:name":"Las Albercas",
    "gn:population":0,
    "gn:timezone":"America/Monterrey",
    "iso:country":"MX",
    "name:und_x_variant":[
        "La Alberca",
        "Ejido Albercas",
        "Albercas",
        "Las Albercas"
    ],
    "wof:name":"Las Albercas",
    "wof:placetype":"locality"
},
  "geometry": {"coordinates":[-101.13952,28.54067],"type":"Point"}
}