{
  "type": "Feature",
  "properties": {
    "gn:admin1_code":"30.0",
    "gn:admin2_code":"32.0",
    "gn:asciiname":"Perla de San Martin",
    "gn:country_code":"MX",
    "gn:dem":785,
    "gn:feature_class":"P",
    "gn:feature_code":"PPL",
    "gn:name":"Perla de San Mart\u00edn",
    "gn:population":258,
    "gn:timezone":"America/Mexico_City",
    "iso:country":"MX",
    "name:spa_x_preferred":[
        "Perla de San Mart\u00edn"
    ],
    "wof:name":"Perla de San Martin",
    "wof:placetype":"locality",
    "wof:population":258
},
  "geometry": {"coordinates":[-95.12242999999999,18.54247],"type":"Point"}
}