{
  "type": "Feature",
  "properties": {
    "gn:admin1_code":"5",
    "gn:admin2_code":"24.0",
    "gn:asciiname":"Naranjal",
    "gn:country_code":"MX",
    "gn:dem":1283,
    "gn:feature_class":"P",
    "gn:feature_code":"PPL",
    "gn:name":"Naranjal",
    "gn:population":0,
    "gn:timezone":"America/Mexico_City",
    "iso:country":"MX",
    "name:ceb_x_preferred":[
        "Naranjal"
    ],
    "name:deu_x_preferred":[
        "Naranjal"
    ],
    "name:pol_x_preferred":[
        "Naranjal"
    ],
    "name:spa_x_preferred":[
        "El Naranjal"
    ],
    "name:spa_x_variant":[
        "Naranjal"
    ],
    "name:swe_x_preferred":[
        "Naranjal"
    ],
    "wof:name":"Naranjal",
    "wof:placetype":"locality"
},
  "geometry": {"coordinates":[-92.10597,16.69464],"type":"Point"}
}