{
  "type": "Feature",
  "properties": {
    "gn:admin1_code":"12.0",
    "gn:admin2_code":"48.0",
    "gn:asciiname":"La Cacanicua",
    "gn:country_code":"MX",
    "gn:dem":729,
    "gn:feature_class":"P",
    "gn:feature_code":"PPL",
    "gn:name":"La Cac\u00e1nicua",
    "gn:population":0,
    "gn:timezone":"America/Mexico_City",
    "iso:country":"MX",
    "name:spa_x_preferred":[
        "La Cac\u00e1nicua"
    ],
    "wof:name":"La Cacanicua",
    "wof:placetype":"locality"
},
  "geometry": {"coordinates":[-101.1734,17.51977999999999],"type":"Point"}
}