{
  "type": "Feature",
  "properties": {
    "gn:admin1_code":"30.0",
    "gn:admin2_code":"155.0",
    "gn:asciiname":"Maguey Primero",
    "gn:country_code":"MX",
    "gn:dem":196,
    "gn:feature_class":"P",
    "gn:feature_code":"PPL",
    "gn:name":"Maguey Primero",
    "gn:population":390,
    "gn:timezone":"America/Mexico_City",
    "iso:country":"MX",
    "name:spa_x_preferred":[
        "Maguey Primero"
    ],
    "wof:name":"Maguey Primero",
    "wof:placetype":"locality",
    "wof:population":390
},
  "geometry": {"coordinates":[-98.20305999999999,21.3575],"type":"Point"}
}