{
  "type": "Feature",
  "properties": {
    "gn:admin1_code":"6",
    "gn:admin2_code":"62.0",
    "gn:asciiname":"Nueva Reforma",
    "gn:country_code":"MX",
    "gn:dem":1188,
    "gn:feature_class":"P",
    "gn:feature_code":"PPL",
    "gn:name":"Nueva Reforma",
    "gn:population":0,
    "gn:timezone":"America/Chihuahua",
    "iso:country":"MX",
    "wof:name":"Nueva Reforma",
    "wof:placetype":"locality"
},
  "geometry": {"coordinates":[-105.26667,27.98333],"type":"Point"}
}