{
  "type": "Feature",
  "properties": {
    "gn:admin1_code":"6",
    "gn:admin2_code":"47.0",
    "gn:asciiname":"La Salitrera",
    "gn:country_code":"MX",
    "gn:dem":626,
    "gn:feature_class":"P",
    "gn:feature_code":"PPL",
    "gn:name":"La Salitrera",
    "gn:population":7,
    "gn:timezone":"America/Chihuahua",
    "iso:country":"MX",
    "name:spa_x_preferred":[
        "La Salitrera"
    ],
    "wof:name":"La Salitrera",
    "wof:placetype":"locality",
    "wof:population":7
},
  "geometry": {"coordinates":[-108.72356000000001,28.04429],"type":"Point"}
}