{
  "type": "Feature",
  "properties": {
    "gn:admin1_code":"14",
    "gn:admin2_code":"30.0",
    "gn:asciiname":"Los Coyotes",
    "gn:country_code":"MX",
    "gn:dem":1647,
    "gn:feature_class":"P",
    "gn:feature_code":"PPL",
    "gn:name":"Los Coyotes",
    "gn:population":6,
    "gn:timezone":"America/Mexico_City",
    "iso:country":"MX",
    "wof:name":"Los Coyotes",
    "wof:placetype":"locality",
    "wof:population":6
},
  "geometry": {"coordinates":[-103.22083000000001,20.30444],"type":"Point"}
}