{
  "type": "Feature",
  "properties": {
    "gn:admin1_code":"19",
    "gn:admin2_code":"22.0",
    "gn:asciiname":"La Escondida",
    "gn:country_code":"MX",
    "gn:dem":166,
    "gn:feature_class":"P",
    "gn:feature_code":"PPL",
    "gn:name":"La Escondida",
    "gn:population":1,
    "gn:timezone":"America/Monterrey",
    "iso:country":"MX",
    "name:spa_x_preferred":[
        "La Escondida"
    ],
    "wof:name":"La Escondida",
    "wof:placetype":"locality",
    "wof:population":1
},
  "geometry": {"coordinates":[-99.10227999999999,25.07133],"type":"Point"}
}