{
  "type": "Feature",
  "properties": {
    "gn:admin1_code":"6",
    "gn:admin2_code":"27",
    "gn:asciiname":"Otovachi (Otovachi de Arriba)",
    "gn:country_code":"MX",
    "gn:dem":2511,
    "gn:feature_class":"P",
    "gn:feature_code":"PPL",
    "gn:name":"Otovachi (Otovachi de Arriba)",
    "gn:population":44,
    "gn:timezone":"America/Chihuahua",
    "iso:country":"MX",
    "wof:name":"Otovachi (Otovachi de Arriba)",
    "wof:placetype":"locality",
    "wof:population":44
},
  "geometry": {"coordinates":[-107.22544000000001,26.70411],"type":"Point"}
}