{
  "type": "Feature",
  "properties": {
    "gn:admin1_code":"17",
    "gn:admin2_code":"17",
    "gn:asciiname":"Cascalote",
    "gn:country_code":"MX",
    "gn:dem":950,
    "gn:feature_class":"P",
    "gn:feature_code":"PPL",
    "gn:name":"Cascalote",
    "gn:population":10,
    "gn:timezone":"America/Mexico_City",
    "iso:country":"MX",
    "wof:name":"Cascalote",
    "wof:placetype":"locality",
    "wof:population":10
},
  "geometry": {"coordinates":[-99.23111,18.65528],"type":"Point"}
}