{
  "type": "Feature",
  "properties": {
    "gn:admin1_code":"7",
    "gn:admin2_code":"23.0",
    "gn:asciiname":"Santa Elena Dos (San Josecito)",
    "gn:country_code":"MX",
    "gn:dem":1076,
    "gn:feature_class":"P",
    "gn:feature_code":"PPL",
    "gn:name":"Santa Elena Dos (San Josecito)",
    "gn:population":6,
    "gn:timezone":"America/Monterrey",
    "iso:country":"MX",
    "wof:name":"Santa Elena Dos (San Josecito)",
    "wof:placetype":"locality",
    "wof:population":6
},
  "geometry": {"coordinates":[-103.16154,27.99884],"type":"Point"}
}