{
  "type": "Feature",
  "properties": {
    "gn:admin1_code":"16.0",
    "gn:admin2_code":"9.0",
    "gn:asciiname":"La Alberca",
    "gn:country_code":"MX",
    "gn:dem":1024,
    "gn:feature_class":"P",
    "gn:feature_code":"PPL",
    "gn:name":"La Alberca",
    "gn:population":0,
    "gn:timezone":"America/Mexico_City",
    "iso:country":"MX",
    "name:spa_x_preferred":[
        "La Alberca"
    ],
    "name:und_x_variant":[
        "La Alberquita"
    ],
    "wof:name":"La Alberca",
    "wof:placetype":"locality"
},
  "geometry": {"coordinates":[-101.70271,18.97548],"type":"Point"}
}