{
  "type": "Feature",
  "properties": {
    "gn:admin1_code":"6",
    "gn:admin2_code":"40.0",
    "gn:asciiname":"Arroyo el Agua",
    "gn:country_code":"MX",
    "gn:dem":1161,
    "gn:feature_class":"P",
    "gn:feature_code":"PPL",
    "gn:name":"Arroyo el Agua",
    "gn:population":0,
    "gn:timezone":"America/Chihuahua",
    "iso:country":"MX",
    "name:spa_x_preferred":[
        "Arroyo el Agua"
    ],
    "wof:name":"Arroyo el Agua",
    "wof:placetype":"locality"
},
  "geometry": {"coordinates":[-108.61044,29.10298],"type":"Point"}
}