{
  "type": "Feature",
  "properties": {
    "gn:admin1_code":"21",
    "gn:admin2_code":"70",
    "gn:asciiname":"Socontitla (Barranca Socontitla)",
    "gn:country_code":"MX",
    "gn:dem":1599,
    "gn:feature_class":"P",
    "gn:feature_code":"PPL",
    "gn:name":"Socontitla (Barranca Socontitla)",
    "gn:population":31,
    "gn:timezone":"America/Mexico_City",
    "iso:country":"MX",
    "wof:name":"Socontitla (Barranca Socontitla)",
    "wof:placetype":"locality",
    "wof:population":31
},
  "geometry": {"coordinates":[-98.0269,18.68405],"type":"Point"}
}