{
  "type": "Feature",
  "properties": {
    "gn:admin1_code":"31",
    "gn:admin2_code":"96.0",
    "gn:asciiname":"Luis Echeverria Alvarez",
    "gn:country_code":"MX",
    "gn:dem":22,
    "gn:feature_class":"P",
    "gn:feature_code":"PPL",
    "gn:name":"Luis Echeverr\u00eda Alvarez",
    "gn:population":0,
    "gn:timezone":"America/Merida",
    "iso:country":"MX",
    "name:spa_x_preferred":[
        "Luis Echeverr\u00eda Alvarez"
    ],
    "wof:name":"Luis Echeverria Alvarez",
    "wof:placetype":"locality"
},
  "geometry": {"coordinates":[-87.73777,21.22955],"type":"Point"}
}