{
  "type": "Feature",
  "properties": {
    "gn:admin1_code":"30.0",
    "gn:admin2_code":"155.0",
    "gn:asciiname":"El Desfiladero",
    "gn:country_code":"MX",
    "gn:dem":101,
    "gn:feature_class":"P",
    "gn:feature_code":"PPL",
    "gn:name":"El Desfiladero",
    "gn:population":0,
    "gn:timezone":"America/Mexico_City",
    "iso:country":"MX",
    "name:spa_x_preferred":[
        "El Desfiladero"
    ],
    "wof:name":"El Desfiladero",
    "wof:placetype":"locality"
},
  "geometry": {"coordinates":[-98.13477,21.32257],"type":"Point"}
}