{
  "type": "Feature",
  "properties": {
    "gn:admin1_code":"30",
    "gn:admin2_code":"175.0",
    "gn:asciiname":"San Alejo",
    "gn:country_code":"MX",
    "gn:dem":113,
    "gn:feature_class":"P",
    "gn:feature_code":"PPL",
    "gn:name":"San Alejo",
    "gn:population":6,
    "gn:timezone":"America/Mexico_City",
    "iso:country":"MX",
    "name:ceb_x_preferred":[
        "San Alejo"
    ],
    "name:fra_x_preferred":[
        "San Alejo"
    ],
    "name:ita_x_preferred":[
        "San Alejo"
    ],
    "name:por_x_preferred":[
        "San Alejo"
    ],
    "name:spa_x_preferred":[
        "San Alejo"
    ],
    "name:zho_x_preferred":[
        "\u8056\u963f\u840a\u970d"
    ],
    "wof:name":"San Alejo",
    "wof:placetype":"locality",
    "wof:population":6
},
  "geometry": {"coordinates":[-97.54833000000001,20.70583],"type":"Point"}
}