{
  "type": "Feature",
  "properties": {
    "gn:admin1_code":"7",
    "gn:admin2_code":"34.0",
    "gn:asciiname":"San Martin Bolivar",
    "gn:country_code":"MX",
    "gn:dem":1257,
    "gn:feature_class":"P",
    "gn:feature_code":"PPL",
    "gn:name":"San Mart\u00edn Bol\u00edvar",
    "gn:population":2,
    "gn:timezone":"America/Monterrey",
    "iso:country":"MX",
    "wof:name":"San Martin Bolivar",
    "wof:placetype":"locality",
    "wof:population":2
},
  "geometry": {"coordinates":[-103.85321,27.9444],"type":"Point"}
}