{
  "type": "Feature",
  "properties": {
    "gn:admin1_code":"11",
    "gn:admin2_code":"39",
    "gn:asciiname":"Los Martinez",
    "gn:country_code":"MX",
    "gn:dem":1802,
    "gn:feature_class":"P",
    "gn:feature_code":"PPL",
    "gn:name":"Los Mart\u00ednez",
    "gn:population":19,
    "gn:timezone":"America/Mexico_City",
    "iso:country":"MX",
    "name:und_x_variant":[
        "Los Mart\u00ednez"
    ],
    "wof:name":"Los Martinez",
    "wof:placetype":"locality",
    "wof:population":19
},
  "geometry": {"coordinates":[-100.77694,20.35139],"type":"Point"}
}