{
  "type": "Feature",
  "properties": {
    "gn:admin1_code":"19.0",
    "gn:asciiname":"Los Alacranes",
    "gn:country_code":"MX",
    "gn:dem":582,
    "gn:feature_class":"P",
    "gn:feature_code":"PPL",
    "gn:name":"Los Alacranes",
    "gn:population":0,
    "gn:timezone":"America/Monterrey",
    "iso:country":"MX",
    "name:spa_x_preferred":[
        "Los Alacranes"
    ],
    "wof:name":"Los Alacranes",
    "wof:placetype":"locality"
},
  "geometry": {"coordinates":[-100.45151,25.95977],"type":"Point"}
}