{
  "type": "Feature",
  "properties": {
    "gn:admin1_code":"4.0",
    "gn:asciiname":"El Bohio",
    "gn:country_code":"MX",
    "gn:dem":16,
    "gn:feature_class":"P",
    "gn:feature_code":"PPL",
    "gn:name":"El Boh\u00edo",
    "gn:population":0,
    "gn:timezone":"America/Merida",
    "iso:country":"MX",
    "name:spa_x_preferred":[
        "El Boh\u00edo"
    ],
    "wof:name":"El Bohio",
    "wof:placetype":"locality"
},
  "geometry": {"coordinates":[-91.49084000000001,18.17555],"type":"Point"}
}