{
  "type": "Feature",
  "properties": {
    "gn:admin1_code":"10",
    "gn:admin2_code":"2",
    "gn:asciiname":"El Oro",
    "gn:country_code":"MX",
    "gn:dem":583,
    "gn:feature_class":"P",
    "gn:feature_code":"PPL",
    "gn:name":"El Oro",
    "gn:population":16,
    "gn:timezone":"America/Monterrey",
    "iso:country":"MX",
    "name:ceb_x_preferred":[
        "El Oro"
    ],
    "name:deu_x_preferred":[
        "El Oro"
    ],
    "name:epo_x_preferred":[
        "El Oro"
    ],
    "name:ita_x_preferred":[
        "El Oro"
    ],
    "name:lad_x_preferred":[
        "El Oro"
    ],
    "name:sco_x_preferred":[
        "El Oro"
    ],
    "name:spa_x_preferred":[
        "El Oro"
    ],
    "name:srp_x_preferred":[
        "\u0415\u043b \u041e\u0440\u043e"
    ],
    "name:swe_x_preferred":[
        "El Oro"
    ],
    "wof:name":"El Oro",
    "wof:placetype":"locality",
    "wof:population":16
},
  "geometry": {"coordinates":[-106.70762999999999,25.11771],"type":"Point"}
}