{
  "type": "Feature",
  "properties": {
    "gn:admin1_code":"10",
    "gn:admin2_code":"2",
    "gn:asciiname":"El Oro",
    "gn:country_code":"MX",
    "gn:dem":583,
    "gn:feature_class":"P",
    "gn:feature_code":"PPL",
    "gn:name":"El Oro",
    "gn:population":16,
    "gn:timezone":"America/Monterrey",
    "iso:country":"MX",
    "wof:name":"El Oro",
    "wof:placetype":"locality",
    "wof:population":16
},
  "geometry": {"coordinates":[-106.70762999999999,25.11771],"type":"Point"}
}