{
  "type": "Feature",
  "properties": {
    "gn:admin1_code":"20",
    "gn:admin2_code":"125.0",
    "gn:asciiname":"San Pedro Leapi",
    "gn:country_code":"MX",
    "gn:dem":1574,
    "gn:feature_class":"P",
    "gn:feature_code":"PPL",
    "gn:name":"San Pedro Leapi",
    "gn:population":515,
    "gn:timezone":"America/Mexico_City",
    "iso:country":"MX",
    "name:spa_x_preferred":[
        "San Pedro Leapi"
    ],
    "name:und_x_variant":[
        "San Pedro",
        "Leapi"
    ],
    "wof:name":"San Pedro Leapi",
    "wof:placetype":"locality",
    "wof:population":515
},
  "geometry": {"coordinates":[-96.12795,16.33387],"type":"Point"}
}