{
  "type": "Feature",
  "properties": {
    "gn:admin1_code":"15",
    "gn:admin2_code":"82.0",
    "gn:asciiname":"El Burrito (El Sauz)",
    "gn:country_code":"MX",
    "gn:dem":1181,
    "gn:feature_class":"P",
    "gn:feature_code":"PPL",
    "gn:name":"El Burrito (El Sauz)",
    "gn:population":98,
    "gn:timezone":"America/Mexico_City",
    "iso:country":"MX",
    "wof:name":"El Burrito (El Sauz)",
    "wof:placetype":"locality",
    "wof:population":98
},
  "geometry": {"coordinates":[-100.21593,18.80629],"type":"Point"}
}