{
  "type": "Feature",
  "properties": {
    "gn:admin1_code":"11",
    "gn:admin2_code":"26.0",
    "gn:asciiname":"Los Angeles",
    "gn:country_code":"MX",
    "gn:dem":1782,
    "gn:feature_class":"P",
    "gn:feature_code":"PPL",
    "gn:name":"Los \u00c1ngeles",
    "gn:population":326,
    "gn:timezone":"America/Mexico_City",
    "iso:country":"MX",
    "name:und_x_variant":[
        "Los \u00c1ngeles"
    ],
    "wof:name":"Los Angeles",
    "wof:placetype":"locality",
    "wof:population":326
},
  "geometry": {"coordinates":[-101.57028,20.82361],"type":"Point"}
}