{
  "type": "Feature",
  "properties": {
    "gn:admin1_code":"15.0",
    "gn:admin2_code":"123.0",
    "gn:asciiname":"Avellaneda",
    "gn:country_code":"MX",
    "gn:dem":489,
    "gn:feature_class":"P",
    "gn:feature_code":"PPL",
    "gn:name":"Avellaneda",
    "gn:population":0,
    "gn:timezone":"America/Mexico_City",
    "iso:country":"MX",
    "name:bel_x_preferred":[
        "\u0410\u0432\u0435\u043b\u044c\u044f\u043d\u0435\u0434\u0430"
    ],
    "name:bul_x_preferred":[
        "\u0410\u0432\u0435\u043b\u044f\u043d\u0435\u0434\u0430"
    ],
    "name:cat_x_preferred":[
        "Avellaneda"
    ],
    "name:ceb_x_preferred":[
        "Avellaneda"
    ],
    "name:ces_x_preferred":[
        "Avellaneda"
    ],
    "name:deu_x_preferred":[
        "Avellaneda"
    ],
    "name:epo_x_preferred":[
        "Avellaneda"
    ],
    "name:fas_x_preferred":[
        "\u0622\u0648\u06cc\u0627\u0646\u062f\u0627"
    ],
    "name:fin_x_preferred":[
        "Avellaneda"
    ],
    "name:fra_x_preferred":[
        "Avellaneda"
    ],
    "name:heb_x_preferred":[
        "\u05d0\u05d1\u05d6'\u05d0\u05e0\u05d3\u05d4"
    ],
    "name:hye_x_preferred":[
        "\u0531\u057e\u0565\u056c\u0575\u0561\u0576\u0565\u0564\u0561"
    ],
    "name:ita_x_preferred":[
        "Avellaneda"
    ],
    "name:jpn_x_preferred":[
        "\u30a2\u30d9\u30b8\u30e3\u30cd\u30fc\u30c0"
    ],
    "name:kat_x_preferred":[
        "\u10d0\u10d5\u10d4\u10da\u10d8\u10d0\u10dc\u10d4\u10d3\u10d0"
    ],
    "name:kor_x_preferred":[
        "\uc544\ubca0\uc57c\ub124\ub2e4"
    ],
    "name:lij_x_preferred":[
        "Avellaneda"
    ],
    "name:lit_x_preferred":[
        "Aveljaneda"
    ],
    "name:nld_x_preferred":[
        "Avellaneda"
    ],
    "name:nor_x_preferred":[
        "Avellaneda"
    ],
    "name:pol_x_preferred":[
        "Avellaneda"
    ],
    "name:por_x_preferred":[
        "Avellaneda"
    ],
    "name:rus_x_preferred":[
        "\u0410\u0432\u0435\u043b\u044c\u044f\u043d\u0435\u0434\u0430"
    ],
    "name:sco_x_preferred":[
        "Avellaneda"
    ],
    "name:spa_x_preferred":[
        "Avellaneda"
    ],
    "name:srp_x_preferred":[
        "\u0410\u0432\u0435\u0459\u0430\u043d\u0435\u0434\u0430"
    ],
    "name:swe_x_preferred":[
        "Avellaneda"
    ],
    "name:szl_x_preferred":[
        "Avellaneda"
    ],
    "name:tur_x_preferred":[
        "Avellaneda"
    ],
    "name:ukr_x_preferred":[
        "\u0410\u0432\u0435\u043b\u044c\u044f\u043d\u0435\u0434\u0430"
    ],
    "name:urd_x_preferred":[
        "\u0627\u0648\u06cc\u0626\u0627\u0646\u06cc\u062f\u0627"
    ],
    "name:vol_x_preferred":[
        "Avellaneda"
    ],
    "name:war_x_preferred":[
        "Avellaneda"
    ],
    "name:zho_x_preferred":[
        "\u963f\u97e6\u5229\u4e9a\u5185\u8fbe"
    ],
    "wof:name":"Avellaneda",
    "wof:placetype":"locality"
},
  "geometry": {"coordinates":[-100.54505,18.96367],"type":"Point"}
}