{
  "type": "Feature",
  "properties": {
    "gn:admin1_code":"15.0",
    "gn:admin2_code":"123.0",
    "gn:asciiname":"Avellaneda",
    "gn:country_code":"MX",
    "gn:dem":489,
    "gn:feature_class":"P",
    "gn:feature_code":"PPL",
    "gn:name":"Avellaneda",
    "gn:population":0,
    "gn:timezone":"America/Mexico_City",
    "iso:country":"MX",
    "name:spa_x_preferred":[
        "Avellaneda"
    ],
    "wof:name":"Avellaneda",
    "wof:placetype":"locality"
},
  "geometry": {"coordinates":[-100.54505,18.96367],"type":"Point"}
}