{
  "type": "Feature",
  "properties": {
    "gn:admin1_code":"6",
    "gn:admin2_code":"65.0",
    "gn:asciiname":"Huatebachi",
    "gn:country_code":"MX",
    "gn:dem":1542,
    "gn:feature_class":"P",
    "gn:feature_code":"PPL",
    "gn:name":"Huat\u00e9bachi",
    "gn:population":0,
    "gn:timezone":"America/Chihuahua",
    "iso:country":"MX",
    "name:spa_x_preferred":[
        "Huat\u00e9bachi"
    ],
    "wof:name":"Huatebachi",
    "wof:placetype":"locality"
},
  "geometry": {"coordinates":[-107.94329,27.26698],"type":"Point"}
}