{
  "type": "Feature",
  "properties": {
    "gn:admin1_code":"2",
    "gn:admin2_code":"1.0",
    "gn:asciiname":"Mision San Francisco de Borja",
    "gn:country_code":"MX",
    "gn:dem":434,
    "gn:feature_class":"P",
    "gn:feature_code":"PPL",
    "gn:name":"Misi\u00f3n San Francisco de Borja",
    "gn:population":4,
    "gn:timezone":"America/Tijuana",
    "iso:country":"MX",
    "name:und_x_variant":[
        "San Borgas",
        "San Borja"
    ],
    "wof:name":"Mision San Francisco de Borja",
    "wof:placetype":"locality",
    "wof:population":4
},
  "geometry": {"coordinates":[-113.75345,28.7441],"type":"Point"}
}