{
  "type": "Feature",
  "properties": {
    "gn:admin1_code":"31",
    "gn:admin2_code":"62.0",
    "gn:asciiname":"Yuncu",
    "gn:country_code":"MX",
    "gn:dem":17,
    "gn:feature_class":"P",
    "gn:feature_code":"PPL",
    "gn:name":"Yuncu",
    "gn:population":0,
    "gn:timezone":"America/Merida",
    "iso:country":"MX",
    "name:spa_x_preferred":[
        "Yuncu"
    ],
    "wof:name":"Yuncu",
    "wof:placetype":"locality"
},
  "geometry": {"coordinates":[-89.60332,20.57872],"type":"Point"}
}