{
  "type": "Feature",
  "properties": {
    "gn:admin1_code":"10",
    "gn:admin2_code":"25",
    "gn:asciiname":"Antonio Cardenas Martinez",
    "gn:country_code":"MX",
    "gn:dem":1618,
    "gn:feature_class":"P",
    "gn:feature_code":"PPL",
    "gn:name":"Antonio C\u00e1rdenas Mart\u00ednez",
    "gn:population":13,
    "gn:timezone":"America/Monterrey",
    "iso:country":"MX",
    "name:und_x_variant":[
        "Antonio C\u00e1rdenas Mart\u00ednez"
    ],
    "wof:name":"Antonio Cardenas Martinez",
    "wof:placetype":"locality",
    "wof:population":13
},
  "geometry": {"coordinates":[-105.52667,26.03389],"type":"Point"}
}