{
  "type": "Feature",
  "properties": {
    "gn:admin1_code":"30",
    "gn:admin2_code":"128.0",
    "gn:asciiname":"La Pedrera (El Pedregal)",
    "gn:country_code":"MX",
    "gn:dem":2514,
    "gn:feature_class":"P",
    "gn:feature_code":"PPL",
    "gn:name":"La Pedrera (El Pedregal)",
    "gn:population":7,
    "gn:timezone":"America/Mexico_City",
    "iso:country":"MX",
    "wof:name":"La Pedrera (El Pedregal)",
    "wof:placetype":"locality",
    "wof:population":7
},
  "geometry": {"coordinates":[-97.26083,19.49472],"type":"Point"}
}