{
  "type": "Feature",
  "properties": {
    "gn:admin1_code":"7.0",
    "gn:admin2_code":"8.0",
    "gn:asciiname":"Los Morales",
    "gn:country_code":"MX",
    "gn:dem":503,
    "gn:feature_class":"P",
    "gn:feature_code":"PPL",
    "gn:name":"Los Morales",
    "gn:population":0,
    "gn:timezone":"America/Monterrey",
    "iso:country":"MX",
    "name:spa_x_preferred":[
        "Los Morales"
    ],
    "wof:name":"Los Morales",
    "wof:placetype":"locality"
},
  "geometry": {"coordinates":[-101.31317,27.31342],"type":"Point"}
}