{
  "type": "Feature",
  "properties": {
    "gn:admin1_code":"20",
    "gn:admin2_code":"153.0",
    "gn:asciiname":"La Chopa",
    "gn:country_code":"MX",
    "gn:dem":399,
    "gn:feature_class":"P",
    "gn:feature_code":"PPL",
    "gn:name":"La Chopa",
    "gn:population":9,
    "gn:timezone":"America/Mexico_City",
    "iso:country":"MX",
    "wof:name":"La Chopa",
    "wof:placetype":"locality",
    "wof:population":9
},
  "geometry": {"coordinates":[-97.02833,16.01139],"type":"Point"}
}