{
  "type": "Feature",
  "properties": {
    "gn:admin1_code":"30",
    "gn:admin2_code":"130.0",
    "gn:asciiname":"Jose Ordonez",
    "gn:country_code":"MX",
    "gn:dem":109,
    "gn:feature_class":"P",
    "gn:feature_code":"PPL",
    "gn:name":"Jos\u00e9 Ord\u00f3\u00f1ez",
    "gn:population":5,
    "gn:timezone":"America/Mexico_City",
    "iso:country":"MX",
    "name:und_x_variant":[
        "Jos\u00e9 Ord\u00f3\u00f1ez"
    ],
    "wof:name":"Jose Ordonez",
    "wof:placetype":"locality",
    "wof:population":5
},
  "geometry": {"coordinates":[-95.51333,17.84861],"type":"Point"}
}