{
  "type": "Feature",
  "properties": {
    "gn:admin1_code":"6",
    "gn:admin2_code":"32",
    "gn:asciiname":"El Tule de Enmedio",
    "gn:country_code":"MX",
    "gn:dem":1708,
    "gn:feature_class":"P",
    "gn:feature_code":"PPL",
    "gn:name":"El Tule de Enmedio",
    "gn:population":15,
    "gn:timezone":"America/Chihuahua",
    "iso:country":"MX",
    "wof:name":"El Tule de Enmedio",
    "wof:placetype":"locality",
    "wof:population":15
},
  "geometry": {"coordinates":[-105.67265,27.06134],"type":"Point"}
}