{
  "type": "Feature",
  "properties": {
    "gn:admin1_code":"16.0",
    "gn:admin2_code":"19.0",
    "gn:asciiname":"La Lobera",
    "gn:country_code":"MX",
    "gn:dem":1739,
    "gn:feature_class":"P",
    "gn:feature_code":"PPL",
    "gn:name":"La Lobera",
    "gn:population":0,
    "gn:timezone":"America/Mexico_City",
    "iso:country":"MX",
    "name:spa_x_preferred":[
        "La Lobera"
    ],
    "wof:name":"La Lobera",
    "wof:placetype":"locality"
},
  "geometry": {"coordinates":[-102.69862000000001,19.64688],"type":"Point"}
}