{
  "type": "Feature",
  "properties": {
    "gn:admin1_code":"16",
    "gn:admin2_code":"34",
    "gn:asciiname":"Santa Ana",
    "gn:country_code":"MX",
    "gn:dem":1635,
    "gn:feature_class":"P",
    "gn:feature_code":"PPL",
    "gn:name":"Santa Ana",
    "gn:population":18,
    "gn:timezone":"America/Mexico_City",
    "iso:country":"MX",
    "wof:name":"Santa Ana",
    "wof:placetype":"locality",
    "wof:population":18
},
  "geometry": {"coordinates":[-100.78917,19.42528],"type":"Point"}
}