{
  "type": "Feature",
  "properties": {
    "gn:admin1_code":"13",
    "gn:admin2_code":"16.0",
    "gn:asciiname":"Las Animas",
    "gn:country_code":"MX",
    "gn:dem":2588,
    "gn:feature_class":"P",
    "gn:feature_code":"PPL",
    "gn:name":"Las \u00c1nimas",
    "gn:population":376,
    "gn:timezone":"America/Mexico_City",
    "iso:country":"MX",
    "name:ceb_x_preferred":[
        "Las Animas"
    ],
    "name:deu_x_preferred":[
        "Las \u00c1nimas"
    ],
    "name:nld_x_preferred":[
        "Las Animas"
    ],
    "name:pol_x_preferred":[
        "Las Animas"
    ],
    "name:spa_x_preferred":[
        "Las \u00c1nimas"
    ],
    "name:srp_x_preferred":[
        "\u041b\u0430\u0441 \u0410\u043d\u0438\u043c\u0430\u0441"
    ],
    "name:swe_x_preferred":[
        "Las Animas"
    ],
    "name:und_x_variant":[
        "Las \u00c1nimas"
    ],
    "wof:name":"Las Animas",
    "wof:placetype":"locality",
    "wof:population":376
},
  "geometry": {"coordinates":[-98.33056000000001,19.92139],"type":"Point"}
}