{
  "type": "Feature",
  "properties": {
    "gn:admin1_code":"19",
    "gn:admin2_code":"7.0",
    "gn:asciiname":"La Laguna",
    "gn:country_code":"MX",
    "gn:dem":1981,
    "gn:feature_class":"P",
    "gn:feature_code":"PPL",
    "gn:name":"La Laguna",
    "gn:population":0,
    "gn:timezone":"America/Monterrey",
    "iso:country":"MX",
    "name:spa_x_preferred":[
        "La Laguna"
    ],
    "wof:name":"La Laguna",
    "wof:placetype":"locality"
},
  "geometry": {"coordinates":[-99.87734,24.24888],"type":"Point"}
}