{
  "type": "Feature",
  "properties": {
    "gn:admin1_code":"21",
    "gn:admin2_code":"212.0",
    "gn:asciiname":"El Puerto (Reforma)",
    "gn:country_code":"MX",
    "gn:dem":2579,
    "gn:feature_class":"P",
    "gn:feature_code":"PPL",
    "gn:name":"El Puerto (Reforma)",
    "gn:population":143,
    "gn:timezone":"America/Mexico_City",
    "iso:country":"MX",
    "wof:name":"El Puerto (Reforma)",
    "wof:placetype":"locality",
    "wof:population":143
},
  "geometry": {"coordinates":[-97.59744999999999,19.69815],"type":"Point"}
}