{
  "type": "Feature",
  "properties": {
    "gn:admin1_code":"16",
    "gn:admin2_code":"10.0",
    "gn:asciiname":"Jaujilla",
    "gn:country_code":"MX",
    "gn:dem":170,
    "gn:feature_class":"P",
    "gn:feature_code":"PPL",
    "gn:name":"Jaujilla",
    "gn:population":71,
    "gn:timezone":"America/Mexico_City",
    "iso:country":"MX",
    "wof:name":"Jaujilla",
    "wof:placetype":"locality",
    "wof:population":71
},
  "geometry": {"coordinates":[-102.6425,18.1475],"type":"Point"}
}