{
  "type": "Feature",
  "properties": {
    "gn:admin1_code":"20",
    "gn:admin2_code":"217",
    "gn:asciiname":"Loma de Corral",
    "gn:country_code":"MX",
    "gn:dem":1761,
    "gn:feature_class":"P",
    "gn:feature_code":"PPL",
    "gn:name":"Loma de Corral",
    "gn:population":17,
    "gn:timezone":"America/Mexico_City",
    "iso:country":"MX",
    "wof:name":"Loma de Corral",
    "wof:placetype":"locality",
    "wof:population":17
},
  "geometry": {"coordinates":[-97.12667,17.07777999999999],"type":"Point"}
}