{
  "type": "Feature",
  "properties": {
    "gn:admin1_code":"6",
    "gn:admin2_code":"32.0",
    "gn:asciiname":"El Centenario",
    "gn:country_code":"MX",
    "gn:dem":1683,
    "gn:feature_class":"P",
    "gn:feature_code":"PPL",
    "gn:name":"El Centenario",
    "gn:population":8,
    "gn:timezone":"America/Chihuahua",
    "iso:country":"MX",
    "name:spa_x_preferred":[
        "El Centenario"
    ],
    "name:srp_x_preferred":[
        "\u0415\u043b \u0421\u0435\u043d\u0442\u0435\u043d\u0430\u0440\u0438\u043e"
    ],
    "wof:name":"El Centenario",
    "wof:placetype":"locality",
    "wof:population":8
},
  "geometry": {"coordinates":[-105.74876999999999,27.17627],"type":"Point"}
}