{
  "type": "Feature",
  "properties": {
    "gn:admin1_code":"6",
    "gn:admin2_code":"46.0",
    "gn:asciiname":"El Bosque",
    "gn:country_code":"MX",
    "gn:dem":1659,
    "gn:feature_class":"P",
    "gn:feature_code":"PPL",
    "gn:name":"El Bosque",
    "gn:population":0,
    "gn:timezone":"America/Chihuahua",
    "iso:country":"MX",
    "name:spa_x_preferred":[
        "El Bosque"
    ],
    "wof:name":"El Bosque",
    "wof:placetype":"locality"
},
  "geometry": {"coordinates":[-107.80949,26.48582],"type":"Point"}
}