{
  "type": "Feature",
  "properties": {
    "gn:admin1_code":"22.0",
    "gn:admin2_code":"12.0",
    "gn:asciiname":"Las Hormigas",
    "gn:country_code":"MX",
    "gn:dem":1909,
    "gn:feature_class":"P",
    "gn:feature_code":"PPL",
    "gn:name":"Las Hormigas",
    "gn:population":0,
    "gn:timezone":"America/Mexico_City",
    "iso:country":"MX",
    "name:spa_x_preferred":[
        "Las Hormigas"
    ],
    "wof:name":"Las Hormigas",
    "wof:placetype":"locality"
},
  "geometry": {"coordinates":[-100.15942,20.53179],"type":"Point"}
}