{
  "type": "Feature",
  "properties": {
    "gn:admin1_code":"6",
    "gn:admin2_code":"8",
    "gn:asciiname":"El Carrizal",
    "gn:country_code":"MX",
    "gn:dem":546,
    "gn:feature_class":"P",
    "gn:feature_code":"PPL",
    "gn:name":"El Carrizal",
    "gn:population":36,
    "gn:timezone":"America/Chihuahua",
    "iso:country":"MX",
    "wof:name":"El Carrizal",
    "wof:placetype":"locality",
    "wof:population":36
},
  "geometry": {"coordinates":[-107.76101,26.86355],"type":"Point"}
}