{
  "type": "Feature",
  "properties": {
    "gn:admin1_code":"13",
    "gn:admin2_code":"68",
    "gn:asciiname":"Chalacuaco",
    "gn:country_code":"MX",
    "gn:dem":1851,
    "gn:feature_class":"P",
    "gn:feature_code":"PPL",
    "gn:name":"Chalacuaco",
    "gn:population":10,
    "gn:timezone":"America/Mexico_City",
    "iso:country":"MX",
    "wof:name":"Chalacuaco",
    "wof:placetype":"locality",
    "wof:population":10
},
  "geometry": {"coordinates":[-98.65582000000001,20.71414],"type":"Point"}
}