{
  "type": "Feature",
  "properties": {
    "gn:admin1_code":"23.0",
    "gn:asciiname":"El Huanal",
    "gn:country_code":"MX",
    "gn:dem":57,
    "gn:feature_class":"P",
    "gn:feature_code":"PPL",
    "gn:name":"El Huanal",
    "gn:population":0,
    "gn:timezone":"America/Cancun",
    "iso:country":"MX",
    "name:spa_x_preferred":[
        "El Huanal"
    ],
    "wof:name":"El Huanal",
    "wof:placetype":"locality"
},
  "geometry": {"coordinates":[-88.82231,19.25694],"type":"Point"}
}