{
  "type": "Feature",
  "properties": {
    "gn:admin1_code":"14",
    "gn:admin2_code":"35",
    "gn:asciiname":"Rincon Verde",
    "gn:country_code":"MX",
    "gn:dem":2032,
    "gn:feature_class":"P",
    "gn:feature_code":"PPL",
    "gn:name":"Rinc\u00f3n Verde",
    "gn:population":19,
    "gn:timezone":"America/Mexico_City",
    "iso:country":"MX",
    "name:und_x_variant":[
        "Rinc\u00f3n Verde"
    ],
    "wof:name":"Rincon Verde",
    "wof:placetype":"locality",
    "wof:population":19
},
  "geometry": {"coordinates":[-102.05028,21.63361],"type":"Point"}
}