{
  "type": "Feature",
  "properties": {
    "gn:admin1_code":"15",
    "gn:admin2_code":"78.0",
    "gn:asciiname":"San Pedro el Grande",
    "gn:country_code":"MX",
    "gn:dem":1585,
    "gn:feature_class":"P",
    "gn:feature_code":"PPL",
    "gn:name":"San Pedro el Grande",
    "gn:population":65,
    "gn:timezone":"America/Mexico_City",
    "iso:country":"MX",
    "wof:name":"San Pedro el Grande",
    "wof:placetype":"locality",
    "wof:population":65
},
  "geometry": {"coordinates":[-100.31142,19.20736],"type":"Point"}
}