{
  "type": "Feature",
  "properties": {
    "gn:admin1_code":"25.0",
    "gn:admin2_code":"17.0",
    "gn:asciiname":"Campamento Bacurato S.R.H.",
    "gn:country_code":"MX",
    "gn:dem":181,
    "gn:feature_class":"P",
    "gn:feature_code":"PPL",
    "gn:name":"Campamento Bacurato S.R.H.",
    "gn:population":0,
    "gn:timezone":"America/Mazatlan",
    "iso:country":"MX",
    "name:spa_x_preferred":[
        "Campamento Bacurato S.R.H."
    ],
    "name:und_x_variant":[
        "Bacurato"
    ],
    "wof:name":"Campamento Bacurato S.R.H.",
    "wof:placetype":"locality"
},
  "geometry": {"coordinates":[-107.90600000000001,25.84613],"type":"Point"}
}