{
  "type": "Feature",
  "properties": {
    "gn:admin1_code":"30.0",
    "gn:admin2_code":"121.0",
    "gn:asciiname":"San Pablo",
    "gn:country_code":"MX",
    "gn:dem":68,
    "gn:feature_class":"P",
    "gn:feature_code":"PPL",
    "gn:name":"San Pablo",
    "gn:population":6,
    "gn:timezone":"America/Mexico_City",
    "iso:country":"MX",
    "name:spa_x_preferred":[
        "San Pablo"
    ],
    "wof:name":"San Pablo",
    "wof:placetype":"locality",
    "wof:population":6
},
  "geometry": {"coordinates":[-98.01972000000001,21.73333],"type":"Point"}
}