{
  "type": "Feature",
  "properties": {
    "gn:admin1_code":"19",
    "gn:admin2_code":"32.0",
    "gn:asciiname":"La Tumbaga",
    "gn:country_code":"MX",
    "gn:dem":240,
    "gn:feature_class":"P",
    "gn:feature_code":"PPL",
    "gn:name":"La Tumbaga",
    "gn:population":0,
    "gn:timezone":"America/Monterrey",
    "iso:country":"MX",
    "name:spa_x_preferred":[
        "La Tumbaga"
    ],
    "name:und_x_variant":[
        "Rancho La T\u00fambaga"
    ],
    "wof:name":"La Tumbaga",
    "wof:placetype":"locality"
},
  "geometry": {"coordinates":[-100.49668,27.3596],"type":"Point"}
}