{
  "type": "Feature",
  "properties": {
    "gn:admin1_code":"16",
    "gn:admin2_code":"92.0",
    "gn:asciiname":"El Puerto del Cuachalalate",
    "gn:country_code":"MX",
    "gn:dem":459,
    "gn:feature_class":"P",
    "gn:feature_code":"PPL",
    "gn:name":"El Puerto del Cuachalalate",
    "gn:population":0,
    "gn:timezone":"America/Mexico_City",
    "iso:country":"MX",
    "name:spa_x_preferred":[
        "El Puerto del Cuachalalate"
    ],
    "wof:name":"El Puerto del Cuachalalate",
    "wof:placetype":"locality"
},
  "geometry": {"coordinates":[-100.79131,18.88608],"type":"Point"}
}