{
  "type": "Feature",
  "properties": {
    "gn:admin1_code":"28",
    "gn:admin2_code":"1.0",
    "gn:asciiname":"Ursulo Galvan",
    "gn:country_code":"MX",
    "gn:dem":70,
    "gn:feature_class":"P",
    "gn:feature_code":"PPL",
    "gn:name":"\u00darsulo Galv\u00e1n",
    "gn:population":85,
    "gn:timezone":"America/Monterrey",
    "iso:country":"MX",
    "name:und_x_variant":[
        "\u00darsulo Galv\u00e1n"
    ],
    "wof:name":"Ursulo Galvan",
    "wof:placetype":"locality",
    "wof:population":85
},
  "geometry": {"coordinates":[-98.19667,24.00833],"type":"Point"}
}