{
  "type": "Feature",
  "properties": {
    "gn:admin1_code":"6",
    "gn:admin2_code":"9.0",
    "gn:asciiname":"Bahuichivo",
    "gn:country_code":"MX",
    "gn:dem":2377,
    "gn:feature_class":"P",
    "gn:feature_code":"PPL",
    "gn:name":"Bahuichivo",
    "gn:population":6,
    "gn:timezone":"America/Chihuahua",
    "iso:country":"MX",
    "wof:name":"Bahuichivo",
    "wof:placetype":"locality",
    "wof:population":6
},
  "geometry": {"coordinates":[-107.65576,27.70603],"type":"Point"}
}