{
  "type": "Feature",
  "properties": {
    "gn:admin1_code":"20",
    "gn:admin2_code":"127.0",
    "gn:asciiname":"Union y Progreso",
    "gn:country_code":"MX",
    "gn:dem":2283,
    "gn:feature_class":"P",
    "gn:feature_code":"PPL",
    "gn:name":"Uni\u00f3n y Progreso",
    "gn:population":186,
    "gn:timezone":"America/Mexico_City",
    "iso:country":"MX",
    "name:und_x_variant":[
        "Uni\u00f3n y Progreso"
    ],
    "wof:name":"Union y Progreso",
    "wof:placetype":"locality",
    "wof:population":186
},
  "geometry": {"coordinates":[-97.59028000000001,17.26639],"type":"Point"}
}