{
  "type": "Feature",
  "properties": {
    "gn:admin1_code":"26",
    "gn:admin2_code":"26.0",
    "gn:asciiname":"Bacobampo",
    "gn:country_code":"MX",
    "gn:dem":22,
    "gn:feature_class":"P",
    "gn:feature_code":"PPL",
    "gn:name":"Bacobampo",
    "gn:population":8539,
    "gn:timezone":"America/Hermosillo",
    "iso:country":"MX",
    "name:spa_x_preferred":[
        "Bacobampo"
    ],
    "wof:name":"Bacobampo",
    "wof:placetype":"locality",
    "wof:population":8539
},
  "geometry": {"coordinates":[-109.65194,26.98278],"type":"Point"}
}