{
  "type": "Feature",
  "properties": {
    "gn:admin1_code":"23",
    "gn:admin2_code":"6.0",
    "gn:asciiname":"Jose Maria Morelos",
    "gn:country_code":"MX",
    "gn:dem":23,
    "gn:feature_class":"P",
    "gn:feature_code":"PPLA2",
    "gn:name":"Jos\u00e9 Mar\u00eda Morelos",
    "gn:population":0,
    "gn:timezone":"America/Cancun",
    "iso:country":"MX",
    "name:und_x_variant":[
        "Jos\u00e9 Mar\u00eda Morelos"
    ],
    "wof:name":"Jose Maria Morelos",
    "wof:placetype":"locality"
},
  "geometry": {"coordinates":[-88.70865999999999,19.74887],"type":"Point"}
}