{
  "type": "Feature",
  "properties": {
    "gn:admin1_code":"15",
    "gn:admin2_code":"117.0",
    "gn:asciiname":"Valle Encantado",
    "gn:country_code":"MX",
    "gn:dem":2240,
    "gn:feature_class":"P",
    "gn:feature_code":"PPL",
    "gn:name":"Valle Encantado",
    "gn:population":114,
    "gn:timezone":"America/Mexico_City",
    "iso:country":"MX",
    "wof:name":"Valle Encantado",
    "wof:placetype":"locality",
    "wof:population":114
},
  "geometry": {"coordinates":[-99.85611,18.79333],"type":"Point"}
}