{
  "type": "Feature",
  "properties": {
    "gn:admin1_code":"30",
    "gn:admin2_code":"173.0",
    "gn:asciiname":"Nicoxcotla",
    "gn:country_code":"MX",
    "gn:dem":847,
    "gn:feature_class":"P",
    "gn:feature_code":"PPL",
    "gn:name":"Nicoxcotla",
    "gn:population":168,
    "gn:timezone":"America/Mexico_City",
    "iso:country":"MX",
    "wof:name":"Nicoxcotla",
    "wof:placetype":"locality",
    "wof:population":168
},
  "geometry": {"coordinates":[-96.82194,18.70361],"type":"Point"}
}