{
  "type": "Feature",
  "properties": {
    "gn:admin1_code":"25",
    "gn:admin2_code":"18.0",
    "gn:asciiname":"La Bomba",
    "gn:country_code":"MX",
    "gn:dem":15,
    "gn:feature_class":"P",
    "gn:feature_code":"PPL",
    "gn:name":"La Bomba",
    "gn:population":5,
    "gn:timezone":"America/Mazatlan",
    "iso:country":"MX",
    "name:ceb_x_preferred":[
        "La Bomba"
    ],
    "name:ita_x_preferred":[
        "La bomba"
    ],
    "name:spa_x_preferred":[
        "La bomba"
    ],
    "name:srp_x_preferred":[
        "\u041b\u0430 \u0411\u043e\u043c\u0431\u0430"
    ],
    "name:swe_x_preferred":[
        "La Bomba"
    ],
    "wof:name":"La Bomba",
    "wof:placetype":"locality",
    "wof:population":5
},
  "geometry": {"coordinates":[-107.65696,24.80829],"type":"Point"}
}