{
  "type": "Feature",
  "properties": {
    "gn:admin1_code":"6",
    "gn:admin2_code":"43.0",
    "gn:asciiname":"Los Escuderos",
    "gn:country_code":"MX",
    "gn:dem":1912,
    "gn:feature_class":"P",
    "gn:feature_code":"PPL",
    "gn:name":"Los Escuderos",
    "gn:population":0,
    "gn:timezone":"America/Chihuahua",
    "iso:country":"MX",
    "name:spa_x_preferred":[
        "Los Escuderos"
    ],
    "wof:name":"Los Escuderos",
    "wof:placetype":"locality"
},
  "geometry": {"coordinates":[-107.76199,28.86962],"type":"Point"}
}