{
  "type": "Feature",
  "properties": {
    "gn:admin1_code":"15",
    "gn:admin2_code":"4.0",
    "gn:asciiname":"Aquiapan",
    "gn:country_code":"MX",
    "gn:dem":1975,
    "gn:feature_class":"P",
    "gn:feature_code":"PPL",
    "gn:name":"Aquiapan",
    "gn:population":0,
    "gn:timezone":"America/Mexico_City",
    "iso:country":"MX",
    "name:spa_x_preferred":[
        "Aquiapan"
    ],
    "wof:name":"Aquiapan",
    "wof:placetype":"locality"
},
  "geometry": {"coordinates":[-99.85214000000001,18.74006],"type":"Point"}
}