{
  "type": "Feature",
  "properties": {
    "gn:admin1_code":"26.0",
    "gn:admin2_code":"68.0",
    "gn:asciiname":"Cuervito",
    "gn:cc2":"MX",
    "gn:country_code":"MX",
    "gn:dem":715,
    "gn:feature_class":"P",
    "gn:feature_code":"PPL",
    "gn:name":"Cuervito",
    "gn:population":0,
    "gn:timezone":"America/Hermosillo",
    "iso:country":"MX",
    "name:und_x_variant":[
        "Rancho Cuervito",
        "Cuevitos",
        "Cuervito"
    ],
    "wof:name":"Cuervito",
    "wof:placetype":"locality"
},
  "geometry": {"coordinates":[-109.98333,29.06667],"type":"Point"}
}