{
  "type": "Feature",
  "properties": {
    "gn:admin1_code":"14.0",
    "gn:admin2_code":"76.0",
    "gn:asciiname":"Carrizalillo",
    "gn:country_code":"MX",
    "gn:dem":2294,
    "gn:feature_class":"P",
    "gn:feature_code":"PPL",
    "gn:name":"Carrizalillo",
    "gn:population":0,
    "gn:timezone":"America/Mexico_City",
    "iso:country":"MX",
    "name:spa_x_preferred":[
        "Carrizalillo"
    ],
    "wof:name":"Carrizalillo",
    "wof:placetype":"locality"
},
  "geometry": {"coordinates":[-103.69190999999999,21.45948],"type":"Point"}
}