{
  "type": "Feature",
  "properties": {
    "gn:admin1_code":"10",
    "gn:admin2_code":"16.0",
    "gn:asciiname":"Jalisco Uno",
    "gn:country_code":"MX",
    "gn:dem":1880,
    "gn:feature_class":"P",
    "gn:feature_code":"PPL",
    "gn:name":"Jalisco Uno",
    "gn:population":0,
    "gn:timezone":"America/Monterrey",
    "iso:country":"MX",
    "name:spa_x_preferred":[
        "Jalisco Uno"
    ],
    "wof:name":"Jalisco Uno",
    "wof:placetype":"locality"
},
  "geometry": {"coordinates":[-104.07311,23.80355],"type":"Point"}
}