{
  "type": "Feature",
  "properties": {
    "gn:admin1_code":"27",
    "gn:admin2_code":"10.0",
    "gn:asciiname":"Hermenegildo Galeana 2da. Seccion",
    "gn:country_code":"MX",
    "gn:dem":14,
    "gn:feature_class":"P",
    "gn:feature_code":"PPL",
    "gn:name":"Hermenegildo Galeana 2da. Secci\u00f3n",
    "gn:population":1881,
    "gn:timezone":"America/Mexico_City",
    "iso:country":"MX",
    "name:und_x_variant":[
        "Hermenegildo Galeana 2da. Secci\u00f3n"
    ],
    "wof:name":"Hermenegildo Galeana 2da. Seccion",
    "wof:placetype":"locality",
    "wof:population":1881
},
  "geometry": {"coordinates":[-93.13508,18.17054],"type":"Point"}
}