{
  "type": "Feature",
  "properties": {
    "gn:admin1_code":"30",
    "gn:admin2_code":"192.0",
    "gn:asciiname":"Arroyo Grande Segundo",
    "gn:country_code":"MX",
    "gn:dem":242,
    "gn:feature_class":"P",
    "gn:feature_code":"PPL",
    "gn:name":"Arroyo Grande Segundo",
    "gn:population":0,
    "gn:timezone":"America/Mexico_City",
    "iso:country":"MX",
    "name:und_x_variant":[
        "Arroyo Grande"
    ],
    "wof:name":"Arroyo Grande Segundo",
    "wof:placetype":"locality"
},
  "geometry": {"coordinates":[-96.73112,20.00001],"type":"Point"}
}