{
  "type": "Feature",
  "properties": {
    "gn:admin1_code":"14",
    "gn:admin2_code":"18.0",
    "gn:asciiname":"San Jose de las Moras",
    "gn:country_code":"MX",
    "gn:dem":1552,
    "gn:feature_class":"P",
    "gn:feature_code":"PPL",
    "gn:name":"San Jos\u00e9 de las Moras",
    "gn:population":0,
    "gn:timezone":"America/Mexico_City",
    "iso:country":"MX",
    "name:und_x_variant":[
        "Moras",
        "San Jos\u00e9 de las Moras"
    ],
    "wof:name":"San Jose de las Moras",
    "wof:placetype":"locality"
},
  "geometry": {"coordinates":[-102.59254,20.32622000000001],"type":"Point"}
}