{
  "type": "Feature",
  "properties": {
    "gn:admin1_code":"6.0",
    "gn:admin2_code":"57.0",
    "gn:asciiname":"El Ojito",
    "gn:country_code":"MX",
    "gn:dem":1754,
    "gn:feature_class":"P",
    "gn:feature_code":"PPL",
    "gn:name":"El Ojito",
    "gn:population":0,
    "gn:timezone":"America/Chihuahua",
    "iso:country":"MX",
    "name:spa_x_preferred":[
        "El Ojito"
    ],
    "wof:name":"El Ojito",
    "wof:placetype":"locality"
},
  "geometry": {"coordinates":[-106.62402,27.71486],"type":"Point"}
}