{
  "type": "Feature",
  "properties": {
    "gn:admin1_code":"6",
    "gn:admin2_code":"20.0",
    "gn:asciiname":"El Veranito",
    "gn:country_code":"MX",
    "gn:dem":438,
    "gn:feature_class":"P",
    "gn:feature_code":"PPL",
    "gn:name":"El Veranito",
    "gn:population":0,
    "gn:timezone":"America/Chihuahua",
    "iso:country":"MX",
    "name:spa_x_preferred":[
        "El Veranito"
    ],
    "wof:name":"El Veranito",
    "wof:placetype":"locality"
},
  "geometry": {"coordinates":[-108.48821,27.30901],"type":"Point"}
}