{
  "type": "Feature",
  "properties": {
    "gn:admin1_code":"10",
    "gn:admin2_code":"4.0",
    "gn:asciiname":"El Moquete",
    "gn:country_code":"MX",
    "gn:dem":2061,
    "gn:feature_class":"P",
    "gn:feature_code":"PPL",
    "gn:name":"El Moquete",
    "gn:population":0,
    "gn:timezone":"America/Monterrey",
    "iso:country":"MX",
    "name:spa_x_preferred":[
        "El Moquete"
    ],
    "wof:name":"El Moquete",
    "wof:placetype":"locality"
},
  "geometry": {"coordinates":[-103.78829,24.62851],"type":"Point"}
}