{
  "type": "Feature",
  "properties": {
    "gn:admin1_code":"10.0",
    "gn:admin2_code":"32.0",
    "gn:asciiname":"Hervideros",
    "gn:cc2":"MX",
    "gn:country_code":"MX",
    "gn:dem":1693,
    "gn:feature_class":"P",
    "gn:feature_code":"PPL",
    "gn:name":"Hervideros",
    "gn:population":5,
    "gn:timezone":"America/Monterrey",
    "iso:country":"MX",
    "name:und_x_variant":[
        "Campo de Restablecimiento Nervideros",
        "Hervidero",
        "Hervideros"
    ],
    "wof:name":"Hervideros",
    "wof:placetype":"locality",
    "wof:population":5
},
  "geometry": {"coordinates":[-105.47313,25.15443],"type":"Point"}
}