{
  "type": "Feature",
  "properties": {
    "gn:admin1_code":"11.0",
    "gn:admin2_code":"33.0",
    "gn:asciiname":"Arroyo Colorado",
    "gn:country_code":"MX",
    "gn:dem":1288,
    "gn:feature_class":"P",
    "gn:feature_code":"PPL",
    "gn:name":"Arroyo Colorado",
    "gn:population":0,
    "gn:timezone":"America/Mexico_City",
    "iso:country":"MX",
    "name:ceb_x_preferred":[
        "Arroyo Colorado"
    ],
    "name:spa_x_preferred":[
        "Arroyo Colorado"
    ],
    "wof:name":"Arroyo Colorado",
    "wof:placetype":"locality"
},
  "geometry": {"coordinates":[-100.2289,21.56776],"type":"Point"}
}