{
  "type": "Feature",
  "properties": {
    "gn:admin1_code":"32",
    "gn:admin2_code":"10.0",
    "gn:asciiname":"Rancho Nuevo (Carmelo Monreal Villalobos)",
    "gn:country_code":"MX",
    "gn:dem":2217,
    "gn:feature_class":"P",
    "gn:feature_code":"PPL",
    "gn:name":"Rancho Nuevo (Carmelo Monreal Villalobos)",
    "gn:population":7,
    "gn:timezone":"America/Mexico_City",
    "iso:country":"MX",
    "wof:name":"Rancho Nuevo (Carmelo Monreal Villalobos)",
    "wof:placetype":"locality",
    "wof:population":7
},
  "geometry": {"coordinates":[-103.29806000000001,23.38583],"type":"Point"}
}