{
  "type": "Feature",
  "properties": {
    "gn:admin1_code":"16",
    "gn:admin2_code":"10.0",
    "gn:asciiname":"California",
    "gn:country_code":"MX",
    "gn:dem":1422,
    "gn:feature_class":"P",
    "gn:feature_code":"PPL",
    "gn:name":"California",
    "gn:population":8,
    "gn:timezone":"America/Mexico_City",
    "iso:country":"MX",
    "wof:name":"California",
    "wof:placetype":"locality",
    "wof:population":8
},
  "geometry": {"coordinates":[-102.55806,18.32444],"type":"Point"}
}