{
  "type": "Feature",
  "properties": {
    "gn:admin1_code":"19.0",
    "gn:admin2_code":"50.0",
    "gn:asciiname":"Potrero de Brondo",
    "gn:country_code":"MX",
    "gn:dem":231,
    "gn:feature_class":"P",
    "gn:feature_code":"PPL",
    "gn:name":"Potrero de Brondo",
    "gn:population":0,
    "gn:timezone":"America/Monterrey",
    "iso:country":"MX",
    "name:spa_x_preferred":[
        "Potrero de Brondo"
    ],
    "wof:name":"Potrero de Brondo",
    "wof:placetype":"locality"
},
  "geometry": {"coordinates":[-99.9238,26.44389],"type":"Point"}
}