{
  "type": "Feature",
  "properties": {
    "gn:admin1_code":"22",
    "gn:admin2_code":"8.0",
    "gn:asciiname":"El Garrunal (San Felipe de Jesus)",
    "gn:country_code":"MX",
    "gn:dem":2005,
    "gn:feature_class":"P",
    "gn:feature_code":"PPL",
    "gn:name":"El Garru\u00f1al (San Felipe de Jes\u00fas)",
    "gn:population":203,
    "gn:timezone":"America/Mexico_City",
    "iso:country":"MX",
    "name:und_x_variant":[
        "El Garru\u00f1al (San Felipe de Jes\u00fas)"
    ],
    "wof:name":"El Garrunal (San Felipe de Jesus)",
    "wof:placetype":"locality",
    "wof:population":203
},
  "geometry": {"coordinates":[-100.34213,20.47445],"type":"Point"}
}