{
  "type": "Feature",
  "properties": {
    "gn:admin1_code":"1",
    "gn:admin2_code":"7",
    "gn:asciiname":"El Mezquite (Jose Carlos) [Rancho]",
    "gn:country_code":"MX",
    "gn:dem":1932,
    "gn:feature_class":"P",
    "gn:feature_code":"PPL",
    "gn:name":"El Mezquite (Jos\u00e9 Carlos) [Rancho]",
    "gn:population":9,
    "gn:timezone":"America/Mexico_City",
    "iso:country":"MX",
    "name:und_x_variant":[
        "El Mezquite (Jos\u00e9 Carlos) [Rancho]"
    ],
    "wof:name":"El Mezquite (Jose Carlos) [Rancho]",
    "wof:placetype":"locality",
    "wof:population":9
},
  "geometry": {"coordinates":[-102.34166999999999,22.15583],"type":"Point"}
}