{
  "type": "Feature",
  "properties": {
    "gn:admin1_code":"3.0",
    "gn:admin2_code":"2.0",
    "gn:asciiname":"Guadalupe de los Reyes",
    "gn:country_code":"MX",
    "gn:dem":38,
    "gn:feature_class":"P",
    "gn:feature_code":"PPL",
    "gn:name":"Guadalupe de los Reyes",
    "gn:population":0,
    "gn:timezone":"America/Mazatlan",
    "iso:country":"MX",
    "wof:name":"Guadalupe de los Reyes",
    "wof:placetype":"locality"
},
  "geometry": {"coordinates":[-113.34125,27.31863],"type":"Point"}
}