{
  "type": "Feature",
  "properties": {
    "gn:admin1_code":"6.0",
    "gn:admin2_code":"15.0",
    "gn:asciiname":"La Cantera",
    "gn:country_code":"MX",
    "gn:dem":1026,
    "gn:feature_class":"P",
    "gn:feature_code":"PPL",
    "gn:name":"La Cantera",
    "gn:population":0,
    "gn:timezone":"America/Chihuahua",
    "iso:country":"MX",
    "name:und_x_variant":[
        "Rancho La Cantera",
        "La Cantera"
    ],
    "wof:name":"La Cantera",
    "wof:placetype":"locality"
},
  "geometry": {"coordinates":[-104.95343,29.20762],"type":"Point"}
}