{
  "type": "Feature",
  "properties": {
    "gn:admin1_code":"8.0",
    "gn:admin2_code":"7.0",
    "gn:asciiname":"Las Humedades",
    "gn:country_code":"MX",
    "gn:dem":36,
    "gn:feature_class":"P",
    "gn:feature_code":"PPL",
    "gn:name":"Las Humedades",
    "gn:population":0,
    "gn:timezone":"America/Mexico_City",
    "iso:country":"MX",
    "name:spa_x_preferred":[
        "Las Humedades"
    ],
    "wof:name":"Las Humedades",
    "wof:placetype":"locality"
},
  "geometry": {"coordinates":[-104.29852,19.14064],"type":"Point"}
}