{
  "type": "Feature",
  "properties": {
    "gn:admin1_code":"6",
    "gn:admin2_code":"27.0",
    "gn:asciiname":"Pichique",
    "gn:country_code":"MX",
    "gn:dem":2221,
    "gn:feature_class":"P",
    "gn:feature_code":"PPL",
    "gn:name":"Pichique",
    "gn:population":0,
    "gn:timezone":"America/Chihuahua",
    "iso:country":"MX",
    "name:spa_x_preferred":[
        "Pichique"
    ],
    "wof:name":"Pichique",
    "wof:placetype":"locality"
},
  "geometry": {"coordinates":[-107.03128,27.12809],"type":"Point"}
}