{
  "type": "Feature",
  "properties": {
    "gn:admin1_code":"6",
    "gn:admin2_code":"12.0",
    "gn:asciiname":"Nabor",
    "gn:country_code":"MX",
    "gn:dem":2049,
    "gn:feature_class":"P",
    "gn:feature_code":"PPL",
    "gn:name":"Nabor",
    "gn:population":0,
    "gn:timezone":"America/Chihuahua",
    "iso:country":"MX",
    "name:por_x_preferred":[
        "Nabor"
    ],
    "name:slv_x_preferred":[
        "Nabor"
    ],
    "name:spa_x_preferred":[
        "Nabor"
    ],
    "wof:name":"Nabor",
    "wof:placetype":"locality"
},
  "geometry": {"coordinates":[-107.17994,27.84317],"type":"Point"}
}