{
  "type": "Feature",
  "properties": {
    "gn:admin1_code":"30.0",
    "gn:admin2_code":"123.0",
    "gn:asciiname":"Vega Cercada",
    "gn:country_code":"MX",
    "gn:dem":11,
    "gn:feature_class":"P",
    "gn:feature_code":"PPL",
    "gn:name":"Vega Cercada",
    "gn:population":430,
    "gn:timezone":"America/Mexico_City",
    "iso:country":"MX",
    "name:spa_x_preferred":[
        "Vega Cercada"
    ],
    "wof:name":"Vega Cercada",
    "wof:placetype":"locality",
    "wof:population":430
},
  "geometry": {"coordinates":[-98.29667000000001,22.05417000000001],"type":"Point"}
}