{
  "type": "Feature",
  "properties": {
    "gn:admin1_code":"4.0",
    "gn:admin2_code":"3.0",
    "gn:asciiname":"El Pelicano",
    "gn:country_code":"MX",
    "gn:dem":1,
    "gn:feature_class":"P",
    "gn:feature_code":"PPL",
    "gn:name":"El Pel\u00edcano",
    "gn:population":0,
    "gn:timezone":"America/Merida",
    "iso:country":"MX",
    "name:spa_x_preferred":[
        "El Pel\u00edcano"
    ],
    "wof:name":"El Pelicano",
    "wof:placetype":"locality"
},
  "geometry": {"coordinates":[-91.8681,18.58985],"type":"Point"}
}