{
  "type": "Feature",
  "properties": {
    "gn:admin1_code":"26",
    "gn:admin2_code":"29.0",
    "gn:asciiname":"El Arenoso",
    "gn:country_code":"MX",
    "gn:dem":169,
    "gn:feature_class":"P",
    "gn:feature_code":"PPL",
    "gn:name":"El Arenoso",
    "gn:population":8,
    "gn:timezone":"America/Hermosillo",
    "iso:country":"MX",
    "wof:name":"El Arenoso",
    "wof:placetype":"locality",
    "wof:population":8
},
  "geometry": {"coordinates":[-110.55722,28.41944],"type":"Point"}
}