{
  "type": "Feature",
  "properties": {
    "gn:admin1_code":"30",
    "gn:admin2_code":"143",
    "gn:asciiname":"La Comision",
    "gn:country_code":"MX",
    "gn:dem":16,
    "gn:feature_class":"P",
    "gn:feature_code":"PPL",
    "gn:name":"La Comisi\u00f3n",
    "gn:population":13,
    "gn:timezone":"America/Mexico_City",
    "iso:country":"MX",
    "name:und_x_variant":[
        "La Comisi\u00f3n"
    ],
    "wof:name":"La Comision",
    "wof:placetype":"locality",
    "wof:population":13
},
  "geometry": {"coordinates":[-95.48166999999999,18.45778],"type":"Point"}
}