{
  "type": "Feature",
  "properties": {
    "gn:admin1_code":"18.0",
    "gn:admin2_code":"2.0",
    "gn:asciiname":"Los Chiltes",
    "gn:country_code":"MX",
    "gn:dem":747,
    "gn:feature_class":"P",
    "gn:feature_code":"PPL",
    "gn:name":"Los Chiltes",
    "gn:population":0,
    "gn:timezone":"America/Mazatlan",
    "iso:country":"MX",
    "name:spa_x_preferred":[
        "Los Chiltes"
    ],
    "wof:name":"Los Chiltes",
    "wof:placetype":"locality"
},
  "geometry": {"coordinates":[-104.66607,21.05844],"type":"Point"}
}