{
  "type": "Feature",
  "properties": {
    "gn:admin1_code":"6",
    "gn:admin2_code":"7",
    "gn:asciiname":"Arroyo de las Cuevas",
    "gn:country_code":"MX",
    "gn:dem":2493,
    "gn:feature_class":"P",
    "gn:feature_code":"PPL",
    "gn:name":"Arroyo de las Cuevas",
    "gn:population":20,
    "gn:timezone":"America/Chihuahua",
    "iso:country":"MX",
    "wof:name":"Arroyo de las Cuevas",
    "wof:placetype":"locality",
    "wof:population":20
},
  "geometry": {"coordinates":[-106.59748,26.56678],"type":"Point"}
}