{
  "type": "Feature",
  "properties": {
    "gn:admin1_code":"19",
    "gn:admin2_code":"38",
    "gn:asciiname":"Denes",
    "gn:country_code":"MX",
    "gn:dem":494,
    "gn:feature_class":"P",
    "gn:feature_code":"PPL",
    "gn:name":"Denes",
    "gn:population":20,
    "gn:timezone":"America/Monterrey",
    "iso:country":"MX",
    "wof:name":"Denes",
    "wof:placetype":"locality",
    "wof:population":20
},
  "geometry": {"coordinates":[-99.74554999999999,25.01118],"type":"Point"}
}