{
  "type": "Feature",
  "properties": {
    "gn:admin1_code":"13.0",
    "gn:admin2_code":"27.0",
    "gn:asciiname":"El Denxe",
    "gn:country_code":"MX",
    "gn:dem":738,
    "gn:feature_class":"P",
    "gn:feature_code":"PPL",
    "gn:name":"El Denxe",
    "gn:population":45,
    "gn:timezone":"America/Mexico_City",
    "iso:country":"MX",
    "name:spa_x_preferred":[
        "El Denxe"
    ],
    "wof:name":"El Denxe",
    "wof:placetype":"locality",
    "wof:population":45
},
  "geometry": {"coordinates":[-98.05401999999999,20.5373],"type":"Point"}
}