{
  "type": "Feature",
  "properties": {
    "gn:admin1_code":"30",
    "gn:admin2_code":"144.0",
    "gn:asciiname":"Monte Obscuro",
    "gn:country_code":"MX",
    "gn:dem":41,
    "gn:feature_class":"P",
    "gn:feature_code":"PPL",
    "gn:name":"Monte Obscuro",
    "gn:population":0,
    "gn:timezone":"America/Mexico_City",
    "iso:country":"MX",
    "wof:name":"Monte Obscuro",
    "wof:placetype":"locality"
},
  "geometry": {"coordinates":[-94.90000000000001,17.63332999999999],"type":"Point"}
}