{
  "type": "Feature",
  "properties": {
    "gn:admin1_code":"12",
    "gn:admin2_code":"31.0",
    "gn:asciiname":"Pata de Venado",
    "gn:country_code":"MX",
    "gn:dem":1176,
    "gn:feature_class":"P",
    "gn:feature_code":"PPL",
    "gn:name":"Pata de Venado",
    "gn:population":91,
    "gn:timezone":"America/Mexico_City",
    "iso:country":"MX",
    "wof:name":"Pata de Venado",
    "wof:placetype":"locality",
    "wof:population":91
},
  "geometry": {"coordinates":[-100.13276999999999,18.4357],"type":"Point"}
}