{
  "type": "Feature",
  "properties": {
    "gn:admin1_code":"30.0",
    "gn:admin2_code":"161.0",
    "gn:asciiname":"El Jardin",
    "gn:country_code":"MX",
    "gn:dem":43,
    "gn:feature_class":"P",
    "gn:feature_code":"PPL",
    "gn:name":"El Jard\u00edn",
    "gn:population":10,
    "gn:timezone":"America/Mexico_City",
    "iso:country":"MX",
    "name:spa_x_preferred":[
        "El Jard\u00edn"
    ],
    "wof:name":"El Jardin",
    "wof:placetype":"locality",
    "wof:population":10
},
  "geometry": {"coordinates":[-98.36221999999999,21.62417],"type":"Point"}
}