{
  "type": "Feature",
  "properties": {
    "gn:admin1_code":"15",
    "gn:admin2_code":"117.0",
    "gn:asciiname":"Puerto Oscuro",
    "gn:country_code":"MX",
    "gn:dem":2339,
    "gn:feature_class":"P",
    "gn:feature_code":"PPL",
    "gn:name":"Puerto Oscuro",
    "gn:population":0,
    "gn:timezone":"America/Mexico_City",
    "iso:country":"MX",
    "wof:name":"Puerto Oscuro",
    "wof:placetype":"locality"
},
  "geometry": {"coordinates":[-99.79167,18.66667],"type":"Point"}
}