{
  "type": "Feature",
  "properties": {
    "gn:admin1_code":"32.0",
    "gn:asciiname":"El Colorado",
    "gn:country_code":"MX",
    "gn:dem":2324,
    "gn:feature_class":"P",
    "gn:feature_code":"PPL",
    "gn:name":"El Colorado",
    "gn:population":0,
    "gn:timezone":"America/Mexico_City",
    "iso:country":"MX",
    "name:spa_x_preferred":[
        "El Colorado"
    ],
    "wof:name":"El Colorado",
    "wof:placetype":"locality"
},
  "geometry": {"coordinates":[-101.61384,22.26208],"type":"Point"}
}