{
  "type": "Feature",
  "properties": {
    "gn:admin1_code":"2.0",
    "gn:admin2_code":"1.0",
    "gn:asciiname":"La Chuparrosa",
    "gn:country_code":"MX",
    "gn:dem":132,
    "gn:feature_class":"P",
    "gn:feature_code":"PPL",
    "gn:name":"La Chuparrosa",
    "gn:population":8,
    "gn:timezone":"America/Tijuana",
    "iso:country":"MX",
    "name:spa_x_preferred":[
        "La Chuparrosa"
    ],
    "wof:name":"La Chuparrosa",
    "wof:placetype":"locality",
    "wof:population":8
},
  "geometry": {"coordinates":[-116.20999999999999,31.34361],"type":"Point"}
}