{
  "type": "Feature",
  "properties": {
    "gn:admin1_code":"6",
    "gn:admin2_code":"12.0",
    "gn:asciiname":"Ejido San Isidro",
    "gn:country_code":"MX",
    "gn:dem":2040,
    "gn:feature_class":"P",
    "gn:feature_code":"PPL",
    "gn:name":"Ejido San Isidro",
    "gn:population":0,
    "gn:timezone":"America/Chihuahua",
    "iso:country":"MX",
    "name:spa_x_preferred":[
        "Ejido San Isidro"
    ],
    "name:und_x_variant":[
        "San Isidro"
    ],
    "wof:name":"Ejido San Isidro",
    "wof:placetype":"locality"
},
  "geometry": {"coordinates":[-107.11920000000001,27.93052],"type":"Point"}
}