{
  "type": "Feature",
  "properties": {
    "gn:admin1_code":"14.0",
    "gn:admin2_code":"6.0",
    "gn:asciiname":"Arroyo Grande",
    "gn:country_code":"MX",
    "gn:dem":1324,
    "gn:feature_class":"P",
    "gn:feature_code":"PPL",
    "gn:name":"Arroyo Grande",
    "gn:population":0,
    "gn:timezone":"America/Mexico_City",
    "iso:country":"MX",
    "name:spa_x_preferred":[
        "Arroyo Grande"
    ],
    "wof:name":"Arroyo Grande",
    "wof:placetype":"locality"
},
  "geometry": {"coordinates":[-104.12766000000001,20.51213],"type":"Point"}
}