{
  "type": "Feature",
  "properties": {
    "gn:admin1_code":"28",
    "gn:admin2_code":"35.0",
    "gn:asciiname":"Lavaderos",
    "gn:country_code":"MX",
    "gn:dem":20,
    "gn:feature_class":"P",
    "gn:feature_code":"PPL",
    "gn:name":"Lavaderos",
    "gn:population":0,
    "gn:timezone":"America/Monterrey",
    "iso:country":"MX",
    "name:und_x_variant":[
        "Ejido Lavaderos",
        "Lavaderos"
    ],
    "wof:name":"Lavaderos",
    "wof:placetype":"locality"
},
  "geometry": {"coordinates":[-97.904,24.47458],"type":"Point"}
}