{
  "type": "Feature",
  "properties": {
    "gn:admin1_code":"2.0",
    "gn:admin2_code":"1.0",
    "gn:asciiname":"Carrizo",
    "gn:cc2":"MX",
    "gn:country_code":"MX",
    "gn:dem":697,
    "gn:feature_class":"P",
    "gn:feature_code":"PPL",
    "gn:name":"Carrizo",
    "gn:population":0,
    "gn:timezone":"America/Tijuana",
    "iso:country":"MX",
    "name:und_x_variant":[
        "Carriso",
        "Carrizo"
    ],
    "wof:name":"Carrizo",
    "wof:placetype":"locality"
},
  "geometry": {"coordinates":[-114.98333,30.58333],"type":"Point"}
}