{
  "type": "Feature",
  "properties": {
    "gn:admin1_code":"11",
    "gn:admin2_code":"45.0",
    "gn:asciiname":"Mezquital",
    "gn:country_code":"MX",
    "gn:dem":1314,
    "gn:feature_class":"P",
    "gn:feature_code":"PPL",
    "gn:name":"Mezquital",
    "gn:population":71,
    "gn:timezone":"America/Mexico_City",
    "iso:country":"MX",
    "wof:name":"Mezquital",
    "wof:placetype":"locality",
    "wof:population":71
},
  "geometry": {"coordinates":[-100.09444000000001,21.37556],"type":"Point"}
}