{
  "type": "Feature",
  "properties": {
    "gn:admin1_code":"30",
    "gn:admin2_code":"53",
    "gn:asciiname":"La Represa",
    "gn:country_code":"MX",
    "gn:dem":363,
    "gn:feature_class":"P",
    "gn:feature_code":"PPL",
    "gn:name":"La Represa",
    "gn:population":10,
    "gn:timezone":"America/Mexico_City",
    "iso:country":"MX",
    "name:ita_x_preferred":[
        "La Represa"
    ],
    "name:spa_x_preferred":[
        "La Represa"
    ],
    "name:zho_x_preferred":[
        "\u62c9\u96f7\u666e\u96f7\u85a9"
    ],
    "wof:name":"La Represa",
    "wof:placetype":"locality",
    "wof:population":10
},
  "geometry": {"coordinates":[-96.73305999999999,18.78917],"type":"Point"}
}