{
  "type": "Feature",
  "properties": {
    "gn:admin1_code":"14",
    "gn:admin2_code":"78",
    "gn:asciiname":"Pandillo",
    "gn:country_code":"MX",
    "gn:dem":1861,
    "gn:feature_class":"P",
    "gn:feature_code":"PPL",
    "gn:name":"Pandillo",
    "gn:population":13,
    "gn:timezone":"America/Mexico_City",
    "iso:country":"MX",
    "wof:name":"Pandillo",
    "wof:placetype":"locality",
    "wof:population":13
},
  "geometry": {"coordinates":[-102.41943999999999,21.03389],"type":"Point"}
}