{
  "type": "Feature",
  "properties": {
    "gn:admin1_code":"19",
    "gn:admin2_code":"33.0",
    "gn:asciiname":"La Purisima",
    "gn:country_code":"MX",
    "gn:dem":220,
    "gn:feature_class":"P",
    "gn:feature_code":"PPL",
    "gn:name":"La Pur\u00edsima",
    "gn:population":6,
    "gn:timezone":"America/Monterrey",
    "iso:country":"MX",
    "name:und_x_variant":[
        "La Pur\u00edsima"
    ],
    "wof:name":"La Purisima",
    "wof:placetype":"locality",
    "wof:population":6
},
  "geometry": {"coordinates":[-99.26278000000001,24.92278],"type":"Point"}
}