{
  "type": "Feature",
  "properties": {
    "gn:admin1_code":"32",
    "gn:admin2_code":"41.0",
    "gn:asciiname":"Calabacillas (Las Escobillas)",
    "gn:country_code":"MX",
    "gn:dem":1986,
    "gn:feature_class":"P",
    "gn:feature_code":"PPL",
    "gn:name":"Calabacillas (Las Escobillas)",
    "gn:population":7,
    "gn:timezone":"America/Mexico_City",
    "iso:country":"MX",
    "wof:name":"Calabacillas (Las Escobillas)",
    "wof:placetype":"locality",
    "wof:population":7
},
  "geometry": {"coordinates":[-100.94777999999999,24.42333],"type":"Point"}
}