{
  "type": "Feature",
  "properties": {
    "gn:admin1_code":"10",
    "gn:admin2_code":"35.0",
    "gn:asciiname":"Cruz de Piedra",
    "gn:country_code":"MX",
    "gn:dem":2176,
    "gn:feature_class":"P",
    "gn:feature_code":"PPL",
    "gn:name":"Cruz de Piedra",
    "gn:population":4,
    "gn:timezone":"America/Monterrey",
    "iso:country":"MX",
    "wof:name":"Cruz de Piedra",
    "wof:placetype":"locality",
    "wof:population":4
},
  "geometry": {"coordinates":[-106.16358,25.58011],"type":"Point"}
}