{
  "type": "Feature",
  "properties": {
    "gn:admin1_code":"26.0",
    "gn:admin2_code":"47.0",
    "gn:asciiname":"Mi Ranchito",
    "gn:country_code":"MX",
    "gn:dem":119,
    "gn:feature_class":"P",
    "gn:feature_code":"PPL",
    "gn:name":"Mi Ranchito",
    "gn:population":0,
    "gn:timezone":"America/Hermosillo",
    "iso:country":"MX",
    "name:spa_x_preferred":[
        "Mi Ranchito"
    ],
    "wof:name":"Mi Ranchito",
    "wof:placetype":"locality"
},
  "geometry": {"coordinates":[-112.34902,29.66802],"type":"Point"}
}