{
  "type": "Feature",
  "properties": {
    "gn:admin1_code":"10",
    "gn:admin2_code":"32.0",
    "gn:asciiname":"Madrono (El Madrono)",
    "gn:country_code":"MX",
    "gn:dem":1905,
    "gn:feature_class":"P",
    "gn:feature_code":"PPL",
    "gn:name":"Madro\u00f1o (El Madro\u00f1o)",
    "gn:population":54,
    "gn:timezone":"America/Monterrey",
    "iso:country":"MX",
    "name:und_x_variant":[
        "Madro\u00f1o (El Madro\u00f1o)"
    ],
    "wof:name":"Madrono (El Madrono)",
    "wof:placetype":"locality",
    "wof:population":54
},
  "geometry": {"coordinates":[-106.35508,25.00748],"type":"Point"}
}