{
  "type": "Feature",
  "properties": {
    "gn:admin1_code":"14",
    "gn:admin2_code":"27.0",
    "gn:asciiname":"Las Guasimas (Las Guasimitas)",
    "gn:country_code":"MX",
    "gn:dem":804,
    "gn:feature_class":"P",
    "gn:feature_code":"PPL",
    "gn:name":"Las Gu\u00e1simas (Las Guasimitas)",
    "gn:population":8,
    "gn:timezone":"America/Mexico_City",
    "iso:country":"MX",
    "name:und_x_variant":[
        "Las Gu\u00e1simas (Las Guasimitas)"
    ],
    "wof:name":"Las Guasimas (Las Guasimitas)",
    "wof:placetype":"locality",
    "wof:population":8
},
  "geometry": {"coordinates":[-104.38167,19.36972],"type":"Point"}
}