{
  "type": "Feature",
  "properties": {
    "gn:admin1_code":"7",
    "gn:admin2_code":"20.0",
    "gn:asciiname":"Rancho El Infante",
    "gn:country_code":"MX",
    "gn:dem":986,
    "gn:feature_class":"P",
    "gn:feature_code":"PPL",
    "gn:name":"Rancho El Infante",
    "gn:population":0,
    "gn:timezone":"America/Monterrey",
    "iso:country":"MX",
    "wof:name":"Rancho El Infante",
    "wof:placetype":"locality"
},
  "geometry": {"coordinates":[-101.95,28.76667],"type":"Point"}
}