{
  "type": "Feature",
  "properties": {
    "gn:admin1_code":"11",
    "gn:admin2_code":"19.0",
    "gn:asciiname":"Puroagueita",
    "gn:country_code":"MX",
    "gn:dem":1955,
    "gn:feature_class":"P",
    "gn:feature_code":"PPL",
    "gn:name":"Puroag\u00fcita",
    "gn:population":0,
    "gn:timezone":"America/Mexico_City",
    "iso:country":"MX",
    "name:spa_x_preferred":[
        "Puroag\u00fcita"
    ],
    "name:spa_x_variant":[
        "Puruaguita"
    ],
    "wof:name":"Puroagueita",
    "wof:placetype":"locality"
},
  "geometry": {"coordinates":[-100.4731,20.06409],"type":"Point"}
}