{
  "type": "Feature",
  "properties": {
    "gn:admin1_code":"12",
    "gn:admin2_code":"10.0",
    "gn:asciiname":"Petatlan",
    "gn:country_code":"MX",
    "gn:dem":1355,
    "gn:feature_class":"P",
    "gn:feature_code":"PPL",
    "gn:name":"Petatl\u00e1n",
    "gn:population":0,
    "gn:timezone":"America/Mexico_City",
    "iso:country":"MX",
    "name:spa_x_preferred":[
        "Petatl\u00e1n"
    ],
    "wof:name":"Petatlan",
    "wof:placetype":"locality"
},
  "geometry": {"coordinates":[-98.98969,17.5809],"type":"Point"}
}