{
  "type": "Feature",
  "properties": {
    "gn:admin1_code":"7.0",
    "gn:admin2_code":"27.0",
    "gn:asciiname":"Agua de Arriba",
    "gn:cc2":"MX",
    "gn:country_code":"MX",
    "gn:dem":1439,
    "gn:feature_class":"P",
    "gn:feature_code":"PPL",
    "gn:name":"Agua de Arriba",
    "gn:population":0,
    "gn:timezone":"America/Monterrey",
    "iso:country":"MX",
    "name:und_x_variant":[
        "Rancho Agua de Arriba",
        "Agua de Arriba"
    ],
    "wof:name":"Agua de Arriba",
    "wof:placetype":"locality"
},
  "geometry": {"coordinates":[-101.21666999999999,25.65],"type":"Point"}
}