{
  "type": "Feature",
  "properties": {
    "gn:admin1_code":"21",
    "gn:admin2_code":"76.0",
    "gn:asciiname":"Colonia del Valle",
    "gn:country_code":"MX",
    "gn:dem":499,
    "gn:feature_class":"P",
    "gn:feature_code":"PPL",
    "gn:name":"Colonia del Valle",
    "gn:population":125,
    "gn:timezone":"America/Mexico_City",
    "iso:country":"MX",
    "name:deu_x_preferred":[
        "Colonia del Valle"
    ],
    "name:fra_x_preferred":[
        "Colonia Del Valle"
    ],
    "wof:name":"Colonia del Valle",
    "wof:placetype":"locality",
    "wof:population":125
},
  "geometry": {"coordinates":[-97.35092,20.03318],"type":"Point"}
}