{
  "type": "Feature",
  "properties": {
    "gn:admin1_code":"9",
    "gn:admin2_code":"12",
    "gn:asciiname":"Los Encinos",
    "gn:country_code":"MX",
    "gn:dem":2606,
    "gn:feature_class":"P",
    "gn:feature_code":"PPL",
    "gn:name":"Los Encinos",
    "gn:population":49,
    "gn:timezone":"America/Mexico_City",
    "iso:country":"MX",
    "wof:name":"Los Encinos",
    "wof:placetype":"locality",
    "wof:population":49
},
  "geometry": {"coordinates":[-99.13068,19.19769],"type":"Point"}
}