{
  "type": "Feature",
  "properties": {
    "gn:admin1_code":"20",
    "gn:admin2_code":"523",
    "gn:asciiname":"Rio Grande",
    "gn:country_code":"MX",
    "gn:dem":2239,
    "gn:feature_class":"P",
    "gn:feature_code":"PPL",
    "gn:name":"R\u00edo Grande",
    "gn:population":49,
    "gn:timezone":"America/Mexico_City",
    "iso:country":"MX",
    "name:und_x_variant":[
        "R\u00edo Grande"
    ],
    "wof:name":"Rio Grande",
    "wof:placetype":"locality",
    "wof:population":49
},
  "geometry": {"coordinates":[-97.35805999999999,17.49611],"type":"Point"}
}