{
  "type": "Feature",
  "properties": {
    "gn:admin1_code":"5",
    "gn:admin2_code":"103.0",
    "gn:asciiname":"Segundo Canton",
    "gn:country_code":"MX",
    "gn:dem":36,
    "gn:feature_class":"P",
    "gn:feature_code":"PPL",
    "gn:name":"Segundo Cant\u00f3n",
    "gn:population":952,
    "gn:timezone":"America/Mexico_City",
    "iso:country":"MX",
    "name:und_x_variant":[
        "Segundo Cant\u00f3n"
    ],
    "wof:name":"Segundo Canton",
    "wof:placetype":"locality",
    "wof:population":952
},
  "geometry": {"coordinates":[-92.43528000000001,15.10056],"type":"Point"}
}