{
  "type": "Feature",
  "properties": {
    "gn:admin1_code":"11.0",
    "gn:admin2_code":"8.0",
    "gn:asciiname":"El Carrizo",
    "gn:country_code":"MX",
    "gn:dem":1761,
    "gn:feature_class":"P",
    "gn:feature_code":"PPL",
    "gn:name":"El Carrizo",
    "gn:population":0,
    "gn:timezone":"America/Mexico_City",
    "iso:country":"MX",
    "wof:name":"El Carrizo",
    "wof:placetype":"locality"
},
  "geometry": {"coordinates":[-101.81917,20.66417],"type":"Point"}
}