{
  "type": "Feature",
  "properties": {
    "gn:admin1_code":"12.0",
    "gn:admin2_code":"50.0",
    "gn:asciiname":"Chacamerito",
    "gn:country_code":"MX",
    "gn:dem":304,
    "gn:feature_class":"P",
    "gn:feature_code":"PPL",
    "gn:name":"Chacamerito",
    "gn:population":0,
    "gn:timezone":"America/Mexico_City",
    "iso:country":"MX",
    "name:spa_x_preferred":[
        "Chacamerito"
    ],
    "wof:name":"Chacamerito",
    "wof:placetype":"locality"
},
  "geometry": {"coordinates":[-100.5883,18.32209],"type":"Point"}
}