{
  "type": "Feature",
  "properties": {
    "gn:admin1_code":"14",
    "gn:admin2_code":"15.0",
    "gn:asciiname":"Las Tablas",
    "gn:country_code":"MX",
    "gn:dem":1798,
    "gn:feature_class":"P",
    "gn:feature_code":"PPL",
    "gn:name":"Las Tablas",
    "gn:population":0,
    "gn:timezone":"America/Mexico_City",
    "iso:country":"MX",
    "name:ceb_x_preferred":[
        "Las Tablas"
    ],
    "name:ita_x_preferred":[
        "Las Tablas"
    ],
    "name:spa_x_preferred":[
        "Las Tablas"
    ],
    "name:srp_x_preferred":[
        "\u041b\u0430\u0441 \u0422\u0430\u0431\u043b\u0430\u0441"
    ],
    "name:swe_x_preferred":[
        "Las Tablas"
    ],
    "wof:name":"Las Tablas",
    "wof:placetype":"locality"
},
  "geometry": {"coordinates":[-104.21666999999999,19.61667000000001],"type":"Point"}
}