{
  "type": "Feature",
  "properties": {
    "gn:admin1_code":"25.0",
    "gn:admin2_code":"17.0",
    "gn:asciiname":"El Gatal de Ocoroni",
    "gn:country_code":"MX",
    "gn:dem":88,
    "gn:feature_class":"P",
    "gn:feature_code":"PPL",
    "gn:name":"El Gatal de Ocoroni",
    "gn:population":416,
    "gn:timezone":"America/Mazatlan",
    "iso:country":"MX",
    "wof:name":"El Gatal de Ocoroni",
    "wof:placetype":"locality",
    "wof:population":416
},
  "geometry": {"coordinates":[-108.3853,25.96863],"type":"Point"}
}