{
  "type": "Feature",
  "properties": {
    "gn:admin1_code":"14.0",
    "gn:admin2_code":"87.0",
    "gn:asciiname":"El Pinal",
    "gn:country_code":"MX",
    "gn:dem":1321,
    "gn:feature_class":"P",
    "gn:feature_code":"PPL",
    "gn:name":"El Pinal",
    "gn:population":0,
    "gn:timezone":"America/Mexico_City",
    "iso:country":"MX",
    "name:spa_x_preferred":[
        "El Pinal"
    ],
    "wof:name":"El Pinal",
    "wof:placetype":"locality"
},
  "geometry": {"coordinates":[-103.11948,18.98758],"type":"Point"}
}