{
  "type": "Feature",
  "properties": {
    "gn:admin1_code":"2",
    "gn:admin2_code":"1",
    "gn:asciiname":"Parcela Numero Noventa y Cuatro (Rancho Jayme)",
    "gn:country_code":"MX",
    "gn:dem":13,
    "gn:feature_class":"P",
    "gn:feature_code":"PPL",
    "gn:name":"Parcela N\u00famero Noventa y Cuatro (Rancho Jayme)",
    "gn:population":10,
    "gn:timezone":"America/Tijuana",
    "iso:country":"MX",
    "name:und_x_variant":[
        "Parcela N\u00famero Noventa y Cuatro (Rancho Jayme)"
    ],
    "wof:name":"Parcela Numero Noventa y Cuatro (Rancho Jayme)",
    "wof:placetype":"locality",
    "wof:population":10
},
  "geometry": {"coordinates":[-116.58778,31.72611],"type":"Point"}
}