{
  "type": "Feature",
  "properties": {
    "gn:admin1_code":"16.0",
    "gn:admin2_code":"13.0",
    "gn:asciiname":"La Carrerita",
    "gn:country_code":"MX",
    "gn:dem":518,
    "gn:feature_class":"P",
    "gn:feature_code":"PPL",
    "gn:name":"La Carrerita",
    "gn:population":0,
    "gn:timezone":"America/Mexico_City",
    "iso:country":"MX",
    "name:spa_x_preferred":[
        "La Carrerita"
    ],
    "wof:name":"La Carrerita",
    "wof:placetype":"locality"
},
  "geometry": {"coordinates":[-100.88576999999999,18.99578],"type":"Point"}
}