{
  "type": "Feature",
  "properties": {
    "gn:admin1_code":"5",
    "gn:admin2_code":"108.0",
    "gn:asciiname":"El Llanon",
    "gn:country_code":"MX",
    "gn:dem":812,
    "gn:feature_class":"P",
    "gn:feature_code":"PPL",
    "gn:name":"El Llan\u00f3n",
    "gn:population":6,
    "gn:timezone":"America/Mexico_City",
    "iso:country":"MX",
    "name:und_x_variant":[
        "El Llan\u00f3n"
    ],
    "wof:name":"El Llanon",
    "wof:placetype":"locality",
    "wof:population":6
},
  "geometry": {"coordinates":[-93.10693999999999,16.48333],"type":"Point"}
}