{
  "type": "Feature",
  "properties": {
    "gn:admin1_code":"25",
    "gn:admin2_code":"8",
    "gn:asciiname":"Campo Cachanilla",
    "gn:country_code":"MX",
    "gn:dem":6,
    "gn:feature_class":"P",
    "gn:feature_code":"PPL",
    "gn:name":"Campo Cachanilla",
    "gn:population":10,
    "gn:timezone":"America/Mazatlan",
    "iso:country":"MX",
    "wof:name":"Campo Cachanilla",
    "wof:placetype":"locality",
    "wof:population":10
},
  "geometry": {"coordinates":[-106.99222,24.005],"type":"Point"}
}