{
  "type": "Feature",
  "properties": {
    "gn:admin1_code":"11",
    "gn:admin2_code":"27",
    "gn:asciiname":"Rancho Nuevo",
    "gn:country_code":"MX",
    "gn:dem":1729,
    "gn:feature_class":"P",
    "gn:feature_code":"PPL",
    "gn:name":"Rancho Nuevo",
    "gn:population":34,
    "gn:timezone":"America/Mexico_City",
    "iso:country":"MX",
    "wof:name":"Rancho Nuevo",
    "wof:placetype":"locality",
    "wof:population":34
},
  "geometry": {"coordinates":[-101.05389,20.46639],"type":"Point"}
}