{
  "type": "Feature",
  "properties": {
    "gn:admin1_code":"10",
    "gn:admin2_code":"16.0",
    "gn:asciiname":"La Constancia",
    "gn:country_code":"MX",
    "gn:dem":1787,
    "gn:feature_class":"P",
    "gn:feature_code":"PPL",
    "gn:name":"La Constancia",
    "gn:population":790,
    "gn:timezone":"America/Monterrey",
    "iso:country":"MX",
    "wof:name":"La Constancia",
    "wof:placetype":"locality",
    "wof:population":790
},
  "geometry": {"coordinates":[-104.26582999999999,23.91611],"type":"Point"}
}