{
  "type": "Feature",
  "properties": {
    "gn:admin1_code":"7",
    "gn:admin2_code":"20.0",
    "gn:asciiname":"Roman Gabriel Resendiz (El Papalote)",
    "gn:country_code":"MX",
    "gn:dem":497,
    "gn:feature_class":"P",
    "gn:feature_code":"PPL",
    "gn:name":"Rom\u00e1n Gabriel Res\u00e9ndiz (El Papalote)",
    "gn:population":6,
    "gn:timezone":"America/Monterrey",
    "iso:country":"MX",
    "name:und_x_variant":[
        "Rom\u00e1n Gabriel Res\u00e9ndiz (El Papalote)"
    ],
    "wof:name":"Roman Gabriel Resendiz (El Papalote)",
    "wof:placetype":"locality",
    "wof:population":6
},
  "geometry": {"coordinates":[-101.6951,28.03609],"type":"Point"}
}