{
  "type": "Feature",
  "properties": {
    "gn:admin1_code":"14.0",
    "gn:admin2_code":"28.0",
    "gn:asciiname":"El Zancudo",
    "gn:country_code":"MX",
    "gn:dem":1516,
    "gn:feature_class":"P",
    "gn:feature_code":"PPL",
    "gn:name":"El Zancudo",
    "gn:population":0,
    "gn:timezone":"America/Mexico_City",
    "iso:country":"MX",
    "name:spa_x_preferred":[
        "El Zancudo"
    ],
    "wof:name":"El Zancudo",
    "wof:placetype":"locality"
},
  "geometry": {"coordinates":[-104.54479000000001,20.29007],"type":"Point"}
}