{
  "type": "Feature",
  "properties": {
    "gn:admin1_code":"2",
    "gn:admin2_code":"1.0",
    "gn:asciiname":"Mision Santa Maria",
    "gn:country_code":"MX",
    "gn:dem":499,
    "gn:feature_class":"P",
    "gn:feature_code":"PPL",
    "gn:name":"Misi\u00f3n Santa Mar\u00eda",
    "gn:population":0,
    "gn:timezone":"America/Tijuana",
    "iso:country":"MX",
    "name:und_x_variant":[
        "Santa Mar\u00eda",
        "Misi\u00f3n Santa Mar\u00eda"
    ],
    "wof:name":"Mision Santa Maria",
    "wof:placetype":"locality"
},
  "geometry": {"coordinates":[-114.54798,29.73051],"type":"Point"}
}