{
  "type": "Feature",
  "properties": {
    "gn:admin1_code":"10.0",
    "gn:admin2_code":"37.0",
    "gn:asciiname":"Las Ollas",
    "gn:country_code":"MX",
    "gn:dem":907,
    "gn:feature_class":"P",
    "gn:feature_code":"PPL",
    "gn:name":"Las Ollas",
    "gn:population":0,
    "gn:timezone":"America/Monterrey",
    "iso:country":"MX",
    "name:spa_x_preferred":[
        "Las Ollas"
    ],
    "wof:name":"Las Ollas",
    "wof:placetype":"locality"
},
  "geometry": {"coordinates":[-106.92498000000001,25.25186],"type":"Point"}
}