{
  "type": "Feature",
  "properties": {
    "gn:admin1_code":"3.0",
    "gn:admin2_code":"1.0",
    "gn:asciiname":"El Canelo",
    "gn:country_code":"MX",
    "gn:dem":47,
    "gn:feature_class":"P",
    "gn:feature_code":"PPL",
    "gn:name":"El Canelo",
    "gn:population":0,
    "gn:timezone":"America/Mazatlan",
    "iso:country":"MX",
    "name:spa_x_preferred":[
        "El Canelo"
    ],
    "name:und_x_variant":[
        "Canelo"
    ],
    "wof:name":"El Canelo",
    "wof:placetype":"locality"
},
  "geometry": {"coordinates":[-111.81274999999999,25.63711],"type":"Point"}
}