{
  "type": "Feature",
  "properties": {
    "gn:admin1_code":"7.0",
    "gn:admin2_code":"31.0",
    "gn:asciiname":"La Angostura (La Chicharra)",
    "gn:country_code":"MX",
    "gn:dem":579,
    "gn:feature_class":"P",
    "gn:feature_code":"PPL",
    "gn:name":"La Angostura (La Chicharra)",
    "gn:population":4,
    "gn:timezone":"America/Monterrey",
    "iso:country":"MX",
    "name:spa_x_preferred":[
        "La Chicharra"
    ],
    "wof:name":"La Angostura (La Chicharra)",
    "wof:placetype":"locality",
    "wof:population":4
},
  "geometry": {"coordinates":[-101.5592,27.44013],"type":"Point"}
}