{
  "type": "Feature",
  "properties": {
    "gn:admin1_code":"16",
    "gn:admin2_code":"35",
    "gn:asciiname":"Colonia Morelos",
    "gn:country_code":"MX",
    "gn:dem":518,
    "gn:feature_class":"P",
    "gn:feature_code":"PPL",
    "gn:name":"Colonia Morelos",
    "gn:population":30,
    "gn:timezone":"America/Mexico_City",
    "iso:country":"MX",
    "wof:name":"Colonia Morelos",
    "wof:placetype":"locality",
    "wof:population":30
},
  "geometry": {"coordinates":[-101.80611,18.97083],"type":"Point"}
}