{
  "type": "Feature",
  "properties": {
    "gn:admin1_code":"26.0",
    "gn:admin2_code":"30.0",
    "gn:asciiname":"Piedras Pintas",
    "gn:country_code":"MX",
    "gn:dem":5,
    "gn:feature_class":"P",
    "gn:feature_code":"PPL",
    "gn:name":"Piedras Pintas",
    "gn:population":0,
    "gn:timezone":"America/Hermosillo",
    "iso:country":"MX",
    "name:spa_x_preferred":[
        "Piedras Pintas"
    ],
    "wof:name":"Piedras Pintas",
    "wof:placetype":"locality"
},
  "geometry": {"coordinates":[-111.92206000000002,28.80291],"type":"Point"}
}