{
  "type": "Feature",
  "properties": {
    "gn:admin1_code":"13",
    "gn:admin2_code":"16",
    "gn:asciiname":"La Isla de Montecristo",
    "gn:country_code":"MX",
    "gn:dem":2542,
    "gn:feature_class":"P",
    "gn:feature_code":"PPL",
    "gn:name":"La Isla de Montecristo",
    "gn:population":17,
    "gn:timezone":"America/Mexico_City",
    "iso:country":"MX",
    "wof:name":"La Isla de Montecristo",
    "wof:placetype":"locality",
    "wof:population":17
},
  "geometry": {"coordinates":[-98.36694,19.90389],"type":"Point"}
}