{
  "type": "Feature",
  "properties": {
    "gn:admin1_code":"4.0",
    "gn:admin2_code":"7.0",
    "gn:asciiname":"La Anona",
    "gn:country_code":"MX",
    "gn:dem":1,
    "gn:feature_class":"P",
    "gn:feature_code":"PPL",
    "gn:name":"La Anona",
    "gn:population":0,
    "gn:timezone":"America/Merida",
    "iso:country":"MX",
    "name:spa_x_preferred":[
        "La Nona"
    ],
    "name:spa_x_variant":[
        "La Anona"
    ],
    "wof:name":"La Anona",
    "wof:placetype":"locality"
},
  "geometry": {"coordinates":[-91.89111,18.27248],"type":"Point"}
}