{
  "type": "Feature",
  "properties": {
    "gn:admin1_code":"16",
    "gn:admin2_code":"82.0",
    "gn:asciiname":"Jauja",
    "gn:country_code":"MX",
    "gn:dem":1285,
    "gn:feature_class":"P",
    "gn:feature_code":"PPL",
    "gn:name":"Jauja",
    "gn:population":0,
    "gn:timezone":"America/Mexico_City",
    "iso:country":"MX",
    "name:ara_x_preferred":[
        "\u062c\u0627\u0648\u064a\u0627"
    ],
    "name:aym_x_preferred":[
        "Xauxa"
    ],
    "name:ben_x_preferred":[
        "\u099c\u09be\u0989\u099c\u09be"
    ],
    "name:ceb_x_preferred":[
        "Jauja"
    ],
    "name:deu_x_preferred":[
        "Jauja"
    ],
    "name:ell_x_preferred":[
        "\u03a7\u03ac\u03bf\u03c5\u03c7\u03b1"
    ],
    "name:epo_x_preferred":[
        "Jauja"
    ],
    "name:fas_x_preferred":[
        "\u062e\u0627\u0648\u062e\u0627"
    ],
    "name:fra_x_preferred":[
        "Jauja"
    ],
    "name:hin_x_preferred":[
        "\u0939\u0941\u0906\u091c\u093e"
    ],
    "name:hun_x_preferred":[
        "Jauja"
    ],
    "name:ind_x_preferred":[
        "Jauja"
    ],
    "name:ita_x_preferred":[
        "Jauja"
    ],
    "name:kor_x_preferred":[
        "\ud558\uc6b0\ud558"
    ],
    "name:lit_x_preferred":[
        "Chaucha"
    ],
    "name:nor_x_preferred":[
        "Jauja"
    ],
    "name:pol_x_preferred":[
        "Jauja"
    ],
    "name:por_x_preferred":[
        "Jauja"
    ],
    "name:que_x_preferred":[
        "Shawsha"
    ],
    "name:rus_x_preferred":[
        "\u0425\u0430\u0443\u0445\u0430"
    ],
    "name:sco_x_preferred":[
        "Jauja"
    ],
    "name:spa_x_preferred":[
        "Jauja"
    ],
    "name:swe_x_preferred":[
        "Jauja"
    ],
    "name:tur_x_preferred":[
        "Jauja"
    ],
    "name:ukr_x_preferred":[
        "\u0425\u0430\u0443\u0445\u0430"
    ],
    "name:urd_x_preferred":[
        "\u062c\u0627\u0648\u062c\u0627"
    ],
    "name:vie_x_preferred":[
        "Jauja"
    ],
    "name:war_x_preferred":[
        "Jauja"
    ],
    "wof:name":"Jauja",
    "wof:placetype":"locality"
},
  "geometry": {"coordinates":[-101.36919,19.1851],"type":"Point"}
}