{
  "type": "Feature",
  "properties": {
    "gn:admin1_code":"5",
    "gn:admin2_code":"83",
    "gn:asciiname":"Jesus Hernandez J.",
    "gn:country_code":"MX",
    "gn:dem":692,
    "gn:feature_class":"P",
    "gn:feature_code":"PPL",
    "gn:name":"Jes\u00fas Hern\u00e1ndez J.",
    "gn:population":46,
    "gn:timezone":"America/Mexico_City",
    "iso:country":"MX",
    "name:und_x_variant":[
        "Jes\u00fas Hern\u00e1ndez J."
    ],
    "wof:name":"Jesus Hernandez J.",
    "wof:placetype":"locality",
    "wof:population":46
},
  "geometry": {"coordinates":[-92.35278,16.11389],"type":"Point"}
}