{
  "type": "Feature",
  "properties": {
    "gn:admin1_code":"13",
    "gn:admin2_code":"22.0",
    "gn:asciiname":"Xolostitla de Morelos (Xolostitla)",
    "gn:country_code":"MX",
    "gn:dem":2478,
    "gn:feature_class":"P",
    "gn:feature_code":"PPL",
    "gn:name":"Xolostitla de Morelos (Xolostitla)",
    "gn:population":1179,
    "gn:timezone":"America/Mexico_City",
    "iso:country":"MX",
    "wof:name":"Xolostitla de Morelos (Xolostitla)",
    "wof:placetype":"locality",
    "wof:population":1179
},
  "geometry": {"coordinates":[-98.63861,20.06639],"type":"Point"}
}