{
  "type": "Feature",
  "properties": {
    "gn:admin1_code":"21",
    "gn:admin2_code":"212.0",
    "gn:asciiname":"Tlamanca",
    "gn:country_code":"MX",
    "gn:dem":1999,
    "gn:feature_class":"P",
    "gn:feature_code":"PPL",
    "gn:name":"Tlamanca",
    "gn:population":0,
    "gn:timezone":"America/Mexico_City",
    "iso:country":"MX",
    "name:und_x_variant":[
        "Tlamauca",
        "Tlamanaca"
    ],
    "wof:name":"Tlamanca",
    "wof:placetype":"locality"
},
  "geometry": {"coordinates":[-97.6964,19.67457000000001],"type":"Point"}
}