{
  "type": "Feature",
  "properties": {
    "gn:admin1_code":"6",
    "gn:admin2_code":"20.0",
    "gn:asciiname":"La Vinatita",
    "gn:country_code":"MX",
    "gn:dem":1263,
    "gn:feature_class":"P",
    "gn:feature_code":"PPL",
    "gn:name":"La Vinatita",
    "gn:population":6,
    "gn:timezone":"America/Chihuahua",
    "iso:country":"MX",
    "name:spa_x_preferred":[
        "La Vinatita"
    ],
    "name:und_x_variant":[
        "Rancho La Vinetita"
    ],
    "wof:name":"La Vinatita",
    "wof:placetype":"locality",
    "wof:population":6
},
  "geometry": {"coordinates":[-108.65326,27.55681],"type":"Point"}
}