{
  "type": "Feature",
  "properties": {
    "gn:admin1_code":"21",
    "gn:admin2_code":"53",
    "gn:asciiname":"Santa Cruz",
    "gn:country_code":"MX",
    "gn:dem":2460,
    "gn:feature_class":"P",
    "gn:feature_code":"PPL",
    "gn:name":"Santa Cruz",
    "gn:population":27,
    "gn:timezone":"America/Mexico_City",
    "iso:country":"MX",
    "wof:name":"Santa Cruz",
    "wof:placetype":"locality",
    "wof:population":27
},
  "geometry": {"coordinates":[-98.14145000000001,19.76351],"type":"Point"}
}