{
  "type": "Feature",
  "properties": {
    "gn:admin1_code":"19",
    "gn:admin2_code":"2.0",
    "gn:asciiname":"Tres Hermanos",
    "gn:country_code":"MX",
    "gn:dem":295,
    "gn:feature_class":"P",
    "gn:feature_code":"PPL",
    "gn:name":"Tres Hermanos",
    "gn:population":58,
    "gn:timezone":"America/Monterrey",
    "iso:country":"MX",
    "wof:name":"Tres Hermanos",
    "wof:placetype":"locality",
    "wof:population":58
},
  "geometry": {"coordinates":[-99.83198,26.33199],"type":"Point"}
}