{
  "type": "Feature",
  "properties": {
    "gn:admin1_code":"5",
    "gn:admin2_code":"105.0",
    "gn:asciiname":"Eureka",
    "gn:country_code":"MX",
    "gn:dem":1210,
    "gn:feature_class":"P",
    "gn:feature_code":"PPL",
    "gn:name":"Eureka",
    "gn:population":361,
    "gn:timezone":"America/Mexico_City",
    "iso:country":"MX",
    "name:spa_x_preferred":[
        "Eureka"
    ],
    "wof:name":"Eureka",
    "wof:placetype":"locality",
    "wof:population":361
},
  "geometry": {"coordinates":[-92.12614000000001,15.06151],"type":"Point"}
}