{
  "type": "Feature",
  "properties": {
    "gn:admin1_code":"26.0",
    "gn:admin2_code":"2.0",
    "gn:asciiname":"El Pozo",
    "gn:country_code":"MX",
    "gn:dem":876,
    "gn:feature_class":"P",
    "gn:feature_code":"PPL",
    "gn:name":"El Pozo",
    "gn:population":1,
    "gn:timezone":"America/Hermosillo",
    "iso:country":"MX",
    "name:spa_x_preferred":[
        "El Pozo"
    ],
    "wof:name":"El Pozo",
    "wof:placetype":"locality",
    "wof:population":1
},
  "geometry": {"coordinates":[-109.27,30.91528],"type":"Point"}
}