{
  "type": "Feature",
  "properties": {
    "gn:admin1_code":"12.0",
    "gn:admin2_code":"54.0",
    "gn:asciiname":"Los Bancos",
    "gn:country_code":"MX",
    "gn:dem":525,
    "gn:feature_class":"P",
    "gn:feature_code":"PPL",
    "gn:name":"Los Bancos",
    "gn:population":81,
    "gn:timezone":"America/Mexico_City",
    "iso:country":"MX",
    "name:spa_x_preferred":[
        "Los Bancos"
    ],
    "wof:name":"Los Bancos",
    "wof:placetype":"locality",
    "wof:population":81
},
  "geometry": {"coordinates":[-100.39037999999999,17.98139],"type":"Point"}
}