{
  "type": "Feature",
  "properties": {
    "gn:admin1_code":"1.0",
    "gn:admin2_code":"2.0",
    "gn:asciiname":"Puente [Rancho]",
    "gn:country_code":"MX",
    "gn:dem":2075,
    "gn:feature_class":"P",
    "gn:feature_code":"PPL",
    "gn:name":"Puente [Rancho]",
    "gn:population":7,
    "gn:timezone":"America/Mexico_City",
    "iso:country":"MX",
    "wof:name":"Puente [Rancho]",
    "wof:placetype":"locality",
    "wof:population":7
},
  "geometry": {"coordinates":[-102.05576000000001,22.23229],"type":"Point"}
}