{
  "type": "Feature",
  "properties": {
    "gn:admin1_code":"15",
    "gn:admin2_code":"5.0",
    "gn:asciiname":"Arroyo",
    "gn:country_code":"MX",
    "gn:dem":2586,
    "gn:feature_class":"P",
    "gn:feature_code":"PPL",
    "gn:name":"Arroyo",
    "gn:population":0,
    "gn:timezone":"America/Mexico_City",
    "iso:country":"MX",
    "name:cat_x_preferred":[
        "Arroyo"
    ],
    "name:ceb_x_preferred":[
        "Arroyo"
    ],
    "name:deu_x_preferred":[
        "Arroyo"
    ],
    "name:fra_x_preferred":[
        "Arroyo"
    ],
    "name:heb_x_preferred":[
        "\u05d0\u05e8\u05d5\u05d9\u05d5"
    ],
    "name:ita_x_preferred":[
        "Arroyo"
    ],
    "name:jpn_x_preferred":[
        "\u30a2\u30ed\u30e8"
    ],
    "name:kor_x_preferred":[
        "\uc544\ub85c\uc694"
    ],
    "name:nld_x_preferred":[
        "Arroyo"
    ],
    "name:pol_x_preferred":[
        "Arroyo"
    ],
    "name:por_x_preferred":[
        "Arroyo"
    ],
    "name:rus_x_preferred":[
        "\u0410\u0440\u0440\u043e\u0439\u043e"
    ],
    "name:slk_x_preferred":[
        "Arroyo"
    ],
    "name:slv_x_preferred":[
        "Arroyo"
    ],
    "name:spa_x_preferred":[
        "Arroyo"
    ],
    "name:swe_x_preferred":[
        "Arroyo"
    ],
    "wof:name":"Arroyo",
    "wof:placetype":"locality"
},
  "geometry": {"coordinates":[-99.75,19.41667],"type":"Point"}
}