{
  "type": "Feature",
  "properties": {
    "gn:admin1_code":"14",
    "gn:admin2_code":"91.0",
    "gn:asciiname":"Los Garcia",
    "gn:country_code":"MX",
    "gn:dem":1871,
    "gn:feature_class":"P",
    "gn:feature_code":"PPL",
    "gn:name":"Los Garc\u00eda",
    "gn:population":54,
    "gn:timezone":"America/Mexico_City",
    "iso:country":"MX",
    "name:und_x_variant":[
        "Los Garc\u00eda"
    ],
    "wof:name":"Los Garcia",
    "wof:placetype":"locality",
    "wof:population":54
},
  "geometry": {"coordinates":[-102.61888999999999,21.53556],"type":"Point"}
}