{
  "type": "Feature",
  "properties": {
    "gn:admin1_code":"21",
    "gn:admin2_code":"199.0",
    "gn:asciiname":"Chalma",
    "gn:country_code":"MX",
    "gn:dem":2103,
    "gn:feature_class":"P",
    "gn:feature_code":"PPL",
    "gn:name":"Chalma",
    "gn:population":170,
    "gn:timezone":"America/Mexico_City",
    "iso:country":"MX",
    "wof:name":"Chalma",
    "wof:placetype":"locality",
    "wof:population":170
},
  "geometry": {"coordinates":[-97.32446,19.75703],"type":"Point"}
}