{
  "type": "Feature",
  "properties": {
    "gn:admin1_code":"5",
    "gn:admin2_code":"99.0",
    "gn:asciiname":"Rio Grande el Grijalva",
    "gn:country_code":"MX",
    "gn:dem":582,
    "gn:feature_class":"P",
    "gn:feature_code":"PPL",
    "gn:name":"R\u00edo Grande el Grijalva",
    "gn:population":640,
    "gn:timezone":"America/Mexico_City",
    "iso:country":"MX",
    "name:und_x_variant":[
        "R\u00edo Grande el Grijalva"
    ],
    "wof:name":"Rio Grande el Grijalva",
    "wof:placetype":"locality",
    "wof:population":640
},
  "geometry": {"coordinates":[-92.01056,15.85],"type":"Point"}
}