{
  "type": "Feature",
  "properties": {
    "gn:admin1_code":"31",
    "gn:admin2_code":"65.0",
    "gn:asciiname":"San Benito",
    "gn:country_code":"MX",
    "gn:dem":7,
    "gn:feature_class":"P",
    "gn:feature_code":"PPL",
    "gn:name":"San Benito",
    "gn:population":0,
    "gn:timezone":"America/Merida",
    "iso:country":"MX",
    "name:spa_x_preferred":[
        "San Benito"
    ],
    "wof:name":"San Benito",
    "wof:placetype":"locality"
},
  "geometry": {"coordinates":[-88.21951999999997,21.45475],"type":"Point"}
}