{
  "type": "Feature",
  "properties": {
    "gn:admin1_code":"14.0",
    "gn:admin2_code":"90.0",
    "gn:asciiname":"Colotitlan",
    "gn:country_code":"MX",
    "gn:dem":1397,
    "gn:feature_class":"P",
    "gn:feature_code":"PPL",
    "gn:name":"Colotitl\u00e1n",
    "gn:population":0,
    "gn:timezone":"America/Mexico_City",
    "iso:country":"MX",
    "wof:name":"Colotitlan",
    "wof:placetype":"locality"
},
  "geometry": {"coordinates":[-104.15327000000001,20.09567],"type":"Point"}
}