{
  "type": "Feature",
  "properties": {
    "gn:admin1_code":"4",
    "gn:admin2_code":"11.0",
    "gn:asciiname":"El Julian",
    "gn:country_code":"MX",
    "gn:dem":65,
    "gn:feature_class":"P",
    "gn:feature_code":"PPL",
    "gn:name":"El Juli\u00e1n",
    "gn:population":6,
    "gn:timezone":"America/Merida",
    "iso:country":"MX",
    "name:und_x_variant":[
        "El Juli\u00e1n"
    ],
    "wof:name":"El Julian",
    "wof:placetype":"locality",
    "wof:population":6
},
  "geometry": {"coordinates":[-90.80972,18.24806],"type":"Point"}
}