{
  "type": "Feature",
  "properties": {
    "gn:admin1_code":"5",
    "gn:admin2_code":"80",
    "gn:asciiname":"El Canacal (Tocanaque)",
    "gn:country_code":"MX",
    "gn:dem":1608,
    "gn:feature_class":"P",
    "gn:feature_code":"PPL",
    "gn:name":"El Canacal (Tocanaque)",
    "gn:population":35,
    "gn:timezone":"America/Mexico_City",
    "iso:country":"MX",
    "wof:name":"El Canacal (Tocanaque)",
    "wof:placetype":"locality",
    "wof:population":35
},
  "geometry": {"coordinates":[-92.55833,15.55194],"type":"Point"}
}