{
  "type": "Feature",
  "properties": {
    "gn:admin1_code":"11",
    "gn:admin2_code":"15",
    "gn:asciiname":"El Chocolate (Barrio de Guadalupe)",
    "gn:country_code":"MX",
    "gn:dem":2390,
    "gn:feature_class":"P",
    "gn:feature_code":"PPL",
    "gn:name":"El Chocolate (Barrio de Guadalupe)",
    "gn:population":21,
    "gn:timezone":"America/Mexico_City",
    "iso:country":"MX",
    "wof:name":"El Chocolate (Barrio de Guadalupe)",
    "wof:placetype":"locality",
    "wof:population":21
},
  "geometry": {"coordinates":[-101.29306,21.13361],"type":"Point"}
}