{
  "type": "Feature",
  "properties": {
    "gn:admin1_code":"10",
    "gn:admin2_code":"4.0",
    "gn:asciiname":"La Tarea",
    "gn:country_code":"MX",
    "gn:dem":1908,
    "gn:feature_class":"P",
    "gn:feature_code":"PPL",
    "gn:name":"La Tarea",
    "gn:population":0,
    "gn:timezone":"America/Monterrey",
    "iso:country":"MX",
    "name:spa_x_preferred":[
        "La Tarea"
    ],
    "wof:name":"La Tarea",
    "wof:placetype":"locality"
},
  "geometry": {"coordinates":[-103.80025000000001,24.71632],"type":"Point"}
}