{
  "type": "Feature",
  "properties": {
    "gn:admin1_code":"15",
    "gn:admin2_code":"48.0",
    "gn:asciiname":"Santa Maria Citendeje",
    "gn:country_code":"MX",
    "gn:dem":2575,
    "gn:feature_class":"P",
    "gn:feature_code":"PPL",
    "gn:name":"Santa Mar\u00eda Citendej\u00e9",
    "gn:population":0,
    "gn:timezone":"America/Mexico_City",
    "iso:country":"MX",
    "name:spa_x_preferred":[
        "Santa Mar\u00eda Citendej\u00e9"
    ],
    "name:und_x_variant":[
        "Santa Mar\u00eda",
        "Santiago Citendej\u00e9"
    ],
    "wof:name":"Santa Maria Citendeje",
    "wof:placetype":"locality"
},
  "geometry": {"coordinates":[-99.92863,19.7819],"type":"Point"}
}