{
  "type": "Feature",
  "properties": {
    "gn:admin1_code":"19.0",
    "gn:admin2_code":"32.0",
    "gn:asciiname":"Hacienda San Patricio",
    "gn:country_code":"MX",
    "gn:dem":277,
    "gn:feature_class":"P",
    "gn:feature_code":"PPL",
    "gn:name":"Hacienda San Patricio",
    "gn:population":0,
    "gn:timezone":"America/Monterrey",
    "iso:country":"MX",
    "wof:name":"Hacienda San Patricio",
    "wof:placetype":"locality"
},
  "geometry": {"coordinates":[-100.63333,27.23333],"type":"Point"}
}