{
  "type": "Feature",
  "properties": {
    "gn:admin1_code":"25.0",
    "gn:asciiname":"El Charco Azul",
    "gn:country_code":"MX",
    "gn:dem":482,
    "gn:feature_class":"P",
    "gn:feature_code":"PPL",
    "gn:name":"El Charco Azul",
    "gn:population":0,
    "gn:timezone":"America/Mazatlan",
    "iso:country":"MX",
    "name:spa_x_preferred":[
        "El Charco Azul"
    ],
    "wof:name":"El Charco Azul",
    "wof:placetype":"locality"
},
  "geometry": {"coordinates":[-106.32958000000001,24.26222000000001],"type":"Point"}
}