{
  "type": "Feature",
  "properties": {
    "gn:admin1_code":"32",
    "gn:admin2_code":"42.0",
    "gn:asciiname":"Los Tamayos",
    "gn:country_code":"MX",
    "gn:dem":2353,
    "gn:feature_class":"P",
    "gn:feature_code":"PPL",
    "gn:name":"Los Tamayos",
    "gn:population":9,
    "gn:timezone":"America/Mexico_City",
    "iso:country":"MX",
    "wof:name":"Los Tamayos",
    "wof:placetype":"locality",
    "wof:population":9
},
  "geometry": {"coordinates":[-103.62555999999999,23.73472000000001],"type":"Point"}
}