{
  "type": "Feature",
  "properties": {
    "gn:admin1_code":"14.0",
    "gn:admin2_code":"97.0",
    "gn:asciiname":"Capulin",
    "gn:country_code":"MX",
    "gn:dem":1543,
    "gn:feature_class":"P",
    "gn:feature_code":"PPL",
    "gn:name":"Capul\u00edn",
    "gn:population":0,
    "gn:timezone":"America/Mexico_City",
    "iso:country":"MX",
    "wof:name":"Capulin",
    "wof:placetype":"locality"
},
  "geometry": {"coordinates":[-103.26947,20.47802],"type":"Point"}
}