{
  "type": "Feature",
  "properties": {
    "gn:admin1_code":"26",
    "gn:admin2_code":"31.0",
    "gn:asciiname":"Chirriones",
    "gn:country_code":"MX",
    "gn:dem":1169,
    "gn:feature_class":"P",
    "gn:feature_code":"PPL",
    "gn:name":"Chirriones",
    "gn:population":0,
    "gn:timezone":"America/Hermosillo",
    "iso:country":"MX",
    "name:spa_x_preferred":[
        "Chirriones"
    ],
    "wof:name":"Chirriones",
    "wof:placetype":"locality"
},
  "geometry": {"coordinates":[-108.80868,30.1865],"type":"Point"}
}