{
  "type": "Feature",
  "properties": {
    "gn:admin1_code":"24",
    "gn:admin2_code":"33.0",
    "gn:asciiname":"Laguna de Calero",
    "gn:country_code":"MX",
    "gn:dem":2260,
    "gn:feature_class":"P",
    "gn:feature_code":"PPL",
    "gn:name":"Laguna de Calero",
    "gn:population":0,
    "gn:timezone":"America/Mexico_City",
    "iso:country":"MX",
    "wof:name":"Laguna de Calero",
    "wof:placetype":"locality"
},
  "geometry": {"coordinates":[-101.42719,23.27544],"type":"Point"}
}