{
  "type": "Feature",
  "properties": {
    "gn:admin1_code":"5",
    "gn:admin2_code":"27.0",
    "gn:asciiname":"Francisco Sarabia",
    "gn:country_code":"MX",
    "gn:dem":444,
    "gn:feature_class":"P",
    "gn:feature_code":"PPL",
    "gn:name":"Francisco Sarabia",
    "gn:population":0,
    "gn:timezone":"America/Mexico_City",
    "iso:country":"MX",
    "name:spa_x_preferred":[
        "Francisco Sarabia"
    ],
    "wof:name":"Francisco Sarabia",
    "wof:placetype":"locality"
},
  "geometry": {"coordinates":[-93.00543,16.55605],"type":"Point"}
}