{
  "type": "Feature",
  "properties": {
    "gn:admin1_code":"12.0",
    "gn:admin2_code":"48.0",
    "gn:asciiname":"Alambrado",
    "gn:country_code":"MX",
    "gn:dem":692,
    "gn:feature_class":"P",
    "gn:feature_code":"PPL",
    "gn:name":"Alambrado",
    "gn:population":0,
    "gn:timezone":"America/Mexico_City",
    "iso:country":"MX",
    "name:spa_x_preferred":[
        "Alambrado"
    ],
    "wof:name":"Alambrado",
    "wof:placetype":"locality"
},
  "geometry": {"coordinates":[-101.1966,17.82541],"type":"Point"}
}