{
  "type": "Feature",
  "properties": {
    "gn:admin1_code":"5.0",
    "gn:admin2_code":"26.0",
    "gn:asciiname":"Pushilo",
    "gn:country_code":"MX",
    "gn:dem":969,
    "gn:feature_class":"P",
    "gn:feature_code":"PPL",
    "gn:name":"Pushilo",
    "gn:population":0,
    "gn:timezone":"America/Mexico_City",
    "iso:country":"MX",
    "name:spa_x_preferred":[
        "Pushilo"
    ],
    "wof:name":"Pushilo",
    "wof:placetype":"locality"
},
  "geometry": {"coordinates":[-92.67547,16.96427000000001],"type":"Point"}
}