{
  "type": "Feature",
  "properties": {
    "gn:admin1_code":"5",
    "gn:admin2_code":"109",
    "gn:asciiname":"La Libertad",
    "gn:country_code":"MX",
    "gn:dem":1081,
    "gn:feature_class":"P",
    "gn:feature_code":"PPL",
    "gn:name":"La Libertad",
    "gn:population":24,
    "gn:timezone":"America/Mexico_City",
    "iso:country":"MX",
    "wof:name":"La Libertad",
    "wof:placetype":"locality",
    "wof:population":24
},
  "geometry": {"coordinates":[-92.33194,17.15556],"type":"Point"}
}