{
  "type": "Feature",
  "properties": {
    "gn:admin1_code":"25",
    "gn:admin2_code":"12.0",
    "gn:asciiname":"El Tecolote",
    "gn:country_code":"MX",
    "gn:dem":15,
    "gn:feature_class":"P",
    "gn:feature_code":"PPL",
    "gn:name":"El Tecolote",
    "gn:population":6,
    "gn:timezone":"America/Mazatlan",
    "iso:country":"MX",
    "name:ceb_x_preferred":[
        "El Tecolote"
    ],
    "name:swe_x_preferred":[
        "El Tecolote"
    ],
    "wof:name":"El Tecolote",
    "wof:placetype":"locality",
    "wof:population":6
},
  "geometry": {"coordinates":[-106.572,23.46435],"type":"Point"}
}