{
  "type": "Feature",
  "properties": {
    "gn:admin1_code":"4",
    "gn:admin2_code":"2.0",
    "gn:asciiname":"Cristo en el Camino",
    "gn:country_code":"MX",
    "gn:dem":18,
    "gn:feature_class":"P",
    "gn:feature_code":"PPL",
    "gn:name":"Cristo en el Camino",
    "gn:population":4,
    "gn:timezone":"America/Merida",
    "iso:country":"MX",
    "wof:name":"Cristo en el Camino",
    "wof:placetype":"locality",
    "wof:population":4
},
  "geometry": {"coordinates":[-90.41528,19.905],"type":"Point"}
}