{
  "type": "Feature",
  "properties": {
    "gn:admin1_code":"14.0",
    "gn:asciiname":"Timbes",
    "gn:country_code":"MX",
    "gn:dem":1394,
    "gn:feature_class":"P",
    "gn:feature_code":"PPL",
    "gn:name":"Timbes",
    "gn:population":0,
    "gn:timezone":"America/Mexico_City",
    "iso:country":"MX",
    "name:spa_x_preferred":[
        "Timbes"
    ],
    "wof:name":"Timbes",
    "wof:placetype":"locality"
},
  "geometry": {"coordinates":[-103.88592,21.33774],"type":"Point"}
}