{
  "type": "Feature",
  "properties": {
    "gn:admin1_code":"16.0",
    "gn:admin2_code":"26.0",
    "gn:asciiname":"Las Higueritas",
    "gn:country_code":"MX",
    "gn:dem":701,
    "gn:feature_class":"P",
    "gn:feature_code":"PPL",
    "gn:name":"Las Higueritas",
    "gn:population":0,
    "gn:timezone":"America/Mexico_City",
    "iso:country":"MX",
    "name:spa_x_preferred":[
        "Las Higueritas"
    ],
    "wof:name":"Las Higueritas",
    "wof:placetype":"locality"
},
  "geometry": {"coordinates":[-103.36244000000001,18.7353],"type":"Point"}
}