{
  "type": "Feature",
  "properties": {
    "gn:admin1_code":"5",
    "gn:admin2_code":"69.0",
    "gn:asciiname":"El Guachipilin",
    "gn:country_code":"MX",
    "gn:dem":19,
    "gn:feature_class":"P",
    "gn:feature_code":"PPL",
    "gn:name":"El Guachipil\u00edn",
    "gn:population":4,
    "gn:timezone":"America/Mexico_City",
    "iso:country":"MX",
    "name:und_x_variant":[
        "El Guachipil\u00edn"
    ],
    "wof:name":"El Guachipilin",
    "wof:placetype":"locality",
    "wof:population":4
},
  "geometry": {"coordinates":[-93.11391999999999,15.57144],"type":"Point"}
}