{
  "type": "Feature",
  "properties": {
    "gn:admin1_code":"28",
    "gn:admin2_code":"35.0",
    "gn:asciiname":"El Puerto",
    "gn:country_code":"MX",
    "gn:dem":12,
    "gn:feature_class":"P",
    "gn:feature_code":"PPL",
    "gn:name":"El Puerto",
    "gn:population":0,
    "gn:timezone":"America/Monterrey",
    "iso:country":"MX",
    "name:spa_x_preferred":[
        "El Puerto"
    ],
    "name:und_x_variant":[
        "El Puerto del Rucio"
    ],
    "wof:name":"El Puerto",
    "wof:placetype":"locality"
},
  "geometry": {"coordinates":[-97.86684,24.96984],"type":"Point"}
}