{
  "type": "Feature",
  "properties": {
    "gn:admin1_code":"4",
    "gn:admin2_code":"9.0",
    "gn:asciiname":"Tepehuaje",
    "gn:country_code":"MX",
    "gn:dem":88,
    "gn:feature_class":"P",
    "gn:feature_code":"PPL",
    "gn:name":"Tepehuaje",
    "gn:population":6,
    "gn:timezone":"America/Merida",
    "iso:country":"MX",
    "wof:name":"Tepehuaje",
    "wof:placetype":"locality",
    "wof:population":6
},
  "geometry": {"coordinates":[-90.77694,18.64722],"type":"Point"}
}