{
  "type": "Feature",
  "properties": {
    "gn:admin1_code":"21",
    "gn:admin2_code":"116.0",
    "gn:asciiname":"Tlahuitompa",
    "gn:country_code":"MX",
    "gn:dem":2288,
    "gn:feature_class":"P",
    "gn:feature_code":"PPL",
    "gn:name":"Tlahuitompa",
    "gn:population":256,
    "gn:timezone":"America/Mexico_City",
    "iso:country":"MX",
    "wof:name":"Tlahuitompa",
    "wof:placetype":"locality",
    "wof:population":256
},
  "geometry": {"coordinates":[-97.13785,19.19278],"type":"Point"}
}