{
  "type": "Feature",
  "properties": {
    "gn:admin1_code":"30.0",
    "gn:admin2_code":"69.0",
    "gn:asciiname":"Paguas de Arroyo Grande",
    "gn:country_code":"MX",
    "gn:dem":36,
    "gn:feature_class":"P",
    "gn:feature_code":"PPL",
    "gn:name":"Paguas de Arroyo Grande",
    "gn:population":215,
    "gn:timezone":"America/Mexico_City",
    "iso:country":"MX",
    "name:spa_x_preferred":[
        "Paguas de Arroyo Grande"
    ],
    "wof:name":"Paguas de Arroyo Grande",
    "wof:placetype":"locality",
    "wof:population":215
},
  "geometry": {"coordinates":[-97.13500000000001,20.50083],"type":"Point"}
}