{
  "type": "Feature",
  "properties": {
    "gn:admin1_code":"5",
    "gn:admin2_code":"54.0",
    "gn:asciiname":"San Andres Suyacal",
    "gn:country_code":"MX",
    "gn:dem":33,
    "gn:feature_class":"P",
    "gn:feature_code":"PPL",
    "gn:name":"San Andr\u00e9s Suyacal",
    "gn:population":499,
    "gn:timezone":"America/Mexico_City",
    "iso:country":"MX",
    "name:und_x_variant":[
        "San Andr\u00e9s Suyacal"
    ],
    "wof:name":"San Andres Suyacal",
    "wof:placetype":"locality",
    "wof:population":499
},
  "geometry": {"coordinates":[-92.43722,14.87806],"type":"Point"}
}