{
  "type": "Feature",
  "properties": {
    "gn:admin1_code":"6",
    "gn:admin2_code":"46",
    "gn:asciiname":"Las Lomas de las Lusanias",
    "gn:country_code":"MX",
    "gn:dem":1577,
    "gn:feature_class":"P",
    "gn:feature_code":"PPL",
    "gn:name":"Las Lomas de las Lusanias",
    "gn:population":12,
    "gn:timezone":"America/Mazatlan",
    "iso:country":"MX",
    "wof:name":"Las Lomas de las Lusanias",
    "wof:placetype":"locality",
    "wof:population":12
},
  "geometry": {"coordinates":[-107.95740000000001,26.75216],"type":"Point"}
}