{
  "type": "Feature",
  "properties": {
    "gn:admin1_code":"26",
    "gn:asciiname":"La Gavilana",
    "gn:country_code":"MX",
    "gn:dem":159,
    "gn:feature_class":"P",
    "gn:feature_code":"PPL",
    "gn:name":"La Gavilana",
    "gn:population":0,
    "gn:timezone":"America/Mazatlan",
    "iso:country":"MX",
    "name:spa_x_preferred":[
        "La Gavilana"
    ],
    "wof:name":"La Gavilana",
    "wof:placetype":"locality"
},
  "geometry": {"coordinates":[-108.69168000000001,26.5742],"type":"Point"}
}