{
  "type": "Feature",
  "properties": {
    "gn:admin1_code":"24",
    "gn:admin2_code":"47.0",
    "gn:asciiname":"Santa Rosalia del Centro",
    "gn:country_code":"MX",
    "gn:dem":1544,
    "gn:feature_class":"P",
    "gn:feature_code":"PPL",
    "gn:name":"Santa Rosal\u00eda del Centro",
    "gn:population":60,
    "gn:timezone":"America/Mexico_City",
    "iso:country":"MX",
    "name:und_x_variant":[
        "Santa Rosal\u00eda del Centro"
    ],
    "wof:name":"Santa Rosalia del Centro",
    "wof:placetype":"locality",
    "wof:population":60
},
  "geometry": {"coordinates":[-100.69278,23.45639],"type":"Point"}
}