{
  "type": "Feature",
  "properties": {
    "gn:admin1_code":"5",
    "gn:admin2_code":"4.0",
    "gn:asciiname":"Nuevo Jerusalen",
    "gn:country_code":"MX",
    "gn:dem":1269,
    "gn:feature_class":"P",
    "gn:feature_code":"PPL",
    "gn:name":"Nuevo Jerusal\u00e9n",
    "gn:population":66,
    "gn:timezone":"America/Mexico_City",
    "iso:country":"MX",
    "name:und_x_variant":[
        "Nuevo Jerusal\u00e9n"
    ],
    "wof:name":"Nuevo Jerusalen",
    "wof:placetype":"locality",
    "wof:population":66
},
  "geometry": {"coordinates":[-91.96944000000001,16.61417],"type":"Point"}
}