{
  "type": "Feature",
  "properties": {
    "gn:admin1_code":"5",
    "gn:admin2_code":"50.0",
    "gn:asciiname":"La Martinica",
    "gn:country_code":"MX",
    "gn:dem":8,
    "gn:feature_class":"P",
    "gn:feature_code":"PPL",
    "gn:name":"La Martinica",
    "gn:population":6,
    "gn:timezone":"America/Mexico_City",
    "iso:country":"MX",
    "wof:name":"La Martinica",
    "wof:placetype":"locality",
    "wof:population":6
},
  "geometry": {"coordinates":[-91.80194,17.71777999999999],"type":"Point"}
}