{
  "type": "Feature",
  "properties": {
    "gn:admin1_code":"15",
    "gn:admin2_code":"105.0",
    "gn:asciiname":"El Panal",
    "gn:country_code":"MX",
    "gn:dem":957,
    "gn:feature_class":"P",
    "gn:feature_code":"PPL",
    "gn:name":"El Panal",
    "gn:population":74,
    "gn:timezone":"America/Mexico_City",
    "iso:country":"MX",
    "wof:name":"El Panal",
    "wof:placetype":"locality",
    "wof:population":74
},
  "geometry": {"coordinates":[-100.35137,18.62633],"type":"Point"}
}