{
  "type": "Feature",
  "properties": {
    "gn:admin1_code":"16",
    "gn:admin2_code":"17.0",
    "gn:asciiname":"El Crucero",
    "gn:country_code":"MX",
    "gn:dem":2353,
    "gn:feature_class":"P",
    "gn:feature_code":"PPL",
    "gn:name":"El Crucero",
    "gn:population":257,
    "gn:timezone":"America/Mexico_City",
    "iso:country":"MX",
    "wof:name":"El Crucero",
    "wof:placetype":"locality",
    "wof:population":257
},
  "geometry": {"coordinates":[-100.1825,19.93389],"type":"Point"}
}