{
  "type": "Feature",
  "properties": {
    "gn:admin1_code":"18.0",
    "gn:admin2_code":"19.0",
    "gn:asciiname":"El Trapiche",
    "gn:country_code":"MX",
    "gn:dem":1400,
    "gn:feature_class":"P",
    "gn:feature_code":"PPL",
    "gn:name":"El Trapiche",
    "gn:population":208,
    "gn:timezone":"America/Mazatlan",
    "iso:country":"MX",
    "name:spa_x_preferred":[
        "El Trapiche"
    ],
    "wof:name":"El Trapiche",
    "wof:placetype":"locality",
    "wof:population":208
},
  "geometry": {"coordinates":[-104.20528,21.44778],"type":"Point"}
}