{
  "type": "Feature",
  "properties": {
    "gn:admin1_code":"16",
    "gn:admin2_code":"101.0",
    "gn:asciiname":"Los Cimientillos",
    "gn:country_code":"MX",
    "gn:dem":1012,
    "gn:feature_class":"P",
    "gn:feature_code":"PPL",
    "gn:name":"Los Cimientillos",
    "gn:population":0,
    "gn:timezone":"America/Mexico_City",
    "iso:country":"MX",
    "name:spa_x_preferred":[
        "Los Cimientillos"
    ],
    "wof:name":"Los Cimientillos",
    "wof:placetype":"locality"
},
  "geometry": {"coordinates":[-100.86651999999999,19.41984],"type":"Point"}
}