{
  "type": "Feature",
  "properties": {
    "gn:admin1_code":"30.0",
    "gn:admin2_code":"212.0",
    "gn:asciiname":"Ignacio Ramirez",
    "gn:country_code":"MX",
    "gn:dem":133,
    "gn:feature_class":"P",
    "gn:feature_code":"PPL",
    "gn:name":"Ignacio Ram\u00edrez",
    "gn:population":0,
    "gn:timezone":"America/Mexico_City",
    "iso:country":"MX",
    "name:spa_x_preferred":[
        "Ignacio Ram\u00edrez"
    ],
    "wof:name":"Ignacio Ramirez",
    "wof:placetype":"locality"
},
  "geometry": {"coordinates":[-95.73298,17.71448999999999],"type":"Point"}
}