{
  "type": "Feature",
  "properties": {
    "gn:admin1_code":"20",
    "gn:admin2_code":"125.0",
    "gn:asciiname":"San Antonio los Guajes",
    "gn:country_code":"MX",
    "gn:dem":1553,
    "gn:feature_class":"P",
    "gn:feature_code":"PPL",
    "gn:name":"San Antonio los Guajes",
    "gn:population":28,
    "gn:timezone":"America/Mexico_City",
    "iso:country":"MX",
    "name:spa_x_preferred":[
        "Los Guajes"
    ],
    "wof:name":"San Antonio los Guajes",
    "wof:placetype":"locality",
    "wof:population":28
},
  "geometry": {"coordinates":[-96.23667,16.51917000000001],"type":"Point"}
}