{
  "type": "Feature",
  "properties": {
    "gn:admin1_code":"28.0",
    "gn:admin2_code":"8.0",
    "gn:asciiname":"La Aguilas",
    "gn:country_code":"MX",
    "gn:dem":917,
    "gn:feature_class":"P",
    "gn:feature_code":"PPL",
    "gn:name":"La \u00c1guilas",
    "gn:population":0,
    "gn:timezone":"America/Monterrey",
    "iso:country":"MX",
    "name:spa_x_preferred":[
        "La \u00c1guilas"
    ],
    "name:spa_x_variant":[
        "Loma Prieta"
    ],
    "wof:name":"La Aguilas",
    "wof:placetype":"locality"
},
  "geometry": {"coordinates":[-98.5223,23.37048],"type":"Point"}
}