{
  "type": "Feature",
  "properties": {
    "gn:admin1_code":"19.0",
    "gn:admin2_code":"35.0",
    "gn:asciiname":"El Divisadero",
    "gn:country_code":"MX",
    "gn:dem":209,
    "gn:feature_class":"P",
    "gn:feature_code":"PPL",
    "gn:name":"El Divisadero",
    "gn:population":0,
    "gn:timezone":"America/Monterrey",
    "iso:country":"MX",
    "name:ceb_x_preferred":[
        "El Divisadero"
    ],
    "name:deu_x_preferred":[
        "El Divisadero"
    ],
    "name:ita_x_preferred":[
        "El Divisadero"
    ],
    "name:por_x_preferred":[
        "El Divisadero"
    ],
    "name:spa_x_preferred":[
        "El Divisadero"
    ],
    "name:zho_x_preferred":[
        "\u57c3\u723e\u8fea\u7dad\u85a9\u5fb7\u7f85"
    ],
    "wof:name":"El Divisadero",
    "wof:placetype":"locality"
},
  "geometry": {"coordinates":[-99.49636,26.02553],"type":"Point"}
}