{
  "type": "Feature",
  "properties": {
    "gn:admin1_code":"16",
    "gn:admin2_code":"49",
    "gn:asciiname":"La Concepcion",
    "gn:country_code":"MX",
    "gn:dem":1560,
    "gn:feature_class":"P",
    "gn:feature_code":"PPL",
    "gn:name":"La Concepci\u00f3n",
    "gn:population":16,
    "gn:timezone":"America/Mexico_City",
    "iso:country":"MX",
    "name:und_x_variant":[
        "La Concepci\u00f3n"
    ],
    "wof:name":"La Concepcion",
    "wof:placetype":"locality",
    "wof:population":16
},
  "geometry": {"coordinates":[-101.20639,19.41611],"type":"Point"}
}