{
  "type": "Feature",
  "properties": {
    "gn:admin1_code":"13",
    "gn:admin2_code":"57.0",
    "gn:asciiname":"Las Pintas",
    "gn:country_code":"MX",
    "gn:dem":2741,
    "gn:feature_class":"P",
    "gn:feature_code":"PPL",
    "gn:name":"Las Pintas",
    "gn:population":0,
    "gn:timezone":"America/Mexico_City",
    "iso:country":"MX",
    "name:spa_x_preferred":[
        "Las Pintas"
    ],
    "wof:name":"Las Pintas",
    "wof:placetype":"locality"
},
  "geometry": {"coordinates":[-98.42887,19.93485],"type":"Point"}
}