{
  "type": "Feature",
  "properties": {
    "gn:admin1_code":"2",
    "gn:admin2_code":"2.0",
    "gn:asciiname":"Los Manantiales",
    "gn:country_code":"MX",
    "gn:dem":11,
    "gn:feature_class":"P",
    "gn:feature_code":"PPL",
    "gn:name":"Los Manantiales",
    "gn:population":116,
    "gn:timezone":"America/Tijuana",
    "iso:country":"MX",
    "wof:name":"Los Manantiales",
    "wof:placetype":"locality",
    "wof:population":116
},
  "geometry": {"coordinates":[-115.27249999999999,32.61667],"type":"Point"}
}