{
  "type": "Feature",
  "properties": {
    "gn:admin1_code":"6",
    "gn:admin2_code":"27.0",
    "gn:asciiname":"Paraje El Aguaje",
    "gn:country_code":"MX",
    "gn:dem":2332,
    "gn:feature_class":"P",
    "gn:feature_code":"PPL",
    "gn:name":"Paraje El Aguaje",
    "gn:population":0,
    "gn:timezone":"America/Chihuahua",
    "iso:country":"MX",
    "name:spa_x_preferred":[
        "Paraje El Aguaje"
    ],
    "wof:name":"Paraje El Aguaje",
    "wof:placetype":"locality"
},
  "geometry": {"coordinates":[-106.95619000000001,27.14443],"type":"Point"}
}