{
  "type": "Feature",
  "properties": {
    "gn:admin1_code":"25",
    "gn:admin2_code":"15.0",
    "gn:asciiname":"Nueva Inglaterra",
    "gn:country_code":"MX",
    "gn:dem":191,
    "gn:feature_class":"P",
    "gn:feature_code":"PPL",
    "gn:name":"Nueva Inglaterra",
    "gn:population":0,
    "gn:timezone":"America/Mazatlan",
    "iso:country":"MX",
    "name:spa_x_preferred":[
        "Nueva Inglaterra"
    ],
    "name:und_x_variant":[
        "Nueva Inglaterro"
    ],
    "wof:name":"Nueva Inglaterra",
    "wof:placetype":"locality"
},
  "geometry": {"coordinates":[-107.89746,25.2305],"type":"Point"}
}