{
  "type": "Feature",
  "properties": {
    "gn:admin1_code":"26.0",
    "gn:admin2_code":"69.0",
    "gn:asciiname":"Los Otates",
    "gn:country_code":"MX",
    "gn:dem":873,
    "gn:feature_class":"P",
    "gn:feature_code":"PPL",
    "gn:name":"Los Otates",
    "gn:population":0,
    "gn:timezone":"America/Hermosillo",
    "iso:country":"MX",
    "name:spa_x_preferred":[
        "Los Otates"
    ],
    "wof:name":"Los Otates",
    "wof:placetype":"locality"
},
  "geometry": {"coordinates":[-109.14892999999999,28.47789],"type":"Point"}
}