{
  "type": "Feature",
  "properties": {
    "gn:admin1_code":"16",
    "gn:admin2_code":"68",
    "gn:asciiname":"Arboledas",
    "gn:country_code":"MX",
    "gn:dem":1563,
    "gn:feature_class":"P",
    "gn:feature_code":"PPL",
    "gn:name":"Arboledas",
    "gn:population":14,
    "gn:timezone":"America/Mexico_City",
    "iso:country":"MX",
    "name:ceb_x_preferred":[
        "Arboledas"
    ],
    "name:fra_x_preferred":[
        "Arboledas"
    ],
    "name:ita_x_preferred":[
        "Arboledas"
    ],
    "name:kat_x_preferred":[
        "\u10d0\u10e0\u10d1\u10dd\u10da\u10d4\u10d3\u10d0\u10e1\u10d8"
    ],
    "name:msa_x_preferred":[
        "Arboledas"
    ],
    "name:nld_x_preferred":[
        "Arboledas"
    ],
    "name:por_x_preferred":[
        "Arboledas"
    ],
    "name:swe_x_preferred":[
        "Arboledas"
    ],
    "name:tgl_x_preferred":[
        "Arboledas"
    ],
    "name:vie_x_preferred":[
        "Arboledas"
    ],
    "name:war_x_preferred":[
        "Arboledas"
    ],
    "name:zho_x_preferred":[
        "\u963f\u6c83\u840a\u9054\u65af"
    ],
    "wof:name":"Arboledas",
    "wof:placetype":"locality",
    "wof:population":14
},
  "geometry": {"coordinates":[-102.43000000000001,19.52361],"type":"Point"}
}