{
  "type": "Feature",
  "properties": {
    "gn:admin1_code":"16",
    "gn:admin2_code":"15",
    "gn:asciiname":"El Ocote",
    "gn:country_code":"MX",
    "gn:dem":1181,
    "gn:feature_class":"P",
    "gn:feature_code":"PPL",
    "gn:name":"El Ocote",
    "gn:population":30,
    "gn:timezone":"America/Mexico_City",
    "iso:country":"MX",
    "wof:name":"El Ocote",
    "wof:placetype":"locality",
    "wof:population":30
},
  "geometry": {"coordinates":[-103.23721999999999,18.83472],"type":"Point"}
}