{
  "type": "Feature",
  "properties": {
    "gn:admin1_code":"14",
    "gn:admin2_code":"59",
    "gn:asciiname":"La Llorona [Country Club]",
    "gn:country_code":"MX",
    "gn:dem":2103,
    "gn:feature_class":"P",
    "gn:feature_code":"PPL",
    "gn:name":"La Llorona [Country Club]",
    "gn:population":26,
    "gn:timezone":"America/Mexico_City",
    "iso:country":"MX",
    "wof:name":"La Llorona [Country Club]",
    "wof:placetype":"locality",
    "wof:population":26
},
  "geometry": {"coordinates":[-103.06361,19.91],"type":"Point"}
}