{
  "type": "Feature",
  "properties": {
    "gn:admin1_code":"3",
    "gn:admin2_code":"3.0",
    "gn:asciiname":"El Galeron",
    "gn:country_code":"MX",
    "gn:dem":17,
    "gn:feature_class":"P",
    "gn:feature_code":"PPL",
    "gn:name":"El Galer\u00f3n",
    "gn:population":8,
    "gn:timezone":"America/Mazatlan",
    "iso:country":"MX",
    "name:und_x_variant":[
        "El Galer\u00f3n"
    ],
    "wof:name":"El Galeron",
    "wof:placetype":"locality",
    "wof:population":8
},
  "geometry": {"coordinates":[-110.18316000000002,23.35082],"type":"Point"}
}