{
  "type": "Feature",
  "properties": {
    "gn:admin1_code":"27",
    "gn:admin2_code":"8.0",
    "gn:asciiname":"El Cruceno",
    "gn:country_code":"MX",
    "gn:dem":19,
    "gn:feature_class":"P",
    "gn:feature_code":"PPL",
    "gn:name":"El Cruce\u00f1o",
    "gn:population":8,
    "gn:timezone":"America/Mexico_City",
    "iso:country":"MX",
    "name:und_x_variant":[
        "El Cruce\u00f1o"
    ],
    "wof:name":"El Cruceno",
    "wof:placetype":"locality",
    "wof:population":8
},
  "geometry": {"coordinates":[-93.85833,17.82917],"type":"Point"}
}