{
  "type": "Feature",
  "properties": {
    "gn:admin1_code":"16",
    "gn:admin2_code":"10.0",
    "gn:asciiname":"El Paso de los Perros",
    "gn:country_code":"MX",
    "gn:dem":506,
    "gn:feature_class":"P",
    "gn:feature_code":"PPL",
    "gn:name":"El Paso de los Perros",
    "gn:population":5,
    "gn:timezone":"America/Mexico_City",
    "iso:country":"MX",
    "wof:name":"El Paso de los Perros",
    "wof:placetype":"locality",
    "wof:population":5
},
  "geometry": {"coordinates":[-102.68222,18.34889],"type":"Point"}
}