{
  "type": "Feature",
  "properties": {
    "gn:admin1_code":"25",
    "gn:admin2_code":"18.0",
    "gn:asciiname":"Las Aguamitas",
    "gn:country_code":"MX",
    "gn:dem":18,
    "gn:feature_class":"P",
    "gn:feature_code":"PPL",
    "gn:name":"Las Aguamitas",
    "gn:population":0,
    "gn:timezone":"America/Mazatlan",
    "iso:country":"MX",
    "name:spa_x_preferred":[
        "Las Aguamitas"
    ],
    "wof:name":"Las Aguamitas",
    "wof:placetype":"locality"
},
  "geometry": {"coordinates":[-107.50942000000001,24.69832],"type":"Point"}
}