{
  "type": "Feature",
  "properties": {
    "gn:admin1_code":"12.0",
    "gn:admin2_code":"68.0",
    "gn:asciiname":"Boca de Chutla",
    "gn:country_code":"MX",
    "gn:dem":17,
    "gn:feature_class":"P",
    "gn:feature_code":"PPL",
    "gn:name":"Boca de Chutla",
    "gn:population":0,
    "gn:timezone":"America/Mexico_City",
    "iso:country":"MX",
    "name:und_x_variant":[
        "Chutla",
        "Boca de Chutla"
    ],
    "wof:name":"Boca de Chutla",
    "wof:placetype":"locality"
},
  "geometry": {"coordinates":[-101.79592,17.88602000000001],"type":"Point"}
}