{
  "type": "Feature",
  "properties": {
    "gn:admin1_code":"32",
    "gn:admin2_code":"10.0",
    "gn:asciiname":"La Tapona",
    "gn:country_code":"MX",
    "gn:dem":2083,
    "gn:feature_class":"P",
    "gn:feature_code":"PPL",
    "gn:name":"La Tapona",
    "gn:population":0,
    "gn:timezone":"America/Mexico_City",
    "iso:country":"MX",
    "name:und_x_variant":[
        "La Zarona"
    ],
    "wof:name":"La Tapona",
    "wof:placetype":"locality"
},
  "geometry": {"coordinates":[-102.91151000000001,23.51544],"type":"Point"}
}