{
  "type": "Feature",
  "properties": {
    "gn:admin1_code":"5",
    "gn:admin2_code":"65.0",
    "gn:asciiname":"Brillante Buenavista",
    "gn:country_code":"MX",
    "gn:dem":71,
    "gn:feature_class":"P",
    "gn:feature_code":"PPL",
    "gn:name":"Brillante Buenavista",
    "gn:population":93,
    "gn:timezone":"America/Mexico_City",
    "iso:country":"MX",
    "wof:name":"Brillante Buenavista",
    "wof:placetype":"locality",
    "wof:population":93
},
  "geometry": {"coordinates":[-91.55249999999999,17.40278],"type":"Point"}
}