{
  "type": "Feature",
  "properties": {
    "gn:admin1_code":"5",
    "gn:admin2_code":"66",
    "gn:asciiname":"Santa Cruz (Corazon de Jesus)",
    "gn:country_code":"MX",
    "gn:dem":473,
    "gn:feature_class":"P",
    "gn:feature_code":"PPL",
    "gn:name":"Santa Cruz (Coraz\u00f3n de Jes\u00fas)",
    "gn:population":33,
    "gn:timezone":"America/Mexico_City",
    "iso:country":"MX",
    "name:und_x_variant":[
        "Santa Cruz (Coraz\u00f3n de Jes\u00fas)"
    ],
    "wof:name":"Santa Cruz (Corazon de Jesus)",
    "wof:placetype":"locality",
    "wof:population":33
},
  "geometry": {"coordinates":[-92.47917,17.06833],"type":"Point"}
}