{
  "type": "Feature",
  "properties": {
    "gn:admin1_code":"13",
    "gn:admin2_code":"62.0",
    "gn:asciiname":"Agua Bendita",
    "gn:country_code":"MX",
    "gn:dem":228,
    "gn:feature_class":"P",
    "gn:feature_code":"PPL",
    "gn:name":"Agua Bendita",
    "gn:population":0,
    "gn:timezone":"America/Mexico_City",
    "iso:country":"MX",
    "name:spa_x_preferred":[
        "Agua Bendita"
    ],
    "wof:name":"Agua Bendita",
    "wof:placetype":"locality"
},
  "geometry": {"coordinates":[-98.88129000000001,21.1311],"type":"Point"}
}