{
  "type": "Feature",
  "properties": {
    "gn:admin1_code":"30.0",
    "gn:admin2_code":"154.0",
    "gn:asciiname":"Treinta y Tres",
    "gn:country_code":"MX",
    "gn:dem":32,
    "gn:feature_class":"P",
    "gn:feature_code":"PPL",
    "gn:name":"Treinta y Tres",
    "gn:population":0,
    "gn:timezone":"America/Mexico_City",
    "iso:country":"MX",
    "name:ast_x_preferred":[
        "Treinta y Tres"
    ],
    "name:bul_x_preferred":[
        "\u0422\u0440\u0435\u0439\u043d\u0442\u0430 \u0438 \u0422\u0440\u0435\u0441"
    ],
    "name:cat_x_preferred":[
        "Treinta y Tres"
    ],
    "name:ceb_x_preferred":[
        "Treinta y Tres"
    ],
    "name:ces_x_preferred":[
        "Treinta y Tres"
    ],
    "name:dan_x_preferred":[
        "Treinta y Tres"
    ],
    "name:deu_x_preferred":[
        "Treinta y Tres"
    ],
    "name:fas_x_preferred":[
        "\u062a\u0631\u06cc\u0646\u062a\u0627 \u0627\u06cc \u062a\u0631\u0633"
    ],
    "name:fin_x_preferred":[
        "Treinta y Tres"
    ],
    "name:fra_x_preferred":[
        "Treinta y Tres"
    ],
    "name:glg_x_preferred":[
        "Treinta y Tres"
    ],
    "name:hrv_x_preferred":[
        "Treinta y Tres"
    ],
    "name:hye_x_preferred":[
        "\u054f\u0580\u0565\u0575\u0576\u057f\u0561 \u056b \u054f\u0580\u0565\u057d"
    ],
    "name:ita_x_preferred":[
        "Treinta y Tres"
    ],
    "name:jpn_x_preferred":[
        "\u30c8\u30ec\u30a4\u30f3\u30bf\u30fb\u30a4\u30fb\u30c8\u30ec\u30b9"
    ],
    "name:kat_x_preferred":[
        "\u10e2\u10e0\u10d4\u10d8\u10dc\u10e2\u10d0-\u10d8-\u10e2\u10e0\u10d4\u10e1\u10d8"
    ],
    "name:kor_x_preferred":[
        "\ud2b8\ub808\uc778\ud0c0\uc774\ud2b8\ub808\uc2a4"
    ],
    "name:nld_x_preferred":[
        "Treinta y Tres"
    ],
    "name:nor_x_preferred":[
        "Treinta y Tres"
    ],
    "name:pol_x_preferred":[
        "Treinta y Tres"
    ],
    "name:por_x_preferred":[
        "Treinta y Tres"
    ],
    "name:rus_x_preferred":[
        "\u0422\u0440\u0435\u0439\u043d\u0442\u0430-\u0438-\u0422\u0440\u0435\u0441"
    ],
    "name:slk_x_preferred":[
        "Treinta y Tres"
    ],
    "name:spa_x_preferred":[
        "Treinta y Tres"
    ],
    "name:ukr_x_preferred":[
        "\u0422\u0440\u0435\u0439\u043d\u0442\u0430-\u0456-\u0422\u0440\u0435\u0441"
    ],
    "name:urd_x_preferred":[
        "\u062a\u0631\u06cc\u0646\u062a\u0627 \u06cc \u062a\u0631\u06cc\u0633"
    ],
    "name:war_x_preferred":[
        "Treinta y Tres"
    ],
    "name:zho_x_preferred":[
        "\u4e09\u5341\u4e09\u4eba\u57ce"
    ],
    "wof:name":"Treinta y Tres",
    "wof:placetype":"locality"
},
  "geometry": {"coordinates":[-97.82382,21.43702],"type":"Point"}
}