{
  "type": "Feature",
  "properties": {
    "gn:admin1_code":"5",
    "gn:admin2_code":"12.0",
    "gn:asciiname":"El Penasco (Las Pilas)",
    "gn:country_code":"MX",
    "gn:dem":362,
    "gn:feature_class":"P",
    "gn:feature_code":"PPL",
    "gn:name":"El Pe\u00f1asco (Las Pilas)",
    "gn:population":8,
    "gn:timezone":"America/Mexico_City",
    "iso:country":"MX",
    "name:und_x_variant":[
        "El Pe\u00f1asco (Las Pilas)"
    ],
    "wof:name":"El Penasco (Las Pilas)",
    "wof:placetype":"locality",
    "wof:population":8
},
  "geometry": {"coordinates":[-93.31389,16.92917000000001],"type":"Point"}
}