{
  "type": "Feature",
  "properties": {
    "gn:admin1_code":"11",
    "gn:admin2_code":"32.0",
    "gn:asciiname":"Las Cajitas",
    "gn:country_code":"MX",
    "gn:dem":2106,
    "gn:feature_class":"P",
    "gn:feature_code":"PPL",
    "gn:name":"Las Cajitas",
    "gn:population":8,
    "gn:timezone":"America/Mexico_City",
    "iso:country":"MX",
    "wof:name":"Las Cajitas",
    "wof:placetype":"locality",
    "wof:population":8
},
  "geometry": {"coordinates":[-100.39139,20.96111],"type":"Point"}
}