{
  "type": "Feature",
  "properties": {
    "gn:admin1_code":"6.0",
    "gn:admin2_code":"12.0",
    "gn:asciiname":"Coherachi",
    "gn:country_code":"MX",
    "gn:dem":2300,
    "gn:feature_class":"P",
    "gn:feature_code":"PPL",
    "gn:name":"Coherachi",
    "gn:population":0,
    "gn:timezone":"America/Chihuahua",
    "iso:country":"MX",
    "name:spa_x_preferred":[
        "Coherachi"
    ],
    "wof:name":"Coherachi",
    "wof:placetype":"locality"
},
  "geometry": {"coordinates":[-107.02403,27.56099],"type":"Point"}
}