{
  "type": "Feature",
  "properties": {
    "gn:admin1_code":"14",
    "gn:admin2_code":"94",
    "gn:asciiname":"Amatan",
    "gn:country_code":"MX",
    "gn:dem":1073,
    "gn:feature_class":"P",
    "gn:feature_code":"PPL",
    "gn:name":"Amat\u00e1n",
    "gn:population":14,
    "gn:timezone":"America/Mexico_City",
    "iso:country":"MX",
    "name:und_x_variant":[
        "Amat\u00e1n"
    ],
    "wof:name":"Amatan",
    "wof:placetype":"locality",
    "wof:population":14
},
  "geometry": {"coordinates":[-103.98667,21.16417],"type":"Point"}
}