{
  "type": "Feature",
  "properties": {
    "gn:admin1_code":"10.0",
    "gn:admin2_code":"19.0",
    "gn:asciiname":"La Vega Redonda",
    "gn:country_code":"MX",
    "gn:dem":923,
    "gn:feature_class":"P",
    "gn:feature_code":"PPL",
    "gn:name":"La Vega Redonda",
    "gn:population":0,
    "gn:timezone":"America/Monterrey",
    "iso:country":"MX",
    "name:spa_x_preferred":[
        "La Vega Redonda"
    ],
    "wof:name":"La Vega Redonda",
    "wof:placetype":"locality"
},
  "geometry": {"coordinates":[-106.10193,24.69065],"type":"Point"}
}