{
  "type": "Feature",
  "properties": {
    "gn:admin1_code":"5",
    "gn:admin2_code":"5.0",
    "gn:asciiname":"San Antonio Tres Picos",
    "gn:country_code":"MX",
    "gn:dem":706,
    "gn:feature_class":"P",
    "gn:feature_code":"PPL",
    "gn:name":"San Antonio Tres Picos",
    "gn:population":929,
    "gn:timezone":"America/Mexico_City",
    "iso:country":"MX",
    "wof:name":"San Antonio Tres Picos",
    "wof:placetype":"locality",
    "wof:population":929
},
  "geometry": {"coordinates":[-92.86111,17.32389],"type":"Point"}
}