{
  "type": "Feature",
  "properties": {
    "gn:admin1_code":"15",
    "gn:admin2_code":"111.0",
    "gn:asciiname":"La Pena",
    "gn:country_code":"MX",
    "gn:dem":2413,
    "gn:feature_class":"P",
    "gn:feature_code":"PPL",
    "gn:name":"La Pe\u00f1a",
    "gn:population":430,
    "gn:timezone":"America/Mexico_City",
    "iso:country":"MX",
    "name:und_x_variant":[
        "La Pe\u00f1a"
    ],
    "wof:name":"La Pena",
    "wof:placetype":"locality",
    "wof:population":430
},
  "geometry": {"coordinates":[-100.167,19.36678],"type":"Point"}
}