{
  "type": "Feature",
  "properties": {
    "gn:admin1_code":"10",
    "gn:admin2_code":"35",
    "gn:asciiname":"El Cercado",
    "gn:country_code":"MX",
    "gn:dem":2559,
    "gn:feature_class":"P",
    "gn:feature_code":"PPL",
    "gn:name":"El Cercado",
    "gn:population":10,
    "gn:timezone":"America/Monterrey",
    "iso:country":"MX",
    "name:ceb_x_preferred":[
        "El Cercado"
    ],
    "name:ita_x_preferred":[
        "El Cercado"
    ],
    "name:por_x_preferred":[
        "El Cercado"
    ],
    "name:spa_x_preferred":[
        "El Cercado"
    ],
    "name:swe_x_preferred":[
        "El Cercado"
    ],
    "name:zho_x_preferred":[
        "\u57c3\u723e\u585e\u723e\u5361\u591a"
    ],
    "wof:name":"El Cercado",
    "wof:placetype":"locality",
    "wof:population":10
},
  "geometry": {"coordinates":[-106.32827,25.65984],"type":"Point"}
}