{
  "type": "Feature",
  "properties": {
    "gn:admin1_code":"15.0",
    "gn:asciiname":"Al Saucito",
    "gn:country_code":"MX",
    "gn:dem":743,
    "gn:feature_class":"P",
    "gn:feature_code":"PPL",
    "gn:name":"Al Saucito",
    "gn:population":0,
    "gn:timezone":"America/Mexico_City",
    "iso:country":"MX",
    "name:spa_x_preferred":[
        "Al Saucito"
    ],
    "wof:name":"Al Saucito",
    "wof:placetype":"locality"
},
  "geometry": {"coordinates":[-102.48781,18.19098],"type":"Point"}
}