{
  "type": "Feature",
  "properties": {
    "gn:admin1_code":"27",
    "gn:admin2_code":"6.0",
    "gn:asciiname":"Alianza Periferico",
    "gn:country_code":"MX",
    "gn:dem":16,
    "gn:feature_class":"P",
    "gn:feature_code":"PPL",
    "gn:name":"Alianza Perif\u00e9rico",
    "gn:population":222,
    "gn:timezone":"America/Mexico_City",
    "iso:country":"MX",
    "name:und_x_variant":[
        "Alianza Perif\u00e9rico"
    ],
    "wof:name":"Alianza Periferico",
    "wof:placetype":"locality",
    "wof:population":222
},
  "geometry": {"coordinates":[-93.19372,18.07767],"type":"Point"}
}