{
  "type": "Feature",
  "properties": {
    "gn:admin1_code":"31",
    "gn:admin2_code":"69.0",
    "gn:asciiname":"X-Pablan",
    "gn:country_code":"MX",
    "gn:dem":24,
    "gn:feature_class":"P",
    "gn:feature_code":"PPL",
    "gn:name":"X-Pablan",
    "gn:population":0,
    "gn:timezone":"America/Merida",
    "iso:country":"MX",
    "name:spa_x_preferred":[
        "X-Pablan"
    ],
    "name:spa_x_variant":[
        "Xplacam"
    ],
    "wof:name":"X-Pablan",
    "wof:placetype":"locality"
},
  "geometry": {"coordinates":[-89.12775000000001,20.5948],"type":"Point"}
}