{
  "type": "Feature",
  "properties": {
    "gn:admin1_code":"25.0",
    "gn:admin2_code":"4.0",
    "gn:asciiname":"El Platanar Chabelo",
    "gn:cc2":"MX",
    "gn:country_code":"MX",
    "gn:dem":153,
    "gn:feature_class":"P",
    "gn:feature_code":"PPL",
    "gn:name":"El Platanar Chabelo",
    "gn:population":3,
    "gn:timezone":"America/Mazatlan",
    "iso:country":"MX",
    "name:und_x_variant":[
        "Platanar",
        "El Platanar"
    ],
    "wof:name":"El Platanar Chabelo",
    "wof:placetype":"locality",
    "wof:population":3
},
  "geometry": {"coordinates":[-106.08856000000002,23.38336],"type":"Point"}
}