{
  "type": "Feature",
  "properties": {
    "gn:admin1_code":"11",
    "gn:admin2_code":"32",
    "gn:asciiname":"El Tapanco",
    "gn:country_code":"MX",
    "gn:dem":2252,
    "gn:feature_class":"P",
    "gn:feature_code":"PPL",
    "gn:name":"El Tapanco",
    "gn:population":9,
    "gn:timezone":"America/Mexico_City",
    "iso:country":"MX",
    "wof:name":"El Tapanco",
    "wof:placetype":"locality",
    "wof:population":9
},
  "geometry": {"coordinates":[-100.27028,21.03083],"type":"Point"}
}