{
  "type": "Feature",
  "properties": {
    "gn:admin1_code":"19",
    "gn:admin2_code":"17.0",
    "gn:asciiname":"Tuxpan",
    "gn:country_code":"MX",
    "gn:dem":1732,
    "gn:feature_class":"P",
    "gn:feature_code":"PPL",
    "gn:name":"Tuxpan",
    "gn:population":0,
    "gn:timezone":"America/Monterrey",
    "iso:country":"MX",
    "name:deu_x_preferred":[
        "Tuxpan"
    ],
    "name:fas_x_preferred":[
        "\u062a\u0648\u06a9\u0633\u067e\u0627\u0646"
    ],
    "name:fra_x_preferred":[
        "Tuxpan"
    ],
    "name:ind_x_preferred":[
        "Tuxpan"
    ],
    "name:nld_x_preferred":[
        "Tuxpan"
    ],
    "name:por_x_preferred":[
        "Tuxpan"
    ],
    "name:spa_x_preferred":[
        "Tuxpan"
    ],
    "wof:name":"Tuxpan",
    "wof:placetype":"locality"
},
  "geometry": {"coordinates":[-100.11427,24.82272],"type":"Point"}
}