{
  "type": "Feature",
  "properties": {
    "gn:admin1_code":"20",
    "gn:admin2_code":"339.0",
    "gn:asciiname":"El Molino",
    "gn:country_code":"MX",
    "gn:dem":2227,
    "gn:feature_class":"P",
    "gn:feature_code":"PPL",
    "gn:name":"El Molino",
    "gn:population":125,
    "gn:timezone":"America/Mexico_City",
    "iso:country":"MX",
    "wof:name":"El Molino",
    "wof:placetype":"locality",
    "wof:population":125
},
  "geometry": {"coordinates":[-97.44389,17.48667],"type":"Point"}
}