{
  "type": "Feature",
  "properties": {
    "gn:admin1_code":"5.0",
    "gn:admin2_code":"20.0",
    "gn:asciiname":"Nueva Delhi",
    "gn:country_code":"MX",
    "gn:dem":666,
    "gn:feature_class":"P",
    "gn:feature_code":"PPL",
    "gn:name":"Nueva Delhi",
    "gn:population":0,
    "gn:timezone":"America/Mexico_City",
    "iso:country":"MX",
    "name:spa_x_preferred":[
        "Nueva Delhi"
    ],
    "wof:name":"Nueva Delhi",
    "wof:placetype":"locality"
},
  "geometry": {"coordinates":[-92.81292000000001,15.91101],"type":"Point"}
}