{
  "type": "Feature",
  "properties": {
    "gn:admin1_code":"10",
    "gn:admin2_code":"5.0",
    "gn:asciiname":"Juan Jose Jaramillo",
    "gn:country_code":"MX",
    "gn:dem":1878,
    "gn:feature_class":"P",
    "gn:feature_code":"PPL",
    "gn:name":"Juan Jos\u00e9 Jaramillo",
    "gn:population":6,
    "gn:timezone":"America/Monterrey",
    "iso:country":"MX",
    "name:und_x_variant":[
        "Juan Jos\u00e9 Jaramillo"
    ],
    "wof:name":"Juan Jose Jaramillo",
    "wof:placetype":"locality",
    "wof:population":6
},
  "geometry": {"coordinates":[-104.62612,23.97529],"type":"Point"}
}