{
  "type": "Feature",
  "properties": {
    "gn:admin1_code":"14",
    "gn:admin2_code":"123.0",
    "gn:asciiname":"Atzcatlan",
    "gn:country_code":"MX",
    "gn:dem":1524,
    "gn:feature_class":"P",
    "gn:feature_code":"PPL",
    "gn:name":"Atzcatl\u00e1n",
    "gn:population":266,
    "gn:timezone":"America/Mexico_City",
    "iso:country":"MX",
    "name:und_x_variant":[
        "Atzcatl\u00e1n"
    ],
    "wof:name":"Atzcatlan",
    "wof:placetype":"locality",
    "wof:population":266
},
  "geometry": {"coordinates":[-102.97111,20.40306],"type":"Point"}
}