{
  "type": "Feature",
  "properties": {
    "gn:admin1_code":"24",
    "gn:admin2_code":"57.0",
    "gn:asciiname":"Coaquentla",
    "gn:country_code":"MX",
    "gn:dem":611,
    "gn:feature_class":"P",
    "gn:feature_code":"PPL",
    "gn:name":"Coaquentla",
    "gn:population":571,
    "gn:timezone":"America/Mexico_City",
    "iso:country":"MX",
    "wof:name":"Coaquentla",
    "wof:placetype":"locality",
    "wof:population":571
},
  "geometry": {"coordinates":[-98.895,21.31139],"type":"Point"}
}