{
  "type": "Feature",
  "properties": {
    "gn:admin1_code":"16",
    "gn:admin2_code":"57.0",
    "gn:asciiname":"La Huerta Perdida",
    "gn:country_code":"MX",
    "gn:dem":905,
    "gn:feature_class":"P",
    "gn:feature_code":"PPL",
    "gn:name":"La Huerta Perdida",
    "gn:population":0,
    "gn:timezone":"America/Mexico_City",
    "iso:country":"MX",
    "name:spa_x_preferred":[
        "La Huerta Perdida"
    ],
    "wof:name":"La Huerta Perdida",
    "wof:placetype":"locality"
},
  "geometry": {"coordinates":[-101.13249999999999,19.10095],"type":"Point"}
}