{
  "type": "Feature",
  "properties": {
    "gn:admin1_code":"26.0",
    "gn:admin2_code":"20.0",
    "gn:asciiname":"Calera",
    "gn:country_code":"MX",
    "gn:dem":500,
    "gn:feature_class":"P",
    "gn:feature_code":"PPL",
    "gn:name":"Calera",
    "gn:population":0,
    "gn:timezone":"America/Hermosillo",
    "iso:country":"MX",
    "wof:name":"Calera",
    "wof:placetype":"locality"
},
  "geometry": {"coordinates":[-110.86667,29.68333],"type":"Point"}
}