{
  "type": "Feature",
  "properties": {
    "gn:admin1_code":"12",
    "gn:admin2_code":"21.0",
    "gn:asciiname":"El Papayito",
    "gn:country_code":"MX",
    "gn:dem":295,
    "gn:feature_class":"P",
    "gn:feature_code":"PPL",
    "gn:name":"El Papayito",
    "gn:population":245,
    "gn:timezone":"America/Mexico_City",
    "iso:country":"MX",
    "wof:name":"El Papayito",
    "wof:placetype":"locality",
    "wof:population":245
},
  "geometry": {"coordinates":[-99.96653000000001,17.00289],"type":"Point"}
}