{
  "type": "Feature",
  "properties": {
    "gn:admin1_code":"7",
    "gn:admin2_code":"27.0",
    "gn:asciiname":"Los Bosques de Abajo",
    "gn:country_code":"MX",
    "gn:dem":1444,
    "gn:feature_class":"P",
    "gn:feature_code":"PPL",
    "gn:name":"Los Bosques de Abajo",
    "gn:population":0,
    "gn:timezone":"America/Monterrey",
    "iso:country":"MX",
    "name:spa_x_preferred":[
        "Los Bosques de Abajo"
    ],
    "name:und_x_variant":[
        "Las Bosques"
    ],
    "wof:name":"Los Bosques de Abajo",
    "wof:placetype":"locality"
},
  "geometry": {"coordinates":[-100.96187999999999,25.51231],"type":"Point"}
}