{
  "type": "Feature",
  "properties": {
    "gn:admin1_code":"6.0",
    "gn:asciiname":"Barranco Rosillo",
    "gn:country_code":"MX",
    "gn:dem":1853,
    "gn:feature_class":"P",
    "gn:feature_code":"PPL",
    "gn:name":"Barranco Rosillo",
    "gn:population":0,
    "gn:timezone":"America/Chihuahua",
    "iso:country":"MX",
    "name:spa_x_preferred":[
        "Barranco Rosillo"
    ],
    "wof:name":"Barranco Rosillo",
    "wof:placetype":"locality"
},
  "geometry": {"coordinates":[-105.77767,26.8762],"type":"Point"}
}