{
  "type": "Feature",
  "properties": {
    "gn:admin1_code":"2.0",
    "gn:admin2_code":"1.0",
    "gn:asciiname":"El Mazateco",
    "gn:country_code":"MX",
    "gn:dem":835,
    "gn:feature_class":"P",
    "gn:feature_code":"PPL",
    "gn:name":"El Mazateco",
    "gn:population":0,
    "gn:timezone":"America/Tijuana",
    "iso:country":"MX",
    "name:spa_x_preferred":[
        "El Mazateco"
    ],
    "wof:name":"El Mazateco",
    "wof:placetype":"locality"
},
  "geometry": {"coordinates":[-116.16553999999999,31.95885],"type":"Point"}
}