{
  "type": "Feature",
  "properties": {
    "gn:admin1_code":"30",
    "gn:admin2_code":"125.0",
    "gn:asciiname":"Loma Pelada",
    "gn:country_code":"MX",
    "gn:dem":255,
    "gn:feature_class":"P",
    "gn:feature_code":"PPL",
    "gn:name":"Loma Pelada",
    "gn:population":18,
    "gn:timezone":"America/Mexico_City",
    "iso:country":"MX",
    "wof:name":"Loma Pelada",
    "wof:placetype":"locality",
    "wof:population":18
},
  "geometry": {"coordinates":[-96.55916999999999,18.93472],"type":"Point"}
}