{
  "type": "Feature",
  "properties": {
    "gn:admin1_code":"5",
    "gn:admin2_code":"107.0",
    "gn:asciiname":"El Placer",
    "gn:country_code":"MX",
    "gn:dem":1236,
    "gn:feature_class":"P",
    "gn:feature_code":"PPL",
    "gn:name":"El Placer",
    "gn:population":8,
    "gn:timezone":"America/Mexico_City",
    "iso:country":"MX",
    "wof:name":"El Placer",
    "wof:placetype":"locality",
    "wof:population":8
},
  "geometry": {"coordinates":[-93.37472,15.96861],"type":"Point"}
}