{
  "type": "Feature",
  "properties": {
    "gn:admin1_code":"25",
    "gn:admin2_code":"2.0",
    "gn:asciiname":"Llano Grande",
    "gn:country_code":"MX",
    "gn:dem":23,
    "gn:feature_class":"P",
    "gn:feature_code":"PPL",
    "gn:name":"Llano Grande",
    "gn:population":6,
    "gn:timezone":"America/Mazatlan",
    "iso:country":"MX",
    "name:ceb_x_preferred":[
        "Llano Grande"
    ],
    "name:deu_x_preferred":[
        "Llano Grande"
    ],
    "name:fra_x_preferred":[
        "Llano Grande"
    ],
    "name:ita_x_preferred":[
        "Llano Grande"
    ],
    "name:spa_x_preferred":[
        "Llano Grande"
    ],
    "name:swe_x_preferred":[
        "Llano Grande"
    ],
    "wof:name":"Llano Grande",
    "wof:placetype":"locality",
    "wof:population":6
},
  "geometry": {"coordinates":[-108.15257,25.36034],"type":"Point"}
}