{
  "type": "Feature",
  "properties": {
    "gn:admin1_code":"6",
    "gn:admin2_code":"13.0",
    "gn:asciiname":"Los Marquez",
    "gn:country_code":"MX",
    "gn:dem":1421,
    "gn:feature_class":"P",
    "gn:feature_code":"PPL",
    "gn:name":"Los M\u00e1rquez",
    "gn:population":4,
    "gn:timezone":"America/Chihuahua",
    "iso:country":"MX",
    "name:und_x_variant":[
        "Los M\u00e1rquez"
    ],
    "wof:name":"Los Marquez",
    "wof:placetype":"locality",
    "wof:population":4
},
  "geometry": {"coordinates":[-107.98648,30.53669],"type":"Point"}
}