{
  "type": "Feature",
  "properties": {
    "gn:admin1_code":"12.0",
    "gn:admin2_code":"10.0",
    "gn:asciiname":"Cuapinaloyan",
    "gn:country_code":"MX",
    "gn:dem":2089,
    "gn:feature_class":"P",
    "gn:feature_code":"PPL",
    "gn:name":"Cuapinaloyan",
    "gn:population":0,
    "gn:timezone":"America/Mexico_City",
    "iso:country":"MX",
    "name:spa_x_preferred":[
        "Cuapinaloyan"
    ],
    "wof:name":"Cuapinaloyan",
    "wof:placetype":"locality"
},
  "geometry": {"coordinates":[-98.83911999999999,17.58034],"type":"Point"}
}