{
  "type": "Feature",
  "properties": {
    "gn:admin1_code":"26",
    "gn:admin2_code":"59.0",
    "gn:asciiname":"Miguel Hidalgo",
    "gn:country_code":"MX",
    "gn:dem":1287,
    "gn:feature_class":"P",
    "gn:feature_code":"PPL",
    "gn:name":"Miguel Hidalgo",
    "gn:population":0,
    "gn:timezone":"America/Hermosillo",
    "iso:country":"MX",
    "name:und_x_variant":[
        "San L\u00e1zaro"
    ],
    "wof:name":"Miguel Hidalgo",
    "wof:placetype":"locality"
},
  "geometry": {"coordinates":[-110.64279999999999,31.14543],"type":"Point"}
}