{
  "type": "Feature",
  "properties": {
    "gn:admin1_code":"10",
    "gn:admin2_code":"23.0",
    "gn:asciiname":"Golondrinas",
    "gn:country_code":"MX",
    "gn:dem":1946,
    "gn:feature_class":"P",
    "gn:feature_code":"PPL",
    "gn:name":"Golondrinas",
    "gn:population":149,
    "gn:timezone":"America/Monterrey",
    "iso:country":"MX",
    "name:ceb_x_preferred":[
        "Golondrinas"
    ],
    "name:srp_x_preferred":[
        "\u0413\u043e\u043b\u043e\u043d\u0434\u0440\u0438\u043d\u0430\u0441"
    ],
    "name:swe_x_preferred":[
        "Golondrinas"
    ],
    "wof:name":"Golondrinas",
    "wof:placetype":"locality",
    "wof:population":149
},
  "geometry": {"coordinates":[-105.5675,23.63667],"type":"Point"}
}