{
  "type": "Feature",
  "properties": {
    "gn:admin1_code":"30.0",
    "gn:admin2_code":"161.0",
    "gn:asciiname":"Tres de Oros",
    "gn:country_code":"MX",
    "gn:dem":43,
    "gn:feature_class":"P",
    "gn:feature_code":"PPL",
    "gn:name":"Tres de Oros",
    "gn:population":0,
    "gn:timezone":"America/Mexico_City",
    "iso:country":"MX",
    "name:spa_x_preferred":[
        "Tres de Oros"
    ],
    "wof:name":"Tres de Oros",
    "wof:placetype":"locality"
},
  "geometry": {"coordinates":[-98.41492,21.51365],"type":"Point"}
}