{
  "type": "Feature",
  "properties": {
    "gn:admin1_code":"21.0",
    "gn:asciiname":"El Duraznillo",
    "gn:country_code":"MX",
    "gn:dem":2376,
    "gn:feature_class":"P",
    "gn:feature_code":"PPL",
    "gn:name":"El Duraznillo",
    "gn:population":0,
    "gn:timezone":"America/Mexico_City",
    "iso:country":"MX",
    "name:spa_x_preferred":[
        "El Duraznillo"
    ],
    "wof:name":"El Duraznillo",
    "wof:placetype":"locality"
},
  "geometry": {"coordinates":[-97.63723,18.50642],"type":"Point"}
}