{
  "type": "Feature",
  "properties": {
    "gn:admin1_code":"31",
    "gn:admin2_code":"32.0",
    "gn:asciiname":"Pom",
    "gn:country_code":"MX",
    "gn:dem":16,
    "gn:feature_class":"P",
    "gn:feature_code":"PPL",
    "gn:name":"Pom",
    "gn:population":0,
    "gn:timezone":"America/Merida",
    "iso:country":"MX",
    "name:cat_x_preferred":[
        "Pom"
    ],
    "name:ceb_x_preferred":[
        "Pom"
    ],
    "name:nld_x_preferred":[
        "Pom"
    ],
    "name:spa_x_preferred":[
        "Pom"
    ],
    "name:srp_x_preferred":[
        "\u041f\u043e\u043c"
    ],
    "name:swe_x_preferred":[
        "Pom"
    ],
    "wof:name":"Pom",
    "wof:placetype":"locality"
},
  "geometry": {"coordinates":[-88.42109000000001,21.0591],"type":"Point"}
}