{
  "type": "Feature",
  "properties": {
    "gn:admin1_code":"21",
    "gn:admin2_code":"177.0",
    "gn:asciiname":"Tecalzingo",
    "gn:country_code":"MX",
    "gn:dem":1971,
    "gn:feature_class":"P",
    "gn:feature_code":"PPL",
    "gn:name":"Tecalzingo",
    "gn:population":0,
    "gn:timezone":"America/Mexico_City",
    "iso:country":"MX",
    "name:spa_x_preferred":[
        "Tecalzingo"
    ],
    "name:spa_x_variant":[
        "Tecaltzingo"
    ],
    "wof:name":"Tecalzingo",
    "wof:placetype":"locality"
},
  "geometry": {"coordinates":[-97.67214,18.71288],"type":"Point"}
}