{
  "type": "Feature",
  "properties": {
    "gn:admin1_code":"11.0",
    "gn:admin2_code":"17.0",
    "gn:asciiname":"Guadalupe de Rivera",
    "gn:country_code":"MX",
    "gn:dem":1717,
    "gn:feature_class":"P",
    "gn:feature_code":"PPL",
    "gn:name":"Guadalupe de Rivera",
    "gn:population":0,
    "gn:timezone":"America/Mexico_City",
    "iso:country":"MX",
    "name:spa_x_preferred":[
        "Guadalupe de Rivera"
    ],
    "name:und_x_variant":[
        "Guadalupe Tomel\u00f3pez",
        "Guadalupe"
    ],
    "wof:name":"Guadalupe de Rivera",
    "wof:placetype":"locality"
},
  "geometry": {"coordinates":[-101.46745,20.60499],"type":"Point"}
}