{
  "type": "Feature",
  "properties": {
    "gn:admin1_code":"5",
    "gn:admin2_code":"15",
    "gn:asciiname":"Numancia",
    "gn:country_code":"MX",
    "gn:dem":628,
    "gn:feature_class":"P",
    "gn:feature_code":"PPL",
    "gn:name":"Numancia",
    "gn:population":25,
    "gn:timezone":"America/Mexico_City",
    "iso:country":"MX",
    "wof:name":"Numancia",
    "wof:placetype":"locality",
    "wof:population":25
},
  "geometry": {"coordinates":[-92.16417,15.02361],"type":"Point"}
}