{
  "type": "Feature",
  "properties": {
    "gn:admin1_code":"14",
    "gn:admin2_code":"97",
    "gn:asciiname":"La Nueva Esperanza II (Los Cantaros) [Fraccionamiento]",
    "gn:country_code":"MX",
    "gn:dem":1564,
    "gn:feature_class":"P",
    "gn:feature_code":"PPL",
    "gn:name":"La Nueva Esperanza II (Los Cantaros) [Fraccionamiento]",
    "gn:population":22,
    "gn:timezone":"America/Mexico_City",
    "iso:country":"MX",
    "wof:name":"La Nueva Esperanza II (Los Cantaros) [Fraccionamiento]",
    "wof:placetype":"locality",
    "wof:population":22
},
  "geometry": {"coordinates":[-103.33917,20.50111],"type":"Point"}
}