{
  "type": "Feature",
  "properties": {
    "gn:admin1_code":"13",
    "gn:admin2_code":"71.0",
    "gn:asciiname":"Puerto de Vigas",
    "gn:country_code":"MX",
    "gn:dem":1658,
    "gn:feature_class":"P",
    "gn:feature_code":"PPL",
    "gn:name":"Puerto de Vigas",
    "gn:population":0,
    "gn:timezone":"America/Mexico_City",
    "iso:country":"MX",
    "name:spa_x_preferred":[
        "Puerto de Vigas"
    ],
    "wof:name":"Puerto de Vigas",
    "wof:placetype":"locality"
},
  "geometry": {"coordinates":[-98.97221999999999,20.84028],"type":"Point"}
}