{
  "type": "Feature",
  "properties": {
    "gn:admin1_code":"30.0",
    "gn:asciiname":"La Pena Blanca",
    "gn:country_code":"MX",
    "gn:dem":57,
    "gn:feature_class":"P",
    "gn:feature_code":"PPL",
    "gn:name":"La Pe\u00f1a Blanca",
    "gn:population":0,
    "gn:timezone":"America/Mexico_City",
    "iso:country":"MX",
    "name:spa_x_preferred":[
        "La Pe\u00f1a Blanca"
    ],
    "wof:name":"La Pena Blanca",
    "wof:placetype":"locality"
},
  "geometry": {"coordinates":[-95.82785,17.82945],"type":"Point"}
}