{
  "type": "Feature",
  "properties": {
    "gn:admin1_code":"30",
    "gn:admin2_code":"175.0",
    "gn:asciiname":"Los Palacios",
    "gn:country_code":"MX",
    "gn:dem":121,
    "gn:feature_class":"P",
    "gn:feature_code":"PPL",
    "gn:name":"Los Palacios",
    "gn:population":8,
    "gn:timezone":"America/Mexico_City",
    "iso:country":"MX",
    "wof:name":"Los Palacios",
    "wof:placetype":"locality",
    "wof:population":8
},
  "geometry": {"coordinates":[-97.47194,20.59472],"type":"Point"}
}