{
  "type": "Feature",
  "properties": {
    "gn:admin1_code":"30.0",
    "gn:asciiname":"El Olvido",
    "gn:country_code":"MX",
    "gn:dem":208,
    "gn:feature_class":"P",
    "gn:feature_code":"PPL",
    "gn:name":"El Olvido",
    "gn:population":0,
    "gn:timezone":"America/Mexico_City",
    "iso:country":"MX",
    "name:spa_x_preferred":[
        "El Olvido"
    ],
    "wof:name":"El Olvido",
    "wof:placetype":"locality"
},
  "geometry": {"coordinates":[-95.33374000000001,17.90525],"type":"Point"}
}