{
  "type": "Feature",
  "properties": {
    "gn:admin1_code":"12",
    "gn:admin2_code":"35.0",
    "gn:asciiname":"Ampliacion Jardin Pueblo Viejo",
    "gn:country_code":"MX",
    "gn:dem":813,
    "gn:feature_class":"P",
    "gn:feature_code":"PPL",
    "gn:name":"Ampliaci\u00f3n Jard\u00edn Pueblo Viejo",
    "gn:population":71,
    "gn:timezone":"America/Mexico_City",
    "iso:country":"MX",
    "name:und_x_variant":[
        "Ampliaci\u00f3n Jard\u00edn Pueblo Viejo"
    ],
    "wof:name":"Ampliacion Jardin Pueblo Viejo",
    "wof:placetype":"locality",
    "wof:population":71
},
  "geometry": {"coordinates":[-99.57556,18.36611],"type":"Point"}
}