{
  "type": "Feature",
  "properties": {
    "gn:admin1_code":"21",
    "gn:admin2_code":"75.0",
    "gn:asciiname":"Maloapan",
    "gn:country_code":"MX",
    "gn:dem":633,
    "gn:feature_class":"P",
    "gn:feature_code":"PPL",
    "gn:name":"Maloapan",
    "gn:population":122,
    "gn:timezone":"America/Mexico_City",
    "iso:country":"MX",
    "wof:name":"Maloapan",
    "wof:placetype":"locality",
    "wof:population":122
},
  "geometry": {"coordinates":[-97.36685,19.97597],"type":"Point"}
}