{
  "type": "Feature",
  "properties": {
    "gn:admin1_code":"14",
    "gn:admin2_code":"101.0",
    "gn:asciiname":"San Gaspar de las Flores",
    "gn:country_code":"MX",
    "gn:dem":1577,
    "gn:feature_class":"P",
    "gn:feature_code":"PPL",
    "gn:name":"San Gaspar de las Flores",
    "gn:population":0,
    "gn:timezone":"America/Mexico_City",
    "iso:country":"MX",
    "name:und_x_variant":[
        "San Gaspar"
    ],
    "wof:name":"San Gaspar de las Flores",
    "wof:placetype":"locality"
},
  "geometry": {"coordinates":[-103.24362000000001,20.67796],"type":"Point"}
}