{
  "type": "Feature",
  "properties": {
    "gn:admin1_code":"12.0",
    "gn:admin2_code":"29.0",
    "gn:asciiname":"Tezcal de la Cima",
    "gn:country_code":"MX",
    "gn:dem":1889,
    "gn:feature_class":"P",
    "gn:feature_code":"PPL",
    "gn:name":"Tezcal de la Cima",
    "gn:population":0,
    "gn:timezone":"America/Mexico_City",
    "iso:country":"MX",
    "name:spa_x_preferred":[
        "Tezcal de la Cima"
    ],
    "wof:name":"Tezcal de la Cima",
    "wof:placetype":"locality"
},
  "geometry": {"coordinates":[-99.88052,17.52162],"type":"Point"}
}