{
  "type": "Feature",
  "properties": {
    "gn:admin1_code":"12.0",
    "gn:admin2_code":"16.0",
    "gn:asciiname":"El Timbiriche",
    "gn:country_code":"MX",
    "gn:dem":220,
    "gn:feature_class":"P",
    "gn:feature_code":"PPL",
    "gn:name":"El Timbiriche",
    "gn:population":0,
    "gn:timezone":"America/Mexico_City",
    "iso:country":"MX",
    "name:spa_x_preferred":[
        "El Timbiriche"
    ],
    "wof:name":"El Timbiriche",
    "wof:placetype":"locality"
},
  "geometry": {"coordinates":[-101.755,18.30951],"type":"Point"}
}