{
  "type": "Feature",
  "properties": {
    "gn:admin1_code":"19",
    "gn:admin2_code":"16",
    "gn:asciiname":"Los Pena",
    "gn:country_code":"MX",
    "gn:dem":290,
    "gn:feature_class":"P",
    "gn:feature_code":"PPL",
    "gn:name":"Los Pe\u00f1a",
    "gn:population":22,
    "gn:timezone":"America/Monterrey",
    "iso:country":"MX",
    "name:und_x_variant":[
        "Los Pe\u00f1a"
    ],
    "wof:name":"Los Pena",
    "wof:placetype":"locality",
    "wof:population":22
},
  "geometry": {"coordinates":[-99.86614,25.76034],"type":"Point"}
}