{
  "type": "Feature",
  "properties": {
    "gn:admin1_code":"22",
    "gn:admin2_code":"14",
    "gn:asciiname":"Los Muertos",
    "gn:country_code":"MX",
    "gn:dem":2261,
    "gn:feature_class":"P",
    "gn:feature_code":"PPL",
    "gn:name":"Los Muertos",
    "gn:population":10,
    "gn:timezone":"America/Mexico_City",
    "iso:country":"MX",
    "wof:name":"Los Muertos",
    "wof:placetype":"locality",
    "wof:population":10
},
  "geometry": {"coordinates":[-100.54056,20.73528],"type":"Point"}
}