{
  "type": "Feature",
  "properties": {
    "gn:admin1_code":"5",
    "gn:admin2_code":"101.0",
    "gn:asciiname":"Toledo",
    "gn:country_code":"MX",
    "gn:dem":677,
    "gn:feature_class":"P",
    "gn:feature_code":"PPL",
    "gn:name":"Toledo",
    "gn:population":5,
    "gn:timezone":"America/Mexico_City",
    "iso:country":"MX",
    "wof:name":"Toledo",
    "wof:placetype":"locality",
    "wof:population":5
},
  "geometry": {"coordinates":[-93.21861,16.73667],"type":"Point"}
}