{
  "type": "Feature",
  "properties": {
    "gn:admin1_code":"12",
    "gn:admin2_code":"64.0",
    "gn:asciiname":"Cacanicua (Cacanicua de Abajo)",
    "gn:country_code":"MX",
    "gn:dem":693,
    "gn:feature_class":"P",
    "gn:feature_code":"PPL",
    "gn:name":"Cac\u00e1nicua (Cac\u00e1nicua de Abajo)",
    "gn:population":71,
    "gn:timezone":"America/Mexico_City",
    "iso:country":"MX",
    "name:und_x_variant":[
        "Cac\u00e1nicua (Cac\u00e1nicua de Abajo)"
    ],
    "wof:name":"Cacanicua (Cacanicua de Abajo)",
    "wof:placetype":"locality",
    "wof:population":71
},
  "geometry": {"coordinates":[-100.44316000000001,18.58427],"type":"Point"}
}