{
  "type": "Feature",
  "properties": {
    "gn:admin1_code":"13",
    "gn:admin2_code":"31.0",
    "gn:asciiname":"Agua Fria Grande",
    "gn:country_code":"MX",
    "gn:dem":1420,
    "gn:feature_class":"P",
    "gn:feature_code":"PPL",
    "gn:name":"Agua Fr\u00eda Grande",
    "gn:population":0,
    "gn:timezone":"America/Mexico_City",
    "iso:country":"MX",
    "name:spa_x_preferred":[
        "Agua Fr\u00eda Grande"
    ],
    "wof:name":"Agua Fria Grande",
    "wof:placetype":"locality"
},
  "geometry": {"coordinates":[-99.21141,20.9781],"type":"Point"}
}