{
  "type": "Feature",
  "properties": {
    "gn:admin1_code":"10",
    "gn:admin2_code":"26",
    "gn:asciiname":"El Puerto de la Travesia",
    "gn:country_code":"MX",
    "gn:dem":2531,
    "gn:feature_class":"P",
    "gn:feature_code":"PPL",
    "gn:name":"El Puerto de la Traves\u00eda",
    "gn:population":9,
    "gn:timezone":"America/Monterrey",
    "iso:country":"MX",
    "name:und_x_variant":[
        "El Puerto de la Traves\u00eda"
    ],
    "wof:name":"El Puerto de la Travesia",
    "wof:placetype":"locality",
    "wof:population":9
},
  "geometry": {"coordinates":[-105.56392,24.11084],"type":"Point"}
}