{
  "type": "Feature",
  "properties": {
    "gn:admin1_code":"12.0",
    "gn:admin2_code":"48.0",
    "gn:asciiname":"Las Trojes",
    "gn:country_code":"MX",
    "gn:dem":894,
    "gn:feature_class":"P",
    "gn:feature_code":"PPL",
    "gn:name":"Las Trojes",
    "gn:population":0,
    "gn:timezone":"America/Mexico_City",
    "iso:country":"MX",
    "name:spa_x_preferred":[
        "Las Trojes"
    ],
    "name:und_x_variant":[
        "Trojes"
    ],
    "wof:name":"Las Trojes",
    "wof:placetype":"locality"
},
  "geometry": {"coordinates":[-101.11369999999999,17.70694],"type":"Point"}
}