{
  "type": "Feature",
  "properties": {
    "gn:admin1_code":"20",
    "gn:admin2_code":"466.0",
    "gn:asciiname":"La Muralla",
    "gn:country_code":"MX",
    "gn:dem":349,
    "gn:feature_class":"P",
    "gn:feature_code":"PPL",
    "gn:name":"La Muralla",
    "gn:population":0,
    "gn:timezone":"America/Mexico_City",
    "iso:country":"MX",
    "name:spa_x_preferred":[
        "La Muralla"
    ],
    "wof:name":"La Muralla",
    "wof:placetype":"locality"
},
  "geometry": {"coordinates":[-97.84066,16.4924],"type":"Point"}
}