{
  "type": "Feature",
  "properties": {
    "gn:admin1_code":"11.0",
    "gn:asciiname":"La Haciendita",
    "gn:country_code":"MX",
    "gn:dem":1882,
    "gn:feature_class":"P",
    "gn:feature_code":"PPL",
    "gn:name":"La Haciendita",
    "gn:population":0,
    "gn:timezone":"America/Mexico_City",
    "iso:country":"MX",
    "name:spa_x_preferred":[
        "La Haciendita"
    ],
    "wof:name":"La Haciendita",
    "wof:placetype":"locality"
},
  "geometry": {"coordinates":[-101.22271000000001,20.36183],"type":"Point"}
}