{
  "type": "Feature",
  "properties": {
    "gn:admin1_code":"5",
    "gn:admin2_code":"99.0",
    "gn:asciiname":"Tepancoapan",
    "gn:country_code":"MX",
    "gn:dem":1532,
    "gn:feature_class":"P",
    "gn:feature_code":"PPL",
    "gn:name":"Tepancoapan",
    "gn:population":0,
    "gn:timezone":"America/Mexico_City",
    "iso:country":"MX",
    "name:spa_x_preferred":[
        "Tepancoapan"
    ],
    "name:und_x_variant":[
        "San Francisco Tepancuapan",
        "Tepancuapan",
        "La Tepancuap\u00e1",
        "Tepancuapa"
    ],
    "wof:name":"Tepancoapan",
    "wof:placetype":"locality"
},
  "geometry": {"coordinates":[-91.81672,16.12143],"type":"Point"}
}