{
  "type": "Feature",
  "properties": {
    "gn:admin1_code":"16",
    "gn:admin2_code":"50.0",
    "gn:asciiname":"Huaraqueo",
    "gn:country_code":"MX",
    "gn:dem":2278,
    "gn:feature_class":"P",
    "gn:feature_code":"PPL",
    "gn:name":"Huaraqueo",
    "gn:population":387,
    "gn:timezone":"America/Mexico_City",
    "iso:country":"MX",
    "wof:name":"Huaraqueo",
    "wof:placetype":"locality",
    "wof:population":387
},
  "geometry": {"coordinates":[-100.56305999999999,19.91889],"type":"Point"}
}