{
  "type": "Feature",
  "properties": {
    "gn:admin1_code":"12.0",
    "gn:admin2_code":"54.0",
    "gn:asciiname":"Santa Maria Sur",
    "gn:country_code":"MX",
    "gn:dem":528,
    "gn:feature_class":"P",
    "gn:feature_code":"PPL",
    "gn:name":"Santa Mar\u00eda Sur",
    "gn:population":0,
    "gn:timezone":"America/Mexico_City",
    "iso:country":"MX",
    "name:spa_x_preferred":[
        "Santa Mar\u00eda Sur"
    ],
    "wof:name":"Santa Maria Sur",
    "wof:placetype":"locality"
},
  "geometry": {"coordinates":[-100.44153,17.97952],"type":"Point"}
}