{
  "type": "Feature",
  "properties": {
    "gn:admin1_code":"25.0",
    "gn:admin2_code":"11.0",
    "gn:asciiname":"Cuatro Milpas",
    "gn:country_code":"MX",
    "gn:dem":24,
    "gn:feature_class":"P",
    "gn:feature_code":"PPL",
    "gn:name":"Cuatro Milpas",
    "gn:population":3,
    "gn:timezone":"America/Mazatlan",
    "iso:country":"MX",
    "name:spa_x_preferred":[
        "Cuatro Milpas"
    ],
    "name:und_x_variant":[
        "Campo Cuatro Milpas"
    ],
    "wof:name":"Cuatro Milpas",
    "wof:placetype":"locality",
    "wof:population":3
},
  "geometry": {"coordinates":[-108.56037999999999,25.63918],"type":"Point"}
}