{
  "type": "Feature",
  "properties": {
    "gn:admin1_code":"5",
    "gn:admin2_code":"17.0",
    "gn:asciiname":"Las Carmelitas",
    "gn:country_code":"MX",
    "gn:dem":938,
    "gn:feature_class":"P",
    "gn:feature_code":"PPL",
    "gn:name":"Las Carmelitas",
    "gn:population":129,
    "gn:timezone":"America/Mexico_City",
    "iso:country":"MX",
    "wof:name":"Las Carmelitas",
    "wof:placetype":"locality",
    "wof:population":129
},
  "geometry": {"coordinates":[-93.76889,16.85889],"type":"Point"}
}