{
  "type": "Feature",
  "properties": {
    "gn:admin1_code":"16",
    "gn:admin2_code":"34",
    "gn:asciiname":"Agua Escondida",
    "gn:country_code":"MX",
    "gn:dem":2572,
    "gn:feature_class":"P",
    "gn:feature_code":"PPL",
    "gn:name":"Agua Escondida",
    "gn:population":27,
    "gn:timezone":"America/Mexico_City",
    "iso:country":"MX",
    "wof:name":"Agua Escondida",
    "wof:placetype":"locality",
    "wof:population":27
},
  "geometry": {"coordinates":[-100.71861,19.49667],"type":"Point"}
}