{
  "type": "Feature",
  "properties": {
    "gn:admin1_code":"13",
    "gn:asciiname":"Rancho la Mora",
    "gn:country_code":"MX",
    "gn:dem":196,
    "gn:feature_class":"P",
    "gn:feature_code":"PPL",
    "gn:name":"Rancho la Mora",
    "gn:population":0,
    "gn:timezone":"America/Mexico_City",
    "iso:country":"MX",
    "name:spa_x_preferred":[
        "Rancho la Mora"
    ],
    "wof:name":"Rancho la Mora",
    "wof:placetype":"locality"
},
  "geometry": {"coordinates":[-98.65916,21.31534],"type":"Point"}
}