{
  "type": "Feature",
  "properties": {
    "gn:admin1_code":"5",
    "gn:admin2_code":"107",
    "gn:asciiname":"Rincon Ceibo",
    "gn:country_code":"MX",
    "gn:dem":804,
    "gn:feature_class":"P",
    "gn:feature_code":"PPL",
    "gn:name":"Rinc\u00f3n Ceibo",
    "gn:population":10,
    "gn:timezone":"America/Mexico_City",
    "iso:country":"MX",
    "name:und_x_variant":[
        "Rinc\u00f3n Ceibo"
    ],
    "wof:name":"Rincon Ceibo",
    "wof:placetype":"locality",
    "wof:population":10
},
  "geometry": {"coordinates":[-93.04944,16.05444],"type":"Point"}
}