{
  "type": "Feature",
  "properties": {
    "gn:admin1_code":"18.0",
    "gn:admin2_code":"15.0",
    "gn:asciiname":"Gavilan Chico",
    "gn:country_code":"MX",
    "gn:dem":10,
    "gn:feature_class":"P",
    "gn:feature_code":"PPL",
    "gn:name":"Gavil\u00e1n Chico",
    "gn:population":0,
    "gn:timezone":"America/Mazatlan",
    "iso:country":"MX",
    "name:spa_x_preferred":[
        "Gavil\u00e1n Chico"
    ],
    "wof:name":"Gavilan Chico",
    "wof:placetype":"locality"
},
  "geometry": {"coordinates":[-105.3258,21.81197],"type":"Point"}
}