{
  "type": "Feature",
  "properties": {
    "gn:admin1_code":"10",
    "gn:admin2_code":"12",
    "gn:asciiname":"Estacion Chocolate",
    "gn:country_code":"MX",
    "gn:dem":1414,
    "gn:feature_class":"P",
    "gn:feature_code":"PPL",
    "gn:name":"Estaci\u00f3n Chocolate",
    "gn:population":9,
    "gn:timezone":"America/Monterrey",
    "iso:country":"MX",
    "name:und_x_variant":[
        "Estaci\u00f3n Chocolate"
    ],
    "wof:name":"Estacion Chocolate",
    "wof:placetype":"locality",
    "wof:population":9
},
  "geometry": {"coordinates":[-103.63144,25.29418],"type":"Point"}
}