{
  "type": "Feature",
  "properties": {
    "gn:admin1_code":"5",
    "gn:admin2_code":"22.0",
    "gn:asciiname":"Jolsostetic",
    "gn:country_code":"MX",
    "gn:dem":1520,
    "gn:feature_class":"P",
    "gn:feature_code":"PPL",
    "gn:name":"Jolsostetic",
    "gn:population":164,
    "gn:timezone":"America/Mexico_City",
    "iso:country":"MX",
    "wof:name":"Jolsostetic",
    "wof:placetype":"locality",
    "wof:population":164
},
  "geometry": {"coordinates":[-92.62027999999999,17.01361],"type":"Point"}
}