{
  "type": "Feature",
  "properties": {
    "gn:admin1_code":"21",
    "gn:admin2_code":"27",
    "gn:asciiname":"Loma el Cuatillo",
    "gn:country_code":"MX",
    "gn:dem":1997,
    "gn:feature_class":"P",
    "gn:feature_code":"PPL",
    "gn:name":"Loma el Cuatillo",
    "gn:population":15,
    "gn:timezone":"America/Mexico_City",
    "iso:country":"MX",
    "wof:name":"Loma el Cuatillo",
    "wof:placetype":"locality",
    "wof:population":15
},
  "geometry": {"coordinates":[-97.51716999999999,18.20131],"type":"Point"}
}