{
  "type": "Feature",
  "properties": {
    "gn:admin1_code":"20",
    "gn:admin2_code":"422.0",
    "gn:asciiname":"Rio Verde",
    "gn:country_code":"MX",
    "gn:dem":2225,
    "gn:feature_class":"P",
    "gn:feature_code":"PPL",
    "gn:name":"R\u00edo Verde",
    "gn:population":0,
    "gn:timezone":"America/Mexico_City",
    "iso:country":"MX",
    "name:bre_x_preferred":[
        "Rio Verde"
    ],
    "name:ceb_x_preferred":[
        "Rio Verde"
    ],
    "name:deu_x_preferred":[
        "Rio Verde"
    ],
    "name:fra_x_preferred":[
        "Rio Verde"
    ],
    "name:ita_x_preferred":[
        "Rio Verde"
    ],
    "name:nds_x_preferred":[
        "Rio Verde"
    ],
    "name:nld_x_preferred":[
        "Rio Verde"
    ],
    "name:por_x_preferred":[
        "Rio Verde"
    ],
    "name:rus_x_preferred":[
        "\u0420\u0438\u043e-\u0412\u0435\u0440\u0434\u0435"
    ],
    "name:spa_x_preferred":[
        "R\u00edo Verde"
    ],
    "name:srp_x_preferred":[
        "\u0420\u0438\u043e \u0412\u0435\u0440\u0434\u0435"
    ],
    "name:swe_x_preferred":[
        "Rio Verde"
    ],
    "name:vol_x_preferred":[
        "Rio Verde"
    ],
    "wof:name":"Rio Verde",
    "wof:placetype":"locality"
},
  "geometry": {"coordinates":[-97.30515,17.57134],"type":"Point"}
}