{
  "type": "Feature",
  "properties": {
    "gn:admin1_code":"21.0",
    "gn:admin2_code":"19.0",
    "gn:asciiname":"Chapultepec",
    "gn:country_code":"MX",
    "gn:dem":1939,
    "gn:feature_class":"P",
    "gn:feature_code":"PPL",
    "gn:name":"Chapultepec",
    "gn:population":0,
    "gn:timezone":"America/Mexico_City",
    "iso:country":"MX",
    "name:ces_x_preferred":[
        "Chapultepec"
    ],
    "name:deu_x_preferred":[
        "Chapultepec"
    ],
    "name:epo_x_preferred":[
        "Chapultepec"
    ],
    "name:fin_x_preferred":[
        "Chapultepec"
    ],
    "name:fra_x_preferred":[
        "Chapultepec"
    ],
    "name:heb_x_preferred":[
        "\u05e6'\u05e4\u05d5\u05dc\u05d8\u05e4\u05e7"
    ],
    "name:hye_x_preferred":[
        "\u0549\u0561\u057a\u0578\u0582\u056c\u057f\u0565\u057a\u0565\u056f \u0566\u0562\u0578\u057d\u0561\u0575\u0563\u056b"
    ],
    "name:ind_x_preferred":[
        "Chapultepec"
    ],
    "name:ita_x_preferred":[
        "Chapultepec"
    ],
    "name:lit_x_preferred":[
        "\u010capultepekas"
    ],
    "name:nld_x_preferred":[
        "Chapultepec"
    ],
    "name:nor_x_preferred":[
        "Chapultepec"
    ],
    "name:por_x_preferred":[
        "Chapultepec"
    ],
    "name:rus_x_preferred":[
        "\u0427\u0430\u043f\u0443\u043b\u044c\u0442\u0435\u043f\u0435\u043a"
    ],
    "name:spa_x_preferred":[
        "Chapultepec"
    ],
    "name:swe_x_preferred":[
        "Chapultepec"
    ],
    "name:tur_x_preferred":[
        "Chapultepec"
    ],
    "name:ukr_x_preferred":[
        "\u0427\u0430\u043f\u0443\u043b\u044c\u0442\u0435\u043f\u0435\u043a"
    ],
    "name:vie_x_preferred":[
        "Chapultepec"
    ],
    "wof:name":"Chapultepec",
    "wof:placetype":"locality"
},
  "geometry": {"coordinates":[-98.4744,18.91522],"type":"Point"}
}