{
  "type": "Feature",
  "properties": {
    "gn:admin1_code":"21.0",
    "gn:admin2_code":"19.0",
    "gn:asciiname":"Chapultepec",
    "gn:country_code":"MX",
    "gn:dem":1939,
    "gn:feature_class":"P",
    "gn:feature_code":"PPL",
    "gn:name":"Chapultepec",
    "gn:population":0,
    "gn:timezone":"America/Mexico_City",
    "iso:country":"MX",
    "name:spa_x_preferred":[
        "Chapultepec"
    ],
    "wof:name":"Chapultepec",
    "wof:placetype":"locality"
},
  "geometry": {"coordinates":[-98.4744,18.91522],"type":"Point"}
}