{
  "type": "Feature",
  "properties": {
    "gn:admin1_code":"5",
    "gn:admin2_code":"38",
    "gn:asciiname":"El Paraiso las Delicias",
    "gn:country_code":"MX",
    "gn:dem":1730,
    "gn:feature_class":"P",
    "gn:feature_code":"PPL",
    "gn:name":"El Para\u00edso las Delicias",
    "gn:population":28,
    "gn:timezone":"America/Mexico_City",
    "iso:country":"MX",
    "name:und_x_variant":[
        "El Para\u00edso las Delicias"
    ],
    "wof:name":"El Paraiso las Delicias",
    "wof:placetype":"locality",
    "wof:population":28
},
  "geometry": {"coordinates":[-92.30472,16.69139],"type":"Point"}
}