{
  "type": "Feature",
  "properties": {
    "gn:admin1_code":"7",
    "gn:admin2_code":"11.0",
    "gn:asciiname":"Sacramento",
    "gn:country_code":"MX",
    "gn:dem":1211,
    "gn:feature_class":"P",
    "gn:feature_code":"PPL",
    "gn:name":"Sacramento",
    "gn:population":0,
    "gn:timezone":"America/Monterrey",
    "iso:country":"MX",
    "name:spa_x_preferred":[
        "Sacramento"
    ],
    "wof:name":"Sacramento",
    "wof:placetype":"locality"
},
  "geometry": {"coordinates":[-101.83323,25.63155],"type":"Point"}
}