{
  "type": "Feature",
  "properties": {
    "gn:admin1_code":"24",
    "gn:asciiname":"Saltillito",
    "gn:country_code":"MX",
    "gn:dem":2132,
    "gn:feature_class":"P",
    "gn:feature_code":"PPL",
    "gn:name":"Saltillito",
    "gn:population":0,
    "gn:timezone":"America/Mexico_City",
    "iso:country":"MX",
    "name:spa_x_preferred":[
        "Saltillito"
    ],
    "wof:name":"Saltillito",
    "wof:placetype":"locality"
},
  "geometry": {"coordinates":[-100.95416,24.34878],"type":"Point"}
}