{
  "type": "Feature",
  "properties": {
    "gn:admin1_code":"16",
    "gn:admin2_code":"8",
    "gn:asciiname":"La Cuidara",
    "gn:country_code":"MX",
    "gn:dem":484,
    "gn:feature_class":"P",
    "gn:feature_code":"PPL",
    "gn:name":"La Cuidara",
    "gn:population":21,
    "gn:timezone":"America/Mexico_City",
    "iso:country":"MX",
    "wof:name":"La Cuidara",
    "wof:placetype":"locality",
    "wof:population":21
},
  "geometry": {"coordinates":[-103.26944,18.42833],"type":"Point"}
}