{
  "type": "Feature",
  "properties": {
    "gn:admin1_code":"7.0",
    "gn:admin2_code":"26.0",
    "gn:asciiname":"El Diablo",
    "gn:country_code":"MX",
    "gn:dem":447,
    "gn:feature_class":"P",
    "gn:feature_code":"PPL",
    "gn:name":"El Diablo",
    "gn:population":0,
    "gn:timezone":"America/Monterrey",
    "iso:country":"MX",
    "name:spa_x_preferred":[
        "El Diablo"
    ],
    "wof:name":"El Diablo",
    "wof:placetype":"locality"
},
  "geometry": {"coordinates":[-100.92139,27.19899],"type":"Point"}
}