{
  "type": "Feature",
  "properties": {
    "gn:admin1_code":"5",
    "gn:admin2_code":"81.0",
    "gn:asciiname":"Amor de Dios",
    "gn:country_code":"MX",
    "gn:dem":590,
    "gn:feature_class":"P",
    "gn:feature_code":"PPL",
    "gn:name":"Amor de Dios",
    "gn:population":116,
    "gn:timezone":"America/Mexico_City",
    "iso:country":"MX",
    "wof:name":"Amor de Dios",
    "wof:placetype":"locality",
    "wof:population":116
},
  "geometry": {"coordinates":[-92.77667,17.18944],"type":"Point"}
}