{
  "type": "Feature",
  "properties": {
    "gn:admin1_code":"13",
    "gn:admin2_code":"79.0",
    "gn:asciiname":"Barrio Nuevo",
    "gn:country_code":"MX",
    "gn:dem":1551,
    "gn:feature_class":"P",
    "gn:feature_code":"PPL",
    "gn:name":"Barrio Nuevo",
    "gn:population":6,
    "gn:timezone":"America/Mexico_City",
    "iso:country":"MX",
    "wof:name":"Barrio Nuevo",
    "wof:placetype":"locality",
    "wof:population":6
},
  "geometry": {"coordinates":[-98.66786999999999,20.7699],"type":"Point"}
}