{
  "type": "Feature",
  "properties": {
    "gn:admin1_code":"11",
    "gn:admin2_code":"42.0",
    "gn:asciiname":"San Jose de Araceo",
    "gn:country_code":"MX",
    "gn:dem":1738,
    "gn:feature_class":"P",
    "gn:feature_code":"PPL",
    "gn:name":"San Jos\u00e9 de Araceo",
    "gn:population":675,
    "gn:timezone":"America/Mexico_City",
    "iso:country":"MX",
    "name:und_x_variant":[
        "San Jos\u00e9 de Araceo"
    ],
    "wof:name":"San Jose de Araceo",
    "wof:placetype":"locality",
    "wof:population":675
},
  "geometry": {"coordinates":[-101.16500000000001,20.37833],"type":"Point"}
}