{
  "type": "Feature",
  "properties": {
    "gn:admin1_code":"12",
    "gn:admin2_code":"79.0",
    "gn:asciiname":"El Caracol",
    "gn:country_code":"MX",
    "gn:dem":1878,
    "gn:feature_class":"P",
    "gn:feature_code":"PPL",
    "gn:name":"El Caracol",
    "gn:population":95,
    "gn:timezone":"America/Mexico_City",
    "iso:country":"MX",
    "wof:name":"El Caracol",
    "wof:placetype":"locality",
    "wof:population":95
},
  "geometry": {"coordinates":[-99.03946999999999,17.46623],"type":"Point"}
}