{
  "type": "Feature",
  "properties": {
    "gn:admin1_code":"26",
    "gn:admin2_code":"23.0",
    "gn:asciiname":"La Puerta de Cajon",
    "gn:country_code":"MX",
    "gn:dem":896,
    "gn:feature_class":"P",
    "gn:feature_code":"PPL",
    "gn:name":"La Puerta de Caj\u00f3n",
    "gn:population":0,
    "gn:timezone":"America/Hermosillo",
    "iso:country":"MX",
    "name:spa_x_preferred":[
        "La Puerta de Caj\u00f3n"
    ],
    "wof:name":"La Puerta de Cajon",
    "wof:placetype":"locality"
},
  "geometry": {"coordinates":[-109.69968,30.18182],"type":"Point"}
}