{
  "type": "Feature",
  "properties": {
    "gn:admin1_code":"17",
    "gn:admin2_code":"29.0",
    "gn:asciiname":"El Caudillo del Sur",
    "gn:country_code":"MX",
    "gn:dem":1219,
    "gn:feature_class":"P",
    "gn:feature_code":"PPL",
    "gn:name":"El Caudillo del Sur",
    "gn:population":631,
    "gn:timezone":"America/Mexico_City",
    "iso:country":"MX",
    "wof:name":"El Caudillo del Sur",
    "wof:placetype":"locality",
    "wof:population":631
},
  "geometry": {"coordinates":[-99.09084,18.86399],"type":"Point"}
}