{
  "type": "Feature",
  "properties": {
    "gn:admin1_code":"26",
    "gn:admin2_code":"68.0",
    "gn:asciiname":"Los Cuervos",
    "gn:country_code":"MX",
    "gn:dem":704,
    "gn:feature_class":"P",
    "gn:feature_code":"PPL",
    "gn:name":"Los Cuervos",
    "gn:population":0,
    "gn:timezone":"America/Hermosillo",
    "iso:country":"MX",
    "name:spa_x_preferred":[
        "Los Cuervos"
    ],
    "wof:name":"Los Cuervos",
    "wof:placetype":"locality"
},
  "geometry": {"coordinates":[-109.97778,29.05278],"type":"Point"}
}