{
  "type": "Feature",
  "properties": {
    "gn:admin1_code":"15",
    "gn:admin2_code":"47.0",
    "gn:asciiname":"Loma del Astillero",
    "gn:country_code":"MX",
    "gn:dem":2557,
    "gn:feature_class":"P",
    "gn:feature_code":"PPL",
    "gn:name":"Loma del Astillero",
    "gn:population":655,
    "gn:timezone":"America/Mexico_City",
    "iso:country":"MX",
    "wof:name":"Loma del Astillero",
    "wof:placetype":"locality",
    "wof:population":655
},
  "geometry": {"coordinates":[-99.67333000000001,19.58556],"type":"Point"}
}