{
  "type": "Feature",
  "properties": {
    "gn:admin1_code":"30",
    "gn:admin2_code":"193.0",
    "gn:asciiname":"Mata Cocuite",
    "gn:country_code":"MX",
    "gn:dem":27,
    "gn:feature_class":"P",
    "gn:feature_code":"PPL",
    "gn:name":"Mata Cocuite",
    "gn:population":0,
    "gn:timezone":"America/Mexico_City",
    "iso:country":"MX",
    "wof:name":"Mata Cocuite",
    "wof:placetype":"locality"
},
  "geometry": {"coordinates":[-96.21528000000001,19.12892],"type":"Point"}
}