{
  "type": "Feature",
  "properties": {
    "gn:admin1_code":"11",
    "gn:admin2_code":"20.0",
    "gn:asciiname":"Granja San Ignacio",
    "gn:country_code":"MX",
    "gn:dem":1793,
    "gn:feature_class":"P",
    "gn:feature_code":"PPL",
    "gn:name":"Granja San Ignacio",
    "gn:population":5,
    "gn:timezone":"America/Mexico_City",
    "iso:country":"MX",
    "wof:name":"Granja San Ignacio",
    "wof:placetype":"locality",
    "wof:population":5
},
  "geometry": {"coordinates":[-101.64361,21.02472],"type":"Point"}
}