{
  "type": "Feature",
  "properties": {
    "gn:admin1_code":"19.0",
    "gn:asciiname":"Morteros",
    "gn:country_code":"MX",
    "gn:dem":516,
    "gn:feature_class":"P",
    "gn:feature_code":"PPL",
    "gn:name":"Morteros",
    "gn:population":0,
    "gn:timezone":"America/Monterrey",
    "iso:country":"MX",
    "name:spa_x_preferred":[
        "Morteros"
    ],
    "wof:name":"Morteros",
    "wof:placetype":"locality"
},
  "geometry": {"coordinates":[-100.42271,25.96063],"type":"Point"}
}