{
  "type": "Feature",
  "properties": {
    "gn:admin1_code":"10",
    "gn:admin2_code":"14",
    "gn:asciiname":"Los Nopales",
    "gn:country_code":"MX",
    "gn:dem":1723,
    "gn:feature_class":"P",
    "gn:feature_code":"PPL",
    "gn:name":"Los Nopales",
    "gn:population":16,
    "gn:timezone":"America/Monterrey",
    "iso:country":"MX",
    "wof:name":"Los Nopales",
    "wof:placetype":"locality",
    "wof:population":16
},
  "geometry": {"coordinates":[-104.70023999999999,22.88198],"type":"Point"}
}