{
  "type": "Feature",
  "properties": {
    "gn:admin1_code":"30",
    "gn:admin2_code":"160.0",
    "gn:asciiname":"El Catorce (Buenavista Molino)",
    "gn:country_code":"MX",
    "gn:dem":19,
    "gn:feature_class":"P",
    "gn:feature_code":"PPL",
    "gn:name":"El Catorce (Buenavista Molino)",
    "gn:population":78,
    "gn:timezone":"America/Mexico_City",
    "iso:country":"MX",
    "wof:name":"El Catorce (Buenavista Molino)",
    "wof:placetype":"locality",
    "wof:population":78
},
  "geometry": {"coordinates":[-97.62582999999999,20.88361],"type":"Point"}
}