{
  "type": "Feature",
  "properties": {
    "gn:admin1_code":"9",
    "gn:admin2_code":"11",
    "gn:asciiname":"El Tetecon (El Solitario)",
    "gn:country_code":"MX",
    "gn:dem":2340,
    "gn:feature_class":"P",
    "gn:feature_code":"PPL",
    "gn:name":"El Tetecon (El Solitario)",
    "gn:population":9,
    "gn:timezone":"America/Mexico_City",
    "iso:country":"MX",
    "wof:name":"El Tetecon (El Solitario)",
    "wof:placetype":"locality",
    "wof:population":9
},
  "geometry": {"coordinates":[-99.02472,19.31917],"type":"Point"}
}