{
  "type": "Feature",
  "properties": {
    "gn:admin1_code":"32",
    "gn:admin2_code":"10.0",
    "gn:asciiname":"Ramos",
    "gn:country_code":"MX",
    "gn:dem":2102,
    "gn:feature_class":"P",
    "gn:feature_code":"PPL",
    "gn:name":"Ramos",
    "gn:population":0,
    "gn:timezone":"America/Mexico_City",
    "iso:country":"MX",
    "name:spa_x_preferred":[
        "Ramos"
    ],
    "wof:name":"Ramos",
    "wof:placetype":"locality"
},
  "geometry": {"coordinates":[-103.11803999999999,23.24784],"type":"Point"}
}