{
  "type": "Feature",
  "properties": {
    "gn:admin1_code":"16.0",
    "gn:admin2_code":"59.0",
    "gn:asciiname":"La Plana",
    "gn:country_code":"MX",
    "gn:dem":892,
    "gn:feature_class":"P",
    "gn:feature_code":"PPL",
    "gn:name":"La Plana",
    "gn:population":0,
    "gn:timezone":"America/Mexico_City",
    "iso:country":"MX",
    "name:spa_x_preferred":[
        "La Plana"
    ],
    "wof:name":"La Plana",
    "wof:placetype":"locality"
},
  "geometry": {"coordinates":[-101.83502,19.16995],"type":"Point"}
}