{
  "type": "Feature",
  "properties": {
    "gn:admin1_code":"6",
    "gn:admin2_code":"30.0",
    "gn:asciiname":"El Comanche",
    "gn:country_code":"MX",
    "gn:dem":2078,
    "gn:feature_class":"P",
    "gn:feature_code":"PPL",
    "gn:name":"El Comanche",
    "gn:population":6,
    "gn:timezone":"America/Chihuahua",
    "iso:country":"MX",
    "wof:name":"El Comanche",
    "wof:placetype":"locality",
    "wof:population":6
},
  "geometry": {"coordinates":[-108.06993,27.55714],"type":"Point"}
}