{
  "type": "Feature",
  "properties": {
    "gn:admin1_code":"26.0",
    "gn:admin2_code":"63.0",
    "gn:asciiname":"Casa Grande",
    "gn:country_code":"MX",
    "gn:dem":528,
    "gn:feature_class":"P",
    "gn:feature_code":"PPL",
    "gn:name":"Casa Grande",
    "gn:population":0,
    "gn:timezone":"America/Hermosillo",
    "iso:country":"MX",
    "name:spa_x_preferred":[
        "Casa Grande"
    ],
    "wof:name":"Casa Grande",
    "wof:placetype":"locality"
},
  "geometry": {"coordinates":[-109.58369,29.51403],"type":"Point"}
}