{
  "type": "Feature",
  "properties": {
    "gn:admin1_code":"3",
    "gn:admin2_code":"1.0",
    "gn:asciiname":"Santa Catalina",
    "gn:country_code":"MX",
    "gn:dem":593,
    "gn:feature_class":"P",
    "gn:feature_code":"PPL",
    "gn:name":"Santa Catalina",
    "gn:population":0,
    "gn:timezone":"America/Mazatlan",
    "iso:country":"MX",
    "name:cat_x_preferred":[
        "Santa Catalina"
    ],
    "name:ceb_x_preferred":[
        "Santa Catalina"
    ],
    "name:deu_x_preferred":[
        "Santa Catalina"
    ],
    "name:fra_x_preferred":[
        "Santa Catalina"
    ],
    "name:glg_x_preferred":[
        "Santa Catalina"
    ],
    "name:hye_x_preferred":[
        "\u054d\u0561\u0576\u057f\u0561 \u053f\u0561\u057f\u0561\u056c\u056b\u0576\u0561"
    ],
    "name:ilo_x_preferred":[
        "Santa Catalina"
    ],
    "name:ita_x_preferred":[
        "Santa Catalina"
    ],
    "name:kor_x_preferred":[
        "\uc0b0\ud0c0\uce74\ud0c8\ub9ac\ub098"
    ],
    "name:nld_x_preferred":[
        "Santa Catalina"
    ],
    "name:pol_x_preferred":[
        "Santa Catalina"
    ],
    "name:por_x_preferred":[
        "Santa Catalina"
    ],
    "name:rus_x_preferred":[
        "\u0421\u0430\u043d\u0442\u0430-\u041a\u0430\u0442\u0430\u043b\u0438\u043d\u0430"
    ],
    "name:sco_x_preferred":[
        "Santa Catalina"
    ],
    "name:spa_x_preferred":[
        "Santa Catalina"
    ],
    "name:swe_x_preferred":[
        "Santa Catalina"
    ],
    "name:vie_x_preferred":[
        "Santa Catalina"
    ],
    "name:war_x_preferred":[
        "Santa Catalina"
    ],
    "wof:name":"Santa Catalina",
    "wof:placetype":"locality"
},
  "geometry": {"coordinates":[-112.34999999999999,26.55],"type":"Point"}
}