{
  "type": "Feature",
  "properties": {
    "gn:admin1_code":"32",
    "gn:admin2_code":"38.0",
    "gn:asciiname":"El Salitrillo",
    "gn:country_code":"MX",
    "gn:dem":2010,
    "gn:feature_class":"P",
    "gn:feature_code":"PPL",
    "gn:name":"El Salitrillo",
    "gn:population":404,
    "gn:timezone":"America/Mexico_City",
    "iso:country":"MX",
    "wof:name":"El Salitrillo",
    "wof:placetype":"locality",
    "wof:population":404
},
  "geometry": {"coordinates":[-101.46194,22.62889],"type":"Point"}
}