{
  "type": "Feature",
  "properties": {
    "gn:admin1_code":"30",
    "gn:admin2_code":"126",
    "gn:asciiname":"La Loma del Mango (La Loma de los Morales)",
    "gn:country_code":"MX",
    "gn:dem":22,
    "gn:feature_class":"P",
    "gn:feature_code":"PPL",
    "gn:name":"La Loma del Mango (La Loma de los Morales)",
    "gn:population":19,
    "gn:timezone":"America/Mexico_City",
    "iso:country":"MX",
    "wof:name":"La Loma del Mango (La Loma de los Morales)",
    "wof:placetype":"locality",
    "wof:population":19
},
  "geometry": {"coordinates":[-96.39278,19.3275],"type":"Point"}
}