{
  "type": "Feature",
  "properties": {
    "gn:admin1_code":"20",
    "gn:admin2_code":"73.0",
    "gn:asciiname":"Santo Domingo del Estado",
    "gn:country_code":"MX",
    "gn:dem":2421,
    "gn:feature_class":"P",
    "gn:feature_code":"PPL",
    "gn:name":"Santo Domingo del Estado",
    "gn:population":0,
    "gn:timezone":"America/Mexico_City",
    "iso:country":"MX",
    "name:spa_x_preferred":[
        "Santo Domingo del Estado"
    ],
    "name:und_x_variant":[
        "Santo Domingo",
        "Chicahuaxtla"
    ],
    "wof:name":"Santo Domingo del Estado",
    "wof:placetype":"locality"
},
  "geometry": {"coordinates":[-97.84903,17.15497],"type":"Point"}
}