{
  "type": "Feature",
  "properties": {
    "gn:admin1_code":"20",
    "gn:admin2_code":"73.0",
    "gn:asciiname":"Santo Domingo del Estado",
    "gn:country_code":"MX",
    "gn:dem":2421,
    "gn:feature_class":"P",
    "gn:feature_code":"PPL",
    "gn:name":"Santo Domingo del Estado",
    "gn:population":0,
    "gn:timezone":"America/Mexico_City",
    "iso:country":"MX",
    "name:ceb_x_preferred":[
        "Santo Domingo del Estado"
    ],
    "name:sco_x_preferred":[
        "Santo Domingo del Estado"
    ],
    "name:spa_x_preferred":[
        "Santo Domingo del Estado"
    ],
    "name:srp_x_preferred":[
        "\u0421\u0430\u043d\u0442\u043e \u0414\u043e\u043c\u0438\u043d\u0433\u043e \u0434\u0435\u043b \u0415\u0441\u0442\u0430\u0434\u043e"
    ],
    "name:swe_x_preferred":[
        "Santo Domingo del Estado"
    ],
    "name:und_x_variant":[
        "Santo Domingo",
        "Chicahuaxtla"
    ],
    "wof:name":"Santo Domingo del Estado",
    "wof:placetype":"locality"
},
  "geometry": {"coordinates":[-97.84903,17.15497],"type":"Point"}
}