{
  "type": "Feature",
  "properties": {
    "gn:admin1_code":"12.0",
    "gn:asciiname":"Llano del Burrito",
    "gn:country_code":"MX",
    "gn:dem":2063,
    "gn:feature_class":"P",
    "gn:feature_code":"PPL",
    "gn:name":"Llano del Burrito",
    "gn:population":0,
    "gn:timezone":"America/Mexico_City",
    "iso:country":"MX",
    "name:spa_x_preferred":[
        "Llano del Burrito"
    ],
    "wof:name":"Llano del Burrito",
    "wof:placetype":"locality"
},
  "geometry": {"coordinates":[-98.46863999999999,17.2021],"type":"Point"}
}