{
  "type": "Feature",
  "properties": {
    "gn:admin1_code":"14.0",
    "gn:admin2_code":"69.0",
    "gn:asciiname":"Los Otatitos",
    "gn:country_code":"MX",
    "gn:dem":1725,
    "gn:feature_class":"P",
    "gn:feature_code":"PPL",
    "gn:name":"Los Otatitos",
    "gn:population":0,
    "gn:timezone":"America/Mexico_City",
    "iso:country":"MX",
    "name:spa_x_preferred":[
        "Los Otatitos"
    ],
    "wof:name":"Los Otatitos",
    "wof:placetype":"locality"
},
  "geometry": {"coordinates":[-102.81868,19.70932],"type":"Point"}
}