{
  "type": "Feature",
  "properties": {
    "gn:admin1_code":"32",
    "gn:admin2_code":"38.0",
    "gn:asciiname":"Huertas del Mezquite",
    "gn:country_code":"MX",
    "gn:dem":2141,
    "gn:feature_class":"P",
    "gn:feature_code":"PPL",
    "gn:name":"Huertas del Mezquite",
    "gn:population":449,
    "gn:timezone":"America/Mexico_City",
    "iso:country":"MX",
    "wof:name":"Huertas del Mezquite",
    "wof:placetype":"locality",
    "wof:population":449
},
  "geometry": {"coordinates":[-101.40917,22.26194],"type":"Point"}
}