{
  "type": "Feature",
  "properties": {
    "gn:admin1_code":"6.0",
    "gn:admin2_code":"48.0",
    "gn:asciiname":"Cienaga del Alamo",
    "gn:cc2":"MX",
    "gn:country_code":"MX",
    "gn:dem":2047,
    "gn:feature_class":"P",
    "gn:feature_code":"PPL",
    "gn:name":"Ci\u00e9naga del \u00c1lamo",
    "gn:population":0,
    "gn:timezone":"America/Chihuahua",
    "iso:country":"MX",
    "name:und_x_variant":[
        "Ci\u00e9nega de Alamo",
        "Ci\u00e9naga del \u00c1lamo"
    ],
    "wof:name":"Cienaga del Alamo",
    "wof:placetype":"locality"
},
  "geometry": {"coordinates":[-107.31667,29.13333],"type":"Point"}
}