{
  "type": "Feature",
  "properties": {
    "gn:admin1_code":"18.0",
    "gn:admin2_code":"5.0",
    "gn:asciiname":"Santa Maria de Ocotan",
    "gn:country_code":"MX",
    "gn:dem":1508,
    "gn:feature_class":"P",
    "gn:feature_code":"PPL",
    "gn:name":"Santa Maria de Ocot\u00e1n",
    "gn:population":0,
    "gn:timezone":"America/Mazatlan",
    "iso:country":"MX",
    "wof:name":"Santa Maria de Ocotan",
    "wof:placetype":"locality"
},
  "geometry": {"coordinates":[-105.18111,22.7025],"type":"Point"}
}