{
  "type": "Feature",
  "properties": {
    "gn:admin1_code":"16.0",
    "gn:admin2_code":"63.0",
    "gn:asciiname":"San Diego Amecuaro",
    "gn:country_code":"MX",
    "gn:dem":1774,
    "gn:feature_class":"P",
    "gn:feature_code":"PPL",
    "gn:name":"San Diego Am\u00e9cuaro",
    "gn:population":0,
    "gn:timezone":"America/Mexico_City",
    "iso:country":"MX",
    "name:spa_x_preferred":[
        "San Diego Am\u00e9cuaro"
    ],
    "wof:name":"San Diego Amecuaro",
    "wof:placetype":"locality"
},
  "geometry": {"coordinates":[-101.73804,19.98249],"type":"Point"}
}