{
  "type": "Feature",
  "properties": {
    "gn:admin1_code":"5",
    "gn:admin2_code":"38.0",
    "gn:asciiname":"Lazaro Cardenas",
    "gn:country_code":"MX",
    "gn:dem":2298,
    "gn:feature_class":"P",
    "gn:feature_code":"PPL",
    "gn:name":"L\u00e1zaro C\u00e1rdenas",
    "gn:population":0,
    "gn:timezone":"America/Mexico_City",
    "iso:country":"MX",
    "name:spa_x_preferred":[
        "L\u00e1zaro C\u00e1rdenas"
    ],
    "name:und_x_variant":[
        "Chilil"
    ],
    "wof:name":"Lazaro Cardenas",
    "wof:placetype":"locality"
},
  "geometry": {"coordinates":[-92.48885,16.67617000000001],"type":"Point"}
}