{
  "type": "Feature",
  "properties": {
    "gn:admin1_code":"28.0",
    "gn:admin2_code":"21.0",
    "gn:asciiname":"La Rosita",
    "gn:country_code":"MX",
    "gn:dem":95,
    "gn:feature_class":"P",
    "gn:feature_code":"PPL",
    "gn:name":"La Rosita",
    "gn:population":1,
    "gn:timezone":"America/Monterrey",
    "iso:country":"MX",
    "name:spa_x_preferred":[
        "La Rosita"
    ],
    "wof:name":"La Rosita",
    "wof:placetype":"locality",
    "wof:population":1
},
  "geometry": {"coordinates":[-98.92333000000001,22.53917],"type":"Point"}
}