{
  "type": "Feature",
  "properties": {
    "gn:admin1_code":"28.0",
    "gn:admin2_code":"37.0",
    "gn:asciiname":"Los Mosqueteros",
    "gn:country_code":"MX",
    "gn:dem":238,
    "gn:feature_class":"P",
    "gn:feature_code":"PPL",
    "gn:name":"Los Mosqueteros",
    "gn:population":0,
    "gn:timezone":"America/Monterrey",
    "iso:country":"MX",
    "name:spa_x_preferred":[
        "Los Mosqueteros"
    ],
    "wof:name":"Los Mosqueteros",
    "wof:placetype":"locality"
},
  "geometry": {"coordinates":[-98.27333,23.56528],"type":"Point"}
}