{
  "type": "Feature",
  "properties": {
    "gn:admin1_code":"5",
    "gn:admin2_code":"97",
    "gn:asciiname":"Las Lomitas",
    "gn:country_code":"MX",
    "gn:dem":10,
    "gn:feature_class":"P",
    "gn:feature_code":"PPL",
    "gn:name":"Las Lomitas",
    "gn:population":9,
    "gn:timezone":"America/Mexico_City",
    "iso:country":"MX",
    "name:ben_x_preferred":[
        "\u09b2\u09be\u09b8 \u09b2\u09cb\u09ae\u09bf\u09a4\u09be\u09b8"
    ],
    "name:deu_x_preferred":[
        "Las Lomitas"
    ],
    "name:ell_x_preferred":[
        "\u039b\u03b1\u03c2 \u039b\u03bf\u03bc\u03af\u03c4\u03b1\u03c2"
    ],
    "name:hin_x_preferred":[
        "\u0932\u093e\u0938 \u0932\u094b\u092e\u093f\u091f\u093e\u0938"
    ],
    "name:hun_x_preferred":[
        "Las Lomitas"
    ],
    "name:ind_x_preferred":[
        "Las Lomitas"
    ],
    "name:kor_x_preferred":[
        "\ub77c\uc2a4 \ub85c\ubbf8\ud0c0\uc2a4"
    ],
    "name:pol_x_preferred":[
        "Las Lomitas"
    ],
    "name:rus_x_preferred":[
        "\u041b\u0430\u0441-\u041b\u043e\u043c\u0438\u0442\u0430\u0441"
    ],
    "name:spa_x_preferred":[
        "Las Lomitas"
    ],
    "name:tur_x_preferred":[
        "Las Lomitas"
    ],
    "name:urd_x_preferred":[
        "\u0644\u0627\u0633 \u0644\u0648\u0645\u06cc\u0679\u0627\u0633"
    ],
    "name:vie_x_preferred":[
        "Las Lomitas"
    ],
    "name:zho_cn_x_preferred":[
        "\u62c9\u65af\u6d1b\u7c73\u5854\u65af"
    ],
    "name:zho_tw_x_preferred":[
        "\u62c9\u65af\u6d1b\u7c73\u5854\u65af"
    ],
    "wof:name":"Las Lomitas",
    "wof:placetype":"locality",
    "wof:population":9
},
  "geometry": {"coordinates":[-93.84833,16.06333],"type":"Point"}
}