{
  "type": "Feature",
  "properties": {
    "gn:admin1_code":"25",
    "gn:admin2_code":"9.0",
    "gn:asciiname":"El Bacho (Los Sabalos)",
    "gn:country_code":"MX",
    "gn:dem":8,
    "gn:feature_class":"P",
    "gn:feature_code":"PPL",
    "gn:name":"El Bacho (Los S\u00e1balos)",
    "gn:population":7,
    "gn:timezone":"America/Mazatlan",
    "iso:country":"MX",
    "name:und_x_variant":[
        "El Bacho (Los S\u00e1balos)"
    ],
    "wof:name":"El Bacho (Los Sabalos)",
    "wof:placetype":"locality",
    "wof:population":7
},
  "geometry": {"coordinates":[-105.7809,22.77263],"type":"Point"}
}