{
  "type": "Feature",
  "properties": {
    "gn:admin1_code":"30",
    "gn:admin2_code":"9",
    "gn:asciiname":"Juan Hernandez",
    "gn:country_code":"MX",
    "gn:dem":706,
    "gn:feature_class":"P",
    "gn:feature_code":"PPL",
    "gn:name":"Juan Hern\u00e1ndez",
    "gn:population":11,
    "gn:timezone":"America/Mexico_City",
    "iso:country":"MX",
    "name:und_x_variant":[
        "Juan Hern\u00e1ndez"
    ],
    "wof:name":"Juan Hernandez",
    "wof:placetype":"locality",
    "wof:population":11
},
  "geometry": {"coordinates":[-96.58778,19.7625],"type":"Point"}
}