{
  "type": "Feature",
  "properties": {
    "gn:admin1_code":"10",
    "gn:admin2_code":"34.0",
    "gn:asciiname":"El Durazno",
    "gn:country_code":"MX",
    "gn:dem":1398,
    "gn:feature_class":"P",
    "gn:feature_code":"PPL",
    "gn:name":"El Durazno",
    "gn:population":7,
    "gn:timezone":"America/Monterrey",
    "iso:country":"MX",
    "name:ceb_x_preferred":[
        "El Durazno"
    ],
    "name:swe_x_preferred":[
        "El Durazno"
    ],
    "wof:name":"El Durazno",
    "wof:placetype":"locality",
    "wof:population":7
},
  "geometry": {"coordinates":[-106.42116,24.36138],"type":"Point"}
}