{
  "type": "Feature",
  "properties": {
    "gn:admin1_code":"6",
    "gn:admin2_code":"29.0",
    "gn:asciiname":"Batayechi",
    "gn:country_code":"MX",
    "gn:dem":2122,
    "gn:feature_class":"P",
    "gn:feature_code":"PPL",
    "gn:name":"Batayechi",
    "gn:population":0,
    "gn:timezone":"America/Chihuahua",
    "iso:country":"MX",
    "name:spa_x_preferred":[
        "Batayechi"
    ],
    "name:und_x_variant":[
        "Batavechi"
    ],
    "wof:name":"Batayechi",
    "wof:placetype":"locality"
},
  "geometry": {"coordinates":[-106.94037,26.60017],"type":"Point"}
}