{
  "type": "Feature",
  "properties": {
    "gn:admin1_code":"6",
    "gn:admin2_code":"41.0",
    "gn:asciiname":"Rio las Casas",
    "gn:country_code":"MX",
    "gn:dem":1011,
    "gn:feature_class":"P",
    "gn:feature_code":"PPL",
    "gn:name":"R\u00edo las Casas",
    "gn:population":0,
    "gn:timezone":"America/Chihuahua",
    "iso:country":"MX",
    "name:spa_x_preferred":[
        "R\u00edo las Casas"
    ],
    "wof:name":"Rio las Casas",
    "wof:placetype":"locality"
},
  "geometry": {"coordinates":[-108.07294,27.80737],"type":"Point"}
}