{
  "type": "Feature",
  "properties": {
    "gn:admin1_code":"2",
    "gn:admin2_code":"1.0",
    "gn:asciiname":"Familia Cardenas",
    "gn:country_code":"MX",
    "gn:dem":80,
    "gn:feature_class":"P",
    "gn:feature_code":"PPL",
    "gn:name":"Familia C\u00e1rdenas",
    "gn:population":5,
    "gn:timezone":"America/Tijuana",
    "iso:country":"MX",
    "name:und_x_variant":[
        "Familia C\u00e1rdenas"
    ],
    "wof:name":"Familia Cardenas",
    "wof:placetype":"locality",
    "wof:population":5
},
  "geometry": {"coordinates":[-116.04277999999999,30.87306],"type":"Point"}
}