{
  "type": "Feature",
  "properties": {
    "gn:admin1_code":"26",
    "gn:admin2_code":"30",
    "gn:asciiname":"La Veinticinco",
    "gn:country_code":"MX",
    "gn:dem":46,
    "gn:feature_class":"P",
    "gn:feature_code":"PPL",
    "gn:name":"La Veinticinco",
    "gn:population":23,
    "gn:timezone":"America/Hermosillo",
    "iso:country":"MX",
    "wof:name":"La Veinticinco",
    "wof:placetype":"locality",
    "wof:population":23
},
  "geometry": {"coordinates":[-111.48888999999998,28.69778],"type":"Point"}
}