{
  "type": "Feature",
  "properties": {
    "gn:admin1_code":"12",
    "gn:admin2_code":"76.0",
    "gn:asciiname":"Ixtlahuatepec",
    "gn:country_code":"MX",
    "gn:dem":2427,
    "gn:feature_class":"P",
    "gn:feature_code":"PPL",
    "gn:name":"Ixtlahuatepec",
    "gn:population":97,
    "gn:timezone":"America/Mexico_City",
    "iso:country":"MX",
    "wof:name":"Ixtlahuatepec",
    "wof:placetype":"locality",
    "wof:population":97
},
  "geometry": {"coordinates":[-98.86621,17.33602999999999],"type":"Point"}
}