{
  "type": "Feature",
  "properties": {
    "gn:admin1_code":"10",
    "gn:admin2_code":"16.0",
    "gn:asciiname":"San Miguel del Porvenir",
    "gn:country_code":"MX",
    "gn:dem":1878,
    "gn:feature_class":"P",
    "gn:feature_code":"PPL",
    "gn:name":"San Miguel del Porvenir",
    "gn:population":0,
    "gn:timezone":"America/Monterrey",
    "iso:country":"MX",
    "name:spa_x_preferred":[
        "San Miguel del Porvenir"
    ],
    "name:spa_x_variant":[
        "Huijolas"
    ],
    "wof:name":"San Miguel del Porvenir",
    "wof:placetype":"locality"
},
  "geometry": {"coordinates":[-104.11329000000001,23.81839],"type":"Point"}
}