{
  "type": "Feature",
  "properties": {
    "gn:admin1_code":"14.0",
    "gn:admin2_code":"15.0",
    "gn:asciiname":"El Agua Salada",
    "gn:country_code":"MX",
    "gn:dem":1049,
    "gn:feature_class":"P",
    "gn:feature_code":"PPL",
    "gn:name":"El Agua Salada",
    "gn:population":0,
    "gn:timezone":"America/Mexico_City",
    "iso:country":"MX",
    "name:spa_x_preferred":[
        "El Agua Salada"
    ],
    "wof:name":"El Agua Salada",
    "wof:placetype":"locality"
},
  "geometry": {"coordinates":[-104.41338,19.77676],"type":"Point"}
}