{
  "type": "Feature",
  "properties": {
    "gn:admin1_code":"25.0",
    "gn:admin2_code":"11.0",
    "gn:asciiname":"Las Golondrinas",
    "gn:country_code":"MX",
    "gn:dem":9,
    "gn:feature_class":"P",
    "gn:feature_code":"PPL",
    "gn:name":"Las Golondrinas",
    "gn:population":0,
    "gn:timezone":"America/Mazatlan",
    "iso:country":"MX",
    "name:spa_x_preferred":[
        "Las Golondrinas"
    ],
    "wof:name":"Las Golondrinas",
    "wof:placetype":"locality"
},
  "geometry": {"coordinates":[-108.73386000000001,25.63482],"type":"Point"}
}