{
  "type": "Feature",
  "properties": {
    "gn:admin1_code":"30",
    "gn:admin2_code":"3.0",
    "gn:asciiname":"El Amigo",
    "gn:country_code":"MX",
    "gn:dem":80,
    "gn:feature_class":"P",
    "gn:feature_code":"PPL",
    "gn:name":"El Amigo",
    "gn:population":6,
    "gn:timezone":"America/Mexico_City",
    "iso:country":"MX",
    "wof:name":"El Amigo",
    "wof:placetype":"locality",
    "wof:population":6
},
  "geometry": {"coordinates":[-94.98417000000001,17.97611000000001],"type":"Point"}
}