{
  "type": "Feature",
  "properties": {
    "gn:admin1_code":"25",
    "gn:admin2_code":"14.0",
    "gn:asciiname":"Casas Blancas",
    "gn:country_code":"MX",
    "gn:dem":10,
    "gn:feature_class":"P",
    "gn:feature_code":"PPL",
    "gn:name":"Casas Blancas",
    "gn:population":5,
    "gn:timezone":"America/Mazatlan",
    "iso:country":"MX",
    "wof:name":"Casas Blancas",
    "wof:placetype":"locality",
    "wof:population":5
},
  "geometry": {"coordinates":[-106.14792,23.08438],"type":"Point"}
}