{
  "type": "Feature",
  "properties": {
    "gn:admin1_code":"26",
    "gn:admin2_code":"55.0",
    "gn:asciiname":"La Capital del Desierto",
    "gn:country_code":"MX",
    "gn:dem":17,
    "gn:feature_class":"P",
    "gn:feature_code":"PPL",
    "gn:name":"La Capital del Desierto",
    "gn:population":7,
    "gn:timezone":"America/Hermosillo",
    "iso:country":"MX",
    "wof:name":"La Capital del Desierto",
    "wof:placetype":"locality",
    "wof:population":7
},
  "geometry": {"coordinates":[-114.67861000000001,31.89833],"type":"Point"}
}