{
  "type": "Feature",
  "properties": {
    "gn:admin1_code":"14",
    "gn:admin2_code":"61",
    "gn:asciiname":"El Terrero",
    "gn:country_code":"MX",
    "gn:dem":1411,
    "gn:feature_class":"P",
    "gn:feature_code":"PPL",
    "gn:name":"El Terrero",
    "gn:population":19,
    "gn:timezone":"America/Mexico_City",
    "iso:country":"MX",
    "wof:name":"El Terrero",
    "wof:placetype":"locality",
    "wof:population":19
},
  "geometry": {"coordinates":[-104.00528,21.96389],"type":"Point"}
}