{
  "type": "Feature",
  "properties": {
    "gn:admin1_code":"20",
    "gn:admin2_code":"232.0",
    "gn:asciiname":"Cacahuatal",
    "gn:country_code":"MX",
    "gn:dem":111,
    "gn:feature_class":"P",
    "gn:feature_code":"PPL",
    "gn:name":"Cacahuatal",
    "gn:population":434,
    "gn:timezone":"America/Mexico_City",
    "iso:country":"MX",
    "wof:name":"Cacahuatal",
    "wof:placetype":"locality",
    "wof:population":434
},
  "geometry": {"coordinates":[-96.48583000000001,17.99389],"type":"Point"}
}