{
  "type": "Feature",
  "properties": {
    "gn:admin1_code":"26",
    "gn:admin2_code":"6.0",
    "gn:asciiname":"La Virgen",
    "gn:country_code":"MX",
    "gn:dem":1174,
    "gn:feature_class":"P",
    "gn:feature_code":"PPL",
    "gn:name":"La Virgen",
    "gn:population":0,
    "gn:timezone":"America/Hermosillo",
    "iso:country":"MX",
    "name:spa_x_preferred":[
        "La Virgen"
    ],
    "name:und_x_variant":[
        "Rancho La Virgen"
    ],
    "wof:name":"La Virgen",
    "wof:placetype":"locality"
},
  "geometry": {"coordinates":[-110.32678,30.59088],"type":"Point"}
}