{
  "type": "Feature",
  "properties": {
    "gn:admin1_code":"12",
    "gn:admin2_code":"18.0",
    "gn:asciiname":"Campanilla",
    "gn:country_code":"MX",
    "gn:dem":33,
    "gn:feature_class":"P",
    "gn:feature_code":"PPL",
    "gn:name":"Campanilla",
    "gn:population":121,
    "gn:timezone":"America/Mexico_City",
    "iso:country":"MX",
    "wof:name":"Campanilla",
    "wof:placetype":"locality",
    "wof:population":121
},
  "geometry": {"coordinates":[-98.90225,16.60156],"type":"Point"}
}