{
  "type": "Feature",
  "properties": {
    "gn:admin1_code":"16",
    "gn:admin2_code":"49.0",
    "gn:asciiname":"Las Truchitas",
    "gn:country_code":"MX",
    "gn:dem":1180,
    "gn:feature_class":"P",
    "gn:feature_code":"PPL",
    "gn:name":"Las Truchitas",
    "gn:population":7,
    "gn:timezone":"America/Mexico_City",
    "iso:country":"MX",
    "wof:name":"Las Truchitas",
    "wof:placetype":"locality",
    "wof:population":7
},
  "geometry": {"coordinates":[-101.08333,19.27833],"type":"Point"}
}