{
  "type": "Feature",
  "properties": {
    "gn:gn_country":"MX",
    "gn:gn_fcode":"PPL",
    "gn:gn_pop":0,
    "iso:country":"MX",
    "name:ceb_x_preferred":[
        "Gonzalez"
    ],
    "name:deu_x_preferred":[
        "Gonzalez"
    ],
    "name:ind_x_preferred":[
        "Gonzalez"
    ],
    "name:nld_x_preferred":[
        "Gonzalez"
    ],
    "name:spa_x_preferred":[
        "Gonz\u00e1lez"
    ],
    "name:srp_x_preferred":[
        "\u0413\u043e\u043d\u0437\u0430\u043b\u0435\u0437"
    ],
    "name:swe_x_preferred":[
        "Gonzalez"
    ],
    "name:vie_x_preferred":[
        "Gonzalez"
    ],
    "qs_pg:aaroncc":"MX",
    "qs_pg:gn_country":"MX",
    "qs_pg:gn_fcode":"PPL",
    "qs_pg:gn_pop":0,
    "qs_pg:name":"Gonzalez",
    "qs_pg:name_adm0":"M\u00e9xico",
    "qs_pg:name_adm1":"Tamaulipas",
    "qs_pg:photos_9r":0,
    "qs_pg:photos_sr":0,
    "qs_pg:pop_sr":0,
    "qs_pg:qs_pg_placetype":"locality",
    "qs_pg:qs_pg_placetype_gp":"Town",
    "qs_pg:woe_adm0":23424900,
    "woe:adm0_id":23424900,
    "woe:name_adm0":"M\u00e9xico",
    "woe:name_adm1":"Tamaulipas",
    "woe:placetype":"Town",
    "wof:name":"Gonzalez",
    "wof:placetype":"locality"
},
  "geometry": {"coordinates":[-98.65158,23.3734],"type":"Point"}
}