{
  "type": "Feature",
  "properties": {
    "gn:admin1_code":"12",
    "gn:admin2_code":"45.0",
    "gn:asciiname":"San Jose Tecomulco",
    "gn:country_code":"MX",
    "gn:dem":1594,
    "gn:feature_class":"P",
    "gn:feature_code":"PPL",
    "gn:name":"San Jos\u00e9 Tecomulco",
    "gn:population":23,
    "gn:timezone":"America/Mexico_City",
    "iso:country":"MX",
    "wof:name":"San Jose Tecomulco",
    "wof:placetype":"locality",
    "wof:population":23
},
  "geometry": {"coordinates":[-98.71561,17.86753],"type":"Point"}
}