{
  "type": "Feature",
  "properties": {
    "gn:admin1_code":"31",
    "gn:admin2_code":"55.0",
    "gn:asciiname":"Acansip",
    "gn:country_code":"MX",
    "gn:dem":12,
    "gn:feature_class":"P",
    "gn:feature_code":"PPL",
    "gn:name":"Acansip",
    "gn:population":0,
    "gn:timezone":"America/Merida",
    "iso:country":"MX",
    "wof:name":"Acansip",
    "wof:placetype":"locality"
},
  "geometry": {"coordinates":[-89.83333,20.58333],"type":"Point"}
}