{
  "type": "Feature",
  "properties": {
    "gn:admin1_code":"5",
    "gn:admin2_code":"50.0",
    "gn:asciiname":"Zaragoza",
    "gn:country_code":"MX",
    "gn:dem":41,
    "gn:feature_class":"P",
    "gn:feature_code":"PPL",
    "gn:name":"Zaragoza",
    "gn:population":0,
    "gn:timezone":"America/Mexico_City",
    "iso:country":"MX",
    "name:spa_x_preferred":[
        "Zaragoza"
    ],
    "name:spa_x_variant":[
        "Zaragoza Segunda Secci\u00f3n",
        "Segunda Secci\u00f3n"
    ],
    "wof:name":"Zaragoza",
    "wof:placetype":"locality"
},
  "geometry": {"coordinates":[-91.8141,17.60029],"type":"Point"}
}