{
  "type": "Feature",
  "properties": {
    "gn:admin1_code":"16",
    "gn:admin2_code":"97",
    "gn:asciiname":"Cahurica",
    "gn:country_code":"MX",
    "gn:dem":704,
    "gn:feature_class":"P",
    "gn:feature_code":"PPL",
    "gn:name":"Cahurica",
    "gn:population":14,
    "gn:timezone":"America/Mexico_City",
    "iso:country":"MX",
    "wof:name":"Cahurica",
    "wof:placetype":"locality",
    "wof:population":14
},
  "geometry": {"coordinates":[-101.31471999999999,19.01361],"type":"Point"}
}