{
  "type": "Feature",
  "properties": {
    "gn:admin1_code":"2.0",
    "gn:admin2_code":"1.0",
    "gn:asciiname":"Rancho Constancia de Garcia",
    "gn:country_code":"MX",
    "gn:dem":242,
    "gn:feature_class":"P",
    "gn:feature_code":"PPL",
    "gn:name":"Rancho Constancia de Garc\u00eda",
    "gn:population":5,
    "gn:timezone":"America/Tijuana",
    "iso:country":"MX",
    "name:spa_x_preferred":[
        "Estancia de Garc\u00eda"
    ],
    "wof:name":"Rancho Constancia de Garcia",
    "wof:placetype":"locality",
    "wof:population":5
},
  "geometry": {"coordinates":[-116.42677999999999,31.41972],"type":"Point"}
}