{
  "type": "Feature",
  "properties": {
    "gn:admin1_code":"32",
    "gn:admin2_code":"10.0",
    "gn:asciiname":"Manga de Vera",
    "gn:country_code":"MX",
    "gn:dem":2292,
    "gn:feature_class":"P",
    "gn:feature_code":"PPL",
    "gn:name":"Manga de Vera",
    "gn:population":0,
    "gn:timezone":"America/Mexico_City",
    "iso:country":"MX",
    "wof:name":"Manga de Vera",
    "wof:placetype":"locality"
},
  "geometry": {"coordinates":[-103.08333,22.96667],"type":"Point"}
}