{
  "type": "Feature",
  "properties": {
    "gn:admin1_code":"13",
    "gn:admin2_code":"77.0",
    "gn:asciiname":"La Pastoria",
    "gn:country_code":"MX",
    "gn:dem":2247,
    "gn:feature_class":"P",
    "gn:feature_code":"PPL",
    "gn:name":"La Pastor\u00eda",
    "gn:population":230,
    "gn:timezone":"America/Mexico_City",
    "iso:country":"MX",
    "name:und_x_variant":[
        "La Pastor\u00eda"
    ],
    "wof:name":"La Pastoria",
    "wof:placetype":"locality",
    "wof:population":230
},
  "geometry": {"coordinates":[-98.34236,20.08463],"type":"Point"}
}