{
  "type": "Feature",
  "properties": {
    "gn:admin1_code":"21",
    "gn:admin2_code":"27",
    "gn:asciiname":"Cruz Chica",
    "gn:country_code":"MX",
    "gn:dem":2235,
    "gn:feature_class":"P",
    "gn:feature_code":"PPL",
    "gn:name":"Cruz Chica",
    "gn:population":15,
    "gn:timezone":"America/Mexico_City",
    "iso:country":"MX",
    "wof:name":"Cruz Chica",
    "wof:placetype":"locality",
    "wof:population":15
},
  "geometry": {"coordinates":[-97.53051000000001,18.08048],"type":"Point"}
}