{
  "type": "Feature",
  "properties": {
    "gn:admin1_code":"6.0",
    "gn:asciiname":"El Dragon",
    "gn:country_code":"MX",
    "gn:dem":1194,
    "gn:feature_class":"P",
    "gn:feature_code":"PPL",
    "gn:name":"El Drag\u00f3n",
    "gn:population":0,
    "gn:timezone":"America/Chihuahua",
    "iso:country":"MX",
    "name:spa_x_preferred":[
        "El Drag\u00f3n"
    ],
    "wof:name":"El Dragon",
    "wof:placetype":"locality"
},
  "geometry": {"coordinates":[-105.35802,28.21236],"type":"Point"}
}