{
  "type": "Feature",
  "properties": {
    "gn:admin1_code":"28",
    "gn:admin2_code":"14.0",
    "gn:asciiname":"Los Tiernos",
    "gn:country_code":"MX",
    "gn:dem":129,
    "gn:feature_class":"P",
    "gn:feature_code":"PPL",
    "gn:name":"Los Tiernos",
    "gn:population":0,
    "gn:timezone":"America/Monterrey",
    "iso:country":"MX",
    "name:spa_x_preferred":[
        "Los Tiernos"
    ],
    "name:und_x_variant":[
        "Rancho Los Tiernos"
    ],
    "wof:name":"Los Tiernos",
    "wof:placetype":"locality"
},
  "geometry": {"coordinates":[-99.63484,27.21692],"type":"Point"}
}