{
  "type": "Feature",
  "properties": {
    "gn:admin1_code":"30.0",
    "gn:admin2_code":"121.0",
    "gn:asciiname":"Los Pescadores",
    "gn:country_code":"MX",
    "gn:dem":33,
    "gn:feature_class":"P",
    "gn:feature_code":"PPL",
    "gn:name":"Los Pescadores",
    "gn:population":0,
    "gn:timezone":"America/Mexico_City",
    "iso:country":"MX",
    "name:spa_x_preferred":[
        "Los Pescadores"
    ],
    "wof:name":"Los Pescadores",
    "wof:placetype":"locality"
},
  "geometry": {"coordinates":[-98.14333000000001,21.71333],"type":"Point"}
}