{
  "type": "Feature",
  "properties": {
    "gn:admin1_code":"6",
    "gn:admin2_code":"47.0",
    "gn:asciiname":"El Aterrizaje",
    "gn:country_code":"MX",
    "gn:dem":806,
    "gn:feature_class":"P",
    "gn:feature_code":"PPL",
    "gn:name":"El Aterrizaje",
    "gn:population":5,
    "gn:timezone":"America/Chihuahua",
    "iso:country":"MX",
    "wof:name":"El Aterrizaje",
    "wof:placetype":"locality",
    "wof:population":5
},
  "geometry": {"coordinates":[-108.52495999999999,28.16546],"type":"Point"}
}