{
  "type": "Feature",
  "properties": {
    "gn:admin1_code":"13",
    "gn:admin2_code":"42",
    "gn:asciiname":"Acatla",
    "gn:country_code":"MX",
    "gn:dem":987,
    "gn:feature_class":"P",
    "gn:feature_code":"PPL",
    "gn:name":"Acatla",
    "gn:population":17,
    "gn:timezone":"America/Mexico_City",
    "iso:country":"MX",
    "wof:name":"Acatla",
    "wof:placetype":"locality",
    "wof:population":17
},
  "geometry": {"coordinates":[-98.78176999999999,20.87411],"type":"Point"}
}