{
  "type": "Feature",
  "properties": {
    "gn:admin1_code":"26",
    "gn:admin2_code":"29.0",
    "gn:asciiname":"Los Petates [Restaurante]",
    "gn:country_code":"MX",
    "gn:dem":104,
    "gn:feature_class":"P",
    "gn:feature_code":"PPL",
    "gn:name":"Los Petates [Restaurante]",
    "gn:population":5,
    "gn:timezone":"America/Hermosillo",
    "iso:country":"MX",
    "wof:name":"Los Petates [Restaurante]",
    "wof:placetype":"locality",
    "wof:population":5
},
  "geometry": {"coordinates":[-111.02639000000001,28.25361],"type":"Point"}
}