{
  "type": "Feature",
  "properties": {
    "gn:admin1_code":"5",
    "gn:admin2_code":"67.0",
    "gn:asciiname":"San Antonio 2da. Seccion",
    "gn:country_code":"MX",
    "gn:dem":1485,
    "gn:feature_class":"P",
    "gn:feature_code":"PPL",
    "gn:name":"San Antonio 2da. Secci\u00f3n",
    "gn:population":288,
    "gn:timezone":"America/Mexico_City",
    "iso:country":"MX",
    "name:und_x_variant":[
        "San Antonio 2da. Secci\u00f3n"
    ],
    "wof:name":"San Antonio 2da. Seccion",
    "wof:placetype":"locality",
    "wof:population":288
},
  "geometry": {"coordinates":[-93.03417,17.21167],"type":"Point"}
}