{
  "type": "Feature",
  "properties": {
    "gn:admin1_code":"5",
    "gn:admin2_code":"2",
    "gn:asciiname":"6 de Mayo",
    "gn:country_code":"MX",
    "gn:dem":477,
    "gn:feature_class":"P",
    "gn:feature_code":"PPL",
    "gn:name":"6 de Mayo",
    "gn:population":27,
    "gn:timezone":"America/Mexico_City",
    "iso:country":"MX",
    "wof:name":"6 de Mayo",
    "wof:placetype":"locality",
    "wof:population":27
},
  "geometry": {"coordinates":[-92.88639000000001,16.50667],"type":"Point"}
}