{
  "type": "Feature",
  "properties": {
    "gn:admin1_code":"17",
    "gn:admin2_code":"4",
    "gn:asciiname":"Granja las Cebollas",
    "gn:country_code":"MX",
    "gn:dem":1236,
    "gn:feature_class":"P",
    "gn:feature_code":"PPL",
    "gn:name":"Granja las Cebollas",
    "gn:population":34,
    "gn:timezone":"America/Mexico_City",
    "iso:country":"MX",
    "wof:name":"Granja las Cebollas",
    "wof:placetype":"locality",
    "wof:population":34
},
  "geometry": {"coordinates":[-98.90167,18.71167],"type":"Point"}
}