{
  "type": "Feature",
  "properties": {
    "gn:admin1_code":"14",
    "gn:admin2_code":"65",
    "gn:asciiname":"El Tepalcate",
    "gn:country_code":"MX",
    "gn:dem":757,
    "gn:feature_class":"P",
    "gn:feature_code":"PPL",
    "gn:name":"El Tepalcate",
    "gn:population":10,
    "gn:timezone":"America/Mexico_City",
    "iso:country":"MX",
    "wof:name":"El Tepalcate",
    "wof:placetype":"locality",
    "wof:population":10
},
  "geometry": {"coordinates":[-103.32306,19.205],"type":"Point"}
}