{
  "type": "Feature",
  "properties": {
    "gn:admin1_code":"28",
    "gn:admin2_code":"29",
    "gn:asciiname":"El Sagrado Corazon de Jesus",
    "gn:country_code":"MX",
    "gn:dem":151,
    "gn:feature_class":"P",
    "gn:feature_code":"PPL",
    "gn:name":"El Sagrado Coraz\u00f3n de Jes\u00fas",
    "gn:population":16,
    "gn:timezone":"America/Monterrey",
    "iso:country":"MX",
    "name:und_x_variant":[
        "El Sagrado Coraz\u00f3n de Jes\u00fas"
    ],
    "wof:name":"El Sagrado Corazon de Jesus",
    "wof:placetype":"locality",
    "wof:population":16
},
  "geometry": {"coordinates":[-99.175,22.755],"type":"Point"}
}