{
  "type": "Feature",
  "properties": {
    "gn:admin1_code":"25",
    "gn:admin2_code":"14.0",
    "gn:asciiname":"El Palo",
    "gn:country_code":"MX",
    "gn:dem":27,
    "gn:feature_class":"P",
    "gn:feature_code":"PPL",
    "gn:name":"El Palo",
    "gn:population":5,
    "gn:timezone":"America/Mazatlan",
    "iso:country":"MX",
    "wof:name":"El Palo",
    "wof:placetype":"locality",
    "wof:population":5
},
  "geometry": {"coordinates":[-105.85684999999999,22.95314],"type":"Point"}
}