{
  "type": "Feature",
  "properties": {
    "gn:admin1_code":"17",
    "gn:asciiname":"Tepa",
    "gn:country_code":"MX",
    "gn:dem":2479,
    "gn:feature_class":"P",
    "gn:feature_code":"PPL",
    "gn:name":"Tepa",
    "gn:population":0,
    "gn:timezone":"America/Mexico_City",
    "iso:country":"MX",
    "name:ceb_x_preferred":[
        "Tepa"
    ],
    "name:deu_x_preferred":[
        "Tepa"
    ],
    "name:fin_x_preferred":[
        "Tepa"
    ],
    "name:fra_x_preferred":[
        "Tepa"
    ],
    "name:pol_x_preferred":[
        "Tepa"
    ],
    "name:spa_x_preferred":[
        "Tepa"
    ],
    "name:swe_x_preferred":[
        "Tepa"
    ],
    "wof:name":"Tepa",
    "wof:placetype":"locality"
},
  "geometry": {"coordinates":[-98.7341,19.66689],"type":"Point"}
}