{
  "type": "Feature",
  "properties": {
    "gn:admin1_code":"25",
    "gn:admin2_code":"6",
    "gn:asciiname":"El Rincon de los Monzon",
    "gn:country_code":"MX",
    "gn:dem":80,
    "gn:feature_class":"P",
    "gn:feature_code":"PPL",
    "gn:name":"El Rinc\u00f3n de los Monz\u00f3n",
    "gn:population":37,
    "gn:timezone":"America/Mazatlan",
    "iso:country":"MX",
    "name:und_x_variant":[
        "El Rinc\u00f3n de los Monz\u00f3n"
    ],
    "wof:name":"El Rincon de los Monzon",
    "wof:placetype":"locality",
    "wof:population":37
},
  "geometry": {"coordinates":[-107.39386,25.03518],"type":"Point"}
}