{
  "type": "Feature",
  "properties": {
    "gn:admin1_code":"22",
    "gn:admin2_code":"14.0",
    "gn:asciiname":"Seccion Noroeste de la Gotera",
    "gn:country_code":"MX",
    "gn:dem":2147,
    "gn:feature_class":"P",
    "gn:feature_code":"PPL",
    "gn:name":"Secci\u00f3n Noroeste de la Gotera",
    "gn:population":9,
    "gn:timezone":"America/Mexico_City",
    "iso:country":"MX",
    "name:und_x_variant":[
        "Secci\u00f3n Noroeste de la Gotera"
    ],
    "wof:name":"Seccion Noroeste de la Gotera",
    "wof:placetype":"locality",
    "wof:population":9
},
  "geometry": {"coordinates":[-100.38139,20.86861],"type":"Point"}
}