{
  "type": "Feature",
  "properties": {
    "gn:admin1_code":"16.0",
    "gn:admin2_code":"96.0",
    "gn:asciiname":"El Caulote",
    "gn:country_code":"MX",
    "gn:dem":965,
    "gn:feature_class":"P",
    "gn:feature_code":"PPL",
    "gn:name":"El Caulote",
    "gn:population":0,
    "gn:timezone":"America/Mexico_City",
    "iso:country":"MX",
    "name:spa_x_preferred":[
        "El Caulote"
    ],
    "wof:name":"El Caulote",
    "wof:placetype":"locality"
},
  "geometry": {"coordinates":[-102.39257000000001,18.50586],"type":"Point"}
}