{
  "type": "Feature",
  "properties": {
    "gn:admin1_code":"21",
    "gn:admin2_code":"115",
    "gn:asciiname":"Autopista Puebla Orizaba Kilometro 191",
    "gn:country_code":"MX",
    "gn:dem":2192,
    "gn:feature_class":"P",
    "gn:feature_code":"PPL",
    "gn:name":"Autopista Puebla Orizaba Kil\u00f3metro 191",
    "gn:population":22,
    "gn:timezone":"America/Mexico_City",
    "iso:country":"MX",
    "name:und_x_variant":[
        "Autopista Puebla Orizaba Kil\u00f3metro 191"
    ],
    "wof:name":"Autopista Puebla Orizaba Kilometro 191",
    "wof:placetype":"locality",
    "wof:population":22
},
  "geometry": {"coordinates":[-97.59764,18.88988],"type":"Point"}
}