{
  "type": "Feature",
  "properties": {
    "gn:admin1_code":"5",
    "gn:admin2_code":"87.0",
    "gn:asciiname":"Dorado Viejo",
    "gn:country_code":"MX",
    "gn:dem":30,
    "gn:feature_class":"P",
    "gn:feature_code":"PPL",
    "gn:name":"Dorado Viejo",
    "gn:population":0,
    "gn:timezone":"America/Mexico_City",
    "iso:country":"MX",
    "name:spa_x_preferred":[
        "Dorado Viejo"
    ],
    "name:und_x_variant":[
        "Dorado",
        "Finca El Dorado",
        "El Dorado",
        "El Dorado Viejo"
    ],
    "wof:name":"Dorado Viejo",
    "wof:placetype":"locality"
},
  "geometry": {"coordinates":[-92.20323,14.70383],"type":"Point"}
}