{
  "type": "Feature",
  "properties": {
    "gn:admin1_code":"5",
    "gn:admin2_code":"97.0",
    "gn:asciiname":"El Borbollon",
    "gn:country_code":"MX",
    "gn:dem":6,
    "gn:feature_class":"P",
    "gn:feature_code":"PPL",
    "gn:name":"El Borboll\u00f3n",
    "gn:population":6,
    "gn:timezone":"America/Mexico_City",
    "iso:country":"MX",
    "name:und_x_variant":[
        "El Borboll\u00f3n"
    ],
    "wof:name":"El Borbollon",
    "wof:placetype":"locality",
    "wof:population":6
},
  "geometry": {"coordinates":[-93.64306000000001,15.845],"type":"Point"}
}