{
  "type": "Feature",
  "properties": {
    "gn:admin1_code":"22",
    "gn:admin2_code":"16.0",
    "gn:asciiname":"Rancho El Siete",
    "gn:country_code":"MX",
    "gn:dem":1910,
    "gn:feature_class":"P",
    "gn:feature_code":"PPL",
    "gn:name":"Rancho El Siete",
    "gn:population":0,
    "gn:timezone":"America/Mexico_City",
    "iso:country":"MX",
    "name:spa_x_preferred":[
        "Rancho El Siete"
    ],
    "wof:name":"Rancho El Siete",
    "wof:placetype":"locality"
},
  "geometry": {"coordinates":[-99.95862,20.44907000000001],"type":"Point"}
}