{
  "type": "Feature",
  "properties": {
    "gn:admin1_code":"21.0",
    "gn:admin2_code":"47.0",
    "gn:asciiname":"El Copal",
    "gn:country_code":"MX",
    "gn:dem":1182,
    "gn:feature_class":"P",
    "gn:feature_code":"PPL",
    "gn:name":"El Copal",
    "gn:population":0,
    "gn:timezone":"America/Mexico_City",
    "iso:country":"MX",
    "name:spa_x_preferred":[
        "El Copal"
    ],
    "wof:name":"El Copal",
    "wof:placetype":"locality"
},
  "geometry": {"coordinates":[-98.67028999999999,18.13302],"type":"Point"}
}