{
  "type": "Feature",
  "properties": {
    "gn:admin1_code":"5.0",
    "gn:admin2_code":"12.0",
    "gn:asciiname":"Orejeria",
    "gn:country_code":"MX",
    "gn:dem":892,
    "gn:feature_class":"P",
    "gn:feature_code":"PPL",
    "gn:name":"Orejer\u00eda",
    "gn:population":0,
    "gn:timezone":"America/Mexico_City",
    "iso:country":"MX",
    "name:spa_x_preferred":[
        "Orejer\u00eda"
    ],
    "wof:name":"Orejeria",
    "wof:placetype":"locality"
},
  "geometry": {"coordinates":[-93.27574,16.72729],"type":"Point"}
}