{
  "type": "Feature",
  "properties": {
    "gn:admin1_code":"21",
    "gn:admin2_code":"177.0",
    "gn:asciiname":"La Virgen",
    "gn:country_code":"MX",
    "gn:dem":1882,
    "gn:feature_class":"P",
    "gn:feature_code":"PPL",
    "gn:name":"La Virgen",
    "gn:population":155,
    "gn:timezone":"America/Mexico_City",
    "iso:country":"MX",
    "wof:name":"La Virgen",
    "wof:placetype":"locality",
    "wof:population":155
},
  "geometry": {"coordinates":[-97.60784,18.62135],"type":"Point"}
}