{
  "type": "Feature",
  "properties": {
    "gn:admin1_code":"5",
    "gn:admin2_code":"51",
    "gn:asciiname":"Marcedonio Salas",
    "gn:country_code":"MX",
    "gn:dem":109,
    "gn:feature_class":"P",
    "gn:feature_code":"PPL",
    "gn:name":"Marcedonio Salas",
    "gn:population":9,
    "gn:timezone":"America/Mexico_City",
    "iso:country":"MX",
    "wof:name":"Marcedonio Salas",
    "wof:placetype":"locality",
    "wof:population":9
},
  "geometry": {"coordinates":[-92.85639,15.43139],"type":"Point"}
}