{
  "type": "Feature",
  "properties": {
    "gn:admin1_code":"24",
    "gn:admin2_code":"20.0",
    "gn:asciiname":"La Mision",
    "gn:country_code":"MX",
    "gn:dem":1676,
    "gn:feature_class":"P",
    "gn:feature_code":"PPL",
    "gn:name":"La Misi\u00f3n",
    "gn:population":69,
    "gn:timezone":"America/Mexico_City",
    "iso:country":"MX",
    "name:und_x_variant":[
        "La Misi\u00f3n"
    ],
    "wof:name":"La Mision",
    "wof:placetype":"locality",
    "wof:population":69
},
  "geometry": {"coordinates":[-100.52972,23.74],"type":"Point"}
}