{
  "type": "Feature",
  "properties": {
    "gn:admin1_code":"25.0",
    "gn:admin2_code":"6.0",
    "gn:asciiname":"Ejido Pueblo Nuevo Higueras de Achota",
    "gn:country_code":"MX",
    "gn:dem":16,
    "gn:feature_class":"P",
    "gn:feature_code":"PPL",
    "gn:name":"Ejido Pueblo Nuevo Higueras de Achota",
    "gn:population":0,
    "gn:timezone":"America/Mazatlan",
    "iso:country":"MX",
    "name:spa_x_preferred":[
        "Ejido Pueblo Nuevo Higueras de Achota"
    ],
    "wof:name":"Ejido Pueblo Nuevo Higueras de Achota",
    "wof:placetype":"locality"
},
  "geometry": {"coordinates":[-107.33732999999999,24.31764],"type":"Point"}
}