{
  "type": "Feature",
  "properties": {
    "gn:admin1_code":"20",
    "gn:admin2_code":"327.0",
    "gn:asciiname":"Palo Blanco (Los Pinos)",
    "gn:country_code":"MX",
    "gn:dem":12,
    "gn:feature_class":"P",
    "gn:feature_code":"PPL",
    "gn:name":"Palo Blanco (Los Pinos)",
    "gn:population":8,
    "gn:timezone":"America/Mexico_City",
    "iso:country":"MX",
    "wof:name":"Palo Blanco (Los Pinos)",
    "wof:placetype":"locality",
    "wof:population":8
},
  "geometry": {"coordinates":[-94.14082999999999,16.25083],"type":"Point"}
}