{
  "type": "Feature",
  "properties": {
    "gn:admin1_code":"20",
    "gn:admin2_code":"43.0",
    "gn:asciiname":"San Dionisio Viejo",
    "gn:country_code":"MX",
    "gn:dem":1,
    "gn:feature_class":"P",
    "gn:feature_code":"PPL",
    "gn:name":"San Dionisio Viejo",
    "gn:population":0,
    "gn:timezone":"America/Mexico_City",
    "iso:country":"MX",
    "wof:name":"San Dionisio Viejo",
    "wof:placetype":"locality"
},
  "geometry": {"coordinates":[-94.84999999999999,16.26667],"type":"Point"}
}