{
  "type": "Feature",
  "properties": {
    "gn:admin1_code":"14",
    "gn:admin2_code":"118",
    "gn:asciiname":"Rancho Nuevo (Los Llanos)",
    "gn:country_code":"MX",
    "gn:dem":2168,
    "gn:feature_class":"P",
    "gn:feature_code":"PPL",
    "gn:name":"Rancho Nuevo (Los Llanos)",
    "gn:population":33,
    "gn:timezone":"America/Mexico_City",
    "iso:country":"MX",
    "wof:name":"Rancho Nuevo (Los Llanos)",
    "wof:placetype":"locality",
    "wof:population":33
},
  "geometry": {"coordinates":[-103.06722000000001,21.1125],"type":"Point"}
}