{
  "type": "Feature",
  "properties": {
    "gn:admin1_code":"6",
    "gn:admin2_code":"48.0",
    "gn:asciiname":"Cerro Prieto",
    "gn:country_code":"MX",
    "gn:dem":2124,
    "gn:feature_class":"P",
    "gn:feature_code":"PPL",
    "gn:name":"Cerro Prieto",
    "gn:population":0,
    "gn:timezone":"America/Chihuahua",
    "iso:country":"MX",
    "name:hun_x_preferred":[
        "Cerro Prieto"
    ],
    "name:hye_x_preferred":[
        "\u054d\u0565\u057c\u0578 \u054a\u0580\u056b\u0565\u057f\u0578"
    ],
    "name:ita_x_preferred":[
        "Cerro Prieto"
    ],
    "name:slk_x_preferred":[
        "Cerro Prieto"
    ],
    "name:spa_x_preferred":[
        "Cerro Prieto"
    ],
    "wof:name":"Cerro Prieto",
    "wof:placetype":"locality"
},
  "geometry": {"coordinates":[-107.21262,29.33935],"type":"Point"}
}