{
  "type": "Feature",
  "properties": {
    "gn:admin1_code":"5",
    "gn:admin2_code":"107",
    "gn:asciiname":"San Agustinito",
    "gn:country_code":"MX",
    "gn:dem":558,
    "gn:feature_class":"P",
    "gn:feature_code":"PPL",
    "gn:name":"San Agustinito",
    "gn:population":20,
    "gn:timezone":"America/Mexico_City",
    "iso:country":"MX",
    "wof:name":"San Agustinito",
    "wof:placetype":"locality",
    "wof:population":20
},
  "geometry": {"coordinates":[-93.27528,16.21027999999999],"type":"Point"}
}