{
  "type": "Feature",
  "properties": {
    "gn:admin1_code":"5",
    "gn:admin2_code":"109",
    "gn:asciiname":"Las Brisas",
    "gn:country_code":"MX",
    "gn:dem":1227,
    "gn:feature_class":"P",
    "gn:feature_code":"PPL",
    "gn:name":"Las Brisas",
    "gn:population":29,
    "gn:timezone":"America/Mexico_City",
    "iso:country":"MX",
    "wof:name":"Las Brisas",
    "wof:placetype":"locality",
    "wof:population":29
},
  "geometry": {"coordinates":[-92.30583,17.17444],"type":"Point"}
}