{
  "type": "Feature",
  "properties": {
    "gn:admin1_code":"12",
    "gn:admin2_code":"1.0",
    "gn:asciiname":"Agua Zarca de la Pena",
    "gn:country_code":"MX",
    "gn:dem":351,
    "gn:feature_class":"P",
    "gn:feature_code":"PPL",
    "gn:name":"Agua Zarca de la Pe\u00f1a",
    "gn:population":561,
    "gn:timezone":"America/Mexico_City",
    "iso:country":"MX",
    "name:spa_x_preferred":[
        "Agua Zarca de la Pe\u00f1a"
    ],
    "name:und_x_variant":[
        "Agua Zarca de la Pe\u00f1a"
    ],
    "wof:name":"Agua Zarca de la Pena",
    "wof:placetype":"locality",
    "wof:population":561
},
  "geometry": {"coordinates":[-99.60389000000001,16.96806],"type":"Point"}
}