{
  "type": "Feature",
  "properties": {
    "gn:admin1_code":"30",
    "gn:admin2_code":"125",
    "gn:asciiname":"Rancho Canamazo",
    "gn:country_code":"MX",
    "gn:dem":567,
    "gn:feature_class":"P",
    "gn:feature_code":"PPL",
    "gn:name":"Rancho Ca\u00f1amazo",
    "gn:population":38,
    "gn:timezone":"America/Mexico_City",
    "iso:country":"MX",
    "name:und_x_variant":[
        "Rancho Ca\u00f1amazo"
    ],
    "wof:name":"Rancho Canamazo",
    "wof:placetype":"locality",
    "wof:population":38
},
  "geometry": {"coordinates":[-96.75694,18.99667],"type":"Point"}
}