{
  "type": "Feature",
  "properties": {
    "gn:admin1_code":"26.0",
    "gn:admin2_code":"29.0",
    "gn:asciiname":"La Jaimea Abajo",
    "gn:cc2":"MX",
    "gn:country_code":"MX",
    "gn:dem":142,
    "gn:feature_class":"P",
    "gn:feature_code":"PPL",
    "gn:name":"La Jaimea Abajo",
    "gn:population":0,
    "gn:timezone":"America/Hermosillo",
    "iso:country":"MX",
    "name:und_x_variant":[
        "Rancho La Jaimea",
        "Jaimea Abajo",
        "La Jaimea Abajo"
    ],
    "wof:name":"La Jaimea Abajo",
    "wof:placetype":"locality"
},
  "geometry": {"coordinates":[-110.59999999999999,28.33333],"type":"Point"}
}