{
  "type": "Feature",
  "properties": {
    "gn:admin1_code":"28",
    "gn:admin2_code":"21.0",
    "gn:asciiname":"La Mora",
    "gn:country_code":"MX",
    "gn:dem":60,
    "gn:feature_class":"P",
    "gn:feature_code":"PPL",
    "gn:name":"La Mora",
    "gn:population":0,
    "gn:timezone":"America/Monterrey",
    "iso:country":"MX",
    "name:und_x_variant":[
        "Mora",
        "La Mora"
    ],
    "wof:name":"La Mora",
    "wof:placetype":"locality"
},
  "geometry": {"coordinates":[-98.88415000000001,22.7795],"type":"Point"}
}