{
  "type": "Feature",
  "properties": {
    "gn:admin1_code":"30",
    "gn:admin2_code":"61",
    "gn:asciiname":"El Encajonado",
    "gn:country_code":"MX",
    "gn:dem":45,
    "gn:feature_class":"P",
    "gn:feature_code":"PPL",
    "gn:name":"El Encajonado",
    "gn:population":14,
    "gn:timezone":"America/Mexico_City",
    "iso:country":"MX",
    "wof:name":"El Encajonado",
    "wof:placetype":"locality",
    "wof:population":14
},
  "geometry": {"coordinates":[-93.90056,17.54639],"type":"Point"}
}