{
  "type": "Feature",
  "properties": {
    "gn:admin1_code":"6",
    "gn:admin2_code":"29",
    "gn:asciiname":"Bajichi (Cieneguita)",
    "gn:country_code":"MX",
    "gn:dem":2401,
    "gn:feature_class":"P",
    "gn:feature_code":"PPL",
    "gn:name":"Bajichi (Cieneguita)",
    "gn:population":12,
    "gn:timezone":"America/Chihuahua",
    "iso:country":"MX",
    "wof:name":"Bajichi (Cieneguita)",
    "wof:placetype":"locality",
    "wof:population":12
},
  "geometry": {"coordinates":[-106.97404,26.55161],"type":"Point"}
}