{
  "type": "Feature",
  "properties": {
    "gn:admin1_code":"20.0",
    "gn:asciiname":"El Manantial",
    "gn:country_code":"MX",
    "gn:dem":109,
    "gn:feature_class":"P",
    "gn:feature_code":"PPL",
    "gn:name":"El Manantial",
    "gn:population":0,
    "gn:timezone":"America/Mexico_City",
    "iso:country":"MX",
    "name:spa_x_preferred":[
        "El Manantial"
    ],
    "wof:name":"El Manantial",
    "wof:placetype":"locality"
},
  "geometry": {"coordinates":[-95.85335000000001,17.96312],"type":"Point"}
}