{
  "type": "Feature",
  "properties": {
    "gn:admin1_code":"14.0",
    "gn:asciiname":"Arroyo Grande",
    "gn:country_code":"MX",
    "gn:dem":1202,
    "gn:feature_class":"P",
    "gn:feature_code":"PPL",
    "gn:name":"Arroyo Grande",
    "gn:population":0,
    "gn:timezone":"America/Mexico_City",
    "iso:country":"MX",
    "name:spa_x_preferred":[
        "Arroyo Grande"
    ],
    "wof:name":"Arroyo Grande",
    "wof:placetype":"locality"
},
  "geometry": {"coordinates":[-103.77975000000001,21.46362],"type":"Point"}
}