{
  "type": "Feature",
  "properties": {
    "gn:admin1_code":"6",
    "gn:admin2_code":"27.0",
    "gn:asciiname":"Cumbres de Gualayna",
    "gn:country_code":"MX",
    "gn:dem":2487,
    "gn:feature_class":"P",
    "gn:feature_code":"PPL",
    "gn:name":"Cumbres de Gualayna",
    "gn:population":0,
    "gn:timezone":"America/Chihuahua",
    "iso:country":"MX",
    "name:spa_x_preferred":[
        "Cumbres de Gualayna"
    ],
    "wof:name":"Cumbres de Gualayna",
    "wof:placetype":"locality"
},
  "geometry": {"coordinates":[-107.24509999999999,26.85684],"type":"Point"}
}