{
  "type": "Feature",
  "properties": {
    "gn:admin1_code":"32",
    "gn:admin2_code":"10.0",
    "gn:asciiname":"Los Tanques",
    "gn:country_code":"MX",
    "gn:dem":2172,
    "gn:feature_class":"P",
    "gn:feature_code":"PPL",
    "gn:name":"Los Tanques",
    "gn:population":8,
    "gn:timezone":"America/Mexico_City",
    "iso:country":"MX",
    "wof:name":"Los Tanques",
    "wof:placetype":"locality",
    "wof:population":8
},
  "geometry": {"coordinates":[-103.32083,23.21056],"type":"Point"}
}