{
  "type": "Feature",
  "properties": {
    "gn:admin1_code":"15",
    "gn:admin2_code":"114.0",
    "gn:asciiname":"Turcio Primera Seccion",
    "gn:country_code":"MX",
    "gn:dem":2711,
    "gn:feature_class":"P",
    "gn:feature_code":"PPL",
    "gn:name":"Turcio Primera Secci\u00f3n",
    "gn:population":0,
    "gn:timezone":"America/Mexico_City",
    "iso:country":"MX",
    "name:spa_x_preferred":[
        "Turcio Primera Secci\u00f3n"
    ],
    "name:und_x_variant":[
        "Turcio"
    ],
    "wof:name":"Turcio Primera Seccion",
    "wof:placetype":"locality"
},
  "geometry": {"coordinates":[-99.96726,19.33378],"type":"Point"}
}