{
  "type": "Feature",
  "properties": {
    "gn:admin1_code":"5",
    "gn:admin2_code":"11.0",
    "gn:asciiname":"La Lucha San Marcos",
    "gn:country_code":"MX",
    "gn:dem":1452,
    "gn:feature_class":"P",
    "gn:feature_code":"PPL",
    "gn:name":"La Lucha San Marcos",
    "gn:population":121,
    "gn:timezone":"America/Mexico_City",
    "iso:country":"MX",
    "wof:name":"La Lucha San Marcos",
    "wof:placetype":"locality",
    "wof:population":121
},
  "geometry": {"coordinates":[-92.23889,15.58722],"type":"Point"}
}