{
  "type": "Feature",
  "properties": {
    "gn:admin1_code":"10.0",
    "gn:admin2_code":"28.0",
    "gn:asciiname":"El Molino Primero",
    "gn:country_code":"MX",
    "gn:dem":1708,
    "gn:feature_class":"P",
    "gn:feature_code":"PPL",
    "gn:name":"El Molino Primero",
    "gn:population":0,
    "gn:timezone":"America/Monterrey",
    "iso:country":"MX",
    "name:spa_x_preferred":[
        "El Molino Primero"
    ],
    "wof:name":"El Molino Primero",
    "wof:placetype":"locality"
},
  "geometry": {"coordinates":[-104.45681999999999,24.77377000000001],"type":"Point"}
}