{
  "type": "Feature",
  "properties": {
    "gn:admin1_code":"26",
    "gn:admin2_code":"3.0",
    "gn:asciiname":"Promontorios",
    "gn:cc2":"MX",
    "gn:country_code":"MX",
    "gn:dem":631,
    "gn:feature_class":"P",
    "gn:feature_code":"PPL",
    "gn:name":"Promontorios",
    "gn:population":0,
    "gn:timezone":"America/Hermosillo",
    "iso:country":"MX",
    "name:und_x_variant":[
        "Promontorio",
        "Promontorios"
    ],
    "wof:name":"Promontorios",
    "wof:placetype":"locality"
},
  "geometry": {"coordinates":[-109.03333000000001,27.01667],"type":"Point"}
}