{
  "type": "Feature",
  "properties": {
    "gn:admin1_code":"5.0",
    "gn:admin2_code":"69.0",
    "gn:asciiname":"Tierra de Dios",
    "gn:country_code":"MX",
    "gn:dem":425,
    "gn:feature_class":"P",
    "gn:feature_code":"PPL",
    "gn:name":"Tierra de Dios",
    "gn:population":0,
    "gn:timezone":"America/Mexico_City",
    "iso:country":"MX",
    "name:spa_x_preferred":[
        "Tierra de Dios"
    ],
    "wof:name":"Tierra de Dios",
    "wof:placetype":"locality"
},
  "geometry": {"coordinates":[-93.29362999999999,15.80782],"type":"Point"}
}