{
  "type": "Feature",
  "properties": {
    "gn:admin1_code":"30",
    "gn:admin2_code":"144.0",
    "gn:asciiname":"El Cristo",
    "gn:country_code":"MX",
    "gn:dem":111,
    "gn:feature_class":"P",
    "gn:feature_code":"PPL",
    "gn:name":"El Cristo",
    "gn:population":6,
    "gn:timezone":"America/Mexico_City",
    "iso:country":"MX",
    "name:ceb_x_preferred":[
        "El Cristo"
    ],
    "name:glg_x_preferred":[
        "O Cristo"
    ],
    "name:spa_x_preferred":[
        "El Cristo"
    ],
    "name:swe_x_preferred":[
        "El Cristo"
    ],
    "wof:name":"El Cristo",
    "wof:placetype":"locality",
    "wof:population":6
},
  "geometry": {"coordinates":[-95.03167000000001,17.80444],"type":"Point"}
}