{
  "type": "Feature",
  "properties": {
    "gn:admin1_code":"11",
    "gn:admin2_code":"37.0",
    "gn:asciiname":"San Jose del Carmen",
    "gn:country_code":"MX",
    "gn:dem":1782,
    "gn:feature_class":"P",
    "gn:feature_code":"PPL",
    "gn:name":"San Jos\u00e9 del Carmen",
    "gn:population":179,
    "gn:timezone":"America/Mexico_City",
    "iso:country":"MX",
    "name:und_x_variant":[
        "San Jos\u00e9 del Carmen"
    ],
    "wof:name":"San Jose del Carmen",
    "wof:placetype":"locality",
    "wof:population":179
},
  "geometry": {"coordinates":[-101.38678,20.91643],"type":"Point"}
}