{
  "type": "Feature",
  "properties": {
    "gn:admin1_code":"28",
    "gn:admin2_code":"35",
    "gn:asciiname":"Rancho Escondido",
    "gn:country_code":"MX",
    "gn:dem":42,
    "gn:feature_class":"P",
    "gn:feature_code":"PPL",
    "gn:name":"Rancho Escondido",
    "gn:population":11,
    "gn:timezone":"America/Monterrey",
    "iso:country":"MX",
    "wof:name":"Rancho Escondido",
    "wof:placetype":"locality",
    "wof:population":11
},
  "geometry": {"coordinates":[-98.14194000000001,25.24639],"type":"Point"}
}