{
  "type": "Feature",
  "properties": {
    "gn:admin1_code":"6",
    "gn:admin2_code":"19.0",
    "gn:asciiname":"Ejido Rancho Ojo Laguna",
    "gn:country_code":"MX",
    "gn:dem":1599,
    "gn:feature_class":"P",
    "gn:feature_code":"PPL",
    "gn:name":"Ejido Rancho Ojo Laguna",
    "gn:population":86,
    "gn:timezone":"America/Chihuahua",
    "iso:country":"MX",
    "wof:name":"Ejido Rancho Ojo Laguna",
    "wof:placetype":"locality",
    "wof:population":86
},
  "geometry": {"coordinates":[-106.42064999999999,29.44935],"type":"Point"}
}