{
  "type": "Feature",
  "properties": {
    "gn:admin1_code":"11",
    "gn:admin2_code":"8.0",
    "gn:asciiname":"Rancho Campo Verde",
    "gn:country_code":"MX",
    "gn:dem":1733,
    "gn:feature_class":"P",
    "gn:feature_code":"PPL",
    "gn:name":"Rancho Campo Verde",
    "gn:population":7,
    "gn:timezone":"America/Mexico_City",
    "iso:country":"MX",
    "wof:name":"Rancho Campo Verde",
    "wof:placetype":"locality",
    "wof:population":7
},
  "geometry": {"coordinates":[-101.85611,20.81139],"type":"Point"}
}