{
  "type": "Feature",
  "properties": {
    "gn:admin1_code":"3",
    "gn:admin2_code":"3",
    "gn:asciiname":"Los Arenales",
    "gn:country_code":"MX",
    "gn:dem":664,
    "gn:feature_class":"P",
    "gn:feature_code":"PPL",
    "gn:name":"Los Arenales",
    "gn:population":15,
    "gn:timezone":"America/Mazatlan",
    "iso:country":"MX",
    "wof:name":"Los Arenales",
    "wof:placetype":"locality",
    "wof:population":15
},
  "geometry": {"coordinates":[-110.11731,23.94869],"type":"Point"}
}