{
  "type": "Feature",
  "properties": {
    "gn:admin1_code":"11",
    "gn:admin2_code":"23.0",
    "gn:asciiname":"Taxcalilla",
    "gn:country_code":"MX",
    "gn:dem":2229,
    "gn:feature_class":"P",
    "gn:feature_code":"PPL",
    "gn:name":"Taxcalilla",
    "gn:population":7,
    "gn:timezone":"America/Mexico_City",
    "iso:country":"MX",
    "wof:name":"Taxcalilla",
    "wof:placetype":"locality",
    "wof:population":7
},
  "geometry": {"coordinates":[-101.76222,20.59639],"type":"Point"}
}