{
  "type": "Feature",
  "properties": {
    "gn:admin1_code":"4.0",
    "gn:admin2_code":"3.0",
    "gn:asciiname":"La Libertad",
    "gn:country_code":"MX",
    "gn:dem":25,
    "gn:feature_class":"P",
    "gn:feature_code":"PPL",
    "gn:name":"La Libertad",
    "gn:population":0,
    "gn:timezone":"America/Merida",
    "iso:country":"MX",
    "name:spa_x_preferred":[
        "La Libertad"
    ],
    "wof:name":"La Libertad",
    "wof:placetype":"locality"
},
  "geometry": {"coordinates":[-91.37081999999999,18.24109],"type":"Point"}
}