{
  "type": "Feature",
  "properties": {
    "gn:admin1_code":"24",
    "gn:admin2_code":"17.0",
    "gn:asciiname":"El Refugio del Amparito",
    "gn:country_code":"MX",
    "gn:dem":1582,
    "gn:feature_class":"P",
    "gn:feature_code":"PPL",
    "gn:name":"El Refugio del Amparito",
    "gn:population":25,
    "gn:timezone":"America/Mexico_City",
    "iso:country":"MX",
    "wof:name":"El Refugio del Amparito",
    "wof:placetype":"locality",
    "wof:population":25
},
  "geometry": {"coordinates":[-100.26528,22.71889],"type":"Point"}
}