{
  "type": "Feature",
  "properties": {
    "gn:admin1_code":"15",
    "gn:admin2_code":"114.0",
    "gn:asciiname":"El Sitio",
    "gn:country_code":"MX",
    "gn:dem":2603,
    "gn:feature_class":"P",
    "gn:feature_code":"PPL",
    "gn:name":"El Sitio",
    "gn:population":0,
    "gn:timezone":"America/Mexico_City",
    "iso:country":"MX",
    "name:spa_x_preferred":[
        "El Sitio"
    ],
    "wof:name":"El Sitio",
    "wof:placetype":"locality"
},
  "geometry": {"coordinates":[-99.90327000000001,19.45675],"type":"Point"}
}