{
  "type": "Feature",
  "properties": {
    "gn:admin1_code":"13",
    "gn:admin2_code":"83.0",
    "gn:asciiname":"Tepa el Grande",
    "gn:country_code":"MX",
    "gn:dem":2643,
    "gn:feature_class":"P",
    "gn:feature_code":"PPL",
    "gn:name":"Tepa el Grande",
    "gn:population":0,
    "gn:timezone":"America/Mexico_City",
    "iso:country":"MX",
    "name:spa_x_preferred":[
        "Tepa el Grande"
    ],
    "wof:name":"Tepa el Grande",
    "wof:placetype":"locality"
},
  "geometry": {"coordinates":[-98.60696,19.85996],"type":"Point"}
}