{
  "type": "Feature",
  "properties": {
    "gn:admin1_code":"4.0",
    "gn:asciiname":"Profesor Jose Luis Olivet",
    "gn:country_code":"MX",
    "gn:dem":10,
    "gn:feature_class":"P",
    "gn:feature_code":"PPL",
    "gn:name":"Profesor Jos\u00e9 Luis Olivet",
    "gn:population":0,
    "gn:timezone":"America/Merida",
    "iso:country":"MX",
    "name:spa_x_preferred":[
        "Profesor Jos\u00e9 Luis Olivet"
    ],
    "wof:name":"Profesor Jose Luis Olivet",
    "wof:placetype":"locality"
},
  "geometry": {"coordinates":[-91.6028,18.10274],"type":"Point"}
}