{
  "type": "Feature",
  "properties": {
    "gn:admin1_code":"28",
    "gn:admin2_code":"41.0",
    "gn:asciiname":"Crucitas",
    "gn:country_code":"MX",
    "gn:dem":302,
    "gn:feature_class":"P",
    "gn:feature_code":"PPL",
    "gn:name":"Crucitas",
    "gn:population":0,
    "gn:timezone":"America/Monterrey",
    "iso:country":"MX",
    "name:spa_x_preferred":[
        "Crucitas"
    ],
    "name:und_x_variant":[
        "Las Crucitas"
    ],
    "wof:name":"Crucitas",
    "wof:placetype":"locality"
},
  "geometry": {"coordinates":[-99.25754000000001,23.89604],"type":"Point"}
}