{
  "type": "Feature",
  "properties": {
    "gn:admin1_code":"32",
    "gn:admin2_code":"10.0",
    "gn:asciiname":"San Rafael de Abrego",
    "gn:country_code":"MX",
    "gn:dem":2178,
    "gn:feature_class":"P",
    "gn:feature_code":"PPL",
    "gn:name":"San Rafael de \u00c1brego",
    "gn:population":4,
    "gn:timezone":"America/Mexico_City",
    "iso:country":"MX",
    "wof:name":"San Rafael de Abrego",
    "wof:placetype":"locality",
    "wof:population":4
},
  "geometry": {"coordinates":[-103.33167,23.20333],"type":"Point"}
}