{
  "type": "Feature",
  "properties": {
    "gn:admin1_code":"18",
    "gn:admin2_code":"5.0",
    "gn:asciiname":"La Majada",
    "gn:country_code":"MX",
    "gn:dem":549,
    "gn:feature_class":"P",
    "gn:feature_code":"PPL",
    "gn:name":"La Majada",
    "gn:population":0,
    "gn:timezone":"America/Mazatlan",
    "iso:country":"MX",
    "name:spa_x_preferred":[
        "La Majada"
    ],
    "wof:name":"La Majada",
    "wof:placetype":"locality"
},
  "geometry": {"coordinates":[-105.25554,22.8302],"type":"Point"}
}