{
  "type": "Feature",
  "properties": {
    "gn:admin1_code":"6",
    "gn:admin2_code":"1.0",
    "gn:asciiname":"Moctezuma",
    "gn:country_code":"MX",
    "gn:dem":1376,
    "gn:feature_class":"P",
    "gn:feature_code":"PPL",
    "gn:name":"Moctezuma",
    "gn:population":154,
    "gn:timezone":"America/Chihuahua",
    "iso:country":"MX",
    "name:ara_x_preferred":[
        "\u0645\u0648\u0646\u062a\u064a\u0632\u0648\u0645\u0627"
    ],
    "name:ben_x_preferred":[
        "\u09ae\u09cb\u0995\u09cd\u09a4\u09c7\u099c\u09c1\u09ae\u09be"
    ],
    "name:deu_x_preferred":[
        "Rio Moctezuma"
    ],
    "name:ell_x_preferred":[
        "\u039c\u03bf\u03ba\u03c4\u03b5\u03b6\u03bf\u03cd\u03bc\u03b1"
    ],
    "name:eng_x_preferred":[
        "Moctezuma River"
    ],
    "name:fas_x_preferred":[
        "\u0645\u0648\u06a9\u062a\u0632\u0648\u0645\u0648"
    ],
    "name:fra_x_preferred":[
        "Moctezuma"
    ],
    "name:heb_x_preferred":[
        "\u05de\u05d5\u05d2\u05d0\u05dc\u05e7\u05d5\u05d5\u05e0\u05d4"
    ],
    "name:hin_x_preferred":[
        "\u092e\u094b\u0915\u094d\u091f\u0947\u091c\u093c\u0941\u092e\u093e"
    ],
    "name:hun_x_preferred":[
        "Moctezuma"
    ],
    "name:ind_x_preferred":[
        "Moctezuma"
    ],
    "name:ita_x_preferred":[
        "Moctezuma"
    ],
    "name:jpn_x_preferred":[
        "\u30e2\u30af\u30c6\u30b9\u30de\u5ddd"
    ],
    "name:kor_x_preferred":[
        "\ubaa9\ud14c\uc8fc\ub9c8"
    ],
    "name:nld_x_preferred":[
        "Moctezuma"
    ],
    "name:pol_x_preferred":[
        "Moctezuma"
    ],
    "name:por_x_preferred":[
        "Moctezuma"
    ],
    "name:rus_x_preferred":[
        "\u0440\u0435\u043a\u0430 \u041c\u043e\u043a\u0442\u0435\u0441\u0443\u043c\u0430"
    ],
    "name:spa_x_preferred":[
        "Moctezuma"
    ],
    "name:tur_x_preferred":[
        "Moctezuma"
    ],
    "name:ukr_x_preferred":[
        "\u041c\u043e\u043a\u0442\u0435\u0437\u0443\u043c\u0430"
    ],
    "name:urd_x_preferred":[
        "\u0645\u0627\u06a9\u0679\u06cc\u0632\u0648\u0645\u0627"
    ],
    "name:vie_x_preferred":[
        "S\u00f4ng Moctezuma"
    ],
    "name:zho_cn_x_preferred":[
        "\u8499\u7279\u7956\u9a6c\u6cb3"
    ],
    "name:zho_tw_x_preferred":[
        "\u8499\u7279\u8607\u99ac\u6cb3"
    ],
    "wof:name":"Moctezuma",
    "wof:placetype":"locality",
    "wof:population":154
},
  "geometry": {"coordinates":[-106.43639,30.19778],"type":"Point"}
}