{
  "type": "Feature",
  "properties": {
    "gn:admin1_code":"6",
    "gn:admin2_code":"1.0",
    "gn:asciiname":"Moctezuma",
    "gn:country_code":"MX",
    "gn:dem":1376,
    "gn:feature_class":"P",
    "gn:feature_code":"PPL",
    "gn:name":"Moctezuma",
    "gn:population":154,
    "gn:timezone":"America/Chihuahua",
    "iso:country":"MX",
    "name:spa_x_preferred":[
        "Moctezuma"
    ],
    "wof:name":"Moctezuma",
    "wof:placetype":"locality",
    "wof:population":154
},
  "geometry": {"coordinates":[-106.43639,30.19778],"type":"Point"}
}