{
  "type": "Feature",
  "properties": {
    "gn:admin1_code":"6.0",
    "gn:asciiname":"El Terminal",
    "gn:country_code":"MX",
    "gn:dem":2185,
    "gn:feature_class":"P",
    "gn:feature_code":"PPL",
    "gn:name":"El Terminal",
    "gn:population":0,
    "gn:timezone":"America/Monterrey",
    "iso:country":"MX",
    "name:spa_x_preferred":[
        "El Terminal"
    ],
    "name:und_x_variant":[
        "Rancho El Terminal"
    ],
    "wof:name":"El Terminal",
    "wof:placetype":"locality"
},
  "geometry": {"coordinates":[-105.93371,26.76928],"type":"Point"}
}