{
  "type": "Feature",
  "properties": {
    "gn:admin1_code":"5",
    "gn:admin2_code":"99.0",
    "gn:asciiname":"San Francisco Laguna Seca",
    "gn:country_code":"MX",
    "gn:dem":784,
    "gn:feature_class":"P",
    "gn:feature_code":"PPL",
    "gn:name":"San Francisco Laguna Seca",
    "gn:population":55,
    "gn:timezone":"America/Mexico_City",
    "iso:country":"MX",
    "wof:name":"San Francisco Laguna Seca",
    "wof:placetype":"locality",
    "wof:population":55
},
  "geometry": {"coordinates":[-92.04167,15.96333],"type":"Point"}
}