{
  "type": "Feature",
  "properties": {
    "gn:admin1_code":"20",
    "gn:admin2_code":"229",
    "gn:asciiname":"Rio Pescadito",
    "gn:country_code":"MX",
    "gn:dem":1122,
    "gn:feature_class":"P",
    "gn:feature_code":"PPL",
    "gn:name":"R\u00edo Pescadito",
    "gn:population":25,
    "gn:timezone":"America/Mexico_City",
    "iso:country":"MX",
    "name:und_x_variant":[
        "R\u00edo Pescadito"
    ],
    "wof:name":"Rio Pescadito",
    "wof:placetype":"locality",
    "wof:population":25
},
  "geometry": {"coordinates":[-97.22221999999999,16.5275],"type":"Point"}
}