{
  "type": "Feature",
  "properties": {
    "gn:admin1_code":"20",
    "gn:admin2_code":"10",
    "gn:asciiname":"Rancho la Herradura",
    "gn:country_code":"MX",
    "gn:dem":159,
    "gn:feature_class":"P",
    "gn:feature_code":"PPL",
    "gn:name":"Rancho la Herradura",
    "gn:population":11,
    "gn:timezone":"America/Mexico_City",
    "iso:country":"MX",
    "wof:name":"Rancho la Herradura",
    "wof:placetype":"locality",
    "wof:population":11
},
  "geometry": {"coordinates":[-94.93889,16.8775],"type":"Point"}
}