{
  "type": "Feature",
  "properties": {
    "gn:admin1_code":"6",
    "gn:admin2_code":"55.0",
    "gn:asciiname":"Los Churumbeles",
    "gn:country_code":"MX",
    "gn:dem":1193,
    "gn:feature_class":"P",
    "gn:feature_code":"PPL",
    "gn:name":"Los Churumbeles",
    "gn:population":0,
    "gn:timezone":"America/Chihuahua",
    "iso:country":"MX",
    "name:spa_x_preferred":[
        "Los Churumbeles"
    ],
    "name:und_x_variant":[
        "Rancho Los Churumbeles"
    ],
    "wof:name":"Los Churumbeles",
    "wof:placetype":"locality"
},
  "geometry": {"coordinates":[-105.59258,28.17159],"type":"Point"}
}