{
  "type": "Feature",
  "properties": {
    "gn:admin1_code":"20",
    "gn:admin2_code":"79.0",
    "gn:asciiname":"Boca del Rio",
    "gn:country_code":"MX",
    "gn:dem":6,
    "gn:feature_class":"P",
    "gn:feature_code":"PPL",
    "gn:name":"Boca del R\u00edo",
    "gn:population":825,
    "gn:timezone":"America/Mexico_City",
    "iso:country":"MX",
    "name:und_x_variant":[
        "Boca del R\u00edo"
    ],
    "wof:name":"Boca del Rio",
    "wof:placetype":"locality",
    "wof:population":825
},
  "geometry": {"coordinates":[-95.16139,16.20722],"type":"Point"}
}