{
  "type": "Feature",
  "properties": {
    "gn:admin1_code":"8.0",
    "gn:admin2_code":"7.0",
    "gn:asciiname":"Camichin",
    "gn:country_code":"MX",
    "gn:dem":417,
    "gn:feature_class":"P",
    "gn:feature_code":"PPL",
    "gn:name":"Camich\u00edn",
    "gn:population":38,
    "gn:timezone":"America/Mexico_City",
    "iso:country":"MX",
    "name:spa_x_preferred":[
        "Camich\u00edn"
    ],
    "wof:name":"Camichin",
    "wof:placetype":"locality",
    "wof:population":38
},
  "geometry": {"coordinates":[-104.17856999999999,19.27893],"type":"Point"}
}