{
  "type": "Feature",
  "properties": {
    "gn:admin1_code":"2",
    "gn:admin2_code":"1.0",
    "gn:asciiname":"Rancho Jimenez",
    "gn:country_code":"MX",
    "gn:dem":682,
    "gn:feature_class":"P",
    "gn:feature_code":"PPL",
    "gn:name":"Rancho Jim\u00e9nez",
    "gn:population":8,
    "gn:timezone":"America/Tijuana",
    "iso:country":"MX",
    "name:und_x_variant":[
        "Rancho Jim\u00e9nez"
    ],
    "wof:name":"Rancho Jimenez",
    "wof:placetype":"locality",
    "wof:population":8
},
  "geometry": {"coordinates":[-116.28306000000001,31.96528],"type":"Point"}
}