{
  "type": "Feature",
  "properties": {
    "gn:admin1_code":"6",
    "gn:admin2_code":"9.0",
    "gn:asciiname":"La Mesa del Tomate",
    "gn:country_code":"MX",
    "gn:dem":2355,
    "gn:feature_class":"P",
    "gn:feature_code":"PPL",
    "gn:name":"La Mesa del Tomate",
    "gn:population":6,
    "gn:timezone":"America/Chihuahua",
    "iso:country":"MX",
    "wof:name":"La Mesa del Tomate",
    "wof:placetype":"locality",
    "wof:population":6
},
  "geometry": {"coordinates":[-107.68243,27.8063],"type":"Point"}
}