{
  "type": "Feature",
  "properties": {
    "gn:admin1_code":"2",
    "gn:admin2_code":"3.0",
    "gn:asciiname":"Ruidoso",
    "gn:country_code":"MX",
    "gn:dem":717,
    "gn:feature_class":"P",
    "gn:feature_code":"PPL",
    "gn:name":"Ruidoso",
    "gn:population":0,
    "gn:timezone":"America/Tijuana",
    "iso:country":"MX",
    "name:spa_x_preferred":[
        "Ruidoso"
    ],
    "wof:name":"Ruidoso",
    "wof:placetype":"locality"
},
  "geometry": {"coordinates":[-116.47427999999999,32.441],"type":"Point"}
}