{
  "type": "Feature",
  "properties": {
    "gn:admin1_code":"28",
    "gn:admin2_code":"42.0",
    "gn:asciiname":"Veintiuno de Enero",
    "gn:country_code":"MX",
    "gn:dem":306,
    "gn:feature_class":"P",
    "gn:feature_code":"PPL",
    "gn:name":"Veintiuno de Enero",
    "gn:population":9,
    "gn:timezone":"America/Monterrey",
    "iso:country":"MX",
    "name:spa_x_preferred":[
        "Veintiuno de Enero"
    ],
    "wof:name":"Veintiuno de Enero",
    "wof:placetype":"locality",
    "wof:population":9
},
  "geometry": {"coordinates":[-99.39234,24.69544],"type":"Point"}
}