{
  "type": "Feature",
  "properties": {
    "gn:admin1_code":"4",
    "gn:admin2_code":"10.0",
    "gn:asciiname":"Nuevo Progreso",
    "gn:country_code":"MX",
    "gn:dem":200,
    "gn:feature_class":"P",
    "gn:feature_code":"PPL",
    "gn:name":"Nuevo Progreso",
    "gn:population":69,
    "gn:timezone":"America/Cancun",
    "iso:country":"MX",
    "wof:name":"Nuevo Progreso",
    "wof:placetype":"locality",
    "wof:population":69
},
  "geometry": {"coordinates":[-89.22944,18.27111],"type":"Point"}
}