{
  "type": "Feature",
  "properties": {
    "gn:admin1_code":"16.0",
    "gn:admin2_code":"2.0",
    "gn:asciiname":"General Lazaro Cardenas",
    "gn:country_code":"MX",
    "gn:dem":400,
    "gn:feature_class":"P",
    "gn:feature_code":"PPL",
    "gn:name":"General L\u00e1zaro Cardenas",
    "gn:population":0,
    "gn:timezone":"America/Mexico_City",
    "iso:country":"MX",
    "name:spa_x_preferred":[
        "General L\u00e1zaro Cardenas"
    ],
    "name:spa_x_variant":[
        "El Lim\u00f3n"
    ],
    "name:und_x_variant":[
        "L\u00e1zaro C\u00e1rdenas"
    ],
    "wof:name":"General Lazaro Cardenas",
    "wof:placetype":"locality"
},
  "geometry": {"coordinates":[-102.79483,18.8944],"type":"Point"}
}