{
  "type": "Feature",
  "properties": {
    "gn:admin1_code":"25",
    "gn:admin2_code":"18.0",
    "gn:asciiname":"Campo Mascareno",
    "gn:country_code":"MX",
    "gn:dem":8,
    "gn:feature_class":"P",
    "gn:feature_code":"PPL",
    "gn:name":"Campo Mascare\u00f1o",
    "gn:population":8,
    "gn:timezone":"America/Mazatlan",
    "iso:country":"MX",
    "name:und_x_variant":[
        "Campo Mascare\u00f1o"
    ],
    "wof:name":"Campo Mascareno",
    "wof:placetype":"locality",
    "wof:population":8
},
  "geometry": {"coordinates":[-107.83049,24.73863],"type":"Point"}
}