{
  "type": "Feature",
  "properties": {
    "gn:admin1_code":"11",
    "gn:admin2_code":"20.0",
    "gn:asciiname":"San Jose de Otates Norte",
    "gn:country_code":"MX",
    "gn:dem":2363,
    "gn:feature_class":"P",
    "gn:feature_code":"PPL",
    "gn:name":"San Jos\u00e9 de Otates Norte",
    "gn:population":65,
    "gn:timezone":"America/Mexico_City",
    "iso:country":"MX",
    "wof:name":"San Jose de Otates Norte",
    "wof:placetype":"locality",
    "wof:population":65
},
  "geometry": {"coordinates":[-101.49778000000001,21.19417],"type":"Point"}
}