{
  "type": "Feature",
  "properties": {
    "gn:admin1_code":"32",
    "gn:admin2_code":"48",
    "gn:asciiname":"Ex-Hacienda de Temoloazco",
    "gn:country_code":"MX",
    "gn:dem":1672,
    "gn:feature_class":"P",
    "gn:feature_code":"PPL",
    "gn:name":"Ex-Hacienda de Temoloazco",
    "gn:population":14,
    "gn:timezone":"America/Mexico_City",
    "iso:country":"MX",
    "wof:name":"Ex-Hacienda de Temoloazco",
    "wof:placetype":"locality",
    "wof:population":14
},
  "geometry": {"coordinates":[-103.30806,21.83472],"type":"Point"}
}