{
  "type": "Feature",
  "properties": {
    "gn:admin1_code":"31",
    "gn:admin2_code":"19.0",
    "gn:asciiname":"X-Jaas",
    "gn:country_code":"MX",
    "gn:dem":20,
    "gn:feature_class":"P",
    "gn:feature_code":"PPL",
    "gn:name":"X-Jaas",
    "gn:population":0,
    "gn:timezone":"America/Merida",
    "iso:country":"MX",
    "name:spa_x_preferred":[
        "X-Jaas"
    ],
    "wof:name":"X-Jaas",
    "wof:placetype":"locality"
},
  "geometry": {"coordinates":[-87.89967,20.72674],"type":"Point"}
}