{
  "type": "Feature",
  "properties": {
    "gn:admin1_code":"27",
    "gn:admin2_code":"4.0",
    "gn:asciiname":"Torno Largo Primera Seccion",
    "gn:country_code":"MX",
    "gn:dem":11,
    "gn:feature_class":"P",
    "gn:feature_code":"PPL",
    "gn:name":"Torno Largo Primera Secci\u00f3n",
    "gn:population":0,
    "gn:timezone":"America/Mexico_City",
    "iso:country":"MX",
    "name:spa_x_preferred":[
        "Torno Largo"
    ],
    "name:spa_x_variant":[
        "Torno Largo Primera Secci\u00f3n",
        "Primera Secci\u00f3n"
    ],
    "wof:name":"Torno Largo Primera Seccion",
    "wof:placetype":"locality"
},
  "geometry": {"coordinates":[-92.89426,17.93117999999999],"type":"Point"}
}