{
  "type": "Feature",
  "properties": {
    "gn:admin1_code":"25.0",
    "gn:admin2_code":"10.0",
    "gn:asciiname":"El Pasito",
    "gn:country_code":"MX",
    "gn:dem":120,
    "gn:feature_class":"P",
    "gn:feature_code":"PPL",
    "gn:name":"El Pasito",
    "gn:population":50,
    "gn:timezone":"America/Mazatlan",
    "iso:country":"MX",
    "name:spa_x_preferred":[
        "El Pasito"
    ],
    "wof:name":"El Pasito",
    "wof:placetype":"locality",
    "wof:population":50
},
  "geometry": {"coordinates":[-108.70994,26.51763],"type":"Point"}
}