{
  "type": "Feature",
  "properties": {
    "gn:admin1_code":"23",
    "gn:asciiname":"Mahas",
    "gn:country_code":"MX",
    "gn:dem":23,
    "gn:feature_class":"P",
    "gn:feature_code":"PPL",
    "gn:name":"Mahas",
    "gn:population":0,
    "gn:timezone":"America/Cancun",
    "iso:country":"MX",
    "name:und_x_variant":[
        "Mahas Nahyaxche",
        "Mahas"
    ],
    "wof:name":"Mahas",
    "wof:placetype":"locality"
},
  "geometry": {"coordinates":[-88.33234,20.31055],"type":"Point"}
}