{
  "type": "Feature",
  "properties": {
    "gn:admin1_code":"6",
    "gn:admin2_code":"27.0",
    "gn:asciiname":"Huisarochi",
    "gn:country_code":"MX",
    "gn:dem":2251,
    "gn:feature_class":"P",
    "gn:feature_code":"PPL",
    "gn:name":"Huisarochi",
    "gn:population":0,
    "gn:timezone":"America/Chihuahua",
    "iso:country":"MX",
    "name:spa_x_preferred":[
        "Huisarochi"
    ],
    "wof:name":"Huisarochi",
    "wof:placetype":"locality"
},
  "geometry": {"coordinates":[-107.3873,27.48386],"type":"Point"}
}