{
  "type": "Feature",
  "properties": {
    "gn:admin1_code":"5",
    "gn:admin2_code":"37.0",
    "gn:asciiname":"Coapantes",
    "gn:country_code":"MX",
    "gn:dem":27,
    "gn:feature_class":"P",
    "gn:feature_code":"PPL",
    "gn:name":"Coapantes",
    "gn:population":0,
    "gn:timezone":"America/Mexico_City",
    "iso:country":"MX",
    "wof:name":"Coapantes",
    "wof:placetype":"locality"
},
  "geometry": {"coordinates":[-92.39313,14.95081],"type":"Point"}
}