{
  "type": "Feature",
  "properties": {
    "gn:admin1_code":"28",
    "gn:admin2_code":"34.0",
    "gn:asciiname":"La Ele",
    "gn:country_code":"MX",
    "gn:dem":339,
    "gn:feature_class":"P",
    "gn:feature_code":"PPL",
    "gn:name":"La Ele",
    "gn:population":9,
    "gn:timezone":"America/Monterrey",
    "iso:country":"MX",
    "wof:name":"La Ele",
    "wof:placetype":"locality",
    "wof:population":9
},
  "geometry": {"coordinates":[-98.87721999999999,24.44194],"type":"Point"}
}