{
  "type": "Feature",
  "properties": {
    "gn:admin1_code":"30.0",
    "gn:admin2_code":"155.0",
    "gn:asciiname":"Rancho la Herradura",
    "gn:country_code":"MX",
    "gn:dem":61,
    "gn:feature_class":"P",
    "gn:feature_code":"PPL",
    "gn:name":"Rancho la Herradura",
    "gn:population":0,
    "gn:timezone":"America/Mexico_City",
    "iso:country":"MX",
    "name:spa_x_preferred":[
        "Rancho la Herradura"
    ],
    "wof:name":"Rancho la Herradura",
    "wof:placetype":"locality"
},
  "geometry": {"coordinates":[-98.25508000000001,21.26689],"type":"Point"}
}