{
  "type": "Feature",
  "properties": {
    "gn:admin1_code":"26",
    "gn:admin2_code":"35.0",
    "gn:asciiname":"La Cienega",
    "gn:country_code":"MX",
    "gn:dem":945,
    "gn:feature_class":"P",
    "gn:feature_code":"PPL",
    "gn:name":"La Cienega",
    "gn:population":6,
    "gn:timezone":"America/Hermosillo",
    "iso:country":"MX",
    "wof:name":"La Cienega",
    "wof:placetype":"locality",
    "wof:population":6
},
  "geometry": {"coordinates":[-110.86139,30.92167],"type":"Point"}
}