{
  "type": "Feature",
  "properties": {
    "gn:admin1_code":"26.0",
    "gn:admin2_code":"44.0",
    "gn:asciiname":"Nopalera la Mina",
    "gn:country_code":"MX",
    "gn:dem":367,
    "gn:feature_class":"P",
    "gn:feature_code":"PPL",
    "gn:name":"Nopalera la Mina",
    "gn:population":0,
    "gn:timezone":"America/Hermosillo",
    "iso:country":"MX",
    "name:spa_x_preferred":[
        "Nopalera la Mina"
    ],
    "wof:name":"Nopalera la Mina",
    "wof:placetype":"locality"
},
  "geometry": {"coordinates":[-109.48994999999999,28.47993],"type":"Point"}
}