{
  "type": "Feature",
  "properties": {
    "gn:admin1_code":"30",
    "gn:admin2_code":"73.0",
    "gn:asciiname":"Hueyapan Soconusco",
    "gn:country_code":"MX",
    "gn:dem":40,
    "gn:feature_class":"P",
    "gn:feature_code":"PPL",
    "gn:name":"Hueyapan Soconusco",
    "gn:population":0,
    "gn:timezone":"America/Mexico_City",
    "iso:country":"MX",
    "name:spa_x_preferred":[
        "Hueyapan Soconusco"
    ],
    "wof:name":"Hueyapan Soconusco",
    "wof:placetype":"locality"
},
  "geometry": {"coordinates":[-95.17006000000001,18.15158],"type":"Point"}
}