{
  "type": "Feature",
  "properties": {
    "gn:admin1_code":"22",
    "gn:admin2_code":"18.0",
    "gn:asciiname":"Santa Agueda",
    "gn:country_code":"MX",
    "gn:dem":1478,
    "gn:feature_class":"P",
    "gn:feature_code":"PPL",
    "gn:name":"Santa \u00c1gueda",
    "gn:population":0,
    "gn:timezone":"America/Mexico_City",
    "iso:country":"MX",
    "wof:name":"Santa Agueda",
    "wof:placetype":"locality"
},
  "geometry": {"coordinates":[-99.86667,20.98333],"type":"Point"}
}