{
  "type": "Feature",
  "properties": {
    "gn:admin1_code":"22.0",
    "gn:admin2_code":"11.0",
    "gn:asciiname":"Agua Azul",
    "gn:country_code":"MX",
    "gn:dem":1948,
    "gn:feature_class":"P",
    "gn:feature_code":"PPL",
    "gn:name":"Agua Azul",
    "gn:population":0,
    "gn:timezone":"America/Mexico_City",
    "iso:country":"MX",
    "name:bre_x_preferred":[
        "Agua Azul"
    ],
    "name:lit_x_preferred":[
        "Agua Asulio krioklys"
    ],
    "name:pol_x_preferred":[
        "Wodospady Agua Azul"
    ],
    "name:spa_x_preferred":[
        "Agua Azul"
    ],
    "name:swe_x_preferred":[
        "Agua Azul"
    ],
    "name:ukr_x_preferred":[
        "\u0410\u0433\u0432\u0430 \u0410\u0441\u0443\u043b\u044c"
    ],
    "wof:name":"Agua Azul",
    "wof:placetype":"locality"
},
  "geometry": {"coordinates":[-100.20471999999999,20.60271],"type":"Point"}
}