{
  "type": "Feature",
  "properties": {
    "gn:admin1_code":"12.0",
    "gn:admin2_code":"80.0",
    "gn:asciiname":"Carrizalito",
    "gn:country_code":"MX",
    "gn:dem":96,
    "gn:feature_class":"P",
    "gn:feature_code":"PPL",
    "gn:name":"Carrizalito",
    "gn:population":0,
    "gn:timezone":"America/Mexico_City",
    "iso:country":"MX",
    "name:spa_x_preferred":[
        "Carrizalito"
    ],
    "wof:name":"Carrizalito",
    "wof:placetype":"locality"
},
  "geometry": {"coordinates":[-98.76439999999999,16.60734],"type":"Point"}
}