{
  "type": "Feature",
  "properties": {
    "gn:admin1_code":"4",
    "gn:admin2_code":"3.0",
    "gn:asciiname":"El Infierno",
    "gn:country_code":"MX",
    "gn:dem":9,
    "gn:feature_class":"P",
    "gn:feature_code":"PPL",
    "gn:name":"El Infierno",
    "gn:population":0,
    "gn:timezone":"America/Merida",
    "iso:country":"MX",
    "name:spa_x_preferred":[
        "El Infierno"
    ],
    "wof:name":"El Infierno",
    "wof:placetype":"locality"
},
  "geometry": {"coordinates":[-91.05155000000001,18.70671],"type":"Point"}
}