{
  "type": "Feature",
  "properties": {
    "gn:admin1_code":"20.0",
    "gn:asciiname":"La Chamusca",
    "gn:country_code":"MX",
    "gn:dem":20,
    "gn:feature_class":"P",
    "gn:feature_code":"PPL",
    "gn:name":"La Chamusca",
    "gn:population":0,
    "gn:timezone":"America/Mexico_City",
    "iso:country":"MX",
    "name:spa_x_preferred":[
        "La Chamusca"
    ],
    "wof:name":"La Chamusca",
    "wof:placetype":"locality"
},
  "geometry": {"coordinates":[-98.22811,16.30598],"type":"Point"}
}