{
  "type": "Feature",
  "properties": {
    "gn:admin1_code":"3",
    "gn:admin2_code":"8",
    "gn:asciiname":"Las Vinoramas",
    "gn:country_code":"MX",
    "gn:dem":326,
    "gn:feature_class":"P",
    "gn:feature_code":"PPL",
    "gn:name":"Las Vinoramas",
    "gn:population":9,
    "gn:timezone":"America/Mazatlan",
    "iso:country":"MX",
    "wof:name":"Las Vinoramas",
    "wof:placetype":"locality",
    "wof:population":9
},
  "geometry": {"coordinates":[-109.81347,23.42214],"type":"Point"}
}