{
  "type": "Feature",
  "properties": {
    "gn:admin1_code":"18",
    "gn:admin2_code":"9",
    "gn:asciiname":"Aserradero",
    "gn:country_code":"MX",
    "gn:dem":1380,
    "gn:feature_class":"P",
    "gn:feature_code":"PPL",
    "gn:name":"Aserradero",
    "gn:population":29,
    "gn:timezone":"America/Mazatlan",
    "iso:country":"MX",
    "wof:name":"Aserradero",
    "wof:placetype":"locality",
    "wof:population":29
},
  "geometry": {"coordinates":[-104.65056,22.22972],"type":"Point"}
}