{
  "type": "Feature",
  "properties": {
    "gn:admin1_code":"5",
    "gn:admin2_code":"46.0",
    "gn:asciiname":"La Sierra",
    "gn:country_code":"MX",
    "gn:dem":604,
    "gn:feature_class":"P",
    "gn:feature_code":"PPL",
    "gn:name":"La Sierra",
    "gn:population":100,
    "gn:timezone":"America/Mexico_City",
    "iso:country":"MX",
    "name:ast_x_preferred":[
        "La Sierra"
    ],
    "name:ceb_x_preferred":[
        "La Sierra"
    ],
    "name:ita_x_preferred":[
        "La Sierra"
    ],
    "name:spa_x_preferred":[
        "La Sierra"
    ],
    "name:swe_x_preferred":[
        "La Sierra"
    ],
    "name:vie_x_preferred":[
        "La Sierra"
    ],
    "wof:name":"La Sierra",
    "wof:placetype":"locality",
    "wof:population":100
},
  "geometry": {"coordinates":[-93.67556,16.44556],"type":"Point"}
}