{
  "type": "Feature",
  "properties": {
    "gn:admin1_code":"25",
    "gn:admin2_code":"11.0",
    "gn:asciiname":"El Papachal",
    "gn:country_code":"MX",
    "gn:dem":7,
    "gn:feature_class":"P",
    "gn:feature_code":"PPL",
    "gn:name":"El Papachal",
    "gn:population":231,
    "gn:timezone":"America/Mazatlan",
    "iso:country":"MX",
    "wof:name":"El Papachal",
    "wof:placetype":"locality",
    "wof:population":231
},
  "geometry": {"coordinates":[-108.45999999999999,25.38528],"type":"Point"}
}