{
  "type": "Feature",
  "properties": {
    "gn:admin1_code":"30",
    "gn:admin2_code":"203.0",
    "gn:asciiname":"Linda Vista",
    "gn:country_code":"MX",
    "gn:dem":363,
    "gn:feature_class":"P",
    "gn:feature_code":"PPL",
    "gn:name":"Linda Vista",
    "gn:population":144,
    "gn:timezone":"America/Mexico_City",
    "iso:country":"MX",
    "wof:name":"Linda Vista",
    "wof:placetype":"locality",
    "wof:population":144
},
  "geometry": {"coordinates":[-97.60167,20.15222],"type":"Point"}
}