{
  "type": "Feature",
  "properties": {
    "gn:admin1_code":"32.0",
    "gn:asciiname":"La Haciendita",
    "gn:country_code":"MX",
    "gn:dem":2035,
    "gn:feature_class":"P",
    "gn:feature_code":"PPL",
    "gn:name":"La Haciendita",
    "gn:population":0,
    "gn:timezone":"America/Mexico_City",
    "iso:country":"MX",
    "name:spa_x_preferred":[
        "La Haciendita"
    ],
    "wof:name":"La Haciendita",
    "wof:placetype":"locality"
},
  "geometry": {"coordinates":[-102.72248999999999,21.55179],"type":"Point"}
}