{
  "type": "Feature",
  "properties": {
    "gn:admin1_code":"15.0",
    "gn:admin2_code":"124.0",
    "gn:asciiname":"Palo Amarillo",
    "gn:country_code":"MX",
    "gn:dem":3076,
    "gn:feature_class":"P",
    "gn:feature_code":"PPL",
    "gn:name":"Palo Amarillo",
    "gn:population":0,
    "gn:timezone":"America/Mexico_City",
    "iso:country":"MX",
    "name:spa_x_preferred":[
        "Palo Amarillo"
    ],
    "wof:name":"Palo Amarillo",
    "wof:placetype":"locality"
},
  "geometry": {"coordinates":[-100.22589000000001,19.66188],"type":"Point"}
}