{
  "type": "Feature",
  "properties": {
    "gn:admin1_code":"6.0",
    "gn:admin2_code":"2.0",
    "gn:asciiname":"El Alamo",
    "gn:country_code":"MX",
    "gn:dem":1416,
    "gn:feature_class":"P",
    "gn:feature_code":"PPL",
    "gn:name":"El Alamo",
    "gn:population":0,
    "gn:timezone":"America/Chihuahua",
    "iso:country":"MX",
    "name:und_x_variant":[
        "Rancho del Alamo",
        "El Alamo"
    ],
    "wof:name":"El Alamo",
    "wof:placetype":"locality"
},
  "geometry": {"coordinates":[-105.69293999999999,29.54178],"type":"Point"}
}