{
  "type": "Feature",
  "properties": {
    "gn:admin1_code":"19",
    "gn:admin2_code":"48.0",
    "gn:asciiname":"San Cristobal",
    "gn:country_code":"MX",
    "gn:dem":1107,
    "gn:feature_class":"P",
    "gn:feature_code":"PPL",
    "gn:name":"San Crist\u00f3bal",
    "gn:population":0,
    "gn:timezone":"America/Monterrey",
    "iso:country":"MX",
    "name:fas_x_preferred":[
        "\u0633\u0627\u0646 \u06a9\u0631\u06cc\u0633\u062a\u0648\u0628\u0627\u0644"
    ],
    "name:heb_x_preferred":[
        "\u05d0\u05d9\u05d9 \u05e1\u05df \u05db\u05e8\u05d9\u05e1\u05d8\u05d5\u05d1\u05dc"
    ],
    "name:hun_x_preferred":[
        "San Cristobal"
    ],
    "name:und_x_variant":[
        "Rancho San Crist\u00f3bal",
        "San Crist\u00f3bal"
    ],
    "wof:name":"San Cristobal",
    "wof:placetype":"locality"
},
  "geometry": {"coordinates":[-100.28999,25.44087],"type":"Point"}
}