{
  "type": "Feature",
  "properties": {
    "gn:admin1_code":"16",
    "gn:admin2_code":"98.0",
    "gn:asciiname":"Colonia Nueva Mariel [Radio Difusora]",
    "gn:country_code":"MX",
    "gn:dem":1826,
    "gn:feature_class":"P",
    "gn:feature_code":"PPL",
    "gn:name":"Colonia Nueva Mariel [Radio Difusora]",
    "gn:population":337,
    "gn:timezone":"America/Mexico_City",
    "iso:country":"MX",
    "wof:name":"Colonia Nueva Mariel [Radio Difusora]",
    "wof:placetype":"locality",
    "wof:population":337
},
  "geometry": {"coordinates":[-100.47583,19.53111],"type":"Point"}
}