{
  "type": "Feature",
  "properties": {
    "gn:admin1_code":"6",
    "gn:admin2_code":"5.0",
    "gn:asciiname":"El Nogalito",
    "gn:country_code":"MX",
    "gn:dem":1436,
    "gn:feature_class":"P",
    "gn:feature_code":"PPL",
    "gn:name":"El Nogalito",
    "gn:population":0,
    "gn:timezone":"America/Chihuahua",
    "iso:country":"MX",
    "wof:name":"El Nogalito",
    "wof:placetype":"locality"
},
  "geometry": {"coordinates":[-107.78017,30.98207],"type":"Point"}
}