{
  "type": "Feature",
  "properties": {
    "gn:admin1_code":"31",
    "gn:admin2_code":"70.0",
    "gn:asciiname":"Chac Lol",
    "gn:country_code":"MX",
    "gn:dem":13,
    "gn:feature_class":"P",
    "gn:feature_code":"PPL",
    "gn:name":"Chac Lol",
    "gn:population":0,
    "gn:timezone":"America/Merida",
    "iso:country":"MX",
    "name:spa_x_preferred":[
        "Chac Lol"
    ],
    "wof:name":"Chac Lol",
    "wof:placetype":"locality"
},
  "geometry": {"coordinates":[-88.36287,21.26542],"type":"Point"}
}