{
  "type": "Feature",
  "properties": {
    "gn:admin1_code":"18.0",
    "gn:admin2_code":"5.0",
    "gn:asciiname":"La Mina",
    "gn:country_code":"MX",
    "gn:dem":667,
    "gn:feature_class":"P",
    "gn:feature_code":"PPL",
    "gn:name":"La Mina",
    "gn:population":0,
    "gn:timezone":"America/Mazatlan",
    "iso:country":"MX",
    "name:ita_x_preferred":[
        "La Mina"
    ],
    "wof:name":"La Mina",
    "wof:placetype":"locality"
},
  "geometry": {"coordinates":[-105.26667,22.85833],"type":"Point"}
}