{
  "type": "Feature",
  "properties": {
    "gn:admin1_code":"21",
    "gn:admin2_code":"110.0",
    "gn:asciiname":"Amozoquillo Piletas",
    "gn:country_code":"MX",
    "gn:dem":2384,
    "gn:feature_class":"P",
    "gn:feature_code":"PPL",
    "gn:name":"Amozoquillo Piletas",
    "gn:population":603,
    "gn:timezone":"America/Mexico_City",
    "iso:country":"MX",
    "wof:name":"Amozoquillo Piletas",
    "wof:placetype":"locality",
    "wof:population":603
},
  "geometry": {"coordinates":[-97.39745000000001,18.83464],"type":"Point"}
}