{
  "type": "Feature",
  "properties": {
    "gn:admin1_code":"26.0",
    "gn:admin2_code":"42.0",
    "gn:asciiname":"Antonio Rosales",
    "gn:country_code":"MX",
    "gn:dem":55,
    "gn:feature_class":"P",
    "gn:feature_code":"PPL",
    "gn:name":"Antonio Rosales",
    "gn:population":0,
    "gn:timezone":"America/Hermosillo",
    "iso:country":"MX",
    "name:spa_x_preferred":[
        "Antonio Rosales"
    ],
    "name:spa_x_variant":[
        "General Antonio Rosales",
        "Las \u00c1nimas"
    ],
    "name:und_x_variant":[
        "\u00c1nimas"
    ],
    "wof:name":"Antonio Rosales",
    "wof:placetype":"locality"
},
  "geometry": {"coordinates":[-109.40621000000002,27.04037000000001],"type":"Point"}
}