{
  "type": "Feature",
  "properties": {
    "gn:admin1_code":"30.0",
    "gn:admin2_code":"155.0",
    "gn:asciiname":"Tetillas",
    "gn:country_code":"MX",
    "gn:dem":168,
    "gn:feature_class":"P",
    "gn:feature_code":"PPL",
    "gn:name":"Tetillas",
    "gn:population":410,
    "gn:timezone":"America/Mexico_City",
    "iso:country":"MX",
    "name:spa_x_preferred":[
        "Tetillas"
    ],
    "wof:name":"Tetillas",
    "wof:placetype":"locality",
    "wof:population":410
},
  "geometry": {"coordinates":[-98.13222,21.30111],"type":"Point"}
}