{
  "type": "Feature",
  "properties": {
    "gn:admin1_code":"13",
    "gn:admin2_code":"33.0",
    "gn:asciiname":"Tetipanchalco",
    "gn:country_code":"MX",
    "gn:dem":683,
    "gn:feature_class":"P",
    "gn:feature_code":"PPL",
    "gn:name":"Tetipanchalco",
    "gn:population":0,
    "gn:timezone":"America/Mexico_City",
    "iso:country":"MX",
    "name:spa_x_preferred":[
        "Tetipanchalco"
    ],
    "wof:name":"Tetipanchalco",
    "wof:placetype":"locality"
},
  "geometry": {"coordinates":[-98.79935999999999,20.87811],"type":"Point"}
}