{
  "type": "Feature",
  "properties": {
    "gn:admin1_code":"20",
    "gn:admin2_code":"332.0",
    "gn:asciiname":"Santo Domingo Tlatayapan",
    "gn:country_code":"MX",
    "gn:dem":2215,
    "gn:feature_class":"P",
    "gn:feature_code":"PPL",
    "gn:name":"Santo Domingo Tlatayapan",
    "gn:population":0,
    "gn:timezone":"America/Mexico_City",
    "iso:country":"MX",
    "name:spa_x_preferred":[
        "Santo Domingo Tlatayapan"
    ],
    "wof:name":"Santo Domingo Tlatayapan",
    "wof:placetype":"locality"
},
  "geometry": {"coordinates":[-97.35693999999999,17.43028],"type":"Point"}
}