{
  "type": "Feature",
  "properties": {
    "gn:admin1_code":"17",
    "gn:admin2_code":"7.0",
    "gn:asciiname":"Colonia Milpillas",
    "gn:country_code":"MX",
    "gn:dem":1574,
    "gn:feature_class":"P",
    "gn:feature_code":"PPL",
    "gn:name":"Colonia Milpillas",
    "gn:population":769,
    "gn:timezone":"America/Mexico_City",
    "iso:country":"MX",
    "wof:name":"Colonia Milpillas",
    "wof:placetype":"locality",
    "wof:population":769
},
  "geometry": {"coordinates":[-99.18639,18.94639],"type":"Point"}
}