{
  "type": "Feature",
  "properties": {
    "gn:admin1_code":"21",
    "gn:admin2_code":"152.0",
    "gn:asciiname":"San Antonio Xicotenco",
    "gn:country_code":"MX",
    "gn:dem":2368,
    "gn:feature_class":"P",
    "gn:feature_code":"PPL",
    "gn:name":"San Antonio Xicotenco",
    "gn:population":145,
    "gn:timezone":"America/Mexico_City",
    "iso:country":"MX",
    "wof:name":"San Antonio Xicotenco",
    "wof:placetype":"locality",
    "wof:population":145
},
  "geometry": {"coordinates":[-97.71217,19.1368],"type":"Point"}
}