{
  "type": "Feature",
  "properties": {
    "gn:admin1_code":"16.0",
    "gn:asciiname":"Rancho San Lorenzo",
    "gn:country_code":"MX",
    "gn:dem":1986,
    "gn:feature_class":"P",
    "gn:feature_code":"PPL",
    "gn:name":"Rancho San Lorenzo",
    "gn:population":0,
    "gn:timezone":"America/Mexico_City",
    "iso:country":"MX",
    "name:spa_x_preferred":[
        "Rancho San Lorenzo"
    ],
    "wof:name":"Rancho San Lorenzo",
    "wof:placetype":"locality"
},
  "geometry": {"coordinates":[-100.43071999999999,19.95397],"type":"Point"}
}