{
  "type": "Feature",
  "properties": {
    "gn:admin1_code":"5",
    "gn:admin2_code":"25.0",
    "gn:asciiname":"Carmen Tonapac",
    "gn:country_code":"MX",
    "gn:dem":654,
    "gn:feature_class":"P",
    "gn:feature_code":"PPL",
    "gn:name":"Carmen Tonapac",
    "gn:population":313,
    "gn:timezone":"America/Mexico_City",
    "iso:country":"MX",
    "wof:name":"Carmen Tonapac",
    "wof:placetype":"locality",
    "wof:population":313
},
  "geometry": {"coordinates":[-93.18083,17.30806],"type":"Point"}
}