{
  "type": "Feature",
  "properties": {
    "gn:admin1_code":"24.0",
    "gn:asciiname":"Plan del Cerrito",
    "gn:country_code":"MX",
    "gn:dem":1144,
    "gn:feature_class":"P",
    "gn:feature_code":"PPL",
    "gn:name":"Plan del Cerrito",
    "gn:population":0,
    "gn:timezone":"America/Mexico_City",
    "iso:country":"MX",
    "name:spa_x_preferred":[
        "Plan del Cerrito"
    ],
    "wof:name":"Plan del Cerrito",
    "wof:placetype":"locality"
},
  "geometry": {"coordinates":[-99.66363,21.91317],"type":"Point"}
}