{
  "type": "Feature",
  "properties": {
    "gn:admin1_code":"14",
    "gn:admin2_code":"104.0",
    "gn:asciiname":"Toriles",
    "gn:country_code":"MX",
    "gn:dem":1669,
    "gn:feature_class":"P",
    "gn:feature_code":"PPL",
    "gn:name":"Toriles",
    "gn:population":0,
    "gn:timezone":"America/Mexico_City",
    "iso:country":"MX",
    "name:spa_x_preferred":[
        "Toriles"
    ],
    "wof:name":"Toriles",
    "wof:placetype":"locality"
},
  "geometry": {"coordinates":[-103.52582,22.1034],"type":"Point"}
}