{
  "type": "Feature",
  "properties": {
    "gn:admin1_code":"16.0",
    "gn:admin2_code":"96.0",
    "gn:asciiname":"Tepeguajillos",
    "gn:country_code":"MX",
    "gn:dem":813,
    "gn:feature_class":"P",
    "gn:feature_code":"PPL",
    "gn:name":"Tepeguajillos",
    "gn:population":0,
    "gn:timezone":"America/Mexico_City",
    "iso:country":"MX",
    "name:spa_x_preferred":[
        "Tepeguajillos"
    ],
    "wof:name":"Tepeguajillos",
    "wof:placetype":"locality"
},
  "geometry": {"coordinates":[-102.86373,18.50091],"type":"Point"}
}