{
  "type": "Feature",
  "properties": {
    "gn:admin1_code":"5",
    "gn:admin2_code":"19",
    "gn:asciiname":"Pashton Acapulco",
    "gn:country_code":"MX",
    "gn:dem":1673,
    "gn:feature_class":"P",
    "gn:feature_code":"PPL",
    "gn:name":"Pasht\u00f3n Acapulco",
    "gn:population":16,
    "gn:timezone":"America/Mexico_City",
    "iso:country":"MX",
    "name:und_x_variant":[
        "Pasht\u00f3n Acapulco"
    ],
    "wof:name":"Pashton Acapulco",
    "wof:placetype":"locality",
    "wof:population":16
},
  "geometry": {"coordinates":[-92.16224,16.23735],"type":"Point"}
}