{
  "type": "Feature",
  "properties": {
    "gn:admin1_code":"5.0",
    "gn:admin2_code":"70.0",
    "gn:asciiname":"San Jose las Pilas",
    "gn:country_code":"MX",
    "gn:dem":2836,
    "gn:feature_class":"P",
    "gn:feature_code":"PPL",
    "gn:name":"San Jos\u00e9 las Pilas",
    "gn:population":0,
    "gn:timezone":"America/Mexico_City",
    "iso:country":"MX",
    "name:spa_x_preferred":[
        "San Jos\u00e9 las Pilas"
    ],
    "wof:name":"San Jose las Pilas",
    "wof:placetype":"locality"
},
  "geometry": {"coordinates":[-92.27108,15.46243],"type":"Point"}
}