{
  "type": "Feature",
  "properties": {
    "gn:admin1_code":"15",
    "gn:admin2_code":"114.0",
    "gn:asciiname":"Barrio el Vivero",
    "gn:country_code":"MX",
    "gn:dem":2579,
    "gn:feature_class":"P",
    "gn:feature_code":"PPL",
    "gn:name":"Barrio el Vivero",
    "gn:population":1371,
    "gn:timezone":"America/Mexico_City",
    "iso:country":"MX",
    "wof:name":"Barrio el Vivero",
    "wof:placetype":"locality",
    "wof:population":1371
},
  "geometry": {"coordinates":[-100.03528,19.45306],"type":"Point"}
}