{
  "type": "Feature",
  "properties": {
    "gn:admin1_code":"12",
    "gn:admin2_code":"22.0",
    "gn:asciiname":"Los Pozos",
    "gn:country_code":"MX",
    "gn:dem":356,
    "gn:feature_class":"P",
    "gn:feature_code":"PPL",
    "gn:name":"Los Pozos",
    "gn:population":154,
    "gn:timezone":"America/Mexico_City",
    "iso:country":"MX",
    "wof:name":"Los Pozos",
    "wof:placetype":"locality",
    "wof:population":154
},
  "geometry": {"coordinates":[-100.81843000000001,18.31898],"type":"Point"}
}