{
  "type": "Feature",
  "properties": {
    "gn:admin1_code":"16",
    "gn:admin2_code":"31",
    "gn:asciiname":"La Cima",
    "gn:country_code":"MX",
    "gn:dem":2715,
    "gn:feature_class":"P",
    "gn:feature_code":"PPL",
    "gn:name":"La Cima",
    "gn:population":51,
    "gn:timezone":"America/Mexico_City",
    "iso:country":"MX",
    "wof:name":"La Cima",
    "wof:placetype":"locality",
    "wof:population":51
},
  "geometry": {"coordinates":[-100.21111000000001,20.16972],"type":"Point"}
}