{
  "type": "Feature",
  "properties": {
    "gn:admin1_code":"5.0",
    "gn:admin2_code":"86.0",
    "gn:asciiname":"La Cambiosa",
    "gn:country_code":"MX",
    "gn:dem":852,
    "gn:feature_class":"P",
    "gn:feature_code":"PPL",
    "gn:name":"La Cambiosa",
    "gn:population":0,
    "gn:timezone":"America/Mexico_City",
    "iso:country":"MX",
    "name:spa_x_preferred":[
        "La Cambiosa"
    ],
    "wof:name":"La Cambiosa",
    "wof:placetype":"locality"
},
  "geometry": {"coordinates":[-93.1065,16.51419],"type":"Point"}
}