{
  "type": "Feature",
  "properties": {
    "gn:admin1_code":"20",
    "gn:admin2_code":"236",
    "gn:asciiname":"Morelos",
    "gn:country_code":"MX",
    "gn:dem":2153,
    "gn:feature_class":"P",
    "gn:feature_code":"PPL",
    "gn:name":"Morelos",
    "gn:population":38,
    "gn:timezone":"America/Mexico_City",
    "iso:country":"MX",
    "wof:name":"Morelos",
    "wof:placetype":"locality",
    "wof:population":38
},
  "geometry": {"coordinates":[-96.38861,16.05278],"type":"Point"}
}