{
  "type": "Feature",
  "properties": {
    "gn:admin1_code":"6",
    "gn:admin2_code":"30.0",
    "gn:asciiname":"Yucatan",
    "gn:country_code":"MX",
    "gn:dem":1770,
    "gn:feature_class":"P",
    "gn:feature_code":"PPL",
    "gn:name":"Yucat\u00e1n",
    "gn:population":5,
    "gn:timezone":"America/Chihuahua",
    "iso:country":"MX",
    "name:spa_x_preferred":[
        "Yucat\u00e1n"
    ],
    "wof:name":"Yucatan",
    "wof:placetype":"locality",
    "wof:population":5
},
  "geometry": {"coordinates":[-108.29881,27.24909],"type":"Point"}
}