{
  "type": "Feature",
  "properties": {
    "gn:admin1_code":"4",
    "gn:admin2_code":"3.0",
    "gn:asciiname":"Capricornio",
    "gn:country_code":"MX",
    "gn:dem":15,
    "gn:feature_class":"P",
    "gn:feature_code":"PPL",
    "gn:name":"Capricornio",
    "gn:population":5,
    "gn:timezone":"America/Merida",
    "iso:country":"MX",
    "name:ita_x_preferred":[
        "Capricornio"
    ],
    "name:spa_x_preferred":[
        "Capricornio"
    ],
    "wof:name":"Capricornio",
    "wof:placetype":"locality",
    "wof:population":5
},
  "geometry": {"coordinates":[-91.23222,18.325],"type":"Point"}
}