{
  "type": "Feature",
  "properties": {
    "gn:admin1_code":"11",
    "gn:admin2_code":"5",
    "gn:asciiname":"Fandila",
    "gn:country_code":"MX",
    "gn:dem":1795,
    "gn:feature_class":"P",
    "gn:feature_code":"PPL",
    "gn:name":"Fandila",
    "gn:population":18,
    "gn:timezone":"America/Mexico_City",
    "iso:country":"MX",
    "wof:name":"Fandila",
    "wof:placetype":"locality",
    "wof:population":18
},
  "geometry": {"coordinates":[-100.49778000000001,20.59056],"type":"Point"}
}