{
  "type": "Feature",
  "properties": {
    "gn:admin1_code":"12",
    "gn:admin2_code":"28.0",
    "gn:asciiname":"Trigomila",
    "gn:country_code":"MX",
    "gn:dem":1395,
    "gn:feature_class":"P",
    "gn:feature_code":"PPL",
    "gn:name":"Trigomila",
    "gn:population":0,
    "gn:timezone":"America/Mexico_City",
    "iso:country":"MX",
    "wof:name":"Trigomila",
    "wof:placetype":"locality"
},
  "geometry": {"coordinates":[-99.12957,17.58269],"type":"Point"}
}