{
  "type": "Feature",
  "properties": {
    "gn:admin1_code":"14.0",
    "gn:asciiname":"Betania",
    "gn:country_code":"MX",
    "gn:dem":1874,
    "gn:feature_class":"P",
    "gn:feature_code":"PPL",
    "gn:name":"Betania",
    "gn:population":0,
    "gn:timezone":"America/Mexico_City",
    "iso:country":"MX",
    "name:bre_x_preferred":[
        "Betania"
    ],
    "name:ceb_x_preferred":[
        "Betania"
    ],
    "name:deu_x_preferred":[
        "Betania"
    ],
    "name:ita_x_preferred":[
        "Betania"
    ],
    "name:nld_x_preferred":[
        "Betania"
    ],
    "name:nor_x_preferred":[
        "Betania"
    ],
    "name:ron_x_preferred":[
        "Betania"
    ],
    "name:sco_x_preferred":[
        "Betania"
    ],
    "name:spa_x_preferred":[
        "Betania"
    ],
    "name:swe_x_preferred":[
        "Betania"
    ],
    "name:tgl_x_preferred":[
        "Betania"
    ],
    "name:war_x_preferred":[
        "Betania"
    ],
    "wof:name":"Betania",
    "wof:placetype":"locality"
},
  "geometry": {"coordinates":[-102.03691999999999,21.12287],"type":"Point"}
}