{
  "type": "Feature",
  "properties": {
    "gn:admin1_code":"13",
    "gn:admin2_code":"3",
    "gn:asciiname":"Manzana de Golondrinas",
    "gn:country_code":"MX",
    "gn:dem":2011,
    "gn:feature_class":"P",
    "gn:feature_code":"PPL",
    "gn:name":"Manzana de Golondrinas",
    "gn:population":41,
    "gn:timezone":"America/Mexico_City",
    "iso:country":"MX",
    "wof:name":"Manzana de Golondrinas",
    "wof:placetype":"locality",
    "wof:population":41
},
  "geometry": {"coordinates":[-98.81805,20.28817],"type":"Point"}
}