{
  "type": "Feature",
  "properties": {
    "gn:admin1_code":"21",
    "gn:admin2_code":"76.0",
    "gn:asciiname":"El Reparo",
    "gn:country_code":"MX",
    "gn:dem":1074,
    "gn:feature_class":"P",
    "gn:feature_code":"PPL",
    "gn:name":"El Reparo",
    "gn:population":95,
    "gn:timezone":"America/Mexico_City",
    "iso:country":"MX",
    "wof:name":"El Reparo",
    "wof:placetype":"locality",
    "wof:population":95
},
  "geometry": {"coordinates":[-97.28598,19.90318],"type":"Point"}
}