{
  "type": "Feature",
  "properties": {
    "gn:admin1_code":"9",
    "gn:admin2_code":"9",
    "gn:asciiname":"Mecatlan (Rancho el Refugio)",
    "gn:country_code":"MX",
    "gn:dem":2637,
    "gn:feature_class":"P",
    "gn:feature_code":"PPL",
    "gn:name":"Mecatl\u00e1n (Rancho el Refugio)",
    "gn:population":42,
    "gn:timezone":"America/Mexico_City",
    "iso:country":"MX",
    "name:und_x_variant":[
        "Mecatl\u00e1n (Rancho el Refugio)"
    ],
    "wof:name":"Mecatlan (Rancho el Refugio)",
    "wof:placetype":"locality",
    "wof:population":42
},
  "geometry": {"coordinates":[-99.0843,19.20991],"type":"Point"}
}