{
  "type": "Feature",
  "properties": {
    "gn:admin1_code":"1",
    "gn:admin2_code":"6",
    "gn:asciiname":"Sector de Produccion de la Escuela Secundaria Tecnica Numero 3",
    "gn:country_code":"MX",
    "gn:dem":1903,
    "gn:feature_class":"P",
    "gn:feature_code":"PPL",
    "gn:name":"Sector de Producci\u00f3n de la Escuela Secundaria T\u00e9cnica N\u00famero 3",
    "gn:population":13,
    "gn:timezone":"America/Mexico_City",
    "iso:country":"MX",
    "name:und_x_variant":[
        "Sector de Producci\u00f3n de la Escuela Secundaria T\u00e9cnica N\u00famero 3"
    ],
    "wof:name":"Sector de Produccion de la Escuela Secundaria Tecnica Numero 3",
    "wof:placetype":"locality",
    "wof:population":13
},
  "geometry": {"coordinates":[-102.26167,22.16028],"type":"Point"}
}