{
  "type": "Feature",
  "properties": {
    "gn:admin1_code":"21",
    "gn:admin2_code":"10.0",
    "gn:asciiname":"San Isidro Labrador (Teopuxco)",
    "gn:country_code":"MX",
    "gn:dem":1271,
    "gn:feature_class":"P",
    "gn:feature_code":"PPL",
    "gn:name":"San Isidro Labrador (Teopuxco)",
    "gn:population":264,
    "gn:timezone":"America/Mexico_City",
    "iso:country":"MX",
    "wof:name":"San Isidro Labrador (Teopuxco)",
    "wof:placetype":"locality",
    "wof:population":264
},
  "geometry": {"coordinates":[-97.25611000000001,18.395],"type":"Point"}
}