{
  "type": "Feature",
  "properties": {
    "gn:admin1_code":"1",
    "gn:admin2_code":"9",
    "gn:asciiname":"Granja Susy",
    "gn:country_code":"MX",
    "gn:dem":1934,
    "gn:feature_class":"P",
    "gn:feature_code":"PPL",
    "gn:name":"Granja Susy",
    "gn:population":20,
    "gn:timezone":"America/Mexico_City",
    "iso:country":"MX",
    "wof:name":"Granja Susy",
    "wof:placetype":"locality",
    "wof:population":20
},
  "geometry": {"coordinates":[-102.2325,22.29639],"type":"Point"}
}