{
  "type": "Feature",
  "properties": {
    "gn:admin1_code":"14.0",
    "gn:admin2_code":"110.0",
    "gn:asciiname":"Villa Marqueza",
    "gn:country_code":"MX",
    "gn:dem":1321,
    "gn:feature_class":"P",
    "gn:feature_code":"PPL",
    "gn:name":"Villa Marqueza",
    "gn:population":0,
    "gn:timezone":"America/Mexico_City",
    "iso:country":"MX",
    "name:spa_x_preferred":[
        "Villa Marqueza"
    ],
    "wof:name":"Villa Marqueza",
    "wof:placetype":"locality"
},
  "geometry": {"coordinates":[-104.26394000000001,20.02047],"type":"Point"}
}