{
  "type": "Feature",
  "properties": {
    "gn:admin1_code":"11",
    "gn:admin2_code":"8",
    "gn:asciiname":"Tortugas",
    "gn:country_code":"MX",
    "gn:dem":1753,
    "gn:feature_class":"P",
    "gn:feature_code":"PPL",
    "gn:name":"Tortugas",
    "gn:population":48,
    "gn:timezone":"America/Mexico_City",
    "iso:country":"MX",
    "wof:name":"Tortugas",
    "wof:placetype":"locality",
    "wof:population":48
},
  "geometry": {"coordinates":[-101.76721999999999,20.72722000000001],"type":"Point"}
}