{
  "type": "Feature",
  "properties": {
    "gn:admin1_code":"6.0",
    "gn:admin2_code":"65.0",
    "gn:asciiname":"La Laja",
    "gn:country_code":"MX",
    "gn:dem":1973,
    "gn:feature_class":"P",
    "gn:feature_code":"PPL",
    "gn:name":"La Laja",
    "gn:population":0,
    "gn:timezone":"America/Chihuahua",
    "iso:country":"MX",
    "name:ita_x_preferred":[
        "La Laja"
    ],
    "name:spa_x_preferred":[
        "La Laja"
    ],
    "name:zho_x_preferred":[
        "\u62c9\u62c9\u54c8"
    ],
    "wof:name":"La Laja",
    "wof:placetype":"locality"
},
  "geometry": {"coordinates":[-107.96663999999998,27.2815],"type":"Point"}
}