{
  "type": "Feature",
  "properties": {
    "gn:admin1_code":"5.0",
    "gn:asciiname":"Crucero Monte Libano",
    "gn:country_code":"MX",
    "gn:dem":634,
    "gn:feature_class":"P",
    "gn:feature_code":"PPL",
    "gn:name":"Crucero Monte L\u00edbano",
    "gn:population":0,
    "gn:timezone":"America/Mexico_City",
    "iso:country":"MX",
    "name:spa_x_preferred":[
        "Crucero Monte L\u00edbano"
    ],
    "wof:name":"Crucero Monte Libano",
    "wof:placetype":"locality"
},
  "geometry": {"coordinates":[-91.62444000000001,16.9063],"type":"Point"}
}