{
  "type": "Feature",
  "properties": {
    "gn:admin1_code":"6.0",
    "gn:admin2_code":"41.0",
    "gn:asciiname":"Los Gavilanes",
    "gn:country_code":"MX",
    "gn:dem":1990,
    "gn:feature_class":"P",
    "gn:feature_code":"PPL",
    "gn:name":"Los Gavilanes",
    "gn:population":0,
    "gn:timezone":"America/Chihuahua",
    "iso:country":"MX",
    "name:spa_x_preferred":[
        "Los Gavilanes"
    ],
    "name:und_x_variant":[
        "Gavilanes"
    ],
    "wof:name":"Los Gavilanes",
    "wof:placetype":"locality"
},
  "geometry": {"coordinates":[-108.03717,27.86219],"type":"Point"}
}