{
  "type": "Feature",
  "properties": {
    "gn:admin1_code":"32.0",
    "gn:admin2_code":"25.0",
    "gn:asciiname":"San Angel",
    "gn:country_code":"MX",
    "gn:dem":1988,
    "gn:feature_class":"P",
    "gn:feature_code":"PPL",
    "gn:name":"San \u00c1ngel",
    "gn:population":0,
    "gn:timezone":"America/Mexico_City",
    "iso:country":"MX",
    "name:spa_x_preferred":[
        "San \u00c1ngel"
    ],
    "wof:name":"San Angel",
    "wof:placetype":"locality"
},
  "geometry": {"coordinates":[-102.2685,22.45103],"type":"Point"}
}