{
  "type": "Feature",
  "properties": {
    "gn:admin1_code":"10",
    "gn:admin2_code":"9.0",
    "gn:asciiname":"San Francisco de Los Cano",
    "gn:country_code":"MX",
    "gn:dem":2337,
    "gn:feature_class":"P",
    "gn:feature_code":"PPL",
    "gn:name":"San Francisco de Los Cano",
    "gn:population":0,
    "gn:timezone":"America/Monterrey",
    "iso:country":"MX",
    "name:spa_x_preferred":[
        "San Francisco de Los Cano"
    ],
    "name:und_x_variant":[
        "San Franciscisco de los Carros",
        "San Francisco",
        "San Francisco de los Canos"
    ],
    "wof:name":"San Francisco de Los Cano",
    "wof:placetype":"locality"
},
  "geometry": {"coordinates":[-106.48393,25.8364],"type":"Point"}
}