{
  "type": "Feature",
  "properties": {
    "gn:admin1_code":"10",
    "gn:admin2_code":"14.0",
    "gn:asciiname":"El Agua Caliente",
    "gn:country_code":"MX",
    "gn:dem":1376,
    "gn:feature_class":"P",
    "gn:feature_code":"PPL",
    "gn:name":"El Agua Caliente",
    "gn:population":0,
    "gn:timezone":"America/Monterrey",
    "iso:country":"MX",
    "name:spa_x_preferred":[
        "El Agua Caliente"
    ],
    "wof:name":"El Agua Caliente",
    "wof:placetype":"locality"
},
  "geometry": {"coordinates":[-104.42993,23.40411],"type":"Point"}
}