{
  "type": "Feature",
  "properties": {
    "gn:admin1_code":"26.0",
    "gn:admin2_code":"52.0",
    "gn:asciiname":"Cajon de los Lobos",
    "gn:country_code":"MX",
    "gn:dem":1008,
    "gn:feature_class":"P",
    "gn:feature_code":"PPL",
    "gn:name":"Caj\u00f3n de los Lobos",
    "gn:population":0,
    "gn:timezone":"America/Hermosillo",
    "iso:country":"MX",
    "name:spa_x_preferred":[
        "Caj\u00f3n de los Lobos"
    ],
    "wof:name":"Cajon de los Lobos",
    "wof:placetype":"locality"
},
  "geometry": {"coordinates":[-108.98989,29.33298],"type":"Point"}
}