{
  "type": "Feature",
  "properties": {
    "gn:admin1_code":"14.0",
    "gn:admin2_code":"18.0",
    "gn:asciiname":"El Tapatio",
    "gn:country_code":"MX",
    "gn:dem":1544,
    "gn:feature_class":"P",
    "gn:feature_code":"PPL",
    "gn:name":"El Tapat\u00edo",
    "gn:population":0,
    "gn:timezone":"America/Mexico_City",
    "iso:country":"MX",
    "name:spa_x_preferred":[
        "El Tapat\u00edo"
    ],
    "wof:name":"El Tapatio",
    "wof:placetype":"locality"
},
  "geometry": {"coordinates":[-102.48869999999999,20.42521],"type":"Point"}
}