{
  "type": "Feature",
  "properties": {
    "gn:admin1_code":"18",
    "gn:admin2_code":"9",
    "gn:asciiname":"La Polvareda (Higueral de Don Pancho)",
    "gn:country_code":"MX",
    "gn:dem":479,
    "gn:feature_class":"P",
    "gn:feature_code":"PPL",
    "gn:name":"La Polvareda (Higueral de Don Pancho)",
    "gn:population":17,
    "gn:timezone":"America/Mazatlan",
    "iso:country":"MX",
    "wof:name":"La Polvareda (Higueral de Don Pancho)",
    "wof:placetype":"locality",
    "wof:population":17
},
  "geometry": {"coordinates":[-104.51611,21.68028],"type":"Point"}
}