{
  "type": "Feature",
  "properties": {
    "gn:admin1_code":"10",
    "gn:admin2_code":"14",
    "gn:asciiname":"Sudai Sabar Mir",
    "gn:country_code":"MX",
    "gn:dem":2397,
    "gn:feature_class":"P",
    "gn:feature_code":"PPL",
    "gn:name":"Sudai Sabar Mir",
    "gn:population":9,
    "gn:timezone":"America/Monterrey",
    "iso:country":"MX",
    "wof:name":"Sudai Sabar Mir",
    "wof:placetype":"locality",
    "wof:population":9
},
  "geometry": {"coordinates":[-104.51134999999999,22.82142],"type":"Point"}
}