{
  "type": "Feature",
  "properties": {
    "gn:admin1_code":"5",
    "gn:admin2_code":"52",
    "gn:asciiname":"El Recreo",
    "gn:country_code":"MX",
    "gn:dem":1528,
    "gn:feature_class":"P",
    "gn:feature_code":"PPL",
    "gn:name":"El Recreo",
    "gn:population":14,
    "gn:timezone":"America/Mexico_City",
    "iso:country":"MX",
    "wof:name":"El Recreo",
    "wof:placetype":"locality",
    "wof:population":14
},
  "geometry": {"coordinates":[-91.87139000000001,16.27861],"type":"Point"}
}