{
  "type": "Feature",
  "properties": {
    "gn:admin1_code":"16",
    "gn:admin2_code":"54.0",
    "gn:asciiname":"San Miguel (Huango el Viejo)",
    "gn:country_code":"MX",
    "gn:dem":2302,
    "gn:feature_class":"P",
    "gn:feature_code":"PPL",
    "gn:name":"San Miguel (Huango el Viejo)",
    "gn:population":217,
    "gn:timezone":"America/Mexico_City",
    "iso:country":"MX",
    "wof:name":"San Miguel (Huango el Viejo)",
    "wof:placetype":"locality",
    "wof:population":217
},
  "geometry": {"coordinates":[-101.45528,19.97972],"type":"Point"}
}