{
  "type": "Feature",
  "properties": {
    "gn:admin1_code":"6",
    "gn:admin2_code":"46",
    "gn:asciiname":"Los Novillos",
    "gn:country_code":"MX",
    "gn:dem":1043,
    "gn:feature_class":"P",
    "gn:feature_code":"PPL",
    "gn:name":"Los Novillos",
    "gn:population":12,
    "gn:timezone":"America/Mazatlan",
    "iso:country":"MX",
    "wof:name":"Los Novillos",
    "wof:placetype":"locality",
    "wof:population":12
},
  "geometry": {"coordinates":[-107.90488999999999,26.51688],"type":"Point"}
}