{
  "type": "Feature",
  "properties": {
    "gn:admin1_code":"11.0",
    "gn:admin2_code":"30.0",
    "gn:asciiname":"La Chiripa",
    "gn:country_code":"MX",
    "gn:dem":2358,
    "gn:feature_class":"P",
    "gn:feature_code":"PPL",
    "gn:name":"La Chiripa",
    "gn:population":0,
    "gn:timezone":"America/Mexico_City",
    "iso:country":"MX",
    "name:spa_x_preferred":[
        "La Chiripa"
    ],
    "wof:name":"La Chiripa",
    "wof:placetype":"locality"
},
  "geometry": {"coordinates":[-101.46961,21.25889],"type":"Point"}
}