{
  "type": "Feature",
  "properties": {
    "gn:admin1_code":"12",
    "gn:admin2_code":"12.0",
    "gn:asciiname":"El Zanate",
    "gn:country_code":"MX",
    "gn:dem":400,
    "gn:feature_class":"P",
    "gn:feature_code":"PPL",
    "gn:name":"El Zanate",
    "gn:population":165,
    "gn:timezone":"America/Mexico_City",
    "iso:country":"MX",
    "wof:name":"El Zanate",
    "wof:placetype":"locality",
    "wof:population":165
},
  "geometry": {"coordinates":[-99.13943999999999,17.02667000000001],"type":"Point"}
}