{
  "type": "Feature",
  "properties": {
    "gn:admin1_code":"5",
    "gn:admin2_code":"30.0",
    "gn:asciiname":"San Juan las Pilas",
    "gn:country_code":"MX",
    "gn:dem":621,
    "gn:feature_class":"P",
    "gn:feature_code":"PPL",
    "gn:name":"San Juan las Pilas",
    "gn:population":5,
    "gn:timezone":"America/Mexico_City",
    "iso:country":"MX",
    "wof:name":"San Juan las Pilas",
    "wof:placetype":"locality",
    "wof:population":5
},
  "geometry": {"coordinates":[-92.27333,15.82972],"type":"Point"}
}