{
  "type": "Feature",
  "properties": {
    "gn:admin1_code":"28.0",
    "gn:admin2_code":"13.0",
    "gn:asciiname":"Las Lomas",
    "gn:country_code":"MX",
    "gn:dem":181,
    "gn:feature_class":"P",
    "gn:feature_code":"PPL",
    "gn:name":"Las Lomas",
    "gn:population":4,
    "gn:timezone":"America/Monterrey",
    "iso:country":"MX",
    "name:ceb_x_preferred":[
        "Las Lomas"
    ],
    "name:deu_x_preferred":[
        "Las Lomas"
    ],
    "name:ita_x_preferred":[
        "Las Lomas"
    ],
    "name:nld_x_preferred":[
        "Las Lomas"
    ],
    "name:por_x_preferred":[
        "Las Lomas"
    ],
    "name:sco_x_preferred":[
        "Las Lomas"
    ],
    "name:spa_x_preferred":[
        "Las Lomas"
    ],
    "name:srp_x_preferred":[
        "\u041b\u0430\u0441 \u041b\u043e\u043c\u0430\u0441"
    ],
    "name:swe_x_preferred":[
        "Las Lomas"
    ],
    "name:vol_x_preferred":[
        "Las Lomas"
    ],
    "wof:name":"Las Lomas",
    "wof:placetype":"locality",
    "wof:population":4
},
  "geometry": {"coordinates":[-99.04722,23.91556],"type":"Point"}
}