{
  "type": "Feature",
  "properties": {
    "gn:admin1_code":"17",
    "gn:admin2_code":"23",
    "gn:asciiname":"Fraccionamiento los Robles",
    "gn:country_code":"MX",
    "gn:dem":2377,
    "gn:feature_class":"P",
    "gn:feature_code":"PPL",
    "gn:name":"Fraccionamiento los Robles",
    "gn:population":35,
    "gn:timezone":"America/Mexico_City",
    "iso:country":"MX",
    "wof:name":"Fraccionamiento los Robles",
    "wof:placetype":"locality",
    "wof:population":35
},
  "geometry": {"coordinates":[-98.96509,19.02894],"type":"Point"}
}