{
  "type": "Feature",
  "properties": {
    "gn:admin1_code":"20",
    "gn:admin2_code":"482.0",
    "gn:asciiname":"La Palma del Coyul",
    "gn:country_code":"MX",
    "gn:dem":144,
    "gn:feature_class":"P",
    "gn:feature_code":"PPL",
    "gn:name":"La Palma del Coyul",
    "gn:population":135,
    "gn:timezone":"America/Mexico_City",
    "iso:country":"MX",
    "wof:name":"La Palma del Coyul",
    "wof:placetype":"locality",
    "wof:population":135
},
  "geometry": {"coordinates":[-98.08222000000001,16.30027999999999],"type":"Point"}
}