{
  "type": "Feature",
  "properties": {
    "gn:admin1_code":"12",
    "gn:admin2_code":"19",
    "gn:asciiname":"Tehuixchio",
    "gn:country_code":"MX",
    "gn:dem":909,
    "gn:feature_class":"P",
    "gn:feature_code":"PPL",
    "gn:name":"Tehuixchio",
    "gn:population":11,
    "gn:timezone":"America/Mexico_City",
    "iso:country":"MX",
    "wof:name":"Tehuixchio",
    "wof:placetype":"locality",
    "wof:population":11
},
  "geometry": {"coordinates":[-99.04696,18.01883],"type":"Point"}
}