{
  "type": "Feature",
  "properties": {
    "gn:admin1_code":"10.0",
    "gn:admin2_code":"4.0",
    "gn:asciiname":"La Curena de Abajo",
    "gn:country_code":"MX",
    "gn:dem":1483,
    "gn:feature_class":"P",
    "gn:feature_code":"PPL",
    "gn:name":"La Cure\u00f1a de Abajo",
    "gn:population":0,
    "gn:timezone":"America/Monterrey",
    "iso:country":"MX",
    "name:spa_x_preferred":[
        "La Cure\u00f1a de Abajo"
    ],
    "name:und_x_variant":[
        "Rancho La Cure\u00f1a",
        "Cure\u00f1a",
        "La Cure\u00f1a"
    ],
    "wof:name":"La Curena de Abajo",
    "wof:placetype":"locality"
},
  "geometry": {"coordinates":[-103.62285,24.97819],"type":"Point"}
}