{
  "type": "Feature",
  "properties": {
    "gn:admin1_code":"23",
    "gn:admin2_code":"7.0",
    "gn:asciiname":"Pacchen",
    "gn:country_code":"MX",
    "gn:dem":16,
    "gn:feature_class":"P",
    "gn:feature_code":"PPL",
    "gn:name":"Pacchen",
    "gn:population":131,
    "gn:timezone":"America/Cancun",
    "iso:country":"MX",
    "wof:name":"Pacchen",
    "wof:placetype":"locality",
    "wof:population":131
},
  "geometry": {"coordinates":[-87.58972,20.63667],"type":"Point"}
}