{
  "type": "Feature",
  "properties": {
    "gn:admin1_code":"30.0",
    "gn:admin2_code":"141.0",
    "gn:asciiname":"Primero de Mayo",
    "gn:country_code":"MX",
    "gn:dem":602,
    "gn:feature_class":"P",
    "gn:feature_code":"PPL",
    "gn:name":"Primero de Mayo",
    "gn:population":7,
    "gn:timezone":"America/Mexico_City",
    "iso:country":"MX",
    "name:spa_x_preferred":[
        "Primero de Mayo"
    ],
    "wof:name":"Primero de Mayo",
    "wof:placetype":"locality",
    "wof:population":7
},
  "geometry": {"coordinates":[-95.2375,18.60972000000001],"type":"Point"}
}