{
  "type": "Feature",
  "properties": {
    "gn:admin1_code":"16.0",
    "gn:admin2_code":"6.0",
    "gn:asciiname":"La Gueera",
    "gn:country_code":"MX",
    "gn:dem":832,
    "gn:feature_class":"P",
    "gn:feature_code":"PPL",
    "gn:name":"La G\u00fcera",
    "gn:population":0,
    "gn:timezone":"America/Mexico_City",
    "iso:country":"MX",
    "name:spa_x_preferred":[
        "La G\u00fcera"
    ],
    "wof:name":"La Gueera",
    "wof:placetype":"locality"
},
  "geometry": {"coordinates":[-102.27099,19.14978],"type":"Point"}
}