{
  "type": "Feature",
  "properties": {
    "gn:admin1_code":"30.0",
    "gn:admin2_code":"123.0",
    "gn:asciiname":"La Bonita",
    "gn:country_code":"MX",
    "gn:dem":31,
    "gn:feature_class":"P",
    "gn:feature_code":"PPL",
    "gn:name":"La Bonita",
    "gn:population":4,
    "gn:timezone":"America/Mexico_City",
    "iso:country":"MX",
    "name:spa_x_preferred":[
        "La Bonita"
    ],
    "wof:name":"La Bonita",
    "wof:placetype":"locality",
    "wof:population":4
},
  "geometry": {"coordinates":[-98.30474,22.18994],"type":"Point"}
}