{
  "type": "Feature",
  "properties": {
    "gn:admin1_code":"11",
    "gn:admin2_code":"17",
    "gn:asciiname":"Granja Sofia",
    "gn:country_code":"MX",
    "gn:dem":1735,
    "gn:feature_class":"P",
    "gn:feature_code":"PPL",
    "gn:name":"Granja Sof\u00eda",
    "gn:population":9,
    "gn:timezone":"America/Mexico_City",
    "iso:country":"MX",
    "name:und_x_variant":[
        "Granja Sof\u00eda"
    ],
    "wof:name":"Granja Sofia",
    "wof:placetype":"locality",
    "wof:population":9
},
  "geometry": {"coordinates":[-101.32138999999999,20.73306],"type":"Point"}
}