{
  "type": "Feature",
  "properties": {
    "gn:admin1_code":"31",
    "gn:admin2_code":"50.0",
    "gn:asciiname":"Noco",
    "gn:country_code":"MX",
    "gn:dem":15,
    "gn:feature_class":"P",
    "gn:feature_code":"PPL",
    "gn:name":"Noco",
    "gn:population":0,
    "gn:timezone":"America/Merida",
    "iso:country":"MX",
    "wof:name":"Noco",
    "wof:placetype":"locality"
},
  "geometry": {"coordinates":[-89.66667,20.91667],"type":"Point"}
}