{
  "type": "Feature",
  "properties": {
    "gn:admin1_code":"24",
    "gn:admin2_code":"3.0",
    "gn:asciiname":"Jactzen",
    "gn:country_code":"MX",
    "gn:dem":743,
    "gn:feature_class":"P",
    "gn:feature_code":"PPL",
    "gn:name":"Jactz\u00e9n",
    "gn:population":8,
    "gn:timezone":"America/Mexico_City",
    "iso:country":"MX",
    "name:und_x_variant":[
        "Jactz\u00e9n"
    ],
    "wof:name":"Jactzen",
    "wof:placetype":"locality",
    "wof:population":8
},
  "geometry": {"coordinates":[-99.07444,21.53139],"type":"Point"}
}