{
  "type": "Feature",
  "properties": {
    "gn:admin1_code":"21",
    "gn:admin2_code":"128.0",
    "gn:asciiname":"Texalucan",
    "gn:country_code":"MX",
    "gn:dem":2352,
    "gn:feature_class":"P",
    "gn:feature_code":"PPL",
    "gn:name":"Texalucan",
    "gn:population":5,
    "gn:timezone":"America/Mexico_City",
    "iso:country":"MX",
    "wof:name":"Texalucan",
    "wof:placetype":"locality",
    "wof:population":5
},
  "geometry": {"coordinates":[-97.68519000000001,19.27097],"type":"Point"}
}