{
  "type": "Feature",
  "properties": {
    "gn:admin1_code":"30.0",
    "gn:admin2_code":"109.0",
    "gn:asciiname":"Mundo Nuevo",
    "gn:country_code":"MX",
    "gn:dem":14,
    "gn:feature_class":"P",
    "gn:feature_code":"PPL",
    "gn:name":"Mundo Nuevo",
    "gn:population":25,
    "gn:timezone":"America/Mexico_City",
    "iso:country":"MX",
    "name:spa_x_preferred":[
        "Mundo Nuevo"
    ],
    "wof:name":"Mundo Nuevo",
    "wof:placetype":"locality",
    "wof:population":25
},
  "geometry": {"coordinates":[-96.90194,20.13583],"type":"Point"}
}