{
  "type": "Feature",
  "properties": {
    "gn:admin1_code":"11.0",
    "gn:admin2_code":"2.0",
    "gn:asciiname":"Moncloa",
    "gn:country_code":"MX",
    "gn:dem":2041,
    "gn:feature_class":"P",
    "gn:feature_code":"PPL",
    "gn:name":"Moncloa",
    "gn:population":0,
    "gn:timezone":"America/Mexico_City",
    "iso:country":"MX",
    "name:spa_x_preferred":[
        "Moncloa"
    ],
    "name:und_x_variant":[
        "Monclova"
    ],
    "wof:name":"Moncloa",
    "wof:placetype":"locality"
},
  "geometry": {"coordinates":[-100.69403,20.166],"type":"Point"}
}