{
  "type": "Feature",
  "properties": {
    "gn:admin1_code":"26.0",
    "gn:admin2_code":"25.0",
    "gn:asciiname":"Las Tortolitas",
    "gn:country_code":"MX",
    "gn:dem":47,
    "gn:feature_class":"P",
    "gn:feature_code":"PPL",
    "gn:name":"Las Tortolitas",
    "gn:population":0,
    "gn:timezone":"America/Hermosillo",
    "iso:country":"MX",
    "name:spa_x_preferred":[
        "Las Tortolitas"
    ],
    "wof:name":"Las Tortolitas",
    "wof:placetype":"locality"
},
  "geometry": {"coordinates":[-110.67901999999999,28.08596],"type":"Point"}
}