{
  "type": "Feature",
  "properties": {
    "gn:admin1_code":"12",
    "gn:admin2_code":"32.0",
    "gn:asciiname":"Durazno Oriente",
    "gn:country_code":"MX",
    "gn:dem":1449,
    "gn:feature_class":"P",
    "gn:feature_code":"PPL",
    "gn:name":"Durazno Oriente",
    "gn:population":167,
    "gn:timezone":"America/Mexico_City",
    "iso:country":"MX",
    "wof:name":"Durazno Oriente",
    "wof:placetype":"locality",
    "wof:population":167
},
  "geometry": {"coordinates":[-99.83972,17.79944],"type":"Point"}
}