{
  "type": "Feature",
  "properties": {
    "gn:admin1_code":"10",
    "gn:admin2_code":"34",
    "gn:asciiname":"Rio de los Barragan",
    "gn:country_code":"MX",
    "gn:dem":390,
    "gn:feature_class":"P",
    "gn:feature_code":"PPL",
    "gn:name":"R\u00edo de los Barrag\u00e1n",
    "gn:population":10,
    "gn:timezone":"America/Monterrey",
    "iso:country":"MX",
    "name:und_x_variant":[
        "R\u00edo de los Barrag\u00e1n"
    ],
    "wof:name":"Rio de los Barragan",
    "wof:placetype":"locality",
    "wof:population":10
},
  "geometry": {"coordinates":[-106.53033000000001,24.32249],"type":"Point"}
}