{
  "type": "Feature",
  "properties": {
    "gn:admin1_code":"11.0",
    "gn:admin2_code":"46.0",
    "gn:asciiname":"Rancho Viejo",
    "gn:country_code":"MX",
    "gn:dem":1784,
    "gn:feature_class":"P",
    "gn:feature_code":"PPL",
    "gn:name":"Rancho Viejo",
    "gn:population":0,
    "gn:timezone":"America/Mexico_City",
    "iso:country":"MX",
    "name:ceb_x_preferred":[
        "Rancho Viejo"
    ],
    "name:deu_x_preferred":[
        "Rancho Viejo"
    ],
    "name:ita_x_preferred":[
        "Rancho Viejo"
    ],
    "name:srp_x_preferred":[
        "\u0420\u0430\u043d\u0447\u043e \u0412\u0438\u0458\u0435\u0445\u043e"
    ],
    "name:swe_x_preferred":[
        "Rancho Viejo"
    ],
    "name:und_x_variant":[
        "Rancho Viejo de Casacuar\u00e1n"
    ],
    "wof:name":"Rancho Viejo",
    "wof:placetype":"locality"
},
  "geometry": {"coordinates":[-101.03556,20.16361],"type":"Point"}
}