{
  "type": "Feature",
  "properties": {
    "gn:admin1_code":"11.0",
    "gn:admin2_code":"46.0",
    "gn:asciiname":"Rancho Viejo",
    "gn:country_code":"MX",
    "gn:dem":1784,
    "gn:feature_class":"P",
    "gn:feature_code":"PPL",
    "gn:name":"Rancho Viejo",
    "gn:population":0,
    "gn:timezone":"America/Mexico_City",
    "iso:country":"MX",
    "name:und_x_variant":[
        "Rancho Viejo de Casacuar\u00e1n",
        "Rancho Viejo"
    ],
    "wof:name":"Rancho Viejo",
    "wof:placetype":"locality"
},
  "geometry": {"coordinates":[-101.03556,20.16361],"type":"Point"}
}