{
  "type": "Feature",
  "properties": {
    "gn:admin1_code":"5",
    "gn:admin2_code":"107.0",
    "gn:asciiname":"San Juan de los Angeles",
    "gn:country_code":"MX",
    "gn:dem":820,
    "gn:feature_class":"P",
    "gn:feature_code":"PPL",
    "gn:name":"San Juan de los \u00c1ngeles",
    "gn:population":150,
    "gn:timezone":"America/Mexico_City",
    "iso:country":"MX",
    "name:und_x_variant":[
        "San Juan de los \u00c1ngeles"
    ],
    "wof:name":"San Juan de los Angeles",
    "wof:placetype":"locality",
    "wof:population":150
},
  "geometry": {"coordinates":[-93.23271,15.93842],"type":"Point"}
}