{
  "type": "Feature",
  "properties": {
    "gn:admin1_code":"16",
    "gn:admin2_code":"93.0",
    "gn:asciiname":"Lomas de Avila (Los Miradores)",
    "gn:country_code":"MX",
    "gn:dem":2593,
    "gn:feature_class":"P",
    "gn:feature_code":"PPL",
    "gn:name":"Lomas de \u00c1vila (Los Miradores)",
    "gn:population":6,
    "gn:timezone":"America/Mexico_City",
    "iso:country":"MX",
    "name:und_x_variant":[
        "Lomas de \u00c1vila (Los Miradores)"
    ],
    "wof:name":"Lomas de Avila (Los Miradores)",
    "wof:placetype":"locality",
    "wof:population":6
},
  "geometry": {"coordinates":[-100.17139,19.80167],"type":"Point"}
}