{
  "type": "Feature",
  "properties": {
    "gn:admin1_code":"28.0",
    "gn:admin2_code":"14.0",
    "gn:asciiname":"El Ebanal",
    "gn:country_code":"MX",
    "gn:dem":140,
    "gn:feature_class":"P",
    "gn:feature_code":"PPL",
    "gn:name":"El Ebanal",
    "gn:population":0,
    "gn:timezone":"America/Monterrey",
    "iso:country":"MX",
    "name:spa_x_preferred":[
        "El Ebanal"
    ],
    "wof:name":"El Ebanal",
    "wof:placetype":"locality"
},
  "geometry": {"coordinates":[-99.42956,26.67539],"type":"Point"}
}