{
  "type": "Feature",
  "properties": {
    "gn:admin1_code":"20",
    "gn:admin2_code":"397",
    "gn:asciiname":"El Apartadero",
    "gn:country_code":"MX",
    "gn:dem":2228,
    "gn:feature_class":"P",
    "gn:feature_code":"PPL",
    "gn:name":"El Apartadero",
    "gn:population":31,
    "gn:timezone":"America/Mexico_City",
    "iso:country":"MX",
    "wof:name":"El Apartadero",
    "wof:placetype":"locality",
    "wof:population":31
},
  "geometry": {"coordinates":[-97.64944,17.22306],"type":"Point"}
}