{
  "type": "Feature",
  "properties": {
    "gn:admin1_code":"25",
    "gn:admin2_code":"14.0",
    "gn:asciiname":"La Piiedra Labrada",
    "gn:country_code":"MX",
    "gn:dem":210,
    "gn:feature_class":"P",
    "gn:feature_code":"PPL",
    "gn:name":"La Piiedra Labrada",
    "gn:population":0,
    "gn:timezone":"America/Mazatlan",
    "iso:country":"MX",
    "name:spa_x_preferred":[
        "La Piiedra Labrada"
    ],
    "wof:name":"La Piiedra Labrada",
    "wof:placetype":"locality"
},
  "geometry": {"coordinates":[-105.63427,23.03613],"type":"Point"}
}