{
  "type": "Feature",
  "properties": {
    "gn:admin1_code":"17.0",
    "gn:asciiname":"Estacion de Solis",
    "gn:country_code":"MX",
    "gn:dem":2438,
    "gn:feature_class":"P",
    "gn:feature_code":"PPL",
    "gn:name":"Estaci\u00f3n de Sol\u00eds",
    "gn:population":0,
    "gn:timezone":"America/Mexico_City",
    "iso:country":"MX",
    "name:spa_x_preferred":[
        "Estaci\u00f3n Alberto Gardu\u00f1o C."
    ],
    "name:und_x_variant":[
        "Alberto Gardu\u00f1o",
        "Estaci\u00f3n de Sol\u00eds",
        "Estacin Alberto Gardu\u00f1o C."
    ],
    "wof:name":"Estacion de Solis",
    "wof:placetype":"locality"
},
  "geometry": {"coordinates":[-100.09313,19.89394],"type":"Point"}
}