{
  "type": "Feature",
  "properties": {
    "gn:admin1_code":"21",
    "gn:admin2_code":"179.0",
    "gn:asciiname":"Bella Vista",
    "gn:country_code":"MX",
    "gn:dem":2463,
    "gn:feature_class":"P",
    "gn:feature_code":"PPL",
    "gn:name":"Bella Vista",
    "gn:population":0,
    "gn:timezone":"America/Mexico_City",
    "iso:country":"MX",
    "name:spa_x_preferred":[
        "Bella Vista"
    ],
    "name:und_x_variant":[
        "Bellavista"
    ],
    "wof:name":"Bella Vista",
    "wof:placetype":"locality"
},
  "geometry": {"coordinates":[-97.41913,19.24971],"type":"Point"}
}