{
  "type": "Feature",
  "properties": {
    "gn:admin1_code":"6",
    "gn:admin2_code":"32",
    "gn:asciiname":"Los Jales",
    "gn:country_code":"MX",
    "gn:dem":1733,
    "gn:feature_class":"P",
    "gn:feature_code":"PPL",
    "gn:name":"Los Jales",
    "gn:population":12,
    "gn:timezone":"America/Chihuahua",
    "iso:country":"MX",
    "wof:name":"Los Jales",
    "wof:placetype":"locality",
    "wof:population":12
},
  "geometry": {"coordinates":[-105.66265,26.94745],"type":"Point"}
}