{
  "type": "Feature",
  "properties": {
    "gn:admin1_code":"12",
    "gn:admin2_code":"57",
    "gn:asciiname":"Los Toronjos",
    "gn:country_code":"MX",
    "gn:dem":392,
    "gn:feature_class":"P",
    "gn:feature_code":"PPL",
    "gn:name":"Los Toronjos",
    "gn:population":22,
    "gn:timezone":"America/Mexico_City",
    "iso:country":"MX",
    "wof:name":"Los Toronjos",
    "wof:placetype":"locality",
    "wof:population":22
},
  "geometry": {"coordinates":[-100.55058,17.24879],"type":"Point"}
}