{
  "type": "Feature",
  "properties": {
    "gn:admin1_code":"30",
    "gn:admin2_code":"189.0",
    "gn:asciiname":"Macuiltepetl",
    "gn:country_code":"MX",
    "gn:dem":40,
    "gn:feature_class":"P",
    "gn:feature_code":"PPL",
    "gn:name":"Macuilt\u00e9petl",
    "gn:population":0,
    "gn:timezone":"America/Mexico_City",
    "iso:country":"MX",
    "name:spa_x_preferred":[
        "Macuilt\u00e9petl"
    ],
    "name:und_x_variant":[
        "Macuiltepec"
    ],
    "wof:name":"Macuiltepetl",
    "wof:placetype":"locality"
},
  "geometry": {"coordinates":[-97.43147,20.82332],"type":"Point"}
}