{
  "type": "Feature",
  "properties": {
    "gn:admin1_code":"12",
    "gn:admin2_code":"58.0",
    "gn:asciiname":"Oxtotitlan",
    "gn:country_code":"MX",
    "gn:dem":1074,
    "gn:feature_class":"P",
    "gn:feature_code":"PPL",
    "gn:name":"Oxtotitl\u00e1n",
    "gn:population":0,
    "gn:timezone":"America/Mexico_City",
    "iso:country":"MX",
    "name:spa_x_preferred":[
        "Oxtotitl\u00e1n"
    ],
    "name:und_x_variant":[
        "Ostotitl\u00e1n"
    ],
    "wof:name":"Oxtotitlan",
    "wof:placetype":"locality"
},
  "geometry": {"coordinates":[-99.93248,18.19004],"type":"Point"}
}