{
  "type": "Feature",
  "properties": {
    "gn:admin1_code":"5",
    "gn:admin2_code":"4.0",
    "gn:asciiname":"Emiliano Zapata",
    "gn:country_code":"MX",
    "gn:dem":1220,
    "gn:feature_class":"P",
    "gn:feature_code":"PPL",
    "gn:name":"Emiliano Zapata",
    "gn:population":219,
    "gn:timezone":"America/Mexico_City",
    "iso:country":"MX",
    "wof:name":"Emiliano Zapata",
    "wof:placetype":"locality",
    "wof:population":219
},
  "geometry": {"coordinates":[-91.78749999999999,16.68389],"type":"Point"}
}