{
  "type": "Feature",
  "properties": {
    "gn:admin1_code":"6",
    "gn:admin2_code":"27.0",
    "gn:asciiname":"Boquimoba",
    "gn:country_code":"MX",
    "gn:dem":2332,
    "gn:feature_class":"P",
    "gn:feature_code":"PPL",
    "gn:name":"Boquimoba",
    "gn:population":30,
    "gn:timezone":"America/Chihuahua",
    "iso:country":"MX",
    "name:spa_x_preferred":[
        "Boquimoba"
    ],
    "wof:name":"Boquimoba",
    "wof:placetype":"locality",
    "wof:population":30
},
  "geometry": {"coordinates":[-107.22295,27.13521],"type":"Point"}
}