{
  "type": "Feature",
  "properties": {
    "gn:admin1_code":"26",
    "gn:admin2_code":"42.0",
    "gn:asciiname":"Ejido Primero de Abril",
    "gn:country_code":"MX",
    "gn:dem":28,
    "gn:feature_class":"P",
    "gn:feature_code":"PPL",
    "gn:name":"Ejido Primero de Abril",
    "gn:population":6,
    "gn:timezone":"America/Hermosillo",
    "iso:country":"MX",
    "wof:name":"Ejido Primero de Abril",
    "wof:placetype":"locality",
    "wof:population":6
},
  "geometry": {"coordinates":[-109.46193999999998,26.96611],"type":"Point"}
}