{
  "type": "Feature",
  "properties": {
    "gn:admin1_code":"26",
    "gn:admin2_code":"26.0",
    "gn:asciiname":"Bachoco el Alto",
    "gn:country_code":"MX",
    "gn:dem":30,
    "gn:feature_class":"P",
    "gn:feature_code":"PPL",
    "gn:name":"Bachoco el Alto",
    "gn:population":137,
    "gn:timezone":"America/Hermosillo",
    "iso:country":"MX",
    "wof:name":"Bachoco el Alto",
    "wof:placetype":"locality",
    "wof:population":137
},
  "geometry": {"coordinates":[-109.6289,27.09389],"type":"Point"}
}