{
  "type": "Feature",
  "properties": {
    "gn:admin1_code":"21",
    "gn:admin2_code":"172.0",
    "gn:asciiname":"Xilitetitla",
    "gn:country_code":"MX",
    "gn:dem":1888,
    "gn:feature_class":"P",
    "gn:feature_code":"PPL",
    "gn:name":"Xilitetitla",
    "gn:population":346,
    "gn:timezone":"America/Mexico_City",
    "iso:country":"MX",
    "wof:name":"Xilitetitla",
    "wof:placetype":"locality",
    "wof:population":346
},
  "geometry": {"coordinates":[-97.88056,19.8475],"type":"Point"}
}