{
  "type": "Feature",
  "properties": {
    "gn:admin1_code":"14",
    "gn:admin2_code":"8",
    "gn:asciiname":"Capadero (San Miguel)",
    "gn:country_code":"MX",
    "gn:dem":1876,
    "gn:feature_class":"P",
    "gn:feature_code":"PPL",
    "gn:name":"Capadero (San Miguel)",
    "gn:population":11,
    "gn:timezone":"America/Mexico_City",
    "iso:country":"MX",
    "wof:name":"Capadero (San Miguel)",
    "wof:placetype":"locality",
    "wof:population":11
},
  "geometry": {"coordinates":[-102.11694,20.845],"type":"Point"}
}