{
  "type": "Feature",
  "properties": {
    "gn:admin1_code":"6",
    "gn:admin2_code":"46",
    "gn:asciiname":"Sahuarare",
    "gn:country_code":"MX",
    "gn:dem":2140,
    "gn:feature_class":"P",
    "gn:feature_code":"PPL",
    "gn:name":"Sahuarare",
    "gn:population":15,
    "gn:timezone":"America/Chihuahua",
    "iso:country":"MX",
    "wof:name":"Sahuarare",
    "wof:placetype":"locality",
    "wof:population":15
},
  "geometry": {"coordinates":[-107.50154999999999,26.63827],"type":"Point"}
}