{
  "type": "Feature",
  "properties": {
    "gn:admin1_code":"1",
    "gn:admin2_code":"9.0",
    "gn:asciiname":"El Realengo",
    "gn:country_code":"MX",
    "gn:dem":1929,
    "gn:feature_class":"P",
    "gn:feature_code":"PPL",
    "gn:name":"El Realengo",
    "gn:population":81,
    "gn:timezone":"America/Mexico_City",
    "iso:country":"MX",
    "wof:name":"El Realengo",
    "wof:placetype":"locality",
    "wof:population":81
},
  "geometry": {"coordinates":[-102.23056,22.28333],"type":"Point"}
}