{
  "type": "Feature",
  "properties": {
    "gn:admin1_code":"14",
    "gn:admin2_code":"71",
    "gn:asciiname":"Llano Grande",
    "gn:country_code":"MX",
    "gn:dem":1765,
    "gn:feature_class":"P",
    "gn:feature_code":"PPL",
    "gn:name":"Llano Grande",
    "gn:population":23,
    "gn:timezone":"America/Mexico_City",
    "iso:country":"MX",
    "name:ceb_x_preferred":[
        "Llano Grande"
    ],
    "name:deu_x_preferred":[
        "Llano Grande"
    ],
    "name:fra_x_preferred":[
        "Llano Grande"
    ],
    "name:ita_x_preferred":[
        "Llano Grande"
    ],
    "name:spa_x_preferred":[
        "Llano Grande"
    ],
    "name:swe_x_preferred":[
        "Llano Grande"
    ],
    "wof:name":"Llano Grande",
    "wof:placetype":"locality",
    "wof:population":23
},
  "geometry": {"coordinates":[-103.58028,21.11389],"type":"Point"}
}