{
  "type": "Feature",
  "properties": {
    "gn:admin1_code":"18",
    "gn:admin2_code":"9.0",
    "gn:asciiname":"Los Encinos",
    "gn:country_code":"MX",
    "gn:dem":1968,
    "gn:feature_class":"P",
    "gn:feature_code":"PPL",
    "gn:name":"Los Encinos",
    "gn:population":298,
    "gn:timezone":"America/Mazatlan",
    "iso:country":"MX",
    "wof:name":"Los Encinos",
    "wof:placetype":"locality",
    "wof:population":298
},
  "geometry": {"coordinates":[-104.80139,22.21472],"type":"Point"}
}