{
  "type": "Feature",
  "properties": {
    "gn:admin1_code":"10",
    "gn:admin2_code":"23.0",
    "gn:asciiname":"Tascatito",
    "gn:country_code":"MX",
    "gn:dem":2697,
    "gn:feature_class":"P",
    "gn:feature_code":"PPL",
    "gn:name":"Tascatito",
    "gn:population":0,
    "gn:timezone":"America/Monterrey",
    "iso:country":"MX",
    "name:spa_x_preferred":[
        "Tascatito"
    ],
    "wof:name":"Tascatito",
    "wof:placetype":"locality"
},
  "geometry": {"coordinates":[-105.3558,23.48681],"type":"Point"}
}