{
  "type": "Feature",
  "properties": {
    "gn:admin1_code":"5",
    "gn:admin2_code":"31",
    "gn:asciiname":"Chut Witz",
    "gn:country_code":"MX",
    "gn:dem":743,
    "gn:feature_class":"P",
    "gn:feature_code":"PPL",
    "gn:name":"Chut Witz",
    "gn:population":20,
    "gn:timezone":"America/Mexico_City",
    "iso:country":"MX",
    "wof:name":"Chut Witz",
    "wof:placetype":"locality",
    "wof:population":20
},
  "geometry": {"coordinates":[-91.97638999999999,17.09722],"type":"Point"}
}