{
  "type": "Feature",
  "properties": {
    "gn:admin1_code":"11",
    "gn:admin2_code":"27.0",
    "gn:asciiname":"Ampliacion Perico de Razo",
    "gn:country_code":"MX",
    "gn:dem":1724,
    "gn:feature_class":"P",
    "gn:feature_code":"PPL",
    "gn:name":"Ampliaci\u00f3n Perico de Razo",
    "gn:population":226,
    "gn:timezone":"America/Mexico_City",
    "iso:country":"MX",
    "name:und_x_variant":[
        "Ampliaci\u00f3n Perico de Razo"
    ],
    "wof:name":"Ampliacion Perico de Razo",
    "wof:placetype":"locality",
    "wof:population":226
},
  "geometry": {"coordinates":[-101.07306,20.50889],"type":"Point"}
}