{
  "type": "Feature",
  "properties": {
    "gn:admin1_code":"26",
    "gn:admin2_code":"21.0",
    "gn:asciiname":"La Presa",
    "gn:country_code":"MX",
    "gn:dem":387,
    "gn:feature_class":"P",
    "gn:feature_code":"PPL",
    "gn:name":"La Presa",
    "gn:population":2,
    "gn:timezone":"America/Hermosillo",
    "iso:country":"MX",
    "name:spa_x_preferred":[
        "La Presa"
    ],
    "wof:name":"La Presa",
    "wof:placetype":"locality",
    "wof:population":2
},
  "geometry": {"coordinates":[-110.62528,28.93556],"type":"Point"}
}