{
  "type": "Feature",
  "properties": {
    "gn:admin1_code":"15",
    "gn:admin2_code":"39.0",
    "gn:asciiname":"Ejido San Francisco (Las Joyas)",
    "gn:country_code":"MX",
    "gn:dem":2291,
    "gn:feature_class":"P",
    "gn:feature_code":"PPL",
    "gn:name":"Ejido San Francisco (Las Joyas)",
    "gn:population":79,
    "gn:timezone":"America/Mexico_City",
    "iso:country":"MX",
    "wof:name":"Ejido San Francisco (Las Joyas)",
    "wof:placetype":"locality",
    "wof:population":79
},
  "geometry": {"coordinates":[-98.87153000000001,19.34937],"type":"Point"}
}