{
  "type": "Feature",
  "properties": {
    "gn:admin1_code":"14.0",
    "gn:asciiname":"Centro de Guadalupe",
    "gn:country_code":"MX",
    "gn:dem":1865,
    "gn:feature_class":"P",
    "gn:feature_code":"PPL",
    "gn:name":"Centro de Guadalupe",
    "gn:population":0,
    "gn:timezone":"America/Mexico_City",
    "iso:country":"MX",
    "name:spa_x_preferred":[
        "Centro de Guadalupe"
    ],
    "name:spa_x_variant":[
        "El Centro"
    ],
    "wof:name":"Centro de Guadalupe",
    "wof:placetype":"locality"
},
  "geometry": {"coordinates":[-102.19631,21.10312],"type":"Point"}
}