{
  "type": "Feature",
  "properties": {
    "gn:admin1_code":"21",
    "gn:admin2_code":"115.0",
    "gn:asciiname":"Progreso de Madero",
    "gn:country_code":"MX",
    "gn:dem":2147,
    "gn:feature_class":"P",
    "gn:feature_code":"PPL",
    "gn:name":"Progreso de Madero",
    "gn:population":387,
    "gn:timezone":"America/Mexico_City",
    "iso:country":"MX",
    "wof:name":"Progreso de Madero",
    "wof:placetype":"locality",
    "wof:population":387
},
  "geometry": {"coordinates":[-97.67917,18.94056],"type":"Point"}
}