{
  "type": "Feature",
  "properties": {
    "gn:admin1_code":"22",
    "gn:admin2_code":"1",
    "gn:asciiname":"El Salvador",
    "gn:country_code":"MX",
    "gn:dem":2512,
    "gn:feature_class":"P",
    "gn:feature_code":"PPL",
    "gn:name":"El Salvador",
    "gn:population":50,
    "gn:timezone":"America/Mexico_City",
    "iso:country":"MX",
    "wof:name":"El Salvador",
    "wof:placetype":"locality",
    "wof:population":50
},
  "geometry": {"coordinates":[-100.23056,20.29889],"type":"Point"}
}