{
  "type": "Feature",
  "properties": {
    "gn:admin1_code":"13",
    "gn:admin2_code":"28.0",
    "gn:asciiname":"Poxtla Ixcatlan",
    "gn:country_code":"MX",
    "gn:dem":286,
    "gn:feature_class":"P",
    "gn:feature_code":"PPL",
    "gn:name":"Poxtla Ixcatl\u00e1n",
    "gn:population":480,
    "gn:timezone":"America/Mexico_City",
    "iso:country":"MX",
    "name:und_x_variant":[
        "Poxtla Ixcatl\u00e1n"
    ],
    "wof:name":"Poxtla Ixcatlan",
    "wof:placetype":"locality",
    "wof:population":480
},
  "geometry": {"coordinates":[-98.48139,21.08778],"type":"Point"}
}