{
  "type": "Feature",
  "properties": {
    "gn:admin1_code":"12.0",
    "gn:asciiname":"Portezuelo del Lobo",
    "gn:country_code":"MX",
    "gn:dem":1371,
    "gn:feature_class":"P",
    "gn:feature_code":"PPL",
    "gn:name":"Portezuelo del Lobo",
    "gn:population":0,
    "gn:timezone":"America/Mexico_City",
    "iso:country":"MX",
    "name:spa_x_preferred":[
        "Portezuelo del Lobo"
    ],
    "wof:name":"Portezuelo del Lobo",
    "wof:placetype":"locality"
},
  "geometry": {"coordinates":[-98.27701999999999,17.89576],"type":"Point"}
}