{
  "type": "Feature",
  "properties": {
    "gn:admin1_code":"6.0",
    "gn:admin2_code":"23.0",
    "gn:asciiname":"El Dren",
    "gn:country_code":"MX",
    "gn:dem":1412,
    "gn:feature_class":"P",
    "gn:feature_code":"PPL",
    "gn:name":"El Dren",
    "gn:population":0,
    "gn:timezone":"America/Chihuahua",
    "iso:country":"MX",
    "name:spa_x_preferred":[
        "El Dren"
    ],
    "name:spa_x_variant":[
        "El Cascabel"
    ],
    "wof:name":"El Dren",
    "wof:placetype":"locality"
},
  "geometry": {"coordinates":[-107.58598000000001,30.18805],"type":"Point"}
}