{
  "type": "Feature",
  "properties": {
    "gn:admin1_code":"11",
    "gn:admin2_code":"3",
    "gn:asciiname":"Cruz del Mezquital (Santa Elena de la Cruz)",
    "gn:country_code":"MX",
    "gn:dem":2017,
    "gn:feature_class":"P",
    "gn:feature_code":"PPL",
    "gn:name":"Cruz del Mezquital (Santa Elena de la Cruz)",
    "gn:population":27,
    "gn:timezone":"America/Mexico_City",
    "iso:country":"MX",
    "wof:name":"Cruz del Mezquital (Santa Elena de la Cruz)",
    "wof:placetype":"locality",
    "wof:population":27
},
  "geometry": {"coordinates":[-100.56972,21.09167],"type":"Point"}
}