{
  "type": "Feature",
  "properties": {
    "gn:admin1_code":"28",
    "gn:admin2_code":"35.0",
    "gn:asciiname":"San German",
    "gn:country_code":"MX",
    "gn:dem":13,
    "gn:feature_class":"P",
    "gn:feature_code":"PPL",
    "gn:name":"San Germ\u00e1n",
    "gn:population":0,
    "gn:timezone":"America/Monterrey",
    "iso:country":"MX",
    "name:spa_x_preferred":[
        "San Germ\u00e1n"
    ],
    "name:und_x_variant":[
        "Germ\u00e1n"
    ],
    "wof:name":"San German",
    "wof:placetype":"locality"
},
  "geometry": {"coordinates":[-97.92186,25.21681],"type":"Point"}
}