{
  "type": "Feature",
  "properties": {
    "gn:admin1_code":"11",
    "gn:admin2_code":"3",
    "gn:asciiname":"Fraccion San Jose el Alto",
    "gn:country_code":"MX",
    "gn:dem":2157,
    "gn:feature_class":"P",
    "gn:feature_code":"PPL",
    "gn:name":"Fracci\u00f3n San Jos\u00e9 el Alto",
    "gn:population":10,
    "gn:timezone":"America/Mexico_City",
    "iso:country":"MX",
    "name:und_x_variant":[
        "Fracci\u00f3n San Jos\u00e9 el Alto"
    ],
    "wof:name":"Fraccion San Jose el Alto",
    "wof:placetype":"locality",
    "wof:population":10
},
  "geometry": {"coordinates":[-100.53778,20.87333],"type":"Point"}
}