{
  "type": "Feature",
  "properties": {
    "gn:admin1_code":"30",
    "gn:admin2_code":"49",
    "gn:asciiname":"Mata Catarina",
    "gn:country_code":"MX",
    "gn:dem":60,
    "gn:feature_class":"P",
    "gn:feature_code":"PPL",
    "gn:name":"Mata Catarina",
    "gn:population":14,
    "gn:timezone":"America/Mexico_City",
    "iso:country":"MX",
    "wof:name":"Mata Catarina",
    "wof:placetype":"locality",
    "wof:population":14
},
  "geometry": {"coordinates":[-96.33611000000001,18.92528],"type":"Point"}
}