{
  "type": "Feature",
  "properties": {
    "gn:admin1_code":"11",
    "gn:admin2_code":"33.0",
    "gn:asciiname":"Macuala",
    "gn:country_code":"MX",
    "gn:dem":1495,
    "gn:feature_class":"P",
    "gn:feature_code":"PPL",
    "gn:name":"Macuala",
    "gn:population":0,
    "gn:timezone":"America/Mexico_City",
    "iso:country":"MX",
    "name:und_x_variant":[
        "Macuata",
        "Macula",
        "Macuala"
    ],
    "wof:name":"Macuala",
    "wof:placetype":"locality"
},
  "geometry": {"coordinates":[-100.2783,21.53817],"type":"Point"}
}