{
  "type": "Feature",
  "properties": {
    "gn:admin1_code":"13",
    "gn:admin2_code":"15.0",
    "gn:asciiname":"Jonacapa",
    "gn:country_code":"MX",
    "gn:dem":1348,
    "gn:feature_class":"P",
    "gn:feature_code":"PPL",
    "gn:name":"Jonacapa",
    "gn:population":0,
    "gn:timezone":"America/Mexico_City",
    "iso:country":"MX",
    "name:spa_x_preferred":[
        "Jonacapa"
    ],
    "wof:name":"Jonacapa",
    "wof:placetype":"locality"
},
  "geometry": {"coordinates":[-99.03363,20.76722],"type":"Point"}
}