{
  "type": "Feature",
  "properties": {
    "gn:admin1_code":"10.0",
    "gn:admin2_code":"34.0",
    "gn:asciiname":"La Mesa Colorada",
    "gn:country_code":"MX",
    "gn:dem":1985,
    "gn:feature_class":"P",
    "gn:feature_code":"PPL",
    "gn:name":"La Mesa Colorada",
    "gn:population":0,
    "gn:timezone":"America/Monterrey",
    "iso:country":"MX",
    "name:spa_x_preferred":[
        "La Mesa Colorada"
    ],
    "wof:name":"La Mesa Colorada",
    "wof:placetype":"locality"
},
  "geometry": {"coordinates":[-106.63769000000001,24.88165],"type":"Point"}
}