{
  "type": "Feature",
  "properties": {
    "gn:admin1_code":"10",
    "gn:admin2_code":"7",
    "gn:asciiname":"Reyes Castro [Propiedad Privada]",
    "gn:country_code":"MX",
    "gn:dem":1117,
    "gn:feature_class":"P",
    "gn:feature_code":"PPL",
    "gn:name":"Reyes Castro [Propiedad Privada]",
    "gn:population":14,
    "gn:timezone":"America/Monterrey",
    "iso:country":"MX",
    "wof:name":"Reyes Castro [Propiedad Privada]",
    "wof:placetype":"locality",
    "wof:population":14
},
  "geometry": {"coordinates":[-103.43924,25.69778],"type":"Point"}
}