{
  "type": "Feature",
  "properties": {
    "gn:admin1_code":"19.0",
    "gn:admin2_code":"23.0",
    "gn:asciiname":"El Aguila",
    "gn:country_code":"MX",
    "gn:dem":170,
    "gn:feature_class":"P",
    "gn:feature_code":"PPL",
    "gn:name":"El \u00c1guila",
    "gn:population":0,
    "gn:timezone":"America/Monterrey",
    "iso:country":"MX",
    "name:spa_x_preferred":[
        "El \u00c1guila"
    ],
    "wof:name":"El Aguila",
    "wof:placetype":"locality"
},
  "geometry": {"coordinates":[-99.45137,26.17743],"type":"Point"}
}