{
  "type": "Feature",
  "properties": {
    "gn:admin1_code":"16",
    "gn:admin2_code":"82.0",
    "gn:asciiname":"San Jeronimo Arroyo de Apo (Huatzanguio)",
    "gn:country_code":"MX",
    "gn:dem":1306,
    "gn:feature_class":"P",
    "gn:feature_code":"PPL",
    "gn:name":"San Jer\u00f3nimo Arroyo de Apo (Huatzangu\u00edo)",
    "gn:population":65,
    "gn:timezone":"America/Mexico_City",
    "iso:country":"MX",
    "name:und_x_variant":[
        "San Jer\u00f3nimo Arroyo de Apo (Huatzangu\u00edo)"
    ],
    "wof:name":"San Jeronimo Arroyo de Apo (Huatzanguio)",
    "wof:placetype":"locality",
    "wof:population":65
},
  "geometry": {"coordinates":[-101.36611000000001,19.19917],"type":"Point"}
}