{
  "type": "Feature",
  "properties": {
    "gn:admin1_code":"19.0",
    "gn:admin2_code":"37.0",
    "gn:asciiname":"Las Estacas",
    "gn:country_code":"MX",
    "gn:dem":643,
    "gn:feature_class":"P",
    "gn:feature_code":"PPL",
    "gn:name":"Las Estacas",
    "gn:population":0,
    "gn:timezone":"America/Monterrey",
    "iso:country":"MX",
    "name:ast_x_preferred":[
        "Las Estacas"
    ],
    "name:deu_x_preferred":[
        "Las Estacas"
    ],
    "name:spa_x_preferred":[
        "Estacas"
    ],
    "name:spa_x_variant":[
        "Las Estacas"
    ],
    "name:und_x_variant":[
        "Rancho Estacas"
    ],
    "name:urd_x_preferred":[
        "\u0644\u0627\u0633 \u06cc\u0633\u0679\u0627\u06a9\u0627\u0633"
    ],
    "wof:name":"Las Estacas",
    "wof:placetype":"locality"
},
  "geometry": {"coordinates":[-100.86905,26.36383],"type":"Point"}
}