{
  "type": "Feature",
  "properties": {
    "gn:admin1_code":"7",
    "gn:asciiname":"Las Esperanzas",
    "gn:country_code":"MX",
    "gn:dem":1220,
    "gn:feature_class":"P",
    "gn:feature_code":"PPL",
    "gn:name":"Las Esperanzas",
    "gn:population":0,
    "gn:timezone":"America/Chihuahua",
    "iso:country":"MX",
    "name:und_x_variant":[
        "Rancho Las Esperanzas",
        "Las Esperanzas"
    ],
    "wof:name":"Las Esperanzas",
    "wof:placetype":"locality"
},
  "geometry": {"coordinates":[-103.86939,27.27961],"type":"Point"}
}