{
  "type": "Feature",
  "properties": {
    "gn:admin1_code":"30",
    "gn:admin2_code":"108",
    "gn:asciiname":"San Eulalio",
    "gn:country_code":"MX",
    "gn:dem":14,
    "gn:feature_class":"P",
    "gn:feature_code":"PPL",
    "gn:name":"San Eulalio",
    "gn:population":15,
    "gn:timezone":"America/Mexico_City",
    "iso:country":"MX",
    "wof:name":"San Eulalio",
    "wof:placetype":"locality",
    "wof:population":15
},
  "geometry": {"coordinates":[-94.21778,17.85306],"type":"Point"}
}