{
  "type": "Feature",
  "properties": {
    "gn:admin1_code":"6",
    "gn:admin2_code":"11.0",
    "gn:asciiname":"Las Conchas",
    "gn:country_code":"MX",
    "gn:dem":1465,
    "gn:feature_class":"P",
    "gn:feature_code":"PPL",
    "gn:name":"Las Conchas",
    "gn:population":0,
    "gn:timezone":"America/Chihuahua",
    "iso:country":"MX",
    "name:spa_x_preferred":[
        "Las Conchas"
    ],
    "wof:name":"Las Conchas",
    "wof:placetype":"locality"
},
  "geometry": {"coordinates":[-104.11906,27.81437],"type":"Point"}
}