{
  "type": "Feature",
  "properties": {
    "gn:admin1_code":"19",
    "gn:admin2_code":"33.0",
    "gn:asciiname":"Gerardo Jimenez Cantu (Ex-Hacienda Lozada)",
    "gn:country_code":"MX",
    "gn:dem":238,
    "gn:feature_class":"P",
    "gn:feature_code":"PPL",
    "gn:name":"Gerardo Jim\u00e9nez Cant\u00fa (Ex-Hacienda Lozada)",
    "gn:population":7,
    "gn:timezone":"America/Monterrey",
    "iso:country":"MX",
    "name:und_x_variant":[
        "Gerardo Jim\u00e9nez Cant\u00fa (Ex-Hacienda Lozada)"
    ],
    "wof:name":"Gerardo Jimenez Cantu (Ex-Hacienda Lozada)",
    "wof:placetype":"locality",
    "wof:population":7
},
  "geometry": {"coordinates":[-99.32026999999999,24.95869],"type":"Point"}
}