{
  "type": "Feature",
  "properties": {
    "gn:admin1_code":"15",
    "gn:admin2_code":"87.0",
    "gn:asciiname":"Allende",
    "gn:country_code":"MX",
    "gn:dem":2594,
    "gn:feature_class":"P",
    "gn:feature_code":"PPL",
    "gn:name":"Allende",
    "gn:population":0,
    "gn:timezone":"America/Mexico_City",
    "iso:country":"MX",
    "name:spa_x_preferred":[
        "Allende"
    ],
    "wof:name":"Allende",
    "wof:placetype":"locality"
},
  "geometry": {"coordinates":[-99.71528000000001,19.47628],"type":"Point"}
}