{
  "type": "Feature",
  "properties": {
    "gn:admin1_code":"30.0",
    "gn:admin2_code":"167.0",
    "gn:asciiname":"Deborah",
    "gn:country_code":"MX",
    "gn:dem":89,
    "gn:feature_class":"P",
    "gn:feature_code":"PPL",
    "gn:name":"Deborah",
    "gn:population":0,
    "gn:timezone":"America/Mexico_City",
    "iso:country":"MX",
    "name:ara_x_preferred":[
        "\u062f\u0628\u0648\u0631\u0647"
    ],
    "name:aze_x_preferred":[
        "Debora"
    ],
    "name:bcl_x_preferred":[
        "Deborah"
    ],
    "name:bel_x_preferred":[
        "\u0414\u044d\u0432\u043e\u0440\u0430"
    ],
    "name:bre_x_preferred":[
        "Debora"
    ],
    "name:bul_x_preferred":[
        "\u0414\u0435\u0432\u043e\u0440\u0430"
    ],
    "name:cat_x_preferred":[
        "D\u00e8bora"
    ],
    "name:ces_x_preferred":[
        "Debora"
    ],
    "name:deu_x_preferred":[
        "Debora"
    ],
    "name:ell_x_preferred":[
        "\u0394\u03b5\u03b2\u03b2\u03ce\u03c1\u03b1"
    ],
    "name:epo_x_preferred":[
        "Debora"
    ],
    "name:est_x_preferred":[
        "Deboora"
    ],
    "name:eus_x_preferred":[
        "Debora"
    ],
    "name:fas_x_preferred":[
        "\u062f\u0628\u0648\u0631\u0647"
    ],
    "name:fin_x_preferred":[
        "Debora"
    ],
    "name:fra_x_preferred":[
        "D\u00e9bora"
    ],
    "name:gle_x_preferred":[
        "Deabr\u00e1"
    ],
    "name:heb_x_preferred":[
        "\u05d3\u05d1\u05d5\u05e8\u05d4 \u05d4\u05e0\u05d1\u05d9\u05d0\u05d4"
    ],
    "name:ind_x_preferred":[
        "Debora"
    ],
    "name:ita_x_preferred":[
        "Debora"
    ],
    "name:jpn_x_preferred":[
        "\u30c7\u30dc\u30e9"
    ],
    "name:kat_x_preferred":[
        "\u10d3\u10d4\u10d1\u10dd\u10e0\u10d0"
    ],
    "name:kor_x_preferred":[
        "\ub370\ubcf4\ub77c"
    ],
    "name:mal_x_preferred":[
        "\u0d26\u0d46\u0d2c\u0d4b\u0d31\u0d3e"
    ],
    "name:mlg_x_preferred":[
        "Debora"
    ],
    "name:nld_x_preferred":[
        "Debora"
    ],
    "name:nno_x_preferred":[
        "Profeten Debora"
    ],
    "name:nor_x_preferred":[
        "Debora"
    ],
    "name:pnb_x_preferred":[
        "\u062f\u0628\u0648\u0631\u06c1"
    ],
    "name:pol_x_preferred":[
        "Debora"
    ],
    "name:por_x_preferred":[
        "D\u00e9bora"
    ],
    "name:rus_x_preferred":[
        "\u0414\u0435\u0432\u043e\u0440\u0430"
    ],
    "name:sco_x_preferred":[
        "Deborah"
    ],
    "name:spa_x_preferred":[
        "Deborah"
    ],
    "name:spa_x_variant":[
        "D\u00e9bora"
    ],
    "name:srp_x_preferred":[
        "\u0414\u0435\u0431\u043e\u0440\u0430"
    ],
    "name:swa_x_preferred":[
        "Debora"
    ],
    "name:swe_x_preferred":[
        "Debora"
    ],
    "name:tgl_x_preferred":[
        "Debora"
    ],
    "name:tur_x_preferred":[
        "Debora"
    ],
    "name:ukr_x_preferred":[
        "\u0414\u0435\u0432\u043e\u0440\u0430"
    ],
    "name:urd_x_preferred":[
        "\u062f\u0628\u0648\u0631\u06c1"
    ],
    "name:zho_x_preferred":[
        "\u5e95\u6ce2\u62c9"
    ],
    "wof:name":"Deborah",
    "wof:placetype":"locality"
},
  "geometry": {"coordinates":[-97.75069999999999,21.09962],"type":"Point"}
}