{
  "type": "Feature",
  "properties": {
    "gn:admin1_code":"30.0",
    "gn:admin2_code":"167.0",
    "gn:asciiname":"Deborah",
    "gn:country_code":"MX",
    "gn:dem":89,
    "gn:feature_class":"P",
    "gn:feature_code":"PPL",
    "gn:name":"Deborah",
    "gn:population":0,
    "gn:timezone":"America/Mexico_City",
    "iso:country":"MX",
    "name:spa_x_preferred":[
        "Deborah"
    ],
    "wof:name":"Deborah",
    "wof:placetype":"locality"
},
  "geometry": {"coordinates":[-97.75069999999999,21.09962],"type":"Point"}
}