{
  "type": "Feature",
  "properties": {
    "gn:admin1_code":"16.0",
    "gn:asciiname":"El Kilometro Veintitres",
    "gn:country_code":"MX",
    "gn:dem":2061,
    "gn:feature_class":"P",
    "gn:feature_code":"PPL",
    "gn:name":"El Kil\u00f3metro Veintitr\u00e9s",
    "gn:population":0,
    "gn:timezone":"America/Mexico_City",
    "iso:country":"MX",
    "name:spa_x_preferred":[
        "El Kil\u00f3metro Veintitr\u00e9s"
    ],
    "wof:name":"El Kilometro Veintitres",
    "wof:placetype":"locality"
},
  "geometry": {"coordinates":[-101.00675,19.66952],"type":"Point"}
}