{
  "type": "Feature",
  "properties": {
    "gn:admin1_code":"6.0",
    "gn:admin2_code":"9.0",
    "gn:asciiname":"Chamachi",
    "gn:country_code":"MX",
    "gn:dem":2449,
    "gn:feature_class":"P",
    "gn:feature_code":"PPL",
    "gn:name":"Chamachi",
    "gn:population":0,
    "gn:timezone":"America/Chihuahua",
    "iso:country":"MX",
    "name:spa_x_preferred":[
        "Chamachi"
    ],
    "wof:name":"Chamachi",
    "wof:placetype":"locality"
},
  "geometry": {"coordinates":[-107.64901,27.65898],"type":"Point"}
}