{
  "type": "Feature",
  "properties": {
    "gn:admin1_code":"21",
    "gn:admin2_code":"107.0",
    "gn:asciiname":"Zum Reforma",
    "gn:country_code":"MX",
    "gn:dem":388,
    "gn:feature_class":"P",
    "gn:feature_code":"PPL",
    "gn:name":"Zum Reforma",
    "gn:population":0,
    "gn:timezone":"America/Mexico_City",
    "iso:country":"MX",
    "name:spa_x_preferred":[
        "El Zun"
    ],
    "name:spa_x_variant":[
        "Zum Reforma",
        "Zun Reforma"
    ],
    "wof:name":"Zum Reforma",
    "wof:placetype":"locality"
},
  "geometry": {"coordinates":[-97.69535999999999,20.10415],"type":"Point"}
}