{
  "type": "Feature",
  "properties": {
    "gn:admin1_code":"12",
    "gn:admin2_code":"49",
    "gn:asciiname":"Los Puentes",
    "gn:country_code":"MX",
    "gn:dem":1311,
    "gn:feature_class":"P",
    "gn:feature_code":"PPL",
    "gn:name":"Los Puentes",
    "gn:population":12,
    "gn:timezone":"America/Mexico_City",
    "iso:country":"MX",
    "wof:name":"Los Puentes",
    "wof:placetype":"locality",
    "wof:population":12
},
  "geometry": {"coordinates":[-99.67155,18.7167],"type":"Point"}
}