{
  "type": "Feature",
  "properties": {
    "gn:admin1_code":"7",
    "gn:admin2_code":"33.0",
    "gn:asciiname":"Diez de Mayo (Las Casitas)",
    "gn:country_code":"MX",
    "gn:dem":1108,
    "gn:feature_class":"P",
    "gn:feature_code":"PPL",
    "gn:name":"Diez de Mayo (Las Casitas)",
    "gn:population":281,
    "gn:timezone":"America/Monterrey",
    "iso:country":"MX",
    "wof:name":"Diez de Mayo (Las Casitas)",
    "wof:placetype":"locality",
    "wof:population":281
},
  "geometry": {"coordinates":[-103.18222,25.79472],"type":"Point"}
}