{
  "type": "Feature",
  "properties": {
    "gn:admin1_code":"14.0",
    "gn:admin2_code":"121.0",
    "gn:asciiname":"El Aserradero",
    "gn:country_code":"MX",
    "gn:dem":1176,
    "gn:feature_class":"P",
    "gn:feature_code":"PPL",
    "gn:name":"El Aserradero",
    "gn:population":0,
    "gn:timezone":"America/Mexico_City",
    "iso:country":"MX",
    "name:spa_x_preferred":[
        "El Aserradero"
    ],
    "wof:name":"El Aserradero",
    "wof:placetype":"locality"
},
  "geometry": {"coordinates":[-103.25320000000001,19.54116],"type":"Point"}
}