{
  "type": "Feature",
  "properties": {
    "gn:admin1_code":"30",
    "gn:admin2_code":"157.0",
    "gn:asciiname":"Xuchil",
    "gn:country_code":"MX",
    "gn:dem":130,
    "gn:feature_class":"P",
    "gn:feature_code":"PPL",
    "gn:name":"Xuchil",
    "gn:population":0,
    "gn:timezone":"America/Mexico_City",
    "iso:country":"MX",
    "wof:name":"Xuchil",
    "wof:placetype":"locality"
},
  "geometry": {"coordinates":[-97.71868000000001,20.70417],"type":"Point"}
}