{
  "type": "Feature",
  "properties": {
    "gn:admin1_code":"31",
    "gn:admin2_code":"70.0",
    "gn:asciiname":"Chum-ox",
    "gn:country_code":"MX",
    "gn:dem":12,
    "gn:feature_class":"P",
    "gn:feature_code":"PPL",
    "gn:name":"Chum-ox",
    "gn:population":0,
    "gn:timezone":"America/Merida",
    "iso:country":"MX",
    "name:spa_x_preferred":[
        "Chum-ox"
    ],
    "wof:name":"Chum-ox",
    "wof:placetype":"locality"
},
  "geometry": {"coordinates":[-88.35933,21.2478],"type":"Point"}
}