{
  "type": "Feature",
  "properties": {
    "gn:admin1_code":"20",
    "gn:admin2_code":"179.0",
    "gn:asciiname":"Nanchal",
    "gn:country_code":"MX",
    "gn:dem":1482,
    "gn:feature_class":"P",
    "gn:feature_code":"PPL",
    "gn:name":"Nanchal",
    "gn:population":0,
    "gn:timezone":"America/Mexico_City",
    "iso:country":"MX",
    "wof:name":"Nanchal",
    "wof:placetype":"locality"
},
  "geometry": {"coordinates":[-96.83333,17.43333],"type":"Point"}
}