{
  "type": "Feature",
  "properties": {
    "gn:admin1_code":"20",
    "gn:admin2_code":"30.0",
    "gn:asciiname":"Los Tulipanes (Ricardo Toledo)",
    "gn:country_code":"MX",
    "gn:dem":23,
    "gn:feature_class":"P",
    "gn:feature_code":"PPL",
    "gn:name":"Los Tulipanes (Ricardo Toledo)",
    "gn:population":6,
    "gn:timezone":"America/Mexico_City",
    "iso:country":"MX",
    "wof:name":"Los Tulipanes (Ricardo Toledo)",
    "wof:placetype":"locality",
    "wof:population":6
},
  "geometry": {"coordinates":[-95.05028,16.43],"type":"Point"}
}