{
  "type": "Feature",
  "properties": {
    "gn:admin1_code":"23",
    "gn:admin2_code":"1.0",
    "gn:asciiname":"Rancho Real",
    "gn:country_code":"MX",
    "gn:dem":8,
    "gn:feature_class":"P",
    "gn:feature_code":"PPL",
    "gn:name":"Rancho Real",
    "gn:population":7,
    "gn:timezone":"America/Cancun",
    "iso:country":"MX",
    "wof:name":"Rancho Real",
    "wof:placetype":"locality",
    "wof:population":7
},
  "geometry": {"coordinates":[-86.91946,20.48682],"type":"Point"}
}