{
  "type": "Feature",
  "properties": {
    "gn:admin1_code":"8.0",
    "gn:admin2_code":"2.0",
    "gn:asciiname":"El Astillero de Arriba",
    "gn:country_code":"MX",
    "gn:dem":567,
    "gn:feature_class":"P",
    "gn:feature_code":"PPL",
    "gn:name":"El Astillero de Arriba",
    "gn:population":0,
    "gn:timezone":"America/Mexico_City",
    "iso:country":"MX",
    "name:spa_x_preferred":[
        "El Astillero de Arriba"
    ],
    "wof:name":"El Astillero de Arriba",
    "wof:placetype":"locality"
},
  "geometry": {"coordinates":[-103.55638,19.18828],"type":"Point"}
}