{
  "type": "Feature",
  "properties": {
    "gn:admin1_code":"25.0",
    "gn:admin2_code":"3.0",
    "gn:asciiname":"Canada Larga",
    "gn:country_code":"MX",
    "gn:dem":1710,
    "gn:feature_class":"P",
    "gn:feature_code":"PPL",
    "gn:name":"Ca\u00f1ada Larga",
    "gn:population":0,
    "gn:timezone":"America/Mazatlan",
    "iso:country":"MX",
    "name:spa_x_preferred":[
        "Ca\u00f1ada Larga"
    ],
    "wof:name":"Canada Larga",
    "wof:placetype":"locality"
},
  "geometry": {"coordinates":[-107.55398999999998,25.84389],"type":"Point"}
}