{
  "type": "Feature",
  "properties": {
    "gn:admin1_code":"27",
    "gn:admin2_code":"12.0",
    "gn:asciiname":"Los Gueiros",
    "gn:country_code":"MX",
    "gn:dem":6,
    "gn:feature_class":"P",
    "gn:feature_code":"PPL",
    "gn:name":"Los G\u00fciros",
    "gn:population":136,
    "gn:timezone":"America/Mexico_City",
    "iso:country":"MX",
    "name:und_x_variant":[
        "Los G\u00fciros"
    ],
    "wof:name":"Los Gueiros",
    "wof:placetype":"locality",
    "wof:population":136
},
  "geometry": {"coordinates":[-92.345,18.12222],"type":"Point"}
}