{
  "type": "Feature",
  "properties": {
    "gn:admin1_code":"10",
    "gn:admin2_code":"37.0",
    "gn:asciiname":"San Jose de las Manzanas",
    "gn:country_code":"MX",
    "gn:dem":1922,
    "gn:feature_class":"P",
    "gn:feature_code":"PPL",
    "gn:name":"San Jos\u00e9 de las Manzanas",
    "gn:population":0,
    "gn:timezone":"America/Monterrey",
    "iso:country":"MX",
    "name:spa_x_preferred":[
        "San Jos\u00e9 de las Manzanas"
    ],
    "wof:name":"San Jose de las Manzanas",
    "wof:placetype":"locality"
},
  "geometry": {"coordinates":[-106.43889,25.19384],"type":"Point"}
}