{
  "type": "Feature",
  "properties": {
    "gn:admin1_code":"20",
    "gn:admin2_code":"469",
    "gn:asciiname":"Torre de Babel (Flechador del Sol)",
    "gn:country_code":"MX",
    "gn:dem":1722,
    "gn:feature_class":"P",
    "gn:feature_code":"PPL",
    "gn:name":"Torre de Babel (Flechador del Sol)",
    "gn:population":30,
    "gn:timezone":"America/Mexico_City",
    "iso:country":"MX",
    "wof:name":"Torre de Babel (Flechador del Sol)",
    "wof:placetype":"locality",
    "wof:population":30
},
  "geometry": {"coordinates":[-98.01944,17.32167],"type":"Point"}
}