{
  "type": "Feature",
  "properties": {
    "gn:admin1_code":"7.0",
    "gn:admin2_code":"38.0",
    "gn:asciiname":"La Arena",
    "gn:country_code":"MX",
    "gn:dem":699,
    "gn:feature_class":"P",
    "gn:feature_code":"PPL",
    "gn:name":"La Arena",
    "gn:population":0,
    "gn:timezone":"America/Monterrey",
    "iso:country":"MX",
    "name:ceb_x_preferred":[
        "La Arena"
    ],
    "name:ita_x_preferred":[
        "La Arena"
    ],
    "name:srp_x_preferred":[
        "\u041b\u0430 \u0410\u0440\u0435\u043d\u0430"
    ],
    "name:swe_x_preferred":[
        "La Arena"
    ],
    "wof:name":"La Arena",
    "wof:placetype":"locality"
},
  "geometry": {"coordinates":[-101.41667,28.78333],"type":"Point"}
}