{
  "type": "Feature",
  "properties": {
    "gn:admin1_code":"24",
    "gn:admin2_code":"56.0",
    "gn:asciiname":"San Jose del Arbolito",
    "gn:country_code":"MX",
    "gn:dem":1605,
    "gn:feature_class":"P",
    "gn:feature_code":"PPL",
    "gn:name":"San Jos\u00e9 del Arbolito",
    "gn:population":577,
    "gn:timezone":"America/Mexico_City",
    "iso:country":"MX",
    "name:und_x_variant":[
        "San Jos\u00e9 del Arbolito"
    ],
    "wof:name":"San Jose del Arbolito",
    "wof:placetype":"locality",
    "wof:population":577
},
  "geometry": {"coordinates":[-100.84444000000001,22.67917000000001],"type":"Point"}
}