{
  "type": "Feature",
  "properties": {
    "gn:admin1_code":"32",
    "gn:admin2_code":"19.0",
    "gn:asciiname":"El Caracol",
    "gn:country_code":"MX",
    "gn:dem":1561,
    "gn:feature_class":"P",
    "gn:feature_code":"PPL",
    "gn:name":"El Caracol",
    "gn:population":0,
    "gn:timezone":"America/Mexico_City",
    "iso:country":"MX",
    "name:spa_x_preferred":[
        "El Caracol"
    ],
    "wof:name":"El Caracol",
    "wof:placetype":"locality"
},
  "geometry": {"coordinates":[-102.84959000000001,21.71164],"type":"Point"}
}