{
  "type": "Feature",
  "properties": {
    "gn:admin1_code":"31",
    "gn:admin2_code":"8.0",
    "gn:asciiname":"Champocoboch",
    "gn:country_code":"MX",
    "gn:dem":29,
    "gn:feature_class":"P",
    "gn:feature_code":"PPL",
    "gn:name":"Champocoboch",
    "gn:population":0,
    "gn:timezone":"America/Merida",
    "iso:country":"MX",
    "name:spa_x_preferred":[
        "Champocoboch"
    ],
    "wof:name":"Champocoboch",
    "wof:placetype":"locality"
},
  "geometry": {"coordinates":[-88.11555,20.95941],"type":"Point"}
}