{
  "type": "Feature",
  "properties": {
    "gn:admin1_code":"21",
    "gn:admin2_code":"54.0",
    "gn:asciiname":"Los Parajes (Zompanateno)",
    "gn:country_code":"MX",
    "gn:dem":2383,
    "gn:feature_class":"P",
    "gn:feature_code":"PPL",
    "gn:name":"Los Parajes (Zompanateno)",
    "gn:population":324,
    "gn:timezone":"America/Mexico_City",
    "iso:country":"MX",
    "wof:name":"Los Parajes (Zompanateno)",
    "wof:placetype":"locality",
    "wof:population":324
},
  "geometry": {"coordinates":[-97.42931,19.78516],"type":"Point"}
}