{
  "type": "Feature",
  "properties": {
    "gn:admin1_code":"5",
    "gn:admin2_code":"107.0",
    "gn:asciiname":"Arroyo Negro",
    "gn:country_code":"MX",
    "gn:dem":641,
    "gn:feature_class":"P",
    "gn:feature_code":"PPL",
    "gn:name":"Arroyo Negro",
    "gn:population":4,
    "gn:timezone":"America/Mexico_City",
    "iso:country":"MX",
    "wof:name":"Arroyo Negro",
    "wof:placetype":"locality",
    "wof:population":4
},
  "geometry": {"coordinates":[-93.31556,16.11722],"type":"Point"}
}