{
  "type": "Feature",
  "properties": {
    "gn:admin1_code":"30",
    "gn:admin2_code":"211.0",
    "gn:asciiname":"Loma del Pital",
    "gn:country_code":"MX",
    "gn:dem":89,
    "gn:feature_class":"P",
    "gn:feature_code":"PPL",
    "gn:name":"Loma del Pital",
    "gn:population":7,
    "gn:timezone":"America/Mexico_City",
    "iso:country":"MX",
    "wof:name":"Loma del Pital",
    "wof:placetype":"locality",
    "wof:population":7
},
  "geometry": {"coordinates":[-97.01528,20.22389],"type":"Point"}
}