{
  "type": "Feature",
  "properties": {
    "gn:admin1_code":"18",
    "gn:admin2_code":"10.0",
    "gn:asciiname":"Las Negras",
    "gn:country_code":"MX",
    "gn:dem":68,
    "gn:feature_class":"P",
    "gn:feature_code":"PPL",
    "gn:name":"Las Negras",
    "gn:population":0,
    "gn:timezone":"America/Mazatlan",
    "iso:country":"MX",
    "wof:name":"Las Negras",
    "wof:placetype":"locality"
},
  "geometry": {"coordinates":[-105.26667,22.23333],"type":"Point"}
}