{
  "type": "Feature",
  "properties": {
    "gn:admin1_code":"26",
    "gn:admin2_code":"42",
    "gn:asciiname":"Avicola Sonqui",
    "gn:country_code":"MX",
    "gn:dem":60,
    "gn:feature_class":"P",
    "gn:feature_code":"PPL",
    "gn:name":"Av\u00edcola Sonqui",
    "gn:population":11,
    "gn:timezone":"America/Hermosillo",
    "iso:country":"MX",
    "name:und_x_variant":[
        "Av\u00edcola Sonqui"
    ],
    "wof:name":"Avicola Sonqui",
    "wof:placetype":"locality",
    "wof:population":11
},
  "geometry": {"coordinates":[-109.75139,27.25556],"type":"Point"}
}