{
  "type": "Feature",
  "properties": {
    "gn:admin1_code":"28.0",
    "gn:admin2_code":"30.0",
    "gn:asciiname":"La Trinidad",
    "gn:country_code":"MX",
    "gn:dem":162,
    "gn:feature_class":"P",
    "gn:feature_code":"PPL",
    "gn:name":"La Trinidad",
    "gn:population":0,
    "gn:timezone":"America/Monterrey",
    "iso:country":"MX",
    "name:spa_x_preferred":[
        "La Trinidad"
    ],
    "wof:name":"La Trinidad",
    "wof:placetype":"locality"
},
  "geometry": {"coordinates":[-98.83,23.95944],"type":"Point"}
}