{
  "type": "Feature",
  "properties": {
    "gn:admin1_code":"5.0",
    "gn:asciiname":"San Isidro",
    "gn:country_code":"MX",
    "gn:dem":1027,
    "gn:feature_class":"P",
    "gn:feature_code":"PPL",
    "gn:name":"San Isidro",
    "gn:population":0,
    "gn:timezone":"America/Mexico_City",
    "iso:country":"MX",
    "name:spa_x_preferred":[
        "San Isidro"
    ],
    "wof:name":"San Isidro",
    "wof:placetype":"locality"
},
  "geometry": {"coordinates":[-92.10709,16.99536],"type":"Point"}
}