{
  "type": "Feature",
  "properties": {
    "gn:admin1_code":"6",
    "gn:admin2_code":"29.0",
    "gn:asciiname":"Mesa del Ganado",
    "gn:country_code":"MX",
    "gn:dem":2799,
    "gn:feature_class":"P",
    "gn:feature_code":"PPL",
    "gn:name":"Mesa del Ganado",
    "gn:population":0,
    "gn:timezone":"America/Chihuahua",
    "iso:country":"MX",
    "name:spa_x_preferred":[
        "Mesa del Ganado"
    ],
    "wof:name":"Mesa del Ganado",
    "wof:placetype":"locality"
},
  "geometry": {"coordinates":[-106.64108,26.25231],"type":"Point"}
}