{
  "type": "Feature",
  "properties": {
    "gn:admin1_code":"30",
    "gn:admin2_code":"204",
    "gn:asciiname":"Hector Ricardez",
    "gn:country_code":"MX",
    "gn:dem":31,
    "gn:feature_class":"P",
    "gn:feature_code":"PPL",
    "gn:name":"H\u00e9ctor Ric\u00e1rdez",
    "gn:population":17,
    "gn:timezone":"America/Mexico_City",
    "iso:country":"MX",
    "name:und_x_variant":[
        "H\u00e9ctor Ric\u00e1rdez"
    ],
    "wof:name":"Hector Ricardez",
    "wof:placetype":"locality",
    "wof:population":17
},
  "geometry": {"coordinates":[-94.14278,18.10917],"type":"Point"}
}