{
  "type": "Feature",
  "properties": {
    "gn:admin1_code":"26",
    "gn:admin2_code":"72.0",
    "gn:asciiname":"San Jose el Tata",
    "gn:country_code":"MX",
    "gn:dem":8,
    "gn:feature_class":"P",
    "gn:feature_code":"PPL",
    "gn:name":"San Jos\u00e9 el Tata",
    "gn:population":5,
    "gn:timezone":"America/Hermosillo",
    "iso:country":"MX",
    "name:und_x_variant":[
        "San Jos\u00e9 el Tata"
    ],
    "wof:name":"San Jose el Tata",
    "wof:placetype":"locality",
    "wof:population":5
},
  "geometry": {"coordinates":[-110.27056,27.34972],"type":"Point"}
}