{
  "type": "Feature",
  "properties": {
    "gn:admin1_code":"19",
    "gn:admin2_code":"14.0",
    "gn:asciiname":"El Desmonte",
    "gn:country_code":"MX",
    "gn:dem":1862,
    "gn:feature_class":"P",
    "gn:feature_code":"PPL",
    "gn:name":"El Desmonte",
    "gn:population":0,
    "gn:timezone":"America/Monterrey",
    "iso:country":"MX",
    "name:ceb_x_preferred":[
        "El Desmonte"
    ],
    "name:spa_x_preferred":[
        "El Desmonte"
    ],
    "wof:name":"El Desmonte",
    "wof:placetype":"locality"
},
  "geometry": {"coordinates":[-100.34535,23.76176],"type":"Point"}
}