{
  "type": "Feature",
  "properties": {
    "gn:admin1_code":"18",
    "gn:admin2_code":"3",
    "gn:asciiname":"El Naranjo",
    "gn:country_code":"MX",
    "gn:dem":894,
    "gn:feature_class":"P",
    "gn:feature_code":"PPL",
    "gn:name":"El Naranjo",
    "gn:population":17,
    "gn:timezone":"America/Mexico_City",
    "iso:country":"MX",
    "wof:name":"El Naranjo",
    "wof:placetype":"locality",
    "wof:population":17
},
  "geometry": {"coordinates":[-104.31861000000001,20.71444],"type":"Point"}
}