{
  "type": "Feature",
  "properties": {
    "gn:admin1_code":"20",
    "gn:admin2_code":"315.0",
    "gn:asciiname":"Agua Blanca",
    "gn:country_code":"MX",
    "gn:dem":1501,
    "gn:feature_class":"P",
    "gn:feature_code":"PPL",
    "gn:name":"Agua Blanca",
    "gn:population":0,
    "gn:timezone":"America/Mexico_City",
    "iso:country":"MX",
    "name:spa_x_preferred":[
        "Agua Blanca"
    ],
    "wof:name":"Agua Blanca",
    "wof:placetype":"locality"
},
  "geometry": {"coordinates":[-96.71278,16.74194],"type":"Point"}
}