{
  "type": "Feature",
  "properties": {
    "gn:admin1_code":"11.0",
    "gn:asciiname":"Coto San Miguel",
    "gn:country_code":"MX",
    "gn:dem":1860,
    "gn:feature_class":"P",
    "gn:feature_code":"PPL",
    "gn:name":"Coto San Miguel",
    "gn:population":0,
    "gn:timezone":"America/Mexico_City",
    "iso:country":"MX",
    "name:spa_x_preferred":[
        "Coto San Miguel"
    ],
    "wof:name":"Coto San Miguel",
    "wof:placetype":"locality"
},
  "geometry": {"coordinates":[-100.78649,20.90105],"type":"Point"}
}