{
  "type": "Feature",
  "properties": {
    "gn:admin1_code":"11",
    "gn:admin2_code":"37",
    "gn:asciiname":"La Montanita",
    "gn:country_code":"MX",
    "gn:dem":2486,
    "gn:feature_class":"P",
    "gn:feature_code":"PPL",
    "gn:name":"La Monta\u00f1ita",
    "gn:population":11,
    "gn:timezone":"America/Mexico_City",
    "iso:country":"MX",
    "name:und_x_variant":[
        "La Monta\u00f1ita"
    ],
    "wof:name":"La Montanita",
    "wof:placetype":"locality",
    "wof:population":11
},
  "geometry": {"coordinates":[-101.37083,21.015],"type":"Point"}
}