{
  "type": "Feature",
  "properties": {
    "gn:admin1_code":"12",
    "gn:admin2_code":"12.0",
    "gn:asciiname":"Tecruz",
    "gn:country_code":"MX",
    "gn:dem":1173,
    "gn:feature_class":"P",
    "gn:feature_code":"PPL",
    "gn:name":"Tecruz",
    "gn:population":0,
    "gn:timezone":"America/Mexico_City",
    "iso:country":"MX",
    "name:spa_x_preferred":[
        "Tecruz"
    ],
    "name:spa_x_variant":[
        "Te Cruz"
    ],
    "wof:name":"Tecruz",
    "wof:placetype":"locality"
},
  "geometry": {"coordinates":[-99.04088,17.0617],"type":"Point"}
}