{
  "type": "Feature",
  "properties": {
    "gn:admin1_code":"8",
    "gn:admin2_code":"1.0",
    "gn:asciiname":"Rancho de Cheque",
    "gn:country_code":"MX",
    "gn:dem":33,
    "gn:feature_class":"P",
    "gn:feature_code":"PPL",
    "gn:name":"Rancho de Cheque",
    "gn:population":4,
    "gn:timezone":"America/Mexico_City",
    "iso:country":"MX",
    "wof:name":"Rancho de Cheque",
    "wof:placetype":"locality",
    "wof:population":4
},
  "geometry": {"coordinates":[-103.97056000000001,18.95611],"type":"Point"}
}