{
  "type": "Feature",
  "properties": {
    "gn:admin1_code":"25",
    "gn:admin2_code":"17.0",
    "gn:asciiname":"Hacienda de los Ceballos",
    "gn:country_code":"MX",
    "gn:dem":260,
    "gn:feature_class":"P",
    "gn:feature_code":"PPL",
    "gn:name":"Hacienda de los Ceballos",
    "gn:population":93,
    "gn:timezone":"America/Mazatlan",
    "iso:country":"MX",
    "wof:name":"Hacienda de los Ceballos",
    "wof:placetype":"locality",
    "wof:population":93
},
  "geometry": {"coordinates":[-107.81661,25.75247],"type":"Point"}
}