{
  "type": "Feature",
  "properties": {
    "gn:admin1_code":"5.0",
    "gn:admin2_code":"38.0",
    "gn:asciiname":"Naok Il",
    "gn:country_code":"MX",
    "gn:dem":2025,
    "gn:feature_class":"P",
    "gn:feature_code":"PPL",
    "gn:name":"Naok Il",
    "gn:population":0,
    "gn:timezone":"America/Mexico_City",
    "iso:country":"MX",
    "name:spa_x_preferred":[
        "Naok\u2019il"
    ],
    "name:spa_x_variant":[
        "Naok Il"
    ],
    "wof:name":"Naok Il",
    "wof:placetype":"locality"
},
  "geometry": {"coordinates":[-92.35566,16.73102],"type":"Point"}
}