{
  "type": "Feature",
  "properties": {
    "gn:admin1_code":"6.0",
    "gn:admin2_code":"15.0",
    "gn:asciiname":"Nueva Esperanza",
    "gn:country_code":"MX",
    "gn:dem":1318,
    "gn:feature_class":"P",
    "gn:feature_code":"PPL",
    "gn:name":"Nueva Esperanza",
    "gn:population":0,
    "gn:timezone":"America/Chihuahua",
    "iso:country":"MX",
    "name:und_x_variant":[
        "Rancho La Esperanza",
        "Nueva Esperanza",
        "Celaya"
    ],
    "wof:name":"Nueva Esperanza",
    "wof:placetype":"locality"
},
  "geometry": {"coordinates":[-105.07805,29.75865],"type":"Point"}
}