{
  "type": "Feature",
  "properties": {
    "gn:admin1_code":"20",
    "gn:admin2_code":"336",
    "gn:asciiname":"Chirimoya Yolox",
    "gn:country_code":"MX",
    "gn:dem":876,
    "gn:feature_class":"P",
    "gn:feature_code":"PPL",
    "gn:name":"Chirimoya Y\u00f3lox",
    "gn:population":26,
    "gn:timezone":"America/Mexico_City",
    "iso:country":"MX",
    "name:und_x_variant":[
        "Chirimoya Y\u00f3lox"
    ],
    "wof:name":"Chirimoya Yolox",
    "wof:placetype":"locality",
    "wof:population":26
},
  "geometry": {"coordinates":[-96.43556,17.62806],"type":"Point"}
}