{
  "type": "Feature",
  "properties": {
    "gn:admin1_code":"12",
    "gn:admin2_code":"7.0",
    "gn:asciiname":"Valle Galeana (El Tamarindo)",
    "gn:country_code":"MX",
    "gn:dem":378,
    "gn:feature_class":"P",
    "gn:feature_code":"PPL",
    "gn:name":"Valle Galeana (El Tamarindo)",
    "gn:population":595,
    "gn:timezone":"America/Mexico_City",
    "iso:country":"MX",
    "wof:name":"Valle Galeana (El Tamarindo)",
    "wof:placetype":"locality",
    "wof:population":595
},
  "geometry": {"coordinates":[-100.23860999999999,18.13],"type":"Point"}
}