{
  "type": "Feature",
  "properties": {
    "gn:admin1_code":"19",
    "gn:admin2_code":"43.0",
    "gn:asciiname":"El Becerro",
    "gn:country_code":"MX",
    "gn:dem":886,
    "gn:feature_class":"P",
    "gn:feature_code":"PPL",
    "gn:name":"El Becerro",
    "gn:population":1,
    "gn:timezone":"America/Monterrey",
    "iso:country":"MX",
    "name:spa_x_preferred":[
        "El Becerro"
    ],
    "wof:name":"El Becerro",
    "wof:placetype":"locality",
    "wof:population":1
},
  "geometry": {"coordinates":[-100.11306,25.03923],"type":"Point"}
}