{
  "type": "Feature",
  "properties": {
    "gn:admin1_code":"10",
    "gn:admin2_code":"26.0",
    "gn:asciiname":"El Ranchito",
    "gn:country_code":"MX",
    "gn:dem":942,
    "gn:feature_class":"P",
    "gn:feature_code":"PPL",
    "gn:name":"El Ranchito",
    "gn:population":8,
    "gn:timezone":"America/Monterrey",
    "iso:country":"MX",
    "wof:name":"El Ranchito",
    "wof:placetype":"locality",
    "wof:population":8
},
  "geometry": {"coordinates":[-105.90948,24.12167],"type":"Point"}
}