{
  "type": "Feature",
  "properties": {
    "gn:admin1_code":"28",
    "gn:admin2_code":"1.0",
    "gn:asciiname":"Las Coloradas",
    "gn:country_code":"MX",
    "gn:dem":68,
    "gn:feature_class":"P",
    "gn:feature_code":"PPL",
    "gn:name":"Las Coloradas",
    "gn:population":0,
    "gn:timezone":"America/Monterrey",
    "iso:country":"MX",
    "name:spa_x_preferred":[
        "Las Coloradas"
    ],
    "name:und_x_variant":[
        "Rancho Coloradas"
    ],
    "wof:name":"Las Coloradas",
    "wof:placetype":"locality"
},
  "geometry": {"coordinates":[-98.03136000000001,24.26886],"type":"Point"}
}