{
  "type": "Feature",
  "properties": {
    "gn:admin1_code":"6",
    "gn:admin2_code":"35.0",
    "gn:asciiname":"Rancho Los Apaches",
    "gn:country_code":"MX",
    "gn:dem":1311,
    "gn:feature_class":"P",
    "gn:feature_code":"PPL",
    "gn:name":"Rancho Los Apaches",
    "gn:population":0,
    "gn:timezone":"America/Chihuahua",
    "iso:country":"MX",
    "wof:name":"Rancho Los Apaches",
    "wof:placetype":"locality"
},
  "geometry": {"coordinates":[-108.05,31.03333],"type":"Point"}
}