{
  "type": "Feature",
  "properties": {
    "gn:admin1_code":"25",
    "gn:admin2_code":"16.0",
    "gn:asciiname":"El Zapoton",
    "gn:country_code":"MX",
    "gn:dem":303,
    "gn:feature_class":"P",
    "gn:feature_code":"PPL",
    "gn:name":"El Zapot\u00f3n",
    "gn:population":0,
    "gn:timezone":"America/Mazatlan",
    "iso:country":"MX",
    "name:spa_x_preferred":[
        "El Zapot\u00f3n"
    ],
    "wof:name":"El Zapoton",
    "wof:placetype":"locality"
},
  "geometry": {"coordinates":[-106.44473000000001,23.82311],"type":"Point"}
}