{
  "type": "Feature",
  "properties": {
    "gn:admin1_code":"13",
    "gn:admin2_code":"43.0",
    "gn:asciiname":"El Aguacate",
    "gn:country_code":"MX",
    "gn:dem":1271,
    "gn:feature_class":"P",
    "gn:feature_code":"PPL",
    "gn:name":"El Aguacate",
    "gn:population":108,
    "gn:timezone":"America/Mexico_City",
    "iso:country":"MX",
    "wof:name":"El Aguacate",
    "wof:placetype":"locality",
    "wof:population":108
},
  "geometry": {"coordinates":[-99.15129,20.85267],"type":"Point"}
}