{
  "type": "Feature",
  "properties": {
    "gn:admin1_code":"5.0",
    "gn:admin2_code":"23.0",
    "gn:asciiname":"Nukulpatik",
    "gn:country_code":"MX",
    "gn:dem":2484,
    "gn:feature_class":"P",
    "gn:feature_code":"PPL",
    "gn:name":"Nukulpatik",
    "gn:population":0,
    "gn:timezone":"America/Mexico_City",
    "iso:country":"MX",
    "name:spa_x_preferred":[
        "Nukulpatik"
    ],
    "wof:name":"Nukulpatik",
    "wof:placetype":"locality"
},
  "geometry": {"coordinates":[-92.76727,16.82429],"type":"Point"}
}