{
  "type": "Feature",
  "properties": {
    "gn:admin1_code":"28",
    "gn:admin2_code":"16.0",
    "gn:asciiname":"Santa Clotilde",
    "gn:country_code":"MX",
    "gn:dem":359,
    "gn:feature_class":"P",
    "gn:feature_code":"PPL",
    "gn:name":"Santa Clotilde",
    "gn:population":0,
    "gn:timezone":"America/Monterrey",
    "iso:country":"MX",
    "name:spa_x_preferred":[
        "Santa Clotilde"
    ],
    "name:spa_x_variant":[
        "Santa Cleotilde"
    ],
    "name:und_x_variant":[
        "Ejido La Cleotilde"
    ],
    "wof:name":"Santa Clotilde",
    "wof:placetype":"locality"
},
  "geometry": {"coordinates":[-99.46133,24.28126],"type":"Point"}
}