{
  "type": "Feature",
  "properties": {
    "gn:admin1_code":"3",
    "gn:admin2_code":"1.0",
    "gn:asciiname":"San Luis Gonzaga",
    "gn:country_code":"MX",
    "gn:dem":158,
    "gn:feature_class":"P",
    "gn:feature_code":"PPL",
    "gn:name":"San Luis Gonzaga",
    "gn:population":0,
    "gn:timezone":"America/Mazatlan",
    "iso:country":"MX",
    "name:und_x_variant":[
        "San Luis"
    ],
    "wof:name":"San Luis Gonzaga",
    "wof:placetype":"locality"
},
  "geometry": {"coordinates":[-111.29156,24.9083],"type":"Point"}
}