{
  "type": "Feature",
  "properties": {
    "gn:admin1_code":"16.0",
    "gn:admin2_code":"26.0",
    "gn:asciiname":"El Chafre",
    "gn:country_code":"MX",
    "gn:dem":586,
    "gn:feature_class":"P",
    "gn:feature_code":"PPL",
    "gn:name":"El Chafre",
    "gn:population":0,
    "gn:timezone":"America/Mexico_City",
    "iso:country":"MX",
    "name:spa_x_preferred":[
        "El Chafre"
    ],
    "wof:name":"El Chafre",
    "wof:placetype":"locality"
},
  "geometry": {"coordinates":[-103.48045999999999,18.65205],"type":"Point"}
}