{
  "type": "Feature",
  "properties": {
    "gn:admin1_code":"15.0",
    "gn:admin2_code":"82.0",
    "gn:asciiname":"Las Juntas de Ixtapan",
    "gn:country_code":"MX",
    "gn:dem":941,
    "gn:feature_class":"P",
    "gn:feature_code":"PPL",
    "gn:name":"Las Juntas de Ixtapan",
    "gn:population":138,
    "gn:timezone":"America/Mexico_City",
    "iso:country":"MX",
    "name:und_x_variant":[
        "Llamas",
        "Ilamos"
    ],
    "wof:name":"Las Juntas de Ixtapan",
    "wof:placetype":"locality",
    "wof:population":138
},
  "geometry": {"coordinates":[-100.16249000000001,18.80036],"type":"Point"}
}