{
  "type": "Feature",
  "properties": {
    "gn:admin1_code":"32",
    "gn:admin2_code":"49.0",
    "gn:asciiname":"San Martin de la Palma",
    "gn:country_code":"MX",
    "gn:dem":1923,
    "gn:feature_class":"P",
    "gn:feature_code":"PPL",
    "gn:name":"San Mart\u00edn de la Palma",
    "gn:population":0,
    "gn:timezone":"America/Mexico_City",
    "iso:country":"MX",
    "name:spa_x_preferred":[
        "San Mart\u00edn de la Palma"
    ],
    "wof:name":"San Martin de la Palma",
    "wof:placetype":"locality"
},
  "geometry": {"coordinates":[-103.55439,22.69371],"type":"Point"}
}