{
  "type": "Feature",
  "properties": {
    "gn:admin1_code":"12",
    "gn:admin2_code":"11.0",
    "gn:asciiname":"Cuatro Milpas",
    "gn:country_code":"MX",
    "gn:dem":20,
    "gn:feature_class":"P",
    "gn:feature_code":"PPL",
    "gn:name":"Cuatro Milpas",
    "gn:population":80,
    "gn:timezone":"America/Mexico_City",
    "iso:country":"MX",
    "wof:name":"Cuatro Milpas",
    "wof:placetype":"locality",
    "wof:population":80
},
  "geometry": {"coordinates":[-100.38587,17.13486],"type":"Point"}
}