{
  "type": "Feature",
  "properties": {
    "gn:admin1_code":"19",
    "gn:admin2_code":"5.0",
    "gn:asciiname":"San Antonio",
    "gn:country_code":"MX",
    "gn:dem":145,
    "gn:feature_class":"P",
    "gn:feature_code":"PPL",
    "gn:name":"San Antonio",
    "gn:population":0,
    "gn:timezone":"America/Matamoros",
    "iso:country":"MX",
    "name:und_x_variant":[
        "Rancho San Antonio",
        "San Antonio"
    ],
    "wof:name":"San Antonio",
    "wof:placetype":"locality"
},
  "geometry": {"coordinates":[-99.87927999999999,26.92683],"type":"Point"}
}