{
  "type": "Feature",
  "properties": {
    "gn:admin1_code":"16",
    "gn:admin2_code":"8",
    "gn:asciiname":"Sibiahues",
    "gn:country_code":"MX",
    "gn:dem":47,
    "gn:feature_class":"P",
    "gn:feature_code":"PPL",
    "gn:name":"Sibiahues",
    "gn:population":14,
    "gn:timezone":"America/Mexico_City",
    "iso:country":"MX",
    "wof:name":"Sibiahues",
    "wof:placetype":"locality",
    "wof:population":14
},
  "geometry": {"coordinates":[-103.43861,18.34889],"type":"Point"}
}