{
  "type": "Feature",
  "properties": {
    "gn:admin1_code":"19",
    "gn:admin2_code":"17",
    "gn:asciiname":"La Palapa",
    "gn:country_code":"MX",
    "gn:dem":1882,
    "gn:feature_class":"P",
    "gn:feature_code":"PPL",
    "gn:name":"La Palapa",
    "gn:population":14,
    "gn:timezone":"America/Monterrey",
    "iso:country":"MX",
    "wof:name":"La Palapa",
    "wof:placetype":"locality",
    "wof:population":14
},
  "geometry": {"coordinates":[-100.31234000000001,24.75395],"type":"Point"}
}