{
  "type": "Feature",
  "properties": {
    "gn:admin1_code":"6",
    "gn:admin2_code":"27.0",
    "gn:asciiname":"El Aguajito",
    "gn:country_code":"MX",
    "gn:dem":2235,
    "gn:feature_class":"P",
    "gn:feature_code":"PPL",
    "gn:name":"El Aguajito",
    "gn:population":5,
    "gn:timezone":"America/Chihuahua",
    "iso:country":"MX",
    "wof:name":"El Aguajito",
    "wof:placetype":"locality",
    "wof:population":5
},
  "geometry": {"coordinates":[-107.45739,26.80577000000001],"type":"Point"}
}