{
  "type": "Feature",
  "properties": {
    "gn:admin1_code":"5",
    "gn:admin2_code":"87",
    "gn:asciiname":"Tierra Brava",
    "gn:country_code":"MX",
    "gn:dem":20,
    "gn:feature_class":"P",
    "gn:feature_code":"PPL",
    "gn:name":"Tierra Brava",
    "gn:population":17,
    "gn:timezone":"America/Mexico_City",
    "iso:country":"MX",
    "wof:name":"Tierra Brava",
    "wof:placetype":"locality",
    "wof:population":17
},
  "geometry": {"coordinates":[-92.20556000000001,14.64583],"type":"Point"}
}