{
  "type": "Feature",
  "properties": {
    "gn:admin1_code":"6",
    "gn:admin2_code":"66.0",
    "gn:asciiname":"Chiltepin",
    "gn:country_code":"MX",
    "gn:dem":1144,
    "gn:feature_class":"P",
    "gn:feature_code":"PPL",
    "gn:name":"Chiltep\u00edn",
    "gn:population":83,
    "gn:timezone":"America/Chihuahua",
    "iso:country":"MX",
    "name:spa_x_preferred":[
        "Chiltep\u00edn"
    ],
    "wof:name":"Chiltepin",
    "wof:placetype":"locality",
    "wof:population":83
},
  "geometry": {"coordinates":[-108.62994999999999,27.93435],"type":"Point"}
}