{
  "type": "Feature",
  "properties": {
    "gn:admin1_code":"6.0",
    "gn:admin2_code":"29.0",
    "gn:asciiname":"El Rosado",
    "gn:country_code":"MX",
    "gn:dem":2551,
    "gn:feature_class":"P",
    "gn:feature_code":"PPL",
    "gn:name":"El Rosado",
    "gn:population":0,
    "gn:timezone":"America/Chihuahua",
    "iso:country":"MX",
    "name:spa_x_preferred":[
        "El Rosado"
    ],
    "wof:name":"El Rosado",
    "wof:placetype":"locality"
},
  "geometry": {"coordinates":[-106.64199000000001,26.33696],"type":"Point"}
}