{
  "type": "Feature",
  "properties": {
    "gn:admin1_code":"25",
    "gn:admin2_code":"8.0",
    "gn:asciiname":"Alta Rosa (Pipila II)",
    "gn:country_code":"MX",
    "gn:dem":62,
    "gn:feature_class":"P",
    "gn:feature_code":"PPL",
    "gn:name":"Alta Rosa (P\u00edpila II)",
    "gn:population":224,
    "gn:timezone":"America/Mazatlan",
    "iso:country":"MX",
    "name:und_x_variant":[
        "Alta Rosa (P\u00edpila II)"
    ],
    "wof:name":"Alta Rosa (Pipila II)",
    "wof:placetype":"locality",
    "wof:population":224
},
  "geometry": {"coordinates":[-106.99944000000001,24.15417],"type":"Point"}
}