{
  "type": "Feature",
  "properties": {
    "gn:admin1_code":"6",
    "gn:admin2_code":"29",
    "gn:asciiname":"Los Arbolitos",
    "gn:country_code":"MX",
    "gn:dem":2402,
    "gn:feature_class":"P",
    "gn:feature_code":"PPL",
    "gn:name":"Los Arbolitos",
    "gn:population":27,
    "gn:timezone":"America/Chihuahua",
    "iso:country":"MX",
    "wof:name":"Los Arbolitos",
    "wof:placetype":"locality",
    "wof:population":27
},
  "geometry": {"coordinates":[-106.96373,25.88774],"type":"Point"}
}