{
  "type": "Feature",
  "properties": {
    "gn:admin1_code":"12.0",
    "gn:asciiname":"Lagunas",
    "gn:country_code":"MX",
    "gn:dem":2584,
    "gn:feature_class":"P",
    "gn:feature_code":"PPL",
    "gn:name":"Lagunas",
    "gn:population":0,
    "gn:timezone":"America/Mexico_City",
    "iso:country":"MX",
    "name:spa_x_preferred":[
        "Lagunas"
    ],
    "wof:name":"Lagunas",
    "wof:placetype":"locality"
},
  "geometry": {"coordinates":[-98.34206,17.25008],"type":"Point"}
}