{
  "type": "Feature",
  "properties": {
    "gn:admin1_code":"5",
    "gn:admin2_code":"27",
    "gn:asciiname":"San Miguel Dos",
    "gn:country_code":"MX",
    "gn:dem":528,
    "gn:feature_class":"P",
    "gn:feature_code":"PPL",
    "gn:name":"San Miguel Dos",
    "gn:population":22,
    "gn:timezone":"America/Mexico_City",
    "iso:country":"MX",
    "wof:name":"San Miguel Dos",
    "wof:placetype":"locality",
    "wof:population":22
},
  "geometry": {"coordinates":[-92.97083000000001,16.72389],"type":"Point"}
}