{
  "type": "Feature",
  "properties": {
    "gn:admin1_code":"10",
    "gn:admin2_code":"35",
    "gn:asciiname":"El Ranchito de la Purisima",
    "gn:country_code":"MX",
    "gn:dem":1891,
    "gn:feature_class":"P",
    "gn:feature_code":"PPL",
    "gn:name":"El Ranchito de la Pur\u00edsima",
    "gn:population":11,
    "gn:timezone":"America/Monterrey",
    "iso:country":"MX",
    "name:und_x_variant":[
        "El Ranchito de la Pur\u00edsima"
    ],
    "wof:name":"El Ranchito de la Purisima",
    "wof:placetype":"locality",
    "wof:population":11
},
  "geometry": {"coordinates":[-106.37232,25.37331],"type":"Point"}
}