{
  "type": "Feature",
  "properties": {
    "gn:admin1_code":"6",
    "gn:admin2_code":"30.0",
    "gn:asciiname":"Los Parajes",
    "gn:country_code":"MX",
    "gn:dem":1487,
    "gn:feature_class":"P",
    "gn:feature_code":"PPL",
    "gn:name":"Los Parajes",
    "gn:population":0,
    "gn:timezone":"America/Chihuahua",
    "iso:country":"MX",
    "name:spa_x_preferred":[
        "Los Parajes"
    ],
    "wof:name":"Los Parajes",
    "wof:placetype":"locality"
},
  "geometry": {"coordinates":[-108.19678999999999,27.35256],"type":"Point"}
}