{
  "type": "Feature",
  "properties": {
    "gn:admin1_code":"19",
    "gn:admin2_code":"38.0",
    "gn:asciiname":"San Agustin",
    "gn:country_code":"MX",
    "gn:dem":293,
    "gn:feature_class":"P",
    "gn:feature_code":"PPL",
    "gn:name":"San Agust\u00edn",
    "gn:population":15,
    "gn:timezone":"America/Monterrey",
    "iso:country":"MX",
    "wof:name":"San Agustin",
    "wof:placetype":"locality",
    "wof:population":15
},
  "geometry": {"coordinates":[-99.82917999999999,25.34034],"type":"Point"}
}