{
  "type": "Feature",
  "properties": {
    "gn:admin1_code":"26",
    "gn:admin2_code":"57.0",
    "gn:asciiname":"Notechape",
    "gn:country_code":"MX",
    "gn:dem":553,
    "gn:feature_class":"P",
    "gn:feature_code":"PPL",
    "gn:name":"Notechape",
    "gn:population":0,
    "gn:timezone":"America/Hermosillo",
    "iso:country":"MX",
    "name:spa_x_preferred":[
        "Notechape"
    ],
    "wof:name":"Notechape",
    "wof:placetype":"locality"
},
  "geometry": {"coordinates":[-109.86875999999999,29.36406],"type":"Point"}
}