{
  "type": "Feature",
  "properties": {
    "gn:admin1_code":"16",
    "gn:admin2_code":"49.0",
    "gn:asciiname":"Cerro Blanco (Cabuayana)",
    "gn:country_code":"MX",
    "gn:dem":1872,
    "gn:feature_class":"P",
    "gn:feature_code":"PPL",
    "gn:name":"Cerro Blanco (Cabuayana)",
    "gn:population":71,
    "gn:timezone":"America/Mexico_City",
    "iso:country":"MX",
    "wof:name":"Cerro Blanco (Cabuayana)",
    "wof:placetype":"locality",
    "wof:population":71
},
  "geometry": {"coordinates":[-101.27110999999999,19.28639],"type":"Point"}
}