{
  "type": "Feature",
  "properties": {
    "gn:admin1_code":"25",
    "gn:admin2_code":"10.0",
    "gn:asciiname":"El Charco Verde",
    "gn:country_code":"MX",
    "gn:dem":146,
    "gn:feature_class":"P",
    "gn:feature_code":"PPL",
    "gn:name":"El Charco Verde",
    "gn:population":0,
    "gn:timezone":"America/Mazatlan",
    "iso:country":"MX",
    "name:spa_x_preferred":[
        "El Charco Verde"
    ],
    "wof:name":"El Charco Verde",
    "wof:placetype":"locality"
},
  "geometry": {"coordinates":[-108.56780000000001,26.27756],"type":"Point"}
}