{
  "type": "Feature",
  "properties": {
    "gn:admin1_code":"5.0",
    "gn:asciiname":"San Antonio Sabinal Paso Blanco",
    "gn:country_code":"MX",
    "gn:dem":1543,
    "gn:feature_class":"P",
    "gn:feature_code":"PPL",
    "gn:name":"San Antonio Sabinal Paso Blanco",
    "gn:population":0,
    "gn:timezone":"America/Mexico_City",
    "iso:country":"MX",
    "name:spa_x_preferred":[
        "San Antonio Sabinal Paso Blanco"
    ],
    "wof:name":"San Antonio Sabinal Paso Blanco",
    "wof:placetype":"locality"
},
  "geometry": {"coordinates":[-92.12803,16.16698],"type":"Point"}
}