{
  "type": "Feature",
  "properties": {
    "gn:admin1_code":"6.0",
    "gn:admin2_code":"10.0",
    "gn:asciiname":"El Sombreretillo",
    "gn:country_code":"MX",
    "gn:dem":1290,
    "gn:feature_class":"P",
    "gn:feature_code":"PPL",
    "gn:name":"El Sombreretillo",
    "gn:population":0,
    "gn:timezone":"America/Chihuahua",
    "iso:country":"MX",
    "name:spa_x_preferred":[
        "El Sombreretillo"
    ],
    "wof:name":"El Sombreretillo",
    "wof:placetype":"locality"
},
  "geometry": {"coordinates":[-107.35890000000001,30.70604],"type":"Point"}
}