{
  "type": "Feature",
  "properties": {
    "gn:admin1_code":"23",
    "gn:admin2_code":"2.0",
    "gn:asciiname":"San Bartolo",
    "gn:country_code":"MX",
    "gn:dem":22,
    "gn:feature_class":"P",
    "gn:feature_code":"PPL",
    "gn:name":"San Bartolo",
    "gn:population":0,
    "gn:timezone":"America/Cancun",
    "iso:country":"MX",
    "name:spa_x_preferred":[
        "San Bartolo"
    ],
    "wof:name":"San Bartolo",
    "wof:placetype":"locality"
},
  "geometry": {"coordinates":[-88.06286999999998,20.1617],"type":"Point"}
}