{
  "type": "Feature",
  "properties": {
    "gn:admin1_code":"6",
    "gn:admin2_code":"28.0",
    "gn:asciiname":"Los Frailes",
    "gn:country_code":"MX",
    "gn:dem":1228,
    "gn:feature_class":"P",
    "gn:feature_code":"PPL",
    "gn:name":"Los Frailes",
    "gn:population":0,
    "gn:timezone":"America/Chihuahua",
    "iso:country":"MX",
    "name:und_x_variant":[
        "Rancho Los Frailes",
        "Los Frailes"
    ],
    "wof:name":"Los Frailes",
    "wof:placetype":"locality"
},
  "geometry": {"coordinates":[-105.5802,30.89596],"type":"Point"}
}