{
  "type": "Feature",
  "properties": {
    "gn:admin1_code":"12.0",
    "gn:admin2_code":"11.0",
    "gn:asciiname":"Plan de las Delicias",
    "gn:country_code":"MX",
    "gn:dem":753,
    "gn:feature_class":"P",
    "gn:feature_code":"PPL",
    "gn:name":"Plan de las Delicias",
    "gn:population":0,
    "gn:timezone":"America/Mexico_City",
    "iso:country":"MX",
    "name:und_x_variant":[
        "Plan de Delicas",
        "Delicias del Plan Grande"
    ],
    "wof:name":"Plan de las Delicias",
    "wof:placetype":"locality"
},
  "geometry": {"coordinates":[-100.23153000000001,17.40525],"type":"Point"}
}