{
  "type": "Feature",
  "properties": {
    "gn:gn_country":"MX",
    "gn:gn_fcode":"PPL",
    "gn:gn_pop":0,
    "iso:country":"MX",
    "name:bel_x_preferred":[
        "\u042d\u043b\u044c-\u041c\u0456\u0440\u0430\u0434\u043e\u0440"
    ],
    "name:dan_x_preferred":[
        "El Mirador"
    ],
    "name:deu_x_preferred":[
        "El Mirador"
    ],
    "name:epo_x_preferred":[
        "El Mirador"
    ],
    "name:fin_x_preferred":[
        "El Mirador"
    ],
    "name:fra_x_preferred":[
        "El Mirador"
    ],
    "name:hun_x_preferred":[
        "El Mirador"
    ],
    "name:ind_x_preferred":[
        "El Mirador"
    ],
    "name:ita_x_preferred":[
        "El Mirador"
    ],
    "name:jpn_x_preferred":[
        "\u30a8\u30eb\u30fb\u30df\u30e9\u30c9\u30fc\u30eb"
    ],
    "name:lit_x_preferred":[
        "El Miradoras"
    ],
    "name:mkd_x_preferred":[
        "\u0415\u043b \u041c\u0438\u0440\u0430\u0434\u043e\u0440"
    ],
    "name:nds_x_preferred":[
        "El Mirador"
    ],
    "name:nor_x_preferred":[
        "El Mirador"
    ],
    "name:pol_x_preferred":[
        "El Mirador"
    ],
    "name:por_x_preferred":[
        "El Mirador"
    ],
    "name:rus_x_preferred":[
        "\u042d\u043b\u044c-\u041c\u0438\u0440\u0430\u0434\u043e\u0440"
    ],
    "name:spa_x_preferred":[
        "El Mirador"
    ],
    "name:ukr_x_preferred":[
        "\u0415\u043b\u044c-\u041c\u0456\u0440\u0430\u0434\u043e\u0440"
    ],
    "qs_pg:aaroncc":"MX",
    "qs_pg:gn_country":"MX",
    "qs_pg:gn_fcode":"PPL",
    "qs_pg:gn_pop":0,
    "qs_pg:name":"El Mirador",
    "qs_pg:name_adm0":"M\u00e9xico",
    "qs_pg:name_adm1":"Nayarit",
    "qs_pg:photos":3,
    "qs_pg:photos_1k":1,
    "qs_pg:photos_9k":1,
    "qs_pg:photos_9r":1,
    "qs_pg:photos_all":3,
    "qs_pg:photos_sr":1,
    "qs_pg:pop_sr":0,
    "qs_pg:qs_pg_placetype":"neighbourhood",
    "qs_pg:qs_pg_placetype_gp":"Suburb",
    "qs_pg:woe_adm0":23424900,
    "woe:adm0_id":23424900,
    "woe:name_adm0":"M\u00e9xico",
    "woe:name_adm1":"Nayarit",
    "woe:placetype":"Suburb",
    "wof:name":"El Mirador",
    "wof:placetype":"neighbourhood"
},
  "geometry": {"coordinates":[-105.13341,21.69106],"type":"Point"}
}