{
  "type": "Feature",
  "properties": {
    "gn:admin1_code":"11.0",
    "gn:admin2_code":"30.0",
    "gn:asciiname":"Los Placeres",
    "gn:country_code":"MX",
    "gn:dem":2414,
    "gn:feature_class":"P",
    "gn:feature_code":"PPL",
    "gn:name":"Los Placeres",
    "gn:population":0,
    "gn:timezone":"America/Mexico_City",
    "iso:country":"MX",
    "name:spa_x_preferred":[
        "Los Placeres"
    ],
    "wof:name":"Los Placeres",
    "wof:placetype":"locality"
},
  "geometry": {"coordinates":[-101.53812000000001,21.34859],"type":"Point"}
}