{
  "type": "Feature",
  "properties": {
    "gn:admin1_code":"21",
    "gn:admin2_code":"6.0",
    "gn:asciiname":"Tlapoxtecoya",
    "gn:country_code":"MX",
    "gn:dem":1563,
    "gn:feature_class":"P",
    "gn:feature_code":"PPL",
    "gn:name":"Tlapoxtecoya",
    "gn:population":84,
    "gn:timezone":"America/Mexico_City",
    "iso:country":"MX",
    "wof:name":"Tlapoxtecoya",
    "wof:placetype":"locality",
    "wof:population":84
},
  "geometry": {"coordinates":[-97.84473,19.99826],"type":"Point"}
}