{
  "type": "Feature",
  "properties": {
    "gn:admin1_code":"20",
    "gn:admin2_code":"270",
    "gn:asciiname":"El Rosario",
    "gn:country_code":"MX",
    "gn:dem":1948,
    "gn:feature_class":"P",
    "gn:feature_code":"PPL",
    "gn:name":"El Rosario",
    "gn:population":49,
    "gn:timezone":"America/Mexico_City",
    "iso:country":"MX",
    "wof:name":"El Rosario",
    "wof:placetype":"locality",
    "wof:population":49
},
  "geometry": {"coordinates":[-97.14333000000001,17.75361000000001],"type":"Point"}
}