{
  "type": "Feature",
  "properties": {
    "gn:admin1_code":"27",
    "gn:admin2_code":"8.0",
    "gn:asciiname":"Pejelagartero 1ra. Seccion (Plataforma)",
    "gn:country_code":"MX",
    "gn:dem":13,
    "gn:feature_class":"P",
    "gn:feature_code":"PPL",
    "gn:name":"Pejelagartero 1ra. Secci\u00f3n (Plataforma)",
    "gn:population":1817,
    "gn:timezone":"America/Mexico_City",
    "iso:country":"MX",
    "name:und_x_variant":[
        "Pejelagartero 1ra. Secci\u00f3n (Plataforma)"
    ],
    "wof:name":"Pejelagartero 1ra. Seccion (Plataforma)",
    "wof:placetype":"locality",
    "wof:population":1817
},
  "geometry": {"coordinates":[-93.82472,18.055],"type":"Point"}
}