{
  "type": "Feature",
  "properties": {
    "gn:admin1_code":"6",
    "gn:admin2_code":"51.0",
    "gn:asciiname":"Chocachi",
    "gn:country_code":"MX",
    "gn:dem":2565,
    "gn:feature_class":"P",
    "gn:feature_code":"PPL",
    "gn:name":"Chocachi",
    "gn:population":0,
    "gn:timezone":"America/Chihuahua",
    "iso:country":"MX",
    "name:spa_x_preferred":[
        "Chocachi"
    ],
    "wof:name":"Chocachi",
    "wof:placetype":"locality"
},
  "geometry": {"coordinates":[-108.0544,28.21802000000001],"type":"Point"}
}