{
  "type": "Feature",
  "properties": {
    "gn:admin1_code":"6.0",
    "gn:admin2_code":"28.0",
    "gn:asciiname":"Allende",
    "gn:country_code":"MX",
    "gn:dem":1065,
    "gn:feature_class":"P",
    "gn:feature_code":"PPL",
    "gn:name":"Allende",
    "gn:population":0,
    "gn:timezone":"America/Chihuahua",
    "iso:country":"MX",
    "name:spa_x_preferred":[
        "Allende"
    ],
    "wof:name":"Allende",
    "wof:placetype":"locality"
},
  "geometry": {"coordinates":[-105.75163999999999,31.15466],"type":"Point"}
}