{
  "type": "Feature",
  "properties": {
    "gn:admin1_code":"7.0",
    "gn:admin2_code":"33.0",
    "gn:asciiname":"Ignacio Zaragoza",
    "gn:country_code":"MX",
    "gn:dem":1102,
    "gn:feature_class":"P",
    "gn:feature_code":"PPL",
    "gn:name":"Ignacio Zaragoza",
    "gn:population":706,
    "gn:timezone":"America/Monterrey",
    "iso:country":"MX",
    "name:spa_x_preferred":[
        "Ignacio Zaragoza"
    ],
    "wof:name":"Ignacio Zaragoza",
    "wof:placetype":"locality",
    "wof:population":706
},
  "geometry": {"coordinates":[-102.9753,25.70167],"type":"Point"}
}