{
  "type": "Feature",
  "properties": {
    "gn:admin1_code":"32",
    "gn:admin2_code":"37.0",
    "gn:asciiname":"La Zuliana Tres",
    "gn:country_code":"MX",
    "gn:dem":2005,
    "gn:feature_class":"P",
    "gn:feature_code":"PPL",
    "gn:name":"La Zuliana Tres",
    "gn:population":66,
    "gn:timezone":"America/Mexico_City",
    "iso:country":"MX",
    "wof:name":"La Zuliana Tres",
    "wof:placetype":"locality",
    "wof:population":66
},
  "geometry": {"coordinates":[-102.33194,23.02833],"type":"Point"}
}