{
  "type": "Feature",
  "properties": {
    "gn:admin1_code":"5",
    "gn:admin2_code":"24.0",
    "gn:asciiname":"San Jose Tzibalche",
    "gn:country_code":"MX",
    "gn:dem":2178,
    "gn:feature_class":"P",
    "gn:feature_code":"PPL",
    "gn:name":"San Jos\u00e9 Tzibalch\u00e9",
    "gn:population":132,
    "gn:timezone":"America/Mexico_City",
    "iso:country":"MX",
    "name:und_x_variant":[
        "San Jos\u00e9 Tzibalch\u00e9"
    ],
    "wof:name":"San Jose Tzibalche",
    "wof:placetype":"locality",
    "wof:population":132
},
  "geometry": {"coordinates":[-92.31305999999999,16.61611],"type":"Point"}
}