{
  "type": "Feature",
  "properties": {
    "gn:admin1_code":"16.0",
    "gn:admin2_code":"108.0",
    "gn:asciiname":"Atecuario",
    "gn:country_code":"MX",
    "gn:dem":1670,
    "gn:feature_class":"P",
    "gn:feature_code":"PPL",
    "gn:name":"Atecuario",
    "gn:population":0,
    "gn:timezone":"America/Mexico_City",
    "iso:country":"MX",
    "wof:name":"Atecuario",
    "wof:placetype":"locality"
},
  "geometry": {"coordinates":[-102.21666999999999,20.06667],"type":"Point"}
}