{
  "type": "Feature",
  "properties": {
    "gn:admin1_code":"15",
    "gn:admin2_code":"24",
    "gn:asciiname":"Ejido el Tejado",
    "gn:country_code":"MX",
    "gn:dem":2247,
    "gn:feature_class":"P",
    "gn:feature_code":"PPL",
    "gn:name":"Ejido el Tejado",
    "gn:population":35,
    "gn:timezone":"America/Mexico_City",
    "iso:country":"MX",
    "wof:name":"Ejido el Tejado",
    "wof:placetype":"locality",
    "wof:population":35
},
  "geometry": {"coordinates":[-99.12277,19.73657],"type":"Point"}
}