{
  "type": "Feature",
  "properties": {
    "gn:admin1_code":"12.0",
    "gn:admin2_code":"70.0",
    "gn:asciiname":"Cuateconyo",
    "gn:country_code":"MX",
    "gn:dem":1287,
    "gn:feature_class":"P",
    "gn:feature_code":"PPL",
    "gn:name":"Cuateconyo",
    "gn:population":0,
    "gn:timezone":"America/Mexico_City",
    "iso:country":"MX",
    "name:spa_x_preferred":[
        "Cuateconyo"
    ],
    "wof:name":"Cuateconyo",
    "wof:placetype":"locality"
},
  "geometry": {"coordinates":[-98.43491,17.97471],"type":"Point"}
}