{
  "type": "Feature",
  "properties": {
    "gn:admin1_code":"28",
    "gn:admin2_code":"39",
    "gn:asciiname":"Ojo de Agua del Capitan",
    "gn:country_code":"MX",
    "gn:dem":1328,
    "gn:feature_class":"P",
    "gn:feature_code":"PPL",
    "gn:name":"Ojo de Agua del Capit\u00e1n",
    "gn:population":18,
    "gn:timezone":"America/Monterrey",
    "iso:country":"MX",
    "name:und_x_variant":[
        "Ojo de Agua del Capit\u00e1n"
    ],
    "wof:name":"Ojo de Agua del Capitan",
    "wof:placetype":"locality",
    "wof:population":18
},
  "geometry": {"coordinates":[-99.69638999999999,23.13667],"type":"Point"}
}