{
  "type": "Feature",
  "properties": {
    "gn:admin1_code":"19",
    "gn:admin2_code":"20.0",
    "gn:asciiname":"Cabeza de Toro",
    "gn:country_code":"MX",
    "gn:dem":163,
    "gn:feature_class":"P",
    "gn:feature_code":"PPL",
    "gn:name":"Cabeza de Toro",
    "gn:population":0,
    "gn:timezone":"America/Monterrey",
    "iso:country":"MX",
    "name:und_x_variant":[
        "Cabeza de Toro de Rafael Mart\u00ednez"
    ],
    "wof:name":"Cabeza de Toro",
    "wof:placetype":"locality"
},
  "geometry": {"coordinates":[-99.09759,25.66314],"type":"Point"}
}