{
  "type": "Feature",
  "properties": {
    "gn:admin1_code":"3",
    "gn:admin2_code":"1.0",
    "gn:asciiname":"La Polita",
    "gn:country_code":"MX",
    "gn:dem":206,
    "gn:feature_class":"P",
    "gn:feature_code":"PPL",
    "gn:name":"La Polita",
    "gn:population":0,
    "gn:timezone":"America/Mazatlan",
    "iso:country":"MX",
    "name:spa_x_preferred":[
        "La Polita"
    ],
    "wof:name":"La Polita",
    "wof:placetype":"locality"
},
  "geometry": {"coordinates":[-112.14348,26.33903],"type":"Point"}
}