{
  "type": "Feature",
  "properties": {
    "gn:admin1_code":"21",
    "gn:admin2_code":"39.0",
    "gn:asciiname":"Hueytentan",
    "gn:country_code":"MX",
    "gn:dem":1615,
    "gn:feature_class":"P",
    "gn:feature_code":"PPL",
    "gn:name":"Hueytentan",
    "gn:population":0,
    "gn:timezone":"America/Mexico_City",
    "iso:country":"MX",
    "name:spa_x_preferred":[
        "Hueytentan"
    ],
    "name:und_x_variant":[
        "Hueytent\u00e1n"
    ],
    "wof:name":"Hueytentan",
    "wof:placetype":"locality"
},
  "geometry": {"coordinates":[-97.82326999999999,19.88049],"type":"Point"}
}