{
  "type": "Feature",
  "properties": {
    "gn:admin1_code":"6",
    "gn:admin2_code":"9",
    "gn:asciiname":"Rijuviachi",
    "gn:country_code":"MX",
    "gn:dem":2455,
    "gn:feature_class":"P",
    "gn:feature_code":"PPL",
    "gn:name":"Rijuviachi",
    "gn:population":45,
    "gn:timezone":"America/Chihuahua",
    "iso:country":"MX",
    "wof:name":"Rijuviachi",
    "wof:placetype":"locality",
    "wof:population":45
},
  "geometry": {"coordinates":[-107.60492000000001,27.68492],"type":"Point"}
}