{
  "type": "Feature",
  "properties": {
    "gn:admin1_code":"30",
    "gn:admin2_code":"114",
    "gn:asciiname":"Colonia el Mirador",
    "gn:country_code":"MX",
    "gn:dem":23,
    "gn:feature_class":"P",
    "gn:feature_code":"PPL",
    "gn:name":"Colonia el Mirador",
    "gn:population":19,
    "gn:timezone":"America/Mexico_City",
    "iso:country":"MX",
    "wof:name":"Colonia el Mirador",
    "wof:placetype":"locality",
    "wof:population":19
},
  "geometry": {"coordinates":[-96.89278,20.085],"type":"Point"}
}