{
  "type": "Feature",
  "properties": {
    "gn:admin1_code":"16",
    "gn:admin2_code":"14",
    "gn:asciiname":"Palmita",
    "gn:country_code":"MX",
    "gn:dem":236,
    "gn:feature_class":"P",
    "gn:feature_code":"PPL",
    "gn:name":"Palmita",
    "gn:population":38,
    "gn:timezone":"America/Mexico_City",
    "iso:country":"MX",
    "wof:name":"Palmita",
    "wof:placetype":"locality",
    "wof:population":38
},
  "geometry": {"coordinates":[-103.55361000000001,18.73889],"type":"Point"}
}