{
  "type": "Feature",
  "properties": {
    "gn:admin1_code":"21",
    "gn:admin2_code":"43.0",
    "gn:asciiname":"Totocuahuta (Tamaya)",
    "gn:country_code":"MX",
    "gn:dem":502,
    "gn:feature_class":"P",
    "gn:feature_code":"PPL",
    "gn:name":"Totocuahuta (Tamaya)",
    "gn:population":84,
    "gn:timezone":"America/Mexico_City",
    "iso:country":"MX",
    "wof:name":"Totocuahuta (Tamaya)",
    "wof:placetype":"locality",
    "wof:population":84
},
  "geometry": {"coordinates":[-97.43000000000001,20.035],"type":"Point"}
}