{
  "type": "Feature",
  "properties": {
    "gn:admin1_code":"30",
    "gn:admin2_code":"105.0",
    "gn:asciiname":"El Rubi",
    "gn:country_code":"MX",
    "gn:dem":18,
    "gn:feature_class":"P",
    "gn:feature_code":"PPL",
    "gn:name":"El Rub\u00ed",
    "gn:population":63,
    "gn:timezone":"America/Mexico_City",
    "iso:country":"MX",
    "name:und_x_variant":[
        "El Rub\u00ed"
    ],
    "wof:name":"El Rubi",
    "wof:placetype":"locality",
    "wof:population":63
},
  "geometry": {"coordinates":[-96.19722,18.93028],"type":"Point"}
}