{
  "type": "Feature",
  "properties": {
    "gn:admin1_code":"10",
    "gn:admin2_code":"32",
    "gn:asciiname":"La Herradura",
    "gn:country_code":"MX",
    "gn:dem":1832,
    "gn:feature_class":"P",
    "gn:feature_code":"PPL",
    "gn:name":"La Herradura",
    "gn:population":11,
    "gn:timezone":"America/Monterrey",
    "iso:country":"MX",
    "wof:name":"La Herradura",
    "wof:placetype":"locality",
    "wof:population":11
},
  "geometry": {"coordinates":[-105.51035,25.11527],"type":"Point"}
}