{
  "type": "Feature",
  "properties": {
    "gn:admin1_code":"14",
    "gn:admin2_code":"65.0",
    "gn:asciiname":"El Fortin",
    "gn:country_code":"MX",
    "gn:dem":690,
    "gn:feature_class":"P",
    "gn:feature_code":"PPL",
    "gn:name":"El Fort\u00edn",
    "gn:population":9,
    "gn:timezone":"America/Mexico_City",
    "iso:country":"MX",
    "name:und_x_variant":[
        "El Fort\u00edn"
    ],
    "wof:name":"El Fortin",
    "wof:placetype":"locality",
    "wof:population":9
},
  "geometry": {"coordinates":[-103.41194,19.14056],"type":"Point"}
}