{
  "type": "Feature",
  "properties": {
    "gn:admin1_code":"5.0",
    "gn:asciiname":"Oriente",
    "gn:country_code":"MX",
    "gn:dem":572,
    "gn:feature_class":"P",
    "gn:feature_code":"PPL",
    "gn:name":"Oriente",
    "gn:population":0,
    "gn:timezone":"America/Mexico_City",
    "iso:country":"MX",
    "name:ast_x_preferred":[
        "Oriente"
    ],
    "name:bre_x_preferred":[
        "Oriente"
    ],
    "name:ceb_x_preferred":[
        "Oriente"
    ],
    "name:deu_x_preferred":[
        "Oriente"
    ],
    "name:epo_x_preferred":[
        "Oriente"
    ],
    "name:fra_x_preferred":[
        "Oriente"
    ],
    "name:ita_x_preferred":[
        "Oriente"
    ],
    "name:nld_x_preferred":[
        "Oriente"
    ],
    "name:por_x_preferred":[
        "Oriente"
    ],
    "name:spa_x_preferred":[
        "Oriente"
    ],
    "name:swe_x_preferred":[
        "Oriente"
    ],
    "wof:name":"Oriente",
    "wof:placetype":"locality"
},
  "geometry": {"coordinates":[-93.66182999999999,16.50165],"type":"Point"}
}