{
  "type": "Feature",
  "properties": {
    "gn:admin1_code":"11.0",
    "gn:admin2_code":"37.0",
    "gn:asciiname":"Medio Sitio",
    "gn:country_code":"MX",
    "gn:dem":1778,
    "gn:feature_class":"P",
    "gn:feature_code":"PPL",
    "gn:name":"Medio Sitio",
    "gn:population":1490,
    "gn:timezone":"America/Mexico_City",
    "iso:country":"MX",
    "name:und_x_variant":[
        "El Medio Sitio"
    ],
    "wof:name":"Medio Sitio",
    "wof:placetype":"locality",
    "wof:population":1490
},
  "geometry": {"coordinates":[-101.35689000000001,20.86948],"type":"Point"}
}