{
  "type": "Feature",
  "properties": {
    "gn:admin1_code":"31",
    "gn:admin2_code":"92.0",
    "gn:asciiname":"Cozamil",
    "gn:cc2":"MX",
    "gn:country_code":"MX",
    "gn:dem":32,
    "gn:feature_class":"P",
    "gn:feature_code":"PPL",
    "gn:name":"Cozamil",
    "gn:population":0,
    "gn:timezone":"America/Merida",
    "iso:country":"MX",
    "name:und_x_variant":[
        "Casamit",
        "Cozamil"
    ],
    "wof:name":"Cozamil",
    "wof:placetype":"locality"
},
  "geometry": {"coordinates":[-88.36667,20.43333],"type":"Point"}
}