{
  "type": "Feature",
  "properties": {
    "gn:admin1_code":"24",
    "gn:admin2_code":"54.0",
    "gn:asciiname":"Pena Blanca",
    "gn:country_code":"MX",
    "gn:dem":597,
    "gn:feature_class":"P",
    "gn:feature_code":"PPL",
    "gn:name":"Pe\u00f1a Blanca",
    "gn:population":742,
    "gn:timezone":"America/Mexico_City",
    "iso:country":"MX",
    "name:und_x_variant":[
        "Pe\u00f1a Blanca"
    ],
    "wof:name":"Pena Blanca",
    "wof:placetype":"locality",
    "wof:population":742
},
  "geometry": {"coordinates":[-98.98139,21.42889],"type":"Point"}
}