{
  "type": "Feature",
  "properties": {
    "gn:admin1_code":"5",
    "gn:admin2_code":"107.0",
    "gn:asciiname":"La Muralla",
    "gn:country_code":"MX",
    "gn:dem":772,
    "gn:feature_class":"P",
    "gn:feature_code":"PPL",
    "gn:name":"La Muralla",
    "gn:population":7,
    "gn:timezone":"America/Mexico_City",
    "iso:country":"MX",
    "wof:name":"La Muralla",
    "wof:placetype":"locality",
    "wof:population":7
},
  "geometry": {"coordinates":[-93.30777999999999,16.07417],"type":"Point"}
}