{
  "type": "Feature",
  "properties": {
    "gn:admin1_code":"26",
    "gn:admin2_code":"69.0",
    "gn:asciiname":"Maicova",
    "gn:country_code":"MX",
    "gn:dem":1545,
    "gn:feature_class":"P",
    "gn:feature_code":"PPL",
    "gn:name":"Maicova",
    "gn:population":0,
    "gn:timezone":"America/Hermosillo",
    "iso:country":"MX",
    "wof:name":"Maicova",
    "wof:placetype":"locality"
},
  "geometry": {"coordinates":[-108.65000000000001,28.38333],"type":"Point"}
}