{
  "type": "Feature",
  "properties": {
    "gn:admin1_code":"7.0",
    "gn:admin2_code":"22.0",
    "gn:asciiname":"Carlona",
    "gn:country_code":"MX",
    "gn:dem":322,
    "gn:feature_class":"P",
    "gn:feature_code":"PPL",
    "gn:name":"Carlona",
    "gn:population":0,
    "gn:timezone":"America/Monterrey",
    "iso:country":"MX",
    "name:spa_x_preferred":[
        "Carlona"
    ],
    "wof:name":"Carlona",
    "wof:placetype":"locality"
},
  "geometry": {"coordinates":[-100.78106,28.48529000000001],"type":"Point"}
}