{
  "type": "Feature",
  "properties": {
    "gn:admin1_code":"20",
    "gn:admin2_code":"242.0",
    "gn:asciiname":"Piedra Azul",
    "gn:country_code":"MX",
    "gn:dem":2297,
    "gn:feature_class":"P",
    "gn:feature_code":"PPL",
    "gn:name":"Piedra Azul",
    "gn:population":0,
    "gn:timezone":"America/Mexico_City",
    "iso:country":"MX",
    "name:spa_x_preferred":[
        "Piedra Azul"
    ],
    "wof:name":"Piedra Azul",
    "wof:placetype":"locality"
},
  "geometry": {"coordinates":[-98.18608999999999,17.38931],"type":"Point"}
}