{
  "type": "Feature",
  "properties": {
    "gn:admin1_code":"11.0",
    "gn:admin2_code":"34.0",
    "gn:asciiname":"Milpas Coloradas",
    "gn:country_code":"MX",
    "gn:dem":2452,
    "gn:feature_class":"P",
    "gn:feature_code":"PPL",
    "gn:name":"Milpas Coloradas",
    "gn:population":0,
    "gn:timezone":"America/Mexico_City",
    "iso:country":"MX",
    "name:spa_x_preferred":[
        "Milpas Coloradas"
    ],
    "wof:name":"Milpas Coloradas",
    "wof:placetype":"locality"
},
  "geometry": {"coordinates":[-100.03100999999999,21.196],"type":"Point"}
}