{
  "type": "Feature",
  "properties": {
    "gn:admin1_code":"6",
    "gn:admin2_code":"65.0",
    "gn:asciiname":"Arroyo Hondo",
    "gn:country_code":"MX",
    "gn:dem":1600,
    "gn:feature_class":"P",
    "gn:feature_code":"PPL",
    "gn:name":"Arroyo Hondo",
    "gn:population":7,
    "gn:timezone":"America/Chihuahua",
    "iso:country":"MX",
    "wof:name":"Arroyo Hondo",
    "wof:placetype":"locality",
    "wof:population":7
},
  "geometry": {"coordinates":[-107.76685999999999,27.36715],"type":"Point"}
}