{
  "type": "Feature",
  "properties": {
    "gn:admin1_code":"10",
    "gn:admin2_code":"34.0",
    "gn:asciiname":"Santa Catarina",
    "gn:country_code":"MX",
    "gn:dem":1266,
    "gn:feature_class":"P",
    "gn:feature_code":"PPL",
    "gn:name":"Santa Catarina",
    "gn:population":0,
    "gn:timezone":"America/Monterrey",
    "iso:country":"MX",
    "wof:name":"Santa Catarina",
    "wof:placetype":"locality"
},
  "geometry": {"coordinates":[-106.38367,24.51638],"type":"Point"}
}