{
  "type": "Feature",
  "properties": {
    "gn:admin1_code":"5",
    "gn:admin2_code":"94.0",
    "gn:asciiname":"Galilea",
    "gn:country_code":"MX",
    "gn:dem":2288,
    "gn:feature_class":"P",
    "gn:feature_code":"PPL",
    "gn:name":"Galilea",
    "gn:population":569,
    "gn:timezone":"America/Mexico_City",
    "iso:country":"MX",
    "wof:name":"Galilea",
    "wof:placetype":"locality",
    "wof:population":569
},
  "geometry": {"coordinates":[-92.51000000000001,16.61],"type":"Point"}
}