{
  "type": "Feature",
  "properties": {
    "gn:admin1_code":"32",
    "gn:admin2_code":"38.0",
    "gn:asciiname":"Las Coloradas",
    "gn:country_code":"MX",
    "gn:dem":2254,
    "gn:feature_class":"P",
    "gn:feature_code":"PPL",
    "gn:name":"Las Coloradas",
    "gn:population":6,
    "gn:timezone":"America/Mexico_City",
    "iso:country":"MX",
    "name:ceb_x_preferred":[
        "Las Coloradas"
    ],
    "name:swe_x_preferred":[
        "Las Coloradas"
    ],
    "wof:name":"Las Coloradas",
    "wof:placetype":"locality",
    "wof:population":6
},
  "geometry": {"coordinates":[-101.57722,22.40556],"type":"Point"}
}