{
  "type": "Feature",
  "properties": {
    "gn:admin1_code":"26",
    "gn:admin2_code":"66.0",
    "gn:asciiname":"Santa Rosa",
    "gn:cc2":"MX",
    "gn:country_code":"MX",
    "gn:dem":358,
    "gn:feature_class":"P",
    "gn:feature_code":"PPL",
    "gn:name":"Santa Rosa",
    "gn:population":0,
    "gn:timezone":"America/Hermosillo",
    "iso:country":"MX",
    "name:und_x_variant":[
        "Rancho Santa Rosa",
        "Santa Rosa"
    ],
    "wof:name":"Santa Rosa",
    "wof:placetype":"locality"
},
  "geometry": {"coordinates":[-110.51667,29.36667000000001],"type":"Point"}
}