{
  "type": "Feature",
  "properties": {
    "gn:admin1_code":"19.0",
    "gn:admin2_code":"13.0",
    "gn:asciiname":"El Ebano",
    "gn:country_code":"MX",
    "gn:dem":133,
    "gn:feature_class":"P",
    "gn:feature_code":"PPL",
    "gn:name":"El \u00c9bano",
    "gn:population":0,
    "gn:timezone":"America/Monterrey",
    "iso:country":"MX",
    "name:spa_x_preferred":[
        "El \u00c9bano"
    ],
    "wof:name":"El Ebano",
    "wof:placetype":"locality"
},
  "geometry": {"coordinates":[-99.24257,25.77528],"type":"Point"}
}