{
  "type": "Feature",
  "properties": {
    "gn:admin1_code":"22.0",
    "gn:admin2_code":"16.0",
    "gn:asciiname":"Laguna de Vaquerias",
    "gn:country_code":"MX",
    "gn:dem":2201,
    "gn:feature_class":"P",
    "gn:feature_code":"PPL",
    "gn:name":"Laguna de Vaquer\u00edas",
    "gn:population":0,
    "gn:timezone":"America/Mexico_City",
    "iso:country":"MX",
    "name:spa_x_preferred":[
        "Laguna de Vaquer\u00edas"
    ],
    "wof:name":"Laguna de Vaquerias",
    "wof:placetype":"locality"
},
  "geometry": {"coordinates":[-100.13515,20.35392],"type":"Point"}
}