{
  "type": "Feature",
  "properties": {
    "gn:admin1_code":"7",
    "gn:admin2_code":"33.0",
    "gn:asciiname":"Medio Lote",
    "gn:country_code":"MX",
    "gn:dem":1105,
    "gn:feature_class":"P",
    "gn:feature_code":"PPL",
    "gn:name":"Medio Lote",
    "gn:population":0,
    "gn:timezone":"America/Monterrey",
    "iso:country":"MX",
    "name:spa_x_preferred":[
        "Medio Lote"
    ],
    "wof:name":"Medio Lote",
    "wof:placetype":"locality"
},
  "geometry": {"coordinates":[-103.01424,25.73483],"type":"Point"}
}