{
  "type": "Feature",
  "properties": {
    "gn:admin1_code":"14",
    "gn:admin2_code":"30",
    "gn:asciiname":"La Antena",
    "gn:country_code":"MX",
    "gn:dem":1578,
    "gn:feature_class":"P",
    "gn:feature_code":"PPL",
    "gn:name":"La Antena",
    "gn:population":47,
    "gn:timezone":"America/Mexico_City",
    "iso:country":"MX",
    "name:deu_x_preferred":[
        "La Antena"
    ],
    "name:fra_x_preferred":[
        "Telepolis"
    ],
    "wof:name":"La Antena",
    "wof:placetype":"locality",
    "wof:population":47
},
  "geometry": {"coordinates":[-103.18805999999999,20.31667],"type":"Point"}
}