{
  "type": "Feature",
  "properties": {
    "gn:admin1_code":"14.0",
    "gn:admin2_code":"36.0",
    "gn:asciiname":"Los Zapotes",
    "gn:country_code":"MX",
    "gn:dem":1530,
    "gn:feature_class":"P",
    "gn:feature_code":"PPL",
    "gn:name":"Los Zapotes",
    "gn:population":0,
    "gn:timezone":"America/Mexico_City",
    "iso:country":"MX",
    "name:spa_x_preferred":[
        "Los Zapotes"
    ],
    "wof:name":"Los Zapotes",
    "wof:placetype":"locality"
},
  "geometry": {"coordinates":[-104.17007,20.67222000000001],"type":"Point"}
}