{
  "type": "Feature",
  "properties": {
    "gn:admin1_code":"28.0",
    "gn:admin2_code":"8.0",
    "gn:asciiname":"Cinco de Mayo",
    "gn:country_code":"MX",
    "gn:dem":460,
    "gn:feature_class":"P",
    "gn:feature_code":"PPL",
    "gn:name":"Cinco de Mayo",
    "gn:population":1,
    "gn:timezone":"America/Monterrey",
    "iso:country":"MX",
    "name:spa_x_preferred":[
        "Cinco de Mayo"
    ],
    "wof:name":"Cinco de Mayo",
    "wof:placetype":"locality",
    "wof:population":1
},
  "geometry": {"coordinates":[-98.61333,23.30639],"type":"Point"}
}