{
  "type": "Feature",
  "properties": {
    "gn:admin1_code":"28.0",
    "gn:admin2_code":"8.0",
    "gn:asciiname":"Cinco de Mayo",
    "gn:country_code":"MX",
    "gn:dem":460,
    "gn:feature_class":"P",
    "gn:feature_code":"PPL",
    "gn:name":"Cinco de Mayo",
    "gn:population":1,
    "gn:timezone":"America/Monterrey",
    "iso:country":"MX",
    "name:ara_x_preferred":[
        "\u0633\u064a\u0646\u0643\u0648 \u062f\u064a \u0645\u0627\u064a\u0648"
    ],
    "name:bul_x_preferred":[
        "\u0421\u0438\u043d\u043a\u043e \u0434\u0435 \u041c\u0430\u0439\u043e"
    ],
    "name:fas_x_preferred":[
        "\u0633\u06cc\u0646\u06a9\u0648 \u062f\u06cc \u0645\u0627\u06cc\u0648"
    ],
    "name:heb_x_preferred":[
        "\u05e1\u05d9\u05e0\u05e7\u05d5 \u05d3\u05d4 \u05de\u05d0\u05d9\u05d5"
    ],
    "name:hye_x_preferred":[
        "\u054d\u056b\u0576\u056f\u0578 \u0564\u0565 \u0544\u0561\u0575\u0578"
    ],
    "name:jpn_x_preferred":[
        "\u30b7\u30f3\u30b3\u30fb\u30c7\u30fb\u30de\u30e8"
    ],
    "name:kat_x_preferred":[
        "\u10e1\u10d8\u10dc\u10d9\u10dd-\u10d3\u10d4-\u10db\u10d0\u10d8\u10dd"
    ],
    "name:kor_x_preferred":[
        "\uc2f1\ucf54 \ub370 \ub9c8\uc694"
    ],
    "name:mar_x_preferred":[
        "\u0938\u093f\u0902\u0915\u094b \u0926\u0947 \u092e\u093e\u092f\u094b"
    ],
    "name:rus_x_preferred":[
        "\u0421\u0438\u043d\u043a\u043e \u0434\u0435 \u041c\u0430\u0439\u043e"
    ],
    "name:spa_x_preferred":[
        "Cinco de Mayo"
    ],
    "name:tam_x_preferred":[
        "\u0b9a\u0bbf\u0b99\u0bcd\u0b95\u0bcd\u0b95\u0bcb \u0b9f\u0bc7 \u0bae\u0bbe\u0baf\u0bcb"
    ],
    "name:zho_x_preferred":[
        "\u4e94\u6708\u4e94\u65e5\u8282"
    ],
    "wof:name":"Cinco de Mayo",
    "wof:placetype":"locality",
    "wof:population":1
},
  "geometry": {"coordinates":[-98.61333,23.30639],"type":"Point"}
}