{
  "type": "Feature",
  "properties": {
    "gn:admin1_code":"16.0",
    "gn:admin2_code":"110.0",
    "gn:asciiname":"Ojo de Agua de Bucio",
    "gn:country_code":"MX",
    "gn:dem":2558,
    "gn:feature_class":"P",
    "gn:feature_code":"PPL",
    "gn:name":"Ojo de Agua de Bucio",
    "gn:population":0,
    "gn:timezone":"America/Mexico_City",
    "iso:country":"MX",
    "name:spa_x_preferred":[
        "Ojo de Agua de Bucio"
    ],
    "wof:name":"Ojo de Agua de Bucio",
    "wof:placetype":"locality"
},
  "geometry": {"coordinates":[-100.72815,19.78048],"type":"Point"}
}