{
  "type": "Feature",
  "properties": {
    "gn:admin1_code":"30",
    "gn:admin2_code":"119.0",
    "gn:asciiname":"Zacatixpa",
    "gn:country_code":"MX",
    "gn:dem":20,
    "gn:feature_class":"P",
    "gn:feature_code":"PPL",
    "gn:name":"Zacatixpa",
    "gn:population":0,
    "gn:timezone":"America/Mexico_City",
    "iso:country":"MX",
    "name:spa_x_preferred":[
        "Zacatixpa"
    ],
    "wof:name":"Zacatixpa",
    "wof:placetype":"locality"
},
  "geometry": {"coordinates":[-96.02046,18.15596],"type":"Point"}
}