{
  "type": "Feature",
  "properties": {
    "gn:admin1_code":"32.0",
    "gn:admin2_code":"55.0",
    "gn:asciiname":"Saltito",
    "gn:country_code":"MX",
    "gn:dem":1835,
    "gn:feature_class":"P",
    "gn:feature_code":"PPL",
    "gn:name":"Saltito",
    "gn:population":0,
    "gn:timezone":"America/Mexico_City",
    "iso:country":"MX",
    "name:spa_x_preferred":[
        "Saltito"
    ],
    "name:spa_x_variant":[
        "El Saltito"
    ],
    "wof:name":"Saltito",
    "wof:placetype":"locality"
},
  "geometry": {"coordinates":[-102.80642,22.12395],"type":"Point"}
}