{
  "type": "Feature",
  "properties": {
    "gn:admin1_code":"22",
    "gn:admin2_code":"14.0",
    "gn:asciiname":"Loma del Chino",
    "gn:country_code":"MX",
    "gn:dem":2125,
    "gn:feature_class":"P",
    "gn:feature_code":"PPL",
    "gn:name":"Loma del Chino",
    "gn:population":423,
    "gn:timezone":"America/Mexico_City",
    "iso:country":"MX",
    "wof:name":"Loma del Chino",
    "wof:placetype":"locality",
    "wof:population":423
},
  "geometry": {"coordinates":[-100.47638999999999,20.84917],"type":"Point"}
}