{
  "type": "Feature",
  "properties": {
    "gn:admin1_code":"7",
    "gn:admin2_code":"24.0",
    "gn:asciiname":"Rancho Ceres",
    "gn:country_code":"MX",
    "gn:dem":1088,
    "gn:feature_class":"P",
    "gn:feature_code":"PPL",
    "gn:name":"Rancho Ceres",
    "gn:population":0,
    "gn:timezone":"America/Monterrey",
    "iso:country":"MX",
    "wof:name":"Rancho Ceres",
    "wof:placetype":"locality"
},
  "geometry": {"coordinates":[-102.51667,25.73333],"type":"Point"}
}