{
  "type": "Feature",
  "properties": {
    "gn:admin1_code":"20",
    "gn:admin2_code":"364.0",
    "gn:asciiname":"Junta de los Rios",
    "gn:country_code":"MX",
    "gn:dem":567,
    "gn:feature_class":"P",
    "gn:feature_code":"PPL",
    "gn:name":"Junta de los R\u00edos",
    "gn:population":193,
    "gn:timezone":"America/Mexico_City",
    "iso:country":"MX",
    "name:und_x_variant":[
        "Junta de los R\u00edos"
    ],
    "wof:name":"Junta de los Rios",
    "wof:placetype":"locality",
    "wof:population":193
},
  "geometry": {"coordinates":[-97.29667000000001,16.11333],"type":"Point"}
}