{
  "type": "Feature",
  "properties": {
    "gn:admin1_code":"30",
    "gn:admin2_code":"54",
    "gn:asciiname":"Veinte de Noviembre [Agricola]",
    "gn:country_code":"MX",
    "gn:dem":13,
    "gn:feature_class":"P",
    "gn:feature_code":"PPL",
    "gn:name":"Veinte de Noviembre [Agr\u00edcola]",
    "gn:population":44,
    "gn:timezone":"America/Mexico_City",
    "iso:country":"MX",
    "name:und_x_variant":[
        "Veinte de Noviembre [Agr\u00edcola]"
    ],
    "wof:name":"Veinte de Noviembre [Agricola]",
    "wof:placetype":"locality",
    "wof:population":44
},
  "geometry": {"coordinates":[-95.83833,18.32972],"type":"Point"}
}