{
  "type": "Feature",
  "properties": {
    "gn:admin1_code":"28",
    "gn:admin2_code":"22.0",
    "gn:asciiname":"La Yerbajosa",
    "gn:cc2":"MX",
    "gn:country_code":"MX",
    "gn:dem":4,
    "gn:feature_class":"P",
    "gn:feature_code":"PPL",
    "gn:name":"La Yerbajosa",
    "gn:population":2,
    "gn:timezone":"America/Matamoros",
    "iso:country":"MX",
    "name:und_x_variant":[
        "Yerbajosa",
        "La Yerbajosa"
    ],
    "wof:name":"La Yerbajosa",
    "wof:placetype":"locality",
    "wof:population":2
},
  "geometry": {"coordinates":[-97.38111000000001,25.78083],"type":"Point"}
}