{
  "type": "Feature",
  "properties": {
    "gn:admin1_code":"15",
    "gn:admin2_code":"97.0",
    "gn:asciiname":"Gavia Chica",
    "gn:country_code":"MX",
    "gn:dem":2398,
    "gn:feature_class":"P",
    "gn:feature_code":"PPL",
    "gn:name":"Gavia Chica",
    "gn:population":0,
    "gn:timezone":"America/Mexico_City",
    "iso:country":"MX",
    "name:und_x_variant":[
        "Rinc\u00f3n",
        "Gavia Chica",
        "El Rinc\u00f3n"
    ],
    "wof:name":"Gavia Chica",
    "wof:placetype":"locality"
},
  "geometry": {"coordinates":[-99.95869999999999,18.95318],"type":"Point"}
}