{
  "type": "Feature",
  "properties": {
    "gn:admin1_code":"24.0",
    "gn:admin2_code":"42.0",
    "gn:asciiname":"El Alto",
    "gn:country_code":"MX",
    "gn:dem":63,
    "gn:feature_class":"P",
    "gn:feature_code":"PPL",
    "gn:name":"El Alto",
    "gn:population":8,
    "gn:timezone":"America/Mexico_City",
    "iso:country":"MX",
    "name:spa_x_preferred":[
        "El Alto"
    ],
    "wof:name":"El Alto",
    "wof:placetype":"locality",
    "wof:population":8
},
  "geometry": {"coordinates":[-98.66619,21.62778],"type":"Point"}
}