{
  "type": "Feature",
  "properties": {
    "gn:admin1_code":"12",
    "gn:admin2_code":"63.0",
    "gn:asciiname":"Llano Zopilote",
    "gn:country_code":"MX",
    "gn:dem":2126,
    "gn:feature_class":"P",
    "gn:feature_code":"PPL",
    "gn:name":"Llano Zopilote",
    "gn:population":6,
    "gn:timezone":"America/Mexico_City",
    "iso:country":"MX",
    "wof:name":"Llano Zopilote",
    "wof:placetype":"locality",
    "wof:population":6
},
  "geometry": {"coordinates":[-98.73857,17.28899],"type":"Point"}
}