{
  "type": "Feature",
  "properties": {
    "gn:admin1_code":"13",
    "gn:admin2_code":"7.0",
    "gn:asciiname":"La Defensa",
    "gn:country_code":"MX",
    "gn:dem":2731,
    "gn:feature_class":"P",
    "gn:feature_code":"PPL",
    "gn:name":"La Defensa",
    "gn:population":0,
    "gn:timezone":"America/Mexico_City",
    "iso:country":"MX",
    "name:spa_x_preferred":[
        "La Defensa"
    ],
    "wof:name":"La Defensa",
    "wof:placetype":"locality"
},
  "geometry": {"coordinates":[-98.29158,19.77426],"type":"Point"}
}