{
  "type": "Feature",
  "properties": {
    "gn:admin1_code":"26.0",
    "gn:admin2_code":"6.0",
    "gn:asciiname":"El Sombrero",
    "gn:country_code":"MX",
    "gn:dem":1356,
    "gn:feature_class":"P",
    "gn:feature_code":"PPL",
    "gn:name":"El Sombrero",
    "gn:population":0,
    "gn:timezone":"America/Hermosillo",
    "iso:country":"MX",
    "name:spa_x_preferred":[
        "El Sombrero"
    ],
    "wof:name":"El Sombrero",
    "wof:placetype":"locality"
},
  "geometry": {"coordinates":[-110.04722,30.25639],"type":"Point"}
}