{
  "type": "Feature",
  "properties": {
    "gn:admin1_code":"5",
    "gn:admin2_code":"106.0",
    "gn:asciiname":"Rio Jordan",
    "gn:country_code":"MX",
    "gn:dem":616,
    "gn:feature_class":"P",
    "gn:feature_code":"PPL",
    "gn:name":"R\u00edo Jord\u00e1n",
    "gn:population":305,
    "gn:timezone":"America/Mexico_City",
    "iso:country":"MX",
    "name:und_x_variant":[
        "R\u00edo Jord\u00e1n"
    ],
    "wof:name":"Rio Jordan",
    "wof:placetype":"locality",
    "wof:population":305
},
  "geometry": {"coordinates":[-92.59999999999999,16.18389],"type":"Point"}
}