{
  "type": "Feature",
  "properties": {
    "gn:admin1_code":"26.0",
    "gn:admin2_code":"36.0",
    "gn:asciiname":"La Cotena",
    "gn:country_code":"MX",
    "gn:dem":780,
    "gn:feature_class":"P",
    "gn:feature_code":"PPL",
    "gn:name":"La Cote\u00f1a",
    "gn:population":2,
    "gn:timezone":"America/Hermosillo",
    "iso:country":"MX",
    "wof:name":"La Cotena",
    "wof:placetype":"locality",
    "wof:population":2
},
  "geometry": {"coordinates":[-110.92778,30.67833],"type":"Point"}
}