{
  "type": "Feature",
  "properties": {
    "gn:admin1_code":"19.0",
    "gn:admin2_code":"14.0",
    "gn:asciiname":"Guadalupe",
    "gn:cc2":"MX",
    "gn:country_code":"MX",
    "gn:dem":1708,
    "gn:feature_class":"P",
    "gn:feature_code":"PPL",
    "gn:name":"Guadalupe",
    "gn:population":3,
    "gn:timezone":"America/Monterrey",
    "iso:country":"MX",
    "name:und_x_variant":[
        "Guadalupe de Silva"
    ],
    "wof:name":"Guadalupe",
    "wof:placetype":"locality",
    "wof:population":3
},
  "geometry": {"coordinates":[-100.19661000000001,23.68258],"type":"Point"}
}