{
  "type": "Feature",
  "properties": {
    "gn:admin1_code":"32",
    "gn:admin2_code":"26.0",
    "gn:asciiname":"San Rafael (Jose Maria Morelos)",
    "gn:country_code":"MX",
    "gn:dem":2012,
    "gn:feature_class":"P",
    "gn:feature_code":"PPL",
    "gn:name":"San Rafael (Jos\u00e9 Mar\u00eda Morelos)",
    "gn:population":306,
    "gn:timezone":"America/Mexico_City",
    "iso:country":"MX",
    "wof:name":"San Rafael (Jose Maria Morelos)",
    "wof:placetype":"locality",
    "wof:population":306
},
  "geometry": {"coordinates":[-102.11033999999999,24.59127],"type":"Point"}
}