{
  "type": "Feature",
  "properties": {
    "gn:admin1_code":"5",
    "gn:admin2_code":"3",
    "gn:asciiname":"El Almendro",
    "gn:country_code":"MX",
    "gn:dem":21,
    "gn:feature_class":"P",
    "gn:feature_code":"PPL",
    "gn:name":"El Almendro",
    "gn:population":12,
    "gn:timezone":"America/Mexico_City",
    "iso:country":"MX",
    "name:ceb_x_preferred":[
        "El Almendro"
    ],
    "name:fra_x_preferred":[
        "El Almendro"
    ],
    "name:ita_x_preferred":[
        "El Almendro"
    ],
    "name:sco_x_preferred":[
        "El Almendro"
    ],
    "name:spa_x_preferred":[
        "El Almendro"
    ],
    "name:swe_x_preferred":[
        "El Almendro"
    ],
    "name:urd_x_preferred":[
        "\u0627\u06cc\u0644 \u0627\u0644\u0645\u06cc\u0646\u062f\u0631\u0648"
    ],
    "name:vie_x_preferred":[
        "El Almendro"
    ],
    "name:zho_x_preferred":[
        "\u57c3\u723e\u963f\u723e\u9580\u5fb7\u7f85"
    ],
    "wof:name":"El Almendro",
    "wof:placetype":"locality",
    "wof:population":12
},
  "geometry": {"coordinates":[-92.65472,15.23861],"type":"Point"}
}