{
  "type": "Feature",
  "properties": {
    "gn:admin1_code":"5",
    "gn:admin2_code":"3",
    "gn:asciiname":"El Almendro",
    "gn:country_code":"MX",
    "gn:dem":21,
    "gn:feature_class":"P",
    "gn:feature_code":"PPL",
    "gn:name":"El Almendro",
    "gn:population":12,
    "gn:timezone":"America/Mexico_City",
    "iso:country":"MX",
    "wof:name":"El Almendro",
    "wof:placetype":"locality",
    "wof:population":12
},
  "geometry": {"coordinates":[-92.65472,15.23861],"type":"Point"}
}