{
  "type": "Feature",
  "properties": {
    "gn:admin1_code":"25",
    "gn:admin2_code":"13",
    "gn:asciiname":"Los Vasitos",
    "gn:country_code":"MX",
    "gn:dem":505,
    "gn:feature_class":"P",
    "gn:feature_code":"PPL",
    "gn:name":"Los Vasitos",
    "gn:population":49,
    "gn:timezone":"America/Mazatlan",
    "iso:country":"MX",
    "wof:name":"Los Vasitos",
    "wof:placetype":"locality",
    "wof:population":49
},
  "geometry": {"coordinates":[-107.69513000000001,25.72523],"type":"Point"}
}