{
  "type": "Feature",
  "properties": {
    "gn:admin1_code":"6.0",
    "gn:admin2_code":"5.0",
    "gn:asciiname":"El Dos",
    "gn:country_code":"MX",
    "gn:dem":1276,
    "gn:feature_class":"P",
    "gn:feature_code":"PPL",
    "gn:name":"El Dos",
    "gn:population":0,
    "gn:timezone":"America/Chihuahua",
    "iso:country":"MX",
    "name:spa_x_preferred":[
        "El Dos"
    ],
    "wof:name":"El Dos",
    "wof:placetype":"locality"
},
  "geometry": {"coordinates":[-108.00704,31.35742],"type":"Point"}
}