{
  "type": "Feature",
  "properties": {
    "gn:admin1_code":"6",
    "gn:admin2_code":"5.0",
    "gn:asciiname":"Los Moscos (El Texano)",
    "gn:country_code":"MX",
    "gn:dem":1255,
    "gn:feature_class":"P",
    "gn:feature_code":"PPL",
    "gn:name":"Los Moscos (El Texano)",
    "gn:population":1,
    "gn:timezone":"America/Chihuahua",
    "iso:country":"MX",
    "name:und_x_variant":[
        "Rancho Los Moscos",
        "Los Moscos"
    ],
    "wof:name":"Los Moscos (El Texano)",
    "wof:placetype":"locality",
    "wof:population":1
},
  "geometry": {"coordinates":[-108.18770000000001,31.56264],"type":"Point"}
}