{
  "type": "Feature",
  "properties": {
    "gn:admin1_code":"6.0",
    "gn:admin2_code":"12.0",
    "gn:asciiname":"Satehuerachi",
    "gn:country_code":"MX",
    "gn:dem":1866,
    "gn:feature_class":"P",
    "gn:feature_code":"PPL",
    "gn:name":"Satehuerachi",
    "gn:population":0,
    "gn:timezone":"America/Chihuahua",
    "iso:country":"MX",
    "name:spa_x_preferred":[
        "Satehuerachi"
    ],
    "wof:name":"Satehuerachi",
    "wof:placetype":"locality"
},
  "geometry": {"coordinates":[-107.10504,27.64795],"type":"Point"}
}