{
  "type": "Feature",
  "properties": {
    "gn:admin1_code":"14.0",
    "gn:admin2_code":"115.0",
    "gn:asciiname":"El Fortin",
    "gn:country_code":"MX",
    "gn:dem":1244,
    "gn:feature_class":"P",
    "gn:feature_code":"PPL",
    "gn:name":"El Fort\u00edn",
    "gn:population":0,
    "gn:timezone":"America/Mexico_City",
    "iso:country":"MX",
    "name:spa_x_preferred":[
        "El Fort\u00edn"
    ],
    "wof:name":"El Fortin",
    "wof:placetype":"locality"
},
  "geometry": {"coordinates":[-103.75397,22.04],"type":"Point"}
}