{
  "type": "Feature",
  "properties": {
    "gn:admin1_code":"30",
    "gn:admin2_code":"11.0",
    "gn:asciiname":"Buenpais",
    "gn:country_code":"MX",
    "gn:dem":11,
    "gn:feature_class":"P",
    "gn:feature_code":"PPL",
    "gn:name":"Buenpa\u00eds",
    "gn:population":421,
    "gn:timezone":"America/Mexico_City",
    "iso:country":"MX",
    "name:spa_x_preferred":[
        "Buenpa\u00eds"
    ],
    "wof:name":"Buenpais",
    "wof:placetype":"locality",
    "wof:population":421
},
  "geometry": {"coordinates":[-95.85026000000001,18.82156],"type":"Point"}
}