{
  "type": "Feature",
  "properties": {
    "gn:admin1_code":"2.0",
    "gn:admin2_code":"5.0",
    "gn:asciiname":"El Campito",
    "gn:country_code":"MX",
    "gn:dem":8,
    "gn:feature_class":"P",
    "gn:feature_code":"PPL",
    "gn:name":"El Campito",
    "gn:population":232,
    "gn:timezone":"America/Tijuana",
    "iso:country":"MX",
    "name:spa_x_preferred":[
        "El Campito"
    ],
    "wof:name":"El Campito",
    "wof:placetype":"locality",
    "wof:population":232
},
  "geometry": {"coordinates":[-116.90917,32.17972],"type":"Point"}
}