{
  "type": "Feature",
  "properties": {
    "gn:admin1_code":"10",
    "gn:admin2_code":"14.0",
    "gn:asciiname":"Campamento Canoas",
    "gn:country_code":"MX",
    "gn:dem":2721,
    "gn:feature_class":"P",
    "gn:feature_code":"PPL",
    "gn:name":"Campamento Canoas",
    "gn:population":262,
    "gn:timezone":"America/Monterrey",
    "iso:country":"MX",
    "wof:name":"Campamento Canoas",
    "wof:placetype":"locality",
    "wof:population":262
},
  "geometry": {"coordinates":[-104.29416999999999,22.62056],"type":"Point"}
}