{
  "type": "Feature",
  "properties": {
    "gn:admin1_code":"12",
    "gn:admin2_code":"74.0",
    "gn:asciiname":"Azoacapa",
    "gn:country_code":"MX",
    "gn:dem":1700,
    "gn:feature_class":"P",
    "gn:feature_code":"PPL",
    "gn:name":"Azoacapa",
    "gn:population":328,
    "gn:timezone":"America/Mexico_City",
    "iso:country":"MX",
    "wof:name":"Azoacapa",
    "wof:placetype":"locality",
    "wof:population":328
},
  "geometry": {"coordinates":[-99.23900999999999,17.70654],"type":"Point"}
}