{
  "type": "Feature",
  "properties": {
    "gn:admin1_code":"10.0",
    "gn:admin2_code":"7.0",
    "gn:asciiname":"Aquiles Serdan",
    "gn:country_code":"MX",
    "gn:dem":1122,
    "gn:feature_class":"P",
    "gn:feature_code":"PPL",
    "gn:name":"Aquiles Serd\u00e1n",
    "gn:population":274,
    "gn:timezone":"America/Monterrey",
    "iso:country":"MX",
    "name:spa_x_preferred":[
        "Aquiles Serd\u00e1n"
    ],
    "wof:name":"Aquiles Serdan",
    "wof:placetype":"locality",
    "wof:population":274
},
  "geometry": {"coordinates":[-103.4359,25.64266],"type":"Point"}
}