{
  "type": "Feature",
  "properties": {
    "gn:admin1_code":"20.0",
    "gn:admin2_code":"137.0",
    "gn:asciiname":"El Costoche",
    "gn:country_code":"MX",
    "gn:dem":2087,
    "gn:feature_class":"P",
    "gn:feature_code":"PPL",
    "gn:name":"El Costoche",
    "gn:population":0,
    "gn:timezone":"America/Mexico_City",
    "iso:country":"MX",
    "name:spa_x_preferred":[
        "El Costoche"
    ],
    "wof:name":"El Costoche",
    "wof:placetype":"locality"
},
  "geometry": {"coordinates":[-97.32794,16.85501],"type":"Point"}
}