{
  "type": "Feature",
  "properties": {
    "gn:admin1_code":"12.0",
    "gn:admin2_code":"57.0",
    "gn:asciiname":"La Vinata",
    "gn:country_code":"MX",
    "gn:dem":11,
    "gn:feature_class":"P",
    "gn:feature_code":"PPL",
    "gn:name":"La Vinata",
    "gn:population":95,
    "gn:timezone":"America/Mexico_City",
    "iso:country":"MX",
    "name:spa_x_preferred":[
        "La Vinata"
    ],
    "wof:name":"La Vinata",
    "wof:placetype":"locality",
    "wof:population":95
},
  "geometry": {"coordinates":[-100.67819,17.14766],"type":"Point"}
}