{
  "type": "Feature",
  "properties": {
    "gn:admin1_code":"16.0",
    "gn:admin2_code":"67.0",
    "gn:asciiname":"Los Fresnos",
    "gn:country_code":"MX",
    "gn:dem":1877,
    "gn:feature_class":"P",
    "gn:feature_code":"PPL",
    "gn:name":"Los Fresnos",
    "gn:population":0,
    "gn:timezone":"America/Mexico_City",
    "iso:country":"MX",
    "name:und_x_variant":[
        "Fresno de la Reforma",
        "Los Fresnos"
    ],
    "wof:name":"Los Fresnos",
    "wof:placetype":"locality"
},
  "geometry": {"coordinates":[-101.94298000000001,20.04069],"type":"Point"}
}