{
  "type": "Feature",
  "properties": {
    "gn:admin1_code":"22",
    "gn:admin2_code":"16.0",
    "gn:asciiname":"El Porvenir [Residencial]",
    "gn:country_code":"MX",
    "gn:dem":1911,
    "gn:feature_class":"P",
    "gn:feature_code":"PPL",
    "gn:name":"El Porvenir [Residencial]",
    "gn:population":70,
    "gn:timezone":"America/Mexico_City",
    "iso:country":"MX",
    "wof:name":"El Porvenir [Residencial]",
    "wof:placetype":"locality",
    "wof:population":70
},
  "geometry": {"coordinates":[-100.05472,20.43056],"type":"Point"}
}