{
  "type": "Feature",
  "properties": {
    "gn:admin1_code":"7",
    "gn:admin2_code":"33.0",
    "gn:asciiname":"Las Margaritas de Santa Maria",
    "gn:country_code":"MX",
    "gn:dem":1096,
    "gn:feature_class":"P",
    "gn:feature_code":"PPL",
    "gn:name":"Las Margaritas de Santa Mar\u00eda",
    "gn:population":0,
    "gn:timezone":"America/Monterrey",
    "iso:country":"MX",
    "name:spa_x_preferred":[
        "Las Margaritas de Santa Mar\u00eda"
    ],
    "wof:name":"Las Margaritas de Santa Maria",
    "wof:placetype":"locality"
},
  "geometry": {"coordinates":[-102.98417000000001,25.80562],"type":"Point"}
}