{
  "type": "Feature",
  "properties": {
    "gn:admin1_code":"28",
    "gn:admin2_code":"32.0",
    "gn:asciiname":"San Jacinto",
    "gn:country_code":"MX",
    "gn:dem":74,
    "gn:feature_class":"P",
    "gn:feature_code":"PPL",
    "gn:name":"San Jacinto",
    "gn:population":0,
    "gn:timezone":"America/Matamoros",
    "iso:country":"MX",
    "name:spa_x_preferred":[
        "San Jacinto"
    ],
    "name:und_x_variant":[
        "Granja San Jacinto"
    ],
    "wof:name":"San Jacinto",
    "wof:placetype":"locality"
},
  "geometry": {"coordinates":[-98.54891000000001,26.01353],"type":"Point"}
}