{
  "type": "Feature",
  "properties": {
    "gn:admin1_code":"6",
    "gn:admin2_code":"23.0",
    "gn:asciiname":"Ojo Caliente",
    "gn:country_code":"MX",
    "gn:dem":1391,
    "gn:feature_class":"P",
    "gn:feature_code":"PPL",
    "gn:name":"Ojo Caliente",
    "gn:population":0,
    "gn:timezone":"America/Chihuahua",
    "iso:country":"MX",
    "name:und_x_variant":[
        "Rancho Ojo Caliente",
        "Ojo Caliente"
    ],
    "wof:name":"Ojo Caliente",
    "wof:placetype":"locality"
},
  "geometry": {"coordinates":[-107.61391,30.2513],"type":"Point"}
}