{
  "type": "Feature",
  "properties": {
    "gn:admin1_code":"30",
    "gn:admin2_code":"94.0",
    "gn:asciiname":"Miraflores",
    "gn:country_code":"MX",
    "gn:dem":43,
    "gn:feature_class":"P",
    "gn:feature_code":"PPL",
    "gn:name":"Miraflores",
    "gn:population":0,
    "gn:timezone":"America/Mexico_City",
    "iso:country":"MX",
    "name:spa_x_preferred":[
        "Miraflores"
    ],
    "wof:name":"Miraflores",
    "wof:placetype":"locality"
},
  "geometry": {"coordinates":[-95.50955,18.14279],"type":"Point"}
}