{
  "type": "Feature",
  "properties": {
    "gn:admin1_code":"21.0",
    "gn:admin2_code":"154.0",
    "gn:asciiname":"El Cuiji",
    "gn:country_code":"MX",
    "gn:dem":1993,
    "gn:feature_class":"P",
    "gn:feature_code":"PPL",
    "gn:name":"El Cuiji",
    "gn:population":0,
    "gn:timezone":"America/Mexico_City",
    "iso:country":"MX",
    "name:spa_x_preferred":[
        "El Cuiji"
    ],
    "wof:name":"El Cuiji",
    "wof:placetype":"locality"
},
  "geometry": {"coordinates":[-97.756,18.85873],"type":"Point"}
}