{
  "type": "Feature",
  "properties": {
    "gn:admin1_code":"6",
    "gn:admin2_code":"46",
    "gn:asciiname":"Arroyo el Frijol (El Frijolar)",
    "gn:country_code":"MX",
    "gn:dem":1427,
    "gn:feature_class":"P",
    "gn:feature_code":"PPL",
    "gn:name":"Arroyo el Frijol (El Frijolar)",
    "gn:population":11,
    "gn:timezone":"America/Mazatlan",
    "iso:country":"MX",
    "wof:name":"Arroyo el Frijol (El Frijolar)",
    "wof:placetype":"locality",
    "wof:population":11
},
  "geometry": {"coordinates":[-107.97127999999999,26.63021],"type":"Point"}
}