{
  "type": "Feature",
  "properties": {
    "gn:admin1_code":"6",
    "gn:admin2_code":"29.0",
    "gn:asciiname":"La Soledad",
    "gn:country_code":"MX",
    "gn:dem":1278,
    "gn:feature_class":"P",
    "gn:feature_code":"PPL",
    "gn:name":"La Soledad",
    "gn:population":208,
    "gn:timezone":"America/Chihuahua",
    "iso:country":"MX",
    "wof:name":"La Soledad",
    "wof:placetype":"locality",
    "wof:population":208
},
  "geometry": {"coordinates":[-107.21861,26.14361],"type":"Point"}
}