{
  "type": "Feature",
  "properties": {
    "gn:admin1_code":"20",
    "gn:admin2_code":"426.0",
    "gn:asciiname":"Duraznal",
    "gn:country_code":"MX",
    "gn:dem":2288,
    "gn:feature_class":"P",
    "gn:feature_code":"PPL",
    "gn:name":"Duraznal",
    "gn:population":539,
    "gn:timezone":"America/Mexico_City",
    "iso:country":"MX",
    "wof:name":"Duraznal",
    "wof:placetype":"locality",
    "wof:population":539
},
  "geometry": {"coordinates":[-96.96556,17.06667],"type":"Point"}
}