{
  "type": "Feature",
  "properties": {
    "gn:admin1_code":"27",
    "gn:admin2_code":"8.0",
    "gn:asciiname":"Tierra Nueva",
    "gn:country_code":"MX",
    "gn:dem":55,
    "gn:feature_class":"P",
    "gn:feature_code":"PPL",
    "gn:name":"Tierra Nueva",
    "gn:population":0,
    "gn:timezone":"America/Mexico_City",
    "iso:country":"MX",
    "name:spa_x_preferred":[
        "Tierra Nueva Tercera Secci\u00f3n"
    ],
    "name:spa_x_variant":[
        "Tierra Nueva",
        "Tercera Secci\u00f3n"
    ],
    "wof:name":"Tierra Nueva",
    "wof:placetype":"locality"
},
  "geometry": {"coordinates":[-93.47562000000001,17.70002999999999],"type":"Point"}
}