{
  "type": "Feature",
  "properties": {
    "gn:admin1_code":"7",
    "gn:admin2_code":"22.0",
    "gn:asciiname":"El Fenix",
    "gn:country_code":"MX",
    "gn:dem":289,
    "gn:feature_class":"P",
    "gn:feature_code":"PPL",
    "gn:name":"El F\u00e9nix",
    "gn:population":0,
    "gn:timezone":"America/Monterrey",
    "iso:country":"MX",
    "name:spa_x_preferred":[
        "El F\u00e9nix"
    ],
    "wof:name":"El Fenix",
    "wof:placetype":"locality"
},
  "geometry": {"coordinates":[-100.64303,28.53265],"type":"Point"}
}