{
  "type": "Feature",
  "properties": {
    "gn:admin1_code":"13",
    "gn:admin2_code":"75",
    "gn:asciiname":"Lomas de San Miguel",
    "gn:country_code":"MX",
    "gn:dem":2355,
    "gn:feature_class":"P",
    "gn:feature_code":"PPL",
    "gn:name":"Lomas de San Miguel",
    "gn:population":22,
    "gn:timezone":"America/Mexico_City",
    "iso:country":"MX",
    "wof:name":"Lomas de San Miguel",
    "wof:placetype":"locality",
    "wof:population":22
},
  "geometry": {"coordinates":[-98.91815,19.89262],"type":"Point"}
}