{
  "type": "Feature",
  "properties": {
    "gn:admin1_code":"5",
    "gn:admin2_code":"78.0",
    "gn:asciiname":"Corazon de Maria",
    "gn:country_code":"MX",
    "gn:dem":2347,
    "gn:feature_class":"P",
    "gn:feature_code":"PPL",
    "gn:name":"Coraz\u00f3n de Mar\u00eda",
    "gn:population":714,
    "gn:timezone":"America/Mexico_City",
    "iso:country":"MX",
    "name:und_x_variant":[
        "Coraz\u00f3n de Mar\u00eda"
    ],
    "wof:name":"Corazon de Maria",
    "wof:placetype":"locality",
    "wof:population":714
},
  "geometry": {"coordinates":[-92.53444,16.69944],"type":"Point"}
}