{
  "type": "Feature",
  "properties": {
    "gn:admin1_code":"32",
    "gn:admin2_code":"4.0",
    "gn:asciiname":"Cuevas Grandes",
    "gn:country_code":"MX",
    "gn:dem":2086,
    "gn:feature_class":"P",
    "gn:feature_code":"PPL",
    "gn:name":"Cuevas Grandes",
    "gn:population":0,
    "gn:timezone":"America/Mexico_City",
    "iso:country":"MX",
    "wof:name":"Cuevas Grandes",
    "wof:placetype":"locality"
},
  "geometry": {"coordinates":[-103.62002,21.53019],"type":"Point"}
}