{
  "type": "Feature",
  "properties": {
    "gn:admin1_code":"32",
    "gn:admin2_code":"54.0",
    "gn:asciiname":"Colonia Juarez",
    "gn:country_code":"MX",
    "gn:dem":2114,
    "gn:feature_class":"P",
    "gn:feature_code":"PPL",
    "gn:name":"Colonia Ju\u00e1rez",
    "gn:population":67,
    "gn:timezone":"America/Mexico_City",
    "iso:country":"MX",
    "name:und_x_variant":[
        "Colonia Ju\u00e1rez"
    ],
    "wof:name":"Colonia Juarez",
    "wof:placetype":"locality",
    "wof:population":67
},
  "geometry": {"coordinates":[-101.77639000000001,22.44639],"type":"Point"}
}