{
  "type": "Feature",
  "properties": {
    "gn:admin1_code":"7",
    "gn:admin2_code":"2.0",
    "gn:asciiname":"La Rosita",
    "gn:country_code":"MX",
    "gn:dem":1024,
    "gn:feature_class":"P",
    "gn:feature_code":"PPL",
    "gn:name":"La Rosita",
    "gn:population":0,
    "gn:timezone":"America/Matamoros",
    "iso:country":"MX",
    "name:spa_x_preferred":[
        "La Rosita"
    ],
    "wof:name":"La Rosita",
    "wof:placetype":"locality"
},
  "geometry": {"coordinates":[-102.31744,29.28477],"type":"Point"}
}