{
  "type": "Feature",
  "properties": {
    "gn:admin1_code":"5",
    "gn:admin2_code":"26.0",
    "gn:asciiname":"Cruzton",
    "gn:country_code":"MX",
    "gn:dem":807,
    "gn:feature_class":"P",
    "gn:feature_code":"PPL",
    "gn:name":"Cruzt\u00f3n",
    "gn:population":557,
    "gn:timezone":"America/Mexico_City",
    "iso:country":"MX",
    "name:und_x_variant":[
        "Cruzt\u00f3n"
    ],
    "wof:name":"Cruzton",
    "wof:placetype":"locality",
    "wof:population":557
},
  "geometry": {"coordinates":[-92.5275,17.05556],"type":"Point"}
}