{
  "type": "Feature",
  "properties": {
    "gn:admin1_code":"20",
    "gn:admin2_code":"57",
    "gn:asciiname":"Rancho Alegre",
    "gn:country_code":"MX",
    "gn:dem":48,
    "gn:feature_class":"P",
    "gn:feature_code":"PPL",
    "gn:name":"Rancho Alegre",
    "gn:population":12,
    "gn:timezone":"America/Mexico_City",
    "iso:country":"MX",
    "name:ceb_x_preferred":[
        "Rancho Alegre"
    ],
    "name:nld_x_preferred":[
        "Rancho Alegre"
    ],
    "name:por_x_preferred":[
        "Rancho Alegre"
    ],
    "name:swe_x_preferred":[
        "Rancho Alegre"
    ],
    "name:vol_x_preferred":[
        "Rancho Alegre"
    ],
    "wof:name":"Rancho Alegre",
    "wof:placetype":"locality",
    "wof:population":12
},
  "geometry": {"coordinates":[-95.08111,17.35278],"type":"Point"}
}