{
  "type": "Feature",
  "properties": {
    "gn:admin1_code":"31",
    "gn:admin2_code":"91.0",
    "gn:asciiname":"Acachen",
    "gn:country_code":"MX",
    "gn:dem":31,
    "gn:feature_class":"P",
    "gn:feature_code":"PPL",
    "gn:name":"Acachen",
    "gn:population":0,
    "gn:timezone":"America/Merida",
    "iso:country":"MX",
    "name:spa_x_preferred":[
        "Acachen"
    ],
    "wof:name":"Acachen",
    "wof:placetype":"locality"
},
  "geometry": {"coordinates":[-88.34154000000002,20.7888],"type":"Point"}
}