{
  "type": "Feature",
  "properties": {
    "gn:admin1_code":"10",
    "gn:admin2_code":"34.0",
    "gn:asciiname":"Los Zapotes",
    "gn:country_code":"MX",
    "gn:dem":417,
    "gn:feature_class":"P",
    "gn:feature_code":"PPL",
    "gn:name":"Los Zapotes",
    "gn:population":0,
    "gn:timezone":"America/Monterrey",
    "iso:country":"MX",
    "name:spa_x_preferred":[
        "Los Zapotes"
    ],
    "wof:name":"Los Zapotes",
    "wof:placetype":"locality"
},
  "geometry": {"coordinates":[-106.7822,24.75662],"type":"Point"}
}