{
  "type": "Feature",
  "properties": {
    "gn:admin1_code":"30",
    "gn:admin2_code":"47.0",
    "gn:asciiname":"Barrio San Jose",
    "gn:country_code":"MX",
    "gn:dem":1828,
    "gn:feature_class":"P",
    "gn:feature_code":"PPL",
    "gn:name":"Barrio San Jos\u00e9",
    "gn:population":325,
    "gn:timezone":"America/Mexico_City",
    "iso:country":"MX",
    "name:und_x_variant":[
        "Barrio San Jos\u00e9"
    ],
    "wof:name":"Barrio San Jose",
    "wof:placetype":"locality",
    "wof:population":325
},
  "geometry": {"coordinates":[-97.07944000000001,19.02861],"type":"Point"}
}