{
  "type": "Feature",
  "properties": {
    "gn:admin1_code":"30",
    "gn:admin2_code":"124.0",
    "gn:asciiname":"El Esfuerzo",
    "gn:country_code":"MX",
    "gn:dem":220,
    "gn:feature_class":"P",
    "gn:feature_code":"PPL",
    "gn:name":"El Esfuerzo",
    "gn:population":216,
    "gn:timezone":"America/Mexico_City",
    "iso:country":"MX",
    "wof:name":"El Esfuerzo",
    "wof:placetype":"locality",
    "wof:population":216
},
  "geometry": {"coordinates":[-97.39610999999999,20.54194],"type":"Point"}
}