{
  "type": "Feature",
  "properties": {
    "gn:admin1_code":"26",
    "gn:admin2_code":"56.0",
    "gn:asciiname":"La Pedregosa",
    "gn:country_code":"MX",
    "gn:dem":348,
    "gn:feature_class":"P",
    "gn:feature_code":"PPL",
    "gn:name":"La Pedregosa",
    "gn:population":0,
    "gn:timezone":"America/Hermosillo",
    "iso:country":"MX",
    "name:spa_x_preferred":[
        "La Pedregosa"
    ],
    "wof:name":"La Pedregosa",
    "wof:placetype":"locality"
},
  "geometry": {"coordinates":[-110.85026000000001,29.34991],"type":"Point"}
}