{
  "type": "Feature",
  "properties": {
    "gn:admin1_code":"28.0",
    "gn:admin2_code":"8.0",
    "gn:asciiname":"La Pizcacha",
    "gn:country_code":"MX",
    "gn:dem":177,
    "gn:feature_class":"P",
    "gn:feature_code":"PPL",
    "gn:name":"La Pizcacha",
    "gn:population":6,
    "gn:timezone":"America/Monterrey",
    "iso:country":"MX",
    "name:spa_x_preferred":[
        "La Pizcacha"
    ],
    "wof:name":"La Pizcacha",
    "wof:placetype":"locality",
    "wof:population":6
},
  "geometry": {"coordinates":[-98.765,23.50583],"type":"Point"}
}