{
  "type": "Feature",
  "properties": {
    "gn:admin1_code":"28.0",
    "gn:admin2_code":"4.0",
    "gn:asciiname":"La Cabra",
    "gn:country_code":"MX",
    "gn:dem":207,
    "gn:feature_class":"P",
    "gn:feature_code":"PPL",
    "gn:name":"La Cabra",
    "gn:population":12,
    "gn:timezone":"America/Monterrey",
    "iso:country":"MX",
    "name:spa_x_preferred":[
        "La Cabra"
    ],
    "wof:name":"La Cabra",
    "wof:placetype":"locality",
    "wof:population":12
},
  "geometry": {"coordinates":[-99.16639000000001,22.68278],"type":"Point"}
}