{
  "type": "Feature",
  "properties": {
    "gn:admin1_code":"12",
    "gn:admin2_code":"37.0",
    "gn:asciiname":"Romita",
    "gn:country_code":"MX",
    "gn:dem":1790,
    "gn:feature_class":"P",
    "gn:feature_code":"PPL",
    "gn:name":"Romita",
    "gn:population":0,
    "gn:timezone":"America/Mexico_City",
    "iso:country":"MX",
    "name:spa_x_preferred":[
        "Romita"
    ],
    "wof:name":"Romita",
    "wof:placetype":"locality"
},
  "geometry": {"coordinates":[-99.81121,18.48786],"type":"Point"}
}