{
  "type": "Feature",
  "properties": {
    "gn:admin1_code":"30",
    "gn:admin2_code":"88.0",
    "gn:asciiname":"Santa Maria Tatetla",
    "gn:country_code":"MX",
    "gn:dem":279,
    "gn:feature_class":"P",
    "gn:feature_code":"PPL",
    "gn:name":"Santa Mar\u00eda Tatetla",
    "gn:population":0,
    "gn:timezone":"America/Mexico_City",
    "iso:country":"MX",
    "name:und_x_variant":[
        "Tatetla",
        "Tetetla",
        "Santa Mar\u00eda Tatetla"
    ],
    "wof:name":"Santa Maria Tatetla",
    "wof:placetype":"locality"
},
  "geometry": {"coordinates":[-96.71250999999999,19.27278],"type":"Point"}
}