{
  "type": "Feature",
  "properties": {
    "gn:admin1_code":"5",
    "gn:admin2_code":"81.0",
    "gn:asciiname":"Sal Si Puedes",
    "gn:country_code":"MX",
    "gn:dem":308,
    "gn:feature_class":"P",
    "gn:feature_code":"PPL",
    "gn:name":"Sal Si Puedes",
    "gn:population":166,
    "gn:timezone":"America/Mexico_City",
    "iso:country":"MX",
    "wof:name":"Sal Si Puedes",
    "wof:placetype":"locality",
    "wof:population":166
},
  "geometry": {"coordinates":[-92.57917,17.11667000000001],"type":"Point"}
}