{
  "type": "Feature",
  "properties": {
    "gn:admin1_code":"30",
    "gn:admin2_code":"193.0",
    "gn:asciiname":"Unidad Antorchista",
    "gn:country_code":"MX",
    "gn:dem":49,
    "gn:feature_class":"P",
    "gn:feature_code":"PPL",
    "gn:name":"Unidad Antorchista",
    "gn:population":620,
    "gn:timezone":"America/Mexico_City",
    "iso:country":"MX",
    "wof:name":"Unidad Antorchista",
    "wof:placetype":"locality",
    "wof:population":620
},
  "geometry": {"coordinates":[-96.23611,19.13778],"type":"Point"}
}