{
  "type": "Feature",
  "properties": {
    "gn:admin1_code":"20",
    "gn:admin2_code":"66.0",
    "gn:asciiname":"El Punto del Chorro",
    "gn:country_code":"MX",
    "gn:dem":31,
    "gn:feature_class":"P",
    "gn:feature_code":"PPL",
    "gn:name":"El Punto del Chorro",
    "gn:population":0,
    "gn:timezone":"America/Mexico_City",
    "iso:country":"MX",
    "name:spa_x_preferred":[
        "El Punto del Chorro"
    ],
    "name:und_x_variant":[
        "El Chorro"
    ],
    "wof:name":"El Punto del Chorro",
    "wof:placetype":"locality"
},
  "geometry": {"coordinates":[-94.58382,16.46596],"type":"Point"}
}