{
  "type": "Feature",
  "properties": {
    "gn:admin1_code":"25",
    "gn:admin2_code":"16.0",
    "gn:asciiname":"El Carrizal",
    "gn:country_code":"MX",
    "gn:dem":281,
    "gn:feature_class":"P",
    "gn:feature_code":"PPL",
    "gn:name":"El Carrizal",
    "gn:population":80,
    "gn:timezone":"America/Mazatlan",
    "iso:country":"MX",
    "name:spa_x_preferred":[
        "El Carrizal"
    ],
    "name:spa_x_variant":[
        "Carrizal"
    ],
    "wof:name":"El Carrizal",
    "wof:placetype":"locality",
    "wof:population":80
},
  "geometry": {"coordinates":[-106.39556,24.06139],"type":"Point"}
}