{
  "type": "Feature",
  "properties": {
    "gn:admin1_code":"16",
    "gn:admin2_code":"77.0",
    "gn:asciiname":"Los Olivos",
    "gn:country_code":"MX",
    "gn:dem":244,
    "gn:feature_class":"P",
    "gn:feature_code":"PPL",
    "gn:name":"Los Olivos",
    "gn:population":6,
    "gn:timezone":"America/Mexico_City",
    "iso:country":"MX",
    "name:ceb_x_preferred":[
        "Los Olivos"
    ],
    "name:deu_x_preferred":[
        "Los Olivos"
    ],
    "name:fra_x_preferred":[
        "Los Olivos"
    ],
    "name:ita_x_preferred":[
        "Los Olivos"
    ],
    "name:srp_x_preferred":[
        "\u041b\u043e\u0441 \u041e\u043b\u0438\u0432\u043e\u0441"
    ],
    "name:swe_x_preferred":[
        "Los Olivos"
    ],
    "wof:name":"Los Olivos",
    "wof:placetype":"locality",
    "wof:population":6
},
  "geometry": {"coordinates":[-100.67333000000001,18.38778],"type":"Point"}
}