{
  "type": "Feature",
  "properties": {
    "gn:admin1_code":"24.0",
    "gn:admin2_code":"15.0",
    "gn:asciiname":"Estacion Berrendo",
    "gn:country_code":"MX",
    "gn:dem":1993,
    "gn:feature_class":"P",
    "gn:feature_code":"PPL",
    "gn:name":"Estaci\u00f3n Berrendo",
    "gn:population":62,
    "gn:timezone":"America/Mexico_City",
    "iso:country":"MX",
    "wof:name":"Estacion Berrendo",
    "wof:placetype":"locality",
    "wof:population":62
},
  "geometry": {"coordinates":[-100.98891,23.3293],"type":"Point"}
}