{
  "type": "Feature",
  "properties": {
    "gn:admin1_code":"20",
    "gn:admin2_code":"516.0",
    "gn:asciiname":"El Piojo",
    "gn:country_code":"MX",
    "gn:dem":914,
    "gn:feature_class":"P",
    "gn:feature_code":"PPL",
    "gn:name":"El Piojo",
    "gn:population":0,
    "gn:timezone":"America/Mexico_City",
    "iso:country":"MX",
    "wof:name":"El Piojo",
    "wof:placetype":"locality"
},
  "geometry": {"coordinates":[-97.23333,16.53333],"type":"Point"}
}