{
  "type": "Feature",
  "properties": {
    "gn:admin1_code":"23",
    "gn:admin2_code":"4.0",
    "gn:asciiname":"La Rosita",
    "gn:country_code":"MX",
    "gn:dem":43,
    "gn:feature_class":"P",
    "gn:feature_code":"PPL",
    "gn:name":"La Rosita",
    "gn:population":5,
    "gn:timezone":"America/Cancun",
    "iso:country":"MX",
    "wof:name":"La Rosita",
    "wof:placetype":"locality",
    "wof:population":5
},
  "geometry": {"coordinates":[-88.66376,18.26205],"type":"Point"}
}