{
  "type": "Feature",
  "properties": {
    "gn:admin1_code":"25",
    "gn:admin2_code":"3.0",
    "gn:asciiname":"El Mahutal",
    "gn:country_code":"MX",
    "gn:dem":404,
    "gn:feature_class":"P",
    "gn:feature_code":"PPL",
    "gn:name":"El Mahutal",
    "gn:population":0,
    "gn:timezone":"America/Mazatlan",
    "iso:country":"MX",
    "name:spa_x_preferred":[
        "El Mahutal"
    ],
    "name:und_x_variant":[
        "El Mautal"
    ],
    "wof:name":"El Mahutal",
    "wof:placetype":"locality"
},
  "geometry": {"coordinates":[-107.26152999999999,25.184],"type":"Point"}
}