{
  "type": "Feature",
  "properties": {
    "gn:admin1_code":"10",
    "gn:admin2_code":"37.0",
    "gn:asciiname":"La Tasajera",
    "gn:country_code":"MX",
    "gn:dem":2451,
    "gn:feature_class":"P",
    "gn:feature_code":"PPL",
    "gn:name":"La Tasajera",
    "gn:population":0,
    "gn:timezone":"America/Monterrey",
    "iso:country":"MX",
    "name:spa_x_preferred":[
        "La Tasajera"
    ],
    "wof:name":"La Tasajera",
    "wof:placetype":"locality"
},
  "geometry": {"coordinates":[-106.52016999999999,25.21993],"type":"Point"}
}