{
  "type": "Feature",
  "properties": {
    "gn:admin1_code":"28.0",
    "gn:admin2_code":"21.0",
    "gn:asciiname":"El Siete y Medio",
    "gn:country_code":"MX",
    "gn:dem":58,
    "gn:feature_class":"P",
    "gn:feature_code":"PPL",
    "gn:name":"El Siete y Med\u00edo",
    "gn:population":0,
    "gn:timezone":"America/Monterrey",
    "iso:country":"MX",
    "name:spa_x_preferred":[
        "El Siete y Med\u00edo"
    ],
    "wof:name":"El Siete y Medio",
    "wof:placetype":"locality"
},
  "geometry": {"coordinates":[-98.89807999999999,22.71533],"type":"Point"}
}