{
  "type": "Feature",
  "properties": {
    "gn:admin1_code":"26",
    "gn:admin2_code":"18.0",
    "gn:asciiname":"Huacaporo",
    "gn:country_code":"MX",
    "gn:dem":53,
    "gn:feature_class":"P",
    "gn:feature_code":"PPL",
    "gn:name":"Huacaporo",
    "gn:population":0,
    "gn:timezone":"America/Hermosillo",
    "iso:country":"MX",
    "name:spa_x_preferred":[
        "Huacaporo"
    ],
    "wof:name":"Huacaporo",
    "wof:placetype":"locality"
},
  "geometry": {"coordinates":[-109.83087,27.3082],"type":"Point"}
}