{
  "type": "Feature",
  "properties": {
    "gn:admin1_code":"1.0",
    "gn:admin2_code":"2.0",
    "gn:asciiname":"San Jose El Alto",
    "gn:country_code":"MX",
    "gn:dem":2033,
    "gn:feature_class":"P",
    "gn:feature_code":"PPL",
    "gn:name":"San Jos\u00e9 El Alto",
    "gn:population":0,
    "gn:timezone":"America/Mexico_City",
    "iso:country":"MX",
    "name:spa_x_preferred":[
        "San Jos\u00e9 El Alto"
    ],
    "wof:name":"San Jose El Alto",
    "wof:placetype":"locality"
},
  "geometry": {"coordinates":[-102.1331,22.08361],"type":"Point"}
}