{
  "type": "Feature",
  "properties": {
    "gn:admin1_code":"13",
    "gn:admin2_code":"62.0",
    "gn:asciiname":"Xalamatitla",
    "gn:country_code":"MX",
    "gn:dem":748,
    "gn:feature_class":"P",
    "gn:feature_code":"PPL",
    "gn:name":"Xalamatitla",
    "gn:population":0,
    "gn:timezone":"America/Mexico_City",
    "iso:country":"MX",
    "name:spa_x_preferred":[
        "Xolamantitla"
    ],
    "name:spa_x_variant":[
        "Xalamatitla"
    ],
    "wof:name":"Xalamatitla",
    "wof:placetype":"locality"
},
  "geometry": {"coordinates":[-98.77252,21.09344],"type":"Point"}
}