{
  "type": "Feature",
  "properties": {
    "gn:admin1_code":"15.0",
    "gn:asciiname":"Camino la Via",
    "gn:country_code":"MX",
    "gn:dem":2256,
    "gn:feature_class":"P",
    "gn:feature_code":"PPL",
    "gn:name":"Camino la V\u00eda",
    "gn:population":0,
    "gn:timezone":"America/Mexico_City",
    "iso:country":"MX",
    "name:spa_x_preferred":[
        "Camino la V\u00eda"
    ],
    "wof:name":"Camino la Via",
    "wof:placetype":"locality"
},
  "geometry": {"coordinates":[-98.87544,19.23122],"type":"Point"}
}