{
  "type": "Feature",
  "properties": {
    "gn:admin1_code":"14",
    "gn:admin2_code":"61.0",
    "gn:asciiname":"Ara Ropa",
    "gn:country_code":"MX",
    "gn:dem":1587,
    "gn:feature_class":"P",
    "gn:feature_code":"PPL",
    "gn:name":"Ara Ropa",
    "gn:population":0,
    "gn:timezone":"America/Mexico_City",
    "iso:country":"MX",
    "name:spa_x_preferred":[
        "Ara Ropa"
    ],
    "name:und_x_variant":[
        "El Arado"
    ],
    "wof:name":"Ara Ropa",
    "wof:placetype":"locality"
},
  "geometry": {"coordinates":[-104.295,22.20536],"type":"Point"}
}