{
  "type": "Feature",
  "properties": {
    "gn:admin1_code":"29",
    "gn:admin2_code":"34.0",
    "gn:asciiname":"Los Alamos",
    "gn:country_code":"MX",
    "gn:dem":2695,
    "gn:feature_class":"P",
    "gn:feature_code":"PPL",
    "gn:name":"Los Alamos",
    "gn:population":0,
    "gn:timezone":"America/Mexico_City",
    "iso:country":"MX",
    "name:spa_x_preferred":[
        "Los Alamos"
    ],
    "wof:name":"Los Alamos",
    "wof:placetype":"locality"
},
  "geometry": {"coordinates":[-98.03149999999999,19.55762],"type":"Point"}
}