{
  "type": "Feature",
  "properties": {
    "gn:admin1_code":"5",
    "gn:admin2_code":"52.0",
    "gn:asciiname":"San Lorenzo",
    "gn:country_code":"MX",
    "gn:dem":1072,
    "gn:feature_class":"P",
    "gn:feature_code":"PPL",
    "gn:name":"San Lorenzo",
    "gn:population":276,
    "gn:timezone":"America/Mexico_City",
    "iso:country":"MX",
    "wof:name":"San Lorenzo",
    "wof:placetype":"locality",
    "wof:population":276
},
  "geometry": {"coordinates":[-91.65778,16.32972],"type":"Point"}
}