{
  "type": "Feature",
  "properties": {
    "gn:admin1_code":"30",
    "gn:admin2_code":"151.0",
    "gn:asciiname":"Barra de Corazones",
    "gn:country_code":"MX",
    "gn:dem":3,
    "gn:feature_class":"P",
    "gn:feature_code":"PPL",
    "gn:name":"Barra de Corazones",
    "gn:population":370,
    "gn:timezone":"America/Mexico_City",
    "iso:country":"MX",
    "name:spa_x_preferred":[
        "Barra de Corazones"
    ],
    "wof:name":"Barra de Corazones",
    "wof:placetype":"locality",
    "wof:population":370
},
  "geometry": {"coordinates":[-97.43394000000001,21.2572],"type":"Point"}
}