{
  "type": "Feature",
  "properties": {
    "gn:admin1_code":"5.0",
    "gn:asciiname":"El Porvenir",
    "gn:country_code":"MX",
    "gn:dem":58,
    "gn:feature_class":"P",
    "gn:feature_code":"PPL",
    "gn:name":"El Porvenir",
    "gn:population":0,
    "gn:timezone":"America/Mexico_City",
    "iso:country":"MX",
    "name:spa_x_preferred":[
        "El Porvenir"
    ],
    "wof:name":"El Porvenir",
    "wof:placetype":"locality"
},
  "geometry": {"coordinates":[-92.98734,15.53433],"type":"Point"}
}