{
  "type": "Feature",
  "properties": {
    "gn:admin1_code":"20",
    "gn:admin2_code":"500.0",
    "gn:asciiname":"Yuku Magnu",
    "gn:country_code":"MX",
    "gn:dem":2439,
    "gn:feature_class":"P",
    "gn:feature_code":"PPL",
    "gn:name":"Yuku Mag\u00f1u",
    "gn:population":81,
    "gn:timezone":"America/Mexico_City",
    "iso:country":"MX",
    "name:und_x_variant":[
        "Yuku Mag\u00f1u"
    ],
    "wof:name":"Yuku Magnu",
    "wof:placetype":"locality",
    "wof:population":81
},
  "geometry": {"coordinates":[-97.60028,16.87083],"type":"Point"}
}