{
  "type": "Feature",
  "properties": {
    "gn:admin1_code":"26",
    "gn:asciiname":"Los Algodones",
    "gn:country_code":"MX",
    "gn:dem":154,
    "gn:feature_class":"P",
    "gn:feature_code":"PPL",
    "gn:name":"Los Algodones",
    "gn:population":0,
    "gn:timezone":"America/Hermosillo",
    "iso:country":"MX",
    "name:spa_x_preferred":[
        "Los Algodones"
    ],
    "wof:name":"Los Algodones",
    "wof:placetype":"locality"
},
  "geometry": {"coordinates":[-108.52612999999999,26.81654],"type":"Point"}
}