{
  "type": "Feature",
  "properties": {
    "gn:admin1_code":"20",
    "gn:admin2_code":"217.0",
    "gn:asciiname":"Joya Grande",
    "gn:country_code":"MX",
    "gn:dem":2162,
    "gn:feature_class":"P",
    "gn:feature_code":"PPL",
    "gn:name":"Joya Grande",
    "gn:population":7,
    "gn:timezone":"America/Mexico_City",
    "iso:country":"MX",
    "wof:name":"Joya Grande",
    "wof:placetype":"locality",
    "wof:population":7
},
  "geometry": {"coordinates":[-97.09,17.13694],"type":"Point"}
}