{
  "type": "Feature",
  "properties": {
    "gn:admin1_code":"32",
    "gn:admin2_code":"45.0",
    "gn:asciiname":"Las Viudas",
    "gn:country_code":"MX",
    "gn:dem":1834,
    "gn:feature_class":"P",
    "gn:feature_code":"PPL",
    "gn:name":"Las Viudas",
    "gn:population":6,
    "gn:timezone":"America/Mexico_City",
    "iso:country":"MX",
    "wof:name":"Las Viudas",
    "wof:placetype":"locality",
    "wof:population":6
},
  "geometry": {"coordinates":[-103.30638999999999,21.59722],"type":"Point"}
}