{
  "type": "Feature",
  "properties": {
    "gn:admin1_code":"12.0",
    "gn:admin2_code":"53.0",
    "gn:asciiname":"Zoyamite",
    "gn:country_code":"MX",
    "gn:dem":38,
    "gn:feature_class":"P",
    "gn:feature_code":"PPL",
    "gn:name":"Zoyamite",
    "gn:population":0,
    "gn:timezone":"America/Mexico_City",
    "iso:country":"MX",
    "name:spa_x_preferred":[
        "Zoyamite"
    ],
    "wof:name":"Zoyamite",
    "wof:placetype":"locality"
},
  "geometry": {"coordinates":[-99.35439,16.73571],"type":"Point"}
}