{
  "type": "Feature",
  "properties": {
    "gn:admin1_code":"24.0",
    "gn:admin2_code":"36.0",
    "gn:asciiname":"Carrizalito de Moctezuma",
    "gn:country_code":"MX",
    "gn:dem":1058,
    "gn:feature_class":"P",
    "gn:feature_code":"PPL",
    "gn:name":"Carrizalito de Moctezuma",
    "gn:population":0,
    "gn:timezone":"America/Mexico_City",
    "iso:country":"MX",
    "name:spa_x_preferred":[
        "Carrizalito de Moctezuma"
    ],
    "wof:name":"Carrizalito de Moctezuma",
    "wof:placetype":"locality"
},
  "geometry": {"coordinates":[-99.4662,22.05716],"type":"Point"}
}