{
  "type": "Feature",
  "properties": {
    "gn:admin1_code":"6",
    "gn:admin2_code":"23.0",
    "gn:asciiname":"Cienega de Horcones",
    "gn:country_code":"MX",
    "gn:dem":1450,
    "gn:feature_class":"P",
    "gn:feature_code":"PPL",
    "gn:name":"Ci\u00e9nega de Horcones",
    "gn:population":0,
    "gn:timezone":"America/Chihuahua",
    "iso:country":"MX",
    "name:spa_x_preferred":[
        "Ci\u00e9nega de Horcones"
    ],
    "name:und_x_variant":[
        "Ci\u00e9naga de Horcones"
    ],
    "wof:name":"Cienega de Horcones",
    "wof:placetype":"locality"
},
  "geometry": {"coordinates":[-107.65991,30.05327],"type":"Point"}
}