{
  "type": "Feature",
  "properties": {
    "gn:admin1_code":"24",
    "gn:admin2_code":"33.0",
    "gn:asciiname":"San Antonio del Mezquite",
    "gn:country_code":"MX",
    "gn:dem":2081,
    "gn:feature_class":"P",
    "gn:feature_code":"PPL",
    "gn:name":"San Antonio del Mezquite",
    "gn:population":385,
    "gn:timezone":"America/Mexico_City",
    "iso:country":"MX",
    "name:spa_x_preferred":[
        "San Antonio del Mezquite"
    ],
    "wof:name":"San Antonio del Mezquite",
    "wof:placetype":"locality",
    "wof:population":385
},
  "geometry": {"coordinates":[-101.88876999999999,23.1633],"type":"Point"}
}