{
  "type": "Feature",
  "properties": {
    "gn:admin1_code":"28",
    "gn:admin2_code":"25.0",
    "gn:asciiname":"Santa Ignacia",
    "gn:country_code":"MX",
    "gn:dem":53,
    "gn:feature_class":"P",
    "gn:feature_code":"PPL",
    "gn:name":"Santa Ignacia",
    "gn:population":7,
    "gn:timezone":"America/Monterrey",
    "iso:country":"MX",
    "wof:name":"Santa Ignacia",
    "wof:placetype":"locality",
    "wof:population":7
},
  "geometry": {"coordinates":[-98.97499999999999,26.38417],"type":"Point"}
}