{
  "type": "Feature",
  "properties": {
    "gn:admin1_code":"11",
    "gn:admin2_code":"37",
    "gn:asciiname":"Los Alamos Norte",
    "gn:country_code":"MX",
    "gn:dem":2257,
    "gn:feature_class":"P",
    "gn:feature_code":"PPL",
    "gn:name":"Los \u00c1lamos Norte",
    "gn:population":34,
    "gn:timezone":"America/Mexico_City",
    "iso:country":"MX",
    "name:und_x_variant":[
        "Los \u00c1lamos Norte"
    ],
    "wof:name":"Los Alamos Norte",
    "wof:placetype":"locality",
    "wof:population":34
},
  "geometry": {"coordinates":[-101.44528,21.13556],"type":"Point"}
}