{
  "type": "Feature",
  "properties": {
    "gn:admin1_code":"24",
    "gn:admin2_code":"56.0",
    "gn:asciiname":"El Pozo",
    "gn:country_code":"MX",
    "gn:dem":1597,
    "gn:feature_class":"P",
    "gn:feature_code":"PPL",
    "gn:name":"El Pozo",
    "gn:population":497,
    "gn:timezone":"America/Mexico_City",
    "iso:country":"MX",
    "name:deu_x_preferred":[
        "El Pozo"
    ],
    "name:srp_x_preferred":[
        "\u0415\u043b \u041f\u043e\u0437\u043e"
    ],
    "wof:name":"El Pozo",
    "wof:placetype":"locality",
    "wof:population":497
},
  "geometry": {"coordinates":[-100.82889,22.705],"type":"Point"}
}