{
  "type": "Feature",
  "properties": {
    "gn:admin1_code":"7.0",
    "gn:admin2_code":"14.0",
    "gn:asciiname":"El Viejo Campo Real",
    "gn:country_code":"MX",
    "gn:dem":261,
    "gn:feature_class":"P",
    "gn:feature_code":"PPL",
    "gn:name":"El Viejo Campo Real",
    "gn:population":0,
    "gn:timezone":"America/Monterrey",
    "iso:country":"MX",
    "name:spa_x_preferred":[
        "El Viejo Campo Real"
    ],
    "wof:name":"El Viejo Campo Real",
    "wof:placetype":"locality"
},
  "geometry": {"coordinates":[-100.6647,28.97357],"type":"Point"}
}