{
  "type": "Feature",
  "properties": {
    "gn:admin1_code":"10.0",
    "gn:asciiname":"Rincon de Tablillas",
    "gn:country_code":"MX",
    "gn:dem":2401,
    "gn:feature_class":"P",
    "gn:feature_code":"PPL",
    "gn:name":"Rinc\u00f3n de Tablillas",
    "gn:population":0,
    "gn:timezone":"America/Monterrey",
    "iso:country":"MX",
    "name:spa_x_preferred":[
        "Rinc\u00f3n de Tablillas"
    ],
    "wof:name":"Rincon de Tablillas",
    "wof:placetype":"locality"
},
  "geometry": {"coordinates":[-105.37909000000001,24.17209],"type":"Point"}
}