{
  "type": "Feature",
  "properties": {
    "gn:admin1_code":"14",
    "gn:admin2_code":"24",
    "gn:asciiname":"Colimilla",
    "gn:country_code":"MX",
    "gn:dem":1350,
    "gn:feature_class":"P",
    "gn:feature_code":"PPL",
    "gn:name":"Colimilla",
    "gn:population":41,
    "gn:timezone":"America/Mexico_City",
    "iso:country":"MX",
    "wof:name":"Colimilla",
    "wof:placetype":"locality",
    "wof:population":41
},
  "geometry": {"coordinates":[-103.84083,20.36139],"type":"Point"}
}