{
  "type": "Feature",
  "properties": {
    "gn:admin1_code":"6",
    "gn:admin2_code":"39.0",
    "gn:asciiname":"Rancho San Buenaventura",
    "gn:country_code":"MX",
    "gn:dem":1425,
    "gn:feature_class":"P",
    "gn:feature_code":"PPL",
    "gn:name":"Rancho San Buenaventura",
    "gn:population":0,
    "gn:timezone":"America/Chihuahua",
    "iso:country":"MX",
    "wof:name":"Rancho San Buenaventura",
    "wof:placetype":"locality"
},
  "geometry": {"coordinates":[-105.03333000000001,27.01667],"type":"Point"}
}