{
  "type": "Feature",
  "properties": {
    "gn:admin1_code":"5",
    "gn:admin2_code":"57.0",
    "gn:asciiname":"El Pizarrin",
    "gn:country_code":"MX",
    "gn:dem":2365,
    "gn:feature_class":"P",
    "gn:feature_code":"PPL",
    "gn:name":"El Pizarr\u00edn",
    "gn:population":277,
    "gn:timezone":"America/Mexico_City",
    "iso:country":"MX",
    "wof:name":"El Pizarrin",
    "wof:placetype":"locality",
    "wof:population":277
},
  "geometry": {"coordinates":[-92.32944000000001,15.405],"type":"Point"}
}