{
  "type": "Feature",
  "properties": {
    "gn:admin1_code":"12",
    "gn:admin2_code":"53.0",
    "gn:asciiname":"Los Mogotes",
    "gn:country_code":"MX",
    "gn:dem":9,
    "gn:feature_class":"P",
    "gn:feature_code":"PPL",
    "gn:name":"Los Mogotes",
    "gn:population":7,
    "gn:timezone":"America/Mexico_City",
    "iso:country":"MX",
    "wof:name":"Los Mogotes",
    "wof:placetype":"locality",
    "wof:population":7
},
  "geometry": {"coordinates":[-99.29497000000001,16.65834],"type":"Point"}
}