{
  "type": "Feature",
  "properties": {
    "gn:admin1_code":"5",
    "gn:admin2_code":"17",
    "gn:asciiname":"San Carlos",
    "gn:country_code":"MX",
    "gn:dem":659,
    "gn:feature_class":"P",
    "gn:feature_code":"PPL",
    "gn:name":"San Carlos",
    "gn:population":17,
    "gn:timezone":"America/Mexico_City",
    "iso:country":"MX",
    "wof:name":"San Carlos",
    "wof:placetype":"locality",
    "wof:population":17
},
  "geometry": {"coordinates":[-93.89972,16.55694],"type":"Point"}
}