{
  "type": "Feature",
  "properties": {
    "gn:admin1_code":"27",
    "gn:admin2_code":"8.0",
    "gn:asciiname":"Lago Escondido",
    "gn:country_code":"MX",
    "gn:dem":20,
    "gn:feature_class":"P",
    "gn:feature_code":"PPL",
    "gn:name":"Lago Escondido",
    "gn:population":0,
    "gn:timezone":"America/Mexico_City",
    "iso:country":"MX",
    "name:nld_x_preferred":[
        "Lago Escondido"
    ],
    "name:sco_x_preferred":[
        "Lago Escondido"
    ],
    "name:spa_x_preferred":[
        "El Tasiste"
    ],
    "name:spa_x_variant":[
        "Lago Escondido"
    ],
    "name:urd_x_preferred":[
        "\u0644\u0627\u06af\u0648 \u0627\u06cc\u0633\u06a9\u0648\u0646\u0688\u06cc\u0688\u0648"
    ],
    "wof:name":"Lago Escondido",
    "wof:placetype":"locality"
},
  "geometry": {"coordinates":[-93.87277,17.89067],"type":"Point"}
}