{
  "type": "Feature",
  "properties": {
    "gn:admin1_code":"16",
    "gn:admin2_code":"49.0",
    "gn:asciiname":"La Cieneguita",
    "gn:country_code":"MX",
    "gn:dem":1198,
    "gn:feature_class":"P",
    "gn:feature_code":"PPL",
    "gn:name":"La Cieneguita",
    "gn:population":8,
    "gn:timezone":"America/Mexico_City",
    "iso:country":"MX",
    "wof:name":"La Cieneguita",
    "wof:placetype":"locality",
    "wof:population":8
},
  "geometry": {"coordinates":[-101.07083,19.29417],"type":"Point"}
}