{
  "type": "Feature",
  "properties": {
    "gn:admin1_code":"30",
    "gn:admin2_code":"48",
    "gn:asciiname":"El Pinal",
    "gn:country_code":"MX",
    "gn:dem":24,
    "gn:feature_class":"P",
    "gn:feature_code":"PPL",
    "gn:name":"El Pi\u00f1al",
    "gn:population":50,
    "gn:timezone":"America/Mexico_City",
    "iso:country":"MX",
    "name:und_x_variant":[
        "El Pi\u00f1al"
    ],
    "wof:name":"El Pinal",
    "wof:placetype":"locality",
    "wof:population":50
},
  "geometry": {"coordinates":[-94.62917,17.96583],"type":"Point"}
}