{
  "type": "Feature",
  "properties": {
    "gn:admin1_code":"26",
    "gn:admin2_code":"72",
    "gn:asciiname":"Urbalejo",
    "gn:country_code":"MX",
    "gn:dem":21,
    "gn:feature_class":"P",
    "gn:feature_code":"PPL",
    "gn:name":"Urbalejo",
    "gn:population":11,
    "gn:timezone":"America/Hermosillo",
    "iso:country":"MX",
    "wof:name":"Urbalejo",
    "wof:placetype":"locality",
    "wof:population":11
},
  "geometry": {"coordinates":[-110.22028,27.51889000000001],"type":"Point"}
}