{
  "type": "Feature",
  "properties": {
    "gn:admin1_code":"26",
    "gn:admin2_code":"35.0",
    "gn:asciiname":"Los Remedios",
    "gn:cc2":"MX",
    "gn:country_code":"MX",
    "gn:dem":1025,
    "gn:feature_class":"P",
    "gn:feature_code":"PPL",
    "gn:name":"Los Remedios",
    "gn:population":0,
    "gn:timezone":"America/Hermosillo",
    "iso:country":"MX",
    "name:cat_x_preferred":[
        "Los Remedios"
    ],
    "name:glg_x_preferred":[
        "Distrito Los Remedios"
    ],
    "name:rus_x_preferred":[
        "\u041b\u043e\u0441-\u0420\u0435\u043c\u0435\u0434\u0438\u043e\u0441"
    ],
    "name:spa_x_preferred":[
        "Distrito Los Remedios"
    ],
    "name:und_x_variant":[
        "Remedios",
        "Los Remedios"
    ],
    "wof:name":"Los Remedios",
    "wof:placetype":"locality"
},
  "geometry": {"coordinates":[-110.70611,30.76944],"type":"Point"}
}