{
  "type": "Feature",
  "properties": {
    "gn:admin1_code":"5",
    "gn:admin2_code":"27",
    "gn:asciiname":"Laguna Pato",
    "gn:country_code":"MX",
    "gn:dem":547,
    "gn:feature_class":"P",
    "gn:feature_code":"PPL",
    "gn:name":"Laguna Pato",
    "gn:population":22,
    "gn:timezone":"America/Mexico_City",
    "iso:country":"MX",
    "wof:name":"Laguna Pato",
    "wof:placetype":"locality",
    "wof:population":22
},
  "geometry": {"coordinates":[-92.955,16.69056],"type":"Point"}
}