{
  "type": "Feature",
  "properties": {
    "gn:admin1_code":"30",
    "gn:admin2_code":"123.0",
    "gn:asciiname":"Chila Silva",
    "gn:country_code":"MX",
    "gn:dem":5,
    "gn:feature_class":"P",
    "gn:feature_code":"PPL",
    "gn:name":"Chila Silva",
    "gn:population":0,
    "gn:timezone":"America/Mexico_City",
    "iso:country":"MX",
    "name:und_x_variant":[
        "Chila",
        "Chila Silva"
    ],
    "wof:name":"Chila Silva",
    "wof:placetype":"locality"
},
  "geometry": {"coordinates":[-98.01017,22.19725],"type":"Point"}
}