{
  "type": "Feature",
  "properties": {
    "gn:admin1_code":"28",
    "gn:asciiname":"Jesus Maria",
    "gn:country_code":"MX",
    "gn:dem":-9999,
    "gn:feature_class":"P",
    "gn:feature_code":"PPL",
    "gn:name":"Jes\u00fas Mar\u00eda",
    "gn:population":0,
    "gn:timezone":"America/Monterrey",
    "iso:country":"MX",
    "wof:name":"Jesus Maria",
    "wof:placetype":"locality"
},
  "geometry": {"coordinates":[-97.66667,24.51667],"type":"Point"}
}