{
  "type": "Feature",
  "properties": {
    "gn:admin1_code":"28",
    "gn:admin2_code":"20.0",
    "gn:asciiname":"Francisco Ignacio Madero",
    "gn:country_code":"MX",
    "gn:dem":385,
    "gn:feature_class":"P",
    "gn:feature_code":"PPL",
    "gn:name":"Francisco Ignacio Madero",
    "gn:population":0,
    "gn:timezone":"America/Monterrey",
    "iso:country":"MX",
    "name:spa_x_preferred":[
        "Francisco I. Madero"
    ],
    "name:spa_x_variant":[
        "Francisco Ignacio Madero"
    ],
    "name:und_x_variant":[
        "Francisco Madero"
    ],
    "wof:name":"Francisco Ignacio Madero",
    "wof:placetype":"locality"
},
  "geometry": {"coordinates":[-99.5072,24.56094],"type":"Point"}
}