{
  "type": "Feature",
  "properties": {
    "gn:admin1_code":"28.0",
    "gn:admin2_code":"43.0",
    "gn:asciiname":"San Jose Buenaventura",
    "gn:country_code":"MX",
    "gn:dem":97,
    "gn:feature_class":"P",
    "gn:feature_code":"PPL",
    "gn:name":"San Jos\u00e9 Buenaventura",
    "gn:population":0,
    "gn:timezone":"America/Monterrey",
    "iso:country":"MX",
    "name:spa_x_preferred":[
        "San Jos\u00e9 Buenaventura"
    ],
    "wof:name":"San Jose Buenaventura",
    "wof:placetype":"locality"
},
  "geometry": {"coordinates":[-98.82444,22.92972],"type":"Point"}
}