{
  "type": "Feature",
  "properties": {
    "gn:admin1_code":"21.0",
    "gn:admin2_code":"152.0",
    "gn:asciiname":"Cruz Verde",
    "gn:country_code":"MX",
    "gn:dem":2449,
    "gn:feature_class":"P",
    "gn:feature_code":"PPL",
    "gn:name":"Cruz Verde",
    "gn:population":0,
    "gn:timezone":"America/Mexico_City",
    "iso:country":"MX",
    "name:spa_x_preferred":[
        "Cruz Verde"
    ],
    "wof:name":"Cruz Verde",
    "wof:placetype":"locality"
},
  "geometry": {"coordinates":[-97.732,19.12862],"type":"Point"}
}