{
  "type": "Feature",
  "properties": {
    "gn:admin1_code":"30",
    "gn:admin2_code":"14",
    "gn:asciiname":"Los Tapia",
    "gn:country_code":"MX",
    "gn:dem":546,
    "gn:feature_class":"P",
    "gn:feature_code":"PPL",
    "gn:name":"Los Tapia",
    "gn:population":40,
    "gn:timezone":"America/Mexico_City",
    "iso:country":"MX",
    "wof:name":"Los Tapia",
    "wof:placetype":"locality",
    "wof:population":40
},
  "geometry": {"coordinates":[-96.8275,18.82444],"type":"Point"}
}