{
  "type": "Feature",
  "properties": {
    "gn:admin1_code":"31",
    "gn:admin2_code":"104.0",
    "gn:asciiname":"Tiholop",
    "gn:country_code":"MX",
    "gn:dem":30,
    "gn:feature_class":"P",
    "gn:feature_code":"PPL",
    "gn:name":"Tiholop",
    "gn:population":1463,
    "gn:timezone":"America/Merida",
    "iso:country":"MX",
    "name:spa_x_preferred":[
        "Tiholop"
    ],
    "wof:name":"Tiholop",
    "wof:placetype":"locality",
    "wof:population":1463
},
  "geometry": {"coordinates":[-88.68958000000001,20.33234],"type":"Point"}
}