{
  "type": "Feature",
  "properties": {
    "gn:admin1_code":"30.0",
    "gn:admin2_code":"145.0",
    "gn:asciiname":"Consoyapa",
    "gn:country_code":"MX",
    "gn:dem":56,
    "gn:feature_class":"P",
    "gn:feature_code":"PPL",
    "gn:name":"Consoyapa",
    "gn:population":0,
    "gn:timezone":"America/Mexico_City",
    "iso:country":"MX",
    "name:spa_x_preferred":[
        "Consoyapa"
    ],
    "wof:name":"Consoyapa",
    "wof:placetype":"locality"
},
  "geometry": {"coordinates":[-94.85424,17.96142],"type":"Point"}
}