{
  "type": "Feature",
  "properties": {
    "gn:admin1_code":"22",
    "gn:admin2_code":"5.0",
    "gn:asciiname":"San Vicente el Alto",
    "gn:country_code":"MX",
    "gn:dem":1922,
    "gn:feature_class":"P",
    "gn:feature_code":"PPL",
    "gn:name":"San Vicente el Alto",
    "gn:population":0,
    "gn:timezone":"America/Mexico_City",
    "iso:country":"MX",
    "name:spa_x_preferred":[
        "San Vicente el Alto"
    ],
    "name:spa_x_variant":[
        "San Vicente"
    ],
    "wof:name":"San Vicente el Alto",
    "wof:placetype":"locality"
},
  "geometry": {"coordinates":[-100.16495,20.56857],"type":"Point"}
}