{
  "type": "Feature",
  "properties": {
    "gn:admin1_code":"23",
    "gn:admin2_code":"4.0",
    "gn:asciiname":"Ramon",
    "gn:country_code":"MX",
    "gn:dem":12,
    "gn:feature_class":"P",
    "gn:feature_code":"PPL",
    "gn:name":"Ram\u00f3n",
    "gn:population":8,
    "gn:timezone":"America/Cancun",
    "iso:country":"MX",
    "name:und_x_variant":[
        "Ram\u00f3n"
    ],
    "wof:name":"Ramon",
    "wof:placetype":"locality",
    "wof:population":8
},
  "geometry": {"coordinates":[-88.29555999999999,18.65321],"type":"Point"}
}