{
  "type": "Feature",
  "properties": {
    "gn:admin1_code":"6",
    "gn:admin2_code":"12.0",
    "gn:asciiname":"Paraje Rechaneachi",
    "gn:country_code":"MX",
    "gn:dem":2108,
    "gn:feature_class":"P",
    "gn:feature_code":"PPL",
    "gn:name":"Paraje Rechaneachi",
    "gn:population":0,
    "gn:timezone":"America/Chihuahua",
    "iso:country":"MX",
    "name:spa_x_preferred":[
        "Paraje Rechaneachi"
    ],
    "wof:name":"Paraje Rechaneachi",
    "wof:placetype":"locality"
},
  "geometry": {"coordinates":[-107.16193,27.78232],"type":"Point"}
}