{
  "type": "Feature",
  "properties": {
    "gn:admin1_code":"31",
    "gn:admin2_code":"96.0",
    "gn:asciiname":"Polceh",
    "gn:country_code":"MX",
    "gn:dem":16,
    "gn:feature_class":"P",
    "gn:feature_code":"PPL",
    "gn:name":"Polceh",
    "gn:population":0,
    "gn:timezone":"America/Merida",
    "iso:country":"MX",
    "name:spa_x_preferred":[
        "Polceh"
    ],
    "wof:name":"Polceh",
    "wof:placetype":"locality"
},
  "geometry": {"coordinates":[-88.02248,21.37128],"type":"Point"}
}