{
  "type": "Feature",
  "properties": {
    "gn:admin1_code":"32",
    "gn:admin2_code":"7",
    "gn:asciiname":"El Jazmin",
    "gn:country_code":"MX",
    "gn:dem":1777,
    "gn:feature_class":"P",
    "gn:feature_code":"PPL",
    "gn:name":"El Jazm\u00edn",
    "gn:population":15,
    "gn:timezone":"America/Mexico_City",
    "iso:country":"MX",
    "name:und_x_variant":[
        "El Jazm\u00edn"
    ],
    "wof:name":"El Jazmin",
    "wof:placetype":"locality",
    "wof:population":15
},
  "geometry": {"coordinates":[-101.34305999999999,24.39528],"type":"Point"}
}