{
  "type": "Feature",
  "properties": {
    "gn:admin1_code":"12",
    "gn:admin2_code":"76.0",
    "gn:asciiname":"Palo Seco",
    "gn:country_code":"MX",
    "gn:dem":2390,
    "gn:feature_class":"P",
    "gn:feature_code":"PPL",
    "gn:name":"Palo Seco",
    "gn:population":177,
    "gn:timezone":"America/Mexico_City",
    "iso:country":"MX",
    "name:ceb_x_preferred":[
        "Palo Seco"
    ],
    "name:nld_x_preferred":[
        "Palo Seco"
    ],
    "name:spa_x_preferred":[
        "Palo Seco"
    ],
    "name:swe_x_preferred":[
        "Palo Seco"
    ],
    "wof:name":"Palo Seco",
    "wof:placetype":"locality",
    "wof:population":177
},
  "geometry": {"coordinates":[-98.84656,17.33701],"type":"Point"}
}