{
  "type": "Feature",
  "properties": {
    "gn:admin1_code":"20.0",
    "gn:asciiname":"Agua de Cal",
    "gn:country_code":"MX",
    "gn:dem":1013,
    "gn:feature_class":"P",
    "gn:feature_code":"PPL",
    "gn:name":"Agua de Cal",
    "gn:population":0,
    "gn:timezone":"America/Mexico_City",
    "iso:country":"MX",
    "name:spa_x_preferred":[
        "Agua de Cal"
    ],
    "wof:name":"Agua de Cal",
    "wof:placetype":"locality"
},
  "geometry": {"coordinates":[-96.69493,18.15087],"type":"Point"}
}