{
  "type": "Feature",
  "properties": {
    "gn:admin1_code":"7",
    "gn:admin2_code":"4.0",
    "gn:asciiname":"Guadalupe",
    "gn:country_code":"MX",
    "gn:dem":1999,
    "gn:feature_class":"P",
    "gn:feature_code":"PPL",
    "gn:name":"Guadalupe",
    "gn:population":0,
    "gn:timezone":"America/Monterrey",
    "iso:country":"MX",
    "name:spa_x_preferred":[
        "Guadalupe"
    ],
    "name:spa_x_variant":[
        "Rancho Guadalupe"
    ],
    "wof:name":"Guadalupe",
    "wof:placetype":"locality"
},
  "geometry": {"coordinates":[-100.7693,25.19977],"type":"Point"}
}