{
  "type": "Feature",
  "properties": {
    "gn:admin1_code":"16",
    "gn:admin2_code":"75.0",
    "gn:asciiname":"La Zarzamora",
    "gn:country_code":"MX",
    "gn:dem":1919,
    "gn:feature_class":"P",
    "gn:feature_code":"PPL",
    "gn:name":"La Zarzamora",
    "gn:population":876,
    "gn:timezone":"America/Mexico_City",
    "iso:country":"MX",
    "name:spa_x_preferred":[
        "La Zarzamora"
    ],
    "name:und_x_variant":[
        "Zarzamora"
    ],
    "wof:name":"La Zarzamora",
    "wof:placetype":"locality",
    "wof:population":876
},
  "geometry": {"coordinates":[-102.41361000000001,19.70278],"type":"Point"}
}