{
  "type": "Feature",
  "properties": {
    "gn:admin1_code":"12.0",
    "gn:admin2_code":"73.0",
    "gn:asciiname":"La Pedregosa",
    "gn:country_code":"MX",
    "gn:dem":912,
    "gn:feature_class":"P",
    "gn:feature_code":"PPL",
    "gn:name":"La Pedregosa",
    "gn:population":16,
    "gn:timezone":"America/Mexico_City",
    "iso:country":"MX",
    "name:spa_x_preferred":[
        "La Pedregosa"
    ],
    "wof:name":"La Pedregosa",
    "wof:placetype":"locality",
    "wof:population":16
},
  "geometry": {"coordinates":[-101.32055,18.25317],"type":"Point"}
}