{
  "type": "Feature",
  "properties": {
    "gn:admin1_code":"4.0",
    "gn:admin2_code":"3.0",
    "gn:asciiname":"Aguada del Pajaro",
    "gn:country_code":"MX",
    "gn:dem":9,
    "gn:feature_class":"P",
    "gn:feature_code":"PPL",
    "gn:name":"Aguada del P\u00e1jaro",
    "gn:population":0,
    "gn:timezone":"America/Merida",
    "iso:country":"MX",
    "name:spa_x_preferred":[
        "Aguada del P\u00e1jaro"
    ],
    "wof:name":"Aguada del Pajaro",
    "wof:placetype":"locality"
},
  "geometry": {"coordinates":[-91.03418000000001,18.77697],"type":"Point"}
}