{
  "type": "Feature",
  "properties": {
    "gn:admin1_code":"15.0",
    "gn:admin2_code":"78.0",
    "gn:asciiname":"Potrero de Abajo (Colonia Guadalupe)",
    "gn:country_code":"MX",
    "gn:dem":1377,
    "gn:feature_class":"P",
    "gn:feature_code":"PPL",
    "gn:name":"Potrero de Abajo (Colonia Guadalupe)",
    "gn:population":75,
    "gn:timezone":"America/Mexico_City",
    "iso:country":"MX",
    "wof:name":"Potrero de Abajo (Colonia Guadalupe)",
    "wof:placetype":"locality",
    "wof:population":75
},
  "geometry": {"coordinates":[-100.3455,19.18251],"type":"Point"}
}