{
  "type": "Feature",
  "properties": {
    "gn:admin1_code":"6",
    "gn:admin2_code":"8.0",
    "gn:asciiname":"El Chinal",
    "gn:country_code":"MX",
    "gn:dem":2102,
    "gn:feature_class":"P",
    "gn:feature_code":"PPL",
    "gn:name":"El Chinal",
    "gn:population":7,
    "gn:timezone":"America/Chihuahua",
    "iso:country":"MX",
    "wof:name":"El Chinal",
    "wof:placetype":"locality",
    "wof:population":7
},
  "geometry": {"coordinates":[-107.78713,27.10993],"type":"Point"}
}