{
  "type": "Feature",
  "properties": {
    "gn:admin1_code":"5",
    "gn:admin2_code":"44.0",
    "gn:asciiname":"Chigton",
    "gn:country_code":"MX",
    "gn:dem":1098,
    "gn:feature_class":"P",
    "gn:feature_code":"PPL",
    "gn:name":"Chigt\u00f3n",
    "gn:population":0,
    "gn:timezone":"America/Mexico_City",
    "iso:country":"MX",
    "name:spa_x_preferred":[
        "Chigt\u00f3n"
    ],
    "name:und_x_variant":[
        "Chugton"
    ],
    "wof:name":"Chigton",
    "wof:placetype":"locality"
},
  "geometry": {"coordinates":[-92.87309,16.84371],"type":"Point"}
}