{
  "type": "Feature",
  "properties": {
    "gn:admin1_code":"26",
    "gn:admin2_code":"14.0",
    "gn:asciiname":"El Bagote",
    "gn:country_code":"MX",
    "gn:dem":565,
    "gn:feature_class":"P",
    "gn:feature_code":"PPL",
    "gn:name":"El Bagote",
    "gn:population":4,
    "gn:timezone":"America/Hermosillo",
    "iso:country":"MX",
    "name:spa_x_preferred":[
        "El Bagote"
    ],
    "wof:name":"El Bagote",
    "wof:placetype":"locality",
    "wof:population":4
},
  "geometry": {"coordinates":[-110.15778,29.70139],"type":"Point"}
}