{
  "type": "Feature",
  "properties": {
    "gn:admin1_code":"14",
    "gn:admin2_code":"31.0",
    "gn:asciiname":"La Uva",
    "gn:country_code":"MX",
    "gn:dem":1741,
    "gn:feature_class":"P",
    "gn:feature_code":"PPL",
    "gn:name":"La Uva",
    "gn:population":0,
    "gn:timezone":"America/Mexico_City",
    "iso:country":"MX",
    "name:spa_x_preferred":[
        "La Uva"
    ],
    "wof:name":"La Uva",
    "wof:placetype":"locality"
},
  "geometry": {"coordinates":[-103.63576,21.83456],"type":"Point"}
}