{
  "type": "Feature",
  "properties": {
    "gn:admin1_code":"6",
    "gn:admin2_code":"29",
    "gn:asciiname":"Mesa de San Rafael",
    "gn:country_code":"MX",
    "gn:dem":2641,
    "gn:feature_class":"P",
    "gn:feature_code":"PPL",
    "gn:name":"Mesa de San Rafael",
    "gn:population":16,
    "gn:timezone":"America/Chihuahua",
    "iso:country":"MX",
    "wof:name":"Mesa de San Rafael",
    "wof:placetype":"locality",
    "wof:population":16
},
  "geometry": {"coordinates":[-106.60041,26.19412],"type":"Point"}
}