{
  "type": "Feature",
  "properties": {
    "gn:admin1_code":"24.0",
    "gn:admin2_code":"34.0",
    "gn:asciiname":"Las Trojas",
    "gn:country_code":"MX",
    "gn:dem":32,
    "gn:feature_class":"P",
    "gn:feature_code":"PPL",
    "gn:name":"Las Trojas",
    "gn:population":5,
    "gn:timezone":"America/Mexico_City",
    "iso:country":"MX",
    "name:spa_x_preferred":[
        "Las Trojas"
    ],
    "wof:name":"Las Trojas",
    "wof:placetype":"locality",
    "wof:population":5
},
  "geometry": {"coordinates":[-98.56444,21.70056],"type":"Point"}
}