{
  "type": "Feature",
  "properties": {
    "gn:admin1_code":"29",
    "gn:admin2_code":"30.0",
    "gn:asciiname":"Rancho Tepeyahualco",
    "gn:country_code":"MX",
    "gn:dem":2529,
    "gn:feature_class":"P",
    "gn:feature_code":"PPL",
    "gn:name":"Rancho Tepeyahualco",
    "gn:population":3,
    "gn:timezone":"America/Mexico_City",
    "iso:country":"MX",
    "wof:name":"Rancho Tepeyahualco",
    "wof:placetype":"locality",
    "wof:population":3
},
  "geometry": {"coordinates":[-97.93714,19.43792],"type":"Point"}
}