{
  "type": "Feature",
  "properties": {
    "gn:admin1_code":"7",
    "gn:admin2_code":"24.0",
    "gn:asciiname":"La Guadiana",
    "gn:country_code":"MX",
    "gn:dem":1111,
    "gn:feature_class":"P",
    "gn:feature_code":"PPL",
    "gn:name":"La Guadiana",
    "gn:population":4,
    "gn:timezone":"America/Monterrey",
    "iso:country":"MX",
    "name:spa_x_preferred":[
        "La Guadiana"
    ],
    "wof:name":"La Guadiana",
    "wof:placetype":"locality",
    "wof:population":4
},
  "geometry": {"coordinates":[-102.30562,25.75334],"type":"Point"}
}