{
  "type": "Feature",
  "properties": {
    "gn:admin1_code":"5",
    "gn:admin2_code":"118",
    "gn:asciiname":"La Sultana",
    "gn:country_code":"MX",
    "gn:dem":827,
    "gn:feature_class":"P",
    "gn:feature_code":"PPL",
    "gn:name":"La Sultana",
    "gn:population":19,
    "gn:timezone":"America/Mexico_City",
    "iso:country":"MX",
    "wof:name":"La Sultana",
    "wof:placetype":"locality",
    "wof:population":19
},
  "geometry": {"coordinates":[-92.79667000000001,17.17389],"type":"Point"}
}