{
  "type": "Feature",
  "properties": {
    "gn:admin1_code":"24.0",
    "gn:admin2_code":"32.0",
    "gn:asciiname":"Rincon de San Jeronimo",
    "gn:country_code":"MX",
    "gn:dem":2154,
    "gn:feature_class":"P",
    "gn:feature_code":"PPL",
    "gn:name":"Rinc\u00f3n de San Jer\u00f3nimo",
    "gn:population":0,
    "gn:timezone":"America/Mexico_City",
    "iso:country":"MX",
    "name:spa_x_preferred":[
        "Rinc\u00f3n de San Jer\u00f3nimo"
    ],
    "wof:name":"Rincon de San Jeronimo",
    "wof:placetype":"locality"
},
  "geometry": {"coordinates":[-100.55923,21.88478],"type":"Point"}
}