{
  "type": "Feature",
  "properties": {
    "gn:admin1_code":"22",
    "gn:admin2_code":"14.0",
    "gn:asciiname":"Rancho Bellavista [Fraccionamiento]",
    "gn:country_code":"MX",
    "gn:dem":1798,
    "gn:feature_class":"P",
    "gn:feature_code":"PPL",
    "gn:name":"Rancho Bellavista [Fraccionamiento]",
    "gn:population":1705,
    "gn:timezone":"America/Mexico_City",
    "iso:country":"MX",
    "wof:name":"Rancho Bellavista [Fraccionamiento]",
    "wof:placetype":"locality",
    "wof:population":1705
},
  "geometry": {"coordinates":[-100.44972,20.60667],"type":"Point"}
}