{
  "type": "Feature",
  "properties": {
    "gn:admin1_code":"24",
    "gn:admin2_code":"6.0",
    "gn:asciiname":"Puerto de la Cruz",
    "gn:country_code":"MX",
    "gn:dem":2679,
    "gn:feature_class":"P",
    "gn:feature_code":"PPL",
    "gn:name":"Puerto de la Cruz",
    "gn:population":0,
    "gn:timezone":"America/Mexico_City",
    "iso:country":"MX",
    "name:ara_x_preferred":[
        "\u0628\u0648\u064a\u0631\u062a\u0648 \u062f\u064a \u0644\u0627 \u0643\u0631\u0648\u062b"
    ],
    "name:azb_x_preferred":[
        "\u067e\u0648\u0626\u0631\u062a\u0648 \u062f \u0644\u0627 \u06a9\u0631\u0648\u0633"
    ],
    "name:bul_x_preferred":[
        "\u041f\u0443\u0435\u0440\u0442\u043e \u0434\u0435 \u043b\u0430 \u041a\u0440\u0443\u0441"
    ],
    "name:fas_x_preferred":[
        "\u067e\u0648\u0626\u0631\u062a\u0648 \u062f \u0644\u0627 \u06a9\u0631\u0648\u0633"
    ],
    "name:spa_x_preferred":[
        "Puerto de la Cruz"
    ],
    "name:srp_x_preferred":[
        "\u041f\u0443\u0435\u0440\u0442\u043e \u0434\u0435 \u043b\u0430 \u041a\u0440\u0443\u0437"
    ],
    "wof:name":"Puerto de la Cruz",
    "wof:placetype":"locality"
},
  "geometry": {"coordinates":[-100.87379,23.56749],"type":"Point"}
}