{
  "type": "Feature",
  "properties": {
    "gn:admin1_code":"24",
    "gn:admin2_code":"6.0",
    "gn:asciiname":"Puerto de la Cruz",
    "gn:country_code":"MX",
    "gn:dem":2679,
    "gn:feature_class":"P",
    "gn:feature_code":"PPL",
    "gn:name":"Puerto de la Cruz",
    "gn:population":0,
    "gn:timezone":"America/Mexico_City",
    "iso:country":"MX",
    "name:spa_x_preferred":[
        "Puerto de la Cruz"
    ],
    "wof:name":"Puerto de la Cruz",
    "wof:placetype":"locality"
},
  "geometry": {"coordinates":[-100.87379,23.56749],"type":"Point"}
}