{
  "type": "Feature",
  "properties": {
    "gn:admin1_code":"30",
    "gn:admin2_code":"202",
    "gn:asciiname":"Ayojcuantla",
    "gn:country_code":"MX",
    "gn:dem":1104,
    "gn:feature_class":"P",
    "gn:feature_code":"PPL",
    "gn:name":"Ayojcuantla",
    "gn:population":20,
    "gn:timezone":"America/Mexico_City",
    "iso:country":"MX",
    "wof:name":"Ayojcuantla",
    "wof:placetype":"locality",
    "wof:population":20
},
  "geometry": {"coordinates":[-98.40861,20.7425],"type":"Point"}
}