{
  "type": "Feature",
  "properties": {
    "gn:admin1_code":"11",
    "gn:admin2_code":"42.0",
    "gn:asciiname":"Granja Francisco Jaramillo",
    "gn:country_code":"MX",
    "gn:dem":1757,
    "gn:feature_class":"P",
    "gn:feature_code":"PPL",
    "gn:name":"Granja Francisco Jaramillo",
    "gn:population":5,
    "gn:timezone":"America/Mexico_City",
    "iso:country":"MX",
    "wof:name":"Granja Francisco Jaramillo",
    "wof:placetype":"locality",
    "wof:population":5
},
  "geometry": {"coordinates":[-101.33694,20.51472],"type":"Point"}
}