{
  "type": "Feature",
  "properties": {
    "gn:admin1_code":"19",
    "gn:admin2_code":"5.0",
    "gn:asciiname":"Diez de Marzo",
    "gn:country_code":"MX",
    "gn:dem":144,
    "gn:feature_class":"P",
    "gn:feature_code":"PPL",
    "gn:name":"Diez de Marzo",
    "gn:population":0,
    "gn:timezone":"America/Monterrey",
    "iso:country":"MX",
    "name:spa_x_preferred":[
        "Diez de Marzo"
    ],
    "name:und_x_variant":[
        "Rancho Diez de Marzo"
    ],
    "wof:name":"Diez de Marzo",
    "wof:placetype":"locality"
},
  "geometry": {"coordinates":[-99.71984999999999,27.01858],"type":"Point"}
}