{
  "type": "Feature",
  "properties": {
    "gn:admin1_code":"20.0",
    "gn:asciiname":"Loma Quemada",
    "gn:country_code":"MX",
    "gn:dem":1467,
    "gn:feature_class":"P",
    "gn:feature_code":"PPL",
    "gn:name":"Loma Quemada",
    "gn:population":0,
    "gn:timezone":"America/Mexico_City",
    "iso:country":"MX",
    "name:spa_x_preferred":[
        "Loma Quemada"
    ],
    "wof:name":"Loma Quemada",
    "wof:placetype":"locality"
},
  "geometry": {"coordinates":[-96.90045000000001,18.14482000000001],"type":"Point"}
}