{
  "type": "Feature",
  "properties": {
    "gn:admin1_code":"26.0",
    "gn:admin2_code":"3.0",
    "gn:asciiname":"Jusacucha",
    "gn:cc2":"MX",
    "gn:country_code":"MX",
    "gn:dem":304,
    "gn:feature_class":"P",
    "gn:feature_code":"PPL",
    "gn:name":"Jusacucha",
    "gn:population":0,
    "gn:timezone":"America/Hermosillo",
    "iso:country":"MX",
    "name:und_x_variant":[
        "Rancho Jusacucsa",
        "Jusacucha"
    ],
    "wof:name":"Jusacucha",
    "wof:placetype":"locality"
},
  "geometry": {"coordinates":[-109.09999999999999,26.98333],"type":"Point"}
}