{
  "type": "Feature",
  "properties": {
    "gn:gn_country":"MX",
    "gn:gn_fcode":"PPL",
    "gn:gn_pop":0,
    "iso:country":"MX",
    "name:afr_x_preferred":[
        "Xochimilco"
    ],
    "name:cat_x_preferred":[
        "Xochimilco"
    ],
    "name:ces_x_preferred":[
        "Xochimilco"
    ],
    "name:dan_x_preferred":[
        "Xochimilco"
    ],
    "name:deu_x_preferred":[
        "Xochimilco"
    ],
    "name:epo_x_preferred":[
        "\u015co\u0109imilko"
    ],
    "name:eus_x_preferred":[
        "Xochimilco"
    ],
    "name:fin_x_preferred":[
        "Xochimilco"
    ],
    "name:fra_x_preferred":[
        "Xochimilco"
    ],
    "name:gle_x_preferred":[
        "Xochimilco"
    ],
    "name:glg_x_preferred":[
        "Xochimilco"
    ],
    "name:hrv_x_preferred":[
        "Xochimilco"
    ],
    "name:hun_x_preferred":[
        "Xochimilco"
    ],
    "name:hye_x_preferred":[
        "\u054d\u0578\u0579\u056b\u0574\u056b\u056c\u056f\u0578"
    ],
    "name:ind_x_preferred":[
        "Xochimilco"
    ],
    "name:ita_x_preferred":[
        "Xochimilco"
    ],
    "name:jpn_x_preferred":[
        "\u30bd\u30c1\u30df\u30eb\u30b3"
    ],
    "name:kat_x_preferred":[
        "\u10e8\u10dd\u10e9\u10d8\u10db\u10d8\u10da\u10d9\u10dd"
    ],
    "name:kor_x_preferred":[
        "\uc18c\uce58\ubc00\ucf54"
    ],
    "name:lad_x_preferred":[
        "Xochimilco"
    ],
    "name:lat_x_preferred":[
        "Xochimilco"
    ],
    "name:nah_x_preferred":[
        "Xochimilco"
    ],
    "name:nld_x_preferred":[
        "Xochimilco"
    ],
    "name:nor_x_preferred":[
        "Xochimilco"
    ],
    "name:oci_x_preferred":[
        "Xochimilco"
    ],
    "name:pol_x_preferred":[
        "Xochimilco"
    ],
    "name:por_x_preferred":[
        "Xochimilco"
    ],
    "name:ron_x_preferred":[
        "Xochimilco"
    ],
    "name:rus_x_preferred":[
        "\u0421\u043e\u0447\u0438\u043c\u0438\u043b\u044c\u043a\u043e"
    ],
    "name:sco_x_preferred":[
        "Xochimilco"
    ],
    "name:spa_x_preferred":[
        "Xochimilco"
    ],
    "name:srp_x_preferred":[
        "\u0421\u043e\u0447\u0438\u043c\u0438\u043b\u043a\u043e"
    ],
    "name:stq_x_preferred":[
        "X\u014dchim\u012blco"
    ],
    "name:swe_x_preferred":[
        "Xochimilco"
    ],
    "name:tur_x_preferred":[
        "Xochimilco"
    ],
    "name:ukr_x_preferred":[
        "\u0421\u043e\u0448\u0438\u043c\u0456\u043b\u043a\u043e"
    ],
    "name:unk_x_variant":[
        "Ejido Xochimilco"
    ],
    "name:vie_x_preferred":[
        "Xochimilco"
    ],
    "name:war_x_preferred":[
        "Xochimilco"
    ],
    "name:zho_x_preferred":[
        "\u7d22\u5947\u7c73\u5c14\u79d1"
    ],
    "qs_pg:aaroncc":"MX",
    "qs_pg:gn_country":"MX",
    "qs_pg:gn_fcode":"PPL",
    "qs_pg:gn_pop":0,
    "qs_pg:name":"Xochimilco",
    "qs_pg:name_adm0":"M\u00e9xico",
    "qs_pg:name_adm1":"Baja California",
    "qs_pg:photos":1,
    "qs_pg:photos_1k":1,
    "qs_pg:photos_9k":1,
    "qs_pg:photos_9r":1,
    "qs_pg:photos_all":1,
    "qs_pg:photos_sr":1,
    "qs_pg:pop_sr":0,
    "qs_pg:qs_pg_placetype":"neighbourhood",
    "qs_pg:qs_pg_placetype_gp":"Suburb",
    "qs_pg:woe_adm0":23424900,
    "woe:adm0_id":23424900,
    "woe:name_adm0":"M\u00e9xico",
    "woe:name_adm1":"Baja California",
    "woe:placetype":"Suburb",
    "wof:name":"Xochimilco",
    "wof:placetype":"neighbourhood"
},
  "geometry": {"coordinates":[-115.48403,32.58403],"type":"Point"}
}