{
  "type": "Feature",
  "properties": {
    "gn:admin1_code":"7",
    "gn:admin2_code":"36.0",
    "gn:asciiname":"Paredones",
    "gn:country_code":"MX",
    "gn:dem":1194,
    "gn:feature_class":"P",
    "gn:feature_code":"PPL",
    "gn:name":"Paredones",
    "gn:population":42,
    "gn:timezone":"America/Monterrey",
    "iso:country":"MX",
    "wof:name":"Paredones",
    "wof:placetype":"locality",
    "wof:population":42
},
  "geometry": {"coordinates":[-103.44579,25.35389],"type":"Point"}
}