{
  "type": "Feature",
  "properties": {
    "gn:admin1_code":"18.0",
    "gn:admin2_code":"4.0",
    "gn:asciiname":"El Huisapolero",
    "gn:country_code":"MX",
    "gn:dem":553,
    "gn:feature_class":"P",
    "gn:feature_code":"PPL",
    "gn:name":"El Huisapolero",
    "gn:population":0,
    "gn:timezone":"America/Mazatlan",
    "iso:country":"MX",
    "name:spa_x_preferred":[
        "El Huisapolero"
    ],
    "wof:name":"El Huisapolero",
    "wof:placetype":"locality"
},
  "geometry": {"coordinates":[-105.01262,21.14076],"type":"Point"}
}