{
  "type": "Feature",
  "properties": {
    "gn:admin1_code":"5",
    "gn:admin2_code":"68.0",
    "gn:asciiname":"Esquipulas",
    "gn:country_code":"MX",
    "gn:dem":130,
    "gn:feature_class":"P",
    "gn:feature_code":"PPL",
    "gn:name":"Esquipulas",
    "gn:population":0,
    "gn:timezone":"America/Mexico_City",
    "iso:country":"MX",
    "wof:name":"Esquipulas",
    "wof:placetype":"locality"
},
  "geometry": {"coordinates":[-93.15000000000001,17.53333],"type":"Point"}
}