{
  "type": "Feature",
  "properties": {
    "gn:admin1_code":"14.0",
    "gn:admin2_code":"6.0",
    "gn:asciiname":"Arroyo Hondo",
    "gn:country_code":"MX",
    "gn:dem":1226,
    "gn:feature_class":"P",
    "gn:feature_code":"PPL",
    "gn:name":"Arroyo Hondo",
    "gn:population":0,
    "gn:timezone":"America/Mexico_City",
    "iso:country":"MX",
    "name:ceb_x_preferred":[
        "Arroyo Hondo"
    ],
    "name:spa_x_preferred":[
        "Arroyo Hondo"
    ],
    "name:swe_x_preferred":[
        "Arroyo Hondo"
    ],
    "wof:name":"Arroyo Hondo",
    "wof:placetype":"locality"
},
  "geometry": {"coordinates":[-104.09807000000001,20.56272],"type":"Point"}
}