{
  "type": "Feature",
  "properties": {
    "gn:admin1_code":"26",
    "gn:admin2_code":"34.0",
    "gn:asciiname":"La Bellota",
    "gn:country_code":"MX",
    "gn:dem":739,
    "gn:feature_class":"P",
    "gn:feature_code":"PPL",
    "gn:name":"La Bellota",
    "gn:population":0,
    "gn:timezone":"America/Hermosillo",
    "iso:country":"MX",
    "name:spa_x_preferred":[
        "La Bellota"
    ],
    "wof:name":"La Bellota",
    "wof:placetype":"locality"
},
  "geometry": {"coordinates":[-110.36816,29.91686],"type":"Point"}
}