{
  "type": "Feature",
  "properties": {
    "gn:admin1_code":"28",
    "gn:admin2_code":"27.0",
    "gn:asciiname":"Los Flores",
    "gn:country_code":"MX",
    "gn:dem":129,
    "gn:feature_class":"P",
    "gn:feature_code":"PPL",
    "gn:name":"Los Flores",
    "gn:population":0,
    "gn:timezone":"America/Matamoros",
    "iso:country":"MX",
    "name:und_x_variant":[
        "Las Flores",
        "Los Flores"
    ],
    "wof:name":"Los Flores",
    "wof:placetype":"locality"
},
  "geometry": {"coordinates":[-99.58445,27.61863],"type":"Point"}
}