{
  "type": "Feature",
  "properties": {
    "gn:admin1_code":"6.0",
    "gn:admin2_code":"29.0",
    "gn:asciiname":"La Mesa del Trigo",
    "gn:country_code":"MX",
    "gn:dem":1562,
    "gn:feature_class":"P",
    "gn:feature_code":"PPL",
    "gn:name":"La Mesa del Trigo",
    "gn:population":0,
    "gn:timezone":"America/Chihuahua",
    "iso:country":"MX",
    "name:spa_x_preferred":[
        "La Mesa del Trigo"
    ],
    "wof:name":"La Mesa del Trigo",
    "wof:placetype":"locality"
},
  "geometry": {"coordinates":[-107.12967,25.99358],"type":"Point"}
}