{
  "type": "Feature",
  "properties": {
    "gn:admin1_code":"15",
    "gn:admin2_code":"51.0",
    "gn:asciiname":"Colonia Buenavista",
    "gn:country_code":"MX",
    "gn:dem":2775,
    "gn:feature_class":"P",
    "gn:feature_code":"PPL",
    "gn:name":"Colonia Buenavista",
    "gn:population":293,
    "gn:timezone":"America/Mexico_City",
    "iso:country":"MX",
    "wof:name":"Colonia Buenavista",
    "wof:placetype":"locality",
    "wof:population":293
},
  "geometry": {"coordinates":[-99.45162000000001,19.35783],"type":"Point"}
}