{
  "type": "Feature",
  "properties": {
    "gn:admin1_code":"5",
    "gn:admin2_code":"10",
    "gn:asciiname":"Pena Flor",
    "gn:country_code":"MX",
    "gn:dem":1956,
    "gn:feature_class":"P",
    "gn:feature_code":"PPL",
    "gn:name":"Pe\u00f1a Flor",
    "gn:population":22,
    "gn:timezone":"America/Mexico_City",
    "iso:country":"MX",
    "name:und_x_variant":[
        "Pe\u00f1a Flor"
    ],
    "wof:name":"Pena Flor",
    "wof:placetype":"locality",
    "wof:population":22
},
  "geometry": {"coordinates":[-92.14833,15.44194],"type":"Point"}
}