{
  "type": "Feature",
  "properties": {
    "gn:admin1_code":"5",
    "gn:admin2_code":"59.0",
    "gn:asciiname":"Nuevo Centro Lindavista",
    "gn:country_code":"MX",
    "gn:dem":1376,
    "gn:feature_class":"P",
    "gn:feature_code":"PPL",
    "gn:name":"Nuevo Centro Lindavista",
    "gn:population":102,
    "gn:timezone":"America/Mexico_City",
    "iso:country":"MX",
    "wof:name":"Nuevo Centro Lindavista",
    "wof:placetype":"locality",
    "wof:population":102
},
  "geometry": {"coordinates":[-92.17083,16.86277999999999],"type":"Point"}
}