{
  "type": "Feature",
  "properties": {
    "gn:admin1_code":"11",
    "gn:admin2_code":"17",
    "gn:asciiname":"Granja el Rosario Dos",
    "gn:country_code":"MX",
    "gn:dem":1727,
    "gn:feature_class":"P",
    "gn:feature_code":"PPL",
    "gn:name":"Granja el Rosario Dos",
    "gn:population":29,
    "gn:timezone":"America/Mexico_City",
    "iso:country":"MX",
    "wof:name":"Granja el Rosario Dos",
    "wof:placetype":"locality",
    "wof:population":29
},
  "geometry": {"coordinates":[-101.43583,20.64917],"type":"Point"}
}