{
  "type": "Feature",
  "properties": {
    "gn:admin1_code":"7.0",
    "gn:admin2_code":"11.0",
    "gn:asciiname":"El Nogal",
    "gn:country_code":"MX",
    "gn:dem":1685,
    "gn:feature_class":"P",
    "gn:feature_code":"PPL",
    "gn:name":"El Nogal",
    "gn:population":0,
    "gn:timezone":"America/Monterrey",
    "iso:country":"MX",
    "wof:name":"El Nogal",
    "wof:placetype":"locality"
},
  "geometry": {"coordinates":[-101.42778,25.29424],"type":"Point"}
}