{
  "type": "Feature",
  "properties": {
    "gn:admin1_code":"16",
    "gn:admin2_code":"97.0",
    "gn:asciiname":"Las Pelonas",
    "gn:country_code":"MX",
    "gn:dem":906,
    "gn:feature_class":"P",
    "gn:feature_code":"PPL",
    "gn:name":"Las Pelonas",
    "gn:population":0,
    "gn:timezone":"America/Mexico_City",
    "iso:country":"MX",
    "name:spa_x_preferred":[
        "Las Pelonas"
    ],
    "wof:name":"Las Pelonas",
    "wof:placetype":"locality"
},
  "geometry": {"coordinates":[-101.47875999999999,19.01129],"type":"Point"}
}