{
  "type": "Feature",
  "properties": {
    "gn:admin1_code":"26",
    "gn:admin2_code":"42.0",
    "gn:asciiname":"Panteon de Capuquiza",
    "gn:country_code":"MX",
    "gn:dem":35,
    "gn:feature_class":"P",
    "gn:feature_code":"PPL",
    "gn:name":"Pante\u00f3n de Capuquiza",
    "gn:population":0,
    "gn:timezone":"America/Hermosillo",
    "iso:country":"MX",
    "wof:name":"Panteon de Capuquiza",
    "wof:placetype":"locality"
},
  "geometry": {"coordinates":[-109.45,27.11667000000001],"type":"Point"}
}