{
  "type": "Feature",
  "properties": {
    "gn:admin1_code":"16.0",
    "gn:admin2_code":"81.0",
    "gn:asciiname":"Agua Zarca",
    "gn:country_code":"MX",
    "gn:dem":1961,
    "gn:feature_class":"P",
    "gn:feature_code":"PPL",
    "gn:name":"Agua Zarca",
    "gn:population":0,
    "gn:timezone":"America/Mexico_City",
    "iso:country":"MX",
    "name:spa_x_preferred":[
        "Agua Zarca"
    ],
    "wof:name":"Agua Zarca",
    "wof:placetype":"locality"
},
  "geometry": {"coordinates":[-100.36629000000001,19.28264],"type":"Point"}
}