{
  "type": "Feature",
  "properties": {
    "gn:admin1_code":"19.0",
    "gn:admin2_code":"17.0",
    "gn:asciiname":"El Anhelo",
    "gn:country_code":"MX",
    "gn:dem":2345,
    "gn:feature_class":"P",
    "gn:feature_code":"PPL",
    "gn:name":"El Anhelo",
    "gn:population":0,
    "gn:timezone":"America/Monterrey",
    "iso:country":"MX",
    "name:spa_x_preferred":[
        "El Anhelo"
    ],
    "wof:name":"El Anhelo",
    "wof:placetype":"locality"
},
  "geometry": {"coordinates":[-100.41628,25.11076],"type":"Point"}
}