{
  "type": "Feature",
  "properties": {
    "gn:admin1_code":"26.0",
    "gn:admin2_code":"12.0",
    "gn:asciiname":"Campo Uno Ciento Tres",
    "gn:country_code":"MX",
    "gn:dem":9,
    "gn:feature_class":"P",
    "gn:feature_code":"PPL",
    "gn:name":"Campo Uno Ciento Tres",
    "gn:population":0,
    "gn:timezone":"America/Hermosillo",
    "iso:country":"MX",
    "wof:name":"Campo Uno Ciento Tres",
    "wof:placetype":"locality"
},
  "geometry": {"coordinates":[-110.15000000000001,27.35],"type":"Point"}
}