{
  "type": "Feature",
  "properties": {
    "gn:admin1_code":"30",
    "gn:admin2_code":"175",
    "gn:asciiname":"Graciela Guadalupe Lopez Juarez",
    "gn:country_code":"MX",
    "gn:dem":66,
    "gn:feature_class":"P",
    "gn:feature_code":"PPL",
    "gn:name":"Graciela Guadalupe L\u00f3pez Ju\u00e1rez",
    "gn:population":13,
    "gn:timezone":"America/Mexico_City",
    "iso:country":"MX",
    "name:und_x_variant":[
        "Graciela Guadalupe L\u00f3pez Ju\u00e1rez"
    ],
    "wof:name":"Graciela Guadalupe Lopez Juarez",
    "wof:placetype":"locality",
    "wof:population":13
},
  "geometry": {"coordinates":[-97.51889,20.55083],"type":"Point"}
}