{
  "type": "Feature",
  "properties": {
    "gn:admin1_code":"21",
    "gn:admin2_code":"157.0",
    "gn:asciiname":"San Jose las Calaveras",
    "gn:country_code":"MX",
    "gn:dem":1257,
    "gn:feature_class":"P",
    "gn:feature_code":"PPL",
    "gn:name":"San Jos\u00e9 las Calaveras",
    "gn:population":0,
    "gn:timezone":"America/Mexico_City",
    "iso:country":"MX",
    "name:spa_x_preferred":[
        "San Jos\u00e9 las Calaveras"
    ],
    "name:spa_x_variant":[
        "Las Calaveras"
    ],
    "wof:name":"San Jose las Calaveras",
    "wof:placetype":"locality"
},
  "geometry": {"coordinates":[-98.19426,18.30015],"type":"Point"}
}