{
  "type": "Feature",
  "properties": {
    "gn:admin1_code":"28.0",
    "gn:admin2_code":"4.0",
    "gn:asciiname":"El Pachoncito",
    "gn:country_code":"MX",
    "gn:dem":188,
    "gn:feature_class":"P",
    "gn:feature_code":"PPL",
    "gn:name":"El Pachoncito",
    "gn:population":0,
    "gn:timezone":"America/Monterrey",
    "iso:country":"MX",
    "name:spa_x_preferred":[
        "El Pachoncito"
    ],
    "wof:name":"El Pachoncito",
    "wof:placetype":"locality"
},
  "geometry": {"coordinates":[-99.14427000000001,22.67845],"type":"Point"}
}