{
  "type": "Feature",
  "properties": {
    "gn:admin1_code":"14",
    "gn:admin2_code":"33",
    "gn:asciiname":"Los Sauces",
    "gn:country_code":"MX",
    "gn:dem":1683,
    "gn:feature_class":"P",
    "gn:feature_code":"PPL",
    "gn:name":"Los Sauces",
    "gn:population":51,
    "gn:timezone":"America/Mexico_City",
    "iso:country":"MX",
    "wof:name":"Los Sauces",
    "wof:placetype":"locality",
    "wof:population":51
},
  "geometry": {"coordinates":[-102.18416999999999,20.42889],"type":"Point"}
}