{
  "type": "Feature",
  "properties": {
    "gn:admin1_code":"19",
    "gn:admin2_code":"11.0",
    "gn:asciiname":"Santa Francisca",
    "gn:country_code":"MX",
    "gn:dem":832,
    "gn:feature_class":"P",
    "gn:feature_code":"PPL",
    "gn:name":"Santa Francisca",
    "gn:population":3,
    "gn:timezone":"America/Monterrey",
    "iso:country":"MX",
    "wof:name":"Santa Francisca",
    "wof:placetype":"locality",
    "wof:population":3
},
  "geometry": {"coordinates":[-99.89976,26.05394],"type":"Point"}
}