{
  "type": "Feature",
  "properties": {
    "gn:admin1_code":"7",
    "gn:admin2_code":"20.0",
    "gn:asciiname":"Los Lirios",
    "gn:country_code":"MX",
    "gn:dem":1261,
    "gn:feature_class":"P",
    "gn:feature_code":"PPL",
    "gn:name":"Los Lirios",
    "gn:population":0,
    "gn:timezone":"America/Monterrey",
    "iso:country":"MX",
    "wof:name":"Los Lirios",
    "wof:placetype":"locality"
},
  "geometry": {"coordinates":[-102.42515,28.79495],"type":"Point"}
}