{
  "type": "Feature",
  "properties": {
    "gn:admin1_code":"6",
    "gn:admin2_code":"65",
    "gn:asciiname":"La Bolsa",
    "gn:country_code":"MX",
    "gn:dem":1322,
    "gn:feature_class":"P",
    "gn:feature_code":"PPL",
    "gn:name":"La Bolsa",
    "gn:population":34,
    "gn:timezone":"America/Chihuahua",
    "iso:country":"MX",
    "wof:name":"La Bolsa",
    "wof:placetype":"locality",
    "wof:population":34
},
  "geometry": {"coordinates":[-107.97769,27.07243],"type":"Point"}
}