{
  "type": "Feature",
  "properties": {
    "gn:admin1_code":"32",
    "gn:admin2_code":"52",
    "gn:asciiname":"Rancheria de Juan Alvarez",
    "gn:country_code":"MX",
    "gn:dem":2194,
    "gn:feature_class":"P",
    "gn:feature_code":"PPL",
    "gn:name":"Rancher\u00eda de Juan \u00c1lvarez",
    "gn:population":14,
    "gn:timezone":"America/Mexico_City",
    "iso:country":"MX",
    "name:und_x_variant":[
        "Rancher\u00eda de Juan \u00c1lvarez"
    ],
    "wof:name":"Rancheria de Juan Alvarez",
    "wof:placetype":"locality",
    "wof:population":14
},
  "geometry": {"coordinates":[-101.87833000000001,22.14472],"type":"Point"}
}