{
  "type": "Feature",
  "properties": {
    "gn:admin1_code":"12",
    "gn:admin2_code":"58.0",
    "gn:asciiname":"Villa de Ayala",
    "gn:country_code":"MX",
    "gn:dem":1566,
    "gn:feature_class":"P",
    "gn:feature_code":"PPL",
    "gn:name":"Villa de Ayala",
    "gn:population":73,
    "gn:timezone":"America/Mexico_City",
    "iso:country":"MX",
    "wof:name":"Villa de Ayala",
    "wof:placetype":"locality",
    "wof:population":73
},
  "geometry": {"coordinates":[-100.03005,18.39715],"type":"Point"}
}