{
  "type": "Feature",
  "properties": {
    "gn:admin1_code":"20.0",
    "gn:admin2_code":"450.0",
    "gn:asciiname":"El Ciruelo",
    "gn:country_code":"MX",
    "gn:dem":1229,
    "gn:feature_class":"P",
    "gn:feature_code":"PPL",
    "gn:name":"El Ciruelo",
    "gn:population":0,
    "gn:timezone":"America/Mexico_City",
    "iso:country":"MX",
    "name:ita_x_preferred":[
        "El Ciruelo"
    ],
    "name:spa_x_preferred":[
        "El Ciruelo"
    ],
    "name:zho_x_preferred":[
        "\u57c3\u723e\u897f\u9b6f\u57c3\u6d1b"
    ],
    "wof:name":"El Ciruelo",
    "wof:placetype":"locality"
},
  "geometry": {"coordinates":[-97.46225,16.66217],"type":"Point"}
}