{
  "type": "Feature",
  "properties": {
    "gn:admin1_code":"20",
    "gn:admin2_code":"171.0",
    "gn:asciiname":"Llano de Arnica",
    "gn:country_code":"MX",
    "gn:dem":957,
    "gn:feature_class":"P",
    "gn:feature_code":"PPL",
    "gn:name":"Llano de \u00c1rnica",
    "gn:population":208,
    "gn:timezone":"America/Mexico_City",
    "iso:country":"MX",
    "name:und_x_variant":[
        "Llano de \u00c1rnica"
    ],
    "wof:name":"Llano de Arnica",
    "wof:placetype":"locality",
    "wof:population":208
},
  "geometry": {"coordinates":[-96.73583000000001,18.13083],"type":"Point"}
}