{
  "type": "Feature",
  "properties": {
    "gn:admin1_code":"11.0",
    "gn:admin2_code":"30.0",
    "gn:asciiname":"La Sauceda",
    "gn:country_code":"MX",
    "gn:dem":2411,
    "gn:feature_class":"P",
    "gn:feature_code":"PPL",
    "gn:name":"La Sauceda",
    "gn:population":0,
    "gn:timezone":"America/Mexico_City",
    "iso:country":"MX",
    "name:spa_x_preferred":[
        "La Sauceda"
    ],
    "name:spa_x_variant":[
        "Colonia Benito Ju\u00e1rez"
    ],
    "wof:name":"La Sauceda",
    "wof:placetype":"locality"
},
  "geometry": {"coordinates":[-101.21142999999999,21.76132],"type":"Point"}
}