{
  "type": "Feature",
  "properties": {
    "gn:admin1_code":"11",
    "gn:admin2_code":"17.0",
    "gn:asciiname":"San Jose de los Naranjos (Juan Rivera)",
    "gn:country_code":"MX",
    "gn:dem":1725,
    "gn:feature_class":"P",
    "gn:feature_code":"PPL",
    "gn:name":"San Jos\u00e9 de los Naranjos (Juan Rivera)",
    "gn:population":7,
    "gn:timezone":"America/Mexico_City",
    "iso:country":"MX",
    "name:und_x_variant":[
        "San Jos\u00e9 de los Naranjos (Juan Rivera)"
    ],
    "wof:name":"San Jose de los Naranjos (Juan Rivera)",
    "wof:placetype":"locality",
    "wof:population":7
},
  "geometry": {"coordinates":[-101.44972,20.63417],"type":"Point"}
}