{
  "type": "Feature",
  "properties": {
    "gn:admin1_code":"4.0",
    "gn:admin2_code":"11.0",
    "gn:asciiname":"Nueva Aventura",
    "gn:country_code":"MX",
    "gn:dem":50,
    "gn:feature_class":"P",
    "gn:feature_code":"PPL",
    "gn:name":"Nueva Aventura",
    "gn:population":0,
    "gn:timezone":"America/Merida",
    "iso:country":"MX",
    "name:spa_x_preferred":[
        "Nueva Ventura"
    ],
    "name:spa_x_variant":[
        "Nueva Aventura"
    ],
    "wof:name":"Nueva Aventura",
    "wof:placetype":"locality"
},
  "geometry": {"coordinates":[-90.98253,17.97347000000001],"type":"Point"}
}