{
  "type": "Feature",
  "properties": {
    "iso:country":"MX",
    "name:spa_x_preferred":[
        "Fracc Brasilia"
    ],
    "name:unk_x_variant":[
        "Fracc Brasilia"
    ],
    "qs:gn_adm0_cc":"MX",
    "qs:gn_local":3515001,
    "qs:gn_nam_loc":"Tuxtla Gutierrez, Tuxtla Guti\u00e9rrez, Chiapas, MX",
    "qs:gn_namadm1":"05",
    "qs:local_max":250,
    "qs:local_sum":646,
    "qs:localhoods":8,
    "qs:name":"Fracc Brasilia",
    "qs:name_adm0":"M\u00e9xico",
    "qs:name_adm1":"Chiapas",
    "qs:name_adm2":"Tuxtla Gutierrez",
    "qs:name_local":"Tuxtla Guti\u00e9rrez",
    "qs:photo_max":81,
    "qs:photo_sum":165,
    "qs:placetype":"Suburb",
    "qs:quad_count":10,
    "qs:woe_adm0":23424900,
    "qs:woe_adm1":2346268,
    "qs:woe_adm2":12599809,
    "qs:woe_lau":0,
    "qs:woe_local":150281,
    "qs:woe_ver":"7.10.0",
    "wof:lang":[
        "spa"
    ],
    "wof:name":"Fracc Brasilia",
    "wof:placetype":"neighbourhood"
},
  "geometry": {"coordinates":[-93.10760000000001,16.758404],"type":"Point"}
}