{
  "type": "Feature",
  "properties": {
    "gn:admin1_code":"10",
    "gn:admin2_code":"3",
    "gn:asciiname":"Los Alhelies",
    "gn:country_code":"MX",
    "gn:dem":1923,
    "gn:feature_class":"P",
    "gn:feature_code":"PPL",
    "gn:name":"Los Alhel\u00edes",
    "gn:population":26,
    "gn:timezone":"America/Monterrey",
    "iso:country":"MX",
    "name:und_x_variant":[
        "Los Alhel\u00edes"
    ],
    "wof:name":"Los Alhelies",
    "wof:placetype":"locality",
    "wof:population":26
},
  "geometry": {"coordinates":[-104.6656,24.86167],"type":"Point"}
}