{
  "type": "Feature",
  "properties": {
    "gn:admin1_code":"16",
    "gn:admin2_code":"53.0",
    "gn:asciiname":"Rio Bello (El Campamento)",
    "gn:country_code":"MX",
    "gn:dem":2053,
    "gn:feature_class":"P",
    "gn:feature_code":"PPL",
    "gn:name":"R\u00edo Bello (El Campamento)",
    "gn:population":433,
    "gn:timezone":"America/Mexico_City",
    "iso:country":"MX",
    "name:und_x_variant":[
        "R\u00edo Bello (El Campamento)"
    ],
    "wof:name":"Rio Bello (El Campamento)",
    "wof:placetype":"locality",
    "wof:population":433
},
  "geometry": {"coordinates":[-101.13444,19.6475],"type":"Point"}
}