{
  "type": "Feature",
  "properties": {
    "gn:admin1_code":"19",
    "gn:admin2_code":"37.0",
    "gn:asciiname":"El Puerto San Bernabe",
    "gn:country_code":"MX",
    "gn:dem":746,
    "gn:feature_class":"P",
    "gn:feature_code":"PPL",
    "gn:name":"El Puerto San Bernab\u00e9",
    "gn:population":0,
    "gn:timezone":"America/Monterrey",
    "iso:country":"MX",
    "name:spa_x_preferred":[
        "El Puerto San Bernab\u00e9"
    ],
    "name:und_x_variant":[
        "Puerto San Bernav\u00e9",
        "Rancho El Puerto San Bernab\u00e9",
        "Puerto San Bernab\u00e9"
    ],
    "wof:name":"El Puerto San Bernabe",
    "wof:placetype":"locality"
},
  "geometry": {"coordinates":[-100.88155,26.2523],"type":"Point"}
}