{
  "type": "Feature",
  "properties": {
    "gn:admin1_code":"11",
    "gn:admin2_code":"33",
    "gn:asciiname":"La Lajilla (La Estancita)",
    "gn:country_code":"MX",
    "gn:dem":2099,
    "gn:feature_class":"P",
    "gn:feature_code":"PPL",
    "gn:name":"La Lajilla (La Estancita)",
    "gn:population":11,
    "gn:timezone":"America/Mexico_City",
    "iso:country":"MX",
    "wof:name":"La Lajilla (La Estancita)",
    "wof:placetype":"locality",
    "wof:population":11
},
  "geometry": {"coordinates":[-100.44861,21.45278],"type":"Point"}
}