{
  "type": "Feature",
  "properties": {
    "gn:admin1_code":"24",
    "gn:admin2_code":"24.0",
    "gn:asciiname":"Las Pilas",
    "gn:country_code":"MX",
    "gn:dem":1222,
    "gn:feature_class":"P",
    "gn:feature_code":"PPL",
    "gn:name":"Las Pilas",
    "gn:population":0,
    "gn:timezone":"America/Mexico_City",
    "iso:country":"MX",
    "name:fra_x_preferred":[
        "Las Pilas"
    ],
    "name:lit_x_preferred":[
        "Las Pilasas"
    ],
    "name:nld_x_preferred":[
        "Las Pilas"
    ],
    "name:rus_x_preferred":[
        "\u041b\u0430\u0441-\u041f\u0438\u043b\u0430\u0441"
    ],
    "name:slk_x_preferred":[
        "Las Pilas"
    ],
    "name:spa_x_preferred":[
        "Las Pilas"
    ],
    "name:spa_x_variant":[
        "Las P\u00edlas"
    ],
    "wof:name":"Las Pilas",
    "wof:placetype":"locality"
},
  "geometry": {"coordinates":[-99.96863,21.67661],"type":"Point"}
}