{
  "type": "Feature",
  "properties": {
    "gn:admin1_code":"14",
    "gn:admin2_code":"91.0",
    "gn:asciiname":"Paso Hondo",
    "gn:country_code":"MX",
    "gn:dem":1816,
    "gn:feature_class":"P",
    "gn:feature_code":"PPL",
    "gn:name":"Paso Hondo",
    "gn:population":5,
    "gn:timezone":"America/Mexico_City",
    "iso:country":"MX",
    "wof:name":"Paso Hondo",
    "wof:placetype":"locality",
    "wof:population":5
},
  "geometry": {"coordinates":[-102.42055999999999,21.49833],"type":"Point"}
}