{
  "type": "Feature",
  "properties": {
    "gn:admin1_code":"30",
    "gn:admin2_code":"145.0",
    "gn:asciiname":"El Castano",
    "gn:country_code":"MX",
    "gn:dem":53,
    "gn:feature_class":"P",
    "gn:feature_code":"PPL",
    "gn:name":"El Casta\u00f1o",
    "gn:population":97,
    "gn:timezone":"America/Mexico_City",
    "iso:country":"MX",
    "name:und_x_variant":[
        "El Casta\u00f1o"
    ],
    "wof:name":"El Castano",
    "wof:placetype":"locality",
    "wof:population":97
},
  "geometry": {"coordinates":[-94.82722,17.96722],"type":"Point"}
}