{
  "type": "Feature",
  "properties": {
    "gn:admin1_code":"3",
    "gn:admin2_code":"2.0",
    "gn:asciiname":"Los Aguilar",
    "gn:country_code":"MX",
    "gn:dem":276,
    "gn:feature_class":"P",
    "gn:feature_code":"PPL",
    "gn:name":"Los Aguilar",
    "gn:population":0,
    "gn:timezone":"America/Mazatlan",
    "iso:country":"MX",
    "name:spa_x_preferred":[
        "Los Aguilar"
    ],
    "wof:name":"Los Aguilar",
    "wof:placetype":"locality"
},
  "geometry": {"coordinates":[-112.11932,26.71688],"type":"Point"}
}