{
  "type": "Feature",
  "properties": {
    "gn:admin1_code":"30",
    "gn:admin2_code":"129.0",
    "gn:asciiname":"Zacatianguis",
    "gn:country_code":"MX",
    "gn:dem":63,
    "gn:feature_class":"P",
    "gn:feature_code":"PPL",
    "gn:name":"Zacatianguis",
    "gn:population":0,
    "gn:timezone":"America/Mexico_City",
    "iso:country":"MX",
    "name:spa_x_preferred":[
        "Zacatianguis"
    ],
    "wof:name":"Zacatianguis",
    "wof:placetype":"locality"
},
  "geometry": {"coordinates":[-98.4451,21.31814],"type":"Point"}
}