{
  "type": "Feature",
  "properties": {
    "gn:admin1_code":"30",
    "gn:admin2_code":"182.0",
    "gn:asciiname":"Cuauzacatla",
    "gn:country_code":"MX",
    "gn:dem":1605,
    "gn:feature_class":"P",
    "gn:feature_code":"PPL",
    "gn:name":"Cuauzacatla",
    "gn:population":206,
    "gn:timezone":"America/Mexico_City",
    "iso:country":"MX",
    "wof:name":"Cuauzacatla",
    "wof:placetype":"locality",
    "wof:population":206
},
  "geometry": {"coordinates":[-96.97861,19.56361],"type":"Point"}
}