{
  "type": "Feature",
  "properties": {
    "gn:admin1_code":"30",
    "gn:admin2_code":"129",
    "gn:asciiname":"El Mante",
    "gn:country_code":"MX",
    "gn:dem":75,
    "gn:feature_class":"P",
    "gn:feature_code":"PPL",
    "gn:name":"El Mante",
    "gn:population":31,
    "gn:timezone":"America/Mexico_City",
    "iso:country":"MX",
    "wof:name":"El Mante",
    "wof:placetype":"locality",
    "wof:population":31
},
  "geometry": {"coordinates":[-98.41556,21.33833],"type":"Point"}
}