{
  "type": "Feature",
  "properties": {
    "gn:admin1_code":"5",
    "gn:admin2_code":"34.0",
    "gn:asciiname":"La Tuna (Parcelas el Portal)",
    "gn:country_code":"MX",
    "gn:dem":679,
    "gn:feature_class":"P",
    "gn:feature_code":"PPL",
    "gn:name":"La Tuna (Parcelas el Portal)",
    "gn:population":55,
    "gn:timezone":"America/Mexico_City",
    "iso:country":"MX",
    "wof:name":"La Tuna (Parcelas el Portal)",
    "wof:placetype":"locality",
    "wof:population":55
},
  "geometry": {"coordinates":[-92.11750000000001,15.68667],"type":"Point"}
}