{
  "type": "Feature",
  "properties": {
    "gn:admin1_code":"4",
    "gn:admin2_code":"6.0",
    "gn:asciiname":"X-Panzil",
    "gn:country_code":"MX",
    "gn:dem":135,
    "gn:feature_class":"P",
    "gn:feature_code":"PPL",
    "gn:name":"X-Panzil",
    "gn:population":0,
    "gn:timezone":"America/Cancun",
    "iso:country":"MX",
    "name:spa_x_preferred":[
        "X-Panzil"
    ],
    "name:und_x_variant":[
        "X-panzil",
        "Xpanzil"
    ],
    "wof:name":"X-Panzil",
    "wof:placetype":"locality"
},
  "geometry": {"coordinates":[-89.30913000000002,18.99667],"type":"Point"}
}