{
  "type": "Feature",
  "properties": {
    "gn:admin1_code":"16.0",
    "gn:asciiname":"Rincon de Cofradia",
    "gn:country_code":"MX",
    "gn:dem":1860,
    "gn:feature_class":"P",
    "gn:feature_code":"PPL",
    "gn:name":"Rinc\u00f3n de Cofrad\u00eda",
    "gn:population":0,
    "gn:timezone":"America/Mexico_City",
    "iso:country":"MX",
    "name:spa_x_preferred":[
        "Rinc\u00f3n de Cofrad\u00eda"
    ],
    "wof:name":"Rincon de Cofradia",
    "wof:placetype":"locality"
},
  "geometry": {"coordinates":[-100.44971,19.59812],"type":"Point"}
}