{
  "type": "Feature",
  "properties": {
    "gn:admin1_code":"10",
    "gn:admin2_code":"14",
    "gn:asciiname":"Carricillos",
    "gn:country_code":"MX",
    "gn:dem":1940,
    "gn:feature_class":"P",
    "gn:feature_code":"PPL",
    "gn:name":"Carricillos",
    "gn:population":9,
    "gn:timezone":"America/Monterrey",
    "iso:country":"MX",
    "wof:name":"Carricillos",
    "wof:placetype":"locality",
    "wof:population":9
},
  "geometry": {"coordinates":[-104.62441,22.91892],"type":"Point"}
}