{
  "type": "Feature",
  "properties": {
    "gn:admin1_code":"6",
    "gn:admin2_code":"65.0",
    "gn:asciiname":"Divisadero Gallego",
    "gn:country_code":"MX",
    "gn:dem":2115,
    "gn:feature_class":"P",
    "gn:feature_code":"PPL",
    "gn:name":"Divisadero Gallego",
    "gn:population":6,
    "gn:timezone":"America/Chihuahua",
    "iso:country":"MX",
    "wof:name":"Divisadero Gallego",
    "wof:placetype":"locality",
    "wof:population":6
},
  "geometry": {"coordinates":[-107.94297,27.24048],"type":"Point"}
}