{
  "type": "Feature",
  "properties": {
    "gn:admin1_code":"20",
    "gn:admin2_code":"5.0",
    "gn:asciiname":"Lagarteros",
    "gn:country_code":"MX",
    "gn:dem":44,
    "gn:feature_class":"P",
    "gn:feature_code":"PPL",
    "gn:name":"Lagarteros",
    "gn:population":0,
    "gn:timezone":"America/Mexico_City",
    "iso:country":"MX",
    "wof:name":"Lagarteros",
    "wof:placetype":"locality"
},
  "geometry": {"coordinates":[-94.95,16.58333],"type":"Point"}
}