{
  "type": "Feature",
  "properties": {
    "gn:admin1_code":"19.0",
    "gn:admin2_code":"37.0",
    "gn:asciiname":"Las Ovejas",
    "gn:country_code":"MX",
    "gn:dem":717,
    "gn:feature_class":"P",
    "gn:feature_code":"PPL",
    "gn:name":"Las Ovejas",
    "gn:population":0,
    "gn:timezone":"America/Monterrey",
    "iso:country":"MX",
    "name:spa_x_preferred":[
        "Las Ovejas"
    ],
    "name:und_x_variant":[
        "Rancho Las Ov\u00e9jas"
    ],
    "wof:name":"Las Ovejas",
    "wof:placetype":"locality"
},
  "geometry": {"coordinates":[-100.66144,26.03281],"type":"Point"}
}