{
  "type": "Feature",
  "properties": {
    "gn:admin1_code":"26",
    "gn:admin2_code":"42.0",
    "gn:asciiname":"La Quince",
    "gn:country_code":"MX",
    "gn:dem":38,
    "gn:feature_class":"P",
    "gn:feature_code":"PPL",
    "gn:name":"La Quince",
    "gn:population":82,
    "gn:timezone":"America/Hermosillo",
    "iso:country":"MX",
    "wof:name":"La Quince",
    "wof:placetype":"locality",
    "wof:population":82
},
  "geometry": {"coordinates":[-109.47806,27.11083],"type":"Point"}
}