{
  "type": "Feature",
  "properties": {
    "gn:admin1_code":"32",
    "gn:admin2_code":"26.0",
    "gn:asciiname":"Las Playas",
    "gn:country_code":"MX",
    "gn:dem":1867,
    "gn:feature_class":"P",
    "gn:feature_code":"PPL",
    "gn:name":"Las Playas",
    "gn:population":11,
    "gn:timezone":"America/Mexico_City",
    "iso:country":"MX",
    "wof:name":"Las Playas",
    "wof:placetype":"locality",
    "wof:population":11
},
  "geometry": {"coordinates":[-101.9255,24.29134],"type":"Point"}
}