{
  "type": "Feature",
  "properties": {
    "gn:admin1_code":"28",
    "gn:admin2_code":"35.0",
    "gn:asciiname":"La Diana",
    "gn:country_code":"MX",
    "gn:dem":27,
    "gn:feature_class":"P",
    "gn:feature_code":"PPL",
    "gn:name":"La Diana",
    "gn:population":0,
    "gn:timezone":"America/Monterrey",
    "iso:country":"MX",
    "name:spa_x_preferred":[
        "La Diana"
    ],
    "name:und_x_variant":[
        "Rancho La Diana"
    ],
    "wof:name":"La Diana",
    "wof:placetype":"locality"
},
  "geometry": {"coordinates":[-97.9521,24.49563],"type":"Point"}
}