{
  "type": "Feature",
  "properties": {
    "gn:admin1_code":"32",
    "gn:admin2_code":"53.0",
    "gn:asciiname":"El Centenario",
    "gn:country_code":"MX",
    "gn:dem":2154,
    "gn:feature_class":"P",
    "gn:feature_code":"PPL",
    "gn:name":"El Centenario",
    "gn:population":0,
    "gn:timezone":"America/Mexico_City",
    "iso:country":"MX",
    "name:srp_x_preferred":[
        "\u0415\u043b \u0421\u0435\u043d\u0442\u0435\u043d\u0430\u0440\u0438\u043e"
    ],
    "wof:name":"El Centenario",
    "wof:placetype":"locality"
},
  "geometry": {"coordinates":[-101.94992000000001,22.57604],"type":"Point"}
}