{
  "type": "Feature",
  "properties": {
    "gn:admin1_code":"30",
    "gn:admin2_code":"94",
    "gn:asciiname":"El Mirador (El Cerrito)",
    "gn:country_code":"MX",
    "gn:dem":157,
    "gn:feature_class":"P",
    "gn:feature_code":"PPL",
    "gn:name":"El Mirador (El Cerrito)",
    "gn:population":48,
    "gn:timezone":"America/Mexico_City",
    "iso:country":"MX",
    "wof:name":"El Mirador (El Cerrito)",
    "wof:placetype":"locality",
    "wof:population":48
},
  "geometry": {"coordinates":[-95.47917,17.83694],"type":"Point"}
}