{
  "type": "Feature",
  "properties": {
    "gn:admin1_code":"30.0",
    "gn:admin2_code":"124.0",
    "gn:asciiname":"Reynosa",
    "gn:country_code":"MX",
    "gn:dem":29,
    "gn:feature_class":"P",
    "gn:feature_code":"PPL",
    "gn:name":"Reynosa",
    "gn:population":3,
    "gn:timezone":"America/Mexico_City",
    "iso:country":"MX",
    "name:ara_x_preferred":[
        "\u0631\u064a\u0646\u0648\u0633\u0627"
    ],
    "name:bul_x_preferred":[
        "\u0420\u0435\u0439\u043d\u043e\u0441\u0430"
    ],
    "name:cat_x_preferred":[
        "Reynosa"
    ],
    "name:dan_x_preferred":[
        "Reynosa"
    ],
    "name:deu_x_preferred":[
        "Reynosa"
    ],
    "name:ell_x_preferred":[
        "\u03a1\u03b5\u03ca\u03bd\u03cc\u03c3\u03b1"
    ],
    "name:epo_x_preferred":[
        "Reynosa"
    ],
    "name:eus_x_preferred":[
        "Reynosa"
    ],
    "name:fas_x_preferred":[
        "\u0631\u06cc\u0646\u0648\u0633\u0627 \u062a\u0627\u0645\u0627\u0626\u0648\u0644\u06cc\u067e\u0627\u0633"
    ],
    "name:fra_x_preferred":[
        "Reynosa"
    ],
    "name:heb_x_preferred":[
        "\u05e8\u05d9\u05d9\u05e0\u05d5\u05e1\u05d4"
    ],
    "name:hun_x_preferred":[
        "Reynosa"
    ],
    "name:ilo_x_preferred":[
        "Reynosa"
    ],
    "name:ita_x_preferred":[
        "Reynosa"
    ],
    "name:jpn_x_preferred":[
        "\u30ec\u30a4\u30ce\u30b5"
    ],
    "name:kat_x_preferred":[
        "\u10e0\u10d4\u10d8\u10dc\u10dd\u10e1\u10d0"
    ],
    "name:kor_x_preferred":[
        "\ub808\uc774\ub178\uc0ac"
    ],
    "name:lit_x_preferred":[
        "Reinosa"
    ],
    "name:nld_x_preferred":[
        "Reynosa"
    ],
    "name:nor_x_preferred":[
        "Reynosa"
    ],
    "name:pol_x_preferred":[
        "Reynosa"
    ],
    "name:por_x_preferred":[
        "Reynosa"
    ],
    "name:rus_x_preferred":[
        "\u0420\u0435\u0439\u043d\u043e\u0441\u0430"
    ],
    "name:spa_x_preferred":[
        "Reynosa"
    ],
    "name:srp_x_preferred":[
        "\u0420\u0435\u0458\u043d\u043e\u0441\u0430"
    ],
    "name:swa_x_preferred":[
        "Reynosa"
    ],
    "name:swe_x_preferred":[
        "Reynosa"
    ],
    "name:tgl_x_preferred":[
        "Reynosa"
    ],
    "name:tur_x_preferred":[
        "Reynosa"
    ],
    "name:urd_x_preferred":[
        "\u0631\u06cc\u0626\u0646\u0648\u0633\u0627"
    ],
    "name:vie_x_preferred":[
        "Reynosa"
    ],
    "name:war_x_preferred":[
        "Reynosa"
    ],
    "name:xmf_x_preferred":[
        "\u10e0\u10d4\u10d8\u10dc\u10dd\u10e1\u10d0"
    ],
    "name:zho_x_preferred":[
        "\u96f7\u8afe\u85a9"
    ],
    "wof:name":"Reynosa",
    "wof:placetype":"locality",
    "wof:population":3
},
  "geometry": {"coordinates":[-97.16764999999999,20.59796],"type":"Point"}
}