{
  "type": "Feature",
  "properties": {
    "gn:admin1_code":"30.0",
    "gn:admin2_code":"124.0",
    "gn:asciiname":"Reynosa",
    "gn:country_code":"MX",
    "gn:dem":29,
    "gn:feature_class":"P",
    "gn:feature_code":"PPL",
    "gn:name":"Reynosa",
    "gn:population":3,
    "gn:timezone":"America/Mexico_City",
    "iso:country":"MX",
    "name:spa_x_preferred":[
        "Reynosa"
    ],
    "wof:name":"Reynosa",
    "wof:placetype":"locality",
    "wof:population":3
},
  "geometry": {"coordinates":[-97.16764999999999,20.59796],"type":"Point"}
}