{
  "type": "Feature",
  "properties": {
    "gn:admin1_code":"20",
    "gn:admin2_code":"334.0",
    "gn:asciiname":"Santiago Jocotepec",
    "gn:country_code":"MX",
    "gn:dem":657,
    "gn:feature_class":"P",
    "gn:feature_code":"PPL",
    "gn:name":"Santiago Jocotepec",
    "gn:population":0,
    "gn:timezone":"America/Mexico_City",
    "iso:country":"MX",
    "name:und_x_variant":[
        "Jacotepec",
        "Jocotepec",
        "Santiago Jocotepec"
    ],
    "wof:name":"Santiago Jocotepec",
    "wof:placetype":"locality"
},
  "geometry": {"coordinates":[-97.4376,16.12837],"type":"Point"}
}