{
  "type": "Feature",
  "properties": {
    "gn:admin1_code":"20",
    "gn:admin2_code":"334.0",
    "gn:asciiname":"Santiago Jocotepec",
    "gn:country_code":"MX",
    "gn:dem":657,
    "gn:feature_class":"P",
    "gn:feature_code":"PPL",
    "gn:name":"Santiago Jocotepec",
    "gn:population":0,
    "gn:timezone":"America/Mexico_City",
    "iso:country":"MX",
    "name:ceb_x_preferred":[
        "Santiago Jocotepec"
    ],
    "name:epo_x_preferred":[
        "Santiago Jocotepec"
    ],
    "name:eus_x_preferred":[
        "Santiago Jocotepec"
    ],
    "name:ita_x_preferred":[
        "Santiago Jocotepec"
    ],
    "name:rus_x_preferred":[
        "\u0421\u0430\u043d\u0442\u044c\u044f\u0433\u043e-\u0425\u043e\u043a\u043e\u0442\u0435\u043f\u0435\u043a"
    ],
    "name:sco_x_preferred":[
        "Santiago Jocotepec"
    ],
    "name:srp_x_preferred":[
        "\u041e\u043f\u0448\u0442\u0438\u043d\u0430 \u0421\u0430\u043d\u0442\u0438\u0458\u0430\u0433\u043e \u0425\u043e\u043a\u043e\u0442\u0435\u043f\u0435\u043a"
    ],
    "name:swe_x_preferred":[
        "Santiago Jocotepec"
    ],
    "name:und_x_variant":[
        "Jacotepec",
        "Jocotepec",
        "Santiago Jocotepec"
    ],
    "name:vie_x_preferred":[
        "Santiago Jocotepec"
    ],
    "wof:name":"Santiago Jocotepec",
    "wof:placetype":"locality"
},
  "geometry": {"coordinates":[-97.4376,16.12837],"type":"Point"}
}