{
  "type": "Feature",
  "properties": {
    "gn:admin1_code":"27",
    "gn:admin2_code":"12",
    "gn:asciiname":"Corozo",
    "gn:country_code":"MX",
    "gn:dem":4,
    "gn:feature_class":"P",
    "gn:feature_code":"PPL",
    "gn:name":"Corozo",
    "gn:population":29,
    "gn:timezone":"America/Mexico_City",
    "iso:country":"MX",
    "wof:name":"Corozo",
    "wof:placetype":"locality",
    "wof:population":29
},
  "geometry": {"coordinates":[-92.30361000000001,17.86889],"type":"Point"}
}