{
  "type": "Feature",
  "properties": {
    "gn:admin1_code":"30",
    "gn:admin2_code":"178.0",
    "gn:asciiname":"Mata de Cana",
    "gn:country_code":"MX",
    "gn:dem":13,
    "gn:feature_class":"P",
    "gn:feature_code":"PPL",
    "gn:name":"Mata de Ca\u00f1a",
    "gn:population":0,
    "gn:timezone":"America/Mexico_City",
    "iso:country":"MX",
    "name:und_x_variant":[
        "Matilla de Ca\u00f1a",
        "Mata de Ca\u00f1a"
    ],
    "wof:name":"Mata de Cana",
    "wof:placetype":"locality"
},
  "geometry": {"coordinates":[-95.488,18.37933],"type":"Point"}
}