{
  "type": "Feature",
  "properties": {
    "gn:admin1_code":"4",
    "gn:admin2_code":"2.0",
    "gn:asciiname":"Dziche",
    "gn:country_code":"MX",
    "gn:dem":7,
    "gn:feature_class":"P",
    "gn:feature_code":"PPL",
    "gn:name":"Dzich\u00e9",
    "gn:population":5,
    "gn:timezone":"America/Merida",
    "iso:country":"MX",
    "name:und_x_variant":[
        "Dzich\u00e9"
    ],
    "wof:name":"Dziche",
    "wof:placetype":"locality",
    "wof:population":5
},
  "geometry": {"coordinates":[-90.31667,19.80694],"type":"Point"}
}