{
  "type": "Feature",
  "properties": {
    "gn:admin1_code":"6.0",
    "gn:admin2_code":"66.0",
    "gn:asciiname":"Las Cuevas",
    "gn:country_code":"MX",
    "gn:dem":2344,
    "gn:feature_class":"P",
    "gn:feature_code":"PPL",
    "gn:name":"Las Cuevas",
    "gn:population":0,
    "gn:timezone":"America/Chihuahua",
    "iso:country":"MX",
    "name:ceb_x_preferred":[
        "Las Cuevas"
    ],
    "name:deu_x_preferred":[
        "Las Cuevas"
    ],
    "name:nds_x_preferred":[
        "Las Cuevas"
    ],
    "name:spa_x_preferred":[
        "Las Cuevas"
    ],
    "name:swe_x_preferred":[
        "Las Cuevas"
    ],
    "wof:name":"Las Cuevas",
    "wof:placetype":"locality"
},
  "geometry": {"coordinates":[-108.16385,27.9498],"type":"Point"}
}