{
  "type": "Feature",
  "properties": {
    "gn:admin1_code":"20",
    "gn:admin2_code":"469",
    "gn:asciiname":"Desviacion la Raya",
    "gn:country_code":"MX",
    "gn:dem":2497,
    "gn:feature_class":"P",
    "gn:feature_code":"PPL",
    "gn:name":"Desviaci\u00f3n la Raya",
    "gn:population":25,
    "gn:timezone":"America/Mexico_City",
    "iso:country":"MX",
    "name:und_x_variant":[
        "Desviaci\u00f3n la Raya"
    ],
    "wof:name":"Desviacion la Raya",
    "wof:placetype":"locality",
    "wof:population":25
},
  "geometry": {"coordinates":[-97.96722,17.33889],"type":"Point"}
}