{
  "type": "Feature",
  "properties": {
    "gn:admin1_code":"30",
    "gn:admin2_code":"76.0",
    "gn:asciiname":"Apachitla",
    "gn:country_code":"MX",
    "gn:dem":1336,
    "gn:feature_class":"P",
    "gn:feature_code":"PPL",
    "gn:name":"Apachitla",
    "gn:population":581,
    "gn:timezone":"America/Mexico_City",
    "iso:country":"MX",
    "wof:name":"Apachitla",
    "wof:placetype":"locality",
    "wof:population":581
},
  "geometry": {"coordinates":[-98.47944,20.72667],"type":"Point"}
}