{
  "type": "Feature",
  "properties": {
    "gn:admin1_code":"11",
    "gn:admin2_code":"33",
    "gn:asciiname":"Aguacate",
    "gn:country_code":"MX",
    "gn:dem":1065,
    "gn:feature_class":"P",
    "gn:feature_code":"PPL",
    "gn:name":"Aguacate",
    "gn:population":20,
    "gn:timezone":"America/Mexico_City",
    "iso:country":"MX",
    "name:ceb_x_preferred":[
        "Aguacate"
    ],
    "name:nds_x_preferred":[
        "Aguacate"
    ],
    "name:spa_x_preferred":[
        "Aguacate"
    ],
    "name:swe_x_preferred":[
        "Aguacate"
    ],
    "wof:name":"Aguacate",
    "wof:placetype":"locality",
    "wof:population":20
},
  "geometry": {"coordinates":[-100.23,21.59389],"type":"Point"}
}