{
  "type": "Feature",
  "properties": {
    "gn:admin1_code":"24.0",
    "gn:asciiname":"La Cajeta",
    "gn:country_code":"MX",
    "gn:dem":998,
    "gn:feature_class":"P",
    "gn:feature_code":"PPL",
    "gn:name":"La Cajeta",
    "gn:population":0,
    "gn:timezone":"America/Mexico_City",
    "iso:country":"MX",
    "name:spa_x_preferred":[
        "La Cajeta"
    ],
    "wof:name":"La Cajeta",
    "wof:placetype":"locality"
},
  "geometry": {"coordinates":[-99.95283000000001,21.97854],"type":"Point"}
}