{
  "type": "Feature",
  "properties": {
    "gn:admin1_code":"25",
    "gn:admin2_code":"12.0",
    "gn:asciiname":"El Arrayanal",
    "gn:country_code":"MX",
    "gn:dem":21,
    "gn:feature_class":"P",
    "gn:feature_code":"PPL",
    "gn:name":"El Arrayanal",
    "gn:population":5,
    "gn:timezone":"America/Mazatlan",
    "iso:country":"MX",
    "wof:name":"El Arrayanal",
    "wof:placetype":"locality",
    "wof:population":5
},
  "geometry": {"coordinates":[-106.47563,23.3649],"type":"Point"}
}