{
  "type": "Feature",
  "properties": {
    "gn:admin1_code":"26.0",
    "gn:admin2_code":"61.0",
    "gn:asciiname":"Las Noritas",
    "gn:country_code":"MX",
    "gn:dem":373,
    "gn:feature_class":"P",
    "gn:feature_code":"PPL",
    "gn:name":"Las Noritas",
    "gn:population":0,
    "gn:timezone":"America/Hermosillo",
    "iso:country":"MX",
    "name:spa_x_preferred":[
        "Las Noritas"
    ],
    "wof:name":"Las Noritas",
    "wof:placetype":"locality"
},
  "geometry": {"coordinates":[-109.51999000000001,28.68981],"type":"Point"}
}