{
  "type": "Feature",
  "properties": {
    "gn:admin1_code":"14",
    "gn:admin2_code":"22.0",
    "gn:asciiname":"Los Ingenios",
    "gn:country_code":"MX",
    "gn:dem":46,
    "gn:feature_class":"P",
    "gn:feature_code":"PPL",
    "gn:name":"Los Ingenios",
    "gn:population":253,
    "gn:timezone":"America/Mexico_City",
    "iso:country":"MX",
    "wof:name":"Los Ingenios",
    "wof:placetype":"locality",
    "wof:population":253
},
  "geometry": {"coordinates":[-104.76639,19.30028],"type":"Point"}
}