{
  "type": "Feature",
  "properties": {
    "gn:admin1_code":"14.0",
    "gn:admin2_code":"81.0",
    "gn:asciiname":"El Sauz",
    "gn:country_code":"MX",
    "gn:dem":1916,
    "gn:feature_class":"P",
    "gn:feature_code":"PPL",
    "gn:name":"El Sauz",
    "gn:population":0,
    "gn:timezone":"America/Mexico_City",
    "iso:country":"MX",
    "wof:name":"El Sauz",
    "wof:placetype":"locality"
},
  "geometry": {"coordinates":[-103.13333,22.18333],"type":"Point"}
}