{
  "type": "Feature",
  "properties": {
    "gn:admin1_code":"10",
    "gn:admin2_code":"13.0",
    "gn:asciiname":"San Jeronimo",
    "gn:country_code":"MX",
    "gn:dem":1103,
    "gn:feature_class":"P",
    "gn:feature_code":"PPL",
    "gn:name":"San Jer\u00f3nimo",
    "gn:population":0,
    "gn:timezone":"America/Monterrey",
    "iso:country":"MX",
    "name:spa_x_preferred":[
        "San Jer\u00f3nimo"
    ],
    "wof:name":"San Jeronimo",
    "wof:placetype":"locality"
},
  "geometry": {"coordinates":[-103.58468000000001,25.90272],"type":"Point"}
}