{
  "type": "Feature",
  "properties": {
    "gn:admin1_code":"32",
    "gn:admin2_code":"33",
    "gn:asciiname":"Barranca del Rio (El Potrero)",
    "gn:country_code":"MX",
    "gn:dem":1231,
    "gn:feature_class":"P",
    "gn:feature_code":"PPL",
    "gn:name":"Barranca del R\u00edo (El Potrero)",
    "gn:population":50,
    "gn:timezone":"America/Mexico_City",
    "iso:country":"MX",
    "name:und_x_variant":[
        "Barranca del R\u00edo (El Potrero)"
    ],
    "wof:name":"Barranca del Rio (El Potrero)",
    "wof:placetype":"locality",
    "wof:population":50
},
  "geometry": {"coordinates":[-103.20305999999999,21.14778],"type":"Point"}
}