{
  "type": "Feature",
  "properties": {
    "gn:admin1_code":"22",
    "gn:admin2_code":"11",
    "gn:asciiname":"Estacion la Griega",
    "gn:country_code":"MX",
    "gn:dem":1894,
    "gn:feature_class":"P",
    "gn:feature_code":"PPL",
    "gn:name":"Estaci\u00f3n la Griega",
    "gn:population":35,
    "gn:timezone":"America/Mexico_City",
    "iso:country":"MX",
    "name:und_x_variant":[
        "Estaci\u00f3n la Griega"
    ],
    "wof:name":"Estacion la Griega",
    "wof:placetype":"locality",
    "wof:population":35
},
  "geometry": {"coordinates":[-100.26083,20.62639],"type":"Point"}
}