{
  "type": "Feature",
  "properties": {
    "gn:admin1_code":"6",
    "gn:admin2_code":"29.0",
    "gn:asciiname":"Potrerillo",
    "gn:country_code":"MX",
    "gn:dem":833,
    "gn:feature_class":"P",
    "gn:feature_code":"PPL",
    "gn:name":"Potrerillo",
    "gn:population":0,
    "gn:timezone":"America/Chihuahua",
    "iso:country":"MX",
    "name:spa_x_preferred":[
        "Potrerillo"
    ],
    "wof:name":"Potrerillo",
    "wof:placetype":"locality"
},
  "geometry": {"coordinates":[-107.57089000000001,26.17242],"type":"Point"}
}