{
  "type": "Feature",
  "properties": {
    "gn:admin1_code":"20",
    "gn:admin2_code":"439.0",
    "gn:asciiname":"Paso Zanate",
    "gn:country_code":"MX",
    "gn:dem":62,
    "gn:feature_class":"P",
    "gn:feature_code":"PPL",
    "gn:name":"Paso Zanate",
    "gn:population":131,
    "gn:timezone":"America/Mexico_City",
    "iso:country":"MX",
    "wof:name":"Paso Zanate",
    "wof:placetype":"locality",
    "wof:population":131
},
  "geometry": {"coordinates":[-96.75472000000001,15.7675],"type":"Point"}
}