{
  "type": "Feature",
  "properties": {
    "gn:admin1_code":"15",
    "gn:admin2_code":"1.0",
    "gn:asciiname":"Ganzda",
    "gn:country_code":"MX",
    "gn:dem":2801,
    "gn:feature_class":"P",
    "gn:feature_code":"PPL",
    "gn:name":"Ganzda",
    "gn:population":2433,
    "gn:timezone":"America/Mexico_City",
    "iso:country":"MX",
    "wof:name":"Ganzda",
    "wof:placetype":"locality",
    "wof:population":2433
},
  "geometry": {"coordinates":[-99.8475,19.99],"type":"Point"}
}