{
  "type": "Feature",
  "properties": {
    "gn:admin1_code":"5",
    "gn:admin2_code":"70.0",
    "gn:asciiname":"Las Nubes",
    "gn:country_code":"MX",
    "gn:dem":2939,
    "gn:feature_class":"P",
    "gn:feature_code":"PPL",
    "gn:name":"Las Nubes",
    "gn:population":237,
    "gn:timezone":"America/Mexico_City",
    "iso:country":"MX",
    "wof:name":"Las Nubes",
    "wof:placetype":"locality",
    "wof:population":237
},
  "geometry": {"coordinates":[-92.29134999999999,15.44808],"type":"Point"}
}