{
  "type": "Feature",
  "properties": {
    "gn:admin1_code":"10",
    "gn:admin2_code":"16.0",
    "gn:asciiname":"La Pequena",
    "gn:country_code":"MX",
    "gn:dem":1726,
    "gn:feature_class":"P",
    "gn:feature_code":"PPL",
    "gn:name":"La Peque\u00f1a",
    "gn:population":4,
    "gn:timezone":"America/Monterrey",
    "iso:country":"MX",
    "name:und_x_variant":[
        "La Peque\u00f1a"
    ],
    "wof:name":"La Pequena",
    "wof:placetype":"locality",
    "wof:population":4
},
  "geometry": {"coordinates":[-104.25951999999999,23.82493],"type":"Point"}
}