{
  "type": "Feature",
  "properties": {
    "gn:admin1_code":"21.0",
    "gn:asciiname":"Ex-hacienda las Vaquerias",
    "gn:country_code":"MX",
    "gn:dem":2320,
    "gn:feature_class":"P",
    "gn:feature_code":"PPL",
    "gn:name":"Ex-hacienda las Vaquer\u00edas",
    "gn:population":0,
    "gn:timezone":"America/Mexico_City",
    "iso:country":"MX",
    "name:spa_x_preferred":[
        "Ex-hacienda las Vaquer\u00edas"
    ],
    "name:spa_x_variant":[
        "Vaquer\u00eda"
    ],
    "wof:name":"Ex-hacienda las Vaquerias",
    "wof:placetype":"locality"
},
  "geometry": {"coordinates":[-97.4669,18.74542000000001],"type":"Point"}
}