{
  "type": "Feature",
  "properties": {
    "gn:admin1_code":"2",
    "gn:admin2_code":"2.0",
    "gn:asciiname":"Baja Palms",
    "gn:country_code":"MX",
    "gn:dem":53,
    "gn:feature_class":"P",
    "gn:feature_code":"PPL",
    "gn:name":"Baja Palms",
    "gn:population":8,
    "gn:timezone":"America/Tijuana",
    "iso:country":"MX",
    "wof:name":"Baja Palms",
    "wof:placetype":"locality",
    "wof:population":8
},
  "geometry": {"coordinates":[-114.89888999999999,31.11528],"type":"Point"}
}