{
  "type": "Feature",
  "properties": {
    "gn:admin1_code":"30",
    "gn:admin2_code":"132.0",
    "gn:asciiname":"Manzanillo",
    "gn:cc2":"MX",
    "gn:country_code":"MX",
    "gn:dem":2444,
    "gn:feature_class":"P",
    "gn:feature_code":"PPL",
    "gn:name":"Manzanillo",
    "gn:population":359,
    "gn:timezone":"America/Mexico_City",
    "iso:country":"MX",
    "name:und_x_variant":[
        "El Manzanillo"
    ],
    "wof:name":"Manzanillo",
    "wof:placetype":"locality",
    "wof:population":359
},
  "geometry": {"coordinates":[-97.12889,19.6425],"type":"Point"}
}