{
  "type": "Feature",
  "properties": {
    "gn:admin1_code":"20",
    "gn:admin2_code":"429.0",
    "gn:asciiname":"Colon",
    "gn:country_code":"MX",
    "gn:dem":1468,
    "gn:feature_class":"P",
    "gn:feature_code":"PPL",
    "gn:name":"Col\u00f3n",
    "gn:population":72,
    "gn:timezone":"America/Mexico_City",
    "iso:country":"MX",
    "name:bul_x_preferred":[
        "\u041a\u043e\u043b\u043e\u043d"
    ],
    "name:ceb_x_preferred":[
        "Colon"
    ],
    "name:deu_x_preferred":[
        "Colon"
    ],
    "name:eus_x_preferred":[
        "Colon"
    ],
    "name:fas_x_preferred":[
        "\u06a9\u0648\u0644\u0648\u0646"
    ],
    "name:fra_x_preferred":[
        "Colon"
    ],
    "name:heb_x_preferred":[
        "\u05e7\u05d5\u05dc\u05d5\u05df"
    ],
    "name:ita_x_preferred":[
        "Colon"
    ],
    "name:jpn_x_preferred":[
        "\u30b3\u30ed\u30f3"
    ],
    "name:nld_x_preferred":[
        "Colon"
    ],
    "name:nno_x_preferred":[
        "Colon"
    ],
    "name:pol_x_preferred":[
        "Colon"
    ],
    "name:por_x_preferred":[
        "Colon"
    ],
    "name:sco_x_preferred":[
        "Colon"
    ],
    "name:srp_x_preferred":[
        "\u041a\u043e\u043b\u043e\u043d"
    ],
    "name:tha_x_preferred":[
        "Colon"
    ],
    "name:tur_x_preferred":[
        "Koloni"
    ],
    "name:und_x_variant":[
        "Col\u00f3n"
    ],
    "name:vol_x_preferred":[
        "Colon"
    ],
    "name:wln_x_preferred":[
        "Colon"
    ],
    "wof:name":"Colon",
    "wof:placetype":"locality",
    "wof:population":72
},
  "geometry": {"coordinates":[-97.02943999999999,16.56417],"type":"Point"}
}