{
  "type": "Feature",
  "properties": {
    "gn:admin1_code":"20",
    "gn:admin2_code":"429.0",
    "gn:asciiname":"Colon",
    "gn:country_code":"MX",
    "gn:dem":1468,
    "gn:feature_class":"P",
    "gn:feature_code":"PPL",
    "gn:name":"Col\u00f3n",
    "gn:population":72,
    "gn:timezone":"America/Mexico_City",
    "iso:country":"MX",
    "name:und_x_variant":[
        "Col\u00f3n"
    ],
    "wof:name":"Colon",
    "wof:placetype":"locality",
    "wof:population":72
},
  "geometry": {"coordinates":[-97.02943999999999,16.56417],"type":"Point"}
}