{
  "type": "Feature",
  "properties": {
    "gn:admin1_code":"26.0",
    "gn:admin2_code":"37.0",
    "gn:asciiname":"Duraznilla",
    "gn:country_code":"MX",
    "gn:dem":519,
    "gn:feature_class":"P",
    "gn:feature_code":"PPL",
    "gn:name":"Duraznilla",
    "gn:population":0,
    "gn:timezone":"America/Hermosillo",
    "iso:country":"MX",
    "wof:name":"Duraznilla",
    "wof:placetype":"locality"
},
  "geometry": {"coordinates":[-110.26667,29.01667],"type":"Point"}
}