{
  "type": "Feature",
  "properties": {
    "gn:admin1_code":"25",
    "gn:admin2_code":"3",
    "gn:asciiname":"El Naranjo de los Salomones",
    "gn:country_code":"MX",
    "gn:dem":788,
    "gn:feature_class":"P",
    "gn:feature_code":"PPL",
    "gn:name":"El Naranjo de los Salomones",
    "gn:population":14,
    "gn:timezone":"America/Mazatlan",
    "iso:country":"MX",
    "wof:name":"El Naranjo de los Salomones",
    "wof:placetype":"locality",
    "wof:population":14
},
  "geometry": {"coordinates":[-107.36541,25.75185],"type":"Point"}
}