{
  "type": "Feature",
  "properties": {
    "gn:admin1_code":"31",
    "gn:admin2_code":"22.0",
    "gn:asciiname":"Yodzonot Carrillo",
    "gn:country_code":"MX",
    "gn:dem":36,
    "gn:feature_class":"P",
    "gn:feature_code":"PPL",
    "gn:name":"Yodzonot Carrillo",
    "gn:population":0,
    "gn:timezone":"America/Merida",
    "iso:country":"MX",
    "name:spa_x_preferred":[
        "Yodzonot Carrillo"
    ],
    "wof:name":"Yodzonot Carrillo",
    "wof:placetype":"locality"
},
  "geometry": {"coordinates":[-88.54115,20.20625],"type":"Point"}
}