{
  "type": "Feature",
  "properties": {
    "gn:admin1_code":"16.0",
    "gn:admin2_code":"10.0",
    "gn:asciiname":"Paso Ancho",
    "gn:country_code":"MX",
    "gn:dem":807,
    "gn:feature_class":"P",
    "gn:feature_code":"PPL",
    "gn:name":"Paso Ancho",
    "gn:population":0,
    "gn:timezone":"America/Mexico_City",
    "iso:country":"MX",
    "name:spa_x_preferred":[
        "Paso Ancho"
    ],
    "name:zho_x_preferred":[
        "\u57c3\u5c14\u5e15\u7d22\u5b89\u4e54"
    ],
    "wof:name":"Paso Ancho",
    "wof:placetype":"locality"
},
  "geometry": {"coordinates":[-102.21638,18.28185],"type":"Point"}
}