{
  "type": "Feature",
  "properties": {
    "gn:admin1_code":"6",
    "gn:admin2_code":"38.0",
    "gn:asciiname":"La Mosca",
    "gn:country_code":"MX",
    "gn:dem":1449,
    "gn:feature_class":"P",
    "gn:feature_code":"PPL",
    "gn:name":"La Mosca",
    "gn:population":0,
    "gn:timezone":"America/Chihuahua",
    "iso:country":"MX",
    "wof:name":"La Mosca",
    "wof:placetype":"locality"
},
  "geometry": {"coordinates":[-105.18321,28.55992],"type":"Point"}
}