{
  "type": "Feature",
  "properties": {
    "gn:admin1_code":"10",
    "gn:admin2_code":"34",
    "gn:asciiname":"La Mesita de San Pablo",
    "gn:country_code":"MX",
    "gn:dem":2587,
    "gn:feature_class":"P",
    "gn:feature_code":"PPL",
    "gn:name":"La Mesita de San Pablo",
    "gn:population":9,
    "gn:timezone":"America/Monterrey",
    "iso:country":"MX",
    "wof:name":"La Mesita de San Pablo",
    "wof:placetype":"locality",
    "wof:population":9
},
  "geometry": {"coordinates":[-106.81899,25.49302],"type":"Point"}
}