{
  "type": "Feature",
  "properties": {
    "gn:admin1_code":"26",
    "gn:admin2_code":"18.0",
    "gn:asciiname":"Familia Vega Encinas",
    "gn:country_code":"MX",
    "gn:dem":37,
    "gn:feature_class":"P",
    "gn:feature_code":"PPL",
    "gn:name":"Familia Vega Encinas",
    "gn:population":6,
    "gn:timezone":"America/Hermosillo",
    "iso:country":"MX",
    "wof:name":"Familia Vega Encinas",
    "wof:placetype":"locality",
    "wof:population":6
},
  "geometry": {"coordinates":[-109.92638999999998,27.66528],"type":"Point"}
}