{
  "type": "Feature",
  "properties": {
    "iso:country":"MX",
    "name:eus_x_preferred":[
        "Los Sauces"
    ],
    "name:fra_x_preferred":[
        "Los Sauces"
    ],
    "name:ita_x_preferred":[
        "Los Sauces"
    ],
    "name:kor_x_preferred":[
        "\ub85c\uc2a4\uc0ac\uc6b0\uc138\uc2a4"
    ],
    "name:nld_x_preferred":[
        "Los Sauces"
    ],
    "name:por_x_preferred":[
        "Los Sauces"
    ],
    "name:ron_x_preferred":[
        "Los Sauces"
    ],
    "name:rus_x_preferred":[
        "\u041b\u043e\u0441-\u0421\u0430\u0443\u0441\u0435\u0441"
    ],
    "name:spa_x_preferred":[
        "Los Sauces"
    ],
    "name:zho_x_preferred":[
        "\u6d1b\u65af\u7d39\u585e\u65af"
    ],
    "qs:gn_adm0_cc":"MX",
    "qs:gn_local":4011743,
    "qs:gn_nam_loc":"Victoria de Durango, Durango, Durango, Durango, MX",
    "qs:gn_namadm1":"10",
    "qs:local_max":821,
    "qs:local_sum":1157,
    "qs:localhoods":5,
    "qs:name":"Los Sauces",
    "qs:name_adm0":"M\u00e9xico",
    "qs:name_adm1":"Durango",
    "qs:name_adm2":"Durango",
    "qs:name_local":"Victoria de Durango (durango)",
    "qs:photo_max":16,
    "qs:photo_sum":42,
    "qs:placetype":"Suburb",
    "qs:quad_count":6,
    "qs:woe_adm0":23424900,
    "qs:woe_adm1":2346273,
    "qs:woe_adm2":12599954,
    "qs:woe_lau":0,
    "qs:woe_local":55910400,
    "qs:woe_ver":"7.10.0",
    "wof:lang":[
        "spa"
    ],
    "wof:name":"Los Sauces",
    "wof:placetype":"neighbourhood"
},
  "geometry": {"coordinates":[-104.684359,24.028118],"type":"Point"}
}