{
  "type": "Feature",
  "properties": {
    "gn:admin1_code":"2.0",
    "gn:admin2_code":"1.0",
    "gn:asciiname":"Mike Maria",
    "gn:country_code":"MX",
    "gn:dem":4,
    "gn:feature_class":"P",
    "gn:feature_code":"PPL",
    "gn:name":"Mike Mar\u00eda",
    "gn:population":0,
    "gn:timezone":"America/Tijuana",
    "iso:country":"MX",
    "name:spa_x_preferred":[
        "Mike Mar\u00eda"
    ],
    "wof:name":"Mike Maria",
    "wof:placetype":"locality"
},
  "geometry": {"coordinates":[-115.96415,30.46269],"type":"Point"}
}