{
  "type": "Feature",
  "properties": {
    "gn:admin1_code":"15.0",
    "gn:asciiname":"La Joyita",
    "gn:country_code":"MX",
    "gn:dem":1575,
    "gn:feature_class":"P",
    "gn:feature_code":"PPL",
    "gn:name":"La Joyita",
    "gn:population":0,
    "gn:timezone":"America/Mexico_City",
    "iso:country":"MX",
    "name:spa_x_preferred":[
        "La Joyita"
    ],
    "wof:name":"La Joyita",
    "wof:placetype":"locality"
},
  "geometry": {"coordinates":[-102.34105,19.95993],"type":"Point"}
}