{
  "type": "Feature",
  "properties": {
    "gn:admin1_code":"6",
    "gn:admin2_code":"56",
    "gn:asciiname":"El Chismillo",
    "gn:country_code":"MX",
    "gn:dem":1514,
    "gn:feature_class":"P",
    "gn:feature_code":"PPL",
    "gn:name":"El Chismillo",
    "gn:population":11,
    "gn:timezone":"America/Chihuahua",
    "iso:country":"MX",
    "wof:name":"El Chismillo",
    "wof:placetype":"locality",
    "wof:population":11
},
  "geometry": {"coordinates":[-106.29210999999999,27.20855],"type":"Point"}
}