{
  "type": "Feature",
  "properties": {
    "gn:admin1_code":"2",
    "gn:admin2_code":"2.0",
    "gn:asciiname":"Los Figueroa (Ejido Tlaxcala)",
    "gn:country_code":"MX",
    "gn:dem":14,
    "gn:feature_class":"P",
    "gn:feature_code":"PPL",
    "gn:name":"Los Figueroa (Ejido Tlaxcala)",
    "gn:population":8,
    "gn:timezone":"America/Tijuana",
    "iso:country":"MX",
    "wof:name":"Los Figueroa (Ejido Tlaxcala)",
    "wof:placetype":"locality",
    "wof:population":8
},
  "geometry": {"coordinates":[-115.13861,32.46667],"type":"Point"}
}