{
  "type": "Feature",
  "properties": {
    "gn:admin1_code":"25",
    "gn:admin2_code":"14.0",
    "gn:asciiname":"San Rafael",
    "gn:country_code":"MX",
    "gn:dem":73,
    "gn:feature_class":"P",
    "gn:feature_code":"PPL",
    "gn:name":"San Rafael",
    "gn:population":0,
    "gn:timezone":"America/Mazatlan",
    "iso:country":"MX",
    "wof:name":"San Rafael",
    "wof:placetype":"locality"
},
  "geometry": {"coordinates":[-105.84999999999999,22.95],"type":"Point"}
}