{
  "type": "Feature",
  "properties": {
    "gn:country":"MX",
    "gn:fcode":"PPL",
    "gn:population":0,
    "iso:country":"MX",
    "name:bre_x_preferred":[
        "El Rosario"
    ],
    "name:ceb_x_preferred":[
        "El Rosario"
    ],
    "name:fra_x_preferred":[
        "El Rosario"
    ],
    "name:ita_x_preferred":[
        "El Rosario"
    ],
    "name:msa_x_preferred":[
        "El Rosario"
    ],
    "name:pol_x_preferred":[
        "El Rosario"
    ],
    "name:por_x_preferred":[
        "El Rosario"
    ],
    "name:rus_x_preferred":[
        "\u042d\u043b\u044c-\u0420\u043e\u0441\u0430\u0440\u0438\u043e"
    ],
    "name:sco_x_preferred":[
        "El Rosario"
    ],
    "name:spa_x_preferred":[
        "El Rosario"
    ],
    "name:srp_x_preferred":[
        "\u0415\u043b \u0420\u043e\u0441\u0430\u0440\u0438\u043e"
    ],
    "name:swe_x_preferred":[
        "El Rosario"
    ],
    "name:vie_x_preferred":[
        "El Rosario"
    ],
    "name:war_x_preferred":[
        "El Rosario"
    ],
    "qs_pg:aaroncc":"MX",
    "qs_pg:gn_country":"MX",
    "qs_pg:gn_fcode":"PPL",
    "qs_pg:gn_pop":0,
    "qs_pg:name":"El Rosario",
    "qs_pg:name_adm0":"M\u00e9xico",
    "qs_pg:name_adm1":"Nayarit",
    "qs_pg:photos_9k":1,
    "qs_pg:photos_9r":1,
    "qs_pg:photos_all":3,
    "qs_pg:photos_sr":0,
    "qs_pg:pop_sr":0,
    "qs_pg:qs_pg_placetype":"locality",
    "qs_pg:qs_pg_placetype_gp":"Town",
    "qs_pg:woe_adm0":23424900,
    "woe:adm0_id":23424900,
    "woe:name_adm0":"M\u00e9xico",
    "woe:name_adm1":"Nayarit",
    "woe:placetype":"Town",
    "wof:name":"El Rosario",
    "wof:placetype":"locality"
},
  "geometry": {"coordinates":[-104.46836,20.89195],"type":"Point"}
}