{
  "type": "Feature",
  "properties": {
    "gn:admin1_code":"26",
    "gn:admin2_code":"37.0",
    "gn:asciiname":"El Chuparrosal",
    "gn:country_code":"MX",
    "gn:dem":584,
    "gn:feature_class":"P",
    "gn:feature_code":"PPL",
    "gn:name":"El Chuparrosal",
    "gn:population":0,
    "gn:timezone":"America/Hermosillo",
    "iso:country":"MX",
    "name:spa_x_preferred":[
        "El Chuparrosal"
    ],
    "wof:name":"El Chuparrosal",
    "wof:placetype":"locality"
},
  "geometry": {"coordinates":[-110.08481999999999,29.02592000000001],"type":"Point"}
}