{
  "type": "Feature",
  "properties": {
    "gn:admin1_code":"10",
    "gn:admin2_code":"37",
    "gn:asciiname":"La Tarasca",
    "gn:country_code":"MX",
    "gn:dem":969,
    "gn:feature_class":"P",
    "gn:feature_code":"PPL",
    "gn:name":"La Tarasca",
    "gn:population":19,
    "gn:timezone":"America/Monterrey",
    "iso:country":"MX",
    "wof:name":"La Tarasca",
    "wof:placetype":"locality",
    "wof:population":19
},
  "geometry": {"coordinates":[-106.75537,25.15859],"type":"Point"}
}