{
  "type": "Feature",
  "properties": {
    "gn:admin1_code":"17",
    "gn:admin2_code":"21.0",
    "gn:asciiname":"Palos de Fierro",
    "gn:country_code":"MX",
    "gn:dem":1076,
    "gn:feature_class":"P",
    "gn:feature_code":"PPL",
    "gn:name":"Palos de Fierro",
    "gn:population":9,
    "gn:timezone":"America/Mexico_City",
    "iso:country":"MX",
    "wof:name":"Palos de Fierro",
    "wof:placetype":"locality",
    "wof:population":9
},
  "geometry": {"coordinates":[-99.41333,18.65889],"type":"Point"}
}