{
  "type": "Feature",
  "properties": {
    "gn:admin1_code":"23.0",
    "gn:admin2_code":"2.0",
    "gn:asciiname":"Andrea Angelica",
    "gn:country_code":"MX",
    "gn:dem":4,
    "gn:feature_class":"P",
    "gn:feature_code":"PPL",
    "gn:name":"Andrea Ang\u00e9lica",
    "gn:population":0,
    "gn:timezone":"America/Cancun",
    "iso:country":"MX",
    "name:spa_x_preferred":[
        "Andrea Ang\u00e9lica"
    ],
    "wof:name":"Andrea Angelica",
    "wof:placetype":"locality"
},
  "geometry": {"coordinates":[-87.49072,19.26101],"type":"Point"}
}