{
  "type": "Feature",
  "properties": {
    "gn:admin1_code":"20.0",
    "gn:asciiname":"San Fernando el Acicate",
    "gn:country_code":"MX",
    "gn:dem":124,
    "gn:feature_class":"P",
    "gn:feature_code":"PPL",
    "gn:name":"San Fernando el Acicate",
    "gn:population":0,
    "gn:timezone":"America/Mexico_City",
    "iso:country":"MX",
    "name:spa_x_preferred":[
        "San Fernando el Acicate"
    ],
    "wof:name":"San Fernando el Acicate",
    "wof:placetype":"locality"
},
  "geometry": {"coordinates":[-95.86441000000001,17.96022],"type":"Point"}
}