{
  "type": "Feature",
  "properties": {
    "gn:admin1_code":"16",
    "gn:admin2_code":"61.0",
    "gn:asciiname":"San Juan",
    "gn:country_code":"MX",
    "gn:dem":2321,
    "gn:feature_class":"P",
    "gn:feature_code":"PPL",
    "gn:name":"San Juan",
    "gn:population":487,
    "gn:timezone":"America/Mexico_City",
    "iso:country":"MX",
    "wof:name":"San Juan",
    "wof:placetype":"locality",
    "wof:population":487
},
  "geometry": {"coordinates":[-100.34193999999999,19.57306],"type":"Point"}
}