{
  "type": "Feature",
  "properties": {
    "gn:admin1_code":"6",
    "gn:admin2_code":"11.0",
    "gn:asciiname":"El Pacifico",
    "gn:country_code":"MX",
    "gn:dem":1260,
    "gn:feature_class":"P",
    "gn:feature_code":"PPL",
    "gn:name":"El Pac\u00edfico",
    "gn:population":0,
    "gn:timezone":"America/Chihuahua",
    "iso:country":"MX",
    "wof:name":"El Pacifico",
    "wof:placetype":"locality"
},
  "geometry": {"coordinates":[-103.98130999999999,27.97949],"type":"Point"}
}