{
  "type": "Feature",
  "properties": {
    "gn:admin1_code":"30",
    "gn:admin2_code":"142",
    "gn:asciiname":"Piedra y Zamorano",
    "gn:country_code":"MX",
    "gn:dem":81,
    "gn:feature_class":"P",
    "gn:feature_code":"PPL",
    "gn:name":"Piedra y Zamorano",
    "gn:population":14,
    "gn:timezone":"America/Mexico_City",
    "iso:country":"MX",
    "wof:name":"Piedra y Zamorano",
    "wof:placetype":"locality",
    "wof:population":14
},
  "geometry": {"coordinates":[-95.23222,17.81472],"type":"Point"}
}