{
  "type": "Feature",
  "properties": {
    "gn:admin1_code":"20",
    "gn:admin2_code":"27.0",
    "gn:asciiname":"Agua Espina",
    "gn:country_code":"MX",
    "gn:dem":1164,
    "gn:feature_class":"P",
    "gn:feature_code":"PPL",
    "gn:name":"Agua Espina",
    "gn:population":104,
    "gn:timezone":"America/Mexico_City",
    "iso:country":"MX",
    "wof:name":"Agua Espina",
    "wof:placetype":"locality",
    "wof:population":104
},
  "geometry": {"coordinates":[-96.75749999999999,17.97361],"type":"Point"}
}