{
  "type": "Feature",
  "properties": {
    "iso:country":"MX",
    "name:cat_x_preferred":[
        "Maider Teller\u00eda Go\u00f1i"
    ],
    "name:eus_x_preferred":[
        "Maider Telleria"
    ],
    "name:spa_x_preferred":[
        "Telleria",
        "Maider Telleria"
    ],
    "name:swe_x_preferred":[
        "Maider Teller\u00eda"
    ],
    "name:unk_x_variant":[
        "Telleria"
    ],
    "qs:gn_adm0_cc":"MX",
    "qs:gn_local":3996322,
    "qs:gn_nam_loc":"mazatlan",
    "qs:gn_namadm1":"25",
    "qs:local_max":927,
    "qs:local_sum":4580,
    "qs:localhoods":17,
    "qs:name":"Telleria",
    "qs:name_adm0":"M\u00e9xico",
    "qs:name_adm1":"Sinaloa",
    "qs:name_adm2":"Mazatlan",
    "qs:name_local":"Mazatl\u00e1n",
    "qs:photo_max":30,
    "qs:photo_sum":94,
    "qs:placetype":"Suburb",
    "qs:quad_count":5,
    "qs:woe_adm0":23424900,
    "qs:woe_adm1":2346288,
    "qs:woe_adm2":12601538,
    "qs:woe_lau":0,
    "qs:woe_local":133233,
    "qs:woe_ver":"7.10.0",
    "wof:lang":[
        "spa"
    ],
    "wof:name":"Telleria",
    "wof:placetype":"neighbourhood"
},
  "geometry": {"coordinates":[-106.430419,23.228615],"type":"Point"}
}