{
  "type": "Feature",
  "properties": {
    "gn:admin1_code":"26.0",
    "gn:admin2_code":"69.0",
    "gn:asciiname":"Carrizal de Vargas",
    "gn:country_code":"MX",
    "gn:dem":905,
    "gn:feature_class":"P",
    "gn:feature_code":"PPL",
    "gn:name":"Carrizal de Vargas",
    "gn:population":0,
    "gn:timezone":"America/Hermosillo",
    "iso:country":"MX",
    "name:spa_x_preferred":[
        "Carrizal de Vargas"
    ],
    "wof:name":"Carrizal de Vargas",
    "wof:placetype":"locality"
},
  "geometry": {"coordinates":[-109.16826,28.55003],"type":"Point"}
}