{
  "type": "Feature",
  "properties": {
    "gn:admin1_code":"6",
    "gn:admin2_code":"1.0",
    "gn:asciiname":"Ojo del Berrendo",
    "gn:country_code":"MX",
    "gn:dem":1287,
    "gn:feature_class":"P",
    "gn:feature_code":"PPL",
    "gn:name":"Ojo del Berrendo",
    "gn:population":0,
    "gn:timezone":"America/Chihuahua",
    "iso:country":"MX",
    "wof:name":"Ojo del Berrendo",
    "wof:placetype":"locality"
},
  "geometry": {"coordinates":[-107.03333000000001,30.45],"type":"Point"}
}