{
  "type": "Feature",
  "properties": {
    "gn:admin1_code":"25.0",
    "gn:admin2_code":"6.0",
    "gn:asciiname":"Los Hornos",
    "gn:country_code":"MX",
    "gn:dem":166,
    "gn:feature_class":"P",
    "gn:feature_code":"PPL",
    "gn:name":"Los Hornos",
    "gn:population":0,
    "gn:timezone":"America/Mazatlan",
    "iso:country":"MX",
    "name:nld_x_preferred":[
        "Los Hornos"
    ],
    "name:rus_x_preferred":[
        "\u041b\u043e\u0441-\u041e\u0440\u043d\u043e\u0441"
    ],
    "name:spa_x_preferred":[
        "Los Hornos"
    ],
    "wof:name":"Los Hornos",
    "wof:placetype":"locality"
},
  "geometry": {"coordinates":[-107.15064,24.9047],"type":"Point"}
}