{
  "type": "Feature",
  "properties": {
    "gn:admin1_code":"16",
    "gn:admin2_code":"110.0",
    "gn:asciiname":"Mesa Colorada",
    "gn:country_code":"MX",
    "gn:dem":2119,
    "gn:feature_class":"P",
    "gn:feature_code":"PPL",
    "gn:name":"Mesa Colorada",
    "gn:population":73,
    "gn:timezone":"America/Mexico_City",
    "iso:country":"MX",
    "wof:name":"Mesa Colorada",
    "wof:placetype":"locality",
    "wof:population":73
},
  "geometry": {"coordinates":[-100.78806,19.83222],"type":"Point"}
}