{
  "type": "Feature",
  "properties": {
    "gn:admin1_code":"32",
    "gn:admin2_code":"36.0",
    "gn:asciiname":"San Juan de Carboneras",
    "gn:country_code":"MX",
    "gn:dem":2125,
    "gn:feature_class":"P",
    "gn:feature_code":"PPL",
    "gn:name":"San Juan de Carboneras",
    "gn:population":0,
    "gn:timezone":"America/Mexico_City",
    "iso:country":"MX",
    "name:spa_x_preferred":[
        "San Juan de Carboneras"
    ],
    "wof:name":"San Juan de Carboneras",
    "wof:placetype":"locality"
},
  "geometry": {"coordinates":[-102.14303,22.45872],"type":"Point"}
}