{
  "type": "Feature",
  "properties": {
    "gn:admin1_code":"24",
    "gn:admin2_code":"3.0",
    "gn:asciiname":"Barrio San Miguel",
    "gn:country_code":"MX",
    "gn:dem":559,
    "gn:feature_class":"P",
    "gn:feature_code":"PPL",
    "gn:name":"Barrio San Miguel",
    "gn:population":361,
    "gn:timezone":"America/Mexico_City",
    "iso:country":"MX",
    "wof:name":"Barrio San Miguel",
    "wof:placetype":"locality",
    "wof:population":361
},
  "geometry": {"coordinates":[-99.07138999999999,21.615],"type":"Point"}
}