{
  "type": "Feature",
  "properties": {
    "gn:admin1_code":"6.0",
    "gn:admin2_code":"13.0",
    "gn:asciiname":"Garcia",
    "gn:country_code":"MX",
    "gn:dem":2143,
    "gn:feature_class":"P",
    "gn:feature_code":"PPL",
    "gn:name":"Garc\u00eda",
    "gn:population":0,
    "gn:timezone":"America/Chihuahua",
    "iso:country":"MX",
    "name:und_x_variant":[
        "Colonia Garc\u00eda",
        "Garc\u00eda"
    ],
    "wof:name":"Garcia",
    "wof:placetype":"locality"
},
  "geometry": {"coordinates":[-108.33729,29.97499],"type":"Point"}
}