{
  "type": "Feature",
  "properties": {
    "gn:admin1_code":"26",
    "gn:admin2_code":"10.0",
    "gn:asciiname":"El Vaso",
    "gn:country_code":"MX",
    "gn:dem":1874,
    "gn:feature_class":"P",
    "gn:feature_code":"PPL",
    "gn:name":"El Vaso",
    "gn:population":0,
    "gn:timezone":"America/Hermosillo",
    "iso:country":"MX",
    "name:spa_x_preferred":[
        "El Vaso"
    ],
    "wof:name":"El Vaso",
    "wof:placetype":"locality"
},
  "geometry": {"coordinates":[-108.65782,30.1723],"type":"Point"}
}