{
  "type": "Feature",
  "properties": {
    "gn:admin1_code":"28",
    "gn:admin2_code":"1.0",
    "gn:asciiname":"General Gildardo Magana",
    "gn:country_code":"MX",
    "gn:dem":192,
    "gn:feature_class":"P",
    "gn:feature_code":"PPL",
    "gn:name":"General Gildardo Maga\u00f1a",
    "gn:population":0,
    "gn:timezone":"America/Monterrey",
    "iso:country":"MX",
    "name:spa_x_preferred":[
        "General Gildardo Maga\u00f1a"
    ],
    "wof:name":"General Gildardo Magana",
    "wof:placetype":"locality"
},
  "geometry": {"coordinates":[-98.44942,23.83803],"type":"Point"}
}