{
  "type": "Feature",
  "properties": {
    "gn:admin1_code":"16.0",
    "gn:admin2_code":"99.0",
    "gn:asciiname":"Palos Mochos",
    "gn:country_code":"MX",
    "gn:dem":653,
    "gn:feature_class":"P",
    "gn:feature_code":"PPL",
    "gn:name":"Palos Mochos",
    "gn:population":0,
    "gn:timezone":"America/Mexico_City",
    "iso:country":"MX",
    "name:spa_x_preferred":[
        "Palos Mochos"
    ],
    "wof:name":"Palos Mochos",
    "wof:placetype":"locality"
},
  "geometry": {"coordinates":[-100.64514,19.20886],"type":"Point"}
}