{
  "type": "Feature",
  "properties": {
    "gn:admin1_code":"14",
    "gn:admin2_code":"124",
    "gn:asciiname":"Los Chombos",
    "gn:country_code":"MX",
    "gn:dem":1550,
    "gn:feature_class":"P",
    "gn:feature_code":"PPL",
    "gn:name":"Los Chombos",
    "gn:population":45,
    "gn:timezone":"America/Mexico_City",
    "iso:country":"MX",
    "wof:name":"Los Chombos",
    "wof:placetype":"locality",
    "wof:population":45
},
  "geometry": {"coordinates":[-103.04443999999999,20.68028],"type":"Point"}
}