{
  "type": "Feature",
  "properties": {
    "gn:admin1_code":"15.0",
    "gn:asciiname":"Tejocote San Isidro",
    "gn:country_code":"MX",
    "gn:dem":2489,
    "gn:feature_class":"P",
    "gn:feature_code":"PPL",
    "gn:name":"Tejocote San Isidro",
    "gn:population":0,
    "gn:timezone":"America/Mexico_City",
    "iso:country":"MX",
    "name:spa_x_preferred":[
        "Tejocote San Isidro"
    ],
    "wof:name":"Tejocote San Isidro",
    "wof:placetype":"locality"
},
  "geometry": {"coordinates":[-100.34144999999999,20.03009],"type":"Point"}
}