{
  "type": "Feature",
  "properties": {
    "gn:admin1_code":"25",
    "gn:admin2_code":"4.0",
    "gn:asciiname":"Padilla",
    "gn:country_code":"MX",
    "gn:dem":152,
    "gn:feature_class":"P",
    "gn:feature_code":"PPL",
    "gn:name":"Padilla",
    "gn:population":0,
    "gn:timezone":"America/Mazatlan",
    "iso:country":"MX",
    "name:spa_x_preferred":[
        "Padilla"
    ],
    "wof:name":"Padilla",
    "wof:placetype":"locality"
},
  "geometry": {"coordinates":[-106.10908999999999,23.28868],"type":"Point"}
}