{
  "type": "Feature",
  "properties": {
    "gn:admin1_code":"25",
    "gn:admin2_code":"4.0",
    "gn:asciiname":"Padilla",
    "gn:country_code":"MX",
    "gn:dem":152,
    "gn:feature_class":"P",
    "gn:feature_code":"PPL",
    "gn:name":"Padilla",
    "gn:population":0,
    "gn:timezone":"America/Mazatlan",
    "iso:country":"MX",
    "name:ben_x_preferred":[
        "\u09aa\u09be\u09a6\u09bf\u09b2\u09cd\u09b2\u09be"
    ],
    "name:ceb_x_preferred":[
        "Padilla"
    ],
    "name:deu_x_preferred":[
        "Padilla"
    ],
    "name:ell_x_preferred":[
        "\u03a0\u03b1\u03b4\u03af\u03b3\u03b9\u03b1"
    ],
    "name:fas_x_preferred":[
        "\u067e\u0627\u062f\u06cc\u0644\u0627"
    ],
    "name:fra_x_preferred":[
        "Padilla"
    ],
    "name:heb_x_preferred":[
        "\u05e4\u05d3\u05d9\u05dc\u05d4"
    ],
    "name:hin_x_preferred":[
        "\u092a\u093e\u0921\u093f\u0932\u093e"
    ],
    "name:hun_x_preferred":[
        "Padilla"
    ],
    "name:ind_x_preferred":[
        "Padilla"
    ],
    "name:ita_x_preferred":[
        "Padilla"
    ],
    "name:kor_x_preferred":[
        "\ud30c\ub514\uc57c"
    ],
    "name:nds_x_preferred":[
        "Padilla"
    ],
    "name:nld_x_preferred":[
        "Padilla"
    ],
    "name:rus_x_preferred":[
        "\u041f\u0430\u0434\u0438\u043b\u044c\u044f"
    ],
    "name:spa_x_preferred":[
        "Padilla"
    ],
    "name:swe_x_preferred":[
        "Padilla"
    ],
    "name:tur_x_preferred":[
        "Padilla"
    ],
    "name:ukr_x_preferred":[
        "\u041f\u0430\u0434\u0456\u043b\u044c\u044f"
    ],
    "name:urd_x_preferred":[
        "\u067e\u06cc\u0688\u06cc\u0644\u0627"
    ],
    "name:vie_x_preferred":[
        "Padilla"
    ],
    "wof:name":"Padilla",
    "wof:placetype":"locality"
},
  "geometry": {"coordinates":[-106.10908999999999,23.28868],"type":"Point"}
}