{
  "type": "Feature",
  "properties": {
    "gn:admin1_code":"14",
    "gn:admin2_code":"56",
    "gn:asciiname":"Cataquio",
    "gn:country_code":"MX",
    "gn:dem":656,
    "gn:feature_class":"P",
    "gn:feature_code":"PPL",
    "gn:name":"Cataqu\u00edo",
    "gn:population":27,
    "gn:timezone":"America/Mexico_City",
    "iso:country":"MX",
    "name:und_x_variant":[
        "Cataqu\u00edo"
    ],
    "wof:name":"Cataquio",
    "wof:placetype":"locality",
    "wof:population":27
},
  "geometry": {"coordinates":[-102.77556,19.53833],"type":"Point"}
}