{
  "type": "Feature",
  "properties": {
    "gn:admin1_code":"20.0",
    "gn:asciiname":"San Martin Caballero",
    "gn:country_code":"MX",
    "gn:dem":1181,
    "gn:feature_class":"P",
    "gn:feature_code":"PPL",
    "gn:name":"San Mart\u00edn Caballero",
    "gn:population":0,
    "gn:timezone":"America/Mexico_City",
    "iso:country":"MX",
    "name:spa_x_preferred":[
        "San Mart\u00edn Caballero"
    ],
    "wof:name":"San Martin Caballero",
    "wof:placetype":"locality"
},
  "geometry": {"coordinates":[-96.84786,18.18637],"type":"Point"}
}