{
  "type": "Feature",
  "properties": {
    "gn:admin1_code":"15",
    "gn:admin2_code":"89",
    "gn:asciiname":"Tecorral",
    "gn:country_code":"MX",
    "gn:dem":2432,
    "gn:feature_class":"P",
    "gn:feature_code":"PPL",
    "gn:name":"Tecorral",
    "gn:population":37,
    "gn:timezone":"America/Mexico_City",
    "iso:country":"MX",
    "wof:name":"Tecorral",
    "wof:placetype":"locality",
    "wof:population":37
},
  "geometry": {"coordinates":[-98.87135000000001,19.14121],"type":"Point"}
}