{
  "type": "Feature",
  "properties": {
    "gn:admin1_code":"4",
    "gn:admin2_code":"2.0",
    "gn:asciiname":"Santa Genoveva",
    "gn:country_code":"MX",
    "gn:dem":27,
    "gn:feature_class":"P",
    "gn:feature_code":"PPL",
    "gn:name":"Santa Genoveva",
    "gn:population":0,
    "gn:timezone":"America/Merida",
    "iso:country":"MX",
    "name:spa_x_preferred":[
        "Santa Genoveva"
    ],
    "wof:name":"Santa Genoveva",
    "wof:placetype":"locality"
},
  "geometry": {"coordinates":[-90.59701,19.79765],"type":"Point"}
}