{
  "type": "Feature",
  "properties": {
    "gn:admin1_code":"5",
    "gn:admin2_code":"108",
    "gn:asciiname":"La Experiencia",
    "gn:country_code":"MX",
    "gn:dem":700,
    "gn:feature_class":"P",
    "gn:feature_code":"PPL",
    "gn:name":"La Experiencia",
    "gn:population":14,
    "gn:timezone":"America/Mexico_City",
    "iso:country":"MX",
    "wof:name":"La Experiencia",
    "wof:placetype":"locality",
    "wof:population":14
},
  "geometry": {"coordinates":[-93.35666999999999,16.29583],"type":"Point"}
}