{
  "type": "Feature",
  "properties": {
    "gn:admin1_code":"21",
    "gn:admin2_code":"217.0",
    "gn:asciiname":"Cruztitla",
    "gn:country_code":"MX",
    "gn:dem":1254,
    "gn:feature_class":"P",
    "gn:feature_code":"PPL",
    "gn:name":"Cruztitla",
    "gn:population":139,
    "gn:timezone":"America/Mexico_City",
    "iso:country":"MX",
    "wof:name":"Cruztitla",
    "wof:placetype":"locality",
    "wof:population":139
},
  "geometry": {"coordinates":[-96.92361,18.41778],"type":"Point"}
}