{
  "type": "Feature",
  "properties": {
    "gn:admin1_code":"12",
    "gn:admin2_code":"3.0",
    "gn:asciiname":"Charco Azul",
    "gn:country_code":"MX",
    "gn:dem":415,
    "gn:feature_class":"P",
    "gn:feature_code":"PPL",
    "gn:name":"Charco Azul",
    "gn:population":72,
    "gn:timezone":"America/Mexico_City",
    "iso:country":"MX",
    "name:zho_x_preferred":[
        "\u67e5\u79d1\u963f\u82cf\u5c14\u6e7e"
    ],
    "wof:name":"Charco Azul",
    "wof:placetype":"locality",
    "wof:population":72
},
  "geometry": {"coordinates":[-100.4795,18.06661],"type":"Point"}
}