{
  "type": "Feature",
  "properties": {
    "gn:admin1_code":"22",
    "gn:admin2_code":"4.0",
    "gn:asciiname":"El Divino Pastor",
    "gn:country_code":"MX",
    "gn:dem":1926,
    "gn:feature_class":"P",
    "gn:feature_code":"PPL",
    "gn:name":"El Divino Pastor",
    "gn:population":93,
    "gn:timezone":"America/Mexico_City",
    "iso:country":"MX",
    "wof:name":"El Divino Pastor",
    "wof:placetype":"locality",
    "wof:population":93
},
  "geometry": {"coordinates":[-99.54806000000001,20.82833],"type":"Point"}
}