{
  "type": "Feature",
  "properties": {
    "gn:admin1_code":"32",
    "gn:admin2_code":"24.0",
    "gn:asciiname":"Norias de Guadalupe",
    "gn:country_code":"MX",
    "gn:dem":2022,
    "gn:feature_class":"P",
    "gn:feature_code":"PPL",
    "gn:name":"Norias de Guadalupe",
    "gn:population":882,
    "gn:timezone":"America/Mexico_City",
    "iso:country":"MX",
    "wof:name":"Norias de Guadalupe",
    "wof:placetype":"locality",
    "wof:population":882
},
  "geometry": {"coordinates":[-102.01167,22.27],"type":"Point"}
}