{
  "type": "Feature",
  "properties": {
    "gn:admin1_code":"26",
    "gn:admin2_code":"30.0",
    "gn:asciiname":"La Chinena",
    "gn:country_code":"MX",
    "gn:dem":99,
    "gn:feature_class":"P",
    "gn:feature_code":"PPL",
    "gn:name":"La Chine\u00f1a",
    "gn:population":0,
    "gn:timezone":"America/Hermosillo",
    "iso:country":"MX",
    "name:und_x_variant":[
        "La Chine\u00f1a",
        "La Chime\u00f1a"
    ],
    "wof:name":"La Chinena",
    "wof:placetype":"locality"
},
  "geometry": {"coordinates":[-111.3252,28.846],"type":"Point"}
}