{
  "type": "Feature",
  "properties": {
    "gn:admin1_code":"3",
    "gn:admin2_code":"1.0",
    "gn:asciiname":"Rancho",
    "gn:country_code":"MX",
    "gn:dem":100,
    "gn:feature_class":"P",
    "gn:feature_code":"PPL",
    "gn:name":"Rancho",
    "gn:population":0,
    "gn:timezone":"America/Mazatlan",
    "iso:country":"MX",
    "name:ceb_x_preferred":[
        "Rancho"
    ],
    "name:deu_x_preferred":[
        "Rancho"
    ],
    "name:fra_x_preferred":[
        "Rancho"
    ],
    "name:por_x_preferred":[
        "Rancho"
    ],
    "name:spa_x_preferred":[
        "Rancho"
    ],
    "name:swe_x_preferred":[
        "Rancho"
    ],
    "wof:name":"Rancho",
    "wof:placetype":"locality"
},
  "geometry": {"coordinates":[-112.25,26.15],"type":"Point"}
}