{
  "type": "Feature",
  "properties": {
    "gn:admin1_code":"30.0",
    "gn:admin2_code":"154.0",
    "gn:asciiname":"Monte Alto",
    "gn:country_code":"MX",
    "gn:dem":38,
    "gn:feature_class":"P",
    "gn:feature_code":"PPL",
    "gn:name":"Monte Alto",
    "gn:population":0,
    "gn:timezone":"America/Mexico_City",
    "iso:country":"MX",
    "name:spa_x_preferred":[
        "Monte Alto"
    ],
    "name:spa_x_variant":[
        "La Brecha"
    ],
    "wof:name":"Monte Alto",
    "wof:placetype":"locality"
},
  "geometry": {"coordinates":[-97.61721,21.44496],"type":"Point"}
}