{
  "type": "Feature",
  "properties": {
    "gn:admin1_code":"16",
    "gn:admin2_code":"86.0",
    "gn:asciiname":"Las Tortugas",
    "gn:country_code":"MX",
    "gn:dem":1540,
    "gn:feature_class":"P",
    "gn:feature_code":"PPL",
    "gn:name":"Las Tortugas",
    "gn:population":9,
    "gn:timezone":"America/Mexico_City",
    "iso:country":"MX",
    "wof:name":"Las Tortugas",
    "wof:placetype":"locality",
    "wof:population":9
},
  "geometry": {"coordinates":[-102.38361,20.26333],"type":"Point"}
}