{
  "type": "Feature",
  "properties": {
    "gn:admin1_code":"4",
    "gn:admin2_code":"11.0",
    "gn:asciiname":"Escondido",
    "gn:country_code":"MX",
    "gn:dem":72,
    "gn:feature_class":"P",
    "gn:feature_code":"PPL",
    "gn:name":"Escondido",
    "gn:population":5,
    "gn:timezone":"America/Merida",
    "iso:country":"MX",
    "name:ceb_x_preferred":[
        "Escondido"
    ],
    "name:ces_x_preferred":[
        "Escondido"
    ],
    "name:deu_x_preferred":[
        "Escondido"
    ],
    "name:fra_x_preferred":[
        "Escondido"
    ],
    "name:por_x_preferred":[
        "Escondido"
    ],
    "name:rus_x_preferred":[
        "\u042d\u0441\u043a\u043e\u043d\u0434\u0438\u0434\u043e"
    ],
    "name:spa_x_preferred":[
        "El Marente"
    ],
    "name:spa_x_variant":[
        "Escondido"
    ],
    "name:swe_x_preferred":[
        "Escondido"
    ],
    "wof:name":"Escondido",
    "wof:placetype":"locality",
    "wof:population":5
},
  "geometry": {"coordinates":[-91.06167000000001,17.97806],"type":"Point"}
}