{
  "type": "Feature",
  "properties": {
    "gn:admin1_code":"6.0",
    "gn:admin2_code":"25.0",
    "gn:asciiname":"El Rastro",
    "gn:country_code":"MX",
    "gn:dem":2154,
    "gn:feature_class":"P",
    "gn:feature_code":"PPL",
    "gn:name":"El Rastro",
    "gn:population":0,
    "gn:timezone":"America/Chihuahua",
    "iso:country":"MX",
    "name:epo_x_preferred":[
        "Pulbazaro El Rastro"
    ],
    "name:eus_x_preferred":[
        "Madrilgo rastroa"
    ],
    "name:fra_x_preferred":[
        "Rastro"
    ],
    "name:heb_x_preferred":[
        "\u05d0\u05dc \u05e8\u05e1\u05d8\u05e8\u05d5"
    ],
    "name:nld_x_preferred":[
        "El Rastro"
    ],
    "name:spa_x_preferred":[
        "El Rastro"
    ],
    "wof:name":"El Rastro",
    "wof:placetype":"locality"
},
  "geometry": {"coordinates":[-107.74045,29.37158],"type":"Point"}
}