{
  "type": "Feature",
  "properties": {
    "gn:admin1_code":"26.0",
    "gn:admin2_code":"4.0",
    "gn:asciiname":"La Rinconada",
    "gn:country_code":"MX",
    "gn:dem":517,
    "gn:feature_class":"P",
    "gn:feature_code":"PPL",
    "gn:name":"La Rinconada",
    "gn:population":0,
    "gn:timezone":"America/Hermosillo",
    "iso:country":"MX",
    "wof:name":"La Rinconada",
    "wof:placetype":"locality"
},
  "geometry": {"coordinates":[-111.87327999999999,30.87729],"type":"Point"}
}