{
  "type": "Feature",
  "properties": {
    "gn:admin1_code":"2",
    "gn:admin2_code":"1.0",
    "gn:asciiname":"Malibu Beach (Parcela 31)",
    "gn:country_code":"MX",
    "gn:dem":7,
    "gn:feature_class":"P",
    "gn:feature_code":"PPL",
    "gn:name":"Malib\u00fa Beach (Parcela 31)",
    "gn:population":5,
    "gn:timezone":"America/Tijuana",
    "iso:country":"MX",
    "name:und_x_variant":[
        "Malib\u00fa Beach (Parcela 31)"
    ],
    "wof:name":"Malibu Beach (Parcela 31)",
    "wof:placetype":"locality",
    "wof:population":5
},
  "geometry": {"coordinates":[-116.35833,31.23972],"type":"Point"}
}