{
  "type": "Feature",
  "properties": {
    "gn:admin1_code":"27",
    "gn:admin2_code":"14.0",
    "gn:asciiname":"Las Flores Tercera Seccion",
    "gn:country_code":"MX",
    "gn:dem":12,
    "gn:feature_class":"P",
    "gn:feature_code":"PPL",
    "gn:name":"Las Flores Tercera Secci\u00f3n",
    "gn:population":0,
    "gn:timezone":"America/Mexico_City",
    "iso:country":"MX",
    "name:spa_x_preferred":[
        "Las Flores Tercera Secci\u00f3n"
    ],
    "wof:name":"Las Flores Tercera Seccion",
    "wof:placetype":"locality"
},
  "geometry": {"coordinates":[-93.28236,18.42568],"type":"Point"}
}