{
  "type": "Feature",
  "properties": {
    "gn:admin1_code":"20.0",
    "gn:admin2_code":"413.0",
    "gn:asciiname":"Chahue",
    "gn:country_code":"MX",
    "gn:dem":9,
    "gn:feature_class":"P",
    "gn:feature_code":"PPL",
    "gn:name":"Chahu\u00e9",
    "gn:population":0,
    "gn:timezone":"America/Mexico_City",
    "iso:country":"MX",
    "name:spa_x_preferred":[
        "Chahu\u00e9"
    ],
    "wof:name":"Chahue",
    "wof:placetype":"locality"
},
  "geometry": {"coordinates":[-96.12485,15.76161],"type":"Point"}
}