{
  "type": "Feature",
  "properties": {
    "gn:admin1_code":"5",
    "gn:admin2_code":"61",
    "gn:asciiname":"Lucio Cabanas Barrientos",
    "gn:country_code":"MX",
    "gn:dem":840,
    "gn:feature_class":"P",
    "gn:feature_code":"PPL",
    "gn:name":"Lucio Caba\u00f1as Barrientos",
    "gn:population":17,
    "gn:timezone":"America/Mexico_City",
    "iso:country":"MX",
    "name:und_x_variant":[
        "Lucio Caba\u00f1as Barrientos"
    ],
    "wof:name":"Lucio Cabanas Barrientos",
    "wof:placetype":"locality",
    "wof:population":17
},
  "geometry": {"coordinates":[-93.45028000000001,16.84417],"type":"Point"}
}