{
  "type": "Feature",
  "properties": {
    "gn:admin1_code":"20",
    "gn:admin2_code":"28.0",
    "gn:asciiname":"La Noria Seccion Trece",
    "gn:country_code":"MX",
    "gn:dem":1359,
    "gn:feature_class":"P",
    "gn:feature_code":"PPL",
    "gn:name":"La Noria Secci\u00f3n Trece",
    "gn:population":0,
    "gn:timezone":"America/Mexico_City",
    "iso:country":"MX",
    "name:spa_x_preferred":[
        "La Noria Secci\u00f3n Trece"
    ],
    "name:und_x_variant":[
        "Noria",
        "La Noria"
    ],
    "wof:name":"La Noria Seccion Trece",
    "wof:placetype":"locality"
},
  "geometry": {"coordinates":[-96.78867,16.48587],"type":"Point"}
}