{
  "type": "Feature",
  "properties": {
    "gn:admin1_code":"26",
    "gn:admin2_code":"43.0",
    "gn:asciiname":"Las Minitas",
    "gn:country_code":"MX",
    "gn:dem":1133,
    "gn:feature_class":"P",
    "gn:feature_code":"PPL",
    "gn:name":"Las Minitas",
    "gn:population":0,
    "gn:timezone":"America/Hermosillo",
    "iso:country":"MX",
    "name:spa_x_preferred":[
        "Las Minitas"
    ],
    "name:und_x_variant":[
        "Rancho La Minita"
    ],
    "wof:name":"Las Minitas",
    "wof:placetype":"locality"
},
  "geometry": {"coordinates":[-110.8699,31.08178],"type":"Point"}
}