{
  "type": "Feature",
  "properties": {
    "gn:admin1_code":"5",
    "gn:admin2_code":"89.0",
    "gn:asciiname":"Las Palmeras",
    "gn:cc2":"MX",
    "gn:country_code":"MX",
    "gn:dem":110,
    "gn:feature_class":"P",
    "gn:feature_code":"PPL",
    "gn:name":"Las Palmeras",
    "gn:population":936,
    "gn:timezone":"America/Mexico_City",
    "iso:country":"MX",
    "name:und_x_variant":[
        "Palmas",
        "Las Palmas"
    ],
    "wof:name":"Las Palmeras",
    "wof:placetype":"locality",
    "wof:population":936
},
  "geometry": {"coordinates":[-92.27584,14.86704],"type":"Point"}
}