{
  "type": "Feature",
  "properties": {
    "gn:admin1_code":"6",
    "gn:admin2_code":"19.0",
    "gn:asciiname":"Valverde",
    "gn:cc2":"MX",
    "gn:country_code":"MX",
    "gn:dem":1842,
    "gn:feature_class":"P",
    "gn:feature_code":"PPL",
    "gn:name":"Valverde",
    "gn:population":0,
    "gn:timezone":"America/Chihuahua",
    "iso:country":"MX",
    "name:und_x_variant":[
        "Rancho Valverde",
        "Valverde"
    ],
    "wof:name":"Valverde",
    "wof:placetype":"locality"
},
  "geometry": {"coordinates":[-106.03333000000001,28.25],"type":"Point"}
}