{
  "type": "Feature",
  "properties": {
    "gn:admin1_code":"16",
    "gn:admin2_code":"66",
    "gn:asciiname":"San Jose (El Cerrito)",
    "gn:country_code":"MX",
    "gn:dem":2067,
    "gn:feature_class":"P",
    "gn:feature_code":"PPL",
    "gn:name":"San Jos\u00e9 (El Cerrito)",
    "gn:population":17,
    "gn:timezone":"America/Mexico_City",
    "iso:country":"MX",
    "name:und_x_variant":[
        "San Jos\u00e9 (El Cerrito)"
    ],
    "wof:name":"San Jose (El Cerrito)",
    "wof:placetype":"locality",
    "wof:population":17
},
  "geometry": {"coordinates":[-101.62361,19.52889],"type":"Point"}
}