{
  "type": "Feature",
  "properties": {
    "gn:admin1_code":"10",
    "gn:admin2_code":"14.0",
    "gn:asciiname":"Los Alacranes",
    "gn:country_code":"MX",
    "gn:dem":2085,
    "gn:feature_class":"P",
    "gn:feature_code":"PPL",
    "gn:name":"Los Alacranes",
    "gn:population":0,
    "gn:timezone":"America/Monterrey",
    "iso:country":"MX",
    "name:spa_x_preferred":[
        "Los Alacranes"
    ],
    "wof:name":"Los Alacranes",
    "wof:placetype":"locality"
},
  "geometry": {"coordinates":[-104.49896,23.74414],"type":"Point"}
}