{
  "type": "Feature",
  "properties": {
    "gn:admin1_code":"21.0",
    "gn:admin2_code":"86.0",
    "gn:asciiname":"La Tablita",
    "gn:country_code":"MX",
    "gn:dem":505,
    "gn:feature_class":"P",
    "gn:feature_code":"PPL",
    "gn:name":"La Tablita",
    "gn:population":0,
    "gn:timezone":"America/Mexico_City",
    "iso:country":"MX",
    "name:spa_x_preferred":[
        "La Tablita"
    ],
    "wof:name":"La Tablita",
    "wof:placetype":"locality"
},
  "geometry": {"coordinates":[-97.80777999999999,20.46639],"type":"Point"}
}