{
  "type": "Feature",
  "properties": {
    "gn:admin1_code":"5",
    "gn:admin2_code":"26.0",
    "gn:asciiname":"Tzomolton",
    "gn:country_code":"MX",
    "gn:dem":1323,
    "gn:feature_class":"P",
    "gn:feature_code":"PPL",
    "gn:name":"Tzomolt\u00f3n",
    "gn:population":242,
    "gn:timezone":"America/Mexico_City",
    "iso:country":"MX",
    "name:und_x_variant":[
        "Tzomolt\u00f3n"
    ],
    "wof:name":"Tzomolton",
    "wof:placetype":"locality",
    "wof:population":242
},
  "geometry": {"coordinates":[-92.61166,16.95333],"type":"Point"}
}