{
  "type": "Feature",
  "properties": {
    "gn:admin1_code":"6.0",
    "gn:admin2_code":"29.0",
    "gn:asciiname":"Algarrobos",
    "gn:country_code":"MX",
    "gn:dem":1260,
    "gn:feature_class":"P",
    "gn:feature_code":"PPL",
    "gn:name":"Algarrobos",
    "gn:population":0,
    "gn:timezone":"America/Chihuahua",
    "iso:country":"MX",
    "name:spa_x_preferred":[
        "Algarrobos"
    ],
    "wof:name":"Algarrobos",
    "wof:placetype":"locality"
},
  "geometry": {"coordinates":[-107.43898,26.41997000000001],"type":"Point"}
}