{
  "type": "Feature",
  "properties": {
    "gn:admin1_code":"19",
    "gn:admin2_code":"42.0",
    "gn:asciiname":"Las Mojarras",
    "gn:country_code":"MX",
    "gn:dem":202,
    "gn:feature_class":"P",
    "gn:feature_code":"PPL",
    "gn:name":"Las Mojarras",
    "gn:population":0,
    "gn:timezone":"America/Monterrey",
    "iso:country":"MX",
    "name:spa_x_preferred":[
        "Las Mojarras"
    ],
    "name:und_x_variant":[
        "Mojarras"
    ],
    "name:urd_x_preferred":[
        "\u0644\u0627\u0633 \u0645\u0648\u062c\u0627\u0631\u0627\u0633"
    ],
    "wof:name":"Las Mojarras",
    "wof:placetype":"locality"
},
  "geometry": {"coordinates":[-99.62542000000001,25.82927],"type":"Point"}
}