{
  "type": "Feature",
  "properties": {
    "gn:admin1_code":"13",
    "gn:admin2_code":"30.0",
    "gn:asciiname":"El Maye",
    "gn:country_code":"MX",
    "gn:dem":1720,
    "gn:feature_class":"P",
    "gn:feature_code":"PPL",
    "gn:name":"El Maye",
    "gn:population":0,
    "gn:timezone":"America/Mexico_City",
    "iso:country":"MX",
    "name:und_x_variant":[
        "El Fitzi",
        "El Maye",
        "May\u00e9",
        "El Mayo"
    ],
    "wof:name":"El Maye",
    "wof:placetype":"locality"
},
  "geometry": {"coordinates":[-99.22516,20.46668],"type":"Point"}
}