{
  "type": "Feature",
  "properties": {
    "gn:admin1_code":"25",
    "gn:admin2_code":"16.0",
    "gn:asciiname":"Los Salates",
    "gn:country_code":"MX",
    "gn:dem":175,
    "gn:feature_class":"P",
    "gn:feature_code":"PPL",
    "gn:name":"Los Salates",
    "gn:population":0,
    "gn:timezone":"America/Mazatlan",
    "iso:country":"MX",
    "name:spa_x_preferred":[
        "Los Salates"
    ],
    "wof:name":"Los Salates",
    "wof:placetype":"locality"
},
  "geometry": {"coordinates":[-106.32725000000001,23.68779],"type":"Point"}
}