{
  "type": "Feature",
  "properties": {
    "gn:admin1_code":"5",
    "gn:admin2_code":"3.0",
    "gn:asciiname":"Paloma Blanca",
    "gn:country_code":"MX",
    "gn:dem":29,
    "gn:feature_class":"P",
    "gn:feature_code":"PPL",
    "gn:name":"Paloma Blanca",
    "gn:population":414,
    "gn:timezone":"America/Mexico_City",
    "iso:country":"MX",
    "name:bul_x_preferred":[
        "Una Paloma Blanca"
    ],
    "name:fin_x_preferred":[
        "Paloma Blanca"
    ],
    "name:nld_x_preferred":[
        "Paloma Blanca"
    ],
    "name:nor_x_preferred":[
        "Paloma Blanca"
    ],
    "name:swe_x_preferred":[
        "Paloma Blanca"
    ],
    "name:zho_x_preferred":[
        "\u767d\u5170\u9e3d"
    ],
    "wof:name":"Paloma Blanca",
    "wof:placetype":"locality",
    "wof:population":414
},
  "geometry": {"coordinates":[-92.73361,15.29056],"type":"Point"}
}