{
  "type": "Feature",
  "properties": {
    "gn:admin1_code":"16",
    "gn:admin2_code":"15",
    "gn:asciiname":"Potrero del Ojo de Agua",
    "gn:country_code":"MX",
    "gn:dem":1071,
    "gn:feature_class":"P",
    "gn:feature_code":"PPL",
    "gn:name":"Potrero del Ojo de Agua",
    "gn:population":10,
    "gn:timezone":"America/Mexico_City",
    "iso:country":"MX",
    "wof:name":"Potrero del Ojo de Agua",
    "wof:placetype":"locality",
    "wof:population":10
},
  "geometry": {"coordinates":[-103.16056,18.79],"type":"Point"}
}