{
  "type": "Feature",
  "properties": {
    "gn:admin1_code":"6.0",
    "gn:admin2_code":"52.0",
    "gn:asciiname":"El Zapatero",
    "gn:country_code":"MX",
    "gn:dem":786,
    "gn:feature_class":"P",
    "gn:feature_code":"PPL",
    "gn:name":"El Zapatero",
    "gn:population":0,
    "gn:timezone":"America/Ojinaga",
    "iso:country":"MX",
    "name:spa_x_preferred":[
        "El Zapatero"
    ],
    "wof:name":"El Zapatero",
    "wof:placetype":"locality"
},
  "geometry": {"coordinates":[-104.35491,29.51917000000001],"type":"Point"}
}