{
  "type": "Feature",
  "properties": {
    "gn:admin1_code":"10",
    "gn:admin2_code":"12.0",
    "gn:asciiname":"Vallecillos",
    "gn:country_code":"MX",
    "gn:dem":1252,
    "gn:feature_class":"P",
    "gn:feature_code":"PPL",
    "gn:name":"Vallecillos",
    "gn:population":61,
    "gn:timezone":"America/Monterrey",
    "iso:country":"MX",
    "wof:name":"Vallecillos",
    "wof:placetype":"locality",
    "wof:population":61
},
  "geometry": {"coordinates":[-103.75951000000001,25.6075],"type":"Point"}
}