{
  "type": "Feature",
  "properties": {
    "gn:admin1_code":"5",
    "gn:admin2_code":"65",
    "gn:asciiname":"La Lupita",
    "gn:country_code":"MX",
    "gn:dem":61,
    "gn:feature_class":"P",
    "gn:feature_code":"PPL",
    "gn:name":"La Lupita",
    "gn:population":11,
    "gn:timezone":"America/Mexico_City",
    "iso:country":"MX",
    "wof:name":"La Lupita",
    "wof:placetype":"locality",
    "wof:population":11
},
  "geometry": {"coordinates":[-91.98222,17.49167000000001],"type":"Point"}
}