{
  "type": "Feature",
  "properties": {
    "gn:admin1_code":"10",
    "gn:admin2_code":"18.0",
    "gn:asciiname":"Sauco",
    "gn:country_code":"MX",
    "gn:dem":1587,
    "gn:feature_class":"P",
    "gn:feature_code":"PPL",
    "gn:name":"Sa\u00faco",
    "gn:population":0,
    "gn:timezone":"America/Monterrey",
    "iso:country":"MX",
    "wof:name":"Sauco",
    "wof:placetype":"locality"
},
  "geometry": {"coordinates":[-105.33333,25.35],"type":"Point"}
}