{
  "type": "Feature",
  "properties": {
    "gn:admin1_code":"3",
    "gn:admin2_code":"8.0",
    "gn:asciiname":"El Jeffrey",
    "gn:country_code":"MX",
    "gn:dem":138,
    "gn:feature_class":"P",
    "gn:feature_code":"PPL",
    "gn:name":"El Jeffrey",
    "gn:population":7,
    "gn:timezone":"America/Mazatlan",
    "iso:country":"MX",
    "name:ara_x_preferred":[
        "\u0625\u0644 \u062c\u064a\u0641\u0631\u064a"
    ],
    "wof:name":"El Jeffrey",
    "wof:placetype":"locality",
    "wof:population":7
},
  "geometry": {"coordinates":[-109.88687,22.92486],"type":"Point"}
}