{
  "type": "Feature",
  "properties": {
    "gn:admin1_code":"10",
    "gn:admin2_code":"26.0",
    "gn:asciiname":"El Saucillal",
    "gn:country_code":"MX",
    "gn:dem":2374,
    "gn:feature_class":"P",
    "gn:feature_code":"PPL",
    "gn:name":"El Saucillal",
    "gn:population":0,
    "gn:timezone":"America/Monterrey",
    "iso:country":"MX",
    "name:spa_x_preferred":[
        "El Saucillal"
    ],
    "wof:name":"El Saucillal",
    "wof:placetype":"locality"
},
  "geometry": {"coordinates":[-105.48318,24.54473],"type":"Point"}
}