{
  "type": "Feature",
  "properties": {
    "gn:admin1_code":"20",
    "gn:admin2_code":"379.0",
    "gn:asciiname":"San Jose Yatandoyo",
    "gn:country_code":"MX",
    "gn:dem":2515,
    "gn:feature_class":"P",
    "gn:feature_code":"PPL",
    "gn:name":"San Jos\u00e9 Yatandoyo",
    "gn:population":267,
    "gn:timezone":"America/Mexico_City",
    "iso:country":"MX",
    "name:und_x_variant":[
        "San Jos\u00e9 Yatandoyo"
    ],
    "wof:name":"San Jose Yatandoyo",
    "wof:placetype":"locality",
    "wof:population":267
},
  "geometry": {"coordinates":[-97.7025,17.16056],"type":"Point"}
}