{
  "type": "Feature",
  "properties": {
    "gn:admin1_code":"30",
    "gn:admin2_code":"147.0",
    "gn:asciiname":"Tlatilpa",
    "gn:country_code":"MX",
    "gn:dem":2225,
    "gn:feature_class":"P",
    "gn:feature_code":"PPL",
    "gn:name":"Tlatilpa",
    "gn:population":1078,
    "gn:timezone":"America/Mexico_City",
    "iso:country":"MX",
    "wof:name":"Tlatilpa",
    "wof:placetype":"locality",
    "wof:population":1078
},
  "geometry": {"coordinates":[-97.14417,18.73389],"type":"Point"}
}