{
  "type": "Feature",
  "properties": {
    "gn:admin1_code":"30",
    "gn:admin2_code":"73.0",
    "gn:asciiname":"La Nueva Esperanza",
    "gn:country_code":"MX",
    "gn:dem":189,
    "gn:feature_class":"P",
    "gn:feature_code":"PPL",
    "gn:name":"La Nueva Esperanza",
    "gn:population":110,
    "gn:timezone":"America/Mexico_City",
    "iso:country":"MX",
    "wof:name":"La Nueva Esperanza",
    "wof:placetype":"locality",
    "wof:population":110
},
  "geometry": {"coordinates":[-95.145,18.27583],"type":"Point"}
}