{
  "type": "Feature",
  "properties": {
    "gn:admin1_code":"30",
    "gn:admin2_code":"65.0",
    "gn:asciiname":"Xoltepec",
    "gn:country_code":"MX",
    "gn:dem":536,
    "gn:feature_class":"P",
    "gn:feature_code":"PPL",
    "gn:name":"Xoltepec",
    "gn:population":0,
    "gn:timezone":"America/Mexico_City",
    "iso:country":"MX",
    "wof:name":"Xoltepec",
    "wof:placetype":"locality"
},
  "geometry": {"coordinates":[-96.67805,19.4526],"type":"Point"}
}