{
  "type": "Feature",
  "properties": {
    "gn:admin1_code":"16.0",
    "gn:admin2_code":"96.0",
    "gn:asciiname":"La Huertita",
    "gn:country_code":"MX",
    "gn:dem":859,
    "gn:feature_class":"P",
    "gn:feature_code":"PPL",
    "gn:name":"La Huertita",
    "gn:population":0,
    "gn:timezone":"America/Mexico_City",
    "iso:country":"MX",
    "name:spa_x_preferred":[
        "La Huertita"
    ],
    "name:spa_x_variant":[
        "La Huerta"
    ],
    "wof:name":"La Huertita",
    "wof:placetype":"locality"
},
  "geometry": {"coordinates":[-102.38802,18.57966],"type":"Point"}
}