{
  "type": "Feature",
  "properties": {
    "gn:admin1_code":"9",
    "gn:admin2_code":"9.0",
    "gn:asciiname":"Coametzu",
    "gn:country_code":"MX",
    "gn:dem":2627,
    "gn:feature_class":"P",
    "gn:feature_code":"PPL",
    "gn:name":"Coametzu",
    "gn:population":136,
    "gn:timezone":"America/Mexico_City",
    "iso:country":"MX",
    "wof:name":"Coametzu",
    "wof:placetype":"locality",
    "wof:population":136
},
  "geometry": {"coordinates":[-99.05817999999999,19.18769],"type":"Point"}
}