{
  "type": "Feature",
  "properties": {
    "gn:admin1_code":"6",
    "gn:admin2_code":"17.0",
    "gn:asciiname":"Granja Presidente",
    "gn:country_code":"MX",
    "gn:dem":2062,
    "gn:feature_class":"P",
    "gn:feature_code":"PPL",
    "gn:name":"Granja Presidente",
    "gn:population":8,
    "gn:timezone":"America/Chihuahua",
    "iso:country":"MX",
    "wof:name":"Granja Presidente",
    "wof:placetype":"locality",
    "wof:population":8
},
  "geometry": {"coordinates":[-106.90772,28.39991],"type":"Point"}
}