{
  "type": "Feature",
  "properties": {
    "gn:admin1_code":"5.0",
    "gn:asciiname":"El Encuentro",
    "gn:country_code":"MX",
    "gn:dem":489,
    "gn:feature_class":"P",
    "gn:feature_code":"PPL",
    "gn:name":"El Encuentro",
    "gn:population":0,
    "gn:timezone":"America/Mexico_City",
    "iso:country":"MX",
    "name:spa_x_preferred":[
        "El Encuentro"
    ],
    "wof:name":"El Encuentro",
    "wof:placetype":"locality"
},
  "geometry": {"coordinates":[-92.68819000000001,16.39492000000001],"type":"Point"}
}