{
  "type": "Feature",
  "properties": {
    "gn:admin1_code":"6",
    "gn:admin2_code":"47.0",
    "gn:asciiname":"El Rincon",
    "gn:country_code":"MX",
    "gn:dem":779,
    "gn:feature_class":"P",
    "gn:feature_code":"PPL",
    "gn:name":"El Rinc\u00f3n",
    "gn:population":0,
    "gn:timezone":"America/Chihuahua",
    "iso:country":"MX",
    "name:spa_x_preferred":[
        "El Rinc\u00f3n"
    ],
    "name:und_x_variant":[
        "Rinc\u00f3n",
        "Jos\u00e9 Rincon",
        "San Jos\u00e9 del Rinc\u00f3n"
    ],
    "wof:name":"El Rincon",
    "wof:placetype":"locality"
},
  "geometry": {"coordinates":[-108.53865999999999,28.18485],"type":"Point"}
}