{
  "type": "Feature",
  "properties": {
    "gn:admin1_code":"20",
    "gn:admin2_code":"232.0",
    "gn:asciiname":"Puerto Angel",
    "gn:country_code":"MX",
    "gn:dem":76,
    "gn:feature_class":"P",
    "gn:feature_code":"PPL",
    "gn:name":"Puerto \u00c1ngel",
    "gn:population":117,
    "gn:timezone":"America/Mexico_City",
    "iso:country":"MX",
    "name:und_x_variant":[
        "Puerto \u00c1ngel"
    ],
    "wof:name":"Puerto Angel",
    "wof:placetype":"locality",
    "wof:population":117
},
  "geometry": {"coordinates":[-96.45917,18.03722],"type":"Point"}
}