{
  "type": "Feature",
  "properties": {
    "gn:admin1_code":"5",
    "gn:admin2_code":"26.0",
    "gn:asciiname":"Sac Lum",
    "gn:country_code":"MX",
    "gn:dem":1219,
    "gn:feature_class":"P",
    "gn:feature_code":"PPL",
    "gn:name":"Sac Lum",
    "gn:population":312,
    "gn:timezone":"America/Mexico_City",
    "iso:country":"MX",
    "wof:name":"Sac Lum",
    "wof:placetype":"locality",
    "wof:population":312
},
  "geometry": {"coordinates":[-92.69222000000001,16.95583],"type":"Point"}
}