{
  "type": "Feature",
  "properties": {
    "gn:admin1_code":"16",
    "gn:admin2_code":"72.0",
    "gn:asciiname":"Los Fresnos (La Alberca)",
    "gn:country_code":"MX",
    "gn:dem":1842,
    "gn:feature_class":"P",
    "gn:feature_code":"PPL",
    "gn:name":"Los Fresnos (La Alberca)",
    "gn:population":6,
    "gn:timezone":"America/Mexico_City",
    "iso:country":"MX",
    "wof:name":"Los Fresnos (La Alberca)",
    "wof:placetype":"locality",
    "wof:population":6
},
  "geometry": {"coordinates":[-100.90139000000001,19.80444],"type":"Point"}
}