{
  "type": "Feature",
  "properties": {
    "iso:country":"MX",
    "name:ara_x_preferred":[
        "\u0644\u0648\u064a\u0633 \u062f\u0648\u0646\u0627\u0644\u062f\u0648 \u0643\u0648\u0644\u0648\u0633\u064a\u0648"
    ],
    "name:cat_x_preferred":[
        "Luis Donaldo Colosio Murrieta"
    ],
    "name:dan_x_preferred":[
        "Luis Donaldo Colosio"
    ],
    "name:deu_x_preferred":[
        "Luis Donaldo Colosio"
    ],
    "name:eng_x_preferred":[
        "Luis Donaldo Colosio"
    ],
    "name:fas_x_preferred":[
        "\u0644\u0648\u0626\u06cc\u0633 \u062f\u0648\u0646\u0627\u0644\u062f\u0648 \u06a9\u0648\u0644\u0648\u0633\u06cc\u0648"
    ],
    "name:fra_x_preferred":[
        "Luis Donaldo Colosio"
    ],
    "name:hun_x_preferred":[
        "Luis Donaldo Colosio"
    ],
    "name:ind_x_preferred":[
        "Luis Donaldo Colosio"
    ],
    "name:ita_x_preferred":[
        "Luis Donaldo Colosio"
    ],
    "name:jpn_x_preferred":[
        "\u30eb\u30a4\u30b9\u30fb\u30c9\u30ca\u30eb\u30c9\u30fb\u30b3\u30ed\u30b7\u30aa"
    ],
    "name:nah_x_preferred":[
        "Luis Donaldo Colosio"
    ],
    "name:nld_x_preferred":[
        "Luis Donaldo Colosio"
    ],
    "name:nno_x_preferred":[
        "Luis Donaldo Colosio"
    ],
    "name:nob_x_preferred":[
        "Luis Donaldo Colosio"
    ],
    "name:nor_x_preferred":[
        "Luis Donaldo Colosio"
    ],
    "name:pol_x_preferred":[
        "Luis Colosio"
    ],
    "name:por_x_preferred":[
        "Luis Donaldo Colosio"
    ],
    "name:rus_x_preferred":[
        "\u041a\u043e\u043b\u043e\u0441\u0438\u043e"
    ],
    "name:slv_x_preferred":[
        "Luis Donaldo Colosio"
    ],
    "name:spa_x_preferred":[
        "Luis Donaldo Colosio"
    ],
    "name:srp_x_preferred":[
        "\u041b\u0443\u0438\u0441 \u0414\u043e\u043d\u0430\u043b\u0434\u043e \u041a\u043e\u043b\u043e\u0441\u0438\u043e"
    ],
    "name:swe_x_preferred":[
        "Luis Donaldo Colosio"
    ],
    "qs:gn_adm0_cc":"MX",
    "qs:gn_local":3521342,
    "qs:gn_nam_loc":"playa del carmen",
    "qs:gn_namadm1":"23",
    "qs:local_max":10960,
    "qs:local_sum":28603,
    "qs:localhoods":9,
    "qs:name":"Luis Donaldo Colosio",
    "qs:name_adm0":"M\u00e9xico",
    "qs:name_adm1":"Quintana Roo",
    "qs:name_adm2":"Solidaridad",
    "qs:name_local":"Playa del Carmen",
    "qs:photo_max":88,
    "qs:photo_sum":487,
    "qs:placetype":"Suburb",
    "qs:quad_count":21,
    "qs:woe_adm0":23424900,
    "qs:woe_adm1":2346286,
    "qs:woe_adm2":24550675,
    "qs:woe_lau":0,
    "qs:woe_local":136973,
    "qs:woe_ver":"7.10.0",
    "wd:wordcount":1328,
    "wof:lang":[
        "spa"
    ],
    "wof:name":"Luis Donaldo Colosio",
    "wof:placetype":"neighbourhood"
},
  "geometry": {"coordinates":[-87.05947500000001,20.644097],"type":"Point"}
}