{
  "type": "Feature",
  "properties": {
    "gn:admin1_code":"1",
    "gn:admin2_code":"10.0",
    "gn:asciiname":"San Angel [Rancho]",
    "gn:country_code":"MX",
    "gn:dem":1984,
    "gn:feature_class":"P",
    "gn:feature_code":"PPL",
    "gn:name":"San \u00c1ngel [Rancho]",
    "gn:population":5,
    "gn:timezone":"America/Mexico_City",
    "iso:country":"MX",
    "name:und_x_variant":[
        "San \u00c1ngel [Rancho]"
    ],
    "wof:name":"San Angel [Rancho]",
    "wof:placetype":"locality",
    "wof:population":5
},
  "geometry": {"coordinates":[-102.06111,21.80639],"type":"Point"}
}