{
  "type": "Feature",
  "properties": {
    "gn:admin1_code":"14",
    "gn:admin2_code":"43",
    "gn:asciiname":"La Gasera",
    "gn:country_code":"MX",
    "gn:dem":286,
    "gn:feature_class":"P",
    "gn:feature_code":"PPL",
    "gn:name":"La Gasera",
    "gn:population":13,
    "gn:timezone":"America/Mexico_City",
    "iso:country":"MX",
    "wof:name":"La Gasera",
    "wof:placetype":"locality",
    "wof:population":13
},
  "geometry": {"coordinates":[-104.625,19.49],"type":"Point"}
}