{
  "type": "Feature",
  "properties": {
    "gn:admin1_code":"18.0",
    "gn:admin2_code":"4.0",
    "gn:asciiname":"Las Cebollitas",
    "gn:country_code":"MX",
    "gn:dem":1244,
    "gn:feature_class":"P",
    "gn:feature_code":"PPL",
    "gn:name":"Las Cebollitas",
    "gn:population":0,
    "gn:timezone":"America/Mazatlan",
    "iso:country":"MX",
    "wof:name":"Las Cebollitas",
    "wof:placetype":"locality"
},
  "geometry": {"coordinates":[-104.87341000000001,21.04373],"type":"Point"}
}