{
  "type": "Feature",
  "properties": {
    "gn:admin1_code":"15",
    "gn:admin2_code":"40.0",
    "gn:asciiname":"Plan de Don Antonio",
    "gn:country_code":"MX",
    "gn:dem":2000,
    "gn:feature_class":"P",
    "gn:feature_code":"PPL",
    "gn:name":"Plan de Don Antonio",
    "gn:population":0,
    "gn:timezone":"America/Mexico_City",
    "iso:country":"MX",
    "wof:name":"Plan de Don Antonio",
    "wof:placetype":"locality"
},
  "geometry": {"coordinates":[-99.71666999999999,18.84167],"type":"Point"}
}