{
  "type": "Feature",
  "properties": {
    "gn:admin1_code":"5",
    "gn:admin2_code":"21.0",
    "gn:asciiname":"San Isidro (San Antonio)",
    "gn:country_code":"MX",
    "gn:dem":626,
    "gn:feature_class":"P",
    "gn:feature_code":"PPL",
    "gn:name":"San Isidro (San Antonio)",
    "gn:population":70,
    "gn:timezone":"America/Mexico_City",
    "iso:country":"MX",
    "wof:name":"San Isidro (San Antonio)",
    "wof:placetype":"locality",
    "wof:population":70
},
  "geometry": {"coordinates":[-93.26361,17.18361],"type":"Point"}
}