{
  "type": "Feature",
  "properties": {
    "gn:admin1_code":"21",
    "gn:admin2_code":"159.0",
    "gn:asciiname":"Huitlachapa",
    "gn:country_code":"MX",
    "gn:dem":1934,
    "gn:feature_class":"P",
    "gn:feature_code":"PPL",
    "gn:name":"Huitlachapa",
    "gn:population":9,
    "gn:timezone":"America/Mexico_City",
    "iso:country":"MX",
    "wof:name":"Huitlachapa",
    "wof:placetype":"locality",
    "wof:population":9
},
  "geometry": {"coordinates":[-98.30969,18.84959],"type":"Point"}
}