{
  "type": "Feature",
  "properties": {
    "gn:admin1_code":"30",
    "gn:admin2_code":"58.0",
    "gn:asciiname":"El Carril",
    "gn:country_code":"MX",
    "gn:dem":99,
    "gn:feature_class":"P",
    "gn:feature_code":"PPL",
    "gn:name":"El Carril",
    "gn:population":6,
    "gn:timezone":"America/Mexico_City",
    "iso:country":"MX",
    "name:spa_x_preferred":[
        "El Carril"
    ],
    "wof:name":"El Carril",
    "wof:placetype":"locality",
    "wof:population":6
},
  "geometry": {"coordinates":[-98.14219,21.06574],"type":"Point"}
}