{
  "type": "Feature",
  "properties": {
    "gn:admin1_code":"5",
    "gn:admin2_code":"68.0",
    "gn:asciiname":"General Emiliano Zapata (Zoque)",
    "gn:country_code":"MX",
    "gn:dem":29,
    "gn:feature_class":"P",
    "gn:feature_code":"PPL",
    "gn:name":"General Emiliano Zapata (Zoque)",
    "gn:population":152,
    "gn:timezone":"America/Mexico_City",
    "iso:country":"MX",
    "wof:name":"General Emiliano Zapata (Zoque)",
    "wof:placetype":"locality",
    "wof:population":152
},
  "geometry": {"coordinates":[-93.11167,17.54667],"type":"Point"}
}