{
  "type": "Feature",
  "properties": {
    "gn:admin1_code":"28.0",
    "gn:admin2_code":"7.0",
    "gn:asciiname":"Seccion Diez",
    "gn:country_code":"MX",
    "gn:dem":56,
    "gn:feature_class":"P",
    "gn:feature_code":"PPL",
    "gn:name":"Secci\u00f3n Diez",
    "gn:population":0,
    "gn:timezone":"America/Monterrey",
    "iso:country":"MX",
    "name:spa_x_preferred":[
        "Secci\u00f3n Diez"
    ],
    "wof:name":"Seccion Diez",
    "wof:placetype":"locality"
},
  "geometry": {"coordinates":[-98.83817999999999,26.24998],"type":"Point"}
}