{
  "type": "Feature",
  "properties": {
    "gn:admin1_code":"12",
    "gn:admin2_code":"46",
    "gn:asciiname":"Rancho Rafael Aburto (Los Carreno)",
    "gn:country_code":"MX",
    "gn:dem":53,
    "gn:feature_class":"P",
    "gn:feature_code":"PPL",
    "gn:name":"Rancho Rafael Aburto (Los Carre\u00f1o)",
    "gn:population":10,
    "gn:timezone":"America/Mexico_City",
    "iso:country":"MX",
    "name:und_x_variant":[
        "Rancho Rafael Aburto (Los Carre\u00f1o)"
    ],
    "wof:name":"Rancho Rafael Aburto (Los Carreno)",
    "wof:placetype":"locality",
    "wof:population":10
},
  "geometry": {"coordinates":[-98.38025,16.67017],"type":"Point"}
}