{
  "type": "Feature",
  "properties": {
    "gn:admin1_code":"12.0",
    "gn:admin2_code":"22.0",
    "gn:asciiname":"El Jilguero",
    "gn:country_code":"MX",
    "gn:dem":2184,
    "gn:feature_class":"P",
    "gn:feature_code":"PPL",
    "gn:name":"El Jilguero",
    "gn:population":0,
    "gn:timezone":"America/Mexico_City",
    "iso:country":"MX",
    "name:spa_x_preferred":[
        "El Jilguero"
    ],
    "wof:name":"El Jilguero",
    "wof:placetype":"locality"
},
  "geometry": {"coordinates":[-101.34713000000001,18.13064],"type":"Point"}
}