{
  "type": "Feature",
  "properties": {
    "gn:admin1_code":"30",
    "gn:admin2_code":"71.0",
    "gn:asciiname":"La Patrona",
    "gn:country_code":"MX",
    "gn:dem":1171,
    "gn:feature_class":"P",
    "gn:feature_code":"PPL",
    "gn:name":"La Patrona",
    "gn:population":354,
    "gn:timezone":"America/Mexico_City",
    "iso:country":"MX",
    "name:ell_x_preferred":[
        "La Patrona"
    ],
    "name:fra_x_preferred":[
        "La patrona"
    ],
    "name:hat_x_preferred":[
        "La patrona"
    ],
    "name:hun_x_preferred":[
        "Az \u00f6r\u00f6ks\u00e9g"
    ],
    "name:pol_x_preferred":[
        "La Patrona"
    ],
    "name:por_x_preferred":[
        "La patrona"
    ],
    "name:spa_x_preferred":[
        "La patrona"
    ],
    "name:srp_x_preferred":[
        "\u0413\u0430\u0437\u0434\u0430\u0440\u0438\u0446\u0430"
    ],
    "wof:name":"La Patrona",
    "wof:placetype":"locality",
    "wof:population":354
},
  "geometry": {"coordinates":[-96.93194,19.15639],"type":"Point"}
}