{
  "type": "Feature",
  "properties": {
    "gn:admin1_code":"11",
    "gn:admin2_code":"27.0",
    "gn:asciiname":"Los Martinez (El Coraje)",
    "gn:country_code":"MX",
    "gn:dem":1720,
    "gn:feature_class":"P",
    "gn:feature_code":"PPL",
    "gn:name":"Los Mart\u00ednez (El Coraje)",
    "gn:population":8,
    "gn:timezone":"America/Mexico_City",
    "iso:country":"MX",
    "name:und_x_variant":[
        "Los Mart\u00ednez (El Coraje)"
    ],
    "wof:name":"Los Martinez (El Coraje)",
    "wof:placetype":"locality",
    "wof:population":8
},
  "geometry": {"coordinates":[-101.14639,20.55028],"type":"Point"}
}