{
  "type": "Feature",
  "properties": {
    "gn:admin1_code":"20",
    "gn:admin2_code":"171.0",
    "gn:asciiname":"Pena Grande",
    "gn:country_code":"MX",
    "gn:dem":625,
    "gn:feature_class":"P",
    "gn:feature_code":"PPL",
    "gn:name":"Pe\u00f1a Grande",
    "gn:population":54,
    "gn:timezone":"America/Mexico_City",
    "iso:country":"MX",
    "name:und_x_variant":[
        "Pe\u00f1a Grande"
    ],
    "wof:name":"Pena Grande",
    "wof:placetype":"locality",
    "wof:population":54
},
  "geometry": {"coordinates":[-96.6375,18.18722],"type":"Point"}
}