{
  "type": "Feature",
  "properties": {
    "gn:admin1_code":"22",
    "gn:admin2_code":"10.0",
    "gn:asciiname":"Tres Lagunas",
    "gn:country_code":"MX",
    "gn:dem":1636,
    "gn:feature_class":"P",
    "gn:feature_code":"PPL",
    "gn:name":"Tres Lagunas",
    "gn:population":0,
    "gn:timezone":"America/Mexico_City",
    "iso:country":"MX",
    "name:por_x_preferred":[
        "Tres Lagunas"
    ],
    "name:spa_x_preferred":[
        "Tres Lagunas"
    ],
    "wof:name":"Tres Lagunas",
    "wof:placetype":"locality"
},
  "geometry": {"coordinates":[-99.20425,21.334],"type":"Point"}
}