{
  "type": "Feature",
  "properties": {
    "gn:admin1_code":"19",
    "gn:admin2_code":"17.0",
    "gn:asciiname":"Agua Nueva",
    "gn:country_code":"MX",
    "gn:dem":1922,
    "gn:feature_class":"P",
    "gn:feature_code":"PPL",
    "gn:name":"Agua Nueva",
    "gn:population":0,
    "gn:timezone":"America/Monterrey",
    "iso:country":"MX",
    "name:spa_x_preferred":[
        "Agua Nueva"
    ],
    "name:spa_x_variant":[
        "Agua nueva"
    ],
    "name:und_x_variant":[
        "Agua Nuevo"
    ],
    "wof:name":"Agua Nueva",
    "wof:placetype":"locality"
},
  "geometry": {"coordinates":[-99.99643,24.6845],"type":"Point"}
}