{
  "type": "Feature",
  "properties": {
    "gn:admin1_code":"11.0",
    "gn:asciiname":"San Antonio de Teran",
    "gn:country_code":"MX",
    "gn:dem":1718,
    "gn:feature_class":"P",
    "gn:feature_code":"PPL",
    "gn:name":"San Antonio de Ter\u00e1n",
    "gn:population":0,
    "gn:timezone":"America/Mexico_City",
    "iso:country":"MX",
    "name:spa_x_preferred":[
        "San Antonio de Ter\u00e1n"
    ],
    "wof:name":"San Antonio de Teran",
    "wof:placetype":"locality"
},
  "geometry": {"coordinates":[-101.13487000000001,20.44817],"type":"Point"}
}