{
  "type": "Feature",
  "properties": {
    "gn:admin1_code":"6",
    "gn:admin2_code":"29",
    "gn:asciiname":"El Volcan",
    "gn:country_code":"MX",
    "gn:dem":2305,
    "gn:feature_class":"P",
    "gn:feature_code":"PPL",
    "gn:name":"El Volc\u00e1n",
    "gn:population":13,
    "gn:timezone":"America/Chihuahua",
    "iso:country":"MX",
    "name:und_x_variant":[
        "El Volc\u00e1n"
    ],
    "wof:name":"El Volcan",
    "wof:placetype":"locality",
    "wof:population":13
},
  "geometry": {"coordinates":[-106.72861,26.31444],"type":"Point"}
}