{
  "type": "Feature",
  "properties": {
    "gn:admin1_code":"7.0",
    "gn:admin2_code":"38.0",
    "gn:asciiname":"Papalote de Santa Ana",
    "gn:country_code":"MX",
    "gn:dem":571,
    "gn:feature_class":"P",
    "gn:feature_code":"PPL",
    "gn:name":"Papalote de Santa Ana",
    "gn:population":0,
    "gn:timezone":"America/Monterrey",
    "iso:country":"MX",
    "name:spa_x_preferred":[
        "Papalote de Santa Ana"
    ],
    "wof:name":"Papalote de Santa Ana",
    "wof:placetype":"locality"
},
  "geometry": {"coordinates":[-101.54958999999999,29.22565],"type":"Point"}
}