{
  "type": "Feature",
  "properties": {
    "gn:admin1_code":"11",
    "gn:admin2_code":"5.0",
    "gn:asciiname":"La Flor",
    "gn:country_code":"MX",
    "gn:dem":1765,
    "gn:feature_class":"P",
    "gn:feature_code":"PPL",
    "gn:name":"La Flor",
    "gn:population":4,
    "gn:timezone":"America/Mexico_City",
    "iso:country":"MX",
    "name:fra_x_preferred":[
        "La flor"
    ],
    "wof:name":"La Flor",
    "wof:placetype":"locality",
    "wof:population":4
},
  "geometry": {"coordinates":[-100.73027999999999,20.52639],"type":"Point"}
}