{
  "type": "Feature",
  "properties": {
    "gn:admin1_code":"6.0",
    "gn:admin2_code":"10.0",
    "gn:asciiname":"Los Lobos",
    "gn:country_code":"MX",
    "gn:dem":1887,
    "gn:feature_class":"P",
    "gn:feature_code":"PPL",
    "gn:name":"Los Lobos",
    "gn:population":0,
    "gn:timezone":"America/Chihuahua",
    "iso:country":"MX",
    "name:spa_x_preferred":[
        "Los Lobos"
    ],
    "name:spa_x_variant":[
        "La Regina"
    ],
    "wof:name":"Los Lobos",
    "wof:placetype":"locality"
},
  "geometry": {"coordinates":[-107.13376,29.66605],"type":"Point"}
}