{
  "type": "Feature",
  "properties": {
    "gn:admin1_code":"27",
    "gn:admin2_code":"1.0",
    "gn:asciiname":"San Lazaro",
    "gn:country_code":"MX",
    "gn:dem":32,
    "gn:feature_class":"P",
    "gn:feature_code":"PPL",
    "gn:name":"San L\u00e1zaro",
    "gn:population":6,
    "gn:timezone":"America/Mexico_City",
    "iso:country":"MX",
    "name:ceb_x_preferred":[
        "San L\u00e1zaro"
    ],
    "name:deu_x_preferred":[
        "San L\u00e1zaro"
    ],
    "name:glg_x_preferred":[
        "San L\u00e1zaro"
    ],
    "name:nds_x_preferred":[
        "San L\u00e1zaro"
    ],
    "name:spa_x_preferred":[
        "San L\u00e1zaro"
    ],
    "name:srp_x_preferred":[
        "\u0421\u0430\u043d \u041b\u0430\u0437\u0430\u0440\u043e"
    ],
    "name:swe_x_preferred":[
        "San L\u00e1zaro"
    ],
    "wof:name":"San Lazaro",
    "wof:placetype":"locality",
    "wof:population":6
},
  "geometry": {"coordinates":[-91.41333,17.90833],"type":"Point"}
}