{
  "type": "Feature",
  "properties": {
    "gn:admin1_code":"6",
    "gn:admin2_code":"15.0",
    "gn:asciiname":"Moscu",
    "gn:country_code":"MX",
    "gn:dem":1504,
    "gn:feature_class":"P",
    "gn:feature_code":"PPL",
    "gn:name":"Mosc\u00fa",
    "gn:population":0,
    "gn:timezone":"America/Chihuahua",
    "iso:country":"MX",
    "name:spa_x_preferred":[
        "Mosc\u00fa"
    ],
    "name:und_x_variant":[
        "Rancho Mosco"
    ],
    "wof:name":"Moscu",
    "wof:placetype":"locality"
},
  "geometry": {"coordinates":[-105.17256999999999,29.6688],"type":"Point"}
}