{
  "type": "Feature",
  "properties": {
    "gn:admin1_code":"10",
    "gn:admin2_code":"21.0",
    "gn:asciiname":"La Baya",
    "gn:country_code":"MX",
    "gn:dem":1659,
    "gn:feature_class":"P",
    "gn:feature_code":"PPL",
    "gn:name":"La Baya",
    "gn:population":0,
    "gn:timezone":"America/Monterrey",
    "iso:country":"MX",
    "wof:name":"La Baya",
    "wof:placetype":"locality"
},
  "geometry": {"coordinates":[-104.11217000000001,24.87156],"type":"Point"}
}