{
  "type": "Feature",
  "properties": {
    "gn:admin1_code":"31",
    "gn:admin2_code":"92.0",
    "gn:asciiname":"Sahcaba",
    "gn:cc2":"MX",
    "gn:country_code":"MX",
    "gn:dem":28,
    "gn:feature_class":"P",
    "gn:feature_code":"PPL",
    "gn:name":"Sahcab\u00e1",
    "gn:population":0,
    "gn:timezone":"America/Merida",
    "iso:country":"MX",
    "name:und_x_variant":[
        "Sahacaba",
        "Sahcab\u00e1"
    ],
    "wof:name":"Sahcaba",
    "wof:placetype":"locality"
},
  "geometry": {"coordinates":[-88.28333000000001,20.43333],"type":"Point"}
}