{
  "type": "Feature",
  "properties": {
    "gn:admin1_code":"3",
    "gn:admin2_code":"1.0",
    "gn:asciiname":"Armendariz",
    "gn:country_code":"MX",
    "gn:dem":42,
    "gn:feature_class":"P",
    "gn:feature_code":"PPL",
    "gn:name":"Armend\u00e1riz",
    "gn:population":0,
    "gn:timezone":"America/Mazatlan",
    "iso:country":"MX",
    "name:spa_x_preferred":[
        "Armend\u00e1riz"
    ],
    "wof:name":"Armendariz",
    "wof:placetype":"locality"
},
  "geometry": {"coordinates":[-111.74448,25.30592],"type":"Point"}
}