{
  "type": "Feature",
  "properties": {
    "gn:admin1_code":"6",
    "gn:admin2_code":"63.0",
    "gn:asciiname":"San Antonio Rocheachic",
    "gn:cc2":"MX",
    "gn:country_code":"MX",
    "gn:dem":1770,
    "gn:feature_class":"P",
    "gn:feature_code":"PPL",
    "gn:name":"San Antonio Rocheachic",
    "gn:population":0,
    "gn:timezone":"America/Chihuahua",
    "iso:country":"MX",
    "name:und_x_variant":[
        "Rocheachic",
        "San Antonio Rocheachic"
    ],
    "wof:name":"San Antonio Rocheachic",
    "wof:placetype":"locality"
},
  "geometry": {"coordinates":[-107.88333,28.63333],"type":"Point"}
}