{
  "type": "Feature",
  "properties": {
    "gn:admin1_code":"30",
    "gn:admin2_code":"121.0",
    "gn:asciiname":"El Dormidero",
    "gn:cc2":"MX",
    "gn:country_code":"MX",
    "gn:dem":90,
    "gn:feature_class":"P",
    "gn:feature_code":"PPL",
    "gn:name":"El Dormidero",
    "gn:population":1,
    "gn:timezone":"America/Mexico_City",
    "iso:country":"MX",
    "name:und_x_variant":[
        "Dormidero",
        "El Dormidero"
    ],
    "wof:name":"El Dormidero",
    "wof:placetype":"locality",
    "wof:population":1
},
  "geometry": {"coordinates":[-97.92610999999999,21.47889],"type":"Point"}
}