{
  "type": "Feature",
  "properties": {
    "gn:admin1_code":"26",
    "gn:admin2_code":"70",
    "gn:asciiname":"El Cerrito",
    "gn:country_code":"MX",
    "gn:dem":534,
    "gn:feature_class":"P",
    "gn:feature_code":"PPL",
    "gn:name":"El Cerrito",
    "gn:population":13,
    "gn:timezone":"America/Hermosillo",
    "iso:country":"MX",
    "wof:name":"El Cerrito",
    "wof:placetype":"locality",
    "wof:population":13
},
  "geometry": {"coordinates":[-112.50556,31.64444],"type":"Point"}
}