{
  "type": "Feature",
  "properties": {
    "gn:admin1_code":"24",
    "gn:admin2_code":"11.0",
    "gn:asciiname":"El Mosco",
    "gn:country_code":"MX",
    "gn:dem":1403,
    "gn:feature_class":"P",
    "gn:feature_code":"PPL",
    "gn:name":"El Mosco",
    "gn:population":0,
    "gn:timezone":"America/Mexico_City",
    "iso:country":"MX",
    "name:spa_x_preferred":[
        "El Mosco"
    ],
    "wof:name":"El Mosco",
    "wof:placetype":"locality"
},
  "geometry": {"coordinates":[-100.43256,21.97718],"type":"Point"}
}