{
  "type": "Feature",
  "properties": {
    "gn:admin1_code":"30",
    "gn:admin2_code":"109",
    "gn:asciiname":"Rancho Nuevo",
    "gn:country_code":"MX",
    "gn:dem":472,
    "gn:feature_class":"P",
    "gn:feature_code":"PPL",
    "gn:name":"Rancho Nuevo",
    "gn:population":21,
    "gn:timezone":"America/Mexico_City",
    "iso:country":"MX",
    "wof:name":"Rancho Nuevo",
    "wof:placetype":"locality",
    "wof:population":21
},
  "geometry": {"coordinates":[-96.79722,19.90389],"type":"Point"}
}