{
  "type": "Feature",
  "properties": {
    "gn:admin1_code":"11",
    "gn:admin2_code":"3.0",
    "gn:asciiname":"Marlusa",
    "gn:country_code":"MX",
    "gn:dem":2029,
    "gn:feature_class":"P",
    "gn:feature_code":"PPL",
    "gn:name":"Marlusa",
    "gn:population":4,
    "gn:timezone":"America/Mexico_City",
    "iso:country":"MX",
    "wof:name":"Marlusa",
    "wof:placetype":"locality",
    "wof:population":4
},
  "geometry": {"coordinates":[-100.65639,20.98667],"type":"Point"}
}