{
  "type": "Feature",
  "properties": {
    "gn:admin1_code":"10",
    "gn:admin2_code":"14",
    "gn:asciiname":"Zalatita",
    "gn:country_code":"MX",
    "gn:dem":1737,
    "gn:feature_class":"P",
    "gn:feature_code":"PPL",
    "gn:name":"Zalatita",
    "gn:population":11,
    "gn:timezone":"America/Monterrey",
    "iso:country":"MX",
    "wof:name":"Zalatita",
    "wof:placetype":"locality",
    "wof:population":11
},
  "geometry": {"coordinates":[-104.38329,22.74226],"type":"Point"}
}