{
  "type": "Feature",
  "properties": {
    "iso:country":"MX",
    "name:ceb_x_preferred":[
        "La Trinidad"
    ],
    "name:deu_x_preferred":[
        "La Trinidad"
    ],
    "name:ita_x_preferred":[
        "La Trinidad"
    ],
    "name:nld_x_preferred":[
        "La Trinidad"
    ],
    "name:srp_x_preferred":[
        "\u041b\u0430 \u0422\u0440\u0438\u043d\u0438\u0434\u0430\u0434"
    ],
    "name:swe_x_preferred":[
        "La Trinidad"
    ],
    "name:vie_x_preferred":[
        "La Trinidad"
    ],
    "qs_pg:aaroncc":"MX",
    "qs_pg:name":"La Trinidad",
    "qs_pg:name_adm0":"M\u00e9xico",
    "qs_pg:name_adm1":"Mexico",
    "qs_pg:photos":1,
    "qs_pg:photos_1k":1,
    "qs_pg:photos_9k":1,
    "qs_pg:photos_9r":1,
    "qs_pg:photos_all":1,
    "qs_pg:photos_sr":1,
    "qs_pg:pop_sr":0,
    "qs_pg:qs_pg_placetype":"neighbourhood",
    "qs_pg:qs_pg_placetype_gp":"Suburb",
    "qs_pg:woe_adm0":23424900,
    "woe:adm0_id":23424900,
    "woe:name_adm0":"M\u00e9xico",
    "woe:name_adm1":"Mexico",
    "woe:placetype":"Suburb",
    "wof:name":"La Trinidad",
    "wof:placetype":"neighbourhood"
},
  "geometry": {"coordinates":[-99.60617000000001,18.970909],"type":"Point"}
}