{
  "type": "Feature",
  "properties": {
    "gn:admin1_code":"29",
    "gn:admin2_code":"31.0",
    "gn:asciiname":"Fraccion el Derramadero",
    "gn:country_code":"MX",
    "gn:dem":2639,
    "gn:feature_class":"P",
    "gn:feature_code":"PPL",
    "gn:name":"Fracci\u00f3n el Derramadero",
    "gn:population":5,
    "gn:timezone":"America/Mexico_City",
    "iso:country":"MX",
    "name:und_x_variant":[
        "Fracci\u00f3n el Derramadero"
    ],
    "wof:name":"Fraccion el Derramadero",
    "wof:placetype":"locality",
    "wof:population":5
},
  "geometry": {"coordinates":[-98.02455,19.54155],"type":"Point"}
}