{
  "type": "Feature",
  "properties": {
    "gn:admin1_code":"14.0",
    "gn:admin2_code":"68.0",
    "gn:asciiname":"Charco del Remolino",
    "gn:country_code":"MX",
    "gn:dem":863,
    "gn:feature_class":"P",
    "gn:feature_code":"PPL",
    "gn:name":"Charco del Remolino",
    "gn:population":0,
    "gn:timezone":"America/Mexico_City",
    "iso:country":"MX",
    "name:spa_x_preferred":[
        "Charco del Remolino"
    ],
    "wof:name":"Charco del Remolino",
    "wof:placetype":"locality"
},
  "geometry": {"coordinates":[-104.59573,19.88334],"type":"Point"}
}