{
  "type": "Feature",
  "properties": {
    "gn:admin1_code":"18",
    "gn:admin2_code":"15.0",
    "gn:asciiname":"Canada del Tabaco",
    "gn:country_code":"MX",
    "gn:dem":8,
    "gn:feature_class":"P",
    "gn:feature_code":"PPL",
    "gn:name":"Ca\u00f1ada del Tabaco",
    "gn:population":1636,
    "gn:timezone":"America/Mazatlan",
    "iso:country":"MX",
    "name:und_x_variant":[
        "Ca\u00f1ada del Tabaco"
    ],
    "wof:name":"Canada del Tabaco",
    "wof:placetype":"locality",
    "wof:population":1636
},
  "geometry": {"coordinates":[-105.35417,21.70972],"type":"Point"}
}