{
  "type": "Feature",
  "properties": {
    "gn:admin1_code":"32.0",
    "gn:admin2_code":"40.0",
    "gn:asciiname":"Atotonilco",
    "gn:country_code":"MX",
    "gn:dem":2051,
    "gn:feature_class":"P",
    "gn:feature_code":"PPL",
    "gn:name":"Atotonilco",
    "gn:population":0,
    "gn:timezone":"America/Mexico_City",
    "iso:country":"MX",
    "name:ceb_x_preferred":[
        "Atotonilco"
    ],
    "name:deu_x_preferred":[
        "Atotonilco"
    ],
    "name:ita_x_preferred":[
        "Atotonilco"
    ],
    "name:sco_x_preferred":[
        "Atotonilco"
    ],
    "name:spa_x_preferred":[
        "Atotonilco"
    ],
    "name:swe_x_preferred":[
        "Atotonilco"
    ],
    "wof:name":"Atotonilco",
    "wof:placetype":"locality"
},
  "geometry": {"coordinates":[-103.2641,23.55326],"type":"Point"}
}