{
  "type": "Feature",
  "properties": {
    "gn:admin1_code":"19",
    "gn:admin2_code":"9",
    "gn:asciiname":"El Olvido",
    "gn:country_code":"MX",
    "gn:dem":409,
    "gn:feature_class":"P",
    "gn:feature_code":"PPL",
    "gn:name":"El Olvido",
    "gn:population":42,
    "gn:timezone":"America/Monterrey",
    "iso:country":"MX",
    "wof:name":"El Olvido",
    "wof:placetype":"locality",
    "wof:population":42
},
  "geometry": {"coordinates":[-100.08889000000001,25.50139],"type":"Point"}
}