{
  "type": "Feature",
  "properties": {
    "gn:admin1_code":"16",
    "gn:admin2_code":"34.0",
    "gn:asciiname":"Fraccionamiento Lomas Casa Blanca",
    "gn:country_code":"MX",
    "gn:dem":2080,
    "gn:feature_class":"P",
    "gn:feature_code":"PPL",
    "gn:name":"Fraccionamiento Lomas Casa Blanca",
    "gn:population":6,
    "gn:timezone":"America/Mexico_City",
    "iso:country":"MX",
    "wof:name":"Fraccionamiento Lomas Casa Blanca",
    "wof:placetype":"locality",
    "wof:population":6
},
  "geometry": {"coordinates":[-100.60278,19.69611],"type":"Point"}
}