{
  "type": "Feature",
  "properties": {
    "gn:admin1_code":"30.0",
    "gn:admin2_code":"181.0",
    "gn:asciiname":"El Nuevo Despertar",
    "gn:country_code":"MX",
    "gn:dem":31,
    "gn:feature_class":"P",
    "gn:feature_code":"PPL",
    "gn:name":"El Nuevo Despertar",
    "gn:population":0,
    "gn:timezone":"America/Mexico_City",
    "iso:country":"MX",
    "name:spa_x_preferred":[
        "El Nuevo Despertar"
    ],
    "wof:name":"El Nuevo Despertar",
    "wof:placetype":"locality"
},
  "geometry": {"coordinates":[-96.1627,18.67723],"type":"Point"}
}