{
  "type": "Feature",
  "properties": {
    "gn:admin1_code":"25",
    "gn:admin2_code":"7",
    "gn:asciiname":"El Llano",
    "gn:country_code":"MX",
    "gn:dem":674,
    "gn:feature_class":"P",
    "gn:feature_code":"PPL",
    "gn:name":"El Llano",
    "gn:population":40,
    "gn:timezone":"America/Mazatlan",
    "iso:country":"MX",
    "wof:name":"El Llano",
    "wof:placetype":"locality",
    "wof:population":40
},
  "geometry": {"coordinates":[-108.10266,26.45466],"type":"Point"}
}