{
  "type": "Feature",
  "properties": {
    "gn:admin1_code":"6.0",
    "gn:admin2_code":"61.0",
    "gn:asciiname":"El Toro",
    "gn:country_code":"MX",
    "gn:dem":1496,
    "gn:feature_class":"P",
    "gn:feature_code":"PPL",
    "gn:name":"El Toro",
    "gn:population":0,
    "gn:timezone":"America/Chihuahua",
    "iso:country":"MX",
    "name:spa_x_preferred":[
        "El Toro"
    ],
    "wof:name":"El Toro",
    "wof:placetype":"locality"
},
  "geometry": {"coordinates":[-106.13294,27.76095],"type":"Point"}
}