{
  "type": "Feature",
  "properties": {
    "gn:admin1_code":"30",
    "gn:admin2_code":"114.0",
    "gn:asciiname":"Santa Teresa",
    "gn:country_code":"MX",
    "gn:dem":286,
    "gn:feature_class":"P",
    "gn:feature_code":"PPL",
    "gn:name":"Santa Teresa",
    "gn:population":6,
    "gn:timezone":"America/Mexico_City",
    "iso:country":"MX",
    "wof:name":"Santa Teresa",
    "wof:placetype":"locality",
    "wof:population":6
},
  "geometry": {"coordinates":[-96.83389,20.01917000000001],"type":"Point"}
}