{
  "type": "Feature",
  "properties": {
    "gn:admin1_code":"17",
    "gn:admin2_code":"19.0",
    "gn:asciiname":"Mano Pintada",
    "gn:country_code":"MX",
    "gn:dem":1136,
    "gn:feature_class":"P",
    "gn:feature_code":"PPL",
    "gn:name":"Mano Pintada",
    "gn:population":7,
    "gn:timezone":"America/Mexico_City",
    "iso:country":"MX",
    "wof:name":"Mano Pintada",
    "wof:placetype":"locality",
    "wof:population":7
},
  "geometry": {"coordinates":[-98.77333,18.58583],"type":"Point"}
}