{
  "type": "Feature",
  "properties": {
    "gn:admin1_code":"26.0",
    "gn:asciiname":"Baromiquito",
    "gn:country_code":"MX",
    "gn:dem":426,
    "gn:feature_class":"P",
    "gn:feature_code":"PPL",
    "gn:name":"Baromiquito",
    "gn:population":0,
    "gn:timezone":"America/Chihuahua",
    "iso:country":"MX",
    "name:und_x_variant":[
        "Rancho Baromiquito",
        "Baromiquito"
    ],
    "wof:name":"Baromiquito",
    "wof:placetype":"locality"
},
  "geometry": {"coordinates":[-108.5356,27.03792],"type":"Point"}
}