{
  "type": "Feature",
  "properties": {
    "gn:admin1_code":"26",
    "gn:admin2_code":"30.0",
    "gn:asciiname":"Don Isaac",
    "gn:country_code":"MX",
    "gn:dem":24,
    "gn:feature_class":"P",
    "gn:feature_code":"PPL",
    "gn:name":"Don Isaac",
    "gn:population":0,
    "gn:timezone":"America/Hermosillo",
    "iso:country":"MX",
    "name:spa_x_preferred":[
        "Don Isaac"
    ],
    "wof:name":"Don Isaac",
    "wof:placetype":"locality"
},
  "geometry": {"coordinates":[-111.28529,28.30561],"type":"Point"}
}