{
  "type": "Feature",
  "properties": {
    "gn:admin1_code":"7.0",
    "gn:asciiname":"Los Olleros",
    "gn:country_code":"MX",
    "gn:dem":1577,
    "gn:feature_class":"P",
    "gn:feature_code":"PPL",
    "gn:name":"Los Olleros",
    "gn:population":0,
    "gn:timezone":"America/Monterrey",
    "iso:country":"MX",
    "name:spa_x_preferred":[
        "Los Olleros"
    ],
    "wof:name":"Los Olleros",
    "wof:placetype":"locality"
},
  "geometry": {"coordinates":[-102.14684,25.41922000000001],"type":"Point"}
}