{
  "type": "Feature",
  "properties": {
    "gn:admin1_code":"25",
    "gn:admin2_code":"4.0",
    "gn:asciiname":"Los Cajones",
    "gn:country_code":"MX",
    "gn:dem":1631,
    "gn:feature_class":"P",
    "gn:feature_code":"PPL",
    "gn:name":"Los Cajones",
    "gn:population":0,
    "gn:timezone":"America/Mazatlan",
    "iso:country":"MX",
    "name:spa_x_preferred":[
        "Los Cajones"
    ],
    "wof:name":"Los Cajones",
    "wof:placetype":"locality"
},
  "geometry": {"coordinates":[-105.81762000000001,23.47475],"type":"Point"}
}