{
  "type": "Feature",
  "properties": {
    "gn:admin1_code":"27",
    "gn:admin2_code":"14.0",
    "gn:asciiname":"La Gloria",
    "gn:country_code":"MX",
    "gn:dem":7,
    "gn:feature_class":"P",
    "gn:feature_code":"PPL",
    "gn:name":"La Gloria",
    "gn:population":0,
    "gn:timezone":"America/Mexico_City",
    "iso:country":"MX",
    "name:ast_x_preferred":[
        "La Gloria"
    ],
    "name:ceb_x_preferred":[
        "La Gloria"
    ],
    "name:deu_x_preferred":[
        "La Gloria"
    ],
    "name:ita_x_preferred":[
        "La Gloria"
    ],
    "name:nld_x_preferred":[
        "La Gloria"
    ],
    "name:spa_x_preferred":[
        "Nicolas Bravo Segunda Secci\u00f3n"
    ],
    "name:spa_x_variant":[
        "La Gloria",
        "Nicol\u00e1s Bravo",
        "Segunda Secci\u00f3n"
    ],
    "name:swe_x_preferred":[
        "La Gloria"
    ],
    "name:vie_x_preferred":[
        "La Gloria"
    ],
    "wof:name":"La Gloria",
    "wof:placetype":"locality"
},
  "geometry": {"coordinates":[-93.11111,18.31435],"type":"Point"}
}