{
  "type": "Feature",
  "properties": {
    "gn:admin1_code":"2",
    "gn:admin2_code":"1",
    "gn:asciiname":"Rancho Carmelita",
    "gn:country_code":"MX",
    "gn:dem":304,
    "gn:feature_class":"P",
    "gn:feature_code":"PPL",
    "gn:name":"Rancho Carmelita",
    "gn:population":10,
    "gn:timezone":"America/Tijuana",
    "iso:country":"MX",
    "wof:name":"Rancho Carmelita",
    "wof:placetype":"locality",
    "wof:population":10
},
  "geometry": {"coordinates":[-116.65472,32.05417],"type":"Point"}
}