{
  "type": "Feature",
  "properties": {
    "gn:admin1_code":"11",
    "gn:admin2_code":"15.0",
    "gn:asciiname":"Taray",
    "gn:country_code":"MX",
    "gn:dem":2066,
    "gn:feature_class":"P",
    "gn:feature_code":"PPL",
    "gn:name":"Taray",
    "gn:population":0,
    "gn:timezone":"America/Mexico_City",
    "iso:country":"MX",
    "name:ceb_x_preferred":[
        "Taray"
    ],
    "name:swe_x_preferred":[
        "Taray"
    ],
    "wof:name":"Taray",
    "wof:placetype":"locality"
},
  "geometry": {"coordinates":[-101.18333,20.85],"type":"Point"}
}