{
  "type": "Feature",
  "properties": {
    "gn:admin1_code":"5.0",
    "gn:admin2_code":"51.0",
    "gn:asciiname":"La Playa",
    "gn:country_code":"MX",
    "gn:dem":38,
    "gn:feature_class":"P",
    "gn:feature_code":"PPL",
    "gn:name":"La Playa",
    "gn:population":0,
    "gn:timezone":"America/Mexico_City",
    "iso:country":"MX",
    "name:ceb_x_preferred":[
        "La Playa"
    ],
    "name:fra_x_preferred":[
        "La Playa"
    ],
    "name:nld_x_preferred":[
        "La Playa"
    ],
    "name:spa_x_preferred":[
        "Las Playas"
    ],
    "name:spa_x_variant":[
        "La Playa"
    ],
    "name:swe_x_preferred":[
        "La Playa"
    ],
    "wof:name":"La Playa",
    "wof:placetype":"locality"
},
  "geometry": {"coordinates":[-92.86353,15.4042],"type":"Point"}
}