{
  "type": "Feature",
  "properties": {
    "gn:admin1_code":"10",
    "gn:admin2_code":"23.0",
    "gn:asciiname":"Agua Verde",
    "gn:country_code":"MX",
    "gn:dem":888,
    "gn:feature_class":"P",
    "gn:feature_code":"PPL",
    "gn:name":"Agua Verde",
    "gn:population":92,
    "gn:timezone":"America/Monterrey",
    "iso:country":"MX",
    "wof:name":"Agua Verde",
    "wof:placetype":"locality",
    "wof:population":92
},
  "geometry": {"coordinates":[-105.154,23.10003],"type":"Point"}
}