{
  "type": "Feature",
  "properties": {
    "gn:admin1_code":"21",
    "gn:admin2_code":"71.0",
    "gn:asciiname":"Chicuase",
    "gn:country_code":"MX",
    "gn:dem":1823,
    "gn:feature_class":"P",
    "gn:feature_code":"PPL",
    "gn:name":"Chicuase",
    "gn:population":129,
    "gn:timezone":"America/Mexico_City",
    "iso:country":"MX",
    "wof:name":"Chicuase",
    "wof:placetype":"locality",
    "wof:population":129
},
  "geometry": {"coordinates":[-97.99258,20.12547],"type":"Point"}
}