{
  "type": "Feature",
  "properties": {
    "gn:admin1_code":"14",
    "gn:admin2_code":"71.0",
    "gn:asciiname":"Tepeaca",
    "gn:country_code":"MX",
    "gn:dem":1088,
    "gn:feature_class":"P",
    "gn:feature_code":"PPL",
    "gn:name":"Tepeaca",
    "gn:population":127,
    "gn:timezone":"America/Mexico_City",
    "iso:country":"MX",
    "wof:name":"Tepeaca",
    "wof:placetype":"locality",
    "wof:population":127
},
  "geometry": {"coordinates":[-103.52556,21.05389],"type":"Point"}
}