{
  "type": "Feature",
  "properties": {
    "gn:admin1_code":"14",
    "gn:admin2_code":"71.0",
    "gn:asciiname":"Tepeaca",
    "gn:country_code":"MX",
    "gn:dem":1088,
    "gn:feature_class":"P",
    "gn:feature_code":"PPL",
    "gn:name":"Tepeaca",
    "gn:population":127,
    "gn:timezone":"America/Mexico_City",
    "iso:country":"MX",
    "name:ceb_x_preferred":[
        "Tepeaca"
    ],
    "name:deu_x_preferred":[
        "Tepeaca"
    ],
    "name:epo_x_preferred":[
        "Tepeaca"
    ],
    "name:eus_x_preferred":[
        "Tepeaca"
    ],
    "name:ita_x_preferred":[
        "Tepeaca"
    ],
    "name:rus_x_preferred":[
        "\u0422\u0435\u043f\u0435\u0430\u043a\u0430"
    ],
    "name:spa_x_preferred":[
        "Tepeaca"
    ],
    "name:srp_x_preferred":[
        "\u041e\u043f\u0448\u0442\u0438\u043d\u0430 \u0422\u0435\u043f\u0435\u0430\u043a\u0430"
    ],
    "name:swe_x_preferred":[
        "Tepeaca"
    ],
    "name:vie_x_preferred":[
        "Tepeaca"
    ],
    "wof:name":"Tepeaca",
    "wof:placetype":"locality",
    "wof:population":127
},
  "geometry": {"coordinates":[-103.52556,21.05389],"type":"Point"}
}