{
  "type": "Feature",
  "properties": {
    "gn:admin1_code":"11.0",
    "gn:admin2_code":"31.0",
    "gn:asciiname":"El Panal",
    "gn:country_code":"MX",
    "gn:dem":1778,
    "gn:feature_class":"P",
    "gn:feature_code":"PPL",
    "gn:name":"El Panal",
    "gn:population":0,
    "gn:timezone":"America/Mexico_City",
    "iso:country":"MX",
    "name:spa_x_preferred":[
        "El Panal"
    ],
    "wof:name":"El Panal",
    "wof:placetype":"locality"
},
  "geometry": {"coordinates":[-101.70910000000001,20.89219],"type":"Point"}
}