{
  "type": "Feature",
  "properties": {
    "gn:admin1_code":"32",
    "gn:admin2_code":"10.0",
    "gn:asciiname":"El Banos",
    "gn:country_code":"MX",
    "gn:dem":2270,
    "gn:feature_class":"P",
    "gn:feature_code":"PPL",
    "gn:name":"El Ba\u00f1os",
    "gn:population":0,
    "gn:timezone":"America/Mexico_City",
    "iso:country":"MX",
    "name:spa_x_preferred":[
        "El Ba\u00f1os"
    ],
    "name:spa_x_variant":[
        "Ba\u00f1os"
    ],
    "wof:name":"El Banos",
    "wof:placetype":"locality"
},
  "geometry": {"coordinates":[-103.25273,23.30623],"type":"Point"}
}