{
  "type": "Feature",
  "properties": {
    "gn:admin1_code":"10",
    "gn:admin2_code":"13.0",
    "gn:asciiname":"El Grillo",
    "gn:country_code":"MX",
    "gn:dem":1159,
    "gn:feature_class":"P",
    "gn:feature_code":"PPL",
    "gn:name":"El Grillo",
    "gn:population":2,
    "gn:timezone":"America/Monterrey",
    "iso:country":"MX",
    "wof:name":"El Grillo",
    "wof:placetype":"locality",
    "wof:population":2
},
  "geometry": {"coordinates":[-103.96147000000001,26.31948],"type":"Point"}
}