{
  "type": "Feature",
  "properties": {
    "gn:admin1_code":"5",
    "gn:admin2_code":"30.0",
    "gn:asciiname":"Josefa Ortiz de Dominguez (La Fortuna)",
    "gn:country_code":"MX",
    "gn:dem":580,
    "gn:feature_class":"P",
    "gn:feature_code":"PPL",
    "gn:name":"Josefa Ortiz de Dom\u00ednguez (La Fortuna)",
    "gn:population":366,
    "gn:timezone":"America/Mexico_City",
    "iso:country":"MX",
    "name:und_x_variant":[
        "Josefa Ortiz de Dom\u00ednguez (La Fortuna)"
    ],
    "wof:name":"Josefa Ortiz de Dominguez (La Fortuna)",
    "wof:placetype":"locality",
    "wof:population":366
},
  "geometry": {"coordinates":[-92.2608,15.77444],"type":"Point"}
}