{
  "type": "Feature",
  "properties": {
    "gn:admin1_code":"5",
    "gn:admin2_code":"84",
    "gn:asciiname":"El Calvario",
    "gn:country_code":"MX",
    "gn:dem":324,
    "gn:feature_class":"P",
    "gn:feature_code":"PPL",
    "gn:name":"El Calvario",
    "gn:population":10,
    "gn:timezone":"America/Mexico_City",
    "iso:country":"MX",
    "wof:name":"El Calvario",
    "wof:placetype":"locality",
    "wof:population":10
},
  "geometry": {"coordinates":[-93.01000000000001,17.36667000000001],"type":"Point"}
}