{
  "type": "Feature",
  "properties": {
    "gn:admin1_code":"18",
    "gn:admin2_code":"9.0",
    "gn:asciiname":"Los Barros",
    "gn:country_code":"MX",
    "gn:dem":1306,
    "gn:feature_class":"P",
    "gn:feature_code":"PPL",
    "gn:name":"Los Barros",
    "gn:population":0,
    "gn:timezone":"America/Mazatlan",
    "iso:country":"MX",
    "name:spa_x_preferred":[
        "Los Barros"
    ],
    "wof:name":"Los Barros",
    "wof:placetype":"locality"
},
  "geometry": {"coordinates":[-104.35285,22.29985],"type":"Point"}
}