{
  "type": "Feature",
  "properties": {
    "gn:admin1_code":"18.0",
    "gn:admin2_code":"1.0",
    "gn:asciiname":"El Tejon",
    "gn:country_code":"MX",
    "gn:dem":48,
    "gn:feature_class":"P",
    "gn:feature_code":"PPL",
    "gn:name":"El Tej\u00f3n",
    "gn:population":0,
    "gn:timezone":"America/Mazatlan",
    "iso:country":"MX",
    "wof:name":"El Tejon",
    "wof:placetype":"locality"
},
  "geometry": {"coordinates":[-105.40000000000001,22.57083],"type":"Point"}
}