{
  "type": "Feature",
  "properties": {
    "gn:admin1_code":"23.0",
    "gn:asciiname":"Loma Seca",
    "gn:country_code":"MX",
    "gn:dem":26,
    "gn:feature_class":"P",
    "gn:feature_code":"PPL",
    "gn:name":"Loma Seca",
    "gn:population":0,
    "gn:timezone":"America/Cancun",
    "iso:country":"MX",
    "name:spa_x_preferred":[
        "Loma Seca"
    ],
    "wof:name":"Loma Seca",
    "wof:placetype":"locality"
},
  "geometry": {"coordinates":[-88.56043000000003,18.51012],"type":"Point"}
}