{
  "type": "Feature",
  "properties": {
    "gn:admin1_code":"12",
    "gn:admin2_code":"54.0",
    "gn:asciiname":"Tehuehuetla",
    "gn:country_code":"MX",
    "gn:dem":722,
    "gn:feature_class":"P",
    "gn:feature_code":"PPL",
    "gn:name":"Tehuehuetla",
    "gn:population":0,
    "gn:timezone":"America/Mexico_City",
    "iso:country":"MX",
    "name:spa_x_preferred":[
        "Tehuehuetla"
    ],
    "wof:name":"Tehuehuetla",
    "wof:placetype":"locality"
},
  "geometry": {"coordinates":[-100.4041,17.82522],"type":"Point"}
}