{
  "type": "Feature",
  "properties": {
    "gn:admin1_code":"15",
    "gn:admin2_code":"63.0",
    "gn:asciiname":"Santa Maria Nativitas",
    "gn:country_code":"MX",
    "gn:dem":2541,
    "gn:feature_class":"P",
    "gn:feature_code":"PPL",
    "gn:name":"Santa Mar\u00eda Nativitas",
    "gn:population":445,
    "gn:timezone":"America/Mexico_City",
    "iso:country":"MX",
    "wof:name":"Santa Maria Nativitas",
    "wof:placetype":"locality",
    "wof:population":445
},
  "geometry": {"coordinates":[-99.39082999999999,19.005],"type":"Point"}
}