{
  "type": "Feature",
  "properties": {
    "gn:admin1_code":"30.0",
    "gn:asciiname":"Anton Vicente",
    "gn:country_code":"MX",
    "gn:dem":5,
    "gn:feature_class":"P",
    "gn:feature_code":"PPL",
    "gn:name":"Ant\u00f3n Vicente",
    "gn:population":0,
    "gn:timezone":"America/Mexico_City",
    "iso:country":"MX",
    "name:spa_x_preferred":[
        "Ant\u00f3n Vicente"
    ],
    "wof:name":"Anton Vicente",
    "wof:placetype":"locality"
},
  "geometry": {"coordinates":[-95.57545,18.42157000000001],"type":"Point"}
}