{
  "type": "Feature",
  "properties": {
    "gn:admin1_code":"13",
    "gn:admin2_code":"74",
    "gn:asciiname":"El Sauz",
    "gn:country_code":"MX",
    "gn:dem":2098,
    "gn:feature_class":"P",
    "gn:feature_code":"PPL",
    "gn:name":"El Sauz",
    "gn:population":24,
    "gn:timezone":"America/Mexico_City",
    "iso:country":"MX",
    "wof:name":"El Sauz",
    "wof:placetype":"locality",
    "wof:population":24
},
  "geometry": {"coordinates":[-99.20553,20.12032],"type":"Point"}
}