{
  "type": "Feature",
  "properties": {
    "gn:admin1_code":"20",
    "gn:admin2_code":"413.0",
    "gn:asciiname":"Puente de Todos Santos",
    "gn:country_code":"MX",
    "gn:dem":154,
    "gn:feature_class":"P",
    "gn:feature_code":"PPL",
    "gn:name":"Puente de Todos Santos",
    "gn:population":0,
    "gn:timezone":"America/Mexico_City",
    "iso:country":"MX",
    "name:spa_x_preferred":[
        "Puente Todos Santos"
    ],
    "name:spa_x_variant":[
        "Puente de Todos Santos"
    ],
    "wof:name":"Puente de Todos Santos",
    "wof:placetype":"locality"
},
  "geometry": {"coordinates":[-96.29055,15.78548],"type":"Point"}
}