{
  "type": "Feature",
  "properties": {
    "gn:admin1_code":"12",
    "gn:admin2_code":"54",
    "gn:asciiname":"Laguna Seca",
    "gn:country_code":"MX",
    "gn:dem":1562,
    "gn:feature_class":"P",
    "gn:feature_code":"PPL",
    "gn:name":"Laguna Seca",
    "gn:population":14,
    "gn:timezone":"America/Mexico_City",
    "iso:country":"MX",
    "name:ceb_x_preferred":[
        "Laguna Seca"
    ],
    "name:deu_x_preferred":[
        "Laguna Seca"
    ],
    "name:nld_x_preferred":[
        "Laguna Seca"
    ],
    "name:srp_x_preferred":[
        "\u041b\u0430\u0433\u0443\u043d\u0430 \u0421\u0435\u043a\u0430"
    ],
    "name:swe_x_preferred":[
        "Laguna Seca"
    ],
    "wof:name":"Laguna Seca",
    "wof:placetype":"locality",
    "wof:population":14
},
  "geometry": {"coordinates":[-100.23867,17.87896],"type":"Point"}
}