{
  "type": "Feature",
  "properties": {
    "gn:admin1_code":"18.0",
    "gn:admin2_code":"19.0",
    "gn:asciiname":"Colomitos",
    "gn:country_code":"MX",
    "gn:dem":1631,
    "gn:feature_class":"P",
    "gn:feature_code":"PPL",
    "gn:name":"Colomitos",
    "gn:population":0,
    "gn:timezone":"America/Mexico_City",
    "iso:country":"MX",
    "name:spa_x_preferred":[
        "Colomitos"
    ],
    "wof:name":"Colomitos",
    "wof:placetype":"locality"
},
  "geometry": {"coordinates":[-104.05880000000001,21.49337],"type":"Point"}
}