{
  "type": "Feature",
  "properties": {
    "gn:admin1_code":"28.0",
    "gn:admin2_code":"32.0",
    "gn:asciiname":"Maria Luisa",
    "gn:country_code":"MX",
    "gn:dem":82,
    "gn:feature_class":"P",
    "gn:feature_code":"PPL",
    "gn:name":"Mar\u00eda Luisa",
    "gn:population":0,
    "gn:timezone":"America/Monterrey",
    "iso:country":"MX",
    "name:bre_x_preferred":[
        "Maria Luisa"
    ],
    "name:ita_x_preferred":[
        "Maria Luisa"
    ],
    "name:spa_x_preferred":[
        "Mar\u00eda Luisa"
    ],
    "wof:name":"Maria Luisa",
    "wof:placetype":"locality"
},
  "geometry": {"coordinates":[-98.58020999999999,25.9728],"type":"Point"}
}