{
  "type": "Feature",
  "properties": {
    "gn:admin1_code":"20",
    "gn:admin2_code":"6",
    "gn:asciiname":"Tiza-Coto",
    "gn:country_code":"MX",
    "gn:dem":2065,
    "gn:feature_class":"P",
    "gn:feature_code":"PPL",
    "gn:name":"Tiza-Coto",
    "gn:population":19,
    "gn:timezone":"America/Mexico_City",
    "iso:country":"MX",
    "wof:name":"Tiza-Coto",
    "wof:placetype":"locality",
    "wof:population":19
},
  "geometry": {"coordinates":[-97.19472,17.41111],"type":"Point"}
}