{
  "type": "Feature",
  "properties": {
    "gn:admin1_code":"23",
    "gn:asciiname":"Astro Rey",
    "gn:country_code":"MX",
    "gn:dem":84,
    "gn:feature_class":"P",
    "gn:feature_code":"PPL",
    "gn:name":"Astro Rey",
    "gn:population":0,
    "gn:timezone":"America/Cancun",
    "iso:country":"MX",
    "name:spa_x_preferred":[
        "Astro Rey"
    ],
    "wof:name":"Astro Rey",
    "wof:placetype":"locality"
},
  "geometry": {"coordinates":[-89.08118,18.94652],"type":"Point"}
}