{
  "type": "Feature",
  "properties": {
    "gn:admin1_code":"12",
    "gn:admin2_code":"51.0",
    "gn:asciiname":"Los Amates",
    "gn:country_code":"MX",
    "gn:dem":818,
    "gn:feature_class":"P",
    "gn:feature_code":"PPL",
    "gn:name":"Los Amates",
    "gn:population":73,
    "gn:timezone":"America/Mexico_City",
    "iso:country":"MX",
    "wof:name":"Los Amates",
    "wof:placetype":"locality",
    "wof:population":73
},
  "geometry": {"coordinates":[-99.14157,17.23384],"type":"Point"}
}