{
  "type": "Feature",
  "properties": {
    "gn:admin1_code":"30",
    "gn:admin2_code":"11.0",
    "gn:asciiname":"Juana Maria",
    "gn:country_code":"MX",
    "gn:dem":5,
    "gn:feature_class":"P",
    "gn:feature_code":"PPL",
    "gn:name":"Juana Mar\u00eda",
    "gn:population":96,
    "gn:timezone":"America/Mexico_City",
    "iso:country":"MX",
    "name:und_x_variant":[
        "Juana Mar\u00eda"
    ],
    "wof:name":"Juana Maria",
    "wof:placetype":"locality",
    "wof:population":96
},
  "geometry": {"coordinates":[-95.88833,18.83278],"type":"Point"}
}