{
  "type": "Feature",
  "properties": {
    "gn:admin1_code":"10",
    "gn:admin2_code":"36.0",
    "gn:asciiname":"Penjamo",
    "gn:country_code":"MX",
    "gn:dem":1094,
    "gn:feature_class":"P",
    "gn:feature_code":"PPL",
    "gn:name":"P\u00e9njamo",
    "gn:population":0,
    "gn:timezone":"America/Monterrey",
    "iso:country":"MX",
    "name:spa_x_preferred":[
        "P\u00e9njamo"
    ],
    "wof:name":"Penjamo",
    "wof:placetype":"locality"
},
  "geometry": {"coordinates":[-103.38663,25.97115],"type":"Point"}
}