{
  "type": "Feature",
  "properties": {
    "gn:admin1_code":"5.0",
    "gn:asciiname":"Muctajitic",
    "gn:country_code":"MX",
    "gn:dem":667,
    "gn:feature_class":"P",
    "gn:feature_code":"PPL",
    "gn:name":"Muctajitic",
    "gn:population":0,
    "gn:timezone":"America/Mexico_City",
    "iso:country":"MX",
    "name:spa_x_preferred":[
        "Muctajitic"
    ],
    "wof:name":"Muctajitic",
    "wof:placetype":"locality"
},
  "geometry": {"coordinates":[-92.71406,16.29112000000001],"type":"Point"}
}