{
  "type": "Feature",
  "properties": {
    "gn:admin1_code":"21",
    "gn:admin2_code":"74.0",
    "gn:asciiname":"Los Oroza",
    "gn:country_code":"MX",
    "gn:dem":2311,
    "gn:feature_class":"P",
    "gn:feature_code":"PPL",
    "gn:name":"Los Oroza",
    "gn:population":271,
    "gn:timezone":"America/Mexico_City",
    "iso:country":"MX",
    "wof:name":"Los Oroza",
    "wof:placetype":"locality",
    "wof:population":271
},
  "geometry": {"coordinates":[-98.42937999999999,19.16128],"type":"Point"}
}