{
  "type": "Feature",
  "properties": {
    "gn:admin1_code":"6.0",
    "gn:admin2_code":"42.0",
    "gn:asciiname":"Los Altares",
    "gn:country_code":"MX",
    "gn:dem":732,
    "gn:feature_class":"P",
    "gn:feature_code":"PPL",
    "gn:name":"Los Altares",
    "gn:population":0,
    "gn:timezone":"America/Chihuahua",
    "iso:country":"MX",
    "name:ita_x_preferred":[
        "Los Altares"
    ],
    "name:nld_x_preferred":[
        "Los Altares"
    ],
    "name:spa_x_preferred":[
        "Los Altares"
    ],
    "name:und_x_variant":[
        "Ejido de los Altares",
        "Altares"
    ],
    "wof:name":"Los Altares",
    "wof:placetype":"locality"
},
  "geometry": {"coordinates":[-103.40372000000001,28.89376],"type":"Point"}
}