{
  "type": "Feature",
  "properties": {
    "gn:admin1_code":"32",
    "gn:admin2_code":"25.0",
    "gn:asciiname":"Colonia Veinte de Noviembre",
    "gn:country_code":"MX",
    "gn:dem":2020,
    "gn:feature_class":"P",
    "gn:feature_code":"PPL",
    "gn:name":"Colonia Veinte de Noviembre",
    "gn:population":0,
    "gn:timezone":"America/Mexico_City",
    "iso:country":"MX",
    "name:und_x_variant":[
        "Veinte de Noviembre"
    ],
    "wof:name":"Colonia Veinte de Noviembre",
    "wof:placetype":"locality"
},
  "geometry": {"coordinates":[-102.2816,22.50239],"type":"Point"}
}