{
  "type": "Feature",
  "properties": {
    "gn:admin1_code":"25.0",
    "gn:asciiname":"Luis Echeverria Alvarez",
    "gn:country_code":"MX",
    "gn:dem":20,
    "gn:feature_class":"P",
    "gn:feature_code":"PPL",
    "gn:name":"Luis Echeverria Alvarez",
    "gn:population":0,
    "gn:timezone":"America/Mazatlan",
    "iso:country":"MX",
    "name:spa_x_preferred":[
        "Luis Echeverria Alvarez"
    ],
    "name:spa_x_variant":[
        "Luis Echeverr\u00eda Alv\u00e1rez"
    ],
    "wof:name":"Luis Echeverria Alvarez",
    "wof:placetype":"locality"
},
  "geometry": {"coordinates":[-108.86181999999999,25.81208],"type":"Point"}
}