{
  "type": "Feature",
  "properties": {
    "gn:admin1_code":"15.0",
    "gn:admin2_code":"39.0",
    "gn:asciiname":"La Cotera",
    "gn:country_code":"MX",
    "gn:dem":2241,
    "gn:feature_class":"P",
    "gn:feature_code":"PPL",
    "gn:name":"La Cotera",
    "gn:population":0,
    "gn:timezone":"America/Mexico_City",
    "iso:country":"MX",
    "name:spa_x_preferred":[
        "La Catera"
    ],
    "name:spa_x_variant":[
        "La Cotera"
    ],
    "wof:name":"La Cotera",
    "wof:placetype":"locality"
},
  "geometry": {"coordinates":[-98.89212000000001,19.29969],"type":"Point"}
}