{
  "type": "Feature",
  "properties": {
    "gn:admin1_code":"16.0",
    "gn:admin2_code":"96.0",
    "gn:asciiname":"El Resumidero",
    "gn:country_code":"MX",
    "gn:dem":1530,
    "gn:feature_class":"P",
    "gn:feature_code":"PPL",
    "gn:name":"El Resumidero",
    "gn:population":0,
    "gn:timezone":"America/Mexico_City",
    "iso:country":"MX",
    "name:spa_x_preferred":[
        "El Resumidero"
    ],
    "wof:name":"El Resumidero",
    "wof:placetype":"locality"
},
  "geometry": {"coordinates":[-102.64491,18.45582000000001],"type":"Point"}
}