{
  "type": "Feature",
  "properties": {
    "gn:admin1_code":"6",
    "gn:admin2_code":"7.0",
    "gn:asciiname":"Paraje La Colorada",
    "gn:country_code":"MX",
    "gn:dem":2574,
    "gn:feature_class":"P",
    "gn:feature_code":"PPL",
    "gn:name":"Paraje La Colorada",
    "gn:population":0,
    "gn:timezone":"America/Chihuahua",
    "iso:country":"MX",
    "name:spa_x_preferred":[
        "Paraje La Colorada"
    ],
    "wof:name":"Paraje La Colorada",
    "wof:placetype":"locality"
},
  "geometry": {"coordinates":[-106.52073,26.64868],"type":"Point"}
}