{
  "type": "Feature",
  "properties": {
    "gn:admin1_code":"28",
    "gn:admin2_code":"33.0",
    "gn:asciiname":"Manuel Rodriguez Cavazos",
    "gn:country_code":"MX",
    "gn:dem":19,
    "gn:feature_class":"P",
    "gn:feature_code":"PPL",
    "gn:name":"Manuel Rodr\u00edguez Cavazos",
    "gn:population":6,
    "gn:timezone":"America/Monterrey",
    "iso:country":"MX",
    "name:und_x_variant":[
        "Manuel Rodr\u00edguez Cavazos"
    ],
    "wof:name":"Manuel Rodriguez Cavazos",
    "wof:placetype":"locality",
    "wof:population":6
},
  "geometry": {"coordinates":[-97.95860999999999,25.58583],"type":"Point"}
}