{
  "type": "Feature",
  "properties": {
    "gn:admin1_code":"28",
    "gn:admin2_code":"39.0",
    "gn:asciiname":"Nicolas Medrano",
    "gn:country_code":"MX",
    "gn:dem":1200,
    "gn:feature_class":"P",
    "gn:feature_code":"PPL",
    "gn:name":"Nicol\u00e1s Medrano",
    "gn:population":0,
    "gn:timezone":"America/Monterrey",
    "iso:country":"MX",
    "wof:name":"Nicolas Medrano",
    "wof:placetype":"locality"
},
  "geometry": {"coordinates":[-99.78576,23.0952],"type":"Point"}
}