{
  "type": "Feature",
  "properties": {
    "gn:admin1_code":"15",
    "gn:admin2_code":"46.0",
    "gn:asciiname":"Barrio Gorondoni",
    "gn:country_code":"MX",
    "gn:dem":2824,
    "gn:feature_class":"P",
    "gn:feature_code":"PPL",
    "gn:name":"Barrio Gorondoni",
    "gn:population":98,
    "gn:timezone":"America/Mexico_City",
    "iso:country":"MX",
    "wof:name":"Barrio Gorondoni",
    "wof:placetype":"locality",
    "wof:population":98
},
  "geometry": {"coordinates":[-99.40342,19.53632],"type":"Point"}
}