{
  "type": "Feature",
  "properties": {
    "gn:admin1_code":"7",
    "gn:admin2_code":"37.0",
    "gn:asciiname":"La Gloria",
    "gn:country_code":"MX",
    "gn:dem":374,
    "gn:feature_class":"P",
    "gn:feature_code":"PPL",
    "gn:name":"La Gloria",
    "gn:population":6,
    "gn:timezone":"America/Monterrey",
    "iso:country":"MX",
    "name:ast_x_preferred":[
        "La Gloria"
    ],
    "name:ceb_x_preferred":[
        "La Gloria"
    ],
    "name:deu_x_preferred":[
        "La Gloria"
    ],
    "name:ita_x_preferred":[
        "La Gloria"
    ],
    "name:nld_x_preferred":[
        "La Gloria"
    ],
    "name:spa_x_preferred":[
        "La Gloria"
    ],
    "name:swe_x_preferred":[
        "La Gloria"
    ],
    "name:vie_x_preferred":[
        "La Gloria"
    ],
    "wof:name":"La Gloria",
    "wof:placetype":"locality",
    "wof:population":6
},
  "geometry": {"coordinates":[-100.75175,28.24527],"type":"Point"}
}