{
  "type": "Feature",
  "properties": {
    "gn:admin1_code":"14.0",
    "gn:admin2_code":"61.0",
    "gn:asciiname":"Los Cantaros",
    "gn:country_code":"MX",
    "gn:dem":1870,
    "gn:feature_class":"P",
    "gn:feature_code":"PPL",
    "gn:name":"Los C\u00e1ntaros",
    "gn:population":0,
    "gn:timezone":"America/Mexico_City",
    "iso:country":"MX",
    "name:spa_x_preferred":[
        "Los C\u00e1ntaros"
    ],
    "wof:name":"Los Cantaros",
    "wof:placetype":"locality"
},
  "geometry": {"coordinates":[-104.29604,22.2578],"type":"Point"}
}