{
  "type": "Feature",
  "properties": {
    "gn:admin1_code":"26",
    "gn:admin2_code":"12.0",
    "gn:asciiname":"Eligio Lugo",
    "gn:country_code":"MX",
    "gn:dem":16,
    "gn:feature_class":"P",
    "gn:feature_code":"PPL",
    "gn:name":"Eligio Lugo",
    "gn:population":5,
    "gn:timezone":"America/Hermosillo",
    "iso:country":"MX",
    "wof:name":"Eligio Lugo",
    "wof:placetype":"locality",
    "wof:population":5
},
  "geometry": {"coordinates":[-110.17638999999998,27.46333],"type":"Point"}
}