{
  "type": "Feature",
  "properties": {
    "gn:admin1_code":"19",
    "gn:admin2_code":"9.0",
    "gn:asciiname":"Los Garza",
    "gn:country_code":"MX",
    "gn:dem":369,
    "gn:feature_class":"P",
    "gn:feature_code":"PPL",
    "gn:name":"Los Garza",
    "gn:population":5,
    "gn:timezone":"America/Monterrey",
    "iso:country":"MX",
    "wof:name":"Los Garza",
    "wof:placetype":"locality",
    "wof:population":5
},
  "geometry": {"coordinates":[-99.99418,25.43617],"type":"Point"}
}