{
  "type": "Feature",
  "properties": {
    "gn:admin1_code":"14.0",
    "gn:admin2_code":"86.0",
    "gn:asciiname":"Potrero de la Tuna Amarilla",
    "gn:country_code":"MX",
    "gn:dem":2029,
    "gn:feature_class":"P",
    "gn:feature_code":"PPL",
    "gn:name":"Potrero de la Tuna Amarilla",
    "gn:population":0,
    "gn:timezone":"America/Mexico_City",
    "iso:country":"MX",
    "name:spa_x_preferred":[
        "Potrero de la Tuna Amarilla"
    ],
    "wof:name":"Potrero de la Tuna Amarilla",
    "wof:placetype":"locality"
},
  "geometry": {"coordinates":[-103.76809,19.92448],"type":"Point"}
}