{
  "type": "Feature",
  "properties": {
    "gn:admin1_code":"7.0",
    "gn:admin2_code":"28.0",
    "gn:asciiname":"El Bonito",
    "gn:country_code":"MX",
    "gn:dem":335,
    "gn:feature_class":"P",
    "gn:feature_code":"PPL",
    "gn:name":"El Bonito",
    "gn:population":0,
    "gn:timezone":"America/Monterrey",
    "iso:country":"MX",
    "name:spa_x_preferred":[
        "El Bonito"
    ],
    "wof:name":"El Bonito",
    "wof:placetype":"locality"
},
  "geometry": {"coordinates":[-101.03308,27.80038],"type":"Point"}
}