{
  "type": "Feature",
  "properties": {
    "gn:admin1_code":"20",
    "gn:admin2_code":"234.0",
    "gn:asciiname":"Los Frailes",
    "gn:country_code":"MX",
    "gn:dem":2060,
    "gn:feature_class":"P",
    "gn:feature_code":"PPL",
    "gn:name":"Los Frailes",
    "gn:population":0,
    "gn:timezone":"America/Mexico_City",
    "iso:country":"MX",
    "name:spa_x_preferred":[
        "Los Frailes"
    ],
    "wof:name":"Los Frailes",
    "wof:placetype":"locality"
},
  "geometry": {"coordinates":[-96.94875999999999,18.10294],"type":"Point"}
}