{
  "type": "Feature",
  "properties": {
    "gn:admin1_code":"12.0",
    "gn:admin2_code":"38.0",
    "gn:asciiname":"Laguna de Abajo",
    "gn:country_code":"MX",
    "gn:dem":856,
    "gn:feature_class":"P",
    "gn:feature_code":"PPL",
    "gn:name":"Laguna de Abajo",
    "gn:population":0,
    "gn:timezone":"America/Mexico_City",
    "iso:country":"MX",
    "name:spa_x_preferred":[
        "Laguna de Abajo"
    ],
    "wof:name":"Laguna de Abajo",
    "wof:placetype":"locality"
},
  "geometry": {"coordinates":[-101.27453,17.89803999999999],"type":"Point"}
}