{
  "type": "Feature",
  "properties": {
    "gn:admin1_code":"12.0",
    "gn:admin2_code":"22.0",
    "gn:asciiname":"Sesteadero",
    "gn:country_code":"MX",
    "gn:dem":290,
    "gn:feature_class":"P",
    "gn:feature_code":"PPL",
    "gn:name":"Sesteadero",
    "gn:population":0,
    "gn:timezone":"America/Mexico_City",
    "iso:country":"MX",
    "name:spa_x_preferred":[
        "Sesteadero"
    ],
    "name:und_x_variant":[
        "El Sesteadero"
    ],
    "wof:name":"Sesteadero",
    "wof:placetype":"locality"
},
  "geometry": {"coordinates":[-100.73769,18.26889],"type":"Point"}
}