{
  "type": "Feature",
  "properties": {
    "gn:admin1_code":"10.0",
    "gn:admin2_code":"23.0",
    "gn:asciiname":"Coscomatito",
    "gn:country_code":"MX",
    "gn:dem":2382,
    "gn:feature_class":"P",
    "gn:feature_code":"PPL",
    "gn:name":"Coscomatito",
    "gn:population":0,
    "gn:timezone":"America/Monterrey",
    "iso:country":"MX",
    "name:und_x_variant":[
        "Coscomate"
    ],
    "wof:name":"Coscomatito",
    "wof:placetype":"locality"
},
  "geometry": {"coordinates":[-105.58880000000001,23.69155],"type":"Point"}
}