{
  "type": "Feature",
  "properties": {
    "gn:admin1_code":"9.0",
    "gn:admin2_code":"11.0",
    "gn:asciiname":"San Pedro Tlahuac",
    "gn:country_code":"MX",
    "gn:dem":2237,
    "gn:feature_class":"P",
    "gn:feature_code":"PPL",
    "gn:name":"San Pedro Tl\u00e1huac",
    "gn:population":0,
    "gn:timezone":"America/Mexico_City",
    "iso:country":"MX",
    "name:spa_x_preferred":[
        "San Pedro Tl\u00e1huac"
    ],
    "wof:name":"San Pedro Tlahuac",
    "wof:placetype":"locality"
},
  "geometry": {"coordinates":[-98.99845999999999,19.26927],"type":"Point"}
}