{
  "type": "Feature",
  "properties": {
    "gn:admin1_code":"30",
    "gn:admin2_code":"123.0",
    "gn:asciiname":"Vuelta de las Adjuntas",
    "gn:country_code":"MX",
    "gn:dem":23,
    "gn:feature_class":"P",
    "gn:feature_code":"PPL",
    "gn:name":"Vuelta de las Adjuntas",
    "gn:population":0,
    "gn:timezone":"America/Mexico_City",
    "iso:country":"MX",
    "name:und_x_variant":[
        "Adjuntas",
        "La Vuelta de las Adjuntas"
    ],
    "wof:name":"Vuelta de las Adjuntas",
    "wof:placetype":"locality"
},
  "geometry": {"coordinates":[-98.57822,21.96232],"type":"Point"}
}