{
  "type": "Feature",
  "properties": {
    "gn:admin1_code":"26.0",
    "gn:admin2_code":"3.0",
    "gn:asciiname":"Gocopiro",
    "gn:cc2":"MX",
    "gn:country_code":"MX",
    "gn:dem":557,
    "gn:feature_class":"P",
    "gn:feature_code":"PPL",
    "gn:name":"Gocopiro",
    "gn:population":0,
    "gn:timezone":"America/Hermosillo",
    "iso:country":"MX",
    "name:und_x_variant":[
        "Cocopiro",
        "Gocopiro"
    ],
    "wof:name":"Gocopiro",
    "wof:placetype":"locality"
},
  "geometry": {"coordinates":[-108.83333,27.58333],"type":"Point"}
}