{
  "type": "Feature",
  "properties": {
    "gn:admin1_code":"31",
    "gn:admin2_code":"69.0",
    "gn:asciiname":"Zavala",
    "gn:country_code":"MX",
    "gn:dem":18,
    "gn:feature_class":"P",
    "gn:feature_code":"PPL",
    "gn:name":"Zavala",
    "gn:population":0,
    "gn:timezone":"America/Merida",
    "iso:country":"MX",
    "name:bos_x_preferred":[
        "Zavala"
    ],
    "name:ceb_x_preferred":[
        "Zavala"
    ],
    "name:deu_x_preferred":[
        "Zavala"
    ],
    "name:est_x_preferred":[
        "Zavala"
    ],
    "name:fra_x_preferred":[
        "Zavala"
    ],
    "name:hrv_x_preferred":[
        "Zavala"
    ],
    "name:hun_x_preferred":[
        "Zavala"
    ],
    "name:ita_x_preferred":[
        "Zavala"
    ],
    "name:nld_x_preferred":[
        "Zavala"
    ],
    "name:rus_x_preferred":[
        "\u0417\u0430\u0432\u0430\u043b\u0430"
    ],
    "name:slv_x_preferred":[
        "Zavala"
    ],
    "name:spa_x_preferred":[
        "Zavala"
    ],
    "name:srp_x_preferred":[
        "\u0417\u0430\u0432\u0430\u043b\u0430"
    ],
    "name:swe_x_preferred":[
        "Zavala"
    ],
    "name:ukr_x_preferred":[
        "\u0417\u0430\u0432\u0430\u043b\u0430"
    ],
    "wof:name":"Zavala",
    "wof:placetype":"locality"
},
  "geometry": {"coordinates":[-89.11525,20.60954],"type":"Point"}
}