{
  "type": "Feature",
  "properties": {
    "gn:admin1_code":"7",
    "gn:admin2_code":"17",
    "gn:asciiname":"El Tejaban",
    "gn:country_code":"MX",
    "gn:dem":1113,
    "gn:feature_class":"P",
    "gn:feature_code":"PPL",
    "gn:name":"El Tejab\u00e1n",
    "gn:population":26,
    "gn:timezone":"America/Monterrey",
    "iso:country":"MX",
    "name:und_x_variant":[
        "El Tejab\u00e1n"
    ],
    "wof:name":"El Tejaban",
    "wof:placetype":"locality",
    "wof:population":26
},
  "geometry": {"coordinates":[-103.22785,25.76277],"type":"Point"}
}