{
  "type": "Feature",
  "properties": {
    "gn:admin1_code":"30.0",
    "gn:admin2_code":"175.0",
    "gn:asciiname":"Chichimantla Segundo",
    "gn:country_code":"MX",
    "gn:dem":57,
    "gn:feature_class":"P",
    "gn:feature_code":"PPL",
    "gn:name":"Chichimantla Segundo",
    "gn:population":0,
    "gn:timezone":"America/Mexico_City",
    "iso:country":"MX",
    "name:spa_x_preferred":[
        "Chilchimantla Segundo"
    ],
    "name:spa_x_variant":[
        "Chichimantla Segundo"
    ],
    "wof:name":"Chichimantla Segundo",
    "wof:placetype":"locality"
},
  "geometry": {"coordinates":[-97.46821,20.70373],"type":"Point"}
}