{
  "type": "Feature",
  "properties": {
    "gn:admin1_code":"6",
    "gn:admin2_code":"31",
    "gn:asciiname":"El Capulin",
    "gn:country_code":"MX",
    "gn:dem":2611,
    "gn:feature_class":"P",
    "gn:feature_code":"PPL",
    "gn:name":"El Capul\u00edn",
    "gn:population":10,
    "gn:timezone":"America/Chihuahua",
    "iso:country":"MX",
    "name:und_x_variant":[
        "El Capul\u00edn"
    ],
    "wof:name":"El Capulin",
    "wof:placetype":"locality",
    "wof:population":10
},
  "geometry": {"coordinates":[-107.90134999999999,28.11891],"type":"Point"}
}