{
  "type": "Feature",
  "properties": {
    "gn:admin1_code":"10",
    "gn:admin2_code":"32.0",
    "gn:asciiname":"Meleros",
    "gn:country_code":"MX",
    "gn:dem":1693,
    "gn:feature_class":"P",
    "gn:feature_code":"PPL",
    "gn:name":"Meleros",
    "gn:population":57,
    "gn:timezone":"America/Monterrey",
    "iso:country":"MX",
    "wof:name":"Meleros",
    "wof:placetype":"locality",
    "wof:population":57
},
  "geometry": {"coordinates":[-105.44062,25.12138],"type":"Point"}
}