{
  "type": "Feature",
  "properties": {
    "gn:admin1_code":"30",
    "gn:admin2_code":"24.0",
    "gn:asciiname":"Rincon de Poxtla",
    "gn:country_code":"MX",
    "gn:dem":1049,
    "gn:feature_class":"P",
    "gn:feature_code":"PPL",
    "gn:name":"Rinc\u00f3n de Poxtla",
    "gn:population":0,
    "gn:timezone":"America/Mexico_City",
    "iso:country":"MX",
    "name:spa_x_preferred":[
        "Rinc\u00f3n de Poxtla"
    ],
    "name:und_x_variant":[
        "Rinc\u00f3n de Poxtl\u00e1"
    ],
    "wof:name":"Rincon de Poxtla",
    "wof:placetype":"locality"
},
  "geometry": {"coordinates":[-96.91372,19.28143],"type":"Point"}
}