{
  "type": "Feature",
  "properties": {
    "gn:admin1_code":"21",
    "gn:admin2_code":"208",
    "gn:asciiname":"La Ferreria",
    "gn:country_code":"MX",
    "gn:dem":2145,
    "gn:feature_class":"P",
    "gn:feature_code":"PPL",
    "gn:name":"La Ferrer\u00eda",
    "gn:population":30,
    "gn:timezone":"America/Mexico_City",
    "iso:country":"MX",
    "name:und_x_variant":[
        "La Ferrer\u00eda"
    ],
    "wof:name":"La Ferreria",
    "wof:placetype":"locality",
    "wof:population":30
},
  "geometry": {"coordinates":[-97.98666,20.00972],"type":"Point"}
}