{
  "type": "Feature",
  "properties": {
    "gn:admin1_code":"7",
    "gn:admin2_code":"26.0",
    "gn:asciiname":"La Rana",
    "gn:country_code":"MX",
    "gn:dem":355,
    "gn:feature_class":"P",
    "gn:feature_code":"PPL",
    "gn:name":"La Rana",
    "gn:population":0,
    "gn:timezone":"America/Monterrey",
    "iso:country":"MX",
    "name:spa_x_preferred":[
        "La Rana"
    ],
    "name:und_x_variant":[
        "Rancho La Rana"
    ],
    "wof:name":"La Rana",
    "wof:placetype":"locality"
},
  "geometry": {"coordinates":[-101.11475,27.54939],"type":"Point"}
}