{
  "type": "Feature",
  "properties": {
    "gn:admin1_code":"10",
    "gn:admin2_code":"16.0",
    "gn:asciiname":"El Vergel",
    "gn:country_code":"MX",
    "gn:dem":1882,
    "gn:feature_class":"P",
    "gn:feature_code":"PPL",
    "gn:name":"El Vergel",
    "gn:population":0,
    "gn:timezone":"America/Monterrey",
    "iso:country":"MX",
    "name:spa_x_preferred":[
        "El Vergel"
    ],
    "wof:name":"El Vergel",
    "wof:placetype":"locality"
},
  "geometry": {"coordinates":[-104.06854,23.80579],"type":"Point"}
}