{
  "type": "Feature",
  "properties": {
    "gn:admin1_code":"25",
    "gn:admin2_code":"14.0",
    "gn:asciiname":"Santa Maria (Santa Maria de Gracia)",
    "gn:country_code":"MX",
    "gn:dem":104,
    "gn:feature_class":"P",
    "gn:feature_code":"PPL",
    "gn:name":"Santa Mar\u00eda (Santa Mar\u00eda de Gracia)",
    "gn:population":246,
    "gn:timezone":"America/Mazatlan",
    "iso:country":"MX",
    "name:und_x_variant":[
        "Santa Mar\u00eda (Santa Mar\u00eda de Gracia)"
    ],
    "wof:name":"Santa Maria (Santa Maria de Gracia)",
    "wof:placetype":"locality",
    "wof:population":246
},
  "geometry": {"coordinates":[-105.6675,23.11056],"type":"Point"}
}