{
  "type": "Feature",
  "properties": {
    "gn:admin1_code":"13",
    "gn:admin2_code":"50.0",
    "gn:asciiname":"La Rancheria",
    "gn:country_code":"MX",
    "gn:dem":1987,
    "gn:feature_class":"P",
    "gn:feature_code":"PPL",
    "gn:name":"La Rancheria",
    "gn:population":0,
    "gn:timezone":"America/Mexico_City",
    "iso:country":"MX",
    "name:spa_x_preferred":[
        "La Rancher\u00eda"
    ],
    "name:spa_x_variant":[
        "La Rancheria"
    ],
    "wof:name":"La Rancheria",
    "wof:placetype":"locality"
},
  "geometry": {"coordinates":[-99.19342,20.28577],"type":"Point"}
}