{
  "type": "Feature",
  "properties": {
    "gn:admin1_code":"10.0",
    "gn:admin2_code":"12.0",
    "gn:asciiname":"Canon del Borrego",
    "gn:country_code":"MX",
    "gn:dem":1194,
    "gn:feature_class":"P",
    "gn:feature_code":"PPL",
    "gn:name":"Ca\u00f1\u00f3n del Borrego",
    "gn:population":0,
    "gn:timezone":"America/Monterrey",
    "iso:country":"MX",
    "name:spa_x_preferred":[
        "Ca\u00f1\u00f3n del Borrego"
    ],
    "name:und_x_variant":[
        "Rancho Ca\u00f1on del Borrego"
    ],
    "wof:name":"Canon del Borrego",
    "wof:placetype":"locality"
},
  "geometry": {"coordinates":[-103.7294,25.29691],"type":"Point"}
}