{
  "type": "Feature",
  "properties": {
    "gn:admin1_code":"21.0",
    "gn:admin2_code":"194.0",
    "gn:asciiname":"Anahuac",
    "gn:country_code":"MX",
    "gn:dem":244,
    "gn:feature_class":"P",
    "gn:feature_code":"PPL",
    "gn:name":"An\u00e1huac",
    "gn:population":0,
    "gn:timezone":"America/Mexico_City",
    "iso:country":"MX",
    "name:ceb_x_preferred":[
        "Anahuac"
    ],
    "name:ita_x_preferred":[
        "Anahuac"
    ],
    "name:nld_x_preferred":[
        "Anahuac"
    ],
    "name:sco_x_preferred":[
        "Anahuac"
    ],
    "name:spa_x_preferred":[
        "An\u00e1huac"
    ],
    "name:swe_x_preferred":[
        "Anahuac"
    ],
    "wof:name":"Anahuac",
    "wof:placetype":"locality"
},
  "geometry": {"coordinates":[-97.58783,20.49964],"type":"Point"}
}