{
  "type": "Feature",
  "properties": {
    "gn:admin1_code":"14.0",
    "gn:admin2_code":"110.0",
    "gn:asciiname":"El Puerto de las Varas",
    "gn:country_code":"MX",
    "gn:dem":1528,
    "gn:feature_class":"P",
    "gn:feature_code":"PPL",
    "gn:name":"El Puerto de las Varas",
    "gn:population":0,
    "gn:timezone":"America/Mexico_City",
    "iso:country":"MX",
    "name:spa_x_preferred":[
        "El Puerto de las Varas"
    ],
    "wof:name":"El Puerto de las Varas",
    "wof:placetype":"locality"
},
  "geometry": {"coordinates":[-104.30750999999999,19.98778],"type":"Point"}
}