{
  "type": "Feature",
  "properties": {
    "gn:admin1_code":"30.0",
    "gn:admin2_code":"155.0",
    "gn:asciiname":"Palo Lima",
    "gn:country_code":"MX",
    "gn:dem":157,
    "gn:feature_class":"P",
    "gn:feature_code":"PPL",
    "gn:name":"Palo Lima",
    "gn:population":9,
    "gn:timezone":"America/Mexico_City",
    "iso:country":"MX",
    "name:spa_x_preferred":[
        "Palo Lima"
    ],
    "wof:name":"Palo Lima",
    "wof:placetype":"locality",
    "wof:population":9
},
  "geometry": {"coordinates":[-98.21305,21.48768],"type":"Point"}
}