{
  "type": "Feature",
  "properties": {
    "gn:admin1_code":"28",
    "gn:admin2_code":"14.0",
    "gn:asciiname":"Jara China",
    "gn:country_code":"MX",
    "gn:dem":109,
    "gn:feature_class":"P",
    "gn:feature_code":"PPL",
    "gn:name":"Jara China",
    "gn:population":0,
    "gn:timezone":"America/Monterrey",
    "iso:country":"MX",
    "name:spa_x_preferred":[
        "Jara China"
    ],
    "name:und_x_variant":[
        "Rancho Jarchina"
    ],
    "wof:name":"Jara China",
    "wof:placetype":"locality"
},
  "geometry": {"coordinates":[-99.40093,26.94769],"type":"Point"}
}