{
  "type": "Feature",
  "properties": {
    "gn:admin1_code":"7",
    "gn:admin2_code":"18.0",
    "gn:asciiname":"San Jose del Oro",
    "gn:country_code":"MX",
    "gn:dem":592,
    "gn:feature_class":"P",
    "gn:feature_code":"PPL",
    "gn:name":"San Jos\u00e9 del Oro",
    "gn:population":0,
    "gn:timezone":"America/Monterrey",
    "iso:country":"MX",
    "name:spa_x_preferred":[
        "San Jos\u00e9 de las Ca\u00f1as"
    ],
    "name:spa_x_variant":[
        "San Jos\u00e9 del Oro"
    ],
    "name:und_x_variant":[
        "Rancho San Jos\u00e9"
    ],
    "wof:name":"San Jose del Oro",
    "wof:placetype":"locality"
},
  "geometry": {"coordinates":[-101.32227,26.93647],"type":"Point"}
}