{
  "type": "Feature",
  "properties": {
    "gn:admin1_code":"14",
    "gn:admin2_code":"16.0",
    "gn:asciiname":"La Nopalera",
    "gn:country_code":"MX",
    "gn:dem":1561,
    "gn:feature_class":"P",
    "gn:feature_code":"PPL",
    "gn:name":"La Nopalera",
    "gn:population":0,
    "gn:timezone":"America/Mexico_City",
    "iso:country":"MX",
    "name:spa_x_preferred":[
        "La Nopalera"
    ],
    "wof:name":"La Nopalera",
    "wof:placetype":"locality"
},
  "geometry": {"coordinates":[-102.40061,20.47683],"type":"Point"}
}