{
  "type": "Feature",
  "properties": {
    "gn:admin1_code":"5",
    "gn:admin2_code":"103.0",
    "gn:asciiname":"Francisco Sarabia 1ra. Seccion",
    "gn:country_code":"MX",
    "gn:dem":206,
    "gn:feature_class":"P",
    "gn:feature_code":"PPL",
    "gn:name":"Francisco Sarabia 1ra. Secci\u00f3n",
    "gn:population":643,
    "gn:timezone":"America/Mexico_City",
    "iso:country":"MX",
    "wof:name":"Francisco Sarabia 1ra. Seccion",
    "wof:placetype":"locality",
    "wof:population":643
},
  "geometry": {"coordinates":[-92.40361,15.15944],"type":"Point"}
}