{
  "type": "Feature",
  "properties": {
    "gn:admin1_code":"12",
    "gn:admin2_code":"71.0",
    "gn:asciiname":"Colonia Cerro Nanche",
    "gn:country_code":"MX",
    "gn:dem":433,
    "gn:feature_class":"P",
    "gn:feature_code":"PPL",
    "gn:name":"Colonia Cerro Nanche",
    "gn:population":160,
    "gn:timezone":"America/Mexico_City",
    "iso:country":"MX",
    "wof:name":"Colonia Cerro Nanche",
    "wof:placetype":"locality",
    "wof:population":160
},
  "geometry": {"coordinates":[-98.18868999999999,16.76173],"type":"Point"}
}