{
  "type": "Feature",
  "properties": {
    "gn:admin1_code":"26",
    "gn:admin2_code":"55.0",
    "gn:asciiname":"Ninguno [Reynaldo Reyna]",
    "gn:country_code":"MX",
    "gn:dem":17,
    "gn:feature_class":"P",
    "gn:feature_code":"PPL",
    "gn:name":"Ninguno [Reynaldo Reyna]",
    "gn:population":6,
    "gn:timezone":"America/Hermosillo",
    "iso:country":"MX",
    "wof:name":"Ninguno [Reynaldo Reyna]",
    "wof:placetype":"locality",
    "wof:population":6
},
  "geometry": {"coordinates":[-114.93277999999999,32.22528],"type":"Point"}
}