{
  "type": "Feature",
  "properties": {
    "gn:admin1_code":"23",
    "gn:admin2_code":"4",
    "gn:asciiname":"Anastacio Valdez Huchin",
    "gn:country_code":"MX",
    "gn:dem":11,
    "gn:feature_class":"P",
    "gn:feature_code":"PPL",
    "gn:name":"Anastacio Valdez Huchin",
    "gn:population":13,
    "gn:timezone":"America/Cancun",
    "iso:country":"MX",
    "wof:name":"Anastacio Valdez Huchin",
    "wof:placetype":"locality",
    "wof:population":13
},
  "geometry": {"coordinates":[-88.11221999999999,19.00278],"type":"Point"}
}