{
  "type": "Feature",
  "properties": {
    "gn:admin1_code":"11",
    "gn:admin2_code":"44",
    "gn:asciiname":"San Francisco",
    "gn:country_code":"MX",
    "gn:dem":1745,
    "gn:feature_class":"P",
    "gn:feature_code":"PPL",
    "gn:name":"San Francisco",
    "gn:population":15,
    "gn:timezone":"America/Mexico_City",
    "iso:country":"MX",
    "wof:name":"San Francisco",
    "wof:placetype":"locality",
    "wof:population":15
},
  "geometry": {"coordinates":[-100.90917,20.53472],"type":"Point"}
}