{
  "type": "Feature",
  "properties": {
    "gn:admin1_code":"25.0",
    "gn:admin2_code":"6.0",
    "gn:asciiname":"El Alacran",
    "gn:country_code":"MX",
    "gn:dem":84,
    "gn:feature_class":"P",
    "gn:feature_code":"PPL",
    "gn:name":"El Alacr\u00e1n",
    "gn:population":0,
    "gn:timezone":"America/Mazatlan",
    "iso:country":"MX",
    "name:spa_x_preferred":[
        "El Alacr\u00e1n"
    ],
    "wof:name":"El Alacran",
    "wof:placetype":"locality"
},
  "geometry": {"coordinates":[-107.23703,24.60253],"type":"Point"}
}