{
  "type": "Feature",
  "properties": {
    "gn:admin1_code":"16.0",
    "gn:admin2_code":"89.0",
    "gn:asciiname":"Los Huarinches",
    "gn:country_code":"MX",
    "gn:dem":377,
    "gn:feature_class":"P",
    "gn:feature_code":"PPL",
    "gn:name":"Los Huarinches",
    "gn:population":0,
    "gn:timezone":"America/Mexico_City",
    "iso:country":"MX",
    "name:spa_x_preferred":[
        "Los Huarinches"
    ],
    "wof:name":"Los Huarinches",
    "wof:placetype":"locality"
},
  "geometry": {"coordinates":[-102.88557,19.16803],"type":"Point"}
}