{
  "type": "Feature",
  "properties": {
    "gn:admin1_code":"6",
    "gn:admin2_code":"40.0",
    "gn:asciiname":"La Libertad",
    "gn:country_code":"MX",
    "gn:dem":1963,
    "gn:feature_class":"P",
    "gn:feature_code":"PPL",
    "gn:name":"La Libertad",
    "gn:population":0,
    "gn:timezone":"America/Chihuahua",
    "iso:country":"MX",
    "name:spa_x_preferred":[
        "La Libertad"
    ],
    "name:und_x_variant":[
        "Libertad"
    ],
    "wof:name":"La Libertad",
    "wof:placetype":"locality"
},
  "geometry": {"coordinates":[-108.02217,29.01826],"type":"Point"}
}