{
  "type": "Feature",
  "properties": {
    "gn:admin1_code":"25",
    "gn:admin2_code":"17.0",
    "gn:asciiname":"El Amapal del Llano",
    "gn:country_code":"MX",
    "gn:dem":168,
    "gn:feature_class":"P",
    "gn:feature_code":"PPL",
    "gn:name":"El Amapal del Llano",
    "gn:population":8,
    "gn:timezone":"America/Mazatlan",
    "iso:country":"MX",
    "wof:name":"El Amapal del Llano",
    "wof:placetype":"locality",
    "wof:population":8
},
  "geometry": {"coordinates":[-108.05540999999999,25.72856],"type":"Point"}
}