{
  "type": "Feature",
  "properties": {
    "gn:admin1_code":"5",
    "gn:admin2_code":"97.0",
    "gn:asciiname":"Veinte de Noviembre",
    "gn:country_code":"MX",
    "gn:dem":12,
    "gn:feature_class":"P",
    "gn:feature_code":"PPL",
    "gn:name":"Veinte de Noviembre",
    "gn:population":0,
    "gn:timezone":"America/Mexico_City",
    "iso:country":"MX",
    "name:spa_x_preferred":[
        "Veinte de Noviembre"
    ],
    "wof:name":"Veinte de Noviembre",
    "wof:placetype":"locality"
},
  "geometry": {"coordinates":[-93.78028,15.96675],"type":"Point"}
}