{
  "type": "Feature",
  "properties": {
    "gn:admin1_code":"6",
    "gn:admin2_code":"18.0",
    "gn:asciiname":"El Aserradero",
    "gn:country_code":"MX",
    "gn:dem":2056,
    "gn:feature_class":"P",
    "gn:feature_code":"PPL",
    "gn:name":"El Aserradero",
    "gn:population":0,
    "gn:timezone":"America/Chihuahua",
    "iso:country":"MX",
    "wof:name":"El Aserradero",
    "wof:placetype":"locality"
},
  "geometry": {"coordinates":[-106.83737000000001,28.1088],"type":"Point"}
}