{
  "type": "Feature",
  "properties": {
    "gn:admin1_code":"23",
    "gn:admin2_code":"2.0",
    "gn:asciiname":"X-yatil",
    "gn:country_code":"MX",
    "gn:dem":27,
    "gn:feature_class":"P",
    "gn:feature_code":"PPL",
    "gn:name":"X-yatil",
    "gn:population":0,
    "gn:timezone":"America/Cancun",
    "iso:country":"MX",
    "name:spa_x_preferred":[
        "X-yatil"
    ],
    "name:spa_x_variant":[
        "Xiatil"
    ],
    "wof:name":"X-yatil",
    "wof:placetype":"locality"
},
  "geometry": {"coordinates":[-88.44374999999999,19.66176],"type":"Point"}
}