{
  "type": "Feature",
  "properties": {
    "gn:admin1_code":"10",
    "gn:admin2_code":"32.0",
    "gn:asciiname":"Barrancos Blancos",
    "gn:country_code":"MX",
    "gn:dem":2023,
    "gn:feature_class":"P",
    "gn:feature_code":"PPL",
    "gn:name":"Barrancos Blancos",
    "gn:population":4,
    "gn:timezone":"America/Monterrey",
    "iso:country":"MX",
    "wof:name":"Barrancos Blancos",
    "wof:placetype":"locality",
    "wof:population":4
},
  "geometry": {"coordinates":[-105.29756,24.9261],"type":"Point"}
}