{
  "type": "Feature",
  "properties": {
    "gn:admin1_code":"27",
    "gn:admin2_code":"3",
    "gn:asciiname":"El Porvenir (De Quintin Arauz)",
    "gn:country_code":"MX",
    "gn:dem":4,
    "gn:feature_class":"P",
    "gn:feature_code":"PPL",
    "gn:name":"El Porvenir (De Quint\u00edn Arauz)",
    "gn:population":34,
    "gn:timezone":"America/Mexico_City",
    "iso:country":"MX",
    "name:und_x_variant":[
        "El Porvenir (De Quint\u00edn Arauz)"
    ],
    "wof:name":"El Porvenir (De Quintin Arauz)",
    "wof:placetype":"locality",
    "wof:population":34
},
  "geometry": {"coordinates":[-92.3625,18.38528],"type":"Point"}
}