{
  "type": "Feature",
  "properties": {
    "gn:admin1_code":"6",
    "gn:admin2_code":"65",
    "gn:asciiname":"Buenavista (Las Tinajas)",
    "gn:country_code":"MX",
    "gn:dem":2158,
    "gn:feature_class":"P",
    "gn:feature_code":"PPL",
    "gn:name":"Buenavista (Las Tinajas)",
    "gn:population":19,
    "gn:timezone":"America/Chihuahua",
    "iso:country":"MX",
    "wof:name":"Buenavista (Las Tinajas)",
    "wof:placetype":"locality",
    "wof:population":19
},
  "geometry": {"coordinates":[-107.96935999999999,27.30742],"type":"Point"}
}