{
  "type": "Feature",
  "properties": {
    "gn:admin1_code":"20",
    "gn:admin2_code":"422",
    "gn:asciiname":"Loma del Tepejillo",
    "gn:country_code":"MX",
    "gn:dem":2329,
    "gn:feature_class":"P",
    "gn:feature_code":"PPL",
    "gn:name":"Loma del Tepejillo",
    "gn:population":12,
    "gn:timezone":"America/Mexico_City",
    "iso:country":"MX",
    "wof:name":"Loma del Tepejillo",
    "wof:placetype":"locality",
    "wof:population":12
},
  "geometry": {"coordinates":[-97.34361,17.65556],"type":"Point"}
}