{
  "type": "Feature",
  "properties": {
    "gn:admin1_code":"11",
    "gn:admin2_code":"14",
    "gn:asciiname":"La Purisima (Santo Nino)",
    "gn:country_code":"MX",
    "gn:dem":2000,
    "gn:feature_class":"P",
    "gn:feature_code":"PPL",
    "gn:name":"La Pur\u00edsima (Santo Ni\u00f1o)",
    "gn:population":11,
    "gn:timezone":"America/Mexico_City",
    "iso:country":"MX",
    "name:und_x_variant":[
        "La Pur\u00edsima (Santo Ni\u00f1o)"
    ],
    "wof:name":"La Purisima (Santo Nino)",
    "wof:placetype":"locality",
    "wof:population":11
},
  "geometry": {"coordinates":[-100.72667,21.26056],"type":"Point"}
}