{
  "type": "Feature",
  "properties": {
    "gn:admin1_code":"12",
    "gn:admin2_code":"11.0",
    "gn:asciiname":"Rio Santiago",
    "gn:country_code":"MX",
    "gn:dem":697,
    "gn:feature_class":"P",
    "gn:feature_code":"PPL",
    "gn:name":"R\u00edo Santiago",
    "gn:population":946,
    "gn:timezone":"America/Mexico_City",
    "iso:country":"MX",
    "name:ceb_x_preferred":[
        "Rio Santiago"
    ],
    "name:swe_x_preferred":[
        "Rio Santiago"
    ],
    "name:und_x_variant":[
        "R\u00edo Santiago"
    ],
    "wof:name":"Rio Santiago",
    "wof:placetype":"locality",
    "wof:population":946
},
  "geometry": {"coordinates":[-100.31694,17.25361],"type":"Point"}
}