{
  "type": "Feature",
  "properties": {
    "gn:admin1_code":"10.0",
    "gn:admin2_code":"14.0",
    "gn:asciiname":"Chilapa",
    "gn:country_code":"MX",
    "gn:dem":1654,
    "gn:feature_class":"P",
    "gn:feature_code":"PPL",
    "gn:name":"Chilapa",
    "gn:population":0,
    "gn:timezone":"America/Monterrey",
    "iso:country":"MX",
    "name:spa_x_preferred":[
        "Chilapa"
    ],
    "wof:name":"Chilapa",
    "wof:placetype":"locality"
},
  "geometry": {"coordinates":[-104.41500000000001,22.85324],"type":"Point"}
}