{
  "type": "Feature",
  "properties": {
    "gn:admin1_code":"7.0",
    "gn:admin2_code":"12.0",
    "gn:asciiname":"La Colonia",
    "gn:country_code":"MX",
    "gn:dem":226,
    "gn:feature_class":"P",
    "gn:feature_code":"PPL",
    "gn:name":"La Colonia",
    "gn:population":0,
    "gn:timezone":"America/Monterrey",
    "iso:country":"MX",
    "wof:name":"La Colonia",
    "wof:placetype":"locality"
},
  "geometry": {"coordinates":[-100.36667,28.36667000000001],"type":"Point"}
}