{
  "type": "Feature",
  "properties": {
    "gn:admin1_code":"7.0",
    "gn:admin2_code":"2.0",
    "gn:asciiname":"San Esteban de Egipto",
    "gn:country_code":"MX",
    "gn:dem":791,
    "gn:feature_class":"P",
    "gn:feature_code":"PPL",
    "gn:name":"San Esteban de Egipto",
    "gn:population":0,
    "gn:timezone":"America/Matamoros",
    "iso:country":"MX",
    "name:spa_x_preferred":[
        "San Esteban de Egipto"
    ],
    "wof:name":"San Esteban de Egipto",
    "wof:placetype":"locality"
},
  "geometry": {"coordinates":[-102.18509,29.49623],"type":"Point"}
}