{
  "type": "Feature",
  "properties": {
    "gn:admin1_code":"24",
    "gn:admin2_code":"40.0",
    "gn:asciiname":"El Corozo",
    "gn:country_code":"MX",
    "gn:dem":27,
    "gn:feature_class":"P",
    "gn:feature_code":"PPL",
    "gn:name":"El Corozo",
    "gn:population":0,
    "gn:timezone":"America/Mexico_City",
    "iso:country":"MX",
    "name:und_x_variant":[
        "Corzo",
        "Coroso",
        "El Corozo"
    ],
    "wof:name":"El Corozo",
    "wof:placetype":"locality"
},
  "geometry": {"coordinates":[-98.71357999999999,21.9733],"type":"Point"}
}