{
  "type": "Feature",
  "properties": {
    "gn:admin1_code":"6",
    "gn:admin2_code":"27.0",
    "gn:asciiname":"Gueirarachi",
    "gn:country_code":"MX",
    "gn:dem":2254,
    "gn:feature_class":"P",
    "gn:feature_code":"PPL",
    "gn:name":"G\u00fcir\u00e1rachi",
    "gn:population":0,
    "gn:timezone":"America/Chihuahua",
    "iso:country":"MX",
    "name:spa_x_preferred":[
        "G\u00fcir\u00e1rachi"
    ],
    "name:und_x_variant":[
        "Guirarachi"
    ],
    "wof:name":"Gueirarachi",
    "wof:placetype":"locality"
},
  "geometry": {"coordinates":[-107.33137000000001,27.1849],"type":"Point"}
}