{
  "type": "Feature",
  "properties": {
    "gn:admin1_code":"20",
    "gn:admin2_code":"439.0",
    "gn:asciiname":"El Carnero",
    "gn:country_code":"MX",
    "gn:dem":63,
    "gn:feature_class":"P",
    "gn:feature_code":"PPL",
    "gn:name":"El Carnero",
    "gn:population":60,
    "gn:timezone":"America/Mexico_City",
    "iso:country":"MX",
    "name:spa_x_preferred":[
        "El Carnero"
    ],
    "wof:name":"El Carnero",
    "wof:placetype":"locality",
    "wof:population":60
},
  "geometry": {"coordinates":[-96.51528,15.68056],"type":"Point"}
}