{
  "type": "Feature",
  "properties": {
    "gn:admin1_code":"31",
    "gn:admin2_code":"48.0",
    "gn:asciiname":"Chen Ceh",
    "gn:country_code":"MX",
    "gn:dem":7,
    "gn:feature_class":"P",
    "gn:feature_code":"PPL",
    "gn:name":"Chen Ceh",
    "gn:population":0,
    "gn:timezone":"America/Merida",
    "iso:country":"MX",
    "name:spa_x_preferred":[
        "Chen Ceh"
    ],
    "wof:name":"Chen Ceh",
    "wof:placetype":"locality"
},
  "geometry": {"coordinates":[-90.08018,20.73475],"type":"Point"}
}