{
  "type": "Feature",
  "properties": {
    "gn:admin1_code":"12.0",
    "gn:asciiname":"Teoyatlan",
    "gn:country_code":"MX",
    "gn:dem":924,
    "gn:feature_class":"P",
    "gn:feature_code":"PPL",
    "gn:name":"Teoyatl\u00e1n",
    "gn:population":0,
    "gn:timezone":"America/Mexico_City",
    "iso:country":"MX",
    "name:spa_x_preferred":[
        "Teoyatl\u00e1n"
    ],
    "wof:name":"Teoyatlan",
    "wof:placetype":"locality"
},
  "geometry": {"coordinates":[-99.02964,17.40778],"type":"Point"}
}