{
  "type": "Feature",
  "properties": {
    "gn:admin1_code":"12",
    "gn:admin2_code":"38",
    "gn:asciiname":"La Gardenia",
    "gn:country_code":"MX",
    "gn:dem":374,
    "gn:feature_class":"P",
    "gn:feature_code":"PPL",
    "gn:name":"La Gardenia",
    "gn:population":23,
    "gn:timezone":"America/Mexico_City",
    "iso:country":"MX",
    "wof:name":"La Gardenia",
    "wof:placetype":"locality",
    "wof:population":23
},
  "geometry": {"coordinates":[-101.44450999999999,17.80337999999999],"type":"Point"}
}