{
  "type": "Feature",
  "properties": {
    "gn:admin1_code":"11",
    "gn:admin2_code":"11.0",
    "gn:asciiname":"La Luz de Orozco",
    "gn:country_code":"MX",
    "gn:dem":1752,
    "gn:feature_class":"P",
    "gn:feature_code":"PPL",
    "gn:name":"La Luz de Orozco",
    "gn:population":62,
    "gn:timezone":"America/Mexico_City",
    "iso:country":"MX",
    "wof:name":"La Luz de Orozco",
    "wof:placetype":"locality",
    "wof:population":62
},
  "geometry": {"coordinates":[-100.85639,20.48389],"type":"Point"}
}