{
  "type": "Feature",
  "properties": {
    "gn:admin1_code":"26",
    "gn:admin2_code":"30.0",
    "gn:asciiname":"El Rojo",
    "gn:country_code":"MX",
    "gn:dem":48,
    "gn:feature_class":"P",
    "gn:feature_code":"PPL",
    "gn:name":"El Rojo",
    "gn:population":0,
    "gn:timezone":"America/Hermosillo",
    "iso:country":"MX",
    "name:spa_x_preferred":[
        "Progreso N\u00famero Dos"
    ],
    "name:spa_x_variant":[
        "Mar\u00eda Belem",
        "El Rojo",
        "El Cincuenta y Siete"
    ],
    "wof:name":"El Rojo",
    "wof:placetype":"locality"
},
  "geometry": {"coordinates":[-111.45385,28.68427],"type":"Point"}
}