{
  "type": "Feature",
  "properties": {
    "gn:admin1_code":"27",
    "gn:admin2_code":"6.0",
    "gn:asciiname":"Libertad Tercera Seccion",
    "gn:country_code":"MX",
    "gn:dem":14,
    "gn:feature_class":"P",
    "gn:feature_code":"PPL",
    "gn:name":"Libertad Tercera Secci\u00f3n",
    "gn:population":0,
    "gn:timezone":"America/Mexico_City",
    "iso:country":"MX",
    "name:spa_x_preferred":[
        "Libertad Tercera Secci\u00f3n"
    ],
    "wof:name":"Libertad Tercera Seccion",
    "wof:placetype":"locality"
},
  "geometry": {"coordinates":[-93.37757000000001,18.13934],"type":"Point"}
}