{
  "type": "Feature",
  "properties": {
    "gn:admin1_code":"2",
    "gn:admin2_code":"2",
    "gn:asciiname":"Ejido Otilio Montano",
    "gn:country_code":"MX",
    "gn:dem":11,
    "gn:feature_class":"P",
    "gn:feature_code":"PPL",
    "gn:name":"Ejido Otilio Monta\u00f1o",
    "gn:population":47,
    "gn:timezone":"America/Tijuana",
    "iso:country":"MX",
    "name:und_x_variant":[
        "Ejido Otilio Monta\u00f1o"
    ],
    "wof:name":"Ejido Otilio Montano",
    "wof:placetype":"locality",
    "wof:population":47
},
  "geometry": {"coordinates":[-115.27556,32.43722],"type":"Point"}
}