{
  "type": "Feature",
  "properties": {
    "gn:admin1_code":"17",
    "gn:asciiname":"Astillero El Fraile",
    "gn:country_code":"MX",
    "gn:dem":3016,
    "gn:feature_class":"P",
    "gn:feature_code":"PPL",
    "gn:name":"Astillero El Fraile",
    "gn:population":0,
    "gn:timezone":"America/Mexico_City",
    "iso:country":"MX",
    "name:spa_x_preferred":[
        "Astillero El Fraile"
    ],
    "name:spa_x_variant":[
        "Astillero"
    ],
    "wof:name":"Astillero El Fraile",
    "wof:placetype":"locality"
},
  "geometry": {"coordinates":[-99.2435,19.11793],"type":"Point"}
}