{
  "type": "Feature",
  "properties": {
    "gn:admin1_code":"12.0",
    "gn:asciiname":"Mesa de los Gallos",
    "gn:country_code":"MX",
    "gn:dem":1090,
    "gn:feature_class":"P",
    "gn:feature_code":"PPL",
    "gn:name":"Mesa de los Gallos",
    "gn:population":0,
    "gn:timezone":"America/Mexico_City",
    "iso:country":"MX",
    "name:spa_x_preferred":[
        "Mesa de los Gallos"
    ],
    "wof:name":"Mesa de los Gallos",
    "wof:placetype":"locality"
},
  "geometry": {"coordinates":[-100.47562000000001,18.82876],"type":"Point"}
}