{
  "type": "Feature",
  "properties": {
    "gn:admin1_code":"17",
    "gn:admin2_code":"7",
    "gn:asciiname":"Tlachichilpa",
    "gn:country_code":"MX",
    "gn:dem":1941,
    "gn:feature_class":"P",
    "gn:feature_code":"PPL",
    "gn:name":"Tlachichilpa",
    "gn:population":19,
    "gn:timezone":"America/Mexico_City",
    "iso:country":"MX",
    "wof:name":"Tlachichilpa",
    "wof:placetype":"locality",
    "wof:population":19
},
  "geometry": {"coordinates":[-99.30361000000001,18.9475],"type":"Point"}
}