{
  "type": "Feature",
  "properties": {
    "gn:admin1_code":"5",
    "gn:admin2_code":"97.0",
    "gn:asciiname":"Playa del Sol",
    "gn:country_code":"MX",
    "gn:dem":1,
    "gn:feature_class":"P",
    "gn:feature_code":"PPL",
    "gn:name":"Playa del Sol",
    "gn:population":69,
    "gn:timezone":"America/Mexico_City",
    "iso:country":"MX",
    "name:swe_x_preferred":[
        "Playa del Sol"
    ],
    "wof:name":"Playa del Sol",
    "wof:placetype":"locality",
    "wof:population":69
},
  "geometry": {"coordinates":[-93.78471999999999,15.91833],"type":"Point"}
}