{
  "type": "Feature",
  "properties": {
    "gn:admin1_code":"19.0",
    "gn:asciiname":"El Sufrimiento",
    "gn:country_code":"MX",
    "gn:dem":405,
    "gn:feature_class":"P",
    "gn:feature_code":"PPL",
    "gn:name":"El Sufrimiento",
    "gn:population":0,
    "gn:timezone":"America/Monterrey",
    "iso:country":"MX",
    "name:spa_x_preferred":[
        "El Sufrimiento"
    ],
    "wof:name":"El Sufrimiento",
    "wof:placetype":"locality"
},
  "geometry": {"coordinates":[-99.61476,24.79895],"type":"Point"}
}