{
  "type": "Feature",
  "properties": {
    "gn:admin1_code":"20.0",
    "gn:admin2_code":"59.0",
    "gn:asciiname":"Los Jijones",
    "gn:country_code":"MX",
    "gn:dem":1543,
    "gn:feature_class":"P",
    "gn:feature_code":"PPL",
    "gn:name":"Los Jijones",
    "gn:population":0,
    "gn:timezone":"America/Mexico_City",
    "iso:country":"MX",
    "name:spa_x_preferred":[
        "Los Jijones"
    ],
    "wof:name":"Los Jijones",
    "wof:placetype":"locality"
},
  "geometry": {"coordinates":[-96.79901,16.29212],"type":"Point"}
}