{
  "type": "Feature",
  "properties": {
    "gn:admin1_code":"20",
    "gn:admin2_code":"469.0",
    "gn:asciiname":"Guadalupe Tilapa",
    "gn:country_code":"MX",
    "gn:dem":1283,
    "gn:feature_class":"P",
    "gn:feature_code":"PPL",
    "gn:name":"Guadalupe Tilapa",
    "gn:population":0,
    "gn:timezone":"America/Mexico_City",
    "iso:country":"MX",
    "name:spa_x_preferred":[
        "Tilapa"
    ],
    "wof:name":"Guadalupe Tilapa",
    "wof:placetype":"locality"
},
  "geometry": {"coordinates":[-97.98913,17.15797],"type":"Point"}
}