{
  "type": "Feature",
  "properties": {
    "gn:admin1_code":"28",
    "gn:admin2_code":"22.0",
    "gn:asciiname":"La Higuera",
    "gn:country_code":"MX",
    "gn:dem":7,
    "gn:feature_class":"P",
    "gn:feature_code":"PPL",
    "gn:name":"La Higuera",
    "gn:population":7,
    "gn:timezone":"America/Matamoros",
    "iso:country":"MX",
    "wof:name":"La Higuera",
    "wof:placetype":"locality",
    "wof:population":7
},
  "geometry": {"coordinates":[-97.28445000000001,25.85639],"type":"Point"}
}