{
  "type": "Feature",
  "properties": {
    "gn:admin1_code":"19.0",
    "gn:admin2_code":"28.0",
    "gn:asciiname":"Plan del Derramadero",
    "gn:country_code":"MX",
    "gn:dem":595,
    "gn:feature_class":"P",
    "gn:feature_code":"PPL",
    "gn:name":"Plan del Derramadero",
    "gn:population":0,
    "gn:timezone":"America/Monterrey",
    "iso:country":"MX",
    "name:spa_x_preferred":[
        "Plan de Derramadero"
    ],
    "name:spa_x_variant":[
        "Plan del Derramadero"
    ],
    "wof:name":"Plan del Derramadero",
    "wof:placetype":"locality"
},
  "geometry": {"coordinates":[-100.04818,26.05108],"type":"Point"}
}