{
  "type": "Feature",
  "properties": {
    "gn:admin1_code":"4",
    "gn:admin2_code":"9.0",
    "gn:asciiname":"Flor de Mayo",
    "gn:country_code":"MX",
    "gn:dem":48,
    "gn:feature_class":"P",
    "gn:feature_code":"PPL",
    "gn:name":"Flor de Mayo",
    "gn:population":7,
    "gn:timezone":"America/Merida",
    "iso:country":"MX",
    "wof:name":"Flor de Mayo",
    "wof:placetype":"locality",
    "wof:population":7
},
  "geometry": {"coordinates":[-91.01306,18.41528],"type":"Point"}
}