{
  "type": "Feature",
  "properties": {
    "gn:admin1_code":"15",
    "gn:admin2_code":"61",
    "gn:asciiname":"Ex-Hacienda de Tepatepec",
    "gn:country_code":"MX",
    "gn:dem":2461,
    "gn:feature_class":"P",
    "gn:feature_code":"PPL",
    "gn:name":"Ex-Hacienda de Tepatepec",
    "gn:population":45,
    "gn:timezone":"America/Mexico_City",
    "iso:country":"MX",
    "wof:name":"Ex-Hacienda de Tepatepec",
    "wof:placetype":"locality",
    "wof:population":45
},
  "geometry": {"coordinates":[-98.71165000000001,19.79925],"type":"Point"}
}