{
  "type": "Feature",
  "properties": {
    "gn:admin1_code":"25",
    "gn:admin2_code":"4.0",
    "gn:asciiname":"La Cieneguilla",
    "gn:country_code":"MX",
    "gn:dem":579,
    "gn:feature_class":"P",
    "gn:feature_code":"PPL",
    "gn:name":"La Cieneguilla",
    "gn:population":0,
    "gn:timezone":"America/Mazatlan",
    "iso:country":"MX",
    "name:spa_x_preferred":[
        "La Cieneguilla"
    ],
    "wof:name":"La Cieneguilla",
    "wof:placetype":"locality"
},
  "geometry": {"coordinates":[-106.05503,23.54084],"type":"Point"}
}