{
  "type": "Feature",
  "properties": {
    "gn:admin1_code":"25.0",
    "gn:admin2_code":"13.0",
    "gn:asciiname":"El Tule",
    "gn:country_code":"MX",
    "gn:dem":257,
    "gn:feature_class":"P",
    "gn:feature_code":"PPL",
    "gn:name":"El Tule",
    "gn:population":0,
    "gn:timezone":"America/Mazatlan",
    "iso:country":"MX",
    "name:ceb_x_preferred":[
        "El Tule"
    ],
    "name:spa_x_preferred":[
        "El Tule"
    ],
    "name:srp_x_preferred":[
        "\u0415\u043b \u0422\u0443\u043b\u0435"
    ],
    "name:swe_x_preferred":[
        "El Tule"
    ],
    "wof:name":"El Tule",
    "wof:placetype":"locality"
},
  "geometry": {"coordinates":[-107.88263999999999,25.63912],"type":"Point"}
}