{
  "type": "Feature",
  "properties": {
    "gn:admin1_code":"31.0",
    "gn:admin2_code":"38.0",
    "gn:asciiname":"Naox",
    "gn:country_code":"MX",
    "gn:dem":4,
    "gn:feature_class":"P",
    "gn:feature_code":"PPL",
    "gn:name":"Naox",
    "gn:population":0,
    "gn:timezone":"America/Merida",
    "iso:country":"MX",
    "name:spa_x_preferred":[
        "Naox"
    ],
    "wof:name":"Naox",
    "wof:placetype":"locality"
},
  "geometry": {"coordinates":[-89.87761,21.0433],"type":"Point"}
}