{
  "type": "Feature",
  "properties": {
    "gn:admin1_code":"13",
    "gn:admin2_code":"28",
    "gn:asciiname":"Aquexquillo",
    "gn:country_code":"MX",
    "gn:dem":275,
    "gn:feature_class":"P",
    "gn:feature_code":"PPL",
    "gn:name":"Aquexquillo",
    "gn:population":37,
    "gn:timezone":"America/Mexico_City",
    "iso:country":"MX",
    "wof:name":"Aquexquillo",
    "wof:placetype":"locality",
    "wof:population":37
},
  "geometry": {"coordinates":[-98.57932,21.11372],"type":"Point"}
}