{
  "type": "Feature",
  "properties": {
    "gn:admin1_code":"16",
    "gn:admin2_code":"11.0",
    "gn:asciiname":"San Miguel",
    "gn:country_code":"MX",
    "gn:dem":1531,
    "gn:feature_class":"P",
    "gn:feature_code":"PPL",
    "gn:name":"San Miguel",
    "gn:population":60,
    "gn:timezone":"America/Mexico_City",
    "iso:country":"MX",
    "wof:name":"San Miguel",
    "wof:placetype":"locality",
    "wof:population":60
},
  "geometry": {"coordinates":[-102.57832999999999,20.26306],"type":"Point"}
}