{
  "type": "Feature",
  "properties": {
    "gn:admin1_code":"1",
    "gn:admin2_code":"11.0",
    "gn:asciiname":"Rancho Coyonoxtle",
    "gn:country_code":"MX",
    "gn:dem":1891,
    "gn:feature_class":"P",
    "gn:feature_code":"PPL",
    "gn:name":"Rancho Coyonoxtle",
    "gn:population":7,
    "gn:timezone":"America/Mexico_City",
    "iso:country":"MX",
    "wof:name":"Rancho Coyonoxtle",
    "wof:placetype":"locality",
    "wof:population":7
},
  "geometry": {"coordinates":[-102.27943999999999,22.04917],"type":"Point"}
}