{
  "type": "Feature",
  "properties": {
    "gn:admin1_code":"28",
    "gn:admin2_code":"35.0",
    "gn:asciiname":"Rancho San Francisco",
    "gn:country_code":"MX",
    "gn:dem":25,
    "gn:feature_class":"P",
    "gn:feature_code":"PPL",
    "gn:name":"Rancho San Francisco",
    "gn:population":0,
    "gn:timezone":"America/Monterrey",
    "iso:country":"MX",
    "name:fra_x_preferred":[
        "Rancho San Francisco"
    ],
    "wof:name":"Rancho San Francisco",
    "wof:placetype":"locality"
},
  "geometry": {"coordinates":[-98.11667,24.73333],"type":"Point"}
}