{
  "type": "Feature",
  "properties": {
    "gn:admin1_code":"14.0",
    "gn:admin2_code":"67.0",
    "gn:asciiname":"Marina",
    "gn:country_code":"MX",
    "gn:dem":6,
    "gn:feature_class":"P",
    "gn:feature_code":"PPL",
    "gn:name":"Marina",
    "gn:population":0,
    "gn:timezone":"America/Mexico_City",
    "iso:country":"MX",
    "name:ara_x_preferred":[
        "\u0645\u0627\u0631\u064a\u0646\u0627"
    ],
    "name:ast_x_preferred":[
        "Puertu deportivu"
    ],
    "name:cat_x_preferred":[
        "Port esportiu"
    ],
    "name:ces_x_preferred":[
        "Marina"
    ],
    "name:cym_x_preferred":[
        "Marina"
    ],
    "name:dan_x_preferred":[
        "Lystb\u00e5dehavn"
    ],
    "name:deu_x_preferred":[
        "Marina"
    ],
    "name:ell_x_preferred":[
        "\u039c\u03b1\u03c1\u03af\u03bd\u03b1"
    ],
    "name:epo_x_preferred":[
        "Ja\u0125t-haveno"
    ],
    "name:est_x_preferred":[
        "V\u00e4ikesadam"
    ],
    "name:eus_x_preferred":[
        "Kirol-portu"
    ],
    "name:fas_x_preferred":[
        "\u0645\u0627\u0631\u06cc\u0646\u0627"
    ],
    "name:fin_x_preferred":[
        "Venesatama"
    ],
    "name:heb_x_preferred":[
        "\u05de\u05e8\u05d9\u05e0\u05d4"
    ],
    "name:hrv_x_preferred":[
        "Marina"
    ],
    "name:hun_x_preferred":[
        "Jachtkik\u00f6t\u0151"
    ],
    "name:ind_x_preferred":[
        "Marina"
    ],
    "name:isl_x_preferred":[
        "Sm\u00e1b\u00e1tah\u00f6fn"
    ],
    "name:ita_x_preferred":[
        "Porto turistico"
    ],
    "name:jpn_x_preferred":[
        "\u30de\u30ea\u30fc\u30ca"
    ],
    "name:kor_x_preferred":[
        "\ub9c8\ub9ac\ub098"
    ],
    "name:lit_x_preferred":[
        "Marina"
    ],
    "name:nld_x_preferred":[
        "Jachthaven"
    ],
    "name:nor_x_preferred":[
        "Lystb\u00e5thavn"
    ],
    "name:pol_x_preferred":[
        "Marina"
    ],
    "name:por_x_preferred":[
        "Marina"
    ],
    "name:slv_x_preferred":[
        "Marina"
    ],
    "name:spa_x_preferred":[
        "Puerto deportivo"
    ],
    "name:swe_x_preferred":[
        "Sm\u00e5b\u00e5tshamn"
    ],
    "name:tur_x_preferred":[
        "Marina"
    ],
    "name:ukr_x_preferred":[
        "\u041c\u0430\u0440\u0438\u043d\u0430"
    ],
    "wof:name":"Marina",
    "wof:placetype":"locality"
},
  "geometry": {"coordinates":[-105.23515999999999,20.64234],"type":"Point"}
}