{
  "type": "Feature",
  "properties": {
    "gn:admin1_code":"14.0",
    "gn:admin2_code":"67.0",
    "gn:asciiname":"Marina",
    "gn:country_code":"MX",
    "gn:dem":6,
    "gn:feature_class":"P",
    "gn:feature_code":"PPL",
    "gn:name":"Marina",
    "gn:population":0,
    "gn:timezone":"America/Mexico_City",
    "iso:country":"MX",
    "wof:name":"Marina",
    "wof:placetype":"locality"
},
  "geometry": {"coordinates":[-105.23515999999999,20.64234],"type":"Point"}
}