{
  "type": "Feature",
  "properties": {
    "gn:admin1_code":"11.0",
    "gn:admin2_code":"2.0",
    "gn:asciiname":"Las Partidas",
    "gn:country_code":"MX",
    "gn:dem":2086,
    "gn:feature_class":"P",
    "gn:feature_code":"PPL",
    "gn:name":"Las Partidas",
    "gn:population":245,
    "gn:timezone":"America/Mexico_City",
    "iso:country":"MX",
    "wof:name":"Las Partidas",
    "wof:placetype":"locality",
    "wof:population":245
},
  "geometry": {"coordinates":[-100.84999999999999,20.02778],"type":"Point"}
}