{
  "type": "Feature",
  "properties": {
    "gn:admin1_code":"16.0",
    "gn:admin2_code":"34.0",
    "gn:asciiname":"Casas Pintas",
    "gn:country_code":"MX",
    "gn:dem":2669,
    "gn:feature_class":"P",
    "gn:feature_code":"PPL",
    "gn:name":"Casas Pintas",
    "gn:population":188,
    "gn:timezone":"America/Mexico_City",
    "iso:country":"MX",
    "name:spa_x_preferred":[
        "Casas Pintas"
    ],
    "wof:name":"Casas Pintas",
    "wof:placetype":"locality",
    "wof:population":188
},
  "geometry": {"coordinates":[-100.57411,19.77839],"type":"Point"}
}