{
  "type": "Feature",
  "properties": {
    "gn:admin1_code":"11",
    "gn:admin2_code":"44",
    "gn:asciiname":"Alfredo Carmona",
    "gn:country_code":"MX",
    "gn:dem":1750,
    "gn:feature_class":"P",
    "gn:feature_code":"PPL",
    "gn:name":"Alfredo Carmona",
    "gn:population":9,
    "gn:timezone":"America/Mexico_City",
    "iso:country":"MX",
    "wof:name":"Alfredo Carmona",
    "wof:placetype":"locality",
    "wof:population":9
},
  "geometry": {"coordinates":[-100.92528,20.54528],"type":"Point"}
}