{
  "type": "Feature",
  "properties": {
    "gn:admin1_code":"16.0",
    "gn:admin2_code":"34.0",
    "gn:asciiname":"El Purgatorio",
    "gn:country_code":"MX",
    "gn:dem":2155,
    "gn:feature_class":"P",
    "gn:feature_code":"PPL",
    "gn:name":"El Purgator\u00edo",
    "gn:population":0,
    "gn:timezone":"America/Mexico_City",
    "iso:country":"MX",
    "name:spa_x_preferred":[
        "El Purgator\u00edo"
    ],
    "wof:name":"El Purgatorio",
    "wof:placetype":"locality"
},
  "geometry": {"coordinates":[-100.65459,19.4857],"type":"Point"}
}