{
  "type": "Feature",
  "properties": {
    "gn:admin1_code":"14",
    "gn:admin2_code":"125.0",
    "gn:asciiname":"El Saucito",
    "gn:country_code":"MX",
    "gn:dem":2040,
    "gn:feature_class":"P",
    "gn:feature_code":"PPL",
    "gn:name":"El Saucito",
    "gn:population":119,
    "gn:timezone":"America/Mexico_City",
    "iso:country":"MX",
    "wof:name":"El Saucito",
    "wof:placetype":"locality",
    "wof:population":119
},
  "geometry": {"coordinates":[-102.50888999999999,20.73194],"type":"Point"}
}