{
  "type": "Feature",
  "properties": {
    "gn:admin1_code":"18.0",
    "gn:admin2_code":"4.0",
    "gn:asciiname":"La Florida",
    "gn:country_code":"MX",
    "gn:dem":20,
    "gn:feature_class":"P",
    "gn:feature_code":"PPL",
    "gn:name":"La Florida",
    "gn:population":0,
    "gn:timezone":"America/Mazatlan",
    "iso:country":"MX",
    "name:spa_x_preferred":[
        "La Florida"
    ],
    "wof:name":"La Florida",
    "wof:placetype":"locality"
},
  "geometry": {"coordinates":[-105.30683000000001,20.974],"type":"Point"}
}