{
  "type": "Feature",
  "properties": {
    "gn:admin1_code":"5.0",
    "gn:admin2_code":"35.0",
    "gn:asciiname":"Las Viudas",
    "gn:country_code":"MX",
    "gn:dem":38,
    "gn:feature_class":"P",
    "gn:feature_code":"PPL",
    "gn:name":"Las Viudas",
    "gn:population":0,
    "gn:timezone":"America/Mexico_City",
    "iso:country":"MX",
    "name:spa_x_preferred":[
        "Las Vludas"
    ],
    "name:spa_x_variant":[
        "Las Viudas"
    ],
    "wof:name":"Las Viudas",
    "wof:placetype":"locality"
},
  "geometry": {"coordinates":[-92.21929,14.73946],"type":"Point"}
}