{
  "type": "Feature",
  "properties": {
    "gn:admin1_code":"13",
    "gn:admin2_code":"10.0",
    "gn:asciiname":"El Gavillero",
    "gn:country_code":"MX",
    "gn:dem":2105,
    "gn:feature_class":"P",
    "gn:feature_code":"PPL",
    "gn:name":"El Gavillero",
    "gn:population":5,
    "gn:timezone":"America/Mexico_City",
    "iso:country":"MX",
    "wof:name":"El Gavillero",
    "wof:placetype":"locality",
    "wof:population":5
},
  "geometry": {"coordinates":[-99.26000000000001,20.06389],"type":"Point"}
}