{
  "type": "Feature",
  "properties": {
    "gn:admin1_code":"20",
    "gn:admin2_code":"57.0",
    "gn:asciiname":"San Juan del Rio",
    "gn:country_code":"MX",
    "gn:dem":121,
    "gn:feature_class":"P",
    "gn:feature_code":"PPL",
    "gn:name":"San Juan del R\u00edo",
    "gn:population":476,
    "gn:timezone":"America/Mexico_City",
    "iso:country":"MX",
    "name:und_x_variant":[
        "San Juan del R\u00edo"
    ],
    "wof:name":"San Juan del Rio",
    "wof:placetype":"locality",
    "wof:population":476
},
  "geometry": {"coordinates":[-95.25333000000001,17.25139],"type":"Point"}
}