{
  "type": "Feature",
  "properties": {
    "gn:admin1_code":"19",
    "gn:admin2_code":"41.0",
    "gn:asciiname":"El Puas",
    "gn:country_code":"MX",
    "gn:dem":352,
    "gn:feature_class":"P",
    "gn:feature_code":"PPL",
    "gn:name":"El P\u00faas",
    "gn:population":5,
    "gn:timezone":"America/Monterrey",
    "iso:country":"MX",
    "name:und_x_variant":[
        "El P\u00faas"
    ],
    "wof:name":"El Puas",
    "wof:placetype":"locality",
    "wof:population":5
},
  "geometry": {"coordinates":[-100.07586000000001,25.78339],"type":"Point"}
}