{
  "type": "Feature",
  "properties": {
    "gn:admin1_code":"28.0",
    "gn:admin2_code":"37.0",
    "gn:asciiname":"El Tercer Mundo",
    "gn:country_code":"MX",
    "gn:dem":34,
    "gn:feature_class":"P",
    "gn:feature_code":"PPL",
    "gn:name":"El Tercer Mundo",
    "gn:population":0,
    "gn:timezone":"America/Monterrey",
    "iso:country":"MX",
    "name:spa_x_preferred":[
        "El Tercer Mundo"
    ],
    "wof:name":"El Tercer Mundo",
    "wof:placetype":"locality"
},
  "geometry": {"coordinates":[-98.23639,23.72167],"type":"Point"}
}