{
  "type": "Feature",
  "properties": {
    "gn:admin1_code":"7",
    "gn:admin2_code":"20.0",
    "gn:asciiname":"Rancho San Alberto",
    "gn:country_code":"MX",
    "gn:dem":563,
    "gn:feature_class":"P",
    "gn:feature_code":"PPL",
    "gn:name":"Rancho San Alberto",
    "gn:population":0,
    "gn:timezone":"America/Monterrey",
    "iso:country":"MX",
    "wof:name":"Rancho San Alberto",
    "wof:placetype":"locality"
},
  "geometry": {"coordinates":[-101.51667,27.83333],"type":"Point"}
}