{
  "type": "Feature",
  "properties": {
    "gn:admin1_code":"11",
    "gn:admin2_code":"14",
    "gn:asciiname":"Los Godinez",
    "gn:country_code":"MX",
    "gn:dem":2003,
    "gn:feature_class":"P",
    "gn:feature_code":"PPL",
    "gn:name":"Los God\u00ednez",
    "gn:population":13,
    "gn:timezone":"America/Mexico_City",
    "iso:country":"MX",
    "name:und_x_variant":[
        "Los God\u00ednez"
    ],
    "wof:name":"Los Godinez",
    "wof:placetype":"locality",
    "wof:population":13
},
  "geometry": {"coordinates":[-100.99639000000001,21.19278],"type":"Point"}
}