{
  "type": "Feature",
  "properties": {
    "gn:admin1_code":"24",
    "gn:admin2_code":"41.0",
    "gn:asciiname":"Santa Cliteria Dos",
    "gn:country_code":"MX",
    "gn:dem":40,
    "gn:feature_class":"P",
    "gn:feature_code":"PPL",
    "gn:name":"Santa Cliteria Dos",
    "gn:population":5,
    "gn:timezone":"America/Mexico_City",
    "iso:country":"MX",
    "wof:name":"Santa Cliteria Dos",
    "wof:placetype":"locality",
    "wof:population":5
},
  "geometry": {"coordinates":[-98.83028,21.81139],"type":"Point"}
}