{
  "type": "Feature",
  "properties": {
    "gn:admin1_code":"26",
    "gn:admin2_code":"42.0",
    "gn:asciiname":"5 de Junio",
    "gn:country_code":"MX",
    "gn:dem":21,
    "gn:feature_class":"P",
    "gn:feature_code":"PPL",
    "gn:name":"5 de Junio",
    "gn:population":434,
    "gn:timezone":"America/Hermosillo",
    "iso:country":"MX",
    "wof:name":"5 de Junio",
    "wof:placetype":"locality",
    "wof:population":434
},
  "geometry": {"coordinates":[-109.54703000000001,26.98434],"type":"Point"}
}