{
  "type": "Feature",
  "properties": {
    "gn:admin1_code":"26",
    "gn:admin2_code":"26.0",
    "gn:asciiname":"Navolato",
    "gn:country_code":"MX",
    "gn:dem":28,
    "gn:feature_class":"P",
    "gn:feature_code":"PPL",
    "gn:name":"Navolato",
    "gn:population":614,
    "gn:timezone":"America/Hermosillo",
    "iso:country":"MX",
    "name:spa_x_preferred":[
        "Navolato"
    ],
    "wof:name":"Navolato",
    "wof:placetype":"locality",
    "wof:population":614
},
  "geometry": {"coordinates":[-109.56882,27.03377],"type":"Point"}
}