{
  "type": "Feature",
  "properties": {
    "gn:admin1_code":"3",
    "gn:admin2_code":"3.0",
    "gn:asciiname":"Juan Marquez",
    "gn:country_code":"MX",
    "gn:dem":180,
    "gn:feature_class":"P",
    "gn:feature_code":"PPL",
    "gn:name":"Juan M\u00e1rquez",
    "gn:population":0,
    "gn:timezone":"America/Mazatlan",
    "iso:country":"MX",
    "name:spa_x_preferred":[
        "Juan M\u00e1rquez"
    ],
    "wof:name":"Juan Marquez",
    "wof:placetype":"locality"
},
  "geometry": {"coordinates":[-110.29933,23.72434],"type":"Point"}
}