{
  "type": "Feature",
  "properties": {
    "gn:admin1_code":"14",
    "gn:admin2_code":"93.0",
    "gn:asciiname":"San Antonio de los Franco (San Antonio)",
    "gn:country_code":"MX",
    "gn:dem":2076,
    "gn:feature_class":"P",
    "gn:feature_code":"PPL",
    "gn:name":"San Antonio de los Franco (San Antonio)",
    "gn:population":128,
    "gn:timezone":"America/Mexico_City",
    "iso:country":"MX",
    "wof:name":"San Antonio de los Franco (San Antonio)",
    "wof:placetype":"locality",
    "wof:population":128
},
  "geometry": {"coordinates":[-102.58583,20.80139],"type":"Point"}
}