{
  "type": "Feature",
  "properties": {
    "gn:admin1_code":"19",
    "gn:admin2_code":"15.0",
    "gn:asciiname":"Comitas",
    "gn:country_code":"MX",
    "gn:dem":88,
    "gn:feature_class":"P",
    "gn:feature_code":"PPL",
    "gn:name":"Comitas",
    "gn:population":8,
    "gn:timezone":"America/Monterrey",
    "iso:country":"MX",
    "wof:name":"Comitas",
    "wof:placetype":"locality",
    "wof:population":8
},
  "geometry": {"coordinates":[-99.01918999999999,26.09174],"type":"Point"}
}