{
  "type": "Feature",
  "properties": {
    "gn:admin1_code":"11",
    "gn:admin2_code":"11.0",
    "gn:asciiname":"Merino",
    "gn:country_code":"MX",
    "gn:dem":1746,
    "gn:feature_class":"P",
    "gn:feature_code":"PPL",
    "gn:name":"Merino",
    "gn:population":0,
    "gn:timezone":"America/Mexico_City",
    "iso:country":"MX",
    "name:und_x_variant":[
        "Salitre",
        "Mermo",
        "Merino"
    ],
    "wof:name":"Merino",
    "wof:placetype":"locality"
},
  "geometry": {"coordinates":[-100.88411000000001,20.49424],"type":"Point"}
}