{
  "type": "Feature",
  "properties": {
    "gn:admin1_code":"11",
    "gn:admin2_code":"11.0",
    "gn:asciiname":"Merino",
    "gn:country_code":"MX",
    "gn:dem":1746,
    "gn:feature_class":"P",
    "gn:feature_code":"PPL",
    "gn:name":"Merino",
    "gn:population":0,
    "gn:timezone":"America/Mexico_City",
    "iso:country":"MX",
    "name:afr_x_preferred":[
        "Merino"
    ],
    "name:ara_x_preferred":[
        "\u0645\u0627\u0631\u064a\u0646\u0648"
    ],
    "name:aze_x_preferred":[
        "Merinos qoyunu"
    ],
    "name:cat_x_preferred":[
        "Ovella merina"
    ],
    "name:ces_x_preferred":[
        "Merino"
    ],
    "name:dan_x_preferred":[
        "Merinof\u00e5r"
    ],
    "name:deu_x_preferred":[
        "Merinoschaf"
    ],
    "name:epo_x_preferred":[
        "Merino"
    ],
    "name:fin_x_preferred":[
        "Merinolammas"
    ],
    "name:fra_x_preferred":[
        "M\u00e9rinos"
    ],
    "name:gle_x_preferred":[
        "Meir\u00edon\u00f3"
    ],
    "name:hun_x_preferred":[
        "Merin\u00f3 juh"
    ],
    "name:hye_x_preferred":[
        "\u0544\u0565\u0580\u056b\u0576\u0578\u057d\u0576\u0565\u0580"
    ],
    "name:isl_x_preferred":[
        "Merin\u00f3f\u00e9"
    ],
    "name:ita_x_preferred":[
        "Merino"
    ],
    "name:jpn_x_preferred":[
        "\u30e1\u30ea\u30ce\u7a2e"
    ],
    "name:kat_x_preferred":[
        "\u10db\u10d4\u10e0\u10d8\u10dc\u10dd\u10e1\u10d8"
    ],
    "name:kaz_x_preferred":[
        "\u041c\u0435\u0440\u0438\u043d\u043e\u0441"
    ],
    "name:kir_x_preferred":[
        "\u041c\u0435\u0440\u0438\u043d\u043e\u0441 \u043a\u043e\u044e"
    ],
    "name:kor_x_preferred":[
        "\uba54\ub9ac\ub178"
    ],
    "name:lim_x_preferred":[
        "Merinosjaop"
    ],
    "name:nld_x_preferred":[
        "Merino"
    ],
    "name:nor_x_preferred":[
        "Merinosau"
    ],
    "name:pol_x_preferred":[
        "Merynosy"
    ],
    "name:por_x_preferred":[
        "Merino"
    ],
    "name:rus_x_preferred":[
        "\u041c\u0435\u0440\u0438\u043d\u043e\u0441"
    ],
    "name:slk_x_preferred":[
        "Merino"
    ],
    "name:slv_x_preferred":[
        "Merino"
    ],
    "name:spa_x_preferred":[
        "Oveja merina"
    ],
    "name:srp_x_preferred":[
        "\u041c\u0435\u0440\u0438\u043d\u043e"
    ],
    "name:swe_x_preferred":[
        "Merino"
    ],
    "name:tam_x_preferred":[
        "\u0bae\u0bc6\u0bb0\u0bc0\u0ba9\u0bcb"
    ],
    "name:tur_x_preferred":[
        "Merinos"
    ],
    "name:ukr_x_preferred":[
        "\u041c\u0435\u0440\u0438\u043d\u043e\u0441"
    ],
    "name:und_x_variant":[
        "Salitre",
        "Mermo",
        "Merino"
    ],
    "name:vie_x_preferred":[
        "C\u1eebu Merino"
    ],
    "name:zho_x_preferred":[
        "\u7f8e\u5229\u5974\u7f8a"
    ],
    "wof:name":"Merino",
    "wof:placetype":"locality"
},
  "geometry": {"coordinates":[-100.88411000000001,20.49424],"type":"Point"}
}