{
  "type": "Feature",
  "properties": {
    "gn:admin1_code":"5",
    "gn:admin2_code":"69",
    "gn:asciiname":"Nuevo Rio Bravo",
    "gn:country_code":"MX",
    "gn:dem":415,
    "gn:feature_class":"P",
    "gn:feature_code":"PPL",
    "gn:name":"Nuevo R\u00edo Bravo",
    "gn:population":19,
    "gn:timezone":"America/Mexico_City",
    "iso:country":"MX",
    "name:und_x_variant":[
        "Nuevo R\u00edo Bravo"
    ],
    "wof:name":"Nuevo Rio Bravo",
    "wof:placetype":"locality",
    "wof:population":19
},
  "geometry": {"coordinates":[-93.13288,15.75508],"type":"Point"}
}