{
  "type": "Feature",
  "properties": {
    "gn:admin1_code":"25.0",
    "gn:admin2_code":"6.0",
    "gn:asciiname":"Chiqueritos",
    "gn:country_code":"MX",
    "gn:dem":44,
    "gn:feature_class":"P",
    "gn:feature_code":"PPL",
    "gn:name":"Chiqueritos",
    "gn:population":0,
    "gn:timezone":"America/Mazatlan",
    "iso:country":"MX",
    "name:spa_x_preferred":[
        "Chiqueritos"
    ],
    "name:und_x_variant":[
        "Chiquerito"
    ],
    "wof:name":"Chiqueritos",
    "wof:placetype":"locality"
},
  "geometry": {"coordinates":[-107.0389,24.17974],"type":"Point"}
}