{
  "type": "Feature",
  "properties": {
    "gn:admin1_code":"24",
    "gn:admin2_code":"34",
    "gn:asciiname":"Las Mananitas",
    "gn:country_code":"MX",
    "gn:dem":34,
    "gn:feature_class":"P",
    "gn:feature_code":"PPL",
    "gn:name":"Las Ma\u00f1anitas",
    "gn:population":25,
    "gn:timezone":"America/Mexico_City",
    "iso:country":"MX",
    "name:und_x_variant":[
        "Las Ma\u00f1anitas"
    ],
    "wof:name":"Las Mananitas",
    "wof:placetype":"locality",
    "wof:population":25
},
  "geometry": {"coordinates":[-98.48611,21.78972000000001],"type":"Point"}
}