{
  "type": "Feature",
  "properties": {
    "gn:admin1_code":"23.0",
    "gn:asciiname":"Rivemar",
    "gn:country_code":"MX",
    "gn:dem":8,
    "gn:feature_class":"P",
    "gn:feature_code":"PPL",
    "gn:name":"Rivemar",
    "gn:population":0,
    "gn:timezone":"America/Cancun",
    "iso:country":"MX",
    "name:spa_x_preferred":[
        "Rivemar"
    ],
    "wof:name":"Rivemar",
    "wof:placetype":"locality"
},
  "geometry": {"coordinates":[-87.19731,20.52721],"type":"Point"}
}