{
  "type": "Feature",
  "properties": {
    "gn:admin1_code":"2.0",
    "gn:admin2_code":"1.0",
    "gn:asciiname":"La Huertita",
    "gn:country_code":"MX",
    "gn:dem":283,
    "gn:feature_class":"P",
    "gn:feature_code":"PPL",
    "gn:name":"La Huertita",
    "gn:population":0,
    "gn:timezone":"America/Tijuana",
    "iso:country":"MX",
    "name:spa_x_preferred":[
        "La Huertita"
    ],
    "wof:name":"La Huertita",
    "wof:placetype":"locality"
},
  "geometry": {"coordinates":[-116.36226000000001,31.64127],"type":"Point"}
}