{
  "type": "Feature",
  "properties": {
    "gn:admin1_code":"10",
    "gn:admin2_code":"30.0",
    "gn:asciiname":"Tres Hermanos",
    "gn:country_code":"MX",
    "gn:dem":1750,
    "gn:feature_class":"P",
    "gn:feature_code":"PPL",
    "gn:name":"Tres Hermanos",
    "gn:population":0,
    "gn:timezone":"America/Monterrey",
    "iso:country":"MX",
    "name:spa_x_preferred":[
        "Tres Hermanos"
    ],
    "name:spa_x_variant":[
        "El Setenta y Cinco"
    ],
    "name:und_x_variant":[
        "Rancho Tres Hermanas"
    ],
    "wof:name":"Tres Hermanos",
    "wof:placetype":"locality"
},
  "geometry": {"coordinates":[-104.33413,25.83251],"type":"Point"}
}