{
  "type": "Feature",
  "properties": {
    "gn:admin1_code":"13",
    "gn:admin2_code":"18.0",
    "gn:asciiname":"Sayula",
    "gn:country_code":"MX",
    "gn:dem":586,
    "gn:feature_class":"P",
    "gn:feature_code":"PPL",
    "gn:name":"Sayula",
    "gn:population":7,
    "gn:timezone":"America/Mexico_City",
    "iso:country":"MX",
    "wof:name":"Sayula",
    "wof:placetype":"locality",
    "wof:population":7
},
  "geometry": {"coordinates":[-98.87174,21.15752],"type":"Point"}
}