{
  "type": "Feature",
  "properties": {
    "gn:admin1_code":"19.0",
    "gn:admin2_code":"16.0",
    "gn:asciiname":"Los Encinitos",
    "gn:country_code":"MX",
    "gn:dem":396,
    "gn:feature_class":"P",
    "gn:feature_code":"PPL",
    "gn:name":"Los Encinitos",
    "gn:population":0,
    "gn:timezone":"America/Monterrey",
    "iso:country":"MX",
    "name:spa_x_preferred":[
        "Los Encinitos"
    ],
    "wof:name":"Los Encinitos",
    "wof:placetype":"locality"
},
  "geometry": {"coordinates":[-99.84045,25.88606],"type":"Point"}
}