{
  "type": "Feature",
  "properties": {
    "gn:admin1_code":"6",
    "gn:admin2_code":"27.0",
    "gn:asciiname":"Agua Escondida",
    "gn:country_code":"MX",
    "gn:dem":2472,
    "gn:feature_class":"P",
    "gn:feature_code":"PPL",
    "gn:name":"Agua Escondida",
    "gn:population":72,
    "gn:timezone":"America/Chihuahua",
    "iso:country":"MX",
    "wof:name":"Agua Escondida",
    "wof:placetype":"locality",
    "wof:population":72
},
  "geometry": {"coordinates":[-107.111,26.89966],"type":"Point"}
}