{
  "type": "Feature",
  "properties": {
    "gn:admin1_code":"27",
    "gn:admin2_code":"3.0",
    "gn:asciiname":"San Francisco",
    "gn:country_code":"MX",
    "gn:dem":0,
    "gn:feature_class":"P",
    "gn:feature_code":"PPL",
    "gn:name":"San Francisco",
    "gn:population":0,
    "gn:timezone":"America/Mexico_City",
    "iso:country":"MX",
    "wof:name":"San Francisco",
    "wof:placetype":"locality"
},
  "geometry": {"coordinates":[-92.56667,18.31667],"type":"Point"}
}