{
  "type": "Feature",
  "properties": {
    "gn:admin1_code":"10.0",
    "gn:admin2_code":"7.0",
    "gn:asciiname":"Jerico",
    "gn:country_code":"MX",
    "gn:dem":1110,
    "gn:feature_class":"P",
    "gn:feature_code":"PPL",
    "gn:name":"Jeric\u00f3",
    "gn:population":0,
    "gn:timezone":"America/Monterrey",
    "iso:country":"MX",
    "name:spa_x_preferred":[
        "Jeric\u00f3"
    ],
    "wof:name":"Jerico",
    "wof:placetype":"locality"
},
  "geometry": {"coordinates":[-103.53489999999999,25.77654],"type":"Point"}
}