{
  "type": "Feature",
  "properties": {
    "gn:admin1_code":"12.0",
    "gn:admin2_code":"11.0",
    "gn:asciiname":"Huerta de los Benitez",
    "gn:country_code":"MX",
    "gn:dem":18,
    "gn:feature_class":"P",
    "gn:feature_code":"PPL",
    "gn:name":"Huerta de los Ben\u00edtez",
    "gn:population":0,
    "gn:timezone":"America/Mexico_City",
    "iso:country":"MX",
    "name:spa_x_preferred":[
        "Huerta de los Ben\u00edtez"
    ],
    "wof:name":"Huerta de los Benitez",
    "wof:placetype":"locality"
},
  "geometry": {"coordinates":[-100.35872999999999,17.101],"type":"Point"}
}