{
  "type": "Feature",
  "properties": {
    "gn:admin1_code":"26",
    "gn:admin2_code":"60.0",
    "gn:asciiname":"El Silencio (El Silencioso)",
    "gn:country_code":"MX",
    "gn:dem":971,
    "gn:feature_class":"P",
    "gn:feature_code":"PPL",
    "gn:name":"El Silencio (El Silencioso)",
    "gn:population":1,
    "gn:timezone":"America/Hermosillo",
    "iso:country":"MX",
    "wof:name":"El Silencio (El Silencioso)",
    "wof:placetype":"locality",
    "wof:population":1
},
  "geometry": {"coordinates":[-111.35457,31.32056],"type":"Point"}
}