{
  "type": "Feature",
  "properties": {
    "gn:admin1_code":"24",
    "gn:admin2_code":"19.0",
    "gn:asciiname":"Calderon",
    "gn:country_code":"MX",
    "gn:dem":739,
    "gn:feature_class":"P",
    "gn:feature_code":"PPL",
    "gn:name":"Calder\u00f3n",
    "gn:population":0,
    "gn:timezone":"America/Mexico_City",
    "iso:country":"MX",
    "wof:name":"Calderon",
    "wof:placetype":"locality"
},
  "geometry": {"coordinates":[-99.68333,21.68333],"type":"Point"}
}