{
  "type": "Feature",
  "properties": {
    "gn:admin1_code":"30",
    "gn:admin2_code":"148.0",
    "gn:asciiname":"La Vigia",
    "gn:country_code":"MX",
    "gn:dem":179,
    "gn:feature_class":"P",
    "gn:feature_code":"PPL",
    "gn:name":"La Vig\u00eda",
    "gn:population":0,
    "gn:timezone":"America/Mexico_City",
    "iso:country":"MX",
    "name:spa_x_preferred":[
        "La Vig\u00eda"
    ],
    "wof:name":"La Vigia",
    "wof:placetype":"locality"
},
  "geometry": {"coordinates":[-96.48148999999999,18.97803],"type":"Point"}
}