{
  "type": "Feature",
  "properties": {
    "gn:admin1_code":"12",
    "gn:admin2_code":"27.0",
    "gn:asciiname":"Rancho el Coco",
    "gn:country_code":"MX",
    "gn:dem":280,
    "gn:feature_class":"P",
    "gn:feature_code":"PPL",
    "gn:name":"Rancho el Coco",
    "gn:population":5,
    "gn:timezone":"America/Mexico_City",
    "iso:country":"MX",
    "wof:name":"Rancho el Coco",
    "wof:placetype":"locality",
    "wof:population":5
},
  "geometry": {"coordinates":[-100.59806,18.43917],"type":"Point"}
}