{
  "type": "Feature",
  "properties": {
    "iso:country":"MX",
    "name:eng_x_preferred":[
        "Barrio Hombres Blancos"
    ],
    "name:spa_x_preferred":[
        "Barrio Hombres Blancos"
    ],
    "qs:gn_adm0_cc":"MX",
    "qs:gn_local":3982837,
    "qs:gn_nam_loc":"sonoyta",
    "qs:gn_namadm1":"26",
    "qs:local_max":76,
    "qs:local_sum":76,
    "qs:localhoods":1,
    "qs:name":"Barrio Hombres Blancos",
    "qs:name_adm0":"M\u00e9xico",
    "qs:name_adm1":"Sonora",
    "qs:name_adm2":"General Plutarco Elias Calles",
    "qs:name_local":"Sonoyta",
    "qs:photo_max":36,
    "qs:photo_sum":76,
    "qs:placetype":"Suburb",
    "qs:quad_count":9,
    "qs:woe_adm0":23424900,
    "qs:woe_adm1":2346289,
    "qs:woe_adm2":12601571,
    "qs:woe_lau":0,
    "qs:woe_local":147790,
    "qs:woe_ver":"7.10.0",
    "wof:lang":[
        "spa"
    ],
    "wof:name":"Barrio Hombres Blancos",
    "wof:placetype":"neighbourhood"
},
  "geometry": {"coordinates":[-112.819361,31.880105],"type":"Point"}
}