{
  "type": "Feature",
  "properties": {
    "gn:admin1_code":"7",
    "gn:admin2_code":"31.0",
    "gn:asciiname":"El Mesteno",
    "gn:country_code":"MX",
    "gn:dem":714,
    "gn:feature_class":"P",
    "gn:feature_code":"PPL",
    "gn:name":"El Meste\u00f1o",
    "gn:population":0,
    "gn:timezone":"America/Monterrey",
    "iso:country":"MX",
    "name:spa_x_preferred":[
        "El Meste\u00f1o"
    ],
    "name:und_x_variant":[
        "Rancho El Meste\u00f1o"
    ],
    "wof:name":"El Mesteno",
    "wof:placetype":"locality"
},
  "geometry": {"coordinates":[-101.71738999999999,27.53149],"type":"Point"}
}