{
  "type": "Feature",
  "properties": {
    "gn:gn_country":"MX",
    "gn:gn_fcode":"PPL",
    "gn:gn_pop":0,
    "iso:country":"MX",
    "name:spa_x_preferred":[
        "Marina Vallarta"
    ],
    "name:unk_x_variant":[
        "Marina Vallarta"
    ],
    "qs:gn_adm0_cc":"MX",
    "qs:gn_fcode":"PPL",
    "qs:gn_local":3991328,
    "qs:gn_nam_loc":"Puerto Vallarta, Puerto Vallarta, Jalisco, MX",
    "qs:gn_namadm1":"14",
    "qs:gn_name":"Marina Vallarta",
    "qs:local_max":6256,
    "qs:local_sum":18911,
    "qs:localhoods":15,
    "qs:name":"Marina Vallarta",
    "qs:name_adm0":"M\u00e9xico",
    "qs:name_adm1":"Jalisco",
    "qs:name_adm2":"Puerto Vallarta",
    "qs:name_local":"Puerto Vallarta",
    "qs:photo_max":666,
    "qs:photo_sum":1328,
    "qs:placetype":"Suburb",
    "qs:quad_count":40,
    "qs:woe_adm0":23424900,
    "qs:woe_adm1":2346277,
    "qs:woe_adm2":12600264,
    "qs:woe_lau":0,
    "qs:woe_local":137895,
    "qs:woe_ver":"7.10.0",
    "qs_pg:aaroncc":"MX",
    "qs_pg:gn_country":"MX",
    "qs_pg:gn_fcode":"PPL",
    "qs_pg:gn_pop":0,
    "qs_pg:name":"Marina Vallarta",
    "qs_pg:name_adm0":"M\u00e9xico",
    "qs_pg:name_adm1":"Jalisco",
    "qs_pg:photos":665,
    "qs_pg:photos_1k":135,
    "qs_pg:photos_9k":3,
    "qs_pg:photos_9r":5,
    "qs_pg:photos_all":665,
    "qs_pg:photos_sr":8,
    "qs_pg:pop_sr":0,
    "qs_pg:qs_pg_placetype":"neighbourhood",
    "qs_pg:qs_pg_placetype_gp":"Suburb",
    "qs_pg:woe_adm0":23424900,
    "wof:lang":[
        "spa"
    ],
    "wof:name":"Marina Vallarta",
    "wof:placetype":"neighbourhood"
},
  "geometry": {"coordinates":[-105.25563,20.662442],"type":"Point"}
}