{
  "type": "Feature",
  "properties": {
    "gn:admin1_code":"8",
    "gn:admin2_code":"9",
    "gn:asciiname":"Las Mercedes",
    "gn:country_code":"MX",
    "gn:dem":27,
    "gn:feature_class":"P",
    "gn:feature_code":"PPL",
    "gn:name":"Las Mercedes",
    "gn:population":16,
    "gn:timezone":"America/Mexico_City",
    "iso:country":"MX",
    "name:ceb_x_preferred":[
        "Las Mercedes"
    ],
    "name:deu_x_preferred":[
        "Las Mercedes"
    ],
    "name:spa_x_preferred":[
        "Las Mercedes"
    ],
    "name:swe_x_preferred":[
        "Las Mercedes"
    ],
    "wof:name":"Las Mercedes",
    "wof:placetype":"locality",
    "wof:population":16
},
  "geometry": {"coordinates":[-103.85778000000001,18.88167],"type":"Point"}
}