{
  "type": "Feature",
  "properties": {
    "gn:admin1_code":"19",
    "gn:admin2_code":"41.0",
    "gn:asciiname":"Santa Candelaria",
    "gn:country_code":"MX",
    "gn:dem":350,
    "gn:feature_class":"P",
    "gn:feature_code":"PPL",
    "gn:name":"Santa Candelaria",
    "gn:population":6,
    "gn:timezone":"America/Monterrey",
    "iso:country":"MX",
    "wof:name":"Santa Candelaria",
    "wof:placetype":"locality",
    "wof:population":6
},
  "geometry": {"coordinates":[-100.08083000000001,25.7925],"type":"Point"}
}