{
  "type": "Feature",
  "properties": {
    "gn:admin1_code":"25",
    "gn:admin2_code":"14.0",
    "gn:asciiname":"El Cardon (La Ceiba)",
    "gn:country_code":"MX",
    "gn:dem":73,
    "gn:feature_class":"P",
    "gn:feature_code":"PPL",
    "gn:name":"El Card\u00f3n (La Ceiba)",
    "gn:population":5,
    "gn:timezone":"America/Mazatlan",
    "iso:country":"MX",
    "name:und_x_variant":[
        "El Card\u00f3n (La Ceiba)"
    ],
    "wof:name":"El Cardon (La Ceiba)",
    "wof:placetype":"locality",
    "wof:population":5
},
  "geometry": {"coordinates":[-105.80642,23.07505],"type":"Point"}
}