{
  "type": "Feature",
  "properties": {
    "gn:admin1_code":"25",
    "gn:admin2_code":"13.0",
    "gn:asciiname":"Pie de la Cuesta",
    "gn:country_code":"MX",
    "gn:dem":755,
    "gn:feature_class":"P",
    "gn:feature_code":"PPL",
    "gn:name":"Pie de la Cuesta",
    "gn:population":0,
    "gn:timezone":"America/Mazatlan",
    "iso:country":"MX",
    "wof:name":"Pie de la Cuesta",
    "wof:placetype":"locality"
},
  "geometry": {"coordinates":[-107.68333,25.73333],"type":"Point"}
}