{
  "type": "Feature",
  "properties": {
    "gn:admin1_code":"19.0",
    "gn:admin2_code":"42.0",
    "gn:asciiname":"Santa Magdalena",
    "gn:country_code":"MX",
    "gn:dem":208,
    "gn:feature_class":"P",
    "gn:feature_code":"PPL",
    "gn:name":"Santa Magdalena",
    "gn:population":0,
    "gn:timezone":"America/Monterrey",
    "iso:country":"MX",
    "name:spa_x_preferred":[
        "Santa Magdalena"
    ],
    "wof:name":"Santa Magdalena",
    "wof:placetype":"locality"
},
  "geometry": {"coordinates":[-99.60120999999999,25.68032],"type":"Point"}
}