{
  "type": "Feature",
  "properties": {
    "gn:admin1_code":"30",
    "gn:admin2_code":"126.0",
    "gn:asciiname":"La Vibora",
    "gn:country_code":"MX",
    "gn:dem":24,
    "gn:feature_class":"P",
    "gn:feature_code":"PPL",
    "gn:name":"La V\u00edbora",
    "gn:population":405,
    "gn:timezone":"America/Mexico_City",
    "iso:country":"MX",
    "wof:name":"La Vibora",
    "wof:placetype":"locality",
    "wof:population":405
},
  "geometry": {"coordinates":[-96.37194,19.30833],"type":"Point"}
}