{
  "type": "Feature",
  "properties": {
    "gn:admin1_code":"13",
    "gn:admin2_code":"20.0",
    "gn:asciiname":"Eloxochitlan",
    "gn:country_code":"MX",
    "gn:dem":1969,
    "gn:feature_class":"P",
    "gn:feature_code":"PPL",
    "gn:name":"Eloxochitl\u00e1n",
    "gn:population":0,
    "gn:timezone":"America/Mexico_City",
    "iso:country":"MX",
    "name:und_x_variant":[
        "San Agust\u00edn Eloxtitla",
        "Eloxoehitlan",
        "Eloxochitl\u00e1n",
        "San Agust\u00edn"
    ],
    "wof:name":"Eloxochitlan",
    "wof:placetype":"locality"
},
  "geometry": {"coordinates":[-98.80851,20.74287],"type":"Point"}
}