{
  "type": "Feature",
  "properties": {
    "gn:admin1_code":"13",
    "gn:admin2_code":"20.0",
    "gn:asciiname":"Eloxochitlan",
    "gn:country_code":"MX",
    "gn:dem":1969,
    "gn:feature_class":"P",
    "gn:feature_code":"PPL",
    "gn:name":"Eloxochitl\u00e1n",
    "gn:population":0,
    "gn:timezone":"America/Mexico_City",
    "iso:country":"MX",
    "name:epo_x_preferred":[
        "Eloxochitl\u00e1n"
    ],
    "name:ita_x_preferred":[
        "Eloxochitl\u00e1n"
    ],
    "name:sco_x_preferred":[
        "Eloxochitl\u00e1n"
    ],
    "name:srp_x_preferred":[
        "\u041e\u043f\u0448\u0442\u0438\u043d\u0430 \u0415\u043b\u043e\u043a\u0441\u043e\u0447\u0438\u0442\u043b\u0430\u043d"
    ],
    "name:und_x_variant":[
        "San Agust\u00edn Eloxtitla",
        "Eloxoehitlan",
        "San Agust\u00edn"
    ],
    "name:vie_x_preferred":[
        "Eloxochitl\u00e1n"
    ],
    "wof:name":"Eloxochitlan",
    "wof:placetype":"locality"
},
  "geometry": {"coordinates":[-98.80851,20.74287],"type":"Point"}
}