{
  "type": "Feature",
  "properties": {
    "gn:admin1_code":"12",
    "gn:admin2_code":"10",
    "gn:asciiname":"Hueyitepec",
    "gn:country_code":"MX",
    "gn:dem":1562,
    "gn:feature_class":"P",
    "gn:feature_code":"PPL",
    "gn:name":"Hueyitepec",
    "gn:population":40,
    "gn:timezone":"America/Mexico_City",
    "iso:country":"MX",
    "wof:name":"Hueyitepec",
    "wof:placetype":"locality",
    "wof:population":40
},
  "geometry": {"coordinates":[-98.97235999999999,17.61422],"type":"Point"}
}