{
  "type": "Feature",
  "properties": {
    "gn:admin1_code":"16.0",
    "gn:admin2_code":"10.0",
    "gn:asciiname":"La Higuera Baleada",
    "gn:country_code":"MX",
    "gn:dem":384,
    "gn:feature_class":"P",
    "gn:feature_code":"PPL",
    "gn:name":"La Higuera Baleada",
    "gn:population":0,
    "gn:timezone":"America/Mexico_City",
    "iso:country":"MX",
    "name:spa_x_preferred":[
        "La Higuera Baleada"
    ],
    "wof:name":"La Higuera Baleada",
    "wof:placetype":"locality"
},
  "geometry": {"coordinates":[-102.06793,18.31989],"type":"Point"}
}