{
  "type": "Feature",
  "properties": {
    "gn:admin1_code":"21",
    "gn:admin2_code":"49.0",
    "gn:asciiname":"Zempoala",
    "gn:country_code":"MX",
    "gn:dem":1486,
    "gn:feature_class":"P",
    "gn:feature_code":"PPL",
    "gn:name":"Zempoala",
    "gn:population":0,
    "gn:timezone":"America/Mexico_City",
    "iso:country":"MX",
    "name:spa_x_preferred":[
        "Zempoala"
    ],
    "wof:name":"Zempoala",
    "wof:placetype":"locality"
},
  "geometry": {"coordinates":[-97.99850000000001,20.0867],"type":"Point"}
}