{
  "type": "Feature",
  "properties": {
    "gn:admin1_code":"12",
    "gn:admin2_code":"73.0",
    "gn:asciiname":"La Ceja",
    "gn:country_code":"MX",
    "gn:dem":225,
    "gn:feature_class":"P",
    "gn:feature_code":"PPL",
    "gn:name":"La Ceja",
    "gn:population":0,
    "gn:timezone":"America/Mexico_City",
    "iso:country":"MX",
    "name:spa_x_preferred":[
        "La Ceja"
    ],
    "wof:name":"La Ceja",
    "wof:placetype":"locality"
},
  "geometry": {"coordinates":[-101.06946000000001,18.48356],"type":"Point"}
}