{
  "type": "Feature",
  "properties": {
    "gn:admin1_code":"6",
    "gn:admin2_code":"27.0",
    "gn:asciiname":"Cieneguitas (Ocorare)",
    "gn:country_code":"MX",
    "gn:dem":2283,
    "gn:feature_class":"P",
    "gn:feature_code":"PPL",
    "gn:name":"Cieneguitas (Ocorare)",
    "gn:population":5,
    "gn:timezone":"America/Chihuahua",
    "iso:country":"MX",
    "wof:name":"Cieneguitas (Ocorare)",
    "wof:placetype":"locality",
    "wof:population":5
},
  "geometry": {"coordinates":[-107.46185,27.2266],"type":"Point"}
}