{
  "type": "Feature",
  "properties": {
    "gn:admin1_code":"14",
    "gn:admin2_code":"49.0",
    "gn:asciiname":"Coaquixpala",
    "gn:country_code":"MX",
    "gn:dem":545,
    "gn:feature_class":"P",
    "gn:feature_code":"PPL",
    "gn:name":"Coaquixpala",
    "gn:population":7,
    "gn:timezone":"America/Mexico_City",
    "iso:country":"MX",
    "wof:name":"Coaquixpala",
    "wof:placetype":"locality",
    "wof:population":7
},
  "geometry": {"coordinates":[-102.93028,19.38639],"type":"Point"}
}