{
  "type": "Feature",
  "properties": {
    "gn:admin1_code":"11.0",
    "gn:admin2_code":"42.0",
    "gn:asciiname":"El Pitahayo",
    "gn:cc2":"MX",
    "gn:country_code":"MX",
    "gn:dem":1718,
    "gn:feature_class":"P",
    "gn:feature_code":"PPL",
    "gn:name":"El Pitahayo",
    "gn:population":330,
    "gn:timezone":"America/Mexico_City",
    "iso:country":"MX",
    "name:und_x_variant":[
        "Pitahaya",
        "El Pitahayo"
    ],
    "wof:name":"El Pitahayo",
    "wof:placetype":"locality",
    "wof:population":330
},
  "geometry": {"coordinates":[-101.13583,20.47361],"type":"Point"}
}