{
  "type": "Feature",
  "properties": {
    "gn:admin1_code":"10",
    "gn:admin2_code":"3.0",
    "gn:asciiname":"La Leona",
    "gn:country_code":"MX",
    "gn:dem":1930,
    "gn:feature_class":"P",
    "gn:feature_code":"PPL",
    "gn:name":"La Leona",
    "gn:population":0,
    "gn:timezone":"America/Monterrey",
    "iso:country":"MX",
    "name:spa_x_preferred":[
        "La Leona"
    ],
    "wof:name":"La Leona",
    "wof:placetype":"locality"
},
  "geometry": {"coordinates":[-104.64681,24.82488],"type":"Point"}
}