{
  "type": "Feature",
  "properties": {
    "gn:admin1_code":"6",
    "gn:admin2_code":"29.0",
    "gn:asciiname":"Saucito de los Perez",
    "gn:country_code":"MX",
    "gn:dem":1445,
    "gn:feature_class":"P",
    "gn:feature_code":"PPL",
    "gn:name":"Saucito de los P\u00e9rez",
    "gn:population":0,
    "gn:timezone":"America/Chihuahua",
    "iso:country":"MX",
    "name:spa_x_preferred":[
        "Saucito de los P\u00e9rez"
    ],
    "wof:name":"Saucito de los Perez",
    "wof:placetype":"locality"
},
  "geometry": {"coordinates":[-107.3319,26.09654],"type":"Point"}
}