{
  "type": "Feature",
  "properties": {
    "gn:admin1_code":"5.0",
    "gn:asciiname":"Seis de Octubre",
    "gn:country_code":"MX",
    "gn:dem":947,
    "gn:feature_class":"P",
    "gn:feature_code":"PPL",
    "gn:name":"Seis de Octubre",
    "gn:population":0,
    "gn:timezone":"America/Mexico_City",
    "iso:country":"MX",
    "name:spa_x_preferred":[
        "Seis de Octubre"
    ],
    "wof:name":"Seis de Octubre",
    "wof:placetype":"locality"
},
  "geometry": {"coordinates":[-91.43868000000001,16.89345],"type":"Point"}
}