{
  "type": "Feature",
  "properties": {
    "gn:admin1_code":"5",
    "gn:admin2_code":"34.0",
    "gn:asciiname":"Las Canoitas",
    "gn:country_code":"MX",
    "gn:dem":736,
    "gn:feature_class":"P",
    "gn:feature_code":"PPL",
    "gn:name":"Las Canoitas",
    "gn:population":6,
    "gn:timezone":"America/Mexico_City",
    "iso:country":"MX",
    "wof:name":"Las Canoitas",
    "wof:placetype":"locality",
    "wof:population":6
},
  "geometry": {"coordinates":[-92.10444,15.70111],"type":"Point"}
}