{
  "type": "Feature",
  "properties": {
    "gn:admin1_code":"26",
    "gn:admin2_code":"42.0",
    "gn:asciiname":"El Chapote (El Zapote)",
    "gn:country_code":"MX",
    "gn:dem":41,
    "gn:feature_class":"P",
    "gn:feature_code":"PPL",
    "gn:name":"El Chapote (El Zapote)",
    "gn:population":138,
    "gn:timezone":"America/Hermosillo",
    "iso:country":"MX",
    "wof:name":"El Chapote (El Zapote)",
    "wof:placetype":"locality",
    "wof:population":138
},
  "geometry": {"coordinates":[-109.39792,27.15385],"type":"Point"}
}