{
  "type": "Feature",
  "properties": {
    "gn:admin1_code":"15",
    "gn:admin2_code":"110.0",
    "gn:asciiname":"Loma de Chihuahua",
    "gn:country_code":"MX",
    "gn:dem":2003,
    "gn:feature_class":"P",
    "gn:feature_code":"PPL",
    "gn:name":"Loma de Chihuahua",
    "gn:population":273,
    "gn:timezone":"America/Mexico_City",
    "iso:country":"MX",
    "wof:name":"Loma de Chihuahua",
    "wof:placetype":"locality",
    "wof:population":273
},
  "geometry": {"coordinates":[-100.09344,19.17738],"type":"Point"}
}