{
  "type": "Feature",
  "properties": {
    "gn:admin1_code":"32.0",
    "gn:admin2_code":"49.0",
    "gn:asciiname":"Las Cuevecillas",
    "gn:country_code":"MX",
    "gn:dem":2185,
    "gn:feature_class":"P",
    "gn:feature_code":"PPL",
    "gn:name":"Las Cuevecillas",
    "gn:population":0,
    "gn:timezone":"America/Mexico_City",
    "iso:country":"MX",
    "name:spa_x_preferred":[
        "Las Cuevecillas"
    ],
    "wof:name":"Las Cuevecillas",
    "wof:placetype":"locality"
},
  "geometry": {"coordinates":[-103.3608,22.95311],"type":"Point"}
}