{
  "type": "Feature",
  "properties": {
    "gn:admin1_code":"28.0",
    "gn:admin2_code":"27.0",
    "gn:asciiname":"La Huizachoza",
    "gn:country_code":"MX",
    "gn:dem":130,
    "gn:feature_class":"P",
    "gn:feature_code":"PPL",
    "gn:name":"La Huizachoza",
    "gn:population":3,
    "gn:timezone":"America/Matamoros",
    "iso:country":"MX",
    "name:spa_x_preferred":[
        "La Huisachosa"
    ],
    "wof:name":"La Huizachoza",
    "wof:placetype":"locality",
    "wof:population":3
},
  "geometry": {"coordinates":[-99.51347,27.3684],"type":"Point"}
}