{
  "type": "Feature",
  "properties": {
    "gn:admin1_code":"25",
    "gn:admin2_code":"17.0",
    "gn:asciiname":"Mapiri",
    "gn:country_code":"MX",
    "gn:dem":299,
    "gn:feature_class":"P",
    "gn:feature_code":"PPL",
    "gn:name":"Mapiri",
    "gn:population":32,
    "gn:timezone":"America/Mazatlan",
    "iso:country":"MX",
    "name:ceb_x_preferred":[
        "Mapiri"
    ],
    "name:deu_x_preferred":[
        "Mapiri"
    ],
    "name:fra_x_preferred":[
        "Mapiri"
    ],
    "name:pol_x_preferred":[
        "Mapiri"
    ],
    "name:que_x_preferred":[
        "Mapiri"
    ],
    "name:spa_x_preferred":[
        "Mapiri"
    ],
    "name:zho_x_preferred":[
        "\u99ac\u76ae\u91cc"
    ],
    "wof:name":"Mapiri",
    "wof:placetype":"locality",
    "wof:population":32
},
  "geometry": {"coordinates":[-107.94793,25.73242],"type":"Point"}
}