{
  "type": "Feature",
  "properties": {
    "gn:admin1_code":"7.0",
    "gn:admin2_code":"2.0",
    "gn:asciiname":"Garcia Zuazua",
    "gn:country_code":"MX",
    "gn:dem":286,
    "gn:feature_class":"P",
    "gn:feature_code":"PPL",
    "gn:name":"Garc\u00eda Zuazua",
    "gn:population":0,
    "gn:timezone":"America/Matamoros",
    "iso:country":"MX",
    "wof:name":"Garcia Zuazua",
    "wof:placetype":"locality"
},
  "geometry": {"coordinates":[-100.96666999999999,29.31667],"type":"Point"}
}