{
  "type": "Feature",
  "properties": {
    "gn:admin1_code":"30",
    "gn:admin2_code":"155.0",
    "gn:asciiname":"Mano de Leon",
    "gn:country_code":"MX",
    "gn:dem":120,
    "gn:feature_class":"P",
    "gn:feature_code":"PPL",
    "gn:name":"Mano de Le\u00f3n",
    "gn:population":168,
    "gn:timezone":"America/Mexico_City",
    "iso:country":"MX",
    "name:spa_x_preferred":[
        "Mano de Le\u00f3n"
    ],
    "wof:name":"Mano de Leon",
    "wof:placetype":"locality",
    "wof:population":168
},
  "geometry": {"coordinates":[-98.145,21.23528],"type":"Point"}
}