{
  "type": "Feature",
  "properties": {
    "gn:admin1_code":"24",
    "gn:admin2_code":"39.0",
    "gn:asciiname":"El Rincon Rico",
    "gn:country_code":"MX",
    "gn:dem":77,
    "gn:feature_class":"P",
    "gn:feature_code":"PPL",
    "gn:name":"El Rinc\u00f3n Rico",
    "gn:population":0,
    "gn:timezone":"America/Mexico_City",
    "iso:country":"MX",
    "name:spa_x_preferred":[
        "El Rinc\u00f3n Rico"
    ],
    "wof:name":"El Rincon Rico",
    "wof:placetype":"locality"
},
  "geometry": {"coordinates":[-98.72251,21.52099],"type":"Point"}
}