{
  "type": "Feature",
  "properties": {
    "gn:admin1_code":"21",
    "gn:admin2_code":"96.0",
    "gn:asciiname":"San Luis Sesma",
    "gn:country_code":"MX",
    "gn:dem":2356,
    "gn:feature_class":"P",
    "gn:feature_code":"PPL",
    "gn:name":"San Luis Sesma",
    "gn:population":0,
    "gn:timezone":"America/Mexico_City",
    "iso:country":"MX",
    "name:spa_x_preferred":[
        "San Luis Sesma"
    ],
    "wof:name":"San Luis Sesma",
    "wof:placetype":"locality"
},
  "geometry": {"coordinates":[-97.70583999999999,19.19344],"type":"Point"}
}