{
  "type": "Feature",
  "properties": {
    "gn:admin1_code":"6.0",
    "gn:admin2_code":"34.0",
    "gn:asciiname":"Casa de la Presa",
    "gn:country_code":"MX",
    "gn:dem":2069,
    "gn:feature_class":"P",
    "gn:feature_code":"PPL",
    "gn:name":"Casa de la Presa",
    "gn:population":0,
    "gn:timezone":"America/Chihuahua",
    "iso:country":"MX",
    "name:spa_x_preferred":[
        "Casa de la Presa"
    ],
    "name:spa_x_variant":[
        "Junta de los Arroyos"
    ],
    "wof:name":"Casa de la Presa",
    "wof:placetype":"locality"
},
  "geometry": {"coordinates":[-107.81229999999999,29.63663],"type":"Point"}
}