{
  "type": "Feature",
  "properties": {
    "gn:admin1_code":"28.0",
    "gn:admin2_code":"7.0",
    "gn:asciiname":"La Mecha",
    "gn:country_code":"MX",
    "gn:dem":93,
    "gn:feature_class":"P",
    "gn:feature_code":"PPL",
    "gn:name":"La Mecha",
    "gn:population":0,
    "gn:timezone":"America/Monterrey",
    "iso:country":"MX",
    "name:spa_x_preferred":[
        "La Mecha"
    ],
    "wof:name":"La Mecha",
    "wof:placetype":"locality"
},
  "geometry": {"coordinates":[-98.95525000000001,26.1049],"type":"Point"}
}