{
  "type": "Feature",
  "properties": {
    "gn:admin1_code":"13",
    "gn:admin2_code":"17.0",
    "gn:asciiname":"Santiago Loma",
    "gn:country_code":"MX",
    "gn:dem":2261,
    "gn:feature_class":"P",
    "gn:feature_code":"PPL",
    "gn:name":"Santiago Loma",
    "gn:population":0,
    "gn:timezone":"America/Mexico_City",
    "iso:country":"MX",
    "wof:name":"Santiago Loma",
    "wof:placetype":"locality"
},
  "geometry": {"coordinates":[-99.48333,20.25],"type":"Point"}
}