{
  "type": "Feature",
  "properties": {
    "gn:admin1_code":"28.0",
    "gn:admin2_code":"12.0",
    "gn:asciiname":"Plan de Ayutla",
    "gn:country_code":"MX",
    "gn:dem":74,
    "gn:feature_class":"P",
    "gn:feature_code":"PPL",
    "gn:name":"Plan de Ayutla",
    "gn:population":0,
    "gn:timezone":"America/Monterrey",
    "iso:country":"MX",
    "name:spa_x_preferred":[
        "Plan de Ayutla"
    ],
    "wof:name":"Plan de Ayutla",
    "wof:placetype":"locality"
},
  "geometry": {"coordinates":[-98.858,22.87739],"type":"Point"}
}