{
  "type": "Feature",
  "properties": {
    "gn:admin1_code":"19.0",
    "gn:asciiname":"El Gringo",
    "gn:country_code":"MX",
    "gn:dem":340,
    "gn:feature_class":"P",
    "gn:feature_code":"PPL",
    "gn:name":"El Gringo",
    "gn:population":0,
    "gn:timezone":"America/Monterrey",
    "iso:country":"MX",
    "name:deu_x_preferred":[
        "El Gringo"
    ],
    "name:fas_x_preferred":[
        "\u0627\u0644 \u06af\u0631\u06cc\u0646\u06af\u0648"
    ],
    "name:rus_x_preferred":[
        "\u0413\u0440\u0438\u043d\u0433\u043e"
    ],
    "name:spa_x_preferred":[
        "El Gringo"
    ],
    "wof:name":"El Gringo",
    "wof:placetype":"locality"
},
  "geometry": {"coordinates":[-100.06218,25.81189],"type":"Point"}
}