{
  "type": "Feature",
  "properties": {
    "gn:admin1_code":"11",
    "gn:admin2_code":"3",
    "gn:asciiname":"Canada de San Jose",
    "gn:country_code":"MX",
    "gn:dem":2155,
    "gn:feature_class":"P",
    "gn:feature_code":"PPL",
    "gn:name":"Ca\u00f1ada de San Jos\u00e9",
    "gn:population":17,
    "gn:timezone":"America/Mexico_City",
    "iso:country":"MX",
    "name:und_x_variant":[
        "Ca\u00f1ada de San Jos\u00e9"
    ],
    "wof:name":"Canada de San Jose",
    "wof:placetype":"locality",
    "wof:population":17
},
  "geometry": {"coordinates":[-100.54861,20.99444],"type":"Point"}
}