{
  "type": "Feature",
  "properties": {
    "gn:admin1_code":"7.0",
    "gn:admin2_code":"23.0",
    "gn:asciiname":"Adan",
    "gn:country_code":"MX",
    "gn:dem":1115,
    "gn:feature_class":"P",
    "gn:feature_code":"PPL",
    "gn:name":"Ad\u00e1n",
    "gn:population":0,
    "gn:timezone":"America/Monterrey",
    "iso:country":"MX",
    "name:cat_x_preferred":[
        "Adan"
    ],
    "name:ceb_x_preferred":[
        "Adan"
    ],
    "name:deu_x_preferred":[
        "Adan"
    ],
    "name:heb_x_preferred":[
        "\u05d0\u05d3\u05df"
    ],
    "name:nld_x_preferred":[
        "Adan"
    ],
    "name:rus_x_preferred":[
        "\u0410\u0434\u0435\u043d"
    ],
    "name:spa_x_preferred":[
        "Ad\u00e1n"
    ],
    "name:swe_x_preferred":[
        "Adan"
    ],
    "name:tur_x_preferred":[
        "Adan"
    ],
    "name:uzb_x_preferred":[
        "Adan"
    ],
    "wof:name":"Adan",
    "wof:placetype":"locality"
},
  "geometry": {"coordinates":[-102.31138,27.42429000000001],"type":"Point"}
}