{
  "type": "Feature",
  "properties": {
    "gn:admin1_code":"30.0",
    "gn:admin2_code":"155.0",
    "gn:asciiname":"San Ventura",
    "gn:country_code":"MX",
    "gn:dem":72,
    "gn:feature_class":"P",
    "gn:feature_code":"PPL",
    "gn:name":"San Ventura",
    "gn:population":5,
    "gn:timezone":"America/Mexico_City",
    "iso:country":"MX",
    "name:spa_x_preferred":[
        "San Ventura"
    ],
    "wof:name":"San Ventura",
    "wof:placetype":"locality",
    "wof:population":5
},
  "geometry": {"coordinates":[-98.02916999999999,21.58972],"type":"Point"}
}