{
  "type": "Feature",
  "properties": {
    "gn:admin1_code":"5.0",
    "gn:asciiname":"Saltillo",
    "gn:country_code":"MX",
    "gn:dem":735,
    "gn:feature_class":"P",
    "gn:feature_code":"PPL",
    "gn:name":"Saltillo",
    "gn:population":0,
    "gn:timezone":"America/Mexico_City",
    "iso:country":"MX",
    "name:spa_x_preferred":[
        "Saltillo"
    ],
    "wof:name":"Saltillo",
    "wof:placetype":"locality"
},
  "geometry": {"coordinates":[-92.96077,15.87959],"type":"Point"}
}