{
  "type": "Feature",
  "properties": {
    "gn:admin1_code":"11.0",
    "gn:asciiname":"La Martena",
    "gn:country_code":"MX",
    "gn:dem":2039,
    "gn:feature_class":"P",
    "gn:feature_code":"PPL",
    "gn:name":"La Marte\u00f1a",
    "gn:population":0,
    "gn:timezone":"America/Mexico_City",
    "iso:country":"MX",
    "name:spa_x_preferred":[
        "La Marte\u00f1a"
    ],
    "wof:name":"La Martena",
    "wof:placetype":"locality"
},
  "geometry": {"coordinates":[-100.67411,20.90909],"type":"Point"}
}