{
  "type": "Feature",
  "properties": {
    "gn:admin1_code":"31",
    "gn:admin2_code":"79.0",
    "gn:asciiname":"Ticum",
    "gn:country_code":"MX",
    "gn:dem":40,
    "gn:feature_class":"P",
    "gn:feature_code":"PPL",
    "gn:name":"Ticum",
    "gn:population":922,
    "gn:timezone":"America/Merida",
    "iso:country":"MX",
    "wof:name":"Ticum",
    "wof:placetype":"locality",
    "wof:population":922
},
  "geometry": {"coordinates":[-89.21666999999999,20.14861],"type":"Point"}
}