{
  "type": "Feature",
  "properties": {
    "gn:admin1_code":"26",
    "gn:admin2_code":"30.0",
    "gn:asciiname":"Santa Cecilia (Licona)",
    "gn:country_code":"MX",
    "gn:dem":181,
    "gn:feature_class":"P",
    "gn:feature_code":"PPL",
    "gn:name":"Santa Cecilia (Licona)",
    "gn:population":9,
    "gn:timezone":"America/Hermosillo",
    "iso:country":"MX",
    "wof:name":"Santa Cecilia (Licona)",
    "wof:placetype":"locality",
    "wof:population":9
},
  "geometry": {"coordinates":[-111.04222,29.0625],"type":"Point"}
}