{
  "type": "Feature",
  "properties": {
    "gn:admin1_code":"26",
    "gn:admin2_code":"18.0",
    "gn:asciiname":"Ramon Rocha (Las Palapas)",
    "gn:country_code":"MX",
    "gn:dem":26,
    "gn:feature_class":"P",
    "gn:feature_code":"PPL",
    "gn:name":"Ram\u00f3n Rocha (Las Palapas)",
    "gn:population":9,
    "gn:timezone":"America/Hermosillo",
    "iso:country":"MX",
    "name:und_x_variant":[
        "Ram\u00f3n Rocha (Las Palapas)"
    ],
    "wof:name":"Ramon Rocha (Las Palapas)",
    "wof:placetype":"locality",
    "wof:population":9
},
  "geometry": {"coordinates":[-110.05110999999999,27.51889000000001],"type":"Point"}
}