{
  "type": "Feature",
  "properties": {
    "gn:admin1_code":"26.0",
    "gn:admin2_code":"26.0",
    "gn:asciiname":"La Ladrillera",
    "gn:country_code":"MX",
    "gn:dem":15,
    "gn:feature_class":"P",
    "gn:feature_code":"PPL",
    "gn:name":"La Ladrillera",
    "gn:population":0,
    "gn:timezone":"America/Hermosillo",
    "iso:country":"MX",
    "name:spa_x_preferred":[
        "La Ladrillera"
    ],
    "wof:name":"La Ladrillera",
    "wof:placetype":"locality"
},
  "geometry": {"coordinates":[-109.61405000000001,26.91702],"type":"Point"}
}