{
  "type": "Feature",
  "properties": {
    "gn:admin1_code":"30",
    "gn:admin2_code":"125.0",
    "gn:asciiname":"Mata del Gallo",
    "gn:country_code":"MX",
    "gn:dem":453,
    "gn:feature_class":"P",
    "gn:feature_code":"PPL",
    "gn:name":"Mata del Gallo",
    "gn:population":171,
    "gn:timezone":"America/Mexico_City",
    "iso:country":"MX",
    "wof:name":"Mata del Gallo",
    "wof:placetype":"locality",
    "wof:population":171
},
  "geometry": {"coordinates":[-96.71389000000001,18.95028],"type":"Point"}
}