{
  "type": "Feature",
  "properties": {
    "gn:admin1_code":"12",
    "gn:admin2_code":"73",
    "gn:asciiname":"El Recodo",
    "gn:country_code":"MX",
    "gn:dem":209,
    "gn:feature_class":"P",
    "gn:feature_code":"PPL",
    "gn:name":"El Recodo",
    "gn:population":11,
    "gn:timezone":"America/Mexico_City",
    "iso:country":"MX",
    "wof:name":"El Recodo",
    "wof:placetype":"locality",
    "wof:population":11
},
  "geometry": {"coordinates":[-101.01088,18.52186],"type":"Point"}
}