{
  "type": "Feature",
  "properties": {
    "gn:admin1_code":"15.0",
    "gn:admin2_code":"123.0",
    "gn:asciiname":"Rancho Viejo",
    "gn:country_code":"MX",
    "gn:dem":1145,
    "gn:feature_class":"P",
    "gn:feature_code":"PPL",
    "gn:name":"Rancho Viejo",
    "gn:population":407,
    "gn:timezone":"America/Mexico_City",
    "iso:country":"MX",
    "name:ceb_x_preferred":[
        "Rancho Viejo"
    ],
    "name:deu_x_preferred":[
        "Rancho Viejo"
    ],
    "name:ita_x_preferred":[
        "Rancho Viejo"
    ],
    "name:spa_x_preferred":[
        "Rancho Viejo"
    ],
    "name:srp_x_preferred":[
        "\u0420\u0430\u043d\u0447\u043e \u0412\u0438\u0458\u0435\u0445\u043e"
    ],
    "name:swe_x_preferred":[
        "Rancho Viejo"
    ],
    "wof:name":"Rancho Viejo",
    "wof:placetype":"locality",
    "wof:population":407
},
  "geometry": {"coordinates":[-100.33938999999999,19.04152],"type":"Point"}
}