{
  "type": "Feature",
  "properties": {
    "gn:admin1_code":"26",
    "gn:admin2_code":"24.0",
    "gn:asciiname":"La Polvareda",
    "gn:country_code":"MX",
    "gn:dem":816,
    "gn:feature_class":"P",
    "gn:feature_code":"PPL",
    "gn:name":"La Polvareda",
    "gn:population":0,
    "gn:timezone":"America/Hermosillo",
    "iso:country":"MX",
    "name:spa_x_preferred":[
        "La Polvareda"
    ],
    "wof:name":"La Polvareda",
    "wof:placetype":"locality"
},
  "geometry": {"coordinates":[-109.41231000000001,29.61502],"type":"Point"}
}