{
  "type": "Feature",
  "properties": {
    "gn:admin1_code":"16",
    "gn:admin2_code":"97",
    "gn:asciiname":"El Yarin",
    "gn:country_code":"MX",
    "gn:dem":1555,
    "gn:feature_class":"P",
    "gn:feature_code":"PPL",
    "gn:name":"El Yar\u00edn",
    "gn:population":15,
    "gn:timezone":"America/Mexico_City",
    "iso:country":"MX",
    "name:und_x_variant":[
        "El Yar\u00edn"
    ],
    "wof:name":"El Yarin",
    "wof:placetype":"locality",
    "wof:population":15
},
  "geometry": {"coordinates":[-101.54944,19.12722],"type":"Point"}
}