{
  "type": "Feature",
  "properties": {
    "gn:admin1_code":"7",
    "gn:admin2_code":"38.0",
    "gn:asciiname":"Reynaldo Salinas Vara",
    "gn:country_code":"MX",
    "gn:dem":362,
    "gn:feature_class":"P",
    "gn:feature_code":"PPL",
    "gn:name":"Reynaldo Salinas Vara",
    "gn:population":4,
    "gn:timezone":"America/Monterrey",
    "iso:country":"MX",
    "wof:name":"Reynaldo Salinas Vara",
    "wof:placetype":"locality",
    "wof:population":4
},
  "geometry": {"coordinates":[-100.92870000000001,28.49802],"type":"Point"}
}