{
  "type": "Feature",
  "properties": {
    "gn:admin1_code":"26",
    "gn:admin2_code":"51.0",
    "gn:asciiname":"El Enredo",
    "gn:country_code":"MX",
    "gn:dem":648,
    "gn:feature_class":"P",
    "gn:feature_code":"PPL",
    "gn:name":"El Enredo",
    "gn:population":0,
    "gn:timezone":"America/Hermosillo",
    "iso:country":"MX",
    "name:spa_x_preferred":[
        "El Enredo"
    ],
    "wof:name":"El Enredo",
    "wof:placetype":"locality"
},
  "geometry": {"coordinates":[-109.21577000000001,28.12295],"type":"Point"}
}