{
  "type": "Feature",
  "properties": {
    "gn:admin1_code":"23.0",
    "gn:admin2_code":"2.0",
    "gn:asciiname":"Las Sardinas",
    "gn:country_code":"MX",
    "gn:dem":4,
    "gn:feature_class":"P",
    "gn:feature_code":"PPL",
    "gn:name":"Las Sardinas",
    "gn:population":0,
    "gn:timezone":"America/Cancun",
    "iso:country":"MX",
    "name:spa_x_preferred":[
        "Las Sardinas"
    ],
    "wof:name":"Las Sardinas",
    "wof:placetype":"locality"
},
  "geometry": {"coordinates":[-87.46156999999999,19.29503],"type":"Point"}
}