{
  "type": "Feature",
  "properties": {
    "gn:admin1_code":"28.0",
    "gn:admin2_code":"3.0",
    "gn:asciiname":"El Establo",
    "gn:country_code":"MX",
    "gn:dem":37,
    "gn:feature_class":"P",
    "gn:feature_code":"PPL",
    "gn:name":"El Establo",
    "gn:population":0,
    "gn:timezone":"America/Monterrey",
    "iso:country":"MX",
    "name:spa_x_preferred":[
        "El Establo"
    ],
    "wof:name":"El Establo",
    "wof:placetype":"locality"
},
  "geometry": {"coordinates":[-98.19541,22.62634],"type":"Point"}
}