{
  "type": "Feature",
  "properties": {
    "gn:admin1_code":"20",
    "gn:admin2_code":"318",
    "gn:asciiname":"La Yerba Santa",
    "gn:country_code":"MX",
    "gn:dem":108,
    "gn:feature_class":"P",
    "gn:feature_code":"PPL",
    "gn:name":"La Yerba Santa",
    "gn:population":34,
    "gn:timezone":"America/Mexico_City",
    "iso:country":"MX",
    "wof:name":"La Yerba Santa",
    "wof:placetype":"locality",
    "wof:population":34
},
  "geometry": {"coordinates":[-97.07333,15.94194],"type":"Point"}
}