{
  "type": "Feature",
  "properties": {
    "gn:admin1_code":"30",
    "gn:admin2_code":"184.0",
    "gn:asciiname":"Tlaltenango",
    "gn:country_code":"MX",
    "gn:dem":2402,
    "gn:feature_class":"P",
    "gn:feature_code":"PPL",
    "gn:name":"Tlaltenango",
    "gn:population":174,
    "gn:timezone":"America/Mexico_City",
    "iso:country":"MX",
    "wof:name":"Tlaltenango",
    "wof:placetype":"locality",
    "wof:population":174
},
  "geometry": {"coordinates":[-97.11360999999999,18.62333],"type":"Point"}
}