{
  "type": "Feature",
  "properties": {
    "gn:admin1_code":"32.0",
    "gn:admin2_code":"49.0",
    "gn:asciiname":"Los Yugos",
    "gn:country_code":"MX",
    "gn:dem":2647,
    "gn:feature_class":"P",
    "gn:feature_code":"PPL",
    "gn:name":"Los Yugos",
    "gn:population":0,
    "gn:timezone":"America/Mexico_City",
    "iso:country":"MX",
    "name:spa_x_preferred":[
        "Los Yugos"
    ],
    "wof:name":"Los Yugos",
    "wof:placetype":"locality"
},
  "geometry": {"coordinates":[-103.23828,22.70957000000001],"type":"Point"}
}