{
  "type": "Feature",
  "properties": {
    "gn:admin1_code":"2.0",
    "gn:admin2_code":"2.0",
    "gn:asciiname":"Colonia del Bosque",
    "gn:country_code":"MX",
    "gn:dem":12,
    "gn:feature_class":"P",
    "gn:feature_code":"PPL",
    "gn:name":"Colonia del Bosque",
    "gn:population":142,
    "gn:timezone":"America/Tijuana",
    "iso:country":"MX",
    "name:spa_x_preferred":[
        "Colonias Nuevas"
    ],
    "wof:name":"Colonia del Bosque",
    "wof:placetype":"locality",
    "wof:population":142
},
  "geometry": {"coordinates":[-115.00749999999999,32.1875],"type":"Point"}
}