{
  "type": "Feature",
  "properties": {
    "gn:admin1_code":"22.0",
    "gn:asciiname":"Los Sanchez",
    "gn:country_code":"MX",
    "gn:dem":2032,
    "gn:feature_class":"P",
    "gn:feature_code":"PPL",
    "gn:name":"Los S\u00e1nchez",
    "gn:population":0,
    "gn:timezone":"America/Mexico_City",
    "iso:country":"MX",
    "name:spa_x_preferred":[
        "Los S\u00e1nchez"
    ],
    "wof:name":"Los Sanchez",
    "wof:placetype":"locality"
},
  "geometry": {"coordinates":[-99.70762000000001,20.69939],"type":"Point"}
}