{
  "type": "Feature",
  "properties": {
    "gn:admin1_code":"26",
    "gn:admin2_code":"3.0",
    "gn:asciiname":"El Cajon",
    "gn:country_code":"MX",
    "gn:dem":410,
    "gn:feature_class":"P",
    "gn:feature_code":"PPL",
    "gn:name":"El Caj\u00f3n",
    "gn:population":5,
    "gn:timezone":"America/Hermosillo",
    "iso:country":"MX",
    "name:und_x_variant":[
        "El Caj\u00f3n"
    ],
    "wof:name":"El Cajon",
    "wof:placetype":"locality",
    "wof:population":5
},
  "geometry": {"coordinates":[-108.73333,27.04028],"type":"Point"}
}