{
  "type": "Feature",
  "properties": {
    "gn:admin1_code":"5",
    "gn:admin2_code":"111.0",
    "gn:asciiname":"Apas",
    "gn:country_code":"MX",
    "gn:dem":2124,
    "gn:feature_class":"P",
    "gn:feature_code":"PPL",
    "gn:name":"Apas",
    "gn:population":1485,
    "gn:timezone":"America/Mexico_City",
    "iso:country":"MX",
    "wof:name":"Apas",
    "wof:placetype":"locality",
    "wof:population":1485
},
  "geometry": {"coordinates":[-92.79335,16.71066],"type":"Point"}
}