{
  "type": "Feature",
  "properties": {
    "gn:admin1_code":"18",
    "gn:admin2_code":"9.0",
    "gn:asciiname":"El Jazmin",
    "gn:country_code":"MX",
    "gn:dem":888,
    "gn:feature_class":"P",
    "gn:feature_code":"PPL",
    "gn:name":"El Jazmin",
    "gn:population":0,
    "gn:timezone":"America/Mazatlan",
    "iso:country":"MX",
    "name:spa_x_preferred":[
        "El Jazmin"
    ],
    "wof:name":"El Jazmin",
    "wof:placetype":"locality"
},
  "geometry": {"coordinates":[-104.54443000000001,22.32458],"type":"Point"}
}