{
  "type": "Feature",
  "properties": {
    "gn:admin1_code":"15",
    "gn:admin2_code":"85.0",
    "gn:asciiname":"Mesa de Bani",
    "gn:country_code":"MX",
    "gn:dem":2666,
    "gn:feature_class":"P",
    "gn:feature_code":"PPL",
    "gn:name":"Mesa de Ba\u00f1i",
    "gn:population":615,
    "gn:timezone":"America/Mexico_City",
    "iso:country":"MX",
    "name:und_x_variant":[
        "Mesa de Ba\u00f1i"
    ],
    "wof:name":"Mesa de Bani",
    "wof:placetype":"locality",
    "wof:population":615
},
  "geometry": {"coordinates":[-100.05316999999999,19.86881],"type":"Point"}
}