{
  "type": "Feature",
  "properties": {
    "gn:admin1_code":"14",
    "gn:admin2_code":"64.0",
    "gn:asciiname":"Salitrillo de Chinampas",
    "gn:country_code":"MX",
    "gn:dem":2161,
    "gn:feature_class":"P",
    "gn:feature_code":"PPL",
    "gn:name":"Salitrillo de Chinampas",
    "gn:population":0,
    "gn:timezone":"America/Mexico_City",
    "iso:country":"MX",
    "name:spa_x_preferred":[
        "Salitrillo de Chinampas"
    ],
    "name:und_x_variant":[
        "Salitrillo de Chinanpas"
    ],
    "wof:name":"Salitrillo de Chinampas",
    "wof:placetype":"locality"
},
  "geometry": {"coordinates":[-101.75552999999999,21.91472000000001],"type":"Point"}
}