{
  "type": "Feature",
  "properties": {
    "gn:admin1_code":"26",
    "gn:admin2_code":"33.0",
    "gn:asciiname":"La Arenita",
    "gn:country_code":"MX",
    "gn:dem":4,
    "gn:feature_class":"P",
    "gn:feature_code":"PPL",
    "gn:name":"La Arenita",
    "gn:population":164,
    "gn:timezone":"America/Hermosillo",
    "iso:country":"MX",
    "wof:name":"La Arenita",
    "wof:placetype":"locality",
    "wof:population":164
},
  "geometry": {"coordinates":[-109.77583,26.79722000000001],"type":"Point"}
}