{
  "type": "Feature",
  "properties": {
    "gn:admin1_code":"15.0",
    "gn:admin2_code":"78.0",
    "gn:asciiname":"San Pedro Ixtapantongo (Ixtapantongo)",
    "gn:country_code":"MX",
    "gn:dem":1336,
    "gn:feature_class":"P",
    "gn:feature_code":"PPL",
    "gn:name":"San Pedro Ixtapantongo (Ixtapantongo)",
    "gn:population":335,
    "gn:timezone":"America/Mexico_City",
    "iso:country":"MX",
    "wof:name":"San Pedro Ixtapantongo (Ixtapantongo)",
    "wof:placetype":"locality",
    "wof:population":335
},
  "geometry": {"coordinates":[-100.24472,19.17389],"type":"Point"}
}