{
  "type": "Feature",
  "properties": {
    "gn:admin1_code":"25",
    "gn:asciiname":"La Tuna",
    "gn:cc2":"MX",
    "gn:country_code":"MX",
    "gn:dem":550,
    "gn:feature_class":"P",
    "gn:feature_code":"PPL",
    "gn:name":"La Tuna",
    "gn:population":0,
    "gn:timezone":"America/Mazatlan",
    "iso:country":"MX",
    "name:und_x_variant":[
        "Tuna",
        "La Tuna"
    ],
    "wof:name":"La Tuna",
    "wof:placetype":"locality"
},
  "geometry": {"coordinates":[-105.21666999999999,22.96667],"type":"Point"}
}