{
  "type": "Feature",
  "properties": {
    "gn:admin1_code":"15.0",
    "gn:asciiname":"Aparicio",
    "gn:country_code":"MX",
    "gn:dem":3038,
    "gn:feature_class":"P",
    "gn:feature_code":"PPL",
    "gn:name":"Aparicio",
    "gn:population":0,
    "gn:timezone":"America/Mexico_City",
    "iso:country":"MX",
    "name:eus_x_preferred":[
        "Aparizio"
    ],
    "name:jpn_x_preferred":[
        "\u30a2\u30d1\u30ea\u30b7\u30aa"
    ],
    "name:spa_x_preferred":[
        "Aparicio"
    ],
    "wof:name":"Aparicio",
    "wof:placetype":"locality"
},
  "geometry": {"coordinates":[-100.18762,19.49229],"type":"Point"}
}