{
  "type": "Feature",
  "properties": {
    "gn:admin1_code":"5",
    "gn:admin2_code":"27.0",
    "gn:asciiname":"Santa Clara",
    "gn:country_code":"MX",
    "gn:dem":526,
    "gn:feature_class":"P",
    "gn:feature_code":"PPL",
    "gn:name":"Santa Clara",
    "gn:population":5,
    "gn:timezone":"America/Mexico_City",
    "iso:country":"MX",
    "wof:name":"Santa Clara",
    "wof:placetype":"locality",
    "wof:population":5
},
  "geometry": {"coordinates":[-92.97111,16.58861],"type":"Point"}
}