{
  "type": "Feature",
  "properties": {
    "gn:admin1_code":"6",
    "gn:admin2_code":"12.0",
    "gn:asciiname":"Nacaruri",
    "gn:country_code":"MX",
    "gn:dem":2050,
    "gn:feature_class":"P",
    "gn:feature_code":"PPL",
    "gn:name":"Nac\u00e1ruri",
    "gn:population":54,
    "gn:timezone":"America/Chihuahua",
    "iso:country":"MX",
    "name:und_x_variant":[
        "Nac\u00e1ruri"
    ],
    "wof:name":"Nacaruri",
    "wof:placetype":"locality",
    "wof:population":54
},
  "geometry": {"coordinates":[-106.94381,27.5184],"type":"Point"}
}