{
  "type": "Feature",
  "properties": {
    "gn:admin1_code":"29",
    "gn:admin2_code":"24.0",
    "gn:asciiname":"Apatlaco",
    "gn:country_code":"MX",
    "gn:dem":2560,
    "gn:feature_class":"P",
    "gn:feature_code":"PPL",
    "gn:name":"Apatlaco",
    "gn:population":0,
    "gn:timezone":"America/Mexico_City",
    "iso:country":"MX",
    "wof:name":"Apatlaco",
    "wof:placetype":"locality"
},
  "geometry": {"coordinates":[-98.29028,19.35278],"type":"Point"}
}