{
  "type": "Feature",
  "properties": {
    "gn:admin1_code":"28.0",
    "gn:admin2_code":"22.0",
    "gn:asciiname":"Los Dos Ebanos",
    "gn:country_code":"MX",
    "gn:dem":6,
    "gn:feature_class":"P",
    "gn:feature_code":"PPL",
    "gn:name":"Los Dos Ebanos",
    "gn:population":0,
    "gn:timezone":"America/Matamoros",
    "iso:country":"MX",
    "name:spa_x_preferred":[
        "Los Dos Ebanos"
    ],
    "wof:name":"Los Dos Ebanos",
    "wof:placetype":"locality"
},
  "geometry": {"coordinates":[-97.398,25.74513],"type":"Point"}
}