{
  "type": "Feature",
  "properties": {
    "gn:admin1_code":"10.0",
    "gn:admin2_code":"22.0",
    "gn:asciiname":"El Seco",
    "gn:country_code":"MX",
    "gn:dem":2091,
    "gn:feature_class":"P",
    "gn:feature_code":"PPL",
    "gn:name":"El Seco",
    "gn:population":0,
    "gn:timezone":"America/Monterrey",
    "iso:country":"MX",
    "name:spa_x_preferred":[
        "El Seco"
    ],
    "wof:name":"El Seco",
    "wof:placetype":"locality"
},
  "geometry": {"coordinates":[-104.03721,24.15282],"type":"Point"}
}