{
  "type": "Feature",
  "properties": {
    "gn:admin1_code":"26",
    "gn:admin2_code":"70",
    "gn:asciiname":"El Mirador [Cafe]",
    "gn:country_code":"MX",
    "gn:dem":533,
    "gn:feature_class":"P",
    "gn:feature_code":"PPL",
    "gn:name":"El Mirador [Caf\u00e9]",
    "gn:population":15,
    "gn:timezone":"America/Hermosillo",
    "iso:country":"MX",
    "name:und_x_variant":[
        "El Mirador [Caf\u00e9]"
    ],
    "wof:name":"El Mirador [Cafe]",
    "wof:placetype":"locality",
    "wof:population":15
},
  "geometry": {"coordinates":[-112.84472,31.69194],"type":"Point"}
}