{
  "type": "Feature",
  "properties": {
    "gn:admin1_code":"18.0",
    "gn:admin2_code":"19.0",
    "gn:asciiname":"Los Rosales",
    "gn:country_code":"MX",
    "gn:dem":651,
    "gn:feature_class":"P",
    "gn:feature_code":"PPL",
    "gn:name":"Los Rosales",
    "gn:population":0,
    "gn:timezone":"America/Mazatlan",
    "iso:country":"MX",
    "name:ceb_x_preferred":[
        "Los Rosales"
    ],
    "name:spa_x_preferred":[
        "Los Rosales"
    ],
    "name:spa_x_variant":[
        "Rosales"
    ],
    "name:srp_x_preferred":[
        "\u041b\u043e\u0441 \u0420\u043e\u0441\u0430\u043b\u0435\u0441"
    ],
    "name:swe_x_preferred":[
        "Los Rosales"
    ],
    "wof:name":"Los Rosales",
    "wof:placetype":"locality"
},
  "geometry": {"coordinates":[-104.35505000000001,21.51356],"type":"Point"}
}