{
  "type": "Feature",
  "properties": {
    "gn:admin1_code":"7.0",
    "gn:admin2_code":"20.0",
    "gn:asciiname":"Calvillo",
    "gn:country_code":"MX",
    "gn:dem":548,
    "gn:feature_class":"P",
    "gn:feature_code":"PPL",
    "gn:name":"Calvillo",
    "gn:population":0,
    "gn:timezone":"America/Monterrey",
    "iso:country":"MX",
    "name:bul_x_preferred":[
        "\u041a\u0430\u043b\u0432\u0438\u043b\u044c\u043e"
    ],
    "name:ind_x_preferred":[
        "Calvillo"
    ],
    "name:ita_x_preferred":[
        "Calvillo"
    ],
    "name:jpn_x_preferred":[
        "\u30ab\u30eb\u30d3\u30fc\u30b8\u30e7"
    ],
    "name:kor_x_preferred":[
        "\uce7c\ube44\uc694"
    ],
    "name:lad_x_preferred":[
        "Calvillo"
    ],
    "name:nld_x_preferred":[
        "Calvillo"
    ],
    "name:pol_x_preferred":[
        "Calvillo"
    ],
    "name:rus_x_preferred":[
        "\u041a\u0430\u043b\u044c\u0432\u0438\u043b\u044c\u043e"
    ],
    "name:sco_x_preferred":[
        "Calvillo"
    ],
    "name:spa_x_preferred":[
        "Calvillo"
    ],
    "name:srp_x_preferred":[
        "\u041a\u0430\u043b\u0432\u0438\u0459\u043e"
    ],
    "name:zho_x_preferred":[
        "\u5361\u7ef4\u6d1b"
    ],
    "wof:name":"Calvillo",
    "wof:placetype":"locality"
},
  "geometry": {"coordinates":[-101.71722,27.89937],"type":"Point"}
}