{
  "type": "Feature",
  "properties": {
    "gn:admin1_code":"7.0",
    "gn:admin2_code":"20.0",
    "gn:asciiname":"Calvillo",
    "gn:country_code":"MX",
    "gn:dem":548,
    "gn:feature_class":"P",
    "gn:feature_code":"PPL",
    "gn:name":"Calvillo",
    "gn:population":0,
    "gn:timezone":"America/Monterrey",
    "iso:country":"MX",
    "name:spa_x_preferred":[
        "Calvillo"
    ],
    "wof:name":"Calvillo",
    "wof:placetype":"locality"
},
  "geometry": {"coordinates":[-101.71722,27.89937],"type":"Point"}
}