{
  "type": "Feature",
  "properties": {
    "gn:admin1_code":"20",
    "gn:admin2_code":"424.0",
    "gn:asciiname":"Rio Grande",
    "gn:country_code":"MX",
    "gn:dem":2885,
    "gn:feature_class":"P",
    "gn:feature_code":"PPL",
    "gn:name":"R\u00edo Grande",
    "gn:population":6,
    "gn:timezone":"America/Mexico_City",
    "iso:country":"MX",
    "name:und_x_variant":[
        "R\u00edo Grande"
    ],
    "wof:name":"Rio Grande",
    "wof:placetype":"locality",
    "wof:population":6
},
  "geometry": {"coordinates":[-96.37306,16.16111],"type":"Point"}
}