{
  "type": "Feature",
  "properties": {
    "gn:admin1_code":"28",
    "gn:admin2_code":"34.0",
    "gn:asciiname":"El Estanque",
    "gn:country_code":"MX",
    "gn:dem":312,
    "gn:feature_class":"P",
    "gn:feature_code":"PPL",
    "gn:name":"El Estanque",
    "gn:population":0,
    "gn:timezone":"America/Monterrey",
    "iso:country":"MX",
    "name:spa_x_preferred":[
        "El Estanque"
    ],
    "name:und_x_variant":[
        "El Tanque"
    ],
    "wof:name":"El Estanque",
    "wof:placetype":"locality"
},
  "geometry": {"coordinates":[-98.79098999999999,24.357],"type":"Point"}
}