{
  "type": "Feature",
  "properties": {
    "gn:admin1_code":"3",
    "gn:admin2_code":"8.0",
    "gn:asciiname":"El Machete",
    "gn:country_code":"MX",
    "gn:dem":159,
    "gn:feature_class":"P",
    "gn:feature_code":"PPL",
    "gn:name":"El Machete",
    "gn:population":4,
    "gn:timezone":"America/Mazatlan",
    "iso:country":"MX",
    "wof:name":"El Machete",
    "wof:placetype":"locality",
    "wof:population":4
},
  "geometry": {"coordinates":[-109.64225,23.46235],"type":"Point"}
}