{
  "type": "Feature",
  "properties": {
    "gn:admin1_code":"26.0",
    "gn:admin2_code":"62.0",
    "gn:asciiname":"El Garambullo",
    "gn:country_code":"MX",
    "gn:dem":330,
    "gn:feature_class":"P",
    "gn:feature_code":"PPL",
    "gn:name":"El Garambullo",
    "gn:population":0,
    "gn:timezone":"America/Hermosillo",
    "iso:country":"MX",
    "name:spa_x_preferred":[
        "El Garambullo"
    ],
    "wof:name":"El Garambullo",
    "wof:placetype":"locality"
},
  "geometry": {"coordinates":[-109.80691000000002,28.48494],"type":"Point"}
}