{
  "type": "Feature",
  "properties": {
    "gn:admin1_code":"6.0",
    "gn:admin2_code":"19.0",
    "gn:asciiname":"Canada",
    "gn:cc2":"MX",
    "gn:country_code":"MX",
    "gn:dem":1612,
    "gn:feature_class":"P",
    "gn:feature_code":"PPL",
    "gn:name":"Ca\u00f1ada",
    "gn:population":0,
    "gn:timezone":"America/Chihuahua",
    "iso:country":"MX",
    "name:und_x_variant":[
        "La Ca\u00f1ada",
        "Ca\u00f1ada"
    ],
    "wof:name":"Canada",
    "wof:placetype":"locality"
},
  "geometry": {"coordinates":[-106.08333,28.55],"type":"Point"}
}