{
  "type": "Feature",
  "properties": {
    "gn:admin1_code":"12",
    "gn:admin2_code":"56.0",
    "gn:asciiname":"El Tejolote",
    "gn:country_code":"MX",
    "gn:dem":231,
    "gn:feature_class":"P",
    "gn:feature_code":"PPL",
    "gn:name":"El Tejolote",
    "gn:population":114,
    "gn:timezone":"America/Mexico_City",
    "iso:country":"MX",
    "wof:name":"El Tejolote",
    "wof:placetype":"locality",
    "wof:population":114
},
  "geometry": {"coordinates":[-99.20447,16.90359],"type":"Point"}
}