{
  "type": "Feature",
  "properties": {
    "gn:admin1_code":"24",
    "gn:admin2_code":"24.0",
    "gn:asciiname":"Yerbabuena",
    "gn:country_code":"MX",
    "gn:dem":1153,
    "gn:feature_class":"P",
    "gn:feature_code":"PPL",
    "gn:name":"Yerbabuena",
    "gn:population":0,
    "gn:timezone":"America/Mexico_City",
    "iso:country":"MX",
    "wof:name":"Yerbabuena",
    "wof:placetype":"locality"
},
  "geometry": {"coordinates":[-100.11667,21.68333],"type":"Point"}
}