{
  "type": "Feature",
  "properties": {
    "gn:admin1_code":"5",
    "gn:admin2_code":"30.0",
    "gn:asciiname":"El Brasilito",
    "gn:country_code":"MX",
    "gn:dem":589,
    "gn:feature_class":"P",
    "gn:feature_code":"PPL",
    "gn:name":"El Brasilito",
    "gn:population":75,
    "gn:timezone":"America/Mexico_City",
    "iso:country":"MX",
    "wof:name":"El Brasilito",
    "wof:placetype":"locality",
    "wof:population":75
},
  "geometry": {"coordinates":[-92.30556,15.7475],"type":"Point"}
}