{
  "type": "Feature",
  "properties": {
    "gn:admin1_code":"11",
    "gn:admin2_code":"6.0",
    "gn:asciiname":"El Pinonal",
    "gn:country_code":"MX",
    "gn:dem":1754,
    "gn:feature_class":"P",
    "gn:feature_code":"PPL",
    "gn:name":"El Pi\u00f1onal",
    "gn:population":84,
    "gn:timezone":"America/Mexico_City",
    "iso:country":"MX",
    "name:und_x_variant":[
        "El Pi\u00f1onal"
    ],
    "wof:name":"El Pinonal",
    "wof:placetype":"locality",
    "wof:population":84
},
  "geometry": {"coordinates":[-99.83833,21.28667],"type":"Point"}
}