{
  "type": "Feature",
  "properties": {
    "gn:admin1_code":"3",
    "gn:admin2_code":"1",
    "gn:asciiname":"El Tequezquite",
    "gn:country_code":"MX",
    "gn:dem":151,
    "gn:feature_class":"P",
    "gn:feature_code":"PPL",
    "gn:name":"El Tequezquite",
    "gn:population":15,
    "gn:timezone":"America/Mazatlan",
    "iso:country":"MX",
    "wof:name":"El Tequezquite",
    "wof:placetype":"locality",
    "wof:population":15
},
  "geometry": {"coordinates":[-111.36083000000001,25.20905],"type":"Point"}
}