{
  "type": "Feature",
  "properties": {
    "gn:admin1_code":"24",
    "gn:admin2_code":"12.0",
    "gn:asciiname":"Chuche-Mom",
    "gn:country_code":"MX",
    "gn:dem":392,
    "gn:feature_class":"P",
    "gn:feature_code":"PPL",
    "gn:name":"Chuche-Mom",
    "gn:population":0,
    "gn:timezone":"America/Mexico_City",
    "iso:country":"MX",
    "name:spa_x_preferred":[
        "Chuche-Mom"
    ],
    "wof:name":"Chuche-Mom",
    "wof:placetype":"locality"
},
  "geometry": {"coordinates":[-98.94335,21.60935],"type":"Point"}
}