{
  "type": "Feature",
  "properties": {
    "gn:admin1_code":"20",
    "gn:admin2_code":"276",
    "gn:asciiname":"Pena Colorada",
    "gn:country_code":"MX",
    "gn:dem":1810,
    "gn:feature_class":"P",
    "gn:feature_code":"PPL",
    "gn:name":"Pe\u00f1a Colorada",
    "gn:population":20,
    "gn:timezone":"America/Mexico_City",
    "iso:country":"MX",
    "name:und_x_variant":[
        "Pe\u00f1a Colorada"
    ],
    "wof:name":"Pena Colorada",
    "wof:placetype":"locality",
    "wof:population":20
},
  "geometry": {"coordinates":[-96.79861,17.93222],"type":"Point"}
}