{
  "type": "Feature",
  "properties": {
    "gn:admin1_code":"6",
    "gn:admin2_code":"29.0",
    "gn:asciiname":"El Palacio",
    "gn:country_code":"MX",
    "gn:dem":2580,
    "gn:feature_class":"P",
    "gn:feature_code":"PPL",
    "gn:name":"El Palacio",
    "gn:population":4,
    "gn:timezone":"America/Chihuahua",
    "iso:country":"MX",
    "wof:name":"El Palacio",
    "wof:placetype":"locality",
    "wof:population":4
},
  "geometry": {"coordinates":[-106.69429,25.90385],"type":"Point"}
}