{
  "type": "Feature",
  "properties": {
    "gn:admin1_code":"14",
    "gn:admin2_code":"61",
    "gn:asciiname":"El Roble (El Roblito)",
    "gn:country_code":"MX",
    "gn:dem":1719,
    "gn:feature_class":"P",
    "gn:feature_code":"PPL",
    "gn:name":"El Roble (El Roblito)",
    "gn:population":31,
    "gn:timezone":"America/Mexico_City",
    "iso:country":"MX",
    "wof:name":"El Roble (El Roblito)",
    "wof:placetype":"locality",
    "wof:population":31
},
  "geometry": {"coordinates":[-104.32944000000001,22.17028],"type":"Point"}
}