{
  "type": "Feature",
  "properties": {
    "gn:admin1_code":"24",
    "gn:admin2_code":"13",
    "gn:asciiname":"Palmillas",
    "gn:country_code":"MX",
    "gn:dem":104,
    "gn:feature_class":"P",
    "gn:feature_code":"PPL",
    "gn:name":"Palmillas",
    "gn:population":36,
    "gn:timezone":"America/Mexico_City",
    "iso:country":"MX",
    "name:srp_x_preferred":[
        "\u041f\u0430\u043b\u043c\u0438\u0459\u0430\u0441"
    ],
    "wof:name":"Palmillas",
    "wof:placetype":"locality",
    "wof:population":36
},
  "geometry": {"coordinates":[-99.10861,22.01667],"type":"Point"}
}