{
  "type": "Feature",
  "properties": {
    "gn:admin1_code":"11.0",
    "gn:admin2_code":"37.0",
    "gn:asciiname":"Trojes",
    "gn:country_code":"MX",
    "gn:dem":1747,
    "gn:feature_class":"P",
    "gn:feature_code":"PPL",
    "gn:name":"Trojes",
    "gn:population":0,
    "gn:timezone":"America/Mexico_City",
    "iso:country":"MX",
    "name:ceb_x_preferred":[
        "Trojes"
    ],
    "name:fra_x_preferred":[
        "Trojes"
    ],
    "name:ita_x_preferred":[
        "Trojes"
    ],
    "name:nld_x_preferred":[
        "Trojes"
    ],
    "name:pol_x_preferred":[
        "Trojes"
    ],
    "name:por_x_preferred":[
        "Trojes"
    ],
    "name:spa_x_preferred":[
        "Trojes"
    ],
    "name:swe_x_preferred":[
        "Trojes"
    ],
    "name:und_x_variant":[
        "Las Trojes"
    ],
    "name:zho_x_preferred":[
        "\u7279\u7f85\u8d6b\u65af"
    ],
    "wof:name":"Trojes",
    "wof:placetype":"locality"
},
  "geometry": {"coordinates":[-101.44224,20.84021],"type":"Point"}
}