{
  "type": "Feature",
  "properties": {
    "gn:admin1_code":"5",
    "gn:admin2_code":"77",
    "gn:asciiname":"Las Pampas",
    "gn:country_code":"MX",
    "gn:dem":70,
    "gn:feature_class":"P",
    "gn:feature_code":"PPL",
    "gn:name":"Las Pampas",
    "gn:population":11,
    "gn:timezone":"America/Mexico_City",
    "iso:country":"MX",
    "wof:name":"Las Pampas",
    "wof:placetype":"locality",
    "wof:population":11
},
  "geometry": {"coordinates":[-92.25472000000001,17.40028],"type":"Point"}
}