{
  "type": "Feature",
  "properties": {
    "gn:admin1_code":"30",
    "gn:admin2_code":"128.0",
    "gn:asciiname":"Colonia Veinte de Noviembre",
    "gn:country_code":"MX",
    "gn:dem":2505,
    "gn:feature_class":"P",
    "gn:feature_code":"PPL",
    "gn:name":"Colonia Veinte de Noviembre",
    "gn:population":0,
    "gn:timezone":"America/Mexico_City",
    "iso:country":"MX",
    "name:spa_x_preferred":[
        "Colonia Veinte de Noviembre"
    ],
    "name:und_x_variant":[
        "Veinte de Noviembre"
    ],
    "wof:name":"Colonia Veinte de Noviembre",
    "wof:placetype":"locality"
},
  "geometry": {"coordinates":[-97.17337000000001,19.61718],"type":"Point"}
}