{
  "type": "Feature",
  "properties": {
    "gn:admin1_code":"10.0",
    "gn:asciiname":"Castellana",
    "gn:country_code":"MX",
    "gn:dem":732,
    "gn:feature_class":"P",
    "gn:feature_code":"PPL",
    "gn:name":"Castellana",
    "gn:population":0,
    "gn:timezone":"America/Mazatlan",
    "iso:country":"MX",
    "name:spa_x_preferred":[
        "Castellana"
    ],
    "wof:name":"Castellana",
    "wof:placetype":"locality"
},
  "geometry": {"coordinates":[-105.96601,24.12073],"type":"Point"}
}