{
  "type": "Feature",
  "properties": {
    "gn:admin1_code":"25",
    "gn:admin2_code":"6.0",
    "gn:asciiname":"Punta del Cerro",
    "gn:country_code":"MX",
    "gn:dem":52,
    "gn:feature_class":"P",
    "gn:feature_code":"PPL",
    "gn:name":"Punta del Cerro",
    "gn:population":0,
    "gn:timezone":"America/Mazatlan",
    "iso:country":"MX",
    "name:spa_x_preferred":[
        "Punta del Cerro"
    ],
    "wof:name":"Punta del Cerro",
    "wof:placetype":"locality"
},
  "geometry": {"coordinates":[-107.01734,24.17313],"type":"Point"}
}