{
  "type": "Feature",
  "properties": {
    "gn:admin1_code":"5",
    "gn:admin2_code":"34.0",
    "gn:asciiname":"La Sabinada",
    "gn:country_code":"MX",
    "gn:dem":655,
    "gn:feature_class":"P",
    "gn:feature_code":"PPL",
    "gn:name":"La Sabinada",
    "gn:population":534,
    "gn:timezone":"America/Mexico_City",
    "iso:country":"MX",
    "wof:name":"La Sabinada",
    "wof:placetype":"locality",
    "wof:population":534
},
  "geometry": {"coordinates":[-92.15278000000001,15.69194],"type":"Point"}
}