{
  "type": "Feature",
  "properties": {
    "gn:admin1_code":"2.0",
    "gn:admin2_code":"1.0",
    "gn:asciiname":"La Nopalera",
    "gn:country_code":"MX",
    "gn:dem":84,
    "gn:feature_class":"P",
    "gn:feature_code":"PPL",
    "gn:name":"La Nopalera",
    "gn:population":7,
    "gn:timezone":"America/Tijuana",
    "iso:country":"MX",
    "name:spa_x_preferred":[
        "La Nopalera"
    ],
    "wof:name":"La Nopalera",
    "wof:placetype":"locality",
    "wof:population":7
},
  "geometry": {"coordinates":[-116.25749,31.32942],"type":"Point"}
}