{
  "type": "Feature",
  "properties": {
    "gn:admin1_code":"3",
    "gn:admin2_code":"2.0",
    "gn:asciiname":"La Huertita",
    "gn:country_code":"MX",
    "gn:dem":286,
    "gn:feature_class":"P",
    "gn:feature_code":"PPL",
    "gn:name":"La Huertita",
    "gn:population":7,
    "gn:timezone":"America/Mazatlan",
    "iso:country":"MX",
    "wof:name":"La Huertita",
    "wof:placetype":"locality",
    "wof:population":7
},
  "geometry": {"coordinates":[-112.75454999999999,26.87202000000001],"type":"Point"}
}