{
  "type": "Feature",
  "properties": {
    "gn:admin1_code":"32.0",
    "gn:admin2_code":"21.0",
    "gn:asciiname":"El Banco de Oro",
    "gn:country_code":"MX",
    "gn:dem":2001,
    "gn:feature_class":"P",
    "gn:feature_code":"PPL",
    "gn:name":"El Banco de Oro",
    "gn:population":0,
    "gn:timezone":"America/Mexico_City",
    "iso:country":"MX",
    "name:spa_x_preferred":[
        "El Banco de Oro"
    ],
    "wof:name":"El Banco de Oro",
    "wof:placetype":"locality"
},
  "geometry": {"coordinates":[-103.82456000000001,23.21791],"type":"Point"}
}