{
  "type": "Feature",
  "properties": {
    "gn:admin1_code":"26.0",
    "gn:asciiname":"El Desierto",
    "gn:country_code":"MX",
    "gn:dem":590,
    "gn:feature_class":"P",
    "gn:feature_code":"PPL",
    "gn:name":"El Desierto",
    "gn:population":0,
    "gn:timezone":"America/Hermosillo",
    "iso:country":"MX",
    "name:spa_x_preferred":[
        "El Desierto"
    ],
    "wof:name":"El Desierto",
    "wof:placetype":"locality"
},
  "geometry": {"coordinates":[-109.22906999999999,27.87323],"type":"Point"}
}