{
  "type": "Feature",
  "properties": {
    "gn:admin1_code":"11",
    "gn:admin2_code":"37.0",
    "gn:asciiname":"La Virgen",
    "gn:country_code":"MX",
    "gn:dem":1798,
    "gn:feature_class":"P",
    "gn:feature_code":"PPL",
    "gn:name":"La Virgen",
    "gn:population":133,
    "gn:timezone":"America/Mexico_City",
    "iso:country":"MX",
    "wof:name":"La Virgen",
    "wof:placetype":"locality",
    "wof:population":133
},
  "geometry": {"coordinates":[-101.54306,21.01389],"type":"Point"}
}