{
  "type": "Feature",
  "properties": {
    "iso:country":"MX",
    "name:spa_x_preferred":[
        "Fracc Jardines Los Fuertes"
    ],
    "qs:gn_adm0_cc":"MX",
    "qs:gn_local":3521081,
    "qs:gn_nam_loc":"Puebla, Puebla, Puebla, MX",
    "qs:gn_namadm1":"21",
    "qs:local_max":15140,
    "qs:local_sum":49373,
    "qs:localhoods":21,
    "qs:name":"Fracc Jardines Los Fuertes",
    "qs:name_adm0":"M\u00e9xico",
    "qs:name_adm1":"Puebla",
    "qs:name_adm2":"Puebla",
    "qs:name_local":"Puebla",
    "qs:photo_max":189,
    "qs:photo_sum":533,
    "qs:placetype":"Suburb",
    "qs:quad_count":13,
    "qs:woe_adm0":23424900,
    "qs:woe_adm1":2346284,
    "qs:woe_adm2":12601342,
    "qs:woe_lau":0,
    "qs:woe_local":137612,
    "qs:woe_ver":"7.10.0",
    "wof:lang":[
        "spa"
    ],
    "wof:name":"Fracc Jardines Los Fuertes",
    "wof:placetype":"neighbourhood"
},
  "geometry": {"coordinates":[-98.18785099999999,19.06041],"type":"Point"}
}