{
  "type": "Feature",
  "properties": {
    "gn:admin1_code":"24",
    "gn:admin2_code":"35.0",
    "gn:asciiname":"Parcela Don Federico",
    "gn:country_code":"MX",
    "gn:dem":1838,
    "gn:feature_class":"P",
    "gn:feature_code":"PPL",
    "gn:name":"Parcela Don Federico",
    "gn:population":5,
    "gn:timezone":"America/Mexico_City",
    "iso:country":"MX",
    "wof:name":"Parcela Don Federico",
    "wof:placetype":"locality",
    "wof:population":5
},
  "geometry": {"coordinates":[-100.88444,22.2125],"type":"Point"}
}