{
  "type": "Feature",
  "properties": {
    "gn:admin1_code":"19.0",
    "gn:asciiname":"La Placeta",
    "gn:country_code":"MX",
    "gn:dem":357,
    "gn:feature_class":"P",
    "gn:feature_code":"PPL",
    "gn:name":"La Placeta",
    "gn:population":0,
    "gn:timezone":"America/Monterrey",
    "iso:country":"MX",
    "name:spa_x_preferred":[
        "La Placeta"
    ],
    "wof:name":"La Placeta",
    "wof:placetype":"locality"
},
  "geometry": {"coordinates":[-100.09399000000001,25.86598],"type":"Point"}
}