{
  "type": "Feature",
  "properties": {
    "gn:admin1_code":"32.0",
    "gn:admin2_code":"26.0",
    "gn:asciiname":"La Alegria",
    "gn:country_code":"MX",
    "gn:dem":1555,
    "gn:feature_class":"P",
    "gn:feature_code":"PPL",
    "gn:name":"La Alegria",
    "gn:population":0,
    "gn:timezone":"America/Mexico_City",
    "iso:country":"MX",
    "name:spa_x_preferred":[
        "La Alegria"
    ],
    "name:und_x_variant":[
        "Rancho La Alegr\u00eda"
    ],
    "wof:name":"La Alegria",
    "wof:placetype":"locality"
},
  "geometry": {"coordinates":[-102.31744999999999,24.91295],"type":"Point"}
}