{
  "type": "Feature",
  "properties": {
    "gn:admin1_code":"11.0",
    "gn:asciiname":"La Resolana",
    "gn:country_code":"MX",
    "gn:dem":1727,
    "gn:feature_class":"P",
    "gn:feature_code":"PPL",
    "gn:name":"La Resolana",
    "gn:population":0,
    "gn:timezone":"America/Mexico_City",
    "iso:country":"MX",
    "name:spa_x_preferred":[
        "La Resolana"
    ],
    "name:spa_x_variant":[
        "Maravillas"
    ],
    "wof:name":"La Resolana",
    "wof:placetype":"locality"
},
  "geometry": {"coordinates":[-101.67943,20.64239],"type":"Point"}
}