{
  "type": "Feature",
  "properties": {
    "gn:admin1_code":"5",
    "gn:admin2_code":"109.0",
    "gn:asciiname":"San Antonio de la Giralda",
    "gn:country_code":"MX",
    "gn:dem":629,
    "gn:feature_class":"P",
    "gn:feature_code":"PPL",
    "gn:name":"San Antonio de la Giralda",
    "gn:population":61,
    "gn:timezone":"America/Mexico_City",
    "iso:country":"MX",
    "wof:name":"San Antonio de la Giralda",
    "wof:placetype":"locality",
    "wof:population":61
},
  "geometry": {"coordinates":[-92.31694,17.23889],"type":"Point"}
}