{
  "type": "Feature",
  "properties": {
    "gn:admin1_code":"32",
    "gn:admin2_code":"17.0",
    "gn:asciiname":"La Luz",
    "gn:country_code":"MX",
    "gn:dem":2049,
    "gn:feature_class":"P",
    "gn:feature_code":"PPL",
    "gn:name":"La Luz",
    "gn:population":1244,
    "gn:timezone":"America/Mexico_City",
    "iso:country":"MX",
    "wof:name":"La Luz",
    "wof:placetype":"locality",
    "wof:population":1244
},
  "geometry": {"coordinates":[-102.31028000000001,22.88],"type":"Point"}
}