{
  "type": "Feature",
  "properties": {
    "gn:admin1_code":"2.0",
    "gn:admin2_code":"2.0",
    "gn:asciiname":"Los Angulos (Colonia Venustiano Carranza)",
    "gn:country_code":"MX",
    "gn:dem":9,
    "gn:feature_class":"P",
    "gn:feature_code":"PPL",
    "gn:name":"Los \u00c1ngulos (Colonia Venustiano Carranza)",
    "gn:population":9,
    "gn:timezone":"America/Tijuana",
    "iso:country":"MX",
    "name:und_x_variant":[
        "Colonia Venustiano Carranzo",
        "Venustiano Carranzo"
    ],
    "wof:name":"Los Angulos (Colonia Venustiano Carranza)",
    "wof:placetype":"locality",
    "wof:population":9
},
  "geometry": {"coordinates":[-115.14599,32.20864],"type":"Point"}
}