{
  "type": "Feature",
  "properties": {
    "gn:admin1_code":"32",
    "gn:admin2_code":"30.0",
    "gn:asciiname":"La Providencia",
    "gn:country_code":"MX",
    "gn:dem":1711,
    "gn:feature_class":"P",
    "gn:feature_code":"PPL",
    "gn:name":"La Providencia",
    "gn:population":8,
    "gn:timezone":"America/Mexico_City",
    "iso:country":"MX",
    "wof:name":"La Providencia",
    "wof:placetype":"locality",
    "wof:population":8
},
  "geometry": {"coordinates":[-103.27278,21.9625],"type":"Point"}
}