{
  "type": "Feature",
  "properties": {
    "gn:admin1_code":"18",
    "gn:admin2_code":"10.0",
    "gn:asciiname":"Teponahuaxtla",
    "gn:country_code":"MX",
    "gn:dem":73,
    "gn:feature_class":"P",
    "gn:feature_code":"PPL",
    "gn:name":"Teponahuaxtla",
    "gn:population":0,
    "gn:timezone":"America/Mazatlan",
    "iso:country":"MX",
    "name:und_x_variant":[
        "Teponahuastla",
        "Teponahuaxtla"
    ],
    "wof:name":"Teponahuaxtla",
    "wof:placetype":"locality"
},
  "geometry": {"coordinates":[-105.1901,22.22383],"type":"Point"}
}