{
  "type": "Feature",
  "properties": {
    "gn:admin1_code":"12",
    "gn:admin2_code":"1.0",
    "gn:asciiname":"Kilometro Cuarenta",
    "gn:country_code":"MX",
    "gn:dem":417,
    "gn:feature_class":"P",
    "gn:feature_code":"PPL",
    "gn:name":"Kil\u00f3metro Cuarenta",
    "gn:population":0,
    "gn:timezone":"America/Mexico_City",
    "iso:country":"MX",
    "name:spa_x_preferred":[
        "Kil\u00f3metro Cuarenta"
    ],
    "name:und_x_variant":[
        "El Cuarenta"
    ],
    "wof:name":"Kilometro Cuarenta",
    "wof:placetype":"locality"
},
  "geometry": {"coordinates":[-99.7696,17.04911],"type":"Point"}
}