{
  "type": "Feature",
  "properties": {
    "gn:admin1_code":"32",
    "gn:admin2_code":"10",
    "gn:asciiname":"Los Charcos",
    "gn:country_code":"MX",
    "gn:dem":2131,
    "gn:feature_class":"P",
    "gn:feature_code":"PPL",
    "gn:name":"Los Charcos",
    "gn:population":34,
    "gn:timezone":"America/Mexico_City",
    "iso:country":"MX",
    "wof:name":"Los Charcos",
    "wof:placetype":"locality",
    "wof:population":34
},
  "geometry": {"coordinates":[-103.13111000000001,23.26556],"type":"Point"}
}