{
  "type": "Feature",
  "properties": {
    "gn:admin1_code":"10",
    "gn:admin2_code":"2",
    "gn:asciiname":"Los Chirimoyos",
    "gn:country_code":"MX",
    "gn:dem":1197,
    "gn:feature_class":"P",
    "gn:feature_code":"PPL",
    "gn:name":"Los Chirimoyos",
    "gn:population":22,
    "gn:timezone":"America/Monterrey",
    "iso:country":"MX",
    "wof:name":"Los Chirimoyos",
    "wof:placetype":"locality",
    "wof:population":22
},
  "geometry": {"coordinates":[-106.63898,25.1047],"type":"Point"}
}