{
  "type": "Feature",
  "properties": {
    "gn:admin1_code":"15",
    "gn:admin2_code":"86.0",
    "gn:asciiname":"Barrio la Cascada (Barrio del Varal)",
    "gn:country_code":"MX",
    "gn:dem":1787,
    "gn:feature_class":"P",
    "gn:feature_code":"PPL",
    "gn:name":"Barrio la Cascada (Barrio del Varal)",
    "gn:population":85,
    "gn:timezone":"America/Mexico_City",
    "iso:country":"MX",
    "wof:name":"Barrio la Cascada (Barrio del Varal)",
    "wof:placetype":"locality",
    "wof:population":85
},
  "geometry": {"coordinates":[-100.04259999999999,19.04883],"type":"Point"}
}