{
  "type": "Feature",
  "properties": {
    "gn:admin1_code":"10",
    "gn:admin2_code":"17.0",
    "gn:asciiname":"La Rasposa",
    "gn:country_code":"MX",
    "gn:dem":1652,
    "gn:feature_class":"P",
    "gn:feature_code":"PPL",
    "gn:name":"La Rasposa",
    "gn:population":0,
    "gn:timezone":"America/Monterrey",
    "iso:country":"MX",
    "name:spa_x_preferred":[
        "La Rasposa"
    ],
    "wof:name":"La Rasposa",
    "wof:placetype":"locality"
},
  "geometry": {"coordinates":[-105.33060999999999,26.43237],"type":"Point"}
}