{
  "type": "Feature",
  "properties": {
    "gn:admin1_code":"15.0",
    "gn:asciiname":"La Dalia",
    "gn:country_code":"MX",
    "gn:dem":2432,
    "gn:feature_class":"P",
    "gn:feature_code":"PPL",
    "gn:name":"La Dalia",
    "gn:population":0,
    "gn:timezone":"America/Mexico_City",
    "iso:country":"MX",
    "name:spa_x_preferred":[
        "La Dalia"
    ],
    "wof:name":"La Dalia",
    "wof:placetype":"locality"
},
  "geometry": {"coordinates":[-99.51588,19.95832],"type":"Point"}
}