{
  "type": "Feature",
  "properties": {
    "gn:admin1_code":"6.0",
    "gn:admin2_code":"20.0",
    "gn:asciiname":"Los Bajios",
    "gn:country_code":"MX",
    "gn:dem":1465,
    "gn:feature_class":"P",
    "gn:feature_code":"PPL",
    "gn:name":"Los Baj\u00edos",
    "gn:population":0,
    "gn:timezone":"America/Chihuahua",
    "iso:country":"MX",
    "name:spa_x_preferred":[
        "Los Baj\u00edos"
    ],
    "wof:name":"Los Bajios",
    "wof:placetype":"locality"
},
  "geometry": {"coordinates":[-108.66278,27.56772],"type":"Point"}
}