{
  "type": "Feature",
  "properties": {
    "gn:country":"MX",
    "gn:fcode":"PPL",
    "gn:population":0,
    "iso:country":"MX",
    "name:spa_x_preferred":[
        "Las Sabanetas"
    ],
    "qs_pg:aaroncc":"MX",
    "qs_pg:gn_country":"MX",
    "qs_pg:gn_fcode":"PPL",
    "qs_pg:gn_pop":0,
    "qs_pg:name":"Las Aneas",
    "qs_pg:name_adm0":"M\u00e9xico",
    "qs_pg:name_adm1":"Veracruz-Llave",
    "qs_pg:photos":16,
    "qs_pg:photos_1k":3,
    "qs_pg:photos_9k":1,
    "qs_pg:photos_9r":1,
    "qs_pg:photos_all":16,
    "qs_pg:photos_sr":1,
    "qs_pg:pop_sr":0,
    "qs_pg:qs_pg_placetype":"neighbourhood",
    "qs_pg:qs_pg_placetype_gp":"Suburb",
    "qs_pg:woe_adm0":23424900,
    "woe:adm0_id":23424900,
    "woe:name_adm0":"M\u00e9xico",
    "woe:name_adm1":"Veracruz-Llave",
    "woe:placetype":"Suburb",
    "wof:name":"Las Aneas",
    "wof:placetype":"neighbourhood"
},
  "geometry": {"coordinates":[-95.82138,18.12667],"type":"Point"}
}