{
  "type": "Feature",
  "properties": {
    "gn:admin1_code":"30",
    "gn:admin2_code":"105",
    "gn:asciiname":"Fraccionamiento Residencial Marino",
    "gn:country_code":"MX",
    "gn:dem":5,
    "gn:feature_class":"P",
    "gn:feature_code":"PPL",
    "gn:name":"Fraccionamiento Residencial Marino",
    "gn:population":38,
    "gn:timezone":"America/Mexico_City",
    "iso:country":"MX",
    "wof:name":"Fraccionamiento Residencial Marino",
    "wof:placetype":"locality",
    "wof:population":38
},
  "geometry": {"coordinates":[-96.11694,19.09778],"type":"Point"}
}