{
  "type": "Feature",
  "properties": {
    "gn:admin1_code":"12",
    "gn:admin2_code":"31",
    "gn:asciiname":"Chipilatlan (La Memela)",
    "gn:country_code":"MX",
    "gn:dem":872,
    "gn:feature_class":"P",
    "gn:feature_code":"PPL",
    "gn:name":"Chipilatl\u00e1n (La Memela)",
    "gn:population":11,
    "gn:timezone":"America/Mexico_City",
    "iso:country":"MX",
    "name:und_x_variant":[
        "Chipilatl\u00e1n (La Memela)"
    ],
    "wof:name":"Chipilatlan (La Memela)",
    "wof:placetype":"locality",
    "wof:population":11
},
  "geometry": {"coordinates":[-100.16338,18.45631],"type":"Point"}
}