{
  "type": "Feature",
  "properties": {
    "gn:admin1_code":"16",
    "gn:admin2_code":"108.0",
    "gn:asciiname":"Rancho de Antonio Torres",
    "gn:country_code":"MX",
    "gn:dem":1566,
    "gn:feature_class":"P",
    "gn:feature_code":"PPL",
    "gn:name":"Rancho de Antonio Torres",
    "gn:population":9,
    "gn:timezone":"America/Mexico_City",
    "iso:country":"MX",
    "wof:name":"Rancho de Antonio Torres",
    "wof:placetype":"locality",
    "wof:population":9
},
  "geometry": {"coordinates":[-102.25778,19.98917],"type":"Point"}
}