{
  "type": "Feature",
  "properties": {
    "gn:admin1_code":"5",
    "gn:admin2_code":"38.0",
    "gn:asciiname":"Las Lajas",
    "gn:country_code":"MX",
    "gn:dem":1942,
    "gn:feature_class":"P",
    "gn:feature_code":"PPL",
    "gn:name":"Las Lajas",
    "gn:population":140,
    "gn:timezone":"America/Mexico_City",
    "iso:country":"MX",
    "name:ara_x_preferred":[
        "\u0644\u0627\u0633 \u0644\u0627\u062c\u0627\u0633"
    ],
    "name:ben_x_preferred":[
        "\u09b2\u09be\u09b8 \u09b2\u09be\u099c\u09be\u09b8"
    ],
    "name:bre_x_preferred":[
        "Las Lajas"
    ],
    "name:ceb_x_preferred":[
        "Las Lajas"
    ],
    "name:deu_x_preferred":[
        "Las Lajas"
    ],
    "name:ell_x_preferred":[
        "\u039b\u03b1\u03c2 \u039b\u03ac\u03c7\u03b1\u03c2"
    ],
    "name:fra_x_preferred":[
        "Las Lajas"
    ],
    "name:heb_x_preferred":[
        "\u05dc\u05d0\u05e1 \u05dc\u05d0\u05d7\u05d0\u05e1"
    ],
    "name:hin_x_preferred":[
        "\u0932\u093e \u0932\u091c\u093e\u0938"
    ],
    "name:hun_x_preferred":[
        "Las Lajas"
    ],
    "name:ind_x_preferred":[
        "Las Lajas"
    ],
    "name:ita_x_preferred":[
        "Las Lajas"
    ],
    "name:jpn_x_preferred":[
        "\u30e9\u30b9\u30e9\u30cf\u30b9"
    ],
    "name:kor_x_preferred":[
        "\ub77c\uc2a4 \ub77c\ud558\uc2a4"
    ],
    "name:lit_x_preferred":[
        "Las Lachasas"
    ],
    "name:nld_x_preferred":[
        "Las Lajas"
    ],
    "name:pol_x_preferred":[
        "Las Lajas"
    ],
    "name:spa_x_preferred":[
        "Las Lajas"
    ],
    "name:swe_x_preferred":[
        "Las Lajas"
    ],
    "name:urd_x_preferred":[
        "\u0644\u0627\u0633 \u0644\u0627\u062c\u0627\u0633"
    ],
    "name:vie_x_preferred":[
        "Las Lajas"
    ],
    "wof:name":"Las Lajas",
    "wof:placetype":"locality",
    "wof:population":140
},
  "geometry": {"coordinates":[-92.42778,16.71389],"type":"Point"}
}