{
  "type": "Feature",
  "properties": {
    "gn:admin1_code":"30",
    "gn:admin2_code":"175",
    "gn:asciiname":"Puente del Muerto",
    "gn:country_code":"MX",
    "gn:dem":104,
    "gn:feature_class":"P",
    "gn:feature_code":"PPL",
    "gn:name":"Puente del Muerto",
    "gn:population":18,
    "gn:timezone":"America/Mexico_City",
    "iso:country":"MX",
    "wof:name":"Puente del Muerto",
    "wof:placetype":"locality",
    "wof:population":18
},
  "geometry": {"coordinates":[-97.58056000000001,20.72528],"type":"Point"}
}