{
  "type": "Feature",
  "properties": {
    "gn:admin1_code":"26",
    "gn:admin2_code":"61.0",
    "gn:asciiname":"Salomas",
    "gn:cc2":"MX",
    "gn:country_code":"MX",
    "gn:dem":433,
    "gn:feature_class":"P",
    "gn:feature_code":"PPL",
    "gn:name":"Salomas",
    "gn:population":0,
    "gn:timezone":"America/Hermosillo",
    "iso:country":"MX",
    "name:und_x_variant":[
        "Palomas",
        "Salomas"
    ],
    "wof:name":"Salomas",
    "wof:placetype":"locality"
},
  "geometry": {"coordinates":[-109.76667,28.86667000000001],"type":"Point"}
}