{
  "type": "Feature",
  "properties": {
    "gn:admin1_code":"26",
    "gn:admin2_code":"21.0",
    "gn:asciiname":"Paredones",
    "gn:country_code":"MX",
    "gn:dem":294,
    "gn:feature_class":"P",
    "gn:feature_code":"PPL",
    "gn:name":"Paredones",
    "gn:population":0,
    "gn:timezone":"America/Hermosillo",
    "iso:country":"MX",
    "wof:name":"Paredones",
    "wof:placetype":"locality"
},
  "geometry": {"coordinates":[-110.68333,28.78333],"type":"Point"}
}