{
  "type": "Feature",
  "properties": {
    "gn:admin1_code":"5",
    "gn:admin2_code":"65.0",
    "gn:asciiname":"San Juanito",
    "gn:country_code":"MX",
    "gn:dem":35,
    "gn:feature_class":"P",
    "gn:feature_code":"PPL",
    "gn:name":"San Juanito",
    "gn:population":4,
    "gn:timezone":"America/Mexico_City",
    "iso:country":"MX",
    "name:ceb_x_preferred":[
        "San Juanito"
    ],
    "name:deu_x_preferred":[
        "San Juanito"
    ],
    "name:msa_x_preferred":[
        "San Juanito"
    ],
    "name:spa_x_preferred":[
        "San Juanito"
    ],
    "name:swe_x_preferred":[
        "San Juanito"
    ],
    "name:tgl_x_preferred":[
        "San Juanito"
    ],
    "name:vie_x_preferred":[
        "San Juanito"
    ],
    "wof:name":"San Juanito",
    "wof:placetype":"locality",
    "wof:population":4
},
  "geometry": {"coordinates":[-91.77056,17.51056],"type":"Point"}
}