{
  "type": "Feature",
  "properties": {
    "gn:admin1_code":"30",
    "gn:admin2_code":"212.0",
    "gn:asciiname":"El Tauro",
    "gn:country_code":"MX",
    "gn:dem":93,
    "gn:feature_class":"P",
    "gn:feature_code":"PPL",
    "gn:name":"El Tauro",
    "gn:population":5,
    "gn:timezone":"America/Mexico_City",
    "iso:country":"MX",
    "wof:name":"El Tauro",
    "wof:placetype":"locality",
    "wof:population":5
},
  "geometry": {"coordinates":[-95.58333,17.58806],"type":"Point"}
}