{
  "type": "Feature",
  "properties": {
    "gn:admin1_code":"27.0",
    "gn:asciiname":"Amate Cocoyol",
    "gn:country_code":"MX",
    "gn:dem":5,
    "gn:feature_class":"P",
    "gn:feature_code":"PPL",
    "gn:name":"Amate Cocoyol",
    "gn:population":0,
    "gn:timezone":"America/Mexico_City",
    "iso:country":"MX",
    "name:spa_x_preferred":[
        "Amate Cocoyol"
    ],
    "wof:name":"Amate Cocoyol",
    "wof:placetype":"locality"
},
  "geometry": {"coordinates":[-92.64229,17.99782],"type":"Point"}
}