{
  "type": "Feature",
  "properties": {
    "gn:admin1_code":"12",
    "gn:admin2_code":"3",
    "gn:asciiname":"Caballos",
    "gn:country_code":"MX",
    "gn:dem":1166,
    "gn:feature_class":"P",
    "gn:feature_code":"PPL",
    "gn:name":"Caballos",
    "gn:population":15,
    "gn:timezone":"America/Mexico_City",
    "iso:country":"MX",
    "wof:name":"Caballos",
    "wof:placetype":"locality",
    "wof:population":15
},
  "geometry": {"coordinates":[-100.60505000000001,17.95922999999999],"type":"Point"}
}