{
  "type": "Feature",
  "properties": {
    "gn:admin1_code":"25",
    "gn:admin2_code":"16.0",
    "gn:asciiname":"La Bebelama",
    "gn:country_code":"MX",
    "gn:dem":31,
    "gn:feature_class":"P",
    "gn:feature_code":"PPL",
    "gn:name":"La Bebelama",
    "gn:population":0,
    "gn:timezone":"America/Mazatlan",
    "iso:country":"MX",
    "name:spa_x_preferred":[
        "La Bebelama"
    ],
    "wof:name":"La Bebelama",
    "wof:placetype":"locality"
},
  "geometry": {"coordinates":[-106.69556,23.81536],"type":"Point"}
}