{
  "type": "Feature",
  "properties": {
    "gn:admin1_code":"21",
    "gn:admin2_code":"50.0",
    "gn:asciiname":"Colonia Guadalupe",
    "gn:country_code":"MX",
    "gn:dem":1842,
    "gn:feature_class":"P",
    "gn:feature_code":"PPL",
    "gn:name":"Colonia Guadalupe",
    "gn:population":471,
    "gn:timezone":"America/Mexico_City",
    "iso:country":"MX",
    "wof:name":"Colonia Guadalupe",
    "wof:placetype":"locality",
    "wof:population":471
},
  "geometry": {"coordinates":[-97.05556,19.21556],"type":"Point"}
}