{
  "type": "Feature",
  "properties": {
    "gn:admin1_code":"4",
    "gn:admin2_code":"10.0",
    "gn:asciiname":"Becan",
    "gn:country_code":"MX",
    "gn:dem":272,
    "gn:feature_class":"P",
    "gn:feature_code":"PPL",
    "gn:name":"Bec\u00e1n",
    "gn:population":268,
    "gn:timezone":"America/Merida",
    "iso:country":"MX",
    "name:bul_x_preferred":[
        "\u0411\u0435\u043a\u0430\u043d"
    ],
    "name:deu_x_preferred":[
        "Bec\u00e1n"
    ],
    "name:fra_x_preferred":[
        "Bec\u00e1n"
    ],
    "name:hun_x_preferred":[
        "Bec\u00e1n"
    ],
    "name:ind_x_preferred":[
        "Becan"
    ],
    "name:ita_x_preferred":[
        "Bec\u00e1n"
    ],
    "name:kat_x_preferred":[
        "\u10d1\u10d4\u10d9\u10d0\u10dc\u10d8"
    ],
    "name:lit_x_preferred":[
        "Bekanas"
    ],
    "name:mkd_x_preferred":[
        "\u0411\u0435\u043a\u0430\u043d"
    ],
    "name:rus_x_preferred":[
        "\u0411\u0435\u043a\u0430\u043d"
    ],
    "name:spa_x_preferred":[
        "Bec\u00e1n"
    ],
    "name:ukr_x_preferred":[
        "\u0411\u0435\u043a\u0430\u043d"
    ],
    "wof:name":"Becan",
    "wof:placetype":"locality",
    "wof:population":268
},
  "geometry": {"coordinates":[-89.46333,18.5125],"type":"Point"}
}