{
  "type": "Feature",
  "properties": {
    "gn:admin1_code":"4",
    "gn:admin2_code":"10.0",
    "gn:asciiname":"Becan",
    "gn:country_code":"MX",
    "gn:dem":272,
    "gn:feature_class":"P",
    "gn:feature_code":"PPL",
    "gn:name":"Bec\u00e1n",
    "gn:population":268,
    "gn:timezone":"America/Merida",
    "iso:country":"MX",
    "name:und_x_variant":[
        "Bec\u00e1n"
    ],
    "wof:name":"Becan",
    "wof:placetype":"locality",
    "wof:population":268
},
  "geometry": {"coordinates":[-89.46333,18.5125],"type":"Point"}
}