{
  "type": "Feature",
  "properties": {
    "gn:admin1_code":"20",
    "gn:admin2_code":"370",
    "gn:asciiname":"Barrio Dolores (Primera Seccion)",
    "gn:country_code":"MX",
    "gn:dem":2105,
    "gn:feature_class":"P",
    "gn:feature_code":"PPL",
    "gn:name":"Barrio Dolores (Primera Secci\u00f3n)",
    "gn:population":17,
    "gn:timezone":"America/Mexico_City",
    "iso:country":"MX",
    "name:und_x_variant":[
        "Barrio Dolores (Primera Secci\u00f3n)"
    ],
    "wof:name":"Barrio Dolores (Primera Seccion)",
    "wof:placetype":"locality",
    "wof:population":17
},
  "geometry": {"coordinates":[-97.55722,17.34944],"type":"Point"}
}