{
  "type": "Feature",
  "properties": {
    "gn:admin1_code":"2.0",
    "gn:admin2_code":"2.0",
    "gn:asciiname":"Rancho Juan Horta",
    "gn:country_code":"MX",
    "gn:dem":68,
    "gn:feature_class":"P",
    "gn:feature_code":"PPL",
    "gn:name":"Rancho Juan Horta",
    "gn:population":0,
    "gn:timezone":"America/Tijuana",
    "iso:country":"MX",
    "name:spa_x_preferred":[
        "Rancho Juan Horta"
    ],
    "wof:name":"Rancho Juan Horta",
    "wof:placetype":"locality"
},
  "geometry": {"coordinates":[-115.04694000000001,31.42415],"type":"Point"}
}