{
  "type": "Feature",
  "properties": {
    "gn:admin1_code":"5.0",
    "gn:asciiname":"Los Larelitos",
    "gn:country_code":"MX",
    "gn:dem":877,
    "gn:feature_class":"P",
    "gn:feature_code":"PPL",
    "gn:name":"Los Larelitos",
    "gn:population":0,
    "gn:timezone":"America/Mexico_City",
    "iso:country":"MX",
    "name:spa_x_preferred":[
        "Los Larelitos"
    ],
    "wof:name":"Los Larelitos",
    "wof:placetype":"locality"
},
  "geometry": {"coordinates":[-92.08405,16.928],"type":"Point"}
}