{
  "type": "Feature",
  "properties": {
    "gn:admin1_code":"16",
    "gn:admin2_code":"47.0",
    "gn:asciiname":"La Miel",
    "gn:country_code":"MX",
    "gn:dem":1619,
    "gn:feature_class":"P",
    "gn:feature_code":"PPL",
    "gn:name":"La Miel",
    "gn:population":56,
    "gn:timezone":"America/Mexico_City",
    "iso:country":"MX",
    "wof:name":"La Miel",
    "wof:placetype":"locality",
    "wof:population":56
},
  "geometry": {"coordinates":[-100.47944,19.48528],"type":"Point"}
}