{
  "type": "Feature",
  "properties": {
    "gn:admin1_code":"4",
    "gn:admin2_code":"5.0",
    "gn:asciiname":"Monte Bello",
    "gn:country_code":"MX",
    "gn:dem":68,
    "gn:feature_class":"P",
    "gn:feature_code":"PPL",
    "gn:name":"Monte Bello",
    "gn:population":0,
    "gn:timezone":"America/Merida",
    "iso:country":"MX",
    "name:ceb_x_preferred":[
        "Monte Bello"
    ],
    "name:spa_x_preferred":[
        "Monte Bello"
    ],
    "name:swe_x_preferred":[
        "Monte Bello"
    ],
    "name:und_x_variant":[
        "Montebello"
    ],
    "wof:name":"Monte Bello",
    "wof:placetype":"locality"
},
  "geometry": {"coordinates":[-89.96168,19.95264],"type":"Point"}
}