{
  "type": "Feature",
  "properties": {
    "gn:admin1_code":"6",
    "gn:admin2_code":"49.0",
    "gn:asciiname":"Bacazorare",
    "gn:country_code":"MX",
    "gn:dem":2026,
    "gn:feature_class":"P",
    "gn:feature_code":"PPL",
    "gn:name":"Bacaz\u00f3rare",
    "gn:population":0,
    "gn:timezone":"America/Chihuahua",
    "iso:country":"MX",
    "name:spa_x_preferred":[
        "Bacaz\u00f3rare"
    ],
    "wof:name":"Bacazorare",
    "wof:placetype":"locality"
},
  "geometry": {"coordinates":[-106.84631,27.22914],"type":"Point"}
}