{
  "type": "Feature",
  "properties": {
    "gn:admin1_code":"14",
    "gn:admin2_code":"8.0",
    "gn:asciiname":"Aguila de Gutierrez (Aguila Chica)",
    "gn:country_code":"MX",
    "gn:dem":2055,
    "gn:feature_class":"P",
    "gn:feature_code":"PPL",
    "gn:name":"\u00c1guila de Guti\u00e9rrez (\u00c1guila Chica)",
    "gn:population":6,
    "gn:timezone":"America/Mexico_City",
    "iso:country":"MX",
    "name:und_x_variant":[
        "\u00c1guila de Guti\u00e9rrez (\u00c1guila Chica)"
    ],
    "wof:name":"Aguila de Gutierrez (Aguila Chica)",
    "wof:placetype":"locality",
    "wof:population":6
},
  "geometry": {"coordinates":[-102.32222,20.85],"type":"Point"}
}