{
  "type": "Feature",
  "properties": {
    "gn:admin1_code":"16",
    "gn:admin2_code":"101.0",
    "gn:asciiname":"Santas Marias",
    "gn:country_code":"MX",
    "gn:dem":1562,
    "gn:feature_class":"P",
    "gn:feature_code":"PPL",
    "gn:name":"Santas Mar\u00edas",
    "gn:population":0,
    "gn:timezone":"America/Mexico_City",
    "iso:country":"MX",
    "name:spa_x_preferred":[
        "Santas Mar\u00edas"
    ],
    "wof:name":"Santas Marias",
    "wof:placetype":"locality"
},
  "geometry": {"coordinates":[-100.86291,19.47573],"type":"Point"}
}