{
  "type": "Feature",
  "properties": {
    "gn:admin1_code":"25.0",
    "gn:admin2_code":"10.0",
    "gn:asciiname":"El Tepeguaje",
    "gn:country_code":"MX",
    "gn:dem":238,
    "gn:feature_class":"P",
    "gn:feature_code":"PPL",
    "gn:name":"El Tepeguaje",
    "gn:population":0,
    "gn:timezone":"America/Mazatlan",
    "iso:country":"MX",
    "name:spa_x_preferred":[
        "El Tepeguaje"
    ],
    "wof:name":"El Tepeguaje",
    "wof:placetype":"locality"
},
  "geometry": {"coordinates":[-108.4272,26.59345],"type":"Point"}
}