{
  "type": "Feature",
  "properties": {
    "gn:admin1_code":"30.0",
    "gn:admin2_code":"78.0",
    "gn:asciiname":"Florijomil",
    "gn:country_code":"MX",
    "gn:dem":225,
    "gn:feature_class":"P",
    "gn:feature_code":"PPL",
    "gn:name":"Florijomil",
    "gn:population":0,
    "gn:timezone":"America/Mexico_City",
    "iso:country":"MX",
    "name:spa_x_preferred":[
        "Florijomil"
    ],
    "name:spa_x_variant":[
        "La Pe\u00f1a"
    ],
    "wof:name":"Florijomil",
    "wof:placetype":"locality"
},
  "geometry": {"coordinates":[-97.96287,21.21355],"type":"Point"}
}