{
  "type": "Feature",
  "properties": {
    "gn:admin1_code":"31",
    "gn:admin2_code":"96.0",
    "gn:asciiname":"Kabichen",
    "gn:country_code":"MX",
    "gn:dem":20,
    "gn:feature_class":"P",
    "gn:feature_code":"PPL",
    "gn:name":"Kabich\u00e9n",
    "gn:population":231,
    "gn:timezone":"America/Merida",
    "iso:country":"MX",
    "wof:name":"Kabichen",
    "wof:placetype":"locality",
    "wof:population":231
},
  "geometry": {"coordinates":[-87.95806,21.14861],"type":"Point"}
}