{
  "type": "Feature",
  "properties": {
    "gn:admin1_code":"5",
    "gn:admin2_code":"41.0",
    "gn:asciiname":"Santa Rita el Vergel",
    "gn:country_code":"MX",
    "gn:dem":1173,
    "gn:feature_class":"P",
    "gn:feature_code":"PPL",
    "gn:name":"Santa Rita el Vergel",
    "gn:population":738,
    "gn:timezone":"America/Mexico_City",
    "iso:country":"MX",
    "wof:name":"Santa Rita el Vergel",
    "wof:placetype":"locality",
    "wof:population":738
},
  "geometry": {"coordinates":[-91.72624,16.25456],"type":"Point"}
}