{
  "type": "Feature",
  "properties": {
    "gn:admin1_code":"15.0",
    "gn:asciiname":"El Sauz de Guzman",
    "gn:country_code":"MX",
    "gn:dem":2103,
    "gn:feature_class":"P",
    "gn:feature_code":"PPL",
    "gn:name":"El S\u00e1uz de Guzm\u00e1n",
    "gn:population":0,
    "gn:timezone":"America/Mexico_City",
    "iso:country":"MX",
    "name:spa_x_preferred":[
        "El S\u00e1uz de Guzm\u00e1n"
    ],
    "wof:name":"El Sauz de Guzman",
    "wof:placetype":"locality"
},
  "geometry": {"coordinates":[-102.36537,19.85846],"type":"Point"}
}