{
  "type": "Feature",
  "properties": {
    "gn:admin1_code":"22",
    "gn:admin2_code":"13.0",
    "gn:asciiname":"El Lindero",
    "gn:country_code":"MX",
    "gn:dem":1478,
    "gn:feature_class":"P",
    "gn:feature_code":"PPL",
    "gn:name":"El Lindero",
    "gn:population":168,
    "gn:timezone":"America/Mexico_City",
    "iso:country":"MX",
    "wof:name":"El Lindero",
    "wof:placetype":"locality",
    "wof:population":168
},
  "geometry": {"coordinates":[-99.85250000000001,21.09417],"type":"Point"}
}