{
  "type": "Feature",
  "properties": {
    "gn:admin1_code":"26.0",
    "gn:asciiname":"El Cielito",
    "gn:country_code":"MX",
    "gn:dem":533,
    "gn:feature_class":"P",
    "gn:feature_code":"PPL",
    "gn:name":"El Cielito",
    "gn:population":0,
    "gn:timezone":"America/Hermosillo",
    "iso:country":"MX",
    "name:spa_x_preferred":[
        "El Cielito"
    ],
    "wof:name":"El Cielito",
    "wof:placetype":"locality"
},
  "geometry": {"coordinates":[-112.04676000000001,29.90429],"type":"Point"}
}