{
  "type": "Feature",
  "properties": {
    "gn:admin1_code":"30",
    "gn:admin2_code":"161.0",
    "gn:asciiname":"Crescencio Sanchez Arrieta",
    "gn:country_code":"MX",
    "gn:dem":112,
    "gn:feature_class":"P",
    "gn:feature_code":"PPL",
    "gn:name":"Crescencio S\u00e1nchez Arrieta",
    "gn:population":5,
    "gn:timezone":"America/Mexico_City",
    "iso:country":"MX",
    "name:und_x_variant":[
        "Crescencio S\u00e1nchez Arrieta"
    ],
    "wof:name":"Crescencio Sanchez Arrieta",
    "wof:placetype":"locality",
    "wof:population":5
},
  "geometry": {"coordinates":[-98.27639000000001,21.52],"type":"Point"}
}