{
  "type": "Feature",
  "properties": {
    "gn:admin1_code":"16.0",
    "gn:admin2_code":"38.0",
    "gn:asciiname":"San Nicolas Arroyo Hondo",
    "gn:country_code":"MX",
    "gn:dem":238,
    "gn:feature_class":"P",
    "gn:feature_code":"PPL",
    "gn:name":"San Nicol\u00e1s Arroyo Hondo",
    "gn:population":0,
    "gn:timezone":"America/Mexico_City",
    "iso:country":"MX",
    "name:spa_x_preferred":[
        "San Nicol\u00e1s Arroyo Hondo"
    ],
    "name:und_x_variant":[
        "Arroyo Hondo"
    ],
    "wof:name":"San Nicolas Arroyo Hondo",
    "wof:placetype":"locality"
},
  "geometry": {"coordinates":[-100.86091,18.53724],"type":"Point"}
}