{
  "type": "Feature",
  "properties": {
    "gn:admin1_code":"10",
    "gn:admin2_code":"11",
    "gn:asciiname":"San Jose del Nopal (El Nopal)",
    "gn:country_code":"MX",
    "gn:dem":1799,
    "gn:feature_class":"P",
    "gn:feature_code":"PPL",
    "gn:name":"San Jos\u00e9 del Nopal (El Nopal)",
    "gn:population":28,
    "gn:timezone":"America/Monterrey",
    "iso:country":"MX",
    "name:und_x_variant":[
        "San Jos\u00e9 del Nopal (El Nopal)"
    ],
    "wof:name":"San Jose del Nopal (El Nopal)",
    "wof:placetype":"locality",
    "wof:population":28
},
  "geometry": {"coordinates":[-105.19092999999999,25.83137],"type":"Point"}
}