{
  "type": "Feature",
  "properties": {
    "gn:admin1_code":"7",
    "gn:admin2_code":"30.0",
    "gn:asciiname":"Resa",
    "gn:country_code":"MX",
    "gn:dem":1725,
    "gn:feature_class":"P",
    "gn:feature_code":"PPL",
    "gn:name":"Resa",
    "gn:population":7,
    "gn:timezone":"America/Monterrey",
    "iso:country":"MX",
    "wof:name":"Resa",
    "wof:placetype":"locality",
    "wof:population":7
},
  "geometry": {"coordinates":[-101.3192,25.29837],"type":"Point"}
}