{
  "type": "Feature",
  "properties": {
    "gn:admin1_code":"11",
    "gn:admin2_code":"8.0",
    "gn:asciiname":"Rincon de la Presa del Sitio",
    "gn:country_code":"MX",
    "gn:dem":1723,
    "gn:feature_class":"P",
    "gn:feature_code":"PPL",
    "gn:name":"Rinc\u00f3n de la Presa del Sitio",
    "gn:population":6,
    "gn:timezone":"America/Mexico_City",
    "iso:country":"MX",
    "name:und_x_variant":[
        "Rinc\u00f3n de la Presa del Sitio"
    ],
    "wof:name":"Rincon de la Presa del Sitio",
    "wof:placetype":"locality",
    "wof:population":6
},
  "geometry": {"coordinates":[-101.93167,20.77306],"type":"Point"}
}