{
  "type": "Feature",
  "properties": {
    "gn:admin1_code":"6",
    "gn:admin2_code":"10.0",
    "gn:asciiname":"Don Jose",
    "gn:country_code":"MX",
    "gn:dem":1508,
    "gn:feature_class":"P",
    "gn:feature_code":"PPL",
    "gn:name":"Don Jos\u00e9",
    "gn:population":0,
    "gn:timezone":"America/Chihuahua",
    "iso:country":"MX",
    "name:spa_x_preferred":[
        "Don Jos\u00e9"
    ],
    "wof:name":"Don Jose",
    "wof:placetype":"locality"
},
  "geometry": {"coordinates":[-107.08872,29.92416],"type":"Point"}
}