{
  "type": "Feature",
  "properties": {
    "gn:admin1_code":"30",
    "gn:admin2_code":"61.0",
    "gn:asciiname":"Francisco I. Madero (Agua Fria)",
    "gn:country_code":"MX",
    "gn:dem":43,
    "gn:feature_class":"P",
    "gn:feature_code":"PPL",
    "gn:name":"Francisco I. Madero (Agua Fr\u00eda)",
    "gn:population":355,
    "gn:timezone":"America/Mexico_City",
    "iso:country":"MX",
    "name:und_x_variant":[
        "Francisco I. Madero (Agua Fr\u00eda)"
    ],
    "wof:name":"Francisco I. Madero (Agua Fria)",
    "wof:placetype":"locality",
    "wof:population":355
},
  "geometry": {"coordinates":[-94.12027999999999,17.47528],"type":"Point"}
}