{
  "type": "Feature",
  "properties": {
    "gn:admin1_code":"29",
    "gn:admin2_code":"6.0",
    "gn:asciiname":"Don Ramon",
    "gn:country_code":"MX",
    "gn:dem":2553,
    "gn:feature_class":"P",
    "gn:feature_code":"PPL",
    "gn:name":"Don Ram\u00f3n",
    "gn:population":5,
    "gn:timezone":"America/Mexico_City",
    "iso:country":"MX",
    "name:und_x_variant":[
        "Don Ram\u00f3n"
    ],
    "wof:name":"Don Ramon",
    "wof:placetype":"locality",
    "wof:population":5
},
  "geometry": {"coordinates":[-98.57606,19.60961],"type":"Point"}
}