{
  "type": "Feature",
  "properties": {
    "gn:admin1_code":"26",
    "gn:admin2_code":"26.0",
    "gn:asciiname":"Pueblo Viejo",
    "gn:country_code":"MX",
    "gn:dem":17,
    "gn:feature_class":"P",
    "gn:feature_code":"PPL",
    "gn:name":"Pueblo Viejo",
    "gn:population":0,
    "gn:timezone":"America/Hermosillo",
    "iso:country":"MX",
    "name:ceb_x_preferred":[
        "Pueblo Viejo"
    ],
    "name:deu_x_preferred":[
        "Pueblo Viejo"
    ],
    "name:fra_x_preferred":[
        "Pueblo Viejo"
    ],
    "name:nds_x_preferred":[
        "Pueblo Viejo"
    ],
    "name:sco_x_preferred":[
        "Pueblo Viejo"
    ],
    "name:spa_x_preferred":[
        "Pueblo Viejo"
    ],
    "name:swe_x_preferred":[
        "Pueblo Viejo"
    ],
    "name:vie_x_preferred":[
        "Pueblo Viejo"
    ],
    "wof:name":"Pueblo Viejo",
    "wof:placetype":"locality"
},
  "geometry": {"coordinates":[-109.63692,26.91452],"type":"Point"}
}