{
  "type": "Feature",
  "properties": {
    "gn:admin1_code":"28",
    "gn:admin2_code":"22.0",
    "gn:asciiname":"La Amistad",
    "gn:country_code":"MX",
    "gn:dem":7,
    "gn:feature_class":"P",
    "gn:feature_code":"PPL",
    "gn:name":"La Amistad",
    "gn:population":9,
    "gn:timezone":"America/Matamoros",
    "iso:country":"MX",
    "wof:name":"La Amistad",
    "wof:placetype":"locality",
    "wof:population":9
},
  "geometry": {"coordinates":[-97.41195,25.7725],"type":"Point"}
}