{
  "type": "Feature",
  "properties": {
    "gn:admin1_code":"22",
    "gn:admin2_code":"4",
    "gn:asciiname":"El Chivo",
    "gn:country_code":"MX",
    "gn:dem":1932,
    "gn:feature_class":"P",
    "gn:feature_code":"PPL",
    "gn:name":"El Chivo",
    "gn:population":12,
    "gn:timezone":"America/Mexico_City",
    "iso:country":"MX",
    "name:bul_x_preferred":[
        "\u041a\u043e\u0437\u0435\u043b\u044a\u0442"
    ],
    "name:fas_x_preferred":[
        "\u0627\u0644 \u0686\u06cc\u0648\u0648"
    ],
    "name:spa_x_preferred":[
        "El Chivo"
    ],
    "wof:name":"El Chivo",
    "wof:placetype":"locality",
    "wof:population":12
},
  "geometry": {"coordinates":[-99.55583,20.69556],"type":"Point"}
}