{
  "type": "Feature",
  "properties": {
    "gn:admin1_code":"30",
    "gn:admin2_code":"61.0",
    "gn:asciiname":"Venustiano Carranza",
    "gn:country_code":"MX",
    "gn:dem":49,
    "gn:feature_class":"P",
    "gn:feature_code":"PPL",
    "gn:name":"Venustiano Carranza",
    "gn:population":92,
    "gn:timezone":"America/Mexico_City",
    "iso:country":"MX",
    "wof:name":"Venustiano Carranza",
    "wof:placetype":"locality",
    "wof:population":92
},
  "geometry": {"coordinates":[-94.14917,17.92972],"type":"Point"}
}