{
  "type": "Feature",
  "properties": {
    "gn:admin1_code":"19.0",
    "gn:asciiname":"La Purisima",
    "gn:country_code":"MX",
    "gn:dem":1890,
    "gn:feature_class":"P",
    "gn:feature_code":"PPL",
    "gn:name":"La Pur\u00edsima",
    "gn:population":0,
    "gn:timezone":"America/Monterrey",
    "iso:country":"MX",
    "name:spa_x_preferred":[
        "La Pur\u00edsima"
    ],
    "name:und_x_variant":[
        "Granja La Pur\u00edsima"
    ],
    "wof:name":"La Purisima",
    "wof:placetype":"locality"
},
  "geometry": {"coordinates":[-100.82526,25.06878],"type":"Point"}
}