{
  "type": "Feature",
  "properties": {
    "gn:admin1_code":"12",
    "gn:admin2_code":"22.0",
    "gn:asciiname":"Las Parotas",
    "gn:country_code":"MX",
    "gn:dem":944,
    "gn:feature_class":"P",
    "gn:feature_code":"PPL",
    "gn:name":"Las Parotas",
    "gn:population":7,
    "gn:timezone":"America/Mexico_City",
    "iso:country":"MX",
    "wof:name":"Las Parotas",
    "wof:placetype":"locality",
    "wof:population":7
},
  "geometry": {"coordinates":[-101.14490000000001,17.82976],"type":"Point"}
}