{
  "type": "Feature",
  "properties": {
    "iso:country":"MX",
    "name:spa_x_preferred":[
        "Colinas Del Sol Iii"
    ],
    "qs:gn_adm0_cc":"MX",
    "qs:gn_local":4014338,
    "qs:gn_nam_loc":"Chihuahua, Chihuahua, Chihuahua, MX",
    "qs:gn_namadm1":"06",
    "qs:local_max":1142,
    "qs:local_sum":1903,
    "qs:localhoods":12,
    "qs:name":"Colinas Del Sol Iii",
    "qs:name_adm0":"M\u00e9xico",
    "qs:name_adm1":"Chihuahua",
    "qs:name_adm2":"Chihuahua",
    "qs:name_local":"Chihuahua",
    "qs:photo_max":25,
    "qs:photo_sum":59,
    "qs:placetype":"Suburb",
    "qs:quad_count":13,
    "qs:woe_adm0":23424900,
    "qs:woe_adm1":2346269,
    "qs:woe_adm2":12599832,
    "qs:woe_lau":0,
    "qs:woe_local":115958,
    "qs:woe_ver":"7.10.0",
    "wof:lang":[
        "spa"
    ],
    "wof:name":"Colinas Del Sol Iii",
    "wof:placetype":"neighbourhood"
},
  "geometry": {"coordinates":[-106.13049599999999,28.653572],"type":"Point"}
}