{
  "type": "Feature",
  "properties": {
    "gn:admin1_code":"14",
    "gn:admin2_code":"118.0",
    "gn:asciiname":"Coyotillos",
    "gn:country_code":"MX",
    "gn:dem":1878,
    "gn:feature_class":"P",
    "gn:feature_code":"PPL",
    "gn:name":"Coyotillos",
    "gn:population":5,
    "gn:timezone":"America/Mexico_City",
    "iso:country":"MX",
    "wof:name":"Coyotillos",
    "wof:placetype":"locality",
    "wof:population":5
},
  "geometry": {"coordinates":[-102.92306000000001,21.18444],"type":"Point"}
}