{
  "type": "Feature",
  "properties": {
    "gn:admin1_code":"19",
    "gn:admin2_code":"38.0",
    "gn:asciiname":"Charco Verde",
    "gn:country_code":"MX",
    "gn:dem":527,
    "gn:feature_class":"P",
    "gn:feature_code":"PPL",
    "gn:name":"Charco Verde",
    "gn:population":0,
    "gn:timezone":"America/Monterrey",
    "iso:country":"MX",
    "name:spa_x_preferred":[
        "Charco Verde"
    ],
    "wof:name":"Charco Verde",
    "wof:placetype":"locality"
},
  "geometry": {"coordinates":[-99.93917999999999,25.14245],"type":"Point"}
}