{
  "type": "Feature",
  "properties": {
    "gn:admin1_code":"5.0",
    "gn:asciiname":"La Guacamaya",
    "gn:country_code":"MX",
    "gn:dem":647,
    "gn:feature_class":"P",
    "gn:feature_code":"PPL",
    "gn:name":"La Guacamaya",
    "gn:population":0,
    "gn:timezone":"America/Mexico_City",
    "iso:country":"MX",
    "name:spa_x_preferred":[
        "La Guacamaya"
    ],
    "wof:name":"La Guacamaya",
    "wof:placetype":"locality"
},
  "geometry": {"coordinates":[-93.59312,16.51353],"type":"Point"}
}