{
  "type": "Feature",
  "properties": {
    "gn:admin1_code":"10",
    "gn:admin2_code":"26",
    "gn:asciiname":"Los Ojitos",
    "gn:country_code":"MX",
    "gn:dem":2293,
    "gn:feature_class":"P",
    "gn:feature_code":"PPL",
    "gn:name":"Los Ojitos",
    "gn:population":13,
    "gn:timezone":"America/Monterrey",
    "iso:country":"MX",
    "wof:name":"Los Ojitos",
    "wof:placetype":"locality",
    "wof:population":13
},
  "geometry": {"coordinates":[-105.76142,24.21667],"type":"Point"}
}