{
  "type": "Feature",
  "properties": {
    "gn:admin1_code":"20",
    "gn:admin2_code":"325.0",
    "gn:asciiname":"Agua Colorada",
    "gn:country_code":"MX",
    "gn:dem":2249,
    "gn:feature_class":"P",
    "gn:feature_code":"PPL",
    "gn:name":"Agua Colorada",
    "gn:population":101,
    "gn:timezone":"America/Mexico_City",
    "iso:country":"MX",
    "wof:name":"Agua Colorada",
    "wof:placetype":"locality",
    "wof:population":101
},
  "geometry": {"coordinates":[-96.07306,16.83],"type":"Point"}
}