{
  "type": "Feature",
  "properties": {
    "gn:admin1_code":"19.0",
    "gn:admin2_code":"5.0",
    "gn:asciiname":"Los Garcia",
    "gn:country_code":"MX",
    "gn:dem":238,
    "gn:feature_class":"P",
    "gn:feature_code":"PPL",
    "gn:name":"Los Garc\u00eda",
    "gn:population":0,
    "gn:timezone":"America/Matamoros",
    "iso:country":"MX",
    "name:spa_x_preferred":[
        "Los Garc\u00eda"
    ],
    "wof:name":"Los Garcia",
    "wof:placetype":"locality"
},
  "geometry": {"coordinates":[-100.35102999999999,27.38469000000001],"type":"Point"}
}