{
  "type": "Feature",
  "properties": {
    "gn:admin1_code":"31",
    "gn:admin2_code":"79.0",
    "gn:asciiname":"Zabac-halal",
    "gn:country_code":"MX",
    "gn:dem":133,
    "gn:feature_class":"P",
    "gn:feature_code":"PPL",
    "gn:name":"Zabac-halal",
    "gn:population":0,
    "gn:timezone":"America/Merida",
    "iso:country":"MX",
    "name:und_x_variant":[
        "Zabackalal",
        "Zabac-Halal"
    ],
    "wof:name":"Zabac-halal",
    "wof:placetype":"locality"
},
  "geometry": {"coordinates":[-89.21044999999999,19.9752],"type":"Point"}
}