{
  "type": "Feature",
  "properties": {
    "gn:admin1_code":"27",
    "gn:admin2_code":"11.0",
    "gn:asciiname":"Santa Anita",
    "gn:country_code":"MX",
    "gn:dem":4,
    "gn:feature_class":"P",
    "gn:feature_code":"PPL",
    "gn:name":"Santa Anita",
    "gn:population":0,
    "gn:timezone":"America/Mexico_City",
    "iso:country":"MX",
    "name:spa_x_preferred":[
        "Santa Anita"
    ],
    "wof:name":"Santa Anita",
    "wof:placetype":"locality"
},
  "geometry": {"coordinates":[-92.25592,18.32103],"type":"Point"}
}