{
  "type": "Feature",
  "properties": {
    "gn:admin1_code":"3",
    "gn:admin2_code":"3.0",
    "gn:asciiname":"La Arenosa",
    "gn:country_code":"MX",
    "gn:dem":174,
    "gn:feature_class":"P",
    "gn:feature_code":"PPL",
    "gn:name":"La Arenosa",
    "gn:population":4,
    "gn:timezone":"America/Mazatlan",
    "iso:country":"MX",
    "wof:name":"La Arenosa",
    "wof:placetype":"locality",
    "wof:population":4
},
  "geometry": {"coordinates":[-110.98192,24.63701],"type":"Point"}
}