{
  "type": "Feature",
  "properties": {
    "gn:admin1_code":"24",
    "gn:admin2_code":"12.0",
    "gn:asciiname":"Zojualo",
    "gn:country_code":"MX",
    "gn:dem":286,
    "gn:feature_class":"P",
    "gn:feature_code":"PPL",
    "gn:name":"Zojualo",
    "gn:population":411,
    "gn:timezone":"America/Mexico_City",
    "iso:country":"MX",
    "wof:name":"Zojualo",
    "wof:placetype":"locality",
    "wof:population":411
},
  "geometry": {"coordinates":[-98.90917,21.55917],"type":"Point"}
}