{
  "type": "Feature",
  "properties": {
    "gn:admin1_code":"20",
    "gn:admin2_code":"24",
    "gn:asciiname":"Pena Prieta",
    "gn:country_code":"MX",
    "gn:dem":1075,
    "gn:feature_class":"P",
    "gn:feature_code":"PPL",
    "gn:name":"Pe\u00f1a Prieta",
    "gn:population":10,
    "gn:timezone":"America/Mexico_City",
    "iso:country":"MX",
    "name:und_x_variant":[
        "Pe\u00f1a Prieta"
    ],
    "wof:name":"Pena Prieta",
    "wof:placetype":"locality",
    "wof:population":10
},
  "geometry": {"coordinates":[-96.83278,17.99472],"type":"Point"}
}