{
  "type": "Feature",
  "properties": {
    "gn:admin1_code":"13",
    "gn:admin2_code":"84.0",
    "gn:asciiname":"Xhita Primero",
    "gn:country_code":"MX",
    "gn:dem":2166,
    "gn:feature_class":"P",
    "gn:feature_code":"PPL",
    "gn:name":"Xhit\u00e1 Primero",
    "gn:population":0,
    "gn:timezone":"America/Mexico_City",
    "iso:country":"MX",
    "name:spa_x_preferred":[
        "Xith\u00e1 Primero"
    ],
    "name:spa_x_variant":[
        "Xhit\u00e1 Primero"
    ],
    "wof:name":"Xhita Primero",
    "wof:placetype":"locality"
},
  "geometry": {"coordinates":[-99.31919000000001,20.62209],"type":"Point"}
}