{
  "type": "Feature",
  "properties": {
    "gn:admin1_code":"6.0",
    "gn:admin2_code":"65.0",
    "gn:asciiname":"Puerto Blanco",
    "gn:country_code":"MX",
    "gn:dem":1997,
    "gn:feature_class":"P",
    "gn:feature_code":"PPL",
    "gn:name":"Puerto Blanco",
    "gn:population":0,
    "gn:timezone":"America/Chihuahua",
    "iso:country":"MX",
    "name:spa_x_preferred":[
        "Puerto Blanco"
    ],
    "wof:name":"Puerto Blanco",
    "wof:placetype":"locality"
},
  "geometry": {"coordinates":[-108.05803,27.50493],"type":"Point"}
}