{
  "type": "Feature",
  "properties": {
    "gn:admin1_code":"14",
    "gn:admin2_code":"6",
    "gn:asciiname":"El Zoquite",
    "gn:country_code":"MX",
    "gn:dem":1351,
    "gn:feature_class":"P",
    "gn:feature_code":"PPL",
    "gn:name":"El Zoquite",
    "gn:population":31,
    "gn:timezone":"America/Mexico_City",
    "iso:country":"MX",
    "wof:name":"El Zoquite",
    "wof:placetype":"locality",
    "wof:population":31
},
  "geometry": {"coordinates":[-104.10666999999999,20.49694],"type":"Point"}
}