{
  "type": "Feature",
  "properties": {
    "gn:admin1_code":"5",
    "gn:admin2_code":"51.0",
    "gn:asciiname":"Los Cerritos",
    "gn:country_code":"MX",
    "gn:dem":34,
    "gn:feature_class":"P",
    "gn:feature_code":"PPL",
    "gn:name":"Los Cerritos",
    "gn:population":55,
    "gn:timezone":"America/Mexico_City",
    "iso:country":"MX",
    "wof:name":"Los Cerritos",
    "wof:placetype":"locality",
    "wof:population":55
},
  "geometry": {"coordinates":[-92.87860999999999,15.41889],"type":"Point"}
}