{
  "type": "Feature",
  "properties": {
    "gn:admin1_code":"30",
    "gn:admin2_code":"148.0",
    "gn:asciiname":"Altamira",
    "gn:country_code":"MX",
    "gn:dem":111,
    "gn:feature_class":"P",
    "gn:feature_code":"PPL",
    "gn:name":"Altamira",
    "gn:population":0,
    "gn:timezone":"America/Mexico_City",
    "iso:country":"MX",
    "name:spa_x_preferred":[
        "Altamira"
    ],
    "wof:name":"Altamira",
    "wof:placetype":"locality"
},
  "geometry": {"coordinates":[-96.44329999999999,18.97855],"type":"Point"}
}