{
  "type": "Feature",
  "properties": {
    "gn:admin1_code":"24",
    "gn:admin2_code":"22.0",
    "gn:asciiname":"La Carpa",
    "gn:country_code":"MX",
    "gn:dem":1636,
    "gn:feature_class":"P",
    "gn:feature_code":"PPL",
    "gn:name":"La Carpa",
    "gn:population":93,
    "gn:timezone":"America/Mexico_City",
    "iso:country":"MX",
    "wof:name":"La Carpa",
    "wof:placetype":"locality",
    "wof:population":93
},
  "geometry": {"coordinates":[-100.95056,22.69389],"type":"Point"}
}