{
  "type": "Feature",
  "properties": {
    "gn:admin1_code":"27",
    "gn:admin2_code":"8.0",
    "gn:asciiname":"Francisco Rueda",
    "gn:country_code":"MX",
    "gn:dem":15,
    "gn:feature_class":"P",
    "gn:feature_code":"PPL",
    "gn:name":"Francisco Rueda",
    "gn:population":1499,
    "gn:timezone":"America/Mexico_City",
    "iso:country":"MX",
    "wof:name":"Francisco Rueda",
    "wof:placetype":"locality",
    "wof:population":1499
},
  "geometry": {"coordinates":[-93.93389000000001,17.82917],"type":"Point"}
}