{
  "type": "Feature",
  "properties": {
    "gn:admin1_code":"10",
    "gn:admin2_code":"23.0",
    "gn:asciiname":"La Lajita",
    "gn:country_code":"MX",
    "gn:dem":2566,
    "gn:feature_class":"P",
    "gn:feature_code":"PPL",
    "gn:name":"La Lajita",
    "gn:population":0,
    "gn:timezone":"America/Monterrey",
    "iso:country":"MX",
    "name:spa_x_preferred":[
        "La Lajita"
    ],
    "wof:name":"La Lajita",
    "wof:placetype":"locality"
},
  "geometry": {"coordinates":[-105.68785,23.7391],"type":"Point"}
}