{
  "type": "Feature",
  "properties": {
    "gn:admin1_code":"6.0",
    "gn:admin2_code":"15.0",
    "gn:asciiname":"El Quemado",
    "gn:country_code":"MX",
    "gn:dem":1248,
    "gn:feature_class":"P",
    "gn:feature_code":"PPL",
    "gn:name":"El Quemado",
    "gn:population":3,
    "gn:timezone":"America/Chihuahua",
    "iso:country":"MX",
    "name:und_x_variant":[
        "Rancho El Quemado",
        "El Quemado"
    ],
    "wof:name":"El Quemado",
    "wof:placetype":"locality",
    "wof:population":3
},
  "geometry": {"coordinates":[-105.68778,30.19876],"type":"Point"}
}