{
  "type": "Feature",
  "properties": {
    "gn:admin1_code":"16",
    "gn:admin2_code":"20.0",
    "gn:asciiname":"Doctor Miguel Silva (San Guillermo)",
    "gn:country_code":"MX",
    "gn:dem":1848,
    "gn:feature_class":"P",
    "gn:feature_code":"PPL",
    "gn:name":"Doctor Miguel Silva (San Guillermo)",
    "gn:population":1014,
    "gn:timezone":"America/Mexico_City",
    "iso:country":"MX",
    "wof:name":"Doctor Miguel Silva (San Guillermo)",
    "wof:placetype":"locality",
    "wof:population":1014
},
  "geometry": {"coordinates":[-101.17417,19.96583],"type":"Point"}
}