{
  "type": "Feature",
  "properties": {
    "gn:admin1_code":"16",
    "gn:admin2_code":"50.0",
    "gn:asciiname":"La Mesa Chiquita (Las Mesitas)",
    "gn:country_code":"MX",
    "gn:dem":2609,
    "gn:feature_class":"P",
    "gn:feature_code":"PPL",
    "gn:name":"La Mesa Chiquita (Las Mesitas)",
    "gn:population":109,
    "gn:timezone":"America/Mexico_City",
    "iso:country":"MX",
    "wof:name":"La Mesa Chiquita (Las Mesitas)",
    "wof:placetype":"locality",
    "wof:population":109
},
  "geometry": {"coordinates":[-100.27500000000001,19.84667],"type":"Point"}
}