{
  "type": "Feature",
  "properties": {
    "gn:admin1_code":"12",
    "gn:admin2_code":"1",
    "gn:asciiname":"El Libramiento (La Gasera)",
    "gn:country_code":"MX",
    "gn:dem":174,
    "gn:feature_class":"P",
    "gn:feature_code":"PPL",
    "gn:name":"El Libramiento (La Gasera)",
    "gn:population":32,
    "gn:timezone":"America/Mexico_City",
    "iso:country":"MX",
    "wof:name":"El Libramiento (La Gasera)",
    "wof:placetype":"locality",
    "wof:population":32
},
  "geometry": {"coordinates":[-99.83138,16.98221],"type":"Point"}
}