{
  "type": "Feature",
  "properties": {
    "gn:admin1_code":"4.0",
    "gn:admin2_code":"3.0",
    "gn:asciiname":"Encarnacion",
    "gn:country_code":"MX",
    "gn:dem":32,
    "gn:feature_class":"P",
    "gn:feature_code":"PPL",
    "gn:name":"Encarnaci\u00f3n",
    "gn:population":0,
    "gn:timezone":"America/Merida",
    "iso:country":"MX",
    "name:spa_x_preferred":[
        "Encarnaci\u00f3n"
    ],
    "wof:name":"Encarnacion",
    "wof:placetype":"locality"
},
  "geometry": {"coordinates":[-91.01690000000001,18.49636],"type":"Point"}
}