{
  "type": "Feature",
  "properties": {
    "gn:admin1_code":"6.0",
    "gn:admin2_code":"10.0",
    "gn:asciiname":"La Varillera",
    "gn:country_code":"MX",
    "gn:dem":1721,
    "gn:feature_class":"P",
    "gn:feature_code":"PPL",
    "gn:name":"La Varillera",
    "gn:population":0,
    "gn:timezone":"America/Chihuahua",
    "iso:country":"MX",
    "name:spa_x_preferred":[
        "La Varillera"
    ],
    "wof:name":"La Varillera",
    "wof:placetype":"locality"
},
  "geometry": {"coordinates":[-107.35807,29.53997],"type":"Point"}
}