{
  "type": "Feature",
  "properties": {
    "gn:admin1_code":"5",
    "gn:admin2_code":"33.0",
    "gn:asciiname":"San Miguel la Sardina",
    "gn:country_code":"MX",
    "gn:dem":495,
    "gn:feature_class":"P",
    "gn:feature_code":"PPL",
    "gn:name":"San Miguel la Sardina",
    "gn:population":1106,
    "gn:timezone":"America/Mexico_City",
    "iso:country":"MX",
    "wof:name":"San Miguel la Sardina",
    "wof:placetype":"locality",
    "wof:population":1106
},
  "geometry": {"coordinates":[-93.35250000000001,17.29417],"type":"Point"}
}