{
  "type": "Feature",
  "properties": {
    "gn:admin1_code":"4",
    "gn:admin2_code":"3.0",
    "gn:asciiname":"San Jose (El Volantin)",
    "gn:country_code":"MX",
    "gn:dem":-3,
    "gn:feature_class":"P",
    "gn:feature_code":"PPL",
    "gn:name":"San Jos\u00e9 (El Volant\u00edn)",
    "gn:population":5,
    "gn:timezone":"America/Merida",
    "iso:country":"MX",
    "name:und_x_variant":[
        "San Jos\u00e9 (El Volant\u00edn)"
    ],
    "wof:name":"San Jose (El Volantin)",
    "wof:placetype":"locality",
    "wof:population":5
},
  "geometry": {"coordinates":[-91.17278,18.94361],"type":"Point"}
}