{
  "type": "Feature",
  "properties": {
    "gn:admin1_code":"6",
    "gn:admin2_code":"46",
    "gn:asciiname":"Rincon del Chapote",
    "gn:country_code":"MX",
    "gn:dem":1017,
    "gn:feature_class":"P",
    "gn:feature_code":"PPL",
    "gn:name":"Rinc\u00f3n del Chapote",
    "gn:population":12,
    "gn:timezone":"America/Chihuahua",
    "iso:country":"MX",
    "name:und_x_variant":[
        "Rinc\u00f3n del Chapote"
    ],
    "wof:name":"Rincon del Chapote",
    "wof:placetype":"locality",
    "wof:population":12
},
  "geometry": {"coordinates":[-107.60487999999999,26.553],"type":"Point"}
}