{
  "type": "Feature",
  "properties": {
    "gn:admin1_code":"31",
    "gn:admin2_code":"85.0",
    "gn:asciiname":"San Basilio",
    "gn:country_code":"MX",
    "gn:dem":23,
    "gn:feature_class":"P",
    "gn:feature_code":"PPL",
    "gn:name":"San Basilio",
    "gn:population":78,
    "gn:timezone":"America/Merida",
    "iso:country":"MX",
    "wof:name":"San Basilio",
    "wof:placetype":"locality",
    "wof:population":78
},
  "geometry": {"coordinates":[-88.14278,20.80528],"type":"Point"}
}