{
  "type": "Feature",
  "properties": {
    "gn:admin1_code":"5.0",
    "gn:asciiname":"Acapulco",
    "gn:country_code":"MX",
    "gn:dem":598,
    "gn:feature_class":"P",
    "gn:feature_code":"PPL",
    "gn:name":"Acapulco",
    "gn:population":0,
    "gn:timezone":"America/Mexico_City",
    "iso:country":"MX",
    "name:spa_x_preferred":[
        "Acapulco"
    ],
    "wof:name":"Acapulco",
    "wof:placetype":"locality"
},
  "geometry": {"coordinates":[-93.64165,16.5073],"type":"Point"}
}