{
  "type": "Feature",
  "properties": {
    "gn:admin1_code":"15",
    "gn:admin2_code":"39",
    "gn:asciiname":"Cabana de los Medina",
    "gn:country_code":"MX",
    "gn:dem":2340,
    "gn:feature_class":"P",
    "gn:feature_code":"PPL",
    "gn:name":"Caba\u00f1a de los Medina",
    "gn:population":26,
    "gn:timezone":"America/Mexico_City",
    "iso:country":"MX",
    "name:und_x_variant":[
        "Caba\u00f1a de los Medina"
    ],
    "wof:name":"Cabana de los Medina",
    "wof:placetype":"locality",
    "wof:population":26
},
  "geometry": {"coordinates":[-98.86165,19.38734],"type":"Point"}
}