{
  "type": "Feature",
  "properties": {
    "gn:admin1_code":"5",
    "gn:admin2_code":"117",
    "gn:asciiname":"El Nominado",
    "gn:country_code":"MX",
    "gn:dem":1721,
    "gn:feature_class":"P",
    "gn:feature_code":"PPL",
    "gn:name":"El Nominado",
    "gn:population":39,
    "gn:timezone":"America/Mexico_City",
    "iso:country":"MX",
    "wof:name":"El Nominado",
    "wof:placetype":"locality",
    "wof:population":39
},
  "geometry": {"coordinates":[-92.73222,15.65639],"type":"Point"}
}