{
  "type": "Feature",
  "properties": {
    "gn:admin1_code":"22",
    "gn:admin2_code":"11",
    "gn:asciiname":"Familia Mejia Uribe",
    "gn:country_code":"MX",
    "gn:dem":1929,
    "gn:feature_class":"P",
    "gn:feature_code":"PPL",
    "gn:name":"Familia Mej\u00eda Uribe",
    "gn:population":12,
    "gn:timezone":"America/Mexico_City",
    "iso:country":"MX",
    "name:und_x_variant":[
        "Familia Mej\u00eda Uribe"
    ],
    "wof:name":"Familia Mejia Uribe",
    "wof:placetype":"locality",
    "wof:population":12
},
  "geometry": {"coordinates":[-100.25749999999999,20.72194],"type":"Point"}
}