{
  "type": "Feature",
  "properties": {
    "gn:admin1_code":"5",
    "gn:admin2_code":"20.0",
    "gn:asciiname":"Nuevo San Juan",
    "gn:country_code":"MX",
    "gn:dem":680,
    "gn:feature_class":"P",
    "gn:feature_code":"PPL",
    "gn:name":"Nuevo San Juan",
    "gn:population":58,
    "gn:timezone":"America/Mexico_City",
    "iso:country":"MX",
    "wof:name":"Nuevo San Juan",
    "wof:placetype":"locality",
    "wof:population":58
},
  "geometry": {"coordinates":[-92.73444000000001,16.13389],"type":"Point"}
}