{
  "type": "Feature",
  "properties": {
    "gn:admin1_code":"32",
    "gn:admin2_code":"49.0",
    "gn:asciiname":"El Turbantillo",
    "gn:country_code":"MX",
    "gn:dem":1028,
    "gn:feature_class":"P",
    "gn:feature_code":"PPL",
    "gn:name":"El Turbantillo",
    "gn:population":0,
    "gn:timezone":"America/Mexico_City",
    "iso:country":"MX",
    "name:spa_x_preferred":[
        "El Turbantillo"
    ],
    "wof:name":"El Turbantillo",
    "wof:placetype":"locality"
},
  "geometry": {"coordinates":[-104.02891,22.63905],"type":"Point"}
}