{
  "type": "Feature",
  "properties": {
    "gn:admin1_code":"26",
    "gn:admin2_code":"18.0",
    "gn:asciiname":"La Carabina",
    "gn:country_code":"MX",
    "gn:dem":74,
    "gn:feature_class":"P",
    "gn:feature_code":"PPL",
    "gn:name":"La Carabina",
    "gn:population":130,
    "gn:timezone":"America/Hermosillo",
    "iso:country":"MX",
    "wof:name":"La Carabina",
    "wof:placetype":"locality",
    "wof:population":130
},
  "geometry": {"coordinates":[-109.8434,27.48101],"type":"Point"}
}