{
  "type": "Feature",
  "properties": {
    "gn:admin1_code":"25",
    "gn:admin2_code":"3.0",
    "gn:asciiname":"Higueras de Bayaca (Bayaca)",
    "gn:country_code":"MX",
    "gn:dem":213,
    "gn:feature_class":"P",
    "gn:feature_code":"PPL",
    "gn:name":"Higueras de Bayaca (Bayaca)",
    "gn:population":77,
    "gn:timezone":"America/Mazatlan",
    "iso:country":"MX",
    "wof:name":"Higueras de Bayaca (Bayaca)",
    "wof:placetype":"locality",
    "wof:population":77
},
  "geometry": {"coordinates":[-107.46218,25.17959],"type":"Point"}
}