{
  "type": "Feature",
  "properties": {
    "gn:admin1_code":"19.0",
    "gn:admin2_code":"45.0",
    "gn:asciiname":"Las Carretas",
    "gn:country_code":"MX",
    "gn:dem":456,
    "gn:feature_class":"P",
    "gn:feature_code":"PPL",
    "gn:name":"Las Carretas",
    "gn:population":0,
    "gn:timezone":"America/Monterrey",
    "iso:country":"MX",
    "name:spa_x_preferred":[
        "Las Carretas"
    ],
    "wof:name":"Las Carretas",
    "wof:placetype":"locality"
},
  "geometry": {"coordinates":[-100.30146000000001,26.03885],"type":"Point"}
}