{
  "type": "Feature",
  "properties": {
    "gn:admin1_code":"1",
    "gn:admin2_code":"5",
    "gn:asciiname":"Rancho Maria Antonieta",
    "gn:country_code":"MX",
    "gn:dem":1912,
    "gn:feature_class":"P",
    "gn:feature_code":"PPL",
    "gn:name":"Rancho Mar\u00eda Antonieta",
    "gn:population":11,
    "gn:timezone":"America/Mexico_City",
    "iso:country":"MX",
    "name:und_x_variant":[
        "Rancho Mar\u00eda Antonieta"
    ],
    "wof:name":"Rancho Maria Antonieta",
    "wof:placetype":"locality",
    "wof:population":11
},
  "geometry": {"coordinates":[-102.34556000000001,22.01111],"type":"Point"}
}