{
  "type": "Feature",
  "properties": {
    "gn:admin1_code":"30",
    "gn:admin2_code":"175",
    "gn:asciiname":"Tres Marias",
    "gn:country_code":"MX",
    "gn:dem":63,
    "gn:feature_class":"P",
    "gn:feature_code":"PPL",
    "gn:name":"Tres Mar\u00edas",
    "gn:population":15,
    "gn:timezone":"America/Mexico_City",
    "iso:country":"MX",
    "name:und_x_variant":[
        "Tres Mar\u00edas"
    ],
    "wof:name":"Tres Marias",
    "wof:placetype":"locality",
    "wof:population":15
},
  "geometry": {"coordinates":[-97.48721999999999,20.55639],"type":"Point"}
}