{
  "type": "Feature",
  "properties": {
    "gn:admin1_code":"30",
    "gn:admin2_code":"192.0",
    "gn:asciiname":"El Diamante",
    "gn:country_code":"MX",
    "gn:dem":16,
    "gn:feature_class":"P",
    "gn:feature_code":"PPL",
    "gn:name":"El Diamante",
    "gn:population":0,
    "gn:timezone":"America/Mexico_City",
    "iso:country":"MX",
    "wof:name":"El Diamante",
    "wof:placetype":"locality"
},
  "geometry": {"coordinates":[-96.69016000000001,20.0564],"type":"Point"}
}