{
  "type": "Feature",
  "properties": {
    "gn:admin1_code":"32",
    "gn:admin2_code":"49",
    "gn:asciiname":"El Pino",
    "gn:country_code":"MX",
    "gn:dem":1982,
    "gn:feature_class":"P",
    "gn:feature_code":"PPL",
    "gn:name":"El Pino",
    "gn:population":21,
    "gn:timezone":"America/Mexico_City",
    "iso:country":"MX",
    "name:ast_x_preferred":[
        "El Pino"
    ],
    "name:ceb_x_preferred":[
        "El Pino"
    ],
    "name:deu_x_preferred":[
        "El Pino"
    ],
    "name:glg_x_preferred":[
        "O Pino"
    ],
    "name:spa_x_preferred":[
        "El Pino"
    ],
    "name:srp_x_preferred":[
        "\u0415\u043b \u041f\u0438\u043d\u043e"
    ],
    "name:swe_x_preferred":[
        "El Pino"
    ],
    "wof:name":"El Pino",
    "wof:placetype":"locality",
    "wof:population":21
},
  "geometry": {"coordinates":[-103.75694,22.56167],"type":"Point"}
}