{
  "type": "Feature",
  "properties": {
    "gn:admin1_code":"6",
    "gn:admin2_code":"31.0",
    "gn:asciiname":"Las Tortugas",
    "gn:country_code":"MX",
    "gn:dem":2051,
    "gn:feature_class":"P",
    "gn:feature_code":"PPL",
    "gn:name":"Las Tortugas",
    "gn:population":6,
    "gn:timezone":"America/Chihuahua",
    "iso:country":"MX",
    "wof:name":"Las Tortugas",
    "wof:placetype":"locality",
    "wof:population":6
},
  "geometry": {"coordinates":[-107.34327999999999,28.47129],"type":"Point"}
}