{
  "type": "Feature",
  "properties": {
    "gn:admin1_code":"5.0",
    "gn:admin2_code":"19.0",
    "gn:asciiname":"El Sabinal",
    "gn:country_code":"MX",
    "gn:dem":1554,
    "gn:feature_class":"P",
    "gn:feature_code":"PPL",
    "gn:name":"El Sabinal",
    "gn:population":0,
    "gn:timezone":"America/Mexico_City",
    "iso:country":"MX",
    "name:spa_x_preferred":[
        "El Sabinal"
    ],
    "wof:name":"El Sabinal",
    "wof:placetype":"locality"
},
  "geometry": {"coordinates":[-92.04282000000001,16.18749],"type":"Point"}
}