{
  "type": "Feature",
  "properties": {
    "gn:admin1_code":"14",
    "gn:admin2_code":"120.0",
    "gn:asciiname":"Rancho los Amigos",
    "gn:country_code":"MX",
    "gn:dem":1675,
    "gn:feature_class":"P",
    "gn:feature_code":"PPL",
    "gn:name":"Rancho los Amigos",
    "gn:population":5,
    "gn:timezone":"America/Mexico_City",
    "iso:country":"MX",
    "wof:name":"Rancho los Amigos",
    "wof:placetype":"locality",
    "wof:population":5
},
  "geometry": {"coordinates":[-103.56332999999999,20.76694],"type":"Point"}
}