{
  "type": "Feature",
  "properties": {
    "gn:admin1_code":"7",
    "gn:admin2_code":"37.0",
    "gn:asciiname":"San Francisco",
    "gn:country_code":"MX",
    "gn:dem":374,
    "gn:feature_class":"P",
    "gn:feature_code":"PPL",
    "gn:name":"San Francisco",
    "gn:population":5,
    "gn:timezone":"America/Monterrey",
    "iso:country":"MX",
    "name:spa_x_preferred":[
        "San Francisco"
    ],
    "wof:name":"San Francisco",
    "wof:placetype":"locality",
    "wof:population":5
},
  "geometry": {"coordinates":[-100.73600999999999,28.2519],"type":"Point"}
}