{
  "type": "Feature",
  "properties": {
    "gn:admin1_code":"14",
    "gn:admin2_code":"6.0",
    "gn:asciiname":"El Arco",
    "gn:country_code":"MX",
    "gn:dem":1429,
    "gn:feature_class":"P",
    "gn:feature_code":"PPL",
    "gn:name":"El Arco",
    "gn:population":117,
    "gn:timezone":"America/Mexico_City",
    "iso:country":"MX",
    "name:ceb_x_preferred":[
        "El Arco"
    ],
    "name:spa_x_preferred":[
        "El Arco"
    ],
    "name:swe_x_preferred":[
        "El Arco"
    ],
    "wof:name":"El Arco",
    "wof:placetype":"locality",
    "wof:population":117
},
  "geometry": {"coordinates":[-104.07333,20.60944],"type":"Point"}
}