{
  "type": "Feature",
  "properties": {
    "gn:admin1_code":"5",
    "gn:admin2_code":"100.0",
    "gn:asciiname":"Tres Arroyos",
    "gn:country_code":"MX",
    "gn:dem":1284,
    "gn:feature_class":"P",
    "gn:feature_code":"PPL",
    "gn:name":"Tres Arroyos",
    "gn:population":5,
    "gn:timezone":"America/Mexico_City",
    "iso:country":"MX",
    "wof:name":"Tres Arroyos",
    "wof:placetype":"locality",
    "wof:population":5
},
  "geometry": {"coordinates":[-92.34056,17.34056],"type":"Point"}
}