{
  "type": "Feature",
  "properties": {
    "gn:admin1_code":"5",
    "gn:admin2_code":"100.0",
    "gn:asciiname":"Tres Arroyos",
    "gn:country_code":"MX",
    "gn:dem":1284,
    "gn:feature_class":"P",
    "gn:feature_code":"PPL",
    "gn:name":"Tres Arroyos",
    "gn:population":5,
    "gn:timezone":"America/Mexico_City",
    "iso:country":"MX",
    "name:ara_x_preferred":[
        "\u062a\u0631\u064a\u0633 \u0622\u0631\u0648\u064a\u0648\u0633"
    ],
    "name:azb_x_preferred":[
        "\u062a\u0631\u0633 \u0622\u0631\u0648\u06cc\u0648\u0633"
    ],
    "name:ces_x_preferred":[
        "Tres Arroyos"
    ],
    "name:dan_x_preferred":[
        "Tres Arroyos"
    ],
    "name:fas_x_preferred":[
        "\u062a\u0631\u0633 \u0622\u0631\u0648\u06cc\u0648\u0633"
    ],
    "name:fin_x_preferred":[
        "Tres Arroyos"
    ],
    "name:fra_x_preferred":[
        "Tres Arroyos"
    ],
    "name:ind_x_preferred":[
        "Tres Arroyos"
    ],
    "name:ita_x_preferred":[
        "Tres Arroyos"
    ],
    "name:lit_x_preferred":[
        "Tres Arojosas"
    ],
    "name:nld_x_preferred":[
        "Tres Arroyos"
    ],
    "name:nor_x_preferred":[
        "Tres Arroyos"
    ],
    "name:pol_x_preferred":[
        "Tres Arroyos"
    ],
    "name:sco_x_preferred":[
        "Tres Arroyos"
    ],
    "name:spa_x_preferred":[
        "Tres Arroyos"
    ],
    "name:zho_x_preferred":[
        "\u7279\u96f7\u65af\u963f\u7f85\u7d04\u65af"
    ],
    "wof:name":"Tres Arroyos",
    "wof:placetype":"locality",
    "wof:population":5
},
  "geometry": {"coordinates":[-92.34056,17.34056],"type":"Point"}
}