{
  "type": "Feature",
  "properties": {
    "gn:admin1_code":"30.0",
    "gn:admin2_code":"151.0",
    "gn:asciiname":"Rancho Nuevo",
    "gn:country_code":"MX",
    "gn:dem":20,
    "gn:feature_class":"P",
    "gn:feature_code":"PPL",
    "gn:name":"Rancho Nuevo",
    "gn:population":0,
    "gn:timezone":"America/Mexico_City",
    "iso:country":"MX",
    "name:spa_x_preferred":[
        "Rancho Nuevo"
    ],
    "name:spa_x_variant":[
        "San Enrique"
    ],
    "wof:name":"Rancho Nuevo",
    "wof:placetype":"locality",
    "wof:population":5
},
  "geometry": {"coordinates":[-97.51635,21.28324],"type":"Point"}
}