{
  "type": "Feature",
  "properties": {
    "gn:admin1_code":"1",
    "gn:admin2_code":"3",
    "gn:asciiname":"Zaragoza I",
    "gn:country_code":"MX",
    "gn:dem":1763,
    "gn:feature_class":"P",
    "gn:feature_code":"PPL",
    "gn:name":"Zaragoza I",
    "gn:population":32,
    "gn:timezone":"America/Mexico_City",
    "iso:country":"MX",
    "wof:name":"Zaragoza I",
    "wof:placetype":"locality",
    "wof:population":32
},
  "geometry": {"coordinates":[-102.68944,21.96833],"type":"Point"}
}