{
  "type": "Feature",
  "properties": {
    "gn:admin1_code":"4",
    "gn:admin2_code":"7.0",
    "gn:asciiname":"Laguna Blanca",
    "gn:country_code":"MX",
    "gn:dem":6,
    "gn:feature_class":"P",
    "gn:feature_code":"PPL",
    "gn:name":"Laguna Blanca",
    "gn:population":5,
    "gn:timezone":"America/Merida",
    "iso:country":"MX",
    "name:ceb_x_preferred":[
        "Laguna Blanca"
    ],
    "name:deu_x_preferred":[
        "Laguna Blanca"
    ],
    "name:fin_x_preferred":[
        "Laguna Blanca"
    ],
    "name:fra_x_preferred":[
        "Laguna Blanca"
    ],
    "name:ita_x_preferred":[
        "Laguna Blanca"
    ],
    "name:nld_x_preferred":[
        "Laguna Blanca"
    ],
    "name:pol_x_preferred":[
        "Laguna Blanca"
    ],
    "name:por_x_preferred":[
        "Laguna Blanca"
    ],
    "name:spa_x_preferred":[
        "Laguna Blanca"
    ],
    "name:swe_x_preferred":[
        "Laguna Blanca"
    ],
    "wof:name":"Laguna Blanca",
    "wof:placetype":"locality",
    "wof:population":5
},
  "geometry": {"coordinates":[-91.77306,18.11056],"type":"Point"}
}