{
  "type": "Feature",
  "properties": {
    "gn:admin1_code":"14",
    "gn:admin2_code":"41.0",
    "gn:asciiname":"Cerrito Alto",
    "gn:country_code":"MX",
    "gn:dem":2068,
    "gn:feature_class":"P",
    "gn:feature_code":"PPL",
    "gn:name":"Cerrito Alto",
    "gn:population":0,
    "gn:timezone":"America/Mexico_City",
    "iso:country":"MX",
    "name:spa_x_preferred":[
        "Cerrito Alto"
    ],
    "wof:name":"Cerrito Alto",
    "wof:placetype":"locality"
},
  "geometry": {"coordinates":[-103.29170000000001,22.34668],"type":"Point"}
}