{
  "type": "Feature",
  "properties": {
    "gn:admin1_code":"14",
    "gn:admin2_code":"123.0",
    "gn:asciiname":"La Vibora",
    "gn:country_code":"MX",
    "gn:dem":1551,
    "gn:feature_class":"P",
    "gn:feature_code":"PPL",
    "gn:name":"La Vibora",
    "gn:population":0,
    "gn:timezone":"America/Mexico_City",
    "iso:country":"MX",
    "name:deu_x_preferred":[
        "La Vibora"
    ],
    "name:fra_x_preferred":[
        "La Vibora"
    ],
    "name:nld_x_preferred":[
        "La Vibora"
    ],
    "wof:name":"La Vibora",
    "wof:placetype":"locality"
},
  "geometry": {"coordinates":[-102.81314,20.4781],"type":"Point"}
}