{
  "type": "Feature",
  "properties": {
    "gn:admin1_code":"17",
    "gn:admin2_code":"25.0",
    "gn:asciiname":"Cuevillas",
    "gn:country_code":"MX",
    "gn:dem":1011,
    "gn:feature_class":"P",
    "gn:feature_code":"PPL",
    "gn:name":"Cuevillas",
    "gn:population":0,
    "gn:timezone":"America/Mexico_City",
    "iso:country":"MX",
    "wof:name":"Cuevillas",
    "wof:placetype":"locality"
},
  "geometry": {"coordinates":[-99.09999999999999,18.46667],"type":"Point"}
}