{
  "type": "Feature",
  "properties": {
    "gn:admin1_code":"30",
    "gn:admin2_code":"61",
    "gn:asciiname":"Ambrosio Martinez Antonio",
    "gn:country_code":"MX",
    "gn:dem":42,
    "gn:feature_class":"P",
    "gn:feature_code":"PPL",
    "gn:name":"Ambrosio Mart\u00ednez Antonio",
    "gn:population":10,
    "gn:timezone":"America/Mexico_City",
    "iso:country":"MX",
    "name:und_x_variant":[
        "Ambrosio Mart\u00ednez Antonio"
    ],
    "wof:name":"Ambrosio Martinez Antonio",
    "wof:placetype":"locality",
    "wof:population":10
},
  "geometry": {"coordinates":[-94.08333,17.67361],"type":"Point"}
}