{
  "type": "Feature",
  "properties": {
    "gn:admin1_code":"25.0",
    "gn:admin2_code":"10.0",
    "gn:asciiname":"Jecolua",
    "gn:country_code":"MX",
    "gn:dem":92,
    "gn:feature_class":"P",
    "gn:feature_code":"PPL",
    "gn:name":"Jecolua",
    "gn:population":0,
    "gn:timezone":"America/Mazatlan",
    "iso:country":"MX",
    "name:spa_x_preferred":[
        "Jecolua"
    ],
    "name:und_x_variant":[
        "Presa Jecol\u00faa"
    ],
    "wof:name":"Jecolua",
    "wof:placetype":"locality"
},
  "geometry": {"coordinates":[-108.67749999999999,26.29817],"type":"Point"}
}