{
  "type": "Feature",
  "properties": {
    "gn:admin1_code":"24",
    "gn:admin2_code":"19.0",
    "gn:asciiname":"Chimulco",
    "gn:country_code":"MX",
    "gn:dem":734,
    "gn:feature_class":"P",
    "gn:feature_code":"PPL",
    "gn:name":"Chimulco",
    "gn:population":0,
    "gn:timezone":"America/Mexico_City",
    "iso:country":"MX",
    "wof:name":"Chimulco",
    "wof:placetype":"locality"
},
  "geometry": {"coordinates":[-99.56667,21.68333],"type":"Point"}
}