{
  "type": "Feature",
  "properties": {
    "gn:admin1_code":"4",
    "gn:admin2_code":"3.0",
    "gn:asciiname":"La Uvita",
    "gn:country_code":"MX",
    "gn:dem":-1,
    "gn:feature_class":"P",
    "gn:feature_code":"PPL",
    "gn:name":"La Uvita",
    "gn:population":0,
    "gn:timezone":"America/Merida",
    "iso:country":"MX",
    "name:ceb_x_preferred":[
        "La Uvita"
    ],
    "name:fra_x_preferred":[
        "La Uvita"
    ],
    "name:ita_x_preferred":[
        "La Uvita"
    ],
    "name:kat_x_preferred":[
        "\u10da\u10d0-\u10e3\u10d5\u10d8\u10e2\u10d0"
    ],
    "name:msa_x_preferred":[
        "La Uvita"
    ],
    "name:nld_x_preferred":[
        "La Uvita"
    ],
    "name:por_x_preferred":[
        "La Uvita"
    ],
    "name:rus_x_preferred":[
        "\u041b\u0430-\u0423\u0432\u0438\u0442\u0430"
    ],
    "name:sco_x_preferred":[
        "La Uvita"
    ],
    "name:spa_x_preferred":[
        "La Uvita"
    ],
    "name:swe_x_preferred":[
        "La Uvita"
    ],
    "name:tgl_x_preferred":[
        "La Uvita"
    ],
    "name:urd_x_preferred":[
        "\u0644\u0627 \u06cc\u0648\u0648\u06cc\u0679\u0627"
    ],
    "name:vie_x_preferred":[
        "La Uvita"
    ],
    "name:war_x_preferred":[
        "La Uvita"
    ],
    "name:zho_x_preferred":[
        "\u62c9\u70cf\u7dad\u5854"
    ],
    "wof:name":"La Uvita",
    "wof:placetype":"locality"
},
  "geometry": {"coordinates":[-92.42766,18.65847],"type":"Point"}
}