{
  "type": "Feature",
  "properties": {
    "gn:admin1_code":"4",
    "gn:admin2_code":"3.0",
    "gn:asciiname":"La Uvita",
    "gn:country_code":"MX",
    "gn:dem":-1,
    "gn:feature_class":"P",
    "gn:feature_code":"PPL",
    "gn:name":"La Uvita",
    "gn:population":0,
    "gn:timezone":"America/Merida",
    "iso:country":"MX",
    "name:spa_x_preferred":[
        "La Uvita"
    ],
    "wof:name":"La Uvita",
    "wof:placetype":"locality"
},
  "geometry": {"coordinates":[-92.42766,18.65847],"type":"Point"}
}