{
  "type": "Feature",
  "properties": {
    "gn:admin1_code":"11.0",
    "gn:admin2_code":"18.0",
    "gn:asciiname":"El Armadillo",
    "gn:country_code":"MX",
    "gn:dem":1735,
    "gn:feature_class":"P",
    "gn:feature_code":"PPL",
    "gn:name":"El Armadillo",
    "gn:population":0,
    "gn:timezone":"America/Mexico_City",
    "iso:country":"MX",
    "name:spa_x_preferred":[
        "El Armadillo"
    ],
    "wof:name":"El Armadillo",
    "wof:placetype":"locality"
},
  "geometry": {"coordinates":[-101.04025,20.28187],"type":"Point"}
}