{
  "type": "Feature",
  "properties": {
    "gn:admin1_code":"6",
    "gn:admin2_code":"7.0",
    "gn:asciiname":"Piedra Agujerada",
    "gn:country_code":"MX",
    "gn:dem":2235,
    "gn:feature_class":"P",
    "gn:feature_code":"PPL",
    "gn:name":"Piedra Agujerada",
    "gn:population":64,
    "gn:timezone":"America/Chihuahua",
    "iso:country":"MX",
    "wof:name":"Piedra Agujerada",
    "wof:placetype":"locality",
    "wof:population":64
},
  "geometry": {"coordinates":[-106.62653,26.73569],"type":"Point"}
}