{
  "type": "Feature",
  "properties": {
    "gn:admin1_code":"19",
    "gn:admin2_code":"22.0",
    "gn:asciiname":"San Felipe de Jesus",
    "gn:country_code":"MX",
    "gn:dem":242,
    "gn:feature_class":"P",
    "gn:feature_code":"PPL",
    "gn:name":"San Felipe de Jes\u00fas",
    "gn:population":5,
    "gn:timezone":"America/Monterrey",
    "iso:country":"MX",
    "name:und_x_variant":[
        "San Felipe de Jes\u00fas"
    ],
    "wof:name":"San Felipe de Jesus",
    "wof:placetype":"locality",
    "wof:population":5
},
  "geometry": {"coordinates":[-99.58168000000001,25.3834],"type":"Point"}
}