{
  "type": "Feature",
  "properties": {
    "gn:admin1_code":"5.0",
    "gn:admin2_code":"107.0",
    "gn:asciiname":"El Salvador",
    "gn:country_code":"MX",
    "gn:dem":589,
    "gn:feature_class":"P",
    "gn:feature_code":"PPL",
    "gn:name":"El Salvador",
    "gn:population":0,
    "gn:timezone":"America/Mexico_City",
    "iso:country":"MX",
    "name:spa_x_preferred":[
        "El Salvador"
    ],
    "wof:name":"El Salvador",
    "wof:placetype":"locality"
},
  "geometry": {"coordinates":[-93.18577000000001,16.20802999999999],"type":"Point"}
}