{
  "type": "Feature",
  "properties": {
    "gn:admin1_code":"18",
    "gn:admin2_code":"4",
    "gn:asciiname":"Agua Azul",
    "gn:country_code":"MX",
    "gn:dem":368,
    "gn:feature_class":"P",
    "gn:feature_code":"PPL",
    "gn:name":"Agua Azul",
    "gn:population":13,
    "gn:timezone":"America/Mazatlan",
    "iso:country":"MX",
    "wof:name":"Agua Azul",
    "wof:placetype":"locality",
    "wof:population":13
},
  "geometry": {"coordinates":[-105.02889,21.21917],"type":"Point"}
}