{
  "type": "Feature",
  "properties": {
    "gn:admin1_code":"3",
    "gn:admin2_code":"8.0",
    "gn:asciiname":"El Tio Juan",
    "gn:country_code":"MX",
    "gn:dem":119,
    "gn:feature_class":"P",
    "gn:feature_code":"PPL",
    "gn:name":"El T\u00edo Juan",
    "gn:population":7,
    "gn:timezone":"America/Mazatlan",
    "iso:country":"MX",
    "name:und_x_variant":[
        "El T\u00edo Juan"
    ],
    "wof:name":"El Tio Juan",
    "wof:placetype":"locality",
    "wof:population":7
},
  "geometry": {"coordinates":[-109.71545,23.18854],"type":"Point"}
}