{
  "type": "Feature",
  "properties": {
    "gn:admin1_code":"27",
    "gn:admin2_code":"2.0",
    "gn:asciiname":"Azucena Quinta Seccion",
    "gn:country_code":"MX",
    "gn:dem":8,
    "gn:feature_class":"P",
    "gn:feature_code":"PPL",
    "gn:name":"Azucena Quinta Secci\u00f3n",
    "gn:population":0,
    "gn:timezone":"America/Mexico_City",
    "iso:country":"MX",
    "name:spa_x_preferred":[
        "Azucena Quinta Secci\u00f3n"
    ],
    "wof:name":"Azucena Quinta Seccion",
    "wof:placetype":"locality"
},
  "geometry": {"coordinates":[-93.61981,18.26991],"type":"Point"}
}