{
  "type": "Feature",
  "properties": {
    "iso:country":"MX",
    "name:eng_x_preferred":[
        "Fracc Jardin"
    ],
    "name:spa_x_preferred":[
        "Fracc Jardin"
    ],
    "qs:gn_local":0,
    "qs:local_max":20,
    "qs:local_sum":20,
    "qs:localhoods":1,
    "qs:name":"Fracc Jardin",
    "qs:name_adm0":"M\u00e9xico",
    "qs:name_adm1":"Tamaulipas",
    "qs:name_adm2":"Miguel Aleman",
    "qs:name_local":"Ciudad Miguel Alem\u00e1n",
    "qs:photo_max":12,
    "qs:photo_sum":20,
    "qs:placetype":"Suburb",
    "qs:quad_count":4,
    "qs:woe_adm0":23424900,
    "qs:woe_adm1":2346291,
    "qs:woe_adm2":12601656,
    "qs:woe_lau":0,
    "qs:woe_local":116563,
    "qs:woe_ver":"7.10.0",
    "wof:lang":[
        "spa"
    ],
    "wof:name":"Fracc Jardin",
    "wof:placetype":"neighbourhood"
},
  "geometry": {"coordinates":[-99.02087400000001,26.404909],"type":"Point"}
}