{
  "type": "Feature",
  "properties": {
    "gn:admin1_code":"11",
    "gn:admin2_code":"8",
    "gn:asciiname":"El Chamizal",
    "gn:country_code":"MX",
    "gn:dem":1726,
    "gn:feature_class":"P",
    "gn:feature_code":"PPL",
    "gn:name":"El Chamizal",
    "gn:population":22,
    "gn:timezone":"America/Mexico_City",
    "iso:country":"MX",
    "wof:name":"El Chamizal",
    "wof:placetype":"locality",
    "wof:population":22
},
  "geometry": {"coordinates":[-101.96222,20.75722],"type":"Point"}
}