{
  "type": "Feature",
  "properties": {
    "gn:admin1_code":"11.0",
    "gn:admin2_code":"30.0",
    "gn:asciiname":"Santelices",
    "gn:country_code":"MX",
    "gn:dem":2072,
    "gn:feature_class":"P",
    "gn:feature_code":"PPL",
    "gn:name":"Santelices",
    "gn:population":0,
    "gn:timezone":"America/Mexico_City",
    "iso:country":"MX",
    "name:spa_x_preferred":[
        "Santelices"
    ],
    "name:spa_x_variant":[
        "Los Santelices"
    ],
    "wof:name":"Santelices",
    "wof:placetype":"locality"
},
  "geometry": {"coordinates":[-101.21131,21.44313],"type":"Point"}
}