{
  "type": "Feature",
  "properties": {
    "gn:admin1_code":"18",
    "gn:admin2_code":"13.0",
    "gn:asciiname":"Tequilita",
    "gn:country_code":"MX",
    "gn:dem":911,
    "gn:feature_class":"P",
    "gn:feature_code":"PPL",
    "gn:name":"Tequilita",
    "gn:population":0,
    "gn:timezone":"America/Mazatlan",
    "iso:country":"MX",
    "wof:name":"Tequilita",
    "wof:placetype":"locality"
},
  "geometry": {"coordinates":[-104.79828999999999,21.08715],"type":"Point"}
}