{
  "type": "Feature",
  "properties": {
    "gn:admin1_code":"16",
    "gn:admin2_code":"2",
    "gn:asciiname":"La Canoyita (Canoitas)",
    "gn:country_code":"MX",
    "gn:dem":843,
    "gn:feature_class":"P",
    "gn:feature_code":"PPL",
    "gn:name":"La Canoyita (Cano\u00edtas)",
    "gn:population":12,
    "gn:timezone":"America/Mexico_City",
    "iso:country":"MX",
    "name:und_x_variant":[
        "La Canoyita (Cano\u00edtas)"
    ],
    "wof:name":"La Canoyita (Canoitas)",
    "wof:placetype":"locality",
    "wof:population":12
},
  "geometry": {"coordinates":[-102.81083,18.80361],"type":"Point"}
}