{
  "type": "Feature",
  "properties": {
    "gn:admin1_code":"32.0",
    "gn:asciiname":"La Boquilla",
    "gn:country_code":"MX",
    "gn:dem":1560,
    "gn:feature_class":"P",
    "gn:feature_code":"PPL",
    "gn:name":"La Boquilla",
    "gn:population":0,
    "gn:timezone":"America/Mexico_City",
    "iso:country":"MX",
    "name:spa_x_preferred":[
        "La Boquilla"
    ],
    "wof:name":"La Boquilla",
    "wof:placetype":"locality"
},
  "geometry": {"coordinates":[-102.91433000000001,21.65311],"type":"Point"}
}