{
  "type": "Feature",
  "properties": {
    "gn:admin1_code":"31",
    "gn:admin2_code":"69.0",
    "gn:asciiname":"Xhua",
    "gn:country_code":"MX",
    "gn:dem":19,
    "gn:feature_class":"P",
    "gn:feature_code":"PPL",
    "gn:name":"Xhu\u00e1",
    "gn:population":0,
    "gn:timezone":"America/Merida",
    "iso:country":"MX",
    "name:spa_x_preferred":[
        "Xhu\u00e1"
    ],
    "wof:name":"Xhua",
    "wof:placetype":"locality"
},
  "geometry": {"coordinates":[-88.99695,20.71159],"type":"Point"}
}