{
  "type": "Feature",
  "properties": {
    "gn:admin1_code":"32",
    "gn:admin2_code":"36.0",
    "gn:asciiname":"El Nuevo Mundo",
    "gn:country_code":"MX",
    "gn:dem":2128,
    "gn:feature_class":"P",
    "gn:feature_code":"PPL",
    "gn:name":"El Nuevo Mundo",
    "gn:population":0,
    "gn:timezone":"America/Mexico_City",
    "iso:country":"MX",
    "name:und_x_variant":[
        "Nuevo Mundo"
    ],
    "wof:name":"El Nuevo Mundo",
    "wof:placetype":"locality"
},
  "geometry": {"coordinates":[-102.20469,22.73453],"type":"Point"}
}