{
  "type": "Feature",
  "properties": {
    "gn:admin1_code":"30",
    "gn:admin2_code":"178.0",
    "gn:asciiname":"El Limon (San Jose de Chazaro)",
    "gn:country_code":"MX",
    "gn:dem":9,
    "gn:feature_class":"P",
    "gn:feature_code":"PPL",
    "gn:name":"El Lim\u00f3n (San Jos\u00e9 de Ch\u00e1zaro)",
    "gn:population":75,
    "gn:timezone":"America/Mexico_City",
    "iso:country":"MX",
    "name:und_x_variant":[
        "El Lim\u00f3n (San Jos\u00e9 de Ch\u00e1zaro)"
    ],
    "wof:name":"El Limon (San Jose de Chazaro)",
    "wof:placetype":"locality",
    "wof:population":75
},
  "geometry": {"coordinates":[-95.56610999999999,18.37306],"type":"Point"}
}