{
  "type": "Feature",
  "properties": {
    "gn:admin1_code":"14.0",
    "gn:admin2_code":"115.0",
    "gn:asciiname":"El Toloache",
    "gn:country_code":"MX",
    "gn:dem":1523,
    "gn:feature_class":"P",
    "gn:feature_code":"PPL",
    "gn:name":"El Toloache",
    "gn:population":0,
    "gn:timezone":"America/Mexico_City",
    "iso:country":"MX",
    "name:spa_x_preferred":[
        "El Toloache"
    ],
    "wof:name":"El Toloache",
    "wof:placetype":"locality"
},
  "geometry": {"coordinates":[-103.79505,22.03617],"type":"Point"}
}