{
  "type": "Feature",
  "properties": {
    "gn:admin1_code":"10",
    "gn:admin2_code":"14.0",
    "gn:asciiname":"Agua Verde",
    "gn:country_code":"MX",
    "gn:dem":903,
    "gn:feature_class":"P",
    "gn:feature_code":"PPL",
    "gn:name":"Agua Verde",
    "gn:population":71,
    "gn:timezone":"America/Monterrey",
    "iso:country":"MX",
    "wof:name":"Agua Verde",
    "wof:placetype":"locality",
    "wof:population":71
},
  "geometry": {"coordinates":[-104.62139000000001,22.74306],"type":"Point"}
}