{
  "type": "Feature",
  "properties": {
    "gn:admin1_code":"27",
    "gn:admin2_code":"2.0",
    "gn:asciiname":"La Peninsula",
    "gn:country_code":"MX",
    "gn:dem":28,
    "gn:feature_class":"P",
    "gn:feature_code":"PPL",
    "gn:name":"La Pen\u00ednsula",
    "gn:population":1516,
    "gn:timezone":"America/Mexico_City",
    "iso:country":"MX",
    "name:und_x_variant":[
        "La Pen\u00ednsula"
    ],
    "wof:name":"La Peninsula",
    "wof:placetype":"locality",
    "wof:population":1516
},
  "geometry": {"coordinates":[-93.36148,17.94347],"type":"Point"}
}