{
  "type": "Feature",
  "properties": {
    "gn:admin1_code":"6.0",
    "gn:admin2_code":"21.0",
    "gn:asciiname":"Cuatro Vientos",
    "gn:country_code":"MX",
    "gn:dem":1187,
    "gn:feature_class":"P",
    "gn:feature_code":"PPL",
    "gn:name":"Cuatro Vientos",
    "gn:population":4,
    "gn:timezone":"America/Chihuahua",
    "iso:country":"MX",
    "name:cat_x_preferred":[
        "Cuatro Vientos"
    ],
    "name:eus_x_preferred":[
        "Cuatro Vientos"
    ],
    "name:por_x_preferred":[
        "Cuatro Vientos"
    ],
    "name:spa_x_preferred":[
        "Cuatro Vientos"
    ],
    "name:und_x_variant":[
        "Colonia Morelos",
        "Cuatro Vientos"
    ],
    "wof:name":"Cuatro Vientos",
    "wof:placetype":"locality",
    "wof:population":4
},
  "geometry": {"coordinates":[-105.39243,28.24231],"type":"Point"}
}