{
  "type": "Feature",
  "properties": {
    "gn:admin1_code":"25",
    "gn:admin2_code":"10",
    "gn:asciiname":"Las Praderas",
    "gn:country_code":"MX",
    "gn:dem":134,
    "gn:feature_class":"P",
    "gn:feature_code":"PPL",
    "gn:name":"Las Praderas",
    "gn:population":35,
    "gn:timezone":"America/Mazatlan",
    "iso:country":"MX",
    "wof:name":"Las Praderas",
    "wof:placetype":"locality",
    "wof:population":35
},
  "geometry": {"coordinates":[-108.90373,26.40763],"type":"Point"}
}