{
  "type": "Feature",
  "properties": {
    "iso:country":"MX",
    "name:spa_x_preferred":[
        "Barrio San Miguel"
    ],
    "qs:gn_adm0_cc":"MX",
    "qs:gn_local":3530757,
    "qs:gn_nam_loc":"cholula",
    "qs:gn_namadm1":"21",
    "qs:local_max":137,
    "qs:local_sum":404,
    "qs:localhoods":5,
    "qs:name":"Barrio San Miguel",
    "qs:name_adm0":"M\u00e9xico",
    "qs:name_adm1":"Puebla",
    "qs:name_adm2":"San Andres Cholula",
    "qs:name_local":"Cholula",
    "qs:photo_max":26,
    "qs:photo_sum":26,
    "qs:placetype":"Suburb",
    "qs:quad_count":1,
    "qs:woe_adm0":23424900,
    "qs:woe_adm1":2346284,
    "qs:woe_adm2":12601346,
    "qs:woe_lau":0,
    "qs:woe_local":116182,
    "qs:woe_ver":"7.10.0",
    "wof:lang":[
        "spa"
    ],
    "wof:name":"Barrio San Miguel",
    "wof:placetype":"neighbourhood"
},
  "geometry": {"coordinates":[-98.30429100000001,19.055628],"type":"Point"}
}