{
  "type": "Feature",
  "properties": {
    "gn:admin1_code":"6.0",
    "gn:admin2_code":"40.0",
    "gn:asciiname":"Cebadilla",
    "gn:country_code":"MX",
    "gn:dem":2203,
    "gn:feature_class":"P",
    "gn:feature_code":"PPL",
    "gn:name":"Cebadilla",
    "gn:population":0,
    "gn:timezone":"America/Chihuahua",
    "iso:country":"MX",
    "name:spa_x_preferred":[
        "Cebadilla"
    ],
    "wof:name":"Cebadilla",
    "wof:placetype":"locality"
},
  "geometry": {"coordinates":[-108.1387,29.30822],"type":"Point"}
}