{
  "type": "Feature",
  "properties": {
    "gn:admin1_code":"8.0",
    "gn:admin2_code":"9.0",
    "gn:asciiname":"El Tecuanillo",
    "gn:country_code":"MX",
    "gn:dem":9,
    "gn:feature_class":"P",
    "gn:feature_code":"PPL",
    "gn:name":"El Tecuanillo",
    "gn:population":0,
    "gn:timezone":"America/Mexico_City",
    "iso:country":"MX",
    "wof:name":"El Tecuanillo",
    "wof:placetype":"locality"
},
  "geometry": {"coordinates":[-103.89442,18.81097],"type":"Point"}
}