{
  "type": "Feature",
  "properties": {
    "gn:admin1_code":"2",
    "gn:admin2_code":"5.0",
    "gn:asciiname":"Rancho Daysis",
    "gn:country_code":"MX",
    "gn:dem":58,
    "gn:feature_class":"P",
    "gn:feature_code":"PPL",
    "gn:name":"Rancho Daysis",
    "gn:population":4,
    "gn:timezone":"America/Tijuana",
    "iso:country":"MX",
    "wof:name":"Rancho Daysis",
    "wof:placetype":"locality",
    "wof:population":4
},
  "geometry": {"coordinates":[-116.90667000000001,32.19583],"type":"Point"}
}