{
  "type": "Feature",
  "properties": {
    "gn:admin1_code":"14",
    "gn:admin2_code":"93",
    "gn:asciiname":"Miraflores",
    "gn:country_code":"MX",
    "gn:dem":1690,
    "gn:feature_class":"P",
    "gn:feature_code":"PPL",
    "gn:name":"Miraflores",
    "gn:population":10,
    "gn:timezone":"America/Mexico_City",
    "iso:country":"MX",
    "wof:name":"Miraflores",
    "wof:placetype":"locality",
    "wof:population":10
},
  "geometry": {"coordinates":[-102.83556,20.93556],"type":"Point"}
}