{
  "type": "Feature",
  "properties": {
    "gn:admin1_code":"14",
    "gn:admin2_code":"83.0",
    "gn:asciiname":"San Ignacio de Carboneras",
    "gn:country_code":"MX",
    "gn:dem":1562,
    "gn:feature_class":"P",
    "gn:feature_code":"PPL",
    "gn:name":"San Ignacio de Carboneras",
    "gn:population":115,
    "gn:timezone":"America/Mexico_City",
    "iso:country":"MX",
    "wof:name":"San Ignacio de Carboneras",
    "wof:placetype":"locality",
    "wof:population":115
},
  "geometry": {"coordinates":[-103.59778,20.48833],"type":"Point"}
}