{
  "type": "Feature",
  "properties": {
    "gn:admin1_code":"30",
    "gn:admin2_code":"164.0",
    "gn:asciiname":"La Resurreccion",
    "gn:country_code":"MX",
    "gn:dem":1328,
    "gn:feature_class":"P",
    "gn:feature_code":"PPL",
    "gn:name":"La Resurrecci\u00f3n",
    "gn:population":5,
    "gn:timezone":"America/Mexico_City",
    "iso:country":"MX",
    "name:und_x_variant":[
        "La Resurrecci\u00f3n"
    ],
    "wof:name":"La Resurreccion",
    "wof:placetype":"locality",
    "wof:population":5
},
  "geometry": {"coordinates":[-97.01389,19.38778],"type":"Point"}
}