{
  "type": "Feature",
  "properties": {
    "gn:admin1_code":"13",
    "gn:admin2_code":"50.0",
    "gn:asciiname":"Los Olivos",
    "gn:country_code":"MX",
    "gn:dem":1941,
    "gn:feature_class":"P",
    "gn:feature_code":"PPL",
    "gn:name":"Los Olivos",
    "gn:population":75,
    "gn:timezone":"America/Mexico_City",
    "iso:country":"MX",
    "name:ceb_x_preferred":[
        "Los Olivos"
    ],
    "name:deu_x_preferred":[
        "Los Olivos"
    ],
    "name:fra_x_preferred":[
        "Los Olivos"
    ],
    "name:ita_x_preferred":[
        "Los Olivos"
    ],
    "name:srp_x_preferred":[
        "\u041b\u043e\u0441 \u041e\u043b\u0438\u0432\u043e\u0441"
    ],
    "name:swe_x_preferred":[
        "Los Olivos"
    ],
    "wof:name":"Los Olivos",
    "wof:placetype":"locality",
    "wof:population":75
},
  "geometry": {"coordinates":[-99.18107999999999,20.27546],"type":"Point"}
}