{
  "type": "Feature",
  "properties": {
    "gn:admin1_code":"6.0",
    "gn:asciiname":"Gomera de Enmedio",
    "gn:country_code":"MX",
    "gn:dem":1636,
    "gn:feature_class":"P",
    "gn:feature_code":"PPL",
    "gn:name":"Gomera de Enmedio",
    "gn:population":0,
    "gn:timezone":"America/Chihuahua",
    "iso:country":"MX",
    "name:spa_x_preferred":[
        "Gomera de Enmedio"
    ],
    "wof:name":"Gomera de Enmedio",
    "wof:placetype":"locality"
},
  "geometry": {"coordinates":[-105.57915,27.01152],"type":"Point"}
}