{
  "type": "Feature",
  "properties": {
    "gn:admin1_code":"25",
    "gn:admin2_code":"11",
    "gn:asciiname":"Campo las Margaritas Dos",
    "gn:country_code":"MX",
    "gn:dem":21,
    "gn:feature_class":"P",
    "gn:feature_code":"PPL",
    "gn:name":"Campo las Margaritas Dos",
    "gn:population":12,
    "gn:timezone":"America/Mazatlan",
    "iso:country":"MX",
    "wof:name":"Campo las Margaritas Dos",
    "wof:placetype":"locality",
    "wof:population":12
},
  "geometry": {"coordinates":[-108.70701,25.74538],"type":"Point"}
}