{
  "type": "Feature",
  "properties": {
    "gn:admin1_code":"14",
    "gn:admin2_code":"16.0",
    "gn:asciiname":"Las Villas",
    "gn:country_code":"MX",
    "gn:dem":1642,
    "gn:feature_class":"P",
    "gn:feature_code":"PPL",
    "gn:name":"Las Villas",
    "gn:population":0,
    "gn:timezone":"America/Mexico_City",
    "iso:country":"MX",
    "name:cat_x_preferred":[
        "Las Villas"
    ],
    "name:deu_x_preferred":[
        "Las Villas"
    ],
    "name:fra_x_preferred":[
        "Las Villas"
    ],
    "name:kaz_x_preferred":[
        "\u041b\u0430\u0441-\u0412\u0438\u043b\u044c\u044f\u0441"
    ],
    "name:rus_x_preferred":[
        "\u041b\u0430\u0441-\u0412\u0438\u043b\u044c\u044f\u0441"
    ],
    "name:spa_x_preferred":[
        "Las Villas"
    ],
    "name:uzb_x_preferred":[
        "Las Villas"
    ],
    "wof:name":"Las Villas",
    "wof:placetype":"locality"
},
  "geometry": {"coordinates":[-102.38993000000001,20.53229],"type":"Point"}
}