{
  "type": "Feature",
  "properties": {
    "gn:admin1_code":"3",
    "gn:admin2_code":"1.0",
    "gn:asciiname":"Los Burros",
    "gn:country_code":"MX",
    "gn:dem":50,
    "gn:feature_class":"P",
    "gn:feature_code":"PPL",
    "gn:name":"Los Burros",
    "gn:population":0,
    "gn:timezone":"America/Mazatlan",
    "iso:country":"MX",
    "name:spa_x_preferred":[
        "Los Burros"
    ],
    "wof:name":"Los Burros",
    "wof:placetype":"locality"
},
  "geometry": {"coordinates":[-112.28167000000001,26.26401],"type":"Point"}
}