{
  "type": "Feature",
  "properties": {
    "gn:admin1_code":"16",
    "gn:admin2_code":"101",
    "gn:asciiname":"Rosa de Castilla",
    "gn:country_code":"MX",
    "gn:dem":2049,
    "gn:feature_class":"P",
    "gn:feature_code":"PPL",
    "gn:name":"Rosa de Castilla",
    "gn:population":12,
    "gn:timezone":"America/Mexico_City",
    "iso:country":"MX",
    "wof:name":"Rosa de Castilla",
    "wof:placetype":"locality",
    "wof:population":12
},
  "geometry": {"coordinates":[-100.90861,19.64361],"type":"Point"}
}