{
  "type": "Feature",
  "properties": {
    "gn:admin1_code":"13",
    "gn:asciiname":"Chichictla",
    "gn:country_code":"MX",
    "gn:dem":255,
    "gn:feature_class":"P",
    "gn:feature_code":"PPL",
    "gn:name":"Chichictla",
    "gn:population":0,
    "gn:timezone":"America/Mexico_City",
    "iso:country":"MX",
    "name:spa_x_preferred":[
        "Chichictla"
    ],
    "wof:name":"Chichictla",
    "wof:placetype":"locality"
},
  "geometry": {"coordinates":[-98.69015,21.2003],"type":"Point"}
}