{
  "type": "Feature",
  "properties": {
    "gn:admin1_code":"5",
    "gn:admin2_code":"77.0",
    "gn:asciiname":"Tientiul Grande 1ra. Seccion",
    "gn:country_code":"MX",
    "gn:dem":455,
    "gn:feature_class":"P",
    "gn:feature_code":"PPL",
    "gn:name":"Tientiul Grande 1ra. Secci\u00f3n",
    "gn:population":197,
    "gn:timezone":"America/Mexico_City",
    "iso:country":"MX",
    "name:und_x_variant":[
        "Tientiul Grande 1ra. Secci\u00f3n"
    ],
    "wof:name":"Tientiul Grande 1ra. Seccion",
    "wof:placetype":"locality",
    "wof:population":197
},
  "geometry": {"coordinates":[-92.26416999999999,17.37778],"type":"Point"}
}