{
  "type": "Feature",
  "properties": {
    "gn:admin1_code":"32",
    "gn:admin2_code":"54",
    "gn:asciiname":"Fraccionamiento Victoria (La Victoria)",
    "gn:country_code":"MX",
    "gn:dem":2146,
    "gn:feature_class":"P",
    "gn:feature_code":"PPL",
    "gn:name":"Fraccionamiento Victoria (La Victoria)",
    "gn:population":20,
    "gn:timezone":"America/Mexico_City",
    "iso:country":"MX",
    "wof:name":"Fraccionamiento Victoria (La Victoria)",
    "wof:placetype":"locality",
    "wof:population":20
},
  "geometry": {"coordinates":[-101.74278,22.32611],"type":"Point"}
}