{
  "type": "Feature",
  "properties": {
    "gn:admin1_code":"30",
    "gn:admin2_code":"43.0",
    "gn:asciiname":"Dos Caminos",
    "gn:country_code":"MX",
    "gn:dem":465,
    "gn:feature_class":"P",
    "gn:feature_code":"PPL",
    "gn:name":"Dos Caminos",
    "gn:population":0,
    "gn:timezone":"America/Mexico_City",
    "iso:country":"MX",
    "name:spa_x_preferred":[
        "Dos Caminos"
    ],
    "wof:name":"Dos Caminos",
    "wof:placetype":"locality"
},
  "geometry": {"coordinates":[-96.65855999999999,19.19064],"type":"Point"}
}