{
  "type": "Feature",
  "properties": {
    "gn:admin1_code":"10",
    "gn:admin2_code":"19.0",
    "gn:asciiname":"Los Cardos",
    "gn:country_code":"MX",
    "gn:dem":1697,
    "gn:feature_class":"P",
    "gn:feature_code":"PPL",
    "gn:name":"Los Cardos",
    "gn:population":0,
    "gn:timezone":"America/Monterrey",
    "iso:country":"MX",
    "name:und_x_variant":[
        "Cardo",
        "Cardos",
        "Los Cardos"
    ],
    "wof:name":"Los Cardos",
    "wof:placetype":"locality"
},
  "geometry": {"coordinates":[-105.88797,24.57025],"type":"Point"}
}