{
  "type": "Feature",
  "properties": {
    "gn:admin1_code":"16",
    "gn:admin2_code":"57.0",
    "gn:asciiname":"La Loma del Copal",
    "gn:country_code":"MX",
    "gn:dem":1378,
    "gn:feature_class":"P",
    "gn:feature_code":"PPL",
    "gn:name":"La Loma del Copal",
    "gn:population":74,
    "gn:timezone":"America/Mexico_City",
    "iso:country":"MX",
    "wof:name":"La Loma del Copal",
    "wof:placetype":"locality",
    "wof:population":74
},
  "geometry": {"coordinates":[-101.27056,19.19972000000001],"type":"Point"}
}