{
  "type": "Feature",
  "properties": {
    "gn:admin1_code":"25",
    "gn:admin2_code":"4.0",
    "gn:asciiname":"La Paloma",
    "gn:country_code":"MX",
    "gn:dem":53,
    "gn:feature_class":"P",
    "gn:feature_code":"PPL",
    "gn:name":"La Paloma",
    "gn:population":9,
    "gn:timezone":"America/Mazatlan",
    "iso:country":"MX",
    "name:dan_x_preferred":[
        "No More"
    ],
    "name:deu_x_preferred":[
        "La Paloma"
    ],
    "name:ell_x_preferred":[
        "La Paloma"
    ],
    "name:fin_x_preferred":[
        "La Paloma"
    ],
    "name:fra_x_preferred":[
        "La paloma"
    ],
    "name:hun_x_preferred":[
        "La Paloma"
    ],
    "name:ita_x_preferred":[
        "La paloma"
    ],
    "name:nld_x_preferred":[
        "La Paloma ade"
    ],
    "name:nno_x_preferred":[
        "La Paloma"
    ],
    "name:nor_x_preferred":[
        "La paloma"
    ],
    "name:pol_x_preferred":[
        "La Paloma"
    ],
    "name:por_x_preferred":[
        "La Paloma"
    ],
    "name:pus_x_preferred":[
        "\u0644\u0647 \u067e\u0644\u0648\u0645\u0627"
    ],
    "name:rus_x_preferred":[
        "\u0413\u043e\u043b\u0443\u0431\u043a\u0430"
    ],
    "name:spa_x_preferred":[
        "La paloma"
    ],
    "name:tha_x_preferred":[
        "\u0e25\u0e32\u0e1b\u0e32\u0e42\u0e25\u0e21\u0e32"
    ],
    "name:tur_x_preferred":[
        "La Paloma"
    ],
    "name:ukr_x_preferred":[
        "\u0413\u043e\u043b\u0443\u0431\u043a\u0430"
    ],
    "name:vie_x_preferred":[
        "La Paloma"
    ],
    "name:vie_x_variant":[
        "C\u00e1nh bu\u1ed3m xa x\u01b0a"
    ],
    "wof:name":"La Paloma",
    "wof:placetype":"locality",
    "wof:population":9
},
  "geometry": {"coordinates":[-106.06059,23.1358],"type":"Point"}
}