{
  "type": "Feature",
  "properties": {
    "gn:admin1_code":"3",
    "gn:admin2_code":"1.0",
    "gn:asciiname":"Boca de las Canadas",
    "gn:country_code":"MX",
    "gn:dem":247,
    "gn:feature_class":"P",
    "gn:feature_code":"PPL",
    "gn:name":"Boca de las Ca\u00f1adas",
    "gn:population":0,
    "gn:timezone":"America/Mazatlan",
    "iso:country":"MX",
    "name:spa_x_preferred":[
        "Boca de las Ca\u00f1adas"
    ],
    "wof:name":"Boca de las Canadas",
    "wof:placetype":"locality"
},
  "geometry": {"coordinates":[-111.15131,25.0577],"type":"Point"}
}