{
  "type": "Feature",
  "properties": {
    "gn:admin1_code":"19",
    "gn:admin2_code":"38.0",
    "gn:asciiname":"El Alamo",
    "gn:country_code":"MX",
    "gn:dem":301,
    "gn:feature_class":"P",
    "gn:feature_code":"PPL",
    "gn:name":"El Alamo",
    "gn:population":0,
    "gn:timezone":"America/Monterrey",
    "iso:country":"MX",
    "name:spa_x_preferred":[
        "El Alamo"
    ],
    "name:und_x_variant":[
        "Alamo",
        "El \u00c1lamo"
    ],
    "wof:name":"El Alamo",
    "wof:placetype":"locality"
},
  "geometry": {"coordinates":[-99.83831000000001,25.32641],"type":"Point"}
}