{
  "type": "Feature",
  "properties": {
    "gn:admin1_code":"32",
    "gn:admin2_code":"10.0",
    "gn:asciiname":"Balneario las Palmas",
    "gn:country_code":"MX",
    "gn:dem":2074,
    "gn:feature_class":"P",
    "gn:feature_code":"PPL",
    "gn:name":"Balneario las Palmas",
    "gn:population":0,
    "gn:timezone":"America/Mexico_City",
    "iso:country":"MX",
    "name:spa_x_preferred":[
        "Balneario las Palmas"
    ],
    "wof:name":"Balneario las Palmas",
    "wof:placetype":"locality"
},
  "geometry": {"coordinates":[-102.9401,23.34247],"type":"Point"}
}