{
  "type": "Feature",
  "properties": {
    "gn:admin1_code":"30",
    "gn:admin2_code":"100.0",
    "gn:asciiname":"La Venta",
    "gn:country_code":"MX",
    "gn:dem":46,
    "gn:feature_class":"P",
    "gn:feature_code":"PPL",
    "gn:name":"La Venta",
    "gn:population":0,
    "gn:timezone":"America/Mexico_City",
    "iso:country":"MX",
    "name:spa_x_preferred":[
        "La Venta"
    ],
    "wof:name":"La Venta",
    "wof:placetype":"locality"
},
  "geometry": {"coordinates":[-96.30394,19.0683],"type":"Point"}
}