{
  "type": "Feature",
  "properties": {
    "gn:admin1_code":"2",
    "gn:admin2_code":"2",
    "gn:asciiname":"Familia Salazar (Ejido Sonora 2 Parcela Setenta y Cinco)",
    "gn:country_code":"MX",
    "gn:dem":10,
    "gn:feature_class":"P",
    "gn:feature_code":"PPL",
    "gn:name":"Familia Salazar (Ejido Sonora 2 Parcela Setenta y Cinco)",
    "gn:population":16,
    "gn:timezone":"America/Tijuana",
    "iso:country":"MX",
    "wof:name":"Familia Salazar (Ejido Sonora 2 Parcela Setenta y Cinco)",
    "wof:placetype":"locality",
    "wof:population":16
},
  "geometry": {"coordinates":[-115.175,32.29056],"type":"Point"}
}