{
  "type": "Feature",
  "properties": {
    "gn:admin1_code":"14.0",
    "gn:admin2_code":"92.0",
    "gn:asciiname":"Puerta de Citala",
    "gn:country_code":"MX",
    "gn:dem":1375,
    "gn:feature_class":"P",
    "gn:feature_code":"PPL",
    "gn:name":"Puerta de Citala",
    "gn:population":0,
    "gn:timezone":"America/Mexico_City",
    "iso:country":"MX",
    "name:und_x_variant":[
        "Citala"
    ],
    "wof:name":"Puerta de Citala",
    "wof:placetype":"locality"
},
  "geometry": {"coordinates":[-103.35071000000001,20.11772],"type":"Point"}
}