{
  "type": "Feature",
  "properties": {
    "gn:admin1_code":"4",
    "gn:admin2_code":"3.0",
    "gn:asciiname":"El Sacrificio",
    "gn:country_code":"MX",
    "gn:dem":32,
    "gn:feature_class":"P",
    "gn:feature_code":"PPL",
    "gn:name":"El Sacrificio",
    "gn:population":4,
    "gn:timezone":"America/Merida",
    "iso:country":"MX",
    "wof:name":"El Sacrificio",
    "wof:placetype":"locality",
    "wof:population":4
},
  "geometry": {"coordinates":[-91.09166999999999,18.46611],"type":"Point"}
}