{
  "type": "Feature",
  "properties": {
    "gn:admin1_code":"30",
    "gn:admin2_code":"168",
    "gn:asciiname":"Tepectlaxitla (Xochitiouacanapa)",
    "gn:country_code":"MX",
    "gn:dem":2330,
    "gn:feature_class":"P",
    "gn:feature_code":"PPL",
    "gn:name":"Tepectlaxitla (Xochitiouacanapa)",
    "gn:population":12,
    "gn:timezone":"America/Mexico_City",
    "iso:country":"MX",
    "wof:name":"Tepectlaxitla (Xochitiouacanapa)",
    "wof:placetype":"locality",
    "wof:population":12
},
  "geometry": {"coordinates":[-97.09889,18.72361],"type":"Point"}
}