{
  "type": "Feature",
  "properties": {
    "gn:admin1_code":"20",
    "gn:admin2_code":"424",
    "gn:asciiname":"La Guacamaya",
    "gn:country_code":"MX",
    "gn:dem":1564,
    "gn:feature_class":"P",
    "gn:feature_code":"PPL",
    "gn:name":"La Guacamaya",
    "gn:population":27,
    "gn:timezone":"America/Mexico_City",
    "iso:country":"MX",
    "wof:name":"La Guacamaya",
    "wof:placetype":"locality",
    "wof:population":27
},
  "geometry": {"coordinates":[-96.34639,16.04361],"type":"Point"}
}