{
  "type": "Feature",
  "properties": {
    "gn:admin1_code":"21",
    "gn:admin2_code":"208.0",
    "gn:asciiname":"Atotonilco",
    "gn:country_code":"MX",
    "gn:dem":2284,
    "gn:feature_class":"P",
    "gn:feature_code":"PPL",
    "gn:name":"Atotonilco",
    "gn:population":581,
    "gn:timezone":"America/Mexico_City",
    "iso:country":"MX",
    "wof:name":"Atotonilco",
    "wof:placetype":"locality",
    "wof:population":581
},
  "geometry": {"coordinates":[-98.13278,19.99944],"type":"Point"}
}