{
  "type": "Feature",
  "properties": {
    "gn:admin1_code":"25",
    "gn:admin2_code":"10.0",
    "gn:asciiname":"Arroyo de los Armenta",
    "gn:country_code":"MX",
    "gn:dem":78,
    "gn:feature_class":"P",
    "gn:feature_code":"PPL",
    "gn:name":"Arroyo de los Armenta",
    "gn:population":0,
    "gn:timezone":"America/Mazatlan",
    "iso:country":"MX",
    "name:spa_x_preferred":[
        "Arroyo de los Armenta"
    ],
    "wof:name":"Arroyo de los Armenta",
    "wof:placetype":"locality"
},
  "geometry": {"coordinates":[-108.71012,26.40592],"type":"Point"}
}