{
  "type": "Feature",
  "properties": {
    "gn:admin1_code":"5",
    "gn:admin2_code":"27.0",
    "gn:asciiname":"Las Benjaminas",
    "gn:country_code":"MX",
    "gn:dem":515,
    "gn:feature_class":"P",
    "gn:feature_code":"PPL",
    "gn:name":"Las Benjaminas",
    "gn:population":6,
    "gn:timezone":"America/Mexico_City",
    "iso:country":"MX",
    "wof:name":"Las Benjaminas",
    "wof:placetype":"locality",
    "wof:population":6
},
  "geometry": {"coordinates":[-93.03888999999999,16.54],"type":"Point"}
}