{
  "type": "Feature",
  "properties": {
    "gn:admin1_code":"32.0",
    "gn:admin2_code":"22.0",
    "gn:asciiname":"Los Tres Portrillos",
    "gn:country_code":"MX",
    "gn:dem":2021,
    "gn:feature_class":"P",
    "gn:feature_code":"PPL",
    "gn:name":"Los Tres Portrillos",
    "gn:population":0,
    "gn:timezone":"America/Mexico_City",
    "iso:country":"MX",
    "name:spa_x_preferred":[
        "Los Tres Portrillos"
    ],
    "wof:name":"Los Tres Portrillos",
    "wof:placetype":"locality"
},
  "geometry": {"coordinates":[-103.39422999999999,24.26535],"type":"Point"}
}