{
  "type": "Feature",
  "properties": {
    "gn:admin1_code":"22",
    "gn:admin2_code":"11.0",
    "gn:asciiname":"Hacienda la Cruz [Fraccionamiento]",
    "gn:country_code":"MX",
    "gn:dem":1891,
    "gn:feature_class":"P",
    "gn:feature_code":"PPL",
    "gn:name":"Hacienda la Cruz [Fraccionamiento]",
    "gn:population":2373,
    "gn:timezone":"America/Mexico_City",
    "iso:country":"MX",
    "wof:name":"Hacienda la Cruz [Fraccionamiento]",
    "wof:placetype":"locality",
    "wof:population":2373
},
  "geometry": {"coordinates":[-100.26278000000001,20.63333],"type":"Point"}
}