{
  "type": "Feature",
  "properties": {
    "gn:admin1_code":"12",
    "gn:admin2_code":"77.0",
    "gn:asciiname":"El Zapote",
    "gn:country_code":"MX",
    "gn:dem":22,
    "gn:feature_class":"P",
    "gn:feature_code":"PPL",
    "gn:name":"El Zapote",
    "gn:population":192,
    "gn:timezone":"America/Mexico_City",
    "iso:country":"MX",
    "wof:name":"El Zapote",
    "wof:placetype":"locality",
    "wof:population":192
},
  "geometry": {"coordinates":[-98.82083,16.60556],"type":"Point"}
}