{
  "type": "Feature",
  "properties": {
    "gn:admin1_code":"16",
    "gn:admin2_code":"15.0",
    "gn:asciiname":"El Huache",
    "gn:country_code":"MX",
    "gn:dem":1006,
    "gn:feature_class":"P",
    "gn:feature_code":"PPL",
    "gn:name":"El Huache",
    "gn:population":8,
    "gn:timezone":"America/Mexico_City",
    "iso:country":"MX",
    "wof:name":"El Huache",
    "wof:placetype":"locality",
    "wof:population":8
},
  "geometry": {"coordinates":[-103.18556,18.50806],"type":"Point"}
}