{
  "type": "Feature",
  "properties": {
    "gn:admin1_code":"16.0",
    "gn:admin2_code":"96.0",
    "gn:asciiname":"El Ojo de Agua de los Venados",
    "gn:country_code":"MX",
    "gn:dem":612,
    "gn:feature_class":"P",
    "gn:feature_code":"PPL",
    "gn:name":"El Ojo de Agua de los Venados",
    "gn:population":0,
    "gn:timezone":"America/Mexico_City",
    "iso:country":"MX",
    "name:spa_x_preferred":[
        "El Ojo de Agua de los Venados"
    ],
    "wof:name":"El Ojo de Agua de los Venados",
    "wof:placetype":"locality"
},
  "geometry": {"coordinates":[-102.79283,18.46111],"type":"Point"}
}