{
  "type": "Feature",
  "properties": {
    "gn:admin1_code":"2.0",
    "gn:admin2_code":"1.0",
    "gn:asciiname":"Compostela",
    "gn:country_code":"MX",
    "gn:dem":277,
    "gn:feature_class":"P",
    "gn:feature_code":"PPL",
    "gn:name":"Compostela",
    "gn:population":0,
    "gn:timezone":"America/Tijuana",
    "iso:country":"MX",
    "name:ceb_x_preferred":[
        "Compostela"
    ],
    "name:deu_x_preferred":[
        "Compostela"
    ],
    "name:fas_x_preferred":[
        "\u06a9\u0627\u0645\u067e\u0648\u0633\u062a\u0644\u0627"
    ],
    "name:fra_x_preferred":[
        "Compostela"
    ],
    "name:glg_x_preferred":[
        "Compostela"
    ],
    "name:ita_x_preferred":[
        "Compostela"
    ],
    "name:nld_x_preferred":[
        "Compostela"
    ],
    "name:por_x_preferred":[
        "Compostela"
    ],
    "name:rus_x_preferred":[
        "\u041a\u043e\u043c\u043f\u043e\u0441\u0442\u0435\u043b\u0430"
    ],
    "name:sco_x_preferred":[
        "Compostela"
    ],
    "name:spa_x_preferred":[
        "Compostela"
    ],
    "name:srp_x_preferred":[
        "\u041a\u043e\u043c\u043f\u043e\u0441\u0442\u0435\u043b\u0430"
    ],
    "name:swe_x_preferred":[
        "Compostela"
    ],
    "name:war_x_preferred":[
        "Compostela"
    ],
    "wof:name":"Compostela",
    "wof:placetype":"locality"
},
  "geometry": {"coordinates":[-113.91667,28.86667000000001],"type":"Point"}
}