{
  "type": "Feature",
  "properties": {
    "gn:admin1_code":"7",
    "gn:admin2_code":"31.0",
    "gn:asciiname":"La Sauceda",
    "gn:country_code":"MX",
    "gn:dem":600,
    "gn:feature_class":"P",
    "gn:feature_code":"PPL",
    "gn:name":"La Sauceda",
    "gn:population":0,
    "gn:timezone":"America/Monterrey",
    "iso:country":"MX",
    "name:spa_x_preferred":[
        "La Sauceda"
    ],
    "name:und_x_variant":[
        "Sauceda",
        "Rancho Sauceda"
    ],
    "wof:name":"La Sauceda",
    "wof:placetype":"locality"
},
  "geometry": {"coordinates":[-101.578,27.46323],"type":"Point"}
}