{
  "type": "Feature",
  "properties": {
    "gn:admin1_code":"12.0",
    "gn:admin2_code":"32.0",
    "gn:asciiname":"Huautla",
    "gn:country_code":"MX",
    "gn:dem":518,
    "gn:feature_class":"P",
    "gn:feature_code":"PPL",
    "gn:name":"Huautla",
    "gn:population":646,
    "gn:timezone":"America/Mexico_City",
    "iso:country":"MX",
    "name:ceb_x_preferred":[
        "Huautla"
    ],
    "name:ita_x_preferred":[
        "Huautla"
    ],
    "name:sco_x_preferred":[
        "Huautla"
    ],
    "name:spa_x_preferred":[
        "Huautla"
    ],
    "name:swe_x_preferred":[
        "Huautla"
    ],
    "name:vie_x_preferred":[
        "Huautla"
    ],
    "wof:name":"Huautla",
    "wof:placetype":"locality",
    "wof:population":646
},
  "geometry": {"coordinates":[-100.10299999999999,17.85262999999999],"type":"Point"}
}