{
  "type": "Feature",
  "properties": {
    "gn:admin1_code":"28",
    "gn:admin2_code":"19.0",
    "gn:asciiname":"La Encantada",
    "gn:country_code":"MX",
    "gn:dem":344,
    "gn:feature_class":"P",
    "gn:feature_code":"PPL",
    "gn:name":"La Encantada",
    "gn:population":0,
    "gn:timezone":"America/Monterrey",
    "iso:country":"MX",
    "name:spa_x_preferred":[
        "La Encantada"
    ],
    "wof:name":"La Encantada",
    "wof:placetype":"locality"
},
  "geometry": {"coordinates":[-99.07550999999999,23.3843],"type":"Point"}
}