{
  "type": "Feature",
  "properties": {
    "gn:admin1_code":"5",
    "gn:admin2_code":"65",
    "gn:asciiname":"San Luis Chico",
    "gn:country_code":"MX",
    "gn:dem":36,
    "gn:feature_class":"P",
    "gn:feature_code":"PPL",
    "gn:name":"San Luis Chico",
    "gn:population":18,
    "gn:timezone":"America/Mexico_City",
    "iso:country":"MX",
    "wof:name":"San Luis Chico",
    "wof:placetype":"locality",
    "wof:population":18
},
  "geometry": {"coordinates":[-92.075,17.51444],"type":"Point"}
}