{
  "type": "Feature",
  "properties": {
    "gn:admin1_code":"7",
    "gn:admin2_code":"3.0",
    "gn:asciiname":"Martha Rodriguez",
    "gn:country_code":"MX",
    "gn:dem":364,
    "gn:feature_class":"P",
    "gn:feature_code":"PPL",
    "gn:name":"Martha Rodr\u00edguez",
    "gn:population":6,
    "gn:timezone":"America/Monterrey",
    "iso:country":"MX",
    "name:und_x_variant":[
        "Martha Rodr\u00edguez"
    ],
    "wof:name":"Martha Rodriguez",
    "wof:placetype":"locality",
    "wof:population":6
},
  "geometry": {"coordinates":[-100.81009,28.35136],"type":"Point"}
}