{
  "type": "Feature",
  "properties": {
    "gn:admin1_code":"2.0",
    "gn:admin2_code":"1.0",
    "gn:asciiname":"El Forzado",
    "gn:country_code":"MX",
    "gn:dem":1281,
    "gn:feature_class":"P",
    "gn:feature_code":"PPL",
    "gn:name":"El Forzado",
    "gn:population":0,
    "gn:timezone":"America/Tijuana",
    "iso:country":"MX",
    "name:spa_x_preferred":[
        "El Forzado"
    ],
    "name:und_x_variant":[
        "Rancho el Florido",
        "Florido"
    ],
    "wof:name":"El Forzado",
    "wof:placetype":"locality"
},
  "geometry": {"coordinates":[-116.0634,31.52104000000001],"type":"Point"}
}