{
  "type": "Feature",
  "properties": {
    "gn:admin1_code":"16",
    "gn:admin2_code":"26",
    "gn:asciiname":"Los Arroyos",
    "gn:country_code":"MX",
    "gn:dem":575,
    "gn:feature_class":"P",
    "gn:feature_code":"PPL",
    "gn:name":"Los Arroyos",
    "gn:population":12,
    "gn:timezone":"America/Mexico_City",
    "iso:country":"MX",
    "wof:name":"Los Arroyos",
    "wof:placetype":"locality",
    "wof:population":12
},
  "geometry": {"coordinates":[-103.41694,18.63583],"type":"Point"}
}