{
  "type": "Feature",
  "properties": {
    "gn:admin1_code":"6",
    "gn:admin2_code":"20.0",
    "gn:asciiname":"La Huerta",
    "gn:country_code":"MX",
    "gn:dem":1457,
    "gn:feature_class":"P",
    "gn:feature_code":"PPL",
    "gn:name":"La Huerta",
    "gn:population":0,
    "gn:timezone":"America/Chihuahua",
    "iso:country":"MX",
    "name:ceb_x_preferred":[
        "La Huerta"
    ],
    "name:spa_x_preferred":[
        "La Huerta"
    ],
    "name:swe_x_preferred":[
        "La Huerta"
    ],
    "wof:name":"La Huerta",
    "wof:placetype":"locality"
},
  "geometry": {"coordinates":[-108.44368,27.7191],"type":"Point"}
}