{
  "type": "Feature",
  "properties": {
    "gn:admin1_code":"19.0",
    "gn:admin2_code":"14.0",
    "gn:asciiname":"Guadalupe de Silva",
    "gn:country_code":"MX",
    "gn:dem":1715,
    "gn:feature_class":"P",
    "gn:feature_code":"PPL",
    "gn:name":"Guadalupe de Silva",
    "gn:population":0,
    "gn:timezone":"America/Monterrey",
    "iso:country":"MX",
    "name:spa_x_preferred":[
        "Guadalupe de Silva"
    ],
    "name:und_x_variant":[
        "Guadalupe"
    ],
    "wof:name":"Guadalupe de Silva",
    "wof:placetype":"locality"
},
  "geometry": {"coordinates":[-100.46398000000001,23.80827],"type":"Point"}
}