{
  "type": "Feature",
  "properties": {
    "gn:admin1_code":"6",
    "gn:admin2_code":"5.0",
    "gn:asciiname":"La Viuda",
    "gn:country_code":"MX",
    "gn:dem":1354,
    "gn:feature_class":"P",
    "gn:feature_code":"PPL",
    "gn:name":"La Viuda",
    "gn:population":0,
    "gn:timezone":"America/Chihuahua",
    "iso:country":"MX",
    "wof:name":"La Viuda",
    "wof:placetype":"locality"
},
  "geometry": {"coordinates":[-107.8107,31.38457],"type":"Point"}
}