{
  "type": "Feature",
  "properties": {
    "gn:admin1_code":"19",
    "gn:admin2_code":"45.0",
    "gn:asciiname":"El Leal (Predio Alfonso Martinez Dominguez)",
    "gn:country_code":"MX",
    "gn:dem":466,
    "gn:feature_class":"P",
    "gn:feature_code":"PPL",
    "gn:name":"El Leal (Predio Alfonso Mart\u00ednez Dom\u00ednguez)",
    "gn:population":206,
    "gn:timezone":"America/Monterrey",
    "iso:country":"MX",
    "name:und_x_variant":[
        "El Leal (Predio Alfonso Mart\u00ednez Dom\u00ednguez)"
    ],
    "wof:name":"El Leal (Predio Alfonso Martinez Dominguez)",
    "wof:placetype":"locality",
    "wof:population":206
},
  "geometry": {"coordinates":[-100.2925,25.885],"type":"Point"}
}