{
  "type": "Feature",
  "properties": {
    "gn:admin1_code":"18",
    "gn:admin2_code":"19",
    "gn:asciiname":"Agua Mala",
    "gn:country_code":"MX",
    "gn:dem":1484,
    "gn:feature_class":"P",
    "gn:feature_code":"PPL",
    "gn:name":"Agua Mala",
    "gn:population":13,
    "gn:timezone":"America/Mazatlan",
    "iso:country":"MX",
    "wof:name":"Agua Mala",
    "wof:placetype":"locality",
    "wof:population":13
},
  "geometry": {"coordinates":[-104.1425,21.73222],"type":"Point"}
}