{
  "type": "Feature",
  "properties": {
    "gn:admin1_code":"5",
    "gn:admin2_code":"34.0",
    "gn:asciiname":"Sabinalito",
    "gn:country_code":"MX",
    "gn:dem":679,
    "gn:feature_class":"P",
    "gn:feature_code":"PPL",
    "gn:name":"Sabinalito",
    "gn:population":0,
    "gn:timezone":"America/Mexico_City",
    "iso:country":"MX",
    "name:spa_x_preferred":[
        "Sabinalito"
    ],
    "name:und_x_variant":[
        "Sabinal",
        "El Sabinalito",
        "El Sabinal"
    ],
    "wof:name":"Sabinalito",
    "wof:placetype":"locality"
},
  "geometry": {"coordinates":[-91.98636,15.70186],"type":"Point"}
}