{
  "type": "Feature",
  "properties": {
    "gn:admin1_code":"29",
    "gn:admin2_code":"34.0",
    "gn:asciiname":"San Jose Tepeyahualco",
    "gn:country_code":"MX",
    "gn:dem":2560,
    "gn:feature_class":"P",
    "gn:feature_code":"PPL",
    "gn:name":"San Jos\u00e9 Tepeyahualco",
    "gn:population":1074,
    "gn:timezone":"America/Mexico_City",
    "iso:country":"MX",
    "wof:name":"San Jose Tepeyahualco",
    "wof:placetype":"locality",
    "wof:population":1074
},
  "geometry": {"coordinates":[-98.26889,19.59944],"type":"Point"}
}