{
  "type": "Feature",
  "properties": {
    "gn:admin1_code":"11",
    "gn:admin2_code":"5.0",
    "gn:asciiname":"El Sifon",
    "gn:country_code":"MX",
    "gn:dem":1768,
    "gn:feature_class":"P",
    "gn:feature_code":"PPL",
    "gn:name":"El Sif\u00f3n",
    "gn:population":86,
    "gn:timezone":"America/Mexico_City",
    "iso:country":"MX",
    "name:und_x_variant":[
        "El Sif\u00f3n"
    ],
    "wof:name":"El Sifon",
    "wof:placetype":"locality",
    "wof:population":86
},
  "geometry": {"coordinates":[-100.72944,20.50083],"type":"Point"}
}