{
  "type": "Feature",
  "properties": {
    "gn:admin1_code":"20",
    "gn:admin2_code":"412.0",
    "gn:asciiname":"Lachiguxe",
    "gn:country_code":"MX",
    "gn:dem":483,
    "gn:feature_class":"P",
    "gn:feature_code":"PPL",
    "gn:name":"Lachigux\u00e9",
    "gn:population":264,
    "gn:timezone":"America/Mexico_City",
    "iso:country":"MX",
    "name:und_x_variant":[
        "Lachigux\u00e9"
    ],
    "wof:name":"Lachiguxe",
    "wof:placetype":"locality",
    "wof:population":264
},
  "geometry": {"coordinates":[-95.29806000000001,16.87972],"type":"Point"}
}