{
  "type": "Feature",
  "properties": {
    "gn:admin1_code":"10",
    "gn:admin2_code":"1",
    "gn:asciiname":"San Antonio de los Reyes",
    "gn:country_code":"MX",
    "gn:dem":1926,
    "gn:feature_class":"P",
    "gn:feature_code":"PPL",
    "gn:name":"San Antonio de los Reyes",
    "gn:population":9,
    "gn:timezone":"America/Monterrey",
    "iso:country":"MX",
    "wof:name":"San Antonio de los Reyes",
    "wof:placetype":"locality",
    "wof:population":9
},
  "geometry": {"coordinates":[-104.73586,24.38056],"type":"Point"}
}