{
  "type": "Feature",
  "properties": {
    "gn:admin1_code":"32",
    "gn:admin2_code":"26.0",
    "gn:asciiname":"Mineral de Santa Rosa",
    "gn:country_code":"MX",
    "gn:dem":2520,
    "gn:feature_class":"P",
    "gn:feature_code":"PPL",
    "gn:name":"Mineral de Santa Rosa",
    "gn:population":0,
    "gn:timezone":"America/Mexico_City",
    "iso:country":"MX",
    "name:spa_x_preferred":[
        "Mineral de Santa Rosa"
    ],
    "name:und_x_variant":[
        "Santa Rosa"
    ],
    "wof:name":"Mineral de Santa Rosa",
    "wof:placetype":"locality"
},
  "geometry": {"coordinates":[-101.4971,24.58236],"type":"Point"}
}