{
  "type": "Feature",
  "properties": {
    "gn:admin1_code":"30.0",
    "gn:admin2_code":"167.0",
    "gn:asciiname":"La Cuchilla",
    "gn:country_code":"MX",
    "gn:dem":256,
    "gn:feature_class":"P",
    "gn:feature_code":"PPL",
    "gn:name":"La Cuchilla",
    "gn:population":4,
    "gn:timezone":"America/Mexico_City",
    "iso:country":"MX",
    "name:spa_x_preferred":[
        "La Cuchilla"
    ],
    "wof:name":"La Cuchilla",
    "wof:placetype":"locality",
    "wof:population":4
},
  "geometry": {"coordinates":[-97.84712,21.18319],"type":"Point"}
}