{
  "type": "Feature",
  "properties": {
    "gn:admin1_code":"6",
    "gn:admin2_code":"45",
    "gn:asciiname":"Rancho los Gonzalez",
    "gn:country_code":"MX",
    "gn:dem":1160,
    "gn:feature_class":"P",
    "gn:feature_code":"PPL",
    "gn:name":"Rancho los Gonz\u00e1lez",
    "gn:population":11,
    "gn:timezone":"America/Chihuahua",
    "iso:country":"MX",
    "name:und_x_variant":[
        "Rancho los Gonz\u00e1lez"
    ],
    "wof:name":"Rancho los Gonzalez",
    "wof:placetype":"locality",
    "wof:population":11
},
  "geometry": {"coordinates":[-105.53046999999999,28.39881],"type":"Point"}
}