{
  "type": "Feature",
  "properties": {
    "gn:admin1_code":"32",
    "gn:admin2_code":"27.0",
    "gn:asciiname":"Tierra y Libertad (La Maroma)",
    "gn:country_code":"MX",
    "gn:dem":2100,
    "gn:feature_class":"P",
    "gn:feature_code":"PPL",
    "gn:name":"Tierra y Libertad (La Maroma)",
    "gn:population":175,
    "gn:timezone":"America/Mexico_City",
    "iso:country":"MX",
    "wof:name":"Tierra y Libertad (La Maroma)",
    "wof:placetype":"locality",
    "wof:population":175
},
  "geometry": {"coordinates":[-101.68222,24.83222],"type":"Point"}
}