{
  "type": "Feature",
  "properties": {
    "gn:admin1_code":"19.0",
    "gn:asciiname":"Dona Isidra",
    "gn:country_code":"MX",
    "gn:dem":390,
    "gn:feature_class":"P",
    "gn:feature_code":"PPL",
    "gn:name":"Do\u00f1a Isidra",
    "gn:population":0,
    "gn:timezone":"America/Monterrey",
    "iso:country":"MX",
    "name:spa_x_preferred":[
        "Do\u00f1a Isidra"
    ],
    "wof:name":"Dona Isidra",
    "wof:placetype":"locality"
},
  "geometry": {"coordinates":[-99.59332999999999,24.80973],"type":"Point"}
}