{
  "type": "Feature",
  "properties": {
    "gn:admin1_code":"6.0",
    "gn:admin2_code":"7.0",
    "gn:asciiname":"Comunidad Agostadero de Aguirre",
    "gn:country_code":"MX",
    "gn:dem":2307,
    "gn:feature_class":"P",
    "gn:feature_code":"PPL",
    "gn:name":"Comunidad Agostadero de Aguirre",
    "gn:population":0,
    "gn:timezone":"America/Chihuahua",
    "iso:country":"MX",
    "name:spa_x_preferred":[
        "Comunidad Agostadero de Aguirre"
    ],
    "name:und_x_variant":[
        "Agostadero",
        "Agostadero de Aguirre"
    ],
    "wof:name":"Comunidad Agostadero de Aguirre",
    "wof:placetype":"locality"
},
  "geometry": {"coordinates":[-106.6703,26.95901],"type":"Point"}
}