{
  "type": "Feature",
  "properties": {
    "gn:admin1_code":"3",
    "gn:admin2_code":"9.0",
    "gn:asciiname":"Rentoy",
    "gn:country_code":"MX",
    "gn:dem":24,
    "gn:feature_class":"P",
    "gn:feature_code":"PPL",
    "gn:name":"Rentoy",
    "gn:population":0,
    "gn:timezone":"America/Mazatlan",
    "iso:country":"MX",
    "name:spa_x_preferred":[
        "Rentoy"
    ],
    "wof:name":"Rentoy",
    "wof:placetype":"locality"
},
  "geometry": {"coordinates":[-111.4402,26.20044],"type":"Point"}
}