{
  "type": "Feature",
  "properties": {
    "gn:admin1_code":"30",
    "gn:admin2_code":"58.0",
    "gn:asciiname":"San Miguel",
    "gn:country_code":"MX",
    "gn:dem":507,
    "gn:feature_class":"P",
    "gn:feature_code":"PPL",
    "gn:name":"San Miguel",
    "gn:population":80,
    "gn:timezone":"America/Mexico_City",
    "iso:country":"MX",
    "wof:name":"San Miguel",
    "wof:placetype":"locality",
    "wof:population":80
},
  "geometry": {"coordinates":[-98.16611,20.95722],"type":"Point"}
}