{
  "type": "Feature",
  "properties": {
    "gn:admin1_code":"27.0",
    "gn:asciiname":"El Colmenar",
    "gn:country_code":"MX",
    "gn:dem":14,
    "gn:feature_class":"P",
    "gn:feature_code":"PPL",
    "gn:name":"El Colmenar",
    "gn:population":0,
    "gn:timezone":"America/Mexico_City",
    "iso:country":"MX",
    "name:spa_x_preferred":[
        "El Colmenar"
    ],
    "wof:name":"El Colmenar",
    "wof:placetype":"locality"
},
  "geometry": {"coordinates":[-91.54415,17.81925],"type":"Point"}
}