{
  "type": "Feature",
  "properties": {
    "gn:admin1_code":"20",
    "gn:admin2_code":"327.0",
    "gn:asciiname":"Costa Rica",
    "gn:country_code":"MX",
    "gn:dem":48,
    "gn:feature_class":"P",
    "gn:feature_code":"PPL",
    "gn:name":"Costa Rica",
    "gn:population":0,
    "gn:timezone":"America/Mexico_City",
    "iso:country":"MX",
    "wof:name":"Costa Rica",
    "wof:placetype":"locality"
},
  "geometry": {"coordinates":[-94.21666999999999,16.35],"type":"Point"}
}