{
  "type": "Feature",
  "properties": {
    "gn:admin1_code":"26.0",
    "gn:admin2_code":"55.0",
    "gn:asciiname":"Emiliano Zapata",
    "gn:country_code":"MX",
    "gn:dem":14,
    "gn:feature_class":"P",
    "gn:feature_code":"PPL",
    "gn:name":"Emiliano Zapata",
    "gn:population":282,
    "gn:timezone":"America/Hermosillo",
    "iso:country":"MX",
    "name:spa_x_preferred":[
        "Emiliano Zapata"
    ],
    "wof:name":"Emiliano Zapata",
    "wof:placetype":"locality",
    "wof:population":282
},
  "geometry": {"coordinates":[-114.9875,32.24028],"type":"Point"}
}