{
  "type": "Feature",
  "properties": {
    "gn:admin1_code":"14",
    "gn:admin2_code":"19",
    "gn:asciiname":"Crucero Banderitas",
    "gn:country_code":"MX",
    "gn:dem":2519,
    "gn:feature_class":"P",
    "gn:feature_code":"PPL",
    "gn:name":"Crucero Banderitas",
    "gn:population":29,
    "gn:timezone":"America/Mexico_City",
    "iso:country":"MX",
    "wof:name":"Crucero Banderitas",
    "wof:placetype":"locality",
    "wof:population":29
},
  "geometry": {"coordinates":[-103.87,21.91667],"type":"Point"}
}