{
  "type": "Feature",
  "properties": {
    "gn:admin1_code":"10",
    "gn:admin2_code":"23",
    "gn:asciiname":"Tres Lagunas",
    "gn:country_code":"MX",
    "gn:dem":2518,
    "gn:feature_class":"P",
    "gn:feature_code":"PPL",
    "gn:name":"Tres Lagunas",
    "gn:population":32,
    "gn:timezone":"America/Monterrey",
    "iso:country":"MX",
    "name:por_x_preferred":[
        "Tres Lagunas"
    ],
    "name:spa_x_preferred":[
        "Tres Lagunas"
    ],
    "wof:name":"Tres Lagunas",
    "wof:placetype":"locality",
    "wof:population":32
},
  "geometry": {"coordinates":[-104.82079,23.34823],"type":"Point"}
}