{
  "type": "Feature",
  "properties": {
    "gn:admin1_code":"20",
    "gn:admin2_code":"296",
    "gn:asciiname":"Barrio Alto",
    "gn:country_code":"MX",
    "gn:dem":2244,
    "gn:feature_class":"P",
    "gn:feature_code":"PPL",
    "gn:name":"Barrio Alto",
    "gn:population":23,
    "gn:timezone":"America/Mexico_City",
    "iso:country":"MX",
    "wof:name":"Barrio Alto",
    "wof:placetype":"locality",
    "wof:population":23
},
  "geometry": {"coordinates":[-96.5475,17.53444],"type":"Point"}
}