{
  "type": "Feature",
  "properties": {
    "gn:admin1_code":"32",
    "gn:admin2_code":"1.0",
    "gn:asciiname":"Puerta Blanca",
    "gn:country_code":"MX",
    "gn:dem":1268,
    "gn:feature_class":"P",
    "gn:feature_code":"PPL",
    "gn:name":"Puerta Blanca",
    "gn:population":0,
    "gn:timezone":"America/Mexico_City",
    "iso:country":"MX",
    "wof:name":"Puerta Blanca",
    "wof:placetype":"locality"
},
  "geometry": {"coordinates":[-103.10821,21.44589],"type":"Point"}
}