{
  "type": "Feature",
  "properties": {
    "gn:admin1_code":"5.0",
    "gn:admin2_code":"62.0",
    "gn:asciiname":"Paraiso Segunda Seccion",
    "gn:country_code":"MX",
    "gn:dem":206,
    "gn:feature_class":"P",
    "gn:feature_code":"PPL",
    "gn:name":"Para\u00edso Segunda Secci\u00f3n",
    "gn:population":0,
    "gn:timezone":"America/Mexico_City",
    "iso:country":"MX",
    "name:spa_x_preferred":[
        "Para\u00edso Segunda Secci\u00f3n"
    ],
    "wof:name":"Paraiso Segunda Seccion",
    "wof:placetype":"locality"
},
  "geometry": {"coordinates":[-93.34984,17.46158],"type":"Point"}
}