{
  "type": "Feature",
  "properties": {
    "gn:admin1_code":"12.0",
    "gn:admin2_code":"16.0",
    "gn:asciiname":"Quiringucua",
    "gn:country_code":"MX",
    "gn:dem":519,
    "gn:feature_class":"P",
    "gn:feature_code":"PPL",
    "gn:name":"Quiringucua",
    "gn:population":51,
    "gn:timezone":"America/Mexico_City",
    "iso:country":"MX",
    "name:und_x_variant":[
        "Curingucas",
        "Curingueas"
    ],
    "wof:name":"Quiringucua",
    "wof:placetype":"locality",
    "wof:population":51
},
  "geometry": {"coordinates":[-101.57829,18.44527],"type":"Point"}
}