{
  "type": "Feature",
  "properties": {
    "gn:admin1_code":"16",
    "gn:admin2_code":"100.0",
    "gn:asciiname":"La Vinata",
    "gn:country_code":"MX",
    "gn:dem":2051,
    "gn:feature_class":"P",
    "gn:feature_code":"PPL",
    "gn:name":"La Vinata",
    "gn:population":113,
    "gn:timezone":"America/Mexico_City",
    "iso:country":"MX",
    "wof:name":"La Vinata",
    "wof:placetype":"locality",
    "wof:population":113
},
  "geometry": {"coordinates":[-101.62555999999999,19.58944],"type":"Point"}
}