{
  "type": "Feature",
  "properties": {
    "gn:admin1_code":"28",
    "gn:admin2_code":"42.0",
    "gn:asciiname":"Marte R. Gomez",
    "gn:country_code":"MX",
    "gn:dem":263,
    "gn:feature_class":"P",
    "gn:feature_code":"PPL",
    "gn:name":"Marte R. G\u00f3mez",
    "gn:population":0,
    "gn:timezone":"America/Monterrey",
    "iso:country":"MX",
    "name:spa_x_preferred":[
        "Marte R. G\u00f3mez"
    ],
    "name:spa_x_variant":[
        "Patol"
    ],
    "name:und_x_variant":[
        "Ejido Marte R G\u00f3mez"
    ],
    "wof:name":"Marte R. Gomez",
    "wof:placetype":"locality"
},
  "geometry": {"coordinates":[-99.26969,24.47261],"type":"Point"}
}