{
  "type": "Feature",
  "properties": {
    "gn:admin1_code":"22",
    "gn:admin2_code":"14.0",
    "gn:asciiname":"Lomas del Mirador",
    "gn:country_code":"MX",
    "gn:dem":2034,
    "gn:feature_class":"P",
    "gn:feature_code":"PPL",
    "gn:name":"Lomas del Mirador",
    "gn:population":224,
    "gn:timezone":"America/Mexico_City",
    "iso:country":"MX",
    "wof:name":"Lomas del Mirador",
    "wof:placetype":"locality",
    "wof:population":224
},
  "geometry": {"coordinates":[-100.47472,20.82667],"type":"Point"}
}