{
  "type": "Feature",
  "properties": {
    "gn:admin1_code":"6",
    "gn:admin2_code":"9.0",
    "gn:asciiname":"Tucheachi",
    "gn:country_code":"MX",
    "gn:dem":2388,
    "gn:feature_class":"P",
    "gn:feature_code":"PPL",
    "gn:name":"Tucheachi",
    "gn:population":8,
    "gn:timezone":"America/Chihuahua",
    "iso:country":"MX",
    "wof:name":"Tucheachi",
    "wof:placetype":"locality",
    "wof:population":8
},
  "geometry": {"coordinates":[-107.79798999999998,27.90575],"type":"Point"}
}