{
  "type": "Feature",
  "properties": {
    "gn:admin1_code":"30",
    "gn:admin2_code":"183.0",
    "gn:asciiname":"Frijolares",
    "gn:country_code":"MX",
    "gn:dem":254,
    "gn:feature_class":"P",
    "gn:feature_code":"PPL",
    "gn:name":"Frijolares",
    "gn:population":105,
    "gn:timezone":"America/Mexico_City",
    "iso:country":"MX",
    "wof:name":"Frijolares",
    "wof:placetype":"locality",
    "wof:population":105
},
  "geometry": {"coordinates":[-97.16139,19.99917],"type":"Point"}
}