{
  "type": "Feature",
  "properties": {
    "gn:admin1_code":"30",
    "gn:admin2_code":"201.0",
    "gn:asciiname":"Linda Estrella",
    "gn:country_code":"MX",
    "gn:dem":1194,
    "gn:feature_class":"P",
    "gn:feature_code":"PPL",
    "gn:name":"Linda Estrella",
    "gn:population":239,
    "gn:timezone":"America/Mexico_City",
    "iso:country":"MX",
    "name:nld_x_preferred":[
        "Linda Estrella"
    ],
    "name:tgl_x_preferred":[
        "Linda Estrella"
    ],
    "wof:name":"Linda Estrella",
    "wof:placetype":"locality",
    "wof:population":239
},
  "geometry": {"coordinates":[-96.88139,18.69778],"type":"Point"}
}