{
  "type": "Feature",
  "properties": {
    "gn:admin1_code":"6",
    "gn:admin2_code":"46.0",
    "gn:asciiname":"Masayachi",
    "gn:country_code":"MX",
    "gn:dem":2137,
    "gn:feature_class":"P",
    "gn:feature_code":"PPL",
    "gn:name":"Masayachi",
    "gn:population":0,
    "gn:timezone":"America/Chihuahua",
    "iso:country":"MX",
    "name:spa_x_preferred":[
        "Masayachi"
    ],
    "wof:name":"Masayachi",
    "wof:placetype":"locality"
},
  "geometry": {"coordinates":[-107.73318999999999,26.50868],"type":"Point"}
}