{
  "type": "Feature",
  "properties": {
    "gn:admin1_code":"24",
    "gn:admin2_code":"32.0",
    "gn:asciiname":"Puerto Hondo",
    "gn:country_code":"MX",
    "gn:dem":2024,
    "gn:feature_class":"P",
    "gn:feature_code":"PPL",
    "gn:name":"Puerto Hondo",
    "gn:population":7,
    "gn:timezone":"America/Mexico_City",
    "iso:country":"MX",
    "wof:name":"Puerto Hondo",
    "wof:placetype":"locality",
    "wof:population":7
},
  "geometry": {"coordinates":[-100.29806000000001,21.75528],"type":"Point"}
}