{
  "type": "Feature",
  "properties": {
    "gn:admin1_code":"18.0",
    "gn:asciiname":"La Iguana",
    "gn:country_code":"MX",
    "gn:dem":862,
    "gn:feature_class":"P",
    "gn:feature_code":"PPL",
    "gn:name":"La Iguana",
    "gn:population":0,
    "gn:timezone":"America/Mexico_City",
    "iso:country":"MX",
    "name:spa_x_preferred":[
        "La Iguana"
    ],
    "name:spa_x_variant":[
        "El Aguacate"
    ],
    "wof:name":"La Iguana",
    "wof:placetype":"locality"
},
  "geometry": {"coordinates":[-104.35097,20.72601],"type":"Point"}
}