{
  "type": "Feature",
  "properties": {
    "gn:admin1_code":"20",
    "gn:admin2_code":"214.0",
    "gn:asciiname":"Santa Maria las Nieves",
    "gn:country_code":"MX",
    "gn:dem":2000,
    "gn:feature_class":"P",
    "gn:feature_code":"PPL",
    "gn:name":"Santa Mar\u00eda las Nieves",
    "gn:population":0,
    "gn:timezone":"America/Mexico_City",
    "iso:country":"MX",
    "name:spa_x_preferred":[
        "Santa Mar\u00eda las Nieves"
    ],
    "name:und_x_variant":[
        "Nieves",
        "Santa Maria",
        "Santa Mar\u00eda Nieves"
    ],
    "wof:name":"Santa Maria las Nieves",
    "wof:placetype":"locality"
},
  "geometry": {"coordinates":[-96.56234000000001,17.62711000000001],"type":"Point"}
}