{
  "type": "Feature",
  "properties": {
    "gn:admin1_code":"30.0",
    "gn:admin2_code":"189.0",
    "gn:asciiname":"La Colmena",
    "gn:country_code":"MX",
    "gn:dem":14,
    "gn:feature_class":"P",
    "gn:feature_code":"PPL",
    "gn:name":"La Colmena",
    "gn:population":0,
    "gn:timezone":"America/Mexico_City",
    "iso:country":"MX",
    "name:spa_x_preferred":[
        "La Colmena"
    ],
    "wof:name":"La Colmena",
    "wof:placetype":"locality"
},
  "geometry": {"coordinates":[-97.32361,20.81194],"type":"Point"}
}