{
  "type": "Feature",
  "properties": {
    "gn:admin1_code":"11",
    "gn:admin2_code":"27.0",
    "gn:asciiname":"San Jose de las Adjuntas",
    "gn:country_code":"MX",
    "gn:dem":1720,
    "gn:feature_class":"P",
    "gn:feature_code":"PPL",
    "gn:name":"San Jos\u00e9 de las Adjuntas",
    "gn:population":69,
    "gn:timezone":"America/Mexico_City",
    "iso:country":"MX",
    "name:und_x_variant":[
        "San Jos\u00e9 de las Adjuntas"
    ],
    "wof:name":"San Jose de las Adjuntas",
    "wof:placetype":"locality",
    "wof:population":69
},
  "geometry": {"coordinates":[-101.13222,20.54417],"type":"Point"}
}