{
  "type": "Feature",
  "properties": {
    "gn:admin1_code":"1",
    "gn:admin2_code":"3.0",
    "gn:asciiname":"Presa de los Bajios",
    "gn:cc2":"MX",
    "gn:country_code":"MX",
    "gn:dem":2429,
    "gn:feature_class":"P",
    "gn:feature_code":"PPL",
    "gn:name":"Presa de los Baj\u00edos",
    "gn:population":0,
    "gn:timezone":"America/Mexico_City",
    "iso:country":"MX",
    "name:und_x_variant":[
        "Presa Bajio",
        "Presa de los Baj\u00edos"
    ],
    "wof:name":"Presa de los Bajios",
    "wof:placetype":"locality"
},
  "geometry": {"coordinates":[-102.81667,21.96667],"type":"Point"}
}