{
  "type": "Feature",
  "properties": {
    "gn:admin1_code":"11",
    "gn:admin2_code":"44",
    "gn:asciiname":"El Puente (Avenida el Cuartel)",
    "gn:country_code":"MX",
    "gn:dem":1726,
    "gn:feature_class":"P",
    "gn:feature_code":"PPL",
    "gn:name":"El Puente (Avenida el Cuartel)",
    "gn:population":49,
    "gn:timezone":"America/Mexico_City",
    "iso:country":"MX",
    "wof:name":"El Puente (Avenida el Cuartel)",
    "wof:placetype":"locality",
    "wof:population":49
},
  "geometry": {"coordinates":[-101.06245,20.50917],"type":"Point"}
}