{
  "type": "Feature",
  "properties": {
    "gn:admin1_code":"10",
    "gn:admin2_code":"7.0",
    "gn:asciiname":"Sector II",
    "gn:country_code":"MX",
    "gn:dem":1122,
    "gn:feature_class":"P",
    "gn:feature_code":"PPL",
    "gn:name":"Sector II",
    "gn:population":8,
    "gn:timezone":"America/Monterrey",
    "iso:country":"MX",
    "wof:name":"Sector II",
    "wof:placetype":"locality",
    "wof:population":8
},
  "geometry": {"coordinates":[-103.35391,25.7108],"type":"Point"}
}