{
  "type": "Feature",
  "properties": {
    "gn:admin1_code":"10",
    "gn:admin2_code":"2.0",
    "gn:asciiname":"Mirasolar",
    "gn:country_code":"MX",
    "gn:dem":996,
    "gn:feature_class":"P",
    "gn:feature_code":"PPL",
    "gn:name":"Mirasolar",
    "gn:population":6,
    "gn:timezone":"America/Monterrey",
    "iso:country":"MX",
    "wof:name":"Mirasolar",
    "wof:placetype":"locality",
    "wof:population":6
},
  "geometry": {"coordinates":[-106.69723,25.11196],"type":"Point"}
}