{
  "type": "Feature",
  "properties": {
    "gn:admin1_code":"6",
    "gn:admin2_code":"21.0",
    "gn:asciiname":"Colonia Terrazas",
    "gn:country_code":"MX",
    "gn:dem":1158,
    "gn:feature_class":"P",
    "gn:feature_code":"PPL",
    "gn:name":"Colonia Terrazas",
    "gn:population":0,
    "gn:timezone":"America/Chihuahua",
    "iso:country":"MX",
    "name:und_x_variant":[
        "Terrazas"
    ],
    "wof:name":"Colonia Terrazas",
    "wof:placetype":"locality"
},
  "geometry": {"coordinates":[-105.46527,28.23795],"type":"Point"}
}