{
  "type": "Feature",
  "properties": {
    "gn:admin1_code":"30.0",
    "gn:admin2_code":"123.0",
    "gn:asciiname":"El Treinta y Seis",
    "gn:country_code":"MX",
    "gn:dem":44,
    "gn:feature_class":"P",
    "gn:feature_code":"PPL",
    "gn:name":"El Treinta y Seis",
    "gn:population":1,
    "gn:timezone":"America/Mexico_City",
    "iso:country":"MX",
    "name:spa_x_preferred":[
        "El Treinta y Seis"
    ],
    "wof:name":"El Treinta y Seis",
    "wof:placetype":"locality",
    "wof:population":1
},
  "geometry": {"coordinates":[-98.32333,22.22167],"type":"Point"}
}