{
  "type": "Feature",
  "properties": {
    "gn:admin1_code":"6",
    "gn:admin2_code":"27.0",
    "gn:asciiname":"Bajisochi",
    "gn:country_code":"MX",
    "gn:dem":2351,
    "gn:feature_class":"P",
    "gn:feature_code":"PPL",
    "gn:name":"Bajisochi",
    "gn:population":24,
    "gn:timezone":"America/Chihuahua",
    "iso:country":"MX",
    "name:spa_x_preferred":[
        "Bajisochi"
    ],
    "wof:name":"Bajisochi",
    "wof:placetype":"locality",
    "wof:population":24
},
  "geometry": {"coordinates":[-107.11017,27.0641],"type":"Point"}
}