{
  "type": "Feature",
  "properties": {
    "gn:admin1_code":"27",
    "gn:admin2_code":"5.0",
    "gn:asciiname":"El Guayo Primera Seccion",
    "gn:country_code":"MX",
    "gn:dem":9,
    "gn:feature_class":"P",
    "gn:feature_code":"PPL",
    "gn:name":"El Guayo Primera Secci\u00f3n",
    "gn:population":0,
    "gn:timezone":"America/Mexico_City",
    "iso:country":"MX",
    "name:spa_x_preferred":[
        "El Guayo Primera Secci\u00f3n"
    ],
    "wof:name":"El Guayo Primera Seccion",
    "wof:placetype":"locality"
},
  "geometry": {"coordinates":[-93.41936,18.29897],"type":"Point"}
}