{
  "type": "Feature",
  "properties": {
    "gn:admin1_code":"5",
    "gn:admin2_code":"79",
    "gn:asciiname":"El Alteno",
    "gn:country_code":"MX",
    "gn:dem":974,
    "gn:feature_class":"P",
    "gn:feature_code":"PPL",
    "gn:name":"El Alte\u00f1o",
    "gn:population":10,
    "gn:timezone":"America/Mexico_City",
    "iso:country":"MX",
    "name:und_x_variant":[
        "El Alte\u00f1o"
    ],
    "wof:name":"El Alteno",
    "wof:placetype":"locality",
    "wof:population":10
},
  "geometry": {"coordinates":[-93.16943999999999,16.91417],"type":"Point"}
}