{
  "type": "Feature",
  "properties": {
    "gn:admin1_code":"14",
    "gn:admin2_code":"43.0",
    "gn:asciiname":"Las Trojas",
    "gn:country_code":"MX",
    "gn:dem":107,
    "gn:feature_class":"P",
    "gn:feature_code":"PPL",
    "gn:name":"Las Trojas",
    "gn:population":0,
    "gn:timezone":"America/Mexico_City",
    "iso:country":"MX",
    "name:spa_x_preferred":[
        "Las Trojas"
    ],
    "wof:name":"Las Trojas",
    "wof:placetype":"locality"
},
  "geometry": {"coordinates":[-104.83734,19.54241],"type":"Point"}
}