{
  "type": "Feature",
  "properties": {
    "gn:admin1_code":"28.0",
    "gn:admin2_code":"42.0",
    "gn:asciiname":"Santa Lucia de Arriba",
    "gn:country_code":"MX",
    "gn:dem":472,
    "gn:feature_class":"P",
    "gn:feature_code":"PPL",
    "gn:name":"Santa Luc\u00eda de Arriba",
    "gn:population":0,
    "gn:timezone":"America/Monterrey",
    "iso:country":"MX",
    "name:spa_x_preferred":[
        "Santa Luc\u00eda de Arriba"
    ],
    "wof:name":"Santa Lucia de Arriba",
    "wof:placetype":"locality"
},
  "geometry": {"coordinates":[-99.55556,24.47944],"type":"Point"}
}