{
  "type": "Feature",
  "properties": {
    "gn:admin1_code":"20",
    "gn:admin2_code":"487",
    "gn:asciiname":"Loma Chacano",
    "gn:country_code":"MX",
    "gn:dem":1927,
    "gn:feature_class":"P",
    "gn:feature_code":"PPL",
    "gn:name":"Loma Chacano",
    "gn:population":52,
    "gn:timezone":"America/Mexico_City",
    "iso:country":"MX",
    "wof:name":"Loma Chacano",
    "wof:placetype":"locality",
    "wof:population":52
},
  "geometry": {"coordinates":[-96.99527999999999,17.34028],"type":"Point"}
}