{
  "type": "Feature",
  "properties": {
    "gn:admin1_code":"10",
    "gn:admin2_code":"35.0",
    "gn:asciiname":"Presidios de Abajo",
    "gn:cc2":"MX",
    "gn:country_code":"MX",
    "gn:dem":1750,
    "gn:feature_class":"P",
    "gn:feature_code":"PPL",
    "gn:name":"Presidios de Abajo",
    "gn:population":0,
    "gn:timezone":"America/Monterrey",
    "iso:country":"MX",
    "name:und_x_variant":[
        "Presidio de Abajo",
        "Presidios de Abajo"
    ],
    "wof:name":"Presidios de Abajo",
    "wof:placetype":"locality"
},
  "geometry": {"coordinates":[-105.61667,25.26667],"type":"Point"}
}