{
  "type": "Feature",
  "properties": {
    "gn:admin1_code":"32",
    "gn:admin2_code":"36.0",
    "gn:asciiname":"San Jose el Vaquero",
    "gn:country_code":"MX",
    "gn:dem":2103,
    "gn:feature_class":"P",
    "gn:feature_code":"PPL",
    "gn:name":"San Jos\u00e9 el Vaquero",
    "gn:population":0,
    "gn:timezone":"America/Mexico_City",
    "iso:country":"MX",
    "name:und_x_variant":[
        "Jos\u00e9 Vaquero",
        "San Jos\u00e9 Vaquero",
        "San Jos\u00e9 del Vaquero",
        "San Jos\u00e9 el Vaquero"
    ],
    "wof:name":"San Jose el Vaquero",
    "wof:placetype":"locality"
},
  "geometry": {"coordinates":[-102.1964,22.55888],"type":"Point"}
}