{
  "type": "Feature",
  "properties": {
    "gn:admin1_code":"27",
    "gn:admin2_code":"9.0",
    "gn:asciiname":"Jesus Maria",
    "gn:country_code":"MX",
    "gn:dem":14,
    "gn:feature_class":"P",
    "gn:feature_code":"PPL",
    "gn:name":"Jes\u00fas Mar\u00eda",
    "gn:population":9,
    "gn:timezone":"America/Mexico_City",
    "iso:country":"MX",
    "name:und_x_variant":[
        "Jes\u00fas Mar\u00eda"
    ],
    "wof:name":"Jesus Maria",
    "wof:placetype":"locality",
    "wof:population":9
},
  "geometry": {"coordinates":[-92.80806,17.7125],"type":"Point"}
}