{
  "type": "Feature",
  "properties": {
    "gn:admin1_code":"14.0",
    "gn:admin2_code":"79.0",
    "gn:asciiname":"Las Calabazas",
    "gn:country_code":"MX",
    "gn:dem":1906,
    "gn:feature_class":"P",
    "gn:feature_code":"PPL",
    "gn:name":"Las Calabazas",
    "gn:population":0,
    "gn:timezone":"America/Mexico_City",
    "iso:country":"MX",
    "name:spa_x_preferred":[
        "Las Calabazas"
    ],
    "wof:name":"Las Calabazas",
    "wof:placetype":"locality"
},
  "geometry": {"coordinates":[-103.35796000000001,19.85961],"type":"Point"}
}