{
  "type": "Feature",
  "properties": {
    "gn:admin1_code":"19.0",
    "gn:asciiname":"La Chapena",
    "gn:country_code":"MX",
    "gn:dem":325,
    "gn:feature_class":"P",
    "gn:feature_code":"PPL",
    "gn:name":"La Chape\u00f1a",
    "gn:population":0,
    "gn:timezone":"America/Monterrey",
    "iso:country":"MX",
    "name:spa_x_preferred":[
        "La Chape\u00f1a"
    ],
    "name:spa_x_variant":[
        "La Champe\u00f1a"
    ],
    "wof:name":"La Chapena",
    "wof:placetype":"locality"
},
  "geometry": {"coordinates":[-99.52878,24.88606],"type":"Point"}
}