{
  "type": "Feature",
  "properties": {
    "gn:admin1_code":"14.0",
    "gn:admin2_code":"116.0",
    "gn:asciiname":"Arroyo Seco de Abajo",
    "gn:country_code":"MX",
    "gn:dem":1967,
    "gn:feature_class":"P",
    "gn:feature_code":"PPL",
    "gn:name":"Arroyo Seco de Abajo",
    "gn:population":0,
    "gn:timezone":"America/Mexico_City",
    "iso:country":"MX",
    "name:spa_x_preferred":[
        "Arroyo Seco de Abajo"
    ],
    "wof:name":"Arroyo Seco de Abajo",
    "wof:placetype":"locality"
},
  "geometry": {"coordinates":[-102.60137,21.69301],"type":"Point"}
}