{
  "type": "Feature",
  "properties": {
    "gn:admin1_code":"25.0",
    "gn:admin2_code":"6.0",
    "gn:asciiname":"Campo el Porvenir",
    "gn:cc2":"MX",
    "gn:country_code":"MX",
    "gn:dem":16,
    "gn:feature_class":"P",
    "gn:feature_code":"PPL",
    "gn:name":"Campo el Porvenir",
    "gn:population":498,
    "gn:timezone":"America/Mazatlan",
    "iso:country":"MX",
    "name:und_x_variant":[
        "Porvenir",
        "El Porvenir"
    ],
    "wof:name":"Campo el Porvenir",
    "wof:placetype":"locality",
    "wof:population":498
},
  "geometry": {"coordinates":[-107.50806,24.63667],"type":"Point"}
}