{
  "type": "Feature",
  "properties": {
    "gn:admin1_code":"15",
    "gn:admin2_code":"45.0",
    "gn:asciiname":"Shindeje",
    "gn:country_code":"MX",
    "gn:dem":2418,
    "gn:feature_class":"P",
    "gn:feature_code":"PPL",
    "gn:name":"Shindej\u00e9",
    "gn:population":0,
    "gn:timezone":"America/Mexico_City",
    "iso:country":"MX",
    "wof:name":"Shindeje",
    "wof:placetype":"locality"
},
  "geometry": {"coordinates":[-99.48333,19.95],"type":"Point"}
}