{
  "type": "Feature",
  "properties": {
    "gn:admin1_code":"4",
    "gn:admin2_code":"6.0",
    "gn:asciiname":"Chembalan",
    "gn:country_code":"MX",
    "gn:dem":85,
    "gn:feature_class":"P",
    "gn:feature_code":"PPL",
    "gn:name":"Chembal\u00e1n",
    "gn:population":0,
    "gn:timezone":"America/Merida",
    "iso:country":"MX",
    "wof:name":"Chembalan",
    "wof:placetype":"locality"
},
  "geometry": {"coordinates":[-89.51666999999998,19.63333],"type":"Point"}
}