{
  "type": "Feature",
  "properties": {
    "gn:admin1_code":"26",
    "gn:admin2_code":"12.0",
    "gn:asciiname":"Maria Puente",
    "gn:country_code":"MX",
    "gn:dem":12,
    "gn:feature_class":"P",
    "gn:feature_code":"PPL",
    "gn:name":"Mar\u00eda Puente",
    "gn:population":5,
    "gn:timezone":"America/Hermosillo",
    "iso:country":"MX",
    "name:und_x_variant":[
        "Mar\u00eda Puente"
    ],
    "wof:name":"Maria Puente",
    "wof:placetype":"locality",
    "wof:population":5
},
  "geometry": {"coordinates":[-110.11667,27.33639],"type":"Point"}
}