{
  "type": "Feature",
  "properties": {
    "gn:admin1_code":"14",
    "gn:admin2_code":"72",
    "gn:asciiname":"El Salitrillo",
    "gn:country_code":"MX",
    "gn:dem":1998,
    "gn:feature_class":"P",
    "gn:feature_code":"PPL",
    "gn:name":"El Salitrillo",
    "gn:population":37,
    "gn:timezone":"America/Mexico_City",
    "iso:country":"MX",
    "wof:name":"El Salitrillo",
    "wof:placetype":"locality",
    "wof:population":37
},
  "geometry": {"coordinates":[-102.08667,21.03889],"type":"Point"}
}