{
  "type": "Feature",
  "properties": {
    "gn:admin1_code":"13",
    "gn:admin2_code":"24.0",
    "gn:asciiname":"El Vite",
    "gn:country_code":"MX",
    "gn:dem":1753,
    "gn:feature_class":"P",
    "gn:feature_code":"PPL",
    "gn:name":"El Vite",
    "gn:population":0,
    "gn:timezone":"America/Mexico_City",
    "iso:country":"MX",
    "name:und_x_variant":[
        "Vite",
        "El Vite"
    ],
    "wof:name":"El Vite",
    "wof:placetype":"locality"
},
  "geometry": {"coordinates":[-98.49912999999999,20.25986],"type":"Point"}
}