{
  "type": "Feature",
  "properties": {
    "gn:admin1_code":"16",
    "gn:admin2_code":"15",
    "gn:asciiname":"El Corongoro",
    "gn:country_code":"MX",
    "gn:dem":1090,
    "gn:feature_class":"P",
    "gn:feature_code":"PPL",
    "gn:name":"El Corongoro",
    "gn:population":11,
    "gn:timezone":"America/Mexico_City",
    "iso:country":"MX",
    "wof:name":"El Corongoro",
    "wof:placetype":"locality",
    "wof:population":11
},
  "geometry": {"coordinates":[-103.12417000000001,18.85861],"type":"Point"}
}