{
  "type": "Feature",
  "properties": {
    "gn:admin1_code":"32",
    "gn:asciiname":"Loreto",
    "gn:country_code":"MX",
    "gn:dem":2248,
    "gn:feature_class":"P",
    "gn:feature_code":"PPL",
    "gn:name":"Loreto",
    "gn:population":0,
    "gn:timezone":"America/Monterrey",
    "iso:country":"MX",
    "name:ben_x_preferred":[
        "\u09b2\u09cb\u09b0\u09c7\u09a4\u09cb"
    ],
    "name:bpy_x_preferred":[
        "\u09b2\u09cb\u09b0\u09c7\u099f\u09cb"
    ],
    "name:bre_x_preferred":[
        "Loreto"
    ],
    "name:cat_x_preferred":[
        "Loreto"
    ],
    "name:ceb_x_preferred":[
        "Loreto"
    ],
    "name:ces_x_preferred":[
        "Loreto"
    ],
    "name:deu_x_preferred":[
        "Loreto"
    ],
    "name:ell_x_preferred":[
        "\u039b\u03bf\u03c1\u03ad\u03c4\u03bf"
    ],
    "name:epo_x_preferred":[
        "Loreto"
    ],
    "name:eus_x_preferred":[
        "Loreto"
    ],
    "name:fra_x_preferred":[
        "Loreto"
    ],
    "name:glg_x_preferred":[
        "Loreto"
    ],
    "name:heb_x_preferred":[
        "\u05dc\u05d5\u05e8\u05d9"
    ],
    "name:hin_x_preferred":[
        "\u0932\u094b\u0930\u0947\u091f\u094b"
    ],
    "name:hrv_x_preferred":[
        "Loreto"
    ],
    "name:hun_x_preferred":[
        "Loreto"
    ],
    "name:ita_x_preferred":[
        "Loreto"
    ],
    "name:kaz_x_preferred":[
        "\u041b\u043e\u0440\u0435\u0442\u043e"
    ],
    "name:kor_x_preferred":[
        "\ub85c\ub808\ud1a0"
    ],
    "name:lmo_x_preferred":[
        "Lor\u00e9t"
    ],
    "name:nld_x_preferred":[
        "Loreto"
    ],
    "name:nor_x_preferred":[
        "Loreto"
    ],
    "name:pol_x_preferred":[
        "Loreto"
    ],
    "name:por_x_preferred":[
        "Loreto"
    ],
    "name:rus_x_preferred":[
        "\u041b\u043e\u0440\u0435\u0442\u043e"
    ],
    "name:sco_x_preferred":[
        "Loreto"
    ],
    "name:slk_x_preferred":[
        "Loreto"
    ],
    "name:spa_x_preferred":[
        "Loreto"
    ],
    "name:srp_x_preferred":[
        "\u041b\u043e\u0440\u0435\u0442\u043e"
    ],
    "name:swe_x_preferred":[
        "Loreto"
    ],
    "name:ukr_x_preferred":[
        "\u041b\u043e\u0440\u0435\u0442\u043e"
    ],
    "name:urd_x_preferred":[
        "\u0644\u0648\u0631\u06cc\u0679\u0648"
    ],
    "name:vol_x_preferred":[
        "Loreto"
    ],
    "name:war_x_preferred":[
        "Loreto"
    ],
    "wof:name":"Loreto",
    "wof:placetype":"locality"
},
  "geometry": {"coordinates":[-101.18333,24.76667],"type":"Point"}
}