{
  "type": "Feature",
  "properties": {
    "gn:admin1_code":"32",
    "gn:asciiname":"Loreto",
    "gn:country_code":"MX",
    "gn:dem":2248,
    "gn:feature_class":"P",
    "gn:feature_code":"PPL",
    "gn:name":"Loreto",
    "gn:population":0,
    "gn:timezone":"America/Monterrey",
    "iso:country":"MX",
    "name:bpy_x_preferred":[
        "\u09b2\u09cb\u09b0\u09c7\u099f\u09cb"
    ],
    "name:bre_x_preferred":[
        "Loreto"
    ],
    "name:cat_x_preferred":[
        "Loreto"
    ],
    "name:ceb_x_preferred":[
        "Loreto"
    ],
    "name:ces_x_preferred":[
        "Loreto"
    ],
    "name:deu_x_preferred":[
        "Loreto"
    ],
    "name:epo_x_preferred":[
        "Loreto"
    ],
    "name:eus_x_preferred":[
        "Loreto"
    ],
    "name:fra_x_preferred":[
        "Loreto"
    ],
    "name:glg_x_preferred":[
        "Loreto"
    ],
    "name:hrv_x_preferred":[
        "Loreto"
    ],
    "name:hun_x_preferred":[
        "Loreto"
    ],
    "name:ita_x_preferred":[
        "Loreto"
    ],
    "name:kaz_x_preferred":[
        "\u041b\u043e\u0440\u0435\u0442\u043e"
    ],
    "name:kor_x_preferred":[
        "\ub85c\ub808\ud1a0"
    ],
    "name:lmo_x_preferred":[
        "Lor\u00e9t"
    ],
    "name:nld_x_preferred":[
        "Loreto"
    ],
    "name:nor_x_preferred":[
        "Loreto"
    ],
    "name:pol_x_preferred":[
        "Loreto"
    ],
    "name:por_x_preferred":[
        "Loreto"
    ],
    "name:rus_x_preferred":[
        "\u041b\u043e\u0440\u0435\u0442\u043e"
    ],
    "name:sco_x_preferred":[
        "Loreto"
    ],
    "name:slk_x_preferred":[
        "Loreto"
    ],
    "name:spa_x_preferred":[
        "Loreto"
    ],
    "name:srp_x_preferred":[
        "\u041b\u043e\u0440\u0435\u0442\u043e"
    ],
    "name:swe_x_preferred":[
        "Loreto"
    ],
    "name:vol_x_preferred":[
        "Loreto"
    ],
    "name:war_x_preferred":[
        "Loreto"
    ],
    "wof:name":"Loreto",
    "wof:placetype":"locality"
},
  "geometry": {"coordinates":[-101.18333,24.76667],"type":"Point"}
}