{
  "type": "Feature",
  "properties": {
    "gn:admin1_code":"26",
    "gn:admin2_code":"10.0",
    "gn:asciiname":"Dos Cabezas",
    "gn:country_code":"MX",
    "gn:dem":1784,
    "gn:feature_class":"P",
    "gn:feature_code":"PPL",
    "gn:name":"Dos Cabezas",
    "gn:population":0,
    "gn:timezone":"America/Hermosillo",
    "iso:country":"MX",
    "name:spa_x_preferred":[
        "Dos Cabezas"
    ],
    "wof:name":"Dos Cabezas",
    "wof:placetype":"locality"
},
  "geometry": {"coordinates":[-108.66749,30.38698],"type":"Point"}
}