{
  "type": "Feature",
  "properties": {
    "gn:admin1_code":"6",
    "gn:admin2_code":"9.0",
    "gn:asciiname":"Chupeachi",
    "gn:country_code":"MX",
    "gn:dem":2404,
    "gn:feature_class":"P",
    "gn:feature_code":"PPL",
    "gn:name":"Chupeachi",
    "gn:population":8,
    "gn:timezone":"America/Chihuahua",
    "iso:country":"MX",
    "wof:name":"Chupeachi",
    "wof:placetype":"locality",
    "wof:population":8
},
  "geometry": {"coordinates":[-107.35102999999999,27.70492],"type":"Point"}
}