{
  "type": "Feature",
  "properties": {
    "gn:admin1_code":"30.0",
    "gn:asciiname":"Puente de Oro",
    "gn:country_code":"MX",
    "gn:dem":590,
    "gn:feature_class":"P",
    "gn:feature_code":"PPL",
    "gn:name":"Puente de Oro",
    "gn:population":0,
    "gn:timezone":"America/Mexico_City",
    "iso:country":"MX",
    "name:spa_x_preferred":[
        "Puente de Oro"
    ],
    "wof:name":"Puente de Oro",
    "wof:placetype":"locality"
},
  "geometry": {"coordinates":[-96.83790999999999,18.84898],"type":"Point"}
}