{
  "type": "Feature",
  "properties": {
    "gn:admin1_code":"32",
    "gn:admin2_code":"10.0",
    "gn:asciiname":"Los Hernandez",
    "gn:country_code":"MX",
    "gn:dem":2060,
    "gn:feature_class":"P",
    "gn:feature_code":"PPL",
    "gn:name":"Los Hern\u00e1ndez",
    "gn:population":0,
    "gn:timezone":"America/Mexico_City",
    "iso:country":"MX",
    "name:spa_x_preferred":[
        "Los Hern\u00e1ndez"
    ],
    "wof:name":"Los Hernandez",
    "wof:placetype":"locality"
},
  "geometry": {"coordinates":[-102.89011000000001,23.40057],"type":"Point"}
}