{
  "type": "Feature",
  "properties": {
    "gn:admin1_code":"3",
    "gn:admin2_code":"9.0",
    "gn:asciiname":"El Batequito",
    "gn:country_code":"MX",
    "gn:dem":509,
    "gn:feature_class":"P",
    "gn:feature_code":"PPL",
    "gn:name":"El Batequito",
    "gn:population":0,
    "gn:timezone":"America/Mazatlan",
    "iso:country":"MX",
    "name:spa_x_preferred":[
        "El Batequito"
    ],
    "wof:name":"El Batequito",
    "wof:placetype":"locality"
},
  "geometry": {"coordinates":[-111.63144,26.00274],"type":"Point"}
}