{
  "type": "Feature",
  "properties": {
    "gn:admin1_code":"5",
    "gn:admin2_code":"4.0",
    "gn:asciiname":"Nuevo San Carlos",
    "gn:country_code":"MX",
    "gn:dem":1214,
    "gn:feature_class":"P",
    "gn:feature_code":"PPL",
    "gn:name":"Nuevo San Carlos",
    "gn:population":560,
    "gn:timezone":"America/Mexico_City",
    "iso:country":"MX",
    "name:ceb_x_preferred":[
        "Nuevo San Carlos"
    ],
    "name:fas_x_preferred":[
        "\u0646\u0648\u0648\u0647 \u0633\u0646 \u06a9\u0627\u0631\u0644\u0648\u0633"
    ],
    "name:fra_x_preferred":[
        "Nuevo San Carlos"
    ],
    "name:ita_x_preferred":[
        "Nuevo San Carlos"
    ],
    "name:pol_x_preferred":[
        "Nuevo San Carlos"
    ],
    "name:por_x_preferred":[
        "Nuevo San Carlos"
    ],
    "name:swe_x_preferred":[
        "Nuevo San Carlos"
    ],
    "name:urd_x_preferred":[
        "\u0646\u0648\u06cc\u0648\u0648 \u0633\u0627\u0646 \u06a9\u0627\u0631\u0644\u0648\u0633"
    ],
    "name:zho_x_preferred":[
        "\u65b0\u8056\u5361\u6d1b\u65af"
    ],
    "wof:name":"Nuevo San Carlos",
    "wof:placetype":"locality",
    "wof:population":560
},
  "geometry": {"coordinates":[-91.96666999999999,16.69333],"type":"Point"}
}