{
  "type": "Feature",
  "properties": {
    "gn:admin1_code":"10.0",
    "gn:admin2_code":"9.0",
    "gn:asciiname":"El Rio",
    "gn:country_code":"MX",
    "gn:dem":2309,
    "gn:feature_class":"P",
    "gn:feature_code":"PPL",
    "gn:name":"El R\u00edo",
    "gn:population":0,
    "gn:timezone":"America/Monterrey",
    "iso:country":"MX",
    "name:spa_x_preferred":[
        "El R\u00edo"
    ],
    "wof:name":"El Rio",
    "wof:placetype":"locality"
},
  "geometry": {"coordinates":[-106.26272,25.7929],"type":"Point"}
}