{
  "type": "Feature",
  "properties": {
    "gn:admin1_code":"17",
    "gn:admin2_code":"28",
    "gn:asciiname":"Ojo de Agua",
    "gn:country_code":"MX",
    "gn:dem":1160,
    "gn:feature_class":"P",
    "gn:feature_code":"PPL",
    "gn:name":"Ojo de Agua",
    "gn:population":29,
    "gn:timezone":"America/Mexico_City",
    "iso:country":"MX",
    "wof:name":"Ojo de Agua",
    "wof:placetype":"locality",
    "wof:population":29
},
  "geometry": {"coordinates":[-99.2075,18.79222],"type":"Point"}
}