{
  "type": "Feature",
  "properties": {
    "gn:admin1_code":"14.0",
    "gn:admin2_code":"35.0",
    "gn:asciiname":"El Tunel",
    "gn:country_code":"MX",
    "gn:dem":1875,
    "gn:feature_class":"P",
    "gn:feature_code":"PPL",
    "gn:name":"El T\u00fanel",
    "gn:population":0,
    "gn:timezone":"America/Mexico_City",
    "iso:country":"MX",
    "name:spa_x_preferred":[
        "El T\u00fanel"
    ],
    "wof:name":"El Tunel",
    "wof:placetype":"locality"
},
  "geometry": {"coordinates":[-102.28321,21.63167],"type":"Point"}
}