{
  "type": "Feature",
  "properties": {
    "gn:admin1_code":"16.0",
    "gn:admin2_code":"96.0",
    "gn:asciiname":"Pantoja",
    "gn:country_code":"MX",
    "gn:dem":1499,
    "gn:feature_class":"P",
    "gn:feature_code":"PPL",
    "gn:name":"Pantoja",
    "gn:population":0,
    "gn:timezone":"America/Mexico_City",
    "iso:country":"MX",
    "name:spa_x_preferred":[
        "Pantoja"
    ],
    "wof:name":"Pantoja",
    "wof:placetype":"locality"
},
  "geometry": {"coordinates":[-102.60917000000001,18.48067],"type":"Point"}
}