{
  "type": "Feature",
  "properties": {
    "gn:admin1_code":"13",
    "gn:admin2_code":"68",
    "gn:asciiname":"La Tejeria",
    "gn:country_code":"MX",
    "gn:dem":1564,
    "gn:feature_class":"P",
    "gn:feature_code":"PPL",
    "gn:name":"La Tejeria",
    "gn:population":44,
    "gn:timezone":"America/Mexico_City",
    "iso:country":"MX",
    "wof:name":"La Tejeria",
    "wof:placetype":"locality",
    "wof:population":44
},
  "geometry": {"coordinates":[-98.62576,20.72236],"type":"Point"}
}