{
  "type": "Feature",
  "properties": {
    "gn:admin1_code":"13",
    "gn:admin2_code":"70",
    "gn:asciiname":"Colonia Guadalupe (Cerro del Tezontle)",
    "gn:country_code":"MX",
    "gn:dem":2072,
    "gn:feature_class":"P",
    "gn:feature_code":"PPL",
    "gn:name":"Colonia Guadalupe (Cerro del Tezontle)",
    "gn:population":24,
    "gn:timezone":"America/Mexico_City",
    "iso:country":"MX",
    "wof:name":"Colonia Guadalupe (Cerro del Tezontle)",
    "wof:placetype":"locality",
    "wof:population":24
},
  "geometry": {"coordinates":[-99.22722,20.14917],"type":"Point"}
}