{
  "type": "Feature",
  "properties": {
    "gn:country":"MX",
    "gn:fcode":"PPL",
    "gn:population":14269,
    "iso:country":"MX",
    "name:ben_x_preferred":[
        "\u0997\u09c1\u09af\u09bc\u09be\u09a6\u09be\u09b2\u09c1\u09aa\u09c7 \u09ac\u09bf\u0995\u09cd\u09a4\u09cb\u09b0\u09bf\u09af\u09bc\u09be"
    ],
    "name:ceb_x_preferred":[
        "Guadalupe Victoria"
    ],
    "name:eng_x_preferred":[
        "Ciudad Guadalupe Victoria"
    ],
    "name:nld_x_preferred":[
        "Ciudad Guadalupe Victoria"
    ],
    "name:spa_x_preferred":[
        "Ciudad Guadalupe Victoria"
    ],
    "name:srp_x_preferred":[
        "\u0413\u0432\u0430\u0434\u0430\u043b\u0443\u043f\u0435 \u0412\u0438\u043a\u0442\u043e\u0440\u0438\u0458\u0430"
    ],
    "name:swe_x_preferred":[
        "Guadalupe Victoria"
    ],
    "name:und_x_variant":[
        "Tapona"
    ],
    "name:vie_x_preferred":[
        "Guadalupe Victoria"
    ],
    "qs_pg:aaroncc":"MX",
    "qs_pg:gn_country":"MX",
    "qs_pg:gn_fcode":"PPL",
    "qs_pg:gn_pop":14269,
    "qs_pg:name":"Ciudad Guadalupe Victoria",
    "qs_pg:name_adm0":"M\u00e9xico",
    "qs_pg:name_adm1":"Durango",
    "qs_pg:photos_9r":0,
    "qs_pg:photos_sr":0,
    "qs_pg:pop_sr":6,
    "qs_pg:qs_pg_placetype":"locality",
    "qs_pg:qs_pg_placetype_gp":"Town",
    "qs_pg:woe_adm0":23424900,
    "woe:adm0_id":23424900,
    "woe:name_adm0":"M\u00e9xico",
    "woe:name_adm1":"Durango",
    "woe:placetype":"Town",
    "wof:name":"Ciudad Guadalupe Victoria",
    "wof:placetype":"locality",
    "wof:population":14269
},
  "geometry": {"coordinates":[-104.12247000000001,24.44521],"type":"Point"}
}