{
  "type": "Feature",
  "properties": {
    "gn:country":"MX",
    "gn:fcode":"PPL",
    "gn:population":14269,
    "iso:country":"MX",
    "name:ceb_x_preferred":[
        "Guadalupe Victoria"
    ],
    "name:eng_x_preferred":[
        "Ciudad Guadalupe Victoria"
    ],
    "name:nld_x_preferred":[
        "Ciudad Guadalupe Victoria"
    ],
    "name:swe_x_preferred":[
        "Guadalupe Victoria"
    ],
    "name:und_x_variant":[
        "Tapona"
    ],
    "name:vie_x_preferred":[
        "Guadalupe Victoria"
    ],
    "qs_pg:aaroncc":"MX",
    "qs_pg:gn_country":"MX",
    "qs_pg:gn_fcode":"PPL",
    "qs_pg:gn_pop":14269,
    "qs_pg:name":"Ciudad Guadalupe Victoria",
    "qs_pg:name_adm0":"M\u00e9xico",
    "qs_pg:name_adm1":"Durango",
    "qs_pg:photos_9r":0,
    "qs_pg:photos_sr":0,
    "qs_pg:pop_sr":6,
    "qs_pg:qs_pg_placetype":"locality",
    "qs_pg:qs_pg_placetype_gp":"Town",
    "qs_pg:woe_adm0":23424900,
    "woe:adm0_id":23424900,
    "woe:name_adm0":"M\u00e9xico",
    "woe:name_adm1":"Durango",
    "woe:placetype":"Town",
    "wof:name":"Ciudad Guadalupe Victoria",
    "wof:placetype":"locality",
    "wof:population":14269
},
  "geometry": {"coordinates":[-104.12247000000001,24.44521],"type":"Point"}
}