{
  "type": "Feature",
  "properties": {
    "gn:admin1_code":"21",
    "gn:admin2_code":"137.0",
    "gn:asciiname":"Venustiano Carranza",
    "gn:country_code":"MX",
    "gn:dem":2406,
    "gn:feature_class":"P",
    "gn:feature_code":"PPL",
    "gn:name":"Venustiano Carranza",
    "gn:population":0,
    "gn:timezone":"America/Mexico_City",
    "iso:country":"MX",
    "name:spa_x_preferred":[
        "Venustiano Carranza"
    ],
    "wof:name":"Venustiano Carranza",
    "wof:placetype":"locality"
},
  "geometry": {"coordinates":[-97.47808000000001,19.22643],"type":"Point"}
}