{
  "type": "Feature",
  "properties": {
    "gn:admin1_code":"10.0",
    "gn:admin2_code":"35.0",
    "gn:asciiname":"El Venadito",
    "gn:country_code":"MX",
    "gn:dem":1811,
    "gn:feature_class":"P",
    "gn:feature_code":"PPL",
    "gn:name":"El Venadito",
    "gn:population":0,
    "gn:timezone":"America/Monterrey",
    "iso:country":"MX",
    "name:spa_x_preferred":[
        "El Venadito"
    ],
    "wof:name":"El Venadito",
    "wof:placetype":"locality"
},
  "geometry": {"coordinates":[-105.73617,25.34511],"type":"Point"}
}