{
  "type": "Feature",
  "properties": {
    "gn:admin1_code":"26",
    "gn:admin2_code":"42.0",
    "gn:asciiname":"Campo Santini",
    "gn:country_code":"MX",
    "gn:dem":26,
    "gn:feature_class":"P",
    "gn:feature_code":"PPL",
    "gn:name":"Campo Santini",
    "gn:population":0,
    "gn:timezone":"America/Hermosillo",
    "iso:country":"MX",
    "name:spa_x_preferred":[
        "Campo Santini"
    ],
    "wof:name":"Campo Santini",
    "wof:placetype":"locality"
},
  "geometry": {"coordinates":[-109.47149,26.97317],"type":"Point"}
}