{
  "type": "Feature",
  "properties": {
    "gn:admin1_code":"21.0",
    "gn:admin2_code":"104.0",
    "gn:asciiname":"La Floresta",
    "gn:country_code":"MX",
    "gn:dem":2483,
    "gn:feature_class":"P",
    "gn:feature_code":"PPL",
    "gn:name":"La Floresta",
    "gn:population":0,
    "gn:timezone":"America/Mexico_City",
    "iso:country":"MX",
    "name:cat_x_preferred":[
        "La Floresta"
    ],
    "name:ceb_x_preferred":[
        "La Floresta"
    ],
    "name:deu_x_preferred":[
        "La Floresta"
    ],
    "name:eus_x_preferred":[
        "La Floresta"
    ],
    "name:ita_x_preferred":[
        "La Floresta"
    ],
    "name:spa_x_preferred":[
        "La Floresta"
    ],
    "name:srp_x_preferred":[
        "\u041b\u0430 \u0424\u043b\u043e\u0440\u0435\u0441\u0442\u0430"
    ],
    "name:swe_x_preferred":[
        "La Floresta"
    ],
    "wof:name":"La Floresta",
    "wof:placetype":"locality"
},
  "geometry": {"coordinates":[-97.86556,19.19586],"type":"Point"}
}