{
  "type": "Feature",
  "properties": {
    "gn:admin1_code":"28",
    "gn:admin2_code":"22.0",
    "gn:asciiname":"El Control",
    "gn:country_code":"MX",
    "gn:dem":24,
    "gn:feature_class":"P",
    "gn:feature_code":"PPL",
    "gn:name":"El Control",
    "gn:population":3136,
    "gn:timezone":"America/Matamoros",
    "iso:country":"MX",
    "name:spa_x_preferred":[
        "El Control"
    ],
    "name:und_x_variant":[
        "Control Cik"
    ],
    "wof:name":"El Control",
    "wof:placetype":"locality",
    "wof:population":3136
},
  "geometry": {"coordinates":[-97.81281,25.95867],"type":"Point"}
}