{
  "type": "Feature",
  "properties": {
    "gn:admin1_code":"26.0",
    "gn:admin2_code":"47.0",
    "gn:asciiname":"La Banderita",
    "gn:country_code":"MX",
    "gn:dem":193,
    "gn:feature_class":"P",
    "gn:feature_code":"PPL",
    "gn:name":"La Banderita",
    "gn:population":0,
    "gn:timezone":"America/Hermosillo",
    "iso:country":"MX",
    "name:spa_x_preferred":[
        "La Banderita"
    ],
    "wof:name":"La Banderita",
    "wof:placetype":"locality"
},
  "geometry": {"coordinates":[-112.09196,29.60695],"type":"Point"}
}