{
  "type": "Feature",
  "properties": {
    "gn:admin1_code":"6.0",
    "gn:admin2_code":"52.0",
    "gn:asciiname":"Barrancos Blancos",
    "gn:country_code":"MX",
    "gn:dem":884,
    "gn:feature_class":"P",
    "gn:feature_code":"PPL",
    "gn:name":"Barrancos Blancos",
    "gn:population":0,
    "gn:timezone":"America/Ojinaga",
    "iso:country":"MX",
    "wof:name":"Barrancos Blancos",
    "wof:placetype":"locality"
},
  "geometry": {"coordinates":[-104.73333,30.06667],"type":"Point"}
}