{
  "type": "Feature",
  "properties": {
    "gn:admin1_code":"13",
    "gn:admin2_code":"30.0",
    "gn:asciiname":"Lopez Flores",
    "gn:country_code":"MX",
    "gn:dem":1789,
    "gn:feature_class":"P",
    "gn:feature_code":"PPL",
    "gn:name":"L\u00f3pez Flores",
    "gn:population":164,
    "gn:timezone":"America/Mexico_City",
    "iso:country":"MX",
    "name:und_x_variant":[
        "L\u00f3pez Flores"
    ],
    "wof:name":"Lopez Flores",
    "wof:placetype":"locality",
    "wof:population":164
},
  "geometry": {"coordinates":[-99.15006,20.54446],"type":"Point"}
}