{
  "type": "Feature",
  "properties": {
    "gn:admin1_code":"6.0",
    "gn:admin2_code":"14.0",
    "gn:asciiname":"La Cieneguilla",
    "gn:cc2":"MX",
    "gn:country_code":"MX",
    "gn:dem":1623,
    "gn:feature_class":"P",
    "gn:feature_code":"PPL",
    "gn:name":"La Cieneguilla",
    "gn:population":0,
    "gn:timezone":"America/Chihuahua",
    "iso:country":"MX",
    "name:und_x_variant":[
        "Cieneguilla",
        "La Cieneguilla"
    ],
    "wof:name":"La Cieneguilla",
    "wof:placetype":"locality"
},
  "geometry": {"coordinates":[-105.08333,26.65],"type":"Point"}
}