{
  "type": "Feature",
  "properties": {
    "gn:admin1_code":"25",
    "gn:admin2_code":"13.0",
    "gn:asciiname":"La Lechuza",
    "gn:country_code":"MX",
    "gn:dem":69,
    "gn:feature_class":"P",
    "gn:feature_code":"PPL",
    "gn:name":"La Lechuza",
    "gn:population":0,
    "gn:timezone":"America/Mazatlan",
    "iso:country":"MX",
    "name:spa_x_preferred":[
        "La Lechuza"
    ],
    "wof:name":"La Lechuza",
    "wof:placetype":"locality"
},
  "geometry": {"coordinates":[-107.65908,25.11622],"type":"Point"}
}