{
  "type": "Feature",
  "properties": {
    "gn:admin1_code":"14.0",
    "gn:admin2_code":"58.0",
    "gn:asciiname":"La Muertita",
    "gn:country_code":"MX",
    "gn:dem":1048,
    "gn:feature_class":"P",
    "gn:feature_code":"PPL",
    "gn:name":"La Muertita",
    "gn:population":0,
    "gn:timezone":"America/Mexico_City",
    "iso:country":"MX",
    "name:spa_x_preferred":[
        "La Muertita"
    ],
    "wof:name":"La Muertita",
    "wof:placetype":"locality"
},
  "geometry": {"coordinates":[-104.91749,20.56276],"type":"Point"}
}