{
  "type": "Feature",
  "properties": {
    "gn:admin1_code":"16",
    "gn:admin2_code":"82",
    "gn:asciiname":"El Llano de Puquitzimo",
    "gn:country_code":"MX",
    "gn:dem":2167,
    "gn:feature_class":"P",
    "gn:feature_code":"PPL",
    "gn:name":"El Llano de Puquitzimo",
    "gn:population":11,
    "gn:timezone":"America/Mexico_City",
    "iso:country":"MX",
    "wof:name":"El Llano de Puquitzimo",
    "wof:placetype":"locality",
    "wof:population":11
},
  "geometry": {"coordinates":[-101.50639,19.30639],"type":"Point"}
}