{
  "type": "Feature",
  "properties": {
    "gn:admin1_code":"11",
    "gn:admin2_code":"29.0",
    "gn:asciiname":"El Clarin",
    "gn:country_code":"MX",
    "gn:dem":2004,
    "gn:feature_class":"P",
    "gn:feature_code":"PPL",
    "gn:name":"El Clar\u00edn",
    "gn:population":6,
    "gn:timezone":"America/Mexico_City",
    "iso:country":"MX",
    "name:und_x_variant":[
        "El Clar\u00edn"
    ],
    "wof:name":"El Clarin",
    "wof:placetype":"locality",
    "wof:population":6
},
  "geometry": {"coordinates":[-100.72889000000001,21.30444],"type":"Point"}
}