{
  "type": "Feature",
  "properties": {
    "gn:admin1_code":"6",
    "gn:admin2_code":"65.0",
    "gn:asciiname":"Mesa de Arturo",
    "gn:country_code":"MX",
    "gn:dem":2297,
    "gn:feature_class":"P",
    "gn:feature_code":"PPL",
    "gn:name":"Mesa de Arturo",
    "gn:population":172,
    "gn:timezone":"America/Chihuahua",
    "iso:country":"MX",
    "wof:name":"Mesa de Arturo",
    "wof:placetype":"locality",
    "wof:population":172
},
  "geometry": {"coordinates":[-107.99843,27.22563],"type":"Point"}
}