{
  "type": "Feature",
  "properties": {
    "gn:admin1_code":"10",
    "gn:admin2_code":"23.0",
    "gn:asciiname":"Las Rusias",
    "gn:country_code":"MX",
    "gn:dem":2795,
    "gn:feature_class":"P",
    "gn:feature_code":"PPL",
    "gn:name":"Las Rusias",
    "gn:population":0,
    "gn:timezone":"America/Monterrey",
    "iso:country":"MX",
    "name:und_x_variant":[
        "Rucias"
    ],
    "wof:name":"Las Rusias",
    "wof:placetype":"locality"
},
  "geometry": {"coordinates":[-105.53394,23.75152000000001],"type":"Point"}
}