{
  "type": "Feature",
  "properties": {
    "gn:admin1_code":"10",
    "gn:admin2_code":"37.0",
    "gn:asciiname":"El Jardin",
    "gn:country_code":"MX",
    "gn:dem":1581,
    "gn:feature_class":"P",
    "gn:feature_code":"PPL",
    "gn:name":"El Jard\u00edn",
    "gn:population":4,
    "gn:timezone":"America/Monterrey",
    "iso:country":"MX",
    "name:und_x_variant":[
        "El Jard\u00edn"
    ],
    "wof:name":"El Jardin",
    "wof:placetype":"locality",
    "wof:population":4
},
  "geometry": {"coordinates":[-106.68093,25.25525],"type":"Point"}
}