{
  "type": "Feature",
  "properties": {
    "gn:admin1_code":"24",
    "gn:admin2_code":"38.0",
    "gn:asciiname":"Chilillo",
    "gn:country_code":"MX",
    "gn:dem":204,
    "gn:feature_class":"P",
    "gn:feature_code":"PPL",
    "gn:name":"Chilillo",
    "gn:population":0,
    "gn:timezone":"America/Mexico_City",
    "iso:country":"MX",
    "name:spa_x_preferred":[
        "Chilillo"
    ],
    "wof:name":"Chilillo",
    "wof:placetype":"locality"
},
  "geometry": {"coordinates":[-98.75476999999999,21.39488],"type":"Point"}
}