{
  "type": "Feature",
  "properties": {
    "gn:admin1_code":"25",
    "gn:admin2_code":"17.0",
    "gn:asciiname":"Rancho Lupe Felix",
    "gn:country_code":"MX",
    "gn:dem":52,
    "gn:feature_class":"P",
    "gn:feature_code":"PPL",
    "gn:name":"Rancho Lupe F\u00e9lix",
    "gn:population":5,
    "gn:timezone":"America/Mazatlan",
    "iso:country":"MX",
    "name:und_x_variant":[
        "Rancho Lupe F\u00e9lix"
    ],
    "wof:name":"Rancho Lupe Felix",
    "wof:placetype":"locality",
    "wof:population":5
},
  "geometry": {"coordinates":[-108.27979999999999,25.772],"type":"Point"}
}