{
  "type": "Feature",
  "properties": {
    "gn:admin1_code":"12.0",
    "gn:asciiname":"Matzala",
    "gn:country_code":"MX",
    "gn:dem":1150,
    "gn:feature_class":"P",
    "gn:feature_code":"PPL",
    "gn:name":"Matzala",
    "gn:population":0,
    "gn:timezone":"America/Mexico_City",
    "iso:country":"MX",
    "name:spa_x_preferred":[
        "Matzala"
    ],
    "wof:name":"Matzala",
    "wof:placetype":"locality"
},
  "geometry": {"coordinates":[-98.98984,18.22704],"type":"Point"}
}