{
  "type": "Feature",
  "properties": {
    "gn:admin1_code":"5",
    "gn:admin2_code":"27.0",
    "gn:asciiname":"Ignacio Allende",
    "gn:country_code":"MX",
    "gn:dem":443,
    "gn:feature_class":"P",
    "gn:feature_code":"PPL",
    "gn:name":"Ignacio Allende",
    "gn:population":1396,
    "gn:timezone":"America/Mexico_City",
    "iso:country":"MX",
    "wof:name":"Ignacio Allende",
    "wof:placetype":"locality",
    "wof:population":1396
},
  "geometry": {"coordinates":[-92.99222,16.52556],"type":"Point"}
}