{
  "type": "Feature",
  "properties": {
    "gn:admin1_code":"20",
    "gn:admin2_code":"5.0",
    "gn:asciiname":"Mazahua",
    "gn:country_code":"MX",
    "gn:dem":161,
    "gn:feature_class":"P",
    "gn:feature_code":"PPL",
    "gn:name":"Mazahua",
    "gn:population":0,
    "gn:timezone":"America/Mexico_City",
    "iso:country":"MX",
    "name:nld_x_preferred":[
        "Mazahua"
    ],
    "name:rus_x_preferred":[
        "\u041c\u0430\u0441\u0430\u0443\u0430"
    ],
    "name:spa_x_preferred":[
        "Mazahua"
    ],
    "wof:name":"Mazahua",
    "wof:placetype":"locality"
},
  "geometry": {"coordinates":[-94.94920999999999,16.63048],"type":"Point"}
}