{
  "type": "Feature",
  "properties": {
    "gn:admin1_code":"28",
    "gn:admin2_code":"29.0",
    "gn:asciiname":"Tanlajas",
    "gn:country_code":"MX",
    "gn:dem":179,
    "gn:feature_class":"P",
    "gn:feature_code":"PPL",
    "gn:name":"Tanlajas",
    "gn:population":0,
    "gn:timezone":"America/Monterrey",
    "iso:country":"MX",
    "name:spa_x_preferred":[
        "Tanlajas"
    ],
    "name:spa_x_variant":[
        "La Lajilla"
    ],
    "name:und_x_variant":[
        "La Alhajilla"
    ],
    "wof:name":"Tanlajas",
    "wof:placetype":"locality"
},
  "geometry": {"coordinates":[-99.20439,22.75202],"type":"Point"}
}