{
  "type": "Feature",
  "properties": {
    "gn:admin1_code":"30",
    "gn:admin2_code":"70.0",
    "gn:asciiname":"Ignacio Allende Chico (El Robalito)",
    "gn:country_code":"MX",
    "gn:dem":43,
    "gn:feature_class":"P",
    "gn:feature_code":"PPL",
    "gn:name":"Ignacio Allende Chico (El Robalito)",
    "gn:population":110,
    "gn:timezone":"America/Mexico_City",
    "iso:country":"MX",
    "wof:name":"Ignacio Allende Chico (El Robalito)",
    "wof:placetype":"locality",
    "wof:population":110
},
  "geometry": {"coordinates":[-94.59361,17.46278],"type":"Point"}
}