{
  "type": "Feature",
  "properties": {
    "gn:admin1_code":"20",
    "gn:admin2_code":"41.0",
    "gn:asciiname":"Agua de Flor",
    "gn:country_code":"MX",
    "gn:dem":1710,
    "gn:feature_class":"P",
    "gn:feature_code":"PPL",
    "gn:name":"Agua de Flor",
    "gn:population":81,
    "gn:timezone":"America/Mexico_City",
    "iso:country":"MX",
    "wof:name":"Agua de Flor",
    "wof:placetype":"locality",
    "wof:population":81
},
  "geometry": {"coordinates":[-96.77249999999999,18.14722],"type":"Point"}
}