{
  "type": "Feature",
  "properties": {
    "gn:gn_country":"MX",
    "gn:gn_fcode":"PPL",
    "gn:gn_pop":0,
    "iso:country":"MX",
    "name:ceb_x_preferred":[
        "Santa Mar\u00eda Ajoloapan"
    ],
    "name:eng_x_preferred":[
        "Santa Mar\u00eda Ajoloapan"
    ],
    "name:lad_x_preferred":[
        "Santa Mar\u00eda Ajoloapan"
    ],
    "name:nah_x_preferred":[
        "Santa Mar\u00eda \u0100x\u014dl\u014d\u0101pan"
    ],
    "name:nld_x_preferred":[
        "Santa Mar\u00eda Ajoloapan"
    ],
    "name:spa_x_preferred":[
        "Santa Mar\u00eda Ajoloapan"
    ],
    "name:srp_x_preferred":[
        "\u0421\u0430\u043d\u0442\u0430 \u041c\u0430\u0440\u0438\u0458\u0430 \u0410\u0445\u043e\u043b\u043e\u0430\u043f\u0430\u043d"
    ],
    "name:swe_x_preferred":[
        "Santa Mar\u00eda Ajoloapan"
    ],
    "qs_pg:aaroncc":"MX",
    "qs_pg:gn_country":"MX",
    "qs_pg:gn_fcode":"PPL",
    "qs_pg:gn_pop":0,
    "qs_pg:name":"Santa Maria Ajoloapa",
    "qs_pg:name_adm0":"M\u00e9xico",
    "qs_pg:name_adm1":"Mexico",
    "qs_pg:photos_9k":1,
    "qs_pg:photos_9r":1,
    "qs_pg:photos_all":1,
    "qs_pg:photos_sr":0,
    "qs_pg:pop_sr":0,
    "qs_pg:qs_pg_placetype":"locality",
    "qs_pg:qs_pg_placetype_gp":"Town",
    "qs_pg:woe_adm0":23424900,
    "woe:adm0_id":23424900,
    "woe:name_adm0":"M\u00e9xico",
    "woe:name_adm1":"Mexico",
    "woe:placetype":"Town",
    "wof:name":"Santa Maria Ajoloapa",
    "wof:placetype":"locality"
},
  "geometry": {"coordinates":[-98.96290999999999,19.76308],"type":"Point"}
}