{
  "type": "Feature",
  "properties": {
    "gn:admin1_code":"6",
    "gn:admin2_code":"12.0",
    "gn:asciiname":"Mesa del Ojito (Mesa del Terrero)",
    "gn:country_code":"MX",
    "gn:dem":2084,
    "gn:feature_class":"P",
    "gn:feature_code":"PPL",
    "gn:name":"Mesa del Ojito (Mesa del Terrero)",
    "gn:population":8,
    "gn:timezone":"America/Chihuahua",
    "iso:country":"MX",
    "wof:name":"Mesa del Ojito (Mesa del Terrero)",
    "wof:placetype":"locality",
    "wof:population":8
},
  "geometry": {"coordinates":[-106.93659,27.60117],"type":"Point"}
}