{
  "type": "Feature",
  "properties": {
    "gn:admin1_code":"26",
    "gn:admin2_code":"30.0",
    "gn:asciiname":"El Meson",
    "gn:country_code":"MX",
    "gn:dem":113,
    "gn:feature_class":"P",
    "gn:feature_code":"PPL",
    "gn:name":"El Mes\u00f3n",
    "gn:population":5,
    "gn:timezone":"America/Hermosillo",
    "iso:country":"MX",
    "name:und_x_variant":[
        "El Mes\u00f3n"
    ],
    "wof:name":"El Meson",
    "wof:placetype":"locality",
    "wof:population":5
},
  "geometry": {"coordinates":[-111.27222,28.93583],"type":"Point"}
}