{
  "type": "Feature",
  "properties": {
    "gn:admin1_code":"12",
    "gn:admin2_code":"28.0",
    "gn:asciiname":"Ayahualco",
    "gn:country_code":"MX",
    "gn:dem":1425,
    "gn:feature_class":"P",
    "gn:feature_code":"PPL",
    "gn:name":"Ayahualco",
    "gn:population":545,
    "gn:timezone":"America/Mexico_City",
    "iso:country":"MX",
    "wof:name":"Ayahualco",
    "wof:placetype":"locality",
    "wof:population":545
},
  "geometry": {"coordinates":[-99.18611,17.62361],"type":"Point"}
}