{
  "type": "Feature",
  "properties": {
    "gn:admin1_code":"7",
    "gn:admin2_code":"15.0",
    "gn:asciiname":"San Antonio El Rusio",
    "gn:country_code":"MX",
    "gn:dem":280,
    "gn:feature_class":"P",
    "gn:feature_code":"PPL",
    "gn:name":"San Antonio El Rusio",
    "gn:population":0,
    "gn:timezone":"America/Monterrey",
    "iso:country":"MX",
    "name:spa_x_preferred":[
        "San Antonio El Rusio"
    ],
    "name:und_x_variant":[
        "San Antonio",
        "Rancho San Antonio"
    ],
    "wof:name":"San Antonio El Rusio",
    "wof:placetype":"locality"
},
  "geometry": {"coordinates":[-100.80562999999999,27.52431],"type":"Point"}
}