{
  "type": "Feature",
  "properties": {
    "gn:admin1_code":"30",
    "gn:admin2_code":"144.0",
    "gn:asciiname":"Colonia Nueva Esperanza",
    "gn:country_code":"MX",
    "gn:dem":88,
    "gn:feature_class":"P",
    "gn:feature_code":"PPL",
    "gn:name":"Colonia Nueva Esperanza",
    "gn:population":153,
    "gn:timezone":"America/Mexico_City",
    "iso:country":"MX",
    "wof:name":"Colonia Nueva Esperanza",
    "wof:placetype":"locality",
    "wof:population":153
},
  "geometry": {"coordinates":[-94.95722000000001,17.89167],"type":"Point"}
}