{
  "type": "Feature",
  "properties": {
    "gn:admin1_code":"32",
    "gn:admin2_code":"13.0",
    "gn:asciiname":"Bote Viejo",
    "gn:country_code":"MX",
    "gn:dem":2248,
    "gn:feature_class":"P",
    "gn:feature_code":"PPL",
    "gn:name":"Bote Viejo",
    "gn:population":0,
    "gn:timezone":"America/Mexico_City",
    "iso:country":"MX",
    "name:spa_x_preferred":[
        "Bote Viejo"
    ],
    "wof:name":"Bote Viejo",
    "wof:placetype":"locality"
},
  "geometry": {"coordinates":[-102.85053000000001,23.06143],"type":"Point"}
}