{
  "type": "Feature",
  "properties": {
    "gn:admin1_code":"5",
    "gn:admin2_code":"9",
    "gn:asciiname":"Nuevo Colosio",
    "gn:country_code":"MX",
    "gn:dem":99,
    "gn:feature_class":"P",
    "gn:feature_code":"PPL",
    "gn:name":"Nuevo Colosio",
    "gn:population":40,
    "gn:timezone":"America/Mexico_City",
    "iso:country":"MX",
    "wof:name":"Nuevo Colosio",
    "wof:placetype":"locality",
    "wof:population":40
},
  "geometry": {"coordinates":[-94.01721999999999,16.33611],"type":"Point"}
}