{
  "type": "Feature",
  "properties": {
    "gn:admin1_code":"14.0",
    "gn:admin2_code":"115.0",
    "gn:asciiname":"Sabino Quemado",
    "gn:country_code":"MX",
    "gn:dem":1055,
    "gn:feature_class":"P",
    "gn:feature_code":"PPL",
    "gn:name":"Sabino Quemado",
    "gn:population":0,
    "gn:timezone":"America/Mexico_City",
    "iso:country":"MX",
    "name:spa_x_preferred":[
        "Sabino Quemado"
    ],
    "wof:name":"Sabino Quemado",
    "wof:placetype":"locality"
},
  "geometry": {"coordinates":[-103.72505,22.05397],"type":"Point"}
}