{
  "type": "Feature",
  "properties": {
    "gn:admin1_code":"2",
    "gn:admin2_code":"1",
    "gn:asciiname":"San Jorge Tres",
    "gn:country_code":"MX",
    "gn:dem":98,
    "gn:feature_class":"P",
    "gn:feature_code":"PPL",
    "gn:name":"San Jorge Tres",
    "gn:population":25,
    "gn:timezone":"America/Tijuana",
    "iso:country":"MX",
    "wof:name":"San Jorge Tres",
    "wof:placetype":"locality",
    "wof:population":25
},
  "geometry": {"coordinates":[-116.56861000000001,31.81139000000001],"type":"Point"}
}