{
  "type": "Feature",
  "properties": {
    "gn:admin1_code":"18",
    "gn:admin2_code":"9.0",
    "gn:asciiname":"Los Corpos",
    "gn:country_code":"MX",
    "gn:dem":1444,
    "gn:feature_class":"P",
    "gn:feature_code":"PPL",
    "gn:name":"Los Corpos",
    "gn:population":5,
    "gn:timezone":"America/Mazatlan",
    "iso:country":"MX",
    "wof:name":"Los Corpos",
    "wof:placetype":"locality",
    "wof:population":5
},
  "geometry": {"coordinates":[-104.36944,22.36139],"type":"Point"}
}