{
  "type": "Feature",
  "properties": {
    "gn:gn_country":"MX",
    "gn:gn_fcode":"PPL",
    "gn:gn_pop":0,
    "gn:population":919,
    "iso:country":"MX",
    "qs_pg:aaroncc":"MX",
    "qs_pg:gn_country":"MX",
    "qs_pg:gn_fcode":"PPL",
    "qs_pg:gn_pop":0,
    "qs_pg:name":"El Derramadero",
    "qs_pg:name_adm0":"M\u00e9xico",
    "qs_pg:name_adm1":"Guanajuato",
    "qs_pg:photos":1,
    "qs_pg:photos_1k":1,
    "qs_pg:photos_9k":1,
    "qs_pg:photos_9r":1,
    "qs_pg:photos_all":1,
    "qs_pg:photos_sr":1,
    "qs_pg:pop_sr":0,
    "qs_pg:qs_pg_placetype":"neighbourhood",
    "qs_pg:qs_pg_placetype_gp":"Suburb",
    "qs_pg:woe_adm0":23424900,
    "woe:adm0_id":23424900,
    "woe:name_adm0":"M\u00e9xico",
    "woe:name_adm1":"Guanajuato",
    "woe:placetype":"Suburb",
    "wof:name":"El Derramadero",
    "wof:placetype":"neighbourhood",
    "wof:population":919
},
  "geometry": {"coordinates":[-101.12889,20.08113],"type":"Point"}
}