{
  "type": "Feature",
  "properties": {
    "gn:admin1_code":"16.0",
    "gn:admin2_code":"10.0",
    "gn:asciiname":"El Cascalote",
    "gn:country_code":"MX",
    "gn:dem":762,
    "gn:feature_class":"P",
    "gn:feature_code":"PPL",
    "gn:name":"El Cascalote",
    "gn:population":0,
    "gn:timezone":"America/Mexico_City",
    "iso:country":"MX",
    "name:und_x_variant":[
        "Cascalote",
        "El Cascalote"
    ],
    "wof:name":"El Cascalote",
    "wof:placetype":"locality"
},
  "geometry": {"coordinates":[-102.22096999999999,18.54498],"type":"Point"}
}