{
  "type": "Feature",
  "properties": {
    "gn:admin1_code":"12.0",
    "gn:admin2_code":"68.0",
    "gn:asciiname":"Naranjillo",
    "gn:country_code":"MX",
    "gn:dem":504,
    "gn:feature_class":"P",
    "gn:feature_code":"PPL",
    "gn:name":"Naranjillo",
    "gn:population":0,
    "gn:timezone":"America/Mexico_City",
    "iso:country":"MX",
    "name:ceb_x_preferred":[
        "Naranjillo"
    ],
    "name:swe_x_preferred":[
        "Naranjillo"
    ],
    "name:und_x_variant":[
        "El Naranjito",
        "El Naranjillo"
    ],
    "wof:name":"Naranjillo",
    "wof:placetype":"locality"
},
  "geometry": {"coordinates":[-101.8424,18.07598],"type":"Point"}
}