{
  "type": "Feature",
  "properties": {
    "gn:admin1_code":"12",
    "gn:admin2_code":"2.0",
    "gn:asciiname":"Las Jicaras (El Mirador)",
    "gn:country_code":"MX",
    "gn:dem":1160,
    "gn:feature_class":"P",
    "gn:feature_code":"PPL",
    "gn:name":"Las J\u00edcaras (El Mirador)",
    "gn:population":82,
    "gn:timezone":"America/Mexico_City",
    "iso:country":"MX",
    "name:und_x_variant":[
        "Las J\u00edcaras (El Mirador)"
    ],
    "wof:name":"Las Jicaras (El Mirador)",
    "wof:placetype":"locality",
    "wof:population":82
},
  "geometry": {"coordinates":[-98.88361999999999,17.83607],"type":"Point"}
}