{
  "type": "Feature",
  "properties": {
    "gn:admin1_code":"14",
    "gn:admin2_code":"29.0",
    "gn:asciiname":"El Llano de Barajas",
    "gn:country_code":"MX",
    "gn:dem":1770,
    "gn:feature_class":"P",
    "gn:feature_code":"PPL",
    "gn:name":"El Llano de Barajas",
    "gn:population":158,
    "gn:timezone":"America/Mexico_City",
    "iso:country":"MX",
    "wof:name":"El Llano de Barajas",
    "wof:placetype":"locality",
    "wof:population":158
},
  "geometry": {"coordinates":[-103.03722,20.87583],"type":"Point"}
}