{
  "type": "Feature",
  "properties": {
    "gn:admin1_code":"14",
    "gn:admin2_code":"124",
    "gn:asciiname":"Los Arenales",
    "gn:country_code":"MX",
    "gn:dem":1419,
    "gn:feature_class":"P",
    "gn:feature_code":"PPL",
    "gn:name":"Los Arenales",
    "gn:population":14,
    "gn:timezone":"America/Mexico_City",
    "iso:country":"MX",
    "wof:name":"Los Arenales",
    "wof:placetype":"locality",
    "wof:population":14
},
  "geometry": {"coordinates":[-103.13028,20.63472],"type":"Point"}
}