{
  "type": "Feature",
  "properties": {
    "gn:admin1_code":"6",
    "gn:admin2_code":"19.0",
    "gn:asciiname":"El Papalote",
    "gn:country_code":"MX",
    "gn:dem":1492,
    "gn:feature_class":"P",
    "gn:feature_code":"PPL",
    "gn:name":"El Papalote",
    "gn:population":4,
    "gn:timezone":"America/Chihuahua",
    "iso:country":"MX",
    "wof:name":"El Papalote",
    "wof:placetype":"locality",
    "wof:population":4
},
  "geometry": {"coordinates":[-106.22175,28.1867],"type":"Point"}
}