{
  "type": "Feature",
  "properties": {
    "gn:admin1_code":"6",
    "gn:admin2_code":"27.0",
    "gn:asciiname":"Ex-Aserradero Los Charcos",
    "gn:country_code":"MX",
    "gn:dem":2330,
    "gn:feature_class":"P",
    "gn:feature_code":"PPL",
    "gn:name":"Ex-Aserradero Los Charcos",
    "gn:population":0,
    "gn:timezone":"America/Chihuahua",
    "iso:country":"MX",
    "name:spa_x_preferred":[
        "Ex-Aserradero Los Charcos"
    ],
    "wof:name":"Ex-Aserradero Los Charcos",
    "wof:placetype":"locality"
},
  "geometry": {"coordinates":[-107.01857,27.19331],"type":"Point"}
}