{
  "type": "Feature",
  "properties": {
    "gn:admin1_code":"28",
    "gn:admin2_code":"22.0",
    "gn:asciiname":"Los Jaboncillos",
    "gn:cc2":"MX",
    "gn:country_code":"MX",
    "gn:dem":17,
    "gn:feature_class":"P",
    "gn:feature_code":"PPL",
    "gn:name":"Los Jaboncillos",
    "gn:population":0,
    "gn:timezone":"America/Matamoros",
    "iso:country":"MX",
    "name:und_x_variant":[
        "Jaboncillos",
        "Los Jaboncillos"
    ],
    "wof:name":"Los Jaboncillos",
    "wof:placetype":"locality"
},
  "geometry": {"coordinates":[-97.76667,25.96667],"type":"Point"}
}