{
  "type": "Feature",
  "properties": {
    "gn:admin1_code":"5",
    "gn:admin2_code":"4",
    "gn:asciiname":"El Rosario",
    "gn:country_code":"MX",
    "gn:dem":1246,
    "gn:feature_class":"P",
    "gn:feature_code":"PPL",
    "gn:name":"El Rosario",
    "gn:population":52,
    "gn:timezone":"America/Mexico_City",
    "iso:country":"MX",
    "wof:name":"El Rosario",
    "wof:placetype":"locality",
    "wof:population":52
},
  "geometry": {"coordinates":[-91.90139000000001,16.71806],"type":"Point"}
}