{
  "type": "Feature",
  "properties": {
    "gn:admin1_code":"24.0",
    "gn:admin2_code":"40.0",
    "gn:asciiname":"Las Pupinas",
    "gn:country_code":"MX",
    "gn:dem":20,
    "gn:feature_class":"P",
    "gn:feature_code":"PPL",
    "gn:name":"Las Pupinas",
    "gn:population":0,
    "gn:timezone":"America/Mexico_City",
    "iso:country":"MX",
    "name:spa_x_preferred":[
        "Las Pupinas"
    ],
    "wof:name":"Las Pupinas",
    "wof:placetype":"locality"
},
  "geometry": {"coordinates":[-98.61772000000001,21.98908],"type":"Point"}
}