{
  "type": "Feature",
  "properties": {
    "gn:admin1_code":"26",
    "gn:admin2_code":"69.0",
    "gn:asciiname":"Nuevo Carrizal",
    "gn:country_code":"MX",
    "gn:dem":896,
    "gn:feature_class":"P",
    "gn:feature_code":"PPL",
    "gn:name":"Nuevo Carrizal",
    "gn:population":0,
    "gn:timezone":"America/Hermosillo",
    "iso:country":"MX",
    "name:spa_x_preferred":[
        "Nuevo Carrizal"
    ],
    "wof:name":"Nuevo Carrizal",
    "wof:placetype":"locality"
},
  "geometry": {"coordinates":[-109.17694,28.55694],"type":"Point"}
}