{
  "type": "Feature",
  "properties": {
    "gn:admin1_code":"20",
    "gn:admin2_code":"439.0",
    "gn:asciiname":"Arroyo Tres",
    "gn:country_code":"MX",
    "gn:dem":32,
    "gn:feature_class":"P",
    "gn:feature_code":"PPL",
    "gn:name":"Arroyo Tres",
    "gn:population":258,
    "gn:timezone":"America/Mexico_City",
    "iso:country":"MX",
    "wof:name":"Arroyo Tres",
    "wof:placetype":"locality",
    "wof:population":258
},
  "geometry": {"coordinates":[-96.52472,15.66806],"type":"Point"}
}