{
  "type": "Feature",
  "properties": {
    "gn:admin1_code":"28",
    "gn:admin2_code":"31.0",
    "gn:asciiname":"Teran",
    "gn:country_code":"MX",
    "gn:dem":1442,
    "gn:feature_class":"P",
    "gn:feature_code":"PPL",
    "gn:name":"Ter\u00e1n",
    "gn:population":0,
    "gn:timezone":"America/Monterrey",
    "iso:country":"MX",
    "name:deu_x_preferred":[
        "Teran"
    ],
    "name:lfn_x_preferred":[
        "Teran"
    ],
    "name:srp_x_preferred":[
        "\u0422\u0435\u0440\u0430\u043d"
    ],
    "wof:name":"Teran",
    "wof:placetype":"locality"
},
  "geometry": {"coordinates":[-99.56667,23.23333],"type":"Point"}
}