{
  "type": "Feature",
  "properties": {
    "gn:admin1_code":"19",
    "gn:admin2_code":"42.0",
    "gn:asciiname":"La Colorada",
    "gn:country_code":"MX",
    "gn:dem":214,
    "gn:feature_class":"P",
    "gn:feature_code":"PPL",
    "gn:name":"La Colorada",
    "gn:population":9,
    "gn:timezone":"America/Monterrey",
    "iso:country":"MX",
    "wof:name":"La Colorada",
    "wof:placetype":"locality",
    "wof:population":9
},
  "geometry": {"coordinates":[-99.60057,25.50035],"type":"Point"}
}