{
  "type": "Feature",
  "properties": {
    "gn:admin1_code":"14",
    "gn:admin2_code":"119.0",
    "gn:asciiname":"Saixta",
    "gn:cc2":"MX",
    "gn:country_code":"MX",
    "gn:dem":1485,
    "gn:feature_class":"P",
    "gn:feature_code":"PPL",
    "gn:name":"Saixta",
    "gn:population":0,
    "gn:timezone":"America/Mexico_City",
    "iso:country":"MX",
    "name:und_x_variant":[
        "Saieta",
        "Saixta"
    ],
    "wof:name":"Saixta",
    "wof:placetype":"locality"
},
  "geometry": {"coordinates":[-103.66667,20.26667],"type":"Point"}
}