{
  "type": "Feature",
  "properties": {
    "gn:admin1_code":"25",
    "gn:admin2_code":"8",
    "gn:asciiname":"La Bebelama",
    "gn:country_code":"MX",
    "gn:dem":72,
    "gn:feature_class":"P",
    "gn:feature_code":"PPL",
    "gn:name":"La Bebelama",
    "gn:population":11,
    "gn:timezone":"America/Mazatlan",
    "iso:country":"MX",
    "wof:name":"La Bebelama",
    "wof:placetype":"locality",
    "wof:population":11
},
  "geometry": {"coordinates":[-106.81323,24.03316],"type":"Point"}
}