{
  "type": "Feature",
  "properties": {
    "gn:admin1_code":"12",
    "gn:admin2_code":"38.0",
    "gn:asciiname":"Puertecito",
    "gn:country_code":"MX",
    "gn:dem":835,
    "gn:feature_class":"P",
    "gn:feature_code":"PPL",
    "gn:name":"Puertecito",
    "gn:population":70,
    "gn:timezone":"America/Mexico_City",
    "iso:country":"MX",
    "wof:name":"Puertecito",
    "wof:placetype":"locality",
    "wof:population":70
},
  "geometry": {"coordinates":[-101.51694000000001,17.86208],"type":"Point"}
}