{
  "type": "Feature",
  "properties": {
    "gn:admin1_code":"6.0",
    "gn:admin2_code":"52.0",
    "gn:asciiname":"El Pegueis",
    "gn:country_code":"MX",
    "gn:dem":826,
    "gn:feature_class":"P",
    "gn:feature_code":"PPL",
    "gn:name":"El Peg\u00fcis",
    "gn:population":0,
    "gn:timezone":"America/Ojinaga",
    "iso:country":"MX",
    "name:spa_x_preferred":[
        "El Peg\u00fcis"
    ],
    "wof:name":"El Pegueis",
    "wof:placetype":"locality"
},
  "geometry": {"coordinates":[-104.74160000000001,29.50518],"type":"Point"}
}