{
  "type": "Feature",
  "properties": {
    "gn:admin1_code":"6.0",
    "gn:admin2_code":"62.0",
    "gn:asciiname":"El Adobe",
    "gn:country_code":"MX",
    "gn:dem":1413,
    "gn:feature_class":"P",
    "gn:feature_code":"PPL",
    "gn:name":"El Adobe",
    "gn:population":0,
    "gn:timezone":"America/Chihuahua",
    "iso:country":"MX",
    "name:spa_x_preferred":[
        "El Adobe"
    ],
    "wof:name":"El Adobe",
    "wof:placetype":"locality"
},
  "geometry": {"coordinates":[-105.77052,27.84061],"type":"Point"}
}