{
  "type": "Feature",
  "properties": {
    "gn:admin1_code":"5.0",
    "gn:asciiname":"San Jose las Palmas",
    "gn:country_code":"MX",
    "gn:dem":12,
    "gn:feature_class":"P",
    "gn:feature_code":"PPL",
    "gn:name":"San Jos\u00e9 las Palmas",
    "gn:population":0,
    "gn:timezone":"America/Mexico_City",
    "iso:country":"MX",
    "name:spa_x_preferred":[
        "San Jos\u00e9 las Palmas"
    ],
    "wof:name":"San Jose las Palmas",
    "wof:placetype":"locality"
},
  "geometry": {"coordinates":[-93.05902,15.42099],"type":"Point"}
}