{
  "type": "Feature",
  "properties": {
    "gn:admin1_code":"31",
    "gn:admin2_code":"77.0",
    "gn:asciiname":"Thohoku",
    "gn:country_code":"MX",
    "gn:dem":13,
    "gn:feature_class":"P",
    "gn:feature_code":"PPL",
    "gn:name":"Thohok\u00fa",
    "gn:population":0,
    "gn:timezone":"America/Merida",
    "iso:country":"MX",
    "name:und_x_variant":[
        "Thohokuh",
        "Thoholuh",
        "Thohok\u00fa"
    ],
    "wof:name":"Thohoku",
    "wof:placetype":"locality"
},
  "geometry": {"coordinates":[-88.93255000000001,21.04603],"type":"Point"}
}