{
  "type": "Feature",
  "properties": {
    "gn:admin1_code":"5",
    "gn:admin2_code":"51.0",
    "gn:asciiname":"El Carpintero Uno",
    "gn:country_code":"MX",
    "gn:dem":58,
    "gn:feature_class":"P",
    "gn:feature_code":"PPL",
    "gn:name":"El Carpintero Uno",
    "gn:population":6,
    "gn:timezone":"America/Mexico_City",
    "iso:country":"MX",
    "wof:name":"El Carpintero Uno",
    "wof:placetype":"locality",
    "wof:population":6
},
  "geometry": {"coordinates":[-92.91472,15.47083],"type":"Point"}
}