{
  "type": "Feature",
  "properties": {
    "gn:admin1_code":"16.0",
    "gn:admin2_code":"96.0",
    "gn:asciiname":"Los Atutos",
    "gn:country_code":"MX",
    "gn:dem":628,
    "gn:feature_class":"P",
    "gn:feature_code":"PPL",
    "gn:name":"Los Atutos",
    "gn:population":0,
    "gn:timezone":"America/Mexico_City",
    "iso:country":"MX",
    "name:spa_x_preferred":[
        "Los Atutos"
    ],
    "wof:name":"Los Atutos",
    "wof:placetype":"locality"
},
  "geometry": {"coordinates":[-102.82183000000001,18.5235],"type":"Point"}
}