{
  "type": "Feature",
  "properties": {
    "gn:gn_country":"MX",
    "gn:gn_fcode":"PPL",
    "gn:gn_pop":13001,
    "gn:population":13001,
    "iso:country":"MX",
    "name:spa_x_preferred":[
        "Santa Cruz"
    ],
    "name:unk_x_variant":[
        "Santa Cruz de Juarez"
    ],
    "qs_pg:aaroncc":"MX",
    "qs_pg:gn_country":"MX",
    "qs_pg:gn_fcode":"PPL",
    "qs_pg:gn_pop":13001,
    "qs_pg:name":"Benito Juarez",
    "qs_pg:name_adm0":"M\u00e9xico",
    "qs_pg:name_adm1":"San Luis Potosi",
    "qs_pg:photos_9r":0,
    "qs_pg:photos_sr":0,
    "qs_pg:pop_sr":6,
    "qs_pg:qs_pg_placetype":"neighbourhood",
    "qs_pg:qs_pg_placetype_gp":"Suburb",
    "qs_pg:woe_adm0":23424900,
    "woe:adm0_id":23424900,
    "woe:name_adm0":"M\u00e9xico",
    "woe:name_adm1":"San Luis Potosi",
    "woe:placetype":"Suburb",
    "wof:name":"Benito Juarez",
    "wof:placetype":"neighbourhood",
    "wof:population":13001
},
  "geometry": {"coordinates":[-98.20551,20.88601],"type":"Point"}
}