{
  "type": "Feature",
  "properties": {
    "gn:admin1_code":"12",
    "gn:admin2_code":"48",
    "gn:asciiname":"La Angostura",
    "gn:country_code":"MX",
    "gn:dem":850,
    "gn:feature_class":"P",
    "gn:feature_code":"PPL",
    "gn:name":"La Angostura",
    "gn:population":14,
    "gn:timezone":"America/Mexico_City",
    "iso:country":"MX",
    "name:ceb_x_preferred":[
        "La Angostura"
    ],
    "name:deu_x_preferred":[
        "La Angostura"
    ],
    "name:spa_x_preferred":[
        "La Angostura"
    ],
    "name:srp_x_preferred":[
        "\u041b\u0430 \u0410\u043d\u0433\u043e\u0441\u0442\u0443\u0440\u0430"
    ],
    "name:swe_x_preferred":[
        "La Angostura"
    ],
    "wof:name":"La Angostura",
    "wof:placetype":"locality",
    "wof:population":14
},
  "geometry": {"coordinates":[-101.02694,17.61386],"type":"Point"}
}