{
  "type": "Feature",
  "properties": {
    "gn:admin1_code":"22",
    "gn:admin2_code":"16",
    "gn:asciiname":"Norte Nuevo Espiritu Santo [Fraccionamiento]",
    "gn:country_code":"MX",
    "gn:dem":1922,
    "gn:feature_class":"P",
    "gn:feature_code":"PPL",
    "gn:name":"Norte Nuevo Esp\u00edritu Santo [Fraccionamiento]",
    "gn:population":15,
    "gn:timezone":"America/Mexico_City",
    "iso:country":"MX",
    "name:und_x_variant":[
        "Norte Nuevo Esp\u00edritu Santo [Fraccionamiento]"
    ],
    "wof:name":"Norte Nuevo Espiritu Santo [Fraccionamiento]",
    "wof:placetype":"locality",
    "wof:population":15
},
  "geometry": {"coordinates":[-100.01806000000001,20.41083],"type":"Point"}
}