{
  "type": "Feature",
  "properties": {
    "gn:admin1_code":"30",
    "gn:admin2_code":"31.0",
    "gn:asciiname":"El Soldado",
    "gn:country_code":"MX",
    "gn:dem":172,
    "gn:feature_class":"P",
    "gn:feature_code":"PPL",
    "gn:name":"El Soldado",
    "gn:population":93,
    "gn:timezone":"America/Mexico_City",
    "iso:country":"MX",
    "wof:name":"El Soldado",
    "wof:placetype":"locality",
    "wof:population":93
},
  "geometry": {"coordinates":[-96.56778,18.81611],"type":"Point"}
}