{
  "type": "Feature",
  "properties": {
    "gn:admin1_code":"30",
    "gn:admin2_code":"124",
    "gn:asciiname":"Los Siete Hermanos",
    "gn:country_code":"MX",
    "gn:dem":55,
    "gn:feature_class":"P",
    "gn:feature_code":"PPL",
    "gn:name":"Los Siete Hermanos",
    "gn:population":13,
    "gn:timezone":"America/Mexico_City",
    "iso:country":"MX",
    "wof:name":"Los Siete Hermanos",
    "wof:placetype":"locality",
    "wof:population":13
},
  "geometry": {"coordinates":[-97.29194,20.38389],"type":"Point"}
}