{
  "type": "Feature",
  "properties": {
    "gn:admin1_code":"5",
    "gn:admin2_code":"96.0",
    "gn:asciiname":"Jol-Ako",
    "gn:country_code":"MX",
    "gn:dem":84,
    "gn:feature_class":"P",
    "gn:feature_code":"PPL",
    "gn:name":"Jol-Ako",
    "gn:population":429,
    "gn:timezone":"America/Mexico_City",
    "iso:country":"MX",
    "wof:name":"Jol-Ako",
    "wof:placetype":"locality",
    "wof:population":429
},
  "geometry": {"coordinates":[-92.45,17.39611],"type":"Point"}
}