{
  "type": "Feature",
  "properties": {
    "gn:admin1_code":"25",
    "gn:admin2_code":"6.0",
    "gn:asciiname":"La Campana",
    "gn:country_code":"MX",
    "gn:dem":138,
    "gn:feature_class":"P",
    "gn:feature_code":"PPL",
    "gn:name":"La Campana",
    "gn:population":0,
    "gn:timezone":"America/Mazatlan",
    "iso:country":"MX",
    "name:spa_x_preferred":[
        "La Campana"
    ],
    "wof:name":"La Campana",
    "wof:placetype":"locality"
},
  "geometry": {"coordinates":[-107.55838,24.96428],"type":"Point"}
}