{
  "type": "Feature",
  "properties": {
    "gn:admin1_code":"26",
    "gn:admin2_code":"42",
    "gn:asciiname":"Bachoco Veinticinco Diecisiete",
    "gn:country_code":"MX",
    "gn:dem":53,
    "gn:feature_class":"P",
    "gn:feature_code":"PPL",
    "gn:name":"Bachoco Veinticinco Diecisiete",
    "gn:population":10,
    "gn:timezone":"America/Hermosillo",
    "iso:country":"MX",
    "wof:name":"Bachoco Veinticinco Diecisiete",
    "wof:placetype":"locality",
    "wof:population":10
},
  "geometry": {"coordinates":[-109.78903,27.26239],"type":"Point"}
}