{
  "type": "Feature",
  "properties": {
    "gn:admin1_code":"5",
    "gn:admin2_code":"17",
    "gn:asciiname":"Las Murallas",
    "gn:country_code":"MX",
    "gn:dem":690,
    "gn:feature_class":"P",
    "gn:feature_code":"PPL",
    "gn:name":"Las Murallas",
    "gn:population":12,
    "gn:timezone":"America/Mexico_City",
    "iso:country":"MX",
    "wof:name":"Las Murallas",
    "wof:placetype":"locality",
    "wof:population":12
},
  "geometry": {"coordinates":[-94.03222,16.51722],"type":"Point"}
}