{
  "type": "Feature",
  "properties": {
    "gn:admin1_code":"22",
    "gn:admin2_code":"14.0",
    "gn:asciiname":"Linda Vista",
    "gn:country_code":"MX",
    "gn:dem":1965,
    "gn:feature_class":"P",
    "gn:feature_code":"PPL",
    "gn:name":"Linda Vista",
    "gn:population":128,
    "gn:timezone":"America/Mexico_City",
    "iso:country":"MX",
    "name:ceb_x_preferred":[
        "Linda Vista"
    ],
    "name:deu_x_preferred":[
        "Linda Vista"
    ],
    "name:nds_x_preferred":[
        "Linda Vista"
    ],
    "name:srp_x_preferred":[
        "\u041b\u0438\u043d\u0434\u0430 \u0412\u0438\u0441\u0442\u0430"
    ],
    "name:swe_x_preferred":[
        "Linda Vista"
    ],
    "wof:name":"Linda Vista",
    "wof:placetype":"locality",
    "wof:population":128
},
  "geometry": {"coordinates":[-100.46278,20.74111],"type":"Point"}
}