{
  "type": "Feature",
  "properties": {
    "gn:admin1_code":"15",
    "gn:admin2_code":"45",
    "gn:asciiname":"Los Laureles",
    "gn:country_code":"MX",
    "gn:dem":1701,
    "gn:feature_class":"P",
    "gn:feature_code":"PPL",
    "gn:name":"Los Laureles",
    "gn:population":0,
    "gn:timezone":"America/Mexico_City",
    "iso:country":"MX",
    "name:por_x_preferred":[
        "Los Laureles"
    ],
    "name:spa_x_preferred":[
        "Los Laureles"
    ],
    "wof:name":"Los Laureles",
    "wof:placetype":"locality",
    "wof:population":28
},
  "geometry": {"coordinates":[-102.75257999999999,19.95319],"type":"Point"}
}