{
  "type": "Feature",
  "properties": {
    "gn:admin1_code":"7",
    "gn:admin2_code":"27",
    "gn:asciiname":"Ana Isabel",
    "gn:country_code":"MX",
    "gn:dem":1475,
    "gn:feature_class":"P",
    "gn:feature_code":"PPL",
    "gn:name":"Ana Isabel",
    "gn:population":9,
    "gn:timezone":"America/Monterrey",
    "iso:country":"MX",
    "wof:name":"Ana Isabel",
    "wof:placetype":"locality",
    "wof:population":9
},
  "geometry": {"coordinates":[-101.00143,25.5167],"type":"Point"}
}