{
  "type": "Feature",
  "properties": {
    "gn:admin1_code":"28.0",
    "gn:admin2_code":"16.0",
    "gn:asciiname":"La Mesa Redonda",
    "gn:country_code":"MX",
    "gn:dem":775,
    "gn:feature_class":"P",
    "gn:feature_code":"PPL",
    "gn:name":"La Mesa Redonda",
    "gn:population":0,
    "gn:timezone":"America/Monterrey",
    "iso:country":"MX",
    "name:spa_x_preferred":[
        "La Mesa Redonda"
    ],
    "wof:name":"La Mesa Redonda",
    "wof:placetype":"locality"
},
  "geometry": {"coordinates":[-99.42957,24.08116],"type":"Point"}
}