{
  "type": "Feature",
  "properties": {
    "gn:admin1_code":"12",
    "gn:admin2_code":"75.0",
    "gn:asciiname":"El Carrizal",
    "gn:country_code":"MX",
    "gn:dem":976,
    "gn:feature_class":"P",
    "gn:feature_code":"PPL",
    "gn:name":"El Carrizal",
    "gn:population":8,
    "gn:timezone":"America/Mexico_City",
    "iso:country":"MX",
    "wof:name":"El Carrizal",
    "wof:placetype":"locality",
    "wof:population":8
},
  "geometry": {"coordinates":[-99.53467000000001,17.68599],"type":"Point"}
}