{
  "type": "Feature",
  "properties": {
    "gn:admin1_code":"26",
    "gn:admin2_code":"36.0",
    "gn:asciiname":"La Taza",
    "gn:country_code":"MX",
    "gn:dem":743,
    "gn:feature_class":"P",
    "gn:feature_code":"PPL",
    "gn:name":"La Taza",
    "gn:population":0,
    "gn:timezone":"America/Hermosillo",
    "iso:country":"MX",
    "name:spa_x_preferred":[
        "La Taza"
    ],
    "name:und_x_variant":[
        "Rancho La Taza"
    ],
    "wof:name":"La Taza",
    "wof:placetype":"locality"
},
  "geometry": {"coordinates":[-111.1618,30.72343],"type":"Point"}
}