{
  "type": "Feature",
  "properties": {
    "gn:admin1_code":"5",
    "gn:admin2_code":"7.0",
    "gn:asciiname":"San Miguel el Alto",
    "gn:country_code":"MX",
    "gn:dem":2274,
    "gn:feature_class":"P",
    "gn:feature_code":"PPL",
    "gn:name":"San Miguel el Alto",
    "gn:population":138,
    "gn:timezone":"America/Mexico_City",
    "iso:country":"MX",
    "wof:name":"San Miguel el Alto",
    "wof:placetype":"locality",
    "wof:population":138
},
  "geometry": {"coordinates":[-92.35833,16.49472],"type":"Point"}
}