{
  "type": "Feature",
  "properties": {
    "gn:admin1_code":"5",
    "gn:admin2_code":"7.0",
    "gn:asciiname":"San Miguel el Alto",
    "gn:country_code":"MX",
    "gn:dem":2274,
    "gn:feature_class":"P",
    "gn:feature_code":"PPL",
    "gn:name":"San Miguel el Alto",
    "gn:population":138,
    "gn:timezone":"America/Mexico_City",
    "iso:country":"MX",
    "name:ceb_x_preferred":[
        "San Miguel el Alto"
    ],
    "name:epo_x_preferred":[
        "San Miguel el Alto"
    ],
    "name:eus_x_preferred":[
        "San Miguel el Alto"
    ],
    "name:ita_x_preferred":[
        "San Miguel el Alto"
    ],
    "name:por_x_preferred":[
        "San Miguel el Alto"
    ],
    "name:sco_x_preferred":[
        "San Miguel el Alto"
    ],
    "name:spa_x_preferred":[
        "San Miguel el Alto"
    ],
    "name:srp_x_preferred":[
        "\u041e\u043f\u0448\u0442\u0438\u043d\u0430 \u0421\u0430\u043d \u041c\u0438\u0433\u0435\u043b \u0435\u043b \u0410\u043b\u0442\u043e"
    ],
    "name:swe_x_preferred":[
        "San Miguel el Alto"
    ],
    "name:vie_x_preferred":[
        "San Miguel el Alto"
    ],
    "wof:name":"San Miguel el Alto",
    "wof:placetype":"locality",
    "wof:population":138
},
  "geometry": {"coordinates":[-92.35833,16.49472],"type":"Point"}
}