{
  "type": "Feature",
  "properties": {
    "gn:admin1_code":"10.0",
    "gn:admin2_code":"8.0",
    "gn:asciiname":"Juan Aldama",
    "gn:country_code":"MX",
    "gn:dem":2047,
    "gn:feature_class":"P",
    "gn:feature_code":"PPL",
    "gn:name":"Juan Aldama",
    "gn:population":0,
    "gn:timezone":"America/Monterrey",
    "iso:country":"MX",
    "wof:name":"Juan Aldama",
    "wof:placetype":"locality"
},
  "geometry": {"coordinates":[-104.14806,24.46722],"type":"Point"}
}