{
  "type": "Feature",
  "properties": {
    "gn:admin1_code":"10.0",
    "gn:admin2_code":"8.0",
    "gn:asciiname":"Juan Aldama",
    "gn:country_code":"MX",
    "gn:dem":2047,
    "gn:feature_class":"P",
    "gn:feature_code":"PPL",
    "gn:name":"Juan Aldama",
    "gn:population":0,
    "gn:timezone":"America/Monterrey",
    "iso:country":"MX",
    "name:cat_x_preferred":[
        "Juan Aldama Gonz\u00e1lez"
    ],
    "name:deu_x_preferred":[
        "Juan Aldama"
    ],
    "name:fra_x_preferred":[
        "Juan Aldama"
    ],
    "name:hun_x_preferred":[
        "Juan Aldama"
    ],
    "name:ita_x_preferred":[
        "Juan Aldama"
    ],
    "name:jpn_x_preferred":[
        "\u30d5\u30a1\u30f3\u30fb\u30a2\u30eb\u30c0\u30de"
    ],
    "name:nah_x_preferred":[
        "Juan Aldama"
    ],
    "name:nor_x_preferred":[
        "Juan Aldama"
    ],
    "name:por_x_preferred":[
        "Juan Aldama"
    ],
    "name:que_x_preferred":[
        "Juan Aldama"
    ],
    "name:spa_x_preferred":[
        "Juan Aldama"
    ],
    "name:swe_x_preferred":[
        "Juan Aldama"
    ],
    "name:tur_x_preferred":[
        "Juan Aldama"
    ],
    "wof:name":"Juan Aldama",
    "wof:placetype":"locality"
},
  "geometry": {"coordinates":[-104.14806,24.46722],"type":"Point"}
}