{
  "type": "Feature",
  "properties": {
    "gn:admin1_code":"25",
    "gn:admin2_code":"17.0",
    "gn:asciiname":"Espadanal",
    "gn:country_code":"MX",
    "gn:dem":939,
    "gn:feature_class":"P",
    "gn:feature_code":"PPL",
    "gn:name":"Espada\u00f1al",
    "gn:population":0,
    "gn:timezone":"America/Mazatlan",
    "iso:country":"MX",
    "name:spa_x_preferred":[
        "Espada\u00f1al"
    ],
    "wof:name":"Espadanal",
    "wof:placetype":"locality"
},
  "geometry": {"coordinates":[-107.56551,26.12515],"type":"Point"}
}