{
  "type": "Feature",
  "properties": {
    "gn:gn_country":"MX",
    "gn:gn_fcode":"PPL",
    "gn:gn_pop":0,
    "gn:population":82,
    "iso:country":"MX",
    "name:unk_x_variant":[
        "Juan de los Rangeles"
    ],
    "qs_pg:aaroncc":"MX",
    "qs_pg:gn_country":"MX",
    "qs_pg:gn_fcode":"PPL",
    "qs_pg:gn_pop":0,
    "qs_pg:name":"Res Los Angeles",
    "qs_pg:name_adm0":"M\u00e9xico",
    "qs_pg:name_adm1":"Queretaro de Arteaga",
    "qs_pg:photos":2,
    "qs_pg:photos_1k":1,
    "qs_pg:photos_9k":1,
    "qs_pg:photos_9r":1,
    "qs_pg:photos_all":2,
    "qs_pg:photos_sr":1,
    "qs_pg:pop_sr":0,
    "qs_pg:qs_pg_placetype":"neighbourhood",
    "qs_pg:qs_pg_placetype_gp":"Suburb",
    "qs_pg:woe_adm0":23424900,
    "woe:adm0_id":23424900,
    "woe:name_adm0":"M\u00e9xico",
    "woe:name_adm1":"Queretaro de Arteaga",
    "woe:placetype":"Suburb",
    "wof:name":"Res Los Angeles",
    "wof:placetype":"neighbourhood",
    "wof:population":82
},
  "geometry": {"coordinates":[-100.40000000000001,21.36667],"type":"Point"}
}