{
  "type": "Feature",
  "properties": {
    "gn:admin1_code":"12",
    "gn:admin2_code":"7",
    "gn:asciiname":"Los Limos",
    "gn:country_code":"MX",
    "gn:dem":775,
    "gn:feature_class":"P",
    "gn:feature_code":"PPL",
    "gn:name":"Los Limos",
    "gn:population":37,
    "gn:timezone":"America/Mexico_City",
    "iso:country":"MX",
    "wof:name":"Los Limos",
    "wof:placetype":"locality",
    "wof:population":37
},
  "geometry": {"coordinates":[-100.14894,18.32827],"type":"Point"}
}