{
  "type": "Feature",
  "properties": {
    "gn:admin1_code":"6",
    "gn:admin2_code":"42.0",
    "gn:asciiname":"La Monilla",
    "gn:country_code":"MX",
    "gn:dem":1034,
    "gn:feature_class":"P",
    "gn:feature_code":"PPL",
    "gn:name":"La Monilla",
    "gn:population":3,
    "gn:timezone":"America/Chihuahua",
    "iso:country":"MX",
    "wof:name":"La Monilla",
    "wof:placetype":"locality",
    "wof:population":3
},
  "geometry": {"coordinates":[-103.57111999999999,28.8431],"type":"Point"}
}