{
  "type": "Feature",
  "properties": {
    "gn:admin1_code":"21",
    "gn:admin2_code":"106.0",
    "gn:asciiname":"Francisco Sarabia",
    "gn:country_code":"MX",
    "gn:dem":2136,
    "gn:feature_class":"P",
    "gn:feature_code":"PPL",
    "gn:name":"Francisco Sarabia",
    "gn:population":1294,
    "gn:timezone":"America/Mexico_City",
    "iso:country":"MX",
    "wof:name":"Francisco Sarabia",
    "wof:placetype":"locality",
    "wof:population":1294
},
  "geometry": {"coordinates":[-98.31389,18.96417000000001],"type":"Point"}
}