{
  "type": "Feature",
  "properties": {
    "gn:admin1_code":"5.0",
    "gn:asciiname":"Los Muchachos",
    "gn:country_code":"MX",
    "gn:dem":21,
    "gn:feature_class":"P",
    "gn:feature_code":"PPL",
    "gn:name":"Los Muchachos",
    "gn:population":0,
    "gn:timezone":"America/Mexico_City",
    "iso:country":"MX",
    "name:spa_x_preferred":[
        "Los Muchachos"
    ],
    "wof:name":"Los Muchachos",
    "wof:placetype":"locality"
},
  "geometry": {"coordinates":[-92.1302,17.76645],"type":"Point"}
}