{
  "type": "Feature",
  "properties": {
    "gn:admin1_code":"18.0",
    "gn:admin2_code":"20.0",
    "gn:asciiname":"El Coatante",
    "gn:country_code":"MX",
    "gn:dem":63,
    "gn:feature_class":"P",
    "gn:feature_code":"PPL",
    "gn:name":"El Coatante",
    "gn:population":0,
    "gn:timezone":"America/Bahia_Banderas",
    "iso:country":"MX",
    "name:spa_x_preferred":[
        "El Coatante"
    ],
    "wof:name":"El Coatante",
    "wof:placetype":"locality"
},
  "geometry": {"coordinates":[-105.12587000000001,20.90234],"type":"Point"}
}