{
  "type": "Feature",
  "properties": {
    "gn:admin1_code":"26",
    "gn:admin2_code":"17",
    "gn:asciiname":"Juan Jimenez Hernandez (Colonia Vicente Guerrero)",
    "gn:country_code":"MX",
    "gn:dem":51,
    "gn:feature_class":"P",
    "gn:feature_code":"PPL",
    "gn:name":"Juan Jim\u00e9nez Hern\u00e1ndez (Colonia Vicente Guerrero)",
    "gn:population":29,
    "gn:timezone":"America/Hermosillo",
    "iso:country":"MX",
    "name:und_x_variant":[
        "Juan Jim\u00e9nez Hern\u00e1ndez (Colonia Vicente Guerrero)"
    ],
    "wof:name":"Juan Jimenez Hernandez (Colonia Vicente Guerrero)",
    "wof:placetype":"locality",
    "wof:population":29
},
  "geometry": {"coordinates":[-112.88278,30.84806],"type":"Point"}
}