{
  "type": "Feature",
  "properties": {
    "gn:admin1_code":"5",
    "gn:admin2_code":"80.0",
    "gn:asciiname":"San Lucas",
    "gn:country_code":"MX",
    "gn:dem":1537,
    "gn:feature_class":"P",
    "gn:feature_code":"PPL",
    "gn:name":"San Lucas",
    "gn:population":308,
    "gn:timezone":"America/Mexico_City",
    "iso:country":"MX",
    "wof:name":"San Lucas",
    "wof:placetype":"locality",
    "wof:population":308
},
  "geometry": {"coordinates":[-92.32639,15.52222],"type":"Point"}
}