{
  "type": "Feature",
  "properties": {
    "gn:admin1_code":"2.0",
    "gn:admin2_code":"1.0",
    "gn:asciiname":"Los Chichos",
    "gn:country_code":"MX",
    "gn:dem":26,
    "gn:feature_class":"P",
    "gn:feature_code":"PPL",
    "gn:name":"Los Chichos",
    "gn:population":0,
    "gn:timezone":"America/Tijuana",
    "iso:country":"MX",
    "name:spa_x_preferred":[
        "Los Chichos"
    ],
    "name:und_x_variant":[
        "Rub\u00e9n Jaramillo"
    ],
    "wof:name":"Los Chichos",
    "wof:placetype":"locality"
},
  "geometry": {"coordinates":[-116.19575,30.89601],"type":"Point"}
}