{
  "type": "Feature",
  "properties": {
    "gn:admin1_code":"6",
    "gn:admin2_code":"54.0",
    "gn:asciiname":"Campo Cuarenta y Dos B",
    "gn:country_code":"MX",
    "gn:dem":2169,
    "gn:feature_class":"P",
    "gn:feature_code":"PPL",
    "gn:name":"Campo Cuarenta y Dos B",
    "gn:population":15,
    "gn:timezone":"America/Chihuahua",
    "iso:country":"MX",
    "name:spa_x_preferred":[
        "Campo Cuarenta y Dos B"
    ],
    "name:spa_x_variant":[
        "Pino Cuate"
    ],
    "wof:name":"Campo Cuarenta y Dos B",
    "wof:placetype":"locality",
    "wof:population":15
},
  "geometry": {"coordinates":[-106.72273,28.91434000000001],"type":"Point"}
}