{
  "type": "Feature",
  "properties": {
    "gn:admin1_code":"16",
    "gn:admin2_code":"68",
    "gn:asciiname":"Llanos de Periban",
    "gn:country_code":"MX",
    "gn:dem":1427,
    "gn:feature_class":"P",
    "gn:feature_code":"PPL",
    "gn:name":"Llanos de Perib\u00e1n",
    "gn:population":12,
    "gn:timezone":"America/Mexico_City",
    "iso:country":"MX",
    "name:und_x_variant":[
        "Llanos de Perib\u00e1n"
    ],
    "wof:name":"Llanos de Periban",
    "wof:placetype":"locality",
    "wof:population":12
},
  "geometry": {"coordinates":[-102.44499999999999,19.55361],"type":"Point"}
}