{
  "type": "Feature",
  "properties": {
    "gn:admin1_code":"10",
    "gn:admin2_code":"26.0",
    "gn:asciiname":"Potrerillos",
    "gn:country_code":"MX",
    "gn:dem":2429,
    "gn:feature_class":"P",
    "gn:feature_code":"PPL",
    "gn:name":"Potrerillos",
    "gn:population":0,
    "gn:timezone":"America/Monterrey",
    "iso:country":"MX",
    "name:spa_x_preferred":[
        "Potrerillos"
    ],
    "wof:name":"Potrerillos",
    "wof:placetype":"locality"
},
  "geometry": {"coordinates":[-105.67825999999999,24.3516],"type":"Point"}
}