{
  "type": "Feature",
  "properties": {
    "gn:admin1_code":"2",
    "gn:admin2_code":"1.0",
    "gn:asciiname":"La Casa de Herrera",
    "gn:country_code":"MX",
    "gn:dem":10,
    "gn:feature_class":"P",
    "gn:feature_code":"PPL",
    "gn:name":"La Casa de Herrera",
    "gn:population":4,
    "gn:timezone":"America/Tijuana",
    "iso:country":"MX",
    "wof:name":"La Casa de Herrera",
    "wof:placetype":"locality",
    "wof:population":4
},
  "geometry": {"coordinates":[-116.63889,31.54278],"type":"Point"}
}