{
  "type": "Feature",
  "properties": {
    "gn:admin1_code":"5",
    "gn:admin2_code":"61.0",
    "gn:asciiname":"Llano San Juan",
    "gn:country_code":"MX",
    "gn:dem":1042,
    "gn:feature_class":"P",
    "gn:feature_code":"PPL",
    "gn:name":"Llano San Juan",
    "gn:population":4,
    "gn:timezone":"America/Mexico_City",
    "iso:country":"MX",
    "wof:name":"Llano San Juan",
    "wof:placetype":"locality",
    "wof:population":4
},
  "geometry": {"coordinates":[-93.33972,16.75444],"type":"Point"}
}