{
  "type": "Feature",
  "properties": {
    "gn:admin1_code":"11",
    "gn:admin2_code":"23",
    "gn:asciiname":"Monte Redondo Uno (Los Cortes)",
    "gn:country_code":"MX",
    "gn:dem":1693,
    "gn:feature_class":"P",
    "gn:feature_code":"PPL",
    "gn:name":"Monte Redondo Uno (Los Cort\u00e9s)",
    "gn:population":43,
    "gn:timezone":"America/Mexico_City",
    "iso:country":"MX",
    "name:und_x_variant":[
        "Monte Redondo Uno (Los Cort\u00e9s)"
    ],
    "wof:name":"Monte Redondo Uno (Los Cortes)",
    "wof:placetype":"locality",
    "wof:population":43
},
  "geometry": {"coordinates":[-101.62860999999999,20.40944],"type":"Point"}
}