{
  "type": "Feature",
  "properties": {
    "gn:admin1_code":"30",
    "gn:admin2_code":"92.0",
    "gn:asciiname":"Coxmatla",
    "gn:country_code":"MX",
    "gn:dem":1961,
    "gn:feature_class":"P",
    "gn:feature_code":"PPL",
    "gn:name":"Coxmatla",
    "gn:population":0,
    "gn:timezone":"America/Mexico_City",
    "iso:country":"MX",
    "name:spa_x_preferred":[
        "Coxmatla"
    ],
    "name:und_x_variant":[
        "Caxmatla"
    ],
    "wof:name":"Coxmatla",
    "wof:placetype":"locality"
},
  "geometry": {"coordinates":[-97.07633,19.42703],"type":"Point"}
}