{
  "type": "Feature",
  "properties": {
    "gn:admin1_code":"29",
    "gn:admin2_code":"18.0",
    "gn:asciiname":"Santa Maria Tlacatecpa",
    "gn:country_code":"MX",
    "gn:dem":2354,
    "gn:feature_class":"P",
    "gn:feature_code":"PPL",
    "gn:name":"Santa Mar\u00eda Tlacatecpa",
    "gn:population":0,
    "gn:timezone":"America/Mexico_City",
    "iso:country":"MX",
    "name:spa_x_preferred":[
        "Santa Mar\u00eda Tlacatecpa"
    ],
    "name:spa_x_variant":[
        "Cuba"
    ],
    "wof:name":"Santa Maria Tlacatecpa",
    "wof:placetype":"locality"
},
  "geometry": {"coordinates":[-98.15223,19.33389],"type":"Point"}
}