{
  "type": "Feature",
  "properties": {
    "gn:admin1_code":"20",
    "gn:admin2_code":"135.0",
    "gn:asciiname":"Rio Seco",
    "gn:country_code":"MX",
    "gn:dem":1747,
    "gn:feature_class":"P",
    "gn:feature_code":"PPL",
    "gn:name":"R\u00edo Seco",
    "gn:population":108,
    "gn:timezone":"America/Mexico_City",
    "iso:country":"MX",
    "name:und_x_variant":[
        "R\u00edo Seco"
    ],
    "wof:name":"Rio Seco",
    "wof:placetype":"locality",
    "wof:population":108
},
  "geometry": {"coordinates":[-96.88278,17.0675],"type":"Point"}
}