{
  "type": "Feature",
  "properties": {
    "gn:admin1_code":"10.0",
    "gn:admin2_code":"26.0",
    "gn:asciiname":"El Arroyito Colorado",
    "gn:country_code":"MX",
    "gn:dem":2409,
    "gn:feature_class":"P",
    "gn:feature_code":"PPL",
    "gn:name":"El Arroyito Colorado",
    "gn:population":0,
    "gn:timezone":"America/Monterrey",
    "iso:country":"MX",
    "name:spa_x_preferred":[
        "El Arroyito Colorado"
    ],
    "wof:name":"El Arroyito Colorado",
    "wof:placetype":"locality"
},
  "geometry": {"coordinates":[-105.77319,24.35029],"type":"Point"}
}