{
  "type": "Feature",
  "properties": {
    "gn:admin1_code":"2",
    "gn:admin2_code":"2.0",
    "gn:asciiname":"Villa Hermosa",
    "gn:country_code":"MX",
    "gn:dem":24,
    "gn:feature_class":"P",
    "gn:feature_code":"PPL",
    "gn:name":"Villa Hermosa",
    "gn:population":472,
    "gn:timezone":"America/Tijuana",
    "iso:country":"MX",
    "name:spa_x_preferred":[
        "Villa Hermosa"
    ],
    "wof:name":"Villa Hermosa",
    "wof:placetype":"locality",
    "wof:population":472
},
  "geometry": {"coordinates":[-114.97483,32.63869],"type":"Point"}
}