{
  "type": "Feature",
  "properties": {
    "gn:admin1_code":"12.0",
    "gn:admin2_code":"38.0",
    "gn:asciiname":"El Ternejal",
    "gn:country_code":"MX",
    "gn:dem":539,
    "gn:feature_class":"P",
    "gn:feature_code":"PPL",
    "gn:name":"El Ternejal",
    "gn:population":0,
    "gn:timezone":"America/Mexico_City",
    "iso:country":"MX",
    "name:spa_x_preferred":[
        "El Ternejal"
    ],
    "wof:name":"El Ternejal",
    "wof:placetype":"locality"
},
  "geometry": {"coordinates":[-101.43941,18.02014],"type":"Point"}
}