{
  "type": "Feature",
  "properties": {
    "gn:admin1_code":"24",
    "gn:admin2_code":"3.0",
    "gn:asciiname":"Tampete",
    "gn:country_code":"MX",
    "gn:dem":964,
    "gn:feature_class":"P",
    "gn:feature_code":"PPL",
    "gn:name":"Tampete",
    "gn:population":55,
    "gn:timezone":"America/Mexico_City",
    "iso:country":"MX",
    "wof:name":"Tampete",
    "wof:placetype":"locality",
    "wof:population":55
},
  "geometry": {"coordinates":[-99.09193999999999,21.54028],"type":"Point"}
}