{
  "type": "Feature",
  "properties": {
    "gn:admin1_code":"16",
    "gn:admin2_code":"49.0",
    "gn:asciiname":"San Jose el Durazno",
    "gn:country_code":"MX",
    "gn:dem":2145,
    "gn:feature_class":"P",
    "gn:feature_code":"PPL",
    "gn:name":"San Jos\u00e9 el Durazno",
    "gn:population":0,
    "gn:timezone":"America/Mexico_City",
    "iso:country":"MX",
    "name:spa_x_preferred":[
        "San Jos\u00e9 el Durazno"
    ],
    "wof:name":"San Jose el Durazno",
    "wof:placetype":"locality"
},
  "geometry": {"coordinates":[-101.28995,19.42415],"type":"Point"}
}