{
  "type": "Feature",
  "properties": {
    "gn:admin1_code":"1",
    "gn:admin2_code":"11",
    "gn:asciiname":"Granja Liliana",
    "gn:country_code":"MX",
    "gn:dem":1896,
    "gn:feature_class":"P",
    "gn:feature_code":"PPL",
    "gn:name":"Granja Liliana",
    "gn:population":12,
    "gn:timezone":"America/Mexico_City",
    "iso:country":"MX",
    "wof:name":"Granja Liliana",
    "wof:placetype":"locality",
    "wof:population":12
},
  "geometry": {"coordinates":[-102.27167,22.02139],"type":"Point"}
}