{
  "type": "Feature",
  "properties": {
    "gn:admin1_code":"16.0",
    "gn:admin2_code":"5.0",
    "gn:asciiname":"Los Lirios",
    "gn:country_code":"MX",
    "gn:dem":2616,
    "gn:feature_class":"P",
    "gn:feature_code":"PPL",
    "gn:name":"Los Lirios",
    "gn:population":0,
    "gn:timezone":"America/Mexico_City",
    "iso:country":"MX",
    "name:spa_x_preferred":[
        "Los Lirios"
    ],
    "wof:name":"Los Lirios",
    "wof:placetype":"locality"
},
  "geometry": {"coordinates":[-100.3236,19.66562],"type":"Point"}
}