{
  "type": "Feature",
  "properties": {
    "gn:admin1_code":"7.0",
    "gn:admin2_code":"6.0",
    "gn:asciiname":"Cuautla",
    "gn:cc2":"MX",
    "gn:country_code":"MX",
    "gn:dem":846,
    "gn:feature_class":"P",
    "gn:feature_code":"PPL",
    "gn:name":"Cuautla",
    "gn:population":0,
    "gn:timezone":"America/Monterrey",
    "iso:country":"MX",
    "name:und_x_variant":[
        "Cuzuilla",
        "Cuautla"
    ],
    "wof:name":"Cuautla",
    "wof:placetype":"locality"
},
  "geometry": {"coordinates":[-101.48333,26.78333],"type":"Point"}
}