{
  "type": "Feature",
  "properties": {
    "gn:admin1_code":"7",
    "gn:admin2_code":"34.0",
    "gn:asciiname":"El Reves",
    "gn:country_code":"MX",
    "gn:dem":1273,
    "gn:feature_class":"P",
    "gn:feature_code":"PPL",
    "gn:name":"El Rev\u00e9s",
    "gn:population":0,
    "gn:timezone":"America/Monterrey",
    "iso:country":"MX",
    "wof:name":"El Reves",
    "wof:placetype":"locality"
},
  "geometry": {"coordinates":[-103.55,27.88333],"type":"Point"}
}