{
  "type": "Feature",
  "properties": {
    "gn:admin1_code":"22.0",
    "gn:admin2_code":"1.0",
    "gn:asciiname":"Guadalupe el Terrero",
    "gn:country_code":"MX",
    "gn:dem":2502,
    "gn:feature_class":"P",
    "gn:feature_code":"PPL",
    "gn:name":"Guadalupe el Terrero",
    "gn:population":728,
    "gn:timezone":"America/Mexico_City",
    "iso:country":"MX",
    "name:und_x_variant":[
        "El Terrero",
        "Guadalupe el Terrero"
    ],
    "wof:name":"Guadalupe el Terrero",
    "wof:placetype":"locality",
    "wof:population":728
},
  "geometry": {"coordinates":[-100.14737,20.11876],"type":"Point"}
}