{
  "type": "Feature",
  "properties": {
    "gn:admin1_code":"12.0",
    "gn:admin2_code":"38.0",
    "gn:asciiname":"El Faisan",
    "gn:country_code":"MX",
    "gn:dem":1137,
    "gn:feature_class":"P",
    "gn:feature_code":"PPL",
    "gn:name":"El Fais\u00e1n",
    "gn:population":4,
    "gn:timezone":"America/Mexico_City",
    "iso:country":"MX",
    "wof:name":"El Faisan",
    "wof:placetype":"locality",
    "wof:population":4
},
  "geometry": {"coordinates":[-101.3758,18.00512],"type":"Point"}
}