{
  "type": "Feature",
  "properties": {
    "gn:admin1_code":"19.0",
    "gn:asciiname":"La Fabrica",
    "gn:country_code":"MX",
    "gn:dem":2060,
    "gn:feature_class":"P",
    "gn:feature_code":"PPL",
    "gn:name":"La F\u00e1brica",
    "gn:population":0,
    "gn:timezone":"America/Monterrey",
    "iso:country":"MX",
    "name:spa_x_preferred":[
        "La F\u00e1brica"
    ],
    "wof:name":"La Fabrica",
    "wof:placetype":"locality"
},
  "geometry": {"coordinates":[-99.99012999999999,24.59895],"type":"Point"}
}