{
  "type": "Feature",
  "properties": {
    "gn:admin1_code":"11.0",
    "gn:asciiname":"Pinalito de Palomas",
    "gn:country_code":"MX",
    "gn:dem":1862,
    "gn:feature_class":"P",
    "gn:feature_code":"PPL",
    "gn:name":"Pinalito de Palomas",
    "gn:population":0,
    "gn:timezone":"America/Mexico_City",
    "iso:country":"MX",
    "name:spa_x_preferred":[
        "Pinalito de Palomas"
    ],
    "wof:name":"Pinalito de Palomas",
    "wof:placetype":"locality"
},
  "geometry": {"coordinates":[-99.89559,21.39953],"type":"Point"}
}