{
  "type": "Feature",
  "properties": {
    "gn:admin1_code":"30",
    "gn:admin2_code":"57.0",
    "gn:asciiname":"La Parra",
    "gn:country_code":"MX",
    "gn:dem":1824,
    "gn:feature_class":"P",
    "gn:feature_code":"PPL",
    "gn:name":"La Parra",
    "gn:population":331,
    "gn:timezone":"America/Mexico_City",
    "iso:country":"MX",
    "wof:name":"La Parra",
    "wof:placetype":"locality",
    "wof:population":331
},
  "geometry": {"coordinates":[-96.83278,19.7675],"type":"Point"}
}