{
  "type": "Feature",
  "properties": {
    "gn:admin1_code":"13",
    "gn:asciiname":"Los Reyes",
    "gn:country_code":"MX",
    "gn:dem":2655,
    "gn:feature_class":"P",
    "gn:feature_code":"PPL",
    "gn:name":"Los Reyes",
    "gn:population":0,
    "gn:timezone":"America/Mexico_City",
    "iso:country":"MX",
    "name:spa_x_preferred":[
        "Los Reyes"
    ],
    "wof:name":"Los Reyes",
    "wof:placetype":"locality"
},
  "geometry": {"coordinates":[-98.24697,19.80379],"type":"Point"}
}