{
  "type": "Feature",
  "properties": {
    "gn:admin1_code":"25.0",
    "gn:admin2_code":"7.0",
    "gn:asciiname":"El Mezquite",
    "gn:country_code":"MX",
    "gn:dem":397,
    "gn:feature_class":"P",
    "gn:feature_code":"PPL",
    "gn:name":"El Mezquite",
    "gn:population":0,
    "gn:timezone":"America/Mazatlan",
    "iso:country":"MX",
    "name:spa_x_preferred":[
        "El Mezquite"
    ],
    "wof:name":"El Mezquite",
    "wof:placetype":"locality"
},
  "geometry": {"coordinates":[-108.37511000000001,26.63768],"type":"Point"}
}