{
  "type": "Feature",
  "properties": {
    "gn:admin1_code":"28.0",
    "gn:admin2_code":"37.0",
    "gn:asciiname":"La Jaiba",
    "gn:country_code":"MX",
    "gn:dem":14,
    "gn:feature_class":"P",
    "gn:feature_code":"PPL",
    "gn:name":"La Jaiba",
    "gn:population":4,
    "gn:timezone":"America/Monterrey",
    "iso:country":"MX",
    "name:spa_x_preferred":[
        "La Jaiba"
    ],
    "wof:name":"La Jaiba",
    "wof:placetype":"locality",
    "wof:population":4
},
  "geometry": {"coordinates":[-98.21028,23.74167000000001],"type":"Point"}
}