{
  "type": "Feature",
  "properties": {
    "gn:admin1_code":"14",
    "gn:admin2_code":"20.0",
    "gn:asciiname":"Maxeque",
    "gn:country_code":"MX",
    "gn:dem":335,
    "gn:feature_class":"P",
    "gn:feature_code":"PPL",
    "gn:name":"Maxeque",
    "gn:population":0,
    "gn:timezone":"America/Mexico_City",
    "iso:country":"MX",
    "name:spa_x_preferred":[
        "Maxeque"
    ],
    "wof:name":"Maxeque",
    "wof:placetype":"locality"
},
  "geometry": {"coordinates":[-105.51911,20.39691],"type":"Point"}
}