{
  "type": "Feature",
  "properties": {
    "gn:admin1_code":"30.0",
    "gn:admin2_code":"207.0",
    "gn:asciiname":"La Placa",
    "gn:country_code":"MX",
    "gn:dem":29,
    "gn:feature_class":"P",
    "gn:feature_code":"PPL",
    "gn:name":"La Placa",
    "gn:population":0,
    "gn:timezone":"America/Mexico_City",
    "iso:country":"MX",
    "name:spa_x_preferred":[
        "La Placa"
    ],
    "wof:name":"La Placa",
    "wof:placetype":"locality"
},
  "geometry": {"coordinates":[-96.13872000000001,18.36215],"type":"Point"}
}