{
  "type": "Feature",
  "properties": {
    "gn:admin1_code":"30",
    "gn:admin2_code":"198.0",
    "gn:asciiname":"Puerto Chico",
    "gn:country_code":"MX",
    "gn:dem":2109,
    "gn:feature_class":"P",
    "gn:feature_code":"PPL",
    "gn:name":"Puerto Chico",
    "gn:population":58,
    "gn:timezone":"America/Mexico_City",
    "iso:country":"MX",
    "wof:name":"Puerto Chico",
    "wof:placetype":"locality",
    "wof:population":58
},
  "geometry": {"coordinates":[-98.38083,20.47972],"type":"Point"}
}