{
  "type": "Feature",
  "properties": {
    "gn:admin1_code":"14",
    "gn:admin2_code":"15.0",
    "gn:asciiname":"Segunda Ampliacion de Autlan",
    "gn:country_code":"MX",
    "gn:dem":906,
    "gn:feature_class":"P",
    "gn:feature_code":"PPL",
    "gn:name":"Segunda Ampliaci\u00f3n de Autl\u00e1n",
    "gn:population":7,
    "gn:timezone":"America/Mexico_City",
    "iso:country":"MX",
    "name:und_x_variant":[
        "Segunda Ampliaci\u00f3n de Autl\u00e1n"
    ],
    "wof:name":"Segunda Ampliacion de Autlan",
    "wof:placetype":"locality",
    "wof:population":7
},
  "geometry": {"coordinates":[-104.35693999999999,19.72056],"type":"Point"}
}