{
  "type": "Feature",
  "properties": {
    "gn:admin1_code":"6",
    "gn:admin2_code":"3.0",
    "gn:asciiname":"Santa Isabel",
    "gn:cc2":"MX",
    "gn:country_code":"MX",
    "gn:dem":1596,
    "gn:feature_class":"P",
    "gn:feature_code":"PPL",
    "gn:name":"Santa Isabel",
    "gn:population":0,
    "gn:timezone":"America/Chihuahua",
    "iso:country":"MX",
    "name:und_x_variant":[
        "Rancho Santa Isabel",
        "Santa Isabel"
    ],
    "wof:name":"Santa Isabel",
    "wof:placetype":"locality"
},
  "geometry": {"coordinates":[-105.36667,26.96667],"type":"Point"}
}