{
  "type": "Feature",
  "properties": {
    "gn:admin1_code":"24",
    "gn:admin2_code":"57.0",
    "gn:asciiname":"Tezonquilillo",
    "gn:country_code":"MX",
    "gn:dem":142,
    "gn:feature_class":"P",
    "gn:feature_code":"PPL",
    "gn:name":"Tezonquilillo",
    "gn:population":113,
    "gn:timezone":"America/Mexico_City",
    "iso:country":"MX",
    "wof:name":"Tezonquilillo",
    "wof:placetype":"locality",
    "wof:population":113
},
  "geometry": {"coordinates":[-98.88806,21.33389],"type":"Point"}
}