{
  "type": "Feature",
  "properties": {
    "gn:admin1_code":"12",
    "gn:admin2_code":"53.0",
    "gn:asciiname":"Vista Hermosa",
    "gn:country_code":"MX",
    "gn:dem":63,
    "gn:feature_class":"P",
    "gn:feature_code":"PPL",
    "gn:name":"Vista Hermosa",
    "gn:population":40,
    "gn:timezone":"America/Mexico_City",
    "iso:country":"MX",
    "name:ceb_x_preferred":[
        "Vista Hermosa"
    ],
    "name:deu_x_preferred":[
        "Vista Hermosa"
    ],
    "name:spa_x_preferred":[
        "Vista Hermosa"
    ],
    "name:swe_x_preferred":[
        "Vista Hermosa"
    ],
    "name:vie_x_preferred":[
        "Vista Hermosa"
    ],
    "wof:name":"Vista Hermosa",
    "wof:placetype":"locality",
    "wof:population":40
},
  "geometry": {"coordinates":[-99.38686,16.73907],"type":"Point"}
}