{
  "type": "Feature",
  "properties": {
    "gn:admin1_code":"14",
    "gn:admin2_code":"93",
    "gn:asciiname":"La Paleta",
    "gn:country_code":"MX",
    "gn:dem":2056,
    "gn:feature_class":"P",
    "gn:feature_code":"PPL",
    "gn:name":"La Paleta",
    "gn:population":37,
    "gn:timezone":"America/Mexico_City",
    "iso:country":"MX",
    "wof:name":"La Paleta",
    "wof:placetype":"locality",
    "wof:population":37
},
  "geometry": {"coordinates":[-102.60917000000001,20.84194],"type":"Point"}
}