{
  "type": "Feature",
  "properties": {
    "gn:admin1_code":"10",
    "gn:admin2_code":"21.0",
    "gn:asciiname":"El Divisadero",
    "gn:country_code":"MX",
    "gn:dem":1848,
    "gn:feature_class":"P",
    "gn:feature_code":"PPL",
    "gn:name":"El Divisadero",
    "gn:population":0,
    "gn:timezone":"America/Monterrey",
    "iso:country":"MX",
    "name:spa_x_preferred":[
        "El Divisadero"
    ],
    "wof:name":"El Divisadero",
    "wof:placetype":"locality"
},
  "geometry": {"coordinates":[-103.9308,24.63737],"type":"Point"}
}