{
  "type": "Feature",
  "properties": {
    "gn:admin1_code":"6",
    "gn:admin2_code":"19.0",
    "gn:asciiname":"La Providencia",
    "gn:country_code":"MX",
    "gn:dem":1651,
    "gn:feature_class":"P",
    "gn:feature_code":"PPL",
    "gn:name":"La Providencia",
    "gn:population":7,
    "gn:timezone":"America/Chihuahua",
    "iso:country":"MX",
    "name:und_x_variant":[
        "Rancho La Providencia",
        "La Providencia"
    ],
    "wof:name":"La Providencia",
    "wof:placetype":"locality",
    "wof:population":7
},
  "geometry": {"coordinates":[-106.47854,29.56612],"type":"Point"}
}