{
  "type": "Feature",
  "properties": {
    "gn:admin1_code":"31",
    "gn:admin2_code":"29.0",
    "gn:asciiname":"El Oasis",
    "gn:country_code":"MX",
    "gn:dem":1,
    "gn:feature_class":"P",
    "gn:feature_code":"PPL",
    "gn:name":"El Oasis",
    "gn:population":0,
    "gn:timezone":"America/Merida",
    "iso:country":"MX",
    "name:sco_x_preferred":[
        "El Oasis"
    ],
    "name:spa_x_preferred":[
        "El Oasis"
    ],
    "name:srp_x_preferred":[
        "\u0415\u043b \u041e\u0430\u0441\u0438\u0441"
    ],
    "wof:name":"El Oasis",
    "wof:placetype":"locality"
},
  "geometry": {"coordinates":[-88.74406,21.393],"type":"Point"}
}