{
  "type": "Feature",
  "properties": {
    "gn:admin1_code":"30.0",
    "gn:admin2_code":"151.0",
    "gn:asciiname":"Las Ardillas",
    "gn:country_code":"MX",
    "gn:dem":32,
    "gn:feature_class":"P",
    "gn:feature_code":"PPL",
    "gn:name":"Las Ardillas",
    "gn:population":0,
    "gn:timezone":"America/Mexico_City",
    "iso:country":"MX",
    "name:spa_x_preferred":[
        "Las Ardillas"
    ],
    "wof:name":"Las Ardillas",
    "wof:placetype":"locality"
},
  "geometry": {"coordinates":[-97.54613000000001,21.30513],"type":"Point"}
}