{
  "type": "Feature",
  "properties": {
    "gn:admin1_code":"26.0",
    "gn:admin2_code":"29.0",
    "gn:asciiname":"La Granadita",
    "gn:country_code":"MX",
    "gn:dem":172,
    "gn:feature_class":"P",
    "gn:feature_code":"PPL",
    "gn:name":"La Granadita",
    "gn:population":0,
    "gn:timezone":"America/Hermosillo",
    "iso:country":"MX",
    "name:spa_x_preferred":[
        "La Granadita"
    ],
    "wof:name":"La Granadita",
    "wof:placetype":"locality"
},
  "geometry": {"coordinates":[-110.50997,28.33097],"type":"Point"}
}