{
  "type": "Feature",
  "properties": {
    "gn:admin1_code":"12",
    "gn:admin2_code":"16",
    "gn:asciiname":"La Chorrera",
    "gn:country_code":"MX",
    "gn:dem":194,
    "gn:feature_class":"P",
    "gn:feature_code":"PPL",
    "gn:name":"La Chorrera",
    "gn:population":11,
    "gn:timezone":"America/Mexico_City",
    "iso:country":"MX",
    "wof:name":"La Chorrera",
    "wof:placetype":"locality",
    "wof:population":11
},
  "geometry": {"coordinates":[-101.76687,18.29476],"type":"Point"}
}