{
  "type": "Feature",
  "properties": {
    "gn:admin1_code":"10",
    "gn:admin2_code":"16.0",
    "gn:asciiname":"El Clavo Uno",
    "gn:country_code":"MX",
    "gn:dem":1894,
    "gn:feature_class":"P",
    "gn:feature_code":"PPL",
    "gn:name":"El Clavo Uno",
    "gn:population":0,
    "gn:timezone":"America/Monterrey",
    "iso:country":"MX",
    "name:spa_x_preferred":[
        "El Clavo Uno"
    ],
    "wof:name":"El Clavo Uno",
    "wof:placetype":"locality"
},
  "geometry": {"coordinates":[-104.35097,23.94224],"type":"Point"}
}