{
  "type": "Feature",
  "properties": {
    "gn:admin1_code":"16",
    "gn:admin2_code":"53.0",
    "gn:asciiname":"Los Capulines",
    "gn:country_code":"MX",
    "gn:dem":2092,
    "gn:feature_class":"P",
    "gn:feature_code":"PPL",
    "gn:name":"Los Capulines",
    "gn:population":8,
    "gn:timezone":"America/Mexico_City",
    "iso:country":"MX",
    "wof:name":"Los Capulines",
    "wof:placetype":"locality",
    "wof:population":8
},
  "geometry": {"coordinates":[-101.16777999999999,19.67194],"type":"Point"}
}