{
  "type": "Feature",
  "properties": {
    "gn:admin1_code":"14.0",
    "gn:admin2_code":"69.0",
    "gn:asciiname":"Gueibida",
    "gn:country_code":"MX",
    "gn:dem":1465,
    "gn:feature_class":"P",
    "gn:feature_code":"PPL",
    "gn:name":"G\u00fcibida",
    "gn:population":0,
    "gn:timezone":"America/Mexico_City",
    "iso:country":"MX",
    "name:spa_x_preferred":[
        "G\u00fcibida"
    ],
    "wof:name":"Gueibida",
    "wof:placetype":"locality"
},
  "geometry": {"coordinates":[-102.88903999999999,19.67188],"type":"Point"}
}