{
  "type": "Feature",
  "properties": {
    "gn:admin1_code":"30",
    "gn:admin2_code":"184",
    "gn:asciiname":"Crucero de Pitzcuautla",
    "gn:country_code":"MX",
    "gn:dem":2236,
    "gn:feature_class":"P",
    "gn:feature_code":"PPL",
    "gn:name":"Crucero de Pitzcuautla",
    "gn:population":42,
    "gn:timezone":"America/Mexico_City",
    "iso:country":"MX",
    "wof:name":"Crucero de Pitzcuautla",
    "wof:placetype":"locality",
    "wof:population":42
},
  "geometry": {"coordinates":[-97.095,18.59444],"type":"Point"}
}