{
  "type": "Feature",
  "properties": {
    "gn:admin1_code":"30",
    "gn:admin2_code":"11.0",
    "gn:asciiname":"Las Trochas",
    "gn:country_code":"MX",
    "gn:dem":9,
    "gn:feature_class":"P",
    "gn:feature_code":"PPL",
    "gn:name":"Las Trochas",
    "gn:population":0,
    "gn:timezone":"America/Mexico_City",
    "iso:country":"MX",
    "name:spa_x_preferred":[
        "Las Trochas"
    ],
    "wof:name":"Las Trochas",
    "wof:placetype":"locality"
},
  "geometry": {"coordinates":[-95.75324000000001,18.78118],"type":"Point"}
}