{
  "type": "Feature",
  "properties": {
    "gn:admin1_code":"30",
    "gn:admin2_code":"25.0",
    "gn:asciiname":"El Tepeyac",
    "gn:country_code":"MX",
    "gn:dem":2192,
    "gn:feature_class":"P",
    "gn:feature_code":"PPL",
    "gn:name":"El Tepeyac",
    "gn:population":443,
    "gn:timezone":"America/Mexico_City",
    "iso:country":"MX",
    "wof:name":"El Tepeyac",
    "wof:placetype":"locality",
    "wof:population":443
},
  "geometry": {"coordinates":[-97.16028,19.34944],"type":"Point"}
}