{
  "type": "Feature",
  "properties": {
    "gn:admin1_code":"4",
    "gn:admin2_code":"9.0",
    "gn:asciiname":"Don Gume",
    "gn:country_code":"MX",
    "gn:dem":62,
    "gn:feature_class":"P",
    "gn:feature_code":"PPL",
    "gn:name":"Don Gume",
    "gn:population":7,
    "gn:timezone":"America/Merida",
    "iso:country":"MX",
    "wof:name":"Don Gume",
    "wof:placetype":"locality",
    "wof:population":7
},
  "geometry": {"coordinates":[-90.97944,18.44417],"type":"Point"}
}