{
  "type": "Feature",
  "properties": {
    "gn:admin1_code":"30",
    "gn:admin2_code":"81.0",
    "gn:asciiname":"Rancho de Pala",
    "gn:country_code":"MX",
    "gn:dem":1388,
    "gn:feature_class":"P",
    "gn:feature_code":"PPL",
    "gn:name":"Rancho de Pala",
    "gn:population":837,
    "gn:timezone":"America/Mexico_City",
    "iso:country":"MX",
    "wof:name":"Rancho de Pala",
    "wof:placetype":"locality",
    "wof:population":837
},
  "geometry": {"coordinates":[-97.1375,18.88278],"type":"Point"}
}