{
  "type": "Feature",
  "properties": {
    "gn:admin1_code":"7",
    "gn:admin2_code":"2.0",
    "gn:asciiname":"Los Cuates",
    "gn:country_code":"MX",
    "gn:dem":558,
    "gn:feature_class":"P",
    "gn:feature_code":"PPL",
    "gn:name":"Los Cuates",
    "gn:population":0,
    "gn:timezone":"America/Matamoros",
    "iso:country":"MX",
    "name:spa_x_preferred":[
        "Los Cuates"
    ],
    "name:und_x_variant":[
        "Rancho Los Cuates",
        "Los Albertos"
    ],
    "wof:name":"Los Cuates",
    "wof:placetype":"locality"
},
  "geometry": {"coordinates":[-101.64031,29.58084],"type":"Point"}
}