{
  "type": "Feature",
  "properties": {
    "gn:admin1_code":"10.0",
    "gn:asciiname":"Las Joyas",
    "gn:country_code":"MX",
    "gn:dem":2400,
    "gn:feature_class":"P",
    "gn:feature_code":"PPL",
    "gn:name":"Las Joyas",
    "gn:population":0,
    "gn:timezone":"America/Monterrey",
    "iso:country":"MX",
    "name:spa_x_preferred":[
        "Las Joyas"
    ],
    "wof:name":"Las Joyas",
    "wof:placetype":"locality"
},
  "geometry": {"coordinates":[-105.70819,24.00614],"type":"Point"}
}