{
  "type": "Feature",
  "properties": {
    "gn:admin1_code":"30.0",
    "gn:asciiname":"Desviacion a Aguacatillo",
    "gn:country_code":"MX",
    "gn:dem":117,
    "gn:feature_class":"P",
    "gn:feature_code":"PPL",
    "gn:name":"Desviaci\u00f3n a Aguacatillo",
    "gn:population":0,
    "gn:timezone":"America/Mexico_City",
    "iso:country":"MX",
    "name:spa_x_preferred":[
        "Desviaci\u00f3n a Aguacatillo"
    ],
    "wof:name":"Desviacion a Aguacatillo",
    "wof:placetype":"locality"
},
  "geometry": {"coordinates":[-95.07868999999999,17.89885],"type":"Point"}
}