{
  "type": "Feature",
  "properties": {
    "gn:admin1_code":"10.0",
    "gn:admin2_code":"14.0",
    "gn:asciiname":"La Cena",
    "gn:country_code":"MX",
    "gn:dem":1028,
    "gn:feature_class":"P",
    "gn:feature_code":"PPL",
    "gn:name":"La Cena",
    "gn:population":0,
    "gn:timezone":"America/Mazatlan",
    "iso:country":"MX",
    "name:spa_x_preferred":[
        "La Cena"
    ],
    "wof:name":"La Cena",
    "wof:placetype":"locality"
},
  "geometry": {"coordinates":[-104.56882,22.41506],"type":"Point"}
}