{
  "type": "Feature",
  "properties": {
    "gn:admin1_code":"6",
    "gn:admin2_code":"29.0",
    "gn:asciiname":"Alisos de Arriba",
    "gn:country_code":"MX",
    "gn:dem":1211,
    "gn:feature_class":"P",
    "gn:feature_code":"PPL",
    "gn:name":"Alisos de Arriba",
    "gn:population":0,
    "gn:timezone":"America/Chihuahua",
    "iso:country":"MX",
    "name:spa_x_preferred":[
        "Alisos de Arriba"
    ],
    "wof:name":"Alisos de Arriba",
    "wof:placetype":"locality"
},
  "geometry": {"coordinates":[-107.26108000000001,26.19315],"type":"Point"}
}