{
  "type": "Feature",
  "properties": {
    "gn:admin1_code":"28.0",
    "gn:admin2_code":"20.0",
    "gn:asciiname":"Magueycitos",
    "gn:country_code":"MX",
    "gn:dem":309,
    "gn:feature_class":"P",
    "gn:feature_code":"PPL",
    "gn:name":"Magueycitos",
    "gn:population":0,
    "gn:timezone":"America/Monterrey",
    "iso:country":"MX",
    "name:spa_x_preferred":[
        "Magueyes"
    ],
    "name:spa_x_variant":[
        "Magueycitos"
    ],
    "wof:name":"Magueycitos",
    "wof:placetype":"locality"
},
  "geometry": {"coordinates":[-99.46933,24.71329],"type":"Point"}
}