{
  "type": "Feature",
  "properties": {
    "gn:admin1_code":"12",
    "gn:admin2_code":"71.0",
    "gn:asciiname":"Cerro Cenizas",
    "gn:country_code":"MX",
    "gn:dem":380,
    "gn:feature_class":"P",
    "gn:feature_code":"PPL",
    "gn:name":"Cerro Cenizas",
    "gn:population":91,
    "gn:timezone":"America/Mexico_City",
    "iso:country":"MX",
    "wof:name":"Cerro Cenizas",
    "wof:placetype":"locality",
    "wof:population":91
},
  "geometry": {"coordinates":[-98.19284,16.74574],"type":"Point"}
}