{
  "type": "Feature",
  "properties": {
    "gn:admin1_code":"7.0",
    "gn:admin2_code":"20.0",
    "gn:asciiname":"Torrecillas",
    "gn:country_code":"MX",
    "gn:dem":1295,
    "gn:feature_class":"P",
    "gn:feature_code":"PPL",
    "gn:name":"Torrecillas",
    "gn:population":0,
    "gn:timezone":"America/Monterrey",
    "iso:country":"MX",
    "name:spa_x_preferred":[
        "Torrecillas"
    ],
    "wof:name":"Torrecillas",
    "wof:placetype":"locality"
},
  "geometry": {"coordinates":[-102.45115,28.8105],"type":"Point"}
}