{
  "type": "Feature",
  "properties": {
    "gn:admin1_code":"17",
    "gn:admin2_code":"10.0",
    "gn:asciiname":"La Renta",
    "gn:country_code":"MX",
    "gn:dem":1444,
    "gn:feature_class":"P",
    "gn:feature_code":"PPL",
    "gn:name":"La Renta",
    "gn:population":148,
    "gn:timezone":"America/Mexico_City",
    "iso:country":"MX",
    "wof:name":"La Renta",
    "wof:placetype":"locality",
    "wof:population":148
},
  "geometry": {"coordinates":[-98.80833,18.73056],"type":"Point"}
}