{
  "type": "Feature",
  "properties": {
    "gn:admin1_code":"32",
    "gn:admin2_code":"31.0",
    "gn:asciiname":"Huicholes",
    "gn:country_code":"MX",
    "gn:dem":2423,
    "gn:feature_class":"P",
    "gn:feature_code":"PPL",
    "gn:name":"Huicholes",
    "gn:population":0,
    "gn:timezone":"America/Mexico_City",
    "iso:country":"MX",
    "name:spa_x_preferred":[
        "Huicholes"
    ],
    "wof:name":"Huicholes",
    "wof:placetype":"locality"
},
  "geometry": {"coordinates":[-103.59536,22.32293],"type":"Point"}
}