{
  "type": "Feature",
  "properties": {
    "gn:admin1_code":"28",
    "gn:admin2_code":"39",
    "gn:asciiname":"Espiritu Santo (Gordas de Horno)",
    "gn:country_code":"MX",
    "gn:dem":1099,
    "gn:feature_class":"P",
    "gn:feature_code":"PPL",
    "gn:name":"Esp\u00edritu Santo (Gordas de Horno)",
    "gn:population":18,
    "gn:timezone":"America/Monterrey",
    "iso:country":"MX",
    "name:und_x_variant":[
        "Esp\u00edritu Santo (Gordas de Horno)"
    ],
    "wof:name":"Espiritu Santo (Gordas de Horno)",
    "wof:placetype":"locality",
    "wof:population":18
},
  "geometry": {"coordinates":[-99.70694,22.92444],"type":"Point"}
}