{
  "type": "Feature",
  "properties": {
    "gn:admin1_code":"11",
    "gn:admin2_code":"44.0",
    "gn:asciiname":"El Chinaco (El Pujido)",
    "gn:country_code":"MX",
    "gn:dem":1742,
    "gn:feature_class":"P",
    "gn:feature_code":"PPL",
    "gn:name":"El Chinaco (El Pujido)",
    "gn:population":1534,
    "gn:timezone":"America/Mexico_City",
    "iso:country":"MX",
    "wof:name":"El Chinaco (El Pujido)",
    "wof:placetype":"locality",
    "wof:population":1534
},
  "geometry": {"coordinates":[-100.91972,20.52222],"type":"Point"}
}