{
  "type": "Feature",
  "properties": {
    "gn:admin1_code":"5",
    "gn:admin2_code":"92.0",
    "gn:asciiname":"Chimalapa",
    "gn:country_code":"MX",
    "gn:dem":103,
    "gn:feature_class":"P",
    "gn:feature_code":"PPL",
    "gn:name":"Chimalapa",
    "gn:population":0,
    "gn:timezone":"America/Mexico_City",
    "iso:country":"MX",
    "name:spa_x_preferred":[
        "Chimalapa"
    ],
    "wof:name":"Chimalapa",
    "wof:placetype":"locality"
},
  "geometry": {"coordinates":[-93.56259,17.34036],"type":"Point"}
}