{
  "type": "Feature",
  "properties": {
    "gn:admin1_code":"6",
    "gn:admin2_code":"27.0",
    "gn:asciiname":"Ritoachi",
    "gn:country_code":"MX",
    "gn:dem":2184,
    "gn:feature_class":"P",
    "gn:feature_code":"PPL",
    "gn:name":"Ritoachi",
    "gn:population":0,
    "gn:timezone":"America/Chihuahua",
    "iso:country":"MX",
    "name:spa_x_preferred":[
        "Lituachi"
    ],
    "name:spa_x_variant":[
        "Ritoachi"
    ],
    "wof:name":"Ritoachi",
    "wof:placetype":"locality"
},
  "geometry": {"coordinates":[-107.52785,27.30534],"type":"Point"}
}