{
  "type": "Feature",
  "properties": {
    "gn:admin1_code":"20",
    "gn:admin2_code":"325.0",
    "gn:asciiname":"San Pablo Lachiriega",
    "gn:country_code":"MX",
    "gn:dem":1028,
    "gn:feature_class":"P",
    "gn:feature_code":"PPL",
    "gn:name":"San Pablo Lachiriega",
    "gn:population":614,
    "gn:timezone":"America/Mexico_City",
    "iso:country":"MX",
    "name:spa_x_preferred":[
        "San Pablo Lachiriega"
    ],
    "wof:name":"San Pablo Lachiriega",
    "wof:placetype":"locality",
    "wof:population":614
},
  "geometry": {"coordinates":[-96.01083,16.84111],"type":"Point"}
}