{
  "type": "Feature",
  "properties": {
    "gn:admin1_code":"4",
    "gn:admin2_code":"11.0",
    "gn:asciiname":"El Divino Nino",
    "gn:country_code":"MX",
    "gn:dem":82,
    "gn:feature_class":"P",
    "gn:feature_code":"PPL",
    "gn:name":"El Divino Ni\u00f1o",
    "gn:population":5,
    "gn:timezone":"America/Merida",
    "iso:country":"MX",
    "name:und_x_variant":[
        "El Divino Ni\u00f1o"
    ],
    "wof:name":"El Divino Nino",
    "wof:placetype":"locality",
    "wof:population":5
},
  "geometry": {"coordinates":[-90.50778,17.90111],"type":"Point"}
}