{
  "type": "Feature",
  "properties": {
    "gn:admin1_code":"2",
    "gn:admin2_code":"1.0",
    "gn:asciiname":"Rancho Los Olivos",
    "gn:country_code":"MX",
    "gn:dem":31,
    "gn:feature_class":"P",
    "gn:feature_code":"PPL",
    "gn:name":"Rancho Los Olivos",
    "gn:population":0,
    "gn:timezone":"America/Tijuana",
    "iso:country":"MX",
    "wof:name":"Rancho Los Olivos",
    "wof:placetype":"locality"
},
  "geometry": {"coordinates":[-116.00363,30.7448],"type":"Point"}
}