{
  "type": "Feature",
  "properties": {
    "gn:admin1_code":"5",
    "gn:admin2_code":"46.0",
    "gn:asciiname":"Rio Negro",
    "gn:country_code":"MX",
    "gn:dem":547,
    "gn:feature_class":"P",
    "gn:feature_code":"PPL",
    "gn:name":"R\u00edo Negro",
    "gn:population":5,
    "gn:timezone":"America/Mexico_City",
    "iso:country":"MX",
    "name:und_x_variant":[
        "R\u00edo Negro"
    ],
    "wof:name":"Rio Negro",
    "wof:placetype":"locality",
    "wof:population":5
},
  "geometry": {"coordinates":[-93.57611,16.60639],"type":"Point"}
}