{
  "type": "Feature",
  "properties": {
    "gn:admin1_code":"6.0",
    "gn:admin2_code":"7.0",
    "gn:asciiname":"Aguaje de Salome",
    "gn:country_code":"MX",
    "gn:dem":1998,
    "gn:feature_class":"P",
    "gn:feature_code":"PPL",
    "gn:name":"Aguaje de Salom\u00e9",
    "gn:population":0,
    "gn:timezone":"America/Chihuahua",
    "iso:country":"MX",
    "name:spa_x_preferred":[
        "Aguaje de Salom\u00e9"
    ],
    "wof:name":"Aguaje de Salome",
    "wof:placetype":"locality"
},
  "geometry": {"coordinates":[-106.80302,27.05998],"type":"Point"}
}