{
  "type": "Feature",
  "properties": {
    "gn:admin1_code":"18.0",
    "gn:admin2_code":"9.0",
    "gn:asciiname":"El Magueey",
    "gn:country_code":"MX",
    "gn:dem":605,
    "gn:feature_class":"P",
    "gn:feature_code":"PPL",
    "gn:name":"El Mag\u00fcey",
    "gn:population":0,
    "gn:timezone":"America/Mazatlan",
    "iso:country":"MX",
    "name:spa_x_preferred":[
        "El Mag\u00fcey"
    ],
    "wof:name":"El Magueey",
    "wof:placetype":"locality"
},
  "geometry": {"coordinates":[-104.53055999999999,22.02413],"type":"Point"}
}