{
  "type": "Feature",
  "properties": {
    "gn:admin1_code":"14",
    "gn:admin2_code":"110.0",
    "gn:asciiname":"El Nogal",
    "gn:country_code":"MX",
    "gn:dem":1344,
    "gn:feature_class":"P",
    "gn:feature_code":"PPL",
    "gn:name":"El Nogal",
    "gn:population":7,
    "gn:timezone":"America/Mexico_City",
    "iso:country":"MX",
    "wof:name":"El Nogal",
    "wof:placetype":"locality",
    "wof:population":7
},
  "geometry": {"coordinates":[-104.25139,19.98639],"type":"Point"}
}