{
  "type": "Feature",
  "properties": {
    "gn:admin1_code":"4",
    "gn:admin2_code":"3.0",
    "gn:asciiname":"Heras",
    "gn:country_code":"MX",
    "gn:dem":6,
    "gn:feature_class":"P",
    "gn:feature_code":"PPL",
    "gn:name":"Heras",
    "gn:population":0,
    "gn:timezone":"America/Merida",
    "iso:country":"MX",
    "name:deu_x_preferred":[
        "Heras"
    ],
    "name:fra_x_preferred":[
        "Heras"
    ],
    "name:rus_x_preferred":[
        "\u042d\u0440\u0430\u0441"
    ],
    "name:spa_x_preferred":[
        "Heras"
    ],
    "wof:name":"Heras",
    "wof:placetype":"locality"
},
  "geometry": {"coordinates":[-91.25,18.36278],"type":"Point"}
}