{
  "type": "Feature",
  "properties": {
    "gn:admin1_code":"2",
    "gn:admin2_code":"2",
    "gn:asciiname":"Familia Bernal Ordonez (Colonia Madero)",
    "gn:country_code":"MX",
    "gn:dem":15,
    "gn:feature_class":"P",
    "gn:feature_code":"PPL",
    "gn:name":"Familia Bernal Ord\u00f3\u00f1ez (Colonia Madero)",
    "gn:population":10,
    "gn:timezone":"America/Tijuana",
    "iso:country":"MX",
    "name:und_x_variant":[
        "Familia Bernal Ord\u00f3\u00f1ez (Colonia Madero)"
    ],
    "wof:name":"Familia Bernal Ordonez (Colonia Madero)",
    "wof:placetype":"locality",
    "wof:population":10
},
  "geometry": {"coordinates":[-115.02943999999999,32.32556],"type":"Point"}
}