{
  "type": "Feature",
  "properties": {
    "gn:admin1_code":"20",
    "gn:admin2_code":"408.0",
    "gn:asciiname":"Boca del Perro",
    "gn:country_code":"MX",
    "gn:dem":2339,
    "gn:feature_class":"P",
    "gn:feature_code":"PPL",
    "gn:name":"Boca del Perro",
    "gn:population":64,
    "gn:timezone":"America/Mexico_City",
    "iso:country":"MX",
    "wof:name":"Boca del Perro",
    "wof:placetype":"locality",
    "wof:population":64
},
  "geometry": {"coordinates":[-97.61111,17.35861],"type":"Point"}
}