{
  "type": "Feature",
  "properties": {
    "gn:admin1_code":"11.0",
    "gn:admin2_code":"23.0",
    "gn:asciiname":"Noria de Barajas",
    "gn:country_code":"MX",
    "gn:dem":1709,
    "gn:feature_class":"P",
    "gn:feature_code":"PPL",
    "gn:name":"Noria de Barajas",
    "gn:population":0,
    "gn:timezone":"America/Mexico_City",
    "iso:country":"MX",
    "name:spa_x_preferred":[
        "Noria de Barajas"
    ],
    "name:spa_x_variant":[
        "La Noria"
    ],
    "wof:name":"Noria de Barajas",
    "wof:placetype":"locality"
},
  "geometry": {"coordinates":[-101.6674,20.33662],"type":"Point"}
}