{
  "type": "Feature",
  "properties": {
    "gn:admin1_code":"20",
    "gn:admin2_code":"141.0",
    "gn:asciiname":"Aguachil",
    "gn:country_code":"MX",
    "gn:dem":12,
    "gn:feature_class":"P",
    "gn:feature_code":"PPL",
    "gn:name":"Aguachil",
    "gn:population":0,
    "gn:timezone":"America/Mexico_City",
    "iso:country":"MX",
    "name:spa_x_preferred":[
        "Aguachil"
    ],
    "wof:name":"Aguachil",
    "wof:placetype":"locality"
},
  "geometry": {"coordinates":[-94.51092,16.19192],"type":"Point"}
}