{
  "type": "Feature",
  "properties": {
    "gn:admin1_code":"7",
    "gn:admin2_code":"31.0",
    "gn:asciiname":"San Guillermo",
    "gn:country_code":"MX",
    "gn:dem":484,
    "gn:feature_class":"P",
    "gn:feature_code":"PPL",
    "gn:name":"San Guillermo",
    "gn:population":0,
    "gn:timezone":"America/Monterrey",
    "iso:country":"MX",
    "name:spa_x_preferred":[
        "San Guillermo"
    ],
    "wof:name":"San Guillermo",
    "wof:placetype":"locality"
},
  "geometry": {"coordinates":[-101.47441999999999,27.08657],"type":"Point"}
}