{
  "type": "Feature",
  "properties": {
    "gn:admin1_code":"24.0",
    "gn:admin2_code":"32.0",
    "gn:asciiname":"Laborcilla",
    "gn:country_code":"MX",
    "gn:dem":1888,
    "gn:feature_class":"P",
    "gn:feature_code":"PPL",
    "gn:name":"Laborcilla",
    "gn:population":0,
    "gn:timezone":"America/Mexico_City",
    "iso:country":"MX",
    "name:und_x_variant":[
        "Laborcillas",
        "Laborcilla"
    ],
    "wof:name":"Laborcilla",
    "wof:placetype":"locality"
},
  "geometry": {"coordinates":[-100.37481,21.82587],"type":"Point"}
}