{
  "type": "Feature",
  "properties": {
    "gn:admin1_code":"30",
    "gn:admin2_code":"109.0",
    "gn:asciiname":"Arroyo Negro",
    "gn:country_code":"MX",
    "gn:dem":531,
    "gn:feature_class":"P",
    "gn:feature_code":"PPL",
    "gn:name":"Arroyo Negro",
    "gn:population":149,
    "gn:timezone":"America/Mexico_City",
    "iso:country":"MX",
    "wof:name":"Arroyo Negro",
    "wof:placetype":"locality",
    "wof:population":149
},
  "geometry": {"coordinates":[-96.82194,19.89556],"type":"Point"}
}