{
  "type": "Feature",
  "properties": {
    "gn:admin1_code":"19",
    "gn:admin2_code":"20.0",
    "gn:asciiname":"La Simona",
    "gn:country_code":"MX",
    "gn:dem":142,
    "gn:feature_class":"P",
    "gn:feature_code":"PPL",
    "gn:name":"La Simona",
    "gn:population":0,
    "gn:timezone":"America/Monterrey",
    "iso:country":"MX",
    "name:spa_x_preferred":[
        "La Simona"
    ],
    "name:und_x_variant":[
        "Simona"
    ],
    "wof:name":"La Simona",
    "wof:placetype":"locality"
},
  "geometry": {"coordinates":[-98.95474,25.67336],"type":"Point"}
}