{
  "type": "Feature",
  "properties": {
    "gn:admin1_code":"32",
    "gn:admin2_code":"21.0",
    "gn:asciiname":"La Cuchilla de Arriba",
    "gn:country_code":"MX",
    "gn:dem":1983,
    "gn:feature_class":"P",
    "gn:feature_code":"PPL",
    "gn:name":"La Cuchilla de Arriba",
    "gn:population":0,
    "gn:timezone":"America/Mexico_City",
    "iso:country":"MX",
    "name:spa_x_preferred":[
        "La Cuchilla de Arriba"
    ],
    "wof:name":"La Cuchilla de Arriba",
    "wof:placetype":"locality"
},
  "geometry": {"coordinates":[-103.831,23.25418],"type":"Point"}
}