{
  "type": "Feature",
  "properties": {
    "gn:admin1_code":"12",
    "gn:admin2_code":"3.0",
    "gn:asciiname":"Las Chicas",
    "gn:country_code":"MX",
    "gn:dem":610,
    "gn:feature_class":"P",
    "gn:feature_code":"PPL",
    "gn:name":"Las Chicas",
    "gn:population":5,
    "gn:timezone":"America/Mexico_City",
    "iso:country":"MX",
    "wof:name":"Las Chicas",
    "wof:placetype":"locality",
    "wof:population":5
},
  "geometry": {"coordinates":[-100.65382,17.98624],"type":"Point"}
}