{
  "type": "Feature",
  "properties": {
    "gn:admin1_code":"16",
    "gn:admin2_code":"19.0",
    "gn:asciiname":"El Herrero",
    "gn:country_code":"MX",
    "gn:dem":1338,
    "gn:feature_class":"P",
    "gn:feature_code":"PPL",
    "gn:name":"El Herrero",
    "gn:population":7,
    "gn:timezone":"America/Mexico_City",
    "iso:country":"MX",
    "wof:name":"El Herrero",
    "wof:placetype":"locality",
    "wof:population":7
},
  "geometry": {"coordinates":[-102.72499999999999,19.63028],"type":"Point"}
}