{
  "type": "Feature",
  "properties": {
    "gn:admin1_code":"30.0",
    "gn:asciiname":"El Tapon",
    "gn:country_code":"MX",
    "gn:dem":14,
    "gn:feature_class":"P",
    "gn:feature_code":"PPL",
    "gn:name":"El Tap\u00f3n",
    "gn:population":0,
    "gn:timezone":"America/Mexico_City",
    "iso:country":"MX",
    "name:spa_x_preferred":[
        "El Tap\u00f3n"
    ],
    "wof:name":"El Tapon",
    "wof:placetype":"locality"
},
  "geometry": {"coordinates":[-95.5428,18.27713],"type":"Point"}
}