{
  "type": "Feature",
  "properties": {
    "gn:admin1_code":"6",
    "gn:admin2_code":"27.0",
    "gn:asciiname":"Raramuchi",
    "gn:country_code":"MX",
    "gn:dem":2251,
    "gn:feature_class":"P",
    "gn:feature_code":"PPL",
    "gn:name":"Rar\u00e1muchi",
    "gn:population":40,
    "gn:timezone":"America/Chihuahua",
    "iso:country":"MX",
    "name:spa_x_preferred":[
        "Rar\u00e1muchi"
    ],
    "wof:name":"Raramuchi",
    "wof:placetype":"locality",
    "wof:population":40
},
  "geometry": {"coordinates":[-107.60464,27.49187],"type":"Point"}
}