{
  "type": "Feature",
  "properties": {
    "gn:admin1_code":"22",
    "gn:admin2_code":"8.0",
    "gn:asciiname":"La Presita (Palo Blanco)",
    "gn:country_code":"MX",
    "gn:dem":2046,
    "gn:feature_class":"P",
    "gn:feature_code":"PPL",
    "gn:name":"La Presita (Palo Blanco)",
    "gn:population":110,
    "gn:timezone":"America/Mexico_City",
    "iso:country":"MX",
    "wof:name":"La Presita (Palo Blanco)",
    "wof:placetype":"locality",
    "wof:population":110
},
  "geometry": {"coordinates":[-100.32917,20.45222],"type":"Point"}
}