{
  "type": "Feature",
  "properties": {
    "gn:admin1_code":"30",
    "gn:admin2_code":"160.0",
    "gn:asciiname":"Agua Nacida",
    "gn:country_code":"MX",
    "gn:dem":30,
    "gn:feature_class":"P",
    "gn:feature_code":"PPL",
    "gn:name":"Agua Nacida",
    "gn:population":994,
    "gn:timezone":"America/Mexico_City",
    "iso:country":"MX",
    "name:spa_x_preferred":[
        "Agua Nacida"
    ],
    "wof:name":"Agua Nacida",
    "wof:placetype":"locality",
    "wof:population":994
},
  "geometry": {"coordinates":[-97.70667,20.91417],"type":"Point"}
}