{
  "type": "Feature",
  "properties": {
    "gn:admin1_code":"12",
    "gn:admin2_code":"38",
    "gn:asciiname":"Real de Guadalupe (El Mineral de Guadalupe)",
    "gn:country_code":"MX",
    "gn:dem":916,
    "gn:feature_class":"P",
    "gn:feature_code":"PPL",
    "gn:name":"Real de Guadalupe (El Mineral de Guadalupe)",
    "gn:population":38,
    "gn:timezone":"America/Mexico_City",
    "iso:country":"MX",
    "wof:name":"Real de Guadalupe (El Mineral de Guadalupe)",
    "wof:placetype":"locality",
    "wof:population":38
},
  "geometry": {"coordinates":[-101.30586,18.01105],"type":"Point"}
}