{
  "type": "Feature",
  "properties": {
    "gn:admin1_code":"5",
    "gn:admin2_code":"4",
    "gn:asciiname":"Santa Ana",
    "gn:country_code":"MX",
    "gn:dem":543,
    "gn:feature_class":"P",
    "gn:feature_code":"PPL",
    "gn:name":"Santa Ana",
    "gn:population":17,
    "gn:timezone":"America/Mexico_City",
    "iso:country":"MX",
    "wof:name":"Santa Ana",
    "wof:placetype":"locality",
    "wof:population":17
},
  "geometry": {"coordinates":[-91.61444,16.53167],"type":"Point"}
}