{
  "type": "Feature",
  "properties": {
    "gn:admin1_code":"20",
    "gn:admin2_code":"169.0",
    "gn:asciiname":"Cerro Chapultepec",
    "gn:country_code":"MX",
    "gn:dem":95,
    "gn:feature_class":"P",
    "gn:feature_code":"PPL",
    "gn:name":"Cerro Chapultepec",
    "gn:population":0,
    "gn:timezone":"America/Mexico_City",
    "iso:country":"MX",
    "name:spa_x_preferred":[
        "Cerro Chapultepec"
    ],
    "name:spa_x_variant":[
        "Chapultepec"
    ],
    "wof:name":"Cerro Chapultepec",
    "wof:placetype":"locality"
},
  "geometry": {"coordinates":[-96.62989,18.23009],"type":"Point"}
}