{
  "type": "Feature",
  "properties": {
    "gn:admin1_code":"28",
    "gn:admin2_code":"29.0",
    "gn:asciiname":"San Juanito",
    "gn:country_code":"MX",
    "gn:dem":158,
    "gn:feature_class":"P",
    "gn:feature_code":"PPL",
    "gn:name":"San Juanito",
    "gn:population":0,
    "gn:timezone":"America/Monterrey",
    "iso:country":"MX",
    "name:spa_x_preferred":[
        "San Juanito"
    ],
    "name:und_x_variant":[
        "San Juan"
    ],
    "wof:name":"San Juanito",
    "wof:placetype":"locality"
},
  "geometry": {"coordinates":[-99.21747999999999,22.79846],"type":"Point"}
}