{
  "type": "Feature",
  "properties": {
    "gn:admin1_code":"28",
    "gn:admin2_code":"32.0",
    "gn:asciiname":"Argueelles",
    "gn:country_code":"MX",
    "gn:dem":41,
    "gn:feature_class":"P",
    "gn:feature_code":"PPL",
    "gn:name":"Arg\u00fcelles",
    "gn:population":0,
    "gn:timezone":"America/Matamoros",
    "iso:country":"MX",
    "name:spa_x_preferred":[
        "Arg\u00fcelles"
    ],
    "wof:name":"Argueelles",
    "wof:placetype":"locality"
},
  "geometry": {"coordinates":[-98.47117,26.19004],"type":"Point"}
}