{
  "type": "Feature",
  "properties": {
    "gn:admin1_code":"20",
    "gn:admin2_code":"43.0",
    "gn:asciiname":"Colonia Jose Yola",
    "gn:country_code":"MX",
    "gn:dem":19,
    "gn:feature_class":"P",
    "gn:feature_code":"PPL",
    "gn:name":"Colonia Jos\u00e9 Yola",
    "gn:population":100,
    "gn:timezone":"America/Mexico_City",
    "iso:country":"MX",
    "name:und_x_variant":[
        "Colonia Jos\u00e9 Yola"
    ],
    "wof:name":"Colonia Jose Yola",
    "wof:placetype":"locality",
    "wof:population":100
},
  "geometry": {"coordinates":[-95.02722,16.41667],"type":"Point"}
}