{
  "type": "Feature",
  "properties": {
    "gn:admin1_code":"15",
    "gn:admin2_code":"60.0",
    "gn:asciiname":"Cacahuacan",
    "gn:country_code":"MX",
    "gn:dem":2745,
    "gn:feature_class":"P",
    "gn:feature_code":"PPL",
    "gn:name":"Cacahuac\u00e1n",
    "gn:population":0,
    "gn:timezone":"America/Mexico_City",
    "iso:country":"MX",
    "wof:name":"Cacahuacan",
    "wof:placetype":"locality"
},
  "geometry": {"coordinates":[-99.41667,19.63333],"type":"Point"}
}