{
  "type": "Feature",
  "properties": {
    "gn:admin1_code":"6",
    "gn:admin2_code":"27",
    "gn:asciiname":"El Arco",
    "gn:country_code":"MX",
    "gn:dem":2155,
    "gn:feature_class":"P",
    "gn:feature_code":"PPL",
    "gn:name":"El Arco",
    "gn:population":44,
    "gn:timezone":"America/Chihuahua",
    "iso:country":"MX",
    "wof:name":"El Arco",
    "wof:placetype":"locality",
    "wof:population":44
},
  "geometry": {"coordinates":[-107.10462,27.29438],"type":"Point"}
}