{
  "type": "Feature",
  "properties": {
    "gn:admin1_code":"26.0",
    "gn:admin2_code":"46.0",
    "gn:asciiname":"Rancho Alamo",
    "gn:country_code":"MX",
    "gn:dem":489,
    "gn:feature_class":"P",
    "gn:feature_code":"PPL",
    "gn:name":"Rancho \u00c1lamo",
    "gn:population":0,
    "gn:timezone":"America/Hermosillo",
    "iso:country":"MX",
    "name:spa_x_preferred":[
        "Rancho \u00c1lamo"
    ],
    "wof:name":"Rancho Alamo",
    "wof:placetype":"locality"
},
  "geometry": {"coordinates":[-111.71491,30.74754],"type":"Point"}
}