{
  "type": "Feature",
  "properties": {
    "gn:admin1_code":"6",
    "gn:admin2_code":"47.0",
    "gn:asciiname":"El Saucito",
    "gn:country_code":"MX",
    "gn:dem":968,
    "gn:feature_class":"P",
    "gn:feature_code":"PPL",
    "gn:name":"El Saucito",
    "gn:population":7,
    "gn:timezone":"America/Chihuahua",
    "iso:country":"MX",
    "wof:name":"El Saucito",
    "wof:placetype":"locality",
    "wof:population":7
},
  "geometry": {"coordinates":[-108.54218,28.24323],"type":"Point"}
}