{
  "type": "Feature",
  "properties": {
    "gn:admin1_code":"5.0",
    "gn:admin2_code":"59.0",
    "gn:asciiname":"La Peninsula",
    "gn:country_code":"MX",
    "gn:dem":584,
    "gn:feature_class":"P",
    "gn:feature_code":"PPL",
    "gn:name":"La Pen\u00ednsula",
    "gn:population":0,
    "gn:timezone":"America/Mexico_City",
    "iso:country":"MX",
    "name:spa_x_preferred":[
        "La Pen\u00ednsula"
    ],
    "wof:name":"La Peninsula",
    "wof:placetype":"locality"
},
  "geometry": {"coordinates":[-91.77048000000001,16.88853],"type":"Point"}
}