{
  "type": "Feature",
  "properties": {
    "gn:admin1_code":"10.0",
    "gn:admin2_code":"19.0",
    "gn:asciiname":"Sacamova",
    "gn:country_code":"MX",
    "gn:dem":1488,
    "gn:feature_class":"P",
    "gn:feature_code":"PPL",
    "gn:name":"Sacamova",
    "gn:population":0,
    "gn:timezone":"America/Monterrey",
    "iso:country":"MX",
    "name:spa_x_preferred":[
        "Sacamova"
    ],
    "wof:name":"Sacamova",
    "wof:placetype":"locality"
},
  "geometry": {"coordinates":[-106.05848,24.65918],"type":"Point"}
}