{
  "type": "Feature",
  "properties": {
    "gn:admin1_code":"15.0",
    "gn:admin2_code":"113.0",
    "gn:asciiname":"Rancho el Cerrillo",
    "gn:country_code":"MX",
    "gn:dem":1979,
    "gn:feature_class":"P",
    "gn:feature_code":"PPL",
    "gn:name":"Rancho el Cerrillo",
    "gn:population":0,
    "gn:timezone":"America/Mexico_City",
    "iso:country":"MX",
    "name:spa_x_preferred":[
        "Rancho el Cerrillo"
    ],
    "wof:name":"Rancho el Cerrillo",
    "wof:placetype":"locality"
},
  "geometry": {"coordinates":[-99.65213,18.91204],"type":"Point"}
}