{
  "type": "Feature",
  "properties": {
    "gn:admin1_code":"19",
    "gn:admin2_code":"7.0",
    "gn:asciiname":"La Muralla",
    "gn:country_code":"MX",
    "gn:dem":2377,
    "gn:feature_class":"P",
    "gn:feature_code":"PPL",
    "gn:name":"La Muralla",
    "gn:population":7,
    "gn:timezone":"America/Monterrey",
    "iso:country":"MX",
    "wof:name":"La Muralla",
    "wof:placetype":"locality",
    "wof:population":7
},
  "geometry": {"coordinates":[-99.87831,24.48174],"type":"Point"}
}