{
  "type": "Feature",
  "properties": {
    "gn:gn_country":"MX",
    "gn:gn_fcode":"PPL",
    "gn:gn_pop":0,
    "gn:population":1792,
    "iso:country":"MX",
    "name:ben_x_preferred":[
        "\u09b2\u09cb \u09a6\u09c7 \u09ae\u09be\u09b0\u09cd\u0995\u09cb\u09b8"
    ],
    "name:eng_x_preferred":[
        "Lo de Marcos"
    ],
    "name:nld_x_preferred":[
        "Lo de Marcos"
    ],
    "name:srp_x_preferred":[
        "\u041b\u043e \u0434\u0435 \u041c\u0430\u0440\u043a\u043e\u0441"
    ],
    "name:swe_x_preferred":[
        "Lo de Marcos"
    ],
    "qs_pg:aaroncc":"MX",
    "qs_pg:gn_country":"MX",
    "qs_pg:gn_fcode":"PPL",
    "qs_pg:gn_pop":0,
    "qs_pg:name":"Lo de Marcos",
    "qs_pg:name_adm0":"M\u00e9xico",
    "qs_pg:name_adm1":"Nayarit",
    "qs_pg:photos":279,
    "qs_pg:photos_1k":57,
    "qs_pg:photos_9k":1,
    "qs_pg:photos_9r":4,
    "qs_pg:photos_all":279,
    "qs_pg:photos_sr":5,
    "qs_pg:pop_sr":0,
    "qs_pg:qs_pg_placetype":"locality",
    "qs_pg:qs_pg_placetype_gp":"Town",
    "qs_pg:woe_adm0":23424900,
    "woe:adm0_id":23424900,
    "woe:name_adm0":"M\u00e9xico",
    "woe:name_adm1":"Nayarit",
    "woe:placetype":"Town",
    "wof:name":"Lo de Marcos",
    "wof:placetype":"locality",
    "wof:population":1792
},
  "geometry": {"coordinates":[-105.34999999999999,20.95],"type":"Point"}
}