{
  "type": "Feature",
  "properties": {
    "gn:admin1_code":"15.0",
    "gn:admin2_code":"32.0",
    "gn:asciiname":"San Martin Obispo",
    "gn:country_code":"MX",
    "gn:dem":2501,
    "gn:feature_class":"P",
    "gn:feature_code":"PPL",
    "gn:name":"San Mart\u00edn Obispo",
    "gn:population":0,
    "gn:timezone":"America/Mexico_City",
    "iso:country":"MX",
    "name:spa_x_preferred":[
        "San Mart\u00edn Obispo"
    ],
    "name:und_x_variant":[
        "San Mar\u00edn Obispo"
    ],
    "wof:name":"San Martin Obispo",
    "wof:placetype":"locality"
},
  "geometry": {"coordinates":[-100.074,19.32018],"type":"Point"}
}