{
  "type": "Feature",
  "properties": {
    "gn:admin1_code":"6",
    "gn:admin2_code":"8.0",
    "gn:asciiname":"Baquiriachi",
    "gn:country_code":"MX",
    "gn:dem":2349,
    "gn:feature_class":"P",
    "gn:feature_code":"PPL",
    "gn:name":"Baquiriachi",
    "gn:population":0,
    "gn:timezone":"America/Chihuahua",
    "iso:country":"MX",
    "name:spa_x_preferred":[
        "Baquiriachi"
    ],
    "name:spa_x_variant":[
        "Baquireachi"
    ],
    "wof:name":"Baquiriachi",
    "wof:placetype":"locality"
},
  "geometry": {"coordinates":[-107.59573,26.9042],"type":"Point"}
}