{
  "type": "Feature",
  "properties": {
    "gn:admin1_code":"24",
    "gn:admin2_code":"49.0",
    "gn:asciiname":"El Carmen (El Ranchillo)",
    "gn:country_code":"MX",
    "gn:dem":2211,
    "gn:feature_class":"P",
    "gn:feature_code":"PPL",
    "gn:name":"El Carmen (El Ranchillo)",
    "gn:population":9,
    "gn:timezone":"America/Mexico_City",
    "iso:country":"MX",
    "wof:name":"El Carmen (El Ranchillo)",
    "wof:placetype":"locality",
    "wof:population":9
},
  "geometry": {"coordinates":[-101.85194,22.95167],"type":"Point"}
}