{
  "type": "Feature",
  "properties": {
    "gn:admin1_code":"5.0",
    "gn:admin2_code":"96.0",
    "gn:asciiname":"Jol Sivaquil",
    "gn:country_code":"MX",
    "gn:dem":1045,
    "gn:feature_class":"P",
    "gn:feature_code":"PPL",
    "gn:name":"Jol Sivaquil",
    "gn:population":0,
    "gn:timezone":"America/Mexico_City",
    "iso:country":"MX",
    "name:spa_x_preferred":[
        "Jol Sivaquil"
    ],
    "wof:name":"Jol Sivaquil",
    "wof:placetype":"locality"
},
  "geometry": {"coordinates":[-92.48275,17.26045],"type":"Point"}
}