{
  "type": "Feature",
  "properties": {
    "gn:admin1_code":"23",
    "gn:asciiname":"Caobas",
    "gn:country_code":"MX",
    "gn:dem":74,
    "gn:feature_class":"P",
    "gn:feature_code":"PPL",
    "gn:name":"Caobas",
    "gn:population":0,
    "gn:timezone":"America/Cancun",
    "iso:country":"MX",
    "name:spa_x_preferred":[
        "Caobas"
    ],
    "wof:name":"Caobas",
    "wof:placetype":"locality"
},
  "geometry": {"coordinates":[-89.14700999999999,19.79139],"type":"Point"}
}