{
  "type": "Feature",
  "properties": {
    "gn:admin1_code":"27.0",
    "gn:admin2_code":"8.0",
    "gn:asciiname":"Tres Bocas Tercera Seccion",
    "gn:country_code":"MX",
    "gn:dem":15,
    "gn:feature_class":"P",
    "gn:feature_code":"PPL",
    "gn:name":"Tres Bocas Tercera Secci\u00f3n",
    "gn:population":0,
    "gn:timezone":"America/Mexico_City",
    "iso:country":"MX",
    "name:spa_x_preferred":[
        "Tres Bocas Tercera Secci\u00f3n"
    ],
    "wof:name":"Tres Bocas Tercera Seccion",
    "wof:placetype":"locality"
},
  "geometry": {"coordinates":[-93.84916,17.91349],"type":"Point"}
}