{
  "type": "Feature",
  "properties": {
    "gn:gn_country":"MX",
    "gn:gn_fcode":"PPL",
    "gn:gn_pop":3039,
    "gn:population":3039,
    "iso:country":"MX",
    "name:cat_x_preferred":[
        "Tancanhuitz"
    ],
    "name:eng_x_preferred":[
        "Tancanhuitz de Santos"
    ],
    "name:epo_x_preferred":[
        "Tancanhuitz"
    ],
    "name:eus_x_preferred":[
        "Tancanhuitz"
    ],
    "name:fur_x_preferred":[
        "Tancanhuitz"
    ],
    "name:ita_x_preferred":[
        "Tancanhuitz"
    ],
    "name:nld_x_preferred":[
        "Tancanhuitz de Santos"
    ],
    "name:por_x_preferred":[
        "Tancanhuitz de Santos"
    ],
    "name:spa_x_preferred":[
        "Tancanhuitz de Santos"
    ],
    "name:srp_x_preferred":[
        "\u041e\u043f\u0448\u0442\u0438\u043d\u0430 \u0422\u0430\u043d\u043a\u0430\u043d\u0445\u0443\u0438\u0446"
    ],
    "name:swe_x_preferred":[
        "Tancanhuitz de Santos"
    ],
    "name:unk_x_variant":[
        "Ciudad Santos"
    ],
    "name:vec_x_preferred":[
        "Tancanhuitz"
    ],
    "name:vie_x_preferred":[
        "Tancanhuitz de Santos"
    ],
    "qs_pg:aaroncc":"MX",
    "qs_pg:gn_country":"MX",
    "qs_pg:gn_fcode":"PPL",
    "qs_pg:gn_pop":3039,
    "qs_pg:name":"General Pedro Antonio Santos",
    "qs_pg:photos_9r":0,
    "qs_pg:photos_sr":0,
    "qs_pg:pop_sr":4,
    "qs_pg:qs_pg_placetype":"locality",
    "wof:name":"General Pedro Antonio Santos",
    "wof:placetype":"locality",
    "wof:population":3039
},
  "geometry": {"coordinates":[-98.9674,21.59799],"type":"Point"}
}