{
  "type": "Feature",
  "properties": {
    "gn:admin1_code":"5",
    "gn:admin2_code":"18",
    "gn:asciiname":"Jerico",
    "gn:country_code":"MX",
    "gn:dem":1259,
    "gn:feature_class":"P",
    "gn:feature_code":"PPL",
    "gn:name":"Jeric\u00f3",
    "gn:population":14,
    "gn:timezone":"America/Mexico_City",
    "iso:country":"MX",
    "name:und_x_variant":[
        "Jeric\u00f3"
    ],
    "wof:name":"Jerico",
    "wof:placetype":"locality",
    "wof:population":14
},
  "geometry": {"coordinates":[-93.05500000000001,17.09832999999999],"type":"Point"}
}