{
  "type": "Feature",
  "properties": {
    "gn:admin1_code":"22",
    "gn:admin2_code":"4.0",
    "gn:asciiname":"Los Palmitos",
    "gn:country_code":"MX",
    "gn:dem":1994,
    "gn:feature_class":"P",
    "gn:feature_code":"PPL",
    "gn:name":"Los Palmitos",
    "gn:population":59,
    "gn:timezone":"America/Mexico_City",
    "iso:country":"MX",
    "name:ceb_x_preferred":[
        "Los Palmitos"
    ],
    "name:diq_x_preferred":[
        "Los Palmitos"
    ],
    "name:fra_x_preferred":[
        "Los Palmitos"
    ],
    "name:ita_x_preferred":[
        "Los Palmitos"
    ],
    "name:kat_x_preferred":[
        "\u10da\u10dd\u10e1-\u10de\u10d0\u10da\u10db\u10d8\u10e2\u10dd\u10e1\u10d8"
    ],
    "name:msa_x_preferred":[
        "Los Palmitos"
    ],
    "name:nld_x_preferred":[
        "Los Palmitos"
    ],
    "name:spa_x_preferred":[
        "Los Palmitos"
    ],
    "name:swe_x_preferred":[
        "Los Palmitos"
    ],
    "name:vie_x_preferred":[
        "Los Palmitos"
    ],
    "name:war_x_preferred":[
        "Los Palmitos"
    ],
    "name:zho_x_preferred":[
        "\u6d1b\u65af\u5e15\u723e\u7c73\u6258\u65af"
    ],
    "wof:name":"Los Palmitos",
    "wof:placetype":"locality",
    "wof:population":59
},
  "geometry": {"coordinates":[-99.50888999999999,20.92722],"type":"Point"}
}