{
  "type": "Feature",
  "properties": {
    "gn:admin1_code":"20",
    "gn:admin2_code":"466.0",
    "gn:asciiname":"Macahuite Nuevo",
    "gn:country_code":"MX",
    "gn:dem":669,
    "gn:feature_class":"P",
    "gn:feature_code":"PPL",
    "gn:name":"Macahuite Nuevo",
    "gn:population":53,
    "gn:timezone":"America/Mexico_City",
    "iso:country":"MX",
    "wof:name":"Macahuite Nuevo",
    "wof:placetype":"locality",
    "wof:population":53
},
  "geometry": {"coordinates":[-97.70833,16.6075],"type":"Point"}
}