{
  "type": "Feature",
  "properties": {
    "gn:admin1_code":"26",
    "gn:admin2_code":"66.0",
    "gn:asciiname":"Santa Patricia",
    "gn:country_code":"MX",
    "gn:dem":390,
    "gn:feature_class":"P",
    "gn:feature_code":"PPL",
    "gn:name":"Santa Patricia",
    "gn:population":0,
    "gn:timezone":"America/Hermosillo",
    "iso:country":"MX",
    "name:spa_x_preferred":[
        "Santa Patricia"
    ],
    "wof:name":"Santa Patricia",
    "wof:placetype":"locality"
},
  "geometry": {"coordinates":[-110.46222,29.15444],"type":"Point"}
}