{
  "type": "Feature",
  "properties": {
    "gn:admin1_code":"15",
    "gn:admin2_code":"1.0",
    "gn:asciiname":"Pathe",
    "gn:country_code":"MX",
    "gn:dem":2542,
    "gn:feature_class":"P",
    "gn:feature_code":"PPL",
    "gn:name":"Path\u00e9",
    "gn:population":0,
    "gn:timezone":"America/Mexico_City",
    "iso:country":"MX",
    "name:spa_x_preferred":[
        "Path\u00e9"
    ],
    "name:spa_x_variant":[
        "Pathe"
    ],
    "wof:name":"Pathe",
    "wof:placetype":"locality"
},
  "geometry": {"coordinates":[-99.83956999999999,19.92695],"type":"Point"}
}