{
  "type": "Feature",
  "properties": {
    "gn:admin1_code":"6.0",
    "gn:asciiname":"El Molineno",
    "gn:country_code":"MX",
    "gn:dem":1623,
    "gn:feature_class":"P",
    "gn:feature_code":"PPL",
    "gn:name":"El Moline\u00f1o",
    "gn:population":0,
    "gn:timezone":"America/Chihuahua",
    "iso:country":"MX",
    "name:spa_x_preferred":[
        "El Moline\u00f1o"
    ],
    "wof:name":"El Molineno",
    "wof:placetype":"locality"
},
  "geometry": {"coordinates":[-106.35928,26.92826],"type":"Point"}
}