{
  "type": "Feature",
  "properties": {
    "gn:admin1_code":"30",
    "gn:admin2_code":"76.0",
    "gn:asciiname":"Tonalixco",
    "gn:country_code":"MX",
    "gn:dem":695,
    "gn:feature_class":"P",
    "gn:feature_code":"PPL",
    "gn:name":"Tonalixco",
    "gn:population":70,
    "gn:timezone":"America/Mexico_City",
    "iso:country":"MX",
    "wof:name":"Tonalixco",
    "wof:placetype":"locality",
    "wof:population":70
},
  "geometry": {"coordinates":[-98.455,20.72306],"type":"Point"}
}