{
  "type": "Feature",
  "properties": {
    "gn:admin1_code":"20",
    "gn:admin2_code":"159.0",
    "gn:asciiname":"San Cristobal Honduras",
    "gn:country_code":"MX",
    "gn:dem":1090,
    "gn:feature_class":"P",
    "gn:feature_code":"PPL",
    "gn:name":"San Crist\u00f3bal Honduras",
    "gn:population":1086,
    "gn:timezone":"America/Mexico_City",
    "iso:country":"MX",
    "name:spa_x_preferred":[
        "San Crist\u00f3bal Honduras"
    ],
    "wof:name":"San Cristobal Honduras",
    "wof:placetype":"locality",
    "wof:population":1086
},
  "geometry": {"coordinates":[-97.04111,16.32528],"type":"Point"}
}