{
  "type": "Feature",
  "properties": {
    "gn:admin1_code":"20",
    "gn:admin2_code":"134.0",
    "gn:asciiname":"Desviacion Cerro Quemado",
    "gn:country_code":"MX",
    "gn:dem":127,
    "gn:feature_class":"P",
    "gn:feature_code":"PPL",
    "gn:name":"Desviaci\u00f3n Cerro Quemado",
    "gn:population":69,
    "gn:timezone":"America/Mexico_City",
    "iso:country":"MX",
    "name:und_x_variant":[
        "Desviaci\u00f3n Cerro Quemado"
    ],
    "wof:name":"Desviacion Cerro Quemado",
    "wof:placetype":"locality",
    "wof:population":69
},
  "geometry": {"coordinates":[-96.49417,18.11056],"type":"Point"}
}