{
  "type": "Feature",
  "properties": {
    "gn:admin1_code":"32.0",
    "gn:admin2_code":"40.0",
    "gn:asciiname":"La Pipianera",
    "gn:country_code":"MX",
    "gn:dem":2127,
    "gn:feature_class":"P",
    "gn:feature_code":"PPL",
    "gn:name":"La Pipianera",
    "gn:population":0,
    "gn:timezone":"America/Mexico_City",
    "iso:country":"MX",
    "name:spa_x_preferred":[
        "La Pipianera"
    ],
    "wof:name":"La Pipianera",
    "wof:placetype":"locality"
},
  "geometry": {"coordinates":[-103.30557,23.60439],"type":"Point"}
}