{
  "type": "Feature",
  "properties": {
    "gn:admin1_code":"16.0",
    "gn:admin2_code":"37.0",
    "gn:asciiname":"Tacupillo",
    "gn:country_code":"MX",
    "gn:dem":2068,
    "gn:feature_class":"P",
    "gn:feature_code":"PPL",
    "gn:name":"Tacupillo",
    "gn:population":0,
    "gn:timezone":"America/Mexico_City",
    "iso:country":"MX",
    "name:spa_x_preferred":[
        "Tacupillo"
    ],
    "name:spa_x_variant":[
        "Tecupilla"
    ],
    "wof:name":"Tacupillo",
    "wof:placetype":"locality"
},
  "geometry": {"coordinates":[-101.49267999999999,19.82679],"type":"Point"}
}