{
  "type": "Feature",
  "properties": {
    "gn:admin1_code":"6",
    "gn:admin2_code":"48.0",
    "gn:asciiname":"Casavantes",
    "gn:country_code":"MX",
    "gn:dem":1905,
    "gn:feature_class":"P",
    "gn:feature_code":"PPL",
    "gn:name":"Casavantes",
    "gn:population":0,
    "gn:timezone":"America/Chihuahua",
    "iso:country":"MX",
    "name:spa_x_preferred":[
        "Casavantes"
    ],
    "name:und_x_variant":[
        "Casa Avantes"
    ],
    "wof:name":"Casavantes",
    "wof:placetype":"locality"
},
  "geometry": {"coordinates":[-107.33622,29.19562],"type":"Point"}
}