{
  "type": "Feature",
  "properties": {
    "gn:admin1_code":"22",
    "gn:asciiname":"Agua del Cedro",
    "gn:country_code":"MX",
    "gn:dem":1644,
    "gn:feature_class":"P",
    "gn:feature_code":"PPL",
    "gn:name":"Agua del Cedro",
    "gn:population":0,
    "gn:timezone":"America/Mexico_City",
    "iso:country":"MX",
    "name:spa_x_preferred":[
        "Agua del Cedro"
    ],
    "wof:name":"Agua del Cedro",
    "wof:placetype":"locality"
},
  "geometry": {"coordinates":[-99.11069999999999,21.32384],"type":"Point"}
}