{
  "type": "Feature",
  "properties": {
    "gn:admin1_code":"7",
    "gn:admin2_code":"33.0",
    "gn:asciiname":"San Esteban",
    "gn:country_code":"MX",
    "gn:dem":1102,
    "gn:feature_class":"P",
    "gn:feature_code":"PPL",
    "gn:name":"San Esteban",
    "gn:population":0,
    "gn:timezone":"America/Monterrey",
    "iso:country":"MX",
    "wof:name":"San Esteban",
    "wof:placetype":"locality"
},
  "geometry": {"coordinates":[-103.01667,25.71667],"type":"Point"}
}