{
  "type": "Feature",
  "properties": {
    "gn:admin1_code":"20",
    "gn:admin2_code":"66.0",
    "gn:asciiname":"Las Viboras",
    "gn:cc2":"MX",
    "gn:country_code":"MX",
    "gn:dem":41,
    "gn:feature_class":"P",
    "gn:feature_code":"PPL",
    "gn:name":"Las V\u00edboras",
    "gn:population":0,
    "gn:timezone":"America/Mexico_City",
    "iso:country":"MX",
    "name:und_x_variant":[
        "Viboras",
        "Las V\u00edboras"
    ],
    "wof:name":"Las Viboras",
    "wof:placetype":"locality"
},
  "geometry": {"coordinates":[-94.63333,16.51667],"type":"Point"}
}