{
  "type": "Feature",
  "properties": {
    "gn:admin1_code":"10",
    "gn:admin2_code":"19.0",
    "gn:asciiname":"Manzanillas",
    "gn:country_code":"MX",
    "gn:dem":2033,
    "gn:feature_class":"P",
    "gn:feature_code":"PPL",
    "gn:name":"Manzanillas",
    "gn:population":0,
    "gn:timezone":"America/Monterrey",
    "iso:country":"MX",
    "name:spa_x_preferred":[
        "Manzanillas"
    ],
    "wof:name":"Manzanillas",
    "wof:placetype":"locality"
},
  "geometry": {"coordinates":[-106.01774,24.61915],"type":"Point"}
}