{
  "type": "Feature",
  "properties": {
    "gn:admin1_code":"28",
    "gn:admin2_code":"30.0",
    "gn:asciiname":"Pither Klassen Peters",
    "gn:country_code":"MX",
    "gn:dem":147,
    "gn:feature_class":"P",
    "gn:feature_code":"PPL",
    "gn:name":"Pither Klassen Peters",
    "gn:population":7,
    "gn:timezone":"America/Monterrey",
    "iso:country":"MX",
    "wof:name":"Pither Klassen Peters",
    "wof:placetype":"locality",
    "wof:population":7
},
  "geometry": {"coordinates":[-98.88333,24.06778],"type":"Point"}
}