{
  "type": "Feature",
  "properties": {
    "gn:admin1_code":"14",
    "gn:admin2_code":"58",
    "gn:asciiname":"El Nogal",
    "gn:country_code":"MX",
    "gn:dem":875,
    "gn:feature_class":"P",
    "gn:feature_code":"PPL",
    "gn:name":"El Nogal",
    "gn:population":10,
    "gn:timezone":"America/Mexico_City",
    "iso:country":"MX",
    "wof:name":"El Nogal",
    "wof:placetype":"locality",
    "wof:population":10
},
  "geometry": {"coordinates":[-105.09917,20.54556],"type":"Point"}
}