{
  "type": "Feature",
  "properties": {
    "gn:admin1_code":"14.0",
    "gn:admin2_code":"92.0",
    "gn:asciiname":"Gavilan",
    "gn:country_code":"MX",
    "gn:dem":1365,
    "gn:feature_class":"P",
    "gn:feature_code":"PPL",
    "gn:name":"Gavil\u00e1n",
    "gn:population":0,
    "gn:timezone":"America/Mexico_City",
    "iso:country":"MX",
    "name:und_x_variant":[
        "Las Colonias del Gavil\u00e1n",
        "Gavil\u00e1n"
    ],
    "wof:name":"Gavilan",
    "wof:placetype":"locality"
},
  "geometry": {"coordinates":[-103.39202,20.10199],"type":"Point"}
}