{
  "type": "Feature",
  "properties": {
    "gn:admin1_code":"30.0",
    "gn:admin2_code":"153.0",
    "gn:asciiname":"Congregacion Kilometro Cuarenta y Tres",
    "gn:country_code":"MX",
    "gn:dem":251,
    "gn:feature_class":"P",
    "gn:feature_code":"PPL",
    "gn:name":"Congregaci\u00f3n Kil\u00f3metro Cuarenta y Tres",
    "gn:population":0,
    "gn:timezone":"America/Mexico_City",
    "iso:country":"MX",
    "name:spa_x_preferred":[
        "Congregaci\u00f3n Kil\u00f3metro Cuarenta y Tres"
    ],
    "wof:name":"Congregacion Kilometro Cuarenta y Tres",
    "wof:placetype":"locality"
},
  "geometry": {"coordinates":[-97.71613000000001,21.21784],"type":"Point"}
}