{
  "type": "Feature",
  "properties": {
    "iso:country":"MX",
    "name:spa_x_preferred":[
        "Lomas Verdes"
    ],
    "name:spa_x_variant":[
        "Loma Verde"
    ],
    "name:unk_x_variant":[
        "Lomas Verdes"
    ],
    "qs:gn_adm0_cc":"MX",
    "qs:gn_fcode":"PPL",
    "qs:gn_local":3522790,
    "qs:gn_nam_loc":"Naucalpan de Juarez, Naucalpan de Ju\u00e1rez, Mexico, MX",
    "qs:gn_namadm1":"15",
    "qs:gn_name":"Loma Verde",
    "qs:local_max":835,
    "qs:local_sum":2795,
    "qs:localhoods":16,
    "qs:name":"Lomas Verdes",
    "qs:name_adm0":"M\u00e9xico",
    "qs:name_adm1":"Mexico",
    "qs:name_adm2":"Naucalpan de Juarez",
    "qs:name_local":"Naucalpan de Ju\u00e1rez",
    "qs:photo_max":1,
    "qs:photo_sum":1,
    "qs:placetype":"Suburb",
    "qs:quad_count":1,
    "qs:woe_adm0":23424900,
    "qs:woe_adm1":2346278,
    "qs:woe_adm2":12600377,
    "qs:woe_lau":0,
    "qs:woe_local":134395,
    "qs:woe_ver":"7.10.0",
    "wof:lang":[
        "spa"
    ],
    "wof:name":"Lomas Verdes",
    "wof:placetype":"neighbourhood"
},
  "geometry": {"coordinates":[-99.27520800000001,19.510609],"type":"Point"}
}