{
  "type": "Feature",
  "properties": {
    "gn:admin1_code":"15",
    "gn:admin2_code":"42.0",
    "gn:asciiname":"Ejido de la Concepcion de los Banos Primero",
    "gn:country_code":"MX",
    "gn:dem":2554,
    "gn:feature_class":"P",
    "gn:feature_code":"PPL",
    "gn:name":"Ejido de la Concepci\u00f3n de los Ba\u00f1os Primero",
    "gn:population":799,
    "gn:timezone":"America/Mexico_City",
    "iso:country":"MX",
    "name:und_x_variant":[
        "Ejido de la Concepci\u00f3n de los Ba\u00f1os Primero"
    ],
    "wof:name":"Ejido de la Concepcion de los Banos Primero",
    "wof:placetype":"locality",
    "wof:population":799
},
  "geometry": {"coordinates":[-99.85863000000001,19.69591],"type":"Point"}
}