{
  "type": "Feature",
  "properties": {
    "gn:admin1_code":"2",
    "gn:admin2_code":"5.0",
    "gn:asciiname":"Rancho Lomas Pelonas",
    "gn:country_code":"MX",
    "gn:dem":44,
    "gn:feature_class":"P",
    "gn:feature_code":"PPL",
    "gn:name":"Rancho Lomas Pelonas",
    "gn:population":8,
    "gn:timezone":"America/Tijuana",
    "iso:country":"MX",
    "wof:name":"Rancho Lomas Pelonas",
    "wof:placetype":"locality",
    "wof:population":8
},
  "geometry": {"coordinates":[-116.86056000000001,32.10278],"type":"Point"}
}