{
  "type": "Feature",
  "properties": {
    "gn:admin1_code":"30.0",
    "gn:admin2_code":"114.0",
    "gn:asciiname":"Temazcales",
    "gn:country_code":"MX",
    "gn:dem":85,
    "gn:feature_class":"P",
    "gn:feature_code":"PPL",
    "gn:name":"Temazcales",
    "gn:population":41,
    "gn:timezone":"America/Mexico_City",
    "iso:country":"MX",
    "name:spa_x_preferred":[
        "Temazcales"
    ],
    "wof:name":"Temazcales",
    "wof:placetype":"locality",
    "wof:population":41
},
  "geometry": {"coordinates":[-96.75667,20.05611],"type":"Point"}
}