{
  "type": "Feature",
  "properties": {
    "gn:admin1_code":"6",
    "gn:admin2_code":"51.0",
    "gn:asciiname":"Rosahueachic",
    "gn:country_code":"MX",
    "gn:dem":2511,
    "gn:feature_class":"P",
    "gn:feature_code":"PPL",
    "gn:name":"Rosah\u00fcachic",
    "gn:population":0,
    "gn:timezone":"America/Chihuahua",
    "iso:country":"MX",
    "name:spa_x_preferred":[
        "Rosah\u00fcachic"
    ],
    "wof:name":"Rosahueachic",
    "wof:placetype":"locality"
},
  "geometry": {"coordinates":[-108.13567,28.25099],"type":"Point"}
}