{
  "type": "Feature",
  "properties": {
    "gn:admin1_code":"15",
    "gn:admin2_code":"99.0",
    "gn:asciiname":"San Pablo Ixayoc",
    "gn:country_code":"MX",
    "gn:dem":2566,
    "gn:feature_class":"P",
    "gn:feature_code":"PPL",
    "gn:name":"San Pablo Ixayoc",
    "gn:population":0,
    "gn:timezone":"America/Mexico_City",
    "iso:country":"MX",
    "name:und_x_variant":[
        "Ixayoc",
        "San Pablo Izayoc",
        "San Pablo",
        "San Pablo Ixayoc"
    ],
    "wof:name":"San Pablo Ixayoc",
    "wof:placetype":"locality"
},
  "geometry": {"coordinates":[-98.79522,19.47317],"type":"Point"}
}