{
  "type": "Feature",
  "properties": {
    "gn:admin1_code":"5.0",
    "gn:asciiname":"Santa Teresa Uno",
    "gn:country_code":"MX",
    "gn:dem":11,
    "gn:feature_class":"P",
    "gn:feature_code":"PPL",
    "gn:name":"Santa Teresa Uno",
    "gn:population":0,
    "gn:timezone":"America/Mexico_City",
    "iso:country":"MX",
    "name:spa_x_preferred":[
        "Santa Teresa Uno"
    ],
    "wof:name":"Santa Teresa Uno",
    "wof:placetype":"locality"
},
  "geometry": {"coordinates":[-93.35026000000001,15.67216],"type":"Point"}
}