{
  "type": "Feature",
  "properties": {
    "gn:admin1_code":"10.0",
    "gn:admin2_code":"26.0",
    "gn:asciiname":"El Remudadero",
    "gn:country_code":"MX",
    "gn:dem":2571,
    "gn:feature_class":"P",
    "gn:feature_code":"PPL",
    "gn:name":"El Remudadero",
    "gn:population":0,
    "gn:timezone":"America/Monterrey",
    "iso:country":"MX",
    "name:spa_x_preferred":[
        "El Remudadero"
    ],
    "name:spa_x_variant":[
        "Remudadero"
    ],
    "wof:name":"El Remudadero",
    "wof:placetype":"locality"
},
  "geometry": {"coordinates":[-106.0008,24.40097],"type":"Point"}
}