{
  "type": "Feature",
  "properties": {
    "gn:admin1_code":"30",
    "gn:admin2_code":"151.0",
    "gn:asciiname":"Ajoquentla",
    "gn:country_code":"MX",
    "gn:dem":61,
    "gn:feature_class":"P",
    "gn:feature_code":"PPL",
    "gn:name":"Ajoquentla",
    "gn:population":0,
    "gn:timezone":"America/Mexico_City",
    "iso:country":"MX",
    "name:spa_x_preferred":[
        "Ajoquentla"
    ],
    "wof:name":"Ajoquentla",
    "wof:placetype":"locality",
    "wof:population":70
},
  "geometry": {"coordinates":[-97.57023,21.19735],"type":"Point"}
}