{
  "type": "Feature",
  "properties": {
    "gn:admin1_code":"25",
    "gn:admin2_code":"1.0",
    "gn:asciiname":"La Cuba",
    "gn:country_code":"MX",
    "gn:dem":8,
    "gn:feature_class":"P",
    "gn:feature_code":"PPL",
    "gn:name":"La Cuba",
    "gn:population":0,
    "gn:timezone":"America/Mazatlan",
    "iso:country":"MX",
    "name:arg_x_preferred":[
        "La Cuba"
    ],
    "name:cat_x_preferred":[
        "La Cuba"
    ],
    "name:deu_x_preferred":[
        "La Cuba"
    ],
    "name:eus_x_preferred":[
        "La Cuba"
    ],
    "name:fas_x_preferred":[
        "\u0644\u0627 \u06a9\u0648\u0628\u0627"
    ],
    "name:fra_x_preferred":[
        "La Cuba"
    ],
    "name:hun_x_preferred":[
        "La Cuba"
    ],
    "name:ita_x_preferred":[
        "La Cuba"
    ],
    "name:kaz_x_preferred":[
        "\u041b\u0430-\u041a\u0443\u0431\u0430"
    ],
    "name:msa_x_preferred":[
        "La Cuba"
    ],
    "name:nld_x_preferred":[
        "La Cuba"
    ],
    "name:oci_x_preferred":[
        "La Cuba"
    ],
    "name:pol_x_preferred":[
        "La Cuba"
    ],
    "name:por_x_preferred":[
        "La Cuba"
    ],
    "name:rus_x_preferred":[
        "\u041b\u0430-\u041a\u0443\u0431\u0430"
    ],
    "name:spa_x_preferred":[
        "La Cuba"
    ],
    "name:ukr_x_preferred":[
        "\u041b\u0430-\u041a\u0443\u0431\u0430"
    ],
    "name:urd_x_preferred":[
        "\u0644\u0627 \u06a9\u0648\u0628\u0627"
    ],
    "name:uzb_x_preferred":[
        "La Cuba"
    ],
    "name:vie_x_preferred":[
        "La Cuba"
    ],
    "name:war_x_preferred":[
        "La Cuba"
    ],
    "name:zho_x_preferred":[
        "\u62c9\u5e93\u74e6"
    ],
    "wof:name":"La Cuba",
    "wof:placetype":"locality"
},
  "geometry": {"coordinates":[-109.34497,26.02565],"type":"Point"}
}