{
  "type": "Feature",
  "properties": {
    "gn:admin1_code":"11",
    "gn:admin2_code":"25.0",
    "gn:asciiname":"Fraccionamiento las Arcinas",
    "gn:country_code":"MX",
    "gn:dem":1760,
    "gn:feature_class":"P",
    "gn:feature_code":"PPL",
    "gn:name":"Fraccionamiento las Arcinas",
    "gn:population":107,
    "gn:timezone":"America/Mexico_City",
    "iso:country":"MX",
    "wof:name":"Fraccionamiento las Arcinas",
    "wof:placetype":"locality",
    "wof:population":107
},
  "geometry": {"coordinates":[-101.89055999999999,21.01722],"type":"Point"}
}