{
  "type": "Feature",
  "properties": {
    "gn:admin1_code":"10",
    "gn:admin2_code":"24.0",
    "gn:asciiname":"El Canon",
    "gn:country_code":"MX",
    "gn:dem":1616,
    "gn:feature_class":"P",
    "gn:feature_code":"PPL",
    "gn:name":"El Ca\u00f1\u00f3n",
    "gn:population":0,
    "gn:timezone":"America/Monterrey",
    "iso:country":"MX",
    "name:spa_x_preferred":[
        "El Ca\u00f1\u00f3n"
    ],
    "wof:name":"El Canon",
    "wof:placetype":"locality"
},
  "geometry": {"coordinates":[-104.61002999999999,25.13655],"type":"Point"}
}