{
  "type": "Feature",
  "properties": {
    "gn:admin1_code":"14.0",
    "gn:admin2_code":"54.0",
    "gn:asciiname":"El Arroyo la Estancia Los Ibarra",
    "gn:country_code":"MX",
    "gn:dem":889,
    "gn:feature_class":"P",
    "gn:feature_code":"PPL",
    "gn:name":"El Arroyo la Estancia Los Ibarra",
    "gn:population":0,
    "gn:timezone":"America/Mexico_City",
    "iso:country":"MX",
    "name:spa_x_preferred":[
        "El Arroyo la Estancia Los Ibarra"
    ],
    "wof:name":"El Arroyo la Estancia Los Ibarra",
    "wof:placetype":"locality"
},
  "geometry": {"coordinates":[-104.14936,19.83062],"type":"Point"}
}