{
  "type": "Feature",
  "properties": {
    "gn:admin1_code":"20",
    "gn:admin2_code":"242.0",
    "gn:asciiname":"Cerro Hidalgo",
    "gn:country_code":"MX",
    "gn:dem":2550,
    "gn:feature_class":"P",
    "gn:feature_code":"PPL",
    "gn:name":"Cerro Hidalgo",
    "gn:population":212,
    "gn:timezone":"America/Mexico_City",
    "iso:country":"MX",
    "wof:name":"Cerro Hidalgo",
    "wof:placetype":"locality",
    "wof:population":212
},
  "geometry": {"coordinates":[-98.30611,17.27889],"type":"Point"}
}