{
  "type": "Feature",
  "properties": {
    "gn:admin1_code":"32",
    "gn:admin2_code":"55.0",
    "gn:asciiname":"Pasillas",
    "gn:country_code":"MX",
    "gn:dem":1860,
    "gn:feature_class":"P",
    "gn:feature_code":"PPL",
    "gn:name":"Pasillas",
    "gn:population":0,
    "gn:timezone":"America/Mexico_City",
    "iso:country":"MX",
    "wof:name":"Pasillas",
    "wof:placetype":"locality"
},
  "geometry": {"coordinates":[-102.78528,22.095],"type":"Point"}
}