{
  "type": "Feature",
  "properties": {
    "gn:admin1_code":"26",
    "gn:admin2_code":"38.0",
    "gn:asciiname":"La Cieneguita",
    "gn:country_code":"MX",
    "gn:dem":1068,
    "gn:feature_class":"P",
    "gn:feature_code":"PPL",
    "gn:name":"La Cieneguita",
    "gn:population":0,
    "gn:timezone":"America/Hermosillo",
    "iso:country":"MX",
    "name:spa_x_preferred":[
        "La Cieneguita"
    ],
    "wof:name":"La Cieneguita",
    "wof:placetype":"locality"
},
  "geometry": {"coordinates":[-109.74889,29.69833],"type":"Point"}
}