{
  "type": "Feature",
  "properties": {
    "gn:admin1_code":"11",
    "gn:admin2_code":"3.0",
    "gn:asciiname":"La Huertita",
    "gn:country_code":"MX",
    "gn:dem":1856,
    "gn:feature_class":"P",
    "gn:feature_code":"PPL",
    "gn:name":"La Huertita",
    "gn:population":64,
    "gn:timezone":"America/Mexico_City",
    "iso:country":"MX",
    "wof:name":"La Huertita",
    "wof:placetype":"locality",
    "wof:population":64
},
  "geometry": {"coordinates":[-100.84806,20.89306],"type":"Point"}
}