{
  "type": "Feature",
  "properties": {
    "gn:admin1_code":"24",
    "gn:admin2_code":"32.0",
    "gn:asciiname":"El Pajonal",
    "gn:country_code":"MX",
    "gn:dem":1840,
    "gn:feature_class":"P",
    "gn:feature_code":"PPL",
    "gn:name":"El Pajonal",
    "gn:population":47,
    "gn:timezone":"America/Mexico_City",
    "iso:country":"MX",
    "name:ceb_x_preferred":[
        "El Pajonal"
    ],
    "name:spa_x_preferred":[
        "El Pajonal"
    ],
    "wof:name":"El Pajonal",
    "wof:placetype":"locality",
    "wof:population":47
},
  "geometry": {"coordinates":[-100.65778,21.64833],"type":"Point"}
}