{
  "type": "Feature",
  "properties": {
    "gn:admin1_code":"31",
    "gn:admin2_code":"37.0",
    "gn:asciiname":"Chulumay",
    "gn:country_code":"MX",
    "gn:dem":14,
    "gn:feature_class":"P",
    "gn:feature_code":"PPL",
    "gn:name":"Chulumay",
    "gn:population":0,
    "gn:timezone":"America/Merida",
    "iso:country":"MX",
    "name:spa_x_preferred":[
        "Chulumay"
    ],
    "wof:name":"Chulumay",
    "wof:placetype":"locality"
},
  "geometry": {"coordinates":[-89.16913000000002,20.66972],"type":"Point"}
}