{
  "type": "Feature",
  "properties": {
    "gn:admin1_code":"4",
    "gn:admin2_code":"3.0",
    "gn:asciiname":"La Daga",
    "gn:country_code":"MX",
    "gn:dem":-5,
    "gn:feature_class":"P",
    "gn:feature_code":"PPL",
    "gn:name":"La Daga",
    "gn:population":0,
    "gn:timezone":"America/Merida",
    "iso:country":"MX",
    "name:spa_x_preferred":[
        "La Daga"
    ],
    "wof:name":"La Daga",
    "wof:placetype":"locality"
},
  "geometry": {"coordinates":[-91.54724,18.26134],"type":"Point"}
}