{
  "type": "Feature",
  "properties": {
    "gn:admin1_code":"32.0",
    "gn:admin2_code":"29.0",
    "gn:asciiname":"Laguna los Aguilar",
    "gn:country_code":"MX",
    "gn:dem":2245,
    "gn:feature_class":"P",
    "gn:feature_code":"PPL",
    "gn:name":"Laguna los Aguilar",
    "gn:population":0,
    "gn:timezone":"America/Mexico_City",
    "iso:country":"MX",
    "name:spa_x_preferred":[
        "Laguna los Aguilar"
    ],
    "wof:name":"Laguna los Aguilar",
    "wof:placetype":"locality"
},
  "geometry": {"coordinates":[-103.61459000000001,24.04035],"type":"Point"}
}