{
  "type": "Feature",
  "properties": {
    "gn:admin1_code":"10",
    "gn:admin2_code":"34",
    "gn:asciiname":"Rancho Viejo",
    "gn:country_code":"MX",
    "gn:dem":452,
    "gn:feature_class":"P",
    "gn:feature_code":"PPL",
    "gn:name":"Rancho Viejo",
    "gn:population":27,
    "gn:timezone":"America/Monterrey",
    "iso:country":"MX",
    "wof:name":"Rancho Viejo",
    "wof:placetype":"locality",
    "wof:population":27
},
  "geometry": {"coordinates":[-106.79731,25.0697],"type":"Point"}
}