{
  "type": "Feature",
  "properties": {
    "gn:admin1_code":"6",
    "gn:admin2_code":"12.0",
    "gn:asciiname":"Retosachi",
    "gn:country_code":"MX",
    "gn:dem":2122,
    "gn:feature_class":"P",
    "gn:feature_code":"PPL",
    "gn:name":"Ret\u00f3sachi",
    "gn:population":6,
    "gn:timezone":"America/Chihuahua",
    "iso:country":"MX",
    "name:und_x_variant":[
        "Ret\u00f3sachi"
    ],
    "wof:name":"Retosachi",
    "wof:placetype":"locality",
    "wof:population":6
},
  "geometry": {"coordinates":[-106.99889,27.53472],"type":"Point"}
}