{
  "type": "Feature",
  "properties": {
    "gn:admin1_code":"19",
    "gn:admin2_code":"13.0",
    "gn:asciiname":"Rancho Nuevo (Los Charcos)",
    "gn:country_code":"MX",
    "gn:dem":155,
    "gn:feature_class":"P",
    "gn:feature_code":"PPL",
    "gn:name":"Rancho Nuevo (Los Charcos)",
    "gn:population":8,
    "gn:timezone":"America/Monterrey",
    "iso:country":"MX",
    "wof:name":"Rancho Nuevo (Los Charcos)",
    "wof:placetype":"locality",
    "wof:population":8
},
  "geometry": {"coordinates":[-98.92444,25.20064],"type":"Point"}
}