{
  "type": "Feature",
  "properties": {
    "gn:admin1_code":"12",
    "gn:admin2_code":"39.0",
    "gn:asciiname":"Carrizal de la Via",
    "gn:country_code":"MX",
    "gn:dem":567,
    "gn:feature_class":"P",
    "gn:feature_code":"PPL",
    "gn:name":"Carrizal de la V\u00eda",
    "gn:population":396,
    "gn:timezone":"America/Mexico_City",
    "iso:country":"MX",
    "wof:name":"Carrizal de la Via",
    "wof:placetype":"locality",
    "wof:population":396
},
  "geometry": {"coordinates":[-99.51278000000001,17.20472],"type":"Point"}
}