{
  "type": "Feature",
  "properties": {
    "gn:admin1_code":"20",
    "gn:admin2_code":"278.0",
    "gn:asciiname":"Cerro Tepezcuintle",
    "gn:country_code":"MX",
    "gn:dem":82,
    "gn:feature_class":"P",
    "gn:feature_code":"PPL",
    "gn:name":"Cerro Tepezcuintle",
    "gn:population":912,
    "gn:timezone":"America/Mexico_City",
    "iso:country":"MX",
    "name:spa_x_preferred":[
        "Cerro Tepexcuintle"
    ],
    "name:spa_x_variant":[
        "Cerro Tepezcuintle"
    ],
    "wof:name":"Cerro Tepezcuintle",
    "wof:placetype":"locality",
    "wof:population":912
},
  "geometry": {"coordinates":[-96.34171000000001,18.14632000000001],"type":"Point"}
}