{
  "type": "Feature",
  "properties": {
    "gn:admin1_code":"32",
    "gn:admin2_code":"34",
    "gn:asciiname":"La Palma",
    "gn:country_code":"MX",
    "gn:dem":2135,
    "gn:feature_class":"P",
    "gn:feature_code":"PPL",
    "gn:name":"La Palma",
    "gn:population":15,
    "gn:timezone":"America/Mexico_City",
    "iso:country":"MX",
    "wof:name":"La Palma",
    "wof:placetype":"locality",
    "wof:population":15
},
  "geometry": {"coordinates":[-102.81639,21.56361],"type":"Point"}
}