{
  "type": "Feature",
  "properties": {
    "gn:admin1_code":"21",
    "gn:admin2_code":"64",
    "gn:asciiname":"El Caracol",
    "gn:country_code":"MX",
    "gn:dem":141,
    "gn:feature_class":"P",
    "gn:feature_code":"PPL",
    "gn:name":"El Caracol",
    "gn:population":13,
    "gn:timezone":"America/Mexico_City",
    "iso:country":"MX",
    "wof:name":"El Caracol",
    "wof:placetype":"locality",
    "wof:population":13
},
  "geometry": {"coordinates":[-97.78917,20.80889],"type":"Point"}
}