{
  "type": "Feature",
  "properties": {
    "gn:admin1_code":"12",
    "gn:admin2_code":"10",
    "gn:asciiname":"Tlalcueloltetitlan",
    "gn:country_code":"MX",
    "gn:dem":1655,
    "gn:feature_class":"P",
    "gn:feature_code":"PPL",
    "gn:name":"Tlalcueloltetitl\u00e1n",
    "gn:population":37,
    "gn:timezone":"America/Mexico_City",
    "iso:country":"MX",
    "name:und_x_variant":[
        "Tlalcueloltetitl\u00e1n"
    ],
    "wof:name":"Tlalcueloltetitlan",
    "wof:placetype":"locality",
    "wof:population":37
},
  "geometry": {"coordinates":[-98.94045,17.57203],"type":"Point"}
}