{
  "type": "Feature",
  "properties": {
    "gn:admin1_code":"5",
    "gn:admin2_code":"26.0",
    "gn:asciiname":"Tzabalho",
    "gn:country_code":"MX",
    "gn:dem":1688,
    "gn:feature_class":"P",
    "gn:feature_code":"PPL",
    "gn:name":"Tzabalh\u00f3",
    "gn:population":480,
    "gn:timezone":"America/Mexico_City",
    "iso:country":"MX",
    "name:und_x_variant":[
        "Tzabalh\u00f3"
    ],
    "wof:name":"Tzabalho",
    "wof:placetype":"locality",
    "wof:population":480
},
  "geometry": {"coordinates":[-92.62,16.93806],"type":"Point"}
}