{
  "type": "Feature",
  "properties": {
    "gn:admin1_code":"25",
    "gn:admin2_code":"4.0",
    "gn:asciiname":"El Cantil",
    "gn:country_code":"MX",
    "gn:dem":787,
    "gn:feature_class":"P",
    "gn:feature_code":"PPL",
    "gn:name":"El Cantil",
    "gn:population":9,
    "gn:timezone":"America/Mazatlan",
    "iso:country":"MX",
    "wof:name":"El Cantil",
    "wof:placetype":"locality",
    "wof:population":9
},
  "geometry": {"coordinates":[-105.90458,23.40855],"type":"Point"}
}