{
  "type": "Feature",
  "properties": {
    "gn:admin1_code":"4.0",
    "gn:asciiname":"Bonanza",
    "gn:country_code":"MX",
    "gn:dem":247,
    "gn:feature_class":"P",
    "gn:feature_code":"PPL",
    "gn:name":"Bonanza",
    "gn:population":0,
    "gn:timezone":"America/Cancun",
    "iso:country":"MX",
    "name:spa_x_preferred":[
        "Bonanza"
    ],
    "wof:name":"Bonanza",
    "wof:placetype":"locality"
},
  "geometry": {"coordinates":[-89.36343000000002,18.84859],"type":"Point"}
}