{
  "type": "Feature",
  "properties": {
    "gn:admin1_code":"14.0",
    "gn:admin2_code":"110.0",
    "gn:asciiname":"Rancho los Michel",
    "gn:country_code":"MX",
    "gn:dem":1566,
    "gn:feature_class":"P",
    "gn:feature_code":"PPL",
    "gn:name":"Rancho los Michel",
    "gn:population":0,
    "gn:timezone":"America/Mexico_City",
    "iso:country":"MX",
    "name:spa_x_preferred":[
        "Rancho los Michel"
    ],
    "wof:name":"Rancho los Michel",
    "wof:placetype":"locality"
},
  "geometry": {"coordinates":[-104.23204,19.94317],"type":"Point"}
}