{
  "type": "Feature",
  "properties": {
    "gn:admin1_code":"12",
    "gn:admin2_code":"75.0",
    "gn:asciiname":"Tres Cruces",
    "gn:country_code":"MX",
    "gn:dem":2159,
    "gn:feature_class":"P",
    "gn:feature_code":"PPL",
    "gn:name":"Tres Cruces",
    "gn:population":53,
    "gn:timezone":"America/Mexico_City",
    "iso:country":"MX",
    "wof:name":"Tres Cruces",
    "wof:placetype":"locality",
    "wof:population":53
},
  "geometry": {"coordinates":[-99.77293,17.71852999999999],"type":"Point"}
}