{
  "type": "Feature",
  "properties": {
    "gn:admin1_code":"20",
    "gn:admin2_code":"2.0",
    "gn:asciiname":"Cerro Mojarra",
    "gn:country_code":"MX",
    "gn:dem":349,
    "gn:feature_class":"P",
    "gn:feature_code":"PPL",
    "gn:name":"Cerro Mojarra",
    "gn:population":0,
    "gn:timezone":"America/Mexico_City",
    "iso:country":"MX",
    "name:spa_x_preferred":[
        "Cerro Mojarra"
    ],
    "wof:name":"Cerro Mojarra",
    "wof:placetype":"locality"
},
  "geometry": {"coordinates":[-96.65787,18.40751],"type":"Point"}
}