{
  "type": "Feature",
  "properties": {
    "gn:admin1_code":"2.0",
    "gn:admin2_code":"2.0",
    "gn:asciiname":"Ejido Tigres del Desierto",
    "gn:country_code":"MX",
    "gn:dem":62,
    "gn:feature_class":"P",
    "gn:feature_code":"PPL",
    "gn:name":"Ejido Tigres del Desierto",
    "gn:population":0,
    "gn:timezone":"America/Tijuana",
    "iso:country":"MX",
    "name:spa_x_preferred":[
        "Ejido Tigres del Desierto"
    ],
    "wof:name":"Ejido Tigres del Desierto",
    "wof:placetype":"locality"
},
  "geometry": {"coordinates":[-115.71917000000001,32.21306],"type":"Point"}
}