{
  "type": "Feature",
  "properties": {
    "gn:admin1_code":"12",
    "gn:admin2_code":"43.0",
    "gn:asciiname":"El Gitano",
    "gn:country_code":"MX",
    "gn:dem":1968,
    "gn:feature_class":"P",
    "gn:feature_code":"PPL",
    "gn:name":"El Gitano",
    "gn:population":61,
    "gn:timezone":"America/Mexico_City",
    "iso:country":"MX",
    "wof:name":"El Gitano",
    "wof:placetype":"locality",
    "wof:population":61
},
  "geometry": {"coordinates":[-98.44027,17.32787],"type":"Point"}
}