{
  "type": "Feature",
  "properties": {
    "gn:admin1_code":"6",
    "gn:admin2_code":"29",
    "gn:asciiname":"La Providencia",
    "gn:country_code":"MX",
    "gn:dem":2463,
    "gn:feature_class":"P",
    "gn:feature_code":"PPL",
    "gn:name":"La Providencia",
    "gn:population":37,
    "gn:timezone":"America/Chihuahua",
    "iso:country":"MX",
    "wof:name":"La Providencia",
    "wof:placetype":"locality",
    "wof:population":37
},
  "geometry": {"coordinates":[-106.60733999999999,25.83885],"type":"Point"}
}