{
  "type": "Feature",
  "properties": {
    "gn:admin1_code":"28",
    "gn:admin2_code":"23.0",
    "gn:asciiname":"Lechuguillas",
    "gn:country_code":"MX",
    "gn:dem":67,
    "gn:feature_class":"P",
    "gn:feature_code":"PPL",
    "gn:name":"Lechuguillas",
    "gn:population":0,
    "gn:timezone":"America/Monterrey",
    "iso:country":"MX",
    "name:und_x_variant":[
        "Las Lechuguillas",
        "Lechuguillas"
    ],
    "wof:name":"Lechuguillas",
    "wof:placetype":"locality"
},
  "geometry": {"coordinates":[-98.19873,25.24161],"type":"Point"}
}