{
  "type": "Feature",
  "properties": {
    "gn:admin1_code":"19",
    "gn:admin2_code":"33",
    "gn:asciiname":"El Gallo",
    "gn:country_code":"MX",
    "gn:dem":248,
    "gn:feature_class":"P",
    "gn:feature_code":"PPL",
    "gn:name":"El Gallo",
    "gn:population":29,
    "gn:timezone":"America/Monterrey",
    "iso:country":"MX",
    "name:ceb_x_preferred":[
        "El Gallo"
    ],
    "name:fra_x_preferred":[
        "El Gallo"
    ],
    "name:spa_x_preferred":[
        "El Gallo"
    ],
    "name:swe_x_preferred":[
        "El Gallo"
    ],
    "wof:name":"El Gallo",
    "wof:placetype":"locality",
    "wof:population":29
},
  "geometry": {"coordinates":[-99.31749000000001,24.8748],"type":"Point"}
}