{
  "type": "Feature",
  "properties": {
    "gn:admin1_code":"26",
    "gn:admin2_code":"59.0",
    "gn:asciiname":"David Cardenas",
    "gn:country_code":"MX",
    "gn:dem":1364,
    "gn:feature_class":"P",
    "gn:feature_code":"PPL",
    "gn:name":"David C\u00e1rdenas",
    "gn:population":9,
    "gn:timezone":"America/Hermosillo",
    "iso:country":"MX",
    "name:und_x_variant":[
        "David C\u00e1rdenas"
    ],
    "wof:name":"David Cardenas",
    "wof:placetype":"locality",
    "wof:population":9
},
  "geometry": {"coordinates":[-110.59806,31.24361],"type":"Point"}
}