{
  "type": "Feature",
  "properties": {
    "gn:admin1_code":"6",
    "gn:admin2_code":"30.0",
    "gn:asciiname":"El Terrero Amarillo",
    "gn:country_code":"MX",
    "gn:dem":1204,
    "gn:feature_class":"P",
    "gn:feature_code":"PPL",
    "gn:name":"El Terrero Amarillo",
    "gn:population":131,
    "gn:timezone":"America/Chihuahua",
    "iso:country":"MX",
    "wof:name":"El Terrero Amarillo",
    "wof:placetype":"locality",
    "wof:population":131
},
  "geometry": {"coordinates":[-108.26964,27.1552],"type":"Point"}
}