{
  "type": "Feature",
  "properties": {
    "gn:admin1_code":"14.0",
    "gn:admin2_code":"69.0",
    "gn:asciiname":"Rincon del Potrero",
    "gn:country_code":"MX",
    "gn:dem":1812,
    "gn:feature_class":"P",
    "gn:feature_code":"PPL",
    "gn:name":"Rinc\u00f3n del Potrero",
    "gn:population":0,
    "gn:timezone":"America/Mexico_City",
    "iso:country":"MX",
    "name:spa_x_preferred":[
        "Rinc\u00f3n del Potrero"
    ],
    "wof:name":"Rincon del Potrero",
    "wof:placetype":"locality"
},
  "geometry": {"coordinates":[-102.77086,19.83089],"type":"Point"}
}