{
  "type": "Feature",
  "properties": {
    "gn:admin1_code":"14",
    "gn:admin2_code":"44.0",
    "gn:asciiname":"El Costenito",
    "gn:country_code":"MX",
    "gn:dem":1544,
    "gn:feature_class":"P",
    "gn:feature_code":"PPL",
    "gn:name":"El Coste\u00f1ito",
    "gn:population":6,
    "gn:timezone":"America/Mexico_City",
    "iso:country":"MX",
    "name:und_x_variant":[
        "El Coste\u00f1ito"
    ],
    "wof:name":"El Costenito",
    "wof:placetype":"locality",
    "wof:population":6
},
  "geometry": {"coordinates":[-103.22889000000001,20.40667],"type":"Point"}
}