{
  "type": "Feature",
  "properties": {
    "gn:admin1_code":"26",
    "gn:admin2_code":"33.0",
    "gn:asciiname":"Campo Romo",
    "gn:country_code":"MX",
    "gn:dem":20,
    "gn:feature_class":"P",
    "gn:feature_code":"PPL",
    "gn:name":"Campo Romo",
    "gn:population":5,
    "gn:timezone":"America/Hermosillo",
    "iso:country":"MX",
    "wof:name":"Campo Romo",
    "wof:placetype":"locality",
    "wof:population":5
},
  "geometry": {"coordinates":[-109.47778,26.83694],"type":"Point"}
}