{
  "type": "Feature",
  "properties": {
    "gn:admin1_code":"4",
    "gn:admin2_code":"3.0",
    "gn:asciiname":"San Antonio del Pom Primero",
    "gn:country_code":"MX",
    "gn:dem":2,
    "gn:feature_class":"P",
    "gn:feature_code":"PPL",
    "gn:name":"San Antonio del Pom Primero",
    "gn:population":2,
    "gn:timezone":"America/Merida",
    "iso:country":"MX",
    "name:und_x_variant":[
        "San Antonio del Pom",
        "Pom"
    ],
    "wof:name":"San Antonio del Pom Primero",
    "wof:placetype":"locality",
    "wof:population":2
},
  "geometry": {"coordinates":[-92.19235999999999,18.61566],"type":"Point"}
}