{
  "type": "Feature",
  "properties": {
    "gn:admin1_code":"14",
    "gn:admin2_code":"43.0",
    "gn:asciiname":"Puente Arroyo Seco",
    "gn:country_code":"MX",
    "gn:dem":71,
    "gn:feature_class":"P",
    "gn:feature_code":"PPL",
    "gn:name":"Puente Arroyo Seco",
    "gn:population":0,
    "gn:timezone":"America/Mexico_City",
    "iso:country":"MX",
    "name:spa_x_preferred":[
        "Puente Arroyo Seco"
    ],
    "wof:name":"Puente Arroyo Seco",
    "wof:placetype":"locality"
},
  "geometry": {"coordinates":[-104.92619000000001,19.36367000000001],"type":"Point"}
}