{
  "type": "Feature",
  "properties": {
    "gn:admin1_code":"6",
    "gn:admin2_code":"30",
    "gn:asciiname":"Chuihaibo",
    "gn:country_code":"MX",
    "gn:dem":1879,
    "gn:feature_class":"P",
    "gn:feature_code":"PPL",
    "gn:name":"Chuihaibo",
    "gn:population":9,
    "gn:timezone":"America/Chihuahua",
    "iso:country":"MX",
    "wof:name":"Chuihaibo",
    "wof:placetype":"locality",
    "wof:population":9
},
  "geometry": {"coordinates":[-108.11678000000001,27.45012],"type":"Point"}
}