{
  "type": "Feature",
  "properties": {
    "gn:admin1_code":"30",
    "gn:admin2_code":"210.0",
    "gn:asciiname":"Benito Juarez Segundo (La Raya)",
    "gn:country_code":"MX",
    "gn:dem":87,
    "gn:feature_class":"P",
    "gn:feature_code":"PPL",
    "gn:name":"Benito Ju\u00e1rez Segundo (La Raya)",
    "gn:population":308,
    "gn:timezone":"America/Mexico_City",
    "iso:country":"MX",
    "name:und_x_variant":[
        "Benito Ju\u00e1rez Segundo (La Raya)"
    ],
    "wof:name":"Benito Juarez Segundo (La Raya)",
    "wof:placetype":"locality",
    "wof:population":308
},
  "geometry": {"coordinates":[-94.49806,17.31639],"type":"Point"}
}