{
  "type": "Feature",
  "properties": {
    "gn:admin1_code":"11",
    "gn:admin2_code":"33",
    "gn:asciiname":"La Lomita (Jalapa)",
    "gn:country_code":"MX",
    "gn:dem":2024,
    "gn:feature_class":"P",
    "gn:feature_code":"PPL",
    "gn:name":"La Lomita (Jalapa)",
    "gn:population":13,
    "gn:timezone":"America/Mexico_City",
    "iso:country":"MX",
    "wof:name":"La Lomita (Jalapa)",
    "wof:placetype":"locality",
    "wof:population":13
},
  "geometry": {"coordinates":[-100.38028,21.37083],"type":"Point"}
}