{
  "type": "Feature",
  "properties": {
    "gn:admin1_code":"6",
    "gn:admin2_code":"8.0",
    "gn:asciiname":"El Alguate",
    "gn:country_code":"MX",
    "gn:dem":616,
    "gn:feature_class":"P",
    "gn:feature_code":"PPL",
    "gn:name":"El Alguate",
    "gn:population":8,
    "gn:timezone":"America/Chihuahua",
    "iso:country":"MX",
    "wof:name":"El Alguate",
    "wof:placetype":"locality",
    "wof:population":8
},
  "geometry": {"coordinates":[-107.72046,27.04576],"type":"Point"}
}