{
  "type": "Feature",
  "properties": {
    "gn:admin1_code":"30",
    "gn:admin2_code":"121.0",
    "gn:asciiname":"Las Margaritas (La Bolsa)",
    "gn:country_code":"MX",
    "gn:dem":48,
    "gn:feature_class":"P",
    "gn:feature_code":"PPL",
    "gn:name":"Las Margaritas (La Bolsa)",
    "gn:population":9,
    "gn:timezone":"America/Mexico_City",
    "iso:country":"MX",
    "wof:name":"Las Margaritas (La Bolsa)",
    "wof:placetype":"locality",
    "wof:population":9
},
  "geometry": {"coordinates":[-97.96832999999999,21.62472],"type":"Point"}
}