{
  "type": "Feature",
  "properties": {
    "gn:admin1_code":"2.0",
    "gn:asciiname":"Rancho las Hamacas",
    "gn:country_code":"MX",
    "gn:dem":101,
    "gn:feature_class":"P",
    "gn:feature_code":"PPL",
    "gn:name":"Rancho las Hamacas",
    "gn:population":0,
    "gn:timezone":"America/Tijuana",
    "iso:country":"MX",
    "name:spa_x_preferred":[
        "Rancho las Hamacas"
    ],
    "name:spa_x_variant":[
        "Las Hamacas"
    ],
    "wof:name":"Rancho las Hamacas",
    "wof:placetype":"locality"
},
  "geometry": {"coordinates":[-116.50112,31.79644],"type":"Point"}
}