{
  "type": "Feature",
  "properties": {
    "gn:admin1_code":"24",
    "gn:admin2_code":"35",
    "gn:asciiname":"San Gerardo",
    "gn:country_code":"MX",
    "gn:dem":1842,
    "gn:feature_class":"P",
    "gn:feature_code":"PPL",
    "gn:name":"San Gerardo",
    "gn:population":11,
    "gn:timezone":"America/Mexico_City",
    "iso:country":"MX",
    "name:ceb_x_preferred":[
        "San Gerardo"
    ],
    "name:ita_x_preferred":[
        "San Gerardo"
    ],
    "name:por_x_preferred":[
        "San Gerardo"
    ],
    "name:spa_x_preferred":[
        "San Gerardo"
    ],
    "name:zho_x_preferred":[
        "\u8056\u8d6b\u62c9\u723e\u591a"
    ],
    "wof:name":"San Gerardo",
    "wof:placetype":"locality",
    "wof:population":11
},
  "geometry": {"coordinates":[-100.88722,22.18389],"type":"Point"}
}