{
  "type": "Feature",
  "properties": {
    "gn:admin1_code":"11",
    "gn:admin2_code":"33",
    "gn:asciiname":"La Esperanza",
    "gn:country_code":"MX",
    "gn:dem":2047,
    "gn:feature_class":"P",
    "gn:feature_code":"PPL",
    "gn:name":"La Esperanza",
    "gn:population":37,
    "gn:timezone":"America/Mexico_City",
    "iso:country":"MX",
    "wof:name":"La Esperanza",
    "wof:placetype":"locality",
    "wof:population":37
},
  "geometry": {"coordinates":[-100.64944,21.33278],"type":"Point"}
}