{
  "type": "Feature",
  "properties": {
    "gn:admin1_code":"14",
    "gn:admin2_code":"69",
    "gn:asciiname":"Mesa del Guayabo",
    "gn:country_code":"MX",
    "gn:dem":1660,
    "gn:feature_class":"P",
    "gn:feature_code":"PPL",
    "gn:name":"Mesa del Guayabo",
    "gn:population":23,
    "gn:timezone":"America/Mexico_City",
    "iso:country":"MX",
    "wof:name":"Mesa del Guayabo",
    "wof:placetype":"locality",
    "wof:population":23
},
  "geometry": {"coordinates":[-102.87194,19.745],"type":"Point"}
}