{
  "type": "Feature",
  "properties": {
    "gn:admin1_code":"5.0",
    "gn:admin2_code":"23.0",
    "gn:asciiname":"Banoctic",
    "gn:country_code":"MX",
    "gn:dem":2410,
    "gn:feature_class":"P",
    "gn:feature_code":"PPL",
    "gn:name":"Banoctic",
    "gn:population":0,
    "gn:timezone":"America/Mexico_City",
    "iso:country":"MX",
    "name:spa_x_preferred":[
        "Banoptik"
    ],
    "name:spa_x_variant":[
        "Banoctic",
        "Noctic"
    ],
    "wof:name":"Banoctic",
    "wof:placetype":"locality"
},
  "geometry": {"coordinates":[-92.76661,16.79802999999999],"type":"Point"}
}