{
  "type": "Feature",
  "properties": {
    "gn:admin1_code":"10",
    "gn:admin2_code":"23.0",
    "gn:asciiname":"El Ranchito",
    "gn:country_code":"MX",
    "gn:dem":2057,
    "gn:feature_class":"P",
    "gn:feature_code":"PPL",
    "gn:name":"El Ranchito",
    "gn:population":0,
    "gn:timezone":"America/Monterrey",
    "iso:country":"MX",
    "name:spa_x_preferred":[
        "El Ranchito"
    ],
    "name:spa_x_variant":[
        "El Cocedor"
    ],
    "wof:name":"El Ranchito",
    "wof:placetype":"locality"
},
  "geometry": {"coordinates":[-105.59748,23.84446],"type":"Point"}
}