{
  "type": "Feature",
  "properties": {
    "gn:admin1_code":"16.0",
    "gn:admin2_code":"82.0",
    "gn:asciiname":"El Rincon de Copitero",
    "gn:country_code":"MX",
    "gn:dem":2091,
    "gn:feature_class":"P",
    "gn:feature_code":"PPL",
    "gn:name":"El Rinc\u00f3n de Copitero",
    "gn:population":0,
    "gn:timezone":"America/Mexico_City",
    "iso:country":"MX",
    "name:spa_x_preferred":[
        "El Rinc\u00f3n de Copitero"
    ],
    "wof:name":"El Rincon de Copitero",
    "wof:placetype":"locality"
},
  "geometry": {"coordinates":[-101.38339000000001,19.31946],"type":"Point"}
}