{
  "type": "Feature",
  "properties": {
    "gn:admin1_code":"12.0",
    "gn:admin2_code":"50.0",
    "gn:asciiname":"Chacamero Grande",
    "gn:country_code":"MX",
    "gn:dem":301,
    "gn:feature_class":"P",
    "gn:feature_code":"PPL",
    "gn:name":"Chac\u00e1mero Grande",
    "gn:population":0,
    "gn:timezone":"America/Mexico_City",
    "iso:country":"MX",
    "name:spa_x_preferred":[
        "Chac\u00e1mero Grande"
    ],
    "wof:name":"Chacamero Grande",
    "wof:placetype":"locality"
},
  "geometry": {"coordinates":[-100.56676,18.36051],"type":"Point"}
}