{
  "type": "Feature",
  "properties": {
    "gn:admin1_code":"18",
    "gn:admin2_code":"9",
    "gn:asciiname":"Rancho Nuevo (Juventino)",
    "gn:country_code":"MX",
    "gn:dem":1694,
    "gn:feature_class":"P",
    "gn:feature_code":"PPL",
    "gn:name":"Rancho Nuevo (Juventino)",
    "gn:population":30,
    "gn:timezone":"America/Mazatlan",
    "iso:country":"MX",
    "wof:name":"Rancho Nuevo (Juventino)",
    "wof:placetype":"locality",
    "wof:population":30
},
  "geometry": {"coordinates":[-104.42028000000001,22.01333],"type":"Point"}
}