{
  "type": "Feature",
  "properties": {
    "gn:admin1_code":"24",
    "gn:admin2_code":"15.0",
    "gn:asciiname":"La Laguna de los Caballos",
    "gn:country_code":"MX",
    "gn:dem":2145,
    "gn:feature_class":"P",
    "gn:feature_code":"PPL",
    "gn:name":"La Laguna de los Caballos",
    "gn:population":6,
    "gn:timezone":"America/Mexico_City",
    "iso:country":"MX",
    "wof:name":"La Laguna de los Caballos",
    "wof:placetype":"locality",
    "wof:population":6
},
  "geometry": {"coordinates":[-101.27472,23.17722],"type":"Point"}
}