{
  "type": "Feature",
  "properties": {
    "gn:admin1_code":"30",
    "gn:admin2_code":"169.0",
    "gn:asciiname":"Las Cadenas",
    "gn:country_code":"MX",
    "gn:dem":30,
    "gn:feature_class":"P",
    "gn:feature_code":"PPL",
    "gn:name":"Las Cadenas",
    "gn:population":0,
    "gn:timezone":"America/Mexico_City",
    "iso:country":"MX",
    "name:spa_x_preferred":[
        "Las Cadenas"
    ],
    "wof:name":"Las Cadenas",
    "wof:placetype":"locality"
},
  "geometry": {"coordinates":[-95.70291,18.03191],"type":"Point"}
}