{
  "type": "Feature",
  "properties": {
    "gn:admin1_code":"5.0",
    "gn:asciiname":"Florida Espana",
    "gn:country_code":"MX",
    "gn:dem":1275,
    "gn:feature_class":"P",
    "gn:feature_code":"PPL",
    "gn:name":"Florida Espa\u00f1a",
    "gn:population":0,
    "gn:timezone":"America/Mexico_City",
    "iso:country":"MX",
    "name:spa_x_preferred":[
        "Florida Espa\u00f1a"
    ],
    "wof:name":"Florida Espana",
    "wof:placetype":"locality"
},
  "geometry": {"coordinates":[-93.37006,15.96082],"type":"Point"}
}