{
  "type": "Feature",
  "properties": {
    "gn:admin1_code":"2",
    "gn:admin2_code":"1.0",
    "gn:asciiname":"Abelardo L. Rodriguez",
    "gn:country_code":"MX",
    "gn:dem":160,
    "gn:feature_class":"P",
    "gn:feature_code":"PPL",
    "gn:name":"Abelardo L. Rodr\u00edguez",
    "gn:population":0,
    "gn:timezone":"America/Tijuana",
    "iso:country":"MX",
    "name:spa_x_preferred":[
        "Abelardo L. Rodr\u00edguez"
    ],
    "wof:name":"Abelardo L. Rodriguez",
    "wof:placetype":"locality"
},
  "geometry": {"coordinates":[-115.47315,29.80571],"type":"Point"}
}