{
  "type": "Feature",
  "properties": {
    "gn:admin1_code":"21.0",
    "gn:admin2_code":"114.0",
    "gn:asciiname":"Barranca Yocotlan",
    "gn:country_code":"MX",
    "gn:dem":2721,
    "gn:feature_class":"P",
    "gn:feature_code":"PPL",
    "gn:name":"Barranca Yocotlan",
    "gn:population":0,
    "gn:timezone":"America/Mexico_City",
    "iso:country":"MX",
    "name:spa_x_preferred":[
        "Barranca Yocotlan"
    ],
    "wof:name":"Barranca Yocotlan",
    "wof:placetype":"locality"
},
  "geometry": {"coordinates":[-98.08540000000001,19.15813],"type":"Point"}
}