{
  "type": "Feature",
  "properties": {
    "gn:admin1_code":"6",
    "gn:admin2_code":"65.0",
    "gn:asciiname":"Gagueinapuchi",
    "gn:country_code":"MX",
    "gn:dem":1645,
    "gn:feature_class":"P",
    "gn:feature_code":"PPL",
    "gn:name":"Gag\u00fcin\u00e1puchi",
    "gn:population":0,
    "gn:timezone":"America/Chihuahua",
    "iso:country":"MX",
    "name:spa_x_preferred":[
        "Gag\u00fcin\u00e1puchi"
    ],
    "wof:name":"Gagueinapuchi",
    "wof:placetype":"locality"
},
  "geometry": {"coordinates":[-107.78086999999999,27.35415],"type":"Point"}
}