{
  "type": "Feature",
  "properties": {
    "iso:country":"MX",
    "name:spa_x_preferred":[
        "Francisco Villa"
    ],
    "qs:gn_adm0_cc":"MX",
    "qs:gn_fcode":"PPL",
    "qs:gn_local":3529612,
    "qs:gn_nam_loc":"Ecatepec, Ecatepec de Morelos, Mexico, MX",
    "qs:gn_namadm1":"29",
    "qs:gn_name":"Francisco Villa",
    "qs:local_max":140,
    "qs:local_sum":356,
    "qs:localhoods":10,
    "qs:name":"Francisco Villa",
    "qs:name_adm0":"M\u00e9xico",
    "qs:name_adm1":"Mexico",
    "qs:name_adm2":"Ecatepec",
    "qs:name_local":"Ecatepec de Morelos",
    "qs:photo_max":11,
    "qs:photo_sum":20,
    "qs:placetype":"Suburb",
    "qs:quad_count":5,
    "qs:woe_adm0":23424900,
    "qs:woe_adm1":2346278,
    "qs:woe_adm2":12600351,
    "qs:woe_lau":0,
    "qs:woe_local":118466,
    "qs:woe_ver":"7.10.0",
    "wof:lang":[
        "spa"
    ],
    "wof:name":"Francisco Villa",
    "wof:placetype":"neighbourhood"
},
  "geometry": {"coordinates":[-99.046967,19.591103],"type":"Point"}
}