{
  "type": "Feature",
  "properties": {
    "gn:admin1_code":"11",
    "gn:admin2_code":"32.0",
    "gn:asciiname":"El Jaralillo",
    "gn:country_code":"MX",
    "gn:dem":2192,
    "gn:feature_class":"P",
    "gn:feature_code":"PPL",
    "gn:name":"El Jaralillo",
    "gn:population":304,
    "gn:timezone":"America/Mexico_City",
    "iso:country":"MX",
    "wof:name":"El Jaralillo",
    "wof:placetype":"locality",
    "wof:population":304
},
  "geometry": {"coordinates":[-100.36091999999999,20.99542000000001],"type":"Point"}
}