{
  "type": "Feature",
  "properties": {
    "gn:admin1_code":"12.0",
    "gn:admin2_code":"68.0",
    "gn:asciiname":"Magueyes",
    "gn:country_code":"MX",
    "gn:dem":120,
    "gn:feature_class":"P",
    "gn:feature_code":"PPL",
    "gn:name":"Magueyes",
    "gn:population":51,
    "gn:timezone":"America/Mexico_City",
    "iso:country":"MX",
    "name:spa_x_preferred":[
        "Magueyes"
    ],
    "wof:name":"Magueyes",
    "wof:placetype":"locality",
    "wof:population":51
},
  "geometry": {"coordinates":[-101.91135,18.03192],"type":"Point"}
}