{
  "type": "Feature",
  "properties": {
    "gn:admin1_code":"10",
    "gn:admin2_code":"37",
    "gn:asciiname":"La Mesa Rosada",
    "gn:country_code":"MX",
    "gn:dem":2494,
    "gn:feature_class":"P",
    "gn:feature_code":"PPL",
    "gn:name":"La Mesa Rosada",
    "gn:population":31,
    "gn:timezone":"America/Monterrey",
    "iso:country":"MX",
    "wof:name":"La Mesa Rosada",
    "wof:placetype":"locality",
    "wof:population":31
},
  "geometry": {"coordinates":[-106.53842,25.2572],"type":"Point"}
}