{
  "type": "Feature",
  "properties": {
    "gn:admin1_code":"14",
    "gn:admin2_code":"61.0",
    "gn:asciiname":"Los Aires",
    "gn:country_code":"MX",
    "gn:dem":1859,
    "gn:feature_class":"P",
    "gn:feature_code":"PPL",
    "gn:name":"Los Aires",
    "gn:population":0,
    "gn:timezone":"America/Mexico_City",
    "iso:country":"MX",
    "name:spa_x_preferred":[
        "Los Aires"
    ],
    "wof:name":"Los Aires",
    "wof:placetype":"locality"
},
  "geometry": {"coordinates":[-104.19383000000001,22.24149],"type":"Point"}
}