{
  "type": "Feature",
  "properties": {
    "gn:admin1_code":"20",
    "gn:admin2_code":"323.0",
    "gn:asciiname":"Union y Progreso",
    "gn:country_code":"MX",
    "gn:dem":971,
    "gn:feature_class":"P",
    "gn:feature_code":"PPL",
    "gn:name":"Uni\u00f3n y Progreso",
    "gn:population":60,
    "gn:timezone":"America/Mexico_City",
    "iso:country":"MX",
    "name:und_x_variant":[
        "Uni\u00f3n y Progreso"
    ],
    "wof:name":"Union y Progreso",
    "wof:placetype":"locality",
    "wof:population":60
},
  "geometry": {"coordinates":[-95.85611,16.97778],"type":"Point"}
}