{
  "type": "Feature",
  "properties": {
    "gn:admin1_code":"14",
    "gn:admin2_code":"65.0",
    "gn:asciiname":"Cuastecomates (Jesus Mendoza)",
    "gn:country_code":"MX",
    "gn:dem":572,
    "gn:feature_class":"P",
    "gn:feature_code":"PPL",
    "gn:name":"Cuastecomates (Jes\u00fas Mendoza)",
    "gn:population":5,
    "gn:timezone":"America/Mexico_City",
    "iso:country":"MX",
    "name:und_x_variant":[
        "Cuastecomates (Jes\u00fas Mendoza)"
    ],
    "wof:name":"Cuastecomates (Jesus Mendoza)",
    "wof:placetype":"locality",
    "wof:population":5
},
  "geometry": {"coordinates":[-103.48694,19.18333],"type":"Point"}
}