{
  "type": "Feature",
  "properties": {
    "gn:admin1_code":"5.0",
    "gn:admin2_code":"19.0",
    "gn:asciiname":"Belisario Dominguez",
    "gn:country_code":"MX",
    "gn:dem":1629,
    "gn:feature_class":"P",
    "gn:feature_code":"PPL",
    "gn:name":"Belisario Dom\u00ednguez",
    "gn:population":0,
    "gn:timezone":"America/Mexico_City",
    "iso:country":"MX",
    "name:spa_x_preferred":[
        "Belisario Dom\u00ednguez"
    ],
    "wof:name":"Belisario Dominguez",
    "wof:placetype":"locality"
},
  "geometry": {"coordinates":[-92.12745,16.23332000000001],"type":"Point"}
}