{
  "type": "Feature",
  "properties": {
    "gn:admin1_code":"10",
    "gn:admin2_code":"9.0",
    "gn:asciiname":"Paraje La Joya Bonita",
    "gn:country_code":"MX",
    "gn:dem":2799,
    "gn:feature_class":"P",
    "gn:feature_code":"PPL",
    "gn:name":"Paraje La Joya Bonita",
    "gn:population":0,
    "gn:timezone":"America/Monterrey",
    "iso:country":"MX",
    "name:spa_x_preferred":[
        "Paraje La Joya Bonita"
    ],
    "wof:name":"Paraje La Joya Bonita",
    "wof:placetype":"locality"
},
  "geometry": {"coordinates":[-106.07096,26.36218],"type":"Point"}
}