{
  "type": "Feature",
  "properties": {
    "gn:admin1_code":"19.0",
    "gn:admin2_code":"24.0",
    "gn:asciiname":"La Joya del Lenadero",
    "gn:country_code":"MX",
    "gn:dem":2354,
    "gn:feature_class":"P",
    "gn:feature_code":"PPL",
    "gn:name":"La Joya del Le\u00f1adero",
    "gn:population":6,
    "gn:timezone":"America/Monterrey",
    "iso:country":"MX",
    "name:spa_x_preferred":[
        "La Joya del Le\u00f1adero"
    ],
    "wof:name":"La Joya del Lenadero",
    "wof:placetype":"locality",
    "wof:population":6
},
  "geometry": {"coordinates":[-99.60522,23.95147],"type":"Point"}
}