{
  "type": "Feature",
  "properties": {
    "gn:admin1_code":"9",
    "gn:admin2_code":"11.0",
    "gn:asciiname":"Tierra Blanca Parte Alta",
    "gn:country_code":"MX",
    "gn:dem":2357,
    "gn:feature_class":"P",
    "gn:feature_code":"PPL",
    "gn:name":"Tierra Blanca Parte Alta",
    "gn:population":88,
    "gn:timezone":"America/Mexico_City",
    "iso:country":"MX",
    "wof:name":"Tierra Blanca Parte Alta",
    "wof:placetype":"locality",
    "wof:population":88
},
  "geometry": {"coordinates":[-99.00939,19.23321],"type":"Point"}
}