{
  "type": "Feature",
  "properties": {
    "gn:admin1_code":"14",
    "gn:admin2_code":"35",
    "gn:asciiname":"La Concha",
    "gn:country_code":"MX",
    "gn:dem":2007,
    "gn:feature_class":"P",
    "gn:feature_code":"PPL",
    "gn:name":"La Concha",
    "gn:population":11,
    "gn:timezone":"America/Mexico_City",
    "iso:country":"MX",
    "name:ceb_x_preferred":[
        "La Concha"
    ],
    "name:spa_x_preferred":[
        "La Concha"
    ],
    "name:swe_x_preferred":[
        "La Concha"
    ],
    "wof:name":"La Concha",
    "wof:placetype":"locality",
    "wof:population":11
},
  "geometry": {"coordinates":[-102.14749999999999,21.66889],"type":"Point"}
}