{
  "type": "Feature",
  "properties": {
    "gn:admin1_code":"16",
    "gn:admin2_code":"49.0",
    "gn:asciiname":"El Mezquite",
    "gn:country_code":"MX",
    "gn:dem":1035,
    "gn:feature_class":"P",
    "gn:feature_code":"PPL",
    "gn:name":"El Mezquite",
    "gn:population":0,
    "gn:timezone":"America/Mexico_City",
    "iso:country":"MX",
    "name:spa_x_preferred":[
        "El Mezquite"
    ],
    "wof:name":"El Mezquite",
    "wof:placetype":"locality"
},
  "geometry": {"coordinates":[-101.15439000000001,19.33015],"type":"Point"}
}