{
  "type": "Feature",
  "properties": {
    "gn:admin1_code":"11",
    "gn:admin2_code":"37.0",
    "gn:asciiname":"Los Alfaro (Menores)",
    "gn:country_code":"MX",
    "gn:dem":1776,
    "gn:feature_class":"P",
    "gn:feature_code":"PPL",
    "gn:name":"Los Alfaro (Menores)",
    "gn:population":59,
    "gn:timezone":"America/Mexico_City",
    "iso:country":"MX",
    "wof:name":"Los Alfaro (Menores)",
    "wof:placetype":"locality",
    "wof:population":59
},
  "geometry": {"coordinates":[-101.39221999999999,20.91472000000001],"type":"Point"}
}