{
  "type": "Feature",
  "properties": {
    "gn:admin1_code":"7",
    "gn:admin2_code":"20.0",
    "gn:asciiname":"Antonio Jimenez Morales",
    "gn:country_code":"MX",
    "gn:dem":478,
    "gn:feature_class":"P",
    "gn:feature_code":"PPL",
    "gn:name":"Antonio Jim\u00e9nez Morales",
    "gn:population":4,
    "gn:timezone":"America/Monterrey",
    "iso:country":"MX",
    "name:und_x_variant":[
        "Antonio Jim\u00e9nez Morales"
    ],
    "wof:name":"Antonio Jimenez Morales",
    "wof:placetype":"locality",
    "wof:population":4
},
  "geometry": {"coordinates":[-101.4836,27.8717],"type":"Point"}
}