{
  "type": "Feature",
  "properties": {
    "gn:admin1_code":"28.0",
    "gn:admin2_code":"38.0",
    "gn:asciiname":"Cruz Chica",
    "gn:country_code":"MX",
    "gn:dem":5,
    "gn:feature_class":"P",
    "gn:feature_code":"PPL",
    "gn:name":"Cruz Chica",
    "gn:population":0,
    "gn:timezone":"America/Monterrey",
    "iso:country":"MX",
    "name:spa_x_preferred":[
        "Cruz Chica"
    ],
    "wof:name":"Cruz Chica",
    "wof:placetype":"locality"
},
  "geometry": {"coordinates":[-97.92323,22.27772],"type":"Point"}
}