{
  "type": "Feature",
  "properties": {
    "gn:admin1_code":"15",
    "gn:admin2_code":"43.0",
    "gn:asciiname":"Barrio San Bartolo",
    "gn:country_code":"MX",
    "gn:dem":2724,
    "gn:feature_class":"P",
    "gn:feature_code":"PPL",
    "gn:name":"Barrio San Bartolo",
    "gn:population":386,
    "gn:timezone":"America/Mexico_City",
    "iso:country":"MX",
    "wof:name":"Barrio San Bartolo",
    "wof:placetype":"locality",
    "wof:population":386
},
  "geometry": {"coordinates":[-99.435,19.18533],"type":"Point"}
}