{
  "type": "Feature",
  "properties": {
    "gn:admin1_code":"16.0",
    "gn:admin2_code":"81.0",
    "gn:asciiname":"El Ciriansito",
    "gn:country_code":"MX",
    "gn:dem":777,
    "gn:feature_class":"P",
    "gn:feature_code":"PPL",
    "gn:name":"El Ciriansito",
    "gn:population":0,
    "gn:timezone":"America/Mexico_City",
    "iso:country":"MX",
    "name:spa_x_preferred":[
        "El Ciriansito"
    ],
    "wof:name":"El Ciriansito",
    "wof:placetype":"locality"
},
  "geometry": {"coordinates":[-100.40714,19.10842],"type":"Point"}
}