{
  "type": "Feature",
  "properties": {
    "gn:admin1_code":"2",
    "gn:admin2_code":"4",
    "gn:asciiname":"San Fernando [Establo]",
    "gn:country_code":"MX",
    "gn:dem":169,
    "gn:feature_class":"P",
    "gn:feature_code":"PPL",
    "gn:name":"San Fernando [Establo]",
    "gn:population":29,
    "gn:timezone":"America/Tijuana",
    "iso:country":"MX",
    "wof:name":"San Fernando [Establo]",
    "wof:placetype":"locality",
    "wof:population":29
},
  "geometry": {"coordinates":[-116.81471999999999,32.48972],"type":"Point"}
}