{
  "type": "Feature",
  "properties": {
    "gn:admin1_code":"24.0",
    "gn:admin2_code":"21.0",
    "gn:asciiname":"El Jaralito",
    "gn:country_code":"MX",
    "gn:dem":1943,
    "gn:feature_class":"P",
    "gn:feature_code":"PPL",
    "gn:name":"El Jaralito",
    "gn:population":0,
    "gn:timezone":"America/Mexico_City",
    "iso:country":"MX",
    "name:spa_x_preferred":[
        "El Jaralito"
    ],
    "name:und_x_variant":[
        "Jaral",
        "El Jaral"
    ],
    "wof:name":"El Jaralito",
    "wof:placetype":"locality"
},
  "geometry": {"coordinates":[-101.04902,22.1999],"type":"Point"}
}