{
  "type": "Feature",
  "properties": {
    "gn:admin1_code":"13",
    "gn:admin2_code":"53.0",
    "gn:asciiname":"Medio Monte",
    "gn:country_code":"MX",
    "gn:dem":1850,
    "gn:feature_class":"P",
    "gn:feature_code":"PPL",
    "gn:name":"Medio Monte",
    "gn:population":69,
    "gn:timezone":"America/Mexico_City",
    "iso:country":"MX",
    "wof:name":"Medio Monte",
    "wof:placetype":"locality",
    "wof:population":69
},
  "geometry": {"coordinates":[-98.2385,20.41436],"type":"Point"}
}