{
  "type": "Feature",
  "properties": {
    "gn:admin1_code":"6",
    "gn:admin2_code":"63.0",
    "gn:asciiname":"Sehuaybo",
    "gn:country_code":"MX",
    "gn:dem":2513,
    "gn:feature_class":"P",
    "gn:feature_code":"PPL",
    "gn:name":"Sehuaybo",
    "gn:population":0,
    "gn:timezone":"America/Chihuahua",
    "iso:country":"MX",
    "name:und_x_variant":[
        "Rancho Sehuaybo",
        "Sehuayvo",
        "Seguayvo",
        "Sehuaybo"
    ],
    "wof:name":"Sehuaybo",
    "wof:placetype":"locality"
},
  "geometry": {"coordinates":[-108.22987999999999,28.59574000000001],"type":"Point"}
}