{
  "type": "Feature",
  "properties": {
    "gn:admin1_code":"12",
    "gn:admin2_code":"32.0",
    "gn:asciiname":"Izotepec",
    "gn:country_code":"MX",
    "gn:dem":1364,
    "gn:feature_class":"P",
    "gn:feature_code":"PPL",
    "gn:name":"Izotepec",
    "gn:population":1232,
    "gn:timezone":"America/Mexico_City",
    "iso:country":"MX",
    "wof:name":"Izotepec",
    "wof:placetype":"locality",
    "wof:population":1232
},
  "geometry": {"coordinates":[-99.95444000000001,17.585],"type":"Point"}
}