{
  "type": "Feature",
  "properties": {
    "gn:admin1_code":"6",
    "gn:admin2_code":"62.0",
    "gn:asciiname":"Las Elenas",
    "gn:country_code":"MX",
    "gn:dem":1196,
    "gn:feature_class":"P",
    "gn:feature_code":"PPL",
    "gn:name":"Las Elenas",
    "gn:population":0,
    "gn:timezone":"America/Chihuahua",
    "iso:country":"MX",
    "name:spa_x_preferred":[
        "Las Elenas"
    ],
    "wof:name":"Las Elenas",
    "wof:placetype":"locality"
},
  "geometry": {"coordinates":[-105.30009,28.0237],"type":"Point"}
}