{
  "type": "Feature",
  "properties": {
    "gn:admin1_code":"5",
    "gn:admin2_code":"89.0",
    "gn:asciiname":"Toquian Chiquito",
    "gn:country_code":"MX",
    "gn:dem":809,
    "gn:feature_class":"P",
    "gn:feature_code":"PPL",
    "gn:name":"Toqui\u00e1n Chiquito",
    "gn:population":189,
    "gn:timezone":"America/Mexico_City",
    "iso:country":"MX",
    "name:und_x_variant":[
        "Toqui\u00e1n Chiquito"
    ],
    "wof:name":"Toquian Chiquito",
    "wof:placetype":"locality",
    "wof:population":189
},
  "geometry": {"coordinates":[-92.28834999999999,15.14863],"type":"Point"}
}