{
  "type": "Feature",
  "properties": {
    "gn:admin1_code":"30.0",
    "gn:asciiname":"El Transbordador",
    "gn:country_code":"MX",
    "gn:dem":7,
    "gn:feature_class":"P",
    "gn:feature_code":"PPL",
    "gn:name":"El Transbordador",
    "gn:population":0,
    "gn:timezone":"America/Mexico_City",
    "iso:country":"MX",
    "name:spa_x_preferred":[
        "El Transbordador"
    ],
    "wof:name":"El Transbordador",
    "wof:placetype":"locality"
},
  "geometry": {"coordinates":[-95.48085,18.46197],"type":"Point"}
}