{
  "type": "Feature",
  "properties": {
    "gn:admin1_code":"20",
    "gn:admin2_code":"415",
    "gn:asciiname":"Santa Ana",
    "gn:country_code":"MX",
    "gn:dem":486,
    "gn:feature_class":"P",
    "gn:feature_code":"PPL",
    "gn:name":"Santa Ana",
    "gn:population":12,
    "gn:timezone":"America/Mexico_City",
    "iso:country":"MX",
    "name:afr_x_preferred":[
        "Santa Ana"
    ],
    "name:ara_x_preferred":[
        "\u0633\u0627\u0646\u062a\u0627 \u0622\u0646\u0627"
    ],
    "name:bre_x_preferred":[
        "Santa Ana"
    ],
    "name:bul_x_preferred":[
        "\u0421\u0430\u043d\u0442\u0430 \u0410\u043d\u0430"
    ],
    "name:cat_x_preferred":[
        "Santa Ana"
    ],
    "name:ceb_x_preferred":[
        "Santa Ana"
    ],
    "name:deu_x_preferred":[
        "Santa Ana"
    ],
    "name:epo_x_preferred":[
        "Santa Ana"
    ],
    "name:fas_x_preferred":[
        "\u0633\u0627\u0646\u062a\u0627 \u0622\u0646\u0627"
    ],
    "name:fin_x_preferred":[
        "Santa Ana"
    ],
    "name:fra_x_preferred":[
        "Santa Ana"
    ],
    "name:glg_x_preferred":[
        "Santa Ana"
    ],
    "name:heb_x_preferred":[
        "\u05e1\u05e0\u05d8\u05d4 \u05d0\u05e0\u05d4"
    ],
    "name:hun_x_preferred":[
        "Santa Ana"
    ],
    "name:hye_x_preferred":[
        "\u054d\u0561\u0576\u057f\u0561 \u0531\u0576\u0561"
    ],
    "name:ilo_x_preferred":[
        "Santa Ana"
    ],
    "name:ita_x_preferred":[
        "Santa Ana"
    ],
    "name:jpn_x_preferred":[
        "\u30b5\u30f3\u30bf\u30a2\u30ca"
    ],
    "name:kat_x_preferred":[
        "\u10e1\u10d0\u10dc\u10e2\u10d0-\u10d0\u10dc\u10d0"
    ],
    "name:kor_x_preferred":[
        "\uc0b0\ud0c0\uc544\ub098"
    ],
    "name:lav_x_preferred":[
        "Santaana"
    ],
    "name:lit_x_preferred":[
        "Santa Ana"
    ],
    "name:nah_x_preferred":[
        "Santa Ana"
    ],
    "name:nds_x_preferred":[
        "Santa Ana"
    ],
    "name:nld_x_preferred":[
        "Santa Ana"
    ],
    "name:pnb_x_preferred":[
        "\u0633\u0627\u0646\u0679\u0627 \u0627\u06cc\u0646\u0627"
    ],
    "name:pol_x_preferred":[
        "Santa Ana"
    ],
    "name:por_x_preferred":[
        "Santa Ana"
    ],
    "name:que_x_preferred":[
        "Santa Ana"
    ],
    "name:rus_x_preferred":[
        "\u0421\u0430\u043d\u0442\u0430-\u0410\u043d\u0430"
    ],
    "name:sco_x_preferred":[
        "Santa Ana"
    ],
    "name:slk_x_preferred":[
        "Santa Ana"
    ],
    "name:spa_x_preferred":[
        "Santa Ana"
    ],
    "name:srp_x_preferred":[
        "\u0421\u0430\u043d\u0442\u0430 \u0410\u043d\u0430"
    ],
    "name:swe_x_preferred":[
        "Santa Ana"
    ],
    "name:ukr_x_preferred":[
        "\u0421\u0430\u043d\u0442\u0430-\u0410\u043d\u0430"
    ],
    "name:vie_x_preferred":[
        "Santa Ana"
    ],
    "name:war_x_preferred":[
        "Santa Ana"
    ],
    "wof:name":"Santa Ana",
    "wof:placetype":"locality",
    "wof:population":12
},
  "geometry": {"coordinates":[-98.03778,16.65167000000001],"type":"Point"}
}