{
  "type": "Feature",
  "properties": {
    "gn:admin1_code":"30.0",
    "gn:admin2_code":"155.0",
    "gn:asciiname":"Guayabal Mata del Tigre",
    "gn:country_code":"MX",
    "gn:dem":136,
    "gn:feature_class":"P",
    "gn:feature_code":"PPL",
    "gn:name":"Guayabal Mata del Tigre",
    "gn:population":216,
    "gn:timezone":"America/Mexico_City",
    "iso:country":"MX",
    "name:spa_x_preferred":[
        "Guayabal Mata del Tigre"
    ],
    "wof:name":"Guayabal Mata del Tigre",
    "wof:placetype":"locality",
    "wof:population":216
},
  "geometry": {"coordinates":[-98.25241,21.40164],"type":"Point"}
}