{
  "type": "Feature",
  "properties": {
    "gn:admin1_code":"7.0",
    "gn:admin2_code":"2.0",
    "gn:asciiname":"El Utero",
    "gn:country_code":"MX",
    "gn:dem":285,
    "gn:feature_class":"P",
    "gn:feature_code":"PPL",
    "gn:name":"El Utero",
    "gn:population":0,
    "gn:timezone":"America/Matamoros",
    "iso:country":"MX",
    "name:spa_x_preferred":[
        "El Utero"
    ],
    "wof:name":"El Utero",
    "wof:placetype":"locality"
},
  "geometry": {"coordinates":[-100.96823000000001,29.31591],"type":"Point"}
}