{
  "type": "Feature",
  "properties": {
    "gn:admin1_code":"15",
    "gn:admin2_code":"119.0",
    "gn:asciiname":"Llano del Copal",
    "gn:country_code":"MX",
    "gn:dem":1750,
    "gn:feature_class":"P",
    "gn:feature_code":"PPL",
    "gn:name":"Llano del Copal",
    "gn:population":287,
    "gn:timezone":"America/Mexico_City",
    "iso:country":"MX",
    "wof:name":"Llano del Copal",
    "wof:placetype":"locality",
    "wof:population":287
},
  "geometry": {"coordinates":[-99.60167,18.86083],"type":"Point"}
}