{
  "type": "Feature",
  "properties": {
    "gn:admin1_code":"14",
    "gn:admin2_code":"72",
    "gn:asciiname":"Vista Hermosa",
    "gn:country_code":"MX",
    "gn:dem":2040,
    "gn:feature_class":"P",
    "gn:feature_code":"PPL",
    "gn:name":"Vista Hermosa",
    "gn:population":14,
    "gn:timezone":"America/Mexico_City",
    "iso:country":"MX",
    "name:ceb_x_preferred":[
        "Vista Hermosa"
    ],
    "name:deu_x_preferred":[
        "Vista Hermosa"
    ],
    "name:spa_x_preferred":[
        "Vista Hermosa"
    ],
    "name:swe_x_preferred":[
        "Vista Hermosa"
    ],
    "name:vie_x_preferred":[
        "Vista Hermosa"
    ],
    "wof:name":"Vista Hermosa",
    "wof:placetype":"locality",
    "wof:population":14
},
  "geometry": {"coordinates":[-102.11444,20.97778],"type":"Point"}
}