{
  "type": "Feature",
  "properties": {
    "gn:admin1_code":"27",
    "gn:admin2_code":"11.0",
    "gn:asciiname":"Monte Grande (El Pastal)",
    "gn:country_code":"MX",
    "gn:dem":0,
    "gn:feature_class":"P",
    "gn:feature_code":"PPL",
    "gn:name":"Monte Grande (El Pastal)",
    "gn:population":58,
    "gn:timezone":"America/Mexico_City",
    "iso:country":"MX",
    "wof:name":"Monte Grande (El Pastal)",
    "wof:placetype":"locality",
    "wof:population":58
},
  "geometry": {"coordinates":[-92.31028000000001,17.97111],"type":"Point"}
}