{
  "type": "Feature",
  "properties": {
    "gn:admin1_code":"7",
    "gn:admin2_code":"35.0",
    "gn:asciiname":"La Conchita Roja",
    "gn:country_code":"MX",
    "gn:dem":1123,
    "gn:feature_class":"P",
    "gn:feature_code":"PPL",
    "gn:name":"La Conchita Roja",
    "gn:population":177,
    "gn:timezone":"America/Monterrey",
    "iso:country":"MX",
    "wof:name":"La Conchita Roja",
    "wof:placetype":"locality",
    "wof:population":177
},
  "geometry": {"coordinates":[-103.40582999999999,25.64056],"type":"Point"}
}