{
  "type": "Feature",
  "properties": {
    "gn:admin1_code":"30",
    "gn:admin2_code":"159.0",
    "gn:asciiname":"Achichipico",
    "gn:country_code":"MX",
    "gn:dem":2003,
    "gn:feature_class":"P",
    "gn:feature_code":"PPL",
    "gn:name":"Achichipico",
    "gn:population":0,
    "gn:timezone":"America/Mexico_City",
    "iso:country":"MX",
    "name:spa_x_preferred":[
        "Achichipico"
    ],
    "wof:name":"Achichipico",
    "wof:placetype":"locality"
},
  "geometry": {"coordinates":[-96.99923,18.54424],"type":"Point"}
}