{
  "type": "Feature",
  "properties": {
    "gn:admin1_code":"12",
    "gn:admin2_code":"40.0",
    "gn:asciiname":"Iyotla",
    "gn:country_code":"MX",
    "gn:dem":1404,
    "gn:feature_class":"P",
    "gn:feature_code":"PPL",
    "gn:name":"Iyotla",
    "gn:population":0,
    "gn:timezone":"America/Mexico_City",
    "iso:country":"MX",
    "name:und_x_variant":[
        "Ayotla",
        "Iyotla"
    ],
    "wof:name":"Iyotla",
    "wof:placetype":"locality"
},
  "geometry": {"coordinates":[-99.74778000000001,17.62183],"type":"Point"}
}