{
  "type": "Feature",
  "properties": {
    "gn:admin1_code":"5.0",
    "gn:asciiname":"El Gutierrito",
    "gn:country_code":"MX",
    "gn:dem":8,
    "gn:feature_class":"P",
    "gn:feature_code":"PPL",
    "gn:name":"El Gutierrito",
    "gn:population":0,
    "gn:timezone":"America/Mexico_City",
    "iso:country":"MX",
    "name:spa_x_preferred":[
        "El Gutierrito"
    ],
    "wof:name":"El Gutierrito",
    "wof:placetype":"locality"
},
  "geometry": {"coordinates":[-93.71956,15.89561],"type":"Point"}
}