{
  "type": "Feature",
  "properties": {
    "gn:admin1_code":"22",
    "gn:admin2_code":"5",
    "gn:asciiname":"El Leoncito",
    "gn:country_code":"MX",
    "gn:dem":2020,
    "gn:feature_class":"P",
    "gn:feature_code":"PPL",
    "gn:name":"El Leoncito",
    "gn:population":19,
    "gn:timezone":"America/Mexico_City",
    "iso:country":"MX",
    "name:ceb_x_preferred":[
        "El Leoncito"
    ],
    "name:fra_x_preferred":[
        "El Leoncito"
    ],
    "name:ita_x_preferred":[
        "El Leoncito"
    ],
    "name:spa_x_preferred":[
        "El Leoncito"
    ],
    "name:swe_x_preferred":[
        "El Leoncito"
    ],
    "wof:name":"El Leoncito",
    "wof:placetype":"locality",
    "wof:population":19
},
  "geometry": {"coordinates":[-100.04722,20.72806],"type":"Point"}
}