{
  "type": "Feature",
  "properties": {
    "gn:admin1_code":"30.0",
    "gn:admin2_code":"161.0",
    "gn:asciiname":"Rancho Taipan",
    "gn:country_code":"MX",
    "gn:dem":104,
    "gn:feature_class":"P",
    "gn:feature_code":"PPL",
    "gn:name":"Rancho Taip\u00e1n",
    "gn:population":0,
    "gn:timezone":"America/Mexico_City",
    "iso:country":"MX",
    "name:spa_x_preferred":[
        "Rancho Taip\u00e1n"
    ],
    "wof:name":"Rancho Taipan",
    "wof:placetype":"locality"
},
  "geometry": {"coordinates":[-98.26116,21.63058],"type":"Point"}
}