{
  "type": "Feature",
  "properties": {
    "gn:admin1_code":"25",
    "gn:admin2_code":"18.0",
    "gn:asciiname":"Casa Blanca (Angeles Dos)",
    "gn:country_code":"MX",
    "gn:dem":6,
    "gn:feature_class":"P",
    "gn:feature_code":"PPL",
    "gn:name":"Casa Blanca (\u00c1ngeles Dos)",
    "gn:population":417,
    "gn:timezone":"America/Mazatlan",
    "iso:country":"MX",
    "wof:name":"Casa Blanca (Angeles Dos)",
    "wof:placetype":"locality",
    "wof:population":417
},
  "geometry": {"coordinates":[-107.89122999999999,24.82137],"type":"Point"}
}