{
  "type": "Feature",
  "properties": {
    "gn:admin1_code":"30",
    "gn:admin2_code":"101",
    "gn:asciiname":"Tepoxtlan (Alpesur) [Granja]",
    "gn:country_code":"MX",
    "gn:dem":1505,
    "gn:feature_class":"P",
    "gn:feature_code":"PPL",
    "gn:name":"Tepoxtl\u00e1n (Alpesur) [Granja]",
    "gn:population":17,
    "gn:timezone":"America/Mexico_City",
    "iso:country":"MX",
    "name:und_x_variant":[
        "Tepoxtl\u00e1n (Alpesur) [Granja]"
    ],
    "wof:name":"Tepoxtlan (Alpesur) [Granja]",
    "wof:placetype":"locality",
    "wof:population":17
},
  "geometry": {"coordinates":[-97.13388999999999,18.90861],"type":"Point"}
}