{
  "type": "Feature",
  "properties": {
    "gn:admin1_code":"23.0",
    "gn:asciiname":"Jose Amaro",
    "gn:country_code":"MX",
    "gn:dem":10,
    "gn:feature_class":"P",
    "gn:feature_code":"PPL",
    "gn:name":"Jos\u00e9 Amaro",
    "gn:population":0,
    "gn:timezone":"America/Cancun",
    "iso:country":"MX",
    "name:spa_x_preferred":[
        "Jos\u00e9 Amaro"
    ],
    "wof:name":"Jose Amaro",
    "wof:placetype":"locality"
},
  "geometry": {"coordinates":[-88.24366999999999,18.57229],"type":"Point"}
}