{
  "type": "Feature",
  "properties": {
    "gn:admin1_code":"20",
    "gn:admin2_code":"68",
    "gn:asciiname":"La Cofradia",
    "gn:country_code":"MX",
    "gn:dem":1544,
    "gn:feature_class":"P",
    "gn:feature_code":"PPL",
    "gn:name":"La Cofrad\u00eda",
    "gn:population":18,
    "gn:timezone":"America/Mexico_City",
    "iso:country":"MX",
    "name:und_x_variant":[
        "La Cofrad\u00eda"
    ],
    "wof:name":"La Cofradia",
    "wof:placetype":"locality",
    "wof:population":18
},
  "geometry": {"coordinates":[-96.64583,16.7875],"type":"Point"}
}