{
  "type": "Feature",
  "properties": {
    "gn:admin1_code":"11.0",
    "gn:asciiname":"La Chinela",
    "gn:country_code":"MX",
    "gn:dem":1764,
    "gn:feature_class":"P",
    "gn:feature_code":"PPL",
    "gn:name":"La Chinela",
    "gn:population":0,
    "gn:timezone":"America/Mexico_City",
    "iso:country":"MX",
    "name:spa_x_preferred":[
        "La Chinela"
    ],
    "wof:name":"La Chinela",
    "wof:placetype":"locality"
},
  "geometry": {"coordinates":[-101.81204,20.96774],"type":"Point"}
}