{
  "type": "Feature",
  "properties": {
    "gn:admin1_code":"23",
    "gn:admin2_code":"2.0",
    "gn:asciiname":"Tik",
    "gn:country_code":"MX",
    "gn:dem":20,
    "gn:feature_class":"P",
    "gn:feature_code":"PPL",
    "gn:name":"Tik",
    "gn:population":0,
    "gn:timezone":"America/Cancun",
    "iso:country":"MX",
    "name:hat_x_preferred":[
        "Tik"
    ],
    "name:srp_x_preferred":[
        "\u0422\u0438\u043a"
    ],
    "name:tur_x_preferred":[
        "Tik"
    ],
    "wof:name":"Tik",
    "wof:placetype":"locality"
},
  "geometry": {"coordinates":[-88.15000000000001,19.91667],"type":"Point"}
}