{
  "type": "Feature",
  "properties": {
    "gn:admin1_code":"30",
    "gn:admin2_code":"71",
    "gn:asciiname":"Mesa de Ixotla",
    "gn:country_code":"MX",
    "gn:dem":1406,
    "gn:feature_class":"P",
    "gn:feature_code":"PPL",
    "gn:name":"Mesa de Ixotla",
    "gn:population":10,
    "gn:timezone":"America/Mexico_City",
    "iso:country":"MX",
    "wof:name":"Mesa de Ixotla",
    "wof:placetype":"locality",
    "wof:population":10
},
  "geometry": {"coordinates":[-96.96944000000001,19.17028],"type":"Point"}
}