{
  "type": "Feature",
  "properties": {
    "gn:admin1_code":"5.0",
    "gn:asciiname":"Flor Blanca",
    "gn:country_code":"MX",
    "gn:dem":882,
    "gn:feature_class":"P",
    "gn:feature_code":"PPL",
    "gn:name":"Flor Blanca",
    "gn:population":0,
    "gn:timezone":"America/Mexico_City",
    "iso:country":"MX",
    "name:spa_x_preferred":[
        "Flor Blanca"
    ],
    "wof:name":"Flor Blanca",
    "wof:placetype":"locality"
},
  "geometry": {"coordinates":[-93.04401,15.92695],"type":"Point"}
}