{
  "type": "Feature",
  "properties": {
    "gn:admin1_code":"28.0",
    "gn:admin2_code":"5.0",
    "gn:asciiname":"Los Encinos",
    "gn:country_code":"MX",
    "gn:dem":213,
    "gn:feature_class":"P",
    "gn:feature_code":"PPL",
    "gn:name":"Los Encinos",
    "gn:population":0,
    "gn:timezone":"America/Monterrey",
    "iso:country":"MX",
    "name:spa_x_preferred":[
        "Los Encinos"
    ],
    "wof:name":"Los Encinos",
    "wof:placetype":"locality"
},
  "geometry": {"coordinates":[-98.79111,24.90861],"type":"Point"}
}