{
  "type": "Feature",
  "properties": {
    "gn:admin1_code":"32",
    "gn:admin2_code":"26.0",
    "gn:asciiname":"San Ignacio",
    "gn:country_code":"MX",
    "gn:dem":1842,
    "gn:feature_class":"P",
    "gn:feature_code":"PPL",
    "gn:name":"San Ignacio",
    "gn:population":0,
    "gn:timezone":"America/Mexico_City",
    "iso:country":"MX",
    "name:spa_x_preferred":[
        "San Ignacio"
    ],
    "wof:name":"San Ignacio",
    "wof:placetype":"locality"
},
  "geometry": {"coordinates":[-101.94044,24.01517],"type":"Point"}
}