{
  "type": "Feature",
  "properties": {
    "gn:admin1_code":"11.0",
    "gn:admin2_code":"20.0",
    "gn:asciiname":"Madronos",
    "gn:country_code":"MX",
    "gn:dem":2409,
    "gn:feature_class":"P",
    "gn:feature_code":"PPL",
    "gn:name":"Madro\u00f1os",
    "gn:population":0,
    "gn:timezone":"America/Mexico_City",
    "iso:country":"MX",
    "name:spa_x_preferred":[
        "Madro\u00f1os"
    ],
    "wof:name":"Madronos",
    "wof:placetype":"locality"
},
  "geometry": {"coordinates":[-101.48099999999999,21.23599],"type":"Point"}
}