{
  "type": "Feature",
  "properties": {
    "gn:admin1_code":"15",
    "gn:admin2_code":"35.0",
    "gn:asciiname":"Rancho el Rocio (El Jardin)",
    "gn:country_code":"MX",
    "gn:dem":2262,
    "gn:feature_class":"P",
    "gn:feature_code":"PPL",
    "gn:name":"Rancho el Roc\u00edo (El Jard\u00edn)",
    "gn:population":5,
    "gn:timezone":"America/Mexico_City",
    "iso:country":"MX",
    "name:und_x_variant":[
        "Rancho el Roc\u00edo (El Jard\u00edn)"
    ],
    "wof:name":"Rancho el Rocio (El Jardin)",
    "wof:placetype":"locality",
    "wof:population":5
},
  "geometry": {"coordinates":[-99.19453,19.84778],"type":"Point"}
}