{
  "type": "Feature",
  "properties": {
    "gn:admin1_code":"19",
    "gn:admin2_code":"17.0",
    "gn:asciiname":"La Deshidratadora",
    "gn:country_code":"MX",
    "gn:dem":1884,
    "gn:feature_class":"P",
    "gn:feature_code":"PPL",
    "gn:name":"La Deshidratadora",
    "gn:population":5,
    "gn:timezone":"America/Monterrey",
    "iso:country":"MX",
    "wof:name":"La Deshidratadora",
    "wof:placetype":"locality",
    "wof:population":5
},
  "geometry": {"coordinates":[-100.55417,24.97895],"type":"Point"}
}