{
  "type": "Feature",
  "properties": {
    "gn:admin1_code":"5",
    "gn:admin2_code":"39.0",
    "gn:asciiname":"El Remolino",
    "gn:country_code":"MX",
    "gn:dem":136,
    "gn:feature_class":"P",
    "gn:feature_code":"PPL",
    "gn:name":"El Remolino",
    "gn:population":100,
    "gn:timezone":"America/Mexico_City",
    "iso:country":"MX",
    "name:fra_x_preferred":[
        "El Remolino"
    ],
    "name:spa_x_preferred":[
        "El Remolino"
    ],
    "wof:name":"El Remolino",
    "wof:placetype":"locality",
    "wof:population":100
},
  "geometry": {"coordinates":[-92.69499999999999,17.28833],"type":"Point"}
}