{
  "type": "Feature",
  "properties": {
    "gn:admin1_code":"30",
    "gn:admin2_code":"187.0",
    "gn:asciiname":"Piedras Grandes",
    "gn:country_code":"MX",
    "gn:dem":1817,
    "gn:feature_class":"P",
    "gn:feature_code":"PPL",
    "gn:name":"Piedras Grandes",
    "gn:population":576,
    "gn:timezone":"America/Mexico_City",
    "iso:country":"MX",
    "wof:name":"Piedras Grandes",
    "wof:placetype":"locality",
    "wof:population":576
},
  "geometry": {"coordinates":[-96.91611,19.70056],"type":"Point"}
}