{
  "type": "Feature",
  "properties": {
    "gn:admin1_code":"14",
    "gn:admin2_code":"61",
    "gn:asciiname":"Pinos Altos",
    "gn:country_code":"MX",
    "gn:dem":2295,
    "gn:feature_class":"P",
    "gn:feature_code":"PPL",
    "gn:name":"Pinos Altos",
    "gn:population":24,
    "gn:timezone":"America/Mexico_City",
    "iso:country":"MX",
    "wof:name":"Pinos Altos",
    "wof:placetype":"locality",
    "wof:population":24
},
  "geometry": {"coordinates":[-104.05583,22.32889],"type":"Point"}
}