{
  "type": "Feature",
  "properties": {
    "gn:admin1_code":"6.0",
    "gn:admin2_code":"27.0",
    "gn:asciiname":"Corarachi",
    "gn:country_code":"MX",
    "gn:dem":2392,
    "gn:feature_class":"P",
    "gn:feature_code":"PPL",
    "gn:name":"Corarachi",
    "gn:population":0,
    "gn:timezone":"America/Chihuahua",
    "iso:country":"MX",
    "name:spa_x_preferred":[
        "Corarachi"
    ],
    "wof:name":"Corarachi",
    "wof:placetype":"locality"
},
  "geometry": {"coordinates":[-107.49896,27.54788],"type":"Point"}
}