{
  "type": "Feature",
  "properties": {
    "gn:admin1_code":"12.0",
    "gn:admin2_code":"71.0",
    "gn:asciiname":"Piedra del Toro",
    "gn:country_code":"MX",
    "gn:dem":873,
    "gn:feature_class":"P",
    "gn:feature_code":"PPL",
    "gn:name":"Piedra del Toro",
    "gn:population":0,
    "gn:timezone":"America/Mexico_City",
    "iso:country":"MX",
    "name:spa_x_preferred":[
        "Piedra del Toro"
    ],
    "wof:name":"Piedra del Toro",
    "wof:placetype":"locality"
},
  "geometry": {"coordinates":[-98.12990000000001,17.01809],"type":"Point"}
}