{
  "type": "Feature",
  "properties": {
    "gn:admin1_code":"30",
    "gn:admin2_code":"177.0",
    "gn:asciiname":"Omeapa",
    "gn:country_code":"MX",
    "gn:dem":2271,
    "gn:feature_class":"P",
    "gn:feature_code":"PPL",
    "gn:name":"Omeapa",
    "gn:population":295,
    "gn:timezone":"America/Mexico_City",
    "iso:country":"MX",
    "wof:name":"Omeapa",
    "wof:placetype":"locality",
    "wof:population":295
},
  "geometry": {"coordinates":[-97.03,19.71278],"type":"Point"}
}