{
  "type": "Feature",
  "properties": {
    "gn:admin1_code":"22",
    "gn:admin2_code":"14.0",
    "gn:asciiname":"Primero de Junio",
    "gn:country_code":"MX",
    "gn:dem":2010,
    "gn:feature_class":"P",
    "gn:feature_code":"PPL",
    "gn:name":"Primero de Junio",
    "gn:population":228,
    "gn:timezone":"America/Mexico_City",
    "iso:country":"MX",
    "wof:name":"Primero de Junio",
    "wof:placetype":"locality",
    "wof:population":228
},
  "geometry": {"coordinates":[-100.38583,20.6575],"type":"Point"}
}