{
  "type": "Feature",
  "properties": {
    "gn:admin1_code":"30",
    "gn:admin2_code":"6.0",
    "gn:asciiname":"Pinotla",
    "gn:country_code":"MX",
    "gn:dem":1757,
    "gn:feature_class":"P",
    "gn:feature_code":"PPL",
    "gn:name":"Pinotla",
    "gn:population":150,
    "gn:timezone":"America/Mexico_City",
    "iso:country":"MX",
    "wof:name":"Pinotla",
    "wof:placetype":"locality",
    "wof:population":150
},
  "geometry": {"coordinates":[-97.27194,18.70694],"type":"Point"}
}