{
  "type": "Feature",
  "properties": {
    "gn:admin1_code":"30",
    "gn:admin2_code":"89.0",
    "gn:asciiname":"San Silvestre",
    "gn:country_code":"MX",
    "gn:dem":23,
    "gn:feature_class":"P",
    "gn:feature_code":"PPL",
    "gn:name":"San Silvestre",
    "gn:population":5,
    "gn:timezone":"America/Mexico_City",
    "iso:country":"MX",
    "wof:name":"San Silvestre",
    "wof:placetype":"locality",
    "wof:population":5
},
  "geometry": {"coordinates":[-94.70944,17.90556],"type":"Point"}
}