{
  "type": "Feature",
  "properties": {
    "gn:admin1_code":"30",
    "gn:admin2_code":"89.0",
    "gn:asciiname":"San Silvestre",
    "gn:country_code":"MX",
    "gn:dem":23,
    "gn:feature_class":"P",
    "gn:feature_code":"PPL",
    "gn:name":"San Silvestre",
    "gn:population":5,
    "gn:timezone":"America/Mexico_City",
    "iso:country":"MX",
    "name:fra_x_preferred":[
        "San Silvestre"
    ],
    "name:glg_x_preferred":[
        "San Silvestre"
    ],
    "name:por_x_preferred":[
        "San Silvestre"
    ],
    "name:spa_x_preferred":[
        "San Silvestre"
    ],
    "name:srp_x_preferred":[
        "\u0421\u0430\u043d \u0421\u0438\u043b\u0432\u0435\u0441\u0442\u0440\u0435"
    ],
    "name:tgl_x_preferred":[
        "San Silvestre"
    ],
    "wof:name":"San Silvestre",
    "wof:placetype":"locality",
    "wof:population":5
},
  "geometry": {"coordinates":[-94.70944,17.90556],"type":"Point"}
}