{
  "type": "Feature",
  "properties": {
    "gn:admin1_code":"29",
    "gn:admin2_code":"52.0",
    "gn:asciiname":"Colonia Ecologica",
    "gn:country_code":"MX",
    "gn:dem":2626,
    "gn:feature_class":"P",
    "gn:feature_code":"PPL",
    "gn:name":"Colonia Ecol\u00f3gica",
    "gn:population":70,
    "gn:timezone":"America/Mexico_City",
    "iso:country":"MX",
    "name:und_x_variant":[
        "Colonia Ecol\u00f3gica"
    ],
    "wof:name":"Colonia Ecologica",
    "wof:placetype":"locality",
    "wof:population":70
},
  "geometry": {"coordinates":[-98.07511,19.33001],"type":"Point"}
}