{
  "type": "Feature",
  "properties": {
    "gn:admin1_code":"24",
    "gn:admin2_code":"17.0",
    "gn:asciiname":"La Carbonera",
    "gn:country_code":"MX",
    "gn:dem":1735,
    "gn:feature_class":"P",
    "gn:feature_code":"PPL",
    "gn:name":"La Carbonera",
    "gn:population":0,
    "gn:timezone":"America/Mexico_City",
    "iso:country":"MX",
    "wof:name":"La Carbonera",
    "wof:placetype":"locality"
},
  "geometry": {"coordinates":[-100.36306999999999,23.07313],"type":"Point"}
}