{
  "type": "Feature",
  "properties": {
    "gn:admin1_code":"10.0",
    "gn:admin2_code":"26.0",
    "gn:asciiname":"Cinco Senores",
    "gn:country_code":"MX",
    "gn:dem":1512,
    "gn:feature_class":"P",
    "gn:feature_code":"PPL",
    "gn:name":"Cinco Se\u00f1ores",
    "gn:population":4,
    "gn:timezone":"America/Monterrey",
    "iso:country":"MX",
    "wof:name":"Cinco Senores",
    "wof:placetype":"locality",
    "wof:population":4
},
  "geometry": {"coordinates":[-105.92337000000001,24.13972],"type":"Point"}
}