{
  "type": "Feature",
  "properties": {
    "gn:admin1_code":"19.0",
    "gn:admin2_code":"14.0",
    "gn:asciiname":"Presa de Guadalupe",
    "gn:country_code":"MX",
    "gn:dem":1724,
    "gn:feature_class":"P",
    "gn:feature_code":"PPL",
    "gn:name":"Presa de Guadalupe",
    "gn:population":0,
    "gn:timezone":"America/Monterrey",
    "iso:country":"MX",
    "name:spa_x_preferred":[
        "Presa de Guadalupe"
    ],
    "wof:name":"Presa de Guadalupe",
    "wof:placetype":"locality"
},
  "geometry": {"coordinates":[-100.43501999999999,24.10521],"type":"Point"}
}