{
  "type": "Feature",
  "properties": {
    "gn:country":"MX",
    "gn:fcode":"PPL",
    "gn:population":0,
    "iso:country":"MX",
    "name:ceb_x_preferred":[
        "Del Carmen"
    ],
    "name:deu_x_preferred":[
        "Del Carmen"
    ],
    "qs_pg:aaroncc":"MX",
    "qs_pg:gn_country":"MX",
    "qs_pg:gn_fcode":"PPL",
    "qs_pg:gn_pop":0,
    "qs_pg:name":"Del Carmen",
    "qs_pg:name_adm0":"M\u00e9xico",
    "qs_pg:name_adm1":"Aguascalientes",
    "qs_pg:photos":26,
    "qs_pg:photos_1k":5,
    "qs_pg:photos_9k":1,
    "qs_pg:photos_9r":2,
    "qs_pg:photos_all":26,
    "qs_pg:photos_sr":2,
    "qs_pg:pop_sr":0,
    "qs_pg:qs_pg_placetype":"neighbourhood",
    "qs_pg:qs_pg_placetype_gp":"Suburb",
    "qs_pg:woe_adm0":23424900,
    "woe:adm0_id":23424900,
    "woe:name_adm0":"M\u00e9xico",
    "woe:name_adm1":"Aguascalientes",
    "woe:placetype":"Suburb",
    "wof:name":"Del Carmen",
    "wof:placetype":"neighbourhood",
    "wof:population":10
},
  "geometry": {"coordinates":[-101.58333,22.26667],"type":"Point"}
}