{
  "type": "Feature",
  "properties": {
    "gn:admin1_code":"27",
    "gn:admin2_code":"17",
    "gn:asciiname":"El Faisan 3ra. Seccion (Chiniquija)",
    "gn:country_code":"MX",
    "gn:dem":34,
    "gn:feature_class":"P",
    "gn:feature_code":"PPL",
    "gn:name":"El Fais\u00e1n 3ra. Secci\u00f3n (Chiniquij\u00e1)",
    "gn:population":11,
    "gn:timezone":"America/Mexico_City",
    "iso:country":"MX",
    "name:und_x_variant":[
        "El Fais\u00e1n 3ra. Secci\u00f3n (Chiniquij\u00e1)"
    ],
    "wof:name":"El Faisan 3ra. Seccion (Chiniquija)",
    "wof:placetype":"locality",
    "wof:population":11
},
  "geometry": {"coordinates":[-91.51917,17.39944],"type":"Point"}
}