{
  "type": "Feature",
  "properties": {
    "gn:admin1_code":"10.0",
    "gn:admin2_code":"34.0",
    "gn:asciiname":"San Juan del Tecuan",
    "gn:country_code":"MX",
    "gn:dem":2450,
    "gn:feature_class":"P",
    "gn:feature_code":"PPL",
    "gn:name":"San Juan del Tecu\u00e1n",
    "gn:population":0,
    "gn:timezone":"America/Monterrey",
    "iso:country":"MX",
    "name:spa_x_preferred":[
        "San Juan del Tecu\u00e1n"
    ],
    "wof:name":"San Juan del Tecuan",
    "wof:placetype":"locality"
},
  "geometry": {"coordinates":[-106.96614,25.58154],"type":"Point"}
}