{
  "type": "Feature",
  "properties": {
    "gn:admin1_code":"18.0",
    "gn:admin2_code":"19.0",
    "gn:asciiname":"El Desmonte",
    "gn:country_code":"MX",
    "gn:dem":1826,
    "gn:feature_class":"P",
    "gn:feature_code":"PPL",
    "gn:name":"El Desmonte",
    "gn:population":0,
    "gn:timezone":"America/Mazatlan",
    "iso:country":"MX",
    "name:ceb_x_preferred":[
        "El Desmonte"
    ],
    "name:spa_x_preferred":[
        "El Desmonte"
    ],
    "wof:name":"El Desmonte",
    "wof:placetype":"locality"
},
  "geometry": {"coordinates":[-104.1836,21.71331],"type":"Point"}
}