{
  "type": "Feature",
  "properties": {
    "gn:admin1_code":"5.0",
    "gn:admin2_code":"107.0",
    "gn:asciiname":"La Rincon de la Cienega",
    "gn:country_code":"MX",
    "gn:dem":539,
    "gn:feature_class":"P",
    "gn:feature_code":"PPL",
    "gn:name":"La Rinc\u00f3n de la Ci\u00e9nega",
    "gn:population":0,
    "gn:timezone":"America/Mexico_City",
    "iso:country":"MX",
    "name:spa_x_preferred":[
        "El Rinc\u00f3n de la Ci\u00e9nega"
    ],
    "name:spa_x_variant":[
        "La Rinc\u00f3n de la Ci\u00e9nega"
    ],
    "wof:name":"La Rincon de la Cienega",
    "wof:placetype":"locality"
},
  "geometry": {"coordinates":[-92.98186,16.18004],"type":"Point"}
}