{
  "type": "Feature",
  "properties": {
    "gn:admin1_code":"28.0",
    "gn:admin2_code":"35.0",
    "gn:asciiname":"La Jaiba",
    "gn:country_code":"MX",
    "gn:dem":5,
    "gn:feature_class":"P",
    "gn:feature_code":"PPL",
    "gn:name":"La Jaiba",
    "gn:population":0,
    "gn:timezone":"America/Monterrey",
    "iso:country":"MX",
    "name:ita_x_preferred":[
        "La Jaiba"
    ],
    "name:spa_x_preferred":[
        "La Jaiba"
    ],
    "name:urd_x_preferred":[
        "\u0644\u0627 \u062c\u0627\u06cc\u0628\u0627"
    ],
    "wof:name":"La Jaiba",
    "wof:placetype":"locality"
},
  "geometry": {"coordinates":[-97.80274,24.80695],"type":"Point"}
}