{
  "type": "Feature",
  "properties": {
    "gn:admin1_code":"26.0",
    "gn:admin2_code":"4.0",
    "gn:asciiname":"Los Chiveros",
    "gn:country_code":"MX",
    "gn:dem":521,
    "gn:feature_class":"P",
    "gn:feature_code":"PPL",
    "gn:name":"Los Chiveros",
    "gn:population":0,
    "gn:timezone":"America/Hermosillo",
    "iso:country":"MX",
    "wof:name":"Los Chiveros",
    "wof:placetype":"locality"
},
  "geometry": {"coordinates":[-111.88987,30.88725],"type":"Point"}
}