{
  "type": "Feature",
  "properties": {
    "gn:admin1_code":"32",
    "gn:admin2_code":"10.0",
    "gn:asciiname":"El Tildio",
    "gn:country_code":"MX",
    "gn:dem":2470,
    "gn:feature_class":"P",
    "gn:feature_code":"PPL",
    "gn:name":"El Tildio",
    "gn:population":0,
    "gn:timezone":"America/Mexico_City",
    "iso:country":"MX",
    "name:spa_x_preferred":[
        "El Tildio"
    ],
    "wof:name":"El Tildio",
    "wof:placetype":"locality"
},
  "geometry": {"coordinates":[-103.47615999999999,23.27035],"type":"Point"}
}