{
  "type": "Feature",
  "properties": {
    "gn:admin1_code":"12",
    "gn:admin2_code":"71.0",
    "gn:asciiname":"Junta de Arroyo Grande",
    "gn:country_code":"MX",
    "gn:dem":835,
    "gn:feature_class":"P",
    "gn:feature_code":"PPL",
    "gn:name":"Junta de Arroyo Grande",
    "gn:population":0,
    "gn:timezone":"America/Mexico_City",
    "iso:country":"MX",
    "name:spa_x_preferred":[
        "Junta de Arroyo Grande"
    ],
    "wof:name":"Junta de Arroyo Grande",
    "wof:placetype":"locality"
},
  "geometry": {"coordinates":[-98.14133,16.81054],"type":"Point"}
}