{
  "type": "Feature",
  "properties": {
    "gn:admin1_code":"6.0",
    "gn:admin2_code":"27.0",
    "gn:asciiname":"Maquirachi",
    "gn:country_code":"MX",
    "gn:dem":2356,
    "gn:feature_class":"P",
    "gn:feature_code":"PPL",
    "gn:name":"Maquirachi",
    "gn:population":0,
    "gn:timezone":"America/Chihuahua",
    "iso:country":"MX",
    "name:spa_x_preferred":[
        "Maquirachi"
    ],
    "wof:name":"Maquirachi",
    "wof:placetype":"locality"
},
  "geometry": {"coordinates":[-107.50139,27.29447],"type":"Point"}
}