{
  "type": "Feature",
  "properties": {
    "gn:admin1_code":"5",
    "gn:admin2_code":"59",
    "gn:asciiname":"Las Margaritas (Santa Margarita)",
    "gn:country_code":"MX",
    "gn:dem":654,
    "gn:feature_class":"P",
    "gn:feature_code":"PPL",
    "gn:name":"Las Margaritas (Santa Margarita)",
    "gn:population":23,
    "gn:timezone":"America/Mexico_City",
    "iso:country":"MX",
    "wof:name":"Las Margaritas (Santa Margarita)",
    "wof:placetype":"locality",
    "wof:population":23
},
  "geometry": {"coordinates":[-91.65722,16.93889],"type":"Point"}
}