{
  "type": "Feature",
  "properties": {
    "gn:admin1_code":"32",
    "gn:admin2_code":"51.0",
    "gn:asciiname":"Familia Esparza",
    "gn:country_code":"MX",
    "gn:dem":1986,
    "gn:feature_class":"P",
    "gn:feature_code":"PPL",
    "gn:name":"Familia Esparza",
    "gn:population":5,
    "gn:timezone":"America/Mexico_City",
    "iso:country":"MX",
    "wof:name":"Familia Esparza",
    "wof:placetype":"locality",
    "wof:population":5
},
  "geometry": {"coordinates":[-102.26917,23.08333],"type":"Point"}
}