{
  "type": "Feature",
  "properties": {
    "gn:admin1_code":"25",
    "gn:admin2_code":"3.0",
    "gn:asciiname":"Alisos (Alisitos)",
    "gn:country_code":"MX",
    "gn:dem":867,
    "gn:feature_class":"P",
    "gn:feature_code":"PPL",
    "gn:name":"Alisos (Alisitos)",
    "gn:population":85,
    "gn:timezone":"America/Mazatlan",
    "iso:country":"MX",
    "wof:name":"Alisos (Alisitos)",
    "wof:placetype":"locality",
    "wof:population":85
},
  "geometry": {"coordinates":[-107.53539000000001,25.93038],"type":"Point"}
}