{
  "type": "Feature",
  "properties": {
    "gn:admin1_code":"5",
    "gn:admin2_code":"65.0",
    "gn:asciiname":"Tierra de Jehova (San Javier)",
    "gn:country_code":"MX",
    "gn:dem":47,
    "gn:feature_class":"P",
    "gn:feature_code":"PPL",
    "gn:name":"Tierra de Jehov\u00e1 (San Javier)",
    "gn:population":8,
    "gn:timezone":"America/Mexico_City",
    "iso:country":"MX",
    "name:und_x_variant":[
        "Tierra de Jehov\u00e1 (San Javier)"
    ],
    "wof:name":"Tierra de Jehova (San Javier)",
    "wof:placetype":"locality",
    "wof:population":8
},
  "geometry": {"coordinates":[-92.08083000000001,17.57972],"type":"Point"}
}