{
  "type": "Feature",
  "properties": {
    "gn:admin1_code":"19.0",
    "gn:admin2_code":"11.0",
    "gn:asciiname":"Los Higos",
    "gn:country_code":"MX",
    "gn:dem":301,
    "gn:feature_class":"P",
    "gn:feature_code":"PPL",
    "gn:name":"Los Higos",
    "gn:population":0,
    "gn:timezone":"America/Monterrey",
    "iso:country":"MX",
    "name:spa_x_preferred":[
        "Los Higos"
    ],
    "wof:name":"Los Higos",
    "wof:placetype":"locality"
},
  "geometry": {"coordinates":[-99.6551,26.14277],"type":"Point"}
}