{
  "type": "Feature",
  "properties": {
    "gn:admin1_code":"30",
    "gn:admin2_code":"163.0",
    "gn:asciiname":"Trojillas",
    "gn:country_code":"MX",
    "gn:dem":721,
    "gn:feature_class":"P",
    "gn:feature_code":"PPL",
    "gn:name":"Trojillas",
    "gn:population":137,
    "gn:timezone":"America/Mexico_City",
    "iso:country":"MX",
    "wof:name":"Trojillas",
    "wof:placetype":"locality",
    "wof:population":137
},
  "geometry": {"coordinates":[-96.95193999999999,19.85111],"type":"Point"}
}