{
  "type": "Feature",
  "properties": {
    "gn:admin1_code":"15",
    "gn:admin2_code":"112",
    "gn:asciiname":"Los Gutierrez",
    "gn:country_code":"MX",
    "gn:dem":2517,
    "gn:feature_class":"P",
    "gn:feature_code":"PPL",
    "gn:name":"Los Guti\u00e9rrez",
    "gn:population":24,
    "gn:timezone":"America/Mexico_City",
    "iso:country":"MX",
    "name:und_x_variant":[
        "Los Guti\u00e9rrez"
    ],
    "wof:name":"Los Gutierrez",
    "wof:placetype":"locality",
    "wof:population":24
},
  "geometry": {"coordinates":[-99.44589000000001,19.74328],"type":"Point"}
}