{
  "type": "Feature",
  "properties": {
    "gn:admin1_code":"28",
    "gn:admin2_code":"11.0",
    "gn:asciiname":"Gomez Farias",
    "gn:country_code":"MX",
    "gn:dem":80,
    "gn:feature_class":"P",
    "gn:feature_code":"PPLA2",
    "gn:name":"G\u00f3mez Far\u00edas",
    "gn:population":0,
    "gn:timezone":"America/Monterrey",
    "iso:country":"MX",
    "name:spa_x_preferred":[
        "G\u00f3mez Far\u00edas"
    ],
    "name:spa_x_variant":[
        "Loma Alta de G\u00f3mez Far\u00edas"
    ],
    "name:und_x_variant":[
        "G\u00f3mez Farias",
        "Loma Alta"
    ],
    "wof:name":"Gomez Farias",
    "wof:placetype":"locality"
},
  "geometry": {"coordinates":[-99.02612000000001,22.88371],"type":"Point"}
}