{
  "type": "Feature",
  "properties": {
    "gn:admin1_code":"7",
    "gn:admin2_code":"19",
    "gn:asciiname":"Campamento Venustiano Carranza",
    "gn:country_code":"MX",
    "gn:dem":339,
    "gn:feature_class":"P",
    "gn:feature_code":"PPL",
    "gn:name":"Campamento Venustiano Carranza",
    "gn:population":31,
    "gn:timezone":"America/Monterrey",
    "iso:country":"MX",
    "wof:name":"Campamento Venustiano Carranza",
    "wof:placetype":"locality",
    "wof:population":31
},
  "geometry": {"coordinates":[-100.81009,28.41608],"type":"Point"}
}