{
  "type": "Feature",
  "properties": {
    "gn:admin1_code":"1",
    "gn:admin2_code":"11.0",
    "gn:asciiname":"La Esperanza (Las Tuzas)",
    "gn:country_code":"MX",
    "gn:dem":1928,
    "gn:feature_class":"P",
    "gn:feature_code":"PPL",
    "gn:name":"La Esperanza (Las Tuzas)",
    "gn:population":4,
    "gn:timezone":"America/Mexico_City",
    "iso:country":"MX",
    "wof:name":"La Esperanza (Las Tuzas)",
    "wof:placetype":"locality",
    "wof:population":4
},
  "geometry": {"coordinates":[-102.24806,22.08583],"type":"Point"}
}