{
  "type": "Feature",
  "properties": {
    "gn:admin1_code":"26",
    "gn:admin2_code":"69.0",
    "gn:asciiname":"Los Jacales",
    "gn:country_code":"MX",
    "gn:dem":995,
    "gn:feature_class":"P",
    "gn:feature_code":"PPL",
    "gn:name":"Los Jacales",
    "gn:population":2,
    "gn:timezone":"America/Hermosillo",
    "iso:country":"MX",
    "name:spa_x_preferred":[
        "Los Jacales"
    ],
    "wof:name":"Los Jacales",
    "wof:placetype":"locality",
    "wof:population":2
},
  "geometry": {"coordinates":[-109.14667,28.51861],"type":"Point"}
}