{
  "type": "Feature",
  "properties": {
    "gn:admin1_code":"14",
    "gn:admin2_code":"13",
    "gn:asciiname":"La Loma de Piedras",
    "gn:country_code":"MX",
    "gn:dem":2012,
    "gn:feature_class":"P",
    "gn:feature_code":"PPL",
    "gn:name":"La Loma de Piedras",
    "gn:population":19,
    "gn:timezone":"America/Mexico_City",
    "iso:country":"MX",
    "wof:name":"La Loma de Piedras",
    "wof:placetype":"locality",
    "wof:population":19
},
  "geometry": {"coordinates":[-102.545,20.59944],"type":"Point"}
}