{
  "type": "Feature",
  "properties": {
    "gn:admin1_code":"15",
    "gn:admin2_code":"3.0",
    "gn:asciiname":"Los Ailes",
    "gn:country_code":"MX",
    "gn:dem":2664,
    "gn:feature_class":"P",
    "gn:feature_code":"PPL",
    "gn:name":"Los Ailes",
    "gn:population":0,
    "gn:timezone":"America/Mexico_City",
    "iso:country":"MX",
    "name:spa_x_preferred":[
        "Los Ailes"
    ],
    "wof:name":"Los Ailes",
    "wof:placetype":"locality"
},
  "geometry": {"coordinates":[-99.88558999999999,20.04288],"type":"Point"}
}