{
  "type": "Feature",
  "properties": {
    "gn:admin1_code":"16",
    "gn:admin2_code":"53.0",
    "gn:asciiname":"Tumbisca",
    "gn:country_code":"MX",
    "gn:dem":1761,
    "gn:feature_class":"P",
    "gn:feature_code":"PPL",
    "gn:name":"Tumbisca",
    "gn:population":218,
    "gn:timezone":"America/Mexico_City",
    "iso:country":"MX",
    "wof:name":"Tumbisca",
    "wof:placetype":"locality",
    "wof:population":218
},
  "geometry": {"coordinates":[-101.08139,19.58389],"type":"Point"}
}