{
  "type": "Feature",
  "properties": {
    "gn:admin1_code":"30",
    "gn:admin2_code":"108.0",
    "gn:asciiname":"Nuevo Atoyac",
    "gn:country_code":"MX",
    "gn:dem":33,
    "gn:feature_class":"P",
    "gn:feature_code":"PPL",
    "gn:name":"Nuevo Atoyac",
    "gn:population":0,
    "gn:timezone":"America/Mexico_City",
    "iso:country":"MX",
    "name:spa_x_preferred":[
        "Nuevo Atoyac"
    ],
    "wof:name":"Nuevo Atoyac",
    "wof:placetype":"locality"
},
  "geometry": {"coordinates":[-94.40402,17.65749],"type":"Point"}
}