{
  "type": "Feature",
  "properties": {
    "gn:admin1_code":"3.0",
    "gn:admin2_code":"8.0",
    "gn:asciiname":"El Rancho",
    "gn:country_code":"MX",
    "gn:dem":265,
    "gn:feature_class":"P",
    "gn:feature_code":"PPL",
    "gn:name":"El Rancho",
    "gn:population":0,
    "gn:timezone":"America/Mazatlan",
    "iso:country":"MX",
    "name:spa_x_preferred":[
        "El Rancho"
    ],
    "wof:name":"El Rancho",
    "wof:placetype":"locality"
},
  "geometry": {"coordinates":[-109.79161000000001,23.3851],"type":"Point"}
}