{
  "type": "Feature",
  "properties": {
    "gn:admin1_code":"19.0",
    "gn:admin2_code":"5.0",
    "gn:asciiname":"La Uno",
    "gn:country_code":"MX",
    "gn:dem":211,
    "gn:feature_class":"P",
    "gn:feature_code":"PPL",
    "gn:name":"La Uno",
    "gn:population":0,
    "gn:timezone":"America/Matamoros",
    "iso:country":"MX",
    "name:spa_x_preferred":[
        "La Uno"
    ],
    "wof:name":"La Uno",
    "wof:placetype":"locality"
},
  "geometry": {"coordinates":[-100.12116,27.26737],"type":"Point"}
}