{
  "type": "Feature",
  "properties": {
    "gn:admin1_code":"25.0",
    "gn:admin2_code":"16.0",
    "gn:asciiname":"Ixtitan",
    "gn:country_code":"MX",
    "gn:dem":322,
    "gn:feature_class":"P",
    "gn:feature_code":"PPL",
    "gn:name":"Ixtit\u00e1n",
    "gn:population":0,
    "gn:timezone":"America/Mazatlan",
    "iso:country":"MX",
    "wof:name":"Ixtitan",
    "wof:placetype":"locality"
},
  "geometry": {"coordinates":[-106.33333,23.96667],"type":"Point"}
}