{
  "type": "Feature",
  "properties": {
    "gn:admin1_code":"6",
    "gn:admin2_code":"11.0",
    "gn:asciiname":"Santa Elena",
    "gn:country_code":"MX",
    "gn:dem":1230,
    "gn:feature_class":"P",
    "gn:feature_code":"PPL",
    "gn:name":"Santa Elena",
    "gn:population":75,
    "gn:timezone":"America/Chihuahua",
    "iso:country":"MX",
    "wof:name":"Santa Elena",
    "wof:placetype":"locality",
    "wof:population":75
},
  "geometry": {"coordinates":[-105.24362000000001,27.65199],"type":"Point"}
}