{
  "type": "Feature",
  "properties": {
    "gn:admin1_code":"17",
    "gn:admin2_code":"29",
    "gn:asciiname":"El Basurero",
    "gn:country_code":"MX",
    "gn:dem":1232,
    "gn:feature_class":"P",
    "gn:feature_code":"PPL",
    "gn:name":"El Basurero",
    "gn:population":25,
    "gn:timezone":"America/Mexico_City",
    "iso:country":"MX",
    "wof:name":"El Basurero",
    "wof:placetype":"locality",
    "wof:population":25
},
  "geometry": {"coordinates":[-99.07028,18.91528],"type":"Point"}
}