{
  "type": "Feature",
  "properties": {
    "gn:admin1_code":"3.0",
    "gn:admin2_code":"3.0",
    "gn:asciiname":"El Novillo Chico",
    "gn:country_code":"MX",
    "gn:dem":104,
    "gn:feature_class":"P",
    "gn:feature_code":"PPL",
    "gn:name":"El Novillo Chico",
    "gn:population":0,
    "gn:timezone":"America/Mazatlan",
    "iso:country":"MX",
    "name:spa_x_preferred":[
        "El Novillo Chico"
    ],
    "name:spa_x_variant":[
        "El Novillo"
    ],
    "wof:name":"El Novillo Chico",
    "wof:placetype":"locality"
},
  "geometry": {"coordinates":[-110.339,23.93019],"type":"Point"}
}