{
  "type": "Feature",
  "properties": {
    "gn:admin1_code":"13",
    "gn:admin2_code":"2.0",
    "gn:asciiname":"Ejido Tlatzintla",
    "gn:country_code":"MX",
    "gn:dem":2109,
    "gn:feature_class":"P",
    "gn:feature_code":"PPL",
    "gn:name":"Ejido Tlatzintla",
    "gn:population":120,
    "gn:timezone":"America/Mexico_City",
    "iso:country":"MX",
    "wof:name":"Ejido Tlatzintla",
    "wof:placetype":"locality",
    "wof:population":120
},
  "geometry": {"coordinates":[-98.1251,20.14683],"type":"Point"}
}