{
  "type": "Feature",
  "properties": {
    "gn:admin1_code":"21",
    "gn:admin2_code":"116.0",
    "gn:asciiname":"Santa Cruz Caballito",
    "gn:country_code":"MX",
    "gn:dem":2316,
    "gn:feature_class":"P",
    "gn:feature_code":"PPL",
    "gn:name":"Santa Cruz Caballito",
    "gn:population":324,
    "gn:timezone":"America/Mexico_City",
    "iso:country":"MX",
    "wof:name":"Santa Cruz Caballito",
    "wof:placetype":"locality",
    "wof:population":324
},
  "geometry": {"coordinates":[-97.15667000000001,19.23806],"type":"Point"}
}