{
  "type": "Feature",
  "properties": {
    "gn:admin1_code":"16",
    "gn:admin2_code":"97.0",
    "gn:asciiname":"El Manguito",
    "gn:country_code":"MX",
    "gn:dem":896,
    "gn:feature_class":"P",
    "gn:feature_code":"PPL",
    "gn:name":"El Manguito",
    "gn:population":0,
    "gn:timezone":"America/Mexico_City",
    "iso:country":"MX",
    "name:spa_x_preferred":[
        "El Manguito"
    ],
    "wof:name":"El Manguito",
    "wof:placetype":"locality"
},
  "geometry": {"coordinates":[-101.46387,19.02728],"type":"Point"}
}