{
  "type": "Feature",
  "properties": {
    "gn:admin1_code":"28",
    "gn:admin2_code":"22.0",
    "gn:asciiname":"La Bolsa (Pedro Cantu Garcia)",
    "gn:country_code":"MX",
    "gn:dem":25,
    "gn:feature_class":"P",
    "gn:feature_code":"PPL",
    "gn:name":"La Bolsa (Pedro Cant\u00fa Garc\u00eda)",
    "gn:population":5,
    "gn:timezone":"America/Monterrey",
    "iso:country":"MX",
    "wof:name":"La Bolsa (Pedro Cantu Garcia)",
    "wof:placetype":"locality",
    "wof:population":5
},
  "geometry": {"coordinates":[-97.86944,26.05472],"type":"Point"}
}