{
  "type": "Feature",
  "properties": {
    "gn:admin1_code":"5",
    "gn:admin2_code":"89.0",
    "gn:asciiname":"Viva Mexico",
    "gn:country_code":"MX",
    "gn:dem":88,
    "gn:feature_class":"P",
    "gn:feature_code":"PPL",
    "gn:name":"Viva M\u00e9xico",
    "gn:population":0,
    "gn:timezone":"America/Mexico_City",
    "iso:country":"MX",
    "name:spa_x_preferred":[
        "Viva M\u00e9xico"
    ],
    "wof:name":"Viva Mexico",
    "wof:placetype":"locality"
},
  "geometry": {"coordinates":[-92.32608999999999,14.91008],"type":"Point"}
}