{
  "type": "Feature",
  "properties": {
    "gn:admin1_code":"28",
    "gn:admin2_code":"37.0",
    "gn:asciiname":"Tenacitas",
    "gn:country_code":"MX",
    "gn:dem":25,
    "gn:feature_class":"P",
    "gn:feature_code":"PPL",
    "gn:name":"Tenacitas",
    "gn:population":0,
    "gn:timezone":"America/Monterrey",
    "iso:country":"MX",
    "wof:name":"Tenacitas",
    "wof:placetype":"locality"
},
  "geometry": {"coordinates":[-97.79694000000001,23.58631],"type":"Point"}
}