{
  "type": "Feature",
  "properties": {
    "gn:admin1_code":"11",
    "gn:admin2_code":"26.0",
    "gn:asciiname":"El Nuevo San Antonio (La Loma)",
    "gn:country_code":"MX",
    "gn:dem":1772,
    "gn:feature_class":"P",
    "gn:feature_code":"PPL",
    "gn:name":"El Nuevo San Antonio (La Loma)",
    "gn:population":134,
    "gn:timezone":"America/Mexico_City",
    "iso:country":"MX",
    "wof:name":"El Nuevo San Antonio (La Loma)",
    "wof:placetype":"locality",
    "wof:population":134
},
  "geometry": {"coordinates":[-101.59889,20.81389],"type":"Point"}
}