{
  "type": "Feature",
  "properties": {
    "gn:admin1_code":"24",
    "gn:admin2_code":"54.0",
    "gn:asciiname":"Puerto Encinal",
    "gn:country_code":"MX",
    "gn:dem":947,
    "gn:feature_class":"P",
    "gn:feature_code":"PPL",
    "gn:name":"Puerto Encinal",
    "gn:population":384,
    "gn:timezone":"America/Mexico_City",
    "iso:country":"MX",
    "wof:name":"Puerto Encinal",
    "wof:placetype":"locality",
    "wof:population":384
},
  "geometry": {"coordinates":[-98.98556000000001,21.33583],"type":"Point"}
}