{
  "type": "Feature",
  "properties": {
    "gn:admin1_code":"31",
    "gn:admin2_code":"96.0",
    "gn:asciiname":"Tres Reyes",
    "gn:country_code":"MX",
    "gn:dem":13,
    "gn:feature_class":"P",
    "gn:feature_code":"PPL",
    "gn:name":"Tres Reyes",
    "gn:population":9,
    "gn:timezone":"America/Merida",
    "iso:country":"MX",
    "wof:name":"Tres Reyes",
    "wof:placetype":"locality",
    "wof:population":9
},
  "geometry": {"coordinates":[-87.76333000000002,21.18889],"type":"Point"}
}