{
  "type": "Feature",
  "properties": {
    "gn:admin1_code":"28",
    "gn:admin2_code":"40.0",
    "gn:asciiname":"Leogime",
    "gn:country_code":"MX",
    "gn:dem":21,
    "gn:feature_class":"P",
    "gn:feature_code":"PPL",
    "gn:name":"Leogime",
    "gn:population":6,
    "gn:timezone":"America/Monterrey",
    "iso:country":"MX",
    "wof:name":"Leogime",
    "wof:placetype":"locality",
    "wof:population":6
},
  "geometry": {"coordinates":[-97.88861,25.8225],"type":"Point"}
}