{
  "type": "Feature",
  "properties": {
    "gn:admin1_code":"30",
    "gn:admin2_code":"201",
    "gn:asciiname":"Almolonga",
    "gn:country_code":"MX",
    "gn:dem":124,
    "gn:feature_class":"P",
    "gn:feature_code":"PPL",
    "gn:name":"Almolonga",
    "gn:population":25,
    "gn:timezone":"America/Mexico_City",
    "iso:country":"MX",
    "name:ces_x_preferred":[
        "Almolonga"
    ],
    "name:deu_x_preferred":[
        "Almolonga"
    ],
    "name:fas_x_preferred":[
        "\u0622\u0644\u0645\u0648\u0644\u0648\u0646\u06af\u0627"
    ],
    "name:fra_x_preferred":[
        "Almolonga"
    ],
    "name:lit_x_preferred":[
        "Almolonga"
    ],
    "name:nld_x_preferred":[
        "Almolonga"
    ],
    "name:pol_x_preferred":[
        "Almolonga"
    ],
    "name:por_x_preferred":[
        "Almolonga"
    ],
    "name:rus_x_preferred":[
        "\u0410\u043b\u044c\u043c\u043e\u043b\u043e\u043d\u0433\u0430"
    ],
    "name:slk_x_preferred":[
        "Almolonga"
    ],
    "name:zho_x_preferred":[
        "\u963f\u723e\u83ab\u9686\u52a0\u706b\u5c71"
    ],
    "wof:name":"Almolonga",
    "wof:placetype":"locality",
    "wof:population":25
},
  "geometry": {"coordinates":[-96.84917,18.54722000000001],"type":"Point"}
}