{
  "type": "Feature",
  "properties": {
    "gn:admin1_code":"15",
    "gn:admin2_code":"74.0",
    "gn:asciiname":"Fresno Nichi",
    "gn:country_code":"MX",
    "gn:dem":2901,
    "gn:feature_class":"P",
    "gn:feature_code":"PPL",
    "gn:name":"Fresno Nichi",
    "gn:population":2434,
    "gn:timezone":"America/Mexico_City",
    "iso:country":"MX",
    "wof:name":"Fresno Nichi",
    "wof:placetype":"locality",
    "wof:population":2434
},
  "geometry": {"coordinates":[-99.94889000000001,19.56694],"type":"Point"}
}