{
  "type": "Feature",
  "properties": {
    "gn:admin1_code":"6",
    "gn:admin2_code":"29.0",
    "gn:asciiname":"Mesa de los Marines",
    "gn:country_code":"MX",
    "gn:dem":2261,
    "gn:feature_class":"P",
    "gn:feature_code":"PPL",
    "gn:name":"Mesa de los Marines",
    "gn:population":0,
    "gn:timezone":"America/Chihuahua",
    "iso:country":"MX",
    "name:spa_x_preferred":[
        "Huehueche"
    ],
    "name:spa_x_variant":[
        "Mesa de los Marines"
    ],
    "wof:name":"Mesa de los Marines",
    "wof:placetype":"locality"
},
  "geometry": {"coordinates":[-106.88008000000001,26.14653],"type":"Point"}
}