{
  "type": "Feature",
  "properties": {
    "gn:admin1_code":"10",
    "gn:admin2_code":"34.0",
    "gn:asciiname":"Los Aguajitos",
    "gn:country_code":"MX",
    "gn:dem":587,
    "gn:feature_class":"P",
    "gn:feature_code":"PPL",
    "gn:name":"Los Aguajitos",
    "gn:population":88,
    "gn:timezone":"America/Monterrey",
    "iso:country":"MX",
    "wof:name":"Los Aguajitos",
    "wof:placetype":"locality",
    "wof:population":88
},
  "geometry": {"coordinates":[-106.89926,25.07886],"type":"Point"}
}