{
  "type": "Feature",
  "properties": {
    "gn:admin1_code":"26.0",
    "gn:admin2_code":"52.0",
    "gn:asciiname":"Rancheria de Arriba",
    "gn:country_code":"MX",
    "gn:dem":1059,
    "gn:feature_class":"P",
    "gn:feature_code":"PPL",
    "gn:name":"Rancheria de Arriba",
    "gn:population":0,
    "gn:timezone":"America/Hermosillo",
    "iso:country":"MX",
    "name:spa_x_preferred":[
        "Rancheria de Arriba"
    ],
    "wof:name":"Rancheria de Arriba",
    "wof:placetype":"locality"
},
  "geometry": {"coordinates":[-108.82899999999999,29.088],"type":"Point"}
}