{
  "type": "Feature",
  "properties": {
    "gn:admin1_code":"10",
    "gn:admin2_code":"38.0",
    "gn:asciiname":"San Isidro de Murillos",
    "gn:country_code":"MX",
    "gn:dem":1965,
    "gn:feature_class":"P",
    "gn:feature_code":"PPL",
    "gn:name":"San Isidro de Murillos",
    "gn:population":658,
    "gn:timezone":"America/Monterrey",
    "iso:country":"MX",
    "wof:name":"San Isidro de Murillos",
    "wof:placetype":"locality",
    "wof:population":658
},
  "geometry": {"coordinates":[-104.0461,23.6691],"type":"Point"}
}