{
  "type": "Feature",
  "properties": {
    "gn:admin1_code":"21",
    "gn:admin2_code":"19",
    "gn:asciiname":"San Lorenzo los Jagueeyes",
    "gn:country_code":"MX",
    "gn:dem":1791,
    "gn:feature_class":"P",
    "gn:feature_code":"PPL",
    "gn:name":"San Lorenzo los Jag\u00fceyes",
    "gn:population":36,
    "gn:timezone":"America/Mexico_City",
    "iso:country":"MX",
    "name:und_x_variant":[
        "San Lorenzo los Jag\u00fceyes"
    ],
    "wof:name":"San Lorenzo los Jagueeyes",
    "wof:placetype":"locality",
    "wof:population":36
},
  "geometry": {"coordinates":[-98.47024999999999,18.85321],"type":"Point"}
}