{
  "type": "Feature",
  "properties": {
    "gn:admin1_code":"5.0",
    "gn:asciiname":"Grano de Oro",
    "gn:country_code":"MX",
    "gn:dem":770,
    "gn:feature_class":"P",
    "gn:feature_code":"PPL",
    "gn:name":"Grano de Oro",
    "gn:population":0,
    "gn:timezone":"America/Mexico_City",
    "iso:country":"MX",
    "name:spa_x_preferred":[
        "Grano de Oro"
    ],
    "wof:name":"Grano de Oro",
    "wof:placetype":"locality"
},
  "geometry": {"coordinates":[-93.44034000000001,16.70823],"type":"Point"}
}