{
  "type": "Feature",
  "properties": {
    "gn:admin1_code":"32",
    "gn:admin2_code":"10.0",
    "gn:asciiname":"El Cuatro",
    "gn:country_code":"MX",
    "gn:dem":2078,
    "gn:feature_class":"P",
    "gn:feature_code":"PPL",
    "gn:name":"El Cuatro",
    "gn:population":6,
    "gn:timezone":"America/Mexico_City",
    "iso:country":"MX",
    "wof:name":"El Cuatro",
    "wof:placetype":"locality",
    "wof:population":6
},
  "geometry": {"coordinates":[-103.09222,23.26167],"type":"Point"}
}