{
  "type": "Feature",
  "properties": {
    "gn:admin1_code":"29",
    "gn:admin2_code":"4.0",
    "gn:asciiname":"Fraccion de Guadalupe",
    "gn:country_code":"MX",
    "gn:dem":2747,
    "gn:feature_class":"P",
    "gn:feature_code":"PPL",
    "gn:name":"Fracci\u00f3n de Guadalupe",
    "gn:population":0,
    "gn:timezone":"America/Mexico_City",
    "iso:country":"MX",
    "wof:name":"Fraccion de Guadalupe",
    "wof:placetype":"locality"
},
  "geometry": {"coordinates":[-97.73333,19.43333],"type":"Point"}
}