{
  "type": "Feature",
  "properties": {
    "gn:admin1_code":"7.0",
    "gn:admin2_code":"38.0",
    "gn:asciiname":"La Zacatosa",
    "gn:country_code":"MX",
    "gn:dem":314,
    "gn:feature_class":"P",
    "gn:feature_code":"PPL",
    "gn:name":"La Zacatosa",
    "gn:population":0,
    "gn:timezone":"America/Monterrey",
    "iso:country":"MX",
    "name:spa_x_preferred":[
        "La Zacatosa"
    ],
    "wof:name":"La Zacatosa",
    "wof:placetype":"locality"
},
  "geometry": {"coordinates":[-100.79016,28.53135],"type":"Point"}
}