{
  "type": "Feature",
  "properties": {
    "gn:admin1_code":"9",
    "gn:admin2_code":"12.0",
    "gn:asciiname":"Rancho Chico",
    "gn:country_code":"MX",
    "gn:dem":3304,
    "gn:feature_class":"P",
    "gn:feature_code":"PPL",
    "gn:name":"Rancho Chico",
    "gn:population":7,
    "gn:timezone":"America/Mexico_City",
    "iso:country":"MX",
    "wof:name":"Rancho Chico",
    "wof:placetype":"locality",
    "wof:population":7
},
  "geometry": {"coordinates":[-99.23414,19.19901],"type":"Point"}
}