{
  "type": "Feature",
  "properties": {
    "gn:admin1_code":"3",
    "gn:admin2_code":"1.0",
    "gn:asciiname":"Los Palos Blancos",
    "gn:country_code":"MX",
    "gn:dem":328,
    "gn:feature_class":"P",
    "gn:feature_code":"PPL",
    "gn:name":"Los Palos Blancos",
    "gn:population":0,
    "gn:timezone":"America/Mazatlan",
    "iso:country":"MX",
    "name:spa_x_preferred":[
        "Los Palos Blancos"
    ],
    "wof:name":"Los Palos Blancos",
    "wof:placetype":"locality"
},
  "geometry": {"coordinates":[-111.87602,26.29558],"type":"Point"}
}