{
  "type": "Feature",
  "properties": {
    "gn:admin1_code":"26",
    "gn:admin2_code":"30",
    "gn:asciiname":"El Esfuerzo",
    "gn:country_code":"MX",
    "gn:dem":243,
    "gn:feature_class":"P",
    "gn:feature_code":"PPL",
    "gn:name":"El Esfuerzo",
    "gn:population":17,
    "gn:timezone":"America/Hermosillo",
    "iso:country":"MX",
    "wof:name":"El Esfuerzo",
    "wof:placetype":"locality",
    "wof:population":17
},
  "geometry": {"coordinates":[-110.85639,29.15361],"type":"Point"}
}