{
  "type": "Feature",
  "properties": {
    "gn:admin1_code":"6.0",
    "gn:admin2_code":"11.0",
    "gn:asciiname":"Jesus Maria",
    "gn:country_code":"MX",
    "gn:dem":1380,
    "gn:feature_class":"P",
    "gn:feature_code":"PPL",
    "gn:name":"Jes\u00fas Mar\u00eda",
    "gn:population":0,
    "gn:timezone":"America/Chihuahua",
    "iso:country":"MX",
    "name:spa_x_preferred":[
        "Jes\u00fas Mar\u00eda"
    ],
    "name:und_x_variant":[
        "Rancho Jes\u00fas Maria"
    ],
    "wof:name":"Jesus Maria",
    "wof:placetype":"locality"
},
  "geometry": {"coordinates":[-104.77185,27.54333],"type":"Point"}
}