{
  "type": "Feature",
  "properties": {
    "gn:admin1_code":"5",
    "gn:admin2_code":"20",
    "gn:asciiname":"La Providencia",
    "gn:country_code":"MX",
    "gn:dem":636,
    "gn:feature_class":"P",
    "gn:feature_code":"PPL",
    "gn:name":"La Providencia",
    "gn:population":16,
    "gn:timezone":"America/Mexico_City",
    "iso:country":"MX",
    "wof:name":"La Providencia",
    "wof:placetype":"locality",
    "wof:population":16
},
  "geometry": {"coordinates":[-92.92471999999999,15.97917],"type":"Point"}
}