{
  "type": "Feature",
  "properties": {
    "gn:admin1_code":"25",
    "gn:admin2_code":"11.0",
    "gn:asciiname":"Campo San Marcos",
    "gn:country_code":"MX",
    "gn:dem":15,
    "gn:feature_class":"P",
    "gn:feature_code":"PPL",
    "gn:name":"Campo San Marcos",
    "gn:population":0,
    "gn:timezone":"America/Mazatlan",
    "iso:country":"MX",
    "name:spa_x_preferred":[
        "San Marcos"
    ],
    "name:spa_x_variant":[
        "Campo San Marcos"
    ],
    "wof:name":"Campo San Marcos",
    "wof:placetype":"locality"
},
  "geometry": {"coordinates":[-108.67870000000001,25.667],"type":"Point"}
}