{
  "type": "Feature",
  "properties": {
    "gn:admin1_code":"16",
    "gn:admin2_code":"28.0",
    "gn:asciiname":"La Noria",
    "gn:country_code":"MX",
    "gn:dem":1787,
    "gn:feature_class":"P",
    "gn:feature_code":"PPL",
    "gn:name":"La Noria",
    "gn:population":0,
    "gn:timezone":"America/Mexico_City",
    "iso:country":"MX",
    "wof:name":"La Noria",
    "wof:placetype":"locality"
},
  "geometry": {"coordinates":[-102.09352,20.19198],"type":"Point"}
}