{
  "type": "Feature",
  "properties": {
    "gn:admin1_code":"16",
    "gn:admin2_code":"15.0",
    "gn:asciiname":"La Ecuarera",
    "gn:country_code":"MX",
    "gn:dem":1490,
    "gn:feature_class":"P",
    "gn:feature_code":"PPL",
    "gn:name":"La Ecuarera",
    "gn:population":5,
    "gn:timezone":"America/Mexico_City",
    "iso:country":"MX",
    "wof:name":"La Ecuarera",
    "wof:placetype":"locality",
    "wof:population":5
},
  "geometry": {"coordinates":[-103.09528,18.91306],"type":"Point"}
}