{
  "type": "Feature",
  "properties": {
    "gn:admin1_code":"13",
    "gn:admin2_code":"63.0",
    "gn:asciiname":"El Encino",
    "gn:country_code":"MX",
    "gn:dem":2202,
    "gn:feature_class":"P",
    "gn:feature_code":"PPL",
    "gn:name":"El Encino",
    "gn:population":6,
    "gn:timezone":"America/Mexico_City",
    "iso:country":"MX",
    "wof:name":"El Encino",
    "wof:placetype":"locality",
    "wof:population":6
},
  "geometry": {"coordinates":[-99.32501000000001,19.96527],"type":"Point"}
}