{
  "type": "Feature",
  "properties": {
    "gn:admin1_code":"16",
    "gn:admin2_code":"57",
    "gn:asciiname":"La Estancia Chica (La Estancia de Mamey)",
    "gn:country_code":"MX",
    "gn:dem":1021,
    "gn:feature_class":"P",
    "gn:feature_code":"PPL",
    "gn:name":"La Estancia Chica (La Estancia de Mamey)",
    "gn:population":23,
    "gn:timezone":"America/Mexico_City",
    "iso:country":"MX",
    "wof:name":"La Estancia Chica (La Estancia de Mamey)",
    "wof:placetype":"locality",
    "wof:population":23
},
  "geometry": {"coordinates":[-101.14749999999999,19.1575],"type":"Point"}
}