{
  "type": "Feature",
  "properties": {
    "gn:admin1_code":"12",
    "gn:admin2_code":"20.0",
    "gn:asciiname":"Totohuehuetlan",
    "gn:country_code":"MX",
    "gn:dem":1686,
    "gn:feature_class":"P",
    "gn:feature_code":"PPL",
    "gn:name":"Totohuehuetl\u00e1n",
    "gn:population":357,
    "gn:timezone":"America/Mexico_City",
    "iso:country":"MX",
    "name:und_x_variant":[
        "Totohuehuetl\u00e1n"
    ],
    "wof:name":"Totohuehuetlan",
    "wof:placetype":"locality",
    "wof:population":357
},
  "geometry": {"coordinates":[-98.73193999999999,17.42111],"type":"Point"}
}