{
  "type": "Feature",
  "properties": {
    "gn:admin1_code":"6",
    "gn:admin2_code":"8.0",
    "gn:asciiname":"Miramontes",
    "gn:country_code":"MX",
    "gn:dem":692,
    "gn:feature_class":"P",
    "gn:feature_code":"PPL",
    "gn:name":"Miramontes",
    "gn:population":4,
    "gn:timezone":"America/Chihuahua",
    "iso:country":"MX",
    "name:spa_x_preferred":[
        "Miramontes"
    ],
    "wof:name":"Miramontes",
    "wof:placetype":"locality",
    "wof:population":4
},
  "geometry": {"coordinates":[-107.86257999999999,26.77759],"type":"Point"}
}