{
  "type": "Feature",
  "properties": {
    "gn:admin1_code":"30",
    "gn:admin2_code":"102",
    "gn:asciiname":"La Matamba",
    "gn:country_code":"MX",
    "gn:dem":89,
    "gn:feature_class":"P",
    "gn:feature_code":"PPL",
    "gn:name":"La Matamba",
    "gn:population":11,
    "gn:timezone":"America/Mexico_City",
    "iso:country":"MX",
    "wof:name":"La Matamba",
    "wof:placetype":"locality",
    "wof:population":11
},
  "geometry": {"coordinates":[-97.06833,20.155],"type":"Point"}
}