{
  "type": "Feature",
  "properties": {
    "gn:admin1_code":"17.0",
    "gn:asciiname":"Colonia el Crucero de Atlacholoaya",
    "gn:country_code":"MX",
    "gn:dem":1137,
    "gn:feature_class":"P",
    "gn:feature_code":"PPL",
    "gn:name":"Colonia el Crucero de Atlacholoaya",
    "gn:population":0,
    "gn:timezone":"America/Mexico_City",
    "iso:country":"MX",
    "name:spa_x_preferred":[
        "Colonia el Crucero de Atlacholoaya"
    ],
    "name:spa_x_variant":[
        "Atlacholoaya"
    ],
    "wof:name":"Colonia el Crucero de Atlacholoaya",
    "wof:placetype":"locality"
},
  "geometry": {"coordinates":[-99.21196999999999,18.76567],"type":"Point"}
}