{
  "type": "Feature",
  "properties": {
    "gn:admin1_code":"6",
    "gn:admin2_code":"58",
    "gn:asciiname":"Rancho San Juan Tres Dieciseis",
    "gn:country_code":"MX",
    "gn:dem":1286,
    "gn:feature_class":"P",
    "gn:feature_code":"PPL",
    "gn:name":"Rancho San Juan Tres Diecis\u00e9is",
    "gn:population":11,
    "gn:timezone":"America/Chihuahua",
    "iso:country":"MX",
    "name:und_x_variant":[
        "Rancho San Juan Tres Diecis\u00e9is"
    ],
    "wof:name":"Rancho San Juan Tres Dieciseis",
    "wof:placetype":"locality",
    "wof:population":11
},
  "geometry": {"coordinates":[-105.34305999999999,27.5625],"type":"Point"}
}