{
  "type": "Feature",
  "properties": {
    "gn:admin1_code":"10",
    "gn:admin2_code":"9.0",
    "gn:asciiname":"La Joya de Ayala",
    "gn:country_code":"MX",
    "gn:dem":2760,
    "gn:feature_class":"P",
    "gn:feature_code":"PPL",
    "gn:name":"La Joya de Ayala",
    "gn:population":7,
    "gn:timezone":"America/Monterrey",
    "iso:country":"MX",
    "wof:name":"La Joya de Ayala",
    "wof:placetype":"locality",
    "wof:population":7
},
  "geometry": {"coordinates":[-106.13066000000001,25.84358],"type":"Point"}
}