{
  "type": "Feature",
  "properties": {
    "gn:admin1_code":"20",
    "gn:admin2_code":"57.0",
    "gn:asciiname":"Rancho San Manuel",
    "gn:country_code":"MX",
    "gn:dem":63,
    "gn:feature_class":"P",
    "gn:feature_code":"PPL",
    "gn:name":"Rancho San Manuel",
    "gn:population":7,
    "gn:timezone":"America/Mexico_City",
    "iso:country":"MX",
    "wof:name":"Rancho San Manuel",
    "wof:placetype":"locality",
    "wof:population":7
},
  "geometry": {"coordinates":[-95.02444,17.26694],"type":"Point"}
}