{
  "type": "Feature",
  "properties": {
    "gn:admin1_code":"30",
    "gn:admin2_code":"144",
    "gn:asciiname":"Los Pinos",
    "gn:country_code":"MX",
    "gn:dem":82,
    "gn:feature_class":"P",
    "gn:feature_code":"PPL",
    "gn:name":"Los Pinos",
    "gn:population":25,
    "gn:timezone":"America/Mexico_City",
    "iso:country":"MX",
    "wof:name":"Los Pinos",
    "wof:placetype":"locality",
    "wof:population":25
},
  "geometry": {"coordinates":[-94.96861,17.8725],"type":"Point"}
}