{
  "type": "Feature",
  "properties": {
    "gn:admin1_code":"12.0",
    "gn:admin2_code":"6.0",
    "gn:asciiname":"Caxahuacahuil",
    "gn:country_code":"MX",
    "gn:dem":1136,
    "gn:feature_class":"P",
    "gn:feature_code":"PPL",
    "gn:name":"Caxahuacahuil",
    "gn:population":0,
    "gn:timezone":"America/Mexico_City",
    "iso:country":"MX",
    "name:spa_x_preferred":[
        "Caxahuacahuil"
    ],
    "name:spa_x_variant":[
        "Las Parotas"
    ],
    "wof:name":"Caxahuacahuil",
    "wof:placetype":"locality"
},
  "geometry": {"coordinates":[-100.03328,18.04869],"type":"Point"}
}