{
  "type": "Feature",
  "properties": {
    "gn:admin1_code":"10",
    "gn:admin2_code":"14.0",
    "gn:asciiname":"Piedra Ancha",
    "gn:country_code":"MX",
    "gn:dem":1554,
    "gn:feature_class":"P",
    "gn:feature_code":"PPL",
    "gn:name":"Piedra Ancha",
    "gn:population":0,
    "gn:timezone":"America/Monterrey",
    "iso:country":"MX",
    "name:spa_x_preferred":[
        "Piedra Ancha"
    ],
    "wof:name":"Piedra Ancha",
    "wof:placetype":"locality"
},
  "geometry": {"coordinates":[-104.4757,23.14166],"type":"Point"}
}