{
  "type": "Feature",
  "properties": {
    "gn:admin1_code":"10",
    "gn:admin2_code":"35.0",
    "gn:asciiname":"El Taiste",
    "gn:country_code":"MX",
    "gn:dem":2219,
    "gn:feature_class":"P",
    "gn:feature_code":"PPL",
    "gn:name":"El Taiste",
    "gn:population":0,
    "gn:timezone":"America/Monterrey",
    "iso:country":"MX",
    "name:spa_x_preferred":[
        "El Taiste"
    ],
    "name:und_x_variant":[
        "Taixte",
        "El Ta\u00edste"
    ],
    "wof:name":"El Taiste",
    "wof:placetype":"locality"
},
  "geometry": {"coordinates":[-106.16296,25.63406],"type":"Point"}
}