{
  "type": "Feature",
  "properties": {
    "gn:admin1_code":"19",
    "gn:admin2_code":"20.0",
    "gn:asciiname":"La Coma",
    "gn:country_code":"MX",
    "gn:dem":143,
    "gn:feature_class":"P",
    "gn:feature_code":"PPL",
    "gn:name":"La Coma",
    "gn:population":0,
    "gn:timezone":"America/Monterrey",
    "iso:country":"MX",
    "name:und_x_variant":[
        "Santa Cruz de la Coma",
        "Coma",
        "La Coma"
    ],
    "wof:name":"La Coma",
    "wof:placetype":"locality"
},
  "geometry": {"coordinates":[-98.76134,25.87989],"type":"Point"}
}