{
  "type": "Feature",
  "properties": {
    "gn:admin1_code":"12",
    "gn:admin2_code":"2.0",
    "gn:asciiname":"Zacualpa",
    "gn:country_code":"MX",
    "gn:dem":1477,
    "gn:feature_class":"P",
    "gn:feature_code":"PPL",
    "gn:name":"Zacualpa",
    "gn:population":354,
    "gn:timezone":"America/Mexico_City",
    "iso:country":"MX",
    "name:ceb_x_preferred":[
        "Zacualpa"
    ],
    "name:fra_x_preferred":[
        "Zacualpa"
    ],
    "name:ita_x_preferred":[
        "Zacualpa"
    ],
    "name:lit_x_preferred":[
        "Sakualpa"
    ],
    "name:pol_x_preferred":[
        "Zacualpa"
    ],
    "name:por_x_preferred":[
        "Zacualpa"
    ],
    "name:sco_x_preferred":[
        "Zacualpa"
    ],
    "name:spa_x_preferred":[
        "Zacualpa"
    ],
    "name:swe_x_preferred":[
        "Zacualpa"
    ],
    "name:urd_x_preferred":[
        "\u0632\u06a9\u0627\u0644\u067e\u0627"
    ],
    "name:zho_x_preferred":[
        "\u85a9\u5eab\u963f\u723e\u5e15"
    ],
    "wof:name":"Zacualpa",
    "wof:placetype":"locality",
    "wof:population":354
},
  "geometry": {"coordinates":[-98.81753999999999,17.69272999999999],"type":"Point"}
}