{
  "type": "Feature",
  "properties": {
    "gn:admin1_code":"28.0",
    "gn:admin2_code":"12.0",
    "gn:asciiname":"Los Jarales",
    "gn:country_code":"MX",
    "gn:dem":74,
    "gn:feature_class":"P",
    "gn:feature_code":"PPL",
    "gn:name":"Los Jarales",
    "gn:population":7,
    "gn:timezone":"America/Monterrey",
    "iso:country":"MX",
    "name:spa_x_preferred":[
        "Los Jarales"
    ],
    "wof:name":"Los Jarales",
    "wof:placetype":"locality",
    "wof:population":7
},
  "geometry": {"coordinates":[-98.37333,22.57028],"type":"Point"}
}