{
  "type": "Feature",
  "properties": {
    "gn:admin1_code":"25.0",
    "gn:admin2_code":"7.0",
    "gn:asciiname":"Texcalama",
    "gn:country_code":"MX",
    "gn:dem":673,
    "gn:feature_class":"P",
    "gn:feature_code":"PPL",
    "gn:name":"Texcalama",
    "gn:population":0,
    "gn:timezone":"America/Mazatlan",
    "iso:country":"MX",
    "name:spa_x_preferred":[
        "Texcalama"
    ],
    "wof:name":"Texcalama",
    "wof:placetype":"locality"
},
  "geometry": {"coordinates":[-108.10111000000001,26.72185],"type":"Point"}
}