{
  "type": "Feature",
  "properties": {
    "gn:admin1_code":"15.0",
    "gn:asciiname":"El Tezontlal",
    "gn:country_code":"MX",
    "gn:dem":2527,
    "gn:feature_class":"P",
    "gn:feature_code":"PPL",
    "gn:name":"El Tezontlal",
    "gn:population":0,
    "gn:timezone":"America/Mexico_City",
    "iso:country":"MX",
    "name:spa_x_preferred":[
        "El Tezontlal"
    ],
    "wof:name":"El Tezontlal",
    "wof:placetype":"locality"
},
  "geometry": {"coordinates":[-98.85642,19.08585],"type":"Point"}
}