{
  "type": "Feature",
  "properties": {
    "gn:admin1_code":"16.0",
    "gn:admin2_code":"95.0",
    "gn:asciiname":"Los Antigueis",
    "gn:country_code":"MX",
    "gn:dem":993,
    "gn:feature_class":"P",
    "gn:feature_code":"PPL",
    "gn:name":"Los Antig\u00fcis",
    "gn:population":0,
    "gn:timezone":"America/Mexico_City",
    "iso:country":"MX",
    "name:spa_x_preferred":[
        "Los Antig\u00fcis"
    ],
    "wof:name":"Los Antigueis",
    "wof:placetype":"locality"
},
  "geometry": {"coordinates":[-102.69946,19.55821],"type":"Point"}
}