{
  "type": "Feature",
  "properties": {
    "gn:gn_country":"MX",
    "gn:gn_fcode":"PPL",
    "gn:gn_pop":0,
    "iso:country":"MX",
    "name:cat_x_preferred":[
        "Corrales"
    ],
    "name:ceb_x_preferred":[
        "Corrales"
    ],
    "name:deu_x_preferred":[
        "Corrales"
    ],
    "name:eus_x_preferred":[
        "Corrales"
    ],
    "name:fra_x_preferred":[
        "Corrales"
    ],
    "name:ita_x_preferred":[
        "Corrales"
    ],
    "name:nld_x_preferred":[
        "Corrales"
    ],
    "name:pol_x_preferred":[
        "Corrales"
    ],
    "name:por_x_preferred":[
        "Corrales"
    ],
    "name:rus_x_preferred":[
        "\u041a\u043e\u0440\u0440\u0430\u043b\u0435\u0441"
    ],
    "name:spa_x_preferred":[
        "Los Corrales"
    ],
    "name:spa_x_variant":[
        "Corrales"
    ],
    "name:swe_x_preferred":[
        "Corrales"
    ],
    "name:vie_x_preferred":[
        "Corrales"
    ],
    "name:war_x_preferred":[
        "Corrales"
    ],
    "qs_pg:aaroncc":"MX",
    "qs_pg:gn_country":"MX",
    "qs_pg:gn_fcode":"PPL",
    "qs_pg:gn_pop":0,
    "qs_pg:name":"Corrales",
    "qs_pg:name_adm0":"M\u00e9xico",
    "qs_pg:name_adm1":"Distrito Federal",
    "qs_pg:photos":26,
    "qs_pg:photos_1k":5,
    "qs_pg:photos_9k":1,
    "qs_pg:photos_9r":2,
    "qs_pg:photos_all":26,
    "qs_pg:photos_sr":2,
    "qs_pg:pop_sr":0,
    "qs_pg:qs_pg_placetype":"neighbourhood",
    "qs_pg:qs_pg_placetype_gp":"Suburb",
    "qs_pg:woe_adm0":23424900,
    "woe:adm0_id":23424900,
    "woe:name_adm0":"M\u00e9xico",
    "woe:name_adm1":"Distrito Federal",
    "woe:placetype":"Suburb",
    "wof:name":"Corrales",
    "wof:placetype":"neighbourhood"
},
  "geometry": {"coordinates":[-99.49088,20.03573],"type":"Point"}
}