{
  "type": "Feature",
  "properties": {
    "gn:admin1_code":"6",
    "gn:admin2_code":"7.0",
    "gn:asciiname":"Rancheria Riito",
    "gn:country_code":"MX",
    "gn:dem":2518,
    "gn:feature_class":"P",
    "gn:feature_code":"PPL",
    "gn:name":"Rancher\u00eda Ri\u00edto",
    "gn:population":0,
    "gn:timezone":"America/Chihuahua",
    "iso:country":"MX",
    "name:spa_x_preferred":[
        "Rancher\u00eda Ri\u00edto"
    ],
    "wof:name":"Rancheria Riito",
    "wof:placetype":"locality"
},
  "geometry": {"coordinates":[-106.48639,26.54063],"type":"Point"}
}