{
  "type": "Feature",
  "properties": {
    "gn:admin1_code":"22",
    "gn:admin2_code":"2",
    "gn:asciiname":"El Limon de la Cruz",
    "gn:country_code":"MX",
    "gn:dem":1401,
    "gn:feature_class":"P",
    "gn:feature_code":"PPL",
    "gn:name":"El Lim\u00f3n de la Cruz",
    "gn:population":37,
    "gn:timezone":"America/Mexico_City",
    "iso:country":"MX",
    "name:und_x_variant":[
        "El Lim\u00f3n de la Cruz"
    ],
    "wof:name":"El Limon de la Cruz",
    "wof:placetype":"locality",
    "wof:population":37
},
  "geometry": {"coordinates":[-99.4575,21.09639],"type":"Point"}
}