{
  "type": "Feature",
  "properties": {
    "gn:admin1_code":"12",
    "gn:admin2_code":"23.0",
    "gn:asciiname":"Rancho los Limones",
    "gn:country_code":"MX",
    "gn:dem":46,
    "gn:feature_class":"P",
    "gn:feature_code":"PPL",
    "gn:name":"Rancho los Limones",
    "gn:population":8,
    "gn:timezone":"America/Mexico_City",
    "iso:country":"MX",
    "wof:name":"Rancho los Limones",
    "wof:placetype":"locality",
    "wof:population":8
},
  "geometry": {"coordinates":[-98.41134,16.43366],"type":"Point"}
}