{
  "type": "Feature",
  "properties": {
    "gn:admin1_code":"5",
    "gn:admin2_code":"65.0",
    "gn:asciiname":"Emilio Rabasa",
    "gn:country_code":"MX",
    "gn:dem":40,
    "gn:feature_class":"P",
    "gn:feature_code":"PPL",
    "gn:name":"Emilio Rabasa",
    "gn:population":908,
    "gn:timezone":"America/Mexico_City",
    "iso:country":"MX",
    "name:ces_x_preferred":[
        "Emilio Rabasa"
    ],
    "name:nld_x_preferred":[
        "Emilio Rabasa"
    ],
    "name:rus_x_preferred":[
        "\u0420\u0430\u0431\u0430\u0441\u0430"
    ],
    "name:spa_x_preferred":[
        "Emilio Rabasa"
    ],
    "wof:name":"Emilio Rabasa",
    "wof:placetype":"locality",
    "wof:population":908
},
  "geometry": {"coordinates":[-92.16889,17.69693999999999],"type":"Point"}
}