{
  "type": "Feature",
  "properties": {
    "gn:admin1_code":"31",
    "gn:admin2_code":"2.0",
    "gn:asciiname":"La Guayin",
    "gn:country_code":"MX",
    "gn:dem":12,
    "gn:feature_class":"P",
    "gn:feature_code":"PPL",
    "gn:name":"La Guay\u00edn",
    "gn:population":0,
    "gn:timezone":"America/Merida",
    "iso:country":"MX",
    "name:spa_x_preferred":[
        "La Guay\u00edn"
    ],
    "wof:name":"La Guayin",
    "wof:placetype":"locality"
},
  "geometry": {"coordinates":[-89.44483000000002,20.82437],"type":"Point"}
}