{
  "type": "Feature",
  "properties": {
    "gn:admin1_code":"5",
    "gn:admin2_code":"20.0",
    "gn:asciiname":"El Embarcadero",
    "gn:country_code":"MX",
    "gn:dem":589,
    "gn:feature_class":"P",
    "gn:feature_code":"PPL",
    "gn:name":"El Embarcadero",
    "gn:population":6,
    "gn:timezone":"America/Mexico_City",
    "iso:country":"MX",
    "wof:name":"El Embarcadero",
    "wof:placetype":"locality",
    "wof:population":6
},
  "geometry": {"coordinates":[-92.58472,16.11528],"type":"Point"}
}