{
  "type": "Feature",
  "properties": {
    "gn:admin1_code":"19",
    "gn:admin2_code":"17.0",
    "gn:asciiname":"Tanquecillos",
    "gn:country_code":"MX",
    "gn:dem":2484,
    "gn:feature_class":"P",
    "gn:feature_code":"PPL",
    "gn:name":"Tanquecillos",
    "gn:population":0,
    "gn:timezone":"America/Monterrey",
    "iso:country":"MX",
    "name:spa_x_preferred":[
        "Tanquecillos"
    ],
    "wof:name":"Tanquecillos",
    "wof:placetype":"locality"
},
  "geometry": {"coordinates":[-100.39906999999999,25.05215],"type":"Point"}
}