{
  "type": "Feature",
  "properties": {
    "gn:admin1_code":"20",
    "gn:admin2_code":"406.0",
    "gn:asciiname":"San Julio",
    "gn:country_code":"MX",
    "gn:dem":340,
    "gn:feature_class":"P",
    "gn:feature_code":"PPL",
    "gn:name":"San Julio",
    "gn:population":150,
    "gn:timezone":"America/Mexico_City",
    "iso:country":"MX",
    "wof:name":"San Julio",
    "wof:placetype":"locality",
    "wof:population":150
},
  "geometry": {"coordinates":[-96.72694,18.30917],"type":"Point"}
}