{
  "type": "Feature",
  "properties": {
    "gn:admin1_code":"24",
    "gn:admin2_code":"7.0",
    "gn:asciiname":"La Pinta",
    "gn:country_code":"MX",
    "gn:dem":1760,
    "gn:feature_class":"P",
    "gn:feature_code":"PPL",
    "gn:name":"La Pinta",
    "gn:population":59,
    "gn:timezone":"America/Mexico_City",
    "iso:country":"MX",
    "name:spa_x_preferred":[
        "La Pinta"
    ],
    "wof:name":"La Pinta",
    "wof:placetype":"locality",
    "wof:population":59
},
  "geometry": {"coordinates":[-100.61685,23.90886],"type":"Point"}
}