{
  "type": "Feature",
  "properties": {
    "gn:admin1_code":"30.0",
    "gn:admin2_code":"58.0",
    "gn:asciiname":"Chilico",
    "gn:country_code":"MX",
    "gn:dem":481,
    "gn:feature_class":"P",
    "gn:feature_code":"PPL",
    "gn:name":"Chilico",
    "gn:population":0,
    "gn:timezone":"America/Mexico_City",
    "iso:country":"MX",
    "name:spa_x_preferred":[
        "Chilico"
    ],
    "wof:name":"Chilico",
    "wof:placetype":"locality"
},
  "geometry": {"coordinates":[-98.18763,20.95965],"type":"Point"}
}