{
  "type": "Feature",
  "properties": {
    "gn:admin1_code":"24",
    "gn:admin2_code":"33.0",
    "gn:asciiname":"El Convento",
    "gn:country_code":"MX",
    "gn:dem":1948,
    "gn:feature_class":"P",
    "gn:feature_code":"PPL",
    "gn:name":"El Convento",
    "gn:population":0,
    "gn:timezone":"America/Mexico_City",
    "iso:country":"MX",
    "wof:name":"El Convento",
    "wof:placetype":"locality"
},
  "geometry": {"coordinates":[-101.93886999999999,23.34384],"type":"Point"}
}