{
  "type": "Feature",
  "properties": {
    "gn:admin1_code":"4",
    "gn:admin2_code":"11.0",
    "gn:asciiname":"Dos Amigos",
    "gn:country_code":"MX",
    "gn:dem":34,
    "gn:feature_class":"P",
    "gn:feature_code":"PPL",
    "gn:name":"Dos Amigos",
    "gn:population":0,
    "gn:timezone":"America/Merida",
    "iso:country":"MX",
    "name:spa_x_preferred":[
        "Dos Amigos"
    ],
    "wof:name":"Dos Amigos",
    "wof:placetype":"locality"
},
  "geometry": {"coordinates":[-91.19978,18.07825],"type":"Point"}
}