{
  "type": "Feature",
  "properties": {
    "gn:admin1_code":"28",
    "gn:admin2_code":"22.0",
    "gn:asciiname":"El Chaparral",
    "gn:country_code":"MX",
    "gn:dem":13,
    "gn:feature_class":"P",
    "gn:feature_code":"PPL",
    "gn:name":"El Chaparral",
    "gn:population":5,
    "gn:timezone":"America/Matamoros",
    "iso:country":"MX",
    "name:spa_x_preferred":[
        "El Chaparral"
    ],
    "wof:name":"El Chaparral",
    "wof:placetype":"locality",
    "wof:population":5
},
  "geometry": {"coordinates":[-97.64945,25.76861],"type":"Point"}
}