{
  "type": "Feature",
  "properties": {
    "gn:admin1_code":"19",
    "gn:admin2_code":"26.0",
    "gn:asciiname":"Los Banitos",
    "gn:country_code":"MX",
    "gn:dem":426,
    "gn:feature_class":"P",
    "gn:feature_code":"PPL",
    "gn:name":"Los Ba\u00f1itos",
    "gn:population":0,
    "gn:timezone":"America/Monterrey",
    "iso:country":"MX",
    "wof:name":"Los Banitos",
    "wof:placetype":"locality"
},
  "geometry": {"coordinates":[-100.15248,25.65744],"type":"Point"}
}