{
  "type": "Feature",
  "properties": {
    "gn:admin1_code":"13",
    "gn:admin2_code":"84.0",
    "gn:asciiname":"Jagueey Colorado",
    "gn:country_code":"MX",
    "gn:dem":2015,
    "gn:feature_class":"P",
    "gn:feature_code":"PPL",
    "gn:name":"Jag\u00fcey Colorado",
    "gn:population":0,
    "gn:timezone":"America/Mexico_City",
    "iso:country":"MX",
    "name:spa_x_preferred":[
        "Jaguey Colorado"
    ],
    "name:spa_x_variant":[
        "Jag\u00fcey Colorado"
    ],
    "wof:name":"Jagueey Colorado",
    "wof:placetype":"locality"
},
  "geometry": {"coordinates":[-99.27710999999999,20.88166],"type":"Point"}
}