{
  "type": "Feature",
  "properties": {
    "gn:admin1_code":"20",
    "gn:admin2_code":"439.0",
    "gn:asciiname":"Frutilla",
    "gn:country_code":"MX",
    "gn:dem":58,
    "gn:feature_class":"P",
    "gn:feature_code":"PPL",
    "gn:name":"Frutilla",
    "gn:population":127,
    "gn:timezone":"America/Mexico_City",
    "iso:country":"MX",
    "wof:name":"Frutilla",
    "wof:placetype":"locality",
    "wof:population":127
},
  "geometry": {"coordinates":[-96.56,15.77417],"type":"Point"}
}