{
  "type": "Feature",
  "properties": {
    "gn:admin1_code":"20",
    "gn:admin2_code":"2.0",
    "gn:asciiname":"La Isleta",
    "gn:country_code":"MX",
    "gn:dem":117,
    "gn:feature_class":"P",
    "gn:feature_code":"PPL",
    "gn:name":"La Isleta",
    "gn:population":0,
    "gn:timezone":"America/Mexico_City",
    "iso:country":"MX",
    "name:spa_x_preferred":[
        "La Isleta"
    ],
    "wof:name":"La Isleta",
    "wof:placetype":"locality"
},
  "geometry": {"coordinates":[-96.47563,18.57292],"type":"Point"}
}