{
  "type": "Feature",
  "properties": {
    "gn:admin1_code":"14",
    "gn:admin2_code":"29",
    "gn:asciiname":"El Chacon",
    "gn:country_code":"MX",
    "gn:dem":1907,
    "gn:feature_class":"P",
    "gn:feature_code":"PPL",
    "gn:name":"El Chac\u00f3n",
    "gn:population":49,
    "gn:timezone":"America/Mexico_City",
    "iso:country":"MX",
    "name:und_x_variant":[
        "El Chac\u00f3n"
    ],
    "wof:name":"El Chacon",
    "wof:placetype":"locality",
    "wof:population":49
},
  "geometry": {"coordinates":[-103.11722,21.01472],"type":"Point"}
}