{
  "type": "Feature",
  "properties": {
    "gn:admin1_code":"30",
    "gn:admin2_code":"61.0",
    "gn:asciiname":"El Triunfo (Nuevo Presidio)",
    "gn:country_code":"MX",
    "gn:dem":140,
    "gn:feature_class":"P",
    "gn:feature_code":"PPL",
    "gn:name":"El Triunfo (Nuevo Presidio)",
    "gn:population":97,
    "gn:timezone":"America/Mexico_City",
    "iso:country":"MX",
    "wof:name":"El Triunfo (Nuevo Presidio)",
    "wof:placetype":"locality",
    "wof:population":97
},
  "geometry": {"coordinates":[-93.81417,17.34444],"type":"Point"}
}