{
  "type": "Feature",
  "properties": {
    "gn:admin1_code":"3",
    "gn:admin2_code":"8",
    "gn:asciiname":"El Cajon de los Reyes",
    "gn:country_code":"MX",
    "gn:dem":149,
    "gn:feature_class":"P",
    "gn:feature_code":"PPL",
    "gn:name":"El Caj\u00f3n de los Reyes",
    "gn:population":32,
    "gn:timezone":"America/Mazatlan",
    "iso:country":"MX",
    "name:und_x_variant":[
        "El Caj\u00f3n de los Reyes"
    ],
    "wof:name":"El Cajon de los Reyes",
    "wof:placetype":"locality",
    "wof:population":32
},
  "geometry": {"coordinates":[-109.70766999999999,23.32826],"type":"Point"}
}