{
  "type": "Feature",
  "properties": {
    "gn:admin1_code":"11",
    "gn:admin2_code":"7.0",
    "gn:asciiname":"Puerta del Monte (Elguera)",
    "gn:country_code":"MX",
    "gn:dem":1752,
    "gn:feature_class":"P",
    "gn:feature_code":"PPL",
    "gn:name":"Puerta del Monte (Elguera)",
    "gn:population":959,
    "gn:timezone":"America/Mexico_City",
    "iso:country":"MX",
    "wof:name":"Puerta del Monte (Elguera)",
    "wof:placetype":"locality",
    "wof:population":959
},
  "geometry": {"coordinates":[-100.88583,20.56222],"type":"Point"}
}