{
  "type": "Feature",
  "properties": {
    "gn:admin1_code":"11",
    "gn:admin2_code":"24.0",
    "gn:asciiname":"Prisco",
    "gn:country_code":"MX",
    "gn:dem":1705,
    "gn:feature_class":"P",
    "gn:feature_code":"PPL",
    "gn:name":"Prisco",
    "gn:population":0,
    "gn:timezone":"America/Mexico_City",
    "iso:country":"MX",
    "wof:name":"Prisco",
    "wof:placetype":"locality"
},
  "geometry": {"coordinates":[-101.38333,20.51667],"type":"Point"}
}