{
  "type": "Feature",
  "properties": {
    "gn:admin1_code":"20",
    "gn:admin2_code":"494.0",
    "gn:asciiname":"Loma Corazon",
    "gn:country_code":"MX",
    "gn:dem":2684,
    "gn:feature_class":"P",
    "gn:feature_code":"PPL",
    "gn:name":"Loma Coraz\u00f3n",
    "gn:population":144,
    "gn:timezone":"America/Mexico_City",
    "iso:country":"MX",
    "name:und_x_variant":[
        "Loma Coraz\u00f3n"
    ],
    "wof:name":"Loma Corazon",
    "wof:placetype":"locality",
    "wof:population":144
},
  "geometry": {"coordinates":[-96.96693999999999,17.04194],"type":"Point"}
}