{
  "type": "Feature",
  "properties": {
    "gn:admin1_code":"30",
    "gn:admin2_code":"58.0",
    "gn:asciiname":"Alaxtitla Morenotlan",
    "gn:country_code":"MX",
    "gn:dem":127,
    "gn:feature_class":"P",
    "gn:feature_code":"PPL",
    "gn:name":"Alaxtitla Morenotl\u00e1n",
    "gn:population":285,
    "gn:timezone":"America/Mexico_City",
    "iso:country":"MX",
    "name:spa_x_preferred":[
        "Alaxtitla Morenotl\u00e1n"
    ],
    "wof:name":"Alaxtitla Morenotlan",
    "wof:placetype":"locality",
    "wof:population":285
},
  "geometry": {"coordinates":[-98.13167,21.00417],"type":"Point"}
}