{
  "type": "Feature",
  "properties": {
    "gn:admin1_code":"5",
    "gn:admin2_code":"4",
    "gn:asciiname":"Gabino Barrera (Nuevo Centro)",
    "gn:country_code":"MX",
    "gn:dem":1184,
    "gn:feature_class":"P",
    "gn:feature_code":"PPL",
    "gn:name":"Gabino Barrera (Nuevo Centro)",
    "gn:population":49,
    "gn:timezone":"America/Mexico_City",
    "iso:country":"MX",
    "wof:name":"Gabino Barrera (Nuevo Centro)",
    "wof:placetype":"locality",
    "wof:population":49
},
  "geometry": {"coordinates":[-92.01145,16.69149],"type":"Point"}
}