{
  "type": "Feature",
  "properties": {
    "gn:admin1_code":"12",
    "gn:admin2_code":"76.0",
    "gn:asciiname":"Llano de la Parota",
    "gn:country_code":"MX",
    "gn:dem":1305,
    "gn:feature_class":"P",
    "gn:feature_code":"PPL",
    "gn:name":"Llano de la Parota",
    "gn:population":158,
    "gn:timezone":"America/Mexico_City",
    "iso:country":"MX",
    "wof:name":"Llano de la Parota",
    "wof:placetype":"locality",
    "wof:population":158
},
  "geometry": {"coordinates":[-98.98472,17.13806],"type":"Point"}
}