{
  "type": "Feature",
  "properties": {
    "gn:admin1_code":"11.0",
    "gn:admin2_code":"3.0",
    "gn:asciiname":"Rancho Nuevo Tlaxcalilla",
    "gn:country_code":"MX",
    "gn:dem":1855,
    "gn:feature_class":"P",
    "gn:feature_code":"PPL",
    "gn:name":"Rancho Nuevo Tlaxcalilla",
    "gn:population":32,
    "gn:timezone":"America/Mexico_City",
    "iso:country":"MX",
    "wof:name":"Rancho Nuevo Tlaxcalilla",
    "wof:placetype":"locality",
    "wof:population":32
},
  "geometry": {"coordinates":[-100.83917,20.88111],"type":"Point"}
}