{
  "type": "Feature",
  "properties": {
    "gn:admin1_code":"13",
    "gn:admin2_code":"48.0",
    "gn:asciiname":"El Bordo (Barrio del Bordo)",
    "gn:country_code":"MX",
    "gn:dem":2722,
    "gn:feature_class":"P",
    "gn:feature_code":"PPL",
    "gn:name":"El Bordo (Barrio del Bordo)",
    "gn:population":276,
    "gn:timezone":"America/Mexico_City",
    "iso:country":"MX",
    "wof:name":"El Bordo (Barrio del Bordo)",
    "wof:placetype":"locality",
    "wof:population":276
},
  "geometry": {"coordinates":[-98.73944,20.15139],"type":"Point"}
}