{
  "type": "Feature",
  "properties": {
    "gn:admin1_code":"12",
    "gn:admin2_code":"24",
    "gn:asciiname":"Azochitlan",
    "gn:country_code":"MX",
    "gn:dem":1370,
    "gn:feature_class":"P",
    "gn:feature_code":"PPL",
    "gn:name":"Azoch\u00edtlan",
    "gn:population":10,
    "gn:timezone":"America/Mexico_City",
    "iso:country":"MX",
    "name:und_x_variant":[
        "Azoch\u00edtlan"
    ],
    "wof:name":"Azochitlan",
    "wof:placetype":"locality",
    "wof:population":10
},
  "geometry": {"coordinates":[-98.64746,17.75217],"type":"Point"}
}