{
  "type": "Feature",
  "properties": {
    "gn:admin1_code":"24",
    "gn:admin2_code":"3.0",
    "gn:asciiname":"Barrio San Jose",
    "gn:country_code":"MX",
    "gn:dem":563,
    "gn:feature_class":"P",
    "gn:feature_code":"PPL",
    "gn:name":"Barrio San Jos\u00e9",
    "gn:population":134,
    "gn:timezone":"America/Mexico_City",
    "iso:country":"MX",
    "name:und_x_variant":[
        "Barrio San Jos\u00e9"
    ],
    "wof:name":"Barrio San Jose",
    "wof:placetype":"locality",
    "wof:population":134
},
  "geometry": {"coordinates":[-99.05361000000001,21.55111],"type":"Point"}
}